Compiled from "GetTraceSummariesRequest.scala"
public final class zio.aws.xray.model.GetTraceSummariesRequest implements scala.Product,java.io.Serializable {
  private final java.time.Instant startTime;

  private final java.time.Instant endTime;

  private final zio.prelude.data.Optional timeRangeType;

  private final zio.prelude.data.Optional sampling;

  private final zio.prelude.data.Optional samplingStrategy;

  private final zio.prelude.data.Optional filterExpression;

  private final zio.prelude.data.Optional nextToken;

  public static final long OFFSET$_m_0;

  public static zio.aws.xray.model.GetTraceSummariesRequest apply(java.time.Instant, java.time.Instant, zio.prelude.data.Optional<zio.aws.xray.model.TimeRangeType>, zio.prelude.data.Optional<java.lang.Object>, zio.prelude.data.Optional<zio.aws.xray.model.SamplingStrategy>, zio.prelude.data.Optional<java.lang.String>, zio.prelude.data.Optional<java.lang.String>);
    Code:
       0: getstatic     #56                 // Field zio/aws/xray/model/GetTraceSummariesRequest$.MODULE$:Lzio/aws/xray/model/GetTraceSummariesRequest$;
       3: aload_0
       4: aload_1
       5: aload_2
       6: aload_3
       7: aload         4
       9: aload         5
      11: aload         6
      13: invokevirtual #58                 // Method zio/aws/xray/model/GetTraceSummariesRequest$.apply:(Ljava/time/Instant;Ljava/time/Instant;Lzio/prelude/data/Optional;Lzio/prelude/data/Optional;Lzio/prelude/data/Optional;Lzio/prelude/data/Optional;Lzio/prelude/data/Optional;)Lzio/aws/xray/model/GetTraceSummariesRequest;
      16: areturn

  public static zio.aws.xray.model.GetTraceSummariesRequest fromProduct(scala.Product);
    Code:
       0: getstatic     #56                 // Field zio/aws/xray/model/GetTraceSummariesRequest$.MODULE$:Lzio/aws/xray/model/GetTraceSummariesRequest$;
       3: aload_0
       4: invokevirtual #62                 // Method zio/aws/xray/model/GetTraceSummariesRequest$.fromProduct:(Lscala/Product;)Lzio/aws/xray/model/GetTraceSummariesRequest;
       7: areturn

  public static zio.aws.xray.model.GetTraceSummariesRequest unapply(zio.aws.xray.model.GetTraceSummariesRequest);
    Code:
       0: getstatic     #56                 // Field zio/aws/xray/model/GetTraceSummariesRequest$.MODULE$:Lzio/aws/xray/model/GetTraceSummariesRequest$;
       3: aload_0
       4: invokevirtual #66                 // Method zio/aws/xray/model/GetTraceSummariesRequest$.unapply:(Lzio/aws/xray/model/GetTraceSummariesRequest;)Lzio/aws/xray/model/GetTraceSummariesRequest;
       7: areturn

  public static zio.aws.xray.model.GetTraceSummariesRequest$ReadOnly wrap(software.amazon.awssdk.services.xray.model.GetTraceSummariesRequest);
    Code:
       0: getstatic     #56                 // Field zio/aws/xray/model/GetTraceSummariesRequest$.MODULE$:Lzio/aws/xray/model/GetTraceSummariesRequest$;
       3: aload_0
       4: invokevirtual #70                 // Method zio/aws/xray/model/GetTraceSummariesRequest$.wrap:(Lsoftware/amazon/awssdk/services/xray/model/GetTraceSummariesRequest;)Lzio/aws/xray/model/GetTraceSummariesRequest$ReadOnly;
       7: areturn

  public static zio.prelude.data.Optional<zio.aws.xray.model.TimeRangeType> $lessinit$greater$default$3();
    Code:
       0: getstatic     #56                 // Field zio/aws/xray/model/GetTraceSummariesRequest$.MODULE$:Lzio/aws/xray/model/GetTraceSummariesRequest$;
       3: invokevirtual #75                 // Method zio/aws/xray/model/GetTraceSummariesRequest$.$lessinit$greater$default$3:()Lzio/prelude/data/Optional;
       6: areturn

  public static zio.prelude.data.Optional<java.lang.Object> $lessinit$greater$default$4();
    Code:
       0: getstatic     #56                 // Field zio/aws/xray/model/GetTraceSummariesRequest$.MODULE$:Lzio/aws/xray/model/GetTraceSummariesRequest$;
       3: invokevirtual #79                 // Method zio/aws/xray/model/GetTraceSummariesRequest$.$lessinit$greater$default$4:()Lzio/prelude/data/Optional;
       6: areturn

  public static zio.prelude.data.Optional<zio.aws.xray.model.SamplingStrategy> $lessinit$greater$default$5();
    Code:
       0: getstatic     #56                 // Field zio/aws/xray/model/GetTraceSummariesRequest$.MODULE$:Lzio/aws/xray/model/GetTraceSummariesRequest$;
       3: invokevirtual #83                 // Method zio/aws/xray/model/GetTraceSummariesRequest$.$lessinit$greater$default$5:()Lzio/prelude/data/Optional;
       6: areturn

  public static zio.prelude.data.Optional<java.lang.String> $lessinit$greater$default$6();
    Code:
       0: getstatic     #56                 // Field zio/aws/xray/model/GetTraceSummariesRequest$.MODULE$:Lzio/aws/xray/model/GetTraceSummariesRequest$;
       3: invokevirtual #87                 // Method zio/aws/xray/model/GetTraceSummariesRequest$.$lessinit$greater$default$6:()Lzio/prelude/data/Optional;
       6: areturn

  public static zio.prelude.data.Optional<java.lang.String> $lessinit$greater$default$7();
    Code:
       0: getstatic     #56                 // Field zio/aws/xray/model/GetTraceSummariesRequest$.MODULE$:Lzio/aws/xray/model/GetTraceSummariesRequest$;
       3: invokevirtual #90                 // Method zio/aws/xray/model/GetTraceSummariesRequest$.$lessinit$greater$default$7:()Lzio/prelude/data/Optional;
       6: areturn

  public zio.aws.xray.model.GetTraceSummariesRequest(java.time.Instant, java.time.Instant, zio.prelude.data.Optional<zio.aws.xray.model.TimeRangeType>, zio.prelude.data.Optional<java.lang.Object>, zio.prelude.data.Optional<zio.aws.xray.model.SamplingStrategy>, zio.prelude.data.Optional<java.lang.String>, zio.prelude.data.Optional<java.lang.String>);
    Code:
       0: aload_0
       1: aload_1
       2: putfield      #95                 // Field startTime:Ljava/time/Instant;
       5: aload_0
       6: aload_2
       7: putfield      #97                 // Field endTime:Ljava/time/Instant;
      10: aload_0
      11: aload_3
      12: putfield      #99                 // Field timeRangeType:Lzio/prelude/data/Optional;
      15: aload_0
      16: aload         4
      18: putfield      #101                // Field sampling:Lzio/prelude/data/Optional;
      21: aload_0
      22: aload         5
      24: putfield      #103                // Field samplingStrategy:Lzio/prelude/data/Optional;
      27: aload_0
      28: aload         6
      30: putfield      #105                // Field filterExpression:Lzio/prelude/data/Optional;
      33: aload_0
      34: aload         7
      36: putfield      #107                // Field nextToken:Lzio/prelude/data/Optional;
      39: aload_0
      40: invokespecial #110                // Method java/lang/Object."<init>":()V
      43: return

  private static {};
    Code:
       0: getstatic     #118                // Field scala/runtime/LazyVals$.MODULE$:Lscala/runtime/LazyVals$;
       3: ldc           #52                 // class zio/aws/xray/model/GetTraceSummariesRequest$
       5: ldc           #120                // String 0bitmap$1
       7: invokevirtual #126                // Method java/lang/Class.getDeclaredField:(Ljava/lang/String;)Ljava/lang/reflect/Field;
      10: invokevirtual #130                // Method scala/runtime/LazyVals$.getOffsetStatic:(Ljava/lang/reflect/Field;)J
      13: putstatic     #132                // Field OFFSET$_m_0:J
      16: return

  public scala.collection.Iterator productIterator();
    Code:
       0: aload_0
       1: invokestatic  #138                // InterfaceMethod scala/Product.productIterator$:(Lscala/Product;)Lscala/collection/Iterator;
       4: areturn

  public scala.collection.Iterator productElementNames();
    Code:
       0: aload_0
       1: invokestatic  #142                // InterfaceMethod scala/Product.productElementNames$:(Lscala/Product;)Lscala/collection/Iterator;
       4: areturn

  public int hashCode();
    Code:
       0: getstatic     #149                // Field scala/runtime/ScalaRunTime$.MODULE$:Lscala/runtime/ScalaRunTime$;
       3: aload_0
       4: invokevirtual #153                // Method scala/runtime/ScalaRunTime$._hashCode:(Lscala/Product;)I
       7: ireturn

  public boolean equals(java.lang.Object);
    Code:
       0: aload_0
       1: aload_1
       2: if_acmpeq     251
       5: aload_1
       6: astore_2
       7: aload_2
       8: instanceof    #2                  // class zio/aws/xray/model/GetTraceSummariesRequest
      11: ifeq          244
      14: aload_2
      15: checkcast     #2                  // class zio/aws/xray/model/GetTraceSummariesRequest
      18: astore_3
      19: aload_0
      20: invokevirtual #159                // Method startTime:()Ljava/time/Instant;
      23: aload_3
      24: invokevirtual #159                // Method startTime:()Ljava/time/Instant;
      27: astore        4
      29: dup
      30: ifnonnull     42
      33: pop
      34: aload         4
      36: ifnull        50
      39: goto          240
      42: aload         4
      44: invokevirtual #161                // Method java/lang/Object.equals:(Ljava/lang/Object;)Z
      47: ifeq          240
      50: aload_0
      51: invokevirtual #163                // Method endTime:()Ljava/time/Instant;
      54: aload_3
      55: invokevirtual #163                // Method endTime:()Ljava/time/Instant;
      58: astore        5
      60: dup
      61: ifnonnull     73
      64: pop
      65: aload         5
      67: ifnull        81
      70: goto          240
      73: aload         5
      75: invokevirtual #161                // Method java/lang/Object.equals:(Ljava/lang/Object;)Z
      78: ifeq          240
      81: aload_0
      82: invokevirtual #165                // Method timeRangeType:()Lzio/prelude/data/Optional;
      85: aload_3
      86: invokevirtual #165                // Method timeRangeType:()Lzio/prelude/data/Optional;
      89: astore        6
      91: dup
      92: ifnonnull     104
      95: pop
      96: aload         6
      98: ifnull        112
     101: goto          240
     104: aload         6
     106: invokevirtual #161                // Method java/lang/Object.equals:(Ljava/lang/Object;)Z
     109: ifeq          240
     112: aload_0
     113: invokevirtual #167                // Method sampling:()Lzio/prelude/data/Optional;
     116: aload_3
     117: invokevirtual #167                // Method sampling:()Lzio/prelude/data/Optional;
     120: astore        7
     122: dup
     123: ifnonnull     135
     126: pop
     127: aload         7
     129: ifnull        143
     132: goto          240
     135: aload         7
     137: invokevirtual #161                // Method java/lang/Object.equals:(Ljava/lang/Object;)Z
     140: ifeq          240
     143: aload_0
     144: invokevirtual #169                // Method samplingStrategy:()Lzio/prelude/data/Optional;
     147: aload_3
     148: invokevirtual #169                // Method samplingStrategy:()Lzio/prelude/data/Optional;
     151: astore        8
     153: dup
     154: ifnonnull     166
     157: pop
     158: aload         8
     160: ifnull        174
     163: goto          240
     166: aload         8
     168: invokevirtual #161                // Method java/lang/Object.equals:(Ljava/lang/Object;)Z
     171: ifeq          240
     174: aload_0
     175: invokevirtual #171                // Method filterExpression:()Lzio/prelude/data/Optional;
     178: aload_3
     179: invokevirtual #171                // Method filterExpression:()Lzio/prelude/data/Optional;
     182: astore        9
     184: dup
     185: ifnonnull     197
     188: pop
     189: aload         9
     191: ifnull        205
     194: goto          240
     197: aload         9
     199: invokevirtual #161                // Method java/lang/Object.equals:(Ljava/lang/Object;)Z
     202: ifeq          240
     205: aload_0
     206: invokevirtual #173                // Method nextToken:()Lzio/prelude/data/Optional;
     209: aload_3
     210: invokevirtual #173                // Method nextToken:()Lzio/prelude/data/Optional;
     213: astore        10
     215: dup
     216: ifnonnull     228
     219: pop
     220: aload         10
     222: ifnull        236
     225: goto          240
     228: aload         10
     230: invokevirtual #161                // Method java/lang/Object.equals:(Ljava/lang/Object;)Z
     233: ifeq          240
     236: iconst_1
     237: goto          241
     240: iconst_0
     241: goto          248
     244: iconst_0
     245: goto          248
     248: ifeq          255
     251: iconst_1
     252: goto          256
     255: iconst_0
     256: ireturn

  public java.lang.String toString();
    Code:
       0: getstatic     #149                // Field scala/runtime/ScalaRunTime$.MODULE$:Lscala/runtime/ScalaRunTime$;
       3: aload_0
       4: invokevirtual #184                // Method scala/runtime/ScalaRunTime$._toString:(Lscala/Product;)Ljava/lang/String;
       7: areturn

  public boolean canEqual(java.lang.Object);
    Code:
       0: aload_1
       1: instanceof    #2                  // class zio/aws/xray/model/GetTraceSummariesRequest
       4: ireturn

  public int productArity();
    Code:
       0: bipush        7
       2: ireturn

  public java.lang.String productPrefix();
    Code:
       0: ldc           #190                // String GetTraceSummariesRequest
       2: areturn

  public java.lang.Object productElement(int);
    Code:
       0: iload_1
       1: istore_2
       2: iload_2
       3: tableswitch   { // 0 to 6
                     0: 44
                     1: 49
                     2: 54
                     3: 59
                     4: 64
                     5: 69
                     6: 74
               default: 79
          }
      44: aload_0
      45: invokevirtual #196                // Method _1:()Ljava/time/Instant;
      48: areturn
      49: aload_0
      50: invokevirtual #199                // Method _2:()Ljava/time/Instant;
      53: areturn
      54: aload_0
      55: invokevirtual #202                // Method _3:()Lzio/prelude/data/Optional;
      58: areturn
      59: aload_0
      60: invokevirtual #205                // Method _4:()Lzio/prelude/data/Optional;
      63: areturn
      64: aload_0
      65: invokevirtual #208                // Method _5:()Lzio/prelude/data/Optional;
      68: areturn
      69: aload_0
      70: invokevirtual #211                // Method _6:()Lzio/prelude/data/Optional;
      73: areturn
      74: aload_0
      75: invokevirtual #214                // Method _7:()Lzio/prelude/data/Optional;
      78: areturn
      79: new           #216                // class java/lang/IndexOutOfBoundsException
      82: dup
      83: iload_1
      84: invokestatic  #222                // Method scala/runtime/BoxesRunTime.boxToInteger:(I)Ljava/lang/Integer;
      87: invokevirtual #226                // Method java/lang/Integer.toString:()Ljava/lang/String;
      90: invokespecial #229                // Method java/lang/IndexOutOfBoundsException."<init>":(Ljava/lang/String;)V
      93: athrow

  public java.lang.String productElementName(int);
    Code:
       0: iload_1
       1: istore_2
       2: iload_2
       3: tableswitch   { // 0 to 6
                     0: 44
                     1: 47
                     2: 50
                     3: 53
                     4: 56
                     5: 59
                     6: 62
               default: 65
          }
      44: ldc           #233                // String startTime
      46: areturn
      47: ldc           #234                // String endTime
      49: areturn
      50: ldc           #235                // String timeRangeType
      52: areturn
      53: ldc           #236                // String sampling
      55: areturn
      56: ldc           #237                // String samplingStrategy
      58: areturn
      59: ldc           #238                // String filterExpression
      61: areturn
      62: ldc           #239                // String nextToken
      64: areturn
      65: new           #216                // class java/lang/IndexOutOfBoundsException
      68: dup
      69: iload_1
      70: invokestatic  #222                // Method scala/runtime/BoxesRunTime.boxToInteger:(I)Ljava/lang/Integer;
      73: invokevirtual #226                // Method java/lang/Integer.toString:()Ljava/lang/String;
      76: invokespecial #229                // Method java/lang/IndexOutOfBoundsException."<init>":(Ljava/lang/String;)V
      79: athrow

  public java.time.Instant startTime();
    Code:
       0: aload_0
       1: getfield      #95                 // Field startTime:Ljava/time/Instant;
       4: areturn

  public java.time.Instant endTime();
    Code:
       0: aload_0
       1: getfield      #97                 // Field endTime:Ljava/time/Instant;
       4: areturn

  public zio.prelude.data.Optional<zio.aws.xray.model.TimeRangeType> timeRangeType();
    Code:
       0: aload_0
       1: getfield      #99                 // Field timeRangeType:Lzio/prelude/data/Optional;
       4: areturn

  public zio.prelude.data.Optional<java.lang.Object> sampling();
    Code:
       0: aload_0
       1: getfield      #101                // Field sampling:Lzio/prelude/data/Optional;
       4: areturn

  public zio.prelude.data.Optional<zio.aws.xray.model.SamplingStrategy> samplingStrategy();
    Code:
       0: aload_0
       1: getfield      #103                // Field samplingStrategy:Lzio/prelude/data/Optional;
       4: areturn

  public zio.prelude.data.Optional<java.lang.String> filterExpression();
    Code:
       0: aload_0
       1: getfield      #105                // Field filterExpression:Lzio/prelude/data/Optional;
       4: areturn

  public zio.prelude.data.Optional<java.lang.String> nextToken();
    Code:
       0: aload_0
       1: getfield      #107                // Field nextToken:Lzio/prelude/data/Optional;
       4: areturn

  public software.amazon.awssdk.services.xray.model.GetTraceSummariesRequest buildAwsValue();
    Code:
       0: getstatic     #56                 // Field zio/aws/xray/model/GetTraceSummariesRequest$.MODULE$:Lzio/aws/xray/model/GetTraceSummariesRequest$;
       3: invokevirtual #245                // Method zio/aws/xray/model/GetTraceSummariesRequest$.zio$aws$xray$model$GetTraceSummariesRequest$$$zioAwsBuilderHelper:()Lzio/aws/core/BuilderHelper;
       6: getstatic     #56                 // Field zio/aws/xray/model/GetTraceSummariesRequest$.MODULE$:Lzio/aws/xray/model/GetTraceSummariesRequest$;
       9: invokevirtual #245                // Method zio/aws/xray/model/GetTraceSummariesRequest$.zio$aws$xray$model$GetTraceSummariesRequest$$$zioAwsBuilderHelper:()Lzio/aws/core/BuilderHelper;
      12: getstatic     #56                 // Field zio/aws/xray/model/GetTraceSummariesRequest$.MODULE$:Lzio/aws/xray/model/GetTraceSummariesRequest$;
      15: invokevirtual #245                // Method zio/aws/xray/model/GetTraceSummariesRequest$.zio$aws$xray$model$GetTraceSummariesRequest$$$zioAwsBuilderHelper:()Lzio/aws/core/BuilderHelper;
      18: getstatic     #56                 // Field zio/aws/xray/model/GetTraceSummariesRequest$.MODULE$:Lzio/aws/xray/model/GetTraceSummariesRequest$;
      21: invokevirtual #245                // Method zio/aws/xray/model/GetTraceSummariesRequest$.zio$aws$xray$model$GetTraceSummariesRequest$$$zioAwsBuilderHelper:()Lzio/aws/core/BuilderHelper;
      24: getstatic     #56                 // Field zio/aws/xray/model/GetTraceSummariesRequest$.MODULE$:Lzio/aws/xray/model/GetTraceSummariesRequest$;
      27: invokevirtual #245                // Method zio/aws/xray/model/GetTraceSummariesRequest$.zio$aws$xray$model$GetTraceSummariesRequest$$$zioAwsBuilderHelper:()Lzio/aws/core/BuilderHelper;
      30: invokestatic  #249                // Method software/amazon/awssdk/services/xray/model/GetTraceSummariesRequest.builder:()Lsoftware/amazon/awssdk/services/xray/model/GetTraceSummariesRequest$Builder;
      33: getstatic     #252                // Field zio/aws/xray/model/package$primitives$Timestamp$.MODULE$:Lzio/aws/xray/model/package$primitives$Timestamp$;
      36: aload_0
      37: invokevirtual #159                // Method startTime:()Ljava/time/Instant;
      40: invokevirtual #256                // Method zio/aws/xray/model/package$primitives$Timestamp$.unwrap:(Ljava/lang/Object;)Ljava/lang/Object;
      43: checkcast     #176                // class java/time/Instant
      46: invokeinterface #259,  2          // InterfaceMethod software/amazon/awssdk/services/xray/model/GetTraceSummariesRequest$Builder.startTime:(Ljava/time/Instant;)Lsoftware/amazon/awssdk/services/xray/model/GetTraceSummariesRequest$Builder;
      51: getstatic     #252                // Field zio/aws/xray/model/package$primitives$Timestamp$.MODULE$:Lzio/aws/xray/model/package$primitives$Timestamp$;
      54: aload_0
      55: invokevirtual #163                // Method endTime:()Ljava/time/Instant;
      58: invokevirtual #256                // Method zio/aws/xray/model/package$primitives$Timestamp$.unwrap:(Ljava/lang/Object;)Ljava/lang/Object;
      61: checkcast     #176                // class java/time/Instant
      64: invokeinterface #261,  2          // InterfaceMethod software/amazon/awssdk/services/xray/model/GetTraceSummariesRequest$Builder.endTime:(Ljava/time/Instant;)Lsoftware/amazon/awssdk/services/xray/model/GetTraceSummariesRequest$Builder;
      69: invokeinterface #264,  2          // InterfaceMethod zio/aws/core/BuilderHelper.BuilderOps:(Lsoftware/amazon/awssdk/utils/builder/SdkBuilder;)Lzio/aws/core/BuilderHelper$BuilderOps;
      74: aload_0
      75: invokevirtual #165                // Method timeRangeType:()Lzio/prelude/data/Optional;
      78: invokedynamic #283,  0            // InvokeDynamic #0:apply:()Lscala/Function1;
      83: invokeinterface #287,  2          // InterfaceMethod zio/prelude/data/Optional.map:(Lscala/Function1;)Lzio/prelude/data/Optional;
      88: invokedynamic #294,  0            // InvokeDynamic #1:apply:()Lscala/Function1;
      93: invokevirtual #298                // Method zio/aws/core/BuilderHelper$BuilderOps.optionallyWith:(Lzio/prelude/data/Optional;Lscala/Function1;)Lsoftware/amazon/awssdk/utils/builder/SdkBuilder;
      96: invokeinterface #264,  2          // InterfaceMethod zio/aws/core/BuilderHelper.BuilderOps:(Lsoftware/amazon/awssdk/utils/builder/SdkBuilder;)Lzio/aws/core/BuilderHelper$BuilderOps;
     101: aload_0
     102: invokevirtual #167                // Method sampling:()Lzio/prelude/data/Optional;
     105: invokedynamic #305,  0            // InvokeDynamic #2:apply:()Lscala/Function1;
     110: invokeinterface #287,  2          // InterfaceMethod zio/prelude/data/Optional.map:(Lscala/Function1;)Lzio/prelude/data/Optional;
     115: invokedynamic #310,  0            // InvokeDynamic #3:apply:()Lscala/Function1;
     120: invokevirtual #298                // Method zio/aws/core/BuilderHelper$BuilderOps.optionallyWith:(Lzio/prelude/data/Optional;Lscala/Function1;)Lsoftware/amazon/awssdk/utils/builder/SdkBuilder;
     123: invokeinterface #264,  2          // InterfaceMethod zio/aws/core/BuilderHelper.BuilderOps:(Lsoftware/amazon/awssdk/utils/builder/SdkBuilder;)Lzio/aws/core/BuilderHelper$BuilderOps;
     128: aload_0
     129: invokevirtual #169                // Method samplingStrategy:()Lzio/prelude/data/Optional;
     132: invokedynamic #317,  0            // InvokeDynamic #4:apply:()Lscala/Function1;
     137: invokeinterface #287,  2          // InterfaceMethod zio/prelude/data/Optional.map:(Lscala/Function1;)Lzio/prelude/data/Optional;
     142: invokedynamic #322,  0            // InvokeDynamic #5:apply:()Lscala/Function1;
     147: invokevirtual #298                // Method zio/aws/core/BuilderHelper$BuilderOps.optionallyWith:(Lzio/prelude/data/Optional;Lscala/Function1;)Lsoftware/amazon/awssdk/utils/builder/SdkBuilder;
     150: invokeinterface #264,  2          // InterfaceMethod zio/aws/core/BuilderHelper.BuilderOps:(Lsoftware/amazon/awssdk/utils/builder/SdkBuilder;)Lzio/aws/core/BuilderHelper$BuilderOps;
     155: aload_0
     156: invokevirtual #171                // Method filterExpression:()Lzio/prelude/data/Optional;
     159: invokedynamic #329,  0            // InvokeDynamic #6:apply:()Lscala/Function1;
     164: invokeinterface #287,  2          // InterfaceMethod zio/prelude/data/Optional.map:(Lscala/Function1;)Lzio/prelude/data/Optional;
     169: invokedynamic #334,  0            // InvokeDynamic #7:apply:()Lscala/Function1;
     174: invokevirtual #298                // Method zio/aws/core/BuilderHelper$BuilderOps.optionallyWith:(Lzio/prelude/data/Optional;Lscala/Function1;)Lsoftware/amazon/awssdk/utils/builder/SdkBuilder;
     177: invokeinterface #264,  2          // InterfaceMethod zio/aws/core/BuilderHelper.BuilderOps:(Lsoftware/amazon/awssdk/utils/builder/SdkBuilder;)Lzio/aws/core/BuilderHelper$BuilderOps;
     182: aload_0
     183: invokevirtual #173                // Method nextToken:()Lzio/prelude/data/Optional;
     186: invokedynamic #339,  0            // InvokeDynamic #8:apply:()Lscala/Function1;
     191: invokeinterface #287,  2          // InterfaceMethod zio/prelude/data/Optional.map:(Lscala/Function1;)Lzio/prelude/data/Optional;
     196: invokedynamic #344,  0            // InvokeDynamic #9:apply:()Lscala/Function1;
     201: invokevirtual #298                // Method zio/aws/core/BuilderHelper$BuilderOps.optionallyWith:(Lzio/prelude/data/Optional;Lscala/Function1;)Lsoftware/amazon/awssdk/utils/builder/SdkBuilder;
     204: invokeinterface #350,  1          // InterfaceMethod software/amazon/awssdk/utils/builder/SdkBuilder.build:()Ljava/lang/Object;
     209: checkcast     #13                 // class software/amazon/awssdk/services/xray/model/GetTraceSummariesRequest
     212: areturn

  public zio.aws.xray.model.GetTraceSummariesRequest$ReadOnly asReadOnly();
    Code:
       0: getstatic     #56                 // Field zio/aws/xray/model/GetTraceSummariesRequest$.MODULE$:Lzio/aws/xray/model/GetTraceSummariesRequest$;
       3: aload_0
       4: invokevirtual #354                // Method buildAwsValue:()Lsoftware/amazon/awssdk/services/xray/model/GetTraceSummariesRequest;
       7: invokevirtual #70                 // Method zio/aws/xray/model/GetTraceSummariesRequest$.wrap:(Lsoftware/amazon/awssdk/services/xray/model/GetTraceSummariesRequest;)Lzio/aws/xray/model/GetTraceSummariesRequest$ReadOnly;
      10: areturn

  public zio.aws.xray.model.GetTraceSummariesRequest copy(java.time.Instant, java.time.Instant, zio.prelude.data.Optional<zio.aws.xray.model.TimeRangeType>, zio.prelude.data.Optional<java.lang.Object>, zio.prelude.data.Optional<zio.aws.xray.model.SamplingStrategy>, zio.prelude.data.Optional<java.lang.String>, zio.prelude.data.Optional<java.lang.String>);
    Code:
       0: new           #2                  // class zio/aws/xray/model/GetTraceSummariesRequest
       3: dup
       4: aload_1
       5: aload_2
       6: aload_3
       7: aload         4
       9: aload         5
      11: aload         6
      13: aload         7
      15: invokespecial #357                // Method "<init>":(Ljava/time/Instant;Ljava/time/Instant;Lzio/prelude/data/Optional;Lzio/prelude/data/Optional;Lzio/prelude/data/Optional;Lzio/prelude/data/Optional;Lzio/prelude/data/Optional;)V
      18: areturn

  public java.time.Instant copy$default$1();
    Code:
       0: aload_0
       1: invokevirtual #159                // Method startTime:()Ljava/time/Instant;
       4: areturn

  public java.time.Instant copy$default$2();
    Code:
       0: aload_0
       1: invokevirtual #163                // Method endTime:()Ljava/time/Instant;
       4: areturn

  public zio.prelude.data.Optional<zio.aws.xray.model.TimeRangeType> copy$default$3();
    Code:
       0: aload_0
       1: invokevirtual #165                // Method timeRangeType:()Lzio/prelude/data/Optional;
       4: areturn

  public zio.prelude.data.Optional<java.lang.Object> copy$default$4();
    Code:
       0: aload_0
       1: invokevirtual #167                // Method sampling:()Lzio/prelude/data/Optional;
       4: areturn

  public zio.prelude.data.Optional<zio.aws.xray.model.SamplingStrategy> copy$default$5();
    Code:
       0: aload_0
       1: invokevirtual #169                // Method samplingStrategy:()Lzio/prelude/data/Optional;
       4: areturn

  public zio.prelude.data.Optional<java.lang.String> copy$default$6();
    Code:
       0: aload_0
       1: invokevirtual #171                // Method filterExpression:()Lzio/prelude/data/Optional;
       4: areturn

  public zio.prelude.data.Optional<java.lang.String> copy$default$7();
    Code:
       0: aload_0
       1: invokevirtual #173                // Method nextToken:()Lzio/prelude/data/Optional;
       4: areturn

  public java.time.Instant _1();
    Code:
       0: aload_0
       1: invokevirtual #159                // Method startTime:()Ljava/time/Instant;
       4: areturn

  public java.time.Instant _2();
    Code:
       0: aload_0
       1: invokevirtual #163                // Method endTime:()Ljava/time/Instant;
       4: areturn

  public zio.prelude.data.Optional<zio.aws.xray.model.TimeRangeType> _3();
    Code:
       0: aload_0
       1: invokevirtual #165                // Method timeRangeType:()Lzio/prelude/data/Optional;
       4: areturn

  public zio.prelude.data.Optional<java.lang.Object> _4();
    Code:
       0: aload_0
       1: invokevirtual #167                // Method sampling:()Lzio/prelude/data/Optional;
       4: areturn

  public zio.prelude.data.Optional<zio.aws.xray.model.SamplingStrategy> _5();
    Code:
       0: aload_0
       1: invokevirtual #169                // Method samplingStrategy:()Lzio/prelude/data/Optional;
       4: areturn

  public zio.prelude.data.Optional<java.lang.String> _6();
    Code:
       0: aload_0
       1: invokevirtual #171                // Method filterExpression:()Lzio/prelude/data/Optional;
       4: areturn

  public zio.prelude.data.Optional<java.lang.String> _7();
    Code:
       0: aload_0
       1: invokevirtual #173                // Method nextToken:()Lzio/prelude/data/Optional;
       4: areturn

  private static final software.amazon.awssdk.services.xray.model.TimeRangeType buildAwsValue$$anonfun$1(zio.aws.xray.model.TimeRangeType);
    Code:
       0: aload_0
       1: invokeinterface #370,  1          // InterfaceMethod zio/aws/xray/model/TimeRangeType.unwrap:()Lsoftware/amazon/awssdk/services/xray/model/TimeRangeType;
       6: areturn

  private static final software.amazon.awssdk.services.xray.model.GetTraceSummariesRequest$Builder buildAwsValue$$anonfun$2$$anonfun$1(software.amazon.awssdk.services.xray.model.GetTraceSummariesRequest$Builder, software.amazon.awssdk.services.xray.model.TimeRangeType);
    Code:
       0: aload_0
       1: aload_1
       2: invokeinterface #377,  2          // InterfaceMethod software/amazon/awssdk/services/xray/model/GetTraceSummariesRequest$Builder.timeRangeType:(Lsoftware/amazon/awssdk/services/xray/model/TimeRangeType;)Lsoftware/amazon/awssdk/services/xray/model/GetTraceSummariesRequest$Builder;
       7: areturn

  private static final scala.Function1 buildAwsValue$$anonfun$2(software.amazon.awssdk.services.xray.model.GetTraceSummariesRequest$Builder);
    Code:
       0: aload_0
       1: invokedynamic #386,  0            // InvokeDynamic #10:apply:(Lsoftware/amazon/awssdk/services/xray/model/GetTraceSummariesRequest$Builder;)Lscala/Function1;
       6: areturn

  private static final java.lang.Boolean buildAwsValue$$anonfun$3(boolean);
    Code:
       0: getstatic     #393                // Field scala/Predef$.MODULE$:Lscala/Predef$;
       3: iload_0
       4: invokevirtual #396                // Method scala/Predef$.boolean2Boolean:(Z)Ljava/lang/Boolean;
       7: areturn

  private static java.lang.Boolean buildAwsValue$$anonfun$adapted$1(java.lang.Object);
    Code:
       0: aload_0
       1: invokestatic  #400                // Method scala/runtime/BoxesRunTime.unboxToBoolean:(Ljava/lang/Object;)Z
       4: invokestatic  #402                // Method buildAwsValue$$anonfun$3:(Z)Ljava/lang/Boolean;
       7: areturn

  private static final software.amazon.awssdk.services.xray.model.GetTraceSummariesRequest$Builder buildAwsValue$$anonfun$4$$anonfun$1(software.amazon.awssdk.services.xray.model.GetTraceSummariesRequest$Builder, java.lang.Boolean);
    Code:
       0: aload_0
       1: aload_1
       2: invokeinterface #408,  2          // InterfaceMethod software/amazon/awssdk/services/xray/model/GetTraceSummariesRequest$Builder.sampling:(Ljava/lang/Boolean;)Lsoftware/amazon/awssdk/services/xray/model/GetTraceSummariesRequest$Builder;
       7: areturn

  private static final scala.Function1 buildAwsValue$$anonfun$4(software.amazon.awssdk.services.xray.model.GetTraceSummariesRequest$Builder);
    Code:
       0: aload_0
       1: invokedynamic #415,  0            // InvokeDynamic #11:apply:(Lsoftware/amazon/awssdk/services/xray/model/GetTraceSummariesRequest$Builder;)Lscala/Function1;
       6: areturn

  private static final software.amazon.awssdk.services.xray.model.SamplingStrategy buildAwsValue$$anonfun$5(zio.aws.xray.model.SamplingStrategy);
    Code:
       0: aload_0
       1: invokevirtual #420                // Method zio/aws/xray/model/SamplingStrategy.buildAwsValue:()Lsoftware/amazon/awssdk/services/xray/model/SamplingStrategy;
       4: areturn

  private static final software.amazon.awssdk.services.xray.model.GetTraceSummariesRequest$Builder buildAwsValue$$anonfun$6$$anonfun$1(software.amazon.awssdk.services.xray.model.GetTraceSummariesRequest$Builder, software.amazon.awssdk.services.xray.model.SamplingStrategy);
    Code:
       0: aload_0
       1: aload_1
       2: invokeinterface #427,  2          // InterfaceMethod software/amazon/awssdk/services/xray/model/GetTraceSummariesRequest$Builder.samplingStrategy:(Lsoftware/amazon/awssdk/services/xray/model/SamplingStrategy;)Lsoftware/amazon/awssdk/services/xray/model/GetTraceSummariesRequest$Builder;
       7: areturn

  private static final scala.Function1 buildAwsValue$$anonfun$6(software.amazon.awssdk.services.xray.model.GetTraceSummariesRequest$Builder);
    Code:
       0: aload_0
       1: invokedynamic #434,  0            // InvokeDynamic #12:apply:(Lsoftware/amazon/awssdk/services/xray/model/GetTraceSummariesRequest$Builder;)Lscala/Function1;
       6: areturn

  private static final java.lang.String buildAwsValue$$anonfun$7(java.lang.String);
    Code:
       0: getstatic     #437                // Field zio/aws/xray/model/package$primitives$FilterExpression$.MODULE$:Lzio/aws/xray/model/package$primitives$FilterExpression$;
       3: aload_0
       4: invokevirtual #438                // Method zio/aws/xray/model/package$primitives$FilterExpression$.unwrap:(Ljava/lang/Object;)Ljava/lang/Object;
       7: checkcast     #440                // class java/lang/String
      10: areturn

  private static final software.amazon.awssdk.services.xray.model.GetTraceSummariesRequest$Builder buildAwsValue$$anonfun$8$$anonfun$1(software.amazon.awssdk.services.xray.model.GetTraceSummariesRequest$Builder, java.lang.String);
    Code:
       0: aload_0
       1: aload_1
       2: invokeinterface #447,  2          // InterfaceMethod software/amazon/awssdk/services/xray/model/GetTraceSummariesRequest$Builder.filterExpression:(Ljava/lang/String;)Lsoftware/amazon/awssdk/services/xray/model/GetTraceSummariesRequest$Builder;
       7: areturn

  private static final scala.Function1 buildAwsValue$$anonfun$8(software.amazon.awssdk.services.xray.model.GetTraceSummariesRequest$Builder);
    Code:
       0: aload_0
       1: invokedynamic #453,  0            // InvokeDynamic #13:apply:(Lsoftware/amazon/awssdk/services/xray/model/GetTraceSummariesRequest$Builder;)Lscala/Function1;
       6: areturn

  private static final java.lang.String buildAwsValue$$anonfun$9(java.lang.String);
    Code:
       0: aload_0
       1: areturn

  private static final software.amazon.awssdk.services.xray.model.GetTraceSummariesRequest$Builder buildAwsValue$$anonfun$10$$anonfun$1(software.amazon.awssdk.services.xray.model.GetTraceSummariesRequest$Builder, java.lang.String);
    Code:
       0: aload_0
       1: aload_1
       2: invokeinterface #457,  2          // InterfaceMethod software/amazon/awssdk/services/xray/model/GetTraceSummariesRequest$Builder.nextToken:(Ljava/lang/String;)Lsoftware/amazon/awssdk/services/xray/model/GetTraceSummariesRequest$Builder;
       7: areturn

  private static final scala.Function1 buildAwsValue$$anonfun$10(software.amazon.awssdk.services.xray.model.GetTraceSummariesRequest$Builder);
    Code:
       0: aload_0
       1: invokedynamic #462,  0            // InvokeDynamic #14:apply:(Lsoftware/amazon/awssdk/services/xray/model/GetTraceSummariesRequest$Builder;)Lscala/Function1;
       6: areturn

  private static java.lang.Object $deserializeLambda$(java.lang.invoke.SerializedLambda);
    Code:
       0: aload_0
       1: invokedynamic #474,  0            // InvokeDynamic #15:lambdaDeserialize:(Ljava/lang/invoke/SerializedLambda;)Ljava/lang/Object;
       6: areturn
}
