Compiled from "GroupSummary.scala"
public final class zio.aws.xray.model.GroupSummary$Wrapper implements zio.aws.xray.model.GroupSummary$ReadOnly {
  private final zio.prelude.data.Optional groupName;

  private final zio.prelude.data.Optional groupARN;

  private final zio.prelude.data.Optional filterExpression;

  private final zio.prelude.data.Optional insightsConfiguration;

  public zio.aws.xray.model.GroupSummary$Wrapper(software.amazon.awssdk.services.xray.model.GroupSummary);
    Code:
       0: aload_0
       1: invokespecial #26                 // Method java/lang/Object."<init>":()V
       4: aload_0
       5: getstatic     #32                 // Field zio/aws/core/internal/package$.MODULE$:Lzio/aws/core/internal/package$;
       8: aload_1
       9: invokevirtual #37                 // Method software/amazon/awssdk/services/xray/model/GroupSummary.groupName:()Ljava/lang/String;
      12: invokevirtual #41                 // Method zio/aws/core/internal/package$.optionalFromNullable:(Ljava/lang/Object;)Lzio/prelude/data/Optional;
      15: aload_0
      16: invokedynamic #62,  0             // InvokeDynamic #0:apply:(Lzio/aws/xray/model/GroupSummary$Wrapper;)Lscala/Function1;
      21: invokeinterface #68,  2           // InterfaceMethod zio/prelude/data/Optional.map:(Lscala/Function1;)Lzio/prelude/data/Optional;
      26: putfield      #70                 // Field groupName:Lzio/prelude/data/Optional;
      29: aload_0
      30: getstatic     #32                 // Field zio/aws/core/internal/package$.MODULE$:Lzio/aws/core/internal/package$;
      33: aload_1
      34: invokevirtual #72                 // Method software/amazon/awssdk/services/xray/model/GroupSummary.groupARN:()Ljava/lang/String;
      37: invokevirtual #41                 // Method zio/aws/core/internal/package$.optionalFromNullable:(Ljava/lang/Object;)Lzio/prelude/data/Optional;
      40: aload_0
      41: invokedynamic #77,  0             // InvokeDynamic #1:apply:(Lzio/aws/xray/model/GroupSummary$Wrapper;)Lscala/Function1;
      46: invokeinterface #68,  2           // InterfaceMethod zio/prelude/data/Optional.map:(Lscala/Function1;)Lzio/prelude/data/Optional;
      51: putfield      #79                 // Field groupARN:Lzio/prelude/data/Optional;
      54: aload_0
      55: getstatic     #32                 // Field zio/aws/core/internal/package$.MODULE$:Lzio/aws/core/internal/package$;
      58: aload_1
      59: invokevirtual #81                 // Method software/amazon/awssdk/services/xray/model/GroupSummary.filterExpression:()Ljava/lang/String;
      62: invokevirtual #41                 // Method zio/aws/core/internal/package$.optionalFromNullable:(Ljava/lang/Object;)Lzio/prelude/data/Optional;
      65: aload_0
      66: invokedynamic #86,  0             // InvokeDynamic #2:apply:(Lzio/aws/xray/model/GroupSummary$Wrapper;)Lscala/Function1;
      71: invokeinterface #68,  2           // InterfaceMethod zio/prelude/data/Optional.map:(Lscala/Function1;)Lzio/prelude/data/Optional;
      76: putfield      #88                 // Field filterExpression:Lzio/prelude/data/Optional;
      79: aload_0
      80: getstatic     #32                 // Field zio/aws/core/internal/package$.MODULE$:Lzio/aws/core/internal/package$;
      83: aload_1
      84: invokevirtual #91                 // Method software/amazon/awssdk/services/xray/model/GroupSummary.insightsConfiguration:()Lsoftware/amazon/awssdk/services/xray/model/InsightsConfiguration;
      87: invokevirtual #41                 // Method zio/aws/core/internal/package$.optionalFromNullable:(Ljava/lang/Object;)Lzio/prelude/data/Optional;
      90: aload_0
      91: invokedynamic #98,  0             // InvokeDynamic #3:apply:(Lzio/aws/xray/model/GroupSummary$Wrapper;)Lscala/Function1;
      96: invokeinterface #68,  2           // InterfaceMethod zio/prelude/data/Optional.map:(Lscala/Function1;)Lzio/prelude/data/Optional;
     101: putfield      #100                // Field insightsConfiguration:Lzio/prelude/data/Optional;
     104: return

  public zio.aws.xray.model.GroupSummary asEditable();
    Code:
       0: aload_0
       1: invokestatic  #109                // InterfaceMethod zio/aws/xray/model/GroupSummary$ReadOnly.asEditable$:(Lzio/aws/xray/model/GroupSummary$ReadOnly;)Lzio/aws/xray/model/GroupSummary;
       4: areturn

  public zio.ZIO getGroupName();
    Code:
       0: aload_0
       1: invokestatic  #115                // InterfaceMethod zio/aws/xray/model/GroupSummary$ReadOnly.getGroupName$:(Lzio/aws/xray/model/GroupSummary$ReadOnly;)Lzio/ZIO;
       4: areturn

  public zio.ZIO getGroupARN();
    Code:
       0: aload_0
       1: invokestatic  #119                // InterfaceMethod zio/aws/xray/model/GroupSummary$ReadOnly.getGroupARN$:(Lzio/aws/xray/model/GroupSummary$ReadOnly;)Lzio/ZIO;
       4: areturn

  public zio.ZIO getFilterExpression();
    Code:
       0: aload_0
       1: invokestatic  #123                // InterfaceMethod zio/aws/xray/model/GroupSummary$ReadOnly.getFilterExpression$:(Lzio/aws/xray/model/GroupSummary$ReadOnly;)Lzio/ZIO;
       4: areturn

  public zio.ZIO getInsightsConfiguration();
    Code:
       0: aload_0
       1: invokestatic  #127                // InterfaceMethod zio/aws/xray/model/GroupSummary$ReadOnly.getInsightsConfiguration$:(Lzio/aws/xray/model/GroupSummary$ReadOnly;)Lzio/ZIO;
       4: areturn

  public zio.prelude.data.Optional<java.lang.String> groupName();
    Code:
       0: aload_0
       1: getfield      #70                 // Field groupName:Lzio/prelude/data/Optional;
       4: areturn

  public zio.prelude.data.Optional<java.lang.String> groupARN();
    Code:
       0: aload_0
       1: getfield      #79                 // Field groupARN:Lzio/prelude/data/Optional;
       4: areturn

  public zio.prelude.data.Optional<java.lang.String> filterExpression();
    Code:
       0: aload_0
       1: getfield      #88                 // Field filterExpression:Lzio/prelude/data/Optional;
       4: areturn

  public zio.prelude.data.Optional<zio.aws.xray.model.InsightsConfiguration$ReadOnly> insightsConfiguration();
    Code:
       0: aload_0
       1: getfield      #100                // Field insightsConfiguration:Lzio/prelude/data/Optional;
       4: areturn

  private final java.lang.String $init$$$anonfun$1(java.lang.String);
    Code:
       0: aload_1
       1: areturn

  private final java.lang.String $init$$$anonfun$2(java.lang.String);
    Code:
       0: aload_1
       1: areturn

  private final java.lang.String $init$$$anonfun$3(java.lang.String);
    Code:
       0: aload_1
       1: areturn

  private final zio.aws.xray.model.InsightsConfiguration$ReadOnly $init$$$anonfun$4(software.amazon.awssdk.services.xray.model.InsightsConfiguration);
    Code:
       0: getstatic     #137                // Field zio/aws/xray/model/InsightsConfiguration$.MODULE$:Lzio/aws/xray/model/InsightsConfiguration$;
       3: aload_1
       4: invokevirtual #140                // Method zio/aws/xray/model/InsightsConfiguration$.wrap:(Lsoftware/amazon/awssdk/services/xray/model/InsightsConfiguration;)Lzio/aws/xray/model/InsightsConfiguration$ReadOnly;
       7: areturn

  private static java.lang.Object $deserializeLambda$(java.lang.invoke.SerializedLambda);
    Code:
       0: aload_0
       1: invokedynamic #153,  0            // InvokeDynamic #4:lambdaDeserialize:(Ljava/lang/invoke/SerializedLambda;)Ljava/lang/Object;
       6: areturn
}
