Compiled from "HistogramEntry.scala"
public interface zio.aws.xray.model.HistogramEntry$ReadOnly {
  public static zio.aws.xray.model.HistogramEntry asEditable$(zio.aws.xray.model.HistogramEntry$ReadOnly);
    Code:
       0: aload_0
       1: invokespecial #15                 // InterfaceMethod asEditable:()Lzio/aws/xray/model/HistogramEntry;
       4: areturn

  public default zio.aws.xray.model.HistogramEntry asEditable();
    Code:
       0: getstatic     #22                 // Field zio/aws/xray/model/HistogramEntry$.MODULE$:Lzio/aws/xray/model/HistogramEntry$;
       3: aload_0
       4: invokeinterface #26,  1           // InterfaceMethod value:()Lzio/prelude/data/Optional;
       9: aload_0
      10: invokedynamic #44,  0             // InvokeDynamic #0:apply$mcDD$sp:(Lzio/aws/xray/model/HistogramEntry$ReadOnly;)Lscala/runtime/java8/JFunction1$mcDD$sp;
      15: invokeinterface #50,  2           // InterfaceMethod zio/prelude/data/Optional.map:(Lscala/Function1;)Lzio/prelude/data/Optional;
      20: aload_0
      21: invokeinterface #53,  1           // InterfaceMethod count:()Lzio/prelude/data/Optional;
      26: aload_0
      27: invokedynamic #63,  0             // InvokeDynamic #1:apply$mcII$sp:(Lzio/aws/xray/model/HistogramEntry$ReadOnly;)Lscala/runtime/java8/JFunction1$mcII$sp;
      32: invokeinterface #50,  2           // InterfaceMethod zio/prelude/data/Optional.map:(Lscala/Function1;)Lzio/prelude/data/Optional;
      37: invokevirtual #67                 // Method zio/aws/xray/model/HistogramEntry$.apply:(Lzio/prelude/data/Optional;Lzio/prelude/data/Optional;)Lzio/aws/xray/model/HistogramEntry;
      40: areturn

  public abstract zio.prelude.data.Optional<java.lang.Object> value();

  public abstract zio.prelude.data.Optional<java.lang.Object> count();

  public static zio.ZIO getValue$(zio.aws.xray.model.HistogramEntry$ReadOnly);
    Code:
       0: aload_0
       1: invokespecial #75                 // InterfaceMethod getValue:()Lzio/ZIO;
       4: areturn

  public default zio.ZIO<java.lang.Object, zio.aws.core.AwsError, java.lang.Object> getValue();
    Code:
       0: getstatic     #81                 // Field zio/aws/core/AwsError$.MODULE$:Lzio/aws/core/AwsError$;
       3: ldc           #82                 // String value
       5: aload_0
       6: invokedynamic #93,  0             // InvokeDynamic #2:apply:(Lzio/aws/xray/model/HistogramEntry$ReadOnly;)Lscala/Function0;
      11: invokevirtual #97                 // Method zio/aws/core/AwsError$.unwrapOptionField:(Ljava/lang/String;Lscala/Function0;)Lzio/ZIO;
      14: areturn

  public static zio.ZIO getCount$(zio.aws.xray.model.HistogramEntry$ReadOnly);
    Code:
       0: aload_0
       1: invokespecial #101                // InterfaceMethod getCount:()Lzio/ZIO;
       4: areturn

  public default zio.ZIO<java.lang.Object, zio.aws.core.AwsError, java.lang.Object> getCount();
    Code:
       0: getstatic     #81                 // Field zio/aws/core/AwsError$.MODULE$:Lzio/aws/core/AwsError$;
       3: ldc           #102                // String count
       5: aload_0
       6: invokedynamic #107,  0            // InvokeDynamic #3:apply:(Lzio/aws/xray/model/HistogramEntry$ReadOnly;)Lscala/Function0;
      11: invokevirtual #97                 // Method zio/aws/core/AwsError$.unwrapOptionField:(Ljava/lang/String;Lscala/Function0;)Lzio/ZIO;
      14: areturn

  private double asEditable$$anonfun$1(double);
    Code:
       0: dload_1
       1: dreturn

  private int asEditable$$anonfun$2(int);
    Code:
       0: iload_1
       1: ireturn

  private zio.prelude.data.Optional getValue$$anonfun$1();
    Code:
       0: aload_0
       1: invokeinterface #26,  1           // InterfaceMethod value:()Lzio/prelude/data/Optional;
       6: areturn

  private zio.prelude.data.Optional getCount$$anonfun$1();
    Code:
       0: aload_0
       1: invokeinterface #53,  1           // InterfaceMethod count:()Lzio/prelude/data/Optional;
       6: areturn

  private static java.lang.Object $deserializeLambda$(java.lang.invoke.SerializedLambda);
    Code:
       0: aload_0
       1: invokedynamic #121,  0            // InvokeDynamic #4:lambdaDeserialize:(Ljava/lang/invoke/SerializedLambda;)Ljava/lang/Object;
       6: areturn
}
