Compiled from "InsightImpactGraphEdge.scala"
public final class zio.aws.xray.model.InsightImpactGraphEdge$Wrapper implements zio.aws.xray.model.InsightImpactGraphEdge$ReadOnly {
  private final zio.prelude.data.Optional referenceId;

  public zio.aws.xray.model.InsightImpactGraphEdge$Wrapper(software.amazon.awssdk.services.xray.model.InsightImpactGraphEdge);
    Code:
       0: aload_0
       1: invokespecial #19                 // Method java/lang/Object."<init>":()V
       4: aload_0
       5: getstatic     #25                 // Field zio/aws/core/internal/package$.MODULE$:Lzio/aws/core/internal/package$;
       8: aload_1
       9: invokevirtual #30                 // Method software/amazon/awssdk/services/xray/model/InsightImpactGraphEdge.referenceId:()Ljava/lang/Integer;
      12: invokevirtual #34                 // Method zio/aws/core/internal/package$.optionalFromNullable:(Ljava/lang/Object;)Lzio/prelude/data/Optional;
      15: aload_0
      16: invokedynamic #55,  0             // InvokeDynamic #0:apply:(Lzio/aws/xray/model/InsightImpactGraphEdge$Wrapper;)Lscala/Function1;
      21: invokeinterface #61,  2           // InterfaceMethod zio/prelude/data/Optional.map:(Lscala/Function1;)Lzio/prelude/data/Optional;
      26: putfield      #63                 // Field referenceId:Lzio/prelude/data/Optional;
      29: return

  public zio.aws.xray.model.InsightImpactGraphEdge asEditable();
    Code:
       0: aload_0
       1: invokestatic  #72                 // InterfaceMethod zio/aws/xray/model/InsightImpactGraphEdge$ReadOnly.asEditable$:(Lzio/aws/xray/model/InsightImpactGraphEdge$ReadOnly;)Lzio/aws/xray/model/InsightImpactGraphEdge;
       4: areturn

  public zio.ZIO getReferenceId();
    Code:
       0: aload_0
       1: invokestatic  #78                 // InterfaceMethod zio/aws/xray/model/InsightImpactGraphEdge$ReadOnly.getReferenceId$:(Lzio/aws/xray/model/InsightImpactGraphEdge$ReadOnly;)Lzio/ZIO;
       4: areturn

  public zio.prelude.data.Optional<java.lang.Object> referenceId();
    Code:
       0: aload_0
       1: getfield      #63                 // Field referenceId:Lzio/prelude/data/Optional;
       4: areturn

  private final int $init$$$anonfun$1(java.lang.Integer);
    Code:
       0: getstatic     #86                 // Field scala/Predef$.MODULE$:Lscala/Predef$;
       3: aload_1
       4: invokevirtual #89                 // Method scala/Predef$.Integer2int:(Ljava/lang/Integer;)I
       7: ireturn

  private static java.lang.Object $deserializeLambda$(java.lang.invoke.SerializedLambda);
    Code:
       0: aload_0
       1: invokedynamic #102,  0            // InvokeDynamic #1:lambdaDeserialize:(Ljava/lang/invoke/SerializedLambda;)Ljava/lang/Object;
       6: areturn
}
