Compiled from "PutTraceSegmentsRequest.scala"
public interface zio.aws.xray.model.PutTraceSegmentsRequest$ReadOnly {
  public static zio.aws.xray.model.PutTraceSegmentsRequest asEditable$(zio.aws.xray.model.PutTraceSegmentsRequest$ReadOnly);
    Code:
       0: aload_0
       1: invokespecial #15                 // InterfaceMethod asEditable:()Lzio/aws/xray/model/PutTraceSegmentsRequest;
       4: areturn

  public default zio.aws.xray.model.PutTraceSegmentsRequest asEditable();
    Code:
       0: getstatic     #22                 // Field zio/aws/xray/model/PutTraceSegmentsRequest$.MODULE$:Lzio/aws/xray/model/PutTraceSegmentsRequest$;
       3: aload_0
       4: invokeinterface #26,  1           // InterfaceMethod traceSegmentDocuments:()Lscala/collection/immutable/List;
       9: invokevirtual #30                 // Method zio/aws/xray/model/PutTraceSegmentsRequest$.apply:(Lscala/collection/Iterable;)Lzio/aws/xray/model/PutTraceSegmentsRequest;
      12: areturn

  public abstract scala.collection.immutable.List<java.lang.String> traceSegmentDocuments();

  public static zio.ZIO getTraceSegmentDocuments$(zio.aws.xray.model.PutTraceSegmentsRequest$ReadOnly);
    Code:
       0: aload_0
       1: invokespecial #38                 // InterfaceMethod getTraceSegmentDocuments:()Lzio/ZIO;
       4: areturn

  public default zio.ZIO<java.lang.Object, scala.runtime.Nothing$, scala.collection.immutable.List<java.lang.String>> getTraceSegmentDocuments();
    Code:
       0: getstatic     #44                 // Field zio/ZIO$.MODULE$:Lzio/ZIO$;
       3: aload_0
       4: invokedynamic #64,  0             // InvokeDynamic #0:apply:(Lzio/aws/xray/model/PutTraceSegmentsRequest$ReadOnly;)Lscala/Function1;
       9: ldc           #66                 // String zio.aws.xray.model.PutTraceSegmentsRequest.ReadOnly.getTraceSegmentDocuments(PutTraceSegmentsRequest.scala:32)
      11: invokevirtual #70                 // Method zio/ZIO$.succeed:(Lscala/Function1;Ljava/lang/Object;)Lzio/ZIO;
      14: areturn

  private scala.collection.immutable.List getTraceSegmentDocuments$$anonfun$1(zio.Unsafe);
    Code:
       0: aload_0
       1: invokeinterface #26,  1           // InterfaceMethod traceSegmentDocuments:()Lscala/collection/immutable/List;
       6: areturn

  private static java.lang.Object $deserializeLambda$(java.lang.invoke.SerializedLambda);
    Code:
       0: aload_0
       1: invokedynamic #84,  0             // InvokeDynamic #1:lambdaDeserialize:(Ljava/lang/invoke/SerializedLambda;)Ljava/lang/Object;
       6: areturn
}
