Compiled from "TelemetryRecord.scala"
public final class zio.aws.xray.model.TelemetryRecord$Wrapper implements zio.aws.xray.model.TelemetryRecord$ReadOnly {
  private final java.time.Instant timestamp;

  private final zio.prelude.data.Optional segmentsReceivedCount;

  private final zio.prelude.data.Optional segmentsSentCount;

  private final zio.prelude.data.Optional segmentsSpilloverCount;

  private final zio.prelude.data.Optional segmentsRejectedCount;

  private final zio.prelude.data.Optional backendConnectionErrors;

  public zio.aws.xray.model.TelemetryRecord$Wrapper(software.amazon.awssdk.services.xray.model.TelemetryRecord);
    Code:
       0: aload_0
       1: invokespecial #37                 // Method java/lang/Object."<init>":()V
       4: aload_0
       5: getstatic     #41                 // Field zio/aws/xray/model/package$primitives$Timestamp$.MODULE$:Lzio/aws/xray/model/package$primitives$Timestamp$;
       8: astore_2
       9: aload_1
      10: invokevirtual #46                 // Method software/amazon/awssdk/services/xray/model/TelemetryRecord.timestamp:()Ljava/time/Instant;
      13: putfield      #48                 // Field timestamp:Ljava/time/Instant;
      16: aload_0
      17: getstatic     #53                 // Field zio/aws/core/internal/package$.MODULE$:Lzio/aws/core/internal/package$;
      20: aload_1
      21: invokevirtual #56                 // Method software/amazon/awssdk/services/xray/model/TelemetryRecord.segmentsReceivedCount:()Ljava/lang/Integer;
      24: invokevirtual #60                 // Method zio/aws/core/internal/package$.optionalFromNullable:(Ljava/lang/Object;)Lzio/prelude/data/Optional;
      27: aload_0
      28: invokedynamic #81,  0             // InvokeDynamic #0:apply:(Lzio/aws/xray/model/TelemetryRecord$Wrapper;)Lscala/Function1;
      33: invokeinterface #87,  2           // InterfaceMethod zio/prelude/data/Optional.map:(Lscala/Function1;)Lzio/prelude/data/Optional;
      38: putfield      #89                 // Field segmentsReceivedCount:Lzio/prelude/data/Optional;
      41: aload_0
      42: getstatic     #53                 // Field zio/aws/core/internal/package$.MODULE$:Lzio/aws/core/internal/package$;
      45: aload_1
      46: invokevirtual #91                 // Method software/amazon/awssdk/services/xray/model/TelemetryRecord.segmentsSentCount:()Ljava/lang/Integer;
      49: invokevirtual #60                 // Method zio/aws/core/internal/package$.optionalFromNullable:(Ljava/lang/Object;)Lzio/prelude/data/Optional;
      52: aload_0
      53: invokedynamic #96,  0             // InvokeDynamic #1:apply:(Lzio/aws/xray/model/TelemetryRecord$Wrapper;)Lscala/Function1;
      58: invokeinterface #87,  2           // InterfaceMethod zio/prelude/data/Optional.map:(Lscala/Function1;)Lzio/prelude/data/Optional;
      63: putfield      #98                 // Field segmentsSentCount:Lzio/prelude/data/Optional;
      66: aload_0
      67: getstatic     #53                 // Field zio/aws/core/internal/package$.MODULE$:Lzio/aws/core/internal/package$;
      70: aload_1
      71: invokevirtual #100                // Method software/amazon/awssdk/services/xray/model/TelemetryRecord.segmentsSpilloverCount:()Ljava/lang/Integer;
      74: invokevirtual #60                 // Method zio/aws/core/internal/package$.optionalFromNullable:(Ljava/lang/Object;)Lzio/prelude/data/Optional;
      77: aload_0
      78: invokedynamic #105,  0            // InvokeDynamic #2:apply:(Lzio/aws/xray/model/TelemetryRecord$Wrapper;)Lscala/Function1;
      83: invokeinterface #87,  2           // InterfaceMethod zio/prelude/data/Optional.map:(Lscala/Function1;)Lzio/prelude/data/Optional;
      88: putfield      #107                // Field segmentsSpilloverCount:Lzio/prelude/data/Optional;
      91: aload_0
      92: getstatic     #53                 // Field zio/aws/core/internal/package$.MODULE$:Lzio/aws/core/internal/package$;
      95: aload_1
      96: invokevirtual #109                // Method software/amazon/awssdk/services/xray/model/TelemetryRecord.segmentsRejectedCount:()Ljava/lang/Integer;
      99: invokevirtual #60                 // Method zio/aws/core/internal/package$.optionalFromNullable:(Ljava/lang/Object;)Lzio/prelude/data/Optional;
     102: aload_0
     103: invokedynamic #114,  0            // InvokeDynamic #3:apply:(Lzio/aws/xray/model/TelemetryRecord$Wrapper;)Lscala/Function1;
     108: invokeinterface #87,  2           // InterfaceMethod zio/prelude/data/Optional.map:(Lscala/Function1;)Lzio/prelude/data/Optional;
     113: putfield      #116                // Field segmentsRejectedCount:Lzio/prelude/data/Optional;
     116: aload_0
     117: getstatic     #53                 // Field zio/aws/core/internal/package$.MODULE$:Lzio/aws/core/internal/package$;
     120: aload_1
     121: invokevirtual #119                // Method software/amazon/awssdk/services/xray/model/TelemetryRecord.backendConnectionErrors:()Lsoftware/amazon/awssdk/services/xray/model/BackendConnectionErrors;
     124: invokevirtual #60                 // Method zio/aws/core/internal/package$.optionalFromNullable:(Ljava/lang/Object;)Lzio/prelude/data/Optional;
     127: aload_0
     128: invokedynamic #126,  0            // InvokeDynamic #4:apply:(Lzio/aws/xray/model/TelemetryRecord$Wrapper;)Lscala/Function1;
     133: invokeinterface #87,  2           // InterfaceMethod zio/prelude/data/Optional.map:(Lscala/Function1;)Lzio/prelude/data/Optional;
     138: putfield      #128                // Field backendConnectionErrors:Lzio/prelude/data/Optional;
     141: return

  public zio.aws.xray.model.TelemetryRecord asEditable();
    Code:
       0: aload_0
       1: invokestatic  #138                // InterfaceMethod zio/aws/xray/model/TelemetryRecord$ReadOnly.asEditable$:(Lzio/aws/xray/model/TelemetryRecord$ReadOnly;)Lzio/aws/xray/model/TelemetryRecord;
       4: areturn

  public zio.ZIO getTimestamp();
    Code:
       0: aload_0
       1: invokestatic  #144                // InterfaceMethod zio/aws/xray/model/TelemetryRecord$ReadOnly.getTimestamp$:(Lzio/aws/xray/model/TelemetryRecord$ReadOnly;)Lzio/ZIO;
       4: areturn

  public zio.ZIO getSegmentsReceivedCount();
    Code:
       0: aload_0
       1: invokestatic  #148                // InterfaceMethod zio/aws/xray/model/TelemetryRecord$ReadOnly.getSegmentsReceivedCount$:(Lzio/aws/xray/model/TelemetryRecord$ReadOnly;)Lzio/ZIO;
       4: areturn

  public zio.ZIO getSegmentsSentCount();
    Code:
       0: aload_0
       1: invokestatic  #152                // InterfaceMethod zio/aws/xray/model/TelemetryRecord$ReadOnly.getSegmentsSentCount$:(Lzio/aws/xray/model/TelemetryRecord$ReadOnly;)Lzio/ZIO;
       4: areturn

  public zio.ZIO getSegmentsSpilloverCount();
    Code:
       0: aload_0
       1: invokestatic  #156                // InterfaceMethod zio/aws/xray/model/TelemetryRecord$ReadOnly.getSegmentsSpilloverCount$:(Lzio/aws/xray/model/TelemetryRecord$ReadOnly;)Lzio/ZIO;
       4: areturn

  public zio.ZIO getSegmentsRejectedCount();
    Code:
       0: aload_0
       1: invokestatic  #160                // InterfaceMethod zio/aws/xray/model/TelemetryRecord$ReadOnly.getSegmentsRejectedCount$:(Lzio/aws/xray/model/TelemetryRecord$ReadOnly;)Lzio/ZIO;
       4: areturn

  public zio.ZIO getBackendConnectionErrors();
    Code:
       0: aload_0
       1: invokestatic  #164                // InterfaceMethod zio/aws/xray/model/TelemetryRecord$ReadOnly.getBackendConnectionErrors$:(Lzio/aws/xray/model/TelemetryRecord$ReadOnly;)Lzio/ZIO;
       4: areturn

  public java.time.Instant timestamp();
    Code:
       0: aload_0
       1: getfield      #48                 // Field timestamp:Ljava/time/Instant;
       4: areturn

  public zio.prelude.data.Optional<java.lang.Object> segmentsReceivedCount();
    Code:
       0: aload_0
       1: getfield      #89                 // Field segmentsReceivedCount:Lzio/prelude/data/Optional;
       4: areturn

  public zio.prelude.data.Optional<java.lang.Object> segmentsSentCount();
    Code:
       0: aload_0
       1: getfield      #98                 // Field segmentsSentCount:Lzio/prelude/data/Optional;
       4: areturn

  public zio.prelude.data.Optional<java.lang.Object> segmentsSpilloverCount();
    Code:
       0: aload_0
       1: getfield      #107                // Field segmentsSpilloverCount:Lzio/prelude/data/Optional;
       4: areturn

  public zio.prelude.data.Optional<java.lang.Object> segmentsRejectedCount();
    Code:
       0: aload_0
       1: getfield      #116                // Field segmentsRejectedCount:Lzio/prelude/data/Optional;
       4: areturn

  public zio.prelude.data.Optional<zio.aws.xray.model.BackendConnectionErrors$ReadOnly> backendConnectionErrors();
    Code:
       0: aload_0
       1: getfield      #128                // Field backendConnectionErrors:Lzio/prelude/data/Optional;
       4: areturn

  private final int $init$$$anonfun$1(java.lang.Integer);
    Code:
       0: getstatic     #173                // Field scala/Predef$.MODULE$:Lscala/Predef$;
       3: aload_1
       4: invokevirtual #176                // Method scala/Predef$.Integer2int:(Ljava/lang/Integer;)I
       7: ireturn

  private final int $init$$$anonfun$2(java.lang.Integer);
    Code:
       0: getstatic     #173                // Field scala/Predef$.MODULE$:Lscala/Predef$;
       3: aload_1
       4: invokevirtual #176                // Method scala/Predef$.Integer2int:(Ljava/lang/Integer;)I
       7: ireturn

  private final int $init$$$anonfun$3(java.lang.Integer);
    Code:
       0: getstatic     #173                // Field scala/Predef$.MODULE$:Lscala/Predef$;
       3: aload_1
       4: invokevirtual #176                // Method scala/Predef$.Integer2int:(Ljava/lang/Integer;)I
       7: ireturn

  private final int $init$$$anonfun$4(java.lang.Integer);
    Code:
       0: getstatic     #173                // Field scala/Predef$.MODULE$:Lscala/Predef$;
       3: aload_1
       4: invokevirtual #176                // Method scala/Predef$.Integer2int:(Ljava/lang/Integer;)I
       7: ireturn

  private final zio.aws.xray.model.BackendConnectionErrors$ReadOnly $init$$$anonfun$5(software.amazon.awssdk.services.xray.model.BackendConnectionErrors);
    Code:
       0: getstatic     #182                // Field zio/aws/xray/model/BackendConnectionErrors$.MODULE$:Lzio/aws/xray/model/BackendConnectionErrors$;
       3: aload_1
       4: invokevirtual #185                // Method zio/aws/xray/model/BackendConnectionErrors$.wrap:(Lsoftware/amazon/awssdk/services/xray/model/BackendConnectionErrors;)Lzio/aws/xray/model/BackendConnectionErrors$ReadOnly;
       7: areturn

  private static java.lang.Object $deserializeLambda$(java.lang.invoke.SerializedLambda);
    Code:
       0: aload_0
       1: invokedynamic #198,  0            // InvokeDynamic #5:lambdaDeserialize:(Ljava/lang/invoke/SerializedLambda;)Ljava/lang/Object;
       6: areturn
}
