Compiled from "UpdateSamplingRuleRequest.scala"
public final class zio.aws.xray.model.UpdateSamplingRuleRequest$Wrapper implements zio.aws.xray.model.UpdateSamplingRuleRequest$ReadOnly {
  private final zio.aws.xray.model.SamplingRuleUpdate$ReadOnly samplingRuleUpdate;

  public zio.aws.xray.model.UpdateSamplingRuleRequest$Wrapper(software.amazon.awssdk.services.xray.model.UpdateSamplingRuleRequest);
    Code:
       0: aload_0
       1: invokespecial #23                 // Method java/lang/Object."<init>":()V
       4: aload_0
       5: getstatic     #29                 // Field zio/aws/xray/model/SamplingRuleUpdate$.MODULE$:Lzio/aws/xray/model/SamplingRuleUpdate$;
       8: aload_1
       9: invokevirtual #34                 // Method software/amazon/awssdk/services/xray/model/UpdateSamplingRuleRequest.samplingRuleUpdate:()Lsoftware/amazon/awssdk/services/xray/model/SamplingRuleUpdate;
      12: invokevirtual #38                 // Method zio/aws/xray/model/SamplingRuleUpdate$.wrap:(Lsoftware/amazon/awssdk/services/xray/model/SamplingRuleUpdate;)Lzio/aws/xray/model/SamplingRuleUpdate$ReadOnly;
      15: putfield      #40                 // Field samplingRuleUpdate:Lzio/aws/xray/model/SamplingRuleUpdate$ReadOnly;
      18: return

  public zio.aws.xray.model.UpdateSamplingRuleRequest asEditable();
    Code:
       0: aload_0
       1: invokestatic  #49                 // InterfaceMethod zio/aws/xray/model/UpdateSamplingRuleRequest$ReadOnly.asEditable$:(Lzio/aws/xray/model/UpdateSamplingRuleRequest$ReadOnly;)Lzio/aws/xray/model/UpdateSamplingRuleRequest;
       4: areturn

  public zio.ZIO getSamplingRuleUpdate();
    Code:
       0: aload_0
       1: invokestatic  #55                 // InterfaceMethod zio/aws/xray/model/UpdateSamplingRuleRequest$ReadOnly.getSamplingRuleUpdate$:(Lzio/aws/xray/model/UpdateSamplingRuleRequest$ReadOnly;)Lzio/ZIO;
       4: areturn

  public zio.aws.xray.model.SamplingRuleUpdate$ReadOnly samplingRuleUpdate();
    Code:
       0: aload_0
       1: getfield      #40                 // Field samplingRuleUpdate:Lzio/aws/xray/model/SamplingRuleUpdate$ReadOnly;
       4: areturn
}
