Compiled from "SequenceIdentityGenerator.java"
public class org.hibernate.id.SequenceIdentityGenerator extends org.hibernate.id.SequenceGenerator implements org.hibernate.id.PostInsertIdentifierGenerator {
  private static final org.hibernate.internal.CoreMessageLogger LOG;

  public org.hibernate.id.SequenceIdentityGenerator();
    Code:
       0: aload_0
       1: invokespecial #2                  // Method org/hibernate/id/SequenceGenerator."<init>":()V
       4: return

  public java.io.Serializable generate(org.hibernate.engine.spi.SharedSessionContractImplementor, java.lang.Object);
    Code:
       0: getstatic     #3                  // Field org/hibernate/id/IdentifierGeneratorHelper.POST_INSERT_INDICATOR:Ljava/io/Serializable;
       3: areturn

  public org.hibernate.id.insert.InsertGeneratedIdentifierDelegate getInsertGeneratedIdentifierDelegate(org.hibernate.id.PostInsertIdentityPersister, org.hibernate.dialect.Dialect, boolean) throws org.hibernate.HibernateException;
    Code:
       0: new           #4                  // class org/hibernate/id/SequenceIdentityGenerator$Delegate
       3: dup
       4: aload_1
       5: aload_2
       6: aload_0
       7: invokevirtual #5                  // Method getSequenceName:()Ljava/lang/String;
      10: invokespecial #6                  // Method org/hibernate/id/SequenceIdentityGenerator$Delegate."<init>":(Lorg/hibernate/id/PostInsertIdentityPersister;Lorg/hibernate/dialect/Dialect;Ljava/lang/String;)V
      13: areturn

  public void configure(org.hibernate.type.Type, java.util.Properties, org.hibernate.service.ServiceRegistry) throws org.hibernate.MappingException;
    Code:
       0: aload_0
       1: aload_1
       2: aload_2
       3: aload_3
       4: invokespecial #7                  // Method org/hibernate/id/SequenceGenerator.configure:(Lorg/hibernate/type/Type;Ljava/util/Properties;Lorg/hibernate/service/ServiceRegistry;)V
       7: return

  static org.hibernate.internal.CoreMessageLogger access$000();
    Code:
       0: getstatic     #1                  // Field LOG:Lorg/hibernate/internal/CoreMessageLogger;
       3: areturn

  static {};
    Code:
       0: ldc           #8                  // class org/hibernate/id/SequenceIdentityGenerator
       2: invokestatic  #9                  // Method org/hibernate/internal/CoreLogging.messageLogger:(Ljava/lang/Class;)Lorg/hibernate/internal/CoreMessageLogger;
       5: putstatic     #1                  // Field LOG:Lorg/hibernate/internal/CoreMessageLogger;
       8: return
}
