public class org.bouncycastle.cert.dane.DANECertificateFetcher {
  private final org.bouncycastle.cert.dane.DANEEntryFetcherFactory fetcherFactory;

  private final org.bouncycastle.cert.dane.DANEEntrySelectorFactory selectorFactory;

  public org.bouncycastle.cert.dane.DANECertificateFetcher(org.bouncycastle.cert.dane.DANEEntryFetcherFactory, org.bouncycastle.operator.DigestCalculator);
    Code:
       0: aload_0
       1: invokespecial #78                 // Method java/lang/Object."<init>":()V
       4: aload_0
       5: aload_1
       6: putfield      #76                 // Field fetcherFactory:Lorg/bouncycastle/cert/dane/DANEEntryFetcherFactory;
       9: aload_0
      10: new           #43                 // class org/bouncycastle/cert/dane/DANEEntrySelectorFactory
      13: dup
      14: aload_2
      15: invokespecial #84                 // Method org/bouncycastle/cert/dane/DANEEntrySelectorFactory."<init>":(Lorg/bouncycastle/operator/DigestCalculator;)V
      18: putfield      #77                 // Field selectorFactory:Lorg/bouncycastle/cert/dane/DANEEntrySelectorFactory;
      21: return

  public java.util.List fetch(java.lang.String) throws org.bouncycastle.cert.dane.DANEException;
    Code:
       0: aload_0
       1: getfield      #77                 // Field selectorFactory:Lorg/bouncycastle/cert/dane/DANEEntrySelectorFactory;
       4: aload_1
       5: invokevirtual #85                 // Method org/bouncycastle/cert/dane/DANEEntrySelectorFactory.createSelector:(Ljava/lang/String;)Lorg/bouncycastle/cert/dane/DANEEntrySelector;
       8: astore_2
       9: aload_0
      10: getfield      #76                 // Field fetcherFactory:Lorg/bouncycastle/cert/dane/DANEEntryFetcherFactory;
      13: aload_2
      14: invokevirtual #83                 // Method org/bouncycastle/cert/dane/DANEEntrySelector.getDomainName:()Ljava/lang/String;
      17: invokeinterface #92,  2           // InterfaceMethod org/bouncycastle/cert/dane/DANEEntryFetcherFactory.build:(Ljava/lang/String;)Lorg/bouncycastle/cert/dane/DANEEntryFetcher;
      22: invokeinterface #91,  1           // InterfaceMethod org/bouncycastle/cert/dane/DANEEntryFetcher.getEntries:()Ljava/util/List;
      27: astore_3
      28: new           #34                 // class java/util/ArrayList
      31: dup
      32: aload_3
      33: invokeinterface #88,  1           // InterfaceMethod java/util/List.size:()I
      38: invokespecial #79                 // Method java/util/ArrayList."<init>":(I)V
      41: astore        4
      43: aload_3
      44: invokeinterface #90,  1           // InterfaceMethod java/util/List.iterator:()Ljava/util/Iterator;
      49: astore        5
      51: aload         5
      53: invokeinterface #86,  1           // InterfaceMethod java/util/Iterator.hasNext:()Z
      58: ifeq          98
      61: aload         5
      63: invokeinterface #87,  1           // InterfaceMethod java/util/Iterator.next:()Ljava/lang/Object;
      68: checkcast     #39                 // class org/bouncycastle/cert/dane/DANEEntry
      71: astore        6
      73: aload_2
      74: aload         6
      76: invokevirtual #82                 // Method org/bouncycastle/cert/dane/DANEEntrySelector.match:(Ljava/lang/Object;)Z
      79: ifeq          95
      82: aload         4
      84: aload         6
      86: invokevirtual #81                 // Method org/bouncycastle/cert/dane/DANEEntry.getCertificate:()Lorg/bouncycastle/cert/X509CertificateHolder;
      89: invokeinterface #89,  2           // InterfaceMethod java/util/List.add:(Ljava/lang/Object;)Z
      94: pop
      95: goto          51
      98: aload         4
     100: invokestatic  #80                 // Method java/util/Collections.unmodifiableList:(Ljava/util/List;)Ljava/util/List;
     103: areturn
}
