Compiled from "DefaultRuleEngine.java"
public class software.amazon.awssdk.services.waf.regional.endpoints.internal.DefaultRuleEngine implements software.amazon.awssdk.services.waf.regional.endpoints.internal.RuleEngine {
  private final software.amazon.awssdk.services.waf.regional.endpoints.internal.RuleEvaluator evaluator;

  public software.amazon.awssdk.services.waf.regional.endpoints.internal.DefaultRuleEngine();
    Code:
       0: aload_0
       1: invokespecial #1                  // Method java/lang/Object."<init>":()V
       4: aload_0
       5: new           #2                  // class software/amazon/awssdk/services/waf/regional/endpoints/internal/RuleEvaluator
       8: dup
       9: invokespecial #3                  // Method software/amazon/awssdk/services/waf/regional/endpoints/internal/RuleEvaluator."<init>":()V
      12: putfield      #4                  // Field evaluator:Lsoftware/amazon/awssdk/services/waf/regional/endpoints/internal/RuleEvaluator;
      15: return

  public software.amazon.awssdk.services.waf.regional.endpoints.internal.Value evaluate(software.amazon.awssdk.services.waf.regional.endpoints.internal.EndpointRuleset, java.util.Map<software.amazon.awssdk.services.waf.regional.endpoints.internal.Identifier, software.amazon.awssdk.services.waf.regional.endpoints.internal.Value>);
    Code:
       0: aload_0
       1: getfield      #4                  // Field evaluator:Lsoftware/amazon/awssdk/services/waf/regional/endpoints/internal/RuleEvaluator;
       4: aload_1
       5: aload_2
       6: invokevirtual #5                  // Method software/amazon/awssdk/services/waf/regional/endpoints/internal/RuleEvaluator.evaluateRuleset:(Lsoftware/amazon/awssdk/services/waf/regional/endpoints/internal/EndpointRuleset;Ljava/util/Map;)Lsoftware/amazon/awssdk/services/waf/regional/endpoints/internal/Value;
       9: areturn
}
