Compiled from "PeekReader.java"
public final class org.apache.jena.atlas.io.PeekReader extends java.io.Reader {
  private final org.apache.jena.atlas.io.CharStream source;

  private static final int PUSHBACK_SIZE;

  static final byte CHAR0;

  private char[] pushbackChars;

  private int idxPushback;

  private int currChar;

  private long posn;

  public static final int INIT_LINE;

  public static final int INIT_COL;

  private long colNum;

  private long lineNum;

  public static org.apache.jena.atlas.io.PeekReader make(java.io.Reader);
    Code:
       0: aload_0
       1: instanceof    #2                  // class org/apache/jena/atlas/io/PeekReader
       4: ifeq          12
       7: aload_0
       8: checkcast     #2                  // class org/apache/jena/atlas/io/PeekReader
      11: areturn
      12: aload_0
      13: ldc           #4                  // int 131072
      15: invokestatic  #5                  // Method make:(Ljava/io/Reader;I)Lorg/apache/jena/atlas/io/PeekReader;
      18: areturn

  public static org.apache.jena.atlas.io.PeekReader make(java.io.Reader, int);
    Code:
       0: new           #2                  // class org/apache/jena/atlas/io/PeekReader
       3: dup
       4: new           #3                  // class org/apache/jena/atlas/io/CharStreamBuffered
       7: dup
       8: aload_0
       9: iload_1
      10: invokespecial #6                  // Method org/apache/jena/atlas/io/CharStreamBuffered."<init>":(Ljava/io/Reader;I)V
      13: invokespecial #7                  // Method "<init>":(Lorg/apache/jena/atlas/io/CharStream;)V
      16: areturn

  public static org.apache.jena.atlas.io.PeekReader makeUTF8(java.io.InputStream);
    Code:
       0: aload_0
       1: invokestatic  #8                  // Method org/apache/jena/atlas/io/IO.asUTF8:(Ljava/io/InputStream;)Ljava/io/Reader;
       4: astore_2
       5: aload_2
       6: invokestatic  #9                  // Method make:(Ljava/io/Reader;)Lorg/apache/jena/atlas/io/PeekReader;
       9: astore_1
      10: aload_1
      11: invokevirtual #10                 // Method peekChar:()I
      14: istore_2
      15: iload_2
      16: ldc           #12                 // int 65279
      18: if_icmpne     26
      21: aload_1
      22: invokevirtual #13                 // Method readChar:()I
      25: pop
      26: aload_1
      27: areturn

  public static org.apache.jena.atlas.io.PeekReader makeASCII(java.io.InputStream);
    Code:
       0: aload_0
       1: invokestatic  #14                 // Method org/apache/jena/atlas/io/IO.asASCII:(Ljava/io/InputStream;)Ljava/io/Reader;
       4: astore_1
       5: aload_1
       6: invokestatic  #9                  // Method make:(Ljava/io/Reader;)Lorg/apache/jena/atlas/io/PeekReader;
       9: areturn

  public static org.apache.jena.atlas.io.PeekReader make(org.apache.jena.atlas.io.CharStream);
    Code:
       0: new           #2                  // class org/apache/jena/atlas/io/PeekReader
       3: dup
       4: aload_0
       5: invokespecial #7                  // Method "<init>":(Lorg/apache/jena/atlas/io/CharStream;)V
       8: areturn

  public static org.apache.jena.atlas.io.PeekReader readString(java.lang.String);
    Code:
       0: new           #2                  // class org/apache/jena/atlas/io/PeekReader
       3: dup
       4: new           #15                 // class org/apache/jena/atlas/io/CharStreamSequence
       7: dup
       8: aload_0
       9: invokespecial #16                 // Method org/apache/jena/atlas/io/CharStreamSequence."<init>":(Ljava/lang/CharSequence;)V
      12: invokespecial #7                  // Method "<init>":(Lorg/apache/jena/atlas/io/CharStream;)V
      15: areturn

  public static org.apache.jena.atlas.io.PeekReader open(java.lang.String);
    Code:
       0: new           #17                 // class java/io/FileInputStream
       3: dup
       4: aload_0
       5: invokespecial #18                 // Method java/io/FileInputStream."<init>":(Ljava/lang/String;)V
       8: astore_1
       9: aload_1
      10: invokestatic  #19                 // Method makeUTF8:(Ljava/io/InputStream;)Lorg/apache/jena/atlas/io/PeekReader;
      13: areturn
      14: astore_1
      15: new           #21                 // class org/apache/jena/atlas/AtlasException
      18: dup
      19: new           #22                 // class java/lang/StringBuilder
      22: dup
      23: invokespecial #23                 // Method java/lang/StringBuilder."<init>":()V
      26: ldc           #24                 // String File not found:
      28: invokevirtual #25                 // Method java/lang/StringBuilder.append:(Ljava/lang/String;)Ljava/lang/StringBuilder;
      31: aload_0
      32: invokevirtual #25                 // Method java/lang/StringBuilder.append:(Ljava/lang/String;)Ljava/lang/StringBuilder;
      35: invokevirtual #26                 // Method java/lang/StringBuilder.toString:()Ljava/lang/String;
      38: invokespecial #27                 // Method org/apache/jena/atlas/AtlasException."<init>":(Ljava/lang/String;)V
      41: athrow
    Exception table:
       from    to  target type
           0    13    14   Class java/io/FileNotFoundException

  private org.apache.jena.atlas.io.PeekReader(org.apache.jena.atlas.io.CharStream);
    Code:
       0: aload_0
       1: invokespecial #28                 // Method java/io/Reader."<init>":()V
       4: aload_0
       5: bipush        -2
       7: putfield      #29                 // Field currChar:I
      10: aload_0
      11: aload_1
      12: putfield      #30                 // Field source:Lorg/apache/jena/atlas/io/CharStream;
      15: aload_0
      16: bipush        10
      18: newarray       char
      20: putfield      #31                 // Field pushbackChars:[C
      23: aload_0
      24: iconst_m1
      25: putfield      #32                 // Field idxPushback:I
      28: aload_0
      29: lconst_1
      30: putfield      #33                 // Field colNum:J
      33: aload_0
      34: lconst_1
      35: putfield      #34                 // Field lineNum:J
      38: aload_0
      39: lconst_0
      40: putfield      #35                 // Field posn:J
      43: return

  public long getLineNum();
    Code:
       0: aload_0
       1: getfield      #34                 // Field lineNum:J
       4: lreturn

  public long getColNum();
    Code:
       0: aload_0
       1: getfield      #33                 // Field colNum:J
       4: lreturn

  public long getPosition();
    Code:
       0: aload_0
       1: getfield      #35                 // Field posn:J
       4: lreturn

  public final int peekChar();
    Code:
       0: aload_0
       1: getfield      #32                 // Field idxPushback:I
       4: iflt          17
       7: aload_0
       8: getfield      #31                 // Field pushbackChars:[C
      11: aload_0
      12: getfield      #32                 // Field idxPushback:I
      15: caload
      16: ireturn
      17: aload_0
      18: getfield      #29                 // Field currChar:I
      21: bipush        -2
      23: if_icmpne     30
      26: aload_0
      27: invokespecial #36                 // Method init:()V
      30: aload_0
      31: getfield      #29                 // Field currChar:I
      34: ireturn

  private final void setCurrChar(int);
    Code:
       0: aload_0
       1: iload_1
       2: putfield      #29                 // Field currChar:I
       5: return

  public final int readChar();
    Code:
       0: aload_0
       1: invokespecial #37                 // Method nextChar:()I
       4: ireturn

  public final void pushbackChar(int);
    Code:
       0: aload_0
       1: iload_1
       2: invokespecial #38                 // Method unreadChar:(I)V
       5: return

  public final void close() throws java.io.IOException;
    Code:
       0: aload_0
       1: getfield      #30                 // Field source:Lorg/apache/jena/atlas/io/CharStream;
       4: invokeinterface #39,  1           // InterfaceMethod org/apache/jena/atlas/io/CharStream.closeStream:()V
       9: return

  public final int read() throws java.io.IOException;
    Code:
       0: aload_0
       1: invokevirtual #40                 // Method eof:()Z
       4: ifeq          9
       7: iconst_m1
       8: ireturn
       9: aload_0
      10: invokevirtual #13                 // Method readChar:()I
      13: istore_1
      14: iload_1
      15: ireturn

  public final int read(char[], int, int) throws java.io.IOException;
    Code:
       0: aload_0
       1: invokevirtual #40                 // Method eof:()Z
       4: ifeq          9
       7: iconst_m1
       8: ireturn
       9: iconst_0
      10: istore        4
      12: iload         4
      14: iload_3
      15: if_icmpge     57
      18: aload_0
      19: invokevirtual #13                 // Method readChar:()I
      22: istore        5
      24: iload         5
      26: iconst_m1
      27: if_icmpne     42
      30: iload         4
      32: ifne          39
      35: iconst_m1
      36: goto          41
      39: iload         4
      41: ireturn
      42: aload_1
      43: iload         4
      45: iload_2
      46: iadd
      47: iload         5
      49: i2c
      50: castore
      51: iinc          4, 1
      54: goto          12
      57: iload_3
      58: ireturn

  public final boolean eof();
    Code:
       0: aload_0
       1: invokevirtual #10                 // Method peekChar:()I
       4: iconst_m1
       5: if_icmpne     12
       8: iconst_1
       9: goto          13
      12: iconst_0
      13: ireturn

  private final void unreadChar(int);
    Code:
       0: aload_0
       1: getfield      #32                 // Field idxPushback:I
       4: aload_0
       5: getfield      #31                 // Field pushbackChars:[C
       8: arraylength
       9: if_icmplt     42
      12: aload_0
      13: getfield      #31                 // Field pushbackChars:[C
      16: arraylength
      17: iconst_2
      18: imul
      19: newarray       char
      21: astore_2
      22: aload_0
      23: getfield      #31                 // Field pushbackChars:[C
      26: iconst_0
      27: aload_2
      28: iconst_0
      29: aload_0
      30: getfield      #31                 // Field pushbackChars:[C
      33: arraylength
      34: invokestatic  #41                 // Method java/lang/System.arraycopy:(Ljava/lang/Object;ILjava/lang/Object;II)V
      37: aload_0
      38: aload_2
      39: putfield      #31                 // Field pushbackChars:[C
      42: iload_1
      43: iconst_m1
      44: if_icmpeq     53
      47: iload_1
      48: bipush        -2
      50: if_icmpne     75
      53: new           #22                 // class java/lang/StringBuilder
      56: dup
      57: invokespecial #23                 // Method java/lang/StringBuilder."<init>":()V
      60: ldc           #42                 // String Illegal character to push back:
      62: invokevirtual #25                 // Method java/lang/StringBuilder.append:(Ljava/lang/String;)Ljava/lang/StringBuilder;
      65: iload_1
      66: invokevirtual #43                 // Method java/lang/StringBuilder.append:(I)Ljava/lang/StringBuilder;
      69: invokevirtual #26                 // Method java/lang/StringBuilder.toString:()Ljava/lang/String;
      72: invokestatic  #44                 // Method org/apache/jena/atlas/io/IO.exception:(Ljava/lang/String;)V
      75: aload_0
      76: dup
      77: getfield      #32                 // Field idxPushback:I
      80: iconst_1
      81: iadd
      82: putfield      #32                 // Field idxPushback:I
      85: aload_0
      86: getfield      #31                 // Field pushbackChars:[C
      89: aload_0
      90: getfield      #32                 // Field idxPushback:I
      93: iload_1
      94: i2c
      95: castore
      96: return

  private final void init();
    Code:
       0: aload_0
       1: invokespecial #45                 // Method advanceAndSet:()V
       4: aload_0
       5: getfield      #29                 // Field currChar:I
       8: bipush        -2
      10: if_icmpne     18
      13: aload_0
      14: iconst_m1
      15: invokespecial #46                 // Method setCurrChar:(I)V
      18: return

  private final void advanceAndSet();
    Code:
       0: aload_0
       1: getfield      #30                 // Field source:Lorg/apache/jena/atlas/io/CharStream;
       4: invokeinterface #47,  1           // InterfaceMethod org/apache/jena/atlas/io/CharStream.advance:()I
       9: istore_1
      10: aload_0
      11: iload_1
      12: invokespecial #46                 // Method setCurrChar:(I)V
      15: return

  private final int nextChar();
    Code:
       0: aload_0
       1: invokevirtual #10                 // Method peekChar:()I
       4: istore_1
       5: iload_1
       6: iconst_m1
       7: if_icmpne     12
      10: iconst_m1
      11: ireturn
      12: aload_0
      13: getfield      #32                 // Field idxPushback:I
      16: iflt          41
      19: aload_0
      20: getfield      #31                 // Field pushbackChars:[C
      23: aload_0
      24: getfield      #32                 // Field idxPushback:I
      27: caload
      28: istore_2
      29: aload_0
      30: dup
      31: getfield      #32                 // Field idxPushback:I
      34: iconst_1
      35: isub
      36: putfield      #32                 // Field idxPushback:I
      39: iload_2
      40: ireturn
      41: aload_0
      42: dup
      43: getfield      #35                 // Field posn:J
      46: lconst_1
      47: ladd
      48: putfield      #35                 // Field posn:J
      51: iload_1
      52: bipush        10
      54: if_icmpne     75
      57: aload_0
      58: dup
      59: getfield      #34                 // Field lineNum:J
      62: lconst_1
      63: ladd
      64: putfield      #34                 // Field lineNum:J
      67: aload_0
      68: lconst_1
      69: putfield      #33                 // Field colNum:J
      72: goto          85
      75: aload_0
      76: dup
      77: getfield      #33                 // Field colNum:J
      80: lconst_1
      81: ladd
      82: putfield      #33                 // Field colNum:J
      85: aload_0
      86: invokespecial #45                 // Method advanceAndSet:()V
      89: iload_1
      90: ireturn
}
