Compiled from "DialogAPDUType.java"
public final class org.mobicents.protocols.ss7.tcap.asn.DialogAPDUType extends java.lang.Enum<org.mobicents.protocols.ss7.tcap.asn.DialogAPDUType> {
  public static final org.mobicents.protocols.ss7.tcap.asn.DialogAPDUType Request;

  public static final org.mobicents.protocols.ss7.tcap.asn.DialogAPDUType Response;

  public static final org.mobicents.protocols.ss7.tcap.asn.DialogAPDUType Abort;

  public static final org.mobicents.protocols.ss7.tcap.asn.DialogAPDUType UniDirectional;

  private static final org.mobicents.protocols.ss7.tcap.asn.DialogAPDUType[] $VALUES;

  public static org.mobicents.protocols.ss7.tcap.asn.DialogAPDUType[] values();
    Code:
       0: getstatic     #1                  // Field $VALUES:[Lorg/mobicents/protocols/ss7/tcap/asn/DialogAPDUType;
       3: invokevirtual #2                  // Method "[Lorg/mobicents/protocols/ss7/tcap/asn/DialogAPDUType;".clone:()Ljava/lang/Object;
       6: checkcast     #3                  // class "[Lorg/mobicents/protocols/ss7/tcap/asn/DialogAPDUType;"
       9: areturn

  public static org.mobicents.protocols.ss7.tcap.asn.DialogAPDUType valueOf(java.lang.String);
    Code:
       0: ldc_w         #4                  // class org/mobicents/protocols/ss7/tcap/asn/DialogAPDUType
       3: aload_0
       4: invokestatic  #5                  // Method java/lang/Enum.valueOf:(Ljava/lang/Class;Ljava/lang/String;)Ljava/lang/Enum;
       7: checkcast     #4                  // class org/mobicents/protocols/ss7/tcap/asn/DialogAPDUType
      10: areturn

  private org.mobicents.protocols.ss7.tcap.asn.DialogAPDUType();
    Code:
       0: aload_0
       1: aload_1
       2: iload_2
       3: invokespecial #6                  // Method java/lang/Enum."<init>":(Ljava/lang/String;I)V
       6: return

  static {};
    Code:
       0: new           #4                  // class org/mobicents/protocols/ss7/tcap/asn/DialogAPDUType
       3: dup
       4: ldc           #7                  // String Request
       6: iconst_0
       7: invokespecial #8                  // Method "<init>":(Ljava/lang/String;I)V
      10: putstatic     #9                  // Field Request:Lorg/mobicents/protocols/ss7/tcap/asn/DialogAPDUType;
      13: new           #4                  // class org/mobicents/protocols/ss7/tcap/asn/DialogAPDUType
      16: dup
      17: ldc           #10                 // String Response
      19: iconst_1
      20: invokespecial #8                  // Method "<init>":(Ljava/lang/String;I)V
      23: putstatic     #11                 // Field Response:Lorg/mobicents/protocols/ss7/tcap/asn/DialogAPDUType;
      26: new           #4                  // class org/mobicents/protocols/ss7/tcap/asn/DialogAPDUType
      29: dup
      30: ldc           #12                 // String Abort
      32: iconst_2
      33: invokespecial #8                  // Method "<init>":(Ljava/lang/String;I)V
      36: putstatic     #13                 // Field Abort:Lorg/mobicents/protocols/ss7/tcap/asn/DialogAPDUType;
      39: new           #4                  // class org/mobicents/protocols/ss7/tcap/asn/DialogAPDUType
      42: dup
      43: ldc           #14                 // String UniDirectional
      45: iconst_3
      46: invokespecial #8                  // Method "<init>":(Ljava/lang/String;I)V
      49: putstatic     #15                 // Field UniDirectional:Lorg/mobicents/protocols/ss7/tcap/asn/DialogAPDUType;
      52: iconst_4
      53: anewarray     #4                  // class org/mobicents/protocols/ss7/tcap/asn/DialogAPDUType
      56: dup
      57: iconst_0
      58: getstatic     #9                  // Field Request:Lorg/mobicents/protocols/ss7/tcap/asn/DialogAPDUType;
      61: aastore
      62: dup
      63: iconst_1
      64: getstatic     #11                 // Field Response:Lorg/mobicents/protocols/ss7/tcap/asn/DialogAPDUType;
      67: aastore
      68: dup
      69: iconst_2
      70: getstatic     #13                 // Field Abort:Lorg/mobicents/protocols/ss7/tcap/asn/DialogAPDUType;
      73: aastore
      74: dup
      75: iconst_3
      76: getstatic     #15                 // Field UniDirectional:Lorg/mobicents/protocols/ss7/tcap/asn/DialogAPDUType;
      79: aastore
      80: putstatic     #1                  // Field $VALUES:[Lorg/mobicents/protocols/ss7/tcap/asn/DialogAPDUType;
      83: return
}
