Compiled from "WeakHashtable.java"
final class org.apache.htrace.shaded.commons.logging.impl.WeakHashtable$WeakKey extends java.lang.ref.WeakReference {
  private final org.apache.htrace.shaded.commons.logging.impl.WeakHashtable$Referenced referenced;

  private org.apache.htrace.shaded.commons.logging.impl.WeakHashtable$WeakKey(java.lang.Object, java.lang.ref.ReferenceQueue, org.apache.htrace.shaded.commons.logging.impl.WeakHashtable$Referenced);
    Code:
       0: aload_0
       1: aload_1
       2: aload_2
       3: invokespecial #20                 // Method java/lang/ref/WeakReference."<init>":(Ljava/lang/Object;Ljava/lang/ref/ReferenceQueue;)V
       6: aload_0
       7: aload_3
       8: putfield      #22                 // Field referenced:Lorg/apache/htrace/shaded/commons/logging/impl/WeakHashtable$Referenced;
      11: return

  private org.apache.htrace.shaded.commons.logging.impl.WeakHashtable$Referenced getReferenced();
    Code:
       0: aload_0
       1: getfield      #22                 // Field referenced:Lorg/apache/htrace/shaded/commons/logging/impl/WeakHashtable$Referenced;
       4: areturn

  static org.apache.htrace.shaded.commons.logging.impl.WeakHashtable$Referenced access$400(org.apache.htrace.shaded.commons.logging.impl.WeakHashtable$WeakKey);
    Code:
       0: aload_0
       1: invokespecial #34                 // Method getReferenced:()Lorg/apache/htrace/shaded/commons/logging/impl/WeakHashtable$Referenced;
       4: areturn

  org.apache.htrace.shaded.commons.logging.impl.WeakHashtable$WeakKey(java.lang.Object, java.lang.ref.ReferenceQueue, org.apache.htrace.shaded.commons.logging.impl.WeakHashtable$Referenced, org.apache.htrace.shaded.commons.logging.impl.WeakHashtable$1);
    Code:
       0: aload_0
       1: aload_1
       2: aload_2
       3: aload_3
       4: invokespecial #38                 // Method "<init>":(Ljava/lang/Object;Ljava/lang/ref/ReferenceQueue;Lorg/apache/htrace/shaded/commons/logging/impl/WeakHashtable$Referenced;)V
       7: return
}
