Compiled from "RPCBasicMessageListener.java"
public abstract class org.hawkular.bus.common.consumer.RPCBasicMessageListener<T extends org.hawkular.bus.common.BasicMessage, U extends org.hawkular.bus.common.BasicMessage> extends org.hawkular.bus.common.consumer.AbstractBasicMessageListener<T> {
  private final org.hawkular.bus.common.log.MsgLogger msglog;

  private org.hawkular.bus.common.MessageProcessor messageSender;

  public org.hawkular.bus.common.consumer.RPCBasicMessageListener();
    Code:
       0: aload_0
       1: invokespecial #1                  // Method org/hawkular/bus/common/consumer/AbstractBasicMessageListener."<init>":()V
       4: aload_0
       5: getstatic     #2                  // Field org/hawkular/bus/common/log/MsgLogger.LOGGER:Lorg/hawkular/bus/common/log/MsgLogger;
       8: putfield      #3                  // Field msglog:Lorg/hawkular/bus/common/log/MsgLogger;
      11: aload_0
      12: new           #4                  // class org/hawkular/bus/common/MessageProcessor
      15: dup
      16: invokespecial #5                  // Method org/hawkular/bus/common/MessageProcessor."<init>":()V
      19: invokevirtual #6                  // Method setMessageSender:(Lorg/hawkular/bus/common/MessageProcessor;)V
      22: return

  public org.hawkular.bus.common.consumer.RPCBasicMessageListener(org.hawkular.bus.common.MessageProcessor);
    Code:
       0: aload_0
       1: invokespecial #1                  // Method org/hawkular/bus/common/consumer/AbstractBasicMessageListener."<init>":()V
       4: aload_0
       5: getstatic     #2                  // Field org/hawkular/bus/common/log/MsgLogger.LOGGER:Lorg/hawkular/bus/common/log/MsgLogger;
       8: putfield      #3                  // Field msglog:Lorg/hawkular/bus/common/log/MsgLogger;
      11: aload_0
      12: aload_1
      13: invokevirtual #6                  // Method setMessageSender:(Lorg/hawkular/bus/common/MessageProcessor;)V
      16: return

  protected org.hawkular.bus.common.consumer.RPCBasicMessageListener(java.lang.Class<T>);
    Code:
       0: aload_0
       1: aload_1
       2: invokespecial #7                  // Method org/hawkular/bus/common/consumer/AbstractBasicMessageListener."<init>":(Ljava/lang/Class;)V
       5: aload_0
       6: getstatic     #2                  // Field org/hawkular/bus/common/log/MsgLogger.LOGGER:Lorg/hawkular/bus/common/log/MsgLogger;
       9: putfield      #3                  // Field msglog:Lorg/hawkular/bus/common/log/MsgLogger;
      12: aload_0
      13: new           #4                  // class org/hawkular/bus/common/MessageProcessor
      16: dup
      17: invokespecial #5                  // Method org/hawkular/bus/common/MessageProcessor."<init>":()V
      20: invokevirtual #6                  // Method setMessageSender:(Lorg/hawkular/bus/common/MessageProcessor;)V
      23: return

  protected org.hawkular.bus.common.consumer.RPCBasicMessageListener(java.lang.Class<T>, org.hawkular.bus.common.MessageProcessor);
    Code:
       0: aload_0
       1: aload_1
       2: invokespecial #7                  // Method org/hawkular/bus/common/consumer/AbstractBasicMessageListener."<init>":(Ljava/lang/Class;)V
       5: aload_0
       6: getstatic     #2                  // Field org/hawkular/bus/common/log/MsgLogger.LOGGER:Lorg/hawkular/bus/common/log/MsgLogger;
       9: putfield      #3                  // Field msglog:Lorg/hawkular/bus/common/log/MsgLogger;
      12: aload_0
      13: aload_2
      14: invokevirtual #6                  // Method setMessageSender:(Lorg/hawkular/bus/common/MessageProcessor;)V
      17: return

  protected org.hawkular.bus.common.MessageProcessor getMessageSender();
    Code:
       0: aload_0
       1: getfield      #8                  // Field messageSender:Lorg/hawkular/bus/common/MessageProcessor;
       4: areturn

  protected void setMessageSender(org.hawkular.bus.common.MessageProcessor);
    Code:
       0: aload_0
       1: aload_1
       2: putfield      #8                  // Field messageSender:Lorg/hawkular/bus/common/MessageProcessor;
       5: return

  public void onMessage(javax.jms.Message);
    Code:
       0: aload_0
       1: aload_1
       2: invokevirtual #9                  // Method parseMessage:(Ljavax/jms/Message;)Lorg/hawkular/bus/common/BasicMessageWithExtraData;
       5: astore_2
       6: aload_2
       7: ifnonnull     11
      10: return
      11: aload_0
      12: aload_2
      13: invokevirtual #10                 // Method onBasicMessage:(Lorg/hawkular/bus/common/BasicMessageWithExtraData;)Lorg/hawkular/bus/common/BasicMessage;
      16: astore_3
      17: aconst_null
      18: astore        4
      20: aconst_null
      21: astore        5
      23: aload_1
      24: invokeinterface #11,  1           // InterfaceMethod javax/jms/Message.getJMSReplyTo:()Ljavax/jms/Destination;
      29: astore        6
      31: aload         6
      33: ifnull        222
      36: aload_0
      37: invokevirtual #12                 // Method getLog:()Lorg/jboss/logging/Logger;
      40: ldc           #13                 // String RPC client asked to get response sent to [%s]
      42: aload         6
      44: invokevirtual #14                 // Method org/jboss/logging/Logger.debugf:(Ljava/lang/String;Ljava/lang/Object;)V
      47: aload_0
      48: invokevirtual #15                 // Method getMessageSender:()Lorg/hawkular/bus/common/MessageProcessor;
      51: astore        7
      53: aload         7
      55: ifnonnull     96
      58: aload_0
      59: getfield      #3                  // Field msglog:Lorg/hawkular/bus/common/log/MsgLogger;
      62: invokeinterface #16,  1           // InterfaceMethod org/hawkular/bus/common/log/MsgLogger.errorNoMessageSenderInListener:()V
      67: aload         5
      69: ifnull        95
      72: aload         5
      74: invokeinterface #17,  1           // InterfaceMethod javax/jms/MessageProducer.close:()V
      79: goto          95
      82: astore        8
      84: aload_0
      85: getfield      #3                  // Field msglog:Lorg/hawkular/bus/common/log/MsgLogger;
      88: aload         8
      90: invokeinterface #19,  2           // InterfaceMethod org/hawkular/bus/common/log/MsgLogger.errorFailedToCloseResourcesToRPCClient:(Ljava/lang/Throwable;)V
      95: return
      96: aload_0
      97: invokevirtual #20                 // Method getConsumerConnectionContext:()Lorg/hawkular/bus/common/consumer/ConsumerConnectionContext;
     100: astore        4
     102: aload         4
     104: ifnonnull     145
     107: aload_0
     108: getfield      #3                  // Field msglog:Lorg/hawkular/bus/common/log/MsgLogger;
     111: invokeinterface #21,  1           // InterfaceMethod org/hawkular/bus/common/log/MsgLogger.errorNoConnectionContextInListener:()V
     116: aload         5
     118: ifnull        144
     121: aload         5
     123: invokeinterface #17,  1           // InterfaceMethod javax/jms/MessageProducer.close:()V
     128: goto          144
     131: astore        8
     133: aload_0
     134: getfield      #3                  // Field msglog:Lorg/hawkular/bus/common/log/MsgLogger;
     137: aload         8
     139: invokeinterface #19,  2           // InterfaceMethod org/hawkular/bus/common/log/MsgLogger.errorFailedToCloseResourcesToRPCClient:(Ljava/lang/Throwable;)V
     144: return
     145: new           #22                 // class org/hawkular/bus/common/producer/ProducerConnectionContext
     148: dup
     149: invokespecial #23                 // Method org/hawkular/bus/common/producer/ProducerConnectionContext."<init>":()V
     152: astore        8
     154: aload         8
     156: aload         4
     158: invokevirtual #24                 // Method org/hawkular/bus/common/producer/ProducerConnectionContext.copy:(Lorg/hawkular/bus/common/ConnectionContext;)V
     161: aload         8
     163: aload         6
     165: invokevirtual #25                 // Method org/hawkular/bus/common/producer/ProducerConnectionContext.setDestination:(Ljavax/jms/Destination;)V
     168: aload         8
     170: invokevirtual #26                 // Method org/hawkular/bus/common/producer/ProducerConnectionContext.getSession:()Ljavax/jms/Session;
     173: astore        9
     175: aload         9
     177: ifnonnull     192
     180: aload_0
     181: getfield      #3                  // Field msglog:Lorg/hawkular/bus/common/log/MsgLogger;
     184: invokeinterface #27,  1           // InterfaceMethod org/hawkular/bus/common/log/MsgLogger.errorNoSessionInListener:()V
     189: goto          219
     192: aload         9
     194: aload         6
     196: invokeinterface #28,  2           // InterfaceMethod javax/jms/Session.createProducer:(Ljavax/jms/Destination;)Ljavax/jms/MessageProducer;
     201: astore        5
     203: aload         8
     205: aload         5
     207: invokevirtual #29                 // Method org/hawkular/bus/common/producer/ProducerConnectionContext.setMessageProducer:(Ljavax/jms/MessageProducer;)V
     210: aload         7
     212: aload         8
     214: aload_3
     215: invokevirtual #30                 // Method org/hawkular/bus/common/MessageProcessor.send:(Lorg/hawkular/bus/common/producer/ProducerConnectionContext;Lorg/hawkular/bus/common/BasicMessage;)Lorg/hawkular/bus/common/MessageId;
     218: pop
     219: goto          231
     222: aload_0
     223: invokevirtual #12                 // Method getLog:()Lorg/jboss/logging/Logger;
     226: ldc           #31                 // String Sender did not tell us where to reply - will not send any response back
     228: invokevirtual #32                 // Method org/jboss/logging/Logger.debug:(Ljava/lang/Object;)V
     231: aload         5
     233: ifnull        337
     236: aload         5
     238: invokeinterface #17,  1           // InterfaceMethod javax/jms/MessageProducer.close:()V
     243: goto          337
     246: astore        6
     248: aload_0
     249: getfield      #3                  // Field msglog:Lorg/hawkular/bus/common/log/MsgLogger;
     252: aload         6
     254: invokeinterface #19,  2           // InterfaceMethod org/hawkular/bus/common/log/MsgLogger.errorFailedToCloseResourcesToRPCClient:(Ljava/lang/Throwable;)V
     259: goto          337
     262: astore        6
     264: aload_0
     265: getfield      #3                  // Field msglog:Lorg/hawkular/bus/common/log/MsgLogger;
     268: aload         6
     270: invokeinterface #34,  2           // InterfaceMethod org/hawkular/bus/common/log/MsgLogger.errorFailedToSendResponse:(Ljava/lang/Throwable;)V
     275: aload         5
     277: ifnull        303
     280: aload         5
     282: invokeinterface #17,  1           // InterfaceMethod javax/jms/MessageProducer.close:()V
     287: goto          303
     290: astore        7
     292: aload_0
     293: getfield      #3                  // Field msglog:Lorg/hawkular/bus/common/log/MsgLogger;
     296: aload         7
     298: invokeinterface #19,  2           // InterfaceMethod org/hawkular/bus/common/log/MsgLogger.errorFailedToCloseResourcesToRPCClient:(Ljava/lang/Throwable;)V
     303: return
     304: astore        10
     306: aload         5
     308: ifnull        334
     311: aload         5
     313: invokeinterface #17,  1           // InterfaceMethod javax/jms/MessageProducer.close:()V
     318: goto          334
     321: astore        11
     323: aload_0
     324: getfield      #3                  // Field msglog:Lorg/hawkular/bus/common/log/MsgLogger;
     327: aload         11
     329: invokeinterface #19,  2           // InterfaceMethod org/hawkular/bus/common/log/MsgLogger.errorFailedToCloseResourcesToRPCClient:(Ljava/lang/Throwable;)V
     334: aload         10
     336: athrow
     337: return
    Exception table:
       from    to  target type
          72    79    82   Class javax/jms/JMSException
         121   128   131   Class javax/jms/JMSException
         236   243   246   Class javax/jms/JMSException
          23    67   262   Class java/lang/Exception
          96   116   262   Class java/lang/Exception
         145   231   262   Class java/lang/Exception
         280   287   290   Class javax/jms/JMSException
          23    67   304   any
          96   116   304   any
         145   231   304   any
         262   275   304   any
         311   318   321   Class javax/jms/JMSException
         304   306   304   any

  protected U onBasicMessage(org.hawkular.bus.common.BasicMessageWithExtraData<T>);
    Code:
       0: aload_0
       1: aload_1
       2: invokevirtual #35                 // Method org/hawkular/bus/common/BasicMessageWithExtraData.getBasicMessage:()Lorg/hawkular/bus/common/BasicMessage;
       5: invokevirtual #36                 // Method onBasicMessage:(Lorg/hawkular/bus/common/BasicMessage;)Lorg/hawkular/bus/common/BasicMessage;
       8: areturn

  protected U onBasicMessage(T);
    Code:
       0: aconst_null
       1: areturn
}
