Compiled from "OutputStreamOutTransportAdapter.java"
public class org.opensaml.ws.transport.OutputStreamOutTransportAdapter extends org.opensaml.ws.transport.BaseTransport implements org.opensaml.ws.transport.OutTransport {
  private java.io.OutputStream outputStream;

  public org.opensaml.ws.transport.OutputStreamOutTransportAdapter(java.io.OutputStream);
    Code:
       0: aload_0
       1: invokespecial #1                  // Method org/opensaml/ws/transport/BaseTransport."<init>":()V
       4: aload_0
       5: aload_1
       6: putfield      #2                  // Field outputStream:Ljava/io/OutputStream;
       9: return

  public java.io.OutputStream getOutgoingStream();
    Code:
       0: aload_0
       1: getfield      #2                  // Field outputStream:Ljava/io/OutputStream;
       4: areturn

  public void setAttribute(java.lang.String, java.lang.Object);
    Code:
       0: aload_0
       1: aload_1
       2: aload_2
       3: invokespecial #3                  // Method org/opensaml/ws/transport/BaseTransport.setAttribute:(Ljava/lang/String;Ljava/lang/Object;)V
       6: return

  public void setCharacterEncoding(java.lang.String);
    Code:
       0: aload_0
       1: aload_1
       2: invokespecial #4                  // Method org/opensaml/ws/transport/BaseTransport.setCharacterEncoding:(Ljava/lang/String;)V
       5: return
}
