Compiled from "BackendProviderResolver.java"
final class io.tracee.BackendProviderResolver$GetClassLoader implements java.security.PrivilegedAction<java.lang.ClassLoader> {
  private final java.lang.Class<?> clazz;

  private io.tracee.BackendProviderResolver$GetClassLoader(java.lang.Class<?>);
    Code:
       0: aload_0
       1: invokespecial #1                  // Method java/lang/Object."<init>":()V
       4: aload_0
       5: aload_1
       6: putfield      #2                  // Field clazz:Ljava/lang/Class;
       9: return

  public java.lang.ClassLoader run();
    Code:
       0: aload_0
       1: getfield      #2                  // Field clazz:Ljava/lang/Class;
       4: ifnull        15
       7: aload_0
       8: getfield      #2                  // Field clazz:Ljava/lang/Class;
      11: invokevirtual #3                  // Method java/lang/Class.getClassLoader:()Ljava/lang/ClassLoader;
      14: areturn
      15: invokestatic  #4                  // Method java/lang/Thread.currentThread:()Ljava/lang/Thread;
      18: invokevirtual #5                  // Method java/lang/Thread.getContextClassLoader:()Ljava/lang/ClassLoader;
      21: areturn

  public static java.lang.ClassLoader fromContext();
    Code:
       0: new           #6                  // class io/tracee/BackendProviderResolver$GetClassLoader
       3: dup
       4: aconst_null
       5: invokespecial #7                  // Method "<init>":(Ljava/lang/Class;)V
       8: invokestatic  #8                  // Method doPrivileged:(Lio/tracee/BackendProviderResolver$GetClassLoader;)Ljava/lang/ClassLoader;
      11: areturn

  public static java.lang.ClassLoader fromClass(java.lang.Class<?>);
    Code:
       0: aload_0
       1: ifnonnull     14
       4: new           #9                  // class java/lang/IllegalArgumentException
       7: dup
       8: ldc           #10                 // String Class is null
      10: invokespecial #11                 // Method java/lang/IllegalArgumentException."<init>":(Ljava/lang/String;)V
      13: athrow
      14: new           #6                  // class io/tracee/BackendProviderResolver$GetClassLoader
      17: dup
      18: aload_0
      19: invokespecial #7                  // Method "<init>":(Ljava/lang/Class;)V
      22: invokestatic  #8                  // Method doPrivileged:(Lio/tracee/BackendProviderResolver$GetClassLoader;)Ljava/lang/ClassLoader;
      25: areturn

  private static java.lang.ClassLoader doPrivileged(io.tracee.BackendProviderResolver$GetClassLoader);
    Code:
       0: invokestatic  #12                 // Method java/lang/System.getSecurityManager:()Ljava/lang/SecurityManager;
       3: ifnull        14
       6: aload_0
       7: invokestatic  #13                 // Method java/security/AccessController.doPrivileged:(Ljava/security/PrivilegedAction;)Ljava/lang/Object;
      10: checkcast     #14                 // class java/lang/ClassLoader
      13: areturn
      14: aload_0
      15: invokevirtual #15                 // Method run:()Ljava/lang/ClassLoader;
      18: areturn

  public java.lang.Object run();
    Code:
       0: aload_0
       1: invokevirtual #15                 // Method run:()Ljava/lang/ClassLoader;
       4: areturn
}
