Compiled from "TraceeConstants.java"
public final class io.tracee.TraceeConstants {
  public static final java.lang.String TPIC_HEADER;

  public static final java.lang.String SOAP_HEADER_NAMESPACE;

  public static final javax.xml.namespace.QName SOAP_HEADER_QNAME;

  public static final java.lang.String SESSION_ID_KEY;

  public static final java.lang.String INVOCATION_ID_KEY;

  private io.tracee.TraceeConstants();
    Code:
       0: aload_0
       1: invokespecial #1                  // Method java/lang/Object."<init>":()V
       4: return

  static {};
    Code:
       0: new           #2                  // class javax/xml/namespace/QName
       3: dup
       4: ldc           #3                  // String http://tracee.io/tpic/1.0
       6: ldc           #4                  // String TPIC
       8: invokespecial #5                  // Method javax/xml/namespace/QName."<init>":(Ljava/lang/String;Ljava/lang/String;)V
      11: putstatic     #6                  // Field SOAP_HEADER_QNAME:Ljavax/xml/namespace/QName;
      14: return
}
