Compiled from "HttpRequestHandlerRegistry.java"
public class org.apache.http.protocol.HttpRequestHandlerRegistry implements org.apache.http.protocol.HttpRequestHandlerResolver {
  private final org.apache.http.protocol.UriPatternMatcher<org.apache.http.protocol.HttpRequestHandler> matcher;

  public org.apache.http.protocol.HttpRequestHandlerRegistry();
    Code:
       0: aload_0
       1: invokespecial #1                  // Method java/lang/Object."<init>":()V
       4: aload_0
       5: new           #2                  // class org/apache/http/protocol/UriPatternMatcher
       8: dup
       9: invokespecial #3                  // Method org/apache/http/protocol/UriPatternMatcher."<init>":()V
      12: putfield      #4                  // Field matcher:Lorg/apache/http/protocol/UriPatternMatcher;
      15: return

  public void register(java.lang.String, org.apache.http.protocol.HttpRequestHandler);
    Code:
       0: aload_1
       1: ifnonnull     14
       4: new           #5                  // class java/lang/IllegalArgumentException
       7: dup
       8: ldc           #6                  // String URI request pattern may not be null
      10: invokespecial #7                  // Method java/lang/IllegalArgumentException."<init>":(Ljava/lang/String;)V
      13: athrow
      14: aload_2
      15: ifnonnull     28
      18: new           #5                  // class java/lang/IllegalArgumentException
      21: dup
      22: ldc           #8                  // String Request handler may not be null
      24: invokespecial #7                  // Method java/lang/IllegalArgumentException."<init>":(Ljava/lang/String;)V
      27: athrow
      28: aload_0
      29: getfield      #4                  // Field matcher:Lorg/apache/http/protocol/UriPatternMatcher;
      32: aload_1
      33: aload_2
      34: invokevirtual #9                  // Method org/apache/http/protocol/UriPatternMatcher.register:(Ljava/lang/String;Ljava/lang/Object;)V
      37: return

  public void unregister(java.lang.String);
    Code:
       0: aload_0
       1: getfield      #4                  // Field matcher:Lorg/apache/http/protocol/UriPatternMatcher;
       4: aload_1
       5: invokevirtual #10                 // Method org/apache/http/protocol/UriPatternMatcher.unregister:(Ljava/lang/String;)V
       8: return

  public void setHandlers(java.util.Map<java.lang.String, org.apache.http.protocol.HttpRequestHandler>);
    Code:
       0: aload_0
       1: getfield      #4                  // Field matcher:Lorg/apache/http/protocol/UriPatternMatcher;
       4: aload_1
       5: invokevirtual #11                 // Method org/apache/http/protocol/UriPatternMatcher.setObjects:(Ljava/util/Map;)V
       8: return

  public java.util.Map<java.lang.String, org.apache.http.protocol.HttpRequestHandler> getHandlers();
    Code:
       0: aload_0
       1: getfield      #4                  // Field matcher:Lorg/apache/http/protocol/UriPatternMatcher;
       4: invokevirtual #12                 // Method org/apache/http/protocol/UriPatternMatcher.getObjects:()Ljava/util/Map;
       7: areturn

  public org.apache.http.protocol.HttpRequestHandler lookup(java.lang.String);
    Code:
       0: aload_0
       1: getfield      #4                  // Field matcher:Lorg/apache/http/protocol/UriPatternMatcher;
       4: aload_1
       5: invokevirtual #13                 // Method org/apache/http/protocol/UriPatternMatcher.lookup:(Ljava/lang/String;)Ljava/lang/Object;
       8: checkcast     #14                 // class org/apache/http/protocol/HttpRequestHandler
      11: areturn
}
