Compiled from "DatatypeElementFactory.java"
public class org.dom4j.datatype.DatatypeElementFactory extends org.dom4j.DocumentFactory {
  private org.dom4j.QName elementQName;

  private java.util.Map attributeXSDatatypes;

  private java.util.Map childrenXSDatatypes;

  public org.dom4j.datatype.DatatypeElementFactory(org.dom4j.QName);
    Code:
       0: aload_0
       1: invokespecial #1                  // Method org/dom4j/DocumentFactory."<init>":()V
       4: aload_0
       5: new           #2                  // class java/util/HashMap
       8: dup
       9: invokespecial #3                  // Method java/util/HashMap."<init>":()V
      12: putfield      #4                  // Field attributeXSDatatypes:Ljava/util/Map;
      15: aload_0
      16: new           #2                  // class java/util/HashMap
      19: dup
      20: invokespecial #3                  // Method java/util/HashMap."<init>":()V
      23: putfield      #5                  // Field childrenXSDatatypes:Ljava/util/Map;
      26: aload_0
      27: aload_1
      28: putfield      #6                  // Field elementQName:Lorg/dom4j/QName;
      31: return

  public org.dom4j.QName getQName();
    Code:
       0: aload_0
       1: getfield      #6                  // Field elementQName:Lorg/dom4j/QName;
       4: areturn

  public com.sun.msv.datatype.xsd.XSDatatype getAttributeXSDatatype(org.dom4j.QName);
    Code:
       0: aload_0
       1: getfield      #4                  // Field attributeXSDatatypes:Ljava/util/Map;
       4: aload_1
       5: invokeinterface #7,  2            // InterfaceMethod java/util/Map.get:(Ljava/lang/Object;)Ljava/lang/Object;
      10: checkcast     #8                  // class com/sun/msv/datatype/xsd/XSDatatype
      13: areturn

  public void setAttributeXSDatatype(org.dom4j.QName, com.sun.msv.datatype.xsd.XSDatatype);
    Code:
       0: aload_0
       1: getfield      #4                  // Field attributeXSDatatypes:Ljava/util/Map;
       4: aload_1
       5: aload_2
       6: invokeinterface #9,  3            // InterfaceMethod java/util/Map.put:(Ljava/lang/Object;Ljava/lang/Object;)Ljava/lang/Object;
      11: pop
      12: return

  public com.sun.msv.datatype.xsd.XSDatatype getChildElementXSDatatype(org.dom4j.QName);
    Code:
       0: aload_0
       1: getfield      #5                  // Field childrenXSDatatypes:Ljava/util/Map;
       4: aload_1
       5: invokeinterface #7,  2            // InterfaceMethod java/util/Map.get:(Ljava/lang/Object;)Ljava/lang/Object;
      10: checkcast     #8                  // class com/sun/msv/datatype/xsd/XSDatatype
      13: areturn

  public void setChildElementXSDatatype(org.dom4j.QName, com.sun.msv.datatype.xsd.XSDatatype);
    Code:
       0: aload_0
       1: getfield      #5                  // Field childrenXSDatatypes:Ljava/util/Map;
       4: aload_1
       5: aload_2
       6: invokeinterface #9,  3            // InterfaceMethod java/util/Map.put:(Ljava/lang/Object;Ljava/lang/Object;)Ljava/lang/Object;
      11: pop
      12: return

  public org.dom4j.Element createElement(org.dom4j.QName);
    Code:
       0: aload_0
       1: aload_1
       2: invokevirtual #10                 // Method getChildElementXSDatatype:(Lorg/dom4j/QName;)Lcom/sun/msv/datatype/xsd/XSDatatype;
       5: astore_2
       6: aload_2
       7: ifnull        20
      10: new           #11                 // class org/dom4j/datatype/DatatypeElement
      13: dup
      14: aload_1
      15: aload_2
      16: invokespecial #12                 // Method org/dom4j/datatype/DatatypeElement."<init>":(Lorg/dom4j/QName;Lcom/sun/msv/datatype/xsd/XSDatatype;)V
      19: areturn
      20: aload_1
      21: invokevirtual #13                 // Method org/dom4j/QName.getDocumentFactory:()Lorg/dom4j/DocumentFactory;
      24: astore_3
      25: aload_3
      26: instanceof    #14                 // class org/dom4j/datatype/DatatypeElementFactory
      29: ifeq          59
      32: aload_3
      33: checkcast     #14                 // class org/dom4j/datatype/DatatypeElementFactory
      36: astore        4
      38: aload         4
      40: aload_1
      41: invokevirtual #10                 // Method getChildElementXSDatatype:(Lorg/dom4j/QName;)Lcom/sun/msv/datatype/xsd/XSDatatype;
      44: astore_2
      45: aload_2
      46: ifnull        59
      49: new           #11                 // class org/dom4j/datatype/DatatypeElement
      52: dup
      53: aload_1
      54: aload_2
      55: invokespecial #12                 // Method org/dom4j/datatype/DatatypeElement."<init>":(Lorg/dom4j/QName;Lcom/sun/msv/datatype/xsd/XSDatatype;)V
      58: areturn
      59: aload_0
      60: aload_1
      61: invokespecial #15                 // Method org/dom4j/DocumentFactory.createElement:(Lorg/dom4j/QName;)Lorg/dom4j/Element;
      64: areturn

  public org.dom4j.Attribute createAttribute(org.dom4j.Element, org.dom4j.QName, java.lang.String);
    Code:
       0: aload_0
       1: aload_2
       2: invokevirtual #16                 // Method getAttributeXSDatatype:(Lorg/dom4j/QName;)Lcom/sun/msv/datatype/xsd/XSDatatype;
       5: astore        4
       7: aload         4
       9: ifnonnull     20
      12: aload_0
      13: aload_1
      14: aload_2
      15: aload_3
      16: invokespecial #17                 // Method org/dom4j/DocumentFactory.createAttribute:(Lorg/dom4j/Element;Lorg/dom4j/QName;Ljava/lang/String;)Lorg/dom4j/Attribute;
      19: areturn
      20: new           #18                 // class org/dom4j/datatype/DatatypeAttribute
      23: dup
      24: aload_2
      25: aload         4
      27: aload_3
      28: invokespecial #19                 // Method org/dom4j/datatype/DatatypeAttribute."<init>":(Lorg/dom4j/QName;Lcom/sun/msv/datatype/xsd/XSDatatype;Ljava/lang/String;)V
      31: areturn
}
