Compiled from "ComputedColumnInfo.java"
public class info.archinnov.achilles.internals.metamodel.columns.ComputedColumnInfo extends info.archinnov.achilles.internals.metamodel.columns.ColumnInfo {
  public final java.lang.String functionName;

  public final java.lang.String alias;

  public final java.util.List<java.lang.String> functionArgs;

  public final java.lang.Class<?> cqlClass;

  public info.archinnov.achilles.internals.metamodel.columns.ComputedColumnInfo(java.lang.String, java.lang.String, java.util.List<java.lang.String>, java.lang.Class<?>);
    Code:
       0: aload_0
       1: iconst_0
       2: invokespecial #1                  // Method info/archinnov/achilles/internals/metamodel/columns/ColumnInfo."<init>":(Z)V
       5: aload_0
       6: aload_1
       7: putfield      #2                  // Field functionName:Ljava/lang/String;
      10: aload_0
      11: aload_2
      12: putfield      #3                  // Field alias:Ljava/lang/String;
      15: aload_0
      16: aload_3
      17: putfield      #4                  // Field functionArgs:Ljava/util/List;
      20: aload_0
      21: aload         4
      23: putfield      #5                  // Field cqlClass:Ljava/lang/Class;
      26: return

  public java.lang.String toString();
    Code:
       0: new           #6                  // class java/lang/StringBuilder
       3: dup
       4: ldc           #7                  // String ComputedColumnInfo{
       6: invokespecial #8                  // Method java/lang/StringBuilder."<init>":(Ljava/lang/String;)V
       9: astore_1
      10: aload_1
      11: ldc           #9                  // String functionName=\'
      13: invokevirtual #10                 // Method java/lang/StringBuilder.append:(Ljava/lang/String;)Ljava/lang/StringBuilder;
      16: aload_0
      17: getfield      #2                  // Field functionName:Ljava/lang/String;
      20: invokevirtual #10                 // Method java/lang/StringBuilder.append:(Ljava/lang/String;)Ljava/lang/StringBuilder;
      23: bipush        39
      25: invokevirtual #11                 // Method java/lang/StringBuilder.append:(C)Ljava/lang/StringBuilder;
      28: pop
      29: aload_1
      30: ldc           #12                 // String , alias=\'
      32: invokevirtual #10                 // Method java/lang/StringBuilder.append:(Ljava/lang/String;)Ljava/lang/StringBuilder;
      35: aload_0
      36: getfield      #3                  // Field alias:Ljava/lang/String;
      39: invokevirtual #10                 // Method java/lang/StringBuilder.append:(Ljava/lang/String;)Ljava/lang/StringBuilder;
      42: bipush        39
      44: invokevirtual #11                 // Method java/lang/StringBuilder.append:(C)Ljava/lang/StringBuilder;
      47: pop
      48: aload_1
      49: ldc           #13                 // String , functionArgs=
      51: invokevirtual #10                 // Method java/lang/StringBuilder.append:(Ljava/lang/String;)Ljava/lang/StringBuilder;
      54: aload_0
      55: getfield      #4                  // Field functionArgs:Ljava/util/List;
      58: invokevirtual #14                 // Method java/lang/StringBuilder.append:(Ljava/lang/Object;)Ljava/lang/StringBuilder;
      61: pop
      62: aload_1
      63: ldc           #15                 // String , cqlClass=
      65: invokevirtual #10                 // Method java/lang/StringBuilder.append:(Ljava/lang/String;)Ljava/lang/StringBuilder;
      68: aload_0
      69: getfield      #5                  // Field cqlClass:Ljava/lang/Class;
      72: invokevirtual #14                 // Method java/lang/StringBuilder.append:(Ljava/lang/Object;)Ljava/lang/StringBuilder;
      75: pop
      76: aload_1
      77: bipush        125
      79: invokevirtual #11                 // Method java/lang/StringBuilder.append:(C)Ljava/lang/StringBuilder;
      82: pop
      83: aload_1
      84: invokevirtual #16                 // Method java/lang/StringBuilder.toString:()Ljava/lang/String;
      87: areturn
}
