Compiled from "StandaloneSonarLintEngineImpl.java"
public final class org.sonarsource.sonarlint.core.StandaloneSonarLintEngineImpl extends org.sonarsource.sonarlint.core.AbstractSonarLintEngine implements org.sonarsource.sonarlint.core.client.api.standalone.StandaloneSonarLintEngine {
  private final org.sonarsource.sonarlint.core.client.api.standalone.StandaloneGlobalConfiguration globalConfig;

  private final java.util.Collection<org.sonarsource.sonarlint.core.client.api.common.PluginDetails> pluginDetails;

  private final java.util.Map<java.lang.String, org.sonarsource.sonarlint.core.rule.extractor.SonarLintRuleDefinition> allRulesDefinitionsByKey;

  private final org.sonarsource.sonarlint.core.analysis.AnalysisEngine analysisEngine;

  public org.sonarsource.sonarlint.core.StandaloneSonarLintEngineImpl(org.sonarsource.sonarlint.core.client.api.standalone.StandaloneGlobalConfiguration);
    Code:
       0: aload_0
       1: aload_1
       2: invokevirtual #44                 // Method org/sonarsource/sonarlint/core/client/api/standalone/StandaloneGlobalConfiguration.getLogOutput:()Lorg/sonarsource/sonarlint/core/commons/log/ClientLogOutput;
       5: invokespecial #47                 // Method org/sonarsource/sonarlint/core/AbstractSonarLintEngine."<init>":(Lorg/sonarsource/sonarlint/core/commons/log/ClientLogOutput;)V
       8: aload_0
       9: aload_1
      10: putfield      #49                 // Field globalConfig:Lorg/sonarsource/sonarlint/core/client/api/standalone/StandaloneGlobalConfiguration;
      13: aload_0
      14: aconst_null
      15: invokevirtual #52                 // Method setLogging:(Lorg/sonarsource/sonarlint/core/commons/log/ClientLogOutput;)V
      18: aload_0
      19: invokevirtual #56                 // Method createPluginInstancesRepository:()Lorg/sonarsource/sonarlint/core/plugin/commons/PluginInstancesRepository;
      22: astore_2
      23: aload_0
      24: aload_2
      25: invokevirtual #60                 // Method org/sonarsource/sonarlint/core/plugin/commons/PluginInstancesRepository.getPluginCheckResultByKeys:()Ljava/util/Map;
      28: invokeinterface #66,  1           // InterfaceMethod java/util/Map.values:()Ljava/util/Collection;
      33: invokeinterface #72,  1           // InterfaceMethod java/util/Collection.stream:()Ljava/util/stream/Stream;
      38: invokedynamic #91,  0             // InvokeDynamic #0:apply:()Ljava/util/function/Function;
      43: invokeinterface #97,  2           // InterfaceMethod java/util/stream/Stream.map:(Ljava/util/function/Function;)Ljava/util/stream/Stream;
      48: invokestatic  #103                // Method java/util/stream/Collectors.toList:()Ljava/util/stream/Collector;
      51: invokeinterface #107,  2          // InterfaceMethod java/util/stream/Stream.collect:(Ljava/util/stream/Collector;)Ljava/lang/Object;
      56: checkcast     #68                 // class java/util/Collection
      59: putfield      #109                // Field pluginDetails:Ljava/util/Collection;
      62: aload_0
      63: aload_2
      64: aload_1
      65: invokevirtual #113                // Method org/sonarsource/sonarlint/core/client/api/standalone/StandaloneGlobalConfiguration.getEnabledLanguages:()Ljava/util/Set;
      68: iconst_0
      69: invokestatic  #117                // Method loadPluginMetadata:(Lorg/sonarsource/sonarlint/core/plugin/commons/PluginInstancesRepository;Ljava/util/Set;Z)Ljava/util/Map;
      72: putfield      #119                // Field allRulesDefinitionsByKey:Ljava/util/Map;
      75: invokestatic  #123                // Method org/sonarsource/sonarlint/core/analysis/api/AnalysisEngineConfiguration.builder:()Lorg/sonarsource/sonarlint/core/analysis/api/AnalysisEngineConfiguration$Builder;
      78: aload_1
      79: invokevirtual #113                // Method org/sonarsource/sonarlint/core/client/api/standalone/StandaloneGlobalConfiguration.getEnabledLanguages:()Ljava/util/Set;
      82: invokevirtual #127                // Method org/sonarsource/sonarlint/core/analysis/api/AnalysisEngineConfiguration$Builder.addEnabledLanguages:(Ljava/util/Collection;)Lorg/sonarsource/sonarlint/core/analysis/api/AnalysisEngineConfiguration$Builder;
      85: aload_1
      86: invokevirtual #131                // Method org/sonarsource/sonarlint/core/client/api/standalone/StandaloneGlobalConfiguration.getClientPid:()J
      89: invokevirtual #135                // Method org/sonarsource/sonarlint/core/analysis/api/AnalysisEngineConfiguration$Builder.setClientPid:(J)Lorg/sonarsource/sonarlint/core/analysis/api/AnalysisEngineConfiguration$Builder;
      92: aload_1
      93: invokevirtual #138                // Method org/sonarsource/sonarlint/core/client/api/standalone/StandaloneGlobalConfiguration.extraProperties:()Ljava/util/Map;
      96: invokevirtual #142                // Method org/sonarsource/sonarlint/core/analysis/api/AnalysisEngineConfiguration$Builder.setExtraProperties:(Ljava/util/Map;)Lorg/sonarsource/sonarlint/core/analysis/api/AnalysisEngineConfiguration$Builder;
      99: aload_1
     100: invokevirtual #146                // Method org/sonarsource/sonarlint/core/client/api/standalone/StandaloneGlobalConfiguration.getNodeJsPath:()Ljava/nio/file/Path;
     103: invokevirtual #150                // Method org/sonarsource/sonarlint/core/analysis/api/AnalysisEngineConfiguration$Builder.setNodeJs:(Ljava/nio/file/Path;)Lorg/sonarsource/sonarlint/core/analysis/api/AnalysisEngineConfiguration$Builder;
     106: aload_1
     107: invokevirtual #153                // Method org/sonarsource/sonarlint/core/client/api/standalone/StandaloneGlobalConfiguration.getWorkDir:()Ljava/nio/file/Path;
     110: invokevirtual #156                // Method org/sonarsource/sonarlint/core/analysis/api/AnalysisEngineConfiguration$Builder.setWorkDir:(Ljava/nio/file/Path;)Lorg/sonarsource/sonarlint/core/analysis/api/AnalysisEngineConfiguration$Builder;
     113: aload_1
     114: invokevirtual #160                // Method org/sonarsource/sonarlint/core/client/api/standalone/StandaloneGlobalConfiguration.getModulesProvider:()Lorg/sonarsource/sonarlint/core/analysis/api/ClientModulesProvider;
     117: invokevirtual #164                // Method org/sonarsource/sonarlint/core/analysis/api/AnalysisEngineConfiguration$Builder.setModulesProvider:(Lorg/sonarsource/sonarlint/core/analysis/api/ClientModulesProvider;)Lorg/sonarsource/sonarlint/core/analysis/api/AnalysisEngineConfiguration$Builder;
     120: invokevirtual #168                // Method org/sonarsource/sonarlint/core/analysis/api/AnalysisEngineConfiguration$Builder.build:()Lorg/sonarsource/sonarlint/core/analysis/api/AnalysisEngineConfiguration;
     123: astore_3
     124: aload_0
     125: new           #170                // class org/sonarsource/sonarlint/core/analysis/AnalysisEngine
     128: dup
     129: aload_3
     130: aload_2
     131: aload_0
     132: getfield      #174                // Field logOutput:Lorg/sonarsource/sonarlint/core/commons/log/ClientLogOutput;
     135: invokespecial #177                // Method org/sonarsource/sonarlint/core/analysis/AnalysisEngine."<init>":(Lorg/sonarsource/sonarlint/core/analysis/api/AnalysisEngineConfiguration;Lorg/sonarsource/sonarlint/core/plugin/commons/PluginInstancesRepository;Lorg/sonarsource/sonarlint/core/commons/log/ClientLogOutput;)V
     138: putfield      #179                // Field analysisEngine:Lorg/sonarsource/sonarlint/core/analysis/AnalysisEngine;
     141: return

  public org.sonarsource.sonarlint.core.analysis.AnalysisEngine getAnalysisEngine();
    Code:
       0: aload_0
       1: getfield      #179                // Field analysisEngine:Lorg/sonarsource/sonarlint/core/analysis/AnalysisEngine;
       4: areturn

  private org.sonarsource.sonarlint.core.plugin.commons.PluginInstancesRepository createPluginInstancesRepository();
    Code:
       0: new           #9                  // class org/sonarsource/sonarlint/core/plugin/commons/PluginInstancesRepository$Configuration
       3: dup
       4: aload_0
       5: getfield      #49                 // Field globalConfig:Lorg/sonarsource/sonarlint/core/client/api/standalone/StandaloneGlobalConfiguration;
       8: invokevirtual #190                // Method org/sonarsource/sonarlint/core/client/api/standalone/StandaloneGlobalConfiguration.getPluginPaths:()Ljava/util/Set;
      11: aload_0
      12: getfield      #49                 // Field globalConfig:Lorg/sonarsource/sonarlint/core/client/api/standalone/StandaloneGlobalConfiguration;
      15: invokevirtual #113                // Method org/sonarsource/sonarlint/core/client/api/standalone/StandaloneGlobalConfiguration.getEnabledLanguages:()Ljava/util/Set;
      18: aload_0
      19: getfield      #49                 // Field globalConfig:Lorg/sonarsource/sonarlint/core/client/api/standalone/StandaloneGlobalConfiguration;
      22: invokevirtual #194                // Method org/sonarsource/sonarlint/core/client/api/standalone/StandaloneGlobalConfiguration.getNodeJsVersion:()Lorg/sonarsource/sonarlint/core/commons/Version;
      25: invokestatic  #200                // Method java/util/Optional.ofNullable:(Ljava/lang/Object;)Ljava/util/Optional;
      28: invokespecial #203                // Method org/sonarsource/sonarlint/core/plugin/commons/PluginInstancesRepository$Configuration."<init>":(Ljava/util/Set;Ljava/util/Set;Ljava/util/Optional;)V
      31: astore_1
      32: new           #11                 // class org/sonarsource/sonarlint/core/plugin/commons/PluginInstancesRepository
      35: dup
      36: aload_1
      37: invokespecial #206                // Method org/sonarsource/sonarlint/core/plugin/commons/PluginInstancesRepository."<init>":(Lorg/sonarsource/sonarlint/core/plugin/commons/PluginInstancesRepository$Configuration;)V
      40: areturn

  public java.util.Optional<org.sonarsource.sonarlint.core.client.api.standalone.StandaloneRuleDetails> getRuleDetails(java.lang.String);
    Code:
       0: aload_0
       1: getfield      #119                // Field allRulesDefinitionsByKey:Ljava/util/Map;
       4: aload_1
       5: invokeinterface #214,  2          // InterfaceMethod java/util/Map.get:(Ljava/lang/Object;)Ljava/lang/Object;
      10: checkcast     #216                // class org/sonarsource/sonarlint/core/rule/extractor/SonarLintRuleDefinition
      13: invokestatic  #200                // Method java/util/Optional.ofNullable:(Ljava/lang/Object;)Ljava/util/Optional;
      16: invokedynamic #225,  0            // InvokeDynamic #1:apply:()Ljava/util/function/Function;
      21: invokevirtual #228                // Method java/util/Optional.map:(Ljava/util/function/Function;)Ljava/util/Optional;
      24: areturn

  public java.util.Collection<org.sonarsource.sonarlint.core.client.api.standalone.StandaloneRuleDetails> getAllRuleDetails();
    Code:
       0: aload_0
       1: getfield      #119                // Field allRulesDefinitionsByKey:Ljava/util/Map;
       4: invokeinterface #66,  1           // InterfaceMethod java/util/Map.values:()Ljava/util/Collection;
       9: invokeinterface #72,  1           // InterfaceMethod java/util/Collection.stream:()Ljava/util/stream/Stream;
      14: invokedynamic #235,  0            // InvokeDynamic #2:apply:()Ljava/util/function/Function;
      19: invokeinterface #97,  2           // InterfaceMethod java/util/stream/Stream.map:(Ljava/util/function/Function;)Ljava/util/stream/Stream;
      24: invokestatic  #103                // Method java/util/stream/Collectors.toList:()Ljava/util/stream/Collector;
      27: invokeinterface #107,  2          // InterfaceMethod java/util/stream/Stream.collect:(Ljava/util/stream/Collector;)Ljava/lang/Object;
      32: checkcast     #68                 // class java/util/Collection
      35: areturn

  public org.sonarsource.sonarlint.core.analysis.api.AnalysisResults analyze(org.sonarsource.sonarlint.core.client.api.standalone.StandaloneAnalysisConfiguration, org.sonarsource.sonarlint.core.client.api.common.analysis.IssueListener, org.sonarsource.sonarlint.core.commons.log.ClientLogOutput, org.sonarsource.sonarlint.core.commons.progress.ClientProgressMonitor);
    Code:
       0: aload_1
       1: invokestatic  #245                // Method java/util/Objects.requireNonNull:(Ljava/lang/Object;)Ljava/lang/Object;
       4: pop
       5: aload_2
       6: invokestatic  #245                // Method java/util/Objects.requireNonNull:(Ljava/lang/Object;)Ljava/lang/Object;
       9: pop
      10: aload_0
      11: aload_3
      12: invokevirtual #52                 // Method setLogging:(Lorg/sonarsource/sonarlint/core/commons/log/ClientLogOutput;)V
      15: invokestatic  #248                // Method org/sonarsource/sonarlint/core/analysis/api/AnalysisConfiguration.builder:()Lorg/sonarsource/sonarlint/core/analysis/api/AnalysisConfiguration$Builder;
      18: aload_1
      19: invokevirtual #254                // Method org/sonarsource/sonarlint/core/client/api/standalone/StandaloneAnalysisConfiguration.inputFiles:()Ljava/util/List;
      22: invokevirtual #258                // Method org/sonarsource/sonarlint/core/analysis/api/AnalysisConfiguration$Builder.addInputFiles:(Ljava/util/Collection;)Lorg/sonarsource/sonarlint/core/analysis/api/AnalysisConfiguration$Builder;
      25: aload_1
      26: invokevirtual #259                // Method org/sonarsource/sonarlint/core/client/api/standalone/StandaloneAnalysisConfiguration.extraProperties:()Ljava/util/Map;
      29: invokevirtual #263                // Method org/sonarsource/sonarlint/core/analysis/api/AnalysisConfiguration$Builder.putAllExtraProperties:(Ljava/util/Map;)Lorg/sonarsource/sonarlint/core/analysis/api/AnalysisConfiguration$Builder;
      32: aload_0
      33: aload_1
      34: invokevirtual #267                // Method identifyActiveRules:(Lorg/sonarsource/sonarlint/core/client/api/standalone/StandaloneAnalysisConfiguration;)Ljava/util/Collection;
      37: invokevirtual #270                // Method org/sonarsource/sonarlint/core/analysis/api/AnalysisConfiguration$Builder.addActiveRules:(Ljava/util/Collection;)Lorg/sonarsource/sonarlint/core/analysis/api/AnalysisConfiguration$Builder;
      40: aload_1
      41: invokevirtual #273                // Method org/sonarsource/sonarlint/core/client/api/standalone/StandaloneAnalysisConfiguration.baseDir:()Ljava/nio/file/Path;
      44: invokevirtual #277                // Method org/sonarsource/sonarlint/core/analysis/api/AnalysisConfiguration$Builder.setBaseDir:(Ljava/nio/file/Path;)Lorg/sonarsource/sonarlint/core/analysis/api/AnalysisConfiguration$Builder;
      47: invokevirtual #280                // Method org/sonarsource/sonarlint/core/analysis/api/AnalysisConfiguration$Builder.build:()Lorg/sonarsource/sonarlint/core/analysis/api/AnalysisConfiguration;
      50: astore        5
      52: aload_0
      53: getfield      #179                // Field analysisEngine:Lorg/sonarsource/sonarlint/core/analysis/AnalysisEngine;
      56: new           #282                // class org/sonarsource/sonarlint/core/analysis/command/AnalyzeCommand
      59: dup
      60: aload_1
      61: invokevirtual #286                // Method org/sonarsource/sonarlint/core/client/api/standalone/StandaloneAnalysisConfiguration.moduleKey:()Ljava/lang/Object;
      64: aload         5
      66: aload_0
      67: aload_2
      68: invokedynamic #299,  0            // InvokeDynamic #3:accept:(Lorg/sonarsource/sonarlint/core/StandaloneSonarLintEngineImpl;Lorg/sonarsource/sonarlint/core/client/api/common/analysis/IssueListener;)Ljava/util/function/Consumer;
      73: aload_3
      74: invokespecial #302                // Method org/sonarsource/sonarlint/core/analysis/command/AnalyzeCommand."<init>":(Ljava/lang/Object;Lorg/sonarsource/sonarlint/core/analysis/api/AnalysisConfiguration;Ljava/util/function/Consumer;Lorg/sonarsource/sonarlint/core/commons/log/ClientLogOutput;)V
      77: new           #304                // class org/sonarsource/sonarlint/core/commons/progress/ProgressMonitor
      80: dup
      81: aload         4
      83: invokespecial #307                // Method org/sonarsource/sonarlint/core/commons/progress/ProgressMonitor."<init>":(Lorg/sonarsource/sonarlint/core/commons/progress/ClientProgressMonitor;)V
      86: invokevirtual #311                // Method org/sonarsource/sonarlint/core/analysis/AnalysisEngine.post:(Lorg/sonarsource/sonarlint/core/analysis/command/Command;Lorg/sonarsource/sonarlint/core/commons/progress/ProgressMonitor;)Ljava/util/concurrent/CompletableFuture;
      89: invokevirtual #315                // Method java/util/concurrent/CompletableFuture.get:()Ljava/lang/Object;
      92: checkcast     #317                // class org/sonarsource/sonarlint/core/analysis/api/AnalysisResults
      95: astore        6
      97: aload         6
      99: ifnonnull     112
     102: new           #317                // class org/sonarsource/sonarlint/core/analysis/api/AnalysisResults
     105: dup
     106: invokespecial #320                // Method org/sonarsource/sonarlint/core/analysis/api/AnalysisResults."<init>":()V
     109: goto          114
     112: aload         6
     114: areturn
     115: astore        6
     117: aload         6
     119: invokestatic  #332                // Method org/sonarsource/sonarlint/core/client/api/exceptions/SonarLintWrappedException.wrap:(Ljava/lang/Throwable;)Lorg/sonarsource/sonarlint/core/commons/SonarLintException;
     122: athrow
    Exception table:
       from    to  target type
          52   114   115   Class java/lang/Exception

  private java.util.Collection<org.sonarsource.sonarlint.core.analysis.api.ActiveRule> identifyActiveRules(org.sonarsource.sonarlint.core.client.api.standalone.StandaloneAnalysisConfiguration);
    Code:
       0: aload_1
       1: invokevirtual #348                // Method org/sonarsource/sonarlint/core/client/api/standalone/StandaloneAnalysisConfiguration.excludedRules:()Ljava/util/Collection;
       4: invokeinterface #72,  1           // InterfaceMethod java/util/Collection.stream:()Ljava/util/stream/Stream;
       9: invokedynamic #358,  0            // InvokeDynamic #4:apply:()Ljava/util/function/Function;
      14: invokeinterface #97,  2           // InterfaceMethod java/util/stream/Stream.map:(Ljava/util/function/Function;)Ljava/util/stream/Stream;
      19: invokestatic  #361                // Method java/util/stream/Collectors.toSet:()Ljava/util/stream/Collector;
      22: invokeinterface #107,  2          // InterfaceMethod java/util/stream/Stream.collect:(Ljava/util/stream/Collector;)Ljava/lang/Object;
      27: checkcast     #363                // class java/util/Set
      30: astore_2
      31: aload_1
      32: invokevirtual #366                // Method org/sonarsource/sonarlint/core/client/api/standalone/StandaloneAnalysisConfiguration.includedRules:()Ljava/util/Collection;
      35: invokeinterface #72,  1           // InterfaceMethod java/util/Collection.stream:()Ljava/util/stream/Stream;
      40: invokedynamic #358,  0            // InvokeDynamic #4:apply:()Ljava/util/function/Function;
      45: invokeinterface #97,  2           // InterfaceMethod java/util/stream/Stream.map:(Ljava/util/function/Function;)Ljava/util/stream/Stream;
      50: aload_2
      51: invokedynamic #379,  0            // InvokeDynamic #5:test:(Ljava/util/Set;)Ljava/util/function/Predicate;
      56: invokeinterface #383,  2          // InterfaceMethod java/util/stream/Stream.filter:(Ljava/util/function/Predicate;)Ljava/util/stream/Stream;
      61: invokestatic  #361                // Method java/util/stream/Collectors.toSet:()Ljava/util/stream/Collector;
      64: invokeinterface #107,  2          // InterfaceMethod java/util/stream/Stream.collect:(Ljava/util/stream/Collector;)Ljava/lang/Object;
      69: checkcast     #363                // class java/util/Set
      72: astore_3
      73: new           #385                // class java/util/ArrayList
      76: dup
      77: invokespecial #386                // Method java/util/ArrayList."<init>":()V
      80: astore        4
      82: aload         4
      84: aload_0
      85: getfield      #119                // Field allRulesDefinitionsByKey:Ljava/util/Map;
      88: invokeinterface #66,  1           // InterfaceMethod java/util/Map.values:()Ljava/util/Collection;
      93: invokeinterface #72,  1           // InterfaceMethod java/util/Collection.stream:()Ljava/util/stream/Stream;
      98: invokedynamic #396,  0            // InvokeDynamic #6:test:()Ljava/util/function/Predicate;
     103: invokeinterface #383,  2          // InterfaceMethod java/util/stream/Stream.filter:(Ljava/util/function/Predicate;)Ljava/util/stream/Stream;
     108: aload_2
     109: invokestatic  #399                // Method isExcludedByConfiguration:(Ljava/util/Set;)Ljava/util/function/Predicate;
     112: invokeinterface #383,  2          // InterfaceMethod java/util/stream/Stream.filter:(Ljava/util/function/Predicate;)Ljava/util/stream/Stream;
     117: invokestatic  #103                // Method java/util/stream/Collectors.toList:()Ljava/util/stream/Collector;
     120: invokeinterface #107,  2          // InterfaceMethod java/util/stream/Stream.collect:(Ljava/util/stream/Collector;)Ljava/lang/Object;
     125: checkcast     #68                 // class java/util/Collection
     128: invokeinterface #403,  2          // InterfaceMethod java/util/Collection.addAll:(Ljava/util/Collection;)Z
     133: pop
     134: aload         4
     136: aload_0
     137: getfield      #119                // Field allRulesDefinitionsByKey:Ljava/util/Map;
     140: invokeinterface #66,  1           // InterfaceMethod java/util/Map.values:()Ljava/util/Collection;
     145: invokeinterface #72,  1           // InterfaceMethod java/util/Collection.stream:()Ljava/util/stream/Stream;
     150: invokedynamic #408,  0            // InvokeDynamic #7:test:()Ljava/util/function/Predicate;
     155: invokeinterface #383,  2          // InterfaceMethod java/util/stream/Stream.filter:(Ljava/util/function/Predicate;)Ljava/util/stream/Stream;
     160: aload_3
     161: invokestatic  #411                // Method isIncludedByConfiguration:(Ljava/util/Set;)Ljava/util/function/Predicate;
     164: invokeinterface #383,  2          // InterfaceMethod java/util/stream/Stream.filter:(Ljava/util/function/Predicate;)Ljava/util/stream/Stream;
     169: invokestatic  #103                // Method java/util/stream/Collectors.toList:()Ljava/util/stream/Collector;
     172: invokeinterface #107,  2          // InterfaceMethod java/util/stream/Stream.collect:(Ljava/util/stream/Collector;)Ljava/lang/Object;
     177: checkcast     #68                 // class java/util/Collection
     180: invokeinterface #403,  2          // InterfaceMethod java/util/Collection.addAll:(Ljava/util/Collection;)Z
     185: pop
     186: aload         4
     188: invokeinterface #72,  1           // InterfaceMethod java/util/Collection.stream:()Ljava/util/stream/Stream;
     193: aload_1
     194: invokedynamic #421,  0            // InvokeDynamic #8:apply:(Lorg/sonarsource/sonarlint/core/client/api/standalone/StandaloneAnalysisConfiguration;)Ljava/util/function/Function;
     199: invokeinterface #97,  2           // InterfaceMethod java/util/stream/Stream.map:(Ljava/util/function/Function;)Ljava/util/stream/Stream;
     204: invokestatic  #103                // Method java/util/stream/Collectors.toList:()Ljava/util/stream/Collector;
     207: invokeinterface #107,  2          // InterfaceMethod java/util/stream/Stream.collect:(Ljava/util/stream/Collector;)Ljava/lang/Object;
     212: checkcast     #68                 // class java/util/Collection
     215: areturn

  private static java.util.function.Predicate<? super org.sonarsource.sonarlint.core.rule.extractor.SonarLintRuleDefinition> isExcludedByConfiguration(java.util.Set<java.lang.String>);
    Code:
       0: aload_0
       1: invokedynamic #432,  0            // InvokeDynamic #9:test:(Ljava/util/Set;)Ljava/util/function/Predicate;
       6: areturn

  private static java.util.function.Predicate<? super org.sonarsource.sonarlint.core.rule.extractor.SonarLintRuleDefinition> isIncludedByConfiguration(java.util.Set<java.lang.String>);
    Code:
       0: aload_0
       1: invokedynamic #437,  0            // InvokeDynamic #10:test:(Ljava/util/Set;)Ljava/util/function/Predicate;
       6: areturn

  public void stop();
    Code:
       0: aload_0
       1: aconst_null
       2: invokevirtual #52                 // Method setLogging:(Lorg/sonarsource/sonarlint/core/commons/log/ClientLogOutput;)V
       5: aload_0
       6: getfield      #119                // Field allRulesDefinitionsByKey:Ljava/util/Map;
       9: invokeinterface #441,  1          // InterfaceMethod java/util/Map.clear:()V
      14: aload_0
      15: getfield      #179                // Field analysisEngine:Lorg/sonarsource/sonarlint/core/analysis/AnalysisEngine;
      18: invokevirtual #443                // Method org/sonarsource/sonarlint/core/analysis/AnalysisEngine.stop:()V
      21: goto          30
      24: astore_1
      25: aload_1
      26: invokestatic  #332                // Method org/sonarsource/sonarlint/core/client/api/exceptions/SonarLintWrappedException.wrap:(Ljava/lang/Throwable;)Lorg/sonarsource/sonarlint/core/commons/SonarLintException;
      29: athrow
      30: return
    Exception table:
       from    to  target type
           5    21    24   Class java/lang/Exception

  public java.util.Collection<org.sonarsource.sonarlint.core.client.api.common.PluginDetails> getPluginDetails();
    Code:
       0: aload_0
       1: getfield      #109                // Field pluginDetails:Ljava/util/Collection;
       4: areturn

  private static boolean lambda$isIncludedByConfiguration$6(java.util.Set, org.sonarsource.sonarlint.core.rule.extractor.SonarLintRuleDefinition);
    Code:
       0: aload_0
       1: aload_1
       2: invokevirtual #448                // Method org/sonarsource/sonarlint/core/rule/extractor/SonarLintRuleDefinition.getKey:()Ljava/lang/String;
       5: invokeinterface #451,  2          // InterfaceMethod java/util/Set.contains:(Ljava/lang/Object;)Z
      10: ifeq          15
      13: iconst_1
      14: ireturn
      15: aload_1
      16: invokevirtual #454                // Method org/sonarsource/sonarlint/core/rule/extractor/SonarLintRuleDefinition.getDeprecatedKeys:()Ljava/util/Set;
      19: invokeinterface #458,  1          // InterfaceMethod java/util/Set.iterator:()Ljava/util/Iterator;
      24: astore_2
      25: aload_2
      26: invokeinterface #463,  1          // InterfaceMethod java/util/Iterator.hasNext:()Z
      31: ifeq          73
      34: aload_2
      35: invokeinterface #466,  1          // InterfaceMethod java/util/Iterator.next:()Ljava/lang/Object;
      40: checkcast     #468                // class java/lang/String
      43: astore_3
      44: aload_0
      45: aload_3
      46: invokeinterface #451,  2          // InterfaceMethod java/util/Set.contains:(Ljava/lang/Object;)Z
      51: ifeq          70
      54: getstatic     #472                // Field LOG:Lorg/sonarsource/sonarlint/core/commons/log/SonarLintLogger;
      57: ldc_w         #474                // String Rule \'{}\' was included using its deprecated key \'{}\'. Please fix your configuration.
      60: aload_1
      61: invokevirtual #448                // Method org/sonarsource/sonarlint/core/rule/extractor/SonarLintRuleDefinition.getKey:()Ljava/lang/String;
      64: aload_3
      65: invokevirtual #480                // Method org/sonarsource/sonarlint/core/commons/log/SonarLintLogger.warn:(Ljava/lang/String;Ljava/lang/Object;Ljava/lang/Object;)V
      68: iconst_1
      69: ireturn
      70: goto          25
      73: iconst_0
      74: ireturn

  private static boolean lambda$isExcludedByConfiguration$5(java.util.Set, org.sonarsource.sonarlint.core.rule.extractor.SonarLintRuleDefinition);
    Code:
       0: aload_0
       1: aload_1
       2: invokevirtual #448                // Method org/sonarsource/sonarlint/core/rule/extractor/SonarLintRuleDefinition.getKey:()Ljava/lang/String;
       5: invokeinterface #451,  2          // InterfaceMethod java/util/Set.contains:(Ljava/lang/Object;)Z
      10: ifeq          15
      13: iconst_0
      14: ireturn
      15: aload_1
      16: invokevirtual #454                // Method org/sonarsource/sonarlint/core/rule/extractor/SonarLintRuleDefinition.getDeprecatedKeys:()Ljava/util/Set;
      19: invokeinterface #458,  1          // InterfaceMethod java/util/Set.iterator:()Ljava/util/Iterator;
      24: astore_2
      25: aload_2
      26: invokeinterface #463,  1          // InterfaceMethod java/util/Iterator.hasNext:()Z
      31: ifeq          73
      34: aload_2
      35: invokeinterface #466,  1          // InterfaceMethod java/util/Iterator.next:()Ljava/lang/Object;
      40: checkcast     #468                // class java/lang/String
      43: astore_3
      44: aload_0
      45: aload_3
      46: invokeinterface #451,  2          // InterfaceMethod java/util/Set.contains:(Ljava/lang/Object;)Z
      51: ifeq          70
      54: getstatic     #472                // Field LOG:Lorg/sonarsource/sonarlint/core/commons/log/SonarLintLogger;
      57: ldc_w         #485                // String Rule \'{}\' was excluded using its deprecated key \'{}\'. Please fix your configuration.
      60: aload_1
      61: invokevirtual #448                // Method org/sonarsource/sonarlint/core/rule/extractor/SonarLintRuleDefinition.getKey:()Ljava/lang/String;
      64: aload_3
      65: invokevirtual #480                // Method org/sonarsource/sonarlint/core/commons/log/SonarLintLogger.warn:(Ljava/lang/String;Ljava/lang/Object;Ljava/lang/Object;)V
      68: iconst_0
      69: ireturn
      70: goto          25
      73: iconst_1
      74: ireturn

  private static org.sonarsource.sonarlint.core.analysis.api.ActiveRule lambda$identifyActiveRules$4(org.sonarsource.sonarlint.core.client.api.standalone.StandaloneAnalysisConfiguration, org.sonarsource.sonarlint.core.rule.extractor.SonarLintRuleDefinition);
    Code:
       0: new           #487                // class org/sonarsource/sonarlint/core/analysis/api/ActiveRule
       3: dup
       4: aload_1
       5: invokevirtual #448                // Method org/sonarsource/sonarlint/core/rule/extractor/SonarLintRuleDefinition.getKey:()Ljava/lang/String;
       8: aload_1
       9: invokevirtual #491                // Method org/sonarsource/sonarlint/core/rule/extractor/SonarLintRuleDefinition.getLanguage:()Lorg/sonarsource/sonarlint/core/commons/Language;
      12: invokevirtual #496                // Method org/sonarsource/sonarlint/core/commons/Language.getLanguageKey:()Ljava/lang/String;
      15: invokespecial #499                // Method org/sonarsource/sonarlint/core/analysis/api/ActiveRule."<init>":(Ljava/lang/String;Ljava/lang/String;)V
      18: astore_2
      19: new           #501                // class java/util/HashMap
      22: dup
      23: aload_1
      24: invokevirtual #504                // Method org/sonarsource/sonarlint/core/rule/extractor/SonarLintRuleDefinition.getDefaultParams:()Ljava/util/Map;
      27: invokespecial #507                // Method java/util/HashMap."<init>":(Ljava/util/Map;)V
      30: astore_3
      31: aload_0
      32: invokevirtual #510                // Method org/sonarsource/sonarlint/core/client/api/standalone/StandaloneAnalysisConfiguration.ruleParameters:()Ljava/util/Map;
      35: aload_1
      36: invokevirtual #448                // Method org/sonarsource/sonarlint/core/rule/extractor/SonarLintRuleDefinition.getKey:()Ljava/lang/String;
      39: invokestatic  #514                // Method org/sonarsource/sonarlint/core/client/api/common/RuleKey.parse:(Ljava/lang/String;)Lorg/sonarsource/sonarlint/core/client/api/common/RuleKey;
      42: invokeinterface #214,  2          // InterfaceMethod java/util/Map.get:(Ljava/lang/Object;)Ljava/lang/Object;
      47: checkcast     #62                 // class java/util/Map
      50: invokestatic  #200                // Method java/util/Optional.ofNullable:(Ljava/lang/Object;)Ljava/util/Optional;
      53: aload_3
      54: dup
      55: invokestatic  #245                // Method java/util/Objects.requireNonNull:(Ljava/lang/Object;)Ljava/lang/Object;
      58: pop
      59: invokedynamic #522,  0            // InvokeDynamic #11:accept:(Ljava/util/Map;)Ljava/util/function/Consumer;
      64: invokevirtual #526                // Method java/util/Optional.ifPresent:(Ljava/util/function/Consumer;)V
      67: aload_2
      68: aload_3
      69: invokevirtual #529                // Method org/sonarsource/sonarlint/core/analysis/api/ActiveRule.setParams:(Ljava/util/Map;)V
      72: aload_2
      73: areturn

  private static boolean lambda$identifyActiveRules$3(org.sonarsource.sonarlint.core.rule.extractor.SonarLintRuleDefinition);
    Code:
       0: aload_0
       1: invokevirtual #390                // Method org/sonarsource/sonarlint/core/rule/extractor/SonarLintRuleDefinition.isActiveByDefault:()Z
       4: ifne          11
       7: iconst_1
       8: goto          12
      11: iconst_0
      12: ireturn

  private static boolean lambda$identifyActiveRules$2(java.util.Set, java.lang.String);
    Code:
       0: aload_0
       1: aload_1
       2: invokeinterface #451,  2          // InterfaceMethod java/util/Set.contains:(Ljava/lang/Object;)Z
       7: ifne          14
      10: iconst_1
      11: goto          15
      14: iconst_0
      15: ireturn

  private void lambda$analyze$1(org.sonarsource.sonarlint.core.client.api.common.analysis.IssueListener, org.sonarsource.sonarlint.core.analysis.api.Issue);
    Code:
       0: aload_1
       1: new           #536                // class org/sonarsource/sonarlint/core/client/api/common/analysis/DefaultClientIssue
       4: dup
       5: aload_2
       6: aload_0
       7: getfield      #119                // Field allRulesDefinitionsByKey:Ljava/util/Map;
      10: aload_2
      11: invokevirtual #541                // Method org/sonarsource/sonarlint/core/analysis/api/Issue.getRuleKey:()Ljava/lang/String;
      14: invokeinterface #214,  2          // InterfaceMethod java/util/Map.get:(Ljava/lang/Object;)Ljava/lang/Object;
      19: checkcast     #216                // class org/sonarsource/sonarlint/core/rule/extractor/SonarLintRuleDefinition
      22: invokespecial #544                // Method org/sonarsource/sonarlint/core/client/api/common/analysis/DefaultClientIssue."<init>":(Lorg/sonarsource/sonarlint/core/analysis/api/Issue;Lorg/sonarsource/sonarlint/core/rule/extractor/SonarLintRuleDefinition;)V
      25: invokeinterface #548,  2          // InterfaceMethod org/sonarsource/sonarlint/core/client/api/common/analysis/IssueListener.handle:(Lorg/sonarsource/sonarlint/core/client/api/common/analysis/Issue;)V
      30: return

  private static org.sonarsource.sonarlint.core.client.api.common.PluginDetails lambda$new$0(org.sonarsource.sonarlint.core.plugin.commons.loading.PluginRequirementsCheckResult);
    Code:
       0: new           #552                // class org/sonarsource/sonarlint/core/client/api/common/PluginDetails
       3: dup
       4: aload_0
       5: invokevirtual #558                // Method org/sonarsource/sonarlint/core/plugin/commons/loading/PluginRequirementsCheckResult.getPlugin:()Lorg/sonarsource/sonarlint/core/plugin/commons/loading/PluginInfo;
       8: invokevirtual #561                // Method org/sonarsource/sonarlint/core/plugin/commons/loading/PluginInfo.getKey:()Ljava/lang/String;
      11: aload_0
      12: invokevirtual #558                // Method org/sonarsource/sonarlint/core/plugin/commons/loading/PluginRequirementsCheckResult.getPlugin:()Lorg/sonarsource/sonarlint/core/plugin/commons/loading/PluginInfo;
      15: invokevirtual #564                // Method org/sonarsource/sonarlint/core/plugin/commons/loading/PluginInfo.getName:()Ljava/lang/String;
      18: aload_0
      19: invokevirtual #558                // Method org/sonarsource/sonarlint/core/plugin/commons/loading/PluginRequirementsCheckResult.getPlugin:()Lorg/sonarsource/sonarlint/core/plugin/commons/loading/PluginInfo;
      22: invokevirtual #567                // Method org/sonarsource/sonarlint/core/plugin/commons/loading/PluginInfo.getVersion:()Lorg/sonarsource/sonarlint/core/commons/Version;
      25: invokevirtual #570                // Method org/sonarsource/sonarlint/core/commons/Version.toString:()Ljava/lang/String;
      28: aload_0
      29: invokevirtual #574                // Method org/sonarsource/sonarlint/core/plugin/commons/loading/PluginRequirementsCheckResult.getSkipReason:()Ljava/util/Optional;
      32: aconst_null
      33: invokevirtual #577                // Method java/util/Optional.orElse:(Ljava/lang/Object;)Ljava/lang/Object;
      36: checkcast     #579                // class org/sonarsource/sonarlint/core/plugin/commons/SkipReason
      39: invokespecial #582                // Method org/sonarsource/sonarlint/core/client/api/common/PluginDetails."<init>":(Ljava/lang/String;Ljava/lang/String;Ljava/lang/String;Lorg/sonarsource/sonarlint/core/plugin/commons/SkipReason;)V
      42: areturn
}
