Compiled from "BookKeeper.java"
class org.apache.bookkeeper.client.BookKeeper$ListLedgersResultImpl$1 implements java.util.Iterator<java.lang.Long> {
  final org.apache.bookkeeper.client.BookKeeper$ListLedgersResultImpl this$0;

  org.apache.bookkeeper.client.BookKeeper$ListLedgersResultImpl$1(org.apache.bookkeeper.client.BookKeeper$ListLedgersResultImpl);
    Code:
       0: aload_0
       1: aload_1
       2: putfield      #1                  // Field this$0:Lorg/apache/bookkeeper/client/BookKeeper$ListLedgersResultImpl;
       5: aload_0
       6: invokespecial #2                  // Method java/lang/Object."<init>":()V
       9: return

  public boolean hasNext();
    Code:
       0: aload_0
       1: getfield      #1                  // Field this$0:Lorg/apache/bookkeeper/client/BookKeeper$ListLedgersResultImpl;
       4: invokestatic  #3                  // Method org/apache/bookkeeper/client/BookKeeper$ListLedgersResultImpl.access$000:(Lorg/apache/bookkeeper/client/BookKeeper$ListLedgersResultImpl;)Lorg/apache/bookkeeper/client/api/LedgersIterator;
       7: invokeinterface #4,  1            // InterfaceMethod org/apache/bookkeeper/client/api/LedgersIterator.hasNext:()Z
      12: ireturn
      13: astore_1
      14: new           #6                  // class java/lang/RuntimeException
      17: dup
      18: aload_1
      19: invokespecial #7                  // Method java/lang/RuntimeException."<init>":(Ljava/lang/Throwable;)V
      22: athrow
    Exception table:
       from    to  target type
           0    12    13   Class java/io/IOException

  public java.lang.Long next();
    Code:
       0: aload_0
       1: getfield      #1                  // Field this$0:Lorg/apache/bookkeeper/client/BookKeeper$ListLedgersResultImpl;
       4: invokestatic  #3                  // Method org/apache/bookkeeper/client/BookKeeper$ListLedgersResultImpl.access$000:(Lorg/apache/bookkeeper/client/BookKeeper$ListLedgersResultImpl;)Lorg/apache/bookkeeper/client/api/LedgersIterator;
       7: invokeinterface #8,  1            // InterfaceMethod org/apache/bookkeeper/client/api/LedgersIterator.next:()J
      12: invokestatic  #9                  // Method java/lang/Long.valueOf:(J)Ljava/lang/Long;
      15: areturn
      16: astore_1
      17: new           #6                  // class java/lang/RuntimeException
      20: dup
      21: aload_1
      22: invokespecial #7                  // Method java/lang/RuntimeException."<init>":(Ljava/lang/Throwable;)V
      25: athrow
    Exception table:
       from    to  target type
           0    15    16   Class java/io/IOException

  public java.lang.Object next();
    Code:
       0: aload_0
       1: invokevirtual #10                 // Method next:()Ljava/lang/Long;
       4: areturn
}
