Compiled from "LedgerChecker.java"
class org.apache.bookkeeper.client.LedgerChecker$EntryExistsCallback implements org.apache.bookkeeper.proto.BookkeeperInternalCallbacks$ReadEntryCallback {
  java.util.concurrent.atomic.AtomicBoolean entryMayExist;

  final java.util.concurrent.atomic.AtomicInteger numReads;

  final org.apache.bookkeeper.proto.BookkeeperInternalCallbacks$GenericCallback<java.lang.Boolean> cb;

  org.apache.bookkeeper.client.LedgerChecker$EntryExistsCallback(int, org.apache.bookkeeper.proto.BookkeeperInternalCallbacks$GenericCallback<java.lang.Boolean>);
    Code:
       0: aload_0
       1: invokespecial #1                  // Method java/lang/Object."<init>":()V
       4: aload_0
       5: new           #2                  // class java/util/concurrent/atomic/AtomicBoolean
       8: dup
       9: iconst_0
      10: invokespecial #3                  // Method java/util/concurrent/atomic/AtomicBoolean."<init>":(Z)V
      13: putfield      #4                  // Field entryMayExist:Ljava/util/concurrent/atomic/AtomicBoolean;
      16: aload_0
      17: new           #5                  // class java/util/concurrent/atomic/AtomicInteger
      20: dup
      21: iload_1
      22: invokespecial #6                  // Method java/util/concurrent/atomic/AtomicInteger."<init>":(I)V
      25: putfield      #7                  // Field numReads:Ljava/util/concurrent/atomic/AtomicInteger;
      28: aload_0
      29: aload_2
      30: putfield      #8                  // Field cb:Lorg/apache/bookkeeper/proto/BookkeeperInternalCallbacks$GenericCallback;
      33: return

  public void readEntryComplete(int, long, long, io.netty.buffer.ByteBuf, java.lang.Object);
    Code:
       0: bipush        -13
       2: iload_1
       3: if_icmpeq     26
       6: bipush        -7
       8: iload_1
       9: if_icmpeq     26
      12: bipush        -25
      14: iload_1
      15: if_icmpeq     26
      18: aload_0
      19: getfield      #4                  // Field entryMayExist:Ljava/util/concurrent/atomic/AtomicBoolean;
      22: iconst_1
      23: invokevirtual #10                 // Method java/util/concurrent/atomic/AtomicBoolean.set:(Z)V
      26: aload_0
      27: getfield      #7                  // Field numReads:Ljava/util/concurrent/atomic/AtomicInteger;
      30: invokevirtual #11                 // Method java/util/concurrent/atomic/AtomicInteger.decrementAndGet:()I
      33: ifne          56
      36: aload_0
      37: getfield      #8                  // Field cb:Lorg/apache/bookkeeper/proto/BookkeeperInternalCallbacks$GenericCallback;
      40: iload_1
      41: aload_0
      42: getfield      #4                  // Field entryMayExist:Ljava/util/concurrent/atomic/AtomicBoolean;
      45: invokevirtual #12                 // Method java/util/concurrent/atomic/AtomicBoolean.get:()Z
      48: invokestatic  #13                 // Method java/lang/Boolean.valueOf:(Z)Ljava/lang/Boolean;
      51: invokeinterface #14,  3           // InterfaceMethod org/apache/bookkeeper/proto/BookkeeperInternalCallbacks$GenericCallback.operationComplete:(ILjava/lang/Object;)V
      56: return
}
