Compiled from "PendingReadOp.java"
abstract class org.apache.bookkeeper.client.PendingReadOp$LedgerEntryRequest implements org.apache.bookkeeper.client.SpeculativeRequestExecutor,java.lang.AutoCloseable {
  final java.util.concurrent.atomic.AtomicBoolean complete;

  int rc;

  int firstError;

  int numBookiesMissingEntry;

  final java.util.List<org.apache.bookkeeper.net.BookieId> ensemble;

  final org.apache.bookkeeper.client.DistributionSchedule$WriteSet writeSet;

  final org.apache.bookkeeper.client.impl.LedgerEntryImpl entryImpl;

  final long eId;

  final org.apache.bookkeeper.client.PendingReadOp this$0;

  org.apache.bookkeeper.client.PendingReadOp$LedgerEntryRequest(java.util.List<org.apache.bookkeeper.net.BookieId>, long, long);
    Code:
       0: aload_0
       1: aload_1
       2: putfield      #1                  // Field this$0:Lorg/apache/bookkeeper/client/PendingReadOp;
       5: aload_0
       6: invokespecial #2                  // Method java/lang/Object."<init>":()V
       9: aload_0
      10: new           #3                  // class java/util/concurrent/atomic/AtomicBoolean
      13: dup
      14: iconst_0
      15: invokespecial #4                  // Method java/util/concurrent/atomic/AtomicBoolean."<init>":(Z)V
      18: putfield      #5                  // Field complete:Ljava/util/concurrent/atomic/AtomicBoolean;
      21: aload_0
      22: iconst_0
      23: putfield      #7                  // Field rc:I
      26: aload_0
      27: iconst_0
      28: putfield      #8                  // Field firstError:I
      31: aload_0
      32: iconst_0
      33: putfield      #9                  // Field numBookiesMissingEntry:I
      36: aload_0
      37: lload_3
      38: lload         5
      40: invokestatic  #10                 // Method org/apache/bookkeeper/client/impl/LedgerEntryImpl.create:(JJ)Lorg/apache/bookkeeper/client/impl/LedgerEntryImpl;
      43: putfield      #11                 // Field entryImpl:Lorg/apache/bookkeeper/client/impl/LedgerEntryImpl;
      46: aload_0
      47: aload_2
      48: putfield      #12                 // Field ensemble:Ljava/util/List;
      51: aload_0
      52: lload         5
      54: putfield      #13                 // Field eId:J
      57: aload_1
      58: getfield      #14                 // Field org/apache/bookkeeper/client/PendingReadOp.clientCtx:Lorg/apache/bookkeeper/client/ClientContext;
      61: invokeinterface #15,  1           // InterfaceMethod org/apache/bookkeeper/client/ClientContext.getConf:()Lorg/apache/bookkeeper/client/ClientInternalConf;
      66: getfield      #16                 // Field org/apache/bookkeeper/client/ClientInternalConf.enableReorderReadSequence:Z
      69: ifeq          110
      72: aload_0
      73: aload_1
      74: getfield      #14                 // Field org/apache/bookkeeper/client/PendingReadOp.clientCtx:Lorg/apache/bookkeeper/client/ClientContext;
      77: invokeinterface #17,  1           // InterfaceMethod org/apache/bookkeeper/client/ClientContext.getPlacementPolicy:()Lorg/apache/bookkeeper/client/EnsemblePlacementPolicy;
      82: aload_2
      83: aload_1
      84: getfield      #18                 // Field org/apache/bookkeeper/client/PendingReadOp.lh:Lorg/apache/bookkeeper/client/LedgerHandle;
      87: invokevirtual #19                 // Method org/apache/bookkeeper/client/LedgerHandle.getBookiesHealthInfo:()Lorg/apache/bookkeeper/client/BookiesHealthInfo;
      90: aload_1
      91: getfield      #18                 // Field org/apache/bookkeeper/client/PendingReadOp.lh:Lorg/apache/bookkeeper/client/LedgerHandle;
      94: lload         5
      96: invokevirtual #20                 // Method org/apache/bookkeeper/client/LedgerHandle.getWriteSetForReadOperation:(J)Lorg/apache/bookkeeper/client/DistributionSchedule$WriteSet;
      99: invokeinterface #21,  4           // InterfaceMethod org/apache/bookkeeper/client/EnsemblePlacementPolicy.reorderReadSequence:(Ljava/util/List;Lorg/apache/bookkeeper/client/BookiesHealthInfo;Lorg/apache/bookkeeper/client/DistributionSchedule$WriteSet;)Lorg/apache/bookkeeper/client/DistributionSchedule$WriteSet;
     104: putfield      #22                 // Field writeSet:Lorg/apache/bookkeeper/client/DistributionSchedule$WriteSet;
     107: goto          123
     110: aload_0
     111: aload_1
     112: getfield      #18                 // Field org/apache/bookkeeper/client/PendingReadOp.lh:Lorg/apache/bookkeeper/client/LedgerHandle;
     115: lload         5
     117: invokevirtual #20                 // Method org/apache/bookkeeper/client/LedgerHandle.getWriteSetForReadOperation:(J)Lorg/apache/bookkeeper/client/DistributionSchedule$WriteSet;
     120: putfield      #22                 // Field writeSet:Lorg/apache/bookkeeper/client/DistributionSchedule$WriteSet;
     123: return

  public void close();
    Code:
       0: aload_0
       1: getfield      #11                 // Field entryImpl:Lorg/apache/bookkeeper/client/impl/LedgerEntryImpl;
       4: invokevirtual #23                 // Method org/apache/bookkeeper/client/impl/LedgerEntryImpl.close:()V
       7: return

  abstract void read();

  boolean complete(int, org.apache.bookkeeper.net.BookieId, io.netty.buffer.ByteBuf);
    Code:
       0: aload_0
       1: invokevirtual #24                 // Method isComplete:()Z
       4: ifeq          9
       7: iconst_0
       8: ireturn
       9: aload_0
      10: getfield      #1                  // Field this$0:Lorg/apache/bookkeeper/client/PendingReadOp;
      13: getfield      #18                 // Field org/apache/bookkeeper/client/PendingReadOp.lh:Lorg/apache/bookkeeper/client/LedgerHandle;
      16: getfield      #25                 // Field org/apache/bookkeeper/client/LedgerHandle.macManager:Lorg/apache/bookkeeper/proto/checksum/DigestManager;
      19: aload_0
      20: getfield      #13                 // Field eId:J
      23: aload_3
      24: invokevirtual #26                 // Method org/apache/bookkeeper/proto/checksum/DigestManager.verifyDigestAndReturnData:(JLio/netty/buffer/ByteBuf;)Lio/netty/buffer/ByteBuf;
      27: astore        4
      29: goto          68
      32: astore        5
      34: aload_0
      35: getfield      #1                  // Field this$0:Lorg/apache/bookkeeper/client/PendingReadOp;
      38: getfield      #14                 // Field org/apache/bookkeeper/client/PendingReadOp.clientCtx:Lorg/apache/bookkeeper/client/ClientContext;
      41: invokeinterface #28,  1           // InterfaceMethod org/apache/bookkeeper/client/ClientContext.getClientStats:()Lorg/apache/bookkeeper/client/BookKeeperClientStats;
      46: invokeinterface #29,  1           // InterfaceMethod org/apache/bookkeeper/client/BookKeeperClientStats.getReadOpDmCounter:()Lorg/apache/bookkeeper/stats/Counter;
      51: invokeinterface #30,  1           // InterfaceMethod org/apache/bookkeeper/stats/Counter.inc:()V
      56: aload_0
      57: iload_1
      58: aload_2
      59: ldc           #31                 // String Mac mismatch
      61: bipush        -5
      63: invokevirtual #32                 // Method logErrorAndReattemptRead:(ILorg/apache/bookkeeper/net/BookieId;Ljava/lang/String;I)V
      66: iconst_0
      67: ireturn
      68: aload_0
      69: getfield      #5                  // Field complete:Ljava/util/concurrent/atomic/AtomicBoolean;
      72: iconst_1
      73: invokevirtual #33                 // Method java/util/concurrent/atomic/AtomicBoolean.getAndSet:(Z)Z
      76: ifne          117
      79: aload_0
      80: iconst_0
      81: putfield      #7                  // Field rc:I
      84: aload_0
      85: getfield      #11                 // Field entryImpl:Lorg/apache/bookkeeper/client/impl/LedgerEntryImpl;
      88: aload_3
      89: bipush        24
      91: invokevirtual #35                 // Method io/netty/buffer/ByteBuf.getLong:(I)J
      94: invokevirtual #36                 // Method org/apache/bookkeeper/client/impl/LedgerEntryImpl.setLength:(J)V
      97: aload_0
      98: getfield      #11                 // Field entryImpl:Lorg/apache/bookkeeper/client/impl/LedgerEntryImpl;
     101: aload         4
     103: invokevirtual #37                 // Method org/apache/bookkeeper/client/impl/LedgerEntryImpl.setEntryBuf:(Lio/netty/buffer/ByteBuf;)V
     106: aload_0
     107: getfield      #22                 // Field writeSet:Lorg/apache/bookkeeper/client/DistributionSchedule$WriteSet;
     110: invokeinterface #38,  1           // InterfaceMethod org/apache/bookkeeper/client/DistributionSchedule$WriteSet.recycle:()V
     115: iconst_1
     116: ireturn
     117: iconst_0
     118: ireturn
    Exception table:
       from    to  target type
           9    29    32   Class org/apache/bookkeeper/client/BKException$BKDigestMatchException

  boolean fail(int);
    Code:
       0: aload_0
       1: getfield      #5                  // Field complete:Ljava/util/concurrent/atomic/AtomicBoolean;
       4: iconst_0
       5: iconst_1
       6: invokevirtual #39                 // Method java/util/concurrent/atomic/AtomicBoolean.compareAndSet:(ZZ)Z
       9: ifeq          36
      12: aload_0
      13: iload_1
      14: putfield      #7                  // Field rc:I
      17: aload_0
      18: getfield      #1                  // Field this$0:Lorg/apache/bookkeeper/client/PendingReadOp;
      21: iload_1
      22: invokevirtual #40                 // Method org/apache/bookkeeper/client/PendingReadOp.submitCallback:(I)V
      25: aload_0
      26: getfield      #22                 // Field writeSet:Lorg/apache/bookkeeper/client/DistributionSchedule$WriteSet;
      29: invokeinterface #38,  1           // InterfaceMethod org/apache/bookkeeper/client/DistributionSchedule$WriteSet.recycle:()V
      34: iconst_1
      35: ireturn
      36: iconst_0
      37: ireturn

  synchronized void logErrorAndReattemptRead(int, org.apache.bookkeeper.net.BookieId, java.lang.String, int);
    Code:
       0: iconst_0
       1: aload_0
       2: getfield      #8                  // Field firstError:I
       5: if_icmpeq     26
       8: bipush        -13
      10: aload_0
      11: getfield      #8                  // Field firstError:I
      14: if_icmpeq     26
      17: bipush        -7
      19: aload_0
      20: getfield      #8                  // Field firstError:I
      23: if_icmpne     35
      26: aload_0
      27: iload         4
      29: putfield      #8                  // Field firstError:I
      32: goto          64
      35: bipush        -8
      37: aload_0
      38: getfield      #8                  // Field firstError:I
      41: if_icmpne     64
      44: bipush        -13
      46: iload         4
      48: if_icmpeq     64
      51: bipush        -7
      53: iload         4
      55: if_icmpeq     64
      58: aload_0
      59: iload         4
      61: putfield      #8                  // Field firstError:I
      64: bipush        -13
      66: iload         4
      68: if_icmpeq     78
      71: bipush        -7
      73: iload         4
      75: if_icmpne     146
      78: aload_0
      79: dup
      80: getfield      #9                  // Field numBookiesMissingEntry:I
      83: iconst_1
      84: iadd
      85: putfield      #9                  // Field numBookiesMissingEntry:I
      88: invokestatic  #41                 // Method org/apache/bookkeeper/client/PendingReadOp.access$000:()Lorg/slf4j/Logger;
      91: invokeinterface #42,  1           // InterfaceMethod org/slf4j/Logger.isDebugEnabled:()Z
      96: ifeq          205
      99: invokestatic  #41                 // Method org/apache/bookkeeper/client/PendingReadOp.access$000:()Lorg/slf4j/Logger;
     102: ldc           #43                 // String No such entry found on bookie.  L{} E{} bookie: {}
     104: iconst_3
     105: anewarray     #44                 // class java/lang/Object
     108: dup
     109: iconst_0
     110: aload_0
     111: getfield      #1                  // Field this$0:Lorg/apache/bookkeeper/client/PendingReadOp;
     114: getfield      #18                 // Field org/apache/bookkeeper/client/PendingReadOp.lh:Lorg/apache/bookkeeper/client/LedgerHandle;
     117: getfield      #45                 // Field org/apache/bookkeeper/client/LedgerHandle.ledgerId:J
     120: invokestatic  #46                 // Method java/lang/Long.valueOf:(J)Ljava/lang/Long;
     123: aastore
     124: dup
     125: iconst_1
     126: aload_0
     127: getfield      #13                 // Field eId:J
     130: invokestatic  #46                 // Method java/lang/Long.valueOf:(J)Ljava/lang/Long;
     133: aastore
     134: dup
     135: iconst_2
     136: aload_2
     137: aastore
     138: invokeinterface #47,  3           // InterfaceMethod org/slf4j/Logger.debug:(Ljava/lang/String;[Ljava/lang/Object;)V
     143: goto          205
     146: invokestatic  #41                 // Method org/apache/bookkeeper/client/PendingReadOp.access$000:()Lorg/slf4j/Logger;
     149: invokeinterface #48,  1           // InterfaceMethod org/slf4j/Logger.isInfoEnabled:()Z
     154: ifeq          205
     157: invokestatic  #41                 // Method org/apache/bookkeeper/client/PendingReadOp.access$000:()Lorg/slf4j/Logger;
     160: ldc           #49                 // String {} while reading L{} E{} from bookie: {}
     162: iconst_4
     163: anewarray     #44                 // class java/lang/Object
     166: dup
     167: iconst_0
     168: aload_3
     169: aastore
     170: dup
     171: iconst_1
     172: aload_0
     173: getfield      #1                  // Field this$0:Lorg/apache/bookkeeper/client/PendingReadOp;
     176: getfield      #18                 // Field org/apache/bookkeeper/client/PendingReadOp.lh:Lorg/apache/bookkeeper/client/LedgerHandle;
     179: getfield      #45                 // Field org/apache/bookkeeper/client/LedgerHandle.ledgerId:J
     182: invokestatic  #46                 // Method java/lang/Long.valueOf:(J)Ljava/lang/Long;
     185: aastore
     186: dup
     187: iconst_2
     188: aload_0
     189: getfield      #13                 // Field eId:J
     192: invokestatic  #46                 // Method java/lang/Long.valueOf:(J)Ljava/lang/Long;
     195: aastore
     196: dup
     197: iconst_3
     198: aload_2
     199: aastore
     200: invokeinterface #50,  3           // InterfaceMethod org/slf4j/Logger.info:(Ljava/lang/String;[Ljava/lang/Object;)V
     205: aload_0
     206: getfield      #1                  // Field this$0:Lorg/apache/bookkeeper/client/PendingReadOp;
     209: getfield      #18                 // Field org/apache/bookkeeper/client/PendingReadOp.lh:Lorg/apache/bookkeeper/client/LedgerHandle;
     212: iload_1
     213: invokevirtual #51                 // Method org/apache/bookkeeper/client/LedgerHandle.recordReadErrorOnBookie:(I)V
     216: return

  abstract org.apache.bookkeeper.net.BookieId maybeSendSpeculativeRead(java.util.BitSet);

  boolean isComplete();
    Code:
       0: aload_0
       1: getfield      #5                  // Field complete:Ljava/util/concurrent/atomic/AtomicBoolean;
       4: invokevirtual #52                 // Method java/util/concurrent/atomic/AtomicBoolean.get:()Z
       7: ireturn

  int getRc();
    Code:
       0: aload_0
       1: getfield      #7                  // Field rc:I
       4: ireturn

  public java.lang.String toString();
    Code:
       0: ldc           #53                 // String L%d-E%d
       2: iconst_2
       3: anewarray     #44                 // class java/lang/Object
       6: dup
       7: iconst_0
       8: aload_0
       9: getfield      #1                  // Field this$0:Lorg/apache/bookkeeper/client/PendingReadOp;
      12: getfield      #18                 // Field org/apache/bookkeeper/client/PendingReadOp.lh:Lorg/apache/bookkeeper/client/LedgerHandle;
      15: invokevirtual #54                 // Method org/apache/bookkeeper/client/LedgerHandle.getId:()J
      18: invokestatic  #46                 // Method java/lang/Long.valueOf:(J)Ljava/lang/Long;
      21: aastore
      22: dup
      23: iconst_1
      24: aload_0
      25: getfield      #13                 // Field eId:J
      28: invokestatic  #46                 // Method java/lang/Long.valueOf:(J)Ljava/lang/Long;
      31: aastore
      32: invokestatic  #55                 // Method java/lang/String.format:(Ljava/lang/String;[Ljava/lang/Object;)Ljava/lang/String;
      35: areturn

  public com.google.common.util.concurrent.ListenableFuture<java.lang.Boolean> issueSpeculativeRequest();
    Code:
       0: aload_0
       1: getfield      #1                  // Field this$0:Lorg/apache/bookkeeper/client/PendingReadOp;
       4: getfield      #14                 // Field org/apache/bookkeeper/client/PendingReadOp.clientCtx:Lorg/apache/bookkeeper/client/ClientContext;
       7: invokeinterface #56,  1           // InterfaceMethod org/apache/bookkeeper/client/ClientContext.getMainWorkerPool:()Lorg/apache/bookkeeper/common/util/OrderedExecutor;
      12: aload_0
      13: getfield      #1                  // Field this$0:Lorg/apache/bookkeeper/client/PendingReadOp;
      16: getfield      #18                 // Field org/apache/bookkeeper/client/PendingReadOp.lh:Lorg/apache/bookkeeper/client/LedgerHandle;
      19: invokevirtual #54                 // Method org/apache/bookkeeper/client/LedgerHandle.getId:()J
      22: new           #57                 // class org/apache/bookkeeper/client/PendingReadOp$LedgerEntryRequest$1
      25: dup
      26: aload_0
      27: invokespecial #58                 // Method org/apache/bookkeeper/client/PendingReadOp$LedgerEntryRequest$1."<init>":(Lorg/apache/bookkeeper/client/PendingReadOp$LedgerEntryRequest;)V
      30: invokevirtual #59                 // Method org/apache/bookkeeper/common/util/OrderedExecutor.submitOrdered:(JLjava/util/concurrent/Callable;)Lcom/google/common/util/concurrent/ListenableFuture;
      33: areturn
}
