Compiled from "MonitoringPoint.java"
public abstract class org.hortonmachine.hmachine.modules.hydrogeomorphology.adige.core.MonitoringPoint implements java.util.Comparator<org.hortonmachine.hmachine.modules.hydrogeomorphology.adige.core.MonitoringPoint>, org.hortonmachine.hmachine.modules.hydrogeomorphology.adige.core.MonitoringPointsConstants {
  public static final int TYPE_HYDROMETER_DISCHARGE;

  public static final int TYPE_DAM_SCARICO;

  public static final int TYPE_DAM_TURBINATA;

  protected int currentIdentifier;

  protected com.vividsolutions.jts.geom.Coordinate position;

  protected int ID;

  protected org.hortonmachine.hmachine.modules.network.PfafstetterNumber pfafstetterNumber;

  protected java.lang.String name;

  protected java.lang.String description;

  protected int type;

  protected int relatedID;

  protected java.util.Hashtable<java.lang.String, org.hortonmachine.hmachine.modules.hydrogeomorphology.adige.core.MonitoringPoint> pfafRelatedMonitoringPointsTable;

  protected boolean isActive;

  protected double dataTimeInterval;

  protected java.lang.String dataTimeIntervalUnit;

  protected java.lang.String srsCode;

  protected java.lang.String quantityName;

  protected java.lang.String quantityUnit;

  public org.hortonmachine.hmachine.modules.hydrogeomorphology.adige.core.MonitoringPoint();
    Code:
       0: aload_0
       1: invokespecial #1                  // Method java/lang/Object."<init>":()V
       4: aload_0
       5: iconst_m1
       6: putfield      #2                  // Field currentIdentifier:I
       9: aload_0
      10: aconst_null
      11: putfield      #3                  // Field position:Lcom/vividsolutions/jts/geom/Coordinate;
      14: aload_0
      15: iconst_m1
      16: putfield      #4                  // Field ID:I
      19: aload_0
      20: ldc           #5                  // String  -
      22: putfield      #6                  // Field name:Ljava/lang/String;
      25: aload_0
      26: ldc           #5                  // String  -
      28: putfield      #7                  // Field description:Ljava/lang/String;
      31: aload_0
      32: new           #8                  // class java/util/Hashtable
      35: dup
      36: invokespecial #9                  // Method java/util/Hashtable."<init>":()V
      39: putfield      #10                 // Field pfafRelatedMonitoringPointsTable:Ljava/util/Hashtable;
      42: aload_0
      43: iconst_0
      44: putfield      #11                 // Field isActive:Z
      47: aload_0
      48: ldc2_w        #12                 // double -1.0d
      51: putfield      #14                 // Field dataTimeInterval:D
      54: aload_0
      55: ldc           #15                 // String
      57: putfield      #16                 // Field dataTimeIntervalUnit:Ljava/lang/String;
      60: aload_0
      61: ldc           #15                 // String
      63: putfield      #17                 // Field srsCode:Ljava/lang/String;
      66: aload_0
      67: ldc           #15                 // String
      69: putfield      #18                 // Field quantityName:Ljava/lang/String;
      72: aload_0
      73: ldc           #15                 // String
      75: putfield      #19                 // Field quantityUnit:Ljava/lang/String;
      78: return

  public java.lang.String getName();
    Code:
       0: aload_0
       1: getfield      #6                  // Field name:Ljava/lang/String;
       4: areturn

  public java.lang.String getDescription();
    Code:
       0: aload_0
       1: getfield      #7                  // Field description:Ljava/lang/String;
       4: areturn

  public org.hortonmachine.hmachine.modules.network.PfafstetterNumber getPfatstetterNumber();
    Code:
       0: aload_0
       1: getfield      #20                 // Field pfafstetterNumber:Lorg/hortonmachine/hmachine/modules/network/PfafstetterNumber;
       4: areturn

  public int getID();
    Code:
       0: aload_0
       1: getfield      #4                  // Field ID:I
       4: ireturn

  public int getRelatedID();
    Code:
       0: aload_0
       1: getfield      #21                 // Field relatedID:I
       4: ireturn

  public boolean connectIfPossible(org.hortonmachine.hmachine.modules.hydrogeomorphology.adige.core.MonitoringPoint);
    Code:
       0: aload_0
       1: getfield      #4                  // Field ID:I
       4: aload_1
       5: invokevirtual #22                 // Method getRelatedID:()I
       8: if_icmpne     29
      11: aload_0
      12: getfield      #10                 // Field pfafRelatedMonitoringPointsTable:Ljava/util/Hashtable;
      15: aload_1
      16: invokevirtual #23                 // Method getPfatstetterNumber:()Lorg/hortonmachine/hmachine/modules/network/PfafstetterNumber;
      19: invokevirtual #24                 // Method org/hortonmachine/hmachine/modules/network/PfafstetterNumber.toString:()Ljava/lang/String;
      22: aload_1
      23: invokevirtual #25                 // Method java/util/Hashtable.put:(Ljava/lang/Object;Ljava/lang/Object;)Ljava/lang/Object;
      26: pop
      27: iconst_1
      28: ireturn
      29: iconst_0
      30: ireturn

  public org.hortonmachine.hmachine.modules.hydrogeomorphology.adige.core.MonitoringPoint getRelatedMonitoringPoint(java.lang.String);
    Code:
       0: aload_1
       1: ifnull        16
       4: aload_0
       5: getfield      #10                 // Field pfafRelatedMonitoringPointsTable:Ljava/util/Hashtable;
       8: aload_1
       9: invokevirtual #26                 // Method java/util/Hashtable.get:(Ljava/lang/Object;)Ljava/lang/Object;
      12: checkcast     #27                 // class org/hortonmachine/hmachine/modules/hydrogeomorphology/adige/core/MonitoringPoint
      15: areturn
      16: aload_0
      17: getfield      #10                 // Field pfafRelatedMonitoringPointsTable:Ljava/util/Hashtable;
      20: invokevirtual #28                 // Method java/util/Hashtable.keySet:()Ljava/util/Set;
      23: astore_2
      24: aload_2
      25: invokeinterface #29,  1           // InterfaceMethod java/util/Set.iterator:()Ljava/util/Iterator;
      30: astore_3
      31: aload_3
      32: invokeinterface #30,  1           // InterfaceMethod java/util/Iterator.hasNext:()Z
      37: ifeq          64
      40: aload_3
      41: invokeinterface #31,  1           // InterfaceMethod java/util/Iterator.next:()Ljava/lang/Object;
      46: checkcast     #32                 // class java/lang/String
      49: astore        4
      51: aload_0
      52: getfield      #10                 // Field pfafRelatedMonitoringPointsTable:Ljava/util/Hashtable;
      55: aload         4
      57: invokevirtual #26                 // Method java/util/Hashtable.get:(Ljava/lang/Object;)Ljava/lang/Object;
      60: checkcast     #27                 // class org/hortonmachine/hmachine/modules/hydrogeomorphology/adige/core/MonitoringPoint
      63: areturn
      64: aconst_null
      65: areturn

  public int getType();
    Code:
       0: aload_0
       1: getfield      #33                 // Field type:I
       4: ireturn

  public com.vividsolutions.jts.geom.Coordinate getPosition();
    Code:
       0: aload_0
       1: getfield      #3                  // Field position:Lcom/vividsolutions/jts/geom/Coordinate;
       4: areturn

  public boolean isActive();
    Code:
       0: aload_0
       1: getfield      #11                 // Field isActive:Z
       4: ireturn

  public void setActive(boolean);
    Code:
       0: aload_0
       1: iload_1
       2: putfield      #11                 // Field isActive:Z
       5: return

  public abstract void addDateValueRecord(java.util.Date, java.lang.Double, int);

  public abstract void addValueValueRecord(java.lang.Double, java.lang.Double, int);

  public abstract java.lang.Double getDataValueAt(java.util.Date, java.lang.Double, int);

  public int compare(org.hortonmachine.hmachine.modules.hydrogeomorphology.adige.core.MonitoringPoint, org.hortonmachine.hmachine.modules.hydrogeomorphology.adige.core.MonitoringPoint);
    Code:
       0: aload_1
       1: invokevirtual #23                 // Method getPfatstetterNumber:()Lorg/hortonmachine/hmachine/modules/network/PfafstetterNumber;
       4: astore_3
       5: aload_2
       6: invokevirtual #23                 // Method getPfatstetterNumber:()Lorg/hortonmachine/hmachine/modules/network/PfafstetterNumber;
       9: astore        4
      11: aload_3
      12: ifnull        138
      15: aload         4
      17: ifnull        138
      20: aload_1
      21: invokevirtual #23                 // Method getPfatstetterNumber:()Lorg/hortonmachine/hmachine/modules/network/PfafstetterNumber;
      24: invokevirtual #34                 // Method org/hortonmachine/hmachine/modules/network/PfafstetterNumber.getOrdersList:()Ljava/util/List;
      27: astore        5
      29: aload_2
      30: invokevirtual #23                 // Method getPfatstetterNumber:()Lorg/hortonmachine/hmachine/modules/network/PfafstetterNumber;
      33: invokevirtual #34                 // Method org/hortonmachine/hmachine/modules/network/PfafstetterNumber.getOrdersList:()Ljava/util/List;
      36: astore        6
      38: aload         5
      40: invokeinterface #35,  1           // InterfaceMethod java/util/List.size:()I
      45: istore        7
      47: aload         6
      49: invokeinterface #35,  1           // InterfaceMethod java/util/List.size:()I
      54: iload         7
      56: if_icmpge     68
      59: aload         6
      61: invokeinterface #35,  1           // InterfaceMethod java/util/List.size:()I
      66: istore        7
      68: iconst_0
      69: istore        8
      71: iload         8
      73: iload         7
      75: if_icmpge     136
      78: aload         5
      80: iload         8
      82: invokeinterface #36,  2           // InterfaceMethod java/util/List.get:(I)Ljava/lang/Object;
      87: checkcast     #37                 // class java/lang/Integer
      90: invokevirtual #38                 // Method java/lang/Integer.intValue:()I
      93: istore        9
      95: aload         6
      97: iload         8
      99: invokeinterface #36,  2           // InterfaceMethod java/util/List.get:(I)Ljava/lang/Object;
     104: checkcast     #37                 // class java/lang/Integer
     107: invokevirtual #38                 // Method java/lang/Integer.intValue:()I
     110: istore        10
     112: iload         9
     114: iload         10
     116: if_icmple     121
     119: iconst_m1
     120: ireturn
     121: iload         9
     123: iload         10
     125: if_icmpge     130
     128: iconst_1
     129: ireturn
     130: iinc          8, 1
     133: goto          71
     136: iconst_0
     137: ireturn
     138: aload_3
     139: ifnonnull     170
     142: getstatic     #39                 // Field java/lang/System.out:Ljava/io/PrintStream;
     145: new           #40                 // class java/lang/StringBuilder
     148: dup
     149: invokespecial #41                 // Method java/lang/StringBuilder."<init>":()V
     152: ldc           #42                 // String Pstaett null  for
     154: invokevirtual #43                 // Method java/lang/StringBuilder.append:(Ljava/lang/String;)Ljava/lang/StringBuilder;
     157: aload_1
     158: invokevirtual #44                 // Method getName:()Ljava/lang/String;
     161: invokevirtual #43                 // Method java/lang/StringBuilder.append:(Ljava/lang/String;)Ljava/lang/StringBuilder;
     164: invokevirtual #45                 // Method java/lang/StringBuilder.toString:()Ljava/lang/String;
     167: invokevirtual #46                 // Method java/io/PrintStream.println:(Ljava/lang/String;)V
     170: aload         4
     172: ifnonnull     203
     175: getstatic     #39                 // Field java/lang/System.out:Ljava/io/PrintStream;
     178: new           #40                 // class java/lang/StringBuilder
     181: dup
     182: invokespecial #41                 // Method java/lang/StringBuilder."<init>":()V
     185: ldc           #42                 // String Pstaett null  for
     187: invokevirtual #43                 // Method java/lang/StringBuilder.append:(Ljava/lang/String;)Ljava/lang/StringBuilder;
     190: aload_2
     191: invokevirtual #44                 // Method getName:()Ljava/lang/String;
     194: invokevirtual #43                 // Method java/lang/StringBuilder.append:(Ljava/lang/String;)Ljava/lang/StringBuilder;
     197: invokevirtual #45                 // Method java/lang/StringBuilder.toString:()Ljava/lang/String;
     200: invokevirtual #46                 // Method java/io/PrintStream.println:(Ljava/lang/String;)V
     203: bipush        -2
     205: ireturn

  public org.geotools.data.simple.SimpleFeatureCollection toFeatureCollection(java.util.List<org.hortonmachine.hmachine.modules.hydrogeomorphology.adige.core.MonitoringPoint>);
    Code:
       0: new           #47                 // class org/geotools/feature/simple/SimpleFeatureTypeBuilder
       3: dup
       4: invokespecial #48                 // Method org/geotools/feature/simple/SimpleFeatureTypeBuilder."<init>":()V
       7: astore_2
       8: aload_2
       9: ldc           #49                 // String monitoringpoints
      11: invokevirtual #50                 // Method org/geotools/feature/simple/SimpleFeatureTypeBuilder.setName:(Ljava/lang/String;)V
      14: aload_2
      15: ldc           #51                 // String the_geom
      17: ldc           #52                 // class com/vividsolutions/jts/geom/Point
      19: invokevirtual #53                 // Method org/geotools/feature/simple/SimpleFeatureTypeBuilder.add:(Ljava/lang/String;Ljava/lang/Class;)V
      22: aload_2
      23: ldc           #54                 // String id
      25: ldc           #37                 // class java/lang/Integer
      27: invokevirtual #53                 // Method org/geotools/feature/simple/SimpleFeatureTypeBuilder.add:(Ljava/lang/String;Ljava/lang/Class;)V
      30: aload_2
      31: ldc           #55                 // String relatedid
      33: ldc           #37                 // class java/lang/Integer
      35: invokevirtual #53                 // Method org/geotools/feature/simple/SimpleFeatureTypeBuilder.add:(Ljava/lang/String;Ljava/lang/Class;)V
      38: aload_2
      39: ldc           #56                 // String pfaf
      41: ldc           #32                 // class java/lang/String
      43: invokevirtual #53                 // Method org/geotools/feature/simple/SimpleFeatureTypeBuilder.add:(Ljava/lang/String;Ljava/lang/Class;)V
      46: aload_2
      47: invokevirtual #57                 // Method org/geotools/feature/simple/SimpleFeatureTypeBuilder.buildFeatureType:()Lorg/opengis/feature/simple/SimpleFeatureType;
      50: astore_3
      51: new           #58                 // class org/geotools/feature/simple/SimpleFeatureBuilder
      54: dup
      55: aload_3
      56: invokespecial #59                 // Method org/geotools/feature/simple/SimpleFeatureBuilder."<init>":(Lorg/opengis/feature/simple/SimpleFeatureType;)V
      59: astore        4
      61: new           #60                 // class com/vividsolutions/jts/geom/GeometryFactory
      64: dup
      65: invokespecial #61                 // Method com/vividsolutions/jts/geom/GeometryFactory."<init>":()V
      68: astore        5
      70: new           #62                 // class org/geotools/feature/DefaultFeatureCollection
      73: dup
      74: invokespecial #63                 // Method org/geotools/feature/DefaultFeatureCollection."<init>":()V
      77: astore        6
      79: iconst_0
      80: istore        7
      82: iload         7
      84: aload_1
      85: invokeinterface #35,  1           // InterfaceMethod java/util/List.size:()I
      90: if_icmpge     224
      93: aload_1
      94: aload_1
      95: invokeinterface #35,  1           // InterfaceMethod java/util/List.size:()I
     100: iload         7
     102: isub
     103: iconst_1
     104: isub
     105: invokeinterface #36,  2           // InterfaceMethod java/util/List.get:(I)Ljava/lang/Object;
     110: checkcast     #27                 // class org/hortonmachine/hmachine/modules/hydrogeomorphology/adige/core/MonitoringPoint
     113: astore        8
     115: iconst_4
     116: anewarray     #64                 // class java/lang/Object
     119: dup
     120: iconst_0
     121: aload         5
     123: aload         8
     125: invokevirtual #65                 // Method getPosition:()Lcom/vividsolutions/jts/geom/Coordinate;
     128: invokevirtual #66                 // Method com/vividsolutions/jts/geom/GeometryFactory.createPoint:(Lcom/vividsolutions/jts/geom/Coordinate;)Lcom/vividsolutions/jts/geom/Point;
     131: aastore
     132: dup
     133: iconst_1
     134: aload         8
     136: invokevirtual #67                 // Method getID:()I
     139: invokestatic  #68                 // Method java/lang/Integer.valueOf:(I)Ljava/lang/Integer;
     142: aastore
     143: dup
     144: iconst_2
     145: aload         8
     147: invokevirtual #22                 // Method getRelatedID:()I
     150: invokestatic  #68                 // Method java/lang/Integer.valueOf:(I)Ljava/lang/Integer;
     153: aastore
     154: dup
     155: iconst_3
     156: aload         8
     158: invokevirtual #23                 // Method getPfatstetterNumber:()Lorg/hortonmachine/hmachine/modules/network/PfafstetterNumber;
     161: invokevirtual #24                 // Method org/hortonmachine/hmachine/modules/network/PfafstetterNumber.toString:()Ljava/lang/String;
     164: aastore
     165: astore        9
     167: aload         4
     169: aload         9
     171: invokevirtual #69                 // Method org/geotools/feature/simple/SimpleFeatureBuilder.addAll:([Ljava/lang/Object;)V
     174: aload         4
     176: new           #40                 // class java/lang/StringBuilder
     179: dup
     180: invokespecial #41                 // Method java/lang/StringBuilder."<init>":()V
     183: aload_3
     184: invokeinterface #70,  1           // InterfaceMethod org/opengis/feature/simple/SimpleFeatureType.getTypeName:()Ljava/lang/String;
     189: invokevirtual #43                 // Method java/lang/StringBuilder.append:(Ljava/lang/String;)Ljava/lang/StringBuilder;
     192: ldc           #71                 // String .
     194: invokevirtual #43                 // Method java/lang/StringBuilder.append:(Ljava/lang/String;)Ljava/lang/StringBuilder;
     197: iload         7
     199: invokevirtual #72                 // Method java/lang/StringBuilder.append:(I)Ljava/lang/StringBuilder;
     202: invokevirtual #45                 // Method java/lang/StringBuilder.toString:()Ljava/lang/String;
     205: invokevirtual #73                 // Method org/geotools/feature/simple/SimpleFeatureBuilder.buildFeature:(Ljava/lang/String;)Lorg/opengis/feature/simple/SimpleFeature;
     208: astore        10
     210: aload         6
     212: aload         10
     214: invokevirtual #74                 // Method org/geotools/feature/DefaultFeatureCollection.add:(Lorg/opengis/feature/simple/SimpleFeature;)Z
     217: pop
     218: iinc          7, 1
     221: goto          82
     224: aload         6
     226: areturn

  public int compare(java.lang.Object, java.lang.Object);
    Code:
       0: aload_0
       1: aload_1
       2: checkcast     #27                 // class org/hortonmachine/hmachine/modules/hydrogeomorphology/adige/core/MonitoringPoint
       5: aload_2
       6: checkcast     #27                 // class org/hortonmachine/hmachine/modules/hydrogeomorphology/adige/core/MonitoringPoint
       9: invokevirtual #75                 // Method compare:(Lorg/hortonmachine/hmachine/modules/hydrogeomorphology/adige/core/MonitoringPoint;Lorg/hortonmachine/hmachine/modules/hydrogeomorphology/adige/core/MonitoringPoint;)I
      12: ireturn
}
