Compiled from "Socks5ClientEncoder.java"
public class io.netty.handler.codec.socksx.v5.Socks5ClientEncoder extends io.netty.handler.codec.MessageToByteEncoder<io.netty.handler.codec.socksx.v5.Socks5Message> {
  public static final io.netty.handler.codec.socksx.v5.Socks5ClientEncoder DEFAULT;

  private final io.netty.handler.codec.socksx.v5.Socks5AddressEncoder addressEncoder;

  protected io.netty.handler.codec.socksx.v5.Socks5ClientEncoder();
    Code:
       0: aload_0
       1: getstatic     #1                  // Field io/netty/handler/codec/socksx/v5/Socks5AddressEncoder.DEFAULT:Lio/netty/handler/codec/socksx/v5/Socks5AddressEncoder;
       4: invokespecial #2                  // Method "<init>":(Lio/netty/handler/codec/socksx/v5/Socks5AddressEncoder;)V
       7: return

  public io.netty.handler.codec.socksx.v5.Socks5ClientEncoder(io.netty.handler.codec.socksx.v5.Socks5AddressEncoder);
    Code:
       0: aload_0
       1: invokespecial #3                  // Method io/netty/handler/codec/MessageToByteEncoder."<init>":()V
       4: aload_1
       5: ifnonnull     18
       8: new           #4                  // class java/lang/NullPointerException
      11: dup
      12: ldc           #5                  // String addressEncoder
      14: invokespecial #6                  // Method java/lang/NullPointerException."<init>":(Ljava/lang/String;)V
      17: athrow
      18: aload_0
      19: aload_1
      20: putfield      #7                  // Field addressEncoder:Lio/netty/handler/codec/socksx/v5/Socks5AddressEncoder;
      23: return

  protected final io.netty.handler.codec.socksx.v5.Socks5AddressEncoder addressEncoder();
    Code:
       0: aload_0
       1: getfield      #7                  // Field addressEncoder:Lio/netty/handler/codec/socksx/v5/Socks5AddressEncoder;
       4: areturn

  protected void encode(io.netty.channel.ChannelHandlerContext, io.netty.handler.codec.socksx.v5.Socks5Message, io.netty.buffer.ByteBuf) throws java.lang.Exception;
    Code:
       0: aload_2
       1: instanceof    #8                  // class io/netty/handler/codec/socksx/v5/Socks5InitialRequest
       4: ifeq          18
       7: aload_2
       8: checkcast     #8                  // class io/netty/handler/codec/socksx/v5/Socks5InitialRequest
      11: aload_3
      12: invokestatic  #9                  // Method encodeAuthMethodRequest:(Lio/netty/handler/codec/socksx/v5/Socks5InitialRequest;Lio/netty/buffer/ByteBuf;)V
      15: goto          85
      18: aload_2
      19: instanceof    #10                 // class io/netty/handler/codec/socksx/v5/Socks5PasswordAuthRequest
      22: ifeq          36
      25: aload_2
      26: checkcast     #10                 // class io/netty/handler/codec/socksx/v5/Socks5PasswordAuthRequest
      29: aload_3
      30: invokestatic  #11                 // Method encodePasswordAuthRequest:(Lio/netty/handler/codec/socksx/v5/Socks5PasswordAuthRequest;Lio/netty/buffer/ByteBuf;)V
      33: goto          85
      36: aload_2
      37: instanceof    #12                 // class io/netty/handler/codec/socksx/v5/Socks5CommandRequest
      40: ifeq          55
      43: aload_0
      44: aload_2
      45: checkcast     #12                 // class io/netty/handler/codec/socksx/v5/Socks5CommandRequest
      48: aload_3
      49: invokespecial #13                 // Method encodeCommandRequest:(Lio/netty/handler/codec/socksx/v5/Socks5CommandRequest;Lio/netty/buffer/ByteBuf;)V
      52: goto          85
      55: new           #14                 // class io/netty/handler/codec/EncoderException
      58: dup
      59: new           #15                 // class java/lang/StringBuilder
      62: dup
      63: invokespecial #16                 // Method java/lang/StringBuilder."<init>":()V
      66: ldc           #17                 // String unsupported message type:
      68: invokevirtual #18                 // Method java/lang/StringBuilder.append:(Ljava/lang/String;)Ljava/lang/StringBuilder;
      71: aload_2
      72: invokestatic  #19                 // Method io/netty/util/internal/StringUtil.simpleClassName:(Ljava/lang/Object;)Ljava/lang/String;
      75: invokevirtual #18                 // Method java/lang/StringBuilder.append:(Ljava/lang/String;)Ljava/lang/StringBuilder;
      78: invokevirtual #20                 // Method java/lang/StringBuilder.toString:()Ljava/lang/String;
      81: invokespecial #21                 // Method io/netty/handler/codec/EncoderException."<init>":(Ljava/lang/String;)V
      84: athrow
      85: return

  private static void encodeAuthMethodRequest(io.netty.handler.codec.socksx.v5.Socks5InitialRequest, io.netty.buffer.ByteBuf);
    Code:
       0: aload_1
       1: aload_0
       2: invokeinterface #22,  1           // InterfaceMethod io/netty/handler/codec/socksx/v5/Socks5InitialRequest.version:()Lio/netty/handler/codec/socksx/SocksVersion;
       7: invokevirtual #23                 // Method io/netty/handler/codec/socksx/SocksVersion.byteValue:()B
      10: invokevirtual #24                 // Method io/netty/buffer/ByteBuf.writeByte:(I)Lio/netty/buffer/ByteBuf;
      13: pop
      14: aload_0
      15: invokeinterface #25,  1           // InterfaceMethod io/netty/handler/codec/socksx/v5/Socks5InitialRequest.authMethods:()Ljava/util/List;
      20: astore_2
      21: aload_2
      22: invokeinterface #26,  1           // InterfaceMethod java/util/List.size:()I
      27: istore_3
      28: aload_1
      29: iload_3
      30: invokevirtual #24                 // Method io/netty/buffer/ByteBuf.writeByte:(I)Lio/netty/buffer/ByteBuf;
      33: pop
      34: aload_2
      35: instanceof    #27                 // class java/util/RandomAccess
      38: ifeq          78
      41: iconst_0
      42: istore        4
      44: iload         4
      46: iload_3
      47: if_icmpge     75
      50: aload_1
      51: aload_2
      52: iload         4
      54: invokeinterface #28,  2           // InterfaceMethod java/util/List.get:(I)Ljava/lang/Object;
      59: checkcast     #29                 // class io/netty/handler/codec/socksx/v5/Socks5AuthMethod
      62: invokevirtual #30                 // Method io/netty/handler/codec/socksx/v5/Socks5AuthMethod.byteValue:()B
      65: invokevirtual #24                 // Method io/netty/buffer/ByteBuf.writeByte:(I)Lio/netty/buffer/ByteBuf;
      68: pop
      69: iinc          4, 1
      72: goto          44
      75: goto          121
      78: aload_2
      79: invokeinterface #31,  1           // InterfaceMethod java/util/List.iterator:()Ljava/util/Iterator;
      84: astore        4
      86: aload         4
      88: invokeinterface #32,  1           // InterfaceMethod java/util/Iterator.hasNext:()Z
      93: ifeq          121
      96: aload         4
      98: invokeinterface #33,  1           // InterfaceMethod java/util/Iterator.next:()Ljava/lang/Object;
     103: checkcast     #29                 // class io/netty/handler/codec/socksx/v5/Socks5AuthMethod
     106: astore        5
     108: aload_1
     109: aload         5
     111: invokevirtual #30                 // Method io/netty/handler/codec/socksx/v5/Socks5AuthMethod.byteValue:()B
     114: invokevirtual #24                 // Method io/netty/buffer/ByteBuf.writeByte:(I)Lio/netty/buffer/ByteBuf;
     117: pop
     118: goto          86
     121: return

  private static void encodePasswordAuthRequest(io.netty.handler.codec.socksx.v5.Socks5PasswordAuthRequest, io.netty.buffer.ByteBuf);
    Code:
       0: aload_1
       1: iconst_1
       2: invokevirtual #24                 // Method io/netty/buffer/ByteBuf.writeByte:(I)Lio/netty/buffer/ByteBuf;
       5: pop
       6: aload_0
       7: invokeinterface #34,  1           // InterfaceMethod io/netty/handler/codec/socksx/v5/Socks5PasswordAuthRequest.username:()Ljava/lang/String;
      12: astore_2
      13: aload_1
      14: aload_2
      15: invokevirtual #35                 // Method java/lang/String.length:()I
      18: invokevirtual #24                 // Method io/netty/buffer/ByteBuf.writeByte:(I)Lio/netty/buffer/ByteBuf;
      21: pop
      22: aload_1
      23: aload_2
      24: invokestatic  #36                 // Method io/netty/buffer/ByteBufUtil.writeAscii:(Lio/netty/buffer/ByteBuf;Ljava/lang/CharSequence;)I
      27: pop
      28: aload_0
      29: invokeinterface #37,  1           // InterfaceMethod io/netty/handler/codec/socksx/v5/Socks5PasswordAuthRequest.password:()Ljava/lang/String;
      34: astore_3
      35: aload_1
      36: aload_3
      37: invokevirtual #35                 // Method java/lang/String.length:()I
      40: invokevirtual #24                 // Method io/netty/buffer/ByteBuf.writeByte:(I)Lio/netty/buffer/ByteBuf;
      43: pop
      44: aload_1
      45: aload_3
      46: invokestatic  #36                 // Method io/netty/buffer/ByteBufUtil.writeAscii:(Lio/netty/buffer/ByteBuf;Ljava/lang/CharSequence;)I
      49: pop
      50: return

  private void encodeCommandRequest(io.netty.handler.codec.socksx.v5.Socks5CommandRequest, io.netty.buffer.ByteBuf) throws java.lang.Exception;
    Code:
       0: aload_2
       1: aload_1
       2: invokeinterface #38,  1           // InterfaceMethod io/netty/handler/codec/socksx/v5/Socks5CommandRequest.version:()Lio/netty/handler/codec/socksx/SocksVersion;
       7: invokevirtual #23                 // Method io/netty/handler/codec/socksx/SocksVersion.byteValue:()B
      10: invokevirtual #24                 // Method io/netty/buffer/ByteBuf.writeByte:(I)Lio/netty/buffer/ByteBuf;
      13: pop
      14: aload_2
      15: aload_1
      16: invokeinterface #39,  1           // InterfaceMethod io/netty/handler/codec/socksx/v5/Socks5CommandRequest.type:()Lio/netty/handler/codec/socksx/v5/Socks5CommandType;
      21: invokevirtual #40                 // Method io/netty/handler/codec/socksx/v5/Socks5CommandType.byteValue:()B
      24: invokevirtual #24                 // Method io/netty/buffer/ByteBuf.writeByte:(I)Lio/netty/buffer/ByteBuf;
      27: pop
      28: aload_2
      29: iconst_0
      30: invokevirtual #24                 // Method io/netty/buffer/ByteBuf.writeByte:(I)Lio/netty/buffer/ByteBuf;
      33: pop
      34: aload_1
      35: invokeinterface #41,  1           // InterfaceMethod io/netty/handler/codec/socksx/v5/Socks5CommandRequest.dstAddrType:()Lio/netty/handler/codec/socksx/v5/Socks5AddressType;
      40: astore_3
      41: aload_2
      42: aload_3
      43: invokevirtual #42                 // Method io/netty/handler/codec/socksx/v5/Socks5AddressType.byteValue:()B
      46: invokevirtual #24                 // Method io/netty/buffer/ByteBuf.writeByte:(I)Lio/netty/buffer/ByteBuf;
      49: pop
      50: aload_0
      51: getfield      #7                  // Field addressEncoder:Lio/netty/handler/codec/socksx/v5/Socks5AddressEncoder;
      54: aload_3
      55: aload_1
      56: invokeinterface #43,  1           // InterfaceMethod io/netty/handler/codec/socksx/v5/Socks5CommandRequest.dstAddr:()Ljava/lang/String;
      61: aload_2
      62: invokeinterface #44,  4           // InterfaceMethod io/netty/handler/codec/socksx/v5/Socks5AddressEncoder.encodeAddress:(Lio/netty/handler/codec/socksx/v5/Socks5AddressType;Ljava/lang/String;Lio/netty/buffer/ByteBuf;)V
      67: aload_2
      68: aload_1
      69: invokeinterface #45,  1           // InterfaceMethod io/netty/handler/codec/socksx/v5/Socks5CommandRequest.dstPort:()I
      74: invokevirtual #46                 // Method io/netty/buffer/ByteBuf.writeShort:(I)Lio/netty/buffer/ByteBuf;
      77: pop
      78: return

  protected void encode(io.netty.channel.ChannelHandlerContext, java.lang.Object, io.netty.buffer.ByteBuf) throws java.lang.Exception;
    Code:
       0: aload_0
       1: aload_1
       2: aload_2
       3: checkcast     #47                 // class io/netty/handler/codec/socksx/v5/Socks5Message
       6: aload_3
       7: invokevirtual #48                 // Method encode:(Lio/netty/channel/ChannelHandlerContext;Lio/netty/handler/codec/socksx/v5/Socks5Message;Lio/netty/buffer/ByteBuf;)V
      10: return

  static {};
    Code:
       0: new           #49                 // class io/netty/handler/codec/socksx/v5/Socks5ClientEncoder
       3: dup
       4: invokespecial #50                 // Method "<init>":()V
       7: putstatic     #51                 // Field DEFAULT:Lio/netty/handler/codec/socksx/v5/Socks5ClientEncoder;
      10: return
}
