Compiled from "KClassImpl.kt"
final class kotlin.reflect.jvm.internal.KClassImpl$Data$simpleName$2 extends kotlin.jvm.internal.Lambda implements kotlin.jvm.functions.Function0<java.lang.String> {
  final kotlin.reflect.jvm.internal.KClassImpl$Data this$0;

  public java.lang.Object invoke();
    Code:
       0: aload_0
       1: invokevirtual #24                 // Method invoke:()Ljava/lang/String;
       4: areturn

  public final java.lang.String invoke();
    Code:
       0: aload_0
       1: getfield      #17                 // Field this$0:Lkotlin/reflect/jvm/internal/KClassImpl$Data;
       4: getfield      #16                 // Field kotlin/reflect/jvm/internal/KClassImpl$Data.this$0:Lkotlin/reflect/jvm/internal/KClassImpl;
       7: invokevirtual #22                 // Method kotlin/reflect/jvm/internal/KClassImpl.getJClass:()Ljava/lang/Class;
      10: invokevirtual #18                 // Method java/lang/Class.isAnonymousClass:()Z
      13: ifeq          18
      16: aconst_null
      17: areturn
      18: aload_0
      19: getfield      #17                 // Field this$0:Lkotlin/reflect/jvm/internal/KClassImpl$Data;
      22: getfield      #16                 // Field kotlin/reflect/jvm/internal/KClassImpl$Data.this$0:Lkotlin/reflect/jvm/internal/KClassImpl;
      25: invokestatic  #21                 // Method kotlin/reflect/jvm/internal/KClassImpl.access$getClassId$p:(Lkotlin/reflect/jvm/internal/KClassImpl;)Lkotlin/reflect/jvm/internal/impl/name/ClassId;
      28: astore_1
      29: aload_1
      30: invokevirtual #26                 // Method kotlin/reflect/jvm/internal/impl/name/ClassId.isLocal:()Z
      33: ifeq          56
      36: aload_0
      37: getfield      #17                 // Field this$0:Lkotlin/reflect/jvm/internal/KClassImpl$Data;
      40: aload_0
      41: getfield      #17                 // Field this$0:Lkotlin/reflect/jvm/internal/KClassImpl$Data;
      44: getfield      #16                 // Field kotlin/reflect/jvm/internal/KClassImpl$Data.this$0:Lkotlin/reflect/jvm/internal/KClassImpl;
      47: invokevirtual #22                 // Method kotlin/reflect/jvm/internal/KClassImpl.getJClass:()Ljava/lang/Class;
      50: invokestatic  #23                 // Method kotlin/reflect/jvm/internal/KClassImpl$Data.access$calculateLocalClassName:(Lkotlin/reflect/jvm/internal/KClassImpl$Data;Ljava/lang/Class;)Ljava/lang/String;
      53: goto          69
      56: aload_1
      57: invokevirtual #25                 // Method kotlin/reflect/jvm/internal/impl/name/ClassId.getShortClassName:()Lkotlin/reflect/jvm/internal/impl/name/Name;
      60: invokevirtual #27                 // Method kotlin/reflect/jvm/internal/impl/name/Name.asString:()Ljava/lang/String;
      63: dup
      64: ldc           #5                  // String classId.shortClassName.asString()
      66: invokestatic  #19                 // Method kotlin/jvm/internal/Intrinsics.checkExpressionValueIsNotNull:(Ljava/lang/Object;Ljava/lang/String;)V
      69: areturn

  kotlin.reflect.jvm.internal.KClassImpl$Data$simpleName$2(kotlin.reflect.jvm.internal.KClassImpl$Data);
    Code:
       0: aload_0
       1: aload_1
       2: putfield      #17                 // Field this$0:Lkotlin/reflect/jvm/internal/KClassImpl$Data;
       5: aload_0
       6: iconst_0
       7: invokespecial #20                 // Method kotlin/jvm/internal/Lambda."<init>":(I)V
      10: return
}
