Compiled from "kClassCache.kt"
public final class kotlin.reflect.jvm.internal.KClassCacheKt {
  private static kotlin.reflect.jvm.internal.pcollections.HashPMap<java.lang.String, java.lang.Object> K_CLASS_CACHE;

  public static final <T> kotlin.reflect.jvm.internal.KClassImpl<T> getOrCreateKotlinClass(java.lang.Class<T>);
    Code:
       0: aload_0
       1: ldc           #10                 // String jClass
       3: invokestatic  #29                 // Method kotlin/jvm/internal/Intrinsics.checkParameterIsNotNull:(Ljava/lang/Object;Ljava/lang/String;)V
       6: aload_0
       7: invokevirtual #23                 // Method java/lang/Class.getName:()Ljava/lang/String;
      10: astore_1
      11: getstatic     #22                 // Field K_CLASS_CACHE:Lkotlin/reflect/jvm/internal/pcollections/HashPMap;
      14: aload_1
      15: invokevirtual #33                 // Method kotlin/reflect/jvm/internal/pcollections/HashPMap.get:(Ljava/lang/Object;)Ljava/lang/Object;
      18: astore_2
      19: aload_2
      20: instanceof    #17                 // class java/lang/ref/WeakReference
      23: ifeq          59
      26: aload_2
      27: checkcast     #17                 // class java/lang/ref/WeakReference
      30: invokevirtual #26                 // Method java/lang/ref/WeakReference.get:()Ljava/lang/Object;
      33: checkcast     #20                 // class kotlin/reflect/jvm/internal/KClassImpl
      36: astore_3
      37: aload_3
      38: dup
      39: ifnull        48
      42: invokevirtual #31                 // Method kotlin/reflect/jvm/internal/KClassImpl.getJClass:()Ljava/lang/Class;
      45: goto          50
      48: pop
      49: aconst_null
      50: aload_0
      51: invokestatic  #27                 // Method kotlin/jvm/internal/Intrinsics.areEqual:(Ljava/lang/Object;Ljava/lang/Object;)Z
      54: ifeq          201
      57: aload_3
      58: areturn
      59: aload_2
      60: ifnull        201
      63: aload_2
      64: checkcast     #12                 // class "[Ljava/lang/ref/WeakReference;"
      67: pop
      68: aload_2
      69: checkcast     #12                 // class "[Ljava/lang/ref/WeakReference;"
      72: astore        5
      74: aload         5
      76: arraylength
      77: istore        6
      79: iconst_0
      80: istore        4
      82: iload         4
      84: iload         6
      86: if_icmpge     134
      89: aload         5
      91: iload         4
      93: aaload
      94: astore_3
      95: aload_3
      96: invokevirtual #26                 // Method java/lang/ref/WeakReference.get:()Ljava/lang/Object;
      99: checkcast     #20                 // class kotlin/reflect/jvm/internal/KClassImpl
     102: astore        7
     104: aload         7
     106: dup
     107: ifnull        116
     110: invokevirtual #31                 // Method kotlin/reflect/jvm/internal/KClassImpl.getJClass:()Ljava/lang/Class;
     113: goto          118
     116: pop
     117: aconst_null
     118: aload_0
     119: invokestatic  #27                 // Method kotlin/jvm/internal/Intrinsics.areEqual:(Ljava/lang/Object;Ljava/lang/Object;)Z
     122: ifeq          128
     125: aload         7
     127: areturn
     128: iinc          4, 1
     131: goto          82
     134: aload_2
     135: checkcast     #11                 // class "[Ljava/lang/Object;"
     138: arraylength
     139: istore_3
     140: iload_3
     141: iconst_1
     142: iadd
     143: anewarray     #17                 // class java/lang/ref/WeakReference
     146: astore        4
     148: aload_2
     149: iconst_0
     150: aload         4
     152: iconst_0
     153: iload_3
     154: invokestatic  #24                 // Method java/lang/System.arraycopy:(Ljava/lang/Object;ILjava/lang/Object;II)V
     157: new           #20                 // class kotlin/reflect/jvm/internal/KClassImpl
     160: dup
     161: aload_0
     162: invokespecial #30                 // Method kotlin/reflect/jvm/internal/KClassImpl."<init>":(Ljava/lang/Class;)V
     165: astore        5
     167: aload         4
     169: iload_3
     170: new           #17                 // class java/lang/ref/WeakReference
     173: dup
     174: aload         5
     176: invokespecial #25                 // Method java/lang/ref/WeakReference."<init>":(Ljava/lang/Object;)V
     179: aastore
     180: getstatic     #22                 // Field K_CLASS_CACHE:Lkotlin/reflect/jvm/internal/pcollections/HashPMap;
     183: aload_1
     184: aload         4
     186: invokevirtual #34                 // Method kotlin/reflect/jvm/internal/pcollections/HashPMap.plus:(Ljava/lang/Object;Ljava/lang/Object;)Lkotlin/reflect/jvm/internal/pcollections/HashPMap;
     189: dup
     190: ldc           #9                  // String K_CLASS_CACHE.plus(name, newArray)
     192: invokestatic  #28                 // Method kotlin/jvm/internal/Intrinsics.checkExpressionValueIsNotNull:(Ljava/lang/Object;Ljava/lang/String;)V
     195: putstatic     #22                 // Field K_CLASS_CACHE:Lkotlin/reflect/jvm/internal/pcollections/HashPMap;
     198: aload         5
     200: areturn
     201: new           #20                 // class kotlin/reflect/jvm/internal/KClassImpl
     204: dup
     205: aload_0
     206: invokespecial #30                 // Method kotlin/reflect/jvm/internal/KClassImpl."<init>":(Ljava/lang/Class;)V
     209: astore_3
     210: getstatic     #22                 // Field K_CLASS_CACHE:Lkotlin/reflect/jvm/internal/pcollections/HashPMap;
     213: aload_1
     214: new           #17                 // class java/lang/ref/WeakReference
     217: dup
     218: aload_3
     219: invokespecial #25                 // Method java/lang/ref/WeakReference."<init>":(Ljava/lang/Object;)V
     222: invokevirtual #34                 // Method kotlin/reflect/jvm/internal/pcollections/HashPMap.plus:(Ljava/lang/Object;Ljava/lang/Object;)Lkotlin/reflect/jvm/internal/pcollections/HashPMap;
     225: dup
     226: ldc           #8                  // String K_CLASS_CACHE.plus(name, WeakReference(newKClass))
     228: invokestatic  #28                 // Method kotlin/jvm/internal/Intrinsics.checkExpressionValueIsNotNull:(Ljava/lang/Object;Ljava/lang/String;)V
     231: putstatic     #22                 // Field K_CLASS_CACHE:Lkotlin/reflect/jvm/internal/pcollections/HashPMap;
     234: aload_3
     235: areturn

  public static final void clearKClassCache();
    Code:
       0: invokestatic  #32                 // Method kotlin/reflect/jvm/internal/pcollections/HashPMap.empty:()Lkotlin/reflect/jvm/internal/pcollections/HashPMap;
       3: dup
       4: ldc           #6                  // String HashPMap.empty()
       6: invokestatic  #28                 // Method kotlin/jvm/internal/Intrinsics.checkExpressionValueIsNotNull:(Ljava/lang/Object;Ljava/lang/String;)V
       9: putstatic     #22                 // Field K_CLASS_CACHE:Lkotlin/reflect/jvm/internal/pcollections/HashPMap;
      12: return

  static {};
    Code:
       0: invokestatic  #32                 // Method kotlin/reflect/jvm/internal/pcollections/HashPMap.empty:()Lkotlin/reflect/jvm/internal/pcollections/HashPMap;
       3: dup
       4: ldc           #7                  // String HashPMap.empty<String, Any>()
       6: invokestatic  #28                 // Method kotlin/jvm/internal/Intrinsics.checkExpressionValueIsNotNull:(Ljava/lang/Object;Ljava/lang/String;)V
       9: putstatic     #22                 // Field K_CLASS_CACHE:Lkotlin/reflect/jvm/internal/pcollections/HashPMap;
      12: return
}
