Compiled from "KTypeImpl.kt"
final class kotlin.reflect.jvm.internal.KTypeImpl$arguments$2$parameterizedTypeArguments$2 extends kotlin.jvm.internal.Lambda implements kotlin.jvm.functions.Function0<java.util.List<? extends java.lang.reflect.Type>> {
  final kotlin.reflect.jvm.internal.KTypeImpl$arguments$2 this$0;

  public java.lang.Object invoke();
    Code:
       0: aload_0
       1: invokevirtual #15                 // Method invoke:()Ljava/util/List;
       4: areturn

  public final java.util.List<java.lang.reflect.Type> invoke();
    Code:
       0: aload_0
       1: getfield      #12                 // Field this$0:Lkotlin/reflect/jvm/internal/KTypeImpl$arguments$2;
       4: getfield      #11                 // Field kotlin/reflect/jvm/internal/KTypeImpl$arguments$2.this$0:Lkotlin/reflect/jvm/internal/KTypeImpl;
       7: invokevirtual #14                 // Method kotlin/reflect/jvm/internal/KTypeImpl.getJavaType$kotlin_reflect_api:()Ljava/lang/reflect/Type;
      10: invokestatic  #16                 // Method kotlin/reflect/jvm/internal/structure/ReflectClassUtilKt.getParameterizedTypeArguments:(Ljava/lang/reflect/Type;)Ljava/util/List;
      13: areturn

  kotlin.reflect.jvm.internal.KTypeImpl$arguments$2$parameterizedTypeArguments$2(kotlin.reflect.jvm.internal.KTypeImpl$arguments$2);
    Code:
       0: aload_0
       1: aload_1
       2: putfield      #12                 // Field this$0:Lkotlin/reflect/jvm/internal/KTypeImpl$arguments$2;
       5: aload_0
       6: iconst_0
       7: invokespecial #13                 // Method kotlin/jvm/internal/Lambda."<init>":(I)V
      10: return
}
