Compiled from "Window.java"
final class be.yildiz.module.graphic.gui.Window$BasicTitleBar implements be.yildiz.module.graphic.gui.Window$TitleBar {
  private final int height;

  private final be.yildiz.module.graphic.gui.GuiTextLine title;

  private final be.yildiz.module.graphic.gui.GuiButton close;

  final be.yildiz.module.graphic.gui.Window this$0;

  public be.yildiz.module.graphic.gui.Window$BasicTitleBar(be.yildiz.module.graphic.gui.Window, be.yildiz.module.graphic.gui.GuiBuilder);
    Code:
       0: aload_0
       1: aload_1
       2: putfield      #2                  // Field this$0:Lbe/yildiz/module/graphic/gui/Window;
       5: aload_0
       6: invokespecial #3                  // Method java/lang/Object."<init>":()V
       9: aload_0
      10: bipush        30
      12: putfield      #4                  // Field height:I
      15: aload_1
      16: invokevirtual #5                  // Method be/yildiz/module/graphic/gui/Window.getContainer:()Lbe/yildiz/module/graphic/gui/GuiContainer;
      19: astore_3
      20: aload_0
      21: aload_2
      22: new           #6                  // class java/lang/StringBuilder
      25: dup
      26: invokespecial #7                  // Method java/lang/StringBuilder."<init>":()V
      29: ldc           #8                  // String title_
      31: invokevirtual #9                  // Method java/lang/StringBuilder.append:(Ljava/lang/String;)Ljava/lang/StringBuilder;
      34: aload_1
      35: invokevirtual #10                 // Method be/yildiz/module/graphic/gui/Window.getName:()Ljava/lang/String;
      38: invokevirtual #9                  // Method java/lang/StringBuilder.append:(Ljava/lang/String;)Ljava/lang/StringBuilder;
      41: invokevirtual #11                 // Method java/lang/StringBuilder.toString:()Ljava/lang/String;
      44: new           #12                 // class be/yildiz/common/Coordinates
      47: dup
      48: aload_1
      49: invokevirtual #5                  // Method be/yildiz/module/graphic/gui/Window.getContainer:()Lbe/yildiz/module/graphic/gui/GuiContainer;
      52: invokevirtual #13                 // Method be/yildiz/module/graphic/gui/GuiContainer.getWidth:()I
      55: bipush        20
      57: getstatic     #14                 // Field be/yildiz/common/Position.ZERO:Lbe/yildiz/common/Position;
      60: invokespecial #15                 // Method be/yildiz/common/Coordinates."<init>":(IILbe/yildiz/common/Position;)V
      63: invokestatic  #16                 // Method be/yildiz/module/graphic/gui/Window.access$000:()Ljava/lang/String;
      66: invokestatic  #17                 // Method be/yildiz/module/graphic/Font.get:(Ljava/lang/String;)Lbe/yildiz/module/graphic/Font;
      69: aload_3
      70: invokevirtual #18                 // Method be/yildiz/module/graphic/gui/GuiBuilder.buildTextLine:(Ljava/lang/String;Lbe/yildiz/common/Coordinates;Lbe/yildiz/module/graphic/Font;Lbe/yildiz/module/graphic/gui/GuiContainer;)Lbe/yildiz/module/graphic/gui/GuiTextLine;
      73: putfield      #19                 // Field title:Lbe/yildiz/module/graphic/gui/GuiTextLine;
      76: new           #12                 // class be/yildiz/common/Coordinates
      79: dup
      80: aload_0
      81: getfield      #4                  // Field height:I
      84: aload_0
      85: getfield      #4                  // Field height:I
      88: aload_1
      89: invokevirtual #5                  // Method be/yildiz/module/graphic/gui/Window.getContainer:()Lbe/yildiz/module/graphic/gui/GuiContainer;
      92: invokevirtual #13                 // Method be/yildiz/module/graphic/gui/GuiContainer.getWidth:()I
      95: aload_0
      96: getfield      #4                  // Field height:I
      99: isub
     100: iconst_0
     101: invokespecial #20                 // Method be/yildiz/common/Coordinates."<init>":(IIII)V
     104: astore        4
     106: aload_0
     107: aload_2
     108: new           #6                  // class java/lang/StringBuilder
     111: dup
     112: invokespecial #7                  // Method java/lang/StringBuilder."<init>":()V
     115: ldc           #21                 // String close_
     117: invokevirtual #9                  // Method java/lang/StringBuilder.append:(Ljava/lang/String;)Ljava/lang/StringBuilder;
     120: aload_1
     121: invokevirtual #10                 // Method be/yildiz/module/graphic/gui/Window.getName:()Ljava/lang/String;
     124: invokevirtual #9                  // Method java/lang/StringBuilder.append:(Ljava/lang/String;)Ljava/lang/StringBuilder;
     127: invokevirtual #11                 // Method java/lang/StringBuilder.toString:()Ljava/lang/String;
     130: aload         4
     132: invokestatic  #22                 // Method be/yildiz/module/graphic/gui/Window.access$100:()Lbe/yildiz/module/graphic/gui/ButtonMaterial;
     135: aload_3
     136: invokevirtual #23                 // Method be/yildiz/module/graphic/gui/GuiBuilder.buildButton:(Ljava/lang/String;Lbe/yildiz/common/BaseCoordinate;Lbe/yildiz/module/graphic/gui/ButtonMaterial;Lbe/yildiz/module/graphic/gui/GuiContainer;)Lbe/yildiz/module/graphic/gui/GuiButton;
     139: putfield      #24                 // Field close:Lbe/yildiz/module/graphic/gui/GuiButton;
     142: aload_0
     143: getfield      #24                 // Field close:Lbe/yildiz/module/graphic/gui/GuiButton;
     146: aload_1
     147: invokedynamic #25,  0             // InvokeDynamic #0:click:(Lbe/yildiz/module/graphic/gui/Window;)Lbe/yildiz/common/client/gui/listener/MouseLeftClickListener;
     152: invokevirtual #26                 // Method be/yildiz/module/graphic/gui/GuiButton.addMouseLeftClickListener:(Lbe/yildiz/common/client/gui/listener/MouseLeftClickListener;)V
     155: return

  public void showContent();
    Code:
       0: aload_0
       1: getfield      #24                 // Field close:Lbe/yildiz/module/graphic/gui/GuiButton;
       4: invokevirtual #27                 // Method be/yildiz/module/graphic/gui/GuiButton.show:()Lbe/yildiz/module/graphic/gui/Element;
       7: pop
       8: aload_0
       9: getfield      #19                 // Field title:Lbe/yildiz/module/graphic/gui/GuiTextLine;
      12: invokevirtual #28                 // Method be/yildiz/module/graphic/gui/GuiTextLine.show:()Lbe/yildiz/module/graphic/gui/Element;
      15: pop
      16: return
}
