Compiled from "Window.java"
public abstract class be.yildiz.module.graphic.gui.Window extends be.yildiz.module.graphic.gui.View {
  private static final int MINIMIZED_SIZE;

  private static java.lang.String font;

  private static be.yildiz.module.graphic.gui.ButtonMaterial titleClose;

  private final int initialHeight;

  private final be.yildiz.module.graphic.gui.Window$TitleBar titleBar;

  private be.yildiz.module.graphic.gui.ContainerState state;

  public be.yildiz.module.graphic.gui.Window(java.lang.String, be.yildiz.module.graphic.gui.GuiBuilder, be.yildiz.module.graphic.gui.Zorder, be.yildiz.module.graphic.gui.Window$Parameter...);
    Code:
       0: aload_0
       1: aload_2
       2: aload_1
       3: invokestatic  #3                  // Method be/yildiz/module/graphic/Material.empty:()Lbe/yildiz/module/graphic/Material;
       6: getstatic     #4                  // Field be/yildiz/common/BaseCoordinate.ZERO:Lbe/yildiz/common/BaseCoordinate;
       9: invokevirtual #5                  // Method be/yildiz/module/graphic/gui/GuiBuilder.buildOverlayContainer:(Ljava/lang/String;Lbe/yildiz/module/graphic/Material;Lbe/yildiz/common/BaseCoordinate;)Lbe/yildiz/module/graphic/gui/GuiContainer;
      12: aload_2
      13: aload_3
      14: aload         4
      16: invokespecial #6                  // Method "<init>":(Lbe/yildiz/module/graphic/gui/GuiContainer;Lbe/yildiz/module/graphic/gui/GuiBuilder;Lbe/yildiz/module/graphic/gui/Zorder;[Lbe/yildiz/module/graphic/gui/Window$Parameter;)V
      19: return

  public be.yildiz.module.graphic.gui.Window(be.yildiz.module.graphic.gui.GuiContainer, be.yildiz.module.graphic.gui.GuiBuilder, be.yildiz.module.graphic.gui.Zorder);
    Code:
       0: aload_0
       1: aload_1
       2: aload_2
       3: aload_3
       4: iconst_1
       5: anewarray     #7                  // class be/yildiz/module/graphic/gui/Window$Parameter
       8: dup
       9: iconst_0
      10: getstatic     #8                  // Field be/yildiz/module/graphic/gui/Window$Parameter.NOTHING:Lbe/yildiz/module/graphic/gui/Window$Parameter;
      13: aastore
      14: invokespecial #6                  // Method "<init>":(Lbe/yildiz/module/graphic/gui/GuiContainer;Lbe/yildiz/module/graphic/gui/GuiBuilder;Lbe/yildiz/module/graphic/gui/Zorder;[Lbe/yildiz/module/graphic/gui/Window$Parameter;)V
      17: return

  public be.yildiz.module.graphic.gui.Window(be.yildiz.module.graphic.gui.GuiContainer, be.yildiz.module.graphic.gui.GuiBuilder, be.yildiz.module.graphic.gui.Zorder, be.yildiz.module.graphic.gui.Window$Parameter...);
    Code:
       0: aload_0
       1: aload_1
       2: aload_3
       3: invokespecial #9                  // Method be/yildiz/module/graphic/gui/View."<init>":(Lbe/yildiz/module/graphic/gui/GuiContainer;Lbe/yildiz/module/graphic/gui/Zorder;)V
       6: aload         4
       8: invokestatic  #10                 // Method java/util/Arrays.asList:([Ljava/lang/Object;)Ljava/util/List;
      11: astore        5
      13: aload         5
      15: getstatic     #11                 // Field be/yildiz/module/graphic/gui/Window$Parameter.NOT_MOVABLE:Lbe/yildiz/module/graphic/gui/Window$Parameter;
      18: invokeinterface #12,  2           // InterfaceMethod java/util/List.contains:(Ljava/lang/Object;)Z
      23: ifne          61
      26: aload_1
      27: new           #13                 // class be/yildiz/module/graphic/gui/ContainerElementDragListener
      30: dup
      31: aload_1
      32: new           #14                 // class be/yildiz/common/Rectangle
      35: dup
      36: iconst_0
      37: iconst_0
      38: aload_2
      39: invokevirtual #15                 // Method be/yildiz/module/graphic/gui/GuiBuilder.getScreenSize:()Lbe/yildiz/common/Size;
      42: getfield      #16                 // Field be/yildiz/common/Size.width:I
      45: aload_2
      46: invokevirtual #15                 // Method be/yildiz/module/graphic/gui/GuiBuilder.getScreenSize:()Lbe/yildiz/common/Size;
      49: getfield      #17                 // Field be/yildiz/common/Size.height:I
      52: invokespecial #18                 // Method be/yildiz/common/Rectangle."<init>":(IIII)V
      55: invokespecial #19                 // Method be/yildiz/module/graphic/gui/ContainerElementDragListener."<init>":(Lbe/yildiz/module/graphic/gui/GuiContainer;Lbe/yildiz/common/Rectangle;)V
      58: invokevirtual #20                 // Method be/yildiz/module/graphic/gui/GuiContainer.addMouseDragListener:(Lbe/yildiz/common/client/gui/listener/MouseDragListener;)V
      61: aload_0
      62: getstatic     #21                 // Field be/yildiz/module/graphic/gui/ContainerState.OPEN:Lbe/yildiz/module/graphic/gui/ContainerState;
      65: putfield      #22                 // Field state:Lbe/yildiz/module/graphic/gui/ContainerState;
      68: aload         5
      70: getstatic     #23                 // Field be/yildiz/module/graphic/gui/Window$Parameter.NO_TITLE_BAR:Lbe/yildiz/module/graphic/gui/Window$Parameter;
      73: invokeinterface #12,  2           // InterfaceMethod java/util/List.contains:(Ljava/lang/Object;)Z
      78: ifne          97
      81: aload_0
      82: new           #24                 // class be/yildiz/module/graphic/gui/Window$BasicTitleBar
      85: dup
      86: aload_0
      87: aload_2
      88: invokespecial #25                 // Method be/yildiz/module/graphic/gui/Window$BasicTitleBar."<init>":(Lbe/yildiz/module/graphic/gui/Window;Lbe/yildiz/module/graphic/gui/GuiBuilder;)V
      91: putfield      #26                 // Field titleBar:Lbe/yildiz/module/graphic/gui/Window$TitleBar;
      94: goto          109
      97: aload_0
      98: new           #27                 // class be/yildiz/module/graphic/gui/Window$NoTitleBar
     101: dup
     102: aload_0
     103: invokespecial #28                 // Method be/yildiz/module/graphic/gui/Window$NoTitleBar."<init>":(Lbe/yildiz/module/graphic/gui/Window;)V
     106: putfield      #26                 // Field titleBar:Lbe/yildiz/module/graphic/gui/Window$TitleBar;
     109: aload_0
     110: aload_1
     111: invokevirtual #29                 // Method be/yildiz/module/graphic/gui/GuiContainer.getHeight:()I
     114: putfield      #30                 // Field initialHeight:I
     117: return

  public static void setDefaultTitleBarMaterials(be.yildiz.module.graphic.gui.ButtonMaterial);
    Code:
       0: aload_0
       1: putstatic     #1                  // Field titleClose:Lbe/yildiz/module/graphic/gui/ButtonMaterial;
       4: return

  public final void switchState();
    Code:
       0: aload_0
       1: getfield      #22                 // Field state:Lbe/yildiz/module/graphic/gui/ContainerState;
       4: getstatic     #21                 // Field be/yildiz/module/graphic/gui/ContainerState.OPEN:Lbe/yildiz/module/graphic/gui/ContainerState;
       7: if_acmpne     45
      10: aload_0
      11: getstatic     #31                 // Field be/yildiz/module/graphic/gui/ContainerState.MINIMIZED:Lbe/yildiz/module/graphic/gui/ContainerState;
      14: putfield      #22                 // Field state:Lbe/yildiz/module/graphic/gui/ContainerState;
      17: aload_0
      18: invokevirtual #32                 // Method getContainer:()Lbe/yildiz/module/graphic/gui/GuiContainer;
      21: bipush        30
      23: invokevirtual #34                 // Method be/yildiz/module/graphic/gui/GuiContainer.setHeight:(I)V
      26: aload_0
      27: invokevirtual #32                 // Method getContainer:()Lbe/yildiz/module/graphic/gui/GuiContainer;
      30: invokevirtual #35                 // Method be/yildiz/module/graphic/gui/GuiContainer.hideContent:()V
      33: aload_0
      34: getfield      #26                 // Field titleBar:Lbe/yildiz/module/graphic/gui/Window$TitleBar;
      37: invokeinterface #36,  1           // InterfaceMethod be/yildiz/module/graphic/gui/Window$TitleBar.showContent:()V
      42: goto          80
      45: aload_0
      46: getfield      #22                 // Field state:Lbe/yildiz/module/graphic/gui/ContainerState;
      49: getstatic     #31                 // Field be/yildiz/module/graphic/gui/ContainerState.MINIMIZED:Lbe/yildiz/module/graphic/gui/ContainerState;
      52: if_acmpne     80
      55: aload_0
      56: getstatic     #21                 // Field be/yildiz/module/graphic/gui/ContainerState.OPEN:Lbe/yildiz/module/graphic/gui/ContainerState;
      59: putfield      #22                 // Field state:Lbe/yildiz/module/graphic/gui/ContainerState;
      62: aload_0
      63: invokevirtual #32                 // Method getContainer:()Lbe/yildiz/module/graphic/gui/GuiContainer;
      66: aload_0
      67: getfield      #30                 // Field initialHeight:I
      70: invokevirtual #34                 // Method be/yildiz/module/graphic/gui/GuiContainer.setHeight:(I)V
      73: aload_0
      74: invokevirtual #32                 // Method getContainer:()Lbe/yildiz/module/graphic/gui/GuiContainer;
      77: invokevirtual #37                 // Method be/yildiz/module/graphic/gui/GuiContainer.showContent:()V
      80: return

  static java.lang.String access$000();
    Code:
       0: getstatic     #2                  // Field font:Ljava/lang/String;
       3: areturn

  static be.yildiz.module.graphic.gui.ButtonMaterial access$100();
    Code:
       0: getstatic     #1                  // Field titleClose:Lbe/yildiz/module/graphic/gui/ButtonMaterial;
       3: areturn

  static {};
    Code:
       0: invokestatic  #38                 // Method be/yildiz/module/graphic/Font.getDefault:()Lbe/yildiz/module/graphic/Font;
       3: invokevirtual #39                 // Method be/yildiz/module/graphic/Font.getName:()Ljava/lang/String;
       6: putstatic     #2                  // Field font:Ljava/lang/String;
       9: new           #40                 // class be/yildiz/module/graphic/gui/ButtonMaterial
      12: dup
      13: invokestatic  #3                  // Method be/yildiz/module/graphic/Material.empty:()Lbe/yildiz/module/graphic/Material;
      16: invokestatic  #3                  // Method be/yildiz/module/graphic/Material.empty:()Lbe/yildiz/module/graphic/Material;
      19: getstatic     #2                  // Field font:Ljava/lang/String;
      22: invokestatic  #41                 // Method be/yildiz/module/graphic/Font.get:(Ljava/lang/String;)Lbe/yildiz/module/graphic/Font;
      25: invokespecial #42                 // Method be/yildiz/module/graphic/gui/ButtonMaterial."<init>":(Lbe/yildiz/module/graphic/Material;Lbe/yildiz/module/graphic/Material;Lbe/yildiz/module/graphic/Font;)V
      28: putstatic     #1                  // Field titleClose:Lbe/yildiz/module/graphic/gui/ButtonMaterial;
      31: return
}
