Compiled from "HashMap.scala"
public final class scala.collection.immutable.HashMap$HashTrieMap$$anon$1 extends scala.collection.immutable.TrieIterator<scala.Tuple2<A, B>> {
  public final scala.Tuple2<A, B> getElem(java.lang.Object);
    Code:
       0: aload_1
       1: checkcast     #15                 // class scala/collection/immutable/HashMap$HashMap1
       4: invokevirtual #19                 // Method scala/collection/immutable/HashMap$HashMap1.ensurePair:()Lscala/Tuple2;
       7: areturn

  public final java.lang.Object getElem(java.lang.Object);
    Code:
       0: aload_0
       1: aload_1
       2: invokevirtual #26                 // Method getElem:(Ljava/lang/Object;)Lscala/Tuple2;
       5: areturn

  public scala.collection.immutable.HashMap$HashTrieMap$$anon$1(scala.collection.immutable.HashMap$HashTrieMap<A, B>);
    Code:
       0: aload_0
       1: aload_1
       2: invokevirtual #33                 // Method scala/collection/immutable/HashMap$HashTrieMap.elems:()[Lscala/collection/immutable/HashMap;
       5: checkcast     #35                 // class "[Lscala/collection/immutable/Iterable;"
       8: invokespecial #38                 // Method scala/collection/immutable/TrieIterator."<init>":([Lscala/collection/immutable/Iterable;)V
      11: return
}
