Compiled from "MessageModeOutInterceptor.java"
public class org.apache.cxf.jaxws.interceptors.MessageModeOutInterceptor extends org.apache.cxf.phase.AbstractPhaseInterceptor<org.apache.cxf.message.Message> {
  org.apache.cxf.jaxws.interceptors.MessageModeOutInterceptor$MessageModeOutInterceptorInternal internal;

  org.apache.cxf.binding.soap.saaj.SAAJOutInterceptor saajOut;

  java.lang.Class<?> type;

  javax.xml.namespace.QName bindingName;

  public org.apache.cxf.jaxws.interceptors.MessageModeOutInterceptor(org.apache.cxf.binding.soap.saaj.SAAJOutInterceptor, javax.xml.namespace.QName);
    Code:
       0: aload_0
       1: ldc           #2                  // String prepare-send
       3: invokespecial #3                  // Method org/apache/cxf/phase/AbstractPhaseInterceptor."<init>":(Ljava/lang/String;)V
       6: aload_0
       7: aload_1
       8: putfield      #4                  // Field saajOut:Lorg/apache/cxf/binding/soap/saaj/SAAJOutInterceptor;
      11: aload_0
      12: aload_2
      13: putfield      #5                  // Field bindingName:Ljavax/xml/namespace/QName;
      16: aload_0
      17: new           #6                  // class org/apache/cxf/jaxws/interceptors/MessageModeOutInterceptor$MessageModeOutInterceptorInternal
      20: dup
      21: aload_0
      22: invokespecial #7                  // Method org/apache/cxf/jaxws/interceptors/MessageModeOutInterceptor$MessageModeOutInterceptorInternal."<init>":(Lorg/apache/cxf/jaxws/interceptors/MessageModeOutInterceptor;)V
      25: putfield      #8                  // Field internal:Lorg/apache/cxf/jaxws/interceptors/MessageModeOutInterceptor$MessageModeOutInterceptorInternal;
      28: return

  public org.apache.cxf.jaxws.interceptors.MessageModeOutInterceptor(java.lang.Class<?>, javax.xml.namespace.QName);
    Code:
       0: aload_0
       1: ldc           #2                  // String prepare-send
       3: invokespecial #3                  // Method org/apache/cxf/phase/AbstractPhaseInterceptor."<init>":(Ljava/lang/String;)V
       6: aload_0
       7: aload_1
       8: putfield      #9                  // Field type:Ljava/lang/Class;
      11: aload_0
      12: aload_2
      13: putfield      #5                  // Field bindingName:Ljavax/xml/namespace/QName;
      16: return

  public void handleMessage(org.apache.cxf.message.Message) throws org.apache.cxf.interceptor.Fault;
    Code:
       0: aload_1
       1: invokeinterface #10,  1           // InterfaceMethod org/apache/cxf/message/Message.getExchange:()Lorg/apache/cxf/message/Exchange;
       6: invokeinterface #11,  1           // InterfaceMethod org/apache/cxf/message/Exchange.getBindingOperationInfo:()Lorg/apache/cxf/service/model/BindingOperationInfo;
      11: astore_2
      12: aload_2
      13: ifnull        34
      16: aload_0
      17: getfield      #5                  // Field bindingName:Ljavax/xml/namespace/QName;
      20: aload_2
      21: invokevirtual #12                 // Method org/apache/cxf/service/model/BindingOperationInfo.getBinding:()Lorg/apache/cxf/service/model/BindingInfo;
      24: invokevirtual #13                 // Method org/apache/cxf/service/model/BindingInfo.getName:()Ljavax/xml/namespace/QName;
      27: invokevirtual #14                 // Method javax/xml/namespace/QName.equals:(Ljava/lang/Object;)Z
      30: ifne          34
      33: return
      34: aload_0
      35: getfield      #4                  // Field saajOut:Lorg/apache/cxf/binding/soap/saaj/SAAJOutInterceptor;
      38: ifnull        49
      41: aload_0
      42: aload_1
      43: invokespecial #15                 // Method doSoap:(Lorg/apache/cxf/message/Message;)V
      46: goto          489
      49: ldc_w         #16                 // class javax/activation/DataSource
      52: aload_0
      53: getfield      #9                  // Field type:Ljava/lang/Class;
      56: invokevirtual #17                 // Method java/lang/Class.isAssignableFrom:(Ljava/lang/Class;)Z
      59: ifeq          384
      62: aload_1
      63: ldc_w         #18                 // class java/util/List
      66: invokeinterface #19,  2           // InterfaceMethod org/apache/cxf/message/Message.getContent:(Ljava/lang/Class;)Ljava/lang/Object;
      71: checkcast     #20                 // class org/apache/cxf/message/MessageContentsList
      74: astore_3
      75: aload_3
      76: iconst_0
      77: invokevirtual #21                 // Method org/apache/cxf/message/MessageContentsList.get:(I)Ljava/lang/Object;
      80: checkcast     #16                 // class javax/activation/DataSource
      83: astore        4
      85: aload         4
      87: invokeinterface #22,  1           // InterfaceMethod javax/activation/DataSource.getContentType:()Ljava/lang/String;
      92: astore        5
      94: aload         5
      96: invokevirtual #23                 // Method java/lang/String.toLowerCase:()Ljava/lang/String;
      99: ldc           #24                 // String multipart/related
     101: invokevirtual #25                 // Method java/lang/String.contains:(Ljava/lang/CharSequence;)Z
     104: ifeq          252
     107: new           #26                 // class org/apache/cxf/message/MessageImpl
     110: dup
     111: invokespecial #27                 // Method org/apache/cxf/message/MessageImpl."<init>":()V
     114: astore        6
     116: aload         6
     118: aload_1
     119: invokeinterface #10,  1           // InterfaceMethod org/apache/cxf/message/Message.getExchange:()Lorg/apache/cxf/message/Exchange;
     124: invokeinterface #28,  2           // InterfaceMethod org/apache/cxf/message/Message.setExchange:(Lorg/apache/cxf/message/Exchange;)V
     129: aload         6
     131: ldc           #29                 // String Content-Type
     133: aload         5
     135: invokeinterface #30,  3           // InterfaceMethod org/apache/cxf/message/Message.put:(Ljava/lang/Object;Ljava/lang/Object;)Ljava/lang/Object;
     140: pop
     141: aload         6
     143: ldc_w         #31                 // class java/io/InputStream
     146: aload         4
     148: invokeinterface #32,  1           // InterfaceMethod javax/activation/DataSource.getInputStream:()Ljava/io/InputStream;
     153: invokeinterface #33,  3           // InterfaceMethod org/apache/cxf/message/Message.setContent:(Ljava/lang/Class;Ljava/lang/Object;)V
     158: new           #34                 // class org/apache/cxf/attachment/AttachmentDeserializer
     161: dup
     162: aload         6
     164: invokespecial #35                 // Method org/apache/cxf/attachment/AttachmentDeserializer."<init>":(Lorg/apache/cxf/message/Message;)V
     167: astore        7
     169: aload         7
     171: invokevirtual #36                 // Method org/apache/cxf/attachment/AttachmentDeserializer.initializeAttachments:()V
     174: goto          189
     177: astore        7
     179: new           #38                 // class org/apache/cxf/interceptor/Fault
     182: dup
     183: aload         7
     185: invokespecial #39                 // Method org/apache/cxf/interceptor/Fault."<init>":(Ljava/lang/Throwable;)V
     188: athrow
     189: aload_1
     190: aload         6
     192: invokeinterface #40,  1           // InterfaceMethod org/apache/cxf/message/Message.getAttachments:()Ljava/util/Collection;
     197: invokeinterface #41,  2           // InterfaceMethod org/apache/cxf/message/Message.setAttachments:(Ljava/util/Collection;)V
     202: aload         6
     204: ldc_w         #31                 // class java/io/InputStream
     207: invokeinterface #19,  2           // InterfaceMethod org/apache/cxf/message/Message.getContent:(Ljava/lang/Class;)Ljava/lang/Object;
     212: checkcast     #31                 // class java/io/InputStream
     215: astore        7
     217: aload         6
     219: ldc           #29                 // String Content-Type
     221: invokeinterface #42,  2           // InterfaceMethod org/apache/cxf/message/Message.get:(Ljava/lang/Object;)Ljava/lang/Object;
     226: checkcast     #43                 // class java/lang/String
     229: astore        8
     231: aload_3
     232: iconst_0
     233: new           #44                 // class org/apache/cxf/jaxws/interceptors/MessageModeOutInterceptor$1
     236: dup
     237: aload_0
     238: aload         8
     240: aload         7
     242: invokespecial #45                 // Method org/apache/cxf/jaxws/interceptors/MessageModeOutInterceptor$1."<init>":(Lorg/apache/cxf/jaxws/interceptors/MessageModeOutInterceptor;Ljava/lang/String;Ljava/io/InputStream;)V
     245: invokevirtual #46                 // Method org/apache/cxf/message/MessageContentsList.set:(ILjava/lang/Object;)Ljava/lang/Object;
     248: pop
     249: goto          381
     252: aload         5
     254: invokevirtual #23                 // Method java/lang/String.toLowerCase:()Ljava/lang/String;
     257: ldc           #47                 // String xml
     259: invokevirtual #25                 // Method java/lang/String.contains:(Ljava/lang/CharSequence;)Z
     262: ifne          381
     265: aload_1
     266: ldc_w         #48                 // class java/io/OutputStream
     269: invokeinterface #19,  2           // InterfaceMethod org/apache/cxf/message/Message.getContent:(Ljava/lang/Class;)Ljava/lang/Object;
     274: checkcast     #48                 // class java/io/OutputStream
     277: astore        6
     279: aload_1
     280: ldc           #29                 // String Content-Type
     282: aload         5
     284: invokeinterface #30,  3           // InterfaceMethod org/apache/cxf/message/Message.put:(Ljava/lang/Object;Ljava/lang/Object;)Ljava/lang/Object;
     289: pop
     290: aload         4
     292: invokeinterface #32,  1           // InterfaceMethod javax/activation/DataSource.getInputStream:()Ljava/io/InputStream;
     297: astore        7
     299: aload         7
     301: aload         6
     303: invokestatic  #49                 // Method org/apache/cxf/helpers/IOUtils.copy:(Ljava/io/InputStream;Ljava/io/OutputStream;)I
     306: pop
     307: aload         7
     309: invokevirtual #50                 // Method java/io/InputStream.close:()V
     312: aload         6
     314: invokevirtual #51                 // Method java/io/OutputStream.flush:()V
     317: aload         6
     319: invokevirtual #52                 // Method java/io/OutputStream.close:()V
     322: goto          337
     325: astore        7
     327: new           #38                 // class org/apache/cxf/interceptor/Fault
     330: dup
     331: aload         7
     333: invokespecial #39                 // Method org/apache/cxf/interceptor/Fault."<init>":(Ljava/lang/Throwable;)V
     336: athrow
     337: aload_3
     338: iconst_0
     339: invokevirtual #53                 // Method org/apache/cxf/message/MessageContentsList.remove:(I)Ljava/lang/Object;
     342: pop
     343: new           #54                 // class org/apache/cxf/io/CachedOutputStream
     346: dup
     347: invokespecial #55                 // Method org/apache/cxf/io/CachedOutputStream."<init>":()V
     350: astore        6
     352: aload_1
     353: ldc_w         #48                 // class java/io/OutputStream
     356: aload         6
     358: invokeinterface #33,  3           // InterfaceMethod org/apache/cxf/message/Message.setContent:(Ljava/lang/Class;Ljava/lang/Object;)V
     363: aload         6
     365: invokestatic  #56                 // Method org/apache/cxf/staxutils/StaxUtils.createXMLStreamWriter:(Ljava/io/OutputStream;)Ljavax/xml/stream/XMLStreamWriter;
     368: astore        7
     370: aload_1
     371: ldc_w         #57                 // class javax/xml/stream/XMLStreamWriter
     374: aload         7
     376: invokeinterface #33,  3           // InterfaceMethod org/apache/cxf/message/Message.setContent:(Ljava/lang/Class;Ljava/lang/Object;)V
     381: goto          489
     384: getstatic     #58                 // Field org/apache/cxf/annotations/SchemaValidation$SchemaValidationType.OUT:Lorg/apache/cxf/annotations/SchemaValidation$SchemaValidationType;
     387: aload_1
     388: invokestatic  #59                 // Method org/apache/cxf/helpers/ServiceUtils.isSchemaValidationEnabled:(Lorg/apache/cxf/annotations/SchemaValidation$SchemaValidationType;Lorg/apache/cxf/message/Message;)Z
     391: ifeq          489
     394: ldc_w         #60                 // class javax/xml/transform/Source
     397: aload_0
     398: getfield      #9                  // Field type:Ljava/lang/Class;
     401: invokevirtual #17                 // Method java/lang/Class.isAssignableFrom:(Ljava/lang/Class;)Z
     404: ifeq          489
     407: aload_1
     408: ldc_w         #18                 // class java/util/List
     411: invokeinterface #19,  2           // InterfaceMethod org/apache/cxf/message/Message.getContent:(Ljava/lang/Class;)Ljava/lang/Object;
     416: checkcast     #20                 // class org/apache/cxf/message/MessageContentsList
     419: astore_3
     420: aload_3
     421: iconst_0
     422: invokevirtual #21                 // Method org/apache/cxf/message/MessageContentsList.get:(I)Ljava/lang/Object;
     425: checkcast     #60                 // class javax/xml/transform/Source
     428: astore        4
     430: aload         4
     432: instanceof    #61                 // class javax/xml/transform/dom/DOMSource
     435: ifne          489
     438: new           #61                 // class javax/xml/transform/dom/DOMSource
     441: dup
     442: aload         4
     444: invokestatic  #62                 // Method org/apache/cxf/staxutils/StaxUtils.read:(Ljavax/xml/transform/Source;)Lorg/w3c/dom/Document;
     447: invokespecial #63                 // Method javax/xml/transform/dom/DOMSource."<init>":(Lorg/w3c/dom/Node;)V
     450: astore        4
     452: goto          467
     455: astore        5
     457: new           #38                 // class org/apache/cxf/interceptor/Fault
     460: dup
     461: aload         5
     463: invokespecial #39                 // Method org/apache/cxf/interceptor/Fault."<init>":(Ljava/lang/Throwable;)V
     466: athrow
     467: aload_3
     468: iconst_0
     469: aload         4
     471: invokevirtual #46                 // Method org/apache/cxf/message/MessageContentsList.set:(ILjava/lang/Object;)Ljava/lang/Object;
     474: pop
     475: aload_0
     476: aload_1
     477: aload_2
     478: aload         4
     480: checkcast     #61                 // class javax/xml/transform/dom/DOMSource
     483: invokevirtual #65                 // Method javax/xml/transform/dom/DOMSource.getNode:()Lorg/w3c/dom/Node;
     486: invokespecial #66                 // Method validatePossibleFault:(Lorg/apache/cxf/message/Message;Lorg/apache/cxf/service/model/BindingOperationInfo;Lorg/w3c/dom/Node;)V
     489: return
    Exception table:
       from    to  target type
         141   174   177   Class java/io/IOException
         290   322   325   Class java/io/IOException
         438   452   455   Class javax/xml/stream/XMLStreamException

  private void validatePossibleFault(org.apache.cxf.message.Message, org.apache.cxf.service.model.BindingOperationInfo, org.w3c.dom.Node);
    Code:
       0: aload_3
       1: invokestatic  #67                 // Method org/apache/cxf/helpers/DOMUtils.getFirstElement:(Lorg/w3c/dom/Node;)Lorg/w3c/dom/Element;
       4: astore        4
       6: ldc           #68                 // String Fault
       8: aload         4
      10: invokeinterface #69,  1           // InterfaceMethod org/w3c/dom/Element.getLocalName:()Ljava/lang/String;
      15: invokevirtual #70                 // Method java/lang/String.equals:(Ljava/lang/Object;)Z
      18: ifne          22
      21: return
      22: aload_1
      23: getstatic     #71                 // Field org/apache/cxf/message/Message.RESPONSE_CODE:Ljava/lang/String;
      26: sipush        500
      29: invokestatic  #72                 // Method java/lang/Integer.valueOf:(I)Ljava/lang/Integer;
      32: invokeinterface #30,  3           // InterfaceMethod org/apache/cxf/message/Message.put:(Ljava/lang/Object;Ljava/lang/Object;)Ljava/lang/Object;
      37: pop
      38: aload         4
      40: invokestatic  #67                 // Method org/apache/cxf/helpers/DOMUtils.getFirstElement:(Lorg/w3c/dom/Node;)Lorg/w3c/dom/Element;
      43: astore        4
      45: aload         4
      47: ifnull        75
      50: ldc           #73                 // String detail
      52: aload         4
      54: invokeinterface #69,  1           // InterfaceMethod org/w3c/dom/Element.getLocalName:()Ljava/lang/String;
      59: invokevirtual #70                 // Method java/lang/String.equals:(Ljava/lang/Object;)Z
      62: ifne          75
      65: aload         4
      67: invokestatic  #74                 // Method org/apache/cxf/helpers/DOMUtils.getNextElement:(Lorg/w3c/dom/Element;)Lorg/w3c/dom/Element;
      70: astore        4
      72: goto          45
      75: aload         4
      77: ifnull        157
      80: aload_1
      81: invokeinterface #10,  1           // InterfaceMethod org/apache/cxf/message/Message.getExchange:()Lorg/apache/cxf/message/Exchange;
      86: invokeinterface #75,  1           // InterfaceMethod org/apache/cxf/message/Exchange.getService:()Lorg/apache/cxf/service/Service;
      91: invokeinterface #76,  1           // InterfaceMethod org/apache/cxf/service/Service.getServiceInfos:()Ljava/util/List;
      96: iconst_0
      97: invokeinterface #77,  2           // InterfaceMethod java/util/List.get:(I)Ljava/lang/Object;
     102: checkcast     #78                 // class org/apache/cxf/service/model/ServiceInfo
     105: aload_1
     106: invokeinterface #10,  1           // InterfaceMethod org/apache/cxf/message/Message.getExchange:()Lorg/apache/cxf/message/Exchange;
     111: invokeinterface #79,  1           // InterfaceMethod org/apache/cxf/message/Exchange.getBus:()Lorg/apache/cxf/Bus;
     116: invokestatic  #80                 // Method org/apache/cxf/ws/addressing/EndpointReferenceUtils.getSchema:(Lorg/apache/cxf/service/model/ServiceInfo;Lorg/apache/cxf/Bus;)Ljavax/xml/validation/Schema;
     119: astore        5
     121: aload_0
     122: aload         4
     124: aload         5
     126: aload_2
     127: invokespecial #81                 // Method validateFaultDetail:(Lorg/w3c/dom/Element;Ljavax/xml/validation/Schema;Lorg/apache/cxf/service/model/BindingOperationInfo;)V
     130: goto          145
     133: astore        6
     135: new           #38                 // class org/apache/cxf/interceptor/Fault
     138: dup
     139: aload         6
     141: invokespecial #39                 // Method org/apache/cxf/interceptor/Fault."<init>":(Ljava/lang/Throwable;)V
     144: athrow
     145: aload_1
     146: ldc           #83                 // String schema-validation-enabled
     148: getstatic     #84                 // Field java/lang/Boolean.FALSE:Ljava/lang/Boolean;
     151: invokeinterface #30,  3           // InterfaceMethod org/apache/cxf/message/Message.put:(Ljava/lang/Object;Ljava/lang/Object;)Ljava/lang/Object;
     156: pop
     157: return
    Exception table:
       from    to  target type
         121   130   133   Class java/lang/Exception

  private void validateFaultDetail(org.w3c.dom.Element, javax.xml.validation.Schema, org.apache.cxf.service.model.BindingOperationInfo) throws java.lang.Exception;
    Code:
       0: aload_1
       1: ifnull        104
       4: aload_1
       5: invokestatic  #67                 // Method org/apache/cxf/helpers/DOMUtils.getFirstElement:(Lorg/w3c/dom/Node;)Lorg/w3c/dom/Element;
       8: astore        4
      10: aload         4
      12: ifnull        104
      15: aload         4
      17: invokestatic  #85                 // Method org/apache/cxf/helpers/DOMUtils.getElementQName:(Lorg/w3c/dom/Element;)Ljavax/xml/namespace/QName;
      20: astore        5
      22: aload_3
      23: invokevirtual #86                 // Method org/apache/cxf/service/model/BindingOperationInfo.getFaults:()Ljava/util/Collection;
      26: invokeinterface #87,  1           // InterfaceMethod java/util/Collection.iterator:()Ljava/util/Iterator;
      31: astore        6
      33: aload         6
      35: invokeinterface #88,  1           // InterfaceMethod java/util/Iterator.hasNext:()Z
      40: ifeq          94
      43: aload         6
      45: invokeinterface #89,  1           // InterfaceMethod java/util/Iterator.next:()Ljava/lang/Object;
      50: checkcast     #90                 // class org/apache/cxf/service/model/BindingFaultInfo
      53: astore        7
      55: aload         7
      57: invokevirtual #91                 // Method org/apache/cxf/service/model/BindingFaultInfo.getFaultInfo:()Lorg/apache/cxf/service/model/FaultInfo;
      60: iconst_0
      61: invokevirtual #92                 // Method org/apache/cxf/service/model/FaultInfo.getMessagePartByIndex:(I)Lorg/apache/cxf/service/model/MessagePartInfo;
      64: invokevirtual #93                 // Method org/apache/cxf/service/model/MessagePartInfo.getConcreteName:()Ljavax/xml/namespace/QName;
      67: aload         5
      69: invokevirtual #14                 // Method javax/xml/namespace/QName.equals:(Ljava/lang/Object;)Z
      72: ifeq          91
      75: aload_2
      76: invokevirtual #94                 // Method javax/xml/validation/Schema.newValidator:()Ljavax/xml/validation/Validator;
      79: new           #61                 // class javax/xml/transform/dom/DOMSource
      82: dup
      83: aload         4
      85: invokespecial #63                 // Method javax/xml/transform/dom/DOMSource."<init>":(Lorg/w3c/dom/Node;)V
      88: invokevirtual #95                 // Method javax/xml/validation/Validator.validate:(Ljavax/xml/transform/Source;)V
      91: goto          33
      94: aload         4
      96: invokestatic  #74                 // Method org/apache/cxf/helpers/DOMUtils.getNextElement:(Lorg/w3c/dom/Element;)Lorg/w3c/dom/Element;
      99: astore        4
     101: goto          10
     104: return

  private void validateFault(org.apache.cxf.binding.soap.SoapMessage, javax.xml.soap.SOAPFault, org.apache.cxf.service.model.BindingOperationInfo);
    Code:
       0: getstatic     #58                 // Field org/apache/cxf/annotations/SchemaValidation$SchemaValidationType.OUT:Lorg/apache/cxf/annotations/SchemaValidation$SchemaValidationType;
       3: aload_1
       4: invokestatic  #59                 // Method org/apache/cxf/helpers/ServiceUtils.isSchemaValidationEnabled:(Lorg/apache/cxf/annotations/SchemaValidation$SchemaValidationType;Lorg/apache/cxf/message/Message;)Z
       7: ifeq          103
      10: aload_1
      11: invokevirtual #96                 // Method org/apache/cxf/binding/soap/SoapMessage.getExchange:()Lorg/apache/cxf/message/Exchange;
      14: invokeinterface #75,  1           // InterfaceMethod org/apache/cxf/message/Exchange.getService:()Lorg/apache/cxf/service/Service;
      19: invokeinterface #76,  1           // InterfaceMethod org/apache/cxf/service/Service.getServiceInfos:()Ljava/util/List;
      24: iconst_0
      25: invokeinterface #77,  2           // InterfaceMethod java/util/List.get:(I)Ljava/lang/Object;
      30: checkcast     #78                 // class org/apache/cxf/service/model/ServiceInfo
      33: aload_1
      34: invokevirtual #96                 // Method org/apache/cxf/binding/soap/SoapMessage.getExchange:()Lorg/apache/cxf/message/Exchange;
      37: invokeinterface #79,  1           // InterfaceMethod org/apache/cxf/message/Exchange.getBus:()Lorg/apache/cxf/Bus;
      42: invokestatic  #80                 // Method org/apache/cxf/ws/addressing/EndpointReferenceUtils.getSchema:(Lorg/apache/cxf/service/model/ServiceInfo;Lorg/apache/cxf/Bus;)Ljavax/xml/validation/Schema;
      45: astore        4
      47: aload_2
      48: invokeinterface #97,  1           // InterfaceMethod javax/xml/soap/SOAPFault.getDetail:()Ljavax/xml/soap/Detail;
      53: astore        5
      55: aload_0
      56: aload         5
      58: aload         4
      60: aload_3
      61: invokespecial #81                 // Method validateFaultDetail:(Lorg/w3c/dom/Element;Ljavax/xml/validation/Schema;Lorg/apache/cxf/service/model/BindingOperationInfo;)V
      64: goto          93
      67: astore        6
      69: new           #98                 // class org/apache/cxf/binding/soap/SoapFault
      72: dup
      73: aload         6
      75: invokevirtual #99                 // Method java/lang/Exception.getMessage:()Ljava/lang/String;
      78: aload         6
      80: aload_1
      81: invokevirtual #100                // Method org/apache/cxf/binding/soap/SoapMessage.getVersion:()Lorg/apache/cxf/binding/soap/SoapVersion;
      84: invokeinterface #101,  1          // InterfaceMethod org/apache/cxf/binding/soap/SoapVersion.getReceiver:()Ljavax/xml/namespace/QName;
      89: invokespecial #102                // Method org/apache/cxf/binding/soap/SoapFault."<init>":(Ljava/lang/String;Ljava/lang/Throwable;Ljavax/xml/namespace/QName;)V
      92: athrow
      93: aload_1
      94: ldc           #83                 // String schema-validation-enabled
      96: getstatic     #84                 // Field java/lang/Boolean.FALSE:Ljava/lang/Boolean;
      99: invokevirtual #103                // Method org/apache/cxf/binding/soap/SoapMessage.put:(Ljava/lang/String;Ljava/lang/Object;)Ljava/lang/Object;
     102: pop
     103: return
    Exception table:
       from    to  target type
          55    64    67   Class java/lang/Exception

  private void doSoap(org.apache.cxf.message.Message);
    Code:
       0: aload_1
       1: ldc_w         #18                 // class java/util/List
       4: invokeinterface #19,  2           // InterfaceMethod org/apache/cxf/message/Message.getContent:(Ljava/lang/Class;)Ljava/lang/Object;
       9: checkcast     #20                 // class org/apache/cxf/message/MessageContentsList
      12: astore_2
      13: aload_2
      14: ifnull        24
      17: aload_2
      18: invokevirtual #104                // Method org/apache/cxf/message/MessageContentsList.isEmpty:()Z
      21: ifeq          25
      24: return
      25: aload_2
      26: iconst_0
      27: invokevirtual #21                 // Method org/apache/cxf/message/MessageContentsList.get:(I)Ljava/lang/Object;
      30: astore_3
      31: aload_3
      32: instanceof    #105                // class javax/xml/soap/SOAPMessage
      35: ifeq          249
      38: aload_3
      39: checkcast     #105                // class javax/xml/soap/SOAPMessage
      42: astore        4
      44: aload         4
      46: invokevirtual #106                // Method javax/xml/soap/SOAPMessage.countAttachments:()I
      49: ifle          64
      52: aload_1
      53: ldc           #107                // String write.attachments
      55: getstatic     #108                // Field java/lang/Boolean.TRUE:Ljava/lang/Boolean;
      58: invokeinterface #30,  3           // InterfaceMethod org/apache/cxf/message/Message.put:(Ljava/lang/Object;Ljava/lang/Object;)Ljava/lang/Object;
      63: pop
      64: aload_1
      65: instanceof    #109                // class org/apache/cxf/binding/soap/SoapMessage
      68: ifeq          170
      71: aload_1
      72: checkcast     #109                // class org/apache/cxf/binding/soap/SoapMessage
      75: astore        5
      77: aload         5
      79: invokevirtual #100                // Method org/apache/cxf/binding/soap/SoapMessage.getVersion:()Lorg/apache/cxf/binding/soap/SoapVersion;
      82: invokeinterface #110,  1          // InterfaceMethod org/apache/cxf/binding/soap/SoapVersion.getNamespace:()Ljava/lang/String;
      87: astore        6
      89: aload         4
      91: invokevirtual #111                // Method javax/xml/soap/SOAPMessage.getSOAPHeader:()Ljavax/xml/soap/SOAPHeader;
      94: astore        7
      96: aload         7
      98: ifnonnull     105
     101: aconst_null
     102: goto          112
     105: aload         7
     107: invokeinterface #112,  1          // InterfaceMethod javax/xml/soap/SOAPHeader.getNamespaceURI:()Ljava/lang/String;
     112: astore        8
     114: aload         8
     116: ifnull        170
     119: aload         6
     121: ifnull        170
     124: aload         8
     126: aload         6
     128: invokevirtual #70                 // Method java/lang/String.equals:(Ljava/lang/Object;)Z
     131: ifne          170
     134: ldc           #113                // String http://www.w3.org/2003/05/soap-envelope
     136: aload         8
     138: invokevirtual #70                 // Method java/lang/String.equals:(Ljava/lang/Object;)Z
     141: ifeq          170
     144: aload         5
     146: invokestatic  #114                // Method org/apache/cxf/binding/soap/Soap12.getInstance:()Lorg/apache/cxf/binding/soap/Soap12;
     149: invokevirtual #115                // Method org/apache/cxf/binding/soap/SoapMessage.setVersion:(Lorg/apache/cxf/binding/soap/SoapVersion;)V
     152: aload         5
     154: ldc           #29                 // String Content-Type
     156: aload         5
     158: invokevirtual #100                // Method org/apache/cxf/binding/soap/SoapMessage.getVersion:()Lorg/apache/cxf/binding/soap/SoapVersion;
     161: invokeinterface #116,  1          // InterfaceMethod org/apache/cxf/binding/soap/SoapVersion.getContentType:()Ljava/lang/String;
     166: invokevirtual #103                // Method org/apache/cxf/binding/soap/SoapMessage.put:(Ljava/lang/String;Ljava/lang/Object;)Ljava/lang/Object;
     169: pop
     170: goto          175
     173: astore        5
     175: aload         4
     177: ldc           #118                // String javax.xml.soap.character-set-encoding
     179: invokevirtual #119                // Method javax/xml/soap/SOAPMessage.getProperty:(Ljava/lang/String;)Ljava/lang/Object;
     182: astore        5
     184: aload         5
     186: instanceof    #43                 // class java/lang/String
     189: ifeq          204
     192: aload_1
     193: getstatic     #120                // Field org/apache/cxf/message/Message.ENCODING:Ljava/lang/String;
     196: aload         5
     198: invokeinterface #30,  3           // InterfaceMethod org/apache/cxf/message/Message.put:(Ljava/lang/Object;Ljava/lang/Object;)Ljava/lang/Object;
     203: pop
     204: goto          209
     207: astore        5
     209: aload         4
     211: ldc           #121                // String javax.xml.soap.write-xml-declaration
     213: invokevirtual #119                // Method javax/xml/soap/SOAPMessage.getProperty:(Ljava/lang/String;)Ljava/lang/Object;
     216: astore        5
     218: aload         5
     220: ifnull        244
     223: aload         5
     225: invokestatic  #122                // Method org/apache/cxf/message/MessageUtils.isTrue:(Ljava/lang/Object;)Z
     228: istore        6
     230: aload_1
     231: ldc           #123                // String org.apache.cxf.stax.force-start-document
     233: iload         6
     235: invokestatic  #124                // Method java/lang/Boolean.valueOf:(Z)Ljava/lang/Boolean;
     238: invokeinterface #30,  3           // InterfaceMethod org/apache/cxf/message/Message.put:(Ljava/lang/Object;Ljava/lang/Object;)Ljava/lang/Object;
     243: pop
     244: goto          249
     247: astore        5
     249: aload_1
     250: invokeinterface #125,  1          // InterfaceMethod org/apache/cxf/message/Message.getInterceptorChain:()Lorg/apache/cxf/interceptor/InterceptorChain;
     255: aload_0
     256: getfield      #8                  // Field internal:Lorg/apache/cxf/jaxws/interceptors/MessageModeOutInterceptor$MessageModeOutInterceptorInternal;
     259: invokeinterface #126,  2          // InterfaceMethod org/apache/cxf/interceptor/InterceptorChain.add:(Lorg/apache/cxf/interceptor/Interceptor;)V
     264: return
    Exception table:
       from    to  target type
          64   170   173   Class javax/xml/soap/SOAPException
         175   204   207   Class javax/xml/soap/SOAPException
         209   244   247   Class javax/xml/soap/SOAPException

  static void access$000(org.apache.cxf.jaxws.interceptors.MessageModeOutInterceptor, org.apache.cxf.binding.soap.SoapMessage, javax.xml.soap.SOAPFault, org.apache.cxf.service.model.BindingOperationInfo);
    Code:
       0: aload_0
       1: aload_1
       2: aload_2
       3: aload_3
       4: invokespecial #1                  // Method validateFault:(Lorg/apache/cxf/binding/soap/SoapMessage;Ljavax/xml/soap/SOAPFault;Lorg/apache/cxf/service/model/BindingOperationInfo;)V
       7: return
}
