Compiled from "SwAOutInterceptor.java"
class org.apache.cxf.jaxws.interceptors.SwAOutInterceptor$1 implements java.security.PrivilegedExceptionAction<java.lang.reflect.Method> {
  final javax.xml.bind.JAXBContext val$ctx;

  final org.apache.cxf.jaxws.interceptors.SwAOutInterceptor this$0;

  org.apache.cxf.jaxws.interceptors.SwAOutInterceptor$1(org.apache.cxf.jaxws.interceptors.SwAOutInterceptor, javax.xml.bind.JAXBContext);
    Code:
       0: aload_0
       1: aload_1
       2: putfield      #1                  // Field this$0:Lorg/apache/cxf/jaxws/interceptors/SwAOutInterceptor;
       5: aload_0
       6: aload_2
       7: putfield      #2                  // Field val$ctx:Ljavax/xml/bind/JAXBContext;
      10: aload_0
      11: invokespecial #3                  // Method java/lang/Object."<init>":()V
      14: return

  public java.lang.reflect.Method run() throws java.lang.Exception;
    Code:
       0: aload_0
       1: getfield      #2                  // Field val$ctx:Ljavax/xml/bind/JAXBContext;
       4: invokevirtual #4                  // Method java/lang/Object.getClass:()Ljava/lang/Class;
       7: ldc           #5                  // String hasSwaRef
       9: iconst_0
      10: anewarray     #6                  // class java/lang/Class
      13: invokevirtual #7                  // Method java/lang/Class.getMethod:(Ljava/lang/String;[Ljava/lang/Class;)Ljava/lang/reflect/Method;
      16: astore_1
      17: aload_1
      18: invokevirtual #8                  // Method java/lang/reflect/Method.isAccessible:()Z
      21: ifne          29
      24: aload_1
      25: iconst_1
      26: invokevirtual #9                  // Method java/lang/reflect/Method.setAccessible:(Z)V
      29: aload_1
      30: areturn

  public java.lang.Object run() throws java.lang.Exception;
    Code:
       0: aload_0
       1: invokevirtual #10                 // Method run:()Ljava/lang/reflect/Method;
       4: areturn
}
