Compiled from "GitBuildResourceDecorationContributorIT.kt"
final class net.nemerosa.ontrack.extension.git.GitBuildResourceDecorationContributorIT$No change log link on a build not configured$node$1 extends kotlin.jvm.internal.Lambda implements kotlin.jvm.functions.Function0<com.fasterxml.jackson.databind.JsonNode> {
  final net.nemerosa.ontrack.extension.git.GitBuildResourceDecorationContributorIT this$0;

  final net.nemerosa.ontrack.model.structure.Build $build;

  net.nemerosa.ontrack.extension.git.GitBuildResourceDecorationContributorIT$No change log link on a build not configured$node$1(net.nemerosa.ontrack.extension.git.GitBuildResourceDecorationContributorIT, net.nemerosa.ontrack.model.structure.Build);
    Code:
       0: aload_0
       1: aload_1
       2: putfield      #13                 // Field this$0:Lnet/nemerosa/ontrack/extension/git/GitBuildResourceDecorationContributorIT;
       5: aload_0
       6: aload_2
       7: putfield      #17                 // Field $build:Lnet/nemerosa/ontrack/model/structure/Build;
      10: aload_0
      11: iconst_0
      12: invokespecial #20                 // Method kotlin/jvm/internal/Lambda."<init>":(I)V
      15: return

  public final com.fasterxml.jackson.databind.JsonNode invoke();
    Code:
       0: aload_0
       1: getfield      #13                 // Field this$0:Lnet/nemerosa/ontrack/extension/git/GitBuildResourceDecorationContributorIT;
       4: invokestatic  #31                 // Method net/nemerosa/ontrack/extension/git/GitBuildResourceDecorationContributorIT.access$getResourceObjectMapper$p:(Lnet/nemerosa/ontrack/extension/git/GitBuildResourceDecorationContributorIT;)Lnet/nemerosa/ontrack/ui/resource/ResourceObjectMapper;
       7: dup
       8: ifnonnull     18
      11: pop
      12: ldc           #33                 // String resourceObjectMapper
      14: invokestatic  #39                 // Method kotlin/jvm/internal/Intrinsics.throwUninitializedPropertyAccessException:(Ljava/lang/String;)V
      17: aconst_null
      18: invokeinterface #45,  1           // InterfaceMethod net/nemerosa/ontrack/ui/resource/ResourceObjectMapper.getObjectMapper:()Lcom/fasterxml/jackson/databind/ObjectMapper;
      23: aload_0
      24: getfield      #17                 // Field $build:Lnet/nemerosa/ontrack/model/structure/Build;
      27: invokevirtual #51                 // Method com/fasterxml/jackson/databind/ObjectMapper.valueToTree:(Ljava/lang/Object;)Lcom/fasterxml/jackson/databind/JsonNode;
      30: areturn

  public java.lang.Object invoke();
    Code:
       0: aload_0
       1: invokevirtual #54                 // Method invoke:()Lcom/fasterxml/jackson/databind/JsonNode;
       4: areturn
}
