Compiled from "GitMockConfig.java"
public class net.nemerosa.ontrack.extension.git.GitMockConfig {
  public net.nemerosa.ontrack.extension.git.GitMockConfig();
    Code:
       0: aload_0
       1: invokespecial #1                  // Method java/lang/Object."<init>":()V
       4: return

  public net.nemerosa.ontrack.git.GitRepositoryClient testGitRepositoryClient();
    Code:
       0: ldc           #2                  // class net/nemerosa/ontrack/git/GitRepositoryClient
       2: invokestatic  #3                  // Method org/mockito/Mockito.mock:(Ljava/lang/Class;)Ljava/lang/Object;
       5: checkcast     #2                  // class net/nemerosa/ontrack/git/GitRepositoryClient
       8: areturn

  public net.nemerosa.ontrack.git.GitRepositoryClientFactory repositoryClientFactory();
    Code:
       0: ldc           #4                  // class net/nemerosa/ontrack/git/GitRepositoryClientFactory
       2: invokestatic  #3                  // Method org/mockito/Mockito.mock:(Ljava/lang/Class;)Ljava/lang/Object;
       5: checkcast     #4                  // class net/nemerosa/ontrack/git/GitRepositoryClientFactory
       8: astore_1
       9: aload_1
      10: ldc           #5                  // class net/nemerosa/ontrack/git/GitRepository
      12: invokestatic  #6                  // Method org/mockito/ArgumentMatchers.any:(Ljava/lang/Class;)Ljava/lang/Object;
      15: checkcast     #5                  // class net/nemerosa/ontrack/git/GitRepository
      18: invokeinterface #7,  2            // InterfaceMethod net/nemerosa/ontrack/git/GitRepositoryClientFactory.getClient:(Lnet/nemerosa/ontrack/git/GitRepository;)Lnet/nemerosa/ontrack/git/GitRepositoryClient;
      23: invokestatic  #8                  // Method org/mockito/Mockito.when:(Ljava/lang/Object;)Lorg/mockito/stubbing/OngoingStubbing;
      26: aload_0
      27: invokevirtual #9                  // Method testGitRepositoryClient:()Lnet/nemerosa/ontrack/git/GitRepositoryClient;
      30: invokeinterface #10,  2           // InterfaceMethod org/mockito/stubbing/OngoingStubbing.thenReturn:(Ljava/lang/Object;)Lorg/mockito/stubbing/OngoingStubbing;
      35: pop
      36: aload_1
      37: areturn
}
