Compiled from "ByteMatchSetUpdate.java"
final class software.amazon.awssdk.services.waf.model.ByteMatchSetUpdate$BuilderImpl implements software.amazon.awssdk.services.waf.model.ByteMatchSetUpdate$Builder {
  private java.lang.String action;

  private software.amazon.awssdk.services.waf.model.ByteMatchTuple byteMatchTuple;

  private software.amazon.awssdk.services.waf.model.ByteMatchSetUpdate$BuilderImpl();
    Code:
       0: aload_0
       1: invokespecial #5                  // Method java/lang/Object."<init>":()V
       4: return

  private software.amazon.awssdk.services.waf.model.ByteMatchSetUpdate$BuilderImpl(software.amazon.awssdk.services.waf.model.ByteMatchSetUpdate);
    Code:
       0: aload_0
       1: invokespecial #5                  // Method java/lang/Object."<init>":()V
       4: aload_0
       5: aload_1
       6: invokestatic  #6                  // Method software/amazon/awssdk/services/waf/model/ByteMatchSetUpdate.access$400:(Lsoftware/amazon/awssdk/services/waf/model/ByteMatchSetUpdate;)Ljava/lang/String;
       9: invokevirtual #7                  // Method action:(Ljava/lang/String;)Lsoftware/amazon/awssdk/services/waf/model/ByteMatchSetUpdate$Builder;
      12: pop
      13: aload_0
      14: aload_1
      15: invokestatic  #8                  // Method software/amazon/awssdk/services/waf/model/ByteMatchSetUpdate.access$500:(Lsoftware/amazon/awssdk/services/waf/model/ByteMatchSetUpdate;)Lsoftware/amazon/awssdk/services/waf/model/ByteMatchTuple;
      18: invokevirtual #9                  // Method byteMatchTuple:(Lsoftware/amazon/awssdk/services/waf/model/ByteMatchTuple;)Lsoftware/amazon/awssdk/services/waf/model/ByteMatchSetUpdate$Builder;
      21: pop
      22: return

  public final java.lang.String getAction();
    Code:
       0: aload_0
       1: getfield      #4                  // Field action:Ljava/lang/String;
       4: areturn

  public final void setAction(java.lang.String);
    Code:
       0: aload_0
       1: aload_1
       2: putfield      #4                  // Field action:Ljava/lang/String;
       5: return

  public final software.amazon.awssdk.services.waf.model.ByteMatchSetUpdate$Builder action(java.lang.String);
    Code:
       0: aload_0
       1: aload_1
       2: putfield      #4                  // Field action:Ljava/lang/String;
       5: aload_0
       6: areturn

  public final software.amazon.awssdk.services.waf.model.ByteMatchSetUpdate$Builder action(software.amazon.awssdk.services.waf.model.ChangeAction);
    Code:
       0: aload_0
       1: aload_1
       2: ifnonnull     9
       5: aconst_null
       6: goto          13
       9: aload_1
      10: invokevirtual #10                 // Method software/amazon/awssdk/services/waf/model/ChangeAction.toString:()Ljava/lang/String;
      13: invokevirtual #7                  // Method action:(Ljava/lang/String;)Lsoftware/amazon/awssdk/services/waf/model/ByteMatchSetUpdate$Builder;
      16: pop
      17: aload_0
      18: areturn

  public final software.amazon.awssdk.services.waf.model.ByteMatchTuple$Builder getByteMatchTuple();
    Code:
       0: aload_0
       1: getfield      #3                  // Field byteMatchTuple:Lsoftware/amazon/awssdk/services/waf/model/ByteMatchTuple;
       4: ifnull        17
       7: aload_0
       8: getfield      #3                  // Field byteMatchTuple:Lsoftware/amazon/awssdk/services/waf/model/ByteMatchTuple;
      11: invokevirtual #11                 // Method software/amazon/awssdk/services/waf/model/ByteMatchTuple.toBuilder:()Lsoftware/amazon/awssdk/services/waf/model/ByteMatchTuple$Builder;
      14: goto          18
      17: aconst_null
      18: areturn

  public final void setByteMatchTuple(software.amazon.awssdk.services.waf.model.ByteMatchTuple$BuilderImpl);
    Code:
       0: aload_0
       1: aload_1
       2: ifnull        12
       5: aload_1
       6: invokevirtual #12                 // Method software/amazon/awssdk/services/waf/model/ByteMatchTuple$BuilderImpl.build:()Lsoftware/amazon/awssdk/services/waf/model/ByteMatchTuple;
       9: goto          13
      12: aconst_null
      13: putfield      #3                  // Field byteMatchTuple:Lsoftware/amazon/awssdk/services/waf/model/ByteMatchTuple;
      16: return

  public final software.amazon.awssdk.services.waf.model.ByteMatchSetUpdate$Builder byteMatchTuple(software.amazon.awssdk.services.waf.model.ByteMatchTuple);
    Code:
       0: aload_0
       1: aload_1
       2: putfield      #3                  // Field byteMatchTuple:Lsoftware/amazon/awssdk/services/waf/model/ByteMatchTuple;
       5: aload_0
       6: areturn

  public software.amazon.awssdk.services.waf.model.ByteMatchSetUpdate build();
    Code:
       0: new           #13                 // class software/amazon/awssdk/services/waf/model/ByteMatchSetUpdate
       3: dup
       4: aload_0
       5: aconst_null
       6: invokespecial #14                 // Method software/amazon/awssdk/services/waf/model/ByteMatchSetUpdate."<init>":(Lsoftware/amazon/awssdk/services/waf/model/ByteMatchSetUpdate$BuilderImpl;Lsoftware/amazon/awssdk/services/waf/model/ByteMatchSetUpdate$1;)V
       9: areturn

  public java.util.List<software.amazon.awssdk.core.SdkField<?>> sdkFields();
    Code:
       0: invokestatic  #15                 // Method software/amazon/awssdk/services/waf/model/ByteMatchSetUpdate.access$700:()Ljava/util/List;
       3: areturn

  public java.lang.Object build();
    Code:
       0: aload_0
       1: invokevirtual #16                 // Method build:()Lsoftware/amazon/awssdk/services/waf/model/ByteMatchSetUpdate;
       4: areturn

  static java.lang.String access$000(software.amazon.awssdk.services.waf.model.ByteMatchSetUpdate$BuilderImpl);
    Code:
       0: aload_0
       1: getfield      #4                  // Field action:Ljava/lang/String;
       4: areturn

  static software.amazon.awssdk.services.waf.model.ByteMatchTuple access$100(software.amazon.awssdk.services.waf.model.ByteMatchSetUpdate$BuilderImpl);
    Code:
       0: aload_0
       1: getfield      #3                  // Field byteMatchTuple:Lsoftware/amazon/awssdk/services/waf/model/ByteMatchTuple;
       4: areturn

  software.amazon.awssdk.services.waf.model.ByteMatchSetUpdate$BuilderImpl(software.amazon.awssdk.services.waf.model.ByteMatchSetUpdate, software.amazon.awssdk.services.waf.model.ByteMatchSetUpdate$1);
    Code:
       0: aload_0
       1: aload_1
       2: invokespecial #2                  // Method "<init>":(Lsoftware/amazon/awssdk/services/waf/model/ByteMatchSetUpdate;)V
       5: return

  software.amazon.awssdk.services.waf.model.ByteMatchSetUpdate$BuilderImpl(software.amazon.awssdk.services.waf.model.ByteMatchSetUpdate$1);
    Code:
       0: aload_0
       1: invokespecial #1                  // Method "<init>":()V
       4: return
}
