Compiled from "CreateRateBasedRuleResponse.java"
public interface software.amazon.awssdk.services.waf.model.CreateRateBasedRuleResponse$Builder extends software.amazon.awssdk.services.waf.model.WafResponse$Builder, software.amazon.awssdk.core.SdkPojo, software.amazon.awssdk.utils.builder.CopyableBuilder<software.amazon.awssdk.services.waf.model.CreateRateBasedRuleResponse$Builder, software.amazon.awssdk.services.waf.model.CreateRateBasedRuleResponse> {
  public abstract software.amazon.awssdk.services.waf.model.CreateRateBasedRuleResponse$Builder rule(software.amazon.awssdk.services.waf.model.RateBasedRule);

  public default software.amazon.awssdk.services.waf.model.CreateRateBasedRuleResponse$Builder rule(java.util.function.Consumer<software.amazon.awssdk.services.waf.model.RateBasedRule$Builder>);
    Code:
       0: aload_0
       1: invokestatic  #1                  // Method software/amazon/awssdk/services/waf/model/RateBasedRule.builder:()Lsoftware/amazon/awssdk/services/waf/model/RateBasedRule$Builder;
       4: aload_1
       5: invokeinterface #2,  2            // InterfaceMethod software/amazon/awssdk/services/waf/model/RateBasedRule$Builder.applyMutation:(Ljava/util/function/Consumer;)Lsoftware/amazon/awssdk/utils/builder/SdkBuilder;
      10: checkcast     #3                  // class software/amazon/awssdk/services/waf/model/RateBasedRule$Builder
      13: invokeinterface #4,  1            // InterfaceMethod software/amazon/awssdk/services/waf/model/RateBasedRule$Builder.build:()Ljava/lang/Object;
      18: checkcast     #5                  // class software/amazon/awssdk/services/waf/model/RateBasedRule
      21: invokeinterface #6,  2            // InterfaceMethod rule:(Lsoftware/amazon/awssdk/services/waf/model/RateBasedRule;)Lsoftware/amazon/awssdk/services/waf/model/CreateRateBasedRuleResponse$Builder;
      26: areturn

  public abstract software.amazon.awssdk.services.waf.model.CreateRateBasedRuleResponse$Builder changeToken(java.lang.String);
}
