Compiled from "ListResourcesForWebAclResponse.java"
final class software.amazon.awssdk.services.waf.model.ListResourcesForWebAclResponse$BuilderImpl extends software.amazon.awssdk.services.waf.model.WafResponse$BuilderImpl implements software.amazon.awssdk.services.waf.model.ListResourcesForWebAclResponse$Builder {
  private java.util.List<java.lang.String> resourceArns;

  private software.amazon.awssdk.services.waf.model.ListResourcesForWebAclResponse$BuilderImpl();
    Code:
       0: aload_0
       1: invokespecial #4                  // Method software/amazon/awssdk/services/waf/model/WafResponse$BuilderImpl."<init>":()V
       4: aload_0
       5: invokestatic  #5                  // Method software/amazon/awssdk/core/util/DefaultSdkAutoConstructList.getInstance:()Lsoftware/amazon/awssdk/core/util/DefaultSdkAutoConstructList;
       8: putfield      #3                  // Field resourceArns:Ljava/util/List;
      11: return

  private software.amazon.awssdk.services.waf.model.ListResourcesForWebAclResponse$BuilderImpl(software.amazon.awssdk.services.waf.model.ListResourcesForWebAclResponse);
    Code:
       0: aload_0
       1: aload_1
       2: invokespecial #6                  // Method software/amazon/awssdk/services/waf/model/WafResponse$BuilderImpl."<init>":(Lsoftware/amazon/awssdk/services/waf/model/WafResponse;)V
       5: aload_0
       6: invokestatic  #5                  // Method software/amazon/awssdk/core/util/DefaultSdkAutoConstructList.getInstance:()Lsoftware/amazon/awssdk/core/util/DefaultSdkAutoConstructList;
       9: putfield      #3                  // Field resourceArns:Ljava/util/List;
      12: aload_0
      13: aload_1
      14: invokestatic  #7                  // Method software/amazon/awssdk/services/waf/model/ListResourcesForWebAclResponse.access$300:(Lsoftware/amazon/awssdk/services/waf/model/ListResourcesForWebAclResponse;)Ljava/util/List;
      17: invokevirtual #8                  // Method resourceArns:(Ljava/util/Collection;)Lsoftware/amazon/awssdk/services/waf/model/ListResourcesForWebAclResponse$Builder;
      20: pop
      21: return

  public final java.util.Collection<java.lang.String> getResourceArns();
    Code:
       0: aload_0
       1: getfield      #3                  // Field resourceArns:Ljava/util/List;
       4: instanceof    #9                  // class software/amazon/awssdk/core/util/SdkAutoConstructList
       7: ifeq          12
      10: aconst_null
      11: areturn
      12: aload_0
      13: getfield      #3                  // Field resourceArns:Ljava/util/List;
      16: areturn

  public final void setResourceArns(java.util.Collection<java.lang.String>);
    Code:
       0: aload_0
       1: aload_1
       2: invokestatic  #10                 // Method software/amazon/awssdk/services/waf/model/ResourceArnsCopier.copy:(Ljava/util/Collection;)Ljava/util/List;
       5: putfield      #3                  // Field resourceArns:Ljava/util/List;
       8: return

  public final software.amazon.awssdk.services.waf.model.ListResourcesForWebAclResponse$Builder resourceArns(java.util.Collection<java.lang.String>);
    Code:
       0: aload_0
       1: aload_1
       2: invokestatic  #10                 // Method software/amazon/awssdk/services/waf/model/ResourceArnsCopier.copy:(Ljava/util/Collection;)Ljava/util/List;
       5: putfield      #3                  // Field resourceArns:Ljava/util/List;
       8: aload_0
       9: areturn

  public final software.amazon.awssdk.services.waf.model.ListResourcesForWebAclResponse$Builder resourceArns(java.lang.String...);
    Code:
       0: aload_0
       1: aload_1
       2: invokestatic  #11                 // Method java/util/Arrays.asList:([Ljava/lang/Object;)Ljava/util/List;
       5: invokevirtual #8                  // Method resourceArns:(Ljava/util/Collection;)Lsoftware/amazon/awssdk/services/waf/model/ListResourcesForWebAclResponse$Builder;
       8: pop
       9: aload_0
      10: areturn

  public software.amazon.awssdk.services.waf.model.ListResourcesForWebAclResponse build();
    Code:
       0: new           #12                 // class software/amazon/awssdk/services/waf/model/ListResourcesForWebAclResponse
       3: dup
       4: aload_0
       5: aconst_null
       6: invokespecial #13                 // Method software/amazon/awssdk/services/waf/model/ListResourcesForWebAclResponse."<init>":(Lsoftware/amazon/awssdk/services/waf/model/ListResourcesForWebAclResponse$BuilderImpl;Lsoftware/amazon/awssdk/services/waf/model/ListResourcesForWebAclResponse$1;)V
       9: areturn

  public java.util.List<software.amazon.awssdk.core.SdkField<?>> sdkFields();
    Code:
       0: invokestatic  #14                 // Method software/amazon/awssdk/services/waf/model/ListResourcesForWebAclResponse.access$500:()Ljava/util/List;
       3: areturn

  public software.amazon.awssdk.services.waf.model.WafResponse build();
    Code:
       0: aload_0
       1: invokevirtual #15                 // Method build:()Lsoftware/amazon/awssdk/services/waf/model/ListResourcesForWebAclResponse;
       4: areturn

  public software.amazon.awssdk.awscore.AwsResponse build();
    Code:
       0: aload_0
       1: invokevirtual #15                 // Method build:()Lsoftware/amazon/awssdk/services/waf/model/ListResourcesForWebAclResponse;
       4: areturn

  public software.amazon.awssdk.core.SdkResponse build();
    Code:
       0: aload_0
       1: invokevirtual #15                 // Method build:()Lsoftware/amazon/awssdk/services/waf/model/ListResourcesForWebAclResponse;
       4: areturn

  public java.lang.Object build();
    Code:
       0: aload_0
       1: invokevirtual #15                 // Method build:()Lsoftware/amazon/awssdk/services/waf/model/ListResourcesForWebAclResponse;
       4: areturn

  static java.util.List access$000(software.amazon.awssdk.services.waf.model.ListResourcesForWebAclResponse$BuilderImpl);
    Code:
       0: aload_0
       1: getfield      #3                  // Field resourceArns:Ljava/util/List;
       4: areturn

  software.amazon.awssdk.services.waf.model.ListResourcesForWebAclResponse$BuilderImpl(software.amazon.awssdk.services.waf.model.ListResourcesForWebAclResponse, software.amazon.awssdk.services.waf.model.ListResourcesForWebAclResponse$1);
    Code:
       0: aload_0
       1: aload_1
       2: invokespecial #2                  // Method "<init>":(Lsoftware/amazon/awssdk/services/waf/model/ListResourcesForWebAclResponse;)V
       5: return

  software.amazon.awssdk.services.waf.model.ListResourcesForWebAclResponse$BuilderImpl(software.amazon.awssdk.services.waf.model.ListResourcesForWebAclResponse$1);
    Code:
       0: aload_0
       1: invokespecial #1                  // Method "<init>":()V
       4: return
}
