Compiled from "ParameterExceptionField.java"
public final class software.amazon.awssdk.services.waf.model.ParameterExceptionField extends java.lang.Enum<software.amazon.awssdk.services.waf.model.ParameterExceptionField> {
  public static final software.amazon.awssdk.services.waf.model.ParameterExceptionField CHANGE_ACTION;

  public static final software.amazon.awssdk.services.waf.model.ParameterExceptionField WAF_ACTION;

  public static final software.amazon.awssdk.services.waf.model.ParameterExceptionField WAF_OVERRIDE_ACTION;

  public static final software.amazon.awssdk.services.waf.model.ParameterExceptionField PREDICATE_TYPE;

  public static final software.amazon.awssdk.services.waf.model.ParameterExceptionField IPSET_TYPE;

  public static final software.amazon.awssdk.services.waf.model.ParameterExceptionField BYTE_MATCH_FIELD_TYPE;

  public static final software.amazon.awssdk.services.waf.model.ParameterExceptionField SQL_INJECTION_MATCH_FIELD_TYPE;

  public static final software.amazon.awssdk.services.waf.model.ParameterExceptionField BYTE_MATCH_TEXT_TRANSFORMATION;

  public static final software.amazon.awssdk.services.waf.model.ParameterExceptionField BYTE_MATCH_POSITIONAL_CONSTRAINT;

  public static final software.amazon.awssdk.services.waf.model.ParameterExceptionField SIZE_CONSTRAINT_COMPARISON_OPERATOR;

  public static final software.amazon.awssdk.services.waf.model.ParameterExceptionField GEO_MATCH_LOCATION_TYPE;

  public static final software.amazon.awssdk.services.waf.model.ParameterExceptionField GEO_MATCH_LOCATION_VALUE;

  public static final software.amazon.awssdk.services.waf.model.ParameterExceptionField RATE_KEY;

  public static final software.amazon.awssdk.services.waf.model.ParameterExceptionField RULE_TYPE;

  public static final software.amazon.awssdk.services.waf.model.ParameterExceptionField NEXT_MARKER;

  public static final software.amazon.awssdk.services.waf.model.ParameterExceptionField RESOURCE_ARN;

  public static final software.amazon.awssdk.services.waf.model.ParameterExceptionField TAGS;

  public static final software.amazon.awssdk.services.waf.model.ParameterExceptionField TAG_KEYS;

  public static final software.amazon.awssdk.services.waf.model.ParameterExceptionField UNKNOWN_TO_SDK_VERSION;

  private static final java.util.Map<java.lang.String, software.amazon.awssdk.services.waf.model.ParameterExceptionField> VALUE_MAP;

  private final java.lang.String value;

  private static final software.amazon.awssdk.services.waf.model.ParameterExceptionField[] $VALUES;

  public static software.amazon.awssdk.services.waf.model.ParameterExceptionField[] values();
    Code:
       0: getstatic     #1                  // Field $VALUES:[Lsoftware/amazon/awssdk/services/waf/model/ParameterExceptionField;
       3: invokevirtual #2                  // Method "[Lsoftware/amazon/awssdk/services/waf/model/ParameterExceptionField;".clone:()Ljava/lang/Object;
       6: checkcast     #3                  // class "[Lsoftware/amazon/awssdk/services/waf/model/ParameterExceptionField;"
       9: areturn

  public static software.amazon.awssdk.services.waf.model.ParameterExceptionField valueOf(java.lang.String);
    Code:
       0: ldc           #4                  // class software/amazon/awssdk/services/waf/model/ParameterExceptionField
       2: aload_0
       3: invokestatic  #5                  // Method java/lang/Enum.valueOf:(Ljava/lang/Class;Ljava/lang/String;)Ljava/lang/Enum;
       6: checkcast     #4                  // class software/amazon/awssdk/services/waf/model/ParameterExceptionField
       9: areturn

  private software.amazon.awssdk.services.waf.model.ParameterExceptionField(java.lang.String);
    Code:
       0: aload_0
       1: aload_1
       2: iload_2
       3: invokespecial #6                  // Method java/lang/Enum."<init>":(Ljava/lang/String;I)V
       6: aload_0
       7: aload_3
       8: putfield      #7                  // Field value:Ljava/lang/String;
      11: return

  public java.lang.String toString();
    Code:
       0: aload_0
       1: getfield      #7                  // Field value:Ljava/lang/String;
       4: invokestatic  #8                  // Method java/lang/String.valueOf:(Ljava/lang/Object;)Ljava/lang/String;
       7: areturn

  public static software.amazon.awssdk.services.waf.model.ParameterExceptionField fromValue(java.lang.String);
    Code:
       0: aload_0
       1: ifnonnull     6
       4: aconst_null
       5: areturn
       6: getstatic     #9                  // Field VALUE_MAP:Ljava/util/Map;
       9: aload_0
      10: getstatic     #10                 // Field UNKNOWN_TO_SDK_VERSION:Lsoftware/amazon/awssdk/services/waf/model/ParameterExceptionField;
      13: invokeinterface #11,  3           // InterfaceMethod java/util/Map.getOrDefault:(Ljava/lang/Object;Ljava/lang/Object;)Ljava/lang/Object;
      18: checkcast     #4                  // class software/amazon/awssdk/services/waf/model/ParameterExceptionField
      21: areturn

  public static java.util.Set<software.amazon.awssdk.services.waf.model.ParameterExceptionField> knownValues();
    Code:
       0: ldc           #4                  // class software/amazon/awssdk/services/waf/model/ParameterExceptionField
       2: invokestatic  #12                 // Method java/util/EnumSet.allOf:(Ljava/lang/Class;)Ljava/util/EnumSet;
       5: astore_0
       6: aload_0
       7: getstatic     #10                 // Field UNKNOWN_TO_SDK_VERSION:Lsoftware/amazon/awssdk/services/waf/model/ParameterExceptionField;
      10: invokeinterface #13,  2           // InterfaceMethod java/util/Set.remove:(Ljava/lang/Object;)Z
      15: pop
      16: aload_0
      17: areturn

  static {};
    Code:
       0: new           #4                  // class software/amazon/awssdk/services/waf/model/ParameterExceptionField
       3: dup
       4: ldc           #14                 // String CHANGE_ACTION
       6: iconst_0
       7: ldc           #14                 // String CHANGE_ACTION
       9: invokespecial #15                 // Method "<init>":(Ljava/lang/String;ILjava/lang/String;)V
      12: putstatic     #16                 // Field CHANGE_ACTION:Lsoftware/amazon/awssdk/services/waf/model/ParameterExceptionField;
      15: new           #4                  // class software/amazon/awssdk/services/waf/model/ParameterExceptionField
      18: dup
      19: ldc           #17                 // String WAF_ACTION
      21: iconst_1
      22: ldc           #17                 // String WAF_ACTION
      24: invokespecial #15                 // Method "<init>":(Ljava/lang/String;ILjava/lang/String;)V
      27: putstatic     #18                 // Field WAF_ACTION:Lsoftware/amazon/awssdk/services/waf/model/ParameterExceptionField;
      30: new           #4                  // class software/amazon/awssdk/services/waf/model/ParameterExceptionField
      33: dup
      34: ldc           #19                 // String WAF_OVERRIDE_ACTION
      36: iconst_2
      37: ldc           #19                 // String WAF_OVERRIDE_ACTION
      39: invokespecial #15                 // Method "<init>":(Ljava/lang/String;ILjava/lang/String;)V
      42: putstatic     #20                 // Field WAF_OVERRIDE_ACTION:Lsoftware/amazon/awssdk/services/waf/model/ParameterExceptionField;
      45: new           #4                  // class software/amazon/awssdk/services/waf/model/ParameterExceptionField
      48: dup
      49: ldc           #21                 // String PREDICATE_TYPE
      51: iconst_3
      52: ldc           #21                 // String PREDICATE_TYPE
      54: invokespecial #15                 // Method "<init>":(Ljava/lang/String;ILjava/lang/String;)V
      57: putstatic     #22                 // Field PREDICATE_TYPE:Lsoftware/amazon/awssdk/services/waf/model/ParameterExceptionField;
      60: new           #4                  // class software/amazon/awssdk/services/waf/model/ParameterExceptionField
      63: dup
      64: ldc           #23                 // String IPSET_TYPE
      66: iconst_4
      67: ldc           #23                 // String IPSET_TYPE
      69: invokespecial #15                 // Method "<init>":(Ljava/lang/String;ILjava/lang/String;)V
      72: putstatic     #24                 // Field IPSET_TYPE:Lsoftware/amazon/awssdk/services/waf/model/ParameterExceptionField;
      75: new           #4                  // class software/amazon/awssdk/services/waf/model/ParameterExceptionField
      78: dup
      79: ldc           #25                 // String BYTE_MATCH_FIELD_TYPE
      81: iconst_5
      82: ldc           #25                 // String BYTE_MATCH_FIELD_TYPE
      84: invokespecial #15                 // Method "<init>":(Ljava/lang/String;ILjava/lang/String;)V
      87: putstatic     #26                 // Field BYTE_MATCH_FIELD_TYPE:Lsoftware/amazon/awssdk/services/waf/model/ParameterExceptionField;
      90: new           #4                  // class software/amazon/awssdk/services/waf/model/ParameterExceptionField
      93: dup
      94: ldc           #27                 // String SQL_INJECTION_MATCH_FIELD_TYPE
      96: bipush        6
      98: ldc           #27                 // String SQL_INJECTION_MATCH_FIELD_TYPE
     100: invokespecial #15                 // Method "<init>":(Ljava/lang/String;ILjava/lang/String;)V
     103: putstatic     #28                 // Field SQL_INJECTION_MATCH_FIELD_TYPE:Lsoftware/amazon/awssdk/services/waf/model/ParameterExceptionField;
     106: new           #4                  // class software/amazon/awssdk/services/waf/model/ParameterExceptionField
     109: dup
     110: ldc           #29                 // String BYTE_MATCH_TEXT_TRANSFORMATION
     112: bipush        7
     114: ldc           #29                 // String BYTE_MATCH_TEXT_TRANSFORMATION
     116: invokespecial #15                 // Method "<init>":(Ljava/lang/String;ILjava/lang/String;)V
     119: putstatic     #30                 // Field BYTE_MATCH_TEXT_TRANSFORMATION:Lsoftware/amazon/awssdk/services/waf/model/ParameterExceptionField;
     122: new           #4                  // class software/amazon/awssdk/services/waf/model/ParameterExceptionField
     125: dup
     126: ldc           #31                 // String BYTE_MATCH_POSITIONAL_CONSTRAINT
     128: bipush        8
     130: ldc           #31                 // String BYTE_MATCH_POSITIONAL_CONSTRAINT
     132: invokespecial #15                 // Method "<init>":(Ljava/lang/String;ILjava/lang/String;)V
     135: putstatic     #32                 // Field BYTE_MATCH_POSITIONAL_CONSTRAINT:Lsoftware/amazon/awssdk/services/waf/model/ParameterExceptionField;
     138: new           #4                  // class software/amazon/awssdk/services/waf/model/ParameterExceptionField
     141: dup
     142: ldc           #33                 // String SIZE_CONSTRAINT_COMPARISON_OPERATOR
     144: bipush        9
     146: ldc           #33                 // String SIZE_CONSTRAINT_COMPARISON_OPERATOR
     148: invokespecial #15                 // Method "<init>":(Ljava/lang/String;ILjava/lang/String;)V
     151: putstatic     #34                 // Field SIZE_CONSTRAINT_COMPARISON_OPERATOR:Lsoftware/amazon/awssdk/services/waf/model/ParameterExceptionField;
     154: new           #4                  // class software/amazon/awssdk/services/waf/model/ParameterExceptionField
     157: dup
     158: ldc           #35                 // String GEO_MATCH_LOCATION_TYPE
     160: bipush        10
     162: ldc           #35                 // String GEO_MATCH_LOCATION_TYPE
     164: invokespecial #15                 // Method "<init>":(Ljava/lang/String;ILjava/lang/String;)V
     167: putstatic     #36                 // Field GEO_MATCH_LOCATION_TYPE:Lsoftware/amazon/awssdk/services/waf/model/ParameterExceptionField;
     170: new           #4                  // class software/amazon/awssdk/services/waf/model/ParameterExceptionField
     173: dup
     174: ldc           #37                 // String GEO_MATCH_LOCATION_VALUE
     176: bipush        11
     178: ldc           #37                 // String GEO_MATCH_LOCATION_VALUE
     180: invokespecial #15                 // Method "<init>":(Ljava/lang/String;ILjava/lang/String;)V
     183: putstatic     #38                 // Field GEO_MATCH_LOCATION_VALUE:Lsoftware/amazon/awssdk/services/waf/model/ParameterExceptionField;
     186: new           #4                  // class software/amazon/awssdk/services/waf/model/ParameterExceptionField
     189: dup
     190: ldc           #39                 // String RATE_KEY
     192: bipush        12
     194: ldc           #39                 // String RATE_KEY
     196: invokespecial #15                 // Method "<init>":(Ljava/lang/String;ILjava/lang/String;)V
     199: putstatic     #40                 // Field RATE_KEY:Lsoftware/amazon/awssdk/services/waf/model/ParameterExceptionField;
     202: new           #4                  // class software/amazon/awssdk/services/waf/model/ParameterExceptionField
     205: dup
     206: ldc           #41                 // String RULE_TYPE
     208: bipush        13
     210: ldc           #41                 // String RULE_TYPE
     212: invokespecial #15                 // Method "<init>":(Ljava/lang/String;ILjava/lang/String;)V
     215: putstatic     #42                 // Field RULE_TYPE:Lsoftware/amazon/awssdk/services/waf/model/ParameterExceptionField;
     218: new           #4                  // class software/amazon/awssdk/services/waf/model/ParameterExceptionField
     221: dup
     222: ldc           #43                 // String NEXT_MARKER
     224: bipush        14
     226: ldc           #43                 // String NEXT_MARKER
     228: invokespecial #15                 // Method "<init>":(Ljava/lang/String;ILjava/lang/String;)V
     231: putstatic     #44                 // Field NEXT_MARKER:Lsoftware/amazon/awssdk/services/waf/model/ParameterExceptionField;
     234: new           #4                  // class software/amazon/awssdk/services/waf/model/ParameterExceptionField
     237: dup
     238: ldc           #45                 // String RESOURCE_ARN
     240: bipush        15
     242: ldc           #45                 // String RESOURCE_ARN
     244: invokespecial #15                 // Method "<init>":(Ljava/lang/String;ILjava/lang/String;)V
     247: putstatic     #46                 // Field RESOURCE_ARN:Lsoftware/amazon/awssdk/services/waf/model/ParameterExceptionField;
     250: new           #4                  // class software/amazon/awssdk/services/waf/model/ParameterExceptionField
     253: dup
     254: ldc           #47                 // String TAGS
     256: bipush        16
     258: ldc           #47                 // String TAGS
     260: invokespecial #15                 // Method "<init>":(Ljava/lang/String;ILjava/lang/String;)V
     263: putstatic     #48                 // Field TAGS:Lsoftware/amazon/awssdk/services/waf/model/ParameterExceptionField;
     266: new           #4                  // class software/amazon/awssdk/services/waf/model/ParameterExceptionField
     269: dup
     270: ldc           #49                 // String TAG_KEYS
     272: bipush        17
     274: ldc           #49                 // String TAG_KEYS
     276: invokespecial #15                 // Method "<init>":(Ljava/lang/String;ILjava/lang/String;)V
     279: putstatic     #50                 // Field TAG_KEYS:Lsoftware/amazon/awssdk/services/waf/model/ParameterExceptionField;
     282: new           #4                  // class software/amazon/awssdk/services/waf/model/ParameterExceptionField
     285: dup
     286: ldc           #51                 // String UNKNOWN_TO_SDK_VERSION
     288: bipush        18
     290: aconst_null
     291: invokespecial #15                 // Method "<init>":(Ljava/lang/String;ILjava/lang/String;)V
     294: putstatic     #10                 // Field UNKNOWN_TO_SDK_VERSION:Lsoftware/amazon/awssdk/services/waf/model/ParameterExceptionField;
     297: bipush        19
     299: anewarray     #4                  // class software/amazon/awssdk/services/waf/model/ParameterExceptionField
     302: dup
     303: iconst_0
     304: getstatic     #16                 // Field CHANGE_ACTION:Lsoftware/amazon/awssdk/services/waf/model/ParameterExceptionField;
     307: aastore
     308: dup
     309: iconst_1
     310: getstatic     #18                 // Field WAF_ACTION:Lsoftware/amazon/awssdk/services/waf/model/ParameterExceptionField;
     313: aastore
     314: dup
     315: iconst_2
     316: getstatic     #20                 // Field WAF_OVERRIDE_ACTION:Lsoftware/amazon/awssdk/services/waf/model/ParameterExceptionField;
     319: aastore
     320: dup
     321: iconst_3
     322: getstatic     #22                 // Field PREDICATE_TYPE:Lsoftware/amazon/awssdk/services/waf/model/ParameterExceptionField;
     325: aastore
     326: dup
     327: iconst_4
     328: getstatic     #24                 // Field IPSET_TYPE:Lsoftware/amazon/awssdk/services/waf/model/ParameterExceptionField;
     331: aastore
     332: dup
     333: iconst_5
     334: getstatic     #26                 // Field BYTE_MATCH_FIELD_TYPE:Lsoftware/amazon/awssdk/services/waf/model/ParameterExceptionField;
     337: aastore
     338: dup
     339: bipush        6
     341: getstatic     #28                 // Field SQL_INJECTION_MATCH_FIELD_TYPE:Lsoftware/amazon/awssdk/services/waf/model/ParameterExceptionField;
     344: aastore
     345: dup
     346: bipush        7
     348: getstatic     #30                 // Field BYTE_MATCH_TEXT_TRANSFORMATION:Lsoftware/amazon/awssdk/services/waf/model/ParameterExceptionField;
     351: aastore
     352: dup
     353: bipush        8
     355: getstatic     #32                 // Field BYTE_MATCH_POSITIONAL_CONSTRAINT:Lsoftware/amazon/awssdk/services/waf/model/ParameterExceptionField;
     358: aastore
     359: dup
     360: bipush        9
     362: getstatic     #34                 // Field SIZE_CONSTRAINT_COMPARISON_OPERATOR:Lsoftware/amazon/awssdk/services/waf/model/ParameterExceptionField;
     365: aastore
     366: dup
     367: bipush        10
     369: getstatic     #36                 // Field GEO_MATCH_LOCATION_TYPE:Lsoftware/amazon/awssdk/services/waf/model/ParameterExceptionField;
     372: aastore
     373: dup
     374: bipush        11
     376: getstatic     #38                 // Field GEO_MATCH_LOCATION_VALUE:Lsoftware/amazon/awssdk/services/waf/model/ParameterExceptionField;
     379: aastore
     380: dup
     381: bipush        12
     383: getstatic     #40                 // Field RATE_KEY:Lsoftware/amazon/awssdk/services/waf/model/ParameterExceptionField;
     386: aastore
     387: dup
     388: bipush        13
     390: getstatic     #42                 // Field RULE_TYPE:Lsoftware/amazon/awssdk/services/waf/model/ParameterExceptionField;
     393: aastore
     394: dup
     395: bipush        14
     397: getstatic     #44                 // Field NEXT_MARKER:Lsoftware/amazon/awssdk/services/waf/model/ParameterExceptionField;
     400: aastore
     401: dup
     402: bipush        15
     404: getstatic     #46                 // Field RESOURCE_ARN:Lsoftware/amazon/awssdk/services/waf/model/ParameterExceptionField;
     407: aastore
     408: dup
     409: bipush        16
     411: getstatic     #48                 // Field TAGS:Lsoftware/amazon/awssdk/services/waf/model/ParameterExceptionField;
     414: aastore
     415: dup
     416: bipush        17
     418: getstatic     #50                 // Field TAG_KEYS:Lsoftware/amazon/awssdk/services/waf/model/ParameterExceptionField;
     421: aastore
     422: dup
     423: bipush        18
     425: getstatic     #10                 // Field UNKNOWN_TO_SDK_VERSION:Lsoftware/amazon/awssdk/services/waf/model/ParameterExceptionField;
     428: aastore
     429: putstatic     #1                  // Field $VALUES:[Lsoftware/amazon/awssdk/services/waf/model/ParameterExceptionField;
     432: ldc           #4                  // class software/amazon/awssdk/services/waf/model/ParameterExceptionField
     434: invokedynamic #52,  0             // InvokeDynamic #0:apply:()Ljava/util/function/Function;
     439: invokestatic  #53                 // Method software/amazon/awssdk/utils/internal/EnumUtils.uniqueIndex:(Ljava/lang/Class;Ljava/util/function/Function;)Ljava/util/Map;
     442: putstatic     #9                  // Field VALUE_MAP:Ljava/util/Map;
     445: return
}
