Compiled from "DisconnectMessage.java"
public class org.apache.activemq.artemis.core.protocol.core.impl.wireformat.DisconnectMessage extends org.apache.activemq.artemis.core.protocol.core.impl.PacketImpl {
  protected org.apache.activemq.artemis.api.core.SimpleString nodeID;

  public org.apache.activemq.artemis.core.protocol.core.impl.wireformat.DisconnectMessage(org.apache.activemq.artemis.api.core.SimpleString);
    Code:
       0: aload_0
       1: bipush        11
       3: invokespecial #2                  // Method org/apache/activemq/artemis/core/protocol/core/impl/PacketImpl."<init>":(B)V
       6: aload_0
       7: aload_1
       8: putfield      #3                  // Field nodeID:Lorg/apache/activemq/artemis/api/core/SimpleString;
      11: return

  public org.apache.activemq.artemis.core.protocol.core.impl.wireformat.DisconnectMessage();
    Code:
       0: aload_0
       1: bipush        11
       3: invokespecial #2                  // Method org/apache/activemq/artemis/core/protocol/core/impl/PacketImpl."<init>":(B)V
       6: return

  public org.apache.activemq.artemis.core.protocol.core.impl.wireformat.DisconnectMessage(byte);
    Code:
       0: aload_0
       1: iload_1
       2: invokespecial #2                  // Method org/apache/activemq/artemis/core/protocol/core/impl/PacketImpl."<init>":(B)V
       5: return

  public org.apache.activemq.artemis.api.core.SimpleString getNodeID();
    Code:
       0: aload_0
       1: getfield      #3                  // Field nodeID:Lorg/apache/activemq/artemis/api/core/SimpleString;
       4: areturn

  public void encodeRest(org.apache.activemq.artemis.api.core.ActiveMQBuffer);
    Code:
       0: aload_1
       1: aload_0
       2: getfield      #3                  // Field nodeID:Lorg/apache/activemq/artemis/api/core/SimpleString;
       5: invokeinterface #4,  2            // InterfaceMethod org/apache/activemq/artemis/api/core/ActiveMQBuffer.writeNullableSimpleString:(Lorg/apache/activemq/artemis/api/core/SimpleString;)V
      10: return

  public void decodeRest(org.apache.activemq.artemis.api.core.ActiveMQBuffer);
    Code:
       0: aload_0
       1: aload_1
       2: invokeinterface #5,  1            // InterfaceMethod org/apache/activemq/artemis/api/core/ActiveMQBuffer.readNullableSimpleString:()Lorg/apache/activemq/artemis/api/core/SimpleString;
       7: putfield      #3                  // Field nodeID:Lorg/apache/activemq/artemis/api/core/SimpleString;
      10: return

  public java.lang.String toString();
    Code:
       0: new           #6                  // class java/lang/StringBuffer
       3: dup
       4: aload_0
       5: invokevirtual #7                  // Method getParentString:()Ljava/lang/String;
       8: invokespecial #8                  // Method java/lang/StringBuffer."<init>":(Ljava/lang/String;)V
      11: astore_1
      12: aload_1
      13: new           #9                  // class java/lang/StringBuilder
      16: dup
      17: invokespecial #10                 // Method java/lang/StringBuilder."<init>":()V
      20: ldc           #11                 // String , nodeID=
      22: invokevirtual #12                 // Method java/lang/StringBuilder.append:(Ljava/lang/String;)Ljava/lang/StringBuilder;
      25: aload_0
      26: getfield      #3                  // Field nodeID:Lorg/apache/activemq/artemis/api/core/SimpleString;
      29: invokevirtual #13                 // Method java/lang/StringBuilder.append:(Ljava/lang/Object;)Ljava/lang/StringBuilder;
      32: invokevirtual #14                 // Method java/lang/StringBuilder.toString:()Ljava/lang/String;
      35: invokevirtual #15                 // Method java/lang/StringBuffer.append:(Ljava/lang/String;)Ljava/lang/StringBuffer;
      38: pop
      39: aload_1
      40: ldc           #16                 // String ]
      42: invokevirtual #15                 // Method java/lang/StringBuffer.append:(Ljava/lang/String;)Ljava/lang/StringBuffer;
      45: pop
      46: aload_1
      47: invokevirtual #17                 // Method java/lang/StringBuffer.toString:()Ljava/lang/String;
      50: areturn

  public final boolean isRequiresConfirmations();
    Code:
       0: iconst_0
       1: ireturn

  public int hashCode();
    Code:
       0: bipush        31
       2: istore_1
       3: aload_0
       4: invokespecial #18                 // Method org/apache/activemq/artemis/core/protocol/core/impl/PacketImpl.hashCode:()I
       7: istore_2
       8: bipush        31
      10: iload_2
      11: imul
      12: aload_0
      13: getfield      #3                  // Field nodeID:Lorg/apache/activemq/artemis/api/core/SimpleString;
      16: ifnonnull     23
      19: iconst_0
      20: goto          30
      23: aload_0
      24: getfield      #3                  // Field nodeID:Lorg/apache/activemq/artemis/api/core/SimpleString;
      27: invokevirtual #19                 // Method org/apache/activemq/artemis/api/core/SimpleString.hashCode:()I
      30: iadd
      31: istore_2
      32: iload_2
      33: ireturn

  public boolean equals(java.lang.Object);
    Code:
       0: aload_0
       1: aload_1
       2: if_acmpne     7
       5: iconst_1
       6: ireturn
       7: aload_0
       8: aload_1
       9: invokespecial #20                 // Method org/apache/activemq/artemis/core/protocol/core/impl/PacketImpl.equals:(Ljava/lang/Object;)Z
      12: ifne          17
      15: iconst_0
      16: ireturn
      17: aload_1
      18: instanceof    #21                 // class org/apache/activemq/artemis/core/protocol/core/impl/wireformat/DisconnectMessage
      21: ifne          26
      24: iconst_0
      25: ireturn
      26: aload_1
      27: checkcast     #21                 // class org/apache/activemq/artemis/core/protocol/core/impl/wireformat/DisconnectMessage
      30: astore_2
      31: aload_0
      32: getfield      #3                  // Field nodeID:Lorg/apache/activemq/artemis/api/core/SimpleString;
      35: ifnonnull     47
      38: aload_2
      39: getfield      #3                  // Field nodeID:Lorg/apache/activemq/artemis/api/core/SimpleString;
      42: ifnull        63
      45: iconst_0
      46: ireturn
      47: aload_0
      48: getfield      #3                  // Field nodeID:Lorg/apache/activemq/artemis/api/core/SimpleString;
      51: aload_2
      52: getfield      #3                  // Field nodeID:Lorg/apache/activemq/artemis/api/core/SimpleString;
      55: invokevirtual #22                 // Method org/apache/activemq/artemis/api/core/SimpleString.equals:(Ljava/lang/Object;)Z
      58: ifne          63
      61: iconst_0
      62: ireturn
      63: iconst_1
      64: ireturn
}
