Compiled from "SessionQueueQueryResponseMessage.java"
public class org.apache.activemq.artemis.core.protocol.core.impl.wireformat.SessionQueueQueryResponseMessage extends org.apache.activemq.artemis.core.protocol.core.impl.PacketImpl {
  protected org.apache.activemq.artemis.api.core.SimpleString name;

  protected boolean exists;

  protected boolean durable;

  protected int consumerCount;

  protected long messageCount;

  protected org.apache.activemq.artemis.api.core.SimpleString filterString;

  protected org.apache.activemq.artemis.api.core.SimpleString address;

  protected boolean temporary;

  public org.apache.activemq.artemis.core.protocol.core.impl.wireformat.SessionQueueQueryResponseMessage(org.apache.activemq.artemis.core.server.QueueQueryResult);
    Code:
       0: aload_0
       1: aload_1
       2: invokevirtual #1                  // Method org/apache/activemq/artemis/core/server/QueueQueryResult.getName:()Lorg/apache/activemq/artemis/api/core/SimpleString;
       5: aload_1
       6: invokevirtual #2                  // Method org/apache/activemq/artemis/core/server/QueueQueryResult.getAddress:()Lorg/apache/activemq/artemis/api/core/SimpleString;
       9: aload_1
      10: invokevirtual #3                  // Method org/apache/activemq/artemis/core/server/QueueQueryResult.isDurable:()Z
      13: aload_1
      14: invokevirtual #4                  // Method org/apache/activemq/artemis/core/server/QueueQueryResult.isTemporary:()Z
      17: aload_1
      18: invokevirtual #5                  // Method org/apache/activemq/artemis/core/server/QueueQueryResult.getFilterString:()Lorg/apache/activemq/artemis/api/core/SimpleString;
      21: aload_1
      22: invokevirtual #6                  // Method org/apache/activemq/artemis/core/server/QueueQueryResult.getConsumerCount:()I
      25: aload_1
      26: invokevirtual #7                  // Method org/apache/activemq/artemis/core/server/QueueQueryResult.getMessageCount:()J
      29: aload_1
      30: invokevirtual #8                  // Method org/apache/activemq/artemis/core/server/QueueQueryResult.isExists:()Z
      33: invokespecial #9                  // Method "<init>":(Lorg/apache/activemq/artemis/api/core/SimpleString;Lorg/apache/activemq/artemis/api/core/SimpleString;ZZLorg/apache/activemq/artemis/api/core/SimpleString;IJZ)V
      36: return

  public org.apache.activemq.artemis.core.protocol.core.impl.wireformat.SessionQueueQueryResponseMessage();
    Code:
       0: aload_0
       1: aconst_null
       2: aconst_null
       3: iconst_0
       4: iconst_0
       5: aconst_null
       6: iconst_0
       7: lconst_0
       8: iconst_0
       9: invokespecial #9                  // Method "<init>":(Lorg/apache/activemq/artemis/api/core/SimpleString;Lorg/apache/activemq/artemis/api/core/SimpleString;ZZLorg/apache/activemq/artemis/api/core/SimpleString;IJZ)V
      12: return

  public org.apache.activemq.artemis.core.protocol.core.impl.wireformat.SessionQueueQueryResponseMessage(byte);
    Code:
       0: aload_0
       1: iload_1
       2: invokespecial #10                 // Method org/apache/activemq/artemis/core/protocol/core/impl/PacketImpl."<init>":(B)V
       5: return

  private org.apache.activemq.artemis.core.protocol.core.impl.wireformat.SessionQueueQueryResponseMessage(org.apache.activemq.artemis.api.core.SimpleString, org.apache.activemq.artemis.api.core.SimpleString, boolean, boolean, org.apache.activemq.artemis.api.core.SimpleString, int, long, boolean);
    Code:
       0: aload_0
       1: bipush        46
       3: invokespecial #10                 // Method org/apache/activemq/artemis/core/protocol/core/impl/PacketImpl."<init>":(B)V
       6: aload_0
       7: iload_3
       8: putfield      #12                 // Field durable:Z
      11: aload_0
      12: iload         4
      14: putfield      #13                 // Field temporary:Z
      17: aload_0
      18: iload         6
      20: putfield      #14                 // Field consumerCount:I
      23: aload_0
      24: lload         7
      26: putfield      #15                 // Field messageCount:J
      29: aload_0
      30: aload         5
      32: putfield      #16                 // Field filterString:Lorg/apache/activemq/artemis/api/core/SimpleString;
      35: aload_0
      36: aload_2
      37: putfield      #17                 // Field address:Lorg/apache/activemq/artemis/api/core/SimpleString;
      40: aload_0
      41: aload_1
      42: putfield      #18                 // Field name:Lorg/apache/activemq/artemis/api/core/SimpleString;
      45: aload_0
      46: iload         9
      48: putfield      #19                 // Field exists:Z
      51: return

  public boolean isResponse();
    Code:
       0: iconst_1
       1: ireturn

  public boolean isExists();
    Code:
       0: aload_0
       1: getfield      #19                 // Field exists:Z
       4: ireturn

  public boolean isDurable();
    Code:
       0: aload_0
       1: getfield      #12                 // Field durable:Z
       4: ireturn

  public int getConsumerCount();
    Code:
       0: aload_0
       1: getfield      #14                 // Field consumerCount:I
       4: ireturn

  public long getMessageCount();
    Code:
       0: aload_0
       1: getfield      #15                 // Field messageCount:J
       4: lreturn

  public org.apache.activemq.artemis.api.core.SimpleString getFilterString();
    Code:
       0: aload_0
       1: getfield      #16                 // Field filterString:Lorg/apache/activemq/artemis/api/core/SimpleString;
       4: areturn

  public org.apache.activemq.artemis.api.core.SimpleString getAddress();
    Code:
       0: aload_0
       1: getfield      #17                 // Field address:Lorg/apache/activemq/artemis/api/core/SimpleString;
       4: areturn

  public org.apache.activemq.artemis.api.core.SimpleString getName();
    Code:
       0: aload_0
       1: getfield      #18                 // Field name:Lorg/apache/activemq/artemis/api/core/SimpleString;
       4: areturn

  public boolean isTemporary();
    Code:
       0: aload_0
       1: getfield      #13                 // Field temporary:Z
       4: ireturn

  public void encodeRest(org.apache.activemq.artemis.api.core.ActiveMQBuffer);
    Code:
       0: aload_1
       1: aload_0
       2: getfield      #19                 // Field exists:Z
       5: invokeinterface #20,  2           // InterfaceMethod org/apache/activemq/artemis/api/core/ActiveMQBuffer.writeBoolean:(Z)V
      10: aload_1
      11: aload_0
      12: getfield      #12                 // Field durable:Z
      15: invokeinterface #20,  2           // InterfaceMethod org/apache/activemq/artemis/api/core/ActiveMQBuffer.writeBoolean:(Z)V
      20: aload_1
      21: aload_0
      22: getfield      #13                 // Field temporary:Z
      25: invokeinterface #20,  2           // InterfaceMethod org/apache/activemq/artemis/api/core/ActiveMQBuffer.writeBoolean:(Z)V
      30: aload_1
      31: aload_0
      32: getfield      #14                 // Field consumerCount:I
      35: invokeinterface #21,  2           // InterfaceMethod org/apache/activemq/artemis/api/core/ActiveMQBuffer.writeInt:(I)V
      40: aload_1
      41: aload_0
      42: getfield      #15                 // Field messageCount:J
      45: invokeinterface #22,  3           // InterfaceMethod org/apache/activemq/artemis/api/core/ActiveMQBuffer.writeLong:(J)V
      50: aload_1
      51: aload_0
      52: getfield      #16                 // Field filterString:Lorg/apache/activemq/artemis/api/core/SimpleString;
      55: invokeinterface #23,  2           // InterfaceMethod org/apache/activemq/artemis/api/core/ActiveMQBuffer.writeNullableSimpleString:(Lorg/apache/activemq/artemis/api/core/SimpleString;)V
      60: aload_1
      61: aload_0
      62: getfield      #17                 // Field address:Lorg/apache/activemq/artemis/api/core/SimpleString;
      65: invokeinterface #23,  2           // InterfaceMethod org/apache/activemq/artemis/api/core/ActiveMQBuffer.writeNullableSimpleString:(Lorg/apache/activemq/artemis/api/core/SimpleString;)V
      70: aload_1
      71: aload_0
      72: getfield      #18                 // Field name:Lorg/apache/activemq/artemis/api/core/SimpleString;
      75: invokeinterface #23,  2           // InterfaceMethod org/apache/activemq/artemis/api/core/ActiveMQBuffer.writeNullableSimpleString:(Lorg/apache/activemq/artemis/api/core/SimpleString;)V
      80: return

  public void decodeRest(org.apache.activemq.artemis.api.core.ActiveMQBuffer);
    Code:
       0: aload_0
       1: aload_1
       2: invokeinterface #24,  1           // InterfaceMethod org/apache/activemq/artemis/api/core/ActiveMQBuffer.readBoolean:()Z
       7: putfield      #19                 // Field exists:Z
      10: aload_0
      11: aload_1
      12: invokeinterface #24,  1           // InterfaceMethod org/apache/activemq/artemis/api/core/ActiveMQBuffer.readBoolean:()Z
      17: putfield      #12                 // Field durable:Z
      20: aload_0
      21: aload_1
      22: invokeinterface #24,  1           // InterfaceMethod org/apache/activemq/artemis/api/core/ActiveMQBuffer.readBoolean:()Z
      27: putfield      #13                 // Field temporary:Z
      30: aload_0
      31: aload_1
      32: invokeinterface #25,  1           // InterfaceMethod org/apache/activemq/artemis/api/core/ActiveMQBuffer.readInt:()I
      37: putfield      #14                 // Field consumerCount:I
      40: aload_0
      41: aload_1
      42: invokeinterface #26,  1           // InterfaceMethod org/apache/activemq/artemis/api/core/ActiveMQBuffer.readLong:()J
      47: putfield      #15                 // Field messageCount:J
      50: aload_0
      51: aload_1
      52: invokeinterface #27,  1           // InterfaceMethod org/apache/activemq/artemis/api/core/ActiveMQBuffer.readNullableSimpleString:()Lorg/apache/activemq/artemis/api/core/SimpleString;
      57: putfield      #16                 // Field filterString:Lorg/apache/activemq/artemis/api/core/SimpleString;
      60: aload_0
      61: aload_1
      62: invokeinterface #27,  1           // InterfaceMethod org/apache/activemq/artemis/api/core/ActiveMQBuffer.readNullableSimpleString:()Lorg/apache/activemq/artemis/api/core/SimpleString;
      67: putfield      #17                 // Field address:Lorg/apache/activemq/artemis/api/core/SimpleString;
      70: aload_0
      71: aload_1
      72: invokeinterface #27,  1           // InterfaceMethod org/apache/activemq/artemis/api/core/ActiveMQBuffer.readNullableSimpleString:()Lorg/apache/activemq/artemis/api/core/SimpleString;
      77: putfield      #18                 // Field name:Lorg/apache/activemq/artemis/api/core/SimpleString;
      80: return

  public int hashCode();
    Code:
       0: bipush        31
       2: istore_1
       3: aload_0
       4: invokespecial #28                 // Method org/apache/activemq/artemis/core/protocol/core/impl/PacketImpl.hashCode:()I
       7: istore_2
       8: bipush        31
      10: iload_2
      11: imul
      12: aload_0
      13: getfield      #17                 // Field address:Lorg/apache/activemq/artemis/api/core/SimpleString;
      16: ifnonnull     23
      19: iconst_0
      20: goto          30
      23: aload_0
      24: getfield      #17                 // Field address:Lorg/apache/activemq/artemis/api/core/SimpleString;
      27: invokevirtual #29                 // Method org/apache/activemq/artemis/api/core/SimpleString.hashCode:()I
      30: iadd
      31: istore_2
      32: bipush        31
      34: iload_2
      35: imul
      36: aload_0
      37: getfield      #14                 // Field consumerCount:I
      40: iadd
      41: istore_2
      42: bipush        31
      44: iload_2
      45: imul
      46: aload_0
      47: getfield      #12                 // Field durable:Z
      50: ifeq          59
      53: sipush        1231
      56: goto          62
      59: sipush        1237
      62: iadd
      63: istore_2
      64: bipush        31
      66: iload_2
      67: imul
      68: aload_0
      69: getfield      #19                 // Field exists:Z
      72: ifeq          81
      75: sipush        1231
      78: goto          84
      81: sipush        1237
      84: iadd
      85: istore_2
      86: bipush        31
      88: iload_2
      89: imul
      90: aload_0
      91: getfield      #16                 // Field filterString:Lorg/apache/activemq/artemis/api/core/SimpleString;
      94: ifnonnull     101
      97: iconst_0
      98: goto          108
     101: aload_0
     102: getfield      #16                 // Field filterString:Lorg/apache/activemq/artemis/api/core/SimpleString;
     105: invokevirtual #29                 // Method org/apache/activemq/artemis/api/core/SimpleString.hashCode:()I
     108: iadd
     109: istore_2
     110: bipush        31
     112: iload_2
     113: imul
     114: aload_0
     115: getfield      #15                 // Field messageCount:J
     118: aload_0
     119: getfield      #15                 // Field messageCount:J
     122: bipush        32
     124: lushr
     125: lxor
     126: l2i
     127: iadd
     128: istore_2
     129: bipush        31
     131: iload_2
     132: imul
     133: aload_0
     134: getfield      #18                 // Field name:Lorg/apache/activemq/artemis/api/core/SimpleString;
     137: ifnonnull     144
     140: iconst_0
     141: goto          151
     144: aload_0
     145: getfield      #18                 // Field name:Lorg/apache/activemq/artemis/api/core/SimpleString;
     148: invokevirtual #29                 // Method org/apache/activemq/artemis/api/core/SimpleString.hashCode:()I
     151: iadd
     152: istore_2
     153: bipush        31
     155: iload_2
     156: imul
     157: aload_0
     158: getfield      #13                 // Field temporary:Z
     161: ifeq          170
     164: sipush        1231
     167: goto          173
     170: sipush        1237
     173: iadd
     174: istore_2
     175: iload_2
     176: ireturn

  public org.apache.activemq.artemis.api.core.client.ClientSession$QueueQuery toQueueQuery();
    Code:
       0: new           #30                 // class org/apache/activemq/artemis/core/client/impl/QueueQueryImpl
       3: dup
       4: aload_0
       5: invokevirtual #31                 // Method isDurable:()Z
       8: aload_0
       9: invokevirtual #32                 // Method isTemporary:()Z
      12: aload_0
      13: invokevirtual #33                 // Method getConsumerCount:()I
      16: aload_0
      17: invokevirtual #34                 // Method getMessageCount:()J
      20: aload_0
      21: invokevirtual #35                 // Method getFilterString:()Lorg/apache/activemq/artemis/api/core/SimpleString;
      24: aload_0
      25: invokevirtual #36                 // Method getAddress:()Lorg/apache/activemq/artemis/api/core/SimpleString;
      28: aload_0
      29: invokevirtual #37                 // Method getName:()Lorg/apache/activemq/artemis/api/core/SimpleString;
      32: aload_0
      33: invokevirtual #38                 // Method isExists:()Z
      36: invokespecial #39                 // Method org/apache/activemq/artemis/core/client/impl/QueueQueryImpl."<init>":(ZZIJLorg/apache/activemq/artemis/api/core/SimpleString;Lorg/apache/activemq/artemis/api/core/SimpleString;Lorg/apache/activemq/artemis/api/core/SimpleString;Z)V
      39: areturn

  public boolean equals(java.lang.Object);
    Code:
       0: aload_0
       1: aload_1
       2: if_acmpne     7
       5: iconst_1
       6: ireturn
       7: aload_0
       8: aload_1
       9: invokespecial #40                 // Method org/apache/activemq/artemis/core/protocol/core/impl/PacketImpl.equals:(Ljava/lang/Object;)Z
      12: ifne          17
      15: iconst_0
      16: ireturn
      17: aload_1
      18: instanceof    #41                 // class org/apache/activemq/artemis/core/protocol/core/impl/wireformat/SessionQueueQueryResponseMessage
      21: ifne          26
      24: iconst_0
      25: ireturn
      26: aload_1
      27: checkcast     #41                 // class org/apache/activemq/artemis/core/protocol/core/impl/wireformat/SessionQueueQueryResponseMessage
      30: astore_2
      31: aload_0
      32: getfield      #17                 // Field address:Lorg/apache/activemq/artemis/api/core/SimpleString;
      35: ifnonnull     47
      38: aload_2
      39: getfield      #17                 // Field address:Lorg/apache/activemq/artemis/api/core/SimpleString;
      42: ifnull        63
      45: iconst_0
      46: ireturn
      47: aload_0
      48: getfield      #17                 // Field address:Lorg/apache/activemq/artemis/api/core/SimpleString;
      51: aload_2
      52: getfield      #17                 // Field address:Lorg/apache/activemq/artemis/api/core/SimpleString;
      55: invokevirtual #42                 // Method org/apache/activemq/artemis/api/core/SimpleString.equals:(Ljava/lang/Object;)Z
      58: ifne          63
      61: iconst_0
      62: ireturn
      63: aload_0
      64: getfield      #14                 // Field consumerCount:I
      67: aload_2
      68: getfield      #14                 // Field consumerCount:I
      71: if_icmpeq     76
      74: iconst_0
      75: ireturn
      76: aload_0
      77: getfield      #12                 // Field durable:Z
      80: aload_2
      81: getfield      #12                 // Field durable:Z
      84: if_icmpeq     89
      87: iconst_0
      88: ireturn
      89: aload_0
      90: getfield      #19                 // Field exists:Z
      93: aload_2
      94: getfield      #19                 // Field exists:Z
      97: if_icmpeq     102
     100: iconst_0
     101: ireturn
     102: aload_0
     103: getfield      #16                 // Field filterString:Lorg/apache/activemq/artemis/api/core/SimpleString;
     106: ifnonnull     118
     109: aload_2
     110: getfield      #16                 // Field filterString:Lorg/apache/activemq/artemis/api/core/SimpleString;
     113: ifnull        134
     116: iconst_0
     117: ireturn
     118: aload_0
     119: getfield      #16                 // Field filterString:Lorg/apache/activemq/artemis/api/core/SimpleString;
     122: aload_2
     123: getfield      #16                 // Field filterString:Lorg/apache/activemq/artemis/api/core/SimpleString;
     126: invokevirtual #42                 // Method org/apache/activemq/artemis/api/core/SimpleString.equals:(Ljava/lang/Object;)Z
     129: ifne          134
     132: iconst_0
     133: ireturn
     134: aload_0
     135: getfield      #15                 // Field messageCount:J
     138: aload_2
     139: getfield      #15                 // Field messageCount:J
     142: lcmp
     143: ifeq          148
     146: iconst_0
     147: ireturn
     148: aload_0
     149: getfield      #18                 // Field name:Lorg/apache/activemq/artemis/api/core/SimpleString;
     152: ifnonnull     164
     155: aload_2
     156: getfield      #18                 // Field name:Lorg/apache/activemq/artemis/api/core/SimpleString;
     159: ifnull        180
     162: iconst_0
     163: ireturn
     164: aload_0
     165: getfield      #18                 // Field name:Lorg/apache/activemq/artemis/api/core/SimpleString;
     168: aload_2
     169: getfield      #18                 // Field name:Lorg/apache/activemq/artemis/api/core/SimpleString;
     172: invokevirtual #42                 // Method org/apache/activemq/artemis/api/core/SimpleString.equals:(Ljava/lang/Object;)Z
     175: ifne          180
     178: iconst_0
     179: ireturn
     180: aload_0
     181: getfield      #13                 // Field temporary:Z
     184: aload_2
     185: getfield      #13                 // Field temporary:Z
     188: if_icmpeq     193
     191: iconst_0
     192: ireturn
     193: iconst_1
     194: ireturn
}
