Compiled from "SessionBeanSetSessionContextMethodInvocationInterceptor.java"
public class org.jboss.as.ejb3.component.session.SessionBeanSetSessionContextMethodInvocationInterceptor implements org.jboss.invocation.Interceptor {
  public static final org.jboss.invocation.InterceptorFactory FACTORY;

  private org.jboss.as.ejb3.component.session.SessionBeanSetSessionContextMethodInvocationInterceptor();
    Code:
       0: aload_0
       1: invokespecial #1                  // Method java/lang/Object."<init>":()V
       4: return

  public java.lang.Object processInvocation(org.jboss.invocation.InterceptorContext) throws java.lang.Exception;
    Code:
       0: aload_1
       1: ldc           #2                  // class org/jboss/as/ee/component/ComponentInstance
       3: invokevirtual #3                  // Method org/jboss/invocation/InterceptorContext.getPrivateData:(Ljava/lang/Class;)Ljava/lang/Object;
       6: checkcast     #4                  // class org/jboss/as/ejb3/component/session/SessionBeanComponentInstance
       9: astore_2
      10: aload_1
      11: ldc           #5                  // class org/jboss/as/ee/component/interceptors/InvocationType
      13: invokevirtual #3                  // Method org/jboss/invocation/InterceptorContext.getPrivateData:(Ljava/lang/Class;)Ljava/lang/Object;
      16: checkcast     #5                  // class org/jboss/as/ee/component/interceptors/InvocationType
      19: astore_3
      20: aload_1
      21: ldc           #5                  // class org/jboss/as/ee/component/interceptors/InvocationType
      23: getstatic     #6                  // Field org/jboss/as/ee/component/interceptors/InvocationType.DEPENDENCY_INJECTION:Lorg/jboss/as/ee/component/interceptors/InvocationType;
      26: invokevirtual #7                  // Method org/jboss/invocation/InterceptorContext.putPrivateData:(Ljava/lang/Class;Ljava/lang/Object;)Ljava/lang/Object;
      29: pop
      30: aload_1
      31: invokevirtual #8                  // Method org/jboss/invocation/InterceptorContext.getTarget:()Ljava/lang/Object;
      34: checkcast     #9                  // class javax/ejb/SessionBean
      37: aload_2
      38: invokevirtual #10                 // Method org/jboss/as/ejb3/component/session/SessionBeanComponentInstance.getEjbContext:()Lorg/jboss/as/ejb3/context/SessionContextImpl;
      41: invokeinterface #11,  2           // InterfaceMethod javax/ejb/SessionBean.setSessionContext:(Ljavax/ejb/SessionContext;)V
      46: aload_1
      47: ldc           #5                  // class org/jboss/as/ee/component/interceptors/InvocationType
      49: aload_3
      50: invokevirtual #7                  // Method org/jboss/invocation/InterceptorContext.putPrivateData:(Ljava/lang/Class;Ljava/lang/Object;)Ljava/lang/Object;
      53: pop
      54: goto          70
      57: astore        4
      59: aload_1
      60: ldc           #5                  // class org/jboss/as/ee/component/interceptors/InvocationType
      62: aload_3
      63: invokevirtual #7                  // Method org/jboss/invocation/InterceptorContext.putPrivateData:(Ljava/lang/Class;Ljava/lang/Object;)Ljava/lang/Object;
      66: pop
      67: aload         4
      69: athrow
      70: aload_1
      71: invokevirtual #12                 // Method org/jboss/invocation/InterceptorContext.proceed:()Ljava/lang/Object;
      74: areturn
    Exception table:
       from    to  target type
          20    46    57   any
          57    59    57   any

  static {};
    Code:
       0: new           #13                 // class org/jboss/invocation/ImmediateInterceptorFactory
       3: dup
       4: new           #14                 // class org/jboss/as/ejb3/component/session/SessionBeanSetSessionContextMethodInvocationInterceptor
       7: dup
       8: invokespecial #15                 // Method "<init>":()V
      11: invokespecial #16                 // Method org/jboss/invocation/ImmediateInterceptorFactory."<init>":(Lorg/jboss/invocation/Interceptor;)V
      14: putstatic     #17                 // Field FACTORY:Lorg/jboss/invocation/InterceptorFactory;
      17: return
}
