Compiled from "FileChangeEvent.java"
public class org.xnio.FileChangeEvent {
  private final java.io.File file;

  private final org.xnio.FileChangeEvent$Type type;

  public org.xnio.FileChangeEvent(java.io.File, org.xnio.FileChangeEvent$Type);
    Code:
       0: aload_0
       1: invokespecial #17                 // Method java/lang/Object."<init>":()V
       4: aload_0
       5: aload_1
       6: putfield      #19                 // Field file:Ljava/io/File;
       9: aload_0
      10: aload_2
      11: putfield      #21                 // Field type:Lorg/xnio/FileChangeEvent$Type;
      14: return

  public java.io.File getFile();
    Code:
       0: aload_0
       1: getfield      #19                 // Field file:Ljava/io/File;
       4: areturn

  public org.xnio.FileChangeEvent$Type getType();
    Code:
       0: aload_0
       1: getfield      #21                 // Field type:Lorg/xnio/FileChangeEvent$Type;
       4: areturn
}
