Compiled from "Annotate.java"
public class eus.ixa.ixa.pipe.tok.Annotate {
  private final eus.ixa.ixa.pipe.tok.Tokenizer toker;

  private final eus.ixa.ixa.pipe.seg.RuleBasedSegmenter segmenter;

  public eus.ixa.ixa.pipe.tok.Annotate(java.io.BufferedReader, java.util.Properties);
    Code:
       0: aload_0
       1: invokespecial #1                  // Method java/lang/Object."<init>":()V
       4: aload_1
       5: invokestatic  #2                  // Method eus/ixa/ixa/pipe/tok/StringUtils.readText:(Ljava/io/BufferedReader;)Ljava/lang/String;
       8: astore_3
       9: aload_0
      10: new           #3                  // class eus/ixa/ixa/pipe/seg/RuleBasedSegmenter
      13: dup
      14: aload_3
      15: aload_2
      16: invokespecial #4                  // Method eus/ixa/ixa/pipe/seg/RuleBasedSegmenter."<init>":(Ljava/lang/String;Ljava/util/Properties;)V
      19: putfield      #5                  // Field segmenter:Leus/ixa/ixa/pipe/seg/RuleBasedSegmenter;
      22: aload_0
      23: new           #6                  // class eus/ixa/ixa/pipe/tok/RuleBasedTokenizer
      26: dup
      27: aload_3
      28: aload_2
      29: invokespecial #7                  // Method eus/ixa/ixa/pipe/tok/RuleBasedTokenizer."<init>":(Ljava/lang/String;Ljava/util/Properties;)V
      32: putfield      #8                  // Field toker:Leus/ixa/ixa/pipe/tok/Tokenizer;
      35: return

  public void tokenizeToKAF(ixa.kaflib.KAFDocument) throws java.io.IOException;
    Code:
       0: iconst_0
       1: istore_2
       2: iconst_1
       3: istore_3
       4: aload_0
       5: getfield      #5                  // Field segmenter:Leus/ixa/ixa/pipe/seg/RuleBasedSegmenter;
       8: invokevirtual #9                  // Method eus/ixa/ixa/pipe/seg/RuleBasedSegmenter.segmentSentence:()[Ljava/lang/String;
      11: astore        4
      13: aload_0
      14: getfield      #8                  // Field toker:Leus/ixa/ixa/pipe/tok/Tokenizer;
      17: aload         4
      19: invokeinterface #10,  2           // InterfaceMethod eus/ixa/ixa/pipe/tok/Tokenizer.tokenize:([Ljava/lang/String;)Ljava/util/List;
      24: astore        5
      26: aload         5
      28: invokeinterface #11,  1           // InterfaceMethod java/util/List.iterator:()Ljava/util/Iterator;
      33: astore        6
      35: aload         6
      37: invokeinterface #12,  1           // InterfaceMethod java/util/Iterator.hasNext:()Z
      42: ifeq          150
      45: aload         6
      47: invokeinterface #13,  1           // InterfaceMethod java/util/Iterator.next:()Ljava/lang/Object;
      52: checkcast     #14                 // class java/util/List
      55: astore        7
      57: iload_2
      58: iconst_1
      59: iadd
      60: istore_2
      61: aload         7
      63: invokeinterface #11,  1           // InterfaceMethod java/util/List.iterator:()Ljava/util/Iterator;
      68: astore        8
      70: aload         8
      72: invokeinterface #12,  1           // InterfaceMethod java/util/Iterator.hasNext:()Z
      77: ifeq          147
      80: aload         8
      82: invokeinterface #13,  1           // InterfaceMethod java/util/Iterator.next:()Ljava/lang/Object;
      87: checkcast     #15                 // class eus/ixa/ixa/pipe/tok/Token
      90: astore        9
      92: aload         9
      94: invokevirtual #16                 // Method eus/ixa/ixa/pipe/tok/Token.getTokenValue:()Ljava/lang/String;
      97: ldc           #17                 // String ¶¶
      99: invokevirtual #18                 // Method java/lang/String.equals:(Ljava/lang/Object;)Z
     102: ifeq          111
     105: iinc          3, 1
     108: goto          144
     111: aload_1
     112: aload         9
     114: invokevirtual #19                 // Method eus/ixa/ixa/pipe/tok/Token.startOffset:()I
     117: aload         9
     119: invokevirtual #16                 // Method eus/ixa/ixa/pipe/tok/Token.getTokenValue:()Ljava/lang/String;
     122: iload_2
     123: invokevirtual #20                 // Method ixa/kaflib/KAFDocument.newWF:(ILjava/lang/String;I)Lixa/kaflib/WF;
     126: astore        10
     128: aload         10
     130: aload         9
     132: invokevirtual #21                 // Method eus/ixa/ixa/pipe/tok/Token.tokenLength:()I
     135: invokevirtual #22                 // Method ixa/kaflib/WF.setLength:(I)V
     138: aload         10
     140: iload_3
     141: invokevirtual #23                 // Method ixa/kaflib/WF.setPara:(I)V
     144: goto          70
     147: goto          35
     150: return

  public java.lang.String tokenizeToCoNLL();
    Code:
       0: new           #24                 // class java/lang/StringBuilder
       3: dup
       4: invokespecial #25                 // Method java/lang/StringBuilder."<init>":()V
       7: astore_1
       8: aload_0
       9: getfield      #5                  // Field segmenter:Leus/ixa/ixa/pipe/seg/RuleBasedSegmenter;
      12: invokevirtual #9                  // Method eus/ixa/ixa/pipe/seg/RuleBasedSegmenter.segmentSentence:()[Ljava/lang/String;
      15: astore_2
      16: aload_0
      17: getfield      #8                  // Field toker:Leus/ixa/ixa/pipe/tok/Tokenizer;
      20: aload_2
      21: invokeinterface #10,  2           // InterfaceMethod eus/ixa/ixa/pipe/tok/Tokenizer.tokenize:([Ljava/lang/String;)Ljava/util/List;
      26: astore_3
      27: aload_3
      28: invokeinterface #11,  1           // InterfaceMethod java/util/List.iterator:()Ljava/util/Iterator;
      33: astore        4
      35: aload         4
      37: invokeinterface #12,  1           // InterfaceMethod java/util/Iterator.hasNext:()Z
      42: ifeq          137
      45: aload         4
      47: invokeinterface #13,  1           // InterfaceMethod java/util/Iterator.next:()Ljava/lang/Object;
      52: checkcast     #14                 // class java/util/List
      55: astore        5
      57: aload         5
      59: invokeinterface #11,  1           // InterfaceMethod java/util/List.iterator:()Ljava/util/Iterator;
      64: astore        6
      66: aload         6
      68: invokeinterface #12,  1           // InterfaceMethod java/util/Iterator.hasNext:()Z
      73: ifeq          127
      76: aload         6
      78: invokeinterface #13,  1           // InterfaceMethod java/util/Iterator.next:()Ljava/lang/Object;
      83: checkcast     #15                 // class eus/ixa/ixa/pipe/tok/Token
      86: astore        7
      88: aload         7
      90: invokevirtual #16                 // Method eus/ixa/ixa/pipe/tok/Token.getTokenValue:()Ljava/lang/String;
      93: astore        8
      95: aload         8
      97: ldc           #17                 // String ¶¶
      99: invokevirtual #18                 // Method java/lang/String.equals:(Ljava/lang/Object;)Z
     102: ifeq          109
     105: ldc           #26                 // String *<P>*
     107: astore        8
     109: aload_1
     110: aload         8
     112: invokevirtual #27                 // Method java/lang/String.trim:()Ljava/lang/String;
     115: invokevirtual #28                 // Method java/lang/StringBuilder.append:(Ljava/lang/String;)Ljava/lang/StringBuilder;
     118: ldc           #29                 // String \n
     120: invokevirtual #28                 // Method java/lang/StringBuilder.append:(Ljava/lang/String;)Ljava/lang/StringBuilder;
     123: pop
     124: goto          66
     127: aload_1
     128: ldc           #29                 // String \n
     130: invokevirtual #28                 // Method java/lang/StringBuilder.append:(Ljava/lang/String;)Ljava/lang/StringBuilder;
     133: pop
     134: goto          35
     137: aload_1
     138: invokevirtual #30                 // Method java/lang/StringBuilder.toString:()Ljava/lang/String;
     141: areturn

  public java.lang.String tokenizeToCoNLLOffsets();
    Code:
       0: new           #24                 // class java/lang/StringBuilder
       3: dup
       4: invokespecial #25                 // Method java/lang/StringBuilder."<init>":()V
       7: astore_1
       8: aload_0
       9: getfield      #5                  // Field segmenter:Leus/ixa/ixa/pipe/seg/RuleBasedSegmenter;
      12: invokevirtual #9                  // Method eus/ixa/ixa/pipe/seg/RuleBasedSegmenter.segmentSentence:()[Ljava/lang/String;
      15: astore_2
      16: aload_0
      17: getfield      #8                  // Field toker:Leus/ixa/ixa/pipe/tok/Tokenizer;
      20: aload_2
      21: invokeinterface #10,  2           // InterfaceMethod eus/ixa/ixa/pipe/tok/Tokenizer.tokenize:([Ljava/lang/String;)Ljava/util/List;
      26: astore_3
      27: aload_3
      28: invokeinterface #11,  1           // InterfaceMethod java/util/List.iterator:()Ljava/util/Iterator;
      33: astore        4
      35: aload         4
      37: invokeinterface #12,  1           // InterfaceMethod java/util/Iterator.hasNext:()Z
      42: ifeq          163
      45: aload         4
      47: invokeinterface #13,  1           // InterfaceMethod java/util/Iterator.next:()Ljava/lang/Object;
      52: checkcast     #14                 // class java/util/List
      55: astore        5
      57: aload         5
      59: invokeinterface #11,  1           // InterfaceMethod java/util/List.iterator:()Ljava/util/Iterator;
      64: astore        6
      66: aload         6
      68: invokeinterface #12,  1           // InterfaceMethod java/util/Iterator.hasNext:()Z
      73: ifeq          153
      76: aload         6
      78: invokeinterface #13,  1           // InterfaceMethod java/util/Iterator.next:()Ljava/lang/Object;
      83: checkcast     #15                 // class eus/ixa/ixa/pipe/tok/Token
      86: astore        7
      88: aload         7
      90: invokevirtual #16                 // Method eus/ixa/ixa/pipe/tok/Token.getTokenValue:()Ljava/lang/String;
      93: astore        8
      95: aload         8
      97: ldc           #17                 // String ¶¶
      99: invokevirtual #18                 // Method java/lang/String.equals:(Ljava/lang/Object;)Z
     102: ifeq          109
     105: ldc           #26                 // String *<P>*
     107: astore        8
     109: aload_1
     110: aload         8
     112: invokevirtual #27                 // Method java/lang/String.trim:()Ljava/lang/String;
     115: invokevirtual #28                 // Method java/lang/StringBuilder.append:(Ljava/lang/String;)Ljava/lang/StringBuilder;
     118: ldc           #31                 // String
     120: invokevirtual #28                 // Method java/lang/StringBuilder.append:(Ljava/lang/String;)Ljava/lang/StringBuilder;
     123: aload         7
     125: invokevirtual #19                 // Method eus/ixa/ixa/pipe/tok/Token.startOffset:()I
     128: invokevirtual #32                 // Method java/lang/StringBuilder.append:(I)Ljava/lang/StringBuilder;
     131: ldc           #31                 // String
     133: invokevirtual #28                 // Method java/lang/StringBuilder.append:(Ljava/lang/String;)Ljava/lang/StringBuilder;
     136: aload         7
     138: invokevirtual #21                 // Method eus/ixa/ixa/pipe/tok/Token.tokenLength:()I
     141: invokevirtual #32                 // Method java/lang/StringBuilder.append:(I)Ljava/lang/StringBuilder;
     144: ldc           #29                 // String \n
     146: invokevirtual #28                 // Method java/lang/StringBuilder.append:(Ljava/lang/String;)Ljava/lang/StringBuilder;
     149: pop
     150: goto          66
     153: aload_1
     154: ldc           #29                 // String \n
     156: invokevirtual #28                 // Method java/lang/StringBuilder.append:(Ljava/lang/String;)Ljava/lang/StringBuilder;
     159: pop
     160: goto          35
     163: aload_1
     164: invokevirtual #30                 // Method java/lang/StringBuilder.toString:()Ljava/lang/String;
     167: areturn

  public java.lang.String tokenizeToText();
    Code:
       0: new           #24                 // class java/lang/StringBuilder
       3: dup
       4: invokespecial #25                 // Method java/lang/StringBuilder."<init>":()V
       7: astore_1
       8: aload_0
       9: getfield      #5                  // Field segmenter:Leus/ixa/ixa/pipe/seg/RuleBasedSegmenter;
      12: invokevirtual #9                  // Method eus/ixa/ixa/pipe/seg/RuleBasedSegmenter.segmentSentence:()[Ljava/lang/String;
      15: astore_2
      16: aload_0
      17: getfield      #8                  // Field toker:Leus/ixa/ixa/pipe/tok/Tokenizer;
      20: aload_2
      21: invokeinterface #10,  2           // InterfaceMethod eus/ixa/ixa/pipe/tok/Tokenizer.tokenize:([Ljava/lang/String;)Ljava/util/List;
      26: astore_3
      27: aload_3
      28: invokeinterface #11,  1           // InterfaceMethod java/util/List.iterator:()Ljava/util/Iterator;
      33: astore        4
      35: aload         4
      37: invokeinterface #12,  1           // InterfaceMethod java/util/Iterator.hasNext:()Z
      42: ifeq          148
      45: aload         4
      47: invokeinterface #13,  1           // InterfaceMethod java/util/Iterator.next:()Ljava/lang/Object;
      52: checkcast     #14                 // class java/util/List
      55: astore        5
      57: aload         5
      59: invokeinterface #11,  1           // InterfaceMethod java/util/List.iterator:()Ljava/util/Iterator;
      64: astore        6
      66: aload         6
      68: invokeinterface #12,  1           // InterfaceMethod java/util/Iterator.hasNext:()Z
      73: ifeq          138
      76: aload         6
      78: invokeinterface #13,  1           // InterfaceMethod java/util/Iterator.next:()Ljava/lang/Object;
      83: checkcast     #15                 // class eus/ixa/ixa/pipe/tok/Token
      86: astore        7
      88: aload         7
      90: invokevirtual #16                 // Method eus/ixa/ixa/pipe/tok/Token.getTokenValue:()Ljava/lang/String;
      93: astore        8
      95: aload         8
      97: ldc           #17                 // String ¶¶
      99: invokevirtual #18                 // Method java/lang/String.equals:(Ljava/lang/Object;)Z
     102: ifeq          120
     105: aload_1
     106: ldc           #26                 // String *<P>*
     108: invokevirtual #28                 // Method java/lang/StringBuilder.append:(Ljava/lang/String;)Ljava/lang/StringBuilder;
     111: ldc           #29                 // String \n
     113: invokevirtual #28                 // Method java/lang/StringBuilder.append:(Ljava/lang/String;)Ljava/lang/StringBuilder;
     116: pop
     117: goto          135
     120: aload_1
     121: aload         8
     123: invokevirtual #27                 // Method java/lang/String.trim:()Ljava/lang/String;
     126: invokevirtual #28                 // Method java/lang/StringBuilder.append:(Ljava/lang/String;)Ljava/lang/StringBuilder;
     129: ldc           #31                 // String
     131: invokevirtual #28                 // Method java/lang/StringBuilder.append:(Ljava/lang/String;)Ljava/lang/StringBuilder;
     134: pop
     135: goto          66
     138: aload_1
     139: ldc           #29                 // String \n
     141: invokevirtual #28                 // Method java/lang/StringBuilder.append:(Ljava/lang/String;)Ljava/lang/StringBuilder;
     144: pop
     145: goto          35
     148: aload_1
     149: invokevirtual #30                 // Method java/lang/StringBuilder.toString:()Ljava/lang/String;
     152: invokevirtual #27                 // Method java/lang/String.trim:()Ljava/lang/String;
     155: areturn

  public static void tokensToKAF(java.io.Reader, ixa.kaflib.KAFDocument) throws java.io.IOException;
    Code:
       0: iconst_0
       1: istore_2
       2: iconst_1
       3: istore_3
       4: aload_0
       5: invokestatic  #33                 // Method com/google/common/io/CharStreams.readLines:(Ljava/lang/Readable;)Ljava/util/List;
       8: astore        4
      10: aload         4
      12: invokeinterface #11,  1           // InterfaceMethod java/util/List.iterator:()Ljava/util/Iterator;
      17: astore        5
      19: aload         5
      21: invokeinterface #12,  1           // InterfaceMethod java/util/Iterator.hasNext:()Z
      26: ifeq          129
      29: aload         5
      31: invokeinterface #13,  1           // InterfaceMethod java/util/Iterator.next:()Ljava/lang/Object;
      36: checkcast     #34                 // class java/lang/String
      39: astore        6
      41: iload_2
      42: iconst_1
      43: iadd
      44: istore_2
      45: aload         6
      47: ldc           #31                 // String
      49: invokevirtual #35                 // Method java/lang/String.split:(Ljava/lang/String;)[Ljava/lang/String;
      52: astore        7
      54: aload         7
      56: astore        8
      58: aload         8
      60: arraylength
      61: istore        9
      63: iconst_0
      64: istore        10
      66: iload         10
      68: iload         9
      70: if_icmpge     126
      73: aload         8
      75: iload         10
      77: aaload
      78: astore        11
      80: aload         11
      82: ldc           #17                 // String ¶¶
      84: invokevirtual #18                 // Method java/lang/String.equals:(Ljava/lang/Object;)Z
      87: ifeq          104
      90: iinc          3, 1
      93: iload_3
      94: iload_2
      95: if_icmple     120
      98: iinc          2, 1
     101: goto          93
     104: aload_1
     105: iconst_0
     106: aload         11
     108: iload_2
     109: invokevirtual #20                 // Method ixa/kaflib/KAFDocument.newWF:(ILjava/lang/String;I)Lixa/kaflib/WF;
     112: astore        12
     114: aload         12
     116: iload_3
     117: invokevirtual #23                 // Method ixa/kaflib/WF.setPara:(I)V
     120: iinc          10, 1
     123: goto          66
     126: goto          19
     129: return
}
