Compiled from "AssertionInfoMap.java"
public class org.apache.cxf.ws.policy.AssertionInfoMap extends java.util.HashMap<javax.xml.namespace.QName, java.util.Collection<org.apache.cxf.ws.policy.AssertionInfo>> {
  private static final long serialVersionUID;

  private static final java.util.ResourceBundle BUNDLE;

  public org.apache.cxf.ws.policy.AssertionInfoMap(org.apache.neethi.Policy);
    Code:
       0: aload_0
       1: aload_1
       2: invokestatic  #1                  // Method getAssertions:(Lorg/apache/neethi/PolicyOperator;)Ljava/util/Collection;
       5: invokespecial #2                  // Method "<init>":(Ljava/util/Collection;)V
       8: return

  public org.apache.cxf.ws.policy.AssertionInfoMap(java.util.Collection<? extends org.apache.neethi.Assertion>);
    Code:
       0: aload_0
       1: aload_1
       2: invokeinterface #3,  1            // InterfaceMethod java/util/Collection.size:()I
       7: bipush        6
       9: if_icmpge     17
      12: bipush        6
      14: goto          23
      17: aload_1
      18: invokeinterface #3,  1            // InterfaceMethod java/util/Collection.size:()I
      23: invokespecial #4                  // Method java/util/HashMap."<init>":(I)V
      26: aload_1
      27: invokeinterface #5,  1            // InterfaceMethod java/util/Collection.iterator:()Ljava/util/Iterator;
      32: astore_2
      33: aload_2
      34: invokeinterface #6,  1            // InterfaceMethod java/util/Iterator.hasNext:()Z
      39: ifeq          60
      42: aload_2
      43: invokeinterface #7,  1            // InterfaceMethod java/util/Iterator.next:()Ljava/lang/Object;
      48: checkcast     #8                  // class org/apache/neethi/Assertion
      51: astore_3
      52: aload_0
      53: aload_3
      54: invokespecial #9                  // Method putAssertionInfo:(Lorg/apache/neethi/Assertion;)V
      57: goto          33
      60: return

  private void putAssertionInfo(org.apache.neethi.Assertion);
    Code:
       0: aload_1
       1: instanceof    #10                 // class org/apache/neethi/PolicyContainingAssertion
       4: ifeq          73
       7: aload_1
       8: checkcast     #10                 // class org/apache/neethi/PolicyContainingAssertion
      11: invokeinterface #11,  1           // InterfaceMethod org/apache/neethi/PolicyContainingAssertion.getPolicy:()Lorg/apache/neethi/Policy;
      16: astore_2
      17: aload_2
      18: ifnull        73
      21: new           #12                 // class java/util/ArrayList
      24: dup
      25: invokespecial #13                 // Method java/util/ArrayList."<init>":()V
      28: astore_3
      29: aload_2
      30: aload_3
      31: invokestatic  #14                 // Method getAssertions:(Lorg/apache/neethi/PolicyOperator;Ljava/util/Collection;)V
      34: aload_3
      35: invokeinterface #15,  1           // InterfaceMethod java/util/List.iterator:()Ljava/util/Iterator;
      40: astore        4
      42: aload         4
      44: invokeinterface #6,  1            // InterfaceMethod java/util/Iterator.hasNext:()Z
      49: ifeq          73
      52: aload         4
      54: invokeinterface #7,  1            // InterfaceMethod java/util/Iterator.next:()Ljava/lang/Object;
      59: checkcast     #8                  // class org/apache/neethi/Assertion
      62: astore        5
      64: aload_0
      65: aload         5
      67: invokespecial #9                  // Method putAssertionInfo:(Lorg/apache/neethi/Assertion;)V
      70: goto          42
      73: new           #16                 // class org/apache/cxf/ws/policy/AssertionInfo
      76: dup
      77: aload_1
      78: invokespecial #17                 // Method org/apache/cxf/ws/policy/AssertionInfo."<init>":(Lorg/apache/neethi/Assertion;)V
      81: astore_2
      82: aload_0
      83: aload_1
      84: invokeinterface #18,  1           // InterfaceMethod org/apache/neethi/Assertion.getName:()Ljavax/xml/namespace/QName;
      89: invokevirtual #19                 // Method get:(Ljava/lang/Object;)Ljava/lang/Object;
      92: checkcast     #20                 // class java/util/Collection
      95: astore_3
      96: aload_3
      97: ifnonnull     120
     100: new           #12                 // class java/util/ArrayList
     103: dup
     104: invokespecial #13                 // Method java/util/ArrayList."<init>":()V
     107: astore_3
     108: aload_0
     109: aload_1
     110: invokeinterface #18,  1           // InterfaceMethod org/apache/neethi/Assertion.getName:()Ljavax/xml/namespace/QName;
     115: aload_3
     116: invokevirtual #21                 // Method put:(Ljava/lang/Object;Ljava/lang/Object;)Ljava/lang/Object;
     119: pop
     120: aload_3
     121: invokeinterface #5,  1            // InterfaceMethod java/util/Collection.iterator:()Ljava/util/Iterator;
     126: astore        4
     128: aload         4
     130: invokeinterface #6,  1            // InterfaceMethod java/util/Iterator.hasNext:()Z
     135: ifeq          163
     138: aload         4
     140: invokeinterface #7,  1            // InterfaceMethod java/util/Iterator.next:()Ljava/lang/Object;
     145: checkcast     #16                 // class org/apache/cxf/ws/policy/AssertionInfo
     148: astore        5
     150: aload         5
     152: invokevirtual #22                 // Method org/apache/cxf/ws/policy/AssertionInfo.getAssertion:()Lorg/apache/neethi/Assertion;
     155: aload_1
     156: if_acmpne     160
     159: return
     160: goto          128
     163: aload_3
     164: aload_2
     165: invokeinterface #23,  2           // InterfaceMethod java/util/Collection.add:(Ljava/lang/Object;)Z
     170: pop
     171: return

  public java.util.Collection<org.apache.cxf.ws.policy.AssertionInfo> getAssertionInfo(javax.xml.namespace.QName);
    Code:
       0: aload_0
       1: aload_1
       2: invokevirtual #19                 // Method get:(Ljava/lang/Object;)Ljava/lang/Object;
       5: checkcast     #20                 // class java/util/Collection
       8: astore_2
       9: aload_2
      10: ifnull        17
      13: aload_2
      14: goto          26
      17: getstatic     #24                 // Field java/util/Collections.EMPTY_LIST:Ljava/util/List;
      20: ldc_w         #16                 // class org/apache/cxf/ws/policy/AssertionInfo
      23: invokestatic  #25                 // Method org/apache/cxf/helpers/CastUtils.cast:(Ljava/util/List;Ljava/lang/Class;)Ljava/util/List;
      26: areturn

  public boolean supportsAlternative(org.apache.neethi.PolicyComponent, java.util.List<javax.xml.namespace.QName>);
    Code:
       0: iconst_1
       1: istore_3
       2: aload_1
       3: instanceof    #26                 // class org/apache/cxf/ws/policy/PolicyAssertion
       6: ifeq          55
       9: aload_1
      10: checkcast     #26                 // class org/apache/cxf/ws/policy/PolicyAssertion
      13: astore        4
      15: aload         4
      17: aload_0
      18: invokeinterface #27,  2           // InterfaceMethod org/apache/cxf/ws/policy/PolicyAssertion.isAsserted:(Lorg/apache/cxf/ws/policy/AssertionInfoMap;)Z
      23: ifne          52
      26: aload         4
      28: invokeinterface #28,  1           // InterfaceMethod org/apache/cxf/ws/policy/PolicyAssertion.isOptional:()Z
      33: ifne          52
      36: aload_2
      37: aload         4
      39: invokeinterface #29,  1           // InterfaceMethod org/apache/cxf/ws/policy/PolicyAssertion.getName:()Ljavax/xml/namespace/QName;
      44: invokeinterface #30,  2           // InterfaceMethod java/util/List.add:(Ljava/lang/Object;)Z
      49: pop
      50: iconst_0
      51: istore_3
      52: goto          191
      55: aload_1
      56: instanceof    #8                  // class org/apache/neethi/Assertion
      59: ifeq          191
      62: aload_1
      63: checkcast     #8                  // class org/apache/neethi/Assertion
      66: astore        4
      68: aload_0
      69: aload         4
      71: invokeinterface #18,  1           // InterfaceMethod org/apache/neethi/Assertion.getName:()Ljavax/xml/namespace/QName;
      76: invokevirtual #31                 // Method getAssertionInfo:(Ljavax/xml/namespace/QName;)Ljava/util/Collection;
      79: astore        5
      81: iconst_0
      82: istore        6
      84: aload         5
      86: invokeinterface #5,  1            // InterfaceMethod java/util/Collection.iterator:()Ljava/util/Iterator;
      91: astore        7
      93: aload         7
      95: invokeinterface #6,  1            // InterfaceMethod java/util/Iterator.hasNext:()Z
     100: ifeq          170
     103: aload         7
     105: invokeinterface #7,  1            // InterfaceMethod java/util/Iterator.next:()Ljava/lang/Object;
     110: checkcast     #16                 // class org/apache/cxf/ws/policy/AssertionInfo
     113: astore        8
     115: aload         8
     117: invokevirtual #22                 // Method org/apache/cxf/ws/policy/AssertionInfo.getAssertion:()Lorg/apache/neethi/Assertion;
     120: aload         4
     122: invokeinterface #32,  2           // InterfaceMethod org/apache/neethi/Assertion.equal:(Lorg/apache/neethi/PolicyComponent;)Z
     127: ifeq          167
     130: iconst_1
     131: istore        6
     133: aload         8
     135: invokevirtual #33                 // Method org/apache/cxf/ws/policy/AssertionInfo.isAsserted:()Z
     138: ifne          167
     141: aload         4
     143: invokeinterface #34,  1           // InterfaceMethod org/apache/neethi/Assertion.isOptional:()Z
     148: ifne          167
     151: aload_2
     152: aload         4
     154: invokeinterface #18,  1           // InterfaceMethod org/apache/neethi/Assertion.getName:()Ljavax/xml/namespace/QName;
     159: invokeinterface #30,  2           // InterfaceMethod java/util/List.add:(Ljava/lang/Object;)Z
     164: pop
     165: iconst_0
     166: istore_3
     167: goto          93
     170: iload         6
     172: ifne          191
     175: aload_2
     176: aload         4
     178: invokeinterface #18,  1           // InterfaceMethod org/apache/neethi/Assertion.getName:()Ljavax/xml/namespace/QName;
     183: invokeinterface #30,  2           // InterfaceMethod java/util/List.add:(Ljava/lang/Object;)Z
     188: pop
     189: iconst_0
     190: ireturn
     191: aload_1
     192: instanceof    #10                 // class org/apache/neethi/PolicyContainingAssertion
     195: ifeq          290
     198: aload_1
     199: checkcast     #10                 // class org/apache/neethi/PolicyContainingAssertion
     202: invokeinterface #11,  1           // InterfaceMethod org/apache/neethi/PolicyContainingAssertion.getPolicy:()Lorg/apache/neethi/Policy;
     207: astore        4
     209: aload         4
     211: ifnull        290
     214: aload         4
     216: invokevirtual #35                 // Method org/apache/neethi/Policy.getAlternatives:()Ljava/util/Iterator;
     219: astore        5
     221: aload         5
     223: invokeinterface #6,  1            // InterfaceMethod java/util/Iterator.hasNext:()Z
     228: ifeq          290
     231: aload         5
     233: invokeinterface #7,  1            // InterfaceMethod java/util/Iterator.next:()Ljava/lang/Object;
     238: checkcast     #36                 // class java/util/List
     241: astore        6
     243: aload         6
     245: invokeinterface #15,  1           // InterfaceMethod java/util/List.iterator:()Ljava/util/Iterator;
     250: astore        7
     252: aload         7
     254: invokeinterface #6,  1            // InterfaceMethod java/util/Iterator.hasNext:()Z
     259: ifeq          287
     262: aload         7
     264: invokeinterface #7,  1            // InterfaceMethod java/util/Iterator.next:()Ljava/lang/Object;
     269: checkcast     #8                  // class org/apache/neethi/Assertion
     272: astore        8
     274: iload_3
     275: aload_0
     276: aload         8
     278: aload_2
     279: invokevirtual #37                 // Method supportsAlternative:(Lorg/apache/neethi/PolicyComponent;Ljava/util/List;)Z
     282: iand
     283: istore_3
     284: goto          252
     287: goto          221
     290: iload_3
     291: ireturn

  public boolean supportsAlternative(java.util.Collection<? extends org.apache.neethi.PolicyComponent>, java.util.List<javax.xml.namespace.QName>);
    Code:
       0: iconst_1
       1: istore_3
       2: aload_1
       3: invokeinterface #5,  1            // InterfaceMethod java/util/Collection.iterator:()Ljava/util/Iterator;
       8: astore        4
      10: aload         4
      12: invokeinterface #6,  1            // InterfaceMethod java/util/Iterator.hasNext:()Z
      17: ifeq          45
      20: aload         4
      22: invokeinterface #7,  1            // InterfaceMethod java/util/Iterator.next:()Ljava/lang/Object;
      27: checkcast     #38                 // class org/apache/neethi/PolicyComponent
      30: astore        5
      32: iload_3
      33: aload_0
      34: aload         5
      36: aload_2
      37: invokevirtual #37                 // Method supportsAlternative:(Lorg/apache/neethi/PolicyComponent;Ljava/util/List;)Z
      40: iand
      41: istore_3
      42: goto          10
      45: iload_3
      46: ireturn

  public java.util.List<java.util.List<org.apache.neethi.Assertion>> checkEffectivePolicy(org.apache.neethi.Policy);
    Code:
       0: new           #12                 // class java/util/ArrayList
       3: dup
       4: iconst_4
       5: invokespecial #39                 // Method java/util/ArrayList."<init>":(I)V
       8: astore_2
       9: new           #12                 // class java/util/ArrayList
      12: dup
      13: invokespecial #13                 // Method java/util/ArrayList."<init>":()V
      16: astore_3
      17: aload_1
      18: invokevirtual #35                 // Method org/apache/neethi/Policy.getAlternatives:()Ljava/util/Iterator;
      21: astore        4
      23: aload         4
      25: invokeinterface #6,  1            // InterfaceMethod java/util/Iterator.hasNext:()Z
      30: ifeq          67
      33: aload         4
      35: invokeinterface #7,  1            // InterfaceMethod java/util/Iterator.next:()Ljava/lang/Object;
      40: checkcast     #36                 // class java/util/List
      43: astore        5
      45: aload_0
      46: aload         5
      48: aload_3
      49: invokevirtual #40                 // Method supportsAlternative:(Ljava/util/Collection;Ljava/util/List;)Z
      52: ifeq          64
      55: aload_2
      56: aload         5
      58: invokeinterface #30,  2           // InterfaceMethod java/util/List.add:(Ljava/lang/Object;)Z
      63: pop
      64: goto          23
      67: aload_2
      68: invokeinterface #41,  1           // InterfaceMethod java/util/List.isEmpty:()Z
      73: ifne          78
      76: aload_2
      77: areturn
      78: new           #42                 // class java/util/LinkedHashSet
      81: dup
      82: invokespecial #43                 // Method java/util/LinkedHashSet."<init>":()V
      85: astore        5
      87: aload_3
      88: invokeinterface #15,  1           // InterfaceMethod java/util/List.iterator:()Ljava/util/Iterator;
      93: astore        6
      95: aload         6
      97: invokeinterface #6,  1            // InterfaceMethod java/util/Iterator.hasNext:()Z
     102: ifeq          249
     105: aload         6
     107: invokeinterface #7,  1            // InterfaceMethod java/util/Iterator.next:()Ljava/lang/Object;
     112: checkcast     #44                 // class javax/xml/namespace/QName
     115: astore        7
     117: aload_0
     118: aload         7
     120: invokevirtual #31                 // Method getAssertionInfo:(Ljavax/xml/namespace/QName;)Ljava/util/Collection;
     123: astore        8
     125: iconst_0
     126: istore        9
     128: aload         8
     130: invokeinterface #5,  1            // InterfaceMethod java/util/Collection.iterator:()Ljava/util/Iterator;
     135: astore        10
     137: aload         10
     139: invokeinterface #6,  1            // InterfaceMethod java/util/Iterator.hasNext:()Z
     144: ifeq          228
     147: aload         10
     149: invokeinterface #7,  1            // InterfaceMethod java/util/Iterator.next:()Ljava/lang/Object;
     154: checkcast     #16                 // class org/apache/cxf/ws/policy/AssertionInfo
     157: astore        11
     159: aload         11
     161: invokevirtual #33                 // Method org/apache/cxf/ws/policy/AssertionInfo.isAsserted:()Z
     164: ifne          225
     167: aload         7
     169: invokevirtual #45                 // Method javax/xml/namespace/QName.toString:()Ljava/lang/String;
     172: astore        12
     174: aload         11
     176: invokevirtual #46                 // Method org/apache/cxf/ws/policy/AssertionInfo.getErrorMessage:()Ljava/lang/String;
     179: ifnull        212
     182: new           #47                 // class java/lang/StringBuilder
     185: dup
     186: invokespecial #48                 // Method java/lang/StringBuilder."<init>":()V
     189: aload         12
     191: invokevirtual #49                 // Method java/lang/StringBuilder.append:(Ljava/lang/String;)Ljava/lang/StringBuilder;
     194: ldc           #50                 // String :
     196: invokevirtual #49                 // Method java/lang/StringBuilder.append:(Ljava/lang/String;)Ljava/lang/StringBuilder;
     199: aload         11
     201: invokevirtual #46                 // Method org/apache/cxf/ws/policy/AssertionInfo.getErrorMessage:()Ljava/lang/String;
     204: invokevirtual #49                 // Method java/lang/StringBuilder.append:(Ljava/lang/String;)Ljava/lang/StringBuilder;
     207: invokevirtual #51                 // Method java/lang/StringBuilder.toString:()Ljava/lang/String;
     210: astore        12
     212: aload         5
     214: aload         12
     216: invokeinterface #52,  2           // InterfaceMethod java/util/Set.add:(Ljava/lang/Object;)Z
     221: pop
     222: iconst_1
     223: istore        9
     225: goto          137
     228: iload         9
     230: ifne          246
     233: aload         5
     235: aload         7
     237: invokevirtual #45                 // Method javax/xml/namespace/QName.toString:()Ljava/lang/String;
     240: invokeinterface #52,  2           // InterfaceMethod java/util/Set.add:(Ljava/lang/Object;)Z
     245: pop
     246: goto          95
     249: new           #47                 // class java/lang/StringBuilder
     252: dup
     253: invokespecial #48                 // Method java/lang/StringBuilder."<init>":()V
     256: astore        6
     258: aload         5
     260: invokeinterface #53,  1           // InterfaceMethod java/util/Set.iterator:()Ljava/util/Iterator;
     265: astore        7
     267: aload         7
     269: invokeinterface #6,  1            // InterfaceMethod java/util/Iterator.hasNext:()Z
     274: ifeq          305
     277: aload         7
     279: invokeinterface #7,  1            // InterfaceMethod java/util/Iterator.next:()Ljava/lang/Object;
     284: checkcast     #54                 // class java/lang/String
     287: astore        8
     289: aload         6
     291: ldc           #55                 // String \n
     293: invokevirtual #49                 // Method java/lang/StringBuilder.append:(Ljava/lang/String;)Ljava/lang/StringBuilder;
     296: aload         8
     298: invokevirtual #49                 // Method java/lang/StringBuilder.append:(Ljava/lang/String;)Ljava/lang/StringBuilder;
     301: pop
     302: goto          267
     305: new           #56                 // class org/apache/cxf/ws/policy/PolicyException
     308: dup
     309: new           #57                 // class org/apache/cxf/common/i18n/Message
     312: dup
     313: ldc           #58                 // String NO_ALTERNATIVE_EXC
     315: getstatic     #59                 // Field BUNDLE:Ljava/util/ResourceBundle;
     318: iconst_1
     319: anewarray     #60                 // class java/lang/Object
     322: dup
     323: iconst_0
     324: aload         6
     326: invokevirtual #51                 // Method java/lang/StringBuilder.toString:()Ljava/lang/String;
     329: aastore
     330: invokespecial #61                 // Method org/apache/cxf/common/i18n/Message."<init>":(Ljava/lang/String;Ljava/util/ResourceBundle;[Ljava/lang/Object;)V
     333: invokespecial #62                 // Method org/apache/cxf/ws/policy/PolicyException."<init>":(Lorg/apache/cxf/common/i18n/Message;)V
     336: athrow

  public void check();
    Code:
       0: aload_0
       1: invokevirtual #63                 // Method values:()Ljava/util/Collection;
       4: invokeinterface #5,  1            // InterfaceMethod java/util/Collection.iterator:()Ljava/util/Iterator;
       9: astore_1
      10: aload_1
      11: invokeinterface #6,  1            // InterfaceMethod java/util/Iterator.hasNext:()Z
      16: ifeq          107
      19: aload_1
      20: invokeinterface #7,  1            // InterfaceMethod java/util/Iterator.next:()Ljava/lang/Object;
      25: checkcast     #20                 // class java/util/Collection
      28: astore_2
      29: aload_2
      30: invokeinterface #5,  1            // InterfaceMethod java/util/Collection.iterator:()Ljava/util/Iterator;
      35: astore_3
      36: aload_3
      37: invokeinterface #6,  1            // InterfaceMethod java/util/Iterator.hasNext:()Z
      42: ifeq          104
      45: aload_3
      46: invokeinterface #7,  1            // InterfaceMethod java/util/Iterator.next:()Ljava/lang/Object;
      51: checkcast     #16                 // class org/apache/cxf/ws/policy/AssertionInfo
      54: astore        4
      56: aload         4
      58: invokevirtual #33                 // Method org/apache/cxf/ws/policy/AssertionInfo.isAsserted:()Z
      61: ifne          101
      64: new           #56                 // class org/apache/cxf/ws/policy/PolicyException
      67: dup
      68: new           #57                 // class org/apache/cxf/common/i18n/Message
      71: dup
      72: ldc           #64                 // String NOT_ASSERTED_EXC
      74: getstatic     #59                 // Field BUNDLE:Ljava/util/ResourceBundle;
      77: iconst_1
      78: anewarray     #60                 // class java/lang/Object
      81: dup
      82: iconst_0
      83: aload         4
      85: invokevirtual #22                 // Method org/apache/cxf/ws/policy/AssertionInfo.getAssertion:()Lorg/apache/neethi/Assertion;
      88: invokeinterface #18,  1           // InterfaceMethod org/apache/neethi/Assertion.getName:()Ljavax/xml/namespace/QName;
      93: aastore
      94: invokespecial #61                 // Method org/apache/cxf/common/i18n/Message."<init>":(Ljava/lang/String;Ljava/util/ResourceBundle;[Ljava/lang/Object;)V
      97: invokespecial #62                 // Method org/apache/cxf/ws/policy/PolicyException."<init>":(Lorg/apache/cxf/common/i18n/Message;)V
     100: athrow
     101: goto          36
     104: goto          10
     107: return

  private static java.util.Collection<org.apache.neethi.Assertion> getAssertions(org.apache.neethi.PolicyOperator);
    Code:
       0: new           #12                 // class java/util/ArrayList
       3: dup
       4: invokespecial #13                 // Method java/util/ArrayList."<init>":()V
       7: astore_1
       8: aload_0
       9: aload_1
      10: invokestatic  #14                 // Method getAssertions:(Lorg/apache/neethi/PolicyOperator;Ljava/util/Collection;)V
      13: aload_1
      14: areturn

  private static void getAssertions(org.apache.neethi.PolicyOperator, java.util.Collection<org.apache.neethi.Assertion>);
    Code:
       0: aload_0
       1: invokeinterface #65,  1           // InterfaceMethod org/apache/neethi/PolicyOperator.getPolicyComponents:()Ljava/util/List;
       6: astore_2
       7: aload_2
       8: invokeinterface #15,  1           // InterfaceMethod java/util/List.iterator:()Ljava/util/Iterator;
      13: astore_3
      14: aload_3
      15: invokeinterface #6,  1            // InterfaceMethod java/util/Iterator.hasNext:()Z
      20: ifeq          69
      23: aload_3
      24: invokeinterface #7,  1            // InterfaceMethod java/util/Iterator.next:()Ljava/lang/Object;
      29: checkcast     #38                 // class org/apache/neethi/PolicyComponent
      32: astore        4
      34: aload         4
      36: instanceof    #8                  // class org/apache/neethi/Assertion
      39: ifeq          57
      42: aload_1
      43: aload         4
      45: checkcast     #8                  // class org/apache/neethi/Assertion
      48: invokeinterface #23,  2           // InterfaceMethod java/util/Collection.add:(Ljava/lang/Object;)Z
      53: pop
      54: goto          66
      57: aload         4
      59: checkcast     #66                 // class org/apache/neethi/PolicyOperator
      62: aload_1
      63: invokestatic  #14                 // Method getAssertions:(Lorg/apache/neethi/PolicyOperator;Ljava/util/Collection;)V
      66: goto          14
      69: return

  static {};
    Code:
       0: ldc_w         #67                 // class org/apache/cxf/ws/policy/AssertionInfoMap
       3: ldc           #68                 // String APIMessages
       5: invokestatic  #69                 // Method org/apache/cxf/common/i18n/BundleUtils.getBundle:(Ljava/lang/Class;Ljava/lang/String;)Ljava/util/ResourceBundle;
       8: putstatic     #59                 // Field BUNDLE:Ljava/util/ResourceBundle;
      11: return
}
