Compiled from "EndpointPolicyImpl.java"
public class org.apache.cxf.ws.policy.EndpointPolicyImpl implements org.apache.cxf.ws.policy.EndpointPolicy {
  private static final java.util.ResourceBundle BUNDLE;

  private org.apache.neethi.Policy policy;

  private java.util.Collection<org.apache.neethi.Assertion> chosenAlternative;

  private volatile java.util.Collection<org.apache.neethi.Assertion> vocabulary;

  private java.util.Collection<org.apache.neethi.Assertion> faultVocabulary;

  private volatile java.util.List<org.apache.cxf.interceptor.Interceptor<? extends org.apache.cxf.message.Message>> interceptors;

  private java.util.List<org.apache.cxf.interceptor.Interceptor<? extends org.apache.cxf.message.Message>> faultInterceptors;

  private org.apache.cxf.service.model.EndpointInfo ei;

  private org.apache.cxf.ws.policy.PolicyEngineImpl engine;

  private boolean requestor;

  private org.apache.cxf.ws.policy.Assertor assertor;

  public org.apache.cxf.ws.policy.EndpointPolicyImpl();
    Code:
       0: aload_0
       1: invokespecial #1                  // Method java/lang/Object."<init>":()V
       4: return

  public org.apache.cxf.ws.policy.EndpointPolicyImpl(org.apache.neethi.Policy);
    Code:
       0: aload_0
       1: invokespecial #1                  // Method java/lang/Object."<init>":()V
       4: aload_0
       5: aload_1
       6: putfield      #2                  // Field policy:Lorg/apache/neethi/Policy;
       9: return

  public org.apache.cxf.ws.policy.EndpointPolicyImpl(org.apache.cxf.service.model.EndpointInfo, org.apache.cxf.ws.policy.PolicyEngineImpl, boolean, org.apache.cxf.ws.policy.Assertor);
    Code:
       0: aload_0
       1: invokespecial #1                  // Method java/lang/Object."<init>":()V
       4: aload_0
       5: aload_1
       6: putfield      #3                  // Field ei:Lorg/apache/cxf/service/model/EndpointInfo;
       9: aload_0
      10: aload_2
      11: putfield      #4                  // Field engine:Lorg/apache/cxf/ws/policy/PolicyEngineImpl;
      14: aload_0
      15: iload_3
      16: putfield      #5                  // Field requestor:Z
      19: aload_0
      20: aload         4
      22: putfield      #6                  // Field assertor:Lorg/apache/cxf/ws/policy/Assertor;
      25: return

  public org.apache.neethi.Policy getPolicy();
    Code:
       0: aload_0
       1: getfield      #2                  // Field policy:Lorg/apache/neethi/Policy;
       4: areturn

  public org.apache.cxf.ws.policy.Assertor getAssertor();
    Code:
       0: aload_0
       1: getfield      #6                  // Field assertor:Lorg/apache/cxf/ws/policy/Assertor;
       4: areturn

  public org.apache.cxf.ws.policy.EndpointPolicy updatePolicy(org.apache.neethi.Policy, org.apache.cxf.message.Message);
    Code:
       0: aload_0
       1: invokevirtual #7                  // Method createEndpointPolicy:()Lorg/apache/cxf/ws/policy/EndpointPolicyImpl;
       4: astore_3
       5: aload_1
       6: invokestatic  #8                  // Method org/apache/cxf/ws/policy/PolicyUtils.isEmptyPolicy:(Lorg/apache/neethi/Policy;)Z
       9: ifne          53
      12: aload_1
      13: aload_0
      14: getfield      #4                  // Field engine:Lorg/apache/cxf/ws/policy/PolicyEngineImpl;
      17: ifnonnull     24
      20: aconst_null
      21: goto          31
      24: aload_0
      25: getfield      #4                  // Field engine:Lorg/apache/cxf/ws/policy/PolicyEngineImpl;
      28: invokevirtual #9                  // Method org/apache/cxf/ws/policy/PolicyEngineImpl.getRegistry:()Lorg/apache/neethi/PolicyRegistry;
      31: iconst_1
      32: invokevirtual #10                 // Method org/apache/neethi/Policy.normalize:(Lorg/apache/neethi/PolicyRegistry;Z)Lorg/apache/neethi/Policy;
      35: astore        4
      37: aload_3
      38: aload_0
      39: invokevirtual #11                 // Method getPolicy:()Lorg/apache/neethi/Policy;
      42: aload         4
      44: invokevirtual #12                 // Method org/apache/neethi/Policy.merge:(Lorg/apache/neethi/Policy;)Lorg/apache/neethi/Policy;
      47: invokevirtual #13                 // Method setPolicy:(Lorg/apache/neethi/Policy;)V
      50: goto          80
      53: new           #14                 // class org/apache/neethi/Policy
      56: dup
      57: invokespecial #15                 // Method org/apache/neethi/Policy."<init>":()V
      60: astore        4
      62: aload         4
      64: aload_0
      65: invokevirtual #11                 // Method getPolicy:()Lorg/apache/neethi/Policy;
      68: invokevirtual #16                 // Method org/apache/neethi/Policy.getPolicyComponents:()Ljava/util/List;
      71: invokevirtual #17                 // Method org/apache/neethi/Policy.addPolicyComponents:(Ljava/util/List;)V
      74: aload_3
      75: aload         4
      77: invokevirtual #13                 // Method setPolicy:(Lorg/apache/neethi/Policy;)V
      80: aload_3
      81: invokevirtual #18                 // Method checkExactlyOnes:()V
      84: aload_3
      85: aload_2
      86: invokevirtual #19                 // Method finalizeConfig:(Lorg/apache/cxf/message/Message;)V
      89: aload_3
      90: areturn

  public java.util.Collection<org.apache.neethi.Assertion> getChosenAlternative();
    Code:
       0: aload_0
       1: getfield      #20                 // Field chosenAlternative:Ljava/util/Collection;
       4: areturn

  public java.util.Collection<org.apache.neethi.Assertion> getVocabulary(org.apache.cxf.message.Message);
    Code:
       0: aload_0
       1: getfield      #21                 // Field vocabulary:Ljava/util/Collection;
       4: ifnonnull     12
       7: aload_0
       8: aload_1
       9: invokevirtual #22                 // Method initializeVocabulary:(Lorg/apache/cxf/message/Message;)V
      12: aload_0
      13: getfield      #21                 // Field vocabulary:Ljava/util/Collection;
      16: areturn

  public java.util.Collection<org.apache.neethi.Assertion> getFaultVocabulary(org.apache.cxf.message.Message);
    Code:
       0: aload_0
       1: getfield      #21                 // Field vocabulary:Ljava/util/Collection;
       4: ifnonnull     12
       7: aload_0
       8: aload_1
       9: invokevirtual #22                 // Method initializeVocabulary:(Lorg/apache/cxf/message/Message;)V
      12: aload_0
      13: getfield      #23                 // Field faultVocabulary:Ljava/util/Collection;
      16: areturn

  public java.util.List<org.apache.cxf.interceptor.Interceptor<? extends org.apache.cxf.message.Message>> getInterceptors(org.apache.cxf.message.Message);
    Code:
       0: aload_0
       1: getfield      #24                 // Field interceptors:Ljava/util/List;
       4: ifnonnull     12
       7: aload_0
       8: aload_1
       9: invokevirtual #25                 // Method initializeInterceptors:(Lorg/apache/cxf/message/Message;)V
      12: aload_0
      13: getfield      #24                 // Field interceptors:Ljava/util/List;
      16: areturn

  public java.util.List<org.apache.cxf.interceptor.Interceptor<? extends org.apache.cxf.message.Message>> getFaultInterceptors(org.apache.cxf.message.Message);
    Code:
       0: aload_0
       1: getfield      #24                 // Field interceptors:Ljava/util/List;
       4: ifnonnull     12
       7: aload_0
       8: aload_1
       9: invokevirtual #25                 // Method initializeInterceptors:(Lorg/apache/cxf/message/Message;)V
      12: aload_0
      13: getfield      #26                 // Field faultInterceptors:Ljava/util/List;
      16: areturn

  public void initialize(org.apache.cxf.message.Message);
    Code:
       0: aload_0
       1: aload_1
       2: invokevirtual #27                 // Method initializePolicy:(Lorg/apache/cxf/message/Message;)V
       5: aload_0
       6: invokevirtual #18                 // Method checkExactlyOnes:()V
       9: aload_0
      10: aload_1
      11: invokevirtual #19                 // Method finalizeConfig:(Lorg/apache/cxf/message/Message;)V
      14: return

  void finalizeConfig(org.apache.cxf.message.Message);
    Code:
       0: aload_0
       1: aload_1
       2: invokevirtual #28                 // Method chooseAlternative:(Lorg/apache/cxf/message/Message;)V
       5: return

  void initializePolicy(org.apache.cxf.message.Message);
    Code:
       0: aload_0
       1: getfield      #4                  // Field engine:Lorg/apache/cxf/ws/policy/PolicyEngineImpl;
       4: ifnull        78
       7: aload_0
       8: aload_0
       9: getfield      #4                  // Field engine:Lorg/apache/cxf/ws/policy/PolicyEngineImpl;
      12: aload_0
      13: getfield      #3                  // Field ei:Lorg/apache/cxf/service/model/EndpointInfo;
      16: invokevirtual #29                 // Method org/apache/cxf/service/model/EndpointInfo.getService:()Lorg/apache/cxf/service/model/ServiceInfo;
      19: aload_1
      20: invokevirtual #30                 // Method org/apache/cxf/ws/policy/PolicyEngineImpl.getAggregatedServicePolicy:(Lorg/apache/cxf/service/model/ServiceInfo;Lorg/apache/cxf/message/Message;)Lorg/apache/neethi/Policy;
      23: putfield      #2                  // Field policy:Lorg/apache/neethi/Policy;
      26: aload_0
      27: aload_0
      28: getfield      #2                  // Field policy:Lorg/apache/neethi/Policy;
      31: aload_0
      32: getfield      #4                  // Field engine:Lorg/apache/cxf/ws/policy/PolicyEngineImpl;
      35: aload_0
      36: getfield      #3                  // Field ei:Lorg/apache/cxf/service/model/EndpointInfo;
      39: aload_1
      40: invokevirtual #31                 // Method org/apache/cxf/ws/policy/PolicyEngineImpl.getAggregatedEndpointPolicy:(Lorg/apache/cxf/service/model/EndpointInfo;Lorg/apache/cxf/message/Message;)Lorg/apache/neethi/Policy;
      43: invokevirtual #12                 // Method org/apache/neethi/Policy.merge:(Lorg/apache/neethi/Policy;)Lorg/apache/neethi/Policy;
      46: putfield      #2                  // Field policy:Lorg/apache/neethi/Policy;
      49: aload_0
      50: getfield      #2                  // Field policy:Lorg/apache/neethi/Policy;
      53: invokevirtual #32                 // Method org/apache/neethi/Policy.isEmpty:()Z
      56: ifne          78
      59: aload_0
      60: aload_0
      61: getfield      #2                  // Field policy:Lorg/apache/neethi/Policy;
      64: aload_0
      65: getfield      #4                  // Field engine:Lorg/apache/cxf/ws/policy/PolicyEngineImpl;
      68: invokevirtual #9                  // Method org/apache/cxf/ws/policy/PolicyEngineImpl.getRegistry:()Lorg/apache/neethi/PolicyRegistry;
      71: iconst_1
      72: invokevirtual #10                 // Method org/apache/neethi/Policy.normalize:(Lorg/apache/neethi/PolicyRegistry;Z)Lorg/apache/neethi/Policy;
      75: putfield      #2                  // Field policy:Lorg/apache/neethi/Policy;
      78: return

  void chooseAlternative(org.apache.cxf.message.Message);
    Code:
       0: aconst_null
       1: astore_2
       2: aload_0
       3: getfield      #5                  // Field requestor:Z
       6: ifeq          56
       9: aload_0
      10: getfield      #4                  // Field engine:Lorg/apache/cxf/ws/policy/PolicyEngineImpl;
      13: invokevirtual #33                 // Method org/apache/cxf/ws/policy/PolicyEngineImpl.isEnabled:()Z
      16: ifeq          49
      19: aload_0
      20: getfield      #4                  // Field engine:Lorg/apache/cxf/ws/policy/PolicyEngineImpl;
      23: invokevirtual #34                 // Method org/apache/cxf/ws/policy/PolicyEngineImpl.getAlternativeSelector:()Lorg/apache/cxf/ws/policy/AlternativeSelector;
      26: aload_0
      27: getfield      #2                  // Field policy:Lorg/apache/neethi/Policy;
      30: aload_0
      31: getfield      #4                  // Field engine:Lorg/apache/cxf/ws/policy/PolicyEngineImpl;
      34: aload_0
      35: getfield      #6                  // Field assertor:Lorg/apache/cxf/ws/policy/Assertor;
      38: aconst_null
      39: aload_1
      40: invokeinterface #35,  6           // InterfaceMethod org/apache/cxf/ws/policy/AlternativeSelector.selectAlternative:(Lorg/apache/neethi/Policy;Lorg/apache/cxf/ws/policy/PolicyEngine;Lorg/apache/cxf/ws/policy/Assertor;Ljava/util/List;Lorg/apache/cxf/message/Message;)Ljava/util/Collection;
      45: astore_2
      46: goto          62
      49: invokestatic  #36                 // Method java/util/Collections.emptyList:()Ljava/util/List;
      52: astore_2
      53: goto          62
      56: aload_0
      57: aload_1
      58: invokevirtual #37                 // Method getSupportedAlternatives:(Lorg/apache/cxf/message/Message;)Ljava/util/Collection;
      61: astore_2
      62: aconst_null
      63: aload_2
      64: if_acmpne     91
      67: new           #38                 // class org/apache/cxf/ws/policy/PolicyException
      70: dup
      71: new           #39                 // class org/apache/cxf/common/i18n/Message
      74: dup
      75: ldc           #40                 // String NO_ALTERNATIVE_EXC
      77: getstatic     #41                 // Field BUNDLE:Ljava/util/ResourceBundle;
      80: iconst_0
      81: anewarray     #42                 // class java/lang/Object
      84: invokespecial #43                 // Method org/apache/cxf/common/i18n/Message."<init>":(Ljava/lang/String;Ljava/util/ResourceBundle;[Ljava/lang/Object;)V
      87: invokespecial #44                 // Method org/apache/cxf/ws/policy/PolicyException."<init>":(Lorg/apache/cxf/common/i18n/Message;)V
      90: athrow
      91: aload_0
      92: aload_2
      93: invokevirtual #45                 // Method setChosenAlternative:(Ljava/util/Collection;)V
      96: return

  protected java.util.Collection<org.apache.neethi.Assertion> getSupportedAlternatives(org.apache.cxf.message.Message);
    Code:
       0: new           #46                 // class java/util/ArrayList
       3: dup
       4: invokespecial #47                 // Method java/util/ArrayList."<init>":()V
       7: astore_2
       8: aload_0
       9: getfield      #2                  // Field policy:Lorg/apache/neethi/Policy;
      12: invokevirtual #48                 // Method org/apache/neethi/Policy.getAlternatives:()Ljava/util/Iterator;
      15: astore_3
      16: aload_3
      17: invokeinterface #49,  1           // InterfaceMethod java/util/Iterator.hasNext:()Z
      22: ifeq          65
      25: aload_3
      26: invokeinterface #50,  1           // InterfaceMethod java/util/Iterator.next:()Ljava/lang/Object;
      31: checkcast     #51                 // class java/util/List
      34: astore        4
      36: aload_0
      37: getfield      #4                  // Field engine:Lorg/apache/cxf/ws/policy/PolicyEngineImpl;
      40: aload         4
      42: aload_0
      43: getfield      #6                  // Field assertor:Lorg/apache/cxf/ws/policy/Assertor;
      46: aload_1
      47: invokevirtual #52                 // Method org/apache/cxf/ws/policy/PolicyEngineImpl.supportsAlternative:(Ljava/util/Collection;Lorg/apache/cxf/ws/policy/Assertor;Lorg/apache/cxf/message/Message;)Z
      50: ifeq          62
      53: aload_2
      54: aload         4
      56: invokeinterface #53,  2           // InterfaceMethod java/util/Collection.addAll:(Ljava/util/Collection;)Z
      61: pop
      62: goto          16
      65: aload_2
      66: areturn

  private void addAll(java.util.Collection<org.apache.neethi.Assertion>, java.util.Collection<org.apache.neethi.Assertion>);
    Code:
       0: aload_2
       1: invokeinterface #54,  1           // InterfaceMethod java/util/Collection.iterator:()Ljava/util/Iterator;
       6: astore_3
       7: aload_3
       8: invokeinterface #49,  1           // InterfaceMethod java/util/Iterator.hasNext:()Z
      13: ifeq          50
      16: aload_3
      17: invokeinterface #50,  1           // InterfaceMethod java/util/Iterator.next:()Ljava/lang/Object;
      22: checkcast     #55                 // class org/apache/neethi/Assertion
      25: astore        4
      27: aload_1
      28: aload         4
      30: invokeinterface #56,  2           // InterfaceMethod java/util/Collection.contains:(Ljava/lang/Object;)Z
      35: ifne          47
      38: aload_1
      39: aload         4
      41: invokeinterface #57,  2           // InterfaceMethod java/util/Collection.add:(Ljava/lang/Object;)Z
      46: pop
      47: goto          7
      50: return

  synchronized void initializeVocabulary(org.apache.cxf.message.Message);
    Code:
       0: aload_0
       1: getfield      #21                 // Field vocabulary:Ljava/util/Collection;
       4: ifnull        8
       7: return
       8: new           #46                 // class java/util/ArrayList
      11: dup
      12: invokespecial #47                 // Method java/util/ArrayList."<init>":()V
      15: astore_2
      16: aconst_null
      17: astore_3
      18: aload_0
      19: getfield      #5                  // Field requestor:Z
      22: ifeq          33
      25: new           #46                 // class java/util/ArrayList
      28: dup
      29: invokespecial #47                 // Method java/util/ArrayList."<init>":()V
      32: astore_3
      33: aload_0
      34: invokevirtual #58                 // Method getChosenAlternative:()Ljava/util/Collection;
      37: ifnull        112
      40: aload_0
      41: invokevirtual #58                 // Method getChosenAlternative:()Ljava/util/Collection;
      44: invokeinterface #54,  1           // InterfaceMethod java/util/Collection.iterator:()Ljava/util/Iterator;
      49: astore        4
      51: aload         4
      53: invokeinterface #49,  1           // InterfaceMethod java/util/Iterator.hasNext:()Z
      58: ifeq          112
      61: aload         4
      63: invokeinterface #50,  1           // InterfaceMethod java/util/Iterator.next:()Ljava/lang/Object;
      68: checkcast     #55                 // class org/apache/neethi/Assertion
      71: astore        5
      73: aload         5
      75: invokeinterface #59,  1           // InterfaceMethod org/apache/neethi/Assertion.isOptional:()Z
      80: ifeq          86
      83: goto          51
      86: aload_2
      87: aload         5
      89: invokeinterface #60,  2           // InterfaceMethod java/util/List.add:(Ljava/lang/Object;)Z
      94: pop
      95: aconst_null
      96: aload_3
      97: if_acmpeq     109
     100: aload_3
     101: aload         5
     103: invokeinterface #60,  2           // InterfaceMethod java/util/List.add:(Ljava/lang/Object;)Z
     108: pop
     109: goto          51
     112: aload_0
     113: getfield      #3                  // Field ei:Lorg/apache/cxf/service/model/EndpointInfo;
     116: invokevirtual #61                 // Method org/apache/cxf/service/model/EndpointInfo.getBinding:()Lorg/apache/cxf/service/model/BindingInfo;
     119: invokevirtual #62                 // Method org/apache/cxf/service/model/BindingInfo.getOperations:()Ljava/util/Collection;
     122: invokeinterface #54,  1           // InterfaceMethod java/util/Collection.iterator:()Ljava/util/Iterator;
     127: astore        4
     129: aload         4
     131: invokeinterface #49,  1           // InterfaceMethod java/util/Iterator.hasNext:()Z
     136: ifeq          351
     139: aload         4
     141: invokeinterface #50,  1           // InterfaceMethod java/util/Iterator.next:()Ljava/lang/Object;
     146: checkcast     #63                 // class org/apache/cxf/service/model/BindingOperationInfo
     149: astore        5
     151: aconst_null
     152: astore        6
     154: aload_0
     155: getfield      #5                  // Field requestor:Z
     158: ifne          204
     161: aload_0
     162: getfield      #4                  // Field engine:Lorg/apache/cxf/ws/policy/PolicyEngineImpl;
     165: aload_0
     166: getfield      #3                  // Field ei:Lorg/apache/cxf/service/model/EndpointInfo;
     169: aload         5
     171: aload_1
     172: invokevirtual #64                 // Method org/apache/cxf/ws/policy/PolicyEngineImpl.getEffectiveServerRequestPolicy:(Lorg/apache/cxf/service/model/EndpointInfo;Lorg/apache/cxf/service/model/BindingOperationInfo;Lorg/apache/cxf/message/Message;)Lorg/apache/cxf/ws/policy/EffectivePolicy;
     175: astore        6
     177: aload_0
     178: getfield      #4                  // Field engine:Lorg/apache/cxf/ws/policy/PolicyEngineImpl;
     181: aload         6
     183: iconst_0
     184: invokevirtual #65                 // Method org/apache/cxf/ws/policy/PolicyEngineImpl.getAssertions:(Lorg/apache/cxf/ws/policy/EffectivePolicy;Z)Ljava/util/Collection;
     187: astore        7
     189: aload         7
     191: ifnull        201
     194: aload_0
     195: aload_2
     196: aload         7
     198: invokespecial #66                 // Method addAll:(Ljava/util/Collection;Ljava/util/Collection;)V
     201: goto          348
     204: aload_0
     205: getfield      #4                  // Field engine:Lorg/apache/cxf/ws/policy/PolicyEngineImpl;
     208: aload_0
     209: getfield      #3                  // Field ei:Lorg/apache/cxf/service/model/EndpointInfo;
     212: aload         5
     214: aload_1
     215: invokevirtual #67                 // Method org/apache/cxf/ws/policy/PolicyEngineImpl.getEffectiveClientResponsePolicy:(Lorg/apache/cxf/service/model/EndpointInfo;Lorg/apache/cxf/service/model/BindingOperationInfo;Lorg/apache/cxf/message/Message;)Lorg/apache/cxf/ws/policy/EffectivePolicy;
     218: astore        6
     220: aload_0
     221: getfield      #4                  // Field engine:Lorg/apache/cxf/ws/policy/PolicyEngineImpl;
     224: aload         6
     226: iconst_0
     227: invokevirtual #65                 // Method org/apache/cxf/ws/policy/PolicyEngineImpl.getAssertions:(Lorg/apache/cxf/ws/policy/EffectivePolicy;Z)Ljava/util/Collection;
     230: astore        7
     232: aload         7
     234: ifnull        256
     237: aload_0
     238: aload_2
     239: aload         7
     241: invokespecial #66                 // Method addAll:(Ljava/util/Collection;Ljava/util/Collection;)V
     244: aconst_null
     245: aload_3
     246: if_acmpeq     256
     249: aload_0
     250: aload_3
     251: aload         7
     253: invokespecial #66                 // Method addAll:(Ljava/util/Collection;Ljava/util/Collection;)V
     256: aload         5
     258: invokevirtual #68                 // Method org/apache/cxf/service/model/BindingOperationInfo.getFaults:()Ljava/util/Collection;
     261: ifnull        348
     264: aconst_null
     265: aload_3
     266: if_acmpeq     348
     269: aload         5
     271: invokevirtual #68                 // Method org/apache/cxf/service/model/BindingOperationInfo.getFaults:()Ljava/util/Collection;
     274: invokeinterface #54,  1           // InterfaceMethod java/util/Collection.iterator:()Ljava/util/Iterator;
     279: astore        8
     281: aload         8
     283: invokeinterface #49,  1           // InterfaceMethod java/util/Iterator.hasNext:()Z
     288: ifeq          348
     291: aload         8
     293: invokeinterface #50,  1           // InterfaceMethod java/util/Iterator.next:()Ljava/lang/Object;
     298: checkcast     #69                 // class org/apache/cxf/service/model/BindingFaultInfo
     301: astore        9
     303: aload_0
     304: getfield      #4                  // Field engine:Lorg/apache/cxf/ws/policy/PolicyEngineImpl;
     307: aload_0
     308: getfield      #3                  // Field ei:Lorg/apache/cxf/service/model/EndpointInfo;
     311: aload         5
     313: aload         9
     315: aload_1
     316: invokevirtual #70                 // Method org/apache/cxf/ws/policy/PolicyEngineImpl.getEffectiveClientFaultPolicy:(Lorg/apache/cxf/service/model/EndpointInfo;Lorg/apache/cxf/service/model/BindingOperationInfo;Lorg/apache/cxf/service/model/BindingFaultInfo;Lorg/apache/cxf/message/Message;)Lorg/apache/cxf/ws/policy/EffectivePolicy;
     319: astore        6
     321: aload_0
     322: getfield      #4                  // Field engine:Lorg/apache/cxf/ws/policy/PolicyEngineImpl;
     325: aload         6
     327: iconst_0
     328: invokevirtual #65                 // Method org/apache/cxf/ws/policy/PolicyEngineImpl.getAssertions:(Lorg/apache/cxf/ws/policy/EffectivePolicy;Z)Ljava/util/Collection;
     331: astore        7
     333: aload         7
     335: ifnull        345
     338: aload_0
     339: aload_3
     340: aload         7
     342: invokespecial #66                 // Method addAll:(Ljava/util/Collection;Ljava/util/Collection;)V
     345: goto          281
     348: goto          129
     351: aload_0
     352: getfield      #5                  // Field requestor:Z
     355: ifeq          363
     358: aload_0
     359: aload_3
     360: putfield      #23                 // Field faultVocabulary:Ljava/util/Collection;
     363: aload_0
     364: aload_2
     365: putfield      #21                 // Field vocabulary:Ljava/util/Collection;
     368: return

  java.util.Collection<org.apache.neethi.Assertion> getSupportedAlternatives(org.apache.neethi.Policy, org.apache.cxf.message.Message);
    Code:
       0: new           #46                 // class java/util/ArrayList
       3: dup
       4: invokespecial #47                 // Method java/util/ArrayList."<init>":()V
       7: astore_3
       8: aload_1
       9: invokevirtual #48                 // Method org/apache/neethi/Policy.getAlternatives:()Ljava/util/Iterator;
      12: astore        4
      14: aload         4
      16: invokeinterface #49,  1           // InterfaceMethod java/util/Iterator.hasNext:()Z
      21: ifeq          62
      24: aload         4
      26: invokeinterface #50,  1           // InterfaceMethod java/util/Iterator.next:()Ljava/lang/Object;
      31: checkcast     #51                 // class java/util/List
      34: astore        5
      36: aload_0
      37: getfield      #4                  // Field engine:Lorg/apache/cxf/ws/policy/PolicyEngineImpl;
      40: aload         5
      42: aconst_null
      43: aload_2
      44: invokevirtual #52                 // Method org/apache/cxf/ws/policy/PolicyEngineImpl.supportsAlternative:(Ljava/util/Collection;Lorg/apache/cxf/ws/policy/Assertor;Lorg/apache/cxf/message/Message;)Z
      47: ifeq          59
      50: aload_3
      51: aload         5
      53: invokeinterface #53,  2           // InterfaceMethod java/util/Collection.addAll:(Ljava/util/Collection;)Z
      58: pop
      59: goto          14
      62: aload_3
      63: areturn

  void initializeInterceptors(org.apache.cxf.ws.policy.PolicyInterceptorProviderRegistry, java.util.Set<org.apache.cxf.interceptor.Interceptor<? extends org.apache.cxf.message.Message>>, org.apache.neethi.Assertion, boolean, org.apache.cxf.message.Message);
    Code:
       0: aload_3
       1: invokeinterface #71,  1           // InterfaceMethod org/apache/neethi/Assertion.getName:()Ljavax/xml/namespace/QName;
       6: astore        6
       8: iload         4
      10: ifeq          24
      13: aload_1
      14: aload         6
      16: invokeinterface #72,  2           // InterfaceMethod org/apache/cxf/ws/policy/PolicyInterceptorProviderRegistry.getInFaultInterceptorsForAssertion:(Ljavax/xml/namespace/QName;)Ljava/util/List;
      21: goto          32
      24: aload_1
      25: aload         6
      27: invokeinterface #73,  2           // InterfaceMethod org/apache/cxf/ws/policy/PolicyInterceptorProviderRegistry.getInInterceptorsForAssertion:(Ljavax/xml/namespace/QName;)Ljava/util/List;
      32: astore        7
      34: aload_2
      35: aload         7
      37: invokeinterface #74,  2           // InterfaceMethod java/util/Set.addAll:(Ljava/util/Collection;)Z
      42: pop
      43: aload_3
      44: instanceof    #75                 // class org/apache/neethi/PolicyContainingAssertion
      47: ifeq          118
      50: aload_3
      51: checkcast     #75                 // class org/apache/neethi/PolicyContainingAssertion
      54: invokeinterface #76,  1           // InterfaceMethod org/apache/neethi/PolicyContainingAssertion.getPolicy:()Lorg/apache/neethi/Policy;
      59: astore        8
      61: aload         8
      63: ifnull        118
      66: aload_0
      67: aload         8
      69: aload         5
      71: invokevirtual #77                 // Method getSupportedAlternatives:(Lorg/apache/neethi/Policy;Lorg/apache/cxf/message/Message;)Ljava/util/Collection;
      74: invokeinterface #54,  1           // InterfaceMethod java/util/Collection.iterator:()Ljava/util/Iterator;
      79: astore        9
      81: aload         9
      83: invokeinterface #49,  1           // InterfaceMethod java/util/Iterator.hasNext:()Z
      88: ifeq          118
      91: aload         9
      93: invokeinterface #50,  1           // InterfaceMethod java/util/Iterator.next:()Ljava/lang/Object;
      98: checkcast     #55                 // class org/apache/neethi/Assertion
     101: astore        10
     103: aload_0
     104: aload_1
     105: aload_2
     106: aload         10
     108: iload         4
     110: aload         5
     112: invokevirtual #78                 // Method initializeInterceptors:(Lorg/apache/cxf/ws/policy/PolicyInterceptorProviderRegistry;Ljava/util/Set;Lorg/apache/neethi/Assertion;ZLorg/apache/cxf/message/Message;)V
     115: goto          81
     118: return

  synchronized void initializeInterceptors(org.apache.cxf.message.Message);
    Code:
       0: aload_0
       1: getfield      #24                 // Field interceptors:Ljava/util/List;
       4: ifnull        8
       7: return
       8: aload_0
       9: getfield      #4                  // Field engine:Lorg/apache/cxf/ws/policy/PolicyEngineImpl;
      12: ifnull        43
      15: aload_0
      16: getfield      #4                  // Field engine:Lorg/apache/cxf/ws/policy/PolicyEngineImpl;
      19: invokevirtual #79                 // Method org/apache/cxf/ws/policy/PolicyEngineImpl.getBus:()Lorg/apache/cxf/Bus;
      22: ifnull        43
      25: aload_0
      26: getfield      #4                  // Field engine:Lorg/apache/cxf/ws/policy/PolicyEngineImpl;
      29: invokevirtual #79                 // Method org/apache/cxf/ws/policy/PolicyEngineImpl.getBus:()Lorg/apache/cxf/Bus;
      32: ldc_w         #80                 // class org/apache/cxf/ws/policy/PolicyInterceptorProviderRegistry
      35: invokeinterface #81,  2           // InterfaceMethod org/apache/cxf/Bus.getExtension:(Ljava/lang/Class;)Ljava/lang/Object;
      40: ifnonnull     44
      43: return
      44: aload_0
      45: getfield      #4                  // Field engine:Lorg/apache/cxf/ws/policy/PolicyEngineImpl;
      48: invokevirtual #79                 // Method org/apache/cxf/ws/policy/PolicyEngineImpl.getBus:()Lorg/apache/cxf/Bus;
      51: ldc_w         #80                 // class org/apache/cxf/ws/policy/PolicyInterceptorProviderRegistry
      54: invokeinterface #81,  2           // InterfaceMethod org/apache/cxf/Bus.getExtension:(Ljava/lang/Class;)Ljava/lang/Object;
      59: checkcast     #80                 // class org/apache/cxf/ws/policy/PolicyInterceptorProviderRegistry
      62: astore_2
      63: new           #82                 // class java/util/LinkedHashSet
      66: dup
      67: invokespecial #83                 // Method java/util/LinkedHashSet."<init>":()V
      70: astore_3
      71: aload_0
      72: invokevirtual #58                 // Method getChosenAlternative:()Ljava/util/Collection;
      75: ifnull        124
      78: aload_0
      79: invokevirtual #58                 // Method getChosenAlternative:()Ljava/util/Collection;
      82: invokeinterface #54,  1           // InterfaceMethod java/util/Collection.iterator:()Ljava/util/Iterator;
      87: astore        4
      89: aload         4
      91: invokeinterface #49,  1           // InterfaceMethod java/util/Iterator.hasNext:()Z
      96: ifeq          124
      99: aload         4
     101: invokeinterface #50,  1           // InterfaceMethod java/util/Iterator.next:()Ljava/lang/Object;
     106: checkcast     #55                 // class org/apache/neethi/Assertion
     109: astore        5
     111: aload_0
     112: aload_2
     113: aload_3
     114: aload         5
     116: iconst_0
     117: aload_1
     118: invokevirtual #78                 // Method initializeInterceptors:(Lorg/apache/cxf/ws/policy/PolicyInterceptorProviderRegistry;Ljava/util/Set;Lorg/apache/neethi/Assertion;ZLorg/apache/cxf/message/Message;)V
     121: goto          89
     124: aconst_null
     125: astore        4
     127: aload_0
     128: getfield      #5                  // Field requestor:Z
     131: ifeq          211
     134: new           #46                 // class java/util/ArrayList
     137: dup
     138: aload_3
     139: invokespecial #84                 // Method java/util/ArrayList."<init>":(Ljava/util/Collection;)V
     142: astore        4
     144: aload_3
     145: invokeinterface #85,  1           // InterfaceMethod java/util/Set.clear:()V
     150: aload_0
     151: invokevirtual #58                 // Method getChosenAlternative:()Ljava/util/Collection;
     154: invokeinterface #54,  1           // InterfaceMethod java/util/Collection.iterator:()Ljava/util/Iterator;
     159: astore        5
     161: aload         5
     163: invokeinterface #49,  1           // InterfaceMethod java/util/Iterator.hasNext:()Z
     168: ifeq          196
     171: aload         5
     173: invokeinterface #50,  1           // InterfaceMethod java/util/Iterator.next:()Ljava/lang/Object;
     178: checkcast     #55                 // class org/apache/neethi/Assertion
     181: astore        6
     183: aload_0
     184: aload_2
     185: aload_3
     186: aload         6
     188: iconst_1
     189: aload_1
     190: invokevirtual #78                 // Method initializeInterceptors:(Lorg/apache/cxf/ws/policy/PolicyInterceptorProviderRegistry;Ljava/util/Set;Lorg/apache/neethi/Assertion;ZLorg/apache/cxf/message/Message;)V
     193: goto          161
     196: aload_0
     197: new           #46                 // class java/util/ArrayList
     200: dup
     201: aload_3
     202: invokespecial #84                 // Method java/util/ArrayList."<init>":(Ljava/util/Collection;)V
     205: putfield      #26                 // Field faultInterceptors:Ljava/util/List;
     208: goto          411
     211: aload_0
     212: getfield      #3                  // Field ei:Lorg/apache/cxf/service/model/EndpointInfo;
     215: ifnull        401
     218: aload_0
     219: getfield      #3                  // Field ei:Lorg/apache/cxf/service/model/EndpointInfo;
     222: invokevirtual #61                 // Method org/apache/cxf/service/model/EndpointInfo.getBinding:()Lorg/apache/cxf/service/model/BindingInfo;
     225: ifnull        401
     228: aload_0
     229: getfield      #3                  // Field ei:Lorg/apache/cxf/service/model/EndpointInfo;
     232: invokevirtual #61                 // Method org/apache/cxf/service/model/EndpointInfo.getBinding:()Lorg/apache/cxf/service/model/BindingInfo;
     235: invokevirtual #62                 // Method org/apache/cxf/service/model/BindingInfo.getOperations:()Ljava/util/Collection;
     238: invokeinterface #54,  1           // InterfaceMethod java/util/Collection.iterator:()Ljava/util/Iterator;
     243: astore        5
     245: aload         5
     247: invokeinterface #49,  1           // InterfaceMethod java/util/Iterator.hasNext:()Z
     252: ifeq          388
     255: aload         5
     257: invokeinterface #50,  1           // InterfaceMethod java/util/Iterator.next:()Ljava/lang/Object;
     262: checkcast     #63                 // class org/apache/cxf/service/model/BindingOperationInfo
     265: astore        6
     267: aload_0
     268: getfield      #4                  // Field engine:Lorg/apache/cxf/ws/policy/PolicyEngineImpl;
     271: aload_0
     272: getfield      #3                  // Field ei:Lorg/apache/cxf/service/model/EndpointInfo;
     275: aload         6
     277: aload_1
     278: invokevirtual #64                 // Method org/apache/cxf/ws/policy/PolicyEngineImpl.getEffectiveServerRequestPolicy:(Lorg/apache/cxf/service/model/EndpointInfo;Lorg/apache/cxf/service/model/BindingOperationInfo;Lorg/apache/cxf/message/Message;)Lorg/apache/cxf/ws/policy/EffectivePolicy;
     281: astore        7
     283: aload         7
     285: ifnull        245
     288: aload         7
     290: invokeinterface #86,  1           // InterfaceMethod org/apache/cxf/ws/policy/EffectivePolicy.getPolicy:()Lorg/apache/neethi/Policy;
     295: ifnull        245
     298: aload         7
     300: invokeinterface #86,  1           // InterfaceMethod org/apache/cxf/ws/policy/EffectivePolicy.getPolicy:()Lorg/apache/neethi/Policy;
     305: invokevirtual #32                 // Method org/apache/neethi/Policy.isEmpty:()Z
     308: ifeq          314
     311: goto          245
     314: aload_0
     315: getfield      #4                  // Field engine:Lorg/apache/cxf/ws/policy/PolicyEngineImpl;
     318: aload         7
     320: iconst_1
     321: invokevirtual #65                 // Method org/apache/cxf/ws/policy/PolicyEngineImpl.getAssertions:(Lorg/apache/cxf/ws/policy/EffectivePolicy;Z)Ljava/util/Collection;
     324: astore        8
     326: aload         8
     328: ifnull        385
     331: aload         8
     333: invokeinterface #54,  1           // InterfaceMethod java/util/Collection.iterator:()Ljava/util/Iterator;
     338: astore        9
     340: aload         9
     342: invokeinterface #49,  1           // InterfaceMethod java/util/Iterator.hasNext:()Z
     347: ifeq          385
     350: aload         9
     352: invokeinterface #50,  1           // InterfaceMethod java/util/Iterator.next:()Ljava/lang/Object;
     357: checkcast     #55                 // class org/apache/neethi/Assertion
     360: astore        10
     362: aload_0
     363: aload_2
     364: aload_3
     365: aload         10
     367: iconst_0
     368: aload_1
     369: invokevirtual #78                 // Method initializeInterceptors:(Lorg/apache/cxf/ws/policy/PolicyInterceptorProviderRegistry;Ljava/util/Set;Lorg/apache/neethi/Assertion;ZLorg/apache/cxf/message/Message;)V
     372: aload_0
     373: aload_2
     374: aload_3
     375: aload         10
     377: iconst_1
     378: aload_1
     379: invokevirtual #78                 // Method initializeInterceptors:(Lorg/apache/cxf/ws/policy/PolicyInterceptorProviderRegistry;Ljava/util/Set;Lorg/apache/neethi/Assertion;ZLorg/apache/cxf/message/Message;)V
     382: goto          340
     385: goto          245
     388: new           #46                 // class java/util/ArrayList
     391: dup
     392: aload_3
     393: invokespecial #84                 // Method java/util/ArrayList."<init>":(Ljava/util/Collection;)V
     396: astore        4
     398: goto          411
     401: new           #46                 // class java/util/ArrayList
     404: dup
     405: aload_3
     406: invokespecial #84                 // Method java/util/ArrayList."<init>":(Ljava/util/Collection;)V
     409: astore        4
     411: aload_0
     412: aload         4
     414: putfield      #24                 // Field interceptors:Ljava/util/List;
     417: return

  void setPolicy(org.apache.neethi.Policy);
    Code:
       0: aload_0
       1: aload_1
       2: putfield      #2                  // Field policy:Lorg/apache/neethi/Policy;
       5: return

  void setChosenAlternative(java.util.Collection<org.apache.neethi.Assertion>);
    Code:
       0: aload_0
       1: aload_1
       2: putfield      #20                 // Field chosenAlternative:Ljava/util/Collection;
       5: return

  void setVocabulary(java.util.Collection<org.apache.neethi.Assertion>);
    Code:
       0: aload_0
       1: aload_1
       2: putfield      #21                 // Field vocabulary:Ljava/util/Collection;
       5: return

  void setFaultVocabulary(java.util.Collection<org.apache.neethi.Assertion>);
    Code:
       0: aload_0
       1: aload_1
       2: putfield      #23                 // Field faultVocabulary:Ljava/util/Collection;
       5: return

  void setInterceptors(java.util.List<org.apache.cxf.interceptor.Interceptor<? extends org.apache.cxf.message.Message>>);
    Code:
       0: aload_0
       1: aload_1
       2: putfield      #24                 // Field interceptors:Ljava/util/List;
       5: return

  void setFaultInterceptors(java.util.List<org.apache.cxf.interceptor.Interceptor<? extends org.apache.cxf.message.Message>>);
    Code:
       0: aload_0
       1: aload_1
       2: putfield      #26                 // Field faultInterceptors:Ljava/util/List;
       5: return

  protected org.apache.cxf.ws.policy.EndpointPolicyImpl createEndpointPolicy();
    Code:
       0: new           #87                 // class org/apache/cxf/ws/policy/EndpointPolicyImpl
       3: dup
       4: aload_0
       5: getfield      #3                  // Field ei:Lorg/apache/cxf/service/model/EndpointInfo;
       8: aload_0
       9: getfield      #4                  // Field engine:Lorg/apache/cxf/ws/policy/PolicyEngineImpl;
      12: aload_0
      13: getfield      #5                  // Field requestor:Z
      16: aload_0
      17: getfield      #6                  // Field assertor:Lorg/apache/cxf/ws/policy/Assertor;
      20: invokespecial #88                 // Method "<init>":(Lorg/apache/cxf/service/model/EndpointInfo;Lorg/apache/cxf/ws/policy/PolicyEngineImpl;ZLorg/apache/cxf/ws/policy/Assertor;)V
      23: areturn

  void checkExactlyOnes();
    Code:
       0: aload_0
       1: getfield      #2                  // Field policy:Lorg/apache/neethi/Policy;
       4: invokevirtual #16                 // Method org/apache/neethi/Policy.getPolicyComponents:()Ljava/util/List;
       7: astore_1
       8: aload_1
       9: invokeinterface #89,  1           // InterfaceMethod java/util/List.size:()I
      14: iconst_1
      15: if_icmpgt     19
      18: return
      19: new           #14                 // class org/apache/neethi/Policy
      22: dup
      23: invokespecial #15                 // Method org/apache/neethi/Policy."<init>":()V
      26: astore_2
      27: new           #90                 // class org/apache/neethi/ExactlyOne
      30: dup
      31: invokespecial #91                 // Method org/apache/neethi/ExactlyOne."<init>":()V
      34: astore_3
      35: aload_2
      36: aload_3
      37: invokevirtual #92                 // Method org/apache/neethi/Policy.addPolicyComponent:(Lorg/apache/neethi/PolicyComponent;)V
      40: aload_1
      41: invokeinterface #93,  1           // InterfaceMethod java/util/List.iterator:()Ljava/util/Iterator;
      46: astore        4
      48: aload         4
      50: invokeinterface #49,  1           // InterfaceMethod java/util/Iterator.hasNext:()Z
      55: ifeq          82
      58: aload         4
      60: invokeinterface #50,  1           // InterfaceMethod java/util/Iterator.next:()Ljava/lang/Object;
      65: astore        5
      67: aload_3
      68: aload         5
      70: checkcast     #90                 // class org/apache/neethi/ExactlyOne
      73: invokevirtual #94                 // Method org/apache/neethi/ExactlyOne.getPolicyComponents:()Ljava/util/List;
      76: invokevirtual #95                 // Method org/apache/neethi/ExactlyOne.addPolicyComponents:(Ljava/util/List;)V
      79: goto          48
      82: aload_0
      83: aload_2
      84: invokevirtual #13                 // Method setPolicy:(Lorg/apache/neethi/Policy;)V
      87: return

  static {};
    Code:
       0: ldc_w         #87                 // class org/apache/cxf/ws/policy/EndpointPolicyImpl
       3: invokestatic  #96                 // Method org/apache/cxf/common/i18n/BundleUtils.getBundle:(Ljava/lang/Class;)Ljava/util/ResourceBundle;
       6: putstatic     #41                 // Field BUNDLE:Ljava/util/ResourceBundle;
       9: return
}
