Compiled from "GetAttributesToNodesRequestPBImpl.java"
public class org.apache.hadoop.yarn.api.protocolrecords.impl.pb.GetAttributesToNodesRequestPBImpl extends org.apache.hadoop.yarn.api.protocolrecords.GetAttributesToNodesRequest {
  private java.util.Set<org.apache.hadoop.yarn.api.records.NodeAttributeKey> nodeAttributes;

  private org.apache.hadoop.yarn.proto.YarnServiceProtos$GetAttributesToNodesRequestProto proto;

  private org.apache.hadoop.yarn.proto.YarnServiceProtos$GetAttributesToNodesRequestProto$Builder builder;

  private boolean viaProto;

  public org.apache.hadoop.yarn.api.protocolrecords.impl.pb.GetAttributesToNodesRequestPBImpl();
    Code:
       0: aload_0
       1: invokespecial #3                  // Method org/apache/hadoop/yarn/api/protocolrecords/GetAttributesToNodesRequest."<init>":()V
       4: aload_0
       5: aconst_null
       6: putfield      #2                  // Field nodeAttributes:Ljava/util/Set;
       9: aload_0
      10: invokestatic  #4                  // Method org/apache/hadoop/yarn/proto/YarnServiceProtos$GetAttributesToNodesRequestProto.getDefaultInstance:()Lorg/apache/hadoop/yarn/proto/YarnServiceProtos$GetAttributesToNodesRequestProto;
      13: putfield      #5                  // Field proto:Lorg/apache/hadoop/yarn/proto/YarnServiceProtos$GetAttributesToNodesRequestProto;
      16: aload_0
      17: aconst_null
      18: putfield      #6                  // Field builder:Lorg/apache/hadoop/yarn/proto/YarnServiceProtos$GetAttributesToNodesRequestProto$Builder;
      21: aload_0
      22: iconst_0
      23: putfield      #7                  // Field viaProto:Z
      26: aload_0
      27: invokestatic  #8                  // Method org/apache/hadoop/yarn/proto/YarnServiceProtos$GetAttributesToNodesRequestProto.newBuilder:()Lorg/apache/hadoop/yarn/proto/YarnServiceProtos$GetAttributesToNodesRequestProto$Builder;
      30: putfield      #6                  // Field builder:Lorg/apache/hadoop/yarn/proto/YarnServiceProtos$GetAttributesToNodesRequestProto$Builder;
      33: return

  public org.apache.hadoop.yarn.api.protocolrecords.impl.pb.GetAttributesToNodesRequestPBImpl(org.apache.hadoop.yarn.proto.YarnServiceProtos$GetAttributesToNodesRequestProto);
    Code:
       0: aload_0
       1: invokespecial #3                  // Method org/apache/hadoop/yarn/api/protocolrecords/GetAttributesToNodesRequest."<init>":()V
       4: aload_0
       5: aconst_null
       6: putfield      #2                  // Field nodeAttributes:Ljava/util/Set;
       9: aload_0
      10: invokestatic  #4                  // Method org/apache/hadoop/yarn/proto/YarnServiceProtos$GetAttributesToNodesRequestProto.getDefaultInstance:()Lorg/apache/hadoop/yarn/proto/YarnServiceProtos$GetAttributesToNodesRequestProto;
      13: putfield      #5                  // Field proto:Lorg/apache/hadoop/yarn/proto/YarnServiceProtos$GetAttributesToNodesRequestProto;
      16: aload_0
      17: aconst_null
      18: putfield      #6                  // Field builder:Lorg/apache/hadoop/yarn/proto/YarnServiceProtos$GetAttributesToNodesRequestProto$Builder;
      21: aload_0
      22: iconst_0
      23: putfield      #7                  // Field viaProto:Z
      26: aload_0
      27: aload_1
      28: putfield      #5                  // Field proto:Lorg/apache/hadoop/yarn/proto/YarnServiceProtos$GetAttributesToNodesRequestProto;
      31: aload_0
      32: iconst_1
      33: putfield      #7                  // Field viaProto:Z
      36: return

  public org.apache.hadoop.yarn.proto.YarnServiceProtos$GetAttributesToNodesRequestProto getProto();
    Code:
       0: aload_0
       1: invokespecial #9                  // Method mergeLocalToProto:()V
       4: aload_0
       5: aload_0
       6: getfield      #7                  // Field viaProto:Z
       9: ifeq          19
      12: aload_0
      13: getfield      #5                  // Field proto:Lorg/apache/hadoop/yarn/proto/YarnServiceProtos$GetAttributesToNodesRequestProto;
      16: goto          26
      19: aload_0
      20: getfield      #6                  // Field builder:Lorg/apache/hadoop/yarn/proto/YarnServiceProtos$GetAttributesToNodesRequestProto$Builder;
      23: invokevirtual #10                 // Method org/apache/hadoop/yarn/proto/YarnServiceProtos$GetAttributesToNodesRequestProto$Builder.build:()Lorg/apache/hadoop/yarn/proto/YarnServiceProtos$GetAttributesToNodesRequestProto;
      26: putfield      #5                  // Field proto:Lorg/apache/hadoop/yarn/proto/YarnServiceProtos$GetAttributesToNodesRequestProto;
      29: aload_0
      30: iconst_1
      31: putfield      #7                  // Field viaProto:Z
      34: aload_0
      35: getfield      #5                  // Field proto:Lorg/apache/hadoop/yarn/proto/YarnServiceProtos$GetAttributesToNodesRequestProto;
      38: areturn

  private void mergeLocalToProto();
    Code:
       0: aload_0
       1: getfield      #7                  // Field viaProto:Z
       4: ifeq          11
       7: aload_0
       8: invokespecial #11                 // Method maybeInitBuilder:()V
      11: aload_0
      12: invokespecial #12                 // Method mergeLocalToBuilder:()V
      15: aload_0
      16: aload_0
      17: getfield      #6                  // Field builder:Lorg/apache/hadoop/yarn/proto/YarnServiceProtos$GetAttributesToNodesRequestProto$Builder;
      20: invokevirtual #10                 // Method org/apache/hadoop/yarn/proto/YarnServiceProtos$GetAttributesToNodesRequestProto$Builder.build:()Lorg/apache/hadoop/yarn/proto/YarnServiceProtos$GetAttributesToNodesRequestProto;
      23: putfield      #5                  // Field proto:Lorg/apache/hadoop/yarn/proto/YarnServiceProtos$GetAttributesToNodesRequestProto;
      26: aload_0
      27: iconst_1
      28: putfield      #7                  // Field viaProto:Z
      31: return

  private void mergeLocalToBuilder();
    Code:
       0: aload_0
       1: getfield      #2                  // Field nodeAttributes:Ljava/util/Set;
       4: ifnull        11
       7: aload_0
       8: invokespecial #13                 // Method addLocalAttributesToProto:()V
      11: return

  private void addLocalAttributesToProto();
    Code:
       0: aload_0
       1: invokespecial #11                 // Method maybeInitBuilder:()V
       4: aload_0
       5: getfield      #6                  // Field builder:Lorg/apache/hadoop/yarn/proto/YarnServiceProtos$GetAttributesToNodesRequestProto$Builder;
       8: invokevirtual #14                 // Method org/apache/hadoop/yarn/proto/YarnServiceProtos$GetAttributesToNodesRequestProto$Builder.clearNodeAttributes:()Lorg/apache/hadoop/yarn/proto/YarnServiceProtos$GetAttributesToNodesRequestProto$Builder;
      11: pop
      12: aload_0
      13: getfield      #2                  // Field nodeAttributes:Ljava/util/Set;
      16: ifnonnull     20
      19: return
      20: aload_0
      21: invokedynamic #15,  0             // InvokeDynamic #0:iterator:(Lorg/apache/hadoop/yarn/api/protocolrecords/impl/pb/GetAttributesToNodesRequestPBImpl;)Ljava/lang/Iterable;
      26: astore_1
      27: aload_0
      28: getfield      #6                  // Field builder:Lorg/apache/hadoop/yarn/proto/YarnServiceProtos$GetAttributesToNodesRequestProto$Builder;
      31: aload_1
      32: invokevirtual #16                 // Method org/apache/hadoop/yarn/proto/YarnServiceProtos$GetAttributesToNodesRequestProto$Builder.addAllNodeAttributes:(Ljava/lang/Iterable;)Lorg/apache/hadoop/yarn/proto/YarnServiceProtos$GetAttributesToNodesRequestProto$Builder;
      35: pop
      36: return

  private org.apache.hadoop.yarn.api.records.impl.pb.NodeAttributeKeyPBImpl convertFromProtoFormat(org.apache.hadoop.yarn.proto.YarnProtos$NodeAttributeKeyProto);
    Code:
       0: new           #17                 // class org/apache/hadoop/yarn/api/records/impl/pb/NodeAttributeKeyPBImpl
       3: dup
       4: aload_1
       5: invokespecial #18                 // Method org/apache/hadoop/yarn/api/records/impl/pb/NodeAttributeKeyPBImpl."<init>":(Lorg/apache/hadoop/yarn/proto/YarnProtos$NodeAttributeKeyProto;)V
       8: areturn

  private org.apache.hadoop.yarn.proto.YarnProtos$NodeAttributeKeyProto convertToProtoFormat(org.apache.hadoop.yarn.api.records.NodeAttributeKey);
    Code:
       0: aload_1
       1: checkcast     #17                 // class org/apache/hadoop/yarn/api/records/impl/pb/NodeAttributeKeyPBImpl
       4: invokevirtual #19                 // Method org/apache/hadoop/yarn/api/records/impl/pb/NodeAttributeKeyPBImpl.getProto:()Lorg/apache/hadoop/yarn/proto/YarnProtos$NodeAttributeKeyProto;
       7: areturn

  private void maybeInitBuilder();
    Code:
       0: aload_0
       1: getfield      #7                  // Field viaProto:Z
       4: ifne          14
       7: aload_0
       8: getfield      #6                  // Field builder:Lorg/apache/hadoop/yarn/proto/YarnServiceProtos$GetAttributesToNodesRequestProto$Builder;
      11: ifnonnull     25
      14: aload_0
      15: aload_0
      16: getfield      #5                  // Field proto:Lorg/apache/hadoop/yarn/proto/YarnServiceProtos$GetAttributesToNodesRequestProto;
      19: invokestatic  #20                 // Method org/apache/hadoop/yarn/proto/YarnServiceProtos$GetAttributesToNodesRequestProto.newBuilder:(Lorg/apache/hadoop/yarn/proto/YarnServiceProtos$GetAttributesToNodesRequestProto;)Lorg/apache/hadoop/yarn/proto/YarnServiceProtos$GetAttributesToNodesRequestProto$Builder;
      22: putfield      #6                  // Field builder:Lorg/apache/hadoop/yarn/proto/YarnServiceProtos$GetAttributesToNodesRequestProto$Builder;
      25: aload_0
      26: iconst_0
      27: putfield      #7                  // Field viaProto:Z
      30: return

  private void initNodeAttributes();
    Code:
       0: aload_0
       1: getfield      #2                  // Field nodeAttributes:Ljava/util/Set;
       4: ifnull        8
       7: return
       8: aload_0
       9: getfield      #7                  // Field viaProto:Z
      12: ifeq          22
      15: aload_0
      16: getfield      #5                  // Field proto:Lorg/apache/hadoop/yarn/proto/YarnServiceProtos$GetAttributesToNodesRequestProto;
      19: goto          26
      22: aload_0
      23: getfield      #6                  // Field builder:Lorg/apache/hadoop/yarn/proto/YarnServiceProtos$GetAttributesToNodesRequestProto$Builder;
      26: astore_1
      27: aload_1
      28: invokeinterface #21,  1           // InterfaceMethod org/apache/hadoop/yarn/proto/YarnServiceProtos$GetAttributesToNodesRequestProtoOrBuilder.getNodeAttributesList:()Ljava/util/List;
      33: astore_2
      34: aload_0
      35: new           #22                 // class java/util/HashSet
      38: dup
      39: invokespecial #23                 // Method java/util/HashSet."<init>":()V
      42: putfield      #2                  // Field nodeAttributes:Ljava/util/Set;
      45: aload_2
      46: aload_0
      47: invokedynamic #24,  0             // InvokeDynamic #1:accept:(Lorg/apache/hadoop/yarn/api/protocolrecords/impl/pb/GetAttributesToNodesRequestPBImpl;)Ljava/util/function/Consumer;
      52: invokeinterface #25,  2           // InterfaceMethod java/util/List.forEach:(Ljava/util/function/Consumer;)V
      57: return

  public int hashCode();
    Code:
       0: aload_0
       1: invokevirtual #26                 // Method getProto:()Lorg/apache/hadoop/yarn/proto/YarnServiceProtos$GetAttributesToNodesRequestProto;
       4: invokevirtual #27                 // Method org/apache/hadoop/yarn/proto/YarnServiceProtos$GetAttributesToNodesRequestProto.hashCode:()I
       7: ireturn

  public boolean equals(java.lang.Object);
    Code:
       0: aload_1
       1: ifnonnull     6
       4: iconst_0
       5: ireturn
       6: aload_1
       7: invokevirtual #28                 // Method java/lang/Object.getClass:()Ljava/lang/Class;
      10: aload_0
      11: invokevirtual #28                 // Method java/lang/Object.getClass:()Ljava/lang/Class;
      14: invokevirtual #29                 // Method java/lang/Class.isAssignableFrom:(Ljava/lang/Class;)Z
      17: ifeq          42
      20: aload_0
      21: invokevirtual #26                 // Method getProto:()Lorg/apache/hadoop/yarn/proto/YarnServiceProtos$GetAttributesToNodesRequestProto;
      24: aload_0
      25: invokevirtual #28                 // Method java/lang/Object.getClass:()Ljava/lang/Class;
      28: aload_1
      29: invokevirtual #30                 // Method java/lang/Class.cast:(Ljava/lang/Object;)Ljava/lang/Object;
      32: checkcast     #31                 // class org/apache/hadoop/yarn/api/protocolrecords/impl/pb/GetAttributesToNodesRequestPBImpl
      35: invokevirtual #26                 // Method getProto:()Lorg/apache/hadoop/yarn/proto/YarnServiceProtos$GetAttributesToNodesRequestProto;
      38: invokevirtual #32                 // Method org/apache/hadoop/yarn/proto/YarnServiceProtos$GetAttributesToNodesRequestProto.equals:(Ljava/lang/Object;)Z
      41: ireturn
      42: iconst_0
      43: ireturn

  public java.lang.String toString();
    Code:
       0: aload_0
       1: invokevirtual #26                 // Method getProto:()Lorg/apache/hadoop/yarn/proto/YarnServiceProtos$GetAttributesToNodesRequestProto;
       4: invokestatic  #33                 // Method com/google/protobuf/TextFormat.shortDebugString:(Lcom/google/protobuf/MessageOrBuilder;)Ljava/lang/String;
       7: areturn

  public void setNodeAttributes(java.util.Set<org.apache.hadoop.yarn.api.records.NodeAttributeKey>);
    Code:
       0: aload_0
       1: invokespecial #11                 // Method maybeInitBuilder:()V
       4: aload_0
       5: getfield      #2                  // Field nodeAttributes:Ljava/util/Set;
       8: ifnonnull     19
      11: aload_0
      12: getfield      #6                  // Field builder:Lorg/apache/hadoop/yarn/proto/YarnServiceProtos$GetAttributesToNodesRequestProto$Builder;
      15: invokevirtual #14                 // Method org/apache/hadoop/yarn/proto/YarnServiceProtos$GetAttributesToNodesRequestProto$Builder.clearNodeAttributes:()Lorg/apache/hadoop/yarn/proto/YarnServiceProtos$GetAttributesToNodesRequestProto$Builder;
      18: pop
      19: aload_0
      20: aload_1
      21: putfield      #2                  // Field nodeAttributes:Ljava/util/Set;
      24: return

  public java.util.Set<org.apache.hadoop.yarn.api.records.NodeAttributeKey> getNodeAttributes();
    Code:
       0: aload_0
       1: invokespecial #34                 // Method initNodeAttributes:()V
       4: aload_0
       5: getfield      #2                  // Field nodeAttributes:Ljava/util/Set;
       8: areturn

  private void lambda$initNodeAttributes$1(org.apache.hadoop.yarn.proto.YarnProtos$NodeAttributeKeyProto);
    Code:
       0: aload_0
       1: getfield      #2                  // Field nodeAttributes:Ljava/util/Set;
       4: aload_0
       5: aload_1
       6: invokespecial #35                 // Method convertFromProtoFormat:(Lorg/apache/hadoop/yarn/proto/YarnProtos$NodeAttributeKeyProto;)Lorg/apache/hadoop/yarn/api/records/impl/pb/NodeAttributeKeyPBImpl;
       9: invokeinterface #36,  2           // InterfaceMethod java/util/Set.add:(Ljava/lang/Object;)Z
      14: pop
      15: return

  private java.util.Iterator lambda$addLocalAttributesToProto$0();
    Code:
       0: new           #37                 // class org/apache/hadoop/yarn/api/protocolrecords/impl/pb/GetAttributesToNodesRequestPBImpl$1
       3: dup
       4: aload_0
       5: invokespecial #38                 // Method org/apache/hadoop/yarn/api/protocolrecords/impl/pb/GetAttributesToNodesRequestPBImpl$1."<init>":(Lorg/apache/hadoop/yarn/api/protocolrecords/impl/pb/GetAttributesToNodesRequestPBImpl;)V
       8: areturn

  static java.util.Set access$000(org.apache.hadoop.yarn.api.protocolrecords.impl.pb.GetAttributesToNodesRequestPBImpl);
    Code:
       0: aload_0
       1: getfield      #2                  // Field nodeAttributes:Ljava/util/Set;
       4: areturn

  static org.apache.hadoop.yarn.proto.YarnProtos$NodeAttributeKeyProto access$100(org.apache.hadoop.yarn.api.protocolrecords.impl.pb.GetAttributesToNodesRequestPBImpl, org.apache.hadoop.yarn.api.records.NodeAttributeKey);
    Code:
       0: aload_0
       1: aload_1
       2: invokespecial #1                  // Method convertToProtoFormat:(Lorg/apache/hadoop/yarn/api/records/NodeAttributeKey;)Lorg/apache/hadoop/yarn/proto/YarnProtos$NodeAttributeKeyProto;
       5: areturn
}
