Compiled from "GetAllResourceProfilesRequestPBImpl.java"
public class org.apache.hadoop.yarn.api.protocolrecords.impl.pb.GetAllResourceProfilesRequestPBImpl extends org.apache.hadoop.yarn.api.protocolrecords.GetAllResourceProfilesRequest {
  private org.apache.hadoop.yarn.proto.YarnServiceProtos$GetAllResourceProfilesRequestProto proto;

  private org.apache.hadoop.yarn.proto.YarnServiceProtos$GetAllResourceProfilesRequestProto$Builder builder;

  private boolean viaProto;

  public org.apache.hadoop.yarn.api.protocolrecords.impl.pb.GetAllResourceProfilesRequestPBImpl();
    Code:
       0: aload_0
       1: invokespecial #1                  // Method org/apache/hadoop/yarn/api/protocolrecords/GetAllResourceProfilesRequest."<init>":()V
       4: aload_0
       5: invokestatic  #2                  // Method org/apache/hadoop/yarn/proto/YarnServiceProtos$GetAllResourceProfilesRequestProto.getDefaultInstance:()Lorg/apache/hadoop/yarn/proto/YarnServiceProtos$GetAllResourceProfilesRequestProto;
       8: putfield      #3                  // Field proto:Lorg/apache/hadoop/yarn/proto/YarnServiceProtos$GetAllResourceProfilesRequestProto;
      11: aload_0
      12: aconst_null
      13: putfield      #4                  // Field builder:Lorg/apache/hadoop/yarn/proto/YarnServiceProtos$GetAllResourceProfilesRequestProto$Builder;
      16: aload_0
      17: iconst_0
      18: putfield      #5                  // Field viaProto:Z
      21: aload_0
      22: invokestatic  #6                  // Method org/apache/hadoop/yarn/proto/YarnServiceProtos$GetAllResourceProfilesRequestProto.newBuilder:()Lorg/apache/hadoop/yarn/proto/YarnServiceProtos$GetAllResourceProfilesRequestProto$Builder;
      25: putfield      #4                  // Field builder:Lorg/apache/hadoop/yarn/proto/YarnServiceProtos$GetAllResourceProfilesRequestProto$Builder;
      28: return

  public org.apache.hadoop.yarn.api.protocolrecords.impl.pb.GetAllResourceProfilesRequestPBImpl(org.apache.hadoop.yarn.proto.YarnServiceProtos$GetAllResourceProfilesRequestProto);
    Code:
       0: aload_0
       1: invokespecial #1                  // Method org/apache/hadoop/yarn/api/protocolrecords/GetAllResourceProfilesRequest."<init>":()V
       4: aload_0
       5: invokestatic  #2                  // Method org/apache/hadoop/yarn/proto/YarnServiceProtos$GetAllResourceProfilesRequestProto.getDefaultInstance:()Lorg/apache/hadoop/yarn/proto/YarnServiceProtos$GetAllResourceProfilesRequestProto;
       8: putfield      #3                  // Field proto:Lorg/apache/hadoop/yarn/proto/YarnServiceProtos$GetAllResourceProfilesRequestProto;
      11: aload_0
      12: aconst_null
      13: putfield      #4                  // Field builder:Lorg/apache/hadoop/yarn/proto/YarnServiceProtos$GetAllResourceProfilesRequestProto$Builder;
      16: aload_0
      17: iconst_0
      18: putfield      #5                  // Field viaProto:Z
      21: aload_0
      22: aload_1
      23: putfield      #3                  // Field proto:Lorg/apache/hadoop/yarn/proto/YarnServiceProtos$GetAllResourceProfilesRequestProto;
      26: aload_0
      27: iconst_1
      28: putfield      #5                  // Field viaProto:Z
      31: return

  public org.apache.hadoop.yarn.proto.YarnServiceProtos$GetAllResourceProfilesRequestProto getProto();
    Code:
       0: aload_0
       1: aload_0
       2: getfield      #5                  // Field viaProto:Z
       5: ifeq          15
       8: aload_0
       9: getfield      #3                  // Field proto:Lorg/apache/hadoop/yarn/proto/YarnServiceProtos$GetAllResourceProfilesRequestProto;
      12: goto          22
      15: aload_0
      16: getfield      #4                  // Field builder:Lorg/apache/hadoop/yarn/proto/YarnServiceProtos$GetAllResourceProfilesRequestProto$Builder;
      19: invokevirtual #7                  // Method org/apache/hadoop/yarn/proto/YarnServiceProtos$GetAllResourceProfilesRequestProto$Builder.build:()Lorg/apache/hadoop/yarn/proto/YarnServiceProtos$GetAllResourceProfilesRequestProto;
      22: putfield      #3                  // Field proto:Lorg/apache/hadoop/yarn/proto/YarnServiceProtos$GetAllResourceProfilesRequestProto;
      25: aload_0
      26: iconst_1
      27: putfield      #5                  // Field viaProto:Z
      30: aload_0
      31: getfield      #3                  // Field proto:Lorg/apache/hadoop/yarn/proto/YarnServiceProtos$GetAllResourceProfilesRequestProto;
      34: areturn
}
