Compiled from "GetNodesToAttributesResponsePBImpl.java"
public class org.apache.hadoop.yarn.api.protocolrecords.impl.pb.GetNodesToAttributesResponsePBImpl extends org.apache.hadoop.yarn.api.protocolrecords.GetNodesToAttributesResponse {
  private org.apache.hadoop.yarn.proto.YarnServiceProtos$GetNodesToAttributesResponseProto proto;

  private org.apache.hadoop.yarn.proto.YarnServiceProtos$GetNodesToAttributesResponseProto$Builder builder;

  private boolean viaProto;

  private java.util.Map<java.lang.String, java.util.Set<org.apache.hadoop.yarn.api.records.NodeAttribute>> nodesToAttributes;

  static final boolean $assertionsDisabled;

  public org.apache.hadoop.yarn.api.protocolrecords.impl.pb.GetNodesToAttributesResponsePBImpl();
    Code:
       0: aload_0
       1: invokespecial #3                  // Method org/apache/hadoop/yarn/api/protocolrecords/GetNodesToAttributesResponse."<init>":()V
       4: aload_0
       5: invokestatic  #4                  // Method org/apache/hadoop/yarn/proto/YarnServiceProtos$GetNodesToAttributesResponseProto.getDefaultInstance:()Lorg/apache/hadoop/yarn/proto/YarnServiceProtos$GetNodesToAttributesResponseProto;
       8: putfield      #5                  // Field proto:Lorg/apache/hadoop/yarn/proto/YarnServiceProtos$GetNodesToAttributesResponseProto;
      11: aload_0
      12: aconst_null
      13: putfield      #6                  // Field builder:Lorg/apache/hadoop/yarn/proto/YarnServiceProtos$GetNodesToAttributesResponseProto$Builder;
      16: aload_0
      17: iconst_0
      18: putfield      #7                  // Field viaProto:Z
      21: aload_0
      22: invokestatic  #8                  // Method org/apache/hadoop/yarn/proto/YarnServiceProtos$GetNodesToAttributesResponseProto.newBuilder:()Lorg/apache/hadoop/yarn/proto/YarnServiceProtos$GetNodesToAttributesResponseProto$Builder;
      25: putfield      #6                  // Field builder:Lorg/apache/hadoop/yarn/proto/YarnServiceProtos$GetNodesToAttributesResponseProto$Builder;
      28: return

  public org.apache.hadoop.yarn.api.protocolrecords.impl.pb.GetNodesToAttributesResponsePBImpl(org.apache.hadoop.yarn.proto.YarnServiceProtos$GetNodesToAttributesResponseProto);
    Code:
       0: aload_0
       1: invokespecial #3                  // Method org/apache/hadoop/yarn/api/protocolrecords/GetNodesToAttributesResponse."<init>":()V
       4: aload_0
       5: invokestatic  #4                  // Method org/apache/hadoop/yarn/proto/YarnServiceProtos$GetNodesToAttributesResponseProto.getDefaultInstance:()Lorg/apache/hadoop/yarn/proto/YarnServiceProtos$GetNodesToAttributesResponseProto;
       8: putfield      #5                  // Field proto:Lorg/apache/hadoop/yarn/proto/YarnServiceProtos$GetNodesToAttributesResponseProto;
      11: aload_0
      12: aconst_null
      13: putfield      #6                  // Field builder:Lorg/apache/hadoop/yarn/proto/YarnServiceProtos$GetNodesToAttributesResponseProto$Builder;
      16: aload_0
      17: iconst_0
      18: putfield      #7                  // Field viaProto:Z
      21: aload_0
      22: aload_1
      23: putfield      #5                  // Field proto:Lorg/apache/hadoop/yarn/proto/YarnServiceProtos$GetNodesToAttributesResponseProto;
      26: aload_0
      27: iconst_1
      28: putfield      #7                  // Field viaProto:Z
      31: return

  private void initNodesToAttributes();
    Code:
       0: aload_0
       1: getfield      #2                  // Field nodesToAttributes:Ljava/util/Map;
       4: ifnull        8
       7: return
       8: aload_0
       9: getfield      #7                  // Field viaProto:Z
      12: ifeq          22
      15: aload_0
      16: getfield      #5                  // Field proto:Lorg/apache/hadoop/yarn/proto/YarnServiceProtos$GetNodesToAttributesResponseProto;
      19: goto          26
      22: aload_0
      23: getfield      #6                  // Field builder:Lorg/apache/hadoop/yarn/proto/YarnServiceProtos$GetNodesToAttributesResponseProto$Builder;
      26: astore_1
      27: aload_1
      28: invokeinterface #9,  1            // InterfaceMethod org/apache/hadoop/yarn/proto/YarnServiceProtos$GetNodesToAttributesResponseProtoOrBuilder.getNodesToAttributesList:()Ljava/util/List;
      33: astore_2
      34: aload_0
      35: new           #10                 // class java/util/HashMap
      38: dup
      39: invokespecial #11                 // Method java/util/HashMap."<init>":()V
      42: putfield      #2                  // Field nodesToAttributes:Ljava/util/Map;
      45: aload_2
      46: invokeinterface #12,  1           // InterfaceMethod java/util/List.iterator:()Ljava/util/Iterator;
      51: astore_3
      52: aload_3
      53: invokeinterface #13,  1           // InterfaceMethod java/util/Iterator.hasNext:()Z
      58: ifeq          153
      61: aload_3
      62: invokeinterface #14,  1           // InterfaceMethod java/util/Iterator.next:()Ljava/lang/Object;
      67: checkcast     #15                 // class org/apache/hadoop/yarn/proto/YarnProtos$NodeToAttributesProto
      70: astore        4
      72: new           #16                 // class java/util/HashSet
      75: dup
      76: invokespecial #17                 // Method java/util/HashSet."<init>":()V
      79: astore        5
      81: aload         4
      83: invokevirtual #18                 // Method org/apache/hadoop/yarn/proto/YarnProtos$NodeToAttributesProto.getNodeAttributesList:()Ljava/util/List;
      86: invokeinterface #12,  1           // InterfaceMethod java/util/List.iterator:()Ljava/util/Iterator;
      91: astore        6
      93: aload         6
      95: invokeinterface #13,  1           // InterfaceMethod java/util/Iterator.hasNext:()Z
     100: ifeq          133
     103: aload         6
     105: invokeinterface #14,  1           // InterfaceMethod java/util/Iterator.next:()Ljava/lang/Object;
     110: checkcast     #19                 // class org/apache/hadoop/yarn/proto/YarnProtos$NodeAttributeProto
     113: astore        7
     115: aload         5
     117: new           #20                 // class org/apache/hadoop/yarn/api/records/impl/pb/NodeAttributePBImpl
     120: dup
     121: aload         7
     123: invokespecial #21                 // Method org/apache/hadoop/yarn/api/records/impl/pb/NodeAttributePBImpl."<init>":(Lorg/apache/hadoop/yarn/proto/YarnProtos$NodeAttributeProto;)V
     126: invokevirtual #22                 // Method java/util/HashSet.add:(Ljava/lang/Object;)Z
     129: pop
     130: goto          93
     133: aload_0
     134: getfield      #2                  // Field nodesToAttributes:Ljava/util/Map;
     137: aload         4
     139: invokevirtual #23                 // Method org/apache/hadoop/yarn/proto/YarnProtos$NodeToAttributesProto.getNode:()Ljava/lang/String;
     142: aload         5
     144: invokeinterface #24,  3           // InterfaceMethod java/util/Map.put:(Ljava/lang/Object;Ljava/lang/Object;)Ljava/lang/Object;
     149: pop
     150: goto          52
     153: return

  private void maybeInitBuilder();
    Code:
       0: aload_0
       1: getfield      #7                  // Field viaProto:Z
       4: ifne          14
       7: aload_0
       8: getfield      #6                  // Field builder:Lorg/apache/hadoop/yarn/proto/YarnServiceProtos$GetNodesToAttributesResponseProto$Builder;
      11: ifnonnull     25
      14: aload_0
      15: aload_0
      16: getfield      #5                  // Field proto:Lorg/apache/hadoop/yarn/proto/YarnServiceProtos$GetNodesToAttributesResponseProto;
      19: invokestatic  #25                 // Method org/apache/hadoop/yarn/proto/YarnServiceProtos$GetNodesToAttributesResponseProto.newBuilder:(Lorg/apache/hadoop/yarn/proto/YarnServiceProtos$GetNodesToAttributesResponseProto;)Lorg/apache/hadoop/yarn/proto/YarnServiceProtos$GetNodesToAttributesResponseProto$Builder;
      22: putfield      #6                  // Field builder:Lorg/apache/hadoop/yarn/proto/YarnServiceProtos$GetNodesToAttributesResponseProto$Builder;
      25: aload_0
      26: iconst_0
      27: putfield      #7                  // Field viaProto:Z
      30: return

  private void addNodesToAttributesToProto();
    Code:
       0: aload_0
       1: invokespecial #26                 // Method maybeInitBuilder:()V
       4: aload_0
       5: getfield      #6                  // Field builder:Lorg/apache/hadoop/yarn/proto/YarnServiceProtos$GetNodesToAttributesResponseProto$Builder;
       8: invokevirtual #27                 // Method org/apache/hadoop/yarn/proto/YarnServiceProtos$GetNodesToAttributesResponseProto$Builder.clearNodesToAttributes:()Lorg/apache/hadoop/yarn/proto/YarnServiceProtos$GetNodesToAttributesResponseProto$Builder;
      11: pop
      12: aload_0
      13: getfield      #2                  // Field nodesToAttributes:Ljava/util/Map;
      16: ifnonnull     20
      19: return
      20: aload_0
      21: invokedynamic #28,  0             // InvokeDynamic #0:iterator:(Lorg/apache/hadoop/yarn/api/protocolrecords/impl/pb/GetNodesToAttributesResponsePBImpl;)Ljava/lang/Iterable;
      26: astore_1
      27: aload_0
      28: getfield      #6                  // Field builder:Lorg/apache/hadoop/yarn/proto/YarnServiceProtos$GetNodesToAttributesResponseProto$Builder;
      31: aload_1
      32: invokevirtual #29                 // Method org/apache/hadoop/yarn/proto/YarnServiceProtos$GetNodesToAttributesResponseProto$Builder.addAllNodesToAttributes:(Ljava/lang/Iterable;)Lorg/apache/hadoop/yarn/proto/YarnServiceProtos$GetNodesToAttributesResponseProto$Builder;
      35: pop
      36: return

  private org.apache.hadoop.yarn.api.records.impl.pb.NodeAttributePBImpl convertFromProtoFormat(org.apache.hadoop.yarn.proto.YarnProtos$NodeAttributeProto);
    Code:
       0: new           #20                 // class org/apache/hadoop/yarn/api/records/impl/pb/NodeAttributePBImpl
       3: dup
       4: aload_1
       5: invokespecial #21                 // Method org/apache/hadoop/yarn/api/records/impl/pb/NodeAttributePBImpl."<init>":(Lorg/apache/hadoop/yarn/proto/YarnProtos$NodeAttributeProto;)V
       8: areturn

  private org.apache.hadoop.yarn.proto.YarnProtos$NodeAttributeProto convertToProtoFormat(org.apache.hadoop.yarn.api.records.NodeAttribute);
    Code:
       0: aload_1
       1: checkcast     #20                 // class org/apache/hadoop/yarn/api/records/impl/pb/NodeAttributePBImpl
       4: invokevirtual #30                 // Method org/apache/hadoop/yarn/api/records/impl/pb/NodeAttributePBImpl.getProto:()Lorg/apache/hadoop/yarn/proto/YarnProtos$NodeAttributeProto;
       7: areturn

  private void mergeLocalToBuilder();
    Code:
       0: aload_0
       1: getfield      #2                  // Field nodesToAttributes:Ljava/util/Map;
       4: ifnull        11
       7: aload_0
       8: invokespecial #31                 // Method addNodesToAttributesToProto:()V
      11: return

  private void mergeLocalToProto();
    Code:
       0: aload_0
       1: getfield      #7                  // Field viaProto:Z
       4: ifeq          11
       7: aload_0
       8: invokespecial #26                 // Method maybeInitBuilder:()V
      11: aload_0
      12: invokespecial #32                 // Method mergeLocalToBuilder:()V
      15: aload_0
      16: aload_0
      17: getfield      #6                  // Field builder:Lorg/apache/hadoop/yarn/proto/YarnServiceProtos$GetNodesToAttributesResponseProto$Builder;
      20: invokevirtual #33                 // Method org/apache/hadoop/yarn/proto/YarnServiceProtos$GetNodesToAttributesResponseProto$Builder.build:()Lorg/apache/hadoop/yarn/proto/YarnServiceProtos$GetNodesToAttributesResponseProto;
      23: putfield      #5                  // Field proto:Lorg/apache/hadoop/yarn/proto/YarnServiceProtos$GetNodesToAttributesResponseProto;
      26: aload_0
      27: iconst_1
      28: putfield      #7                  // Field viaProto:Z
      31: return

  public org.apache.hadoop.yarn.proto.YarnServiceProtos$GetNodesToAttributesResponseProto getProto();
    Code:
       0: aload_0
       1: invokespecial #34                 // Method mergeLocalToProto:()V
       4: aload_0
       5: aload_0
       6: getfield      #7                  // Field viaProto:Z
       9: ifeq          19
      12: aload_0
      13: getfield      #5                  // Field proto:Lorg/apache/hadoop/yarn/proto/YarnServiceProtos$GetNodesToAttributesResponseProto;
      16: goto          26
      19: aload_0
      20: getfield      #6                  // Field builder:Lorg/apache/hadoop/yarn/proto/YarnServiceProtos$GetNodesToAttributesResponseProto$Builder;
      23: invokevirtual #33                 // Method org/apache/hadoop/yarn/proto/YarnServiceProtos$GetNodesToAttributesResponseProto$Builder.build:()Lorg/apache/hadoop/yarn/proto/YarnServiceProtos$GetNodesToAttributesResponseProto;
      26: putfield      #5                  // Field proto:Lorg/apache/hadoop/yarn/proto/YarnServiceProtos$GetNodesToAttributesResponseProto;
      29: aload_0
      30: iconst_1
      31: putfield      #7                  // Field viaProto:Z
      34: aload_0
      35: getfield      #5                  // Field proto:Lorg/apache/hadoop/yarn/proto/YarnServiceProtos$GetNodesToAttributesResponseProto;
      38: areturn

  public int hashCode();
    Code:
       0: getstatic     #35                 // Field $assertionsDisabled:Z
       3: ifne          16
       6: new           #36                 // class java/lang/AssertionError
       9: dup
      10: ldc           #37                 // String hashCode not designed
      12: invokespecial #38                 // Method java/lang/AssertionError."<init>":(Ljava/lang/Object;)V
      15: athrow
      16: iconst_0
      17: ireturn

  public boolean equals(java.lang.Object);
    Code:
       0: aload_1
       1: ifnonnull     6
       4: iconst_0
       5: ireturn
       6: aload_1
       7: invokevirtual #39                 // Method java/lang/Object.getClass:()Ljava/lang/Class;
      10: aload_0
      11: invokevirtual #39                 // Method java/lang/Object.getClass:()Ljava/lang/Class;
      14: invokevirtual #40                 // Method java/lang/Class.isAssignableFrom:(Ljava/lang/Class;)Z
      17: ifeq          42
      20: aload_0
      21: invokevirtual #41                 // Method getProto:()Lorg/apache/hadoop/yarn/proto/YarnServiceProtos$GetNodesToAttributesResponseProto;
      24: aload_0
      25: invokevirtual #39                 // Method java/lang/Object.getClass:()Ljava/lang/Class;
      28: aload_1
      29: invokevirtual #42                 // Method java/lang/Class.cast:(Ljava/lang/Object;)Ljava/lang/Object;
      32: checkcast     #43                 // class org/apache/hadoop/yarn/api/protocolrecords/impl/pb/GetNodesToAttributesResponsePBImpl
      35: invokevirtual #41                 // Method getProto:()Lorg/apache/hadoop/yarn/proto/YarnServiceProtos$GetNodesToAttributesResponseProto;
      38: invokevirtual #44                 // Method org/apache/hadoop/yarn/proto/YarnServiceProtos$GetNodesToAttributesResponseProto.equals:(Ljava/lang/Object;)Z
      41: ireturn
      42: iconst_0
      43: ireturn

  public void setNodeToAttributes(java.util.Map<java.lang.String, java.util.Set<org.apache.hadoop.yarn.api.records.NodeAttribute>>);
    Code:
       0: aload_0
       1: invokespecial #45                 // Method initNodesToAttributes:()V
       4: aload_0
       5: getfield      #2                  // Field nodesToAttributes:Ljava/util/Map;
       8: invokeinterface #46,  1           // InterfaceMethod java/util/Map.clear:()V
      13: aload_0
      14: getfield      #2                  // Field nodesToAttributes:Ljava/util/Map;
      17: aload_1
      18: invokeinterface #47,  2           // InterfaceMethod java/util/Map.putAll:(Ljava/util/Map;)V
      23: return

  public java.util.Map<java.lang.String, java.util.Set<org.apache.hadoop.yarn.api.records.NodeAttribute>> getNodeToAttributes();
    Code:
       0: aload_0
       1: invokespecial #45                 // Method initNodesToAttributes:()V
       4: aload_0
       5: getfield      #2                  // Field nodesToAttributes:Ljava/util/Map;
       8: areturn

  private java.util.Iterator lambda$addNodesToAttributesToProto$0();
    Code:
       0: new           #48                 // class org/apache/hadoop/yarn/api/protocolrecords/impl/pb/GetNodesToAttributesResponsePBImpl$1
       3: dup
       4: aload_0
       5: invokespecial #49                 // Method org/apache/hadoop/yarn/api/protocolrecords/impl/pb/GetNodesToAttributesResponsePBImpl$1."<init>":(Lorg/apache/hadoop/yarn/api/protocolrecords/impl/pb/GetNodesToAttributesResponsePBImpl;)V
       8: areturn

  static java.util.Map access$000(org.apache.hadoop.yarn.api.protocolrecords.impl.pb.GetNodesToAttributesResponsePBImpl);
    Code:
       0: aload_0
       1: getfield      #2                  // Field nodesToAttributes:Ljava/util/Map;
       4: areturn

  static org.apache.hadoop.yarn.proto.YarnProtos$NodeAttributeProto access$100(org.apache.hadoop.yarn.api.protocolrecords.impl.pb.GetNodesToAttributesResponsePBImpl, org.apache.hadoop.yarn.api.records.NodeAttribute);
    Code:
       0: aload_0
       1: aload_1
       2: invokespecial #1                  // Method convertToProtoFormat:(Lorg/apache/hadoop/yarn/api/records/NodeAttribute;)Lorg/apache/hadoop/yarn/proto/YarnProtos$NodeAttributeProto;
       5: areturn

  static {};
    Code:
       0: ldc           #43                 // class org/apache/hadoop/yarn/api/protocolrecords/impl/pb/GetNodesToAttributesResponsePBImpl
       2: invokevirtual #50                 // Method java/lang/Class.desiredAssertionStatus:()Z
       5: ifne          12
       8: iconst_1
       9: goto          13
      12: iconst_0
      13: putstatic     #35                 // Field $assertionsDisabled:Z
      16: return
}
