Compiled from "ReservationDeleteRequestPBImpl.java"
public class org.apache.hadoop.yarn.api.protocolrecords.impl.pb.ReservationDeleteRequestPBImpl extends org.apache.hadoop.yarn.api.protocolrecords.ReservationDeleteRequest {
  org.apache.hadoop.yarn.proto.YarnServiceProtos$ReservationDeleteRequestProto proto;

  org.apache.hadoop.yarn.proto.YarnServiceProtos$ReservationDeleteRequestProto$Builder builder;

  boolean viaProto;

  private org.apache.hadoop.yarn.api.records.ReservationId reservationId;

  public org.apache.hadoop.yarn.api.protocolrecords.impl.pb.ReservationDeleteRequestPBImpl();
    Code:
       0: aload_0
       1: invokespecial #1                  // Method org/apache/hadoop/yarn/api/protocolrecords/ReservationDeleteRequest."<init>":()V
       4: aload_0
       5: invokestatic  #2                  // Method org/apache/hadoop/yarn/proto/YarnServiceProtos$ReservationDeleteRequestProto.getDefaultInstance:()Lorg/apache/hadoop/yarn/proto/YarnServiceProtos$ReservationDeleteRequestProto;
       8: putfield      #3                  // Field proto:Lorg/apache/hadoop/yarn/proto/YarnServiceProtos$ReservationDeleteRequestProto;
      11: aload_0
      12: aconst_null
      13: putfield      #4                  // Field builder:Lorg/apache/hadoop/yarn/proto/YarnServiceProtos$ReservationDeleteRequestProto$Builder;
      16: aload_0
      17: iconst_0
      18: putfield      #5                  // Field viaProto:Z
      21: aload_0
      22: invokestatic  #6                  // Method org/apache/hadoop/yarn/proto/YarnServiceProtos$ReservationDeleteRequestProto.newBuilder:()Lorg/apache/hadoop/yarn/proto/YarnServiceProtos$ReservationDeleteRequestProto$Builder;
      25: putfield      #4                  // Field builder:Lorg/apache/hadoop/yarn/proto/YarnServiceProtos$ReservationDeleteRequestProto$Builder;
      28: return

  public org.apache.hadoop.yarn.api.protocolrecords.impl.pb.ReservationDeleteRequestPBImpl(org.apache.hadoop.yarn.proto.YarnServiceProtos$ReservationDeleteRequestProto);
    Code:
       0: aload_0
       1: invokespecial #1                  // Method org/apache/hadoop/yarn/api/protocolrecords/ReservationDeleteRequest."<init>":()V
       4: aload_0
       5: invokestatic  #2                  // Method org/apache/hadoop/yarn/proto/YarnServiceProtos$ReservationDeleteRequestProto.getDefaultInstance:()Lorg/apache/hadoop/yarn/proto/YarnServiceProtos$ReservationDeleteRequestProto;
       8: putfield      #3                  // Field proto:Lorg/apache/hadoop/yarn/proto/YarnServiceProtos$ReservationDeleteRequestProto;
      11: aload_0
      12: aconst_null
      13: putfield      #4                  // Field builder:Lorg/apache/hadoop/yarn/proto/YarnServiceProtos$ReservationDeleteRequestProto$Builder;
      16: aload_0
      17: iconst_0
      18: putfield      #5                  // Field viaProto:Z
      21: aload_0
      22: aload_1
      23: putfield      #3                  // Field proto:Lorg/apache/hadoop/yarn/proto/YarnServiceProtos$ReservationDeleteRequestProto;
      26: aload_0
      27: iconst_1
      28: putfield      #5                  // Field viaProto:Z
      31: return

  public org.apache.hadoop.yarn.proto.YarnServiceProtos$ReservationDeleteRequestProto getProto();
    Code:
       0: aload_0
       1: invokespecial #7                  // Method mergeLocalToProto:()V
       4: aload_0
       5: aload_0
       6: getfield      #5                  // Field viaProto:Z
       9: ifeq          19
      12: aload_0
      13: getfield      #3                  // Field proto:Lorg/apache/hadoop/yarn/proto/YarnServiceProtos$ReservationDeleteRequestProto;
      16: goto          26
      19: aload_0
      20: getfield      #4                  // Field builder:Lorg/apache/hadoop/yarn/proto/YarnServiceProtos$ReservationDeleteRequestProto$Builder;
      23: invokevirtual #8                  // Method org/apache/hadoop/yarn/proto/YarnServiceProtos$ReservationDeleteRequestProto$Builder.build:()Lorg/apache/hadoop/yarn/proto/YarnServiceProtos$ReservationDeleteRequestProto;
      26: putfield      #3                  // Field proto:Lorg/apache/hadoop/yarn/proto/YarnServiceProtos$ReservationDeleteRequestProto;
      29: aload_0
      30: iconst_1
      31: putfield      #5                  // Field viaProto:Z
      34: aload_0
      35: getfield      #3                  // Field proto:Lorg/apache/hadoop/yarn/proto/YarnServiceProtos$ReservationDeleteRequestProto;
      38: areturn

  private void mergeLocalToBuilder();
    Code:
       0: aload_0
       1: getfield      #9                  // Field reservationId:Lorg/apache/hadoop/yarn/api/records/ReservationId;
       4: ifnull        23
       7: aload_0
       8: getfield      #4                  // Field builder:Lorg/apache/hadoop/yarn/proto/YarnServiceProtos$ReservationDeleteRequestProto$Builder;
      11: aload_0
      12: aload_0
      13: getfield      #9                  // Field reservationId:Lorg/apache/hadoop/yarn/api/records/ReservationId;
      16: invokespecial #10                 // Method convertToProtoFormat:(Lorg/apache/hadoop/yarn/api/records/ReservationId;)Lorg/apache/hadoop/yarn/proto/YarnProtos$ReservationIdProto;
      19: invokevirtual #11                 // Method org/apache/hadoop/yarn/proto/YarnServiceProtos$ReservationDeleteRequestProto$Builder.setReservationId:(Lorg/apache/hadoop/yarn/proto/YarnProtos$ReservationIdProto;)Lorg/apache/hadoop/yarn/proto/YarnServiceProtos$ReservationDeleteRequestProto$Builder;
      22: pop
      23: return

  private void mergeLocalToProto();
    Code:
       0: aload_0
       1: getfield      #5                  // Field viaProto:Z
       4: ifeq          11
       7: aload_0
       8: invokespecial #12                 // Method maybeInitBuilder:()V
      11: aload_0
      12: invokespecial #13                 // Method mergeLocalToBuilder:()V
      15: aload_0
      16: aload_0
      17: getfield      #4                  // Field builder:Lorg/apache/hadoop/yarn/proto/YarnServiceProtos$ReservationDeleteRequestProto$Builder;
      20: invokevirtual #8                  // Method org/apache/hadoop/yarn/proto/YarnServiceProtos$ReservationDeleteRequestProto$Builder.build:()Lorg/apache/hadoop/yarn/proto/YarnServiceProtos$ReservationDeleteRequestProto;
      23: putfield      #3                  // Field proto:Lorg/apache/hadoop/yarn/proto/YarnServiceProtos$ReservationDeleteRequestProto;
      26: aload_0
      27: iconst_1
      28: putfield      #5                  // Field viaProto:Z
      31: return

  private void maybeInitBuilder();
    Code:
       0: aload_0
       1: getfield      #5                  // Field viaProto:Z
       4: ifne          14
       7: aload_0
       8: getfield      #4                  // Field builder:Lorg/apache/hadoop/yarn/proto/YarnServiceProtos$ReservationDeleteRequestProto$Builder;
      11: ifnonnull     25
      14: aload_0
      15: aload_0
      16: getfield      #3                  // Field proto:Lorg/apache/hadoop/yarn/proto/YarnServiceProtos$ReservationDeleteRequestProto;
      19: invokestatic  #14                 // Method org/apache/hadoop/yarn/proto/YarnServiceProtos$ReservationDeleteRequestProto.newBuilder:(Lorg/apache/hadoop/yarn/proto/YarnServiceProtos$ReservationDeleteRequestProto;)Lorg/apache/hadoop/yarn/proto/YarnServiceProtos$ReservationDeleteRequestProto$Builder;
      22: putfield      #4                  // Field builder:Lorg/apache/hadoop/yarn/proto/YarnServiceProtos$ReservationDeleteRequestProto$Builder;
      25: aload_0
      26: iconst_0
      27: putfield      #5                  // Field viaProto:Z
      30: return

  public org.apache.hadoop.yarn.api.records.ReservationId getReservationId();
    Code:
       0: aload_0
       1: getfield      #5                  // Field viaProto:Z
       4: ifeq          14
       7: aload_0
       8: getfield      #3                  // Field proto:Lorg/apache/hadoop/yarn/proto/YarnServiceProtos$ReservationDeleteRequestProto;
      11: goto          18
      14: aload_0
      15: getfield      #4                  // Field builder:Lorg/apache/hadoop/yarn/proto/YarnServiceProtos$ReservationDeleteRequestProto$Builder;
      18: astore_1
      19: aload_0
      20: getfield      #9                  // Field reservationId:Lorg/apache/hadoop/yarn/api/records/ReservationId;
      23: ifnull        31
      26: aload_0
      27: getfield      #9                  // Field reservationId:Lorg/apache/hadoop/yarn/api/records/ReservationId;
      30: areturn
      31: aload_1
      32: invokeinterface #15,  1           // InterfaceMethod org/apache/hadoop/yarn/proto/YarnServiceProtos$ReservationDeleteRequestProtoOrBuilder.hasReservationId:()Z
      37: ifne          42
      40: aconst_null
      41: areturn
      42: aload_0
      43: aload_0
      44: aload_1
      45: invokeinterface #16,  1           // InterfaceMethod org/apache/hadoop/yarn/proto/YarnServiceProtos$ReservationDeleteRequestProtoOrBuilder.getReservationId:()Lorg/apache/hadoop/yarn/proto/YarnProtos$ReservationIdProto;
      50: invokespecial #17                 // Method convertFromProtoFormat:(Lorg/apache/hadoop/yarn/proto/YarnProtos$ReservationIdProto;)Lorg/apache/hadoop/yarn/api/records/impl/pb/ReservationIdPBImpl;
      53: putfield      #9                  // Field reservationId:Lorg/apache/hadoop/yarn/api/records/ReservationId;
      56: aload_0
      57: getfield      #9                  // Field reservationId:Lorg/apache/hadoop/yarn/api/records/ReservationId;
      60: areturn

  public void setReservationId(org.apache.hadoop.yarn.api.records.ReservationId);
    Code:
       0: aload_0
       1: invokespecial #12                 // Method maybeInitBuilder:()V
       4: aload_1
       5: ifnonnull     17
       8: aload_0
       9: getfield      #4                  // Field builder:Lorg/apache/hadoop/yarn/proto/YarnServiceProtos$ReservationDeleteRequestProto$Builder;
      12: invokevirtual #18                 // Method org/apache/hadoop/yarn/proto/YarnServiceProtos$ReservationDeleteRequestProto$Builder.clearReservationId:()Lorg/apache/hadoop/yarn/proto/YarnServiceProtos$ReservationDeleteRequestProto$Builder;
      15: pop
      16: return
      17: aload_0
      18: aload_1
      19: putfield      #9                  // Field reservationId:Lorg/apache/hadoop/yarn/api/records/ReservationId;
      22: return

  private org.apache.hadoop.yarn.api.records.impl.pb.ReservationIdPBImpl convertFromProtoFormat(org.apache.hadoop.yarn.proto.YarnProtos$ReservationIdProto);
    Code:
       0: new           #19                 // class org/apache/hadoop/yarn/api/records/impl/pb/ReservationIdPBImpl
       3: dup
       4: aload_1
       5: invokespecial #20                 // Method org/apache/hadoop/yarn/api/records/impl/pb/ReservationIdPBImpl."<init>":(Lorg/apache/hadoop/yarn/proto/YarnProtos$ReservationIdProto;)V
       8: areturn

  private org.apache.hadoop.yarn.proto.YarnProtos$ReservationIdProto convertToProtoFormat(org.apache.hadoop.yarn.api.records.ReservationId);
    Code:
       0: aload_1
       1: checkcast     #19                 // class org/apache/hadoop/yarn/api/records/impl/pb/ReservationIdPBImpl
       4: invokevirtual #21                 // Method org/apache/hadoop/yarn/api/records/impl/pb/ReservationIdPBImpl.getProto:()Lorg/apache/hadoop/yarn/proto/YarnProtos$ReservationIdProto;
       7: areturn

  public int hashCode();
    Code:
       0: aload_0
       1: invokevirtual #22                 // Method getProto:()Lorg/apache/hadoop/yarn/proto/YarnServiceProtos$ReservationDeleteRequestProto;
       4: invokevirtual #23                 // Method org/apache/hadoop/yarn/proto/YarnServiceProtos$ReservationDeleteRequestProto.hashCode:()I
       7: ireturn

  public boolean equals(java.lang.Object);
    Code:
       0: aload_1
       1: ifnonnull     6
       4: iconst_0
       5: ireturn
       6: aload_1
       7: invokevirtual #24                 // Method java/lang/Object.getClass:()Ljava/lang/Class;
      10: aload_0
      11: invokevirtual #24                 // Method java/lang/Object.getClass:()Ljava/lang/Class;
      14: invokevirtual #25                 // Method java/lang/Class.isAssignableFrom:(Ljava/lang/Class;)Z
      17: ifeq          42
      20: aload_0
      21: invokevirtual #22                 // Method getProto:()Lorg/apache/hadoop/yarn/proto/YarnServiceProtos$ReservationDeleteRequestProto;
      24: aload_0
      25: invokevirtual #24                 // Method java/lang/Object.getClass:()Ljava/lang/Class;
      28: aload_1
      29: invokevirtual #26                 // Method java/lang/Class.cast:(Ljava/lang/Object;)Ljava/lang/Object;
      32: checkcast     #27                 // class org/apache/hadoop/yarn/api/protocolrecords/impl/pb/ReservationDeleteRequestPBImpl
      35: invokevirtual #22                 // Method getProto:()Lorg/apache/hadoop/yarn/proto/YarnServiceProtos$ReservationDeleteRequestProto;
      38: invokevirtual #28                 // Method org/apache/hadoop/yarn/proto/YarnServiceProtos$ReservationDeleteRequestProto.equals:(Ljava/lang/Object;)Z
      41: ireturn
      42: iconst_0
      43: ireturn

  public java.lang.String toString();
    Code:
       0: aload_0
       1: invokevirtual #22                 // Method getProto:()Lorg/apache/hadoop/yarn/proto/YarnServiceProtos$ReservationDeleteRequestProto;
       4: invokestatic  #29                 // Method com/google/protobuf/TextFormat.shortDebugString:(Lcom/google/protobuf/MessageOrBuilder;)Ljava/lang/String;
       7: areturn
}
