Compiled from "SuffixTreeCloneDetectionAlgorithm.java"
public final class org.sonar.duplications.detector.suffixtree.SuffixTreeCloneDetectionAlgorithm {
  private static final java.util.Comparator<org.sonar.duplications.block.Block> BLOCK_COMPARATOR;

  private org.sonar.duplications.detector.suffixtree.SuffixTreeCloneDetectionAlgorithm();
    Code:
       0: aload_0
       1: invokespecial #27                 // Method java/lang/Object."<init>":()V
       4: return

  public static java.util.List<org.sonar.duplications.index.CloneGroup> detect(org.sonar.duplications.index.CloneIndex, java.util.Collection<org.sonar.duplications.block.Block>);
    Code:
       0: aload_1
       1: invokeinterface #37,  1           // InterfaceMethod java/util/Collection.isEmpty:()Z
       6: ifeq          13
       9: invokestatic  #43                 // Method java/util/Collections.emptyList:()Ljava/util/List;
      12: areturn
      13: aload_0
      14: aload_1
      15: invokestatic  #47                 // Method createTextSet:(Lorg/sonar/duplications/index/CloneIndex;Ljava/util/Collection;)Lorg/sonar/duplications/detector/suffixtree/TextSet;
      18: astore_2
      19: aload_2
      20: ifnonnull     27
      23: invokestatic  #43                 // Method java/util/Collections.emptyList:()Ljava/util/List;
      26: areturn
      27: new           #49                 // class org/sonar/duplications/detector/suffixtree/DuplicationsCollector
      30: dup
      31: aload_2
      32: invokespecial #52                 // Method org/sonar/duplications/detector/suffixtree/DuplicationsCollector."<init>":(Lorg/sonar/duplications/detector/suffixtree/TextSet;)V
      35: astore_3
      36: aload_2
      37: aload_3
      38: invokestatic  #56                 // Method org/sonar/duplications/detector/suffixtree/Search.perform:(Lorg/sonar/duplications/detector/suffixtree/TextSet;Lorg/sonar/duplications/detector/suffixtree/Search$Collector;)V
      41: aload_3
      42: invokevirtual #59                 // Method org/sonar/duplications/detector/suffixtree/DuplicationsCollector.getResult:()Ljava/util/List;
      45: areturn

  private static org.sonar.duplications.detector.suffixtree.TextSet createTextSet(org.sonar.duplications.index.CloneIndex, java.util.Collection<org.sonar.duplications.block.Block>);
    Code:
       0: new           #70                 // class java/util/HashSet
       3: dup
       4: invokespecial #71                 // Method java/util/HashSet."<init>":()V
       7: astore_2
       8: aload_1
       9: invokeinterface #75,  1           // InterfaceMethod java/util/Collection.iterator:()Ljava/util/Iterator;
      14: astore_3
      15: aload_3
      16: invokeinterface #82,  1           // InterfaceMethod java/util/Iterator.hasNext:()Z
      21: ifeq          50
      24: aload_3
      25: invokeinterface #86,  1           // InterfaceMethod java/util/Iterator.next:()Ljava/lang/Object;
      30: checkcast     #88                 // class org/sonar/duplications/block/Block
      33: astore        4
      35: aload_2
      36: aload         4
      38: invokevirtual #92                 // Method org/sonar/duplications/block/Block.getBlockHash:()Lorg/sonar/duplications/block/ByteArray;
      41: invokeinterface #96,  2           // InterfaceMethod java/util/Set.add:(Ljava/lang/Object;)Z
      46: pop
      47: goto          15
      50: aload_1
      51: invokeinterface #75,  1           // InterfaceMethod java/util/Collection.iterator:()Ljava/util/Iterator;
      56: invokeinterface #86,  1           // InterfaceMethod java/util/Iterator.next:()Ljava/lang/Object;
      61: checkcast     #88                 // class org/sonar/duplications/block/Block
      64: invokevirtual #100                // Method org/sonar/duplications/block/Block.getResourceId:()Ljava/lang/String;
      67: astore_3
      68: aload_0
      69: aload_3
      70: aload_2
      71: invokestatic  #104                // Method retrieveFromIndex:(Lorg/sonar/duplications/index/CloneIndex;Ljava/lang/String;Ljava/util/Set;)Ljava/util/Map;
      74: astore        4
      76: aload         4
      78: invokeinterface #107,  1          // InterfaceMethod java/util/Map.isEmpty:()Z
      83: ifeq          103
      86: aload_2
      87: invokeinterface #111,  1          // InterfaceMethod java/util/Set.size:()I
      92: aload_1
      93: invokeinterface #112,  1          // InterfaceMethod java/util/Collection.size:()I
      98: if_icmpne     103
     101: aconst_null
     102: areturn
     103: aload_1
     104: aload         4
     106: invokestatic  #117                // Method createTextSet:(Ljava/util/Collection;Ljava/util/Map;)Lorg/sonar/duplications/detector/suffixtree/TextSet;
     109: areturn

  private static org.sonar.duplications.detector.suffixtree.TextSet createTextSet(java.util.Collection<org.sonar.duplications.block.Block>, java.util.Map<java.lang.String, java.util.List<org.sonar.duplications.block.Block>>);
    Code:
       0: invokestatic  #132                // Method org/sonar/duplications/detector/suffixtree/TextSet.builder:()Lorg/sonar/duplications/detector/suffixtree/TextSet$Builder;
       3: astore_2
       4: new           #134                // class java/util/ArrayList
       7: dup
       8: aload_0
       9: invokespecial #137                // Method java/util/ArrayList."<init>":(Ljava/util/Collection;)V
      12: astore_3
      13: aload_3
      14: getstatic     #139                // Field BLOCK_COMPARATOR:Ljava/util/Comparator;
      17: invokestatic  #143                // Method java/util/Collections.sort:(Ljava/util/List;Ljava/util/Comparator;)V
      20: aload_2
      21: aload_3
      22: invokevirtual #146                // Method org/sonar/duplications/detector/suffixtree/TextSet$Builder.add:(Ljava/util/List;)V
      25: aload_1
      26: invokeinterface #150,  1          // InterfaceMethod java/util/Map.values:()Ljava/util/Collection;
      31: invokeinterface #75,  1           // InterfaceMethod java/util/Collection.iterator:()Ljava/util/Iterator;
      36: astore        4
      38: aload         4
      40: invokeinterface #82,  1           // InterfaceMethod java/util/Iterator.hasNext:()Z
      45: ifeq          169
      48: aload         4
      50: invokeinterface #86,  1           // InterfaceMethod java/util/Iterator.next:()Ljava/lang/Object;
      55: checkcast     #152                // class java/util/List
      58: astore        5
      60: aload         5
      62: getstatic     #139                // Field BLOCK_COMPARATOR:Ljava/util/Comparator;
      65: invokestatic  #143                // Method java/util/Collections.sort:(Ljava/util/List;Ljava/util/Comparator;)V
      68: iconst_0
      69: istore        6
      71: iload         6
      73: aload         5
      75: invokeinterface #153,  1          // InterfaceMethod java/util/List.size:()I
      80: if_icmpge     166
      83: iload         6
      85: iconst_1
      86: iadd
      87: istore        7
      89: iload         7
      91: aload         5
      93: invokeinterface #153,  1          // InterfaceMethod java/util/List.size:()I
      98: if_icmpge     144
     101: aload         5
     103: iload         7
     105: invokeinterface #157,  2          // InterfaceMethod java/util/List.get:(I)Ljava/lang/Object;
     110: checkcast     #88                 // class org/sonar/duplications/block/Block
     113: invokevirtual #160                // Method org/sonar/duplications/block/Block.getIndexInFile:()I
     116: aload         5
     118: iload         7
     120: iconst_1
     121: isub
     122: invokeinterface #157,  2          // InterfaceMethod java/util/List.get:(I)Ljava/lang/Object;
     127: checkcast     #88                 // class org/sonar/duplications/block/Block
     130: invokevirtual #160                // Method org/sonar/duplications/block/Block.getIndexInFile:()I
     133: iconst_1
     134: iadd
     135: if_icmpne     144
     138: iinc          7, 1
     141: goto          89
     144: aload_2
     145: aload         5
     147: iload         6
     149: iload         7
     151: invokeinterface #164,  3          // InterfaceMethod java/util/List.subList:(II)Ljava/util/List;
     156: invokevirtual #146                // Method org/sonar/duplications/detector/suffixtree/TextSet$Builder.add:(Ljava/util/List;)V
     159: iload         7
     161: istore        6
     163: goto          71
     166: goto          38
     169: aload_2
     170: invokevirtual #168                // Method org/sonar/duplications/detector/suffixtree/TextSet$Builder.build:()Lorg/sonar/duplications/detector/suffixtree/TextSet;
     173: areturn

  private static java.util.Map<java.lang.String, java.util.List<org.sonar.duplications.block.Block>> retrieveFromIndex(org.sonar.duplications.index.CloneIndex, java.lang.String, java.util.Set<org.sonar.duplications.block.ByteArray>);
    Code:
       0: new           #179                // class java/util/HashMap
       3: dup
       4: invokespecial #180                // Method java/util/HashMap."<init>":()V
       7: astore_3
       8: aload_2
       9: invokeinterface #181,  1          // InterfaceMethod java/util/Set.iterator:()Ljava/util/Iterator;
      14: astore        4
      16: aload         4
      18: invokeinterface #82,  1           // InterfaceMethod java/util/Iterator.hasNext:()Z
      23: ifeq          149
      26: aload         4
      28: invokeinterface #86,  1           // InterfaceMethod java/util/Iterator.next:()Ljava/lang/Object;
      33: checkcast     #183                // class org/sonar/duplications/block/ByteArray
      36: astore        5
      38: aload_0
      39: aload         5
      41: invokeinterface #189,  2          // InterfaceMethod org/sonar/duplications/index/CloneIndex.getBySequenceHash:(Lorg/sonar/duplications/block/ByteArray;)Ljava/util/Collection;
      46: astore        6
      48: aload         6
      50: invokeinterface #75,  1           // InterfaceMethod java/util/Collection.iterator:()Ljava/util/Iterator;
      55: astore        7
      57: aload         7
      59: invokeinterface #82,  1           // InterfaceMethod java/util/Iterator.hasNext:()Z
      64: ifeq          146
      67: aload         7
      69: invokeinterface #86,  1           // InterfaceMethod java/util/Iterator.next:()Ljava/lang/Object;
      74: checkcast     #88                 // class org/sonar/duplications/block/Block
      77: astore        8
      79: aload         8
      81: invokevirtual #100                // Method org/sonar/duplications/block/Block.getResourceId:()Ljava/lang/String;
      84: astore        9
      86: aload_1
      87: aload         9
      89: invokevirtual #192                // Method java/lang/String.equals:(Ljava/lang/Object;)Z
      92: ifne          143
      95: aload_3
      96: aload         9
      98: invokeinterface #195,  2          // InterfaceMethod java/util/Map.get:(Ljava/lang/Object;)Ljava/lang/Object;
     103: checkcast     #152                // class java/util/List
     106: astore        10
     108: aload         10
     110: ifnonnull     133
     113: new           #134                // class java/util/ArrayList
     116: dup
     117: invokespecial #196                // Method java/util/ArrayList."<init>":()V
     120: astore        10
     122: aload_3
     123: aload         9
     125: aload         10
     127: invokeinterface #200,  3          // InterfaceMethod java/util/Map.put:(Ljava/lang/Object;Ljava/lang/Object;)Ljava/lang/Object;
     132: pop
     133: aload         10
     135: aload         8
     137: invokeinterface #201,  2          // InterfaceMethod java/util/List.add:(Ljava/lang/Object;)Z
     142: pop
     143: goto          57
     146: goto          16
     149: aload_3
     150: areturn

  private static int lambda$static$0(org.sonar.duplications.block.Block, org.sonar.duplications.block.Block);
    Code:
       0: aload_0
       1: invokevirtual #160                // Method org/sonar/duplications/block/Block.getIndexInFile:()I
       4: aload_1
       5: invokevirtual #160                // Method org/sonar/duplications/block/Block.getIndexInFile:()I
       8: isub
       9: ireturn

  static {};
    Code:
       0: invokedynamic #229,  0            // InvokeDynamic #0:compare:()Ljava/util/Comparator;
       5: putstatic     #139                // Field BLOCK_COMPARATOR:Ljava/util/Comparator;
       8: return
}
