Compiled from "KeyStoreX509CredentialAdapter.java"
public class org.opensaml.security.x509.impl.KeyStoreX509CredentialAdapter extends org.opensaml.security.credential.AbstractCredential implements org.opensaml.security.x509.X509Credential {
  private org.slf4j.Logger log;

  private final java.security.KeyStore keyStore;

  private final java.lang.String credentialAlias;

  private final char[] keyPassword;

  public org.opensaml.security.x509.impl.KeyStoreX509CredentialAdapter(java.security.KeyStore, java.lang.String, char[]);
    Code:
       0: aload_0
       1: invokespecial #1                  // Method org/opensaml/security/credential/AbstractCredential."<init>":()V
       4: aload_0
       5: ldc_w         #2                  // class org/opensaml/security/x509/impl/KeyStoreX509CredentialAdapter
       8: invokestatic  #3                  // Method org/slf4j/LoggerFactory.getLogger:(Ljava/lang/Class;)Lorg/slf4j/Logger;
      11: putfield      #4                  // Field log:Lorg/slf4j/Logger;
      14: aload_0
      15: aload_1
      16: ldc           #5                  // String Keystore cannot be null
      18: invokestatic  #6                  // Method net/shibboleth/utilities/java/support/logic/Constraint.isNotNull:(Ljava/lang/Object;Ljava/lang/String;)Ljava/lang/Object;
      21: checkcast     #7                  // class java/security/KeyStore
      24: putfield      #8                  // Field keyStore:Ljava/security/KeyStore;
      27: aload_0
      28: aload_2
      29: invokestatic  #9                  // Method net/shibboleth/utilities/java/support/primitive/StringSupport.trimOrNull:(Ljava/lang/String;)Ljava/lang/String;
      32: ldc           #10                 // String Keystore alias cannot be null or empty
      34: invokestatic  #6                  // Method net/shibboleth/utilities/java/support/logic/Constraint.isNotNull:(Ljava/lang/Object;Ljava/lang/String;)Ljava/lang/Object;
      37: checkcast     #11                 // class java/lang/String
      40: putfield      #12                 // Field credentialAlias:Ljava/lang/String;
      43: aload_0
      44: aload_3
      45: putfield      #13                 // Field keyPassword:[C
      48: return

  public java.util.Collection<java.security.cert.X509CRL> getCRLs();
    Code:
       0: getstatic     #14                 // Field java/util/Collections.EMPTY_LIST:Ljava/util/List;
       3: areturn

  public java.security.cert.X509Certificate getEntityCertificate();
    Code:
       0: aload_0
       1: getfield      #8                  // Field keyStore:Ljava/security/KeyStore;
       4: aload_0
       5: getfield      #12                 // Field credentialAlias:Ljava/lang/String;
       8: invokevirtual #15                 // Method java/security/KeyStore.getCertificate:(Ljava/lang/String;)Ljava/security/cert/Certificate;
      11: checkcast     #16                 // class java/security/cert/X509Certificate
      14: areturn
      15: astore_1
      16: aload_0
      17: getfield      #4                  // Field log:Lorg/slf4j/Logger;
      20: ldc           #18                 // String Error accessing {} certificates in keystore
      22: aload_0
      23: getfield      #12                 // Field credentialAlias:Ljava/lang/String;
      26: aload_1
      27: invokeinterface #19,  4           // InterfaceMethod org/slf4j/Logger.error:(Ljava/lang/String;Ljava/lang/Object;Ljava/lang/Object;)V
      32: aconst_null
      33: areturn
    Exception table:
       from    to  target type
           0    14    15   Class java/security/KeyStoreException

  public java.util.Collection<java.security.cert.X509Certificate> getEntityCertificateChain();
    Code:
       0: getstatic     #14                 // Field java/util/Collections.EMPTY_LIST:Ljava/util/List;
       3: astore_1
       4: aload_0
       5: getfield      #8                  // Field keyStore:Ljava/security/KeyStore;
       8: aload_0
       9: getfield      #12                 // Field credentialAlias:Ljava/lang/String;
      12: invokevirtual #20                 // Method java/security/KeyStore.getCertificateChain:(Ljava/lang/String;)[Ljava/security/cert/Certificate;
      15: astore_2
      16: aload_2
      17: ifnull        70
      20: new           #21                 // class java/util/ArrayList
      23: dup
      24: aload_2
      25: arraylength
      26: invokespecial #22                 // Method java/util/ArrayList."<init>":(I)V
      29: astore_1
      30: aload_2
      31: astore_3
      32: aload_3
      33: arraylength
      34: istore        4
      36: iconst_0
      37: istore        5
      39: iload         5
      41: iload         4
      43: if_icmpge     70
      46: aload_3
      47: iload         5
      49: aaload
      50: astore        6
      52: aload_1
      53: aload         6
      55: checkcast     #16                 // class java/security/cert/X509Certificate
      58: invokeinterface #23,  2           // InterfaceMethod java/util/List.add:(Ljava/lang/Object;)Z
      63: pop
      64: iinc          5, 1
      67: goto          39
      70: goto          90
      73: astore_2
      74: aload_0
      75: getfield      #4                  // Field log:Lorg/slf4j/Logger;
      78: ldc           #18                 // String Error accessing {} certificates in keystore
      80: aload_0
      81: getfield      #12                 // Field credentialAlias:Ljava/lang/String;
      84: aload_2
      85: invokeinterface #19,  4           // InterfaceMethod org/slf4j/Logger.error:(Ljava/lang/String;Ljava/lang/Object;Ljava/lang/Object;)V
      90: aload_1
      91: areturn
    Exception table:
       from    to  target type
           4    70    73   Class java/security/KeyStoreException

  public java.security.PrivateKey getPrivateKey();
    Code:
       0: aload_0
       1: getfield      #8                  // Field keyStore:Ljava/security/KeyStore;
       4: aload_0
       5: getfield      #12                 // Field credentialAlias:Ljava/lang/String;
       8: aload_0
       9: getfield      #13                 // Field keyPassword:[C
      12: invokevirtual #24                 // Method java/security/KeyStore.getKey:(Ljava/lang/String;[C)Ljava/security/Key;
      15: checkcast     #25                 // class java/security/PrivateKey
      18: areturn
      19: astore_1
      20: aload_0
      21: getfield      #4                  // Field log:Lorg/slf4j/Logger;
      24: ldc           #28                 // String Error accessing {} private key in keystore
      26: aload_0
      27: getfield      #12                 // Field credentialAlias:Ljava/lang/String;
      30: aload_1
      31: invokeinterface #19,  4           // InterfaceMethod org/slf4j/Logger.error:(Ljava/lang/String;Ljava/lang/Object;Ljava/lang/Object;)V
      36: aconst_null
      37: areturn
    Exception table:
       from    to  target type
           0    18    19   Class java/security/KeyStoreException
           0    18    19   Class java/security/UnrecoverableKeyException
           0    18    19   Class java/security/NoSuchAlgorithmException

  public java.security.PublicKey getPublicKey();
    Code:
       0: aload_0
       1: invokevirtual #29                 // Method getEntityCertificate:()Ljava/security/cert/X509Certificate;
       4: invokevirtual #30                 // Method java/security/cert/X509Certificate.getPublicKey:()Ljava/security/PublicKey;
       7: areturn

  public java.lang.Class<? extends org.opensaml.security.credential.Credential> getCredentialType();
    Code:
       0: ldc_w         #31                 // class org/opensaml/security/x509/X509Credential
       3: areturn

  public void setEntityId(java.lang.String);
    Code:
       0: aload_0
       1: aload_1
       2: invokespecial #32                 // Method org/opensaml/security/credential/AbstractCredential.setEntityId:(Ljava/lang/String;)V
       5: return

  public void setUsageType(org.opensaml.security.credential.UsageType);
    Code:
       0: aload_0
       1: aload_1
       2: invokespecial #33                 // Method org/opensaml/security/credential/AbstractCredential.setUsageType:(Lorg/opensaml/security/credential/UsageType;)V
       5: return
}
