Compiled from "X509KeyManagerX509CredentialAdapter.java"
public class org.opensaml.security.x509.impl.X509KeyManagerX509CredentialAdapter extends org.opensaml.security.credential.AbstractCredential implements org.opensaml.security.x509.X509Credential {
  private final java.lang.String credentialAlias;

  private final javax.net.ssl.X509KeyManager keyManager;

  public org.opensaml.security.x509.impl.X509KeyManagerX509CredentialAdapter(javax.net.ssl.X509KeyManager, java.lang.String);
    Code:
       0: aload_0
       1: invokespecial #1                  // Method org/opensaml/security/credential/AbstractCredential."<init>":()V
       4: aload_0
       5: aload_1
       6: ldc           #2                  // String Key manager cannot be null
       8: invokestatic  #3                  // Method net/shibboleth/utilities/java/support/logic/Constraint.isNotNull:(Ljava/lang/Object;Ljava/lang/String;)Ljava/lang/Object;
      11: checkcast     #4                  // class javax/net/ssl/X509KeyManager
      14: putfield      #5                  // Field keyManager:Ljavax/net/ssl/X509KeyManager;
      17: aload_0
      18: aload_2
      19: invokestatic  #6                  // Method net/shibboleth/utilities/java/support/primitive/StringSupport.trimOrNull:(Ljava/lang/String;)Ljava/lang/String;
      22: ldc           #7                  // String Entity alias cannot be null
      24: invokestatic  #3                  // Method net/shibboleth/utilities/java/support/logic/Constraint.isNotNull:(Ljava/lang/Object;Ljava/lang/String;)Ljava/lang/Object;
      27: checkcast     #8                  // class java/lang/String
      30: putfield      #9                  // Field credentialAlias:Ljava/lang/String;
      33: return

  public java.util.Collection<java.security.cert.X509CRL> getCRLs();
    Code:
       0: getstatic     #10                 // Field java/util/Collections.EMPTY_LIST:Ljava/util/List;
       3: areturn

  public java.security.cert.X509Certificate getEntityCertificate();
    Code:
       0: aload_0
       1: getfield      #5                  // Field keyManager:Ljavax/net/ssl/X509KeyManager;
       4: aload_0
       5: getfield      #9                  // Field credentialAlias:Ljava/lang/String;
       8: invokeinterface #11,  2           // InterfaceMethod javax/net/ssl/X509KeyManager.getCertificateChain:(Ljava/lang/String;)[Ljava/security/cert/X509Certificate;
      13: astore_1
      14: aload_1
      15: ifnull        27
      18: aload_1
      19: arraylength
      20: ifle          27
      23: aload_1
      24: iconst_0
      25: aaload
      26: areturn
      27: aconst_null
      28: areturn

  public java.util.Collection<java.security.cert.X509Certificate> getEntityCertificateChain();
    Code:
       0: aload_0
       1: getfield      #5                  // Field keyManager:Ljavax/net/ssl/X509KeyManager;
       4: aload_0
       5: getfield      #9                  // Field credentialAlias:Ljava/lang/String;
       8: invokeinterface #11,  2           // InterfaceMethod javax/net/ssl/X509KeyManager.getCertificateChain:(Ljava/lang/String;)[Ljava/security/cert/X509Certificate;
      13: astore_1
      14: aload_1
      15: ifnull        28
      18: aload_1
      19: arraylength
      20: ifle          28
      23: aload_1
      24: invokestatic  #12                 // Method java/util/Arrays.asList:([Ljava/lang/Object;)Ljava/util/List;
      27: areturn
      28: aconst_null
      29: areturn

  public java.security.PrivateKey getPrivateKey();
    Code:
       0: aload_0
       1: getfield      #5                  // Field keyManager:Ljavax/net/ssl/X509KeyManager;
       4: aload_0
       5: getfield      #9                  // Field credentialAlias:Ljava/lang/String;
       8: invokeinterface #13,  2           // InterfaceMethod javax/net/ssl/X509KeyManager.getPrivateKey:(Ljava/lang/String;)Ljava/security/PrivateKey;
      13: areturn

  public java.security.PublicKey getPublicKey();
    Code:
       0: aload_0
       1: invokevirtual #14                 // Method getEntityCertificate:()Ljava/security/cert/X509Certificate;
       4: invokevirtual #15                 // Method java/security/cert/X509Certificate.getPublicKey:()Ljava/security/PublicKey;
       7: areturn

  public java.lang.Class<? extends org.opensaml.security.credential.Credential> getCredentialType();
    Code:
       0: ldc_w         #16                 // class org/opensaml/security/x509/X509Credential
       3: areturn

  public void setEntityId(java.lang.String);
    Code:
       0: aload_0
       1: aload_1
       2: invokespecial #17                 // Method org/opensaml/security/credential/AbstractCredential.setEntityId:(Ljava/lang/String;)V
       5: return

  public void setUsageType(org.opensaml.security.credential.UsageType);
    Code:
       0: aload_0
       1: aload_1
       2: invokespecial #18                 // Method org/opensaml/security/credential/AbstractCredential.setUsageType:(Lorg/opensaml/security/credential/UsageType;)V
       5: return
}
