Compiled from "CPU_A64.java"
public final class jnr.a64asm.CPU_A64 extends java.lang.Enum<jnr.a64asm.CPU_A64> {
  public static final jnr.a64asm.CPU_A64 Aarch32;

  public static final jnr.a64asm.CPU_A64 Aarch64;

  public static final jnr.a64asm.CPU_A64 X86_32;

  public static final jnr.a64asm.CPU_A64 X86_64;

  public static final jnr.a64asm.CPU_A64 I386;

  public static final jnr.a64asm.CPU_A64 A64;

  private static final jnr.a64asm.CPU_A64[] $VALUES;

  public static jnr.a64asm.CPU_A64[] values();
    Code:
       0: getstatic     #1                  // Field $VALUES:[Ljnr/a64asm/CPU_A64;
       3: invokevirtual #2                  // Method "[Ljnr/a64asm/CPU_A64;".clone:()Ljava/lang/Object;
       6: checkcast     #3                  // class "[Ljnr/a64asm/CPU_A64;"
       9: areturn

  public static jnr.a64asm.CPU_A64 valueOf(java.lang.String);
    Code:
       0: ldc           #4                  // class jnr/a64asm/CPU_A64
       2: aload_0
       3: invokestatic  #5                  // Method java/lang/Enum.valueOf:(Ljava/lang/Class;Ljava/lang/String;)Ljava/lang/Enum;
       6: checkcast     #4                  // class jnr/a64asm/CPU_A64
       9: areturn

  private jnr.a64asm.CPU_A64();
    Code:
       0: aload_0
       1: aload_1
       2: iload_2
       3: invokespecial #6                  // Method java/lang/Enum."<init>":(Ljava/lang/String;I)V
       6: return

  static {};
    Code:
       0: new           #4                  // class jnr/a64asm/CPU_A64
       3: dup
       4: ldc           #7                  // String Aarch32
       6: iconst_0
       7: invokespecial #8                  // Method "<init>":(Ljava/lang/String;I)V
      10: putstatic     #9                  // Field Aarch32:Ljnr/a64asm/CPU_A64;
      13: new           #4                  // class jnr/a64asm/CPU_A64
      16: dup
      17: ldc           #10                 // String Aarch64
      19: iconst_1
      20: invokespecial #8                  // Method "<init>":(Ljava/lang/String;I)V
      23: putstatic     #11                 // Field Aarch64:Ljnr/a64asm/CPU_A64;
      26: new           #4                  // class jnr/a64asm/CPU_A64
      29: dup
      30: ldc           #12                 // String X86_32
      32: iconst_2
      33: invokespecial #8                  // Method "<init>":(Ljava/lang/String;I)V
      36: putstatic     #13                 // Field X86_32:Ljnr/a64asm/CPU_A64;
      39: new           #4                  // class jnr/a64asm/CPU_A64
      42: dup
      43: ldc           #14                 // String X86_64
      45: iconst_3
      46: invokespecial #8                  // Method "<init>":(Ljava/lang/String;I)V
      49: putstatic     #15                 // Field X86_64:Ljnr/a64asm/CPU_A64;
      52: iconst_4
      53: anewarray     #4                  // class jnr/a64asm/CPU_A64
      56: dup
      57: iconst_0
      58: getstatic     #9                  // Field Aarch32:Ljnr/a64asm/CPU_A64;
      61: aastore
      62: dup
      63: iconst_1
      64: getstatic     #11                 // Field Aarch64:Ljnr/a64asm/CPU_A64;
      67: aastore
      68: dup
      69: iconst_2
      70: getstatic     #13                 // Field X86_32:Ljnr/a64asm/CPU_A64;
      73: aastore
      74: dup
      75: iconst_3
      76: getstatic     #15                 // Field X86_64:Ljnr/a64asm/CPU_A64;
      79: aastore
      80: putstatic     #1                  // Field $VALUES:[Ljnr/a64asm/CPU_A64;
      83: getstatic     #13                 // Field X86_32:Ljnr/a64asm/CPU_A64;
      86: putstatic     #16                 // Field I386:Ljnr/a64asm/CPU_A64;
      89: getstatic     #11                 // Field Aarch64:Ljnr/a64asm/CPU_A64;
      92: putstatic     #17                 // Field A64:Ljnr/a64asm/CPU_A64;
      95: return
}
