Compiled from "ClusterConfig.java"
public class won.matcher.service.common.config.ClusterConfig {
  private java.lang.String nodeHost;

  private java.lang.String name;

  private int localPort;

  private java.util.List<java.lang.String> seedNodes;

  public won.matcher.service.common.config.ClusterConfig();
    Code:
       0: aload_0
       1: invokespecial #1                  // Method java/lang/Object."<init>":()V
       4: return

  public java.lang.String getNodeHost();
    Code:
       0: aload_0
       1: getfield      #2                  // Field nodeHost:Ljava/lang/String;
       4: areturn

  public java.lang.String getName();
    Code:
       0: aload_0
       1: getfield      #3                  // Field name:Ljava/lang/String;
       4: areturn

  public int getLocalPort();
    Code:
       0: aload_0
       1: getfield      #4                  // Field localPort:I
       4: ireturn

  public void setNodeHost(java.lang.String);
    Code:
       0: aload_0
       1: aload_1
       2: putfield      #2                  // Field nodeHost:Ljava/lang/String;
       5: return

  public void setName(java.lang.String);
    Code:
       0: aload_0
       1: aload_1
       2: putfield      #3                  // Field name:Ljava/lang/String;
       5: return

  public void setLocalPort(int);
    Code:
       0: aload_0
       1: iload_1
       2: putfield      #4                  // Field localPort:I
       5: return

  public java.util.List<java.lang.String> getSeedNodes();
    Code:
       0: aload_0
       1: getfield      #5                  // Field seedNodes:Ljava/util/List;
       4: areturn

  public void setSeedNodes(java.util.List<java.lang.String>);
    Code:
       0: aload_0
       1: aload_1
       2: putfield      #5                  // Field seedNodes:Ljava/util/List;
       5: return
}
