Compiled from "ScriptManager.java"
abstract class org.apache.logging.log4j.core.script.ScriptManager$AbstractScriptRunner implements org.apache.logging.log4j.core.script.ScriptManager$ScriptRunner {
  private static final java.lang.String KEY_STATUS_LOGGER;

  private static final java.lang.String KEY_CONFIGURATION;

  final org.apache.logging.log4j.core.script.ScriptManager this$0;

  private org.apache.logging.log4j.core.script.ScriptManager$AbstractScriptRunner(org.apache.logging.log4j.core.script.ScriptManager);
    Code:
       0: aload_0
       1: aload_1
       2: putfield      #2                  // Field this$0:Lorg/apache/logging/log4j/core/script/ScriptManager;
       5: aload_0
       6: invokespecial #3                  // Method java/lang/Object."<init>":()V
       9: return

  public javax.script.Bindings createBindings();
    Code:
       0: new           #4                  // class javax/script/SimpleBindings
       3: dup
       4: invokespecial #5                  // Method javax/script/SimpleBindings."<init>":()V
       7: astore_1
       8: aload_1
       9: ldc           #7                  // String configuration
      11: aload_0
      12: getfield      #2                  // Field this$0:Lorg/apache/logging/log4j/core/script/ScriptManager;
      15: invokestatic  #8                  // Method org/apache/logging/log4j/core/script/ScriptManager.access$000:(Lorg/apache/logging/log4j/core/script/ScriptManager;)Lorg/apache/logging/log4j/core/config/Configuration;
      18: invokevirtual #9                  // Method javax/script/SimpleBindings.put:(Ljava/lang/String;Ljava/lang/Object;)Ljava/lang/Object;
      21: pop
      22: aload_1
      23: ldc           #10                 // String statusLogger
      25: invokestatic  #11                 // Method org/apache/logging/log4j/core/script/ScriptManager.access$100:()Lorg/apache/logging/log4j/Logger;
      28: invokevirtual #9                  // Method javax/script/SimpleBindings.put:(Ljava/lang/String;Ljava/lang/Object;)Ljava/lang/Object;
      31: pop
      32: aload_1
      33: areturn

  org.apache.logging.log4j.core.script.ScriptManager$AbstractScriptRunner(org.apache.logging.log4j.core.script.ScriptManager, org.apache.logging.log4j.core.script.ScriptManager$1);
    Code:
       0: aload_0
       1: aload_1
       2: invokespecial #1                  // Method "<init>":(Lorg/apache/logging/log4j/core/script/ScriptManager;)V
       5: return
}
