Compiled from "ScriptRef.java"
public class org.apache.logging.log4j.core.script.ScriptRef extends org.apache.logging.log4j.core.script.AbstractScript {
  private final org.apache.logging.log4j.core.script.ScriptManager scriptManager;

  public org.apache.logging.log4j.core.script.ScriptRef(java.lang.String, org.apache.logging.log4j.core.script.ScriptManager);
    Code:
       0: aload_0
       1: aload_1
       2: aconst_null
       3: aconst_null
       4: invokespecial #1                  // Method org/apache/logging/log4j/core/script/AbstractScript."<init>":(Ljava/lang/String;Ljava/lang/String;Ljava/lang/String;)V
       7: aload_0
       8: aload_2
       9: putfield      #2                  // Field scriptManager:Lorg/apache/logging/log4j/core/script/ScriptManager;
      12: return

  public java.lang.String getLanguage();
    Code:
       0: aload_0
       1: getfield      #2                  // Field scriptManager:Lorg/apache/logging/log4j/core/script/ScriptManager;
       4: aload_0
       5: invokevirtual #3                  // Method getName:()Ljava/lang/String;
       8: invokevirtual #4                  // Method org/apache/logging/log4j/core/script/ScriptManager.getScript:(Ljava/lang/String;)Lorg/apache/logging/log4j/core/script/AbstractScript;
      11: astore_1
      12: aload_1
      13: ifnull        23
      16: aload_1
      17: invokevirtual #5                  // Method org/apache/logging/log4j/core/script/AbstractScript.getLanguage:()Ljava/lang/String;
      20: goto          24
      23: aconst_null
      24: areturn

  public java.lang.String getScriptText();
    Code:
       0: aload_0
       1: getfield      #2                  // Field scriptManager:Lorg/apache/logging/log4j/core/script/ScriptManager;
       4: aload_0
       5: invokevirtual #3                  // Method getName:()Ljava/lang/String;
       8: invokevirtual #4                  // Method org/apache/logging/log4j/core/script/ScriptManager.getScript:(Ljava/lang/String;)Lorg/apache/logging/log4j/core/script/AbstractScript;
      11: astore_1
      12: aload_1
      13: ifnull        23
      16: aload_1
      17: invokevirtual #6                  // Method org/apache/logging/log4j/core/script/AbstractScript.getScriptText:()Ljava/lang/String;
      20: goto          24
      23: aconst_null
      24: areturn

  public static org.apache.logging.log4j.core.script.ScriptRef createReference(java.lang.String, org.apache.logging.log4j.core.config.Configuration);
    Code:
       0: aload_0
       1: ifnonnull     16
       4: getstatic     #7                  // Field LOGGER:Lorg/apache/logging/log4j/Logger;
       7: ldc           #8                  // String No script name provided
       9: invokeinterface #9,  2            // InterfaceMethod org/apache/logging/log4j/Logger.error:(Ljava/lang/String;)V
      14: aconst_null
      15: areturn
      16: new           #10                 // class org/apache/logging/log4j/core/script/ScriptRef
      19: dup
      20: aload_0
      21: aload_1
      22: invokeinterface #11,  1           // InterfaceMethod org/apache/logging/log4j/core/config/Configuration.getScriptManager:()Lorg/apache/logging/log4j/core/script/ScriptManager;
      27: invokespecial #12                 // Method "<init>":(Ljava/lang/String;Lorg/apache/logging/log4j/core/script/ScriptManager;)V
      30: areturn

  public java.lang.String toString();
    Code:
       0: new           #13                 // class java/lang/StringBuilder
       3: dup
       4: invokespecial #14                 // Method java/lang/StringBuilder."<init>":()V
       7: ldc           #15                 // String ref=
       9: invokevirtual #16                 // Method java/lang/StringBuilder.append:(Ljava/lang/String;)Ljava/lang/StringBuilder;
      12: aload_0
      13: invokevirtual #3                  // Method getName:()Ljava/lang/String;
      16: invokevirtual #16                 // Method java/lang/StringBuilder.append:(Ljava/lang/String;)Ljava/lang/StringBuilder;
      19: invokevirtual #17                 // Method java/lang/StringBuilder.toString:()Ljava/lang/String;
      22: areturn
}
