Compiled from "TimelineV2Client.java"
public abstract class org.apache.hadoop.yarn.client.api.TimelineV2Client extends org.apache.hadoop.service.CompositeService {
  public static org.apache.hadoop.yarn.client.api.TimelineV2Client createTimelineClient(org.apache.hadoop.yarn.api.records.ApplicationId);
    Code:
       0: new           #1                  // class org/apache/hadoop/yarn/client/api/impl/TimelineV2ClientImpl
       3: dup
       4: aload_0
       5: invokespecial #2                  // Method org/apache/hadoop/yarn/client/api/impl/TimelineV2ClientImpl."<init>":(Lorg/apache/hadoop/yarn/api/records/ApplicationId;)V
       8: astore_1
       9: aload_1
      10: areturn

  protected org.apache.hadoop.yarn.client.api.TimelineV2Client(java.lang.String);
    Code:
       0: aload_0
       1: aload_1
       2: invokespecial #3                  // Method org/apache/hadoop/service/CompositeService."<init>":(Ljava/lang/String;)V
       5: return

  public abstract void putEntities(org.apache.hadoop.yarn.api.records.timelineservice.TimelineEntity...) throws java.io.IOException, org.apache.hadoop.yarn.exceptions.YarnException;

  public abstract void putEntitiesAsync(org.apache.hadoop.yarn.api.records.timelineservice.TimelineEntity...) throws java.io.IOException, org.apache.hadoop.yarn.exceptions.YarnException;

  public abstract void setTimelineCollectorInfo(org.apache.hadoop.yarn.api.records.CollectorInfo);

  public abstract void putSubAppEntities(org.apache.hadoop.yarn.api.records.timelineservice.TimelineEntity...) throws java.io.IOException, org.apache.hadoop.yarn.exceptions.YarnException;

  public abstract void putSubAppEntitiesAsync(org.apache.hadoop.yarn.api.records.timelineservice.TimelineEntity...) throws java.io.IOException, org.apache.hadoop.yarn.exceptions.YarnException;
}
