Compiled from "JavaZipFileSystem.java"
class org.jboss.vfs.spi.JavaZipFileSystem$1 implements java.io.Closeable {
  final org.jboss.vfs.spi.JavaZipFileSystem this$0;

  org.jboss.vfs.spi.JavaZipFileSystem$1(org.jboss.vfs.spi.JavaZipFileSystem);
    Code:
       0: aload_0
       1: aload_1
       2: putfield      #1                  // Field this$0:Lorg/jboss/vfs/spi/JavaZipFileSystem;
       5: aload_0
       6: invokespecial #2                  // Method java/lang/Object."<init>":()V
       9: return

  public void close() throws java.io.IOException;
    Code:
       0: aload_0
       1: getfield      #1                  // Field this$0:Lorg/jboss/vfs/spi/JavaZipFileSystem;
       4: invokestatic  #3                  // Method org/jboss/vfs/spi/JavaZipFileSystem.access$600:(Lorg/jboss/vfs/spi/JavaZipFileSystem;)Ljava/util/jar/JarFile;
       7: invokevirtual #4                  // Method java/util/jar/JarFile.close:()V
      10: return
}
