Compiled from "PersistentEntityJackson2Module.java"
class org.springframework.data.rest.webmvc.json.PersistentEntityJackson2Module$PersistentEntityResourceSerializer extends com.fasterxml.jackson.databind.ser.std.StdSerializer<org.springframework.data.rest.webmvc.PersistentEntityResource> {
  private final org.springframework.data.rest.webmvc.mapping.LinkCollector collector;

  private org.springframework.data.rest.webmvc.json.PersistentEntityJackson2Module$PersistentEntityResourceSerializer(org.springframework.data.rest.webmvc.mapping.LinkCollector);
    Code:
       0: aload_0
       1: ldc           #2                  // class org/springframework/data/rest/webmvc/PersistentEntityResource
       3: invokespecial #3                  // Method com/fasterxml/jackson/databind/ser/std/StdSerializer."<init>":(Ljava/lang/Class;)V
       6: aload_0
       7: aload_1
       8: putfield      #4                  // Field collector:Lorg/springframework/data/rest/webmvc/mapping/LinkCollector;
      11: return

  public void serialize(org.springframework.data.rest.webmvc.PersistentEntityResource, com.fasterxml.jackson.core.JsonGenerator, com.fasterxml.jackson.databind.SerializerProvider) throws java.io.IOException, com.fasterxml.jackson.core.JsonGenerationException;
    Code:
       0: invokestatic  #5                  // Method org/springframework/data/rest/webmvc/json/PersistentEntityJackson2Module.access$200:()Lorg/slf4j/Logger;
       3: ldc           #6                  // String Serializing PersistentEntity {}.
       5: aload_1
       6: invokevirtual #7                  // Method org/springframework/data/rest/webmvc/PersistentEntityResource.getPersistentEntity:()Lorg/springframework/data/mapping/PersistentEntity;
       9: invokeinterface #8,  3            // InterfaceMethod org/slf4j/Logger.debug:(Ljava/lang/String;Ljava/lang/Object;)V
      14: aload_1
      15: invokevirtual #9                  // Method org/springframework/data/rest/webmvc/PersistentEntityResource.getContent:()Ljava/lang/Object;
      18: astore        4
      20: aload         4
      22: aload_3
      23: invokestatic  #10                 // Method hasScalarSerializer:(Ljava/lang/Object;Lcom/fasterxml/jackson/databind/SerializerProvider;)Z
      26: ifeq          37
      29: aload_3
      30: aload         4
      32: aload_2
      33: invokevirtual #11                 // Method com/fasterxml/jackson/databind/SerializerProvider.defaultSerializeValue:(Ljava/lang/Object;Lcom/fasterxml/jackson/core/JsonGenerator;)V
      36: return
      37: aload_0
      38: aload_1
      39: invokespecial #12                 // Method getLinks:(Lorg/springframework/data/rest/webmvc/PersistentEntityResource;)Lorg/springframework/hateoas/Links;
      42: astore        5
      44: ldc           #13                 // class org/springframework/data/projection/TargetAware
      46: aload         4
      48: invokevirtual #14                 // Method java/lang/Class.isInstance:(Ljava/lang/Object;)Z
      51: ifeq          78
      54: aload         4
      56: checkcast     #13                 // class org/springframework/data/projection/TargetAware
      59: astore        6
      61: aload_3
      62: new           #15                 // class org/springframework/data/rest/webmvc/json/PersistentEntityJackson2Module$ProjectionResource
      65: dup
      66: aload         6
      68: aload         5
      70: invokespecial #16                 // Method org/springframework/data/rest/webmvc/json/PersistentEntityJackson2Module$ProjectionResource."<init>":(Lorg/springframework/data/projection/TargetAware;Ljava/lang/Iterable;)V
      73: aload_2
      74: invokevirtual #11                 // Method com/fasterxml/jackson/databind/SerializerProvider.defaultSerializeValue:(Ljava/lang/Object;Lcom/fasterxml/jackson/core/JsonGenerator;)V
      77: return
      78: new           #17                 // class org/springframework/data/rest/webmvc/json/PersistentEntityJackson2Module$PersistentEntityResourceSerializer$1
      81: dup
      82: aload_0
      83: aload_1
      84: invokevirtual #9                  // Method org/springframework/data/rest/webmvc/PersistentEntityResource.getContent:()Ljava/lang/Object;
      87: aload         5
      89: aload_1
      90: invokespecial #18                 // Method org/springframework/data/rest/webmvc/json/PersistentEntityJackson2Module$PersistentEntityResourceSerializer$1."<init>":(Lorg/springframework/data/rest/webmvc/json/PersistentEntityJackson2Module$PersistentEntityResourceSerializer;Ljava/lang/Object;Ljava/lang/Iterable;Lorg/springframework/data/rest/webmvc/PersistentEntityResource;)V
      93: astore        6
      95: aload_3
      96: aload         6
      98: aload_2
      99: invokevirtual #11                 // Method com/fasterxml/jackson/databind/SerializerProvider.defaultSerializeValue:(Ljava/lang/Object;Lcom/fasterxml/jackson/core/JsonGenerator;)V
     102: return

  private org.springframework.hateoas.Links getLinks(org.springframework.data.rest.webmvc.PersistentEntityResource);
    Code:
       0: aload_0
       1: aload_1
       2: invokevirtual #9                  // Method org/springframework/data/rest/webmvc/PersistentEntityResource.getContent:()Ljava/lang/Object;
       5: invokespecial #19                 // Method getLinkSource:(Ljava/lang/Object;)Ljava/lang/Object;
       8: astore_2
       9: aload_1
      10: invokevirtual #20                 // Method org/springframework/data/rest/webmvc/PersistentEntityResource.isNested:()Z
      13: ifeq          31
      16: aload_0
      17: getfield      #4                  // Field collector:Lorg/springframework/data/rest/webmvc/mapping/LinkCollector;
      20: aload_2
      21: aload_1
      22: invokevirtual #21                 // Method org/springframework/data/rest/webmvc/PersistentEntityResource.getLinks:()Ljava/util/List;
      25: invokevirtual #22                 // Method org/springframework/data/rest/webmvc/mapping/LinkCollector.getLinksForNested:(Ljava/lang/Object;Ljava/util/List;)Lorg/springframework/hateoas/Links;
      28: goto          43
      31: aload_0
      32: getfield      #4                  // Field collector:Lorg/springframework/data/rest/webmvc/mapping/LinkCollector;
      35: aload_2
      36: aload_1
      37: invokevirtual #21                 // Method org/springframework/data/rest/webmvc/PersistentEntityResource.getLinks:()Ljava/util/List;
      40: invokevirtual #23                 // Method org/springframework/data/rest/webmvc/mapping/LinkCollector.getLinksFor:(Ljava/lang/Object;Ljava/util/List;)Lorg/springframework/hateoas/Links;
      43: areturn

  private java.lang.Object getLinkSource(java.lang.Object);
    Code:
       0: ldc           #13                 // class org/springframework/data/projection/TargetAware
       2: aload_1
       3: invokevirtual #14                 // Method java/lang/Class.isInstance:(Ljava/lang/Object;)Z
       6: ifeq          21
       9: aload_1
      10: checkcast     #13                 // class org/springframework/data/projection/TargetAware
      13: invokeinterface #24,  1           // InterfaceMethod org/springframework/data/projection/TargetAware.getTarget:()Ljava/lang/Object;
      18: goto          22
      21: aload_1
      22: areturn

  private static boolean hasScalarSerializer(java.lang.Object, com.fasterxml.jackson.databind.SerializerProvider) throws com.fasterxml.jackson.databind.JsonMappingException;
    Code:
       0: aload_1
       1: aload_0
       2: invokevirtual #25                 // Method java/lang/Object.getClass:()Ljava/lang/Class;
       5: invokevirtual #26                 // Method com/fasterxml/jackson/databind/SerializerProvider.findValueSerializer:(Ljava/lang/Class;)Lcom/fasterxml/jackson/databind/JsonSerializer;
       8: astore_2
       9: aload_2
      10: instanceof    #27                 // class com/fasterxml/jackson/databind/ser/std/ToStringSerializer
      13: ifne          23
      16: aload_2
      17: instanceof    #28                 // class com/fasterxml/jackson/databind/ser/std/StdScalarSerializer
      20: ifeq          27
      23: iconst_1
      24: goto          28
      27: iconst_0
      28: ireturn

  public void serialize(java.lang.Object, com.fasterxml.jackson.core.JsonGenerator, com.fasterxml.jackson.databind.SerializerProvider) throws java.io.IOException;
    Code:
       0: aload_0
       1: aload_1
       2: checkcast     #2                  // class org/springframework/data/rest/webmvc/PersistentEntityResource
       5: aload_2
       6: aload_3
       7: invokevirtual #29                 // Method serialize:(Lorg/springframework/data/rest/webmvc/PersistentEntityResource;Lcom/fasterxml/jackson/core/JsonGenerator;Lcom/fasterxml/jackson/databind/SerializerProvider;)V
      10: return

  org.springframework.data.rest.webmvc.json.PersistentEntityJackson2Module$PersistentEntityResourceSerializer(org.springframework.data.rest.webmvc.mapping.LinkCollector, org.springframework.data.rest.webmvc.json.PersistentEntityJackson2Module$1);
    Code:
       0: aload_0
       1: aload_1
       2: invokespecial #1                  // Method "<init>":(Lorg/springframework/data/rest/webmvc/mapping/LinkCollector;)V
       5: return
}
