Compiled from "ASMHelper.java"
class org.apache.cxf.common.util.ASMHelper$2 implements org.apache.cxf.common.util.ASMHelper$Label {
  java.lang.Object l;

  final java.lang.Class val$cls;

  final org.apache.cxf.common.util.ASMHelper this$0;

  org.apache.cxf.common.util.ASMHelper$2(org.apache.cxf.common.util.ASMHelper, java.lang.Class) throws java.lang.IllegalAccessException, java.lang.InstantiationException;
    Code:
       0: aload_0
       1: aload_1
       2: putfield      #1                  // Field this$0:Lorg/apache/cxf/common/util/ASMHelper;
       5: aload_0
       6: aload_2
       7: putfield      #2                  // Field val$cls:Ljava/lang/Class;
      10: aload_0
      11: invokespecial #3                  // Method java/lang/Object."<init>":()V
      14: aload_0
      15: aload_0
      16: getfield      #2                  // Field val$cls:Ljava/lang/Class;
      19: invokevirtual #4                  // Method java/lang/Class.newInstance:()Ljava/lang/Object;
      22: putfield      #5                  // Field l:Ljava/lang/Object;
      25: return

  public java.lang.Object getValue();
    Code:
       0: aload_0
       1: getfield      #5                  // Field l:Ljava/lang/Object;
       4: areturn

  public java.lang.Class<?> realType();
    Code:
       0: aload_0
       1: getfield      #2                  // Field val$cls:Ljava/lang/Class;
       4: areturn
}
