Compiled from "SystemPropertyAction.java"
public final class org.apache.cxf.common.util.SystemPropertyAction implements java.security.PrivilegedAction<java.lang.String> {
  private static final java.util.logging.Logger LOG;

  private final java.lang.String property;

  private final java.lang.String def;

  private org.apache.cxf.common.util.SystemPropertyAction(java.lang.String);
    Code:
       0: aload_0
       1: invokespecial #1                  // Method java/lang/Object."<init>":()V
       4: aload_0
       5: aload_1
       6: putfield      #2                  // Field property:Ljava/lang/String;
       9: aload_0
      10: aconst_null
      11: putfield      #3                  // Field def:Ljava/lang/String;
      14: return

  private org.apache.cxf.common.util.SystemPropertyAction(java.lang.String, java.lang.String);
    Code:
       0: aload_0
       1: invokespecial #1                  // Method java/lang/Object."<init>":()V
       4: aload_0
       5: aload_1
       6: putfield      #2                  // Field property:Ljava/lang/String;
       9: aload_0
      10: aload_2
      11: putfield      #3                  // Field def:Ljava/lang/String;
      14: return

  public java.lang.String run();
    Code:
       0: aload_0
       1: getfield      #3                  // Field def:Ljava/lang/String;
       4: ifnull        19
       7: aload_0
       8: getfield      #2                  // Field property:Ljava/lang/String;
      11: aload_0
      12: getfield      #3                  // Field def:Ljava/lang/String;
      15: invokestatic  #4                  // Method java/lang/System.getProperty:(Ljava/lang/String;Ljava/lang/String;)Ljava/lang/String;
      18: areturn
      19: aload_0
      20: getfield      #2                  // Field property:Ljava/lang/String;
      23: invokestatic  #5                  // Method java/lang/System.getProperty:(Ljava/lang/String;)Ljava/lang/String;
      26: areturn

  public static java.lang.String getProperty(java.lang.String);
    Code:
       0: new           #6                  // class org/apache/cxf/common/util/SystemPropertyAction
       3: dup
       4: aload_0
       5: invokespecial #7                  // Method "<init>":(Ljava/lang/String;)V
       8: invokestatic  #8                  // Method java/security/AccessController.doPrivileged:(Ljava/security/PrivilegedAction;)Ljava/lang/Object;
      11: checkcast     #9                  // class java/lang/String
      14: areturn

  public static java.lang.String getProperty(java.lang.String, java.lang.String);
    Code:
       0: new           #6                  // class org/apache/cxf/common/util/SystemPropertyAction
       3: dup
       4: aload_0
       5: aload_1
       6: invokespecial #10                 // Method "<init>":(Ljava/lang/String;Ljava/lang/String;)V
       9: invokestatic  #8                  // Method java/security/AccessController.doPrivileged:(Ljava/security/PrivilegedAction;)Ljava/lang/Object;
      12: checkcast     #9                  // class java/lang/String
      15: areturn
      16: astore_2
      17: getstatic     #12                 // Field LOG:Ljava/util/logging/Logger;
      20: getstatic     #13                 // Field java/util/logging/Level.FINE:Ljava/util/logging/Level;
      23: new           #14                 // class java/lang/StringBuilder
      26: dup
      27: invokespecial #15                 // Method java/lang/StringBuilder."<init>":()V
      30: ldc           #16                 // String SecurityException raised getting property
      32: invokevirtual #17                 // Method java/lang/StringBuilder.append:(Ljava/lang/String;)Ljava/lang/StringBuilder;
      35: aload_0
      36: invokevirtual #17                 // Method java/lang/StringBuilder.append:(Ljava/lang/String;)Ljava/lang/StringBuilder;
      39: invokevirtual #18                 // Method java/lang/StringBuilder.toString:()Ljava/lang/String;
      42: aload_2
      43: invokevirtual #19                 // Method java/util/logging/Logger.log:(Ljava/util/logging/Level;Ljava/lang/String;Ljava/lang/Throwable;)V
      46: aload_1
      47: areturn
    Exception table:
       from    to  target type
           0    15    16   Class java/lang/SecurityException

  public static java.lang.String getPropertyOrNull(java.lang.String);
    Code:
       0: new           #6                  // class org/apache/cxf/common/util/SystemPropertyAction
       3: dup
       4: aload_0
       5: invokespecial #7                  // Method "<init>":(Ljava/lang/String;)V
       8: invokestatic  #8                  // Method java/security/AccessController.doPrivileged:(Ljava/security/PrivilegedAction;)Ljava/lang/Object;
      11: checkcast     #9                  // class java/lang/String
      14: areturn
      15: astore_1
      16: getstatic     #12                 // Field LOG:Ljava/util/logging/Logger;
      19: getstatic     #13                 // Field java/util/logging/Level.FINE:Ljava/util/logging/Level;
      22: new           #14                 // class java/lang/StringBuilder
      25: dup
      26: invokespecial #15                 // Method java/lang/StringBuilder."<init>":()V
      29: ldc           #16                 // String SecurityException raised getting property
      31: invokevirtual #17                 // Method java/lang/StringBuilder.append:(Ljava/lang/String;)Ljava/lang/StringBuilder;
      34: aload_0
      35: invokevirtual #17                 // Method java/lang/StringBuilder.append:(Ljava/lang/String;)Ljava/lang/StringBuilder;
      38: invokevirtual #18                 // Method java/lang/StringBuilder.toString:()Ljava/lang/String;
      41: aload_1
      42: invokevirtual #19                 // Method java/util/logging/Logger.log:(Ljava/util/logging/Level;Ljava/lang/String;Ljava/lang/Throwable;)V
      45: aconst_null
      46: areturn
    Exception table:
       from    to  target type
           0    14    15   Class java/lang/SecurityException

  public java.lang.Object run();
    Code:
       0: aload_0
       1: invokevirtual #20                 // Method run:()Ljava/lang/String;
       4: areturn

  static {};
    Code:
       0: ldc_w         #6                  // class org/apache/cxf/common/util/SystemPropertyAction
       3: invokestatic  #21                 // Method org/apache/cxf/common/logging/LogUtils.getL7dLogger:(Ljava/lang/Class;)Ljava/util/logging/Logger;
       6: putstatic     #12                 // Field LOG:Ljava/util/logging/Logger;
       9: return
}
