Compiled from "URIParserUtil.java"
public final class org.apache.cxf.common.util.URIParserUtil {
  private static final java.lang.String EXCLUDED_CHARS;

  private static final java.lang.String HEX_DIGITS;

  private org.apache.cxf.common.util.URIParserUtil();
    Code:
       0: aload_0
       1: invokespecial #1                  // Method java/lang/Object."<init>":()V
       4: return

  private static boolean isExcluded(char);
    Code:
       0: iload_0
       1: bipush        32
       3: if_icmple     22
       6: iload_0
       7: bipush        127
       9: if_icmpge     22
      12: ldc           #2                  // String <>\"{}|\\^`
      14: iload_0
      15: invokevirtual #3                  // Method java/lang/String.indexOf:(I)I
      18: iconst_m1
      19: if_icmpeq     26
      22: iconst_1
      23: goto          27
      26: iconst_0
      27: ireturn

  public static java.net.URL[] pathToURLs(java.lang.String);
    Code:
       0: new           #4                  // class java/util/StringTokenizer
       3: dup
       4: aload_0
       5: getstatic     #5                  // Field java/io/File.pathSeparator:Ljava/lang/String;
       8: invokespecial #6                  // Method java/util/StringTokenizer."<init>":(Ljava/lang/String;Ljava/lang/String;)V
      11: astore_1
      12: aload_1
      13: invokevirtual #7                  // Method java/util/StringTokenizer.countTokens:()I
      16: anewarray     #8                  // class java/net/URL
      19: astore_2
      20: iconst_0
      21: istore_3
      22: aload_1
      23: invokevirtual #9                  // Method java/util/StringTokenizer.hasMoreTokens:()Z
      26: ifeq          81
      29: new           #10                 // class java/io/File
      32: dup
      33: aload_1
      34: invokevirtual #11                 // Method java/util/StringTokenizer.nextToken:()Ljava/lang/String;
      37: invokespecial #12                 // Method java/io/File."<init>":(Ljava/lang/String;)V
      40: astore        4
      42: aconst_null
      43: astore        5
      45: aload         4
      47: invokevirtual #13                 // Method java/io/File.toURI:()Ljava/net/URI;
      50: invokevirtual #14                 // Method java/net/URI.toURL:()Ljava/net/URL;
      53: astore        5
      55: goto          65
      58: astore        6
      60: aload         6
      62: invokevirtual #16                 // Method java/net/MalformedURLException.printStackTrace:()V
      65: aload         5
      67: ifnull        78
      70: aload_2
      71: iload_3
      72: iinc          3, 1
      75: aload         5
      77: aastore
      78: goto          22
      81: aload_2
      82: arraylength
      83: iload_3
      84: if_icmpeq     105
      87: iload_3
      88: anewarray     #8                  // class java/net/URL
      91: astore        4
      93: aload_2
      94: iconst_0
      95: aload         4
      97: iconst_0
      98: iload_3
      99: invokestatic  #17                 // Method java/lang/System.arraycopy:(Ljava/lang/Object;ILjava/lang/Object;II)V
     102: aload         4
     104: astore_2
     105: aload_2
     106: areturn
    Exception table:
       from    to  target type
          45    55    58   Class java/net/MalformedURLException

  public static java.lang.String parsePackageName(java.lang.String, java.lang.String);
    Code:
       0: aload_1
       1: ifnull        18
       4: aload_1
       5: invokevirtual #18                 // Method java/lang/String.trim:()Ljava/lang/String;
       8: invokevirtual #19                 // Method java/lang/String.length:()I
      11: ifle          18
      14: aload_1
      15: goto          19
      18: aconst_null
      19: astore_2
      20: aload_2
      21: ifnonnull     29
      24: aload_0
      25: invokestatic  #20                 // Method getPackageName:(Ljava/lang/String;)Ljava/lang/String;
      28: astore_2
      29: aload_2
      30: areturn

  public static java.lang.String getPackageName(java.lang.String);
    Code:
       0: aload_0
       1: bipush        58
       3: invokevirtual #3                  // Method java/lang/String.indexOf:(I)I
       6: istore_1
       7: ldc           #21                 // String
       9: astore_2
      10: iload_1
      11: iflt          47
      14: aload_0
      15: iconst_0
      16: iload_1
      17: invokevirtual #22                 // Method java/lang/String.substring:(II)Ljava/lang/String;
      20: astore_2
      21: ldc           #23                 // String http
      23: aload_2
      24: invokevirtual #24                 // Method java/lang/String.equalsIgnoreCase:(Ljava/lang/String;)Z
      27: ifne          39
      30: ldc           #25                 // String urn
      32: aload_2
      33: invokevirtual #24                 // Method java/lang/String.equalsIgnoreCase:(Ljava/lang/String;)Z
      36: ifeq          47
      39: aload_0
      40: iload_1
      41: iconst_1
      42: iadd
      43: invokevirtual #26                 // Method java/lang/String.substring:(I)Ljava/lang/String;
      46: astore_0
      47: aload_0
      48: ldc           #27                 // String /:
      50: invokestatic  #28                 // Method tokenize:(Ljava/lang/String;Ljava/lang/String;)Ljava/util/List;
      53: astore_3
      54: aload_3
      55: invokeinterface #29,  1           // InterfaceMethod java/util/List.size:()I
      60: ifne          66
      63: ldc           #30                 // String cxf
      65: areturn
      66: aload_3
      67: invokeinterface #29,  1           // InterfaceMethod java/util/List.size:()I
      72: iconst_1
      73: if_icmple     135
      76: aload_3
      77: aload_3
      78: invokeinterface #29,  1           // InterfaceMethod java/util/List.size:()I
      83: iconst_1
      84: isub
      85: invokeinterface #31,  2           // InterfaceMethod java/util/List.get:(I)Ljava/lang/Object;
      90: checkcast     #32                 // class java/lang/String
      93: astore        4
      95: aload         4
      97: bipush        46
      99: invokevirtual #33                 // Method java/lang/String.lastIndexOf:(I)I
     102: istore_1
     103: iload_1
     104: ifle          135
     107: aload         4
     109: bipush        46
     111: bipush        95
     113: invokevirtual #34                 // Method java/lang/String.replace:(CC)Ljava/lang/String;
     116: astore        4
     118: aload_3
     119: aload_3
     120: invokeinterface #29,  1           // InterfaceMethod java/util/List.size:()I
     125: iconst_1
     126: isub
     127: aload         4
     129: invokeinterface #35,  3           // InterfaceMethod java/util/List.set:(ILjava/lang/Object;)Ljava/lang/Object;
     134: pop
     135: aload_3
     136: iconst_0
     137: invokeinterface #31,  2           // InterfaceMethod java/util/List.get:(I)Ljava/lang/Object;
     142: checkcast     #32                 // class java/lang/String
     145: astore        4
     147: aload         4
     149: bipush        58
     151: invokevirtual #3                  // Method java/lang/String.indexOf:(I)I
     154: istore_1
     155: iload_1
     156: iflt          168
     159: aload         4
     161: iconst_0
     162: iload_1
     163: invokevirtual #22                 // Method java/lang/String.substring:(II)Ljava/lang/String;
     166: astore        4
     168: aload         4
     170: ldc           #25                 // String urn
     172: aload_2
     173: invokevirtual #36                 // Method java/lang/String.equals:(Ljava/lang/Object;)Z
     176: ifeq          184
     179: ldc           #37                 // String .-
     181: goto          186
     184: ldc           #38                 // String .
     186: invokestatic  #28                 // Method tokenize:(Ljava/lang/String;Ljava/lang/String;)Ljava/util/List;
     189: invokestatic  #39                 // Method reverse:(Ljava/util/List;)Ljava/util/List;
     192: astore        5
     194: ldc           #40                 // String www
     196: aload         5
     198: aload         5
     200: invokeinterface #29,  1           // InterfaceMethod java/util/List.size:()I
     205: iconst_1
     206: isub
     207: invokeinterface #31,  2           // InterfaceMethod java/util/List.get:(I)Ljava/lang/Object;
     212: checkcast     #32                 // class java/lang/String
     215: invokevirtual #24                 // Method java/lang/String.equalsIgnoreCase:(Ljava/lang/String;)Z
     218: ifeq          238
     221: aload         5
     223: aload         5
     225: invokeinterface #29,  1           // InterfaceMethod java/util/List.size:()I
     230: iconst_1
     231: isub
     232: invokeinterface #41,  2           // InterfaceMethod java/util/List.remove:(I)Ljava/lang/Object;
     237: pop
     238: aload_3
     239: iconst_1
     240: aload         5
     242: invokeinterface #42,  3           // InterfaceMethod java/util/List.addAll:(ILjava/util/Collection;)Z
     247: pop
     248: aload_3
     249: iconst_0
     250: invokeinterface #41,  2           // InterfaceMethod java/util/List.remove:(I)Ljava/lang/Object;
     255: pop
     256: iconst_0
     257: istore        6
     259: iload         6
     261: aload_3
     262: invokeinterface #29,  1           // InterfaceMethod java/util/List.size:()I
     267: if_icmpge     340
     270: aload_3
     271: iload         6
     273: invokeinterface #31,  2           // InterfaceMethod java/util/List.get:(I)Ljava/lang/Object;
     278: checkcast     #32                 // class java/lang/String
     281: astore        7
     283: aload         7
     285: invokestatic  #43                 // Method removeIllegalIdentifierChars:(Ljava/lang/String;)Ljava/lang/String;
     288: astore        7
     290: aload         7
     292: invokestatic  #44                 // Method containsReservedKeywords:(Ljava/lang/String;)Z
     295: ifeq          320
     298: new           #45                 // class java/lang/StringBuilder
     301: dup
     302: invokespecial #46                 // Method java/lang/StringBuilder."<init>":()V
     305: bipush        95
     307: invokevirtual #47                 // Method java/lang/StringBuilder.append:(C)Ljava/lang/StringBuilder;
     310: aload         7
     312: invokevirtual #48                 // Method java/lang/StringBuilder.append:(Ljava/lang/String;)Ljava/lang/StringBuilder;
     315: invokevirtual #49                 // Method java/lang/StringBuilder.toString:()Ljava/lang/String;
     318: astore        7
     320: aload_3
     321: iload         6
     323: aload         7
     325: invokevirtual #50                 // Method java/lang/String.toLowerCase:()Ljava/lang/String;
     328: invokeinterface #35,  3           // InterfaceMethod java/util/List.set:(ILjava/lang/Object;)Ljava/lang/Object;
     333: pop
     334: iinc          6, 1
     337: goto          259
     340: aload_3
     341: bipush        46
     343: invokestatic  #51                 // Method combine:(Ljava/util/List;C)Ljava/lang/String;
     346: areturn

  public static java.lang.String getNamespace(java.lang.String);
    Code:
       0: aload_0
       1: ifnull        11
       4: aload_0
       5: invokevirtual #19                 // Method java/lang/String.length:()I
       8: ifne          13
      11: aconst_null
      12: areturn
      13: new           #4                  // class java/util/StringTokenizer
      16: dup
      17: aload_0
      18: ldc           #38                 // String .
      20: invokespecial #6                  // Method java/util/StringTokenizer."<init>":(Ljava/lang/String;Ljava/lang/String;)V
      23: astore_1
      24: aload_1
      25: invokevirtual #7                  // Method java/util/StringTokenizer.countTokens:()I
      28: ifne          39
      31: iconst_0
      32: anewarray     #32                 // class java/lang/String
      35: astore_2
      36: goto          71
      39: aload_1
      40: invokevirtual #7                  // Method java/util/StringTokenizer.countTokens:()I
      43: anewarray     #32                 // class java/lang/String
      46: astore_2
      47: aload_1
      48: invokevirtual #7                  // Method java/util/StringTokenizer.countTokens:()I
      51: iconst_1
      52: isub
      53: istore_3
      54: iload_3
      55: iflt          71
      58: aload_2
      59: iload_3
      60: aload_1
      61: invokevirtual #11                 // Method java/util/StringTokenizer.nextToken:()Ljava/lang/String;
      64: aastore
      65: iinc          3, -1
      68: goto          54
      71: new           #45                 // class java/lang/StringBuilder
      74: dup
      75: ldc           #52                 // String http://
      77: invokespecial #53                 // Method java/lang/StringBuilder."<init>":(Ljava/lang/String;)V
      80: astore_3
      81: ldc           #21                 // String
      83: astore        4
      85: iconst_0
      86: istore        5
      88: iload         5
      90: aload_2
      91: arraylength
      92: if_icmpge     138
      95: iload         5
      97: iconst_1
      98: if_icmpne     105
     101: ldc           #38                 // String .
     103: astore        4
     105: aload_3
     106: new           #45                 // class java/lang/StringBuilder
     109: dup
     110: invokespecial #46                 // Method java/lang/StringBuilder."<init>":()V
     113: aload         4
     115: invokevirtual #48                 // Method java/lang/StringBuilder.append:(Ljava/lang/String;)Ljava/lang/StringBuilder;
     118: aload_2
     119: iload         5
     121: aaload
     122: invokevirtual #48                 // Method java/lang/StringBuilder.append:(Ljava/lang/String;)Ljava/lang/StringBuilder;
     125: invokevirtual #49                 // Method java/lang/StringBuilder.toString:()Ljava/lang/String;
     128: invokevirtual #48                 // Method java/lang/StringBuilder.append:(Ljava/lang/String;)Ljava/lang/StringBuilder;
     131: pop
     132: iinc          5, 1
     135: goto          88
     138: aload_3
     139: bipush        47
     141: invokevirtual #47                 // Method java/lang/StringBuilder.append:(C)Ljava/lang/StringBuilder;
     144: pop
     145: aload_3
     146: invokevirtual #49                 // Method java/lang/StringBuilder.toString:()Ljava/lang/String;
     149: areturn

  private static java.util.List<java.lang.String> tokenize(java.lang.String, java.lang.String);
    Code:
       0: new           #4                  // class java/util/StringTokenizer
       3: dup
       4: aload_0
       5: aload_1
       6: invokespecial #6                  // Method java/util/StringTokenizer."<init>":(Ljava/lang/String;Ljava/lang/String;)V
       9: astore_2
      10: new           #54                 // class java/util/ArrayList
      13: dup
      14: invokespecial #55                 // Method java/util/ArrayList."<init>":()V
      17: astore_3
      18: aload_2
      19: invokevirtual #9                  // Method java/util/StringTokenizer.hasMoreTokens:()Z
      22: ifeq          39
      25: aload_3
      26: aload_2
      27: invokevirtual #11                 // Method java/util/StringTokenizer.nextToken:()Ljava/lang/String;
      30: invokeinterface #56,  2           // InterfaceMethod java/util/List.add:(Ljava/lang/Object;)Z
      35: pop
      36: goto          18
      39: aload_3
      40: areturn

  private static java.lang.String removeIllegalIdentifierChars(java.lang.String);
    Code:
       0: new           #45                 // class java/lang/StringBuilder
       3: dup
       4: invokespecial #46                 // Method java/lang/StringBuilder."<init>":()V
       7: astore_1
       8: iconst_0
       9: istore_2
      10: iload_2
      11: aload_0
      12: invokevirtual #19                 // Method java/lang/String.length:()I
      15: if_icmpge     91
      18: aload_0
      19: iload_2
      20: invokevirtual #57                 // Method java/lang/String.charAt:(I)C
      23: istore_3
      24: iload_2
      25: ifne          62
      28: iload_3
      29: invokestatic  #58                 // Method java/lang/Character.isJavaIdentifierStart:(C)Z
      32: ifne          62
      35: aload_1
      36: new           #45                 // class java/lang/StringBuilder
      39: dup
      40: invokespecial #46                 // Method java/lang/StringBuilder."<init>":()V
      43: ldc           #59                 // String _
      45: invokevirtual #48                 // Method java/lang/StringBuilder.append:(Ljava/lang/String;)Ljava/lang/StringBuilder;
      48: iload_3
      49: invokevirtual #47                 // Method java/lang/StringBuilder.append:(C)Ljava/lang/StringBuilder;
      52: invokevirtual #49                 // Method java/lang/StringBuilder.toString:()Ljava/lang/String;
      55: invokevirtual #48                 // Method java/lang/StringBuilder.append:(Ljava/lang/String;)Ljava/lang/StringBuilder;
      58: pop
      59: goto          85
      62: iload_3
      63: invokestatic  #60                 // Method java/lang/Character.isJavaIdentifierPart:(C)Z
      66: ifne          79
      69: aload_1
      70: bipush        95
      72: invokevirtual #47                 // Method java/lang/StringBuilder.append:(C)Ljava/lang/StringBuilder;
      75: pop
      76: goto          85
      79: aload_1
      80: iload_3
      81: invokevirtual #47                 // Method java/lang/StringBuilder.append:(C)Ljava/lang/StringBuilder;
      84: pop
      85: iinc          2, 1
      88: goto          10
      91: aload_1
      92: invokevirtual #49                 // Method java/lang/StringBuilder.toString:()Ljava/lang/String;
      95: areturn

  private static java.lang.String combine(java.util.List<java.lang.String>, char);
    Code:
       0: new           #45                 // class java/lang/StringBuilder
       3: dup
       4: aload_0
       5: iconst_0
       6: invokeinterface #31,  2           // InterfaceMethod java/util/List.get:(I)Ljava/lang/Object;
      11: checkcast     #32                 // class java/lang/String
      14: invokespecial #53                 // Method java/lang/StringBuilder."<init>":(Ljava/lang/String;)V
      17: astore_2
      18: iconst_1
      19: istore_3
      20: iload_3
      21: aload_0
      22: invokeinterface #29,  1           // InterfaceMethod java/util/List.size:()I
      27: if_icmpge     57
      30: aload_2
      31: iload_1
      32: invokevirtual #47                 // Method java/lang/StringBuilder.append:(C)Ljava/lang/StringBuilder;
      35: pop
      36: aload_2
      37: aload_0
      38: iload_3
      39: invokeinterface #31,  2           // InterfaceMethod java/util/List.get:(I)Ljava/lang/Object;
      44: checkcast     #32                 // class java/lang/String
      47: invokevirtual #48                 // Method java/lang/StringBuilder.append:(Ljava/lang/String;)Ljava/lang/StringBuilder;
      50: pop
      51: iinc          3, 1
      54: goto          20
      57: aload_2
      58: invokevirtual #49                 // Method java/lang/StringBuilder.toString:()Ljava/lang/String;
      61: areturn

  private static <T> java.util.List<T> reverse(java.util.List<T>);
    Code:
       0: new           #54                 // class java/util/ArrayList
       3: dup
       4: invokespecial #55                 // Method java/util/ArrayList."<init>":()V
       7: astore_1
       8: aload_0
       9: invokeinterface #29,  1           // InterfaceMethod java/util/List.size:()I
      14: iconst_1
      15: isub
      16: istore_2
      17: iload_2
      18: iflt          41
      21: aload_1
      22: aload_0
      23: iload_2
      24: invokeinterface #31,  2           // InterfaceMethod java/util/List.get:(I)Ljava/lang/Object;
      29: invokeinterface #56,  2           // InterfaceMethod java/util/List.add:(Ljava/lang/Object;)Z
      34: pop
      35: iinc          2, -1
      38: goto          17
      41: aload_1
      42: areturn

  public static boolean containsReservedKeywords(java.lang.String);
    Code:
       0: aload_0
       1: invokestatic  #61                 // Method org/apache/cxf/helpers/JavaUtils.isJavaKeyword:(Ljava/lang/String;)Z
       4: ireturn

  public static java.lang.String escapeChars(java.lang.String);
    Code:
       0: new           #45                 // class java/lang/StringBuilder
       3: dup
       4: aload_0
       5: invokevirtual #19                 // Method java/lang/String.length:()I
       8: invokespecial #62                 // Method java/lang/StringBuilder."<init>":(I)V
      11: astore_1
      12: iconst_0
      13: istore_2
      14: iload_2
      15: aload_0
      16: invokevirtual #19                 // Method java/lang/String.length:()I
      19: if_icmpge     129
      22: aload_0
      23: iload_2
      24: invokevirtual #57                 // Method java/lang/String.charAt:(I)C
      27: istore_3
      28: iload_3
      29: invokestatic  #63                 // Method isExcluded:(C)Z
      32: ifeq          117
      35: iload_3
      36: invokestatic  #64                 // Method java/lang/Character.toString:(C)Ljava/lang/String;
      39: ldc           #65                 // String UTF-8
      41: invokevirtual #66                 // Method java/lang/String.getBytes:(Ljava/lang/String;)[B
      44: astore        4
      46: iconst_0
      47: istore        5
      49: iload         5
      51: aload         4
      53: arraylength
      54: if_icmpge     109
      57: aload_1
      58: ldc           #67                 // String %
      60: invokevirtual #48                 // Method java/lang/StringBuilder.append:(Ljava/lang/String;)Ljava/lang/StringBuilder;
      63: pop
      64: aload_1
      65: ldc           #68                 // String 0123456789abcdef
      67: aload         4
      69: iload         5
      71: baload
      72: sipush        255
      75: iand
      76: iconst_4
      77: ishr
      78: invokevirtual #57                 // Method java/lang/String.charAt:(I)C
      81: invokevirtual #47                 // Method java/lang/StringBuilder.append:(C)Ljava/lang/StringBuilder;
      84: pop
      85: aload_1
      86: ldc           #68                 // String 0123456789abcdef
      88: aload         4
      90: iload         5
      92: baload
      93: bipush        15
      95: iand
      96: invokevirtual #57                 // Method java/lang/String.charAt:(I)C
      99: invokevirtual #47                 // Method java/lang/StringBuilder.append:(C)Ljava/lang/StringBuilder;
     102: pop
     103: iinc          5, 1
     106: goto          49
     109: goto          123
     112: astore        4
     114: goto          123
     117: aload_1
     118: iload_3
     119: invokevirtual #47                 // Method java/lang/StringBuilder.append:(C)Ljava/lang/StringBuilder;
     122: pop
     123: iinc          2, 1
     126: goto          14
     129: aload_1
     130: invokevirtual #49                 // Method java/lang/StringBuilder.toString:()Ljava/lang/String;
     133: areturn
    Exception table:
       from    to  target type
          35   109   112   Class java/io/UnsupportedEncodingException

  public static java.lang.String normalize(java.lang.String);
    Code:
       0: aconst_null
       1: astore_1
       2: aconst_null
       3: astore_2
       4: new           #8                  // class java/net/URL
       7: dup
       8: aload_0
       9: invokespecial #70                 // Method java/net/URL."<init>":(Ljava/lang/String;)V
      12: astore_1
      13: aload_1
      14: invokevirtual #71                 // Method java/net/URL.toURI:()Ljava/net/URI;
      17: invokevirtual #72                 // Method java/net/URI.normalize:()Ljava/net/URI;
      20: invokevirtual #73                 // Method java/net/URI.toString:()Ljava/lang/String;
      23: ldc           #74                 // String \\
      25: ldc           #75                 // String /
      27: invokevirtual #76                 // Method java/lang/String.replace:(Ljava/lang/CharSequence;Ljava/lang/CharSequence;)Ljava/lang/String;
      30: invokestatic  #77                 // Method escapeChars:(Ljava/lang/String;)Ljava/lang/String;
      33: astore_2
      34: goto          225
      37: astore_3
      38: aload_0
      39: ldc           #78                 // String classpath:
      41: invokevirtual #79                 // Method java/lang/String.startsWith:(Ljava/lang/String;)Z
      44: ifeq          73
      47: aload_0
      48: bipush        10
      50: invokevirtual #26                 // Method java/lang/String.substring:(I)Ljava/lang/String;
      53: ldc_w         #80                 // class org/apache/cxf/common/util/URIParserUtil
      56: invokestatic  #81                 // Method org/apache/cxf/common/classloader/ClassLoaderUtils.getResource:(Ljava/lang/String;Ljava/lang/Class;)Ljava/net/URL;
      59: astore_1
      60: aload_1
      61: ifnull        71
      64: aload_1
      65: invokevirtual #82                 // Method java/net/URL.toExternalForm:()Ljava/lang/String;
      68: goto          72
      71: aload_0
      72: areturn
      73: new           #10                 // class java/io/File
      76: dup
      77: aload_0
      78: invokespecial #12                 // Method java/io/File."<init>":(Ljava/lang/String;)V
      81: astore        4
      83: aload         4
      85: invokevirtual #83                 // Method java/io/File.exists:()Z
      88: ifeq          103
      91: aload         4
      93: invokevirtual #13                 // Method java/io/File.toURI:()Ljava/net/URI;
      96: invokevirtual #72                 // Method java/net/URI.normalize:()Ljava/net/URI;
      99: invokevirtual #73                 // Method java/net/URI.toString:()Ljava/lang/String;
     102: areturn
     103: aconst_null
     104: astore        5
     106: aload_0
     107: ldc           #84                 // String :
     109: invokevirtual #85                 // Method java/lang/String.indexOf:(Ljava/lang/String;)I
     112: iconst_m1
     113: if_icmpeq     149
     116: aload_0
     117: ldc           #75                 // String /
     119: invokevirtual #79                 // Method java/lang/String.startsWith:(Ljava/lang/String;)Z
     122: ifne          149
     125: new           #45                 // class java/lang/StringBuilder
     128: dup
     129: invokespecial #46                 // Method java/lang/StringBuilder."<init>":()V
     132: ldc           #86                 // String file:/
     134: invokevirtual #48                 // Method java/lang/StringBuilder.append:(Ljava/lang/String;)Ljava/lang/StringBuilder;
     137: aload_0
     138: invokevirtual #48                 // Method java/lang/StringBuilder.append:(Ljava/lang/String;)Ljava/lang/StringBuilder;
     141: invokevirtual #49                 // Method java/lang/StringBuilder.toString:()Ljava/lang/String;
     144: astore        5
     146: goto          170
     149: new           #45                 // class java/lang/StringBuilder
     152: dup
     153: invokespecial #46                 // Method java/lang/StringBuilder."<init>":()V
     156: ldc           #87                 // String file:
     158: invokevirtual #48                 // Method java/lang/StringBuilder.append:(Ljava/lang/String;)Ljava/lang/StringBuilder;
     161: aload_0
     162: invokevirtual #48                 // Method java/lang/StringBuilder.append:(Ljava/lang/String;)Ljava/lang/StringBuilder;
     165: invokevirtual #49                 // Method java/lang/StringBuilder.toString:()Ljava/lang/String;
     168: astore        5
     170: new           #8                  // class java/net/URL
     173: dup
     174: aload         5
     176: invokespecial #70                 // Method java/net/URL."<init>":(Ljava/lang/String;)V
     179: astore_1
     180: aload_1
     181: invokevirtual #88                 // Method java/net/URL.toString:()Ljava/lang/String;
     184: ldc           #74                 // String \\
     186: ldc           #75                 // String /
     188: invokevirtual #76                 // Method java/lang/String.replace:(Ljava/lang/CharSequence;Ljava/lang/CharSequence;)Ljava/lang/String;
     191: invokestatic  #77                 // Method escapeChars:(Ljava/lang/String;)Ljava/lang/String;
     194: areturn
     195: astore        4
     197: aload_0
     198: ldc           #74                 // String \\
     200: ldc           #75                 // String /
     202: invokevirtual #76                 // Method java/lang/String.replace:(Ljava/lang/CharSequence;Ljava/lang/CharSequence;)Ljava/lang/String;
     205: invokestatic  #77                 // Method escapeChars:(Ljava/lang/String;)Ljava/lang/String;
     208: areturn
     209: astore_3
     210: aload_1
     211: invokevirtual #88                 // Method java/net/URL.toString:()Ljava/lang/String;
     214: ldc           #74                 // String \\
     216: ldc           #75                 // String /
     218: invokevirtual #76                 // Method java/lang/String.replace:(Ljava/lang/CharSequence;Ljava/lang/CharSequence;)Ljava/lang/String;
     221: invokestatic  #77                 // Method escapeChars:(Ljava/lang/String;)Ljava/lang/String;
     224: astore_2
     225: aload_2
     226: areturn
    Exception table:
       from    to  target type
           4    34    37   Class java/net/MalformedURLException
          38    72   195   Class java/lang/Exception
          73   102   195   Class java/lang/Exception
         103   194   195   Class java/lang/Exception
           4    34   209   Class java/net/URISyntaxException

  public static java.lang.String getAbsoluteURI(java.lang.String);
    Code:
       0: aload_0
       1: ifnonnull     6
       4: aconst_null
       5: areturn
       6: new           #91                 // class java/net/URI
       9: dup
      10: aload_0
      11: invokespecial #92                 // Method java/net/URI."<init>":(Ljava/lang/String;)V
      14: astore_1
      15: ldc           #93                 // String file
      17: aload_1
      18: invokevirtual #94                 // Method java/net/URI.getScheme:()Ljava/lang/String;
      21: invokevirtual #24                 // Method java/lang/String.equalsIgnoreCase:(Ljava/lang/String;)Z
      24: ifeq          65
      27: aload_1
      28: invokevirtual #95                 // Method java/net/URI.isOpaque:()Z
      31: ifne          42
      34: aload_1
      35: invokevirtual #72                 // Method java/net/URI.normalize:()Ljava/net/URI;
      38: invokevirtual #73                 // Method java/net/URI.toString:()Ljava/lang/String;
      41: areturn
      42: new           #10                 // class java/io/File
      45: dup
      46: ldc           #21                 // String
      48: invokespecial #12                 // Method java/io/File."<init>":(Ljava/lang/String;)V
      51: invokevirtual #13                 // Method java/io/File.toURI:()Ljava/net/URI;
      54: aload_1
      55: invokevirtual #96                 // Method java/net/URI.getPath:()Ljava/lang/String;
      58: invokevirtual #97                 // Method java/net/URI.resolve:(Ljava/lang/String;)Ljava/net/URI;
      61: invokevirtual #73                 // Method java/net/URI.toString:()Ljava/lang/String;
      64: areturn
      65: aload_0
      66: invokestatic  #98                 // Method normalize:(Ljava/lang/String;)Ljava/lang/String;
      69: areturn
      70: astore_1
      71: aload_0
      72: invokestatic  #98                 // Method normalize:(Ljava/lang/String;)Ljava/lang/String;
      75: areturn
    Exception table:
       from    to  target type
           6    41    70   Class java/lang/Exception
          42    64    70   Class java/lang/Exception
          65    69    70   Class java/lang/Exception

  public static java.lang.String relativize(java.lang.String, java.lang.String) throws java.net.URISyntaxException;
    Code:
       0: aload_0
       1: ifnull        8
       4: aload_1
       5: ifnonnull     10
       8: aconst_null
       9: areturn
      10: new           #91                 // class java/net/URI
      13: dup
      14: aload_0
      15: invokespecial #92                 // Method java/net/URI."<init>":(Ljava/lang/String;)V
      18: new           #91                 // class java/net/URI
      21: dup
      22: aload_1
      23: invokespecial #92                 // Method java/net/URI."<init>":(Ljava/lang/String;)V
      26: invokestatic  #99                 // Method relativize:(Ljava/net/URI;Ljava/net/URI;)Ljava/lang/String;
      29: areturn

  public static java.lang.String relativize(java.net.URI, java.net.URI) throws java.net.URISyntaxException;
    Code:
       0: aload_0
       1: ifnull        8
       4: aload_1
       5: ifnonnull     10
       8: aconst_null
       9: areturn
      10: aload_0
      11: invokevirtual #100                // Method java/net/URI.isAbsolute:()Z
      14: aload_1
      15: invokevirtual #100                // Method java/net/URI.isAbsolute:()Z
      18: ixor
      19: ifeq          24
      22: aconst_null
      23: areturn
      24: aload_0
      25: invokevirtual #101                // Method java/net/URI.getSchemeSpecificPart:()Ljava/lang/String;
      28: astore_2
      29: aload_1
      30: invokevirtual #101                // Method java/net/URI.getSchemeSpecificPart:()Ljava/lang/String;
      33: astore_3
      34: aload_2
      35: invokevirtual #19                 // Method java/lang/String.length:()I
      38: istore        4
      40: aload_3
      41: invokevirtual #19                 // Method java/lang/String.length:()I
      44: istore        5
      46: iload         4
      48: ifne          53
      51: aload_3
      52: areturn
      53: iconst_0
      54: istore        6
      56: new           #45                 // class java/lang/StringBuilder
      59: dup
      60: invokespecial #46                 // Method java/lang/StringBuilder."<init>":()V
      63: astore        7
      65: iconst_0
      66: istore        8
      68: iconst_0
      69: istore        9
      71: iload         9
      73: iload         4
      75: if_icmpge     152
      78: aload_2
      79: iload         9
      81: invokevirtual #57                 // Method java/lang/String.charAt:(I)C
      84: istore        10
      86: iload         9
      88: iload         5
      90: if_icmpge     136
      93: iload         8
      95: ifne          120
      98: iload         10
     100: aload_3
     101: iload         9
     103: invokevirtual #57                 // Method java/lang/String.charAt:(I)C
     106: if_icmpne     120
     109: aload         7
     111: iload         10
     113: invokevirtual #47                 // Method java/lang/StringBuilder.append:(C)Ljava/lang/StringBuilder;
     116: pop
     117: goto          146
     120: iconst_1
     121: istore        8
     123: iload         10
     125: bipush        47
     127: if_icmpne     146
     130: iinc          6, 1
     133: goto          146
     136: iload         10
     138: bipush        47
     140: if_icmpne     146
     143: iinc          6, 1
     146: iinc          9, 1
     149: goto          71
     152: new           #91                 // class java/net/URI
     155: dup
     156: aload         7
     158: invokevirtual #49                 // Method java/lang/StringBuilder.toString:()Ljava/lang/String;
     161: invokestatic  #102                // Method getRoot:(Ljava/lang/String;)Ljava/lang/String;
     164: invokespecial #92                 // Method java/net/URI."<init>":(Ljava/lang/String;)V
     167: new           #91                 // class java/net/URI
     170: dup
     171: aload_3
     172: invokespecial #92                 // Method java/net/URI."<init>":(Ljava/lang/String;)V
     175: invokevirtual #103                // Method java/net/URI.relativize:(Ljava/net/URI;)Ljava/net/URI;
     178: invokevirtual #73                 // Method java/net/URI.toString:()Ljava/lang/String;
     181: astore        9
     183: new           #45                 // class java/lang/StringBuilder
     186: dup
     187: invokespecial #46                 // Method java/lang/StringBuilder."<init>":()V
     190: astore        10
     192: iconst_0
     193: istore        11
     195: iload         11
     197: iload         6
     199: if_icmpge     216
     202: aload         10
     204: ldc           #104                // String ../
     206: invokevirtual #48                 // Method java/lang/StringBuilder.append:(Ljava/lang/String;)Ljava/lang/StringBuilder;
     209: pop
     210: iinc          11, 1
     213: goto          195
     216: aload         10
     218: aload         9
     220: invokevirtual #48                 // Method java/lang/StringBuilder.append:(Ljava/lang/String;)Ljava/lang/StringBuilder;
     223: pop
     224: aload         10
     226: invokevirtual #49                 // Method java/lang/StringBuilder.toString:()Ljava/lang/String;
     229: areturn

  private static java.lang.String getRoot(java.lang.String);
    Code:
       0: aload_0
       1: bipush        47
       3: invokevirtual #33                 // Method java/lang/String.lastIndexOf:(I)I
       6: istore_1
       7: iload_1
       8: aload_0
       9: invokevirtual #19                 // Method java/lang/String.length:()I
      12: iconst_1
      13: isub
      14: if_icmpne     19
      17: aload_0
      18: areturn
      19: iload_1
      20: iconst_m1
      21: if_icmpne     27
      24: ldc           #21                 // String
      26: areturn
      27: aload_0
      28: iconst_0
      29: iload_1
      30: iconst_1
      31: iadd
      32: invokevirtual #22                 // Method java/lang/String.substring:(II)Ljava/lang/String;
      35: areturn
}
