Compiled from "PatchedConsoleReader.groovy"
public class org.codehaus.groovy.tools.shell.PatchedConsoleReader extends jline.console.ConsoleReader implements groovy.lang.GroovyObject {
  private static org.codehaus.groovy.reflection.ClassInfo $staticClassInfo;

  public static transient boolean __$stMC;

  private transient groovy.lang.MetaClass metaClass;

  public org.codehaus.groovy.tools.shell.PatchedConsoleReader(java.io.InputStream, java.io.OutputStream) throws java.io.IOException;
    Code:
       0: aload_0
       1: aload_1
       2: aload_2
       3: invokespecial #19                 // Method jline/console/ConsoleReader."<init>":(Ljava/io/InputStream;Ljava/io/OutputStream;)V
       6: aload_0
       7: invokevirtual #23                 // Method $getStaticMetaClass:()Lgroovy/lang/MetaClass;
      10: astore_3
      11: aload_3
      12: aload_0
      13: swap
      14: putfield      #25                 // Field metaClass:Lgroovy/lang/MetaClass;
      17: aload_3
      18: pop
      19: return

  public void printColumns(java.util.Collection<? extends java.lang.CharSequence>) throws java.io.IOException;
    Code:
       0: aload_1
       1: ifnonnull     8
       4: iconst_1
       5: goto          9
       8: iconst_0
       9: ifne          21
      12: aload_1
      13: invokeinterface #39,  1           // InterfaceMethod java/util/Collection.isEmpty:()Z
      18: ifeq          25
      21: iconst_1
      22: goto          26
      25: iconst_0
      26: ifeq          30
      29: return
      30: aload_0
      31: checkcast     #2                  // class org/codehaus/groovy/tools/shell/PatchedConsoleReader
      34: invokevirtual #43                 // Method getTerminal:()Ljline/Terminal;
      37: invokeinterface #49,  1           // InterfaceMethod jline/Terminal.getWidth:()I
      42: istore_2
      43: iload_2
      44: pop
      45: aload_0
      46: checkcast     #2                  // class org/codehaus/groovy/tools/shell/PatchedConsoleReader
      49: invokevirtual #43                 // Method getTerminal:()Ljline/Terminal;
      52: invokeinterface #52,  1           // InterfaceMethod jline/Terminal.getHeight:()I
      57: istore_3
      58: iload_3
      59: pop
      60: iconst_0
      61: istore        4
      63: iload         4
      65: pop
      66: aconst_null
      67: astore        5
      69: aload_1
      70: invokeinterface #56,  1           // InterfaceMethod java/util/Collection.iterator:()Ljava/util/Iterator;
      75: astore        6
      77: aload         6
      79: invokeinterface #61,  1           // InterfaceMethod java/util/Iterator.hasNext:()Z
      84: ifeq          131
      87: aload         6
      89: invokeinterface #65,  1           // InterfaceMethod java/util/Iterator.next:()Ljava/lang/Object;
      94: ldc           #67                 // class java/lang/CharSequence
      96: invokestatic  #73                 // Method org/codehaus/groovy/runtime/ScriptBytecodeAdapter.castToType:(Ljava/lang/Object;Ljava/lang/Class;)Ljava/lang/Object;
      99: checkcast     #67                 // class java/lang/CharSequence
     102: astore        5
     104: iload         4
     106: aload         5
     108: invokestatic  #79                 // Method org/codehaus/groovy/tools/shell/util/JAnsiHelper.stripAnsi:(Ljava/lang/CharSequence;)Ljava/lang/CharSequence;
     111: invokeinterface #82,  1           // InterfaceMethod java/lang/CharSequence.length:()I
     116: invokestatic  #88                 // Method java/lang/Math.max:(II)I
     119: istore        7
     121: iload         7
     123: istore        4
     125: iload         7
     127: pop
     128: goto          77
     131: iload         4
     133: iconst_3
     134: iadd
     135: istore        8
     137: iload         8
     139: istore        4
     141: iload         8
     143: pop
     144: iconst_2
     145: anewarray     #90                 // class java/lang/Object
     148: dup
     149: iconst_0
     150: ldc           #92                 // String Max width:
     152: aastore
     153: dup
     154: iconst_1
     155: iload         4
     157: invokestatic  #98                 // Method java/lang/Integer.valueOf:(I)Ljava/lang/Integer;
     160: aastore
     161: invokestatic  #104                // Method jline/internal/Log.debug:([Ljava/lang/Object;)V
     164: aconst_null
     165: pop
     166: ldc           #105                // int 0
     168: istore        9
     170: iload         9
     172: pop
     173: aload_0
     174: checkcast     #2                  // class org/codehaus/groovy/tools/shell/PatchedConsoleReader
     177: invokevirtual #108                // Method isPaginationEnabled:()Z
     180: ifeq          198
     183: iload_3
     184: iconst_1
     185: isub
     186: istore        10
     188: iload         10
     190: istore        9
     192: iload         10
     194: pop
     195: goto          210
     198: getstatic     #112                // Field java/lang/Integer.MAX_VALUE:I
     201: istore        11
     203: iload         11
     205: istore        9
     207: iload         11
     209: pop
     210: new           #114                // class java/lang/StringBuilder
     213: dup
     214: invokespecial #117                // Method java/lang/StringBuilder."<init>":()V
     217: astore        12
     219: aload         12
     221: pop
     222: iconst_0
     223: istore        13
     225: iload         13
     227: pop
     228: aconst_null
     229: astore        14
     231: aload_1
     232: invokeinterface #56,  1           // InterfaceMethod java/util/Collection.iterator:()Ljava/util/Iterator;
     237: astore        15
     239: aload         15
     241: invokeinterface #61,  1           // InterfaceMethod java/util/Iterator.hasNext:()Z
     246: ifeq          602
     249: aload         15
     251: invokeinterface #65,  1           // InterfaceMethod java/util/Iterator.next:()Ljava/lang/Object;
     256: ldc           #67                 // class java/lang/CharSequence
     258: invokestatic  #73                 // Method org/codehaus/groovy/runtime/ScriptBytecodeAdapter.castToType:(Ljava/lang/Object;Ljava/lang/Class;)Ljava/lang/Object;
     261: checkcast     #67                 // class java/lang/CharSequence
     264: astore        14
     266: iload         13
     268: iload         4
     270: iadd
     271: iload_2
     272: if_icmple     279
     275: iconst_1
     276: goto          280
     279: iconst_0
     280: ifeq          501
     283: aload_0
     284: checkcast     #2                  // class org/codehaus/groovy/tools/shell/PatchedConsoleReader
     287: aload         12
     289: invokevirtual #121                // Method println:(Ljava/lang/CharSequence;)V
     292: aconst_null
     293: pop
     294: aload         12
     296: iconst_0
     297: invokevirtual #125                // Method java/lang/StringBuilder.setLength:(I)V
     300: aconst_null
     301: pop
     302: iconst_0
     303: istore        16
     305: iload         16
     307: istore        13
     309: iload         16
     311: pop
     312: iload         9
     314: iconst_1
     315: isub
     316: dup
     317: istore        9
     319: iconst_0
     320: if_icmpne     327
     323: iconst_1
     324: goto          328
     327: iconst_0
     328: ifeq          501
     331: aload_0
     332: checkcast     #2                  // class org/codehaus/groovy/tools/shell/PatchedConsoleReader
     335: aload_0
     336: ldc           #127                // String resources
     338: invokeinterface #131,  2          // InterfaceMethod groovy/lang/GroovyObject.getProperty:(Ljava/lang/String;)Ljava/lang/Object;
     343: checkcast     #133                // class java/util/ResourceBundle
     346: ldc           #135                // String DISPLAY_MORE
     348: invokevirtual #139                // Method java/util/ResourceBundle.getString:(Ljava/lang/String;)Ljava/lang/String;
     351: invokevirtual #142                // Method print:(Ljava/lang/CharSequence;)V
     354: aconst_null
     355: pop
     356: aload_0
     357: checkcast     #2                  // class org/codehaus/groovy/tools/shell/PatchedConsoleReader
     360: invokevirtual #145                // Method flush:()V
     363: aconst_null
     364: pop
     365: aload_0
     366: checkcast     #2                  // class org/codehaus/groovy/tools/shell/PatchedConsoleReader
     369: invokevirtual #148                // Method readCharacter:()I
     372: istore        17
     374: iload         17
     376: pop
     377: iload         17
     379: bipush        13
     381: if_icmpne     388
     384: iconst_1
     385: goto          389
     388: iconst_0
     389: ifne          407
     392: iload         17
     394: bipush        10
     396: if_icmpne     403
     399: iconst_1
     400: goto          404
     403: iconst_0
     404: ifeq          411
     407: iconst_1
     408: goto          412
     411: iconst_0
     412: ifeq          428
     415: iconst_1
     416: istore        18
     418: iload         18
     420: istore        9
     422: iload         18
     424: pop
     425: goto          455
     428: iload         17
     430: bipush        113
     432: if_icmpeq     439
     435: iconst_1
     436: goto          440
     439: iconst_0
     440: ifeq          455
     443: iload_3
     444: iconst_1
     445: isub
     446: istore        19
     448: iload         19
     450: istore        9
     452: iload         19
     454: pop
     455: aload_0
     456: checkcast     #2                  // class org/codehaus/groovy/tools/shell/PatchedConsoleReader
     459: aload_0
     460: ldc           #127                // String resources
     462: invokeinterface #131,  2          // InterfaceMethod groovy/lang/GroovyObject.getProperty:(Ljava/lang/String;)Ljava/lang/Object;
     467: checkcast     #133                // class java/util/ResourceBundle
     470: ldc           #135                // String DISPLAY_MORE
     472: invokevirtual #139                // Method java/util/ResourceBundle.getString:(Ljava/lang/String;)Ljava/lang/String;
     475: invokevirtual #151                // Method java/lang/String.length:()I
     478: invokevirtual #154                // Method back:(I)V
     481: aconst_null
     482: pop
     483: iload         17
     485: bipush        113
     487: if_icmpne     494
     490: iconst_1
     491: goto          495
     494: iconst_0
     495: ifeq          501
     498: goto          602
     501: aload         12
     503: aload         14
     505: invokeinterface #158,  1          // InterfaceMethod java/lang/CharSequence.toString:()Ljava/lang/String;
     510: invokevirtual #162                // Method java/lang/StringBuilder.append:(Ljava/lang/String;)Ljava/lang/StringBuilder;
     513: pop
     514: aload         14
     516: invokestatic  #79                 // Method org/codehaus/groovy/tools/shell/util/JAnsiHelper.stripAnsi:(Ljava/lang/CharSequence;)Ljava/lang/CharSequence;
     519: invokeinterface #82,  1           // InterfaceMethod java/lang/CharSequence.length:()I
     524: istore        20
     526: iload         20
     528: pop
     529: iload         13
     531: iload         20
     533: iadd
     534: dup
     535: istore        13
     537: pop
     538: iconst_0
     539: istore        21
     541: iload         21
     543: pop
     544: iload         21
     546: iload         4
     548: iload         20
     550: isub
     551: if_icmpge     558
     554: iconst_1
     555: goto          559
     558: iconst_0
     559: ifeq          587
     562: aload         12
     564: ldc           #164                // String
     566: invokevirtual #162                // Method java/lang/StringBuilder.append:(Ljava/lang/String;)Ljava/lang/StringBuilder;
     569: pop
     570: iload         21
     572: dup
     573: istore        22
     575: iconst_1
     576: iadd
     577: dup
     578: istore        21
     580: pop
     581: iload         22
     583: pop
     584: goto          544
     587: iload         13
     589: iload         4
     591: iload         20
     593: isub
     594: iadd
     595: dup
     596: istore        13
     598: pop
     599: goto          239
     602: aload         12
     604: invokevirtual #165                // Method java/lang/StringBuilder.length:()I
     607: iconst_0
     608: if_icmple     615
     611: iconst_1
     612: goto          616
     615: iconst_0
     616: ifeq          630
     619: aload_0
     620: checkcast     #2                  // class org/codehaus/groovy/tools/shell/PatchedConsoleReader
     623: aload         12
     625: invokevirtual #121                // Method println:(Ljava/lang/CharSequence;)V
     628: aconst_null
     629: pop
     630: return

  public static void access$0(org.codehaus.groovy.tools.shell.PatchedConsoleReader, int) throws java.io.IOException;
    Code:
       0: aload_0
       1: checkcast     #2                  // class org/codehaus/groovy/tools/shell/PatchedConsoleReader
       4: iload_1
       5: invokevirtual #154                // Method back:(I)V
       8: aconst_null
       9: pop
      10: return

  protected groovy.lang.MetaClass $getStaticMetaClass();
    Code:
       0: aload_0
       1: invokevirtual #187                // Method java/lang/Object.getClass:()Ljava/lang/Class;
       4: ldc           #2                  // class org/codehaus/groovy/tools/shell/PatchedConsoleReader
       6: if_acmpeq     14
       9: aload_0
      10: invokestatic  #191                // Method org/codehaus/groovy/runtime/ScriptBytecodeAdapter.initMetaClass:(Ljava/lang/Object;)Lgroovy/lang/MetaClass;
      13: areturn
      14: getstatic     #193                // Field $staticClassInfo:Lorg/codehaus/groovy/reflection/ClassInfo;
      17: astore_1
      18: aload_1
      19: ifnonnull     34
      22: aload_0
      23: invokevirtual #187                // Method java/lang/Object.getClass:()Ljava/lang/Class;
      26: invokestatic  #199                // Method org/codehaus/groovy/reflection/ClassInfo.getClassInfo:(Ljava/lang/Class;)Lorg/codehaus/groovy/reflection/ClassInfo;
      29: dup
      30: astore_1
      31: putstatic     #193                // Field $staticClassInfo:Lorg/codehaus/groovy/reflection/ClassInfo;
      34: aload_1
      35: invokevirtual #202                // Method org/codehaus/groovy/reflection/ClassInfo.getMetaClass:()Lgroovy/lang/MetaClass;
      38: areturn

  public groovy.lang.MetaClass getMetaClass();
    Code:
       0: aload_0
       1: getfield      #25                 // Field metaClass:Lgroovy/lang/MetaClass;
       4: dup
       5: ifnull        9
       8: areturn
       9: pop
      10: aload_0
      11: dup
      12: invokevirtual #23                 // Method $getStaticMetaClass:()Lgroovy/lang/MetaClass;
      15: putfield      #25                 // Field metaClass:Lgroovy/lang/MetaClass;
      18: aload_0
      19: getfield      #25                 // Field metaClass:Lgroovy/lang/MetaClass;
      22: areturn

  public void setMetaClass(groovy.lang.MetaClass);
    Code:
       0: aload_0
       1: aload_1
       2: putfield      #25                 // Field metaClass:Lgroovy/lang/MetaClass;
       5: return

  public java.lang.Object invokeMethod(java.lang.String, java.lang.Object);
    Code:
       0: aload_0
       1: invokevirtual #207                // Method getMetaClass:()Lgroovy/lang/MetaClass;
       4: aload_0
       5: aload_1
       6: aload_2
       7: invokeinterface #212,  4          // InterfaceMethod groovy/lang/MetaClass.invokeMethod:(Ljava/lang/Object;Ljava/lang/String;Ljava/lang/Object;)Ljava/lang/Object;
      12: areturn

  public java.lang.Object getProperty(java.lang.String);
    Code:
       0: aload_0
       1: invokevirtual #207                // Method getMetaClass:()Lgroovy/lang/MetaClass;
       4: aload_0
       5: aload_1
       6: invokeinterface #215,  3          // InterfaceMethod groovy/lang/MetaClass.getProperty:(Ljava/lang/Object;Ljava/lang/String;)Ljava/lang/Object;
      11: areturn

  public void setProperty(java.lang.String, java.lang.Object);
    Code:
       0: aload_0
       1: invokevirtual #207                // Method getMetaClass:()Lgroovy/lang/MetaClass;
       4: aload_0
       5: aload_1
       6: aload_2
       7: invokeinterface #220,  4          // InterfaceMethod groovy/lang/MetaClass.setProperty:(Ljava/lang/Object;Ljava/lang/String;Ljava/lang/Object;)V
      12: return
}
