Compiled from "BufferRecycler.java"
public final class org.elasticsearch.hadoop.thirdparty.codehaus.jackson.util.BufferRecycler$CharBufferType extends java.lang.Enum<org.elasticsearch.hadoop.thirdparty.codehaus.jackson.util.BufferRecycler$CharBufferType> {
  public static final org.elasticsearch.hadoop.thirdparty.codehaus.jackson.util.BufferRecycler$CharBufferType TOKEN_BUFFER;

  public static final org.elasticsearch.hadoop.thirdparty.codehaus.jackson.util.BufferRecycler$CharBufferType CONCAT_BUFFER;

  public static final org.elasticsearch.hadoop.thirdparty.codehaus.jackson.util.BufferRecycler$CharBufferType TEXT_BUFFER;

  public static final org.elasticsearch.hadoop.thirdparty.codehaus.jackson.util.BufferRecycler$CharBufferType NAME_COPY_BUFFER;

  private final int size;

  private static final org.elasticsearch.hadoop.thirdparty.codehaus.jackson.util.BufferRecycler$CharBufferType[] $VALUES;

  public static org.elasticsearch.hadoop.thirdparty.codehaus.jackson.util.BufferRecycler$CharBufferType[] values();
    Code:
       0: getstatic     #22                 // Field $VALUES:[Lorg/elasticsearch/hadoop/thirdparty/codehaus/jackson/util/BufferRecycler$CharBufferType;
       3: invokevirtual #27                 // Method "[Lorg/elasticsearch/hadoop/thirdparty/codehaus/jackson/util/BufferRecycler$CharBufferType;".clone:()Ljava/lang/Object;
       6: checkcast     #23                 // class "[Lorg/elasticsearch/hadoop/thirdparty/codehaus/jackson/util/BufferRecycler$CharBufferType;"
       9: areturn

  public static org.elasticsearch.hadoop.thirdparty.codehaus.jackson.util.BufferRecycler$CharBufferType valueOf(java.lang.String);
    Code:
       0: ldc           #2                  // class org/elasticsearch/hadoop/thirdparty/codehaus/jackson/util/BufferRecycler$CharBufferType
       2: aload_0
       3: invokestatic  #32                 // Method java/lang/Enum.valueOf:(Ljava/lang/Class;Ljava/lang/String;)Ljava/lang/Enum;
       6: checkcast     #2                  // class org/elasticsearch/hadoop/thirdparty/codehaus/jackson/util/BufferRecycler$CharBufferType
       9: areturn

  private org.elasticsearch.hadoop.thirdparty.codehaus.jackson.util.BufferRecycler$CharBufferType(int);
    Code:
       0: aload_0
       1: aload_1
       2: iload_2
       3: invokespecial #40                 // Method java/lang/Enum."<init>":(Ljava/lang/String;I)V
       6: aload_0
       7: iload_3
       8: putfield      #42                 // Field size:I
      11: return

  static int access$100(org.elasticsearch.hadoop.thirdparty.codehaus.jackson.util.BufferRecycler$CharBufferType);
    Code:
       0: aload_0
       1: getfield      #42                 // Field size:I
       4: ireturn

  static {};
    Code:
       0: new           #2                  // class org/elasticsearch/hadoop/thirdparty/codehaus/jackson/util/BufferRecycler$CharBufferType
       3: dup
       4: ldc           #49                 // String TOKEN_BUFFER
       6: iconst_0
       7: sipush        2000
      10: invokespecial #51                 // Method "<init>":(Ljava/lang/String;II)V
      13: putstatic     #53                 // Field TOKEN_BUFFER:Lorg/elasticsearch/hadoop/thirdparty/codehaus/jackson/util/BufferRecycler$CharBufferType;
      16: new           #2                  // class org/elasticsearch/hadoop/thirdparty/codehaus/jackson/util/BufferRecycler$CharBufferType
      19: dup
      20: ldc           #54                 // String CONCAT_BUFFER
      22: iconst_1
      23: sipush        2000
      26: invokespecial #51                 // Method "<init>":(Ljava/lang/String;II)V
      29: putstatic     #56                 // Field CONCAT_BUFFER:Lorg/elasticsearch/hadoop/thirdparty/codehaus/jackson/util/BufferRecycler$CharBufferType;
      32: new           #2                  // class org/elasticsearch/hadoop/thirdparty/codehaus/jackson/util/BufferRecycler$CharBufferType
      35: dup
      36: ldc           #57                 // String TEXT_BUFFER
      38: iconst_2
      39: sipush        200
      42: invokespecial #51                 // Method "<init>":(Ljava/lang/String;II)V
      45: putstatic     #59                 // Field TEXT_BUFFER:Lorg/elasticsearch/hadoop/thirdparty/codehaus/jackson/util/BufferRecycler$CharBufferType;
      48: new           #2                  // class org/elasticsearch/hadoop/thirdparty/codehaus/jackson/util/BufferRecycler$CharBufferType
      51: dup
      52: ldc           #60                 // String NAME_COPY_BUFFER
      54: iconst_3
      55: sipush        200
      58: invokespecial #51                 // Method "<init>":(Ljava/lang/String;II)V
      61: putstatic     #62                 // Field NAME_COPY_BUFFER:Lorg/elasticsearch/hadoop/thirdparty/codehaus/jackson/util/BufferRecycler$CharBufferType;
      64: iconst_4
      65: anewarray     #2                  // class org/elasticsearch/hadoop/thirdparty/codehaus/jackson/util/BufferRecycler$CharBufferType
      68: dup
      69: iconst_0
      70: getstatic     #53                 // Field TOKEN_BUFFER:Lorg/elasticsearch/hadoop/thirdparty/codehaus/jackson/util/BufferRecycler$CharBufferType;
      73: aastore
      74: dup
      75: iconst_1
      76: getstatic     #56                 // Field CONCAT_BUFFER:Lorg/elasticsearch/hadoop/thirdparty/codehaus/jackson/util/BufferRecycler$CharBufferType;
      79: aastore
      80: dup
      81: iconst_2
      82: getstatic     #59                 // Field TEXT_BUFFER:Lorg/elasticsearch/hadoop/thirdparty/codehaus/jackson/util/BufferRecycler$CharBufferType;
      85: aastore
      86: dup
      87: iconst_3
      88: getstatic     #62                 // Field NAME_COPY_BUFFER:Lorg/elasticsearch/hadoop/thirdparty/codehaus/jackson/util/BufferRecycler$CharBufferType;
      91: aastore
      92: putstatic     #22                 // Field $VALUES:[Lorg/elasticsearch/hadoop/thirdparty/codehaus/jackson/util/BufferRecycler$CharBufferType;
      95: return
}
