Compiled from "NodeMonitor.java"
public abstract class hudson.node_monitors.NodeMonitor implements hudson.ExtensionPoint, hudson.model.Describable<hudson.node_monitors.NodeMonitor> {
  public static final hudson.util.DescriptorList<hudson.node_monitors.NodeMonitor> LIST;

  public hudson.node_monitors.NodeMonitor();
    Code:
       0: aload_0
       1: invokespecial #1                  // Method java/lang/Object."<init>":()V
       4: return

  public java.lang.String getColumnCaption();
    Code:
       0: aload_0
       1: invokevirtual #2                  // Method getDescriptor:()Lhudson/node_monitors/AbstractNodeMonitorDescriptor;
       4: invokevirtual #3                  // Method hudson/node_monitors/AbstractNodeMonitorDescriptor.getDisplayName:()Ljava/lang/String;
       7: areturn

  public abstract hudson.node_monitors.AbstractNodeMonitorDescriptor<?> getDescriptor();

  public java.lang.Object data(hudson.model.Computer);
    Code:
       0: aload_0
       1: invokevirtual #2                  // Method getDescriptor:()Lhudson/node_monitors/AbstractNodeMonitorDescriptor;
       4: aload_1
       5: invokevirtual #4                  // Method hudson/node_monitors/AbstractNodeMonitorDescriptor.get:(Lhudson/model/Computer;)Ljava/lang/Object;
       8: areturn

  public static java.util.List<hudson.node_monitors.NodeMonitor> getAll();
    Code:
       0: invokestatic  #5                  // Method hudson/model/ComputerSet.get_monitors:()Ljava/util/List;
       3: areturn

  public hudson.model.Descriptor getDescriptor();
    Code:
       0: aload_0
       1: invokevirtual #2                  // Method getDescriptor:()Lhudson/node_monitors/AbstractNodeMonitorDescriptor;
       4: areturn

  static {};
    Code:
       0: new           #6                  // class hudson/util/DescriptorList
       3: dup
       4: iconst_0
       5: anewarray     #7                  // class hudson/model/Descriptor
       8: invokespecial #8                  // Method hudson/util/DescriptorList."<init>":([Lhudson/model/Descriptor;)V
      11: putstatic     #9                  // Field LIST:Lhudson/util/DescriptorList;
      14: getstatic     #9                  // Field LIST:Lhudson/util/DescriptorList;
      17: ldc_w         #10                 // class hudson/node_monitors/ClockMonitor
      20: invokevirtual #11                 // Method hudson/util/DescriptorList.load:(Ljava/lang/Class;)V
      23: invokestatic  #12                 // Method hudson/Functions.isMustangOrAbove:()Z
      26: ifeq          38
      29: getstatic     #9                  // Field LIST:Lhudson/util/DescriptorList;
      32: ldc_w         #13                 // class hudson/node_monitors/DiskSpaceMonitor
      35: invokevirtual #11                 // Method hudson/util/DescriptorList.load:(Ljava/lang/Class;)V
      38: getstatic     #9                  // Field LIST:Lhudson/util/DescriptorList;
      41: ldc_w         #14                 // class hudson/node_monitors/ArchitectureMonitor
      44: invokevirtual #11                 // Method hudson/util/DescriptorList.load:(Ljava/lang/Class;)V
      47: goto          69
      50: astore_0
      51: ldc_w         #16                 // class hudson/node_monitors/NodeMonitor
      54: invokevirtual #17                 // Method java/lang/Class.getName:()Ljava/lang/String;
      57: invokestatic  #18                 // Method java/util/logging/Logger.getLogger:(Ljava/lang/String;)Ljava/util/logging/Logger;
      60: getstatic     #19                 // Field java/util/logging/Level.SEVERE:Ljava/util/logging/Level;
      63: ldc           #20                 // String Failed to load built-in monitors
      65: aload_0
      66: invokevirtual #21                 // Method java/util/logging/Logger.log:(Ljava/util/logging/Level;Ljava/lang/String;Ljava/lang/Throwable;)V
      69: return
    Exception table:
       from    to  target type
          14    47    50   Class java/lang/Throwable
}
