Compiled from "ASTEscapedDirective.java"
public class io.sundr.shaded.org.apache.velocity.runtime.parser.node.ASTEscapedDirective extends io.sundr.shaded.org.apache.velocity.runtime.parser.node.SimpleNode {
  public io.sundr.shaded.org.apache.velocity.runtime.parser.node.ASTEscapedDirective(int);
    Code:
       0: aload_0
       1: iload_1
       2: invokespecial #9                  // Method io/sundr/shaded/org/apache/velocity/runtime/parser/node/SimpleNode."<init>":(I)V
       5: return

  public io.sundr.shaded.org.apache.velocity.runtime.parser.node.ASTEscapedDirective(io.sundr.shaded.org.apache.velocity.runtime.parser.Parser, int);
    Code:
       0: aload_0
       1: aload_1
       2: iload_2
       3: invokespecial #16                 // Method io/sundr/shaded/org/apache/velocity/runtime/parser/node/SimpleNode."<init>":(Lio/sundr/shaded/org/apache/velocity/runtime/parser/Parser;I)V
       6: return

  public java.lang.Object jjtAccept(io.sundr.shaded.org.apache.velocity.runtime.parser.node.ParserVisitor, java.lang.Object);
    Code:
       0: aload_1
       1: aload_0
       2: aload_2
       3: invokeinterface #26,  3           // InterfaceMethod io/sundr/shaded/org/apache/velocity/runtime/parser/node/ParserVisitor.visit:(Lio/sundr/shaded/org/apache/velocity/runtime/parser/node/ASTEscapedDirective;Ljava/lang/Object;)Ljava/lang/Object;
       8: areturn

  public boolean render(io.sundr.shaded.org.apache.velocity.context.InternalContextAdapter, java.io.Writer) throws java.io.IOException;
    Code:
       0: aload_2
       1: aload_0
       2: invokevirtual #38                 // Method getFirstToken:()Lio/sundr/shaded/org/apache/velocity/runtime/parser/Token;
       5: getfield      #44                 // Field io/sundr/shaded/org/apache/velocity/runtime/parser/Token.image:Ljava/lang/String;
       8: invokevirtual #50                 // Method java/io/Writer.write:(Ljava/lang/String;)V
      11: iconst_1
      12: ireturn
}
