Compiled from "TimelineServiceHelper.java"
public final class org.apache.hadoop.yarn.util.TimelineServiceHelper {
  private org.apache.hadoop.yarn.util.TimelineServiceHelper();
    Code:
       0: aload_0
       1: invokespecial #1                  // Method java/lang/Object."<init>":()V
       4: return

  public static <E, V> java.util.HashMap<E, V> mapCastToHashMap(java.util.Map<E, V>);
    Code:
       0: aload_0
       1: ifnonnull     8
       4: aconst_null
       5: goto          30
       8: aload_0
       9: instanceof    #2                  // class java/util/HashMap
      12: ifeq          22
      15: aload_0
      16: checkcast     #2                  // class java/util/HashMap
      19: goto          30
      22: new           #2                  // class java/util/HashMap
      25: dup
      26: aload_0
      27: invokespecial #3                  // Method java/util/HashMap."<init>":(Ljava/util/Map;)V
      30: areturn

  public static long invertLong(long);
    Code:
       0: ldc2_w        #5                  // long 9223372036854775807l
       3: lload_0
       4: lsub
       5: lreturn
}
