Compiled from "HttpProtocolInputStream.java"
public class org.smallmind.web.reverse.http1_1.HttpProtocolInputStream extends java.io.InputStream {
  private final org.smallmind.nutsnbolts.io.ByteArrayIOStream$ByteArrayInputStream byteArrayInputStream;

  private final int index;

  java.io.BufferedInputStream b;

  public org.smallmind.web.reverse.http1_1.HttpProtocolInputStream(org.smallmind.nutsnbolts.io.ByteArrayIOStream$ByteArrayInputStream);
    Code:
       0: aload_0
       1: invokespecial #1                  // Method java/io/InputStream."<init>":()V
       4: aload_0
       5: iconst_0
       6: putfield      #2                  // Field index:I
       9: aload_0
      10: aload_1
      11: putfield      #3                  // Field byteArrayInputStream:Lorg/smallmind/nutsnbolts/io/ByteArrayIOStream$ByteArrayInputStream;
      14: return

  public synchronized void mark(int);
    Code:
       0: aload_0
       1: getfield      #3                  // Field byteArrayInputStream:Lorg/smallmind/nutsnbolts/io/ByteArrayIOStream$ByteArrayInputStream;
       4: iload_1
       5: invokevirtual #4                  // Method org/smallmind/nutsnbolts/io/ByteArrayIOStream$ByteArrayInputStream.mark:(I)V
       8: return

  public synchronized void reset() throws java.io.IOException;
    Code:
       0: aload_0
       1: getfield      #3                  // Field byteArrayInputStream:Lorg/smallmind/nutsnbolts/io/ByteArrayIOStream$ByteArrayInputStream;
       4: invokevirtual #5                  // Method org/smallmind/nutsnbolts/io/ByteArrayIOStream$ByteArrayInputStream.reset:()V
       7: return

  public int read() throws java.io.IOException;
    Code:
       0: aload_0
       1: getfield      #3                  // Field byteArrayInputStream:Lorg/smallmind/nutsnbolts/io/ByteArrayIOStream$ByteArrayInputStream;
       4: invokevirtual #6                  // Method org/smallmind/nutsnbolts/io/ByteArrayIOStream$ByteArrayInputStream.available:()I
       7: ifne          14
      10: iconst_m1
      11: goto          21
      14: aload_0
      15: getfield      #3                  // Field byteArrayInputStream:Lorg/smallmind/nutsnbolts/io/ByteArrayIOStream$ByteArrayInputStream;
      18: invokevirtual #7                  // Method org/smallmind/nutsnbolts/io/ByteArrayIOStream$ByteArrayInputStream.read:()I
      21: ireturn

  public java.lang.String readLine() throws java.io.IOException;
    Code:
       0: aload_0
       1: getfield      #3                  // Field byteArrayInputStream:Lorg/smallmind/nutsnbolts/io/ByteArrayIOStream$ByteArrayInputStream;
       4: invokevirtual #6                  // Method org/smallmind/nutsnbolts/io/ByteArrayIOStream$ByteArrayInputStream.available:()I
       7: ifle          76
      10: new           #8                  // class java/lang/StringBuilder
      13: dup
      14: invokespecial #9                  // Method java/lang/StringBuilder."<init>":()V
      17: astore_1
      18: aload_0
      19: getfield      #3                  // Field byteArrayInputStream:Lorg/smallmind/nutsnbolts/io/ByteArrayIOStream$ByteArrayInputStream;
      22: invokevirtual #7                  // Method org/smallmind/nutsnbolts/io/ByteArrayIOStream$ByteArrayInputStream.read:()I
      25: dup
      26: istore_2
      27: bipush        10
      29: if_icmpne     59
      32: aload_1
      33: aload_1
      34: invokevirtual #10                 // Method java/lang/StringBuilder.length:()I
      37: iconst_1
      38: isub
      39: invokevirtual #11                 // Method java/lang/StringBuilder.charAt:(I)C
      42: bipush        13
      44: if_icmpne     59
      47: aload_1
      48: iconst_0
      49: aload_1
      50: invokevirtual #10                 // Method java/lang/StringBuilder.length:()I
      53: iconst_1
      54: isub
      55: invokevirtual #12                 // Method java/lang/StringBuilder.substring:(II)Ljava/lang/String;
      58: areturn
      59: aload_1
      60: iload_2
      61: i2c
      62: invokevirtual #13                 // Method java/lang/StringBuilder.append:(C)Ljava/lang/StringBuilder;
      65: pop
      66: aload_0
      67: getfield      #3                  // Field byteArrayInputStream:Lorg/smallmind/nutsnbolts/io/ByteArrayIOStream$ByteArrayInputStream;
      70: invokevirtual #6                  // Method org/smallmind/nutsnbolts/io/ByteArrayIOStream$ByteArrayInputStream.available:()I
      73: ifgt          18
      76: aconst_null
      77: areturn
}
