Compiled from "EJB3Subsystem12Parser.java"
public class org.jboss.as.ejb3.subsystem.EJB3Subsystem12Parser implements org.jboss.staxmapper.XMLElementReader<java.util.List<org.jboss.dmr.ModelNode>> {
  public static final org.jboss.as.ejb3.subsystem.EJB3Subsystem12Parser INSTANCE;

  protected static final org.jboss.as.controller.PathAddress SUBSYSTEM_PATH;

  protected org.jboss.as.ejb3.subsystem.EJB3Subsystem12Parser();
    Code:
       0: aload_0
       1: invokespecial #3                  // Method java/lang/Object."<init>":()V
       4: return

  protected void readAttributes(org.jboss.staxmapper.XMLExtendedStreamReader) throws javax.xml.stream.XMLStreamException;
    Code:
       0: iconst_0
       1: istore_2
       2: iload_2
       3: aload_1
       4: invokeinterface #4,  1            // InterfaceMethod org/jboss/staxmapper/XMLExtendedStreamReader.getAttributeCount:()I
       9: if_icmpge     23
      12: aload_1
      13: iload_2
      14: invokestatic  #5                  // Method org/jboss/as/controller/parsing/ParseUtils.requireNoNamespaceAttribute:(Lorg/jboss/staxmapper/XMLExtendedStreamReader;I)V
      17: aload_1
      18: iload_2
      19: invokestatic  #6                  // Method org/jboss/as/controller/parsing/ParseUtils.unexpectedAttribute:(Lorg/jboss/staxmapper/XMLExtendedStreamReader;I)Ljavax/xml/stream/XMLStreamException;
      22: athrow
      23: return

  public void readElement(org.jboss.staxmapper.XMLExtendedStreamReader, java.util.List<org.jboss.dmr.ModelNode>) throws javax.xml.stream.XMLStreamException;
    Code:
       0: getstatic     #7                  // Field SUBSYSTEM_PATH:Lorg/jboss/as/controller/PathAddress;
       3: invokestatic  #8                  // Method org/jboss/as/controller/operations/common/Util.createAddOperation:(Lorg/jboss/as/controller/PathAddress;)Lorg/jboss/dmr/ModelNode;
       6: astore_3
       7: aload_2
       8: aload_3
       9: invokeinterface #9,  2            // InterfaceMethod java/util/List.add:(Ljava/lang/Object;)Z
      14: pop
      15: aload_0
      16: aload_1
      17: invokevirtual #10                 // Method readAttributes:(Lorg/jboss/staxmapper/XMLExtendedStreamReader;)V
      20: ldc           #11                 // class org/jboss/as/ejb3/subsystem/EJB3SubsystemXMLElement
      22: invokestatic  #12                 // Method java/util/EnumSet.noneOf:(Ljava/lang/Class;)Ljava/util/EnumSet;
      25: astore        4
      27: aload_1
      28: invokeinterface #13,  1           // InterfaceMethod org/jboss/staxmapper/XMLExtendedStreamReader.hasNext:()Z
      33: ifeq          105
      36: aload_1
      37: invokeinterface #14,  1           // InterfaceMethod org/jboss/staxmapper/XMLExtendedStreamReader.nextTag:()I
      42: iconst_2
      43: if_icmpeq     105
      46: aload_1
      47: invokeinterface #16,  1           // InterfaceMethod org/jboss/staxmapper/XMLExtendedStreamReader.getNamespaceURI:()Ljava/lang/String;
      52: invokestatic  #17                 // Method org/jboss/as/ejb3/subsystem/EJB3SubsystemNamespace.forUri:(Ljava/lang/String;)Lorg/jboss/as/ejb3/subsystem/EJB3SubsystemNamespace;
      55: aload_0
      56: invokevirtual #18                 // Method getExpectedNamespace:()Lorg/jboss/as/ejb3/subsystem/EJB3SubsystemNamespace;
      59: if_acmpeq     67
      62: aload_1
      63: invokestatic  #19                 // Method org/jboss/as/controller/parsing/ParseUtils.unexpectedElement:(Lorg/jboss/staxmapper/XMLExtendedStreamReader;)Ljavax/xml/stream/XMLStreamException;
      66: athrow
      67: aload_1
      68: invokeinterface #20,  1           // InterfaceMethod org/jboss/staxmapper/XMLExtendedStreamReader.getLocalName:()Ljava/lang/String;
      73: invokestatic  #21                 // Method org/jboss/as/ejb3/subsystem/EJB3SubsystemXMLElement.forName:(Ljava/lang/String;)Lorg/jboss/as/ejb3/subsystem/EJB3SubsystemXMLElement;
      76: astore        5
      78: aload         4
      80: aload         5
      82: invokevirtual #22                 // Method java/util/EnumSet.add:(Ljava/lang/Object;)Z
      85: ifne          93
      88: aload_1
      89: invokestatic  #19                 // Method org/jboss/as/controller/parsing/ParseUtils.unexpectedElement:(Lorg/jboss/staxmapper/XMLExtendedStreamReader;)Ljavax/xml/stream/XMLStreamException;
      92: athrow
      93: aload_0
      94: aload_1
      95: aload         5
      97: aload_2
      98: aload_3
      99: invokevirtual #23                 // Method readElement:(Lorg/jboss/staxmapper/XMLExtendedStreamReader;Lorg/jboss/as/ejb3/subsystem/EJB3SubsystemXMLElement;Ljava/util/List;Lorg/jboss/dmr/ModelNode;)V
     102: goto          27
     105: return

  protected void readElement(org.jboss.staxmapper.XMLExtendedStreamReader, org.jboss.as.ejb3.subsystem.EJB3SubsystemXMLElement, java.util.List<org.jboss.dmr.ModelNode>, org.jboss.dmr.ModelNode) throws javax.xml.stream.XMLStreamException;
    Code:
       0: getstatic     #24                 // Field org/jboss/as/ejb3/subsystem/EJB3Subsystem12Parser$1.$SwitchMap$org$jboss$as$ejb3$subsystem$EJB3SubsystemXMLElement:[I
       3: aload_2
       4: invokevirtual #25                 // Method org/jboss/as/ejb3/subsystem/EJB3SubsystemXMLElement.ordinal:()I
       7: iaload
       8: tableswitch   { // 1 to 12
                     1: 72
                     2: 81
                     3: 90
                     4: 101
                     5: 112
                     6: 121
                     7: 130
                     8: 139
                     9: 150
                    10: 159
                    11: 168
                    12: 177
               default: 187
          }
      72: aload_0
      73: aload_1
      74: aload_3
      75: invokespecial #26                 // Method parseCaches:(Lorg/jboss/staxmapper/XMLExtendedStreamReader;Ljava/util/List;)V
      78: goto          192
      81: aload_0
      82: aload_1
      83: aload_3
      84: invokevirtual #27                 // Method parsePassivationStores:(Lorg/jboss/staxmapper/XMLExtendedStreamReader;Ljava/util/List;)V
      87: goto          192
      90: aload_0
      91: aload_1
      92: aload_3
      93: aload         4
      95: invokevirtual #28                 // Method parseMDB:(Lorg/jboss/staxmapper/XMLExtendedStreamReader;Ljava/util/List;Lorg/jboss/dmr/ModelNode;)V
      98: goto          192
     101: aload_0
     102: aload_1
     103: aload_3
     104: aload         4
     106: invokespecial #29                 // Method parseEntityBean:(Lorg/jboss/staxmapper/XMLExtendedStreamReader;Ljava/util/List;Lorg/jboss/dmr/ModelNode;)V
     109: goto          192
     112: aload_0
     113: aload_1
     114: aload_3
     115: invokespecial #30                 // Method parsePools:(Lorg/jboss/staxmapper/XMLExtendedStreamReader;Ljava/util/List;)V
     118: goto          192
     121: aload_0
     122: aload_1
     123: aload_3
     124: invokevirtual #31                 // Method parseRemote:(Lorg/jboss/staxmapper/XMLExtendedStreamReader;Ljava/util/List;)V
     127: goto          192
     130: aload_0
     131: aload_1
     132: aload_3
     133: invokespecial #32                 // Method parseAsync:(Lorg/jboss/staxmapper/XMLExtendedStreamReader;Ljava/util/List;)V
     136: goto          192
     139: aload_0
     140: aload_1
     141: aload_3
     142: aload         4
     144: invokespecial #33                 // Method parseSessionBean:(Lorg/jboss/staxmapper/XMLExtendedStreamReader;Ljava/util/List;Lorg/jboss/dmr/ModelNode;)V
     147: goto          192
     150: aload_0
     151: aload_1
     152: aload_3
     153: invokevirtual #34                 // Method parseTimerService:(Lorg/jboss/staxmapper/XMLExtendedStreamReader;Ljava/util/List;)V
     156: goto          192
     159: aload_0
     160: aload_1
     161: aload_3
     162: invokespecial #35                 // Method parseThreadPools:(Lorg/jboss/staxmapper/XMLExtendedStreamReader;Ljava/util/List;)V
     165: goto          192
     168: aload_0
     169: aload_1
     170: aload_3
     171: invokespecial #36                 // Method parseIIOP:(Lorg/jboss/staxmapper/XMLExtendedStreamReader;Ljava/util/List;)V
     174: goto          192
     177: aload_0
     178: aload_1
     179: aload         4
     181: invokespecial #37                 // Method parseInVMRemoteInterfaceInvocation:(Lorg/jboss/staxmapper/XMLExtendedStreamReader;Lorg/jboss/dmr/ModelNode;)V
     184: goto          192
     187: aload_1
     188: invokestatic  #19                 // Method org/jboss/as/controller/parsing/ParseUtils.unexpectedElement:(Lorg/jboss/staxmapper/XMLExtendedStreamReader;)Ljavax/xml/stream/XMLStreamException;
     191: athrow
     192: return

  protected void parseRemote(org.jboss.staxmapper.XMLExtendedStreamReader, java.util.List<org.jboss.dmr.ModelNode>) throws javax.xml.stream.XMLStreamException;
    Code:
       0: aload_1
       1: invokeinterface #4,  1            // InterfaceMethod org/jboss/staxmapper/XMLExtendedStreamReader.getAttributeCount:()I
       6: istore_3
       7: getstatic     #7                  // Field SUBSYSTEM_PATH:Lorg/jboss/as/controller/PathAddress;
      10: ldc           #38                 // String service
      12: ldc           #39                 // String remote
      14: invokevirtual #40                 // Method org/jboss/as/controller/PathAddress.append:(Ljava/lang/String;Ljava/lang/String;)Lorg/jboss/as/controller/PathAddress;
      17: invokestatic  #8                  // Method org/jboss/as/controller/operations/common/Util.createAddOperation:(Lorg/jboss/as/controller/PathAddress;)Lorg/jboss/dmr/ModelNode;
      20: astore        4
      22: getstatic     #41                 // Field org/jboss/as/ejb3/subsystem/EJB3SubsystemXMLAttribute.CONNECTOR_REF:Lorg/jboss/as/ejb3/subsystem/EJB3SubsystemXMLAttribute;
      25: getstatic     #42                 // Field org/jboss/as/ejb3/subsystem/EJB3SubsystemXMLAttribute.THREAD_POOL_NAME:Lorg/jboss/as/ejb3/subsystem/EJB3SubsystemXMLAttribute;
      28: invokestatic  #43                 // Method java/util/EnumSet.of:(Ljava/lang/Enum;Ljava/lang/Enum;)Ljava/util/EnumSet;
      31: astore        5
      33: iconst_0
      34: istore        6
      36: iload         6
      38: iload_3
      39: if_icmpge     157
      42: aload_1
      43: iload         6
      45: invokestatic  #5                  // Method org/jboss/as/controller/parsing/ParseUtils.requireNoNamespaceAttribute:(Lorg/jboss/staxmapper/XMLExtendedStreamReader;I)V
      48: aload_1
      49: iload         6
      51: invokeinterface #44,  2           // InterfaceMethod org/jboss/staxmapper/XMLExtendedStreamReader.getAttributeValue:(I)Ljava/lang/String;
      56: astore        7
      58: aload_1
      59: iload         6
      61: invokeinterface #45,  2           // InterfaceMethod org/jboss/staxmapper/XMLExtendedStreamReader.getAttributeLocalName:(I)Ljava/lang/String;
      66: invokestatic  #46                 // Method org/jboss/as/ejb3/subsystem/EJB3SubsystemXMLAttribute.forName:(Ljava/lang/String;)Lorg/jboss/as/ejb3/subsystem/EJB3SubsystemXMLAttribute;
      69: astore        8
      71: aload         5
      73: aload         8
      75: invokevirtual #47                 // Method java/util/EnumSet.remove:(Ljava/lang/Object;)Z
      78: pop
      79: getstatic     #48                 // Field org/jboss/as/ejb3/subsystem/EJB3Subsystem12Parser$1.$SwitchMap$org$jboss$as$ejb3$subsystem$EJB3SubsystemXMLAttribute:[I
      82: aload         8
      84: invokevirtual #49                 // Method org/jboss/as/ejb3/subsystem/EJB3SubsystemXMLAttribute.ordinal:()I
      87: iaload
      88: lookupswitch  { // 2
                     1: 116
                     2: 130
               default: 144
          }
     116: getstatic     #50                 // Field org/jboss/as/ejb3/subsystem/EJB3RemoteResourceDefinition.CONNECTOR_REF:Lorg/jboss/as/controller/SimpleAttributeDefinition;
     119: aload         7
     121: aload         4
     123: aload_1
     124: invokevirtual #51                 // Method org/jboss/as/controller/SimpleAttributeDefinition.parseAndSetParameter:(Ljava/lang/String;Lorg/jboss/dmr/ModelNode;Ljavax/xml/stream/XMLStreamReader;)V
     127: goto          151
     130: getstatic     #52                 // Field org/jboss/as/ejb3/subsystem/EJB3RemoteResourceDefinition.THREAD_POOL_NAME:Lorg/jboss/as/controller/SimpleAttributeDefinition;
     133: aload         7
     135: aload         4
     137: aload_1
     138: invokevirtual #51                 // Method org/jboss/as/controller/SimpleAttributeDefinition.parseAndSetParameter:(Ljava/lang/String;Lorg/jboss/dmr/ModelNode;Ljavax/xml/stream/XMLStreamReader;)V
     141: goto          151
     144: aload_1
     145: iload         6
     147: invokestatic  #6                  // Method org/jboss/as/controller/parsing/ParseUtils.unexpectedAttribute:(Lorg/jboss/staxmapper/XMLExtendedStreamReader;I)Ljavax/xml/stream/XMLStreamException;
     150: athrow
     151: iinc          6, 1
     154: goto          36
     157: aload         5
     159: invokevirtual #53                 // Method java/util/EnumSet.isEmpty:()Z
     162: ifne          172
     165: aload_1
     166: aload         5
     168: invokestatic  #54                 // Method org/jboss/as/controller/parsing/ParseUtils.missingRequired:(Lorg/jboss/staxmapper/XMLExtendedStreamReader;Ljava/util/Set;)Ljavax/xml/stream/XMLStreamException;
     171: athrow
     172: aload         4
     174: ldc           #55                 // String execute-in-worker
     176: invokevirtual #56                 // Method org/jboss/dmr/ModelNode.get:(Ljava/lang/String;)Lorg/jboss/dmr/ModelNode;
     179: new           #57                 // class org/jboss/dmr/ModelNode
     182: dup
     183: iconst_0
     184: invokespecial #58                 // Method org/jboss/dmr/ModelNode."<init>":(Z)V
     187: invokevirtual #59                 // Method org/jboss/dmr/ModelNode.set:(Lorg/jboss/dmr/ModelNode;)Lorg/jboss/dmr/ModelNode;
     190: pop
     191: aload_1
     192: invokestatic  #60                 // Method org/jboss/as/controller/parsing/ParseUtils.requireNoContent:(Lorg/jboss/staxmapper/XMLExtendedStreamReader;)V
     195: aload_2
     196: aload         4
     198: invokeinterface #9,  2            // InterfaceMethod java/util/List.add:(Ljava/lang/Object;)Z
     203: pop
     204: return

  private void parseAsync(org.jboss.staxmapper.XMLExtendedStreamReader, java.util.List<org.jboss.dmr.ModelNode>) throws javax.xml.stream.XMLStreamException;
    Code:
       0: aload_1
       1: invokeinterface #4,  1            // InterfaceMethod org/jboss/staxmapper/XMLExtendedStreamReader.getAttributeCount:()I
       6: istore_3
       7: getstatic     #7                  // Field SUBSYSTEM_PATH:Lorg/jboss/as/controller/PathAddress;
      10: ldc           #38                 // String service
      12: ldc           #61                 // String async
      14: invokevirtual #40                 // Method org/jboss/as/controller/PathAddress.append:(Ljava/lang/String;Ljava/lang/String;)Lorg/jboss/as/controller/PathAddress;
      17: invokestatic  #8                  // Method org/jboss/as/controller/operations/common/Util.createAddOperation:(Lorg/jboss/as/controller/PathAddress;)Lorg/jboss/dmr/ModelNode;
      20: astore        4
      22: getstatic     #42                 // Field org/jboss/as/ejb3/subsystem/EJB3SubsystemXMLAttribute.THREAD_POOL_NAME:Lorg/jboss/as/ejb3/subsystem/EJB3SubsystemXMLAttribute;
      25: invokestatic  #62                 // Method java/util/EnumSet.of:(Ljava/lang/Enum;)Ljava/util/EnumSet;
      28: astore        5
      30: iconst_0
      31: istore        6
      33: iload         6
      35: iload_3
      36: if_icmpge     131
      39: aload_1
      40: iload         6
      42: invokestatic  #5                  // Method org/jboss/as/controller/parsing/ParseUtils.requireNoNamespaceAttribute:(Lorg/jboss/staxmapper/XMLExtendedStreamReader;I)V
      45: aload_1
      46: iload         6
      48: invokeinterface #44,  2           // InterfaceMethod org/jboss/staxmapper/XMLExtendedStreamReader.getAttributeValue:(I)Ljava/lang/String;
      53: astore        7
      55: aload_1
      56: iload         6
      58: invokeinterface #45,  2           // InterfaceMethod org/jboss/staxmapper/XMLExtendedStreamReader.getAttributeLocalName:(I)Ljava/lang/String;
      63: invokestatic  #46                 // Method org/jboss/as/ejb3/subsystem/EJB3SubsystemXMLAttribute.forName:(Ljava/lang/String;)Lorg/jboss/as/ejb3/subsystem/EJB3SubsystemXMLAttribute;
      66: astore        8
      68: aload         5
      70: aload         8
      72: invokevirtual #47                 // Method java/util/EnumSet.remove:(Ljava/lang/Object;)Z
      75: pop
      76: getstatic     #48                 // Field org/jboss/as/ejb3/subsystem/EJB3Subsystem12Parser$1.$SwitchMap$org$jboss$as$ejb3$subsystem$EJB3SubsystemXMLAttribute:[I
      79: aload         8
      81: invokevirtual #49                 // Method org/jboss/as/ejb3/subsystem/EJB3SubsystemXMLAttribute.ordinal:()I
      84: iaload
      85: lookupswitch  { // 1
                     2: 104
               default: 118
          }
     104: getstatic     #63                 // Field org/jboss/as/ejb3/subsystem/EJB3AsyncResourceDefinition.THREAD_POOL_NAME:Lorg/jboss/as/controller/SimpleAttributeDefinition;
     107: aload         7
     109: aload         4
     111: aload_1
     112: invokevirtual #51                 // Method org/jboss/as/controller/SimpleAttributeDefinition.parseAndSetParameter:(Ljava/lang/String;Lorg/jboss/dmr/ModelNode;Ljavax/xml/stream/XMLStreamReader;)V
     115: goto          125
     118: aload_1
     119: iload         6
     121: invokestatic  #6                  // Method org/jboss/as/controller/parsing/ParseUtils.unexpectedAttribute:(Lorg/jboss/staxmapper/XMLExtendedStreamReader;I)Ljavax/xml/stream/XMLStreamException;
     124: athrow
     125: iinc          6, 1
     128: goto          33
     131: aload         5
     133: invokevirtual #53                 // Method java/util/EnumSet.isEmpty:()Z
     136: ifne          146
     139: aload_1
     140: aload         5
     142: invokestatic  #54                 // Method org/jboss/as/controller/parsing/ParseUtils.missingRequired:(Lorg/jboss/staxmapper/XMLExtendedStreamReader;Ljava/util/Set;)Ljavax/xml/stream/XMLStreamException;
     145: athrow
     146: aload_1
     147: invokestatic  #60                 // Method org/jboss/as/controller/parsing/ParseUtils.requireNoContent:(Lorg/jboss/staxmapper/XMLExtendedStreamReader;)V
     150: aload_2
     151: aload         4
     153: invokeinterface #9,  2            // InterfaceMethod java/util/List.add:(Ljava/lang/Object;)Z
     158: pop
     159: return

  private void parseIIOP(org.jboss.staxmapper.XMLExtendedStreamReader, java.util.List<org.jboss.dmr.ModelNode>) throws javax.xml.stream.XMLStreamException;
    Code:
       0: getstatic     #7                  // Field SUBSYSTEM_PATH:Lorg/jboss/as/controller/PathAddress;
       3: ldc           #38                 // String service
       5: ldc           #64                 // String iiop
       7: invokevirtual #40                 // Method org/jboss/as/controller/PathAddress.append:(Ljava/lang/String;Ljava/lang/String;)Lorg/jboss/as/controller/PathAddress;
      10: invokestatic  #8                  // Method org/jboss/as/controller/operations/common/Util.createAddOperation:(Lorg/jboss/as/controller/PathAddress;)Lorg/jboss/dmr/ModelNode;
      13: astore_3
      14: aload_1
      15: invokeinterface #4,  1            // InterfaceMethod org/jboss/staxmapper/XMLExtendedStreamReader.getAttributeCount:()I
      20: istore        4
      22: getstatic     #65                 // Field org/jboss/as/ejb3/subsystem/EJB3SubsystemXMLAttribute.ENABLE_BY_DEFAULT:Lorg/jboss/as/ejb3/subsystem/EJB3SubsystemXMLAttribute;
      25: getstatic     #66                 // Field org/jboss/as/ejb3/subsystem/EJB3SubsystemXMLAttribute.USE_QUALIFIED_NAME:Lorg/jboss/as/ejb3/subsystem/EJB3SubsystemXMLAttribute;
      28: invokestatic  #43                 // Method java/util/EnumSet.of:(Ljava/lang/Enum;Ljava/lang/Enum;)Ljava/util/EnumSet;
      31: astore        5
      33: iconst_0
      34: istore        6
      36: iload         6
      38: iload         4
      40: if_icmpge     155
      43: aload_1
      44: iload         6
      46: invokestatic  #5                  // Method org/jboss/as/controller/parsing/ParseUtils.requireNoNamespaceAttribute:(Lorg/jboss/staxmapper/XMLExtendedStreamReader;I)V
      49: aload_1
      50: iload         6
      52: invokeinterface #44,  2           // InterfaceMethod org/jboss/staxmapper/XMLExtendedStreamReader.getAttributeValue:(I)Ljava/lang/String;
      57: astore        7
      59: aload_1
      60: iload         6
      62: invokeinterface #45,  2           // InterfaceMethod org/jboss/staxmapper/XMLExtendedStreamReader.getAttributeLocalName:(I)Ljava/lang/String;
      67: invokestatic  #46                 // Method org/jboss/as/ejb3/subsystem/EJB3SubsystemXMLAttribute.forName:(Ljava/lang/String;)Lorg/jboss/as/ejb3/subsystem/EJB3SubsystemXMLAttribute;
      70: astore        8
      72: aload         5
      74: aload         8
      76: invokevirtual #47                 // Method java/util/EnumSet.remove:(Ljava/lang/Object;)Z
      79: pop
      80: getstatic     #48                 // Field org/jboss/as/ejb3/subsystem/EJB3Subsystem12Parser$1.$SwitchMap$org$jboss$as$ejb3$subsystem$EJB3SubsystemXMLAttribute:[I
      83: aload         8
      85: invokevirtual #49                 // Method org/jboss/as/ejb3/subsystem/EJB3SubsystemXMLAttribute.ordinal:()I
      88: iaload
      89: lookupswitch  { // 2
                     3: 116
                     4: 129
               default: 142
          }
     116: getstatic     #67                 // Field org/jboss/as/ejb3/subsystem/EJB3IIOPResourceDefinition.ENABLE_BY_DEFAULT:Lorg/jboss/as/controller/SimpleAttributeDefinition;
     119: aload         7
     121: aload_3
     122: aload_1
     123: invokevirtual #51                 // Method org/jboss/as/controller/SimpleAttributeDefinition.parseAndSetParameter:(Ljava/lang/String;Lorg/jboss/dmr/ModelNode;Ljavax/xml/stream/XMLStreamReader;)V
     126: goto          149
     129: getstatic     #68                 // Field org/jboss/as/ejb3/subsystem/EJB3IIOPResourceDefinition.USE_QUALIFIED_NAME:Lorg/jboss/as/controller/SimpleAttributeDefinition;
     132: aload         7
     134: aload_3
     135: aload_1
     136: invokevirtual #51                 // Method org/jboss/as/controller/SimpleAttributeDefinition.parseAndSetParameter:(Ljava/lang/String;Lorg/jboss/dmr/ModelNode;Ljavax/xml/stream/XMLStreamReader;)V
     139: goto          149
     142: aload_1
     143: iload         6
     145: invokestatic  #6                  // Method org/jboss/as/controller/parsing/ParseUtils.unexpectedAttribute:(Lorg/jboss/staxmapper/XMLExtendedStreamReader;I)Ljavax/xml/stream/XMLStreamException;
     148: athrow
     149: iinc          6, 1
     152: goto          36
     155: aload         5
     157: invokevirtual #53                 // Method java/util/EnumSet.isEmpty:()Z
     160: ifne          170
     163: aload_1
     164: aload         5
     166: invokestatic  #54                 // Method org/jboss/as/controller/parsing/ParseUtils.missingRequired:(Lorg/jboss/staxmapper/XMLExtendedStreamReader;Ljava/util/Set;)Ljavax/xml/stream/XMLStreamException;
     169: athrow
     170: aload_1
     171: invokestatic  #60                 // Method org/jboss/as/controller/parsing/ParseUtils.requireNoContent:(Lorg/jboss/staxmapper/XMLExtendedStreamReader;)V
     174: aload_2
     175: aload_3
     176: invokeinterface #9,  2            // InterfaceMethod java/util/List.add:(Ljava/lang/Object;)Z
     181: pop
     182: return

  protected void parseMDB(org.jboss.staxmapper.XMLExtendedStreamReader, java.util.List<org.jboss.dmr.ModelNode>, org.jboss.dmr.ModelNode) throws javax.xml.stream.XMLStreamException;
    Code:
       0: aload_1
       1: invokestatic  #69                 // Method org/jboss/as/controller/parsing/ParseUtils.requireNoAttributes:(Lorg/jboss/staxmapper/XMLExtendedStreamReader;)V
       4: aload_1
       5: invokeinterface #13,  1           // InterfaceMethod org/jboss/staxmapper/XMLExtendedStreamReader.hasNext:()Z
      10: ifeq          119
      13: aload_1
      14: invokeinterface #14,  1           // InterfaceMethod org/jboss/staxmapper/XMLExtendedStreamReader.nextTag:()I
      19: iconst_2
      20: if_icmpeq     119
      23: getstatic     #24                 // Field org/jboss/as/ejb3/subsystem/EJB3Subsystem12Parser$1.$SwitchMap$org$jboss$as$ejb3$subsystem$EJB3SubsystemXMLElement:[I
      26: aload_1
      27: invokeinterface #20,  1           // InterfaceMethod org/jboss/staxmapper/XMLExtendedStreamReader.getLocalName:()Ljava/lang/String;
      32: invokestatic  #21                 // Method org/jboss/as/ejb3/subsystem/EJB3SubsystemXMLElement.forName:(Ljava/lang/String;)Lorg/jboss/as/ejb3/subsystem/EJB3SubsystemXMLElement;
      35: invokevirtual #25                 // Method org/jboss/as/ejb3/subsystem/EJB3SubsystemXMLElement.ordinal:()I
      38: iaload
      39: lookupswitch  { // 2
                    13: 64
                    14: 89
               default: 114
          }
      64: aload_1
      65: getstatic     #70                 // Field org/jboss/as/ejb3/subsystem/EJB3SubsystemXMLAttribute.POOL_NAME:Lorg/jboss/as/ejb3/subsystem/EJB3SubsystemXMLAttribute;
      68: invokevirtual #71                 // Method org/jboss/as/ejb3/subsystem/EJB3SubsystemXMLAttribute.getLocalName:()Ljava/lang/String;
      71: invokestatic  #72                 // Method org/jboss/as/controller/parsing/ParseUtils.readStringAttributeElement:(Lorg/jboss/staxmapper/XMLExtendedStreamReader;Ljava/lang/String;)Ljava/lang/String;
      74: astore        4
      76: getstatic     #73                 // Field org/jboss/as/ejb3/subsystem/EJB3SubsystemRootResourceDefinition.DEFAULT_MDB_INSTANCE_POOL:Lorg/jboss/as/controller/SimpleAttributeDefinition;
      79: aload         4
      81: aload_3
      82: aload_1
      83: invokevirtual #51                 // Method org/jboss/as/controller/SimpleAttributeDefinition.parseAndSetParameter:(Ljava/lang/String;Lorg/jboss/dmr/ModelNode;Ljavax/xml/stream/XMLStreamReader;)V
      86: goto          4
      89: aload_1
      90: getstatic     #74                 // Field org/jboss/as/ejb3/subsystem/EJB3SubsystemXMLAttribute.RESOURCE_ADAPTER_NAME:Lorg/jboss/as/ejb3/subsystem/EJB3SubsystemXMLAttribute;
      93: invokevirtual #71                 // Method org/jboss/as/ejb3/subsystem/EJB3SubsystemXMLAttribute.getLocalName:()Ljava/lang/String;
      96: invokestatic  #72                 // Method org/jboss/as/controller/parsing/ParseUtils.readStringAttributeElement:(Lorg/jboss/staxmapper/XMLExtendedStreamReader;Ljava/lang/String;)Ljava/lang/String;
      99: astore        4
     101: getstatic     #75                 // Field org/jboss/as/ejb3/subsystem/EJB3SubsystemRootResourceDefinition.DEFAULT_RESOURCE_ADAPTER_NAME:Lorg/jboss/as/controller/SimpleAttributeDefinition;
     104: aload         4
     106: aload_3
     107: aload_1
     108: invokevirtual #51                 // Method org/jboss/as/controller/SimpleAttributeDefinition.parseAndSetParameter:(Ljava/lang/String;Lorg/jboss/dmr/ModelNode;Ljavax/xml/stream/XMLStreamReader;)V
     111: goto          4
     114: aload_1
     115: invokestatic  #19                 // Method org/jboss/as/controller/parsing/ParseUtils.unexpectedElement:(Lorg/jboss/staxmapper/XMLExtendedStreamReader;)Ljavax/xml/stream/XMLStreamException;
     118: athrow
     119: return

  private void parseEntityBean(org.jboss.staxmapper.XMLExtendedStreamReader, java.util.List<org.jboss.dmr.ModelNode>, org.jboss.dmr.ModelNode) throws javax.xml.stream.XMLStreamException;
    Code:
       0: aload_1
       1: invokestatic  #69                 // Method org/jboss/as/controller/parsing/ParseUtils.requireNoAttributes:(Lorg/jboss/staxmapper/XMLExtendedStreamReader;)V
       4: aload_1
       5: invokeinterface #13,  1           // InterfaceMethod org/jboss/staxmapper/XMLExtendedStreamReader.hasNext:()Z
      10: ifeq          119
      13: aload_1
      14: invokeinterface #14,  1           // InterfaceMethod org/jboss/staxmapper/XMLExtendedStreamReader.nextTag:()I
      19: iconst_2
      20: if_icmpeq     119
      23: getstatic     #24                 // Field org/jboss/as/ejb3/subsystem/EJB3Subsystem12Parser$1.$SwitchMap$org$jboss$as$ejb3$subsystem$EJB3SubsystemXMLElement:[I
      26: aload_1
      27: invokeinterface #20,  1           // InterfaceMethod org/jboss/staxmapper/XMLExtendedStreamReader.getLocalName:()Ljava/lang/String;
      32: invokestatic  #21                 // Method org/jboss/as/ejb3/subsystem/EJB3SubsystemXMLElement.forName:(Ljava/lang/String;)Lorg/jboss/as/ejb3/subsystem/EJB3SubsystemXMLElement;
      35: invokevirtual #25                 // Method org/jboss/as/ejb3/subsystem/EJB3SubsystemXMLElement.ordinal:()I
      38: iaload
      39: lookupswitch  { // 2
                    13: 64
                    15: 89
               default: 114
          }
      64: aload_1
      65: getstatic     #70                 // Field org/jboss/as/ejb3/subsystem/EJB3SubsystemXMLAttribute.POOL_NAME:Lorg/jboss/as/ejb3/subsystem/EJB3SubsystemXMLAttribute;
      68: invokevirtual #71                 // Method org/jboss/as/ejb3/subsystem/EJB3SubsystemXMLAttribute.getLocalName:()Ljava/lang/String;
      71: invokestatic  #72                 // Method org/jboss/as/controller/parsing/ParseUtils.readStringAttributeElement:(Lorg/jboss/staxmapper/XMLExtendedStreamReader;Ljava/lang/String;)Ljava/lang/String;
      74: astore        4
      76: getstatic     #76                 // Field org/jboss/as/ejb3/subsystem/EJB3SubsystemRootResourceDefinition.DEFAULT_ENTITY_BEAN_INSTANCE_POOL:Lorg/jboss/as/controller/SimpleAttributeDefinition;
      79: aload         4
      81: aload_3
      82: aload_1
      83: invokevirtual #51                 // Method org/jboss/as/controller/SimpleAttributeDefinition.parseAndSetParameter:(Ljava/lang/String;Lorg/jboss/dmr/ModelNode;Ljavax/xml/stream/XMLStreamReader;)V
      86: goto          4
      89: aload_1
      90: getstatic     #77                 // Field org/jboss/as/ejb3/subsystem/EJB3SubsystemXMLAttribute.ENABLED:Lorg/jboss/as/ejb3/subsystem/EJB3SubsystemXMLAttribute;
      93: invokevirtual #71                 // Method org/jboss/as/ejb3/subsystem/EJB3SubsystemXMLAttribute.getLocalName:()Ljava/lang/String;
      96: invokestatic  #72                 // Method org/jboss/as/controller/parsing/ParseUtils.readStringAttributeElement:(Lorg/jboss/staxmapper/XMLExtendedStreamReader;Ljava/lang/String;)Ljava/lang/String;
      99: astore        4
     101: getstatic     #78                 // Field org/jboss/as/ejb3/subsystem/EJB3SubsystemRootResourceDefinition.DEFAULT_ENTITY_BEAN_OPTIMISTIC_LOCKING:Lorg/jboss/as/controller/SimpleAttributeDefinition;
     104: aload         4
     106: aload_3
     107: aload_1
     108: invokevirtual #51                 // Method org/jboss/as/controller/SimpleAttributeDefinition.parseAndSetParameter:(Ljava/lang/String;Lorg/jboss/dmr/ModelNode;Ljavax/xml/stream/XMLStreamReader;)V
     111: goto          4
     114: aload_1
     115: invokestatic  #19                 // Method org/jboss/as/controller/parsing/ParseUtils.unexpectedElement:(Lorg/jboss/staxmapper/XMLExtendedStreamReader;)Ljavax/xml/stream/XMLStreamException;
     118: athrow
     119: return

  private void parseSessionBean(org.jboss.staxmapper.XMLExtendedStreamReader, java.util.List<org.jboss.dmr.ModelNode>, org.jboss.dmr.ModelNode) throws javax.xml.stream.XMLStreamException;
    Code:
       0: aload_1
       1: invokestatic  #69                 // Method org/jboss/as/controller/parsing/ParseUtils.requireNoAttributes:(Lorg/jboss/staxmapper/XMLExtendedStreamReader;)V
       4: aload_1
       5: invokeinterface #13,  1           // InterfaceMethod org/jboss/staxmapper/XMLExtendedStreamReader.hasNext:()Z
      10: ifeq          99
      13: aload_1
      14: invokeinterface #14,  1           // InterfaceMethod org/jboss/staxmapper/XMLExtendedStreamReader.nextTag:()I
      19: iconst_2
      20: if_icmpeq     99
      23: getstatic     #24                 // Field org/jboss/as/ejb3/subsystem/EJB3Subsystem12Parser$1.$SwitchMap$org$jboss$as$ejb3$subsystem$EJB3SubsystemXMLElement:[I
      26: aload_1
      27: invokeinterface #20,  1           // InterfaceMethod org/jboss/staxmapper/XMLExtendedStreamReader.getLocalName:()Ljava/lang/String;
      32: invokestatic  #21                 // Method org/jboss/as/ejb3/subsystem/EJB3SubsystemXMLElement.forName:(Ljava/lang/String;)Lorg/jboss/as/ejb3/subsystem/EJB3SubsystemXMLElement;
      35: invokevirtual #25                 // Method org/jboss/as/ejb3/subsystem/EJB3SubsystemXMLElement.ordinal:()I
      38: iaload
      39: tableswitch   { // 16 to 18
                    16: 64
                    17: 74
                    18: 84
               default: 94
          }
      64: aload_0
      65: aload_1
      66: aload_2
      67: aload_3
      68: invokespecial #79                 // Method parseStatelessBean:(Lorg/jboss/staxmapper/XMLExtendedStreamReader;Ljava/util/List;Lorg/jboss/dmr/ModelNode;)V
      71: goto          4
      74: aload_0
      75: aload_1
      76: aload_2
      77: aload_3
      78: invokevirtual #80                 // Method parseStatefulBean:(Lorg/jboss/staxmapper/XMLExtendedStreamReader;Ljava/util/List;Lorg/jboss/dmr/ModelNode;)V
      81: goto          4
      84: aload_0
      85: aload_1
      86: aload_2
      87: aload_3
      88: invokespecial #81                 // Method parseSingletonBean:(Lorg/jboss/staxmapper/XMLExtendedStreamReader;Ljava/util/List;Lorg/jboss/dmr/ModelNode;)V
      91: goto          4
      94: aload_1
      95: invokestatic  #19                 // Method org/jboss/as/controller/parsing/ParseUtils.unexpectedElement:(Lorg/jboss/staxmapper/XMLExtendedStreamReader;)Ljavax/xml/stream/XMLStreamException;
      98: athrow
      99: return

  private void parseStatelessBean(org.jboss.staxmapper.XMLExtendedStreamReader, java.util.List<org.jboss.dmr.ModelNode>, org.jboss.dmr.ModelNode) throws javax.xml.stream.XMLStreamException;
    Code:
       0: aload_1
       1: invokestatic  #69                 // Method org/jboss/as/controller/parsing/ParseUtils.requireNoAttributes:(Lorg/jboss/staxmapper/XMLExtendedStreamReader;)V
       4: aload_1
       5: invokeinterface #13,  1           // InterfaceMethod org/jboss/staxmapper/XMLExtendedStreamReader.hasNext:()Z
      10: ifeq          86
      13: aload_1
      14: invokeinterface #14,  1           // InterfaceMethod org/jboss/staxmapper/XMLExtendedStreamReader.nextTag:()I
      19: iconst_2
      20: if_icmpeq     86
      23: getstatic     #24                 // Field org/jboss/as/ejb3/subsystem/EJB3Subsystem12Parser$1.$SwitchMap$org$jboss$as$ejb3$subsystem$EJB3SubsystemXMLElement:[I
      26: aload_1
      27: invokeinterface #20,  1           // InterfaceMethod org/jboss/staxmapper/XMLExtendedStreamReader.getLocalName:()Ljava/lang/String;
      32: invokestatic  #21                 // Method org/jboss/as/ejb3/subsystem/EJB3SubsystemXMLElement.forName:(Ljava/lang/String;)Lorg/jboss/as/ejb3/subsystem/EJB3SubsystemXMLElement;
      35: invokevirtual #25                 // Method org/jboss/as/ejb3/subsystem/EJB3SubsystemXMLElement.ordinal:()I
      38: iaload
      39: lookupswitch  { // 1
                    13: 56
               default: 81
          }
      56: aload_1
      57: getstatic     #70                 // Field org/jboss/as/ejb3/subsystem/EJB3SubsystemXMLAttribute.POOL_NAME:Lorg/jboss/as/ejb3/subsystem/EJB3SubsystemXMLAttribute;
      60: invokevirtual #71                 // Method org/jboss/as/ejb3/subsystem/EJB3SubsystemXMLAttribute.getLocalName:()Ljava/lang/String;
      63: invokestatic  #72                 // Method org/jboss/as/controller/parsing/ParseUtils.readStringAttributeElement:(Lorg/jboss/staxmapper/XMLExtendedStreamReader;Ljava/lang/String;)Ljava/lang/String;
      66: astore        4
      68: getstatic     #82                 // Field org/jboss/as/ejb3/subsystem/EJB3SubsystemRootResourceDefinition.DEFAULT_SLSB_INSTANCE_POOL:Lorg/jboss/as/controller/SimpleAttributeDefinition;
      71: aload         4
      73: aload_3
      74: aload_1
      75: invokevirtual #51                 // Method org/jboss/as/controller/SimpleAttributeDefinition.parseAndSetParameter:(Ljava/lang/String;Lorg/jboss/dmr/ModelNode;Ljavax/xml/stream/XMLStreamReader;)V
      78: goto          4
      81: aload_1
      82: invokestatic  #19                 // Method org/jboss/as/controller/parsing/ParseUtils.unexpectedElement:(Lorg/jboss/staxmapper/XMLExtendedStreamReader;)Ljavax/xml/stream/XMLStreamException;
      85: athrow
      86: return

  protected void parseStatefulBean(org.jboss.staxmapper.XMLExtendedStreamReader, java.util.List<org.jboss.dmr.ModelNode>, org.jboss.dmr.ModelNode) throws javax.xml.stream.XMLStreamException;
    Code:
       0: aload_1
       1: invokeinterface #4,  1            // InterfaceMethod org/jboss/staxmapper/XMLExtendedStreamReader.getAttributeCount:()I
       6: istore        4
       8: getstatic     #83                 // Field org/jboss/as/ejb3/subsystem/EJB3SubsystemXMLAttribute.DEFAULT_ACCESS_TIMEOUT:Lorg/jboss/as/ejb3/subsystem/EJB3SubsystemXMLAttribute;
      11: getstatic     #84                 // Field org/jboss/as/ejb3/subsystem/EJB3SubsystemXMLAttribute.CACHE_REF:Lorg/jboss/as/ejb3/subsystem/EJB3SubsystemXMLAttribute;
      14: invokestatic  #43                 // Method java/util/EnumSet.of:(Ljava/lang/Enum;Ljava/lang/Enum;)Ljava/util/EnumSet;
      17: astore        5
      19: iconst_0
      20: istore        6
      22: iload         6
      24: iload         4
      26: if_icmpge     152
      29: aload_1
      30: iload         6
      32: invokestatic  #5                  // Method org/jboss/as/controller/parsing/ParseUtils.requireNoNamespaceAttribute:(Lorg/jboss/staxmapper/XMLExtendedStreamReader;I)V
      35: aload_1
      36: iload         6
      38: invokeinterface #44,  2           // InterfaceMethod org/jboss/staxmapper/XMLExtendedStreamReader.getAttributeValue:(I)Ljava/lang/String;
      43: astore        7
      45: aload_1
      46: iload         6
      48: invokeinterface #45,  2           // InterfaceMethod org/jboss/staxmapper/XMLExtendedStreamReader.getAttributeLocalName:(I)Ljava/lang/String;
      53: invokestatic  #46                 // Method org/jboss/as/ejb3/subsystem/EJB3SubsystemXMLAttribute.forName:(Ljava/lang/String;)Lorg/jboss/as/ejb3/subsystem/EJB3SubsystemXMLAttribute;
      56: astore        8
      58: getstatic     #48                 // Field org/jboss/as/ejb3/subsystem/EJB3Subsystem12Parser$1.$SwitchMap$org$jboss$as$ejb3$subsystem$EJB3SubsystemXMLAttribute:[I
      61: aload         8
      63: invokevirtual #49                 // Method org/jboss/as/ejb3/subsystem/EJB3SubsystemXMLAttribute.ordinal:()I
      66: iaload
      67: tableswitch   { // 5 to 7
                     5: 92
                     6: 105
                     7: 118
               default: 131
          }
      92: getstatic     #85                 // Field org/jboss/as/ejb3/subsystem/EJB3SubsystemRootResourceDefinition.DEFAULT_STATEFUL_BEAN_ACCESS_TIMEOUT:Lorg/jboss/as/controller/SimpleAttributeDefinition;
      95: aload         7
      97: aload_3
      98: aload_1
      99: invokevirtual #51                 // Method org/jboss/as/controller/SimpleAttributeDefinition.parseAndSetParameter:(Ljava/lang/String;Lorg/jboss/dmr/ModelNode;Ljavax/xml/stream/XMLStreamReader;)V
     102: goto          138
     105: getstatic     #86                 // Field org/jboss/as/ejb3/subsystem/EJB3SubsystemRootResourceDefinition.DEFAULT_SFSB_CACHE:Lorg/jboss/as/controller/SimpleAttributeDefinition;
     108: aload         7
     110: aload_3
     111: aload_1
     112: invokevirtual #51                 // Method org/jboss/as/controller/SimpleAttributeDefinition.parseAndSetParameter:(Ljava/lang/String;Lorg/jboss/dmr/ModelNode;Ljavax/xml/stream/XMLStreamReader;)V
     115: goto          138
     118: getstatic     #87                 // Field org/jboss/as/ejb3/subsystem/EJB3SubsystemRootResourceDefinition.DEFAULT_CLUSTERED_SFSB_CACHE:Lorg/jboss/as/controller/SimpleAttributeDefinition;
     121: aload         7
     123: aload_3
     124: aload_1
     125: invokevirtual #51                 // Method org/jboss/as/controller/SimpleAttributeDefinition.parseAndSetParameter:(Ljava/lang/String;Lorg/jboss/dmr/ModelNode;Ljavax/xml/stream/XMLStreamReader;)V
     128: goto          138
     131: aload_1
     132: iload         6
     134: invokestatic  #6                  // Method org/jboss/as/controller/parsing/ParseUtils.unexpectedAttribute:(Lorg/jboss/staxmapper/XMLExtendedStreamReader;I)Ljavax/xml/stream/XMLStreamException;
     137: athrow
     138: aload         5
     140: aload         8
     142: invokevirtual #47                 // Method java/util/EnumSet.remove:(Ljava/lang/Object;)Z
     145: pop
     146: iinc          6, 1
     149: goto          22
     152: aload_1
     153: invokestatic  #60                 // Method org/jboss/as/controller/parsing/ParseUtils.requireNoContent:(Lorg/jboss/staxmapper/XMLExtendedStreamReader;)V
     156: aload         5
     158: invokevirtual #53                 // Method java/util/EnumSet.isEmpty:()Z
     161: ifne          171
     164: aload_1
     165: aload         5
     167: invokestatic  #54                 // Method org/jboss/as/controller/parsing/ParseUtils.missingRequired:(Lorg/jboss/staxmapper/XMLExtendedStreamReader;Ljava/util/Set;)Ljavax/xml/stream/XMLStreamException;
     170: athrow
     171: return

  private void parseSingletonBean(org.jboss.staxmapper.XMLExtendedStreamReader, java.util.List<org.jboss.dmr.ModelNode>, org.jboss.dmr.ModelNode) throws javax.xml.stream.XMLStreamException;
    Code:
       0: aload_1
       1: invokeinterface #4,  1            // InterfaceMethod org/jboss/staxmapper/XMLExtendedStreamReader.getAttributeCount:()I
       6: istore        4
       8: getstatic     #83                 // Field org/jboss/as/ejb3/subsystem/EJB3SubsystemXMLAttribute.DEFAULT_ACCESS_TIMEOUT:Lorg/jboss/as/ejb3/subsystem/EJB3SubsystemXMLAttribute;
      11: invokestatic  #62                 // Method java/util/EnumSet.of:(Ljava/lang/Enum;)Ljava/util/EnumSet;
      14: astore        5
      16: iconst_0
      17: istore        6
      19: iload         6
      21: iload         4
      23: if_icmpge     119
      26: aload_1
      27: iload         6
      29: invokestatic  #5                  // Method org/jboss/as/controller/parsing/ParseUtils.requireNoNamespaceAttribute:(Lorg/jboss/staxmapper/XMLExtendedStreamReader;I)V
      32: aload_1
      33: iload         6
      35: invokeinterface #44,  2           // InterfaceMethod org/jboss/staxmapper/XMLExtendedStreamReader.getAttributeValue:(I)Ljava/lang/String;
      40: astore        7
      42: aload_1
      43: iload         6
      45: invokeinterface #45,  2           // InterfaceMethod org/jboss/staxmapper/XMLExtendedStreamReader.getAttributeLocalName:(I)Ljava/lang/String;
      50: invokestatic  #46                 // Method org/jboss/as/ejb3/subsystem/EJB3SubsystemXMLAttribute.forName:(Ljava/lang/String;)Lorg/jboss/as/ejb3/subsystem/EJB3SubsystemXMLAttribute;
      53: astore        8
      55: getstatic     #48                 // Field org/jboss/as/ejb3/subsystem/EJB3Subsystem12Parser$1.$SwitchMap$org$jboss$as$ejb3$subsystem$EJB3SubsystemXMLAttribute:[I
      58: aload         8
      60: invokevirtual #49                 // Method org/jboss/as/ejb3/subsystem/EJB3SubsystemXMLAttribute.ordinal:()I
      63: iaload
      64: lookupswitch  { // 1
                     5: 84
               default: 106
          }
      84: getstatic     #88                 // Field org/jboss/as/ejb3/subsystem/EJB3SubsystemRootResourceDefinition.DEFAULT_SINGLETON_BEAN_ACCESS_TIMEOUT:Lorg/jboss/as/controller/SimpleAttributeDefinition;
      87: aload         7
      89: aload_3
      90: aload_1
      91: invokevirtual #51                 // Method org/jboss/as/controller/SimpleAttributeDefinition.parseAndSetParameter:(Ljava/lang/String;Lorg/jboss/dmr/ModelNode;Ljavax/xml/stream/XMLStreamReader;)V
      94: aload         5
      96: getstatic     #83                 // Field org/jboss/as/ejb3/subsystem/EJB3SubsystemXMLAttribute.DEFAULT_ACCESS_TIMEOUT:Lorg/jboss/as/ejb3/subsystem/EJB3SubsystemXMLAttribute;
      99: invokevirtual #47                 // Method java/util/EnumSet.remove:(Ljava/lang/Object;)Z
     102: pop
     103: goto          113
     106: aload_1
     107: iload         6
     109: invokestatic  #6                  // Method org/jboss/as/controller/parsing/ParseUtils.unexpectedAttribute:(Lorg/jboss/staxmapper/XMLExtendedStreamReader;I)Ljavax/xml/stream/XMLStreamException;
     112: athrow
     113: iinc          6, 1
     116: goto          19
     119: aload_1
     120: invokestatic  #60                 // Method org/jboss/as/controller/parsing/ParseUtils.requireNoContent:(Lorg/jboss/staxmapper/XMLExtendedStreamReader;)V
     123: aload         5
     125: invokevirtual #53                 // Method java/util/EnumSet.isEmpty:()Z
     128: ifne          138
     131: aload_1
     132: aload         5
     134: invokestatic  #54                 // Method org/jboss/as/controller/parsing/ParseUtils.missingRequired:(Lorg/jboss/staxmapper/XMLExtendedStreamReader;Ljava/util/Set;)Ljavax/xml/stream/XMLStreamException;
     137: athrow
     138: return

  private void parsePools(org.jboss.staxmapper.XMLExtendedStreamReader, java.util.List<org.jboss.dmr.ModelNode>) throws javax.xml.stream.XMLStreamException;
    Code:
       0: aload_1
       1: invokestatic  #69                 // Method org/jboss/as/controller/parsing/ParseUtils.requireNoAttributes:(Lorg/jboss/staxmapper/XMLExtendedStreamReader;)V
       4: aload_1
       5: invokeinterface #13,  1           // InterfaceMethod org/jboss/staxmapper/XMLExtendedStreamReader.hasNext:()Z
      10: ifeq          70
      13: aload_1
      14: invokeinterface #14,  1           // InterfaceMethod org/jboss/staxmapper/XMLExtendedStreamReader.nextTag:()I
      19: iconst_2
      20: if_icmpeq     70
      23: getstatic     #24                 // Field org/jboss/as/ejb3/subsystem/EJB3Subsystem12Parser$1.$SwitchMap$org$jboss$as$ejb3$subsystem$EJB3SubsystemXMLElement:[I
      26: aload_1
      27: invokeinterface #20,  1           // InterfaceMethod org/jboss/staxmapper/XMLExtendedStreamReader.getLocalName:()Ljava/lang/String;
      32: invokestatic  #21                 // Method org/jboss/as/ejb3/subsystem/EJB3SubsystemXMLElement.forName:(Ljava/lang/String;)Lorg/jboss/as/ejb3/subsystem/EJB3SubsystemXMLElement;
      35: invokevirtual #25                 // Method org/jboss/as/ejb3/subsystem/EJB3SubsystemXMLElement.ordinal:()I
      38: iaload
      39: lookupswitch  { // 1
                    19: 56
               default: 65
          }
      56: aload_0
      57: aload_1
      58: aload_2
      59: invokespecial #89                 // Method parseBeanInstancePools:(Lorg/jboss/staxmapper/XMLExtendedStreamReader;Ljava/util/List;)V
      62: goto          4
      65: aload_1
      66: invokestatic  #19                 // Method org/jboss/as/controller/parsing/ParseUtils.unexpectedElement:(Lorg/jboss/staxmapper/XMLExtendedStreamReader;)Ljavax/xml/stream/XMLStreamException;
      69: athrow
      70: return

  private void parseBeanInstancePools(org.jboss.staxmapper.XMLExtendedStreamReader, java.util.List<org.jboss.dmr.ModelNode>) throws javax.xml.stream.XMLStreamException;
    Code:
       0: aload_1
       1: invokestatic  #69                 // Method org/jboss/as/controller/parsing/ParseUtils.requireNoAttributes:(Lorg/jboss/staxmapper/XMLExtendedStreamReader;)V
       4: aload_1
       5: invokeinterface #13,  1           // InterfaceMethod org/jboss/staxmapper/XMLExtendedStreamReader.hasNext:()Z
      10: ifeq          70
      13: aload_1
      14: invokeinterface #14,  1           // InterfaceMethod org/jboss/staxmapper/XMLExtendedStreamReader.nextTag:()I
      19: iconst_2
      20: if_icmpeq     70
      23: getstatic     #24                 // Field org/jboss/as/ejb3/subsystem/EJB3Subsystem12Parser$1.$SwitchMap$org$jboss$as$ejb3$subsystem$EJB3SubsystemXMLElement:[I
      26: aload_1
      27: invokeinterface #20,  1           // InterfaceMethod org/jboss/staxmapper/XMLExtendedStreamReader.getLocalName:()Ljava/lang/String;
      32: invokestatic  #21                 // Method org/jboss/as/ejb3/subsystem/EJB3SubsystemXMLElement.forName:(Ljava/lang/String;)Lorg/jboss/as/ejb3/subsystem/EJB3SubsystemXMLElement;
      35: invokevirtual #25                 // Method org/jboss/as/ejb3/subsystem/EJB3SubsystemXMLElement.ordinal:()I
      38: iaload
      39: lookupswitch  { // 1
                    20: 56
               default: 65
          }
      56: aload_0
      57: aload_1
      58: aload_2
      59: invokevirtual #90                 // Method parseStrictMaxPool:(Lorg/jboss/staxmapper/XMLExtendedStreamReader;Ljava/util/List;)V
      62: goto          4
      65: aload_1
      66: invokestatic  #19                 // Method org/jboss/as/controller/parsing/ParseUtils.unexpectedElement:(Lorg/jboss/staxmapper/XMLExtendedStreamReader;)Ljavax/xml/stream/XMLStreamException;
      69: athrow
      70: return

  void parseStrictMaxPool(org.jboss.staxmapper.XMLExtendedStreamReader, java.util.List<org.jboss.dmr.ModelNode>) throws javax.xml.stream.XMLStreamException;
    Code:
       0: aload_1
       1: invokeinterface #4,  1            // InterfaceMethod org/jboss/staxmapper/XMLExtendedStreamReader.getAttributeCount:()I
       6: istore_3
       7: aconst_null
       8: astore        4
      10: invokestatic  #91                 // Method org/jboss/as/controller/operations/common/Util.createAddOperation:()Lorg/jboss/dmr/ModelNode;
      13: astore        5
      15: iconst_0
      16: istore        6
      18: iload         6
      20: iload_3
      21: if_icmpge     154
      24: aload_1
      25: iload         6
      27: invokestatic  #5                  // Method org/jboss/as/controller/parsing/ParseUtils.requireNoNamespaceAttribute:(Lorg/jboss/staxmapper/XMLExtendedStreamReader;I)V
      30: aload_1
      31: iload         6
      33: invokeinterface #44,  2           // InterfaceMethod org/jboss/staxmapper/XMLExtendedStreamReader.getAttributeValue:(I)Ljava/lang/String;
      38: astore        7
      40: aload_1
      41: iload         6
      43: invokeinterface #45,  2           // InterfaceMethod org/jboss/staxmapper/XMLExtendedStreamReader.getAttributeLocalName:(I)Ljava/lang/String;
      48: invokestatic  #46                 // Method org/jboss/as/ejb3/subsystem/EJB3SubsystemXMLAttribute.forName:(Ljava/lang/String;)Lorg/jboss/as/ejb3/subsystem/EJB3SubsystemXMLAttribute;
      51: astore        8
      53: getstatic     #48                 // Field org/jboss/as/ejb3/subsystem/EJB3Subsystem12Parser$1.$SwitchMap$org$jboss$as$ejb3$subsystem$EJB3SubsystemXMLAttribute:[I
      56: aload         8
      58: invokevirtual #49                 // Method org/jboss/as/ejb3/subsystem/EJB3SubsystemXMLAttribute.ordinal:()I
      61: iaload
      62: tableswitch   { // 8 to 11
                     8: 92
                     9: 99
                    10: 113
                    11: 127
               default: 141
          }
      92: aload         7
      94: astore        4
      96: goto          148
      99: getstatic     #92                 // Field org/jboss/as/ejb3/subsystem/StrictMaxPoolResourceDefinition.MAX_POOL_SIZE:Lorg/jboss/as/controller/SimpleAttributeDefinition;
     102: aload         7
     104: aload         5
     106: aload_1
     107: invokevirtual #51                 // Method org/jboss/as/controller/SimpleAttributeDefinition.parseAndSetParameter:(Ljava/lang/String;Lorg/jboss/dmr/ModelNode;Ljavax/xml/stream/XMLStreamReader;)V
     110: goto          148
     113: getstatic     #93                 // Field org/jboss/as/ejb3/subsystem/StrictMaxPoolResourceDefinition.INSTANCE_ACQUISITION_TIMEOUT:Lorg/jboss/as/controller/SimpleAttributeDefinition;
     116: aload         7
     118: aload         5
     120: aload_1
     121: invokevirtual #51                 // Method org/jboss/as/controller/SimpleAttributeDefinition.parseAndSetParameter:(Ljava/lang/String;Lorg/jboss/dmr/ModelNode;Ljavax/xml/stream/XMLStreamReader;)V
     124: goto          148
     127: getstatic     #94                 // Field org/jboss/as/ejb3/subsystem/StrictMaxPoolResourceDefinition.INSTANCE_ACQUISITION_TIMEOUT_UNIT:Lorg/jboss/as/controller/SimpleAttributeDefinition;
     130: aload         7
     132: aload         5
     134: aload_1
     135: invokevirtual #51                 // Method org/jboss/as/controller/SimpleAttributeDefinition.parseAndSetParameter:(Ljava/lang/String;Lorg/jboss/dmr/ModelNode;Ljavax/xml/stream/XMLStreamReader;)V
     138: goto          148
     141: aload_1
     142: iload         6
     144: invokestatic  #6                  // Method org/jboss/as/controller/parsing/ParseUtils.unexpectedAttribute:(Lorg/jboss/staxmapper/XMLExtendedStreamReader;I)Ljavax/xml/stream/XMLStreamException;
     147: athrow
     148: iinc          6, 1
     151: goto          18
     154: aload_1
     155: invokestatic  #60                 // Method org/jboss/as/controller/parsing/ParseUtils.requireNoContent:(Lorg/jboss/staxmapper/XMLExtendedStreamReader;)V
     158: aload         4
     160: ifnonnull     177
     163: aload_1
     164: getstatic     #95                 // Field org/jboss/as/ejb3/subsystem/EJB3SubsystemXMLAttribute.NAME:Lorg/jboss/as/ejb3/subsystem/EJB3SubsystemXMLAttribute;
     167: invokevirtual #71                 // Method org/jboss/as/ejb3/subsystem/EJB3SubsystemXMLAttribute.getLocalName:()Ljava/lang/String;
     170: invokestatic  #96                 // Method java/util/Collections.singleton:(Ljava/lang/Object;)Ljava/util/Set;
     173: invokestatic  #54                 // Method org/jboss/as/controller/parsing/ParseUtils.missingRequired:(Lorg/jboss/staxmapper/XMLExtendedStreamReader;Ljava/util/Set;)Ljavax/xml/stream/XMLStreamException;
     176: athrow
     177: aload_0
     178: invokevirtual #97                 // Method getEJB3SubsystemAddress:()Lorg/jboss/as/controller/PathAddress;
     181: ldc           #98                 // String strict-max-bean-instance-pool
     183: aload         4
     185: invokevirtual #40                 // Method org/jboss/as/controller/PathAddress.append:(Ljava/lang/String;Ljava/lang/String;)Lorg/jboss/as/controller/PathAddress;
     188: astore        6
     190: aload         5
     192: ldc           #99                 // String address
     194: invokevirtual #56                 // Method org/jboss/dmr/ModelNode.get:(Ljava/lang/String;)Lorg/jboss/dmr/ModelNode;
     197: aload         6
     199: invokevirtual #100                // Method org/jboss/as/controller/PathAddress.toModelNode:()Lorg/jboss/dmr/ModelNode;
     202: invokevirtual #59                 // Method org/jboss/dmr/ModelNode.set:(Lorg/jboss/dmr/ModelNode;)Lorg/jboss/dmr/ModelNode;
     205: pop
     206: aload_2
     207: aload         5
     209: invokeinterface #9,  2            // InterfaceMethod java/util/List.add:(Ljava/lang/Object;)Z
     214: pop
     215: return

  private void parseCaches(org.jboss.staxmapper.XMLExtendedStreamReader, java.util.List<org.jboss.dmr.ModelNode>) throws javax.xml.stream.XMLStreamException;
    Code:
       0: aload_1
       1: invokestatic  #69                 // Method org/jboss/as/controller/parsing/ParseUtils.requireNoAttributes:(Lorg/jboss/staxmapper/XMLExtendedStreamReader;)V
       4: aload_1
       5: invokeinterface #13,  1           // InterfaceMethod org/jboss/staxmapper/XMLExtendedStreamReader.hasNext:()Z
      10: ifeq          70
      13: aload_1
      14: invokeinterface #14,  1           // InterfaceMethod org/jboss/staxmapper/XMLExtendedStreamReader.nextTag:()I
      19: iconst_2
      20: if_icmpeq     70
      23: getstatic     #24                 // Field org/jboss/as/ejb3/subsystem/EJB3Subsystem12Parser$1.$SwitchMap$org$jboss$as$ejb3$subsystem$EJB3SubsystemXMLElement:[I
      26: aload_1
      27: invokeinterface #20,  1           // InterfaceMethod org/jboss/staxmapper/XMLExtendedStreamReader.getLocalName:()Ljava/lang/String;
      32: invokestatic  #21                 // Method org/jboss/as/ejb3/subsystem/EJB3SubsystemXMLElement.forName:(Ljava/lang/String;)Lorg/jboss/as/ejb3/subsystem/EJB3SubsystemXMLElement;
      35: invokevirtual #25                 // Method org/jboss/as/ejb3/subsystem/EJB3SubsystemXMLElement.ordinal:()I
      38: iaload
      39: lookupswitch  { // 1
                    21: 56
               default: 65
          }
      56: aload_0
      57: aload_1
      58: aload_2
      59: invokespecial #101                // Method parseCache:(Lorg/jboss/staxmapper/XMLExtendedStreamReader;Ljava/util/List;)V
      62: goto          4
      65: aload_1
      66: invokestatic  #19                 // Method org/jboss/as/controller/parsing/ParseUtils.unexpectedElement:(Lorg/jboss/staxmapper/XMLExtendedStreamReader;)Ljavax/xml/stream/XMLStreamException;
      69: athrow
      70: return

  private void parseCache(org.jboss.staxmapper.XMLExtendedStreamReader, java.util.List<org.jboss.dmr.ModelNode>) throws javax.xml.stream.XMLStreamException;
    Code:
       0: aconst_null
       1: astore_3
       2: invokestatic  #91                 // Method org/jboss/as/controller/operations/common/Util.createAddOperation:()Lorg/jboss/dmr/ModelNode;
       5: astore        4
       7: iconst_0
       8: istore        5
      10: iload         5
      12: aload_1
      13: invokeinterface #4,  1            // InterfaceMethod org/jboss/staxmapper/XMLExtendedStreamReader.getAttributeCount:()I
      18: if_icmpge     175
      21: aload_1
      22: iload         5
      24: invokestatic  #5                  // Method org/jboss/as/controller/parsing/ParseUtils.requireNoNamespaceAttribute:(Lorg/jboss/staxmapper/XMLExtendedStreamReader;I)V
      27: aload_1
      28: iload         5
      30: invokeinterface #44,  2           // InterfaceMethod org/jboss/staxmapper/XMLExtendedStreamReader.getAttributeValue:(I)Ljava/lang/String;
      35: astore        6
      37: getstatic     #48                 // Field org/jboss/as/ejb3/subsystem/EJB3Subsystem12Parser$1.$SwitchMap$org$jboss$as$ejb3$subsystem$EJB3SubsystemXMLAttribute:[I
      40: aload_1
      41: iload         5
      43: invokeinterface #45,  2           // InterfaceMethod org/jboss/staxmapper/XMLExtendedStreamReader.getAttributeLocalName:(I)Ljava/lang/String;
      48: invokestatic  #46                 // Method org/jboss/as/ejb3/subsystem/EJB3SubsystemXMLAttribute.forName:(Ljava/lang/String;)Lorg/jboss/as/ejb3/subsystem/EJB3SubsystemXMLAttribute;
      51: invokevirtual #49                 // Method org/jboss/as/ejb3/subsystem/EJB3SubsystemXMLAttribute.ordinal:()I
      54: iaload
      55: lookupswitch  { // 3
                     8: 88
                    12: 94
                    13: 108
               default: 162
          }
      88: aload         6
      90: astore_3
      91: goto          169
      94: getstatic     #102                // Field org/jboss/as/ejb3/subsystem/CacheFactoryResourceDefinition.PASSIVATION_STORE:Lorg/jboss/as/controller/SimpleAttributeDefinition;
      97: aload         6
      99: aload         4
     101: aload_1
     102: invokevirtual #51                 // Method org/jboss/as/controller/SimpleAttributeDefinition.parseAndSetParameter:(Ljava/lang/String;Lorg/jboss/dmr/ModelNode;Ljavax/xml/stream/XMLStreamReader;)V
     105: goto          169
     108: aload_1
     109: iload         5
     111: invokeinterface #103,  2          // InterfaceMethod org/jboss/staxmapper/XMLExtendedStreamReader.getListAttributeValue:(I)Ljava/util/List;
     116: invokeinterface #104,  1          // InterfaceMethod java/util/List.iterator:()Ljava/util/Iterator;
     121: astore        7
     123: aload         7
     125: invokeinterface #105,  1          // InterfaceMethod java/util/Iterator.hasNext:()Z
     130: ifeq          159
     133: aload         7
     135: invokeinterface #106,  1          // InterfaceMethod java/util/Iterator.next:()Ljava/lang/Object;
     140: checkcast     #107                // class java/lang/String
     143: astore        8
     145: getstatic     #108                // Field org/jboss/as/ejb3/subsystem/CacheFactoryResourceDefinition.ALIASES:Lorg/jboss/as/controller/StringListAttributeDefinition;
     148: aload         8
     150: aload         4
     152: aload_1
     153: invokevirtual #109                // Method org/jboss/as/controller/StringListAttributeDefinition.parseAndAddParameterElement:(Ljava/lang/String;Lorg/jboss/dmr/ModelNode;Ljavax/xml/stream/XMLStreamReader;)V
     156: goto          123
     159: goto          169
     162: aload_1
     163: iload         5
     165: invokestatic  #6                  // Method org/jboss/as/controller/parsing/ParseUtils.unexpectedAttribute:(Lorg/jboss/staxmapper/XMLExtendedStreamReader;I)Ljavax/xml/stream/XMLStreamException;
     168: athrow
     169: iinc          5, 1
     172: goto          10
     175: aload_1
     176: invokestatic  #60                 // Method org/jboss/as/controller/parsing/ParseUtils.requireNoContent:(Lorg/jboss/staxmapper/XMLExtendedStreamReader;)V
     179: aload_3
     180: ifnonnull     197
     183: aload_1
     184: getstatic     #95                 // Field org/jboss/as/ejb3/subsystem/EJB3SubsystemXMLAttribute.NAME:Lorg/jboss/as/ejb3/subsystem/EJB3SubsystemXMLAttribute;
     187: invokevirtual #71                 // Method org/jboss/as/ejb3/subsystem/EJB3SubsystemXMLAttribute.getLocalName:()Ljava/lang/String;
     190: invokestatic  #96                 // Method java/util/Collections.singleton:(Ljava/lang/Object;)Ljava/util/Set;
     193: invokestatic  #54                 // Method org/jboss/as/controller/parsing/ParseUtils.missingRequired:(Lorg/jboss/staxmapper/XMLExtendedStreamReader;Ljava/util/Set;)Ljavax/xml/stream/XMLStreamException;
     196: athrow
     197: aload_0
     198: invokevirtual #97                 // Method getEJB3SubsystemAddress:()Lorg/jboss/as/controller/PathAddress;
     201: iconst_1
     202: anewarray     #110                // class org/jboss/as/controller/PathElement
     205: dup
     206: iconst_0
     207: ldc           #111                // String cache
     209: aload_3
     210: invokestatic  #112                // Method org/jboss/as/controller/PathElement.pathElement:(Ljava/lang/String;Ljava/lang/String;)Lorg/jboss/as/controller/PathElement;
     213: aastore
     214: invokevirtual #113                // Method org/jboss/as/controller/PathAddress.append:([Lorg/jboss/as/controller/PathElement;)Lorg/jboss/as/controller/PathAddress;
     217: astore        5
     219: aload         4
     221: ldc           #99                 // String address
     223: invokevirtual #56                 // Method org/jboss/dmr/ModelNode.get:(Ljava/lang/String;)Lorg/jboss/dmr/ModelNode;
     226: aload         5
     228: invokevirtual #100                // Method org/jboss/as/controller/PathAddress.toModelNode:()Lorg/jboss/dmr/ModelNode;
     231: invokevirtual #59                 // Method org/jboss/dmr/ModelNode.set:(Lorg/jboss/dmr/ModelNode;)Lorg/jboss/dmr/ModelNode;
     234: pop
     235: aload_2
     236: aload         4
     238: invokeinterface #9,  2            // InterfaceMethod java/util/List.add:(Ljava/lang/Object;)Z
     243: pop
     244: return

  protected void parsePassivationStores(org.jboss.staxmapper.XMLExtendedStreamReader, java.util.List<org.jboss.dmr.ModelNode>) throws javax.xml.stream.XMLStreamException;
    Code:
       0: aload_1
       1: invokestatic  #69                 // Method org/jboss/as/controller/parsing/ParseUtils.requireNoAttributes:(Lorg/jboss/staxmapper/XMLExtendedStreamReader;)V
       4: aload_1
       5: invokeinterface #13,  1           // InterfaceMethod org/jboss/staxmapper/XMLExtendedStreamReader.hasNext:()Z
      10: ifeq          87
      13: aload_1
      14: invokeinterface #14,  1           // InterfaceMethod org/jboss/staxmapper/XMLExtendedStreamReader.nextTag:()I
      19: iconst_2
      20: if_icmpeq     87
      23: getstatic     #24                 // Field org/jboss/as/ejb3/subsystem/EJB3Subsystem12Parser$1.$SwitchMap$org$jboss$as$ejb3$subsystem$EJB3SubsystemXMLElement:[I
      26: aload_1
      27: invokeinterface #20,  1           // InterfaceMethod org/jboss/staxmapper/XMLExtendedStreamReader.getLocalName:()Ljava/lang/String;
      32: invokestatic  #21                 // Method org/jboss/as/ejb3/subsystem/EJB3SubsystemXMLElement.forName:(Ljava/lang/String;)Lorg/jboss/as/ejb3/subsystem/EJB3SubsystemXMLElement;
      35: invokevirtual #25                 // Method org/jboss/as/ejb3/subsystem/EJB3SubsystemXMLElement.ordinal:()I
      38: iaload
      39: lookupswitch  { // 2
                    22: 64
                    23: 73
               default: 82
          }
      64: aload_0
      65: aload_1
      66: aload_2
      67: invokevirtual #114                // Method parseFilePassivationStore:(Lorg/jboss/staxmapper/XMLExtendedStreamReader;Ljava/util/List;)V
      70: goto          4
      73: aload_0
      74: aload_1
      75: aload_2
      76: invokevirtual #115                // Method parseClusterPassivationStore:(Lorg/jboss/staxmapper/XMLExtendedStreamReader;Ljava/util/List;)V
      79: goto          4
      82: aload_1
      83: invokestatic  #19                 // Method org/jboss/as/controller/parsing/ParseUtils.unexpectedElement:(Lorg/jboss/staxmapper/XMLExtendedStreamReader;)Ljavax/xml/stream/XMLStreamException;
      86: athrow
      87: return

  protected void parseFilePassivationStore(org.jboss.staxmapper.XMLExtendedStreamReader, java.util.List<org.jboss.dmr.ModelNode>) throws javax.xml.stream.XMLStreamException;
    Code:
       0: aconst_null
       1: astore_3
       2: invokestatic  #91                 // Method org/jboss/as/controller/operations/common/Util.createAddOperation:()Lorg/jboss/dmr/ModelNode;
       5: astore        4
       7: iconst_0
       8: istore        5
      10: iload         5
      12: aload_1
      13: invokeinterface #4,  1            // InterfaceMethod org/jboss/staxmapper/XMLExtendedStreamReader.getAttributeCount:()I
      18: if_icmpge     237
      21: aload_1
      22: iload         5
      24: invokestatic  #5                  // Method org/jboss/as/controller/parsing/ParseUtils.requireNoNamespaceAttribute:(Lorg/jboss/staxmapper/XMLExtendedStreamReader;I)V
      27: aload_1
      28: iload         5
      30: invokeinterface #44,  2           // InterfaceMethod org/jboss/staxmapper/XMLExtendedStreamReader.getAttributeValue:(I)Ljava/lang/String;
      35: astore        6
      37: getstatic     #48                 // Field org/jboss/as/ejb3/subsystem/EJB3Subsystem12Parser$1.$SwitchMap$org$jboss$as$ejb3$subsystem$EJB3SubsystemXMLAttribute:[I
      40: aload_1
      41: iload         5
      43: invokeinterface #45,  2           // InterfaceMethod org/jboss/staxmapper/XMLExtendedStreamReader.getAttributeLocalName:(I)Ljava/lang/String;
      48: invokestatic  #46                 // Method org/jboss/as/ejb3/subsystem/EJB3SubsystemXMLAttribute.forName:(Ljava/lang/String;)Lorg/jboss/as/ejb3/subsystem/EJB3SubsystemXMLAttribute;
      51: invokevirtual #49                 // Method org/jboss/as/ejb3/subsystem/EJB3SubsystemXMLAttribute.ordinal:()I
      54: iaload
      55: tableswitch   { // 8 to 20
                     8: 120
                     9: 224
                    10: 224
                    11: 224
                    12: 224
                    13: 224
                    14: 126
                    15: 140
                    16: 154
                    17: 168
                    18: 182
                    19: 196
                    20: 210
               default: 224
          }
     120: aload         6
     122: astore_3
     123: goto          231
     126: getstatic     #116                // Field org/jboss/as/ejb3/subsystem/FilePassivationStoreResourceDefinition.MAX_SIZE:Lorg/jboss/as/controller/SimpleAttributeDefinition;
     129: aload         6
     131: aload         4
     133: aload_1
     134: invokevirtual #51                 // Method org/jboss/as/controller/SimpleAttributeDefinition.parseAndSetParameter:(Ljava/lang/String;Lorg/jboss/dmr/ModelNode;Ljavax/xml/stream/XMLStreamReader;)V
     137: goto          231
     140: getstatic     #117                // Field org/jboss/as/ejb3/subsystem/LegacyPassivationStoreResourceDefinition.IDLE_TIMEOUT:Lorg/jboss/as/controller/SimpleAttributeDefinition;
     143: aload         6
     145: aload         4
     147: aload_1
     148: invokevirtual #51                 // Method org/jboss/as/controller/SimpleAttributeDefinition.parseAndSetParameter:(Ljava/lang/String;Lorg/jboss/dmr/ModelNode;Ljavax/xml/stream/XMLStreamReader;)V
     151: goto          231
     154: getstatic     #118                // Field org/jboss/as/ejb3/subsystem/LegacyPassivationStoreResourceDefinition.IDLE_TIMEOUT_UNIT:Lorg/jboss/as/controller/SimpleAttributeDefinition;
     157: aload         6
     159: aload         4
     161: aload_1
     162: invokevirtual #51                 // Method org/jboss/as/controller/SimpleAttributeDefinition.parseAndSetParameter:(Ljava/lang/String;Lorg/jboss/dmr/ModelNode;Ljavax/xml/stream/XMLStreamReader;)V
     165: goto          231
     168: getstatic     #119                // Field org/jboss/as/ejb3/subsystem/FilePassivationStoreResourceDefinition.RELATIVE_TO:Lorg/jboss/as/controller/SimpleAttributeDefinition;
     171: aload         6
     173: aload         4
     175: aload_1
     176: invokevirtual #51                 // Method org/jboss/as/controller/SimpleAttributeDefinition.parseAndSetParameter:(Ljava/lang/String;Lorg/jboss/dmr/ModelNode;Ljavax/xml/stream/XMLStreamReader;)V
     179: goto          231
     182: getstatic     #120                // Field org/jboss/as/ejb3/subsystem/FilePassivationStoreResourceDefinition.GROUPS_PATH:Lorg/jboss/as/controller/SimpleAttributeDefinition;
     185: aload         6
     187: aload         4
     189: aload_1
     190: invokevirtual #51                 // Method org/jboss/as/controller/SimpleAttributeDefinition.parseAndSetParameter:(Ljava/lang/String;Lorg/jboss/dmr/ModelNode;Ljavax/xml/stream/XMLStreamReader;)V
     193: goto          231
     196: getstatic     #121                // Field org/jboss/as/ejb3/subsystem/FilePassivationStoreResourceDefinition.SESSIONS_PATH:Lorg/jboss/as/controller/SimpleAttributeDefinition;
     199: aload         6
     201: aload         4
     203: aload_1
     204: invokevirtual #51                 // Method org/jboss/as/controller/SimpleAttributeDefinition.parseAndSetParameter:(Ljava/lang/String;Lorg/jboss/dmr/ModelNode;Ljavax/xml/stream/XMLStreamReader;)V
     207: goto          231
     210: getstatic     #122                // Field org/jboss/as/ejb3/subsystem/FilePassivationStoreResourceDefinition.SUBDIRECTORY_COUNT:Lorg/jboss/as/controller/SimpleAttributeDefinition;
     213: aload         6
     215: aload         4
     217: aload_1
     218: invokevirtual #51                 // Method org/jboss/as/controller/SimpleAttributeDefinition.parseAndSetParameter:(Ljava/lang/String;Lorg/jboss/dmr/ModelNode;Ljavax/xml/stream/XMLStreamReader;)V
     221: goto          231
     224: aload_1
     225: iload         5
     227: invokestatic  #6                  // Method org/jboss/as/controller/parsing/ParseUtils.unexpectedAttribute:(Lorg/jboss/staxmapper/XMLExtendedStreamReader;I)Ljavax/xml/stream/XMLStreamException;
     230: athrow
     231: iinc          5, 1
     234: goto          10
     237: aload_1
     238: invokestatic  #60                 // Method org/jboss/as/controller/parsing/ParseUtils.requireNoContent:(Lorg/jboss/staxmapper/XMLExtendedStreamReader;)V
     241: aload_3
     242: ifnonnull     259
     245: aload_1
     246: getstatic     #95                 // Field org/jboss/as/ejb3/subsystem/EJB3SubsystemXMLAttribute.NAME:Lorg/jboss/as/ejb3/subsystem/EJB3SubsystemXMLAttribute;
     249: invokevirtual #71                 // Method org/jboss/as/ejb3/subsystem/EJB3SubsystemXMLAttribute.getLocalName:()Ljava/lang/String;
     252: invokestatic  #96                 // Method java/util/Collections.singleton:(Ljava/lang/Object;)Ljava/util/Set;
     255: invokestatic  #54                 // Method org/jboss/as/controller/parsing/ParseUtils.missingRequired:(Lorg/jboss/staxmapper/XMLExtendedStreamReader;Ljava/util/Set;)Ljavax/xml/stream/XMLStreamException;
     258: athrow
     259: aload         4
     261: ldc           #99                 // String address
     263: invokevirtual #56                 // Method org/jboss/dmr/ModelNode.get:(Ljava/lang/String;)Lorg/jboss/dmr/ModelNode;
     266: getstatic     #7                  // Field SUBSYSTEM_PATH:Lorg/jboss/as/controller/PathAddress;
     269: ldc           #123                // String file-passivation-store
     271: aload_3
     272: invokevirtual #40                 // Method org/jboss/as/controller/PathAddress.append:(Ljava/lang/String;Ljava/lang/String;)Lorg/jboss/as/controller/PathAddress;
     275: invokevirtual #100                // Method org/jboss/as/controller/PathAddress.toModelNode:()Lorg/jboss/dmr/ModelNode;
     278: invokevirtual #59                 // Method org/jboss/dmr/ModelNode.set:(Lorg/jboss/dmr/ModelNode;)Lorg/jboss/dmr/ModelNode;
     281: pop
     282: aload_2
     283: aload         4
     285: invokeinterface #9,  2            // InterfaceMethod java/util/List.add:(Ljava/lang/Object;)Z
     290: pop
     291: return

  protected void parseClusterPassivationStore(org.jboss.staxmapper.XMLExtendedStreamReader, java.util.List<org.jboss.dmr.ModelNode>) throws javax.xml.stream.XMLStreamException;
    Code:
       0: aconst_null
       1: astore_3
       2: invokestatic  #91                 // Method org/jboss/as/controller/operations/common/Util.createAddOperation:()Lorg/jboss/dmr/ModelNode;
       5: astore        4
       7: iconst_0
       8: istore        5
      10: iload         5
      12: aload_1
      13: invokeinterface #4,  1            // InterfaceMethod org/jboss/staxmapper/XMLExtendedStreamReader.getAttributeCount:()I
      18: if_icmpge     253
      21: aload_1
      22: iload         5
      24: invokestatic  #5                  // Method org/jboss/as/controller/parsing/ParseUtils.requireNoNamespaceAttribute:(Lorg/jboss/staxmapper/XMLExtendedStreamReader;I)V
      27: aload_1
      28: iload         5
      30: invokeinterface #44,  2           // InterfaceMethod org/jboss/staxmapper/XMLExtendedStreamReader.getAttributeValue:(I)Ljava/lang/String;
      35: astore        6
      37: getstatic     #48                 // Field org/jboss/as/ejb3/subsystem/EJB3Subsystem12Parser$1.$SwitchMap$org$jboss$as$ejb3$subsystem$EJB3SubsystemXMLAttribute:[I
      40: aload_1
      41: iload         5
      43: invokeinterface #45,  2           // InterfaceMethod org/jboss/staxmapper/XMLExtendedStreamReader.getAttributeLocalName:(I)Ljava/lang/String;
      48: invokestatic  #46                 // Method org/jboss/as/ejb3/subsystem/EJB3SubsystemXMLAttribute.forName:(Ljava/lang/String;)Lorg/jboss/as/ejb3/subsystem/EJB3SubsystemXMLAttribute;
      51: invokevirtual #49                 // Method org/jboss/as/ejb3/subsystem/EJB3SubsystemXMLAttribute.ordinal:()I
      54: iaload
      55: tableswitch   { // 8 to 24
                     8: 136
                     9: 240
                    10: 240
                    11: 240
                    12: 240
                    13: 240
                    14: 142
                    15: 156
                    16: 170
                    17: 240
                    18: 240
                    19: 240
                    20: 240
                    21: 184
                    22: 198
                    23: 212
                    24: 226
               default: 240
          }
     136: aload         6
     138: astore_3
     139: goto          247
     142: getstatic     #124                // Field org/jboss/as/ejb3/subsystem/ClusterPassivationStoreResourceDefinition.MAX_SIZE:Lorg/jboss/as/controller/SimpleAttributeDefinition;
     145: aload         6
     147: aload         4
     149: aload_1
     150: invokevirtual #51                 // Method org/jboss/as/controller/SimpleAttributeDefinition.parseAndSetParameter:(Ljava/lang/String;Lorg/jboss/dmr/ModelNode;Ljavax/xml/stream/XMLStreamReader;)V
     153: goto          247
     156: getstatic     #117                // Field org/jboss/as/ejb3/subsystem/LegacyPassivationStoreResourceDefinition.IDLE_TIMEOUT:Lorg/jboss/as/controller/SimpleAttributeDefinition;
     159: aload         6
     161: aload         4
     163: aload_1
     164: invokevirtual #51                 // Method org/jboss/as/controller/SimpleAttributeDefinition.parseAndSetParameter:(Ljava/lang/String;Lorg/jboss/dmr/ModelNode;Ljavax/xml/stream/XMLStreamReader;)V
     167: goto          247
     170: getstatic     #118                // Field org/jboss/as/ejb3/subsystem/LegacyPassivationStoreResourceDefinition.IDLE_TIMEOUT_UNIT:Lorg/jboss/as/controller/SimpleAttributeDefinition;
     173: aload         6
     175: aload         4
     177: aload_1
     178: invokevirtual #51                 // Method org/jboss/as/controller/SimpleAttributeDefinition.parseAndSetParameter:(Ljava/lang/String;Lorg/jboss/dmr/ModelNode;Ljavax/xml/stream/XMLStreamReader;)V
     181: goto          247
     184: getstatic     #125                // Field org/jboss/as/ejb3/subsystem/ClusterPassivationStoreResourceDefinition.CACHE_CONTAINER:Lorg/jboss/as/controller/SimpleAttributeDefinition;
     187: aload         6
     189: aload         4
     191: aload_1
     192: invokevirtual #51                 // Method org/jboss/as/controller/SimpleAttributeDefinition.parseAndSetParameter:(Ljava/lang/String;Lorg/jboss/dmr/ModelNode;Ljavax/xml/stream/XMLStreamReader;)V
     195: goto          247
     198: getstatic     #126                // Field org/jboss/as/ejb3/subsystem/ClusterPassivationStoreResourceDefinition.BEAN_CACHE:Lorg/jboss/as/controller/SimpleAttributeDefinition;
     201: aload         6
     203: aload         4
     205: aload_1
     206: invokevirtual #51                 // Method org/jboss/as/controller/SimpleAttributeDefinition.parseAndSetParameter:(Ljava/lang/String;Lorg/jboss/dmr/ModelNode;Ljavax/xml/stream/XMLStreamReader;)V
     209: goto          247
     212: getstatic     #127                // Field org/jboss/as/ejb3/subsystem/ClusterPassivationStoreResourceDefinition.CLIENT_MAPPINGS_CACHE:Lorg/jboss/as/controller/SimpleAttributeDefinition;
     215: aload         6
     217: aload         4
     219: aload_1
     220: invokevirtual #51                 // Method org/jboss/as/controller/SimpleAttributeDefinition.parseAndSetParameter:(Ljava/lang/String;Lorg/jboss/dmr/ModelNode;Ljavax/xml/stream/XMLStreamReader;)V
     223: goto          247
     226: getstatic     #128                // Field org/jboss/as/ejb3/subsystem/ClusterPassivationStoreResourceDefinition.PASSIVATE_EVENTS_ON_REPLICATE:Lorg/jboss/as/controller/SimpleAttributeDefinition;
     229: aload         6
     231: aload         4
     233: aload_1
     234: invokevirtual #51                 // Method org/jboss/as/controller/SimpleAttributeDefinition.parseAndSetParameter:(Ljava/lang/String;Lorg/jboss/dmr/ModelNode;Ljavax/xml/stream/XMLStreamReader;)V
     237: goto          247
     240: aload_1
     241: iload         5
     243: invokestatic  #6                  // Method org/jboss/as/controller/parsing/ParseUtils.unexpectedAttribute:(Lorg/jboss/staxmapper/XMLExtendedStreamReader;I)Ljavax/xml/stream/XMLStreamException;
     246: athrow
     247: iinc          5, 1
     250: goto          10
     253: aload_1
     254: invokestatic  #60                 // Method org/jboss/as/controller/parsing/ParseUtils.requireNoContent:(Lorg/jboss/staxmapper/XMLExtendedStreamReader;)V
     257: aload_3
     258: ifnonnull     275
     261: aload_1
     262: getstatic     #95                 // Field org/jboss/as/ejb3/subsystem/EJB3SubsystemXMLAttribute.NAME:Lorg/jboss/as/ejb3/subsystem/EJB3SubsystemXMLAttribute;
     265: invokevirtual #71                 // Method org/jboss/as/ejb3/subsystem/EJB3SubsystemXMLAttribute.getLocalName:()Ljava/lang/String;
     268: invokestatic  #96                 // Method java/util/Collections.singleton:(Ljava/lang/Object;)Ljava/util/Set;
     271: invokestatic  #54                 // Method org/jboss/as/controller/parsing/ParseUtils.missingRequired:(Lorg/jboss/staxmapper/XMLExtendedStreamReader;Ljava/util/Set;)Ljavax/xml/stream/XMLStreamException;
     274: athrow
     275: aload         4
     277: ldc           #99                 // String address
     279: invokevirtual #56                 // Method org/jboss/dmr/ModelNode.get:(Ljava/lang/String;)Lorg/jboss/dmr/ModelNode;
     282: getstatic     #7                  // Field SUBSYSTEM_PATH:Lorg/jboss/as/controller/PathAddress;
     285: ldc           #129                // String cluster-passivation-store
     287: aload_3
     288: invokevirtual #40                 // Method org/jboss/as/controller/PathAddress.append:(Ljava/lang/String;Ljava/lang/String;)Lorg/jboss/as/controller/PathAddress;
     291: invokevirtual #100                // Method org/jboss/as/controller/PathAddress.toModelNode:()Lorg/jboss/dmr/ModelNode;
     294: invokevirtual #59                 // Method org/jboss/dmr/ModelNode.set:(Lorg/jboss/dmr/ModelNode;)Lorg/jboss/dmr/ModelNode;
     297: pop
     298: aload_2
     299: aload         4
     301: invokeinterface #9,  2            // InterfaceMethod java/util/List.add:(Ljava/lang/Object;)Z
     306: pop
     307: return

  protected void parseTimerService(org.jboss.staxmapper.XMLExtendedStreamReader, java.util.List<org.jboss.dmr.ModelNode>) throws javax.xml.stream.XMLStreamException;
    Code:
       0: aconst_null
       1: astore_3
       2: new           #57                 // class org/jboss/dmr/ModelNode
       5: dup
       6: invokespecial #130                // Method org/jboss/dmr/ModelNode."<init>":()V
       9: astore        4
      11: aload         4
      13: ldc           #131                // String subsystem
      15: ldc           #133                // String ejb3
      17: invokevirtual #134                // Method org/jboss/dmr/ModelNode.add:(Ljava/lang/String;Ljava/lang/String;)Lorg/jboss/dmr/ModelNode;
      20: pop
      21: aload         4
      23: ldc           #38                 // String service
      25: ldc           #135                // String timer-service
      27: invokevirtual #134                // Method org/jboss/dmr/ModelNode.add:(Ljava/lang/String;Ljava/lang/String;)Lorg/jboss/dmr/ModelNode;
      30: pop
      31: new           #57                 // class org/jboss/dmr/ModelNode
      34: dup
      35: invokespecial #130                // Method org/jboss/dmr/ModelNode."<init>":()V
      38: astore        5
      40: aload         5
      42: ldc           #136                // String operation
      44: invokevirtual #56                 // Method org/jboss/dmr/ModelNode.get:(Ljava/lang/String;)Lorg/jboss/dmr/ModelNode;
      47: ldc           #137                // String add
      49: invokevirtual #138                // Method org/jboss/dmr/ModelNode.set:(Ljava/lang/String;)Lorg/jboss/dmr/ModelNode;
      52: pop
      53: aload         5
      55: ldc           #99                 // String address
      57: invokevirtual #56                 // Method org/jboss/dmr/ModelNode.get:(Ljava/lang/String;)Lorg/jboss/dmr/ModelNode;
      60: aload         4
      62: invokevirtual #59                 // Method org/jboss/dmr/ModelNode.set:(Lorg/jboss/dmr/ModelNode;)Lorg/jboss/dmr/ModelNode;
      65: pop
      66: aconst_null
      67: astore        6
      69: aconst_null
      70: astore        7
      72: aload_1
      73: invokeinterface #4,  1            // InterfaceMethod org/jboss/staxmapper/XMLExtendedStreamReader.getAttributeCount:()I
      78: istore        8
      80: getstatic     #42                 // Field org/jboss/as/ejb3/subsystem/EJB3SubsystemXMLAttribute.THREAD_POOL_NAME:Lorg/jboss/as/ejb3/subsystem/EJB3SubsystemXMLAttribute;
      83: invokestatic  #62                 // Method java/util/EnumSet.of:(Ljava/lang/Enum;)Ljava/util/EnumSet;
      86: astore        9
      88: iconst_0
      89: istore        10
      91: iload         10
      93: iload         8
      95: if_icmpge     191
      98: aload_1
      99: iload         10
     101: invokestatic  #5                  // Method org/jboss/as/controller/parsing/ParseUtils.requireNoNamespaceAttribute:(Lorg/jboss/staxmapper/XMLExtendedStreamReader;I)V
     104: aload_1
     105: iload         10
     107: invokeinterface #44,  2           // InterfaceMethod org/jboss/staxmapper/XMLExtendedStreamReader.getAttributeValue:(I)Ljava/lang/String;
     112: astore        11
     114: aload_1
     115: iload         10
     117: invokeinterface #45,  2           // InterfaceMethod org/jboss/staxmapper/XMLExtendedStreamReader.getAttributeLocalName:(I)Ljava/lang/String;
     122: invokestatic  #46                 // Method org/jboss/as/ejb3/subsystem/EJB3SubsystemXMLAttribute.forName:(Ljava/lang/String;)Lorg/jboss/as/ejb3/subsystem/EJB3SubsystemXMLAttribute;
     125: astore        12
     127: aload         9
     129: aload         12
     131: invokevirtual #47                 // Method java/util/EnumSet.remove:(Ljava/lang/Object;)Z
     134: pop
     135: getstatic     #48                 // Field org/jboss/as/ejb3/subsystem/EJB3Subsystem12Parser$1.$SwitchMap$org$jboss$as$ejb3$subsystem$EJB3SubsystemXMLAttribute:[I
     138: aload         12
     140: invokevirtual #49                 // Method org/jboss/as/ejb3/subsystem/EJB3SubsystemXMLAttribute.ordinal:()I
     143: iaload
     144: lookupswitch  { // 1
                     2: 164
               default: 178
          }
     164: getstatic     #139                // Field org/jboss/as/ejb3/subsystem/TimerServiceResourceDefinition.THREAD_POOL_NAME:Lorg/jboss/as/controller/SimpleAttributeDefinition;
     167: aload         11
     169: aload         5
     171: aload_1
     172: invokevirtual #51                 // Method org/jboss/as/controller/SimpleAttributeDefinition.parseAndSetParameter:(Ljava/lang/String;Lorg/jboss/dmr/ModelNode;Ljavax/xml/stream/XMLStreamReader;)V
     175: goto          185
     178: aload_1
     179: iload         10
     181: invokestatic  #6                  // Method org/jboss/as/controller/parsing/ParseUtils.unexpectedAttribute:(Lorg/jboss/staxmapper/XMLExtendedStreamReader;I)Ljavax/xml/stream/XMLStreamException;
     184: athrow
     185: iinc          10, 1
     188: goto          91
     191: aload         9
     193: invokevirtual #53                 // Method java/util/EnumSet.isEmpty:()Z
     196: ifne          206
     199: aload_1
     200: aload         9
     202: invokestatic  #54                 // Method org/jboss/as/controller/parsing/ParseUtils.missingRequired:(Lorg/jboss/staxmapper/XMLExtendedStreamReader;Ljava/util/Set;)Ljavax/xml/stream/XMLStreamException;
     205: athrow
     206: aload_1
     207: invokeinterface #13,  1           // InterfaceMethod org/jboss/staxmapper/XMLExtendedStreamReader.hasNext:()Z
     212: ifeq          528
     215: aload_1
     216: invokeinterface #14,  1           // InterfaceMethod org/jboss/staxmapper/XMLExtendedStreamReader.nextTag:()I
     221: iconst_2
     222: if_icmpeq     528
     225: getstatic     #24                 // Field org/jboss/as/ejb3/subsystem/EJB3Subsystem12Parser$1.$SwitchMap$org$jboss$as$ejb3$subsystem$EJB3SubsystemXMLElement:[I
     228: aload_1
     229: invokeinterface #20,  1           // InterfaceMethod org/jboss/staxmapper/XMLExtendedStreamReader.getLocalName:()Ljava/lang/String;
     234: invokestatic  #21                 // Method org/jboss/as/ejb3/subsystem/EJB3SubsystemXMLElement.forName:(Ljava/lang/String;)Lorg/jboss/as/ejb3/subsystem/EJB3SubsystemXMLElement;
     237: invokevirtual #25                 // Method org/jboss/as/ejb3/subsystem/EJB3SubsystemXMLElement.ordinal:()I
     240: iaload
     241: lookupswitch  { // 1
                    24: 260
               default: 523
          }
     260: aload_1
     261: invokeinterface #4,  1            // InterfaceMethod org/jboss/staxmapper/XMLExtendedStreamReader.getAttributeCount:()I
     266: istore        10
     268: iconst_0
     269: istore        11
     271: iload         11
     273: iload         10
     275: if_icmpge     409
     278: aload_1
     279: iload         11
     281: invokestatic  #5                  // Method org/jboss/as/controller/parsing/ParseUtils.requireNoNamespaceAttribute:(Lorg/jboss/staxmapper/XMLExtendedStreamReader;I)V
     284: aload_1
     285: iload         11
     287: invokeinterface #44,  2           // InterfaceMethod org/jboss/staxmapper/XMLExtendedStreamReader.getAttributeValue:(I)Ljava/lang/String;
     292: astore        12
     294: aload_1
     295: iload         11
     297: invokeinterface #45,  2           // InterfaceMethod org/jboss/staxmapper/XMLExtendedStreamReader.getAttributeLocalName:(I)Ljava/lang/String;
     302: invokestatic  #46                 // Method org/jboss/as/ejb3/subsystem/EJB3SubsystemXMLAttribute.forName:(Ljava/lang/String;)Lorg/jboss/as/ejb3/subsystem/EJB3SubsystemXMLAttribute;
     305: astore        13
     307: getstatic     #48                 // Field org/jboss/as/ejb3/subsystem/EJB3Subsystem12Parser$1.$SwitchMap$org$jboss$as$ejb3$subsystem$EJB3SubsystemXMLAttribute:[I
     310: aload         13
     312: invokevirtual #49                 // Method org/jboss/as/ejb3/subsystem/EJB3SubsystemXMLAttribute.ordinal:()I
     315: iaload
     316: lookupswitch  { // 2
                    17: 370
                    25: 344
               default: 396
          }
     344: aload         6
     346: ifnull        356
     349: aload_1
     350: iload         11
     352: invokestatic  #6                  // Method org/jboss/as/controller/parsing/ParseUtils.unexpectedAttribute:(Lorg/jboss/staxmapper/XMLExtendedStreamReader;I)Ljavax/xml/stream/XMLStreamException;
     355: athrow
     356: getstatic     #140                // Field org/jboss/as/ejb3/subsystem/FileDataStoreResourceDefinition.PATH:Lorg/jboss/as/controller/SimpleAttributeDefinition;
     359: aload         12
     361: aload_1
     362: invokevirtual #141                // Method org/jboss/as/controller/SimpleAttributeDefinition.parse:(Ljava/lang/String;Ljavax/xml/stream/XMLStreamReader;)Lorg/jboss/dmr/ModelNode;
     365: astore        6
     367: goto          403
     370: aload         7
     372: ifnull        382
     375: aload_1
     376: iload         11
     378: invokestatic  #6                  // Method org/jboss/as/controller/parsing/ParseUtils.unexpectedAttribute:(Lorg/jboss/staxmapper/XMLExtendedStreamReader;I)Ljavax/xml/stream/XMLStreamException;
     381: athrow
     382: getstatic     #142                // Field org/jboss/as/ejb3/subsystem/FileDataStoreResourceDefinition.RELATIVE_TO:Lorg/jboss/as/controller/SimpleAttributeDefinition;
     385: aload         12
     387: aload_1
     388: invokevirtual #141                // Method org/jboss/as/controller/SimpleAttributeDefinition.parse:(Ljava/lang/String;Ljavax/xml/stream/XMLStreamReader;)Lorg/jboss/dmr/ModelNode;
     391: astore        7
     393: goto          403
     396: aload_1
     397: iload         11
     399: invokestatic  #6                  // Method org/jboss/as/controller/parsing/ParseUtils.unexpectedAttribute:(Lorg/jboss/staxmapper/XMLExtendedStreamReader;I)Ljavax/xml/stream/XMLStreamException;
     402: athrow
     403: iinc          11, 1
     406: goto          271
     409: aload         6
     411: ifnonnull     425
     414: aload_1
     415: getstatic     #143                // Field org/jboss/as/ejb3/subsystem/EJB3SubsystemXMLAttribute.PATH:Lorg/jboss/as/ejb3/subsystem/EJB3SubsystemXMLAttribute;
     418: invokestatic  #96                 // Method java/util/Collections.singleton:(Ljava/lang/Object;)Ljava/util/Set;
     421: invokestatic  #54                 // Method org/jboss/as/controller/parsing/ParseUtils.missingRequired:(Lorg/jboss/staxmapper/XMLExtendedStreamReader;Ljava/util/Set;)Ljavax/xml/stream/XMLStreamException;
     424: athrow
     425: aload         5
     427: ldc           #144                // String default-data-store
     429: invokevirtual #56                 // Method org/jboss/dmr/ModelNode.get:(Ljava/lang/String;)Lorg/jboss/dmr/ModelNode;
     432: ldc           #145                // String default-file-store
     434: invokevirtual #138                // Method org/jboss/dmr/ModelNode.set:(Ljava/lang/String;)Lorg/jboss/dmr/ModelNode;
     437: pop
     438: new           #57                 // class org/jboss/dmr/ModelNode
     441: dup
     442: invokespecial #130                // Method org/jboss/dmr/ModelNode."<init>":()V
     445: astore_3
     446: aload         4
     448: invokevirtual #146                // Method org/jboss/dmr/ModelNode.clone:()Lorg/jboss/dmr/ModelNode;
     451: astore        11
     453: aload         11
     455: ldc           #147                // String file-data-store
     457: ldc           #145                // String default-file-store
     459: invokevirtual #134                // Method org/jboss/dmr/ModelNode.add:(Ljava/lang/String;Ljava/lang/String;)Lorg/jboss/dmr/ModelNode;
     462: pop
     463: aload_3
     464: ldc           #136                // String operation
     466: invokevirtual #56                 // Method org/jboss/dmr/ModelNode.get:(Ljava/lang/String;)Lorg/jboss/dmr/ModelNode;
     469: ldc           #137                // String add
     471: invokevirtual #138                // Method org/jboss/dmr/ModelNode.set:(Ljava/lang/String;)Lorg/jboss/dmr/ModelNode;
     474: pop
     475: aload_3
     476: ldc           #99                 // String address
     478: invokevirtual #56                 // Method org/jboss/dmr/ModelNode.get:(Ljava/lang/String;)Lorg/jboss/dmr/ModelNode;
     481: aload         11
     483: invokevirtual #59                 // Method org/jboss/dmr/ModelNode.set:(Lorg/jboss/dmr/ModelNode;)Lorg/jboss/dmr/ModelNode;
     486: pop
     487: aload_3
     488: ldc           #148                // String path
     490: invokevirtual #56                 // Method org/jboss/dmr/ModelNode.get:(Ljava/lang/String;)Lorg/jboss/dmr/ModelNode;
     493: aload         6
     495: invokevirtual #59                 // Method org/jboss/dmr/ModelNode.set:(Lorg/jboss/dmr/ModelNode;)Lorg/jboss/dmr/ModelNode;
     498: pop
     499: aload         7
     501: ifnull        516
     504: aload_3
     505: ldc           #149                // String relative-to
     507: invokevirtual #56                 // Method org/jboss/dmr/ModelNode.get:(Ljava/lang/String;)Lorg/jboss/dmr/ModelNode;
     510: aload         7
     512: invokevirtual #59                 // Method org/jboss/dmr/ModelNode.set:(Lorg/jboss/dmr/ModelNode;)Lorg/jboss/dmr/ModelNode;
     515: pop
     516: aload_1
     517: invokestatic  #60                 // Method org/jboss/as/controller/parsing/ParseUtils.requireNoContent:(Lorg/jboss/staxmapper/XMLExtendedStreamReader;)V
     520: goto          206
     523: aload_1
     524: invokestatic  #19                 // Method org/jboss/as/controller/parsing/ParseUtils.unexpectedElement:(Lorg/jboss/staxmapper/XMLExtendedStreamReader;)Ljavax/xml/stream/XMLStreamException;
     527: athrow
     528: aload_2
     529: aload         5
     531: invokeinterface #9,  2            // InterfaceMethod java/util/List.add:(Ljava/lang/Object;)Z
     536: pop
     537: aload_3
     538: ifnull        549
     541: aload_2
     542: aload_3
     543: invokeinterface #9,  2            // InterfaceMethod java/util/List.add:(Ljava/lang/Object;)Z
     548: pop
     549: return

  private void parseThreadPools(org.jboss.staxmapper.XMLExtendedStreamReader, java.util.List<org.jboss.dmr.ModelNode>) throws javax.xml.stream.XMLStreamException;
    Code:
       0: aload_1
       1: invokestatic  #69                 // Method org/jboss/as/controller/parsing/ParseUtils.requireNoAttributes:(Lorg/jboss/staxmapper/XMLExtendedStreamReader;)V
       4: getstatic     #7                  // Field SUBSYSTEM_PATH:Lorg/jboss/as/controller/PathAddress;
       7: invokevirtual #100                // Method org/jboss/as/controller/PathAddress.toModelNode:()Lorg/jboss/dmr/ModelNode;
      10: astore_3
      11: aload_1
      12: invokeinterface #13,  1           // InterfaceMethod org/jboss/staxmapper/XMLExtendedStreamReader.hasNext:()Z
      17: ifeq          108
      20: aload_1
      21: invokeinterface #14,  1           // InterfaceMethod org/jboss/staxmapper/XMLExtendedStreamReader.nextTag:()I
      26: iconst_2
      27: if_icmpeq     108
      30: aload_1
      31: invokeinterface #16,  1           // InterfaceMethod org/jboss/staxmapper/XMLExtendedStreamReader.getNamespaceURI:()Ljava/lang/String;
      36: invokestatic  #17                 // Method org/jboss/as/ejb3/subsystem/EJB3SubsystemNamespace.forUri:(Ljava/lang/String;)Lorg/jboss/as/ejb3/subsystem/EJB3SubsystemNamespace;
      39: astore        4
      41: getstatic     #24                 // Field org/jboss/as/ejb3/subsystem/EJB3Subsystem12Parser$1.$SwitchMap$org$jboss$as$ejb3$subsystem$EJB3SubsystemXMLElement:[I
      44: aload_1
      45: invokeinterface #20,  1           // InterfaceMethod org/jboss/staxmapper/XMLExtendedStreamReader.getLocalName:()Ljava/lang/String;
      50: invokestatic  #21                 // Method org/jboss/as/ejb3/subsystem/EJB3SubsystemXMLElement.forName:(Ljava/lang/String;)Lorg/jboss/as/ejb3/subsystem/EJB3SubsystemXMLElement;
      53: invokevirtual #25                 // Method org/jboss/as/ejb3/subsystem/EJB3SubsystemXMLElement.ordinal:()I
      56: iaload
      57: lookupswitch  { // 1
                    25: 76
               default: 100
          }
      76: invokestatic  #150                // Method org/jboss/as/threads/ThreadsParser.getInstance:()Lorg/jboss/as/threads/ThreadsParser;
      79: aload_1
      80: aload         4
      82: invokevirtual #151                // Method org/jboss/as/ejb3/subsystem/EJB3SubsystemNamespace.getUriString:()Ljava/lang/String;
      85: getstatic     #152                // Field org/jboss/as/threads/Namespace.THREADS_1_1:Lorg/jboss/as/threads/Namespace;
      88: aload_3
      89: aload_2
      90: ldc           #153                // String thread-pool
      92: aconst_null
      93: invokevirtual #154                // Method org/jboss/as/threads/ThreadsParser.parseUnboundedQueueThreadPool:(Lorg/jboss/staxmapper/XMLExtendedStreamReader;Ljava/lang/String;Lorg/jboss/as/threads/Namespace;Lorg/jboss/dmr/ModelNode;Ljava/util/List;Ljava/lang/String;Ljava/lang/String;)Ljava/lang/String;
      96: pop
      97: goto          105
     100: aload_1
     101: invokestatic  #19                 // Method org/jboss/as/controller/parsing/ParseUtils.unexpectedElement:(Lorg/jboss/staxmapper/XMLExtendedStreamReader;)Ljavax/xml/stream/XMLStreamException;
     104: athrow
     105: goto          11
     108: return

  protected org.jboss.as.ejb3.subsystem.EJB3SubsystemNamespace getExpectedNamespace();
    Code:
       0: getstatic     #155                // Field org/jboss/as/ejb3/subsystem/EJB3SubsystemNamespace.EJB3_1_2:Lorg/jboss/as/ejb3/subsystem/EJB3SubsystemNamespace;
       3: areturn

  org.jboss.as.controller.PathAddress getEJB3SubsystemAddress();
    Code:
       0: getstatic     #7                  // Field SUBSYSTEM_PATH:Lorg/jboss/as/controller/PathAddress;
       3: areturn

  private void parseInVMRemoteInterfaceInvocation(org.jboss.staxmapper.XMLExtendedStreamReader, org.jboss.dmr.ModelNode) throws javax.xml.stream.XMLStreamException;
    Code:
       0: aload_1
       1: invokeinterface #4,  1            // InterfaceMethod org/jboss/staxmapper/XMLExtendedStreamReader.getAttributeCount:()I
       6: istore_3
       7: getstatic     #156                // Field org/jboss/as/ejb3/subsystem/EJB3SubsystemXMLAttribute.PASS_BY_VALUE:Lorg/jboss/as/ejb3/subsystem/EJB3SubsystemXMLAttribute;
      10: invokestatic  #62                 // Method java/util/EnumSet.of:(Ljava/lang/Enum;)Ljava/util/EnumSet;
      13: astore        4
      15: iconst_0
      16: istore        5
      18: iload         5
      20: iload_3
      21: if_icmpge     115
      24: aload_1
      25: iload         5
      27: invokestatic  #5                  // Method org/jboss/as/controller/parsing/ParseUtils.requireNoNamespaceAttribute:(Lorg/jboss/staxmapper/XMLExtendedStreamReader;I)V
      30: aload_1
      31: iload         5
      33: invokeinterface #44,  2           // InterfaceMethod org/jboss/staxmapper/XMLExtendedStreamReader.getAttributeValue:(I)Ljava/lang/String;
      38: astore        6
      40: aload_1
      41: iload         5
      43: invokeinterface #45,  2           // InterfaceMethod org/jboss/staxmapper/XMLExtendedStreamReader.getAttributeLocalName:(I)Ljava/lang/String;
      48: invokestatic  #46                 // Method org/jboss/as/ejb3/subsystem/EJB3SubsystemXMLAttribute.forName:(Ljava/lang/String;)Lorg/jboss/as/ejb3/subsystem/EJB3SubsystemXMLAttribute;
      51: astore        7
      53: getstatic     #48                 // Field org/jboss/as/ejb3/subsystem/EJB3Subsystem12Parser$1.$SwitchMap$org$jboss$as$ejb3$subsystem$EJB3SubsystemXMLAttribute:[I
      56: aload         7
      58: invokevirtual #49                 // Method org/jboss/as/ejb3/subsystem/EJB3SubsystemXMLAttribute.ordinal:()I
      61: iaload
      62: lookupswitch  { // 1
                    26: 80
               default: 102
          }
      80: getstatic     #157                // Field org/jboss/as/ejb3/subsystem/EJB3SubsystemRootResourceDefinition.PASS_BY_VALUE:Lorg/jboss/as/controller/SimpleAttributeDefinition;
      83: aload         6
      85: aload_2
      86: aload_1
      87: invokevirtual #51                 // Method org/jboss/as/controller/SimpleAttributeDefinition.parseAndSetParameter:(Ljava/lang/String;Lorg/jboss/dmr/ModelNode;Ljavax/xml/stream/XMLStreamReader;)V
      90: aload         4
      92: getstatic     #156                // Field org/jboss/as/ejb3/subsystem/EJB3SubsystemXMLAttribute.PASS_BY_VALUE:Lorg/jboss/as/ejb3/subsystem/EJB3SubsystemXMLAttribute;
      95: invokevirtual #47                 // Method java/util/EnumSet.remove:(Ljava/lang/Object;)Z
      98: pop
      99: goto          109
     102: aload_1
     103: iload         5
     105: invokestatic  #6                  // Method org/jboss/as/controller/parsing/ParseUtils.unexpectedAttribute:(Lorg/jboss/staxmapper/XMLExtendedStreamReader;I)Ljavax/xml/stream/XMLStreamException;
     108: athrow
     109: iinc          5, 1
     112: goto          18
     115: aload_1
     116: invokestatic  #60                 // Method org/jboss/as/controller/parsing/ParseUtils.requireNoContent:(Lorg/jboss/staxmapper/XMLExtendedStreamReader;)V
     119: aload         4
     121: invokevirtual #53                 // Method java/util/EnumSet.isEmpty:()Z
     124: ifne          134
     127: aload_1
     128: aload         4
     130: invokestatic  #54                 // Method org/jboss/as/controller/parsing/ParseUtils.missingRequired:(Lorg/jboss/staxmapper/XMLExtendedStreamReader;Ljava/util/Set;)Ljavax/xml/stream/XMLStreamException;
     133: athrow
     134: return

  public void readElement(org.jboss.staxmapper.XMLExtendedStreamReader, java.lang.Object) throws javax.xml.stream.XMLStreamException;
    Code:
       0: aload_0
       1: aload_1
       2: aload_2
       3: checkcast     #158                // class java/util/List
       6: invokevirtual #159                // Method readElement:(Lorg/jboss/staxmapper/XMLExtendedStreamReader;Ljava/util/List;)V
       9: return

  static {};
    Code:
       0: new           #160                // class org/jboss/as/ejb3/subsystem/EJB3Subsystem12Parser
       3: dup
       4: invokespecial #161                // Method "<init>":()V
       7: putstatic     #162                // Field INSTANCE:Lorg/jboss/as/ejb3/subsystem/EJB3Subsystem12Parser;
      10: iconst_1
      11: anewarray     #110                // class org/jboss/as/controller/PathElement
      14: dup
      15: iconst_0
      16: ldc           #131                // String subsystem
      18: ldc           #133                // String ejb3
      20: invokestatic  #112                // Method org/jboss/as/controller/PathElement.pathElement:(Ljava/lang/String;Ljava/lang/String;)Lorg/jboss/as/controller/PathElement;
      23: aastore
      24: invokestatic  #163                // Method org/jboss/as/controller/PathAddress.pathAddress:([Lorg/jboss/as/controller/PathElement;)Lorg/jboss/as/controller/PathAddress;
      27: putstatic     #7                  // Field SUBSYSTEM_PATH:Lorg/jboss/as/controller/PathAddress;
      30: return
}
