Compiled from "RemotingProfileChildResourceHandlerBase.java"
class org.jboss.as.ejb3.subsystem.RemotingProfileChildResourceHandlerBase$1 implements org.jboss.as.controller.OperationStepHandler {
  final org.jboss.as.controller.PathAddress val$parentAddress;

  final org.jboss.dmr.ModelNode val$parentModel;

  final org.jboss.as.ejb3.subsystem.RemotingProfileChildResourceHandlerBase this$0;

  org.jboss.as.ejb3.subsystem.RemotingProfileChildResourceHandlerBase$1(org.jboss.as.ejb3.subsystem.RemotingProfileChildResourceHandlerBase, org.jboss.as.controller.PathAddress, org.jboss.dmr.ModelNode);
    Code:
       0: aload_0
       1: aload_1
       2: putfield      #1                  // Field this$0:Lorg/jboss/as/ejb3/subsystem/RemotingProfileChildResourceHandlerBase;
       5: aload_0
       6: aload_2
       7: putfield      #2                  // Field val$parentAddress:Lorg/jboss/as/controller/PathAddress;
      10: aload_0
      11: aload_3
      12: putfield      #3                  // Field val$parentModel:Lorg/jboss/dmr/ModelNode;
      15: aload_0
      16: invokespecial #4                  // Method java/lang/Object."<init>":()V
      19: return

  public void execute(org.jboss.as.controller.OperationContext, org.jboss.dmr.ModelNode) throws org.jboss.as.controller.OperationFailedException;
    Code:
       0: getstatic     #5                  // Field org/jboss/as/ejb3/subsystem/RemotingProfileAdd.INSTANCE:Lorg/jboss/as/ejb3/subsystem/RemotingProfileAdd;
       3: aload_1
       4: aload_0
       5: getfield      #2                  // Field val$parentAddress:Lorg/jboss/as/controller/PathAddress;
       8: aload_0
       9: getfield      #3                  // Field val$parentModel:Lorg/jboss/dmr/ModelNode;
      12: invokevirtual #6                  // Method org/jboss/as/ejb3/subsystem/RemotingProfileAdd.installServices:(Lorg/jboss/as/controller/OperationContext;Lorg/jboss/as/controller/PathAddress;Lorg/jboss/dmr/ModelNode;)V
      15: aload_1
      16: invokeinterface #7,  1            // InterfaceMethod org/jboss/as/controller/OperationContext.stepCompleted:()V
      21: return
}
