Compiled from "RemoteConnectorChannelCreationOptionResource.java"
class org.jboss.as.ejb3.subsystem.RemoteConnectorChannelCreationOptionResource extends org.jboss.as.controller.SimpleResourceDefinition {
  static final org.jboss.as.ejb3.subsystem.RemoteConnectorChannelCreationOptionResource INSTANCE;

  static final org.jboss.as.controller.SimpleAttributeDefinition CHANNEL_CREATION_OPTION_VALUE;

  static final org.jboss.as.controller.SimpleAttributeDefinition CHANNEL_CREATION_OPTION_TYPE;

  org.jboss.as.ejb3.subsystem.RemoteConnectorChannelCreationOptionResource();
    Code:
       0: aload_0
       1: ldc           #3                  // String channel-creation-options
       3: invokestatic  #4                  // Method org/jboss/as/controller/PathElement.pathElement:(Ljava/lang/String;)Lorg/jboss/as/controller/PathElement;
       6: ldc           #3                  // String channel-creation-options
       8: invokestatic  #5                  // Method org/jboss/as/ejb3/subsystem/EJB3Extension.getResourceDescriptionResolver:(Ljava/lang/String;)Lorg/jboss/as/controller/descriptions/ResourceDescriptionResolver;
      11: new           #6                  // class org/jboss/as/ejb3/subsystem/RemoteConnectorChannelCreationOptionResource$ChannelCreationOptionAdd
      14: dup
      15: aconst_null
      16: invokespecial #7                  // Method org/jboss/as/ejb3/subsystem/RemoteConnectorChannelCreationOptionResource$ChannelCreationOptionAdd."<init>":(Lorg/jboss/as/ejb3/subsystem/RemoteConnectorChannelCreationOptionResource$1;)V
      19: new           #8                  // class org/jboss/as/ejb3/subsystem/RemoteConnectorChannelCreationOptionResource$ChannelCreationOptionRemove
      22: dup
      23: aconst_null
      24: invokespecial #9                  // Method org/jboss/as/ejb3/subsystem/RemoteConnectorChannelCreationOptionResource$ChannelCreationOptionRemove."<init>":(Lorg/jboss/as/ejb3/subsystem/RemoteConnectorChannelCreationOptionResource$1;)V
      27: invokespecial #10                 // Method org/jboss/as/controller/SimpleResourceDefinition."<init>":(Lorg/jboss/as/controller/PathElement;Lorg/jboss/as/controller/descriptions/ResourceDescriptionResolver;Lorg/jboss/as/controller/OperationStepHandler;Lorg/jboss/as/controller/OperationStepHandler;)V
      30: return

  public void registerAttributes(org.jboss.as.controller.registry.ManagementResourceRegistration);
    Code:
       0: aload_1
       1: getstatic     #11                 // Field CHANNEL_CREATION_OPTION_VALUE:Lorg/jboss/as/controller/SimpleAttributeDefinition;
       4: aconst_null
       5: new           #12                 // class org/jboss/as/ejb3/subsystem/RemoteConnectorChannelCreationOptionResource$ChannelCreationOptionWriteAttributeHandler
       8: dup
       9: getstatic     #11                 // Field CHANNEL_CREATION_OPTION_VALUE:Lorg/jboss/as/controller/SimpleAttributeDefinition;
      12: invokespecial #13                 // Method org/jboss/as/ejb3/subsystem/RemoteConnectorChannelCreationOptionResource$ChannelCreationOptionWriteAttributeHandler."<init>":(Lorg/jboss/as/controller/AttributeDefinition;)V
      15: invokeinterface #14,  4           // InterfaceMethod org/jboss/as/controller/registry/ManagementResourceRegistration.registerReadWriteAttribute:(Lorg/jboss/as/controller/AttributeDefinition;Lorg/jboss/as/controller/OperationStepHandler;Lorg/jboss/as/controller/OperationStepHandler;)V
      20: aload_1
      21: getstatic     #15                 // Field CHANNEL_CREATION_OPTION_TYPE:Lorg/jboss/as/controller/SimpleAttributeDefinition;
      24: aconst_null
      25: new           #12                 // class org/jboss/as/ejb3/subsystem/RemoteConnectorChannelCreationOptionResource$ChannelCreationOptionWriteAttributeHandler
      28: dup
      29: getstatic     #15                 // Field CHANNEL_CREATION_OPTION_TYPE:Lorg/jboss/as/controller/SimpleAttributeDefinition;
      32: invokespecial #13                 // Method org/jboss/as/ejb3/subsystem/RemoteConnectorChannelCreationOptionResource$ChannelCreationOptionWriteAttributeHandler."<init>":(Lorg/jboss/as/controller/AttributeDefinition;)V
      35: invokeinterface #14,  4           // InterfaceMethod org/jboss/as/controller/registry/ManagementResourceRegistration.registerReadWriteAttribute:(Lorg/jboss/as/controller/AttributeDefinition;Lorg/jboss/as/controller/OperationStepHandler;Lorg/jboss/as/controller/OperationStepHandler;)V
      40: return

  private static void recreateParentService(org.jboss.as.controller.OperationContext, org.jboss.dmr.ModelNode) throws org.jboss.as.controller.OperationFailedException;
    Code:
       0: getstatic     #16                 // Field org/jboss/as/ejb3/subsystem/EJB3RemoteServiceAdd.INSTANCE:Lorg/jboss/as/ejb3/subsystem/EJB3RemoteServiceAdd;
       3: aload_0
       4: aload_1
       5: invokevirtual #17                 // Method org/jboss/as/ejb3/subsystem/EJB3RemoteServiceAdd.installRuntimeServices:(Lorg/jboss/as/controller/OperationContext;Lorg/jboss/dmr/ModelNode;)V
       8: return

  static void registerTransformers_1_1_0(org.jboss.as.controller.transform.description.ResourceTransformationDescriptionBuilder);
    Code:
       0: aload_0
       1: getstatic     #18                 // Field INSTANCE:Lorg/jboss/as/ejb3/subsystem/RemoteConnectorChannelCreationOptionResource;
       4: invokevirtual #19                 // Method getPathElement:()Lorg/jboss/as/controller/PathElement;
       7: invokeinterface #20,  2           // InterfaceMethod org/jboss/as/controller/transform/description/ResourceTransformationDescriptionBuilder.addChildResource:(Lorg/jboss/as/controller/PathElement;)Lorg/jboss/as/controller/transform/description/ResourceTransformationDescriptionBuilder;
      12: invokeinterface #21,  1           // InterfaceMethod org/jboss/as/controller/transform/description/ResourceTransformationDescriptionBuilder.getAttributeBuilder:()Lorg/jboss/as/controller/transform/description/AttributeTransformationDescriptionBuilder;
      17: getstatic     #22                 // Field org/jboss/as/controller/transform/description/RejectAttributeChecker.SIMPLE_EXPRESSIONS:Lorg/jboss/as/controller/transform/description/RejectAttributeChecker;
      20: iconst_1
      21: anewarray     #23                 // class org/jboss/as/controller/AttributeDefinition
      24: dup
      25: iconst_0
      26: getstatic     #11                 // Field CHANNEL_CREATION_OPTION_VALUE:Lorg/jboss/as/controller/SimpleAttributeDefinition;
      29: aastore
      30: invokeinterface #24,  3           // InterfaceMethod org/jboss/as/controller/transform/description/AttributeTransformationDescriptionBuilder.addRejectCheck:(Lorg/jboss/as/controller/transform/description/RejectAttributeChecker;[Lorg/jboss/as/controller/AttributeDefinition;)Lorg/jboss/as/controller/transform/description/BaseAttributeTransformationDescriptionBuilder;
      35: pop
      36: return

  static void access$200(org.jboss.as.controller.OperationContext, org.jboss.dmr.ModelNode) throws org.jboss.as.controller.OperationFailedException;
    Code:
       0: aload_0
       1: aload_1
       2: invokestatic  #1                  // Method recreateParentService:(Lorg/jboss/as/controller/OperationContext;Lorg/jboss/dmr/ModelNode;)V
       5: return

  static {};
    Code:
       0: new           #25                 // class org/jboss/as/ejb3/subsystem/RemoteConnectorChannelCreationOptionResource
       3: dup
       4: invokespecial #26                 // Method "<init>":()V
       7: putstatic     #18                 // Field INSTANCE:Lorg/jboss/as/ejb3/subsystem/RemoteConnectorChannelCreationOptionResource;
      10: new           #27                 // class org/jboss/as/controller/SimpleAttributeDefinitionBuilder
      13: dup
      14: ldc           #28                 // String value
      16: getstatic     #29                 // Field org/jboss/dmr/ModelType.STRING:Lorg/jboss/dmr/ModelType;
      19: iconst_1
      20: invokespecial #30                 // Method org/jboss/as/controller/SimpleAttributeDefinitionBuilder."<init>":(Ljava/lang/String;Lorg/jboss/dmr/ModelType;Z)V
      23: iconst_1
      24: invokevirtual #31                 // Method org/jboss/as/controller/SimpleAttributeDefinitionBuilder.setAllowExpression:(Z)Lorg/jboss/as/controller/AbstractAttributeDefinitionBuilder;
      27: checkcast     #27                 // class org/jboss/as/controller/SimpleAttributeDefinitionBuilder
      30: iconst_1
      31: anewarray     #32                 // class org/jboss/as/controller/registry/AttributeAccess$Flag
      34: dup
      35: iconst_0
      36: getstatic     #33                 // Field org/jboss/as/controller/registry/AttributeAccess$Flag.RESTART_RESOURCE_SERVICES:Lorg/jboss/as/controller/registry/AttributeAccess$Flag;
      39: aastore
      40: invokevirtual #34                 // Method org/jboss/as/controller/SimpleAttributeDefinitionBuilder.setFlags:([Lorg/jboss/as/controller/registry/AttributeAccess$Flag;)Lorg/jboss/as/controller/AbstractAttributeDefinitionBuilder;
      43: checkcast     #27                 // class org/jboss/as/controller/SimpleAttributeDefinitionBuilder
      46: invokevirtual #35                 // Method org/jboss/as/controller/SimpleAttributeDefinitionBuilder.build:()Lorg/jboss/as/controller/SimpleAttributeDefinition;
      49: putstatic     #11                 // Field CHANNEL_CREATION_OPTION_VALUE:Lorg/jboss/as/controller/SimpleAttributeDefinition;
      52: new           #27                 // class org/jboss/as/controller/SimpleAttributeDefinitionBuilder
      55: dup
      56: ldc           #36                 // String type
      58: getstatic     #29                 // Field org/jboss/dmr/ModelType.STRING:Lorg/jboss/dmr/ModelType;
      61: iconst_1
      62: invokespecial #30                 // Method org/jboss/as/controller/SimpleAttributeDefinitionBuilder."<init>":(Ljava/lang/String;Lorg/jboss/dmr/ModelType;Z)V
      65: iconst_1
      66: anewarray     #32                 // class org/jboss/as/controller/registry/AttributeAccess$Flag
      69: dup
      70: iconst_0
      71: getstatic     #33                 // Field org/jboss/as/controller/registry/AttributeAccess$Flag.RESTART_RESOURCE_SERVICES:Lorg/jboss/as/controller/registry/AttributeAccess$Flag;
      74: aastore
      75: invokevirtual #34                 // Method org/jboss/as/controller/SimpleAttributeDefinitionBuilder.setFlags:([Lorg/jboss/as/controller/registry/AttributeAccess$Flag;)Lorg/jboss/as/controller/AbstractAttributeDefinitionBuilder;
      78: checkcast     #27                 // class org/jboss/as/controller/SimpleAttributeDefinitionBuilder
      81: getstatic     #37                 // Field org/jboss/as/ejb3/subsystem/AllowedChannelOptionTypesValidator.INSTANCE:Lorg/jboss/as/ejb3/subsystem/AllowedChannelOptionTypesValidator;
      84: invokevirtual #38                 // Method org/jboss/as/controller/SimpleAttributeDefinitionBuilder.setValidator:(Lorg/jboss/as/controller/operations/validation/ParameterValidator;)Lorg/jboss/as/controller/AbstractAttributeDefinitionBuilder;
      87: checkcast     #27                 // class org/jboss/as/controller/SimpleAttributeDefinitionBuilder
      90: invokevirtual #35                 // Method org/jboss/as/controller/SimpleAttributeDefinitionBuilder.build:()Lorg/jboss/as/controller/SimpleAttributeDefinition;
      93: putstatic     #15                 // Field CHANNEL_CREATION_OPTION_TYPE:Lorg/jboss/as/controller/SimpleAttributeDefinition;
      96: return
}
