Compiled from "DynamicFilterParameterSpecification.java"
public class org.hibernate.param.DynamicFilterParameterSpecification implements org.hibernate.param.ParameterSpecification {
  private final java.lang.String filterName;

  private final java.lang.String parameterName;

  private final org.hibernate.type.Type definedParameterType;

  public org.hibernate.param.DynamicFilterParameterSpecification(java.lang.String, java.lang.String, org.hibernate.type.Type);
    Code:
       0: aload_0
       1: invokespecial #1                  // Method java/lang/Object."<init>":()V
       4: aload_0
       5: aload_1
       6: putfield      #2                  // Field filterName:Ljava/lang/String;
       9: aload_0
      10: aload_2
      11: putfield      #3                  // Field parameterName:Ljava/lang/String;
      14: aload_0
      15: aload_3
      16: putfield      #4                  // Field definedParameterType:Lorg/hibernate/type/Type;
      19: return

  public int bind(java.sql.PreparedStatement, org.hibernate.engine.spi.QueryParameters, org.hibernate.engine.spi.SharedSessionContractImplementor, int) throws java.sql.SQLException;
    Code:
       0: aload_0
       1: getfield      #4                  // Field definedParameterType:Lorg/hibernate/type/Type;
       4: aload_3
       5: invokeinterface #5,  1            // InterfaceMethod org/hibernate/engine/spi/SharedSessionContractImplementor.getFactory:()Lorg/hibernate/engine/spi/SessionFactoryImplementor;
      10: invokeinterface #6,  2            // InterfaceMethod org/hibernate/type/Type.getColumnSpan:(Lorg/hibernate/engine/spi/Mapping;)I
      15: istore        5
      17: new           #7                  // class java/lang/StringBuilder
      20: dup
      21: invokespecial #8                  // Method java/lang/StringBuilder."<init>":()V
      24: aload_0
      25: getfield      #2                  // Field filterName:Ljava/lang/String;
      28: invokevirtual #9                  // Method java/lang/StringBuilder.append:(Ljava/lang/String;)Ljava/lang/StringBuilder;
      31: bipush        46
      33: invokevirtual #10                 // Method java/lang/StringBuilder.append:(C)Ljava/lang/StringBuilder;
      36: aload_0
      37: getfield      #3                  // Field parameterName:Ljava/lang/String;
      40: invokevirtual #9                  // Method java/lang/StringBuilder.append:(Ljava/lang/String;)Ljava/lang/StringBuilder;
      43: invokevirtual #11                 // Method java/lang/StringBuilder.toString:()Ljava/lang/String;
      46: astore        6
      48: aload_3
      49: invokeinterface #12,  1           // InterfaceMethod org/hibernate/engine/spi/SharedSessionContractImplementor.getLoadQueryInfluencers:()Lorg/hibernate/engine/spi/LoadQueryInfluencers;
      54: aload         6
      56: invokevirtual #13                 // Method org/hibernate/engine/spi/LoadQueryInfluencers.getFilterParameterValue:(Ljava/lang/String;)Ljava/lang/Object;
      59: astore        7
      61: aload_3
      62: invokeinterface #12,  1           // InterfaceMethod org/hibernate/engine/spi/SharedSessionContractImplementor.getLoadQueryInfluencers:()Lorg/hibernate/engine/spi/LoadQueryInfluencers;
      67: aload         6
      69: invokevirtual #14                 // Method org/hibernate/engine/spi/LoadQueryInfluencers.getFilterParameterType:(Ljava/lang/String;)Lorg/hibernate/type/Type;
      72: astore        8
      74: ldc           #15                 // class java/util/Collection
      76: aload         7
      78: invokevirtual #16                 // Method java/lang/Class.isInstance:(Ljava/lang/Object;)Z
      81: ifeq          157
      84: iconst_0
      85: istore        9
      87: aload         7
      89: checkcast     #15                 // class java/util/Collection
      92: invokeinterface #17,  1           // InterfaceMethod java/util/Collection.iterator:()Ljava/util/Iterator;
      97: astore        10
      99: aload         10
     101: invokeinterface #18,  1           // InterfaceMethod java/util/Iterator.hasNext:()Z
     106: ifeq          154
     109: aload         10
     111: invokeinterface #19,  1           // InterfaceMethod java/util/Iterator.next:()Ljava/lang/Object;
     116: astore        11
     118: aload_2
     119: aload         8
     121: aload         11
     123: invokevirtual #20                 // Method org/hibernate/engine/spi/QueryParameters.bindDynamicParameter:(Lorg/hibernate/type/Type;Ljava/lang/Object;)V
     126: aload_0
     127: getfield      #4                  // Field definedParameterType:Lorg/hibernate/type/Type;
     130: aload_1
     131: aload         11
     133: iload         4
     135: iload         9
     137: iadd
     138: aload_3
     139: invokeinterface #21,  5           // InterfaceMethod org/hibernate/type/Type.nullSafeSet:(Ljava/sql/PreparedStatement;Ljava/lang/Object;ILorg/hibernate/engine/spi/SharedSessionContractImplementor;)V
     144: iload         9
     146: iload         5
     148: iadd
     149: istore        9
     151: goto          99
     154: iload         9
     156: ireturn
     157: aload_2
     158: aload         8
     160: aload         7
     162: invokevirtual #20                 // Method org/hibernate/engine/spi/QueryParameters.bindDynamicParameter:(Lorg/hibernate/type/Type;Ljava/lang/Object;)V
     165: aload_0
     166: getfield      #4                  // Field definedParameterType:Lorg/hibernate/type/Type;
     169: aload_1
     170: aload         7
     172: iload         4
     174: aload_3
     175: invokeinterface #21,  5           // InterfaceMethod org/hibernate/type/Type.nullSafeSet:(Ljava/sql/PreparedStatement;Ljava/lang/Object;ILorg/hibernate/engine/spi/SharedSessionContractImplementor;)V
     180: iload         5
     182: ireturn

  public org.hibernate.type.Type getExpectedType();
    Code:
       0: aload_0
       1: getfield      #4                  // Field definedParameterType:Lorg/hibernate/type/Type;
       4: areturn

  public void setExpectedType(org.hibernate.type.Type);
    Code:
       0: return

  public java.lang.String renderDisplayInfo();
    Code:
       0: new           #7                  // class java/lang/StringBuilder
       3: dup
       4: invokespecial #8                  // Method java/lang/StringBuilder."<init>":()V
       7: ldc           #22                 // String dynamic-filter={filterName=
       9: invokevirtual #9                  // Method java/lang/StringBuilder.append:(Ljava/lang/String;)Ljava/lang/StringBuilder;
      12: aload_0
      13: getfield      #2                  // Field filterName:Ljava/lang/String;
      16: invokevirtual #9                  // Method java/lang/StringBuilder.append:(Ljava/lang/String;)Ljava/lang/StringBuilder;
      19: ldc           #23                 // String ,paramName=
      21: invokevirtual #9                  // Method java/lang/StringBuilder.append:(Ljava/lang/String;)Ljava/lang/StringBuilder;
      24: aload_0
      25: getfield      #3                  // Field parameterName:Ljava/lang/String;
      28: invokevirtual #9                  // Method java/lang/StringBuilder.append:(Ljava/lang/String;)Ljava/lang/StringBuilder;
      31: ldc           #24                 // String }
      33: invokevirtual #9                  // Method java/lang/StringBuilder.append:(Ljava/lang/String;)Ljava/lang/StringBuilder;
      36: invokevirtual #11                 // Method java/lang/StringBuilder.toString:()Ljava/lang/String;
      39: areturn
}
