Compiled from "StringDecoder.java"
public class io.netty.handler.codec.string.StringDecoder extends io.netty.handler.codec.MessageToMessageDecoder<io.netty.buffer.ByteBuf> {
  private final java.nio.charset.Charset charset;

  public io.netty.handler.codec.string.StringDecoder();
    Code:
       0: aload_0
       1: invokestatic  #1                  // Method java/nio/charset/Charset.defaultCharset:()Ljava/nio/charset/Charset;
       4: invokespecial #2                  // Method "<init>":(Ljava/nio/charset/Charset;)V
       7: return

  public io.netty.handler.codec.string.StringDecoder(java.nio.charset.Charset);
    Code:
       0: aload_0
       1: invokespecial #3                  // Method io/netty/handler/codec/MessageToMessageDecoder."<init>":()V
       4: aload_0
       5: aload_1
       6: ldc           #4                  // String charset
       8: invokestatic  #5                  // Method io/netty/util/internal/ObjectUtil.checkNotNull:(Ljava/lang/Object;Ljava/lang/String;)Ljava/lang/Object;
      11: checkcast     #6                  // class java/nio/charset/Charset
      14: putfield      #7                  // Field charset:Ljava/nio/charset/Charset;
      17: return

  protected void decode(io.netty.channel.ChannelHandlerContext, io.netty.buffer.ByteBuf, java.util.List<java.lang.Object>) throws java.lang.Exception;
    Code:
       0: aload_3
       1: aload_2
       2: aload_0
       3: getfield      #7                  // Field charset:Ljava/nio/charset/Charset;
       6: invokevirtual #8                  // Method io/netty/buffer/ByteBuf.toString:(Ljava/nio/charset/Charset;)Ljava/lang/String;
       9: invokeinterface #9,  2            // InterfaceMethod java/util/List.add:(Ljava/lang/Object;)Z
      14: pop
      15: return

  protected void decode(io.netty.channel.ChannelHandlerContext, java.lang.Object, java.util.List) throws java.lang.Exception;
    Code:
       0: aload_0
       1: aload_1
       2: aload_2
       3: checkcast     #10                 // class io/netty/buffer/ByteBuf
       6: aload_3
       7: invokevirtual #11                 // Method decode:(Lio/netty/channel/ChannelHandlerContext;Lio/netty/buffer/ByteBuf;Ljava/util/List;)V
      10: return
}
