Compiled from "ListPackageRequestWrapper.java"
public class org.hpccsystems.ws.client.wrappers.gen.wspackageprocess.ListPackageRequestWrapper {
  protected java.lang.String local_target;

  protected java.lang.String local_process;

  public org.hpccsystems.ws.client.wrappers.gen.wspackageprocess.ListPackageRequestWrapper();
    Code:
       0: aload_0
       1: invokespecial #1                  // Method java/lang/Object."<init>":()V
       4: return

  public org.hpccsystems.ws.client.wrappers.gen.wspackageprocess.ListPackageRequestWrapper(org.hpccsystems.ws.client.gen.axis2.wspackageprocess.v1_04.ListPackageRequest);
    Code:
       0: aload_0
       1: invokespecial #1                  // Method java/lang/Object."<init>":()V
       4: aload_0
       5: aload_1
       6: invokespecial #2                  // Method copy:(Lorg/hpccsystems/ws/client/gen/axis2/wspackageprocess/v1_04/ListPackageRequest;)V
       9: return

  public org.hpccsystems.ws.client.wrappers.gen.wspackageprocess.ListPackageRequestWrapper(java.lang.String, java.lang.String);
    Code:
       0: aload_0
       1: invokespecial #1                  // Method java/lang/Object."<init>":()V
       4: aload_0
       5: aload_1
       6: putfield      #3                  // Field local_target:Ljava/lang/String;
       9: aload_0
      10: aload_2
      11: putfield      #4                  // Field local_process:Ljava/lang/String;
      14: return

  private void copy(org.hpccsystems.ws.client.gen.axis2.wspackageprocess.v1_04.ListPackageRequest);
    Code:
       0: aload_1
       1: ifnonnull     5
       4: return
       5: aload_0
       6: aload_1
       7: invokevirtual #5                  // Method org/hpccsystems/ws/client/gen/axis2/wspackageprocess/v1_04/ListPackageRequest.getTarget:()Ljava/lang/String;
      10: putfield      #3                  // Field local_target:Ljava/lang/String;
      13: aload_0
      14: aload_1
      15: invokevirtual #6                  // Method org/hpccsystems/ws/client/gen/axis2/wspackageprocess/v1_04/ListPackageRequest.getProcess:()Ljava/lang/String;
      18: putfield      #4                  // Field local_process:Ljava/lang/String;
      21: return

  public java.lang.String toString();
    Code:
       0: new           #7                  // class java/lang/StringBuilder
       3: dup
       4: invokespecial #8                  // Method java/lang/StringBuilder."<init>":()V
       7: ldc           #9                  // String ListPackageRequestWrapper [target =
       9: invokevirtual #10                 // Method java/lang/StringBuilder.append:(Ljava/lang/String;)Ljava/lang/StringBuilder;
      12: aload_0
      13: getfield      #3                  // Field local_target:Ljava/lang/String;
      16: invokevirtual #10                 // Method java/lang/StringBuilder.append:(Ljava/lang/String;)Ljava/lang/StringBuilder;
      19: ldc           #11                 // String , process =
      21: invokevirtual #10                 // Method java/lang/StringBuilder.append:(Ljava/lang/String;)Ljava/lang/StringBuilder;
      24: aload_0
      25: getfield      #4                  // Field local_process:Ljava/lang/String;
      28: invokevirtual #10                 // Method java/lang/StringBuilder.append:(Ljava/lang/String;)Ljava/lang/StringBuilder;
      31: ldc           #12                 // String ]
      33: invokevirtual #10                 // Method java/lang/StringBuilder.append:(Ljava/lang/String;)Ljava/lang/StringBuilder;
      36: invokevirtual #13                 // Method java/lang/StringBuilder.toString:()Ljava/lang/String;
      39: areturn

  public org.hpccsystems.ws.client.gen.axis2.wspackageprocess.v1_04.ListPackageRequest getRaw();
    Code:
       0: new           #14                 // class org/hpccsystems/ws/client/gen/axis2/wspackageprocess/v1_04/ListPackageRequest
       3: dup
       4: invokespecial #15                 // Method org/hpccsystems/ws/client/gen/axis2/wspackageprocess/v1_04/ListPackageRequest."<init>":()V
       7: astore_1
       8: aload_1
       9: aload_0
      10: getfield      #3                  // Field local_target:Ljava/lang/String;
      13: invokevirtual #16                 // Method org/hpccsystems/ws/client/gen/axis2/wspackageprocess/v1_04/ListPackageRequest.setTarget:(Ljava/lang/String;)V
      16: aload_1
      17: aload_0
      18: getfield      #4                  // Field local_process:Ljava/lang/String;
      21: invokevirtual #17                 // Method org/hpccsystems/ws/client/gen/axis2/wspackageprocess/v1_04/ListPackageRequest.setProcess:(Ljava/lang/String;)V
      24: aload_1
      25: areturn

  public void setTarget(java.lang.String);
    Code:
       0: aload_0
       1: aload_1
       2: putfield      #3                  // Field local_target:Ljava/lang/String;
       5: return

  public java.lang.String getTarget();
    Code:
       0: aload_0
       1: getfield      #3                  // Field local_target:Ljava/lang/String;
       4: areturn

  public void setProcess(java.lang.String);
    Code:
       0: aload_0
       1: aload_1
       2: putfield      #4                  // Field local_process:Ljava/lang/String;
       5: return

  public java.lang.String getProcess();
    Code:
       0: aload_0
       1: getfield      #4                  // Field local_process:Ljava/lang/String;
       4: areturn
}
