Compiled from "ListExternalizer.java"
public class org.infinispan.marshall.exts.ListExternalizer extends org.infinispan.commons.marshall.AbstractExternalizer<java.util.List> {
  private static final int ARRAY_LIST;

  private static final int LINKED_LIST;

  private final org.jboss.marshalling.util.IdentityIntMap<java.lang.Class<?>> numbers;

  public org.infinispan.marshall.exts.ListExternalizer();
    Code:
       0: aload_0
       1: invokespecial #1                  // Method org/infinispan/commons/marshall/AbstractExternalizer."<init>":()V
       4: aload_0
       5: new           #2                  // class org/jboss/marshalling/util/IdentityIntMap
       8: dup
       9: iconst_2
      10: invokespecial #3                  // Method org/jboss/marshalling/util/IdentityIntMap."<init>":(I)V
      13: putfield      #4                  // Field numbers:Lorg/jboss/marshalling/util/IdentityIntMap;
      16: aload_0
      17: getfield      #4                  // Field numbers:Lorg/jboss/marshalling/util/IdentityIntMap;
      20: ldc           #5                  // class java/util/ArrayList
      22: iconst_0
      23: invokevirtual #7                  // Method org/jboss/marshalling/util/IdentityIntMap.put:(Ljava/lang/Object;I)V
      26: aload_0
      27: getfield      #4                  // Field numbers:Lorg/jboss/marshalling/util/IdentityIntMap;
      30: aload_0
      31: invokespecial #8                  // Method getPrivateArrayListClass:()Ljava/lang/Class;
      34: iconst_0
      35: invokevirtual #7                  // Method org/jboss/marshalling/util/IdentityIntMap.put:(Ljava/lang/Object;I)V
      38: aload_0
      39: getfield      #4                  // Field numbers:Lorg/jboss/marshalling/util/IdentityIntMap;
      42: ldc           #9                  // class java/util/LinkedList
      44: iconst_1
      45: invokevirtual #7                  // Method org/jboss/marshalling/util/IdentityIntMap.put:(Ljava/lang/Object;I)V
      48: return

  public void writeObject(java.io.ObjectOutput, java.util.List) throws java.io.IOException;
    Code:
       0: aload_0
       1: getfield      #4                  // Field numbers:Lorg/jboss/marshalling/util/IdentityIntMap;
       4: aload_2
       5: invokevirtual #10                 // Method java/lang/Object.getClass:()Ljava/lang/Class;
       8: iconst_m1
       9: invokevirtual #11                 // Method org/jboss/marshalling/util/IdentityIntMap.get:(Ljava/lang/Object;I)I
      12: istore_3
      13: aload_1
      14: iload_3
      15: invokeinterface #12,  2           // InterfaceMethod java/io/ObjectOutput.writeByte:(I)V
      20: aload_2
      21: aload_1
      22: invokestatic  #13                 // Method org/infinispan/commons/marshall/MarshallUtil.marshallCollection:(Ljava/util/Collection;Ljava/io/ObjectOutput;)V
      25: return

  public java.util.List readObject(java.io.ObjectInput) throws java.io.IOException, java.lang.ClassNotFoundException;
    Code:
       0: aload_1
       1: invokeinterface #14,  1           // InterfaceMethod java/io/ObjectInput.readUnsignedByte:()I
       6: istore_2
       7: aload_1
       8: invokestatic  #15                 // Method org/infinispan/commons/io/UnsignedNumeric.readUnsignedInt:(Ljava/io/ObjectInput;)I
      11: istore_3
      12: aconst_null
      13: astore        4
      15: iload_2
      16: lookupswitch  { // 2
                     0: 44
                     1: 57
               default: 66
          }
      44: new           #5                  // class java/util/ArrayList
      47: dup
      48: iload_3
      49: invokespecial #16                 // Method java/util/ArrayList."<init>":(I)V
      52: astore        4
      54: goto          66
      57: new           #9                  // class java/util/LinkedList
      60: dup
      61: invokespecial #17                 // Method java/util/LinkedList."<init>":()V
      64: astore        4
      66: iconst_0
      67: istore        5
      69: iload         5
      71: iload_3
      72: if_icmpge     95
      75: aload         4
      77: aload_1
      78: invokeinterface #18,  1           // InterfaceMethod java/io/ObjectInput.readObject:()Ljava/lang/Object;
      83: invokeinterface #19,  2           // InterfaceMethod java/util/List.add:(Ljava/lang/Object;)Z
      88: pop
      89: iinc          5, 1
      92: goto          69
      95: aload         4
      97: areturn

  public java.lang.Integer getId();
    Code:
       0: iconst_0
       1: invokestatic  #21                 // Method java/lang/Integer.valueOf:(I)Ljava/lang/Integer;
       4: areturn

  public java.util.Set<java.lang.Class<? extends java.util.List>> getTypeClasses();
    Code:
       0: iconst_3
       1: anewarray     #22                 // class java/lang/Class
       4: dup
       5: iconst_0
       6: ldc           #5                  // class java/util/ArrayList
       8: aastore
       9: dup
      10: iconst_1
      11: ldc           #9                  // class java/util/LinkedList
      13: aastore
      14: dup
      15: iconst_2
      16: aload_0
      17: invokespecial #8                  // Method getPrivateArrayListClass:()Ljava/lang/Class;
      20: aastore
      21: invokestatic  #23                 // Method org/infinispan/commons/util/Util.asSet:([Ljava/lang/Object;)Ljava/util/Set;
      24: areturn

  private java.lang.Class<java.util.List> getPrivateArrayListClass();
    Code:
       0: ldc           #24                 // String java.util.Arrays$ArrayList
       2: ldc           #25                 // class java/util/List
       4: invokevirtual #26                 // Method java/lang/Class.getClassLoader:()Ljava/lang/ClassLoader;
       7: invokestatic  #27                 // Method org/infinispan/commons/util/Util.loadClass:(Ljava/lang/String;Ljava/lang/ClassLoader;)Ljava/lang/Class;
      10: areturn

  public java.lang.Object readObject(java.io.ObjectInput) throws java.io.IOException, java.lang.ClassNotFoundException;
    Code:
       0: aload_0
       1: aload_1
       2: invokevirtual #28                 // Method readObject:(Ljava/io/ObjectInput;)Ljava/util/List;
       5: areturn

  public void writeObject(java.io.ObjectOutput, java.lang.Object) throws java.io.IOException;
    Code:
       0: aload_0
       1: aload_1
       2: aload_2
       3: checkcast     #25                 // class java/util/List
       6: invokevirtual #29                 // Method writeObject:(Ljava/io/ObjectOutput;Ljava/util/List;)V
       9: return
}
