Compiled from "AttestationContainer.java"
class edu.internet2.middleware.grouper.grouperUi.beans.ui.AttestationContainer$1 implements edu.internet2.middleware.grouper.misc.GrouperSessionHandler {
  final edu.internet2.middleware.grouper.attr.assign.AttributeAssign val$attributeAssign;

  final edu.internet2.middleware.grouper.grouperUi.beans.ui.AttestationContainer this$0;

  edu.internet2.middleware.grouper.grouperUi.beans.ui.AttestationContainer$1(edu.internet2.middleware.grouper.grouperUi.beans.ui.AttestationContainer, edu.internet2.middleware.grouper.attr.assign.AttributeAssign);
    Code:
       0: aload_0
       1: aload_1
       2: putfield      #1                  // Field this$0:Ledu/internet2/middleware/grouper/grouperUi/beans/ui/AttestationContainer;
       5: aload_0
       6: aload_2
       7: putfield      #2                  // Field val$attributeAssign:Ledu/internet2/middleware/grouper/attr/assign/AttributeAssign;
      10: aload_0
      11: invokespecial #3                  // Method java/lang/Object."<init>":()V
      14: return

  public java.lang.Object callback(edu.internet2.middleware.grouper.GrouperSession) throws edu.internet2.middleware.grouper.exception.GrouperSessionException;
    Code:
       0: aload_0
       1: getfield      #2                  // Field val$attributeAssign:Ledu/internet2/middleware/grouper/attr/assign/AttributeAssign;
       4: invokevirtual #4                  // Method edu/internet2/middleware/grouper/attr/assign/AttributeAssign.getAttributeValueDelegate:()Ledu/internet2/middleware/grouper/attr/value/AttributeValueDelegate;
       7: invokestatic  #5                  // Method edu/internet2/middleware/grouper/app/attestation/GrouperAttestationJob.retrieveAttributeDefNameReportConfigurationId:()Ledu/internet2/middleware/grouper/attr/AttributeDefName;
      10: invokevirtual #6                  // Method edu/internet2/middleware/grouper/attr/AttributeDefName.getName:()Ljava/lang/String;
      13: invokevirtual #7                  // Method edu/internet2/middleware/grouper/attr/value/AttributeValueDelegate.retrieveValueString:(Ljava/lang/String;)Ljava/lang/String;
      16: astore_2
      17: aload_2
      18: ifnonnull     23
      21: aconst_null
      22: areturn
      23: aload_0
      24: getfield      #2                  // Field val$attributeAssign:Ledu/internet2/middleware/grouper/attr/assign/AttributeAssign;
      27: invokevirtual #8                  // Method edu/internet2/middleware/grouper/attr/assign/AttributeAssign.getOwnerStemId:()Ljava/lang/String;
      30: ifnull        54
      33: aload_0
      34: getfield      #2                  // Field val$attributeAssign:Ledu/internet2/middleware/grouper/attr/assign/AttributeAssign;
      37: invokevirtual #9                  // Method edu/internet2/middleware/grouper/attr/assign/AttributeAssign.getOwnerStem:()Ledu/internet2/middleware/grouper/Stem;
      40: aload_2
      41: invokestatic  #10                 // Method edu/internet2/middleware/grouper/app/reports/GrouperReportInstanceService.getMostRecentReportInstance:(Ledu/internet2/middleware/grouper/misc/GrouperObject;Ljava/lang/String;)Ledu/internet2/middleware/grouper/app/reports/GrouperReportInstance;
      44: astore_3
      45: aload_3
      46: ifnull        54
      49: aload_3
      50: invokevirtual #11                 // Method edu/internet2/middleware/grouper/app/reports/GrouperReportInstance.getAttributeAssignId:()Ljava/lang/String;
      53: areturn
      54: aconst_null
      55: areturn
}
