Compiled from "TemplateContainerConfig.java"
public class edu.internet2.middleware.grouper.grouperUi.beans.ui.TemplateContainerConfig {
  private java.lang.String configKey;

  private java.lang.String logicClassName;

  private edu.internet2.middleware.grouper.grouperUi.beans.ui.GrouperTemplateLogicBase logicInstance;

  public edu.internet2.middleware.grouper.grouperUi.beans.ui.TemplateContainerConfig();
    Code:
       0: aload_0
       1: invokespecial #1                  // Method java/lang/Object."<init>":()V
       4: return

  public edu.internet2.middleware.grouper.grouperUi.beans.ui.GrouperTemplateLogicBase getLogicInstance();
    Code:
       0: aload_0
       1: getfield      #2                  // Field logicInstance:Ledu/internet2/middleware/grouper/grouperUi/beans/ui/GrouperTemplateLogicBase;
       4: ifnonnull     28
       7: aload_0
       8: getfield      #3                  // Field logicClassName:Ljava/lang/String;
      11: invokestatic  #4                  // Method edu/internet2/middleware/grouperClient/util/GrouperClientUtils.forName:(Ljava/lang/String;)Ljava/lang/Class;
      14: astore_1
      15: aload_1
      16: invokestatic  #5                  // Method edu/internet2/middleware/grouper/util/GrouperUtil.newInstance:(Ljava/lang/Class;)Ljava/lang/Object;
      19: checkcast     #6                  // class edu/internet2/middleware/grouper/grouperUi/beans/ui/GrouperTemplateLogicBase
      22: astore_2
      23: aload_0
      24: aload_2
      25: putfield      #2                  // Field logicInstance:Ledu/internet2/middleware/grouper/grouperUi/beans/ui/GrouperTemplateLogicBase;
      28: aload_0
      29: getfield      #2                  // Field logicInstance:Ledu/internet2/middleware/grouper/grouperUi/beans/ui/GrouperTemplateLogicBase;
      32: areturn
}
