Compiled from "VisualizationContainer.java"
public class edu.internet2.middleware.grouper.grouperUi.beans.ui.VisualizationContainer {
  private java.lang.String operation;

  private java.lang.String drawModule;

  private java.lang.String drawObjectNameType;

  private java.lang.String objectType;

  private java.lang.String objectId;

  private long drawNumParentsLevels;

  private long drawNumChildrenLevels;

  private long drawMaxSiblings;

  private boolean drawShowStems;

  private boolean drawShowLoaders;

  private boolean drawShowProvisioners;

  private boolean drawShowAllMemberCounts;

  private boolean drawShowDirectMemberCounts;

  private boolean drawShowObjectTypes;

  private boolean drawIncludeGroupsInMemberCounts;

  private boolean drawShowLegend;

  private edu.internet2.middleware.grouper.misc.GrouperObject grouperObject;

  public edu.internet2.middleware.grouper.grouperUi.beans.ui.VisualizationContainer();
    Code:
       0: aload_0
       1: invokespecial #1                  // Method java/lang/Object."<init>":()V
       4: return

  public java.lang.String getOperation();
    Code:
       0: aload_0
       1: getfield      #2                  // Field operation:Ljava/lang/String;
       4: areturn

  public void setOperation(java.lang.String);
    Code:
       0: aload_0
       1: aload_1
       2: putfield      #2                  // Field operation:Ljava/lang/String;
       5: return

  public java.lang.String getDrawModule();
    Code:
       0: aload_0
       1: getfield      #3                  // Field drawModule:Ljava/lang/String;
       4: areturn

  public void setDrawModule(java.lang.String, java.lang.String);
    Code:
       0: aload_0
       1: aload_1
       2: invokestatic  #4                  // Method edu/internet2/middleware/grouper/util/GrouperUtil.isBlank:(Ljava/lang/String;)Z
       5: ifne          12
       8: aload_1
       9: goto          13
      12: aload_2
      13: putfield      #3                  // Field drawModule:Ljava/lang/String;
      16: return

  public java.lang.String getDrawObjectNameType();
    Code:
       0: aload_0
       1: getfield      #5                  // Field drawObjectNameType:Ljava/lang/String;
       4: areturn

  public void setDrawObjectNameType(java.lang.String, java.lang.String);
    Code:
       0: aload_0
       1: aload_1
       2: invokestatic  #4                  // Method edu/internet2/middleware/grouper/util/GrouperUtil.isBlank:(Ljava/lang/String;)Z
       5: ifne          12
       8: aload_1
       9: goto          13
      12: aload_2
      13: putfield      #5                  // Field drawObjectNameType:Ljava/lang/String;
      16: return

  public java.lang.String getObjectType();
    Code:
       0: aload_0
       1: getfield      #6                  // Field objectType:Ljava/lang/String;
       4: areturn

  public void setObjectType(java.lang.String);
    Code:
       0: aload_0
       1: aload_1
       2: putfield      #6                  // Field objectType:Ljava/lang/String;
       5: return

  public java.lang.String getObjectId();
    Code:
       0: aload_0
       1: getfield      #7                  // Field objectId:Ljava/lang/String;
       4: areturn

  public void setObjectId(java.lang.String);
    Code:
       0: aload_0
       1: aload_1
       2: putfield      #7                  // Field objectId:Ljava/lang/String;
       5: return

  public long getDrawNumParentsLevels();
    Code:
       0: aload_0
       1: getfield      #8                  // Field drawNumParentsLevels:J
       4: lreturn

  public void setDrawNumParentsLevels(long);
    Code:
       0: aload_0
       1: lload_1
       2: putfield      #8                  // Field drawNumParentsLevels:J
       5: return

  public long getDrawNumChildrenLevels();
    Code:
       0: aload_0
       1: getfield      #9                  // Field drawNumChildrenLevels:J
       4: lreturn

  public void setDrawNumChildrenLevels(long);
    Code:
       0: aload_0
       1: lload_1
       2: putfield      #9                  // Field drawNumChildrenLevels:J
       5: return

  public long getDrawMaxSiblings();
    Code:
       0: aload_0
       1: getfield      #10                 // Field drawMaxSiblings:J
       4: lreturn

  public void setDrawMaxSiblings(long);
    Code:
       0: aload_0
       1: lload_1
       2: putfield      #10                 // Field drawMaxSiblings:J
       5: return

  public boolean isDrawShowStems();
    Code:
       0: aload_0
       1: getfield      #11                 // Field drawShowStems:Z
       4: ireturn

  public void setDrawShowStems(boolean);
    Code:
       0: aload_0
       1: iload_1
       2: putfield      #11                 // Field drawShowStems:Z
       5: return

  public boolean isDrawShowLoaders();
    Code:
       0: aload_0
       1: getfield      #12                 // Field drawShowLoaders:Z
       4: ireturn

  public void setDrawShowLoaders(boolean);
    Code:
       0: aload_0
       1: iload_1
       2: putfield      #12                 // Field drawShowLoaders:Z
       5: return

  public boolean isDrawShowProvisioners();
    Code:
       0: aload_0
       1: getfield      #13                 // Field drawShowProvisioners:Z
       4: ireturn

  public void setDrawShowProvisioners(boolean);
    Code:
       0: aload_0
       1: iload_1
       2: putfield      #13                 // Field drawShowProvisioners:Z
       5: return

  public boolean isDrawShowAllMemberCounts();
    Code:
       0: aload_0
       1: getfield      #14                 // Field drawShowAllMemberCounts:Z
       4: ireturn

  public void setDrawShowAllMemberCounts(boolean);
    Code:
       0: aload_0
       1: iload_1
       2: putfield      #14                 // Field drawShowAllMemberCounts:Z
       5: return

  public boolean isDrawShowDirectMemberCounts();
    Code:
       0: aload_0
       1: getfield      #15                 // Field drawShowDirectMemberCounts:Z
       4: ireturn

  public void setDrawShowDirectMemberCounts(boolean);
    Code:
       0: aload_0
       1: iload_1
       2: putfield      #15                 // Field drawShowDirectMemberCounts:Z
       5: return

  public boolean isDrawShowObjectTypes();
    Code:
       0: aload_0
       1: getfield      #16                 // Field drawShowObjectTypes:Z
       4: ireturn

  public void setDrawShowObjectTypes(boolean);
    Code:
       0: aload_0
       1: iload_1
       2: putfield      #16                 // Field drawShowObjectTypes:Z
       5: return

  public boolean isDrawIncludeGroupsInMemberCounts();
    Code:
       0: aload_0
       1: getfield      #17                 // Field drawIncludeGroupsInMemberCounts:Z
       4: ireturn

  public void setDrawIncludeGroupsInMemberCounts(boolean);
    Code:
       0: aload_0
       1: iload_1
       2: putfield      #17                 // Field drawIncludeGroupsInMemberCounts:Z
       5: return

  public boolean isDrawShowLegend();
    Code:
       0: aload_0
       1: getfield      #18                 // Field drawShowLegend:Z
       4: ireturn

  public void setDrawShowLegend(boolean);
    Code:
       0: aload_0
       1: iload_1
       2: putfield      #18                 // Field drawShowLegend:Z
       5: return

  public edu.internet2.middleware.grouper.misc.GrouperObject getGrouperObject();
    Code:
       0: aload_0
       1: getfield      #19                 // Field grouperObject:Ledu/internet2/middleware/grouper/misc/GrouperObject;
       4: ifnonnull     178
       7: invokestatic  #20                 // Method edu/internet2/middleware/grouper/ui/GrouperUiFilter.retrieveSubjectLoggedIn:()Ledu/internet2/middleware/subject/Subject;
      10: astore_1
      11: invokestatic  #21                 // Method edu/internet2/middleware/grouper/GrouperSession.staticGrouperSession:()Ledu/internet2/middleware/grouper/GrouperSession;
      14: astore_2
      15: ldc           #22                 // String group
      17: aload_0
      18: invokevirtual #23                 // Method getObjectType:()Ljava/lang/String;
      21: invokevirtual #24                 // Method java/lang/String.equals:(Ljava/lang/Object;)Z
      24: ifeq          43
      27: aload_0
      28: aload_2
      29: aload_0
      30: invokevirtual #25                 // Method getObjectId:()Ljava/lang/String;
      33: iconst_1
      34: invokestatic  #26                 // Method edu/internet2/middleware/grouper/GroupFinder.findByUuid:(Ledu/internet2/middleware/grouper/GrouperSession;Ljava/lang/String;Z)Ledu/internet2/middleware/grouper/Group;
      37: putfield      #19                 // Field grouperObject:Ledu/internet2/middleware/grouper/misc/GrouperObject;
      40: goto          178
      43: ldc           #27                 // String stem
      45: aload_0
      46: invokevirtual #23                 // Method getObjectType:()Ljava/lang/String;
      49: invokevirtual #24                 // Method java/lang/String.equals:(Ljava/lang/Object;)Z
      52: ifeq          71
      55: aload_0
      56: aload_2
      57: aload_0
      58: invokevirtual #25                 // Method getObjectId:()Ljava/lang/String;
      61: iconst_1
      62: invokestatic  #28                 // Method edu/internet2/middleware/grouper/StemFinder.findByUuid:(Ledu/internet2/middleware/grouper/GrouperSession;Ljava/lang/String;Z)Ledu/internet2/middleware/grouper/Stem;
      65: putfield      #19                 // Field grouperObject:Ledu/internet2/middleware/grouper/misc/GrouperObject;
      68: goto          178
      71: ldc           #29                 // String subject
      73: aload_0
      74: invokevirtual #23                 // Method getObjectType:()Ljava/lang/String;
      77: invokevirtual #24                 // Method java/lang/String.equals:(Ljava/lang/Object;)Z
      80: ifeq          143
      83: aload_0
      84: invokevirtual #25                 // Method getObjectId:()Ljava/lang/String;
      87: ldc           #30                 // String ||||
      89: invokestatic  #31                 // Method edu/internet2/middleware/grouper/util/GrouperUtil.split:(Ljava/lang/String;Ljava/lang/String;)[Ljava/lang/String;
      92: astore_3
      93: aconst_null
      94: astore        4
      96: aload_3
      97: arraylength
      98: iconst_2
      99: if_icmplt     117
     102: aload_3
     103: iconst_1
     104: aaload
     105: aload_3
     106: iconst_0
     107: aaload
     108: iconst_1
     109: invokestatic  #32                 // Method edu/internet2/middleware/grouper/SubjectFinder.findByIdAndSource:(Ljava/lang/String;Ljava/lang/String;Z)Ledu/internet2/middleware/subject/Subject;
     112: astore        4
     114: goto          127
     117: aload_0
     118: invokevirtual #25                 // Method getObjectId:()Ljava/lang/String;
     121: iconst_1
     122: invokestatic  #33                 // Method edu/internet2/middleware/grouper/SubjectFinder.findById:(Ljava/lang/String;Z)Ledu/internet2/middleware/subject/Subject;
     125: astore        4
     127: aload_0
     128: new           #34                 // class edu/internet2/middleware/grouper/misc/GrouperObjectSubjectWrapper
     131: dup
     132: aload         4
     134: invokespecial #35                 // Method edu/internet2/middleware/grouper/misc/GrouperObjectSubjectWrapper."<init>":(Ledu/internet2/middleware/subject/Subject;)V
     137: putfield      #19                 // Field grouperObject:Ledu/internet2/middleware/grouper/misc/GrouperObject;
     140: goto          178
     143: new           #36                 // class java/lang/RuntimeException
     146: dup
     147: new           #37                 // class java/lang/StringBuilder
     150: dup
     151: invokespecial #38                 // Method java/lang/StringBuilder."<init>":()V
     154: ldc           #39                 // String Unknown object type \'
     156: invokevirtual #40                 // Method java/lang/StringBuilder.append:(Ljava/lang/String;)Ljava/lang/StringBuilder;
     159: aload_0
     160: invokevirtual #23                 // Method getObjectType:()Ljava/lang/String;
     163: invokevirtual #40                 // Method java/lang/StringBuilder.append:(Ljava/lang/String;)Ljava/lang/StringBuilder;
     166: ldc           #41                 // String \'
     168: invokevirtual #40                 // Method java/lang/StringBuilder.append:(Ljava/lang/String;)Ljava/lang/StringBuilder;
     171: invokevirtual #42                 // Method java/lang/StringBuilder.toString:()Ljava/lang/String;
     174: invokespecial #43                 // Method java/lang/RuntimeException."<init>":(Ljava/lang/String;)V
     177: athrow
     178: aload_0
     179: getfield      #19                 // Field grouperObject:Ledu/internet2/middleware/grouper/misc/GrouperObject;
     182: areturn
}
