Compiled from "WorkflowContainer.java"
class edu.internet2.middleware.grouper.grouperUi.beans.ui.WorkflowContainer$4 implements edu.internet2.middleware.grouper.misc.GrouperSessionHandler {
  final edu.internet2.middleware.subject.Subject val$loggedInSubject;

  final edu.internet2.middleware.grouper.grouperUi.beans.ui.WorkflowContainer this$0;

  edu.internet2.middleware.grouper.grouperUi.beans.ui.WorkflowContainer$4(edu.internet2.middleware.grouper.grouperUi.beans.ui.WorkflowContainer, edu.internet2.middleware.subject.Subject);
    Code:
       0: aload_0
       1: aload_1
       2: putfield      #1                  // Field this$0:Ledu/internet2/middleware/grouper/grouperUi/beans/ui/WorkflowContainer;
       5: aload_0
       6: aload_2
       7: putfield      #2                  // Field val$loggedInSubject:Ledu/internet2/middleware/subject/Subject;
      10: aload_0
      11: invokespecial #3                  // Method java/lang/Object."<init>":()V
      14: return

  public java.lang.Object callback(edu.internet2.middleware.grouper.GrouperSession) throws edu.internet2.middleware.grouper.exception.GrouperSessionException;
    Code:
       0: aload_0
       1: getfield      #1                  // Field this$0:Ledu/internet2/middleware/grouper/grouperUi/beans/ui/WorkflowContainer;
       4: invokestatic  #4                  // Method edu/internet2/middleware/grouper/grouperUi/beans/ui/WorkflowContainer.access$000:(Ledu/internet2/middleware/grouper/grouperUi/beans/ui/WorkflowContainer;)Ledu/internet2/middleware/grouper/grouperUi/beans/ui/GuiGrouperWorkflowInstance;
       7: invokevirtual #5                  // Method edu/internet2/middleware/grouper/grouperUi/beans/ui/GuiGrouperWorkflowInstance.getGrouperWorkflowInstance:()Ledu/internet2/middleware/grouper/app/workflow/GrouperWorkflowInstance;
      10: aload_0
      11: getfield      #2                  // Field val$loggedInSubject:Ledu/internet2/middleware/subject/Subject;
      14: invokestatic  #6                  // Method edu/internet2/middleware/grouper/app/workflow/GrouperWorkflowInstanceService.canInstanceBeApproved:(Ledu/internet2/middleware/grouper/app/workflow/GrouperWorkflowInstance;Ledu/internet2/middleware/subject/Subject;)Z
      17: invokestatic  #7                  // Method java/lang/Boolean.valueOf:(Z)Ljava/lang/Boolean;
      20: areturn
}
