Compiled from "SimpleInstanceAttributeCopier.java"
public class org.infinispan.commons.configuration.attributes.SimpleInstanceAttributeCopier<T> implements org.infinispan.commons.configuration.attributes.AttributeCopier<T> {
  public static final org.infinispan.commons.configuration.attributes.AttributeCopier<java.lang.Object> INSTANCE;

  private org.infinispan.commons.configuration.attributes.SimpleInstanceAttributeCopier();
    Code:
       0: aload_0
       1: invokespecial #1                  // Method java/lang/Object."<init>":()V
       4: return

  public T copyAttribute(T);
    Code:
       0: aload_1
       1: ifnonnull     6
       4: aconst_null
       5: areturn
       6: aload_1
       7: invokevirtual #2                  // Method java/lang/Object.getClass:()Ljava/lang/Class;
      10: invokestatic  #3                  // Method org/infinispan/commons/util/Util.getInstance:(Ljava/lang/Class;)Ljava/lang/Object;
      13: areturn

  static {};
    Code:
       0: new           #4                  // class org/infinispan/commons/configuration/attributes/SimpleInstanceAttributeCopier
       3: dup
       4: invokespecial #5                  // Method "<init>":()V
       7: putstatic     #6                  // Field INSTANCE:Lorg/infinispan/commons/configuration/attributes/AttributeCopier;
      10: return
}
