Compiled from "TypedPropertiesAttributeCopier.java"
public class org.infinispan.commons.configuration.attributes.TypedPropertiesAttributeCopier implements org.infinispan.commons.configuration.attributes.AttributeCopier<org.infinispan.commons.util.TypedProperties> {
  public static final org.infinispan.commons.configuration.attributes.AttributeCopier<org.infinispan.commons.util.TypedProperties> INSTANCE;

  public org.infinispan.commons.configuration.attributes.TypedPropertiesAttributeCopier();
    Code:
       0: aload_0
       1: invokespecial #1                  // Method java/lang/Object."<init>":()V
       4: return

  public org.infinispan.commons.util.TypedProperties copyAttribute(org.infinispan.commons.util.TypedProperties);
    Code:
       0: new           #2                  // class org/infinispan/commons/util/TypedProperties
       3: dup
       4: aload_1
       5: invokespecial #3                  // Method org/infinispan/commons/util/TypedProperties."<init>":(Ljava/util/Properties;)V
       8: areturn

  public java.lang.Object copyAttribute(java.lang.Object);
    Code:
       0: aload_0
       1: aload_1
       2: checkcast     #2                  // class org/infinispan/commons/util/TypedProperties
       5: invokevirtual #4                  // Method copyAttribute:(Lorg/infinispan/commons/util/TypedProperties;)Lorg/infinispan/commons/util/TypedProperties;
       8: areturn

  static {};
    Code:
       0: new           #5                  // class org/infinispan/commons/configuration/attributes/TypedPropertiesAttributeCopier
       3: dup
       4: invokespecial #6                  // Method "<init>":()V
       7: putstatic     #7                  // Field INSTANCE:Lorg/infinispan/commons/configuration/attributes/AttributeCopier;
      10: return
}
