Compiled from "CaptionDescription.java"
final class software.amazon.awssdk.services.mediaconvert.model.CaptionDescription$BuilderImpl implements software.amazon.awssdk.services.mediaconvert.model.CaptionDescription$Builder {
  private java.lang.String captionSelectorName;

  private java.lang.String customLanguageCode;

  private software.amazon.awssdk.services.mediaconvert.model.CaptionDestinationSettings destinationSettings;

  private java.lang.String languageCode;

  private java.lang.String languageDescription;

  private software.amazon.awssdk.services.mediaconvert.model.CaptionDescription$BuilderImpl();
    Code:
       0: aload_0
       1: invokespecial #8                  // Method java/lang/Object."<init>":()V
       4: return

  private software.amazon.awssdk.services.mediaconvert.model.CaptionDescription$BuilderImpl(software.amazon.awssdk.services.mediaconvert.model.CaptionDescription);
    Code:
       0: aload_0
       1: invokespecial #8                  // Method java/lang/Object."<init>":()V
       4: aload_0
       5: aload_1
       6: invokestatic  #9                  // Method software/amazon/awssdk/services/mediaconvert/model/CaptionDescription.access$700:(Lsoftware/amazon/awssdk/services/mediaconvert/model/CaptionDescription;)Ljava/lang/String;
       9: invokevirtual #10                 // Method captionSelectorName:(Ljava/lang/String;)Lsoftware/amazon/awssdk/services/mediaconvert/model/CaptionDescription$Builder;
      12: pop
      13: aload_0
      14: aload_1
      15: invokestatic  #11                 // Method software/amazon/awssdk/services/mediaconvert/model/CaptionDescription.access$800:(Lsoftware/amazon/awssdk/services/mediaconvert/model/CaptionDescription;)Ljava/lang/String;
      18: invokevirtual #12                 // Method customLanguageCode:(Ljava/lang/String;)Lsoftware/amazon/awssdk/services/mediaconvert/model/CaptionDescription$Builder;
      21: pop
      22: aload_0
      23: aload_1
      24: invokestatic  #13                 // Method software/amazon/awssdk/services/mediaconvert/model/CaptionDescription.access$900:(Lsoftware/amazon/awssdk/services/mediaconvert/model/CaptionDescription;)Lsoftware/amazon/awssdk/services/mediaconvert/model/CaptionDestinationSettings;
      27: invokevirtual #14                 // Method destinationSettings:(Lsoftware/amazon/awssdk/services/mediaconvert/model/CaptionDestinationSettings;)Lsoftware/amazon/awssdk/services/mediaconvert/model/CaptionDescription$Builder;
      30: pop
      31: aload_0
      32: aload_1
      33: invokestatic  #15                 // Method software/amazon/awssdk/services/mediaconvert/model/CaptionDescription.access$1000:(Lsoftware/amazon/awssdk/services/mediaconvert/model/CaptionDescription;)Ljava/lang/String;
      36: invokevirtual #16                 // Method languageCode:(Ljava/lang/String;)Lsoftware/amazon/awssdk/services/mediaconvert/model/CaptionDescription$Builder;
      39: pop
      40: aload_0
      41: aload_1
      42: invokestatic  #17                 // Method software/amazon/awssdk/services/mediaconvert/model/CaptionDescription.access$1100:(Lsoftware/amazon/awssdk/services/mediaconvert/model/CaptionDescription;)Ljava/lang/String;
      45: invokevirtual #18                 // Method languageDescription:(Ljava/lang/String;)Lsoftware/amazon/awssdk/services/mediaconvert/model/CaptionDescription$Builder;
      48: pop
      49: return

  public final java.lang.String getCaptionSelectorName();
    Code:
       0: aload_0
       1: getfield      #7                  // Field captionSelectorName:Ljava/lang/String;
       4: areturn

  public final software.amazon.awssdk.services.mediaconvert.model.CaptionDescription$Builder captionSelectorName(java.lang.String);
    Code:
       0: aload_0
       1: aload_1
       2: putfield      #7                  // Field captionSelectorName:Ljava/lang/String;
       5: aload_0
       6: areturn

  public final void setCaptionSelectorName(java.lang.String);
    Code:
       0: aload_0
       1: aload_1
       2: putfield      #7                  // Field captionSelectorName:Ljava/lang/String;
       5: return

  public final java.lang.String getCustomLanguageCode();
    Code:
       0: aload_0
       1: getfield      #6                  // Field customLanguageCode:Ljava/lang/String;
       4: areturn

  public final software.amazon.awssdk.services.mediaconvert.model.CaptionDescription$Builder customLanguageCode(java.lang.String);
    Code:
       0: aload_0
       1: aload_1
       2: putfield      #6                  // Field customLanguageCode:Ljava/lang/String;
       5: aload_0
       6: areturn

  public final void setCustomLanguageCode(java.lang.String);
    Code:
       0: aload_0
       1: aload_1
       2: putfield      #6                  // Field customLanguageCode:Ljava/lang/String;
       5: return

  public final software.amazon.awssdk.services.mediaconvert.model.CaptionDestinationSettings$Builder getDestinationSettings();
    Code:
       0: aload_0
       1: getfield      #5                  // Field destinationSettings:Lsoftware/amazon/awssdk/services/mediaconvert/model/CaptionDestinationSettings;
       4: ifnull        17
       7: aload_0
       8: getfield      #5                  // Field destinationSettings:Lsoftware/amazon/awssdk/services/mediaconvert/model/CaptionDestinationSettings;
      11: invokevirtual #19                 // Method software/amazon/awssdk/services/mediaconvert/model/CaptionDestinationSettings.toBuilder:()Lsoftware/amazon/awssdk/services/mediaconvert/model/CaptionDestinationSettings$Builder;
      14: goto          18
      17: aconst_null
      18: areturn

  public final software.amazon.awssdk.services.mediaconvert.model.CaptionDescription$Builder destinationSettings(software.amazon.awssdk.services.mediaconvert.model.CaptionDestinationSettings);
    Code:
       0: aload_0
       1: aload_1
       2: putfield      #5                  // Field destinationSettings:Lsoftware/amazon/awssdk/services/mediaconvert/model/CaptionDestinationSettings;
       5: aload_0
       6: areturn

  public final void setDestinationSettings(software.amazon.awssdk.services.mediaconvert.model.CaptionDestinationSettings$BuilderImpl);
    Code:
       0: aload_0
       1: aload_1
       2: ifnull        12
       5: aload_1
       6: invokevirtual #20                 // Method software/amazon/awssdk/services/mediaconvert/model/CaptionDestinationSettings$BuilderImpl.build:()Lsoftware/amazon/awssdk/services/mediaconvert/model/CaptionDestinationSettings;
       9: goto          13
      12: aconst_null
      13: putfield      #5                  // Field destinationSettings:Lsoftware/amazon/awssdk/services/mediaconvert/model/CaptionDestinationSettings;
      16: return

  public final java.lang.String getLanguageCodeAsString();
    Code:
       0: aload_0
       1: getfield      #4                  // Field languageCode:Ljava/lang/String;
       4: areturn

  public final software.amazon.awssdk.services.mediaconvert.model.CaptionDescription$Builder languageCode(java.lang.String);
    Code:
       0: aload_0
       1: aload_1
       2: putfield      #4                  // Field languageCode:Ljava/lang/String;
       5: aload_0
       6: areturn

  public final software.amazon.awssdk.services.mediaconvert.model.CaptionDescription$Builder languageCode(software.amazon.awssdk.services.mediaconvert.model.LanguageCode);
    Code:
       0: aload_0
       1: aload_1
       2: ifnonnull     9
       5: aconst_null
       6: goto          13
       9: aload_1
      10: invokevirtual #21                 // Method software/amazon/awssdk/services/mediaconvert/model/LanguageCode.toString:()Ljava/lang/String;
      13: invokevirtual #16                 // Method languageCode:(Ljava/lang/String;)Lsoftware/amazon/awssdk/services/mediaconvert/model/CaptionDescription$Builder;
      16: pop
      17: aload_0
      18: areturn

  public final void setLanguageCode(java.lang.String);
    Code:
       0: aload_0
       1: aload_1
       2: putfield      #4                  // Field languageCode:Ljava/lang/String;
       5: return

  public final java.lang.String getLanguageDescription();
    Code:
       0: aload_0
       1: getfield      #3                  // Field languageDescription:Ljava/lang/String;
       4: areturn

  public final software.amazon.awssdk.services.mediaconvert.model.CaptionDescription$Builder languageDescription(java.lang.String);
    Code:
       0: aload_0
       1: aload_1
       2: putfield      #3                  // Field languageDescription:Ljava/lang/String;
       5: aload_0
       6: areturn

  public final void setLanguageDescription(java.lang.String);
    Code:
       0: aload_0
       1: aload_1
       2: putfield      #3                  // Field languageDescription:Ljava/lang/String;
       5: return

  public software.amazon.awssdk.services.mediaconvert.model.CaptionDescription build();
    Code:
       0: new           #22                 // class software/amazon/awssdk/services/mediaconvert/model/CaptionDescription
       3: dup
       4: aload_0
       5: aconst_null
       6: invokespecial #23                 // Method software/amazon/awssdk/services/mediaconvert/model/CaptionDescription."<init>":(Lsoftware/amazon/awssdk/services/mediaconvert/model/CaptionDescription$BuilderImpl;Lsoftware/amazon/awssdk/services/mediaconvert/model/CaptionDescription$1;)V
       9: areturn

  public java.util.List<software.amazon.awssdk.core.SdkField<?>> sdkFields();
    Code:
       0: invokestatic  #24                 // Method software/amazon/awssdk/services/mediaconvert/model/CaptionDescription.access$1300:()Ljava/util/List;
       3: areturn

  public java.lang.Object build();
    Code:
       0: aload_0
       1: invokevirtual #25                 // Method build:()Lsoftware/amazon/awssdk/services/mediaconvert/model/CaptionDescription;
       4: areturn

  static java.lang.String access$000(software.amazon.awssdk.services.mediaconvert.model.CaptionDescription$BuilderImpl);
    Code:
       0: aload_0
       1: getfield      #7                  // Field captionSelectorName:Ljava/lang/String;
       4: areturn

  static java.lang.String access$100(software.amazon.awssdk.services.mediaconvert.model.CaptionDescription$BuilderImpl);
    Code:
       0: aload_0
       1: getfield      #6                  // Field customLanguageCode:Ljava/lang/String;
       4: areturn

  static software.amazon.awssdk.services.mediaconvert.model.CaptionDestinationSettings access$200(software.amazon.awssdk.services.mediaconvert.model.CaptionDescription$BuilderImpl);
    Code:
       0: aload_0
       1: getfield      #5                  // Field destinationSettings:Lsoftware/amazon/awssdk/services/mediaconvert/model/CaptionDestinationSettings;
       4: areturn

  static java.lang.String access$300(software.amazon.awssdk.services.mediaconvert.model.CaptionDescription$BuilderImpl);
    Code:
       0: aload_0
       1: getfield      #4                  // Field languageCode:Ljava/lang/String;
       4: areturn

  static java.lang.String access$400(software.amazon.awssdk.services.mediaconvert.model.CaptionDescription$BuilderImpl);
    Code:
       0: aload_0
       1: getfield      #3                  // Field languageDescription:Ljava/lang/String;
       4: areturn

  software.amazon.awssdk.services.mediaconvert.model.CaptionDescription$BuilderImpl(software.amazon.awssdk.services.mediaconvert.model.CaptionDescription, software.amazon.awssdk.services.mediaconvert.model.CaptionDescription$1);
    Code:
       0: aload_0
       1: aload_1
       2: invokespecial #2                  // Method "<init>":(Lsoftware/amazon/awssdk/services/mediaconvert/model/CaptionDescription;)V
       5: return

  software.amazon.awssdk.services.mediaconvert.model.CaptionDescription$BuilderImpl(software.amazon.awssdk.services.mediaconvert.model.CaptionDescription$1);
    Code:
       0: aload_0
       1: invokespecial #1                  // Method "<init>":()V
       4: return
}
