Compiled from "HlsSettings.java"
public final class software.amazon.awssdk.services.mediaconvert.model.HlsSettings implements software.amazon.awssdk.core.SdkPojo, java.io.Serializable, software.amazon.awssdk.utils.builder.ToCopyableBuilder<software.amazon.awssdk.services.mediaconvert.model.HlsSettings$Builder, software.amazon.awssdk.services.mediaconvert.model.HlsSettings> {
  private static final software.amazon.awssdk.core.SdkField<java.lang.String> AUDIO_GROUP_ID_FIELD;

  private static final software.amazon.awssdk.core.SdkField<java.lang.String> AUDIO_ONLY_CONTAINER_FIELD;

  private static final software.amazon.awssdk.core.SdkField<java.lang.String> AUDIO_RENDITION_SETS_FIELD;

  private static final software.amazon.awssdk.core.SdkField<java.lang.String> AUDIO_TRACK_TYPE_FIELD;

  private static final software.amazon.awssdk.core.SdkField<java.lang.String> I_FRAME_ONLY_MANIFEST_FIELD;

  private static final software.amazon.awssdk.core.SdkField<java.lang.String> SEGMENT_MODIFIER_FIELD;

  private static final java.util.List<software.amazon.awssdk.core.SdkField<?>> SDK_FIELDS;

  private static final long serialVersionUID;

  private final java.lang.String audioGroupId;

  private final java.lang.String audioOnlyContainer;

  private final java.lang.String audioRenditionSets;

  private final java.lang.String audioTrackType;

  private final java.lang.String iFrameOnlyManifest;

  private final java.lang.String segmentModifier;

  private software.amazon.awssdk.services.mediaconvert.model.HlsSettings(software.amazon.awssdk.services.mediaconvert.model.HlsSettings$BuilderImpl);
    Code:
       0: aload_0
       1: invokespecial #9                  // Method java/lang/Object."<init>":()V
       4: aload_0
       5: aload_1
       6: invokestatic  #10                 // Method software/amazon/awssdk/services/mediaconvert/model/HlsSettings$BuilderImpl.access$000:(Lsoftware/amazon/awssdk/services/mediaconvert/model/HlsSettings$BuilderImpl;)Ljava/lang/String;
       9: putfield      #8                  // Field audioGroupId:Ljava/lang/String;
      12: aload_0
      13: aload_1
      14: invokestatic  #11                 // Method software/amazon/awssdk/services/mediaconvert/model/HlsSettings$BuilderImpl.access$100:(Lsoftware/amazon/awssdk/services/mediaconvert/model/HlsSettings$BuilderImpl;)Ljava/lang/String;
      17: putfield      #7                  // Field audioOnlyContainer:Ljava/lang/String;
      20: aload_0
      21: aload_1
      22: invokestatic  #12                 // Method software/amazon/awssdk/services/mediaconvert/model/HlsSettings$BuilderImpl.access$200:(Lsoftware/amazon/awssdk/services/mediaconvert/model/HlsSettings$BuilderImpl;)Ljava/lang/String;
      25: putfield      #6                  // Field audioRenditionSets:Ljava/lang/String;
      28: aload_0
      29: aload_1
      30: invokestatic  #13                 // Method software/amazon/awssdk/services/mediaconvert/model/HlsSettings$BuilderImpl.access$300:(Lsoftware/amazon/awssdk/services/mediaconvert/model/HlsSettings$BuilderImpl;)Ljava/lang/String;
      33: putfield      #5                  // Field audioTrackType:Ljava/lang/String;
      36: aload_0
      37: aload_1
      38: invokestatic  #14                 // Method software/amazon/awssdk/services/mediaconvert/model/HlsSettings$BuilderImpl.access$400:(Lsoftware/amazon/awssdk/services/mediaconvert/model/HlsSettings$BuilderImpl;)Ljava/lang/String;
      41: putfield      #4                  // Field iFrameOnlyManifest:Ljava/lang/String;
      44: aload_0
      45: aload_1
      46: invokestatic  #15                 // Method software/amazon/awssdk/services/mediaconvert/model/HlsSettings$BuilderImpl.access$500:(Lsoftware/amazon/awssdk/services/mediaconvert/model/HlsSettings$BuilderImpl;)Ljava/lang/String;
      49: putfield      #3                  // Field segmentModifier:Ljava/lang/String;
      52: return

  public java.lang.String audioGroupId();
    Code:
       0: aload_0
       1: getfield      #8                  // Field audioGroupId:Ljava/lang/String;
       4: areturn

  public software.amazon.awssdk.services.mediaconvert.model.HlsAudioOnlyContainer audioOnlyContainer();
    Code:
       0: aload_0
       1: getfield      #7                  // Field audioOnlyContainer:Ljava/lang/String;
       4: invokestatic  #16                 // Method software/amazon/awssdk/services/mediaconvert/model/HlsAudioOnlyContainer.fromValue:(Ljava/lang/String;)Lsoftware/amazon/awssdk/services/mediaconvert/model/HlsAudioOnlyContainer;
       7: areturn

  public java.lang.String audioOnlyContainerAsString();
    Code:
       0: aload_0
       1: getfield      #7                  // Field audioOnlyContainer:Ljava/lang/String;
       4: areturn

  public java.lang.String audioRenditionSets();
    Code:
       0: aload_0
       1: getfield      #6                  // Field audioRenditionSets:Ljava/lang/String;
       4: areturn

  public software.amazon.awssdk.services.mediaconvert.model.HlsAudioTrackType audioTrackType();
    Code:
       0: aload_0
       1: getfield      #5                  // Field audioTrackType:Ljava/lang/String;
       4: invokestatic  #17                 // Method software/amazon/awssdk/services/mediaconvert/model/HlsAudioTrackType.fromValue:(Ljava/lang/String;)Lsoftware/amazon/awssdk/services/mediaconvert/model/HlsAudioTrackType;
       7: areturn

  public java.lang.String audioTrackTypeAsString();
    Code:
       0: aload_0
       1: getfield      #5                  // Field audioTrackType:Ljava/lang/String;
       4: areturn

  public software.amazon.awssdk.services.mediaconvert.model.HlsIFrameOnlyManifest iFrameOnlyManifest();
    Code:
       0: aload_0
       1: getfield      #4                  // Field iFrameOnlyManifest:Ljava/lang/String;
       4: invokestatic  #18                 // Method software/amazon/awssdk/services/mediaconvert/model/HlsIFrameOnlyManifest.fromValue:(Ljava/lang/String;)Lsoftware/amazon/awssdk/services/mediaconvert/model/HlsIFrameOnlyManifest;
       7: areturn

  public java.lang.String iFrameOnlyManifestAsString();
    Code:
       0: aload_0
       1: getfield      #4                  // Field iFrameOnlyManifest:Ljava/lang/String;
       4: areturn

  public java.lang.String segmentModifier();
    Code:
       0: aload_0
       1: getfield      #3                  // Field segmentModifier:Ljava/lang/String;
       4: areturn

  public software.amazon.awssdk.services.mediaconvert.model.HlsSettings$Builder toBuilder();
    Code:
       0: new           #19                 // class software/amazon/awssdk/services/mediaconvert/model/HlsSettings$BuilderImpl
       3: dup
       4: aload_0
       5: aconst_null
       6: invokespecial #20                 // Method software/amazon/awssdk/services/mediaconvert/model/HlsSettings$BuilderImpl."<init>":(Lsoftware/amazon/awssdk/services/mediaconvert/model/HlsSettings;Lsoftware/amazon/awssdk/services/mediaconvert/model/HlsSettings$1;)V
       9: areturn

  public static software.amazon.awssdk.services.mediaconvert.model.HlsSettings$Builder builder();
    Code:
       0: new           #19                 // class software/amazon/awssdk/services/mediaconvert/model/HlsSettings$BuilderImpl
       3: dup
       4: aconst_null
       5: invokespecial #21                 // Method software/amazon/awssdk/services/mediaconvert/model/HlsSettings$BuilderImpl."<init>":(Lsoftware/amazon/awssdk/services/mediaconvert/model/HlsSettings$1;)V
       8: areturn

  public static java.lang.Class<? extends software.amazon.awssdk.services.mediaconvert.model.HlsSettings$Builder> serializableBuilderClass();
    Code:
       0: ldc           #19                 // class software/amazon/awssdk/services/mediaconvert/model/HlsSettings$BuilderImpl
       2: areturn

  public int hashCode();
    Code:
       0: iconst_1
       1: istore_1
       2: bipush        31
       4: iload_1
       5: imul
       6: aload_0
       7: invokevirtual #22                 // Method audioGroupId:()Ljava/lang/String;
      10: invokestatic  #23                 // Method java/util/Objects.hashCode:(Ljava/lang/Object;)I
      13: iadd
      14: istore_1
      15: bipush        31
      17: iload_1
      18: imul
      19: aload_0
      20: invokevirtual #24                 // Method audioOnlyContainerAsString:()Ljava/lang/String;
      23: invokestatic  #23                 // Method java/util/Objects.hashCode:(Ljava/lang/Object;)I
      26: iadd
      27: istore_1
      28: bipush        31
      30: iload_1
      31: imul
      32: aload_0
      33: invokevirtual #25                 // Method audioRenditionSets:()Ljava/lang/String;
      36: invokestatic  #23                 // Method java/util/Objects.hashCode:(Ljava/lang/Object;)I
      39: iadd
      40: istore_1
      41: bipush        31
      43: iload_1
      44: imul
      45: aload_0
      46: invokevirtual #26                 // Method audioTrackTypeAsString:()Ljava/lang/String;
      49: invokestatic  #23                 // Method java/util/Objects.hashCode:(Ljava/lang/Object;)I
      52: iadd
      53: istore_1
      54: bipush        31
      56: iload_1
      57: imul
      58: aload_0
      59: invokevirtual #27                 // Method iFrameOnlyManifestAsString:()Ljava/lang/String;
      62: invokestatic  #23                 // Method java/util/Objects.hashCode:(Ljava/lang/Object;)I
      65: iadd
      66: istore_1
      67: bipush        31
      69: iload_1
      70: imul
      71: aload_0
      72: invokevirtual #28                 // Method segmentModifier:()Ljava/lang/String;
      75: invokestatic  #23                 // Method java/util/Objects.hashCode:(Ljava/lang/Object;)I
      78: iadd
      79: istore_1
      80: iload_1
      81: ireturn

  public boolean equals(java.lang.Object);
    Code:
       0: aload_0
       1: aload_1
       2: invokevirtual #29                 // Method equalsBySdkFields:(Ljava/lang/Object;)Z
       5: ireturn

  public boolean equalsBySdkFields(java.lang.Object);
    Code:
       0: aload_0
       1: aload_1
       2: if_acmpne     7
       5: iconst_1
       6: ireturn
       7: aload_1
       8: ifnonnull     13
      11: iconst_0
      12: ireturn
      13: aload_1
      14: instanceof    #30                 // class software/amazon/awssdk/services/mediaconvert/model/HlsSettings
      17: ifne          22
      20: iconst_0
      21: ireturn
      22: aload_1
      23: checkcast     #30                 // class software/amazon/awssdk/services/mediaconvert/model/HlsSettings
      26: astore_2
      27: aload_0
      28: invokevirtual #22                 // Method audioGroupId:()Ljava/lang/String;
      31: aload_2
      32: invokevirtual #22                 // Method audioGroupId:()Ljava/lang/String;
      35: invokestatic  #31                 // Method java/util/Objects.equals:(Ljava/lang/Object;Ljava/lang/Object;)Z
      38: ifeq          115
      41: aload_0
      42: invokevirtual #24                 // Method audioOnlyContainerAsString:()Ljava/lang/String;
      45: aload_2
      46: invokevirtual #24                 // Method audioOnlyContainerAsString:()Ljava/lang/String;
      49: invokestatic  #31                 // Method java/util/Objects.equals:(Ljava/lang/Object;Ljava/lang/Object;)Z
      52: ifeq          115
      55: aload_0
      56: invokevirtual #25                 // Method audioRenditionSets:()Ljava/lang/String;
      59: aload_2
      60: invokevirtual #25                 // Method audioRenditionSets:()Ljava/lang/String;
      63: invokestatic  #31                 // Method java/util/Objects.equals:(Ljava/lang/Object;Ljava/lang/Object;)Z
      66: ifeq          115
      69: aload_0
      70: invokevirtual #26                 // Method audioTrackTypeAsString:()Ljava/lang/String;
      73: aload_2
      74: invokevirtual #26                 // Method audioTrackTypeAsString:()Ljava/lang/String;
      77: invokestatic  #31                 // Method java/util/Objects.equals:(Ljava/lang/Object;Ljava/lang/Object;)Z
      80: ifeq          115
      83: aload_0
      84: invokevirtual #27                 // Method iFrameOnlyManifestAsString:()Ljava/lang/String;
      87: aload_2
      88: invokevirtual #27                 // Method iFrameOnlyManifestAsString:()Ljava/lang/String;
      91: invokestatic  #31                 // Method java/util/Objects.equals:(Ljava/lang/Object;Ljava/lang/Object;)Z
      94: ifeq          115
      97: aload_0
      98: invokevirtual #28                 // Method segmentModifier:()Ljava/lang/String;
     101: aload_2
     102: invokevirtual #28                 // Method segmentModifier:()Ljava/lang/String;
     105: invokestatic  #31                 // Method java/util/Objects.equals:(Ljava/lang/Object;Ljava/lang/Object;)Z
     108: ifeq          115
     111: iconst_1
     112: goto          116
     115: iconst_0
     116: ireturn

  public java.lang.String toString();
    Code:
       0: ldc           #32                 // String HlsSettings
       2: invokestatic  #33                 // Method software/amazon/awssdk/utils/ToString.builder:(Ljava/lang/String;)Lsoftware/amazon/awssdk/utils/ToString;
       5: ldc           #34                 // String AudioGroupId
       7: aload_0
       8: invokevirtual #22                 // Method audioGroupId:()Ljava/lang/String;
      11: invokevirtual #35                 // Method software/amazon/awssdk/utils/ToString.add:(Ljava/lang/String;Ljava/lang/Object;)Lsoftware/amazon/awssdk/utils/ToString;
      14: ldc           #36                 // String AudioOnlyContainer
      16: aload_0
      17: invokevirtual #24                 // Method audioOnlyContainerAsString:()Ljava/lang/String;
      20: invokevirtual #35                 // Method software/amazon/awssdk/utils/ToString.add:(Ljava/lang/String;Ljava/lang/Object;)Lsoftware/amazon/awssdk/utils/ToString;
      23: ldc           #37                 // String AudioRenditionSets
      25: aload_0
      26: invokevirtual #25                 // Method audioRenditionSets:()Ljava/lang/String;
      29: invokevirtual #35                 // Method software/amazon/awssdk/utils/ToString.add:(Ljava/lang/String;Ljava/lang/Object;)Lsoftware/amazon/awssdk/utils/ToString;
      32: ldc           #38                 // String AudioTrackType
      34: aload_0
      35: invokevirtual #26                 // Method audioTrackTypeAsString:()Ljava/lang/String;
      38: invokevirtual #35                 // Method software/amazon/awssdk/utils/ToString.add:(Ljava/lang/String;Ljava/lang/Object;)Lsoftware/amazon/awssdk/utils/ToString;
      41: ldc           #39                 // String IFrameOnlyManifest
      43: aload_0
      44: invokevirtual #27                 // Method iFrameOnlyManifestAsString:()Ljava/lang/String;
      47: invokevirtual #35                 // Method software/amazon/awssdk/utils/ToString.add:(Ljava/lang/String;Ljava/lang/Object;)Lsoftware/amazon/awssdk/utils/ToString;
      50: ldc           #40                 // String SegmentModifier
      52: aload_0
      53: invokevirtual #28                 // Method segmentModifier:()Ljava/lang/String;
      56: invokevirtual #35                 // Method software/amazon/awssdk/utils/ToString.add:(Ljava/lang/String;Ljava/lang/Object;)Lsoftware/amazon/awssdk/utils/ToString;
      59: invokevirtual #41                 // Method software/amazon/awssdk/utils/ToString.build:()Ljava/lang/String;
      62: areturn

  public <T> java.util.Optional<T> getValueForField(java.lang.String, java.lang.Class<T>);
    Code:
       0: aload_1
       1: astore_3
       2: iconst_m1
       3: istore        4
       5: aload_3
       6: invokevirtual #42                 // Method java/lang/String.hashCode:()I
       9: lookupswitch  { // 6
           -1128607900: 68
            -604286001: 98
             -47278065: 113
            1018817055: 83
            1073011466: 143
            1767064255: 128
               default: 155
          }
      68: aload_3
      69: ldc           #34                 // String AudioGroupId
      71: invokevirtual #43                 // Method java/lang/String.equals:(Ljava/lang/Object;)Z
      74: ifeq          155
      77: iconst_0
      78: istore        4
      80: goto          155
      83: aload_3
      84: ldc           #36                 // String AudioOnlyContainer
      86: invokevirtual #43                 // Method java/lang/String.equals:(Ljava/lang/Object;)Z
      89: ifeq          155
      92: iconst_1
      93: istore        4
      95: goto          155
      98: aload_3
      99: ldc           #37                 // String AudioRenditionSets
     101: invokevirtual #43                 // Method java/lang/String.equals:(Ljava/lang/Object;)Z
     104: ifeq          155
     107: iconst_2
     108: istore        4
     110: goto          155
     113: aload_3
     114: ldc           #38                 // String AudioTrackType
     116: invokevirtual #43                 // Method java/lang/String.equals:(Ljava/lang/Object;)Z
     119: ifeq          155
     122: iconst_3
     123: istore        4
     125: goto          155
     128: aload_3
     129: ldc           #39                 // String IFrameOnlyManifest
     131: invokevirtual #43                 // Method java/lang/String.equals:(Ljava/lang/Object;)Z
     134: ifeq          155
     137: iconst_4
     138: istore        4
     140: goto          155
     143: aload_3
     144: ldc           #40                 // String SegmentModifier
     146: invokevirtual #43                 // Method java/lang/String.equals:(Ljava/lang/Object;)Z
     149: ifeq          155
     152: iconst_5
     153: istore        4
     155: iload         4
     157: tableswitch   { // 0 to 5
                     0: 196
                     1: 208
                     2: 220
                     3: 232
                     4: 244
                     5: 256
               default: 268
          }
     196: aload_2
     197: aload_0
     198: invokevirtual #22                 // Method audioGroupId:()Ljava/lang/String;
     201: invokevirtual #44                 // Method java/lang/Class.cast:(Ljava/lang/Object;)Ljava/lang/Object;
     204: invokestatic  #45                 // Method java/util/Optional.ofNullable:(Ljava/lang/Object;)Ljava/util/Optional;
     207: areturn
     208: aload_2
     209: aload_0
     210: invokevirtual #24                 // Method audioOnlyContainerAsString:()Ljava/lang/String;
     213: invokevirtual #44                 // Method java/lang/Class.cast:(Ljava/lang/Object;)Ljava/lang/Object;
     216: invokestatic  #45                 // Method java/util/Optional.ofNullable:(Ljava/lang/Object;)Ljava/util/Optional;
     219: areturn
     220: aload_2
     221: aload_0
     222: invokevirtual #25                 // Method audioRenditionSets:()Ljava/lang/String;
     225: invokevirtual #44                 // Method java/lang/Class.cast:(Ljava/lang/Object;)Ljava/lang/Object;
     228: invokestatic  #45                 // Method java/util/Optional.ofNullable:(Ljava/lang/Object;)Ljava/util/Optional;
     231: areturn
     232: aload_2
     233: aload_0
     234: invokevirtual #26                 // Method audioTrackTypeAsString:()Ljava/lang/String;
     237: invokevirtual #44                 // Method java/lang/Class.cast:(Ljava/lang/Object;)Ljava/lang/Object;
     240: invokestatic  #45                 // Method java/util/Optional.ofNullable:(Ljava/lang/Object;)Ljava/util/Optional;
     243: areturn
     244: aload_2
     245: aload_0
     246: invokevirtual #27                 // Method iFrameOnlyManifestAsString:()Ljava/lang/String;
     249: invokevirtual #44                 // Method java/lang/Class.cast:(Ljava/lang/Object;)Ljava/lang/Object;
     252: invokestatic  #45                 // Method java/util/Optional.ofNullable:(Ljava/lang/Object;)Ljava/util/Optional;
     255: areturn
     256: aload_2
     257: aload_0
     258: invokevirtual #28                 // Method segmentModifier:()Ljava/lang/String;
     261: invokevirtual #44                 // Method java/lang/Class.cast:(Ljava/lang/Object;)Ljava/lang/Object;
     264: invokestatic  #45                 // Method java/util/Optional.ofNullable:(Ljava/lang/Object;)Ljava/util/Optional;
     267: areturn
     268: invokestatic  #46                 // Method java/util/Optional.empty:()Ljava/util/Optional;
     271: areturn

  public java.util.List<software.amazon.awssdk.core.SdkField<?>> sdkFields();
    Code:
       0: getstatic     #1                  // Field SDK_FIELDS:Ljava/util/List;
       3: areturn

  private static <T> java.util.function.Function<java.lang.Object, T> getter(java.util.function.Function<software.amazon.awssdk.services.mediaconvert.model.HlsSettings, T>);
    Code:
       0: aload_0
       1: invokedynamic #47,  0             // InvokeDynamic #0:apply:(Ljava/util/function/Function;)Ljava/util/function/Function;
       6: areturn

  private static <T> java.util.function.BiConsumer<java.lang.Object, T> setter(java.util.function.BiConsumer<software.amazon.awssdk.services.mediaconvert.model.HlsSettings$Builder, T>);
    Code:
       0: aload_0
       1: invokedynamic #48,  0             // InvokeDynamic #1:accept:(Ljava/util/function/BiConsumer;)Ljava/util/function/BiConsumer;
       6: areturn

  public software.amazon.awssdk.utils.builder.CopyableBuilder toBuilder();
    Code:
       0: aload_0
       1: invokevirtual #49                 // Method toBuilder:()Lsoftware/amazon/awssdk/services/mediaconvert/model/HlsSettings$Builder;
       4: areturn

  private static void lambda$setter$1(java.util.function.BiConsumer, java.lang.Object, java.lang.Object);
    Code:
       0: aload_0
       1: aload_1
       2: checkcast     #50                 // class software/amazon/awssdk/services/mediaconvert/model/HlsSettings$Builder
       5: aload_2
       6: invokeinterface #51,  3           // InterfaceMethod java/util/function/BiConsumer.accept:(Ljava/lang/Object;Ljava/lang/Object;)V
      11: return

  private static java.lang.Object lambda$getter$0(java.util.function.Function, java.lang.Object);
    Code:
       0: aload_0
       1: aload_1
       2: checkcast     #30                 // class software/amazon/awssdk/services/mediaconvert/model/HlsSettings
       5: invokeinterface #52,  2           // InterfaceMethod java/util/function/Function.apply:(Ljava/lang/Object;)Ljava/lang/Object;
      10: areturn

  static java.lang.String access$800(software.amazon.awssdk.services.mediaconvert.model.HlsSettings);
    Code:
       0: aload_0
       1: getfield      #8                  // Field audioGroupId:Ljava/lang/String;
       4: areturn

  static java.lang.String access$900(software.amazon.awssdk.services.mediaconvert.model.HlsSettings);
    Code:
       0: aload_0
       1: getfield      #7                  // Field audioOnlyContainer:Ljava/lang/String;
       4: areturn

  static java.lang.String access$1000(software.amazon.awssdk.services.mediaconvert.model.HlsSettings);
    Code:
       0: aload_0
       1: getfield      #6                  // Field audioRenditionSets:Ljava/lang/String;
       4: areturn

  static java.lang.String access$1100(software.amazon.awssdk.services.mediaconvert.model.HlsSettings);
    Code:
       0: aload_0
       1: getfield      #5                  // Field audioTrackType:Ljava/lang/String;
       4: areturn

  static java.lang.String access$1200(software.amazon.awssdk.services.mediaconvert.model.HlsSettings);
    Code:
       0: aload_0
       1: getfield      #4                  // Field iFrameOnlyManifest:Ljava/lang/String;
       4: areturn

  static java.lang.String access$1300(software.amazon.awssdk.services.mediaconvert.model.HlsSettings);
    Code:
       0: aload_0
       1: getfield      #3                  // Field segmentModifier:Ljava/lang/String;
       4: areturn

  software.amazon.awssdk.services.mediaconvert.model.HlsSettings(software.amazon.awssdk.services.mediaconvert.model.HlsSettings$BuilderImpl, software.amazon.awssdk.services.mediaconvert.model.HlsSettings$1);
    Code:
       0: aload_0
       1: aload_1
       2: invokespecial #2                  // Method "<init>":(Lsoftware/amazon/awssdk/services/mediaconvert/model/HlsSettings$BuilderImpl;)V
       5: return

  static java.util.List access$1500();
    Code:
       0: getstatic     #1                  // Field SDK_FIELDS:Ljava/util/List;
       3: areturn

  static {};
    Code:
       0: getstatic     #53                 // Field software/amazon/awssdk/core/protocol/MarshallingType.STRING:Lsoftware/amazon/awssdk/core/protocol/MarshallingType;
       3: invokestatic  #54                 // Method software/amazon/awssdk/core/SdkField.builder:(Lsoftware/amazon/awssdk/core/protocol/MarshallingType;)Lsoftware/amazon/awssdk/core/SdkField$Builder;
       6: invokedynamic #55,  0             // InvokeDynamic #2:apply:()Ljava/util/function/Function;
      11: invokestatic  #56                 // Method getter:(Ljava/util/function/Function;)Ljava/util/function/Function;
      14: invokevirtual #57                 // Method software/amazon/awssdk/core/SdkField$Builder.getter:(Ljava/util/function/Function;)Lsoftware/amazon/awssdk/core/SdkField$Builder;
      17: invokedynamic #58,  0             // InvokeDynamic #3:accept:()Ljava/util/function/BiConsumer;
      22: invokestatic  #59                 // Method setter:(Ljava/util/function/BiConsumer;)Ljava/util/function/BiConsumer;
      25: invokevirtual #60                 // Method software/amazon/awssdk/core/SdkField$Builder.setter:(Ljava/util/function/BiConsumer;)Lsoftware/amazon/awssdk/core/SdkField$Builder;
      28: iconst_1
      29: anewarray     #61                 // class software/amazon/awssdk/core/traits/Trait
      32: dup
      33: iconst_0
      34: invokestatic  #62                 // Method software/amazon/awssdk/core/traits/LocationTrait.builder:()Lsoftware/amazon/awssdk/core/traits/LocationTrait$Builder;
      37: getstatic     #63                 // Field software/amazon/awssdk/core/protocol/MarshallLocation.PAYLOAD:Lsoftware/amazon/awssdk/core/protocol/MarshallLocation;
      40: invokevirtual #64                 // Method software/amazon/awssdk/core/traits/LocationTrait$Builder.location:(Lsoftware/amazon/awssdk/core/protocol/MarshallLocation;)Lsoftware/amazon/awssdk/core/traits/LocationTrait$Builder;
      43: ldc           #65                 // String audioGroupId
      45: invokevirtual #66                 // Method software/amazon/awssdk/core/traits/LocationTrait$Builder.locationName:(Ljava/lang/String;)Lsoftware/amazon/awssdk/core/traits/LocationTrait$Builder;
      48: invokevirtual #67                 // Method software/amazon/awssdk/core/traits/LocationTrait$Builder.build:()Lsoftware/amazon/awssdk/core/traits/LocationTrait;
      51: aastore
      52: invokevirtual #68                 // Method software/amazon/awssdk/core/SdkField$Builder.traits:([Lsoftware/amazon/awssdk/core/traits/Trait;)Lsoftware/amazon/awssdk/core/SdkField$Builder;
      55: invokevirtual #69                 // Method software/amazon/awssdk/core/SdkField$Builder.build:()Lsoftware/amazon/awssdk/core/SdkField;
      58: putstatic     #70                 // Field AUDIO_GROUP_ID_FIELD:Lsoftware/amazon/awssdk/core/SdkField;
      61: getstatic     #53                 // Field software/amazon/awssdk/core/protocol/MarshallingType.STRING:Lsoftware/amazon/awssdk/core/protocol/MarshallingType;
      64: invokestatic  #54                 // Method software/amazon/awssdk/core/SdkField.builder:(Lsoftware/amazon/awssdk/core/protocol/MarshallingType;)Lsoftware/amazon/awssdk/core/SdkField$Builder;
      67: invokedynamic #71,  0             // InvokeDynamic #4:apply:()Ljava/util/function/Function;
      72: invokestatic  #56                 // Method getter:(Ljava/util/function/Function;)Ljava/util/function/Function;
      75: invokevirtual #57                 // Method software/amazon/awssdk/core/SdkField$Builder.getter:(Ljava/util/function/Function;)Lsoftware/amazon/awssdk/core/SdkField$Builder;
      78: invokedynamic #72,  0             // InvokeDynamic #5:accept:()Ljava/util/function/BiConsumer;
      83: invokestatic  #59                 // Method setter:(Ljava/util/function/BiConsumer;)Ljava/util/function/BiConsumer;
      86: invokevirtual #60                 // Method software/amazon/awssdk/core/SdkField$Builder.setter:(Ljava/util/function/BiConsumer;)Lsoftware/amazon/awssdk/core/SdkField$Builder;
      89: iconst_1
      90: anewarray     #61                 // class software/amazon/awssdk/core/traits/Trait
      93: dup
      94: iconst_0
      95: invokestatic  #62                 // Method software/amazon/awssdk/core/traits/LocationTrait.builder:()Lsoftware/amazon/awssdk/core/traits/LocationTrait$Builder;
      98: getstatic     #63                 // Field software/amazon/awssdk/core/protocol/MarshallLocation.PAYLOAD:Lsoftware/amazon/awssdk/core/protocol/MarshallLocation;
     101: invokevirtual #64                 // Method software/amazon/awssdk/core/traits/LocationTrait$Builder.location:(Lsoftware/amazon/awssdk/core/protocol/MarshallLocation;)Lsoftware/amazon/awssdk/core/traits/LocationTrait$Builder;
     104: ldc           #73                 // String audioOnlyContainer
     106: invokevirtual #66                 // Method software/amazon/awssdk/core/traits/LocationTrait$Builder.locationName:(Ljava/lang/String;)Lsoftware/amazon/awssdk/core/traits/LocationTrait$Builder;
     109: invokevirtual #67                 // Method software/amazon/awssdk/core/traits/LocationTrait$Builder.build:()Lsoftware/amazon/awssdk/core/traits/LocationTrait;
     112: aastore
     113: invokevirtual #68                 // Method software/amazon/awssdk/core/SdkField$Builder.traits:([Lsoftware/amazon/awssdk/core/traits/Trait;)Lsoftware/amazon/awssdk/core/SdkField$Builder;
     116: invokevirtual #69                 // Method software/amazon/awssdk/core/SdkField$Builder.build:()Lsoftware/amazon/awssdk/core/SdkField;
     119: putstatic     #74                 // Field AUDIO_ONLY_CONTAINER_FIELD:Lsoftware/amazon/awssdk/core/SdkField;
     122: getstatic     #53                 // Field software/amazon/awssdk/core/protocol/MarshallingType.STRING:Lsoftware/amazon/awssdk/core/protocol/MarshallingType;
     125: invokestatic  #54                 // Method software/amazon/awssdk/core/SdkField.builder:(Lsoftware/amazon/awssdk/core/protocol/MarshallingType;)Lsoftware/amazon/awssdk/core/SdkField$Builder;
     128: invokedynamic #75,  0             // InvokeDynamic #6:apply:()Ljava/util/function/Function;
     133: invokestatic  #56                 // Method getter:(Ljava/util/function/Function;)Ljava/util/function/Function;
     136: invokevirtual #57                 // Method software/amazon/awssdk/core/SdkField$Builder.getter:(Ljava/util/function/Function;)Lsoftware/amazon/awssdk/core/SdkField$Builder;
     139: invokedynamic #76,  0             // InvokeDynamic #7:accept:()Ljava/util/function/BiConsumer;
     144: invokestatic  #59                 // Method setter:(Ljava/util/function/BiConsumer;)Ljava/util/function/BiConsumer;
     147: invokevirtual #60                 // Method software/amazon/awssdk/core/SdkField$Builder.setter:(Ljava/util/function/BiConsumer;)Lsoftware/amazon/awssdk/core/SdkField$Builder;
     150: iconst_1
     151: anewarray     #61                 // class software/amazon/awssdk/core/traits/Trait
     154: dup
     155: iconst_0
     156: invokestatic  #62                 // Method software/amazon/awssdk/core/traits/LocationTrait.builder:()Lsoftware/amazon/awssdk/core/traits/LocationTrait$Builder;
     159: getstatic     #63                 // Field software/amazon/awssdk/core/protocol/MarshallLocation.PAYLOAD:Lsoftware/amazon/awssdk/core/protocol/MarshallLocation;
     162: invokevirtual #64                 // Method software/amazon/awssdk/core/traits/LocationTrait$Builder.location:(Lsoftware/amazon/awssdk/core/protocol/MarshallLocation;)Lsoftware/amazon/awssdk/core/traits/LocationTrait$Builder;
     165: ldc           #77                 // String audioRenditionSets
     167: invokevirtual #66                 // Method software/amazon/awssdk/core/traits/LocationTrait$Builder.locationName:(Ljava/lang/String;)Lsoftware/amazon/awssdk/core/traits/LocationTrait$Builder;
     170: invokevirtual #67                 // Method software/amazon/awssdk/core/traits/LocationTrait$Builder.build:()Lsoftware/amazon/awssdk/core/traits/LocationTrait;
     173: aastore
     174: invokevirtual #68                 // Method software/amazon/awssdk/core/SdkField$Builder.traits:([Lsoftware/amazon/awssdk/core/traits/Trait;)Lsoftware/amazon/awssdk/core/SdkField$Builder;
     177: invokevirtual #69                 // Method software/amazon/awssdk/core/SdkField$Builder.build:()Lsoftware/amazon/awssdk/core/SdkField;
     180: putstatic     #78                 // Field AUDIO_RENDITION_SETS_FIELD:Lsoftware/amazon/awssdk/core/SdkField;
     183: getstatic     #53                 // Field software/amazon/awssdk/core/protocol/MarshallingType.STRING:Lsoftware/amazon/awssdk/core/protocol/MarshallingType;
     186: invokestatic  #54                 // Method software/amazon/awssdk/core/SdkField.builder:(Lsoftware/amazon/awssdk/core/protocol/MarshallingType;)Lsoftware/amazon/awssdk/core/SdkField$Builder;
     189: invokedynamic #79,  0             // InvokeDynamic #8:apply:()Ljava/util/function/Function;
     194: invokestatic  #56                 // Method getter:(Ljava/util/function/Function;)Ljava/util/function/Function;
     197: invokevirtual #57                 // Method software/amazon/awssdk/core/SdkField$Builder.getter:(Ljava/util/function/Function;)Lsoftware/amazon/awssdk/core/SdkField$Builder;
     200: invokedynamic #80,  0             // InvokeDynamic #9:accept:()Ljava/util/function/BiConsumer;
     205: invokestatic  #59                 // Method setter:(Ljava/util/function/BiConsumer;)Ljava/util/function/BiConsumer;
     208: invokevirtual #60                 // Method software/amazon/awssdk/core/SdkField$Builder.setter:(Ljava/util/function/BiConsumer;)Lsoftware/amazon/awssdk/core/SdkField$Builder;
     211: iconst_1
     212: anewarray     #61                 // class software/amazon/awssdk/core/traits/Trait
     215: dup
     216: iconst_0
     217: invokestatic  #62                 // Method software/amazon/awssdk/core/traits/LocationTrait.builder:()Lsoftware/amazon/awssdk/core/traits/LocationTrait$Builder;
     220: getstatic     #63                 // Field software/amazon/awssdk/core/protocol/MarshallLocation.PAYLOAD:Lsoftware/amazon/awssdk/core/protocol/MarshallLocation;
     223: invokevirtual #64                 // Method software/amazon/awssdk/core/traits/LocationTrait$Builder.location:(Lsoftware/amazon/awssdk/core/protocol/MarshallLocation;)Lsoftware/amazon/awssdk/core/traits/LocationTrait$Builder;
     226: ldc           #81                 // String audioTrackType
     228: invokevirtual #66                 // Method software/amazon/awssdk/core/traits/LocationTrait$Builder.locationName:(Ljava/lang/String;)Lsoftware/amazon/awssdk/core/traits/LocationTrait$Builder;
     231: invokevirtual #67                 // Method software/amazon/awssdk/core/traits/LocationTrait$Builder.build:()Lsoftware/amazon/awssdk/core/traits/LocationTrait;
     234: aastore
     235: invokevirtual #68                 // Method software/amazon/awssdk/core/SdkField$Builder.traits:([Lsoftware/amazon/awssdk/core/traits/Trait;)Lsoftware/amazon/awssdk/core/SdkField$Builder;
     238: invokevirtual #69                 // Method software/amazon/awssdk/core/SdkField$Builder.build:()Lsoftware/amazon/awssdk/core/SdkField;
     241: putstatic     #82                 // Field AUDIO_TRACK_TYPE_FIELD:Lsoftware/amazon/awssdk/core/SdkField;
     244: getstatic     #53                 // Field software/amazon/awssdk/core/protocol/MarshallingType.STRING:Lsoftware/amazon/awssdk/core/protocol/MarshallingType;
     247: invokestatic  #54                 // Method software/amazon/awssdk/core/SdkField.builder:(Lsoftware/amazon/awssdk/core/protocol/MarshallingType;)Lsoftware/amazon/awssdk/core/SdkField$Builder;
     250: invokedynamic #83,  0             // InvokeDynamic #10:apply:()Ljava/util/function/Function;
     255: invokestatic  #56                 // Method getter:(Ljava/util/function/Function;)Ljava/util/function/Function;
     258: invokevirtual #57                 // Method software/amazon/awssdk/core/SdkField$Builder.getter:(Ljava/util/function/Function;)Lsoftware/amazon/awssdk/core/SdkField$Builder;
     261: invokedynamic #84,  0             // InvokeDynamic #11:accept:()Ljava/util/function/BiConsumer;
     266: invokestatic  #59                 // Method setter:(Ljava/util/function/BiConsumer;)Ljava/util/function/BiConsumer;
     269: invokevirtual #60                 // Method software/amazon/awssdk/core/SdkField$Builder.setter:(Ljava/util/function/BiConsumer;)Lsoftware/amazon/awssdk/core/SdkField$Builder;
     272: iconst_1
     273: anewarray     #61                 // class software/amazon/awssdk/core/traits/Trait
     276: dup
     277: iconst_0
     278: invokestatic  #62                 // Method software/amazon/awssdk/core/traits/LocationTrait.builder:()Lsoftware/amazon/awssdk/core/traits/LocationTrait$Builder;
     281: getstatic     #63                 // Field software/amazon/awssdk/core/protocol/MarshallLocation.PAYLOAD:Lsoftware/amazon/awssdk/core/protocol/MarshallLocation;
     284: invokevirtual #64                 // Method software/amazon/awssdk/core/traits/LocationTrait$Builder.location:(Lsoftware/amazon/awssdk/core/protocol/MarshallLocation;)Lsoftware/amazon/awssdk/core/traits/LocationTrait$Builder;
     287: ldc           #85                 // String iFrameOnlyManifest
     289: invokevirtual #66                 // Method software/amazon/awssdk/core/traits/LocationTrait$Builder.locationName:(Ljava/lang/String;)Lsoftware/amazon/awssdk/core/traits/LocationTrait$Builder;
     292: invokevirtual #67                 // Method software/amazon/awssdk/core/traits/LocationTrait$Builder.build:()Lsoftware/amazon/awssdk/core/traits/LocationTrait;
     295: aastore
     296: invokevirtual #68                 // Method software/amazon/awssdk/core/SdkField$Builder.traits:([Lsoftware/amazon/awssdk/core/traits/Trait;)Lsoftware/amazon/awssdk/core/SdkField$Builder;
     299: invokevirtual #69                 // Method software/amazon/awssdk/core/SdkField$Builder.build:()Lsoftware/amazon/awssdk/core/SdkField;
     302: putstatic     #86                 // Field I_FRAME_ONLY_MANIFEST_FIELD:Lsoftware/amazon/awssdk/core/SdkField;
     305: getstatic     #53                 // Field software/amazon/awssdk/core/protocol/MarshallingType.STRING:Lsoftware/amazon/awssdk/core/protocol/MarshallingType;
     308: invokestatic  #54                 // Method software/amazon/awssdk/core/SdkField.builder:(Lsoftware/amazon/awssdk/core/protocol/MarshallingType;)Lsoftware/amazon/awssdk/core/SdkField$Builder;
     311: invokedynamic #87,  0             // InvokeDynamic #12:apply:()Ljava/util/function/Function;
     316: invokestatic  #56                 // Method getter:(Ljava/util/function/Function;)Ljava/util/function/Function;
     319: invokevirtual #57                 // Method software/amazon/awssdk/core/SdkField$Builder.getter:(Ljava/util/function/Function;)Lsoftware/amazon/awssdk/core/SdkField$Builder;
     322: invokedynamic #88,  0             // InvokeDynamic #13:accept:()Ljava/util/function/BiConsumer;
     327: invokestatic  #59                 // Method setter:(Ljava/util/function/BiConsumer;)Ljava/util/function/BiConsumer;
     330: invokevirtual #60                 // Method software/amazon/awssdk/core/SdkField$Builder.setter:(Ljava/util/function/BiConsumer;)Lsoftware/amazon/awssdk/core/SdkField$Builder;
     333: iconst_1
     334: anewarray     #61                 // class software/amazon/awssdk/core/traits/Trait
     337: dup
     338: iconst_0
     339: invokestatic  #62                 // Method software/amazon/awssdk/core/traits/LocationTrait.builder:()Lsoftware/amazon/awssdk/core/traits/LocationTrait$Builder;
     342: getstatic     #63                 // Field software/amazon/awssdk/core/protocol/MarshallLocation.PAYLOAD:Lsoftware/amazon/awssdk/core/protocol/MarshallLocation;
     345: invokevirtual #64                 // Method software/amazon/awssdk/core/traits/LocationTrait$Builder.location:(Lsoftware/amazon/awssdk/core/protocol/MarshallLocation;)Lsoftware/amazon/awssdk/core/traits/LocationTrait$Builder;
     348: ldc           #89                 // String segmentModifier
     350: invokevirtual #66                 // Method software/amazon/awssdk/core/traits/LocationTrait$Builder.locationName:(Ljava/lang/String;)Lsoftware/amazon/awssdk/core/traits/LocationTrait$Builder;
     353: invokevirtual #67                 // Method software/amazon/awssdk/core/traits/LocationTrait$Builder.build:()Lsoftware/amazon/awssdk/core/traits/LocationTrait;
     356: aastore
     357: invokevirtual #68                 // Method software/amazon/awssdk/core/SdkField$Builder.traits:([Lsoftware/amazon/awssdk/core/traits/Trait;)Lsoftware/amazon/awssdk/core/SdkField$Builder;
     360: invokevirtual #69                 // Method software/amazon/awssdk/core/SdkField$Builder.build:()Lsoftware/amazon/awssdk/core/SdkField;
     363: putstatic     #90                 // Field SEGMENT_MODIFIER_FIELD:Lsoftware/amazon/awssdk/core/SdkField;
     366: bipush        6
     368: anewarray     #91                 // class software/amazon/awssdk/core/SdkField
     371: dup
     372: iconst_0
     373: getstatic     #70                 // Field AUDIO_GROUP_ID_FIELD:Lsoftware/amazon/awssdk/core/SdkField;
     376: aastore
     377: dup
     378: iconst_1
     379: getstatic     #74                 // Field AUDIO_ONLY_CONTAINER_FIELD:Lsoftware/amazon/awssdk/core/SdkField;
     382: aastore
     383: dup
     384: iconst_2
     385: getstatic     #78                 // Field AUDIO_RENDITION_SETS_FIELD:Lsoftware/amazon/awssdk/core/SdkField;
     388: aastore
     389: dup
     390: iconst_3
     391: getstatic     #82                 // Field AUDIO_TRACK_TYPE_FIELD:Lsoftware/amazon/awssdk/core/SdkField;
     394: aastore
     395: dup
     396: iconst_4
     397: getstatic     #86                 // Field I_FRAME_ONLY_MANIFEST_FIELD:Lsoftware/amazon/awssdk/core/SdkField;
     400: aastore
     401: dup
     402: iconst_5
     403: getstatic     #90                 // Field SEGMENT_MODIFIER_FIELD:Lsoftware/amazon/awssdk/core/SdkField;
     406: aastore
     407: invokestatic  #92                 // Method java/util/Arrays.asList:([Ljava/lang/Object;)Ljava/util/List;
     410: invokestatic  #93                 // Method java/util/Collections.unmodifiableList:(Ljava/util/List;)Ljava/util/List;
     413: putstatic     #1                  // Field SDK_FIELDS:Ljava/util/List;
     416: return
}
