Compiled from "TDBMaker.java"
public class org.apache.jena.tdb.sys.TDBMaker {
  public org.apache.jena.tdb.sys.TDBMaker();
    Code:
       0: aload_0
       1: invokespecial #1                  // Method java/lang/Object."<init>":()V
       4: return

  static org.apache.jena.tdb.transaction.DatasetGraphTransaction createDatasetGraphTransaction(java.lang.String);
    Code:
       0: aload_0
       1: invokestatic  #2                  // Method org/apache/jena/tdb/base/file/Location.create:(Ljava/lang/String;)Lorg/apache/jena/tdb/base/file/Location;
       4: invokestatic  #3                  // Method createDatasetGraphTransaction:(Lorg/apache/jena/tdb/base/file/Location;)Lorg/apache/jena/tdb/transaction/DatasetGraphTransaction;
       7: areturn

  public static org.apache.jena.tdb.transaction.DatasetGraphTransaction createDatasetGraphTransaction(org.apache.jena.tdb.base.file.Location);
    Code:
       0: aload_0
       1: invokestatic  #4                  // Method _create:(Lorg/apache/jena/tdb/base/file/Location;)Lorg/apache/jena/tdb/transaction/DatasetGraphTransaction;
       4: areturn

  public static org.apache.jena.tdb.transaction.DatasetGraphTransaction createDatasetGraphTransaction();
    Code:
       0: invokestatic  #5                  // Method org/apache/jena/tdb/base/file/Location.mem:()Lorg/apache/jena/tdb/base/file/Location;
       3: invokestatic  #3                  // Method createDatasetGraphTransaction:(Lorg/apache/jena/tdb/base/file/Location;)Lorg/apache/jena/tdb/transaction/DatasetGraphTransaction;
       6: areturn

  private static org.apache.jena.tdb.transaction.DatasetGraphTransaction _create(org.apache.jena.tdb.base.file.Location);
    Code:
       0: new           #6                  // class org/apache/jena/tdb/transaction/DatasetGraphTransaction
       3: dup
       4: aload_0
       5: invokespecial #7                  // Method org/apache/jena/tdb/transaction/DatasetGraphTransaction."<init>":(Lorg/apache/jena/tdb/base/file/Location;)V
       8: areturn

  public static void releaseLocation(org.apache.jena.tdb.base.file.Location);
    Code:
       0: aload_0
       1: invokestatic  #8                  // Method org/apache/jena/tdb/StoreConnection.release:(Lorg/apache/jena/tdb/base/file/Location;)V
       4: return

  public static void reset();
    Code:
       0: invokestatic  #9                  // Method org/apache/jena/tdb/StoreConnection.reset:()V
       3: return

  public static org.apache.jena.tdb.store.DatasetGraphTDB createDatasetGraphTDB(org.apache.jena.tdb.base.file.Location, org.apache.jena.tdb.setup.StoreParams);
    Code:
       0: aload_0
       1: aload_1
       2: invokestatic  #10                 // Method org/apache/jena/tdb/setup/DatasetBuilderStd.create:(Lorg/apache/jena/tdb/base/file/Location;Lorg/apache/jena/tdb/setup/StoreParams;)Lorg/apache/jena/tdb/store/DatasetGraphTDB;
       5: areturn
}
