Compiled from "DebugProbes.kt"
public final class kotlin.coroutines.jvm.internal.DebugProbesKt {
  public static final <T> kotlin.coroutines.Continuation<T> probeCoroutineCreated(kotlin.coroutines.Continuation<? super T>);
    Code:
       0: aload_0
       1: ldc           #12                 // String completion
       3: invokestatic  #18                 // Method kotlin/jvm/internal/Intrinsics.checkParameterIsNotNull:(Ljava/lang/Object;Ljava/lang/String;)V
       6: aload_0
       7: areturn

  public static final void probeCoroutineResumed(kotlin.coroutines.Continuation<?>);
    Code:
       0: aload_0
       1: ldc           #23                 // String frame
       3: invokestatic  #18                 // Method kotlin/jvm/internal/Intrinsics.checkParameterIsNotNull:(Ljava/lang/Object;Ljava/lang/String;)V
       6: return

  public static final void probeCoroutineSuspended(kotlin.coroutines.Continuation<?>);
    Code:
       0: aload_0
       1: ldc           #23                 // String frame
       3: invokestatic  #18                 // Method kotlin/jvm/internal/Intrinsics.checkParameterIsNotNull:(Ljava/lang/Object;Ljava/lang/String;)V
       6: return
}
