Compiled from "CellLayoutUtil.java"
class org.eclipse.ui.internal.layout.CellLayoutUtil {
  private static org.eclipse.swt.graphics.Point zero;

  private static org.eclipse.swt.graphics.Point minimumShellSize;

  private static org.eclipse.ui.internal.layout.CellData defaultData;

  static {};
    Code:
       0: new           #28                 // class org/eclipse/swt/graphics/Point
       3: dup
       4: iconst_0
       5: iconst_0
       6: invokespecial #62                 // Method org/eclipse/swt/graphics/Point."<init>":(II)V
       9: putstatic     #59                 // Field zero:Lorg/eclipse/swt/graphics/Point;
      12: new           #32                 // class org/eclipse/ui/internal/layout/CellData
      15: dup
      16: invokespecial #68                 // Method org/eclipse/ui/internal/layout/CellData."<init>":()V
      19: putstatic     #60                 // Field defaultData:Lorg/eclipse/ui/internal/layout/CellData;
      22: return

  org.eclipse.ui.internal.layout.CellLayoutUtil();
    Code:
       0: aload_0
       1: invokespecial #61                 // Method java/lang/Object."<init>":()V
       4: return

  static org.eclipse.swt.graphics.Point computeMinimumSize(org.eclipse.swt.widgets.Composite);
    Code:
       0: aload_0
       1: instanceof    #31                 // class org/eclipse/swt/widgets/Shell
       4: ifeq          49
       7: getstatic     #58                 // Field minimumShellSize:Lorg/eclipse/swt/graphics/Point;
      10: ifnonnull     45
      13: new           #31                 // class org/eclipse/swt/widgets/Shell
      16: dup
      17: aload_0
      18: checkcast     #31                 // class org/eclipse/swt/widgets/Shell
      21: sipush        2160
      24: invokespecial #67                 // Method org/eclipse/swt/widgets/Shell."<init>":(Lorg/eclipse/swt/widgets/Shell;I)V
      27: astore_1
      28: aload_1
      29: iconst_0
      30: iconst_0
      31: invokevirtual #65                 // Method org/eclipse/swt/widgets/Shell.setSize:(II)V
      34: aload_1
      35: invokevirtual #66                 // Method org/eclipse/swt/widgets/Shell.getSize:()Lorg/eclipse/swt/graphics/Point;
      38: putstatic     #58                 // Field minimumShellSize:Lorg/eclipse/swt/graphics/Point;
      41: aload_1
      42: invokevirtual #64                 // Method org/eclipse/swt/widgets/Shell.dispose:()V
      45: getstatic     #58                 // Field minimumShellSize:Lorg/eclipse/swt/graphics/Point;
      48: areturn
      49: getstatic     #59                 // Field zero:Lorg/eclipse/swt/graphics/Point;
      52: areturn

  static org.eclipse.ui.internal.layout.CellData getData(org.eclipse.swt.widgets.Control);
    Code:
       0: aload_0
       1: invokevirtual #63                 // Method org/eclipse/swt/widgets/Control.getLayoutData:()Ljava/lang/Object;
       4: astore_1
       5: aconst_null
       6: astore_2
       7: aload_1
       8: instanceof    #32                 // class org/eclipse/ui/internal/layout/CellData
      11: ifeq          22
      14: aload_1
      15: checkcast     #32                 // class org/eclipse/ui/internal/layout/CellData
      18: astore_2
      19: goto          41
      22: aload_1
      23: instanceof    #29                 // class org/eclipse/swt/layout/GridData
      26: ifeq          41
      29: new           #32                 // class org/eclipse/ui/internal/layout/CellData
      32: dup
      33: aload_1
      34: checkcast     #29                 // class org/eclipse/swt/layout/GridData
      37: invokespecial #69                 // Method org/eclipse/ui/internal/layout/CellData."<init>":(Lorg/eclipse/swt/layout/GridData;)V
      40: astore_2
      41: aload_2
      42: ifnonnull     49
      45: getstatic     #60                 // Field defaultData:Lorg/eclipse/ui/internal/layout/CellData;
      48: astore_2
      49: aload_2
      50: areturn
}
