Compiled from "RaptorEntitiesGraphComponent.kt"
public final class io.fluidsonic.raptor.RaptorEntitiesGraphComponentKt {
  public static final void definition(io.fluidsonic.raptor.graph.RaptorGraphComponent, io.fluidsonic.raptor.RaptorEntityId$Definition<?>);
    Code:
       0: aload_0
       1: ldc           #11                 // String <this>
       3: invokestatic  #17                 // Method kotlin/jvm/internal/Intrinsics.checkNotNullParameter:(Ljava/lang/Object;Ljava/lang/String;)V
       6: aload_1
       7: ldc           #18                 // String definition
       9: invokestatic  #17                 // Method kotlin/jvm/internal/Intrinsics.checkNotNullParameter:(Ljava/lang/Object;Ljava/lang/String;)V
      12: aload_0
      13: invokevirtual #24                 // Method io/fluidsonic/raptor/graph/RaptorGraphComponent.getDefinitions:()Lio/fluidsonic/raptor/graph/RaptorGraphComponent$Definitions;
      16: checkcast     #26                 // class io/fluidsonic/raptor/RaptorAssemblyQuery
      19: iconst_1
      20: anewarray     #28                 // class io/fluidsonic/raptor/graph/RaptorGraphDefinition
      23: astore_2
      24: aload_2
      25: iconst_0
      26: aload_1
      27: invokestatic  #34                 // Method io/fluidsonic/raptor/RaptorEntityId_graphqlKt.graphDefinition:(Lio/fluidsonic/raptor/RaptorEntityId$Definition;)Lio/fluidsonic/raptor/graph/RaptorGraphDefinition;
      30: aastore
      31: aload_2
      32: invokestatic  #40                 // Method io/fluidsonic/raptor/graph/RaptorGraphComponentKt.add:(Lio/fluidsonic/raptor/RaptorAssemblyQuery;[Lio/fluidsonic/raptor/graph/RaptorGraphDefinition;)V
      35: aload_0
      36: checkcast     #42                 // class io/fluidsonic/raptor/RaptorComponent
      39: invokestatic  #48                 // Method io/fluidsonic/raptor/RaptorComponentRegistryKt.getComponentRegistry:(Lio/fluidsonic/raptor/RaptorComponent;)Lio/fluidsonic/raptor/RaptorComponentRegistry;
      42: astore_2
      43: getstatic     #54                 // Field io/fluidsonic/raptor/RaptorEntitiesGraphComponent.Companion:Lio/fluidsonic/raptor/RaptorEntitiesGraphComponent$Companion;
      46: invokevirtual #60                 // Method io/fluidsonic/raptor/RaptorEntitiesGraphComponent$Companion.getKey:()Lio/fluidsonic/raptor/RaptorComponentKey;
      49: astore_3
      50: iconst_0
      51: istore        4
      53: aload_2
      54: aload_3
      55: invokeinterface #66,  2           // InterfaceMethod io/fluidsonic/raptor/RaptorComponentRegistry.oneOrNull:(Lio/fluidsonic/raptor/RaptorComponentKey;)Lio/fluidsonic/raptor/RaptorComponent;
      60: dup
      61: ifnonnull     98
      64: pop
      65: aload_2
      66: aload_3
      67: astore        7
      69: astore        6
      71: iconst_0
      72: istore        5
      74: new           #50                 // class io/fluidsonic/raptor/RaptorEntitiesGraphComponent
      77: dup
      78: aload_0
      79: invokespecial #70                 // Method io/fluidsonic/raptor/RaptorEntitiesGraphComponent."<init>":(Lio/fluidsonic/raptor/graph/RaptorGraphComponent;)V
      82: astore        8
      84: aload         6
      86: aload         7
      88: aload         8
      90: checkcast     #42                 // class io/fluidsonic/raptor/RaptorComponent
      93: invokeinterface #74,  3           // InterfaceMethod io/fluidsonic/raptor/RaptorComponentRegistry.register:(Lio/fluidsonic/raptor/RaptorComponentKey;Lio/fluidsonic/raptor/RaptorComponent;)Lio/fluidsonic/raptor/RaptorComponent;
      98: checkcast     #50                 // class io/fluidsonic/raptor/RaptorEntitiesGraphComponent
     101: aload_1
     102: invokevirtual #78                 // Method io/fluidsonic/raptor/RaptorEntitiesGraphComponent.addIdDefinition$raptor_entities:(Lio/fluidsonic/raptor/RaptorEntityId$Definition;)V
     105: return
}
