Compiled from "RaptorEntitiesPlugin.kt"
public final class io.fluidsonic.raptor.RaptorEntitiesPluginKt {
  public static final io.fluidsonic.raptor.RaptorEntitiesComponent getEntities(io.fluidsonic.raptor.RaptorAssemblyScope);
    Code:
       0: aload_0
       1: ldc           #9                  // String <this>
       3: invokestatic  #15                 // Method kotlin/jvm/internal/Intrinsics.checkNotNullParameter:(Ljava/lang/Object;Ljava/lang/String;)V
       6: aload_0
       7: invokeinterface #21,  1           // InterfaceMethod io/fluidsonic/raptor/RaptorAssemblyScope.getComponentRegistry:()Lio/fluidsonic/raptor/RaptorComponentRegistry;
      12: astore_1
      13: getstatic     #27                 // Field io/fluidsonic/raptor/RaptorEntitiesComponent.Companion:Lio/fluidsonic/raptor/RaptorEntitiesComponent$Companion;
      16: invokevirtual #33                 // Method io/fluidsonic/raptor/RaptorEntitiesComponent$Companion.getKey:()Lio/fluidsonic/raptor/RaptorComponentKey;
      19: astore_2
      20: iconst_0
      21: istore_3
      22: aload_1
      23: aload_2
      24: invokeinterface #39,  2           // InterfaceMethod io/fluidsonic/raptor/RaptorComponentRegistry.oneOrNull:(Lio/fluidsonic/raptor/RaptorComponentKey;)Lio/fluidsonic/raptor/RaptorComponent;
      29: dup
      30: ifnonnull     66
      33: pop
      34: aload_1
      35: aload_2
      36: astore        6
      38: astore        5
      40: iconst_0
      41: istore        4
      43: new           #23                 // class io/fluidsonic/raptor/RaptorEntitiesComponent
      46: dup
      47: invokespecial #43                 // Method io/fluidsonic/raptor/RaptorEntitiesComponent."<init>":()V
      50: astore        7
      52: aload         5
      54: aload         6
      56: aload         7
      58: checkcast     #45                 // class io/fluidsonic/raptor/RaptorComponent
      61: invokeinterface #49,  3           // InterfaceMethod io/fluidsonic/raptor/RaptorComponentRegistry.register:(Lio/fluidsonic/raptor/RaptorComponentKey;Lio/fluidsonic/raptor/RaptorComponent;)Lio/fluidsonic/raptor/RaptorComponent;
      66: checkcast     #23                 // class io/fluidsonic/raptor/RaptorEntitiesComponent
      69: areturn

  public static void getEntities$annotations(io.fluidsonic.raptor.RaptorAssemblyScope);
    Code:
       0: return
}
