Compiled from "TypeDescriptor.java"
class org.springframework.core.convert.TypeDescriptor$StreamDelegate {
  private org.springframework.core.convert.TypeDescriptor$StreamDelegate();
    Code:
       0: aload_0
       1: invokespecial #1                  // Method java/lang/Object."<init>":()V
       4: return

  public static boolean isStream(java.lang.Class<?>);
    Code:
       0: ldc           #2                  // class java/util/stream/Stream
       2: aload_0
       3: invokevirtual #3                  // Method java/lang/Class.isAssignableFrom:(Ljava/lang/Class;)Z
       6: ireturn

  public static org.springframework.core.convert.TypeDescriptor getStreamElementType(org.springframework.core.convert.TypeDescriptor);
    Code:
       0: aload_0
       1: aload_0
       2: invokestatic  #4                  // Method org/springframework/core/convert/TypeDescriptor.access$000:(Lorg/springframework/core/convert/TypeDescriptor;)Lorg/springframework/core/ResolvableType;
       5: ldc           #2                  // class java/util/stream/Stream
       7: invokevirtual #5                  // Method org/springframework/core/ResolvableType.as:(Ljava/lang/Class;)Lorg/springframework/core/ResolvableType;
      10: iconst_1
      11: newarray       int
      13: dup
      14: iconst_0
      15: iconst_0
      16: iastore
      17: invokevirtual #6                  // Method org/springframework/core/ResolvableType.getGeneric:([I)Lorg/springframework/core/ResolvableType;
      20: invokestatic  #7                  // Method org/springframework/core/convert/TypeDescriptor.access$100:(Lorg/springframework/core/convert/TypeDescriptor;Lorg/springframework/core/ResolvableType;)Lorg/springframework/core/convert/TypeDescriptor;
      23: areturn
}
