Compiled from "BoosterState.java"
public final class org.bidib.api.json.types.booster.BoosterState$BoosterStateType extends java.lang.Enum<org.bidib.api.json.types.booster.BoosterState$BoosterStateType> {
  public static final org.bidib.api.json.types.booster.BoosterState$BoosterStateType OFF;

  public static final org.bidib.api.json.types.booster.BoosterState$BoosterStateType OFF_SHORT;

  public static final org.bidib.api.json.types.booster.BoosterState$BoosterStateType OFF_HOT;

  public static final org.bidib.api.json.types.booster.BoosterState$BoosterStateType OFF_NOPOWER;

  public static final org.bidib.api.json.types.booster.BoosterState$BoosterStateType OFF_GO_REQ;

  public static final org.bidib.api.json.types.booster.BoosterState$BoosterStateType OFF_HERE;

  public static final org.bidib.api.json.types.booster.BoosterState$BoosterStateType OFF_NO_DCC;

  public static final org.bidib.api.json.types.booster.BoosterState$BoosterStateType ON;

  public static final org.bidib.api.json.types.booster.BoosterState$BoosterStateType ON_LIMIT;

  public static final org.bidib.api.json.types.booster.BoosterState$BoosterStateType ON_HOT;

  public static final org.bidib.api.json.types.booster.BoosterState$BoosterStateType ON_STOP_REQ;

  public static final org.bidib.api.json.types.booster.BoosterState$BoosterStateType ON_HERE;

  private final java.lang.String value;

  private static final java.util.Map<java.lang.String, org.bidib.api.json.types.booster.BoosterState$BoosterStateType> CONSTANTS;

  private static final org.bidib.api.json.types.booster.BoosterState$BoosterStateType[] $VALUES;

  public static org.bidib.api.json.types.booster.BoosterState$BoosterStateType[] values();
    Code:
       0: getstatic     #1                  // Field $VALUES:[Lorg/bidib/api/json/types/booster/BoosterState$BoosterStateType;
       3: invokevirtual #2                  // Method "[Lorg/bidib/api/json/types/booster/BoosterState$BoosterStateType;".clone:()Ljava/lang/Object;
       6: checkcast     #3                  // class "[Lorg/bidib/api/json/types/booster/BoosterState$BoosterStateType;"
       9: areturn

  public static org.bidib.api.json.types.booster.BoosterState$BoosterStateType valueOf(java.lang.String);
    Code:
       0: ldc           #4                  // class org/bidib/api/json/types/booster/BoosterState$BoosterStateType
       2: aload_0
       3: invokestatic  #5                  // Method java/lang/Enum.valueOf:(Ljava/lang/Class;Ljava/lang/String;)Ljava/lang/Enum;
       6: checkcast     #4                  // class org/bidib/api/json/types/booster/BoosterState$BoosterStateType
       9: areturn

  private org.bidib.api.json.types.booster.BoosterState$BoosterStateType(java.lang.String);
    Code:
       0: aload_0
       1: aload_1
       2: iload_2
       3: invokespecial #6                  // Method java/lang/Enum."<init>":(Ljava/lang/String;I)V
       6: aload_0
       7: aload_3
       8: putfield      #7                  // Field value:Ljava/lang/String;
      11: return

  public java.lang.String toString();
    Code:
       0: aload_0
       1: getfield      #7                  // Field value:Ljava/lang/String;
       4: areturn

  public java.lang.String value();
    Code:
       0: aload_0
       1: getfield      #7                  // Field value:Ljava/lang/String;
       4: areturn

  public static org.bidib.api.json.types.booster.BoosterState$BoosterStateType fromValue(java.lang.String);
    Code:
       0: getstatic     #8                  // Field CONSTANTS:Ljava/util/Map;
       3: aload_0
       4: invokeinterface #9,  2            // InterfaceMethod java/util/Map.get:(Ljava/lang/Object;)Ljava/lang/Object;
       9: checkcast     #4                  // class org/bidib/api/json/types/booster/BoosterState$BoosterStateType
      12: astore_1
      13: aload_1
      14: ifnonnull     26
      17: new           #10                 // class java/lang/IllegalArgumentException
      20: dup
      21: aload_0
      22: invokespecial #11                 // Method java/lang/IllegalArgumentException."<init>":(Ljava/lang/String;)V
      25: athrow
      26: aload_1
      27: areturn

  static {};
    Code:
       0: new           #4                  // class org/bidib/api/json/types/booster/BoosterState$BoosterStateType
       3: dup
       4: ldc           #12                 // String OFF
       6: iconst_0
       7: ldc           #12                 // String OFF
       9: invokespecial #13                 // Method "<init>":(Ljava/lang/String;ILjava/lang/String;)V
      12: putstatic     #14                 // Field OFF:Lorg/bidib/api/json/types/booster/BoosterState$BoosterStateType;
      15: new           #4                  // class org/bidib/api/json/types/booster/BoosterState$BoosterStateType
      18: dup
      19: ldc           #15                 // String OFF_SHORT
      21: iconst_1
      22: ldc           #15                 // String OFF_SHORT
      24: invokespecial #13                 // Method "<init>":(Ljava/lang/String;ILjava/lang/String;)V
      27: putstatic     #16                 // Field OFF_SHORT:Lorg/bidib/api/json/types/booster/BoosterState$BoosterStateType;
      30: new           #4                  // class org/bidib/api/json/types/booster/BoosterState$BoosterStateType
      33: dup
      34: ldc           #17                 // String OFF_HOT
      36: iconst_2
      37: ldc           #17                 // String OFF_HOT
      39: invokespecial #13                 // Method "<init>":(Ljava/lang/String;ILjava/lang/String;)V
      42: putstatic     #18                 // Field OFF_HOT:Lorg/bidib/api/json/types/booster/BoosterState$BoosterStateType;
      45: new           #4                  // class org/bidib/api/json/types/booster/BoosterState$BoosterStateType
      48: dup
      49: ldc           #19                 // String OFF_NOPOWER
      51: iconst_3
      52: ldc           #19                 // String OFF_NOPOWER
      54: invokespecial #13                 // Method "<init>":(Ljava/lang/String;ILjava/lang/String;)V
      57: putstatic     #20                 // Field OFF_NOPOWER:Lorg/bidib/api/json/types/booster/BoosterState$BoosterStateType;
      60: new           #4                  // class org/bidib/api/json/types/booster/BoosterState$BoosterStateType
      63: dup
      64: ldc           #21                 // String OFF_GO_REQ
      66: iconst_4
      67: ldc           #21                 // String OFF_GO_REQ
      69: invokespecial #13                 // Method "<init>":(Ljava/lang/String;ILjava/lang/String;)V
      72: putstatic     #22                 // Field OFF_GO_REQ:Lorg/bidib/api/json/types/booster/BoosterState$BoosterStateType;
      75: new           #4                  // class org/bidib/api/json/types/booster/BoosterState$BoosterStateType
      78: dup
      79: ldc           #23                 // String OFF_HERE
      81: iconst_5
      82: ldc           #23                 // String OFF_HERE
      84: invokespecial #13                 // Method "<init>":(Ljava/lang/String;ILjava/lang/String;)V
      87: putstatic     #24                 // Field OFF_HERE:Lorg/bidib/api/json/types/booster/BoosterState$BoosterStateType;
      90: new           #4                  // class org/bidib/api/json/types/booster/BoosterState$BoosterStateType
      93: dup
      94: ldc           #25                 // String OFF_NO_DCC
      96: bipush        6
      98: ldc           #25                 // String OFF_NO_DCC
     100: invokespecial #13                 // Method "<init>":(Ljava/lang/String;ILjava/lang/String;)V
     103: putstatic     #26                 // Field OFF_NO_DCC:Lorg/bidib/api/json/types/booster/BoosterState$BoosterStateType;
     106: new           #4                  // class org/bidib/api/json/types/booster/BoosterState$BoosterStateType
     109: dup
     110: ldc           #27                 // String ON
     112: bipush        7
     114: ldc           #27                 // String ON
     116: invokespecial #13                 // Method "<init>":(Ljava/lang/String;ILjava/lang/String;)V
     119: putstatic     #28                 // Field ON:Lorg/bidib/api/json/types/booster/BoosterState$BoosterStateType;
     122: new           #4                  // class org/bidib/api/json/types/booster/BoosterState$BoosterStateType
     125: dup
     126: ldc           #29                 // String ON_LIMIT
     128: bipush        8
     130: ldc           #29                 // String ON_LIMIT
     132: invokespecial #13                 // Method "<init>":(Ljava/lang/String;ILjava/lang/String;)V
     135: putstatic     #30                 // Field ON_LIMIT:Lorg/bidib/api/json/types/booster/BoosterState$BoosterStateType;
     138: new           #4                  // class org/bidib/api/json/types/booster/BoosterState$BoosterStateType
     141: dup
     142: ldc           #31                 // String ON_HOT
     144: bipush        9
     146: ldc           #31                 // String ON_HOT
     148: invokespecial #13                 // Method "<init>":(Ljava/lang/String;ILjava/lang/String;)V
     151: putstatic     #32                 // Field ON_HOT:Lorg/bidib/api/json/types/booster/BoosterState$BoosterStateType;
     154: new           #4                  // class org/bidib/api/json/types/booster/BoosterState$BoosterStateType
     157: dup
     158: ldc           #33                 // String ON_STOP_REQ
     160: bipush        10
     162: ldc           #33                 // String ON_STOP_REQ
     164: invokespecial #13                 // Method "<init>":(Ljava/lang/String;ILjava/lang/String;)V
     167: putstatic     #34                 // Field ON_STOP_REQ:Lorg/bidib/api/json/types/booster/BoosterState$BoosterStateType;
     170: new           #4                  // class org/bidib/api/json/types/booster/BoosterState$BoosterStateType
     173: dup
     174: ldc           #35                 // String ON_HERE
     176: bipush        11
     178: ldc           #35                 // String ON_HERE
     180: invokespecial #13                 // Method "<init>":(Ljava/lang/String;ILjava/lang/String;)V
     183: putstatic     #36                 // Field ON_HERE:Lorg/bidib/api/json/types/booster/BoosterState$BoosterStateType;
     186: bipush        12
     188: anewarray     #4                  // class org/bidib/api/json/types/booster/BoosterState$BoosterStateType
     191: dup
     192: iconst_0
     193: getstatic     #14                 // Field OFF:Lorg/bidib/api/json/types/booster/BoosterState$BoosterStateType;
     196: aastore
     197: dup
     198: iconst_1
     199: getstatic     #16                 // Field OFF_SHORT:Lorg/bidib/api/json/types/booster/BoosterState$BoosterStateType;
     202: aastore
     203: dup
     204: iconst_2
     205: getstatic     #18                 // Field OFF_HOT:Lorg/bidib/api/json/types/booster/BoosterState$BoosterStateType;
     208: aastore
     209: dup
     210: iconst_3
     211: getstatic     #20                 // Field OFF_NOPOWER:Lorg/bidib/api/json/types/booster/BoosterState$BoosterStateType;
     214: aastore
     215: dup
     216: iconst_4
     217: getstatic     #22                 // Field OFF_GO_REQ:Lorg/bidib/api/json/types/booster/BoosterState$BoosterStateType;
     220: aastore
     221: dup
     222: iconst_5
     223: getstatic     #24                 // Field OFF_HERE:Lorg/bidib/api/json/types/booster/BoosterState$BoosterStateType;
     226: aastore
     227: dup
     228: bipush        6
     230: getstatic     #26                 // Field OFF_NO_DCC:Lorg/bidib/api/json/types/booster/BoosterState$BoosterStateType;
     233: aastore
     234: dup
     235: bipush        7
     237: getstatic     #28                 // Field ON:Lorg/bidib/api/json/types/booster/BoosterState$BoosterStateType;
     240: aastore
     241: dup
     242: bipush        8
     244: getstatic     #30                 // Field ON_LIMIT:Lorg/bidib/api/json/types/booster/BoosterState$BoosterStateType;
     247: aastore
     248: dup
     249: bipush        9
     251: getstatic     #32                 // Field ON_HOT:Lorg/bidib/api/json/types/booster/BoosterState$BoosterStateType;
     254: aastore
     255: dup
     256: bipush        10
     258: getstatic     #34                 // Field ON_STOP_REQ:Lorg/bidib/api/json/types/booster/BoosterState$BoosterStateType;
     261: aastore
     262: dup
     263: bipush        11
     265: getstatic     #36                 // Field ON_HERE:Lorg/bidib/api/json/types/booster/BoosterState$BoosterStateType;
     268: aastore
     269: putstatic     #1                  // Field $VALUES:[Lorg/bidib/api/json/types/booster/BoosterState$BoosterStateType;
     272: new           #37                 // class java/util/HashMap
     275: dup
     276: invokespecial #38                 // Method java/util/HashMap."<init>":()V
     279: putstatic     #8                  // Field CONSTANTS:Ljava/util/Map;
     282: invokestatic  #39                 // Method values:()[Lorg/bidib/api/json/types/booster/BoosterState$BoosterStateType;
     285: astore_0
     286: aload_0
     287: arraylength
     288: istore_1
     289: iconst_0
     290: istore_2
     291: iload_2
     292: iload_1
     293: if_icmpge     320
     296: aload_0
     297: iload_2
     298: aaload
     299: astore_3
     300: getstatic     #8                  // Field CONSTANTS:Ljava/util/Map;
     303: aload_3
     304: getfield      #7                  // Field value:Ljava/lang/String;
     307: aload_3
     308: invokeinterface #40,  3           // InterfaceMethod java/util/Map.put:(Ljava/lang/Object;Ljava/lang/Object;)Ljava/lang/Object;
     313: pop
     314: iinc          2, 1
     317: goto          291
     320: return
}
