Compiled from "ResultStatistics.scala"
public class org.yupana.proto.ResultStatistics$ResultStatisticsLens<UpperPB> extends scalapb.lenses.ObjectLens<UpperPB, org.yupana.proto.ResultStatistics> {
  public scalapb.lenses.Lens<UpperPB, java.lang.Object> seconds();
    Code:
       0: aload_0
       1: invokedynamic #40,  0             // InvokeDynamic #0:apply:()Lscala/Function1;
       6: invokedynamic #51,  0             // InvokeDynamic #1:apply:()Lscala/Function2;
      11: invokevirtual #55                 // Method field:(Lscala/Function1;Lscala/Function2;)Lscalapb/lenses/Lens;
      14: areturn

  public scalapb.lenses.Lens<UpperPB, java.lang.Object> rowCount();
    Code:
       0: aload_0
       1: invokedynamic #63,  0             // InvokeDynamic #2:apply:()Lscala/Function1;
       6: invokedynamic #68,  0             // InvokeDynamic #3:apply:()Lscala/Function2;
      11: invokevirtual #55                 // Method field:(Lscala/Function1;Lscala/Function2;)Lscalapb/lenses/Lens;
      14: areturn

  public static final int $anonfun$seconds$1(org.yupana.proto.ResultStatistics);
    Code:
       0: aload_0
       1: invokevirtual #74                 // Method org/yupana/proto/ResultStatistics.seconds:()I
       4: ireturn

  public static final org.yupana.proto.ResultStatistics $anonfun$seconds$2(org.yupana.proto.ResultStatistics, int);
    Code:
       0: aload_0
       1: iload_1
       2: aload_0
       3: invokevirtual #82                 // Method org/yupana/proto/ResultStatistics.copy$default$2:()I
       6: invokevirtual #86                 // Method org/yupana/proto/ResultStatistics.copy:(II)Lorg/yupana/proto/ResultStatistics;
       9: areturn

  public static final int $anonfun$rowCount$1(org.yupana.proto.ResultStatistics);
    Code:
       0: aload_0
       1: invokevirtual #91                 // Method org/yupana/proto/ResultStatistics.rowCount:()I
       4: ireturn

  public static final org.yupana.proto.ResultStatistics $anonfun$rowCount$2(org.yupana.proto.ResultStatistics, int);
    Code:
       0: iload_1
       1: istore_2
       2: aload_0
       3: invokevirtual #95                 // Method org/yupana/proto/ResultStatistics.copy$default$1:()I
       6: istore_3
       7: aload_0
       8: iload_3
       9: iload_2
      10: invokevirtual #86                 // Method org/yupana/proto/ResultStatistics.copy:(II)Lorg/yupana/proto/ResultStatistics;
      13: areturn

  public org.yupana.proto.ResultStatistics$ResultStatisticsLens(scalapb.lenses.Lens<UpperPB, org.yupana.proto.ResultStatistics>);
    Code:
       0: aload_0
       1: aload_1
       2: invokespecial #103                // Method scalapb/lenses/ObjectLens."<init>":(Lscalapb/lenses/Lens;)V
       5: return

  public static final java.lang.Object $anonfun$seconds$1$adapted(org.yupana.proto.ResultStatistics);
    Code:
       0: aload_0
       1: invokestatic  #106                // Method $anonfun$seconds$1:(Lorg/yupana/proto/ResultStatistics;)I
       4: invokestatic  #112                // Method scala/runtime/BoxesRunTime.boxToInteger:(I)Ljava/lang/Integer;
       7: areturn

  public static final org.yupana.proto.ResultStatistics $anonfun$seconds$2$adapted(org.yupana.proto.ResultStatistics, java.lang.Object);
    Code:
       0: aload_0
       1: aload_1
       2: invokestatic  #116                // Method scala/runtime/BoxesRunTime.unboxToInt:(Ljava/lang/Object;)I
       5: invokestatic  #118                // Method $anonfun$seconds$2:(Lorg/yupana/proto/ResultStatistics;I)Lorg/yupana/proto/ResultStatistics;
       8: areturn

  public static final java.lang.Object $anonfun$rowCount$1$adapted(org.yupana.proto.ResultStatistics);
    Code:
       0: aload_0
       1: invokestatic  #121                // Method $anonfun$rowCount$1:(Lorg/yupana/proto/ResultStatistics;)I
       4: invokestatic  #112                // Method scala/runtime/BoxesRunTime.boxToInteger:(I)Ljava/lang/Integer;
       7: areturn

  public static final org.yupana.proto.ResultStatistics $anonfun$rowCount$2$adapted(org.yupana.proto.ResultStatistics, java.lang.Object);
    Code:
       0: aload_0
       1: aload_1
       2: invokestatic  #116                // Method scala/runtime/BoxesRunTime.unboxToInt:(Ljava/lang/Object;)I
       5: invokestatic  #123                // Method $anonfun$rowCount$2:(Lorg/yupana/proto/ResultStatistics;I)Lorg/yupana/proto/ResultStatistics;
       8: areturn

  private static java.lang.Object $deserializeLambda$(java.lang.invoke.SerializedLambda);
    Code:
       0: aload_0
       1: invokedynamic #135,  0            // InvokeDynamic #4:lambdaDeserialize:(Ljava/lang/invoke/SerializedLambda;)Ljava/lang/Object;
       6: areturn
}
