Compiled from "EntityGraph.java"
public final class org.springframework.data.jpa.repository.EntityGraph$EntityGraphType extends java.lang.Enum<org.springframework.data.jpa.repository.EntityGraph$EntityGraphType> {
  public static final org.springframework.data.jpa.repository.EntityGraph$EntityGraphType LOAD;

  public static final org.springframework.data.jpa.repository.EntityGraph$EntityGraphType FETCH;

  private final java.lang.String key;

  private static final org.springframework.data.jpa.repository.EntityGraph$EntityGraphType[] $VALUES;

  public static org.springframework.data.jpa.repository.EntityGraph$EntityGraphType[] values();
    Code:
       0: getstatic     #1                  // Field $VALUES:[Lorg/springframework/data/jpa/repository/EntityGraph$EntityGraphType;
       3: invokevirtual #2                  // Method "[Lorg/springframework/data/jpa/repository/EntityGraph$EntityGraphType;".clone:()Ljava/lang/Object;
       6: checkcast     #3                  // class "[Lorg/springframework/data/jpa/repository/EntityGraph$EntityGraphType;"
       9: areturn

  public static org.springframework.data.jpa.repository.EntityGraph$EntityGraphType valueOf(java.lang.String);
    Code:
       0: ldc           #4                  // class org/springframework/data/jpa/repository/EntityGraph$EntityGraphType
       2: aload_0
       3: invokestatic  #5                  // Method java/lang/Enum.valueOf:(Ljava/lang/Class;Ljava/lang/String;)Ljava/lang/Enum;
       6: checkcast     #4                  // class org/springframework/data/jpa/repository/EntityGraph$EntityGraphType
       9: areturn

  private org.springframework.data.jpa.repository.EntityGraph$EntityGraphType(java.lang.String);
    Code:
       0: aload_0
       1: aload_1
       2: iload_2
       3: invokespecial #6                  // Method java/lang/Enum."<init>":(Ljava/lang/String;I)V
       6: aload_0
       7: aload_3
       8: putfield      #7                  // Field key:Ljava/lang/String;
      11: return

  public java.lang.String getKey();
    Code:
       0: aload_0
       1: getfield      #7                  // Field key:Ljava/lang/String;
       4: areturn

  static {};
    Code:
       0: new           #4                  // class org/springframework/data/jpa/repository/EntityGraph$EntityGraphType
       3: dup
       4: ldc           #8                  // String LOAD
       6: iconst_0
       7: ldc           #9                  // String javax.persistence.loadgraph
       9: invokespecial #10                 // Method "<init>":(Ljava/lang/String;ILjava/lang/String;)V
      12: putstatic     #11                 // Field LOAD:Lorg/springframework/data/jpa/repository/EntityGraph$EntityGraphType;
      15: new           #4                  // class org/springframework/data/jpa/repository/EntityGraph$EntityGraphType
      18: dup
      19: ldc           #12                 // String FETCH
      21: iconst_1
      22: ldc           #13                 // String javax.persistence.fetchgraph
      24: invokespecial #10                 // Method "<init>":(Ljava/lang/String;ILjava/lang/String;)V
      27: putstatic     #14                 // Field FETCH:Lorg/springframework/data/jpa/repository/EntityGraph$EntityGraphType;
      30: iconst_2
      31: anewarray     #4                  // class org/springframework/data/jpa/repository/EntityGraph$EntityGraphType
      34: dup
      35: iconst_0
      36: getstatic     #11                 // Field LOAD:Lorg/springframework/data/jpa/repository/EntityGraph$EntityGraphType;
      39: aastore
      40: dup
      41: iconst_1
      42: getstatic     #14                 // Field FETCH:Lorg/springframework/data/jpa/repository/EntityGraph$EntityGraphType;
      45: aastore
      46: putstatic     #1                  // Field $VALUES:[Lorg/springframework/data/jpa/repository/EntityGraph$EntityGraphType;
      49: return
}
