Compiled from "AlternativeElement.java"
abstract class groovyjarjarantlr.AlternativeElement extends groovyjarjarantlr.GrammarElement {
  groovyjarjarantlr.AlternativeElement next;

  protected int autoGenType;

  protected java.lang.String enclosingRuleName;

  public groovyjarjarantlr.AlternativeElement(groovyjarjarantlr.Grammar);
    Code:
       0: aload_0
       1: aload_1
       2: invokespecial #15                 // Method groovyjarjarantlr/GrammarElement."<init>":(Lgroovyjarjarantlr/Grammar;)V
       5: aload_0
       6: iconst_1
       7: putfield      #17                 // Field autoGenType:I
      10: return

  public groovyjarjarantlr.AlternativeElement(groovyjarjarantlr.Grammar, groovyjarjarantlr.Token);
    Code:
       0: aload_0
       1: aload_1
       2: aload_2
       3: invokespecial #20                 // Method groovyjarjarantlr/GrammarElement."<init>":(Lgroovyjarjarantlr/Grammar;Lgroovyjarjarantlr/Token;)V
       6: aload_0
       7: iconst_1
       8: putfield      #17                 // Field autoGenType:I
      11: return

  public groovyjarjarantlr.AlternativeElement(groovyjarjarantlr.Grammar, groovyjarjarantlr.Token, int);
    Code:
       0: aload_0
       1: aload_1
       2: aload_2
       3: invokespecial #20                 // Method groovyjarjarantlr/GrammarElement."<init>":(Lgroovyjarjarantlr/Grammar;Lgroovyjarjarantlr/Token;)V
       6: aload_0
       7: iconst_1
       8: putfield      #17                 // Field autoGenType:I
      11: aload_0
      12: iload_3
      13: putfield      #17                 // Field autoGenType:I
      16: return

  public int getAutoGenType();
    Code:
       0: aload_0
       1: getfield      #17                 // Field autoGenType:I
       4: ireturn

  public void setAutoGenType(int);
    Code:
       0: aload_0
       1: iload_1
       2: putfield      #17                 // Field autoGenType:I
       5: return

  public java.lang.String getLabel();
    Code:
       0: aconst_null
       1: areturn

  public void setLabel(java.lang.String);
    Code:
       0: return
}
