Compiled from "MakeGrammar.java"
public class groovyjarjarantlr.MakeGrammar extends groovyjarjarantlr.DefineGrammarSymbols {
  protected groovyjarjarantlr.collections.Stack blocks;

  protected groovyjarjarantlr.RuleRefElement lastRuleRef;

  protected groovyjarjarantlr.RuleEndElement ruleEnd;

  protected groovyjarjarantlr.RuleBlock ruleBlock;

  protected int nested;

  protected boolean grammarError;

  groovyjarjarantlr.ExceptionSpec currentExceptionSpec;

  public groovyjarjarantlr.MakeGrammar(groovyjarjarantlr.Tool, java.lang.String[], groovyjarjarantlr.LLkAnalyzer);
    Code:
       0: aload_0
       1: aload_1
       2: aload_2
       3: aload_3
       4: invokespecial #23                 // Method groovyjarjarantlr/DefineGrammarSymbols."<init>":(Lgroovyjarjarantlr/Tool;[Ljava/lang/String;Lgroovyjarjarantlr/LLkAnalyzer;)V
       7: aload_0
       8: new           #25                 // class groovyjarjarantlr/collections/impl/LList
      11: dup
      12: invokespecial #28                 // Method groovyjarjarantlr/collections/impl/LList."<init>":()V
      15: putfield      #30                 // Field blocks:Lgroovyjarjarantlr/collections/Stack;
      18: aload_0
      19: iconst_0
      20: putfield      #32                 // Field nested:I
      23: aload_0
      24: iconst_0
      25: putfield      #34                 // Field grammarError:Z
      28: aload_0
      29: aconst_null
      30: putfield      #36                 // Field currentExceptionSpec:Lgroovyjarjarantlr/ExceptionSpec;
      33: return

  public void abortGrammar();
    Code:
       0: ldc           #39                 // String unknown grammar
       2: astore_1
       3: aload_0
       4: getfield      #43                 // Field grammar:Lgroovyjarjarantlr/Grammar;
       7: ifnull        18
      10: aload_0
      11: getfield      #43                 // Field grammar:Lgroovyjarjarantlr/Grammar;
      14: invokevirtual #49                 // Method groovyjarjarantlr/Grammar.getClassName:()Ljava/lang/String;
      17: astore_1
      18: aload_0
      19: getfield      #53                 // Field tool:Lgroovyjarjarantlr/Tool;
      22: new           #55                 // class java/lang/StringBuffer
      25: dup
      26: invokespecial #56                 // Method java/lang/StringBuffer."<init>":()V
      29: ldc           #58                 // String aborting grammar \'
      31: invokevirtual #62                 // Method java/lang/StringBuffer.append:(Ljava/lang/String;)Ljava/lang/StringBuffer;
      34: aload_1
      35: invokevirtual #62                 // Method java/lang/StringBuffer.append:(Ljava/lang/String;)Ljava/lang/StringBuffer;
      38: ldc           #64                 // String \' due to errors
      40: invokevirtual #62                 // Method java/lang/StringBuffer.append:(Ljava/lang/String;)Ljava/lang/StringBuffer;
      43: invokevirtual #67                 // Method java/lang/StringBuffer.toString:()Ljava/lang/String;
      46: invokevirtual #73                 // Method groovyjarjarantlr/Tool.error:(Ljava/lang/String;)V
      49: aload_0
      50: invokespecial #75                 // Method groovyjarjarantlr/DefineGrammarSymbols.abortGrammar:()V
      53: return

  protected void addElementToCurrentAlt(groovyjarjarantlr.AlternativeElement);
    Code:
       0: aload_1
       1: aload_0
       2: getfield      #79                 // Field ruleBlock:Lgroovyjarjarantlr/RuleBlock;
       5: getfield      #85                 // Field groovyjarjarantlr/RuleBlock.ruleName:Ljava/lang/String;
       8: putfield      #90                 // Field groovyjarjarantlr/AlternativeElement.enclosingRuleName:Ljava/lang/String;
      11: aload_0
      12: invokevirtual #94                 // Method context:()Lgroovyjarjarantlr/BlockContext;
      15: aload_1
      16: invokevirtual #99                 // Method groovyjarjarantlr/BlockContext.addAlternativeElement:(Lgroovyjarjarantlr/AlternativeElement;)V
      19: return

  public void beginAlt(boolean);
    Code:
       0: aload_0
       1: iload_1
       2: invokespecial #103                // Method groovyjarjarantlr/DefineGrammarSymbols.beginAlt:(Z)V
       5: new           #105                // class groovyjarjarantlr/Alternative
       8: dup
       9: invokespecial #106                // Method groovyjarjarantlr/Alternative."<init>":()V
      12: astore_2
      13: aload_2
      14: iload_1
      15: invokevirtual #109                // Method groovyjarjarantlr/Alternative.setAutoGen:(Z)V
      18: aload_0
      19: invokevirtual #94                 // Method context:()Lgroovyjarjarantlr/BlockContext;
      22: getfield      #113                // Field groovyjarjarantlr/BlockContext.block:Lgroovyjarjarantlr/AlternativeBlock;
      25: aload_2
      26: invokevirtual #119                // Method groovyjarjarantlr/AlternativeBlock.addAlternative:(Lgroovyjarjarantlr/Alternative;)V
      29: return

  public void beginChildList();
    Code:
       0: aload_0
       1: invokespecial #122                // Method groovyjarjarantlr/DefineGrammarSymbols.beginChildList:()V
       4: aload_0
       5: invokevirtual #94                 // Method context:()Lgroovyjarjarantlr/BlockContext;
       8: getfield      #113                // Field groovyjarjarantlr/BlockContext.block:Lgroovyjarjarantlr/AlternativeBlock;
      11: new           #105                // class groovyjarjarantlr/Alternative
      14: dup
      15: invokespecial #106                // Method groovyjarjarantlr/Alternative."<init>":()V
      18: invokevirtual #119                // Method groovyjarjarantlr/AlternativeBlock.addAlternative:(Lgroovyjarjarantlr/Alternative;)V
      21: return

  public void beginExceptionGroup();
    Code:
       0: aload_0
       1: invokespecial #125                // Method groovyjarjarantlr/DefineGrammarSymbols.beginExceptionGroup:()V
       4: aload_0
       5: invokevirtual #94                 // Method context:()Lgroovyjarjarantlr/BlockContext;
       8: getfield      #113                // Field groovyjarjarantlr/BlockContext.block:Lgroovyjarjarantlr/AlternativeBlock;
      11: instanceof    #81                 // class groovyjarjarantlr/RuleBlock
      14: ifne          26
      17: aload_0
      18: getfield      #53                 // Field tool:Lgroovyjarjarantlr/Tool;
      21: ldc           #127                // String beginExceptionGroup called outside of rule block
      23: invokevirtual #130                // Method groovyjarjarantlr/Tool.panic:(Ljava/lang/String;)V
      26: return

  public void beginExceptionSpec(groovyjarjarantlr.Token);
    Code:
       0: aload_1
       1: ifnull        22
       4: aload_1
       5: aload_1
       6: invokevirtual #137                // Method groovyjarjarantlr/Token.getText:()Ljava/lang/String;
       9: ldc           #139                // String  \n\r\t
      11: invokestatic  #145                // Method groovyjarjarantlr/StringUtils.stripBack:(Ljava/lang/String;Ljava/lang/String;)Ljava/lang/String;
      14: ldc           #139                // String  \n\r\t
      16: invokestatic  #148                // Method groovyjarjarantlr/StringUtils.stripFront:(Ljava/lang/String;Ljava/lang/String;)Ljava/lang/String;
      19: invokevirtual #151                // Method groovyjarjarantlr/Token.setText:(Ljava/lang/String;)V
      22: aload_0
      23: aload_1
      24: invokespecial #153                // Method groovyjarjarantlr/DefineGrammarSymbols.beginExceptionSpec:(Lgroovyjarjarantlr/Token;)V
      27: aload_0
      28: new           #155                // class groovyjarjarantlr/ExceptionSpec
      31: dup
      32: aload_1
      33: invokespecial #157                // Method groovyjarjarantlr/ExceptionSpec."<init>":(Lgroovyjarjarantlr/Token;)V
      36: putfield      #36                 // Field currentExceptionSpec:Lgroovyjarjarantlr/ExceptionSpec;
      39: return

  public void beginSubRule(groovyjarjarantlr.Token, groovyjarjarantlr.Token, boolean);
    Code:
       0: aload_0
       1: aload_1
       2: aload_2
       3: iload_3
       4: invokespecial #161                // Method groovyjarjarantlr/DefineGrammarSymbols.beginSubRule:(Lgroovyjarjarantlr/Token;Lgroovyjarjarantlr/Token;Z)V
       7: aload_0
       8: getfield      #30                 // Field blocks:Lgroovyjarjarantlr/collections/Stack;
      11: new           #96                 // class groovyjarjarantlr/BlockContext
      14: dup
      15: invokespecial #162                // Method groovyjarjarantlr/BlockContext."<init>":()V
      18: invokeinterface #168,  2          // InterfaceMethod groovyjarjarantlr/collections/Stack.push:(Ljava/lang/Object;)V
      23: aload_0
      24: invokevirtual #94                 // Method context:()Lgroovyjarjarantlr/BlockContext;
      27: new           #115                // class groovyjarjarantlr/AlternativeBlock
      30: dup
      31: aload_0
      32: getfield      #43                 // Field grammar:Lgroovyjarjarantlr/Grammar;
      35: aload_2
      36: iload_3
      37: invokespecial #171                // Method groovyjarjarantlr/AlternativeBlock."<init>":(Lgroovyjarjarantlr/Grammar;Lgroovyjarjarantlr/Token;Z)V
      40: putfield      #113                // Field groovyjarjarantlr/BlockContext.block:Lgroovyjarjarantlr/AlternativeBlock;
      43: aload_0
      44: invokevirtual #94                 // Method context:()Lgroovyjarjarantlr/BlockContext;
      47: iconst_0
      48: putfield      #174                // Field groovyjarjarantlr/BlockContext.altNum:I
      51: aload_0
      52: dup
      53: getfield      #32                 // Field nested:I
      56: iconst_1
      57: iadd
      58: putfield      #32                 // Field nested:I
      61: aload_0
      62: invokevirtual #94                 // Method context:()Lgroovyjarjarantlr/BlockContext;
      65: new           #176                // class groovyjarjarantlr/BlockEndElement
      68: dup
      69: aload_0
      70: getfield      #43                 // Field grammar:Lgroovyjarjarantlr/Grammar;
      73: invokespecial #179                // Method groovyjarjarantlr/BlockEndElement."<init>":(Lgroovyjarjarantlr/Grammar;)V
      76: putfield      #183                // Field groovyjarjarantlr/BlockContext.blockEnd:Lgroovyjarjarantlr/BlockEndElement;
      79: aload_0
      80: invokevirtual #94                 // Method context:()Lgroovyjarjarantlr/BlockContext;
      83: getfield      #183                // Field groovyjarjarantlr/BlockContext.blockEnd:Lgroovyjarjarantlr/BlockEndElement;
      86: aload_0
      87: invokevirtual #94                 // Method context:()Lgroovyjarjarantlr/BlockContext;
      90: getfield      #113                // Field groovyjarjarantlr/BlockContext.block:Lgroovyjarjarantlr/AlternativeBlock;
      93: putfield      #184                // Field groovyjarjarantlr/BlockEndElement.block:Lgroovyjarjarantlr/AlternativeBlock;
      96: aload_0
      97: aload_0
      98: invokevirtual #94                 // Method context:()Lgroovyjarjarantlr/BlockContext;
     101: getfield      #113                // Field groovyjarjarantlr/BlockContext.block:Lgroovyjarjarantlr/AlternativeBlock;
     104: aload_1
     105: invokespecial #188                // Method labelElement:(Lgroovyjarjarantlr/AlternativeElement;Lgroovyjarjarantlr/Token;)V
     108: return

  public void beginTree(groovyjarjarantlr.Token) throws groovyjarjarantlr.SemanticException;
    Code:
       0: aload_0
       1: getfield      #43                 // Field grammar:Lgroovyjarjarantlr/Grammar;
       4: instanceof    #193                // class groovyjarjarantlr/TreeWalkerGrammar
       7: ifne          44
      10: aload_0
      11: getfield      #53                 // Field tool:Lgroovyjarjarantlr/Tool;
      14: ldc           #195                // String Trees only allowed in TreeParser
      16: aload_0
      17: getfield      #43                 // Field grammar:Lgroovyjarjarantlr/Grammar;
      20: invokevirtual #198                // Method groovyjarjarantlr/Grammar.getFilename:()Ljava/lang/String;
      23: aload_1
      24: invokevirtual #202                // Method groovyjarjarantlr/Token.getLine:()I
      27: aload_1
      28: invokevirtual #205                // Method groovyjarjarantlr/Token.getColumn:()I
      31: invokevirtual #208                // Method groovyjarjarantlr/Tool.error:(Ljava/lang/String;Ljava/lang/String;II)V
      34: new           #191                // class groovyjarjarantlr/SemanticException
      37: dup
      38: ldc           #195                // String Trees only allowed in TreeParser
      40: invokespecial #210                // Method groovyjarjarantlr/SemanticException."<init>":(Ljava/lang/String;)V
      43: athrow
      44: aload_0
      45: aload_1
      46: invokespecial #212                // Method groovyjarjarantlr/DefineGrammarSymbols.beginTree:(Lgroovyjarjarantlr/Token;)V
      49: aload_0
      50: getfield      #30                 // Field blocks:Lgroovyjarjarantlr/collections/Stack;
      53: new           #214                // class groovyjarjarantlr/TreeBlockContext
      56: dup
      57: invokespecial #215                // Method groovyjarjarantlr/TreeBlockContext."<init>":()V
      60: invokeinterface #168,  2          // InterfaceMethod groovyjarjarantlr/collections/Stack.push:(Ljava/lang/Object;)V
      65: aload_0
      66: invokevirtual #94                 // Method context:()Lgroovyjarjarantlr/BlockContext;
      69: new           #217                // class groovyjarjarantlr/TreeElement
      72: dup
      73: aload_0
      74: getfield      #43                 // Field grammar:Lgroovyjarjarantlr/Grammar;
      77: aload_1
      78: invokespecial #220                // Method groovyjarjarantlr/TreeElement."<init>":(Lgroovyjarjarantlr/Grammar;Lgroovyjarjarantlr/Token;)V
      81: putfield      #113                // Field groovyjarjarantlr/BlockContext.block:Lgroovyjarjarantlr/AlternativeBlock;
      84: aload_0
      85: invokevirtual #94                 // Method context:()Lgroovyjarjarantlr/BlockContext;
      88: iconst_0
      89: putfield      #174                // Field groovyjarjarantlr/BlockContext.altNum:I
      92: return

  public groovyjarjarantlr.BlockContext context();
    Code:
       0: aload_0
       1: getfield      #30                 // Field blocks:Lgroovyjarjarantlr/collections/Stack;
       4: invokeinterface #223,  1          // InterfaceMethod groovyjarjarantlr/collections/Stack.height:()I
       9: ifne          14
      12: aconst_null
      13: areturn
      14: aload_0
      15: getfield      #30                 // Field blocks:Lgroovyjarjarantlr/collections/Stack;
      18: invokeinterface #227,  1          // InterfaceMethod groovyjarjarantlr/collections/Stack.top:()Ljava/lang/Object;
      23: checkcast     #96                 // class groovyjarjarantlr/BlockContext
      26: areturn

  public static groovyjarjarantlr.RuleBlock createNextTokenRule(groovyjarjarantlr.Grammar, groovyjarjarantlr.collections.impl.Vector, java.lang.String);
    Code:
       0: new           #81                 // class groovyjarjarantlr/RuleBlock
       3: dup
       4: aload_0
       5: aload_2
       6: invokespecial #232                // Method groovyjarjarantlr/RuleBlock."<init>":(Lgroovyjarjarantlr/Grammar;Ljava/lang/String;)V
       9: astore_3
      10: aload_3
      11: aload_0
      12: invokevirtual #236                // Method groovyjarjarantlr/Grammar.getDefaultErrorHandler:()Z
      15: invokevirtual #239                // Method groovyjarjarantlr/RuleBlock.setDefaultErrorHandler:(Z)V
      18: new           #241                // class groovyjarjarantlr/RuleEndElement
      21: dup
      22: aload_0
      23: invokespecial #242                // Method groovyjarjarantlr/RuleEndElement."<init>":(Lgroovyjarjarantlr/Grammar;)V
      26: astore        4
      28: aload_3
      29: aload         4
      31: invokevirtual #246                // Method groovyjarjarantlr/RuleBlock.setEndElement:(Lgroovyjarjarantlr/RuleEndElement;)V
      34: aload         4
      36: aload_3
      37: putfield      #247                // Field groovyjarjarantlr/RuleEndElement.block:Lgroovyjarjarantlr/AlternativeBlock;
      40: iconst_0
      41: istore        5
      43: iload         5
      45: aload_1
      46: invokevirtual #252                // Method groovyjarjarantlr/collections/impl/Vector.size:()I
      49: if_icmpge     275
      52: aload_1
      53: iload         5
      55: invokevirtual #256                // Method groovyjarjarantlr/collections/impl/Vector.elementAt:(I)Ljava/lang/Object;
      58: checkcast     #258                // class groovyjarjarantlr/RuleSymbol
      61: astore        6
      63: aload         6
      65: invokevirtual #261                // Method groovyjarjarantlr/RuleSymbol.isDefined:()Z
      68: ifne          115
      71: aload_0
      72: getfield      #264                // Field groovyjarjarantlr/Grammar.antlrTool:Lgroovyjarjarantlr/Tool;
      75: new           #55                 // class java/lang/StringBuffer
      78: dup
      79: invokespecial #56                 // Method java/lang/StringBuffer."<init>":()V
      82: ldc_w         #266                // String Lexer rule
      85: invokevirtual #62                 // Method java/lang/StringBuffer.append:(Ljava/lang/String;)Ljava/lang/StringBuffer;
      88: aload         6
      90: getfield      #269                // Field groovyjarjarantlr/RuleSymbol.id:Ljava/lang/String;
      93: iconst_1
      94: invokevirtual #275                // Method java/lang/String.substring:(I)Ljava/lang/String;
      97: invokevirtual #62                 // Method java/lang/StringBuffer.append:(Ljava/lang/String;)Ljava/lang/StringBuffer;
     100: ldc_w         #277                // String  is not defined
     103: invokevirtual #62                 // Method java/lang/StringBuffer.append:(Ljava/lang/String;)Ljava/lang/StringBuffer;
     106: invokevirtual #67                 // Method java/lang/StringBuffer.toString:()Ljava/lang/String;
     109: invokevirtual #73                 // Method groovyjarjarantlr/Tool.error:(Ljava/lang/String;)V
     112: goto          269
     115: aload         6
     117: getfield      #280                // Field groovyjarjarantlr/RuleSymbol.access:Ljava/lang/String;
     120: ldc_w         #282                // String public
     123: invokevirtual #286                // Method java/lang/String.equals:(Ljava/lang/Object;)Z
     126: ifeq          269
     129: new           #105                // class groovyjarjarantlr/Alternative
     132: dup
     133: invokespecial #106                // Method groovyjarjarantlr/Alternative."<init>":()V
     136: astore        7
     138: aload         6
     140: invokevirtual #290                // Method groovyjarjarantlr/RuleSymbol.getBlock:()Lgroovyjarjarantlr/RuleBlock;
     143: astore        8
     145: aload         8
     147: invokevirtual #294                // Method groovyjarjarantlr/RuleBlock.getAlternatives:()Lgroovyjarjarantlr/collections/impl/Vector;
     150: astore        9
     152: aload         9
     154: ifnull        195
     157: aload         9
     159: invokevirtual #252                // Method groovyjarjarantlr/collections/impl/Vector.size:()I
     162: iconst_1
     163: if_icmpne     195
     166: aload         9
     168: iconst_0
     169: invokevirtual #256                // Method groovyjarjarantlr/collections/impl/Vector.elementAt:(I)Ljava/lang/Object;
     172: checkcast     #105                // class groovyjarjarantlr/Alternative
     175: astore        10
     177: aload         10
     179: getfield      #297                // Field groovyjarjarantlr/Alternative.semPred:Ljava/lang/String;
     182: ifnull        195
     185: aload         7
     187: aload         10
     189: getfield      #297                // Field groovyjarjarantlr/Alternative.semPred:Ljava/lang/String;
     192: putfield      #297                // Field groovyjarjarantlr/Alternative.semPred:Ljava/lang/String;
     195: new           #299                // class groovyjarjarantlr/RuleRefElement
     198: dup
     199: aload_0
     200: new           #301                // class groovyjarjarantlr/CommonToken
     203: dup
     204: bipush        41
     206: aload         6
     208: invokevirtual #304                // Method groovyjarjarantlr/RuleSymbol.getId:()Ljava/lang/String;
     211: invokespecial #307                // Method groovyjarjarantlr/CommonToken."<init>":(ILjava/lang/String;)V
     214: iconst_1
     215: invokespecial #310                // Method groovyjarjarantlr/RuleRefElement."<init>":(Lgroovyjarjarantlr/Grammar;Lgroovyjarjarantlr/Token;I)V
     218: astore        10
     220: aload         10
     222: ldc_w         #312                // String theRetToken
     225: invokevirtual #315                // Method groovyjarjarantlr/RuleRefElement.setLabel:(Ljava/lang/String;)V
     228: aload         10
     230: ldc_w         #317                // String nextToken
     233: putfield      #318                // Field groovyjarjarantlr/RuleRefElement.enclosingRuleName:Ljava/lang/String;
     236: aload         10
     238: aload         4
     240: putfield      #322                // Field groovyjarjarantlr/RuleRefElement.next:Lgroovyjarjarantlr/AlternativeElement;
     243: aload         7
     245: aload         10
     247: invokevirtual #325                // Method groovyjarjarantlr/Alternative.addElement:(Lgroovyjarjarantlr/AlternativeElement;)V
     250: aload         7
     252: iconst_1
     253: invokevirtual #109                // Method groovyjarjarantlr/Alternative.setAutoGen:(Z)V
     256: aload_3
     257: aload         7
     259: invokevirtual #326                // Method groovyjarjarantlr/RuleBlock.addAlternative:(Lgroovyjarjarantlr/Alternative;)V
     262: aload         6
     264: aload         10
     266: invokevirtual #330                // Method groovyjarjarantlr/RuleSymbol.addReference:(Lgroovyjarjarantlr/RuleRefElement;)V
     269: iinc          5, 1
     272: goto          43
     275: aload_3
     276: iconst_1
     277: invokevirtual #331                // Method groovyjarjarantlr/RuleBlock.setAutoGen:(Z)V
     280: aload_3
     281: invokevirtual #334                // Method groovyjarjarantlr/RuleBlock.prepareForAnalysis:()V
     284: aload_3
     285: areturn

  private groovyjarjarantlr.AlternativeBlock createOptionalRuleRef(java.lang.String, groovyjarjarantlr.Token);
    Code:
       0: new           #115                // class groovyjarjarantlr/AlternativeBlock
       3: dup
       4: aload_0
       5: getfield      #43                 // Field grammar:Lgroovyjarjarantlr/Grammar;
       8: aload_2
       9: iconst_0
      10: invokespecial #171                // Method groovyjarjarantlr/AlternativeBlock."<init>":(Lgroovyjarjarantlr/Grammar;Lgroovyjarjarantlr/Token;Z)V
      13: astore_3
      14: aload_1
      15: invokestatic  #342                // Method groovyjarjarantlr/CodeGenerator.encodeLexerRuleName:(Ljava/lang/String;)Ljava/lang/String;
      18: astore        4
      20: aload_0
      21: getfield      #43                 // Field grammar:Lgroovyjarjarantlr/Grammar;
      24: aload         4
      26: invokevirtual #345                // Method groovyjarjarantlr/Grammar.isDefined:(Ljava/lang/String;)Z
      29: ifne          48
      32: aload_0
      33: getfield      #43                 // Field grammar:Lgroovyjarjarantlr/Grammar;
      36: new           #258                // class groovyjarjarantlr/RuleSymbol
      39: dup
      40: aload         4
      42: invokespecial #346                // Method groovyjarjarantlr/RuleSymbol."<init>":(Ljava/lang/String;)V
      45: invokevirtual #350                // Method groovyjarjarantlr/Grammar.define:(Lgroovyjarjarantlr/RuleSymbol;)V
      48: new           #301                // class groovyjarjarantlr/CommonToken
      51: dup
      52: bipush        24
      54: aload_1
      55: invokespecial #307                // Method groovyjarjarantlr/CommonToken."<init>":(ILjava/lang/String;)V
      58: astore        5
      60: aload         5
      62: aload_2
      63: invokevirtual #202                // Method groovyjarjarantlr/Token.getLine:()I
      66: invokevirtual #354                // Method groovyjarjarantlr/Token.setLine:(I)V
      69: aload         5
      71: aload_2
      72: invokevirtual #205                // Method groovyjarjarantlr/Token.getColumn:()I
      75: invokevirtual #354                // Method groovyjarjarantlr/Token.setLine:(I)V
      78: new           #299                // class groovyjarjarantlr/RuleRefElement
      81: dup
      82: aload_0
      83: getfield      #43                 // Field grammar:Lgroovyjarjarantlr/Grammar;
      86: aload         5
      88: iconst_1
      89: invokespecial #310                // Method groovyjarjarantlr/RuleRefElement."<init>":(Lgroovyjarjarantlr/Grammar;Lgroovyjarjarantlr/Token;I)V
      92: astore        6
      94: aload         6
      96: aload_0
      97: getfield      #79                 // Field ruleBlock:Lgroovyjarjarantlr/RuleBlock;
     100: getfield      #85                 // Field groovyjarjarantlr/RuleBlock.ruleName:Ljava/lang/String;
     103: putfield      #318                // Field groovyjarjarantlr/RuleRefElement.enclosingRuleName:Ljava/lang/String;
     106: new           #176                // class groovyjarjarantlr/BlockEndElement
     109: dup
     110: aload_0
     111: getfield      #43                 // Field grammar:Lgroovyjarjarantlr/Grammar;
     114: invokespecial #179                // Method groovyjarjarantlr/BlockEndElement."<init>":(Lgroovyjarjarantlr/Grammar;)V
     117: astore        7
     119: aload         7
     121: aload_3
     122: putfield      #184                // Field groovyjarjarantlr/BlockEndElement.block:Lgroovyjarjarantlr/AlternativeBlock;
     125: new           #105                // class groovyjarjarantlr/Alternative
     128: dup
     129: aload         6
     131: invokespecial #356                // Method groovyjarjarantlr/Alternative."<init>":(Lgroovyjarjarantlr/AlternativeElement;)V
     134: astore        8
     136: aload         8
     138: aload         7
     140: invokevirtual #325                // Method groovyjarjarantlr/Alternative.addElement:(Lgroovyjarjarantlr/AlternativeElement;)V
     143: aload_3
     144: aload         8
     146: invokevirtual #119                // Method groovyjarjarantlr/AlternativeBlock.addAlternative:(Lgroovyjarjarantlr/Alternative;)V
     149: new           #105                // class groovyjarjarantlr/Alternative
     152: dup
     153: invokespecial #106                // Method groovyjarjarantlr/Alternative."<init>":()V
     156: astore        9
     158: aload         9
     160: aload         7
     162: invokevirtual #325                // Method groovyjarjarantlr/Alternative.addElement:(Lgroovyjarjarantlr/AlternativeElement;)V
     165: aload_3
     166: aload         9
     168: invokevirtual #119                // Method groovyjarjarantlr/AlternativeBlock.addAlternative:(Lgroovyjarjarantlr/Alternative;)V
     171: aload_3
     172: invokevirtual #357                // Method groovyjarjarantlr/AlternativeBlock.prepareForAnalysis:()V
     175: aload_3
     176: areturn

  public void defineRuleName(groovyjarjarantlr.Token, java.lang.String, boolean, java.lang.String) throws groovyjarjarantlr.SemanticException;
    Code:
       0: aload_1
       1: getfield      #362                // Field groovyjarjarantlr/Token.type:I
       4: bipush        24
       6: if_icmpne     84
       9: aload_0
      10: getfield      #43                 // Field grammar:Lgroovyjarjarantlr/Grammar;
      13: instanceof    #364                // class groovyjarjarantlr/LexerGrammar
      16: ifne          156
      19: aload_0
      20: getfield      #53                 // Field tool:Lgroovyjarjarantlr/Tool;
      23: new           #55                 // class java/lang/StringBuffer
      26: dup
      27: invokespecial #56                 // Method java/lang/StringBuffer."<init>":()V
      30: ldc_w         #366                // String Lexical rule
      33: invokevirtual #62                 // Method java/lang/StringBuffer.append:(Ljava/lang/String;)Ljava/lang/StringBuffer;
      36: aload_1
      37: invokevirtual #137                // Method groovyjarjarantlr/Token.getText:()Ljava/lang/String;
      40: invokevirtual #62                 // Method java/lang/StringBuffer.append:(Ljava/lang/String;)Ljava/lang/StringBuffer;
      43: ldc_w         #368                // String  defined outside of lexer
      46: invokevirtual #62                 // Method java/lang/StringBuffer.append:(Ljava/lang/String;)Ljava/lang/StringBuffer;
      49: invokevirtual #67                 // Method java/lang/StringBuffer.toString:()Ljava/lang/String;
      52: aload_0
      53: getfield      #43                 // Field grammar:Lgroovyjarjarantlr/Grammar;
      56: invokevirtual #198                // Method groovyjarjarantlr/Grammar.getFilename:()Ljava/lang/String;
      59: aload_1
      60: invokevirtual #202                // Method groovyjarjarantlr/Token.getLine:()I
      63: aload_1
      64: invokevirtual #205                // Method groovyjarjarantlr/Token.getColumn:()I
      67: invokevirtual #208                // Method groovyjarjarantlr/Tool.error:(Ljava/lang/String;Ljava/lang/String;II)V
      70: aload_1
      71: aload_1
      72: invokevirtual #137                // Method groovyjarjarantlr/Token.getText:()Ljava/lang/String;
      75: invokevirtual #371                // Method java/lang/String.toLowerCase:()Ljava/lang/String;
      78: invokevirtual #151                // Method groovyjarjarantlr/Token.setText:(Ljava/lang/String;)V
      81: goto          156
      84: aload_0
      85: getfield      #43                 // Field grammar:Lgroovyjarjarantlr/Grammar;
      88: instanceof    #364                // class groovyjarjarantlr/LexerGrammar
      91: ifeq          156
      94: aload_0
      95: getfield      #53                 // Field tool:Lgroovyjarjarantlr/Tool;
      98: new           #55                 // class java/lang/StringBuffer
     101: dup
     102: invokespecial #56                 // Method java/lang/StringBuffer."<init>":()V
     105: ldc_w         #373                // String Lexical rule names must be upper case, \'
     108: invokevirtual #62                 // Method java/lang/StringBuffer.append:(Ljava/lang/String;)Ljava/lang/StringBuffer;
     111: aload_1
     112: invokevirtual #137                // Method groovyjarjarantlr/Token.getText:()Ljava/lang/String;
     115: invokevirtual #62                 // Method java/lang/StringBuffer.append:(Ljava/lang/String;)Ljava/lang/StringBuffer;
     118: ldc_w         #375                // String \' is not
     121: invokevirtual #62                 // Method java/lang/StringBuffer.append:(Ljava/lang/String;)Ljava/lang/StringBuffer;
     124: invokevirtual #67                 // Method java/lang/StringBuffer.toString:()Ljava/lang/String;
     127: aload_0
     128: getfield      #43                 // Field grammar:Lgroovyjarjarantlr/Grammar;
     131: invokevirtual #198                // Method groovyjarjarantlr/Grammar.getFilename:()Ljava/lang/String;
     134: aload_1
     135: invokevirtual #202                // Method groovyjarjarantlr/Token.getLine:()I
     138: aload_1
     139: invokevirtual #205                // Method groovyjarjarantlr/Token.getColumn:()I
     142: invokevirtual #208                // Method groovyjarjarantlr/Tool.error:(Ljava/lang/String;Ljava/lang/String;II)V
     145: aload_1
     146: aload_1
     147: invokevirtual #137                // Method groovyjarjarantlr/Token.getText:()Ljava/lang/String;
     150: invokevirtual #378                // Method java/lang/String.toUpperCase:()Ljava/lang/String;
     153: invokevirtual #151                // Method groovyjarjarantlr/Token.setText:(Ljava/lang/String;)V
     156: aload_0
     157: aload_1
     158: aload_2
     159: iload_3
     160: aload         4
     162: invokespecial #380                // Method groovyjarjarantlr/DefineGrammarSymbols.defineRuleName:(Lgroovyjarjarantlr/Token;Ljava/lang/String;ZLjava/lang/String;)V
     165: aload_1
     166: invokevirtual #137                // Method groovyjarjarantlr/Token.getText:()Ljava/lang/String;
     169: astore        5
     171: aload_1
     172: getfield      #362                // Field groovyjarjarantlr/Token.type:I
     175: bipush        24
     177: if_icmpne     187
     180: aload         5
     182: invokestatic  #342                // Method groovyjarjarantlr/CodeGenerator.encodeLexerRuleName:(Ljava/lang/String;)Ljava/lang/String;
     185: astore        5
     187: aload_0
     188: getfield      #43                 // Field grammar:Lgroovyjarjarantlr/Grammar;
     191: aload         5
     193: invokevirtual #384                // Method groovyjarjarantlr/Grammar.getSymbol:(Ljava/lang/String;)Lgroovyjarjarantlr/GrammarSymbol;
     196: checkcast     #258                // class groovyjarjarantlr/RuleSymbol
     199: astore        6
     201: new           #81                 // class groovyjarjarantlr/RuleBlock
     204: dup
     205: aload_0
     206: getfield      #43                 // Field grammar:Lgroovyjarjarantlr/Grammar;
     209: aload_1
     210: invokevirtual #137                // Method groovyjarjarantlr/Token.getText:()Ljava/lang/String;
     213: aload_1
     214: invokevirtual #202                // Method groovyjarjarantlr/Token.getLine:()I
     217: iload_3
     218: invokespecial #387                // Method groovyjarjarantlr/RuleBlock."<init>":(Lgroovyjarjarantlr/Grammar;Ljava/lang/String;IZ)V
     221: astore        7
     223: aload         7
     225: aload_0
     226: getfield      #43                 // Field grammar:Lgroovyjarjarantlr/Grammar;
     229: invokevirtual #236                // Method groovyjarjarantlr/Grammar.getDefaultErrorHandler:()Z
     232: invokevirtual #239                // Method groovyjarjarantlr/RuleBlock.setDefaultErrorHandler:(Z)V
     235: aload_0
     236: aload         7
     238: putfield      #79                 // Field ruleBlock:Lgroovyjarjarantlr/RuleBlock;
     241: aload_0
     242: getfield      #30                 // Field blocks:Lgroovyjarjarantlr/collections/Stack;
     245: new           #96                 // class groovyjarjarantlr/BlockContext
     248: dup
     249: invokespecial #162                // Method groovyjarjarantlr/BlockContext."<init>":()V
     252: invokeinterface #168,  2          // InterfaceMethod groovyjarjarantlr/collections/Stack.push:(Ljava/lang/Object;)V
     257: aload_0
     258: invokevirtual #94                 // Method context:()Lgroovyjarjarantlr/BlockContext;
     261: aload         7
     263: putfield      #113                // Field groovyjarjarantlr/BlockContext.block:Lgroovyjarjarantlr/AlternativeBlock;
     266: aload         6
     268: aload         7
     270: invokevirtual #391                // Method groovyjarjarantlr/RuleSymbol.setBlock:(Lgroovyjarjarantlr/RuleBlock;)V
     273: aload_0
     274: new           #241                // class groovyjarjarantlr/RuleEndElement
     277: dup
     278: aload_0
     279: getfield      #43                 // Field grammar:Lgroovyjarjarantlr/Grammar;
     282: invokespecial #242                // Method groovyjarjarantlr/RuleEndElement."<init>":(Lgroovyjarjarantlr/Grammar;)V
     285: putfield      #393                // Field ruleEnd:Lgroovyjarjarantlr/RuleEndElement;
     288: aload         7
     290: aload_0
     291: getfield      #393                // Field ruleEnd:Lgroovyjarjarantlr/RuleEndElement;
     294: invokevirtual #246                // Method groovyjarjarantlr/RuleBlock.setEndElement:(Lgroovyjarjarantlr/RuleEndElement;)V
     297: aload_0
     298: iconst_0
     299: putfield      #32                 // Field nested:I
     302: return

  public void endAlt();
    Code:
       0: aload_0
       1: invokespecial #396                // Method groovyjarjarantlr/DefineGrammarSymbols.endAlt:()V
       4: aload_0
       5: getfield      #32                 // Field nested:I
       8: ifne          22
      11: aload_0
      12: aload_0
      13: getfield      #393                // Field ruleEnd:Lgroovyjarjarantlr/RuleEndElement;
      16: invokevirtual #398                // Method addElementToCurrentAlt:(Lgroovyjarjarantlr/AlternativeElement;)V
      19: goto          33
      22: aload_0
      23: aload_0
      24: invokevirtual #94                 // Method context:()Lgroovyjarjarantlr/BlockContext;
      27: getfield      #183                // Field groovyjarjarantlr/BlockContext.blockEnd:Lgroovyjarjarantlr/BlockEndElement;
      30: invokevirtual #398                // Method addElementToCurrentAlt:(Lgroovyjarjarantlr/AlternativeElement;)V
      33: aload_0
      34: invokevirtual #94                 // Method context:()Lgroovyjarjarantlr/BlockContext;
      37: dup
      38: getfield      #174                // Field groovyjarjarantlr/BlockContext.altNum:I
      41: iconst_1
      42: iadd
      43: putfield      #174                // Field groovyjarjarantlr/BlockContext.altNum:I
      46: return

  public void endChildList();
    Code:
       0: aload_0
       1: invokespecial #401                // Method groovyjarjarantlr/DefineGrammarSymbols.endChildList:()V
       4: new           #176                // class groovyjarjarantlr/BlockEndElement
       7: dup
       8: aload_0
       9: getfield      #43                 // Field grammar:Lgroovyjarjarantlr/Grammar;
      12: invokespecial #179                // Method groovyjarjarantlr/BlockEndElement."<init>":(Lgroovyjarjarantlr/Grammar;)V
      15: astore_1
      16: aload_1
      17: aload_0
      18: invokevirtual #94                 // Method context:()Lgroovyjarjarantlr/BlockContext;
      21: getfield      #113                // Field groovyjarjarantlr/BlockContext.block:Lgroovyjarjarantlr/AlternativeBlock;
      24: putfield      #184                // Field groovyjarjarantlr/BlockEndElement.block:Lgroovyjarjarantlr/AlternativeBlock;
      27: aload_0
      28: aload_1
      29: invokevirtual #398                // Method addElementToCurrentAlt:(Lgroovyjarjarantlr/AlternativeElement;)V
      32: return

  public void endExceptionGroup();
    Code:
       0: aload_0
       1: invokespecial #404                // Method groovyjarjarantlr/DefineGrammarSymbols.endExceptionGroup:()V
       4: return

  public void endExceptionSpec();
    Code:
       0: aload_0
       1: invokespecial #407                // Method groovyjarjarantlr/DefineGrammarSymbols.endExceptionSpec:()V
       4: aload_0
       5: getfield      #36                 // Field currentExceptionSpec:Lgroovyjarjarantlr/ExceptionSpec;
       8: ifnonnull     21
      11: aload_0
      12: getfield      #53                 // Field tool:Lgroovyjarjarantlr/Tool;
      15: ldc_w         #409                // String exception processing internal error -- no active exception spec
      18: invokevirtual #130                // Method groovyjarjarantlr/Tool.panic:(Ljava/lang/String;)V
      21: aload_0
      22: invokevirtual #94                 // Method context:()Lgroovyjarjarantlr/BlockContext;
      25: getfield      #113                // Field groovyjarjarantlr/BlockContext.block:Lgroovyjarjarantlr/AlternativeBlock;
      28: instanceof    #81                 // class groovyjarjarantlr/RuleBlock
      31: ifeq          54
      34: aload_0
      35: invokevirtual #94                 // Method context:()Lgroovyjarjarantlr/BlockContext;
      38: getfield      #113                // Field groovyjarjarantlr/BlockContext.block:Lgroovyjarjarantlr/AlternativeBlock;
      41: checkcast     #81                 // class groovyjarjarantlr/RuleBlock
      44: aload_0
      45: getfield      #36                 // Field currentExceptionSpec:Lgroovyjarjarantlr/ExceptionSpec;
      48: invokevirtual #413                // Method groovyjarjarantlr/RuleBlock.addExceptionSpec:(Lgroovyjarjarantlr/ExceptionSpec;)V
      51: goto          121
      54: aload_0
      55: invokevirtual #94                 // Method context:()Lgroovyjarjarantlr/BlockContext;
      58: invokevirtual #417                // Method groovyjarjarantlr/BlockContext.currentAlt:()Lgroovyjarjarantlr/Alternative;
      61: getfield      #420                // Field groovyjarjarantlr/Alternative.exceptionSpec:Lgroovyjarjarantlr/ExceptionSpec;
      64: ifnull        107
      67: aload_0
      68: getfield      #53                 // Field tool:Lgroovyjarjarantlr/Tool;
      71: ldc_w         #422                // String Alternative already has an exception specification
      74: aload_0
      75: getfield      #43                 // Field grammar:Lgroovyjarjarantlr/Grammar;
      78: invokevirtual #198                // Method groovyjarjarantlr/Grammar.getFilename:()Ljava/lang/String;
      81: aload_0
      82: invokevirtual #94                 // Method context:()Lgroovyjarjarantlr/BlockContext;
      85: getfield      #113                // Field groovyjarjarantlr/BlockContext.block:Lgroovyjarjarantlr/AlternativeBlock;
      88: invokevirtual #423                // Method groovyjarjarantlr/AlternativeBlock.getLine:()I
      91: aload_0
      92: invokevirtual #94                 // Method context:()Lgroovyjarjarantlr/BlockContext;
      95: getfield      #113                // Field groovyjarjarantlr/BlockContext.block:Lgroovyjarjarantlr/AlternativeBlock;
      98: invokevirtual #424                // Method groovyjarjarantlr/AlternativeBlock.getColumn:()I
     101: invokevirtual #208                // Method groovyjarjarantlr/Tool.error:(Ljava/lang/String;Ljava/lang/String;II)V
     104: goto          121
     107: aload_0
     108: invokevirtual #94                 // Method context:()Lgroovyjarjarantlr/BlockContext;
     111: invokevirtual #417                // Method groovyjarjarantlr/BlockContext.currentAlt:()Lgroovyjarjarantlr/Alternative;
     114: aload_0
     115: getfield      #36                 // Field currentExceptionSpec:Lgroovyjarjarantlr/ExceptionSpec;
     118: putfield      #420                // Field groovyjarjarantlr/Alternative.exceptionSpec:Lgroovyjarjarantlr/ExceptionSpec;
     121: aload_0
     122: aconst_null
     123: putfield      #36                 // Field currentExceptionSpec:Lgroovyjarjarantlr/ExceptionSpec;
     126: return

  public void endGrammar();
    Code:
       0: aload_0
       1: getfield      #34                 // Field grammarError:Z
       4: ifeq          14
       7: aload_0
       8: invokevirtual #426                // Method abortGrammar:()V
      11: goto          18
      14: aload_0
      15: invokespecial #428                // Method groovyjarjarantlr/DefineGrammarSymbols.endGrammar:()V
      18: return

  public void endRule(java.lang.String);
    Code:
       0: aload_0
       1: aload_1
       2: invokespecial #431                // Method groovyjarjarantlr/DefineGrammarSymbols.endRule:(Ljava/lang/String;)V
       5: aload_0
       6: getfield      #30                 // Field blocks:Lgroovyjarjarantlr/collections/Stack;
       9: invokeinterface #434,  1          // InterfaceMethod groovyjarjarantlr/collections/Stack.pop:()Ljava/lang/Object;
      14: checkcast     #96                 // class groovyjarjarantlr/BlockContext
      17: astore_2
      18: aload_0
      19: getfield      #393                // Field ruleEnd:Lgroovyjarjarantlr/RuleEndElement;
      22: aload_2
      23: getfield      #113                // Field groovyjarjarantlr/BlockContext.block:Lgroovyjarjarantlr/AlternativeBlock;
      26: putfield      #247                // Field groovyjarjarantlr/RuleEndElement.block:Lgroovyjarjarantlr/AlternativeBlock;
      29: aload_0
      30: getfield      #393                // Field ruleEnd:Lgroovyjarjarantlr/RuleEndElement;
      33: getfield      #247                // Field groovyjarjarantlr/RuleEndElement.block:Lgroovyjarjarantlr/AlternativeBlock;
      36: invokevirtual #357                // Method groovyjarjarantlr/AlternativeBlock.prepareForAnalysis:()V
      39: return

  public void endSubRule();
    Code:
       0: aload_0
       1: invokespecial #437                // Method groovyjarjarantlr/DefineGrammarSymbols.endSubRule:()V
       4: aload_0
       5: dup
       6: getfield      #32                 // Field nested:I
       9: iconst_1
      10: isub
      11: putfield      #32                 // Field nested:I
      14: aload_0
      15: getfield      #30                 // Field blocks:Lgroovyjarjarantlr/collections/Stack;
      18: invokeinterface #434,  1          // InterfaceMethod groovyjarjarantlr/collections/Stack.pop:()Ljava/lang/Object;
      23: checkcast     #96                 // class groovyjarjarantlr/BlockContext
      26: astore_1
      27: aload_1
      28: getfield      #113                // Field groovyjarjarantlr/BlockContext.block:Lgroovyjarjarantlr/AlternativeBlock;
      31: astore_2
      32: aload_2
      33: getfield      #440                // Field groovyjarjarantlr/AlternativeBlock.not:Z
      36: ifeq          153
      39: aload_2
      40: instanceof    #442                // class groovyjarjarantlr/SynPredBlock
      43: ifne          153
      46: aload_2
      47: instanceof    #444                // class groovyjarjarantlr/ZeroOrMoreBlock
      50: ifne          153
      53: aload_2
      54: instanceof    #446                // class groovyjarjarantlr/OneOrMoreBlock
      57: ifne          153
      60: aload_0
      61: getfield      #450                // Field analyzer:Lgroovyjarjarantlr/LLkAnalyzer;
      64: aload_2
      65: aload_0
      66: getfield      #43                 // Field grammar:Lgroovyjarjarantlr/Grammar;
      69: instanceof    #364                // class groovyjarjarantlr/LexerGrammar
      72: invokevirtual #456                // Method groovyjarjarantlr/LLkAnalyzer.subruleCanBeInverted:(Lgroovyjarjarantlr/AlternativeBlock;Z)Z
      75: ifne          153
      78: ldc_w         #458                // String line.separator
      81: invokestatic  #463                // Method java/lang/System.getProperty:(Ljava/lang/String;)Ljava/lang/String;
      84: astore_3
      85: aload_0
      86: getfield      #53                 // Field tool:Lgroovyjarjarantlr/Tool;
      89: new           #55                 // class java/lang/StringBuffer
      92: dup
      93: invokespecial #56                 // Method java/lang/StringBuffer."<init>":()V
      96: ldc_w         #465                // String This subrule cannot be inverted.  Only subrules of the form:
      99: invokevirtual #62                 // Method java/lang/StringBuffer.append:(Ljava/lang/String;)Ljava/lang/StringBuffer;
     102: aload_3
     103: invokevirtual #62                 // Method java/lang/StringBuffer.append:(Ljava/lang/String;)Ljava/lang/StringBuffer;
     106: ldc_w         #467                // String     (T1|T2|T3...) or
     109: invokevirtual #62                 // Method java/lang/StringBuffer.append:(Ljava/lang/String;)Ljava/lang/StringBuffer;
     112: aload_3
     113: invokevirtual #62                 // Method java/lang/StringBuffer.append:(Ljava/lang/String;)Ljava/lang/StringBuffer;
     116: ldc_w         #469                // String     (\'c1\'|\'c2\'|\'c3\'...)
     119: invokevirtual #62                 // Method java/lang/StringBuffer.append:(Ljava/lang/String;)Ljava/lang/StringBuffer;
     122: aload_3
     123: invokevirtual #62                 // Method java/lang/StringBuffer.append:(Ljava/lang/String;)Ljava/lang/StringBuffer;
     126: ldc_w         #471                // String may be inverted (ranges are also allowed).
     129: invokevirtual #62                 // Method java/lang/StringBuffer.append:(Ljava/lang/String;)Ljava/lang/StringBuffer;
     132: invokevirtual #67                 // Method java/lang/StringBuffer.toString:()Ljava/lang/String;
     135: aload_0
     136: getfield      #43                 // Field grammar:Lgroovyjarjarantlr/Grammar;
     139: invokevirtual #198                // Method groovyjarjarantlr/Grammar.getFilename:()Ljava/lang/String;
     142: aload_2
     143: invokevirtual #423                // Method groovyjarjarantlr/AlternativeBlock.getLine:()I
     146: aload_2
     147: invokevirtual #424                // Method groovyjarjarantlr/AlternativeBlock.getColumn:()I
     150: invokevirtual #208                // Method groovyjarjarantlr/Tool.error:(Ljava/lang/String;Ljava/lang/String;II)V
     153: aload_2
     154: instanceof    #442                // class groovyjarjarantlr/SynPredBlock
     157: ifeq          206
     160: aload_2
     161: checkcast     #442                // class groovyjarjarantlr/SynPredBlock
     164: astore_3
     165: aload_0
     166: invokevirtual #94                 // Method context:()Lgroovyjarjarantlr/BlockContext;
     169: getfield      #113                // Field groovyjarjarantlr/BlockContext.block:Lgroovyjarjarantlr/AlternativeBlock;
     172: iconst_1
     173: putfield      #474                // Field groovyjarjarantlr/AlternativeBlock.hasASynPred:Z
     176: aload_0
     177: invokevirtual #94                 // Method context:()Lgroovyjarjarantlr/BlockContext;
     180: invokevirtual #417                // Method groovyjarjarantlr/BlockContext.currentAlt:()Lgroovyjarjarantlr/Alternative;
     183: aload_3
     184: putfield      #478                // Field groovyjarjarantlr/Alternative.synPred:Lgroovyjarjarantlr/SynPredBlock;
     187: aload_0
     188: getfield      #43                 // Field grammar:Lgroovyjarjarantlr/Grammar;
     191: iconst_1
     192: putfield      #481                // Field groovyjarjarantlr/Grammar.hasSyntacticPredicate:Z
     195: aload_3
     196: aload_0
     197: getfield      #43                 // Field grammar:Lgroovyjarjarantlr/Grammar;
     200: invokevirtual #484                // Method groovyjarjarantlr/SynPredBlock.removeTrackingOfRuleRefs:(Lgroovyjarjarantlr/Grammar;)V
     203: goto          211
     206: aload_0
     207: aload_2
     208: invokevirtual #398                // Method addElementToCurrentAlt:(Lgroovyjarjarantlr/AlternativeElement;)V
     211: aload_1
     212: getfield      #183                // Field groovyjarjarantlr/BlockContext.blockEnd:Lgroovyjarjarantlr/BlockEndElement;
     215: getfield      #184                // Field groovyjarjarantlr/BlockEndElement.block:Lgroovyjarjarantlr/AlternativeBlock;
     218: invokevirtual #357                // Method groovyjarjarantlr/AlternativeBlock.prepareForAnalysis:()V
     221: return

  public void endTree();
    Code:
       0: aload_0
       1: invokespecial #487                // Method groovyjarjarantlr/DefineGrammarSymbols.endTree:()V
       4: aload_0
       5: getfield      #30                 // Field blocks:Lgroovyjarjarantlr/collections/Stack;
       8: invokeinterface #434,  1          // InterfaceMethod groovyjarjarantlr/collections/Stack.pop:()Ljava/lang/Object;
      13: checkcast     #96                 // class groovyjarjarantlr/BlockContext
      16: astore_1
      17: aload_0
      18: aload_1
      19: getfield      #113                // Field groovyjarjarantlr/BlockContext.block:Lgroovyjarjarantlr/AlternativeBlock;
      22: invokevirtual #398                // Method addElementToCurrentAlt:(Lgroovyjarjarantlr/AlternativeElement;)V
      25: return

  public void hasError();
    Code:
       0: aload_0
       1: iconst_1
       2: putfield      #34                 // Field grammarError:Z
       5: return

  private void labelElement(groovyjarjarantlr.AlternativeElement, groovyjarjarantlr.Token);
    Code:
       0: aload_2
       1: ifnull        137
       4: iconst_0
       5: istore_3
       6: iload_3
       7: aload_0
       8: getfield      #79                 // Field ruleBlock:Lgroovyjarjarantlr/RuleBlock;
      11: getfield      #492                // Field groovyjarjarantlr/RuleBlock.labeledElements:Lgroovyjarjarantlr/collections/impl/Vector;
      14: invokevirtual #252                // Method groovyjarjarantlr/collections/impl/Vector.size:()I
      17: if_icmpge     118
      20: aload_0
      21: getfield      #79                 // Field ruleBlock:Lgroovyjarjarantlr/RuleBlock;
      24: getfield      #492                // Field groovyjarjarantlr/RuleBlock.labeledElements:Lgroovyjarjarantlr/collections/impl/Vector;
      27: iload_3
      28: invokevirtual #256                // Method groovyjarjarantlr/collections/impl/Vector.elementAt:(I)Ljava/lang/Object;
      31: checkcast     #87                 // class groovyjarjarantlr/AlternativeElement
      34: astore        4
      36: aload         4
      38: invokevirtual #495                // Method groovyjarjarantlr/AlternativeElement.getLabel:()Ljava/lang/String;
      41: astore        5
      43: aload         5
      45: ifnull        112
      48: aload         5
      50: aload_2
      51: invokevirtual #137                // Method groovyjarjarantlr/Token.getText:()Ljava/lang/String;
      54: invokevirtual #286                // Method java/lang/String.equals:(Ljava/lang/Object;)Z
      57: ifeq          112
      60: aload_0
      61: getfield      #53                 // Field tool:Lgroovyjarjarantlr/Tool;
      64: new           #55                 // class java/lang/StringBuffer
      67: dup
      68: invokespecial #56                 // Method java/lang/StringBuffer."<init>":()V
      71: ldc_w         #497                // String Label \'
      74: invokevirtual #62                 // Method java/lang/StringBuffer.append:(Ljava/lang/String;)Ljava/lang/StringBuffer;
      77: aload_2
      78: invokevirtual #137                // Method groovyjarjarantlr/Token.getText:()Ljava/lang/String;
      81: invokevirtual #62                 // Method java/lang/StringBuffer.append:(Ljava/lang/String;)Ljava/lang/StringBuffer;
      84: ldc_w         #499                // String \' has already been defined
      87: invokevirtual #62                 // Method java/lang/StringBuffer.append:(Ljava/lang/String;)Ljava/lang/StringBuffer;
      90: invokevirtual #67                 // Method java/lang/StringBuffer.toString:()Ljava/lang/String;
      93: aload_0
      94: getfield      #43                 // Field grammar:Lgroovyjarjarantlr/Grammar;
      97: invokevirtual #198                // Method groovyjarjarantlr/Grammar.getFilename:()Ljava/lang/String;
     100: aload_2
     101: invokevirtual #202                // Method groovyjarjarantlr/Token.getLine:()I
     104: aload_2
     105: invokevirtual #205                // Method groovyjarjarantlr/Token.getColumn:()I
     108: invokevirtual #208                // Method groovyjarjarantlr/Tool.error:(Ljava/lang/String;Ljava/lang/String;II)V
     111: return
     112: iinc          3, 1
     115: goto          6
     118: aload_1
     119: aload_2
     120: invokevirtual #137                // Method groovyjarjarantlr/Token.getText:()Ljava/lang/String;
     123: invokevirtual #500                // Method groovyjarjarantlr/AlternativeElement.setLabel:(Ljava/lang/String;)V
     126: aload_0
     127: getfield      #79                 // Field ruleBlock:Lgroovyjarjarantlr/RuleBlock;
     130: getfield      #492                // Field groovyjarjarantlr/RuleBlock.labeledElements:Lgroovyjarjarantlr/collections/impl/Vector;
     133: aload_1
     134: invokevirtual #503                // Method groovyjarjarantlr/collections/impl/Vector.appendElement:(Ljava/lang/Object;)V
     137: return

  public void noAutoGenSubRule();
    Code:
       0: aload_0
       1: invokevirtual #94                 // Method context:()Lgroovyjarjarantlr/BlockContext;
       4: getfield      #113                // Field groovyjarjarantlr/BlockContext.block:Lgroovyjarjarantlr/AlternativeBlock;
       7: iconst_0
       8: invokevirtual #505                // Method groovyjarjarantlr/AlternativeBlock.setAutoGen:(Z)V
      11: return

  public void oneOrMoreSubRule();
    Code:
       0: aload_0
       1: invokevirtual #94                 // Method context:()Lgroovyjarjarantlr/BlockContext;
       4: getfield      #113                // Field groovyjarjarantlr/BlockContext.block:Lgroovyjarjarantlr/AlternativeBlock;
       7: getfield      #440                // Field groovyjarjarantlr/AlternativeBlock.not:Z
      10: ifeq          50
      13: aload_0
      14: getfield      #53                 // Field tool:Lgroovyjarjarantlr/Tool;
      17: ldc_w         #508                // String \'~\' cannot be applied to (...)* subrule
      20: aload_0
      21: getfield      #43                 // Field grammar:Lgroovyjarjarantlr/Grammar;
      24: invokevirtual #198                // Method groovyjarjarantlr/Grammar.getFilename:()Ljava/lang/String;
      27: aload_0
      28: invokevirtual #94                 // Method context:()Lgroovyjarjarantlr/BlockContext;
      31: getfield      #113                // Field groovyjarjarantlr/BlockContext.block:Lgroovyjarjarantlr/AlternativeBlock;
      34: invokevirtual #423                // Method groovyjarjarantlr/AlternativeBlock.getLine:()I
      37: aload_0
      38: invokevirtual #94                 // Method context:()Lgroovyjarjarantlr/BlockContext;
      41: getfield      #113                // Field groovyjarjarantlr/BlockContext.block:Lgroovyjarjarantlr/AlternativeBlock;
      44: invokevirtual #424                // Method groovyjarjarantlr/AlternativeBlock.getColumn:()I
      47: invokevirtual #208                // Method groovyjarjarantlr/Tool.error:(Ljava/lang/String;Ljava/lang/String;II)V
      50: new           #446                // class groovyjarjarantlr/OneOrMoreBlock
      53: dup
      54: aload_0
      55: getfield      #43                 // Field grammar:Lgroovyjarjarantlr/Grammar;
      58: invokespecial #509                // Method groovyjarjarantlr/OneOrMoreBlock."<init>":(Lgroovyjarjarantlr/Grammar;)V
      61: astore_1
      62: aload_1
      63: aload_0
      64: invokevirtual #94                 // Method context:()Lgroovyjarjarantlr/BlockContext;
      67: getfield      #113                // Field groovyjarjarantlr/BlockContext.block:Lgroovyjarjarantlr/AlternativeBlock;
      70: invokestatic  #512                // Method setBlock:(Lgroovyjarjarantlr/AlternativeBlock;Lgroovyjarjarantlr/AlternativeBlock;)V
      73: aload_0
      74: getfield      #30                 // Field blocks:Lgroovyjarjarantlr/collections/Stack;
      77: invokeinterface #434,  1          // InterfaceMethod groovyjarjarantlr/collections/Stack.pop:()Ljava/lang/Object;
      82: checkcast     #96                 // class groovyjarjarantlr/BlockContext
      85: astore_2
      86: aload_0
      87: getfield      #30                 // Field blocks:Lgroovyjarjarantlr/collections/Stack;
      90: new           #96                 // class groovyjarjarantlr/BlockContext
      93: dup
      94: invokespecial #162                // Method groovyjarjarantlr/BlockContext."<init>":()V
      97: invokeinterface #168,  2          // InterfaceMethod groovyjarjarantlr/collections/Stack.push:(Ljava/lang/Object;)V
     102: aload_0
     103: invokevirtual #94                 // Method context:()Lgroovyjarjarantlr/BlockContext;
     106: aload_1
     107: putfield      #113                // Field groovyjarjarantlr/BlockContext.block:Lgroovyjarjarantlr/AlternativeBlock;
     110: aload_0
     111: invokevirtual #94                 // Method context:()Lgroovyjarjarantlr/BlockContext;
     114: aload_2
     115: getfield      #183                // Field groovyjarjarantlr/BlockContext.blockEnd:Lgroovyjarjarantlr/BlockEndElement;
     118: putfield      #183                // Field groovyjarjarantlr/BlockContext.blockEnd:Lgroovyjarjarantlr/BlockEndElement;
     121: aload_0
     122: invokevirtual #94                 // Method context:()Lgroovyjarjarantlr/BlockContext;
     125: getfield      #183                // Field groovyjarjarantlr/BlockContext.blockEnd:Lgroovyjarjarantlr/BlockEndElement;
     128: aload_1
     129: putfield      #184                // Field groovyjarjarantlr/BlockEndElement.block:Lgroovyjarjarantlr/AlternativeBlock;
     132: return

  public void optionalSubRule();
    Code:
       0: aload_0
       1: invokevirtual #94                 // Method context:()Lgroovyjarjarantlr/BlockContext;
       4: getfield      #113                // Field groovyjarjarantlr/BlockContext.block:Lgroovyjarjarantlr/AlternativeBlock;
       7: getfield      #440                // Field groovyjarjarantlr/AlternativeBlock.not:Z
      10: ifeq          50
      13: aload_0
      14: getfield      #53                 // Field tool:Lgroovyjarjarantlr/Tool;
      17: ldc_w         #515                // String \'~\' cannot be applied to (...)? subrule
      20: aload_0
      21: getfield      #43                 // Field grammar:Lgroovyjarjarantlr/Grammar;
      24: invokevirtual #198                // Method groovyjarjarantlr/Grammar.getFilename:()Ljava/lang/String;
      27: aload_0
      28: invokevirtual #94                 // Method context:()Lgroovyjarjarantlr/BlockContext;
      31: getfield      #113                // Field groovyjarjarantlr/BlockContext.block:Lgroovyjarjarantlr/AlternativeBlock;
      34: invokevirtual #423                // Method groovyjarjarantlr/AlternativeBlock.getLine:()I
      37: aload_0
      38: invokevirtual #94                 // Method context:()Lgroovyjarjarantlr/BlockContext;
      41: getfield      #113                // Field groovyjarjarantlr/BlockContext.block:Lgroovyjarjarantlr/AlternativeBlock;
      44: invokevirtual #424                // Method groovyjarjarantlr/AlternativeBlock.getColumn:()I
      47: invokevirtual #208                // Method groovyjarjarantlr/Tool.error:(Ljava/lang/String;Ljava/lang/String;II)V
      50: aload_0
      51: iconst_0
      52: invokevirtual #516                // Method beginAlt:(Z)V
      55: aload_0
      56: invokevirtual #517                // Method endAlt:()V
      59: return

  public void refAction(groovyjarjarantlr.Token);
    Code:
       0: aload_0
       1: aload_1
       2: invokespecial #520                // Method groovyjarjarantlr/DefineGrammarSymbols.refAction:(Lgroovyjarjarantlr/Token;)V
       5: aload_0
       6: invokevirtual #94                 // Method context:()Lgroovyjarjarantlr/BlockContext;
       9: getfield      #113                // Field groovyjarjarantlr/BlockContext.block:Lgroovyjarjarantlr/AlternativeBlock;
      12: iconst_1
      13: putfield      #523                // Field groovyjarjarantlr/AlternativeBlock.hasAnAction:Z
      16: aload_0
      17: new           #525                // class groovyjarjarantlr/ActionElement
      20: dup
      21: aload_0
      22: getfield      #43                 // Field grammar:Lgroovyjarjarantlr/Grammar;
      25: aload_1
      26: invokespecial #526                // Method groovyjarjarantlr/ActionElement."<init>":(Lgroovyjarjarantlr/Grammar;Lgroovyjarjarantlr/Token;)V
      29: invokevirtual #398                // Method addElementToCurrentAlt:(Lgroovyjarjarantlr/AlternativeElement;)V
      32: return

  public void setUserExceptions(java.lang.String);
    Code:
       0: aload_0
       1: invokevirtual #94                 // Method context:()Lgroovyjarjarantlr/BlockContext;
       4: getfield      #113                // Field groovyjarjarantlr/BlockContext.block:Lgroovyjarjarantlr/AlternativeBlock;
       7: checkcast     #81                 // class groovyjarjarantlr/RuleBlock
      10: aload_1
      11: putfield      #530                // Field groovyjarjarantlr/RuleBlock.throwsSpec:Ljava/lang/String;
      14: return

  public void refArgAction(groovyjarjarantlr.Token);
    Code:
       0: aload_0
       1: invokevirtual #94                 // Method context:()Lgroovyjarjarantlr/BlockContext;
       4: getfield      #113                // Field groovyjarjarantlr/BlockContext.block:Lgroovyjarjarantlr/AlternativeBlock;
       7: checkcast     #81                 // class groovyjarjarantlr/RuleBlock
      10: aload_1
      11: invokevirtual #137                // Method groovyjarjarantlr/Token.getText:()Ljava/lang/String;
      14: putfield      #534                // Field groovyjarjarantlr/RuleBlock.argAction:Ljava/lang/String;
      17: return

  public void refCharLiteral(groovyjarjarantlr.Token, groovyjarjarantlr.Token, boolean, int, boolean);
    Code:
       0: aload_0
       1: getfield      #43                 // Field grammar:Lgroovyjarjarantlr/Grammar;
       4: instanceof    #364                // class groovyjarjarantlr/LexerGrammar
       7: ifne          36
      10: aload_0
      11: getfield      #53                 // Field tool:Lgroovyjarjarantlr/Tool;
      14: ldc_w         #538                // String Character literal only valid in lexer
      17: aload_0
      18: getfield      #43                 // Field grammar:Lgroovyjarjarantlr/Grammar;
      21: invokevirtual #198                // Method groovyjarjarantlr/Grammar.getFilename:()Ljava/lang/String;
      24: aload_1
      25: invokevirtual #202                // Method groovyjarjarantlr/Token.getLine:()I
      28: aload_1
      29: invokevirtual #205                // Method groovyjarjarantlr/Token.getColumn:()I
      32: invokevirtual #208                // Method groovyjarjarantlr/Tool.error:(Ljava/lang/String;Ljava/lang/String;II)V
      35: return
      36: aload_0
      37: aload_1
      38: aload_2
      39: iload_3
      40: iload         4
      42: iload         5
      44: invokespecial #540                // Method groovyjarjarantlr/DefineGrammarSymbols.refCharLiteral:(Lgroovyjarjarantlr/Token;Lgroovyjarjarantlr/Token;ZIZ)V
      47: new           #542                // class groovyjarjarantlr/CharLiteralElement
      50: dup
      51: aload_0
      52: getfield      #43                 // Field grammar:Lgroovyjarjarantlr/Grammar;
      55: checkcast     #364                // class groovyjarjarantlr/LexerGrammar
      58: aload_1
      59: iload_3
      60: iload         4
      62: invokespecial #545                // Method groovyjarjarantlr/CharLiteralElement."<init>":(Lgroovyjarjarantlr/LexerGrammar;Lgroovyjarjarantlr/Token;ZI)V
      65: astore        6
      67: aload_0
      68: getfield      #43                 // Field grammar:Lgroovyjarjarantlr/Grammar;
      71: checkcast     #364                // class groovyjarjarantlr/LexerGrammar
      74: getfield      #548                // Field groovyjarjarantlr/LexerGrammar.caseSensitive:Z
      77: ifne          134
      80: aload         6
      82: invokevirtual #551                // Method groovyjarjarantlr/CharLiteralElement.getType:()I
      85: sipush        128
      88: if_icmpge     134
      91: aload         6
      93: invokevirtual #551                // Method groovyjarjarantlr/CharLiteralElement.getType:()I
      96: i2c
      97: invokestatic  #556                // Method java/lang/Character.toLowerCase:(C)C
     100: aload         6
     102: invokevirtual #551                // Method groovyjarjarantlr/CharLiteralElement.getType:()I
     105: i2c
     106: if_icmpeq     134
     109: aload_0
     110: getfield      #53                 // Field tool:Lgroovyjarjarantlr/Tool;
     113: ldc_w         #558                // String Character literal must be lowercase when caseSensitive=false
     116: aload_0
     117: getfield      #43                 // Field grammar:Lgroovyjarjarantlr/Grammar;
     120: invokevirtual #198                // Method groovyjarjarantlr/Grammar.getFilename:()Ljava/lang/String;
     123: aload_1
     124: invokevirtual #202                // Method groovyjarjarantlr/Token.getLine:()I
     127: aload_1
     128: invokevirtual #205                // Method groovyjarjarantlr/Token.getColumn:()I
     131: invokevirtual #561                // Method groovyjarjarantlr/Tool.warning:(Ljava/lang/String;Ljava/lang/String;II)V
     134: aload_0
     135: aload         6
     137: invokevirtual #398                // Method addElementToCurrentAlt:(Lgroovyjarjarantlr/AlternativeElement;)V
     140: aload_0
     141: aload         6
     143: aload_2
     144: invokespecial #188                // Method labelElement:(Lgroovyjarjarantlr/AlternativeElement;Lgroovyjarjarantlr/Token;)V
     147: aload_0
     148: getfield      #79                 // Field ruleBlock:Lgroovyjarjarantlr/RuleBlock;
     151: invokevirtual #564                // Method groovyjarjarantlr/RuleBlock.getIgnoreRule:()Ljava/lang/String;
     154: astore        7
     156: iload         5
     158: ifne          177
     161: aload         7
     163: ifnull        177
     166: aload_0
     167: aload_0
     168: aload         7
     170: aload_1
     171: invokespecial #566                // Method createOptionalRuleRef:(Ljava/lang/String;Lgroovyjarjarantlr/Token;)Lgroovyjarjarantlr/AlternativeBlock;
     174: invokevirtual #398                // Method addElementToCurrentAlt:(Lgroovyjarjarantlr/AlternativeElement;)V
     177: return

  public void refCharRange(groovyjarjarantlr.Token, groovyjarjarantlr.Token, groovyjarjarantlr.Token, int, boolean);
    Code:
       0: aload_0
       1: getfield      #43                 // Field grammar:Lgroovyjarjarantlr/Grammar;
       4: instanceof    #364                // class groovyjarjarantlr/LexerGrammar
       7: ifne          36
      10: aload_0
      11: getfield      #53                 // Field tool:Lgroovyjarjarantlr/Tool;
      14: ldc_w         #570                // String Character range only valid in lexer
      17: aload_0
      18: getfield      #43                 // Field grammar:Lgroovyjarjarantlr/Grammar;
      21: invokevirtual #198                // Method groovyjarjarantlr/Grammar.getFilename:()Ljava/lang/String;
      24: aload_1
      25: invokevirtual #202                // Method groovyjarjarantlr/Token.getLine:()I
      28: aload_1
      29: invokevirtual #205                // Method groovyjarjarantlr/Token.getColumn:()I
      32: invokevirtual #208                // Method groovyjarjarantlr/Tool.error:(Ljava/lang/String;Ljava/lang/String;II)V
      35: return
      36: aload_1
      37: invokevirtual #137                // Method groovyjarjarantlr/Token.getText:()Ljava/lang/String;
      40: invokestatic  #576                // Method groovyjarjarantlr/ANTLRLexer.tokenTypeForCharLiteral:(Ljava/lang/String;)I
      43: istore        6
      45: aload_2
      46: invokevirtual #137                // Method groovyjarjarantlr/Token.getText:()Ljava/lang/String;
      49: invokestatic  #576                // Method groovyjarjarantlr/ANTLRLexer.tokenTypeForCharLiteral:(Ljava/lang/String;)I
      52: istore        7
      54: iload         7
      56: iload         6
      58: if_icmpge     87
      61: aload_0
      62: getfield      #53                 // Field tool:Lgroovyjarjarantlr/Tool;
      65: ldc_w         #578                // String Malformed range.
      68: aload_0
      69: getfield      #43                 // Field grammar:Lgroovyjarjarantlr/Grammar;
      72: invokevirtual #198                // Method groovyjarjarantlr/Grammar.getFilename:()Ljava/lang/String;
      75: aload_1
      76: invokevirtual #202                // Method groovyjarjarantlr/Token.getLine:()I
      79: aload_1
      80: invokevirtual #205                // Method groovyjarjarantlr/Token.getColumn:()I
      83: invokevirtual #208                // Method groovyjarjarantlr/Tool.error:(Ljava/lang/String;Ljava/lang/String;II)V
      86: return
      87: aload_0
      88: getfield      #43                 // Field grammar:Lgroovyjarjarantlr/Grammar;
      91: checkcast     #364                // class groovyjarjarantlr/LexerGrammar
      94: getfield      #548                // Field groovyjarjarantlr/LexerGrammar.caseSensitive:Z
      97: ifne          190
     100: iload         6
     102: sipush        128
     105: if_icmpge     145
     108: iload         6
     110: i2c
     111: invokestatic  #556                // Method java/lang/Character.toLowerCase:(C)C
     114: iload         6
     116: i2c
     117: if_icmpeq     145
     120: aload_0
     121: getfield      #53                 // Field tool:Lgroovyjarjarantlr/Tool;
     124: ldc_w         #558                // String Character literal must be lowercase when caseSensitive=false
     127: aload_0
     128: getfield      #43                 // Field grammar:Lgroovyjarjarantlr/Grammar;
     131: invokevirtual #198                // Method groovyjarjarantlr/Grammar.getFilename:()Ljava/lang/String;
     134: aload_1
     135: invokevirtual #202                // Method groovyjarjarantlr/Token.getLine:()I
     138: aload_1
     139: invokevirtual #205                // Method groovyjarjarantlr/Token.getColumn:()I
     142: invokevirtual #561                // Method groovyjarjarantlr/Tool.warning:(Ljava/lang/String;Ljava/lang/String;II)V
     145: iload         7
     147: sipush        128
     150: if_icmpge     190
     153: iload         7
     155: i2c
     156: invokestatic  #556                // Method java/lang/Character.toLowerCase:(C)C
     159: iload         7
     161: i2c
     162: if_icmpeq     190
     165: aload_0
     166: getfield      #53                 // Field tool:Lgroovyjarjarantlr/Tool;
     169: ldc_w         #558                // String Character literal must be lowercase when caseSensitive=false
     172: aload_0
     173: getfield      #43                 // Field grammar:Lgroovyjarjarantlr/Grammar;
     176: invokevirtual #198                // Method groovyjarjarantlr/Grammar.getFilename:()Ljava/lang/String;
     179: aload_2
     180: invokevirtual #202                // Method groovyjarjarantlr/Token.getLine:()I
     183: aload_2
     184: invokevirtual #205                // Method groovyjarjarantlr/Token.getColumn:()I
     187: invokevirtual #561                // Method groovyjarjarantlr/Tool.warning:(Ljava/lang/String;Ljava/lang/String;II)V
     190: aload_0
     191: aload_1
     192: aload_2
     193: aload_3
     194: iload         4
     196: iload         5
     198: invokespecial #580                // Method groovyjarjarantlr/DefineGrammarSymbols.refCharRange:(Lgroovyjarjarantlr/Token;Lgroovyjarjarantlr/Token;Lgroovyjarjarantlr/Token;IZ)V
     201: new           #582                // class groovyjarjarantlr/CharRangeElement
     204: dup
     205: aload_0
     206: getfield      #43                 // Field grammar:Lgroovyjarjarantlr/Grammar;
     209: checkcast     #364                // class groovyjarjarantlr/LexerGrammar
     212: aload_1
     213: aload_2
     214: iload         4
     216: invokespecial #585                // Method groovyjarjarantlr/CharRangeElement."<init>":(Lgroovyjarjarantlr/LexerGrammar;Lgroovyjarjarantlr/Token;Lgroovyjarjarantlr/Token;I)V
     219: astore        8
     221: aload_0
     222: aload         8
     224: invokevirtual #398                // Method addElementToCurrentAlt:(Lgroovyjarjarantlr/AlternativeElement;)V
     227: aload_0
     228: aload         8
     230: aload_3
     231: invokespecial #188                // Method labelElement:(Lgroovyjarjarantlr/AlternativeElement;Lgroovyjarjarantlr/Token;)V
     234: aload_0
     235: getfield      #79                 // Field ruleBlock:Lgroovyjarjarantlr/RuleBlock;
     238: invokevirtual #564                // Method groovyjarjarantlr/RuleBlock.getIgnoreRule:()Ljava/lang/String;
     241: astore        9
     243: iload         5
     245: ifne          264
     248: aload         9
     250: ifnull        264
     253: aload_0
     254: aload_0
     255: aload         9
     257: aload_1
     258: invokespecial #566                // Method createOptionalRuleRef:(Ljava/lang/String;Lgroovyjarjarantlr/Token;)Lgroovyjarjarantlr/AlternativeBlock;
     261: invokevirtual #398                // Method addElementToCurrentAlt:(Lgroovyjarjarantlr/AlternativeElement;)V
     264: return

  public void refTokensSpecElementOption(groovyjarjarantlr.Token, groovyjarjarantlr.Token, groovyjarjarantlr.Token);
    Code:
       0: aload_0
       1: getfield      #43                 // Field grammar:Lgroovyjarjarantlr/Grammar;
       4: getfield      #591                // Field groovyjarjarantlr/Grammar.tokenManager:Lgroovyjarjarantlr/TokenManager;
       7: aload_1
       8: invokevirtual #137                // Method groovyjarjarantlr/Token.getText:()Ljava/lang/String;
      11: invokeinterface #597,  2          // InterfaceMethod groovyjarjarantlr/TokenManager.getTokenSymbol:(Ljava/lang/String;)Lgroovyjarjarantlr/TokenSymbol;
      16: astore        4
      18: aload         4
      20: ifnonnull     59
      23: aload_0
      24: getfield      #53                 // Field tool:Lgroovyjarjarantlr/Tool;
      27: new           #55                 // class java/lang/StringBuffer
      30: dup
      31: invokespecial #56                 // Method java/lang/StringBuffer."<init>":()V
      34: ldc_w         #599                // String cannot find
      37: invokevirtual #62                 // Method java/lang/StringBuffer.append:(Ljava/lang/String;)Ljava/lang/StringBuffer;
      40: aload_1
      41: invokevirtual #137                // Method groovyjarjarantlr/Token.getText:()Ljava/lang/String;
      44: invokevirtual #62                 // Method java/lang/StringBuffer.append:(Ljava/lang/String;)Ljava/lang/StringBuffer;
      47: ldc_w         #601                // String in tokens {...}
      50: invokevirtual #62                 // Method java/lang/StringBuffer.append:(Ljava/lang/String;)Ljava/lang/StringBuffer;
      53: invokevirtual #67                 // Method java/lang/StringBuffer.toString:()Ljava/lang/String;
      56: invokevirtual #130                // Method groovyjarjarantlr/Tool.panic:(Ljava/lang/String;)V
      59: aload_2
      60: invokevirtual #137                // Method groovyjarjarantlr/Token.getText:()Ljava/lang/String;
      63: ldc_w         #603                // String AST
      66: invokevirtual #286                // Method java/lang/String.equals:(Ljava/lang/Object;)Z
      69: ifeq          84
      72: aload         4
      74: aload_3
      75: invokevirtual #137                // Method groovyjarjarantlr/Token.getText:()Ljava/lang/String;
      78: invokevirtual #608                // Method groovyjarjarantlr/TokenSymbol.setASTNodeType:(Ljava/lang/String;)V
      81: goto          132
      84: aload_0
      85: getfield      #43                 // Field grammar:Lgroovyjarjarantlr/Grammar;
      88: getfield      #264                // Field groovyjarjarantlr/Grammar.antlrTool:Lgroovyjarjarantlr/Tool;
      91: new           #55                 // class java/lang/StringBuffer
      94: dup
      95: invokespecial #56                 // Method java/lang/StringBuffer."<init>":()V
      98: ldc_w         #610                // String invalid tokens {...} element option:
     101: invokevirtual #62                 // Method java/lang/StringBuffer.append:(Ljava/lang/String;)Ljava/lang/StringBuffer;
     104: aload_2
     105: invokevirtual #137                // Method groovyjarjarantlr/Token.getText:()Ljava/lang/String;
     108: invokevirtual #62                 // Method java/lang/StringBuffer.append:(Ljava/lang/String;)Ljava/lang/StringBuffer;
     111: invokevirtual #67                 // Method java/lang/StringBuffer.toString:()Ljava/lang/String;
     114: aload_0
     115: getfield      #43                 // Field grammar:Lgroovyjarjarantlr/Grammar;
     118: invokevirtual #198                // Method groovyjarjarantlr/Grammar.getFilename:()Ljava/lang/String;
     121: aload_2
     122: invokevirtual #202                // Method groovyjarjarantlr/Token.getLine:()I
     125: aload_2
     126: invokevirtual #205                // Method groovyjarjarantlr/Token.getColumn:()I
     129: invokevirtual #208                // Method groovyjarjarantlr/Tool.error:(Ljava/lang/String;Ljava/lang/String;II)V
     132: return

  public void refElementOption(groovyjarjarantlr.Token, groovyjarjarantlr.Token);
    Code:
       0: aload_0
       1: invokevirtual #94                 // Method context:()Lgroovyjarjarantlr/BlockContext;
       4: invokevirtual #616                // Method groovyjarjarantlr/BlockContext.currentElement:()Lgroovyjarjarantlr/AlternativeElement;
       7: astore_3
       8: aload_3
       9: instanceof    #618                // class groovyjarjarantlr/StringLiteralElement
      12: ifne          29
      15: aload_3
      16: instanceof    #620                // class groovyjarjarantlr/TokenRefElement
      19: ifne          29
      22: aload_3
      23: instanceof    #622                // class groovyjarjarantlr/WildcardElement
      26: ifeq          41
      29: aload_3
      30: checkcast     #624                // class groovyjarjarantlr/GrammarAtom
      33: aload_1
      34: aload_2
      35: invokevirtual #627                // Method groovyjarjarantlr/GrammarAtom.setOption:(Lgroovyjarjarantlr/Token;Lgroovyjarjarantlr/Token;)V
      38: goto          92
      41: aload_0
      42: getfield      #53                 // Field tool:Lgroovyjarjarantlr/Tool;
      45: new           #55                 // class java/lang/StringBuffer
      48: dup
      49: invokespecial #56                 // Method java/lang/StringBuffer."<init>":()V
      52: ldc_w         #629                // String cannot use element option (
      55: invokevirtual #62                 // Method java/lang/StringBuffer.append:(Ljava/lang/String;)Ljava/lang/StringBuffer;
      58: aload_1
      59: invokevirtual #137                // Method groovyjarjarantlr/Token.getText:()Ljava/lang/String;
      62: invokevirtual #62                 // Method java/lang/StringBuffer.append:(Ljava/lang/String;)Ljava/lang/StringBuffer;
      65: ldc_w         #631                // String ) for this kind of element
      68: invokevirtual #62                 // Method java/lang/StringBuffer.append:(Ljava/lang/String;)Ljava/lang/StringBuffer;
      71: invokevirtual #67                 // Method java/lang/StringBuffer.toString:()Ljava/lang/String;
      74: aload_0
      75: getfield      #43                 // Field grammar:Lgroovyjarjarantlr/Grammar;
      78: invokevirtual #198                // Method groovyjarjarantlr/Grammar.getFilename:()Ljava/lang/String;
      81: aload_1
      82: invokevirtual #202                // Method groovyjarjarantlr/Token.getLine:()I
      85: aload_1
      86: invokevirtual #205                // Method groovyjarjarantlr/Token.getColumn:()I
      89: invokevirtual #208                // Method groovyjarjarantlr/Tool.error:(Ljava/lang/String;Ljava/lang/String;II)V
      92: return

  public void refExceptionHandler(groovyjarjarantlr.Token, groovyjarjarantlr.Token);
    Code:
       0: aload_0
       1: aload_1
       2: aload_2
       3: invokespecial #634                // Method groovyjarjarantlr/DefineGrammarSymbols.refExceptionHandler:(Lgroovyjarjarantlr/Token;Lgroovyjarjarantlr/Token;)V
       6: aload_0
       7: getfield      #36                 // Field currentExceptionSpec:Lgroovyjarjarantlr/ExceptionSpec;
      10: ifnonnull     23
      13: aload_0
      14: getfield      #53                 // Field tool:Lgroovyjarjarantlr/Tool;
      17: ldc_w         #636                // String exception handler processing internal error
      20: invokevirtual #130                // Method groovyjarjarantlr/Tool.panic:(Ljava/lang/String;)V
      23: aload_0
      24: getfield      #36                 // Field currentExceptionSpec:Lgroovyjarjarantlr/ExceptionSpec;
      27: new           #638                // class groovyjarjarantlr/ExceptionHandler
      30: dup
      31: aload_1
      32: aload_2
      33: invokespecial #640                // Method groovyjarjarantlr/ExceptionHandler."<init>":(Lgroovyjarjarantlr/Token;Lgroovyjarjarantlr/Token;)V
      36: invokevirtual #644                // Method groovyjarjarantlr/ExceptionSpec.addHandler:(Lgroovyjarjarantlr/ExceptionHandler;)V
      39: return

  public void refInitAction(groovyjarjarantlr.Token);
    Code:
       0: aload_0
       1: aload_1
       2: invokespecial #520                // Method groovyjarjarantlr/DefineGrammarSymbols.refAction:(Lgroovyjarjarantlr/Token;)V
       5: aload_0
       6: invokevirtual #94                 // Method context:()Lgroovyjarjarantlr/BlockContext;
       9: getfield      #113                // Field groovyjarjarantlr/BlockContext.block:Lgroovyjarjarantlr/AlternativeBlock;
      12: aload_1
      13: invokevirtual #137                // Method groovyjarjarantlr/Token.getText:()Ljava/lang/String;
      16: invokevirtual #648                // Method groovyjarjarantlr/AlternativeBlock.setInitAction:(Ljava/lang/String;)V
      19: return

  public void refMemberAction(groovyjarjarantlr.Token);
    Code:
       0: aload_0
       1: getfield      #43                 // Field grammar:Lgroovyjarjarantlr/Grammar;
       4: aload_1
       5: putfield      #653                // Field groovyjarjarantlr/Grammar.classMemberAction:Lgroovyjarjarantlr/Token;
       8: return

  public void refPreambleAction(groovyjarjarantlr.Token);
    Code:
       0: aload_0
       1: aload_1
       2: invokespecial #656                // Method groovyjarjarantlr/DefineGrammarSymbols.refPreambleAction:(Lgroovyjarjarantlr/Token;)V
       5: return

  public void refReturnAction(groovyjarjarantlr.Token);
    Code:
       0: aload_0
       1: getfield      #43                 // Field grammar:Lgroovyjarjarantlr/Grammar;
       4: instanceof    #364                // class groovyjarjarantlr/LexerGrammar
       7: ifeq          78
      10: aload_0
      11: invokevirtual #94                 // Method context:()Lgroovyjarjarantlr/BlockContext;
      14: getfield      #113                // Field groovyjarjarantlr/BlockContext.block:Lgroovyjarjarantlr/AlternativeBlock;
      17: checkcast     #81                 // class groovyjarjarantlr/RuleBlock
      20: invokevirtual #660                // Method groovyjarjarantlr/RuleBlock.getRuleName:()Ljava/lang/String;
      23: invokestatic  #342                // Method groovyjarjarantlr/CodeGenerator.encodeLexerRuleName:(Ljava/lang/String;)Ljava/lang/String;
      26: astore_2
      27: aload_0
      28: getfield      #43                 // Field grammar:Lgroovyjarjarantlr/Grammar;
      31: aload_2
      32: invokevirtual #384                // Method groovyjarjarantlr/Grammar.getSymbol:(Ljava/lang/String;)Lgroovyjarjarantlr/GrammarSymbol;
      35: checkcast     #258                // class groovyjarjarantlr/RuleSymbol
      38: astore_3
      39: aload_3
      40: getfield      #280                // Field groovyjarjarantlr/RuleSymbol.access:Ljava/lang/String;
      43: ldc_w         #282                // String public
      46: invokevirtual #286                // Method java/lang/String.equals:(Ljava/lang/Object;)Z
      49: ifeq          78
      52: aload_0
      53: getfield      #53                 // Field tool:Lgroovyjarjarantlr/Tool;
      56: ldc_w         #662                // String public Lexical rules cannot specify return type
      59: aload_0
      60: getfield      #43                 // Field grammar:Lgroovyjarjarantlr/Grammar;
      63: invokevirtual #198                // Method groovyjarjarantlr/Grammar.getFilename:()Ljava/lang/String;
      66: aload_1
      67: invokevirtual #202                // Method groovyjarjarantlr/Token.getLine:()I
      70: aload_1
      71: invokevirtual #205                // Method groovyjarjarantlr/Token.getColumn:()I
      74: invokevirtual #561                // Method groovyjarjarantlr/Tool.warning:(Ljava/lang/String;Ljava/lang/String;II)V
      77: return
      78: aload_0
      79: invokevirtual #94                 // Method context:()Lgroovyjarjarantlr/BlockContext;
      82: getfield      #113                // Field groovyjarjarantlr/BlockContext.block:Lgroovyjarjarantlr/AlternativeBlock;
      85: checkcast     #81                 // class groovyjarjarantlr/RuleBlock
      88: aload_1
      89: invokevirtual #137                // Method groovyjarjarantlr/Token.getText:()Ljava/lang/String;
      92: putfield      #665                // Field groovyjarjarantlr/RuleBlock.returnAction:Ljava/lang/String;
      95: return

  public void refRule(groovyjarjarantlr.Token, groovyjarjarantlr.Token, groovyjarjarantlr.Token, groovyjarjarantlr.Token, int);
    Code:
       0: aload_0
       1: getfield      #43                 // Field grammar:Lgroovyjarjarantlr/Grammar;
       4: instanceof    #364                // class groovyjarjarantlr/LexerGrammar
       7: ifeq          87
      10: aload_2
      11: getfield      #362                // Field groovyjarjarantlr/Token.type:I
      14: bipush        24
      16: if_icmpeq     56
      19: aload_0
      20: getfield      #53                 // Field tool:Lgroovyjarjarantlr/Tool;
      23: new           #55                 // class java/lang/StringBuffer
      26: dup
      27: invokespecial #56                 // Method java/lang/StringBuffer."<init>":()V
      30: ldc_w         #669                // String Parser rule
      33: invokevirtual #62                 // Method java/lang/StringBuffer.append:(Ljava/lang/String;)Ljava/lang/StringBuffer;
      36: aload_2
      37: invokevirtual #137                // Method groovyjarjarantlr/Token.getText:()Ljava/lang/String;
      40: invokevirtual #62                 // Method java/lang/StringBuffer.append:(Ljava/lang/String;)Ljava/lang/StringBuffer;
      43: ldc_w         #671                // String  referenced in lexer
      46: invokevirtual #62                 // Method java/lang/StringBuffer.append:(Ljava/lang/String;)Ljava/lang/StringBuffer;
      49: invokevirtual #67                 // Method java/lang/StringBuffer.toString:()Ljava/lang/String;
      52: invokevirtual #73                 // Method groovyjarjarantlr/Tool.error:(Ljava/lang/String;)V
      55: return
      56: iload         5
      58: iconst_2
      59: if_icmpne     87
      62: aload_0
      63: getfield      #53                 // Field tool:Lgroovyjarjarantlr/Tool;
      66: ldc_w         #673                // String AST specification ^ not allowed in lexer
      69: aload_0
      70: getfield      #43                 // Field grammar:Lgroovyjarjarantlr/Grammar;
      73: invokevirtual #198                // Method groovyjarjarantlr/Grammar.getFilename:()Ljava/lang/String;
      76: aload_2
      77: invokevirtual #202                // Method groovyjarjarantlr/Token.getLine:()I
      80: aload_2
      81: invokevirtual #205                // Method groovyjarjarantlr/Token.getColumn:()I
      84: invokevirtual #208                // Method groovyjarjarantlr/Tool.error:(Ljava/lang/String;Ljava/lang/String;II)V
      87: aload_0
      88: aload_1
      89: aload_2
      90: aload_3
      91: aload         4
      93: iload         5
      95: invokespecial #675                // Method groovyjarjarantlr/DefineGrammarSymbols.refRule:(Lgroovyjarjarantlr/Token;Lgroovyjarjarantlr/Token;Lgroovyjarjarantlr/Token;Lgroovyjarjarantlr/Token;I)V
      98: aload_0
      99: new           #299                // class groovyjarjarantlr/RuleRefElement
     102: dup
     103: aload_0
     104: getfield      #43                 // Field grammar:Lgroovyjarjarantlr/Grammar;
     107: aload_2
     108: iload         5
     110: invokespecial #310                // Method groovyjarjarantlr/RuleRefElement."<init>":(Lgroovyjarjarantlr/Grammar;Lgroovyjarjarantlr/Token;I)V
     113: putfield      #677                // Field lastRuleRef:Lgroovyjarjarantlr/RuleRefElement;
     116: aload         4
     118: ifnull        133
     121: aload_0
     122: getfield      #677                // Field lastRuleRef:Lgroovyjarjarantlr/RuleRefElement;
     125: aload         4
     127: invokevirtual #137                // Method groovyjarjarantlr/Token.getText:()Ljava/lang/String;
     130: invokevirtual #680                // Method groovyjarjarantlr/RuleRefElement.setArgs:(Ljava/lang/String;)V
     133: aload_1
     134: ifnull        148
     137: aload_0
     138: getfield      #677                // Field lastRuleRef:Lgroovyjarjarantlr/RuleRefElement;
     141: aload_1
     142: invokevirtual #137                // Method groovyjarjarantlr/Token.getText:()Ljava/lang/String;
     145: invokevirtual #683                // Method groovyjarjarantlr/RuleRefElement.setIdAssign:(Ljava/lang/String;)V
     148: aload_0
     149: aload_0
     150: getfield      #677                // Field lastRuleRef:Lgroovyjarjarantlr/RuleRefElement;
     153: invokevirtual #398                // Method addElementToCurrentAlt:(Lgroovyjarjarantlr/AlternativeElement;)V
     156: aload_2
     157: invokevirtual #137                // Method groovyjarjarantlr/Token.getText:()Ljava/lang/String;
     160: astore        6
     162: aload_2
     163: getfield      #362                // Field groovyjarjarantlr/Token.type:I
     166: bipush        24
     168: if_icmpne     178
     171: aload         6
     173: invokestatic  #342                // Method groovyjarjarantlr/CodeGenerator.encodeLexerRuleName:(Ljava/lang/String;)Ljava/lang/String;
     176: astore        6
     178: aload_0
     179: getfield      #43                 // Field grammar:Lgroovyjarjarantlr/Grammar;
     182: aload         6
     184: invokevirtual #384                // Method groovyjarjarantlr/Grammar.getSymbol:(Ljava/lang/String;)Lgroovyjarjarantlr/GrammarSymbol;
     187: checkcast     #258                // class groovyjarjarantlr/RuleSymbol
     190: astore        7
     192: aload         7
     194: aload_0
     195: getfield      #677                // Field lastRuleRef:Lgroovyjarjarantlr/RuleRefElement;
     198: invokevirtual #330                // Method groovyjarjarantlr/RuleSymbol.addReference:(Lgroovyjarjarantlr/RuleRefElement;)V
     201: aload_0
     202: aload_0
     203: getfield      #677                // Field lastRuleRef:Lgroovyjarjarantlr/RuleRefElement;
     206: aload_3
     207: invokespecial #188                // Method labelElement:(Lgroovyjarjarantlr/AlternativeElement;Lgroovyjarjarantlr/Token;)V
     210: return

  public void refSemPred(groovyjarjarantlr.Token);
    Code:
       0: aload_0
       1: aload_1
       2: invokespecial #686                // Method groovyjarjarantlr/DefineGrammarSymbols.refSemPred:(Lgroovyjarjarantlr/Token;)V
       5: aload_0
       6: invokevirtual #94                 // Method context:()Lgroovyjarjarantlr/BlockContext;
       9: invokevirtual #417                // Method groovyjarjarantlr/BlockContext.currentAlt:()Lgroovyjarjarantlr/Alternative;
      12: invokevirtual #689                // Method groovyjarjarantlr/Alternative.atStart:()Z
      15: ifeq          35
      18: aload_0
      19: invokevirtual #94                 // Method context:()Lgroovyjarjarantlr/BlockContext;
      22: invokevirtual #417                // Method groovyjarjarantlr/BlockContext.currentAlt:()Lgroovyjarjarantlr/Alternative;
      25: aload_1
      26: invokevirtual #137                // Method groovyjarjarantlr/Token.getText:()Ljava/lang/String;
      29: putfield      #297                // Field groovyjarjarantlr/Alternative.semPred:Ljava/lang/String;
      32: goto          58
      35: new           #525                // class groovyjarjarantlr/ActionElement
      38: dup
      39: aload_0
      40: getfield      #43                 // Field grammar:Lgroovyjarjarantlr/Grammar;
      43: aload_1
      44: invokespecial #526                // Method groovyjarjarantlr/ActionElement."<init>":(Lgroovyjarjarantlr/Grammar;Lgroovyjarjarantlr/Token;)V
      47: astore_2
      48: aload_2
      49: iconst_1
      50: putfield      #692                // Field groovyjarjarantlr/ActionElement.isSemPred:Z
      53: aload_0
      54: aload_2
      55: invokevirtual #398                // Method addElementToCurrentAlt:(Lgroovyjarjarantlr/AlternativeElement;)V
      58: return

  public void refStringLiteral(groovyjarjarantlr.Token, groovyjarjarantlr.Token, int, boolean);
    Code:
       0: aload_0
       1: aload_1
       2: aload_2
       3: iload_3
       4: iload         4
       6: invokespecial #696                // Method groovyjarjarantlr/DefineGrammarSymbols.refStringLiteral:(Lgroovyjarjarantlr/Token;Lgroovyjarjarantlr/Token;IZ)V
       9: aload_0
      10: getfield      #43                 // Field grammar:Lgroovyjarjarantlr/Grammar;
      13: instanceof    #193                // class groovyjarjarantlr/TreeWalkerGrammar
      16: ifeq          49
      19: iload_3
      20: iconst_2
      21: if_icmpne     49
      24: aload_0
      25: getfield      #53                 // Field tool:Lgroovyjarjarantlr/Tool;
      28: ldc_w         #698                // String ^ not allowed in here for tree-walker
      31: aload_0
      32: getfield      #43                 // Field grammar:Lgroovyjarjarantlr/Grammar;
      35: invokevirtual #198                // Method groovyjarjarantlr/Grammar.getFilename:()Ljava/lang/String;
      38: aload_1
      39: invokevirtual #202                // Method groovyjarjarantlr/Token.getLine:()I
      42: aload_1
      43: invokevirtual #205                // Method groovyjarjarantlr/Token.getColumn:()I
      46: invokevirtual #208                // Method groovyjarjarantlr/Tool.error:(Ljava/lang/String;Ljava/lang/String;II)V
      49: new           #618                // class groovyjarjarantlr/StringLiteralElement
      52: dup
      53: aload_0
      54: getfield      #43                 // Field grammar:Lgroovyjarjarantlr/Grammar;
      57: aload_1
      58: iload_3
      59: invokespecial #699                // Method groovyjarjarantlr/StringLiteralElement."<init>":(Lgroovyjarjarantlr/Grammar;Lgroovyjarjarantlr/Token;I)V
      62: astore        5
      64: aload_0
      65: getfield      #43                 // Field grammar:Lgroovyjarjarantlr/Grammar;
      68: instanceof    #364                // class groovyjarjarantlr/LexerGrammar
      71: ifeq          167
      74: aload_0
      75: getfield      #43                 // Field grammar:Lgroovyjarjarantlr/Grammar;
      78: checkcast     #364                // class groovyjarjarantlr/LexerGrammar
      81: getfield      #548                // Field groovyjarjarantlr/LexerGrammar.caseSensitive:Z
      84: ifne          167
      87: iconst_1
      88: istore        6
      90: iload         6
      92: aload_1
      93: invokevirtual #137                // Method groovyjarjarantlr/Token.getText:()Ljava/lang/String;
      96: invokevirtual #702                // Method java/lang/String.length:()I
      99: iconst_1
     100: isub
     101: if_icmpge     167
     104: aload_1
     105: invokevirtual #137                // Method groovyjarjarantlr/Token.getText:()Ljava/lang/String;
     108: iload         6
     110: invokevirtual #706                // Method java/lang/String.charAt:(I)C
     113: istore        7
     115: iload         7
     117: sipush        128
     120: if_icmpge     161
     123: iload         7
     125: invokestatic  #556                // Method java/lang/Character.toLowerCase:(C)C
     128: iload         7
     130: if_icmpeq     161
     133: aload_0
     134: getfield      #53                 // Field tool:Lgroovyjarjarantlr/Tool;
     137: ldc_w         #708                // String Characters of string literal must be lowercase when caseSensitive=false
     140: aload_0
     141: getfield      #43                 // Field grammar:Lgroovyjarjarantlr/Grammar;
     144: invokevirtual #198                // Method groovyjarjarantlr/Grammar.getFilename:()Ljava/lang/String;
     147: aload_1
     148: invokevirtual #202                // Method groovyjarjarantlr/Token.getLine:()I
     151: aload_1
     152: invokevirtual #205                // Method groovyjarjarantlr/Token.getColumn:()I
     155: invokevirtual #561                // Method groovyjarjarantlr/Tool.warning:(Ljava/lang/String;Ljava/lang/String;II)V
     158: goto          167
     161: iinc          6, 1
     164: goto          90
     167: aload_0
     168: aload         5
     170: invokevirtual #398                // Method addElementToCurrentAlt:(Lgroovyjarjarantlr/AlternativeElement;)V
     173: aload_0
     174: aload         5
     176: aload_2
     177: invokespecial #188                // Method labelElement:(Lgroovyjarjarantlr/AlternativeElement;Lgroovyjarjarantlr/Token;)V
     180: aload_0
     181: getfield      #79                 // Field ruleBlock:Lgroovyjarjarantlr/RuleBlock;
     184: invokevirtual #564                // Method groovyjarjarantlr/RuleBlock.getIgnoreRule:()Ljava/lang/String;
     187: astore        6
     189: iload         4
     191: ifne          210
     194: aload         6
     196: ifnull        210
     199: aload_0
     200: aload_0
     201: aload         6
     203: aload_1
     204: invokespecial #566                // Method createOptionalRuleRef:(Ljava/lang/String;Lgroovyjarjarantlr/Token;)Lgroovyjarjarantlr/AlternativeBlock;
     207: invokevirtual #398                // Method addElementToCurrentAlt:(Lgroovyjarjarantlr/AlternativeElement;)V
     210: return

  public void refToken(groovyjarjarantlr.Token, groovyjarjarantlr.Token, groovyjarjarantlr.Token, groovyjarjarantlr.Token, boolean, int, boolean);
    Code:
       0: aload_0
       1: getfield      #43                 // Field grammar:Lgroovyjarjarantlr/Grammar;
       4: instanceof    #364                // class groovyjarjarantlr/LexerGrammar
       7: ifeq          115
      10: iload         6
      12: iconst_2
      13: if_icmpne     41
      16: aload_0
      17: getfield      #53                 // Field tool:Lgroovyjarjarantlr/Tool;
      20: ldc_w         #673                // String AST specification ^ not allowed in lexer
      23: aload_0
      24: getfield      #43                 // Field grammar:Lgroovyjarjarantlr/Grammar;
      27: invokevirtual #198                // Method groovyjarjarantlr/Grammar.getFilename:()Ljava/lang/String;
      30: aload_2
      31: invokevirtual #202                // Method groovyjarjarantlr/Token.getLine:()I
      34: aload_2
      35: invokevirtual #205                // Method groovyjarjarantlr/Token.getColumn:()I
      38: invokevirtual #208                // Method groovyjarjarantlr/Tool.error:(Ljava/lang/String;Ljava/lang/String;II)V
      41: iload         5
      43: ifeq          71
      46: aload_0
      47: getfield      #53                 // Field tool:Lgroovyjarjarantlr/Tool;
      50: ldc_w         #712                // String ~TOKEN is not allowed in lexer
      53: aload_0
      54: getfield      #43                 // Field grammar:Lgroovyjarjarantlr/Grammar;
      57: invokevirtual #198                // Method groovyjarjarantlr/Grammar.getFilename:()Ljava/lang/String;
      60: aload_2
      61: invokevirtual #202                // Method groovyjarjarantlr/Token.getLine:()I
      64: aload_2
      65: invokevirtual #205                // Method groovyjarjarantlr/Token.getColumn:()I
      68: invokevirtual #208                // Method groovyjarjarantlr/Tool.error:(Ljava/lang/String;Ljava/lang/String;II)V
      71: aload_0
      72: aload_1
      73: aload_2
      74: aload_3
      75: aload         4
      77: iload         6
      79: invokevirtual #713                // Method refRule:(Lgroovyjarjarantlr/Token;Lgroovyjarjarantlr/Token;Lgroovyjarjarantlr/Token;Lgroovyjarjarantlr/Token;I)V
      82: aload_0
      83: getfield      #79                 // Field ruleBlock:Lgroovyjarjarantlr/RuleBlock;
      86: invokevirtual #564                // Method groovyjarjarantlr/RuleBlock.getIgnoreRule:()Ljava/lang/String;
      89: astore        8
      91: iload         7
      93: ifne          222
      96: aload         8
      98: ifnull        222
     101: aload_0
     102: aload_0
     103: aload         8
     105: aload_2
     106: invokespecial #566                // Method createOptionalRuleRef:(Ljava/lang/String;Lgroovyjarjarantlr/Token;)Lgroovyjarjarantlr/AlternativeBlock;
     109: invokevirtual #398                // Method addElementToCurrentAlt:(Lgroovyjarjarantlr/AlternativeElement;)V
     112: goto          222
     115: aload_1
     116: ifnull        144
     119: aload_0
     120: getfield      #53                 // Field tool:Lgroovyjarjarantlr/Tool;
     123: ldc_w         #715                // String Assignment from token reference only allowed in lexer
     126: aload_0
     127: getfield      #43                 // Field grammar:Lgroovyjarjarantlr/Grammar;
     130: invokevirtual #198                // Method groovyjarjarantlr/Grammar.getFilename:()Ljava/lang/String;
     133: aload_1
     134: invokevirtual #202                // Method groovyjarjarantlr/Token.getLine:()I
     137: aload_1
     138: invokevirtual #205                // Method groovyjarjarantlr/Token.getColumn:()I
     141: invokevirtual #208                // Method groovyjarjarantlr/Tool.error:(Ljava/lang/String;Ljava/lang/String;II)V
     144: aload         4
     146: ifnull        176
     149: aload_0
     150: getfield      #53                 // Field tool:Lgroovyjarjarantlr/Tool;
     153: ldc_w         #717                // String Token reference arguments only allowed in lexer
     156: aload_0
     157: getfield      #43                 // Field grammar:Lgroovyjarjarantlr/Grammar;
     160: invokevirtual #198                // Method groovyjarjarantlr/Grammar.getFilename:()Ljava/lang/String;
     163: aload         4
     165: invokevirtual #202                // Method groovyjarjarantlr/Token.getLine:()I
     168: aload         4
     170: invokevirtual #205                // Method groovyjarjarantlr/Token.getColumn:()I
     173: invokevirtual #208                // Method groovyjarjarantlr/Tool.error:(Ljava/lang/String;Ljava/lang/String;II)V
     176: aload_0
     177: aload_1
     178: aload_2
     179: aload_3
     180: aload         4
     182: iload         5
     184: iload         6
     186: iload         7
     188: invokespecial #719                // Method groovyjarjarantlr/DefineGrammarSymbols.refToken:(Lgroovyjarjarantlr/Token;Lgroovyjarjarantlr/Token;Lgroovyjarjarantlr/Token;Lgroovyjarjarantlr/Token;ZIZ)V
     191: new           #620                // class groovyjarjarantlr/TokenRefElement
     194: dup
     195: aload_0
     196: getfield      #43                 // Field grammar:Lgroovyjarjarantlr/Grammar;
     199: aload_2
     200: iload         5
     202: iload         6
     204: invokespecial #722                // Method groovyjarjarantlr/TokenRefElement."<init>":(Lgroovyjarjarantlr/Grammar;Lgroovyjarjarantlr/Token;ZI)V
     207: astore        8
     209: aload_0
     210: aload         8
     212: invokevirtual #398                // Method addElementToCurrentAlt:(Lgroovyjarjarantlr/AlternativeElement;)V
     215: aload_0
     216: aload         8
     218: aload_3
     219: invokespecial #188                // Method labelElement:(Lgroovyjarjarantlr/AlternativeElement;Lgroovyjarjarantlr/Token;)V
     222: return

  public void refTokenRange(groovyjarjarantlr.Token, groovyjarjarantlr.Token, groovyjarjarantlr.Token, int, boolean);
    Code:
       0: aload_0
       1: getfield      #43                 // Field grammar:Lgroovyjarjarantlr/Grammar;
       4: instanceof    #364                // class groovyjarjarantlr/LexerGrammar
       7: ifeq          36
      10: aload_0
      11: getfield      #53                 // Field tool:Lgroovyjarjarantlr/Tool;
      14: ldc_w         #725                // String Token range not allowed in lexer
      17: aload_0
      18: getfield      #43                 // Field grammar:Lgroovyjarjarantlr/Grammar;
      21: invokevirtual #198                // Method groovyjarjarantlr/Grammar.getFilename:()Ljava/lang/String;
      24: aload_1
      25: invokevirtual #202                // Method groovyjarjarantlr/Token.getLine:()I
      28: aload_1
      29: invokevirtual #205                // Method groovyjarjarantlr/Token.getColumn:()I
      32: invokevirtual #208                // Method groovyjarjarantlr/Tool.error:(Ljava/lang/String;Ljava/lang/String;II)V
      35: return
      36: aload_0
      37: aload_1
      38: aload_2
      39: aload_3
      40: iload         4
      42: iload         5
      44: invokespecial #727                // Method groovyjarjarantlr/DefineGrammarSymbols.refTokenRange:(Lgroovyjarjarantlr/Token;Lgroovyjarjarantlr/Token;Lgroovyjarjarantlr/Token;IZ)V
      47: new           #729                // class groovyjarjarantlr/TokenRangeElement
      50: dup
      51: aload_0
      52: getfield      #43                 // Field grammar:Lgroovyjarjarantlr/Grammar;
      55: aload_1
      56: aload_2
      57: iload         4
      59: invokespecial #732                // Method groovyjarjarantlr/TokenRangeElement."<init>":(Lgroovyjarjarantlr/Grammar;Lgroovyjarjarantlr/Token;Lgroovyjarjarantlr/Token;I)V
      62: astore        6
      64: aload         6
      66: getfield      #735                // Field groovyjarjarantlr/TokenRangeElement.end:I
      69: aload         6
      71: getfield      #738                // Field groovyjarjarantlr/TokenRangeElement.begin:I
      74: if_icmpge     103
      77: aload_0
      78: getfield      #53                 // Field tool:Lgroovyjarjarantlr/Tool;
      81: ldc_w         #578                // String Malformed range.
      84: aload_0
      85: getfield      #43                 // Field grammar:Lgroovyjarjarantlr/Grammar;
      88: invokevirtual #198                // Method groovyjarjarantlr/Grammar.getFilename:()Ljava/lang/String;
      91: aload_1
      92: invokevirtual #202                // Method groovyjarjarantlr/Token.getLine:()I
      95: aload_1
      96: invokevirtual #205                // Method groovyjarjarantlr/Token.getColumn:()I
      99: invokevirtual #208                // Method groovyjarjarantlr/Tool.error:(Ljava/lang/String;Ljava/lang/String;II)V
     102: return
     103: aload_0
     104: aload         6
     106: invokevirtual #398                // Method addElementToCurrentAlt:(Lgroovyjarjarantlr/AlternativeElement;)V
     109: aload_0
     110: aload         6
     112: aload_3
     113: invokespecial #188                // Method labelElement:(Lgroovyjarjarantlr/AlternativeElement;Lgroovyjarjarantlr/Token;)V
     116: return

  public void refTreeSpecifier(groovyjarjarantlr.Token);
    Code:
       0: aload_0
       1: invokevirtual #94                 // Method context:()Lgroovyjarjarantlr/BlockContext;
       4: invokevirtual #417                // Method groovyjarjarantlr/BlockContext.currentAlt:()Lgroovyjarjarantlr/Alternative;
       7: aload_1
       8: putfield      #742                // Field groovyjarjarantlr/Alternative.treeSpecifier:Lgroovyjarjarantlr/Token;
      11: return

  public void refWildcard(groovyjarjarantlr.Token, groovyjarjarantlr.Token, int);
    Code:
       0: aload_0
       1: aload_1
       2: aload_2
       3: iload_3
       4: invokespecial #746                // Method groovyjarjarantlr/DefineGrammarSymbols.refWildcard:(Lgroovyjarjarantlr/Token;Lgroovyjarjarantlr/Token;I)V
       7: new           #622                // class groovyjarjarantlr/WildcardElement
      10: dup
      11: aload_0
      12: getfield      #43                 // Field grammar:Lgroovyjarjarantlr/Grammar;
      15: aload_1
      16: iload_3
      17: invokespecial #747                // Method groovyjarjarantlr/WildcardElement."<init>":(Lgroovyjarjarantlr/Grammar;Lgroovyjarjarantlr/Token;I)V
      20: astore        4
      22: aload_0
      23: aload         4
      25: invokevirtual #398                // Method addElementToCurrentAlt:(Lgroovyjarjarantlr/AlternativeElement;)V
      28: aload_0
      29: aload         4
      31: aload_2
      32: invokespecial #188                // Method labelElement:(Lgroovyjarjarantlr/AlternativeElement;Lgroovyjarjarantlr/Token;)V
      35: return

  public void reset();
    Code:
       0: aload_0
       1: invokespecial #750                // Method groovyjarjarantlr/DefineGrammarSymbols.reset:()V
       4: aload_0
       5: new           #25                 // class groovyjarjarantlr/collections/impl/LList
       8: dup
       9: invokespecial #28                 // Method groovyjarjarantlr/collections/impl/LList."<init>":()V
      12: putfield      #30                 // Field blocks:Lgroovyjarjarantlr/collections/Stack;
      15: aload_0
      16: aconst_null
      17: putfield      #677                // Field lastRuleRef:Lgroovyjarjarantlr/RuleRefElement;
      20: aload_0
      21: aconst_null
      22: putfield      #393                // Field ruleEnd:Lgroovyjarjarantlr/RuleEndElement;
      25: aload_0
      26: aconst_null
      27: putfield      #79                 // Field ruleBlock:Lgroovyjarjarantlr/RuleBlock;
      30: aload_0
      31: iconst_0
      32: putfield      #32                 // Field nested:I
      35: aload_0
      36: aconst_null
      37: putfield      #36                 // Field currentExceptionSpec:Lgroovyjarjarantlr/ExceptionSpec;
      40: aload_0
      41: iconst_0
      42: putfield      #34                 // Field grammarError:Z
      45: return

  public void setArgOfRuleRef(groovyjarjarantlr.Token);
    Code:
       0: aload_0
       1: aload_1
       2: invokespecial #753                // Method groovyjarjarantlr/DefineGrammarSymbols.setArgOfRuleRef:(Lgroovyjarjarantlr/Token;)V
       5: aload_0
       6: getfield      #677                // Field lastRuleRef:Lgroovyjarjarantlr/RuleRefElement;
       9: aload_1
      10: invokevirtual #137                // Method groovyjarjarantlr/Token.getText:()Ljava/lang/String;
      13: invokevirtual #680                // Method groovyjarjarantlr/RuleRefElement.setArgs:(Ljava/lang/String;)V
      16: return

  public static void setBlock(groovyjarjarantlr.AlternativeBlock, groovyjarjarantlr.AlternativeBlock);
    Code:
       0: aload_0
       1: aload_1
       2: invokevirtual #754                // Method groovyjarjarantlr/AlternativeBlock.getAlternatives:()Lgroovyjarjarantlr/collections/impl/Vector;
       5: invokevirtual #758                // Method groovyjarjarantlr/AlternativeBlock.setAlternatives:(Lgroovyjarjarantlr/collections/impl/Vector;)V
       8: aload_0
       9: aload_1
      10: getfield      #761                // Field groovyjarjarantlr/AlternativeBlock.initAction:Ljava/lang/String;
      13: putfield      #761                // Field groovyjarjarantlr/AlternativeBlock.initAction:Ljava/lang/String;
      16: aload_0
      17: aload_1
      18: getfield      #764                // Field groovyjarjarantlr/AlternativeBlock.label:Ljava/lang/String;
      21: putfield      #764                // Field groovyjarjarantlr/AlternativeBlock.label:Ljava/lang/String;
      24: aload_0
      25: aload_1
      26: getfield      #474                // Field groovyjarjarantlr/AlternativeBlock.hasASynPred:Z
      29: putfield      #474                // Field groovyjarjarantlr/AlternativeBlock.hasASynPred:Z
      32: aload_0
      33: aload_1
      34: getfield      #523                // Field groovyjarjarantlr/AlternativeBlock.hasAnAction:Z
      37: putfield      #523                // Field groovyjarjarantlr/AlternativeBlock.hasAnAction:Z
      40: aload_0
      41: aload_1
      42: getfield      #767                // Field groovyjarjarantlr/AlternativeBlock.warnWhenFollowAmbig:Z
      45: putfield      #767                // Field groovyjarjarantlr/AlternativeBlock.warnWhenFollowAmbig:Z
      48: aload_0
      49: aload_1
      50: getfield      #770                // Field groovyjarjarantlr/AlternativeBlock.generateAmbigWarnings:Z
      53: putfield      #770                // Field groovyjarjarantlr/AlternativeBlock.generateAmbigWarnings:Z
      56: aload_0
      57: aload_1
      58: getfield      #773                // Field groovyjarjarantlr/AlternativeBlock.line:I
      61: putfield      #773                // Field groovyjarjarantlr/AlternativeBlock.line:I
      64: aload_0
      65: aload_1
      66: getfield      #776                // Field groovyjarjarantlr/AlternativeBlock.greedy:Z
      69: putfield      #776                // Field groovyjarjarantlr/AlternativeBlock.greedy:Z
      72: aload_0
      73: aload_1
      74: getfield      #779                // Field groovyjarjarantlr/AlternativeBlock.greedySet:Z
      77: putfield      #779                // Field groovyjarjarantlr/AlternativeBlock.greedySet:Z
      80: return

  public void setRuleOption(groovyjarjarantlr.Token, groovyjarjarantlr.Token);
    Code:
       0: aload_0
       1: getfield      #79                 // Field ruleBlock:Lgroovyjarjarantlr/RuleBlock;
       4: aload_1
       5: aload_2
       6: invokevirtual #781                // Method groovyjarjarantlr/RuleBlock.setOption:(Lgroovyjarjarantlr/Token;Lgroovyjarjarantlr/Token;)V
       9: return

  public void setSubruleOption(groovyjarjarantlr.Token, groovyjarjarantlr.Token);
    Code:
       0: aload_0
       1: invokevirtual #94                 // Method context:()Lgroovyjarjarantlr/BlockContext;
       4: getfield      #113                // Field groovyjarjarantlr/BlockContext.block:Lgroovyjarjarantlr/AlternativeBlock;
       7: aload_1
       8: aload_2
       9: invokevirtual #783                // Method groovyjarjarantlr/AlternativeBlock.setOption:(Lgroovyjarjarantlr/Token;Lgroovyjarjarantlr/Token;)V
      12: return

  public void synPred();
    Code:
       0: aload_0
       1: invokevirtual #94                 // Method context:()Lgroovyjarjarantlr/BlockContext;
       4: getfield      #113                // Field groovyjarjarantlr/BlockContext.block:Lgroovyjarjarantlr/AlternativeBlock;
       7: getfield      #440                // Field groovyjarjarantlr/AlternativeBlock.not:Z
      10: ifeq          50
      13: aload_0
      14: getfield      #53                 // Field tool:Lgroovyjarjarantlr/Tool;
      17: ldc_w         #785                // String \'~\' cannot be applied to syntactic predicate
      20: aload_0
      21: getfield      #43                 // Field grammar:Lgroovyjarjarantlr/Grammar;
      24: invokevirtual #198                // Method groovyjarjarantlr/Grammar.getFilename:()Ljava/lang/String;
      27: aload_0
      28: invokevirtual #94                 // Method context:()Lgroovyjarjarantlr/BlockContext;
      31: getfield      #113                // Field groovyjarjarantlr/BlockContext.block:Lgroovyjarjarantlr/AlternativeBlock;
      34: invokevirtual #423                // Method groovyjarjarantlr/AlternativeBlock.getLine:()I
      37: aload_0
      38: invokevirtual #94                 // Method context:()Lgroovyjarjarantlr/BlockContext;
      41: getfield      #113                // Field groovyjarjarantlr/BlockContext.block:Lgroovyjarjarantlr/AlternativeBlock;
      44: invokevirtual #424                // Method groovyjarjarantlr/AlternativeBlock.getColumn:()I
      47: invokevirtual #208                // Method groovyjarjarantlr/Tool.error:(Ljava/lang/String;Ljava/lang/String;II)V
      50: new           #442                // class groovyjarjarantlr/SynPredBlock
      53: dup
      54: aload_0
      55: getfield      #43                 // Field grammar:Lgroovyjarjarantlr/Grammar;
      58: invokespecial #786                // Method groovyjarjarantlr/SynPredBlock."<init>":(Lgroovyjarjarantlr/Grammar;)V
      61: astore_1
      62: aload_1
      63: aload_0
      64: invokevirtual #94                 // Method context:()Lgroovyjarjarantlr/BlockContext;
      67: getfield      #113                // Field groovyjarjarantlr/BlockContext.block:Lgroovyjarjarantlr/AlternativeBlock;
      70: invokestatic  #512                // Method setBlock:(Lgroovyjarjarantlr/AlternativeBlock;Lgroovyjarjarantlr/AlternativeBlock;)V
      73: aload_0
      74: getfield      #30                 // Field blocks:Lgroovyjarjarantlr/collections/Stack;
      77: invokeinterface #434,  1          // InterfaceMethod groovyjarjarantlr/collections/Stack.pop:()Ljava/lang/Object;
      82: checkcast     #96                 // class groovyjarjarantlr/BlockContext
      85: astore_2
      86: aload_0
      87: getfield      #30                 // Field blocks:Lgroovyjarjarantlr/collections/Stack;
      90: new           #96                 // class groovyjarjarantlr/BlockContext
      93: dup
      94: invokespecial #162                // Method groovyjarjarantlr/BlockContext."<init>":()V
      97: invokeinterface #168,  2          // InterfaceMethod groovyjarjarantlr/collections/Stack.push:(Ljava/lang/Object;)V
     102: aload_0
     103: invokevirtual #94                 // Method context:()Lgroovyjarjarantlr/BlockContext;
     106: aload_1
     107: putfield      #113                // Field groovyjarjarantlr/BlockContext.block:Lgroovyjarjarantlr/AlternativeBlock;
     110: aload_0
     111: invokevirtual #94                 // Method context:()Lgroovyjarjarantlr/BlockContext;
     114: aload_2
     115: getfield      #183                // Field groovyjarjarantlr/BlockContext.blockEnd:Lgroovyjarjarantlr/BlockEndElement;
     118: putfield      #183                // Field groovyjarjarantlr/BlockContext.blockEnd:Lgroovyjarjarantlr/BlockEndElement;
     121: aload_0
     122: invokevirtual #94                 // Method context:()Lgroovyjarjarantlr/BlockContext;
     125: getfield      #183                // Field groovyjarjarantlr/BlockContext.blockEnd:Lgroovyjarjarantlr/BlockEndElement;
     128: aload_1
     129: putfield      #184                // Field groovyjarjarantlr/BlockEndElement.block:Lgroovyjarjarantlr/AlternativeBlock;
     132: return

  public void zeroOrMoreSubRule();
    Code:
       0: aload_0
       1: invokevirtual #94                 // Method context:()Lgroovyjarjarantlr/BlockContext;
       4: getfield      #113                // Field groovyjarjarantlr/BlockContext.block:Lgroovyjarjarantlr/AlternativeBlock;
       7: getfield      #440                // Field groovyjarjarantlr/AlternativeBlock.not:Z
      10: ifeq          50
      13: aload_0
      14: getfield      #53                 // Field tool:Lgroovyjarjarantlr/Tool;
      17: ldc_w         #789                // String \'~\' cannot be applied to (...)+ subrule
      20: aload_0
      21: getfield      #43                 // Field grammar:Lgroovyjarjarantlr/Grammar;
      24: invokevirtual #198                // Method groovyjarjarantlr/Grammar.getFilename:()Ljava/lang/String;
      27: aload_0
      28: invokevirtual #94                 // Method context:()Lgroovyjarjarantlr/BlockContext;
      31: getfield      #113                // Field groovyjarjarantlr/BlockContext.block:Lgroovyjarjarantlr/AlternativeBlock;
      34: invokevirtual #423                // Method groovyjarjarantlr/AlternativeBlock.getLine:()I
      37: aload_0
      38: invokevirtual #94                 // Method context:()Lgroovyjarjarantlr/BlockContext;
      41: getfield      #113                // Field groovyjarjarantlr/BlockContext.block:Lgroovyjarjarantlr/AlternativeBlock;
      44: invokevirtual #424                // Method groovyjarjarantlr/AlternativeBlock.getColumn:()I
      47: invokevirtual #208                // Method groovyjarjarantlr/Tool.error:(Ljava/lang/String;Ljava/lang/String;II)V
      50: new           #444                // class groovyjarjarantlr/ZeroOrMoreBlock
      53: dup
      54: aload_0
      55: getfield      #43                 // Field grammar:Lgroovyjarjarantlr/Grammar;
      58: invokespecial #790                // Method groovyjarjarantlr/ZeroOrMoreBlock."<init>":(Lgroovyjarjarantlr/Grammar;)V
      61: astore_1
      62: aload_1
      63: aload_0
      64: invokevirtual #94                 // Method context:()Lgroovyjarjarantlr/BlockContext;
      67: getfield      #113                // Field groovyjarjarantlr/BlockContext.block:Lgroovyjarjarantlr/AlternativeBlock;
      70: invokestatic  #512                // Method setBlock:(Lgroovyjarjarantlr/AlternativeBlock;Lgroovyjarjarantlr/AlternativeBlock;)V
      73: aload_0
      74: getfield      #30                 // Field blocks:Lgroovyjarjarantlr/collections/Stack;
      77: invokeinterface #434,  1          // InterfaceMethod groovyjarjarantlr/collections/Stack.pop:()Ljava/lang/Object;
      82: checkcast     #96                 // class groovyjarjarantlr/BlockContext
      85: astore_2
      86: aload_0
      87: getfield      #30                 // Field blocks:Lgroovyjarjarantlr/collections/Stack;
      90: new           #96                 // class groovyjarjarantlr/BlockContext
      93: dup
      94: invokespecial #162                // Method groovyjarjarantlr/BlockContext."<init>":()V
      97: invokeinterface #168,  2          // InterfaceMethod groovyjarjarantlr/collections/Stack.push:(Ljava/lang/Object;)V
     102: aload_0
     103: invokevirtual #94                 // Method context:()Lgroovyjarjarantlr/BlockContext;
     106: aload_1
     107: putfield      #113                // Field groovyjarjarantlr/BlockContext.block:Lgroovyjarjarantlr/AlternativeBlock;
     110: aload_0
     111: invokevirtual #94                 // Method context:()Lgroovyjarjarantlr/BlockContext;
     114: aload_2
     115: getfield      #183                // Field groovyjarjarantlr/BlockContext.blockEnd:Lgroovyjarjarantlr/BlockEndElement;
     118: putfield      #183                // Field groovyjarjarantlr/BlockContext.blockEnd:Lgroovyjarjarantlr/BlockEndElement;
     121: aload_0
     122: invokevirtual #94                 // Method context:()Lgroovyjarjarantlr/BlockContext;
     125: getfield      #183                // Field groovyjarjarantlr/BlockContext.blockEnd:Lgroovyjarjarantlr/BlockEndElement;
     128: aload_1
     129: putfield      #184                // Field groovyjarjarantlr/BlockEndElement.block:Lgroovyjarjarantlr/AlternativeBlock;
     132: return
}
