Compiled from "PreservingFileWriter.java"
public class groovyjarjarantlr.PreservingFileWriter extends java.io.FileWriter {
  protected java.io.File target_file;

  protected java.io.File tmp_file;

  public groovyjarjarantlr.PreservingFileWriter(java.lang.String) throws java.io.IOException;
    Code:
       0: aload_0
       1: new           #14                 // class java/lang/StringBuffer
       4: dup
       5: invokespecial #17                 // Method java/lang/StringBuffer."<init>":()V
       8: aload_1
       9: invokevirtual #21                 // Method java/lang/StringBuffer.append:(Ljava/lang/String;)Ljava/lang/StringBuffer;
      12: ldc           #23                 // String .antlr.tmp
      14: invokevirtual #21                 // Method java/lang/StringBuffer.append:(Ljava/lang/String;)Ljava/lang/StringBuffer;
      17: invokevirtual #27                 // Method java/lang/StringBuffer.toString:()Ljava/lang/String;
      20: invokespecial #29                 // Method java/io/FileWriter."<init>":(Ljava/lang/String;)V
      23: aload_0
      24: new           #31                 // class java/io/File
      27: dup
      28: aload_1
      29: invokespecial #32                 // Method java/io/File."<init>":(Ljava/lang/String;)V
      32: putfield      #34                 // Field target_file:Ljava/io/File;
      35: aload_0
      36: getfield      #34                 // Field target_file:Ljava/io/File;
      39: invokevirtual #37                 // Method java/io/File.getParent:()Ljava/lang/String;
      42: astore_2
      43: aload_2
      44: ifnull        134
      47: new           #31                 // class java/io/File
      50: dup
      51: aload_2
      52: invokespecial #32                 // Method java/io/File."<init>":(Ljava/lang/String;)V
      55: astore_3
      56: aload_3
      57: invokevirtual #41                 // Method java/io/File.exists:()Z
      60: ifne          95
      63: new           #12                 // class java/io/IOException
      66: dup
      67: new           #14                 // class java/lang/StringBuffer
      70: dup
      71: invokespecial #17                 // Method java/lang/StringBuffer."<init>":()V
      74: ldc           #43                 // String destination directory of \'
      76: invokevirtual #21                 // Method java/lang/StringBuffer.append:(Ljava/lang/String;)Ljava/lang/StringBuffer;
      79: aload_1
      80: invokevirtual #21                 // Method java/lang/StringBuffer.append:(Ljava/lang/String;)Ljava/lang/StringBuffer;
      83: ldc           #45                 // String \' doesn\'t exist
      85: invokevirtual #21                 // Method java/lang/StringBuffer.append:(Ljava/lang/String;)Ljava/lang/StringBuffer;
      88: invokevirtual #27                 // Method java/lang/StringBuffer.toString:()Ljava/lang/String;
      91: invokespecial #46                 // Method java/io/IOException."<init>":(Ljava/lang/String;)V
      94: athrow
      95: aload_3
      96: invokevirtual #49                 // Method java/io/File.canWrite:()Z
      99: ifne          134
     102: new           #12                 // class java/io/IOException
     105: dup
     106: new           #14                 // class java/lang/StringBuffer
     109: dup
     110: invokespecial #17                 // Method java/lang/StringBuffer."<init>":()V
     113: ldc           #43                 // String destination directory of \'
     115: invokevirtual #21                 // Method java/lang/StringBuffer.append:(Ljava/lang/String;)Ljava/lang/StringBuffer;
     118: aload_1
     119: invokevirtual #21                 // Method java/lang/StringBuffer.append:(Ljava/lang/String;)Ljava/lang/StringBuffer;
     122: ldc           #51                 // String \' isn\'t writeable
     124: invokevirtual #21                 // Method java/lang/StringBuffer.append:(Ljava/lang/String;)Ljava/lang/StringBuffer;
     127: invokevirtual #27                 // Method java/lang/StringBuffer.toString:()Ljava/lang/String;
     130: invokespecial #46                 // Method java/io/IOException."<init>":(Ljava/lang/String;)V
     133: athrow
     134: aload_0
     135: getfield      #34                 // Field target_file:Ljava/io/File;
     138: invokevirtual #41                 // Method java/io/File.exists:()Z
     141: ifeq          186
     144: aload_0
     145: getfield      #34                 // Field target_file:Ljava/io/File;
     148: invokevirtual #49                 // Method java/io/File.canWrite:()Z
     151: ifne          186
     154: new           #12                 // class java/io/IOException
     157: dup
     158: new           #14                 // class java/lang/StringBuffer
     161: dup
     162: invokespecial #17                 // Method java/lang/StringBuffer."<init>":()V
     165: ldc           #53                 // String cannot write to \'
     167: invokevirtual #21                 // Method java/lang/StringBuffer.append:(Ljava/lang/String;)Ljava/lang/StringBuffer;
     170: aload_1
     171: invokevirtual #21                 // Method java/lang/StringBuffer.append:(Ljava/lang/String;)Ljava/lang/StringBuffer;
     174: ldc           #55                 // String \'
     176: invokevirtual #21                 // Method java/lang/StringBuffer.append:(Ljava/lang/String;)Ljava/lang/StringBuffer;
     179: invokevirtual #27                 // Method java/lang/StringBuffer.toString:()Ljava/lang/String;
     182: invokespecial #46                 // Method java/io/IOException."<init>":(Ljava/lang/String;)V
     185: athrow
     186: aload_0
     187: new           #31                 // class java/io/File
     190: dup
     191: new           #14                 // class java/lang/StringBuffer
     194: dup
     195: invokespecial #17                 // Method java/lang/StringBuffer."<init>":()V
     198: aload_1
     199: invokevirtual #21                 // Method java/lang/StringBuffer.append:(Ljava/lang/String;)Ljava/lang/StringBuffer;
     202: ldc           #23                 // String .antlr.tmp
     204: invokevirtual #21                 // Method java/lang/StringBuffer.append:(Ljava/lang/String;)Ljava/lang/StringBuffer;
     207: invokevirtual #27                 // Method java/lang/StringBuffer.toString:()Ljava/lang/String;
     210: invokespecial #32                 // Method java/io/File."<init>":(Ljava/lang/String;)V
     213: putfield      #57                 // Field tmp_file:Ljava/io/File;
     216: return

  public void close() throws java.io.IOException;
    Code:
       0: aconst_null
       1: astore_1
       2: aconst_null
       3: astore_2
       4: aload_0
       5: invokespecial #60                 // Method java/io/FileWriter.close:()V
       8: sipush        1024
      11: newarray       char
      13: astore_3
      14: aload_0
      15: getfield      #34                 // Field target_file:Ljava/io/File;
      18: invokevirtual #64                 // Method java/io/File.length:()J
      21: aload_0
      22: getfield      #57                 // Field tmp_file:Ljava/io/File;
      25: invokevirtual #64                 // Method java/io/File.length:()J
      28: lcmp
      29: ifne          189
      32: sipush        1024
      35: newarray       char
      37: astore        4
      39: new           #66                 // class java/io/BufferedReader
      42: dup
      43: new           #68                 // class java/io/FileReader
      46: dup
      47: aload_0
      48: getfield      #57                 // Field tmp_file:Ljava/io/File;
      51: invokespecial #71                 // Method java/io/FileReader."<init>":(Ljava/io/File;)V
      54: invokespecial #74                 // Method java/io/BufferedReader."<init>":(Ljava/io/Reader;)V
      57: astore_1
      58: new           #66                 // class java/io/BufferedReader
      61: dup
      62: new           #68                 // class java/io/FileReader
      65: dup
      66: aload_0
      67: getfield      #34                 // Field target_file:Ljava/io/File;
      70: invokespecial #71                 // Method java/io/FileReader."<init>":(Ljava/io/File;)V
      73: invokespecial #74                 // Method java/io/BufferedReader."<init>":(Ljava/io/Reader;)V
      76: astore        5
      78: iconst_1
      79: istore        6
      81: iload         6
      83: ifeq          166
      86: aload_1
      87: aload_3
      88: iconst_0
      89: sipush        1024
      92: invokevirtual #80                 // Method java/io/Reader.read:([CII)I
      95: istore        7
      97: aload         5
      99: aload         4
     101: iconst_0
     102: sipush        1024
     105: invokevirtual #80                 // Method java/io/Reader.read:([CII)I
     108: istore        8
     110: iload         7
     112: iload         8
     114: if_icmpeq     123
     117: iconst_0
     118: istore        6
     120: goto          166
     123: iload         7
     125: iconst_m1
     126: if_icmpne     132
     129: goto          166
     132: iconst_0
     133: istore        9
     135: iload         9
     137: iload         7
     139: if_icmpge     81
     142: aload_3
     143: iload         9
     145: caload
     146: aload         4
     148: iload         9
     150: caload
     151: if_icmpeq     160
     154: iconst_0
     155: istore        6
     157: goto          81
     160: iinc          9, 1
     163: goto          135
     166: aload_1
     167: invokevirtual #81                 // Method java/io/Reader.close:()V
     170: aload         5
     172: invokevirtual #81                 // Method java/io/Reader.close:()V
     175: aconst_null
     176: dup
     177: astore        5
     179: astore_1
     180: iload         6
     182: ifeq          189
     185: jsr           272
     188: return
     189: new           #66                 // class java/io/BufferedReader
     192: dup
     193: new           #68                 // class java/io/FileReader
     196: dup
     197: aload_0
     198: getfield      #57                 // Field tmp_file:Ljava/io/File;
     201: invokespecial #71                 // Method java/io/FileReader."<init>":(Ljava/io/File;)V
     204: invokespecial #74                 // Method java/io/BufferedReader."<init>":(Ljava/io/Reader;)V
     207: astore_1
     208: new           #83                 // class java/io/BufferedWriter
     211: dup
     212: new           #4                  // class java/io/FileWriter
     215: dup
     216: aload_0
     217: getfield      #34                 // Field target_file:Ljava/io/File;
     220: invokespecial #84                 // Method java/io/FileWriter."<init>":(Ljava/io/File;)V
     223: invokespecial #87                 // Method java/io/BufferedWriter."<init>":(Ljava/io/Writer;)V
     226: astore_2
     227: aload_1
     228: aload_3
     229: iconst_0
     230: sipush        1024
     233: invokevirtual #80                 // Method java/io/Reader.read:([CII)I
     236: istore        10
     238: iload         10
     240: iconst_m1
     241: if_icmpne     247
     244: goto          258
     247: aload_2
     248: aload_3
     249: iconst_0
     250: iload         10
     252: invokevirtual #93                 // Method java/io/Writer.write:([CII)V
     255: goto          227
     258: jsr           272
     261: goto          332
     264: astore        11
     266: jsr           272
     269: aload         11
     271: athrow
     272: astore        12
     274: aload_1
     275: ifnull        287
     278: aload_1
     279: invokevirtual #81                 // Method java/io/Reader.close:()V
     282: goto          287
     285: astore        13
     287: aload_2
     288: ifnull        300
     291: aload_2
     292: invokevirtual #94                 // Method java/io/Writer.close:()V
     295: goto          300
     298: astore        13
     300: aload_0
     301: getfield      #57                 // Field tmp_file:Ljava/io/File;
     304: ifnull        330
     307: aload_0
     308: getfield      #57                 // Field tmp_file:Ljava/io/File;
     311: invokevirtual #41                 // Method java/io/File.exists:()Z
     314: ifeq          330
     317: aload_0
     318: getfield      #57                 // Field tmp_file:Ljava/io/File;
     321: invokevirtual #97                 // Method java/io/File.delete:()Z
     324: pop
     325: aload_0
     326: aconst_null
     327: putfield      #57                 // Field tmp_file:Ljava/io/File;
     330: ret           12
     332: return
    Exception table:
       from    to  target type
           4   188   264   any
         189   261   264   any
         264   269   264   any
         278   282   285   Class java/io/IOException
         291   295   298   Class java/io/IOException
}
