Compiled from "TokenStreamRecognitionException.java"
public class groovyjarjarantlr.TokenStreamRecognitionException extends groovyjarjarantlr.TokenStreamException {
  public groovyjarjarantlr.RecognitionException recog;

  public groovyjarjarantlr.TokenStreamRecognitionException(groovyjarjarantlr.RecognitionException);
    Code:
       0: aload_0
       1: aload_1
       2: invokevirtual #15                 // Method groovyjarjarantlr/RecognitionException.getMessage:()Ljava/lang/String;
       5: invokespecial #18                 // Method groovyjarjarantlr/TokenStreamException."<init>":(Ljava/lang/String;)V
       8: aload_0
       9: aload_1
      10: putfield      #20                 // Field recog:Lgroovyjarjarantlr/RecognitionException;
      13: return

  public java.lang.String toString();
    Code:
       0: aload_0
       1: getfield      #20                 // Field recog:Lgroovyjarjarantlr/RecognitionException;
       4: invokevirtual #23                 // Method groovyjarjarantlr/RecognitionException.toString:()Ljava/lang/String;
       7: areturn
}
