Compiled from "time.scala"
public final class scalaz.std.java.time {
  public static scalaz.Enum<java.time.Month> monthInstance();
    Code:
       0: getstatic     #17                 // Field scalaz/std/java/time$.MODULE$:Lscalaz/std/java/time$;
       3: invokevirtual #19                 // Method scalaz/std/java/time$.monthInstance:()Lscalaz/Enum;
       6: areturn

  public static scalaz.Enum<java.time.LocalDate> localDateInstance();
    Code:
       0: getstatic     #17                 // Field scalaz/std/java/time$.MODULE$:Lscalaz/std/java/time$;
       3: invokevirtual #23                 // Method scalaz/std/java/time$.localDateInstance:()Lscalaz/Enum;
       6: areturn

  public static scalaz.Enum<java.time.Year> yearInstance();
    Code:
       0: getstatic     #17                 // Field scalaz/std/java/time$.MODULE$:Lscalaz/std/java/time$;
       3: invokevirtual #27                 // Method scalaz/std/java/time$.yearInstance:()Lscalaz/Enum;
       6: areturn

  public static scalaz.Order<java.time.LocalTime> localTimeInstance();
    Code:
       0: getstatic     #17                 // Field scalaz/std/java/time$.MODULE$:Lscalaz/std/java/time$;
       3: invokevirtual #32                 // Method scalaz/std/java/time$.localTimeInstance:()Lscalaz/Order;
       6: areturn

  public static scalaz.Order<java.time.MonthDay> monthDayInstance();
    Code:
       0: getstatic     #17                 // Field scalaz/std/java/time$.MODULE$:Lscalaz/std/java/time$;
       3: invokevirtual #36                 // Method scalaz/std/java/time$.monthDayInstance:()Lscalaz/Order;
       6: areturn

  public static scalaz.Enum<java.time.YearMonth> yearMonthInstance();
    Code:
       0: getstatic     #17                 // Field scalaz/std/java/time$.MODULE$:Lscalaz/std/java/time$;
       3: invokevirtual #40                 // Method scalaz/std/java/time$.yearMonthInstance:()Lscalaz/Enum;
       6: areturn

  public static scalaz.Monoid<java.time.Period> periodInstance();
    Code:
       0: getstatic     #17                 // Field scalaz/std/java/time$.MODULE$:Lscalaz/std/java/time$;
       3: invokevirtual #45                 // Method scalaz/std/java/time$.periodInstance:()Lscalaz/Monoid;
       6: areturn

  public static scalaz.Monoid<java.time.Duration> durationInstance();
    Code:
       0: getstatic     #17                 // Field scalaz/std/java/time$.MODULE$:Lscalaz/std/java/time$;
       3: invokevirtual #49                 // Method scalaz/std/java/time$.durationInstance:()Lscalaz/Monoid;
       6: areturn

  public static scalaz.Order<java.time.Instant> instantInstance();
    Code:
       0: getstatic     #17                 // Field scalaz/std/java/time$.MODULE$:Lscalaz/std/java/time$;
       3: invokevirtual #53                 // Method scalaz/std/java/time$.instantInstance:()Lscalaz/Order;
       6: areturn

  public static scalaz.Enum<java.time.DayOfWeek> dayOfWeekInstance();
    Code:
       0: getstatic     #17                 // Field scalaz/std/java/time$.MODULE$:Lscalaz/std/java/time$;
       3: invokevirtual #57                 // Method scalaz/std/java/time$.dayOfWeekInstance:()Lscalaz/Enum;
       6: areturn

  public static scalaz.Order<java.time.ZoneOffset> zoneOffsetInstance();
    Code:
       0: getstatic     #17                 // Field scalaz/std/java/time$.MODULE$:Lscalaz/std/java/time$;
       3: invokevirtual #61                 // Method scalaz/std/java/time$.zoneOffsetInstance:()Lscalaz/Order;
       6: areturn

  public static scalaz.Order<java.time.ZonedDateTime> zonedDateTime();
    Code:
       0: getstatic     #17                 // Field scalaz/std/java/time$.MODULE$:Lscalaz/std/java/time$;
       3: invokevirtual #65                 // Method scalaz/std/java/time$.zonedDateTime:()Lscalaz/Order;
       6: areturn

  public static scalaz.Order<java.time.OffsetTime> offsetTimeInstance();
    Code:
       0: getstatic     #17                 // Field scalaz/std/java/time$.MODULE$:Lscalaz/std/java/time$;
       3: invokevirtual #69                 // Method scalaz/std/java/time$.offsetTimeInstance:()Lscalaz/Order;
       6: areturn

  public static scalaz.Order<java.time.OffsetDateTime> offsetDateTimeInstance();
    Code:
       0: getstatic     #17                 // Field scalaz/std/java/time$.MODULE$:Lscalaz/std/java/time$;
       3: invokevirtual #73                 // Method scalaz/std/java/time$.offsetDateTimeInstance:()Lscalaz/Order;
       6: areturn

  public static scalaz.Order<java.time.LocalDateTime> localDateTimeInstance();
    Code:
       0: getstatic     #17                 // Field scalaz/std/java/time$.MODULE$:Lscalaz/std/java/time$;
       3: invokevirtual #77                 // Method scalaz/std/java/time$.localDateTimeInstance:()Lscalaz/Order;
       6: areturn
}
