Compiled from "GoogleResponseParser.java"
public class net.sf.okapi.connectors.google.GoogleResponseParser {
  private org.json.simple.parser.JSONParser parser;

  public net.sf.okapi.connectors.google.GoogleResponseParser();
    Code:
       0: aload_0
       1: invokespecial #1                  // Method java/lang/Object."<init>":()V
       4: aload_0
       5: new           #2                  // class org/json/simple/parser/JSONParser
       8: dup
       9: invokespecial #3                  // Method org/json/simple/parser/JSONParser."<init>":()V
      12: putfield      #4                  // Field parser:Lorg/json/simple/parser/JSONParser;
      15: return

  public java.util.List<java.lang.String> parseResponse(java.io.Reader) throws java.io.IOException, org.json.simple.parser.ParseException;
    Code:
       0: aload_0
       1: aload_1
       2: ldc           #5                  // String translations
       4: ldc           #6                  // String translatedText
       6: invokevirtual #7                  // Method parseArrayResponse:(Ljava/io/Reader;Ljava/lang/String;Ljava/lang/String;)Ljava/util/List;
       9: areturn

  public java.util.List<java.lang.String> parseLanguagesResponse(java.io.Reader) throws java.io.IOException, org.json.simple.parser.ParseException;
    Code:
       0: aload_0
       1: aload_1
       2: ldc           #8                  // String languages
       4: ldc           #9                  // String language
       6: invokevirtual #7                  // Method parseArrayResponse:(Ljava/io/Reader;Ljava/lang/String;Ljava/lang/String;)Ljava/util/List;
       9: areturn

  protected java.util.List<java.lang.String> parseArrayResponse(java.io.Reader, java.lang.String, java.lang.String) throws java.io.IOException, org.json.simple.parser.ParseException;
    Code:
       0: aload_0
       1: getfield      #4                  // Field parser:Lorg/json/simple/parser/JSONParser;
       4: aload_1
       5: invokevirtual #10                 // Method org/json/simple/parser/JSONParser.parse:(Ljava/io/Reader;)Ljava/lang/Object;
       8: checkcast     #11                 // class org/json/simple/JSONObject
      11: astore        4
      13: aload_0
      14: aload_0
      15: aload         4
      17: ldc           #12                 // String data
      19: invokevirtual #13                 // Method require:(Lorg/json/simple/JSONObject;Ljava/lang/String;)Lorg/json/simple/JSONObject;
      22: aload_2
      23: invokevirtual #14                 // Method requireArray:(Lorg/json/simple/JSONObject;Ljava/lang/String;)Lorg/json/simple/JSONArray;
      26: astore        5
      28: new           #15                 // class java/util/ArrayList
      31: dup
      32: invokespecial #16                 // Method java/util/ArrayList."<init>":()V
      35: astore        6
      37: aload         5
      39: invokevirtual #17                 // Method org/json/simple/JSONArray.iterator:()Ljava/util/Iterator;
      42: astore        7
      44: aload         7
      46: invokeinterface #18,  1           // InterfaceMethod java/util/Iterator.hasNext:()Z
      51: ifeq          96
      54: aload         7
      56: invokeinterface #19,  1           // InterfaceMethod java/util/Iterator.next:()Ljava/lang/Object;
      61: astore        8
      63: aload         8
      65: instanceof    #11                 // class org/json/simple/JSONObject
      68: ifeq          93
      71: aload         6
      73: aload_0
      74: aload_0
      75: aload         8
      77: checkcast     #11                 // class org/json/simple/JSONObject
      80: aload_3
      81: invokevirtual #20                 // Method requireString:(Lorg/json/simple/JSONObject;Ljava/lang/String;)Ljava/lang/String;
      84: invokevirtual #21                 // Method unescapeTranslation:(Ljava/lang/String;)Ljava/lang/String;
      87: invokeinterface #22,  2           // InterfaceMethod java/util/List.add:(Ljava/lang/Object;)Z
      92: pop
      93: goto          44
      96: aload         6
      98: areturn

  public net.sf.okapi.connectors.google.GoogleMTErrorException parseError(int, java.lang.String, java.lang.String) throws java.io.IOException, org.json.simple.parser.ParseException;
    Code:
       0: aload_0
       1: getfield      #4                  // Field parser:Lorg/json/simple/parser/JSONParser;
       4: aload_2
       5: invokevirtual #23                 // Method org/json/simple/parser/JSONParser.parse:(Ljava/lang/String;)Ljava/lang/Object;
       8: checkcast     #11                 // class org/json/simple/JSONObject
      11: astore        4
      13: aload_0
      14: aload         4
      16: ldc           #24                 // String error
      18: invokevirtual #13                 // Method require:(Lorg/json/simple/JSONObject;Ljava/lang/String;)Lorg/json/simple/JSONObject;
      21: astore        4
      23: aload_0
      24: aload         4
      26: ldc           #25                 // String errors
      28: invokevirtual #14                 // Method requireArray:(Lorg/json/simple/JSONObject;Ljava/lang/String;)Lorg/json/simple/JSONArray;
      31: iconst_0
      32: invokevirtual #26                 // Method org/json/simple/JSONArray.get:(I)Ljava/lang/Object;
      35: checkcast     #11                 // class org/json/simple/JSONObject
      38: astore        5
      40: new           #27                 // class net/sf/okapi/connectors/google/GoogleMTErrorException
      43: dup
      44: aload_0
      45: aload         4
      47: ldc           #28                 // String code
      49: invokevirtual #29                 // Method requireLong:(Lorg/json/simple/JSONObject;Ljava/lang/String;)J
      52: l2i
      53: aload_0
      54: aload         5
      56: ldc           #30                 // String message
      58: invokevirtual #20                 // Method requireString:(Lorg/json/simple/JSONObject;Ljava/lang/String;)Ljava/lang/String;
      61: aload_0
      62: aload         5
      64: ldc           #31                 // String domain
      66: invokevirtual #20                 // Method requireString:(Lorg/json/simple/JSONObject;Ljava/lang/String;)Ljava/lang/String;
      69: aload_0
      70: aload         5
      72: ldc           #32                 // String reason
      74: invokevirtual #20                 // Method requireString:(Lorg/json/simple/JSONObject;Ljava/lang/String;)Ljava/lang/String;
      77: aload_3
      78: invokespecial #33                 // Method net/sf/okapi/connectors/google/GoogleMTErrorException."<init>":(ILjava/lang/String;Ljava/lang/String;Ljava/lang/String;Ljava/lang/String;)V
      81: areturn
      82: astore        4
      84: new           #27                 // class net/sf/okapi/connectors/google/GoogleMTErrorException
      87: dup
      88: iload_1
      89: aload_2
      90: invokedynamic #35,  0             // InvokeDynamic #0:makeConcatWithConstants:(Ljava/lang/String;)Ljava/lang/String;
      95: ldc           #36                 // String
      97: ldc           #36                 // String
      99: aload_3
     100: invokespecial #33                 // Method net/sf/okapi/connectors/google/GoogleMTErrorException."<init>":(ILjava/lang/String;Ljava/lang/String;Ljava/lang/String;Ljava/lang/String;)V
     103: areturn
    Exception table:
       from    to  target type
           0    81    82   Class java/lang/Exception

  private java.lang.String unescapeTranslation(java.lang.String);
    Code:
       0: aload_1
       1: ldc           #37                 // String &#39;
       3: ldc           #38                 // String \'
       5: invokevirtual #39                 // Method java/lang/String.replace:(Ljava/lang/CharSequence;Ljava/lang/CharSequence;)Ljava/lang/String;
       8: astore_1
       9: aload_1
      10: ldc           #40                 // String &lt;
      12: ldc           #41                 // String <
      14: invokevirtual #39                 // Method java/lang/String.replace:(Ljava/lang/CharSequence;Ljava/lang/CharSequence;)Ljava/lang/String;
      17: astore_1
      18: aload_1
      19: ldc           #42                 // String &gt;
      21: ldc           #43                 // String >
      23: invokevirtual #39                 // Method java/lang/String.replace:(Ljava/lang/CharSequence;Ljava/lang/CharSequence;)Ljava/lang/String;
      26: astore_1
      27: aload_1
      28: ldc           #44                 // String &quot;
      30: ldc           #45                 // String \"
      32: invokevirtual #39                 // Method java/lang/String.replace:(Ljava/lang/CharSequence;Ljava/lang/CharSequence;)Ljava/lang/String;
      35: astore_1
      36: aload_1
      37: ldc           #46                 // String &amp;
      39: ldc           #47                 // String &
      41: invokevirtual #39                 // Method java/lang/String.replace:(Ljava/lang/CharSequence;Ljava/lang/CharSequence;)Ljava/lang/String;
      44: areturn

  private org.json.simple.JSONObject require(org.json.simple.JSONObject, java.lang.String);
    Code:
       0: aload_1
       1: aload_2
       2: invokevirtual #48                 // Method org/json/simple/JSONObject.get:(Ljava/lang/Object;)Ljava/lang/Object;
       5: astore_3
       6: aload_3
       7: ifnull        17
      10: aload_3
      11: instanceof    #11                 // class org/json/simple/JSONObject
      14: ifne          31
      17: new           #49                 // class java/lang/IllegalArgumentException
      20: dup
      21: aload_2
      22: invokedynamic #50,  0             // InvokeDynamic #1:makeConcatWithConstants:(Ljava/lang/String;)Ljava/lang/String;
      27: invokespecial #51                 // Method java/lang/IllegalArgumentException."<init>":(Ljava/lang/String;)V
      30: athrow
      31: aload_3
      32: checkcast     #11                 // class org/json/simple/JSONObject
      35: areturn

  private java.lang.String requireString(org.json.simple.JSONObject, java.lang.String);
    Code:
       0: aload_1
       1: aload_2
       2: invokevirtual #48                 // Method org/json/simple/JSONObject.get:(Ljava/lang/Object;)Ljava/lang/Object;
       5: astore_3
       6: aload_3
       7: ifnull        17
      10: aload_3
      11: instanceof    #52                 // class java/lang/String
      14: ifne          31
      17: new           #49                 // class java/lang/IllegalArgumentException
      20: dup
      21: aload_2
      22: invokedynamic #50,  0             // InvokeDynamic #1:makeConcatWithConstants:(Ljava/lang/String;)Ljava/lang/String;
      27: invokespecial #51                 // Method java/lang/IllegalArgumentException."<init>":(Ljava/lang/String;)V
      30: athrow
      31: aload_3
      32: checkcast     #52                 // class java/lang/String
      35: areturn

  private long requireLong(org.json.simple.JSONObject, java.lang.String);
    Code:
       0: aload_1
       1: aload_2
       2: invokevirtual #48                 // Method org/json/simple/JSONObject.get:(Ljava/lang/Object;)Ljava/lang/Object;
       5: astore_3
       6: aload_3
       7: ifnull        17
      10: aload_3
      11: instanceof    #53                 // class java/lang/Long
      14: ifne          31
      17: new           #49                 // class java/lang/IllegalArgumentException
      20: dup
      21: aload_2
      22: invokedynamic #50,  0             // InvokeDynamic #1:makeConcatWithConstants:(Ljava/lang/String;)Ljava/lang/String;
      27: invokespecial #51                 // Method java/lang/IllegalArgumentException."<init>":(Ljava/lang/String;)V
      30: athrow
      31: aload_3
      32: checkcast     #53                 // class java/lang/Long
      35: invokevirtual #54                 // Method java/lang/Long.longValue:()J
      38: lreturn

  private org.json.simple.JSONArray requireArray(org.json.simple.JSONObject, java.lang.String);
    Code:
       0: aload_1
       1: aload_2
       2: invokevirtual #48                 // Method org/json/simple/JSONObject.get:(Ljava/lang/Object;)Ljava/lang/Object;
       5: astore_3
       6: aload_3
       7: ifnull        17
      10: aload_3
      11: instanceof    #55                 // class org/json/simple/JSONArray
      14: ifne          31
      17: new           #49                 // class java/lang/IllegalArgumentException
      20: dup
      21: aload_2
      22: invokedynamic #56,  0             // InvokeDynamic #2:makeConcatWithConstants:(Ljava/lang/String;)Ljava/lang/String;
      27: invokespecial #51                 // Method java/lang/IllegalArgumentException."<init>":(Ljava/lang/String;)V
      30: athrow
      31: aload_3
      32: checkcast     #55                 // class org/json/simple/JSONArray
      35: areturn
}
