Compiled from "GoogleMTv2Parameters.java"
public class net.sf.okapi.connectors.google.GoogleMTv2Parameters extends net.sf.okapi.common.StringParameters implements net.sf.okapi.common.uidescription.IEditorDescriptionProvider {
  private static final java.lang.String APIKEY;

  private static final java.lang.String RETRY_MS;

  private static final java.lang.String RETRY_COUNT;

  private static final java.lang.String FAILURES_BEFORE_ABORT;

  private static final java.lang.String USE_PBMT;

  public net.sf.okapi.connectors.google.GoogleMTv2Parameters();
    Code:
       0: aload_0
       1: invokespecial #1                  // Method net/sf/okapi/common/StringParameters."<init>":()V
       4: return

  public java.lang.String getApiKey();
    Code:
       0: aload_0
       1: ldc           #3                  // String apiKey
       3: invokevirtual #4                  // Method getString:(Ljava/lang/String;)Ljava/lang/String;
       6: invokevirtual #5                  // Method java/lang/String.trim:()Ljava/lang/String;
       9: areturn

  public void setApiKey(java.lang.String);
    Code:
       0: aload_1
       1: ifnull        9
       4: aload_1
       5: invokevirtual #5                  // Method java/lang/String.trim:()Ljava/lang/String;
       8: astore_1
       9: aload_0
      10: ldc           #3                  // String apiKey
      12: aload_1
      13: invokevirtual #6                  // Method setString:(Ljava/lang/String;Ljava/lang/String;)V
      16: return

  public int getRetryIntervalMs();
    Code:
       0: aload_0
       1: ldc           #7                  // String retryIntervalMs
       3: invokevirtual #8                  // Method getInteger:(Ljava/lang/String;)I
       6: ireturn

  public void setRetryIntervalMs(int);
    Code:
       0: aload_0
       1: ldc           #7                  // String retryIntervalMs
       3: iload_1
       4: invokevirtual #9                  // Method setInteger:(Ljava/lang/String;I)V
       7: return

  public int getRetryCount();
    Code:
       0: aload_0
       1: ldc           #10                 // String retryCount
       3: invokevirtual #8                  // Method getInteger:(Ljava/lang/String;)I
       6: ireturn

  public void setRetryCount(int);
    Code:
       0: aload_0
       1: ldc           #10                 // String retryCount
       3: iload_1
       4: invokevirtual #9                  // Method setInteger:(Ljava/lang/String;I)V
       7: return

  public boolean getUsePBMT();
    Code:
       0: aload_0
       1: ldc           #11                 // String usePBMT
       3: invokevirtual #12                 // Method getBoolean:(Ljava/lang/String;)Z
       6: ireturn

  public void setUsePBMT(boolean);
    Code:
       0: aload_0
       1: ldc           #11                 // String usePBMT
       3: iload_1
       4: invokevirtual #13                 // Method setBoolean:(Ljava/lang/String;Z)V
       7: return

  public int getFailuresBeforeAbort();
    Code:
       0: aload_0
       1: ldc           #14                 // String failuresBeforeAbort
       3: invokevirtual #8                  // Method getInteger:(Ljava/lang/String;)I
       6: ireturn

  public void setFailuresBeforeAbort(int);
    Code:
       0: aload_0
       1: ldc           #14                 // String failuresBeforeAbort
       3: iload_1
       4: invokevirtual #9                  // Method setInteger:(Ljava/lang/String;I)V
       7: return

  public void reset();
    Code:
       0: aload_0
       1: invokespecial #15                 // Method net/sf/okapi/common/StringParameters.reset:()V
       4: aload_0
       5: ldc           #16                 // String
       7: invokevirtual #17                 // Method setApiKey:(Ljava/lang/String;)V
      10: aload_0
      11: iconst_0
      12: invokevirtual #18                 // Method setUsePBMT:(Z)V
      15: aload_0
      16: sipush        10000
      19: invokevirtual #19                 // Method setRetryIntervalMs:(I)V
      22: aload_0
      23: bipush        10
      25: invokevirtual #20                 // Method setRetryCount:(I)V
      28: aload_0
      29: iconst_m1
      30: invokevirtual #21                 // Method setFailuresBeforeAbort:(I)V
      33: return

  public net.sf.okapi.common.ParametersDescription getParametersDescription();
    Code:
       0: new           #22                 // class net/sf/okapi/common/ParametersDescription
       3: dup
       4: aload_0
       5: invokespecial #23                 // Method net/sf/okapi/common/ParametersDescription."<init>":(Ljava/lang/Object;)V
       8: astore_1
       9: aload_1
      10: ldc           #3                  // String apiKey
      12: ldc           #24                 // String Google API key
      14: ldc           #25                 // String The Google API key to identify the application/user
      16: invokevirtual #26                 // Method net/sf/okapi/common/ParametersDescription.add:(Ljava/lang/String;Ljava/lang/String;Ljava/lang/String;)Lnet/sf/okapi/common/ParameterDescriptor;
      19: pop
      20: aload_1
      21: ldc           #11                 // String usePBMT
      23: ldc           #27                 // String Use Phrase-Based MT
      25: ldc           #28                 // String Use the legacy PBMT system rather than Neural MT
      27: invokevirtual #26                 // Method net/sf/okapi/common/ParametersDescription.add:(Ljava/lang/String;Ljava/lang/String;Ljava/lang/String;)Lnet/sf/okapi/common/ParameterDescriptor;
      30: pop
      31: aload_1
      32: ldc           #10                 // String retryCount
      34: ldc           #29                 // String Retry Count
      36: ldc           #30                 // String Number of retries to attempt before failing
      38: invokevirtual #26                 // Method net/sf/okapi/common/ParametersDescription.add:(Ljava/lang/String;Ljava/lang/String;Ljava/lang/String;)Lnet/sf/okapi/common/ParameterDescriptor;
      41: pop
      42: aload_1
      43: ldc           #7                  // String retryIntervalMs
      45: ldc           #31                 // String Retry Interval (ms)
      47: ldc           #32                 // String Time to wait before retrying a failed query
      49: invokevirtual #26                 // Method net/sf/okapi/common/ParametersDescription.add:(Ljava/lang/String;Ljava/lang/String;Ljava/lang/String;)Lnet/sf/okapi/common/ParameterDescriptor;
      52: pop
      53: aload_1
      54: ldc           #14                 // String failuresBeforeAbort
      56: ldc           #33                 // String Failures before abort
      58: ldc           #34                 // String Number of times we let queries fail (after retries) before aborting the process
      60: invokevirtual #26                 // Method net/sf/okapi/common/ParametersDescription.add:(Ljava/lang/String;Ljava/lang/String;Ljava/lang/String;)Lnet/sf/okapi/common/ParameterDescriptor;
      63: pop
      64: aload_1
      65: areturn

  public net.sf.okapi.common.uidescription.EditorDescription createEditorDescription(net.sf.okapi.common.ParametersDescription);
    Code:
       0: new           #35                 // class net/sf/okapi/common/uidescription/EditorDescription
       3: dup
       4: ldc           #36                 // String Google Translate v2 Connector Settings
       6: iconst_1
       7: iconst_0
       8: invokespecial #37                 // Method net/sf/okapi/common/uidescription/EditorDescription."<init>":(Ljava/lang/String;ZZ)V
      11: astore_2
      12: aload_2
      13: aload_1
      14: ldc           #3                  // String apiKey
      16: invokevirtual #38                 // Method net/sf/okapi/common/ParametersDescription.get:(Ljava/lang/String;)Lnet/sf/okapi/common/ParameterDescriptor;
      19: invokevirtual #39                 // Method net/sf/okapi/common/uidescription/EditorDescription.addTextInputPart:(Lnet/sf/okapi/common/ParameterDescriptor;)Lnet/sf/okapi/common/uidescription/TextInputPart;
      22: astore_3
      23: aload_3
      24: iconst_1
      25: invokevirtual #40                 // Method net/sf/okapi/common/uidescription/TextInputPart.setPassword:(Z)V
      28: aload_2
      29: aload_1
      30: ldc           #11                 // String usePBMT
      32: invokevirtual #38                 // Method net/sf/okapi/common/ParametersDescription.get:(Ljava/lang/String;)Lnet/sf/okapi/common/ParameterDescriptor;
      35: invokevirtual #41                 // Method net/sf/okapi/common/uidescription/EditorDescription.addCheckboxPart:(Lnet/sf/okapi/common/ParameterDescriptor;)Lnet/sf/okapi/common/uidescription/CheckboxPart;
      38: pop
      39: aload_2
      40: aload_1
      41: ldc           #10                 // String retryCount
      43: invokevirtual #38                 // Method net/sf/okapi/common/ParametersDescription.get:(Ljava/lang/String;)Lnet/sf/okapi/common/ParameterDescriptor;
      46: invokevirtual #39                 // Method net/sf/okapi/common/uidescription/EditorDescription.addTextInputPart:(Lnet/sf/okapi/common/ParameterDescriptor;)Lnet/sf/okapi/common/uidescription/TextInputPart;
      49: pop
      50: aload_2
      51: aload_1
      52: ldc           #7                  // String retryIntervalMs
      54: invokevirtual #38                 // Method net/sf/okapi/common/ParametersDescription.get:(Ljava/lang/String;)Lnet/sf/okapi/common/ParameterDescriptor;
      57: invokevirtual #39                 // Method net/sf/okapi/common/uidescription/EditorDescription.addTextInputPart:(Lnet/sf/okapi/common/ParameterDescriptor;)Lnet/sf/okapi/common/uidescription/TextInputPart;
      60: pop
      61: aload_2
      62: aload_1
      63: ldc           #14                 // String failuresBeforeAbort
      65: invokevirtual #38                 // Method net/sf/okapi/common/ParametersDescription.get:(Ljava/lang/String;)Lnet/sf/okapi/common/ParameterDescriptor;
      68: invokevirtual #39                 // Method net/sf/okapi/common/uidescription/EditorDescription.addTextInputPart:(Lnet/sf/okapi/common/ParameterDescriptor;)Lnet/sf/okapi/common/uidescription/TextInputPart;
      71: pop
      72: aload_2
      73: areturn
}
