Compiled from "ActorProcessor.scala"
public final class akka.stream.impl.ActorProcessor$ {
  public static final akka.stream.impl.ActorProcessor$ MODULE$;

  public static {};
    Code:
       0: new           #2                  // class akka/stream/impl/ActorProcessor$
       3: invokespecial #12                 // Method "<init>":()V
       6: return

  public <I, O> akka.stream.impl.ActorProcessor<I, O> apply(akka.actor.ActorRef);
    Code:
       0: new           #16                 // class akka/stream/impl/ActorProcessor
       3: dup
       4: aload_1
       5: invokespecial #19                 // Method akka/stream/impl/ActorProcessor."<init>":(Lakka/actor/ActorRef;)V
       8: astore_2
       9: getstatic     #24                 // Field akka/actor/package$.MODULE$:Lakka/actor/package$;
      12: aload_1
      13: invokevirtual #28                 // Method akka/actor/package$.actorRef2Scala:(Lakka/actor/ActorRef;)Lakka/actor/ScalaActorRef;
      16: astore_3
      17: new           #30                 // class akka/stream/impl/ExposedPublisher
      20: dup
      21: aload_2
      22: invokespecial #33                 // Method akka/stream/impl/ExposedPublisher."<init>":(Lakka/stream/impl/ActorPublisher;)V
      25: astore        4
      27: aload_3
      28: aload         4
      30: invokeinterface #39,  2           // InterfaceMethod akka/actor/ScalaActorRef.$bang$default$2:(Ljava/lang/Object;)Lakka/actor/ActorRef;
      35: astore        5
      37: aload_3
      38: aload         4
      40: aload         5
      42: invokeinterface #43,  3           // InterfaceMethod akka/actor/ScalaActorRef.$bang:(Ljava/lang/Object;Lakka/actor/ActorRef;)V
      47: aload_2
      48: areturn

  private akka.stream.impl.ActorProcessor$();
    Code:
       0: aload_0
       1: invokespecial #54                 // Method java/lang/Object."<init>":()V
       4: aload_0
       5: putstatic     #56                 // Field MODULE$:Lakka/stream/impl/ActorProcessor$;
       8: return
}
