Compiled from "Buffers.scala"
public final class akka.stream.impl.BoundedBuffer$DynamicQueue extends java.util.LinkedList<T> implements akka.stream.impl.Buffer<T> {
  private final akka.stream.impl.BoundedBuffer $outer;

  public int capacity();
    Code:
       0: aload_0
       1: getfield      #14                 // Field $outer:Lakka/stream/impl/BoundedBuffer;
       4: invokevirtual #18                 // Method akka/stream/impl/BoundedBuffer.capacity:()I
       7: ireturn

  public int used();
    Code:
       0: aload_0
       1: invokevirtual #24                 // Method size:()I
       4: ireturn

  public boolean isFull();
    Code:
       0: aload_0
       1: invokevirtual #24                 // Method size:()I
       4: aload_0
       5: invokevirtual #27                 // Method capacity:()I
       8: if_icmpne     15
      11: iconst_1
      12: goto          16
      15: iconst_0
      16: ireturn

  public boolean nonEmpty();
    Code:
       0: aload_0
       1: invokevirtual #31                 // Method isEmpty:()Z
       4: ifeq          11
       7: iconst_0
       8: goto          12
      11: iconst_1
      12: ireturn

  public void enqueue(T);
    Code:
       0: aload_0
       1: aload_1
       2: invokevirtual #37                 // Method add:(Ljava/lang/Object;)Z
       5: pop
       6: return

  public T dequeue();
    Code:
       0: aload_0
       1: invokevirtual #44                 // Method remove:()Ljava/lang/Object;
       4: areturn

  public void dropHead();
    Code:
       0: aload_0
       1: invokevirtual #44                 // Method remove:()Ljava/lang/Object;
       4: pop
       5: return

  public void dropTail();
    Code:
       0: aload_0
       1: invokevirtual #50                 // Method removeLast:()Ljava/lang/Object;
       4: pop
       5: return

  public akka.stream.impl.BoundedBuffer$DynamicQueue(akka.stream.impl.BoundedBuffer<T>, int);
    Code:
       0: aload_1
       1: ifnonnull     6
       4: aconst_null
       5: athrow
       6: aload_0
       7: aload_1
       8: putfield      #14                 // Field $outer:Lakka/stream/impl/BoundedBuffer;
      11: aload_0
      12: invokespecial #54                 // Method java/util/LinkedList."<init>":()V
      15: return
}
