Compiled from "FanoutProcessor.scala"
public final class akka.stream.impl.FanoutOutputs$$anonfun$waitingExposedPublisher$1 extends scala.runtime.AbstractPartialFunction<java.lang.Object, scala.runtime.BoxedUnit> implements scala.Serializable {
  public static final long serialVersionUID;

  private final akka.stream.impl.FanoutOutputs $outer;

  public final <A1, B1> B1 applyOrElse(A1, scala.Function1<A1, B1>);
    Code:
       0: aload_1
       1: astore_3
       2: aload_3
       3: instanceof    #23                 // class akka/stream/impl/ExposedPublisher
       6: ifeq          56
       9: aload_3
      10: checkcast     #23                 // class akka/stream/impl/ExposedPublisher
      13: astore        4
      15: aload         4
      17: invokevirtual #27                 // Method akka/stream/impl/ExposedPublisher.publisher:()Lakka/stream/impl/ActorPublisher;
      20: astore        5
      22: aload_0
      23: getfield      #29                 // Field $outer:Lakka/stream/impl/FanoutOutputs;
      26: aload         5
      28: invokevirtual #33                 // Method akka/stream/impl/FanoutOutputs.exposedPublisher_$eq:(Lakka/stream/impl/ActorPublisher;)V
      31: aload_0
      32: getfield      #29                 // Field $outer:Lakka/stream/impl/FanoutOutputs;
      35: invokevirtual #37                 // Method akka/stream/impl/FanoutOutputs.subreceive:()Lakka/stream/impl/SubReceive;
      38: aload_0
      39: getfield      #29                 // Field $outer:Lakka/stream/impl/FanoutOutputs;
      42: invokevirtual #40                 // Method akka/stream/impl/FanoutOutputs.downstreamRunning:()Lscala/PartialFunction;
      45: invokevirtual #46                 // Method akka/stream/impl/SubReceive.become:(Lscala/PartialFunction;)V
      48: getstatic     #52                 // Field scala/runtime/BoxedUnit.UNIT:Lscala/runtime/BoxedUnit;
      51: astore        6
      53: aload         6
      55: areturn
      56: new           #54                 // class java/lang/IllegalStateException
      59: dup
      60: new           #56                 // class scala/StringContext
      63: dup
      64: getstatic     #62                 // Field scala/Predef$.MODULE$:Lscala/Predef$;
      67: iconst_2
      68: anewarray     #64                 // class java/lang/String
      71: dup
      72: iconst_0
      73: ldc           #66                 // String The first message must be ExposedPublisher but was [
      75: aastore
      76: dup
      77: iconst_1
      78: ldc           #68                 // String ]
      80: aastore
      81: checkcast     #70                 // class "[Ljava/lang/Object;"
      84: invokevirtual #74                 // Method scala/Predef$.wrapRefArray:([Ljava/lang/Object;)Lscala/collection/mutable/WrappedArray;
      87: invokespecial #78                 // Method scala/StringContext."<init>":(Lscala/collection/Seq;)V
      90: getstatic     #62                 // Field scala/Predef$.MODULE$:Lscala/Predef$;
      93: iconst_1
      94: anewarray     #80                 // class java/lang/Object
      97: dup
      98: iconst_0
      99: aload_3
     100: aastore
     101: invokevirtual #84                 // Method scala/Predef$.genericWrapArray:(Ljava/lang/Object;)Lscala/collection/mutable/WrappedArray;
     104: invokevirtual #88                 // Method scala/StringContext.s:(Lscala/collection/Seq;)Ljava/lang/String;
     107: invokespecial #91                 // Method java/lang/IllegalStateException."<init>":(Ljava/lang/String;)V
     110: athrow

  public final boolean isDefinedAt(java.lang.Object);
    Code:
       0: aload_1
       1: astore_2
       2: aload_2
       3: instanceof    #23                 // class akka/stream/impl/ExposedPublisher
       6: ifeq          14
       9: iconst_1
      10: istore_3
      11: goto          16
      14: iconst_1
      15: istore_3
      16: iload_3
      17: ireturn

  public akka.stream.impl.FanoutOutputs$$anonfun$waitingExposedPublisher$1(akka.stream.impl.FanoutOutputs);
    Code:
       0: aload_1
       1: ifnonnull     6
       4: aconst_null
       5: athrow
       6: aload_0
       7: aload_1
       8: putfield      #29                 // Field $outer:Lakka/stream/impl/FanoutOutputs;
      11: aload_0
      12: invokespecial #104                // Method scala/runtime/AbstractPartialFunction."<init>":()V
      15: return
}
