Compiled from "Buffers.scala"
public final class akka.stream.impl.FixedSizeBuffer$FixedSizeBuffer$$anonfun$toString$1 extends scala.runtime.AbstractFunction1<java.lang.Object, T> implements scala.Serializable {
  public static final long serialVersionUID;

  private final akka.stream.impl.FixedSizeBuffer$FixedSizeBuffer $outer;

  public final T apply(long);
    Code:
       0: aload_0
       1: getfield      #23                 // Field $outer:Lakka/stream/impl/FixedSizeBuffer$FixedSizeBuffer;
       4: lload_1
       5: invokevirtual #26                 // Method akka/stream/impl/FixedSizeBuffer$FixedSizeBuffer.akka$stream$impl$FixedSizeBuffer$FixedSizeBuffer$$get:(J)Ljava/lang/Object;
       8: areturn

  public final java.lang.Object apply(java.lang.Object);
    Code:
       0: aload_0
       1: aload_1
       2: invokestatic  #36                 // Method scala/runtime/BoxesRunTime.unboxToLong:(Ljava/lang/Object;)J
       5: invokevirtual #38                 // Method apply:(J)Ljava/lang/Object;
       8: areturn

  public akka.stream.impl.FixedSizeBuffer$FixedSizeBuffer$$anonfun$toString$1(akka.stream.impl.FixedSizeBuffer$FixedSizeBuffer<T>);
    Code:
       0: aload_1
       1: ifnonnull     6
       4: aconst_null
       5: athrow
       6: aload_0
       7: aload_1
       8: putfield      #23                 // Field $outer:Lakka/stream/impl/FixedSizeBuffer$FixedSizeBuffer;
      11: aload_0
      12: invokespecial #45                 // Method scala/runtime/AbstractFunction1."<init>":()V
      15: return
}
