Compiled from "ActorMaterializerImpl.scala"
public class akka.stream.impl.FlowNames implements akka.actor.Extension {
  private final akka.stream.impl.SeqActorNameImpl name;

  public static akka.actor.Extension apply(akka.actor.ActorSystem);
    Code:
       0: getstatic     #18                 // Field akka/stream/impl/FlowNames$.MODULE$:Lakka/stream/impl/FlowNames$;
       3: aload_0
       4: invokevirtual #20                 // Method akka/stream/impl/FlowNames$.apply:(Lakka/actor/ActorSystem;)Lakka/actor/Extension;
       7: areturn

  public static akka.stream.impl.FlowNames createExtension(akka.actor.ExtendedActorSystem);
    Code:
       0: getstatic     #18                 // Field akka/stream/impl/FlowNames$.MODULE$:Lakka/stream/impl/FlowNames$;
       3: aload_0
       4: invokevirtual #24                 // Method akka/stream/impl/FlowNames$.createExtension:(Lakka/actor/ExtendedActorSystem;)Lakka/stream/impl/FlowNames;
       7: areturn

  public static akka.stream.impl.FlowNames$ lookup();
    Code:
       0: getstatic     #18                 // Field akka/stream/impl/FlowNames$.MODULE$:Lakka/stream/impl/FlowNames$;
       3: invokevirtual #28                 // Method akka/stream/impl/FlowNames$.lookup:()Lakka/stream/impl/FlowNames$;
       6: areturn

  public static akka.stream.impl.FlowNames get(akka.actor.ActorSystem);
    Code:
       0: getstatic     #18                 // Field akka/stream/impl/FlowNames$.MODULE$:Lakka/stream/impl/FlowNames$;
       3: aload_0
       4: invokevirtual #32                 // Method akka/stream/impl/FlowNames$.get:(Lakka/actor/ActorSystem;)Lakka/stream/impl/FlowNames;
       7: areturn

  public akka.stream.impl.SeqActorNameImpl name();
    Code:
       0: aload_0
       1: getfield      #37                 // Field name:Lakka/stream/impl/SeqActorNameImpl;
       4: areturn

  public akka.stream.impl.FlowNames();
    Code:
       0: aload_0
       1: invokespecial #43                 // Method java/lang/Object."<init>":()V
       4: aload_0
       5: getstatic     #48                 // Field akka/stream/impl/SeqActorName$.MODULE$:Lakka/stream/impl/SeqActorName$;
       8: ldc           #50                 // String Flow
      10: invokevirtual #53                 // Method akka/stream/impl/SeqActorName$.apply:(Ljava/lang/String;)Lakka/stream/impl/SeqActorNameImpl;
      13: putfield      #37                 // Field name:Lakka/stream/impl/SeqActorNameImpl;
      16: return
}
