Compiled from "Transfer.scala"
public abstract class akka.stream.impl.Pump$class {
  public static final void initialPhase(akka.stream.impl.Pump, int, akka.stream.impl.TransferPhase);
    Code:
       0: getstatic     #13                 // Field scala/Predef$.MODULE$:Lscala/Predef$;
       3: iload_1
       4: iconst_1
       5: if_icmplt     12
       8: iconst_1
       9: goto          13
      12: iconst_0
      13: new           #15                 // class akka/stream/impl/Pump$$anonfun$initialPhase$1
      16: dup
      17: aload_0
      18: iload_1
      19: invokespecial #19                 // Method akka/stream/impl/Pump$$anonfun$initialPhase$1."<init>":(Lakka/stream/impl/Pump;I)V
      22: invokevirtual #23                 // Method scala/Predef$.require:(ZLscala/Function0;)V
      25: aload_0
      26: invokeinterface #29,  1           // InterfaceMethod akka/stream/impl/Pump.akka$stream$impl$Pump$$transferState:()Lakka/stream/impl/TransferState;
      31: getstatic     #34                 // Field akka/stream/impl/NotInitialized$.MODULE$:Lakka/stream/impl/NotInitialized$;
      34: astore_3
      35: dup
      36: ifnonnull     47
      39: pop
      40: aload_3
      41: ifnull        54
      44: goto          70
      47: aload_3
      48: invokevirtual #38                 // Method java/lang/Object.equals:(Ljava/lang/Object;)Z
      51: ifeq          70
      54: aload_0
      55: new           #40                 // class akka/stream/impl/WaitingForUpstreamSubscription
      58: dup
      59: iload_1
      60: aload_2
      61: invokespecial #43                 // Method akka/stream/impl/WaitingForUpstreamSubscription."<init>":(ILakka/stream/impl/TransferPhase;)V
      64: invokeinterface #47,  2           // InterfaceMethod akka/stream/impl/Pump.akka$stream$impl$Pump$$transferState_$eq:(Lakka/stream/impl/TransferState;)V
      69: return
      70: new           #49                 // class java/lang/IllegalStateException
      73: dup
      74: new           #51                 // class scala/StringContext
      77: dup
      78: getstatic     #13                 // Field scala/Predef$.MODULE$:Lscala/Predef$;
      81: iconst_2
      82: anewarray     #53                 // class java/lang/String
      85: dup
      86: iconst_0
      87: ldc           #55                 // String initialPhase expected NotInitialized, but was [
      89: aastore
      90: dup
      91: iconst_1
      92: ldc           #57                 // String ]
      94: aastore
      95: checkcast     #59                 // class "[Ljava/lang/Object;"
      98: invokevirtual #63                 // Method scala/Predef$.wrapRefArray:([Ljava/lang/Object;)Lscala/collection/mutable/WrappedArray;
     101: invokespecial #66                 // Method scala/StringContext."<init>":(Lscala/collection/Seq;)V
     104: getstatic     #13                 // Field scala/Predef$.MODULE$:Lscala/Predef$;
     107: iconst_1
     108: anewarray     #4                  // class java/lang/Object
     111: dup
     112: iconst_0
     113: aload_0
     114: invokeinterface #29,  1           // InterfaceMethod akka/stream/impl/Pump.akka$stream$impl$Pump$$transferState:()Lakka/stream/impl/TransferState;
     119: aastore
     120: invokevirtual #70                 // Method scala/Predef$.genericWrapArray:(Ljava/lang/Object;)Lscala/collection/mutable/WrappedArray;
     123: invokevirtual #74                 // Method scala/StringContext.s:(Lscala/collection/Seq;)Ljava/lang/String;
     126: invokespecial #77                 // Method java/lang/IllegalStateException."<init>":(Ljava/lang/String;)V
     129: athrow

  public static final void waitForUpstreams(akka.stream.impl.Pump, int);
    Code:
       0: getstatic     #13                 // Field scala/Predef$.MODULE$:Lscala/Predef$;
       3: iload_1
       4: iconst_1
       5: if_icmplt     12
       8: iconst_1
       9: goto          13
      12: iconst_0
      13: new           #90                 // class akka/stream/impl/Pump$$anonfun$waitForUpstreams$1
      16: dup
      17: aload_0
      18: iload_1
      19: invokespecial #91                 // Method akka/stream/impl/Pump$$anonfun$waitForUpstreams$1."<init>":(Lakka/stream/impl/Pump;I)V
      22: invokevirtual #23                 // Method scala/Predef$.require:(ZLscala/Function0;)V
      25: aload_0
      26: new           #40                 // class akka/stream/impl/WaitingForUpstreamSubscription
      29: dup
      30: iload_1
      31: new           #85                 // class akka/stream/impl/TransferPhase
      34: dup
      35: aload_0
      36: invokeinterface #29,  1           // InterfaceMethod akka/stream/impl/Pump.akka$stream$impl$Pump$$transferState:()Lakka/stream/impl/TransferState;
      41: aload_0
      42: invokeinterface #95,  1           // InterfaceMethod akka/stream/impl/Pump.akka$stream$impl$Pump$$currentAction:()Lscala/Function0;
      47: invokespecial #98                 // Method akka/stream/impl/TransferPhase."<init>":(Lakka/stream/impl/TransferState;Lscala/Function0;)V
      50: invokespecial #43                 // Method akka/stream/impl/WaitingForUpstreamSubscription."<init>":(ILakka/stream/impl/TransferPhase;)V
      53: invokeinterface #47,  2           // InterfaceMethod akka/stream/impl/Pump.akka$stream$impl$Pump$$transferState_$eq:(Lakka/stream/impl/TransferState;)V
      58: return

  public static void gotUpstreamSubscription(akka.stream.impl.Pump);
    Code:
       0: iconst_0
       1: istore_1
       2: aconst_null
       3: astore_2
       4: aload_0
       5: invokeinterface #29,  1           // InterfaceMethod akka/stream/impl/Pump.akka$stream$impl$Pump$$transferState:()Lakka/stream/impl/TransferState;
      10: astore_3
      11: aload_3
      12: instanceof    #40                 // class akka/stream/impl/WaitingForUpstreamSubscription
      15: ifeq          73
      18: iconst_1
      19: istore_1
      20: aload_3
      21: checkcast     #40                 // class akka/stream/impl/WaitingForUpstreamSubscription
      24: astore_2
      25: aload_2
      26: invokevirtual #104                // Method akka/stream/impl/WaitingForUpstreamSubscription.remaining:()I
      29: istore        4
      31: aload_2
      32: invokevirtual #107                // Method akka/stream/impl/WaitingForUpstreamSubscription.andThen:()Lakka/stream/impl/TransferPhase;
      35: astore        5
      37: iconst_1
      38: iload         4
      40: if_icmpne     73
      43: aload_0
      44: aload         5
      46: invokevirtual #110                // Method akka/stream/impl/TransferPhase.precondition:()Lakka/stream/impl/TransferState;
      49: invokeinterface #47,  2           // InterfaceMethod akka/stream/impl/Pump.akka$stream$impl$Pump$$transferState_$eq:(Lakka/stream/impl/TransferState;)V
      54: aload_0
      55: aload         5
      57: invokevirtual #113                // Method akka/stream/impl/TransferPhase.action:()Lscala/Function0;
      60: invokeinterface #117,  2          // InterfaceMethod akka/stream/impl/Pump.akka$stream$impl$Pump$$currentAction_$eq:(Lscala/Function0;)V
      65: getstatic     #123                // Field scala/runtime/BoxedUnit.UNIT:Lscala/runtime/BoxedUnit;
      68: astore        6
      70: goto          121
      73: iload_1
      74: ifeq          116
      77: aload_2
      78: invokevirtual #104                // Method akka/stream/impl/WaitingForUpstreamSubscription.remaining:()I
      81: istore        7
      83: aload_2
      84: invokevirtual #107                // Method akka/stream/impl/WaitingForUpstreamSubscription.andThen:()Lakka/stream/impl/TransferPhase;
      87: astore        8
      89: aload_0
      90: new           #40                 // class akka/stream/impl/WaitingForUpstreamSubscription
      93: dup
      94: iload         7
      96: iconst_1
      97: isub
      98: aload         8
     100: invokespecial #43                 // Method akka/stream/impl/WaitingForUpstreamSubscription."<init>":(ILakka/stream/impl/TransferPhase;)V
     103: invokeinterface #47,  2           // InterfaceMethod akka/stream/impl/Pump.akka$stream$impl$Pump$$transferState_$eq:(Lakka/stream/impl/TransferState;)V
     108: getstatic     #123                // Field scala/runtime/BoxedUnit.UNIT:Lscala/runtime/BoxedUnit;
     111: astore        6
     113: goto          121
     116: getstatic     #123                // Field scala/runtime/BoxedUnit.UNIT:Lscala/runtime/BoxedUnit;
     119: astore        6
     121: aload_0
     122: invokeinterface #127,  1          // InterfaceMethod akka/stream/impl/Pump.pump:()V
     127: return

  public static final void nextPhase(akka.stream.impl.Pump, akka.stream.impl.TransferPhase);
    Code:
       0: aload_0
       1: invokeinterface #29,  1           // InterfaceMethod akka/stream/impl/Pump.akka$stream$impl$Pump$$transferState:()Lakka/stream/impl/TransferState;
       6: astore_2
       7: aload_2
       8: instanceof    #40                 // class akka/stream/impl/WaitingForUpstreamSubscription
      11: ifeq          49
      14: aload_2
      15: checkcast     #40                 // class akka/stream/impl/WaitingForUpstreamSubscription
      18: astore_3
      19: aload_3
      20: invokevirtual #104                // Method akka/stream/impl/WaitingForUpstreamSubscription.remaining:()I
      23: istore        4
      25: aload_0
      26: new           #40                 // class akka/stream/impl/WaitingForUpstreamSubscription
      29: dup
      30: iload         4
      32: aload_1
      33: invokespecial #43                 // Method akka/stream/impl/WaitingForUpstreamSubscription."<init>":(ILakka/stream/impl/TransferPhase;)V
      36: invokeinterface #47,  2           // InterfaceMethod akka/stream/impl/Pump.akka$stream$impl$Pump$$transferState_$eq:(Lakka/stream/impl/TransferState;)V
      41: getstatic     #123                // Field scala/runtime/BoxedUnit.UNIT:Lscala/runtime/BoxedUnit;
      44: astore        5
      46: goto          74
      49: aload_0
      50: aload_1
      51: invokevirtual #110                // Method akka/stream/impl/TransferPhase.precondition:()Lakka/stream/impl/TransferState;
      54: invokeinterface #47,  2           // InterfaceMethod akka/stream/impl/Pump.akka$stream$impl$Pump$$transferState_$eq:(Lakka/stream/impl/TransferState;)V
      59: aload_0
      60: aload_1
      61: invokevirtual #113                // Method akka/stream/impl/TransferPhase.action:()Lscala/Function0;
      64: invokeinterface #117,  2          // InterfaceMethod akka/stream/impl/Pump.akka$stream$impl$Pump$$currentAction_$eq:(Lscala/Function0;)V
      69: getstatic     #123                // Field scala/runtime/BoxedUnit.UNIT:Lscala/runtime/BoxedUnit;
      72: astore        5
      74: return

  public static final boolean isPumpFinished(akka.stream.impl.Pump);
    Code:
       0: aload_0
       1: invokeinterface #29,  1           // InterfaceMethod akka/stream/impl/Pump.akka$stream$impl$Pump$$transferState:()Lakka/stream/impl/TransferState;
       6: invokeinterface #136,  1          // InterfaceMethod akka/stream/impl/TransferState.isCompleted:()Z
      11: ireturn

  public static final void pump(akka.stream.impl.Pump);
    Code:
       0: aload_0
       1: invokeinterface #29,  1           // InterfaceMethod akka/stream/impl/Pump.akka$stream$impl$Pump$$transferState:()Lakka/stream/impl/TransferState;
       6: invokeinterface #139,  1          // InterfaceMethod akka/stream/impl/TransferState.isExecutable:()Z
      11: ifeq          70
      14: aload_0
      15: invokeinterface #95,  1           // InterfaceMethod akka/stream/impl/Pump.akka$stream$impl$Pump$$currentAction:()Lscala/Function0;
      20: invokeinterface #144,  1          // InterfaceMethod scala/Function0.apply$mcV$sp:()V
      25: goto          0
      28: astore_1
      29: aload_1
      30: astore_2
      31: getstatic     #149                // Field scala/util/control/NonFatal$.MODULE$:Lscala/util/control/NonFatal$;
      34: aload_2
      35: invokevirtual #153                // Method scala/util/control/NonFatal$.unapply:(Ljava/lang/Throwable;)Lscala/Option;
      38: astore_3
      39: aload_3
      40: invokevirtual #158                // Method scala/Option.isEmpty:()Z
      43: ifeq          48
      46: aload_1
      47: athrow
      48: aload_3
      49: invokevirtual #162                // Method scala/Option.get:()Ljava/lang/Object;
      52: checkcast     #164                // class java/lang/Throwable
      55: astore        4
      57: aload_0
      58: aload         4
      60: invokeinterface #168,  2          // InterfaceMethod akka/stream/impl/Pump.pumpFailed:(Ljava/lang/Throwable;)V
      65: getstatic     #123                // Field scala/runtime/BoxedUnit.UNIT:Lscala/runtime/BoxedUnit;
      68: astore        5
      70: aload_0
      71: invokeinterface #170,  1          // InterfaceMethod akka/stream/impl/Pump.isPumpFinished:()Z
      76: ifeq          85
      79: aload_0
      80: invokeinterface #173,  1          // InterfaceMethod akka/stream/impl/Pump.pumpFinished:()V
      85: return
    Exception table:
       from    to  target type
           0    28    28   any

  public static void $init$(akka.stream.impl.Pump);
    Code:
       0: aload_0
       1: getstatic     #34                 // Field akka/stream/impl/NotInitialized$.MODULE$:Lakka/stream/impl/NotInitialized$;
       4: invokeinterface #47,  2           // InterfaceMethod akka/stream/impl/Pump.akka$stream$impl$Pump$$transferState_$eq:(Lakka/stream/impl/TransferState;)V
       9: aload_0
      10: new           #178                // class akka/stream/impl/Pump$$anonfun$1
      13: dup
      14: aload_0
      15: invokespecial #180                // Method akka/stream/impl/Pump$$anonfun$1."<init>":(Lakka/stream/impl/Pump;)V
      18: invokeinterface #117,  2          // InterfaceMethod akka/stream/impl/Pump.akka$stream$impl$Pump$$currentAction_$eq:(Lscala/Function0;)V
      23: aload_0
      24: new           #85                 // class akka/stream/impl/TransferPhase
      27: dup
      28: getstatic     #185                // Field akka/stream/impl/Completed$.MODULE$:Lakka/stream/impl/Completed$;
      31: new           #187                // class akka/stream/impl/Pump$$anonfun$2
      34: dup
      35: aload_0
      36: invokespecial #188                // Method akka/stream/impl/Pump$$anonfun$2."<init>":(Lakka/stream/impl/Pump;)V
      39: invokespecial #98                 // Method akka/stream/impl/TransferPhase."<init>":(Lakka/stream/impl/TransferState;Lscala/Function0;)V
      42: invokeinterface #192,  2          // InterfaceMethod akka/stream/impl/Pump.akka$stream$impl$Pump$_setter_$completedPhase_$eq:(Lakka/stream/impl/TransferPhase;)V
      47: return
}
