Compiled from "Sources.scala"
public final class akka.stream.impl.QueueSource$$anon$1$$anonfun$2 extends scala.runtime.AbstractFunction1<akka.stream.impl.QueueSource$Input<T>, scala.runtime.BoxedUnit> implements scala.Serializable {
  public static final long serialVersionUID;

  private final akka.stream.impl.QueueSource$$anon$1 $outer;

  public final void apply(akka.stream.impl.QueueSource$Input<T>);
    Code:
       0: aload_1
       1: astore_2
       2: aload_2
       3: instanceof    #20                 // class akka/stream/impl/QueueSource$Offer
       6: ifeq          541
       9: aload_2
      10: checkcast     #20                 // class akka/stream/impl/QueueSource$Offer
      13: astore_3
      14: aload_3
      15: invokevirtual #24                 // Method akka/stream/impl/QueueSource$Offer.elem:()Ljava/lang/Object;
      18: astore        4
      20: aload_3
      21: invokevirtual #28                 // Method akka/stream/impl/QueueSource$Offer.promise:()Lscala/concurrent/Promise;
      24: astore        5
      26: aload_0
      27: getfield      #30                 // Field $outer:Lakka/stream/impl/QueueSource$$anon$1;
      30: invokevirtual #34                 // Method akka/stream/impl/QueueSource$$anon$1.akka$stream$impl$QueueSource$$anon$$$outer:()Lakka/stream/impl/QueueSource;
      33: getfield      #40                 // Field akka/stream/impl/QueueSource.akka$stream$impl$QueueSource$$maxBuffer:I
      36: iconst_0
      37: if_icmpeq     109
      40: aload_0
      41: getfield      #30                 // Field $outer:Lakka/stream/impl/QueueSource$$anon$1;
      44: aload_3
      45: invokevirtual #44                 // Method akka/stream/impl/QueueSource$$anon$1.akka$stream$impl$QueueSource$$anon$$bufferElem:(Lakka/stream/impl/QueueSource$Offer;)V
      48: aload_0
      49: getfield      #30                 // Field $outer:Lakka/stream/impl/QueueSource$$anon$1;
      52: aload_0
      53: getfield      #30                 // Field $outer:Lakka/stream/impl/QueueSource$$anon$1;
      56: invokevirtual #34                 // Method akka/stream/impl/QueueSource$$anon$1.akka$stream$impl$QueueSource$$anon$$$outer:()Lakka/stream/impl/QueueSource;
      59: invokevirtual #48                 // Method akka/stream/impl/QueueSource.out:()Lakka/stream/Outlet;
      62: invokevirtual #52                 // Method akka/stream/impl/QueueSource$$anon$1.isAvailable:(Lakka/stream/Outlet;)Z
      65: ifeq          103
      68: aload_0
      69: getfield      #30                 // Field $outer:Lakka/stream/impl/QueueSource$$anon$1;
      72: aload_0
      73: getfield      #30                 // Field $outer:Lakka/stream/impl/QueueSource$$anon$1;
      76: invokevirtual #34                 // Method akka/stream/impl/QueueSource$$anon$1.akka$stream$impl$QueueSource$$anon$$$outer:()Lakka/stream/impl/QueueSource;
      79: invokevirtual #48                 // Method akka/stream/impl/QueueSource.out:()Lakka/stream/Outlet;
      82: aload_0
      83: getfield      #30                 // Field $outer:Lakka/stream/impl/QueueSource$$anon$1;
      86: invokevirtual #56                 // Method akka/stream/impl/QueueSource$$anon$1.buffer:()Lakka/stream/impl/Buffer;
      89: invokeinterface #61,  1           // InterfaceMethod akka/stream/impl/Buffer.dequeue:()Ljava/lang/Object;
      94: invokevirtual #65                 // Method akka/stream/impl/QueueSource$$anon$1.push:(Lakka/stream/Outlet;Ljava/lang/Object;)V
      97: getstatic     #71                 // Field scala/runtime/BoxedUnit.UNIT:Lscala/runtime/BoxedUnit;
     100: goto          526
     103: getstatic     #71                 // Field scala/runtime/BoxedUnit.UNIT:Lscala/runtime/BoxedUnit;
     106: goto          526
     109: aload_0
     110: getfield      #30                 // Field $outer:Lakka/stream/impl/QueueSource$$anon$1;
     113: aload_0
     114: getfield      #30                 // Field $outer:Lakka/stream/impl/QueueSource$$anon$1;
     117: invokevirtual #34                 // Method akka/stream/impl/QueueSource$$anon$1.akka$stream$impl$QueueSource$$anon$$$outer:()Lakka/stream/impl/QueueSource;
     120: invokevirtual #48                 // Method akka/stream/impl/QueueSource.out:()Lakka/stream/Outlet;
     123: invokevirtual #52                 // Method akka/stream/impl/QueueSource$$anon$1.isAvailable:(Lakka/stream/Outlet;)Z
     126: ifeq          165
     129: aload_0
     130: getfield      #30                 // Field $outer:Lakka/stream/impl/QueueSource$$anon$1;
     133: aload_0
     134: getfield      #30                 // Field $outer:Lakka/stream/impl/QueueSource$$anon$1;
     137: invokevirtual #34                 // Method akka/stream/impl/QueueSource$$anon$1.akka$stream$impl$QueueSource$$anon$$$outer:()Lakka/stream/impl/QueueSource;
     140: invokevirtual #48                 // Method akka/stream/impl/QueueSource.out:()Lakka/stream/Outlet;
     143: aload         4
     145: invokevirtual #65                 // Method akka/stream/impl/QueueSource$$anon$1.push:(Lakka/stream/Outlet;Ljava/lang/Object;)V
     148: aload         5
     150: getstatic     #77                 // Field akka/stream/QueueOfferResult$Enqueued$.MODULE$:Lakka/stream/QueueOfferResult$Enqueued$;
     153: invokeinterface #83,  2           // InterfaceMethod scala/concurrent/Promise.success:(Ljava/lang/Object;)Lscala/concurrent/Promise;
     158: pop
     159: getstatic     #71                 // Field scala/runtime/BoxedUnit.UNIT:Lscala/runtime/BoxedUnit;
     162: goto          526
     165: aload_0
     166: getfield      #30                 // Field $outer:Lakka/stream/impl/QueueSource$$anon$1;
     169: invokevirtual #87                 // Method akka/stream/impl/QueueSource$$anon$1.pendingOffer:()Lscala/Option;
     172: invokevirtual #93                 // Method scala/Option.isEmpty:()Z
     175: ifeq          199
     178: aload_0
     179: getfield      #30                 // Field $outer:Lakka/stream/impl/QueueSource$$anon$1;
     182: new           #95                 // class scala/Some
     185: dup
     186: aload_3
     187: invokespecial #99                 // Method scala/Some."<init>":(Ljava/lang/Object;)V
     190: invokevirtual #103                // Method akka/stream/impl/QueueSource$$anon$1.pendingOffer_$eq:(Lscala/Option;)V
     193: getstatic     #71                 // Field scala/runtime/BoxedUnit.UNIT:Lscala/runtime/BoxedUnit;
     196: goto          526
     199: aload_0
     200: getfield      #30                 // Field $outer:Lakka/stream/impl/QueueSource$$anon$1;
     203: invokevirtual #34                 // Method akka/stream/impl/QueueSource$$anon$1.akka$stream$impl$QueueSource$$anon$$$outer:()Lakka/stream/impl/QueueSource;
     206: getfield      #107                // Field akka/stream/impl/QueueSource.akka$stream$impl$QueueSource$$overflowStrategy:Lakka/stream/OverflowStrategy;
     209: astore        7
     211: getstatic     #112                // Field akka/stream/OverflowStrategies$DropHead$.MODULE$:Lakka/stream/OverflowStrategies$DropHead$;
     214: aload         7
     216: invokevirtual #118                // Method java/lang/Object.equals:(Ljava/lang/Object;)Z
     219: ifeq          228
     222: iconst_1
     223: istore        8
     225: goto          248
     228: getstatic     #123                // Field akka/stream/OverflowStrategies$DropBuffer$.MODULE$:Lakka/stream/OverflowStrategies$DropBuffer$;
     231: aload         7
     233: invokevirtual #118                // Method java/lang/Object.equals:(Ljava/lang/Object;)Z
     236: ifeq          245
     239: iconst_1
     240: istore        8
     242: goto          248
     245: iconst_0
     246: istore        8
     248: iload         8
     250: ifeq          301
     253: aload_0
     254: getfield      #30                 // Field $outer:Lakka/stream/impl/QueueSource$$anon$1;
     257: invokevirtual #87                 // Method akka/stream/impl/QueueSource$$anon$1.pendingOffer:()Lscala/Option;
     260: invokevirtual #126                // Method scala/Option.get:()Ljava/lang/Object;
     263: checkcast     #20                 // class akka/stream/impl/QueueSource$Offer
     266: invokevirtual #28                 // Method akka/stream/impl/QueueSource$Offer.promise:()Lscala/concurrent/Promise;
     269: getstatic     #131                // Field akka/stream/QueueOfferResult$Dropped$.MODULE$:Lakka/stream/QueueOfferResult$Dropped$;
     272: invokeinterface #83,  2           // InterfaceMethod scala/concurrent/Promise.success:(Ljava/lang/Object;)Lscala/concurrent/Promise;
     277: pop
     278: aload_0
     279: getfield      #30                 // Field $outer:Lakka/stream/impl/QueueSource$$anon$1;
     282: new           #95                 // class scala/Some
     285: dup
     286: aload_3
     287: invokespecial #99                 // Method scala/Some."<init>":(Ljava/lang/Object;)V
     290: invokevirtual #103                // Method akka/stream/impl/QueueSource$$anon$1.pendingOffer_$eq:(Lscala/Option;)V
     293: getstatic     #71                 // Field scala/runtime/BoxedUnit.UNIT:Lscala/runtime/BoxedUnit;
     296: astore        9
     298: goto          523
     301: getstatic     #136                // Field akka/stream/OverflowStrategies$DropTail$.MODULE$:Lakka/stream/OverflowStrategies$DropTail$;
     304: aload         7
     306: invokevirtual #118                // Method java/lang/Object.equals:(Ljava/lang/Object;)Z
     309: ifeq          318
     312: iconst_1
     313: istore        10
     315: goto          338
     318: getstatic     #141                // Field akka/stream/OverflowStrategies$DropNew$.MODULE$:Lakka/stream/OverflowStrategies$DropNew$;
     321: aload         7
     323: invokevirtual #118                // Method java/lang/Object.equals:(Ljava/lang/Object;)Z
     326: ifeq          335
     329: iconst_1
     330: istore        10
     332: goto          338
     335: iconst_0
     336: istore        10
     338: iload         10
     340: ifeq          362
     343: aload         5
     345: getstatic     #131                // Field akka/stream/QueueOfferResult$Dropped$.MODULE$:Lakka/stream/QueueOfferResult$Dropped$;
     348: invokeinterface #83,  2           // InterfaceMethod scala/concurrent/Promise.success:(Ljava/lang/Object;)Lscala/concurrent/Promise;
     353: pop
     354: getstatic     #71                 // Field scala/runtime/BoxedUnit.UNIT:Lscala/runtime/BoxedUnit;
     357: astore        9
     359: goto          523
     362: getstatic     #146                // Field akka/stream/OverflowStrategies$Fail$.MODULE$:Lakka/stream/OverflowStrategies$Fail$;
     365: aload         7
     367: invokevirtual #118                // Method java/lang/Object.equals:(Ljava/lang/Object;)Z
     370: ifeq          490
     373: new           #148                // class akka/stream/BufferOverflowException
     376: dup
     377: new           #150                // class scala/StringContext
     380: dup
     381: getstatic     #155                // Field scala/Predef$.MODULE$:Lscala/Predef$;
     384: iconst_2
     385: anewarray     #157                // class java/lang/String
     388: dup
     389: iconst_0
     390: ldc           #159                // String Buffer overflow (max capacity was:
     392: aastore
     393: dup
     394: iconst_1
     395: ldc           #161                // String )!
     397: aastore
     398: checkcast     #163                // class "[Ljava/lang/Object;"
     401: invokevirtual #167                // Method scala/Predef$.wrapRefArray:([Ljava/lang/Object;)Lscala/collection/mutable/WrappedArray;
     404: invokespecial #170                // Method scala/StringContext."<init>":(Lscala/collection/Seq;)V
     407: getstatic     #155                // Field scala/Predef$.MODULE$:Lscala/Predef$;
     410: iconst_1
     411: anewarray     #114                // class java/lang/Object
     414: dup
     415: iconst_0
     416: aload_0
     417: getfield      #30                 // Field $outer:Lakka/stream/impl/QueueSource$$anon$1;
     420: invokevirtual #34                 // Method akka/stream/impl/QueueSource$$anon$1.akka$stream$impl$QueueSource$$anon$$$outer:()Lakka/stream/impl/QueueSource;
     423: getfield      #40                 // Field akka/stream/impl/QueueSource.akka$stream$impl$QueueSource$$maxBuffer:I
     426: invokestatic  #176                // Method scala/runtime/BoxesRunTime.boxToInteger:(I)Ljava/lang/Integer;
     429: aastore
     430: invokevirtual #180                // Method scala/Predef$.genericWrapArray:(Ljava/lang/Object;)Lscala/collection/mutable/WrappedArray;
     433: invokevirtual #184                // Method scala/StringContext.s:(Lscala/collection/Seq;)Ljava/lang/String;
     436: invokespecial #187                // Method akka/stream/BufferOverflowException."<init>":(Ljava/lang/String;)V
     439: astore        11
     441: aload         5
     443: new           #189                // class akka/stream/QueueOfferResult$Failure
     446: dup
     447: aload         11
     449: invokespecial #192                // Method akka/stream/QueueOfferResult$Failure."<init>":(Ljava/lang/Throwable;)V
     452: invokeinterface #83,  2           // InterfaceMethod scala/concurrent/Promise.success:(Ljava/lang/Object;)Lscala/concurrent/Promise;
     457: pop
     458: aload_0
     459: getfield      #30                 // Field $outer:Lakka/stream/impl/QueueSource$$anon$1;
     462: getfield      #196                // Field akka/stream/impl/QueueSource$$anon$1.completion$1:Lscala/concurrent/Promise;
     465: aload         11
     467: invokeinterface #200,  2          // InterfaceMethod scala/concurrent/Promise.failure:(Ljava/lang/Throwable;)Lscala/concurrent/Promise;
     472: pop
     473: aload_0
     474: getfield      #30                 // Field $outer:Lakka/stream/impl/QueueSource$$anon$1;
     477: aload         11
     479: invokevirtual #203                // Method akka/stream/impl/QueueSource$$anon$1.failStage:(Ljava/lang/Throwable;)V
     482: getstatic     #71                 // Field scala/runtime/BoxedUnit.UNIT:Lscala/runtime/BoxedUnit;
     485: astore        9
     487: goto          523
     490: getstatic     #208                // Field akka/stream/OverflowStrategies$Backpressure$.MODULE$:Lakka/stream/OverflowStrategies$Backpressure$;
     493: aload         7
     495: invokevirtual #118                // Method java/lang/Object.equals:(Ljava/lang/Object;)Z
     498: ifeq          531
     501: aload         5
     503: new           #210                // class java/lang/IllegalStateException
     506: dup
     507: ldc           #212                // String You have to wait for previous offer to be resolved to send another request
     509: invokespecial #213                // Method java/lang/IllegalStateException."<init>":(Ljava/lang/String;)V
     512: invokeinterface #200,  2          // InterfaceMethod scala/concurrent/Promise.failure:(Ljava/lang/Throwable;)Lscala/concurrent/Promise;
     517: pop
     518: getstatic     #71                 // Field scala/runtime/BoxedUnit.UNIT:Lscala/runtime/BoxedUnit;
     521: astore        9
     523: getstatic     #71                 // Field scala/runtime/BoxedUnit.UNIT:Lscala/runtime/BoxedUnit;
     526: astore        6
     528: goto          687
     531: new           #215                // class scala/MatchError
     534: dup
     535: aload         7
     537: invokespecial #216                // Method scala/MatchError."<init>":(Ljava/lang/Object;)V
     540: athrow
     541: getstatic     #221                // Field akka/stream/impl/QueueSource$Completion$.MODULE$:Lakka/stream/impl/QueueSource$Completion$;
     544: aload_2
     545: invokevirtual #118                // Method java/lang/Object.equals:(Ljava/lang/Object;)Z
     548: ifeq          638
     551: aload_0
     552: getfield      #30                 // Field $outer:Lakka/stream/impl/QueueSource$$anon$1;
     555: invokevirtual #34                 // Method akka/stream/impl/QueueSource$$anon$1.akka$stream$impl$QueueSource$$anon$$$outer:()Lakka/stream/impl/QueueSource;
     558: getfield      #40                 // Field akka/stream/impl/QueueSource.akka$stream$impl$QueueSource$$maxBuffer:I
     561: iconst_0
     562: if_icmpeq     580
     565: aload_0
     566: getfield      #30                 // Field $outer:Lakka/stream/impl/QueueSource$$anon$1;
     569: invokevirtual #56                 // Method akka/stream/impl/QueueSource$$anon$1.buffer:()Lakka/stream/impl/Buffer;
     572: invokeinterface #224,  1          // InterfaceMethod akka/stream/impl/Buffer.nonEmpty:()Z
     577: ifne          593
     580: aload_0
     581: getfield      #30                 // Field $outer:Lakka/stream/impl/QueueSource$$anon$1;
     584: invokevirtual #87                 // Method akka/stream/impl/QueueSource$$anon$1.pendingOffer:()Lscala/Option;
     587: invokevirtual #225                // Method scala/Option.nonEmpty:()Z
     590: ifeq          607
     593: aload_0
     594: getfield      #30                 // Field $outer:Lakka/stream/impl/QueueSource$$anon$1;
     597: iconst_1
     598: invokevirtual #229                // Method akka/stream/impl/QueueSource$$anon$1.terminating_$eq:(Z)V
     601: getstatic     #71                 // Field scala/runtime/BoxedUnit.UNIT:Lscala/runtime/BoxedUnit;
     604: goto          633
     607: aload_0
     608: getfield      #30                 // Field $outer:Lakka/stream/impl/QueueSource$$anon$1;
     611: getfield      #196                // Field akka/stream/impl/QueueSource$$anon$1.completion$1:Lscala/concurrent/Promise;
     614: getstatic     #234                // Field akka/Done$.MODULE$:Lakka/Done$;
     617: invokeinterface #83,  2           // InterfaceMethod scala/concurrent/Promise.success:(Ljava/lang/Object;)Lscala/concurrent/Promise;
     622: pop
     623: aload_0
     624: getfield      #30                 // Field $outer:Lakka/stream/impl/QueueSource$$anon$1;
     627: invokevirtual #238                // Method akka/stream/impl/QueueSource$$anon$1.completeStage:()V
     630: getstatic     #71                 // Field scala/runtime/BoxedUnit.UNIT:Lscala/runtime/BoxedUnit;
     633: astore        6
     635: goto          687
     638: aload_2
     639: instanceof    #240                // class akka/stream/impl/QueueSource$Failure
     642: ifeq          688
     645: aload_2
     646: checkcast     #240                // class akka/stream/impl/QueueSource$Failure
     649: astore        12
     651: aload         12
     653: invokevirtual #244                // Method akka/stream/impl/QueueSource$Failure.ex:()Ljava/lang/Throwable;
     656: astore        13
     658: aload_0
     659: getfield      #30                 // Field $outer:Lakka/stream/impl/QueueSource$$anon$1;
     662: getfield      #196                // Field akka/stream/impl/QueueSource$$anon$1.completion$1:Lscala/concurrent/Promise;
     665: aload         13
     667: invokeinterface #200,  2          // InterfaceMethod scala/concurrent/Promise.failure:(Ljava/lang/Throwable;)Lscala/concurrent/Promise;
     672: pop
     673: aload_0
     674: getfield      #30                 // Field $outer:Lakka/stream/impl/QueueSource$$anon$1;
     677: aload         13
     679: invokevirtual #203                // Method akka/stream/impl/QueueSource$$anon$1.failStage:(Ljava/lang/Throwable;)V
     682: getstatic     #71                 // Field scala/runtime/BoxedUnit.UNIT:Lscala/runtime/BoxedUnit;
     685: astore        6
     687: return
     688: new           #215                // class scala/MatchError
     691: dup
     692: aload_2
     693: invokespecial #216                // Method scala/MatchError."<init>":(Ljava/lang/Object;)V
     696: athrow

  public final java.lang.Object apply(java.lang.Object);
    Code:
       0: aload_0
       1: aload_1
       2: checkcast     #254                // class akka/stream/impl/QueueSource$Input
       5: invokevirtual #259                // Method apply:(Lakka/stream/impl/QueueSource$Input;)V
       8: getstatic     #71                 // Field scala/runtime/BoxedUnit.UNIT:Lscala/runtime/BoxedUnit;
      11: areturn

  public akka.stream.impl.QueueSource$$anon$1$$anonfun$2(akka.stream.impl.QueueSource<T>.$anon$1);
    Code:
       0: aload_1
       1: ifnonnull     6
       4: aconst_null
       5: athrow
       6: aload_0
       7: aload_1
       8: putfield      #30                 // Field $outer:Lakka/stream/impl/QueueSource$$anon$1;
      11: aload_0
      12: invokespecial #263                // Method scala/runtime/AbstractFunction1."<init>":()V
      15: return
}
