Compiled from "StreamSubscriptionTimeout.scala"
public abstract class akka.stream.impl.StreamSubscriptionTimeoutSupport$class {
  public static akka.actor.Cancellable scheduleSubscriptionTimeout(akka.stream.impl.StreamSubscriptionTimeoutSupport, akka.actor.ActorRef, java.lang.Object);
    Code:
       0: aload_0
       1: invokeinterface #13,  1           // InterfaceMethod akka/stream/impl/StreamSubscriptionTimeoutSupport.subscriptionTimeoutSettings:()Lakka/stream/StreamSubscriptionTimeoutSettings;
       6: invokevirtual #19                 // Method akka/stream/StreamSubscriptionTimeoutSettings.mode:()Lakka/stream/StreamSubscriptionTimeoutTerminationMode;
       9: astore_3
      10: getstatic     #25                 // Field akka/stream/StreamSubscriptionTimeoutTerminationMode$NoopTermination$.MODULE$:Lakka/stream/StreamSubscriptionTimeoutTerminationMode$NoopTermination$;
      13: aload_3
      14: invokevirtual #29                 // Method java/lang/Object.equals:(Ljava/lang/Object;)Z
      17: ifeq          28
      20: getstatic     #34                 // Field akka/stream/impl/StreamSubscriptionTimeoutSupport$NoopSubscriptionTimeout$.MODULE$:Lakka/stream/impl/StreamSubscriptionTimeoutSupport$NoopSubscriptionTimeout$;
      23: astore        4
      25: goto          90
      28: aload_0
      29: checkcast     #36                 // class akka/actor/Actor
      32: invokeinterface #40,  1           // InterfaceMethod akka/actor/Actor.context:()Lakka/actor/ActorContext;
      37: invokeinterface #46,  1           // InterfaceMethod akka/actor/ActorContext.system:()Lakka/actor/ActorSystem;
      42: invokevirtual #52                 // Method akka/actor/ActorSystem.scheduler:()Lakka/actor/Scheduler;
      45: aload_0
      46: invokeinterface #13,  1           // InterfaceMethod akka/stream/impl/StreamSubscriptionTimeoutSupport.subscriptionTimeoutSettings:()Lakka/stream/StreamSubscriptionTimeoutSettings;
      51: invokevirtual #56                 // Method akka/stream/StreamSubscriptionTimeoutSettings.timeout:()Lscala/concurrent/duration/FiniteDuration;
      54: aload_1
      55: aload_2
      56: aload_0
      57: checkcast     #36                 // class akka/actor/Actor
      60: invokeinterface #40,  1           // InterfaceMethod akka/actor/Actor.context:()Lakka/actor/ActorContext;
      65: invokeinterface #60,  1           // InterfaceMethod akka/actor/ActorContext.dispatcher:()Lscala/concurrent/ExecutionContextExecutor;
      70: aload_0
      71: checkcast     #36                 // class akka/actor/Actor
      74: invokeinterface #64,  1           // InterfaceMethod akka/actor/Actor.self:()Lakka/actor/ActorRef;
      79: invokeinterface #70,  6           // InterfaceMethod akka/actor/Scheduler.scheduleOnce:(Lscala/concurrent/duration/FiniteDuration;Lakka/actor/ActorRef;Ljava/lang/Object;Lscala/concurrent/ExecutionContext;Lakka/actor/ActorRef;)Lakka/actor/Cancellable;
      84: astore        5
      86: aload         5
      88: astore        4
      90: aload         4
      92: areturn

  private static void cancel(akka.stream.impl.StreamSubscriptionTimeoutSupport, org.reactivestreams.Publisher, scala.concurrent.duration.FiniteDuration);
    Code:
       0: aload_2
       1: invokevirtual #90                 // Method scala/concurrent/duration/FiniteDuration.toMillis:()J
       4: lstore_3
       5: aload_1
       6: astore        5
       8: aload         5
      10: instanceof    #92                 // class org/reactivestreams/Processor
      13: ifeq          69
      16: aload         5
      18: checkcast     #92                 // class org/reactivestreams/Processor
      21: astore        6
      23: aload_0
      24: checkcast     #94                 // class akka/actor/ActorLogging
      27: invokeinterface #98,  1           // InterfaceMethod akka/actor/ActorLogging.log:()Lakka/event/LoggingAdapter;
      32: ldc           #100                // String Cancelling {} Processor\'s publisher and subscriber sides (after {} ms)
      34: aload         6
      36: lload_3
      37: invokestatic  #106                // Method scala/runtime/BoxesRunTime.boxToLong:(J)Ljava/lang/Long;
      40: invokeinterface #112,  4          // InterfaceMethod akka/event/LoggingAdapter.debug:(Ljava/lang/String;Ljava/lang/Object;Ljava/lang/Object;)V
      45: aload_0
      46: aload_1
      47: new           #114                // class akka/stream/impl/StreamSubscriptionTimeoutSupport$$anon$1
      50: dup
      51: aload_0
      52: lload_3
      53: invokespecial #118                // Method akka/stream/impl/StreamSubscriptionTimeoutSupport$$anon$1."<init>":(Lakka/stream/impl/StreamSubscriptionTimeoutSupport;J)V
      56: invokeinterface #122,  3          // InterfaceMethod akka/stream/impl/StreamSubscriptionTimeoutSupport.handleSubscriptionTimeout:(Lorg/reactivestreams/Publisher;Ljava/lang/Exception;)V
      61: getstatic     #128                // Field scala/runtime/BoxedUnit.UNIT:Lscala/runtime/BoxedUnit;
      64: astore        7
      66: goto          122
      69: aload         5
      71: ifnull        123
      74: aload         5
      76: astore        8
      78: aload_0
      79: checkcast     #94                 // class akka/actor/ActorLogging
      82: invokeinterface #98,  1           // InterfaceMethod akka/actor/ActorLogging.log:()Lakka/event/LoggingAdapter;
      87: ldc           #130                // String Cancelling {} (after: {} ms)
      89: aload         8
      91: lload_3
      92: invokestatic  #106                // Method scala/runtime/BoxesRunTime.boxToLong:(J)Ljava/lang/Long;
      95: invokeinterface #112,  4          // InterfaceMethod akka/event/LoggingAdapter.debug:(Ljava/lang/String;Ljava/lang/Object;Ljava/lang/Object;)V
     100: aload_0
     101: aload_1
     102: new           #132                // class akka/stream/impl/StreamSubscriptionTimeoutSupport$$anon$2
     105: dup
     106: aload_0
     107: aload         8
     109: invokespecial #135                // Method akka/stream/impl/StreamSubscriptionTimeoutSupport$$anon$2."<init>":(Lakka/stream/impl/StreamSubscriptionTimeoutSupport;Lorg/reactivestreams/Publisher;)V
     112: invokeinterface #122,  3          // InterfaceMethod akka/stream/impl/StreamSubscriptionTimeoutSupport.handleSubscriptionTimeout:(Lorg/reactivestreams/Publisher;Ljava/lang/Exception;)V
     117: getstatic     #128                // Field scala/runtime/BoxedUnit.UNIT:Lscala/runtime/BoxedUnit;
     120: astore        7
     122: return
     123: new           #137                // class scala/MatchError
     126: dup
     127: aload         5
     129: invokespecial #140                // Method scala/MatchError."<init>":(Ljava/lang/Object;)V
     132: athrow

  private static void warn(akka.stream.impl.StreamSubscriptionTimeoutSupport, org.reactivestreams.Publisher, scala.concurrent.duration.FiniteDuration);
    Code:
       0: aload_0
       1: checkcast     #94                 // class akka/actor/ActorLogging
       4: invokeinterface #98,  1           // InterfaceMethod akka/actor/ActorLogging.log:()Lakka/event/LoggingAdapter;
       9: ldc           #150                // String Timed out {} detected (after {} ms)! You should investigate if you either cancel or consume all {} instances
      11: aload_1
      12: aload_2
      13: invokevirtual #90                 // Method scala/concurrent/duration/FiniteDuration.toMillis:()J
      16: invokestatic  #106                // Method scala/runtime/BoxesRunTime.boxToLong:(J)Ljava/lang/Long;
      19: aload_1
      20: invokevirtual #154                // Method java/lang/Object.getClass:()Ljava/lang/Class;
      23: invokevirtual #160                // Method java/lang/Class.getCanonicalName:()Ljava/lang/String;
      26: invokeinterface #164,  5          // InterfaceMethod akka/event/LoggingAdapter.warning:(Ljava/lang/String;Ljava/lang/Object;Ljava/lang/Object;Ljava/lang/Object;)V
      31: return

  public static void subscriptionTimedOut(akka.stream.impl.StreamSubscriptionTimeoutSupport, org.reactivestreams.Publisher);
    Code:
       0: aload_0
       1: invokeinterface #13,  1           // InterfaceMethod akka/stream/impl/StreamSubscriptionTimeoutSupport.subscriptionTimeoutSettings:()Lakka/stream/StreamSubscriptionTimeoutSettings;
       6: invokevirtual #19                 // Method akka/stream/StreamSubscriptionTimeoutSettings.mode:()Lakka/stream/StreamSubscriptionTimeoutTerminationMode;
       9: astore_2
      10: getstatic     #25                 // Field akka/stream/StreamSubscriptionTimeoutTerminationMode$NoopTermination$.MODULE$:Lakka/stream/StreamSubscriptionTimeoutTerminationMode$NoopTermination$;
      13: aload_2
      14: invokevirtual #29                 // Method java/lang/Object.equals:(Ljava/lang/Object;)Z
      17: ifeq          27
      20: getstatic     #128                // Field scala/runtime/BoxedUnit.UNIT:Lscala/runtime/BoxedUnit;
      23: astore_3
      24: goto          86
      27: getstatic     #170                // Field akka/stream/StreamSubscriptionTimeoutTerminationMode$WarnTermination$.MODULE$:Lakka/stream/StreamSubscriptionTimeoutTerminationMode$WarnTermination$;
      30: aload_2
      31: invokevirtual #29                 // Method java/lang/Object.equals:(Ljava/lang/Object;)Z
      34: ifeq          58
      37: aload_0
      38: aload_1
      39: aload_0
      40: invokeinterface #13,  1           // InterfaceMethod akka/stream/impl/StreamSubscriptionTimeoutSupport.subscriptionTimeoutSettings:()Lakka/stream/StreamSubscriptionTimeoutSettings;
      45: invokevirtual #56                 // Method akka/stream/StreamSubscriptionTimeoutSettings.timeout:()Lscala/concurrent/duration/FiniteDuration;
      48: invokestatic  #172                // Method warn:(Lakka/stream/impl/StreamSubscriptionTimeoutSupport;Lorg/reactivestreams/Publisher;Lscala/concurrent/duration/FiniteDuration;)V
      51: getstatic     #128                // Field scala/runtime/BoxedUnit.UNIT:Lscala/runtime/BoxedUnit;
      54: astore_3
      55: goto          86
      58: getstatic     #177                // Field akka/stream/StreamSubscriptionTimeoutTerminationMode$CancelTermination$.MODULE$:Lakka/stream/StreamSubscriptionTimeoutTerminationMode$CancelTermination$;
      61: aload_2
      62: invokevirtual #29                 // Method java/lang/Object.equals:(Ljava/lang/Object;)Z
      65: ifeq          87
      68: aload_0
      69: aload_1
      70: aload_0
      71: invokeinterface #13,  1           // InterfaceMethod akka/stream/impl/StreamSubscriptionTimeoutSupport.subscriptionTimeoutSettings:()Lakka/stream/StreamSubscriptionTimeoutSettings;
      76: invokevirtual #56                 // Method akka/stream/StreamSubscriptionTimeoutSettings.timeout:()Lscala/concurrent/duration/FiniteDuration;
      79: invokestatic  #179                // Method cancel:(Lakka/stream/impl/StreamSubscriptionTimeoutSupport;Lorg/reactivestreams/Publisher;Lscala/concurrent/duration/FiniteDuration;)V
      82: getstatic     #128                // Field scala/runtime/BoxedUnit.UNIT:Lscala/runtime/BoxedUnit;
      85: astore_3
      86: return
      87: new           #137                // class scala/MatchError
      90: dup
      91: aload_2
      92: invokespecial #140                // Method scala/MatchError."<init>":(Ljava/lang/Object;)V
      95: athrow

  public static void $init$(akka.stream.impl.StreamSubscriptionTimeoutSupport);
    Code:
       0: return
}
