Compiled from "StreamLayout.scala"
public final class akka.stream.impl.StreamLayout$ {
  public static final akka.stream.impl.StreamLayout$ MODULE$;

  private final boolean Debug;

  public static {};
    Code:
       0: new           #2                  // class akka/stream/impl/StreamLayout$
       3: invokespecial #12                 // Method "<init>":()V
       6: return

  public final boolean Debug();
    Code:
       0: iconst_0
       1: ireturn

  public final void validate(akka.stream.impl.StreamLayout$Module, int, boolean, java.util.Map<java.lang.Object, java.lang.Integer>);
    Code:
       0: getstatic     #23                 // Field scala/package$.MODULE$:Lscala/package$;
       3: invokevirtual #27                 // Method scala/package$.Iterator:()Lscala/collection/Iterator$;
       6: iconst_1
       7: invokevirtual #33                 // Method scala/collection/Iterator$.from:(I)Lscala/collection/Iterator;
      10: astore        5
      12: aload_1
      13: invokeinterface #39,  1           // InterfaceMethod akka/stream/impl/StreamLayout$Module.shape:()Lakka/stream/Shape;
      18: invokevirtual #45                 // Method akka/stream/Shape.inlets:()Lscala/collection/immutable/Seq;
      21: invokeinterface #51,  1           // InterfaceMethod scala/collection/immutable/Seq.toSet:()Lscala/collection/immutable/Set;
      26: astore        6
      28: aload_1
      29: invokeinterface #39,  1           // InterfaceMethod akka/stream/impl/StreamLayout$Module.shape:()Lakka/stream/Shape;
      34: invokevirtual #54                 // Method akka/stream/Shape.outlets:()Lscala/collection/immutable/Seq;
      37: invokeinterface #51,  1           // InterfaceMethod scala/collection/immutable/Seq.toSet:()Lscala/collection/immutable/Set;
      42: astore        7
      44: getstatic     #59                 // Field scala/collection/immutable/Nil$.MODULE$:Lscala/collection/immutable/Nil$;
      47: astore        8
      49: aload         6
      51: invokeinterface #65,  1           // InterfaceMethod scala/collection/immutable/Set.size:()I
      56: aload_1
      57: invokeinterface #39,  1           // InterfaceMethod akka/stream/impl/StreamLayout$Module.shape:()Lakka/stream/Shape;
      62: invokevirtual #45                 // Method akka/stream/Shape.inlets:()Lscala/collection/immutable/Seq;
      65: invokeinterface #66,  1           // InterfaceMethod scala/collection/immutable/Seq.size:()I
      70: if_icmpeq     115
      73: aload         8
      75: new           #68                 // class scala/collection/mutable/StringBuilder
      78: dup
      79: invokespecial #69                 // Method scala/collection/mutable/StringBuilder."<init>":()V
      82: ldc           #71                 // String shape has duplicate inlets:
      84: invokevirtual #75                 // Method scala/collection/mutable/StringBuilder.append:(Ljava/lang/Object;)Lscala/collection/mutable/StringBuilder;
      87: aload_0
      88: aload_1
      89: invokeinterface #39,  1           // InterfaceMethod akka/stream/impl/StreamLayout$Module.shape:()Lakka/stream/Shape;
      94: invokevirtual #45                 // Method akka/stream/Shape.inlets:()Lscala/collection/immutable/Seq;
      97: aload         4
      99: aload         5
     101: invokespecial #79                 // Method ins$1:(Lscala/collection/Iterable;Ljava/util/Map;Lscala/collection/Iterator;)Ljava/lang/String;
     104: invokevirtual #75                 // Method scala/collection/mutable/StringBuilder.append:(Ljava/lang/Object;)Lscala/collection/mutable/StringBuilder;
     107: invokevirtual #83                 // Method scala/collection/mutable/StringBuilder.toString:()Ljava/lang/String;
     110: invokevirtual #89                 // Method scala/collection/immutable/List.$colon$colon:(Ljava/lang/Object;)Lscala/collection/immutable/List;
     113: astore        8
     115: aload         6
     117: aload_1
     118: invokeinterface #92,  1           // InterfaceMethod akka/stream/impl/StreamLayout$Module.inPorts:()Lscala/collection/immutable/Set;
     123: astore        9
     125: dup
     126: ifnonnull     138
     129: pop
     130: aload         9
     132: ifnull        249
     135: goto          146
     138: aload         9
     140: invokevirtual #96                 // Method java/lang/Object.equals:(Ljava/lang/Object;)Z
     143: ifne          249
     146: aload         8
     148: new           #98                 // class scala/StringContext
     151: dup
     152: getstatic     #103                // Field scala/Predef$.MODULE$:Lscala/Predef$;
     155: iconst_3
     156: anewarray     #105                // class java/lang/String
     159: dup
     160: iconst_0
     161: ldc           #107                // String shape has extra
     163: aastore
     164: dup
     165: iconst_1
     166: ldc           #109                // String , module has extra
     168: aastore
     169: dup
     170: iconst_2
     171: ldc           #111                // String
     173: aastore
     174: checkcast     #113                // class "[Ljava/lang/Object;"
     177: invokevirtual #117                // Method scala/Predef$.wrapRefArray:([Ljava/lang/Object;)Lscala/collection/mutable/WrappedArray;
     180: invokespecial #120                // Method scala/StringContext."<init>":(Lscala/collection/Seq;)V
     183: getstatic     #103                // Field scala/Predef$.MODULE$:Lscala/Predef$;
     186: iconst_2
     187: anewarray     #4                  // class java/lang/Object
     190: dup
     191: iconst_0
     192: aload_0
     193: aload         6
     195: aload_1
     196: invokeinterface #92,  1           // InterfaceMethod akka/stream/impl/StreamLayout$Module.inPorts:()Lscala/collection/immutable/Set;
     201: invokeinterface #124,  2          // InterfaceMethod scala/collection/immutable/Set.diff:(Lscala/collection/GenSet;)Lscala/collection/Set;
     206: aload         4
     208: aload         5
     210: invokespecial #79                 // Method ins$1:(Lscala/collection/Iterable;Ljava/util/Map;Lscala/collection/Iterator;)Ljava/lang/String;
     213: aastore
     214: dup
     215: iconst_1
     216: aload_0
     217: aload_1
     218: invokeinterface #92,  1           // InterfaceMethod akka/stream/impl/StreamLayout$Module.inPorts:()Lscala/collection/immutable/Set;
     223: aload         6
     225: invokeinterface #124,  2          // InterfaceMethod scala/collection/immutable/Set.diff:(Lscala/collection/GenSet;)Lscala/collection/Set;
     230: aload         4
     232: aload         5
     234: invokespecial #79                 // Method ins$1:(Lscala/collection/Iterable;Ljava/util/Map;Lscala/collection/Iterator;)Ljava/lang/String;
     237: aastore
     238: invokevirtual #128                // Method scala/Predef$.genericWrapArray:(Ljava/lang/Object;)Lscala/collection/mutable/WrappedArray;
     241: invokevirtual #132                // Method scala/StringContext.s:(Lscala/collection/Seq;)Ljava/lang/String;
     244: invokevirtual #89                 // Method scala/collection/immutable/List.$colon$colon:(Ljava/lang/Object;)Lscala/collection/immutable/List;
     247: astore        8
     249: aload         6
     251: aload_1
     252: invokeinterface #136,  1          // InterfaceMethod akka/stream/impl/StreamLayout$Module.upstreams:()Lscala/collection/immutable/Map;
     257: invokeinterface #141,  1          // InterfaceMethod scala/collection/immutable/Map.keySet:()Lscala/collection/immutable/Set;
     262: invokeinterface #145,  2          // InterfaceMethod scala/collection/immutable/Set.intersect:(Lscala/collection/GenSet;)Ljava/lang/Object;
     267: checkcast     #147                // class scala/collection/TraversableOnce
     270: invokeinterface #150,  1          // InterfaceMethod scala/collection/TraversableOnce.nonEmpty:()Z
     275: ifeq          349
     278: aload         8
     280: new           #98                 // class scala/StringContext
     283: dup
     284: getstatic     #103                // Field scala/Predef$.MODULE$:Lscala/Predef$;
     287: iconst_2
     288: anewarray     #105                // class java/lang/String
     291: dup
     292: iconst_0
     293: ldc           #152                // String found connected inlets
     295: aastore
     296: dup
     297: iconst_1
     298: ldc           #111                // String
     300: aastore
     301: checkcast     #113                // class "[Ljava/lang/Object;"
     304: invokevirtual #117                // Method scala/Predef$.wrapRefArray:([Ljava/lang/Object;)Lscala/collection/mutable/WrappedArray;
     307: invokespecial #120                // Method scala/StringContext."<init>":(Lscala/collection/Seq;)V
     310: getstatic     #103                // Field scala/Predef$.MODULE$:Lscala/Predef$;
     313: iconst_1
     314: anewarray     #4                  // class java/lang/Object
     317: dup
     318: iconst_0
     319: aload         6
     321: aload_1
     322: invokeinterface #136,  1          // InterfaceMethod akka/stream/impl/StreamLayout$Module.upstreams:()Lscala/collection/immutable/Map;
     327: invokeinterface #141,  1          // InterfaceMethod scala/collection/immutable/Map.keySet:()Lscala/collection/immutable/Set;
     332: invokeinterface #145,  2          // InterfaceMethod scala/collection/immutable/Set.intersect:(Lscala/collection/GenSet;)Ljava/lang/Object;
     337: aastore
     338: invokevirtual #128                // Method scala/Predef$.genericWrapArray:(Ljava/lang/Object;)Lscala/collection/mutable/WrappedArray;
     341: invokevirtual #132                // Method scala/StringContext.s:(Lscala/collection/Seq;)Ljava/lang/String;
     344: invokevirtual #89                 // Method scala/collection/immutable/List.$colon$colon:(Ljava/lang/Object;)Lscala/collection/immutable/List;
     347: astore        8
     349: aload         7
     351: invokeinterface #65,  1           // InterfaceMethod scala/collection/immutable/Set.size:()I
     356: aload_1
     357: invokeinterface #39,  1           // InterfaceMethod akka/stream/impl/StreamLayout$Module.shape:()Lakka/stream/Shape;
     362: invokevirtual #54                 // Method akka/stream/Shape.outlets:()Lscala/collection/immutable/Seq;
     365: invokeinterface #66,  1           // InterfaceMethod scala/collection/immutable/Seq.size:()I
     370: if_icmpeq     415
     373: aload         8
     375: new           #68                 // class scala/collection/mutable/StringBuilder
     378: dup
     379: invokespecial #69                 // Method scala/collection/mutable/StringBuilder."<init>":()V
     382: ldc           #154                // String shape has duplicate outlets:
     384: invokevirtual #75                 // Method scala/collection/mutable/StringBuilder.append:(Ljava/lang/Object;)Lscala/collection/mutable/StringBuilder;
     387: aload_0
     388: aload_1
     389: invokeinterface #39,  1           // InterfaceMethod akka/stream/impl/StreamLayout$Module.shape:()Lakka/stream/Shape;
     394: invokevirtual #54                 // Method akka/stream/Shape.outlets:()Lscala/collection/immutable/Seq;
     397: aload         4
     399: aload         5
     401: invokespecial #157                // Method outs$1:(Lscala/collection/Iterable;Ljava/util/Map;Lscala/collection/Iterator;)Ljava/lang/String;
     404: invokevirtual #75                 // Method scala/collection/mutable/StringBuilder.append:(Ljava/lang/Object;)Lscala/collection/mutable/StringBuilder;
     407: invokevirtual #83                 // Method scala/collection/mutable/StringBuilder.toString:()Ljava/lang/String;
     410: invokevirtual #89                 // Method scala/collection/immutable/List.$colon$colon:(Ljava/lang/Object;)Lscala/collection/immutable/List;
     413: astore        8
     415: aload         7
     417: aload_1
     418: invokeinterface #160,  1          // InterfaceMethod akka/stream/impl/StreamLayout$Module.outPorts:()Lscala/collection/immutable/Set;
     423: astore        10
     425: dup
     426: ifnonnull     438
     429: pop
     430: aload         10
     432: ifnull        549
     435: goto          446
     438: aload         10
     440: invokevirtual #96                 // Method java/lang/Object.equals:(Ljava/lang/Object;)Z
     443: ifne          549
     446: aload         8
     448: new           #98                 // class scala/StringContext
     451: dup
     452: getstatic     #103                // Field scala/Predef$.MODULE$:Lscala/Predef$;
     455: iconst_3
     456: anewarray     #105                // class java/lang/String
     459: dup
     460: iconst_0
     461: ldc           #107                // String shape has extra
     463: aastore
     464: dup
     465: iconst_1
     466: ldc           #109                // String , module has extra
     468: aastore
     469: dup
     470: iconst_2
     471: ldc           #111                // String
     473: aastore
     474: checkcast     #113                // class "[Ljava/lang/Object;"
     477: invokevirtual #117                // Method scala/Predef$.wrapRefArray:([Ljava/lang/Object;)Lscala/collection/mutable/WrappedArray;
     480: invokespecial #120                // Method scala/StringContext."<init>":(Lscala/collection/Seq;)V
     483: getstatic     #103                // Field scala/Predef$.MODULE$:Lscala/Predef$;
     486: iconst_2
     487: anewarray     #4                  // class java/lang/Object
     490: dup
     491: iconst_0
     492: aload_0
     493: aload         7
     495: aload_1
     496: invokeinterface #160,  1          // InterfaceMethod akka/stream/impl/StreamLayout$Module.outPorts:()Lscala/collection/immutable/Set;
     501: invokeinterface #124,  2          // InterfaceMethod scala/collection/immutable/Set.diff:(Lscala/collection/GenSet;)Lscala/collection/Set;
     506: aload         4
     508: aload         5
     510: invokespecial #157                // Method outs$1:(Lscala/collection/Iterable;Ljava/util/Map;Lscala/collection/Iterator;)Ljava/lang/String;
     513: aastore
     514: dup
     515: iconst_1
     516: aload_0
     517: aload_1
     518: invokeinterface #160,  1          // InterfaceMethod akka/stream/impl/StreamLayout$Module.outPorts:()Lscala/collection/immutable/Set;
     523: aload         7
     525: invokeinterface #124,  2          // InterfaceMethod scala/collection/immutable/Set.diff:(Lscala/collection/GenSet;)Lscala/collection/Set;
     530: aload         4
     532: aload         5
     534: invokespecial #157                // Method outs$1:(Lscala/collection/Iterable;Ljava/util/Map;Lscala/collection/Iterator;)Ljava/lang/String;
     537: aastore
     538: invokevirtual #128                // Method scala/Predef$.genericWrapArray:(Ljava/lang/Object;)Lscala/collection/mutable/WrappedArray;
     541: invokevirtual #132                // Method scala/StringContext.s:(Lscala/collection/Seq;)Ljava/lang/String;
     544: invokevirtual #89                 // Method scala/collection/immutable/List.$colon$colon:(Ljava/lang/Object;)Lscala/collection/immutable/List;
     547: astore        8
     549: aload         7
     551: aload_1
     552: invokeinterface #163,  1          // InterfaceMethod akka/stream/impl/StreamLayout$Module.downstreams:()Lscala/collection/immutable/Map;
     557: invokeinterface #141,  1          // InterfaceMethod scala/collection/immutable/Map.keySet:()Lscala/collection/immutable/Set;
     562: invokeinterface #145,  2          // InterfaceMethod scala/collection/immutable/Set.intersect:(Lscala/collection/GenSet;)Ljava/lang/Object;
     567: checkcast     #147                // class scala/collection/TraversableOnce
     570: invokeinterface #150,  1          // InterfaceMethod scala/collection/TraversableOnce.nonEmpty:()Z
     575: ifeq          649
     578: aload         8
     580: new           #98                 // class scala/StringContext
     583: dup
     584: getstatic     #103                // Field scala/Predef$.MODULE$:Lscala/Predef$;
     587: iconst_2
     588: anewarray     #105                // class java/lang/String
     591: dup
     592: iconst_0
     593: ldc           #165                // String found connected outlets
     595: aastore
     596: dup
     597: iconst_1
     598: ldc           #111                // String
     600: aastore
     601: checkcast     #113                // class "[Ljava/lang/Object;"
     604: invokevirtual #117                // Method scala/Predef$.wrapRefArray:([Ljava/lang/Object;)Lscala/collection/mutable/WrappedArray;
     607: invokespecial #120                // Method scala/StringContext."<init>":(Lscala/collection/Seq;)V
     610: getstatic     #103                // Field scala/Predef$.MODULE$:Lscala/Predef$;
     613: iconst_1
     614: anewarray     #4                  // class java/lang/Object
     617: dup
     618: iconst_0
     619: aload         7
     621: aload_1
     622: invokeinterface #163,  1          // InterfaceMethod akka/stream/impl/StreamLayout$Module.downstreams:()Lscala/collection/immutable/Map;
     627: invokeinterface #141,  1          // InterfaceMethod scala/collection/immutable/Map.keySet:()Lscala/collection/immutable/Set;
     632: invokeinterface #145,  2          // InterfaceMethod scala/collection/immutable/Set.intersect:(Lscala/collection/GenSet;)Ljava/lang/Object;
     637: aastore
     638: invokevirtual #128                // Method scala/Predef$.genericWrapArray:(Ljava/lang/Object;)Lscala/collection/mutable/WrappedArray;
     641: invokevirtual #132                // Method scala/StringContext.s:(Lscala/collection/Seq;)Ljava/lang/String;
     644: invokevirtual #89                 // Method scala/collection/immutable/List.$colon$colon:(Ljava/lang/Object;)Lscala/collection/immutable/List;
     647: astore        8
     649: aload_1
     650: invokeinterface #136,  1          // InterfaceMethod akka/stream/impl/StreamLayout$Module.upstreams:()Lscala/collection/immutable/Map;
     655: invokeinterface #166,  1          // InterfaceMethod scala/collection/immutable/Map.toSet:()Lscala/collection/immutable/Set;
     660: astore        11
     662: aload         11
     664: new           #168                // class akka/stream/impl/StreamLayout$$anonfun$1
     667: dup
     668: invokespecial #169                // Method akka/stream/impl/StreamLayout$$anonfun$1."<init>":()V
     671: getstatic     #174                // Field scala/collection/immutable/Set$.MODULE$:Lscala/collection/immutable/Set$;
     674: invokevirtual #178                // Method scala/collection/immutable/Set$.canBuildFrom:()Lscala/collection/generic/CanBuildFrom;
     677: invokeinterface #182,  3          // InterfaceMethod scala/collection/immutable/Set.map:(Lscala/Function1;Lscala/collection/generic/CanBuildFrom;)Ljava/lang/Object;
     682: checkcast     #61                 // class scala/collection/immutable/Set
     685: astore        12
     687: aload_1
     688: invokeinterface #163,  1          // InterfaceMethod akka/stream/impl/StreamLayout$Module.downstreams:()Lscala/collection/immutable/Map;
     693: invokeinterface #166,  1          // InterfaceMethod scala/collection/immutable/Map.toSet:()Lscala/collection/immutable/Set;
     698: astore        13
     700: aload         12
     702: aload         13
     704: invokeinterface #145,  2          // InterfaceMethod scala/collection/immutable/Set.intersect:(Lscala/collection/GenSet;)Ljava/lang/Object;
     709: checkcast     #61                 // class scala/collection/immutable/Set
     712: astore        14
     714: aload         13
     716: aload         12
     718: astore        15
     720: dup
     721: ifnonnull     733
     724: pop
     725: aload         15
     727: ifnull        836
     730: goto          741
     733: aload         15
     735: invokevirtual #96                 // Method java/lang/Object.equals:(Ljava/lang/Object;)Z
     738: ifne          836
     741: aload         8
     743: new           #98                 // class scala/StringContext
     746: dup
     747: getstatic     #103                // Field scala/Predef$.MODULE$:Lscala/Predef$;
     750: iconst_3
     751: anewarray     #105                // class java/lang/String
     754: dup
     755: iconst_0
     756: ldc           #184                // String inconsistent maps: ups
     758: aastore
     759: dup
     760: iconst_1
     761: ldc           #186                // String  downs
     763: aastore
     764: dup
     765: iconst_2
     766: ldc           #111                // String
     768: aastore
     769: checkcast     #113                // class "[Ljava/lang/Object;"
     772: invokevirtual #117                // Method scala/Predef$.wrapRefArray:([Ljava/lang/Object;)Lscala/collection/mutable/WrappedArray;
     775: invokespecial #120                // Method scala/StringContext."<init>":(Lscala/collection/Seq;)V
     778: getstatic     #103                // Field scala/Predef$.MODULE$:Lscala/Predef$;
     781: iconst_2
     782: anewarray     #4                  // class java/lang/Object
     785: dup
     786: iconst_0
     787: aload_0
     788: aload         12
     790: aload         14
     792: invokeinterface #124,  2          // InterfaceMethod scala/collection/immutable/Set.diff:(Lscala/collection/GenSet;)Lscala/collection/Set;
     797: aload         4
     799: aload         5
     801: invokespecial #189                // Method pairs$1:(Lscala/collection/Iterable;Ljava/util/Map;Lscala/collection/Iterator;)Ljava/lang/String;
     804: aastore
     805: dup
     806: iconst_1
     807: aload_0
     808: aload         13
     810: aload         14
     812: invokeinterface #124,  2          // InterfaceMethod scala/collection/immutable/Set.diff:(Lscala/collection/GenSet;)Lscala/collection/Set;
     817: aload         4
     819: aload         5
     821: invokespecial #189                // Method pairs$1:(Lscala/collection/Iterable;Ljava/util/Map;Lscala/collection/Iterator;)Ljava/lang/String;
     824: aastore
     825: invokevirtual #128                // Method scala/Predef$.genericWrapArray:(Ljava/lang/Object;)Lscala/collection/mutable/WrappedArray;
     828: invokevirtual #132                // Method scala/StringContext.s:(Lscala/collection/Seq;)Ljava/lang/String;
     831: invokevirtual #89                 // Method scala/collection/immutable/List.$colon$colon:(Ljava/lang/Object;)Lscala/collection/immutable/List;
     834: astore        8
     836: aload_1
     837: invokeinterface #192,  1          // InterfaceMethod akka/stream/impl/StreamLayout$Module.subModules:()Lscala/collection/immutable/Set;
     842: new           #194                // class scala/Tuple4
     845: dup
     846: getstatic     #103                // Field scala/Predef$.MODULE$:Lscala/Predef$;
     849: invokevirtual #198                // Method scala/Predef$.Set:()Lscala/collection/immutable/Set$;
     852: invokevirtual #201                // Method scala/collection/immutable/Set$.empty:()Lscala/collection/immutable/Set;
     855: getstatic     #103                // Field scala/Predef$.MODULE$:Lscala/Predef$;
     858: invokevirtual #198                // Method scala/Predef$.Set:()Lscala/collection/immutable/Set$;
     861: invokevirtual #201                // Method scala/collection/immutable/Set$.empty:()Lscala/collection/immutable/Set;
     864: getstatic     #103                // Field scala/Predef$.MODULE$:Lscala/Predef$;
     867: invokevirtual #198                // Method scala/Predef$.Set:()Lscala/collection/immutable/Set$;
     870: invokevirtual #201                // Method scala/collection/immutable/Set$.empty:()Lscala/collection/immutable/Set;
     873: getstatic     #103                // Field scala/Predef$.MODULE$:Lscala/Predef$;
     876: invokevirtual #198                // Method scala/Predef$.Set:()Lscala/collection/immutable/Set$;
     879: invokevirtual #201                // Method scala/collection/immutable/Set$.empty:()Lscala/collection/immutable/Set;
     882: invokespecial #204                // Method scala/Tuple4."<init>":(Ljava/lang/Object;Ljava/lang/Object;Ljava/lang/Object;Ljava/lang/Object;)V
     885: new           #206                // class akka/stream/impl/StreamLayout$$anonfun$2
     888: dup
     889: invokespecial #207                // Method akka/stream/impl/StreamLayout$$anonfun$2."<init>":()V
     892: invokeinterface #211,  3          // InterfaceMethod scala/collection/immutable/Set.foldLeft:(Ljava/lang/Object;Lscala/Function2;)Ljava/lang/Object;
     897: checkcast     #194                // class scala/Tuple4
     900: astore        17
     902: aload         17
     904: ifnull        2051
     907: aload         17
     909: invokevirtual #215                // Method scala/Tuple4._1:()Ljava/lang/Object;
     912: checkcast     #61                 // class scala/collection/immutable/Set
     915: astore        18
     917: aload         17
     919: invokevirtual #218                // Method scala/Tuple4._2:()Ljava/lang/Object;
     922: checkcast     #61                 // class scala/collection/immutable/Set
     925: astore        19
     927: aload         17
     929: invokevirtual #221                // Method scala/Tuple4._3:()Ljava/lang/Object;
     932: checkcast     #61                 // class scala/collection/immutable/Set
     935: astore        20
     937: aload         17
     939: invokevirtual #224                // Method scala/Tuple4._4:()Ljava/lang/Object;
     942: checkcast     #61                 // class scala/collection/immutable/Set
     945: astore        21
     947: new           #194                // class scala/Tuple4
     950: dup
     951: aload         18
     953: aload         19
     955: aload         20
     957: aload         21
     959: invokespecial #204                // Method scala/Tuple4."<init>":(Ljava/lang/Object;Ljava/lang/Object;Ljava/lang/Object;Ljava/lang/Object;)V
     962: astore        22
     964: aload         22
     966: astore        16
     968: aload         16
     970: invokevirtual #215                // Method scala/Tuple4._1:()Ljava/lang/Object;
     973: checkcast     #61                 // class scala/collection/immutable/Set
     976: astore        23
     978: aload         16
     980: invokevirtual #218                // Method scala/Tuple4._2:()Ljava/lang/Object;
     983: checkcast     #61                 // class scala/collection/immutable/Set
     986: astore        24
     988: aload         16
     990: invokevirtual #221                // Method scala/Tuple4._3:()Ljava/lang/Object;
     993: checkcast     #61                 // class scala/collection/immutable/Set
     996: astore        25
     998: aload         16
    1000: invokevirtual #224                // Method scala/Tuple4._4:()Ljava/lang/Object;
    1003: checkcast     #61                 // class scala/collection/immutable/Set
    1006: astore        26
    1008: aload         24
    1010: invokeinterface #225,  1          // InterfaceMethod scala/collection/immutable/Set.nonEmpty:()Z
    1015: ifeq          1081
    1018: aload         8
    1020: new           #98                 // class scala/StringContext
    1023: dup
    1024: getstatic     #103                // Field scala/Predef$.MODULE$:Lscala/Predef$;
    1027: iconst_2
    1028: anewarray     #105                // class java/lang/String
    1031: dup
    1032: iconst_0
    1033: ldc           #227                // String duplicate ports in submodules
    1035: aastore
    1036: dup
    1037: iconst_1
    1038: ldc           #111                // String
    1040: aastore
    1041: checkcast     #113                // class "[Ljava/lang/Object;"
    1044: invokevirtual #117                // Method scala/Predef$.wrapRefArray:([Ljava/lang/Object;)Lscala/collection/mutable/WrappedArray;
    1047: invokespecial #120                // Method scala/StringContext."<init>":(Lscala/collection/Seq;)V
    1050: getstatic     #103                // Field scala/Predef$.MODULE$:Lscala/Predef$;
    1053: iconst_1
    1054: anewarray     #4                  // class java/lang/Object
    1057: dup
    1058: iconst_0
    1059: aload_0
    1060: aload         24
    1062: aload         4
    1064: aload         5
    1066: invokespecial #79                 // Method ins$1:(Lscala/collection/Iterable;Ljava/util/Map;Lscala/collection/Iterator;)Ljava/lang/String;
    1069: aastore
    1070: invokevirtual #128                // Method scala/Predef$.genericWrapArray:(Ljava/lang/Object;)Lscala/collection/mutable/WrappedArray;
    1073: invokevirtual #132                // Method scala/StringContext.s:(Lscala/collection/Seq;)Ljava/lang/String;
    1076: invokevirtual #89                 // Method scala/collection/immutable/List.$colon$colon:(Ljava/lang/Object;)Lscala/collection/immutable/List;
    1079: astore        8
    1081: aload         26
    1083: invokeinterface #225,  1          // InterfaceMethod scala/collection/immutable/Set.nonEmpty:()Z
    1088: ifeq          1154
    1091: aload         8
    1093: new           #98                 // class scala/StringContext
    1096: dup
    1097: getstatic     #103                // Field scala/Predef$.MODULE$:Lscala/Predef$;
    1100: iconst_2
    1101: anewarray     #105                // class java/lang/String
    1104: dup
    1105: iconst_0
    1106: ldc           #227                // String duplicate ports in submodules
    1108: aastore
    1109: dup
    1110: iconst_1
    1111: ldc           #111                // String
    1113: aastore
    1114: checkcast     #113                // class "[Ljava/lang/Object;"
    1117: invokevirtual #117                // Method scala/Predef$.wrapRefArray:([Ljava/lang/Object;)Lscala/collection/mutable/WrappedArray;
    1120: invokespecial #120                // Method scala/StringContext."<init>":(Lscala/collection/Seq;)V
    1123: getstatic     #103                // Field scala/Predef$.MODULE$:Lscala/Predef$;
    1126: iconst_1
    1127: anewarray     #4                  // class java/lang/Object
    1130: dup
    1131: iconst_0
    1132: aload_0
    1133: aload         26
    1135: aload         4
    1137: aload         5
    1139: invokespecial #157                // Method outs$1:(Lscala/collection/Iterable;Ljava/util/Map;Lscala/collection/Iterator;)Ljava/lang/String;
    1142: aastore
    1143: invokevirtual #128                // Method scala/Predef$.genericWrapArray:(Ljava/lang/Object;)Lscala/collection/mutable/WrappedArray;
    1146: invokevirtual #132                // Method scala/StringContext.s:(Lscala/collection/Seq;)Ljava/lang/String;
    1149: invokevirtual #89                 // Method scala/collection/immutable/List.$colon$colon:(Ljava/lang/Object;)Lscala/collection/immutable/List;
    1152: astore        8
    1154: aload_1
    1155: invokeinterface #230,  1          // InterfaceMethod akka/stream/impl/StreamLayout$Module.isSealed:()Z
    1160: ifne          1250
    1163: aload         6
    1165: aload         23
    1167: invokeinterface #124,  2          // InterfaceMethod scala/collection/immutable/Set.diff:(Lscala/collection/GenSet;)Lscala/collection/Set;
    1172: invokeinterface #233,  1          // InterfaceMethod scala/collection/Set.nonEmpty:()Z
    1177: ifeq          1250
    1180: aload         8
    1182: new           #98                 // class scala/StringContext
    1185: dup
    1186: getstatic     #103                // Field scala/Predef$.MODULE$:Lscala/Predef$;
    1189: iconst_2
    1190: anewarray     #105                // class java/lang/String
    1193: dup
    1194: iconst_0
    1195: ldc           #235                // String foreign inlets
    1197: aastore
    1198: dup
    1199: iconst_1
    1200: ldc           #111                // String
    1202: aastore
    1203: checkcast     #113                // class "[Ljava/lang/Object;"
    1206: invokevirtual #117                // Method scala/Predef$.wrapRefArray:([Ljava/lang/Object;)Lscala/collection/mutable/WrappedArray;
    1209: invokespecial #120                // Method scala/StringContext."<init>":(Lscala/collection/Seq;)V
    1212: getstatic     #103                // Field scala/Predef$.MODULE$:Lscala/Predef$;
    1215: iconst_1
    1216: anewarray     #4                  // class java/lang/Object
    1219: dup
    1220: iconst_0
    1221: aload_0
    1222: aload         6
    1224: aload         23
    1226: invokeinterface #124,  2          // InterfaceMethod scala/collection/immutable/Set.diff:(Lscala/collection/GenSet;)Lscala/collection/Set;
    1231: aload         4
    1233: aload         5
    1235: invokespecial #79                 // Method ins$1:(Lscala/collection/Iterable;Ljava/util/Map;Lscala/collection/Iterator;)Ljava/lang/String;
    1238: aastore
    1239: invokevirtual #128                // Method scala/Predef$.genericWrapArray:(Ljava/lang/Object;)Lscala/collection/mutable/WrappedArray;
    1242: invokevirtual #132                // Method scala/StringContext.s:(Lscala/collection/Seq;)Ljava/lang/String;
    1245: invokevirtual #89                 // Method scala/collection/immutable/List.$colon$colon:(Ljava/lang/Object;)Lscala/collection/immutable/List;
    1248: astore        8
    1250: aload_1
    1251: invokeinterface #230,  1          // InterfaceMethod akka/stream/impl/StreamLayout$Module.isSealed:()Z
    1256: ifne          1346
    1259: aload         7
    1261: aload         25
    1263: invokeinterface #124,  2          // InterfaceMethod scala/collection/immutable/Set.diff:(Lscala/collection/GenSet;)Lscala/collection/Set;
    1268: invokeinterface #233,  1          // InterfaceMethod scala/collection/Set.nonEmpty:()Z
    1273: ifeq          1346
    1276: aload         8
    1278: new           #98                 // class scala/StringContext
    1281: dup
    1282: getstatic     #103                // Field scala/Predef$.MODULE$:Lscala/Predef$;
    1285: iconst_2
    1286: anewarray     #105                // class java/lang/String
    1289: dup
    1290: iconst_0
    1291: ldc           #237                // String foreign outlets
    1293: aastore
    1294: dup
    1295: iconst_1
    1296: ldc           #111                // String
    1298: aastore
    1299: checkcast     #113                // class "[Ljava/lang/Object;"
    1302: invokevirtual #117                // Method scala/Predef$.wrapRefArray:([Ljava/lang/Object;)Lscala/collection/mutable/WrappedArray;
    1305: invokespecial #120                // Method scala/StringContext."<init>":(Lscala/collection/Seq;)V
    1308: getstatic     #103                // Field scala/Predef$.MODULE$:Lscala/Predef$;
    1311: iconst_1
    1312: anewarray     #4                  // class java/lang/Object
    1315: dup
    1316: iconst_0
    1317: aload_0
    1318: aload         7
    1320: aload         25
    1322: invokeinterface #124,  2          // InterfaceMethod scala/collection/immutable/Set.diff:(Lscala/collection/GenSet;)Lscala/collection/Set;
    1327: aload         4
    1329: aload         5
    1331: invokespecial #157                // Method outs$1:(Lscala/collection/Iterable;Ljava/util/Map;Lscala/collection/Iterator;)Ljava/lang/String;
    1334: aastore
    1335: invokevirtual #128                // Method scala/Predef$.genericWrapArray:(Ljava/lang/Object;)Lscala/collection/mutable/WrappedArray;
    1338: invokevirtual #132                // Method scala/StringContext.s:(Lscala/collection/Seq;)Ljava/lang/String;
    1341: invokevirtual #89                 // Method scala/collection/immutable/List.$colon$colon:(Ljava/lang/Object;)Lscala/collection/immutable/List;
    1344: astore        8
    1346: aload         23
    1348: aload         6
    1350: invokeinterface #124,  2          // InterfaceMethod scala/collection/immutable/Set.diff:(Lscala/collection/GenSet;)Lscala/collection/Set;
    1355: aload_1
    1356: invokeinterface #136,  1          // InterfaceMethod akka/stream/impl/StreamLayout$Module.upstreams:()Lscala/collection/immutable/Map;
    1361: invokeinterface #141,  1          // InterfaceMethod scala/collection/immutable/Map.keySet:()Lscala/collection/immutable/Set;
    1366: invokeinterface #238,  2          // InterfaceMethod scala/collection/Set.diff:(Lscala/collection/GenSet;)Lscala/collection/Set;
    1371: checkcast     #61                 // class scala/collection/immutable/Set
    1374: astore        27
    1376: aload         27
    1378: invokeinterface #225,  1          // InterfaceMethod scala/collection/immutable/Set.nonEmpty:()Z
    1383: ifeq          1458
    1386: aload_1
    1387: invokeinterface #241,  1          // InterfaceMethod akka/stream/impl/StreamLayout$Module.isCopied:()Z
    1392: ifne          1458
    1395: aload         8
    1397: new           #98                 // class scala/StringContext
    1400: dup
    1401: getstatic     #103                // Field scala/Predef$.MODULE$:Lscala/Predef$;
    1404: iconst_2
    1405: anewarray     #105                // class java/lang/String
    1408: dup
    1409: iconst_0
    1410: ldc           #243                // String unconnected inlets
    1412: aastore
    1413: dup
    1414: iconst_1
    1415: ldc           #111                // String
    1417: aastore
    1418: checkcast     #113                // class "[Ljava/lang/Object;"
    1421: invokevirtual #117                // Method scala/Predef$.wrapRefArray:([Ljava/lang/Object;)Lscala/collection/mutable/WrappedArray;
    1424: invokespecial #120                // Method scala/StringContext."<init>":(Lscala/collection/Seq;)V
    1427: getstatic     #103                // Field scala/Predef$.MODULE$:Lscala/Predef$;
    1430: iconst_1
    1431: anewarray     #4                  // class java/lang/Object
    1434: dup
    1435: iconst_0
    1436: aload_0
    1437: aload         27
    1439: aload         4
    1441: aload         5
    1443: invokespecial #79                 // Method ins$1:(Lscala/collection/Iterable;Ljava/util/Map;Lscala/collection/Iterator;)Ljava/lang/String;
    1446: aastore
    1447: invokevirtual #128                // Method scala/Predef$.genericWrapArray:(Ljava/lang/Object;)Lscala/collection/mutable/WrappedArray;
    1450: invokevirtual #132                // Method scala/StringContext.s:(Lscala/collection/Seq;)Ljava/lang/String;
    1453: invokevirtual #89                 // Method scala/collection/immutable/List.$colon$colon:(Ljava/lang/Object;)Lscala/collection/immutable/List;
    1456: astore        8
    1458: aload         25
    1460: aload         7
    1462: invokeinterface #124,  2          // InterfaceMethod scala/collection/immutable/Set.diff:(Lscala/collection/GenSet;)Lscala/collection/Set;
    1467: aload_1
    1468: invokeinterface #163,  1          // InterfaceMethod akka/stream/impl/StreamLayout$Module.downstreams:()Lscala/collection/immutable/Map;
    1473: invokeinterface #141,  1          // InterfaceMethod scala/collection/immutable/Map.keySet:()Lscala/collection/immutable/Set;
    1478: invokeinterface #238,  2          // InterfaceMethod scala/collection/Set.diff:(Lscala/collection/GenSet;)Lscala/collection/Set;
    1483: checkcast     #61                 // class scala/collection/immutable/Set
    1486: astore        28
    1488: aload         28
    1490: invokeinterface #225,  1          // InterfaceMethod scala/collection/immutable/Set.nonEmpty:()Z
    1495: ifeq          1570
    1498: aload_1
    1499: invokeinterface #241,  1          // InterfaceMethod akka/stream/impl/StreamLayout$Module.isCopied:()Z
    1504: ifne          1570
    1507: aload         8
    1509: new           #98                 // class scala/StringContext
    1512: dup
    1513: getstatic     #103                // Field scala/Predef$.MODULE$:Lscala/Predef$;
    1516: iconst_2
    1517: anewarray     #105                // class java/lang/String
    1520: dup
    1521: iconst_0
    1522: ldc           #245                // String unconnected outlets
    1524: aastore
    1525: dup
    1526: iconst_1
    1527: ldc           #111                // String
    1529: aastore
    1530: checkcast     #113                // class "[Ljava/lang/Object;"
    1533: invokevirtual #117                // Method scala/Predef$.wrapRefArray:([Ljava/lang/Object;)Lscala/collection/mutable/WrappedArray;
    1536: invokespecial #120                // Method scala/StringContext."<init>":(Lscala/collection/Seq;)V
    1539: getstatic     #103                // Field scala/Predef$.MODULE$:Lscala/Predef$;
    1542: iconst_1
    1543: anewarray     #4                  // class java/lang/Object
    1546: dup
    1547: iconst_0
    1548: aload_0
    1549: aload         28
    1551: aload         4
    1553: aload         5
    1555: invokespecial #157                // Method outs$1:(Lscala/collection/Iterable;Ljava/util/Map;Lscala/collection/Iterator;)Ljava/lang/String;
    1558: aastore
    1559: invokevirtual #128                // Method scala/Predef$.genericWrapArray:(Ljava/lang/Object;)Lscala/collection/mutable/WrappedArray;
    1562: invokevirtual #132                // Method scala/StringContext.s:(Lscala/collection/Seq;)Ljava/lang/String;
    1565: invokevirtual #89                 // Method scala/collection/immutable/List.$colon$colon:(Ljava/lang/Object;)Lscala/collection/immutable/List;
    1568: astore        8
    1570: aload_0
    1571: aload_1
    1572: invokeinterface #249,  1          // InterfaceMethod akka/stream/impl/StreamLayout$Module.materializedValueComputation:()Lakka/stream/impl/StreamLayout$MaterializedValueNode;
    1577: invokespecial #253                // Method atomics$1:(Lakka/stream/impl/StreamLayout$MaterializedValueNode;)Lscala/collection/immutable/Set;
    1580: astore        29
    1582: aload_1
    1583: invokeinterface #192,  1          // InterfaceMethod akka/stream/impl/StreamLayout$Module.subModules:()Lscala/collection/immutable/Set;
    1588: new           #255                // class akka/stream/impl/StreamLayout$$anonfun$3
    1591: dup
    1592: invokespecial #256                // Method akka/stream/impl/StreamLayout$$anonfun$3."<init>":()V
    1595: getstatic     #174                // Field scala/collection/immutable/Set$.MODULE$:Lscala/collection/immutable/Set$;
    1598: invokevirtual #178                // Method scala/collection/immutable/Set$.canBuildFrom:()Lscala/collection/generic/CanBuildFrom;
    1601: invokeinterface #259,  3          // InterfaceMethod scala/collection/immutable/Set.flatMap:(Lscala/Function1;Lscala/collection/generic/CanBuildFrom;)Ljava/lang/Object;
    1606: checkcast     #61                 // class scala/collection/immutable/Set
    1609: astore        30
    1611: aload         29
    1613: aload_1
    1614: invokeinterface #192,  1          // InterfaceMethod akka/stream/impl/StreamLayout$Module.subModules:()Lscala/collection/immutable/Set;
    1619: invokeinterface #124,  2          // InterfaceMethod scala/collection/immutable/Set.diff:(Lscala/collection/GenSet;)Lscala/collection/Set;
    1624: aload         30
    1626: invokeinterface #238,  2          // InterfaceMethod scala/collection/Set.diff:(Lscala/collection/GenSet;)Lscala/collection/Set;
    1631: aload_1
    1632: invokeinterface #263,  2          // InterfaceMethod scala/collection/Set.$minus:(Ljava/lang/Object;)Lscala/collection/Set;
    1637: invokeinterface #233,  1          // InterfaceMethod scala/collection/Set.nonEmpty:()Z
    1642: ifeq          1734
    1645: aload         8
    1647: new           #98                 // class scala/StringContext
    1650: dup
    1651: getstatic     #103                // Field scala/Predef$.MODULE$:Lscala/Predef$;
    1654: iconst_2
    1655: anewarray     #105                // class java/lang/String
    1658: dup
    1659: iconst_0
    1660: ldc_w         #265                // String computation refers to non-existent modules [
    1663: aastore
    1664: dup
    1665: iconst_1
    1666: ldc_w         #267                // String ]
    1669: aastore
    1670: checkcast     #113                // class "[Ljava/lang/Object;"
    1673: invokevirtual #117                // Method scala/Predef$.wrapRefArray:([Ljava/lang/Object;)Lscala/collection/mutable/WrappedArray;
    1676: invokespecial #120                // Method scala/StringContext."<init>":(Lscala/collection/Seq;)V
    1679: getstatic     #103                // Field scala/Predef$.MODULE$:Lscala/Predef$;
    1682: iconst_1
    1683: anewarray     #4                  // class java/lang/Object
    1686: dup
    1687: iconst_0
    1688: aload         29
    1690: aload_1
    1691: invokeinterface #192,  1          // InterfaceMethod akka/stream/impl/StreamLayout$Module.subModules:()Lscala/collection/immutable/Set;
    1696: invokeinterface #124,  2          // InterfaceMethod scala/collection/immutable/Set.diff:(Lscala/collection/GenSet;)Lscala/collection/Set;
    1701: aload         30
    1703: invokeinterface #238,  2          // InterfaceMethod scala/collection/Set.diff:(Lscala/collection/GenSet;)Lscala/collection/Set;
    1708: aload_1
    1709: invokeinterface #263,  2          // InterfaceMethod scala/collection/Set.$minus:(Ljava/lang/Object;)Lscala/collection/Set;
    1714: ldc_w         #269                // String ,
    1717: invokeinterface #273,  2          // InterfaceMethod scala/collection/Set.mkString:(Ljava/lang/String;)Ljava/lang/String;
    1722: aastore
    1723: invokevirtual #128                // Method scala/Predef$.genericWrapArray:(Ljava/lang/Object;)Lscala/collection/mutable/WrappedArray;
    1726: invokevirtual #132                // Method scala/StringContext.s:(Lscala/collection/Seq;)Ljava/lang/String;
    1729: invokevirtual #89                 // Method scala/collection/immutable/List.$colon$colon:(Ljava/lang/Object;)Lscala/collection/immutable/List;
    1732: astore        8
    1734: iload_3
    1735: ifne          1746
    1738: aload         8
    1740: invokevirtual #274                // Method scala/collection/immutable/List.nonEmpty:()Z
    1743: ifeq          1750
    1746: iconst_1
    1747: goto          1751
    1750: iconst_0
    1751: istore        31
    1753: iload         31
    1755: ifeq          1951
    1758: new           #276                // class scala/collection/immutable/StringOps
    1761: dup
    1762: getstatic     #103                // Field scala/Predef$.MODULE$:Lscala/Predef$;
    1765: ldc_w         #278                // String
    1768: invokevirtual #281                // Method scala/Predef$.augmentString:(Ljava/lang/String;)Ljava/lang/String;
    1771: invokespecial #284                // Method scala/collection/immutable/StringOps."<init>":(Ljava/lang/String;)V
    1774: iload_2
    1775: iconst_2
    1776: imul
    1777: invokevirtual #288                // Method scala/collection/immutable/StringOps.$times:(I)Ljava/lang/String;
    1780: astore        32
    1782: getstatic     #103                // Field scala/Predef$.MODULE$:Lscala/Predef$;
    1785: new           #98                 // class scala/StringContext
    1788: dup
    1789: getstatic     #103                // Field scala/Predef$.MODULE$:Lscala/Predef$;
    1792: bipush        6
    1794: anewarray     #105                // class java/lang/String
    1797: dup
    1798: iconst_0
    1799: ldc           #111                // String
    1801: aastore
    1802: dup
    1803: iconst_1
    1804: ldc           #111                // String
    1806: aastore
    1807: dup
    1808: iconst_2
    1809: ldc_w         #290                // String (
    1812: aastore
    1813: dup
    1814: iconst_3
    1815: ldc_w         #292                // String ):
    1818: aastore
    1819: dup
    1820: iconst_4
    1821: ldc_w         #278                // String
    1824: aastore
    1825: dup
    1826: iconst_5
    1827: ldc           #111                // String
    1829: aastore
    1830: checkcast     #113                // class "[Ljava/lang/Object;"
    1833: invokevirtual #117                // Method scala/Predef$.wrapRefArray:([Ljava/lang/Object;)Lscala/collection/mutable/WrappedArray;
    1836: invokespecial #120                // Method scala/StringContext."<init>":(Lscala/collection/Seq;)V
    1839: getstatic     #103                // Field scala/Predef$.MODULE$:Lscala/Predef$;
    1842: iconst_5
    1843: anewarray     #4                  // class java/lang/Object
    1846: dup
    1847: iconst_0
    1848: aload         32
    1850: aastore
    1851: dup
    1852: iconst_1
    1853: getstatic     #297                // Field akka/event/Logging$.MODULE$:Lakka/event/Logging$;
    1856: aload_0
    1857: invokevirtual #301                // Method akka/event/Logging$.simpleName:(Ljava/lang/Object;)Ljava/lang/String;
    1860: aastore
    1861: dup
    1862: iconst_2
    1863: aload_1
    1864: invokeinterface #39,  1           // InterfaceMethod akka/stream/impl/StreamLayout$Module.shape:()Lakka/stream/Shape;
    1869: aastore
    1870: dup
    1871: iconst_3
    1872: aload_0
    1873: aload_1
    1874: invokeinterface #92,  1           // InterfaceMethod akka/stream/impl/StreamLayout$Module.inPorts:()Lscala/collection/immutable/Set;
    1879: aload         4
    1881: aload         5
    1883: invokespecial #79                 // Method ins$1:(Lscala/collection/Iterable;Ljava/util/Map;Lscala/collection/Iterator;)Ljava/lang/String;
    1886: aastore
    1887: dup
    1888: iconst_4
    1889: aload_0
    1890: aload_1
    1891: invokeinterface #160,  1          // InterfaceMethod akka/stream/impl/StreamLayout$Module.outPorts:()Lscala/collection/immutable/Set;
    1896: aload         4
    1898: aload         5
    1900: invokespecial #157                // Method outs$1:(Lscala/collection/Iterable;Ljava/util/Map;Lscala/collection/Iterator;)Ljava/lang/String;
    1903: aastore
    1904: invokevirtual #128                // Method scala/Predef$.genericWrapArray:(Ljava/lang/Object;)Lscala/collection/mutable/WrappedArray;
    1907: invokevirtual #132                // Method scala/StringContext.s:(Lscala/collection/Seq;)Ljava/lang/String;
    1910: invokevirtual #305                // Method scala/Predef$.println:(Ljava/lang/Object;)V
    1913: aload_1
    1914: invokeinterface #163,  1          // InterfaceMethod akka/stream/impl/StreamLayout$Module.downstreams:()Lscala/collection/immutable/Map;
    1919: new           #307                // class akka/stream/impl/StreamLayout$$anonfun$validate$1
    1922: dup
    1923: aload         4
    1925: aload         5
    1927: aload         32
    1929: invokespecial #310                // Method akka/stream/impl/StreamLayout$$anonfun$validate$1."<init>":(Ljava/util/Map;Lscala/collection/Iterator;Ljava/lang/String;)V
    1932: invokeinterface #314,  2          // InterfaceMethod scala/collection/immutable/Map.foreach:(Lscala/Function1;)V
    1937: aload         8
    1939: new           #316                // class akka/stream/impl/StreamLayout$$anonfun$validate$2
    1942: dup
    1943: aload         32
    1945: invokespecial #317                // Method akka/stream/impl/StreamLayout$$anonfun$validate$2."<init>":(Ljava/lang/String;)V
    1948: invokevirtual #318                // Method scala/collection/immutable/List.foreach:(Lscala/Function1;)V
    1951: aload_1
    1952: invokeinterface #192,  1          // InterfaceMethod akka/stream/impl/StreamLayout$Module.subModules:()Lscala/collection/immutable/Set;
    1957: new           #320                // class akka/stream/impl/StreamLayout$$anonfun$validate$3
    1960: dup
    1961: iload_2
    1962: aload         4
    1964: iload         31
    1966: invokespecial #323                // Method akka/stream/impl/StreamLayout$$anonfun$validate$3."<init>":(ILjava/util/Map;Z)V
    1969: invokeinterface #324,  2          // InterfaceMethod scala/collection/immutable/Set.foreach:(Lscala/Function1;)V
    1974: aload         8
    1976: invokevirtual #274                // Method scala/collection/immutable/List.nonEmpty:()Z
    1979: ifeq          2050
    1982: iload_3
    1983: ifne          2050
    1986: new           #326                // class java/lang/IllegalStateException
    1989: dup
    1990: new           #98                 // class scala/StringContext
    1993: dup
    1994: getstatic     #103                // Field scala/Predef$.MODULE$:Lscala/Predef$;
    1997: iconst_2
    1998: anewarray     #105                // class java/lang/String
    2001: dup
    2002: iconst_0
    2003: ldc_w         #328                // String module inconsistent, found
    2006: aastore
    2007: dup
    2008: iconst_1
    2009: ldc_w         #330                // String  problems
    2012: aastore
    2013: checkcast     #113                // class "[Ljava/lang/Object;"
    2016: invokevirtual #117                // Method scala/Predef$.wrapRefArray:([Ljava/lang/Object;)Lscala/collection/mutable/WrappedArray;
    2019: invokespecial #120                // Method scala/StringContext."<init>":(Lscala/collection/Seq;)V
    2022: getstatic     #103                // Field scala/Predef$.MODULE$:Lscala/Predef$;
    2025: iconst_1
    2026: anewarray     #4                  // class java/lang/Object
    2029: dup
    2030: iconst_0
    2031: aload         8
    2033: invokevirtual #331                // Method scala/collection/immutable/List.size:()I
    2036: invokestatic  #337                // Method scala/runtime/BoxesRunTime.boxToInteger:(I)Ljava/lang/Integer;
    2039: aastore
    2040: invokevirtual #128                // Method scala/Predef$.genericWrapArray:(Ljava/lang/Object;)Lscala/collection/mutable/WrappedArray;
    2043: invokevirtual #132                // Method scala/StringContext.s:(Lscala/collection/Seq;)Ljava/lang/String;
    2046: invokespecial #338                // Method java/lang/IllegalStateException."<init>":(Ljava/lang/String;)V
    2049: athrow
    2050: return
    2051: new           #340                // class scala/MatchError
    2054: dup
    2055: aload         17
    2057: invokespecial #342                // Method scala/MatchError."<init>":(Ljava/lang/Object;)V
    2060: athrow

  public final int validate$default$2();
    Code:
       0: iconst_0
       1: ireturn

  public final boolean validate$default$3();
    Code:
       0: iconst_0
       1: ireturn

  public final java.util.Map<java.lang.Object, java.lang.Integer> validate$default$4();
    Code:
       0: new           #381                // class java/util/HashMap
       3: dup
       4: invokespecial #382                // Method java/util/HashMap."<init>":()V
       7: areturn

  private final java.lang.Object id$1(java.lang.Object, java.util.Map, scala.collection.Iterator);
    Code:
       0: aload_2
       1: aload_1
       2: invokeinterface #388,  2          // InterfaceMethod java/util/Map.get:(Ljava/lang/Object;)Ljava/lang/Object;
       7: checkcast     #390                // class java/lang/Integer
      10: astore        4
      12: aload         4
      14: ifnonnull     54
      17: aload_3
      18: invokeinterface #393,  1          // InterfaceMethod scala/collection/Iterator.next:()Ljava/lang/Object;
      23: invokestatic  #397                // Method scala/runtime/BoxesRunTime.unboxToInt:(Ljava/lang/Object;)I
      26: istore        6
      28: aload_2
      29: aload_1
      30: getstatic     #103                // Field scala/Predef$.MODULE$:Lscala/Predef$;
      33: iload         6
      35: invokevirtual #400                // Method scala/Predef$.int2Integer:(I)Ljava/lang/Integer;
      38: invokeinterface #404,  3          // InterfaceMethod java/util/Map.put:(Ljava/lang/Object;Ljava/lang/Object;)Ljava/lang/Object;
      43: pop
      44: iload         6
      46: invokestatic  #337                // Method scala/runtime/BoxesRunTime.boxToInteger:(I)Ljava/lang/Integer;
      49: astore        5
      51: goto          58
      54: aload         4
      56: astore        5
      58: aload         5
      60: areturn

  public final java.lang.String akka$stream$impl$StreamLayout$$in$1(akka.stream.InPort, java.util.Map, scala.collection.Iterator);
    Code:
       0: new           #98                 // class scala/StringContext
       3: dup
       4: getstatic     #103                // Field scala/Predef$.MODULE$:Lscala/Predef$;
       7: iconst_3
       8: anewarray     #105                // class java/lang/String
      11: dup
      12: iconst_0
      13: ldc           #111                // String
      15: aastore
      16: dup
      17: iconst_1
      18: ldc_w         #413                // String @
      21: aastore
      22: dup
      23: iconst_2
      24: ldc           #111                // String
      26: aastore
      27: checkcast     #113                // class "[Ljava/lang/Object;"
      30: invokevirtual #117                // Method scala/Predef$.wrapRefArray:([Ljava/lang/Object;)Lscala/collection/mutable/WrappedArray;
      33: invokespecial #120                // Method scala/StringContext."<init>":(Lscala/collection/Seq;)V
      36: getstatic     #103                // Field scala/Predef$.MODULE$:Lscala/Predef$;
      39: iconst_2
      40: anewarray     #4                  // class java/lang/Object
      43: dup
      44: iconst_0
      45: aload_1
      46: invokevirtual #414                // Method java/lang/Object.toString:()Ljava/lang/String;
      49: aastore
      50: dup
      51: iconst_1
      52: aload_0
      53: aload_1
      54: aload_2
      55: aload_3
      56: invokespecial #416                // Method id$1:(Ljava/lang/Object;Ljava/util/Map;Lscala/collection/Iterator;)Ljava/lang/Object;
      59: aastore
      60: invokevirtual #128                // Method scala/Predef$.genericWrapArray:(Ljava/lang/Object;)Lscala/collection/mutable/WrappedArray;
      63: invokevirtual #132                // Method scala/StringContext.s:(Lscala/collection/Seq;)Ljava/lang/String;
      66: areturn

  public final java.lang.String akka$stream$impl$StreamLayout$$out$1(akka.stream.OutPort, java.util.Map, scala.collection.Iterator);
    Code:
       0: new           #98                 // class scala/StringContext
       3: dup
       4: getstatic     #103                // Field scala/Predef$.MODULE$:Lscala/Predef$;
       7: iconst_3
       8: anewarray     #105                // class java/lang/String
      11: dup
      12: iconst_0
      13: ldc           #111                // String
      15: aastore
      16: dup
      17: iconst_1
      18: ldc_w         #413                // String @
      21: aastore
      22: dup
      23: iconst_2
      24: ldc           #111                // String
      26: aastore
      27: checkcast     #113                // class "[Ljava/lang/Object;"
      30: invokevirtual #117                // Method scala/Predef$.wrapRefArray:([Ljava/lang/Object;)Lscala/collection/mutable/WrappedArray;
      33: invokespecial #120                // Method scala/StringContext."<init>":(Lscala/collection/Seq;)V
      36: getstatic     #103                // Field scala/Predef$.MODULE$:Lscala/Predef$;
      39: iconst_2
      40: anewarray     #4                  // class java/lang/Object
      43: dup
      44: iconst_0
      45: aload_1
      46: invokevirtual #414                // Method java/lang/Object.toString:()Ljava/lang/String;
      49: aastore
      50: dup
      51: iconst_1
      52: aload_0
      53: aload_1
      54: aload_2
      55: aload_3
      56: invokespecial #416                // Method id$1:(Ljava/lang/Object;Ljava/util/Map;Lscala/collection/Iterator;)Ljava/lang/Object;
      59: aastore
      60: invokevirtual #128                // Method scala/Predef$.genericWrapArray:(Ljava/lang/Object;)Lscala/collection/mutable/WrappedArray;
      63: invokevirtual #132                // Method scala/StringContext.s:(Lscala/collection/Seq;)Ljava/lang/String;
      66: areturn

  private final java.lang.String ins$1(scala.collection.Iterable, java.util.Map, scala.collection.Iterator);
    Code:
       0: aload_1
       1: new           #424                // class akka/stream/impl/StreamLayout$$anonfun$ins$1$1
       4: dup
       5: aload_2
       6: aload_3
       7: invokespecial #427                // Method akka/stream/impl/StreamLayout$$anonfun$ins$1$1."<init>":(Ljava/util/Map;Lscala/collection/Iterator;)V
      10: getstatic     #432                // Field scala/collection/Iterable$.MODULE$:Lscala/collection/Iterable$;
      13: invokevirtual #433                // Method scala/collection/Iterable$.canBuildFrom:()Lscala/collection/generic/CanBuildFrom;
      16: invokeinterface #436,  3          // InterfaceMethod scala/collection/Iterable.map:(Lscala/Function1;Lscala/collection/generic/CanBuildFrom;)Ljava/lang/Object;
      21: checkcast     #147                // class scala/collection/TraversableOnce
      24: ldc_w         #438                // String In[
      27: ldc_w         #269                // String ,
      30: ldc_w         #267                // String ]
      33: invokeinterface #441,  4          // InterfaceMethod scala/collection/TraversableOnce.mkString:(Ljava/lang/String;Ljava/lang/String;Ljava/lang/String;)Ljava/lang/String;
      38: areturn

  private final java.lang.String outs$1(scala.collection.Iterable, java.util.Map, scala.collection.Iterator);
    Code:
       0: aload_1
       1: new           #444                // class akka/stream/impl/StreamLayout$$anonfun$outs$1$1
       4: dup
       5: aload_2
       6: aload_3
       7: invokespecial #445                // Method akka/stream/impl/StreamLayout$$anonfun$outs$1$1."<init>":(Ljava/util/Map;Lscala/collection/Iterator;)V
      10: getstatic     #432                // Field scala/collection/Iterable$.MODULE$:Lscala/collection/Iterable$;
      13: invokevirtual #433                // Method scala/collection/Iterable$.canBuildFrom:()Lscala/collection/generic/CanBuildFrom;
      16: invokeinterface #436,  3          // InterfaceMethod scala/collection/Iterable.map:(Lscala/Function1;Lscala/collection/generic/CanBuildFrom;)Ljava/lang/Object;
      21: checkcast     #147                // class scala/collection/TraversableOnce
      24: ldc_w         #447                // String Out[
      27: ldc_w         #269                // String ,
      30: ldc_w         #267                // String ]
      33: invokeinterface #441,  4          // InterfaceMethod scala/collection/TraversableOnce.mkString:(Ljava/lang/String;Ljava/lang/String;Ljava/lang/String;)Ljava/lang/String;
      38: areturn

  public final java.lang.String akka$stream$impl$StreamLayout$$pair$1(scala.Tuple2, java.util.Map, scala.collection.Iterator);
    Code:
       0: new           #98                 // class scala/StringContext
       3: dup
       4: getstatic     #103                // Field scala/Predef$.MODULE$:Lscala/Predef$;
       7: iconst_3
       8: anewarray     #105                // class java/lang/String
      11: dup
      12: iconst_0
      13: ldc           #111                // String
      15: aastore
      16: dup
      17: iconst_1
      18: ldc_w         #451                // String ->
      21: aastore
      22: dup
      23: iconst_2
      24: ldc           #111                // String
      26: aastore
      27: checkcast     #113                // class "[Ljava/lang/Object;"
      30: invokevirtual #117                // Method scala/Predef$.wrapRefArray:([Ljava/lang/Object;)Lscala/collection/mutable/WrappedArray;
      33: invokespecial #120                // Method scala/StringContext."<init>":(Lscala/collection/Seq;)V
      36: getstatic     #103                // Field scala/Predef$.MODULE$:Lscala/Predef$;
      39: iconst_2
      40: anewarray     #4                  // class java/lang/Object
      43: dup
      44: iconst_0
      45: aload_0
      46: aload_1
      47: invokevirtual #454                // Method scala/Tuple2._2:()Ljava/lang/Object;
      50: checkcast     #456                // class akka/stream/InPort
      53: aload_2
      54: aload_3
      55: invokevirtual #458                // Method akka$stream$impl$StreamLayout$$in$1:(Lakka/stream/InPort;Ljava/util/Map;Lscala/collection/Iterator;)Ljava/lang/String;
      58: aastore
      59: dup
      60: iconst_1
      61: aload_0
      62: aload_1
      63: invokevirtual #459                // Method scala/Tuple2._1:()Ljava/lang/Object;
      66: checkcast     #461                // class akka/stream/OutPort
      69: aload_2
      70: aload_3
      71: invokevirtual #463                // Method akka$stream$impl$StreamLayout$$out$1:(Lakka/stream/OutPort;Ljava/util/Map;Lscala/collection/Iterator;)Ljava/lang/String;
      74: aastore
      75: invokevirtual #128                // Method scala/Predef$.genericWrapArray:(Ljava/lang/Object;)Lscala/collection/mutable/WrappedArray;
      78: invokevirtual #132                // Method scala/StringContext.s:(Lscala/collection/Seq;)Ljava/lang/String;
      81: areturn

  private final java.lang.String pairs$1(scala.collection.Iterable, java.util.Map, scala.collection.Iterator);
    Code:
       0: aload_1
       1: new           #467                // class akka/stream/impl/StreamLayout$$anonfun$pairs$1$1
       4: dup
       5: aload_2
       6: aload_3
       7: invokespecial #468                // Method akka/stream/impl/StreamLayout$$anonfun$pairs$1$1."<init>":(Ljava/util/Map;Lscala/collection/Iterator;)V
      10: getstatic     #432                // Field scala/collection/Iterable$.MODULE$:Lscala/collection/Iterable$;
      13: invokevirtual #433                // Method scala/collection/Iterable$.canBuildFrom:()Lscala/collection/generic/CanBuildFrom;
      16: invokeinterface #436,  3          // InterfaceMethod scala/collection/Iterable.map:(Lscala/Function1;Lscala/collection/generic/CanBuildFrom;)Ljava/lang/Object;
      21: checkcast     #147                // class scala/collection/TraversableOnce
      24: ldc_w         #470                // String [
      27: ldc_w         #269                // String ,
      30: ldc_w         #267                // String ]
      33: invokeinterface #441,  4          // InterfaceMethod scala/collection/TraversableOnce.mkString:(Ljava/lang/String;Ljava/lang/String;Ljava/lang/String;)Ljava/lang/String;
      38: areturn

  private final scala.collection.immutable.Set atomics$1(akka.stream.impl.StreamLayout$MaterializedValueNode);
    Code:
       0: aload_1
       1: astore_3
       2: getstatic     #475                // Field akka/stream/impl/StreamLayout$Ignore$.MODULE$:Lakka/stream/impl/StreamLayout$Ignore$;
       5: aload_3
       6: invokevirtual #96                 // Method java/lang/Object.equals:(Ljava/lang/Object;)Z
       9: ifeq          26
      12: getstatic     #103                // Field scala/Predef$.MODULE$:Lscala/Predef$;
      15: invokevirtual #198                // Method scala/Predef$.Set:()Lscala/collection/immutable/Set$;
      18: invokevirtual #201                // Method scala/collection/immutable/Set$.empty:()Lscala/collection/immutable/Set;
      21: astore        4
      23: goto          156
      26: aload_3
      27: instanceof    #477                // class akka/stream/impl/StreamLayout$Transform
      30: ifeq          52
      33: aload_3
      34: checkcast     #477                // class akka/stream/impl/StreamLayout$Transform
      37: astore        5
      39: aload         5
      41: invokevirtual #480                // Method akka/stream/impl/StreamLayout$Transform.dep:()Lakka/stream/impl/StreamLayout$MaterializedValueNode;
      44: astore        6
      46: aload         6
      48: astore_1
      49: goto          0
      52: aload_3
      53: instanceof    #482                // class akka/stream/impl/StreamLayout$Atomic
      56: ifeq          107
      59: aload_3
      60: checkcast     #482                // class akka/stream/impl/StreamLayout$Atomic
      63: astore        7
      65: aload         7
      67: invokevirtual #486                // Method akka/stream/impl/StreamLayout$Atomic.module:()Lakka/stream/impl/StreamLayout$Module;
      70: astore        8
      72: getstatic     #103                // Field scala/Predef$.MODULE$:Lscala/Predef$;
      75: invokevirtual #198                // Method scala/Predef$.Set:()Lscala/collection/immutable/Set$;
      78: getstatic     #103                // Field scala/Predef$.MODULE$:Lscala/Predef$;
      81: iconst_1
      82: anewarray     #35                 // class akka/stream/impl/StreamLayout$Module
      85: dup
      86: iconst_0
      87: aload         8
      89: aastore
      90: checkcast     #113                // class "[Ljava/lang/Object;"
      93: invokevirtual #117                // Method scala/Predef$.wrapRefArray:([Ljava/lang/Object;)Lscala/collection/mutable/WrappedArray;
      96: invokevirtual #490                // Method scala/collection/immutable/Set$.apply:(Lscala/collection/Seq;)Lscala/collection/GenTraversable;
      99: checkcast     #61                 // class scala/collection/immutable/Set
     102: astore        4
     104: goto          156
     107: aload_3
     108: instanceof    #492                // class akka/stream/impl/StreamLayout$Combine
     111: ifeq          159
     114: aload_3
     115: checkcast     #492                // class akka/stream/impl/StreamLayout$Combine
     118: astore        9
     120: aload         9
     122: invokevirtual #495                // Method akka/stream/impl/StreamLayout$Combine.dep1:()Lakka/stream/impl/StreamLayout$MaterializedValueNode;
     125: astore        10
     127: aload         9
     129: invokevirtual #498                // Method akka/stream/impl/StreamLayout$Combine.dep2:()Lakka/stream/impl/StreamLayout$MaterializedValueNode;
     132: astore        11
     134: aload_0
     135: aload         10
     137: invokespecial #253                // Method atomics$1:(Lakka/stream/impl/StreamLayout$MaterializedValueNode;)Lscala/collection/immutable/Set;
     140: aload_0
     141: aload         11
     143: invokespecial #253                // Method atomics$1:(Lakka/stream/impl/StreamLayout$MaterializedValueNode;)Lscala/collection/immutable/Set;
     146: invokeinterface #502,  2          // InterfaceMethod scala/collection/immutable/Set.$plus$plus:(Lscala/collection/GenTraversableOnce;)Lscala/collection/Set;
     151: checkcast     #61                 // class scala/collection/immutable/Set
     154: astore        4
     156: aload         4
     158: areturn
     159: new           #340                // class scala/MatchError
     162: dup
     163: aload_3
     164: invokespecial #342                // Method scala/MatchError."<init>":(Ljava/lang/Object;)V
     167: athrow

  private akka.stream.impl.StreamLayout$();
    Code:
       0: aload_0
       1: invokespecial #509                // Method java/lang/Object."<init>":()V
       4: aload_0
       5: putstatic     #511                // Field MODULE$:Lakka/stream/impl/StreamLayout$;
       8: return
}
