Compiled from "Assigner.java"
public interface org.assertj.core.internal.bytebuddy.implementation.bytecode.assign.Assigner {
  public static final org.assertj.core.internal.bytebuddy.implementation.bytecode.assign.Assigner DEFAULT;

  public abstract org.assertj.core.internal.bytebuddy.implementation.bytecode.StackManipulation assign(org.assertj.core.internal.bytebuddy.description.type.TypeDescription$Generic, org.assertj.core.internal.bytebuddy.description.type.TypeDescription$Generic, org.assertj.core.internal.bytebuddy.implementation.bytecode.assign.Assigner$Typing);

  static {};
    Code:
       0: new           #34                 // class org/assertj/core/internal/bytebuddy/implementation/bytecode/assign/primitive/VoidAwareAssigner
       3: dup
       4: new           #36                 // class org/assertj/core/internal/bytebuddy/implementation/bytecode/assign/primitive/PrimitiveTypeAwareAssigner
       7: dup
       8: getstatic     #42                 // Field org/assertj/core/internal/bytebuddy/implementation/bytecode/assign/reference/ReferenceTypeAwareAssigner.INSTANCE:Lorg/assertj/core/internal/bytebuddy/implementation/bytecode/assign/reference/ReferenceTypeAwareAssigner;
      11: invokespecial #46                 // Method org/assertj/core/internal/bytebuddy/implementation/bytecode/assign/primitive/PrimitiveTypeAwareAssigner."<init>":(Lorg/assertj/core/internal/bytebuddy/implementation/bytecode/assign/Assigner;)V
      14: invokespecial #47                 // Method org/assertj/core/internal/bytebuddy/implementation/bytecode/assign/primitive/VoidAwareAssigner."<init>":(Lorg/assertj/core/internal/bytebuddy/implementation/bytecode/assign/Assigner;)V
      17: putstatic     #49                 // Field DEFAULT:Lorg/assertj/core/internal/bytebuddy/implementation/bytecode/assign/Assigner;
      20: return
}
