Compiled from "ModuleConfigImpl.java"
public class org.jboss.as.cli.handlers.module.ModuleConfigImpl implements org.jboss.as.cli.handlers.module.ModuleConfig {
  static final java.lang.String DEPENDENCIES;

  static final java.lang.String MAIN_CLASS;

  static final java.lang.String MODULE;

  static final java.lang.String MODULE_NS;

  static final java.lang.String NAME;

  static final java.lang.String SLOT;

  static final java.lang.String PATH;

  static final java.lang.String PROPERTY;

  static final java.lang.String PROPERTIES;

  static final java.lang.String RESOURCES;

  static final java.lang.String RESOURCE_ROOT;

  static final java.lang.String VALUE;

  private java.lang.String schemaVersion;

  private java.lang.String moduleName;

  private java.lang.String mainClass;

  private java.lang.String slotName;

  private java.util.Collection<org.jboss.as.cli.handlers.module.ModuleConfig$Resource> resources;

  private java.util.Collection<org.jboss.as.cli.handlers.module.ModuleConfig$Dependency> dependencies;

  private java.util.Map<java.lang.String, java.lang.String> properties;

  private static final char[] NEW_LINE;

  public org.jboss.as.cli.handlers.module.ModuleConfigImpl(java.lang.String);
    Code:
       0: aload_0
       1: invokespecial #1                  // Method java/lang/Object."<init>":()V
       4: aload_0
       5: ldc           #3                  // String urn:jboss:module:1.1
       7: putfield      #4                  // Field schemaVersion:Ljava/lang/String;
      10: aload_1
      11: ifnull        21
      14: aload_1
      15: invokevirtual #5                  // Method java/lang/String.isEmpty:()Z
      18: ifeq          31
      21: new           #6                  // class java/lang/IllegalArgumentException
      24: dup
      25: ldc           #7                  // String Module name can\'t be null
      27: invokespecial #8                  // Method java/lang/IllegalArgumentException."<init>":(Ljava/lang/String;)V
      30: athrow
      31: aload_0
      32: aload_1
      33: putfield      #9                  // Field moduleName:Ljava/lang/String;
      36: return

  public java.lang.String getSchemaVersion();
    Code:
       0: aload_0
       1: getfield      #4                  // Field schemaVersion:Ljava/lang/String;
       4: areturn

  public java.lang.String getModuleName();
    Code:
       0: aload_0
       1: getfield      #9                  // Field moduleName:Ljava/lang/String;
       4: areturn

  public java.lang.String getSlot();
    Code:
       0: aload_0
       1: getfield      #10                 // Field slotName:Ljava/lang/String;
       4: areturn

  public void setSlot(java.lang.String);
    Code:
       0: aload_0
       1: aload_1
       2: putfield      #10                 // Field slotName:Ljava/lang/String;
       5: return

  public java.lang.String getMainClass();
    Code:
       0: aload_0
       1: getfield      #11                 // Field mainClass:Ljava/lang/String;
       4: areturn

  public void setMainClass(java.lang.String);
    Code:
       0: aload_0
       1: aload_1
       2: putfield      #11                 // Field mainClass:Ljava/lang/String;
       5: return

  public java.util.Collection<org.jboss.as.cli.handlers.module.ModuleConfig$Resource> getResources();
    Code:
       0: aload_0
       1: getfield      #12                 // Field resources:Ljava/util/Collection;
       4: ifnonnull     13
       7: invokestatic  #13                 // Method java/util/Collections.emptyList:()Ljava/util/List;
      10: goto          17
      13: aload_0
      14: getfield      #12                 // Field resources:Ljava/util/Collection;
      17: areturn

  public void addResource(org.jboss.as.cli.handlers.module.ModuleConfig$Resource);
    Code:
       0: aload_1
       1: ifnonnull     14
       4: new           #6                  // class java/lang/IllegalArgumentException
       7: dup
       8: ldc           #14                 // String Resource cannot be null.
      10: invokespecial #8                  // Method java/lang/IllegalArgumentException."<init>":(Ljava/lang/String;)V
      13: athrow
      14: aload_0
      15: getfield      #12                 // Field resources:Ljava/util/Collection;
      18: ifnonnull     32
      21: aload_0
      22: new           #15                 // class java/util/ArrayList
      25: dup
      26: invokespecial #16                 // Method java/util/ArrayList."<init>":()V
      29: putfield      #12                 // Field resources:Ljava/util/Collection;
      32: aload_0
      33: getfield      #12                 // Field resources:Ljava/util/Collection;
      36: aload_1
      37: invokeinterface #17,  2           // InterfaceMethod java/util/Collection.add:(Ljava/lang/Object;)Z
      42: pop
      43: return

  public java.util.Collection<org.jboss.as.cli.handlers.module.ModuleConfig$Dependency> getDependencies();
    Code:
       0: aload_0
       1: getfield      #18                 // Field dependencies:Ljava/util/Collection;
       4: ifnonnull     13
       7: invokestatic  #13                 // Method java/util/Collections.emptyList:()Ljava/util/List;
      10: goto          17
      13: aload_0
      14: getfield      #18                 // Field dependencies:Ljava/util/Collection;
      17: areturn

  public void addDependency(org.jboss.as.cli.handlers.module.ModuleConfig$Dependency);
    Code:
       0: aload_1
       1: ifnonnull     14
       4: new           #6                  // class java/lang/IllegalArgumentException
       7: dup
       8: ldc           #19                 // String Dependency cannot be null.
      10: invokespecial #8                  // Method java/lang/IllegalArgumentException."<init>":(Ljava/lang/String;)V
      13: athrow
      14: aload_0
      15: getfield      #18                 // Field dependencies:Ljava/util/Collection;
      18: ifnonnull     32
      21: aload_0
      22: new           #15                 // class java/util/ArrayList
      25: dup
      26: invokespecial #16                 // Method java/util/ArrayList."<init>":()V
      29: putfield      #18                 // Field dependencies:Ljava/util/Collection;
      32: aload_0
      33: getfield      #18                 // Field dependencies:Ljava/util/Collection;
      36: aload_1
      37: invokeinterface #17,  2           // InterfaceMethod java/util/Collection.add:(Ljava/lang/Object;)Z
      42: pop
      43: return

  public java.util.Map<java.lang.String, java.lang.String> getProperties();
    Code:
       0: aload_0
       1: getfield      #20                 // Field properties:Ljava/util/Map;
       4: ifnonnull     13
       7: invokestatic  #21                 // Method java/util/Collections.emptyMap:()Ljava/util/Map;
      10: goto          17
      13: aload_0
      14: getfield      #20                 // Field properties:Ljava/util/Map;
      17: areturn

  public void setProperty(java.lang.String, java.lang.String);
    Code:
       0: aload_1
       1: ifnonnull     14
       4: new           #6                  // class java/lang/IllegalArgumentException
       7: dup
       8: ldc           #22                 // String Property name can\'t be null.
      10: invokespecial #8                  // Method java/lang/IllegalArgumentException."<init>":(Ljava/lang/String;)V
      13: athrow
      14: aload_2
      15: ifnonnull     28
      18: new           #6                  // class java/lang/IllegalArgumentException
      21: dup
      22: ldc           #23                 // String Property value can\'t be null.
      24: invokespecial #8                  // Method java/lang/IllegalArgumentException."<init>":(Ljava/lang/String;)V
      27: athrow
      28: aload_0
      29: getfield      #20                 // Field properties:Ljava/util/Map;
      32: ifnonnull     46
      35: aload_0
      36: new           #24                 // class java/util/HashMap
      39: dup
      40: invokespecial #25                 // Method java/util/HashMap."<init>":()V
      43: putfield      #20                 // Field properties:Ljava/util/Map;
      46: aload_0
      47: getfield      #20                 // Field properties:Ljava/util/Map;
      50: aload_1
      51: aload_2
      52: invokeinterface #26,  3           // InterfaceMethod java/util/Map.put:(Ljava/lang/Object;Ljava/lang/Object;)Ljava/lang/Object;
      57: pop
      58: return

  public void writeContent(org.jboss.staxmapper.XMLExtendedStreamWriter, org.jboss.as.cli.handlers.module.ModuleConfig) throws javax.xml.stream.XMLStreamException;
    Code:
       0: aload_1
       1: invokeinterface #27,  1           // InterfaceMethod org/jboss/staxmapper/XMLExtendedStreamWriter.writeStartDocument:()V
       6: aload_1
       7: ldc           #28                 // String module
       9: invokeinterface #29,  2           // InterfaceMethod org/jboss/staxmapper/XMLExtendedStreamWriter.writeStartElement:(Ljava/lang/String;)V
      14: aload_1
      15: ldc           #3                  // String urn:jboss:module:1.1
      17: invokeinterface #30,  2           // InterfaceMethod org/jboss/staxmapper/XMLExtendedStreamWriter.writeDefaultNamespace:(Ljava/lang/String;)V
      22: aload_0
      23: getfield      #9                  // Field moduleName:Ljava/lang/String;
      26: ifnonnull     39
      29: new           #31                 // class javax/xml/stream/XMLStreamException
      32: dup
      33: ldc           #32                 // String Module name is missing.
      35: invokespecial #33                 // Method javax/xml/stream/XMLStreamException."<init>":(Ljava/lang/String;)V
      38: athrow
      39: aload_1
      40: ldc           #34                 // String name
      42: aload_0
      43: getfield      #9                  // Field moduleName:Ljava/lang/String;
      46: invokeinterface #35,  3           // InterfaceMethod org/jboss/staxmapper/XMLExtendedStreamWriter.writeAttribute:(Ljava/lang/String;Ljava/lang/String;)V
      51: aload_0
      52: getfield      #10                 // Field slotName:Ljava/lang/String;
      55: ifnull        70
      58: aload_1
      59: ldc           #36                 // String slot
      61: aload_0
      62: getfield      #10                 // Field slotName:Ljava/lang/String;
      65: invokeinterface #35,  3           // InterfaceMethod org/jboss/staxmapper/XMLExtendedStreamWriter.writeAttribute:(Ljava/lang/String;Ljava/lang/String;)V
      70: aload_0
      71: getfield      #20                 // Field properties:Ljava/util/Map;
      74: ifnull        183
      77: aload_1
      78: invokestatic  #37                 // Method writeNewLine:(Lorg/jboss/staxmapper/XMLExtendedStreamWriter;)V
      81: aload_1
      82: ldc           #38                 // String properties
      84: invokeinterface #29,  2           // InterfaceMethod org/jboss/staxmapper/XMLExtendedStreamWriter.writeStartElement:(Ljava/lang/String;)V
      89: aload_0
      90: getfield      #20                 // Field properties:Ljava/util/Map;
      93: invokeinterface #39,  1           // InterfaceMethod java/util/Map.entrySet:()Ljava/util/Set;
      98: invokeinterface #40,  1           // InterfaceMethod java/util/Set.iterator:()Ljava/util/Iterator;
     103: astore_3
     104: aload_3
     105: invokeinterface #41,  1           // InterfaceMethod java/util/Iterator.hasNext:()Z
     110: ifeq          177
     113: aload_3
     114: invokeinterface #42,  1           // InterfaceMethod java/util/Iterator.next:()Ljava/lang/Object;
     119: checkcast     #43                 // class java/util/Map$Entry
     122: astore        4
     124: aload_1
     125: ldc           #44                 // String property
     127: invokeinterface #29,  2           // InterfaceMethod org/jboss/staxmapper/XMLExtendedStreamWriter.writeStartElement:(Ljava/lang/String;)V
     132: aload_1
     133: ldc           #34                 // String name
     135: aload         4
     137: invokeinterface #45,  1           // InterfaceMethod java/util/Map$Entry.getKey:()Ljava/lang/Object;
     142: checkcast     #46                 // class java/lang/String
     145: invokeinterface #35,  3           // InterfaceMethod org/jboss/staxmapper/XMLExtendedStreamWriter.writeAttribute:(Ljava/lang/String;Ljava/lang/String;)V
     150: aload_1
     151: ldc           #47                 // String value
     153: aload         4
     155: invokeinterface #48,  1           // InterfaceMethod java/util/Map$Entry.getValue:()Ljava/lang/Object;
     160: checkcast     #46                 // class java/lang/String
     163: invokeinterface #35,  3           // InterfaceMethod org/jboss/staxmapper/XMLExtendedStreamWriter.writeAttribute:(Ljava/lang/String;Ljava/lang/String;)V
     168: aload_1
     169: invokeinterface #49,  1           // InterfaceMethod org/jboss/staxmapper/XMLExtendedStreamWriter.writeEndElement:()V
     174: goto          104
     177: aload_1
     178: invokeinterface #49,  1           // InterfaceMethod org/jboss/staxmapper/XMLExtendedStreamWriter.writeEndElement:()V
     183: aload_0
     184: getfield      #11                 // Field mainClass:Ljava/lang/String;
     187: ifnull        220
     190: aload_1
     191: invokestatic  #37                 // Method writeNewLine:(Lorg/jboss/staxmapper/XMLExtendedStreamWriter;)V
     194: aload_1
     195: ldc           #50                 // String main-class
     197: invokeinterface #29,  2           // InterfaceMethod org/jboss/staxmapper/XMLExtendedStreamWriter.writeStartElement:(Ljava/lang/String;)V
     202: aload_1
     203: ldc           #34                 // String name
     205: aload_0
     206: getfield      #11                 // Field mainClass:Ljava/lang/String;
     209: invokeinterface #35,  3           // InterfaceMethod org/jboss/staxmapper/XMLExtendedStreamWriter.writeAttribute:(Ljava/lang/String;Ljava/lang/String;)V
     214: aload_1
     215: invokeinterface #49,  1           // InterfaceMethod org/jboss/staxmapper/XMLExtendedStreamWriter.writeEndElement:()V
     220: aload_0
     221: getfield      #12                 // Field resources:Ljava/util/Collection;
     224: ifnull        288
     227: aload_1
     228: invokestatic  #37                 // Method writeNewLine:(Lorg/jboss/staxmapper/XMLExtendedStreamWriter;)V
     231: aload_1
     232: ldc           #51                 // String resources
     234: invokeinterface #29,  2           // InterfaceMethod org/jboss/staxmapper/XMLExtendedStreamWriter.writeStartElement:(Ljava/lang/String;)V
     239: aload_0
     240: getfield      #12                 // Field resources:Ljava/util/Collection;
     243: invokeinterface #52,  1           // InterfaceMethod java/util/Collection.iterator:()Ljava/util/Iterator;
     248: astore_3
     249: aload_3
     250: invokeinterface #41,  1           // InterfaceMethod java/util/Iterator.hasNext:()Z
     255: ifeq          282
     258: aload_3
     259: invokeinterface #42,  1           // InterfaceMethod java/util/Iterator.next:()Ljava/lang/Object;
     264: checkcast     #53                 // class org/jboss/as/cli/handlers/module/ModuleConfig$Resource
     267: astore        4
     269: aload         4
     271: aload_1
     272: aload         4
     274: invokeinterface #54,  3           // InterfaceMethod org/jboss/as/cli/handlers/module/ModuleConfig$Resource.writeContent:(Lorg/jboss/staxmapper/XMLExtendedStreamWriter;Ljava/lang/Object;)V
     279: goto          249
     282: aload_1
     283: invokeinterface #49,  1           // InterfaceMethod org/jboss/staxmapper/XMLExtendedStreamWriter.writeEndElement:()V
     288: aload_0
     289: getfield      #18                 // Field dependencies:Ljava/util/Collection;
     292: ifnull        356
     295: aload_1
     296: invokestatic  #37                 // Method writeNewLine:(Lorg/jboss/staxmapper/XMLExtendedStreamWriter;)V
     299: aload_1
     300: ldc           #55                 // String dependencies
     302: invokeinterface #29,  2           // InterfaceMethod org/jboss/staxmapper/XMLExtendedStreamWriter.writeStartElement:(Ljava/lang/String;)V
     307: aload_0
     308: getfield      #18                 // Field dependencies:Ljava/util/Collection;
     311: invokeinterface #52,  1           // InterfaceMethod java/util/Collection.iterator:()Ljava/util/Iterator;
     316: astore_3
     317: aload_3
     318: invokeinterface #41,  1           // InterfaceMethod java/util/Iterator.hasNext:()Z
     323: ifeq          350
     326: aload_3
     327: invokeinterface #42,  1           // InterfaceMethod java/util/Iterator.next:()Ljava/lang/Object;
     332: checkcast     #56                 // class org/jboss/as/cli/handlers/module/ModuleConfig$Dependency
     335: astore        4
     337: aload         4
     339: aload_1
     340: aload         4
     342: invokeinterface #57,  3           // InterfaceMethod org/jboss/as/cli/handlers/module/ModuleConfig$Dependency.writeContent:(Lorg/jboss/staxmapper/XMLExtendedStreamWriter;Ljava/lang/Object;)V
     347: goto          317
     350: aload_1
     351: invokeinterface #49,  1           // InterfaceMethod org/jboss/staxmapper/XMLExtendedStreamWriter.writeEndElement:()V
     356: aload_1
     357: invokestatic  #37                 // Method writeNewLine:(Lorg/jboss/staxmapper/XMLExtendedStreamWriter;)V
     360: aload_1
     361: invokeinterface #49,  1           // InterfaceMethod org/jboss/staxmapper/XMLExtendedStreamWriter.writeEndElement:()V
     366: aload_1
     367: invokeinterface #58,  1           // InterfaceMethod org/jboss/staxmapper/XMLExtendedStreamWriter.writeEndDocument:()V
     372: return

  protected static void writeNewLine(org.jboss.staxmapper.XMLExtendedStreamWriter) throws javax.xml.stream.XMLStreamException;
    Code:
       0: aload_0
       1: getstatic     #59                 // Field NEW_LINE:[C
       4: iconst_0
       5: iconst_1
       6: invokeinterface #60,  4           // InterfaceMethod org/jboss/staxmapper/XMLExtendedStreamWriter.writeCharacters:([CII)V
      11: return

  public static void main(java.lang.String[]) throws java.lang.Exception;
    Code:
       0: new           #2                  // class org/jboss/as/cli/handlers/module/ModuleConfigImpl
       3: dup
       4: ldc           #61                 // String o.r.g
       6: invokespecial #62                 // Method "<init>":(Ljava/lang/String;)V
       9: astore_1
      10: aload_1
      11: ldc           #63                 // String jboss.api
      13: ldc           #64                 // String private
      15: invokevirtual #65                 // Method setProperty:(Ljava/lang/String;Ljava/lang/String;)V
      18: aload_1
      19: ldc           #66                 // String prop
      21: ldc           #47                 // String value
      23: invokevirtual #65                 // Method setProperty:(Ljava/lang/String;Ljava/lang/String;)V
      26: aload_1
      27: ldc           #67                 // String o.r.g.MainClass
      29: invokevirtual #68                 // Method setMainClass:(Ljava/lang/String;)V
      32: aload_1
      33: new           #69                 // class org/jboss/as/cli/handlers/module/ResourceRoot
      36: dup
      37: ldc           #70                 // String a.jar
      39: invokespecial #71                 // Method org/jboss/as/cli/handlers/module/ResourceRoot."<init>":(Ljava/lang/String;)V
      42: invokevirtual #72                 // Method addResource:(Lorg/jboss/as/cli/handlers/module/ModuleConfig$Resource;)V
      45: aload_1
      46: new           #69                 // class org/jboss/as/cli/handlers/module/ResourceRoot
      49: dup
      50: ldc           #73                 // String another.jar
      52: invokespecial #71                 // Method org/jboss/as/cli/handlers/module/ResourceRoot."<init>":(Ljava/lang/String;)V
      55: invokevirtual #72                 // Method addResource:(Lorg/jboss/as/cli/handlers/module/ModuleConfig$Resource;)V
      58: aload_1
      59: new           #74                 // class org/jboss/as/cli/handlers/module/ModuleDependency
      62: dup
      63: ldc           #75                 // String a.module
      65: invokespecial #76                 // Method org/jboss/as/cli/handlers/module/ModuleDependency."<init>":(Ljava/lang/String;)V
      68: invokevirtual #77                 // Method addDependency:(Lorg/jboss/as/cli/handlers/module/ModuleConfig$Dependency;)V
      71: aload_1
      72: new           #74                 // class org/jboss/as/cli/handlers/module/ModuleDependency
      75: dup
      76: ldc           #78                 // String another.module
      78: invokespecial #76                 // Method org/jboss/as/cli/handlers/module/ModuleDependency."<init>":(Ljava/lang/String;)V
      81: invokevirtual #77                 // Method addDependency:(Lorg/jboss/as/cli/handlers/module/ModuleConfig$Dependency;)V
      84: new           #79                 // class java/io/StringWriter
      87: dup
      88: invokespecial #80                 // Method java/io/StringWriter."<init>":()V
      91: astore_2
      92: invokestatic  #81                 // Method javax/xml/stream/XMLOutputFactory.newInstance:()Ljavax/xml/stream/XMLOutputFactory;
      95: aload_2
      96: invokevirtual #82                 // Method javax/xml/stream/XMLOutputFactory.createXMLStreamWriter:(Ljava/io/Writer;)Ljavax/xml/stream/XMLStreamWriter;
      99: invokestatic  #83                 // Method create:(Ljavax/xml/stream/XMLStreamWriter;)Lorg/jboss/staxmapper/XMLExtendedStreamWriter;
     102: astore_3
     103: aload_1
     104: aload_3
     105: aload_1
     106: invokevirtual #84                 // Method writeContent:(Lorg/jboss/staxmapper/XMLExtendedStreamWriter;Lorg/jboss/as/cli/handlers/module/ModuleConfig;)V
     109: aload_3
     110: invokeinterface #85,  1           // InterfaceMethod org/jboss/staxmapper/XMLExtendedStreamWriter.flush:()V
     115: getstatic     #86                 // Field java/lang/System.out:Ljava/io/PrintStream;
     118: aload_2
     119: invokevirtual #87                 // Method java/io/StringWriter.toString:()Ljava/lang/String;
     122: invokevirtual #88                 // Method java/io/PrintStream.println:(Ljava/lang/String;)V
     125: return

  public static org.jboss.staxmapper.XMLExtendedStreamWriter create(javax.xml.stream.XMLStreamWriter) throws java.lang.Exception;
    Code:
       0: new           #89                 // class org/jboss/staxmapper/FormattingXMLStreamWriter
       3: dup
       4: aload_0
       5: invokespecial #90                 // Method org/jboss/staxmapper/FormattingXMLStreamWriter."<init>":(Ljavax/xml/stream/XMLStreamWriter;)V
       8: areturn

  public void writeContent(org.jboss.staxmapper.XMLExtendedStreamWriter, java.lang.Object) throws javax.xml.stream.XMLStreamException;
    Code:
       0: aload_0
       1: aload_1
       2: aload_2
       3: checkcast     #91                 // class org/jboss/as/cli/handlers/module/ModuleConfig
       6: invokevirtual #84                 // Method writeContent:(Lorg/jboss/staxmapper/XMLExtendedStreamWriter;Lorg/jboss/as/cli/handlers/module/ModuleConfig;)V
       9: return

  static {};
    Code:
       0: iconst_1
       1: newarray       char
       3: dup
       4: iconst_0
       5: bipush        10
       7: castore
       8: putstatic     #59                 // Field NEW_LINE:[C
      11: return
}
