Compiled from "ConfigurationHelper.java"
public final class org.apache.camel.impl.ConfigurationHelper {
  private static final org.slf4j.Logger LOG;

  private org.apache.camel.impl.ConfigurationHelper();
    Code:
       0: aload_0
       1: invokespecial #22                 // Method java/lang/Object."<init>":()V
       4: return

  public static org.apache.camel.EndpointConfiguration createConfiguration(java.lang.String, org.apache.camel.CamelContext) throws java.lang.Exception;
    Code:
       0: aload_0
       1: bipush        58
       3: invokevirtual #34                 // Method java/lang/String.indexOf:(I)I
       6: istore_2
       7: iload_2
       8: iconst_m1
       9: if_icmpne     14
      12: aconst_null
      13: areturn
      14: aload_0
      15: iconst_0
      16: iload_2
      17: invokevirtual #38                 // Method java/lang/String.substring:(II)Ljava/lang/String;
      20: astore_3
      21: aload_1
      22: aload_3
      23: invokeinterface #44,  2           // InterfaceMethod org/apache/camel/CamelContext.getComponent:(Ljava/lang/String;)Lorg/apache/camel/Component;
      28: astore        4
      30: getstatic     #46                 // Field LOG:Lorg/slf4j/Logger;
      33: invokeinterface #52,  1           // InterfaceMethod org/slf4j/Logger.isTraceEnabled:()Z
      38: ifeq          80
      41: getstatic     #46                 // Field LOG:Lorg/slf4j/Logger;
      44: ldc           #54                 // String Lookup for Component handling \"{}:\" configuration returned {}
      46: iconst_2
      47: anewarray     #4                  // class java/lang/Object
      50: dup
      51: iconst_0
      52: aload_3
      53: aastore
      54: dup
      55: iconst_1
      56: aload         4
      58: ifnull        72
      61: aload         4
      63: invokevirtual #58                 // Method java/lang/Object.getClass:()Ljava/lang/Class;
      66: invokevirtual #64                 // Method java/lang/Class.getName:()Ljava/lang/String;
      69: goto          74
      72: ldc           #70                 // String <null>
      74: aastore
      75: invokeinterface #74,  3           // InterfaceMethod org/slf4j/Logger.trace:(Ljava/lang/String;[Ljava/lang/Object;)V
      80: aload         4
      82: ifnull        115
      85: aload         4
      87: aload_3
      88: invokeinterface #77,  2           // InterfaceMethod org/apache/camel/Component.createConfiguration:(Ljava/lang/String;)Lorg/apache/camel/EndpointConfiguration;
      93: astore        5
      95: aload         5
      97: instanceof    #79                 // class org/apache/camel/impl/DefaultEndpointConfiguration
     100: ifeq          112
     103: aload         5
     105: checkcast     #79                 // class org/apache/camel/impl/DefaultEndpointConfiguration
     108: aload_0
     109: invokevirtual #83                 // Method org/apache/camel/impl/DefaultEndpointConfiguration.setURI:(Ljava/lang/String;)V
     112: aload         5
     114: areturn
     115: aconst_null
     116: areturn

  public static void populateFromURI(org.apache.camel.CamelContext, org.apache.camel.EndpointConfiguration, org.apache.camel.impl.ConfigurationHelper$ParameterSetter);
    Code:
       0: aload_1
       1: invokeinterface #104,  1          // InterfaceMethod org/apache/camel/EndpointConfiguration.getURI:()Ljava/net/URI;
       6: astore_3
       7: aload_2
       8: aload_0
       9: aload_1
      10: ldc           #105                // String scheme
      12: aload_3
      13: invokevirtual #110                // Method java/net/URI.getScheme:()Ljava/lang/String;
      16: invokeinterface #114,  5          // InterfaceMethod org/apache/camel/impl/ConfigurationHelper$ParameterSetter.set:(Lorg/apache/camel/CamelContext;Lorg/apache/camel/EndpointConfiguration;Ljava/lang/String;Ljava/lang/Object;)V
      21: aload_2
      22: aload_0
      23: aload_1
      24: ldc           #116                // String schemeSpecificPart
      26: aload_3
      27: invokevirtual #119                // Method java/net/URI.getSchemeSpecificPart:()Ljava/lang/String;
      30: invokeinterface #114,  5          // InterfaceMethod org/apache/camel/impl/ConfigurationHelper$ParameterSetter.set:(Lorg/apache/camel/CamelContext;Lorg/apache/camel/EndpointConfiguration;Ljava/lang/String;Ljava/lang/Object;)V
      35: aload_2
      36: aload_0
      37: aload_1
      38: ldc           #121                // String authority
      40: aload_3
      41: invokevirtual #124                // Method java/net/URI.getAuthority:()Ljava/lang/String;
      44: invokeinterface #114,  5          // InterfaceMethod org/apache/camel/impl/ConfigurationHelper$ParameterSetter.set:(Lorg/apache/camel/CamelContext;Lorg/apache/camel/EndpointConfiguration;Ljava/lang/String;Ljava/lang/Object;)V
      49: aload_2
      50: aload_0
      51: aload_1
      52: ldc           #126                // String userInfo
      54: aload_3
      55: invokevirtual #129                // Method java/net/URI.getUserInfo:()Ljava/lang/String;
      58: invokeinterface #114,  5          // InterfaceMethod org/apache/camel/impl/ConfigurationHelper$ParameterSetter.set:(Lorg/apache/camel/CamelContext;Lorg/apache/camel/EndpointConfiguration;Ljava/lang/String;Ljava/lang/Object;)V
      63: aload_2
      64: aload_0
      65: aload_1
      66: ldc           #131                // String host
      68: aload_3
      69: invokevirtual #134                // Method java/net/URI.getHost:()Ljava/lang/String;
      72: invokeinterface #114,  5          // InterfaceMethod org/apache/camel/impl/ConfigurationHelper$ParameterSetter.set:(Lorg/apache/camel/CamelContext;Lorg/apache/camel/EndpointConfiguration;Ljava/lang/String;Ljava/lang/Object;)V
      77: aload_2
      78: aload_0
      79: aload_1
      80: ldc           #136                // String port
      82: aload_3
      83: invokevirtual #140                // Method java/net/URI.getPort:()I
      86: invokestatic  #146                // Method java/lang/Integer.toString:(I)Ljava/lang/String;
      89: invokeinterface #114,  5          // InterfaceMethod org/apache/camel/impl/ConfigurationHelper$ParameterSetter.set:(Lorg/apache/camel/CamelContext;Lorg/apache/camel/EndpointConfiguration;Ljava/lang/String;Ljava/lang/Object;)V
      94: aload_2
      95: aload_0
      96: aload_1
      97: ldc           #148                // String path
      99: aload_3
     100: invokevirtual #151                // Method java/net/URI.getPath:()Ljava/lang/String;
     103: invokeinterface #114,  5          // InterfaceMethod org/apache/camel/impl/ConfigurationHelper$ParameterSetter.set:(Lorg/apache/camel/CamelContext;Lorg/apache/camel/EndpointConfiguration;Ljava/lang/String;Ljava/lang/Object;)V
     108: aload_2
     109: aload_0
     110: aload_1
     111: ldc           #153                // String query
     113: aload_3
     114: invokevirtual #156                // Method java/net/URI.getQuery:()Ljava/lang/String;
     117: invokeinterface #114,  5          // InterfaceMethod org/apache/camel/impl/ConfigurationHelper$ParameterSetter.set:(Lorg/apache/camel/CamelContext;Lorg/apache/camel/EndpointConfiguration;Ljava/lang/String;Ljava/lang/Object;)V
     122: aload_2
     123: aload_0
     124: aload_1
     125: ldc           #158                // String fragment
     127: aload_3
     128: invokevirtual #161                // Method java/net/URI.getFragment:()Ljava/lang/String;
     131: invokeinterface #114,  5          // InterfaceMethod org/apache/camel/impl/ConfigurationHelper$ParameterSetter.set:(Lorg/apache/camel/CamelContext;Lorg/apache/camel/EndpointConfiguration;Ljava/lang/String;Ljava/lang/Object;)V
     136: aload_3
     137: invokestatic  #167                // Method org/apache/camel/util/URISupport.parseParameters:(Ljava/net/URI;)Ljava/util/Map;
     140: astore        4
     142: aload         4
     144: invokeinterface #171,  1          // InterfaceMethod java/util/Map.entrySet:()Ljava/util/Set;
     149: invokeinterface #177,  1          // InterfaceMethod java/util/Set.iterator:()Ljava/util/Iterator;
     154: astore        5
     156: aload         5
     158: invokeinterface #182,  1          // InterfaceMethod java/util/Iterator.hasNext:()Z
     163: ifeq          206
     166: aload         5
     168: invokeinterface #186,  1          // InterfaceMethod java/util/Iterator.next:()Ljava/lang/Object;
     173: checkcast     #13                 // class java/util/Map$Entry
     176: astore        6
     178: aload_2
     179: aload_0
     180: aload_1
     181: aload         6
     183: invokeinterface #189,  1          // InterfaceMethod java/util/Map$Entry.getKey:()Ljava/lang/Object;
     188: checkcast     #30                 // class java/lang/String
     191: aload         6
     193: invokeinterface #192,  1          // InterfaceMethod java/util/Map$Entry.getValue:()Ljava/lang/Object;
     198: invokeinterface #114,  5          // InterfaceMethod org/apache/camel/impl/ConfigurationHelper$ParameterSetter.set:(Lorg/apache/camel/CamelContext;Lorg/apache/camel/EndpointConfiguration;Ljava/lang/String;Ljava/lang/Object;)V
     203: goto          156
     206: goto          221
     209: astore        5
     211: new           #194                // class org/apache/camel/RuntimeCamelException
     214: dup
     215: aload         5
     217: invokespecial #197                // Method org/apache/camel/RuntimeCamelException."<init>":(Ljava/lang/Throwable;)V
     220: athrow
     221: return
    Exception table:
       from    to  target type
         136   206   209   Class java/net/URISyntaxException

  public static java.lang.reflect.Field findConfigurationField(org.apache.camel.EndpointConfiguration, java.lang.String);
    Code:
       0: aload_0
       1: ifnull        164
       4: aload_1
       5: ifnull        164
       8: aload_0
       9: invokevirtual #58                 // Method java/lang/Object.getClass:()Ljava/lang/Class;
      12: astore_2
      13: aload_2
      14: invokevirtual #215                // Method java/lang/Class.getDeclaredFields:()[Ljava/lang/reflect/Field;
      17: astore_3
      18: aload_3
      19: astore        4
      21: aload         4
      23: arraylength
      24: istore        5
      26: iconst_0
      27: istore        6
      29: iload         6
      31: iload         5
      33: if_icmpge     164
      36: aload         4
      38: iload         6
      40: aaload
      41: astore        7
      43: aload         7
      45: ldc           #219                // class org/apache/camel/URIField
      47: invokevirtual #225                // Method java/lang/reflect/Field.getAnnotation:(Ljava/lang/Class;)Ljava/lang/annotation/Annotation;
      50: checkcast     #219                // class org/apache/camel/URIField
      53: astore        8
      55: aload         8
      57: ifnonnull     75
      60: aload         7
      62: invokevirtual #226                // Method java/lang/reflect/Field.getName:()Ljava/lang/String;
      65: aload_1
      66: invokevirtual #230                // Method java/lang/String.equals:(Ljava/lang/Object;)Z
      69: ifeq          158
      72: goto          118
      75: aload         8
      77: invokeinterface #232,  1          // InterfaceMethod org/apache/camel/URIField.component:()Ljava/lang/String;
      82: aload_1
      83: invokevirtual #230                // Method java/lang/String.equals:(Ljava/lang/Object;)Z
      86: ifne          118
      89: aload         8
      91: invokeinterface #232,  1          // InterfaceMethod org/apache/camel/URIField.component:()Ljava/lang/String;
      96: ldc           #153                // String query
      98: invokevirtual #230                // Method java/lang/String.equals:(Ljava/lang/Object;)Z
     101: ifeq          158
     104: aload         8
     106: invokeinterface #235,  1          // InterfaceMethod org/apache/camel/URIField.parameter:()Ljava/lang/String;
     111: aload_1
     112: invokevirtual #230                // Method java/lang/String.equals:(Ljava/lang/Object;)Z
     115: ifeq          158
     118: aload         7
     120: astore        9
     122: getstatic     #46                 // Field LOG:Lorg/slf4j/Logger;
     125: ldc           #237                // String Found field {}.{} as candidate for parameter {}
     127: iconst_3
     128: anewarray     #4                  // class java/lang/Object
     131: dup
     132: iconst_0
     133: aload_2
     134: invokevirtual #64                 // Method java/lang/Class.getName:()Ljava/lang/String;
     137: aastore
     138: dup
     139: iconst_1
     140: aload         9
     142: invokevirtual #226                // Method java/lang/reflect/Field.getName:()Ljava/lang/String;
     145: aastore
     146: dup
     147: iconst_2
     148: aload_1
     149: aastore
     150: invokeinterface #74,  3           // InterfaceMethod org/slf4j/Logger.trace:(Ljava/lang/String;[Ljava/lang/Object;)V
     155: aload         9
     157: areturn
     158: iinc          6, 1
     161: goto          29
     164: aconst_null
     165: areturn

  public static java.lang.Object getConfigurationParameter(org.apache.camel.EndpointConfiguration, java.lang.String);
    Code:
       0: aload_0
       1: aload_1
       2: invokestatic  #251                // Method findConfigurationField:(Lorg/apache/camel/EndpointConfiguration;Ljava/lang/String;)Ljava/lang/reflect/Field;
       5: astore_2
       6: aload_0
       7: aload_2
       8: invokestatic  #254                // Method getConfigurationParameter:(Lorg/apache/camel/EndpointConfiguration;Ljava/lang/reflect/Field;)Ljava/lang/Object;
      11: areturn

  public static java.lang.Object getConfigurationParameter(org.apache.camel.EndpointConfiguration, java.lang.reflect.Field);
    Code:
       0: aload_1
       1: ifnull        69
       4: aload_0
       5: aload_1
       6: invokevirtual #226                // Method java/lang/reflect/Field.getName:()Ljava/lang/String;
       9: invokestatic  #260                // Method org/apache/camel/util/IntrospectionSupport.getProperty:(Ljava/lang/Object;Ljava/lang/String;)Ljava/lang/Object;
      12: areturn
      13: astore_2
      14: new           #194                // class org/apache/camel/RuntimeCamelException
      17: dup
      18: new           #262                // class java/lang/StringBuilder
      21: dup
      22: invokespecial #263                // Method java/lang/StringBuilder."<init>":()V
      25: ldc_w         #265                // String Failed to get property \'
      28: invokevirtual #269                // Method java/lang/StringBuilder.append:(Ljava/lang/String;)Ljava/lang/StringBuilder;
      31: aload_1
      32: invokevirtual #226                // Method java/lang/reflect/Field.getName:()Ljava/lang/String;
      35: invokevirtual #269                // Method java/lang/StringBuilder.append:(Ljava/lang/String;)Ljava/lang/StringBuilder;
      38: ldc_w         #271                // String \' on
      41: invokevirtual #269                // Method java/lang/StringBuilder.append:(Ljava/lang/String;)Ljava/lang/StringBuilder;
      44: aload_0
      45: invokevirtual #274                // Method java/lang/StringBuilder.append:(Ljava/lang/Object;)Ljava/lang/StringBuilder;
      48: ldc_w         #276                // String  due
      51: invokevirtual #269                // Method java/lang/StringBuilder.append:(Ljava/lang/String;)Ljava/lang/StringBuilder;
      54: aload_2
      55: invokevirtual #279                // Method java/lang/Exception.getMessage:()Ljava/lang/String;
      58: invokevirtual #269                // Method java/lang/StringBuilder.append:(Ljava/lang/String;)Ljava/lang/StringBuilder;
      61: invokevirtual #281                // Method java/lang/StringBuilder.toString:()Ljava/lang/String;
      64: aload_2
      65: invokespecial #284                // Method org/apache/camel/RuntimeCamelException."<init>":(Ljava/lang/String;Ljava/lang/Throwable;)V
      68: athrow
      69: aconst_null
      70: areturn
    Exception table:
       from    to  target type
           4    12    13   Class java/lang/Exception

  public static <T> void setConfigurationField(org.apache.camel.CamelContext, org.apache.camel.EndpointConfiguration, java.lang.String, T);
    Code:
       0: aload_1
       1: aload_2
       2: invokestatic  #251                // Method findConfigurationField:(Lorg/apache/camel/EndpointConfiguration;Ljava/lang/String;)Ljava/lang/reflect/Field;
       5: astore        4
       7: aload         4
       9: ifnonnull     13
      12: return
      13: aload_0
      14: invokeinterface #290,  1          // InterfaceMethod org/apache/camel/CamelContext.getTypeConverter:()Lorg/apache/camel/TypeConverter;
      19: aload_1
      20: aload_2
      21: aload_3
      22: invokestatic  #294                // Method org/apache/camel/util/IntrospectionSupport.setProperty:(Lorg/apache/camel/TypeConverter;Ljava/lang/Object;Ljava/lang/String;Ljava/lang/Object;)Z
      25: pop
      26: goto          85
      29: astore        5
      31: new           #194                // class org/apache/camel/RuntimeCamelException
      34: dup
      35: new           #262                // class java/lang/StringBuilder
      38: dup
      39: invokespecial #263                // Method java/lang/StringBuilder."<init>":()V
      42: ldc_w         #296                // String Failed to set property \'
      45: invokevirtual #269                // Method java/lang/StringBuilder.append:(Ljava/lang/String;)Ljava/lang/StringBuilder;
      48: aload_2
      49: invokevirtual #269                // Method java/lang/StringBuilder.append:(Ljava/lang/String;)Ljava/lang/StringBuilder;
      52: ldc_w         #271                // String \' on
      55: invokevirtual #269                // Method java/lang/StringBuilder.append:(Ljava/lang/String;)Ljava/lang/StringBuilder;
      58: aload_1
      59: invokevirtual #274                // Method java/lang/StringBuilder.append:(Ljava/lang/Object;)Ljava/lang/StringBuilder;
      62: ldc_w         #276                // String  due
      65: invokevirtual #269                // Method java/lang/StringBuilder.append:(Ljava/lang/String;)Ljava/lang/StringBuilder;
      68: aload         5
      70: invokevirtual #279                // Method java/lang/Exception.getMessage:()Ljava/lang/String;
      73: invokevirtual #269                // Method java/lang/StringBuilder.append:(Ljava/lang/String;)Ljava/lang/StringBuilder;
      76: invokevirtual #281                // Method java/lang/StringBuilder.toString:()Ljava/lang/String;
      79: aload         5
      81: invokespecial #284                // Method org/apache/camel/RuntimeCamelException."<init>":(Ljava/lang/String;Ljava/lang/Throwable;)V
      84: athrow
      85: return
    Exception table:
       from    to  target type
          13    26    29   Class java/lang/Exception

  static {};
    Code:
       0: ldc           #2                  // class org/apache/camel/impl/ConfigurationHelper
       2: invokestatic  #306                // Method org/slf4j/LoggerFactory.getLogger:(Ljava/lang/Class;)Lorg/slf4j/Logger;
       5: putstatic     #46                 // Field LOG:Lorg/slf4j/Logger;
       8: return
}
