Compiled from "DefaultInflightRepository.java"
class org.apache.camel.impl.DefaultInflightRepository$1 implements java.util.Comparator<org.apache.camel.Exchange> {
  final org.apache.camel.impl.DefaultInflightRepository this$0;

  org.apache.camel.impl.DefaultInflightRepository$1(org.apache.camel.impl.DefaultInflightRepository);
    Code:
       0: aload_0
       1: aload_1
       2: putfield      #19                 // Field this$0:Lorg/apache/camel/impl/DefaultInflightRepository;
       5: aload_0
       6: invokespecial #22                 // Method java/lang/Object."<init>":()V
       9: return

  public int compare(org.apache.camel.Exchange, org.apache.camel.Exchange);
    Code:
       0: aload_1
       1: invokestatic  #30                 // Method org/apache/camel/impl/DefaultInflightRepository.access$000:(Lorg/apache/camel/Exchange;)J
       4: lstore_3
       5: aload_2
       6: invokestatic  #30                 // Method org/apache/camel/impl/DefaultInflightRepository.access$000:(Lorg/apache/camel/Exchange;)J
       9: lstore        5
      11: lload_3
      12: lload         5
      14: invokestatic  #35                 // Method java/lang/Long.compare:(JJ)I
      17: ireturn

  public int compare(java.lang.Object, java.lang.Object);
    Code:
       0: aload_0
       1: aload_1
       2: checkcast     #44                 // class org/apache/camel/Exchange
       5: aload_2
       6: checkcast     #44                 // class org/apache/camel/Exchange
       9: invokevirtual #46                 // Method compare:(Lorg/apache/camel/Exchange;Lorg/apache/camel/Exchange;)I
      12: ireturn
}
