Compiled from "DefaultSubUnitOfWork.java"
public class org.apache.camel.impl.DefaultSubUnitOfWork implements org.apache.camel.spi.SubUnitOfWork,org.apache.camel.spi.SubUnitOfWorkCallback {
  private java.util.List<java.lang.Exception> failedExceptions;

  private boolean failed;

  public org.apache.camel.impl.DefaultSubUnitOfWork();
    Code:
       0: aload_0
       1: invokespecial #18                 // Method java/lang/Object."<init>":()V
       4: return

  public void onExhausted(org.apache.camel.Exchange);
    Code:
       0: aload_1
       1: invokeinterface #28,  1           // InterfaceMethod org/apache/camel/Exchange.getException:()Ljava/lang/Exception;
       6: ifnull        24
       9: aload_0
      10: aload_1
      11: invokeinterface #28,  1           // InterfaceMethod org/apache/camel/Exchange.getException:()Ljava/lang/Exception;
      16: invokespecial #32                 // Method addFailedException:(Ljava/lang/Exception;)V
      19: aload_0
      20: iconst_1
      21: putfield      #34                 // Field failed:Z
      24: return

  public void onDone(org.apache.camel.Exchange);
    Code:
       0: aload_1
       1: invokeinterface #28,  1           // InterfaceMethod org/apache/camel/Exchange.getException:()Ljava/lang/Exception;
       6: ifnull        24
       9: aload_0
      10: aload_1
      11: invokeinterface #28,  1           // InterfaceMethod org/apache/camel/Exchange.getException:()Ljava/lang/Exception;
      16: invokespecial #32                 // Method addFailedException:(Ljava/lang/Exception;)V
      19: aload_0
      20: iconst_1
      21: putfield      #34                 // Field failed:Z
      24: return

  public boolean isFailed();
    Code:
       0: aload_0
       1: getfield      #34                 // Field failed:Z
       4: ireturn

  public java.util.List<java.lang.Exception> getExceptions();
    Code:
       0: aload_0
       1: getfield      #43                 // Field failedExceptions:Ljava/util/List;
       4: areturn

  private void addFailedException(java.lang.Exception);
    Code:
       0: aload_0
       1: getfield      #43                 // Field failedExceptions:Ljava/util/List;
       4: ifnonnull     18
       7: aload_0
       8: new           #45                 // class java/util/ArrayList
      11: dup
      12: invokespecial #46                 // Method java/util/ArrayList."<init>":()V
      15: putfield      #43                 // Field failedExceptions:Ljava/util/List;
      18: aload_0
      19: getfield      #43                 // Field failedExceptions:Ljava/util/List;
      22: aload_1
      23: invokeinterface #52,  2           // InterfaceMethod java/util/List.contains:(Ljava/lang/Object;)Z
      28: ifne          42
      31: aload_0
      32: getfield      #43                 // Field failedExceptions:Ljava/util/List;
      35: aload_1
      36: invokeinterface #55,  2           // InterfaceMethod java/util/List.add:(Ljava/lang/Object;)Z
      41: pop
      42: return
}
