Compiled from "HeaderFilterStrategyComponent.java"
public abstract class org.apache.camel.impl.HeaderFilterStrategyComponent extends org.apache.camel.impl.UriEndpointComponent implements org.apache.camel.spi.HeaderFilterStrategyAware {
  private org.apache.camel.spi.HeaderFilterStrategy headerFilterStrategy;

  public org.apache.camel.impl.HeaderFilterStrategyComponent(java.lang.Class<? extends org.apache.camel.Endpoint>);
    Code:
       0: aload_0
       1: aload_1
       2: invokespecial #13                 // Method org/apache/camel/impl/UriEndpointComponent."<init>":(Ljava/lang/Class;)V
       5: return

  public org.apache.camel.impl.HeaderFilterStrategyComponent(org.apache.camel.CamelContext, java.lang.Class<? extends org.apache.camel.Endpoint>);
    Code:
       0: aload_0
       1: aload_1
       2: aload_2
       3: invokespecial #21                 // Method org/apache/camel/impl/UriEndpointComponent."<init>":(Lorg/apache/camel/CamelContext;Ljava/lang/Class;)V
       6: return

  public org.apache.camel.spi.HeaderFilterStrategy getHeaderFilterStrategy();
    Code:
       0: aload_0
       1: getfield      #27                 // Field headerFilterStrategy:Lorg/apache/camel/spi/HeaderFilterStrategy;
       4: areturn

  public void setHeaderFilterStrategy(org.apache.camel.spi.HeaderFilterStrategy);
    Code:
       0: aload_0
       1: aload_1
       2: putfield      #27                 // Field headerFilterStrategy:Lorg/apache/camel/spi/HeaderFilterStrategy;
       5: return

  public void setEndpointHeaderFilterStrategy(org.apache.camel.Endpoint);
    Code:
       0: aload_0
       1: getfield      #27                 // Field headerFilterStrategy:Lorg/apache/camel/spi/HeaderFilterStrategy;
       4: ifnull        27
       7: aload_1
       8: instanceof    #6                  // class org/apache/camel/spi/HeaderFilterStrategyAware
      11: ifeq          27
      14: aload_1
      15: checkcast     #6                  // class org/apache/camel/spi/HeaderFilterStrategyAware
      18: aload_0
      19: getfield      #27                 // Field headerFilterStrategy:Lorg/apache/camel/spi/HeaderFilterStrategy;
      22: invokeinterface #34,  2           // InterfaceMethod org/apache/camel/spi/HeaderFilterStrategyAware.setHeaderFilterStrategy:(Lorg/apache/camel/spi/HeaderFilterStrategy;)V
      27: return
}
