Compiled from "SynchronousDelegateProducer.java"
public class org.apache.camel.impl.SynchronousDelegateProducer implements org.apache.camel.Producer {
  private final org.apache.camel.Producer producer;

  public org.apache.camel.impl.SynchronousDelegateProducer(org.apache.camel.Producer);
    Code:
       0: aload_0
       1: invokespecial #14                 // Method java/lang/Object."<init>":()V
       4: aload_0
       5: aload_1
       6: putfield      #16                 // Field producer:Lorg/apache/camel/Producer;
       9: return

  public org.apache.camel.Endpoint getEndpoint();
    Code:
       0: aload_0
       1: getfield      #16                 // Field producer:Lorg/apache/camel/Producer;
       4: invokeinterface #22,  1           // InterfaceMethod org/apache/camel/Producer.getEndpoint:()Lorg/apache/camel/Endpoint;
       9: areturn

  public org.apache.camel.Exchange createExchange();
    Code:
       0: aload_0
       1: getfield      #16                 // Field producer:Lorg/apache/camel/Producer;
       4: invokeinterface #26,  1           // InterfaceMethod org/apache/camel/Producer.createExchange:()Lorg/apache/camel/Exchange;
       9: areturn

  public org.apache.camel.Exchange createExchange(org.apache.camel.ExchangePattern);
    Code:
       0: aload_0
       1: getfield      #16                 // Field producer:Lorg/apache/camel/Producer;
       4: aload_1
       5: invokeinterface #29,  2           // InterfaceMethod org/apache/camel/Producer.createExchange:(Lorg/apache/camel/ExchangePattern;)Lorg/apache/camel/Exchange;
      10: areturn

  public org.apache.camel.Exchange createExchange(org.apache.camel.Exchange);
    Code:
       0: aload_0
       1: getfield      #16                 // Field producer:Lorg/apache/camel/Producer;
       4: aload_1
       5: invokeinterface #35,  2           // InterfaceMethod org/apache/camel/Producer.createExchange:(Lorg/apache/camel/Exchange;)Lorg/apache/camel/Exchange;
      10: areturn

  public void process(org.apache.camel.Exchange) throws java.lang.Exception;
    Code:
       0: aload_0
       1: getfield      #16                 // Field producer:Lorg/apache/camel/Producer;
       4: aload_1
       5: invokeinterface #43,  2           // InterfaceMethod org/apache/camel/Producer.process:(Lorg/apache/camel/Exchange;)V
      10: return

  public void start() throws java.lang.Exception;
    Code:
       0: aload_0
       1: getfield      #16                 // Field producer:Lorg/apache/camel/Producer;
       4: invokeinterface #46,  1           // InterfaceMethod org/apache/camel/Producer.start:()V
       9: return

  public void stop() throws java.lang.Exception;
    Code:
       0: aload_0
       1: getfield      #16                 // Field producer:Lorg/apache/camel/Producer;
       4: invokeinterface #49,  1           // InterfaceMethod org/apache/camel/Producer.stop:()V
       9: return

  public boolean isSingleton();
    Code:
       0: aload_0
       1: getfield      #16                 // Field producer:Lorg/apache/camel/Producer;
       4: invokeinterface #53,  1           // InterfaceMethod org/apache/camel/Producer.isSingleton:()Z
       9: ireturn

  public java.lang.String toString();
    Code:
       0: aload_0
       1: getfield      #16                 // Field producer:Lorg/apache/camel/Producer;
       4: invokevirtual #57                 // Method java/lang/Object.toString:()Ljava/lang/String;
       7: areturn
}
