Compiled from "CachePoolStats.java"
public class org.apache.hadoop.hdfs.protocol.CachePoolStats$Builder {
  private long bytesNeeded;

  private long bytesCached;

  private long bytesOverlimit;

  private long filesNeeded;

  private long filesCached;

  public org.apache.hadoop.hdfs.protocol.CachePoolStats$Builder();
    Code:
       0: aload_0
       1: invokespecial #1                  // Method java/lang/Object."<init>":()V
       4: return

  public org.apache.hadoop.hdfs.protocol.CachePoolStats$Builder setBytesNeeded(long);
    Code:
       0: aload_0
       1: lload_1
       2: putfield      #2                  // Field bytesNeeded:J
       5: aload_0
       6: areturn

  public org.apache.hadoop.hdfs.protocol.CachePoolStats$Builder setBytesCached(long);
    Code:
       0: aload_0
       1: lload_1
       2: putfield      #3                  // Field bytesCached:J
       5: aload_0
       6: areturn

  public org.apache.hadoop.hdfs.protocol.CachePoolStats$Builder setBytesOverlimit(long);
    Code:
       0: aload_0
       1: lload_1
       2: putfield      #4                  // Field bytesOverlimit:J
       5: aload_0
       6: areturn

  public org.apache.hadoop.hdfs.protocol.CachePoolStats$Builder setFilesNeeded(long);
    Code:
       0: aload_0
       1: lload_1
       2: putfield      #5                  // Field filesNeeded:J
       5: aload_0
       6: areturn

  public org.apache.hadoop.hdfs.protocol.CachePoolStats$Builder setFilesCached(long);
    Code:
       0: aload_0
       1: lload_1
       2: putfield      #6                  // Field filesCached:J
       5: aload_0
       6: areturn

  public org.apache.hadoop.hdfs.protocol.CachePoolStats build();
    Code:
       0: new           #7                  // class org/apache/hadoop/hdfs/protocol/CachePoolStats
       3: dup
       4: aload_0
       5: getfield      #2                  // Field bytesNeeded:J
       8: aload_0
       9: getfield      #3                  // Field bytesCached:J
      12: aload_0
      13: getfield      #4                  // Field bytesOverlimit:J
      16: aload_0
      17: getfield      #5                  // Field filesNeeded:J
      20: aload_0
      21: getfield      #6                  // Field filesCached:J
      24: aconst_null
      25: invokespecial #8                  // Method org/apache/hadoop/hdfs/protocol/CachePoolStats."<init>":(JJJJJLorg/apache/hadoop/hdfs/protocol/CachePoolStats$1;)V
      28: areturn
}
