Compiled from "DatanodeVolumeInfo.java"
public class org.apache.hadoop.hdfs.protocol.DatanodeVolumeInfo {
  private long usedSpace;

  private long freeSpace;

  private long reservedSpace;

  private long reservedSpaceForReplicas;

  private long numBlocks;

  private org.apache.hadoop.fs.StorageType storageType;

  private java.lang.String path;

  public org.apache.hadoop.hdfs.protocol.DatanodeVolumeInfo(java.lang.String, long, long, long, long, long, org.apache.hadoop.fs.StorageType);
    Code:
       0: aload_0
       1: invokespecial #1                  // Method java/lang/Object."<init>":()V
       4: aload_0
       5: lload_2
       6: putfield      #2                  // Field usedSpace:J
       9: aload_0
      10: lload         4
      12: putfield      #3                  // Field freeSpace:J
      15: aload_0
      16: lload         6
      18: putfield      #4                  // Field reservedSpace:J
      21: aload_0
      22: lload         8
      24: putfield      #5                  // Field reservedSpaceForReplicas:J
      27: aload_0
      28: lload         10
      30: putfield      #6                  // Field numBlocks:J
      33: aload_0
      34: aload         12
      36: putfield      #7                  // Field storageType:Lorg/apache/hadoop/fs/StorageType;
      39: aload_0
      40: aload_1
      41: putfield      #8                  // Field path:Ljava/lang/String;
      44: return

  public long getUsedSpace();
    Code:
       0: aload_0
       1: getfield      #2                  // Field usedSpace:J
       4: lreturn

  public long getFreeSpace();
    Code:
       0: aload_0
       1: getfield      #3                  // Field freeSpace:J
       4: lreturn

  public long getReservedSpace();
    Code:
       0: aload_0
       1: getfield      #4                  // Field reservedSpace:J
       4: lreturn

  public long getReservedSpaceForReplicas();
    Code:
       0: aload_0
       1: getfield      #5                  // Field reservedSpaceForReplicas:J
       4: lreturn

  public long getNumBlocks();
    Code:
       0: aload_0
       1: getfield      #6                  // Field numBlocks:J
       4: lreturn

  public org.apache.hadoop.fs.StorageType getStorageType();
    Code:
       0: aload_0
       1: getfield      #7                  // Field storageType:Lorg/apache/hadoop/fs/StorageType;
       4: areturn

  public java.lang.String getPath();
    Code:
       0: aload_0
       1: getfield      #8                  // Field path:Ljava/lang/String;
       4: areturn

  public java.lang.String getDatanodeVolumeReport();
    Code:
       0: new           #9                  // class java/lang/StringBuilder
       3: dup
       4: invokespecial #10                 // Method java/lang/StringBuilder."<init>":()V
       7: astore_1
       8: aload_1
       9: new           #9                  // class java/lang/StringBuilder
      12: dup
      13: invokespecial #10                 // Method java/lang/StringBuilder."<init>":()V
      16: ldc           #11                 // String Directory:
      18: invokevirtual #12                 // Method java/lang/StringBuilder.append:(Ljava/lang/String;)Ljava/lang/StringBuilder;
      21: aload_0
      22: getfield      #8                  // Field path:Ljava/lang/String;
      25: invokevirtual #12                 // Method java/lang/StringBuilder.append:(Ljava/lang/String;)Ljava/lang/StringBuilder;
      28: invokevirtual #13                 // Method java/lang/StringBuilder.toString:()Ljava/lang/String;
      31: invokevirtual #12                 // Method java/lang/StringBuilder.append:(Ljava/lang/String;)Ljava/lang/StringBuilder;
      34: new           #9                  // class java/lang/StringBuilder
      37: dup
      38: invokespecial #10                 // Method java/lang/StringBuilder."<init>":()V
      41: ldc           #14                 // String \nStorageType:
      43: invokevirtual #12                 // Method java/lang/StringBuilder.append:(Ljava/lang/String;)Ljava/lang/StringBuilder;
      46: aload_0
      47: getfield      #7                  // Field storageType:Lorg/apache/hadoop/fs/StorageType;
      50: invokevirtual #15                 // Method java/lang/StringBuilder.append:(Ljava/lang/Object;)Ljava/lang/StringBuilder;
      53: invokevirtual #13                 // Method java/lang/StringBuilder.toString:()Ljava/lang/String;
      56: invokevirtual #12                 // Method java/lang/StringBuilder.append:(Ljava/lang/String;)Ljava/lang/StringBuilder;
      59: new           #9                  // class java/lang/StringBuilder
      62: dup
      63: invokespecial #10                 // Method java/lang/StringBuilder."<init>":()V
      66: ldc           #16                 // String \nCapacity Used:
      68: invokevirtual #12                 // Method java/lang/StringBuilder.append:(Ljava/lang/String;)Ljava/lang/StringBuilder;
      71: aload_0
      72: getfield      #2                  // Field usedSpace:J
      75: invokevirtual #17                 // Method java/lang/StringBuilder.append:(J)Ljava/lang/StringBuilder;
      78: ldc           #18                 // String (
      80: invokevirtual #12                 // Method java/lang/StringBuilder.append:(Ljava/lang/String;)Ljava/lang/StringBuilder;
      83: aload_0
      84: getfield      #2                  // Field usedSpace:J
      87: invokestatic  #19                 // Method org/apache/hadoop/util/StringUtils.byteDesc:(J)Ljava/lang/String;
      90: invokevirtual #12                 // Method java/lang/StringBuilder.append:(Ljava/lang/String;)Ljava/lang/StringBuilder;
      93: ldc           #20                 // String )
      95: invokevirtual #12                 // Method java/lang/StringBuilder.append:(Ljava/lang/String;)Ljava/lang/StringBuilder;
      98: invokevirtual #13                 // Method java/lang/StringBuilder.toString:()Ljava/lang/String;
     101: invokevirtual #12                 // Method java/lang/StringBuilder.append:(Ljava/lang/String;)Ljava/lang/StringBuilder;
     104: new           #9                  // class java/lang/StringBuilder
     107: dup
     108: invokespecial #10                 // Method java/lang/StringBuilder."<init>":()V
     111: ldc           #21                 // String \nCapacity Left:
     113: invokevirtual #12                 // Method java/lang/StringBuilder.append:(Ljava/lang/String;)Ljava/lang/StringBuilder;
     116: aload_0
     117: getfield      #3                  // Field freeSpace:J
     120: invokevirtual #17                 // Method java/lang/StringBuilder.append:(J)Ljava/lang/StringBuilder;
     123: ldc           #18                 // String (
     125: invokevirtual #12                 // Method java/lang/StringBuilder.append:(Ljava/lang/String;)Ljava/lang/StringBuilder;
     128: aload_0
     129: getfield      #3                  // Field freeSpace:J
     132: invokestatic  #19                 // Method org/apache/hadoop/util/StringUtils.byteDesc:(J)Ljava/lang/String;
     135: invokevirtual #12                 // Method java/lang/StringBuilder.append:(Ljava/lang/String;)Ljava/lang/StringBuilder;
     138: ldc           #20                 // String )
     140: invokevirtual #12                 // Method java/lang/StringBuilder.append:(Ljava/lang/String;)Ljava/lang/StringBuilder;
     143: invokevirtual #13                 // Method java/lang/StringBuilder.toString:()Ljava/lang/String;
     146: invokevirtual #12                 // Method java/lang/StringBuilder.append:(Ljava/lang/String;)Ljava/lang/StringBuilder;
     149: new           #9                  // class java/lang/StringBuilder
     152: dup
     153: invokespecial #10                 // Method java/lang/StringBuilder."<init>":()V
     156: ldc           #22                 // String \nCapacity Reserved:
     158: invokevirtual #12                 // Method java/lang/StringBuilder.append:(Ljava/lang/String;)Ljava/lang/StringBuilder;
     161: aload_0
     162: getfield      #4                  // Field reservedSpace:J
     165: invokevirtual #17                 // Method java/lang/StringBuilder.append:(J)Ljava/lang/StringBuilder;
     168: ldc           #18                 // String (
     170: invokevirtual #12                 // Method java/lang/StringBuilder.append:(Ljava/lang/String;)Ljava/lang/StringBuilder;
     173: aload_0
     174: getfield      #4                  // Field reservedSpace:J
     177: invokestatic  #19                 // Method org/apache/hadoop/util/StringUtils.byteDesc:(J)Ljava/lang/String;
     180: invokevirtual #12                 // Method java/lang/StringBuilder.append:(Ljava/lang/String;)Ljava/lang/StringBuilder;
     183: ldc           #20                 // String )
     185: invokevirtual #12                 // Method java/lang/StringBuilder.append:(Ljava/lang/String;)Ljava/lang/StringBuilder;
     188: invokevirtual #13                 // Method java/lang/StringBuilder.toString:()Ljava/lang/String;
     191: invokevirtual #12                 // Method java/lang/StringBuilder.append:(Ljava/lang/String;)Ljava/lang/StringBuilder;
     194: new           #9                  // class java/lang/StringBuilder
     197: dup
     198: invokespecial #10                 // Method java/lang/StringBuilder."<init>":()V
     201: ldc           #23                 // String \nReserved Space for Replicas:
     203: invokevirtual #12                 // Method java/lang/StringBuilder.append:(Ljava/lang/String;)Ljava/lang/StringBuilder;
     206: aload_0
     207: getfield      #5                  // Field reservedSpaceForReplicas:J
     210: invokevirtual #17                 // Method java/lang/StringBuilder.append:(J)Ljava/lang/StringBuilder;
     213: ldc           #18                 // String (
     215: invokevirtual #12                 // Method java/lang/StringBuilder.append:(Ljava/lang/String;)Ljava/lang/StringBuilder;
     218: aload_0
     219: getfield      #5                  // Field reservedSpaceForReplicas:J
     222: invokestatic  #19                 // Method org/apache/hadoop/util/StringUtils.byteDesc:(J)Ljava/lang/String;
     225: invokevirtual #12                 // Method java/lang/StringBuilder.append:(Ljava/lang/String;)Ljava/lang/StringBuilder;
     228: ldc           #20                 // String )
     230: invokevirtual #12                 // Method java/lang/StringBuilder.append:(Ljava/lang/String;)Ljava/lang/StringBuilder;
     233: invokevirtual #13                 // Method java/lang/StringBuilder.toString:()Ljava/lang/String;
     236: invokevirtual #12                 // Method java/lang/StringBuilder.append:(Ljava/lang/String;)Ljava/lang/StringBuilder;
     239: new           #9                  // class java/lang/StringBuilder
     242: dup
     243: invokespecial #10                 // Method java/lang/StringBuilder."<init>":()V
     246: ldc           #24                 // String \nBlocks:
     248: invokevirtual #12                 // Method java/lang/StringBuilder.append:(Ljava/lang/String;)Ljava/lang/StringBuilder;
     251: aload_0
     252: getfield      #6                  // Field numBlocks:J
     255: invokevirtual #17                 // Method java/lang/StringBuilder.append:(J)Ljava/lang/StringBuilder;
     258: invokevirtual #13                 // Method java/lang/StringBuilder.toString:()Ljava/lang/String;
     261: invokevirtual #12                 // Method java/lang/StringBuilder.append:(Ljava/lang/String;)Ljava/lang/StringBuilder;
     264: pop
     265: aload_1
     266: invokevirtual #13                 // Method java/lang/StringBuilder.toString:()Ljava/lang/String;
     269: areturn
}
