Compiled from "HdfsFileStatus.java"
public interface org.apache.hadoop.hdfs.protocol.HdfsFileStatus extends org.apache.hadoop.io.Writable, java.lang.Comparable<java.lang.Object>, java.io.Serializable, java.io.ObjectInputValidation {
  public static final byte[] EMPTY_NAME;

  public abstract long getFileId();

  public abstract org.apache.hadoop.fs.FileEncryptionInfo getFileEncryptionInfo();

  public default boolean isEmptyLocalName();
    Code:
       0: aload_0
       1: invokeinterface #1,  1            // InterfaceMethod getLocalNameInBytes:()[B
       6: arraylength
       7: ifne          14
      10: iconst_1
      11: goto          15
      14: iconst_0
      15: ireturn

  public default java.lang.String getLocalName();
    Code:
       0: aload_0
       1: invokeinterface #1,  1            // InterfaceMethod getLocalNameInBytes:()[B
       6: invokestatic  #2                  // Method org/apache/hadoop/hdfs/DFSUtilClient.bytes2String:([B)Ljava/lang/String;
       9: areturn

  public abstract byte[] getLocalNameInBytes();

  public default java.lang.String getFullName(java.lang.String);
    Code:
       0: aload_0
       1: invokeinterface #3,  1            // InterfaceMethod isEmptyLocalName:()Z
       6: ifeq          11
       9: aload_1
      10: areturn
      11: new           #4                  // class java/lang/StringBuilder
      14: dup
      15: aload_1
      16: invokespecial #5                  // Method java/lang/StringBuilder."<init>":(Ljava/lang/String;)V
      19: astore_2
      20: aload_1
      21: ldc           #7                  // String /
      23: invokevirtual #8                  // Method java/lang/String.endsWith:(Ljava/lang/String;)Z
      26: ifne          36
      29: aload_2
      30: ldc           #7                  // String /
      32: invokevirtual #9                  // Method java/lang/StringBuilder.append:(Ljava/lang/String;)Ljava/lang/StringBuilder;
      35: pop
      36: aload_2
      37: aload_0
      38: invokeinterface #10,  1           // InterfaceMethod getLocalName:()Ljava/lang/String;
      43: invokevirtual #9                  // Method java/lang/StringBuilder.append:(Ljava/lang/String;)Ljava/lang/StringBuilder;
      46: pop
      47: aload_2
      48: invokevirtual #11                 // Method java/lang/StringBuilder.toString:()Ljava/lang/String;
      51: areturn

  public default org.apache.hadoop.fs.Path getFullPath(org.apache.hadoop.fs.Path);
    Code:
       0: aload_0
       1: invokeinterface #3,  1            // InterfaceMethod isEmptyLocalName:()Z
       6: ifeq          11
       9: aload_1
      10: areturn
      11: new           #6                  // class org/apache/hadoop/fs/Path
      14: dup
      15: aload_1
      16: aload_0
      17: invokeinterface #10,  1           // InterfaceMethod getLocalName:()Ljava/lang/String;
      22: invokespecial #12                 // Method org/apache/hadoop/fs/Path."<init>":(Lorg/apache/hadoop/fs/Path;Ljava/lang/String;)V
      25: areturn

  public abstract byte[] getSymlinkInBytes();

  public abstract int getChildrenNum();

  public abstract org.apache.hadoop.hdfs.protocol.ErasureCodingPolicy getErasureCodingPolicy();

  public abstract byte getStoragePolicy();

  public default org.apache.hadoop.fs.FileStatus makeQualified(java.net.URI, org.apache.hadoop.fs.Path);
    Code:
       0: aload_0
       1: aload_0
       2: aload_2
       3: invokeinterface #13,  2           // InterfaceMethod getFullPath:(Lorg/apache/hadoop/fs/Path;)Lorg/apache/hadoop/fs/Path;
       8: aload_1
       9: aconst_null
      10: invokevirtual #14                 // Method org/apache/hadoop/fs/Path.makeQualified:(Ljava/net/URI;Lorg/apache/hadoop/fs/Path;)Lorg/apache/hadoop/fs/Path;
      13: invokeinterface #15,  2           // InterfaceMethod setPath:(Lorg/apache/hadoop/fs/Path;)V
      18: aload_0
      19: checkcast     #16                 // class org/apache/hadoop/fs/FileStatus
      22: areturn

  public abstract org.apache.hadoop.fs.Path getPath();

  public abstract void setPath(org.apache.hadoop.fs.Path);

  public abstract long getLen();

  public abstract boolean isFile();

  public abstract boolean isDirectory();

  public abstract boolean isDir();

  public abstract boolean isSymlink();

  public abstract long getBlockSize();

  public abstract short getReplication();

  public abstract long getModificationTime();

  public abstract long getAccessTime();

  public abstract org.apache.hadoop.fs.permission.FsPermission getPermission();

  public abstract void setPermission(org.apache.hadoop.fs.permission.FsPermission);

  public abstract java.lang.String getOwner();

  public abstract void setOwner(java.lang.String);

  public abstract java.lang.String getGroup();

  public abstract void setGroup(java.lang.String);

  public abstract boolean hasAcl();

  public abstract boolean isEncrypted();

  public abstract boolean isErasureCoded();

  public abstract boolean isSnapshotEnabled();

  public abstract org.apache.hadoop.fs.Path getSymlink() throws java.io.IOException;

  public abstract void setSymlink(org.apache.hadoop.fs.Path);

  public abstract int compareTo(org.apache.hadoop.fs.FileStatus);

  public static org.apache.hadoop.fs.permission.FsPermission convert(boolean, boolean, org.apache.hadoop.fs.permission.FsPermission, java.util.Set<org.apache.hadoop.hdfs.protocol.HdfsFileStatus$Flags>);
    Code:
       0: aload_2
       1: instanceof    #17                 // class org/apache/hadoop/hdfs/protocol/FsPermissionExtension
       4: ifeq          99
       7: getstatic     #18                 // Field org/apache/hadoop/hdfs/protocol/HdfsFileStatus$1.$assertionsDisabled:Z
      10: ifne          37
      13: aload_2
      14: invokevirtual #19                 // Method org/apache/hadoop/fs/permission/FsPermission.getAclBit:()Z
      17: aload_3
      18: getstatic     #20                 // Field org/apache/hadoop/hdfs/protocol/HdfsFileStatus$Flags.HAS_ACL:Lorg/apache/hadoop/hdfs/protocol/HdfsFileStatus$Flags;
      21: invokeinterface #21,  2           // InterfaceMethod java/util/Set.contains:(Ljava/lang/Object;)Z
      26: if_icmpeq     37
      29: new           #22                 // class java/lang/AssertionError
      32: dup
      33: invokespecial #23                 // Method java/lang/AssertionError."<init>":()V
      36: athrow
      37: getstatic     #18                 // Field org/apache/hadoop/hdfs/protocol/HdfsFileStatus$1.$assertionsDisabled:Z
      40: ifne          67
      43: aload_2
      44: invokevirtual #24                 // Method org/apache/hadoop/fs/permission/FsPermission.getEncryptedBit:()Z
      47: aload_3
      48: getstatic     #25                 // Field org/apache/hadoop/hdfs/protocol/HdfsFileStatus$Flags.HAS_CRYPT:Lorg/apache/hadoop/hdfs/protocol/HdfsFileStatus$Flags;
      51: invokeinterface #21,  2           // InterfaceMethod java/util/Set.contains:(Ljava/lang/Object;)Z
      56: if_icmpeq     67
      59: new           #22                 // class java/lang/AssertionError
      62: dup
      63: invokespecial #23                 // Method java/lang/AssertionError."<init>":()V
      66: athrow
      67: getstatic     #18                 // Field org/apache/hadoop/hdfs/protocol/HdfsFileStatus$1.$assertionsDisabled:Z
      70: ifne          97
      73: aload_2
      74: invokevirtual #26                 // Method org/apache/hadoop/fs/permission/FsPermission.getErasureCodedBit:()Z
      77: aload_3
      78: getstatic     #27                 // Field org/apache/hadoop/hdfs/protocol/HdfsFileStatus$Flags.HAS_EC:Lorg/apache/hadoop/hdfs/protocol/HdfsFileStatus$Flags;
      81: invokeinterface #21,  2           // InterfaceMethod java/util/Set.contains:(Ljava/lang/Object;)Z
      86: if_icmpeq     97
      89: new           #22                 // class java/lang/AssertionError
      92: dup
      93: invokespecial #23                 // Method java/lang/AssertionError."<init>":()V
      96: athrow
      97: aload_2
      98: areturn
      99: aconst_null
     100: aload_2
     101: if_acmpne     130
     104: iload_0
     105: ifeq          115
     108: invokestatic  #28                 // Method org/apache/hadoop/fs/permission/FsPermission.getDirDefault:()Lorg/apache/hadoop/fs/permission/FsPermission;
     111: astore_2
     112: goto          130
     115: iload_1
     116: ifeq          126
     119: invokestatic  #29                 // Method org/apache/hadoop/fs/permission/FsPermission.getDefault:()Lorg/apache/hadoop/fs/permission/FsPermission;
     122: astore_2
     123: goto          130
     126: invokestatic  #30                 // Method org/apache/hadoop/fs/permission/FsPermission.getFileDefault:()Lorg/apache/hadoop/fs/permission/FsPermission;
     129: astore_2
     130: new           #17                 // class org/apache/hadoop/hdfs/protocol/FsPermissionExtension
     133: dup
     134: aload_2
     135: aload_3
     136: getstatic     #20                 // Field org/apache/hadoop/hdfs/protocol/HdfsFileStatus$Flags.HAS_ACL:Lorg/apache/hadoop/hdfs/protocol/HdfsFileStatus$Flags;
     139: invokeinterface #21,  2           // InterfaceMethod java/util/Set.contains:(Ljava/lang/Object;)Z
     144: aload_3
     145: getstatic     #25                 // Field org/apache/hadoop/hdfs/protocol/HdfsFileStatus$Flags.HAS_CRYPT:Lorg/apache/hadoop/hdfs/protocol/HdfsFileStatus$Flags;
     148: invokeinterface #21,  2           // InterfaceMethod java/util/Set.contains:(Ljava/lang/Object;)Z
     153: aload_3
     154: getstatic     #27                 // Field org/apache/hadoop/hdfs/protocol/HdfsFileStatus$Flags.HAS_EC:Lorg/apache/hadoop/hdfs/protocol/HdfsFileStatus$Flags;
     157: invokeinterface #21,  2           // InterfaceMethod java/util/Set.contains:(Ljava/lang/Object;)Z
     162: invokespecial #31                 // Method org/apache/hadoop/hdfs/protocol/FsPermissionExtension."<init>":(Lorg/apache/hadoop/fs/permission/FsPermission;ZZZ)V
     165: areturn

  public static java.util.Set<org.apache.hadoop.fs.FileStatus$AttrFlags> convert(java.util.Set<org.apache.hadoop.hdfs.protocol.HdfsFileStatus$Flags>);
    Code:
       0: aload_0
       1: invokeinterface #32,  1           // InterfaceMethod java/util/Set.isEmpty:()Z
       6: ifeq          13
       9: getstatic     #33                 // Field org/apache/hadoop/fs/FileStatus.NONE:Ljava/util/Set;
      12: areturn
      13: ldc           #34                 // class org/apache/hadoop/fs/FileStatus$AttrFlags
      15: invokestatic  #35                 // Method java/util/EnumSet.noneOf:(Ljava/lang/Class;)Ljava/util/EnumSet;
      18: astore_1
      19: aload_0
      20: getstatic     #20                 // Field org/apache/hadoop/hdfs/protocol/HdfsFileStatus$Flags.HAS_ACL:Lorg/apache/hadoop/hdfs/protocol/HdfsFileStatus$Flags;
      23: invokeinterface #21,  2           // InterfaceMethod java/util/Set.contains:(Ljava/lang/Object;)Z
      28: ifeq          39
      31: aload_1
      32: getstatic     #36                 // Field org/apache/hadoop/fs/FileStatus$AttrFlags.HAS_ACL:Lorg/apache/hadoop/fs/FileStatus$AttrFlags;
      35: invokevirtual #37                 // Method java/util/EnumSet.add:(Ljava/lang/Object;)Z
      38: pop
      39: aload_0
      40: getstatic     #27                 // Field org/apache/hadoop/hdfs/protocol/HdfsFileStatus$Flags.HAS_EC:Lorg/apache/hadoop/hdfs/protocol/HdfsFileStatus$Flags;
      43: invokeinterface #21,  2           // InterfaceMethod java/util/Set.contains:(Ljava/lang/Object;)Z
      48: ifeq          59
      51: aload_1
      52: getstatic     #38                 // Field org/apache/hadoop/fs/FileStatus$AttrFlags.HAS_EC:Lorg/apache/hadoop/fs/FileStatus$AttrFlags;
      55: invokevirtual #37                 // Method java/util/EnumSet.add:(Ljava/lang/Object;)Z
      58: pop
      59: aload_0
      60: getstatic     #25                 // Field org/apache/hadoop/hdfs/protocol/HdfsFileStatus$Flags.HAS_CRYPT:Lorg/apache/hadoop/hdfs/protocol/HdfsFileStatus$Flags;
      63: invokeinterface #21,  2           // InterfaceMethod java/util/Set.contains:(Ljava/lang/Object;)Z
      68: ifeq          79
      71: aload_1
      72: getstatic     #39                 // Field org/apache/hadoop/fs/FileStatus$AttrFlags.HAS_CRYPT:Lorg/apache/hadoop/fs/FileStatus$AttrFlags;
      75: invokevirtual #37                 // Method java/util/EnumSet.add:(Ljava/lang/Object;)Z
      78: pop
      79: aload_0
      80: getstatic     #40                 // Field org/apache/hadoop/hdfs/protocol/HdfsFileStatus$Flags.SNAPSHOT_ENABLED:Lorg/apache/hadoop/hdfs/protocol/HdfsFileStatus$Flags;
      83: invokeinterface #21,  2           // InterfaceMethod java/util/Set.contains:(Ljava/lang/Object;)Z
      88: ifeq          99
      91: aload_1
      92: getstatic     #41                 // Field org/apache/hadoop/fs/FileStatus$AttrFlags.SNAPSHOT_ENABLED:Lorg/apache/hadoop/fs/FileStatus$AttrFlags;
      95: invokevirtual #37                 // Method java/util/EnumSet.add:(Ljava/lang/Object;)Z
      98: pop
      99: aload_1
     100: areturn

  static {};
    Code:
       0: getstatic     #18                 // Field org/apache/hadoop/hdfs/protocol/HdfsFileStatus$1.$assertionsDisabled:Z
       3: ifeq          6
       6: iconst_0
       7: newarray       byte
       9: putstatic     #42                 // Field EMPTY_NAME:[B
      12: return
}
