Compiled from "BasicPOJOClass.java"
public abstract class org.hibernate.tool.hbm2x.pojo.BasicPOJOClass implements org.hibernate.tool.hbm2x.pojo.POJOClass,org.hibernate.tool.hbm2x.MetaAttributeConstants {
  protected org.hibernate.tool.hbm2x.pojo.ImportContext importContext;

  protected org.hibernate.mapping.MetaAttributable meta;

  protected final org.hibernate.tool.hbm2x.Cfg2JavaTool c2j;

  static java.util.Map defaultInitializors;

  public org.hibernate.tool.hbm2x.pojo.BasicPOJOClass(org.hibernate.mapping.MetaAttributable, org.hibernate.tool.hbm2x.Cfg2JavaTool);
    Code:
       0: aload_0
       1: invokespecial #1                  // Method java/lang/Object."<init>":()V
       4: aload_0
       5: aload_1
       6: putfield      #2                  // Field meta:Lorg/hibernate/mapping/MetaAttributable;
       9: aload_0
      10: aload_2
      11: putfield      #3                  // Field c2j:Lorg/hibernate/tool/hbm2x/Cfg2JavaTool;
      14: aload_0
      15: getfield      #2                  // Field meta:Lorg/hibernate/mapping/MetaAttributable;
      18: ifnonnull     31
      21: new           #4                  // class java/lang/IllegalArgumentException
      24: dup
      25: ldc           #5                  // String class Argument must be not null
      27: invokespecial #6                  // Method java/lang/IllegalArgumentException."<init>":(Ljava/lang/String;)V
      30: athrow
      31: aload_0
      32: getfield      #3                  // Field c2j:Lorg/hibernate/tool/hbm2x/Cfg2JavaTool;
      35: ifnonnull     48
      38: new           #4                  // class java/lang/IllegalArgumentException
      41: dup
      42: ldc           #7                  // String c2j must be not null
      44: invokespecial #6                  // Method java/lang/IllegalArgumentException."<init>":(Ljava/lang/String;)V
      47: athrow
      48: return

  protected void init();
    Code:
       0: aload_0
       1: new           #8                  // class org/hibernate/tool/hbm2x/pojo/ImportContextImpl
       4: dup
       5: aload_0
       6: invokevirtual #9                  // Method getPackageName:()Ljava/lang/String;
       9: invokespecial #10                 // Method org/hibernate/tool/hbm2x/pojo/ImportContextImpl."<init>":(Ljava/lang/String;)V
      12: putfield      #11                 // Field importContext:Lorg/hibernate/tool/hbm2x/pojo/ImportContext;
      15: aload_0
      16: getfield      #2                  // Field meta:Lorg/hibernate/mapping/MetaAttributable;
      19: ldc           #12                 // String extra-import
      21: invokeinterface #13,  2           // InterfaceMethod org/hibernate/mapping/MetaAttributable.getMetaAttribute:(Ljava/lang/String;)Lorg/hibernate/mapping/MetaAttribute;
      26: astore_1
      27: aload_1
      28: ifnull        74
      31: aload_1
      32: invokevirtual #14                 // Method org/hibernate/mapping/MetaAttribute.getValues:()Ljava/util/List;
      35: invokeinterface #15,  1           // InterfaceMethod java/util/List.iterator:()Ljava/util/Iterator;
      40: astore_2
      41: aload_2
      42: invokeinterface #16,  1           // InterfaceMethod java/util/Iterator.hasNext:()Z
      47: ifeq          74
      50: aload_2
      51: invokeinterface #17,  1           // InterfaceMethod java/util/Iterator.next:()Ljava/lang/Object;
      56: checkcast     #18                 // class java/lang/String
      59: astore_3
      60: aload_0
      61: getfield      #11                 // Field importContext:Lorg/hibernate/tool/hbm2x/pojo/ImportContext;
      64: aload_3
      65: invokeinterface #19,  2           // InterfaceMethod org/hibernate/tool/hbm2x/pojo/ImportContext.importType:(Ljava/lang/String;)Ljava/lang/String;
      70: pop
      71: goto          41
      74: return

  protected java.lang.String getPackageDeclaration(java.lang.String);
    Code:
       0: aload_1
       1: ifnull        39
       4: aload_1
       5: invokevirtual #20                 // Method java/lang/String.trim:()Ljava/lang/String;
       8: invokevirtual #21                 // Method java/lang/String.length:()I
      11: ifeq          39
      14: new           #22                 // class java/lang/StringBuffer
      17: dup
      18: invokespecial #23                 // Method java/lang/StringBuffer."<init>":()V
      21: ldc           #24                 // String package
      23: invokevirtual #25                 // Method java/lang/StringBuffer.append:(Ljava/lang/String;)Ljava/lang/StringBuffer;
      26: aload_1
      27: invokevirtual #25                 // Method java/lang/StringBuffer.append:(Ljava/lang/String;)Ljava/lang/StringBuffer;
      30: ldc           #26                 // String ;
      32: invokevirtual #25                 // Method java/lang/StringBuffer.append:(Ljava/lang/String;)Ljava/lang/StringBuffer;
      35: invokevirtual #27                 // Method java/lang/StringBuffer.toString:()Ljava/lang/String;
      38: areturn
      39: ldc           #28                 // String // default package
      41: areturn

  public java.lang.String getPackageDeclaration();
    Code:
       0: aload_0
       1: invokevirtual #9                  // Method getPackageName:()Ljava/lang/String;
       4: astore_1
       5: aload_0
       6: aload_1
       7: invokevirtual #29                 // Method getPackageDeclaration:(Ljava/lang/String;)Ljava/lang/String;
      10: areturn

  public java.lang.String getPackageName();
    Code:
       0: aload_0
       1: invokevirtual #30                 // Method getGeneratedClassName:()Ljava/lang/String;
       4: astore_1
       5: aload_1
       6: invokevirtual #20                 // Method java/lang/String.trim:()Ljava/lang/String;
       9: invokestatic  #31                 // Method org/hibernate/util/StringHelper.qualifier:(Ljava/lang/String;)Ljava/lang/String;
      12: areturn

  public java.lang.String getShortName();
    Code:
       0: aload_0
       1: aload_0
       2: invokevirtual #32                 // Method getMappedClassName:()Ljava/lang/String;
       5: invokestatic  #33                 // Method org/hibernate/util/StringHelper.unqualify:(Ljava/lang/String;)Ljava/lang/String;
       8: invokevirtual #34                 // Method qualifyInnerClass:(Ljava/lang/String;)Ljava/lang/String;
      11: areturn

  public java.lang.String getQualifiedDeclarationName();
    Code:
       0: aload_0
       1: aload_0
       2: invokevirtual #30                 // Method getGeneratedClassName:()Ljava/lang/String;
       5: invokevirtual #34                 // Method qualifyInnerClass:(Ljava/lang/String;)Ljava/lang/String;
       8: astore_1
       9: aload_0
      10: invokevirtual #32                 // Method getMappedClassName:()Ljava/lang/String;
      13: invokestatic  #31                 // Method org/hibernate/util/StringHelper.qualifier:(Ljava/lang/String;)Ljava/lang/String;
      16: astore_2
      17: ldc           #35                 // String
      19: aload_2
      20: invokevirtual #36                 // Method java/lang/String.equals:(Ljava/lang/Object;)Z
      23: ifeq          50
      26: new           #22                 // class java/lang/StringBuffer
      29: dup
      30: invokespecial #23                 // Method java/lang/StringBuffer."<init>":()V
      33: aload_2
      34: invokevirtual #25                 // Method java/lang/StringBuffer.append:(Ljava/lang/String;)Ljava/lang/StringBuffer;
      37: ldc           #37                 // String .
      39: invokevirtual #25                 // Method java/lang/StringBuffer.append:(Ljava/lang/String;)Ljava/lang/StringBuffer;
      42: aload_1
      43: invokevirtual #25                 // Method java/lang/StringBuffer.append:(Ljava/lang/String;)Ljava/lang/StringBuffer;
      46: invokevirtual #27                 // Method java/lang/StringBuffer.toString:()Ljava/lang/String;
      49: areturn
      50: aload_1
      51: areturn

  public java.lang.String getDeclarationName();
    Code:
       0: aload_0
       1: aload_0
       2: invokevirtual #30                 // Method getGeneratedClassName:()Ljava/lang/String;
       5: invokestatic  #33                 // Method org/hibernate/util/StringHelper.unqualify:(Ljava/lang/String;)Ljava/lang/String;
       8: invokevirtual #34                 // Method qualifyInnerClass:(Ljava/lang/String;)Ljava/lang/String;
      11: areturn

  protected java.lang.String getGeneratedClassName();
    Code:
       0: aload_0
       1: ldc           #38                 // String generated-class
       3: invokevirtual #39                 // Method getMetaAsString:(Ljava/lang/String;)Ljava/lang/String;
       6: invokevirtual #20                 // Method java/lang/String.trim:()Ljava/lang/String;
       9: astore_1
      10: aload_1
      11: invokestatic  #40                 // Method org/hibernate/util/StringHelper.isEmpty:(Ljava/lang/String;)Z
      14: ifeq          22
      17: aload_0
      18: invokevirtual #32                 // Method getMappedClassName:()Ljava/lang/String;
      21: astore_1
      22: aload_1
      23: ifnonnull     29
      26: ldc           #35                 // String
      28: areturn
      29: aload_1
      30: areturn

  protected java.lang.String qualifyInnerClass(java.lang.String);
    Code:
       0: aload_1
       1: bipush        36
       3: bipush        46
       5: invokevirtual #41                 // Method java/lang/String.replace:(CC)Ljava/lang/String;
       8: areturn

  protected abstract java.lang.String getMappedClassName();

  public java.lang.String getMetaAsString(java.lang.String);
    Code:
       0: aload_0
       1: getfield      #2                  // Field meta:Lorg/hibernate/mapping/MetaAttributable;
       4: aload_1
       5: invokeinterface #13,  2           // InterfaceMethod org/hibernate/mapping/MetaAttributable.getMetaAttribute:(Ljava/lang/String;)Lorg/hibernate/mapping/MetaAttribute;
      10: astore_2
      11: aload_2
      12: invokestatic  #42                 // Method org/hibernate/tool/hbm2x/MetaAttributeHelper.getMetaAsString:(Lorg/hibernate/mapping/MetaAttribute;)Ljava/lang/String;
      15: areturn

  public boolean hasMetaAttribute(java.lang.String);
    Code:
       0: aload_0
       1: getfield      #2                  // Field meta:Lorg/hibernate/mapping/MetaAttributable;
       4: aload_1
       5: invokeinterface #13,  2           // InterfaceMethod org/hibernate/mapping/MetaAttributable.getMetaAttribute:(Ljava/lang/String;)Lorg/hibernate/mapping/MetaAttribute;
      10: ifnull        17
      13: iconst_1
      14: goto          18
      17: iconst_0
      18: ireturn

  public java.lang.String getMetaAsString(java.lang.String, java.lang.String);
    Code:
       0: aload_0
       1: getfield      #2                  // Field meta:Lorg/hibernate/mapping/MetaAttributable;
       4: aload_1
       5: invokeinterface #13,  2           // InterfaceMethod org/hibernate/mapping/MetaAttributable.getMetaAttribute:(Ljava/lang/String;)Lorg/hibernate/mapping/MetaAttribute;
      10: aload_2
      11: invokestatic  #43                 // Method org/hibernate/tool/hbm2x/MetaAttributeHelper.getMetaAsString:(Lorg/hibernate/mapping/MetaAttribute;Ljava/lang/String;)Ljava/lang/String;
      14: areturn

  public boolean getMetaAsBool(java.lang.String);
    Code:
       0: aload_0
       1: aload_1
       2: iconst_0
       3: invokevirtual #44                 // Method getMetaAsBool:(Ljava/lang/String;Z)Z
       6: ireturn

  public boolean getMetaAsBool(java.lang.String, boolean);
    Code:
       0: aload_0
       1: getfield      #2                  // Field meta:Lorg/hibernate/mapping/MetaAttributable;
       4: aload_1
       5: invokeinterface #13,  2           // InterfaceMethod org/hibernate/mapping/MetaAttributable.getMetaAttribute:(Ljava/lang/String;)Lorg/hibernate/mapping/MetaAttribute;
      10: iload_2
      11: invokestatic  #45                 // Method org/hibernate/tool/hbm2x/MetaAttributeHelper.getMetaAsBool:(Lorg/hibernate/mapping/MetaAttribute;Z)Z
      14: ireturn

  public java.lang.String getClassJavaDoc(java.lang.String, int);
    Code:
       0: aload_0
       1: getfield      #2                  // Field meta:Lorg/hibernate/mapping/MetaAttributable;
       4: ldc           #46                 // String class-description
       6: invokeinterface #13,  2           // InterfaceMethod org/hibernate/mapping/MetaAttributable.getMetaAttribute:(Ljava/lang/String;)Lorg/hibernate/mapping/MetaAttribute;
      11: astore_3
      12: aload_3
      13: ifnonnull     26
      16: aload_0
      17: getfield      #3                  // Field c2j:Lorg/hibernate/tool/hbm2x/Cfg2JavaTool;
      20: aload_1
      21: iload_2
      22: invokevirtual #47                 // Method org/hibernate/tool/hbm2x/Cfg2JavaTool.toJavaDoc:(Ljava/lang/String;I)Ljava/lang/String;
      25: areturn
      26: aload_0
      27: getfield      #3                  // Field c2j:Lorg/hibernate/tool/hbm2x/Cfg2JavaTool;
      30: aload_0
      31: ldc           #46                 // String class-description
      33: invokevirtual #39                 // Method getMetaAsString:(Ljava/lang/String;)Ljava/lang/String;
      36: iload_2
      37: invokevirtual #47                 // Method org/hibernate/tool/hbm2x/Cfg2JavaTool.toJavaDoc:(Ljava/lang/String;I)Ljava/lang/String;
      40: areturn

  public java.lang.String getClassModifiers();
    Code:
       0: aconst_null
       1: astore_1
       2: aload_0
       3: getfield      #2                  // Field meta:Lorg/hibernate/mapping/MetaAttributable;
       6: ldc           #48                 // String scope-class
       8: invokeinterface #13,  2           // InterfaceMethod org/hibernate/mapping/MetaAttributable.getMetaAttribute:(Ljava/lang/String;)Lorg/hibernate/mapping/MetaAttribute;
      13: ifnull        26
      16: aload_0
      17: ldc           #48                 // String scope-class
      19: invokevirtual #39                 // Method getMetaAsString:(Ljava/lang/String;)Ljava/lang/String;
      22: invokevirtual #20                 // Method java/lang/String.trim:()Ljava/lang/String;
      25: astore_1
      26: aload_0
      27: getfield      #2                  // Field meta:Lorg/hibernate/mapping/MetaAttributable;
      30: ldc           #49                 // String class-modifier
      32: invokeinterface #13,  2           // InterfaceMethod org/hibernate/mapping/MetaAttributable.getMetaAttribute:(Ljava/lang/String;)Lorg/hibernate/mapping/MetaAttribute;
      37: ifnull        50
      40: aload_0
      41: ldc           #49                 // String class-modifier
      43: invokevirtual #39                 // Method getMetaAsString:(Ljava/lang/String;)Ljava/lang/String;
      46: invokevirtual #20                 // Method java/lang/String.trim:()Ljava/lang/String;
      49: astore_1
      50: aload_1
      51: ifnonnull     59
      54: ldc           #50                 // String public
      56: goto          60
      59: aload_1
      60: areturn

  public java.lang.String getDeclarationType();
    Code:
       0: aload_0
       1: invokevirtual #51                 // Method isInterface:()Z
       4: istore_1
       5: iload_1
       6: ifeq          12
       9: ldc           #52                 // String interface
      11: areturn
      12: ldc           #53                 // String class
      14: areturn

  public boolean isInterface();
    Code:
       0: aload_0
       1: ldc           #52                 // String interface
       3: invokevirtual #54                 // Method getMetaAsBool:(Ljava/lang/String;)Z
       6: ireturn

  public java.lang.String getExtendsDeclaration();
    Code:
       0: aload_0
       1: invokevirtual #55                 // Method getExtends:()Ljava/lang/String;
       4: astore_1
       5: aload_1
       6: ifnull        19
       9: aload_1
      10: invokevirtual #20                 // Method java/lang/String.trim:()Ljava/lang/String;
      13: invokevirtual #21                 // Method java/lang/String.length:()I
      16: ifne          22
      19: ldc           #35                 // String
      21: areturn
      22: new           #22                 // class java/lang/StringBuffer
      25: dup
      26: invokespecial #23                 // Method java/lang/StringBuffer."<init>":()V
      29: ldc           #56                 // String extends
      31: invokevirtual #25                 // Method java/lang/StringBuffer.append:(Ljava/lang/String;)Ljava/lang/StringBuffer;
      34: aload_1
      35: invokevirtual #25                 // Method java/lang/StringBuffer.append:(Ljava/lang/String;)Ljava/lang/StringBuffer;
      38: invokevirtual #27                 // Method java/lang/StringBuffer.toString:()Ljava/lang/String;
      41: areturn

  public java.lang.String getImplementsDeclaration();
    Code:
       0: aload_0
       1: invokevirtual #57                 // Method getImplements:()Ljava/lang/String;
       4: astore_1
       5: aload_1
       6: ifnull        19
       9: aload_1
      10: invokevirtual #20                 // Method java/lang/String.trim:()Ljava/lang/String;
      13: invokevirtual #21                 // Method java/lang/String.length:()I
      16: ifne          22
      19: ldc           #35                 // String
      21: areturn
      22: new           #22                 // class java/lang/StringBuffer
      25: dup
      26: invokespecial #23                 // Method java/lang/StringBuffer."<init>":()V
      29: ldc           #58                 // String implements
      31: invokevirtual #25                 // Method java/lang/StringBuffer.append:(Ljava/lang/String;)Ljava/lang/StringBuffer;
      34: aload_1
      35: invokevirtual #25                 // Method java/lang/StringBuffer.append:(Ljava/lang/String;)Ljava/lang/StringBuffer;
      38: invokevirtual #27                 // Method java/lang/StringBuffer.toString:()Ljava/lang/String;
      41: areturn

  public java.lang.String generateEquals(java.lang.String, java.lang.String, boolean);
    Code:
       0: aload_0
       1: invokevirtual #59                 // Method getEqualsHashCodePropertiesIterator:()Ljava/util/Iterator;
       4: astore        4
       6: aload_0
       7: aload_1
       8: aload_2
       9: aload         4
      11: iload_3
      12: invokevirtual #60                 // Method generateEquals:(Ljava/lang/String;Ljava/lang/String;Ljava/util/Iterator;Z)Ljava/lang/String;
      15: areturn

  public abstract java.util.Iterator getAllPropertiesIterator();

  protected java.lang.String generateEquals(java.lang.String, java.lang.String, java.util.Iterator, boolean);
    Code:
       0: new           #22                 // class java/lang/StringBuffer
       3: dup
       4: invokespecial #23                 // Method java/lang/StringBuffer."<init>":()V
       7: astore        5
       9: aload_3
      10: invokeinterface #16,  1           // InterfaceMethod java/util/Iterator.hasNext:()Z
      15: ifeq          140
      18: aload_3
      19: invokeinterface #17,  1           // InterfaceMethod java/util/Iterator.next:()Ljava/lang/Object;
      24: checkcast     #61                 // class org/hibernate/mapping/Property
      27: astore        6
      29: aload         5
      31: invokevirtual #62                 // Method java/lang/StringBuffer.length:()I
      34: ifle          45
      37: aload         5
      39: ldc           #63                 // String \n &&
      41: invokevirtual #25                 // Method java/lang/StringBuffer.append:(Ljava/lang/String;)Ljava/lang/StringBuffer;
      44: pop
      45: aload_0
      46: getfield      #3                  // Field c2j:Lorg/hibernate/tool/hbm2x/Cfg2JavaTool;
      49: aload         6
      51: iload         4
      53: aload_0
      54: invokevirtual #64                 // Method org/hibernate/tool/hbm2x/Cfg2JavaTool.getJavaTypeName:(Lorg/hibernate/mapping/Property;ZLorg/hibernate/tool/hbm2x/pojo/ImportContext;)Ljava/lang/String;
      57: astore        7
      59: aload         5
      61: aload_0
      62: aload         7
      64: new           #22                 // class java/lang/StringBuffer
      67: dup
      68: invokespecial #23                 // Method java/lang/StringBuffer."<init>":()V
      71: aload_1
      72: invokevirtual #25                 // Method java/lang/StringBuffer.append:(Ljava/lang/String;)Ljava/lang/StringBuffer;
      75: ldc           #37                 // String .
      77: invokevirtual #25                 // Method java/lang/StringBuffer.append:(Ljava/lang/String;)Ljava/lang/StringBuffer;
      80: aload_0
      81: aload         6
      83: invokevirtual #65                 // Method getGetterSignature:(Lorg/hibernate/mapping/Property;)Ljava/lang/String;
      86: invokevirtual #25                 // Method java/lang/StringBuffer.append:(Ljava/lang/String;)Ljava/lang/StringBuffer;
      89: ldc           #66                 // String ()
      91: invokevirtual #25                 // Method java/lang/StringBuffer.append:(Ljava/lang/String;)Ljava/lang/StringBuffer;
      94: invokevirtual #27                 // Method java/lang/StringBuffer.toString:()Ljava/lang/String;
      97: new           #22                 // class java/lang/StringBuffer
     100: dup
     101: invokespecial #23                 // Method java/lang/StringBuffer."<init>":()V
     104: aload_2
     105: invokevirtual #25                 // Method java/lang/StringBuffer.append:(Ljava/lang/String;)Ljava/lang/StringBuffer;
     108: ldc           #37                 // String .
     110: invokevirtual #25                 // Method java/lang/StringBuffer.append:(Ljava/lang/String;)Ljava/lang/StringBuffer;
     113: aload_0
     114: aload         6
     116: invokevirtual #65                 // Method getGetterSignature:(Lorg/hibernate/mapping/Property;)Ljava/lang/String;
     119: invokevirtual #25                 // Method java/lang/StringBuffer.append:(Ljava/lang/String;)Ljava/lang/StringBuffer;
     122: ldc           #66                 // String ()
     124: invokevirtual #25                 // Method java/lang/StringBuffer.append:(Ljava/lang/String;)Ljava/lang/StringBuffer;
     127: invokevirtual #27                 // Method java/lang/StringBuffer.toString:()Ljava/lang/String;
     130: invokespecial #67                 // Method internalgenerateEquals:(Ljava/lang/String;Ljava/lang/String;Ljava/lang/String;)Ljava/lang/String;
     133: invokevirtual #25                 // Method java/lang/StringBuffer.append:(Ljava/lang/String;)Ljava/lang/StringBuffer;
     136: pop
     137: goto          9
     140: aload         5
     142: invokevirtual #62                 // Method java/lang/StringBuffer.length:()I
     145: ifne          151
     148: ldc           #68                 // String false
     150: areturn
     151: aload         5
     153: invokevirtual #27                 // Method java/lang/StringBuffer.toString:()Ljava/lang/String;
     156: areturn

  private boolean usePropertyInEquals(org.hibernate.mapping.Property);
    Code:
       0: aload_0
       1: getfield      #3                  // Field c2j:Lorg/hibernate/tool/hbm2x/Cfg2JavaTool;
       4: aload_1
       5: ldc           #69                 // String use-in-equals
       7: invokevirtual #70                 // Method org/hibernate/tool/hbm2x/Cfg2JavaTool.hasMetaAttribute:(Lorg/hibernate/mapping/MetaAttributable;Ljava/lang/String;)Z
      10: istore_2
      11: aload_0
      12: getfield      #3                  // Field c2j:Lorg/hibernate/tool/hbm2x/Cfg2JavaTool;
      15: aload_1
      16: ldc           #69                 // String use-in-equals
      18: invokevirtual #71                 // Method org/hibernate/tool/hbm2x/Cfg2JavaTool.getMetaAsBool:(Lorg/hibernate/mapping/MetaAttributable;Ljava/lang/String;)Z
      21: istore_3
      22: aload_1
      23: invokevirtual #72                 // Method org/hibernate/mapping/Property.isNaturalIdentifier:()Z
      26: ifeq          41
      29: iload_2
      30: ifeq          39
      33: iload_3
      34: ifne          39
      37: iconst_0
      38: ireturn
      39: iconst_1
      40: ireturn
      41: iload_3
      42: ireturn

  private boolean useCompareTo(java.lang.String);
    Code:
       0: ldc           #73                 // String java.math.BigDecimal
       2: aload_1
       3: invokevirtual #36                 // Method java/lang/String.equals:(Ljava/lang/Object;)Z
       6: ifeq          11
       9: iconst_1
      10: ireturn
      11: iconst_0
      12: ireturn

  private java.lang.String internalgenerateEquals(java.lang.String, java.lang.String, java.lang.String);
    Code:
       0: aload_0
       1: getfield      #3                  // Field c2j:Lorg/hibernate/tool/hbm2x/Cfg2JavaTool;
       4: aload_1
       5: invokevirtual #74                 // Method org/hibernate/tool/hbm2x/Cfg2JavaTool.isPrimitive:(Ljava/lang/String;)Z
       8: ifeq          45
      11: new           #22                 // class java/lang/StringBuffer
      14: dup
      15: invokespecial #23                 // Method java/lang/StringBuffer."<init>":()V
      18: ldc           #75                 // String (
      20: invokevirtual #25                 // Method java/lang/StringBuffer.append:(Ljava/lang/String;)Ljava/lang/StringBuffer;
      23: aload_2
      24: invokevirtual #25                 // Method java/lang/StringBuffer.append:(Ljava/lang/String;)Ljava/lang/StringBuffer;
      27: ldc           #76                 // String ==
      29: invokevirtual #25                 // Method java/lang/StringBuffer.append:(Ljava/lang/String;)Ljava/lang/StringBuffer;
      32: aload_3
      33: invokevirtual #25                 // Method java/lang/StringBuffer.append:(Ljava/lang/String;)Ljava/lang/StringBuffer;
      36: ldc           #77                 // String )
      38: invokevirtual #25                 // Method java/lang/StringBuffer.append:(Ljava/lang/String;)Ljava/lang/StringBuffer;
      41: invokevirtual #27                 // Method java/lang/StringBuffer.toString:()Ljava/lang/String;
      44: areturn
      45: aload_0
      46: aload_1
      47: invokespecial #78                 // Method useCompareTo:(Ljava/lang/String;)Z
      50: ifeq          123
      53: new           #22                 // class java/lang/StringBuffer
      56: dup
      57: invokespecial #23                 // Method java/lang/StringBuffer."<init>":()V
      60: ldc           #79                 // String ( (
      62: invokevirtual #25                 // Method java/lang/StringBuffer.append:(Ljava/lang/String;)Ljava/lang/StringBuffer;
      65: aload_2
      66: invokevirtual #25                 // Method java/lang/StringBuffer.append:(Ljava/lang/String;)Ljava/lang/StringBuffer;
      69: ldc           #76                 // String ==
      71: invokevirtual #25                 // Method java/lang/StringBuffer.append:(Ljava/lang/String;)Ljava/lang/StringBuffer;
      74: aload_3
      75: invokevirtual #25                 // Method java/lang/StringBuffer.append:(Ljava/lang/String;)Ljava/lang/StringBuffer;
      78: ldc           #80                 // String ) || (
      80: invokevirtual #25                 // Method java/lang/StringBuffer.append:(Ljava/lang/String;)Ljava/lang/StringBuffer;
      83: aload_2
      84: invokevirtual #25                 // Method java/lang/StringBuffer.append:(Ljava/lang/String;)Ljava/lang/StringBuffer;
      87: ldc           #81                 // String !=null &&
      89: invokevirtual #25                 // Method java/lang/StringBuffer.append:(Ljava/lang/String;)Ljava/lang/StringBuffer;
      92: aload_3
      93: invokevirtual #25                 // Method java/lang/StringBuffer.append:(Ljava/lang/String;)Ljava/lang/StringBuffer;
      96: ldc           #81                 // String !=null &&
      98: invokevirtual #25                 // Method java/lang/StringBuffer.append:(Ljava/lang/String;)Ljava/lang/StringBuffer;
     101: aload_2
     102: invokevirtual #25                 // Method java/lang/StringBuffer.append:(Ljava/lang/String;)Ljava/lang/StringBuffer;
     105: ldc           #82                 // String .compareTo(
     107: invokevirtual #25                 // Method java/lang/StringBuffer.append:(Ljava/lang/String;)Ljava/lang/StringBuffer;
     110: aload_3
     111: invokevirtual #25                 // Method java/lang/StringBuffer.append:(Ljava/lang/String;)Ljava/lang/StringBuffer;
     114: ldc           #83                 // String )==0 ) )
     116: invokevirtual #25                 // Method java/lang/StringBuffer.append:(Ljava/lang/String;)Ljava/lang/StringBuffer;
     119: invokevirtual #27                 // Method java/lang/StringBuffer.toString:()Ljava/lang/String;
     122: areturn
     123: aload_1
     124: ldc           #84                 // String []
     126: invokevirtual #85                 // Method java/lang/String.endsWith:(Ljava/lang/String;)Z
     129: ifeq          216
     132: new           #22                 // class java/lang/StringBuffer
     135: dup
     136: invokespecial #23                 // Method java/lang/StringBuffer."<init>":()V
     139: ldc           #79                 // String ( (
     141: invokevirtual #25                 // Method java/lang/StringBuffer.append:(Ljava/lang/String;)Ljava/lang/StringBuffer;
     144: aload_2
     145: invokevirtual #25                 // Method java/lang/StringBuffer.append:(Ljava/lang/String;)Ljava/lang/StringBuffer;
     148: ldc           #76                 // String ==
     150: invokevirtual #25                 // Method java/lang/StringBuffer.append:(Ljava/lang/String;)Ljava/lang/StringBuffer;
     153: aload_3
     154: invokevirtual #25                 // Method java/lang/StringBuffer.append:(Ljava/lang/String;)Ljava/lang/StringBuffer;
     157: ldc           #80                 // String ) || (
     159: invokevirtual #25                 // Method java/lang/StringBuffer.append:(Ljava/lang/String;)Ljava/lang/StringBuffer;
     162: aload_2
     163: invokevirtual #25                 // Method java/lang/StringBuffer.append:(Ljava/lang/String;)Ljava/lang/StringBuffer;
     166: ldc           #81                 // String !=null &&
     168: invokevirtual #25                 // Method java/lang/StringBuffer.append:(Ljava/lang/String;)Ljava/lang/StringBuffer;
     171: aload_3
     172: invokevirtual #25                 // Method java/lang/StringBuffer.append:(Ljava/lang/String;)Ljava/lang/StringBuffer;
     175: ldc           #81                 // String !=null &&
     177: invokevirtual #25                 // Method java/lang/StringBuffer.append:(Ljava/lang/String;)Ljava/lang/StringBuffer;
     180: aload_0
     181: ldc           #86                 // String java.util.Arrays
     183: invokevirtual #87                 // Method importType:(Ljava/lang/String;)Ljava/lang/String;
     186: invokevirtual #25                 // Method java/lang/StringBuffer.append:(Ljava/lang/String;)Ljava/lang/StringBuffer;
     189: ldc           #88                 // String .equals(
     191: invokevirtual #25                 // Method java/lang/StringBuffer.append:(Ljava/lang/String;)Ljava/lang/StringBuffer;
     194: aload_2
     195: invokevirtual #25                 // Method java/lang/StringBuffer.append:(Ljava/lang/String;)Ljava/lang/StringBuffer;
     198: ldc           #89                 // String ,
     200: invokevirtual #25                 // Method java/lang/StringBuffer.append:(Ljava/lang/String;)Ljava/lang/StringBuffer;
     203: aload_3
     204: invokevirtual #25                 // Method java/lang/StringBuffer.append:(Ljava/lang/String;)Ljava/lang/StringBuffer;
     207: ldc           #90                 // String ) ) )
     209: invokevirtual #25                 // Method java/lang/StringBuffer.append:(Ljava/lang/String;)Ljava/lang/StringBuffer;
     212: invokevirtual #27                 // Method java/lang/StringBuffer.toString:()Ljava/lang/String;
     215: areturn
     216: new           #22                 // class java/lang/StringBuffer
     219: dup
     220: invokespecial #23                 // Method java/lang/StringBuffer."<init>":()V
     223: ldc           #79                 // String ( (
     225: invokevirtual #25                 // Method java/lang/StringBuffer.append:(Ljava/lang/String;)Ljava/lang/StringBuffer;
     228: aload_2
     229: invokevirtual #25                 // Method java/lang/StringBuffer.append:(Ljava/lang/String;)Ljava/lang/StringBuffer;
     232: ldc           #76                 // String ==
     234: invokevirtual #25                 // Method java/lang/StringBuffer.append:(Ljava/lang/String;)Ljava/lang/StringBuffer;
     237: aload_3
     238: invokevirtual #25                 // Method java/lang/StringBuffer.append:(Ljava/lang/String;)Ljava/lang/StringBuffer;
     241: ldc           #80                 // String ) || (
     243: invokevirtual #25                 // Method java/lang/StringBuffer.append:(Ljava/lang/String;)Ljava/lang/StringBuffer;
     246: aload_2
     247: invokevirtual #25                 // Method java/lang/StringBuffer.append:(Ljava/lang/String;)Ljava/lang/StringBuffer;
     250: ldc           #81                 // String !=null &&
     252: invokevirtual #25                 // Method java/lang/StringBuffer.append:(Ljava/lang/String;)Ljava/lang/StringBuffer;
     255: aload_3
     256: invokevirtual #25                 // Method java/lang/StringBuffer.append:(Ljava/lang/String;)Ljava/lang/StringBuffer;
     259: ldc           #81                 // String !=null &&
     261: invokevirtual #25                 // Method java/lang/StringBuffer.append:(Ljava/lang/String;)Ljava/lang/StringBuffer;
     264: aload_2
     265: invokevirtual #25                 // Method java/lang/StringBuffer.append:(Ljava/lang/String;)Ljava/lang/StringBuffer;
     268: ldc           #88                 // String .equals(
     270: invokevirtual #25                 // Method java/lang/StringBuffer.append:(Ljava/lang/String;)Ljava/lang/StringBuffer;
     273: aload_3
     274: invokevirtual #25                 // Method java/lang/StringBuffer.append:(Ljava/lang/String;)Ljava/lang/StringBuffer;
     277: ldc           #90                 // String ) ) )
     279: invokevirtual #25                 // Method java/lang/StringBuffer.append:(Ljava/lang/String;)Ljava/lang/StringBuffer;
     282: invokevirtual #27                 // Method java/lang/StringBuffer.toString:()Ljava/lang/String;
     285: areturn

  public java.lang.String getExtraClassCode();
    Code:
       0: aload_0
       1: ldc           #91                 // String class-code
       3: ldc           #92                 // String \n
       5: invokevirtual #93                 // Method getMetaAsString:(Ljava/lang/String;Ljava/lang/String;)Ljava/lang/String;
       8: areturn

  private boolean needsEqualsHashCode(java.util.Iterator);
    Code:
       0: aload_1
       1: invokeinterface #16,  1           // InterfaceMethod java/util/Iterator.hasNext:()Z
       6: ifeq          32
       9: aload_1
      10: invokeinterface #17,  1           // InterfaceMethod java/util/Iterator.next:()Ljava/lang/Object;
      15: checkcast     #61                 // class org/hibernate/mapping/Property
      18: astore_2
      19: aload_0
      20: aload_2
      21: invokespecial #94                 // Method usePropertyInEquals:(Lorg/hibernate/mapping/Property;)Z
      24: ifeq          29
      27: iconst_1
      28: ireturn
      29: goto          0
      32: iconst_0
      33: ireturn

  public boolean needsEqualsHashCode();
    Code:
       0: aload_0
       1: invokevirtual #95                 // Method getAllPropertiesIterator:()Ljava/util/Iterator;
       4: astore_1
       5: aload_0
       6: aload_1
       7: invokespecial #96                 // Method needsEqualsHashCode:(Ljava/util/Iterator;)Z
      10: ireturn

  public abstract java.lang.String getExtends();

  public abstract java.lang.String getImplements();

  public java.lang.String importType(java.lang.String);
    Code:
       0: aload_0
       1: getfield      #11                 // Field importContext:Lorg/hibernate/tool/hbm2x/pojo/ImportContext;
       4: aload_1
       5: invokeinterface #19,  2           // InterfaceMethod org/hibernate/tool/hbm2x/pojo/ImportContext.importType:(Ljava/lang/String;)Ljava/lang/String;
      10: areturn

  public java.lang.String generateImports();
    Code:
       0: aload_0
       1: getfield      #11                 // Field importContext:Lorg/hibernate/tool/hbm2x/pojo/ImportContext;
       4: invokeinterface #97,  1           // InterfaceMethod org/hibernate/tool/hbm2x/pojo/ImportContext.generateImports:()Ljava/lang/String;
       9: areturn

  public java.lang.String staticImport(java.lang.String, java.lang.String);
    Code:
       0: aload_0
       1: getfield      #11                 // Field importContext:Lorg/hibernate/tool/hbm2x/pojo/ImportContext;
       4: aload_1
       5: aload_2
       6: invokeinterface #98,  3           // InterfaceMethod org/hibernate/tool/hbm2x/pojo/ImportContext.staticImport:(Ljava/lang/String;Ljava/lang/String;)Ljava/lang/String;
      11: areturn

  public java.lang.String generateBasicAnnotation(org.hibernate.mapping.Property);
    Code:
       0: new           #22                 // class java/lang/StringBuffer
       3: dup
       4: ldc           #99                 // String
       6: invokespecial #100                // Method java/lang/StringBuffer."<init>":(Ljava/lang/String;)V
       9: astore_2
      10: aload_1
      11: invokevirtual #101                // Method org/hibernate/mapping/Property.getValue:()Lorg/hibernate/mapping/Value;
      14: instanceof    #102                // class org/hibernate/mapping/SimpleValue
      17: ifeq          139
      20: aload_0
      21: invokevirtual #103                // Method hasVersionProperty:()Z
      24: ifeq          44
      27: aload_1
      28: aload_0
      29: invokevirtual #104                // Method getVersionProperty:()Lorg/hibernate/mapping/Property;
      32: invokevirtual #105                // Method java/lang/Object.equals:(Ljava/lang/Object;)Z
      35: ifeq          44
      38: aload_0
      39: aload_2
      40: invokespecial #106                // Method buildVersionAnnotation:(Ljava/lang/StringBuffer;)Ljava/lang/StringBuffer;
      43: pop
      44: aload_1
      45: invokevirtual #101                // Method org/hibernate/mapping/Property.getValue:()Lorg/hibernate/mapping/Value;
      48: checkcast     #102                // class org/hibernate/mapping/SimpleValue
      51: invokevirtual #107                // Method org/hibernate/mapping/SimpleValue.getTypeName:()Ljava/lang/String;
      54: astore_3
      55: ldc           #108                // String date
      57: aload_3
      58: invokevirtual #36                 // Method java/lang/String.equals:(Ljava/lang/Object;)Z
      61: ifne          73
      64: ldc           #109                // String java.sql.Date
      66: aload_3
      67: invokevirtual #36                 // Method java/lang/String.equals:(Ljava/lang/Object;)Z
      70: ifeq          84
      73: aload_0
      74: aload_2
      75: ldc           #110                // String DATE
      77: invokespecial #111                // Method buildTemporalAnnotation:(Ljava/lang/StringBuffer;Ljava/lang/String;)Ljava/lang/StringBuffer;
      80: pop
      81: goto          139
      84: ldc           #112                // String timestamp
      86: aload_3
      87: invokevirtual #36                 // Method java/lang/String.equals:(Ljava/lang/Object;)Z
      90: ifne          102
      93: ldc           #113                // String java.sql.Timestamp
      95: aload_3
      96: invokevirtual #36                 // Method java/lang/String.equals:(Ljava/lang/Object;)Z
      99: ifeq          113
     102: aload_0
     103: aload_2
     104: ldc           #114                // String TIMESTAMP
     106: invokespecial #111                // Method buildTemporalAnnotation:(Ljava/lang/StringBuffer;Ljava/lang/String;)Ljava/lang/StringBuffer;
     109: pop
     110: goto          139
     113: ldc           #115                // String time
     115: aload_3
     116: invokevirtual #36                 // Method java/lang/String.equals:(Ljava/lang/Object;)Z
     119: ifne          131
     122: ldc           #116                // String java.sql.Time
     124: aload_3
     125: invokevirtual #36                 // Method java/lang/String.equals:(Ljava/lang/Object;)Z
     128: ifeq          139
     131: aload_0
     132: aload_2
     133: ldc           #117                // String TIME
     135: invokespecial #111                // Method buildTemporalAnnotation:(Ljava/lang/StringBuffer;Ljava/lang/String;)Ljava/lang/StringBuffer;
     138: pop
     139: aload_2
     140: invokevirtual #27                 // Method java/lang/StringBuffer.toString:()Ljava/lang/String;
     143: areturn

  private java.lang.StringBuffer buildTemporalAnnotation(java.lang.StringBuffer, java.lang.String);
    Code:
       0: aload_0
       1: ldc           #118                // String javax.persistence.Temporal
       3: invokevirtual #87                 // Method importType:(Ljava/lang/String;)Ljava/lang/String;
       6: astore_3
       7: aload_0
       8: ldc           #119                // String javax.persistence.TemporalType
      10: invokevirtual #87                 // Method importType:(Ljava/lang/String;)Ljava/lang/String;
      13: astore        4
      15: aload_1
      16: new           #22                 // class java/lang/StringBuffer
      19: dup
      20: invokespecial #23                 // Method java/lang/StringBuffer."<init>":()V
      23: ldc           #120                // String @
      25: invokevirtual #25                 // Method java/lang/StringBuffer.append:(Ljava/lang/String;)Ljava/lang/StringBuffer;
      28: aload_3
      29: invokevirtual #25                 // Method java/lang/StringBuffer.append:(Ljava/lang/String;)Ljava/lang/StringBuffer;
      32: ldc           #75                 // String (
      34: invokevirtual #25                 // Method java/lang/StringBuffer.append:(Ljava/lang/String;)Ljava/lang/StringBuffer;
      37: aload         4
      39: invokevirtual #25                 // Method java/lang/StringBuffer.append:(Ljava/lang/String;)Ljava/lang/StringBuffer;
      42: ldc           #37                 // String .
      44: invokevirtual #25                 // Method java/lang/StringBuffer.append:(Ljava/lang/String;)Ljava/lang/StringBuffer;
      47: aload_2
      48: invokevirtual #25                 // Method java/lang/StringBuffer.append:(Ljava/lang/String;)Ljava/lang/StringBuffer;
      51: ldc           #77                 // String )
      53: invokevirtual #25                 // Method java/lang/StringBuffer.append:(Ljava/lang/String;)Ljava/lang/StringBuffer;
      56: invokevirtual #27                 // Method java/lang/StringBuffer.toString:()Ljava/lang/String;
      59: invokevirtual #25                 // Method java/lang/StringBuffer.append:(Ljava/lang/String;)Ljava/lang/StringBuffer;
      62: areturn

  private java.lang.StringBuffer buildVersionAnnotation(java.lang.StringBuffer);
    Code:
       0: aload_0
       1: ldc           #121                // String javax.persistence.Version
       3: invokevirtual #87                 // Method importType:(Ljava/lang/String;)Ljava/lang/String;
       6: astore_2
       7: aload_1
       8: new           #22                 // class java/lang/StringBuffer
      11: dup
      12: invokespecial #23                 // Method java/lang/StringBuffer."<init>":()V
      15: ldc           #120                // String @
      17: invokevirtual #25                 // Method java/lang/StringBuffer.append:(Ljava/lang/String;)Ljava/lang/StringBuffer;
      20: aload_2
      21: invokevirtual #25                 // Method java/lang/StringBuffer.append:(Ljava/lang/String;)Ljava/lang/StringBuffer;
      24: invokevirtual #27                 // Method java/lang/StringBuffer.toString:()Ljava/lang/String;
      27: invokevirtual #25                 // Method java/lang/StringBuffer.append:(Ljava/lang/String;)Ljava/lang/StringBuffer;
      30: areturn

  public java.lang.String generateAnnColumnAnnotation(org.hibernate.mapping.Property);
    Code:
       0: new           #22                 // class java/lang/StringBuffer
       3: dup
       4: ldc           #99                 // String
       6: invokespecial #100                // Method java/lang/StringBuffer."<init>":(Ljava/lang/String;)V
       9: astore_2
      10: aload_1
      11: invokevirtual #122                // Method org/hibernate/mapping/Property.isInsertable:()Z
      14: istore_3
      15: aload_1
      16: invokevirtual #123                // Method org/hibernate/mapping/Property.isUpdateable:()Z
      19: istore        4
      21: aload_1
      22: invokevirtual #124                // Method org/hibernate/mapping/Property.isComposite:()Z
      25: ifeq          107
      28: aload_2
      29: new           #22                 // class java/lang/StringBuffer
      32: dup
      33: invokespecial #23                 // Method java/lang/StringBuffer."<init>":()V
      36: ldc           #120                // String @
      38: invokevirtual #25                 // Method java/lang/StringBuffer.append:(Ljava/lang/String;)Ljava/lang/StringBuffer;
      41: aload_0
      42: ldc           #125                // String javax.persistence.AttributeOverrides
      44: invokevirtual #87                 // Method importType:(Ljava/lang/String;)Ljava/lang/String;
      47: invokevirtual #25                 // Method java/lang/StringBuffer.append:(Ljava/lang/String;)Ljava/lang/StringBuffer;
      50: ldc           #126                // String ( {
      52: invokevirtual #25                 // Method java/lang/StringBuffer.append:(Ljava/lang/String;)Ljava/lang/StringBuffer;
      55: invokevirtual #27                 // Method java/lang/StringBuffer.toString:()Ljava/lang/String;
      58: invokevirtual #25                 // Method java/lang/StringBuffer.append:(Ljava/lang/String;)Ljava/lang/StringBuffer;
      61: pop
      62: aload_1
      63: invokevirtual #101                // Method org/hibernate/mapping/Property.getValue:()Lorg/hibernate/mapping/Value;
      66: checkcast     #127                // class org/hibernate/mapping/Component
      69: astore        5
      71: aload         5
      73: invokevirtual #128                // Method org/hibernate/mapping/Component.getPropertyIterator:()Ljava/util/Iterator;
      76: astore        6
      78: aload_0
      79: aload         6
      81: aconst_null
      82: aload_1
      83: aload_2
      84: invokespecial #129                // Method buildRecursiveAttributeOverride:(Ljava/util/Iterator;Ljava/lang/String;Lorg/hibernate/mapping/Property;Ljava/lang/StringBuffer;)V
      87: aload_2
      88: aload_2
      89: invokevirtual #62                 // Method java/lang/StringBuffer.length:()I
      92: iconst_2
      93: isub
      94: invokevirtual #130                // Method java/lang/StringBuffer.setLength:(I)V
      97: aload_2
      98: ldc           #131                // String  } )
     100: invokevirtual #25                 // Method java/lang/StringBuffer.append:(Ljava/lang/String;)Ljava/lang/StringBuffer;
     103: pop
     104: goto          248
     107: aload_1
     108: invokevirtual #132                // Method org/hibernate/mapping/Property.getColumnSpan:()I
     111: iconst_1
     112: if_icmpne     142
     115: aload_1
     116: invokevirtual #133                // Method org/hibernate/mapping/Property.getColumnIterator:()Ljava/util/Iterator;
     119: invokeinterface #17,  1           // InterfaceMethod java/util/Iterator.next:()Ljava/lang/Object;
     124: checkcast     #134                // class org/hibernate/mapping/Selectable
     127: astore        5
     129: aload_0
     130: aload         5
     132: aload_2
     133: iload_3
     134: iload         4
     136: invokespecial #135                // Method buildColumnAnnotation:(Lorg/hibernate/mapping/Selectable;Ljava/lang/StringBuffer;ZZ)V
     139: goto          248
     142: aload_1
     143: invokevirtual #133                // Method org/hibernate/mapping/Property.getColumnIterator:()Ljava/util/Iterator;
     146: astore        5
     148: aload_2
     149: ldc           #120                // String @
     151: invokevirtual #25                 // Method java/lang/StringBuffer.append:(Ljava/lang/String;)Ljava/lang/StringBuffer;
     154: aload_0
     155: ldc           #136                // String org.hibernate.annotations.Columns
     157: invokevirtual #87                 // Method importType:(Ljava/lang/String;)Ljava/lang/String;
     160: invokevirtual #25                 // Method java/lang/StringBuffer.append:(Ljava/lang/String;)Ljava/lang/StringBuffer;
     163: ldc           #137                // String ( {
     165: invokevirtual #25                 // Method java/lang/StringBuffer.append:(Ljava/lang/String;)Ljava/lang/StringBuffer;
     168: pop
     169: aload         5
     171: invokeinterface #16,  1           // InterfaceMethod java/util/Iterator.hasNext:()Z
     176: ifeq          231
     179: aload         5
     181: invokeinterface #17,  1           // InterfaceMethod java/util/Iterator.next:()Ljava/lang/Object;
     186: checkcast     #134                // class org/hibernate/mapping/Selectable
     189: astore        6
     191: aload         6
     193: invokeinterface #138,  1          // InterfaceMethod org/hibernate/mapping/Selectable.isFormula:()Z
     198: ifeq          204
     201: goto          228
     204: aload_2
     205: ldc           #139                // String \n
     207: invokevirtual #25                 // Method java/lang/StringBuffer.append:(Ljava/lang/String;)Ljava/lang/StringBuffer;
     210: pop
     211: aload_0
     212: aload         6
     214: aload_2
     215: iload_3
     216: iload         4
     218: invokespecial #135                // Method buildColumnAnnotation:(Lorg/hibernate/mapping/Selectable;Ljava/lang/StringBuffer;ZZ)V
     221: aload_2
     222: ldc           #89                 // String ,
     224: invokevirtual #25                 // Method java/lang/StringBuffer.append:(Ljava/lang/String;)Ljava/lang/StringBuffer;
     227: pop
     228: goto          169
     231: aload_2
     232: aload_2
     233: invokevirtual #62                 // Method java/lang/StringBuffer.length:()I
     236: iconst_2
     237: isub
     238: invokevirtual #130                // Method java/lang/StringBuffer.setLength:(I)V
     241: aload_2
     242: ldc           #131                // String  } )
     244: invokevirtual #25                 // Method java/lang/StringBuffer.append:(Ljava/lang/String;)Ljava/lang/StringBuffer;
     247: pop
     248: aload_2
     249: invokevirtual #27                 // Method java/lang/StringBuffer.toString:()Ljava/lang/String;
     252: areturn

  private void buildRecursiveAttributeOverride(java.util.Iterator, java.lang.String, org.hibernate.mapping.Property, java.lang.StringBuffer);
    Code:
       0: aload_1
       1: invokeinterface #16,  1           // InterfaceMethod java/util/Iterator.hasNext:()Z
       6: ifeq          233
       9: aload_1
      10: invokeinterface #17,  1           // InterfaceMethod java/util/Iterator.next:()Ljava/lang/Object;
      15: checkcast     #61                 // class org/hibernate/mapping/Property
      18: astore        5
      20: aload         5
      22: invokevirtual #124                // Method org/hibernate/mapping/Property.isComposite:()Z
      25: ifeq          108
      28: aload_2
      29: ifnull        55
      32: new           #22                 // class java/lang/StringBuffer
      35: dup
      36: invokespecial #23                 // Method java/lang/StringBuffer."<init>":()V
      39: aload_2
      40: invokevirtual #25                 // Method java/lang/StringBuffer.append:(Ljava/lang/String;)Ljava/lang/StringBuffer;
      43: ldc           #37                 // String .
      45: invokevirtual #25                 // Method java/lang/StringBuffer.append:(Ljava/lang/String;)Ljava/lang/StringBuffer;
      48: invokevirtual #27                 // Method java/lang/StringBuffer.toString:()Ljava/lang/String;
      51: astore_2
      52: goto          58
      55: ldc           #35                 // String
      57: astore_2
      58: new           #22                 // class java/lang/StringBuffer
      61: dup
      62: invokespecial #23                 // Method java/lang/StringBuffer."<init>":()V
      65: aload_2
      66: invokevirtual #25                 // Method java/lang/StringBuffer.append:(Ljava/lang/String;)Ljava/lang/StringBuffer;
      69: aload         5
      71: invokevirtual #140                // Method org/hibernate/mapping/Property.getName:()Ljava/lang/String;
      74: invokevirtual #25                 // Method java/lang/StringBuffer.append:(Ljava/lang/String;)Ljava/lang/StringBuffer;
      77: invokevirtual #27                 // Method java/lang/StringBuffer.toString:()Ljava/lang/String;
      80: astore_2
      81: aload         5
      83: invokevirtual #101                // Method org/hibernate/mapping/Property.getValue:()Lorg/hibernate/mapping/Value;
      86: checkcast     #127                // class org/hibernate/mapping/Component
      89: astore        6
      91: aload_0
      92: aload         6
      94: invokevirtual #128                // Method org/hibernate/mapping/Component.getPropertyIterator:()Ljava/util/Iterator;
      97: aload_2
      98: aload         5
     100: aload         4
     102: invokespecial #129                // Method buildRecursiveAttributeOverride:(Ljava/util/Iterator;Ljava/lang/String;Lorg/hibernate/mapping/Property;Ljava/lang/StringBuffer;)V
     105: goto          230
     108: aload         5
     110: invokevirtual #133                // Method org/hibernate/mapping/Property.getColumnIterator:()Ljava/util/Iterator;
     113: astore        6
     115: aload         6
     117: invokeinterface #17,  1           // InterfaceMethod java/util/Iterator.next:()Ljava/lang/Object;
     122: checkcast     #134                // class org/hibernate/mapping/Selectable
     125: astore        7
     127: aload         7
     129: invokeinterface #138,  1          // InterfaceMethod org/hibernate/mapping/Selectable.isFormula:()Z
     134: ifeq          140
     137: goto          230
     140: aload         4
     142: ldc           #139                // String \n
     144: invokevirtual #25                 // Method java/lang/StringBuffer.append:(Ljava/lang/String;)Ljava/lang/StringBuffer;
     147: ldc           #120                // String @
     149: invokevirtual #25                 // Method java/lang/StringBuffer.append:(Ljava/lang/String;)Ljava/lang/StringBuffer;
     152: aload_0
     153: ldc           #141                // String javax.persistence.AttributeOverride
     155: invokevirtual #87                 // Method importType:(Ljava/lang/String;)Ljava/lang/String;
     158: invokevirtual #25                 // Method java/lang/StringBuffer.append:(Ljava/lang/String;)Ljava/lang/StringBuffer;
     161: ldc           #142                // String (name=\"
     163: invokevirtual #25                 // Method java/lang/StringBuffer.append:(Ljava/lang/String;)Ljava/lang/StringBuffer;
     166: pop
     167: aload_2
     168: ifnull        183
     171: aload         4
     173: aload_2
     174: invokevirtual #25                 // Method java/lang/StringBuffer.append:(Ljava/lang/String;)Ljava/lang/StringBuffer;
     177: ldc           #37                 // String .
     179: invokevirtual #25                 // Method java/lang/StringBuffer.append:(Ljava/lang/String;)Ljava/lang/StringBuffer;
     182: pop
     183: aload         4
     185: aload         5
     187: invokevirtual #140                // Method org/hibernate/mapping/Property.getName:()Ljava/lang/String;
     190: invokevirtual #25                 // Method java/lang/StringBuffer.append:(Ljava/lang/String;)Ljava/lang/StringBuffer;
     193: ldc           #143                // String \"
     195: invokevirtual #25                 // Method java/lang/StringBuffer.append:(Ljava/lang/String;)Ljava/lang/StringBuffer;
     198: ldc           #144                // String , column=
     200: invokevirtual #25                 // Method java/lang/StringBuffer.append:(Ljava/lang/String;)Ljava/lang/StringBuffer;
     203: pop
     204: aload_0
     205: aload         7
     207: aload         4
     209: aload         5
     211: invokevirtual #122                // Method org/hibernate/mapping/Property.isInsertable:()Z
     214: aload         5
     216: invokevirtual #123                // Method org/hibernate/mapping/Property.isUpdateable:()Z
     219: invokespecial #135                // Method buildColumnAnnotation:(Lorg/hibernate/mapping/Selectable;Ljava/lang/StringBuffer;ZZ)V
     222: aload         4
     224: ldc           #145                // String  ),
     226: invokevirtual #25                 // Method java/lang/StringBuffer.append:(Ljava/lang/String;)Ljava/lang/StringBuffer;
     229: pop
     230: goto          0
     233: return

  private void buildColumnAnnotation(org.hibernate.mapping.Selectable, java.lang.StringBuffer, boolean, boolean);
    Code:
       0: aload_1
       1: invokeinterface #138,  1          // InterfaceMethod org/hibernate/mapping/Selectable.isFormula:()Z
       6: ifeq          47
       9: aload_2
      10: ldc           #120                // String @
      12: invokevirtual #25                 // Method java/lang/StringBuffer.append:(Ljava/lang/String;)Ljava/lang/StringBuffer;
      15: aload_0
      16: ldc           #146                // String org.hibernate.annotations.Formula
      18: invokevirtual #87                 // Method importType:(Ljava/lang/String;)Ljava/lang/String;
      21: invokevirtual #25                 // Method java/lang/StringBuffer.append:(Ljava/lang/String;)Ljava/lang/StringBuffer;
      24: ldc           #147                // String (value=\"
      26: invokevirtual #25                 // Method java/lang/StringBuffer.append:(Ljava/lang/String;)Ljava/lang/StringBuffer;
      29: aload_1
      30: invokeinterface #148,  1          // InterfaceMethod org/hibernate/mapping/Selectable.getText:()Ljava/lang/String;
      35: invokevirtual #25                 // Method java/lang/StringBuffer.append:(Ljava/lang/String;)Ljava/lang/StringBuffer;
      38: ldc           #149                // String \")
      40: invokevirtual #25                 // Method java/lang/StringBuffer.append:(Ljava/lang/String;)Ljava/lang/StringBuffer;
      43: pop
      44: goto          195
      47: aload_1
      48: checkcast     #150                // class org/hibernate/mapping/Column
      51: astore        5
      53: aload_2
      54: new           #22                 // class java/lang/StringBuffer
      57: dup
      58: invokespecial #23                 // Method java/lang/StringBuffer."<init>":()V
      61: ldc           #120                // String @
      63: invokevirtual #25                 // Method java/lang/StringBuffer.append:(Ljava/lang/String;)Ljava/lang/StringBuffer;
      66: aload_0
      67: ldc           #151                // String javax.persistence.Column
      69: invokevirtual #87                 // Method importType:(Ljava/lang/String;)Ljava/lang/String;
      72: invokevirtual #25                 // Method java/lang/StringBuffer.append:(Ljava/lang/String;)Ljava/lang/StringBuffer;
      75: ldc           #142                // String (name=\"
      77: invokevirtual #25                 // Method java/lang/StringBuffer.append:(Ljava/lang/String;)Ljava/lang/StringBuffer;
      80: invokevirtual #27                 // Method java/lang/StringBuffer.toString:()Ljava/lang/String;
      83: invokevirtual #25                 // Method java/lang/StringBuffer.append:(Ljava/lang/String;)Ljava/lang/StringBuffer;
      86: aload         5
      88: invokevirtual #152                // Method org/hibernate/mapping/Column.getName:()Ljava/lang/String;
      91: invokevirtual #25                 // Method java/lang/StringBuffer.append:(Ljava/lang/String;)Ljava/lang/StringBuffer;
      94: ldc           #143                // String \"
      96: invokevirtual #25                 // Method java/lang/StringBuffer.append:(Ljava/lang/String;)Ljava/lang/StringBuffer;
      99: pop
     100: aload_0
     101: aload_2
     102: aload         5
     104: iload_3
     105: iload         4
     107: invokevirtual #153                // Method appendCommonColumnInfo:(Ljava/lang/StringBuffer;Lorg/hibernate/mapping/Column;ZZ)V
     110: aload         5
     112: invokevirtual #154                // Method org/hibernate/mapping/Column.getPrecision:()I
     115: bipush        19
     117: if_icmpeq     135
     120: aload_2
     121: ldc           #155                // String , precision=
     123: invokevirtual #25                 // Method java/lang/StringBuffer.append:(Ljava/lang/String;)Ljava/lang/StringBuffer;
     126: aload         5
     128: invokevirtual #154                // Method org/hibernate/mapping/Column.getPrecision:()I
     131: invokevirtual #156                // Method java/lang/StringBuffer.append:(I)Ljava/lang/StringBuffer;
     134: pop
     135: aload         5
     137: invokevirtual #157                // Method org/hibernate/mapping/Column.getScale:()I
     140: iconst_2
     141: if_icmpeq     162
     144: aload_2
     145: ldc           #158                // String , scale=
     147: invokevirtual #25                 // Method java/lang/StringBuffer.append:(Ljava/lang/String;)Ljava/lang/StringBuffer;
     150: aload         5
     152: invokevirtual #157                // Method org/hibernate/mapping/Column.getScale:()I
     155: invokevirtual #156                // Method java/lang/StringBuffer.append:(I)Ljava/lang/StringBuffer;
     158: pop
     159: goto          188
     162: aload         5
     164: invokevirtual #159                // Method org/hibernate/mapping/Column.getLength:()I
     167: sipush        255
     170: if_icmpeq     188
     173: aload_2
     174: ldc           #160                // String , length=
     176: invokevirtual #25                 // Method java/lang/StringBuffer.append:(Ljava/lang/String;)Ljava/lang/StringBuffer;
     179: aload         5
     181: invokevirtual #159                // Method org/hibernate/mapping/Column.getLength:()I
     184: invokevirtual #156                // Method java/lang/StringBuffer.append:(I)Ljava/lang/StringBuffer;
     187: pop
     188: aload_2
     189: ldc           #77                 // String )
     191: invokevirtual #25                 // Method java/lang/StringBuffer.append:(Ljava/lang/String;)Ljava/lang/StringBuffer;
     194: pop
     195: return

  protected void appendCommonColumnInfo(java.lang.StringBuffer, org.hibernate.mapping.Column, boolean, boolean);
    Code:
       0: aload_2
       1: invokevirtual #161                // Method org/hibernate/mapping/Column.isUnique:()Z
       4: ifeq          21
       7: aload_1
       8: ldc           #162                // String , unique=
      10: invokevirtual #25                 // Method java/lang/StringBuffer.append:(Ljava/lang/String;)Ljava/lang/StringBuffer;
      13: aload_2
      14: invokevirtual #161                // Method org/hibernate/mapping/Column.isUnique:()Z
      17: invokevirtual #163                // Method java/lang/StringBuffer.append:(Z)Ljava/lang/StringBuffer;
      20: pop
      21: aload_2
      22: invokevirtual #164                // Method org/hibernate/mapping/Column.isNullable:()Z
      25: ifne          42
      28: aload_1
      29: ldc           #165                // String , nullable=
      31: invokevirtual #25                 // Method java/lang/StringBuffer.append:(Ljava/lang/String;)Ljava/lang/StringBuffer;
      34: aload_2
      35: invokevirtual #164                // Method org/hibernate/mapping/Column.isNullable:()Z
      38: invokevirtual #163                // Method java/lang/StringBuffer.append:(Z)Ljava/lang/StringBuffer;
      41: pop
      42: iload_3
      43: ifne          57
      46: aload_1
      47: ldc           #166                // String , insertable=
      49: invokevirtual #25                 // Method java/lang/StringBuffer.append:(Ljava/lang/String;)Ljava/lang/StringBuffer;
      52: iload_3
      53: invokevirtual #163                // Method java/lang/StringBuffer.append:(Z)Ljava/lang/StringBuffer;
      56: pop
      57: iload         4
      59: ifne          74
      62: aload_1
      63: ldc           #167                // String , updatable=
      65: invokevirtual #25                 // Method java/lang/StringBuffer.append:(Ljava/lang/String;)Ljava/lang/StringBuffer;
      68: iload         4
      70: invokevirtual #163                // Method java/lang/StringBuffer.append:(Z)Ljava/lang/StringBuffer;
      73: pop
      74: aload_2
      75: invokevirtual #168                // Method org/hibernate/mapping/Column.getSqlType:()Ljava/lang/String;
      78: astore        5
      80: aload         5
      82: invokestatic  #169                // Method org/hibernate/util/StringHelper.isNotEmpty:(Ljava/lang/String;)Z
      85: ifeq          105
      88: aload_1
      89: ldc           #170                // String , columnDefinition=\"
      91: invokevirtual #25                 // Method java/lang/StringBuffer.append:(Ljava/lang/String;)Ljava/lang/StringBuffer;
      94: aload         5
      96: invokevirtual #25                 // Method java/lang/StringBuffer.append:(Ljava/lang/String;)Ljava/lang/StringBuffer;
      99: ldc           #143                // String \"
     101: invokevirtual #25                 // Method java/lang/StringBuffer.append:(Ljava/lang/String;)Ljava/lang/StringBuffer;
     104: pop
     105: return

  public java.util.Iterator getToStringPropertiesIterator();
    Code:
       0: aload_0
       1: invokevirtual #95                 // Method getAllPropertiesIterator:()Ljava/util/Iterator;
       4: astore_1
       5: aload_0
       6: aload_1
       7: invokespecial #171                // Method getToStringPropertiesIterator:(Ljava/util/Iterator;)Ljava/util/Iterator;
      10: areturn

  private java.util.Iterator getToStringPropertiesIterator(java.util.Iterator);
    Code:
       0: new           #172                // class java/util/ArrayList
       3: dup
       4: invokespecial #173                // Method java/util/ArrayList."<init>":()V
       7: astore_2
       8: aload_1
       9: invokeinterface #16,  1           // InterfaceMethod java/util/Iterator.hasNext:()Z
      14: ifeq          51
      17: aload_1
      18: invokeinterface #17,  1           // InterfaceMethod java/util/Iterator.next:()Ljava/lang/Object;
      23: checkcast     #61                 // class org/hibernate/mapping/Property
      26: astore_3
      27: aload_0
      28: getfield      #3                  // Field c2j:Lorg/hibernate/tool/hbm2x/Cfg2JavaTool;
      31: aload_3
      32: ldc           #174                // String use-in-tostring
      34: invokevirtual #71                 // Method org/hibernate/tool/hbm2x/Cfg2JavaTool.getMetaAsBool:(Lorg/hibernate/mapping/MetaAttributable;Ljava/lang/String;)Z
      37: ifeq          48
      40: aload_2
      41: aload_3
      42: invokeinterface #175,  2          // InterfaceMethod java/util/List.add:(Ljava/lang/Object;)Z
      47: pop
      48: goto          8
      51: aload_2
      52: invokeinterface #15,  1           // InterfaceMethod java/util/List.iterator:()Ljava/util/Iterator;
      57: areturn

  public java.util.Iterator getEqualsHashCodePropertiesIterator();
    Code:
       0: aload_0
       1: invokevirtual #95                 // Method getAllPropertiesIterator:()Ljava/util/Iterator;
       4: astore_1
       5: aload_0
       6: aload_1
       7: invokespecial #176                // Method getEqualsHashCodePropertiesIterator:(Ljava/util/Iterator;)Ljava/util/Iterator;
      10: areturn

  private java.util.Iterator getEqualsHashCodePropertiesIterator(java.util.Iterator);
    Code:
       0: new           #172                // class java/util/ArrayList
       3: dup
       4: invokespecial #173                // Method java/util/ArrayList."<init>":()V
       7: astore_2
       8: aload_1
       9: invokeinterface #16,  1           // InterfaceMethod java/util/Iterator.hasNext:()Z
      14: ifeq          46
      17: aload_1
      18: invokeinterface #17,  1           // InterfaceMethod java/util/Iterator.next:()Ljava/lang/Object;
      23: checkcast     #61                 // class org/hibernate/mapping/Property
      26: astore_3
      27: aload_0
      28: aload_3
      29: invokespecial #94                 // Method usePropertyInEquals:(Lorg/hibernate/mapping/Property;)Z
      32: ifeq          43
      35: aload_2
      36: aload_3
      37: invokeinterface #175,  2          // InterfaceMethod java/util/List.add:(Ljava/lang/Object;)Z
      42: pop
      43: goto          8
      46: aload_2
      47: invokeinterface #15,  1           // InterfaceMethod java/util/List.iterator:()Ljava/util/Iterator;
      52: areturn

  public boolean needsToString();
    Code:
       0: aload_0
       1: invokevirtual #95                 // Method getAllPropertiesIterator:()Ljava/util/Iterator;
       4: astore_1
       5: aload_0
       6: aload_1
       7: invokespecial #177                // Method needsToString:(Ljava/util/Iterator;)Z
      10: ireturn

  private boolean needsToString(java.util.Iterator);
    Code:
       0: aload_1
       1: invokeinterface #16,  1           // InterfaceMethod java/util/Iterator.hasNext:()Z
       6: ifeq          37
       9: aload_1
      10: invokeinterface #17,  1           // InterfaceMethod java/util/Iterator.next:()Ljava/lang/Object;
      15: checkcast     #61                 // class org/hibernate/mapping/Property
      18: astore_2
      19: aload_0
      20: getfield      #3                  // Field c2j:Lorg/hibernate/tool/hbm2x/Cfg2JavaTool;
      23: aload_2
      24: ldc           #174                // String use-in-tostring
      26: invokevirtual #71                 // Method org/hibernate/tool/hbm2x/Cfg2JavaTool.getMetaAsBool:(Lorg/hibernate/mapping/MetaAttributable;Ljava/lang/String;)Z
      29: ifeq          34
      32: iconst_1
      33: ireturn
      34: goto          0
      37: iconst_0
      38: ireturn

  public boolean hasMetaAttribute(org.hibernate.mapping.MetaAttributable, java.lang.String);
    Code:
       0: aload_1
       1: aload_2
       2: invokeinterface #13,  2           // InterfaceMethod org/hibernate/mapping/MetaAttributable.getMetaAttribute:(Ljava/lang/String;)Lorg/hibernate/mapping/MetaAttribute;
       7: ifnull        14
      10: iconst_1
      11: goto          15
      14: iconst_0
      15: ireturn

  public boolean getMetaAttribAsBool(org.hibernate.mapping.MetaAttributable, java.lang.String, boolean);
    Code:
       0: aload_1
       1: aload_2
       2: invokeinterface #13,  2           // InterfaceMethod org/hibernate/mapping/MetaAttributable.getMetaAttribute:(Ljava/lang/String;)Lorg/hibernate/mapping/MetaAttribute;
       7: iload_3
       8: invokestatic  #45                 // Method org/hibernate/tool/hbm2x/MetaAttributeHelper.getMetaAsBool:(Lorg/hibernate/mapping/MetaAttribute;Z)Z
      11: ireturn

  public boolean hasFieldJavaDoc(org.hibernate.mapping.Property);
    Code:
       0: aload_1
       1: ldc           #178                // String field-description
       3: invokevirtual #179                // Method org/hibernate/mapping/Property.getMetaAttribute:(Ljava/lang/String;)Lorg/hibernate/mapping/MetaAttribute;
       6: ifnull        13
       9: iconst_1
      10: goto          14
      13: iconst_0
      14: ireturn

  public java.lang.String getFieldJavaDoc(org.hibernate.mapping.Property, int);
    Code:
       0: aload_1
       1: ldc           #178                // String field-description
       3: invokevirtual #179                // Method org/hibernate/mapping/Property.getMetaAttribute:(Ljava/lang/String;)Lorg/hibernate/mapping/MetaAttribute;
       6: astore_3
       7: aload_3
       8: ifnonnull     22
      11: aload_0
      12: getfield      #3                  // Field c2j:Lorg/hibernate/tool/hbm2x/Cfg2JavaTool;
      15: ldc           #35                 // String
      17: iload_2
      18: invokevirtual #47                 // Method org/hibernate/tool/hbm2x/Cfg2JavaTool.toJavaDoc:(Ljava/lang/String;I)Ljava/lang/String;
      21: areturn
      22: aload_0
      23: getfield      #3                  // Field c2j:Lorg/hibernate/tool/hbm2x/Cfg2JavaTool;
      26: aload_0
      27: getfield      #3                  // Field c2j:Lorg/hibernate/tool/hbm2x/Cfg2JavaTool;
      30: aload_1
      31: ldc           #178                // String field-description
      33: invokevirtual #180                // Method org/hibernate/tool/hbm2x/Cfg2JavaTool.getMetaAsString:(Lorg/hibernate/mapping/MetaAttributable;Ljava/lang/String;)Ljava/lang/String;
      36: iload_2
      37: invokevirtual #47                 // Method org/hibernate/tool/hbm2x/Cfg2JavaTool.toJavaDoc:(Ljava/lang/String;I)Ljava/lang/String;
      40: areturn

  public java.lang.String getFieldDescription(org.hibernate.mapping.Property);
    Code:
       0: aload_1
       1: ldc           #178                // String field-description
       3: invokevirtual #179                // Method org/hibernate/mapping/Property.getMetaAttribute:(Ljava/lang/String;)Lorg/hibernate/mapping/MetaAttribute;
       6: astore_2
       7: aload_2
       8: ifnonnull     14
      11: ldc           #35                 // String
      13: areturn
      14: aload_0
      15: getfield      #3                  // Field c2j:Lorg/hibernate/tool/hbm2x/Cfg2JavaTool;
      18: aload_1
      19: ldc           #178                // String field-description
      21: invokevirtual #180                // Method org/hibernate/tool/hbm2x/Cfg2JavaTool.getMetaAsString:(Lorg/hibernate/mapping/MetaAttributable;Ljava/lang/String;)Ljava/lang/String;
      24: areturn

  public java.lang.String getGetterSignature(org.hibernate.mapping.Property);
    Code:
       0: aload_0
       1: getfield      #3                  // Field c2j:Lorg/hibernate/tool/hbm2x/Cfg2JavaTool;
       4: aload_1
       5: iconst_0
       6: invokevirtual #181                // Method org/hibernate/tool/hbm2x/Cfg2JavaTool.getJavaTypeName:(Lorg/hibernate/mapping/Property;Z)Ljava/lang/String;
       9: ldc           #182                // String boolean
      11: invokevirtual #36                 // Method java/lang/String.equals:(Ljava/lang/Object;)Z
      14: ifeq          22
      17: ldc           #183                // String is
      19: goto          24
      22: ldc           #184                // String get
      24: astore_2
      25: new           #22                 // class java/lang/StringBuffer
      28: dup
      29: invokespecial #23                 // Method java/lang/StringBuffer."<init>":()V
      32: aload_2
      33: invokevirtual #25                 // Method java/lang/StringBuffer.append:(Ljava/lang/String;)Ljava/lang/StringBuffer;
      36: aload_1
      37: invokevirtual #140                // Method org/hibernate/mapping/Property.getName:()Ljava/lang/String;
      40: invokestatic  #185                // Method beanCapitalize:(Ljava/lang/String;)Ljava/lang/String;
      43: invokevirtual #25                 // Method java/lang/StringBuffer.append:(Ljava/lang/String;)Ljava/lang/StringBuffer;
      46: invokevirtual #27                 // Method java/lang/StringBuffer.toString:()Ljava/lang/String;
      49: areturn

  public java.lang.String getPropertyName(org.hibernate.mapping.Property);
    Code:
       0: aload_1
       1: invokevirtual #140                // Method org/hibernate/mapping/Property.getName:()Ljava/lang/String;
       4: invokestatic  #185                // Method beanCapitalize:(Ljava/lang/String;)Ljava/lang/String;
       7: areturn

  public java.lang.String getCollectionNameFor(org.hibernate.mapping.Property);
    Code:
       0: aload_0
       1: aload_1
       2: invokevirtual #186                // Method getPropertyName:(Lorg/hibernate/mapping/Property;)Ljava/lang/String;
       5: astore_2
       6: aload_2
       7: invokestatic  #187                // Method org/hibernate/cfg/reveng/ReverseEngineeringStrategyUtil.simplePluralize:(Ljava/lang/String;)Ljava/lang/String;
      10: areturn

  public static java.lang.String beanCapitalize(java.lang.String);
    Code:
       0: aload_0
       1: ifnull        11
       4: aload_0
       5: invokevirtual #21                 // Method java/lang/String.length:()I
       8: ifne          13
      11: aload_0
      12: areturn
      13: aload_0
      14: invokevirtual #21                 // Method java/lang/String.length:()I
      17: iconst_1
      18: if_icmple     34
      21: aload_0
      22: iconst_1
      23: invokevirtual #188                // Method java/lang/String.charAt:(I)C
      26: invokestatic  #189                // Method java/lang/Character.isUpperCase:(C)Z
      29: ifeq          34
      32: aload_0
      33: areturn
      34: aload_0
      35: invokevirtual #190                // Method java/lang/String.toCharArray:()[C
      38: astore_1
      39: aload_1
      40: iconst_0
      41: aload_1
      42: iconst_0
      43: caload
      44: invokestatic  #191                // Method java/lang/Character.toUpperCase:(C)C
      47: castore
      48: new           #18                 // class java/lang/String
      51: dup
      52: aload_1
      53: invokespecial #192                // Method java/lang/String."<init>":([C)V
      56: areturn

  public boolean isComponent(org.hibernate.mapping.Property);
    Code:
       0: aload_1
       1: invokevirtual #101                // Method org/hibernate/mapping/Property.getValue:()Lorg/hibernate/mapping/Value;
       4: astore_2
       5: aload_2
       6: ifnull        18
       9: aload_2
      10: instanceof    #127                // class org/hibernate/mapping/Component
      13: ifeq          18
      16: iconst_1
      17: ireturn
      18: iconst_0
      19: ireturn

  public java.lang.String generateHashCode(org.hibernate.mapping.Property, java.lang.String, java.lang.String, boolean);
    Code:
       0: new           #22                 // class java/lang/StringBuffer
       3: dup
       4: invokespecial #23                 // Method java/lang/StringBuffer."<init>":()V
       7: astore        5
       9: aload_0
      10: getfield      #3                  // Field c2j:Lorg/hibernate/tool/hbm2x/Cfg2JavaTool;
      13: aload_1
      14: ldc           #69                 // String use-in-equals
      16: invokevirtual #71                 // Method org/hibernate/tool/hbm2x/Cfg2JavaTool.getMetaAsBool:(Lorg/hibernate/mapping/MetaAttributable;Ljava/lang/String;)Z
      19: ifeq          444
      22: aload_0
      23: getfield      #3                  // Field c2j:Lorg/hibernate/tool/hbm2x/Cfg2JavaTool;
      26: aload_1
      27: iload         4
      29: aload_0
      30: invokevirtual #64                 // Method org/hibernate/tool/hbm2x/Cfg2JavaTool.getJavaTypeName:(Lorg/hibernate/mapping/Property;ZLorg/hibernate/tool/hbm2x/pojo/ImportContext;)Ljava/lang/String;
      33: astore        6
      35: aload_0
      36: getfield      #3                  // Field c2j:Lorg/hibernate/tool/hbm2x/Cfg2JavaTool;
      39: aload         6
      41: invokevirtual #74                 // Method org/hibernate/tool/hbm2x/Cfg2JavaTool.isPrimitive:(Ljava/lang/String;)Z
      44: istore        7
      46: iload         7
      48: ifeq          228
      51: aload         5
      53: aload_2
      54: invokevirtual #25                 // Method java/lang/StringBuffer.append:(Ljava/lang/String;)Ljava/lang/StringBuffer;
      57: ldc           #193                // String  = 37 *
      59: invokevirtual #25                 // Method java/lang/StringBuffer.append:(Ljava/lang/String;)Ljava/lang/StringBuffer;
      62: aload_2
      63: invokevirtual #25                 // Method java/lang/StringBuffer.append:(Ljava/lang/String;)Ljava/lang/StringBuffer;
      66: ldc           #194                // String  +
      68: invokevirtual #25                 // Method java/lang/StringBuffer.append:(Ljava/lang/String;)Ljava/lang/StringBuffer;
      71: pop
      72: new           #22                 // class java/lang/StringBuffer
      75: dup
      76: invokespecial #23                 // Method java/lang/StringBuffer."<init>":()V
      79: aload_3
      80: invokevirtual #25                 // Method java/lang/StringBuffer.append:(Ljava/lang/String;)Ljava/lang/StringBuffer;
      83: ldc           #37                 // String .
      85: invokevirtual #25                 // Method java/lang/StringBuffer.append:(Ljava/lang/String;)Ljava/lang/StringBuffer;
      88: aload_0
      89: aload_1
      90: invokevirtual #65                 // Method getGetterSignature:(Lorg/hibernate/mapping/Property;)Ljava/lang/String;
      93: invokevirtual #25                 // Method java/lang/StringBuffer.append:(Ljava/lang/String;)Ljava/lang/StringBuffer;
      96: ldc           #66                 // String ()
      98: invokevirtual #25                 // Method java/lang/StringBuffer.append:(Ljava/lang/String;)Ljava/lang/StringBuffer;
     101: invokevirtual #27                 // Method java/lang/StringBuffer.toString:()Ljava/lang/String;
     104: astore        8
     106: ldc           #195                // String char
     108: aload         6
     110: invokevirtual #36                 // Method java/lang/String.equals:(Ljava/lang/Object;)Z
     113: ifne          146
     116: ldc           #196                // String int
     118: aload         6
     120: invokevirtual #36                 // Method java/lang/String.equals:(Ljava/lang/Object;)Z
     123: ifne          146
     126: ldc           #197                // String short
     128: aload         6
     130: invokevirtual #36                 // Method java/lang/String.equals:(Ljava/lang/Object;)Z
     133: ifne          146
     136: ldc           #198                // String byte
     138: aload         6
     140: invokevirtual #36                 // Method java/lang/String.equals:(Ljava/lang/Object;)Z
     143: ifeq          157
     146: aload         5
     148: aload         8
     150: invokevirtual #25                 // Method java/lang/StringBuffer.append:(Ljava/lang/String;)Ljava/lang/StringBuffer;
     153: pop
     154: goto          217
     157: ldc           #182                // String boolean
     159: aload         6
     161: invokevirtual #36                 // Method java/lang/String.equals:(Ljava/lang/Object;)Z
     164: ifeq          201
     167: aload         5
     169: new           #22                 // class java/lang/StringBuffer
     172: dup
     173: invokespecial #23                 // Method java/lang/StringBuffer."<init>":()V
     176: ldc           #75                 // String (
     178: invokevirtual #25                 // Method java/lang/StringBuffer.append:(Ljava/lang/String;)Ljava/lang/StringBuffer;
     181: aload         8
     183: invokevirtual #25                 // Method java/lang/StringBuffer.append:(Ljava/lang/String;)Ljava/lang/StringBuffer;
     186: ldc           #199                // String ?1:0)
     188: invokevirtual #25                 // Method java/lang/StringBuffer.append:(Ljava/lang/String;)Ljava/lang/StringBuffer;
     191: invokevirtual #27                 // Method java/lang/StringBuffer.toString:()Ljava/lang/String;
     194: invokevirtual #25                 // Method java/lang/StringBuffer.append:(Ljava/lang/String;)Ljava/lang/StringBuffer;
     197: pop
     198: goto          217
     201: aload         5
     203: ldc           #200                // String (int)
     205: invokevirtual #25                 // Method java/lang/StringBuffer.append:(Ljava/lang/String;)Ljava/lang/StringBuffer;
     208: pop
     209: aload         5
     211: aload         8
     213: invokevirtual #25                 // Method java/lang/StringBuffer.append:(Ljava/lang/String;)Ljava/lang/StringBuffer;
     216: pop
     217: aload         5
     219: ldc           #26                 // String ;
     221: invokevirtual #25                 // Method java/lang/StringBuffer.append:(Ljava/lang/String;)Ljava/lang/StringBuffer;
     224: pop
     225: goto          444
     228: aload         6
     230: ldc           #84                 // String []
     232: invokevirtual #85                 // Method java/lang/String.endsWith:(Ljava/lang/String;)Z
     235: ifeq          365
     238: iload         4
     240: ifeq          347
     243: aload         5
     245: aload_2
     246: invokevirtual #25                 // Method java/lang/StringBuffer.append:(Ljava/lang/String;)Ljava/lang/StringBuffer;
     249: ldc           #193                // String  = 37 *
     251: invokevirtual #25                 // Method java/lang/StringBuffer.append:(Ljava/lang/String;)Ljava/lang/StringBuffer;
     254: aload_2
     255: invokevirtual #25                 // Method java/lang/StringBuffer.append:(Ljava/lang/String;)Ljava/lang/StringBuffer;
     258: ldc           #194                // String  +
     260: invokevirtual #25                 // Method java/lang/StringBuffer.append:(Ljava/lang/String;)Ljava/lang/StringBuffer;
     263: pop
     264: aload         5
     266: ldc           #201                // String (
     268: invokevirtual #25                 // Method java/lang/StringBuffer.append:(Ljava/lang/String;)Ljava/lang/StringBuffer;
     271: aload_0
     272: aload_1
     273: invokevirtual #65                 // Method getGetterSignature:(Lorg/hibernate/mapping/Property;)Ljava/lang/String;
     276: invokevirtual #25                 // Method java/lang/StringBuffer.append:(Ljava/lang/String;)Ljava/lang/StringBuffer;
     279: new           #22                 // class java/lang/StringBuffer
     282: dup
     283: invokespecial #23                 // Method java/lang/StringBuffer."<init>":()V
     286: ldc           #202                // String () == null ? 0 :
     288: invokevirtual #25                 // Method java/lang/StringBuffer.append:(Ljava/lang/String;)Ljava/lang/StringBuffer;
     291: aload_0
     292: ldc           #86                 // String java.util.Arrays
     294: invokevirtual #87                 // Method importType:(Ljava/lang/String;)Ljava/lang/String;
     297: invokevirtual #25                 // Method java/lang/StringBuffer.append:(Ljava/lang/String;)Ljava/lang/StringBuffer;
     300: ldc           #203                // String .hashCode(
     302: invokevirtual #25                 // Method java/lang/StringBuffer.append:(Ljava/lang/String;)Ljava/lang/StringBuffer;
     305: invokevirtual #27                 // Method java/lang/StringBuffer.toString:()Ljava/lang/String;
     308: invokevirtual #25                 // Method java/lang/StringBuffer.append:(Ljava/lang/String;)Ljava/lang/StringBuffer;
     311: aload_3
     312: invokevirtual #25                 // Method java/lang/StringBuffer.append:(Ljava/lang/String;)Ljava/lang/StringBuffer;
     315: ldc           #37                 // String .
     317: invokevirtual #25                 // Method java/lang/StringBuffer.append:(Ljava/lang/String;)Ljava/lang/StringBuffer;
     320: aload_0
     321: aload_1
     322: invokevirtual #65                 // Method getGetterSignature:(Lorg/hibernate/mapping/Property;)Ljava/lang/String;
     325: invokevirtual #25                 // Method java/lang/StringBuffer.append:(Ljava/lang/String;)Ljava/lang/StringBuffer;
     328: ldc           #204                // String ())
     330: invokevirtual #25                 // Method java/lang/StringBuffer.append:(Ljava/lang/String;)Ljava/lang/StringBuffer;
     333: ldc           #205                // String  )
     335: invokevirtual #25                 // Method java/lang/StringBuffer.append:(Ljava/lang/String;)Ljava/lang/StringBuffer;
     338: ldc           #26                 // String ;
     340: invokevirtual #25                 // Method java/lang/StringBuffer.append:(Ljava/lang/String;)Ljava/lang/StringBuffer;
     343: pop
     344: goto          444
     347: aload         5
     349: aload_0
     350: aload_1
     351: aload         6
     353: aload_2
     354: aload_3
     355: invokespecial #206                // Method internalGenerateArrayHashcode:(Lorg/hibernate/mapping/Property;Ljava/lang/String;Ljava/lang/String;Ljava/lang/String;)Ljava/lang/String;
     358: invokevirtual #25                 // Method java/lang/StringBuffer.append:(Ljava/lang/String;)Ljava/lang/StringBuffer;
     361: pop
     362: goto          444
     365: aload         5
     367: aload_2
     368: invokevirtual #25                 // Method java/lang/StringBuffer.append:(Ljava/lang/String;)Ljava/lang/StringBuffer;
     371: ldc           #193                // String  = 37 *
     373: invokevirtual #25                 // Method java/lang/StringBuffer.append:(Ljava/lang/String;)Ljava/lang/StringBuffer;
     376: aload_2
     377: invokevirtual #25                 // Method java/lang/StringBuffer.append:(Ljava/lang/String;)Ljava/lang/StringBuffer;
     380: ldc           #194                // String  +
     382: invokevirtual #25                 // Method java/lang/StringBuffer.append:(Ljava/lang/String;)Ljava/lang/StringBuffer;
     385: pop
     386: aload         5
     388: ldc           #201                // String (
     390: invokevirtual #25                 // Method java/lang/StringBuffer.append:(Ljava/lang/String;)Ljava/lang/StringBuffer;
     393: aload_0
     394: aload_1
     395: invokevirtual #65                 // Method getGetterSignature:(Lorg/hibernate/mapping/Property;)Ljava/lang/String;
     398: invokevirtual #25                 // Method java/lang/StringBuffer.append:(Ljava/lang/String;)Ljava/lang/StringBuffer;
     401: ldc           #202                // String () == null ? 0 :
     403: invokevirtual #25                 // Method java/lang/StringBuffer.append:(Ljava/lang/String;)Ljava/lang/StringBuffer;
     406: aload_3
     407: invokevirtual #25                 // Method java/lang/StringBuffer.append:(Ljava/lang/String;)Ljava/lang/StringBuffer;
     410: ldc           #37                 // String .
     412: invokevirtual #25                 // Method java/lang/StringBuffer.append:(Ljava/lang/String;)Ljava/lang/StringBuffer;
     415: aload_0
     416: aload_1
     417: invokevirtual #65                 // Method getGetterSignature:(Lorg/hibernate/mapping/Property;)Ljava/lang/String;
     420: invokevirtual #25                 // Method java/lang/StringBuffer.append:(Ljava/lang/String;)Ljava/lang/StringBuffer;
     423: ldc           #66                 // String ()
     425: invokevirtual #25                 // Method java/lang/StringBuffer.append:(Ljava/lang/String;)Ljava/lang/StringBuffer;
     428: ldc           #207                // String .hashCode()
     430: invokevirtual #25                 // Method java/lang/StringBuffer.append:(Ljava/lang/String;)Ljava/lang/StringBuffer;
     433: ldc           #205                // String  )
     435: invokevirtual #25                 // Method java/lang/StringBuffer.append:(Ljava/lang/String;)Ljava/lang/StringBuffer;
     438: ldc           #26                 // String ;
     440: invokevirtual #25                 // Method java/lang/StringBuffer.append:(Ljava/lang/String;)Ljava/lang/StringBuffer;
     443: pop
     444: aload         5
     446: invokevirtual #27                 // Method java/lang/StringBuffer.toString:()Ljava/lang/String;
     449: areturn

  private java.lang.String internalGenerateArrayHashcode(org.hibernate.mapping.Property, java.lang.String, java.lang.String, java.lang.String);
    Code:
       0: new           #22                 // class java/lang/StringBuffer
       3: dup
       4: invokespecial #23                 // Method java/lang/StringBuffer."<init>":()V
       7: astore        5
       9: new           #22                 // class java/lang/StringBuffer
      12: dup
      13: invokespecial #23                 // Method java/lang/StringBuffer."<init>":()V
      16: aload_1
      17: invokevirtual #140                // Method org/hibernate/mapping/Property.getName:()Ljava/lang/String;
      20: invokevirtual #25                 // Method java/lang/StringBuffer.append:(Ljava/lang/String;)Ljava/lang/StringBuffer;
      23: ldc           #208                // String Hashcode
      25: invokevirtual #25                 // Method java/lang/StringBuffer.append:(Ljava/lang/String;)Ljava/lang/StringBuffer;
      28: invokevirtual #27                 // Method java/lang/StringBuffer.toString:()Ljava/lang/String;
      31: astore        6
      33: new           #22                 // class java/lang/StringBuffer
      36: dup
      37: invokespecial #23                 // Method java/lang/StringBuffer."<init>":()V
      40: aload_1
      41: invokevirtual #140                // Method org/hibernate/mapping/Property.getName:()Ljava/lang/String;
      44: invokevirtual #25                 // Method java/lang/StringBuffer.append:(Ljava/lang/String;)Ljava/lang/StringBuffer;
      47: ldc           #209                // String Property
      49: invokevirtual #25                 // Method java/lang/StringBuffer.append:(Ljava/lang/String;)Ljava/lang/StringBuffer;
      52: invokevirtual #27                 // Method java/lang/StringBuffer.toString:()Ljava/lang/String;
      55: astore        7
      57: aload         5
      59: ldc           #210                // String int
      61: invokevirtual #25                 // Method java/lang/StringBuffer.append:(Ljava/lang/String;)Ljava/lang/StringBuffer;
      64: aload         6
      66: invokevirtual #25                 // Method java/lang/StringBuffer.append:(Ljava/lang/String;)Ljava/lang/StringBuffer;
      69: ldc           #211                // String  = 0;\n
      71: invokevirtual #25                 // Method java/lang/StringBuffer.append:(Ljava/lang/String;)Ljava/lang/StringBuffer;
      74: pop
      75: aload         5
      77: ldc           #212                // String
      79: invokevirtual #25                 // Method java/lang/StringBuffer.append:(Ljava/lang/String;)Ljava/lang/StringBuffer;
      82: aload_2
      83: invokevirtual #25                 // Method java/lang/StringBuffer.append:(Ljava/lang/String;)Ljava/lang/StringBuffer;
      86: ldc           #213                // String
      88: invokevirtual #25                 // Method java/lang/StringBuffer.append:(Ljava/lang/String;)Ljava/lang/StringBuffer;
      91: aload         7
      93: invokevirtual #25                 // Method java/lang/StringBuffer.append:(Ljava/lang/String;)Ljava/lang/StringBuffer;
      96: ldc           #214                // String  =
      98: invokevirtual #25                 // Method java/lang/StringBuffer.append:(Ljava/lang/String;)Ljava/lang/StringBuffer;
     101: aload         4
     103: invokevirtual #25                 // Method java/lang/StringBuffer.append:(Ljava/lang/String;)Ljava/lang/StringBuffer;
     106: ldc           #37                 // String .
     108: invokevirtual #25                 // Method java/lang/StringBuffer.append:(Ljava/lang/String;)Ljava/lang/StringBuffer;
     111: aload_0
     112: aload_1
     113: invokevirtual #65                 // Method getGetterSignature:(Lorg/hibernate/mapping/Property;)Ljava/lang/String;
     116: invokevirtual #25                 // Method java/lang/StringBuffer.append:(Ljava/lang/String;)Ljava/lang/StringBuffer;
     119: ldc           #215                // String ();\n
     121: invokevirtual #25                 // Method java/lang/StringBuffer.append:(Ljava/lang/String;)Ljava/lang/StringBuffer;
     124: pop
     125: aload         5
     127: ldc           #216                // String          if(
     129: invokevirtual #25                 // Method java/lang/StringBuffer.append:(Ljava/lang/String;)Ljava/lang/StringBuffer;
     132: aload         7
     134: invokevirtual #25                 // Method java/lang/StringBuffer.append:(Ljava/lang/String;)Ljava/lang/StringBuffer;
     137: ldc           #217                // String  != null) {\n
     139: invokevirtual #25                 // Method java/lang/StringBuffer.append:(Ljava/lang/String;)Ljava/lang/StringBuffer;
     142: pop
     143: aload         5
     145: ldc           #218                // String
     147: invokevirtual #25                 // Method java/lang/StringBuffer.append:(Ljava/lang/String;)Ljava/lang/StringBuffer;
     150: aload         6
     152: invokevirtual #25                 // Method java/lang/StringBuffer.append:(Ljava/lang/String;)Ljava/lang/StringBuffer;
     155: ldc           #219                // String  = 1;\n
     157: invokevirtual #25                 // Method java/lang/StringBuffer.append:(Ljava/lang/String;)Ljava/lang/StringBuffer;
     160: pop
     161: aload_2
     162: ldc           #220                // String \\[\\]
     164: ldc           #35                 // String
     166: invokevirtual #221                // Method java/lang/String.replaceAll:(Ljava/lang/String;Ljava/lang/String;)Ljava/lang/String;
     169: astore        8
     171: aload         5
     173: ldc           #222                // String              for (int i=0; i<
     175: invokevirtual #25                 // Method java/lang/StringBuffer.append:(Ljava/lang/String;)Ljava/lang/StringBuffer;
     178: aload         7
     180: invokevirtual #25                 // Method java/lang/StringBuffer.append:(Ljava/lang/String;)Ljava/lang/StringBuffer;
     183: ldc           #223                // String .length; i++) {\n
     185: invokevirtual #25                 // Method java/lang/StringBuffer.append:(Ljava/lang/String;)Ljava/lang/StringBuffer;
     188: pop
     189: aload_2
     190: ldc           #224                // String long
     192: invokevirtual #225                // Method java/lang/String.startsWith:(Ljava/lang/String;)Z
     195: ifeq          257
     198: aload         5
     200: ldc           #226                // String                  int elementHash = (int)(
     202: invokevirtual #25                 // Method java/lang/StringBuffer.append:(Ljava/lang/String;)Ljava/lang/StringBuffer;
     205: aload         7
     207: invokevirtual #25                 // Method java/lang/StringBuffer.append:(Ljava/lang/String;)Ljava/lang/StringBuffer;
     210: ldc           #227                // String [i] ^ (
     212: invokevirtual #25                 // Method java/lang/StringBuffer.append:(Ljava/lang/String;)Ljava/lang/StringBuffer;
     215: aload         7
     217: invokevirtual #25                 // Method java/lang/StringBuffer.append:(Ljava/lang/String;)Ljava/lang/StringBuffer;
     220: ldc           #228                // String [i] >>> 32));\n
     222: invokevirtual #25                 // Method java/lang/StringBuffer.append:(Ljava/lang/String;)Ljava/lang/StringBuffer;
     225: pop
     226: aload         5
     228: ldc           #229                // String
     230: invokevirtual #25                 // Method java/lang/StringBuffer.append:(Ljava/lang/String;)Ljava/lang/StringBuffer;
     233: aload         6
     235: invokevirtual #25                 // Method java/lang/StringBuffer.append:(Ljava/lang/String;)Ljava/lang/StringBuffer;
     238: ldc           #193                // String  = 37 *
     240: invokevirtual #25                 // Method java/lang/StringBuffer.append:(Ljava/lang/String;)Ljava/lang/StringBuffer;
     243: aload         6
     245: invokevirtual #25                 // Method java/lang/StringBuffer.append:(Ljava/lang/String;)Ljava/lang/StringBuffer;
     248: ldc           #230                // String  + elementHash;\n
     250: invokevirtual #25                 // Method java/lang/StringBuffer.append:(Ljava/lang/String;)Ljava/lang/StringBuffer;
     253: pop
     254: goto          530
     257: aload_2
     258: ldc           #182                // String boolean
     260: invokevirtual #225                // Method java/lang/String.startsWith:(Ljava/lang/String;)Z
     263: ifeq          307
     266: aload         5
     268: ldc           #229                // String
     270: invokevirtual #25                 // Method java/lang/StringBuffer.append:(Ljava/lang/String;)Ljava/lang/StringBuffer;
     273: aload         6
     275: invokevirtual #25                 // Method java/lang/StringBuffer.append:(Ljava/lang/String;)Ljava/lang/StringBuffer;
     278: ldc           #193                // String  = 37 *
     280: invokevirtual #25                 // Method java/lang/StringBuffer.append:(Ljava/lang/String;)Ljava/lang/StringBuffer;
     283: aload         6
     285: invokevirtual #25                 // Method java/lang/StringBuffer.append:(Ljava/lang/String;)Ljava/lang/StringBuffer;
     288: ldc           #231                // String  + (
     290: invokevirtual #25                 // Method java/lang/StringBuffer.append:(Ljava/lang/String;)Ljava/lang/StringBuffer;
     293: aload         7
     295: invokevirtual #25                 // Method java/lang/StringBuffer.append:(Ljava/lang/String;)Ljava/lang/StringBuffer;
     298: ldc           #232                // String [i] ? 1231 : 1237);\n
     300: invokevirtual #25                 // Method java/lang/StringBuffer.append:(Ljava/lang/String;)Ljava/lang/StringBuffer;
     303: pop
     304: goto          530
     307: aload_2
     308: ldc           #233                // String float
     310: invokevirtual #225                // Method java/lang/String.startsWith:(Ljava/lang/String;)Z
     313: ifeq          357
     316: aload         5
     318: ldc           #229                // String
     320: invokevirtual #25                 // Method java/lang/StringBuffer.append:(Ljava/lang/String;)Ljava/lang/StringBuffer;
     323: aload         6
     325: invokevirtual #25                 // Method java/lang/StringBuffer.append:(Ljava/lang/String;)Ljava/lang/StringBuffer;
     328: ldc           #193                // String  = 37 *
     330: invokevirtual #25                 // Method java/lang/StringBuffer.append:(Ljava/lang/String;)Ljava/lang/StringBuffer;
     333: aload         6
     335: invokevirtual #25                 // Method java/lang/StringBuffer.append:(Ljava/lang/String;)Ljava/lang/StringBuffer;
     338: ldc           #234                // String  + Float.floatToIntBits(
     340: invokevirtual #25                 // Method java/lang/StringBuffer.append:(Ljava/lang/String;)Ljava/lang/StringBuffer;
     343: aload         7
     345: invokevirtual #25                 // Method java/lang/StringBuffer.append:(Ljava/lang/String;)Ljava/lang/StringBuffer;
     348: ldc           #235                // String [i]);\n
     350: invokevirtual #25                 // Method java/lang/StringBuffer.append:(Ljava/lang/String;)Ljava/lang/StringBuffer;
     353: pop
     354: goto          530
     357: aload_2
     358: ldc           #236                // String double
     360: invokevirtual #225                // Method java/lang/String.startsWith:(Ljava/lang/String;)Z
     363: ifeq          415
     366: aload         5
     368: ldc           #237                // String                  long bits = Double.doubleToLongBits(
     370: invokevirtual #25                 // Method java/lang/StringBuffer.append:(Ljava/lang/String;)Ljava/lang/StringBuffer;
     373: aload         7
     375: invokevirtual #25                 // Method java/lang/StringBuffer.append:(Ljava/lang/String;)Ljava/lang/StringBuffer;
     378: ldc           #235                // String [i]);\n
     380: invokevirtual #25                 // Method java/lang/StringBuffer.append:(Ljava/lang/String;)Ljava/lang/StringBuffer;
     383: pop
     384: aload         5
     386: ldc           #229                // String
     388: invokevirtual #25                 // Method java/lang/StringBuffer.append:(Ljava/lang/String;)Ljava/lang/StringBuffer;
     391: aload         6
     393: invokevirtual #25                 // Method java/lang/StringBuffer.append:(Ljava/lang/String;)Ljava/lang/StringBuffer;
     396: ldc           #193                // String  = 37 *
     398: invokevirtual #25                 // Method java/lang/StringBuffer.append:(Ljava/lang/String;)Ljava/lang/StringBuffer;
     401: aload         6
     403: invokevirtual #25                 // Method java/lang/StringBuffer.append:(Ljava/lang/String;)Ljava/lang/StringBuffer;
     406: ldc           #238                // String  + (int)(bits ^ (bits >>> 32));\n
     408: invokevirtual #25                 // Method java/lang/StringBuffer.append:(Ljava/lang/String;)Ljava/lang/StringBuffer;
     411: pop
     412: goto          530
     415: aload_2
     416: ldc           #196                // String int
     418: invokevirtual #225                // Method java/lang/String.startsWith:(Ljava/lang/String;)Z
     421: ifne          451
     424: aload_2
     425: ldc           #197                // String short
     427: invokevirtual #225                // Method java/lang/String.startsWith:(Ljava/lang/String;)Z
     430: ifne          451
     433: aload_2
     434: ldc           #195                // String char
     436: invokevirtual #225                // Method java/lang/String.startsWith:(Ljava/lang/String;)Z
     439: ifne          451
     442: aload_2
     443: ldc           #198                // String byte
     445: invokevirtual #225                // Method java/lang/String.startsWith:(Ljava/lang/String;)Z
     448: ifeq          492
     451: aload         5
     453: ldc           #229                // String
     455: invokevirtual #25                 // Method java/lang/StringBuffer.append:(Ljava/lang/String;)Ljava/lang/StringBuffer;
     458: aload         6
     460: invokevirtual #25                 // Method java/lang/StringBuffer.append:(Ljava/lang/String;)Ljava/lang/StringBuffer;
     463: ldc           #193                // String  = 37 *
     465: invokevirtual #25                 // Method java/lang/StringBuffer.append:(Ljava/lang/String;)Ljava/lang/StringBuffer;
     468: aload         6
     470: invokevirtual #25                 // Method java/lang/StringBuffer.append:(Ljava/lang/String;)Ljava/lang/StringBuffer;
     473: ldc           #194                // String  +
     475: invokevirtual #25                 // Method java/lang/StringBuffer.append:(Ljava/lang/String;)Ljava/lang/StringBuffer;
     478: aload         7
     480: invokevirtual #25                 // Method java/lang/StringBuffer.append:(Ljava/lang/String;)Ljava/lang/StringBuffer;
     483: ldc           #239                // String [i];\n
     485: invokevirtual #25                 // Method java/lang/StringBuffer.append:(Ljava/lang/String;)Ljava/lang/StringBuffer;
     488: pop
     489: goto          530
     492: aload         5
     494: ldc           #229                // String
     496: invokevirtual #25                 // Method java/lang/StringBuffer.append:(Ljava/lang/String;)Ljava/lang/StringBuffer;
     499: aload         6
     501: invokevirtual #25                 // Method java/lang/StringBuffer.append:(Ljava/lang/String;)Ljava/lang/StringBuffer;
     504: ldc           #193                // String  = 37 *
     506: invokevirtual #25                 // Method java/lang/StringBuffer.append:(Ljava/lang/String;)Ljava/lang/StringBuffer;
     509: aload         6
     511: invokevirtual #25                 // Method java/lang/StringBuffer.append:(Ljava/lang/String;)Ljava/lang/StringBuffer;
     514: ldc           #194                // String  +
     516: invokevirtual #25                 // Method java/lang/StringBuffer.append:(Ljava/lang/String;)Ljava/lang/StringBuffer;
     519: aload         7
     521: invokevirtual #25                 // Method java/lang/StringBuffer.append:(Ljava/lang/String;)Ljava/lang/StringBuffer;
     524: ldc           #240                // String [i].hashCode();\n
     526: invokevirtual #25                 // Method java/lang/StringBuffer.append:(Ljava/lang/String;)Ljava/lang/StringBuffer;
     529: pop
     530: aload         5
     532: ldc           #241                // String              }\n
     534: invokevirtual #25                 // Method java/lang/StringBuffer.append:(Ljava/lang/String;)Ljava/lang/StringBuffer;
     537: pop
     538: aload         5
     540: ldc           #242                // String          }\n\n
     542: invokevirtual #25                 // Method java/lang/StringBuffer.append:(Ljava/lang/String;)Ljava/lang/StringBuffer;
     545: pop
     546: aload         5
     548: ldc           #212                // String
     550: invokevirtual #25                 // Method java/lang/StringBuffer.append:(Ljava/lang/String;)Ljava/lang/StringBuffer;
     553: aload_3
     554: invokevirtual #25                 // Method java/lang/StringBuffer.append:(Ljava/lang/String;)Ljava/lang/StringBuffer;
     557: ldc           #193                // String  = 37 *
     559: invokevirtual #25                 // Method java/lang/StringBuffer.append:(Ljava/lang/String;)Ljava/lang/StringBuffer;
     562: aload_3
     563: invokevirtual #25                 // Method java/lang/StringBuffer.append:(Ljava/lang/String;)Ljava/lang/StringBuffer;
     566: ldc           #194                // String  +
     568: invokevirtual #25                 // Method java/lang/StringBuffer.append:(Ljava/lang/String;)Ljava/lang/StringBuffer;
     571: aload         6
     573: invokevirtual #25                 // Method java/lang/StringBuffer.append:(Ljava/lang/String;)Ljava/lang/StringBuffer;
     576: ldc           #243                // String ;\n
     578: invokevirtual #25                 // Method java/lang/StringBuffer.append:(Ljava/lang/String;)Ljava/lang/StringBuffer;
     581: pop
     582: aload         5
     584: invokevirtual #27                 // Method java/lang/StringBuffer.toString:()Ljava/lang/String;
     587: areturn

  public java.lang.String getFieldModifiers(org.hibernate.mapping.Property);
    Code:
       0: aload_0
       1: aload_1
       2: ldc           #244                // String scope-field
       4: ldc           #245                // String private
       6: invokespecial #246                // Method getModifiers:(Lorg/hibernate/mapping/Property;Ljava/lang/String;Ljava/lang/String;)Ljava/lang/String;
       9: areturn

  public java.lang.String getPropertyGetModifiers(org.hibernate.mapping.Property);
    Code:
       0: aload_0
       1: aload_1
       2: ldc           #247                // String scope-get
       4: ldc           #50                 // String public
       6: invokespecial #246                // Method getModifiers:(Lorg/hibernate/mapping/Property;Ljava/lang/String;Ljava/lang/String;)Ljava/lang/String;
       9: areturn

  public java.lang.String getPropertySetModifiers(org.hibernate.mapping.Property);
    Code:
       0: aload_0
       1: aload_1
       2: ldc           #248                // String scope-set
       4: ldc           #50                 // String public
       6: invokespecial #246                // Method getModifiers:(Lorg/hibernate/mapping/Property;Ljava/lang/String;Ljava/lang/String;)Ljava/lang/String;
       9: areturn

  private java.lang.String getModifiers(org.hibernate.mapping.Property, java.lang.String, java.lang.String);
    Code:
       0: aload_1
       1: aload_2
       2: invokevirtual #179                // Method org/hibernate/mapping/Property.getMetaAttribute:(Ljava/lang/String;)Lorg/hibernate/mapping/MetaAttribute;
       5: astore        4
       7: aload         4
       9: ifnull        18
      12: aload         4
      14: invokestatic  #42                 // Method org/hibernate/tool/hbm2x/MetaAttributeHelper.getMetaAsString:(Lorg/hibernate/mapping/MetaAttribute;)Ljava/lang/String;
      17: areturn
      18: aload_3
      19: areturn

  protected boolean isRequiredInConstructor(org.hibernate.mapping.Property);
    Code:
       0: aload_0
       1: aload_1
       2: ldc           #249                // String default-value
       4: invokevirtual #250                // Method hasMetaAttribute:(Lorg/hibernate/mapping/MetaAttributable;Ljava/lang/String;)Z
       7: ifeq          12
      10: iconst_0
      11: ireturn
      12: aload_1
      13: invokevirtual #101                // Method org/hibernate/mapping/Property.getValue:()Lorg/hibernate/mapping/Value;
      16: ifnull        98
      19: aload_1
      20: invokevirtual #251                // Method org/hibernate/mapping/Property.isOptional:()Z
      23: ifne          41
      26: aload_1
      27: invokevirtual #252                // Method org/hibernate/mapping/Property.getGeneration:()Lorg/hibernate/mapping/PropertyGeneration;
      30: getstatic     #253                // Field org/hibernate/mapping/PropertyGeneration.NEVER:Lorg/hibernate/mapping/PropertyGeneration;
      33: invokevirtual #105                // Method java/lang/Object.equals:(Ljava/lang/Object;)Z
      36: ifeq          41
      39: iconst_1
      40: ireturn
      41: aload_1
      42: invokevirtual #101                // Method org/hibernate/mapping/Property.getValue:()Lorg/hibernate/mapping/Value;
      45: instanceof    #127                // class org/hibernate/mapping/Component
      48: ifeq          98
      51: aload_1
      52: invokevirtual #101                // Method org/hibernate/mapping/Property.getValue:()Lorg/hibernate/mapping/Value;
      55: checkcast     #127                // class org/hibernate/mapping/Component
      58: astore_2
      59: aload_2
      60: invokevirtual #128                // Method org/hibernate/mapping/Component.getPropertyIterator:()Ljava/util/Iterator;
      63: astore_3
      64: aload_3
      65: invokeinterface #16,  1           // InterfaceMethod java/util/Iterator.hasNext:()Z
      70: ifeq          98
      73: aload_3
      74: invokeinterface #17,  1           // InterfaceMethod java/util/Iterator.next:()Ljava/lang/Object;
      79: checkcast     #61                 // class org/hibernate/mapping/Property
      82: astore        4
      84: aload_0
      85: aload         4
      87: invokevirtual #254                // Method isRequiredInConstructor:(Lorg/hibernate/mapping/Property;)Z
      90: ifeq          95
      93: iconst_1
      94: ireturn
      95: goto          64
      98: iconst_0
      99: ireturn

  public boolean needsMinimalConstructor();
    Code:
       0: aload_0
       1: invokevirtual #255                // Method getPropertyClosureForMinimalConstructor:()Ljava/util/List;
       4: astore_1
       5: aload_1
       6: invokeinterface #256,  1          // InterfaceMethod java/util/List.isEmpty:()Z
      11: ifeq          16
      14: iconst_0
      15: ireturn
      16: aload_1
      17: aload_0
      18: invokevirtual #257                // Method getPropertyClosureForFullConstructor:()Ljava/util/List;
      21: invokevirtual #105                // Method java/lang/Object.equals:(Ljava/lang/Object;)Z
      24: ifeq          29
      27: iconst_0
      28: ireturn
      29: iconst_1
      30: ireturn

  public boolean needsFullConstructor();
    Code:
       0: aload_0
       1: invokevirtual #257                // Method getPropertyClosureForFullConstructor:()Ljava/util/List;
       4: invokeinterface #256,  1          // InterfaceMethod java/util/List.isEmpty:()Z
       9: ifne          16
      12: iconst_1
      13: goto          17
      16: iconst_0
      17: ireturn

  public java.lang.String getJavaTypeName(org.hibernate.mapping.Property, boolean);
    Code:
       0: aload_0
       1: getfield      #3                  // Field c2j:Lorg/hibernate/tool/hbm2x/Cfg2JavaTool;
       4: aload_1
       5: iload_2
       6: aload_0
       7: invokevirtual #64                 // Method org/hibernate/tool/hbm2x/Cfg2JavaTool.getJavaTypeName:(Lorg/hibernate/mapping/Property;ZLorg/hibernate/tool/hbm2x/pojo/ImportContext;)Ljava/lang/String;
      10: areturn

  public boolean hasFieldInitializor(org.hibernate.mapping.Property, boolean);
    Code:
       0: aload_0
       1: aload_1
       2: iload_2
       3: invokevirtual #258                // Method getFieldInitialization:(Lorg/hibernate/mapping/Property;Z)Ljava/lang/String;
       6: ifnull        13
       9: iconst_1
      10: goto          14
      13: iconst_0
      14: ireturn

  public java.lang.String getFieldInitialization(org.hibernate.mapping.Property, boolean);
    Code:
       0: aload_0
       1: aload_1
       2: ldc           #249                // String default-value
       4: invokevirtual #250                // Method hasMetaAttribute:(Lorg/hibernate/mapping/MetaAttributable;Ljava/lang/String;)Z
       7: ifeq          20
      10: aload_1
      11: ldc           #249                // String default-value
      13: invokevirtual #179                // Method org/hibernate/mapping/Property.getMetaAttribute:(Ljava/lang/String;)Lorg/hibernate/mapping/MetaAttribute;
      16: invokestatic  #42                 // Method org/hibernate/tool/hbm2x/MetaAttributeHelper.getMetaAsString:(Lorg/hibernate/mapping/MetaAttribute;)Ljava/lang/String;
      19: areturn
      20: aload_0
      21: getfield      #3                  // Field c2j:Lorg/hibernate/tool/hbm2x/Cfg2JavaTool;
      24: aload_1
      25: iconst_0
      26: invokevirtual #181                // Method org/hibernate/tool/hbm2x/Cfg2JavaTool.getJavaTypeName:(Lorg/hibernate/mapping/Property;Z)Ljava/lang/String;
      29: ifnonnull     40
      32: new           #4                  // class java/lang/IllegalArgumentException
      35: dup
      36: invokespecial #259                // Method java/lang/IllegalArgumentException."<init>":()V
      39: athrow
      40: aload_1
      41: invokevirtual #101                // Method org/hibernate/mapping/Property.getValue:()Lorg/hibernate/mapping/Value;
      44: instanceof    #260                // class org/hibernate/mapping/Collection
      47: ifeq          138
      50: aload_1
      51: invokevirtual #101                // Method org/hibernate/mapping/Property.getValue:()Lorg/hibernate/mapping/Value;
      54: checkcast     #260                // class org/hibernate/mapping/Collection
      57: astore_3
      58: aload_3
      59: new           #261                // class org/hibernate/tool/hbm2x/pojo/BasicPOJOClass$1
      62: dup
      63: aload_0
      64: iconst_1
      65: invokespecial #262                // Method org/hibernate/tool/hbm2x/pojo/BasicPOJOClass$1."<init>":(Lorg/hibernate/tool/hbm2x/pojo/BasicPOJOClass;Z)V
      68: invokevirtual #263                // Method org/hibernate/mapping/Collection.accept:(Lorg/hibernate/mapping/ValueVisitor;)Ljava/lang/Object;
      71: checkcast     #264                // class org/hibernate/tool/hbm2x/pojo/BasicPOJOClass$DefaultInitializor
      74: astore        4
      76: aload         4
      78: ifnull        136
      81: aconst_null
      82: astore        5
      84: aconst_null
      85: astore        6
      87: aload_3
      88: invokevirtual #265                // Method org/hibernate/mapping/Collection.isSorted:()Z
      91: ifeq          100
      94: aload_3
      95: invokevirtual #266                // Method org/hibernate/mapping/Collection.getComparatorClassName:()Ljava/lang/String;
      98: astore        5
     100: iload_2
     101: ifeq          125
     104: aload_0
     105: getfield      #3                  // Field c2j:Lorg/hibernate/tool/hbm2x/Cfg2JavaTool;
     108: aload_1
     109: invokevirtual #101                // Method org/hibernate/mapping/Property.getValue:()Lorg/hibernate/mapping/Value;
     112: checkcast     #260                // class org/hibernate/mapping/Collection
     115: iconst_1
     116: aload_0
     117: getfield      #11                 // Field importContext:Lorg/hibernate/tool/hbm2x/pojo/ImportContext;
     120: invokevirtual #267                // Method org/hibernate/tool/hbm2x/Cfg2JavaTool.getGenericCollectionDeclaration:(Lorg/hibernate/mapping/Collection;ZLorg/hibernate/tool/hbm2x/pojo/ImportContext;)Ljava/lang/String;
     123: astore        6
     125: aload         4
     127: aload         5
     129: aload         6
     131: aload_0
     132: invokevirtual #268                // Method org/hibernate/tool/hbm2x/pojo/BasicPOJOClass$DefaultInitializor.getDefaultValue:(Ljava/lang/String;Ljava/lang/String;Lorg/hibernate/tool/hbm2x/pojo/ImportContext;)Ljava/lang/String;
     135: areturn
     136: aconst_null
     137: areturn
     138: aconst_null
     139: areturn

  static {};
    Code:
       0: new           #269                // class java/util/HashMap
       3: dup
       4: invokespecial #270                // Method java/util/HashMap."<init>":()V
       7: putstatic     #271                // Field defaultInitializors:Ljava/util/Map;
      10: getstatic     #271                // Field defaultInitializors:Ljava/util/Map;
      13: ldc_w         #272                // String java.util.List
      16: new           #264                // class org/hibernate/tool/hbm2x/pojo/BasicPOJOClass$DefaultInitializor
      19: dup
      20: ldc_w         #273                // String java.util.ArrayList
      23: iconst_1
      24: invokespecial #274                // Method org/hibernate/tool/hbm2x/pojo/BasicPOJOClass$DefaultInitializor."<init>":(Ljava/lang/String;Z)V
      27: invokeinterface #275,  3          // InterfaceMethod java/util/Map.put:(Ljava/lang/Object;Ljava/lang/Object;)Ljava/lang/Object;
      32: pop
      33: getstatic     #271                // Field defaultInitializors:Ljava/util/Map;
      36: ldc_w         #276                // String java.util.Map
      39: new           #264                // class org/hibernate/tool/hbm2x/pojo/BasicPOJOClass$DefaultInitializor
      42: dup
      43: ldc_w         #277                // String java.util.HashMap
      46: iconst_1
      47: invokespecial #274                // Method org/hibernate/tool/hbm2x/pojo/BasicPOJOClass$DefaultInitializor."<init>":(Ljava/lang/String;Z)V
      50: invokeinterface #275,  3          // InterfaceMethod java/util/Map.put:(Ljava/lang/Object;Ljava/lang/Object;)Ljava/lang/Object;
      55: pop
      56: getstatic     #271                // Field defaultInitializors:Ljava/util/Map;
      59: ldc_w         #278                // String java.util.Set
      62: new           #264                // class org/hibernate/tool/hbm2x/pojo/BasicPOJOClass$DefaultInitializor
      65: dup
      66: ldc_w         #279                // String java.util.HashSet
      69: iconst_1
      70: invokespecial #274                // Method org/hibernate/tool/hbm2x/pojo/BasicPOJOClass$DefaultInitializor."<init>":(Ljava/lang/String;Z)V
      73: invokeinterface #275,  3          // InterfaceMethod java/util/Map.put:(Ljava/lang/Object;Ljava/lang/Object;)Ljava/lang/Object;
      78: pop
      79: getstatic     #271                // Field defaultInitializors:Ljava/util/Map;
      82: ldc_w         #280                // String java.util.SortedSet
      85: new           #264                // class org/hibernate/tool/hbm2x/pojo/BasicPOJOClass$DefaultInitializor
      88: dup
      89: ldc_w         #281                // String java.util.TreeSet
      92: iconst_0
      93: invokespecial #274                // Method org/hibernate/tool/hbm2x/pojo/BasicPOJOClass$DefaultInitializor."<init>":(Ljava/lang/String;Z)V
      96: invokeinterface #275,  3          // InterfaceMethod java/util/Map.put:(Ljava/lang/Object;Ljava/lang/Object;)Ljava/lang/Object;
     101: pop
     102: getstatic     #271                // Field defaultInitializors:Ljava/util/Map;
     105: ldc_w         #282                // String java.util.SortedMap
     108: new           #264                // class org/hibernate/tool/hbm2x/pojo/BasicPOJOClass$DefaultInitializor
     111: dup
     112: ldc_w         #283                // String java.util.TreeMap
     115: iconst_0
     116: invokespecial #274                // Method org/hibernate/tool/hbm2x/pojo/BasicPOJOClass$DefaultInitializor."<init>":(Ljava/lang/String;Z)V
     119: invokeinterface #275,  3          // InterfaceMethod java/util/Map.put:(Ljava/lang/Object;Ljava/lang/Object;)Ljava/lang/Object;
     124: pop
     125: return
}
