Compiled from "HashAlgorithmIdentifier.java"
public class org.sonatype.spice.zapper.hash.HashAlgorithmIdentifier extends org.sonatype.spice.zapper.internal.StringIdentifier {
  private final int hashSizeInBytes;

  public org.sonatype.spice.zapper.hash.HashAlgorithmIdentifier(java.lang.String, int);
    Code:
       0: aload_0
       1: aload_1
       2: invokespecial #1                  // Method org/sonatype/spice/zapper/internal/StringIdentifier."<init>":(Ljava/lang/String;)V
       5: aload_0
       6: iload_2
       7: ifle          14
      10: iconst_1
      11: goto          15
      14: iconst_0
      15: iload_2
      16: invokestatic  #2                  // Method java/lang/Integer.valueOf:(I)Ljava/lang/Integer;
      19: ldc           #3                  // String Hash size not positive!
      21: invokestatic  #4                  // Method org/sonatype/spice/zapper/internal/Check.argument:(ZLjava/lang/Object;Ljava/lang/Object;)Ljava/lang/Object;
      24: checkcast     #5                  // class java/lang/Integer
      27: invokevirtual #6                  // Method java/lang/Integer.intValue:()I
      30: putfield      #7                  // Field hashSizeInBytes:I
      33: return

  public int getHashSize();
    Code:
       0: aload_0
       1: getfield      #7                  // Field hashSizeInBytes:I
       4: ireturn
}
