Compiled from "BaseRepositoryUtils.java"
final class org.leo.aws.ddb.repositories.BaseRepositoryUtils extends java.lang.Enum<org.leo.aws.ddb.repositories.BaseRepositoryUtils> {
  public static final org.leo.aws.ddb.repositories.BaseRepositoryUtils INSTANCE;

  private final java.util.concurrent.ConcurrentHashMap<java.lang.String, java.lang.Class<?>> repoParameterTypeMap;

  private static final org.slf4j.Logger LOGGER;

  private static final org.leo.aws.ddb.repositories.BaseRepositoryUtils[] ENUM$VALUES;

  static {};
    Code:
       0: new           #1                  // class org/leo/aws/ddb/repositories/BaseRepositoryUtils
       3: dup
       4: ldc           #18                 // String INSTANCE
       6: iconst_0
       7: invokespecial #19                 // Method "<init>":(Ljava/lang/String;I)V
      10: putstatic     #23                 // Field INSTANCE:Lorg/leo/aws/ddb/repositories/BaseRepositoryUtils;
      13: iconst_1
      14: anewarray     #1                  // class org/leo/aws/ddb/repositories/BaseRepositoryUtils
      17: dup
      18: iconst_0
      19: getstatic     #23                 // Field INSTANCE:Lorg/leo/aws/ddb/repositories/BaseRepositoryUtils;
      22: aastore
      23: putstatic     #25                 // Field ENUM$VALUES:[Lorg/leo/aws/ddb/repositories/BaseRepositoryUtils;
      26: ldc           #1                  // class org/leo/aws/ddb/repositories/BaseRepositoryUtils
      28: invokestatic  #27                 // Method org/slf4j/LoggerFactory.getLogger:(Ljava/lang/Class;)Lorg/slf4j/Logger;
      31: putstatic     #33                 // Field LOGGER:Lorg/slf4j/Logger;
      34: return

  private org.leo.aws.ddb.repositories.BaseRepositoryUtils(java.lang.String, int);
    Code:
       0: aload_0
       1: aload_1
       2: iload_2
       3: invokespecial #37                 // Method java/lang/Enum."<init>":(Ljava/lang/String;I)V
       6: aload_0
       7: new           #38                 // class java/util/concurrent/ConcurrentHashMap
      10: dup
      11: invokespecial #40                 // Method java/util/concurrent/ConcurrentHashMap."<init>":()V
      14: putfield      #42                 // Field repoParameterTypeMap:Ljava/util/concurrent/ConcurrentHashMap;
      17: return

  static org.leo.aws.ddb.repositories.BaseRepositoryUtils getInstance();
    Code:
       0: getstatic     #23                 // Field INSTANCE:Lorg/leo/aws/ddb/repositories/BaseRepositoryUtils;
       3: areturn

  software.amazon.awssdk.services.dynamodb.model.UpdateItemResponse handleUpdateItemException(org.leo.aws.ddb.data.PrimaryKey, java.lang.String, java.lang.Throwable);
    Code:
       0: getstatic     #33                 // Field LOGGER:Lorg/slf4j/Logger;
       3: ldc           #50                 // String Record with the following primary key [{0}] exists in table [{1}]
       5: iconst_2
       6: anewarray     #52                 // class java/lang/Object
       9: dup
      10: iconst_0
      11: aload_1
      12: aastore
      13: dup
      14: iconst_1
      15: aload_2
      16: aastore
      17: invokestatic  #54                 // Method java/text/MessageFormat.format:(Ljava/lang/String;[Ljava/lang/Object;)Ljava/lang/String;
      20: aload_3
      21: invokeinterface #60,  3           // InterfaceMethod org/slf4j/Logger.debug:(Ljava/lang/String;Ljava/lang/Throwable;)V
      26: aload_3
      27: instanceof    #66                 // class java/util/concurrent/CompletionException
      30: ifeq          55
      33: aload_3
      34: invokevirtual #68                 // Method java/lang/Throwable.getCause:()Ljava/lang/Throwable;
      37: instanceof    #74                 // class software/amazon/awssdk/services/dynamodb/model/ConditionalCheckFailedException
      40: ifeq          55
      43: new           #76                 // class org/leo/aws/ddb/exceptions/OptimisticLockFailureException
      46: dup
      47: aload_3
      48: invokevirtual #68                 // Method java/lang/Throwable.getCause:()Ljava/lang/Throwable;
      51: invokespecial #78                 // Method org/leo/aws/ddb/exceptions/OptimisticLockFailureException."<init>":(Ljava/lang/Throwable;)V
      54: athrow
      55: aload_3
      56: instanceof    #81                 // class java/lang/RuntimeException
      59: ifeq          67
      62: aload_3
      63: checkcast     #81                 // class java/lang/RuntimeException
      66: athrow
      67: new           #83                 // class org/leo/aws/ddb/exceptions/DbException
      70: dup
      71: new           #85                 // class java/lang/StringBuilder
      74: dup
      75: getstatic     #87                 // Field org/leo/aws/ddb/utils/exceptions/Issue.UNKNOWN_ERROR:Lorg/leo/aws/ddb/utils/exceptions/Issue;
      78: invokevirtual #93                 // Method org/leo/aws/ddb/utils/exceptions/Issue.name:()Ljava/lang/String;
      81: invokestatic  #97                 // Method java/lang/String.valueOf:(Ljava/lang/Object;)Ljava/lang/String;
      84: invokespecial #103                // Method java/lang/StringBuilder."<init>":(Ljava/lang/String;)V
      87: ldc           #106                // String  - handleUpdateItemException
      89: invokevirtual #108                // Method java/lang/StringBuilder.append:(Ljava/lang/String;)Ljava/lang/StringBuilder;
      92: invokevirtual #112                // Method java/lang/StringBuilder.toString:()Ljava/lang/String;
      95: aload_3
      96: invokespecial #115                // Method org/leo/aws/ddb/exceptions/DbException."<init>":(Ljava/lang/String;Ljava/lang/Throwable;)V
      99: athrow

  <ENTITY_TYPE> java.lang.Integer setVersion(ENTITY_TYPE, org.leo.aws.ddb.utils.Tuple<java.lang.reflect.Field, org.leo.aws.ddb.annotations.DbAttribute>, software.amazon.awssdk.services.dynamodb.model.UpdateItemRequest$Builder);
    Code:
       0: aload_2
       1: ifnull        211
       4: aload_2
       5: invokevirtual #127                // Method org/leo/aws/ddb/utils/Tuple._1:()Ljava/lang/Object;
       8: checkcast     #133                // class java/lang/reflect/Field
      11: aload_1
      12: invokestatic  #135                // Method org/springframework/util/ReflectionUtils.getField:(Ljava/lang/reflect/Field;Ljava/lang/Object;)Ljava/lang/Object;
      15: checkcast     #141                // class java/lang/Number
      18: astore        5
      20: aload         5
      22: ifnull        35
      25: aload         5
      27: invokevirtual #143                // Method java/lang/Number.intValue:()I
      30: iconst_1
      31: iadd
      32: goto          36
      35: iconst_0
      36: invokestatic  #147                // Method java/lang/Integer.valueOf:(I)Ljava/lang/Integer;
      39: astore        4
      41: aload_2
      42: invokevirtual #127                // Method org/leo/aws/ddb/utils/Tuple._1:()Ljava/lang/Object;
      45: checkcast     #133                // class java/lang/reflect/Field
      48: invokevirtual #152                // Method java/lang/reflect/Field.getType:()Ljava/lang/Class;
      51: astore        6
      53: aload         5
      55: ifnonnull     103
      58: aload_3
      59: aload_2
      60: invokevirtual #156                // Method org/leo/aws/ddb/utils/Tuple._2:()Ljava/lang/Object;
      63: checkcast     #159                // class org/leo/aws/ddb/annotations/DbAttribute
      66: invokeinterface #161,  1          // InterfaceMethod org/leo/aws/ddb/annotations/DbAttribute.value:()Ljava/lang/String;
      71: invokestatic  #164                // Method software/amazon/awssdk/services/dynamodb/model/ExpectedAttributeValue.builder:()Lsoftware/amazon/awssdk/services/dynamodb/model/ExpectedAttributeValue$Builder;
      74: iconst_0
      75: invokestatic  #170                // Method java/lang/Boolean.valueOf:(Z)Ljava/lang/Boolean;
      78: invokeinterface #175,  2          // InterfaceMethod software/amazon/awssdk/services/dynamodb/model/ExpectedAttributeValue$Builder.exists:(Ljava/lang/Boolean;)Lsoftware/amazon/awssdk/services/dynamodb/model/ExpectedAttributeValue$Builder;
      83: invokeinterface #181,  1          // InterfaceMethod software/amazon/awssdk/services/dynamodb/model/ExpectedAttributeValue$Builder.build:()Ljava/lang/Object;
      88: checkcast     #165                // class software/amazon/awssdk/services/dynamodb/model/ExpectedAttributeValue
      91: invokestatic  #184                // Method com/google/common/collect/ImmutableMap.of:(Ljava/lang/Object;Ljava/lang/Object;)Lcom/google/common/collect/ImmutableMap;
      94: invokeinterface #190,  2          // InterfaceMethod software/amazon/awssdk/services/dynamodb/model/UpdateItemRequest$Builder.expected:(Ljava/util/Map;)Lsoftware/amazon/awssdk/services/dynamodb/model/UpdateItemRequest$Builder;
      99: pop
     100: goto          165
     103: aload_3
     104: aload_2
     105: invokevirtual #156                // Method org/leo/aws/ddb/utils/Tuple._2:()Ljava/lang/Object;
     108: checkcast     #159                // class org/leo/aws/ddb/annotations/DbAttribute
     111: invokeinterface #161,  1          // InterfaceMethod org/leo/aws/ddb/annotations/DbAttribute.value:()Ljava/lang/String;
     116: invokestatic  #164                // Method software/amazon/awssdk/services/dynamodb/model/ExpectedAttributeValue.builder:()Lsoftware/amazon/awssdk/services/dynamodb/model/ExpectedAttributeValue$Builder;
     119: invokestatic  #196                // Method software/amazon/awssdk/services/dynamodb/model/AttributeValue.builder:()Lsoftware/amazon/awssdk/services/dynamodb/model/AttributeValue$Builder;
     122: aload         5
     124: invokevirtual #143                // Method java/lang/Number.intValue:()I
     127: invokestatic  #201                // Method java/lang/String.valueOf:(I)Ljava/lang/String;
     130: invokeinterface #204,  2          // InterfaceMethod software/amazon/awssdk/services/dynamodb/model/AttributeValue$Builder.n:(Ljava/lang/String;)Lsoftware/amazon/awssdk/services/dynamodb/model/AttributeValue$Builder;
     135: invokeinterface #210,  1          // InterfaceMethod software/amazon/awssdk/services/dynamodb/model/AttributeValue$Builder.build:()Ljava/lang/Object;
     140: checkcast     #197                // class software/amazon/awssdk/services/dynamodb/model/AttributeValue
     143: invokeinterface #211,  2          // InterfaceMethod software/amazon/awssdk/services/dynamodb/model/ExpectedAttributeValue$Builder.value:(Lsoftware/amazon/awssdk/services/dynamodb/model/AttributeValue;)Lsoftware/amazon/awssdk/services/dynamodb/model/ExpectedAttributeValue$Builder;
     148: invokeinterface #181,  1          // InterfaceMethod software/amazon/awssdk/services/dynamodb/model/ExpectedAttributeValue$Builder.build:()Ljava/lang/Object;
     153: checkcast     #165                // class software/amazon/awssdk/services/dynamodb/model/ExpectedAttributeValue
     156: invokestatic  #184                // Method com/google/common/collect/ImmutableMap.of:(Ljava/lang/Object;Ljava/lang/Object;)Lcom/google/common/collect/ImmutableMap;
     159: invokeinterface #190,  2          // InterfaceMethod software/amazon/awssdk/services/dynamodb/model/UpdateItemRequest$Builder.expected:(Ljava/util/Map;)Lsoftware/amazon/awssdk/services/dynamodb/model/UpdateItemRequest$Builder;
     164: pop
     165: aload         6
     167: ldc           #148                // class java/lang/Integer
     169: if_acmpne     188
     172: aload_2
     173: invokevirtual #127                // Method org/leo/aws/ddb/utils/Tuple._1:()Ljava/lang/Object;
     176: checkcast     #133                // class java/lang/reflect/Field
     179: aload_1
     180: aload         4
     182: invokestatic  #214                // Method org/springframework/util/ReflectionUtils.setField:(Ljava/lang/reflect/Field;Ljava/lang/Object;Ljava/lang/Object;)V
     185: goto          214
     188: aload_2
     189: invokevirtual #127                // Method org/leo/aws/ddb/utils/Tuple._1:()Ljava/lang/Object;
     192: checkcast     #133                // class java/lang/reflect/Field
     195: aload_1
     196: aload         4
     198: invokevirtual #218                // Method java/lang/Integer.intValue:()I
     201: i2l
     202: invokestatic  #219                // Method java/lang/Long.valueOf:(J)Ljava/lang/Long;
     205: invokestatic  #214                // Method org/springframework/util/ReflectionUtils.setField:(Ljava/lang/reflect/Field;Ljava/lang/Object;Ljava/lang/Object;)V
     208: goto          214
     211: aconst_null
     212: astore        4
     214: aload         4
     216: areturn

  <ENTITY_TYPE> reactor.core.publisher.Flux<ENTITY_TYPE> batchWriteRequest(rx.functions.Func1<org.leo.aws.ddb.repositories.DataMapper<ENTITY_TYPE>, java.util.stream.Stream<software.amazon.awssdk.services.dynamodb.model.WriteRequest>>, rx.functions.Func0<java.util.List<ENTITY_TYPE>>, org.leo.aws.ddb.repositories.DataMapper<ENTITY_TYPE>);
    Code:
       0: aload_0
       1: aload_2
       2: aload_3
       3: aload_1
       4: invokedynamic #245,  0            // InvokeDynamic #0:get:(Lorg/leo/aws/ddb/repositories/BaseRepositoryUtils;Lrx/functions/Func0;Lorg/leo/aws/ddb/repositories/DataMapper;Lrx/functions/Func1;)Ljava/util/function/Supplier;
       9: invokestatic  #249                // Method reactor/core/publisher/Flux.defer:(Ljava/util/function/Supplier;)Lreactor/core/publisher/Flux;
      12: areturn

  <ENTITY_TYPE> reactor.core.publisher.Mono<ENTITY_TYPE> updateItem(org.leo.aws.ddb.data.PrimaryKey, java.util.Map<java.lang.String, java.lang.Object>, java.lang.Class<ENTITY_TYPE>, org.leo.aws.ddb.repositories.DataMapper<ENTITY_TYPE>, ENTITY_TYPE);
    Code:
       0: aload_0
       1: aload         4
       3: aload_3
       4: aload_2
       5: aload_1
       6: aload         5
       8: invokedynamic #267,  0            // InvokeDynamic #1:get:(Lorg/leo/aws/ddb/repositories/BaseRepositoryUtils;Lorg/leo/aws/ddb/repositories/DataMapper;Ljava/lang/Class;Ljava/util/Map;Lorg/leo/aws/ddb/data/PrimaryKey;Ljava/lang/Object;)Ljava/util/function/Supplier;
      13: invokestatic  #270                // Method reactor/core/publisher/Mono.defer:(Ljava/util/function/Supplier;)Lreactor/core/publisher/Mono;
      16: areturn

  <ENTITY_TYPE> reactor.core.publisher.Flux<ENTITY_TYPE> findByGlobalSecondaryIndex(java.lang.String, java.lang.Object, java.lang.Object, java.util.function.Function<ENTITY_TYPE, org.leo.aws.ddb.data.PrimaryKey>, java.util.function.Supplier<java.lang.Class<ENTITY_TYPE>>, java.util.function.Function<java.util.List<org.leo.aws.ddb.data.PrimaryKey>, reactor.core.publisher.Flux<ENTITY_TYPE>>, org.leo.aws.ddb.utils.Expr);
    Code:
       0: aload_0
       1: aload         6
       3: aload_2
       4: aload         5
       6: aload_3
       7: aload_1
       8: aload         7
      10: aload         4
      12: invokedynamic #283,  0            // InvokeDynamic #2:get:(Lorg/leo/aws/ddb/repositories/BaseRepositoryUtils;Ljava/util/function/Function;Ljava/lang/Object;Ljava/util/function/Supplier;Ljava/lang/Object;Ljava/lang/String;Lorg/leo/aws/ddb/utils/Expr;Ljava/util/function/Function;)Ljava/util/function/Supplier;
      17: invokestatic  #249                // Method reactor/core/publisher/Flux.defer:(Ljava/util/function/Supplier;)Lreactor/core/publisher/Flux;
      20: areturn

  <ENTITY_TYPE> reactor.core.publisher.Flux<ENTITY_TYPE> findAll(int, java.util.function.Supplier<java.lang.Class<ENTITY_TYPE>>);
    Code:
       0: aload_0
       1: aconst_null
       2: iload_1
       3: aload_2
       4: invokevirtual #302                // Method findAll:(Lorg/leo/aws/ddb/utils/Expr;ILjava/util/function/Supplier;)Lreactor/core/publisher/Flux;
       7: areturn

  <ENTITY_TYPE> reactor.core.publisher.Flux<ENTITY_TYPE> findAll(org.leo.aws.ddb.utils.Expr, int, java.util.function.Supplier<java.lang.Class<ENTITY_TYPE>>);
    Code:
       0: aload_3
       1: invokeinterface #308,  1          // InterfaceMethod java/util/function/Supplier.get:()Ljava/lang/Object;
       6: checkcast     #240                // class java/lang/Class
       9: invokestatic  #312                // Method org/leo/aws/ddb/repositories/DataMapperUtils.getDataMapper:(Ljava/lang/Class;)Lorg/leo/aws/ddb/repositories/DataMapper;
      12: astore        4
      14: invokestatic  #318                // Method software/amazon/awssdk/services/dynamodb/model/ScanRequest.builder:()Lsoftware/amazon/awssdk/services/dynamodb/model/ScanRequest$Builder;
      17: aload         4
      19: invokeinterface #323,  1          // InterfaceMethod org/leo/aws/ddb/repositories/DataMapper.tableName:()Ljava/lang/String;
      24: invokeinterface #327,  2          // InterfaceMethod software/amazon/awssdk/services/dynamodb/model/ScanRequest$Builder.tableName:(Ljava/lang/String;)Lsoftware/amazon/awssdk/services/dynamodb/model/ScanRequest$Builder;
      29: iload_2
      30: invokestatic  #147                // Method java/lang/Integer.valueOf:(I)Ljava/lang/Integer;
      33: invokeinterface #332,  2          // InterfaceMethod software/amazon/awssdk/services/dynamodb/model/ScanRequest$Builder.limit:(Ljava/lang/Integer;)Lsoftware/amazon/awssdk/services/dynamodb/model/ScanRequest$Builder;
      38: astore        5
      40: aload_1
      41: invokestatic  #336                // Method java/util/Objects.nonNull:(Ljava/lang/Object;)Z
      44: ifeq          113
      47: aload_1
      48: invokeinterface #342,  1          // InterfaceMethod org/leo/aws/ddb/utils/Expr.attributeNameMap:()Ljava/util/Map;
      53: astore        7
      55: aload_1
      56: invokeinterface #348,  1          // InterfaceMethod org/leo/aws/ddb/utils/Expr.attributeValueMap:()Ljava/util/Map;
      61: astore        8
      63: aload         5
      65: aload_1
      66: invokeinterface #351,  1          // InterfaceMethod org/leo/aws/ddb/utils/Expr.expression:()Ljava/lang/String;
      71: invokeinterface #354,  2          // InterfaceMethod software/amazon/awssdk/services/dynamodb/model/ScanRequest$Builder.filterExpression:(Ljava/lang/String;)Lsoftware/amazon/awssdk/services/dynamodb/model/ScanRequest$Builder;
      76: pop
      77: aload         7
      79: invokestatic  #356                // Method org/springframework/util/CollectionUtils.isEmpty:(Ljava/util/Map;)Z
      82: ifne          95
      85: aload         5
      87: aload         7
      89: invokeinterface #362,  2          // InterfaceMethod software/amazon/awssdk/services/dynamodb/model/ScanRequest$Builder.expressionAttributeNames:(Ljava/util/Map;)Lsoftware/amazon/awssdk/services/dynamodb/model/ScanRequest$Builder;
      94: pop
      95: aload         8
      97: invokestatic  #356                // Method org/springframework/util/CollectionUtils.isEmpty:(Ljava/util/Map;)Z
     100: ifne          113
     103: aload         5
     105: aload         8
     107: invokeinterface #366,  2          // InterfaceMethod software/amazon/awssdk/services/dynamodb/model/ScanRequest$Builder.expressionAttributeValues:(Ljava/util/Map;)Lsoftware/amazon/awssdk/services/dynamodb/model/ScanRequest$Builder;
     112: pop
     113: invokestatic  #369                // Method org/leo/aws/ddb/repositories/DataMapperUtils.getDynamoDbAsyncClient:()Lsoftware/amazon/awssdk/services/dynamodb/DynamoDbAsyncClient;
     116: aload         5
     118: invokeinterface #373,  1          // InterfaceMethod software/amazon/awssdk/services/dynamodb/model/ScanRequest$Builder.build:()Ljava/lang/Object;
     123: checkcast     #319                // class software/amazon/awssdk/services/dynamodb/model/ScanRequest
     126: invokeinterface #374,  2          // InterfaceMethod software/amazon/awssdk/services/dynamodb/DynamoDbAsyncClient.scanPaginator:(Lsoftware/amazon/awssdk/services/dynamodb/model/ScanRequest;)Lsoftware/amazon/awssdk/services/dynamodb/paginators/ScanPublisher;
     131: astore        6
     133: aload         6
     135: invokestatic  #380                // Method reactor/core/publisher/Flux.from:(Lorg/reactivestreams/Publisher;)Lreactor/core/publisher/Flux;
     138: invokedynamic #384,  0            // InvokeDynamic #3:apply:()Ljava/util/function/Function;
     143: invokevirtual #388                // Method reactor/core/publisher/Flux.flatMapIterable:(Ljava/util/function/Function;)Lreactor/core/publisher/Flux;
     146: aload         4
     148: dup
     149: invokevirtual #392                // Method java/lang/Object.getClass:()Ljava/lang/Class;
     152: pop
     153: invokedynamic #395,  0            // InvokeDynamic #4:apply:(Lorg/leo/aws/ddb/repositories/DataMapper;)Ljava/util/function/Function;
     158: invokevirtual #398                // Method reactor/core/publisher/Flux.map:(Ljava/util/function/Function;)Lreactor/core/publisher/Flux;
     161: areturn

  <ENTITY_TYPE> reactor.core.publisher.Mono<ENTITY_TYPE> findByPrimaryKey(org.leo.aws.ddb.data.PrimaryKey, java.util.function.Supplier<java.lang.Class<ENTITY_TYPE>>);
    Code:
       0: aload_2
       1: aload_1
       2: invokedynamic #415,  0            // InvokeDynamic #5:get:(Ljava/util/function/Supplier;Lorg/leo/aws/ddb/data/PrimaryKey;)Ljava/util/function/Supplier;
       7: invokestatic  #270                // Method reactor/core/publisher/Mono.defer:(Ljava/util/function/Supplier;)Lreactor/core/publisher/Mono;
      10: areturn

  <ENTITY_TYPE> reactor.core.publisher.Flux<ENTITY_TYPE> findByPrimaryKeys(java.util.List<org.leo.aws.ddb.data.PrimaryKey>, java.util.function.Supplier<java.lang.Class<ENTITY_TYPE>>);
    Code:
       0: aload_2
       1: aload_1
       2: invokedynamic #421,  0            // InvokeDynamic #6:get:(Ljava/util/function/Supplier;Ljava/util/List;)Ljava/util/function/Supplier;
       7: invokestatic  #249                // Method reactor/core/publisher/Flux.defer:(Ljava/util/function/Supplier;)Lreactor/core/publisher/Flux;
      10: areturn

  <ENTITY_TYPE> java.util.concurrent.CompletableFuture<ENTITY_TYPE> saveItem(ENTITY_TYPE, boolean, rx.functions.Action2<ENTITY_TYPE, java.util.Map<java.lang.String, software.amazon.awssdk.services.dynamodb.model.AttributeValue>>, org.leo.aws.ddb.repositories.DataMapper<ENTITY_TYPE>);
    Code:
       0: aload         4
       2: aload_1
       3: invokeinterface #430,  2          // InterfaceMethod org/leo/aws/ddb/repositories/DataMapper.createPKFromItem:(Ljava/lang/Object;)Lorg/leo/aws/ddb/data/PrimaryKey;
       8: astore        5
      10: aload         4
      12: invokeinterface #323,  1          // InterfaceMethod org/leo/aws/ddb/repositories/DataMapper.tableName:()Ljava/lang/String;
      17: astore        6
      19: aload         4
      21: invokeinterface #434,  1          // InterfaceMethod org/leo/aws/ddb/repositories/DataMapper.getVersionedAttribute:()Lorg/leo/aws/ddb/utils/Tuple;
      26: astore        10
      28: aload         5
      30: invokevirtual #438                // Method org/leo/aws/ddb/data/PrimaryKey.getRangeKeyName:()Ljava/lang/String;
      33: astore        11
      35: invokestatic  #443                // Method software/amazon/awssdk/services/dynamodb/model/PutItemRequest.builder:()Lsoftware/amazon/awssdk/services/dynamodb/model/PutItemRequest$Builder;
      38: aload         4
      40: invokeinterface #323,  1          // InterfaceMethod org/leo/aws/ddb/repositories/DataMapper.tableName:()Ljava/lang/String;
      45: invokeinterface #448,  2          // InterfaceMethod software/amazon/awssdk/services/dynamodb/model/PutItemRequest$Builder.tableName:(Ljava/lang/String;)Lsoftware/amazon/awssdk/services/dynamodb/model/PutItemRequest$Builder;
      50: astore        9
      52: iload_2
      53: ifne          193
      56: aload         10
      58: ifnull        82
      61: aload         10
      63: invokevirtual #127                // Method org/leo/aws/ddb/utils/Tuple._1:()Ljava/lang/Object;
      66: checkcast     #133                // class java/lang/reflect/Field
      69: aload_1
      70: getstatic     #453                // Field java/math/BigInteger.ZERO:Ljava/math/BigInteger;
      73: invokevirtual #459                // Method java/math/BigInteger.intValue:()I
      76: invokestatic  #147                // Method java/lang/Integer.valueOf:(I)Ljava/lang/Integer;
      79: invokestatic  #214                // Method org/springframework/util/ReflectionUtils.setField:(Ljava/lang/reflect/Field;Ljava/lang/Object;Ljava/lang/Object;)V
      82: aload         11
      84: invokestatic  #460                // Method org/springframework/util/StringUtils.isEmpty:(Ljava/lang/Object;)Z
      87: ifne          154
      90: aload         9
      92: aload         5
      94: invokevirtual #464                // Method org/leo/aws/ddb/data/PrimaryKey.getHashKeyName:()Ljava/lang/String;
      97: invokestatic  #164                // Method software/amazon/awssdk/services/dynamodb/model/ExpectedAttributeValue.builder:()Lsoftware/amazon/awssdk/services/dynamodb/model/ExpectedAttributeValue$Builder;
     100: iconst_0
     101: invokestatic  #170                // Method java/lang/Boolean.valueOf:(Z)Ljava/lang/Boolean;
     104: invokeinterface #175,  2          // InterfaceMethod software/amazon/awssdk/services/dynamodb/model/ExpectedAttributeValue$Builder.exists:(Ljava/lang/Boolean;)Lsoftware/amazon/awssdk/services/dynamodb/model/ExpectedAttributeValue$Builder;
     109: invokeinterface #181,  1          // InterfaceMethod software/amazon/awssdk/services/dynamodb/model/ExpectedAttributeValue$Builder.build:()Ljava/lang/Object;
     114: checkcast     #165                // class software/amazon/awssdk/services/dynamodb/model/ExpectedAttributeValue
     117: aload         5
     119: invokevirtual #438                // Method org/leo/aws/ddb/data/PrimaryKey.getRangeKeyName:()Ljava/lang/String;
     122: invokestatic  #164                // Method software/amazon/awssdk/services/dynamodb/model/ExpectedAttributeValue.builder:()Lsoftware/amazon/awssdk/services/dynamodb/model/ExpectedAttributeValue$Builder;
     125: iconst_0
     126: invokestatic  #170                // Method java/lang/Boolean.valueOf:(Z)Ljava/lang/Boolean;
     129: invokeinterface #175,  2          // InterfaceMethod software/amazon/awssdk/services/dynamodb/model/ExpectedAttributeValue$Builder.exists:(Ljava/lang/Boolean;)Lsoftware/amazon/awssdk/services/dynamodb/model/ExpectedAttributeValue$Builder;
     134: invokeinterface #181,  1          // InterfaceMethod software/amazon/awssdk/services/dynamodb/model/ExpectedAttributeValue$Builder.build:()Ljava/lang/Object;
     139: checkcast     #165                // class software/amazon/awssdk/services/dynamodb/model/ExpectedAttributeValue
     142: invokestatic  #467                // Method com/google/common/collect/ImmutableMap.of:(Ljava/lang/Object;Ljava/lang/Object;Ljava/lang/Object;Ljava/lang/Object;)Lcom/google/common/collect/ImmutableMap;
     145: invokeinterface #470,  2          // InterfaceMethod software/amazon/awssdk/services/dynamodb/model/PutItemRequest$Builder.expected:(Ljava/util/Map;)Lsoftware/amazon/awssdk/services/dynamodb/model/PutItemRequest$Builder;
     150: pop
     151: goto          369
     154: aload         9
     156: aload         5
     158: invokevirtual #464                // Method org/leo/aws/ddb/data/PrimaryKey.getHashKeyName:()Ljava/lang/String;
     161: invokestatic  #164                // Method software/amazon/awssdk/services/dynamodb/model/ExpectedAttributeValue.builder:()Lsoftware/amazon/awssdk/services/dynamodb/model/ExpectedAttributeValue$Builder;
     164: iconst_0
     165: invokestatic  #170                // Method java/lang/Boolean.valueOf:(Z)Ljava/lang/Boolean;
     168: invokeinterface #175,  2          // InterfaceMethod software/amazon/awssdk/services/dynamodb/model/ExpectedAttributeValue$Builder.exists:(Ljava/lang/Boolean;)Lsoftware/amazon/awssdk/services/dynamodb/model/ExpectedAttributeValue$Builder;
     173: invokeinterface #181,  1          // InterfaceMethod software/amazon/awssdk/services/dynamodb/model/ExpectedAttributeValue$Builder.build:()Ljava/lang/Object;
     178: checkcast     #165                // class software/amazon/awssdk/services/dynamodb/model/ExpectedAttributeValue
     181: invokestatic  #184                // Method com/google/common/collect/ImmutableMap.of:(Ljava/lang/Object;Ljava/lang/Object;)Lcom/google/common/collect/ImmutableMap;
     184: invokeinterface #470,  2          // InterfaceMethod software/amazon/awssdk/services/dynamodb/model/PutItemRequest$Builder.expected:(Ljava/util/Map;)Lsoftware/amazon/awssdk/services/dynamodb/model/PutItemRequest$Builder;
     189: pop
     190: goto          369
     193: aload         10
     195: ifnull        369
     198: aload         10
     200: invokevirtual #127                // Method org/leo/aws/ddb/utils/Tuple._1:()Ljava/lang/Object;
     203: checkcast     #133                // class java/lang/reflect/Field
     206: aload_1
     207: invokestatic  #135                // Method org/springframework/util/ReflectionUtils.getField:(Ljava/lang/reflect/Field;Ljava/lang/Object;)Ljava/lang/Object;
     210: checkcast     #141                // class java/lang/Number
     213: astore        12
     215: aload         12
     217: ifnonnull     275
     220: getstatic     #453                // Field java/math/BigInteger.ZERO:Ljava/math/BigInteger;
     223: invokevirtual #459                // Method java/math/BigInteger.intValue:()I
     226: istore        13
     228: aload         9
     230: aload         10
     232: invokevirtual #156                // Method org/leo/aws/ddb/utils/Tuple._2:()Ljava/lang/Object;
     235: checkcast     #159                // class org/leo/aws/ddb/annotations/DbAttribute
     238: invokeinterface #161,  1          // InterfaceMethod org/leo/aws/ddb/annotations/DbAttribute.value:()Ljava/lang/String;
     243: invokestatic  #164                // Method software/amazon/awssdk/services/dynamodb/model/ExpectedAttributeValue.builder:()Lsoftware/amazon/awssdk/services/dynamodb/model/ExpectedAttributeValue$Builder;
     246: iconst_0
     247: invokestatic  #170                // Method java/lang/Boolean.valueOf:(Z)Ljava/lang/Boolean;
     250: invokeinterface #175,  2          // InterfaceMethod software/amazon/awssdk/services/dynamodb/model/ExpectedAttributeValue$Builder.exists:(Ljava/lang/Boolean;)Lsoftware/amazon/awssdk/services/dynamodb/model/ExpectedAttributeValue$Builder;
     255: invokeinterface #181,  1          // InterfaceMethod software/amazon/awssdk/services/dynamodb/model/ExpectedAttributeValue$Builder.build:()Ljava/lang/Object;
     260: checkcast     #165                // class software/amazon/awssdk/services/dynamodb/model/ExpectedAttributeValue
     263: invokestatic  #184                // Method com/google/common/collect/ImmutableMap.of:(Ljava/lang/Object;Ljava/lang/Object;)Lcom/google/common/collect/ImmutableMap;
     266: invokeinterface #470,  2          // InterfaceMethod software/amazon/awssdk/services/dynamodb/model/PutItemRequest$Builder.expected:(Ljava/util/Map;)Lsoftware/amazon/awssdk/services/dynamodb/model/PutItemRequest$Builder;
     271: pop
     272: goto          352
     275: aload         12
     277: invokevirtual #143                // Method java/lang/Number.intValue:()I
     280: iconst_1
     281: iadd
     282: istore        13
     284: aload         9
     286: aload         10
     288: invokevirtual #156                // Method org/leo/aws/ddb/utils/Tuple._2:()Ljava/lang/Object;
     291: checkcast     #159                // class org/leo/aws/ddb/annotations/DbAttribute
     294: invokeinterface #161,  1          // InterfaceMethod org/leo/aws/ddb/annotations/DbAttribute.value:()Ljava/lang/String;
     299: invokestatic  #164                // Method software/amazon/awssdk/services/dynamodb/model/ExpectedAttributeValue.builder:()Lsoftware/amazon/awssdk/services/dynamodb/model/ExpectedAttributeValue$Builder;
     302: iconst_1
     303: anewarray     #197                // class software/amazon/awssdk/services/dynamodb/model/AttributeValue
     306: dup
     307: iconst_0
     308: invokestatic  #196                // Method software/amazon/awssdk/services/dynamodb/model/AttributeValue.builder:()Lsoftware/amazon/awssdk/services/dynamodb/model/AttributeValue$Builder;
     311: aload         12
     313: invokestatic  #97                 // Method java/lang/String.valueOf:(Ljava/lang/Object;)Ljava/lang/String;
     316: invokeinterface #204,  2          // InterfaceMethod software/amazon/awssdk/services/dynamodb/model/AttributeValue$Builder.n:(Ljava/lang/String;)Lsoftware/amazon/awssdk/services/dynamodb/model/AttributeValue$Builder;
     321: invokeinterface #210,  1          // InterfaceMethod software/amazon/awssdk/services/dynamodb/model/AttributeValue$Builder.build:()Ljava/lang/Object;
     326: checkcast     #197                // class software/amazon/awssdk/services/dynamodb/model/AttributeValue
     329: aastore
     330: invokeinterface #473,  2          // InterfaceMethod software/amazon/awssdk/services/dynamodb/model/ExpectedAttributeValue$Builder.attributeValueList:([Lsoftware/amazon/awssdk/services/dynamodb/model/AttributeValue;)Lsoftware/amazon/awssdk/services/dynamodb/model/ExpectedAttributeValue$Builder;
     335: invokeinterface #181,  1          // InterfaceMethod software/amazon/awssdk/services/dynamodb/model/ExpectedAttributeValue$Builder.build:()Ljava/lang/Object;
     340: checkcast     #165                // class software/amazon/awssdk/services/dynamodb/model/ExpectedAttributeValue
     343: invokestatic  #184                // Method com/google/common/collect/ImmutableMap.of:(Ljava/lang/Object;Ljava/lang/Object;)Lcom/google/common/collect/ImmutableMap;
     346: invokeinterface #470,  2          // InterfaceMethod software/amazon/awssdk/services/dynamodb/model/PutItemRequest$Builder.expected:(Ljava/util/Map;)Lsoftware/amazon/awssdk/services/dynamodb/model/PutItemRequest$Builder;
     351: pop
     352: aload         10
     354: invokevirtual #127                // Method org/leo/aws/ddb/utils/Tuple._1:()Ljava/lang/Object;
     357: checkcast     #133                // class java/lang/reflect/Field
     360: aload_1
     361: iload         13
     363: invokestatic  #147                // Method java/lang/Integer.valueOf:(I)Ljava/lang/Integer;
     366: invokestatic  #214                // Method org/springframework/util/ReflectionUtils.setField:(Ljava/lang/reflect/Field;Ljava/lang/Object;Ljava/lang/Object;)V
     369: aload         4
     371: aload_1
     372: invokeinterface #477,  2          // InterfaceMethod org/leo/aws/ddb/repositories/DataMapper.mapFromEntityToAttributeValue:(Ljava/lang/Object;)Ljava/util/Map;
     377: astore        7
     379: aload_3
     380: aload_1
     381: aload         7
     383: invokeinterface #481,  3          // InterfaceMethod rx/functions/Action2.call:(Ljava/lang/Object;Ljava/lang/Object;)V
     388: aload         9
     390: aload         7
     392: invokeinterface #487,  2          // InterfaceMethod software/amazon/awssdk/services/dynamodb/model/PutItemRequest$Builder.item:(Ljava/util/Map;)Lsoftware/amazon/awssdk/services/dynamodb/model/PutItemRequest$Builder;
     397: pop
     398: aload         9
     400: invokeinterface #489,  1          // InterfaceMethod software/amazon/awssdk/services/dynamodb/model/PutItemRequest$Builder.build:()Ljava/lang/Object;
     405: checkcast     #444                // class software/amazon/awssdk/services/dynamodb/model/PutItemRequest
     408: astore        8
     410: invokestatic  #369                // Method org/leo/aws/ddb/repositories/DataMapperUtils.getDynamoDbAsyncClient:()Lsoftware/amazon/awssdk/services/dynamodb/DynamoDbAsyncClient;
     413: aload         8
     415: invokeinterface #490,  2          // InterfaceMethod software/amazon/awssdk/services/dynamodb/DynamoDbAsyncClient.putItem:(Lsoftware/amazon/awssdk/services/dynamodb/model/PutItemRequest;)Ljava/util/concurrent/CompletableFuture;
     420: aload_1
     421: invokedynamic #494,  0            // InvokeDynamic #7:apply:(Ljava/lang/Object;)Ljava/util/function/Function;
     426: invokevirtual #497                // Method java/util/concurrent/CompletableFuture.thenApplyAsync:(Ljava/util/function/Function;)Ljava/util/concurrent/CompletableFuture;
     429: aload_0
     430: aload         5
     432: aload         6
     434: invokedynamic #503,  0            // InvokeDynamic #8:apply:(Lorg/leo/aws/ddb/repositories/BaseRepositoryUtils;Lorg/leo/aws/ddb/data/PrimaryKey;Ljava/lang/String;)Ljava/util/function/Function;
     439: invokevirtual #506                // Method java/util/concurrent/CompletableFuture.exceptionally:(Ljava/util/function/Function;)Ljava/util/concurrent/CompletableFuture;
     442: areturn

  <ENTITY_TYPE> ENTITY_TYPE handleCreateItemException(org.leo.aws.ddb.data.PrimaryKey, java.lang.String, java.lang.Throwable);
    Code:
       0: getstatic     #33                 // Field LOGGER:Lorg/slf4j/Logger;
       3: ldc           #50                 // String Record with the following primary key [{0}] exists in table [{1}]
       5: iconst_2
       6: anewarray     #52                 // class java/lang/Object
       9: dup
      10: iconst_0
      11: aload_1
      12: aastore
      13: dup
      14: iconst_1
      15: aload_2
      16: aastore
      17: invokestatic  #54                 // Method java/text/MessageFormat.format:(Ljava/lang/String;[Ljava/lang/Object;)Ljava/lang/String;
      20: aload_3
      21: invokeinterface #522,  3          // InterfaceMethod org/slf4j/Logger.error:(Ljava/lang/String;Ljava/lang/Throwable;)V
      26: aload_3
      27: instanceof    #66                 // class java/util/concurrent/CompletionException
      30: ifeq          58
      33: aload_3
      34: invokevirtual #68                 // Method java/lang/Throwable.getCause:()Ljava/lang/Throwable;
      37: instanceof    #74                 // class software/amazon/awssdk/services/dynamodb/model/ConditionalCheckFailedException
      40: ifeq          58
      43: new           #83                 // class org/leo/aws/ddb/exceptions/DbException
      46: dup
      47: getstatic     #525                // Field org/leo/aws/ddb/utils/exceptions/Issue.RECORD_ALREADY_EXISTS:Lorg/leo/aws/ddb/utils/exceptions/Issue;
      50: invokevirtual #93                 // Method org/leo/aws/ddb/utils/exceptions/Issue.name:()Ljava/lang/String;
      53: aload_3
      54: invokespecial #115                // Method org/leo/aws/ddb/exceptions/DbException."<init>":(Ljava/lang/String;Ljava/lang/Throwable;)V
      57: athrow
      58: aload_3
      59: instanceof    #81                 // class java/lang/RuntimeException
      62: ifeq          70
      65: aload_3
      66: checkcast     #81                 // class java/lang/RuntimeException
      69: athrow
      70: new           #83                 // class org/leo/aws/ddb/exceptions/DbException
      73: dup
      74: new           #85                 // class java/lang/StringBuilder
      77: dup
      78: getstatic     #87                 // Field org/leo/aws/ddb/utils/exceptions/Issue.UNKNOWN_ERROR:Lorg/leo/aws/ddb/utils/exceptions/Issue;
      81: invokevirtual #93                 // Method org/leo/aws/ddb/utils/exceptions/Issue.name:()Ljava/lang/String;
      84: invokestatic  #97                 // Method java/lang/String.valueOf:(Ljava/lang/Object;)Ljava/lang/String;
      87: invokespecial #103                // Method java/lang/StringBuilder."<init>":(Ljava/lang/String;)V
      90: ldc_w         #528                // String  - handleCreateItemException
      93: invokevirtual #108                // Method java/lang/StringBuilder.append:(Ljava/lang/String;)Ljava/lang/StringBuilder;
      96: invokevirtual #112                // Method java/lang/StringBuilder.toString:()Ljava/lang/String;
      99: aload_3
     100: invokespecial #115                // Method org/leo/aws/ddb/exceptions/DbException."<init>":(Ljava/lang/String;Ljava/lang/Throwable;)V
     103: athrow

  <ENTITY_TYPE> reactor.core.publisher.Mono<ENTITY_TYPE> updateItem(ENTITY_TYPE, java.util.function.Function<ENTITY_TYPE, org.leo.aws.ddb.data.PrimaryKey>, java.util.function.Supplier<java.lang.Class<ENTITY_TYPE>>);
    Code:
       0: aload_0
       1: aload_2
       2: aload_1
       3: aload_3
       4: invokedynamic #532,  0            // InvokeDynamic #9:get:(Lorg/leo/aws/ddb/repositories/BaseRepositoryUtils;Ljava/util/function/Function;Ljava/lang/Object;Ljava/util/function/Supplier;)Ljava/util/function/Supplier;
       9: invokestatic  #270                // Method reactor/core/publisher/Mono.defer:(Ljava/util/function/Supplier;)Lreactor/core/publisher/Mono;
      12: areturn

  <ENTITY_TYPE> reactor.core.publisher.Mono<ENTITY_TYPE> updateItem(org.leo.aws.ddb.data.PrimaryKey, java.util.Map<java.lang.String, java.lang.Object>, java.util.function.Function<org.leo.aws.ddb.data.PrimaryKey, reactor.core.publisher.Mono<ENTITY_TYPE>>, java.util.function.Supplier<java.lang.Class<ENTITY_TYPE>>);
    Code:
       0: aload_3
       1: aload_1
       2: invokeinterface #537,  2          // InterfaceMethod java/util/function/Function.apply:(Ljava/lang/Object;)Ljava/lang/Object;
       7: checkcast     #271                // class reactor/core/publisher/Mono
      10: astore        5
      12: aload         4
      14: invokeinterface #308,  1          // InterfaceMethod java/util/function/Supplier.get:()Ljava/lang/Object;
      19: checkcast     #240                // class java/lang/Class
      22: astore        6
      24: aload         6
      26: invokestatic  #312                // Method org/leo/aws/ddb/repositories/DataMapperUtils.getDataMapper:(Ljava/lang/Class;)Lorg/leo/aws/ddb/repositories/DataMapper;
      29: astore        7
      31: aload         5
      33: aload_0
      34: aload_1
      35: aload_2
      36: aload         6
      38: aload         7
      40: invokedynamic #542,  0            // InvokeDynamic #10:apply:(Lorg/leo/aws/ddb/repositories/BaseRepositoryUtils;Lorg/leo/aws/ddb/data/PrimaryKey;Ljava/util/Map;Ljava/lang/Class;Lorg/leo/aws/ddb/repositories/DataMapper;)Ljava/util/function/Function;
      45: invokevirtual #545                // Method reactor/core/publisher/Mono.flatMap:(Ljava/util/function/Function;)Lreactor/core/publisher/Mono;
      48: areturn

  <ENTITY_TYPE> reactor.core.publisher.Flux<ENTITY_TYPE> updateItem(java.util.List<org.leo.aws.ddb.data.UpdateItem>, java.util.function.Supplier<java.lang.Class<ENTITY_TYPE>>, java.util.function.Function<java.util.List<org.leo.aws.ddb.data.PrimaryKey>, reactor.core.publisher.Flux<ENTITY_TYPE>>);
    Code:
       0: aload_2
       1: invokeinterface #308,  1          // InterfaceMethod java/util/function/Supplier.get:()Ljava/lang/Object;
       6: checkcast     #240                // class java/lang/Class
       9: astore        4
      11: aload         4
      13: invokestatic  #312                // Method org/leo/aws/ddb/repositories/DataMapperUtils.getDataMapper:(Ljava/lang/Class;)Lorg/leo/aws/ddb/repositories/DataMapper;
      16: astore        5
      18: aload_3
      19: aload_1
      20: invokeinterface #556,  1          // InterfaceMethod java/util/List.stream:()Ljava/util/stream/Stream;
      25: invokedynamic #562,  0            // InvokeDynamic #11:apply:()Ljava/util/function/Function;
      30: invokeinterface #563,  2          // InterfaceMethod java/util/stream/Stream.map:(Ljava/util/function/Function;)Ljava/util/stream/Stream;
      35: invokestatic  #568                // Method java/util/stream/Collectors.toList:()Ljava/util/stream/Collector;
      38: invokeinterface #574,  2          // InterfaceMethod java/util/stream/Stream.collect:(Ljava/util/stream/Collector;)Ljava/lang/Object;
      43: checkcast     #557                // class java/util/List
      46: invokeinterface #537,  2          // InterfaceMethod java/util/function/Function.apply:(Ljava/lang/Object;)Ljava/lang/Object;
      51: checkcast     #250                // class reactor/core/publisher/Flux
      54: astore        6
      56: aload_1
      57: invokeinterface #556,  1          // InterfaceMethod java/util/List.stream:()Ljava/util/stream/Stream;
      62: invokedynamic #562,  0            // InvokeDynamic #11:apply:()Ljava/util/function/Function;
      67: invokedynamic #578,  0            // InvokeDynamic #12:apply:()Ljava/util/function/Function;
      72: invokestatic  #579                // Method java/util/stream/Collectors.toMap:(Ljava/util/function/Function;Ljava/util/function/Function;)Ljava/util/stream/Collector;
      75: invokeinterface #574,  2          // InterfaceMethod java/util/stream/Stream.collect:(Ljava/util/stream/Collector;)Ljava/lang/Object;
      80: checkcast     #410                // class java/util/Map
      83: astore        7
      85: aload         6
      87: aload_0
      88: aload         5
      90: aload         7
      92: aload         4
      94: invokedynamic #583,  0            // InvokeDynamic #13:apply:(Lorg/leo/aws/ddb/repositories/BaseRepositoryUtils;Lorg/leo/aws/ddb/repositories/DataMapper;Ljava/util/Map;Ljava/lang/Class;)Ljava/util/function/Function;
      99: invokevirtual #398                // Method reactor/core/publisher/Flux.map:(Ljava/util/function/Function;)Lreactor/core/publisher/Flux;
     102: astore        8
     104: aload         8
     106: invokestatic  #586                // Method reactor/core/publisher/Flux.concat:(Lorg/reactivestreams/Publisher;)Lreactor/core/publisher/Flux;
     109: areturn

  <ENTITY_TYPE> reactor.core.publisher.Flux<ENTITY_TYPE> batchWrite(java.util.List<ENTITY_TYPE>, java.util.List<ENTITY_TYPE>, java.util.function.Supplier<java.lang.Class<ENTITY_TYPE>>);
    Code:
       0: aload_0
       1: aload_1
       2: aload_2
       3: aload_3
       4: invokedynamic #603,  0            // InvokeDynamic #14:get:(Lorg/leo/aws/ddb/repositories/BaseRepositoryUtils;Ljava/util/List;Ljava/util/List;Ljava/util/function/Supplier;)Ljava/util/function/Supplier;
       9: invokestatic  #249                // Method reactor/core/publisher/Flux.defer:(Ljava/util/function/Supplier;)Lreactor/core/publisher/Flux;
      12: areturn

  <ENTITY_TYPE> java.util.concurrent.CompletableFuture<java.util.List<ENTITY_TYPE>> processBatchWriteRequest(rx.functions.Func0<java.util.List<ENTITY_TYPE>>, java.util.Map<java.lang.String, java.util.List<software.amazon.awssdk.services.dynamodb.model.WriteRequest>>);
    Code:
       0: invokestatic  #612                // Method software/amazon/awssdk/services/dynamodb/model/BatchWriteItemRequest.builder:()Lsoftware/amazon/awssdk/services/dynamodb/model/BatchWriteItemRequest$Builder;
       3: getstatic     #617                // Field software/amazon/awssdk/services/dynamodb/model/ReturnConsumedCapacity.TOTAL:Lsoftware/amazon/awssdk/services/dynamodb/model/ReturnConsumedCapacity;
       6: invokeinterface #623,  2          // InterfaceMethod software/amazon/awssdk/services/dynamodb/model/BatchWriteItemRequest$Builder.returnConsumedCapacity:(Lsoftware/amazon/awssdk/services/dynamodb/model/ReturnConsumedCapacity;)Lsoftware/amazon/awssdk/services/dynamodb/model/BatchWriteItemRequest$Builder;
      11: getstatic     #629                // Field software/amazon/awssdk/services/dynamodb/model/ReturnItemCollectionMetrics.SIZE:Lsoftware/amazon/awssdk/services/dynamodb/model/ReturnItemCollectionMetrics;
      14: invokeinterface #635,  2          // InterfaceMethod software/amazon/awssdk/services/dynamodb/model/BatchWriteItemRequest$Builder.returnItemCollectionMetrics:(Lsoftware/amazon/awssdk/services/dynamodb/model/ReturnItemCollectionMetrics;)Lsoftware/amazon/awssdk/services/dynamodb/model/BatchWriteItemRequest$Builder;
      19: aload_2
      20: invokeinterface #639,  2          // InterfaceMethod software/amazon/awssdk/services/dynamodb/model/BatchWriteItemRequest$Builder.requestItems:(Ljava/util/Map;)Lsoftware/amazon/awssdk/services/dynamodb/model/BatchWriteItemRequest$Builder;
      25: invokeinterface #643,  1          // InterfaceMethod software/amazon/awssdk/services/dynamodb/model/BatchWriteItemRequest$Builder.build:()Ljava/lang/Object;
      30: checkcast     #613                // class software/amazon/awssdk/services/dynamodb/model/BatchWriteItemRequest
      33: astore_3
      34: invokestatic  #369                // Method org/leo/aws/ddb/repositories/DataMapperUtils.getDynamoDbAsyncClient:()Lsoftware/amazon/awssdk/services/dynamodb/DynamoDbAsyncClient;
      37: aload_3
      38: invokeinterface #644,  2          // InterfaceMethod software/amazon/awssdk/services/dynamodb/DynamoDbAsyncClient.batchWriteItem:(Lsoftware/amazon/awssdk/services/dynamodb/model/BatchWriteItemRequest;)Ljava/util/concurrent/CompletableFuture;
      43: astore        4
      45: aload         4
      47: aload_0
      48: aload_1
      49: invokedynamic #648,  0            // InvokeDynamic #15:apply:(Lorg/leo/aws/ddb/repositories/BaseRepositoryUtils;Lrx/functions/Func0;)Ljava/util/function/Function;
      54: invokevirtual #497                // Method java/util/concurrent/CompletableFuture.thenApplyAsync:(Ljava/util/function/Function;)Ljava/util/concurrent/CompletableFuture;
      57: areturn

  <ENTITY_TYPE> reactor.core.publisher.Mono<ENTITY_TYPE> deleteItem(ENTITY_TYPE, java.util.function.Supplier<java.lang.Class<ENTITY_TYPE>>);
    Code:
       0: aload_1
       1: aload_2
       2: invokedynamic #660,  0            // InvokeDynamic #16:get:(Ljava/lang/Object;Ljava/util/function/Supplier;)Ljava/util/function/Supplier;
       7: invokestatic  #270                // Method reactor/core/publisher/Mono.defer:(Ljava/util/function/Supplier;)Lreactor/core/publisher/Mono;
      10: areturn

  <ENTITY_TYPE> org.leo.aws.ddb.utils.Tuple<org.leo.aws.ddb.annotations.ProjectionType, software.amazon.awssdk.services.dynamodb.paginators.QueryPublisher> getDataFromIndex(java.lang.String, java.lang.String, java.util.Optional<?>, java.lang.Class<ENTITY_TYPE>, org.leo.aws.ddb.utils.Expr);
    Code:
       0: invokestatic  #669                // Method org/leo/aws/ddb/repositories/MapperUtils.getInstance:()Lorg/leo/aws/ddb/repositories/MapperUtils;
       3: invokevirtual #674                // Method org/leo/aws/ddb/repositories/MapperUtils.getAttributeMappingMap:()Ljava/util/concurrent/ConcurrentHashMap;
       6: aload         4
       8: invokevirtual #678                // Method java/lang/Class.getName:()Ljava/lang/String;
      11: invokevirtual #681                // Method java/util/concurrent/ConcurrentHashMap.get:(Ljava/lang/Object;)Ljava/lang/Object;
      14: checkcast     #683                // class org/leo/aws/ddb/repositories/AttributeMapper
      17: astore        6
      19: aload         6
      21: invokevirtual #685                // Method org/leo/aws/ddb/repositories/AttributeMapper.getGlobalSecondaryIndexMap:()Ljava/util/Map;
      24: aload_1
      25: invokeinterface #688,  2          // InterfaceMethod java/util/Map.get:(Ljava/lang/Object;)Ljava/lang/Object;
      30: checkcast     #689                // class org/leo/aws/ddb/repositories/GSI
      33: astore        7
      35: aload         7
      37: ifnonnull     62
      40: new           #83                 // class org/leo/aws/ddb/exceptions/DbException
      43: dup
      44: ldc_w         #691                // String Index [{0}] not defined in the data model
      47: iconst_1
      48: anewarray     #52                 // class java/lang/Object
      51: dup
      52: iconst_0
      53: aload_1
      54: aastore
      55: invokestatic  #54                 // Method java/text/MessageFormat.format:(Ljava/lang/String;[Ljava/lang/Object;)Ljava/lang/String;
      58: invokespecial #693                // Method org/leo/aws/ddb/exceptions/DbException."<init>":(Ljava/lang/String;)V
      61: athrow
      62: aload_3
      63: invokevirtual #694                // Method java/util/Optional.isPresent:()Z
      66: ifeq          101
      69: aload         7
      71: invokeinterface #700,  1          // InterfaceMethod org/leo/aws/ddb/repositories/GSI.getRangeKeyTuple:()Lorg/leo/aws/ddb/utils/Tuple;
      76: ifnonnull     101
      79: new           #83                 // class org/leo/aws/ddb/exceptions/DbException
      82: dup
      83: ldc_w         #703                // String Sort Key not defined for index[{0}] in the data model
      86: iconst_1
      87: anewarray     #52                 // class java/lang/Object
      90: dup
      91: iconst_0
      92: aload_1
      93: aastore
      94: invokestatic  #54                 // Method java/text/MessageFormat.format:(Ljava/lang/String;[Ljava/lang/Object;)Ljava/lang/String;
      97: invokespecial #693                // Method org/leo/aws/ddb/exceptions/DbException."<init>":(Ljava/lang/String;)V
     100: athrow
     101: new           #85                 // class java/lang/StringBuilder
     104: dup
     105: ldc_w         #705                // String #d = :partition_key
     108: invokespecial #103                // Method java/lang/StringBuilder."<init>":(Ljava/lang/String;)V
     111: aload_3
     112: invokevirtual #694                // Method java/util/Optional.isPresent:()Z
     115: ifeq          156
     118: new           #85                 // class java/lang/StringBuilder
     121: dup
     122: ldc_w         #707                // String  and
     125: invokespecial #103                // Method java/lang/StringBuilder."<init>":(Ljava/lang/String;)V
     128: aload         7
     130: invokeinterface #700,  1          // InterfaceMethod org/leo/aws/ddb/repositories/GSI.getRangeKeyTuple:()Lorg/leo/aws/ddb/utils/Tuple;
     135: invokevirtual #127                // Method org/leo/aws/ddb/utils/Tuple._1:()Ljava/lang/Object;
     138: checkcast     #98                 // class java/lang/String
     141: invokevirtual #108                // Method java/lang/StringBuilder.append:(Ljava/lang/String;)Ljava/lang/StringBuilder;
     144: ldc_w         #709                // String  = :sort_key_val
     147: invokevirtual #108                // Method java/lang/StringBuilder.append:(Ljava/lang/String;)Ljava/lang/StringBuilder;
     150: invokevirtual #112                // Method java/lang/StringBuilder.toString:()Ljava/lang/String;
     153: goto          159
     156: ldc_w         #711                // String
     159: invokevirtual #108                // Method java/lang/StringBuilder.append:(Ljava/lang/String;)Ljava/lang/StringBuilder;
     162: invokevirtual #112                // Method java/lang/StringBuilder.toString:()Ljava/lang/String;
     165: astore        8
     167: invokestatic  #713                // Method software/amazon/awssdk/services/dynamodb/model/QueryRequest.builder:()Lsoftware/amazon/awssdk/services/dynamodb/model/QueryRequest$Builder;
     170: astore        11
     172: new           #718                // class java/util/HashMap
     175: dup
     176: invokestatic  #720                // Method software/amazon/awssdk/utils/ImmutableMap.builder:()Lsoftware/amazon/awssdk/utils/ImmutableMap$Builder;
     179: ldc_w         #725                // String #d
     182: aload         7
     184: invokeinterface #727,  1          // InterfaceMethod org/leo/aws/ddb/repositories/GSI.getHashKeyTuple:()Lorg/leo/aws/ddb/utils/Tuple;
     189: invokevirtual #127                // Method org/leo/aws/ddb/utils/Tuple._1:()Ljava/lang/Object;
     192: checkcast     #98                 // class java/lang/String
     195: invokevirtual #730                // Method software/amazon/awssdk/utils/ImmutableMap$Builder.put:(Ljava/lang/Object;Ljava/lang/Object;)Lsoftware/amazon/awssdk/utils/ImmutableMap$Builder;
     198: invokevirtual #736                // Method software/amazon/awssdk/utils/ImmutableMap$Builder.build:()Lsoftware/amazon/awssdk/utils/ImmutableMap;
     201: invokespecial #739                // Method java/util/HashMap."<init>":(Ljava/util/Map;)V
     204: astore        12
     206: new           #718                // class java/util/HashMap
     209: dup
     210: invokespecial #742                // Method java/util/HashMap."<init>":()V
     213: astore        13
     215: aload_3
     216: aload         13
     218: invokedynamic #743,  0            // InvokeDynamic #17:accept:(Ljava/util/Map;)Ljava/util/function/Consumer;
     223: invokevirtual #747                // Method java/util/Optional.ifPresent:(Ljava/util/function/Consumer;)V
     226: aload         13
     228: ldc_w         #751                // String :partition_key
     231: invokestatic  #196                // Method software/amazon/awssdk/services/dynamodb/model/AttributeValue.builder:()Lsoftware/amazon/awssdk/services/dynamodb/model/AttributeValue$Builder;
     234: aload_2
     235: invokeinterface #753,  2          // InterfaceMethod software/amazon/awssdk/services/dynamodb/model/AttributeValue$Builder.s:(Ljava/lang/String;)Lsoftware/amazon/awssdk/services/dynamodb/model/AttributeValue$Builder;
     240: invokeinterface #210,  1          // InterfaceMethod software/amazon/awssdk/services/dynamodb/model/AttributeValue$Builder.build:()Ljava/lang/Object;
     245: checkcast     #197                // class software/amazon/awssdk/services/dynamodb/model/AttributeValue
     248: invokeinterface #756,  3          // InterfaceMethod java/util/Map.put:(Ljava/lang/Object;Ljava/lang/Object;)Ljava/lang/Object;
     253: pop
     254: aload         11
     256: aload         6
     258: invokevirtual #759                // Method org/leo/aws/ddb/repositories/AttributeMapper.getTableName:()Ljava/lang/String;
     261: invokeinterface #762,  2          // InterfaceMethod software/amazon/awssdk/services/dynamodb/model/QueryRequest$Builder.tableName:(Ljava/lang/String;)Lsoftware/amazon/awssdk/services/dynamodb/model/QueryRequest$Builder;
     266: pop
     267: aload         11
     269: aload         7
     271: invokeinterface #767,  1          // InterfaceMethod org/leo/aws/ddb/repositories/GSI.getName:()Ljava/lang/String;
     276: invokeinterface #768,  2          // InterfaceMethod software/amazon/awssdk/services/dynamodb/model/QueryRequest$Builder.indexName:(Ljava/lang/String;)Lsoftware/amazon/awssdk/services/dynamodb/model/QueryRequest$Builder;
     281: pop
     282: aload_0
     283: aload         5
     285: aload         11
     287: aload         12
     289: aload         13
     291: invokevirtual #770                // Method setFilterExpression:(Lorg/leo/aws/ddb/utils/Expr;Lsoftware/amazon/awssdk/services/dynamodb/model/QueryRequest$Builder;Ljava/util/Map;Ljava/util/Map;)V
     294: aload         11
     296: aload         8
     298: invokeinterface #774,  2          // InterfaceMethod software/amazon/awssdk/services/dynamodb/model/QueryRequest$Builder.keyConditionExpression:(Ljava/lang/String;)Lsoftware/amazon/awssdk/services/dynamodb/model/QueryRequest$Builder;
     303: pop
     304: aload         11
     306: aload         12
     308: invokeinterface #777,  2          // InterfaceMethod software/amazon/awssdk/services/dynamodb/model/QueryRequest$Builder.expressionAttributeNames:(Ljava/util/Map;)Lsoftware/amazon/awssdk/services/dynamodb/model/QueryRequest$Builder;
     313: pop
     314: aload         11
     316: aload         13
     318: invokeinterface #780,  2          // InterfaceMethod software/amazon/awssdk/services/dynamodb/model/QueryRequest$Builder.expressionAttributeValues:(Ljava/util/Map;)Lsoftware/amazon/awssdk/services/dynamodb/model/QueryRequest$Builder;
     323: pop
     324: aload         11
     326: invokeinterface #782,  1          // InterfaceMethod software/amazon/awssdk/services/dynamodb/model/QueryRequest$Builder.build:()Ljava/lang/Object;
     331: checkcast     #714                // class software/amazon/awssdk/services/dynamodb/model/QueryRequest
     334: astore        9
     336: invokestatic  #369                // Method org/leo/aws/ddb/repositories/DataMapperUtils.getDynamoDbAsyncClient:()Lsoftware/amazon/awssdk/services/dynamodb/DynamoDbAsyncClient;
     339: aload         9
     341: invokeinterface #783,  2          // InterfaceMethod software/amazon/awssdk/services/dynamodb/DynamoDbAsyncClient.queryPaginator:(Lsoftware/amazon/awssdk/services/dynamodb/model/QueryRequest;)Lsoftware/amazon/awssdk/services/dynamodb/paginators/QueryPublisher;
     346: astore        10
     348: aload         7
     350: invokeinterface #787,  1          // InterfaceMethod org/leo/aws/ddb/repositories/GSI.getProjectionType:()Lorg/leo/aws/ddb/annotations/ProjectionType;
     355: aload         10
     357: invokestatic  #791                // Method org/leo/aws/ddb/utils/Tuples.of:(Ljava/lang/Object;Ljava/lang/Object;)Lorg/leo/aws/ddb/utils/Tuple;
     360: areturn

  <ENTITY_TYPE> org.leo.aws.ddb.utils.Tuple<org.leo.aws.ddb.annotations.ProjectionType, software.amazon.awssdk.services.dynamodb.paginators.QueryPublisher> getDataFromIndex(java.lang.String, java.lang.String, java.lang.Object, java.lang.Class<ENTITY_TYPE>, org.leo.aws.ddb.utils.Expr);
    Code:
       0: invokestatic  #669                // Method org/leo/aws/ddb/repositories/MapperUtils.getInstance:()Lorg/leo/aws/ddb/repositories/MapperUtils;
       3: invokevirtual #674                // Method org/leo/aws/ddb/repositories/MapperUtils.getAttributeMappingMap:()Ljava/util/concurrent/ConcurrentHashMap;
       6: aload         4
       8: invokevirtual #678                // Method java/lang/Class.getName:()Ljava/lang/String;
      11: invokevirtual #681                // Method java/util/concurrent/ConcurrentHashMap.get:(Ljava/lang/Object;)Ljava/lang/Object;
      14: checkcast     #683                // class org/leo/aws/ddb/repositories/AttributeMapper
      17: astore        6
      19: aload         6
      21: invokevirtual #685                // Method org/leo/aws/ddb/repositories/AttributeMapper.getGlobalSecondaryIndexMap:()Ljava/util/Map;
      24: aload_1
      25: invokeinterface #688,  2          // InterfaceMethod java/util/Map.get:(Ljava/lang/Object;)Ljava/lang/Object;
      30: checkcast     #689                // class org/leo/aws/ddb/repositories/GSI
      33: astore        7
      35: aload         7
      37: ifnonnull     62
      40: new           #83                 // class org/leo/aws/ddb/exceptions/DbException
      43: dup
      44: ldc_w         #691                // String Index [{0}] not defined in the data model
      47: iconst_1
      48: anewarray     #52                 // class java/lang/Object
      51: dup
      52: iconst_0
      53: aload_1
      54: aastore
      55: invokestatic  #54                 // Method java/text/MessageFormat.format:(Ljava/lang/String;[Ljava/lang/Object;)Ljava/lang/String;
      58: invokespecial #693                // Method org/leo/aws/ddb/exceptions/DbException."<init>":(Ljava/lang/String;)V
      61: athrow
      62: aload_3
      63: ifnull        98
      66: aload         7
      68: invokeinterface #700,  1          // InterfaceMethod org/leo/aws/ddb/repositories/GSI.getRangeKeyTuple:()Lorg/leo/aws/ddb/utils/Tuple;
      73: ifnonnull     98
      76: new           #83                 // class org/leo/aws/ddb/exceptions/DbException
      79: dup
      80: ldc_w         #703                // String Sort Key not defined for index[{0}] in the data model
      83: iconst_1
      84: anewarray     #52                 // class java/lang/Object
      87: dup
      88: iconst_0
      89: aload_1
      90: aastore
      91: invokestatic  #54                 // Method java/text/MessageFormat.format:(Ljava/lang/String;[Ljava/lang/Object;)Ljava/lang/String;
      94: invokespecial #693                // Method org/leo/aws/ddb/exceptions/DbException."<init>":(Ljava/lang/String;)V
      97: athrow
      98: new           #85                 // class java/lang/StringBuilder
     101: dup
     102: ldc_w         #705                // String #d = :partition_key
     105: invokespecial #103                // Method java/lang/StringBuilder."<init>":(Ljava/lang/String;)V
     108: aload_3
     109: ifnull        150
     112: new           #85                 // class java/lang/StringBuilder
     115: dup
     116: ldc_w         #707                // String  and
     119: invokespecial #103                // Method java/lang/StringBuilder."<init>":(Ljava/lang/String;)V
     122: aload         7
     124: invokeinterface #700,  1          // InterfaceMethod org/leo/aws/ddb/repositories/GSI.getRangeKeyTuple:()Lorg/leo/aws/ddb/utils/Tuple;
     129: invokevirtual #127                // Method org/leo/aws/ddb/utils/Tuple._1:()Ljava/lang/Object;
     132: checkcast     #98                 // class java/lang/String
     135: invokevirtual #108                // Method java/lang/StringBuilder.append:(Ljava/lang/String;)Ljava/lang/StringBuilder;
     138: ldc_w         #709                // String  = :sort_key_val
     141: invokevirtual #108                // Method java/lang/StringBuilder.append:(Ljava/lang/String;)Ljava/lang/StringBuilder;
     144: invokevirtual #112                // Method java/lang/StringBuilder.toString:()Ljava/lang/String;
     147: goto          153
     150: ldc_w         #711                // String
     153: invokevirtual #108                // Method java/lang/StringBuilder.append:(Ljava/lang/String;)Ljava/lang/StringBuilder;
     156: invokevirtual #112                // Method java/lang/StringBuilder.toString:()Ljava/lang/String;
     159: astore        8
     161: invokestatic  #713                // Method software/amazon/awssdk/services/dynamodb/model/QueryRequest.builder:()Lsoftware/amazon/awssdk/services/dynamodb/model/QueryRequest$Builder;
     164: astore        11
     166: new           #718                // class java/util/HashMap
     169: dup
     170: invokestatic  #720                // Method software/amazon/awssdk/utils/ImmutableMap.builder:()Lsoftware/amazon/awssdk/utils/ImmutableMap$Builder;
     173: ldc_w         #725                // String #d
     176: aload         7
     178: invokeinterface #727,  1          // InterfaceMethod org/leo/aws/ddb/repositories/GSI.getHashKeyTuple:()Lorg/leo/aws/ddb/utils/Tuple;
     183: invokevirtual #127                // Method org/leo/aws/ddb/utils/Tuple._1:()Ljava/lang/Object;
     186: checkcast     #98                 // class java/lang/String
     189: invokevirtual #730                // Method software/amazon/awssdk/utils/ImmutableMap$Builder.put:(Ljava/lang/Object;Ljava/lang/Object;)Lsoftware/amazon/awssdk/utils/ImmutableMap$Builder;
     192: invokevirtual #736                // Method software/amazon/awssdk/utils/ImmutableMap$Builder.build:()Lsoftware/amazon/awssdk/utils/ImmutableMap;
     195: invokespecial #739                // Method java/util/HashMap."<init>":(Ljava/util/Map;)V
     198: astore        12
     200: new           #718                // class java/util/HashMap
     203: dup
     204: invokespecial #742                // Method java/util/HashMap."<init>":()V
     207: astore        13
     209: aload_3
     210: ifnull        244
     213: aload         13
     215: ldc_w         #814                // String :sort_key_val
     218: invokestatic  #196                // Method software/amazon/awssdk/services/dynamodb/model/AttributeValue.builder:()Lsoftware/amazon/awssdk/services/dynamodb/model/AttributeValue$Builder;
     221: aload_3
     222: invokestatic  #97                 // Method java/lang/String.valueOf:(Ljava/lang/Object;)Ljava/lang/String;
     225: invokeinterface #753,  2          // InterfaceMethod software/amazon/awssdk/services/dynamodb/model/AttributeValue$Builder.s:(Ljava/lang/String;)Lsoftware/amazon/awssdk/services/dynamodb/model/AttributeValue$Builder;
     230: invokeinterface #210,  1          // InterfaceMethod software/amazon/awssdk/services/dynamodb/model/AttributeValue$Builder.build:()Ljava/lang/Object;
     235: checkcast     #197                // class software/amazon/awssdk/services/dynamodb/model/AttributeValue
     238: invokeinterface #756,  3          // InterfaceMethod java/util/Map.put:(Ljava/lang/Object;Ljava/lang/Object;)Ljava/lang/Object;
     243: pop
     244: aload         13
     246: ldc_w         #751                // String :partition_key
     249: invokestatic  #196                // Method software/amazon/awssdk/services/dynamodb/model/AttributeValue.builder:()Lsoftware/amazon/awssdk/services/dynamodb/model/AttributeValue$Builder;
     252: aload_2
     253: invokeinterface #753,  2          // InterfaceMethod software/amazon/awssdk/services/dynamodb/model/AttributeValue$Builder.s:(Ljava/lang/String;)Lsoftware/amazon/awssdk/services/dynamodb/model/AttributeValue$Builder;
     258: invokeinterface #210,  1          // InterfaceMethod software/amazon/awssdk/services/dynamodb/model/AttributeValue$Builder.build:()Ljava/lang/Object;
     263: checkcast     #197                // class software/amazon/awssdk/services/dynamodb/model/AttributeValue
     266: invokeinterface #756,  3          // InterfaceMethod java/util/Map.put:(Ljava/lang/Object;Ljava/lang/Object;)Ljava/lang/Object;
     271: pop
     272: aload         11
     274: aload         6
     276: invokevirtual #759                // Method org/leo/aws/ddb/repositories/AttributeMapper.getTableName:()Ljava/lang/String;
     279: invokeinterface #762,  2          // InterfaceMethod software/amazon/awssdk/services/dynamodb/model/QueryRequest$Builder.tableName:(Ljava/lang/String;)Lsoftware/amazon/awssdk/services/dynamodb/model/QueryRequest$Builder;
     284: pop
     285: aload         11
     287: aload         7
     289: invokeinterface #767,  1          // InterfaceMethod org/leo/aws/ddb/repositories/GSI.getName:()Ljava/lang/String;
     294: invokeinterface #768,  2          // InterfaceMethod software/amazon/awssdk/services/dynamodb/model/QueryRequest$Builder.indexName:(Ljava/lang/String;)Lsoftware/amazon/awssdk/services/dynamodb/model/QueryRequest$Builder;
     299: pop
     300: aload_0
     301: aload         5
     303: aload         11
     305: aload         12
     307: aload         13
     309: invokevirtual #770                // Method setFilterExpression:(Lorg/leo/aws/ddb/utils/Expr;Lsoftware/amazon/awssdk/services/dynamodb/model/QueryRequest$Builder;Ljava/util/Map;Ljava/util/Map;)V
     312: aload         11
     314: aload         8
     316: invokeinterface #774,  2          // InterfaceMethod software/amazon/awssdk/services/dynamodb/model/QueryRequest$Builder.keyConditionExpression:(Ljava/lang/String;)Lsoftware/amazon/awssdk/services/dynamodb/model/QueryRequest$Builder;
     321: pop
     322: aload         11
     324: aload         12
     326: invokeinterface #777,  2          // InterfaceMethod software/amazon/awssdk/services/dynamodb/model/QueryRequest$Builder.expressionAttributeNames:(Ljava/util/Map;)Lsoftware/amazon/awssdk/services/dynamodb/model/QueryRequest$Builder;
     331: pop
     332: aload         11
     334: aload         13
     336: invokeinterface #780,  2          // InterfaceMethod software/amazon/awssdk/services/dynamodb/model/QueryRequest$Builder.expressionAttributeValues:(Ljava/util/Map;)Lsoftware/amazon/awssdk/services/dynamodb/model/QueryRequest$Builder;
     341: pop
     342: aload         11
     344: invokeinterface #782,  1          // InterfaceMethod software/amazon/awssdk/services/dynamodb/model/QueryRequest$Builder.build:()Ljava/lang/Object;
     349: checkcast     #714                // class software/amazon/awssdk/services/dynamodb/model/QueryRequest
     352: astore        9
     354: invokestatic  #369                // Method org/leo/aws/ddb/repositories/DataMapperUtils.getDynamoDbAsyncClient:()Lsoftware/amazon/awssdk/services/dynamodb/DynamoDbAsyncClient;
     357: aload         9
     359: invokeinterface #783,  2          // InterfaceMethod software/amazon/awssdk/services/dynamodb/DynamoDbAsyncClient.queryPaginator:(Lsoftware/amazon/awssdk/services/dynamodb/model/QueryRequest;)Lsoftware/amazon/awssdk/services/dynamodb/paginators/QueryPublisher;
     364: astore        10
     366: aload         7
     368: invokeinterface #787,  1          // InterfaceMethod org/leo/aws/ddb/repositories/GSI.getProjectionType:()Lorg/leo/aws/ddb/annotations/ProjectionType;
     373: aload         10
     375: invokestatic  #791                // Method org/leo/aws/ddb/utils/Tuples.of:(Ljava/lang/Object;Ljava/lang/Object;)Lorg/leo/aws/ddb/utils/Tuple;
     378: areturn

  void setFilterExpression(org.leo.aws.ddb.utils.Expr, software.amazon.awssdk.services.dynamodb.model.QueryRequest$Builder, java.util.Map<java.lang.String, java.lang.String>, java.util.Map<java.lang.String, software.amazon.awssdk.services.dynamodb.model.AttributeValue>);
    Code:
       0: aload_1
       1: ifnull        66
       4: aload_1
       5: invokeinterface #342,  1          // InterfaceMethod org/leo/aws/ddb/utils/Expr.attributeNameMap:()Ljava/util/Map;
      10: astore        5
      12: aload_1
      13: invokeinterface #348,  1          // InterfaceMethod org/leo/aws/ddb/utils/Expr.attributeValueMap:()Ljava/util/Map;
      18: astore        6
      20: aload_2
      21: aload_1
      22: invokeinterface #351,  1          // InterfaceMethod org/leo/aws/ddb/utils/Expr.expression:()Ljava/lang/String;
      27: invokeinterface #817,  2          // InterfaceMethod software/amazon/awssdk/services/dynamodb/model/QueryRequest$Builder.filterExpression:(Ljava/lang/String;)Lsoftware/amazon/awssdk/services/dynamodb/model/QueryRequest$Builder;
      32: pop
      33: aload         5
      35: invokestatic  #356                // Method org/springframework/util/CollectionUtils.isEmpty:(Ljava/util/Map;)Z
      38: ifne          49
      41: aload_3
      42: aload         5
      44: invokeinterface #819,  2          // InterfaceMethod java/util/Map.putAll:(Ljava/util/Map;)V
      49: aload         6
      51: invokestatic  #356                // Method org/springframework/util/CollectionUtils.isEmpty:(Ljava/util/Map;)Z
      54: ifne          66
      57: aload         4
      59: aload         6
      61: invokeinterface #819,  2          // InterfaceMethod java/util/Map.putAll:(Ljava/util/Map;)V
      66: return

  <ENTITY_TYPE> java.lang.Class<ENTITY_TYPE> getRepoParameterType(org.leo.aws.ddb.repositories.DynamoDbRepository<ENTITY_TYPE>);
    Code:
       0: aload_0
       1: getfield      #42                 // Field repoParameterTypeMap:Ljava/util/concurrent/ConcurrentHashMap;
       4: aload_1
       5: invokevirtual #392                // Method java/lang/Object.getClass:()Ljava/lang/Class;
       8: invokevirtual #678                // Method java/lang/Class.getName:()Ljava/lang/String;
      11: aload_1
      12: invokedynamic #825,  0            // InvokeDynamic #18:apply:(Lorg/leo/aws/ddb/repositories/DynamoDbRepository;)Ljava/util/function/Function;
      17: invokevirtual #828                // Method java/util/concurrent/ConcurrentHashMap.computeIfAbsent:(Ljava/lang/Object;Ljava/util/function/Function;)Ljava/lang/Object;
      20: checkcast     #240                // class java/lang/Class
      23: areturn

  <ENTITY_TYPE> reactor.core.publisher.Flux<ENTITY_TYPE> findByHashKeyAndRangeKeyStartsWithPagination(java.lang.String, java.lang.Object, java.lang.String, java.lang.String, org.leo.aws.ddb.data.Page, java.lang.String, java.lang.Class<ENTITY_TYPE>, org.leo.aws.ddb.utils.Expr);
    Code:
       0: aload_2
       1: instanceof    #98                 // class java/lang/String
       4: ifne          14
       7: aload_2
       8: instanceof    #141                // class java/lang/Number
      11: ifeq          477
      14: new           #718                // class java/util/HashMap
      17: dup
      18: invokespecial #742                // Method java/util/HashMap."<init>":()V
      21: astore        11
      23: new           #718                // class java/util/HashMap
      26: dup
      27: invokespecial #742                // Method java/util/HashMap."<init>":()V
      30: astore        12
      32: ldc_w         #840                // String #a
      35: pop
      36: invokestatic  #713                // Method software/amazon/awssdk/services/dynamodb/model/QueryRequest.builder:()Lsoftware/amazon/awssdk/services/dynamodb/model/QueryRequest$Builder;
      39: astore        14
      41: aload         7
      43: invokestatic  #312                // Method org/leo/aws/ddb/repositories/DataMapperUtils.getDataMapper:(Ljava/lang/Class;)Lorg/leo/aws/ddb/repositories/DataMapper;
      46: astore        15
      48: aload_3
      49: invokestatic  #460                // Method org/springframework/util/StringUtils.isEmpty:(Ljava/lang/Object;)Z
      52: ifne          92
      55: aload         4
      57: invokestatic  #460                // Method org/springframework/util/StringUtils.isEmpty:(Ljava/lang/Object;)Z
      60: ifne          92
      63: ldc_w         #842                // String {0} = :{1} and begins_with({2}, :sortKeyVal)
      66: iconst_3
      67: anewarray     #52                 // class java/lang/Object
      70: dup
      71: iconst_0
      72: ldc_w         #840                // String #a
      75: aastore
      76: dup
      77: iconst_1
      78: aload_1
      79: aastore
      80: dup
      81: iconst_2
      82: aload_3
      83: aastore
      84: invokestatic  #54                 // Method java/text/MessageFormat.format:(Ljava/lang/String;[Ljava/lang/Object;)Ljava/lang/String;
      87: astore        13
      89: goto          111
      92: new           #85                 // class java/lang/StringBuilder
      95: dup
      96: ldc_w         #844                // String #a = :
      99: invokespecial #103                // Method java/lang/StringBuilder."<init>":(Ljava/lang/String;)V
     102: aload_1
     103: invokevirtual #108                // Method java/lang/StringBuilder.append:(Ljava/lang/String;)Ljava/lang/StringBuilder;
     106: invokevirtual #112                // Method java/lang/StringBuilder.toString:()Ljava/lang/String;
     109: astore        13
     111: aload         11
     113: ldc_w         #840                // String #a
     116: aload_1
     117: invokeinterface #756,  3          // InterfaceMethod java/util/Map.put:(Ljava/lang/Object;Ljava/lang/Object;)Ljava/lang/Object;
     122: pop
     123: aload_2
     124: instanceof    #98                 // class java/lang/String
     127: ifeq          175
     130: aload         12
     132: ldc_w         #846                // String :{0}
     135: iconst_1
     136: anewarray     #52                 // class java/lang/Object
     139: dup
     140: iconst_0
     141: aload_1
     142: aastore
     143: invokestatic  #54                 // Method java/text/MessageFormat.format:(Ljava/lang/String;[Ljava/lang/Object;)Ljava/lang/String;
     146: invokestatic  #196                // Method software/amazon/awssdk/services/dynamodb/model/AttributeValue.builder:()Lsoftware/amazon/awssdk/services/dynamodb/model/AttributeValue$Builder;
     149: aload_2
     150: checkcast     #98                 // class java/lang/String
     153: invokeinterface #753,  2          // InterfaceMethod software/amazon/awssdk/services/dynamodb/model/AttributeValue$Builder.s:(Ljava/lang/String;)Lsoftware/amazon/awssdk/services/dynamodb/model/AttributeValue$Builder;
     158: invokeinterface #210,  1          // InterfaceMethod software/amazon/awssdk/services/dynamodb/model/AttributeValue$Builder.build:()Ljava/lang/Object;
     163: checkcast     #197                // class software/amazon/awssdk/services/dynamodb/model/AttributeValue
     166: invokeinterface #756,  3          // InterfaceMethod java/util/Map.put:(Ljava/lang/Object;Ljava/lang/Object;)Ljava/lang/Object;
     171: pop
     172: goto          220
     175: aload         12
     177: ldc_w         #846                // String :{0}
     180: iconst_1
     181: anewarray     #52                 // class java/lang/Object
     184: dup
     185: iconst_0
     186: aload_1
     187: aastore
     188: invokestatic  #54                 // Method java/text/MessageFormat.format:(Ljava/lang/String;[Ljava/lang/Object;)Ljava/lang/String;
     191: invokestatic  #196                // Method software/amazon/awssdk/services/dynamodb/model/AttributeValue.builder:()Lsoftware/amazon/awssdk/services/dynamodb/model/AttributeValue$Builder;
     194: aload_2
     195: checkcast     #141                // class java/lang/Number
     198: invokestatic  #848                // Method org/leo/aws/ddb/utils/Utils.getUnformattedNumber:(Ljava/lang/Number;)Ljava/lang/String;
     201: invokeinterface #204,  2          // InterfaceMethod software/amazon/awssdk/services/dynamodb/model/AttributeValue$Builder.n:(Ljava/lang/String;)Lsoftware/amazon/awssdk/services/dynamodb/model/AttributeValue$Builder;
     206: invokeinterface #210,  1          // InterfaceMethod software/amazon/awssdk/services/dynamodb/model/AttributeValue$Builder.build:()Ljava/lang/Object;
     211: checkcast     #197                // class software/amazon/awssdk/services/dynamodb/model/AttributeValue
     214: invokeinterface #756,  3          // InterfaceMethod java/util/Map.put:(Ljava/lang/Object;Ljava/lang/Object;)Ljava/lang/Object;
     219: pop
     220: aload_3
     221: invokestatic  #460                // Method org/springframework/util/StringUtils.isEmpty:(Ljava/lang/Object;)Z
     224: ifne          264
     227: aload         4
     229: invokestatic  #460                // Method org/springframework/util/StringUtils.isEmpty:(Ljava/lang/Object;)Z
     232: ifne          264
     235: aload         12
     237: ldc_w         #854                // String :sortKeyVal
     240: invokestatic  #196                // Method software/amazon/awssdk/services/dynamodb/model/AttributeValue.builder:()Lsoftware/amazon/awssdk/services/dynamodb/model/AttributeValue$Builder;
     243: aload         4
     245: invokeinterface #753,  2          // InterfaceMethod software/amazon/awssdk/services/dynamodb/model/AttributeValue$Builder.s:(Ljava/lang/String;)Lsoftware/amazon/awssdk/services/dynamodb/model/AttributeValue$Builder;
     250: invokeinterface #210,  1          // InterfaceMethod software/amazon/awssdk/services/dynamodb/model/AttributeValue$Builder.build:()Ljava/lang/Object;
     255: checkcast     #197                // class software/amazon/awssdk/services/dynamodb/model/AttributeValue
     258: invokeinterface #756,  3          // InterfaceMethod java/util/Map.put:(Ljava/lang/Object;Ljava/lang/Object;)Ljava/lang/Object;
     263: pop
     264: aload         6
     266: invokestatic  #460                // Method org/springframework/util/StringUtils.isEmpty:(Ljava/lang/Object;)Z
     269: ifne          282
     272: aload         14
     274: aload         6
     276: invokeinterface #768,  2          // InterfaceMethod software/amazon/awssdk/services/dynamodb/model/QueryRequest$Builder.indexName:(Ljava/lang/String;)Lsoftware/amazon/awssdk/services/dynamodb/model/QueryRequest$Builder;
     281: pop
     282: aload_0
     283: aload         8
     285: aload         14
     287: aload         11
     289: aload         12
     291: invokevirtual #770                // Method setFilterExpression:(Lorg/leo/aws/ddb/utils/Expr;Lsoftware/amazon/awssdk/services/dynamodb/model/QueryRequest$Builder;Ljava/util/Map;Ljava/util/Map;)V
     294: aload         5
     296: ifnull        391
     299: aload         14
     301: aload         5
     303: invokevirtual #856                // Method org/leo/aws/ddb/data/Page.getPageSize:()I
     306: invokestatic  #147                // Method java/lang/Integer.valueOf:(I)Ljava/lang/Integer;
     309: invokeinterface #861,  2          // InterfaceMethod software/amazon/awssdk/services/dynamodb/model/QueryRequest$Builder.limit:(Ljava/lang/Integer;)Lsoftware/amazon/awssdk/services/dynamodb/model/QueryRequest$Builder;
     314: pop
     315: aload         5
     317: invokevirtual #864                // Method org/leo/aws/ddb/data/Page.getLastEndKey:()Lorg/leo/aws/ddb/data/PrimaryKey;
     320: ifnull        391
     323: aload         5
     325: invokevirtual #864                // Method org/leo/aws/ddb/data/Page.getLastEndKey:()Lorg/leo/aws/ddb/data/PrimaryKey;
     328: invokevirtual #868                // Method org/leo/aws/ddb/data/PrimaryKey.getRangeKeyValue:()Ljava/lang/Object;
     331: checkcast     #98                 // class java/lang/String
     334: astore        16
     336: aload         4
     338: invokestatic  #460                // Method org/springframework/util/StringUtils.isEmpty:(Ljava/lang/Object;)Z
     341: ifne          354
     344: aload         16
     346: aload         4
     348: invokevirtual #871                // Method java/lang/String.startsWith:(Ljava/lang/String;)Z
     351: ifeq          377
     354: aload         14
     356: aload         15
     358: aload         5
     360: invokevirtual #864                // Method org/leo/aws/ddb/data/Page.getLastEndKey:()Lorg/leo/aws/ddb/data/PrimaryKey;
     363: invokeinterface #875,  2          // InterfaceMethod org/leo/aws/ddb/repositories/DataMapper.getPrimaryKey:(Lorg/leo/aws/ddb/data/PrimaryKey;)Ljava/util/Map;
     368: invokeinterface #879,  2          // InterfaceMethod software/amazon/awssdk/services/dynamodb/model/QueryRequest$Builder.exclusiveStartKey:(Ljava/util/Map;)Lsoftware/amazon/awssdk/services/dynamodb/model/QueryRequest$Builder;
     373: pop
     374: goto          391
     377: new           #83                 // class org/leo/aws/ddb/exceptions/DbException
     380: dup
     381: ldc_w         #882                // String INVALID_RANGE_KEY_VALUE
     384: invokespecial #693                // Method org/leo/aws/ddb/exceptions/DbException."<init>":(Ljava/lang/String;)V
     387: invokestatic  #884                // Method reactor/core/publisher/Flux.error:(Ljava/lang/Throwable;)Lreactor/core/publisher/Flux;
     390: areturn
     391: aload         14
     393: aload         15
     395: invokeinterface #323,  1          // InterfaceMethod org/leo/aws/ddb/repositories/DataMapper.tableName:()Ljava/lang/String;
     400: invokeinterface #762,  2          // InterfaceMethod software/amazon/awssdk/services/dynamodb/model/QueryRequest$Builder.tableName:(Ljava/lang/String;)Lsoftware/amazon/awssdk/services/dynamodb/model/QueryRequest$Builder;
     405: aload         13
     407: invokeinterface #774,  2          // InterfaceMethod software/amazon/awssdk/services/dynamodb/model/QueryRequest$Builder.keyConditionExpression:(Ljava/lang/String;)Lsoftware/amazon/awssdk/services/dynamodb/model/QueryRequest$Builder;
     412: aload         11
     414: invokeinterface #777,  2          // InterfaceMethod software/amazon/awssdk/services/dynamodb/model/QueryRequest$Builder.expressionAttributeNames:(Ljava/util/Map;)Lsoftware/amazon/awssdk/services/dynamodb/model/QueryRequest$Builder;
     419: aload         12
     421: invokeinterface #780,  2          // InterfaceMethod software/amazon/awssdk/services/dynamodb/model/QueryRequest$Builder.expressionAttributeValues:(Ljava/util/Map;)Lsoftware/amazon/awssdk/services/dynamodb/model/QueryRequest$Builder;
     426: invokeinterface #782,  1          // InterfaceMethod software/amazon/awssdk/services/dynamodb/model/QueryRequest$Builder.build:()Ljava/lang/Object;
     431: checkcast     #714                // class software/amazon/awssdk/services/dynamodb/model/QueryRequest
     434: astore        9
     436: invokestatic  #369                // Method org/leo/aws/ddb/repositories/DataMapperUtils.getDynamoDbAsyncClient:()Lsoftware/amazon/awssdk/services/dynamodb/DynamoDbAsyncClient;
     439: aload         9
     441: invokeinterface #783,  2          // InterfaceMethod software/amazon/awssdk/services/dynamodb/DynamoDbAsyncClient.queryPaginator:(Lsoftware/amazon/awssdk/services/dynamodb/model/QueryRequest;)Lsoftware/amazon/awssdk/services/dynamodb/paginators/QueryPublisher;
     446: astore        10
     448: aload         10
     450: invokestatic  #380                // Method reactor/core/publisher/Flux.from:(Lorg/reactivestreams/Publisher;)Lreactor/core/publisher/Flux;
     453: invokedynamic #887,  0            // InvokeDynamic #19:apply:()Ljava/util/function/Function;
     458: invokevirtual #388                // Method reactor/core/publisher/Flux.flatMapIterable:(Ljava/util/function/Function;)Lreactor/core/publisher/Flux;
     461: aload         15
     463: dup
     464: invokevirtual #392                // Method java/lang/Object.getClass:()Ljava/lang/Class;
     467: pop
     468: invokedynamic #888,  0            // InvokeDynamic #20:apply:(Lorg/leo/aws/ddb/repositories/DataMapper;)Ljava/util/function/Function;
     473: invokevirtual #398                // Method reactor/core/publisher/Flux.map:(Ljava/util/function/Function;)Lreactor/core/publisher/Flux;
     476: areturn
     477: new           #83                 // class org/leo/aws/ddb/exceptions/DbException
     480: dup
     481: ldc_w         #889                // String Currently only String/Number types are supported for hashKey Values
     484: invokespecial #693                // Method org/leo/aws/ddb/exceptions/DbException."<init>":(Ljava/lang/String;)V
     487: athrow

  public static org.leo.aws.ddb.repositories.BaseRepositoryUtils[] values();
    Code:
       0: getstatic     #25                 // Field ENUM$VALUES:[Lorg/leo/aws/ddb/repositories/BaseRepositoryUtils;
       3: dup
       4: astore_0
       5: iconst_0
       6: aload_0
       7: arraylength
       8: dup
       9: istore_1
      10: anewarray     #1                  // class org/leo/aws/ddb/repositories/BaseRepositoryUtils
      13: dup
      14: astore_2
      15: iconst_0
      16: iload_1
      17: invokestatic  #899                // Method java/lang/System.arraycopy:(Ljava/lang/Object;ILjava/lang/Object;II)V
      20: aload_2
      21: areturn

  public static org.leo.aws.ddb.repositories.BaseRepositoryUtils valueOf(java.lang.String);
    Code:
       0: ldc           #1                  // class org/leo/aws/ddb/repositories/BaseRepositoryUtils
       2: aload_0
       3: invokestatic  #906                // Method java/lang/Enum.valueOf:(Ljava/lang/Class;Ljava/lang/String;)Ljava/lang/Enum;
       6: checkcast     #1                  // class org/leo/aws/ddb/repositories/BaseRepositoryUtils
       9: areturn

  private org.reactivestreams.Publisher lambda$0(rx.functions.Func0, org.leo.aws.ddb.repositories.DataMapper, rx.functions.Func1);
    Code:
       0: aload_0
       1: aload_1
       2: aload_2
       3: invokeinterface #323,  1          // InterfaceMethod org/leo/aws/ddb/repositories/DataMapper.tableName:()Ljava/lang/String;
       8: aload_3
       9: aload_2
      10: invokeinterface #911,  2          // InterfaceMethod rx/functions/Func1.call:(Ljava/lang/Object;)Ljava/lang/Object;
      15: checkcast     #564                // class java/util/stream/Stream
      18: invokestatic  #568                // Method java/util/stream/Collectors.toList:()Ljava/util/stream/Collector;
      21: invokeinterface #574,  2          // InterfaceMethod java/util/stream/Stream.collect:(Ljava/util/stream/Collector;)Ljava/lang/Object;
      26: checkcast     #557                // class java/util/List
      29: invokestatic  #184                // Method com/google/common/collect/ImmutableMap.of:(Ljava/lang/Object;Ljava/lang/Object;)Lcom/google/common/collect/ImmutableMap;
      32: invokevirtual #915                // Method processBatchWriteRequest:(Lrx/functions/Func0;Ljava/util/Map;)Ljava/util/concurrent/CompletableFuture;
      35: invokestatic  #917                // Method reactor/core/publisher/Mono.fromFuture:(Ljava/util/concurrent/CompletableFuture;)Lreactor/core/publisher/Mono;
      38: invokedynamic #921,  0            // InvokeDynamic #21:apply:()Ljava/util/function/Function;
      43: invokevirtual #922                // Method reactor/core/publisher/Mono.flatMapMany:(Ljava/util/function/Function;)Lreactor/core/publisher/Flux;
      46: areturn

  private reactor.core.publisher.Mono lambda$2(org.leo.aws.ddb.repositories.DataMapper, java.lang.Class, java.util.Map, org.leo.aws.ddb.data.PrimaryKey, java.lang.Object);
    Code:
       0: aload_1
       1: invokeinterface #434,  1          // InterfaceMethod org/leo/aws/ddb/repositories/DataMapper.getVersionedAttribute:()Lorg/leo/aws/ddb/utils/Tuple;
       6: astore        6
       8: invokestatic  #927                // Method software/amazon/awssdk/services/dynamodb/model/UpdateItemRequest.builder:()Lsoftware/amazon/awssdk/services/dynamodb/model/UpdateItemRequest$Builder;
      11: astore        7
      13: invokestatic  #669                // Method org/leo/aws/ddb/repositories/MapperUtils.getInstance:()Lorg/leo/aws/ddb/repositories/MapperUtils;
      16: aload_2
      17: invokevirtual #678                // Method java/lang/Class.getName:()Ljava/lang/String;
      20: invokevirtual #932                // Method org/leo/aws/ddb/repositories/MapperUtils.getMappedValues:(Ljava/lang/String;)Ljava/util/stream/Stream;
      23: invokedynamic #936,  0            // InvokeDynamic #22:apply:()Ljava/util/function/Function;
      28: invokedynamic #937,  0            // InvokeDynamic #23:apply:()Ljava/util/function/Function;
      33: invokestatic  #579                // Method java/util/stream/Collectors.toMap:(Ljava/util/function/Function;Ljava/util/function/Function;)Ljava/util/stream/Collector;
      36: invokeinterface #574,  2          // InterfaceMethod java/util/stream/Stream.collect:(Ljava/util/stream/Collector;)Ljava/lang/Object;
      41: checkcast     #410                // class java/util/Map
      44: astore        8
      46: aload_3
      47: invokeinterface #938,  1          // InterfaceMethod java/util/Map.entrySet:()Ljava/util/Set;
      52: invokeinterface #942,  1          // InterfaceMethod java/util/Set.stream:()Ljava/util/stream/Stream;
      57: aload         4
      59: invokedynamic #945,  0            // InvokeDynamic #24:test:(Lorg/leo/aws/ddb/data/PrimaryKey;)Ljava/util/function/Predicate;
      64: invokeinterface #948,  2          // InterfaceMethod java/util/stream/Stream.filter:(Ljava/util/function/Predicate;)Ljava/util/stream/Stream;
      69: aload         4
      71: invokedynamic #952,  0            // InvokeDynamic #25:test:(Lorg/leo/aws/ddb/data/PrimaryKey;)Ljava/util/function/Predicate;
      76: invokeinterface #948,  2          // InterfaceMethod java/util/stream/Stream.filter:(Ljava/util/function/Predicate;)Ljava/util/stream/Stream;
      81: aload         8
      83: invokedynamic #953,  0            // InvokeDynamic #26:accept:(Ljava/util/Map;)Ljava/util/function/Consumer;
      88: invokeinterface #954,  2          // InterfaceMethod java/util/stream/Stream.peek:(Ljava/util/function/Consumer;)Ljava/util/stream/Stream;
      93: aload         8
      95: invokedynamic #958,  0            // InvokeDynamic #27:apply:(Ljava/util/Map;)Ljava/util/function/Function;
     100: invokeinterface #563,  2          // InterfaceMethod java/util/stream/Stream.map:(Ljava/util/function/Function;)Ljava/util/stream/Stream;
     105: astore        9
     107: aload         9
     109: invokedynamic #961,  0            // InvokeDynamic #28:apply:()Ljava/util/function/Function;
     114: invokedynamic #962,  0            // InvokeDynamic #29:apply:()Ljava/util/function/Function;
     119: invokestatic  #579                // Method java/util/stream/Collectors.toMap:(Ljava/util/function/Function;Ljava/util/function/Function;)Ljava/util/stream/Collector;
     122: invokeinterface #574,  2          // InterfaceMethod java/util/stream/Stream.collect:(Ljava/util/stream/Collector;)Ljava/lang/Object;
     127: checkcast     #410                // class java/util/Map
     130: astore        10
     132: aload_0
     133: aload         5
     135: aload         6
     137: aload         7
     139: invokevirtual #963                // Method setVersion:(Ljava/lang/Object;Lorg/leo/aws/ddb/utils/Tuple;Lsoftware/amazon/awssdk/services/dynamodb/model/UpdateItemRequest$Builder;)Ljava/lang/Integer;
     142: astore        12
     144: aload         6
     146: ifnull        218
     149: invokestatic  #965                // Method com/google/common/collect/ImmutableMap.builder:()Lcom/google/common/collect/ImmutableMap$Builder;
     152: aload         10
     154: invokevirtual #968                // Method com/google/common/collect/ImmutableMap$Builder.putAll:(Ljava/util/Map;)Lcom/google/common/collect/ImmutableMap$Builder;
     157: aload         6
     159: invokevirtual #156                // Method org/leo/aws/ddb/utils/Tuple._2:()Ljava/lang/Object;
     162: checkcast     #159                // class org/leo/aws/ddb/annotations/DbAttribute
     165: invokeinterface #161,  1          // InterfaceMethod org/leo/aws/ddb/annotations/DbAttribute.value:()Ljava/lang/String;
     170: invokestatic  #973                // Method software/amazon/awssdk/services/dynamodb/model/AttributeValueUpdate.builder:()Lsoftware/amazon/awssdk/services/dynamodb/model/AttributeValueUpdate$Builder;
     173: invokestatic  #196                // Method software/amazon/awssdk/services/dynamodb/model/AttributeValue.builder:()Lsoftware/amazon/awssdk/services/dynamodb/model/AttributeValue$Builder;
     176: aload         12
     178: invokestatic  #97                 // Method java/lang/String.valueOf:(Ljava/lang/Object;)Ljava/lang/String;
     181: invokeinterface #204,  2          // InterfaceMethod software/amazon/awssdk/services/dynamodb/model/AttributeValue$Builder.n:(Ljava/lang/String;)Lsoftware/amazon/awssdk/services/dynamodb/model/AttributeValue$Builder;
     186: invokeinterface #210,  1          // InterfaceMethod software/amazon/awssdk/services/dynamodb/model/AttributeValue$Builder.build:()Ljava/lang/Object;
     191: checkcast     #197                // class software/amazon/awssdk/services/dynamodb/model/AttributeValue
     194: invokeinterface #978,  2          // InterfaceMethod software/amazon/awssdk/services/dynamodb/model/AttributeValueUpdate$Builder.value:(Lsoftware/amazon/awssdk/services/dynamodb/model/AttributeValue;)Lsoftware/amazon/awssdk/services/dynamodb/model/AttributeValueUpdate$Builder;
     199: invokeinterface #983,  1          // InterfaceMethod software/amazon/awssdk/services/dynamodb/model/AttributeValueUpdate$Builder.build:()Ljava/lang/Object;
     204: checkcast     #974                // class software/amazon/awssdk/services/dynamodb/model/AttributeValueUpdate
     207: invokevirtual #984                // Method com/google/common/collect/ImmutableMap$Builder.put:(Ljava/lang/Object;Ljava/lang/Object;)Lcom/google/common/collect/ImmutableMap$Builder;
     210: invokevirtual #987                // Method com/google/common/collect/ImmutableMap$Builder.build:()Lcom/google/common/collect/ImmutableMap;
     213: astore        11
     215: goto          222
     218: aload         10
     220: astore        11
     222: invokestatic  #369                // Method org/leo/aws/ddb/repositories/DataMapperUtils.getDynamoDbAsyncClient:()Lsoftware/amazon/awssdk/services/dynamodb/DynamoDbAsyncClient;
     225: aload         7
     227: aload_1
     228: invokeinterface #323,  1          // InterfaceMethod org/leo/aws/ddb/repositories/DataMapper.tableName:()Ljava/lang/String;
     233: invokeinterface #990,  2          // InterfaceMethod software/amazon/awssdk/services/dynamodb/model/UpdateItemRequest$Builder.tableName:(Ljava/lang/String;)Lsoftware/amazon/awssdk/services/dynamodb/model/UpdateItemRequest$Builder;
     238: aload_1
     239: aload         4
     241: invokeinterface #875,  2          // InterfaceMethod org/leo/aws/ddb/repositories/DataMapper.getPrimaryKey:(Lorg/leo/aws/ddb/data/PrimaryKey;)Ljava/util/Map;
     246: invokeinterface #993,  2          // InterfaceMethod software/amazon/awssdk/services/dynamodb/model/UpdateItemRequest$Builder.key:(Ljava/util/Map;)Lsoftware/amazon/awssdk/services/dynamodb/model/UpdateItemRequest$Builder;
     251: aload         11
     253: invokeinterface #996,  2          // InterfaceMethod software/amazon/awssdk/services/dynamodb/model/UpdateItemRequest$Builder.attributeUpdates:(Ljava/util/Map;)Lsoftware/amazon/awssdk/services/dynamodb/model/UpdateItemRequest$Builder;
     258: getstatic     #999                // Field software/amazon/awssdk/services/dynamodb/model/ReturnValue.ALL_NEW:Lsoftware/amazon/awssdk/services/dynamodb/model/ReturnValue;
     261: invokeinterface #1005,  2         // InterfaceMethod software/amazon/awssdk/services/dynamodb/model/UpdateItemRequest$Builder.returnValues:(Lsoftware/amazon/awssdk/services/dynamodb/model/ReturnValue;)Lsoftware/amazon/awssdk/services/dynamodb/model/UpdateItemRequest$Builder;
     266: invokeinterface #1009,  1         // InterfaceMethod software/amazon/awssdk/services/dynamodb/model/UpdateItemRequest$Builder.build:()Ljava/lang/Object;
     271: checkcast     #928                // class software/amazon/awssdk/services/dynamodb/model/UpdateItemRequest
     274: invokeinterface #1010,  2         // InterfaceMethod software/amazon/awssdk/services/dynamodb/DynamoDbAsyncClient.updateItem:(Lsoftware/amazon/awssdk/services/dynamodb/model/UpdateItemRequest;)Ljava/util/concurrent/CompletableFuture;
     279: aload_1
     280: invokedynamic #1013,  0           // InvokeDynamic #30:apply:(Lorg/leo/aws/ddb/repositories/DataMapper;)Ljava/util/function/Function;
     285: invokevirtual #497                // Method java/util/concurrent/CompletableFuture.thenApplyAsync:(Ljava/util/function/Function;)Ljava/util/concurrent/CompletableFuture;
     288: invokestatic  #917                // Method reactor/core/publisher/Mono.fromFuture:(Ljava/util/concurrent/CompletableFuture;)Lreactor/core/publisher/Mono;
     291: areturn

  private org.reactivestreams.Publisher lambda$12(java.util.function.Function, java.lang.Object, java.util.function.Supplier, java.lang.Object, java.lang.String, org.leo.aws.ddb.utils.Expr, java.util.function.Function);
    Code:
       0: aload_2
       1: instanceof    #98                 // class java/lang/String
       4: ifeq          137
       7: aload_3
       8: invokeinterface #308,  1          // InterfaceMethod java/util/function/Supplier.get:()Ljava/lang/Object;
      13: checkcast     #240                // class java/lang/Class
      16: astore        12
      18: aload         4
      20: ifnull        42
      23: aload         4
      25: instanceof    #98                 // class java/lang/String
      28: ifne          42
      31: new           #83                 // class org/leo/aws/ddb/exceptions/DbException
      34: dup
      35: ldc_w         #1024               // String Currently only String types are supported for sortKey Values
      38: invokespecial #693                // Method org/leo/aws/ddb/exceptions/DbException."<init>":(Ljava/lang/String;)V
      41: athrow
      42: aload_2
      43: checkcast     #98                 // class java/lang/String
      46: astore        8
      48: aload_0
      49: aload         5
      51: aload         8
      53: aload         4
      55: aload         12
      57: aload         6
      59: invokevirtual #1026               // Method getDataFromIndex:(Ljava/lang/String;Ljava/lang/String;Ljava/lang/Object;Ljava/lang/Class;Lorg/leo/aws/ddb/utils/Expr;)Lorg/leo/aws/ddb/utils/Tuple;
      62: astore        9
      64: aload         9
      66: invokevirtual #156                // Method org/leo/aws/ddb/utils/Tuple._2:()Ljava/lang/Object;
      69: checkcast     #1028               // class org/reactivestreams/Publisher
      72: invokestatic  #380                // Method reactor/core/publisher/Flux.from:(Lorg/reactivestreams/Publisher;)Lreactor/core/publisher/Flux;
      75: invokedynamic #887,  0            // InvokeDynamic #19:apply:()Ljava/util/function/Function;
      80: invokevirtual #388                // Method reactor/core/publisher/Flux.flatMapIterable:(Ljava/util/function/Function;)Lreactor/core/publisher/Flux;
      83: aload         12
      85: invokedynamic #1030,  0           // InvokeDynamic #31:apply:(Ljava/lang/Class;)Ljava/util/function/Function;
      90: invokevirtual #398                // Method reactor/core/publisher/Flux.map:(Ljava/util/function/Function;)Lreactor/core/publisher/Flux;
      93: astore        10
      95: aload         9
      97: invokevirtual #127                // Method org/leo/aws/ddb/utils/Tuple._1:()Ljava/lang/Object;
     100: getstatic     #1033               // Field org/leo/aws/ddb/annotations/ProjectionType.ALL:Lorg/leo/aws/ddb/annotations/ProjectionType;
     103: if_acmpne     113
     106: aload         10
     108: astore        11
     110: goto          134
     113: aload         10
     115: aload         7
     117: invokevirtual #398                // Method reactor/core/publisher/Flux.map:(Ljava/util/function/Function;)Lreactor/core/publisher/Flux;
     120: invokevirtual #1039               // Method reactor/core/publisher/Flux.collectList:()Lreactor/core/publisher/Mono;
     123: aload_1
     124: invokedynamic #1043,  0           // InvokeDynamic #32:apply:(Ljava/util/function/Function;)Ljava/util/function/Function;
     129: invokevirtual #922                // Method reactor/core/publisher/Mono.flatMapMany:(Ljava/util/function/Function;)Lreactor/core/publisher/Flux;
     132: astore        11
     134: aload         11
     136: areturn
     137: new           #83                 // class org/leo/aws/ddb/exceptions/DbException
     140: dup
     141: ldc_w         #1046               // String Currently only String types are supported for hashKey Values
     144: invokespecial #693                // Method org/leo/aws/ddb/exceptions/DbException."<init>":(Ljava/lang/String;)V
     147: athrow

  private static reactor.core.publisher.Mono lambda$18(java.util.function.Supplier, org.leo.aws.ddb.data.PrimaryKey);
    Code:
       0: aload_0
       1: invokeinterface #308,  1          // InterfaceMethod java/util/function/Supplier.get:()Ljava/lang/Object;
       6: checkcast     #240                // class java/lang/Class
       9: invokestatic  #312                // Method org/leo/aws/ddb/repositories/DataMapperUtils.getDataMapper:(Ljava/lang/Class;)Lorg/leo/aws/ddb/repositories/DataMapper;
      12: astore_2
      13: invokestatic  #1054               // Method software/amazon/awssdk/services/dynamodb/model/GetItemRequest.builder:()Lsoftware/amazon/awssdk/services/dynamodb/model/GetItemRequest$Builder;
      16: aload_2
      17: aload_1
      18: invokeinterface #875,  2          // InterfaceMethod org/leo/aws/ddb/repositories/DataMapper.getPrimaryKey:(Lorg/leo/aws/ddb/data/PrimaryKey;)Ljava/util/Map;
      23: invokeinterface #1059,  2         // InterfaceMethod software/amazon/awssdk/services/dynamodb/model/GetItemRequest$Builder.key:(Ljava/util/Map;)Lsoftware/amazon/awssdk/services/dynamodb/model/GetItemRequest$Builder;
      28: aload_2
      29: invokeinterface #323,  1          // InterfaceMethod org/leo/aws/ddb/repositories/DataMapper.tableName:()Ljava/lang/String;
      34: invokeinterface #1064,  2         // InterfaceMethod software/amazon/awssdk/services/dynamodb/model/GetItemRequest$Builder.tableName:(Ljava/lang/String;)Lsoftware/amazon/awssdk/services/dynamodb/model/GetItemRequest$Builder;
      39: invokeinterface #1067,  1         // InterfaceMethod software/amazon/awssdk/services/dynamodb/model/GetItemRequest$Builder.build:()Ljava/lang/Object;
      44: checkcast     #1055               // class software/amazon/awssdk/services/dynamodb/model/GetItemRequest
      47: astore_3
      48: invokestatic  #369                // Method org/leo/aws/ddb/repositories/DataMapperUtils.getDynamoDbAsyncClient:()Lsoftware/amazon/awssdk/services/dynamodb/DynamoDbAsyncClient;
      51: aload_3
      52: invokeinterface #1068,  2         // InterfaceMethod software/amazon/awssdk/services/dynamodb/DynamoDbAsyncClient.getItem:(Lsoftware/amazon/awssdk/services/dynamodb/model/GetItemRequest;)Ljava/util/concurrent/CompletableFuture;
      57: invokestatic  #1072               // Method reactor/core/publisher/Mono.fromCompletionStage:(Ljava/util/concurrent/CompletionStage;)Lreactor/core/publisher/Mono;
      60: aload_2
      61: invokedynamic #1076,  0           // InvokeDynamic #33:apply:(Lorg/leo/aws/ddb/repositories/DataMapper;)Ljava/util/function/Function;
      66: invokevirtual #545                // Method reactor/core/publisher/Mono.flatMap:(Ljava/util/function/Function;)Lreactor/core/publisher/Mono;
      69: areturn

  private static org.reactivestreams.Publisher lambda$20(java.util.function.Supplier, java.util.List);
    Code:
       0: aload_0
       1: invokeinterface #308,  1          // InterfaceMethod java/util/function/Supplier.get:()Ljava/lang/Object;
       6: checkcast     #240                // class java/lang/Class
       9: invokestatic  #312                // Method org/leo/aws/ddb/repositories/DataMapperUtils.getDataMapper:(Ljava/lang/Class;)Lorg/leo/aws/ddb/repositories/DataMapper;
      12: astore_2
      13: new           #1081               // class java/util/ArrayList
      16: dup
      17: new           #1083               // class java/util/HashSet
      20: dup
      21: aload_1
      22: invokespecial #1085               // Method java/util/HashSet."<init>":(Ljava/util/Collection;)V
      25: invokespecial #1088               // Method java/util/ArrayList."<init>":(Ljava/util/Collection;)V
      28: astore_3
      29: invokestatic  #1089               // Method software/amazon/awssdk/services/dynamodb/model/KeysAndAttributes.builder:()Lsoftware/amazon/awssdk/services/dynamodb/model/KeysAndAttributes$Builder;
      32: aload_3
      33: invokeinterface #556,  1          // InterfaceMethod java/util/List.stream:()Ljava/util/stream/Stream;
      38: aload_2
      39: dup
      40: invokevirtual #392                // Method java/lang/Object.getClass:()Ljava/lang/Class;
      43: pop
      44: invokedynamic #1094,  0           // InvokeDynamic #34:apply:(Lorg/leo/aws/ddb/repositories/DataMapper;)Ljava/util/function/Function;
      49: invokeinterface #563,  2          // InterfaceMethod java/util/stream/Stream.map:(Ljava/util/function/Function;)Ljava/util/stream/Stream;
      54: invokestatic  #568                // Method java/util/stream/Collectors.toList:()Ljava/util/stream/Collector;
      57: invokeinterface #574,  2          // InterfaceMethod java/util/stream/Stream.collect:(Ljava/util/stream/Collector;)Ljava/lang/Object;
      62: checkcast     #1095               // class java/util/Collection
      65: invokeinterface #1097,  2         // InterfaceMethod software/amazon/awssdk/services/dynamodb/model/KeysAndAttributes$Builder.keys:(Ljava/util/Collection;)Lsoftware/amazon/awssdk/services/dynamodb/model/KeysAndAttributes$Builder;
      70: invokeinterface #1103,  1         // InterfaceMethod software/amazon/awssdk/services/dynamodb/model/KeysAndAttributes$Builder.build:()Ljava/lang/Object;
      75: checkcast     #1090               // class software/amazon/awssdk/services/dynamodb/model/KeysAndAttributes
      78: astore        4
      80: new           #718                // class java/util/HashMap
      83: dup
      84: invokespecial #742                // Method java/util/HashMap."<init>":()V
      87: astore        6
      89: aload         6
      91: aload_2
      92: invokeinterface #323,  1          // InterfaceMethod org/leo/aws/ddb/repositories/DataMapper.tableName:()Ljava/lang/String;
      97: aload         4
      99: invokeinterface #756,  3          // InterfaceMethod java/util/Map.put:(Ljava/lang/Object;Ljava/lang/Object;)Ljava/lang/Object;
     104: pop
     105: invokestatic  #1104               // Method software/amazon/awssdk/services/dynamodb/model/BatchGetItemRequest.builder:()Lsoftware/amazon/awssdk/services/dynamodb/model/BatchGetItemRequest$Builder;
     108: aload         6
     110: invokeinterface #1109,  2         // InterfaceMethod software/amazon/awssdk/services/dynamodb/model/BatchGetItemRequest$Builder.requestItems:(Ljava/util/Map;)Lsoftware/amazon/awssdk/services/dynamodb/model/BatchGetItemRequest$Builder;
     115: invokeinterface #1114,  1         // InterfaceMethod software/amazon/awssdk/services/dynamodb/model/BatchGetItemRequest$Builder.build:()Ljava/lang/Object;
     120: checkcast     #1105               // class software/amazon/awssdk/services/dynamodb/model/BatchGetItemRequest
     123: astore        7
     125: invokestatic  #369                // Method org/leo/aws/ddb/repositories/DataMapperUtils.getDynamoDbAsyncClient:()Lsoftware/amazon/awssdk/services/dynamodb/DynamoDbAsyncClient;
     128: aload         7
     130: invokeinterface #1115,  2         // InterfaceMethod software/amazon/awssdk/services/dynamodb/DynamoDbAsyncClient.batchGetItemPaginator:(Lsoftware/amazon/awssdk/services/dynamodb/model/BatchGetItemRequest;)Lsoftware/amazon/awssdk/services/dynamodb/paginators/BatchGetItemPublisher;
     135: invokestatic  #380                // Method reactor/core/publisher/Flux.from:(Lorg/reactivestreams/Publisher;)Lreactor/core/publisher/Flux;
     138: aload_2
     139: invokedynamic #1119,  0           // InvokeDynamic #35:apply:(Lorg/leo/aws/ddb/repositories/DataMapper;)Ljava/util/function/Function;
     144: invokevirtual #388                // Method reactor/core/publisher/Flux.flatMapIterable:(Ljava/util/function/Function;)Lreactor/core/publisher/Flux;
     147: aload_2
     148: dup
     149: invokevirtual #392                // Method java/lang/Object.getClass:()Ljava/lang/Class;
     152: pop
     153: invokedynamic #1120,  0           // InvokeDynamic #36:apply:(Lorg/leo/aws/ddb/repositories/DataMapper;)Ljava/util/function/Function;
     158: invokevirtual #398                // Method reactor/core/publisher/Flux.map:(Ljava/util/function/Function;)Lreactor/core/publisher/Flux;
     161: areturn

  private static java.lang.Object lambda$24(java.lang.Object, software.amazon.awssdk.services.dynamodb.model.PutItemResponse);
    Code:
       0: aload_0
       1: areturn

  private java.lang.Object lambda$25(org.leo.aws.ddb.data.PrimaryKey, java.lang.String, java.lang.Throwable);
    Code:
       0: aload_0
       1: aload_1
       2: aload_2
       3: aload_3
       4: invokevirtual #1132               // Method handleCreateItemException:(Lorg/leo/aws/ddb/data/PrimaryKey;Ljava/lang/String;Ljava/lang/Throwable;)Ljava/lang/Object;
       7: areturn

  private reactor.core.publisher.Mono lambda$26(java.util.function.Function, java.lang.Object, java.util.function.Supplier);
    Code:
       0: aload_1
       1: aload_2
       2: invokeinterface #537,  2          // InterfaceMethod java/util/function/Function.apply:(Ljava/lang/Object;)Ljava/lang/Object;
       7: checkcast     #439                // class org/leo/aws/ddb/data/PrimaryKey
      10: astore        4
      12: aload_3
      13: invokeinterface #308,  1          // InterfaceMethod java/util/function/Supplier.get:()Ljava/lang/Object;
      18: checkcast     #240                // class java/lang/Class
      21: astore        5
      23: aload         5
      25: invokestatic  #312                // Method org/leo/aws/ddb/repositories/DataMapperUtils.getDataMapper:(Ljava/lang/Class;)Lorg/leo/aws/ddb/repositories/DataMapper;
      28: astore        6
      30: aload         6
      32: invokeinterface #434,  1          // InterfaceMethod org/leo/aws/ddb/repositories/DataMapper.getVersionedAttribute:()Lorg/leo/aws/ddb/utils/Tuple;
      37: astore        8
      39: invokestatic  #927                // Method software/amazon/awssdk/services/dynamodb/model/UpdateItemRequest.builder:()Lsoftware/amazon/awssdk/services/dynamodb/model/UpdateItemRequest$Builder;
      42: astore        9
      44: aload_0
      45: aload_2
      46: aload         8
      48: aload         9
      50: invokevirtual #963                // Method setVersion:(Ljava/lang/Object;Lorg/leo/aws/ddb/utils/Tuple;Lsoftware/amazon/awssdk/services/dynamodb/model/UpdateItemRequest$Builder;)Ljava/lang/Integer;
      53: pop
      54: invokestatic  #669                // Method org/leo/aws/ddb/repositories/MapperUtils.getInstance:()Lorg/leo/aws/ddb/repositories/MapperUtils;
      57: aload_2
      58: aload         5
      60: invokevirtual #1136               // Method org/leo/aws/ddb/repositories/MapperUtils.getMappedValues:(Ljava/lang/Object;Ljava/lang/Class;)Ljava/util/stream/Stream;
      63: invokedynamic #1139,  0           // InvokeDynamic #37:accept:()Ljava/util/function/Consumer;
      68: invokeinterface #954,  2          // InterfaceMethod java/util/stream/Stream.peek:(Ljava/util/function/Consumer;)Ljava/util/stream/Stream;
      73: invokedynamic #1142,  0           // InvokeDynamic #38:test:()Ljava/util/function/Predicate;
      78: invokeinterface #948,  2          // InterfaceMethod java/util/stream/Stream.filter:(Ljava/util/function/Predicate;)Ljava/util/stream/Stream;
      83: invokedynamic #1145,  0           // InvokeDynamic #39:apply:()Ljava/util/function/Function;
      88: invokeinterface #563,  2          // InterfaceMethod java/util/stream/Stream.map:(Ljava/util/function/Function;)Ljava/util/stream/Stream;
      93: astore        7
      95: invokestatic  #369                // Method org/leo/aws/ddb/repositories/DataMapperUtils.getDynamoDbAsyncClient:()Lsoftware/amazon/awssdk/services/dynamodb/DynamoDbAsyncClient;
      98: aload         9
     100: aload         6
     102: invokeinterface #323,  1          // InterfaceMethod org/leo/aws/ddb/repositories/DataMapper.tableName:()Ljava/lang/String;
     107: invokeinterface #990,  2          // InterfaceMethod software/amazon/awssdk/services/dynamodb/model/UpdateItemRequest$Builder.tableName:(Ljava/lang/String;)Lsoftware/amazon/awssdk/services/dynamodb/model/UpdateItemRequest$Builder;
     112: aload         6
     114: aload         4
     116: invokeinterface #875,  2          // InterfaceMethod org/leo/aws/ddb/repositories/DataMapper.getPrimaryKey:(Lorg/leo/aws/ddb/data/PrimaryKey;)Ljava/util/Map;
     121: invokeinterface #993,  2          // InterfaceMethod software/amazon/awssdk/services/dynamodb/model/UpdateItemRequest$Builder.key:(Ljava/util/Map;)Lsoftware/amazon/awssdk/services/dynamodb/model/UpdateItemRequest$Builder;
     126: aload         7
     128: invokedynamic #961,  0            // InvokeDynamic #28:apply:()Ljava/util/function/Function;
     133: invokedynamic #962,  0            // InvokeDynamic #29:apply:()Ljava/util/function/Function;
     138: invokestatic  #579                // Method java/util/stream/Collectors.toMap:(Ljava/util/function/Function;Ljava/util/function/Function;)Ljava/util/stream/Collector;
     141: invokeinterface #574,  2          // InterfaceMethod java/util/stream/Stream.collect:(Ljava/util/stream/Collector;)Ljava/lang/Object;
     146: checkcast     #410                // class java/util/Map
     149: invokeinterface #996,  2          // InterfaceMethod software/amazon/awssdk/services/dynamodb/model/UpdateItemRequest$Builder.attributeUpdates:(Ljava/util/Map;)Lsoftware/amazon/awssdk/services/dynamodb/model/UpdateItemRequest$Builder;
     154: getstatic     #999                // Field software/amazon/awssdk/services/dynamodb/model/ReturnValue.ALL_NEW:Lsoftware/amazon/awssdk/services/dynamodb/model/ReturnValue;
     157: invokeinterface #1005,  2         // InterfaceMethod software/amazon/awssdk/services/dynamodb/model/UpdateItemRequest$Builder.returnValues:(Lsoftware/amazon/awssdk/services/dynamodb/model/ReturnValue;)Lsoftware/amazon/awssdk/services/dynamodb/model/UpdateItemRequest$Builder;
     162: invokeinterface #1009,  1         // InterfaceMethod software/amazon/awssdk/services/dynamodb/model/UpdateItemRequest$Builder.build:()Ljava/lang/Object;
     167: checkcast     #928                // class software/amazon/awssdk/services/dynamodb/model/UpdateItemRequest
     170: invokeinterface #1010,  2         // InterfaceMethod software/amazon/awssdk/services/dynamodb/DynamoDbAsyncClient.updateItem:(Lsoftware/amazon/awssdk/services/dynamodb/model/UpdateItemRequest;)Ljava/util/concurrent/CompletableFuture;
     175: aload_0
     176: aload         4
     178: aload         6
     180: invokedynamic #1146,  0           // InvokeDynamic #40:apply:(Lorg/leo/aws/ddb/repositories/BaseRepositoryUtils;Lorg/leo/aws/ddb/data/PrimaryKey;Lorg/leo/aws/ddb/repositories/DataMapper;)Ljava/util/function/Function;
     185: invokevirtual #506                // Method java/util/concurrent/CompletableFuture.exceptionally:(Ljava/util/function/Function;)Ljava/util/concurrent/CompletableFuture;
     188: aload         6
     190: invokedynamic #1149,  0           // InvokeDynamic #41:apply:(Lorg/leo/aws/ddb/repositories/DataMapper;)Ljava/util/function/Function;
     195: invokevirtual #497                // Method java/util/concurrent/CompletableFuture.thenApplyAsync:(Ljava/util/function/Function;)Ljava/util/concurrent/CompletableFuture;
     198: invokestatic  #917                // Method reactor/core/publisher/Mono.fromFuture:(Ljava/util/concurrent/CompletableFuture;)Lreactor/core/publisher/Mono;
     201: invokedynamic #1150,  0           // InvokeDynamic #42:test:()Ljava/util/function/Predicate;
     206: invokedynamic #1151,  0           // InvokeDynamic #43:apply:()Ljava/util/function/Function;
     211: invokevirtual #1152               // Method reactor/core/publisher/Mono.onErrorResume:(Ljava/util/function/Predicate;Ljava/util/function/Function;)Lreactor/core/publisher/Mono;
     214: areturn

  private reactor.core.publisher.Mono lambda$36(org.leo.aws.ddb.data.PrimaryKey, java.util.Map, java.lang.Class, org.leo.aws.ddb.repositories.DataMapper, java.lang.Object);
    Code:
       0: aload_0
       1: aload_1
       2: aload_2
       3: aload_3
       4: aload         4
       6: aload         5
       8: invokevirtual #1157               // Method updateItem:(Lorg/leo/aws/ddb/data/PrimaryKey;Ljava/util/Map;Ljava/lang/Class;Lorg/leo/aws/ddb/repositories/DataMapper;Ljava/lang/Object;)Lreactor/core/publisher/Mono;
      11: areturn

  private static org.leo.aws.ddb.data.UpdateItem lambda$39(org.leo.aws.ddb.data.UpdateItem);
    Code:
       0: aload_0
       1: areturn

  private reactor.core.publisher.Mono lambda$40(org.leo.aws.ddb.repositories.DataMapper, java.util.Map, java.lang.Class, java.lang.Object);
    Code:
       0: aload_0
       1: aload_1
       2: aload         4
       4: invokeinterface #430,  2          // InterfaceMethod org/leo/aws/ddb/repositories/DataMapper.createPKFromItem:(Ljava/lang/Object;)Lorg/leo/aws/ddb/data/PrimaryKey;
       9: aload_2
      10: aload_1
      11: aload         4
      13: invokeinterface #430,  2          // InterfaceMethod org/leo/aws/ddb/repositories/DataMapper.createPKFromItem:(Ljava/lang/Object;)Lorg/leo/aws/ddb/data/PrimaryKey;
      18: invokeinterface #688,  2          // InterfaceMethod java/util/Map.get:(Ljava/lang/Object;)Ljava/lang/Object;
      23: checkcast     #1165               // class org/leo/aws/ddb/data/UpdateItem
      26: invokevirtual #1167               // Method org/leo/aws/ddb/data/UpdateItem.getUpdatedValues:()Ljava/util/Map;
      29: aload_3
      30: aload_1
      31: aload         4
      33: invokevirtual #1157               // Method updateItem:(Lorg/leo/aws/ddb/data/PrimaryKey;Ljava/util/Map;Ljava/lang/Class;Lorg/leo/aws/ddb/repositories/DataMapper;Ljava/lang/Object;)Lreactor/core/publisher/Mono;
      36: areturn

  private org.reactivestreams.Publisher lambda$41(java.util.List, java.util.List, java.util.function.Supplier);
    Code:
       0: aload_1
       1: invokedynamic #1172,  0           // InvokeDynamic #44:call:(Ljava/util/List;)Lrx/functions/Func1;
       6: astore        4
       8: aload_2
       9: invokedynamic #1175,  0           // InvokeDynamic #45:call:(Ljava/util/List;)Lrx/functions/Func1;
      14: astore        5
      16: aload         4
      18: aload         5
      20: invokedynamic #1176,  0           // InvokeDynamic #46:call:(Lrx/functions/Func1;Lrx/functions/Func1;)Lrx/functions/Func1;
      25: astore        6
      27: aload_3
      28: invokeinterface #308,  1          // InterfaceMethod java/util/function/Supplier.get:()Ljava/lang/Object;
      33: checkcast     #240                // class java/lang/Class
      36: invokestatic  #312                // Method org/leo/aws/ddb/repositories/DataMapperUtils.getDataMapper:(Ljava/lang/Class;)Lorg/leo/aws/ddb/repositories/DataMapper;
      39: astore        7
      41: aload_0
      42: aload_1
      43: invokedynamic #1179,  0           // InvokeDynamic #47:call:(Ljava/util/List;)Lrx/functions/Func0;
      48: aload         7
      50: invokeinterface #323,  1          // InterfaceMethod org/leo/aws/ddb/repositories/DataMapper.tableName:()Ljava/lang/String;
      55: aload         6
      57: aload         7
      59: invokeinterface #911,  2          // InterfaceMethod rx/functions/Func1.call:(Ljava/lang/Object;)Ljava/lang/Object;
      64: checkcast     #564                // class java/util/stream/Stream
      67: invokestatic  #568                // Method java/util/stream/Collectors.toList:()Ljava/util/stream/Collector;
      70: invokeinterface #574,  2          // InterfaceMethod java/util/stream/Stream.collect:(Ljava/util/stream/Collector;)Ljava/lang/Object;
      75: checkcast     #557                // class java/util/List
      78: invokestatic  #184                // Method com/google/common/collect/ImmutableMap.of:(Ljava/lang/Object;Ljava/lang/Object;)Lcom/google/common/collect/ImmutableMap;
      81: invokevirtual #915                // Method processBatchWriteRequest:(Lrx/functions/Func0;Ljava/util/Map;)Ljava/util/concurrent/CompletableFuture;
      84: invokestatic  #917                // Method reactor/core/publisher/Mono.fromFuture:(Ljava/util/concurrent/CompletableFuture;)Lreactor/core/publisher/Mono;
      87: invokedynamic #1182,  0           // InvokeDynamic #48:apply:()Ljava/util/function/Function;
      92: invokevirtual #922                // Method reactor/core/publisher/Mono.flatMapMany:(Ljava/util/function/Function;)Lreactor/core/publisher/Flux;
      95: areturn

  private java.util.List lambda$49(rx.functions.Func0, software.amazon.awssdk.services.dynamodb.model.BatchWriteItemResponse);
    Code:
       0: aload_2
       1: invokevirtual #1187               // Method software/amazon/awssdk/services/dynamodb/model/BatchWriteItemResponse.hasUnprocessedItems:()Z
       4: istore_3
       5: iload_3
       6: ifeq          37
       9: aload_2
      10: invokevirtual #1192               // Method software/amazon/awssdk/services/dynamodb/model/BatchWriteItemResponse.unprocessedItems:()Ljava/util/Map;
      13: invokestatic  #356                // Method org/springframework/util/CollectionUtils.isEmpty:(Ljava/util/Map;)Z
      16: ifne          37
      19: aload_0
      20: aload_1
      21: aload_2
      22: invokevirtual #1192               // Method software/amazon/awssdk/services/dynamodb/model/BatchWriteItemResponse.unprocessedItems:()Ljava/util/Map;
      25: invokevirtual #915                // Method processBatchWriteRequest:(Lrx/functions/Func0;Ljava/util/Map;)Ljava/util/concurrent/CompletableFuture;
      28: invokestatic  #1195               // Method org/leo/aws/ddb/utils/Utils.getFromFromFuture:(Ljava/util/concurrent/Future;)Ljava/lang/Object;
      31: checkcast     #557                // class java/util/List
      34: goto          46
      37: aload_1
      38: invokeinterface #1199,  1         // InterfaceMethod rx/functions/Func0.call:()Ljava/lang/Object;
      43: checkcast     #557                // class java/util/List
      46: areturn

  private static reactor.core.publisher.Mono lambda$50(java.lang.Object, java.util.function.Supplier);
    Code:
       0: aload_1
       1: invokeinterface #308,  1          // InterfaceMethod java/util/function/Supplier.get:()Ljava/lang/Object;
       6: checkcast     #240                // class java/lang/Class
       9: invokestatic  #312                // Method org/leo/aws/ddb/repositories/DataMapperUtils.getDataMapper:(Ljava/lang/Class;)Lorg/leo/aws/ddb/repositories/DataMapper;
      12: astore_2
      13: aload_2
      14: aload_0
      15: invokeinterface #430,  2          // InterfaceMethod org/leo/aws/ddb/repositories/DataMapper.createPKFromItem:(Ljava/lang/Object;)Lorg/leo/aws/ddb/data/PrimaryKey;
      20: astore_3
      21: invokestatic  #1207               // Method software/amazon/awssdk/services/dynamodb/model/DeleteItemRequest.builder:()Lsoftware/amazon/awssdk/services/dynamodb/model/DeleteItemRequest$Builder;
      24: aload_2
      25: invokeinterface #323,  1          // InterfaceMethod org/leo/aws/ddb/repositories/DataMapper.tableName:()Ljava/lang/String;
      30: invokeinterface #1212,  2         // InterfaceMethod software/amazon/awssdk/services/dynamodb/model/DeleteItemRequest$Builder.tableName:(Ljava/lang/String;)Lsoftware/amazon/awssdk/services/dynamodb/model/DeleteItemRequest$Builder;
      35: aload_2
      36: aload_3
      37: invokeinterface #875,  2          // InterfaceMethod org/leo/aws/ddb/repositories/DataMapper.getPrimaryKey:(Lorg/leo/aws/ddb/data/PrimaryKey;)Ljava/util/Map;
      42: invokeinterface #1217,  2         // InterfaceMethod software/amazon/awssdk/services/dynamodb/model/DeleteItemRequest$Builder.key:(Ljava/util/Map;)Lsoftware/amazon/awssdk/services/dynamodb/model/DeleteItemRequest$Builder;
      47: invokeinterface #1220,  1         // InterfaceMethod software/amazon/awssdk/services/dynamodb/model/DeleteItemRequest$Builder.build:()Ljava/lang/Object;
      52: checkcast     #1208               // class software/amazon/awssdk/services/dynamodb/model/DeleteItemRequest
      55: astore        4
      57: invokestatic  #369                // Method org/leo/aws/ddb/repositories/DataMapperUtils.getDynamoDbAsyncClient:()Lsoftware/amazon/awssdk/services/dynamodb/DynamoDbAsyncClient;
      60: aload         4
      62: invokeinterface #1221,  2         // InterfaceMethod software/amazon/awssdk/services/dynamodb/DynamoDbAsyncClient.deleteItem:(Lsoftware/amazon/awssdk/services/dynamodb/model/DeleteItemRequest;)Ljava/util/concurrent/CompletableFuture;
      67: aload_0
      68: invokedynamic #1224,  0           // InvokeDynamic #49:apply:(Ljava/lang/Object;)Ljava/util/function/Function;
      73: invokevirtual #497                // Method java/util/concurrent/CompletableFuture.thenApplyAsync:(Ljava/util/function/Function;)Ljava/util/concurrent/CompletableFuture;
      76: invokestatic  #917                // Method reactor/core/publisher/Mono.fromFuture:(Ljava/util/concurrent/CompletableFuture;)Lreactor/core/publisher/Mono;
      79: areturn

  private static void lambda$52(java.util.Map, java.lang.Object);
    Code:
       0: aload_0
       1: ldc_w         #814                // String :sort_key_val
       4: invokestatic  #196                // Method software/amazon/awssdk/services/dynamodb/model/AttributeValue.builder:()Lsoftware/amazon/awssdk/services/dynamodb/model/AttributeValue$Builder;
       7: aload_1
       8: invokestatic  #97                 // Method java/lang/String.valueOf:(Ljava/lang/Object;)Ljava/lang/String;
      11: invokeinterface #753,  2          // InterfaceMethod software/amazon/awssdk/services/dynamodb/model/AttributeValue$Builder.s:(Ljava/lang/String;)Lsoftware/amazon/awssdk/services/dynamodb/model/AttributeValue$Builder;
      16: invokeinterface #210,  1          // InterfaceMethod software/amazon/awssdk/services/dynamodb/model/AttributeValue$Builder.build:()Ljava/lang/Object;
      21: checkcast     #197                // class software/amazon/awssdk/services/dynamodb/model/AttributeValue
      24: invokeinterface #756,  3          // InterfaceMethod java/util/Map.put:(Ljava/lang/Object;Ljava/lang/Object;)Ljava/lang/Object;
      29: return

  private static java.lang.Class lambda$53(org.leo.aws.ddb.repositories.DynamoDbRepository, java.lang.String);
    Code:
       0: aload_0
       1: invokevirtual #392                // Method java/lang/Object.getClass:()Ljava/lang/Class;
       4: ldc_w         #1231               // class org/leo/aws/ddb/annotations/DdbRepository
       7: invokevirtual #1233               // Method java/lang/Class.getAnnotation:(Ljava/lang/Class;)Ljava/lang/annotation/Annotation;
      10: checkcast     #1231               // class org/leo/aws/ddb/annotations/DdbRepository
      13: astore_2
      14: aload_2
      15: ifnull        25
      18: aload_2
      19: invokeinterface #1237,  1         // InterfaceMethod org/leo/aws/ddb/annotations/DdbRepository.entityClass:()Ljava/lang/Class;
      24: areturn
      25: new           #83                 // class org/leo/aws/ddb/exceptions/DbException
      28: dup
      29: ldc_w         #1240               // String Annotation not defined in Repository implementation.
      32: invokespecial #693                // Method org/leo/aws/ddb/exceptions/DbException."<init>":(Ljava/lang/String;)V
      35: athrow

  private static org.leo.aws.ddb.utils.Tuple3 lambda$4(org.leo.aws.ddb.utils.Tuple3);
    Code:
       0: aload_0
       1: areturn

  private static boolean lambda$5(org.leo.aws.ddb.data.PrimaryKey, java.util.Map$Entry);
    Code:
       0: aload_1
       1: invokeinterface #1250,  1         // InterfaceMethod java/util/Map$Entry.getKey:()Ljava/lang/Object;
       6: checkcast     #98                 // class java/lang/String
       9: aload_0
      10: invokevirtual #464                // Method org/leo/aws/ddb/data/PrimaryKey.getHashKeyName:()Ljava/lang/String;
      13: invokevirtual #1255               // Method java/lang/String.equals:(Ljava/lang/Object;)Z
      16: ifeq          23
      19: iconst_0
      20: goto          24
      23: iconst_1
      24: ireturn

  private static boolean lambda$6(org.leo.aws.ddb.data.PrimaryKey, java.util.Map$Entry);
    Code:
       0: aload_1
       1: invokeinterface #1250,  1         // InterfaceMethod java/util/Map$Entry.getKey:()Ljava/lang/Object;
       6: checkcast     #98                 // class java/lang/String
       9: aload_0
      10: invokevirtual #438                // Method org/leo/aws/ddb/data/PrimaryKey.getRangeKeyName:()Ljava/lang/String;
      13: invokevirtual #1255               // Method java/lang/String.equals:(Ljava/lang/Object;)Z
      16: ifeq          23
      19: iconst_0
      20: goto          24
      23: iconst_1
      24: ireturn

  private static void lambda$7(java.util.Map, java.util.Map$Entry);
    Code:
       0: aload_0
       1: aload_1
       2: invokeinterface #1250,  1         // InterfaceMethod java/util/Map$Entry.getKey:()Ljava/lang/Object;
       7: invokeinterface #688,  2          // InterfaceMethod java/util/Map.get:(Ljava/lang/Object;)Ljava/lang/Object;
      12: ifnull        66
      15: aload_0
      16: aload_1
      17: invokeinterface #1250,  1         // InterfaceMethod java/util/Map$Entry.getKey:()Ljava/lang/Object;
      22: invokeinterface #688,  2          // InterfaceMethod java/util/Map.get:(Ljava/lang/Object;)Ljava/lang/Object;
      27: checkcast     #1264               // class org/leo/aws/ddb/utils/Tuple3
      30: invokevirtual #1266               // Method org/leo/aws/ddb/utils/Tuple3._3:()Ljava/lang/Object;
      33: checkcast     #159                // class org/leo/aws/ddb/annotations/DbAttribute
      36: aload_1
      37: invokeinterface #1269,  1         // InterfaceMethod java/util/Map$Entry.getValue:()Ljava/lang/Object;
      42: aload_0
      43: aload_1
      44: invokeinterface #1250,  1         // InterfaceMethod java/util/Map$Entry.getKey:()Ljava/lang/Object;
      49: invokeinterface #688,  2          // InterfaceMethod java/util/Map.get:(Ljava/lang/Object;)Ljava/lang/Object;
      54: checkcast     #1264               // class org/leo/aws/ddb/utils/Tuple3
      57: invokevirtual #1272               // Method org/leo/aws/ddb/utils/Tuple3._1:()Ljava/lang/Object;
      60: checkcast     #98                 // class java/lang/String
      63: invokestatic  #1273               // Method org/leo/aws/ddb/utils/DbUtils.checkForNullFields:(Lorg/leo/aws/ddb/annotations/DbAttribute;Ljava/lang/Object;Ljava/lang/String;)V
      66: return

  private static org.leo.aws.ddb.utils.Tuple lambda$8(java.util.Map, java.util.Map$Entry);
    Code:
       0: aload_0
       1: aload_1
       2: invokeinterface #1250,  1         // InterfaceMethod java/util/Map$Entry.getKey:()Ljava/lang/Object;
       7: invokeinterface #688,  2          // InterfaceMethod java/util/Map.get:(Ljava/lang/Object;)Ljava/lang/Object;
      12: ifnull        77
      15: aload_1
      16: invokeinterface #1250,  1         // InterfaceMethod java/util/Map$Entry.getKey:()Ljava/lang/Object;
      21: checkcast     #98                 // class java/lang/String
      24: aload_0
      25: aload_1
      26: invokeinterface #1250,  1         // InterfaceMethod java/util/Map$Entry.getKey:()Ljava/lang/Object;
      31: invokeinterface #688,  2          // InterfaceMethod java/util/Map.get:(Ljava/lang/Object;)Ljava/lang/Object;
      36: checkcast     #1264               // class org/leo/aws/ddb/utils/Tuple3
      39: invokevirtual #1282               // Method org/leo/aws/ddb/utils/Tuple3._2:()Ljava/lang/Object;
      42: checkcast     #133                // class java/lang/reflect/Field
      45: aload_1
      46: invokeinterface #1269,  1         // InterfaceMethod java/util/Map$Entry.getValue:()Ljava/lang/Object;
      51: invokestatic  #1283               // Method org/leo/aws/ddb/utils/DbUtils.modelToAttributeUpdateValue:(Ljava/lang/reflect/Field;Ljava/lang/Object;)Lrx/functions/Func1;
      54: invokestatic  #973                // Method software/amazon/awssdk/services/dynamodb/model/AttributeValueUpdate.builder:()Lsoftware/amazon/awssdk/services/dynamodb/model/AttributeValueUpdate$Builder;
      57: invokeinterface #911,  2          // InterfaceMethod rx/functions/Func1.call:(Ljava/lang/Object;)Ljava/lang/Object;
      62: checkcast     #979                // class software/amazon/awssdk/services/dynamodb/model/AttributeValueUpdate$Builder
      65: invokeinterface #983,  1          // InterfaceMethod software/amazon/awssdk/services/dynamodb/model/AttributeValueUpdate$Builder.build:()Ljava/lang/Object;
      70: checkcast     #974                // class software/amazon/awssdk/services/dynamodb/model/AttributeValueUpdate
      73: invokestatic  #791                // Method org/leo/aws/ddb/utils/Tuples.of:(Ljava/lang/Object;Ljava/lang/Object;)Lorg/leo/aws/ddb/utils/Tuple;
      76: areturn
      77: aload_1
      78: invokeinterface #1250,  1         // InterfaceMethod java/util/Map$Entry.getKey:()Ljava/lang/Object;
      83: checkcast     #98                 // class java/lang/String
      86: invokestatic  #973                // Method software/amazon/awssdk/services/dynamodb/model/AttributeValueUpdate.builder:()Lsoftware/amazon/awssdk/services/dynamodb/model/AttributeValueUpdate$Builder;
      89: invokestatic  #196                // Method software/amazon/awssdk/services/dynamodb/model/AttributeValue.builder:()Lsoftware/amazon/awssdk/services/dynamodb/model/AttributeValue$Builder;
      92: aload_1
      93: invokeinterface #1269,  1         // InterfaceMethod java/util/Map$Entry.getValue:()Ljava/lang/Object;
      98: invokestatic  #97                 // Method java/lang/String.valueOf:(Ljava/lang/Object;)Ljava/lang/String;
     101: invokeinterface #753,  2          // InterfaceMethod software/amazon/awssdk/services/dynamodb/model/AttributeValue$Builder.s:(Ljava/lang/String;)Lsoftware/amazon/awssdk/services/dynamodb/model/AttributeValue$Builder;
     106: invokeinterface #210,  1          // InterfaceMethod software/amazon/awssdk/services/dynamodb/model/AttributeValue$Builder.build:()Ljava/lang/Object;
     111: checkcast     #197                // class software/amazon/awssdk/services/dynamodb/model/AttributeValue
     114: invokeinterface #978,  2          // InterfaceMethod software/amazon/awssdk/services/dynamodb/model/AttributeValueUpdate$Builder.value:(Lsoftware/amazon/awssdk/services/dynamodb/model/AttributeValue;)Lsoftware/amazon/awssdk/services/dynamodb/model/AttributeValueUpdate$Builder;
     119: invokeinterface #983,  1          // InterfaceMethod software/amazon/awssdk/services/dynamodb/model/AttributeValueUpdate$Builder.build:()Ljava/lang/Object;
     124: checkcast     #974                // class software/amazon/awssdk/services/dynamodb/model/AttributeValueUpdate
     127: invokestatic  #791                // Method org/leo/aws/ddb/utils/Tuples.of:(Ljava/lang/Object;Ljava/lang/Object;)Lorg/leo/aws/ddb/utils/Tuple;
     130: areturn

  private static java.lang.Object lambda$11(org.leo.aws.ddb.repositories.DataMapper, software.amazon.awssdk.services.dynamodb.model.UpdateItemResponse);
    Code:
       0: aload_0
       1: aload_1
       2: invokevirtual #1289               // Method software/amazon/awssdk/services/dynamodb/model/UpdateItemResponse.attributes:()Ljava/util/Map;
       5: invokeinterface #1293,  2         // InterfaceMethod org/leo/aws/ddb/repositories/DataMapper.mapFromAttributeValueToEntity:(Ljava/util/Map;)Ljava/lang/Object;
      10: areturn

  private static java.lang.Object lambda$14(java.lang.Class, java.util.Map);
    Code:
       0: aload_0
       1: invokestatic  #312                // Method org/leo/aws/ddb/repositories/DataMapperUtils.getDataMapper:(Ljava/lang/Class;)Lorg/leo/aws/ddb/repositories/DataMapper;
       4: aload_1
       5: invokeinterface #1293,  2         // InterfaceMethod org/leo/aws/ddb/repositories/DataMapper.mapFromAttributeValueToEntity:(Ljava/util/Map;)Ljava/lang/Object;
      10: areturn

  private static org.reactivestreams.Publisher lambda$15(java.util.function.Function, java.util.List);
    Code:
       0: aload_1
       1: invokestatic  #1303               // Method org/springframework/util/CollectionUtils.isEmpty:(Ljava/util/Collection;)Z
       4: ifne          20
       7: aload_0
       8: aload_1
       9: invokeinterface #537,  2          // InterfaceMethod java/util/function/Function.apply:(Ljava/lang/Object;)Ljava/lang/Object;
      14: checkcast     #1028               // class org/reactivestreams/Publisher
      17: goto          23
      20: invokestatic  #1306               // Method reactor/core/publisher/Flux.empty:()Lreactor/core/publisher/Flux;
      23: areturn

  private static reactor.core.publisher.Mono lambda$19(org.leo.aws.ddb.repositories.DataMapper, software.amazon.awssdk.services.dynamodb.model.GetItemResponse);
    Code:
       0: aload_1
       1: invokevirtual #1312               // Method software/amazon/awssdk/services/dynamodb/model/GetItemResponse.item:()Ljava/util/Map;
       4: invokeinterface #1316,  1         // InterfaceMethod java/util/Map.isEmpty:()Z
       9: ifeq          18
      12: invokestatic  #1318               // Method reactor/core/publisher/Mono.empty:()Lreactor/core/publisher/Mono;
      15: goto          31
      18: aload_0
      19: aload_1
      20: invokevirtual #1312               // Method software/amazon/awssdk/services/dynamodb/model/GetItemResponse.item:()Ljava/util/Map;
      23: invokeinterface #1293,  2         // InterfaceMethod org/leo/aws/ddb/repositories/DataMapper.mapFromAttributeValueToEntity:(Ljava/util/Map;)Ljava/lang/Object;
      28: invokestatic  #1320               // Method reactor/core/publisher/Mono.just:(Ljava/lang/Object;)Lreactor/core/publisher/Mono;
      31: areturn

  private static java.lang.Iterable lambda$22(org.leo.aws.ddb.repositories.DataMapper, software.amazon.awssdk.services.dynamodb.model.BatchGetItemResponse);
    Code:
       0: aload_1
       1: invokevirtual #1328               // Method software/amazon/awssdk/services/dynamodb/model/BatchGetItemResponse.responses:()Ljava/util/Map;
       4: aload_0
       5: invokeinterface #323,  1          // InterfaceMethod org/leo/aws/ddb/repositories/DataMapper.tableName:()Ljava/lang/String;
      10: invokeinterface #688,  2          // InterfaceMethod java/util/Map.get:(Ljava/lang/Object;)Ljava/lang/Object;
      15: checkcast     #1333               // class java/lang/Iterable
      18: areturn

  private static void lambda$27(org.leo.aws.ddb.utils.Tuple4);
    Code:
       0: aload_0
       1: invokevirtual #1338               // Method org/leo/aws/ddb/utils/Tuple4._4:()Ljava/lang/Object;
       4: checkcast     #159                // class org/leo/aws/ddb/annotations/DbAttribute
       7: aload_0
       8: invokevirtual #1343               // Method org/leo/aws/ddb/utils/Tuple4._2:()Ljava/lang/Object;
      11: aload_0
      12: invokevirtual #1344               // Method org/leo/aws/ddb/utils/Tuple4._1:()Ljava/lang/Object;
      15: checkcast     #98                 // class java/lang/String
      18: invokestatic  #1273               // Method org/leo/aws/ddb/utils/DbUtils.checkForNullFields:(Lorg/leo/aws/ddb/annotations/DbAttribute;Ljava/lang/Object;Ljava/lang/String;)V
      21: return

  private static boolean lambda$28(org.leo.aws.ddb.utils.Tuple4);
    Code:
       0: aload_0
       1: invokevirtual #1344               // Method org/leo/aws/ddb/utils/Tuple4._1:()Ljava/lang/Object;
       4: ifnull        11
       7: iconst_1
       8: goto          12
      11: iconst_0
      12: ireturn

  private static org.leo.aws.ddb.utils.Tuple lambda$29(org.leo.aws.ddb.utils.Tuple4);
    Code:
       0: aload_0
       1: invokevirtual #1344               // Method org/leo/aws/ddb/utils/Tuple4._1:()Ljava/lang/Object;
       4: checkcast     #98                 // class java/lang/String
       7: aload_0
       8: invokevirtual #1351               // Method org/leo/aws/ddb/utils/Tuple4._3:()Ljava/lang/Object;
      11: checkcast     #133                // class java/lang/reflect/Field
      14: aload_0
      15: invokevirtual #1343               // Method org/leo/aws/ddb/utils/Tuple4._2:()Ljava/lang/Object;
      18: invokestatic  #1283               // Method org/leo/aws/ddb/utils/DbUtils.modelToAttributeUpdateValue:(Ljava/lang/reflect/Field;Ljava/lang/Object;)Lrx/functions/Func1;
      21: invokestatic  #973                // Method software/amazon/awssdk/services/dynamodb/model/AttributeValueUpdate.builder:()Lsoftware/amazon/awssdk/services/dynamodb/model/AttributeValueUpdate$Builder;
      24: invokeinterface #911,  2          // InterfaceMethod rx/functions/Func1.call:(Ljava/lang/Object;)Ljava/lang/Object;
      29: checkcast     #979                // class software/amazon/awssdk/services/dynamodb/model/AttributeValueUpdate$Builder
      32: invokeinterface #983,  1          // InterfaceMethod software/amazon/awssdk/services/dynamodb/model/AttributeValueUpdate$Builder.build:()Ljava/lang/Object;
      37: checkcast     #974                // class software/amazon/awssdk/services/dynamodb/model/AttributeValueUpdate
      40: invokestatic  #791                // Method org/leo/aws/ddb/utils/Tuples.of:(Ljava/lang/Object;Ljava/lang/Object;)Lorg/leo/aws/ddb/utils/Tuple;
      43: areturn

  private software.amazon.awssdk.services.dynamodb.model.UpdateItemResponse lambda$32(org.leo.aws.ddb.data.PrimaryKey, org.leo.aws.ddb.repositories.DataMapper, java.lang.Throwable);
    Code:
       0: aload_0
       1: aload_1
       2: aload_2
       3: invokeinterface #323,  1          // InterfaceMethod org/leo/aws/ddb/repositories/DataMapper.tableName:()Ljava/lang/String;
       8: aload_3
       9: invokevirtual #1354               // Method handleUpdateItemException:(Lorg/leo/aws/ddb/data/PrimaryKey;Ljava/lang/String;Ljava/lang/Throwable;)Lsoftware/amazon/awssdk/services/dynamodb/model/UpdateItemResponse;
      12: areturn

  private static java.lang.Object lambda$33(org.leo.aws.ddb.repositories.DataMapper, software.amazon.awssdk.services.dynamodb.model.UpdateItemResponse);
    Code:
       0: aload_0
       1: aload_1
       2: invokevirtual #1289               // Method software/amazon/awssdk/services/dynamodb/model/UpdateItemResponse.attributes:()Ljava/util/Map;
       5: invokeinterface #1293,  2         // InterfaceMethod org/leo/aws/ddb/repositories/DataMapper.mapFromAttributeValueToEntity:(Ljava/util/Map;)Ljava/lang/Object;
      10: areturn

  private static boolean lambda$34(java.lang.Throwable);
    Code:
       0: aload_0
       1: instanceof    #66                 // class java/util/concurrent/CompletionException
       4: ireturn

  private static reactor.core.publisher.Mono lambda$35(java.lang.Throwable);
    Code:
       0: aload_0
       1: invokevirtual #68                 // Method java/lang/Throwable.getCause:()Ljava/lang/Throwable;
       4: invokestatic  #1362               // Method reactor/core/publisher/Mono.error:(Ljava/lang/Throwable;)Lreactor/core/publisher/Mono;
       7: areturn

  private static java.util.stream.Stream lambda$42(java.util.List, org.leo.aws.ddb.repositories.DataMapper);
    Code:
       0: aload_0
       1: invokeinterface #556,  1          // InterfaceMethod java/util/List.stream:()Ljava/util/stream/Stream;
       6: aload_1
       7: invokedynamic #1366,  0           // InvokeDynamic #50:apply:(Lorg/leo/aws/ddb/repositories/DataMapper;)Ljava/util/function/Function;
      12: invokeinterface #563,  2          // InterfaceMethod java/util/stream/Stream.map:(Ljava/util/function/Function;)Ljava/util/stream/Stream;
      17: areturn

  private static java.util.stream.Stream lambda$44(java.util.List, org.leo.aws.ddb.repositories.DataMapper);
    Code:
       0: aload_0
       1: ifnull        8
       4: aload_0
       5: goto          11
       8: invokestatic  #1368               // Method java/util/Collections.emptyList:()Ljava/util/List;
      11: invokeinterface #556,  1          // InterfaceMethod java/util/List.stream:()Ljava/util/stream/Stream;
      16: aload_1
      17: invokedynamic #1374,  0           // InvokeDynamic #51:apply:(Lorg/leo/aws/ddb/repositories/DataMapper;)Ljava/util/function/Function;
      22: invokeinterface #563,  2          // InterfaceMethod java/util/stream/Stream.map:(Ljava/util/function/Function;)Ljava/util/stream/Stream;
      27: areturn

  private static java.util.stream.Stream lambda$46(rx.functions.Func1, rx.functions.Func1, org.leo.aws.ddb.repositories.DataMapper);
    Code:
       0: aload_0
       1: aload_2
       2: invokeinterface #911,  2          // InterfaceMethod rx/functions/Func1.call:(Ljava/lang/Object;)Ljava/lang/Object;
       7: checkcast     #564                // class java/util/stream/Stream
      10: aload_1
      11: aload_2
      12: invokeinterface #911,  2          // InterfaceMethod rx/functions/Func1.call:(Ljava/lang/Object;)Ljava/lang/Object;
      17: checkcast     #564                // class java/util/stream/Stream
      20: invokestatic  #1377               // InterfaceMethod java/util/stream/Stream.concat:(Ljava/util/stream/Stream;Ljava/util/stream/Stream;)Ljava/util/stream/Stream;
      23: areturn

  private static java.util.List lambda$47(java.util.List);
    Code:
       0: aload_0
       1: areturn

  private static java.lang.Object lambda$51(java.lang.Object, software.amazon.awssdk.services.dynamodb.model.DeleteItemResponse);
    Code:
       0: aload_0
       1: areturn

  private static software.amazon.awssdk.services.dynamodb.model.WriteRequest lambda$43(org.leo.aws.ddb.repositories.DataMapper, java.lang.Object);
    Code:
       0: invokestatic  #1388               // Method software/amazon/awssdk/services/dynamodb/model/WriteRequest.builder:()Lsoftware/amazon/awssdk/services/dynamodb/model/WriteRequest$Builder;
       3: invokestatic  #1393               // Method software/amazon/awssdk/services/dynamodb/model/PutRequest.builder:()Lsoftware/amazon/awssdk/services/dynamodb/model/PutRequest$Builder;
       6: aload_0
       7: aload_1
       8: invokeinterface #477,  2          // InterfaceMethod org/leo/aws/ddb/repositories/DataMapper.mapFromEntityToAttributeValue:(Ljava/lang/Object;)Ljava/util/Map;
      13: invokeinterface #1398,  2         // InterfaceMethod software/amazon/awssdk/services/dynamodb/model/PutRequest$Builder.item:(Ljava/util/Map;)Lsoftware/amazon/awssdk/services/dynamodb/model/PutRequest$Builder;
      18: invokeinterface #1403,  1         // InterfaceMethod software/amazon/awssdk/services/dynamodb/model/PutRequest$Builder.build:()Ljava/lang/Object;
      23: checkcast     #1394               // class software/amazon/awssdk/services/dynamodb/model/PutRequest
      26: invokeinterface #1404,  2         // InterfaceMethod software/amazon/awssdk/services/dynamodb/model/WriteRequest$Builder.putRequest:(Lsoftware/amazon/awssdk/services/dynamodb/model/PutRequest;)Lsoftware/amazon/awssdk/services/dynamodb/model/WriteRequest$Builder;
      31: invokeinterface #1410,  1         // InterfaceMethod software/amazon/awssdk/services/dynamodb/model/WriteRequest$Builder.build:()Ljava/lang/Object;
      36: checkcast     #1389               // class software/amazon/awssdk/services/dynamodb/model/WriteRequest
      39: areturn

  private static software.amazon.awssdk.services.dynamodb.model.WriteRequest lambda$45(org.leo.aws.ddb.repositories.DataMapper, java.lang.Object);
    Code:
       0: invokestatic  #1388               // Method software/amazon/awssdk/services/dynamodb/model/WriteRequest.builder:()Lsoftware/amazon/awssdk/services/dynamodb/model/WriteRequest$Builder;
       3: invokestatic  #1412               // Method software/amazon/awssdk/services/dynamodb/model/DeleteRequest.builder:()Lsoftware/amazon/awssdk/services/dynamodb/model/DeleteRequest$Builder;
       6: aload_0
       7: aload_0
       8: aload_1
       9: invokeinterface #430,  2          // InterfaceMethod org/leo/aws/ddb/repositories/DataMapper.createPKFromItem:(Ljava/lang/Object;)Lorg/leo/aws/ddb/data/PrimaryKey;
      14: invokeinterface #875,  2          // InterfaceMethod org/leo/aws/ddb/repositories/DataMapper.getPrimaryKey:(Lorg/leo/aws/ddb/data/PrimaryKey;)Ljava/util/Map;
      19: invokeinterface #1417,  2         // InterfaceMethod software/amazon/awssdk/services/dynamodb/model/DeleteRequest$Builder.key:(Ljava/util/Map;)Lsoftware/amazon/awssdk/services/dynamodb/model/DeleteRequest$Builder;
      24: invokeinterface #1422,  1         // InterfaceMethod software/amazon/awssdk/services/dynamodb/model/DeleteRequest$Builder.build:()Ljava/lang/Object;
      29: checkcast     #1413               // class software/amazon/awssdk/services/dynamodb/model/DeleteRequest
      32: invokeinterface #1423,  2         // InterfaceMethod software/amazon/awssdk/services/dynamodb/model/WriteRequest$Builder.deleteRequest:(Lsoftware/amazon/awssdk/services/dynamodb/model/DeleteRequest;)Lsoftware/amazon/awssdk/services/dynamodb/model/WriteRequest$Builder;
      37: invokeinterface #1410,  1         // InterfaceMethod software/amazon/awssdk/services/dynamodb/model/WriteRequest$Builder.build:()Ljava/lang/Object;
      42: checkcast     #1389               // class software/amazon/awssdk/services/dynamodb/model/WriteRequest
      45: areturn
}
