Compiled from "FileLocks.java"
public final class com.amazonaws.services.s3.internal.FileLocks extends java.lang.Enum<com.amazonaws.services.s3.internal.FileLocks> {
  private static final boolean EXTERNAL_LOCK;

  private static final org.apache.commons.logging.Log log;

  private static final java.util.Map<java.io.File, java.io.RandomAccessFile> lockedFiles;

  private static final com.amazonaws.services.s3.internal.FileLocks[] $VALUES;

  public static com.amazonaws.services.s3.internal.FileLocks[] values();
    Code:
       0: getstatic     #2                  // Field $VALUES:[Lcom/amazonaws/services/s3/internal/FileLocks;
       3: invokevirtual #3                  // Method "[Lcom/amazonaws/services/s3/internal/FileLocks;".clone:()Ljava/lang/Object;
       6: checkcast     #4                  // class "[Lcom/amazonaws/services/s3/internal/FileLocks;"
       9: areturn

  public static com.amazonaws.services.s3.internal.FileLocks valueOf(java.lang.String);
    Code:
       0: ldc           #1                  // class com/amazonaws/services/s3/internal/FileLocks
       2: aload_0
       3: invokestatic  #5                  // Method java/lang/Enum.valueOf:(Ljava/lang/Class;Ljava/lang/String;)Ljava/lang/Enum;
       6: checkcast     #1                  // class com/amazonaws/services/s3/internal/FileLocks
       9: areturn

  private com.amazonaws.services.s3.internal.FileLocks();
    Code:
       0: aload_0
       1: aload_1
       2: iload_2
       3: invokespecial #6                  // Method java/lang/Enum."<init>":(Ljava/lang/String;I)V
       6: return

  public static boolean lock(java.io.File);
    Code:
       0: getstatic     #7                  // Field lockedFiles:Ljava/util/Map;
       3: dup
       4: astore_1
       5: monitorenter
       6: getstatic     #7                  // Field lockedFiles:Ljava/util/Map;
       9: aload_0
      10: invokeinterface #8,  2            // InterfaceMethod java/util/Map.containsKey:(Ljava/lang/Object;)Z
      15: ifeq          22
      18: iconst_0
      19: aload_1
      20: monitorexit
      21: ireturn
      22: aload_1
      23: monitorexit
      24: goto          32
      27: astore_2
      28: aload_1
      29: monitorexit
      30: aload_2
      31: athrow
      32: aconst_null
      33: astore_1
      34: aconst_null
      35: astore_2
      36: new           #9                  // class java/io/RandomAccessFile
      39: dup
      40: aload_0
      41: ldc           #10                 // String rw
      43: invokespecial #11                 // Method java/io/RandomAccessFile."<init>":(Ljava/io/File;Ljava/lang/String;)V
      46: astore_2
      47: aload_2
      48: invokevirtual #12                 // Method java/io/RandomAccessFile.getChannel:()Ljava/nio/channels/FileChannel;
      51: astore_3
      52: goto          72
      55: astore_3
      56: aload_2
      57: getstatic     #14                 // Field log:Lorg/apache/commons/logging/Log;
      60: invokestatic  #15                 // Method com/amazonaws/util/IOUtils.closeQuietly:(Ljava/io/Closeable;Lorg/apache/commons/logging/Log;)V
      63: new           #16                 // class com/amazonaws/services/s3/transfer/exception/FileLockException
      66: dup
      67: aload_3
      68: invokespecial #17                 // Method com/amazonaws/services/s3/transfer/exception/FileLockException."<init>":(Ljava/lang/Throwable;)V
      71: athrow
      72: getstatic     #7                  // Field lockedFiles:Ljava/util/Map;
      75: dup
      76: astore        4
      78: monitorenter
      79: getstatic     #7                  // Field lockedFiles:Ljava/util/Map;
      82: aload_0
      83: aload_2
      84: invokeinterface #18,  3           // InterfaceMethod java/util/Map.put:(Ljava/lang/Object;Ljava/lang/Object;)Ljava/lang/Object;
      89: checkcast     #9                  // class java/io/RandomAccessFile
      92: astore        5
      94: aload         5
      96: ifnonnull     104
      99: iconst_1
     100: istore_3
     101: goto          118
     104: iconst_0
     105: istore_3
     106: getstatic     #7                  // Field lockedFiles:Ljava/util/Map;
     109: aload_0
     110: aload         5
     112: invokeinterface #18,  3           // InterfaceMethod java/util/Map.put:(Ljava/lang/Object;Ljava/lang/Object;)Ljava/lang/Object;
     117: pop
     118: aload         4
     120: monitorexit
     121: goto          132
     124: astore        6
     126: aload         4
     128: monitorexit
     129: aload         6
     131: athrow
     132: iload_3
     133: ifeq          186
     136: getstatic     #14                 // Field log:Lorg/apache/commons/logging/Log;
     139: invokeinterface #19,  1           // InterfaceMethod org/apache/commons/logging/Log.isDebugEnabled:()Z
     144: ifeq          193
     147: getstatic     #14                 // Field log:Lorg/apache/commons/logging/Log;
     150: new           #20                 // class java/lang/StringBuilder
     153: dup
     154: invokespecial #21                 // Method java/lang/StringBuilder."<init>":()V
     157: ldc           #22                 // String Locked file
     159: invokevirtual #23                 // Method java/lang/StringBuilder.append:(Ljava/lang/String;)Ljava/lang/StringBuilder;
     162: aload_0
     163: invokevirtual #24                 // Method java/lang/StringBuilder.append:(Ljava/lang/Object;)Ljava/lang/StringBuilder;
     166: ldc           #25                 // String  with
     168: invokevirtual #23                 // Method java/lang/StringBuilder.append:(Ljava/lang/String;)Ljava/lang/StringBuilder;
     171: aload_1
     172: invokevirtual #24                 // Method java/lang/StringBuilder.append:(Ljava/lang/Object;)Ljava/lang/StringBuilder;
     175: invokevirtual #26                 // Method java/lang/StringBuilder.toString:()Ljava/lang/String;
     178: invokeinterface #27,  2           // InterfaceMethod org/apache/commons/logging/Log.debug:(Ljava/lang/Object;)V
     183: goto          193
     186: aload_2
     187: getstatic     #14                 // Field log:Lorg/apache/commons/logging/Log;
     190: invokestatic  #15                 // Method com/amazonaws/util/IOUtils.closeQuietly:(Ljava/io/Closeable;Lorg/apache/commons/logging/Log;)V
     193: iload_3
     194: ireturn
    Exception table:
       from    to  target type
           6    21    27   any
          22    24    27   any
          27    30    27   any
          36    52    55   Class java/lang/Exception
          79   121   124   any
         124   129   124   any

  public static boolean isFileLocked(java.io.File);
    Code:
       0: getstatic     #7                  // Field lockedFiles:Ljava/util/Map;
       3: dup
       4: astore_1
       5: monitorenter
       6: getstatic     #7                  // Field lockedFiles:Ljava/util/Map;
       9: aload_0
      10: invokeinterface #8,  2            // InterfaceMethod java/util/Map.containsKey:(Ljava/lang/Object;)Z
      15: aload_1
      16: monitorexit
      17: ireturn
      18: astore_2
      19: aload_1
      20: monitorexit
      21: aload_2
      22: athrow
    Exception table:
       from    to  target type
           6    17    18   any
          18    21    18   any

  public static boolean unlock(java.io.File);
    Code:
       0: getstatic     #7                  // Field lockedFiles:Ljava/util/Map;
       3: dup
       4: astore_1
       5: monitorenter
       6: getstatic     #7                  // Field lockedFiles:Ljava/util/Map;
       9: aload_0
      10: invokeinterface #28,  2           // InterfaceMethod java/util/Map.get:(Ljava/lang/Object;)Ljava/lang/Object;
      15: checkcast     #9                  // class java/io/RandomAccessFile
      18: astore_2
      19: aload_2
      20: ifnonnull     27
      23: iconst_0
      24: aload_1
      25: monitorexit
      26: ireturn
      27: aload_2
      28: getstatic     #14                 // Field log:Lorg/apache/commons/logging/Log;
      31: invokestatic  #15                 // Method com/amazonaws/util/IOUtils.closeQuietly:(Ljava/io/Closeable;Lorg/apache/commons/logging/Log;)V
      34: getstatic     #7                  // Field lockedFiles:Ljava/util/Map;
      37: aload_0
      38: invokeinterface #29,  2           // InterfaceMethod java/util/Map.remove:(Ljava/lang/Object;)Ljava/lang/Object;
      43: pop
      44: aload_1
      45: monitorexit
      46: goto          54
      49: astore_3
      50: aload_1
      51: monitorexit
      52: aload_3
      53: athrow
      54: getstatic     #14                 // Field log:Lorg/apache/commons/logging/Log;
      57: invokeinterface #19,  1           // InterfaceMethod org/apache/commons/logging/Log.isDebugEnabled:()Z
      62: ifeq          92
      65: getstatic     #14                 // Field log:Lorg/apache/commons/logging/Log;
      68: new           #20                 // class java/lang/StringBuilder
      71: dup
      72: invokespecial #21                 // Method java/lang/StringBuilder."<init>":()V
      75: ldc           #30                 // String Unlocked file
      77: invokevirtual #23                 // Method java/lang/StringBuilder.append:(Ljava/lang/String;)Ljava/lang/StringBuilder;
      80: aload_0
      81: invokevirtual #24                 // Method java/lang/StringBuilder.append:(Ljava/lang/Object;)Ljava/lang/StringBuilder;
      84: invokevirtual #26                 // Method java/lang/StringBuilder.toString:()Ljava/lang/String;
      87: invokeinterface #27,  2           // InterfaceMethod org/apache/commons/logging/Log.debug:(Ljava/lang/Object;)V
      92: iconst_1
      93: ireturn
    Exception table:
       from    to  target type
           6    26    49   any
          27    46    49   any
          49    52    49   any

  static {};
    Code:
       0: iconst_0
       1: anewarray     #1                  // class com/amazonaws/services/s3/internal/FileLocks
       4: putstatic     #2                  // Field $VALUES:[Lcom/amazonaws/services/s3/internal/FileLocks;
       7: ldc           #1                  // class com/amazonaws/services/s3/internal/FileLocks
       9: invokestatic  #31                 // Method org/apache/commons/logging/LogFactory.getLog:(Ljava/lang/Class;)Lorg/apache/commons/logging/Log;
      12: putstatic     #14                 // Field log:Lorg/apache/commons/logging/Log;
      15: new           #32                 // class java/util/TreeMap
      18: dup
      19: invokespecial #33                 // Method java/util/TreeMap."<init>":()V
      22: putstatic     #7                  // Field lockedFiles:Ljava/util/Map;
      25: return
}
