Compiled from "S3QueryStringSigner.java"
public class com.amazonaws.services.s3.internal.S3QueryStringSigner extends com.amazonaws.auth.AbstractAWSSigner {
  private final java.lang.String httpVerb;

  private final java.lang.String resourcePath;

  private final java.util.Date expiration;

  public com.amazonaws.services.s3.internal.S3QueryStringSigner(java.lang.String, java.lang.String, java.util.Date);
    Code:
       0: aload_0
       1: invokespecial #1                  // Method com/amazonaws/auth/AbstractAWSSigner."<init>":()V
       4: aload_0
       5: aload_1
       6: putfield      #2                  // Field httpVerb:Ljava/lang/String;
       9: aload_0
      10: aload_2
      11: putfield      #3                  // Field resourcePath:Ljava/lang/String;
      14: aload_0
      15: aload_3
      16: putfield      #4                  // Field expiration:Ljava/util/Date;
      19: aload_2
      20: ifnonnull     33
      23: new           #5                  // class java/lang/IllegalArgumentException
      26: dup
      27: ldc           #6                  // String Parameter resourcePath is empty
      29: invokespecial #7                  // Method java/lang/IllegalArgumentException."<init>":(Ljava/lang/String;)V
      32: athrow
      33: return

  public void sign(com.amazonaws.SignableRequest<?>, com.amazonaws.auth.AWSCredentials) throws com.amazonaws.AmazonClientException;
    Code:
       0: aload_0
       1: aload_2
       2: invokevirtual #8                  // Method sanitizeCredentials:(Lcom/amazonaws/auth/AWSCredentials;)Lcom/amazonaws/auth/AWSCredentials;
       5: astore_3
       6: aload_3
       7: instanceof    #9                  // class com/amazonaws/auth/AWSSessionCredentials
      10: ifeq          22
      13: aload_0
      14: aload_1
      15: aload_3
      16: checkcast     #9                  // class com/amazonaws/auth/AWSSessionCredentials
      19: invokevirtual #10                 // Method addSessionCredentials:(Lcom/amazonaws/SignableRequest;Lcom/amazonaws/auth/AWSSessionCredentials;)V
      22: aload_0
      23: getfield      #4                  // Field expiration:Ljava/util/Date;
      26: invokevirtual #11                 // Method java/util/Date.getTime:()J
      29: ldc2_w        #12                 // long 1000l
      32: ldiv
      33: invokestatic  #14                 // Method java/lang/Long.toString:(J)Ljava/lang/String;
      36: astore        4
      38: aload_0
      39: getfield      #2                  // Field httpVerb:Ljava/lang/String;
      42: aload_0
      43: getfield      #3                  // Field resourcePath:Ljava/lang/String;
      46: aload_1
      47: aload         4
      49: invokestatic  #15                 // Method com/amazonaws/services/s3/internal/RestUtils.makeS3CanonicalString:(Ljava/lang/String;Ljava/lang/String;Lcom/amazonaws/SignableRequest;Ljava/lang/String;)Ljava/lang/String;
      52: astore        5
      54: aload_0
      55: aload         5
      57: aload_3
      58: invokeinterface #16,  1           // InterfaceMethod com/amazonaws/auth/AWSCredentials.getAWSSecretKey:()Ljava/lang/String;
      63: getstatic     #17                 // Field com/amazonaws/auth/SigningAlgorithm.HmacSHA1:Lcom/amazonaws/auth/SigningAlgorithm;
      66: invokespecial #18                 // Method com/amazonaws/auth/AbstractAWSSigner.signAndBase64Encode:(Ljava/lang/String;Ljava/lang/String;Lcom/amazonaws/auth/SigningAlgorithm;)Ljava/lang/String;
      69: astore        6
      71: aload_1
      72: ldc           #19                 // String AWSAccessKeyId
      74: aload_3
      75: invokeinterface #20,  1           // InterfaceMethod com/amazonaws/auth/AWSCredentials.getAWSAccessKeyId:()Ljava/lang/String;
      80: invokeinterface #21,  3           // InterfaceMethod com/amazonaws/SignableRequest.addParameter:(Ljava/lang/String;Ljava/lang/String;)V
      85: aload_1
      86: ldc           #22                 // String Expires
      88: aload         4
      90: invokeinterface #21,  3           // InterfaceMethod com/amazonaws/SignableRequest.addParameter:(Ljava/lang/String;Ljava/lang/String;)V
      95: aload_1
      96: ldc           #23                 // String Signature
      98: aload         6
     100: invokeinterface #21,  3           // InterfaceMethod com/amazonaws/SignableRequest.addParameter:(Ljava/lang/String;Ljava/lang/String;)V
     105: return

  protected void addSessionCredentials(com.amazonaws.SignableRequest<?>, com.amazonaws.auth.AWSSessionCredentials);
    Code:
       0: aload_1
       1: ldc           #24                 // String x-amz-security-token
       3: aload_2
       4: invokeinterface #25,  1           // InterfaceMethod com/amazonaws/auth/AWSSessionCredentials.getSessionToken:()Ljava/lang/String;
       9: invokeinterface #21,  3           // InterfaceMethod com/amazonaws/SignableRequest.addParameter:(Ljava/lang/String;Ljava/lang/String;)V
      14: return
}
