Compiled from "CacheGuava.java"
public final class org.apache.jena.atlas.lib.cache.CacheGuava<K, V> implements org.apache.jena.atlas.lib.Cache<K, V> {
  private java.util.function.BiConsumer<K, V> dropHandler;

  private org.apache.jena.ext.com.google.common.cache.Cache<K, V> cache;

  public org.apache.jena.atlas.lib.cache.CacheGuava(int);
    Code:
       0: aload_0
       1: invokespecial #1                  // Method java/lang/Object."<init>":()V
       4: aload_0
       5: aconst_null
       6: putfield      #2                  // Field dropHandler:Ljava/util/function/BiConsumer;
       9: aload_0
      10: invokedynamic #3,  0              // InvokeDynamic #0:onRemoval:(Lorg/apache/jena/atlas/lib/cache/CacheGuava;)Lorg/apache/jena/ext/com/google/common/cache/RemovalListener;
      15: astore_2
      16: aload_0
      17: invokestatic  #4                  // Method org/apache/jena/ext/com/google/common/cache/CacheBuilder.newBuilder:()Lorg/apache/jena/ext/com/google/common/cache/CacheBuilder;
      20: iload_1
      21: i2l
      22: invokevirtual #5                  // Method org/apache/jena/ext/com/google/common/cache/CacheBuilder.maximumSize:(J)Lorg/apache/jena/ext/com/google/common/cache/CacheBuilder;
      25: aload_2
      26: invokevirtual #6                  // Method org/apache/jena/ext/com/google/common/cache/CacheBuilder.removalListener:(Lorg/apache/jena/ext/com/google/common/cache/RemovalListener;)Lorg/apache/jena/ext/com/google/common/cache/CacheBuilder;
      29: invokevirtual #7                  // Method org/apache/jena/ext/com/google/common/cache/CacheBuilder.recordStats:()Lorg/apache/jena/ext/com/google/common/cache/CacheBuilder;
      32: bipush        8
      34: invokevirtual #8                  // Method org/apache/jena/ext/com/google/common/cache/CacheBuilder.concurrencyLevel:(I)Lorg/apache/jena/ext/com/google/common/cache/CacheBuilder;
      37: invokevirtual #9                  // Method org/apache/jena/ext/com/google/common/cache/CacheBuilder.build:()Lorg/apache/jena/ext/com/google/common/cache/Cache;
      40: putfield      #10                 // Field cache:Lorg/apache/jena/ext/com/google/common/cache/Cache;
      43: return

  public V getOrFill(K, java.util.concurrent.Callable<V>);
    Code:
       0: aload_0
       1: getfield      #10                 // Field cache:Lorg/apache/jena/ext/com/google/common/cache/Cache;
       4: aload_1
       5: aload_2
       6: invokeinterface #11,  3           // InterfaceMethod org/apache/jena/ext/com/google/common/cache/Cache.get:(Ljava/lang/Object;Ljava/util/concurrent/Callable;)Ljava/lang/Object;
      11: areturn
      12: astore_3
      13: ldc           #13                 // class org/apache/jena/atlas/lib/cache/CacheGuava
      15: ldc           #14                 // String Execution exception filling cache
      17: aload_3
      18: invokestatic  #15                 // Method org/apache/jena/atlas/logging/Log.warn:(Ljava/lang/Class;Ljava/lang/String;Ljava/lang/Throwable;)V
      21: aconst_null
      22: areturn
    Exception table:
       from    to  target type
           0    11    12   Class java/util/concurrent/ExecutionException

  public V getIfPresent(K);
    Code:
       0: aload_0
       1: getfield      #10                 // Field cache:Lorg/apache/jena/ext/com/google/common/cache/Cache;
       4: aload_1
       5: invokeinterface #16,  2           // InterfaceMethod org/apache/jena/ext/com/google/common/cache/Cache.getIfPresent:(Ljava/lang/Object;)Ljava/lang/Object;
      10: areturn

  public void put(K, V);
    Code:
       0: aload_2
       1: ifnonnull     17
       4: aload_0
       5: getfield      #10                 // Field cache:Lorg/apache/jena/ext/com/google/common/cache/Cache;
       8: aload_1
       9: invokeinterface #17,  2           // InterfaceMethod org/apache/jena/ext/com/google/common/cache/Cache.invalidate:(Ljava/lang/Object;)V
      14: goto          28
      17: aload_0
      18: getfield      #10                 // Field cache:Lorg/apache/jena/ext/com/google/common/cache/Cache;
      21: aload_1
      22: aload_2
      23: invokeinterface #18,  3           // InterfaceMethod org/apache/jena/ext/com/google/common/cache/Cache.put:(Ljava/lang/Object;Ljava/lang/Object;)V
      28: return

  public boolean containsKey(K);
    Code:
       0: aload_0
       1: getfield      #10                 // Field cache:Lorg/apache/jena/ext/com/google/common/cache/Cache;
       4: aload_1
       5: invokeinterface #16,  2           // InterfaceMethod org/apache/jena/ext/com/google/common/cache/Cache.getIfPresent:(Ljava/lang/Object;)Ljava/lang/Object;
      10: ifnull        17
      13: iconst_1
      14: goto          18
      17: iconst_0
      18: ireturn

  public void remove(K);
    Code:
       0: aload_0
       1: getfield      #10                 // Field cache:Lorg/apache/jena/ext/com/google/common/cache/Cache;
       4: aload_1
       5: invokeinterface #17,  2           // InterfaceMethod org/apache/jena/ext/com/google/common/cache/Cache.invalidate:(Ljava/lang/Object;)V
      10: return

  public java.util.Iterator<K> keys();
    Code:
       0: aload_0
       1: getfield      #10                 // Field cache:Lorg/apache/jena/ext/com/google/common/cache/Cache;
       4: invokeinterface #19,  1           // InterfaceMethod org/apache/jena/ext/com/google/common/cache/Cache.asMap:()Ljava/util/concurrent/ConcurrentMap;
       9: invokeinterface #20,  1           // InterfaceMethod java/util/concurrent/ConcurrentMap.keySet:()Ljava/util/Set;
      14: invokeinterface #21,  1           // InterfaceMethod java/util/Set.iterator:()Ljava/util/Iterator;
      19: areturn

  public boolean isEmpty();
    Code:
       0: aload_0
       1: getfield      #10                 // Field cache:Lorg/apache/jena/ext/com/google/common/cache/Cache;
       4: invokeinterface #22,  1           // InterfaceMethod org/apache/jena/ext/com/google/common/cache/Cache.size:()J
       9: lconst_0
      10: lcmp
      11: ifne          18
      14: iconst_1
      15: goto          19
      18: iconst_0
      19: ireturn

  public void clear();
    Code:
       0: aload_0
       1: getfield      #10                 // Field cache:Lorg/apache/jena/ext/com/google/common/cache/Cache;
       4: invokeinterface #23,  1           // InterfaceMethod org/apache/jena/ext/com/google/common/cache/Cache.invalidateAll:()V
       9: return

  public long size();
    Code:
       0: aload_0
       1: getfield      #10                 // Field cache:Lorg/apache/jena/ext/com/google/common/cache/Cache;
       4: invokeinterface #22,  1           // InterfaceMethod org/apache/jena/ext/com/google/common/cache/Cache.size:()J
       9: lreturn

  public void setDropHandler(java.util.function.BiConsumer<K, V>);
    Code:
       0: aload_0
       1: aload_1
       2: putfield      #2                  // Field dropHandler:Ljava/util/function/BiConsumer;
       5: return

  public org.apache.jena.ext.com.google.common.cache.CacheStats stats();
    Code:
       0: aload_0
       1: getfield      #10                 // Field cache:Lorg/apache/jena/ext/com/google/common/cache/Cache;
       4: invokeinterface #24,  1           // InterfaceMethod org/apache/jena/ext/com/google/common/cache/Cache.stats:()Lorg/apache/jena/ext/com/google/common/cache/CacheStats;
       9: areturn

  private void lambda$new$0(org.apache.jena.ext.com.google.common.cache.RemovalNotification);
    Code:
       0: aload_0
       1: getfield      #2                  // Field dropHandler:Ljava/util/function/BiConsumer;
       4: ifnull        24
       7: aload_0
       8: getfield      #2                  // Field dropHandler:Ljava/util/function/BiConsumer;
      11: aload_1
      12: invokevirtual #25                 // Method org/apache/jena/ext/com/google/common/cache/RemovalNotification.getKey:()Ljava/lang/Object;
      15: aload_1
      16: invokevirtual #26                 // Method org/apache/jena/ext/com/google/common/cache/RemovalNotification.getValue:()Ljava/lang/Object;
      19: invokeinterface #27,  3           // InterfaceMethod java/util/function/BiConsumer.accept:(Ljava/lang/Object;Ljava/lang/Object;)V
      24: return
}
