Compiled from "Node.java"
public class org.sonar.api.utils.dag.Node implements java.lang.Comparable<org.sonar.api.utils.dag.Node> {
  private final java.lang.Object object;

  private int order;

  private boolean seen;

  private final java.util.List<org.sonar.api.utils.dag.Node> dependencies;

  public org.sonar.api.utils.dag.Node(java.lang.Object);
    Code:
       0: aload_0
       1: invokespecial #22                 // Method java/lang/Object."<init>":()V
       4: aload_0
       5: iconst_0
       6: putfield      #24                 // Field order:I
       9: aload_0
      10: iconst_0
      11: putfield      #26                 // Field seen:Z
      14: aload_0
      15: new           #28                 // class java/util/ArrayList
      18: dup
      19: invokespecial #29                 // Method java/util/ArrayList."<init>":()V
      22: putfield      #31                 // Field dependencies:Ljava/util/List;
      25: aload_1
      26: ifnonnull     39
      29: new           #33                 // class org/sonar/api/utils/SonarException
      32: dup
      33: ldc           #35                 // String object can not be null
      35: invokespecial #38                 // Method org/sonar/api/utils/SonarException."<init>":(Ljava/lang/String;)V
      38: athrow
      39: aload_0
      40: aload_1
      41: putfield      #40                 // Field object:Ljava/lang/Object;
      44: return

  public void reset();
    Code:
       0: aload_0
       1: iconst_0
       2: putfield      #24                 // Field order:I
       5: aload_0
       6: iconst_0
       7: putfield      #26                 // Field seen:Z
      10: return

  public java.lang.Object getObject();
    Code:
       0: aload_0
       1: getfield      #40                 // Field object:Ljava/lang/Object;
       4: areturn

  public void addDependency(org.sonar.api.utils.dag.Node);
    Code:
       0: aload_0
       1: aload_1
       2: invokevirtual #51                 // Method equals:(Ljava/lang/Object;)Z
       5: ifne          32
       8: aload_0
       9: getfield      #31                 // Field dependencies:Ljava/util/List;
      12: aload_1
      13: invokeinterface #56,  2           // InterfaceMethod java/util/List.contains:(Ljava/lang/Object;)Z
      18: ifne          32
      21: aload_0
      22: getfield      #31                 // Field dependencies:Ljava/util/List;
      25: aload_1
      26: invokeinterface #59,  2           // InterfaceMethod java/util/List.add:(Ljava/lang/Object;)Z
      31: pop
      32: return

  public void resolveOrder();
    Code:
       0: aload_0
       1: aload_0
       2: invokevirtual #65                 // Method toString:()Ljava/lang/String;
       5: invokespecial #68                 // Method resolveOrder:(Ljava/lang/String;)I
       8: pop
       9: return

  private int resolveOrder(java.lang.String);
    Code:
       0: aload_0
       1: iconst_1
       2: putfield      #26                 // Field seen:Z
       5: iconst_m1
       6: istore_2
       7: aload_0
       8: getfield      #31                 // Field dependencies:Ljava/util/List;
      11: invokeinterface #72,  1           // InterfaceMethod java/util/List.iterator:()Ljava/util/Iterator;
      16: astore_3
      17: aload_3
      18: invokeinterface #78,  1           // InterfaceMethod java/util/Iterator.hasNext:()Z
      23: ifeq          120
      26: aload_3
      27: invokeinterface #81,  1           // InterfaceMethod java/util/Iterator.next:()Ljava/lang/Object;
      32: checkcast     #2                  // class org/sonar/api/utils/dag/Node
      35: astore        4
      37: aload         4
      39: getfield      #26                 // Field seen:Z
      42: ifeq          80
      45: new           #83                 // class org/sonar/api/utils/dag/CyclicDependenciesException
      48: dup
      49: new           #85                 // class java/lang/StringBuilder
      52: dup
      53: invokespecial #86                 // Method java/lang/StringBuilder."<init>":()V
      56: aload_1
      57: invokevirtual #90                 // Method java/lang/StringBuilder.append:(Ljava/lang/String;)Ljava/lang/StringBuilder;
      60: ldc           #92                 // String  ->
      62: invokevirtual #90                 // Method java/lang/StringBuilder.append:(Ljava/lang/String;)Ljava/lang/StringBuilder;
      65: aload         4
      67: invokevirtual #65                 // Method toString:()Ljava/lang/String;
      70: invokevirtual #90                 // Method java/lang/StringBuilder.append:(Ljava/lang/String;)Ljava/lang/StringBuilder;
      73: invokevirtual #93                 // Method java/lang/StringBuilder.toString:()Ljava/lang/String;
      76: invokespecial #94                 // Method org/sonar/api/utils/dag/CyclicDependenciesException."<init>":(Ljava/lang/String;)V
      79: athrow
      80: iload_2
      81: aload         4
      83: new           #85                 // class java/lang/StringBuilder
      86: dup
      87: invokespecial #86                 // Method java/lang/StringBuilder."<init>":()V
      90: aload_1
      91: invokevirtual #90                 // Method java/lang/StringBuilder.append:(Ljava/lang/String;)Ljava/lang/StringBuilder;
      94: ldc           #92                 // String  ->
      96: invokevirtual #90                 // Method java/lang/StringBuilder.append:(Ljava/lang/String;)Ljava/lang/StringBuilder;
      99: aload         4
     101: invokevirtual #65                 // Method toString:()Ljava/lang/String;
     104: invokevirtual #90                 // Method java/lang/StringBuilder.append:(Ljava/lang/String;)Ljava/lang/StringBuilder;
     107: invokevirtual #93                 // Method java/lang/StringBuilder.toString:()Ljava/lang/String;
     110: invokespecial #68                 // Method resolveOrder:(Ljava/lang/String;)I
     113: invokestatic  #100                // Method java/lang/Math.max:(II)I
     116: istore_2
     117: goto          17
     120: aload_0
     121: iload_2
     122: iconst_1
     123: iadd
     124: putfield      #24                 // Field order:I
     127: aload_0
     128: getfield      #24                 // Field order:I
     131: istore_3
     132: aload_0
     133: iconst_0
     134: putfield      #26                 // Field seen:Z
     137: iload_3
     138: ireturn
     139: astore        5
     141: aload_0
     142: iconst_0
     143: putfield      #26                 // Field seen:Z
     146: aload         5
     148: athrow
    Exception table:
       from    to  target type
           5   132   139   any
         139   141   139   any

  public java.util.List<org.sonar.api.utils.dag.Node> getDependencies();
    Code:
       0: aload_0
       1: getfield      #31                 // Field dependencies:Ljava/util/List;
       4: areturn

  public int compareTo(org.sonar.api.utils.dag.Node);
    Code:
       0: iconst_0
       1: istore_2
       2: aload_0
       3: getfield      #24                 // Field order:I
       6: aload_1
       7: getfield      #24                 // Field order:I
      10: if_icmpge     18
      13: iconst_m1
      14: istore_2
      15: goto          31
      18: aload_0
      19: getfield      #24                 // Field order:I
      22: aload_1
      23: getfield      #24                 // Field order:I
      26: if_icmple     31
      29: iconst_1
      30: istore_2
      31: iload_2
      32: ireturn

  public java.lang.String toString();
    Code:
       0: aload_0
       1: getfield      #40                 // Field object:Ljava/lang/Object;
       4: invokevirtual #116                // Method java/lang/Object.toString:()Ljava/lang/String;
       7: areturn

  public boolean equals(java.lang.Object);
    Code:
       0: aload_0
       1: aload_1
       2: if_acmpne     7
       5: iconst_1
       6: ireturn
       7: aload_1
       8: instanceof    #2                  // class org/sonar/api/utils/dag/Node
      11: ifne          16
      14: iconst_0
      15: ireturn
      16: aload_0
      17: getfield      #40                 // Field object:Ljava/lang/Object;
      20: aload_1
      21: checkcast     #2                  // class org/sonar/api/utils/dag/Node
      24: invokevirtual #118                // Method getObject:()Ljava/lang/Object;
      27: invokevirtual #119                // Method java/lang/Object.equals:(Ljava/lang/Object;)Z
      30: ireturn

  public int hashCode();
    Code:
       0: aload_0
       1: getfield      #40                 // Field object:Ljava/lang/Object;
       4: invokevirtual #124                // Method java/lang/Object.hashCode:()I
       7: ireturn

  public int compareTo(java.lang.Object);
    Code:
       0: aload_0
       1: aload_1
       2: checkcast     #2                  // class org/sonar/api/utils/dag/Node
       5: invokevirtual #127                // Method compareTo:(Lorg/sonar/api/utils/dag/Node;)I
       8: ireturn
}
