Compiled from "JavaViewPropertiesFactory.java"
public class org.sklsft.generator.components.metadata.factory.impl.JavaViewPropertiesFactory implements org.sklsft.generator.components.metadata.factory.interfaces.ViewPropertiesFactory {
  public org.sklsft.generator.components.metadata.factory.impl.JavaViewPropertiesFactory();
    Code:
       0: aload_0
       1: invokespecial #1                  // Method java/lang/Object."<init>":()V
       4: return

  private java.util.List<org.sklsft.generator.model.domain.ui.ViewProperty> getViewProperties(org.sklsft.generator.model.domain.business.Property, org.sklsft.generator.model.domain.business.Bean);
    Code:
       0: new           #2                  // class java/util/ArrayList
       3: dup
       4: invokespecial #3                  // Method java/util/ArrayList."<init>":()V
       7: astore_3
       8: aload_1
       9: getfield      #4                  // Field org/sklsft/generator/model/domain/business/Property.referenceBean:Lorg/sklsft/generator/model/domain/business/Bean;
      12: ifnonnull     187
      15: new           #5                  // class org/sklsft/generator/model/domain/ui/ViewProperty
      18: dup
      19: invokespecial #6                  // Method org/sklsft/generator/model/domain/ui/ViewProperty."<init>":()V
      22: astore        4
      24: aload         4
      26: aload_1
      27: getfield      #7                  // Field org/sklsft/generator/model/domain/business/Property.name:Ljava/lang/String;
      30: putfield      #8                  // Field org/sklsft/generator/model/domain/ui/ViewProperty.name:Ljava/lang/String;
      33: aload         4
      35: aload_1
      36: getfield      #9                  // Field org/sklsft/generator/model/domain/business/Property.capName:Ljava/lang/String;
      39: putfield      #10                 // Field org/sklsft/generator/model/domain/ui/ViewProperty.capName:Ljava/lang/String;
      42: aload         4
      44: new           #11                 // class java/lang/StringBuilder
      47: dup
      48: invokespecial #12                 // Method java/lang/StringBuilder."<init>":()V
      51: aload_1
      52: getfield      #13                 // Field org/sklsft/generator/model/domain/business/Property.getterName:Ljava/lang/String;
      55: invokevirtual #14                 // Method java/lang/StringBuilder.append:(Ljava/lang/String;)Ljava/lang/StringBuilder;
      58: ldc           #15                 // String ()
      60: invokevirtual #14                 // Method java/lang/StringBuilder.append:(Ljava/lang/String;)Ljava/lang/StringBuilder;
      63: invokevirtual #16                 // Method java/lang/StringBuilder.toString:()Ljava/lang/String;
      66: putfield      #17                 // Field org/sklsft/generator/model/domain/ui/ViewProperty.mappingPath:Ljava/lang/String;
      69: aload         4
      71: aload_1
      72: getfield      #18                 // Field org/sklsft/generator/model/domain/business/Property.javaType:Ljava/lang/String;
      75: putfield      #19                 // Field org/sklsft/generator/model/domain/ui/ViewProperty.javaType:Ljava/lang/String;
      78: aload         4
      80: aload_1
      81: getfield      #20                 // Field org/sklsft/generator/model/domain/business/Property.tsType:Ljava/lang/String;
      84: putfield      #21                 // Field org/sklsft/generator/model/domain/ui/ViewProperty.tsType:Ljava/lang/String;
      87: aload         4
      89: aload_1
      90: getfield      #22                 // Field org/sklsft/generator/model/domain/business/Property.dataType:Lorg/sklsft/generator/model/metadata/DataType;
      93: putfield      #23                 // Field org/sklsft/generator/model/domain/ui/ViewProperty.dataType:Lorg/sklsft/generator/model/metadata/DataType;
      96: aload         4
      98: aload_1
      99: getfield      #24                 // Field org/sklsft/generator/model/domain/business/Property.nullable:Z
     102: putfield      #25                 // Field org/sklsft/generator/model/domain/ui/ViewProperty.nullable:Z
     105: aload         4
     107: aload_1
     108: getfield      #26                 // Field org/sklsft/generator/model/domain/business/Property.visibility:Lorg/sklsft/generator/model/metadata/Visibility;
     111: putfield      #27                 // Field org/sklsft/generator/model/domain/ui/ViewProperty.visibility:Lorg/sklsft/generator/model/metadata/Visibility;
     114: aload         4
     116: aload_1
     117: getfield      #28                 // Field org/sklsft/generator/model/domain/business/Property.editable:Z
     120: putfield      #29                 // Field org/sklsft/generator/model/domain/ui/ViewProperty.editable:Z
     123: aload         4
     125: aload_1
     126: getfield      #30                 // Field org/sklsft/generator/model/domain/business/Property.filterable:Z
     129: putfield      #31                 // Field org/sklsft/generator/model/domain/ui/ViewProperty.filterable:Z
     132: aload         4
     134: aload_1
     135: getfield      #32                 // Field org/sklsft/generator/model/domain/business/Property.textFilterType:Lorg/sklsft/generator/model/metadata/TextFilterType;
     138: putfield      #33                 // Field org/sklsft/generator/model/domain/ui/ViewProperty.textFilterType:Lorg/sklsft/generator/model/metadata/TextFilterType;
     141: aload         4
     143: aload_1
     144: getfield      #7                  // Field org/sklsft/generator/model/domain/business/Property.name:Ljava/lang/String;
     147: putfield      #34                 // Field org/sklsft/generator/model/domain/ui/ViewProperty.lastPropertyName:Ljava/lang/String;
     150: aload         4
     152: aload_2
     153: getfield      #35                 // Field org/sklsft/generator/model/domain/business/Bean.className:Ljava/lang/String;
     156: putfield      #36                 // Field org/sklsft/generator/model/domain/ui/ViewProperty.lastParentBeanClassName:Ljava/lang/String;
     159: aload         4
     161: ldc           #37                 // String
     163: putfield      #38                 // Field org/sklsft/generator/model/domain/ui/ViewProperty.joinedAliasName:Ljava/lang/String;
     166: aload         4
     168: aload_1
     169: getfield      #39                 // Field org/sklsft/generator/model/domain/business/Property.rendering:Ljava/lang/String;
     172: putfield      #40                 // Field org/sklsft/generator/model/domain/ui/ViewProperty.rendering:Ljava/lang/String;
     175: aload_3
     176: aload         4
     178: invokeinterface #41,  2           // InterfaceMethod java/util/List.add:(Ljava/lang/Object;)Z
     183: pop
     184: goto          1111
     187: aload_1
     188: getfield      #42                 // Field org/sklsft/generator/model/domain/business/Property.embedded:Z
     191: ifeq          209
     194: aload_1
     195: getfield      #4                  // Field org/sklsft/generator/model/domain/business/Property.referenceBean:Lorg/sklsft/generator/model/domain/business/Bean;
     198: getfield      #43                 // Field org/sklsft/generator/model/domain/business/Bean.properties:Ljava/util/List;
     201: invokeinterface #44,  1           // InterfaceMethod java/util/List.size:()I
     206: goto          216
     209: aload_1
     210: getfield      #4                  // Field org/sklsft/generator/model/domain/business/Property.referenceBean:Lorg/sklsft/generator/model/domain/business/Bean;
     213: getfield      #45                 // Field org/sklsft/generator/model/domain/business/Bean.cardinality:I
     216: istore        4
     218: iconst_0
     219: istore        5
     221: iload         5
     223: iload         4
     225: if_icmpge     1111
     228: aload_1
     229: getfield      #4                  // Field org/sklsft/generator/model/domain/business/Property.referenceBean:Lorg/sklsft/generator/model/domain/business/Bean;
     232: getfield      #43                 // Field org/sklsft/generator/model/domain/business/Bean.properties:Ljava/util/List;
     235: iload         5
     237: invokeinterface #46,  2           // InterfaceMethod java/util/List.get:(I)Ljava/lang/Object;
     242: checkcast     #47                 // class org/sklsft/generator/model/domain/business/Property
     245: astore        6
     247: aload         6
     249: getfield      #4                  // Field org/sklsft/generator/model/domain/business/Property.referenceBean:Lorg/sklsft/generator/model/domain/business/Bean;
     252: ifnull        674
     255: aload_0
     256: aload         6
     258: aload_1
     259: getfield      #4                  // Field org/sklsft/generator/model/domain/business/Property.referenceBean:Lorg/sklsft/generator/model/domain/business/Bean;
     262: invokespecial #48                 // Method getViewProperties:(Lorg/sklsft/generator/model/domain/business/Property;Lorg/sklsft/generator/model/domain/business/Bean;)Ljava/util/List;
     265: astore        7
     267: aload         7
     269: invokeinterface #49,  1           // InterfaceMethod java/util/List.iterator:()Ljava/util/Iterator;
     274: astore        8
     276: aload         8
     278: invokeinterface #50,  1           // InterfaceMethod java/util/Iterator.hasNext:()Z
     283: ifeq          671
     286: aload         8
     288: invokeinterface #51,  1           // InterfaceMethod java/util/Iterator.next:()Ljava/lang/Object;
     293: checkcast     #5                  // class org/sklsft/generator/model/domain/ui/ViewProperty
     296: astore        9
     298: new           #5                  // class org/sklsft/generator/model/domain/ui/ViewProperty
     301: dup
     302: invokespecial #6                  // Method org/sklsft/generator/model/domain/ui/ViewProperty."<init>":()V
     305: astore        10
     307: aload_1
     308: getfield      #42                 // Field org/sklsft/generator/model/domain/business/Property.embedded:Z
     311: ifeq          337
     314: aload         10
     316: aload         9
     318: getfield      #8                  // Field org/sklsft/generator/model/domain/ui/ViewProperty.name:Ljava/lang/String;
     321: putfield      #8                  // Field org/sklsft/generator/model/domain/ui/ViewProperty.name:Ljava/lang/String;
     324: aload         10
     326: aload         9
     328: getfield      #10                 // Field org/sklsft/generator/model/domain/ui/ViewProperty.capName:Ljava/lang/String;
     331: putfield      #10                 // Field org/sklsft/generator/model/domain/ui/ViewProperty.capName:Ljava/lang/String;
     334: goto          397
     337: aload         10
     339: new           #11                 // class java/lang/StringBuilder
     342: dup
     343: invokespecial #12                 // Method java/lang/StringBuilder."<init>":()V
     346: aload_1
     347: getfield      #7                  // Field org/sklsft/generator/model/domain/business/Property.name:Ljava/lang/String;
     350: invokevirtual #14                 // Method java/lang/StringBuilder.append:(Ljava/lang/String;)Ljava/lang/StringBuilder;
     353: aload         9
     355: getfield      #10                 // Field org/sklsft/generator/model/domain/ui/ViewProperty.capName:Ljava/lang/String;
     358: invokevirtual #14                 // Method java/lang/StringBuilder.append:(Ljava/lang/String;)Ljava/lang/StringBuilder;
     361: invokevirtual #16                 // Method java/lang/StringBuilder.toString:()Ljava/lang/String;
     364: putfield      #8                  // Field org/sklsft/generator/model/domain/ui/ViewProperty.name:Ljava/lang/String;
     367: aload         10
     369: new           #11                 // class java/lang/StringBuilder
     372: dup
     373: invokespecial #12                 // Method java/lang/StringBuilder."<init>":()V
     376: aload_1
     377: getfield      #9                  // Field org/sklsft/generator/model/domain/business/Property.capName:Ljava/lang/String;
     380: invokevirtual #14                 // Method java/lang/StringBuilder.append:(Ljava/lang/String;)Ljava/lang/StringBuilder;
     383: aload         9
     385: getfield      #10                 // Field org/sklsft/generator/model/domain/ui/ViewProperty.capName:Ljava/lang/String;
     388: invokevirtual #14                 // Method java/lang/StringBuilder.append:(Ljava/lang/String;)Ljava/lang/StringBuilder;
     391: invokevirtual #16                 // Method java/lang/StringBuilder.toString:()Ljava/lang/String;
     394: putfield      #10                 // Field org/sklsft/generator/model/domain/ui/ViewProperty.capName:Ljava/lang/String;
     397: aload         10
     399: new           #11                 // class java/lang/StringBuilder
     402: dup
     403: invokespecial #12                 // Method java/lang/StringBuilder."<init>":()V
     406: aload_1
     407: getfield      #13                 // Field org/sklsft/generator/model/domain/business/Property.getterName:Ljava/lang/String;
     410: invokevirtual #14                 // Method java/lang/StringBuilder.append:(Ljava/lang/String;)Ljava/lang/StringBuilder;
     413: ldc           #52                 // String ().
     415: invokevirtual #14                 // Method java/lang/StringBuilder.append:(Ljava/lang/String;)Ljava/lang/StringBuilder;
     418: aload         9
     420: getfield      #17                 // Field org/sklsft/generator/model/domain/ui/ViewProperty.mappingPath:Ljava/lang/String;
     423: invokevirtual #14                 // Method java/lang/StringBuilder.append:(Ljava/lang/String;)Ljava/lang/StringBuilder;
     426: invokevirtual #16                 // Method java/lang/StringBuilder.toString:()Ljava/lang/String;
     429: putfield      #17                 // Field org/sklsft/generator/model/domain/ui/ViewProperty.mappingPath:Ljava/lang/String;
     432: aload         10
     434: aload         9
     436: getfield      #19                 // Field org/sklsft/generator/model/domain/ui/ViewProperty.javaType:Ljava/lang/String;
     439: putfield      #19                 // Field org/sklsft/generator/model/domain/ui/ViewProperty.javaType:Ljava/lang/String;
     442: aload         10
     444: aload         9
     446: getfield      #21                 // Field org/sklsft/generator/model/domain/ui/ViewProperty.tsType:Ljava/lang/String;
     449: putfield      #21                 // Field org/sklsft/generator/model/domain/ui/ViewProperty.tsType:Ljava/lang/String;
     452: aload         10
     454: aload         9
     456: getfield      #23                 // Field org/sklsft/generator/model/domain/ui/ViewProperty.dataType:Lorg/sklsft/generator/model/metadata/DataType;
     459: putfield      #23                 // Field org/sklsft/generator/model/domain/ui/ViewProperty.dataType:Lorg/sklsft/generator/model/metadata/DataType;
     462: aload         10
     464: aload_1
     465: getfield      #24                 // Field org/sklsft/generator/model/domain/business/Property.nullable:Z
     468: ifne          479
     471: aload         9
     473: getfield      #25                 // Field org/sklsft/generator/model/domain/ui/ViewProperty.nullable:Z
     476: ifeq          483
     479: iconst_1
     480: goto          484
     483: iconst_0
     484: putfield      #25                 // Field org/sklsft/generator/model/domain/ui/ViewProperty.nullable:Z
     487: aload         10
     489: aload_1
     490: getfield      #26                 // Field org/sklsft/generator/model/domain/business/Property.visibility:Lorg/sklsft/generator/model/metadata/Visibility;
     493: aload         9
     495: getfield      #27                 // Field org/sklsft/generator/model/domain/ui/ViewProperty.visibility:Lorg/sklsft/generator/model/metadata/Visibility;
     498: invokestatic  #53                 // Method org/sklsft/generator/model/metadata/Visibility.min:(Lorg/sklsft/generator/model/metadata/Visibility;Lorg/sklsft/generator/model/metadata/Visibility;)Lorg/sklsft/generator/model/metadata/Visibility;
     501: putfield      #27                 // Field org/sklsft/generator/model/domain/ui/ViewProperty.visibility:Lorg/sklsft/generator/model/metadata/Visibility;
     504: aload         10
     506: aload_1
     507: getfield      #42                 // Field org/sklsft/generator/model/domain/business/Property.embedded:Z
     510: ifeq          521
     513: aload         9
     515: getfield      #29                 // Field org/sklsft/generator/model/domain/ui/ViewProperty.editable:Z
     518: goto          525
     521: aload_1
     522: getfield      #28                 // Field org/sklsft/generator/model/domain/business/Property.editable:Z
     525: putfield      #29                 // Field org/sklsft/generator/model/domain/ui/ViewProperty.editable:Z
     528: aload         10
     530: aload_1
     531: getfield      #42                 // Field org/sklsft/generator/model/domain/business/Property.embedded:Z
     534: ifeq          545
     537: aload         9
     539: getfield      #31                 // Field org/sklsft/generator/model/domain/ui/ViewProperty.filterable:Z
     542: goto          549
     545: aload_1
     546: getfield      #30                 // Field org/sklsft/generator/model/domain/business/Property.filterable:Z
     549: putfield      #31                 // Field org/sklsft/generator/model/domain/ui/ViewProperty.filterable:Z
     552: aload         10
     554: aload_1
     555: getfield      #42                 // Field org/sklsft/generator/model/domain/business/Property.embedded:Z
     558: ifeq          569
     561: aload         9
     563: getfield      #33                 // Field org/sklsft/generator/model/domain/ui/ViewProperty.textFilterType:Lorg/sklsft/generator/model/metadata/TextFilterType;
     566: goto          573
     569: aload_1
     570: getfield      #32                 // Field org/sklsft/generator/model/domain/business/Property.textFilterType:Lorg/sklsft/generator/model/metadata/TextFilterType;
     573: putfield      #33                 // Field org/sklsft/generator/model/domain/ui/ViewProperty.textFilterType:Lorg/sklsft/generator/model/metadata/TextFilterType;
     576: aload         10
     578: aload         9
     580: getfield      #34                 // Field org/sklsft/generator/model/domain/ui/ViewProperty.lastPropertyName:Ljava/lang/String;
     583: putfield      #34                 // Field org/sklsft/generator/model/domain/ui/ViewProperty.lastPropertyName:Ljava/lang/String;
     586: aload         10
     588: aload         9
     590: getfield      #36                 // Field org/sklsft/generator/model/domain/ui/ViewProperty.lastParentBeanClassName:Ljava/lang/String;
     593: putfield      #36                 // Field org/sklsft/generator/model/domain/ui/ViewProperty.lastParentBeanClassName:Ljava/lang/String;
     596: aload         10
     598: new           #11                 // class java/lang/StringBuilder
     601: dup
     602: invokespecial #12                 // Method java/lang/StringBuilder."<init>":()V
     605: aload_1
     606: getfield      #7                  // Field org/sklsft/generator/model/domain/business/Property.name:Ljava/lang/String;
     609: invokevirtual #14                 // Method java/lang/StringBuilder.append:(Ljava/lang/String;)Ljava/lang/StringBuilder;
     612: aload         9
     614: getfield      #38                 // Field org/sklsft/generator/model/domain/ui/ViewProperty.joinedAliasName:Ljava/lang/String;
     617: invokestatic  #54                 // Method org/sklsft/generator/model/util/naming/JavaClassNaming.getClassNameFromObjectName:(Ljava/lang/String;)Ljava/lang/String;
     620: invokevirtual #14                 // Method java/lang/StringBuilder.append:(Ljava/lang/String;)Ljava/lang/StringBuilder;
     623: invokevirtual #16                 // Method java/lang/StringBuilder.toString:()Ljava/lang/String;
     626: putfield      #38                 // Field org/sklsft/generator/model/domain/ui/ViewProperty.joinedAliasName:Ljava/lang/String;
     629: aload         10
     631: aload         9
     633: getfield      #55                 // Field org/sklsft/generator/model/domain/ui/ViewProperty.referenceBean:Lorg/sklsft/generator/model/domain/business/Bean;
     636: putfield      #55                 // Field org/sklsft/generator/model/domain/ui/ViewProperty.referenceBean:Lorg/sklsft/generator/model/domain/business/Bean;
     639: aload         10
     641: aload         9
     643: getfield      #56                 // Field org/sklsft/generator/model/domain/ui/ViewProperty.selectableBean:Lorg/sklsft/generator/model/domain/business/Bean;
     646: putfield      #56                 // Field org/sklsft/generator/model/domain/ui/ViewProperty.selectableBean:Lorg/sklsft/generator/model/domain/business/Bean;
     649: aload         10
     651: aload         9
     653: getfield      #40                 // Field org/sklsft/generator/model/domain/ui/ViewProperty.rendering:Ljava/lang/String;
     656: putfield      #40                 // Field org/sklsft/generator/model/domain/ui/ViewProperty.rendering:Ljava/lang/String;
     659: aload_3
     660: aload         10
     662: invokeinterface #41,  2           // InterfaceMethod java/util/List.add:(Ljava/lang/Object;)Z
     667: pop
     668: goto          276
     671: goto          1105
     674: new           #5                  // class org/sklsft/generator/model/domain/ui/ViewProperty
     677: dup
     678: invokespecial #6                  // Method org/sklsft/generator/model/domain/ui/ViewProperty."<init>":()V
     681: astore        7
     683: aload_1
     684: getfield      #42                 // Field org/sklsft/generator/model/domain/business/Property.embedded:Z
     687: ifeq          713
     690: aload         7
     692: aload         6
     694: getfield      #7                  // Field org/sklsft/generator/model/domain/business/Property.name:Ljava/lang/String;
     697: putfield      #8                  // Field org/sklsft/generator/model/domain/ui/ViewProperty.name:Ljava/lang/String;
     700: aload         7
     702: aload         6
     704: getfield      #9                  // Field org/sklsft/generator/model/domain/business/Property.capName:Ljava/lang/String;
     707: putfield      #10                 // Field org/sklsft/generator/model/domain/ui/ViewProperty.capName:Ljava/lang/String;
     710: goto          773
     713: aload         7
     715: new           #11                 // class java/lang/StringBuilder
     718: dup
     719: invokespecial #12                 // Method java/lang/StringBuilder."<init>":()V
     722: aload_1
     723: getfield      #7                  // Field org/sklsft/generator/model/domain/business/Property.name:Ljava/lang/String;
     726: invokevirtual #14                 // Method java/lang/StringBuilder.append:(Ljava/lang/String;)Ljava/lang/StringBuilder;
     729: aload         6
     731: getfield      #9                  // Field org/sklsft/generator/model/domain/business/Property.capName:Ljava/lang/String;
     734: invokevirtual #14                 // Method java/lang/StringBuilder.append:(Ljava/lang/String;)Ljava/lang/StringBuilder;
     737: invokevirtual #16                 // Method java/lang/StringBuilder.toString:()Ljava/lang/String;
     740: putfield      #8                  // Field org/sklsft/generator/model/domain/ui/ViewProperty.name:Ljava/lang/String;
     743: aload         7
     745: new           #11                 // class java/lang/StringBuilder
     748: dup
     749: invokespecial #12                 // Method java/lang/StringBuilder."<init>":()V
     752: aload_1
     753: getfield      #9                  // Field org/sklsft/generator/model/domain/business/Property.capName:Ljava/lang/String;
     756: invokevirtual #14                 // Method java/lang/StringBuilder.append:(Ljava/lang/String;)Ljava/lang/StringBuilder;
     759: aload         6
     761: getfield      #9                  // Field org/sklsft/generator/model/domain/business/Property.capName:Ljava/lang/String;
     764: invokevirtual #14                 // Method java/lang/StringBuilder.append:(Ljava/lang/String;)Ljava/lang/StringBuilder;
     767: invokevirtual #16                 // Method java/lang/StringBuilder.toString:()Ljava/lang/String;
     770: putfield      #10                 // Field org/sklsft/generator/model/domain/ui/ViewProperty.capName:Ljava/lang/String;
     773: aload         7
     775: new           #11                 // class java/lang/StringBuilder
     778: dup
     779: invokespecial #12                 // Method java/lang/StringBuilder."<init>":()V
     782: aload_1
     783: getfield      #13                 // Field org/sklsft/generator/model/domain/business/Property.getterName:Ljava/lang/String;
     786: invokevirtual #14                 // Method java/lang/StringBuilder.append:(Ljava/lang/String;)Ljava/lang/StringBuilder;
     789: ldc           #52                 // String ().
     791: invokevirtual #14                 // Method java/lang/StringBuilder.append:(Ljava/lang/String;)Ljava/lang/StringBuilder;
     794: aload         6
     796: getfield      #13                 // Field org/sklsft/generator/model/domain/business/Property.getterName:Ljava/lang/String;
     799: invokevirtual #14                 // Method java/lang/StringBuilder.append:(Ljava/lang/String;)Ljava/lang/StringBuilder;
     802: ldc           #15                 // String ()
     804: invokevirtual #14                 // Method java/lang/StringBuilder.append:(Ljava/lang/String;)Ljava/lang/StringBuilder;
     807: invokevirtual #16                 // Method java/lang/StringBuilder.toString:()Ljava/lang/String;
     810: putfield      #17                 // Field org/sklsft/generator/model/domain/ui/ViewProperty.mappingPath:Ljava/lang/String;
     813: aload         7
     815: aload         6
     817: getfield      #18                 // Field org/sklsft/generator/model/domain/business/Property.javaType:Ljava/lang/String;
     820: putfield      #19                 // Field org/sklsft/generator/model/domain/ui/ViewProperty.javaType:Ljava/lang/String;
     823: aload         7
     825: aload         6
     827: getfield      #20                 // Field org/sklsft/generator/model/domain/business/Property.tsType:Ljava/lang/String;
     830: putfield      #21                 // Field org/sklsft/generator/model/domain/ui/ViewProperty.tsType:Ljava/lang/String;
     833: aload         7
     835: aload         6
     837: getfield      #22                 // Field org/sklsft/generator/model/domain/business/Property.dataType:Lorg/sklsft/generator/model/metadata/DataType;
     840: putfield      #23                 // Field org/sklsft/generator/model/domain/ui/ViewProperty.dataType:Lorg/sklsft/generator/model/metadata/DataType;
     843: aload         7
     845: aload_1
     846: getfield      #24                 // Field org/sklsft/generator/model/domain/business/Property.nullable:Z
     849: ifne          860
     852: aload         6
     854: getfield      #24                 // Field org/sklsft/generator/model/domain/business/Property.nullable:Z
     857: ifeq          864
     860: iconst_1
     861: goto          865
     864: iconst_0
     865: putfield      #25                 // Field org/sklsft/generator/model/domain/ui/ViewProperty.nullable:Z
     868: aload         7
     870: aload_1
     871: getfield      #26                 // Field org/sklsft/generator/model/domain/business/Property.visibility:Lorg/sklsft/generator/model/metadata/Visibility;
     874: aload         6
     876: getfield      #26                 // Field org/sklsft/generator/model/domain/business/Property.visibility:Lorg/sklsft/generator/model/metadata/Visibility;
     879: invokestatic  #53                 // Method org/sklsft/generator/model/metadata/Visibility.min:(Lorg/sklsft/generator/model/metadata/Visibility;Lorg/sklsft/generator/model/metadata/Visibility;)Lorg/sklsft/generator/model/metadata/Visibility;
     882: putfield      #27                 // Field org/sklsft/generator/model/domain/ui/ViewProperty.visibility:Lorg/sklsft/generator/model/metadata/Visibility;
     885: aload         7
     887: aload_1
     888: getfield      #42                 // Field org/sklsft/generator/model/domain/business/Property.embedded:Z
     891: ifeq          902
     894: aload         6
     896: getfield      #28                 // Field org/sklsft/generator/model/domain/business/Property.editable:Z
     899: goto          906
     902: aload_1
     903: getfield      #28                 // Field org/sklsft/generator/model/domain/business/Property.editable:Z
     906: putfield      #29                 // Field org/sklsft/generator/model/domain/ui/ViewProperty.editable:Z
     909: aload         7
     911: aload_1
     912: getfield      #42                 // Field org/sklsft/generator/model/domain/business/Property.embedded:Z
     915: ifeq          926
     918: aload         6
     920: getfield      #30                 // Field org/sklsft/generator/model/domain/business/Property.filterable:Z
     923: goto          930
     926: aload_1
     927: getfield      #30                 // Field org/sklsft/generator/model/domain/business/Property.filterable:Z
     930: putfield      #31                 // Field org/sklsft/generator/model/domain/ui/ViewProperty.filterable:Z
     933: aload         7
     935: aload_1
     936: getfield      #42                 // Field org/sklsft/generator/model/domain/business/Property.embedded:Z
     939: ifeq          950
     942: aload         6
     944: getfield      #32                 // Field org/sklsft/generator/model/domain/business/Property.textFilterType:Lorg/sklsft/generator/model/metadata/TextFilterType;
     947: goto          954
     950: aload_1
     951: getfield      #32                 // Field org/sklsft/generator/model/domain/business/Property.textFilterType:Lorg/sklsft/generator/model/metadata/TextFilterType;
     954: putfield      #33                 // Field org/sklsft/generator/model/domain/ui/ViewProperty.textFilterType:Lorg/sklsft/generator/model/metadata/TextFilterType;
     957: aload         7
     959: aload         6
     961: getfield      #7                  // Field org/sklsft/generator/model/domain/business/Property.name:Ljava/lang/String;
     964: putfield      #34                 // Field org/sklsft/generator/model/domain/ui/ViewProperty.lastPropertyName:Ljava/lang/String;
     967: aload         7
     969: aload_1
     970: getfield      #18                 // Field org/sklsft/generator/model/domain/business/Property.javaType:Ljava/lang/String;
     973: putfield      #36                 // Field org/sklsft/generator/model/domain/ui/ViewProperty.lastParentBeanClassName:Ljava/lang/String;
     976: aload         7
     978: aload_1
     979: getfield      #7                  // Field org/sklsft/generator/model/domain/business/Property.name:Ljava/lang/String;
     982: putfield      #38                 // Field org/sklsft/generator/model/domain/ui/ViewProperty.joinedAliasName:Ljava/lang/String;
     985: aload         7
     987: aload_1
     988: getfield      #4                  // Field org/sklsft/generator/model/domain/business/Property.referenceBean:Lorg/sklsft/generator/model/domain/business/Bean;
     991: putfield      #55                 // Field org/sklsft/generator/model/domain/ui/ViewProperty.referenceBean:Lorg/sklsft/generator/model/domain/business/Bean;
     994: aload_1
     995: getfield      #4                  // Field org/sklsft/generator/model/domain/business/Property.referenceBean:Lorg/sklsft/generator/model/domain/business/Bean;
     998: getfield      #57                 // Field org/sklsft/generator/model/domain/business/Bean.selectable:Z
    1001: ifeq          1013
    1004: aload         7
    1006: aload_1
    1007: getfield      #4                  // Field org/sklsft/generator/model/domain/business/Property.referenceBean:Lorg/sklsft/generator/model/domain/business/Bean;
    1010: putfield      #56                 // Field org/sklsft/generator/model/domain/ui/ViewProperty.selectableBean:Lorg/sklsft/generator/model/domain/business/Bean;
    1013: aload_1
    1014: getfield      #4                  // Field org/sklsft/generator/model/domain/business/Property.referenceBean:Lorg/sklsft/generator/model/domain/business/Bean;
    1017: getfield      #45                 // Field org/sklsft/generator/model/domain/business/Bean.cardinality:I
    1020: iconst_1
    1021: if_icmpne     1036
    1024: aload         7
    1026: aload_1
    1027: getfield      #39                 // Field org/sklsft/generator/model/domain/business/Property.rendering:Ljava/lang/String;
    1030: putfield      #40                 // Field org/sklsft/generator/model/domain/ui/ViewProperty.rendering:Ljava/lang/String;
    1033: goto          1096
    1036: aload_1
    1037: getfield      #42                 // Field org/sklsft/generator/model/domain/business/Property.embedded:Z
    1040: ifeq          1056
    1043: aload         7
    1045: aload         6
    1047: getfield      #39                 // Field org/sklsft/generator/model/domain/business/Property.rendering:Ljava/lang/String;
    1050: putfield      #40                 // Field org/sklsft/generator/model/domain/ui/ViewProperty.rendering:Ljava/lang/String;
    1053: goto          1096
    1056: aload         7
    1058: new           #11                 // class java/lang/StringBuilder
    1061: dup
    1062: invokespecial #12                 // Method java/lang/StringBuilder."<init>":()V
    1065: aload_1
    1066: getfield      #39                 // Field org/sklsft/generator/model/domain/business/Property.rendering:Ljava/lang/String;
    1069: invokevirtual #14                 // Method java/lang/StringBuilder.append:(Ljava/lang/String;)Ljava/lang/StringBuilder;
    1072: ldc           #58                 // String (
    1074: invokevirtual #14                 // Method java/lang/StringBuilder.append:(Ljava/lang/String;)Ljava/lang/StringBuilder;
    1077: aload         6
    1079: getfield      #39                 // Field org/sklsft/generator/model/domain/business/Property.rendering:Ljava/lang/String;
    1082: invokevirtual #14                 // Method java/lang/StringBuilder.append:(Ljava/lang/String;)Ljava/lang/StringBuilder;
    1085: ldc           #59                 // String )
    1087: invokevirtual #14                 // Method java/lang/StringBuilder.append:(Ljava/lang/String;)Ljava/lang/StringBuilder;
    1090: invokevirtual #16                 // Method java/lang/StringBuilder.toString:()Ljava/lang/String;
    1093: putfield      #40                 // Field org/sklsft/generator/model/domain/ui/ViewProperty.rendering:Ljava/lang/String;
    1096: aload_3
    1097: aload         7
    1099: invokeinterface #41,  2           // InterfaceMethod java/util/List.add:(Ljava/lang/Object;)Z
    1104: pop
    1105: iinc          5, 1
    1108: goto          221
    1111: aload_3
    1112: areturn

  public java.util.List<org.sklsft.generator.model.domain.ui.ViewProperty> getReferenceProperties(org.sklsft.generator.model.domain.business.Bean);
    Code:
       0: new           #2                  // class java/util/ArrayList
       3: dup
       4: invokespecial #3                  // Method java/util/ArrayList."<init>":()V
       7: astore_2
       8: iconst_0
       9: istore_3
      10: iload_3
      11: aload_1
      12: getfield      #45                 // Field org/sklsft/generator/model/domain/business/Bean.cardinality:I
      15: if_icmpge     53
      18: aload_1
      19: getfield      #43                 // Field org/sklsft/generator/model/domain/business/Bean.properties:Ljava/util/List;
      22: iload_3
      23: invokeinterface #46,  2           // InterfaceMethod java/util/List.get:(I)Ljava/lang/Object;
      28: checkcast     #47                 // class org/sklsft/generator/model/domain/business/Property
      31: astore        4
      33: aload_2
      34: aload_0
      35: aload         4
      37: aload_1
      38: invokespecial #48                 // Method getViewProperties:(Lorg/sklsft/generator/model/domain/business/Property;Lorg/sklsft/generator/model/domain/business/Bean;)Ljava/util/List;
      41: invokeinterface #60,  2           // InterfaceMethod java/util/List.addAll:(Ljava/util/Collection;)Z
      46: pop
      47: iinc          3, 1
      50: goto          10
      53: aload_2
      54: areturn

  private java.util.List<org.sklsft.generator.model.domain.ui.ViewProperty> getViewProperties(org.sklsft.generator.model.domain.business.Bean);
    Code:
       0: aload_0
       1: aload_1
       2: aconst_null
       3: invokespecial #61                 // Method getViewPropertiesExcludingField:(Lorg/sklsft/generator/model/domain/business/Bean;Ljava/lang/String;)Ljava/util/List;
       6: areturn

  private java.util.List<org.sklsft.generator.model.domain.ui.ViewProperty> getViewPropertiesExcludingField(org.sklsft.generator.model.domain.business.Bean, java.lang.String);
    Code:
       0: new           #2                  // class java/util/ArrayList
       3: dup
       4: invokespecial #3                  // Method java/util/ArrayList."<init>":()V
       7: astore_3
       8: aload_1
       9: getfield      #43                 // Field org/sklsft/generator/model/domain/business/Bean.properties:Ljava/util/List;
      12: invokeinterface #49,  1           // InterfaceMethod java/util/List.iterator:()Ljava/util/Iterator;
      17: astore        4
      19: aload         4
      21: invokeinterface #50,  1           // InterfaceMethod java/util/Iterator.hasNext:()Z
      26: ifeq          81
      29: aload         4
      31: invokeinterface #51,  1           // InterfaceMethod java/util/Iterator.next:()Ljava/lang/Object;
      36: checkcast     #47                 // class org/sklsft/generator/model/domain/business/Property
      39: astore        5
      41: aload         5
      43: getfield      #62                 // Field org/sklsft/generator/model/domain/business/Property.relation:Lorg/sklsft/generator/model/metadata/RelationType;
      46: invokevirtual #63                 // Method org/sklsft/generator/model/metadata/RelationType.isComponentLink:()Z
      49: ifne          78
      52: aload         5
      54: getfield      #7                  // Field org/sklsft/generator/model/domain/business/Property.name:Ljava/lang/String;
      57: aload_2
      58: invokevirtual #64                 // Method java/lang/String.equals:(Ljava/lang/Object;)Z
      61: ifne          78
      64: aload_3
      65: aload_0
      66: aload         5
      68: aload_1
      69: invokespecial #48                 // Method getViewProperties:(Lorg/sklsft/generator/model/domain/business/Property;Lorg/sklsft/generator/model/domain/business/Bean;)Ljava/util/List;
      72: invokeinterface #60,  2           // InterfaceMethod java/util/List.addAll:(Ljava/util/Collection;)Z
      77: pop
      78: goto          19
      81: aload_3
      82: areturn

  public java.util.List<org.sklsft.generator.model.domain.ui.ViewProperty> getBasicViewProperties(org.sklsft.generator.model.domain.business.Bean);
    Code:
       0: new           #2                  // class java/util/ArrayList
       3: dup
       4: invokespecial #3                  // Method java/util/ArrayList."<init>":()V
       7: astore_2
       8: aload_0
       9: aload_1
      10: invokespecial #65                 // Method getViewProperties:(Lorg/sklsft/generator/model/domain/business/Bean;)Ljava/util/List;
      13: invokeinterface #49,  1           // InterfaceMethod java/util/List.iterator:()Ljava/util/Iterator;
      18: astore_3
      19: aload_3
      20: invokeinterface #50,  1           // InterfaceMethod java/util/Iterator.hasNext:()Z
      25: ifeq          62
      28: aload_3
      29: invokeinterface #51,  1           // InterfaceMethod java/util/Iterator.next:()Ljava/lang/Object;
      34: checkcast     #5                  // class org/sklsft/generator/model/domain/ui/ViewProperty
      37: astore        4
      39: aload         4
      41: getfield      #27                 // Field org/sklsft/generator/model/domain/ui/ViewProperty.visibility:Lorg/sklsft/generator/model/metadata/Visibility;
      44: invokevirtual #66                 // Method org/sklsft/generator/model/metadata/Visibility.isListVisible:()Z
      47: ifeq          59
      50: aload_2
      51: aload         4
      53: invokeinterface #41,  2           // InterfaceMethod java/util/List.add:(Ljava/lang/Object;)Z
      58: pop
      59: goto          19
      62: aload_2
      63: areturn

  public java.util.List<org.sklsft.generator.model.domain.ui.ViewProperty> getFormProperties(org.sklsft.generator.model.domain.business.Bean);
    Code:
       0: new           #2                  // class java/util/ArrayList
       3: dup
       4: invokespecial #3                  // Method java/util/ArrayList."<init>":()V
       7: astore_2
       8: aload_0
       9: aload_1
      10: invokespecial #65                 // Method getViewProperties:(Lorg/sklsft/generator/model/domain/business/Bean;)Ljava/util/List;
      13: invokeinterface #49,  1           // InterfaceMethod java/util/List.iterator:()Ljava/util/Iterator;
      18: astore_3
      19: aload_3
      20: invokeinterface #50,  1           // InterfaceMethod java/util/Iterator.hasNext:()Z
      25: ifeq          62
      28: aload_3
      29: invokeinterface #51,  1           // InterfaceMethod java/util/Iterator.next:()Ljava/lang/Object;
      34: checkcast     #5                  // class org/sklsft/generator/model/domain/ui/ViewProperty
      37: astore        4
      39: aload         4
      41: getfield      #27                 // Field org/sklsft/generator/model/domain/ui/ViewProperty.visibility:Lorg/sklsft/generator/model/metadata/Visibility;
      44: invokevirtual #67                 // Method org/sklsft/generator/model/metadata/Visibility.isDetailVisible:()Z
      47: ifeq          59
      50: aload_2
      51: aload         4
      53: invokeinterface #41,  2           // InterfaceMethod java/util/List.add:(Ljava/lang/Object;)Z
      58: pop
      59: goto          19
      62: aload_2
      63: areturn

  private java.util.List<org.sklsft.generator.model.domain.ui.ViewProperty> getVisibleProperties(org.sklsft.generator.model.domain.business.OneToMany);
    Code:
       0: aload_0
       1: aload_1
       2: getfield      #68                 // Field org/sklsft/generator/model/domain/business/OneToMany.referenceBean:Lorg/sklsft/generator/model/domain/business/Bean;
       5: aload_1
       6: getfield      #69                 // Field org/sklsft/generator/model/domain/business/OneToMany.referenceProperty:Lorg/sklsft/generator/model/domain/business/Property;
       9: getfield      #7                  // Field org/sklsft/generator/model/domain/business/Property.name:Ljava/lang/String;
      12: invokespecial #61                 // Method getViewPropertiesExcludingField:(Lorg/sklsft/generator/model/domain/business/Bean;Ljava/lang/String;)Ljava/util/List;
      15: areturn

  public java.util.List<org.sklsft.generator.model.domain.ui.ViewProperty> getBasicViewProperties(org.sklsft.generator.model.domain.business.OneToMany);
    Code:
       0: new           #2                  // class java/util/ArrayList
       3: dup
       4: invokespecial #3                  // Method java/util/ArrayList."<init>":()V
       7: astore_2
       8: aload_0
       9: aload_1
      10: invokespecial #70                 // Method getVisibleProperties:(Lorg/sklsft/generator/model/domain/business/OneToMany;)Ljava/util/List;
      13: invokeinterface #49,  1           // InterfaceMethod java/util/List.iterator:()Ljava/util/Iterator;
      18: astore_3
      19: aload_3
      20: invokeinterface #50,  1           // InterfaceMethod java/util/Iterator.hasNext:()Z
      25: ifeq          62
      28: aload_3
      29: invokeinterface #51,  1           // InterfaceMethod java/util/Iterator.next:()Ljava/lang/Object;
      34: checkcast     #5                  // class org/sklsft/generator/model/domain/ui/ViewProperty
      37: astore        4
      39: aload         4
      41: getfield      #27                 // Field org/sklsft/generator/model/domain/ui/ViewProperty.visibility:Lorg/sklsft/generator/model/metadata/Visibility;
      44: invokevirtual #66                 // Method org/sklsft/generator/model/metadata/Visibility.isListVisible:()Z
      47: ifeq          59
      50: aload_2
      51: aload         4
      53: invokeinterface #41,  2           // InterfaceMethod java/util/List.add:(Ljava/lang/Object;)Z
      58: pop
      59: goto          19
      62: aload_2
      63: areturn

  public java.util.List<org.sklsft.generator.model.domain.ui.ViewProperty> getFormProperties(org.sklsft.generator.model.domain.business.OneToMany);
    Code:
       0: new           #2                  // class java/util/ArrayList
       3: dup
       4: invokespecial #3                  // Method java/util/ArrayList."<init>":()V
       7: astore_2
       8: aload_0
       9: aload_1
      10: invokespecial #70                 // Method getVisibleProperties:(Lorg/sklsft/generator/model/domain/business/OneToMany;)Ljava/util/List;
      13: invokeinterface #49,  1           // InterfaceMethod java/util/List.iterator:()Ljava/util/Iterator;
      18: astore_3
      19: aload_3
      20: invokeinterface #50,  1           // InterfaceMethod java/util/Iterator.hasNext:()Z
      25: ifeq          62
      28: aload_3
      29: invokeinterface #51,  1           // InterfaceMethod java/util/Iterator.next:()Ljava/lang/Object;
      34: checkcast     #5                  // class org/sklsft/generator/model/domain/ui/ViewProperty
      37: astore        4
      39: aload         4
      41: getfield      #27                 // Field org/sklsft/generator/model/domain/ui/ViewProperty.visibility:Lorg/sklsft/generator/model/metadata/Visibility;
      44: invokevirtual #67                 // Method org/sklsft/generator/model/metadata/Visibility.isDetailVisible:()Z
      47: ifeq          59
      50: aload_2
      51: aload         4
      53: invokeinterface #41,  2           // InterfaceMethod java/util/List.add:(Ljava/lang/Object;)Z
      58: pop
      59: goto          19
      62: aload_2
      63: areturn
}
