Compiled from "TransactionAttributeMergingProcessor.java"
public class org.jboss.as.ejb3.deployment.processors.merging.TransactionAttributeMergingProcessor extends org.jboss.as.ejb3.deployment.processors.merging.AbstractMergingProcessor<org.jboss.as.ejb3.component.EJBComponentDescription> {
  public org.jboss.as.ejb3.deployment.processors.merging.TransactionAttributeMergingProcessor();
    Code:
       0: aload_0
       1: ldc           #1                  // class org/jboss/as/ejb3/component/EJBComponentDescription
       3: invokespecial #2                  // Method org/jboss/as/ejb3/deployment/processors/merging/AbstractMergingProcessor."<init>":(Ljava/lang/Class;)V
       6: return

  protected void handleAnnotations(org.jboss.as.server.deployment.DeploymentUnit, org.jboss.as.ee.component.EEApplicationClasses, org.jboss.as.server.deployment.reflect.DeploymentReflectionIndex, java.lang.Class<?>, org.jboss.as.ejb3.component.EJBComponentDescription) throws org.jboss.as.server.deployment.DeploymentUnitProcessingException;
    Code:
       0: aload_1
       1: getstatic     #3                  // Field org/jboss/as/server/deployment/Attachments.MODULE:Lorg/jboss/as/server/deployment/AttachmentKey;
       4: invokeinterface #4,  2            // InterfaceMethod org/jboss/as/server/deployment/DeploymentUnit.getAttachment:(Lorg/jboss/as/server/deployment/AttachmentKey;)Ljava/lang/Object;
       9: checkcast     #5                  // class org/jboss/modules/Module
      12: astore        6
      14: aload_0
      15: aload_2
      16: aload_3
      17: aload         4
      19: aconst_null
      20: aload         5
      22: invokespecial #6                  // Method processTransactionAttributeAnnotation:(Lorg/jboss/as/ee/component/EEApplicationClasses;Lorg/jboss/as/server/deployment/reflect/DeploymentReflectionIndex;Ljava/lang/Class;Lorg/jboss/as/ejb3/component/MethodIntf;Lorg/jboss/as/ejb3/component/EJBComponentDescription;)V
      25: aload_0
      26: aload_2
      27: aload_3
      28: aload         4
      30: aconst_null
      31: aload         5
      33: invokespecial #7                  // Method processTransactionTimeoutAnnotation:(Lorg/jboss/as/ee/component/EEApplicationClasses;Lorg/jboss/as/server/deployment/reflect/DeploymentReflectionIndex;Ljava/lang/Class;Lorg/jboss/as/ejb3/component/MethodIntf;Lorg/jboss/as/ejb3/component/EJBComponentDescription;)V
      36: aload         5
      38: invokevirtual #8                  // Method org/jboss/as/ejb3/component/EJBComponentDescription.getViews:()Ljava/util/Set;
      41: invokeinterface #9,  1            // InterfaceMethod java/util/Set.iterator:()Ljava/util/Iterator;
      46: astore        7
      48: aload         7
      50: invokeinterface #10,  1           // InterfaceMethod java/util/Iterator.hasNext:()Z
      55: ifeq          141
      58: aload         7
      60: invokeinterface #11,  1           // InterfaceMethod java/util/Iterator.next:()Ljava/lang/Object;
      65: checkcast     #12                 // class org/jboss/as/ee/component/ViewDescription
      68: astore        8
      70: aload         6
      72: invokevirtual #13                 // Method org/jboss/modules/Module.getClassLoader:()Lorg/jboss/modules/ModuleClassLoader;
      75: aload         8
      77: invokevirtual #14                 // Method org/jboss/as/ee/component/ViewDescription.getViewClassName:()Ljava/lang/String;
      80: invokevirtual #15                 // Method org/jboss/modules/ModuleClassLoader.loadClass:(Ljava/lang/String;)Ljava/lang/Class;
      83: astore        9
      85: aload         8
      87: checkcast     #16                 // class org/jboss/as/ejb3/component/EJBViewDescription
      90: astore        10
      92: aload_0
      93: aload_2
      94: aload_3
      95: aload         9
      97: aload         10
      99: invokevirtual #17                 // Method org/jboss/as/ejb3/component/EJBViewDescription.getMethodIntf:()Lorg/jboss/as/ejb3/component/MethodIntf;
     102: aload         5
     104: invokespecial #6                  // Method processTransactionAttributeAnnotation:(Lorg/jboss/as/ee/component/EEApplicationClasses;Lorg/jboss/as/server/deployment/reflect/DeploymentReflectionIndex;Ljava/lang/Class;Lorg/jboss/as/ejb3/component/MethodIntf;Lorg/jboss/as/ejb3/component/EJBComponentDescription;)V
     107: aload_0
     108: aload_2
     109: aload_3
     110: aload         9
     112: aload         10
     114: invokevirtual #17                 // Method org/jboss/as/ejb3/component/EJBViewDescription.getMethodIntf:()Lorg/jboss/as/ejb3/component/MethodIntf;
     117: aload         5
     119: invokespecial #7                  // Method processTransactionTimeoutAnnotation:(Lorg/jboss/as/ee/component/EEApplicationClasses;Lorg/jboss/as/server/deployment/reflect/DeploymentReflectionIndex;Ljava/lang/Class;Lorg/jboss/as/ejb3/component/MethodIntf;Lorg/jboss/as/ejb3/component/EJBComponentDescription;)V
     122: goto          138
     125: astore        9
     127: getstatic     #19                 // Field org/jboss/as/ejb3/logging/EjbLogger.ROOT_LOGGER:Lorg/jboss/as/ejb3/logging/EjbLogger;
     130: aload         9
     132: invokeinterface #20,  2           // InterfaceMethod org/jboss/as/ejb3/logging/EjbLogger.failToLoadEjbViewClass:(Ljava/lang/Throwable;)Ljava/lang/RuntimeException;
     137: athrow
     138: goto          48
     141: return
    Exception table:
       from    to  target type
          70   122   125   Class java/lang/ClassNotFoundException

  private void processTransactionAttributeAnnotation(org.jboss.as.ee.component.EEApplicationClasses, org.jboss.as.server.deployment.reflect.DeploymentReflectionIndex, java.lang.Class<?>, org.jboss.as.ejb3.component.MethodIntf, org.jboss.as.ejb3.component.EJBComponentDescription);
    Code:
       0: aload_3
       1: aload_1
       2: aload_2
       3: ldc           #21                 // class javax/ejb/TransactionAttribute
       5: invokestatic  #22                 // Method org/jboss/as/ee/metadata/MethodAnnotationAggregator.runtimeAnnotationInformation:(Ljava/lang/Class;Lorg/jboss/as/ee/component/EEApplicationClasses;Lorg/jboss/as/server/deployment/reflect/DeploymentReflectionIndex;Ljava/lang/Class;)Lorg/jboss/as/ee/metadata/RuntimeAnnotationInformation;
       8: astore        6
      10: aload         6
      12: invokevirtual #23                 // Method org/jboss/as/ee/metadata/RuntimeAnnotationInformation.getClassAnnotations:()Ljava/util/Map;
      15: invokeinterface #24,  1           // InterfaceMethod java/util/Map.entrySet:()Ljava/util/Set;
      20: invokeinterface #9,  1            // InterfaceMethod java/util/Set.iterator:()Ljava/util/Iterator;
      25: astore        7
      27: aload         7
      29: invokeinterface #10,  1           // InterfaceMethod java/util/Iterator.hasNext:()Z
      34: ifeq          119
      37: aload         7
      39: invokeinterface #11,  1           // InterfaceMethod java/util/Iterator.next:()Ljava/lang/Object;
      44: checkcast     #25                 // class java/util/Map$Entry
      47: astore        8
      49: aload         8
      51: invokeinterface #26,  1           // InterfaceMethod java/util/Map$Entry.getValue:()Ljava/lang/Object;
      56: checkcast     #27                 // class java/util/List
      59: invokeinterface #28,  1           // InterfaceMethod java/util/List.isEmpty:()Z
      64: ifne          116
      67: aload         4
      69: ifnonnull     85
      72: aload         8
      74: invokeinterface #29,  1           // InterfaceMethod java/util/Map$Entry.getKey:()Ljava/lang/Object;
      79: checkcast     #30                 // class java/lang/String
      82: goto          86
      85: aconst_null
      86: astore        9
      88: aload         5
      90: invokevirtual #31                 // Method org/jboss/as/ejb3/component/EJBComponentDescription.getTransactionAttributes:()Lorg/jboss/as/ejb3/deployment/ApplicableMethodInformation;
      93: aload         4
      95: aload         9
      97: aload         8
      99: invokeinterface #26,  1           // InterfaceMethod java/util/Map$Entry.getValue:()Ljava/lang/Object;
     104: checkcast     #27                 // class java/util/List
     107: iconst_0
     108: invokeinterface #32,  2           // InterfaceMethod java/util/List.get:(I)Ljava/lang/Object;
     113: invokevirtual #33                 // Method org/jboss/as/ejb3/deployment/ApplicableMethodInformation.setAttribute:(Lorg/jboss/as/ejb3/component/MethodIntf;Ljava/lang/String;Ljava/lang/Object;)V
     116: goto          27
     119: aload         6
     121: invokevirtual #34                 // Method org/jboss/as/ee/metadata/RuntimeAnnotationInformation.getMethodAnnotations:()Ljava/util/Map;
     124: invokeinterface #24,  1           // InterfaceMethod java/util/Map.entrySet:()Ljava/util/Set;
     129: invokeinterface #9,  1            // InterfaceMethod java/util/Set.iterator:()Ljava/util/Iterator;
     134: astore        7
     136: aload         7
     138: invokeinterface #10,  1           // InterfaceMethod java/util/Iterator.hasNext:()Z
     143: ifeq          251
     146: aload         7
     148: invokeinterface #11,  1           // InterfaceMethod java/util/Iterator.next:()Ljava/lang/Object;
     153: checkcast     #25                 // class java/util/Map$Entry
     156: astore        8
     158: aload         8
     160: invokeinterface #26,  1           // InterfaceMethod java/util/Map$Entry.getValue:()Ljava/lang/Object;
     165: checkcast     #27                 // class java/util/List
     168: invokeinterface #28,  1           // InterfaceMethod java/util/List.isEmpty:()Z
     173: ifne          248
     176: aload         8
     178: invokeinterface #29,  1           // InterfaceMethod java/util/Map$Entry.getKey:()Ljava/lang/Object;
     183: checkcast     #35                 // class java/lang/reflect/Method
     186: invokestatic  #36                 // Method org/jboss/as/ejb3/util/MethodInfoHelper.getCanonicalParameterTypes:(Ljava/lang/reflect/Method;)[Ljava/lang/String;
     189: astore        9
     191: aload         5
     193: invokevirtual #31                 // Method org/jboss/as/ejb3/component/EJBComponentDescription.getTransactionAttributes:()Lorg/jboss/as/ejb3/deployment/ApplicableMethodInformation;
     196: aload         4
     198: aload         8
     200: invokeinterface #26,  1           // InterfaceMethod java/util/Map$Entry.getValue:()Ljava/lang/Object;
     205: checkcast     #27                 // class java/util/List
     208: iconst_0
     209: invokeinterface #32,  2           // InterfaceMethod java/util/List.get:(I)Ljava/lang/Object;
     214: aload         8
     216: invokeinterface #29,  1           // InterfaceMethod java/util/Map$Entry.getKey:()Ljava/lang/Object;
     221: checkcast     #35                 // class java/lang/reflect/Method
     224: invokevirtual #37                 // Method java/lang/reflect/Method.getDeclaringClass:()Ljava/lang/Class;
     227: invokevirtual #38                 // Method java/lang/Class.getName:()Ljava/lang/String;
     230: aload         8
     232: invokeinterface #29,  1           // InterfaceMethod java/util/Map$Entry.getKey:()Ljava/lang/Object;
     237: checkcast     #35                 // class java/lang/reflect/Method
     240: invokevirtual #39                 // Method java/lang/reflect/Method.getName:()Ljava/lang/String;
     243: aload         9
     245: invokevirtual #40                 // Method org/jboss/as/ejb3/deployment/ApplicableMethodInformation.setAttribute:(Lorg/jboss/as/ejb3/component/MethodIntf;Ljava/lang/Object;Ljava/lang/String;Ljava/lang/String;[Ljava/lang/String;)V
     248: goto          136
     251: return

  private void processTransactionTimeoutAnnotation(org.jboss.as.ee.component.EEApplicationClasses, org.jboss.as.server.deployment.reflect.DeploymentReflectionIndex, java.lang.Class<?>, org.jboss.as.ejb3.component.MethodIntf, org.jboss.as.ejb3.component.EJBComponentDescription);
    Code:
       0: aload_3
       1: aload_1
       2: aload_2
       3: ldc           #41                 // class org/jboss/ejb3/annotation/TransactionTimeout
       5: invokestatic  #22                 // Method org/jboss/as/ee/metadata/MethodAnnotationAggregator.runtimeAnnotationInformation:(Ljava/lang/Class;Lorg/jboss/as/ee/component/EEApplicationClasses;Lorg/jboss/as/server/deployment/reflect/DeploymentReflectionIndex;Ljava/lang/Class;)Lorg/jboss/as/ee/metadata/RuntimeAnnotationInformation;
       8: astore        6
      10: aload         6
      12: invokevirtual #23                 // Method org/jboss/as/ee/metadata/RuntimeAnnotationInformation.getClassAnnotations:()Ljava/util/Map;
      15: invokeinterface #24,  1           // InterfaceMethod java/util/Map.entrySet:()Ljava/util/Set;
      20: invokeinterface #9,  1            // InterfaceMethod java/util/Set.iterator:()Ljava/util/Iterator;
      25: astore        7
      27: aload         7
      29: invokeinterface #10,  1           // InterfaceMethod java/util/Iterator.hasNext:()Z
      34: ifeq          119
      37: aload         7
      39: invokeinterface #11,  1           // InterfaceMethod java/util/Iterator.next:()Ljava/lang/Object;
      44: checkcast     #25                 // class java/util/Map$Entry
      47: astore        8
      49: aload         8
      51: invokeinterface #26,  1           // InterfaceMethod java/util/Map$Entry.getValue:()Ljava/lang/Object;
      56: checkcast     #27                 // class java/util/List
      59: invokeinterface #28,  1           // InterfaceMethod java/util/List.isEmpty:()Z
      64: ifne          116
      67: aload         4
      69: ifnonnull     85
      72: aload         8
      74: invokeinterface #29,  1           // InterfaceMethod java/util/Map$Entry.getKey:()Ljava/lang/Object;
      79: checkcast     #30                 // class java/lang/String
      82: goto          86
      85: aconst_null
      86: astore        9
      88: aload         5
      90: invokevirtual #42                 // Method org/jboss/as/ejb3/component/EJBComponentDescription.getTransactionTimeouts:()Lorg/jboss/as/ejb3/deployment/ApplicableMethodInformation;
      93: aload         4
      95: aload         9
      97: aload         8
      99: invokeinterface #26,  1           // InterfaceMethod java/util/Map$Entry.getValue:()Ljava/lang/Object;
     104: checkcast     #27                 // class java/util/List
     107: iconst_0
     108: invokeinterface #32,  2           // InterfaceMethod java/util/List.get:(I)Ljava/lang/Object;
     113: invokevirtual #33                 // Method org/jboss/as/ejb3/deployment/ApplicableMethodInformation.setAttribute:(Lorg/jboss/as/ejb3/component/MethodIntf;Ljava/lang/String;Ljava/lang/Object;)V
     116: goto          27
     119: aload         6
     121: invokevirtual #34                 // Method org/jboss/as/ee/metadata/RuntimeAnnotationInformation.getMethodAnnotations:()Ljava/util/Map;
     124: invokeinterface #24,  1           // InterfaceMethod java/util/Map.entrySet:()Ljava/util/Set;
     129: invokeinterface #9,  1            // InterfaceMethod java/util/Set.iterator:()Ljava/util/Iterator;
     134: astore        7
     136: aload         7
     138: invokeinterface #10,  1           // InterfaceMethod java/util/Iterator.hasNext:()Z
     143: ifeq          255
     146: aload         7
     148: invokeinterface #11,  1           // InterfaceMethod java/util/Iterator.next:()Ljava/lang/Object;
     153: checkcast     #25                 // class java/util/Map$Entry
     156: astore        8
     158: aload         8
     160: invokeinterface #26,  1           // InterfaceMethod java/util/Map$Entry.getValue:()Ljava/lang/Object;
     165: checkcast     #27                 // class java/util/List
     168: invokeinterface #28,  1           // InterfaceMethod java/util/List.isEmpty:()Z
     173: ifne          252
     176: aload         8
     178: invokeinterface #29,  1           // InterfaceMethod java/util/Map$Entry.getKey:()Ljava/lang/Object;
     183: checkcast     #35                 // class java/lang/reflect/Method
     186: invokevirtual #37                 // Method java/lang/reflect/Method.getDeclaringClass:()Ljava/lang/Class;
     189: invokevirtual #38                 // Method java/lang/Class.getName:()Ljava/lang/String;
     192: astore        9
     194: aload         8
     196: invokeinterface #29,  1           // InterfaceMethod java/util/Map$Entry.getKey:()Ljava/lang/Object;
     201: checkcast     #35                 // class java/lang/reflect/Method
     204: invokestatic  #36                 // Method org/jboss/as/ejb3/util/MethodInfoHelper.getCanonicalParameterTypes:(Ljava/lang/reflect/Method;)[Ljava/lang/String;
     207: astore        10
     209: aload         5
     211: invokevirtual #42                 // Method org/jboss/as/ejb3/component/EJBComponentDescription.getTransactionTimeouts:()Lorg/jboss/as/ejb3/deployment/ApplicableMethodInformation;
     214: aload         4
     216: aload         8
     218: invokeinterface #26,  1           // InterfaceMethod java/util/Map$Entry.getValue:()Ljava/lang/Object;
     223: checkcast     #27                 // class java/util/List
     226: iconst_0
     227: invokeinterface #32,  2           // InterfaceMethod java/util/List.get:(I)Ljava/lang/Object;
     232: aload         9
     234: aload         8
     236: invokeinterface #29,  1           // InterfaceMethod java/util/Map$Entry.getKey:()Ljava/lang/Object;
     241: checkcast     #35                 // class java/lang/reflect/Method
     244: invokevirtual #39                 // Method java/lang/reflect/Method.getName:()Ljava/lang/String;
     247: aload         10
     249: invokevirtual #40                 // Method org/jboss/as/ejb3/deployment/ApplicableMethodInformation.setAttribute:(Lorg/jboss/as/ejb3/component/MethodIntf;Ljava/lang/Object;Ljava/lang/String;Ljava/lang/String;[Ljava/lang/String;)V
     252: goto          136
     255: return

  protected void handleDeploymentDescriptor(org.jboss.as.server.deployment.DeploymentUnit, org.jboss.as.server.deployment.reflect.DeploymentReflectionIndex, java.lang.Class<?>, org.jboss.as.ejb3.component.EJBComponentDescription) throws org.jboss.as.server.deployment.DeploymentUnitProcessingException;
    Code:
       0: aload_1
       1: getstatic     #43                 // Field org/jboss/as/ejb3/deployment/EjbDeploymentAttachmentKeys.EJB_JAR_METADATA:Lorg/jboss/as/server/deployment/AttachmentKey;
       4: invokeinterface #4,  2            // InterfaceMethod org/jboss/as/server/deployment/DeploymentUnit.getAttachment:(Lorg/jboss/as/server/deployment/AttachmentKey;)Ljava/lang/Object;
       9: checkcast     #44                 // class org/jboss/metadata/ejb/spec/EjbJarMetaData
      12: astore        5
      14: aload         5
      16: ifnull        643
      19: iconst_0
      20: istore        6
      22: iconst_0
      23: istore        7
      25: aconst_null
      26: astore        8
      28: aload         5
      30: invokevirtual #45                 // Method org/jboss/metadata/ejb/spec/EjbJarMetaData.getAssemblyDescriptor:()Lorg/jboss/metadata/ejb/spec/AssemblyDescriptorMetaData;
      33: astore        9
      35: aload         9
      37: ifnull        445
      40: aload         9
      42: ldc           #46                 // String *
      44: invokevirtual #47                 // Method org/jboss/metadata/ejb/spec/AssemblyDescriptorMetaData.getContainerTransactionsByEjbName:(Ljava/lang/String;)Lorg/jboss/metadata/ejb/spec/ContainerTransactionsMetaData;
      47: astore        10
      49: aload         10
      51: ifnull        144
      54: aload         10
      56: invokevirtual #48                 // Method org/jboss/metadata/ejb/spec/ContainerTransactionsMetaData.size:()I
      59: iconst_1
      60: if_icmple     72
      63: getstatic     #19                 // Field org/jboss/as/ejb3/logging/EjbLogger.ROOT_LOGGER:Lorg/jboss/as/ejb3/logging/EjbLogger;
      66: invokeinterface #49,  1           // InterfaceMethod org/jboss/as/ejb3/logging/EjbLogger.mustOnlyBeSingleContainerTransactionElementWithWildcard:()Lorg/jboss/as/server/deployment/DeploymentUnitProcessingException;
      71: athrow
      72: aload         10
      74: invokevirtual #50                 // Method org/jboss/metadata/ejb/spec/ContainerTransactionsMetaData.iterator:()Ljava/util/Iterator;
      77: invokeinterface #11,  1           // InterfaceMethod java/util/Iterator.next:()Ljava/lang/Object;
      82: checkcast     #51                 // class org/jboss/metadata/ejb/spec/ContainerTransactionMetaData
      85: astore        8
      87: aload         8
      89: invokevirtual #52                 // Method org/jboss/metadata/ejb/spec/ContainerTransactionMetaData.getMethods:()Lorg/jboss/metadata/ejb/spec/MethodsMetaData;
      92: invokevirtual #53                 // Method org/jboss/metadata/ejb/spec/MethodsMetaData.iterator:()Ljava/util/Iterator;
      95: astore        11
      97: aload         11
      99: invokeinterface #10,  1           // InterfaceMethod java/util/Iterator.hasNext:()Z
     104: ifeq          144
     107: aload         11
     109: invokeinterface #11,  1           // InterfaceMethod java/util/Iterator.next:()Ljava/lang/Object;
     114: checkcast     #54                 // class org/jboss/metadata/ejb/spec/MethodMetaData
     117: astore        12
     119: aload         12
     121: invokevirtual #55                 // Method org/jboss/metadata/ejb/spec/MethodMetaData.getMethodName:()Ljava/lang/String;
     124: ldc           #46                 // String *
     126: invokevirtual #56                 // Method java/lang/String.equals:(Ljava/lang/Object;)Z
     129: ifne          141
     132: getstatic     #19                 // Field org/jboss/as/ejb3/logging/EjbLogger.ROOT_LOGGER:Lorg/jboss/as/ejb3/logging/EjbLogger;
     135: invokeinterface #57,  1           // InterfaceMethod org/jboss/as/ejb3/logging/EjbLogger.wildcardContainerTransactionElementsMustHaveWildcardMethodName:()Lorg/jboss/as/server/deployment/DeploymentUnitProcessingException;
     140: athrow
     141: goto          97
     144: aload         9
     146: aload         4
     148: invokevirtual #58                 // Method org/jboss/as/ejb3/component/EJBComponentDescription.getEJBName:()Ljava/lang/String;
     151: invokevirtual #47                 // Method org/jboss/metadata/ejb/spec/AssemblyDescriptorMetaData.getContainerTransactionsByEjbName:(Ljava/lang/String;)Lorg/jboss/metadata/ejb/spec/ContainerTransactionsMetaData;
     154: astore        11
     156: aload         11
     158: ifnull        445
     161: aload         11
     163: invokevirtual #50                 // Method org/jboss/metadata/ejb/spec/ContainerTransactionsMetaData.iterator:()Ljava/util/Iterator;
     166: astore        12
     168: aload         12
     170: invokeinterface #10,  1           // InterfaceMethod java/util/Iterator.hasNext:()Z
     175: ifeq          445
     178: aload         12
     180: invokeinterface #11,  1           // InterfaceMethod java/util/Iterator.next:()Ljava/lang/Object;
     185: checkcast     #51                 // class org/jboss/metadata/ejb/spec/ContainerTransactionMetaData
     188: astore        13
     190: aload         13
     192: invokevirtual #59                 // Method org/jboss/metadata/ejb/spec/ContainerTransactionMetaData.getTransAttribute:()Ljavax/ejb/TransactionAttributeType;
     195: astore        14
     197: aload         13
     199: invokestatic  #60                 // Method timeout:(Lorg/jboss/metadata/ejb/spec/ContainerTransactionMetaData;)Ljava/lang/Integer;
     202: astore        15
     204: aload         13
     206: invokevirtual #52                 // Method org/jboss/metadata/ejb/spec/ContainerTransactionMetaData.getMethods:()Lorg/jboss/metadata/ejb/spec/MethodsMetaData;
     209: astore        16
     211: aload         16
     213: invokevirtual #53                 // Method org/jboss/metadata/ejb/spec/MethodsMetaData.iterator:()Ljava/util/Iterator;
     216: astore        17
     218: aload         17
     220: invokeinterface #10,  1           // InterfaceMethod java/util/Iterator.hasNext:()Z
     225: ifeq          442
     228: aload         17
     230: invokeinterface #11,  1           // InterfaceMethod java/util/Iterator.next:()Ljava/lang/Object;
     235: checkcast     #54                 // class org/jboss/metadata/ejb/spec/MethodMetaData
     238: astore        18
     240: aload         18
     242: invokevirtual #55                 // Method org/jboss/metadata/ejb/spec/MethodMetaData.getMethodName:()Ljava/lang/String;
     245: astore        19
     247: aload         4
     249: instanceof    #61                 // class org/jboss/as/ejb3/component/messagedriven/MessageDrivenComponentDescription
     252: ifeq          261
     255: getstatic     #62                 // Field org/jboss/as/ejb3/component/MethodIntf.MESSAGE_ENDPOINT:Lorg/jboss/as/ejb3/component/MethodIntf;
     258: goto          264
     261: getstatic     #63                 // Field org/jboss/as/ejb3/component/MethodIntf.BEAN:Lorg/jboss/as/ejb3/component/MethodIntf;
     264: astore        20
     266: aload_0
     267: aload         18
     269: invokevirtual #64                 // Method org/jboss/metadata/ejb/spec/MethodMetaData.getMethodIntf:()Lorg/jboss/metadata/ejb/spec/MethodInterfaceType;
     272: aload         20
     274: invokevirtual #65                 // Method getMethodIntf:(Lorg/jboss/metadata/ejb/spec/MethodInterfaceType;Lorg/jboss/as/ejb3/component/MethodIntf;)Lorg/jboss/as/ejb3/component/MethodIntf;
     277: astore        21
     279: aload         19
     281: ldc           #46                 // String *
     283: invokevirtual #56                 // Method java/lang/String.equals:(Ljava/lang/Object;)Z
     286: ifeq          334
     289: aload         14
     291: ifnull        310
     294: iconst_1
     295: istore        6
     297: aload         4
     299: invokevirtual #31                 // Method org/jboss/as/ejb3/component/EJBComponentDescription.getTransactionAttributes:()Lorg/jboss/as/ejb3/deployment/ApplicableMethodInformation;
     302: aload         21
     304: aconst_null
     305: aload         14
     307: invokevirtual #33                 // Method org/jboss/as/ejb3/deployment/ApplicableMethodInformation.setAttribute:(Lorg/jboss/as/ejb3/component/MethodIntf;Ljava/lang/String;Ljava/lang/Object;)V
     310: aload         15
     312: ifnull        439
     315: iconst_1
     316: istore        7
     318: aload         4
     320: invokevirtual #42                 // Method org/jboss/as/ejb3/component/EJBComponentDescription.getTransactionTimeouts:()Lorg/jboss/as/ejb3/deployment/ApplicableMethodInformation;
     323: aload         21
     325: aconst_null
     326: aload         15
     328: invokevirtual #33                 // Method org/jboss/as/ejb3/deployment/ApplicableMethodInformation.setAttribute:(Lorg/jboss/as/ejb3/component/MethodIntf;Ljava/lang/String;Ljava/lang/Object;)V
     331: goto          439
     334: aload         18
     336: invokevirtual #66                 // Method org/jboss/metadata/ejb/spec/MethodMetaData.getMethodParams:()Lorg/jboss/metadata/ejb/spec/MethodParametersMetaData;
     339: astore        22
     341: aload         22
     343: ifnonnull     387
     346: aload         14
     348: ifnull        365
     351: aload         4
     353: invokevirtual #31                 // Method org/jboss/as/ejb3/component/EJBComponentDescription.getTransactionAttributes:()Lorg/jboss/as/ejb3/deployment/ApplicableMethodInformation;
     356: aload         21
     358: aload         14
     360: aload         19
     362: invokevirtual #67                 // Method org/jboss/as/ejb3/deployment/ApplicableMethodInformation.setAttribute:(Lorg/jboss/as/ejb3/component/MethodIntf;Ljava/lang/Object;Ljava/lang/String;)V
     365: aload         15
     367: ifnull        439
     370: aload         4
     372: invokevirtual #42                 // Method org/jboss/as/ejb3/component/EJBComponentDescription.getTransactionTimeouts:()Lorg/jboss/as/ejb3/deployment/ApplicableMethodInformation;
     375: aload         21
     377: aload         15
     379: aload         19
     381: invokevirtual #67                 // Method org/jboss/as/ejb3/deployment/ApplicableMethodInformation.setAttribute:(Lorg/jboss/as/ejb3/component/MethodIntf;Ljava/lang/Object;Ljava/lang/String;)V
     384: goto          439
     387: aload         14
     389: ifnull        413
     392: aload         4
     394: invokevirtual #31                 // Method org/jboss/as/ejb3/component/EJBComponentDescription.getTransactionAttributes:()Lorg/jboss/as/ejb3/deployment/ApplicableMethodInformation;
     397: aload         21
     399: aload         14
     401: aconst_null
     402: aload         19
     404: aload_0
     405: aload         22
     407: invokevirtual #68                 // Method getMethodParams:(Lorg/jboss/metadata/ejb/spec/MethodParametersMetaData;)[Ljava/lang/String;
     410: invokevirtual #40                 // Method org/jboss/as/ejb3/deployment/ApplicableMethodInformation.setAttribute:(Lorg/jboss/as/ejb3/component/MethodIntf;Ljava/lang/Object;Ljava/lang/String;Ljava/lang/String;[Ljava/lang/String;)V
     413: aload         15
     415: ifnull        439
     418: aload         4
     420: invokevirtual #42                 // Method org/jboss/as/ejb3/component/EJBComponentDescription.getTransactionTimeouts:()Lorg/jboss/as/ejb3/deployment/ApplicableMethodInformation;
     423: aload         21
     425: aload         15
     427: aconst_null
     428: aload         19
     430: aload_0
     431: aload         22
     433: invokevirtual #68                 // Method getMethodParams:(Lorg/jboss/metadata/ejb/spec/MethodParametersMetaData;)[Ljava/lang/String;
     436: invokevirtual #40                 // Method org/jboss/as/ejb3/deployment/ApplicableMethodInformation.setAttribute:(Lorg/jboss/as/ejb3/component/MethodIntf;Ljava/lang/Object;Ljava/lang/String;Ljava/lang/String;[Ljava/lang/String;)V
     439: goto          218
     442: goto          168
     445: aload         8
     447: ifnull        643
     450: iload         6
     452: ifne          546
     455: aload         8
     457: invokevirtual #59                 // Method org/jboss/metadata/ejb/spec/ContainerTransactionMetaData.getTransAttribute:()Ljavax/ejb/TransactionAttributeType;
     460: ifnull        546
     463: aload         8
     465: invokevirtual #52                 // Method org/jboss/metadata/ejb/spec/ContainerTransactionMetaData.getMethods:()Lorg/jboss/metadata/ejb/spec/MethodsMetaData;
     468: invokevirtual #53                 // Method org/jboss/metadata/ejb/spec/MethodsMetaData.iterator:()Ljava/util/Iterator;
     471: astore        10
     473: aload         10
     475: invokeinterface #10,  1           // InterfaceMethod java/util/Iterator.hasNext:()Z
     480: ifeq          546
     483: aload         10
     485: invokeinterface #11,  1           // InterfaceMethod java/util/Iterator.next:()Ljava/lang/Object;
     490: checkcast     #54                 // class org/jboss/metadata/ejb/spec/MethodMetaData
     493: astore        11
     495: aload         4
     497: instanceof    #61                 // class org/jboss/as/ejb3/component/messagedriven/MessageDrivenComponentDescription
     500: ifeq          509
     503: getstatic     #62                 // Field org/jboss/as/ejb3/component/MethodIntf.MESSAGE_ENDPOINT:Lorg/jboss/as/ejb3/component/MethodIntf;
     506: goto          512
     509: getstatic     #63                 // Field org/jboss/as/ejb3/component/MethodIntf.BEAN:Lorg/jboss/as/ejb3/component/MethodIntf;
     512: astore        12
     514: aload_0
     515: aload         11
     517: invokevirtual #64                 // Method org/jboss/metadata/ejb/spec/MethodMetaData.getMethodIntf:()Lorg/jboss/metadata/ejb/spec/MethodInterfaceType;
     520: aload         12
     522: invokevirtual #65                 // Method getMethodIntf:(Lorg/jboss/metadata/ejb/spec/MethodInterfaceType;Lorg/jboss/as/ejb3/component/MethodIntf;)Lorg/jboss/as/ejb3/component/MethodIntf;
     525: astore        13
     527: aload         4
     529: invokevirtual #31                 // Method org/jboss/as/ejb3/component/EJBComponentDescription.getTransactionAttributes:()Lorg/jboss/as/ejb3/deployment/ApplicableMethodInformation;
     532: aload         13
     534: aconst_null
     535: aload         8
     537: invokevirtual #59                 // Method org/jboss/metadata/ejb/spec/ContainerTransactionMetaData.getTransAttribute:()Ljavax/ejb/TransactionAttributeType;
     540: invokevirtual #33                 // Method org/jboss/as/ejb3/deployment/ApplicableMethodInformation.setAttribute:(Lorg/jboss/as/ejb3/component/MethodIntf;Ljava/lang/String;Ljava/lang/Object;)V
     543: goto          473
     546: aload         8
     548: invokestatic  #60                 // Method timeout:(Lorg/jboss/metadata/ejb/spec/ContainerTransactionMetaData;)Ljava/lang/Integer;
     551: astore        10
     553: iload         7
     555: ifne          643
     558: aload         10
     560: ifnull        643
     563: aload         8
     565: invokevirtual #52                 // Method org/jboss/metadata/ejb/spec/ContainerTransactionMetaData.getMethods:()Lorg/jboss/metadata/ejb/spec/MethodsMetaData;
     568: invokevirtual #53                 // Method org/jboss/metadata/ejb/spec/MethodsMetaData.iterator:()Ljava/util/Iterator;
     571: astore        11
     573: aload         11
     575: invokeinterface #10,  1           // InterfaceMethod java/util/Iterator.hasNext:()Z
     580: ifeq          643
     583: aload         11
     585: invokeinterface #11,  1           // InterfaceMethod java/util/Iterator.next:()Ljava/lang/Object;
     590: checkcast     #54                 // class org/jboss/metadata/ejb/spec/MethodMetaData
     593: astore        12
     595: aload         4
     597: instanceof    #61                 // class org/jboss/as/ejb3/component/messagedriven/MessageDrivenComponentDescription
     600: ifeq          609
     603: getstatic     #62                 // Field org/jboss/as/ejb3/component/MethodIntf.MESSAGE_ENDPOINT:Lorg/jboss/as/ejb3/component/MethodIntf;
     606: goto          612
     609: getstatic     #63                 // Field org/jboss/as/ejb3/component/MethodIntf.BEAN:Lorg/jboss/as/ejb3/component/MethodIntf;
     612: astore        13
     614: aload_0
     615: aload         12
     617: invokevirtual #64                 // Method org/jboss/metadata/ejb/spec/MethodMetaData.getMethodIntf:()Lorg/jboss/metadata/ejb/spec/MethodInterfaceType;
     620: aload         13
     622: invokevirtual #65                 // Method getMethodIntf:(Lorg/jboss/metadata/ejb/spec/MethodInterfaceType;Lorg/jboss/as/ejb3/component/MethodIntf;)Lorg/jboss/as/ejb3/component/MethodIntf;
     625: astore        14
     627: aload         4
     629: invokevirtual #42                 // Method org/jboss/as/ejb3/component/EJBComponentDescription.getTransactionTimeouts:()Lorg/jboss/as/ejb3/deployment/ApplicableMethodInformation;
     632: aload         14
     634: aconst_null
     635: aload         10
     637: invokevirtual #33                 // Method org/jboss/as/ejb3/deployment/ApplicableMethodInformation.setAttribute:(Lorg/jboss/as/ejb3/component/MethodIntf;Ljava/lang/String;Ljava/lang/Object;)V
     640: goto          573
     643: return

  private static java.lang.Integer timeout(org.jboss.metadata.ejb.spec.ContainerTransactionMetaData);
    Code:
       0: aload_0
       1: ldc           #69                 // class org/jboss/metadata/ejb/jboss/ejb3/TransactionTimeoutMetaData
       3: invokevirtual #70                 // Method org/jboss/metadata/ejb/spec/ContainerTransactionMetaData.getAny:(Ljava/lang/Class;)Ljava/util/List;
       6: astore_1
       7: aload_1
       8: ifnull        20
      11: aload_1
      12: invokeinterface #28,  1           // InterfaceMethod java/util/List.isEmpty:()Z
      17: ifeq          22
      20: aconst_null
      21: areturn
      22: aload_1
      23: iconst_0
      24: invokeinterface #32,  2           // InterfaceMethod java/util/List.get:(I)Ljava/lang/Object;
      29: checkcast     #69                 // class org/jboss/metadata/ejb/jboss/ejb3/TransactionTimeoutMetaData
      32: astore_2
      33: aload_2
      34: invokevirtual #71                 // Method org/jboss/metadata/ejb/jboss/ejb3/TransactionTimeoutMetaData.getUnit:()Ljava/util/concurrent/TimeUnit;
      37: ifnonnull     46
      40: getstatic     #72                 // Field java/util/concurrent/TimeUnit.SECONDS:Ljava/util/concurrent/TimeUnit;
      43: goto          50
      46: aload_2
      47: invokevirtual #71                 // Method org/jboss/metadata/ejb/jboss/ejb3/TransactionTimeoutMetaData.getUnit:()Ljava/util/concurrent/TimeUnit;
      50: astore_3
      51: aload_3
      52: aload_2
      53: invokevirtual #73                 // Method org/jboss/metadata/ejb/jboss/ejb3/TransactionTimeoutMetaData.getTimeout:()J
      56: invokevirtual #74                 // Method java/util/concurrent/TimeUnit.toSeconds:(J)J
      59: l2i
      60: invokestatic  #75                 // Method java/lang/Integer.valueOf:(I)Ljava/lang/Integer;
      63: areturn
}
