Compiled from "SetManagedResultSet.java"
abstract class com.mchange.v2.c3p0.impl.SetManagedResultSet extends com.mchange.v2.sql.filter.FilterResultSet {
  java.util.Set activeResultSets;

  com.mchange.v2.c3p0.impl.SetManagedResultSet(java.util.Set);
    Code:
       0: aload_0
       1: invokespecial #1                  // Method com/mchange/v2/sql/filter/FilterResultSet."<init>":()V
       4: aload_0
       5: aload_1
       6: putfield      #2                  // Field activeResultSets:Ljava/util/Set;
       9: return

  com.mchange.v2.c3p0.impl.SetManagedResultSet(java.sql.ResultSet, java.util.Set);
    Code:
       0: aload_0
       1: aload_1
       2: invokespecial #3                  // Method com/mchange/v2/sql/filter/FilterResultSet."<init>":(Ljava/sql/ResultSet;)V
       5: aload_0
       6: aload_2
       7: putfield      #2                  // Field activeResultSets:Ljava/util/Set;
      10: return

  public synchronized void setInner(java.sql.ResultSet);
    Code:
       0: aload_0
       1: aload_1
       2: putfield      #4                  // Field inner:Ljava/sql/ResultSet;
       5: aload_0
       6: getfield      #2                  // Field activeResultSets:Ljava/util/Set;
       9: aload_1
      10: invokeinterface #5,  2            // InterfaceMethod java/util/Set.add:(Ljava/lang/Object;)Z
      15: pop
      16: return

  public synchronized void close() throws java.sql.SQLException;
    Code:
       0: aload_0
       1: getfield      #4                  // Field inner:Ljava/sql/ResultSet;
       4: ifnull        35
       7: aload_0
       8: getfield      #4                  // Field inner:Ljava/sql/ResultSet;
      11: invokeinterface #6,  1            // InterfaceMethod java/sql/ResultSet.close:()V
      16: aload_0
      17: getfield      #2                  // Field activeResultSets:Ljava/util/Set;
      20: aload_0
      21: getfield      #4                  // Field inner:Ljava/sql/ResultSet;
      24: invokeinterface #7,  2            // InterfaceMethod java/util/Set.remove:(Ljava/lang/Object;)Z
      29: pop
      30: aload_0
      31: aconst_null
      32: putfield      #4                  // Field inner:Ljava/sql/ResultSet;
      35: return
}
