Compiled from "Either.scala"
public final class scalaz.$bslash$div$SwitchingDisjunction<X> {
  private final scala.Function0<X> r;

  private final scalaz.$bslash$div $outer;

  public X $less$less$qmark$colon(X);
    Code:
       0: aload_0
       1: getfield      #25                 // Field $outer:Lscalaz/$bslash$div;
       4: aload_0
       5: getfield      #27                 // Field r:Lscala/Function0;
       8: astore_3
       9: dup
      10: ifnonnull     15
      13: aconst_null
      14: athrow
      15: astore_2
      16: aload_2
      17: instanceof    #29                 // class scalaz/$minus$bslash$div
      20: ifeq          32
      23: aload_1
      24: invokestatic  #32                 // Method $anonfun$$less$less$qmark$colon$1:(Ljava/lang/Object;)Ljava/lang/Object;
      27: astore        4
      29: goto          59
      32: aload_2
      33: instanceof    #34                 // class scalaz/$bslash$div$minus
      36: ifeq          50
      39: aload_3
      40: invokeinterface #40,  1           // InterfaceMethod scala/Function0.apply:()Ljava/lang/Object;
      45: astore        4
      47: goto          59
      50: new           #42                 // class scala/MatchError
      53: dup
      54: aload_2
      55: invokespecial #46                 // Method scala/MatchError."<init>":(Ljava/lang/Object;)V
      58: athrow
      59: aload         4
      61: areturn

  public static final java.lang.Object $anonfun$$less$less$qmark$colon$1(java.lang.Object);
    Code:
       0: aload_0
       1: areturn

  public scalaz.$bslash$div$SwitchingDisjunction(scalaz.$bslash$div<A, B>, scala.Function0<X>);
    Code:
       0: aload_0
       1: aload_2
       2: putfield      #27                 // Field r:Lscala/Function0;
       5: aload_1
       6: ifnonnull     11
       9: aconst_null
      10: athrow
      11: aload_0
      12: aload_1
      13: putfield      #25                 // Field $outer:Lscalaz/$bslash$div;
      16: aload_0
      17: invokespecial #57                 // Method java/lang/Object."<init>":()V
      20: return

  private static java.lang.Object $deserializeLambda$(java.lang.invoke.SerializedLambda);
    Code:
       0: aload_0
       1: invokedynamic #70,  0             // InvokeDynamic #0:lambdaDeserialize:(Ljava/lang/invoke/SerializedLambda;)Ljava/lang/Object;
       6: areturn
}
