Compiled from "Alter.scala"
public interface scalaz.AlterMonoid<F, A> extends scalaz.AlterSemigroup<F, A>, scalaz.Monoid<scalaz.Alter<F, A>> {
  public abstract scalaz.PlusEmpty<F> F();

  public static scalaz.Alter zero$(scalaz.AlterMonoid);
    Code:
       0: aload_0
       1: invokespecial #23                 // InterfaceMethod zero:()Lscalaz/Alter;
       4: areturn

  public default scalaz.Alter<F, A> zero();
    Code:
       0: new           #27                 // class scalaz/Alter
       3: dup
       4: aload_0
       5: invokeinterface #29,  1           // InterfaceMethod F:()Lscalaz/PlusEmpty;
      10: invokeinterface #35,  1           // InterfaceMethod scalaz/PlusEmpty.empty:()Ljava/lang/Object;
      15: invokespecial #39                 // Method scalaz/Alter."<init>":(Ljava/lang/Object;)V
      18: areturn

  public static void $init$(scalaz.AlterMonoid);
    Code:
       0: return
}
