Compiled from "ApplicativePlus.scala"
public final class scalaz.ApplicativePlus$ {
  public static scalaz.ApplicativePlus$ MODULE$;

  public static {};
    Code:
       0: new           #2                  // class scalaz/ApplicativePlus$
       3: invokespecial #19                 // Method "<init>":()V
       6: return

  public <F> scalaz.ApplicativePlus<F> apply(scalaz.ApplicativePlus<F>);
    Code:
       0: aload_1
       1: areturn

  public <F, G> scalaz.ApplicativePlus<F> fromIso(scalaz.Isomorphisms$Iso2<scalaz.NaturalTransformation, F, G>, scalaz.ApplicativePlus<G>);
    Code:
       0: new           #7                  // class scalaz/ApplicativePlus$$anon$4
       3: dup
       4: aload_2
       5: aload_1
       6: invokespecial #33                 // Method scalaz/ApplicativePlus$$anon$4."<init>":(Lscalaz/ApplicativePlus;Lscalaz/Isomorphisms$Iso2;)V
       9: areturn

  private scalaz.ApplicativePlus$();
    Code:
       0: aload_0
       1: invokespecial #35                 // Method java/lang/Object."<init>":()V
       4: aload_0
       5: putstatic     #37                 // Field MODULE$:Lscalaz/ApplicativePlus$;
       8: return
}
