Compiled from "Composition.scala"
public interface scalaz.CompositionBifoldable<F, G> extends scalaz.Bifoldable<?> {
  public abstract scalaz.Bifoldable<F> F();

  public abstract scalaz.Bifoldable<G> G();

  public static java.lang.Object bifoldMap$(scalaz.CompositionBifoldable, java.lang.Object, scala.Function1, scala.Function1, scalaz.Monoid);
    Code:
       0: aload_0
       1: aload_1
       2: aload_2
       3: aload_3
       4: aload         4
       6: invokespecial #32                 // InterfaceMethod bifoldMap:(Ljava/lang/Object;Lscala/Function1;Lscala/Function1;Lscalaz/Monoid;)Ljava/lang/Object;
       9: areturn

  public default <A, B, M> M bifoldMap(F, scala.Function1<A, M>, scala.Function1<B, M>, scalaz.Monoid<M>);
    Code:
       0: aload_0
       1: invokeinterface #39,  1           // InterfaceMethod F:()Lscalaz/Bifoldable;
       6: aload_1
       7: aload_0
       8: aload_2
       9: aload_3
      10: aload         4
      12: invokedynamic #61,  0             // InvokeDynamic #0:apply:(Lscalaz/CompositionBifoldable;Lscala/Function1;Lscala/Function1;Lscalaz/Monoid;)Lscala/Function1;
      17: aload_0
      18: aload_2
      19: aload_3
      20: aload         4
      22: invokedynamic #66,  0             // InvokeDynamic #1:apply:(Lscalaz/CompositionBifoldable;Lscala/Function1;Lscala/Function1;Lscalaz/Monoid;)Lscala/Function1;
      27: aload         4
      29: invokeinterface #67,  5           // InterfaceMethod scalaz/Bifoldable.bifoldMap:(Ljava/lang/Object;Lscala/Function1;Lscala/Function1;Lscalaz/Monoid;)Ljava/lang/Object;
      34: areturn

  public static java.lang.Object bifoldRight$(scalaz.CompositionBifoldable, java.lang.Object, scala.Function0, scala.Function2, scala.Function2);
    Code:
       0: aload_0
       1: aload_1
       2: aload_2
       3: aload_3
       4: aload         4
       6: invokespecial #75                 // InterfaceMethod bifoldRight:(Ljava/lang/Object;Lscala/Function0;Lscala/Function2;Lscala/Function2;)Ljava/lang/Object;
       9: areturn

  public default <A, B, C> C bifoldRight(F, scala.Function0<C>, scala.Function2<A, scala.Function0<C>, C>, scala.Function2<B, scala.Function0<C>, C>);
    Code:
       0: aload_0
       1: invokeinterface #39,  1           // InterfaceMethod F:()Lscalaz/Bifoldable;
       6: aload_1
       7: aload_2
       8: aload_0
       9: aload_3
      10: aload         4
      12: invokedynamic #91,  0             // InvokeDynamic #2:apply:(Lscalaz/CompositionBifoldable;Lscala/Function2;Lscala/Function2;)Lscala/Function2;
      17: aload_0
      18: aload_3
      19: aload         4
      21: invokedynamic #96,  0             // InvokeDynamic #3:apply:(Lscalaz/CompositionBifoldable;Lscala/Function2;Lscala/Function2;)Lscala/Function2;
      26: invokeinterface #97,  5           // InterfaceMethod scalaz/Bifoldable.bifoldRight:(Ljava/lang/Object;Lscala/Function0;Lscala/Function2;Lscala/Function2;)Ljava/lang/Object;
      31: areturn

  public static java.lang.Object bifoldLeft$(scalaz.CompositionBifoldable, java.lang.Object, java.lang.Object, scala.Function2, scala.Function2);
    Code:
       0: aload_0
       1: aload_1
       2: aload_2
       3: aload_3
       4: aload         4
       6: invokespecial #103                // InterfaceMethod bifoldLeft:(Ljava/lang/Object;Ljava/lang/Object;Lscala/Function2;Lscala/Function2;)Ljava/lang/Object;
       9: areturn

  public default <A, B, C> C bifoldLeft(F, C, scala.Function2<C, A, C>, scala.Function2<C, B, C>);
    Code:
       0: aload_0
       1: invokeinterface #39,  1           // InterfaceMethod F:()Lscalaz/Bifoldable;
       6: aload_1
       7: aload_2
       8: aload_0
       9: aload_3
      10: aload         4
      12: invokedynamic #110,  0            // InvokeDynamic #4:apply:(Lscalaz/CompositionBifoldable;Lscala/Function2;Lscala/Function2;)Lscala/Function2;
      17: aload_0
      18: aload_3
      19: aload         4
      21: invokedynamic #115,  0            // InvokeDynamic #5:apply:(Lscalaz/CompositionBifoldable;Lscala/Function2;Lscala/Function2;)Lscala/Function2;
      26: invokeinterface #116,  5          // InterfaceMethod scalaz/Bifoldable.bifoldLeft:(Ljava/lang/Object;Ljava/lang/Object;Lscala/Function2;Lscala/Function2;)Ljava/lang/Object;
      31: areturn

  public static java.lang.Object $anonfun$bifoldMap$1(scalaz.CompositionBifoldable, scala.Function1, scala.Function1, scalaz.Monoid, java.lang.Object);
    Code:
       0: aload_0
       1: invokeinterface #122,  1          // InterfaceMethod G:()Lscalaz/Bifoldable;
       6: aload         4
       8: aload_1
       9: aload_2
      10: aload_3
      11: invokeinterface #67,  5           // InterfaceMethod scalaz/Bifoldable.bifoldMap:(Ljava/lang/Object;Lscala/Function1;Lscala/Function1;Lscalaz/Monoid;)Ljava/lang/Object;
      16: areturn

  public static java.lang.Object $anonfun$bifoldMap$2(scalaz.CompositionBifoldable, scala.Function1, scala.Function1, scalaz.Monoid, java.lang.Object);
    Code:
       0: aload_0
       1: invokeinterface #122,  1          // InterfaceMethod G:()Lscalaz/Bifoldable;
       6: aload         4
       8: aload_1
       9: aload_2
      10: aload_3
      11: invokeinterface #67,  5           // InterfaceMethod scalaz/Bifoldable.bifoldMap:(Ljava/lang/Object;Lscala/Function1;Lscala/Function1;Lscalaz/Monoid;)Ljava/lang/Object;
      16: areturn

  public static java.lang.Object $anonfun$bifoldRight$1(scalaz.CompositionBifoldable, scala.Function2, scala.Function2, java.lang.Object, scala.Function0);
    Code:
       0: aload_0
       1: invokeinterface #122,  1          // InterfaceMethod G:()Lscalaz/Bifoldable;
       6: aload_3
       7: aload         4
       9: aload_1
      10: aload_2
      11: invokeinterface #97,  5           // InterfaceMethod scalaz/Bifoldable.bifoldRight:(Ljava/lang/Object;Lscala/Function0;Lscala/Function2;Lscala/Function2;)Ljava/lang/Object;
      16: areturn

  public static java.lang.Object $anonfun$bifoldRight$2(scalaz.CompositionBifoldable, scala.Function2, scala.Function2, java.lang.Object, scala.Function0);
    Code:
       0: aload_0
       1: invokeinterface #122,  1          // InterfaceMethod G:()Lscalaz/Bifoldable;
       6: aload_3
       7: aload         4
       9: aload_1
      10: aload_2
      11: invokeinterface #97,  5           // InterfaceMethod scalaz/Bifoldable.bifoldRight:(Ljava/lang/Object;Lscala/Function0;Lscala/Function2;Lscala/Function2;)Ljava/lang/Object;
      16: areturn

  public static java.lang.Object $anonfun$bifoldLeft$1(scalaz.CompositionBifoldable, scala.Function2, scala.Function2, java.lang.Object, java.lang.Object);
    Code:
       0: aload_0
       1: invokeinterface #122,  1          // InterfaceMethod G:()Lscalaz/Bifoldable;
       6: aload         4
       8: aload_3
       9: aload_1
      10: aload_2
      11: invokeinterface #116,  5          // InterfaceMethod scalaz/Bifoldable.bifoldLeft:(Ljava/lang/Object;Ljava/lang/Object;Lscala/Function2;Lscala/Function2;)Ljava/lang/Object;
      16: areturn

  public static java.lang.Object $anonfun$bifoldLeft$2(scalaz.CompositionBifoldable, scala.Function2, scala.Function2, java.lang.Object, java.lang.Object);
    Code:
       0: aload_0
       1: invokeinterface #122,  1          // InterfaceMethod G:()Lscalaz/Bifoldable;
       6: aload         4
       8: aload_3
       9: aload_1
      10: aload_2
      11: invokeinterface #116,  5          // InterfaceMethod scalaz/Bifoldable.bifoldLeft:(Ljava/lang/Object;Ljava/lang/Object;Lscala/Function2;Lscala/Function2;)Ljava/lang/Object;
      16: areturn

  public static void $init$(scalaz.CompositionBifoldable);
    Code:
       0: return

  private static java.lang.Object $deserializeLambda$(java.lang.invoke.SerializedLambda);
    Code:
       0: aload_0
       1: invokedynamic #143,  0            // InvokeDynamic #6:lambdaDeserialize:(Ljava/lang/invoke/SerializedLambda;)Ljava/lang/Object;
       6: areturn
}
