Compiled from "Const.scala"
public abstract class scalaz.ConstInstances1 {
  public <C> scalaz.Traverse<?> constTraverse();
    Code:
       0: new           #10                 // class scalaz/ConstInstances1$$anon$1
       3: dup
       4: aconst_null
       5: invokespecial #19                 // Method scalaz/ConstInstances1$$anon$1."<init>":(Lscalaz/ConstInstances1;)V
       8: areturn

  public <C> scalaz.Contravariant<?> constContravariant();
    Code:
       0: new           #12                 // class scalaz/ConstInstances1$$anon$2
       3: dup
       4: aconst_null
       5: invokespecial #25                 // Method scalaz/ConstInstances1$$anon$2."<init>":(Lscalaz/ConstInstances1;)V
       8: areturn

  public scalaz.ConstInstances1();
    Code:
       0: aload_0
       1: invokespecial #28                 // Method java/lang/Object."<init>":()V
       4: return
}
