Compiled from "IndexedContsT.scala"
public interface scalaz.ContsTMonad<W, M, R> extends scalaz.Monad<?>, scalaz.ContsTBind<W, M, R> {
  public abstract scalaz.Comonad<W> W();

  public static scalaz.IndexedContsT point$(scalaz.ContsTMonad, scala.Function0);
    Code:
       0: aload_0
       1: aload_1
       2: invokespecial #34                 // InterfaceMethod point:(Lscala/Function0;)Lscalaz/IndexedContsT;
       5: areturn

  public default <A> scalaz.IndexedContsT<W, R, R, M, A> point(scala.Function0<A>);
    Code:
       0: getstatic     #43                 // Field scalaz/IndexedContsT$.MODULE$:Lscalaz/IndexedContsT$;
       3: aload_0
       4: invokeinterface #45,  1           // InterfaceMethod W:()Lscalaz/Comonad;
       9: astore_2
      10: ifnonnull     15
      13: aconst_null
      14: athrow
      15: getstatic     #48                 // Field scalaz/package$ContsT$.MODULE$:Lscalaz/package$ContsT$;
      18: aload_2
      19: aload_1
      20: invokedynamic #72,  0             // InvokeDynamic #0:apply:(Lscalaz/Comonad;Lscala/Function0;)Lscala/Function1;
      25: astore_3
      26: ifnonnull     31
      29: aconst_null
      30: athrow
      31: new           #74                 // class scalaz/IndexedContsT
      34: dup
      35: aload_3
      36: invokespecial #78                 // Method scalaz/IndexedContsT."<init>":(Lscala/Function1;)V
      39: areturn

  public static void $init$(scalaz.ContsTMonad);
    Code:
       0: return

  private static java.lang.Object $deserializeLambda$(java.lang.invoke.SerializedLambda);
    Code:
       0: aload_0
       1: invokedynamic #101,  0            // InvokeDynamic #1:lambdaDeserialize:(Ljava/lang/invoke/SerializedLambda;)Ljava/lang/Object;
       6: areturn
}
