Compiled from "Divisible.scala"
public final class scalaz.Divisible$ {
  public static scalaz.Divisible$ MODULE$;

  public static {};
    Code:
       0: new           #2                  // class scalaz/Divisible$
       3: invokespecial #19                 // Method "<init>":()V
       6: return

  public <F> scalaz.Divisible<F> apply(scalaz.Divisible<F>);
    Code:
       0: aload_1
       1: areturn

  public <F, G> scalaz.Divisible<F> fromIso(scalaz.Isomorphisms$Iso2<scalaz.NaturalTransformation, F, G>, scalaz.Divisible<G>);
    Code:
       0: new           #7                  // class scalaz/Divisible$$anon$3
       3: dup
       4: aload_2
       5: aload_1
       6: invokespecial #33                 // Method scalaz/Divisible$$anon$3."<init>":(Lscalaz/Divisible;Lscalaz/Isomorphisms$Iso2;)V
       9: areturn

  private scalaz.Divisible$();
    Code:
       0: aload_0
       1: invokespecial #35                 // Method java/lang/Object."<init>":()V
       4: aload_0
       5: putstatic     #37                 // Field MODULE$:Lscalaz/Divisible$;
       8: return
}
