Compiled from "FingerTree.scala"
public final class scalaz.FingerTree$ extends scalaz.FingerTreeInstances {
  public static scalaz.FingerTree$ MODULE$;

  public static {};
    Code:
       0: new           #2                  // class scalaz/FingerTree$
       3: invokespecial #74                 // Method "<init>":()V
       6: return

  public <V, A> scalaz.FingerTree$Node<V, A> Node2(V, scala.Function0<A>, scala.Function0<A>, scalaz.Reducer<A, V>);
    Code:
       0: new           #28                 // class scalaz/FingerTree$$anon$9
       3: dup
       4: aload         4
       6: aload_1
       7: aload_2
       8: aload_3
       9: invokespecial #84                 // Method scalaz/FingerTree$$anon$9."<init>":(Lscalaz/Reducer;Ljava/lang/Object;Lscala/Function0;Lscala/Function0;)V
      12: areturn

  public <V, A> scalaz.FingerTree$Node<V, A> Node3(V, scala.Function0<A>, scala.Function0<A>, scala.Function0<A>, scalaz.Reducer<A, V>);
    Code:
       0: new           #12                 // class scalaz/FingerTree$$anon$10
       3: dup
       4: aload         5
       6: aload_1
       7: aload_2
       8: aload_3
       9: aload         4
      11: invokespecial #96                 // Method scalaz/FingerTree$$anon$10."<init>":(Lscalaz/Reducer;Ljava/lang/Object;Lscala/Function0;Lscala/Function0;Lscala/Function0;)V
      14: areturn

  public <S, A> scalaz.FingerTree$ViewR<S, A> EmptyR();
    Code:
       0: new           #14                 // class scalaz/FingerTree$$anon$11
       3: dup
       4: invokespecial #100                // Method scalaz/FingerTree$$anon$11."<init>":()V
       7: areturn

  public <S, A> scalaz.FingerTree$ViewR<S, A> OnR(scala.Function0<S>, scala.Function0<A>);
    Code:
       0: new           #16                 // class scalaz/FingerTree$$anon$12
       3: dup
       4: aload_1
       5: aload_2
       6: invokespecial #108                // Method scalaz/FingerTree$$anon$12."<init>":(Lscala/Function0;Lscala/Function0;)V
       9: areturn

  public <S, A> scalaz.FingerTree$ViewL<S, A> EmptyL();
    Code:
       0: new           #18                 // class scalaz/FingerTree$$anon$13
       3: dup
       4: invokespecial #112                // Method scalaz/FingerTree$$anon$13."<init>":()V
       7: areturn

  public <S, A> scalaz.FingerTree$ViewL<S, A> OnL(scala.Function0<A>, scala.Function0<S>);
    Code:
       0: new           #20                 // class scalaz/FingerTree$$anon$14
       3: dup
       4: aload_1
       5: aload_2
       6: invokespecial #116                // Method scalaz/FingerTree$$anon$14."<init>":(Lscala/Function0;Lscala/Function0;)V
       9: areturn

  public <V, A> scalaz.FingerTree$Finger<V, A> one(A, scalaz.Reducer<A, V>);
    Code:
       0: new           #41                 // class scalaz/FingerTree$One
       3: dup
       4: aload_2
       5: aload_1
       6: invokeinterface #126,  2          // InterfaceMethod scalaz/Reducer.unit:(Ljava/lang/Object;)Ljava/lang/Object;
      11: aload_1
      12: aload_2
      13: invokespecial #129                // Method scalaz/FingerTree$One."<init>":(Ljava/lang/Object;Ljava/lang/Object;Lscalaz/Reducer;)V
      16: areturn

  public <V, A> scalaz.FingerTree$Finger<V, A> two(A, A, scalaz.Reducer<A, V>);
    Code:
       0: new           #47                 // class scalaz/FingerTree$Two
       3: dup
       4: aload_3
       5: aload_3
       6: aload_1
       7: invokeinterface #126,  2          // InterfaceMethod scalaz/Reducer.unit:(Ljava/lang/Object;)Ljava/lang/Object;
      12: aload_2
      13: invokeinterface #136,  3          // InterfaceMethod scalaz/Reducer.snoc:(Ljava/lang/Object;Ljava/lang/Object;)Ljava/lang/Object;
      18: aload_1
      19: aload_2
      20: aload_3
      21: invokespecial #139                // Method scalaz/FingerTree$Two."<init>":(Ljava/lang/Object;Ljava/lang/Object;Ljava/lang/Object;Lscalaz/Reducer;)V
      24: areturn

  public <V, A> scalaz.FingerTree$Finger<V, A> three(A, A, A, scalaz.Reducer<A, V>);
    Code:
       0: new           #44                 // class scalaz/FingerTree$Three
       3: dup
       4: aload         4
       6: aload         4
       8: aload         4
      10: aload_1
      11: invokeinterface #126,  2          // InterfaceMethod scalaz/Reducer.unit:(Ljava/lang/Object;)Ljava/lang/Object;
      16: aload_2
      17: invokeinterface #136,  3          // InterfaceMethod scalaz/Reducer.snoc:(Ljava/lang/Object;Ljava/lang/Object;)Ljava/lang/Object;
      22: aload_3
      23: invokeinterface #136,  3          // InterfaceMethod scalaz/Reducer.snoc:(Ljava/lang/Object;Ljava/lang/Object;)Ljava/lang/Object;
      28: aload_1
      29: aload_2
      30: aload_3
      31: aload         4
      33: invokespecial #145                // Method scalaz/FingerTree$Three."<init>":(Ljava/lang/Object;Ljava/lang/Object;Ljava/lang/Object;Ljava/lang/Object;Lscalaz/Reducer;)V
      36: areturn

  public <V, A> scalaz.FingerTree$Finger<V, A> four(A, A, A, A, scalaz.Reducer<A, V>);
    Code:
       0: new           #35                 // class scalaz/FingerTree$Four
       3: dup
       4: aload         5
       6: aload         5
       8: aload         5
      10: aload         5
      12: aload_1
      13: invokeinterface #126,  2          // InterfaceMethod scalaz/Reducer.unit:(Ljava/lang/Object;)Ljava/lang/Object;
      18: aload_2
      19: invokeinterface #136,  3          // InterfaceMethod scalaz/Reducer.snoc:(Ljava/lang/Object;Ljava/lang/Object;)Ljava/lang/Object;
      24: aload_3
      25: invokeinterface #136,  3          // InterfaceMethod scalaz/Reducer.snoc:(Ljava/lang/Object;Ljava/lang/Object;)Ljava/lang/Object;
      30: aload         4
      32: invokeinterface #136,  3          // InterfaceMethod scalaz/Reducer.snoc:(Ljava/lang/Object;Ljava/lang/Object;)Ljava/lang/Object;
      37: aload_1
      38: aload_2
      39: aload_3
      40: aload         4
      42: aload         5
      44: invokespecial #152                // Method scalaz/FingerTree$Four."<init>":(Ljava/lang/Object;Ljava/lang/Object;Ljava/lang/Object;Ljava/lang/Object;Ljava/lang/Object;Lscalaz/Reducer;)V
      47: areturn

  public <V, A> scalaz.FingerTree$Node<V, A> node2(A, A, scalaz.Reducer<A, V>);
    Code:
       0: aload_3
       1: aload_3
       2: aload_1
       3: invokeinterface #126,  2          // InterfaceMethod scalaz/Reducer.unit:(Ljava/lang/Object;)Ljava/lang/Object;
       8: aload_2
       9: invokeinterface #136,  3          // InterfaceMethod scalaz/Reducer.snoc:(Ljava/lang/Object;Ljava/lang/Object;)Ljava/lang/Object;
      14: aload_1
      15: invokedynamic #177,  0            // InvokeDynamic #0:apply:(Ljava/lang/Object;)Lscala/Function0;
      20: aload_2
      21: invokedynamic #182,  0            // InvokeDynamic #1:apply:(Ljava/lang/Object;)Lscala/Function0;
      26: astore        6
      28: astore        5
      30: astore        4
      32: new           #28                 // class scalaz/FingerTree$$anon$9
      35: dup
      36: aload_3
      37: aload         4
      39: aload         5
      41: aload         6
      43: invokespecial #84                 // Method scalaz/FingerTree$$anon$9."<init>":(Lscalaz/Reducer;Ljava/lang/Object;Lscala/Function0;Lscala/Function0;)V
      46: areturn

  public <V, A> scalaz.FingerTree$Node<V, A> node3(A, A, A, scalaz.Reducer<A, V>);
    Code:
       0: aload         4
       2: aload         4
       4: aload         4
       6: aload_1
       7: invokeinterface #126,  2          // InterfaceMethod scalaz/Reducer.unit:(Ljava/lang/Object;)Ljava/lang/Object;
      12: aload_2
      13: invokeinterface #136,  3          // InterfaceMethod scalaz/Reducer.snoc:(Ljava/lang/Object;Ljava/lang/Object;)Ljava/lang/Object;
      18: aload_3
      19: invokeinterface #136,  3          // InterfaceMethod scalaz/Reducer.snoc:(Ljava/lang/Object;Ljava/lang/Object;)Ljava/lang/Object;
      24: aload_1
      25: invokedynamic #194,  0            // InvokeDynamic #2:apply:(Ljava/lang/Object;)Lscala/Function0;
      30: aload_2
      31: invokedynamic #199,  0            // InvokeDynamic #3:apply:(Ljava/lang/Object;)Lscala/Function0;
      36: aload_3
      37: invokedynamic #204,  0            // InvokeDynamic #4:apply:(Ljava/lang/Object;)Lscala/Function0;
      42: astore        8
      44: astore        7
      46: astore        6
      48: astore        5
      50: new           #12                 // class scalaz/FingerTree$$anon$10
      53: dup
      54: aload         4
      56: aload         5
      58: aload         6
      60: aload         7
      62: aload         8
      64: invokespecial #96                 // Method scalaz/FingerTree$$anon$10."<init>":(Lscalaz/Reducer;Ljava/lang/Object;Lscala/Function0;Lscala/Function0;Lscala/Function0;)V
      67: areturn

  public <V, A> V mappendVal(V, scalaz.FingerTree<V, A>, scalaz.Semigroup<V>);
    Code:
       0: aload_2
       1: aload_1
       2: invokedynamic #218,  0            // InvokeDynamic #5:apply:(Ljava/lang/Object;)Lscala/Function0;
       7: aload_1
       8: aload_3
       9: invokedynamic #227,  0            // InvokeDynamic #6:apply:(Ljava/lang/Object;Lscalaz/Semigroup;)Lscala/Function2;
      14: aload_1
      15: aload_3
      16: invokedynamic #240,  0            // InvokeDynamic #7:apply:(Ljava/lang/Object;Lscalaz/Semigroup;)Lscala/Function4;
      21: invokevirtual #244                // Method scalaz/FingerTree.fold:(Lscala/Function0;Lscala/Function2;Lscala/Function4;)Ljava/lang/Object;
      24: areturn

  public <V, A> scalaz.FingerTree<V, A> empty(scalaz.Reducer<A, V>);
    Code:
       0: new           #22                 // class scalaz/FingerTree$$anon$15
       3: dup
       4: aload_1
       5: invokespecial #253                // Method scalaz/FingerTree$$anon$15."<init>":(Lscalaz/Reducer;)V
       8: areturn

  public <V, A> scalaz.FingerTree<V, A> single(A, scalaz.Reducer<A, V>);
    Code:
       0: aload_2
       1: aload_1
       2: invokeinterface #126,  2          // InterfaceMethod scalaz/Reducer.unit:(Ljava/lang/Object;)Ljava/lang/Object;
       7: aload_1
       8: invokedynamic #261,  0            // InvokeDynamic #8:apply:(Ljava/lang/Object;)Lscala/Function0;
      13: astore        4
      15: astore_3
      16: new           #24                 // class scalaz/FingerTree$$anon$16
      19: dup
      20: aload_2
      21: aload_3
      22: aload         4
      24: invokespecial #264                // Method scalaz/FingerTree$$anon$16."<init>":(Lscalaz/Reducer;Ljava/lang/Object;Lscala/Function0;)V
      27: areturn

  public <V, A> scalaz.FingerTree<V, A> single(V, scala.Function0<A>, scalaz.Reducer<A, V>);
    Code:
       0: new           #24                 // class scalaz/FingerTree$$anon$16
       3: dup
       4: aload_3
       5: aload_1
       6: aload_2
       7: invokespecial #264                // Method scalaz/FingerTree$$anon$16."<init>":(Lscalaz/Reducer;Ljava/lang/Object;Lscala/Function0;)V
      10: areturn

  public <V, A> scalaz.FingerTree<V, A> deep(scalaz.FingerTree$Finger<V, A>, scala.Function0<scalaz.FingerTree<V, scalaz.FingerTree$Node<V, A>>>, scalaz.FingerTree$Finger<V, A>, scalaz.Reducer<A, V>);
    Code:
       0: aload_0
       1: aload         4
       3: invokeinterface #280,  1          // InterfaceMethod scalaz/Reducer.semigroup:()Lscalaz/Semigroup;
       8: invokevirtual #284                // Method fingerMeasure:(Lscalaz/Semigroup;)Lscalaz/Reducer;
      11: astore        5
      13: aload         5
      15: aload_0
      16: aload         5
      18: aload_1
      19: invokeinterface #126,  2          // InterfaceMethod scalaz/Reducer.unit:(Ljava/lang/Object;)Ljava/lang/Object;
      24: aload_2
      25: invokeinterface #288,  1          // InterfaceMethod scala/Function0.apply:()Ljava/lang/Object;
      30: checkcast     #32                 // class scalaz/FingerTree
      33: aload         4
      35: invokeinterface #280,  1          // InterfaceMethod scalaz/Reducer.semigroup:()Lscalaz/Semigroup;
      40: invokevirtual #290                // Method mappendVal:(Ljava/lang/Object;Lscalaz/FingerTree;Lscalaz/Semigroup;)Ljava/lang/Object;
      43: aload_3
      44: invokeinterface #136,  3          // InterfaceMethod scalaz/Reducer.snoc:(Ljava/lang/Object;Ljava/lang/Object;)Ljava/lang/Object;
      49: astore        6
      51: new           #26                 // class scalaz/FingerTree$$anon$17
      54: dup
      55: aload         4
      57: aload_2
      58: aload         6
      60: aload_1
      61: aload_3
      62: invokespecial #293                // Method scalaz/FingerTree$$anon$17."<init>":(Lscalaz/Reducer;Lscala/Function0;Ljava/lang/Object;Lscalaz/FingerTree$Finger;Lscalaz/FingerTree$Finger;)V
      65: areturn

  public <V, A> scalaz.FingerTree<V, A> deep(V, scalaz.FingerTree$Finger<V, A>, scala.Function0<scalaz.FingerTree<V, scalaz.FingerTree$Node<V, A>>>, scalaz.FingerTree$Finger<V, A>, scalaz.Reducer<A, V>);
    Code:
       0: new           #26                 // class scalaz/FingerTree$$anon$17
       3: dup
       4: aload         5
       6: aload_3
       7: aload_1
       8: aload_2
       9: aload         4
      11: invokespecial #293                // Method scalaz/FingerTree$$anon$17."<init>":(Lscalaz/Reducer;Lscala/Function0;Ljava/lang/Object;Lscalaz/FingerTree$Finger;Lscalaz/FingerTree$Finger;)V
      14: areturn

  public <V, A> scalaz.FingerTree<V, A> deepL(scala.Option<scalaz.FingerTree$Finger<V, A>>, scala.Function0<scalaz.FingerTree<V, scalaz.FingerTree$Node<V, A>>>, scalaz.FingerTree$Finger<V, A>, scalaz.Reducer<A, V>);
    Code:
       0: getstatic     #308                // Field scala/None$.MODULE$:Lscala/None$;
       3: aload_1
       4: invokevirtual #314                // Method java/lang/Object.equals:(Ljava/lang/Object;)Z
       7: ifeq          31
      10: aload_0
      11: aload_2
      12: invokeinterface #288,  1          // InterfaceMethod scala/Function0.apply:()Ljava/lang/Object;
      17: checkcast     #32                 // class scalaz/FingerTree
      20: aload_3
      21: aload         4
      23: invokevirtual #318                // Method rotL:(Lscalaz/FingerTree;Lscalaz/FingerTree$Finger;Lscalaz/Reducer;)Lscalaz/FingerTree;
      26: astore        5
      28: goto          131
      31: aload_1
      32: instanceof    #320                // class scala/Some
      35: ifeq          122
      38: aload_1
      39: checkcast     #320                // class scala/Some
      42: invokevirtual #323                // Method scala/Some.value:()Ljava/lang/Object;
      45: checkcast     #30                 // class scalaz/FingerTree$Finger
      48: astore        6
      50: aload_0
      51: aload         4
      53: invokeinterface #280,  1          // InterfaceMethod scalaz/Reducer.semigroup:()Lscalaz/Semigroup;
      58: invokevirtual #284                // Method fingerMeasure:(Lscalaz/Semigroup;)Lscalaz/Reducer;
      61: astore        7
      63: aload         7
      65: aload_0
      66: aload         7
      68: aload         6
      70: invokeinterface #126,  2          // InterfaceMethod scalaz/Reducer.unit:(Ljava/lang/Object;)Ljava/lang/Object;
      75: aload_2
      76: invokeinterface #288,  1          // InterfaceMethod scala/Function0.apply:()Ljava/lang/Object;
      81: checkcast     #32                 // class scalaz/FingerTree
      84: aload         4
      86: invokeinterface #280,  1          // InterfaceMethod scalaz/Reducer.semigroup:()Lscalaz/Semigroup;
      91: invokevirtual #290                // Method mappendVal:(Ljava/lang/Object;Lscalaz/FingerTree;Lscalaz/Semigroup;)Ljava/lang/Object;
      94: aload_3
      95: invokeinterface #136,  3          // InterfaceMethod scalaz/Reducer.snoc:(Ljava/lang/Object;Ljava/lang/Object;)Ljava/lang/Object;
     100: astore        8
     102: new           #26                 // class scalaz/FingerTree$$anon$17
     105: dup
     106: aload         4
     108: aload_2
     109: aload         8
     111: aload         6
     113: aload_3
     114: invokespecial #293                // Method scalaz/FingerTree$$anon$17."<init>":(Lscalaz/Reducer;Lscala/Function0;Ljava/lang/Object;Lscalaz/FingerTree$Finger;Lscalaz/FingerTree$Finger;)V
     117: astore        5
     119: goto          131
     122: new           #325                // class scala/MatchError
     125: dup
     126: aload_1
     127: invokespecial #328                // Method scala/MatchError."<init>":(Ljava/lang/Object;)V
     130: athrow
     131: aload         5
     133: areturn

  public <V, A> scalaz.FingerTree<V, A> deepR(scalaz.FingerTree$Finger<V, A>, scala.Function0<scalaz.FingerTree<V, scalaz.FingerTree$Node<V, A>>>, scala.Option<scalaz.FingerTree$Finger<V, A>>, scalaz.Reducer<A, V>);
    Code:
       0: getstatic     #308                // Field scala/None$.MODULE$:Lscala/None$;
       3: aload_3
       4: invokevirtual #314                // Method java/lang/Object.equals:(Ljava/lang/Object;)Z
       7: ifeq          31
      10: aload_0
      11: aload_1
      12: aload_2
      13: invokeinterface #288,  1          // InterfaceMethod scala/Function0.apply:()Ljava/lang/Object;
      18: checkcast     #32                 // class scalaz/FingerTree
      21: aload         4
      23: invokevirtual #340                // Method rotR:(Lscalaz/FingerTree$Finger;Lscalaz/FingerTree;Lscalaz/Reducer;)Lscalaz/FingerTree;
      26: astore        5
      28: goto          131
      31: aload_3
      32: instanceof    #320                // class scala/Some
      35: ifeq          122
      38: aload_3
      39: checkcast     #320                // class scala/Some
      42: invokevirtual #323                // Method scala/Some.value:()Ljava/lang/Object;
      45: checkcast     #30                 // class scalaz/FingerTree$Finger
      48: astore        6
      50: aload_0
      51: aload         4
      53: invokeinterface #280,  1          // InterfaceMethod scalaz/Reducer.semigroup:()Lscalaz/Semigroup;
      58: invokevirtual #284                // Method fingerMeasure:(Lscalaz/Semigroup;)Lscalaz/Reducer;
      61: astore        7
      63: aload         7
      65: aload_0
      66: aload         7
      68: aload_1
      69: invokeinterface #126,  2          // InterfaceMethod scalaz/Reducer.unit:(Ljava/lang/Object;)Ljava/lang/Object;
      74: aload_2
      75: invokeinterface #288,  1          // InterfaceMethod scala/Function0.apply:()Ljava/lang/Object;
      80: checkcast     #32                 // class scalaz/FingerTree
      83: aload         4
      85: invokeinterface #280,  1          // InterfaceMethod scalaz/Reducer.semigroup:()Lscalaz/Semigroup;
      90: invokevirtual #290                // Method mappendVal:(Ljava/lang/Object;Lscalaz/FingerTree;Lscalaz/Semigroup;)Ljava/lang/Object;
      93: aload         6
      95: invokeinterface #136,  3          // InterfaceMethod scalaz/Reducer.snoc:(Ljava/lang/Object;Ljava/lang/Object;)Ljava/lang/Object;
     100: astore        8
     102: new           #26                 // class scalaz/FingerTree$$anon$17
     105: dup
     106: aload         4
     108: aload_2
     109: aload         8
     111: aload_1
     112: aload         6
     114: invokespecial #293                // Method scalaz/FingerTree$$anon$17."<init>":(Lscalaz/Reducer;Lscala/Function0;Ljava/lang/Object;Lscalaz/FingerTree$Finger;Lscalaz/FingerTree$Finger;)V
     117: astore        5
     119: goto          131
     122: new           #325                // class scala/MatchError
     125: dup
     126: aload_3
     127: invokespecial #328                // Method scala/MatchError."<init>":(Ljava/lang/Object;)V
     130: athrow
     131: aload         5
     133: areturn

  public <V, A> scalaz.FingerTree<V, A> rotL(scalaz.FingerTree<V, scalaz.FingerTree$Node<V, A>>, scalaz.FingerTree$Finger<V, A>, scalaz.Reducer<A, V>);
    Code:
       0: aload_1
       1: invokevirtual #344                // Method scalaz/FingerTree.viewl:()Lscalaz/FingerTree$ViewL;
       4: aload_2
       5: invokedynamic #354,  0            // InvokeDynamic #9:apply:(Lscalaz/FingerTree$Finger;)Lscala/Function0;
      10: aload_1
      11: aload_3
      12: aload_2
      13: invokedynamic #364,  0            // InvokeDynamic #10:apply:(Lscalaz/FingerTree;Lscalaz/Reducer;Lscalaz/FingerTree$Finger;)Lscala/Function2;
      18: invokevirtual #367                // Method scalaz/FingerTree$ViewL.fold:(Lscala/Function0;Lscala/Function2;)Ljava/lang/Object;
      21: checkcast     #32                 // class scalaz/FingerTree
      24: areturn

  public <V, A> scalaz.FingerTree<V, A> rotR(scalaz.FingerTree$Finger<V, A>, scalaz.FingerTree<V, scalaz.FingerTree$Node<V, A>>, scalaz.Reducer<A, V>);
    Code:
       0: aload_2
       1: invokevirtual #371                // Method scalaz/FingerTree.viewr:()Lscalaz/FingerTree$ViewR;
       4: aload_1
       5: invokedynamic #376,  0            // InvokeDynamic #11:apply:(Lscalaz/FingerTree$Finger;)Lscala/Function0;
      10: aload_1
      11: aload_2
      12: aload_3
      13: invokedynamic #384,  0            // InvokeDynamic #12:apply:(Lscalaz/FingerTree$Finger;Lscalaz/FingerTree;Lscalaz/Reducer;)Lscala/Function2;
      18: invokevirtual #385                // Method scalaz/FingerTree$ViewR.fold:(Lscala/Function0;Lscala/Function2;)Ljava/lang/Object;
      21: checkcast     #32                 // class scalaz/FingerTree
      24: areturn

  public static final java.lang.Object $anonfun$node2$1(java.lang.Object);
    Code:
       0: aload_0
       1: areturn

  public static final java.lang.Object $anonfun$node2$2(java.lang.Object);
    Code:
       0: aload_0
       1: areturn

  public static final java.lang.Object $anonfun$node3$1(java.lang.Object);
    Code:
       0: aload_0
       1: areturn

  public static final java.lang.Object $anonfun$node3$2(java.lang.Object);
    Code:
       0: aload_0
       1: areturn

  public static final java.lang.Object $anonfun$node3$3(java.lang.Object);
    Code:
       0: aload_0
       1: areturn

  public static final java.lang.Object $anonfun$mappendVal$1(java.lang.Object);
    Code:
       0: aload_0
       1: areturn

  public static final java.lang.Object $anonfun$mappendVal$3(java.lang.Object);
    Code:
       0: aload_0
       1: areturn

  public static final java.lang.Object $anonfun$mappendVal$2(java.lang.Object, scalaz.Semigroup, java.lang.Object, java.lang.Object);
    Code:
       0: getstatic     #401                // Field scalaz/syntax/package$.MODULE$:Lscalaz/syntax/package$;
       3: invokevirtual #404                // Method scalaz/syntax/package$.semigroup:()Lscalaz/syntax/Syntaxes$semigroup$;
       6: aload_0
       7: aload_1
       8: invokevirtual #408                // Method scalaz/syntax/Syntaxes$semigroup$.ToSemigroupOps:(Ljava/lang/Object;Lscalaz/Semigroup;)Lscalaz/syntax/SemigroupOps;
      11: aload_2
      12: invokedynamic #412,  0            // InvokeDynamic #13:apply:(Ljava/lang/Object;)Lscala/Function0;
      17: astore        5
      19: dup
      20: ifnonnull     25
      23: aconst_null
      24: athrow
      25: astore        4
      27: aload         4
      29: invokevirtual #417                // Method scalaz/syntax/SemigroupOps.F:()Lscalaz/Semigroup;
      32: aload         4
      34: invokevirtual #420                // Method scalaz/syntax/SemigroupOps.self:()Ljava/lang/Object;
      37: aload         5
      39: invokeinterface #426,  3          // InterfaceMethod scalaz/Semigroup.append:(Ljava/lang/Object;Lscala/Function0;)Ljava/lang/Object;
      44: areturn

  public static final java.lang.Object $anonfun$mappendVal$5(java.lang.Object);
    Code:
       0: aload_0
       1: areturn

  public static final java.lang.Object $anonfun$mappendVal$4(java.lang.Object, scalaz.Semigroup, java.lang.Object, scalaz.FingerTree$Finger, scala.Function0, scalaz.FingerTree$Finger);
    Code:
       0: getstatic     #401                // Field scalaz/syntax/package$.MODULE$:Lscalaz/syntax/package$;
       3: invokevirtual #404                // Method scalaz/syntax/package$.semigroup:()Lscalaz/syntax/Syntaxes$semigroup$;
       6: aload_0
       7: aload_1
       8: invokevirtual #408                // Method scalaz/syntax/Syntaxes$semigroup$.ToSemigroupOps:(Ljava/lang/Object;Lscalaz/Semigroup;)Lscalaz/syntax/SemigroupOps;
      11: aload_2
      12: invokedynamic #438,  0            // InvokeDynamic #14:apply:(Ljava/lang/Object;)Lscala/Function0;
      17: astore        7
      19: dup
      20: ifnonnull     25
      23: aconst_null
      24: athrow
      25: astore        6
      27: aload         6
      29: invokevirtual #417                // Method scalaz/syntax/SemigroupOps.F:()Lscalaz/Semigroup;
      32: aload         6
      34: invokevirtual #420                // Method scalaz/syntax/SemigroupOps.self:()Ljava/lang/Object;
      37: aload         7
      39: invokeinterface #426,  3          // InterfaceMethod scalaz/Semigroup.append:(Ljava/lang/Object;Lscala/Function0;)Ljava/lang/Object;
      44: areturn

  public static final java.lang.Object $anonfun$single$1(java.lang.Object);
    Code:
       0: aload_0
       1: areturn

  public static final scalaz.FingerTree $anonfun$rotL$1(scalaz.FingerTree$Finger);
    Code:
       0: aload_0
       1: invokevirtual #443                // Method scalaz/FingerTree$Finger.toTree:()Lscalaz/FingerTree;
       4: areturn

  public static final java.lang.Object $anonfun$rotL$4(scalaz.FingerTree$Finger);
    Code:
       0: aload_0
       1: invokevirtual #447                // Method scalaz/FingerTree$Finger.measure:()Ljava/lang/Object;
       4: areturn

  public static final java.lang.Object $anonfun$rotL$3(scalaz.Reducer, scalaz.FingerTree$Finger, java.lang.Object);
    Code:
       0: getstatic     #401                // Field scalaz/syntax/package$.MODULE$:Lscalaz/syntax/package$;
       3: invokevirtual #404                // Method scalaz/syntax/package$.semigroup:()Lscalaz/syntax/Syntaxes$semigroup$;
       6: aload_2
       7: aload_0
       8: invokeinterface #280,  1          // InterfaceMethod scalaz/Reducer.semigroup:()Lscalaz/Semigroup;
      13: invokevirtual #408                // Method scalaz/syntax/Syntaxes$semigroup$.ToSemigroupOps:(Ljava/lang/Object;Lscalaz/Semigroup;)Lscalaz/syntax/SemigroupOps;
      16: aload_1
      17: invokedynamic #455,  0            // InvokeDynamic #15:apply:(Lscalaz/FingerTree$Finger;)Lscala/Function0;
      22: astore        4
      24: dup
      25: ifnonnull     30
      28: aconst_null
      29: athrow
      30: astore_3
      31: aload_3
      32: invokevirtual #417                // Method scalaz/syntax/SemigroupOps.F:()Lscalaz/Semigroup;
      35: aload_3
      36: invokevirtual #420                // Method scalaz/syntax/SemigroupOps.self:()Ljava/lang/Object;
      39: aload         4
      41: invokeinterface #426,  3          // InterfaceMethod scalaz/Semigroup.append:(Ljava/lang/Object;Lscala/Function0;)Ljava/lang/Object;
      46: areturn

  public static final java.lang.Object $anonfun$rotL$5(scalaz.FingerTree$Finger);
    Code:
       0: aload_0
       1: invokevirtual #447                // Method scalaz/FingerTree$Finger.measure:()Ljava/lang/Object;
       4: areturn

  public static final scalaz.FingerTree $anonfun$rotL$2(scalaz.FingerTree, scalaz.Reducer, scalaz.FingerTree$Finger, scala.Function0, scala.Function0);
    Code:
       0: getstatic     #460                // Field MODULE$:Lscalaz/FingerTree$;
       3: aload_0
       4: invokevirtual #463                // Method scalaz/FingerTree.measure:()Lscalaz/Maybe;
       7: dup
       8: ifnonnull     13
      11: aconst_null
      12: athrow
      13: astore        5
      15: aload         5
      17: instanceof    #61                 // class scalaz/Maybe$Just
      20: ifeq          45
      23: aload         5
      25: checkcast     #61                 // class scalaz/Maybe$Just
      28: invokevirtual #466                // Method scalaz/Maybe$Just.get:()Ljava/lang/Object;
      31: astore        7
      33: aload_1
      34: aload_2
      35: aload         7
      37: invokestatic  #468                // Method $anonfun$rotL$3:(Lscalaz/Reducer;Lscalaz/FingerTree$Finger;Ljava/lang/Object;)Ljava/lang/Object;
      40: astore        6
      42: goto          72
      45: aload         5
      47: instanceof    #56                 // class scalaz/Maybe$Empty
      50: ifeq          62
      53: aload_2
      54: invokestatic  #470                // Method $anonfun$rotL$5:(Lscalaz/FingerTree$Finger;)Ljava/lang/Object;
      57: astore        6
      59: goto          72
      62: new           #325                // class scala/MatchError
      65: dup
      66: aload         5
      68: invokespecial #328                // Method scala/MatchError."<init>":(Ljava/lang/Object;)V
      71: athrow
      72: aload_3
      73: invokeinterface #288,  1          // InterfaceMethod scala/Function0.apply:()Ljava/lang/Object;
      78: checkcast     #38                 // class scalaz/FingerTree$Node
      81: invokevirtual #474                // Method scalaz/FingerTree$Node.toDigit:()Lscalaz/FingerTree$Finger;
      84: astore        8
      86: ifnonnull     91
      89: aconst_null
      90: athrow
      91: new           #26                 // class scalaz/FingerTree$$anon$17
      94: dup
      95: aload_1
      96: aload         4
      98: aload         6
     100: aload         8
     102: aload_2
     103: invokespecial #293                // Method scalaz/FingerTree$$anon$17."<init>":(Lscalaz/Reducer;Lscala/Function0;Ljava/lang/Object;Lscalaz/FingerTree$Finger;Lscalaz/FingerTree$Finger;)V
     106: areturn

  public static final scalaz.FingerTree $anonfun$rotR$1(scalaz.FingerTree$Finger);
    Code:
       0: aload_0
       1: invokevirtual #443                // Method scalaz/FingerTree$Finger.toTree:()Lscalaz/FingerTree;
       4: areturn

  public static final scalaz.FingerTree $anonfun$rotR$2(scalaz.FingerTree$Finger, scalaz.FingerTree, scalaz.Reducer, scala.Function0, scala.Function0);
    Code:
       0: getstatic     #460                // Field MODULE$:Lscalaz/FingerTree$;
       3: getstatic     #460                // Field MODULE$:Lscalaz/FingerTree$;
       6: aload_0
       7: invokevirtual #447                // Method scalaz/FingerTree$Finger.measure:()Ljava/lang/Object;
      10: aload_1
      11: aload_2
      12: invokeinterface #280,  1          // InterfaceMethod scalaz/Reducer.semigroup:()Lscalaz/Semigroup;
      17: invokevirtual #290                // Method mappendVal:(Ljava/lang/Object;Lscalaz/FingerTree;Lscalaz/Semigroup;)Ljava/lang/Object;
      20: aload         4
      22: invokeinterface #288,  1          // InterfaceMethod scala/Function0.apply:()Ljava/lang/Object;
      27: checkcast     #38                 // class scalaz/FingerTree$Node
      30: invokevirtual #474                // Method scalaz/FingerTree$Node.toDigit:()Lscalaz/FingerTree$Finger;
      33: astore        6
      35: astore        5
      37: ifnonnull     42
      40: aconst_null
      41: athrow
      42: new           #26                 // class scalaz/FingerTree$$anon$17
      45: dup
      46: aload_2
      47: aload_3
      48: aload         5
      50: aload_0
      51: aload         6
      53: invokespecial #293                // Method scalaz/FingerTree$$anon$17."<init>":(Lscalaz/Reducer;Lscala/Function0;Ljava/lang/Object;Lscalaz/FingerTree$Finger;Lscalaz/FingerTree$Finger;)V
      56: areturn

  private scalaz.FingerTree$();
    Code:
       0: aload_0
       1: invokespecial #483                // Method scalaz/FingerTreeInstances."<init>":()V
       4: aload_0
       5: putstatic     #460                // Field MODULE$:Lscalaz/FingerTree$;
       8: return

  private static java.lang.Object $deserializeLambda$(java.lang.invoke.SerializedLambda);
    Code:
       0: aload_0
       1: invokedynamic #497,  0            // InvokeDynamic #16:lambdaDeserialize:(Ljava/lang/invoke/SerializedLambda;)Ljava/lang/Object;
       6: areturn
}
