Compiled from "InvariantAlt.scala"
public interface scalaz.InvariantAlt<F> extends scalaz.InvariantApplicative<F> {
  public static <F, G> scalaz.InvariantAlt<F> fromIso(scalaz.Isomorphisms$Iso2<scalaz.NaturalTransformation, F, G>, scalaz.InvariantAlt<G>);
    Code:
       0: getstatic     #34                 // Field scalaz/InvariantAlt$.MODULE$:Lscalaz/InvariantAlt$;
       3: aload_0
       4: aload_1
       5: invokevirtual #36                 // Method scalaz/InvariantAlt$.fromIso:(Lscalaz/Isomorphisms$Iso2;Lscalaz/InvariantAlt;)Lscalaz/InvariantAlt;
       8: areturn

  public static <F> scalaz.InvariantAlt<F> apply(scalaz.InvariantAlt<F>);
    Code:
       0: getstatic     #34                 // Field scalaz/InvariantAlt$.MODULE$:Lscalaz/InvariantAlt$;
       3: ifnonnull     8
       6: aconst_null
       7: athrow
       8: aload_0
       9: areturn

  public abstract void scalaz$InvariantAlt$_setter_$invariantAltSyntax_$eq(scalaz.syntax.InvariantAltSyntax<F>);

  public static java.lang.Object xcoproduct1$(scalaz.InvariantAlt, scala.Function0, scala.Function1, scala.Function1);
    Code:
       0: aload_0
       1: aload_1
       2: aload_2
       3: aload_3
       4: invokespecial #54                 // InterfaceMethod xcoproduct1:(Lscala/Function0;Lscala/Function1;Lscala/Function1;)Ljava/lang/Object;
       7: areturn

  public default <Z, A1> F xcoproduct1(scala.Function0<F>, scala.Function1<A1, Z>, scala.Function1<Z, A1>);
    Code:
       0: aload_0
       1: aload_1
       2: invokeinterface #63,  1           // InterfaceMethod scala/Function0.apply:()Ljava/lang/Object;
       7: aload_2
       8: aload_3
       9: invokeinterface #67,  4           // InterfaceMethod xmap:(Ljava/lang/Object;Lscala/Function1;Lscala/Function1;)Ljava/lang/Object;
      14: areturn

  public abstract <Z, A1, A2> F xcoproduct2(scala.Function0<F>, scala.Function0<F>, scala.Function1<scalaz.$bslash$div<A1, A2>, Z>, scala.Function1<Z, scalaz.$bslash$div<A1, A2>>);

  public static java.lang.Object xcoproduct3$(scalaz.InvariantAlt, scala.Function0, scala.Function0, scala.Function0, scala.Function1, scala.Function1);
    Code:
       0: aload_0
       1: aload_1
       2: aload_2
       3: aload_3
       4: aload         4
       6: aload         5
       8: invokespecial #79                 // InterfaceMethod xcoproduct3:(Lscala/Function0;Lscala/Function0;Lscala/Function0;Lscala/Function1;Lscala/Function1;)Ljava/lang/Object;
      11: areturn

  public default <Z, A1, A2, A3> F xcoproduct3(scala.Function0<F>, scala.Function0<F>, scala.Function0<F>, scala.Function1<scalaz.$bslash$div<A1, scalaz.$bslash$div<A2, A3>>, Z>, scala.Function1<Z, scalaz.$bslash$div<A1, scalaz.$bslash$div<A2, A3>>>);
    Code:
       0: aload_0
       1: aload_2
       2: aload_3
       3: invokedynamic #102,  0            // InvokeDynamic #0:apply:()Lscala/Function1;
       8: invokedynamic #107,  0            // InvokeDynamic #1:apply:()Lscala/Function1;
      13: invokeinterface #109,  5          // InterfaceMethod xcoproduct2:(Lscala/Function0;Lscala/Function0;Lscala/Function1;Lscala/Function1;)Ljava/lang/Object;
      18: astore        6
      20: aload_0
      21: aload_1
      22: aload         6
      24: invokedynamic #118,  0            // InvokeDynamic #2:apply:(Ljava/lang/Object;)Lscala/Function0;
      29: aload         4
      31: aload         5
      33: invokeinterface #109,  5          // InterfaceMethod xcoproduct2:(Lscala/Function0;Lscala/Function0;Lscala/Function1;Lscala/Function1;)Ljava/lang/Object;
      38: areturn

  public static java.lang.Object xcoproduct4$(scalaz.InvariantAlt, scala.Function0, scala.Function0, scala.Function0, scala.Function0, scala.Function1, scala.Function1);
    Code:
       0: aload_0
       1: aload_1
       2: aload_2
       3: aload_3
       4: aload         4
       6: aload         5
       8: aload         6
      10: invokespecial #127                // InterfaceMethod xcoproduct4:(Lscala/Function0;Lscala/Function0;Lscala/Function0;Lscala/Function0;Lscala/Function1;Lscala/Function1;)Ljava/lang/Object;
      13: areturn

  public default <Z, A1, A2, A3, A4> F xcoproduct4(scala.Function0<F>, scala.Function0<F>, scala.Function0<F>, scala.Function0<F>, scala.Function1<scalaz.$bslash$div<A1, scalaz.$bslash$div<A2, scalaz.$bslash$div<A3, A4>>>, Z>, scala.Function1<Z, scalaz.$bslash$div<A1, scalaz.$bslash$div<A2, scalaz.$bslash$div<A3, A4>>>>);
    Code:
       0: aload_0
       1: aload_2
       2: aload_3
       3: aload         4
       5: invokedynamic #133,  0            // InvokeDynamic #3:apply:()Lscala/Function1;
      10: invokedynamic #138,  0            // InvokeDynamic #4:apply:()Lscala/Function1;
      15: invokeinterface #79,  6           // InterfaceMethod xcoproduct3:(Lscala/Function0;Lscala/Function0;Lscala/Function0;Lscala/Function1;Lscala/Function1;)Ljava/lang/Object;
      20: astore        7
      22: aload_0
      23: aload_1
      24: aload         7
      26: invokedynamic #143,  0            // InvokeDynamic #5:apply:(Ljava/lang/Object;)Lscala/Function0;
      31: aload         5
      33: aload         6
      35: invokeinterface #109,  5          // InterfaceMethod xcoproduct2:(Lscala/Function0;Lscala/Function0;Lscala/Function1;Lscala/Function1;)Ljava/lang/Object;
      40: areturn

  public static java.lang.Object xcoderiving1$(scalaz.InvariantAlt, scala.Function1, scala.Function1, java.lang.Object);
    Code:
       0: aload_0
       1: aload_1
       2: aload_2
       3: aload_3
       4: invokespecial #150                // InterfaceMethod xcoderiving1:(Lscala/Function1;Lscala/Function1;Ljava/lang/Object;)Ljava/lang/Object;
       7: areturn

  public default <Z, A1> F xcoderiving1(scala.Function1<A1, Z>, scala.Function1<Z, A1>, F);
    Code:
       0: aload_0
       1: aload_3
       2: invokedynamic #156,  0            // InvokeDynamic #6:apply:(Ljava/lang/Object;)Lscala/Function0;
       7: aload_1
       8: aload_2
       9: invokeinterface #54,  4           // InterfaceMethod xcoproduct1:(Lscala/Function0;Lscala/Function1;Lscala/Function1;)Ljava/lang/Object;
      14: areturn

  public static java.lang.Object xcoderiving2$(scalaz.InvariantAlt, scala.Function1, scala.Function1, java.lang.Object, java.lang.Object);
    Code:
       0: aload_0
       1: aload_1
       2: aload_2
       3: aload_3
       4: aload         4
       6: invokespecial #162                // InterfaceMethod xcoderiving2:(Lscala/Function1;Lscala/Function1;Ljava/lang/Object;Ljava/lang/Object;)Ljava/lang/Object;
       9: areturn

  public default <Z, A1, A2> F xcoderiving2(scala.Function1<scalaz.$bslash$div<A1, A2>, Z>, scala.Function1<Z, scalaz.$bslash$div<A1, A2>>, F, F);
    Code:
       0: aload_0
       1: aload_3
       2: invokedynamic #168,  0            // InvokeDynamic #7:apply:(Ljava/lang/Object;)Lscala/Function0;
       7: aload         4
       9: invokedynamic #173,  0            // InvokeDynamic #8:apply:(Ljava/lang/Object;)Lscala/Function0;
      14: aload_1
      15: aload_2
      16: invokeinterface #109,  5          // InterfaceMethod xcoproduct2:(Lscala/Function0;Lscala/Function0;Lscala/Function1;Lscala/Function1;)Ljava/lang/Object;
      21: areturn

  public static java.lang.Object xcoderiving3$(scalaz.InvariantAlt, scala.Function1, scala.Function1, java.lang.Object, java.lang.Object, java.lang.Object);
    Code:
       0: aload_0
       1: aload_1
       2: aload_2
       3: aload_3
       4: aload         4
       6: aload         5
       8: invokespecial #179                // InterfaceMethod xcoderiving3:(Lscala/Function1;Lscala/Function1;Ljava/lang/Object;Ljava/lang/Object;Ljava/lang/Object;)Ljava/lang/Object;
      11: areturn

  public default <Z, A1, A2, A3> F xcoderiving3(scala.Function1<scalaz.$bslash$div<A1, scalaz.$bslash$div<A2, A3>>, Z>, scala.Function1<Z, scalaz.$bslash$div<A1, scalaz.$bslash$div<A2, A3>>>, F, F, F);
    Code:
       0: aload_0
       1: aload_3
       2: invokedynamic #185,  0            // InvokeDynamic #9:apply:(Ljava/lang/Object;)Lscala/Function0;
       7: aload         4
       9: invokedynamic #190,  0            // InvokeDynamic #10:apply:(Ljava/lang/Object;)Lscala/Function0;
      14: aload         5
      16: invokedynamic #195,  0            // InvokeDynamic #11:apply:(Ljava/lang/Object;)Lscala/Function0;
      21: aload_1
      22: aload_2
      23: invokeinterface #79,  6           // InterfaceMethod xcoproduct3:(Lscala/Function0;Lscala/Function0;Lscala/Function0;Lscala/Function1;Lscala/Function1;)Ljava/lang/Object;
      28: areturn

  public static java.lang.Object xcoderiving4$(scalaz.InvariantAlt, scala.Function1, scala.Function1, java.lang.Object, java.lang.Object, java.lang.Object, java.lang.Object);
    Code:
       0: aload_0
       1: aload_1
       2: aload_2
       3: aload_3
       4: aload         4
       6: aload         5
       8: aload         6
      10: invokespecial #201                // InterfaceMethod xcoderiving4:(Lscala/Function1;Lscala/Function1;Ljava/lang/Object;Ljava/lang/Object;Ljava/lang/Object;Ljava/lang/Object;)Ljava/lang/Object;
      13: areturn

  public default <Z, A1, A2, A3, A4> F xcoderiving4(scala.Function1<scalaz.$bslash$div<A1, scalaz.$bslash$div<A2, scalaz.$bslash$div<A3, A4>>>, Z>, scala.Function1<Z, scalaz.$bslash$div<A1, scalaz.$bslash$div<A2, scalaz.$bslash$div<A3, A4>>>>, F, F, F, F);
    Code:
       0: aload_0
       1: aload_3
       2: invokedynamic #207,  0            // InvokeDynamic #12:apply:(Ljava/lang/Object;)Lscala/Function0;
       7: aload         4
       9: invokedynamic #212,  0            // InvokeDynamic #13:apply:(Ljava/lang/Object;)Lscala/Function0;
      14: aload         5
      16: invokedynamic #217,  0            // InvokeDynamic #14:apply:(Ljava/lang/Object;)Lscala/Function0;
      21: aload         6
      23: invokedynamic #222,  0            // InvokeDynamic #15:apply:(Ljava/lang/Object;)Lscala/Function0;
      28: aload_1
      29: aload_2
      30: invokeinterface #127,  7          // InterfaceMethod xcoproduct4:(Lscala/Function0;Lscala/Function0;Lscala/Function0;Lscala/Function0;Lscala/Function1;Lscala/Function1;)Ljava/lang/Object;
      35: areturn

  public abstract scalaz.syntax.InvariantAltSyntax<F> invariantAltSyntax();

  public static scalaz.$bslash$div $anonfun$xcoproduct3$1(scalaz.$bslash$div);
    Code:
       0: getstatic     #231                // Field scala/Predef$.MODULE$:Lscala/Predef$;
       3: aload_0
       4: invokevirtual #234                // Method scala/Predef$.identity:(Ljava/lang/Object;)Ljava/lang/Object;
       7: checkcast     #236                // class scalaz/$bslash$div
      10: areturn

  public static scalaz.$bslash$div $anonfun$xcoproduct3$2(scalaz.$bslash$div);
    Code:
       0: getstatic     #231                // Field scala/Predef$.MODULE$:Lscala/Predef$;
       3: aload_0
       4: invokevirtual #234                // Method scala/Predef$.identity:(Ljava/lang/Object;)Ljava/lang/Object;
       7: checkcast     #236                // class scalaz/$bslash$div
      10: areturn

  public static java.lang.Object $anonfun$xcoproduct3$3(java.lang.Object);
    Code:
       0: aload_0
       1: areturn

  public static scalaz.$bslash$div $anonfun$xcoproduct4$1(scalaz.$bslash$div);
    Code:
       0: getstatic     #231                // Field scala/Predef$.MODULE$:Lscala/Predef$;
       3: aload_0
       4: invokevirtual #234                // Method scala/Predef$.identity:(Ljava/lang/Object;)Ljava/lang/Object;
       7: checkcast     #236                // class scalaz/$bslash$div
      10: areturn

  public static scalaz.$bslash$div $anonfun$xcoproduct4$2(scalaz.$bslash$div);
    Code:
       0: getstatic     #231                // Field scala/Predef$.MODULE$:Lscala/Predef$;
       3: aload_0
       4: invokevirtual #234                // Method scala/Predef$.identity:(Ljava/lang/Object;)Ljava/lang/Object;
       7: checkcast     #236                // class scalaz/$bslash$div
      10: areturn

  public static java.lang.Object $anonfun$xcoproduct4$3(java.lang.Object);
    Code:
       0: aload_0
       1: areturn

  public static java.lang.Object $anonfun$xcoderiving1$1(java.lang.Object);
    Code:
       0: aload_0
       1: areturn

  public static java.lang.Object $anonfun$xcoderiving2$1(java.lang.Object);
    Code:
       0: aload_0
       1: areturn

  public static java.lang.Object $anonfun$xcoderiving2$2(java.lang.Object);
    Code:
       0: aload_0
       1: areturn

  public static java.lang.Object $anonfun$xcoderiving3$1(java.lang.Object);
    Code:
       0: aload_0
       1: areturn

  public static java.lang.Object $anonfun$xcoderiving3$2(java.lang.Object);
    Code:
       0: aload_0
       1: areturn

  public static java.lang.Object $anonfun$xcoderiving3$3(java.lang.Object);
    Code:
       0: aload_0
       1: areturn

  public static java.lang.Object $anonfun$xcoderiving4$1(java.lang.Object);
    Code:
       0: aload_0
       1: areturn

  public static java.lang.Object $anonfun$xcoderiving4$2(java.lang.Object);
    Code:
       0: aload_0
       1: areturn

  public static java.lang.Object $anonfun$xcoderiving4$3(java.lang.Object);
    Code:
       0: aload_0
       1: areturn

  public static java.lang.Object $anonfun$xcoderiving4$4(java.lang.Object);
    Code:
       0: aload_0
       1: areturn

  public static void $init$(scalaz.InvariantAlt);
    Code:
       0: aload_0
       1: new           #18                 // class scalaz/InvariantAlt$$anon$1
       4: dup
       5: aload_0
       6: invokespecial #254                // Method scalaz/InvariantAlt$$anon$1."<init>":(Lscalaz/InvariantAlt;)V
       9: invokeinterface #256,  2          // InterfaceMethod scalaz$InvariantAlt$_setter_$invariantAltSyntax_$eq:(Lscalaz/syntax/InvariantAltSyntax;)V
      14: return

  private static java.lang.Object $deserializeLambda$(java.lang.invoke.SerializedLambda);
    Code:
       0: aload_0
       1: invokedynamic #268,  0            // InvokeDynamic #16:lambdaDeserialize:(Ljava/lang/invoke/SerializedLambda;)Ljava/lang/Object;
       6: areturn
}
