Compiled from "Isomorphism.scala"
public interface scalaz.IsomorphismAssociative<F, G> extends scalaz.Associative<F> {
  public abstract scalaz.Associative<G> G();

  public abstract scalaz.Isomorphisms$Iso3<scalaz.BiNaturalTransformation, F, G> iso();

  public static java.lang.Object reassociateLeft$(scalaz.IsomorphismAssociative, java.lang.Object);
    Code:
       0: aload_0
       1: aload_1
       2: invokespecial #35                 // InterfaceMethod reassociateLeft:(Ljava/lang/Object;)Ljava/lang/Object;
       5: areturn

  public default <A, B, C> F reassociateLeft(F);
    Code:
       0: aload_0
       1: invokeinterface #40,  1           // InterfaceMethod iso:()Lscalaz/Isomorphisms$Iso3;
       6: invokeinterface #44,  1           // InterfaceMethod scalaz/Isomorphisms$Iso3.from:()Ljava/lang/Object;
      11: checkcast     #46                 // class scalaz/BiNaturalTransformation
      14: aload_0
      15: invokeinterface #48,  1           // InterfaceMethod G:()Lscalaz/Associative;
      20: checkcast     #50                 // class scalaz/Bifunctor
      23: aload_0
      24: invokeinterface #48,  1           // InterfaceMethod G:()Lscalaz/Associative;
      29: aload_0
      30: invokeinterface #48,  1           // InterfaceMethod G:()Lscalaz/Associative;
      35: checkcast     #50                 // class scalaz/Bifunctor
      38: aload_0
      39: invokeinterface #40,  1           // InterfaceMethod iso:()Lscalaz/Isomorphisms$Iso3;
      44: invokeinterface #53,  1           // InterfaceMethod scalaz/Isomorphisms$Iso3.to:()Ljava/lang/Object;
      49: checkcast     #46                 // class scalaz/BiNaturalTransformation
      52: aload_1
      53: invokeinterface #56,  2           // InterfaceMethod scalaz/BiNaturalTransformation.apply:(Ljava/lang/Object;)Ljava/lang/Object;
      58: aload_0
      59: invokeinterface #40,  1           // InterfaceMethod iso:()Lscalaz/Isomorphisms$Iso3;
      64: invokeinterface #53,  1           // InterfaceMethod scalaz/Isomorphisms$Iso3.to:()Ljava/lang/Object;
      69: checkcast     #46                 // class scalaz/BiNaturalTransformation
      72: invokedynamic #76,  0             // InvokeDynamic #0:apply:(Lscalaz/BiNaturalTransformation;)Lscala/Function1;
      77: invokeinterface #80,  3           // InterfaceMethod scalaz/Bifunctor.rightMap:(Ljava/lang/Object;Lscala/Function1;)Ljava/lang/Object;
      82: invokeinterface #81,  2           // InterfaceMethod scalaz/Associative.reassociateLeft:(Ljava/lang/Object;)Ljava/lang/Object;
      87: aload_0
      88: invokeinterface #40,  1           // InterfaceMethod iso:()Lscalaz/Isomorphisms$Iso3;
      93: invokeinterface #44,  1           // InterfaceMethod scalaz/Isomorphisms$Iso3.from:()Ljava/lang/Object;
      98: checkcast     #46                 // class scalaz/BiNaturalTransformation
     101: invokedynamic #86,  0             // InvokeDynamic #1:apply:(Lscalaz/BiNaturalTransformation;)Lscala/Function1;
     106: invokeinterface #89,  3           // InterfaceMethod scalaz/Bifunctor.leftMap:(Ljava/lang/Object;Lscala/Function1;)Ljava/lang/Object;
     111: invokeinterface #56,  2           // InterfaceMethod scalaz/BiNaturalTransformation.apply:(Ljava/lang/Object;)Ljava/lang/Object;
     116: areturn

  public static java.lang.Object reassociateRight$(scalaz.IsomorphismAssociative, java.lang.Object);
    Code:
       0: aload_0
       1: aload_1
       2: invokespecial #94                 // InterfaceMethod reassociateRight:(Ljava/lang/Object;)Ljava/lang/Object;
       5: areturn

  public default <A, B, C> F reassociateRight(F);
    Code:
       0: aload_0
       1: invokeinterface #40,  1           // InterfaceMethod iso:()Lscalaz/Isomorphisms$Iso3;
       6: invokeinterface #44,  1           // InterfaceMethod scalaz/Isomorphisms$Iso3.from:()Ljava/lang/Object;
      11: checkcast     #46                 // class scalaz/BiNaturalTransformation
      14: aload_0
      15: invokeinterface #48,  1           // InterfaceMethod G:()Lscalaz/Associative;
      20: checkcast     #50                 // class scalaz/Bifunctor
      23: aload_0
      24: invokeinterface #48,  1           // InterfaceMethod G:()Lscalaz/Associative;
      29: aload_0
      30: invokeinterface #48,  1           // InterfaceMethod G:()Lscalaz/Associative;
      35: checkcast     #50                 // class scalaz/Bifunctor
      38: aload_0
      39: invokeinterface #40,  1           // InterfaceMethod iso:()Lscalaz/Isomorphisms$Iso3;
      44: invokeinterface #53,  1           // InterfaceMethod scalaz/Isomorphisms$Iso3.to:()Ljava/lang/Object;
      49: checkcast     #46                 // class scalaz/BiNaturalTransformation
      52: aload_1
      53: invokeinterface #56,  2           // InterfaceMethod scalaz/BiNaturalTransformation.apply:(Ljava/lang/Object;)Ljava/lang/Object;
      58: aload_0
      59: invokeinterface #40,  1           // InterfaceMethod iso:()Lscalaz/Isomorphisms$Iso3;
      64: invokeinterface #53,  1           // InterfaceMethod scalaz/Isomorphisms$Iso3.to:()Ljava/lang/Object;
      69: checkcast     #46                 // class scalaz/BiNaturalTransformation
      72: invokedynamic #99,  0             // InvokeDynamic #2:apply:(Lscalaz/BiNaturalTransformation;)Lscala/Function1;
      77: invokeinterface #89,  3           // InterfaceMethod scalaz/Bifunctor.leftMap:(Ljava/lang/Object;Lscala/Function1;)Ljava/lang/Object;
      82: invokeinterface #100,  2          // InterfaceMethod scalaz/Associative.reassociateRight:(Ljava/lang/Object;)Ljava/lang/Object;
      87: aload_0
      88: invokeinterface #40,  1           // InterfaceMethod iso:()Lscalaz/Isomorphisms$Iso3;
      93: invokeinterface #44,  1           // InterfaceMethod scalaz/Isomorphisms$Iso3.from:()Ljava/lang/Object;
      98: checkcast     #46                 // class scalaz/BiNaturalTransformation
     101: invokedynamic #105,  0            // InvokeDynamic #3:apply:(Lscalaz/BiNaturalTransformation;)Lscala/Function1;
     106: invokeinterface #80,  3           // InterfaceMethod scalaz/Bifunctor.rightMap:(Ljava/lang/Object;Lscala/Function1;)Ljava/lang/Object;
     111: invokeinterface #56,  2           // InterfaceMethod scalaz/BiNaturalTransformation.apply:(Ljava/lang/Object;)Ljava/lang/Object;
     116: areturn

  public static java.lang.Object $anonfun$reassociateLeft$1(scalaz.BiNaturalTransformation, java.lang.Object);
    Code:
       0: aload_0
       1: aload_1
       2: invokeinterface #56,  2           // InterfaceMethod scalaz/BiNaturalTransformation.apply:(Ljava/lang/Object;)Ljava/lang/Object;
       7: areturn

  public static java.lang.Object $anonfun$reassociateLeft$2(scalaz.BiNaturalTransformation, java.lang.Object);
    Code:
       0: aload_0
       1: aload_1
       2: invokeinterface #56,  2           // InterfaceMethod scalaz/BiNaturalTransformation.apply:(Ljava/lang/Object;)Ljava/lang/Object;
       7: areturn

  public static java.lang.Object $anonfun$reassociateRight$1(scalaz.BiNaturalTransformation, java.lang.Object);
    Code:
       0: aload_0
       1: aload_1
       2: invokeinterface #56,  2           // InterfaceMethod scalaz/BiNaturalTransformation.apply:(Ljava/lang/Object;)Ljava/lang/Object;
       7: areturn

  public static java.lang.Object $anonfun$reassociateRight$2(scalaz.BiNaturalTransformation, java.lang.Object);
    Code:
       0: aload_0
       1: aload_1
       2: invokeinterface #56,  2           // InterfaceMethod scalaz/BiNaturalTransformation.apply:(Ljava/lang/Object;)Ljava/lang/Object;
       7: areturn

  public static void $init$(scalaz.IsomorphismAssociative);
    Code:
       0: return

  private static java.lang.Object $deserializeLambda$(java.lang.invoke.SerializedLambda);
    Code:
       0: aload_0
       1: invokedynamic #124,  0            // InvokeDynamic #4:lambdaDeserialize:(Ljava/lang/invoke/SerializedLambda;)Ljava/lang/Object;
       6: areturn
}
