Compiled from "Catchable.scala"
public interface scalaz.IsomorphismCatchable<F, G> extends scalaz.Catchable<F> {
  public abstract scalaz.Catchable<G> G();

  public abstract scalaz.Isomorphisms$Iso2<scalaz.NaturalTransformation, F, G> iso();

  public static java.lang.Object attempt$(scalaz.IsomorphismCatchable, java.lang.Object);
    Code:
       0: aload_0
       1: aload_1
       2: invokespecial #30                 // InterfaceMethod attempt:(Ljava/lang/Object;)Ljava/lang/Object;
       5: areturn

  public default <A> F attempt(F);
    Code:
       0: aload_0
       1: invokeinterface #35,  1           // InterfaceMethod iso:()Lscalaz/Isomorphisms$Iso2;
       6: invokeinterface #39,  1           // InterfaceMethod scalaz/Isomorphisms$Iso2.from:()Ljava/lang/Object;
      11: checkcast     #41                 // class scalaz/NaturalTransformation
      14: aload_0
      15: invokeinterface #43,  1           // InterfaceMethod G:()Lscalaz/Catchable;
      20: aload_0
      21: invokeinterface #35,  1           // InterfaceMethod iso:()Lscalaz/Isomorphisms$Iso2;
      26: invokeinterface #46,  1           // InterfaceMethod scalaz/Isomorphisms$Iso2.to:()Ljava/lang/Object;
      31: checkcast     #41                 // class scalaz/NaturalTransformation
      34: aload_1
      35: invokeinterface #49,  2           // InterfaceMethod scalaz/NaturalTransformation.apply:(Ljava/lang/Object;)Ljava/lang/Object;
      40: invokeinterface #50,  2           // InterfaceMethod scalaz/Catchable.attempt:(Ljava/lang/Object;)Ljava/lang/Object;
      45: invokeinterface #49,  2           // InterfaceMethod scalaz/NaturalTransformation.apply:(Ljava/lang/Object;)Ljava/lang/Object;
      50: areturn

  public static java.lang.Object fail$(scalaz.IsomorphismCatchable, java.lang.Throwable);
    Code:
       0: aload_0
       1: aload_1
       2: invokespecial #58                 // InterfaceMethod fail:(Ljava/lang/Throwable;)Ljava/lang/Object;
       5: areturn

  public default <A> F fail(java.lang.Throwable);
    Code:
       0: aload_0
       1: invokeinterface #35,  1           // InterfaceMethod iso:()Lscalaz/Isomorphisms$Iso2;
       6: invokeinterface #39,  1           // InterfaceMethod scalaz/Isomorphisms$Iso2.from:()Ljava/lang/Object;
      11: checkcast     #41                 // class scalaz/NaturalTransformation
      14: aload_0
      15: invokeinterface #43,  1           // InterfaceMethod G:()Lscalaz/Catchable;
      20: aload_1
      21: invokeinterface #61,  2           // InterfaceMethod scalaz/Catchable.fail:(Ljava/lang/Throwable;)Ljava/lang/Object;
      26: invokeinterface #49,  2           // InterfaceMethod scalaz/NaturalTransformation.apply:(Ljava/lang/Object;)Ljava/lang/Object;
      31: areturn

  public static void $init$(scalaz.IsomorphismCatchable);
    Code:
       0: return
}
