Compiled from "Lens.scala"
public abstract class scalaz.LensFamily<A1, A2, B1, B2> {
  public static <A, B, C> scalaz.LensFamily<scala.Tuple2<A, scalaz.$bslash$div<B, C>>, scala.Tuple2<A, scalaz.$bslash$div<B, C>>, scalaz.$bslash$div<scala.Tuple2<A, B>, scala.Tuple2<A, C>>, scalaz.$bslash$div<scala.Tuple2<A, B>, scala.Tuple2<A, C>>> distributeLens();
    Code:
       0: getstatic     #113                // Field scalaz/LensFamily$.MODULE$:Lscalaz/LensFamily$;
       3: invokevirtual #115                // Method scalaz/LensFamily$.distributeLens:()Lscalaz/LensFamily;
       6: areturn

  public static <A, B, C> scalaz.LensFamily<scalaz.$bslash$div<scala.Tuple2<A, B>, scala.Tuple2<A, C>>, scalaz.$bslash$div<scala.Tuple2<A, B>, scala.Tuple2<A, C>>, scala.Tuple2<A, scalaz.$bslash$div<B, C>>, scala.Tuple2<A, scalaz.$bslash$div<B, C>>> factorLens();
    Code:
       0: getstatic     #113                // Field scalaz/LensFamily$.MODULE$:Lscalaz/LensFamily$;
       3: invokevirtual #119                // Method scalaz/LensFamily$.factorLens:()Lscalaz/LensFamily;
       6: areturn

  public static <A> scalaz.LensFamily<scalaz.IndexedStoreT<java.lang.Object, A, A, java.lang.Object>, scalaz.IndexedStoreT<java.lang.Object, A, A, java.lang.Object>, scalaz.$bslash$div<A, A>, scalaz.$bslash$div<A, A>> predicateLens();
    Code:
       0: getstatic     #113                // Field scalaz/LensFamily$.MODULE$:Lscalaz/LensFamily$;
       3: invokevirtual #123                // Method scalaz/LensFamily$.predicateLens:()Lscalaz/LensFamily;
       6: areturn

  public static <A, B> scalaz.LensFamily<scalaz.IndexedStoreT<java.lang.Object, A, A, B>, scalaz.IndexedStoreT<java.lang.Object, A, A, B>, B, B> applyLens(scala.Function1<B, A>, scalaz.Equal<A>);
    Code:
       0: getstatic     #113                // Field scalaz/LensFamily$.MODULE$:Lscalaz/LensFamily$;
       3: dup
       4: ifnonnull     9
       7: aconst_null
       8: athrow
       9: aload_1
      10: invokedynamic #154,  0            // InvokeDynamic #0:apply:(Lscalaz/Equal;)Lscala/Function1;
      15: invokeinterface #158,  2          // InterfaceMethod scalaz/LensFunctions.lens:(Lscala/Function1;)Lscalaz/LensFamily;
      20: areturn

  public static <A> scalaz.LensFamily<scala.collection.immutable.Set<A>, scala.collection.immutable.Set<A>, java.lang.Object, java.lang.Object> setMembershipLens(A);
    Code:
       0: getstatic     #113                // Field scalaz/LensFamily$.MODULE$:Lscalaz/LensFamily$;
       3: aload_0
       4: invokevirtual #164                // Method scalaz/LensFamily$.setMembershipLens:(Ljava/lang/Object;)Lscalaz/LensFamily;
       7: areturn

  public static <K, V> scalaz.LensFamily<scala.collection.immutable.Map$WithDefault<K, V>, scala.collection.immutable.Map$WithDefault<K, V>, V, V> mapWithDefaultLens(K);
    Code:
       0: getstatic     #113                // Field scalaz/LensFamily$.MODULE$:Lscalaz/LensFamily$;
       3: aload_0
       4: invokevirtual #168                // Method scalaz/LensFamily$.mapWithDefaultLens:(Ljava/lang/Object;)Lscalaz/LensFamily;
       7: areturn

  public static <K, V> scalaz.LensFamily<scala.collection.immutable.Map<K, V>, scala.collection.immutable.Map<K, V>, scala.Option<V>, scala.Option<V>> mapVLens(K);
    Code:
       0: getstatic     #113                // Field scalaz/LensFamily$.MODULE$:Lscalaz/LensFamily$;
       3: aload_0
       4: invokevirtual #172                // Method scalaz/LensFamily$.mapVLens:(Ljava/lang/Object;)Lscalaz/LensFamily;
       7: areturn

  public static <A> scalaz.LensFamily<scalaz.NonEmptyList<A>, scalaz.NonEmptyList<A>, scala.collection.immutable.List<A>, scala.collection.immutable.List<A>> nelTailLens();
    Code:
       0: getstatic     #113                // Field scalaz/LensFamily$.MODULE$:Lscalaz/LensFamily$;
       3: invokevirtual #176                // Method scalaz/LensFamily$.nelTailLens:()Lscalaz/LensFamily;
       6: areturn

  public static <A> scalaz.LensFamily<scalaz.NonEmptyList<A>, scalaz.NonEmptyList<A>, A, A> nelHeadLens();
    Code:
       0: getstatic     #113                // Field scalaz/LensFamily$.MODULE$:Lscalaz/LensFamily$;
       3: invokevirtual #180                // Method scalaz/LensFamily$.nelHeadLens:()Lscalaz/LensFamily;
       6: areturn

  public static <A, B> scalaz.LensFamily<scalaz.LazyTuple2<A, B>, scalaz.LazyTuple2<A, B>, B, B> lazySecondLens();
    Code:
       0: getstatic     #113                // Field scalaz/LensFamily$.MODULE$:Lscalaz/LensFamily$;
       3: invokevirtual #184                // Method scalaz/LensFamily$.lazySecondLens:()Lscalaz/LensFamily;
       6: areturn

  public static <A, B> scalaz.LensFamily<scalaz.LazyTuple2<A, B>, scalaz.LazyTuple2<A, B>, A, A> lazyFirstLens();
    Code:
       0: getstatic     #113                // Field scalaz/LensFamily$.MODULE$:Lscalaz/LensFamily$;
       3: invokevirtual #188                // Method scalaz/LensFamily$.lazyFirstLens:()Lscalaz/LensFamily;
       6: areturn

  public static <A, B> scalaz.LensFamily<scala.Tuple2<A, B>, scala.Tuple2<A, B>, B, B> secondLens();
    Code:
       0: getstatic     #113                // Field scalaz/LensFamily$.MODULE$:Lscalaz/LensFamily$;
       3: invokevirtual #192                // Method scalaz/LensFamily$.secondLens:()Lscalaz/LensFamily;
       6: areturn

  public static <A, B> scalaz.LensFamily<scala.Tuple2<A, B>, scala.Tuple2<A, B>, A, A> firstLens();
    Code:
       0: getstatic     #113                // Field scalaz/LensFamily$.MODULE$:Lscalaz/LensFamily$;
       3: invokevirtual #196                // Method scalaz/LensFamily$.firstLens:()Lscalaz/LensFamily;
       6: areturn

  public static <A> scalaz.LensFamily<scalaz.$bslash$div<A, A>, scalaz.$bslash$div<A, A>, A, A> codiagLens();
    Code:
       0: getstatic     #113                // Field scalaz/LensFamily$.MODULE$:Lscalaz/LensFamily$;
       3: invokevirtual #200                // Method scalaz/LensFamily$.codiagLens:()Lscalaz/LensFamily;
       6: areturn

  public static <A> scalaz.LensFamily<A, A, scala.runtime.BoxedUnit, scala.runtime.BoxedUnit> trivialLens();
    Code:
       0: getstatic     #113                // Field scalaz/LensFamily$.MODULE$:Lscalaz/LensFamily$;
       3: invokevirtual #204                // Method scalaz/LensFamily$.trivialLens:()Lscalaz/LensFamily;
       6: areturn

  public static <A> scalaz.LensFamily<A, A, A, A> lensId();
    Code:
       0: getstatic     #113                // Field scalaz/LensFamily$.MODULE$:Lscalaz/LensFamily$;
       3: invokevirtual #208                // Method scalaz/LensFamily$.lensId:()Lscalaz/LensFamily;
       6: areturn

  public static <A, B> scalaz.LensFamily<A, A, B, B> lensu(scala.Function2<A, B, A>, scala.Function1<A, B>);
    Code:
       0: getstatic     #113                // Field scalaz/LensFamily$.MODULE$:Lscalaz/LensFamily$;
       3: dup
       4: ifnonnull     9
       7: aconst_null
       8: athrow
       9: aload_0
      10: invokeinterface #219,  1          // InterfaceMethod scala/Function2.curried:()Lscala/Function1;
      15: aload_1
      16: invokeinterface #223,  3          // InterfaceMethod scalaz/LensFunctions.lensg:(Lscala/Function1;Lscala/Function1;)Lscalaz/LensFamily;
      21: areturn

  public static <A, B> scalaz.LensFamily<A, A, B, B> lensg(scala.Function1<A, scala.Function1<B, A>>, scala.Function1<A, B>);
    Code:
       0: getstatic     #113                // Field scalaz/LensFamily$.MODULE$:Lscalaz/LensFamily$;
       3: dup
       4: ifnonnull     9
       7: aconst_null
       8: athrow
       9: aload_0
      10: aload_1
      11: invokedynamic #234,  0            // InvokeDynamic #1:apply:(Lscala/Function1;Lscala/Function1;)Lscala/Function1;
      16: invokeinterface #158,  2          // InterfaceMethod scalaz/LensFunctions.lens:(Lscala/Function1;)Lscalaz/LensFamily;
      21: areturn

  public static <A, B> scalaz.LensFamily<A, A, B, B> lens(scala.Function1<A, scalaz.IndexedStoreT<java.lang.Object, B, B, A>>);
    Code:
       0: getstatic     #113                // Field scalaz/LensFamily$.MODULE$:Lscalaz/LensFamily$;
       3: ifnonnull     8
       6: aconst_null
       7: athrow
       8: new           #35                 // class scalaz/LensFunctions$$anon$4
      11: dup
      12: aconst_null
      13: aload_0
      14: invokespecial #240                // Method scalaz/LensFunctions$$anon$4."<init>":(Lscalaz/LensFunctions;Lscala/Function1;)V
      17: areturn

  public static <A1, A2, B1, B2, C1, C2> scalaz.LensFamily<scala.Tuple2<A1, scalaz.$bslash$div<B1, C1>>, scala.Tuple2<A2, scalaz.$bslash$div<B2, C2>>, scalaz.$bslash$div<scala.Tuple2<A1, B1>, scala.Tuple2<A1, C1>>, scalaz.$bslash$div<scala.Tuple2<A2, B2>, scala.Tuple2<A2, C2>>> distributeLensFamily();
    Code:
       0: getstatic     #113                // Field scalaz/LensFamily$.MODULE$:Lscalaz/LensFamily$;
       3: invokevirtual #244                // Method scalaz/LensFamily$.distributeLensFamily:()Lscalaz/LensFamily;
       6: areturn

  public static <A1, A2, B1, B2, C1, C2> scalaz.LensFamily<scalaz.$bslash$div<scala.Tuple2<A1, B1>, scala.Tuple2<A1, C1>>, scalaz.$bslash$div<scala.Tuple2<A2, B2>, scala.Tuple2<A2, C2>>, scala.Tuple2<A1, scalaz.$bslash$div<B1, C1>>, scala.Tuple2<A2, scalaz.$bslash$div<B2, C2>>> factorLensFamily();
    Code:
       0: getstatic     #113                // Field scalaz/LensFamily$.MODULE$:Lscalaz/LensFamily$;
       3: invokevirtual #248                // Method scalaz/LensFamily$.factorLensFamily:()Lscalaz/LensFamily;
       6: areturn

  public static <A1, A2> scalaz.LensFamily<scalaz.IndexedStoreT<java.lang.Object, A1, A1, java.lang.Object>, scalaz.IndexedStoreT<java.lang.Object, A2, A2, java.lang.Object>, scalaz.$bslash$div<A1, A1>, scalaz.$bslash$div<A2, A2>> predicateLensFamily();
    Code:
       0: getstatic     #113                // Field scalaz/LensFamily$.MODULE$:Lscalaz/LensFamily$;
       3: invokevirtual #252                // Method scalaz/LensFamily$.predicateLensFamily:()Lscalaz/LensFamily;
       6: areturn

  public static <A, B1, B2> scalaz.LensFamily<scalaz.LazyTuple2<A, B1>, scalaz.LazyTuple2<A, B2>, B1, B2> lazySecondLensFamily();
    Code:
       0: getstatic     #113                // Field scalaz/LensFamily$.MODULE$:Lscalaz/LensFamily$;
       3: invokevirtual #256                // Method scalaz/LensFamily$.lazySecondLensFamily:()Lscalaz/LensFamily;
       6: areturn

  public static <A1, A2, B> scalaz.LensFamily<scalaz.LazyTuple2<A1, B>, scalaz.LazyTuple2<A2, B>, A1, A2> lazyFirstLensFamily();
    Code:
       0: getstatic     #113                // Field scalaz/LensFamily$.MODULE$:Lscalaz/LensFamily$;
       3: invokevirtual #260                // Method scalaz/LensFamily$.lazyFirstLensFamily:()Lscalaz/LensFamily;
       6: areturn

  public static <A, B1, B2> scalaz.LensFamily<scala.Tuple2<A, B1>, scala.Tuple2<A, B2>, B1, B2> secondLensFamily();
    Code:
       0: getstatic     #113                // Field scalaz/LensFamily$.MODULE$:Lscalaz/LensFamily$;
       3: invokevirtual #264                // Method scalaz/LensFamily$.secondLensFamily:()Lscalaz/LensFamily;
       6: areturn

  public static <A1, A2, B> scalaz.LensFamily<scala.Tuple2<A1, B>, scala.Tuple2<A2, B>, A1, A2> firstLensFamily();
    Code:
       0: getstatic     #113                // Field scalaz/LensFamily$.MODULE$:Lscalaz/LensFamily$;
       3: invokevirtual #268                // Method scalaz/LensFamily$.firstLensFamily:()Lscalaz/LensFamily;
       6: areturn

  public static <A1, A2> scalaz.LensFamily<scalaz.$bslash$div<A1, A1>, scalaz.$bslash$div<A2, A2>, A1, A2> codiagLensFamily();
    Code:
       0: getstatic     #113                // Field scalaz/LensFamily$.MODULE$:Lscalaz/LensFamily$;
       3: invokevirtual #272                // Method scalaz/LensFamily$.codiagLensFamily:()Lscalaz/LensFamily;
       6: areturn

  public static <A1, A2> scalaz.LensFamily<A1, A2, A1, A2> lensFamilyId();
    Code:
       0: getstatic     #113                // Field scalaz/LensFamily$.MODULE$:Lscalaz/LensFamily$;
       3: invokevirtual #276                // Method scalaz/LensFamily$.lensFamilyId:()Lscalaz/LensFamily;
       6: areturn

  public static <A1, A2, B1, B2> scalaz.LensFamily<A1, A2, B1, B2> lensFamilyu(scala.Function2<A1, B2, A2>, scala.Function1<A1, B1>);
    Code:
       0: getstatic     #113                // Field scalaz/LensFamily$.MODULE$:Lscalaz/LensFamily$;
       3: dup
       4: ifnonnull     9
       7: aconst_null
       8: athrow
       9: aload_0
      10: invokeinterface #219,  1          // InterfaceMethod scala/Function2.curried:()Lscala/Function1;
      15: aload_1
      16: invokeinterface #283,  3          // InterfaceMethod scalaz/LensFamilyFunctions.lensFamilyg:(Lscala/Function1;Lscala/Function1;)Lscalaz/LensFamily;
      21: areturn

  public static <A1, A2, B1, B2> scalaz.LensFamily<A1, A2, B1, B2> lensFamilyg(scala.Function1<A1, scala.Function1<B2, A2>>, scala.Function1<A1, B1>);
    Code:
       0: getstatic     #113                // Field scalaz/LensFamily$.MODULE$:Lscalaz/LensFamily$;
       3: dup
       4: ifnonnull     9
       7: aconst_null
       8: athrow
       9: aload_0
      10: aload_1
      11: invokedynamic #289,  0            // InvokeDynamic #2:apply:(Lscala/Function1;Lscala/Function1;)Lscala/Function1;
      16: invokeinterface #292,  2          // InterfaceMethod scalaz/LensFamilyFunctions.lensFamily:(Lscala/Function1;)Lscalaz/LensFamily;
      21: areturn

  public static <A1, A2, B1, B2> scalaz.LensFamily<A1, A2, B1, B2> lensFamily(scala.Function1<A1, scalaz.IndexedStoreT<java.lang.Object, B1, B2, A2>>);
    Code:
       0: getstatic     #113                // Field scalaz/LensFamily$.MODULE$:Lscalaz/LensFamily$;
       3: ifnonnull     8
       6: aconst_null
       7: athrow
       8: new           #33                 // class scalaz/LensFamilyFunctions$$anon$3
      11: dup
      12: aconst_null
      13: aload_0
      14: invokespecial #296                // Method scalaz/LensFamilyFunctions$$anon$3."<init>":(Lscalaz/LensFamilyFunctions;Lscala/Function1;)V
      17: areturn

  public static <S1, S2, A, B, C, D, E, H, I> scala.Tuple7<scalaz.LensFamily<S1, S2, A, A>, scalaz.LensFamily<S1, S2, B, B>, scalaz.LensFamily<S1, S2, C, C>, scalaz.LensFamily<S1, S2, D, D>, scalaz.LensFamily<S1, S2, E, E>, scalaz.LensFamily<S1, S2, H, H>, scalaz.LensFamily<S1, S2, I, I>> tuple7LensFamily(scalaz.LensFamily<S1, S2, scala.Tuple7<A, B, C, D, E, H, I>, scala.Tuple7<A, B, C, D, E, H, I>>);
    Code:
       0: getstatic     #113                // Field scalaz/LensFamily$.MODULE$:Lscalaz/LensFamily$;
       3: aload_0
       4: invokevirtual #301                // Method scalaz/LensFamily$.tuple7LensFamily:(Lscalaz/LensFamily;)Lscala/Tuple7;
       7: areturn

  public static <S1, S2, A, B, C, D, E, H> scala.Tuple6<scalaz.LensFamily<S1, S2, A, A>, scalaz.LensFamily<S1, S2, B, B>, scalaz.LensFamily<S1, S2, C, C>, scalaz.LensFamily<S1, S2, D, D>, scalaz.LensFamily<S1, S2, E, E>, scalaz.LensFamily<S1, S2, H, H>> tuple6LensFamily(scalaz.LensFamily<S1, S2, scala.Tuple6<A, B, C, D, E, H>, scala.Tuple6<A, B, C, D, E, H>>);
    Code:
       0: getstatic     #113                // Field scalaz/LensFamily$.MODULE$:Lscalaz/LensFamily$;
       3: aload_0
       4: invokevirtual #306                // Method scalaz/LensFamily$.tuple6LensFamily:(Lscalaz/LensFamily;)Lscala/Tuple6;
       7: areturn

  public static <S1, S2, A, B, C, D, E> scala.Tuple5<scalaz.LensFamily<S1, S2, A, A>, scalaz.LensFamily<S1, S2, B, B>, scalaz.LensFamily<S1, S2, C, C>, scalaz.LensFamily<S1, S2, D, D>, scalaz.LensFamily<S1, S2, E, E>> tuple5LensFamily(scalaz.LensFamily<S1, S2, scala.Tuple5<A, B, C, D, E>, scala.Tuple5<A, B, C, D, E>>);
    Code:
       0: getstatic     #113                // Field scalaz/LensFamily$.MODULE$:Lscalaz/LensFamily$;
       3: aload_0
       4: invokevirtual #311                // Method scalaz/LensFamily$.tuple5LensFamily:(Lscalaz/LensFamily;)Lscala/Tuple5;
       7: areturn

  public static <S1, S2, A, B, C, D> scala.Tuple4<scalaz.LensFamily<S1, S2, A, A>, scalaz.LensFamily<S1, S2, B, B>, scalaz.LensFamily<S1, S2, C, C>, scalaz.LensFamily<S1, S2, D, D>> tuple4LensFamily(scalaz.LensFamily<S1, S2, scala.Tuple4<A, B, C, D>, scala.Tuple4<A, B, C, D>>);
    Code:
       0: getstatic     #113                // Field scalaz/LensFamily$.MODULE$:Lscalaz/LensFamily$;
       3: aload_0
       4: invokevirtual #316                // Method scalaz/LensFamily$.tuple4LensFamily:(Lscalaz/LensFamily;)Lscala/Tuple4;
       7: areturn

  public static <S1, S2, A, B, C> scala.Tuple3<scalaz.LensFamily<S1, S2, A, A>, scalaz.LensFamily<S1, S2, B, B>, scalaz.LensFamily<S1, S2, C, C>> tuple3LensFamily(scalaz.LensFamily<S1, S2, scala.Tuple3<A, B, C>, scala.Tuple3<A, B, C>>);
    Code:
       0: getstatic     #113                // Field scalaz/LensFamily$.MODULE$:Lscalaz/LensFamily$;
       3: aload_0
       4: invokevirtual #321                // Method scalaz/LensFamily$.tuple3LensFamily:(Lscalaz/LensFamily;)Lscala/Tuple3;
       7: areturn

  public static <S1, S2, A, B> scala.Tuple2<scalaz.LensFamily<S1, S2, A, A>, scalaz.LensFamily<S1, S2, B, B>> tuple2LensFamily(scalaz.LensFamily<S1, S2, scala.Tuple2<A, B>, scala.Tuple2<A, B>>);
    Code:
       0: getstatic     #113                // Field scalaz/LensFamily$.MODULE$:Lscalaz/LensFamily$;
       3: aload_0
       4: invokevirtual #326                // Method scalaz/LensFamily$.tuple2LensFamily:(Lscalaz/LensFamily;)Lscala/Tuple2;
       7: areturn

  public static <S1, S2, I> scalaz.LensInstances$IntegralLensFamily<S1, S2, I> integralLensFamily(scalaz.LensFamily<S1, S2, I, I>, scala.math.Integral<I>);
    Code:
       0: getstatic     #113                // Field scalaz/LensFamily$.MODULE$:Lscalaz/LensFamily$;
       3: aload_0
       4: aload_1
       5: invokevirtual #332                // Method scalaz/LensFamily$.integralLensFamily:(Lscalaz/LensFamily;Lscala/math/Integral;)Lscalaz/LensInstances$IntegralLensFamily;
       8: areturn

  public static scalaz.LensInstances$IntegralLensFamily$ IntegralLensFamily();
    Code:
       0: getstatic     #113                // Field scalaz/LensFamily$.MODULE$:Lscalaz/LensFamily$;
       3: invokevirtual #335                // Method scalaz/LensFamily$.IntegralLensFamily:()Lscalaz/LensInstances$IntegralLensFamily$;
       6: areturn

  public static scalaz.LensInstances$IntegralLensFamily$ IntegralLens();
    Code:
       0: getstatic     #113                // Field scalaz/LensFamily$.MODULE$:Lscalaz/LensFamily$;
       3: invokevirtual #338                // Method scalaz/LensFamily$.IntegralLens:()Lscalaz/LensInstances$IntegralLensFamily$;
       6: areturn

  public static <S1, S2, F> scalaz.LensInstances$FractionalLensFamily<S1, S2, F> fractionalLensFamily(scalaz.LensFamily<S1, S2, F, F>, scala.math.Fractional<F>);
    Code:
       0: getstatic     #113                // Field scalaz/LensFamily$.MODULE$:Lscalaz/LensFamily$;
       3: aload_0
       4: aload_1
       5: invokevirtual #344                // Method scalaz/LensFamily$.fractionalLensFamily:(Lscalaz/LensFamily;Lscala/math/Fractional;)Lscalaz/LensInstances$FractionalLensFamily;
       8: areturn

  public static scalaz.LensInstances$FractionalLensFamily$ FractionalLensFamily();
    Code:
       0: getstatic     #113                // Field scalaz/LensFamily$.MODULE$:Lscalaz/LensFamily$;
       3: invokevirtual #347                // Method scalaz/LensFamily$.FractionalLensFamily:()Lscalaz/LensInstances$FractionalLensFamily$;
       6: areturn

  public static scalaz.LensInstances$FractionalLensFamily$ FractionalLens();
    Code:
       0: getstatic     #113                // Field scalaz/LensFamily$.MODULE$:Lscalaz/LensFamily$;
       3: invokevirtual #350                // Method scalaz/LensFamily$.FractionalLens:()Lscalaz/LensInstances$FractionalLensFamily$;
       6: areturn

  public static <S1, S2, N> scalaz.LensInstances$NumericLensFamily<S1, S2, N> numericLensFamily(scalaz.LensFamily<S1, S2, N, N>, scala.math.Numeric<N>);
    Code:
       0: getstatic     #113                // Field scalaz/LensFamily$.MODULE$:Lscalaz/LensFamily$;
       3: aload_0
       4: aload_1
       5: invokevirtual #356                // Method scalaz/LensFamily$.numericLensFamily:(Lscalaz/LensFamily;Lscala/math/Numeric;)Lscalaz/LensInstances$NumericLensFamily;
       8: areturn

  public static scalaz.LensInstances$NumericLensFamily$ NumericLensFamily();
    Code:
       0: getstatic     #113                // Field scalaz/LensFamily$.MODULE$:Lscalaz/LensFamily$;
       3: invokevirtual #359                // Method scalaz/LensFamily$.NumericLensFamily:()Lscalaz/LensInstances$NumericLensFamily$;
       6: areturn

  public static scalaz.LensInstances$NumericLensFamily$ NumericLens();
    Code:
       0: getstatic     #113                // Field scalaz/LensFamily$.MODULE$:Lscalaz/LensFamily$;
       3: invokevirtual #362                // Method scalaz/LensFamily$.NumericLens:()Lscalaz/LensInstances$NumericLensFamily$;
       6: areturn

  public static <S1, S2, A> scalaz.LensInstances$ArrayLensFamily<S1, S2, A> arrayLensFamily(scalaz.LensFamily<S1, S2, java.lang.Object, java.lang.Object>);
    Code:
       0: getstatic     #113                // Field scalaz/LensFamily$.MODULE$:Lscalaz/LensFamily$;
       3: aload_0
       4: invokevirtual #367                // Method scalaz/LensFamily$.arrayLensFamily:(Lscalaz/LensFamily;)Lscalaz/LensInstances$ArrayLensFamily;
       7: areturn

  public static scalaz.LensInstances$ArrayLensFamily$ ArrayLensFamily();
    Code:
       0: getstatic     #113                // Field scalaz/LensFamily$.MODULE$:Lscalaz/LensFamily$;
       3: invokevirtual #370                // Method scalaz/LensFamily$.ArrayLensFamily:()Lscalaz/LensInstances$ArrayLensFamily$;
       6: areturn

  public static scalaz.LensInstances$ArrayLensFamily$ ArrayLens();
    Code:
       0: getstatic     #113                // Field scalaz/LensFamily$.MODULE$:Lscalaz/LensFamily$;
       3: invokevirtual #373                // Method scalaz/LensFamily$.ArrayLens:()Lscalaz/LensInstances$ArrayLensFamily$;
       6: areturn

  public static <S1, S2, A> scalaz.LensInstances$QueueLensFamily<S1, S2, A> queueLensFamily(scalaz.LensFamily<S1, S2, scala.collection.immutable.Queue<A>, scala.collection.immutable.Queue<A>>);
    Code:
       0: getstatic     #113                // Field scalaz/LensFamily$.MODULE$:Lscalaz/LensFamily$;
       3: aload_0
       4: invokevirtual #378                // Method scalaz/LensFamily$.queueLensFamily:(Lscalaz/LensFamily;)Lscalaz/LensInstances$QueueLensFamily;
       7: areturn

  public static scalaz.LensInstances$QueueLensFamily$ QueueLensFamily();
    Code:
       0: getstatic     #113                // Field scalaz/LensFamily$.MODULE$:Lscalaz/LensFamily$;
       3: invokevirtual #381                // Method scalaz/LensFamily$.QueueLensFamily:()Lscalaz/LensInstances$QueueLensFamily$;
       6: areturn

  public static scalaz.LensInstances$QueueLensFamily$ QueueLens();
    Code:
       0: getstatic     #113                // Field scalaz/LensFamily$.MODULE$:Lscalaz/LensFamily$;
       3: invokevirtual #384                // Method scalaz/LensFamily$.QueueLens:()Lscalaz/LensInstances$QueueLensFamily$;
       6: areturn

  public static <S1, S2, A> scalaz.LensInstances$SeqLikeLensFamily<S1, S2, A, scala.collection.immutable.Seq<A>> seqLensFamily(scalaz.LensFamily<S1, S2, scala.collection.immutable.Seq<A>, scala.collection.immutable.Seq<A>>);
    Code:
       0: getstatic     #113                // Field scalaz/LensFamily$.MODULE$:Lscalaz/LensFamily$;
       3: aload_0
       4: invokevirtual #389                // Method scalaz/LensFamily$.seqLensFamily:(Lscalaz/LensFamily;)Lscalaz/LensInstances$SeqLikeLensFamily;
       7: areturn

  public static scalaz.LensInstances$SeqLikeLensFamily$ SeqLikeLensFamily();
    Code:
       0: getstatic     #113                // Field scalaz/LensFamily$.MODULE$:Lscalaz/LensFamily$;
       3: invokevirtual #392                // Method scalaz/LensFamily$.SeqLikeLensFamily:()Lscalaz/LensInstances$SeqLikeLensFamily$;
       6: areturn

  public static scalaz.LensInstances$SeqLikeLensFamily$ SeqLikeLens();
    Code:
       0: getstatic     #113                // Field scalaz/LensFamily$.MODULE$:Lscalaz/LensFamily$;
       3: invokevirtual #395                // Method scalaz/LensFamily$.SeqLikeLens:()Lscalaz/LensInstances$SeqLikeLensFamily$;
       6: areturn

  public static <S1, S2, K, V> scalaz.LensInstances$MapLensFamily<S1, S2, K, V> mapLensFamily(scalaz.LensFamily<S1, S2, scala.collection.immutable.Map<K, V>, scala.collection.immutable.Map<K, V>>);
    Code:
       0: getstatic     #113                // Field scalaz/LensFamily$.MODULE$:Lscalaz/LensFamily$;
       3: aload_0
       4: invokevirtual #400                // Method scalaz/LensFamily$.mapLensFamily:(Lscalaz/LensFamily;)Lscalaz/LensInstances$MapLensFamily;
       7: areturn

  public static scalaz.LensInstances$MapLensFamily$ MapLensFamily();
    Code:
       0: getstatic     #113                // Field scalaz/LensFamily$.MODULE$:Lscalaz/LensFamily$;
       3: invokevirtual #403                // Method scalaz/LensFamily$.MapLensFamily:()Lscalaz/LensInstances$MapLensFamily$;
       6: areturn

  public static scalaz.LensInstances$MapLensFamily$ MapLens();
    Code:
       0: getstatic     #113                // Field scalaz/LensFamily$.MODULE$:Lscalaz/LensFamily$;
       3: invokevirtual #406                // Method scalaz/LensFamily$.MapLens:()Lscalaz/LensInstances$MapLensFamily$;
       6: areturn

  public static <S1, S2, K> scalaz.LensInstances$SetLensFamily<S1, S2, K> setLensFamily(scalaz.LensFamily<S1, S2, scala.collection.immutable.Set<K>, scala.collection.immutable.Set<K>>);
    Code:
       0: getstatic     #113                // Field scalaz/LensFamily$.MODULE$:Lscalaz/LensFamily$;
       3: aload_0
       4: invokevirtual #411                // Method scalaz/LensFamily$.setLensFamily:(Lscalaz/LensFamily;)Lscalaz/LensInstances$SetLensFamily;
       7: areturn

  public static scalaz.LensInstances$SetLensFamily$ SetLensFamily();
    Code:
       0: getstatic     #113                // Field scalaz/LensFamily$.MODULE$:Lscalaz/LensFamily$;
       3: invokevirtual #414                // Method scalaz/LensFamily$.SetLensFamily:()Lscalaz/LensInstances$SetLensFamily$;
       6: areturn

  public static scalaz.LensInstances$SetLensFamily$ SetLens();
    Code:
       0: getstatic     #113                // Field scalaz/LensFamily$.MODULE$:Lscalaz/LensFamily$;
       3: invokevirtual #417                // Method scalaz/LensFamily$.SetLens:()Lscalaz/LensInstances$SetLensFamily$;
       6: areturn

  public static <S, R> scalaz.Unzip<?> LensFamilyUnzip();
    Code:
       0: getstatic     #113                // Field scalaz/LensFamily$.MODULE$:Lscalaz/LensFamily$;
       3: invokevirtual #422                // Method scalaz/LensFamily$.LensFamilyUnzip:()Lscalaz/Unzip;
       6: areturn

  public static <A, B> scalaz.IndexedStateT<A, A, java.lang.Object, B> LensFamilyState(scalaz.LensFamily<A, ?, B, ?>);
    Code:
       0: getstatic     #113                // Field scalaz/LensFamily$.MODULE$:Lscalaz/LensFamily$;
       3: aload_0
       4: invokevirtual #427                // Method scalaz/LensFamily$.LensFamilyState:(Lscalaz/LensFamily;)Lscalaz/IndexedStateT;
       7: areturn

  public static scalaz.LensCategory lensCategory();
    Code:
       0: getstatic     #113                // Field scalaz/LensFamily$.MODULE$:Lscalaz/LensFamily$;
       3: invokevirtual #431                // Method scalaz/LensFamily$.lensCategory:()Lscalaz/LensCategory;
       6: areturn

  public static <S1, S2, A, Repr extends scala.collection.SeqLike<A, Repr>> scalaz.LensInstances$SeqLikeLensFamily<S1, S2, A, Repr> seqLikeLensFamily(scalaz.LensFamily<S1, S2, Repr, Repr>);
    Code:
       0: getstatic     #113                // Field scalaz/LensFamily$.MODULE$:Lscalaz/LensFamily$;
       3: aload_0
       4: invokevirtual #435                // Method scalaz/LensFamily$.seqLikeLensFamily:(Lscalaz/LensFamily;)Lscalaz/LensInstances$SeqLikeLensFamily;
       7: areturn

  public abstract scalaz.IndexedStoreT<java.lang.Object, B1, B2, A2> run(A1);

  public scalaz.IndexedStoreT<java.lang.Object, B1, B2, A2> apply(A1);
    Code:
       0: aload_0
       1: aload_1
       2: invokevirtual #439                // Method run:(Ljava/lang/Object;)Lscalaz/IndexedStoreT;
       5: areturn

  public <X1, X2> scalaz.LensFamily<X1, X2, B1, B2> xmapA(scala.Function1<A2, X2>, scala.Function1<X1, A1>);
    Code:
       0: getstatic     #113                // Field scalaz/LensFamily$.MODULE$:Lscalaz/LensFamily$;
       3: aload_0
       4: aload_2
       5: aload_1
       6: invokedynamic #454,  0            // InvokeDynamic #3:apply:(Lscalaz/LensFamily;Lscala/Function1;Lscala/Function1;)Lscala/Function1;
      11: astore_3
      12: ifnonnull     17
      15: aconst_null
      16: athrow
      17: new           #33                 // class scalaz/LensFamilyFunctions$$anon$3
      20: dup
      21: aconst_null
      22: aload_3
      23: invokespecial #296                // Method scalaz/LensFamilyFunctions$$anon$3."<init>":(Lscalaz/LensFamilyFunctions;Lscala/Function1;)V
      26: areturn

  public <X, A extends A1> scalaz.LensFamily<X, X, B1, B2> xmapbA(scalaz.BijectionT<java.lang.Object, java.lang.Object, A, X>);
    Code:
       0: aload_1
       1: invokedynamic #471,  0            // InvokeDynamic #4:apply:(Lscalaz/BijectionT;)Lscala/Function1;
       6: aload_1
       7: invokedynamic #476,  0            // InvokeDynamic #5:apply:(Lscalaz/BijectionT;)Lscala/Function1;
      12: astore_3
      13: astore_2
      14: getstatic     #113                // Field scalaz/LensFamily$.MODULE$:Lscalaz/LensFamily$;
      17: aload_0
      18: aload_3
      19: aload_2
      20: invokedynamic #454,  0            // InvokeDynamic #3:apply:(Lscalaz/LensFamily;Lscala/Function1;Lscala/Function1;)Lscala/Function1;
      25: astore        4
      27: ifnonnull     32
      30: aconst_null
      31: athrow
      32: new           #33                 // class scalaz/LensFamilyFunctions$$anon$3
      35: dup
      36: aconst_null
      37: aload         4
      39: invokespecial #296                // Method scalaz/LensFamilyFunctions$$anon$3."<init>":(Lscalaz/LensFamilyFunctions;Lscala/Function1;)V
      42: areturn

  public <X1, X2> scalaz.LensFamily<A1, A2, X1, X2> xmapB(scala.Function1<B1, X1>, scala.Function1<X2, B2>);
    Code:
       0: getstatic     #113                // Field scalaz/LensFamily$.MODULE$:Lscalaz/LensFamily$;
       3: aload_0
       4: aload_1
       5: aload_2
       6: invokedynamic #487,  0            // InvokeDynamic #6:apply:(Lscalaz/LensFamily;Lscala/Function1;Lscala/Function1;)Lscala/Function1;
      11: astore_3
      12: ifnonnull     17
      15: aconst_null
      16: athrow
      17: new           #33                 // class scalaz/LensFamilyFunctions$$anon$3
      20: dup
      21: aconst_null
      22: aload_3
      23: invokespecial #296                // Method scalaz/LensFamilyFunctions$$anon$3."<init>":(Lscalaz/LensFamilyFunctions;Lscala/Function1;)V
      26: areturn

  public <X, B extends B2> scalaz.LensFamily<A1, A2, X, X> xmapbB(scalaz.BijectionT<java.lang.Object, java.lang.Object, B, X>);
    Code:
       0: aload_1
       1: invokedynamic #494,  0            // InvokeDynamic #7:apply:(Lscalaz/BijectionT;)Lscala/Function1;
       6: aload_1
       7: invokedynamic #499,  0            // InvokeDynamic #8:apply:(Lscalaz/BijectionT;)Lscala/Function1;
      12: astore_3
      13: astore_2
      14: getstatic     #113                // Field scalaz/LensFamily$.MODULE$:Lscalaz/LensFamily$;
      17: aload_0
      18: aload_2
      19: aload_3
      20: invokedynamic #487,  0            // InvokeDynamic #6:apply:(Lscalaz/LensFamily;Lscala/Function1;Lscala/Function1;)Lscala/Function1;
      25: astore        4
      27: ifnonnull     32
      30: aconst_null
      31: athrow
      32: new           #33                 // class scalaz/LensFamilyFunctions$$anon$3
      35: dup
      36: aconst_null
      37: aload         4
      39: invokespecial #296                // Method scalaz/LensFamilyFunctions$$anon$3."<init>":(Lscalaz/LensFamilyFunctions;Lscala/Function1;)V
      42: areturn

  public B1 get(A1);
    Code:
       0: aload_0
       1: aload_1
       2: invokevirtual #439                // Method run:(Ljava/lang/Object;)Lscalaz/IndexedStoreT;
       5: invokevirtual #509                // Method scalaz/IndexedStoreT.pos:()Ljava/lang/Object;
       8: areturn

  public A2 set(A1, B2);
    Code:
       0: aload_0
       1: aload_1
       2: invokevirtual #439                // Method run:(Ljava/lang/Object;)Lscalaz/IndexedStoreT;
       5: aload_2
       6: getstatic     #516                // Field scalaz/package$.MODULE$:Lscalaz/package$;
       9: invokevirtual #520                // Method scalaz/package$.idInstance:()Lscalaz/Traverse1;
      12: invokevirtual #524                // Method scalaz/IndexedStoreT.put:(Ljava/lang/Object;Lscalaz/Functor;)Ljava/lang/Object;
      15: areturn

  public <X> X setf(A1, X, scalaz.Functor<X>);
    Code:
       0: aload_0
       1: aload_1
       2: invokevirtual #439                // Method run:(Ljava/lang/Object;)Lscalaz/IndexedStoreT;
       5: aload_2
       6: getstatic     #516                // Field scalaz/package$.MODULE$:Lscalaz/package$;
       9: invokevirtual #520                // Method scalaz/package$.idInstance:()Lscalaz/Traverse1;
      12: aload_3
      13: invokevirtual #532                // Method scalaz/IndexedStoreT.putf:(Ljava/lang/Object;Lscalaz/Functor;Lscalaz/Functor;)Ljava/lang/Object;
      16: areturn

  public scalaz.IndexedStateT<A1, A1, java.lang.Object, B1> st();
    Code:
       0: getstatic     #539                // Field scalaz/package$State$.MODULE$:Lscalaz/package$State$;
       3: aload_0
       4: invokedynamic #549,  0            // InvokeDynamic #9:apply:(Lscalaz/LensFamily;)Lscala/Function1;
       9: astore_1
      10: ifnonnull     15
      13: aconst_null
      14: athrow
      15: getstatic     #552                // Field scalaz/package$StateT$.MODULE$:Lscalaz/package$StateT$;
      18: ifnonnull     23
      21: aconst_null
      22: athrow
      23: getstatic     #557                // Field scalaz/IndexedStateT$.MODULE$:Lscalaz/IndexedStateT$;
      26: ifnonnull     31
      29: aconst_null
      30: athrow
      31: new           #21                 // class scalaz/IndexedStateT$Wrap
      34: dup
      35: aload_1
      36: invokespecial #560                // Method scalaz/IndexedStateT$Wrap."<init>":(Lscala/Function1;)V
      39: areturn

  public A2 mod(scala.Function1<B1, B2>, A1);
    Code:
       0: aload_0
       1: aload_2
       2: invokevirtual #439                // Method run:(Ljava/lang/Object;)Lscalaz/IndexedStoreT;
       5: getstatic     #516                // Field scalaz/package$.MODULE$:Lscalaz/package$;
       8: invokevirtual #520                // Method scalaz/package$.idInstance:()Lscalaz/Traverse1;
      11: astore        4
      13: dup
      14: ifnonnull     19
      17: aconst_null
      18: athrow
      19: astore_3
      20: aload_3
      21: aload_1
      22: aload_3
      23: invokevirtual #509                // Method scalaz/IndexedStoreT.pos:()Ljava/lang/Object;
      26: invokeinterface #566,  2          // InterfaceMethod scala/Function1.apply:(Ljava/lang/Object;)Ljava/lang/Object;
      31: aload         4
      33: invokevirtual #524                // Method scalaz/IndexedStoreT.put:(Ljava/lang/Object;Lscalaz/Functor;)Ljava/lang/Object;
      36: areturn

  public scala.Function1<A1, A2> $eq$greater$eq(scala.Function1<B1, B2>);
    Code:
       0: aload_0
       1: aload_1
       2: invokedynamic #582,  0            // InvokeDynamic #10:apply:(Lscalaz/LensFamily;Lscala/Function1;)Lscala/Function1;
       7: areturn

  public <X> X modf(scala.Function1<B1, X>, A1, scalaz.Functor<X>);
    Code:
       0: aload_0
       1: aload_2
       2: invokevirtual #439                // Method run:(Ljava/lang/Object;)Lscalaz/IndexedStoreT;
       5: getstatic     #516                // Field scalaz/package$.MODULE$:Lscalaz/package$;
       8: invokevirtual #520                // Method scalaz/package$.idInstance:()Lscalaz/Traverse1;
      11: astore        5
      13: dup
      14: ifnonnull     19
      17: aconst_null
      18: athrow
      19: astore        4
      21: aload         4
      23: aload_1
      24: aload         4
      26: invokevirtual #509                // Method scalaz/IndexedStoreT.pos:()Ljava/lang/Object;
      29: invokeinterface #566,  2          // InterfaceMethod scala/Function1.apply:(Ljava/lang/Object;)Ljava/lang/Object;
      34: aload         5
      36: aload_3
      37: invokevirtual #532                // Method scalaz/IndexedStoreT.putf:(Ljava/lang/Object;Lscalaz/Functor;Lscalaz/Functor;)Ljava/lang/Object;
      40: areturn

  public <X> scala.Function1<A1, X> $eq$greater$greater$eq(scala.Function1<B1, X>, scalaz.Functor<X>);
    Code:
       0: aload_0
       1: aload_1
       2: aload_2
       3: invokedynamic #600,  0            // InvokeDynamic #11:apply:(Lscalaz/LensFamily;Lscala/Function1;Lscalaz/Functor;)Lscala/Function1;
       8: areturn

  public <C> scala.Tuple2<A2, C> modp(scala.Function1<B1, scala.Tuple2<B2, C>>, A1);
    Code:
       0: aload_1
       1: aload_0
       2: aload_2
       3: invokevirtual #605                // Method get:(Ljava/lang/Object;)Ljava/lang/Object;
       6: invokeinterface #566,  2          // InterfaceMethod scala/Function1.apply:(Ljava/lang/Object;)Ljava/lang/Object;
      11: checkcast     #607                // class scala/Tuple2
      14: astore_3
      15: aload_3
      16: ifnull        34
      19: aload_3
      20: invokevirtual #610                // Method scala/Tuple2._1:()Ljava/lang/Object;
      23: astore        4
      25: aload_3
      26: invokevirtual #613                // Method scala/Tuple2._2:()Ljava/lang/Object;
      29: astore        5
      31: goto          43
      34: new           #615                // class scala/MatchError
      37: dup
      38: aload_3
      39: invokespecial #618                // Method scala/MatchError."<init>":(Ljava/lang/Object;)V
      42: athrow
      43: new           #607                // class scala/Tuple2
      46: dup
      47: aload_0
      48: aload_2
      49: aload         4
      51: invokevirtual #620                // Method set:(Ljava/lang/Object;Ljava/lang/Object;)Ljava/lang/Object;
      54: aload         5
      56: invokespecial #623                // Method scala/Tuple2."<init>":(Ljava/lang/Object;Ljava/lang/Object;)V
      59: areturn

  public scalaz.IndexedStateT<A1, A2, java.lang.Object, B2> mods(scala.Function1<B1, B2>);
    Code:
       0: getstatic     #630                // Field scalaz/package$IndexedState$.MODULE$:Lscalaz/package$IndexedState$;
       3: aload_0
       4: aload_1
       5: invokedynamic #636,  0            // InvokeDynamic #12:apply:(Lscalaz/LensFamily;Lscala/Function1;)Lscala/Function1;
      10: astore_2
      11: ifnonnull     16
      14: aconst_null
      15: athrow
      16: getstatic     #557                // Field scalaz/IndexedStateT$.MODULE$:Lscalaz/IndexedStateT$;
      19: ifnonnull     24
      22: aconst_null
      23: athrow
      24: new           #21                 // class scalaz/IndexedStateT$Wrap
      27: dup
      28: aload_2
      29: invokespecial #560                // Method scalaz/IndexedStateT$Wrap."<init>":(Lscala/Function1;)V
      32: areturn

  public scalaz.IndexedStateT<A1, A2, java.lang.Object, B2> $percent$eq(scala.Function1<B1, B2>);
    Code:
       0: getstatic     #630                // Field scalaz/package$IndexedState$.MODULE$:Lscalaz/package$IndexedState$;
       3: aload_0
       4: aload_1
       5: invokedynamic #636,  0            // InvokeDynamic #12:apply:(Lscalaz/LensFamily;Lscala/Function1;)Lscala/Function1;
      10: astore_2
      11: ifnonnull     16
      14: aconst_null
      15: athrow
      16: getstatic     #557                // Field scalaz/IndexedStateT$.MODULE$:Lscalaz/IndexedStateT$;
      19: ifnonnull     24
      22: aconst_null
      23: athrow
      24: new           #21                 // class scalaz/IndexedStateT$Wrap
      27: dup
      28: aload_2
      29: invokespecial #560                // Method scalaz/IndexedStateT$Wrap."<init>":(Lscala/Function1;)V
      32: areturn

  public scalaz.IndexedStateT<A1, A2, java.lang.Object, B1> modo(scala.Function1<B1, B2>);
    Code:
       0: getstatic     #630                // Field scalaz/package$IndexedState$.MODULE$:Lscalaz/package$IndexedState$;
       3: aload_0
       4: aload_1
       5: invokedynamic #645,  0            // InvokeDynamic #13:apply:(Lscalaz/LensFamily;Lscala/Function1;)Lscala/Function1;
      10: astore_2
      11: ifnonnull     16
      14: aconst_null
      15: athrow
      16: getstatic     #557                // Field scalaz/IndexedStateT$.MODULE$:Lscalaz/IndexedStateT$;
      19: ifnonnull     24
      22: aconst_null
      23: athrow
      24: new           #21                 // class scalaz/IndexedStateT$Wrap
      27: dup
      28: aload_2
      29: invokespecial #560                // Method scalaz/IndexedStateT$Wrap."<init>":(Lscala/Function1;)V
      32: areturn

  public scalaz.IndexedStateT<A1, A2, java.lang.Object, B1> $less$percent$eq(scala.Function1<B1, B2>);
    Code:
       0: getstatic     #630                // Field scalaz/package$IndexedState$.MODULE$:Lscalaz/package$IndexedState$;
       3: aload_0
       4: aload_1
       5: invokedynamic #645,  0            // InvokeDynamic #13:apply:(Lscalaz/LensFamily;Lscala/Function1;)Lscala/Function1;
      10: astore_2
      11: ifnonnull     16
      14: aconst_null
      15: athrow
      16: getstatic     #557                // Field scalaz/IndexedStateT$.MODULE$:Lscalaz/IndexedStateT$;
      19: ifnonnull     24
      22: aconst_null
      23: athrow
      24: new           #21                 // class scalaz/IndexedStateT$Wrap
      27: dup
      28: aload_2
      29: invokespecial #560                // Method scalaz/IndexedStateT$Wrap."<init>":(Lscala/Function1;)V
      32: areturn

  public scalaz.IndexedStateT<A1, A2, java.lang.Object, B2> assign(scala.Function0<B2>);
    Code:
       0: aload_1
       1: invokedynamic #658,  0            // InvokeDynamic #14:apply:(Lscala/Function0;)Lscala/Function1;
       6: astore_2
       7: getstatic     #630                // Field scalaz/package$IndexedState$.MODULE$:Lscalaz/package$IndexedState$;
      10: aload_0
      11: aload_2
      12: invokedynamic #636,  0            // InvokeDynamic #12:apply:(Lscalaz/LensFamily;Lscala/Function1;)Lscala/Function1;
      17: astore_3
      18: ifnonnull     23
      21: aconst_null
      22: athrow
      23: getstatic     #557                // Field scalaz/IndexedStateT$.MODULE$:Lscalaz/IndexedStateT$;
      26: ifnonnull     31
      29: aconst_null
      30: athrow
      31: new           #21                 // class scalaz/IndexedStateT$Wrap
      34: dup
      35: aload_3
      36: invokespecial #560                // Method scalaz/IndexedStateT$Wrap."<init>":(Lscala/Function1;)V
      39: areturn

  public scalaz.IndexedStateT<A1, A2, java.lang.Object, B2> $colon$eq(scala.Function0<B2>);
    Code:
       0: aload_1
       1: invokedynamic #658,  0            // InvokeDynamic #14:apply:(Lscala/Function0;)Lscala/Function1;
       6: astore_2
       7: getstatic     #630                // Field scalaz/package$IndexedState$.MODULE$:Lscalaz/package$IndexedState$;
      10: aload_0
      11: aload_2
      12: invokedynamic #636,  0            // InvokeDynamic #12:apply:(Lscalaz/LensFamily;Lscala/Function1;)Lscala/Function1;
      17: astore_3
      18: ifnonnull     23
      21: aconst_null
      22: athrow
      23: getstatic     #557                // Field scalaz/IndexedStateT$.MODULE$:Lscalaz/IndexedStateT$;
      26: ifnonnull     31
      29: aconst_null
      30: athrow
      31: new           #21                 // class scalaz/IndexedStateT$Wrap
      34: dup
      35: aload_3
      36: invokespecial #560                // Method scalaz/IndexedStateT$Wrap."<init>":(Lscala/Function1;)V
      39: areturn

  public scalaz.IndexedStateT<A1, A2, java.lang.Object, B1> assigno(scala.Function0<B2>);
    Code:
       0: aload_1
       1: invokedynamic #670,  0            // InvokeDynamic #15:apply:(Lscala/Function0;)Lscala/Function1;
       6: astore_2
       7: getstatic     #630                // Field scalaz/package$IndexedState$.MODULE$:Lscalaz/package$IndexedState$;
      10: aload_0
      11: aload_2
      12: invokedynamic #645,  0            // InvokeDynamic #13:apply:(Lscalaz/LensFamily;Lscala/Function1;)Lscala/Function1;
      17: astore_3
      18: ifnonnull     23
      21: aconst_null
      22: athrow
      23: getstatic     #557                // Field scalaz/IndexedStateT$.MODULE$:Lscalaz/IndexedStateT$;
      26: ifnonnull     31
      29: aconst_null
      30: athrow
      31: new           #21                 // class scalaz/IndexedStateT$Wrap
      34: dup
      35: aload_3
      36: invokespecial #560                // Method scalaz/IndexedStateT$Wrap."<init>":(Lscala/Function1;)V
      39: areturn

  public scalaz.IndexedStateT<A1, A2, java.lang.Object, B1> $less$colon$eq(scala.Function0<B2>);
    Code:
       0: aload_1
       1: invokedynamic #670,  0            // InvokeDynamic #15:apply:(Lscala/Function0;)Lscala/Function1;
       6: astore_2
       7: getstatic     #630                // Field scalaz/package$IndexedState$.MODULE$:Lscalaz/package$IndexedState$;
      10: aload_0
      11: aload_2
      12: invokedynamic #645,  0            // InvokeDynamic #13:apply:(Lscalaz/LensFamily;Lscala/Function1;)Lscala/Function1;
      17: astore_3
      18: ifnonnull     23
      21: aconst_null
      22: athrow
      23: getstatic     #557                // Field scalaz/IndexedStateT$.MODULE$:Lscalaz/IndexedStateT$;
      26: ifnonnull     31
      29: aconst_null
      30: athrow
      31: new           #21                 // class scalaz/IndexedStateT$Wrap
      34: dup
      35: aload_3
      36: invokespecial #560                // Method scalaz/IndexedStateT$Wrap."<init>":(Lscala/Function1;)V
      39: areturn

  public scalaz.IndexedStateT<A1, A2, java.lang.Object, scala.runtime.BoxedUnit> mods_(scala.Function1<B1, B2>);
    Code:
       0: getstatic     #630                // Field scalaz/package$IndexedState$.MODULE$:Lscalaz/package$IndexedState$;
       3: aload_0
       4: aload_1
       5: invokedynamic #681,  0            // InvokeDynamic #16:apply:(Lscalaz/LensFamily;Lscala/Function1;)Lscala/Function1;
      10: astore_2
      11: ifnonnull     16
      14: aconst_null
      15: athrow
      16: getstatic     #557                // Field scalaz/IndexedStateT$.MODULE$:Lscalaz/IndexedStateT$;
      19: ifnonnull     24
      22: aconst_null
      23: athrow
      24: new           #21                 // class scalaz/IndexedStateT$Wrap
      27: dup
      28: aload_2
      29: invokespecial #560                // Method scalaz/IndexedStateT$Wrap."<init>":(Lscala/Function1;)V
      32: areturn

  public scalaz.IndexedStateT<A1, A2, java.lang.Object, scala.runtime.BoxedUnit> $percent$eq$eq(scala.Function1<B1, B2>);
    Code:
       0: getstatic     #630                // Field scalaz/package$IndexedState$.MODULE$:Lscalaz/package$IndexedState$;
       3: aload_0
       4: aload_1
       5: invokedynamic #681,  0            // InvokeDynamic #16:apply:(Lscalaz/LensFamily;Lscala/Function1;)Lscala/Function1;
      10: astore_2
      11: ifnonnull     16
      14: aconst_null
      15: athrow
      16: getstatic     #557                // Field scalaz/IndexedStateT$.MODULE$:Lscalaz/IndexedStateT$;
      19: ifnonnull     24
      22: aconst_null
      23: athrow
      24: new           #21                 // class scalaz/IndexedStateT$Wrap
      27: dup
      28: aload_2
      29: invokespecial #560                // Method scalaz/IndexedStateT$Wrap."<init>":(Lscala/Function1;)V
      32: areturn

  public <C> scalaz.IndexedStateT<A1, A2, java.lang.Object, C> lifts(scalaz.IndexedStateT<B1, B2, java.lang.Object, C>);
    Code:
       0: getstatic     #630                // Field scalaz/package$IndexedState$.MODULE$:Lscalaz/package$IndexedState$;
       3: aload_0
       4: aload_1
       5: invokedynamic #695,  0            // InvokeDynamic #17:apply:(Lscalaz/LensFamily;Lscalaz/IndexedStateT;)Lscala/Function1;
      10: astore_2
      11: ifnonnull     16
      14: aconst_null
      15: athrow
      16: getstatic     #557                // Field scalaz/IndexedStateT$.MODULE$:Lscalaz/IndexedStateT$;
      19: ifnonnull     24
      22: aconst_null
      23: athrow
      24: new           #21                 // class scalaz/IndexedStateT$Wrap
      27: dup
      28: aload_2
      29: invokespecial #560                // Method scalaz/IndexedStateT$Wrap."<init>":(Lscala/Function1;)V
      32: areturn

  public <C> scalaz.IndexedStateT<A1, A2, java.lang.Object, C> $percent$percent$eq(scalaz.IndexedStateT<B1, B2, java.lang.Object, C>);
    Code:
       0: aload_0
       1: aload_1
       2: invokevirtual #699                // Method lifts:(Lscalaz/IndexedStateT;)Lscalaz/IndexedStateT;
       5: areturn

  public <C> scalaz.IndexedStateT<A1, A1, java.lang.Object, C> map(scala.Function1<B1, C>);
    Code:
       0: getstatic     #539                // Field scalaz/package$State$.MODULE$:Lscalaz/package$State$;
       3: aload_0
       4: aload_1
       5: invokedynamic #706,  0            // InvokeDynamic #18:apply:(Lscalaz/LensFamily;Lscala/Function1;)Lscala/Function1;
      10: astore_2
      11: ifnonnull     16
      14: aconst_null
      15: athrow
      16: getstatic     #552                // Field scalaz/package$StateT$.MODULE$:Lscalaz/package$StateT$;
      19: ifnonnull     24
      22: aconst_null
      23: athrow
      24: getstatic     #557                // Field scalaz/IndexedStateT$.MODULE$:Lscalaz/IndexedStateT$;
      27: ifnonnull     32
      30: aconst_null
      31: athrow
      32: new           #21                 // class scalaz/IndexedStateT$Wrap
      35: dup
      36: aload_2
      37: invokespecial #560                // Method scalaz/IndexedStateT$Wrap."<init>":(Lscala/Function1;)V
      40: areturn

  public <C> scalaz.IndexedStateT<A1, A1, java.lang.Object, C> $greater$minus(scala.Function1<B1, C>);
    Code:
       0: getstatic     #539                // Field scalaz/package$State$.MODULE$:Lscalaz/package$State$;
       3: aload_0
       4: aload_1
       5: invokedynamic #706,  0            // InvokeDynamic #18:apply:(Lscalaz/LensFamily;Lscala/Function1;)Lscala/Function1;
      10: astore_2
      11: ifnonnull     16
      14: aconst_null
      15: athrow
      16: getstatic     #552                // Field scalaz/package$StateT$.MODULE$:Lscalaz/package$StateT$;
      19: ifnonnull     24
      22: aconst_null
      23: athrow
      24: getstatic     #557                // Field scalaz/IndexedStateT$.MODULE$:Lscalaz/IndexedStateT$;
      27: ifnonnull     32
      30: aconst_null
      31: athrow
      32: new           #21                 // class scalaz/IndexedStateT$Wrap
      35: dup
      36: aload_2
      37: invokespecial #560                // Method scalaz/IndexedStateT$Wrap."<init>":(Lscala/Function1;)V
      40: areturn

  public <C> scalaz.IndexedStateT<A1, A2, java.lang.Object, C> flatMap(scala.Function1<B1, scalaz.IndexedStateT<A1, A2, java.lang.Object, C>>);
    Code:
       0: getstatic     #630                // Field scalaz/package$IndexedState$.MODULE$:Lscalaz/package$IndexedState$;
       3: aload_0
       4: aload_1
       5: invokedynamic #715,  0            // InvokeDynamic #19:apply:(Lscalaz/LensFamily;Lscala/Function1;)Lscala/Function1;
      10: astore_2
      11: ifnonnull     16
      14: aconst_null
      15: athrow
      16: getstatic     #557                // Field scalaz/IndexedStateT$.MODULE$:Lscalaz/IndexedStateT$;
      19: ifnonnull     24
      22: aconst_null
      23: athrow
      24: new           #21                 // class scalaz/IndexedStateT$Wrap
      27: dup
      28: aload_2
      29: invokespecial #560                // Method scalaz/IndexedStateT$Wrap."<init>":(Lscala/Function1;)V
      32: areturn

  public <C> scalaz.IndexedStateT<A1, A2, java.lang.Object, C> $greater$greater$minus(scala.Function1<B1, scalaz.IndexedStateT<A1, A2, java.lang.Object, C>>);
    Code:
       0: getstatic     #630                // Field scalaz/package$IndexedState$.MODULE$:Lscalaz/package$IndexedState$;
       3: aload_0
       4: aload_1
       5: invokedynamic #715,  0            // InvokeDynamic #19:apply:(Lscalaz/LensFamily;Lscala/Function1;)Lscala/Function1;
      10: astore_2
      11: ifnonnull     16
      14: aconst_null
      15: athrow
      16: getstatic     #557                // Field scalaz/IndexedStateT$.MODULE$:Lscalaz/IndexedStateT$;
      19: ifnonnull     24
      22: aconst_null
      23: athrow
      24: new           #21                 // class scalaz/IndexedStateT$Wrap
      27: dup
      28: aload_2
      29: invokespecial #560                // Method scalaz/IndexedStateT$Wrap."<init>":(Lscala/Function1;)V
      32: areturn

  public <C> scalaz.IndexedStateT<A1, A2, java.lang.Object, C> $minus$greater$greater$minus(scala.Function0<scalaz.IndexedStateT<A1, A2, java.lang.Object, C>>);
    Code:
       0: aload_1
       1: invokedynamic #727,  0            // InvokeDynamic #20:apply:(Lscala/Function0;)Lscala/Function1;
       6: astore_2
       7: getstatic     #630                // Field scalaz/package$IndexedState$.MODULE$:Lscalaz/package$IndexedState$;
      10: aload_0
      11: aload_2
      12: invokedynamic #715,  0            // InvokeDynamic #19:apply:(Lscalaz/LensFamily;Lscala/Function1;)Lscala/Function1;
      17: astore_3
      18: ifnonnull     23
      21: aconst_null
      22: athrow
      23: getstatic     #557                // Field scalaz/IndexedStateT$.MODULE$:Lscalaz/IndexedStateT$;
      26: ifnonnull     31
      29: aconst_null
      30: athrow
      31: new           #21                 // class scalaz/IndexedStateT$Wrap
      34: dup
      35: aload_3
      36: invokespecial #560                // Method scalaz/IndexedStateT$Wrap."<init>":(Lscala/Function1;)V
      39: areturn

  public scalaz.NaturalTransformation<?, ?> liftsNT();
    Code:
       0: new           #26                 // class scalaz/LensFamily$$anon$1
       3: dup
       4: aload_0
       5: invokespecial #734                // Method scalaz/LensFamily$$anon$1."<init>":(Lscalaz/LensFamily;)V
       8: areturn

  public <C1, C2> scalaz.LensFamily<C1, C2, B1, B2> compose(scalaz.LensFamily<C1, C2, A1, A2>);
    Code:
       0: getstatic     #113                // Field scalaz/LensFamily$.MODULE$:Lscalaz/LensFamily$;
       3: aload_0
       4: aload_1
       5: invokedynamic #746,  0            // InvokeDynamic #21:apply:(Lscalaz/LensFamily;Lscalaz/LensFamily;)Lscala/Function1;
      10: astore_2
      11: ifnonnull     16
      14: aconst_null
      15: athrow
      16: new           #33                 // class scalaz/LensFamilyFunctions$$anon$3
      19: dup
      20: aconst_null
      21: aload_2
      22: invokespecial #296                // Method scalaz/LensFamilyFunctions$$anon$3."<init>":(Lscalaz/LensFamilyFunctions;Lscala/Function1;)V
      25: areturn

  public <C1, C2> scalaz.LensFamily<C1, C2, B1, B2> $less$eq$less(scalaz.LensFamily<C1, C2, A1, A2>);
    Code:
       0: aload_0
       1: aload_1
       2: invokevirtual #749                // Method compose:(Lscalaz/LensFamily;)Lscalaz/LensFamily;
       5: areturn

  public <C1, C2> scalaz.LensFamily<A1, A2, C1, C2> andThen(scalaz.LensFamily<B1, B2, C1, C2>);
    Code:
       0: aload_1
       1: aload_0
       2: invokevirtual #749                // Method compose:(Lscalaz/LensFamily;)Lscalaz/LensFamily;
       5: areturn

  public <C1, C2> scalaz.LensFamily<A1, A2, C1, C2> $greater$eq$greater(scalaz.LensFamily<B1, B2, C1, C2>);
    Code:
       0: aload_0
       1: aload_1
       2: invokevirtual #754                // Method andThen:(Lscalaz/LensFamily;)Lscalaz/LensFamily;
       5: areturn

  public <C1, C2> scalaz.LensFamily<scalaz.$bslash$div<A1, C1>, scalaz.$bslash$div<A2, C2>, B1, B2> sum(scala.Function0<scalaz.LensFamily<C1, C2, B1, B2>>);
    Code:
       0: getstatic     #113                // Field scalaz/LensFamily$.MODULE$:Lscalaz/LensFamily$;
       3: aload_0
       4: aload_1
       5: invokedynamic #767,  0            // InvokeDynamic #22:apply:(Lscalaz/LensFamily;Lscala/Function0;)Lscala/Function1;
      10: astore_2
      11: ifnonnull     16
      14: aconst_null
      15: athrow
      16: new           #33                 // class scalaz/LensFamilyFunctions$$anon$3
      19: dup
      20: aconst_null
      21: aload_2
      22: invokespecial #296                // Method scalaz/LensFamilyFunctions$$anon$3."<init>":(Lscalaz/LensFamilyFunctions;Lscala/Function1;)V
      25: areturn

  public <C1, C2> scalaz.LensFamily<scalaz.$bslash$div<A1, C1>, scalaz.$bslash$div<A2, C2>, B1, B2> $bar$bar$bar(scala.Function0<scalaz.LensFamily<C1, C2, B1, B2>>);
    Code:
       0: getstatic     #113                // Field scalaz/LensFamily$.MODULE$:Lscalaz/LensFamily$;
       3: aload_0
       4: aload_1
       5: invokedynamic #767,  0            // InvokeDynamic #22:apply:(Lscalaz/LensFamily;Lscala/Function0;)Lscala/Function1;
      10: astore_2
      11: ifnonnull     16
      14: aconst_null
      15: athrow
      16: new           #33                 // class scalaz/LensFamilyFunctions$$anon$3
      19: dup
      20: aconst_null
      21: aload_2
      22: invokespecial #296                // Method scalaz/LensFamilyFunctions$$anon$3."<init>":(Lscalaz/LensFamilyFunctions;Lscala/Function1;)V
      25: areturn

  public <C1, C2, D1, D2> scalaz.LensFamily<scala.Tuple2<A1, C1>, scala.Tuple2<A2, C2>, scala.Tuple2<B1, D1>, scala.Tuple2<B2, D2>> product(scalaz.LensFamily<C1, C2, D1, D2>);
    Code:
       0: getstatic     #113                // Field scalaz/LensFamily$.MODULE$:Lscalaz/LensFamily$;
       3: aload_0
       4: aload_1
       5: invokedynamic #779,  0            // InvokeDynamic #23:apply:(Lscalaz/LensFamily;Lscalaz/LensFamily;)Lscala/Function1;
      10: astore_2
      11: ifnonnull     16
      14: aconst_null
      15: athrow
      16: new           #33                 // class scalaz/LensFamilyFunctions$$anon$3
      19: dup
      20: aconst_null
      21: aload_2
      22: invokespecial #296                // Method scalaz/LensFamilyFunctions$$anon$3."<init>":(Lscalaz/LensFamilyFunctions;Lscala/Function1;)V
      25: areturn

  public <C1, C2, D1, D2> scalaz.LensFamily<scala.Tuple2<A1, C1>, scala.Tuple2<A2, C2>, scala.Tuple2<B1, D1>, scala.Tuple2<B2, D2>> $times$times$times(scalaz.LensFamily<C1, C2, D1, D2>);
    Code:
       0: aload_0
       1: aload_1
       2: invokevirtual #782                // Method product:(Lscalaz/LensFamily;)Lscalaz/LensFamily;
       5: areturn

  public scalaz.LensFamily<A1, A2, B1, B2>.LensLaw lensLaw();
    Code:
       0: new           #28                 // class scalaz/LensFamily$$anon$2
       3: dup
       4: aload_0
       5: invokespecial #786                // Method scalaz/LensFamily$$anon$2."<init>":(Lscalaz/LensFamily;)V
       8: areturn

  public scalaz.PLensFamily<A1, A2, B1, B2> partial();
    Code:
       0: getstatic     #794                // Field scalaz/PLensFamily$.MODULE$:Lscalaz/PLensFamily$;
       3: aload_0
       4: invokedynamic #802,  0            // InvokeDynamic #24:apply:(Lscalaz/LensFamily;)Lscala/Function1;
       9: astore_1
      10: ifnonnull     15
      13: aconst_null
      14: athrow
      15: new           #87                 // class scalaz/PLensFamilyFunctions$$anon$1
      18: dup
      19: aconst_null
      20: aload_1
      21: invokespecial #805                // Method scalaz/PLensFamilyFunctions$$anon$1."<init>":(Lscalaz/PLensFamilyFunctions;Lscala/Function1;)V
      24: areturn

  public scalaz.PLensFamily<A1, A2, B1, B2> unary_$tilde();
    Code:
       0: aload_0
       1: invokevirtual #809                // Method partial:()Lscalaz/PLensFamily;
       4: areturn

  public static final scalaz.IndexedStoreT $anonfun$xmapA$1(scalaz.LensFamily, scala.Function1, scala.Function1, java.lang.Object);
    Code:
       0: aload_0
       1: aload_1
       2: aload_3
       3: invokeinterface #566,  2          // InterfaceMethod scala/Function1.apply:(Ljava/lang/Object;)Ljava/lang/Object;
       8: invokevirtual #439                // Method run:(Ljava/lang/Object;)Lscalaz/IndexedStoreT;
      11: getstatic     #516                // Field scalaz/package$.MODULE$:Lscalaz/package$;
      14: invokevirtual #520                // Method scalaz/package$.idInstance:()Lscalaz/Traverse1;
      17: astore        5
      19: dup
      20: ifnonnull     25
      23: aconst_null
      24: athrow
      25: astore        4
      27: getstatic     #816                // Field scalaz/package$StoreT$.MODULE$:Lscalaz/package$StoreT$;
      30: aload_2
      31: invokedynamic #822,  0            // InvokeDynamic #25:apply:(Lscala/Function1;)Lscala/Function1;
      36: astore        6
      38: new           #607                // class scala/Tuple2
      41: dup
      42: aload         5
      44: aload         4
      46: invokevirtual #825                // Method scalaz/IndexedStoreT.run:()Lscala/Tuple2;
      49: invokevirtual #610                // Method scala/Tuple2._1:()Ljava/lang/Object;
      52: aload         6
      54: invokeinterface #828,  3          // InterfaceMethod scalaz/Functor.map:(Ljava/lang/Object;Lscala/Function1;)Ljava/lang/Object;
      59: aload         4
      61: invokevirtual #825                // Method scalaz/IndexedStoreT.run:()Lscala/Tuple2;
      64: invokevirtual #613                // Method scala/Tuple2._2:()Ljava/lang/Object;
      67: invokespecial #623                // Method scala/Tuple2."<init>":(Ljava/lang/Object;Ljava/lang/Object;)V
      70: invokevirtual #831                // Method scalaz/package$StoreT$.indexedStoreT:(Lscala/Tuple2;)Lscalaz/IndexedStoreT;
      73: areturn

  public static final java.lang.Object $anonfun$xmapbA$1(scalaz.BijectionT, java.lang.Object);
    Code:
       0: aload_0
       1: aload_1
       2: invokevirtual #840                // Method scalaz/BijectionT.to:(Ljava/lang/Object;)Ljava/lang/Object;
       5: areturn

  public static final java.lang.Object $anonfun$xmapbA$2(scalaz.BijectionT, java.lang.Object);
    Code:
       0: aload_0
       1: aload_1
       2: invokevirtual #843                // Method scalaz/BijectionT.from:(Ljava/lang/Object;)Ljava/lang/Object;
       5: areturn

  public static final scalaz.IndexedStoreT $anonfun$xmapB$1(scalaz.LensFamily, scala.Function1, scala.Function1, java.lang.Object);
    Code:
       0: aload_0
       1: aload_3
       2: invokevirtual #439                // Method run:(Ljava/lang/Object;)Lscalaz/IndexedStoreT;
       5: getstatic     #516                // Field scalaz/package$.MODULE$:Lscalaz/package$;
       8: invokevirtual #520                // Method scalaz/package$.idInstance:()Lscalaz/Traverse1;
      11: astore        5
      13: dup
      14: ifnonnull     19
      17: aconst_null
      18: athrow
      19: astore        4
      21: getstatic     #816                // Field scalaz/package$StoreT$.MODULE$:Lscalaz/package$StoreT$;
      24: new           #607                // class scala/Tuple2
      27: dup
      28: aload         5
      30: aload         4
      32: invokevirtual #847                // Method scalaz/IndexedStoreT.set:()Ljava/lang/Object;
      35: aload_2
      36: invokedynamic #852,  0            // InvokeDynamic #26:apply:(Lscala/Function1;)Lscala/Function1;
      41: invokeinterface #828,  3          // InterfaceMethod scalaz/Functor.map:(Ljava/lang/Object;Lscala/Function1;)Ljava/lang/Object;
      46: aload_1
      47: aload         4
      49: invokevirtual #509                // Method scalaz/IndexedStoreT.pos:()Ljava/lang/Object;
      52: invokeinterface #566,  2          // InterfaceMethod scala/Function1.apply:(Ljava/lang/Object;)Ljava/lang/Object;
      57: invokespecial #623                // Method scala/Tuple2."<init>":(Ljava/lang/Object;Ljava/lang/Object;)V
      60: invokevirtual #831                // Method scalaz/package$StoreT$.indexedStoreT:(Lscala/Tuple2;)Lscalaz/IndexedStoreT;
      63: areturn

  public static final java.lang.Object $anonfun$xmapbB$1(scalaz.BijectionT, java.lang.Object);
    Code:
       0: aload_0
       1: aload_1
       2: invokevirtual #840                // Method scalaz/BijectionT.to:(Ljava/lang/Object;)Ljava/lang/Object;
       5: areturn

  public static final java.lang.Object $anonfun$xmapbB$2(scalaz.BijectionT, java.lang.Object);
    Code:
       0: aload_0
       1: aload_1
       2: invokevirtual #843                // Method scalaz/BijectionT.from:(Ljava/lang/Object;)Ljava/lang/Object;
       5: areturn

  public static final scala.Tuple2 $anonfun$st$1(scalaz.LensFamily, java.lang.Object);
    Code:
       0: new           #607                // class scala/Tuple2
       3: dup
       4: aload_1
       5: aload_0
       6: aload_1
       7: invokevirtual #605                // Method get:(Ljava/lang/Object;)Ljava/lang/Object;
      10: invokespecial #623                // Method scala/Tuple2."<init>":(Ljava/lang/Object;Ljava/lang/Object;)V
      13: areturn

  public static final java.lang.Object $anonfun$$eq$greater$eq$1(scalaz.LensFamily, scala.Function1, java.lang.Object);
    Code:
       0: aload_0
       1: aload_2
       2: invokevirtual #439                // Method run:(Ljava/lang/Object;)Lscalaz/IndexedStoreT;
       5: getstatic     #516                // Field scalaz/package$.MODULE$:Lscalaz/package$;
       8: invokevirtual #520                // Method scalaz/package$.idInstance:()Lscalaz/Traverse1;
      11: astore        4
      13: dup
      14: ifnonnull     19
      17: aconst_null
      18: athrow
      19: astore_3
      20: aload_3
      21: aload_1
      22: aload_3
      23: invokevirtual #509                // Method scalaz/IndexedStoreT.pos:()Ljava/lang/Object;
      26: invokeinterface #566,  2          // InterfaceMethod scala/Function1.apply:(Ljava/lang/Object;)Ljava/lang/Object;
      31: aload         4
      33: invokevirtual #524                // Method scalaz/IndexedStoreT.put:(Ljava/lang/Object;Lscalaz/Functor;)Ljava/lang/Object;
      36: areturn

  public static final java.lang.Object $anonfun$$eq$greater$greater$eq$1(scalaz.LensFamily, scala.Function1, scalaz.Functor, java.lang.Object);
    Code:
       0: aload_0
       1: aload_3
       2: invokevirtual #439                // Method run:(Ljava/lang/Object;)Lscalaz/IndexedStoreT;
       5: getstatic     #516                // Field scalaz/package$.MODULE$:Lscalaz/package$;
       8: invokevirtual #520                // Method scalaz/package$.idInstance:()Lscalaz/Traverse1;
      11: astore        5
      13: dup
      14: ifnonnull     19
      17: aconst_null
      18: athrow
      19: astore        4
      21: aload         4
      23: aload_1
      24: aload         4
      26: invokevirtual #509                // Method scalaz/IndexedStoreT.pos:()Ljava/lang/Object;
      29: invokeinterface #566,  2          // InterfaceMethod scala/Function1.apply:(Ljava/lang/Object;)Ljava/lang/Object;
      34: aload         5
      36: aload_2
      37: invokevirtual #532                // Method scalaz/IndexedStoreT.putf:(Ljava/lang/Object;Lscalaz/Functor;Lscalaz/Functor;)Ljava/lang/Object;
      40: areturn

  public static final scala.Tuple2 $anonfun$mods$1(scalaz.LensFamily, scala.Function1, java.lang.Object);
    Code:
       0: aload_0
       1: aload_2
       2: invokevirtual #439                // Method run:(Ljava/lang/Object;)Lscalaz/IndexedStoreT;
       5: astore_3
       6: aload_1
       7: aload_3
       8: invokevirtual #509                // Method scalaz/IndexedStoreT.pos:()Ljava/lang/Object;
      11: invokeinterface #566,  2          // InterfaceMethod scala/Function1.apply:(Ljava/lang/Object;)Ljava/lang/Object;
      16: astore        4
      18: new           #607                // class scala/Tuple2
      21: dup
      22: aload_3
      23: aload         4
      25: getstatic     #516                // Field scalaz/package$.MODULE$:Lscalaz/package$;
      28: invokevirtual #520                // Method scalaz/package$.idInstance:()Lscalaz/Traverse1;
      31: invokevirtual #524                // Method scalaz/IndexedStoreT.put:(Ljava/lang/Object;Lscalaz/Functor;)Ljava/lang/Object;
      34: aload         4
      36: invokespecial #623                // Method scala/Tuple2."<init>":(Ljava/lang/Object;Ljava/lang/Object;)V
      39: areturn

  public static final scala.Tuple2 $anonfun$modo$1(scalaz.LensFamily, scala.Function1, java.lang.Object);
    Code:
       0: aload_0
       1: aload_2
       2: invokevirtual #439                // Method run:(Ljava/lang/Object;)Lscalaz/IndexedStoreT;
       5: astore_3
       6: aload_3
       7: invokevirtual #509                // Method scalaz/IndexedStoreT.pos:()Ljava/lang/Object;
      10: astore        4
      12: new           #607                // class scala/Tuple2
      15: dup
      16: aload_3
      17: aload_1
      18: aload         4
      20: invokeinterface #566,  2          // InterfaceMethod scala/Function1.apply:(Ljava/lang/Object;)Ljava/lang/Object;
      25: getstatic     #516                // Field scalaz/package$.MODULE$:Lscalaz/package$;
      28: invokevirtual #520                // Method scalaz/package$.idInstance:()Lscalaz/Traverse1;
      31: invokevirtual #524                // Method scalaz/IndexedStoreT.put:(Ljava/lang/Object;Lscalaz/Functor;)Ljava/lang/Object;
      34: aload         4
      36: invokespecial #623                // Method scala/Tuple2."<init>":(Ljava/lang/Object;Ljava/lang/Object;)V
      39: areturn

  public static final java.lang.Object $anonfun$assign$1(scala.Function0, java.lang.Object);
    Code:
       0: aload_0
       1: invokeinterface #873,  1          // InterfaceMethod scala/Function0.apply:()Ljava/lang/Object;
       6: areturn

  public static final java.lang.Object $anonfun$assigno$1(scala.Function0, java.lang.Object);
    Code:
       0: aload_0
       1: invokeinterface #873,  1          // InterfaceMethod scala/Function0.apply:()Ljava/lang/Object;
       6: areturn

  public static final scala.Tuple2 $anonfun$mods_$1(scalaz.LensFamily, scala.Function1, java.lang.Object);
    Code:
       0: new           #607                // class scala/Tuple2
       3: dup
       4: aload_0
       5: aload_2
       6: invokevirtual #439                // Method run:(Ljava/lang/Object;)Lscalaz/IndexedStoreT;
       9: getstatic     #516                // Field scalaz/package$.MODULE$:Lscalaz/package$;
      12: invokevirtual #520                // Method scalaz/package$.idInstance:()Lscalaz/Traverse1;
      15: astore        4
      17: dup
      18: ifnonnull     23
      21: aconst_null
      22: athrow
      23: astore_3
      24: aload_3
      25: aload_1
      26: aload_3
      27: invokevirtual #509                // Method scalaz/IndexedStoreT.pos:()Ljava/lang/Object;
      30: invokeinterface #566,  2          // InterfaceMethod scala/Function1.apply:(Ljava/lang/Object;)Ljava/lang/Object;
      35: aload         4
      37: invokevirtual #524                // Method scalaz/IndexedStoreT.put:(Ljava/lang/Object;Lscalaz/Functor;)Ljava/lang/Object;
      40: getstatic     #882                // Field scala/runtime/BoxedUnit.UNIT:Lscala/runtime/BoxedUnit;
      43: invokespecial #623                // Method scala/Tuple2."<init>":(Ljava/lang/Object;Ljava/lang/Object;)V
      46: areturn

  public static final scala.Tuple2 $anonfun$lifts$2(scalaz.IndexedStateT, java.lang.Object);
    Code:
       0: aload_0
       1: aload_1
       2: getstatic     #516                // Field scalaz/package$.MODULE$:Lscalaz/package$;
       5: invokevirtual #520                // Method scalaz/package$.idInstance:()Lscalaz/Traverse1;
       8: checkcast     #888                // class scalaz/Bind
      11: invokevirtual #891                // Method scalaz/IndexedStateT.apply:(Ljava/lang/Object;Lscalaz/Bind;)Ljava/lang/Object;
      14: checkcast     #607                // class scala/Tuple2
      17: areturn

  public static final scala.Tuple2 $anonfun$lifts$1(scalaz.LensFamily, scalaz.IndexedStateT, java.lang.Object);
    Code:
       0: aload_0
       1: aload_2
       2: invokevirtual #605                // Method get:(Ljava/lang/Object;)Ljava/lang/Object;
       5: astore        6
       7: aload_1
       8: aload         6
      10: invokestatic  #893                // Method $anonfun$lifts$2:(Lscalaz/IndexedStateT;Ljava/lang/Object;)Lscala/Tuple2;
      13: astore_3
      14: aload_3
      15: ifnull        33
      18: aload_3
      19: invokevirtual #610                // Method scala/Tuple2._1:()Ljava/lang/Object;
      22: astore        4
      24: aload_3
      25: invokevirtual #613                // Method scala/Tuple2._2:()Ljava/lang/Object;
      28: astore        5
      30: goto          42
      33: new           #615                // class scala/MatchError
      36: dup
      37: aload_3
      38: invokespecial #618                // Method scala/MatchError."<init>":(Ljava/lang/Object;)V
      41: athrow
      42: new           #607                // class scala/Tuple2
      45: dup
      46: aload_0
      47: aload_2
      48: aload         4
      50: invokevirtual #620                // Method set:(Ljava/lang/Object;Ljava/lang/Object;)Ljava/lang/Object;
      53: aload         5
      55: invokespecial #623                // Method scala/Tuple2."<init>":(Ljava/lang/Object;Ljava/lang/Object;)V
      58: areturn

  public static final scala.Tuple2 $anonfun$map$1(scalaz.LensFamily, scala.Function1, java.lang.Object);
    Code:
       0: new           #607                // class scala/Tuple2
       3: dup
       4: aload_2
       5: aload_1
       6: aload_0
       7: aload_2
       8: invokevirtual #605                // Method get:(Ljava/lang/Object;)Ljava/lang/Object;
      11: invokeinterface #566,  2          // InterfaceMethod scala/Function1.apply:(Ljava/lang/Object;)Ljava/lang/Object;
      16: invokespecial #623                // Method scala/Tuple2."<init>":(Ljava/lang/Object;Ljava/lang/Object;)V
      19: areturn

  public static final scala.Tuple2 $anonfun$flatMap$1(scalaz.LensFamily, scala.Function1, java.lang.Object);
    Code:
       0: aload_1
       1: aload_0
       2: aload_2
       3: invokevirtual #605                // Method get:(Ljava/lang/Object;)Ljava/lang/Object;
       6: invokeinterface #566,  2          // InterfaceMethod scala/Function1.apply:(Ljava/lang/Object;)Ljava/lang/Object;
      11: checkcast     #23                 // class scalaz/IndexedStateT
      14: aload_2
      15: getstatic     #516                // Field scalaz/package$.MODULE$:Lscalaz/package$;
      18: invokevirtual #520                // Method scalaz/package$.idInstance:()Lscalaz/Traverse1;
      21: checkcast     #888                // class scalaz/Bind
      24: invokevirtual #891                // Method scalaz/IndexedStateT.apply:(Ljava/lang/Object;Lscalaz/Bind;)Ljava/lang/Object;
      27: checkcast     #607                // class scala/Tuple2
      30: areturn

  public static final scalaz.IndexedStateT $anonfun$$minus$greater$greater$minus$1(scala.Function0, java.lang.Object);
    Code:
       0: aload_0
       1: invokeinterface #873,  1          // InterfaceMethod scala/Function0.apply:()Ljava/lang/Object;
       6: checkcast     #23                 // class scalaz/IndexedStateT
       9: areturn

  public static final scalaz.IndexedStoreT $anonfun$compose$1(scalaz.LensFamily, scalaz.LensFamily, java.lang.Object);
    Code:
       0: aload_1
       1: aload_2
       2: invokevirtual #439                // Method run:(Ljava/lang/Object;)Lscalaz/IndexedStoreT;
       5: invokevirtual #825                // Method scalaz/IndexedStoreT.run:()Lscala/Tuple2;
       8: astore_3
       9: aload_3
      10: ifnull        31
      13: aload_3
      14: invokevirtual #610                // Method scala/Tuple2._1:()Ljava/lang/Object;
      17: checkcast     #458                // class scala/Function1
      20: astore        4
      22: aload_3
      23: invokevirtual #613                // Method scala/Tuple2._2:()Ljava/lang/Object;
      26: astore        5
      28: goto          40
      31: new           #615                // class scala/MatchError
      34: dup
      35: aload_3
      36: invokespecial #618                // Method scala/MatchError."<init>":(Ljava/lang/Object;)V
      39: athrow
      40: aload         4
      42: astore        6
      44: aload_0
      45: aload         5
      47: invokevirtual #439                // Method run:(Ljava/lang/Object;)Lscalaz/IndexedStoreT;
      50: invokevirtual #825                // Method scalaz/IndexedStoreT.run:()Lscala/Tuple2;
      53: astore        7
      55: aload         7
      57: ifnull        80
      60: aload         7
      62: invokevirtual #610                // Method scala/Tuple2._1:()Ljava/lang/Object;
      65: checkcast     #458                // class scala/Function1
      68: astore        8
      70: aload         7
      72: invokevirtual #613                // Method scala/Tuple2._2:()Ljava/lang/Object;
      75: astore        9
      77: goto          90
      80: new           #615                // class scala/MatchError
      83: dup
      84: aload         7
      86: invokespecial #618                // Method scala/MatchError."<init>":(Ljava/lang/Object;)V
      89: athrow
      90: aload         8
      92: astore        10
      94: getstatic     #903                // Field scalaz/package$IndexedStore$.MODULE$:Lscalaz/package$IndexedStore$;
      97: aload         6
      99: aload         10
     101: invokeinterface #905,  2          // InterfaceMethod scala/Function1.compose:(Lscala/Function1;)Lscala/Function1;
     106: aload         9
     108: invokevirtual #908                // Method scalaz/package$IndexedStore$.apply:(Lscala/Function1;Ljava/lang/Object;)Lscalaz/IndexedStoreT;
     111: areturn

  public static final scalaz.IndexedStoreT $anonfun$sum$1(scalaz.LensFamily, scala.Function0, scalaz.$bslash$div);
    Code:
       0: aload_2
       1: instanceof    #914                // class scalaz/$minus$bslash$div
       4: ifeq          41
       7: aload_2
       8: checkcast     #914                // class scalaz/$minus$bslash$div
      11: invokevirtual #916                // Method scalaz/$minus$bslash$div.a:()Ljava/lang/Object;
      14: astore        4
      16: aload_0
      17: aload         4
      19: invokevirtual #439                // Method run:(Ljava/lang/Object;)Lscalaz/IndexedStoreT;
      22: getstatic     #921                // Field scalaz/$bslash$div$.MODULE$:Lscalaz/$bslash$div$;
      25: invokevirtual #924                // Method scalaz/$bslash$div$.left:()Lscala/Function1;
      28: getstatic     #516                // Field scalaz/package$.MODULE$:Lscalaz/package$;
      31: invokevirtual #520                // Method scalaz/package$.idInstance:()Lscalaz/Traverse1;
      34: invokevirtual #927                // Method scalaz/IndexedStoreT.map:(Lscala/Function1;Lscalaz/Functor;)Lscalaz/IndexedStoreT;
      37: astore_3
      38: goto          99
      41: aload_2
      42: instanceof    #929                // class scalaz/$bslash$div$minus
      45: ifeq          90
      48: aload_2
      49: checkcast     #929                // class scalaz/$bslash$div$minus
      52: invokevirtual #931                // Method scalaz/$bslash$div$minus.b:()Ljava/lang/Object;
      55: astore        5
      57: aload_1
      58: invokeinterface #873,  1          // InterfaceMethod scala/Function0.apply:()Ljava/lang/Object;
      63: checkcast     #2                  // class scalaz/LensFamily
      66: aload         5
      68: invokevirtual #439                // Method run:(Ljava/lang/Object;)Lscalaz/IndexedStoreT;
      71: getstatic     #921                // Field scalaz/$bslash$div$.MODULE$:Lscalaz/$bslash$div$;
      74: invokevirtual #934                // Method scalaz/$bslash$div$.right:()Lscala/Function1;
      77: getstatic     #516                // Field scalaz/package$.MODULE$:Lscalaz/package$;
      80: invokevirtual #520                // Method scalaz/package$.idInstance:()Lscalaz/Traverse1;
      83: invokevirtual #927                // Method scalaz/IndexedStoreT.map:(Lscala/Function1;Lscalaz/Functor;)Lscalaz/IndexedStoreT;
      86: astore_3
      87: goto          99
      90: new           #615                // class scala/MatchError
      93: dup
      94: aload_2
      95: invokespecial #618                // Method scala/MatchError."<init>":(Ljava/lang/Object;)V
      98: athrow
      99: aload_3
     100: areturn

  public static final scalaz.IndexedStoreT $anonfun$product$1(scalaz.LensFamily, scalaz.LensFamily, scala.Tuple2);
    Code:
       0: aload_2
       1: ifnull        44
       4: aload_2
       5: invokevirtual #610                // Method scala/Tuple2._1:()Ljava/lang/Object;
       8: astore        4
      10: aload_2
      11: invokevirtual #613                // Method scala/Tuple2._2:()Ljava/lang/Object;
      14: astore        5
      16: aload_0
      17: aload         4
      19: invokevirtual #439                // Method run:(Ljava/lang/Object;)Lscalaz/IndexedStoreT;
      22: aload_1
      23: aload         5
      25: invokevirtual #439                // Method run:(Ljava/lang/Object;)Lscalaz/IndexedStoreT;
      28: getstatic     #516                // Field scalaz/package$.MODULE$:Lscalaz/package$;
      31: invokevirtual #520                // Method scalaz/package$.idInstance:()Lscalaz/Traverse1;
      34: checkcast     #888                // class scalaz/Bind
      37: invokevirtual #939                // Method scalaz/IndexedStoreT.$times$times$times:(Lscalaz/IndexedStoreT;Lscalaz/Bind;)Lscalaz/IndexedStoreT;
      40: astore_3
      41: goto          53
      44: new           #615                // class scala/MatchError
      47: dup
      48: aload_2
      49: invokespecial #618                // Method scala/MatchError."<init>":(Ljava/lang/Object;)V
      52: athrow
      53: aload_3
      54: areturn

  public static final scala.Option $anonfun$partial$1(scalaz.LensFamily, java.lang.Object);
    Code:
       0: new           #942                // class scala/Some
       3: dup
       4: aload_0
       5: aload_1
       6: invokevirtual #439                // Method run:(Ljava/lang/Object;)Lscalaz/IndexedStoreT;
       9: invokespecial #943                // Method scala/Some."<init>":(Ljava/lang/Object;)V
      12: areturn

  public scalaz.LensFamily();
    Code:
       0: aload_0
       1: invokespecial #946                // Method java/lang/Object."<init>":()V
       4: return

  private static java.lang.Object $deserializeLambda$(java.lang.invoke.SerializedLambda);
    Code:
       0: aload_0
       1: invokedynamic #959,  0            // InvokeDynamic #27:lambdaDeserialize:(Ljava/lang/invoke/SerializedLambda;)Ljava/lang/Object;
       6: areturn
}
