Compiled from "Lens.scala"
public abstract class scalaz.LensInstances extends scalaz.LensInstances0 {
  private volatile scalaz.LensInstances$SetLensFamily$ SetLensFamily$module;

  private volatile scalaz.LensInstances$MapLensFamily$ MapLensFamily$module;

  private volatile scalaz.LensInstances$SeqLikeLensFamily$ SeqLikeLensFamily$module;

  private volatile scalaz.LensInstances$QueueLensFamily$ QueueLensFamily$module;

  private volatile scalaz.LensInstances$ArrayLensFamily$ ArrayLensFamily$module;

  private volatile scalaz.LensInstances$NumericLensFamily$ NumericLensFamily$module;

  private volatile scalaz.LensInstances$FractionalLensFamily$ FractionalLensFamily$module;

  private volatile scalaz.LensInstances$IntegralLensFamily$ IntegralLensFamily$module;

  private final scalaz.LensCategory lensCategory;

  private final scalaz.LensInstances$SetLensFamily$ SetLens;

  private final scalaz.LensInstances$MapLensFamily$ MapLens;

  private final scalaz.LensInstances$SeqLikeLensFamily$ SeqLikeLens;

  private final scalaz.LensInstances$QueueLensFamily$ QueueLens;

  private final scalaz.LensInstances$ArrayLensFamily$ ArrayLens;

  private final scalaz.LensInstances$NumericLensFamily$ NumericLens;

  private final scalaz.LensInstances$FractionalLensFamily$ FractionalLens;

  private final scalaz.LensInstances$IntegralLensFamily$ IntegralLens;

  public scalaz.LensInstances$SetLensFamily$ SetLensFamily();
    Code:
       0: aload_0
       1: getfield      #89                 // Field SetLensFamily$module:Lscalaz/LensInstances$SetLensFamily$;
       4: ifnonnull     11
       7: aload_0
       8: invokespecial #93                 // Method SetLensFamily$lzycompute$1:()V
      11: aload_0
      12: getfield      #89                 // Field SetLensFamily$module:Lscalaz/LensInstances$SetLensFamily$;
      15: areturn

  public scalaz.LensInstances$MapLensFamily$ MapLensFamily();
    Code:
       0: aload_0
       1: getfield      #98                 // Field MapLensFamily$module:Lscalaz/LensInstances$MapLensFamily$;
       4: ifnonnull     11
       7: aload_0
       8: invokespecial #101                // Method MapLensFamily$lzycompute$1:()V
      11: aload_0
      12: getfield      #98                 // Field MapLensFamily$module:Lscalaz/LensInstances$MapLensFamily$;
      15: areturn

  public scalaz.LensInstances$SeqLikeLensFamily$ SeqLikeLensFamily();
    Code:
       0: aload_0
       1: getfield      #104                // Field SeqLikeLensFamily$module:Lscalaz/LensInstances$SeqLikeLensFamily$;
       4: ifnonnull     11
       7: aload_0
       8: invokespecial #107                // Method SeqLikeLensFamily$lzycompute$1:()V
      11: aload_0
      12: getfield      #104                // Field SeqLikeLensFamily$module:Lscalaz/LensInstances$SeqLikeLensFamily$;
      15: areturn

  public scalaz.LensInstances$QueueLensFamily$ QueueLensFamily();
    Code:
       0: aload_0
       1: getfield      #110                // Field QueueLensFamily$module:Lscalaz/LensInstances$QueueLensFamily$;
       4: ifnonnull     11
       7: aload_0
       8: invokespecial #113                // Method QueueLensFamily$lzycompute$1:()V
      11: aload_0
      12: getfield      #110                // Field QueueLensFamily$module:Lscalaz/LensInstances$QueueLensFamily$;
      15: areturn

  public scalaz.LensInstances$ArrayLensFamily$ ArrayLensFamily();
    Code:
       0: aload_0
       1: getfield      #116                // Field ArrayLensFamily$module:Lscalaz/LensInstances$ArrayLensFamily$;
       4: ifnonnull     11
       7: aload_0
       8: invokespecial #119                // Method ArrayLensFamily$lzycompute$1:()V
      11: aload_0
      12: getfield      #116                // Field ArrayLensFamily$module:Lscalaz/LensInstances$ArrayLensFamily$;
      15: areturn

  public scalaz.LensInstances$NumericLensFamily$ NumericLensFamily();
    Code:
       0: aload_0
       1: getfield      #122                // Field NumericLensFamily$module:Lscalaz/LensInstances$NumericLensFamily$;
       4: ifnonnull     11
       7: aload_0
       8: invokespecial #125                // Method NumericLensFamily$lzycompute$1:()V
      11: aload_0
      12: getfield      #122                // Field NumericLensFamily$module:Lscalaz/LensInstances$NumericLensFamily$;
      15: areturn

  public scalaz.LensInstances$FractionalLensFamily$ FractionalLensFamily();
    Code:
       0: aload_0
       1: getfield      #128                // Field FractionalLensFamily$module:Lscalaz/LensInstances$FractionalLensFamily$;
       4: ifnonnull     11
       7: aload_0
       8: invokespecial #131                // Method FractionalLensFamily$lzycompute$1:()V
      11: aload_0
      12: getfield      #128                // Field FractionalLensFamily$module:Lscalaz/LensInstances$FractionalLensFamily$;
      15: areturn

  public scalaz.LensInstances$IntegralLensFamily$ IntegralLensFamily();
    Code:
       0: aload_0
       1: getfield      #134                // Field IntegralLensFamily$module:Lscalaz/LensInstances$IntegralLensFamily$;
       4: ifnonnull     11
       7: aload_0
       8: invokespecial #137                // Method IntegralLensFamily$lzycompute$1:()V
      11: aload_0
      12: getfield      #134                // Field IntegralLensFamily$module:Lscalaz/LensInstances$IntegralLensFamily$;
      15: areturn

  public scalaz.LensCategory lensCategory();
    Code:
       0: aload_0
       1: getfield      #140                // Field lensCategory:Lscalaz/LensCategory;
       4: areturn

  public <A, B> scalaz.IndexedStateT<A, A, java.lang.Object, B> LensFamilyState(scalaz.LensFamily<A, ?, B, ?>);
    Code:
       0: aload_1
       1: invokevirtual #150                // Method scalaz/LensFamily.st:()Lscalaz/IndexedStateT;
       4: areturn

  public <S, R> scalaz.Unzip<?> LensFamilyUnzip();
    Code:
       0: new           #12                 // class scalaz/LensInstances$$anon$6
       3: dup
       4: aconst_null
       5: invokespecial #158                // Method scalaz/LensInstances$$anon$6."<init>":(Lscalaz/LensInstances;)V
       8: areturn

  public scalaz.LensInstances$SetLensFamily$ SetLens();
    Code:
       0: aload_0
       1: getfield      #160                // Field SetLens:Lscalaz/LensInstances$SetLensFamily$;
       4: areturn

  public <S1, S2, K> scalaz.LensInstances$SetLensFamily<S1, S2, K> setLensFamily(scalaz.LensFamily<S1, S2, scala.collection.immutable.Set<K>, scala.collection.immutable.Set<K>>);
    Code:
       0: new           #56                 // class scalaz/LensInstances$SetLensFamily
       3: dup
       4: aload_0
       5: aload_1
       6: invokespecial #166                // Method scalaz/LensInstances$SetLensFamily."<init>":(Lscalaz/LensInstances;Lscalaz/LensFamily;)V
       9: areturn

  public scalaz.LensInstances$MapLensFamily$ MapLens();
    Code:
       0: aload_0
       1: getfield      #168                // Field MapLens:Lscalaz/LensInstances$MapLensFamily$;
       4: areturn

  public <S1, S2, K, V> scalaz.LensInstances$MapLensFamily<S1, S2, K, V> mapLensFamily(scalaz.LensFamily<S1, S2, scala.collection.immutable.Map<K, V>, scala.collection.immutable.Map<K, V>>);
    Code:
       0: new           #32                 // class scalaz/LensInstances$MapLensFamily
       3: dup
       4: aload_0
       5: aload_1
       6: invokespecial #172                // Method scalaz/LensInstances$MapLensFamily."<init>":(Lscalaz/LensInstances;Lscalaz/LensFamily;)V
       9: areturn

  public scalaz.LensInstances$SeqLikeLensFamily$ SeqLikeLens();
    Code:
       0: aload_0
       1: getfield      #174                // Field SeqLikeLens:Lscalaz/LensInstances$SeqLikeLensFamily$;
       4: areturn

  public <S1, S2, A> scalaz.LensInstances$SeqLikeLensFamily<S1, S2, A, scala.collection.immutable.Seq<A>> seqLensFamily(scalaz.LensFamily<S1, S2, scala.collection.immutable.Seq<A>, scala.collection.immutable.Seq<A>>);
    Code:
       0: aload_0
       1: aload_1
       2: invokevirtual #180                // Method seqLikeLensFamily:(Lscalaz/LensFamily;)Lscalaz/LensInstances$SeqLikeLensFamily;
       5: areturn

  public scalaz.LensInstances$QueueLensFamily$ QueueLens();
    Code:
       0: aload_0
       1: getfield      #182                // Field QueueLens:Lscalaz/LensInstances$QueueLensFamily$;
       4: areturn

  public <S1, S2, A> scalaz.LensInstances$QueueLensFamily<S1, S2, A> queueLensFamily(scalaz.LensFamily<S1, S2, scala.collection.immutable.Queue<A>, scala.collection.immutable.Queue<A>>);
    Code:
       0: new           #44                 // class scalaz/LensInstances$QueueLensFamily
       3: dup
       4: aload_0
       5: aload_1
       6: invokespecial #186                // Method scalaz/LensInstances$QueueLensFamily."<init>":(Lscalaz/LensInstances;Lscalaz/LensFamily;)V
       9: areturn

  public scalaz.LensInstances$ArrayLensFamily$ ArrayLens();
    Code:
       0: aload_0
       1: getfield      #188                // Field ArrayLens:Lscalaz/LensInstances$ArrayLensFamily$;
       4: areturn

  public <S1, S2, A> scalaz.LensInstances$ArrayLensFamily<S1, S2, A> arrayLensFamily(scalaz.LensFamily<S1, S2, java.lang.Object, java.lang.Object>);
    Code:
       0: new           #14                 // class scalaz/LensInstances$ArrayLensFamily
       3: dup
       4: aload_0
       5: aload_1
       6: invokespecial #192                // Method scalaz/LensInstances$ArrayLensFamily."<init>":(Lscalaz/LensInstances;Lscalaz/LensFamily;)V
       9: areturn

  public scalaz.LensInstances$NumericLensFamily$ NumericLens();
    Code:
       0: aload_0
       1: getfield      #194                // Field NumericLens:Lscalaz/LensInstances$NumericLensFamily$;
       4: areturn

  public <S1, S2, N> scalaz.LensInstances$NumericLensFamily<S1, S2, N> numericLensFamily(scalaz.LensFamily<S1, S2, N, N>, scala.math.Numeric<N>);
    Code:
       0: aload_0
       1: invokevirtual #200                // Method NumericLens:()Lscalaz/LensInstances$NumericLensFamily$;
       4: aload_1
       5: getstatic     #206                // Field scala/Predef$.MODULE$:Lscala/Predef$;
       8: aload_2
       9: invokevirtual #210                // Method scala/Predef$.implicitly:(Ljava/lang/Object;)Ljava/lang/Object;
      12: checkcast     #212                // class scala/math/Numeric
      15: invokevirtual #215                // Method scalaz/LensInstances$NumericLensFamily$.apply:(Lscalaz/LensFamily;Lscala/math/Numeric;)Lscalaz/LensInstances$NumericLensFamily;
      18: areturn

  public scalaz.LensInstances$FractionalLensFamily$ FractionalLens();
    Code:
       0: aload_0
       1: getfield      #218                // Field FractionalLens:Lscalaz/LensInstances$FractionalLensFamily$;
       4: areturn

  public <S1, S2, F> scalaz.LensInstances$FractionalLensFamily<S1, S2, F> fractionalLensFamily(scalaz.LensFamily<S1, S2, F, F>, scala.math.Fractional<F>);
    Code:
       0: new           #20                 // class scalaz/LensInstances$FractionalLensFamily
       3: dup
       4: aload_0
       5: aload_1
       6: getstatic     #206                // Field scala/Predef$.MODULE$:Lscala/Predef$;
       9: aload_2
      10: invokevirtual #210                // Method scala/Predef$.implicitly:(Ljava/lang/Object;)Ljava/lang/Object;
      13: checkcast     #224                // class scala/math/Fractional
      16: invokespecial #227                // Method scalaz/LensInstances$FractionalLensFamily."<init>":(Lscalaz/LensInstances;Lscalaz/LensFamily;Lscala/math/Fractional;)V
      19: areturn

  public scalaz.LensInstances$IntegralLensFamily$ IntegralLens();
    Code:
       0: aload_0
       1: getfield      #230                // Field IntegralLens:Lscalaz/LensInstances$IntegralLensFamily$;
       4: areturn

  public <S1, S2, I> scalaz.LensInstances$IntegralLensFamily<S1, S2, I> integralLensFamily(scalaz.LensFamily<S1, S2, I, I>, scala.math.Integral<I>);
    Code:
       0: new           #26                 // class scalaz/LensInstances$IntegralLensFamily
       3: dup
       4: aload_0
       5: aload_1
       6: getstatic     #206                // Field scala/Predef$.MODULE$:Lscala/Predef$;
       9: aload_2
      10: invokevirtual #210                // Method scala/Predef$.implicitly:(Ljava/lang/Object;)Ljava/lang/Object;
      13: checkcast     #236                // class scala/math/Integral
      16: invokespecial #239                // Method scalaz/LensInstances$IntegralLensFamily."<init>":(Lscalaz/LensInstances;Lscalaz/LensFamily;Lscala/math/Integral;)V
      19: areturn

  public <S1, S2, A, B> scala.Tuple2<scalaz.LensFamily<S1, S2, A, A>, scalaz.LensFamily<S1, S2, B, B>> tuple2LensFamily(scalaz.LensFamily<S1, S2, scala.Tuple2<A, B>, scala.Tuple2<A, B>>);
    Code:
       0: aload_0
       1: invokevirtual #245                // Method LensFamilyUnzip:()Lscalaz/Unzip;
       4: aload_1
       5: invokeinterface #251,  2          // InterfaceMethod scalaz/Unzip.unzip:(Ljava/lang/Object;)Lscala/Tuple2;
      10: areturn

  public <S1, S2, A, B, C> scala.Tuple3<scalaz.LensFamily<S1, S2, A, A>, scalaz.LensFamily<S1, S2, B, B>, scalaz.LensFamily<S1, S2, C, C>> tuple3LensFamily(scalaz.LensFamily<S1, S2, scala.Tuple3<A, B, C>, scala.Tuple3<A, B, C>>);
    Code:
       0: aload_0
       1: invokevirtual #245                // Method LensFamilyUnzip:()Lscalaz/Unzip;
       4: aload_1
       5: getstatic     #259                // Field scalaz/BijectionT$.MODULE$:Lscalaz/BijectionT$;
       8: invokevirtual #263                // Method scalaz/BijectionT$.tuple3B:()Lscalaz/BijectionT;
      11: invokevirtual #267                // Method scalaz/LensFamily.xmapbB:(Lscalaz/BijectionT;)Lscalaz/LensFamily;
      14: invokeinterface #271,  2          // InterfaceMethod scalaz/Unzip.unzip3:(Ljava/lang/Object;)Lscala/Tuple3;
      19: areturn

  public <S1, S2, A, B, C, D> scala.Tuple4<scalaz.LensFamily<S1, S2, A, A>, scalaz.LensFamily<S1, S2, B, B>, scalaz.LensFamily<S1, S2, C, C>, scalaz.LensFamily<S1, S2, D, D>> tuple4LensFamily(scalaz.LensFamily<S1, S2, scala.Tuple4<A, B, C, D>, scala.Tuple4<A, B, C, D>>);
    Code:
       0: aload_0
       1: invokevirtual #245                // Method LensFamilyUnzip:()Lscalaz/Unzip;
       4: aload_1
       5: getstatic     #259                // Field scalaz/BijectionT$.MODULE$:Lscalaz/BijectionT$;
       8: invokevirtual #277                // Method scalaz/BijectionT$.tuple4B:()Lscalaz/BijectionT;
      11: invokevirtual #267                // Method scalaz/LensFamily.xmapbB:(Lscalaz/BijectionT;)Lscalaz/LensFamily;
      14: invokeinterface #281,  2          // InterfaceMethod scalaz/Unzip.unzip4:(Ljava/lang/Object;)Lscala/Tuple4;
      19: areturn

  public <S1, S2, A, B, C, D, E> scala.Tuple5<scalaz.LensFamily<S1, S2, A, A>, scalaz.LensFamily<S1, S2, B, B>, scalaz.LensFamily<S1, S2, C, C>, scalaz.LensFamily<S1, S2, D, D>, scalaz.LensFamily<S1, S2, E, E>> tuple5LensFamily(scalaz.LensFamily<S1, S2, scala.Tuple5<A, B, C, D, E>, scala.Tuple5<A, B, C, D, E>>);
    Code:
       0: aload_0
       1: invokevirtual #245                // Method LensFamilyUnzip:()Lscalaz/Unzip;
       4: aload_1
       5: getstatic     #259                // Field scalaz/BijectionT$.MODULE$:Lscalaz/BijectionT$;
       8: invokevirtual #287                // Method scalaz/BijectionT$.tuple5B:()Lscalaz/BijectionT;
      11: invokevirtual #267                // Method scalaz/LensFamily.xmapbB:(Lscalaz/BijectionT;)Lscalaz/LensFamily;
      14: invokeinterface #291,  2          // InterfaceMethod scalaz/Unzip.unzip5:(Ljava/lang/Object;)Lscala/Tuple5;
      19: areturn

  public <S1, S2, A, B, C, D, E, H> scala.Tuple6<scalaz.LensFamily<S1, S2, A, A>, scalaz.LensFamily<S1, S2, B, B>, scalaz.LensFamily<S1, S2, C, C>, scalaz.LensFamily<S1, S2, D, D>, scalaz.LensFamily<S1, S2, E, E>, scalaz.LensFamily<S1, S2, H, H>> tuple6LensFamily(scalaz.LensFamily<S1, S2, scala.Tuple6<A, B, C, D, E, H>, scala.Tuple6<A, B, C, D, E, H>>);
    Code:
       0: aload_0
       1: invokevirtual #245                // Method LensFamilyUnzip:()Lscalaz/Unzip;
       4: aload_1
       5: getstatic     #259                // Field scalaz/BijectionT$.MODULE$:Lscalaz/BijectionT$;
       8: invokevirtual #297                // Method scalaz/BijectionT$.tuple6B:()Lscalaz/BijectionT;
      11: invokevirtual #267                // Method scalaz/LensFamily.xmapbB:(Lscalaz/BijectionT;)Lscalaz/LensFamily;
      14: invokeinterface #301,  2          // InterfaceMethod scalaz/Unzip.unzip6:(Ljava/lang/Object;)Lscala/Tuple6;
      19: areturn

  public <S1, S2, A, B, C, D, E, H, I> scala.Tuple7<scalaz.LensFamily<S1, S2, A, A>, scalaz.LensFamily<S1, S2, B, B>, scalaz.LensFamily<S1, S2, C, C>, scalaz.LensFamily<S1, S2, D, D>, scalaz.LensFamily<S1, S2, E, E>, scalaz.LensFamily<S1, S2, H, H>, scalaz.LensFamily<S1, S2, I, I>> tuple7LensFamily(scalaz.LensFamily<S1, S2, scala.Tuple7<A, B, C, D, E, H, I>, scala.Tuple7<A, B, C, D, E, H, I>>);
    Code:
       0: aload_0
       1: invokevirtual #245                // Method LensFamilyUnzip:()Lscalaz/Unzip;
       4: aload_1
       5: getstatic     #259                // Field scalaz/BijectionT$.MODULE$:Lscalaz/BijectionT$;
       8: invokevirtual #307                // Method scalaz/BijectionT$.tuple7B:()Lscalaz/BijectionT;
      11: invokevirtual #267                // Method scalaz/LensFamily.xmapbB:(Lscalaz/BijectionT;)Lscalaz/LensFamily;
      14: invokeinterface #311,  2          // InterfaceMethod scalaz/Unzip.unzip7:(Ljava/lang/Object;)Lscala/Tuple7;
      19: areturn

  private final void SetLensFamily$lzycompute$1();
    Code:
       0: aload_0
       1: monitorenter
       2: aload_0
       3: getfield      #89                 // Field SetLensFamily$module:Lscalaz/LensInstances$SetLensFamily$;
       6: ifnonnull     21
       9: aload_0
      10: new           #59                 // class scalaz/LensInstances$SetLensFamily$
      13: dup
      14: aload_0
      15: invokespecial #312                // Method scalaz/LensInstances$SetLensFamily$."<init>":(Lscalaz/LensInstances;)V
      18: putfield      #89                 // Field SetLensFamily$module:Lscalaz/LensInstances$SetLensFamily$;
      21: aload_0
      22: monitorexit
      23: return
      24: aload_0
      25: monitorexit
      26: athrow
    Exception table:
       from    to  target type
           2    21    24   any

  private final void MapLensFamily$lzycompute$1();
    Code:
       0: aload_0
       1: monitorenter
       2: aload_0
       3: getfield      #98                 // Field MapLensFamily$module:Lscalaz/LensInstances$MapLensFamily$;
       6: ifnonnull     21
       9: aload_0
      10: new           #35                 // class scalaz/LensInstances$MapLensFamily$
      13: dup
      14: aload_0
      15: invokespecial #315                // Method scalaz/LensInstances$MapLensFamily$."<init>":(Lscalaz/LensInstances;)V
      18: putfield      #98                 // Field MapLensFamily$module:Lscalaz/LensInstances$MapLensFamily$;
      21: aload_0
      22: monitorexit
      23: return
      24: aload_0
      25: monitorexit
      26: athrow
    Exception table:
       from    to  target type
           2    21    24   any

  private final void SeqLikeLensFamily$lzycompute$1();
    Code:
       0: aload_0
       1: monitorenter
       2: aload_0
       3: getfield      #104                // Field SeqLikeLensFamily$module:Lscalaz/LensInstances$SeqLikeLensFamily$;
       6: ifnonnull     21
       9: aload_0
      10: new           #53                 // class scalaz/LensInstances$SeqLikeLensFamily$
      13: dup
      14: aload_0
      15: invokespecial #316                // Method scalaz/LensInstances$SeqLikeLensFamily$."<init>":(Lscalaz/LensInstances;)V
      18: putfield      #104                // Field SeqLikeLensFamily$module:Lscalaz/LensInstances$SeqLikeLensFamily$;
      21: aload_0
      22: monitorexit
      23: return
      24: aload_0
      25: monitorexit
      26: athrow
    Exception table:
       from    to  target type
           2    21    24   any

  private final void QueueLensFamily$lzycompute$1();
    Code:
       0: aload_0
       1: monitorenter
       2: aload_0
       3: getfield      #110                // Field QueueLensFamily$module:Lscalaz/LensInstances$QueueLensFamily$;
       6: ifnonnull     21
       9: aload_0
      10: new           #47                 // class scalaz/LensInstances$QueueLensFamily$
      13: dup
      14: aload_0
      15: invokespecial #317                // Method scalaz/LensInstances$QueueLensFamily$."<init>":(Lscalaz/LensInstances;)V
      18: putfield      #110                // Field QueueLensFamily$module:Lscalaz/LensInstances$QueueLensFamily$;
      21: aload_0
      22: monitorexit
      23: return
      24: aload_0
      25: monitorexit
      26: athrow
    Exception table:
       from    to  target type
           2    21    24   any

  private final void ArrayLensFamily$lzycompute$1();
    Code:
       0: aload_0
       1: monitorenter
       2: aload_0
       3: getfield      #116                // Field ArrayLensFamily$module:Lscalaz/LensInstances$ArrayLensFamily$;
       6: ifnonnull     21
       9: aload_0
      10: new           #17                 // class scalaz/LensInstances$ArrayLensFamily$
      13: dup
      14: aload_0
      15: invokespecial #318                // Method scalaz/LensInstances$ArrayLensFamily$."<init>":(Lscalaz/LensInstances;)V
      18: putfield      #116                // Field ArrayLensFamily$module:Lscalaz/LensInstances$ArrayLensFamily$;
      21: aload_0
      22: monitorexit
      23: return
      24: aload_0
      25: monitorexit
      26: athrow
    Exception table:
       from    to  target type
           2    21    24   any

  private final void NumericLensFamily$lzycompute$1();
    Code:
       0: aload_0
       1: monitorenter
       2: aload_0
       3: getfield      #122                // Field NumericLensFamily$module:Lscalaz/LensInstances$NumericLensFamily$;
       6: ifnonnull     21
       9: aload_0
      10: new           #41                 // class scalaz/LensInstances$NumericLensFamily$
      13: dup
      14: aload_0
      15: invokespecial #319                // Method scalaz/LensInstances$NumericLensFamily$."<init>":(Lscalaz/LensInstances;)V
      18: putfield      #122                // Field NumericLensFamily$module:Lscalaz/LensInstances$NumericLensFamily$;
      21: aload_0
      22: monitorexit
      23: return
      24: aload_0
      25: monitorexit
      26: athrow
    Exception table:
       from    to  target type
           2    21    24   any

  private final void FractionalLensFamily$lzycompute$1();
    Code:
       0: aload_0
       1: monitorenter
       2: aload_0
       3: getfield      #128                // Field FractionalLensFamily$module:Lscalaz/LensInstances$FractionalLensFamily$;
       6: ifnonnull     21
       9: aload_0
      10: new           #23                 // class scalaz/LensInstances$FractionalLensFamily$
      13: dup
      14: aload_0
      15: invokespecial #320                // Method scalaz/LensInstances$FractionalLensFamily$."<init>":(Lscalaz/LensInstances;)V
      18: putfield      #128                // Field FractionalLensFamily$module:Lscalaz/LensInstances$FractionalLensFamily$;
      21: aload_0
      22: monitorexit
      23: return
      24: aload_0
      25: monitorexit
      26: athrow
    Exception table:
       from    to  target type
           2    21    24   any

  private final void IntegralLensFamily$lzycompute$1();
    Code:
       0: aload_0
       1: monitorenter
       2: aload_0
       3: getfield      #134                // Field IntegralLensFamily$module:Lscalaz/LensInstances$IntegralLensFamily$;
       6: ifnonnull     21
       9: aload_0
      10: new           #29                 // class scalaz/LensInstances$IntegralLensFamily$
      13: dup
      14: aload_0
      15: invokespecial #321                // Method scalaz/LensInstances$IntegralLensFamily$."<init>":(Lscalaz/LensInstances;)V
      18: putfield      #134                // Field IntegralLensFamily$module:Lscalaz/LensInstances$IntegralLensFamily$;
      21: aload_0
      22: monitorexit
      23: return
      24: aload_0
      25: monitorexit
      26: athrow
    Exception table:
       from    to  target type
           2    21    24   any

  public scalaz.LensInstances();
    Code:
       0: aload_0
       1: invokespecial #323                // Method scalaz/LensInstances0."<init>":()V
       4: aload_0
       5: new           #10                 // class scalaz/LensInstances$$anon$5
       8: dup
       9: aconst_null
      10: invokespecial #324                // Method scalaz/LensInstances$$anon$5."<init>":(Lscalaz/LensInstances;)V
      13: putfield      #140                // Field lensCategory:Lscalaz/LensCategory;
      16: aload_0
      17: aload_0
      18: invokevirtual #326                // Method SetLensFamily:()Lscalaz/LensInstances$SetLensFamily$;
      21: putfield      #160                // Field SetLens:Lscalaz/LensInstances$SetLensFamily$;
      24: aload_0
      25: aload_0
      26: invokevirtual #328                // Method MapLensFamily:()Lscalaz/LensInstances$MapLensFamily$;
      29: putfield      #168                // Field MapLens:Lscalaz/LensInstances$MapLensFamily$;
      32: aload_0
      33: aload_0
      34: invokevirtual #330                // Method SeqLikeLensFamily:()Lscalaz/LensInstances$SeqLikeLensFamily$;
      37: putfield      #174                // Field SeqLikeLens:Lscalaz/LensInstances$SeqLikeLensFamily$;
      40: aload_0
      41: aload_0
      42: invokevirtual #332                // Method QueueLensFamily:()Lscalaz/LensInstances$QueueLensFamily$;
      45: putfield      #182                // Field QueueLens:Lscalaz/LensInstances$QueueLensFamily$;
      48: aload_0
      49: aload_0
      50: invokevirtual #334                // Method ArrayLensFamily:()Lscalaz/LensInstances$ArrayLensFamily$;
      53: putfield      #188                // Field ArrayLens:Lscalaz/LensInstances$ArrayLensFamily$;
      56: aload_0
      57: aload_0
      58: invokevirtual #336                // Method NumericLensFamily:()Lscalaz/LensInstances$NumericLensFamily$;
      61: putfield      #194                // Field NumericLens:Lscalaz/LensInstances$NumericLensFamily$;
      64: aload_0
      65: aload_0
      66: invokevirtual #338                // Method FractionalLensFamily:()Lscalaz/LensInstances$FractionalLensFamily$;
      69: putfield      #218                // Field FractionalLens:Lscalaz/LensInstances$FractionalLensFamily$;
      72: aload_0
      73: aload_0
      74: invokevirtual #340                // Method IntegralLensFamily:()Lscalaz/LensInstances$IntegralLensFamily$;
      77: putfield      #230                // Field IntegralLens:Lscalaz/LensInstances$IntegralLensFamily$;
      80: return
}
