Compiled from "Name.scala"
public final class scalaz.Need<A> extends scalaz.Name<A> {
  private A value;

  private scala.Function0<A> eval;

  private volatile boolean bitmap$0;

  public static scalaz.IsCovariant<scalaz.Value> covariant();
    Code:
       0: getstatic     #26                 // Field scalaz/Need$.MODULE$:Lscalaz/Need$;
       3: invokevirtual #28                 // Method scalaz/Need$.covariant:()Lscalaz/IsCovariant;
       6: areturn

  public static <A> scalaz.Equal<scalaz.Need<A>> needEqual(scalaz.Equal<A>);
    Code:
       0: getstatic     #26                 // Field scalaz/Need$.MODULE$:Lscalaz/Need$;
       3: aload_0
       4: invokevirtual #34                 // Method scalaz/Need$.needEqual:(Lscalaz/Equal;)Lscalaz/Equal;
       7: areturn

  public static scalaz.Monad<scalaz.Need> need();
    Code:
       0: getstatic     #26                 // Field scalaz/Need$.MODULE$:Lscalaz/Need$;
       3: invokevirtual #39                 // Method scalaz/Need$.need:()Lscalaz/Monad;
       6: areturn

  public static <A> scala.Option<A> unapply(scalaz.Need<A>);
    Code:
       0: getstatic     #26                 // Field scalaz/Need$.MODULE$:Lscalaz/Need$;
       3: aload_0
       4: invokevirtual #45                 // Method scalaz/Need$.unapply:(Lscalaz/Need;)Lscala/Option;
       7: areturn

  public static <A> scalaz.Need<A> apply(scala.Function0<A>);
    Code:
       0: getstatic     #26                 // Field scalaz/Need$.MODULE$:Lscalaz/Need$;
       3: ifnonnull     8
       6: aconst_null
       7: athrow
       8: new           #2                  // class scalaz/Need
      11: dup
      12: aload_0
      13: invokespecial #53                 // Method "<init>":(Lscala/Function0;)V
      16: areturn

  private A value$lzycompute();
    Code:
       0: aload_0
       1: monitorenter
       2: aload_0
       3: getfield      #58                 // Field bitmap$0:Z
       6: ifne          34
       9: aload_0
      10: aload_0
      11: getfield      #60                 // Field eval:Lscala/Function0;
      14: invokeinterface #64,  1           // InterfaceMethod scala/Function0.apply:()Ljava/lang/Object;
      19: astore_1
      20: aload_0
      21: aconst_null
      22: putfield      #60                 // Field eval:Lscala/Function0;
      25: aload_1
      26: putfield      #66                 // Field value:Ljava/lang/Object;
      29: aload_0
      30: iconst_1
      31: putfield      #58                 // Field bitmap$0:Z
      34: aload_0
      35: monitorexit
      36: goto          42
      39: aload_0
      40: monitorexit
      41: athrow
      42: aload_0
      43: getfield      #66                 // Field value:Ljava/lang/Object;
      46: areturn
    Exception table:
       from    to  target type
           2    34    39   any

  public A value();
    Code:
       0: aload_0
       1: getfield      #58                 // Field bitmap$0:Z
       4: ifne          12
       7: aload_0
       8: invokespecial #73                 // Method value$lzycompute:()Ljava/lang/Object;
      11: areturn
      12: aload_0
      13: getfield      #66                 // Field value:Ljava/lang/Object;
      16: areturn

  public scalaz.Need(scala.Function0<A>);
    Code:
       0: aload_0
       1: aload_1
       2: putfield      #60                 // Field eval:Lscala/Function0;
       5: aload_0
       6: invokespecial #77                 // Method scalaz/Name."<init>":()V
       9: return
}
