Compiled from "NullArgument.scala"
public interface scalaz.NullArgumentSemigroup<A, B> extends scalaz.Semigroup<scalaz.NullArgument<A, B>> {
  public abstract scalaz.Semigroup<B> M();

  public static scalaz.NullArgument append$(scalaz.NullArgumentSemigroup, scalaz.NullArgument, scala.Function0);
    Code:
       0: aload_0
       1: aload_1
       2: aload_2
       3: invokespecial #23                 // InterfaceMethod append:(Lscalaz/NullArgument;Lscala/Function0;)Lscalaz/NullArgument;
       6: areturn

  public default scalaz.NullArgument<A, B> append(scalaz.NullArgument<A, B>, scala.Function0<scalaz.NullArgument<A, B>>);
    Code:
       0: aload_1
       1: aload_2
       2: invokeinterface #33,  1           // InterfaceMethod scala/Function0.apply:()Ljava/lang/Object;
       7: checkcast     #35                 // class scalaz/NullArgument
      10: aload_0
      11: invokeinterface #37,  1           // InterfaceMethod M:()Lscalaz/Semigroup;
      16: invokevirtual #41                 // Method scalaz/NullArgument.$bar$plus$bar:(Lscalaz/NullArgument;Lscalaz/Semigroup;)Lscalaz/NullArgument;
      19: areturn

  public static void $init$(scalaz.NullArgumentSemigroup);
    Code:
       0: return
}
