Compiled from "OneAnd.scala"
public abstract class scalaz.OneAndInstances extends scalaz.OneAndInstances0 {
  public <F> scalaz.Plus<?> oneAndPlus(scalaz.Applicative<F>, scalaz.Plus<F>);
    Code:
       0: new           #26                 // class scalaz/OneAndInstances$$anon$12
       3: dup
       4: aconst_null
       5: aload_1
       6: aload_2
       7: invokespecial #50                 // Method scalaz/OneAndInstances$$anon$12."<init>":(Lscalaz/OneAndInstances;Lscalaz/Applicative;Lscalaz/Plus;)V
      10: areturn

  public <F> scalaz.Traverse1<?> oneAndTraverse1(scalaz.Traverse1<F>);
    Code:
       0: new           #28                 // class scalaz/OneAndInstances$$anon$13
       3: dup
       4: aconst_null
       5: aload_1
       6: invokespecial #61                 // Method scalaz/OneAndInstances$$anon$13."<init>":(Lscalaz/OneAndInstances;Lscalaz/Traverse1;)V
       9: areturn

  public <F, A> scalaz.Show<scalaz.OneAnd<F, A>> oneAndShow(scalaz.Show<A>, scalaz.Show<F>);
    Code:
       0: getstatic     #73                 // Field scalaz/Show$.MODULE$:Lscalaz/Show$;
       3: aload_1
       4: aload_2
       5: invokedynamic #97,  0             // InvokeDynamic #0:apply:(Lscalaz/Show;Lscalaz/Show;)Lscala/Function1;
      10: astore_3
      11: ifnonnull     16
      14: aconst_null
      15: athrow
      16: new           #36                 // class scalaz/Show$$anon$4
      19: dup
      20: aload_3
      21: invokespecial #100                // Method scalaz/Show$$anon$4."<init>":(Lscala/Function1;)V
      24: areturn

  public <F, A> scalaz.Order<scalaz.OneAnd<F, A>> oneAndOrder(scalaz.Order<A>, scalaz.Order<F>);
    Code:
       0: new           #30                 // class scalaz/OneAndInstances$$anon$14
       3: dup
       4: aconst_null
       5: aload_1
       6: aload_2
       7: invokespecial #111                // Method scalaz/OneAndInstances$$anon$14."<init>":(Lscalaz/OneAndInstances;Lscalaz/Order;Lscalaz/Order;)V
      10: areturn

  public <F, A> scalaz.Semigroup<scalaz.OneAnd<F, A>> oneAndSemigroup(scalaz.Applicative<F>, scalaz.Plus<F>);
    Code:
       0: aload_0
       1: aload_1
       2: aload_2
       3: invokevirtual #119                // Method oneAndPlus:(Lscalaz/Applicative;Lscalaz/Plus;)Lscalaz/Plus;
       6: invokeinterface #125,  1          // InterfaceMethod scalaz/Plus.semigroup:()Lscalaz/Semigroup;
      11: areturn

  public <F> scalaz.Zip<?> oneAndZip(scalaz.Zip<F>);
    Code:
       0: new           #32                 // class scalaz/OneAndInstances$$anon$15
       3: dup
       4: aconst_null
       5: aload_1
       6: invokespecial #132                // Method scalaz/OneAndInstances$$anon$15."<init>":(Lscalaz/OneAndInstances;Lscalaz/Zip;)V
       9: areturn

  public <F> scalaz.Unzip<?> oneAndUnzip(scalaz.Unzip<F>);
    Code:
       0: new           #34                 // class scalaz/OneAndInstances$$anon$16
       3: dup
       4: aconst_null
       5: aload_1
       6: invokespecial #140                // Method scalaz/OneAndInstances$$anon$16."<init>":(Lscalaz/OneAndInstances;Lscalaz/Unzip;)V
       9: areturn

  public static final scalaz.Cord $anonfun$oneAndShow$1(scalaz.Show, scalaz.Show, scalaz.OneAnd);
    Code:
       0: getstatic     #147                // Field scalaz/Cord$CordInterpolator$.MODULE$:Lscalaz/Cord$CordInterpolator$;
       3: getstatic     #152                // Field scalaz/syntax/package$.MODULE$:Lscalaz/syntax/package$;
       6: invokevirtual #156                // Method scalaz/syntax/package$.show:()Lscalaz/syntax/Syntaxes$show$;
       9: new           #158                // class scala/StringContext
      12: dup
      13: getstatic     #163                // Field scala/Predef$.MODULE$:Lscala/Predef$;
      16: iconst_3
      17: anewarray     #165                // class java/lang/String
      20: dup
      21: iconst_0
      22: ldc           #167                // String OneAnd(
      24: aastore
      25: dup
      26: iconst_1
      27: ldc           #169                // String ,
      29: aastore
      30: dup
      31: iconst_2
      32: ldc           #171                // String )
      34: aastore
      35: checkcast     #173                // class "[Ljava/lang/Object;"
      38: invokevirtual #177                // Method scala/Predef$.wrapRefArray:([Ljava/lang/Object;)Lscala/collection/mutable/WrappedArray;
      41: invokespecial #180                // Method scala/StringContext."<init>":(Lscala/collection/Seq;)V
      44: invokevirtual #184                // Method scalaz/syntax/Syntaxes$show$.cordInterpolator:(Lscala/StringContext;)Lscala/StringContext;
      47: getstatic     #163                // Field scala/Predef$.MODULE$:Lscala/Predef$;
      50: iconst_2
      51: anewarray     #20                 // class scalaz/Cord$CordInterpolator$Cords
      54: dup
      55: iconst_0
      56: new           #20                 // class scalaz/Cord$CordInterpolator$Cords
      59: dup
      60: getstatic     #187                // Field scalaz/Cord$CordInterpolator$Cords$.MODULE$:Lscalaz/Cord$CordInterpolator$Cords$;
      63: aload_2
      64: invokevirtual #193                // Method scalaz/OneAnd.head:()Ljava/lang/Object;
      67: aload_0
      68: invokevirtual #197                // Method scalaz/Cord$CordInterpolator$Cords$.mat:(Ljava/lang/Object;Lscalaz/Show;)Lscalaz/Cord;
      71: invokespecial #200                // Method scalaz/Cord$CordInterpolator$Cords."<init>":(Lscalaz/Cord;)V
      74: aastore
      75: dup
      76: iconst_1
      77: new           #20                 // class scalaz/Cord$CordInterpolator$Cords
      80: dup
      81: getstatic     #187                // Field scalaz/Cord$CordInterpolator$Cords$.MODULE$:Lscalaz/Cord$CordInterpolator$Cords$;
      84: aload_2
      85: invokevirtual #203                // Method scalaz/OneAnd.tail:()Ljava/lang/Object;
      88: aload_1
      89: invokevirtual #197                // Method scalaz/Cord$CordInterpolator$Cords$.mat:(Ljava/lang/Object;Lscalaz/Show;)Lscalaz/Cord;
      92: invokespecial #200                // Method scalaz/Cord$CordInterpolator$Cords."<init>":(Lscalaz/Cord;)V
      95: aastore
      96: invokevirtual #207                // Method scala/Predef$.genericWrapArray:(Ljava/lang/Object;)Lscala/collection/mutable/WrappedArray;
      99: invokevirtual #211                // Method scalaz/Cord$CordInterpolator$.cord$extension:(Lscala/StringContext;Lscala/collection/Seq;)Lscalaz/Cord;
     102: areturn

  public scalaz.OneAndInstances();
    Code:
       0: aload_0
       1: invokespecial #215                // Method scalaz/OneAndInstances0."<init>":()V
       4: return

  private static java.lang.Object $deserializeLambda$(java.lang.invoke.SerializedLambda);
    Code:
       0: aload_0
       1: invokedynamic #227,  0            // InvokeDynamic #1:lambdaDeserialize:(Ljava/lang/invoke/SerializedLambda;)Ljava/lang/Object;
       6: areturn
}
