Compiled from "OneOr.scala"
public interface scalaz.OneOrEqual<F, A> extends scalaz.Equal<scalaz.OneOr<F, A>> {
  public abstract scalaz.Equal<A> OA();

  public abstract scalaz.Equal<F> OFA();

  public static boolean equal$(scalaz.OneOrEqual, scalaz.OneOr, scalaz.OneOr);
    Code:
       0: aload_0
       1: aload_1
       2: aload_2
       3: invokespecial #25                 // InterfaceMethod equal:(Lscalaz/OneOr;Lscalaz/OneOr;)Z
       6: ireturn

  public default boolean equal(scalaz.OneOr<F, A>, scalaz.OneOr<F, A>);
    Code:
       0: aload_1
       1: invokevirtual #34                 // Method scalaz/OneOr.run:()Lscalaz/$bslash$div;
       4: aload_2
       5: invokevirtual #34                 // Method scalaz/OneOr.run:()Lscalaz/$bslash$div;
       8: aload_0
       9: invokeinterface #36,  1           // InterfaceMethod OFA:()Lscalaz/Equal;
      14: aload_0
      15: invokeinterface #38,  1           // InterfaceMethod OA:()Lscalaz/Equal;
      20: invokevirtual #44                 // Method scalaz/$bslash$div.$eq$eq$eq:(Lscalaz/$bslash$div;Lscalaz/Equal;Lscalaz/Equal;)Z
      23: ireturn

  public static boolean equalIsNatural$(scalaz.OneOrEqual);
    Code:
       0: aload_0
       1: invokespecial #51                 // InterfaceMethod equalIsNatural:()Z
       4: ireturn

  public default boolean equalIsNatural();
    Code:
       0: aload_0
       1: invokeinterface #38,  1           // InterfaceMethod OA:()Lscalaz/Equal;
       6: invokeinterface #52,  1           // InterfaceMethod scalaz/Equal.equalIsNatural:()Z
      11: ifeq          30
      14: aload_0
      15: invokeinterface #36,  1           // InterfaceMethod OFA:()Lscalaz/Equal;
      20: invokeinterface #52,  1           // InterfaceMethod scalaz/Equal.equalIsNatural:()Z
      25: ifeq          30
      28: iconst_1
      29: ireturn
      30: iconst_0
      31: ireturn

  public static void $init$(scalaz.OneOrEqual);
    Code:
       0: return
}
