Compiled from "Ordering.scala"
public abstract class scalaz.OrderingInstances {
  private final scalaz.Enum<scalaz.Ordering> orderingInstance;

  public scalaz.Enum<scalaz.Ordering> orderingInstance();
    Code:
       0: aload_0
       1: getfield      #17                 // Field orderingInstance:Lscalaz/Enum;
       4: areturn

  public scalaz.OrderingInstances();
    Code:
       0: aload_0
       1: invokespecial #23                 // Method java/lang/Object."<init>":()V
       4: aload_0
       5: new           #10                 // class scalaz/OrderingInstances$$anon$1
       8: dup
       9: aconst_null
      10: invokespecial #26                 // Method scalaz/OrderingInstances$$anon$1."<init>":(Lscalaz/OrderingInstances;)V
      13: putfield      #17                 // Field orderingInstance:Lscalaz/Enum;
      16: return
}
