Compiled from "Product.scala"
public interface scalaz.ProductBitraverse<F, G> extends scalaz.Bitraverse<?>, scalaz.ProductBifunctor<F, G>, scalaz.ProductBifoldable<F, G> {
  public abstract scalaz.Bitraverse<F> F();

  public abstract scalaz.Bitraverse<G> G();

  public static java.lang.Object bitraverseImpl$(scalaz.ProductBitraverse, scala.Tuple2, scala.Function1, scala.Function1, scalaz.Applicative);
    Code:
       0: aload_0
       1: aload_1
       2: aload_2
       3: aload_3
       4: aload         4
       6: invokespecial #36                 // InterfaceMethod bitraverseImpl:(Lscala/Tuple2;Lscala/Function1;Lscala/Function1;Lscalaz/Applicative;)Ljava/lang/Object;
       9: areturn

  public default <X, A, B, C, D> X bitraverseImpl(scala.Tuple2<F, G>, scala.Function1<A, X>, scala.Function1<B, X>, scalaz.Applicative<X>);
    Code:
       0: getstatic     #47                 // Field scalaz/Applicative$.MODULE$:Lscalaz/Applicative$;
       3: ifnonnull     8
       6: aconst_null
       7: athrow
       8: aload         4
      10: aload_0
      11: aload_1
      12: aload_2
      13: aload_3
      14: aload         4
      16: invokedynamic #68,  0             // InvokeDynamic #0:apply:(Lscalaz/ProductBitraverse;Lscala/Tuple2;Lscala/Function1;Lscala/Function1;Lscalaz/Applicative;)Lscala/Function0;
      21: aload_0
      22: aload_1
      23: aload_2
      24: aload_3
      25: aload         4
      27: invokedynamic #73,  0             // InvokeDynamic #1:apply:(Lscalaz/ProductBitraverse;Lscala/Tuple2;Lscala/Function1;Lscala/Function1;Lscalaz/Applicative;)Lscala/Function0;
      32: invokeinterface #79,  3           // InterfaceMethod scalaz/Applicative.tuple2:(Lscala/Function0;Lscala/Function0;)Ljava/lang/Object;
      37: areturn

  public static java.lang.Object $anonfun$bitraverseImpl$1(scalaz.ProductBitraverse, scala.Tuple2, scala.Function1, scala.Function1, scalaz.Applicative);
    Code:
       0: aload_0
       1: invokeinterface #86,  1           // InterfaceMethod F:()Lscalaz/Bitraverse;
       6: aload_1
       7: invokevirtual #91                 // Method scala/Tuple2._1:()Ljava/lang/Object;
      10: aload_2
      11: aload_3
      12: aload         4
      14: invokeinterface #95,  5           // InterfaceMethod scalaz/Bitraverse.bitraverse:(Ljava/lang/Object;Lscala/Function1;Lscala/Function1;Lscalaz/Applicative;)Ljava/lang/Object;
      19: areturn

  public static java.lang.Object $anonfun$bitraverseImpl$2(scalaz.ProductBitraverse, scala.Tuple2, scala.Function1, scala.Function1, scalaz.Applicative);
    Code:
       0: aload_0
       1: invokeinterface #97,  1           // InterfaceMethod G:()Lscalaz/Bitraverse;
       6: aload_1
       7: invokevirtual #100                // Method scala/Tuple2._2:()Ljava/lang/Object;
      10: aload_2
      11: aload_3
      12: aload         4
      14: invokeinterface #95,  5           // InterfaceMethod scalaz/Bitraverse.bitraverse:(Ljava/lang/Object;Lscala/Function1;Lscala/Function1;Lscalaz/Applicative;)Ljava/lang/Object;
      19: areturn

  public static void $init$(scalaz.ProductBitraverse);
    Code:
       0: return

  private static java.lang.Object $deserializeLambda$(java.lang.invoke.SerializedLambda);
    Code:
       0: aload_0
       1: invokedynamic #114,  0            // InvokeDynamic #2:lambdaDeserialize:(Ljava/lang/invoke/SerializedLambda;)Ljava/lang/Object;
       6: areturn
}
