Compiled from "Semigroup.scala"
public interface scalaz.Semigroup$SemigroupApply extends scalaz.Apply<?> {
  public static java.lang.Object map$(scalaz.Semigroup$SemigroupApply, java.lang.Object, scala.Function1);
    Code:
       0: aload_0
       1: aload_1
       2: aload_2
       3: invokespecial #20                 // InterfaceMethod map:(Ljava/lang/Object;Lscala/Function1;)Ljava/lang/Object;
       6: areturn

  public default <A, B> F map(F, scala.Function1<A, B>);
    Code:
       0: aload_1
       1: areturn

  public static java.lang.Object ap$(scalaz.Semigroup$SemigroupApply, scala.Function0, scala.Function0);
    Code:
       0: aload_0
       1: aload_1
       2: aload_2
       3: invokespecial #31                 // InterfaceMethod ap:(Lscala/Function0;Lscala/Function0;)Ljava/lang/Object;
       6: areturn

  public default <A, B> F ap(scala.Function0<F>, scala.Function0<F>);
    Code:
       0: aload_0
       1: invokeinterface #37,  1           // InterfaceMethod scalaz$Semigroup$SemigroupApply$$$outer:()Lscalaz/Semigroup;
       6: aload_2
       7: invokeinterface #43,  1           // InterfaceMethod scala/Function0.apply:()Ljava/lang/Object;
      12: aload_1
      13: invokeinterface #47,  3           // InterfaceMethod scalaz/Semigroup.append:(Ljava/lang/Object;Lscala/Function0;)Ljava/lang/Object;
      18: areturn

  public abstract scalaz.Semigroup scalaz$Semigroup$SemigroupApply$$$outer();

  public static void $init$(scalaz.Semigroup<F>.SemigroupApply);
    Code:
       0: return
}
