Compiled from "Tags.scala"
public final class scalaz.Tags {
  public static scalaz.Tag$TagOf<scalaz.Tags$Parallel> Parallel();
    Code:
       0: getstatic     #63                 // Field scalaz/Tags$.MODULE$:Lscalaz/Tags$;
       3: invokevirtual #65                 // Method scalaz/Tags$.Parallel:()Lscalaz/Tag$TagOf;
       6: areturn

  public static scalaz.Tag$TagOf<scalaz.Tags$Conjunction> Conjunction();
    Code:
       0: getstatic     #63                 // Field scalaz/Tags$.MODULE$:Lscalaz/Tags$;
       3: invokevirtual #68                 // Method scalaz/Tags$.Conjunction:()Lscalaz/Tag$TagOf;
       6: areturn

  public static scalaz.Tag$TagOf<scalaz.Tags$Disjunction> Disjunction();
    Code:
       0: getstatic     #63                 // Field scalaz/Tags$.MODULE$:Lscalaz/Tags$;
       3: invokevirtual #71                 // Method scalaz/Tags$.Disjunction:()Lscalaz/Tag$TagOf;
       6: areturn

  public static scalaz.Tag$TagOf<scalaz.Tags$Zip> Zip();
    Code:
       0: getstatic     #63                 // Field scalaz/Tags$.MODULE$:Lscalaz/Tags$;
       3: invokevirtual #74                 // Method scalaz/Tags$.Zip:()Lscalaz/Tag$TagOf;
       6: areturn

  public static scalaz.Tag$TagOf<scalaz.Tags$Dual> Dual();
    Code:
       0: getstatic     #63                 // Field scalaz/Tags$.MODULE$:Lscalaz/Tags$;
       3: invokevirtual #77                 // Method scalaz/Tags$.Dual:()Lscalaz/Tag$TagOf;
       6: areturn

  public static scalaz.Tag$TagOf<scalaz.Tags$Multiplication> Multiplication();
    Code:
       0: getstatic     #63                 // Field scalaz/Tags$.MODULE$:Lscalaz/Tags$;
       3: invokevirtual #80                 // Method scalaz/Tags$.Multiplication:()Lscalaz/Tag$TagOf;
       6: areturn

  public static scalaz.Tag$TagOf<scalaz.Tags$Max> Max();
    Code:
       0: getstatic     #63                 // Field scalaz/Tags$.MODULE$:Lscalaz/Tags$;
       3: invokevirtual #83                 // Method scalaz/Tags$.Max:()Lscalaz/Tag$TagOf;
       6: areturn

  public static scalaz.Tag$TagOf<scalaz.Tags$Min> Min();
    Code:
       0: getstatic     #63                 // Field scalaz/Tags$.MODULE$:Lscalaz/Tags$;
       3: invokevirtual #86                 // Method scalaz/Tags$.Min:()Lscalaz/Tag$TagOf;
       6: areturn

  public static scalaz.Tag$TagOf<scalaz.Tags$Last> Last();
    Code:
       0: getstatic     #63                 // Field scalaz/Tags$.MODULE$:Lscalaz/Tags$;
       3: invokevirtual #89                 // Method scalaz/Tags$.Last:()Lscalaz/Tag$TagOf;
       6: areturn

  public static scalaz.Tag$TagOf<scalaz.Tags$First> First();
    Code:
       0: getstatic     #63                 // Field scalaz/Tags$.MODULE$:Lscalaz/Tags$;
       3: invokevirtual #92                 // Method scalaz/Tags$.First:()Lscalaz/Tag$TagOf;
       6: areturn

  public static scalaz.Tag$TagOf<scalaz.Tags$MaxVal> MaxVal();
    Code:
       0: getstatic     #63                 // Field scalaz/Tags$.MODULE$:Lscalaz/Tags$;
       3: invokevirtual #95                 // Method scalaz/Tags$.MaxVal:()Lscalaz/Tag$TagOf;
       6: areturn

  public static scalaz.Tag$TagOf<scalaz.Tags$MinVal> MinVal();
    Code:
       0: getstatic     #63                 // Field scalaz/Tags$.MODULE$:Lscalaz/Tags$;
       3: invokevirtual #98                 // Method scalaz/Tags$.MinVal:()Lscalaz/Tag$TagOf;
       6: areturn

  public static scalaz.Tag$TagOf<scalaz.Tags$LastVal> LastVal();
    Code:
       0: getstatic     #63                 // Field scalaz/Tags$.MODULE$:Lscalaz/Tags$;
       3: invokevirtual #101                // Method scalaz/Tags$.LastVal:()Lscalaz/Tag$TagOf;
       6: areturn

  public static scalaz.Tag$TagOf<scalaz.Tags$FirstVal> FirstVal();
    Code:
       0: getstatic     #63                 // Field scalaz/Tags$.MODULE$:Lscalaz/Tags$;
       3: invokevirtual #104                // Method scalaz/Tags$.FirstVal:()Lscalaz/Tag$TagOf;
       6: areturn
}
