Compiled from "These.scala"
public abstract class scalaz.TheseInstances extends scalaz.TheseInstances0 {
  public <A, B> scalaz.Band<scalaz.$bslash$amp$div<A, B>> TheseBand(scalaz.Band<A>, scalaz.Band<B>);
    Code:
       0: new           #10                 // class scalaz/TheseInstances$$anon$1
       3: dup
       4: aconst_null
       5: aload_1
       6: aload_2
       7: invokespecial #19                 // Method scalaz/TheseInstances$$anon$1."<init>":(Lscalaz/TheseInstances;Lscalaz/Band;Lscalaz/Band;)V
      10: areturn

  public scalaz.TheseInstances();
    Code:
       0: aload_0
       1: invokespecial #25                 // Method scalaz/TheseInstances0."<init>":()V
       4: return
}
