Compiled from "These.scala"
public final class scalaz.TheseInstances$$anon$1 implements scalaz.Band<scalaz.$bslash$amp$div<A, B>> {
  private final scalaz.syntax.BandSyntax<scalaz.$bslash$amp$div<A, B>> bandSyntax;

  private final scalaz.syntax.SemigroupSyntax<scalaz.$bslash$amp$div<A, B>> semigroupSyntax;

  private final scalaz.Band evidence$3$1;

  private final scalaz.Band evidence$4$1;

  public java.lang.Object multiply1(java.lang.Object, int);
    Code:
       0: aload_0
       1: aload_1
       2: iload_2
       3: invokestatic  #54                 // InterfaceMethod scalaz/Band.multiply1$:(Lscalaz/Band;Ljava/lang/Object;I)Ljava/lang/Object;
       6: areturn

  public scalaz.Band<scalaz.$bslash$amp$div<A, B>>.BandLaw bandLaw();
    Code:
       0: aload_0
       1: invokestatic  #65                 // InterfaceMethod scalaz/Band.bandLaw$:(Lscalaz/Band;)Lscalaz/Band$BandLaw;
       4: areturn

  public <S> scalaz.Maybe<scalaz.$bslash$amp$div<A, B>> unfoldlSumOpt(S, scala.Function1<S, scalaz.Maybe<scala.Tuple2<S, scalaz.$bslash$amp$div<A, B>>>>);
    Code:
       0: aload_0
       1: aload_1
       2: aload_2
       3: invokestatic  #74                 // InterfaceMethod scalaz/Semigroup.unfoldlSumOpt$:(Lscalaz/Semigroup;Ljava/lang/Object;Lscala/Function1;)Lscalaz/Maybe;
       6: areturn

  public <S> scalaz.Maybe<scalaz.$bslash$amp$div<A, B>> unfoldrSumOpt(S, scala.Function1<S, scalaz.Maybe<scala.Tuple2<scalaz.$bslash$amp$div<A, B>, S>>>);
    Code:
       0: aload_0
       1: aload_1
       2: aload_2
       3: invokestatic  #80                 // InterfaceMethod scalaz/Semigroup.unfoldrSumOpt$:(Lscalaz/Semigroup;Ljava/lang/Object;Lscala/Function1;)Lscalaz/Maybe;
       6: areturn

  public final scalaz.Compose<?> compose();
    Code:
       0: aload_0
       1: invokestatic  #87                 // InterfaceMethod scalaz/Semigroup.compose$:(Lscalaz/Semigroup;)Lscalaz/Compose;
       4: areturn

  public final scalaz.Apply<?> apply();
    Code:
       0: aload_0
       1: invokestatic  #94                 // InterfaceMethod scalaz/Semigroup.apply$:(Lscalaz/Semigroup;)Lscalaz/Apply;
       4: areturn

  public scalaz.Semigroup<scalaz.$bslash$amp$div<A, B>>.SemigroupLaw semigroupLaw();
    Code:
       0: aload_0
       1: invokestatic  #101                // InterfaceMethod scalaz/Semigroup.semigroupLaw$:(Lscalaz/Semigroup;)Lscalaz/Semigroup$SemigroupLaw;
       4: areturn

  public scalaz.syntax.BandSyntax<scalaz.$bslash$amp$div<A, B>> bandSyntax();
    Code:
       0: aload_0
       1: getfield      #105                // Field bandSyntax:Lscalaz/syntax/BandSyntax;
       4: areturn

  public void scalaz$Band$_setter_$bandSyntax_$eq(scalaz.syntax.BandSyntax<scalaz.$bslash$amp$div<A, B>>);
    Code:
       0: aload_0
       1: aload_1
       2: putfield      #105                // Field bandSyntax:Lscalaz/syntax/BandSyntax;
       5: return

  public scalaz.syntax.SemigroupSyntax<scalaz.$bslash$amp$div<A, B>> semigroupSyntax();
    Code:
       0: aload_0
       1: getfield      #113                // Field semigroupSyntax:Lscalaz/syntax/SemigroupSyntax;
       4: areturn

  public void scalaz$Semigroup$_setter_$semigroupSyntax_$eq(scalaz.syntax.SemigroupSyntax<scalaz.$bslash$amp$div<A, B>>);
    Code:
       0: aload_0
       1: aload_1
       2: putfield      #113                // Field semigroupSyntax:Lscalaz/syntax/SemigroupSyntax;
       5: return

  public scalaz.$bslash$amp$div<A, B> append(scalaz.$bslash$amp$div<A, B>, scala.Function0<scalaz.$bslash$amp$div<A, B>>);
    Code:
       0: aload_1
       1: aload_0
       2: getfield      #123                // Field evidence$3$1:Lscalaz/Band;
       5: aload_0
       6: getfield      #125                // Field evidence$4$1:Lscalaz/Band;
       9: astore        4
      11: astore_3
      12: ifnonnull     17
      15: aconst_null
      16: athrow
      17: new           #127                // class scala/Tuple2
      20: dup
      21: aload_2
      22: invokeinterface #132,  1          // InterfaceMethod scala/Function0.apply:()Ljava/lang/Object;
      27: astore        55
      29: aload_1
      30: aload         55
      32: invokespecial #136                // Method scala/Tuple2."<init>":(Ljava/lang/Object;Ljava/lang/Object;)V
      35: astore        6
      37: aload_1
      38: astore        7
      40: aload         55
      42: checkcast     #22                 // class scalaz/$bslash$amp$div
      45: astore        8
      47: aload         7
      49: instanceof    #28                 // class scalaz/$bslash$amp$div$This
      52: ifeq          110
      55: aload         7
      57: checkcast     #28                 // class scalaz/$bslash$amp$div$This
      60: invokevirtual #139                // Method scalaz/$bslash$amp$div$This.aa:()Ljava/lang/Object;
      63: astore        9
      65: aload         8
      67: instanceof    #28                 // class scalaz/$bslash$amp$div$This
      70: ifeq          110
      73: aload         8
      75: checkcast     #28                 // class scalaz/$bslash$amp$div$This
      78: invokevirtual #139                // Method scalaz/$bslash$amp$div$This.aa:()Ljava/lang/Object;
      81: astore        10
      83: new           #28                 // class scalaz/$bslash$amp$div$This
      86: dup
      87: aload_3
      88: aload         9
      90: aload         10
      92: invokedynamic #159,  0            // InvokeDynamic #0:apply:(Ljava/lang/Object;)Lscala/Function0;
      97: invokeinterface #162,  3          // InterfaceMethod scalaz/Semigroup.append:(Ljava/lang/Object;Lscala/Function0;)Ljava/lang/Object;
     102: invokespecial #165                // Method scalaz/$bslash$amp$div$This."<init>":(Ljava/lang/Object;)V
     105: astore        5
     107: goto          775
     110: aload_1
     111: astore        11
     113: aload         55
     115: checkcast     #22                 // class scalaz/$bslash$amp$div
     118: astore        12
     120: aload         11
     122: instanceof    #28                 // class scalaz/$bslash$amp$div$This
     125: ifeq          196
     128: aload         11
     130: checkcast     #28                 // class scalaz/$bslash$amp$div$This
     133: invokevirtual #139                // Method scalaz/$bslash$amp$div$This.aa:()Ljava/lang/Object;
     136: astore        13
     138: aload         12
     140: instanceof    #20                 // class scalaz/$bslash$amp$div$Both
     143: ifeq          196
     146: aload         12
     148: checkcast     #20                 // class scalaz/$bslash$amp$div$Both
     151: astore        14
     153: aload         14
     155: invokevirtual #166                // Method scalaz/$bslash$amp$div$Both.aa:()Ljava/lang/Object;
     158: astore        15
     160: aload         14
     162: invokevirtual #169                // Method scalaz/$bslash$amp$div$Both.bb:()Ljava/lang/Object;
     165: astore        16
     167: new           #20                 // class scalaz/$bslash$amp$div$Both
     170: dup
     171: aload_3
     172: aload         13
     174: aload         15
     176: invokedynamic #174,  0            // InvokeDynamic #1:apply:(Ljava/lang/Object;)Lscala/Function0;
     181: invokeinterface #162,  3          // InterfaceMethod scalaz/Semigroup.append:(Ljava/lang/Object;Lscala/Function0;)Ljava/lang/Object;
     186: aload         16
     188: invokespecial #175                // Method scalaz/$bslash$amp$div$Both."<init>":(Ljava/lang/Object;Ljava/lang/Object;)V
     191: astore        5
     193: goto          775
     196: aload_1
     197: astore        17
     199: aload         55
     201: checkcast     #22                 // class scalaz/$bslash$amp$div
     204: astore        18
     206: aload         17
     208: instanceof    #28                 // class scalaz/$bslash$amp$div$This
     211: ifeq          258
     214: aload         17
     216: checkcast     #28                 // class scalaz/$bslash$amp$div$This
     219: invokevirtual #139                // Method scalaz/$bslash$amp$div$This.aa:()Ljava/lang/Object;
     222: astore        19
     224: aload         18
     226: instanceof    #25                 // class scalaz/$bslash$amp$div$That
     229: ifeq          258
     232: aload         18
     234: checkcast     #25                 // class scalaz/$bslash$amp$div$That
     237: invokevirtual #176                // Method scalaz/$bslash$amp$div$That.bb:()Ljava/lang/Object;
     240: astore        20
     242: new           #20                 // class scalaz/$bslash$amp$div$Both
     245: dup
     246: aload         19
     248: aload         20
     250: invokespecial #175                // Method scalaz/$bslash$amp$div$Both."<init>":(Ljava/lang/Object;Ljava/lang/Object;)V
     253: astore        5
     255: goto          775
     258: aload_1
     259: astore        21
     261: aload         55
     263: checkcast     #22                 // class scalaz/$bslash$amp$div
     266: astore        22
     268: aload         21
     270: instanceof    #20                 // class scalaz/$bslash$amp$div$Both
     273: ifeq          344
     276: aload         21
     278: checkcast     #20                 // class scalaz/$bslash$amp$div$Both
     281: astore        23
     283: aload         23
     285: invokevirtual #166                // Method scalaz/$bslash$amp$div$Both.aa:()Ljava/lang/Object;
     288: astore        24
     290: aload         23
     292: invokevirtual #169                // Method scalaz/$bslash$amp$div$Both.bb:()Ljava/lang/Object;
     295: astore        25
     297: aload         22
     299: instanceof    #28                 // class scalaz/$bslash$amp$div$This
     302: ifeq          344
     305: aload         22
     307: checkcast     #28                 // class scalaz/$bslash$amp$div$This
     310: invokevirtual #139                // Method scalaz/$bslash$amp$div$This.aa:()Ljava/lang/Object;
     313: astore        26
     315: new           #20                 // class scalaz/$bslash$amp$div$Both
     318: dup
     319: aload_3
     320: aload         24
     322: aload         26
     324: invokedynamic #181,  0            // InvokeDynamic #2:apply:(Ljava/lang/Object;)Lscala/Function0;
     329: invokeinterface #162,  3          // InterfaceMethod scalaz/Semigroup.append:(Ljava/lang/Object;Lscala/Function0;)Ljava/lang/Object;
     334: aload         25
     336: invokespecial #175                // Method scalaz/$bslash$amp$div$Both."<init>":(Ljava/lang/Object;Ljava/lang/Object;)V
     339: astore        5
     341: goto          775
     344: aload_1
     345: astore        27
     347: aload         55
     349: checkcast     #22                 // class scalaz/$bslash$amp$div
     352: astore        28
     354: aload         27
     356: instanceof    #20                 // class scalaz/$bslash$amp$div$Both
     359: ifeq          455
     362: aload         27
     364: checkcast     #20                 // class scalaz/$bslash$amp$div$Both
     367: astore        29
     369: aload         29
     371: invokevirtual #166                // Method scalaz/$bslash$amp$div$Both.aa:()Ljava/lang/Object;
     374: astore        30
     376: aload         29
     378: invokevirtual #169                // Method scalaz/$bslash$amp$div$Both.bb:()Ljava/lang/Object;
     381: astore        31
     383: aload         28
     385: instanceof    #20                 // class scalaz/$bslash$amp$div$Both
     388: ifeq          455
     391: aload         28
     393: checkcast     #20                 // class scalaz/$bslash$amp$div$Both
     396: astore        32
     398: aload         32
     400: invokevirtual #166                // Method scalaz/$bslash$amp$div$Both.aa:()Ljava/lang/Object;
     403: astore        33
     405: aload         32
     407: invokevirtual #169                // Method scalaz/$bslash$amp$div$Both.bb:()Ljava/lang/Object;
     410: astore        34
     412: new           #20                 // class scalaz/$bslash$amp$div$Both
     415: dup
     416: aload_3
     417: aload         30
     419: aload         33
     421: invokedynamic #186,  0            // InvokeDynamic #3:apply:(Ljava/lang/Object;)Lscala/Function0;
     426: invokeinterface #162,  3          // InterfaceMethod scalaz/Semigroup.append:(Ljava/lang/Object;Lscala/Function0;)Ljava/lang/Object;
     431: aload         4
     433: aload         31
     435: aload         34
     437: invokedynamic #191,  0            // InvokeDynamic #4:apply:(Ljava/lang/Object;)Lscala/Function0;
     442: invokeinterface #162,  3          // InterfaceMethod scalaz/Semigroup.append:(Ljava/lang/Object;Lscala/Function0;)Ljava/lang/Object;
     447: invokespecial #175                // Method scalaz/$bslash$amp$div$Both."<init>":(Ljava/lang/Object;Ljava/lang/Object;)V
     450: astore        5
     452: goto          775
     455: aload_1
     456: astore        35
     458: aload         55
     460: checkcast     #22                 // class scalaz/$bslash$amp$div
     463: astore        36
     465: aload         35
     467: instanceof    #20                 // class scalaz/$bslash$amp$div$Both
     470: ifeq          542
     473: aload         35
     475: checkcast     #20                 // class scalaz/$bslash$amp$div$Both
     478: astore        37
     480: aload         37
     482: invokevirtual #166                // Method scalaz/$bslash$amp$div$Both.aa:()Ljava/lang/Object;
     485: astore        38
     487: aload         37
     489: invokevirtual #169                // Method scalaz/$bslash$amp$div$Both.bb:()Ljava/lang/Object;
     492: astore        39
     494: aload         36
     496: instanceof    #25                 // class scalaz/$bslash$amp$div$That
     499: ifeq          542
     502: aload         36
     504: checkcast     #25                 // class scalaz/$bslash$amp$div$That
     507: invokevirtual #176                // Method scalaz/$bslash$amp$div$That.bb:()Ljava/lang/Object;
     510: astore        40
     512: new           #20                 // class scalaz/$bslash$amp$div$Both
     515: dup
     516: aload         38
     518: aload         4
     520: aload         39
     522: aload         40
     524: invokedynamic #196,  0            // InvokeDynamic #5:apply:(Ljava/lang/Object;)Lscala/Function0;
     529: invokeinterface #162,  3          // InterfaceMethod scalaz/Semigroup.append:(Ljava/lang/Object;Lscala/Function0;)Ljava/lang/Object;
     534: invokespecial #175                // Method scalaz/$bslash$amp$div$Both."<init>":(Ljava/lang/Object;Ljava/lang/Object;)V
     537: astore        5
     539: goto          775
     542: aload_1
     543: astore        41
     545: aload         55
     547: checkcast     #22                 // class scalaz/$bslash$amp$div
     550: astore        42
     552: aload         41
     554: instanceof    #25                 // class scalaz/$bslash$amp$div$That
     557: ifeq          604
     560: aload         41
     562: checkcast     #25                 // class scalaz/$bslash$amp$div$That
     565: invokevirtual #176                // Method scalaz/$bslash$amp$div$That.bb:()Ljava/lang/Object;
     568: astore        43
     570: aload         42
     572: instanceof    #28                 // class scalaz/$bslash$amp$div$This
     575: ifeq          604
     578: aload         42
     580: checkcast     #28                 // class scalaz/$bslash$amp$div$This
     583: invokevirtual #139                // Method scalaz/$bslash$amp$div$This.aa:()Ljava/lang/Object;
     586: astore        44
     588: new           #20                 // class scalaz/$bslash$amp$div$Both
     591: dup
     592: aload         44
     594: aload         43
     596: invokespecial #175                // Method scalaz/$bslash$amp$div$Both."<init>":(Ljava/lang/Object;Ljava/lang/Object;)V
     599: astore        5
     601: goto          775
     604: aload_1
     605: astore        45
     607: aload         55
     609: checkcast     #22                 // class scalaz/$bslash$amp$div
     612: astore        46
     614: aload         45
     616: instanceof    #25                 // class scalaz/$bslash$amp$div$That
     619: ifeq          691
     622: aload         45
     624: checkcast     #25                 // class scalaz/$bslash$amp$div$That
     627: invokevirtual #176                // Method scalaz/$bslash$amp$div$That.bb:()Ljava/lang/Object;
     630: astore        47
     632: aload         46
     634: instanceof    #20                 // class scalaz/$bslash$amp$div$Both
     637: ifeq          691
     640: aload         46
     642: checkcast     #20                 // class scalaz/$bslash$amp$div$Both
     645: astore        48
     647: aload         48
     649: invokevirtual #166                // Method scalaz/$bslash$amp$div$Both.aa:()Ljava/lang/Object;
     652: astore        49
     654: aload         48
     656: invokevirtual #169                // Method scalaz/$bslash$amp$div$Both.bb:()Ljava/lang/Object;
     659: astore        50
     661: new           #20                 // class scalaz/$bslash$amp$div$Both
     664: dup
     665: aload         49
     667: aload         4
     669: aload         47
     671: aload         50
     673: invokedynamic #201,  0            // InvokeDynamic #6:apply:(Ljava/lang/Object;)Lscala/Function0;
     678: invokeinterface #162,  3          // InterfaceMethod scalaz/Semigroup.append:(Ljava/lang/Object;Lscala/Function0;)Ljava/lang/Object;
     683: invokespecial #175                // Method scalaz/$bslash$amp$div$Both."<init>":(Ljava/lang/Object;Ljava/lang/Object;)V
     686: astore        5
     688: goto          775
     691: aload_1
     692: astore        51
     694: aload         55
     696: checkcast     #22                 // class scalaz/$bslash$amp$div
     699: astore        52
     701: aload         51
     703: instanceof    #25                 // class scalaz/$bslash$amp$div$That
     706: ifeq          765
     709: aload         51
     711: checkcast     #25                 // class scalaz/$bslash$amp$div$That
     714: invokevirtual #176                // Method scalaz/$bslash$amp$div$That.bb:()Ljava/lang/Object;
     717: astore        53
     719: aload         52
     721: instanceof    #25                 // class scalaz/$bslash$amp$div$That
     724: ifeq          765
     727: aload         52
     729: checkcast     #25                 // class scalaz/$bslash$amp$div$That
     732: invokevirtual #176                // Method scalaz/$bslash$amp$div$That.bb:()Ljava/lang/Object;
     735: astore        54
     737: new           #25                 // class scalaz/$bslash$amp$div$That
     740: dup
     741: aload         4
     743: aload         53
     745: aload         54
     747: invokedynamic #206,  0            // InvokeDynamic #7:apply:(Ljava/lang/Object;)Lscala/Function0;
     752: invokeinterface #162,  3          // InterfaceMethod scalaz/Semigroup.append:(Ljava/lang/Object;Lscala/Function0;)Ljava/lang/Object;
     757: invokespecial #207                // Method scalaz/$bslash$amp$div$That."<init>":(Ljava/lang/Object;)V
     760: astore        5
     762: goto          775
     765: new           #209                // class scala/MatchError
     768: dup
     769: aload         6
     771: invokespecial #210                // Method scala/MatchError."<init>":(Ljava/lang/Object;)V
     774: athrow
     775: aload         5
     777: areturn

  public java.lang.Object append(java.lang.Object, scala.Function0);
    Code:
       0: aload_1
       1: checkcast     #22                 // class scalaz/$bslash$amp$div
       4: astore_3
       5: aload_3
       6: aload_0
       7: getfield      #123                // Field evidence$3$1:Lscalaz/Band;
      10: aload_0
      11: getfield      #125                // Field evidence$4$1:Lscalaz/Band;
      14: astore        5
      16: astore        4
      18: ifnonnull     23
      21: aconst_null
      22: athrow
      23: new           #127                // class scala/Tuple2
      26: dup
      27: aload_2
      28: invokeinterface #132,  1          // InterfaceMethod scala/Function0.apply:()Ljava/lang/Object;
      33: astore        56
      35: aload_3
      36: aload         56
      38: invokespecial #136                // Method scala/Tuple2."<init>":(Ljava/lang/Object;Ljava/lang/Object;)V
      41: astore        7
      43: aload_3
      44: astore        8
      46: aload         56
      48: checkcast     #22                 // class scalaz/$bslash$amp$div
      51: astore        9
      53: aload         8
      55: instanceof    #28                 // class scalaz/$bslash$amp$div$This
      58: ifeq          117
      61: aload         8
      63: checkcast     #28                 // class scalaz/$bslash$amp$div$This
      66: invokevirtual #139                // Method scalaz/$bslash$amp$div$This.aa:()Ljava/lang/Object;
      69: astore        10
      71: aload         9
      73: instanceof    #28                 // class scalaz/$bslash$amp$div$This
      76: ifeq          117
      79: aload         9
      81: checkcast     #28                 // class scalaz/$bslash$amp$div$This
      84: invokevirtual #139                // Method scalaz/$bslash$amp$div$This.aa:()Ljava/lang/Object;
      87: astore        11
      89: new           #28                 // class scalaz/$bslash$amp$div$This
      92: dup
      93: aload         4
      95: aload         10
      97: aload         11
      99: invokedynamic #159,  0            // InvokeDynamic #0:apply:(Ljava/lang/Object;)Lscala/Function0;
     104: invokeinterface #162,  3          // InterfaceMethod scalaz/Semigroup.append:(Ljava/lang/Object;Lscala/Function0;)Ljava/lang/Object;
     109: invokespecial #165                // Method scalaz/$bslash$amp$div$This."<init>":(Ljava/lang/Object;)V
     112: astore        6
     114: goto          785
     117: aload_3
     118: astore        12
     120: aload         56
     122: checkcast     #22                 // class scalaz/$bslash$amp$div
     125: astore        13
     127: aload         12
     129: instanceof    #28                 // class scalaz/$bslash$amp$div$This
     132: ifeq          204
     135: aload         12
     137: checkcast     #28                 // class scalaz/$bslash$amp$div$This
     140: invokevirtual #139                // Method scalaz/$bslash$amp$div$This.aa:()Ljava/lang/Object;
     143: astore        14
     145: aload         13
     147: instanceof    #20                 // class scalaz/$bslash$amp$div$Both
     150: ifeq          204
     153: aload         13
     155: checkcast     #20                 // class scalaz/$bslash$amp$div$Both
     158: astore        15
     160: aload         15
     162: invokevirtual #166                // Method scalaz/$bslash$amp$div$Both.aa:()Ljava/lang/Object;
     165: astore        16
     167: aload         15
     169: invokevirtual #169                // Method scalaz/$bslash$amp$div$Both.bb:()Ljava/lang/Object;
     172: astore        17
     174: new           #20                 // class scalaz/$bslash$amp$div$Both
     177: dup
     178: aload         4
     180: aload         14
     182: aload         16
     184: invokedynamic #174,  0            // InvokeDynamic #1:apply:(Ljava/lang/Object;)Lscala/Function0;
     189: invokeinterface #162,  3          // InterfaceMethod scalaz/Semigroup.append:(Ljava/lang/Object;Lscala/Function0;)Ljava/lang/Object;
     194: aload         17
     196: invokespecial #175                // Method scalaz/$bslash$amp$div$Both."<init>":(Ljava/lang/Object;Ljava/lang/Object;)V
     199: astore        6
     201: goto          785
     204: aload_3
     205: astore        18
     207: aload         56
     209: checkcast     #22                 // class scalaz/$bslash$amp$div
     212: astore        19
     214: aload         18
     216: instanceof    #28                 // class scalaz/$bslash$amp$div$This
     219: ifeq          266
     222: aload         18
     224: checkcast     #28                 // class scalaz/$bslash$amp$div$This
     227: invokevirtual #139                // Method scalaz/$bslash$amp$div$This.aa:()Ljava/lang/Object;
     230: astore        20
     232: aload         19
     234: instanceof    #25                 // class scalaz/$bslash$amp$div$That
     237: ifeq          266
     240: aload         19
     242: checkcast     #25                 // class scalaz/$bslash$amp$div$That
     245: invokevirtual #176                // Method scalaz/$bslash$amp$div$That.bb:()Ljava/lang/Object;
     248: astore        21
     250: new           #20                 // class scalaz/$bslash$amp$div$Both
     253: dup
     254: aload         20
     256: aload         21
     258: invokespecial #175                // Method scalaz/$bslash$amp$div$Both."<init>":(Ljava/lang/Object;Ljava/lang/Object;)V
     261: astore        6
     263: goto          785
     266: aload_3
     267: astore        22
     269: aload         56
     271: checkcast     #22                 // class scalaz/$bslash$amp$div
     274: astore        23
     276: aload         22
     278: instanceof    #20                 // class scalaz/$bslash$amp$div$Both
     281: ifeq          353
     284: aload         22
     286: checkcast     #20                 // class scalaz/$bslash$amp$div$Both
     289: astore        24
     291: aload         24
     293: invokevirtual #166                // Method scalaz/$bslash$amp$div$Both.aa:()Ljava/lang/Object;
     296: astore        25
     298: aload         24
     300: invokevirtual #169                // Method scalaz/$bslash$amp$div$Both.bb:()Ljava/lang/Object;
     303: astore        26
     305: aload         23
     307: instanceof    #28                 // class scalaz/$bslash$amp$div$This
     310: ifeq          353
     313: aload         23
     315: checkcast     #28                 // class scalaz/$bslash$amp$div$This
     318: invokevirtual #139                // Method scalaz/$bslash$amp$div$This.aa:()Ljava/lang/Object;
     321: astore        27
     323: new           #20                 // class scalaz/$bslash$amp$div$Both
     326: dup
     327: aload         4
     329: aload         25
     331: aload         27
     333: invokedynamic #181,  0            // InvokeDynamic #2:apply:(Ljava/lang/Object;)Lscala/Function0;
     338: invokeinterface #162,  3          // InterfaceMethod scalaz/Semigroup.append:(Ljava/lang/Object;Lscala/Function0;)Ljava/lang/Object;
     343: aload         26
     345: invokespecial #175                // Method scalaz/$bslash$amp$div$Both."<init>":(Ljava/lang/Object;Ljava/lang/Object;)V
     348: astore        6
     350: goto          785
     353: aload_3
     354: astore        28
     356: aload         56
     358: checkcast     #22                 // class scalaz/$bslash$amp$div
     361: astore        29
     363: aload         28
     365: instanceof    #20                 // class scalaz/$bslash$amp$div$Both
     368: ifeq          465
     371: aload         28
     373: checkcast     #20                 // class scalaz/$bslash$amp$div$Both
     376: astore        30
     378: aload         30
     380: invokevirtual #166                // Method scalaz/$bslash$amp$div$Both.aa:()Ljava/lang/Object;
     383: astore        31
     385: aload         30
     387: invokevirtual #169                // Method scalaz/$bslash$amp$div$Both.bb:()Ljava/lang/Object;
     390: astore        32
     392: aload         29
     394: instanceof    #20                 // class scalaz/$bslash$amp$div$Both
     397: ifeq          465
     400: aload         29
     402: checkcast     #20                 // class scalaz/$bslash$amp$div$Both
     405: astore        33
     407: aload         33
     409: invokevirtual #166                // Method scalaz/$bslash$amp$div$Both.aa:()Ljava/lang/Object;
     412: astore        34
     414: aload         33
     416: invokevirtual #169                // Method scalaz/$bslash$amp$div$Both.bb:()Ljava/lang/Object;
     419: astore        35
     421: new           #20                 // class scalaz/$bslash$amp$div$Both
     424: dup
     425: aload         4
     427: aload         31
     429: aload         34
     431: invokedynamic #186,  0            // InvokeDynamic #3:apply:(Ljava/lang/Object;)Lscala/Function0;
     436: invokeinterface #162,  3          // InterfaceMethod scalaz/Semigroup.append:(Ljava/lang/Object;Lscala/Function0;)Ljava/lang/Object;
     441: aload         5
     443: aload         32
     445: aload         35
     447: invokedynamic #191,  0            // InvokeDynamic #4:apply:(Ljava/lang/Object;)Lscala/Function0;
     452: invokeinterface #162,  3          // InterfaceMethod scalaz/Semigroup.append:(Ljava/lang/Object;Lscala/Function0;)Ljava/lang/Object;
     457: invokespecial #175                // Method scalaz/$bslash$amp$div$Both."<init>":(Ljava/lang/Object;Ljava/lang/Object;)V
     460: astore        6
     462: goto          785
     465: aload_3
     466: astore        36
     468: aload         56
     470: checkcast     #22                 // class scalaz/$bslash$amp$div
     473: astore        37
     475: aload         36
     477: instanceof    #20                 // class scalaz/$bslash$amp$div$Both
     480: ifeq          552
     483: aload         36
     485: checkcast     #20                 // class scalaz/$bslash$amp$div$Both
     488: astore        38
     490: aload         38
     492: invokevirtual #166                // Method scalaz/$bslash$amp$div$Both.aa:()Ljava/lang/Object;
     495: astore        39
     497: aload         38
     499: invokevirtual #169                // Method scalaz/$bslash$amp$div$Both.bb:()Ljava/lang/Object;
     502: astore        40
     504: aload         37
     506: instanceof    #25                 // class scalaz/$bslash$amp$div$That
     509: ifeq          552
     512: aload         37
     514: checkcast     #25                 // class scalaz/$bslash$amp$div$That
     517: invokevirtual #176                // Method scalaz/$bslash$amp$div$That.bb:()Ljava/lang/Object;
     520: astore        41
     522: new           #20                 // class scalaz/$bslash$amp$div$Both
     525: dup
     526: aload         39
     528: aload         5
     530: aload         40
     532: aload         41
     534: invokedynamic #196,  0            // InvokeDynamic #5:apply:(Ljava/lang/Object;)Lscala/Function0;
     539: invokeinterface #162,  3          // InterfaceMethod scalaz/Semigroup.append:(Ljava/lang/Object;Lscala/Function0;)Ljava/lang/Object;
     544: invokespecial #175                // Method scalaz/$bslash$amp$div$Both."<init>":(Ljava/lang/Object;Ljava/lang/Object;)V
     547: astore        6
     549: goto          785
     552: aload_3
     553: astore        42
     555: aload         56
     557: checkcast     #22                 // class scalaz/$bslash$amp$div
     560: astore        43
     562: aload         42
     564: instanceof    #25                 // class scalaz/$bslash$amp$div$That
     567: ifeq          614
     570: aload         42
     572: checkcast     #25                 // class scalaz/$bslash$amp$div$That
     575: invokevirtual #176                // Method scalaz/$bslash$amp$div$That.bb:()Ljava/lang/Object;
     578: astore        44
     580: aload         43
     582: instanceof    #28                 // class scalaz/$bslash$amp$div$This
     585: ifeq          614
     588: aload         43
     590: checkcast     #28                 // class scalaz/$bslash$amp$div$This
     593: invokevirtual #139                // Method scalaz/$bslash$amp$div$This.aa:()Ljava/lang/Object;
     596: astore        45
     598: new           #20                 // class scalaz/$bslash$amp$div$Both
     601: dup
     602: aload         45
     604: aload         44
     606: invokespecial #175                // Method scalaz/$bslash$amp$div$Both."<init>":(Ljava/lang/Object;Ljava/lang/Object;)V
     609: astore        6
     611: goto          785
     614: aload_3
     615: astore        46
     617: aload         56
     619: checkcast     #22                 // class scalaz/$bslash$amp$div
     622: astore        47
     624: aload         46
     626: instanceof    #25                 // class scalaz/$bslash$amp$div$That
     629: ifeq          701
     632: aload         46
     634: checkcast     #25                 // class scalaz/$bslash$amp$div$That
     637: invokevirtual #176                // Method scalaz/$bslash$amp$div$That.bb:()Ljava/lang/Object;
     640: astore        48
     642: aload         47
     644: instanceof    #20                 // class scalaz/$bslash$amp$div$Both
     647: ifeq          701
     650: aload         47
     652: checkcast     #20                 // class scalaz/$bslash$amp$div$Both
     655: astore        49
     657: aload         49
     659: invokevirtual #166                // Method scalaz/$bslash$amp$div$Both.aa:()Ljava/lang/Object;
     662: astore        50
     664: aload         49
     666: invokevirtual #169                // Method scalaz/$bslash$amp$div$Both.bb:()Ljava/lang/Object;
     669: astore        51
     671: new           #20                 // class scalaz/$bslash$amp$div$Both
     674: dup
     675: aload         50
     677: aload         5
     679: aload         48
     681: aload         51
     683: invokedynamic #201,  0            // InvokeDynamic #6:apply:(Ljava/lang/Object;)Lscala/Function0;
     688: invokeinterface #162,  3          // InterfaceMethod scalaz/Semigroup.append:(Ljava/lang/Object;Lscala/Function0;)Ljava/lang/Object;
     693: invokespecial #175                // Method scalaz/$bslash$amp$div$Both."<init>":(Ljava/lang/Object;Ljava/lang/Object;)V
     696: astore        6
     698: goto          785
     701: aload_3
     702: astore        52
     704: aload         56
     706: checkcast     #22                 // class scalaz/$bslash$amp$div
     709: astore        53
     711: aload         52
     713: instanceof    #25                 // class scalaz/$bslash$amp$div$That
     716: ifeq          775
     719: aload         52
     721: checkcast     #25                 // class scalaz/$bslash$amp$div$That
     724: invokevirtual #176                // Method scalaz/$bslash$amp$div$That.bb:()Ljava/lang/Object;
     727: astore        54
     729: aload         53
     731: instanceof    #25                 // class scalaz/$bslash$amp$div$That
     734: ifeq          775
     737: aload         53
     739: checkcast     #25                 // class scalaz/$bslash$amp$div$That
     742: invokevirtual #176                // Method scalaz/$bslash$amp$div$That.bb:()Ljava/lang/Object;
     745: astore        55
     747: new           #25                 // class scalaz/$bslash$amp$div$That
     750: dup
     751: aload         5
     753: aload         54
     755: aload         55
     757: invokedynamic #206,  0            // InvokeDynamic #7:apply:(Ljava/lang/Object;)Lscala/Function0;
     762: invokeinterface #162,  3          // InterfaceMethod scalaz/Semigroup.append:(Ljava/lang/Object;Lscala/Function0;)Ljava/lang/Object;
     767: invokespecial #207                // Method scalaz/$bslash$amp$div$That."<init>":(Ljava/lang/Object;)V
     770: astore        6
     772: goto          785
     775: new           #209                // class scala/MatchError
     778: dup
     779: aload         7
     781: invokespecial #210                // Method scala/MatchError."<init>":(Ljava/lang/Object;)V
     784: athrow
     785: aload         6
     787: areturn

  public scalaz.TheseInstances$$anon$1(scalaz.TheseInstances, scalaz.Band, scalaz.Band);
    Code:
       0: aload_0
       1: aload_2
       2: putfield      #123                // Field evidence$3$1:Lscalaz/Band;
       5: aload_0
       6: aload_3
       7: putfield      #125                // Field evidence$4$1:Lscalaz/Band;
      10: aload_0
      11: invokespecial #235                // Method java/lang/Object."<init>":()V
      14: aload_0
      15: invokestatic  #239                // InterfaceMethod scalaz/Semigroup.$init$:(Lscalaz/Semigroup;)V
      18: aload_0
      19: invokestatic  #242                // InterfaceMethod scalaz/Band.$init$:(Lscalaz/Band;)V
      22: return

  private static java.lang.Object $deserializeLambda$(java.lang.invoke.SerializedLambda);
    Code:
       0: aload_0
       1: invokedynamic #255,  0            // InvokeDynamic #8:lambdaDeserialize:(Ljava/lang/invoke/SerializedLambda;)Ljava/lang/Object;
       6: areturn
}
