Compiled from "DialectResolverInitiator.java"
public class org.hibernate.engine.jdbc.dialect.internal.DialectResolverInitiator implements org.hibernate.boot.registry.StandardServiceInitiator<org.hibernate.engine.jdbc.dialect.spi.DialectResolver> {
  public static final org.hibernate.engine.jdbc.dialect.internal.DialectResolverInitiator INSTANCE;

  public org.hibernate.engine.jdbc.dialect.internal.DialectResolverInitiator();
    Code:
       0: aload_0
       1: invokespecial #1                  // Method java/lang/Object."<init>":()V
       4: return

  public java.lang.Class<org.hibernate.engine.jdbc.dialect.spi.DialectResolver> getServiceInitiated();
    Code:
       0: ldc           #2                  // class org/hibernate/engine/jdbc/dialect/spi/DialectResolver
       2: areturn

  public org.hibernate.engine.jdbc.dialect.spi.DialectResolver initiateService(java.util.Map, org.hibernate.service.spi.ServiceRegistryImplementor);
    Code:
       0: new           #3                  // class org/hibernate/engine/jdbc/dialect/internal/DialectResolverSet
       3: dup
       4: invokespecial #4                  // Method org/hibernate/engine/jdbc/dialect/internal/DialectResolverSet."<init>":()V
       7: astore_3
       8: aload_0
       9: aload_3
      10: aload_2
      11: aload_1
      12: invokespecial #5                  // Method applyCustomerResolvers:(Lorg/hibernate/engine/jdbc/dialect/internal/DialectResolverSet;Lorg/hibernate/service/spi/ServiceRegistryImplementor;Ljava/util/Map;)V
      15: aload_3
      16: getstatic     #6                  // Field org/hibernate/engine/jdbc/dialect/internal/StandardDialectResolver.INSTANCE:Lorg/hibernate/engine/jdbc/dialect/internal/StandardDialectResolver;
      19: invokevirtual #7                  // Method org/hibernate/engine/jdbc/dialect/internal/DialectResolverSet.addResolver:(Lorg/hibernate/engine/jdbc/dialect/spi/DialectResolver;)V
      22: aload_3
      23: areturn

  private void applyCustomerResolvers(org.hibernate.engine.jdbc.dialect.internal.DialectResolverSet, org.hibernate.service.spi.ServiceRegistryImplementor, java.util.Map);
    Code:
       0: aload_3
       1: ldc           #9                  // String hibernate.dialect_resolvers
       3: invokeinterface #10,  2           // InterfaceMethod java/util/Map.get:(Ljava/lang/Object;)Ljava/lang/Object;
       8: checkcast     #11                 // class java/lang/String
      11: astore        4
      13: aload         4
      15: invokestatic  #12                 // Method org/hibernate/internal/util/StringHelper.isNotEmpty:(Ljava/lang/String;)Z
      18: ifeq          135
      21: aload_2
      22: ldc           #13                 // class org/hibernate/boot/registry/classloading/spi/ClassLoaderService
      24: invokeinterface #14,  2           // InterfaceMethod org/hibernate/service/spi/ServiceRegistryImplementor.getService:(Ljava/lang/Class;)Lorg/hibernate/service/Service;
      29: checkcast     #13                 // class org/hibernate/boot/registry/classloading/spi/ClassLoaderService
      32: astore        5
      34: ldc           #15                 // String , \n\r\f\t
      36: aload         4
      38: invokestatic  #16                 // Method org/hibernate/internal/util/StringHelper.split:(Ljava/lang/String;Ljava/lang/String;)[Ljava/lang/String;
      41: astore        6
      43: aload         6
      45: arraylength
      46: istore        7
      48: iconst_0
      49: istore        8
      51: iload         8
      53: iload         7
      55: if_icmpge     135
      58: aload         6
      60: iload         8
      62: aaload
      63: astore        9
      65: aload_1
      66: aload         5
      68: aload         9
      70: invokeinterface #17,  2           // InterfaceMethod org/hibernate/boot/registry/classloading/spi/ClassLoaderService.classForName:(Ljava/lang/String;)Ljava/lang/Class;
      75: invokevirtual #18                 // Method java/lang/Class.newInstance:()Ljava/lang/Object;
      78: checkcast     #2                  // class org/hibernate/engine/jdbc/dialect/spi/DialectResolver
      81: invokevirtual #7                  // Method org/hibernate/engine/jdbc/dialect/internal/DialectResolverSet.addResolver:(Lorg/hibernate/engine/jdbc/dialect/spi/DialectResolver;)V
      84: goto          129
      87: astore        10
      89: aload         10
      91: athrow
      92: astore        10
      94: new           #21                 // class org/hibernate/service/spi/ServiceException
      97: dup
      98: new           #22                 // class java/lang/StringBuilder
     101: dup
     102: invokespecial #23                 // Method java/lang/StringBuilder."<init>":()V
     105: ldc           #24                 // String Unable to instantiate named dialect resolver [
     107: invokevirtual #25                 // Method java/lang/StringBuilder.append:(Ljava/lang/String;)Ljava/lang/StringBuilder;
     110: aload         9
     112: invokevirtual #25                 // Method java/lang/StringBuilder.append:(Ljava/lang/String;)Ljava/lang/StringBuilder;
     115: ldc           #26                 // String ]
     117: invokevirtual #25                 // Method java/lang/StringBuilder.append:(Ljava/lang/String;)Ljava/lang/StringBuilder;
     120: invokevirtual #27                 // Method java/lang/StringBuilder.toString:()Ljava/lang/String;
     123: aload         10
     125: invokespecial #28                 // Method org/hibernate/service/spi/ServiceException."<init>":(Ljava/lang/String;Ljava/lang/Throwable;)V
     128: athrow
     129: iinc          8, 1
     132: goto          51
     135: return
    Exception table:
       from    to  target type
          65    84    87   Class org/hibernate/HibernateException
          65    84    92   Class java/lang/Exception

  public org.hibernate.service.Service initiateService(java.util.Map, org.hibernate.service.spi.ServiceRegistryImplementor);
    Code:
       0: aload_0
       1: aload_1
       2: aload_2
       3: invokevirtual #29                 // Method initiateService:(Ljava/util/Map;Lorg/hibernate/service/spi/ServiceRegistryImplementor;)Lorg/hibernate/engine/jdbc/dialect/spi/DialectResolver;
       6: areturn

  static {};
    Code:
       0: new           #30                 // class org/hibernate/engine/jdbc/dialect/internal/DialectResolverInitiator
       3: dup
       4: invokespecial #31                 // Method "<init>":()V
       7: putstatic     #32                 // Field INSTANCE:Lorg/hibernate/engine/jdbc/dialect/internal/DialectResolverInitiator;
      10: return
}
