Compiled from "AbstractGormMappingFactory.java"
public abstract class org.grails.datastore.mapping.config.AbstractGormMappingFactory<R extends org.grails.datastore.mapping.config.Entity, T extends org.grails.datastore.mapping.config.Property> extends org.grails.datastore.mapping.model.MappingFactory<R, T> {
  protected java.util.Map<org.grails.datastore.mapping.model.PersistentEntity, java.util.Map<java.lang.String, T>> entityToPropertyMap;

  private groovy.lang.Closure defaultMapping;

  public org.grails.datastore.mapping.config.AbstractGormMappingFactory();
    Code:
       0: aload_0
       1: invokespecial #1                  // Method org/grails/datastore/mapping/model/MappingFactory."<init>":()V
       4: aload_0
       5: new           #2                  // class java/util/HashMap
       8: dup
       9: invokespecial #3                  // Method java/util/HashMap."<init>":()V
      12: putfield      #4                  // Field entityToPropertyMap:Ljava/util/Map;
      15: return

  public R createMappedForm(org.grails.datastore.mapping.model.PersistentEntity);
    Code:
       0: aload_1
       1: invokeinterface #5,  1            // InterfaceMethod org/grails/datastore/mapping/model/PersistentEntity.getJavaClass:()Ljava/lang/Class;
       6: invokestatic  #6                  // Method org/grails/datastore/mapping/reflect/ClassPropertyFetcher.forClass:(Ljava/lang/Class;)Lorg/grails/datastore/mapping/reflect/ClassPropertyFetcher;
       9: astore_2
      10: aload_0
      11: invokevirtual #7                  // Method getEntityMappedFormType:()Ljava/lang/Class;
      14: invokestatic  #8                  // Method org/springframework/beans/BeanUtils.instantiate:(Ljava/lang/Class;)Ljava/lang/Object;
      17: checkcast     #9                  // class org/grails/datastore/mapping/config/Entity
      20: astore_3
      21: new           #10                 // class org/grails/datastore/mapping/config/groovy/MappingConfigurationBuilder
      24: dup
      25: aload_3
      26: aload_0
      27: invokevirtual #11                 // Method getPropertyMappedFormType:()Ljava/lang/Class;
      30: invokespecial #12                 // Method org/grails/datastore/mapping/config/groovy/MappingConfigurationBuilder."<init>":(Ljava/lang/Object;Ljava/lang/Class;)V
      33: astore        4
      35: aload_0
      36: getfield      #13                 // Field defaultMapping:Lgroovy/lang/Closure;
      39: ifnull        51
      42: aload         4
      44: aload_0
      45: getfield      #13                 // Field defaultMapping:Lgroovy/lang/Closure;
      48: invokevirtual #14                 // Method org/grails/datastore/mapping/config/groovy/MappingConfigurationBuilder.evaluate:(Lgroovy/lang/Closure;)V
      51: aload_2
      52: ldc           #15                 // String mapping
      54: ldc_w         #16                 // class groovy/lang/Closure
      57: invokevirtual #17                 // Method org/grails/datastore/mapping/reflect/ClassPropertyFetcher.getStaticPropertyValuesFromInheritanceHierarchy:(Ljava/lang/String;Ljava/lang/Class;)Ljava/util/List;
      60: astore        5
      62: aload         5
      64: invokeinterface #18,  1           // InterfaceMethod java/util/List.size:()I
      69: istore        6
      71: iload         6
      73: ifle          105
      76: aload         5
      78: iload         6
      80: iconst_1
      81: isub
      82: invokeinterface #19,  2           // InterfaceMethod java/util/List.get:(I)Ljava/lang/Object;
      87: checkcast     #16                 // class groovy/lang/Closure
      90: astore        7
      92: aload         4
      94: aload         7
      96: invokevirtual #14                 // Method org/grails/datastore/mapping/config/groovy/MappingConfigurationBuilder.evaluate:(Lgroovy/lang/Closure;)V
      99: iinc          6, -1
     102: goto          71
     105: aload_2
     106: ldc           #20                 // String constraints
     108: ldc_w         #16                 // class groovy/lang/Closure
     111: invokevirtual #17                 // Method org/grails/datastore/mapping/reflect/ClassPropertyFetcher.getStaticPropertyValuesFromInheritanceHierarchy:(Ljava/lang/String;Ljava/lang/Class;)Ljava/util/List;
     114: astore        5
     116: aload         5
     118: invokeinterface #18,  1           // InterfaceMethod java/util/List.size:()I
     123: istore        6
     125: iload         6
     127: ifle          159
     130: aload         5
     132: iload         6
     134: iconst_1
     135: isub
     136: invokeinterface #19,  2           // InterfaceMethod java/util/List.get:(I)Ljava/lang/Object;
     141: checkcast     #16                 // class groovy/lang/Closure
     144: astore        7
     146: aload         4
     148: aload         7
     150: invokevirtual #14                 // Method org/grails/datastore/mapping/config/groovy/MappingConfigurationBuilder.evaluate:(Lgroovy/lang/Closure;)V
     153: iinc          6, -1
     156: goto          125
     159: aload_0
     160: getfield      #4                  // Field entityToPropertyMap:Ljava/util/Map;
     163: aload_1
     164: aload         4
     166: invokevirtual #21                 // Method org/grails/datastore/mapping/config/groovy/MappingConfigurationBuilder.getProperties:()Ljava/util/Map;
     169: invokeinterface #22,  3           // InterfaceMethod java/util/Map.put:(Ljava/lang/Object;Ljava/lang/Object;)Ljava/lang/Object;
     174: pop
     175: aload_3
     176: areturn

  public void setDefaultMapping(groovy.lang.Closure);
    Code:
       0: aload_0
       1: aload_1
       2: putfield      #13                 // Field defaultMapping:Lgroovy/lang/Closure;
       5: return

  protected abstract java.lang.Class<T> getPropertyMappedFormType();

  protected abstract java.lang.Class<R> getEntityMappedFormType();

  public org.grails.datastore.mapping.model.IdentityMapping createIdentityMapping(org.grails.datastore.mapping.model.ClassMapping);
    Code:
       0: aload_0
       1: getfield      #4                  // Field entityToPropertyMap:Ljava/util/Map;
       4: aload_1
       5: invokeinterface #23,  1           // InterfaceMethod org/grails/datastore/mapping/model/ClassMapping.getEntity:()Lorg/grails/datastore/mapping/model/PersistentEntity;
      10: invokeinterface #24,  2           // InterfaceMethod java/util/Map.get:(Ljava/lang/Object;)Ljava/lang/Object;
      15: checkcast     #25                 // class java/util/Map
      18: astore_2
      19: aload_2
      20: ifnull        51
      23: aload_2
      24: ldc           #26                 // String id
      26: invokeinterface #24,  2           // InterfaceMethod java/util/Map.get:(Ljava/lang/Object;)Ljava/lang/Object;
      31: checkcast     #27                 // class org/grails/datastore/mapping/config/Property
      34: astore_3
      35: aload_0
      36: aload_1
      37: aload_3
      38: invokevirtual #28                 // Method getIdentityMappedForm:(Lorg/grails/datastore/mapping/model/ClassMapping;Lorg/grails/datastore/mapping/config/Property;)Lorg/grails/datastore/mapping/model/IdentityMapping;
      41: astore        4
      43: aload         4
      45: ifnull        51
      48: aload         4
      50: areturn
      51: aload_0
      52: aload_1
      53: invokespecial #29                 // Method org/grails/datastore/mapping/model/MappingFactory.createIdentityMapping:(Lorg/grails/datastore/mapping/model/ClassMapping;)Lorg/grails/datastore/mapping/model/IdentityMapping;
      56: areturn

  protected org.grails.datastore.mapping.model.IdentityMapping getIdentityMappedForm(org.grails.datastore.mapping.model.ClassMapping, T);
    Code:
       0: aconst_null
       1: areturn

  public T createMappedForm(org.grails.datastore.mapping.model.PersistentProperty);
    Code:
       0: aload_0
       1: getfield      #4                  // Field entityToPropertyMap:Ljava/util/Map;
       4: aload_1
       5: invokeinterface #30,  1           // InterfaceMethod org/grails/datastore/mapping/model/PersistentProperty.getOwner:()Lorg/grails/datastore/mapping/model/PersistentEntity;
      10: invokeinterface #24,  2           // InterfaceMethod java/util/Map.get:(Ljava/lang/Object;)Ljava/lang/Object;
      15: checkcast     #25                 // class java/util/Map
      18: astore_2
      19: aload_2
      20: ifnull        54
      23: aload_2
      24: aload_1
      25: invokeinterface #31,  1           // InterfaceMethod org/grails/datastore/mapping/model/PersistentProperty.getName:()Ljava/lang/String;
      30: invokeinterface #32,  2           // InterfaceMethod java/util/Map.containsKey:(Ljava/lang/Object;)Z
      35: ifeq          54
      38: aload_2
      39: aload_1
      40: invokeinterface #31,  1           // InterfaceMethod org/grails/datastore/mapping/model/PersistentProperty.getName:()Ljava/lang/String;
      45: invokeinterface #24,  2           // InterfaceMethod java/util/Map.get:(Ljava/lang/Object;)Ljava/lang/Object;
      50: checkcast     #27                 // class org/grails/datastore/mapping/config/Property
      53: areturn
      54: aload_2
      55: ifnull        92
      58: aload_2
      59: ldc           #26                 // String id
      61: invokeinterface #24,  2           // InterfaceMethod java/util/Map.get:(Ljava/lang/Object;)Ljava/lang/Object;
      66: checkcast     #27                 // class org/grails/datastore/mapping/config/Property
      69: astore_3
      70: aload_3
      71: ifnull        92
      74: aload_1
      75: invokeinterface #31,  1           // InterfaceMethod org/grails/datastore/mapping/model/PersistentProperty.getName:()Ljava/lang/String;
      80: aload_3
      81: invokevirtual #33                 // Method org/grails/datastore/mapping/config/Property.getName:()Ljava/lang/String;
      84: invokevirtual #34                 // Method java/lang/String.equals:(Ljava/lang/Object;)Z
      87: ifeq          92
      90: aload_3
      91: areturn
      92: aload_2
      93: ifnull        110
      96: aload_2
      97: ldc           #35                 // String *
      99: invokeinterface #24,  2           // InterfaceMethod java/util/Map.get:(Ljava/lang/Object;)Ljava/lang/Object;
     104: checkcast     #27                 // class org/grails/datastore/mapping/config/Property
     107: goto          111
     110: aconst_null
     111: astore_3
     112: aload_3
     113: ifnull        134
     116: aload_3
     117: invokevirtual #36                 // Method org/grails/datastore/mapping/config/Property.clone:()Lorg/grails/datastore/mapping/config/Property;
     120: areturn
     121: astore        4
     123: aload_0
     124: invokevirtual #11                 // Method getPropertyMappedFormType:()Ljava/lang/Class;
     127: invokestatic  #8                  // Method org/springframework/beans/BeanUtils.instantiate:(Ljava/lang/Class;)Ljava/lang/Object;
     130: checkcast     #27                 // class org/grails/datastore/mapping/config/Property
     133: areturn
     134: aload_0
     135: invokevirtual #11                 // Method getPropertyMappedFormType:()Ljava/lang/Class;
     138: invokestatic  #8                  // Method org/springframework/beans/BeanUtils.instantiate:(Ljava/lang/Class;)Ljava/lang/Object;
     141: checkcast     #27                 // class org/grails/datastore/mapping/config/Property
     144: areturn
    Exception table:
       from    to  target type
         116   120   121   Class java/lang/CloneNotSupportedException
}
