Compiled from "Entity.java"
public class org.grails.datastore.mapping.config.Entity {
  private boolean stateless;

  private boolean autoTimestamp;

  public org.grails.datastore.mapping.config.Entity();
    Code:
       0: aload_0
       1: invokespecial #1                  // Method java/lang/Object."<init>":()V
       4: aload_0
       5: iconst_0
       6: putfield      #2                  // Field stateless:Z
       9: aload_0
      10: iconst_1
      11: putfield      #3                  // Field autoTimestamp:Z
      14: return

  public boolean isAutoTimestamp();
    Code:
       0: aload_0
       1: getfield      #3                  // Field autoTimestamp:Z
       4: ireturn

  public void setAutoTimestamp(boolean);
    Code:
       0: aload_0
       1: iload_1
       2: putfield      #3                  // Field autoTimestamp:Z
       5: return

  public boolean isStateless();
    Code:
       0: aload_0
       1: getfield      #2                  // Field stateless:Z
       4: ireturn

  public void setStateless(boolean);
    Code:
       0: aload_0
       1: iload_1
       2: putfield      #2                  // Field stateless:Z
       5: return
}
