Compiled from "Constants.java"
public final class org.apache.logging.log4j.util.Constants {
  public static final boolean IS_WEB_APP;

  public static final boolean ENABLE_THREADLOCALS;

  public static final int JAVA_MAJOR_VERSION;

  public static final int MAX_REUSABLE_MESSAGE_SIZE;

  public static final java.lang.String LOG4J2_DEBUG;

  public static final java.lang.Object[] EMPTY_OBJECT_ARRAY;

  public static final byte[] EMPTY_BYTE_ARRAY;

  private static int size(java.lang.String, int);
    Code:
       0: invokestatic  #1                  // Method org/apache/logging/log4j/util/PropertiesUtil.getProperties:()Lorg/apache/logging/log4j/util/PropertiesUtil;
       3: aload_0
       4: iload_1
       5: invokevirtual #2                  // Method org/apache/logging/log4j/util/PropertiesUtil.getIntegerProperty:(Ljava/lang/String;I)I
       8: ireturn

  private static boolean isClassAvailable(java.lang.String);
    Code:
       0: aload_0
       1: invokestatic  #3                  // Method org/apache/logging/log4j/util/LoaderUtil.loadClass:(Ljava/lang/String;)Ljava/lang/Class;
       4: ifnull        11
       7: iconst_1
       8: goto          12
      11: iconst_0
      12: ireturn
      13: astore_1
      14: iconst_0
      15: ireturn
    Exception table:
       from    to  target type
           0    12    13   Class java/lang/Throwable

  private org.apache.logging.log4j.util.Constants();
    Code:
       0: aload_0
       1: invokespecial #5                  // Method java/lang/Object."<init>":()V
       4: return

  private static int getMajorVersion();
    Code:
       0: ldc           #6                  // String java.version
       2: invokestatic  #7                  // Method java/lang/System.getProperty:(Ljava/lang/String;)Ljava/lang/String;
       5: invokestatic  #8                  // Method getMajorVersion:(Ljava/lang/String;)I
       8: ireturn

  static int getMajorVersion(java.lang.String);
    Code:
       0: aload_0
       1: ldc           #9                  // String -|\\.
       3: invokevirtual #10                 // Method java/lang/String.split:(Ljava/lang/String;)[Ljava/lang/String;
       6: astore_1
       7: aload_1
       8: iconst_0
       9: aaload
      10: invokestatic  #11                 // Method java/lang/Integer.parseInt:(Ljava/lang/String;)I
      13: istore_3
      14: iload_3
      15: iconst_1
      16: if_icmpeq     23
      19: iconst_1
      20: goto          24
      23: iconst_0
      24: istore_2
      25: iload_2
      26: ifeq          31
      29: iload_3
      30: ireturn
      31: aload_1
      32: iconst_1
      33: aaload
      34: invokestatic  #11                 // Method java/lang/Integer.parseInt:(Ljava/lang/String;)I
      37: ireturn
      38: astore_3
      39: iconst_0
      40: ireturn
    Exception table:
       from    to  target type
           7    30    38   Class java/lang/Exception
          31    37    38   Class java/lang/Exception

  static {};
    Code:
       0: invokestatic  #1                  // Method org/apache/logging/log4j/util/PropertiesUtil.getProperties:()Lorg/apache/logging/log4j/util/PropertiesUtil;
       3: ldc           #13                 // String log4j2.is.webapp
       5: ldc           #14                 // String javax.servlet.Servlet
       7: invokestatic  #15                 // Method isClassAvailable:(Ljava/lang/String;)Z
      10: ifne          21
      13: ldc           #16                 // String jakarta.servlet.Servlet
      15: invokestatic  #15                 // Method isClassAvailable:(Ljava/lang/String;)Z
      18: ifeq          25
      21: iconst_1
      22: goto          26
      25: iconst_0
      26: invokevirtual #17                 // Method org/apache/logging/log4j/util/PropertiesUtil.getBooleanProperty:(Ljava/lang/String;Z)Z
      29: putstatic     #18                 // Field IS_WEB_APP:Z
      32: getstatic     #18                 // Field IS_WEB_APP:Z
      35: ifne          54
      38: invokestatic  #1                  // Method org/apache/logging/log4j/util/PropertiesUtil.getProperties:()Lorg/apache/logging/log4j/util/PropertiesUtil;
      41: ldc           #19                 // String log4j2.enable.threadlocals
      43: iconst_1
      44: invokevirtual #17                 // Method org/apache/logging/log4j/util/PropertiesUtil.getBooleanProperty:(Ljava/lang/String;Z)Z
      47: ifeq          54
      50: iconst_1
      51: goto          55
      54: iconst_0
      55: putstatic     #20                 // Field ENABLE_THREADLOCALS:Z
      58: invokestatic  #21                 // Method getMajorVersion:()I
      61: putstatic     #22                 // Field JAVA_MAJOR_VERSION:I
      64: ldc           #23                 // String log4j.maxReusableMsgSize
      66: sipush        518
      69: invokestatic  #24                 // Method size:(Ljava/lang/String;I)I
      72: putstatic     #25                 // Field MAX_REUSABLE_MESSAGE_SIZE:I
      75: iconst_0
      76: anewarray     #26                 // class java/lang/Object
      79: putstatic     #27                 // Field EMPTY_OBJECT_ARRAY:[Ljava/lang/Object;
      82: iconst_0
      83: newarray       byte
      85: putstatic     #28                 // Field EMPTY_BYTE_ARRAY:[B
      88: return
}
