Compiled from "NumberDeserializers.java"
public abstract class com.fasterxml.jackson.databind.deser.std.NumberDeserializers$PrimitiveOrWrapperDeserializer<T> extends com.fasterxml.jackson.databind.deser.std.StdScalarDeserializer<T> {
  private static final long serialVersionUID;

  protected final com.fasterxml.jackson.databind.type.LogicalType _logicalType;

  protected final T _nullValue;

  protected final T _emptyValue;

  protected final boolean _primitive;

  protected com.fasterxml.jackson.databind.deser.std.NumberDeserializers$PrimitiveOrWrapperDeserializer(java.lang.Class<T>, com.fasterxml.jackson.databind.type.LogicalType, T, T);
    Code:
       0: aload_0
       1: aload_1
       2: invokespecial #1                  // Method com/fasterxml/jackson/databind/deser/std/StdScalarDeserializer."<init>":(Ljava/lang/Class;)V
       5: aload_0
       6: aload_2
       7: putfield      #2                  // Field _logicalType:Lcom/fasterxml/jackson/databind/type/LogicalType;
      10: aload_0
      11: aload_3
      12: putfield      #3                  // Field _nullValue:Ljava/lang/Object;
      15: aload_0
      16: aload         4
      18: putfield      #4                  // Field _emptyValue:Ljava/lang/Object;
      21: aload_0
      22: aload_1
      23: invokevirtual #5                  // Method java/lang/Class.isPrimitive:()Z
      26: putfield      #6                  // Field _primitive:Z
      29: return

  protected com.fasterxml.jackson.databind.deser.std.NumberDeserializers$PrimitiveOrWrapperDeserializer(java.lang.Class<T>, T, T);
    Code:
       0: aload_0
       1: aload_1
       2: getstatic     #7                  // Field com/fasterxml/jackson/databind/type/LogicalType.OtherScalar:Lcom/fasterxml/jackson/databind/type/LogicalType;
       5: aload_2
       6: aload_3
       7: invokespecial #8                  // Method "<init>":(Ljava/lang/Class;Lcom/fasterxml/jackson/databind/type/LogicalType;Ljava/lang/Object;Ljava/lang/Object;)V
      10: return

  public com.fasterxml.jackson.databind.util.AccessPattern getNullAccessPattern();
    Code:
       0: aload_0
       1: getfield      #6                  // Field _primitive:Z
       4: ifeq          11
       7: getstatic     #9                  // Field com/fasterxml/jackson/databind/util/AccessPattern.DYNAMIC:Lcom/fasterxml/jackson/databind/util/AccessPattern;
      10: areturn
      11: aload_0
      12: getfield      #3                  // Field _nullValue:Ljava/lang/Object;
      15: ifnonnull     22
      18: getstatic     #10                 // Field com/fasterxml/jackson/databind/util/AccessPattern.ALWAYS_NULL:Lcom/fasterxml/jackson/databind/util/AccessPattern;
      21: areturn
      22: getstatic     #11                 // Field com/fasterxml/jackson/databind/util/AccessPattern.CONSTANT:Lcom/fasterxml/jackson/databind/util/AccessPattern;
      25: areturn

  public final T getNullValue(com.fasterxml.jackson.databind.DeserializationContext) throws com.fasterxml.jackson.databind.JsonMappingException;
    Code:
       0: aload_0
       1: getfield      #6                  // Field _primitive:Z
       4: ifeq          39
       7: aload_1
       8: getstatic     #12                 // Field com/fasterxml/jackson/databind/DeserializationFeature.FAIL_ON_NULL_FOR_PRIMITIVES:Lcom/fasterxml/jackson/databind/DeserializationFeature;
      11: invokevirtual #13                 // Method com/fasterxml/jackson/databind/DeserializationContext.isEnabled:(Lcom/fasterxml/jackson/databind/DeserializationFeature;)Z
      14: ifeq          39
      17: aload_1
      18: aload_0
      19: ldc           #14                 // String Cannot map `null` into type %s (set DeserializationConfig.DeserializationFeature.FAIL_ON_NULL_FOR_PRIMITIVES to \'false\' to allow)
      21: iconst_1
      22: anewarray     #15                 // class java/lang/Object
      25: dup
      26: iconst_0
      27: aload_0
      28: invokevirtual #16                 // Method handledType:()Ljava/lang/Class;
      31: invokestatic  #17                 // Method com/fasterxml/jackson/databind/util/ClassUtil.classNameOf:(Ljava/lang/Object;)Ljava/lang/String;
      34: aastore
      35: invokevirtual #18                 // Method com/fasterxml/jackson/databind/DeserializationContext.reportInputMismatch:(Lcom/fasterxml/jackson/databind/JsonDeserializer;Ljava/lang/String;[Ljava/lang/Object;)Ljava/lang/Object;
      38: pop
      39: aload_0
      40: getfield      #3                  // Field _nullValue:Ljava/lang/Object;
      43: areturn

  public java.lang.Object getEmptyValue(com.fasterxml.jackson.databind.DeserializationContext) throws com.fasterxml.jackson.databind.JsonMappingException;
    Code:
       0: aload_0
       1: getfield      #4                  // Field _emptyValue:Ljava/lang/Object;
       4: areturn

  public final com.fasterxml.jackson.databind.type.LogicalType logicalType();
    Code:
       0: aload_0
       1: getfield      #2                  // Field _logicalType:Lcom/fasterxml/jackson/databind/type/LogicalType;
       4: areturn
}
