Compiled from "AuditMessageTypeAdapter.java"
public class co.cask.cdap.proto.codec.AuditMessageTypeAdapter implements com.google.gson.JsonDeserializer<co.cask.cdap.proto.audit.AuditMessage> {
  public co.cask.cdap.proto.codec.AuditMessageTypeAdapter();
    Code:
       0: aload_0
       1: invokespecial #1                  // Method java/lang/Object."<init>":()V
       4: return

  public co.cask.cdap.proto.audit.AuditMessage deserialize(com.google.gson.JsonElement, java.lang.reflect.Type, com.google.gson.JsonDeserializationContext) throws com.google.gson.JsonParseException;
    Code:
       0: aload_1
       1: invokevirtual #2                  // Method com/google/gson/JsonElement.getAsJsonObject:()Lcom/google/gson/JsonObject;
       4: astore        4
       6: aload         4
       8: ldc           #3                  // String time
      10: invokevirtual #4                  // Method com/google/gson/JsonObject.get:(Ljava/lang/String;)Lcom/google/gson/JsonElement;
      13: invokevirtual #5                  // Method com/google/gson/JsonElement.getAsLong:()J
      16: lstore        5
      18: aload_3
      19: aload         4
      21: ldc           #6                  // String entityId
      23: invokevirtual #7                  // Method com/google/gson/JsonObject.getAsJsonObject:(Ljava/lang/String;)Lcom/google/gson/JsonObject;
      26: ldc_w         #8                  // class co/cask/cdap/proto/id/EntityId
      29: invokeinterface #9,  3            // InterfaceMethod com/google/gson/JsonDeserializationContext.deserialize:(Lcom/google/gson/JsonElement;Ljava/lang/reflect/Type;)Ljava/lang/Object;
      34: checkcast     #8                  // class co/cask/cdap/proto/id/EntityId
      37: astore        7
      39: aload         4
      41: ldc           #10                 // String user
      43: invokevirtual #4                  // Method com/google/gson/JsonObject.get:(Ljava/lang/String;)Lcom/google/gson/JsonElement;
      46: invokevirtual #11                 // Method com/google/gson/JsonElement.getAsString:()Ljava/lang/String;
      49: astore        8
      51: aload_3
      52: aload         4
      54: ldc           #12                 // String type
      56: invokevirtual #13                 // Method com/google/gson/JsonObject.getAsJsonPrimitive:(Ljava/lang/String;)Lcom/google/gson/JsonPrimitive;
      59: ldc_w         #14                 // class co/cask/cdap/proto/audit/AuditType
      62: invokeinterface #9,  3            // InterfaceMethod com/google/gson/JsonDeserializationContext.deserialize:(Lcom/google/gson/JsonElement;Ljava/lang/reflect/Type;)Ljava/lang/Object;
      67: checkcast     #14                 // class co/cask/cdap/proto/audit/AuditType
      70: astore        9
      72: aload         4
      74: ldc           #15                 // String payload
      76: invokevirtual #7                  // Method com/google/gson/JsonObject.getAsJsonObject:(Ljava/lang/String;)Lcom/google/gson/JsonObject;
      79: astore        11
      81: getstatic     #16                 // Field co/cask/cdap/proto/codec/AuditMessageTypeAdapter$1.$SwitchMap$co$cask$cdap$proto$audit$AuditType:[I
      84: aload         9
      86: invokevirtual #17                 // Method co/cask/cdap/proto/audit/AuditType.ordinal:()I
      89: iaload
      90: lookupswitch  { // 2
                     1: 116
                     2: 135
               default: 154
          }
     116: aload_3
     117: aload         11
     119: ldc_w         #18                 // class co/cask/cdap/proto/audit/payload/metadata/MetadataPayload
     122: invokeinterface #9,  3            // InterfaceMethod com/google/gson/JsonDeserializationContext.deserialize:(Lcom/google/gson/JsonElement;Ljava/lang/reflect/Type;)Ljava/lang/Object;
     127: checkcast     #19                 // class co/cask/cdap/proto/audit/AuditPayload
     130: astore        10
     132: goto          159
     135: aload_3
     136: aload         11
     138: ldc_w         #20                 // class co/cask/cdap/proto/audit/payload/access/AccessPayload
     141: invokeinterface #9,  3            // InterfaceMethod com/google/gson/JsonDeserializationContext.deserialize:(Lcom/google/gson/JsonElement;Ljava/lang/reflect/Type;)Ljava/lang/Object;
     146: checkcast     #19                 // class co/cask/cdap/proto/audit/AuditPayload
     149: astore        10
     151: goto          159
     154: getstatic     #21                 // Field co/cask/cdap/proto/audit/AuditPayload.EMPTY_PAYLOAD:Lco/cask/cdap/proto/audit/AuditPayload;
     157: astore        10
     159: new           #22                 // class co/cask/cdap/proto/audit/AuditMessage
     162: dup
     163: lload         5
     165: aload         7
     167: aload         8
     169: aload         9
     171: aload         10
     173: invokespecial #23                 // Method co/cask/cdap/proto/audit/AuditMessage."<init>":(JLco/cask/cdap/proto/id/EntityId;Ljava/lang/String;Lco/cask/cdap/proto/audit/AuditType;Lco/cask/cdap/proto/audit/AuditPayload;)V
     176: areturn

  public java.lang.Object deserialize(com.google.gson.JsonElement, java.lang.reflect.Type, com.google.gson.JsonDeserializationContext) throws com.google.gson.JsonParseException;
    Code:
       0: aload_0
       1: aload_1
       2: aload_2
       3: aload_3
       4: invokevirtual #24                 // Method deserialize:(Lcom/google/gson/JsonElement;Ljava/lang/reflect/Type;Lcom/google/gson/JsonDeserializationContext;)Lco/cask/cdap/proto/audit/AuditMessage;
       7: areturn
}
