Compiled from "ScheduleSpecificationCodec.java"
class co.cask.cdap.proto.codec.ScheduleSpecificationCodec$1 {
  static final int[] $SwitchMap$co$cask$cdap$proto$ScheduleType;

  static {};
    Code:
       0: invokestatic  #1                  // Method co/cask/cdap/proto/ScheduleType.values:()[Lco/cask/cdap/proto/ScheduleType;
       3: arraylength
       4: newarray       int
       6: putstatic     #2                  // Field $SwitchMap$co$cask$cdap$proto$ScheduleType:[I
       9: getstatic     #2                  // Field $SwitchMap$co$cask$cdap$proto$ScheduleType:[I
      12: getstatic     #3                  // Field co/cask/cdap/proto/ScheduleType.TIME:Lco/cask/cdap/proto/ScheduleType;
      15: invokevirtual #4                  // Method co/cask/cdap/proto/ScheduleType.ordinal:()I
      18: iconst_1
      19: iastore
      20: goto          24
      23: astore_0
      24: getstatic     #2                  // Field $SwitchMap$co$cask$cdap$proto$ScheduleType:[I
      27: getstatic     #6                  // Field co/cask/cdap/proto/ScheduleType.STREAM:Lco/cask/cdap/proto/ScheduleType;
      30: invokevirtual #4                  // Method co/cask/cdap/proto/ScheduleType.ordinal:()I
      33: iconst_2
      34: iastore
      35: goto          39
      38: astore_0
      39: return
    Exception table:
       from    to  target type
           9    20    23   Class java/lang/NoSuchFieldError
          24    35    38   Class java/lang/NoSuchFieldError
}
