Compiled from "QuerySpaceHelper.java"
public class org.hibernate.loader.plan.build.internal.spaces.QuerySpaceHelper {
  public static final org.hibernate.loader.plan.build.internal.spaces.QuerySpaceHelper INSTANCE;

  private org.hibernate.loader.plan.build.internal.spaces.QuerySpaceHelper();
    Code:
       0: aload_0
       1: invokespecial #1                  // Method java/lang/Object."<init>":()V
       4: return

  public org.hibernate.loader.plan.build.spi.ExpandingEntityQuerySpace makeEntityQuerySpace(org.hibernate.loader.plan.build.spi.ExpandingQuerySpace, org.hibernate.persister.walking.spi.AssociationAttributeDefinition, java.lang.String, org.hibernate.engine.FetchStrategy);
    Code:
       0: aload_2
       1: invokeinterface #2,  1            // InterfaceMethod org/hibernate/persister/walking/spi/AssociationAttributeDefinition.getType:()Lorg/hibernate/type/AssociationType;
       6: checkcast     #3                  // class org/hibernate/type/EntityType
       9: astore        5
      11: aload_2
      12: invokeinterface #4,  1            // InterfaceMethod org/hibernate/persister/walking/spi/AssociationAttributeDefinition.toEntityDefinition:()Lorg/hibernate/persister/walking/spi/EntityDefinition;
      17: invokeinterface #5,  1            // InterfaceMethod org/hibernate/persister/walking/spi/EntityDefinition.getEntityPersister:()Lorg/hibernate/persister/entity/EntityPersister;
      22: astore        6
      24: aload         6
      26: ifnonnull     63
      29: new           #6                  // class org/hibernate/persister/walking/spi/WalkingException
      32: dup
      33: ldc           #7                  // String Unable to locate EntityPersister [%s] for fetch [%s]
      35: iconst_2
      36: anewarray     #8                  // class java/lang/Object
      39: dup
      40: iconst_0
      41: aload         5
      43: invokevirtual #9                  // Method org/hibernate/type/EntityType.getAssociatedEntityName:()Ljava/lang/String;
      46: aastore
      47: dup
      48: iconst_1
      49: aload_2
      50: invokeinterface #10,  1           // InterfaceMethod org/hibernate/persister/walking/spi/AssociationAttributeDefinition.getName:()Ljava/lang/String;
      55: aastore
      56: invokestatic  #11                 // Method java/lang/String.format:(Ljava/lang/String;[Ljava/lang/Object;)Ljava/lang/String;
      59: invokespecial #12                 // Method org/hibernate/persister/walking/spi/WalkingException."<init>":(Ljava/lang/String;)V
      62: athrow
      63: ldc           #13                 // class org/hibernate/persister/entity/Queryable
      65: aload         6
      67: invokevirtual #14                 // Method java/lang/Class.cast:(Ljava/lang/Object;)Ljava/lang/Object;
      70: checkcast     #13                 // class org/hibernate/persister/entity/Queryable
      73: invokeinterface #15,  1           // InterfaceMethod org/hibernate/persister/entity/Queryable.isMultiTable:()Z
      78: istore        7
      80: aload_1
      81: invokeinterface #16,  1           // InterfaceMethod org/hibernate/loader/plan/build/spi/ExpandingQuerySpace.canJoinsBeRequired:()Z
      86: ifeq          107
      89: iload         7
      91: ifne          107
      94: aload_2
      95: invokeinterface #17,  1           // InterfaceMethod org/hibernate/persister/walking/spi/AssociationAttributeDefinition.isNullable:()Z
     100: ifne          107
     103: iconst_1
     104: goto          108
     107: iconst_0
     108: istore        8
     110: aload_0
     111: aload_1
     112: aload         6
     114: aload_2
     115: invokeinterface #10,  1           // InterfaceMethod org/hibernate/persister/walking/spi/AssociationAttributeDefinition.getName:()Ljava/lang/String;
     120: aload_2
     121: invokeinterface #2,  1            // InterfaceMethod org/hibernate/persister/walking/spi/AssociationAttributeDefinition.getType:()Lorg/hibernate/type/AssociationType;
     126: checkcast     #3                  // class org/hibernate/type/EntityType
     129: aload_3
     130: iload         8
     132: aload_0
     133: aload         4
     135: invokevirtual #18                 // Method shouldIncludeJoin:(Lorg/hibernate/engine/FetchStrategy;)Z
     138: invokevirtual #19                 // Method makeEntityQuerySpace:(Lorg/hibernate/loader/plan/build/spi/ExpandingQuerySpace;Lorg/hibernate/persister/entity/EntityPersister;Ljava/lang/String;Lorg/hibernate/type/EntityType;Ljava/lang/String;ZZ)Lorg/hibernate/loader/plan/build/spi/ExpandingEntityQuerySpace;
     141: areturn

  public org.hibernate.loader.plan.build.spi.ExpandingEntityQuerySpace makeEntityQuerySpace(org.hibernate.loader.plan.build.spi.ExpandingQuerySpace, org.hibernate.persister.entity.EntityPersister, java.lang.String, org.hibernate.type.EntityType, java.lang.String, boolean, boolean);
    Code:
       0: aload_1
       1: invokeinterface #20,  1           // InterfaceMethod org/hibernate/loader/plan/build/spi/ExpandingQuerySpace.getExpandingQuerySpaces:()Lorg/hibernate/loader/plan/build/spi/ExpandingQuerySpaces;
       6: aload         5
       8: aload_2
       9: iload         6
      11: invokeinterface #21,  4           // InterfaceMethod org/hibernate/loader/plan/build/spi/ExpandingQuerySpaces.makeEntityQuerySpace:(Ljava/lang/String;Lorg/hibernate/persister/entity/EntityPersister;Z)Lorg/hibernate/loader/plan/build/spi/ExpandingEntityQuerySpace;
      16: astore        8
      18: iload         7
      20: ifeq          53
      23: getstatic     #22                 // Field org/hibernate/loader/plan/build/internal/spaces/JoinHelper.INSTANCE:Lorg/hibernate/loader/plan/build/internal/spaces/JoinHelper;
      26: aload_1
      27: aload_3
      28: aload         8
      30: iload         6
      32: aload         4
      34: aload_2
      35: invokeinterface #23,  1           // InterfaceMethod org/hibernate/persister/entity/EntityPersister.getFactory:()Lorg/hibernate/engine/spi/SessionFactoryImplementor;
      40: invokevirtual #24                 // Method org/hibernate/loader/plan/build/internal/spaces/JoinHelper.createEntityJoin:(Lorg/hibernate/loader/plan/spi/QuerySpace;Ljava/lang/String;Lorg/hibernate/loader/plan/spi/EntityQuerySpace;ZLorg/hibernate/type/EntityType;Lorg/hibernate/engine/spi/SessionFactoryImplementor;)Lorg/hibernate/loader/plan/spi/JoinDefinedByMetadata;
      43: astore        9
      45: aload_1
      46: aload         9
      48: invokeinterface #25,  2           // InterfaceMethod org/hibernate/loader/plan/build/spi/ExpandingQuerySpace.addJoin:(Lorg/hibernate/loader/plan/spi/Join;)V
      53: aload         8
      55: areturn

  public org.hibernate.loader.plan.build.spi.ExpandingCompositeQuerySpace makeCompositeQuerySpace(org.hibernate.loader.plan.build.spi.ExpandingQuerySpace, org.hibernate.persister.walking.spi.AttributeDefinition, java.lang.String, boolean);
    Code:
       0: aload_1
       1: invokeinterface #16,  1           // InterfaceMethod org/hibernate/loader/plan/build/spi/ExpandingQuerySpace.canJoinsBeRequired:()Z
       6: ifeq          22
       9: aload_2
      10: invokeinterface #26,  1           // InterfaceMethod org/hibernate/persister/walking/spi/AttributeDefinition.isNullable:()Z
      15: ifne          22
      18: iconst_1
      19: goto          23
      22: iconst_0
      23: istore        5
      25: aload_0
      26: aload_1
      27: new           #27                 // class org/hibernate/loader/plan/build/internal/spaces/CompositePropertyMapping
      30: dup
      31: aload_2
      32: invokeinterface #28,  1           // InterfaceMethod org/hibernate/persister/walking/spi/AttributeDefinition.getType:()Lorg/hibernate/type/Type;
      37: checkcast     #29                 // class org/hibernate/type/CompositeType
      40: aload_1
      41: invokeinterface #30,  1           // InterfaceMethod org/hibernate/loader/plan/build/spi/ExpandingQuerySpace.getPropertyMapping:()Lorg/hibernate/persister/entity/PropertyMapping;
      46: aload_2
      47: invokeinterface #31,  1           // InterfaceMethod org/hibernate/persister/walking/spi/AttributeDefinition.getName:()Ljava/lang/String;
      52: invokespecial #32                 // Method org/hibernate/loader/plan/build/internal/spaces/CompositePropertyMapping."<init>":(Lorg/hibernate/type/CompositeType;Lorg/hibernate/persister/entity/PropertyMapping;Ljava/lang/String;)V
      55: aload_2
      56: invokeinterface #31,  1           // InterfaceMethod org/hibernate/persister/walking/spi/AttributeDefinition.getName:()Ljava/lang/String;
      61: aload_2
      62: invokeinterface #28,  1           // InterfaceMethod org/hibernate/persister/walking/spi/AttributeDefinition.getType:()Lorg/hibernate/type/Type;
      67: checkcast     #29                 // class org/hibernate/type/CompositeType
      70: aload_3
      71: iload         5
      73: iload         4
      75: invokevirtual #33                 // Method makeCompositeQuerySpace:(Lorg/hibernate/loader/plan/build/spi/ExpandingQuerySpace;Lorg/hibernate/loader/plan/build/internal/spaces/CompositePropertyMapping;Ljava/lang/String;Lorg/hibernate/type/CompositeType;Ljava/lang/String;ZZ)Lorg/hibernate/loader/plan/build/spi/ExpandingCompositeQuerySpace;
      78: areturn

  public org.hibernate.loader.plan.build.spi.ExpandingCompositeQuerySpace makeCompositeQuerySpace(org.hibernate.loader.plan.build.spi.ExpandingQuerySpace, org.hibernate.loader.plan.build.internal.spaces.CompositePropertyMapping, java.lang.String, org.hibernate.type.CompositeType, java.lang.String, boolean, boolean);
    Code:
       0: aload_1
       1: invokeinterface #20,  1           // InterfaceMethod org/hibernate/loader/plan/build/spi/ExpandingQuerySpace.getExpandingQuerySpaces:()Lorg/hibernate/loader/plan/build/spi/ExpandingQuerySpaces;
       6: aload         5
       8: aload_2
       9: iload         6
      11: invokeinterface #34,  4           // InterfaceMethod org/hibernate/loader/plan/build/spi/ExpandingQuerySpaces.makeCompositeQuerySpace:(Ljava/lang/String;Lorg/hibernate/loader/plan/build/internal/spaces/CompositePropertyMapping;Z)Lorg/hibernate/loader/plan/build/spi/ExpandingCompositeQuerySpace;
      16: astore        8
      18: iload         7
      20: ifeq          47
      23: getstatic     #22                 // Field org/hibernate/loader/plan/build/internal/spaces/JoinHelper.INSTANCE:Lorg/hibernate/loader/plan/build/internal/spaces/JoinHelper;
      26: aload_1
      27: aload_3
      28: aload         8
      30: iload         6
      32: aload         4
      34: invokevirtual #35                 // Method org/hibernate/loader/plan/build/internal/spaces/JoinHelper.createCompositeJoin:(Lorg/hibernate/loader/plan/spi/QuerySpace;Ljava/lang/String;Lorg/hibernate/loader/plan/spi/CompositeQuerySpace;ZLorg/hibernate/type/CompositeType;)Lorg/hibernate/loader/plan/spi/JoinDefinedByMetadata;
      37: astore        9
      39: aload_1
      40: aload         9
      42: invokeinterface #25,  2           // InterfaceMethod org/hibernate/loader/plan/build/spi/ExpandingQuerySpace.addJoin:(Lorg/hibernate/loader/plan/spi/Join;)V
      47: aload         8
      49: areturn

  public org.hibernate.loader.plan.build.spi.ExpandingCollectionQuerySpace makeCollectionQuerySpace(org.hibernate.loader.plan.build.spi.ExpandingQuerySpace, org.hibernate.persister.walking.spi.AssociationAttributeDefinition, java.lang.String, org.hibernate.engine.FetchStrategy);
    Code:
       0: aload_2
       1: invokeinterface #2,  1            // InterfaceMethod org/hibernate/persister/walking/spi/AssociationAttributeDefinition.getType:()Lorg/hibernate/type/AssociationType;
       6: checkcast     #36                 // class org/hibernate/type/CollectionType
       9: astore        5
      11: aload_2
      12: invokeinterface #37,  1           // InterfaceMethod org/hibernate/persister/walking/spi/AssociationAttributeDefinition.toCollectionDefinition:()Lorg/hibernate/persister/walking/spi/CollectionDefinition;
      17: invokeinterface #38,  1           // InterfaceMethod org/hibernate/persister/walking/spi/CollectionDefinition.getCollectionPersister:()Lorg/hibernate/persister/collection/CollectionPersister;
      22: astore        6
      24: aload         6
      26: ifnonnull     63
      29: new           #6                  // class org/hibernate/persister/walking/spi/WalkingException
      32: dup
      33: ldc           #39                 // String Unable to locate CollectionPersister [%s] for fetch [%s]
      35: iconst_2
      36: anewarray     #8                  // class java/lang/Object
      39: dup
      40: iconst_0
      41: aload         5
      43: invokevirtual #40                 // Method org/hibernate/type/CollectionType.getRole:()Ljava/lang/String;
      46: aastore
      47: dup
      48: iconst_1
      49: aload_2
      50: invokeinterface #10,  1           // InterfaceMethod org/hibernate/persister/walking/spi/AssociationAttributeDefinition.getName:()Ljava/lang/String;
      55: aastore
      56: invokestatic  #11                 // Method java/lang/String.format:(Ljava/lang/String;[Ljava/lang/Object;)Ljava/lang/String;
      59: invokespecial #12                 // Method org/hibernate/persister/walking/spi/WalkingException."<init>":(Ljava/lang/String;)V
      62: athrow
      63: aload_1
      64: invokeinterface #16,  1           // InterfaceMethod org/hibernate/loader/plan/build/spi/ExpandingQuerySpace.canJoinsBeRequired:()Z
      69: ifeq          85
      72: aload_2
      73: invokeinterface #17,  1           // InterfaceMethod org/hibernate/persister/walking/spi/AssociationAttributeDefinition.isNullable:()Z
      78: ifne          85
      81: iconst_1
      82: goto          86
      85: iconst_0
      86: istore        7
      88: aload_1
      89: invokeinterface #20,  1           // InterfaceMethod org/hibernate/loader/plan/build/spi/ExpandingQuerySpace.getExpandingQuerySpaces:()Lorg/hibernate/loader/plan/build/spi/ExpandingQuerySpaces;
      94: aload_3
      95: aload         6
      97: iload         7
      99: invokeinterface #41,  4           // InterfaceMethod org/hibernate/loader/plan/build/spi/ExpandingQuerySpaces.makeCollectionQuerySpace:(Ljava/lang/String;Lorg/hibernate/persister/collection/CollectionPersister;Z)Lorg/hibernate/loader/plan/build/spi/ExpandingCollectionQuerySpace;
     104: astore        8
     106: aload_0
     107: aload         4
     109: invokevirtual #18                 // Method shouldIncludeJoin:(Lorg/hibernate/engine/FetchStrategy;)Z
     112: ifeq          158
     115: getstatic     #22                 // Field org/hibernate/loader/plan/build/internal/spaces/JoinHelper.INSTANCE:Lorg/hibernate/loader/plan/build/internal/spaces/JoinHelper;
     118: aload_1
     119: aload_2
     120: invokeinterface #10,  1           // InterfaceMethod org/hibernate/persister/walking/spi/AssociationAttributeDefinition.getName:()Ljava/lang/String;
     125: aload         8
     127: iload         7
     129: aload_2
     130: invokeinterface #2,  1            // InterfaceMethod org/hibernate/persister/walking/spi/AssociationAttributeDefinition.getType:()Lorg/hibernate/type/AssociationType;
     135: checkcast     #36                 // class org/hibernate/type/CollectionType
     138: aload         6
     140: invokeinterface #42,  1           // InterfaceMethod org/hibernate/persister/collection/CollectionPersister.getFactory:()Lorg/hibernate/engine/spi/SessionFactoryImplementor;
     145: invokevirtual #43                 // Method org/hibernate/loader/plan/build/internal/spaces/JoinHelper.createCollectionJoin:(Lorg/hibernate/loader/plan/spi/QuerySpace;Ljava/lang/String;Lorg/hibernate/loader/plan/spi/CollectionQuerySpace;ZLorg/hibernate/type/CollectionType;Lorg/hibernate/engine/spi/SessionFactoryImplementor;)Lorg/hibernate/loader/plan/spi/JoinDefinedByMetadata;
     148: astore        9
     150: aload_1
     151: aload         9
     153: invokeinterface #25,  2           // InterfaceMethod org/hibernate/loader/plan/build/spi/ExpandingQuerySpace.addJoin:(Lorg/hibernate/loader/plan/spi/Join;)V
     158: aload         8
     160: areturn

  public boolean shouldIncludeJoin(org.hibernate.engine.FetchStrategy);
    Code:
       0: aload_1
       1: invokevirtual #44                 // Method org/hibernate/engine/FetchStrategy.getTiming:()Lorg/hibernate/engine/FetchTiming;
       4: getstatic     #45                 // Field org/hibernate/engine/FetchTiming.IMMEDIATE:Lorg/hibernate/engine/FetchTiming;
       7: if_acmpne     24
      10: aload_1
      11: invokevirtual #46                 // Method org/hibernate/engine/FetchStrategy.getStyle:()Lorg/hibernate/engine/FetchStyle;
      14: getstatic     #47                 // Field org/hibernate/engine/FetchStyle.JOIN:Lorg/hibernate/engine/FetchStyle;
      17: if_acmpne     24
      20: iconst_1
      21: goto          25
      24: iconst_0
      25: ireturn

  static {};
    Code:
       0: new           #48                 // class org/hibernate/loader/plan/build/internal/spaces/QuerySpaceHelper
       3: dup
       4: invokespecial #49                 // Method "<init>":()V
       7: putstatic     #50                 // Field INSTANCE:Lorg/hibernate/loader/plan/build/internal/spaces/QuerySpaceHelper;
      10: return
}
