Compiled from "hidden.scala"
public final class slinky.web.html.hidden {
  public static slinky.core.AttrPair<slinky.web.html.$times$tag$> boolToPairstarApplied(slinky.web.html.hidden$);
    Code:
       0: getstatic     #465                // Field slinky/web/html/hidden$.MODULE$:Lslinky/web/html/hidden$;
       3: aload_0
       4: invokevirtual #467                // Method slinky/web/html/hidden$.boolToPairstarApplied:(Lslinky/web/html/hidden$;)Lslinky/core/AttrPair;
       7: areturn

  public static slinky.core.AttrPair<slinky.web.html.wbr$tag$> boolToPairwbrApplied(slinky.web.html.hidden$);
    Code:
       0: getstatic     #465                // Field slinky/web/html/hidden$.MODULE$:Lslinky/web/html/hidden$;
       3: aload_0
       4: invokevirtual #471                // Method slinky/web/html/hidden$.boolToPairwbrApplied:(Lslinky/web/html/hidden$;)Lslinky/core/AttrPair;
       7: areturn

  public static slinky.core.AttrPair<slinky.web.html.video$tag$> boolToPairvideoApplied(slinky.web.html.hidden$);
    Code:
       0: getstatic     #465                // Field slinky/web/html/hidden$.MODULE$:Lslinky/web/html/hidden$;
       3: aload_0
       4: invokevirtual #475                // Method slinky/web/html/hidden$.boolToPairvideoApplied:(Lslinky/web/html/hidden$;)Lslinky/core/AttrPair;
       7: areturn

  public static slinky.core.AttrPair<slinky.web.html.var$tag$> boolToPairvarApplied(slinky.web.html.hidden$);
    Code:
       0: getstatic     #465                // Field slinky/web/html/hidden$.MODULE$:Lslinky/web/html/hidden$;
       3: aload_0
       4: invokevirtual #479                // Method slinky/web/html/hidden$.boolToPairvarApplied:(Lslinky/web/html/hidden$;)Lslinky/core/AttrPair;
       7: areturn

  public static slinky.core.AttrPair<slinky.web.html.ul$tag$> boolToPairulApplied(slinky.web.html.hidden$);
    Code:
       0: getstatic     #465                // Field slinky/web/html/hidden$.MODULE$:Lslinky/web/html/hidden$;
       3: aload_0
       4: invokevirtual #483                // Method slinky/web/html/hidden$.boolToPairulApplied:(Lslinky/web/html/hidden$;)Lslinky/core/AttrPair;
       7: areturn

  public static slinky.core.AttrPair<slinky.web.html.u$tag$> boolToPairuApplied(slinky.web.html.hidden$);
    Code:
       0: getstatic     #465                // Field slinky/web/html/hidden$.MODULE$:Lslinky/web/html/hidden$;
       3: aload_0
       4: invokevirtual #487                // Method slinky/web/html/hidden$.boolToPairuApplied:(Lslinky/web/html/hidden$;)Lslinky/core/AttrPair;
       7: areturn

  public static slinky.core.AttrPair<slinky.web.html.track$tag$> boolToPairtrackApplied(slinky.web.html.hidden$);
    Code:
       0: getstatic     #465                // Field slinky/web/html/hidden$.MODULE$:Lslinky/web/html/hidden$;
       3: aload_0
       4: invokevirtual #491                // Method slinky/web/html/hidden$.boolToPairtrackApplied:(Lslinky/web/html/hidden$;)Lslinky/core/AttrPair;
       7: areturn

  public static slinky.core.AttrPair<slinky.web.html.tr$tag$> boolToPairtrApplied(slinky.web.html.hidden$);
    Code:
       0: getstatic     #465                // Field slinky/web/html/hidden$.MODULE$:Lslinky/web/html/hidden$;
       3: aload_0
       4: invokevirtual #495                // Method slinky/web/html/hidden$.boolToPairtrApplied:(Lslinky/web/html/hidden$;)Lslinky/core/AttrPair;
       7: areturn

  public static slinky.core.AttrPair<slinky.web.html.title$tag$> boolToPairtitleApplied(slinky.web.html.hidden$);
    Code:
       0: getstatic     #465                // Field slinky/web/html/hidden$.MODULE$:Lslinky/web/html/hidden$;
       3: aload_0
       4: invokevirtual #499                // Method slinky/web/html/hidden$.boolToPairtitleApplied:(Lslinky/web/html/hidden$;)Lslinky/core/AttrPair;
       7: areturn

  public static slinky.core.AttrPair<slinky.web.html.time$tag$> boolToPairtimeApplied(slinky.web.html.hidden$);
    Code:
       0: getstatic     #465                // Field slinky/web/html/hidden$.MODULE$:Lslinky/web/html/hidden$;
       3: aload_0
       4: invokevirtual #503                // Method slinky/web/html/hidden$.boolToPairtimeApplied:(Lslinky/web/html/hidden$;)Lslinky/core/AttrPair;
       7: areturn

  public static slinky.core.AttrPair<slinky.web.html.thead$tag$> boolToPairtheadApplied(slinky.web.html.hidden$);
    Code:
       0: getstatic     #465                // Field slinky/web/html/hidden$.MODULE$:Lslinky/web/html/hidden$;
       3: aload_0
       4: invokevirtual #507                // Method slinky/web/html/hidden$.boolToPairtheadApplied:(Lslinky/web/html/hidden$;)Lslinky/core/AttrPair;
       7: areturn

  public static slinky.core.AttrPair<slinky.web.html.th$tag$> boolToPairthApplied(slinky.web.html.hidden$);
    Code:
       0: getstatic     #465                // Field slinky/web/html/hidden$.MODULE$:Lslinky/web/html/hidden$;
       3: aload_0
       4: invokevirtual #511                // Method slinky/web/html/hidden$.boolToPairthApplied:(Lslinky/web/html/hidden$;)Lslinky/core/AttrPair;
       7: areturn

  public static slinky.core.AttrPair<slinky.web.html.tfoot$tag$> boolToPairtfootApplied(slinky.web.html.hidden$);
    Code:
       0: getstatic     #465                // Field slinky/web/html/hidden$.MODULE$:Lslinky/web/html/hidden$;
       3: aload_0
       4: invokevirtual #515                // Method slinky/web/html/hidden$.boolToPairtfootApplied:(Lslinky/web/html/hidden$;)Lslinky/core/AttrPair;
       7: areturn

  public static slinky.core.AttrPair<slinky.web.html.textarea$tag$> boolToPairtextareaApplied(slinky.web.html.hidden$);
    Code:
       0: getstatic     #465                // Field slinky/web/html/hidden$.MODULE$:Lslinky/web/html/hidden$;
       3: aload_0
       4: invokevirtual #519                // Method slinky/web/html/hidden$.boolToPairtextareaApplied:(Lslinky/web/html/hidden$;)Lslinky/core/AttrPair;
       7: areturn

  public static slinky.core.AttrPair<slinky.web.html.td$tag$> boolToPairtdApplied(slinky.web.html.hidden$);
    Code:
       0: getstatic     #465                // Field slinky/web/html/hidden$.MODULE$:Lslinky/web/html/hidden$;
       3: aload_0
       4: invokevirtual #523                // Method slinky/web/html/hidden$.boolToPairtdApplied:(Lslinky/web/html/hidden$;)Lslinky/core/AttrPair;
       7: areturn

  public static slinky.core.AttrPair<slinky.web.html.tbody$tag$> boolToPairtbodyApplied(slinky.web.html.hidden$);
    Code:
       0: getstatic     #465                // Field slinky/web/html/hidden$.MODULE$:Lslinky/web/html/hidden$;
       3: aload_0
       4: invokevirtual #527                // Method slinky/web/html/hidden$.boolToPairtbodyApplied:(Lslinky/web/html/hidden$;)Lslinky/core/AttrPair;
       7: areturn

  public static slinky.core.AttrPair<slinky.web.html.table$tag$> boolToPairtableApplied(slinky.web.html.hidden$);
    Code:
       0: getstatic     #465                // Field slinky/web/html/hidden$.MODULE$:Lslinky/web/html/hidden$;
       3: aload_0
       4: invokevirtual #531                // Method slinky/web/html/hidden$.boolToPairtableApplied:(Lslinky/web/html/hidden$;)Lslinky/core/AttrPair;
       7: areturn

  public static slinky.core.AttrPair<slinky.web.html.sup$tag$> boolToPairsupApplied(slinky.web.html.hidden$);
    Code:
       0: getstatic     #465                // Field slinky/web/html/hidden$.MODULE$:Lslinky/web/html/hidden$;
       3: aload_0
       4: invokevirtual #535                // Method slinky/web/html/hidden$.boolToPairsupApplied:(Lslinky/web/html/hidden$;)Lslinky/core/AttrPair;
       7: areturn

  public static slinky.core.AttrPair<slinky.web.html.summary$tag$> boolToPairsummaryApplied(slinky.web.html.hidden$);
    Code:
       0: getstatic     #465                // Field slinky/web/html/hidden$.MODULE$:Lslinky/web/html/hidden$;
       3: aload_0
       4: invokevirtual #539                // Method slinky/web/html/hidden$.boolToPairsummaryApplied:(Lslinky/web/html/hidden$;)Lslinky/core/AttrPair;
       7: areturn

  public static slinky.core.AttrPair<slinky.web.html.sub$tag$> boolToPairsubApplied(slinky.web.html.hidden$);
    Code:
       0: getstatic     #465                // Field slinky/web/html/hidden$.MODULE$:Lslinky/web/html/hidden$;
       3: aload_0
       4: invokevirtual #543                // Method slinky/web/html/hidden$.boolToPairsubApplied:(Lslinky/web/html/hidden$;)Lslinky/core/AttrPair;
       7: areturn

  public static slinky.core.AttrPair<slinky.web.html.style$tag$> boolToPairstyleApplied(slinky.web.html.hidden$);
    Code:
       0: getstatic     #465                // Field slinky/web/html/hidden$.MODULE$:Lslinky/web/html/hidden$;
       3: aload_0
       4: invokevirtual #547                // Method slinky/web/html/hidden$.boolToPairstyleApplied:(Lslinky/web/html/hidden$;)Lslinky/core/AttrPair;
       7: areturn

  public static slinky.core.AttrPair<slinky.web.html.strong$tag$> boolToPairstrongApplied(slinky.web.html.hidden$);
    Code:
       0: getstatic     #465                // Field slinky/web/html/hidden$.MODULE$:Lslinky/web/html/hidden$;
       3: aload_0
       4: invokevirtual #551                // Method slinky/web/html/hidden$.boolToPairstrongApplied:(Lslinky/web/html/hidden$;)Lslinky/core/AttrPair;
       7: areturn

  public static slinky.core.AttrPair<slinky.web.html.span$tag$> boolToPairspanApplied(slinky.web.html.hidden$);
    Code:
       0: getstatic     #465                // Field slinky/web/html/hidden$.MODULE$:Lslinky/web/html/hidden$;
       3: aload_0
       4: invokevirtual #555                // Method slinky/web/html/hidden$.boolToPairspanApplied:(Lslinky/web/html/hidden$;)Lslinky/core/AttrPair;
       7: areturn

  public static slinky.core.AttrPair<slinky.web.html.source$tag$> boolToPairsourceApplied(slinky.web.html.hidden$);
    Code:
       0: getstatic     #465                // Field slinky/web/html/hidden$.MODULE$:Lslinky/web/html/hidden$;
       3: aload_0
       4: invokevirtual #559                // Method slinky/web/html/hidden$.boolToPairsourceApplied:(Lslinky/web/html/hidden$;)Lslinky/core/AttrPair;
       7: areturn

  public static slinky.core.AttrPair<slinky.web.html.small$tag$> boolToPairsmallApplied(slinky.web.html.hidden$);
    Code:
       0: getstatic     #465                // Field slinky/web/html/hidden$.MODULE$:Lslinky/web/html/hidden$;
       3: aload_0
       4: invokevirtual #563                // Method slinky/web/html/hidden$.boolToPairsmallApplied:(Lslinky/web/html/hidden$;)Lslinky/core/AttrPair;
       7: areturn

  public static slinky.core.AttrPair<slinky.web.html.select$tag$> boolToPairselectApplied(slinky.web.html.hidden$);
    Code:
       0: getstatic     #465                // Field slinky/web/html/hidden$.MODULE$:Lslinky/web/html/hidden$;
       3: aload_0
       4: invokevirtual #567                // Method slinky/web/html/hidden$.boolToPairselectApplied:(Lslinky/web/html/hidden$;)Lslinky/core/AttrPair;
       7: areturn

  public static slinky.core.AttrPair<slinky.web.html.section$tag$> boolToPairsectionApplied(slinky.web.html.hidden$);
    Code:
       0: getstatic     #465                // Field slinky/web/html/hidden$.MODULE$:Lslinky/web/html/hidden$;
       3: aload_0
       4: invokevirtual #571                // Method slinky/web/html/hidden$.boolToPairsectionApplied:(Lslinky/web/html/hidden$;)Lslinky/core/AttrPair;
       7: areturn

  public static slinky.core.AttrPair<slinky.web.html.script$tag$> boolToPairscriptApplied(slinky.web.html.hidden$);
    Code:
       0: getstatic     #465                // Field slinky/web/html/hidden$.MODULE$:Lslinky/web/html/hidden$;
       3: aload_0
       4: invokevirtual #575                // Method slinky/web/html/hidden$.boolToPairscriptApplied:(Lslinky/web/html/hidden$;)Lslinky/core/AttrPair;
       7: areturn

  public static slinky.core.AttrPair<slinky.web.html.samp$tag$> boolToPairsampApplied(slinky.web.html.hidden$);
    Code:
       0: getstatic     #465                // Field slinky/web/html/hidden$.MODULE$:Lslinky/web/html/hidden$;
       3: aload_0
       4: invokevirtual #579                // Method slinky/web/html/hidden$.boolToPairsampApplied:(Lslinky/web/html/hidden$;)Lslinky/core/AttrPair;
       7: areturn

  public static slinky.core.AttrPair<slinky.web.html.s$tag$> boolToPairsApplied(slinky.web.html.hidden$);
    Code:
       0: getstatic     #465                // Field slinky/web/html/hidden$.MODULE$:Lslinky/web/html/hidden$;
       3: aload_0
       4: invokevirtual #583                // Method slinky/web/html/hidden$.boolToPairsApplied:(Lslinky/web/html/hidden$;)Lslinky/core/AttrPair;
       7: areturn

  public static slinky.core.AttrPair<slinky.web.html.ruby$tag$> boolToPairrubyApplied(slinky.web.html.hidden$);
    Code:
       0: getstatic     #465                // Field slinky/web/html/hidden$.MODULE$:Lslinky/web/html/hidden$;
       3: aload_0
       4: invokevirtual #587                // Method slinky/web/html/hidden$.boolToPairrubyApplied:(Lslinky/web/html/hidden$;)Lslinky/core/AttrPair;
       7: areturn

  public static slinky.core.AttrPair<slinky.web.html.rt$tag$> boolToPairrtApplied(slinky.web.html.hidden$);
    Code:
       0: getstatic     #465                // Field slinky/web/html/hidden$.MODULE$:Lslinky/web/html/hidden$;
       3: aload_0
       4: invokevirtual #591                // Method slinky/web/html/hidden$.boolToPairrtApplied:(Lslinky/web/html/hidden$;)Lslinky/core/AttrPair;
       7: areturn

  public static slinky.core.AttrPair<slinky.web.html.rp$tag$> boolToPairrpApplied(slinky.web.html.hidden$);
    Code:
       0: getstatic     #465                // Field slinky/web/html/hidden$.MODULE$:Lslinky/web/html/hidden$;
       3: aload_0
       4: invokevirtual #595                // Method slinky/web/html/hidden$.boolToPairrpApplied:(Lslinky/web/html/hidden$;)Lslinky/core/AttrPair;
       7: areturn

  public static slinky.core.AttrPair<slinky.web.html.q$tag$> boolToPairqApplied(slinky.web.html.hidden$);
    Code:
       0: getstatic     #465                // Field slinky/web/html/hidden$.MODULE$:Lslinky/web/html/hidden$;
       3: aload_0
       4: invokevirtual #599                // Method slinky/web/html/hidden$.boolToPairqApplied:(Lslinky/web/html/hidden$;)Lslinky/core/AttrPair;
       7: areturn

  public static slinky.core.AttrPair<slinky.web.html.progress$tag$> boolToPairprogressApplied(slinky.web.html.hidden$);
    Code:
       0: getstatic     #465                // Field slinky/web/html/hidden$.MODULE$:Lslinky/web/html/hidden$;
       3: aload_0
       4: invokevirtual #603                // Method slinky/web/html/hidden$.boolToPairprogressApplied:(Lslinky/web/html/hidden$;)Lslinky/core/AttrPair;
       7: areturn

  public static slinky.core.AttrPair<slinky.web.html.pre$tag$> boolToPairpreApplied(slinky.web.html.hidden$);
    Code:
       0: getstatic     #465                // Field slinky/web/html/hidden$.MODULE$:Lslinky/web/html/hidden$;
       3: aload_0
       4: invokevirtual #607                // Method slinky/web/html/hidden$.boolToPairpreApplied:(Lslinky/web/html/hidden$;)Lslinky/core/AttrPair;
       7: areturn

  public static slinky.core.AttrPair<slinky.web.html.picture$tag$> boolToPairpictureApplied(slinky.web.html.hidden$);
    Code:
       0: getstatic     #465                // Field slinky/web/html/hidden$.MODULE$:Lslinky/web/html/hidden$;
       3: aload_0
       4: invokevirtual #611                // Method slinky/web/html/hidden$.boolToPairpictureApplied:(Lslinky/web/html/hidden$;)Lslinky/core/AttrPair;
       7: areturn

  public static slinky.core.AttrPair<slinky.web.html.param$tag$> boolToPairparamApplied(slinky.web.html.hidden$);
    Code:
       0: getstatic     #465                // Field slinky/web/html/hidden$.MODULE$:Lslinky/web/html/hidden$;
       3: aload_0
       4: invokevirtual #615                // Method slinky/web/html/hidden$.boolToPairparamApplied:(Lslinky/web/html/hidden$;)Lslinky/core/AttrPair;
       7: areturn

  public static slinky.core.AttrPair<slinky.web.html.p$tag$> boolToPairpApplied(slinky.web.html.hidden$);
    Code:
       0: getstatic     #465                // Field slinky/web/html/hidden$.MODULE$:Lslinky/web/html/hidden$;
       3: aload_0
       4: invokevirtual #619                // Method slinky/web/html/hidden$.boolToPairpApplied:(Lslinky/web/html/hidden$;)Lslinky/core/AttrPair;
       7: areturn

  public static slinky.core.AttrPair<slinky.web.html.output$tag$> boolToPairoutputApplied(slinky.web.html.hidden$);
    Code:
       0: getstatic     #465                // Field slinky/web/html/hidden$.MODULE$:Lslinky/web/html/hidden$;
       3: aload_0
       4: invokevirtual #623                // Method slinky/web/html/hidden$.boolToPairoutputApplied:(Lslinky/web/html/hidden$;)Lslinky/core/AttrPair;
       7: areturn

  public static slinky.core.AttrPair<slinky.web.html.option$tag$> boolToPairoptionApplied(slinky.web.html.hidden$);
    Code:
       0: getstatic     #465                // Field slinky/web/html/hidden$.MODULE$:Lslinky/web/html/hidden$;
       3: aload_0
       4: invokevirtual #627                // Method slinky/web/html/hidden$.boolToPairoptionApplied:(Lslinky/web/html/hidden$;)Lslinky/core/AttrPair;
       7: areturn

  public static slinky.core.AttrPair<slinky.web.html.optgroup$tag$> boolToPairoptgroupApplied(slinky.web.html.hidden$);
    Code:
       0: getstatic     #465                // Field slinky/web/html/hidden$.MODULE$:Lslinky/web/html/hidden$;
       3: aload_0
       4: invokevirtual #631                // Method slinky/web/html/hidden$.boolToPairoptgroupApplied:(Lslinky/web/html/hidden$;)Lslinky/core/AttrPair;
       7: areturn

  public static slinky.core.AttrPair<slinky.web.html.ol$tag$> boolToPairolApplied(slinky.web.html.hidden$);
    Code:
       0: getstatic     #465                // Field slinky/web/html/hidden$.MODULE$:Lslinky/web/html/hidden$;
       3: aload_0
       4: invokevirtual #635                // Method slinky/web/html/hidden$.boolToPairolApplied:(Lslinky/web/html/hidden$;)Lslinky/core/AttrPair;
       7: areturn

  public static slinky.core.AttrPair<slinky.web.html.object$tag$> boolToPairobjectApplied(slinky.web.html.hidden$);
    Code:
       0: getstatic     #465                // Field slinky/web/html/hidden$.MODULE$:Lslinky/web/html/hidden$;
       3: aload_0
       4: invokevirtual #639                // Method slinky/web/html/hidden$.boolToPairobjectApplied:(Lslinky/web/html/hidden$;)Lslinky/core/AttrPair;
       7: areturn

  public static slinky.core.AttrPair<slinky.web.html.noscript$tag$> boolToPairnoscriptApplied(slinky.web.html.hidden$);
    Code:
       0: getstatic     #465                // Field slinky/web/html/hidden$.MODULE$:Lslinky/web/html/hidden$;
       3: aload_0
       4: invokevirtual #643                // Method slinky/web/html/hidden$.boolToPairnoscriptApplied:(Lslinky/web/html/hidden$;)Lslinky/core/AttrPair;
       7: areturn

  public static slinky.core.AttrPair<slinky.web.html.nav$tag$> boolToPairnavApplied(slinky.web.html.hidden$);
    Code:
       0: getstatic     #465                // Field slinky/web/html/hidden$.MODULE$:Lslinky/web/html/hidden$;
       3: aload_0
       4: invokevirtual #647                // Method slinky/web/html/hidden$.boolToPairnavApplied:(Lslinky/web/html/hidden$;)Lslinky/core/AttrPair;
       7: areturn

  public static slinky.core.AttrPair<slinky.web.html.meter$tag$> boolToPairmeterApplied(slinky.web.html.hidden$);
    Code:
       0: getstatic     #465                // Field slinky/web/html/hidden$.MODULE$:Lslinky/web/html/hidden$;
       3: aload_0
       4: invokevirtual #651                // Method slinky/web/html/hidden$.boolToPairmeterApplied:(Lslinky/web/html/hidden$;)Lslinky/core/AttrPair;
       7: areturn

  public static slinky.core.AttrPair<slinky.web.html.meta$tag$> boolToPairmetaApplied(slinky.web.html.hidden$);
    Code:
       0: getstatic     #465                // Field slinky/web/html/hidden$.MODULE$:Lslinky/web/html/hidden$;
       3: aload_0
       4: invokevirtual #655                // Method slinky/web/html/hidden$.boolToPairmetaApplied:(Lslinky/web/html/hidden$;)Lslinky/core/AttrPair;
       7: areturn

  public static slinky.core.AttrPair<slinky.web.html.menuitem$tag$> boolToPairmenuitemApplied(slinky.web.html.hidden$);
    Code:
       0: getstatic     #465                // Field slinky/web/html/hidden$.MODULE$:Lslinky/web/html/hidden$;
       3: aload_0
       4: invokevirtual #659                // Method slinky/web/html/hidden$.boolToPairmenuitemApplied:(Lslinky/web/html/hidden$;)Lslinky/core/AttrPair;
       7: areturn

  public static slinky.core.AttrPair<slinky.web.html.menu$tag$> boolToPairmenuApplied(slinky.web.html.hidden$);
    Code:
       0: getstatic     #465                // Field slinky/web/html/hidden$.MODULE$:Lslinky/web/html/hidden$;
       3: aload_0
       4: invokevirtual #663                // Method slinky/web/html/hidden$.boolToPairmenuApplied:(Lslinky/web/html/hidden$;)Lslinky/core/AttrPair;
       7: areturn

  public static slinky.core.AttrPair<slinky.web.html.mark$tag$> boolToPairmarkApplied(slinky.web.html.hidden$);
    Code:
       0: getstatic     #465                // Field slinky/web/html/hidden$.MODULE$:Lslinky/web/html/hidden$;
       3: aload_0
       4: invokevirtual #667                // Method slinky/web/html/hidden$.boolToPairmarkApplied:(Lslinky/web/html/hidden$;)Lslinky/core/AttrPair;
       7: areturn

  public static slinky.core.AttrPair<slinky.web.html.map$tag$> boolToPairmapApplied(slinky.web.html.hidden$);
    Code:
       0: getstatic     #465                // Field slinky/web/html/hidden$.MODULE$:Lslinky/web/html/hidden$;
       3: aload_0
       4: invokevirtual #671                // Method slinky/web/html/hidden$.boolToPairmapApplied:(Lslinky/web/html/hidden$;)Lslinky/core/AttrPair;
       7: areturn

  public static slinky.core.AttrPair<slinky.web.html.main$tag$> boolToPairmainApplied(slinky.web.html.hidden$);
    Code:
       0: getstatic     #465                // Field slinky/web/html/hidden$.MODULE$:Lslinky/web/html/hidden$;
       3: aload_0
       4: invokevirtual #675                // Method slinky/web/html/hidden$.boolToPairmainApplied:(Lslinky/web/html/hidden$;)Lslinky/core/AttrPair;
       7: areturn

  public static slinky.core.AttrPair<slinky.web.html.link$tag$> boolToPairlinkApplied(slinky.web.html.hidden$);
    Code:
       0: getstatic     #465                // Field slinky/web/html/hidden$.MODULE$:Lslinky/web/html/hidden$;
       3: aload_0
       4: invokevirtual #679                // Method slinky/web/html/hidden$.boolToPairlinkApplied:(Lslinky/web/html/hidden$;)Lslinky/core/AttrPair;
       7: areturn

  public static slinky.core.AttrPair<slinky.web.html.li$tag$> boolToPairliApplied(slinky.web.html.hidden$);
    Code:
       0: getstatic     #465                // Field slinky/web/html/hidden$.MODULE$:Lslinky/web/html/hidden$;
       3: aload_0
       4: invokevirtual #683                // Method slinky/web/html/hidden$.boolToPairliApplied:(Lslinky/web/html/hidden$;)Lslinky/core/AttrPair;
       7: areturn

  public static slinky.core.AttrPair<slinky.web.html.legend$tag$> boolToPairlegendApplied(slinky.web.html.hidden$);
    Code:
       0: getstatic     #465                // Field slinky/web/html/hidden$.MODULE$:Lslinky/web/html/hidden$;
       3: aload_0
       4: invokevirtual #687                // Method slinky/web/html/hidden$.boolToPairlegendApplied:(Lslinky/web/html/hidden$;)Lslinky/core/AttrPair;
       7: areturn

  public static slinky.core.AttrPair<slinky.web.html.label$tag$> boolToPairlabelApplied(slinky.web.html.hidden$);
    Code:
       0: getstatic     #465                // Field slinky/web/html/hidden$.MODULE$:Lslinky/web/html/hidden$;
       3: aload_0
       4: invokevirtual #691                // Method slinky/web/html/hidden$.boolToPairlabelApplied:(Lslinky/web/html/hidden$;)Lslinky/core/AttrPair;
       7: areturn

  public static slinky.core.AttrPair<slinky.web.html.keygen$tag$> boolToPairkeygenApplied(slinky.web.html.hidden$);
    Code:
       0: getstatic     #465                // Field slinky/web/html/hidden$.MODULE$:Lslinky/web/html/hidden$;
       3: aload_0
       4: invokevirtual #695                // Method slinky/web/html/hidden$.boolToPairkeygenApplied:(Lslinky/web/html/hidden$;)Lslinky/core/AttrPair;
       7: areturn

  public static slinky.core.AttrPair<slinky.web.html.kbd$tag$> boolToPairkbdApplied(slinky.web.html.hidden$);
    Code:
       0: getstatic     #465                // Field slinky/web/html/hidden$.MODULE$:Lslinky/web/html/hidden$;
       3: aload_0
       4: invokevirtual #699                // Method slinky/web/html/hidden$.boolToPairkbdApplied:(Lslinky/web/html/hidden$;)Lslinky/core/AttrPair;
       7: areturn

  public static slinky.core.AttrPair<slinky.web.html.ins$tag$> boolToPairinsApplied(slinky.web.html.hidden$);
    Code:
       0: getstatic     #465                // Field slinky/web/html/hidden$.MODULE$:Lslinky/web/html/hidden$;
       3: aload_0
       4: invokevirtual #703                // Method slinky/web/html/hidden$.boolToPairinsApplied:(Lslinky/web/html/hidden$;)Lslinky/core/AttrPair;
       7: areturn

  public static slinky.core.AttrPair<slinky.web.html.input$tag$> boolToPairinputApplied(slinky.web.html.hidden$);
    Code:
       0: getstatic     #465                // Field slinky/web/html/hidden$.MODULE$:Lslinky/web/html/hidden$;
       3: aload_0
       4: invokevirtual #707                // Method slinky/web/html/hidden$.boolToPairinputApplied:(Lslinky/web/html/hidden$;)Lslinky/core/AttrPair;
       7: areturn

  public static slinky.core.AttrPair<slinky.web.html.img$tag$> boolToPairimgApplied(slinky.web.html.hidden$);
    Code:
       0: getstatic     #465                // Field slinky/web/html/hidden$.MODULE$:Lslinky/web/html/hidden$;
       3: aload_0
       4: invokevirtual #711                // Method slinky/web/html/hidden$.boolToPairimgApplied:(Lslinky/web/html/hidden$;)Lslinky/core/AttrPair;
       7: areturn

  public static slinky.core.AttrPair<slinky.web.html.iframe$tag$> boolToPairiframeApplied(slinky.web.html.hidden$);
    Code:
       0: getstatic     #465                // Field slinky/web/html/hidden$.MODULE$:Lslinky/web/html/hidden$;
       3: aload_0
       4: invokevirtual #715                // Method slinky/web/html/hidden$.boolToPairiframeApplied:(Lslinky/web/html/hidden$;)Lslinky/core/AttrPair;
       7: areturn

  public static slinky.core.AttrPair<slinky.web.html.i$tag$> boolToPairiApplied(slinky.web.html.hidden$);
    Code:
       0: getstatic     #465                // Field slinky/web/html/hidden$.MODULE$:Lslinky/web/html/hidden$;
       3: aload_0
       4: invokevirtual #719                // Method slinky/web/html/hidden$.boolToPairiApplied:(Lslinky/web/html/hidden$;)Lslinky/core/AttrPair;
       7: areturn

  public static slinky.core.AttrPair<slinky.web.html.html$tag$> boolToPairhtmlApplied(slinky.web.html.hidden$);
    Code:
       0: getstatic     #465                // Field slinky/web/html/hidden$.MODULE$:Lslinky/web/html/hidden$;
       3: aload_0
       4: invokevirtual #723                // Method slinky/web/html/hidden$.boolToPairhtmlApplied:(Lslinky/web/html/hidden$;)Lslinky/core/AttrPair;
       7: areturn

  public static slinky.core.AttrPair<slinky.web.html.hr$tag$> boolToPairhrApplied(slinky.web.html.hidden$);
    Code:
       0: getstatic     #465                // Field slinky/web/html/hidden$.MODULE$:Lslinky/web/html/hidden$;
       3: aload_0
       4: invokevirtual #727                // Method slinky/web/html/hidden$.boolToPairhrApplied:(Lslinky/web/html/hidden$;)Lslinky/core/AttrPair;
       7: areturn

  public static slinky.core.AttrPair<slinky.web.html.header$tag$> boolToPairheaderApplied(slinky.web.html.hidden$);
    Code:
       0: getstatic     #465                // Field slinky/web/html/hidden$.MODULE$:Lslinky/web/html/hidden$;
       3: aload_0
       4: invokevirtual #731                // Method slinky/web/html/hidden$.boolToPairheaderApplied:(Lslinky/web/html/hidden$;)Lslinky/core/AttrPair;
       7: areturn

  public static slinky.core.AttrPair<slinky.web.html.head$tag$> boolToPairheadApplied(slinky.web.html.hidden$);
    Code:
       0: getstatic     #465                // Field slinky/web/html/hidden$.MODULE$:Lslinky/web/html/hidden$;
       3: aload_0
       4: invokevirtual #735                // Method slinky/web/html/hidden$.boolToPairheadApplied:(Lslinky/web/html/hidden$;)Lslinky/core/AttrPair;
       7: areturn

  public static slinky.core.AttrPair<slinky.web.html.h6$tag$> boolToPairh6Applied(slinky.web.html.hidden$);
    Code:
       0: getstatic     #465                // Field slinky/web/html/hidden$.MODULE$:Lslinky/web/html/hidden$;
       3: aload_0
       4: invokevirtual #739                // Method slinky/web/html/hidden$.boolToPairh6Applied:(Lslinky/web/html/hidden$;)Lslinky/core/AttrPair;
       7: areturn

  public static slinky.core.AttrPair<slinky.web.html.h5$tag$> boolToPairh5Applied(slinky.web.html.hidden$);
    Code:
       0: getstatic     #465                // Field slinky/web/html/hidden$.MODULE$:Lslinky/web/html/hidden$;
       3: aload_0
       4: invokevirtual #743                // Method slinky/web/html/hidden$.boolToPairh5Applied:(Lslinky/web/html/hidden$;)Lslinky/core/AttrPair;
       7: areturn

  public static slinky.core.AttrPair<slinky.web.html.h4$tag$> boolToPairh4Applied(slinky.web.html.hidden$);
    Code:
       0: getstatic     #465                // Field slinky/web/html/hidden$.MODULE$:Lslinky/web/html/hidden$;
       3: aload_0
       4: invokevirtual #747                // Method slinky/web/html/hidden$.boolToPairh4Applied:(Lslinky/web/html/hidden$;)Lslinky/core/AttrPair;
       7: areturn

  public static slinky.core.AttrPair<slinky.web.html.h3$tag$> boolToPairh3Applied(slinky.web.html.hidden$);
    Code:
       0: getstatic     #465                // Field slinky/web/html/hidden$.MODULE$:Lslinky/web/html/hidden$;
       3: aload_0
       4: invokevirtual #751                // Method slinky/web/html/hidden$.boolToPairh3Applied:(Lslinky/web/html/hidden$;)Lslinky/core/AttrPair;
       7: areturn

  public static slinky.core.AttrPair<slinky.web.html.h2$tag$> boolToPairh2Applied(slinky.web.html.hidden$);
    Code:
       0: getstatic     #465                // Field slinky/web/html/hidden$.MODULE$:Lslinky/web/html/hidden$;
       3: aload_0
       4: invokevirtual #755                // Method slinky/web/html/hidden$.boolToPairh2Applied:(Lslinky/web/html/hidden$;)Lslinky/core/AttrPair;
       7: areturn

  public static slinky.core.AttrPair<slinky.web.html.h1$tag$> boolToPairh1Applied(slinky.web.html.hidden$);
    Code:
       0: getstatic     #465                // Field slinky/web/html/hidden$.MODULE$:Lslinky/web/html/hidden$;
       3: aload_0
       4: invokevirtual #759                // Method slinky/web/html/hidden$.boolToPairh1Applied:(Lslinky/web/html/hidden$;)Lslinky/core/AttrPair;
       7: areturn

  public static slinky.core.AttrPair<slinky.web.html.form$tag$> boolToPairformApplied(slinky.web.html.hidden$);
    Code:
       0: getstatic     #465                // Field slinky/web/html/hidden$.MODULE$:Lslinky/web/html/hidden$;
       3: aload_0
       4: invokevirtual #763                // Method slinky/web/html/hidden$.boolToPairformApplied:(Lslinky/web/html/hidden$;)Lslinky/core/AttrPair;
       7: areturn

  public static slinky.core.AttrPair<slinky.web.html.footer$tag$> boolToPairfooterApplied(slinky.web.html.hidden$);
    Code:
       0: getstatic     #465                // Field slinky/web/html/hidden$.MODULE$:Lslinky/web/html/hidden$;
       3: aload_0
       4: invokevirtual #767                // Method slinky/web/html/hidden$.boolToPairfooterApplied:(Lslinky/web/html/hidden$;)Lslinky/core/AttrPair;
       7: areturn

  public static slinky.core.AttrPair<slinky.web.html.figure$tag$> boolToPairfigureApplied(slinky.web.html.hidden$);
    Code:
       0: getstatic     #465                // Field slinky/web/html/hidden$.MODULE$:Lslinky/web/html/hidden$;
       3: aload_0
       4: invokevirtual #771                // Method slinky/web/html/hidden$.boolToPairfigureApplied:(Lslinky/web/html/hidden$;)Lslinky/core/AttrPair;
       7: areturn

  public static slinky.core.AttrPair<slinky.web.html.figcaption$tag$> boolToPairfigcaptionApplied(slinky.web.html.hidden$);
    Code:
       0: getstatic     #465                // Field slinky/web/html/hidden$.MODULE$:Lslinky/web/html/hidden$;
       3: aload_0
       4: invokevirtual #775                // Method slinky/web/html/hidden$.boolToPairfigcaptionApplied:(Lslinky/web/html/hidden$;)Lslinky/core/AttrPair;
       7: areturn

  public static slinky.core.AttrPair<slinky.web.html.fieldset$tag$> boolToPairfieldsetApplied(slinky.web.html.hidden$);
    Code:
       0: getstatic     #465                // Field slinky/web/html/hidden$.MODULE$:Lslinky/web/html/hidden$;
       3: aload_0
       4: invokevirtual #779                // Method slinky/web/html/hidden$.boolToPairfieldsetApplied:(Lslinky/web/html/hidden$;)Lslinky/core/AttrPair;
       7: areturn

  public static slinky.core.AttrPair<slinky.web.html.embed$tag$> boolToPairembedApplied(slinky.web.html.hidden$);
    Code:
       0: getstatic     #465                // Field slinky/web/html/hidden$.MODULE$:Lslinky/web/html/hidden$;
       3: aload_0
       4: invokevirtual #783                // Method slinky/web/html/hidden$.boolToPairembedApplied:(Lslinky/web/html/hidden$;)Lslinky/core/AttrPair;
       7: areturn

  public static slinky.core.AttrPair<slinky.web.html.em$tag$> boolToPairemApplied(slinky.web.html.hidden$);
    Code:
       0: getstatic     #465                // Field slinky/web/html/hidden$.MODULE$:Lslinky/web/html/hidden$;
       3: aload_0
       4: invokevirtual #787                // Method slinky/web/html/hidden$.boolToPairemApplied:(Lslinky/web/html/hidden$;)Lslinky/core/AttrPair;
       7: areturn

  public static slinky.core.AttrPair<slinky.web.html.dl$tag$> boolToPairdlApplied(slinky.web.html.hidden$);
    Code:
       0: getstatic     #465                // Field slinky/web/html/hidden$.MODULE$:Lslinky/web/html/hidden$;
       3: aload_0
       4: invokevirtual #791                // Method slinky/web/html/hidden$.boolToPairdlApplied:(Lslinky/web/html/hidden$;)Lslinky/core/AttrPair;
       7: areturn

  public static slinky.core.AttrPair<slinky.web.html.div$tag$> boolToPairdivApplied(slinky.web.html.hidden$);
    Code:
       0: getstatic     #465                // Field slinky/web/html/hidden$.MODULE$:Lslinky/web/html/hidden$;
       3: aload_0
       4: invokevirtual #795                // Method slinky/web/html/hidden$.boolToPairdivApplied:(Lslinky/web/html/hidden$;)Lslinky/core/AttrPair;
       7: areturn

  public static slinky.core.AttrPair<slinky.web.html.dialog$tag$> boolToPairdialogApplied(slinky.web.html.hidden$);
    Code:
       0: getstatic     #465                // Field slinky/web/html/hidden$.MODULE$:Lslinky/web/html/hidden$;
       3: aload_0
       4: invokevirtual #799                // Method slinky/web/html/hidden$.boolToPairdialogApplied:(Lslinky/web/html/hidden$;)Lslinky/core/AttrPair;
       7: areturn

  public static slinky.core.AttrPair<slinky.web.html.dfn$tag$> boolToPairdfnApplied(slinky.web.html.hidden$);
    Code:
       0: getstatic     #465                // Field slinky/web/html/hidden$.MODULE$:Lslinky/web/html/hidden$;
       3: aload_0
       4: invokevirtual #803                // Method slinky/web/html/hidden$.boolToPairdfnApplied:(Lslinky/web/html/hidden$;)Lslinky/core/AttrPair;
       7: areturn

  public static slinky.core.AttrPair<slinky.web.html.details$tag$> boolToPairdetailsApplied(slinky.web.html.hidden$);
    Code:
       0: getstatic     #465                // Field slinky/web/html/hidden$.MODULE$:Lslinky/web/html/hidden$;
       3: aload_0
       4: invokevirtual #807                // Method slinky/web/html/hidden$.boolToPairdetailsApplied:(Lslinky/web/html/hidden$;)Lslinky/core/AttrPair;
       7: areturn

  public static slinky.core.AttrPair<slinky.web.html.del$tag$> boolToPairdelApplied(slinky.web.html.hidden$);
    Code:
       0: getstatic     #465                // Field slinky/web/html/hidden$.MODULE$:Lslinky/web/html/hidden$;
       3: aload_0
       4: invokevirtual #811                // Method slinky/web/html/hidden$.boolToPairdelApplied:(Lslinky/web/html/hidden$;)Lslinky/core/AttrPair;
       7: areturn

  public static slinky.core.AttrPair<slinky.web.html.datalist$tag$> boolToPairdatalistApplied(slinky.web.html.hidden$);
    Code:
       0: getstatic     #465                // Field slinky/web/html/hidden$.MODULE$:Lslinky/web/html/hidden$;
       3: aload_0
       4: invokevirtual #815                // Method slinky/web/html/hidden$.boolToPairdatalistApplied:(Lslinky/web/html/hidden$;)Lslinky/core/AttrPair;
       7: areturn

  public static slinky.core.AttrPair<slinky.web.html.data$tag$> boolToPairdataApplied(slinky.web.html.hidden$);
    Code:
       0: getstatic     #465                // Field slinky/web/html/hidden$.MODULE$:Lslinky/web/html/hidden$;
       3: aload_0
       4: invokevirtual #819                // Method slinky/web/html/hidden$.boolToPairdataApplied:(Lslinky/web/html/hidden$;)Lslinky/core/AttrPair;
       7: areturn

  public static slinky.core.AttrPair<slinky.web.html.colgroup$tag$> boolToPaircolgroupApplied(slinky.web.html.hidden$);
    Code:
       0: getstatic     #465                // Field slinky/web/html/hidden$.MODULE$:Lslinky/web/html/hidden$;
       3: aload_0
       4: invokevirtual #823                // Method slinky/web/html/hidden$.boolToPaircolgroupApplied:(Lslinky/web/html/hidden$;)Lslinky/core/AttrPair;
       7: areturn

  public static slinky.core.AttrPair<slinky.web.html.col$tag$> boolToPaircolApplied(slinky.web.html.hidden$);
    Code:
       0: getstatic     #465                // Field slinky/web/html/hidden$.MODULE$:Lslinky/web/html/hidden$;
       3: aload_0
       4: invokevirtual #827                // Method slinky/web/html/hidden$.boolToPaircolApplied:(Lslinky/web/html/hidden$;)Lslinky/core/AttrPair;
       7: areturn

  public static slinky.core.AttrPair<slinky.web.html.code$tag$> boolToPaircodeApplied(slinky.web.html.hidden$);
    Code:
       0: getstatic     #465                // Field slinky/web/html/hidden$.MODULE$:Lslinky/web/html/hidden$;
       3: aload_0
       4: invokevirtual #831                // Method slinky/web/html/hidden$.boolToPaircodeApplied:(Lslinky/web/html/hidden$;)Lslinky/core/AttrPair;
       7: areturn

  public static slinky.core.AttrPair<slinky.web.html.cite$tag$> boolToPairciteApplied(slinky.web.html.hidden$);
    Code:
       0: getstatic     #465                // Field slinky/web/html/hidden$.MODULE$:Lslinky/web/html/hidden$;
       3: aload_0
       4: invokevirtual #835                // Method slinky/web/html/hidden$.boolToPairciteApplied:(Lslinky/web/html/hidden$;)Lslinky/core/AttrPair;
       7: areturn

  public static slinky.core.AttrPair<slinky.web.html.caption$tag$> boolToPaircaptionApplied(slinky.web.html.hidden$);
    Code:
       0: getstatic     #465                // Field slinky/web/html/hidden$.MODULE$:Lslinky/web/html/hidden$;
       3: aload_0
       4: invokevirtual #839                // Method slinky/web/html/hidden$.boolToPaircaptionApplied:(Lslinky/web/html/hidden$;)Lslinky/core/AttrPair;
       7: areturn

  public static slinky.core.AttrPair<slinky.web.html.canvas$tag$> boolToPaircanvasApplied(slinky.web.html.hidden$);
    Code:
       0: getstatic     #465                // Field slinky/web/html/hidden$.MODULE$:Lslinky/web/html/hidden$;
       3: aload_0
       4: invokevirtual #843                // Method slinky/web/html/hidden$.boolToPaircanvasApplied:(Lslinky/web/html/hidden$;)Lslinky/core/AttrPair;
       7: areturn

  public static slinky.core.AttrPair<slinky.web.html.button$tag$> boolToPairbuttonApplied(slinky.web.html.hidden$);
    Code:
       0: getstatic     #465                // Field slinky/web/html/hidden$.MODULE$:Lslinky/web/html/hidden$;
       3: aload_0
       4: invokevirtual #847                // Method slinky/web/html/hidden$.boolToPairbuttonApplied:(Lslinky/web/html/hidden$;)Lslinky/core/AttrPair;
       7: areturn

  public static slinky.core.AttrPair<slinky.web.html.br$tag$> boolToPairbrApplied(slinky.web.html.hidden$);
    Code:
       0: getstatic     #465                // Field slinky/web/html/hidden$.MODULE$:Lslinky/web/html/hidden$;
       3: aload_0
       4: invokevirtual #851                // Method slinky/web/html/hidden$.boolToPairbrApplied:(Lslinky/web/html/hidden$;)Lslinky/core/AttrPair;
       7: areturn

  public static slinky.core.AttrPair<slinky.web.html.body$tag$> boolToPairbodyApplied(slinky.web.html.hidden$);
    Code:
       0: getstatic     #465                // Field slinky/web/html/hidden$.MODULE$:Lslinky/web/html/hidden$;
       3: aload_0
       4: invokevirtual #855                // Method slinky/web/html/hidden$.boolToPairbodyApplied:(Lslinky/web/html/hidden$;)Lslinky/core/AttrPair;
       7: areturn

  public static slinky.core.AttrPair<slinky.web.html.blockquote$tag$> boolToPairblockquoteApplied(slinky.web.html.hidden$);
    Code:
       0: getstatic     #465                // Field slinky/web/html/hidden$.MODULE$:Lslinky/web/html/hidden$;
       3: aload_0
       4: invokevirtual #859                // Method slinky/web/html/hidden$.boolToPairblockquoteApplied:(Lslinky/web/html/hidden$;)Lslinky/core/AttrPair;
       7: areturn

  public static slinky.core.AttrPair<slinky.web.html.big$tag$> boolToPairbigApplied(slinky.web.html.hidden$);
    Code:
       0: getstatic     #465                // Field slinky/web/html/hidden$.MODULE$:Lslinky/web/html/hidden$;
       3: aload_0
       4: invokevirtual #863                // Method slinky/web/html/hidden$.boolToPairbigApplied:(Lslinky/web/html/hidden$;)Lslinky/core/AttrPair;
       7: areturn

  public static slinky.core.AttrPair<slinky.web.html.bdo$tag$> boolToPairbdoApplied(slinky.web.html.hidden$);
    Code:
       0: getstatic     #465                // Field slinky/web/html/hidden$.MODULE$:Lslinky/web/html/hidden$;
       3: aload_0
       4: invokevirtual #867                // Method slinky/web/html/hidden$.boolToPairbdoApplied:(Lslinky/web/html/hidden$;)Lslinky/core/AttrPair;
       7: areturn

  public static slinky.core.AttrPair<slinky.web.html.bdi$tag$> boolToPairbdiApplied(slinky.web.html.hidden$);
    Code:
       0: getstatic     #465                // Field slinky/web/html/hidden$.MODULE$:Lslinky/web/html/hidden$;
       3: aload_0
       4: invokevirtual #871                // Method slinky/web/html/hidden$.boolToPairbdiApplied:(Lslinky/web/html/hidden$;)Lslinky/core/AttrPair;
       7: areturn

  public static slinky.core.AttrPair<slinky.web.html.base$tag$> boolToPairbaseApplied(slinky.web.html.hidden$);
    Code:
       0: getstatic     #465                // Field slinky/web/html/hidden$.MODULE$:Lslinky/web/html/hidden$;
       3: aload_0
       4: invokevirtual #875                // Method slinky/web/html/hidden$.boolToPairbaseApplied:(Lslinky/web/html/hidden$;)Lslinky/core/AttrPair;
       7: areturn

  public static slinky.core.AttrPair<slinky.web.html.b$tag$> boolToPairbApplied(slinky.web.html.hidden$);
    Code:
       0: getstatic     #465                // Field slinky/web/html/hidden$.MODULE$:Lslinky/web/html/hidden$;
       3: aload_0
       4: invokevirtual #879                // Method slinky/web/html/hidden$.boolToPairbApplied:(Lslinky/web/html/hidden$;)Lslinky/core/AttrPair;
       7: areturn

  public static slinky.core.AttrPair<slinky.web.html.audio$tag$> boolToPairaudioApplied(slinky.web.html.hidden$);
    Code:
       0: getstatic     #465                // Field slinky/web/html/hidden$.MODULE$:Lslinky/web/html/hidden$;
       3: aload_0
       4: invokevirtual #883                // Method slinky/web/html/hidden$.boolToPairaudioApplied:(Lslinky/web/html/hidden$;)Lslinky/core/AttrPair;
       7: areturn

  public static slinky.core.AttrPair<slinky.web.html.aside$tag$> boolToPairasideApplied(slinky.web.html.hidden$);
    Code:
       0: getstatic     #465                // Field slinky/web/html/hidden$.MODULE$:Lslinky/web/html/hidden$;
       3: aload_0
       4: invokevirtual #887                // Method slinky/web/html/hidden$.boolToPairasideApplied:(Lslinky/web/html/hidden$;)Lslinky/core/AttrPair;
       7: areturn

  public static slinky.core.AttrPair<slinky.web.html.article$tag$> boolToPairarticleApplied(slinky.web.html.hidden$);
    Code:
       0: getstatic     #465                // Field slinky/web/html/hidden$.MODULE$:Lslinky/web/html/hidden$;
       3: aload_0
       4: invokevirtual #891                // Method slinky/web/html/hidden$.boolToPairarticleApplied:(Lslinky/web/html/hidden$;)Lslinky/core/AttrPair;
       7: areturn

  public static slinky.core.AttrPair<slinky.web.html.area$tag$> boolToPairareaApplied(slinky.web.html.hidden$);
    Code:
       0: getstatic     #465                // Field slinky/web/html/hidden$.MODULE$:Lslinky/web/html/hidden$;
       3: aload_0
       4: invokevirtual #895                // Method slinky/web/html/hidden$.boolToPairareaApplied:(Lslinky/web/html/hidden$;)Lslinky/core/AttrPair;
       7: areturn

  public static slinky.core.AttrPair<slinky.web.html.address$tag$> boolToPairaddressApplied(slinky.web.html.hidden$);
    Code:
       0: getstatic     #465                // Field slinky/web/html/hidden$.MODULE$:Lslinky/web/html/hidden$;
       3: aload_0
       4: invokevirtual #899                // Method slinky/web/html/hidden$.boolToPairaddressApplied:(Lslinky/web/html/hidden$;)Lslinky/core/AttrPair;
       7: areturn

  public static slinky.core.AttrPair<slinky.web.html.abbr$tag$> boolToPairabbrApplied(slinky.web.html.hidden$);
    Code:
       0: getstatic     #465                // Field slinky/web/html/hidden$.MODULE$:Lslinky/web/html/hidden$;
       3: aload_0
       4: invokevirtual #903                // Method slinky/web/html/hidden$.boolToPairabbrApplied:(Lslinky/web/html/hidden$;)Lslinky/core/AttrPair;
       7: areturn

  public static slinky.core.AttrPair<slinky.web.html.a$tag$> boolToPairaApplied(slinky.web.html.hidden$);
    Code:
       0: getstatic     #465                // Field slinky/web/html/hidden$.MODULE$:Lslinky/web/html/hidden$;
       3: aload_0
       4: invokevirtual #907                // Method slinky/web/html/hidden$.boolToPairaApplied:(Lslinky/web/html/hidden$;)Lslinky/core/AttrPair;
       7: areturn

  public static slinky.core.OptionalAttrPair<slinky.web.html._hidden_attr$> $colon$eq(scala.Option<java.lang.Object>);
    Code:
       0: getstatic     #465                // Field slinky/web/html/hidden$.MODULE$:Lslinky/web/html/hidden$;
       3: aload_0
       4: invokevirtual #913                // Method slinky/web/html/hidden$.$colon$eq:(Lscala/Option;)Lslinky/core/OptionalAttrPair;
       7: areturn

  public static slinky.core.AttrPair<slinky.web.html._hidden_attr$> $colon$eq(boolean);
    Code:
       0: getstatic     #465                // Field slinky/web/html/hidden$.MODULE$:Lslinky/web/html/hidden$;
       3: iload_0
       4: invokevirtual #917                // Method slinky/web/html/hidden$.$colon$eq:(Z)Lslinky/core/AttrPair;
       7: areturn
}
