Compiled from "DefaultMapperCollection.java"
public class net.minidev.json.writer.DefaultMapperCollection<T> extends net.minidev.json.writer.JsonReaderI<T> {
  java.lang.Class<T> clz;

  public net.minidev.json.writer.DefaultMapperCollection(net.minidev.json.writer.JsonReader, java.lang.Class<T>);
    Code:
       0: aload_0
       1: aload_1
       2: invokespecial #1                  // Method net/minidev/json/writer/JsonReaderI."<init>":(Lnet/minidev/json/writer/JsonReader;)V
       5: aload_0
       6: aload_2
       7: putfield      #2                  // Field clz:Ljava/lang/Class;
      10: return

  public net.minidev.json.writer.JsonReaderI<T> startObject(java.lang.String);
    Code:
       0: aload_0
       1: areturn

  public net.minidev.json.writer.JsonReaderI<T> startArray(java.lang.String);
    Code:
       0: aload_0
       1: areturn

  public java.lang.Object createObject();
    Code:
       0: aload_0
       1: getfield      #2                  // Field clz:Ljava/lang/Class;
       4: iconst_0
       5: anewarray     #3                  // class java/lang/Class
       8: invokevirtual #4                  // Method java/lang/Class.getConstructor:([Ljava/lang/Class;)Ljava/lang/reflect/Constructor;
      11: astore_1
      12: aload_1
      13: iconst_0
      14: anewarray     #5                  // class java/lang/Object
      17: invokevirtual #6                  // Method java/lang/reflect/Constructor.newInstance:([Ljava/lang/Object;)Ljava/lang/Object;
      20: areturn
      21: astore_1
      22: aconst_null
      23: areturn
    Exception table:
       from    to  target type
           0    20    21   Class java/lang/Exception

  public java.lang.Object createArray();
    Code:
       0: aload_0
       1: getfield      #2                  // Field clz:Ljava/lang/Class;
       4: iconst_0
       5: anewarray     #3                  // class java/lang/Class
       8: invokevirtual #4                  // Method java/lang/Class.getConstructor:([Ljava/lang/Class;)Ljava/lang/reflect/Constructor;
      11: astore_1
      12: aload_1
      13: iconst_0
      14: anewarray     #5                  // class java/lang/Object
      17: invokevirtual #6                  // Method java/lang/reflect/Constructor.newInstance:([Ljava/lang/Object;)Ljava/lang/Object;
      20: areturn
      21: astore_1
      22: aconst_null
      23: areturn
    Exception table:
       from    to  target type
           0    20    21   Class java/lang/Exception

  public void setValue(java.lang.Object, java.lang.String, java.lang.Object);
    Code:
       0: aload_1
       1: checkcast     #8                  // class java/util/Map
       4: aload_2
       5: aload_3
       6: invokeinterface #9,  3            // InterfaceMethod java/util/Map.put:(Ljava/lang/Object;Ljava/lang/Object;)Ljava/lang/Object;
      11: pop
      12: return

  public void addValue(java.lang.Object, java.lang.Object);
    Code:
       0: aload_1
       1: checkcast     #10                 // class java/util/List
       4: aload_2
       5: invokeinterface #11,  2           // InterfaceMethod java/util/List.add:(Ljava/lang/Object;)Z
      10: pop
      11: return
}
