Compiled from "ResultMessage.java"
public class org.graylog2.indexer.results.ResultMessage {
  private static final org.slf4j.Logger LOG;

  private org.graylog2.plugin.Message message;

  private java.lang.String index;

  public com.google.common.collect.Multimap<java.lang.String, com.google.common.collect.Range<java.lang.Integer>> highlightRanges;

  protected org.graylog2.indexer.results.ResultMessage();
    Code:
       0: aload_0
       1: invokespecial #1                  // Method java/lang/Object."<init>":()V
       4: return

  private org.graylog2.indexer.results.ResultMessage(java.lang.String, java.lang.String, java.util.Map<java.lang.String, java.lang.Object>, com.google.common.collect.Multimap<java.lang.String, com.google.common.collect.Range<java.lang.Integer>>);
    Code:
       0: aload_0
       1: invokespecial #1                  // Method java/lang/Object."<init>":()V
       4: aload_0
       5: aload_2
       6: putfield      #2                  // Field index:Ljava/lang/String;
       9: aload_0
      10: aload         4
      12: putfield      #3                  // Field highlightRanges:Lcom/google/common/collect/Multimap;
      15: aload_0
      16: aload_1
      17: aload_3
      18: invokevirtual #4                  // Method setMessage:(Ljava/lang/String;Ljava/util/Map;)V
      21: return

  public static org.graylog2.indexer.results.ResultMessage parseFromSource(java.lang.String, java.lang.String, java.util.Map<java.lang.String, java.lang.Object>);
    Code:
       0: aload_0
       1: aload_1
       2: aload_2
       3: invokestatic  #5                  // Method java/util/Collections.emptyMap:()Ljava/util/Map;
       6: invokestatic  #6                  // Method parseFromSource:(Ljava/lang/String;Ljava/lang/String;Ljava/util/Map;Ljava/util/Map;)Lorg/graylog2/indexer/results/ResultMessage;
       9: areturn

  public static org.graylog2.indexer.results.ResultMessage parseFromSource(java.lang.String, java.lang.String, java.util.Map<java.lang.String, java.lang.Object>, java.util.Map<java.lang.String, java.util.List<java.lang.String>>);
    Code:
       0: new           #7                  // class org/graylog2/indexer/results/ResultMessage
       3: dup
       4: aload_0
       5: aload_1
       6: aload_2
       7: aload_3
       8: invokestatic  #8                  // Method org/graylog2/indexer/results/HighlightParser.extractHighlightRanges:(Ljava/util/Map;)Lcom/google/common/collect/Multimap;
      11: invokespecial #9                  // Method "<init>":(Ljava/lang/String;Ljava/lang/String;Ljava/util/Map;Lcom/google/common/collect/Multimap;)V
      14: areturn

  public static org.graylog2.indexer.results.ResultMessage createFromMessage(org.graylog2.plugin.Message);
    Code:
       0: new           #7                  // class org/graylog2/indexer/results/ResultMessage
       3: dup
       4: invokespecial #10                 // Method "<init>":()V
       7: astore_1
       8: aload_1
       9: aload_0
      10: invokevirtual #11                 // Method setMessage:(Lorg/graylog2/plugin/Message;)V
      13: aload_1
      14: areturn

  public void setMessage(org.graylog2.plugin.Message);
    Code:
       0: aload_0
       1: aload_1
       2: putfield      #12                 // Field message:Lorg/graylog2/plugin/Message;
       5: return

  public void setMessage(java.lang.String, java.util.Map<java.lang.String, java.lang.Object>);
    Code:
       0: invokestatic  #13                 // Method com/google/common/collect/Maps.newHashMap:()Ljava/util/HashMap;
       3: astore_3
       4: aload_3
       5: aload_2
       6: invokeinterface #14,  2           // InterfaceMethod java/util/Map.putAll:(Ljava/util/Map;)V
      11: aload_3
      12: ldc           #16                 // String _id
      14: aload_1
      15: invokeinterface #17,  3           // InterfaceMethod java/util/Map.put:(Ljava/lang/Object;Ljava/lang/Object;)Ljava/lang/Object;
      20: pop
      21: aload_3
      22: ldc           #18                 // String timestamp
      24: invokeinterface #19,  2           // InterfaceMethod java/util/Map.containsKey:(Ljava/lang/Object;)Z
      29: ifeq          87
      32: aload_3
      33: ldc           #18                 // String timestamp
      35: invokeinterface #20,  2           // InterfaceMethod java/util/Map.get:(Ljava/lang/Object;)Ljava/lang/Object;
      40: astore        4
      42: aload_3
      43: ldc           #18                 // String timestamp
      45: getstatic     #21                 // Field org/graylog2/plugin/Tools.ES_DATE_FORMAT_FORMATTER:Lorg/joda/time/format/DateTimeFormatter;
      48: aload         4
      50: invokestatic  #22                 // Method java/lang/String.valueOf:(Ljava/lang/Object;)Ljava/lang/String;
      53: invokevirtual #23                 // Method org/joda/time/format/DateTimeFormatter.parseDateTime:(Ljava/lang/String;)Lorg/joda/time/DateTime;
      56: invokeinterface #17,  3           // InterfaceMethod java/util/Map.put:(Ljava/lang/Object;Ljava/lang/Object;)Ljava/lang/Object;
      61: pop
      62: goto          87
      65: astore        5
      67: getstatic     #25                 // Field LOG:Lorg/slf4j/Logger;
      70: ldc           #26                 // String Could not parse timestamp of message {}
      72: aload_2
      73: ldc           #27                 // String id
      75: invokeinterface #20,  2           // InterfaceMethod java/util/Map.get:(Ljava/lang/Object;)Ljava/lang/Object;
      80: aload         5
      82: invokeinterface #28,  4           // InterfaceMethod org/slf4j/Logger.warn:(Ljava/lang/String;Ljava/lang/Object;Ljava/lang/Object;)V
      87: aload_0
      88: new           #15                 // class org/graylog2/plugin/Message
      91: dup
      92: aload_3
      93: invokespecial #29                 // Method org/graylog2/plugin/Message."<init>":(Ljava/util/Map;)V
      96: putfield      #12                 // Field message:Lorg/graylog2/plugin/Message;
      99: return
    Exception table:
       from    to  target type
          42    62    65   Class java/lang/IllegalArgumentException

  public void setIndex(java.lang.String);
    Code:
       0: aload_0
       1: aload_1
       2: putfield      #2                  // Field index:Ljava/lang/String;
       5: return

  public org.graylog2.plugin.Message getMessage();
    Code:
       0: aload_0
       1: getfield      #12                 // Field message:Lorg/graylog2/plugin/Message;
       4: areturn

  public java.lang.String getIndex();
    Code:
       0: aload_0
       1: getfield      #2                  // Field index:Ljava/lang/String;
       4: areturn

  static {};
    Code:
       0: ldc           #7                  // class org/graylog2/indexer/results/ResultMessage
       2: invokestatic  #30                 // Method org/slf4j/LoggerFactory.getLogger:(Ljava/lang/Class;)Lorg/slf4j/Logger;
       5: putstatic     #25                 // Field LOG:Lorg/slf4j/Logger;
       8: return
}
