Compiled from "SignatureMarshaller.java"
public class org.opensaml.xmlsec.signature.impl.SignatureMarshaller implements org.opensaml.core.xml.io.Marshaller {
  private final org.slf4j.Logger log;

  public org.opensaml.xmlsec.signature.impl.SignatureMarshaller();
    Code:
       0: aload_0
       1: invokespecial #1                  // Method java/lang/Object."<init>":()V
       4: aload_0
       5: ldc_w         #2                  // class org/opensaml/xmlsec/signature/impl/SignatureMarshaller
       8: invokestatic  #3                  // Method org/slf4j/LoggerFactory.getLogger:(Ljava/lang/Class;)Lorg/slf4j/Logger;
      11: putfield      #4                  // Field log:Lorg/slf4j/Logger;
      14: invokestatic  #5                  // Method org/apache/xml/security/Init.isInitialized:()Z
      17: ifne          34
      20: aload_0
      21: getfield      #4                  // Field log:Lorg/slf4j/Logger;
      24: ldc           #6                  // String Initializing XML security library
      26: invokeinterface #7,  2            // InterfaceMethod org/slf4j/Logger.debug:(Ljava/lang/String;)V
      31: invokestatic  #8                  // Method org/apache/xml/security/Init.init:()V
      34: return

  public org.w3c.dom.Element marshall(org.opensaml.core.xml.XMLObject) throws org.opensaml.core.xml.io.MarshallingException;
    Code:
       0: invokestatic  #9                  // Method javax/xml/parsers/DocumentBuilderFactory.newInstance:()Ljavax/xml/parsers/DocumentBuilderFactory;
       3: invokevirtual #10                 // Method javax/xml/parsers/DocumentBuilderFactory.newDocumentBuilder:()Ljavax/xml/parsers/DocumentBuilder;
       6: invokevirtual #11                 // Method javax/xml/parsers/DocumentBuilder.newDocument:()Lorg/w3c/dom/Document;
       9: astore_2
      10: aload_0
      11: aload_1
      12: aload_2
      13: invokevirtual #12                 // Method marshall:(Lorg/opensaml/core/xml/XMLObject;Lorg/w3c/dom/Document;)Lorg/w3c/dom/Element;
      16: areturn
      17: astore_2
      18: new           #14                 // class org/opensaml/core/xml/io/MarshallingException
      21: dup
      22: ldc           #15                 // String Unable to create Document to place marshalled elements in
      24: aload_2
      25: invokespecial #16                 // Method org/opensaml/core/xml/io/MarshallingException."<init>":(Ljava/lang/String;Ljava/lang/Exception;)V
      28: athrow
    Exception table:
       from    to  target type
           0    16    17   Class javax/xml/parsers/ParserConfigurationException

  public org.w3c.dom.Element marshall(org.opensaml.core.xml.XMLObject, org.w3c.dom.Element) throws org.opensaml.core.xml.io.MarshallingException;
    Code:
       0: aload_0
       1: aload_1
       2: checkcast     #17                 // class org/opensaml/xmlsec/signature/impl/SignatureImpl
       5: aload_2
       6: invokeinterface #18,  1           // InterfaceMethod org/w3c/dom/Element.getOwnerDocument:()Lorg/w3c/dom/Document;
      11: invokespecial #19                 // Method createSignatureElement:(Lorg/opensaml/xmlsec/signature/Signature;Lorg/w3c/dom/Document;)Lorg/w3c/dom/Element;
      14: astore_3
      15: aload_2
      16: aload_3
      17: invokestatic  #20                 // Method net/shibboleth/utilities/java/support/xml/ElementSupport.appendChildElement:(Lorg/w3c/dom/Element;Lorg/w3c/dom/Element;)V
      20: aload_3
      21: areturn

  public org.w3c.dom.Element marshall(org.opensaml.core.xml.XMLObject, org.w3c.dom.Document) throws org.opensaml.core.xml.io.MarshallingException;
    Code:
       0: aload_0
       1: aload_1
       2: checkcast     #17                 // class org/opensaml/xmlsec/signature/impl/SignatureImpl
       5: aload_2
       6: invokespecial #19                 // Method createSignatureElement:(Lorg/opensaml/xmlsec/signature/Signature;Lorg/w3c/dom/Document;)Lorg/w3c/dom/Element;
       9: astore_3
      10: aload_2
      11: invokeinterface #21,  1           // InterfaceMethod org/w3c/dom/Document.getDocumentElement:()Lorg/w3c/dom/Element;
      16: astore        4
      18: aload         4
      20: ifnull        36
      23: aload_2
      24: aload_3
      25: aload         4
      27: invokeinterface #22,  3           // InterfaceMethod org/w3c/dom/Document.replaceChild:(Lorg/w3c/dom/Node;Lorg/w3c/dom/Node;)Lorg/w3c/dom/Node;
      32: pop
      33: goto          44
      36: aload_2
      37: aload_3
      38: invokeinterface #23,  2           // InterfaceMethod org/w3c/dom/Document.appendChild:(Lorg/w3c/dom/Node;)Lorg/w3c/dom/Node;
      43: pop
      44: aload_3
      45: areturn

  private org.w3c.dom.Element createSignatureElement(org.opensaml.xmlsec.signature.Signature, org.w3c.dom.Document) throws org.opensaml.core.xml.io.MarshallingException;
    Code:
       0: aload_0
       1: getfield      #4                  // Field log:Lorg/slf4j/Logger;
       4: ldc           #24                 // String Starting to marshall {}
       6: aload_1
       7: invokeinterface #25,  1           // InterfaceMethod org/opensaml/xmlsec/signature/Signature.getElementQName:()Ljavax/xml/namespace/QName;
      12: invokeinterface #26,  3           // InterfaceMethod org/slf4j/Logger.debug:(Ljava/lang/String;Ljava/lang/Object;)V
      17: aload_0
      18: getfield      #4                  // Field log:Lorg/slf4j/Logger;
      21: ldc           #27                 // String Creating XMLSignature object
      23: invokeinterface #7,  2            // InterfaceMethod org/slf4j/Logger.debug:(Ljava/lang/String;)V
      28: aconst_null
      29: astore_3
      30: aload_1
      31: invokeinterface #28,  1           // InterfaceMethod org/opensaml/xmlsec/signature/Signature.getHMACOutputLength:()Ljava/lang/Integer;
      36: ifnull        86
      39: aload_1
      40: invokeinterface #29,  1           // InterfaceMethod org/opensaml/xmlsec/signature/Signature.getSignatureAlgorithm:()Ljava/lang/String;
      45: invokestatic  #30                 // Method org/opensaml/xmlsec/algorithm/AlgorithmSupport.isHMAC:(Ljava/lang/String;)Z
      48: ifeq          86
      51: new           #31                 // class org/apache/xml/security/signature/XMLSignature
      54: dup
      55: aload_2
      56: ldc           #32                 // String
      58: aload_1
      59: invokeinterface #29,  1           // InterfaceMethod org/opensaml/xmlsec/signature/Signature.getSignatureAlgorithm:()Ljava/lang/String;
      64: aload_1
      65: invokeinterface #28,  1           // InterfaceMethod org/opensaml/xmlsec/signature/Signature.getHMACOutputLength:()Ljava/lang/Integer;
      70: invokevirtual #33                 // Method java/lang/Integer.intValue:()I
      73: aload_1
      74: invokeinterface #34,  1           // InterfaceMethod org/opensaml/xmlsec/signature/Signature.getCanonicalizationAlgorithm:()Ljava/lang/String;
      79: invokespecial #35                 // Method org/apache/xml/security/signature/XMLSignature."<init>":(Lorg/w3c/dom/Document;Ljava/lang/String;Ljava/lang/String;ILjava/lang/String;)V
      82: astore_3
      83: goto          109
      86: new           #31                 // class org/apache/xml/security/signature/XMLSignature
      89: dup
      90: aload_2
      91: ldc           #32                 // String
      93: aload_1
      94: invokeinterface #29,  1           // InterfaceMethod org/opensaml/xmlsec/signature/Signature.getSignatureAlgorithm:()Ljava/lang/String;
      99: aload_1
     100: invokeinterface #34,  1           // InterfaceMethod org/opensaml/xmlsec/signature/Signature.getCanonicalizationAlgorithm:()Ljava/lang/String;
     105: invokespecial #36                 // Method org/apache/xml/security/signature/XMLSignature."<init>":(Lorg/w3c/dom/Document;Ljava/lang/String;Ljava/lang/String;Ljava/lang/String;)V
     108: astore_3
     109: aload_0
     110: getfield      #4                  // Field log:Lorg/slf4j/Logger;
     113: ldc           #37                 // String Adding content to XMLSignature.
     115: invokeinterface #7,  2            // InterfaceMethod org/slf4j/Logger.debug:(Ljava/lang/String;)V
     120: aload_1
     121: invokeinterface #38,  1           // InterfaceMethod org/opensaml/xmlsec/signature/Signature.getContentReferences:()Ljava/util/List;
     126: invokeinterface #39,  1           // InterfaceMethod java/util/List.iterator:()Ljava/util/Iterator;
     131: astore        4
     133: aload         4
     135: invokeinterface #40,  1           // InterfaceMethod java/util/Iterator.hasNext:()Z
     140: ifeq          166
     143: aload         4
     145: invokeinterface #41,  1           // InterfaceMethod java/util/Iterator.next:()Ljava/lang/Object;
     150: checkcast     #42                 // class org/opensaml/xmlsec/signature/support/ContentReference
     153: astore        5
     155: aload         5
     157: aload_3
     158: invokeinterface #43,  2           // InterfaceMethod org/opensaml/xmlsec/signature/support/ContentReference.createReference:(Lorg/apache/xml/security/signature/XMLSignature;)V
     163: goto          133
     166: aload_0
     167: getfield      #4                  // Field log:Lorg/slf4j/Logger;
     170: ldc           #44                 // String Creating Signature DOM element
     172: invokeinterface #7,  2            // InterfaceMethod org/slf4j/Logger.debug:(Ljava/lang/String;)V
     177: aload_3
     178: invokevirtual #45                 // Method org/apache/xml/security/signature/XMLSignature.getElement:()Lorg/w3c/dom/Element;
     181: astore        4
     183: aload_1
     184: invokeinterface #46,  1           // InterfaceMethod org/opensaml/xmlsec/signature/Signature.getKeyInfo:()Lorg/opensaml/xmlsec/signature/KeyInfo;
     189: ifnull        219
     192: invokestatic  #47                 // Method org/opensaml/core/xml/config/XMLObjectProviderRegistrySupport.getMarshallerFactory:()Lorg/opensaml/core/xml/io/MarshallerFactory;
     195: getstatic     #48                 // Field org/opensaml/xmlsec/signature/KeyInfo.DEFAULT_ELEMENT_NAME:Ljavax/xml/namespace/QName;
     198: invokevirtual #49                 // Method org/opensaml/core/xml/io/MarshallerFactory.getMarshaller:(Ljavax/xml/namespace/QName;)Lorg/opensaml/core/xml/io/Marshaller;
     201: astore        5
     203: aload         5
     205: aload_1
     206: invokeinterface #46,  1           // InterfaceMethod org/opensaml/xmlsec/signature/Signature.getKeyInfo:()Lorg/opensaml/xmlsec/signature/KeyInfo;
     211: aload         4
     213: invokeinterface #50,  3           // InterfaceMethod org/opensaml/core/xml/io/Marshaller.marshall:(Lorg/opensaml/core/xml/XMLObject;Lorg/w3c/dom/Element;)Lorg/w3c/dom/Element;
     218: pop
     219: aload_1
     220: checkcast     #17                 // class org/opensaml/xmlsec/signature/impl/SignatureImpl
     223: aload_3
     224: invokevirtual #51                 // Method org/opensaml/xmlsec/signature/impl/SignatureImpl.setXMLSignature:(Lorg/apache/xml/security/signature/XMLSignature;)V
     227: aload_1
     228: aload         4
     230: invokeinterface #52,  2           // InterfaceMethod org/opensaml/xmlsec/signature/Signature.setDOM:(Lorg/w3c/dom/Element;)V
     235: aload_1
     236: iconst_1
     237: invokeinterface #53,  2           // InterfaceMethod org/opensaml/xmlsec/signature/Signature.releaseParentDOM:(Z)V
     242: aload         4
     244: areturn
     245: astore_3
     246: new           #55                 // class java/lang/StringBuilder
     249: dup
     250: invokespecial #56                 // Method java/lang/StringBuilder."<init>":()V
     253: ldc           #57                 // String Unable to construct signature Element
     255: invokevirtual #58                 // Method java/lang/StringBuilder.append:(Ljava/lang/String;)Ljava/lang/StringBuilder;
     258: aload_1
     259: invokeinterface #25,  1           // InterfaceMethod org/opensaml/xmlsec/signature/Signature.getElementQName:()Ljavax/xml/namespace/QName;
     264: invokevirtual #59                 // Method java/lang/StringBuilder.append:(Ljava/lang/Object;)Ljava/lang/StringBuilder;
     267: invokevirtual #60                 // Method java/lang/StringBuilder.toString:()Ljava/lang/String;
     270: astore        4
     272: aload_0
     273: getfield      #4                  // Field log:Lorg/slf4j/Logger;
     276: aload         4
     278: aload_3
     279: invokeinterface #61,  3           // InterfaceMethod org/slf4j/Logger.error:(Ljava/lang/String;Ljava/lang/Throwable;)V
     284: new           #14                 // class org/opensaml/core/xml/io/MarshallingException
     287: dup
     288: aload         4
     290: aload_3
     291: invokespecial #16                 // Method org/opensaml/core/xml/io/MarshallingException."<init>":(Ljava/lang/String;Ljava/lang/Exception;)V
     294: athrow
    Exception table:
       from    to  target type
          17   244   245   Class org/apache/xml/security/exceptions/XMLSecurityException
}
