Compiled from "TransformBuilder.java"
public class org.opensaml.xmlsec.signature.impl.TransformBuilder extends org.opensaml.core.xml.AbstractXMLObjectBuilder<org.opensaml.xmlsec.signature.Transform> implements org.opensaml.xmlsec.signature.XMLSignatureBuilder<org.opensaml.xmlsec.signature.Transform> {
  public org.opensaml.xmlsec.signature.impl.TransformBuilder();
    Code:
       0: aload_0
       1: invokespecial #1                  // Method org/opensaml/core/xml/AbstractXMLObjectBuilder."<init>":()V
       4: return

  public org.opensaml.xmlsec.signature.Transform buildObject(java.lang.String, java.lang.String, java.lang.String);
    Code:
       0: new           #2                  // class org/opensaml/xmlsec/signature/impl/TransformImpl
       3: dup
       4: aload_1
       5: aload_2
       6: aload_3
       7: invokespecial #3                  // Method org/opensaml/xmlsec/signature/impl/TransformImpl."<init>":(Ljava/lang/String;Ljava/lang/String;Ljava/lang/String;)V
      10: areturn

  public org.opensaml.xmlsec.signature.Transform buildObject();
    Code:
       0: aload_0
       1: ldc           #4                  // String http://www.w3.org/2000/09/xmldsig#
       3: ldc           #5                  // String Transform
       5: ldc           #6                  // String ds
       7: invokevirtual #7                  // Method buildObject:(Ljava/lang/String;Ljava/lang/String;Ljava/lang/String;)Lorg/opensaml/xmlsec/signature/Transform;
      10: areturn

  public org.opensaml.core.xml.XMLObject buildObject(java.lang.String, java.lang.String, java.lang.String);
    Code:
       0: aload_0
       1: aload_1
       2: aload_2
       3: aload_3
       4: invokevirtual #7                  // Method buildObject:(Ljava/lang/String;Ljava/lang/String;Ljava/lang/String;)Lorg/opensaml/xmlsec/signature/Transform;
       7: areturn

  public org.opensaml.core.xml.XMLObject buildObject();
    Code:
       0: aload_0
       1: invokevirtual #8                  // Method buildObject:()Lorg/opensaml/xmlsec/signature/Transform;
       4: areturn
}
