Compiled from "X509DigestMarshaller.java"
public class org.opensaml.xmlsec.signature.impl.X509DigestMarshaller extends org.opensaml.core.xml.schema.impl.XSBase64BinaryMarshaller {
  public org.opensaml.xmlsec.signature.impl.X509DigestMarshaller();
    Code:
       0: aload_0
       1: invokespecial #1                  // Method org/opensaml/core/xml/schema/impl/XSBase64BinaryMarshaller."<init>":()V
       4: return

  protected void marshallAttributes(org.opensaml.core.xml.XMLObject, org.w3c.dom.Element) throws org.opensaml.core.xml.io.MarshallingException;
    Code:
       0: aload_1
       1: checkcast     #2                  // class org/opensaml/xmlsec/signature/X509Digest
       4: astore_3
       5: aload_3
       6: invokeinterface #3,  1            // InterfaceMethod org/opensaml/xmlsec/signature/X509Digest.getAlgorithm:()Ljava/lang/String;
      11: ifnull        29
      14: aload_2
      15: aconst_null
      16: ldc           #4                  // String Algorithm
      18: aload_3
      19: invokeinterface #3,  1            // InterfaceMethod org/opensaml/xmlsec/signature/X509Digest.getAlgorithm:()Ljava/lang/String;
      24: invokeinterface #5,  4            // InterfaceMethod org/w3c/dom/Element.setAttributeNS:(Ljava/lang/String;Ljava/lang/String;Ljava/lang/String;)V
      29: return
}
