Compiled from "RolloverResponse.java"
public final class org.elasticsearch.client.indices.rollover.RolloverResponse extends org.elasticsearch.action.support.master.ShardsAcknowledgedResponse {
  private static final org.elasticsearch.common.ParseField NEW_INDEX;

  private static final org.elasticsearch.common.ParseField OLD_INDEX;

  private static final org.elasticsearch.common.ParseField DRY_RUN;

  private static final org.elasticsearch.common.ParseField ROLLED_OVER;

  private static final org.elasticsearch.common.ParseField CONDITIONS;

  private static final org.elasticsearch.common.xcontent.ConstructingObjectParser<org.elasticsearch.client.indices.rollover.RolloverResponse, java.lang.Void> PARSER;

  private final java.lang.String oldIndex;

  private final java.lang.String newIndex;

  private final java.util.Map<java.lang.String, java.lang.Boolean> conditionStatus;

  private final boolean dryRun;

  private final boolean rolledOver;

  public org.elasticsearch.client.indices.rollover.RolloverResponse(java.lang.String, java.lang.String, java.util.Map<java.lang.String, java.lang.Boolean>, boolean, boolean, boolean, boolean);
    Code:
       0: aload_0
       1: iload         6
       3: iload         7
       5: invokespecial #1                  // Method org/elasticsearch/action/support/master/ShardsAcknowledgedResponse."<init>":(ZZ)V
       8: aload_0
       9: aload_1
      10: putfield      #2                  // Field oldIndex:Ljava/lang/String;
      13: aload_0
      14: aload_2
      15: putfield      #3                  // Field newIndex:Ljava/lang/String;
      18: aload_0
      19: iload         4
      21: putfield      #4                  // Field dryRun:Z
      24: aload_0
      25: iload         5
      27: putfield      #5                  // Field rolledOver:Z
      30: aload_0
      31: aload_3
      32: putfield      #6                  // Field conditionStatus:Ljava/util/Map;
      35: return

  public java.lang.String getOldIndex();
    Code:
       0: aload_0
       1: getfield      #2                  // Field oldIndex:Ljava/lang/String;
       4: areturn

  public java.lang.String getNewIndex();
    Code:
       0: aload_0
       1: getfield      #3                  // Field newIndex:Ljava/lang/String;
       4: areturn

  public java.util.Map<java.lang.String, java.lang.Boolean> getConditionStatus();
    Code:
       0: aload_0
       1: getfield      #6                  // Field conditionStatus:Ljava/util/Map;
       4: areturn

  public boolean isDryRun();
    Code:
       0: aload_0
       1: getfield      #4                  // Field dryRun:Z
       4: ireturn

  public boolean isRolledOver();
    Code:
       0: aload_0
       1: getfield      #5                  // Field rolledOver:Z
       4: ireturn

  public static org.elasticsearch.client.indices.rollover.RolloverResponse fromXContent(org.elasticsearch.common.xcontent.XContentParser);
    Code:
       0: getstatic     #7                  // Field PARSER:Lorg/elasticsearch/common/xcontent/ConstructingObjectParser;
       3: aload_0
       4: aconst_null
       5: invokevirtual #8                  // Method org/elasticsearch/common/xcontent/ConstructingObjectParser.apply:(Lorg/elasticsearch/common/xcontent/XContentParser;Ljava/lang/Object;)Ljava/lang/Object;
       8: checkcast     #9                  // class org/elasticsearch/client/indices/rollover/RolloverResponse
      11: areturn

  public boolean equals(java.lang.Object);
    Code:
       0: aload_0
       1: aload_1
       2: invokespecial #10                 // Method org/elasticsearch/action/support/master/ShardsAcknowledgedResponse.equals:(Ljava/lang/Object;)Z
       5: ifeq          83
       8: aload_1
       9: checkcast     #9                  // class org/elasticsearch/client/indices/rollover/RolloverResponse
      12: astore_2
      13: aload_0
      14: getfield      #4                  // Field dryRun:Z
      17: aload_2
      18: getfield      #4                  // Field dryRun:Z
      21: if_icmpne     81
      24: aload_0
      25: getfield      #5                  // Field rolledOver:Z
      28: aload_2
      29: getfield      #5                  // Field rolledOver:Z
      32: if_icmpne     81
      35: aload_0
      36: getfield      #2                  // Field oldIndex:Ljava/lang/String;
      39: aload_2
      40: getfield      #2                  // Field oldIndex:Ljava/lang/String;
      43: invokestatic  #11                 // Method java/util/Objects.equals:(Ljava/lang/Object;Ljava/lang/Object;)Z
      46: ifeq          81
      49: aload_0
      50: getfield      #3                  // Field newIndex:Ljava/lang/String;
      53: aload_2
      54: getfield      #3                  // Field newIndex:Ljava/lang/String;
      57: invokestatic  #11                 // Method java/util/Objects.equals:(Ljava/lang/Object;Ljava/lang/Object;)Z
      60: ifeq          81
      63: aload_0
      64: getfield      #6                  // Field conditionStatus:Ljava/util/Map;
      67: aload_2
      68: getfield      #6                  // Field conditionStatus:Ljava/util/Map;
      71: invokestatic  #11                 // Method java/util/Objects.equals:(Ljava/lang/Object;Ljava/lang/Object;)Z
      74: ifeq          81
      77: iconst_1
      78: goto          82
      81: iconst_0
      82: ireturn
      83: iconst_0
      84: ireturn

  public int hashCode();
    Code:
       0: bipush        6
       2: anewarray     #12                 // class java/lang/Object
       5: dup
       6: iconst_0
       7: aload_0
       8: invokespecial #13                 // Method org/elasticsearch/action/support/master/ShardsAcknowledgedResponse.hashCode:()I
      11: invokestatic  #14                 // Method java/lang/Integer.valueOf:(I)Ljava/lang/Integer;
      14: aastore
      15: dup
      16: iconst_1
      17: aload_0
      18: getfield      #2                  // Field oldIndex:Ljava/lang/String;
      21: aastore
      22: dup
      23: iconst_2
      24: aload_0
      25: getfield      #3                  // Field newIndex:Ljava/lang/String;
      28: aastore
      29: dup
      30: iconst_3
      31: aload_0
      32: getfield      #6                  // Field conditionStatus:Ljava/util/Map;
      35: aastore
      36: dup
      37: iconst_4
      38: aload_0
      39: getfield      #4                  // Field dryRun:Z
      42: invokestatic  #15                 // Method java/lang/Boolean.valueOf:(Z)Ljava/lang/Boolean;
      45: aastore
      46: dup
      47: iconst_5
      48: aload_0
      49: getfield      #5                  // Field rolledOver:Z
      52: invokestatic  #15                 // Method java/lang/Boolean.valueOf:(Z)Ljava/lang/Boolean;
      55: aastore
      56: invokestatic  #16                 // Method java/util/Objects.hash:([Ljava/lang/Object;)I
      59: ireturn

  private static java.util.Map lambda$static$1(org.elasticsearch.common.xcontent.XContentParser, java.lang.Void) throws java.io.IOException;
    Code:
       0: aload_0
       1: invokeinterface #17,  1           // InterfaceMethod org/elasticsearch/common/xcontent/XContentParser.map:()Ljava/util/Map;
       6: areturn

  private static org.elasticsearch.client.indices.rollover.RolloverResponse lambda$static$0(java.lang.Object[]);
    Code:
       0: new           #9                  // class org/elasticsearch/client/indices/rollover/RolloverResponse
       3: dup
       4: aload_0
       5: iconst_0
       6: aaload
       7: checkcast     #18                 // class java/lang/String
      10: aload_0
      11: iconst_1
      12: aaload
      13: checkcast     #18                 // class java/lang/String
      16: aload_0
      17: iconst_2
      18: aaload
      19: checkcast     #19                 // class java/util/Map
      22: aload_0
      23: iconst_3
      24: aaload
      25: checkcast     #20                 // class java/lang/Boolean
      28: invokevirtual #21                 // Method java/lang/Boolean.booleanValue:()Z
      31: aload_0
      32: iconst_4
      33: aaload
      34: checkcast     #20                 // class java/lang/Boolean
      37: invokevirtual #21                 // Method java/lang/Boolean.booleanValue:()Z
      40: aload_0
      41: iconst_5
      42: aaload
      43: checkcast     #20                 // class java/lang/Boolean
      46: invokevirtual #21                 // Method java/lang/Boolean.booleanValue:()Z
      49: aload_0
      50: bipush        6
      52: aaload
      53: checkcast     #20                 // class java/lang/Boolean
      56: invokevirtual #21                 // Method java/lang/Boolean.booleanValue:()Z
      59: invokespecial #22                 // Method "<init>":(Ljava/lang/String;Ljava/lang/String;Ljava/util/Map;ZZZZ)V
      62: areturn

  static {};
    Code:
       0: new           #23                 // class org/elasticsearch/common/ParseField
       3: dup
       4: ldc           #24                 // String new_index
       6: iconst_0
       7: anewarray     #18                 // class java/lang/String
      10: invokespecial #25                 // Method org/elasticsearch/common/ParseField."<init>":(Ljava/lang/String;[Ljava/lang/String;)V
      13: putstatic     #26                 // Field NEW_INDEX:Lorg/elasticsearch/common/ParseField;
      16: new           #23                 // class org/elasticsearch/common/ParseField
      19: dup
      20: ldc           #27                 // String old_index
      22: iconst_0
      23: anewarray     #18                 // class java/lang/String
      26: invokespecial #25                 // Method org/elasticsearch/common/ParseField."<init>":(Ljava/lang/String;[Ljava/lang/String;)V
      29: putstatic     #28                 // Field OLD_INDEX:Lorg/elasticsearch/common/ParseField;
      32: new           #23                 // class org/elasticsearch/common/ParseField
      35: dup
      36: ldc           #29                 // String dry_run
      38: iconst_0
      39: anewarray     #18                 // class java/lang/String
      42: invokespecial #25                 // Method org/elasticsearch/common/ParseField."<init>":(Ljava/lang/String;[Ljava/lang/String;)V
      45: putstatic     #30                 // Field DRY_RUN:Lorg/elasticsearch/common/ParseField;
      48: new           #23                 // class org/elasticsearch/common/ParseField
      51: dup
      52: ldc           #31                 // String rolled_over
      54: iconst_0
      55: anewarray     #18                 // class java/lang/String
      58: invokespecial #25                 // Method org/elasticsearch/common/ParseField."<init>":(Ljava/lang/String;[Ljava/lang/String;)V
      61: putstatic     #32                 // Field ROLLED_OVER:Lorg/elasticsearch/common/ParseField;
      64: new           #23                 // class org/elasticsearch/common/ParseField
      67: dup
      68: ldc           #33                 // String conditions
      70: iconst_0
      71: anewarray     #18                 // class java/lang/String
      74: invokespecial #25                 // Method org/elasticsearch/common/ParseField."<init>":(Ljava/lang/String;[Ljava/lang/String;)V
      77: putstatic     #34                 // Field CONDITIONS:Lorg/elasticsearch/common/ParseField;
      80: new           #35                 // class org/elasticsearch/common/xcontent/ConstructingObjectParser
      83: dup
      84: ldc           #36                 // String rollover
      86: iconst_1
      87: invokedynamic #37,  0             // InvokeDynamic #0:apply:()Ljava/util/function/Function;
      92: invokespecial #38                 // Method org/elasticsearch/common/xcontent/ConstructingObjectParser."<init>":(Ljava/lang/String;ZLjava/util/function/Function;)V
      95: putstatic     #7                  // Field PARSER:Lorg/elasticsearch/common/xcontent/ConstructingObjectParser;
      98: getstatic     #7                  // Field PARSER:Lorg/elasticsearch/common/xcontent/ConstructingObjectParser;
     101: invokestatic  #39                 // Method org/elasticsearch/common/xcontent/ConstructingObjectParser.constructorArg:()Ljava/util/function/BiConsumer;
     104: getstatic     #28                 // Field OLD_INDEX:Lorg/elasticsearch/common/ParseField;
     107: invokevirtual #40                 // Method org/elasticsearch/common/xcontent/ConstructingObjectParser.declareString:(Ljava/util/function/BiConsumer;Lorg/elasticsearch/common/ParseField;)V
     110: getstatic     #7                  // Field PARSER:Lorg/elasticsearch/common/xcontent/ConstructingObjectParser;
     113: invokestatic  #39                 // Method org/elasticsearch/common/xcontent/ConstructingObjectParser.constructorArg:()Ljava/util/function/BiConsumer;
     116: getstatic     #26                 // Field NEW_INDEX:Lorg/elasticsearch/common/ParseField;
     119: invokevirtual #40                 // Method org/elasticsearch/common/xcontent/ConstructingObjectParser.declareString:(Ljava/util/function/BiConsumer;Lorg/elasticsearch/common/ParseField;)V
     122: getstatic     #7                  // Field PARSER:Lorg/elasticsearch/common/xcontent/ConstructingObjectParser;
     125: invokestatic  #39                 // Method org/elasticsearch/common/xcontent/ConstructingObjectParser.constructorArg:()Ljava/util/function/BiConsumer;
     128: invokedynamic #41,  0             // InvokeDynamic #1:parse:()Lorg/elasticsearch/common/xcontent/ContextParser;
     133: getstatic     #34                 // Field CONDITIONS:Lorg/elasticsearch/common/ParseField;
     136: invokevirtual #42                 // Method org/elasticsearch/common/xcontent/ConstructingObjectParser.declareObject:(Ljava/util/function/BiConsumer;Lorg/elasticsearch/common/xcontent/ContextParser;Lorg/elasticsearch/common/ParseField;)V
     139: getstatic     #7                  // Field PARSER:Lorg/elasticsearch/common/xcontent/ConstructingObjectParser;
     142: invokestatic  #39                 // Method org/elasticsearch/common/xcontent/ConstructingObjectParser.constructorArg:()Ljava/util/function/BiConsumer;
     145: getstatic     #30                 // Field DRY_RUN:Lorg/elasticsearch/common/ParseField;
     148: invokevirtual #43                 // Method org/elasticsearch/common/xcontent/ConstructingObjectParser.declareBoolean:(Ljava/util/function/BiConsumer;Lorg/elasticsearch/common/ParseField;)V
     151: getstatic     #7                  // Field PARSER:Lorg/elasticsearch/common/xcontent/ConstructingObjectParser;
     154: invokestatic  #39                 // Method org/elasticsearch/common/xcontent/ConstructingObjectParser.constructorArg:()Ljava/util/function/BiConsumer;
     157: getstatic     #32                 // Field ROLLED_OVER:Lorg/elasticsearch/common/ParseField;
     160: invokevirtual #43                 // Method org/elasticsearch/common/xcontent/ConstructingObjectParser.declareBoolean:(Ljava/util/function/BiConsumer;Lorg/elasticsearch/common/ParseField;)V
     163: getstatic     #7                  // Field PARSER:Lorg/elasticsearch/common/xcontent/ConstructingObjectParser;
     166: invokestatic  #44                 // Method declareAcknowledgedAndShardsAcknowledgedFields:(Lorg/elasticsearch/common/xcontent/ConstructingObjectParser;)V
     169: return
}
