Compiled from "RequestPartServletServerHttpRequest.java"
public class org.springframework.web.multipart.support.RequestPartServletServerHttpRequest extends org.springframework.http.server.ServletServerHttpRequest {
  private final org.springframework.web.multipart.MultipartHttpServletRequest multipartRequest;

  private final java.lang.String partName;

  private final org.springframework.http.HttpHeaders headers;

  public org.springframework.web.multipart.support.RequestPartServletServerHttpRequest(javax.servlet.http.HttpServletRequest, java.lang.String) throws org.springframework.web.multipart.support.MissingServletRequestPartException;
    Code:
       0: aload_0
       1: aload_1
       2: invokespecial #1                  // Method org/springframework/http/server/ServletServerHttpRequest."<init>":(Ljavax/servlet/http/HttpServletRequest;)V
       5: aload_0
       6: aload_1
       7: invokestatic  #2                  // Method asMultipartRequest:(Ljavax/servlet/http/HttpServletRequest;)Lorg/springframework/web/multipart/MultipartHttpServletRequest;
      10: putfield      #3                  // Field multipartRequest:Lorg/springframework/web/multipart/MultipartHttpServletRequest;
      13: aload_0
      14: aload_2
      15: putfield      #4                  // Field partName:Ljava/lang/String;
      18: aload_0
      19: aload_0
      20: getfield      #3                  // Field multipartRequest:Lorg/springframework/web/multipart/MultipartHttpServletRequest;
      23: aload_0
      24: getfield      #4                  // Field partName:Ljava/lang/String;
      27: invokeinterface #5,  2            // InterfaceMethod org/springframework/web/multipart/MultipartHttpServletRequest.getMultipartHeaders:(Ljava/lang/String;)Lorg/springframework/http/HttpHeaders;
      32: putfield      #6                  // Field headers:Lorg/springframework/http/HttpHeaders;
      35: aload_0
      36: getfield      #6                  // Field headers:Lorg/springframework/http/HttpHeaders;
      39: ifnonnull     100
      42: aload_1
      43: instanceof    #7                  // class org/springframework/web/multipart/MultipartHttpServletRequest
      46: ifeq          58
      49: new           #8                  // class org/springframework/web/multipart/support/MissingServletRequestPartException
      52: dup
      53: aload_2
      54: invokespecial #9                  // Method org/springframework/web/multipart/support/MissingServletRequestPartException."<init>":(Ljava/lang/String;)V
      57: athrow
      58: new           #10                 // class java/lang/IllegalArgumentException
      61: dup
      62: new           #11                 // class java/lang/StringBuilder
      65: dup
      66: invokespecial #12                 // Method java/lang/StringBuilder."<init>":()V
      69: ldc           #13                 // String Failed to obtain request part:
      71: invokevirtual #14                 // Method java/lang/StringBuilder.append:(Ljava/lang/String;)Ljava/lang/StringBuilder;
      74: aload_2
      75: invokevirtual #14                 // Method java/lang/StringBuilder.append:(Ljava/lang/String;)Ljava/lang/StringBuilder;
      78: ldc           #15                 // String .
      80: invokevirtual #14                 // Method java/lang/StringBuilder.append:(Ljava/lang/String;)Ljava/lang/StringBuilder;
      83: ldc           #16                 // String The part is missing or multipart processing is not configured.
      85: invokevirtual #14                 // Method java/lang/StringBuilder.append:(Ljava/lang/String;)Ljava/lang/StringBuilder;
      88: ldc           #17                 // String Check for a MultipartResolver bean or if Servlet 3.0 multipart processing is enabled.
      90: invokevirtual #14                 // Method java/lang/StringBuilder.append:(Ljava/lang/String;)Ljava/lang/StringBuilder;
      93: invokevirtual #18                 // Method java/lang/StringBuilder.toString:()Ljava/lang/String;
      96: invokespecial #19                 // Method java/lang/IllegalArgumentException."<init>":(Ljava/lang/String;)V
      99: athrow
     100: return

  private static org.springframework.web.multipart.MultipartHttpServletRequest asMultipartRequest(javax.servlet.http.HttpServletRequest);
    Code:
       0: aload_0
       1: instanceof    #7                  // class org/springframework/web/multipart/MultipartHttpServletRequest
       4: ifeq          12
       7: aload_0
       8: checkcast     #7                  // class org/springframework/web/multipart/MultipartHttpServletRequest
      11: areturn
      12: ldc           #20                 // class javax/servlet/http/HttpServletRequest
      14: ldc           #21                 // String getParts
      16: iconst_0
      17: anewarray     #22                 // class java/lang/Class
      20: invokestatic  #23                 // Method org/springframework/util/ClassUtils.hasMethod:(Ljava/lang/Class;Ljava/lang/String;[Ljava/lang/Class;)Z
      23: ifeq          35
      26: new           #24                 // class org/springframework/web/multipart/support/StandardMultipartHttpServletRequest
      29: dup
      30: aload_0
      31: invokespecial #25                 // Method org/springframework/web/multipart/support/StandardMultipartHttpServletRequest."<init>":(Ljavax/servlet/http/HttpServletRequest;)V
      34: areturn
      35: new           #10                 // class java/lang/IllegalArgumentException
      38: dup
      39: ldc           #26                 // String Expected MultipartHttpServletRequest: is a MultipartResolver configured?
      41: invokespecial #19                 // Method java/lang/IllegalArgumentException."<init>":(Ljava/lang/String;)V
      44: athrow

  public org.springframework.http.HttpHeaders getHeaders();
    Code:
       0: aload_0
       1: getfield      #6                  // Field headers:Lorg/springframework/http/HttpHeaders;
       4: areturn

  public java.io.InputStream getBody() throws java.io.IOException;
    Code:
       0: aload_0
       1: getfield      #3                  // Field multipartRequest:Lorg/springframework/web/multipart/MultipartHttpServletRequest;
       4: instanceof    #24                 // class org/springframework/web/multipart/support/StandardMultipartHttpServletRequest
       7: ifeq          41
      10: aload_0
      11: getfield      #3                  // Field multipartRequest:Lorg/springframework/web/multipart/MultipartHttpServletRequest;
      14: aload_0
      15: getfield      #4                  // Field partName:Ljava/lang/String;
      18: invokeinterface #27,  2           // InterfaceMethod org/springframework/web/multipart/MultipartHttpServletRequest.getPart:(Ljava/lang/String;)Ljavax/servlet/http/Part;
      23: invokeinterface #28,  1           // InterfaceMethod javax/servlet/http/Part.getInputStream:()Ljava/io/InputStream;
      28: areturn
      29: astore_1
      30: new           #30                 // class org/springframework/web/multipart/MultipartException
      33: dup
      34: ldc           #31                 // String Could not parse multipart servlet request
      36: aload_1
      37: invokespecial #32                 // Method org/springframework/web/multipart/MultipartException."<init>":(Ljava/lang/String;Ljava/lang/Throwable;)V
      40: athrow
      41: aload_0
      42: getfield      #3                  // Field multipartRequest:Lorg/springframework/web/multipart/MultipartHttpServletRequest;
      45: aload_0
      46: getfield      #4                  // Field partName:Ljava/lang/String;
      49: invokeinterface #33,  2           // InterfaceMethod org/springframework/web/multipart/MultipartHttpServletRequest.getFile:(Ljava/lang/String;)Lorg/springframework/web/multipart/MultipartFile;
      54: astore_1
      55: aload_1
      56: ifnull        66
      59: aload_1
      60: invokeinterface #34,  1           // InterfaceMethod org/springframework/web/multipart/MultipartFile.getInputStream:()Ljava/io/InputStream;
      65: areturn
      66: aload_0
      67: getfield      #3                  // Field multipartRequest:Lorg/springframework/web/multipart/MultipartHttpServletRequest;
      70: aload_0
      71: getfield      #4                  // Field partName:Ljava/lang/String;
      74: invokeinterface #35,  2           // InterfaceMethod org/springframework/web/multipart/MultipartHttpServletRequest.getParameter:(Ljava/lang/String;)Ljava/lang/String;
      79: astore_2
      80: new           #36                 // class java/io/ByteArrayInputStream
      83: dup
      84: aload_2
      85: ldc           #38                 // String UTF-8
      87: invokevirtual #39                 // Method java/lang/String.getBytes:(Ljava/lang/String;)[B
      90: invokespecial #40                 // Method java/io/ByteArrayInputStream."<init>":([B)V
      93: areturn
    Exception table:
       from    to  target type
          10    28    29   Class java/lang/Exception
}
