Compiled from "AzureAdUserRoleResolverTest.java"
public class no.nav.common.auth.oidc.filter.AzureAdUserRoleResolverTest {
  public no.nav.common.auth.oidc.filter.AzureAdUserRoleResolverTest();
    Code:
       0: aload_0
       1: invokespecial #1                  // Method java/lang/Object."<init>":()V
       4: return

  public void resolve_subEqualsOid_returnsSystemUser();
    Code:
       0: new           #2                  // class no/nav/common/auth/oidc/filter/AzureAdUserRoleResolver
       3: dup
       4: invokespecial #3                  // Method no/nav/common/auth/oidc/filter/AzureAdUserRoleResolver."<init>":()V
       7: astore_1
       8: new           #4                  // class com/nimbusds/jwt/JWTClaimsSet$Builder
      11: dup
      12: invokespecial #5                  // Method com/nimbusds/jwt/JWTClaimsSet$Builder."<init>":()V
      15: ldc           #6                  // String sub
      17: new           #7                  // class java/lang/String
      20: dup
      21: ldc           #8                  // String test
      23: invokespecial #9                  // Method java/lang/String."<init>":(Ljava/lang/String;)V
      26: invokevirtual #10                 // Method com/nimbusds/jwt/JWTClaimsSet$Builder.claim:(Ljava/lang/String;Ljava/lang/Object;)Lcom/nimbusds/jwt/JWTClaimsSet$Builder;
      29: ldc           #11                 // String oid
      31: ldc           #8                  // String test
      33: invokevirtual #10                 // Method com/nimbusds/jwt/JWTClaimsSet$Builder.claim:(Ljava/lang/String;Ljava/lang/Object;)Lcom/nimbusds/jwt/JWTClaimsSet$Builder;
      36: invokevirtual #12                 // Method com/nimbusds/jwt/JWTClaimsSet$Builder.build:()Lcom/nimbusds/jwt/JWTClaimsSet;
      39: astore_2
      40: getstatic     #13                 // Field no/nav/common/auth/context/UserRole.SYSTEM:Lno/nav/common/auth/context/UserRole;
      43: aload_1
      44: aload_2
      45: invokevirtual #14                 // Method no/nav/common/auth/oidc/filter/AzureAdUserRoleResolver.resolve:(Lcom/nimbusds/jwt/JWTClaimsSet;)Lno/nav/common/auth/context/UserRole;
      48: invokestatic  #15                 // Method org/junit/Assert.assertEquals:(Ljava/lang/Object;Ljava/lang/Object;)V
      51: return

  public void resolve_subNotEqualsOid_returnsInternUser();
    Code:
       0: new           #2                  // class no/nav/common/auth/oidc/filter/AzureAdUserRoleResolver
       3: dup
       4: invokespecial #3                  // Method no/nav/common/auth/oidc/filter/AzureAdUserRoleResolver."<init>":()V
       7: astore_1
       8: new           #4                  // class com/nimbusds/jwt/JWTClaimsSet$Builder
      11: dup
      12: invokespecial #5                  // Method com/nimbusds/jwt/JWTClaimsSet$Builder."<init>":()V
      15: ldc           #6                  // String sub
      17: ldc           #8                  // String test
      19: invokevirtual #10                 // Method com/nimbusds/jwt/JWTClaimsSet$Builder.claim:(Ljava/lang/String;Ljava/lang/Object;)Lcom/nimbusds/jwt/JWTClaimsSet$Builder;
      22: ldc           #11                 // String oid
      24: ldc           #16                 // String test2
      26: invokevirtual #10                 // Method com/nimbusds/jwt/JWTClaimsSet$Builder.claim:(Ljava/lang/String;Ljava/lang/Object;)Lcom/nimbusds/jwt/JWTClaimsSet$Builder;
      29: invokevirtual #12                 // Method com/nimbusds/jwt/JWTClaimsSet$Builder.build:()Lcom/nimbusds/jwt/JWTClaimsSet;
      32: astore_2
      33: getstatic     #17                 // Field no/nav/common/auth/context/UserRole.INTERN:Lno/nav/common/auth/context/UserRole;
      36: aload_1
      37: aload_2
      38: invokevirtual #14                 // Method no/nav/common/auth/oidc/filter/AzureAdUserRoleResolver.resolve:(Lcom/nimbusds/jwt/JWTClaimsSet;)Lno/nav/common/auth/context/UserRole;
      41: invokestatic  #15                 // Method org/junit/Assert.assertEquals:(Ljava/lang/Object;Ljava/lang/Object;)V
      44: return

  public void resolve_subIsNull_throwsException();
    Code:
       0: new           #2                  // class no/nav/common/auth/oidc/filter/AzureAdUserRoleResolver
       3: dup
       4: invokespecial #3                  // Method no/nav/common/auth/oidc/filter/AzureAdUserRoleResolver."<init>":()V
       7: astore_1
       8: new           #4                  // class com/nimbusds/jwt/JWTClaimsSet$Builder
      11: dup
      12: invokespecial #5                  // Method com/nimbusds/jwt/JWTClaimsSet$Builder."<init>":()V
      15: ldc           #6                  // String sub
      17: aconst_null
      18: invokevirtual #10                 // Method com/nimbusds/jwt/JWTClaimsSet$Builder.claim:(Ljava/lang/String;Ljava/lang/Object;)Lcom/nimbusds/jwt/JWTClaimsSet$Builder;
      21: ldc           #11                 // String oid
      23: ldc           #8                  // String test
      25: invokevirtual #10                 // Method com/nimbusds/jwt/JWTClaimsSet$Builder.claim:(Ljava/lang/String;Ljava/lang/Object;)Lcom/nimbusds/jwt/JWTClaimsSet$Builder;
      28: invokevirtual #12                 // Method com/nimbusds/jwt/JWTClaimsSet$Builder.build:()Lcom/nimbusds/jwt/JWTClaimsSet;
      31: astore_2
      32: ldc           #18                 // class java/lang/IllegalArgumentException
      34: aload_1
      35: aload_2
      36: invokedynamic #19,  0             // InvokeDynamic #0:run:(Lno/nav/common/auth/oidc/filter/AzureAdUserRoleResolver;Lcom/nimbusds/jwt/JWTClaimsSet;)Lorg/junit/function/ThrowingRunnable;
      41: invokestatic  #20                 // Method org/junit/Assert.assertThrows:(Ljava/lang/Class;Lorg/junit/function/ThrowingRunnable;)Ljava/lang/Throwable;
      44: pop
      45: return

  public void resolve_subIsUndefined_throwsException();
    Code:
       0: new           #2                  // class no/nav/common/auth/oidc/filter/AzureAdUserRoleResolver
       3: dup
       4: invokespecial #3                  // Method no/nav/common/auth/oidc/filter/AzureAdUserRoleResolver."<init>":()V
       7: astore_1
       8: new           #4                  // class com/nimbusds/jwt/JWTClaimsSet$Builder
      11: dup
      12: invokespecial #5                  // Method com/nimbusds/jwt/JWTClaimsSet$Builder."<init>":()V
      15: ldc           #11                 // String oid
      17: ldc           #8                  // String test
      19: invokevirtual #10                 // Method com/nimbusds/jwt/JWTClaimsSet$Builder.claim:(Ljava/lang/String;Ljava/lang/Object;)Lcom/nimbusds/jwt/JWTClaimsSet$Builder;
      22: invokevirtual #12                 // Method com/nimbusds/jwt/JWTClaimsSet$Builder.build:()Lcom/nimbusds/jwt/JWTClaimsSet;
      25: astore_2
      26: ldc           #18                 // class java/lang/IllegalArgumentException
      28: aload_1
      29: aload_2
      30: invokedynamic #21,  0             // InvokeDynamic #1:run:(Lno/nav/common/auth/oidc/filter/AzureAdUserRoleResolver;Lcom/nimbusds/jwt/JWTClaimsSet;)Lorg/junit/function/ThrowingRunnable;
      35: invokestatic  #20                 // Method org/junit/Assert.assertThrows:(Ljava/lang/Class;Lorg/junit/function/ThrowingRunnable;)Ljava/lang/Throwable;
      38: pop
      39: return

  private static void lambda$resolve_subIsUndefined_throwsException$1(no.nav.common.auth.oidc.filter.AzureAdUserRoleResolver, com.nimbusds.jwt.JWTClaimsSet) throws java.lang.Throwable;
    Code:
       0: aload_0
       1: aload_1
       2: invokevirtual #14                 // Method no/nav/common/auth/oidc/filter/AzureAdUserRoleResolver.resolve:(Lcom/nimbusds/jwt/JWTClaimsSet;)Lno/nav/common/auth/context/UserRole;
       5: pop
       6: return

  private static void lambda$resolve_subIsNull_throwsException$0(no.nav.common.auth.oidc.filter.AzureAdUserRoleResolver, com.nimbusds.jwt.JWTClaimsSet) throws java.lang.Throwable;
    Code:
       0: aload_0
       1: aload_1
       2: invokevirtual #14                 // Method no/nav/common/auth/oidc/filter/AzureAdUserRoleResolver.resolve:(Lcom/nimbusds/jwt/JWTClaimsSet;)Lno/nav/common/auth/context/UserRole;
       5: pop
       6: return
}
