Compiled from "JDOMResult.java"
class org.jdom.transform.JDOMResult$FragmentHandler extends org.jdom.input.SAXHandler {
  private org.jdom.Element dummyRoot;

  public org.jdom.transform.JDOMResult$FragmentHandler(org.jdom.JDOMFactory);
    Code:
       0: aload_0
       1: aload_1
       2: invokespecial #1                  // Method org/jdom/input/SAXHandler."<init>":(Lorg/jdom/JDOMFactory;)V
       5: aload_0
       6: new           #2                  // class org/jdom/Element
       9: dup
      10: ldc           #3                  // String root
      12: aconst_null
      13: aconst_null
      14: invokespecial #4                  // Method org/jdom/Element."<init>":(Ljava/lang/String;Ljava/lang/String;Ljava/lang/String;)V
      17: putfield      #5                  // Field dummyRoot:Lorg/jdom/Element;
      20: aload_0
      21: aload_0
      22: getfield      #5                  // Field dummyRoot:Lorg/jdom/Element;
      25: invokevirtual #6                  // Method pushElement:(Lorg/jdom/Element;)V
      28: return

  public java.util.List getResult();
    Code:
       0: aload_0
       1: invokevirtual #7                  // Method flushCharacters:()V
       4: goto          8
       7: astore_1
       8: aload_0
       9: aload_0
      10: getfield      #5                  // Field dummyRoot:Lorg/jdom/Element;
      13: invokespecial #9                  // Method getDetachedContent:(Lorg/jdom/Element;)Ljava/util/List;
      16: areturn
    Exception table:
       from    to  target type
           0     4     7   Class org/xml/sax/SAXException

  private java.util.List getDetachedContent(org.jdom.Element);
    Code:
       0: aload_1
       1: invokevirtual #10                 // Method org/jdom/Element.getContent:()Ljava/util/List;
       4: astore_2
       5: new           #11                 // class java/util/ArrayList
       8: dup
       9: aload_2
      10: invokeinterface #12,  1           // InterfaceMethod java/util/List.size:()I
      15: invokespecial #13                 // Method java/util/ArrayList."<init>":(I)V
      18: astore_3
      19: aload_2
      20: invokeinterface #12,  1           // InterfaceMethod java/util/List.size:()I
      25: ifeq          49
      28: aload_2
      29: iconst_0
      30: invokeinterface #14,  2           // InterfaceMethod java/util/List.remove:(I)Ljava/lang/Object;
      35: astore        4
      37: aload_3
      38: aload         4
      40: invokeinterface #15,  2           // InterfaceMethod java/util/List.add:(Ljava/lang/Object;)Z
      45: pop
      46: goto          19
      49: aload_3
      50: areturn
}
