Compiled from "AtmosphereFramework.java"
class org.atmosphere.cpr.AtmosphereFramework$InterceptorComparator implements java.util.Comparator<org.atmosphere.cpr.AtmosphereInterceptor> {
  private org.atmosphere.cpr.AtmosphereFramework$InterceptorComparator();
    Code:
       0: aload_0
       1: invokespecial #2                  // Method java/lang/Object."<init>":()V
       4: return

  public int compare(org.atmosphere.cpr.AtmosphereInterceptor, org.atmosphere.cpr.AtmosphereInterceptor);
    Code:
       0: aload_1
       1: instanceof    #3                  // class org/atmosphere/interceptor/InvokationOrder
       4: ifeq          20
       7: aload_1
       8: checkcast     #3                  // class org/atmosphere/interceptor/InvokationOrder
      11: invokeinterface #4,  1            // InterfaceMethod org/atmosphere/interceptor/InvokationOrder.priority:()Lorg/atmosphere/interceptor/InvokationOrder$PRIORITY;
      16: astore_3
      17: goto          24
      20: getstatic     #5                  // Field org/atmosphere/interceptor/InvokationOrder$PRIORITY.AFTER_DEFAULT:Lorg/atmosphere/interceptor/InvokationOrder$PRIORITY;
      23: astore_3
      24: aload_2
      25: instanceof    #3                  // class org/atmosphere/interceptor/InvokationOrder
      28: ifeq          45
      31: aload_2
      32: checkcast     #3                  // class org/atmosphere/interceptor/InvokationOrder
      35: invokeinterface #4,  1            // InterfaceMethod org/atmosphere/interceptor/InvokationOrder.priority:()Lorg/atmosphere/interceptor/InvokationOrder$PRIORITY;
      40: astore        4
      42: goto          50
      45: getstatic     #5                  // Field org/atmosphere/interceptor/InvokationOrder$PRIORITY.AFTER_DEFAULT:Lorg/atmosphere/interceptor/InvokationOrder$PRIORITY;
      48: astore        4
      50: iconst_0
      51: istore        5
      53: getstatic     #6                  // Field org/atmosphere/cpr/AtmosphereFramework$8.$SwitchMap$org$atmosphere$interceptor$InvokationOrder$PRIORITY:[I
      56: aload_3
      57: invokevirtual #7                  // Method org/atmosphere/interceptor/InvokationOrder$PRIORITY.ordinal:()I
      60: iaload
      61: tableswitch   { // 1 to 3
                     1: 130
                     2: 176
                     3: 88
               default: 215
          }
      88: getstatic     #6                  // Field org/atmosphere/cpr/AtmosphereFramework$8.$SwitchMap$org$atmosphere$interceptor$InvokationOrder$PRIORITY:[I
      91: aload         4
      93: invokevirtual #7                  // Method org/atmosphere/interceptor/InvokationOrder$PRIORITY.ordinal:()I
      96: iaload
      97: lookupswitch  { // 2
                     1: 124
                     2: 124
               default: 127
          }
     124: iconst_1
     125: istore        5
     127: goto          215
     130: getstatic     #6                  // Field org/atmosphere/cpr/AtmosphereFramework$8.$SwitchMap$org$atmosphere$interceptor$InvokationOrder$PRIORITY:[I
     133: aload         4
     135: invokevirtual #7                  // Method org/atmosphere/interceptor/InvokationOrder$PRIORITY.ordinal:()I
     138: iaload
     139: lookupswitch  { // 2
                     2: 170
                     3: 164
               default: 173
          }
     164: iconst_m1
     165: istore        5
     167: goto          173
     170: iconst_1
     171: istore        5
     173: goto          215
     176: getstatic     #6                  // Field org/atmosphere/cpr/AtmosphereFramework$8.$SwitchMap$org$atmosphere$interceptor$InvokationOrder$PRIORITY:[I
     179: aload         4
     181: invokevirtual #7                  // Method org/atmosphere/interceptor/InvokationOrder$PRIORITY.ordinal:()I
     184: iaload
     185: lookupswitch  { // 2
                     1: 212
                     3: 212
               default: 215
          }
     212: iconst_m1
     213: istore        5
     215: iload         5
     217: ireturn

  public int compare(java.lang.Object, java.lang.Object);
    Code:
       0: aload_0
       1: aload_1
       2: checkcast     #8                  // class org/atmosphere/cpr/AtmosphereInterceptor
       5: aload_2
       6: checkcast     #8                  // class org/atmosphere/cpr/AtmosphereInterceptor
       9: invokevirtual #9                  // Method compare:(Lorg/atmosphere/cpr/AtmosphereInterceptor;Lorg/atmosphere/cpr/AtmosphereInterceptor;)I
      12: ireturn

  org.atmosphere.cpr.AtmosphereFramework$InterceptorComparator(org.atmosphere.cpr.AtmosphereFramework$1);
    Code:
       0: aload_0
       1: invokespecial #1                  // Method "<init>":()V
       4: return
}
