Compiled from "ContainerInitializer.java"
class org.atmosphere.cpr.ContainerInitializer$1 implements javax.servlet.ServletRequestListener {
  final org.atmosphere.cpr.AtmosphereFramework val$framework;

  final org.atmosphere.cpr.ContainerInitializer this$0;

  org.atmosphere.cpr.ContainerInitializer$1(org.atmosphere.cpr.ContainerInitializer, org.atmosphere.cpr.AtmosphereFramework);
    Code:
       0: aload_0
       1: aload_1
       2: putfield      #1                  // Field this$0:Lorg/atmosphere/cpr/ContainerInitializer;
       5: aload_0
       6: aload_2
       7: putfield      #2                  // Field val$framework:Lorg/atmosphere/cpr/AtmosphereFramework;
      10: aload_0
      11: invokespecial #3                  // Method java/lang/Object."<init>":()V
      14: return

  public void requestDestroyed(javax.servlet.ServletRequestEvent);
    Code:
       0: return

  public void requestInitialized(javax.servlet.ServletRequestEvent);
    Code:
       0: ldc           #4                  // class javax/servlet/http/HttpServletRequest
       2: aload_1
       3: invokevirtual #5                  // Method javax/servlet/ServletRequestEvent.getServletRequest:()Ljavax/servlet/ServletRequest;
       6: invokevirtual #6                  // Method java/lang/Class.cast:(Ljava/lang/Object;)Ljava/lang/Object;
       9: checkcast     #4                  // class javax/servlet/http/HttpServletRequest
      12: astore_2
      13: aload_0
      14: getfield      #2                  // Field val$framework:Lorg/atmosphere/cpr/AtmosphereFramework;
      17: invokevirtual #7                  // Method org/atmosphere/cpr/AtmosphereFramework.getAtmosphereConfig:()Lorg/atmosphere/cpr/AtmosphereConfig;
      20: astore_3
      21: aload_3
      22: invokevirtual #8                  // Method org/atmosphere/cpr/AtmosphereConfig.isSupportSession:()Z
      25: ifeq          49
      28: aload_2
      29: invokestatic  #9                  // Method org/atmosphere/util/Utils.webSocketEnabled:(Ljavax/servlet/http/HttpServletRequest;)Z
      32: ifeq          49
      35: aload_2
      36: aload_3
      37: ldc           #11                 // String org.atmosphere.cpr.sessionCreate
      39: iconst_1
      40: invokevirtual #12                 // Method org/atmosphere/cpr/AtmosphereConfig.getInitParameter:(Ljava/lang/String;Z)Z
      43: invokeinterface #13,  2           // InterfaceMethod javax/servlet/http/HttpServletRequest.getSession:(Z)Ljavax/servlet/http/HttpSession;
      48: pop
      49: return
}
