Compiled from "InputLauncher.java"
class org.graylog2.shared.inputs.InputLauncher$1 implements java.lang.Runnable {
  final org.graylog2.plugin.inputs.MessageInput val$input;

  final org.graylog2.plugin.IOState val$inputState;

  final org.graylog2.shared.inputs.InputLauncher this$0;

  org.graylog2.shared.inputs.InputLauncher$1(org.graylog2.shared.inputs.InputLauncher, org.graylog2.plugin.inputs.MessageInput, org.graylog2.plugin.IOState);
    Code:
       0: aload_0
       1: aload_1
       2: putfield      #1                  // Field this$0:Lorg/graylog2/shared/inputs/InputLauncher;
       5: aload_0
       6: aload_2
       7: putfield      #2                  // Field val$input:Lorg/graylog2/plugin/inputs/MessageInput;
      10: aload_0
      11: aload_3
      12: putfield      #3                  // Field val$inputState:Lorg/graylog2/plugin/IOState;
      15: aload_0
      16: invokespecial #4                  // Method java/lang/Object."<init>":()V
      19: return

  public void run();
    Code:
       0: invokestatic  #5                  // Method org/graylog2/shared/inputs/InputLauncher.access$000:()Lorg/slf4j/Logger;
       3: ldc           #6                  // String Starting [{}] input with ID <{}>
       5: aload_0
       6: getfield      #2                  // Field val$input:Lorg/graylog2/plugin/inputs/MessageInput;
       9: invokevirtual #7                  // Method java/lang/Object.getClass:()Ljava/lang/Class;
      12: invokevirtual #8                  // Method java/lang/Class.getCanonicalName:()Ljava/lang/String;
      15: aload_0
      16: getfield      #2                  // Field val$input:Lorg/graylog2/plugin/inputs/MessageInput;
      19: invokevirtual #9                  // Method org/graylog2/plugin/inputs/MessageInput.getId:()Ljava/lang/String;
      22: invokeinterface #10,  4           // InterfaceMethod org/slf4j/Logger.debug:(Ljava/lang/String;Ljava/lang/Object;Ljava/lang/Object;)V
      27: aload_0
      28: getfield      #2                  // Field val$input:Lorg/graylog2/plugin/inputs/MessageInput;
      31: invokevirtual #11                 // Method org/graylog2/plugin/inputs/MessageInput.checkConfiguration:()V
      34: aload_0
      35: getfield      #3                  // Field val$inputState:Lorg/graylog2/plugin/IOState;
      38: getstatic     #12                 // Field org/graylog2/plugin/IOState$Type.STARTING:Lorg/graylog2/plugin/IOState$Type;
      41: invokevirtual #13                 // Method org/graylog2/plugin/IOState.setState:(Lorg/graylog2/plugin/IOState$Type;)V
      44: aload_0
      45: getfield      #2                  // Field val$input:Lorg/graylog2/plugin/inputs/MessageInput;
      48: aload_0
      49: getfield      #1                  // Field this$0:Lorg/graylog2/shared/inputs/InputLauncher;
      52: invokestatic  #14                 // Method org/graylog2/shared/inputs/InputLauncher.access$100:(Lorg/graylog2/shared/inputs/InputLauncher;)Lorg/graylog2/plugin/buffers/InputBuffer;
      55: invokevirtual #15                 // Method org/graylog2/plugin/inputs/MessageInput.launch:(Lorg/graylog2/plugin/buffers/InputBuffer;)V
      58: aload_0
      59: getfield      #3                  // Field val$inputState:Lorg/graylog2/plugin/IOState;
      62: getstatic     #16                 // Field org/graylog2/plugin/IOState$Type.RUNNING:Lorg/graylog2/plugin/IOState$Type;
      65: invokevirtual #13                 // Method org/graylog2/plugin/IOState.setState:(Lorg/graylog2/plugin/IOState$Type;)V
      68: new           #17                 // class java/lang/StringBuilder
      71: dup
      72: invokespecial #18                 // Method java/lang/StringBuilder."<init>":()V
      75: ldc           #19                 // String Completed starting [
      77: invokevirtual #20                 // Method java/lang/StringBuilder.append:(Ljava/lang/String;)Ljava/lang/StringBuilder;
      80: aload_0
      81: getfield      #2                  // Field val$input:Lorg/graylog2/plugin/inputs/MessageInput;
      84: invokevirtual #7                  // Method java/lang/Object.getClass:()Ljava/lang/Class;
      87: invokevirtual #8                  // Method java/lang/Class.getCanonicalName:()Ljava/lang/String;
      90: invokevirtual #20                 // Method java/lang/StringBuilder.append:(Ljava/lang/String;)Ljava/lang/StringBuilder;
      93: ldc           #21                 // String ] input with ID <
      95: invokevirtual #20                 // Method java/lang/StringBuilder.append:(Ljava/lang/String;)Ljava/lang/StringBuilder;
      98: aload_0
      99: getfield      #2                  // Field val$input:Lorg/graylog2/plugin/inputs/MessageInput;
     102: invokevirtual #9                  // Method org/graylog2/plugin/inputs/MessageInput.getId:()Ljava/lang/String;
     105: invokevirtual #20                 // Method java/lang/StringBuilder.append:(Ljava/lang/String;)Ljava/lang/StringBuilder;
     108: ldc           #22                 // String >
     110: invokevirtual #20                 // Method java/lang/StringBuilder.append:(Ljava/lang/String;)Ljava/lang/StringBuilder;
     113: invokevirtual #23                 // Method java/lang/StringBuilder.toString:()Ljava/lang/String;
     116: astore_1
     117: invokestatic  #5                  // Method org/graylog2/shared/inputs/InputLauncher.access$000:()Lorg/slf4j/Logger;
     120: aload_1
     121: invokeinterface #24,  2           // InterfaceMethod org/slf4j/Logger.debug:(Ljava/lang/String;)V
     126: goto          142
     129: astore_1
     130: aload_0
     131: getfield      #1                  // Field this$0:Lorg/graylog2/shared/inputs/InputLauncher;
     134: aload_1
     135: aload_0
     136: getfield      #3                  // Field val$inputState:Lorg/graylog2/plugin/IOState;
     139: invokevirtual #26                 // Method org/graylog2/shared/inputs/InputLauncher.handleLaunchException:(Ljava/lang/Throwable;Lorg/graylog2/plugin/IOState;)V
     142: return
    Exception table:
       from    to  target type
          27   126   129   Class java/lang/Exception
}
