Compiled from "JavaEETrustModule.java"
public class org.jboss.security.identitytrust.modules.JavaEETrustModule extends org.jboss.security.identitytrust.modules.AbstractIdentityTrustModule {
  public org.jboss.security.identitytrust.modules.JavaEETrustModule();
    Code:
       0: aload_0
       1: invokespecial #1                  // Method org/jboss/security/identitytrust/modules/AbstractIdentityTrustModule."<init>":()V
       4: return

  public org.jboss.security.identitytrust.IdentityTrustManager$TrustDecision isTrusted() throws org.jboss.security.identitytrust.IdentityTrustException;
    Code:
       0: aload_0
       1: getfield      #2                  // Field securityContext:Lorg/jboss/security/SecurityContext;
       4: invokeinterface #3,  1            // InterfaceMethod org/jboss/security/SecurityContext.getIncomingRunAs:()Lorg/jboss/security/RunAs;
       9: astore_1
      10: aload_1
      11: instanceof    #4                  // class org/jboss/security/RunAsIdentity
      14: ifeq          38
      17: aload_1
      18: checkcast     #4                  // class org/jboss/security/RunAsIdentity
      21: astore_2
      22: ldc           #6                  // String JavaEE
      24: aload_2
      25: invokevirtual #7                  // Method org/jboss/security/RunAsIdentity.getProof:()Ljava/lang/Object;
      28: invokevirtual #8                  // Method java/lang/String.equals:(Ljava/lang/Object;)Z
      31: ifeq          38
      34: getstatic     #9                  // Field org/jboss/security/identitytrust/IdentityTrustManager$TrustDecision.Permit:Lorg/jboss/security/identitytrust/IdentityTrustManager$TrustDecision;
      37: areturn
      38: getstatic     #10                 // Field org/jboss/security/identitytrust/IdentityTrustManager$TrustDecision.NotApplicable:Lorg/jboss/security/identitytrust/IdentityTrustManager$TrustDecision;
      41: areturn
}
