Compiled from "DefaultTypeConverter.java"
public class org.apache.camel.impl.converter.DefaultTypeConverter extends org.apache.camel.impl.converter.BaseTypeConverterRegistry {
  public org.apache.camel.impl.converter.DefaultTypeConverter(org.apache.camel.spi.PackageScanClassResolver, org.apache.camel.spi.Injector, org.apache.camel.spi.FactoryFinder);
    Code:
       0: aload_0
       1: aload_1
       2: aload_2
       3: aload_3
       4: invokespecial #9                  // Method org/apache/camel/impl/converter/BaseTypeConverterRegistry."<init>":(Lorg/apache/camel/spi/PackageScanClassResolver;Lorg/apache/camel/spi/Injector;Lorg/apache/camel/spi/FactoryFinder;)V
       7: return

  public boolean allowNull();
    Code:
       0: iconst_0
       1: ireturn

  public boolean isRunAllowed();
    Code:
       0: iconst_1
       1: ireturn

  protected void doStart() throws java.lang.Exception;
    Code:
       0: aload_0
       1: invokespecial #26                 // Method org/apache/camel/impl/converter/BaseTypeConverterRegistry.doStart:()V
       4: aload_0
       5: invokevirtual #29                 // Method loadCoreTypeConverters:()V
       8: aload_0
       9: invokevirtual #32                 // Method loadTypeConverters:()V
      12: aload_0
      13: getfield      #36                 // Field log:Lorg/slf4j/Logger;
      16: ldc           #38                 // String Loaded {} type converters
      18: aload_0
      19: getfield      #42                 // Field typeMappings:Ljava/util/concurrent/ConcurrentMap;
      22: invokeinterface #48,  1           // InterfaceMethod java/util/concurrent/ConcurrentMap.size:()I
      27: invokestatic  #54                 // Method java/lang/Integer.valueOf:(I)Ljava/lang/Integer;
      30: invokeinterface #60,  3           // InterfaceMethod org/slf4j/Logger.info:(Ljava/lang/String;Ljava/lang/Object;)V
      35: return
}
