Compiled from "SessionBuilder.java"
public class org.signal.libsignal.protocol.SessionBuilder {
  private static final java.lang.String TAG;

  private final org.signal.libsignal.protocol.state.SessionStore sessionStore;

  private final org.signal.libsignal.protocol.state.PreKeyStore preKeyStore;

  private final org.signal.libsignal.protocol.state.SignedPreKeyStore signedPreKeyStore;

  private final org.signal.libsignal.protocol.state.IdentityKeyStore identityKeyStore;

  private final org.signal.libsignal.protocol.SignalProtocolAddress remoteAddress;

  public org.signal.libsignal.protocol.SessionBuilder(org.signal.libsignal.protocol.state.SessionStore, org.signal.libsignal.protocol.state.PreKeyStore, org.signal.libsignal.protocol.state.SignedPreKeyStore, org.signal.libsignal.protocol.state.IdentityKeyStore, org.signal.libsignal.protocol.SignalProtocolAddress);
    Code:
       0: aload_0
       1: invokespecial #1                  // Method java/lang/Object."<init>":()V
       4: aload_0
       5: aload_1
       6: putfield      #2                  // Field sessionStore:Lorg/signal/libsignal/protocol/state/SessionStore;
       9: aload_0
      10: aload_2
      11: putfield      #3                  // Field preKeyStore:Lorg/signal/libsignal/protocol/state/PreKeyStore;
      14: aload_0
      15: aload_3
      16: putfield      #4                  // Field signedPreKeyStore:Lorg/signal/libsignal/protocol/state/SignedPreKeyStore;
      19: aload_0
      20: aload         4
      22: putfield      #5                  // Field identityKeyStore:Lorg/signal/libsignal/protocol/state/IdentityKeyStore;
      25: aload_0
      26: aload         5
      28: putfield      #6                  // Field remoteAddress:Lorg/signal/libsignal/protocol/SignalProtocolAddress;
      31: return

  public org.signal.libsignal.protocol.SessionBuilder(org.signal.libsignal.protocol.state.SignalProtocolStore, org.signal.libsignal.protocol.SignalProtocolAddress);
    Code:
       0: aload_0
       1: aload_1
       2: aload_1
       3: aload_1
       4: aload_1
       5: aload_2
       6: invokespecial #7                  // Method "<init>":(Lorg/signal/libsignal/protocol/state/SessionStore;Lorg/signal/libsignal/protocol/state/PreKeyStore;Lorg/signal/libsignal/protocol/state/SignedPreKeyStore;Lorg/signal/libsignal/protocol/state/IdentityKeyStore;Lorg/signal/libsignal/protocol/SignalProtocolAddress;)V
       9: return

  public void process(org.signal.libsignal.protocol.state.PreKeyBundle) throws org.signal.libsignal.protocol.InvalidKeyException, org.signal.libsignal.protocol.UntrustedIdentityException;
    Code:
       0: new           #8                  // class org/signal/libsignal/internal/NativeHandleGuard
       3: dup
       4: aload_1
       5: invokespecial #9                  // Method org/signal/libsignal/internal/NativeHandleGuard."<init>":(Lorg/signal/libsignal/internal/NativeHandleGuard$Owner;)V
       8: astore_2
       9: new           #8                  // class org/signal/libsignal/internal/NativeHandleGuard
      12: dup
      13: aload_0
      14: getfield      #6                  // Field remoteAddress:Lorg/signal/libsignal/protocol/SignalProtocolAddress;
      17: invokespecial #9                  // Method org/signal/libsignal/internal/NativeHandleGuard."<init>":(Lorg/signal/libsignal/internal/NativeHandleGuard$Owner;)V
      20: astore_3
      21: aload_2
      22: invokevirtual #10                 // Method org/signal/libsignal/internal/NativeHandleGuard.nativeHandle:()J
      25: aload_3
      26: invokevirtual #10                 // Method org/signal/libsignal/internal/NativeHandleGuard.nativeHandle:()J
      29: aload_0
      30: getfield      #2                  // Field sessionStore:Lorg/signal/libsignal/protocol/state/SessionStore;
      33: aload_0
      34: getfield      #5                  // Field identityKeyStore:Lorg/signal/libsignal/protocol/state/IdentityKeyStore;
      37: aconst_null
      38: invokestatic  #11                 // Method org/signal/libsignal/internal/Native.SessionBuilder_ProcessPreKeyBundle:(JJLorg/signal/libsignal/protocol/state/SessionStore;Lorg/signal/libsignal/protocol/state/IdentityKeyStore;Ljava/lang/Object;)V
      41: aload_3
      42: invokevirtual #12                 // Method org/signal/libsignal/internal/NativeHandleGuard.close:()V
      45: goto          69
      48: astore        4
      50: aload_3
      51: invokevirtual #12                 // Method org/signal/libsignal/internal/NativeHandleGuard.close:()V
      54: goto          66
      57: astore        5
      59: aload         4
      61: aload         5
      63: invokevirtual #14                 // Method java/lang/Throwable.addSuppressed:(Ljava/lang/Throwable;)V
      66: aload         4
      68: athrow
      69: aload_2
      70: invokevirtual #12                 // Method org/signal/libsignal/internal/NativeHandleGuard.close:()V
      73: goto          94
      76: astore_3
      77: aload_2
      78: invokevirtual #12                 // Method org/signal/libsignal/internal/NativeHandleGuard.close:()V
      81: goto          92
      84: astore        4
      86: aload_3
      87: aload         4
      89: invokevirtual #14                 // Method java/lang/Throwable.addSuppressed:(Ljava/lang/Throwable;)V
      92: aload_3
      93: athrow
      94: return
    Exception table:
       from    to  target type
          21    41    48   Class java/lang/Throwable
          50    54    57   Class java/lang/Throwable
           9    69    76   Class java/lang/Throwable
          77    81    84   Class java/lang/Throwable

  static {};
    Code:
       0: ldc           #15                 // class org/signal/libsignal/protocol/SessionBuilder
       2: invokevirtual #16                 // Method java/lang/Class.getSimpleName:()Ljava/lang/String;
       5: putstatic     #17                 // Field TAG:Ljava/lang/String;
       8: return
}
