Compiled from "FlowAdapters.java"
final class org.reactivestreams.FlowAdapters$FlowToReactiveProcessor<T, U> implements java.util.concurrent.Flow$Processor<T, U> {
  final org.reactivestreams.Processor<? super T, ? extends U> reactiveStreams;

  public org.reactivestreams.FlowAdapters$FlowToReactiveProcessor(org.reactivestreams.Processor<? super T, ? extends U>);
    Code:
       0: aload_0
       1: invokespecial #1                  // Method java/lang/Object."<init>":()V
       4: aload_0
       5: aload_1
       6: putfield      #2                  // Field reactiveStreams:Lorg/reactivestreams/Processor;
       9: return

  public void onSubscribe(java.util.concurrent.Flow$Subscription);
    Code:
       0: aload_0
       1: getfield      #2                  // Field reactiveStreams:Lorg/reactivestreams/Processor;
       4: aload_1
       5: ifnonnull     12
       8: aconst_null
       9: goto          20
      12: new           #3                  // class org/reactivestreams/FlowAdapters$ReactiveToFlowSubscription
      15: dup
      16: aload_1
      17: invokespecial #4                  // Method org/reactivestreams/FlowAdapters$ReactiveToFlowSubscription."<init>":(Ljava/util/concurrent/Flow$Subscription;)V
      20: invokeinterface #5,  2            // InterfaceMethod org/reactivestreams/Processor.onSubscribe:(Lorg/reactivestreams/Subscription;)V
      25: return

  public void onNext(T);
    Code:
       0: aload_0
       1: getfield      #2                  // Field reactiveStreams:Lorg/reactivestreams/Processor;
       4: aload_1
       5: invokeinterface #6,  2            // InterfaceMethod org/reactivestreams/Processor.onNext:(Ljava/lang/Object;)V
      10: return

  public void onError(java.lang.Throwable);
    Code:
       0: aload_0
       1: getfield      #2                  // Field reactiveStreams:Lorg/reactivestreams/Processor;
       4: aload_1
       5: invokeinterface #7,  2            // InterfaceMethod org/reactivestreams/Processor.onError:(Ljava/lang/Throwable;)V
      10: return

  public void onComplete();
    Code:
       0: aload_0
       1: getfield      #2                  // Field reactiveStreams:Lorg/reactivestreams/Processor;
       4: invokeinterface #8,  1            // InterfaceMethod org/reactivestreams/Processor.onComplete:()V
       9: return

  public void subscribe(java.util.concurrent.Flow$Subscriber<? super U>);
    Code:
       0: aload_0
       1: getfield      #2                  // Field reactiveStreams:Lorg/reactivestreams/Processor;
       4: aload_1
       5: ifnonnull     12
       8: aconst_null
       9: goto          20
      12: new           #9                  // class org/reactivestreams/FlowAdapters$ReactiveToFlowSubscriber
      15: dup
      16: aload_1
      17: invokespecial #10                 // Method org/reactivestreams/FlowAdapters$ReactiveToFlowSubscriber."<init>":(Ljava/util/concurrent/Flow$Subscriber;)V
      20: invokeinterface #11,  2           // InterfaceMethod org/reactivestreams/Processor.subscribe:(Lorg/reactivestreams/Subscriber;)V
      25: return
}
