Compiled from "AbstractJsonProvider.java"
public abstract class com.jayway.jsonpath.spi.json.AbstractJsonProvider implements com.jayway.jsonpath.spi.json.JsonProvider {
  public com.jayway.jsonpath.spi.json.AbstractJsonProvider();
    Code:
       0: aload_0
       1: invokespecial #1                  // Method java/lang/Object."<init>":()V
       4: return

  public boolean isArray(java.lang.Object);
    Code:
       0: aload_1
       1: instanceof    #2                  // class java/util/List
       4: ireturn

  public java.lang.Object getArrayIndex(java.lang.Object, int);
    Code:
       0: aload_1
       1: checkcast     #2                  // class java/util/List
       4: iload_2
       5: invokeinterface #3,  2            // InterfaceMethod java/util/List.get:(I)Ljava/lang/Object;
      10: areturn

  public final java.lang.Object getArrayIndex(java.lang.Object, int, boolean);
    Code:
       0: aload_0
       1: aload_1
       2: iload_2
       3: invokevirtual #4                  // Method getArrayIndex:(Ljava/lang/Object;I)Ljava/lang/Object;
       6: areturn

  public void setArrayIndex(java.lang.Object, int, java.lang.Object);
    Code:
       0: aload_0
       1: aload_1
       2: invokevirtual #5                  // Method isArray:(Ljava/lang/Object;)Z
       5: ifne          16
       8: new           #6                  // class java/lang/UnsupportedOperationException
      11: dup
      12: invokespecial #7                  // Method java/lang/UnsupportedOperationException."<init>":()V
      15: athrow
      16: aload_1
      17: checkcast     #2                  // class java/util/List
      20: astore        4
      22: iload_2
      23: aload         4
      25: invokeinterface #8,  1            // InterfaceMethod java/util/List.size:()I
      30: if_icmpne     45
      33: aload         4
      35: aload_3
      36: invokeinterface #9,  2            // InterfaceMethod java/util/List.add:(Ljava/lang/Object;)Z
      41: pop
      42: goto          55
      45: aload         4
      47: iload_2
      48: aload_3
      49: invokeinterface #10,  3           // InterfaceMethod java/util/List.set:(ILjava/lang/Object;)Ljava/lang/Object;
      54: pop
      55: return

  public java.lang.Object getMapValue(java.lang.Object, java.lang.String);
    Code:
       0: aload_1
       1: checkcast     #11                 // class java/util/Map
       4: astore_3
       5: aload_3
       6: aload_2
       7: invokeinterface #12,  2           // InterfaceMethod java/util/Map.containsKey:(Ljava/lang/Object;)Z
      12: ifne          19
      15: getstatic     #13                 // Field com/jayway/jsonpath/spi/json/JsonProvider.UNDEFINED:Ljava/lang/Object;
      18: areturn
      19: aload_3
      20: aload_2
      21: invokeinterface #14,  2           // InterfaceMethod java/util/Map.get:(Ljava/lang/Object;)Ljava/lang/Object;
      26: areturn

  public void setProperty(java.lang.Object, java.lang.Object, java.lang.Object);
    Code:
       0: aload_0
       1: aload_1
       2: invokevirtual #15                 // Method isMap:(Ljava/lang/Object;)Z
       5: ifeq          26
       8: aload_1
       9: checkcast     #11                 // class java/util/Map
      12: aload_2
      13: invokevirtual #16                 // Method java/lang/Object.toString:()Ljava/lang/String;
      16: aload_3
      17: invokeinterface #17,  3           // InterfaceMethod java/util/Map.put:(Ljava/lang/Object;Ljava/lang/Object;)Ljava/lang/Object;
      22: pop
      23: goto          68
      26: new           #18                 // class com/jayway/jsonpath/JsonPathException
      29: dup
      30: new           #19                 // class java/lang/StringBuilder
      33: dup
      34: invokespecial #20                 // Method java/lang/StringBuilder."<init>":()V
      37: ldc           #21                 // String setProperty operation cannot be used with
      39: invokevirtual #22                 // Method java/lang/StringBuilder.append:(Ljava/lang/String;)Ljava/lang/StringBuilder;
      42: aload_1
      43: invokevirtual #23                 // Method java/lang/StringBuilder.append:(Ljava/lang/Object;)Ljava/lang/StringBuilder;
      46: invokevirtual #24                 // Method java/lang/StringBuilder.toString:()Ljava/lang/String;
      49: ifnull        62
      52: aload_1
      53: invokevirtual #25                 // Method java/lang/Object.getClass:()Ljava/lang/Class;
      56: invokevirtual #26                 // Method java/lang/Class.getName:()Ljava/lang/String;
      59: goto          64
      62: ldc           #27                 // String null
      64: invokespecial #28                 // Method com/jayway/jsonpath/JsonPathException."<init>":(Ljava/lang/String;)V
      67: athrow
      68: return

  public void removeProperty(java.lang.Object, java.lang.Object);
    Code:
       0: aload_0
       1: aload_1
       2: invokevirtual #15                 // Method isMap:(Ljava/lang/Object;)Z
       5: ifeq          25
       8: aload_1
       9: checkcast     #11                 // class java/util/Map
      12: aload_2
      13: invokevirtual #16                 // Method java/lang/Object.toString:()Ljava/lang/String;
      16: invokeinterface #29,  2           // InterfaceMethod java/util/Map.remove:(Ljava/lang/Object;)Ljava/lang/Object;
      21: pop
      22: goto          65
      25: aload_1
      26: checkcast     #2                  // class java/util/List
      29: astore_3
      30: aload_2
      31: instanceof    #30                 // class java/lang/Integer
      34: ifeq          47
      37: aload_2
      38: checkcast     #30                 // class java/lang/Integer
      41: invokevirtual #31                 // Method java/lang/Integer.intValue:()I
      44: goto          54
      47: aload_2
      48: invokevirtual #16                 // Method java/lang/Object.toString:()Ljava/lang/String;
      51: invokestatic  #32                 // Method java/lang/Integer.parseInt:(Ljava/lang/String;)I
      54: istore        4
      56: aload_3
      57: iload         4
      59: invokeinterface #33,  2           // InterfaceMethod java/util/List.remove:(I)Ljava/lang/Object;
      64: pop
      65: return

  public boolean isMap(java.lang.Object);
    Code:
       0: aload_1
       1: instanceof    #11                 // class java/util/Map
       4: ireturn

  public java.util.Collection<java.lang.String> getPropertyKeys(java.lang.Object);
    Code:
       0: aload_0
       1: aload_1
       2: invokevirtual #5                  // Method isArray:(Ljava/lang/Object;)Z
       5: ifeq          16
       8: new           #6                  // class java/lang/UnsupportedOperationException
      11: dup
      12: invokespecial #7                  // Method java/lang/UnsupportedOperationException."<init>":()V
      15: athrow
      16: aload_1
      17: checkcast     #11                 // class java/util/Map
      20: invokeinterface #34,  1           // InterfaceMethod java/util/Map.keySet:()Ljava/util/Set;
      25: areturn

  public int length(java.lang.Object);
    Code:
       0: aload_0
       1: aload_1
       2: invokevirtual #5                  // Method isArray:(Ljava/lang/Object;)Z
       5: ifeq          18
       8: aload_1
       9: checkcast     #2                  // class java/util/List
      12: invokeinterface #8,  1            // InterfaceMethod java/util/List.size:()I
      17: ireturn
      18: aload_0
      19: aload_1
      20: invokevirtual #15                 // Method isMap:(Ljava/lang/Object;)Z
      23: ifeq          37
      26: aload_0
      27: aload_1
      28: invokevirtual #35                 // Method getPropertyKeys:(Ljava/lang/Object;)Ljava/util/Collection;
      31: invokeinterface #36,  1           // InterfaceMethod java/util/Collection.size:()I
      36: ireturn
      37: aload_1
      38: instanceof    #37                 // class java/lang/String
      41: ifeq          52
      44: aload_1
      45: checkcast     #37                 // class java/lang/String
      48: invokevirtual #38                 // Method java/lang/String.length:()I
      51: ireturn
      52: new           #18                 // class com/jayway/jsonpath/JsonPathException
      55: dup
      56: new           #19                 // class java/lang/StringBuilder
      59: dup
      60: invokespecial #20                 // Method java/lang/StringBuilder."<init>":()V
      63: ldc           #39                 // String length operation cannot be applied to
      65: invokevirtual #22                 // Method java/lang/StringBuilder.append:(Ljava/lang/String;)Ljava/lang/StringBuilder;
      68: aload_1
      69: invokevirtual #23                 // Method java/lang/StringBuilder.append:(Ljava/lang/Object;)Ljava/lang/StringBuilder;
      72: invokevirtual #24                 // Method java/lang/StringBuilder.toString:()Ljava/lang/String;
      75: ifnull        88
      78: aload_1
      79: invokevirtual #25                 // Method java/lang/Object.getClass:()Ljava/lang/Class;
      82: invokevirtual #26                 // Method java/lang/Class.getName:()Ljava/lang/String;
      85: goto          90
      88: ldc           #27                 // String null
      90: invokespecial #28                 // Method com/jayway/jsonpath/JsonPathException."<init>":(Ljava/lang/String;)V
      93: athrow

  public java.lang.Iterable<? extends java.lang.Object> toIterable(java.lang.Object);
    Code:
       0: aload_0
       1: aload_1
       2: invokevirtual #5                  // Method isArray:(Ljava/lang/Object;)Z
       5: ifeq          13
       8: aload_1
       9: checkcast     #40                 // class java/lang/Iterable
      12: areturn
      13: new           #18                 // class com/jayway/jsonpath/JsonPathException
      16: dup
      17: new           #19                 // class java/lang/StringBuilder
      20: dup
      21: invokespecial #20                 // Method java/lang/StringBuilder."<init>":()V
      24: ldc           #41                 // String Cannot iterate over
      26: invokevirtual #22                 // Method java/lang/StringBuilder.append:(Ljava/lang/String;)Ljava/lang/StringBuilder;
      29: aload_1
      30: invokevirtual #23                 // Method java/lang/StringBuilder.append:(Ljava/lang/Object;)Ljava/lang/StringBuilder;
      33: invokevirtual #24                 // Method java/lang/StringBuilder.toString:()Ljava/lang/String;
      36: ifnull        49
      39: aload_1
      40: invokevirtual #25                 // Method java/lang/Object.getClass:()Ljava/lang/Class;
      43: invokevirtual #26                 // Method java/lang/Class.getName:()Ljava/lang/String;
      46: goto          51
      49: ldc           #27                 // String null
      51: invokespecial #28                 // Method com/jayway/jsonpath/JsonPathException."<init>":(Ljava/lang/String;)V
      54: athrow

  public java.lang.Object unwrap(java.lang.Object);
    Code:
       0: aload_1
       1: areturn
}
