Compiled from "TimelineConnector.java"
public class org.apache.hadoop.yarn.client.api.impl.TimelineConnector extends org.apache.hadoop.service.AbstractService {
  private static final com.google.common.base.Joiner JOINER;

  private static final org.apache.commons.logging.Log LOG;

  public static final int DEFAULT_SOCKET_TIMEOUT;

  private org.apache.hadoop.security.ssl.SSLFactory sslFactory;

  private com.sun.jersey.api.client.Client client;

  private org.apache.hadoop.security.authentication.client.ConnectionConfigurator connConfigurator;

  private org.apache.hadoop.security.token.delegation.web.DelegationTokenAuthenticator authenticator;

  private org.apache.hadoop.security.token.delegation.web.DelegationTokenAuthenticatedURL$Token token;

  private org.apache.hadoop.security.UserGroupInformation authUgi;

  private java.lang.String doAsUser;

  org.apache.hadoop.yarn.client.api.impl.TimelineConnector$TimelineClientConnectionRetry connectionRetry;

  private boolean requireConnectionRetry;

  private static final org.apache.hadoop.security.authentication.client.ConnectionConfigurator DEFAULT_TIMEOUT_CONN_CONFIGURATOR;

  public org.apache.hadoop.yarn.client.api.impl.TimelineConnector(boolean, org.apache.hadoop.security.UserGroupInformation, java.lang.String, org.apache.hadoop.security.token.delegation.web.DelegationTokenAuthenticatedURL$Token);
    Code:
       0: aload_0
       1: ldc           #3                  // String TimelineConnector
       3: invokespecial #4                  // Method org/apache/hadoop/service/AbstractService."<init>":(Ljava/lang/String;)V
       6: aload_0
       7: iload_1
       8: putfield      #5                  // Field requireConnectionRetry:Z
      11: aload_0
      12: aload_2
      13: putfield      #6                  // Field authUgi:Lorg/apache/hadoop/security/UserGroupInformation;
      16: aload_0
      17: aload_3
      18: putfield      #7                  // Field doAsUser:Ljava/lang/String;
      21: aload_0
      22: aload         4
      24: putfield      #8                  // Field token:Lorg/apache/hadoop/security/token/delegation/web/DelegationTokenAuthenticatedURL$Token;
      27: return

  protected void serviceInit(org.apache.hadoop.conf.Configuration) throws java.lang.Exception;
    Code:
       0: aload_0
       1: aload_1
       2: invokespecial #9                  // Method org/apache/hadoop/service/AbstractService.serviceInit:(Lorg/apache/hadoop/conf/Configuration;)V
       5: new           #10                 // class com/sun/jersey/api/client/config/DefaultClientConfig
       8: dup
       9: invokespecial #11                 // Method com/sun/jersey/api/client/config/DefaultClientConfig."<init>":()V
      12: astore_2
      13: aload_2
      14: invokeinterface #12,  1           // InterfaceMethod com/sun/jersey/api/client/config/ClientConfig.getClasses:()Ljava/util/Set;
      19: ldc           #13                 // class org/apache/hadoop/yarn/webapp/YarnJacksonJaxbJsonProvider
      21: invokeinterface #14,  2           // InterfaceMethod java/util/Set.add:(Ljava/lang/Object;)Z
      26: pop
      27: aload_1
      28: invokestatic  #15                 // Method org/apache/hadoop/yarn/conf/YarnConfiguration.useHttps:(Lorg/apache/hadoop/conf/Configuration;)Z
      31: ifeq          58
      34: aload_0
      35: aload_0
      36: aload_1
      37: invokevirtual #16                 // Method getSSLFactory:(Lorg/apache/hadoop/conf/Configuration;)Lorg/apache/hadoop/security/ssl/SSLFactory;
      40: putfield      #17                 // Field sslFactory:Lorg/apache/hadoop/security/ssl/SSLFactory;
      43: aload_0
      44: aload_0
      45: aload_0
      46: getfield      #17                 // Field sslFactory:Lorg/apache/hadoop/security/ssl/SSLFactory;
      49: invokespecial #18                 // Method getConnConfigurator:(Lorg/apache/hadoop/security/ssl/SSLFactory;)Lorg/apache/hadoop/security/authentication/client/ConnectionConfigurator;
      52: putfield      #19                 // Field connConfigurator:Lorg/apache/hadoop/security/authentication/client/ConnectionConfigurator;
      55: goto          65
      58: aload_0
      59: getstatic     #20                 // Field DEFAULT_TIMEOUT_CONN_CONFIGURATOR:Lorg/apache/hadoop/security/authentication/client/ConnectionConfigurator;
      62: putfield      #19                 // Field connConfigurator:Lorg/apache/hadoop/security/authentication/client/ConnectionConfigurator;
      65: invokestatic  #21                 // Method org/apache/hadoop/security/UserGroupInformation.isSecurityEnabled:()Z
      68: ifeq          85
      71: aload_0
      72: new           #22                 // class org/apache/hadoop/security/token/delegation/web/KerberosDelegationTokenAuthenticator
      75: dup
      76: invokespecial #23                 // Method org/apache/hadoop/security/token/delegation/web/KerberosDelegationTokenAuthenticator."<init>":()V
      79: putfield      #24                 // Field authenticator:Lorg/apache/hadoop/security/token/delegation/web/DelegationTokenAuthenticator;
      82: goto          96
      85: aload_0
      86: new           #25                 // class org/apache/hadoop/security/token/delegation/web/PseudoDelegationTokenAuthenticator
      89: dup
      90: invokespecial #26                 // Method org/apache/hadoop/security/token/delegation/web/PseudoDelegationTokenAuthenticator."<init>":()V
      93: putfield      #24                 // Field authenticator:Lorg/apache/hadoop/security/token/delegation/web/DelegationTokenAuthenticator;
      96: aload_0
      97: getfield      #24                 // Field authenticator:Lorg/apache/hadoop/security/token/delegation/web/DelegationTokenAuthenticator;
     100: aload_0
     101: getfield      #19                 // Field connConfigurator:Lorg/apache/hadoop/security/authentication/client/ConnectionConfigurator;
     104: invokevirtual #27                 // Method org/apache/hadoop/security/token/delegation/web/DelegationTokenAuthenticator.setConnectionConfigurator:(Lorg/apache/hadoop/security/authentication/client/ConnectionConfigurator;)V
     107: aload_0
     108: new           #28                 // class org/apache/hadoop/yarn/client/api/impl/TimelineConnector$TimelineClientConnectionRetry
     111: dup
     112: aload_1
     113: invokespecial #29                 // Method org/apache/hadoop/yarn/client/api/impl/TimelineConnector$TimelineClientConnectionRetry."<init>":(Lorg/apache/hadoop/conf/Configuration;)V
     116: putfield      #30                 // Field connectionRetry:Lorg/apache/hadoop/yarn/client/api/impl/TimelineConnector$TimelineClientConnectionRetry;
     119: aload_0
     120: new           #31                 // class com/sun/jersey/api/client/Client
     123: dup
     124: new           #32                 // class com/sun/jersey/client/urlconnection/URLConnectionClientHandler
     127: dup
     128: new           #33                 // class org/apache/hadoop/yarn/client/api/impl/TimelineConnector$TimelineURLConnectionFactory
     131: dup
     132: aload_0
     133: getfield      #6                  // Field authUgi:Lorg/apache/hadoop/security/UserGroupInformation;
     136: aload_0
     137: getfield      #24                 // Field authenticator:Lorg/apache/hadoop/security/token/delegation/web/DelegationTokenAuthenticator;
     140: aload_0
     141: getfield      #19                 // Field connConfigurator:Lorg/apache/hadoop/security/authentication/client/ConnectionConfigurator;
     144: aload_0
     145: getfield      #8                  // Field token:Lorg/apache/hadoop/security/token/delegation/web/DelegationTokenAuthenticatedURL$Token;
     148: aload_0
     149: getfield      #7                  // Field doAsUser:Ljava/lang/String;
     152: invokespecial #34                 // Method org/apache/hadoop/yarn/client/api/impl/TimelineConnector$TimelineURLConnectionFactory."<init>":(Lorg/apache/hadoop/security/UserGroupInformation;Lorg/apache/hadoop/security/token/delegation/web/DelegationTokenAuthenticator;Lorg/apache/hadoop/security/authentication/client/ConnectionConfigurator;Lorg/apache/hadoop/security/token/delegation/web/DelegationTokenAuthenticatedURL$Token;Ljava/lang/String;)V
     155: invokespecial #35                 // Method com/sun/jersey/client/urlconnection/URLConnectionClientHandler."<init>":(Lcom/sun/jersey/client/urlconnection/HttpURLConnectionFactory;)V
     158: aload_2
     159: invokespecial #36                 // Method com/sun/jersey/api/client/Client."<init>":(Lcom/sun/jersey/api/client/ClientHandler;Lcom/sun/jersey/api/client/config/ClientConfig;)V
     162: putfield      #37                 // Field client:Lcom/sun/jersey/api/client/Client;
     165: aload_0
     166: getfield      #5                  // Field requireConnectionRetry:Z
     169: ifeq          192
     172: new           #38                 // class org/apache/hadoop/yarn/client/api/impl/TimelineConnector$TimelineJerseyRetryFilter
     175: dup
     176: aload_0
     177: getfield      #30                 // Field connectionRetry:Lorg/apache/hadoop/yarn/client/api/impl/TimelineConnector$TimelineClientConnectionRetry;
     180: invokespecial #39                 // Method org/apache/hadoop/yarn/client/api/impl/TimelineConnector$TimelineJerseyRetryFilter."<init>":(Lorg/apache/hadoop/yarn/client/api/impl/TimelineConnector$TimelineClientConnectionRetry;)V
     183: astore_3
     184: aload_0
     185: getfield      #37                 // Field client:Lcom/sun/jersey/api/client/Client;
     188: aload_3
     189: invokevirtual #40                 // Method com/sun/jersey/api/client/Client.addFilter:(Lcom/sun/jersey/api/client/filter/ClientFilter;)V
     192: return

  private org.apache.hadoop.security.authentication.client.ConnectionConfigurator getConnConfigurator(org.apache.hadoop.security.ssl.SSLFactory);
    Code:
       0: ldc           #42                 // int 60000
       2: aload_1
       3: invokestatic  #43                 // Method initSslConnConfigurator:(ILorg/apache/hadoop/security/ssl/SSLFactory;)Lorg/apache/hadoop/security/authentication/client/ConnectionConfigurator;
       6: areturn
       7: astore_2
       8: getstatic     #1                  // Field LOG:Lorg/apache/commons/logging/Log;
      11: ldc           #45                 // String Cannot load customized ssl related configuration. Fallback to system-generic settings.
      13: aload_2
      14: invokeinterface #46,  3           // InterfaceMethod org/apache/commons/logging/Log.debug:(Ljava/lang/Object;Ljava/lang/Throwable;)V
      19: getstatic     #20                 // Field DEFAULT_TIMEOUT_CONN_CONFIGURATOR:Lorg/apache/hadoop/security/authentication/client/ConnectionConfigurator;
      22: areturn
    Exception table:
       from    to  target type
           0     6     7   Class java/lang/Exception

  private static org.apache.hadoop.security.authentication.client.ConnectionConfigurator initSslConnConfigurator(int, org.apache.hadoop.security.ssl.SSLFactory) throws java.io.IOException, java.security.GeneralSecurityException;
    Code:
       0: aload_1
       1: invokevirtual #47                 // Method org/apache/hadoop/security/ssl/SSLFactory.createSSLSocketFactory:()Ljavax/net/ssl/SSLSocketFactory;
       4: astore_2
       5: aload_1
       6: invokevirtual #48                 // Method org/apache/hadoop/security/ssl/SSLFactory.getHostnameVerifier:()Ljavax/net/ssl/HostnameVerifier;
       9: astore_3
      10: new           #49                 // class org/apache/hadoop/yarn/client/api/impl/TimelineConnector$2
      13: dup
      14: aload_2
      15: aload_3
      16: iload_0
      17: invokespecial #50                 // Method org/apache/hadoop/yarn/client/api/impl/TimelineConnector$2."<init>":(Ljavax/net/ssl/SSLSocketFactory;Ljavax/net/ssl/HostnameVerifier;I)V
      20: areturn

  protected org.apache.hadoop.security.ssl.SSLFactory getSSLFactory(org.apache.hadoop.conf.Configuration) throws java.security.GeneralSecurityException, java.io.IOException;
    Code:
       0: new           #51                 // class org/apache/hadoop/security/ssl/SSLFactory
       3: dup
       4: getstatic     #52                 // Field org/apache/hadoop/security/ssl/SSLFactory$Mode.CLIENT:Lorg/apache/hadoop/security/ssl/SSLFactory$Mode;
       7: aload_1
       8: invokespecial #53                 // Method org/apache/hadoop/security/ssl/SSLFactory."<init>":(Lorg/apache/hadoop/security/ssl/SSLFactory$Mode;Lorg/apache/hadoop/conf/Configuration;)V
      11: astore_2
      12: aload_2
      13: invokevirtual #54                 // Method org/apache/hadoop/security/ssl/SSLFactory.init:()V
      16: aload_2
      17: areturn

  private static void setTimeouts(java.net.URLConnection, int);
    Code:
       0: aload_0
       1: iload_1
       2: invokevirtual #55                 // Method java/net/URLConnection.setConnectTimeout:(I)V
       5: aload_0
       6: iload_1
       7: invokevirtual #56                 // Method java/net/URLConnection.setReadTimeout:(I)V
      10: return

  public static java.net.URI constructResURI(org.apache.hadoop.conf.Configuration, java.lang.String, java.lang.String);
    Code:
       0: getstatic     #57                 // Field JOINER:Lcom/google/common/base/Joiner;
       3: aload_0
       4: invokestatic  #15                 // Method org/apache/hadoop/yarn/conf/YarnConfiguration.useHttps:(Lorg/apache/hadoop/conf/Configuration;)Z
       7: ifeq          15
      10: ldc           #58                 // String https://
      12: goto          17
      15: ldc           #59                 // String http://
      17: aload_1
      18: iconst_1
      19: anewarray     #60                 // class java/lang/Object
      22: dup
      23: iconst_0
      24: aload_2
      25: aastore
      26: invokevirtual #61                 // Method com/google/common/base/Joiner.join:(Ljava/lang/Object;Ljava/lang/Object;[Ljava/lang/Object;)Ljava/lang/String;
      29: invokestatic  #62                 // Method java/net/URI.create:(Ljava/lang/String;)Ljava/net/URI;
      32: areturn

  org.apache.hadoop.security.token.delegation.web.DelegationTokenAuthenticatedURL getDelegationTokenAuthenticatedURL();
    Code:
       0: new           #63                 // class org/apache/hadoop/security/token/delegation/web/DelegationTokenAuthenticatedURL
       3: dup
       4: aload_0
       5: getfield      #24                 // Field authenticator:Lorg/apache/hadoop/security/token/delegation/web/DelegationTokenAuthenticator;
       8: aload_0
       9: getfield      #19                 // Field connConfigurator:Lorg/apache/hadoop/security/authentication/client/ConnectionConfigurator;
      12: invokespecial #64                 // Method org/apache/hadoop/security/token/delegation/web/DelegationTokenAuthenticatedURL."<init>":(Lorg/apache/hadoop/security/token/delegation/web/DelegationTokenAuthenticator;Lorg/apache/hadoop/security/authentication/client/ConnectionConfigurator;)V
      15: areturn

  protected void serviceStop();
    Code:
       0: aload_0
       1: getfield      #17                 // Field sslFactory:Lorg/apache/hadoop/security/ssl/SSLFactory;
       4: ifnull        14
       7: aload_0
       8: getfield      #17                 // Field sslFactory:Lorg/apache/hadoop/security/ssl/SSLFactory;
      11: invokevirtual #65                 // Method org/apache/hadoop/security/ssl/SSLFactory.destroy:()V
      14: return

  public com.sun.jersey.api.client.Client getClient();
    Code:
       0: aload_0
       1: getfield      #37                 // Field client:Lcom/sun/jersey/api/client/Client;
       4: areturn

  public java.lang.Object operateDelegationToken(java.security.PrivilegedExceptionAction<?>) throws java.io.IOException, org.apache.hadoop.yarn.exceptions.YarnException;
    Code:
       0: aload_0
       1: aload_1
       2: invokevirtual #66                 // Method createRetryOpForOperateDelegationToken:(Ljava/security/PrivilegedExceptionAction;)Lorg/apache/hadoop/yarn/client/api/impl/TimelineConnector$TimelineClientRetryOp;
       5: astore_2
       6: aload_0
       7: getfield      #30                 // Field connectionRetry:Lorg/apache/hadoop/yarn/client/api/impl/TimelineConnector$TimelineClientConnectionRetry;
      10: aload_2
      11: invokevirtual #67                 // Method org/apache/hadoop/yarn/client/api/impl/TimelineConnector$TimelineClientConnectionRetry.retryOn:(Lorg/apache/hadoop/yarn/client/api/impl/TimelineConnector$TimelineClientRetryOp;)Ljava/lang/Object;
      14: areturn

  org.apache.hadoop.yarn.client.api.impl.TimelineConnector$TimelineClientRetryOp createRetryOpForOperateDelegationToken(java.security.PrivilegedExceptionAction<?>) throws java.io.IOException;
    Code:
       0: new           #68                 // class org/apache/hadoop/yarn/client/api/impl/TimelineConnector$TimelineClientRetryOpForOperateDelegationToken
       3: dup
       4: aload_0
       5: getfield      #6                  // Field authUgi:Lorg/apache/hadoop/security/UserGroupInformation;
       8: aload_1
       9: invokespecial #69                 // Method org/apache/hadoop/yarn/client/api/impl/TimelineConnector$TimelineClientRetryOpForOperateDelegationToken."<init>":(Lorg/apache/hadoop/security/UserGroupInformation;Ljava/security/PrivilegedExceptionAction;)V
      12: areturn

  static void access$000(java.net.URLConnection, int);
    Code:
       0: aload_0
       1: iload_1
       2: invokestatic  #2                  // Method setTimeouts:(Ljava/net/URLConnection;I)V
       5: return

  static org.apache.commons.logging.Log access$100();
    Code:
       0: getstatic     #1                  // Field LOG:Lorg/apache/commons/logging/Log;
       3: areturn

  static {};
    Code:
       0: ldc           #70                 // String
       2: invokestatic  #71                 // Method com/google/common/base/Joiner.on:(Ljava/lang/String;)Lcom/google/common/base/Joiner;
       5: putstatic     #57                 // Field JOINER:Lcom/google/common/base/Joiner;
       8: ldc           #41                 // class org/apache/hadoop/yarn/client/api/impl/TimelineConnector
      10: invokestatic  #72                 // Method org/apache/commons/logging/LogFactory.getLog:(Ljava/lang/Class;)Lorg/apache/commons/logging/Log;
      13: putstatic     #1                  // Field LOG:Lorg/apache/commons/logging/Log;
      16: new           #73                 // class org/apache/hadoop/yarn/client/api/impl/TimelineConnector$1
      19: dup
      20: invokespecial #74                 // Method org/apache/hadoop/yarn/client/api/impl/TimelineConnector$1."<init>":()V
      23: putstatic     #20                 // Field DEFAULT_TIMEOUT_CONN_CONFIGURATOR:Lorg/apache/hadoop/security/authentication/client/ConnectionConfigurator;
      26: return
}
