Compiled from "AnnotationCommandSegmentFactory.java"
public class io.lettuce.core.dynamic.segment.AnnotationCommandSegmentFactory implements io.lettuce.core.dynamic.segment.CommandSegmentFactory {
  private static final java.util.regex.Pattern SPACE;

  private static final java.lang.String INDEX_BASED_PARAM_START;

  private static final java.lang.String NAME_BASED_PARAM_START;

  public io.lettuce.core.dynamic.segment.AnnotationCommandSegmentFactory();
    Code:
       0: aload_0
       1: invokespecial #2                  // Method java/lang/Object."<init>":()V
       4: return

  public io.lettuce.core.dynamic.segment.CommandSegments createCommandSegments(io.lettuce.core.dynamic.CommandMethod);
    Code:
       0: getstatic     #3                  // Field io/lettuce/core/dynamic/segment/AnnotationCommandSegmentFactory$CommandSegmentParser.INSTANCE:Lio/lettuce/core/dynamic/segment/AnnotationCommandSegmentFactory$CommandSegmentParser;
       3: aload_1
       4: invokestatic  #4                  // Method io/lettuce/core/dynamic/segment/AnnotationCommandSegmentFactory$CommandSegmentParser.access$000:(Lio/lettuce/core/dynamic/segment/AnnotationCommandSegmentFactory$CommandSegmentParser;Lio/lettuce/core/dynamic/CommandMethod;)Z
       7: ifeq          18
      10: getstatic     #3                  // Field io/lettuce/core/dynamic/segment/AnnotationCommandSegmentFactory$CommandSegmentParser.INSTANCE:Lio/lettuce/core/dynamic/segment/AnnotationCommandSegmentFactory$CommandSegmentParser;
      13: aload_1
      14: invokevirtual #5                  // Method io/lettuce/core/dynamic/segment/AnnotationCommandSegmentFactory$CommandSegmentParser.createCommandSegments:(Lio/lettuce/core/dynamic/CommandMethod;)Lio/lettuce/core/dynamic/segment/CommandSegments;
      17: areturn
      18: aload_0
      19: aload_1
      20: invokespecial #6                  // Method getLetterCase:(Lio/lettuce/core/dynamic/CommandMethod;)Lio/lettuce/core/dynamic/annotation/CommandNaming$LetterCase;
      23: astore_2
      24: aload_0
      25: aload_1
      26: invokespecial #7                  // Method getNamingStrategy:(Lio/lettuce/core/dynamic/CommandMethod;)Lio/lettuce/core/dynamic/annotation/CommandNaming$Strategy;
      29: astore_3
      30: aload_0
      31: aload_1
      32: invokeinterface #8,  1            // InterfaceMethod io/lettuce/core/dynamic/CommandMethod.getName:()Ljava/lang/String;
      37: aload_3
      38: invokespecial #9                  // Method parseMethodName:(Ljava/lang/String;Lio/lettuce/core/dynamic/annotation/CommandNaming$Strategy;)Ljava/util/List;
      41: astore        4
      43: aload_0
      44: aload         4
      46: aload_2
      47: invokespecial #10                 // Method createCommandSegments:(Ljava/util/List;Lio/lettuce/core/dynamic/annotation/CommandNaming$LetterCase;)Lio/lettuce/core/dynamic/segment/CommandSegments;
      50: areturn

  private io.lettuce.core.dynamic.segment.CommandSegments createCommandSegments(java.util.List<java.lang.String>, io.lettuce.core.dynamic.annotation.CommandNaming$LetterCase);
    Code:
       0: new           #11                 // class java/util/ArrayList
       3: dup
       4: aload_1
       5: invokeinterface #12,  1           // InterfaceMethod java/util/List.size:()I
      10: invokespecial #13                 // Method java/util/ArrayList."<init>":(I)V
      13: astore_3
      14: aload_1
      15: invokeinterface #14,  1           // InterfaceMethod java/util/List.iterator:()Ljava/util/Iterator;
      20: astore        4
      22: aload         4
      24: invokeinterface #15,  1           // InterfaceMethod java/util/Iterator.hasNext:()Z
      29: ifeq          84
      32: aload         4
      34: invokeinterface #16,  1           // InterfaceMethod java/util/Iterator.next:()Ljava/lang/Object;
      39: checkcast     #17                 // class java/lang/String
      42: astore        5
      44: aload_2
      45: getstatic     #18                 // Field io/lettuce/core/dynamic/annotation/CommandNaming$LetterCase.AS_IS:Lio/lettuce/core/dynamic/annotation/CommandNaming$LetterCase;
      48: if_acmpne     66
      51: aload_3
      52: aload         5
      54: invokestatic  #19                 // Method io/lettuce/core/dynamic/segment/CommandSegment.constant:(Ljava/lang/String;)Lio/lettuce/core/dynamic/segment/CommandSegment;
      57: invokeinterface #20,  2           // InterfaceMethod java/util/List.add:(Ljava/lang/Object;)Z
      62: pop
      63: goto          81
      66: aload_3
      67: aload         5
      69: invokevirtual #21                 // Method java/lang/String.toUpperCase:()Ljava/lang/String;
      72: invokestatic  #19                 // Method io/lettuce/core/dynamic/segment/CommandSegment.constant:(Ljava/lang/String;)Lio/lettuce/core/dynamic/segment/CommandSegment;
      75: invokeinterface #20,  2           // InterfaceMethod java/util/List.add:(Ljava/lang/Object;)Z
      80: pop
      81: goto          22
      84: new           #22                 // class io/lettuce/core/dynamic/segment/CommandSegments
      87: dup
      88: aload_3
      89: invokespecial #23                 // Method io/lettuce/core/dynamic/segment/CommandSegments."<init>":(Ljava/util/List;)V
      92: areturn

  private java.util.List<java.lang.String> parseMethodName(java.lang.String, io.lettuce.core.dynamic.annotation.CommandNaming$Strategy);
    Code:
       0: aload_2
       1: getstatic     #24                 // Field io/lettuce/core/dynamic/annotation/CommandNaming$Strategy.METHOD_NAME:Lio/lettuce/core/dynamic/annotation/CommandNaming$Strategy;
       4: if_acmpne     12
       7: aload_1
       8: invokestatic  #25                 // Method java/util/Collections.singletonList:(Ljava/lang/Object;)Ljava/util/List;
      11: areturn
      12: new           #11                 // class java/util/ArrayList
      15: dup
      16: invokespecial #26                 // Method java/util/ArrayList."<init>":()V
      19: astore_3
      20: aload_1
      21: invokevirtual #27                 // Method java/lang/String.toCharArray:()[C
      24: astore        4
      26: iconst_0
      27: istore        5
      29: new           #28                 // class java/lang/StringBuffer
      32: dup
      33: aload         4
      35: arraylength
      36: invokespecial #29                 // Method java/lang/StringBuffer."<init>":(I)V
      39: astore        6
      41: aload         4
      43: astore        7
      45: aload         7
      47: arraylength
      48: istore        8
      50: iconst_0
      51: istore        9
      53: iload         9
      55: iload         8
      57: if_icmpge     165
      60: aload         7
      62: iload         9
      64: caload
      65: istore        10
      67: iload         10
      69: invokestatic  #30                 // Method java/lang/Character.isUpperCase:(C)Z
      72: ifne          89
      75: aload         6
      77: iload         10
      79: invokevirtual #31                 // Method java/lang/StringBuffer.append:(C)Ljava/lang/StringBuffer;
      82: pop
      83: iconst_0
      84: istore        5
      86: goto          159
      89: iload         5
      91: ifne          148
      94: aload         6
      96: invokestatic  #32                 // Method io/lettuce/core/LettuceStrings.isEmpty:(Ljava/lang/CharSequence;)Z
      99: ifne          148
     102: aload_2
     103: getstatic     #33                 // Field io/lettuce/core/dynamic/annotation/CommandNaming$Strategy.DOT:Lio/lettuce/core/dynamic/annotation/CommandNaming$Strategy;
     106: if_acmpne     117
     109: aload         6
     111: bipush        46
     113: invokevirtual #31                 // Method java/lang/StringBuffer.append:(C)Ljava/lang/StringBuffer;
     116: pop
     117: aload_2
     118: getstatic     #34                 // Field io/lettuce/core/dynamic/annotation/CommandNaming$Strategy.SPLIT:Lio/lettuce/core/dynamic/annotation/CommandNaming$Strategy;
     121: if_acmpne     148
     124: aload_3
     125: aload         6
     127: invokevirtual #35                 // Method java/lang/StringBuffer.toString:()Ljava/lang/String;
     130: invokeinterface #20,  2           // InterfaceMethod java/util/List.add:(Ljava/lang/Object;)Z
     135: pop
     136: new           #28                 // class java/lang/StringBuffer
     139: dup
     140: aload         4
     142: arraylength
     143: invokespecial #29                 // Method java/lang/StringBuffer."<init>":(I)V
     146: astore        6
     148: iconst_1
     149: istore        5
     151: aload         6
     153: iload         10
     155: invokevirtual #31                 // Method java/lang/StringBuffer.append:(C)Ljava/lang/StringBuffer;
     158: pop
     159: iinc          9, 1
     162: goto          53
     165: aload         6
     167: invokestatic  #36                 // Method io/lettuce/core/LettuceStrings.isNotEmpty:(Ljava/lang/CharSequence;)Z
     170: ifeq          185
     173: aload_3
     174: aload         6
     176: invokevirtual #35                 // Method java/lang/StringBuffer.toString:()Ljava/lang/String;
     179: invokeinterface #20,  2           // InterfaceMethod java/util/List.add:(Ljava/lang/Object;)Z
     184: pop
     185: aload_3
     186: areturn

  private io.lettuce.core.dynamic.annotation.CommandNaming$LetterCase getLetterCase(io.lettuce.core.dynamic.CommandMethod);
    Code:
       0: aload_1
       1: ldc           #37                 // class io/lettuce/core/dynamic/annotation/CommandNaming
       3: invokeinterface #38,  2           // InterfaceMethod io/lettuce/core/dynamic/CommandMethod.hasAnnotation:(Ljava/lang/Class;)Z
       8: ifeq          40
      11: aload_1
      12: invokeinterface #39,  1           // InterfaceMethod io/lettuce/core/dynamic/CommandMethod.getMethod:()Ljava/lang/reflect/Method;
      17: ldc           #37                 // class io/lettuce/core/dynamic/annotation/CommandNaming
      19: invokevirtual #40                 // Method java/lang/reflect/Method.getAnnotation:(Ljava/lang/Class;)Ljava/lang/annotation/Annotation;
      22: checkcast     #37                 // class io/lettuce/core/dynamic/annotation/CommandNaming
      25: invokeinterface #41,  1           // InterfaceMethod io/lettuce/core/dynamic/annotation/CommandNaming.letterCase:()Lio/lettuce/core/dynamic/annotation/CommandNaming$LetterCase;
      30: astore_2
      31: aload_2
      32: getstatic     #42                 // Field io/lettuce/core/dynamic/annotation/CommandNaming$LetterCase.DEFAULT:Lio/lettuce/core/dynamic/annotation/CommandNaming$LetterCase;
      35: if_acmpeq     40
      38: aload_2
      39: areturn
      40: aload_1
      41: invokeinterface #39,  1           // InterfaceMethod io/lettuce/core/dynamic/CommandMethod.getMethod:()Ljava/lang/reflect/Method;
      46: invokevirtual #43                 // Method java/lang/reflect/Method.getDeclaringClass:()Ljava/lang/Class;
      49: astore_2
      50: aload_2
      51: ldc           #37                 // class io/lettuce/core/dynamic/annotation/CommandNaming
      53: invokevirtual #44                 // Method java/lang/Class.getAnnotation:(Ljava/lang/Class;)Ljava/lang/annotation/Annotation;
      56: checkcast     #37                 // class io/lettuce/core/dynamic/annotation/CommandNaming
      59: astore_3
      60: aload_3
      61: ifnull        83
      64: aload_3
      65: invokeinterface #41,  1           // InterfaceMethod io/lettuce/core/dynamic/annotation/CommandNaming.letterCase:()Lio/lettuce/core/dynamic/annotation/CommandNaming$LetterCase;
      70: getstatic     #42                 // Field io/lettuce/core/dynamic/annotation/CommandNaming$LetterCase.DEFAULT:Lio/lettuce/core/dynamic/annotation/CommandNaming$LetterCase;
      73: if_acmpeq     83
      76: aload_3
      77: invokeinterface #41,  1           // InterfaceMethod io/lettuce/core/dynamic/annotation/CommandNaming.letterCase:()Lio/lettuce/core/dynamic/annotation/CommandNaming$LetterCase;
      82: areturn
      83: getstatic     #45                 // Field io/lettuce/core/dynamic/annotation/CommandNaming$LetterCase.UPPERCASE:Lio/lettuce/core/dynamic/annotation/CommandNaming$LetterCase;
      86: areturn

  private io.lettuce.core.dynamic.annotation.CommandNaming$Strategy getNamingStrategy(io.lettuce.core.dynamic.CommandMethod);
    Code:
       0: aload_1
       1: ldc           #37                 // class io/lettuce/core/dynamic/annotation/CommandNaming
       3: invokeinterface #38,  2           // InterfaceMethod io/lettuce/core/dynamic/CommandMethod.hasAnnotation:(Ljava/lang/Class;)Z
       8: ifeq          40
      11: aload_1
      12: invokeinterface #39,  1           // InterfaceMethod io/lettuce/core/dynamic/CommandMethod.getMethod:()Ljava/lang/reflect/Method;
      17: ldc           #37                 // class io/lettuce/core/dynamic/annotation/CommandNaming
      19: invokevirtual #40                 // Method java/lang/reflect/Method.getAnnotation:(Ljava/lang/Class;)Ljava/lang/annotation/Annotation;
      22: checkcast     #37                 // class io/lettuce/core/dynamic/annotation/CommandNaming
      25: invokeinterface #46,  1           // InterfaceMethod io/lettuce/core/dynamic/annotation/CommandNaming.strategy:()Lio/lettuce/core/dynamic/annotation/CommandNaming$Strategy;
      30: astore_2
      31: aload_2
      32: getstatic     #47                 // Field io/lettuce/core/dynamic/annotation/CommandNaming$Strategy.DEFAULT:Lio/lettuce/core/dynamic/annotation/CommandNaming$Strategy;
      35: if_acmpeq     40
      38: aload_2
      39: areturn
      40: aload_1
      41: invokeinterface #39,  1           // InterfaceMethod io/lettuce/core/dynamic/CommandMethod.getMethod:()Ljava/lang/reflect/Method;
      46: invokevirtual #43                 // Method java/lang/reflect/Method.getDeclaringClass:()Ljava/lang/Class;
      49: astore_2
      50: aload_2
      51: ldc           #37                 // class io/lettuce/core/dynamic/annotation/CommandNaming
      53: invokevirtual #44                 // Method java/lang/Class.getAnnotation:(Ljava/lang/Class;)Ljava/lang/annotation/Annotation;
      56: checkcast     #37                 // class io/lettuce/core/dynamic/annotation/CommandNaming
      59: astore_3
      60: aload_3
      61: ifnull        83
      64: aload_3
      65: invokeinterface #46,  1           // InterfaceMethod io/lettuce/core/dynamic/annotation/CommandNaming.strategy:()Lio/lettuce/core/dynamic/annotation/CommandNaming$Strategy;
      70: getstatic     #47                 // Field io/lettuce/core/dynamic/annotation/CommandNaming$Strategy.DEFAULT:Lio/lettuce/core/dynamic/annotation/CommandNaming$Strategy;
      73: if_acmpeq     83
      76: aload_3
      77: invokeinterface #46,  1           // InterfaceMethod io/lettuce/core/dynamic/annotation/CommandNaming.strategy:()Lio/lettuce/core/dynamic/annotation/CommandNaming$Strategy;
      82: areturn
      83: getstatic     #34                 // Field io/lettuce/core/dynamic/annotation/CommandNaming$Strategy.SPLIT:Lio/lettuce/core/dynamic/annotation/CommandNaming$Strategy;
      86: areturn

  static java.util.regex.Pattern access$100();
    Code:
       0: getstatic     #1                  // Field SPACE:Ljava/util/regex/Pattern;
       3: areturn

  static {};
    Code:
       0: ldc           #48                 // String \\s
       2: invokestatic  #49                 // Method java/util/regex/Pattern.compile:(Ljava/lang/String;)Ljava/util/regex/Pattern;
       5: putstatic     #1                  // Field SPACE:Ljava/util/regex/Pattern;
       8: return
}
