Compiled from "CommandSegment.java"
public abstract class io.lettuce.core.dynamic.segment.CommandSegment {
  public io.lettuce.core.dynamic.segment.CommandSegment();
    Code:
       0: aload_0
       1: invokespecial #1                  // Method java/lang/Object."<init>":()V
       4: return

  public static io.lettuce.core.dynamic.segment.CommandSegment constant(java.lang.String);
    Code:
       0: new           #2                  // class io/lettuce/core/dynamic/segment/CommandSegment$Constant
       3: dup
       4: aload_0
       5: invokespecial #3                  // Method io/lettuce/core/dynamic/segment/CommandSegment$Constant."<init>":(Ljava/lang/String;)V
       8: areturn

  public static io.lettuce.core.dynamic.segment.CommandSegment namedParameter(java.lang.String);
    Code:
       0: new           #4                  // class io/lettuce/core/dynamic/segment/CommandSegment$NamedParameter
       3: dup
       4: aload_0
       5: invokespecial #5                  // Method io/lettuce/core/dynamic/segment/CommandSegment$NamedParameter."<init>":(Ljava/lang/String;)V
       8: areturn

  public static io.lettuce.core.dynamic.segment.CommandSegment indexedParameter(int);
    Code:
       0: new           #6                  // class io/lettuce/core/dynamic/segment/CommandSegment$IndexedParameter
       3: dup
       4: iload_0
       5: invokespecial #7                  // Method io/lettuce/core/dynamic/segment/CommandSegment$IndexedParameter."<init>":(I)V
       8: areturn

  public abstract java.lang.String asString();

  public abstract io.lettuce.core.dynamic.segment.CommandSegment$ArgumentContribution contribute(io.lettuce.core.dynamic.parameter.MethodParametersAccessor);

  public java.lang.String toString();
    Code:
       0: new           #8                  // class java/lang/StringBuffer
       3: dup
       4: invokespecial #9                  // Method java/lang/StringBuffer."<init>":()V
       7: astore_1
       8: aload_1
       9: aload_0
      10: invokevirtual #10                 // Method java/lang/Object.getClass:()Ljava/lang/Class;
      13: invokevirtual #11                 // Method java/lang/Class.getSimpleName:()Ljava/lang/String;
      16: invokevirtual #12                 // Method java/lang/StringBuffer.append:(Ljava/lang/String;)Ljava/lang/StringBuffer;
      19: pop
      20: aload_1
      21: ldc           #13                 // String
      23: invokevirtual #12                 // Method java/lang/StringBuffer.append:(Ljava/lang/String;)Ljava/lang/StringBuffer;
      26: aload_0
      27: invokevirtual #14                 // Method asString:()Ljava/lang/String;
      30: invokevirtual #12                 // Method java/lang/StringBuffer.append:(Ljava/lang/String;)Ljava/lang/StringBuffer;
      33: pop
      34: aload_1
      35: invokevirtual #15                 // Method java/lang/StringBuffer.toString:()Ljava/lang/String;
      38: areturn
}
