Compiled from "InetUtils.java"
public class org.springframework.cloud.commons.util.InetUtils implements java.io.Closeable {
  private final java.util.concurrent.ExecutorService executorService;

  private final org.springframework.cloud.commons.util.InetUtilsProperties properties;

  private final org.apache.commons.logging.Log log;

  public org.springframework.cloud.commons.util.InetUtils(org.springframework.cloud.commons.util.InetUtilsProperties);
    Code:
       0: aload_0
       1: invokespecial #1                  // Method java/lang/Object."<init>":()V
       4: aload_0
       5: ldc           #2                  // class org/springframework/cloud/commons/util/InetUtils
       7: invokestatic  #3                  // Method org/apache/commons/logging/LogFactory.getLog:(Ljava/lang/Class;)Lorg/apache/commons/logging/Log;
      10: putfield      #4                  // Field log:Lorg/apache/commons/logging/Log;
      13: aload_0
      14: aload_1
      15: putfield      #5                  // Field properties:Lorg/springframework/cloud/commons/util/InetUtilsProperties;
      18: aload_0
      19: invokedynamic #6,  0              // InvokeDynamic #0:newThread:()Ljava/util/concurrent/ThreadFactory;
      24: invokestatic  #7                  // Method java/util/concurrent/Executors.newSingleThreadExecutor:(Ljava/util/concurrent/ThreadFactory;)Ljava/util/concurrent/ExecutorService;
      27: putfield      #8                  // Field executorService:Ljava/util/concurrent/ExecutorService;
      30: return

  public void close();
    Code:
       0: aload_0
       1: getfield      #8                  // Field executorService:Ljava/util/concurrent/ExecutorService;
       4: invokeinterface #9,  1            // InterfaceMethod java/util/concurrent/ExecutorService.shutdown:()V
       9: return

  public org.springframework.cloud.commons.util.InetUtils$HostInfo findFirstNonLoopbackHostInfo();
    Code:
       0: aload_0
       1: invokevirtual #10                 // Method findFirstNonLoopbackAddress:()Ljava/net/InetAddress;
       4: astore_1
       5: aload_1
       6: ifnull        15
       9: aload_0
      10: aload_1
      11: invokevirtual #11                 // Method convertAddress:(Ljava/net/InetAddress;)Lorg/springframework/cloud/commons/util/InetUtils$HostInfo;
      14: areturn
      15: new           #12                 // class org/springframework/cloud/commons/util/InetUtils$HostInfo
      18: dup
      19: invokespecial #13                 // Method org/springframework/cloud/commons/util/InetUtils$HostInfo."<init>":()V
      22: astore_2
      23: aload_2
      24: aload_0
      25: getfield      #5                  // Field properties:Lorg/springframework/cloud/commons/util/InetUtilsProperties;
      28: invokevirtual #14                 // Method org/springframework/cloud/commons/util/InetUtilsProperties.getDefaultHostname:()Ljava/lang/String;
      31: invokevirtual #15                 // Method org/springframework/cloud/commons/util/InetUtils$HostInfo.setHostname:(Ljava/lang/String;)V
      34: aload_2
      35: aload_0
      36: getfield      #5                  // Field properties:Lorg/springframework/cloud/commons/util/InetUtilsProperties;
      39: invokevirtual #16                 // Method org/springframework/cloud/commons/util/InetUtilsProperties.getDefaultIpAddress:()Ljava/lang/String;
      42: invokevirtual #17                 // Method org/springframework/cloud/commons/util/InetUtils$HostInfo.setIpAddress:(Ljava/lang/String;)V
      45: aload_2
      46: areturn

  public java.net.InetAddress findFirstNonLoopbackAddress();
    Code:
       0: aconst_null
       1: astore_1
       2: ldc           #19                 // int 2147483647
       4: istore_2
       5: invokestatic  #20                 // Method java/net/NetworkInterface.getNetworkInterfaces:()Ljava/util/Enumeration;
       8: astore_3
       9: aload_3
      10: invokeinterface #21,  1           // InterfaceMethod java/util/Enumeration.hasMoreElements:()Z
      15: ifeq          205
      18: aload_3
      19: invokeinterface #22,  1           // InterfaceMethod java/util/Enumeration.nextElement:()Ljava/lang/Object;
      24: checkcast     #23                 // class java/net/NetworkInterface
      27: astore        4
      29: aload         4
      31: invokevirtual #24                 // Method java/net/NetworkInterface.isUp:()Z
      34: ifeq          202
      37: aload_0
      38: getfield      #4                  // Field log:Lorg/apache/commons/logging/Log;
      41: new           #25                 // class java/lang/StringBuilder
      44: dup
      45: invokespecial #26                 // Method java/lang/StringBuilder."<init>":()V
      48: ldc           #27                 // String Testing interface:
      50: invokevirtual #28                 // Method java/lang/StringBuilder.append:(Ljava/lang/String;)Ljava/lang/StringBuilder;
      53: aload         4
      55: invokevirtual #29                 // Method java/net/NetworkInterface.getDisplayName:()Ljava/lang/String;
      58: invokevirtual #28                 // Method java/lang/StringBuilder.append:(Ljava/lang/String;)Ljava/lang/StringBuilder;
      61: invokevirtual #30                 // Method java/lang/StringBuilder.toString:()Ljava/lang/String;
      64: invokeinterface #31,  2           // InterfaceMethod org/apache/commons/logging/Log.trace:(Ljava/lang/Object;)V
      69: aload         4
      71: invokevirtual #32                 // Method java/net/NetworkInterface.getIndex:()I
      74: iload_2
      75: if_icmplt     82
      78: aload_1
      79: ifnonnull     91
      82: aload         4
      84: invokevirtual #32                 // Method java/net/NetworkInterface.getIndex:()I
      87: istore_2
      88: goto          98
      91: aload_1
      92: ifnull        98
      95: goto          9
      98: aload_0
      99: aload         4
     101: invokevirtual #29                 // Method java/net/NetworkInterface.getDisplayName:()Ljava/lang/String;
     104: invokevirtual #33                 // Method ignoreInterface:(Ljava/lang/String;)Z
     107: ifne          202
     110: aload         4
     112: invokevirtual #34                 // Method java/net/NetworkInterface.getInetAddresses:()Ljava/util/Enumeration;
     115: astore        5
     117: aload         5
     119: invokeinterface #21,  1           // InterfaceMethod java/util/Enumeration.hasMoreElements:()Z
     124: ifeq          202
     127: aload         5
     129: invokeinterface #22,  1           // InterfaceMethod java/util/Enumeration.nextElement:()Ljava/lang/Object;
     134: checkcast     #35                 // class java/net/InetAddress
     137: astore        6
     139: aload         6
     141: instanceof    #36                 // class java/net/Inet4Address
     144: ifeq          199
     147: aload         6
     149: invokevirtual #37                 // Method java/net/InetAddress.isLoopbackAddress:()Z
     152: ifne          199
     155: aload_0
     156: aload         6
     158: invokevirtual #38                 // Method isPreferredAddress:(Ljava/net/InetAddress;)Z
     161: ifeq          199
     164: aload_0
     165: getfield      #4                  // Field log:Lorg/apache/commons/logging/Log;
     168: new           #25                 // class java/lang/StringBuilder
     171: dup
     172: invokespecial #26                 // Method java/lang/StringBuilder."<init>":()V
     175: ldc           #39                 // String Found non-loopback interface:
     177: invokevirtual #28                 // Method java/lang/StringBuilder.append:(Ljava/lang/String;)Ljava/lang/StringBuilder;
     180: aload         4
     182: invokevirtual #29                 // Method java/net/NetworkInterface.getDisplayName:()Ljava/lang/String;
     185: invokevirtual #28                 // Method java/lang/StringBuilder.append:(Ljava/lang/String;)Ljava/lang/StringBuilder;
     188: invokevirtual #30                 // Method java/lang/StringBuilder.toString:()Ljava/lang/String;
     191: invokeinterface #31,  2           // InterfaceMethod org/apache/commons/logging/Log.trace:(Ljava/lang/Object;)V
     196: aload         6
     198: astore_1
     199: goto          117
     202: goto          9
     205: goto          221
     208: astore_2
     209: aload_0
     210: getfield      #4                  // Field log:Lorg/apache/commons/logging/Log;
     213: ldc           #41                 // String Cannot get first non-loopback address
     215: aload_2
     216: invokeinterface #42,  3           // InterfaceMethod org/apache/commons/logging/Log.error:(Ljava/lang/Object;Ljava/lang/Throwable;)V
     221: aload_1
     222: ifnull        227
     225: aload_1
     226: areturn
     227: invokestatic  #43                 // Method java/net/InetAddress.getLocalHost:()Ljava/net/InetAddress;
     230: areturn
     231: astore_2
     232: aload_0
     233: getfield      #4                  // Field log:Lorg/apache/commons/logging/Log;
     236: ldc           #45                 // String Unable to retrieve localhost
     238: invokeinterface #46,  2           // InterfaceMethod org/apache/commons/logging/Log.warn:(Ljava/lang/Object;)V
     243: aconst_null
     244: areturn
    Exception table:
       from    to  target type
           2   205   208   Class java/io/IOException
         227   230   231   Class java/net/UnknownHostException

  boolean isPreferredAddress(java.net.InetAddress);
    Code:
       0: aload_0
       1: getfield      #5                  // Field properties:Lorg/springframework/cloud/commons/util/InetUtilsProperties;
       4: invokevirtual #47                 // Method org/springframework/cloud/commons/util/InetUtilsProperties.isUseOnlySiteLocalInterfaces:()Z
       7: ifeq          52
      10: aload_1
      11: invokevirtual #48                 // Method java/net/InetAddress.isSiteLocalAddress:()Z
      14: istore_2
      15: iload_2
      16: ifne          50
      19: aload_0
      20: getfield      #4                  // Field log:Lorg/apache/commons/logging/Log;
      23: new           #25                 // class java/lang/StringBuilder
      26: dup
      27: invokespecial #26                 // Method java/lang/StringBuilder."<init>":()V
      30: ldc           #49                 // String Ignoring address:
      32: invokevirtual #28                 // Method java/lang/StringBuilder.append:(Ljava/lang/String;)Ljava/lang/StringBuilder;
      35: aload_1
      36: invokevirtual #50                 // Method java/net/InetAddress.getHostAddress:()Ljava/lang/String;
      39: invokevirtual #28                 // Method java/lang/StringBuilder.append:(Ljava/lang/String;)Ljava/lang/StringBuilder;
      42: invokevirtual #30                 // Method java/lang/StringBuilder.toString:()Ljava/lang/String;
      45: invokeinterface #31,  2           // InterfaceMethod org/apache/commons/logging/Log.trace:(Ljava/lang/Object;)V
      50: iload_2
      51: ireturn
      52: aload_0
      53: getfield      #5                  // Field properties:Lorg/springframework/cloud/commons/util/InetUtilsProperties;
      56: invokevirtual #51                 // Method org/springframework/cloud/commons/util/InetUtilsProperties.getPreferredNetworks:()Ljava/util/List;
      59: astore_2
      60: aload_2
      61: invokeinterface #52,  1           // InterfaceMethod java/util/List.isEmpty:()Z
      66: ifeq          71
      69: iconst_1
      70: ireturn
      71: aload_2
      72: invokeinterface #53,  1           // InterfaceMethod java/util/List.iterator:()Ljava/util/Iterator;
      77: astore_3
      78: aload_3
      79: invokeinterface #54,  1           // InterfaceMethod java/util/Iterator.hasNext:()Z
      84: ifeq          129
      87: aload_3
      88: invokeinterface #55,  1           // InterfaceMethod java/util/Iterator.next:()Ljava/lang/Object;
      93: checkcast     #56                 // class java/lang/String
      96: astore        4
      98: aload_1
      99: invokevirtual #50                 // Method java/net/InetAddress.getHostAddress:()Ljava/lang/String;
     102: astore        5
     104: aload         5
     106: aload         4
     108: invokevirtual #57                 // Method java/lang/String.matches:(Ljava/lang/String;)Z
     111: ifne          124
     114: aload         5
     116: aload         4
     118: invokevirtual #58                 // Method java/lang/String.startsWith:(Ljava/lang/String;)Z
     121: ifeq          126
     124: iconst_1
     125: ireturn
     126: goto          78
     129: aload_0
     130: getfield      #4                  // Field log:Lorg/apache/commons/logging/Log;
     133: new           #25                 // class java/lang/StringBuilder
     136: dup
     137: invokespecial #26                 // Method java/lang/StringBuilder."<init>":()V
     140: ldc           #49                 // String Ignoring address:
     142: invokevirtual #28                 // Method java/lang/StringBuilder.append:(Ljava/lang/String;)Ljava/lang/StringBuilder;
     145: aload_1
     146: invokevirtual #50                 // Method java/net/InetAddress.getHostAddress:()Ljava/lang/String;
     149: invokevirtual #28                 // Method java/lang/StringBuilder.append:(Ljava/lang/String;)Ljava/lang/StringBuilder;
     152: invokevirtual #30                 // Method java/lang/StringBuilder.toString:()Ljava/lang/String;
     155: invokeinterface #31,  2           // InterfaceMethod org/apache/commons/logging/Log.trace:(Ljava/lang/Object;)V
     160: iconst_0
     161: ireturn

  boolean ignoreInterface(java.lang.String);
    Code:
       0: aload_0
       1: getfield      #5                  // Field properties:Lorg/springframework/cloud/commons/util/InetUtilsProperties;
       4: invokevirtual #59                 // Method org/springframework/cloud/commons/util/InetUtilsProperties.getIgnoredInterfaces:()Ljava/util/List;
       7: invokeinterface #53,  1           // InterfaceMethod java/util/List.iterator:()Ljava/util/Iterator;
      12: astore_2
      13: aload_2
      14: invokeinterface #54,  1           // InterfaceMethod java/util/Iterator.hasNext:()Z
      19: ifeq          73
      22: aload_2
      23: invokeinterface #55,  1           // InterfaceMethod java/util/Iterator.next:()Ljava/lang/Object;
      28: checkcast     #56                 // class java/lang/String
      31: astore_3
      32: aload_1
      33: aload_3
      34: invokevirtual #57                 // Method java/lang/String.matches:(Ljava/lang/String;)Z
      37: ifeq          70
      40: aload_0
      41: getfield      #4                  // Field log:Lorg/apache/commons/logging/Log;
      44: new           #25                 // class java/lang/StringBuilder
      47: dup
      48: invokespecial #26                 // Method java/lang/StringBuilder."<init>":()V
      51: ldc           #60                 // String Ignoring interface:
      53: invokevirtual #28                 // Method java/lang/StringBuilder.append:(Ljava/lang/String;)Ljava/lang/StringBuilder;
      56: aload_1
      57: invokevirtual #28                 // Method java/lang/StringBuilder.append:(Ljava/lang/String;)Ljava/lang/StringBuilder;
      60: invokevirtual #30                 // Method java/lang/StringBuilder.toString:()Ljava/lang/String;
      63: invokeinterface #31,  2           // InterfaceMethod org/apache/commons/logging/Log.trace:(Ljava/lang/Object;)V
      68: iconst_1
      69: ireturn
      70: goto          13
      73: iconst_0
      74: ireturn

  public org.springframework.cloud.commons.util.InetUtils$HostInfo convertAddress(java.net.InetAddress);
    Code:
       0: new           #12                 // class org/springframework/cloud/commons/util/InetUtils$HostInfo
       3: dup
       4: invokespecial #13                 // Method org/springframework/cloud/commons/util/InetUtils$HostInfo."<init>":()V
       7: astore_2
       8: aload_0
       9: getfield      #8                  // Field executorService:Ljava/util/concurrent/ExecutorService;
      12: aload_1
      13: dup
      14: invokevirtual #61                 // Method java/lang/Object.getClass:()Ljava/lang/Class;
      17: pop
      18: invokedynamic #62,  0             // InvokeDynamic #1:call:(Ljava/net/InetAddress;)Ljava/util/concurrent/Callable;
      23: invokeinterface #63,  2           // InterfaceMethod java/util/concurrent/ExecutorService.submit:(Ljava/util/concurrent/Callable;)Ljava/util/concurrent/Future;
      28: astore_3
      29: aload_3
      30: aload_0
      31: getfield      #5                  // Field properties:Lorg/springframework/cloud/commons/util/InetUtilsProperties;
      34: invokevirtual #64                 // Method org/springframework/cloud/commons/util/InetUtilsProperties.getTimeoutSeconds:()I
      37: i2l
      38: getstatic     #65                 // Field java/util/concurrent/TimeUnit.SECONDS:Ljava/util/concurrent/TimeUnit;
      41: invokeinterface #66,  4           // InterfaceMethod java/util/concurrent/Future.get:(JLjava/util/concurrent/TimeUnit;)Ljava/lang/Object;
      46: checkcast     #56                 // class java/lang/String
      49: astore        4
      51: goto          71
      54: astore        5
      56: aload_0
      57: getfield      #4                  // Field log:Lorg/apache/commons/logging/Log;
      60: ldc           #68                 // String Cannot determine local hostname
      62: invokeinterface #69,  2           // InterfaceMethod org/apache/commons/logging/Log.info:(Ljava/lang/Object;)V
      67: ldc           #70                 // String localhost
      69: astore        4
      71: aload_2
      72: aload         4
      74: invokevirtual #15                 // Method org/springframework/cloud/commons/util/InetUtils$HostInfo.setHostname:(Ljava/lang/String;)V
      77: aload_2
      78: aload_1
      79: invokevirtual #50                 // Method java/net/InetAddress.getHostAddress:()Ljava/lang/String;
      82: invokevirtual #17                 // Method org/springframework/cloud/commons/util/InetUtils$HostInfo.setIpAddress:(Ljava/lang/String;)V
      85: aload_2
      86: areturn
    Exception table:
       from    to  target type
          29    51    54   Class java/lang/Exception

  private static java.lang.Thread lambda$new$0(java.lang.Runnable);
    Code:
       0: new           #71                 // class java/lang/Thread
       3: dup
       4: aload_0
       5: invokespecial #72                 // Method java/lang/Thread."<init>":(Ljava/lang/Runnable;)V
       8: astore_1
       9: aload_1
      10: ldc           #74                 // String spring.cloud.inetutils
      12: invokevirtual #75                 // Method java/lang/Thread.setName:(Ljava/lang/String;)V
      15: aload_1
      16: iconst_1
      17: invokevirtual #76                 // Method java/lang/Thread.setDaemon:(Z)V
      20: aload_1
      21: areturn
}
