Compiled from "EmbeddedMetadata.java"
class org.infinispan.metadata.EmbeddedMetadata$EmbeddedExpirableMetadata extends org.infinispan.metadata.EmbeddedMetadata {
  private final long lifespan;

  private final long maxIdle;

  private org.infinispan.metadata.EmbeddedMetadata$EmbeddedExpirableMetadata(long, java.util.concurrent.TimeUnit, long, java.util.concurrent.TimeUnit, org.infinispan.container.versioning.EntryVersion);
    Code:
       0: aload_0
       1: aload         7
       3: aconst_null
       4: invokespecial #2                  // Method org/infinispan/metadata/EmbeddedMetadata."<init>":(Lorg/infinispan/container/versioning/EntryVersion;Lorg/infinispan/metadata/EmbeddedMetadata$1;)V
       7: aload_0
       8: lload_1
       9: lconst_0
      10: lcmp
      11: ifge          20
      14: ldc2_w        #3                  // long -1l
      17: goto          25
      20: aload_3
      21: lload_1
      22: invokevirtual #5                  // Method java/util/concurrent/TimeUnit.toMillis:(J)J
      25: putfield      #6                  // Field lifespan:J
      28: aload_0
      29: lload         4
      31: lconst_0
      32: lcmp
      33: ifge          42
      36: ldc2_w        #3                  // long -1l
      39: goto          49
      42: aload         6
      44: lload         4
      46: invokevirtual #5                  // Method java/util/concurrent/TimeUnit.toMillis:(J)J
      49: putfield      #7                  // Field maxIdle:J
      52: return

  public long lifespan();
    Code:
       0: aload_0
       1: getfield      #6                  // Field lifespan:J
       4: lreturn

  public long maxIdle();
    Code:
       0: aload_0
       1: getfield      #7                  // Field maxIdle:J
       4: lreturn

  public org.infinispan.metadata.Metadata$Builder builder();
    Code:
       0: new           #8                  // class org/infinispan/metadata/EmbeddedMetadata$Builder
       3: dup
       4: invokespecial #9                  // Method org/infinispan/metadata/EmbeddedMetadata$Builder."<init>":()V
       7: aload_0
       8: getfield      #6                  // Field lifespan:J
      11: invokevirtual #10                 // Method org/infinispan/metadata/EmbeddedMetadata$Builder.lifespan:(J)Lorg/infinispan/metadata/Metadata$Builder;
      14: aload_0
      15: getfield      #7                  // Field maxIdle:J
      18: invokeinterface #11,  3           // InterfaceMethod org/infinispan/metadata/Metadata$Builder.maxIdle:(J)Lorg/infinispan/metadata/Metadata$Builder;
      23: aload_0
      24: getfield      #12                 // Field version:Lorg/infinispan/container/versioning/EntryVersion;
      27: invokeinterface #13,  2           // InterfaceMethod org/infinispan/metadata/Metadata$Builder.version:(Lorg/infinispan/container/versioning/EntryVersion;)Lorg/infinispan/metadata/Metadata$Builder;
      32: areturn

  public boolean equals(java.lang.Object);
    Code:
       0: aload_0
       1: aload_1
       2: if_acmpne     7
       5: iconst_1
       6: ireturn
       7: aload_1
       8: ifnull        22
      11: aload_0
      12: invokevirtual #14                 // Method java/lang/Object.getClass:()Ljava/lang/Class;
      15: aload_1
      16: invokevirtual #14                 // Method java/lang/Object.getClass:()Ljava/lang/Class;
      19: if_acmpeq     24
      22: iconst_0
      23: ireturn
      24: aload_0
      25: aload_1
      26: invokespecial #15                 // Method org/infinispan/metadata/EmbeddedMetadata.equals:(Ljava/lang/Object;)Z
      29: ifne          34
      32: iconst_0
      33: ireturn
      34: aload_1
      35: checkcast     #16                 // class org/infinispan/metadata/EmbeddedMetadata$EmbeddedExpirableMetadata
      38: astore_2
      39: aload_0
      40: getfield      #6                  // Field lifespan:J
      43: aload_2
      44: getfield      #6                  // Field lifespan:J
      47: lcmp
      48: ifeq          53
      51: iconst_0
      52: ireturn
      53: aload_0
      54: getfield      #7                  // Field maxIdle:J
      57: aload_2
      58: getfield      #7                  // Field maxIdle:J
      61: lcmp
      62: ifeq          67
      65: iconst_0
      66: ireturn
      67: iconst_1
      68: ireturn

  public int hashCode();
    Code:
       0: aload_0
       1: invokespecial #17                 // Method org/infinispan/metadata/EmbeddedMetadata.hashCode:()I
       4: istore_1
       5: bipush        31
       7: iload_1
       8: imul
       9: aload_0
      10: getfield      #6                  // Field lifespan:J
      13: aload_0
      14: getfield      #6                  // Field lifespan:J
      17: bipush        32
      19: lushr
      20: lxor
      21: l2i
      22: iadd
      23: istore_1
      24: bipush        31
      26: iload_1
      27: imul
      28: aload_0
      29: getfield      #7                  // Field maxIdle:J
      32: aload_0
      33: getfield      #7                  // Field maxIdle:J
      36: bipush        32
      38: lushr
      39: lxor
      40: l2i
      41: iadd
      42: istore_1
      43: iload_1
      44: ireturn

  public java.lang.String toString();
    Code:
       0: new           #18                 // class java/lang/StringBuilder
       3: dup
       4: invokespecial #19                 // Method java/lang/StringBuilder."<init>":()V
       7: ldc           #20                 // String EmbeddedExpirableMetadata{lifespan=
       9: invokevirtual #21                 // Method java/lang/StringBuilder.append:(Ljava/lang/String;)Ljava/lang/StringBuilder;
      12: aload_0
      13: getfield      #6                  // Field lifespan:J
      16: invokevirtual #22                 // Method java/lang/StringBuilder.append:(J)Ljava/lang/StringBuilder;
      19: ldc           #23                 // String , maxIdle=
      21: invokevirtual #21                 // Method java/lang/StringBuilder.append:(Ljava/lang/String;)Ljava/lang/StringBuilder;
      24: aload_0
      25: getfield      #7                  // Field maxIdle:J
      28: invokevirtual #22                 // Method java/lang/StringBuilder.append:(J)Ljava/lang/StringBuilder;
      31: ldc           #24                 // String , version=
      33: invokevirtual #21                 // Method java/lang/StringBuilder.append:(Ljava/lang/String;)Ljava/lang/StringBuilder;
      36: aload_0
      37: getfield      #12                 // Field version:Lorg/infinispan/container/versioning/EntryVersion;
      40: invokevirtual #25                 // Method java/lang/StringBuilder.append:(Ljava/lang/Object;)Ljava/lang/StringBuilder;
      43: bipush        125
      45: invokevirtual #26                 // Method java/lang/StringBuilder.append:(C)Ljava/lang/StringBuilder;
      48: invokevirtual #27                 // Method java/lang/StringBuilder.toString:()Ljava/lang/String;
      51: areturn

  org.infinispan.metadata.EmbeddedMetadata$EmbeddedExpirableMetadata(long, java.util.concurrent.TimeUnit, long, java.util.concurrent.TimeUnit, org.infinispan.container.versioning.EntryVersion, org.infinispan.metadata.EmbeddedMetadata$1);
    Code:
       0: aload_0
       1: lload_1
       2: aload_3
       3: lload         4
       5: aload         6
       7: aload         7
       9: invokespecial #1                  // Method "<init>":(JLjava/util/concurrent/TimeUnit;JLjava/util/concurrent/TimeUnit;Lorg/infinispan/container/versioning/EntryVersion;)V
      12: return
}
