Compiled from "Str2Bytes_GBK.java"
public class cn.sowjz.souwen.v1.util.Str2Bytes_GBK extends cn.sowjz.souwen.v1.util.String2Bytes {
  public cn.sowjz.souwen.v1.util.Str2Bytes_GBK();
    Code:
       0: aload_0
       1: ldc           #2                  // String GBK
       3: invokespecial #3                  // Method cn/sowjz/souwen/v1/util/String2Bytes."<init>":(Ljava/lang/String;)V
       6: return

  public byte[] toBytes(java.lang.String) throws java.io.UnsupportedEncodingException;
    Code:
       0: aload_1
       1: ifnonnull     6
       4: aconst_null
       5: areturn
       6: new           #4                  // class cn/sowjz/souwen/v1/util/ByteBuff
       9: dup
      10: invokespecial #5                  // Method cn/sowjz/souwen/v1/util/ByteBuff."<init>":()V
      13: astore_2
      14: iconst_0
      15: istore_3
      16: iload_3
      17: aload_1
      18: invokevirtual #6                  // Method java/lang/String.length:()I
      21: if_icmpge     93
      24: aload_1
      25: iload_3
      26: iload_3
      27: iconst_1
      28: iadd
      29: invokevirtual #7                  // Method java/lang/String.substring:(II)Ljava/lang/String;
      32: astore        4
      34: aload         4
      36: aload_0
      37: getfield      #8                  // Field charset:Ljava/lang/String;
      40: invokevirtual #9                  // Method java/lang/String.getBytes:(Ljava/lang/String;)[B
      43: astore        5
      45: new           #10                 // class java/lang/String
      48: dup
      49: aload         5
      51: aload_0
      52: getfield      #8                  // Field charset:Ljava/lang/String;
      55: invokespecial #11                 // Method java/lang/String."<init>":([BLjava/lang/String;)V
      58: astore        6
      60: aload         4
      62: aload         6
      64: invokevirtual #12                 // Method java/lang/String.equals:(Ljava/lang/Object;)Z
      67: ifeq          80
      70: aload_2
      71: aload         5
      73: invokevirtual #13                 // Method cn/sowjz/souwen/v1/util/ByteBuff.append:([B)Lcn/sowjz/souwen/v1/util/ByteBuff;
      76: pop
      77: goto          87
      80: aload_2
      81: bipush        32
      83: invokevirtual #14                 // Method cn/sowjz/souwen/v1/util/ByteBuff.append:(B)Lcn/sowjz/souwen/v1/util/ByteBuff;
      86: pop
      87: iinc          3, 1
      90: goto          16
      93: aload_2
      94: invokevirtual #15                 // Method cn/sowjz/souwen/v1/util/ByteBuff.getBytes:()[B
      97: areturn

  public static void main(java.lang.String[]) throws java.lang.Exception;
    Code:
       0: new           #16                 // class cn/sowjz/souwen/v1/util/Str2Bytes_GBK
       3: dup
       4: invokespecial #17                 // Method "<init>":()V
       7: astore_1
       8: new           #10                 // class java/lang/String
      11: dup
      12: aload_1
      13: ldc           #18                 // String ;    中新网兴国6月19日电18日?
      15: invokevirtual #19                 // Method toBytes:(Ljava/lang/String;)[B
      18: ldc           #2                  // String GBK
      20: invokespecial #11                 // Method java/lang/String."<init>":([BLjava/lang/String;)V
      23: astore_2
      24: getstatic     #20                 // Field java/lang/System.out:Ljava/io/PrintStream;
      27: aload_2
      28: invokevirtual #21                 // Method java/io/PrintStream.println:(Ljava/lang/String;)V
      31: return
}
