Compiled from "String2Bytes.java"
public class cn.sowjz.souwen.v1.util.String2Bytes {
  java.lang.String charset;

  protected cn.sowjz.souwen.v1.util.String2Bytes(java.lang.String);
    Code:
       0: aload_0
       1: invokespecial #1                  // Method java/lang/Object."<init>":()V
       4: aload_0
       5: aload_1
       6: putfield      #2                  // Field charset:Ljava/lang/String;
       9: return

  public static cn.sowjz.souwen.v1.util.String2Bytes getInstance(java.lang.String);
    Code:
       0: ldc           #4                  // String GBK
       2: aload_0
       3: invokevirtual #5                  // Method java/lang/String.equalsIgnoreCase:(Ljava/lang/String;)Z
       6: ifeq          17
       9: new           #6                  // class cn/sowjz/souwen/v1/util/Str2Bytes_GBK
      12: dup
      13: invokespecial #7                  // Method cn/sowjz/souwen/v1/util/Str2Bytes_GBK."<init>":()V
      16: areturn
      17: new           #8                  // class cn/sowjz/souwen/v1/util/String2Bytes
      20: dup
      21: aload_0
      22: invokespecial #9                  // Method "<init>":(Ljava/lang/String;)V
      25: areturn

  public byte[] toBytes(java.lang.String) throws java.io.UnsupportedEncodingException;
    Code:
       0: aload_1
       1: ifnonnull     6
       4: aconst_null
       5: areturn
       6: aload_1
       7: aload_0
       8: getfield      #2                  // Field charset:Ljava/lang/String;
      11: invokevirtual #10                 // Method java/lang/String.getBytes:(Ljava/lang/String;)[B
      14: areturn

  public java.lang.String toStr(byte[], int, int) throws java.io.UnsupportedEncodingException;
    Code:
       0: aload_1
       1: ifnonnull     6
       4: aconst_null
       5: areturn
       6: new           #11                 // class java/lang/String
       9: dup
      10: aload_1
      11: iload_2
      12: iload_3
      13: aload_0
      14: getfield      #2                  // Field charset:Ljava/lang/String;
      17: invokespecial #12                 // Method java/lang/String."<init>":([BIILjava/lang/String;)V
      20: areturn
}
