Compiled from "VConvert.java"
public class cn.sowjz.souwen.v1.util.VConvert {
  public cn.sowjz.souwen.v1.util.VConvert();
    Code:
       0: aload_0
       1: invokespecial #1                  // Method java/lang/Object."<init>":()V
       4: return

  public static byte str2Byte(java.lang.String);
    Code:
       0: aload_0
       1: ifnull        14
       4: aload_0
       5: invokevirtual #2                  // Method java/lang/String.trim:()Ljava/lang/String;
       8: invokevirtual #3                  // Method java/lang/String.length:()I
      11: ifne          16
      14: iconst_0
      15: ireturn
      16: aload_0
      17: ldc           #4                  // String 0x
      19: invokevirtual #5                  // Method java/lang/String.startsWith:(Ljava/lang/String;)Z
      22: ifeq          36
      25: aload_0
      26: iconst_2
      27: invokevirtual #6                  // Method java/lang/String.substring:(I)Ljava/lang/String;
      30: bipush        16
      32: invokestatic  #7                  // Method java/lang/Byte.parseByte:(Ljava/lang/String;I)B
      35: ireturn
      36: aload_0
      37: invokestatic  #8                  // Method java/lang/Byte.parseByte:(Ljava/lang/String;)B
      40: ireturn

  public static short str2Short(java.lang.String);
    Code:
       0: aload_0
       1: ifnull        14
       4: aload_0
       5: invokevirtual #2                  // Method java/lang/String.trim:()Ljava/lang/String;
       8: invokevirtual #3                  // Method java/lang/String.length:()I
      11: ifne          16
      14: iconst_0
      15: ireturn
      16: aload_0
      17: ldc           #4                  // String 0x
      19: invokevirtual #5                  // Method java/lang/String.startsWith:(Ljava/lang/String;)Z
      22: ifeq          36
      25: aload_0
      26: iconst_2
      27: invokevirtual #6                  // Method java/lang/String.substring:(I)Ljava/lang/String;
      30: bipush        16
      32: invokestatic  #9                  // Method java/lang/Short.parseShort:(Ljava/lang/String;I)S
      35: ireturn
      36: aload_0
      37: invokestatic  #10                 // Method java/lang/Short.parseShort:(Ljava/lang/String;)S
      40: ireturn

  public static int str2Int(java.lang.String);
    Code:
       0: aload_0
       1: ifnull        14
       4: aload_0
       5: invokevirtual #2                  // Method java/lang/String.trim:()Ljava/lang/String;
       8: invokevirtual #3                  // Method java/lang/String.length:()I
      11: ifne          16
      14: iconst_0
      15: ireturn
      16: aload_0
      17: ldc           #4                  // String 0x
      19: invokevirtual #5                  // Method java/lang/String.startsWith:(Ljava/lang/String;)Z
      22: ifeq          36
      25: aload_0
      26: iconst_2
      27: invokevirtual #6                  // Method java/lang/String.substring:(I)Ljava/lang/String;
      30: bipush        16
      32: invokestatic  #11                 // Method java/lang/Integer.parseUnsignedInt:(Ljava/lang/String;I)I
      35: ireturn
      36: aload_0
      37: invokestatic  #12                 // Method java/lang/Integer.parseInt:(Ljava/lang/String;)I
      40: ireturn

  public static long str2Long(java.lang.String);
    Code:
       0: aload_0
       1: ifnull        14
       4: aload_0
       5: invokevirtual #2                  // Method java/lang/String.trim:()Ljava/lang/String;
       8: invokevirtual #3                  // Method java/lang/String.length:()I
      11: ifne          16
      14: lconst_0
      15: lreturn
      16: aload_0
      17: ldc           #4                  // String 0x
      19: invokevirtual #5                  // Method java/lang/String.startsWith:(Ljava/lang/String;)Z
      22: ifeq          36
      25: aload_0
      26: iconst_2
      27: invokevirtual #6                  // Method java/lang/String.substring:(I)Ljava/lang/String;
      30: bipush        16
      32: invokestatic  #13                 // Method java/lang/Long.parseUnsignedLong:(Ljava/lang/String;I)J
      35: lreturn
      36: aload_0
      37: invokestatic  #14                 // Method java/lang/Long.parseLong:(Ljava/lang/String;)J
      40: lreturn

  public static float str2Float(java.lang.String);
    Code:
       0: aload_0
       1: ifnull        14
       4: aload_0
       5: invokevirtual #2                  // Method java/lang/String.trim:()Ljava/lang/String;
       8: invokevirtual #3                  // Method java/lang/String.length:()I
      11: ifne          16
      14: fconst_0
      15: freturn
      16: aload_0
      17: invokestatic  #15                 // Method java/lang/Float.parseFloat:(Ljava/lang/String;)F
      20: freturn

  public static double str2Double(java.lang.String);
    Code:
       0: aload_0
       1: ifnull        14
       4: aload_0
       5: invokevirtual #2                  // Method java/lang/String.trim:()Ljava/lang/String;
       8: invokevirtual #3                  // Method java/lang/String.length:()I
      11: ifne          16
      14: dconst_0
      15: dreturn
      16: aload_0
      17: invokestatic  #16                 // Method java/lang/Double.parseDouble:(Ljava/lang/String;)D
      20: dreturn

  public static boolean str2Bool(java.lang.String);
    Code:
       0: aload_0
       1: ifnull        14
       4: aload_0
       5: invokevirtual #2                  // Method java/lang/String.trim:()Ljava/lang/String;
       8: invokevirtual #3                  // Method java/lang/String.length:()I
      11: ifne          16
      14: iconst_0
      15: ireturn
      16: aload_0
      17: invokevirtual #2                  // Method java/lang/String.trim:()Ljava/lang/String;
      20: ldc           #17                 // String true
      22: invokevirtual #18                 // Method java/lang/String.equalsIgnoreCase:(Ljava/lang/String;)Z
      25: ifeq          30
      28: iconst_1
      29: ireturn
      30: aload_0
      31: invokevirtual #2                  // Method java/lang/String.trim:()Ljava/lang/String;
      34: ldc           #19                 // String 1
      36: invokevirtual #20                 // Method java/lang/String.equals:(Ljava/lang/Object;)Z
      39: ifeq          44
      42: iconst_1
      43: ireturn
      44: iconst_0
      45: ireturn

  public static byte[] str2Bytes(java.lang.String, java.lang.String) throws java.io.IOException;
    Code:
       0: aconst_null
       1: aload_1
       2: if_acmpne     10
       5: aload_0
       6: invokevirtual #21                 // Method java/lang/String.getBytes:()[B
       9: areturn
      10: aload_0
      11: aload_1
      12: invokevirtual #22                 // Method java/lang/String.getBytes:(Ljava/lang/String;)[B
      15: areturn

  public static byte[] joinBytes(byte[], byte[]);
    Code:
       0: aload_0
       1: arraylength
       2: istore_2
       3: aload_1
       4: arraylength
       5: istore_3
       6: iload_2
       7: iload_3
       8: iadd
       9: newarray       byte
      11: astore        4
      13: iconst_0
      14: istore        5
      16: iload         5
      18: iload_2
      19: if_icmpge     37
      22: aload         4
      24: iload         5
      26: aload_0
      27: iload         5
      29: baload
      30: bastore
      31: iinc          5, 1
      34: goto          16
      37: iconst_0
      38: istore        5
      40: iload         5
      42: iload_3
      43: if_icmpge     63
      46: aload         4
      48: iload_2
      49: iload         5
      51: iadd
      52: aload_1
      53: iload         5
      55: baload
      56: bastore
      57: iinc          5, 1
      60: goto          40
      63: aload         4
      65: areturn

  public static byte[] long2Bytes(long);
    Code:
       0: bipush        8
       2: newarray       byte
       4: astore_2
       5: iconst_0
       6: istore_3
       7: iload_3
       8: aload_2
       9: arraylength
      10: if_icmpge     34
      13: aload_2
      14: iload_3
      15: lload_0
      16: iload_3
      17: bipush        8
      19: imul
      20: lshr
      21: ldc2_w        #23                 // long 255l
      24: land
      25: l2i
      26: i2b
      27: bastore
      28: iinc          3, 1
      31: goto          7
      34: aload_2
      35: areturn

  public static boolean long2Bool(long);
    Code:
       0: lload_0
       1: lconst_0
       2: lcmp
       3: ifne          8
       6: iconst_0
       7: ireturn
       8: iconst_1
       9: ireturn

  public static long bytes2Long(byte[]);
    Code:
       0: aload_0
       1: iconst_0
       2: invokestatic  #25                 // Method bytes2Long:([BI)J
       5: lreturn

  public static long bytes2Long(byte[], int);
    Code:
       0: lconst_0
       1: lstore_2
       2: iconst_0
       3: istore        4
       5: iload         4
       7: bipush        8
       9: if_icmpge     38
      12: lload_2
      13: aload_0
      14: iload_1
      15: iload         4
      17: iadd
      18: baload
      19: i2l
      20: ldc2_w        #23                 // long 255l
      23: land
      24: iload         4
      26: bipush        8
      28: imul
      29: lshl
      30: ladd
      31: lstore_2
      32: iinc          4, 1
      35: goto          5
      38: lload_2
      39: lreturn

  public static byte[] int2Bytes(int);
    Code:
       0: iconst_4
       1: newarray       byte
       3: astore_1
       4: iconst_0
       5: istore_2
       6: iload_2
       7: aload_1
       8: arraylength
       9: if_icmpge     32
      12: aload_1
      13: iload_2
      14: iload_0
      15: iload_2
      16: bipush        8
      18: imul
      19: ishr
      20: sipush        255
      23: iand
      24: i2b
      25: bastore
      26: iinc          2, 1
      29: goto          6
      32: aload_1
      33: areturn

  public static boolean int2Bool(int);
    Code:
       0: iload_0
       1: ifne          6
       4: iconst_0
       5: ireturn
       6: iconst_1
       7: ireturn

  public static int bytes2Int(byte[]);
    Code:
       0: aload_0
       1: iconst_0
       2: invokestatic  #26                 // Method bytes2Int:([BI)I
       5: ireturn

  public static int bytes2Int(byte[], int);
    Code:
       0: iconst_0
       1: istore_2
       2: iconst_0
       3: istore_3
       4: iload_3
       5: iconst_4
       6: if_icmpge     35
       9: iload_2
      10: i2l
      11: aload_0
      12: iload_1
      13: iload_3
      14: iadd
      15: baload
      16: sipush        255
      19: iand
      20: iload_3
      21: bipush        8
      23: imul
      24: ishl
      25: i2l
      26: ladd
      27: l2i
      28: istore_2
      29: iinc          3, 1
      32: goto          4
      35: iload_2
      36: ireturn

  public static double bytes2double(byte[], int);
    Code:
       0: lconst_0
       1: lstore_2
       2: iconst_0
       3: istore        4
       5: iload         4
       7: bipush        8
       9: if_icmpge     38
      12: lload_2
      13: aload_0
      14: iload         4
      16: iload_1
      17: iadd
      18: baload
      19: sipush        255
      22: iand
      23: i2l
      24: bipush        8
      26: iload         4
      28: imul
      29: lshl
      30: lor
      31: lstore_2
      32: iinc          4, 1
      35: goto          5
      38: lload_2
      39: invokestatic  #27                 // Method java/lang/Double.longBitsToDouble:(J)D
      42: dreturn

  public static boolean byte2Bool(byte);
    Code:
       0: iload_0
       1: ifne          6
       4: iconst_0
       5: ireturn
       6: iconst_1
       7: ireturn

  public static byte bool2Byte(boolean);
    Code:
       0: iload_0
       1: ifne          6
       4: iconst_0
       5: ireturn
       6: iconst_1
       7: ireturn

  public static java.lang.String str2Filepath(java.lang.String);
    Code:
       0: aload_0
       1: ifnull        14
       4: aload_0
       5: invokevirtual #2                  // Method java/lang/String.trim:()Ljava/lang/String;
       8: invokevirtual #3                  // Method java/lang/String.length:()I
      11: ifne          16
      14: aload_0
      15: areturn
      16: ldc           #28                 // String file.separator
      18: invokestatic  #29                 // Method java/lang/System.getProperty:(Ljava/lang/String;)Ljava/lang/String;
      21: astore_1
      22: aload_0
      23: ldc           #30                 // String \\
      25: invokevirtual #31                 // Method java/lang/String.endsWith:(Ljava/lang/String;)Z
      28: ifne          59
      31: aload_0
      32: ldc           #32                 // String /
      34: invokevirtual #31                 // Method java/lang/String.endsWith:(Ljava/lang/String;)Z
      37: ifne          59
      40: new           #33                 // class java/lang/StringBuilder
      43: dup
      44: invokespecial #34                 // Method java/lang/StringBuilder."<init>":()V
      47: aload_0
      48: invokevirtual #35                 // Method java/lang/StringBuilder.append:(Ljava/lang/String;)Ljava/lang/StringBuilder;
      51: aload_1
      52: invokevirtual #35                 // Method java/lang/StringBuilder.append:(Ljava/lang/String;)Ljava/lang/StringBuilder;
      55: invokevirtual #36                 // Method java/lang/StringBuilder.toString:()Ljava/lang/String;
      58: astore_0
      59: aload_0
      60: areturn

  public static java.lang.String str2Webpath(java.lang.String);
    Code:
       0: aload_0
       1: ifnull        14
       4: aload_0
       5: invokevirtual #2                  // Method java/lang/String.trim:()Ljava/lang/String;
       8: invokevirtual #3                  // Method java/lang/String.length:()I
      11: ifne          16
      14: aload_0
      15: areturn
      16: aload_0
      17: ldc           #32                 // String /
      19: invokevirtual #31                 // Method java/lang/String.endsWith:(Ljava/lang/String;)Z
      22: ifne          45
      25: new           #33                 // class java/lang/StringBuilder
      28: dup
      29: invokespecial #34                 // Method java/lang/StringBuilder."<init>":()V
      32: aload_0
      33: invokevirtual #35                 // Method java/lang/StringBuilder.append:(Ljava/lang/String;)Ljava/lang/StringBuilder;
      36: ldc           #32                 // String /
      38: invokevirtual #35                 // Method java/lang/StringBuilder.append:(Ljava/lang/String;)Ljava/lang/StringBuilder;
      41: invokevirtual #36                 // Method java/lang/StringBuilder.toString:()Ljava/lang/String;
      44: astore_0
      45: aload_0
      46: areturn

  public static java.lang.String byteArrayToHex(byte[]);
    Code:
       0: aload_0
       1: ifnonnull     6
       4: aconst_null
       5: areturn
       6: new           #37                 // class java/lang/StringBuffer
       9: dup
      10: invokespecial #38                 // Method java/lang/StringBuffer."<init>":()V
      13: astore_1
      14: iconst_0
      15: istore_2
      16: iload_2
      17: aload_0
      18: arraylength
      19: if_icmpge     58
      22: aload_0
      23: iload_2
      24: baload
      25: sipush        255
      28: iand
      29: istore_3
      30: iload_3
      31: bipush        16
      33: if_icmpge     43
      36: aload_1
      37: ldc           #39                 // String 0
      39: invokevirtual #40                 // Method java/lang/StringBuffer.append:(Ljava/lang/String;)Ljava/lang/StringBuffer;
      42: pop
      43: aload_1
      44: iload_3
      45: invokestatic  #41                 // Method java/lang/Integer.toHexString:(I)Ljava/lang/String;
      48: invokevirtual #40                 // Method java/lang/StringBuffer.append:(Ljava/lang/String;)Ljava/lang/StringBuffer;
      51: pop
      52: iinc          2, 1
      55: goto          16
      58: aload_1
      59: invokevirtual #42                 // Method java/lang/StringBuffer.toString:()Ljava/lang/String;
      62: areturn

  public static java.lang.String byteArrayToHex(byte[], int, int);
    Code:
       0: aload_0
       1: ifnonnull     6
       4: aconst_null
       5: areturn
       6: new           #37                 // class java/lang/StringBuffer
       9: dup
      10: invokespecial #38                 // Method java/lang/StringBuffer."<init>":()V
      13: astore_3
      14: iload_1
      15: istore        4
      17: iload         4
      19: aload_0
      20: arraylength
      21: if_icmpge     72
      24: iload         4
      26: iload_1
      27: iload_2
      28: iadd
      29: if_icmpge     72
      32: aload_0
      33: iload         4
      35: baload
      36: sipush        255
      39: iand
      40: istore        5
      42: iload         5
      44: bipush        16
      46: if_icmpge     56
      49: aload_3
      50: ldc           #39                 // String 0
      52: invokevirtual #40                 // Method java/lang/StringBuffer.append:(Ljava/lang/String;)Ljava/lang/StringBuffer;
      55: pop
      56: aload_3
      57: iload         5
      59: invokestatic  #41                 // Method java/lang/Integer.toHexString:(I)Ljava/lang/String;
      62: invokevirtual #40                 // Method java/lang/StringBuffer.append:(Ljava/lang/String;)Ljava/lang/StringBuffer;
      65: pop
      66: iinc          4, 1
      69: goto          17
      72: aload_3
      73: invokevirtual #42                 // Method java/lang/StringBuffer.toString:()Ljava/lang/String;
      76: areturn

  public static byte[] hexToByteArray(java.lang.String);
    Code:
       0: aload_0
       1: ifnonnull     6
       4: aconst_null
       5: areturn
       6: aload_0
       7: invokevirtual #3                  // Method java/lang/String.length:()I
      10: istore_1
      11: aload_0
      12: invokevirtual #43                 // Method java/lang/String.toUpperCase:()Ljava/lang/String;
      15: astore_0
      16: iload_1
      17: iconst_2
      18: idiv
      19: newarray       byte
      21: astore_2
      22: iconst_0
      23: istore_3
      24: iload_3
      25: iload_1
      26: iconst_2
      27: idiv
      28: if_icmpge     131
      31: aload_0
      32: iload_3
      33: iconst_2
      34: imul
      35: invokevirtual #44                 // Method java/lang/String.charAt:(I)C
      38: istore        4
      40: iload         4
      42: bipush        57
      44: if_icmpgt     61
      47: aload_2
      48: iload_3
      49: iload         4
      51: bipush        48
      53: isub
      54: iconst_4
      55: ishl
      56: i2b
      57: bastore
      58: goto          75
      61: aload_2
      62: iload_3
      63: iload         4
      65: bipush        65
      67: isub
      68: bipush        10
      70: iadd
      71: iconst_4
      72: ishl
      73: i2b
      74: bastore
      75: aload_0
      76: iload_3
      77: iconst_2
      78: imul
      79: iconst_1
      80: iadd
      81: invokevirtual #44                 // Method java/lang/String.charAt:(I)C
      84: istore        4
      86: iload         4
      88: bipush        57
      90: if_icmpgt     109
      93: aload_2
      94: iload_3
      95: dup2
      96: baload
      97: iload         4
      99: bipush        48
     101: isub
     102: i2b
     103: iadd
     104: i2b
     105: bastore
     106: goto          125
     109: aload_2
     110: iload_3
     111: dup2
     112: baload
     113: iload         4
     115: bipush        65
     117: isub
     118: bipush        10
     120: iadd
     121: i2b
     122: iadd
     123: i2b
     124: bastore
     125: iinc          3, 1
     128: goto          24
     131: aload_2
     132: areturn

  public static byte[] hexToByteArray(java.lang.String, int);
    Code:
       0: aload_0
       1: ifnonnull     6
       4: aconst_null
       5: areturn
       6: aload_0
       7: invokevirtual #43                 // Method java/lang/String.toUpperCase:()Ljava/lang/String;
      10: astore_0
      11: aload_0
      12: invokevirtual #3                  // Method java/lang/String.length:()I
      15: iload_1
      16: iload_1
      17: iadd
      18: if_icmpge     44
      21: new           #33                 // class java/lang/StringBuilder
      24: dup
      25: invokespecial #34                 // Method java/lang/StringBuilder."<init>":()V
      28: ldc           #39                 // String 0
      30: invokevirtual #35                 // Method java/lang/StringBuilder.append:(Ljava/lang/String;)Ljava/lang/StringBuilder;
      33: aload_0
      34: invokevirtual #35                 // Method java/lang/StringBuilder.append:(Ljava/lang/String;)Ljava/lang/StringBuilder;
      37: invokevirtual #36                 // Method java/lang/StringBuilder.toString:()Ljava/lang/String;
      40: astore_0
      41: goto          11
      44: iload_1
      45: newarray       byte
      47: astore_2
      48: iconst_0
      49: istore_3
      50: iload_3
      51: iload_1
      52: if_icmpge     155
      55: aload_0
      56: iload_3
      57: iconst_2
      58: imul
      59: invokevirtual #44                 // Method java/lang/String.charAt:(I)C
      62: istore        4
      64: iload         4
      66: bipush        57
      68: if_icmpgt     85
      71: aload_2
      72: iload_3
      73: iload         4
      75: bipush        48
      77: isub
      78: iconst_4
      79: ishl
      80: i2b
      81: bastore
      82: goto          99
      85: aload_2
      86: iload_3
      87: iload         4
      89: bipush        65
      91: isub
      92: bipush        10
      94: iadd
      95: iconst_4
      96: ishl
      97: i2b
      98: bastore
      99: aload_0
     100: iload_3
     101: iconst_2
     102: imul
     103: iconst_1
     104: iadd
     105: invokevirtual #44                 // Method java/lang/String.charAt:(I)C
     108: istore        4
     110: iload         4
     112: bipush        57
     114: if_icmpgt     133
     117: aload_2
     118: iload_3
     119: dup2
     120: baload
     121: iload         4
     123: bipush        48
     125: isub
     126: i2b
     127: iadd
     128: i2b
     129: bastore
     130: goto          149
     133: aload_2
     134: iload_3
     135: dup2
     136: baload
     137: iload         4
     139: bipush        65
     141: isub
     142: bipush        10
     144: iadd
     145: i2b
     146: iadd
     147: i2b
     148: bastore
     149: iinc          3, 1
     152: goto          50
     155: aload_2
     156: areturn

  public static void main(java.lang.String[]);
    Code:
       0: ldc           #45                 // String aaaaaaa
       2: astore_1
       3: aload_1
       4: invokevirtual #21                 // Method java/lang/String.getBytes:()[B
       7: invokestatic  #46                 // Method byteArrayToHex:([B)Ljava/lang/String;
      10: astore_1
      11: getstatic     #47                 // Field java/lang/System.out:Ljava/io/PrintStream;
      14: aload_1
      15: invokevirtual #48                 // Method java/io/PrintStream.println:(Ljava/lang/String;)V
      18: aload_1
      19: invokestatic  #49                 // Method hexToByteArray:(Ljava/lang/String;)[B
      22: astore_2
      23: getstatic     #47                 // Field java/lang/System.out:Ljava/io/PrintStream;
      26: new           #50                 // class java/lang/String
      29: dup
      30: aload_2
      31: invokespecial #51                 // Method java/lang/String."<init>":([B)V
      34: invokevirtual #48                 // Method java/io/PrintStream.println:(Ljava/lang/String;)V
      37: sipush        256
      40: newarray       byte
      42: astore_3
      43: iconst_0
      44: istore        4
      46: iload         4
      48: sipush        256
      51: if_icmpge     67
      54: aload_3
      55: iload         4
      57: iload         4
      59: i2b
      60: bastore
      61: iinc          4, 1
      64: goto          46
      67: getstatic     #47                 // Field java/lang/System.out:Ljava/io/PrintStream;
      70: aload_3
      71: invokestatic  #46                 // Method byteArrayToHex:([B)Ljava/lang/String;
      74: invokevirtual #48                 // Method java/io/PrintStream.println:(Ljava/lang/String;)V
      77: return
}
