Compiled from "Ansi.java"
public class io.dekorate.deps.jansi.Ansi {
  private static final char FIRST_ESC_CHAR;

  private static final char SECOND_ESC_CHAR;

  public static final java.lang.String DISABLE;

  private static java.util.concurrent.Callable<java.lang.Boolean> detector;

  private static final java.lang.InheritableThreadLocal<java.lang.Boolean> holder;

  private final java.lang.StringBuilder builder;

  private final java.util.ArrayList<java.lang.Integer> attributeOptions;

  public static void setDetector(java.util.concurrent.Callable<java.lang.Boolean>);
    Code:
       0: aload_0
       1: ifnonnull     12
       4: new           #44                 // class java/lang/IllegalArgumentException
       7: dup
       8: invokespecial #48                 // Method java/lang/IllegalArgumentException."<init>":()V
      11: athrow
      12: aload_0
      13: putstatic     #50                 // Field detector:Ljava/util/concurrent/Callable;
      16: return

  public static boolean isDetected();
    Code:
       0: getstatic     #50                 // Field detector:Ljava/util/concurrent/Callable;
       3: invokeinterface #60,  1           // InterfaceMethod java/util/concurrent/Callable.call:()Ljava/lang/Object;
       8: checkcast     #62                 // class java/lang/Boolean
      11: invokevirtual #65                 // Method java/lang/Boolean.booleanValue:()Z
      14: ireturn
      15: astore_0
      16: iconst_1
      17: ireturn
    Exception table:
       from    to  target type
           0    14    15   Class java/lang/Exception

  public static void setEnabled(boolean);
    Code:
       0: getstatic     #71                 // Field holder:Ljava/lang/InheritableThreadLocal;
       3: iload_0
       4: invokestatic  #75                 // Method java/lang/Boolean.valueOf:(Z)Ljava/lang/Boolean;
       7: invokevirtual #81                 // Method java/lang/InheritableThreadLocal.set:(Ljava/lang/Object;)V
      10: return

  public static boolean isEnabled();
    Code:
       0: getstatic     #71                 // Field holder:Ljava/lang/InheritableThreadLocal;
       3: invokevirtual #87                 // Method java/lang/InheritableThreadLocal.get:()Ljava/lang/Object;
       6: checkcast     #62                 // class java/lang/Boolean
       9: invokevirtual #65                 // Method java/lang/Boolean.booleanValue:()Z
      12: ireturn

  public static io.dekorate.deps.jansi.Ansi ansi();
    Code:
       0: invokestatic  #91                 // Method isEnabled:()Z
       3: ifeq          14
       6: new           #2                  // class io/dekorate/deps/jansi/Ansi
       9: dup
      10: invokespecial #92                 // Method "<init>":()V
      13: areturn
      14: new           #7                  // class io/dekorate/deps/jansi/Ansi$NoAnsi
      17: dup
      18: invokespecial #93                 // Method io/dekorate/deps/jansi/Ansi$NoAnsi."<init>":()V
      21: areturn

  public static io.dekorate.deps.jansi.Ansi ansi(java.lang.StringBuilder);
    Code:
       0: invokestatic  #91                 // Method isEnabled:()Z
       3: ifeq          15
       6: new           #2                  // class io/dekorate/deps/jansi/Ansi
       9: dup
      10: aload_0
      11: invokespecial #97                 // Method "<init>":(Ljava/lang/StringBuilder;)V
      14: areturn
      15: new           #7                  // class io/dekorate/deps/jansi/Ansi$NoAnsi
      18: dup
      19: aload_0
      20: invokespecial #98                 // Method io/dekorate/deps/jansi/Ansi$NoAnsi."<init>":(Ljava/lang/StringBuilder;)V
      23: areturn

  public static io.dekorate.deps.jansi.Ansi ansi(int);
    Code:
       0: invokestatic  #91                 // Method isEnabled:()Z
       3: ifeq          15
       6: new           #2                  // class io/dekorate/deps/jansi/Ansi
       9: dup
      10: iload_0
      11: invokespecial #102                // Method "<init>":(I)V
      14: areturn
      15: new           #7                  // class io/dekorate/deps/jansi/Ansi$NoAnsi
      18: dup
      19: iload_0
      20: invokespecial #103                // Method io/dekorate/deps/jansi/Ansi$NoAnsi."<init>":(I)V
      23: areturn

  public io.dekorate.deps.jansi.Ansi();
    Code:
       0: aload_0
       1: new           #107                // class java/lang/StringBuilder
       4: dup
       5: invokespecial #108                // Method java/lang/StringBuilder."<init>":()V
       8: invokespecial #97                 // Method "<init>":(Ljava/lang/StringBuilder;)V
      11: return

  public io.dekorate.deps.jansi.Ansi(io.dekorate.deps.jansi.Ansi);
    Code:
       0: aload_0
       1: new           #107                // class java/lang/StringBuilder
       4: dup
       5: aload_1
       6: getfield      #113                // Field builder:Ljava/lang/StringBuilder;
       9: invokespecial #116                // Method java/lang/StringBuilder."<init>":(Ljava/lang/CharSequence;)V
      12: invokespecial #97                 // Method "<init>":(Ljava/lang/StringBuilder;)V
      15: aload_0
      16: getfield      #118                // Field attributeOptions:Ljava/util/ArrayList;
      19: aload_1
      20: getfield      #118                // Field attributeOptions:Ljava/util/ArrayList;
      23: invokevirtual #124                // Method java/util/ArrayList.addAll:(Ljava/util/Collection;)Z
      26: pop
      27: return

  public io.dekorate.deps.jansi.Ansi(int);
    Code:
       0: aload_0
       1: new           #107                // class java/lang/StringBuilder
       4: dup
       5: iload_1
       6: invokespecial #126                // Method java/lang/StringBuilder."<init>":(I)V
       9: invokespecial #97                 // Method "<init>":(Ljava/lang/StringBuilder;)V
      12: return

  public io.dekorate.deps.jansi.Ansi(java.lang.StringBuilder);
    Code:
       0: aload_0
       1: invokespecial #127                // Method java/lang/Object."<init>":()V
       4: aload_0
       5: new           #120                // class java/util/ArrayList
       8: dup
       9: iconst_5
      10: invokespecial #128                // Method java/util/ArrayList."<init>":(I)V
      13: putfield      #118                // Field attributeOptions:Ljava/util/ArrayList;
      16: aload_0
      17: aload_1
      18: putfield      #113                // Field builder:Ljava/lang/StringBuilder;
      21: return

  public io.dekorate.deps.jansi.Ansi fg(io.dekorate.deps.jansi.Ansi$Color);
    Code:
       0: aload_0
       1: getfield      #118                // Field attributeOptions:Ljava/util/ArrayList;
       4: aload_1
       5: invokevirtual #133                // Method io/dekorate/deps/jansi/Ansi$Color.fg:()I
       8: invokestatic  #138                // Method java/lang/Integer.valueOf:(I)Ljava/lang/Integer;
      11: invokevirtual #142                // Method java/util/ArrayList.add:(Ljava/lang/Object;)Z
      14: pop
      15: aload_0
      16: areturn

  public io.dekorate.deps.jansi.Ansi fgBlack();
    Code:
       0: aload_0
       1: getstatic     #148                // Field io/dekorate/deps/jansi/Ansi$Color.BLACK:Lio/dekorate/deps/jansi/Ansi$Color;
       4: invokevirtual #150                // Method fg:(Lio/dekorate/deps/jansi/Ansi$Color;)Lio/dekorate/deps/jansi/Ansi;
       7: areturn

  public io.dekorate.deps.jansi.Ansi fgBlue();
    Code:
       0: aload_0
       1: getstatic     #154                // Field io/dekorate/deps/jansi/Ansi$Color.BLUE:Lio/dekorate/deps/jansi/Ansi$Color;
       4: invokevirtual #150                // Method fg:(Lio/dekorate/deps/jansi/Ansi$Color;)Lio/dekorate/deps/jansi/Ansi;
       7: areturn

  public io.dekorate.deps.jansi.Ansi fgCyan();
    Code:
       0: aload_0
       1: getstatic     #158                // Field io/dekorate/deps/jansi/Ansi$Color.CYAN:Lio/dekorate/deps/jansi/Ansi$Color;
       4: invokevirtual #150                // Method fg:(Lio/dekorate/deps/jansi/Ansi$Color;)Lio/dekorate/deps/jansi/Ansi;
       7: areturn

  public io.dekorate.deps.jansi.Ansi fgDefault();
    Code:
       0: aload_0
       1: getstatic     #162                // Field io/dekorate/deps/jansi/Ansi$Color.DEFAULT:Lio/dekorate/deps/jansi/Ansi$Color;
       4: invokevirtual #150                // Method fg:(Lio/dekorate/deps/jansi/Ansi$Color;)Lio/dekorate/deps/jansi/Ansi;
       7: areturn

  public io.dekorate.deps.jansi.Ansi fgGreen();
    Code:
       0: aload_0
       1: getstatic     #166                // Field io/dekorate/deps/jansi/Ansi$Color.GREEN:Lio/dekorate/deps/jansi/Ansi$Color;
       4: invokevirtual #150                // Method fg:(Lio/dekorate/deps/jansi/Ansi$Color;)Lio/dekorate/deps/jansi/Ansi;
       7: areturn

  public io.dekorate.deps.jansi.Ansi fgMagenta();
    Code:
       0: aload_0
       1: getstatic     #170                // Field io/dekorate/deps/jansi/Ansi$Color.MAGENTA:Lio/dekorate/deps/jansi/Ansi$Color;
       4: invokevirtual #150                // Method fg:(Lio/dekorate/deps/jansi/Ansi$Color;)Lio/dekorate/deps/jansi/Ansi;
       7: areturn

  public io.dekorate.deps.jansi.Ansi fgRed();
    Code:
       0: aload_0
       1: getstatic     #174                // Field io/dekorate/deps/jansi/Ansi$Color.RED:Lio/dekorate/deps/jansi/Ansi$Color;
       4: invokevirtual #150                // Method fg:(Lio/dekorate/deps/jansi/Ansi$Color;)Lio/dekorate/deps/jansi/Ansi;
       7: areturn

  public io.dekorate.deps.jansi.Ansi fgYellow();
    Code:
       0: aload_0
       1: getstatic     #178                // Field io/dekorate/deps/jansi/Ansi$Color.YELLOW:Lio/dekorate/deps/jansi/Ansi$Color;
       4: invokevirtual #150                // Method fg:(Lio/dekorate/deps/jansi/Ansi$Color;)Lio/dekorate/deps/jansi/Ansi;
       7: areturn

  public io.dekorate.deps.jansi.Ansi bg(io.dekorate.deps.jansi.Ansi$Color);
    Code:
       0: aload_0
       1: getfield      #118                // Field attributeOptions:Ljava/util/ArrayList;
       4: aload_1
       5: invokevirtual #181                // Method io/dekorate/deps/jansi/Ansi$Color.bg:()I
       8: invokestatic  #138                // Method java/lang/Integer.valueOf:(I)Ljava/lang/Integer;
      11: invokevirtual #142                // Method java/util/ArrayList.add:(Ljava/lang/Object;)Z
      14: pop
      15: aload_0
      16: areturn

  public io.dekorate.deps.jansi.Ansi bgCyan();
    Code:
       0: aload_0
       1: getstatic     #158                // Field io/dekorate/deps/jansi/Ansi$Color.CYAN:Lio/dekorate/deps/jansi/Ansi$Color;
       4: invokevirtual #150                // Method fg:(Lio/dekorate/deps/jansi/Ansi$Color;)Lio/dekorate/deps/jansi/Ansi;
       7: areturn

  public io.dekorate.deps.jansi.Ansi bgDefault();
    Code:
       0: aload_0
       1: getstatic     #162                // Field io/dekorate/deps/jansi/Ansi$Color.DEFAULT:Lio/dekorate/deps/jansi/Ansi$Color;
       4: invokevirtual #185                // Method bg:(Lio/dekorate/deps/jansi/Ansi$Color;)Lio/dekorate/deps/jansi/Ansi;
       7: areturn

  public io.dekorate.deps.jansi.Ansi bgGreen();
    Code:
       0: aload_0
       1: getstatic     #166                // Field io/dekorate/deps/jansi/Ansi$Color.GREEN:Lio/dekorate/deps/jansi/Ansi$Color;
       4: invokevirtual #185                // Method bg:(Lio/dekorate/deps/jansi/Ansi$Color;)Lio/dekorate/deps/jansi/Ansi;
       7: areturn

  public io.dekorate.deps.jansi.Ansi bgMagenta();
    Code:
       0: aload_0
       1: getstatic     #170                // Field io/dekorate/deps/jansi/Ansi$Color.MAGENTA:Lio/dekorate/deps/jansi/Ansi$Color;
       4: invokevirtual #185                // Method bg:(Lio/dekorate/deps/jansi/Ansi$Color;)Lio/dekorate/deps/jansi/Ansi;
       7: areturn

  public io.dekorate.deps.jansi.Ansi bgRed();
    Code:
       0: aload_0
       1: getstatic     #174                // Field io/dekorate/deps/jansi/Ansi$Color.RED:Lio/dekorate/deps/jansi/Ansi$Color;
       4: invokevirtual #185                // Method bg:(Lio/dekorate/deps/jansi/Ansi$Color;)Lio/dekorate/deps/jansi/Ansi;
       7: areturn

  public io.dekorate.deps.jansi.Ansi bgYellow();
    Code:
       0: aload_0
       1: getstatic     #178                // Field io/dekorate/deps/jansi/Ansi$Color.YELLOW:Lio/dekorate/deps/jansi/Ansi$Color;
       4: invokevirtual #185                // Method bg:(Lio/dekorate/deps/jansi/Ansi$Color;)Lio/dekorate/deps/jansi/Ansi;
       7: areturn

  public io.dekorate.deps.jansi.Ansi fgBright(io.dekorate.deps.jansi.Ansi$Color);
    Code:
       0: aload_0
       1: getfield      #118                // Field attributeOptions:Ljava/util/ArrayList;
       4: aload_1
       5: invokevirtual #192                // Method io/dekorate/deps/jansi/Ansi$Color.fgBright:()I
       8: invokestatic  #138                // Method java/lang/Integer.valueOf:(I)Ljava/lang/Integer;
      11: invokevirtual #142                // Method java/util/ArrayList.add:(Ljava/lang/Object;)Z
      14: pop
      15: aload_0
      16: areturn

  public io.dekorate.deps.jansi.Ansi fgBrightBlack();
    Code:
       0: aload_0
       1: getstatic     #148                // Field io/dekorate/deps/jansi/Ansi$Color.BLACK:Lio/dekorate/deps/jansi/Ansi$Color;
       4: invokevirtual #195                // Method fgBright:(Lio/dekorate/deps/jansi/Ansi$Color;)Lio/dekorate/deps/jansi/Ansi;
       7: areturn

  public io.dekorate.deps.jansi.Ansi fgBrightBlue();
    Code:
       0: aload_0
       1: getstatic     #154                // Field io/dekorate/deps/jansi/Ansi$Color.BLUE:Lio/dekorate/deps/jansi/Ansi$Color;
       4: invokevirtual #195                // Method fgBright:(Lio/dekorate/deps/jansi/Ansi$Color;)Lio/dekorate/deps/jansi/Ansi;
       7: areturn

  public io.dekorate.deps.jansi.Ansi fgBrightCyan();
    Code:
       0: aload_0
       1: getstatic     #158                // Field io/dekorate/deps/jansi/Ansi$Color.CYAN:Lio/dekorate/deps/jansi/Ansi$Color;
       4: invokevirtual #195                // Method fgBright:(Lio/dekorate/deps/jansi/Ansi$Color;)Lio/dekorate/deps/jansi/Ansi;
       7: areturn

  public io.dekorate.deps.jansi.Ansi fgBrightDefault();
    Code:
       0: aload_0
       1: getstatic     #162                // Field io/dekorate/deps/jansi/Ansi$Color.DEFAULT:Lio/dekorate/deps/jansi/Ansi$Color;
       4: invokevirtual #195                // Method fgBright:(Lio/dekorate/deps/jansi/Ansi$Color;)Lio/dekorate/deps/jansi/Ansi;
       7: areturn

  public io.dekorate.deps.jansi.Ansi fgBrightGreen();
    Code:
       0: aload_0
       1: getstatic     #166                // Field io/dekorate/deps/jansi/Ansi$Color.GREEN:Lio/dekorate/deps/jansi/Ansi$Color;
       4: invokevirtual #195                // Method fgBright:(Lio/dekorate/deps/jansi/Ansi$Color;)Lio/dekorate/deps/jansi/Ansi;
       7: areturn

  public io.dekorate.deps.jansi.Ansi fgBrightMagenta();
    Code:
       0: aload_0
       1: getstatic     #170                // Field io/dekorate/deps/jansi/Ansi$Color.MAGENTA:Lio/dekorate/deps/jansi/Ansi$Color;
       4: invokevirtual #195                // Method fgBright:(Lio/dekorate/deps/jansi/Ansi$Color;)Lio/dekorate/deps/jansi/Ansi;
       7: areturn

  public io.dekorate.deps.jansi.Ansi fgBrightRed();
    Code:
       0: aload_0
       1: getstatic     #174                // Field io/dekorate/deps/jansi/Ansi$Color.RED:Lio/dekorate/deps/jansi/Ansi$Color;
       4: invokevirtual #195                // Method fgBright:(Lio/dekorate/deps/jansi/Ansi$Color;)Lio/dekorate/deps/jansi/Ansi;
       7: areturn

  public io.dekorate.deps.jansi.Ansi fgBrightYellow();
    Code:
       0: aload_0
       1: getstatic     #178                // Field io/dekorate/deps/jansi/Ansi$Color.YELLOW:Lio/dekorate/deps/jansi/Ansi$Color;
       4: invokevirtual #195                // Method fgBright:(Lio/dekorate/deps/jansi/Ansi$Color;)Lio/dekorate/deps/jansi/Ansi;
       7: areturn

  public io.dekorate.deps.jansi.Ansi bgBright(io.dekorate.deps.jansi.Ansi$Color);
    Code:
       0: aload_0
       1: getfield      #118                // Field attributeOptions:Ljava/util/ArrayList;
       4: aload_1
       5: invokevirtual #205                // Method io/dekorate/deps/jansi/Ansi$Color.bgBright:()I
       8: invokestatic  #138                // Method java/lang/Integer.valueOf:(I)Ljava/lang/Integer;
      11: invokevirtual #142                // Method java/util/ArrayList.add:(Ljava/lang/Object;)Z
      14: pop
      15: aload_0
      16: areturn

  public io.dekorate.deps.jansi.Ansi bgBrightCyan();
    Code:
       0: aload_0
       1: getstatic     #158                // Field io/dekorate/deps/jansi/Ansi$Color.CYAN:Lio/dekorate/deps/jansi/Ansi$Color;
       4: invokevirtual #195                // Method fgBright:(Lio/dekorate/deps/jansi/Ansi$Color;)Lio/dekorate/deps/jansi/Ansi;
       7: areturn

  public io.dekorate.deps.jansi.Ansi bgBrightDefault();
    Code:
       0: aload_0
       1: getstatic     #162                // Field io/dekorate/deps/jansi/Ansi$Color.DEFAULT:Lio/dekorate/deps/jansi/Ansi$Color;
       4: invokevirtual #209                // Method bgBright:(Lio/dekorate/deps/jansi/Ansi$Color;)Lio/dekorate/deps/jansi/Ansi;
       7: areturn

  public io.dekorate.deps.jansi.Ansi bgBrightGreen();
    Code:
       0: aload_0
       1: getstatic     #166                // Field io/dekorate/deps/jansi/Ansi$Color.GREEN:Lio/dekorate/deps/jansi/Ansi$Color;
       4: invokevirtual #209                // Method bgBright:(Lio/dekorate/deps/jansi/Ansi$Color;)Lio/dekorate/deps/jansi/Ansi;
       7: areturn

  public io.dekorate.deps.jansi.Ansi bgBrightMagenta();
    Code:
       0: aload_0
       1: getstatic     #170                // Field io/dekorate/deps/jansi/Ansi$Color.MAGENTA:Lio/dekorate/deps/jansi/Ansi$Color;
       4: invokevirtual #185                // Method bg:(Lio/dekorate/deps/jansi/Ansi$Color;)Lio/dekorate/deps/jansi/Ansi;
       7: areturn

  public io.dekorate.deps.jansi.Ansi bgBrightRed();
    Code:
       0: aload_0
       1: getstatic     #174                // Field io/dekorate/deps/jansi/Ansi$Color.RED:Lio/dekorate/deps/jansi/Ansi$Color;
       4: invokevirtual #209                // Method bgBright:(Lio/dekorate/deps/jansi/Ansi$Color;)Lio/dekorate/deps/jansi/Ansi;
       7: areturn

  public io.dekorate.deps.jansi.Ansi bgBrightYellow();
    Code:
       0: aload_0
       1: getstatic     #178                // Field io/dekorate/deps/jansi/Ansi$Color.YELLOW:Lio/dekorate/deps/jansi/Ansi$Color;
       4: invokevirtual #209                // Method bgBright:(Lio/dekorate/deps/jansi/Ansi$Color;)Lio/dekorate/deps/jansi/Ansi;
       7: areturn

  public io.dekorate.deps.jansi.Ansi a(io.dekorate.deps.jansi.Ansi$Attribute);
    Code:
       0: aload_0
       1: getfield      #118                // Field attributeOptions:Ljava/util/ArrayList;
       4: aload_1
       5: invokevirtual #218                // Method io/dekorate/deps/jansi/Ansi$Attribute.value:()I
       8: invokestatic  #138                // Method java/lang/Integer.valueOf:(I)Ljava/lang/Integer;
      11: invokevirtual #142                // Method java/util/ArrayList.add:(Ljava/lang/Object;)Z
      14: pop
      15: aload_0
      16: areturn

  public io.dekorate.deps.jansi.Ansi cursor(int, int);
    Code:
       0: aload_0
       1: bipush        72
       3: iconst_2
       4: anewarray     #4                  // class java/lang/Object
       7: dup
       8: iconst_0
       9: iload_1
      10: invokestatic  #138                // Method java/lang/Integer.valueOf:(I)Ljava/lang/Integer;
      13: aastore
      14: dup
      15: iconst_1
      16: iload_2
      17: invokestatic  #138                // Method java/lang/Integer.valueOf:(I)Ljava/lang/Integer;
      20: aastore
      21: invokespecial #226                // Method appendEscapeSequence:(C[Ljava/lang/Object;)Lio/dekorate/deps/jansi/Ansi;
      24: areturn

  public io.dekorate.deps.jansi.Ansi cursorToColumn(int);
    Code:
       0: aload_0
       1: bipush        71
       3: iload_1
       4: invokespecial #232                // Method appendEscapeSequence:(CI)Lio/dekorate/deps/jansi/Ansi;
       7: areturn

  public io.dekorate.deps.jansi.Ansi cursorUp(int);
    Code:
       0: aload_0
       1: bipush        65
       3: iload_1
       4: invokespecial #232                // Method appendEscapeSequence:(CI)Lio/dekorate/deps/jansi/Ansi;
       7: areturn

  public io.dekorate.deps.jansi.Ansi cursorDown(int);
    Code:
       0: aload_0
       1: bipush        66
       3: iload_1
       4: invokespecial #232                // Method appendEscapeSequence:(CI)Lio/dekorate/deps/jansi/Ansi;
       7: areturn

  public io.dekorate.deps.jansi.Ansi cursorRight(int);
    Code:
       0: aload_0
       1: bipush        67
       3: iload_1
       4: invokespecial #232                // Method appendEscapeSequence:(CI)Lio/dekorate/deps/jansi/Ansi;
       7: areturn

  public io.dekorate.deps.jansi.Ansi cursorLeft(int);
    Code:
       0: aload_0
       1: bipush        68
       3: iload_1
       4: invokespecial #232                // Method appendEscapeSequence:(CI)Lio/dekorate/deps/jansi/Ansi;
       7: areturn

  public io.dekorate.deps.jansi.Ansi cursorDownLine();
    Code:
       0: aload_0
       1: bipush        69
       3: invokespecial #242                // Method appendEscapeSequence:(C)Lio/dekorate/deps/jansi/Ansi;
       6: areturn

  public io.dekorate.deps.jansi.Ansi cursorDownLine(int);
    Code:
       0: aload_0
       1: bipush        69
       3: iload_1
       4: invokespecial #232                // Method appendEscapeSequence:(CI)Lio/dekorate/deps/jansi/Ansi;
       7: areturn

  public io.dekorate.deps.jansi.Ansi cursorUpLine();
    Code:
       0: aload_0
       1: bipush        70
       3: invokespecial #242                // Method appendEscapeSequence:(C)Lio/dekorate/deps/jansi/Ansi;
       6: areturn

  public io.dekorate.deps.jansi.Ansi cursorUpLine(int);
    Code:
       0: aload_0
       1: bipush        70
       3: iload_1
       4: invokespecial #232                // Method appendEscapeSequence:(CI)Lio/dekorate/deps/jansi/Ansi;
       7: areturn

  public io.dekorate.deps.jansi.Ansi eraseScreen();
    Code:
       0: aload_0
       1: bipush        74
       3: getstatic     #249                // Field io/dekorate/deps/jansi/Ansi$Erase.ALL:Lio/dekorate/deps/jansi/Ansi$Erase;
       6: invokevirtual #250                // Method io/dekorate/deps/jansi/Ansi$Erase.value:()I
       9: invokespecial #232                // Method appendEscapeSequence:(CI)Lio/dekorate/deps/jansi/Ansi;
      12: areturn

  public io.dekorate.deps.jansi.Ansi eraseScreen(io.dekorate.deps.jansi.Ansi$Erase);
    Code:
       0: aload_0
       1: bipush        74
       3: aload_1
       4: invokevirtual #250                // Method io/dekorate/deps/jansi/Ansi$Erase.value:()I
       7: invokespecial #232                // Method appendEscapeSequence:(CI)Lio/dekorate/deps/jansi/Ansi;
      10: areturn

  public io.dekorate.deps.jansi.Ansi eraseLine();
    Code:
       0: aload_0
       1: bipush        75
       3: invokespecial #242                // Method appendEscapeSequence:(C)Lio/dekorate/deps/jansi/Ansi;
       6: areturn

  public io.dekorate.deps.jansi.Ansi eraseLine(io.dekorate.deps.jansi.Ansi$Erase);
    Code:
       0: aload_0
       1: bipush        75
       3: aload_1
       4: invokevirtual #250                // Method io/dekorate/deps/jansi/Ansi$Erase.value:()I
       7: invokespecial #232                // Method appendEscapeSequence:(CI)Lio/dekorate/deps/jansi/Ansi;
      10: areturn

  public io.dekorate.deps.jansi.Ansi scrollUp(int);
    Code:
       0: aload_0
       1: bipush        83
       3: iload_1
       4: invokespecial #232                // Method appendEscapeSequence:(CI)Lio/dekorate/deps/jansi/Ansi;
       7: areturn

  public io.dekorate.deps.jansi.Ansi scrollDown(int);
    Code:
       0: aload_0
       1: bipush        84
       3: iload_1
       4: invokespecial #232                // Method appendEscapeSequence:(CI)Lio/dekorate/deps/jansi/Ansi;
       7: areturn

  public io.dekorate.deps.jansi.Ansi saveCursorPosition();
    Code:
       0: aload_0
       1: bipush        115
       3: invokespecial #242                // Method appendEscapeSequence:(C)Lio/dekorate/deps/jansi/Ansi;
       6: areturn

  public io.dekorate.deps.jansi.Ansi restorCursorPosition();
    Code:
       0: aload_0
       1: bipush        117
       3: invokespecial #242                // Method appendEscapeSequence:(C)Lio/dekorate/deps/jansi/Ansi;
       6: areturn

  public io.dekorate.deps.jansi.Ansi restoreCursorPosition();
    Code:
       0: aload_0
       1: bipush        117
       3: invokespecial #242                // Method appendEscapeSequence:(C)Lio/dekorate/deps/jansi/Ansi;
       6: areturn

  public io.dekorate.deps.jansi.Ansi reset();
    Code:
       0: aload_0
       1: getstatic     #264                // Field io/dekorate/deps/jansi/Ansi$Attribute.RESET:Lio/dekorate/deps/jansi/Ansi$Attribute;
       4: invokevirtual #266                // Method a:(Lio/dekorate/deps/jansi/Ansi$Attribute;)Lio/dekorate/deps/jansi/Ansi;
       7: areturn

  public io.dekorate.deps.jansi.Ansi bold();
    Code:
       0: aload_0
       1: getstatic     #270                // Field io/dekorate/deps/jansi/Ansi$Attribute.INTENSITY_BOLD:Lio/dekorate/deps/jansi/Ansi$Attribute;
       4: invokevirtual #266                // Method a:(Lio/dekorate/deps/jansi/Ansi$Attribute;)Lio/dekorate/deps/jansi/Ansi;
       7: areturn

  public io.dekorate.deps.jansi.Ansi boldOff();
    Code:
       0: aload_0
       1: getstatic     #274                // Field io/dekorate/deps/jansi/Ansi$Attribute.INTENSITY_BOLD_OFF:Lio/dekorate/deps/jansi/Ansi$Attribute;
       4: invokevirtual #266                // Method a:(Lio/dekorate/deps/jansi/Ansi$Attribute;)Lio/dekorate/deps/jansi/Ansi;
       7: areturn

  public io.dekorate.deps.jansi.Ansi a(java.lang.String);
    Code:
       0: aload_0
       1: invokespecial #278                // Method flushAttributes:()V
       4: aload_0
       5: getfield      #113                // Field builder:Ljava/lang/StringBuilder;
       8: aload_1
       9: invokevirtual #282                // Method java/lang/StringBuilder.append:(Ljava/lang/String;)Ljava/lang/StringBuilder;
      12: pop
      13: aload_0
      14: areturn

  public io.dekorate.deps.jansi.Ansi a(boolean);
    Code:
       0: aload_0
       1: invokespecial #278                // Method flushAttributes:()V
       4: aload_0
       5: getfield      #113                // Field builder:Ljava/lang/StringBuilder;
       8: iload_1
       9: invokevirtual #286                // Method java/lang/StringBuilder.append:(Z)Ljava/lang/StringBuilder;
      12: pop
      13: aload_0
      14: areturn

  public io.dekorate.deps.jansi.Ansi a(char);
    Code:
       0: aload_0
       1: invokespecial #278                // Method flushAttributes:()V
       4: aload_0
       5: getfield      #113                // Field builder:Ljava/lang/StringBuilder;
       8: iload_1
       9: invokevirtual #289                // Method java/lang/StringBuilder.append:(C)Ljava/lang/StringBuilder;
      12: pop
      13: aload_0
      14: areturn

  public io.dekorate.deps.jansi.Ansi a(char[], int, int);
    Code:
       0: aload_0
       1: invokespecial #278                // Method flushAttributes:()V
       4: aload_0
       5: getfield      #113                // Field builder:Ljava/lang/StringBuilder;
       8: aload_1
       9: iload_2
      10: iload_3
      11: invokevirtual #293                // Method java/lang/StringBuilder.append:([CII)Ljava/lang/StringBuilder;
      14: pop
      15: aload_0
      16: areturn

  public io.dekorate.deps.jansi.Ansi a(char[]);
    Code:
       0: aload_0
       1: invokespecial #278                // Method flushAttributes:()V
       4: aload_0
       5: getfield      #113                // Field builder:Ljava/lang/StringBuilder;
       8: aload_1
       9: invokevirtual #300                // Method java/lang/StringBuilder.append:([C)Ljava/lang/StringBuilder;
      12: pop
      13: aload_0
      14: areturn

  public io.dekorate.deps.jansi.Ansi a(java.lang.CharSequence, int, int);
    Code:
       0: aload_0
       1: invokespecial #278                // Method flushAttributes:()V
       4: aload_0
       5: getfield      #113                // Field builder:Ljava/lang/StringBuilder;
       8: aload_1
       9: iload_2
      10: iload_3
      11: invokevirtual #304                // Method java/lang/StringBuilder.append:(Ljava/lang/CharSequence;II)Ljava/lang/StringBuilder;
      14: pop
      15: aload_0
      16: areturn

  public io.dekorate.deps.jansi.Ansi a(java.lang.CharSequence);
    Code:
       0: aload_0
       1: invokespecial #278                // Method flushAttributes:()V
       4: aload_0
       5: getfield      #113                // Field builder:Ljava/lang/StringBuilder;
       8: aload_1
       9: invokevirtual #311                // Method java/lang/StringBuilder.append:(Ljava/lang/CharSequence;)Ljava/lang/StringBuilder;
      12: pop
      13: aload_0
      14: areturn

  public io.dekorate.deps.jansi.Ansi a(double);
    Code:
       0: aload_0
       1: invokespecial #278                // Method flushAttributes:()V
       4: aload_0
       5: getfield      #113                // Field builder:Ljava/lang/StringBuilder;
       8: dload_1
       9: invokevirtual #315                // Method java/lang/StringBuilder.append:(D)Ljava/lang/StringBuilder;
      12: pop
      13: aload_0
      14: areturn

  public io.dekorate.deps.jansi.Ansi a(float);
    Code:
       0: aload_0
       1: invokespecial #278                // Method flushAttributes:()V
       4: aload_0
       5: getfield      #113                // Field builder:Ljava/lang/StringBuilder;
       8: fload_1
       9: invokevirtual #320                // Method java/lang/StringBuilder.append:(F)Ljava/lang/StringBuilder;
      12: pop
      13: aload_0
      14: areturn

  public io.dekorate.deps.jansi.Ansi a(int);
    Code:
       0: aload_0
       1: invokespecial #278                // Method flushAttributes:()V
       4: aload_0
       5: getfield      #113                // Field builder:Ljava/lang/StringBuilder;
       8: iload_1
       9: invokevirtual #324                // Method java/lang/StringBuilder.append:(I)Ljava/lang/StringBuilder;
      12: pop
      13: aload_0
      14: areturn

  public io.dekorate.deps.jansi.Ansi a(long);
    Code:
       0: aload_0
       1: invokespecial #278                // Method flushAttributes:()V
       4: aload_0
       5: getfield      #113                // Field builder:Ljava/lang/StringBuilder;
       8: lload_1
       9: invokevirtual #328                // Method java/lang/StringBuilder.append:(J)Ljava/lang/StringBuilder;
      12: pop
      13: aload_0
      14: areturn

  public io.dekorate.deps.jansi.Ansi a(java.lang.Object);
    Code:
       0: aload_0
       1: invokespecial #278                // Method flushAttributes:()V
       4: aload_0
       5: getfield      #113                // Field builder:Ljava/lang/StringBuilder;
       8: aload_1
       9: invokevirtual #333                // Method java/lang/StringBuilder.append:(Ljava/lang/Object;)Ljava/lang/StringBuilder;
      12: pop
      13: aload_0
      14: areturn

  public io.dekorate.deps.jansi.Ansi a(java.lang.StringBuffer);
    Code:
       0: aload_0
       1: invokespecial #278                // Method flushAttributes:()V
       4: aload_0
       5: getfield      #113                // Field builder:Ljava/lang/StringBuilder;
       8: aload_1
       9: invokevirtual #338                // Method java/lang/StringBuilder.append:(Ljava/lang/StringBuffer;)Ljava/lang/StringBuilder;
      12: pop
      13: aload_0
      14: areturn

  public io.dekorate.deps.jansi.Ansi newline();
    Code:
       0: aload_0
       1: invokespecial #278                // Method flushAttributes:()V
       4: aload_0
       5: getfield      #113                // Field builder:Ljava/lang/StringBuilder;
       8: ldc_w         #342                // String line.separator
      11: invokestatic  #348                // Method java/lang/System.getProperty:(Ljava/lang/String;)Ljava/lang/String;
      14: invokevirtual #282                // Method java/lang/StringBuilder.append:(Ljava/lang/String;)Ljava/lang/StringBuilder;
      17: pop
      18: aload_0
      19: areturn

  public io.dekorate.deps.jansi.Ansi format(java.lang.String, java.lang.Object...);
    Code:
       0: aload_0
       1: invokespecial #278                // Method flushAttributes:()V
       4: aload_0
       5: getfield      #113                // Field builder:Ljava/lang/StringBuilder;
       8: aload_1
       9: aload_2
      10: invokestatic  #355                // Method java/lang/String.format:(Ljava/lang/String;[Ljava/lang/Object;)Ljava/lang/String;
      13: invokevirtual #282                // Method java/lang/StringBuilder.append:(Ljava/lang/String;)Ljava/lang/StringBuilder;
      16: pop
      17: aload_0
      18: areturn

  public io.dekorate.deps.jansi.Ansi render(java.lang.String);
    Code:
       0: aload_0
       1: aload_1
       2: invokestatic  #363                // Method io/dekorate/deps/jansi/AnsiRenderer.render:(Ljava/lang/String;)Ljava/lang/String;
       5: invokevirtual #365                // Method a:(Ljava/lang/String;)Lio/dekorate/deps/jansi/Ansi;
       8: pop
       9: aload_0
      10: areturn

  public io.dekorate.deps.jansi.Ansi render(java.lang.String, java.lang.Object...);
    Code:
       0: aload_0
       1: aload_1
       2: invokestatic  #363                // Method io/dekorate/deps/jansi/AnsiRenderer.render:(Ljava/lang/String;)Ljava/lang/String;
       5: aload_2
       6: invokestatic  #355                // Method java/lang/String.format:(Ljava/lang/String;[Ljava/lang/Object;)Ljava/lang/String;
       9: invokevirtual #365                // Method a:(Ljava/lang/String;)Lio/dekorate/deps/jansi/Ansi;
      12: pop
      13: aload_0
      14: areturn

  public java.lang.String toString();
    Code:
       0: aload_0
       1: invokespecial #278                // Method flushAttributes:()V
       4: aload_0
       5: getfield      #113                // Field builder:Ljava/lang/StringBuilder;
       8: invokevirtual #370                // Method java/lang/StringBuilder.toString:()Ljava/lang/String;
      11: areturn

  private io.dekorate.deps.jansi.Ansi appendEscapeSequence(char);
    Code:
       0: aload_0
       1: invokespecial #278                // Method flushAttributes:()V
       4: aload_0
       5: getfield      #113                // Field builder:Ljava/lang/StringBuilder;
       8: bipush        27
      10: invokevirtual #289                // Method java/lang/StringBuilder.append:(C)Ljava/lang/StringBuilder;
      13: pop
      14: aload_0
      15: getfield      #113                // Field builder:Ljava/lang/StringBuilder;
      18: bipush        91
      20: invokevirtual #289                // Method java/lang/StringBuilder.append:(C)Ljava/lang/StringBuilder;
      23: pop
      24: aload_0
      25: getfield      #113                // Field builder:Ljava/lang/StringBuilder;
      28: iload_1
      29: invokevirtual #289                // Method java/lang/StringBuilder.append:(C)Ljava/lang/StringBuilder;
      32: pop
      33: aload_0
      34: areturn

  private io.dekorate.deps.jansi.Ansi appendEscapeSequence(char, int);
    Code:
       0: aload_0
       1: invokespecial #278                // Method flushAttributes:()V
       4: aload_0
       5: getfield      #113                // Field builder:Ljava/lang/StringBuilder;
       8: bipush        27
      10: invokevirtual #289                // Method java/lang/StringBuilder.append:(C)Ljava/lang/StringBuilder;
      13: pop
      14: aload_0
      15: getfield      #113                // Field builder:Ljava/lang/StringBuilder;
      18: bipush        91
      20: invokevirtual #289                // Method java/lang/StringBuilder.append:(C)Ljava/lang/StringBuilder;
      23: pop
      24: aload_0
      25: getfield      #113                // Field builder:Ljava/lang/StringBuilder;
      28: iload_2
      29: invokevirtual #324                // Method java/lang/StringBuilder.append:(I)Ljava/lang/StringBuilder;
      32: pop
      33: aload_0
      34: getfield      #113                // Field builder:Ljava/lang/StringBuilder;
      37: iload_1
      38: invokevirtual #289                // Method java/lang/StringBuilder.append:(C)Ljava/lang/StringBuilder;
      41: pop
      42: aload_0
      43: areturn

  private io.dekorate.deps.jansi.Ansi appendEscapeSequence(char, java.lang.Object...);
    Code:
       0: aload_0
       1: invokespecial #278                // Method flushAttributes:()V
       4: aload_0
       5: iload_1
       6: aload_2
       7: invokespecial #375                // Method _appendEscapeSequence:(C[Ljava/lang/Object;)Lio/dekorate/deps/jansi/Ansi;
      10: areturn

  private void flushAttributes();
    Code:
       0: aload_0
       1: getfield      #118                // Field attributeOptions:Ljava/util/ArrayList;
       4: invokevirtual #379                // Method java/util/ArrayList.isEmpty:()Z
       7: ifeq          11
      10: return
      11: aload_0
      12: getfield      #118                // Field attributeOptions:Ljava/util/ArrayList;
      15: invokevirtual #381                // Method java/util/ArrayList.size:()I
      18: iconst_1
      19: if_icmpne     72
      22: aload_0
      23: getfield      #118                // Field attributeOptions:Ljava/util/ArrayList;
      26: iconst_0
      27: invokevirtual #384                // Method java/util/ArrayList.get:(I)Ljava/lang/Object;
      30: checkcast     #135                // class java/lang/Integer
      33: invokevirtual #387                // Method java/lang/Integer.intValue:()I
      36: ifne          72
      39: aload_0
      40: getfield      #113                // Field builder:Ljava/lang/StringBuilder;
      43: bipush        27
      45: invokevirtual #289                // Method java/lang/StringBuilder.append:(C)Ljava/lang/StringBuilder;
      48: pop
      49: aload_0
      50: getfield      #113                // Field builder:Ljava/lang/StringBuilder;
      53: bipush        91
      55: invokevirtual #289                // Method java/lang/StringBuilder.append:(C)Ljava/lang/StringBuilder;
      58: pop
      59: aload_0
      60: getfield      #113                // Field builder:Ljava/lang/StringBuilder;
      63: bipush        109
      65: invokevirtual #289                // Method java/lang/StringBuilder.append:(C)Ljava/lang/StringBuilder;
      68: pop
      69: goto          86
      72: aload_0
      73: bipush        109
      75: aload_0
      76: getfield      #118                // Field attributeOptions:Ljava/util/ArrayList;
      79: invokevirtual #391                // Method java/util/ArrayList.toArray:()[Ljava/lang/Object;
      82: invokespecial #375                // Method _appendEscapeSequence:(C[Ljava/lang/Object;)Lio/dekorate/deps/jansi/Ansi;
      85: pop
      86: aload_0
      87: getfield      #118                // Field attributeOptions:Ljava/util/ArrayList;
      90: invokevirtual #394                // Method java/util/ArrayList.clear:()V
      93: return

  private io.dekorate.deps.jansi.Ansi _appendEscapeSequence(char, java.lang.Object...);
    Code:
       0: aload_0
       1: getfield      #113                // Field builder:Ljava/lang/StringBuilder;
       4: bipush        27
       6: invokevirtual #289                // Method java/lang/StringBuilder.append:(C)Ljava/lang/StringBuilder;
       9: pop
      10: aload_0
      11: getfield      #113                // Field builder:Ljava/lang/StringBuilder;
      14: bipush        91
      16: invokevirtual #289                // Method java/lang/StringBuilder.append:(C)Ljava/lang/StringBuilder;
      19: pop
      20: aload_2
      21: arraylength
      22: istore_3
      23: iconst_0
      24: istore        4
      26: iload         4
      28: iload_3
      29: if_icmpge     72
      32: iload         4
      34: ifeq          47
      37: aload_0
      38: getfield      #113                // Field builder:Ljava/lang/StringBuilder;
      41: bipush        59
      43: invokevirtual #289                // Method java/lang/StringBuilder.append:(C)Ljava/lang/StringBuilder;
      46: pop
      47: aload_2
      48: iload         4
      50: aaload
      51: ifnull        66
      54: aload_0
      55: getfield      #113                // Field builder:Ljava/lang/StringBuilder;
      58: aload_2
      59: iload         4
      61: aaload
      62: invokevirtual #333                // Method java/lang/StringBuilder.append:(Ljava/lang/Object;)Ljava/lang/StringBuilder;
      65: pop
      66: iinc          4, 1
      69: goto          26
      72: aload_0
      73: getfield      #113                // Field builder:Ljava/lang/StringBuilder;
      76: iload_1
      77: invokevirtual #289                // Method java/lang/StringBuilder.append:(C)Ljava/lang/StringBuilder;
      80: pop
      81: aload_0
      82: areturn

  static {};
    Code:
       0: new           #107                // class java/lang/StringBuilder
       3: dup
       4: invokespecial #108                // Method java/lang/StringBuilder."<init>":()V
       7: ldc           #2                  // class io/dekorate/deps/jansi/Ansi
       9: invokevirtual #401                // Method java/lang/Class.getName:()Ljava/lang/String;
      12: invokevirtual #282                // Method java/lang/StringBuilder.append:(Ljava/lang/String;)Ljava/lang/StringBuilder;
      15: ldc_w         #403                // String .disable
      18: invokevirtual #282                // Method java/lang/StringBuilder.append:(Ljava/lang/String;)Ljava/lang/StringBuilder;
      21: invokevirtual #370                // Method java/lang/StringBuilder.toString:()Ljava/lang/String;
      24: putstatic     #405                // Field DISABLE:Ljava/lang/String;
      27: new           #21                 // class io/dekorate/deps/jansi/Ansi$1
      30: dup
      31: invokespecial #406                // Method io/dekorate/deps/jansi/Ansi$1."<init>":()V
      34: putstatic     #50                 // Field detector:Ljava/util/concurrent/Callable;
      37: new           #19                 // class io/dekorate/deps/jansi/Ansi$2
      40: dup
      41: invokespecial #407                // Method io/dekorate/deps/jansi/Ansi$2."<init>":()V
      44: putstatic     #71                 // Field holder:Ljava/lang/InheritableThreadLocal;
      47: return
}
