Compiled from "DefaultTlsSetupHandler.java"
public final class org.apache.hc.core5.http.io.ssl.DefaultTlsSetupHandler implements org.apache.hc.core5.function.Callback<javax.net.ssl.SSLParameters> {
  public org.apache.hc.core5.http.io.ssl.DefaultTlsSetupHandler();
    Code:
       0: aload_0
       1: invokespecial #1                  // Method java/lang/Object."<init>":()V
       4: return

  public void execute(javax.net.ssl.SSLParameters);
    Code:
       0: aload_1
       1: aload_1
       2: invokevirtual #2                  // Method javax/net/ssl/SSLParameters.getProtocols:()[Ljava/lang/String;
       5: invokestatic  #3                  // Method org/apache/hc/core5/http/ssl/TLS.excludeWeak:([Ljava/lang/String;)[Ljava/lang/String;
       8: invokevirtual #4                  // Method javax/net/ssl/SSLParameters.setProtocols:([Ljava/lang/String;)V
      11: aload_1
      12: aload_1
      13: invokevirtual #5                  // Method javax/net/ssl/SSLParameters.getCipherSuites:()[Ljava/lang/String;
      16: invokestatic  #6                  // Method org/apache/hc/core5/http/ssl/TlsCiphers.excludeWeak:([Ljava/lang/String;)[Ljava/lang/String;
      19: invokevirtual #7                  // Method javax/net/ssl/SSLParameters.setCipherSuites:([Ljava/lang/String;)V
      22: return

  public void execute(java.lang.Object);
    Code:
       0: aload_0
       1: aload_1
       2: checkcast     #8                  // class javax/net/ssl/SSLParameters
       5: invokevirtual #9                  // Method execute:(Ljavax/net/ssl/SSLParameters;)V
       8: return
}
