Compiled from "ActionJsonMarshaller.java"
public class com.amazonaws.services.iot.model.transform.ActionJsonMarshaller {
  private static com.amazonaws.services.iot.model.transform.ActionJsonMarshaller instance;

  public com.amazonaws.services.iot.model.transform.ActionJsonMarshaller();
    Code:
       0: aload_0
       1: invokespecial #1                  // Method java/lang/Object."<init>":()V
       4: return

  public void marshall(com.amazonaws.services.iot.model.Action, com.amazonaws.protocol.json.StructuredJsonGenerator);
    Code:
       0: aload_1
       1: ifnonnull     14
       4: new           #2                  // class com/amazonaws/AmazonClientException
       7: dup
       8: ldc           #3                  // String Invalid argument passed to marshall(...)
      10: invokespecial #4                  // Method com/amazonaws/AmazonClientException."<init>":(Ljava/lang/String;)V
      13: athrow
      14: aload_2
      15: invokeinterface #5,  1            // InterfaceMethod com/amazonaws/protocol/json/StructuredJsonGenerator.writeStartObject:()Lcom/amazonaws/protocol/json/StructuredJsonGenerator;
      20: pop
      21: aload_1
      22: invokevirtual #6                  // Method com/amazonaws/services/iot/model/Action.getDynamoDB:()Lcom/amazonaws/services/iot/model/DynamoDBAction;
      25: ifnull        48
      28: aload_2
      29: ldc           #7                  // String dynamoDB
      31: invokeinterface #8,  2            // InterfaceMethod com/amazonaws/protocol/json/StructuredJsonGenerator.writeFieldName:(Ljava/lang/String;)Lcom/amazonaws/protocol/json/StructuredJsonGenerator;
      36: pop
      37: invokestatic  #9                  // Method com/amazonaws/services/iot/model/transform/DynamoDBActionJsonMarshaller.getInstance:()Lcom/amazonaws/services/iot/model/transform/DynamoDBActionJsonMarshaller;
      40: aload_1
      41: invokevirtual #6                  // Method com/amazonaws/services/iot/model/Action.getDynamoDB:()Lcom/amazonaws/services/iot/model/DynamoDBAction;
      44: aload_2
      45: invokevirtual #10                 // Method com/amazonaws/services/iot/model/transform/DynamoDBActionJsonMarshaller.marshall:(Lcom/amazonaws/services/iot/model/DynamoDBAction;Lcom/amazonaws/protocol/json/StructuredJsonGenerator;)V
      48: aload_1
      49: invokevirtual #11                 // Method com/amazonaws/services/iot/model/Action.getLambda:()Lcom/amazonaws/services/iot/model/LambdaAction;
      52: ifnull        75
      55: aload_2
      56: ldc           #12                 // String lambda
      58: invokeinterface #8,  2            // InterfaceMethod com/amazonaws/protocol/json/StructuredJsonGenerator.writeFieldName:(Ljava/lang/String;)Lcom/amazonaws/protocol/json/StructuredJsonGenerator;
      63: pop
      64: invokestatic  #13                 // Method com/amazonaws/services/iot/model/transform/LambdaActionJsonMarshaller.getInstance:()Lcom/amazonaws/services/iot/model/transform/LambdaActionJsonMarshaller;
      67: aload_1
      68: invokevirtual #11                 // Method com/amazonaws/services/iot/model/Action.getLambda:()Lcom/amazonaws/services/iot/model/LambdaAction;
      71: aload_2
      72: invokevirtual #14                 // Method com/amazonaws/services/iot/model/transform/LambdaActionJsonMarshaller.marshall:(Lcom/amazonaws/services/iot/model/LambdaAction;Lcom/amazonaws/protocol/json/StructuredJsonGenerator;)V
      75: aload_1
      76: invokevirtual #15                 // Method com/amazonaws/services/iot/model/Action.getSns:()Lcom/amazonaws/services/iot/model/SnsAction;
      79: ifnull        102
      82: aload_2
      83: ldc           #16                 // String sns
      85: invokeinterface #8,  2            // InterfaceMethod com/amazonaws/protocol/json/StructuredJsonGenerator.writeFieldName:(Ljava/lang/String;)Lcom/amazonaws/protocol/json/StructuredJsonGenerator;
      90: pop
      91: invokestatic  #17                 // Method com/amazonaws/services/iot/model/transform/SnsActionJsonMarshaller.getInstance:()Lcom/amazonaws/services/iot/model/transform/SnsActionJsonMarshaller;
      94: aload_1
      95: invokevirtual #15                 // Method com/amazonaws/services/iot/model/Action.getSns:()Lcom/amazonaws/services/iot/model/SnsAction;
      98: aload_2
      99: invokevirtual #18                 // Method com/amazonaws/services/iot/model/transform/SnsActionJsonMarshaller.marshall:(Lcom/amazonaws/services/iot/model/SnsAction;Lcom/amazonaws/protocol/json/StructuredJsonGenerator;)V
     102: aload_1
     103: invokevirtual #19                 // Method com/amazonaws/services/iot/model/Action.getSqs:()Lcom/amazonaws/services/iot/model/SqsAction;
     106: ifnull        129
     109: aload_2
     110: ldc           #20                 // String sqs
     112: invokeinterface #8,  2            // InterfaceMethod com/amazonaws/protocol/json/StructuredJsonGenerator.writeFieldName:(Ljava/lang/String;)Lcom/amazonaws/protocol/json/StructuredJsonGenerator;
     117: pop
     118: invokestatic  #21                 // Method com/amazonaws/services/iot/model/transform/SqsActionJsonMarshaller.getInstance:()Lcom/amazonaws/services/iot/model/transform/SqsActionJsonMarshaller;
     121: aload_1
     122: invokevirtual #19                 // Method com/amazonaws/services/iot/model/Action.getSqs:()Lcom/amazonaws/services/iot/model/SqsAction;
     125: aload_2
     126: invokevirtual #22                 // Method com/amazonaws/services/iot/model/transform/SqsActionJsonMarshaller.marshall:(Lcom/amazonaws/services/iot/model/SqsAction;Lcom/amazonaws/protocol/json/StructuredJsonGenerator;)V
     129: aload_1
     130: invokevirtual #23                 // Method com/amazonaws/services/iot/model/Action.getKinesis:()Lcom/amazonaws/services/iot/model/KinesisAction;
     133: ifnull        156
     136: aload_2
     137: ldc           #24                 // String kinesis
     139: invokeinterface #8,  2            // InterfaceMethod com/amazonaws/protocol/json/StructuredJsonGenerator.writeFieldName:(Ljava/lang/String;)Lcom/amazonaws/protocol/json/StructuredJsonGenerator;
     144: pop
     145: invokestatic  #25                 // Method com/amazonaws/services/iot/model/transform/KinesisActionJsonMarshaller.getInstance:()Lcom/amazonaws/services/iot/model/transform/KinesisActionJsonMarshaller;
     148: aload_1
     149: invokevirtual #23                 // Method com/amazonaws/services/iot/model/Action.getKinesis:()Lcom/amazonaws/services/iot/model/KinesisAction;
     152: aload_2
     153: invokevirtual #26                 // Method com/amazonaws/services/iot/model/transform/KinesisActionJsonMarshaller.marshall:(Lcom/amazonaws/services/iot/model/KinesisAction;Lcom/amazonaws/protocol/json/StructuredJsonGenerator;)V
     156: aload_1
     157: invokevirtual #27                 // Method com/amazonaws/services/iot/model/Action.getRepublish:()Lcom/amazonaws/services/iot/model/RepublishAction;
     160: ifnull        183
     163: aload_2
     164: ldc           #28                 // String republish
     166: invokeinterface #8,  2            // InterfaceMethod com/amazonaws/protocol/json/StructuredJsonGenerator.writeFieldName:(Ljava/lang/String;)Lcom/amazonaws/protocol/json/StructuredJsonGenerator;
     171: pop
     172: invokestatic  #29                 // Method com/amazonaws/services/iot/model/transform/RepublishActionJsonMarshaller.getInstance:()Lcom/amazonaws/services/iot/model/transform/RepublishActionJsonMarshaller;
     175: aload_1
     176: invokevirtual #27                 // Method com/amazonaws/services/iot/model/Action.getRepublish:()Lcom/amazonaws/services/iot/model/RepublishAction;
     179: aload_2
     180: invokevirtual #30                 // Method com/amazonaws/services/iot/model/transform/RepublishActionJsonMarshaller.marshall:(Lcom/amazonaws/services/iot/model/RepublishAction;Lcom/amazonaws/protocol/json/StructuredJsonGenerator;)V
     183: aload_1
     184: invokevirtual #31                 // Method com/amazonaws/services/iot/model/Action.getS3:()Lcom/amazonaws/services/iot/model/S3Action;
     187: ifnull        210
     190: aload_2
     191: ldc           #32                 // String s3
     193: invokeinterface #8,  2            // InterfaceMethod com/amazonaws/protocol/json/StructuredJsonGenerator.writeFieldName:(Ljava/lang/String;)Lcom/amazonaws/protocol/json/StructuredJsonGenerator;
     198: pop
     199: invokestatic  #33                 // Method com/amazonaws/services/iot/model/transform/S3ActionJsonMarshaller.getInstance:()Lcom/amazonaws/services/iot/model/transform/S3ActionJsonMarshaller;
     202: aload_1
     203: invokevirtual #31                 // Method com/amazonaws/services/iot/model/Action.getS3:()Lcom/amazonaws/services/iot/model/S3Action;
     206: aload_2
     207: invokevirtual #34                 // Method com/amazonaws/services/iot/model/transform/S3ActionJsonMarshaller.marshall:(Lcom/amazonaws/services/iot/model/S3Action;Lcom/amazonaws/protocol/json/StructuredJsonGenerator;)V
     210: aload_1
     211: invokevirtual #35                 // Method com/amazonaws/services/iot/model/Action.getFirehose:()Lcom/amazonaws/services/iot/model/FirehoseAction;
     214: ifnull        237
     217: aload_2
     218: ldc           #36                 // String firehose
     220: invokeinterface #8,  2            // InterfaceMethod com/amazonaws/protocol/json/StructuredJsonGenerator.writeFieldName:(Ljava/lang/String;)Lcom/amazonaws/protocol/json/StructuredJsonGenerator;
     225: pop
     226: invokestatic  #37                 // Method com/amazonaws/services/iot/model/transform/FirehoseActionJsonMarshaller.getInstance:()Lcom/amazonaws/services/iot/model/transform/FirehoseActionJsonMarshaller;
     229: aload_1
     230: invokevirtual #35                 // Method com/amazonaws/services/iot/model/Action.getFirehose:()Lcom/amazonaws/services/iot/model/FirehoseAction;
     233: aload_2
     234: invokevirtual #38                 // Method com/amazonaws/services/iot/model/transform/FirehoseActionJsonMarshaller.marshall:(Lcom/amazonaws/services/iot/model/FirehoseAction;Lcom/amazonaws/protocol/json/StructuredJsonGenerator;)V
     237: aload_1
     238: invokevirtual #39                 // Method com/amazonaws/services/iot/model/Action.getCloudwatchMetric:()Lcom/amazonaws/services/iot/model/CloudwatchMetricAction;
     241: ifnull        264
     244: aload_2
     245: ldc           #40                 // String cloudwatchMetric
     247: invokeinterface #8,  2            // InterfaceMethod com/amazonaws/protocol/json/StructuredJsonGenerator.writeFieldName:(Ljava/lang/String;)Lcom/amazonaws/protocol/json/StructuredJsonGenerator;
     252: pop
     253: invokestatic  #41                 // Method com/amazonaws/services/iot/model/transform/CloudwatchMetricActionJsonMarshaller.getInstance:()Lcom/amazonaws/services/iot/model/transform/CloudwatchMetricActionJsonMarshaller;
     256: aload_1
     257: invokevirtual #39                 // Method com/amazonaws/services/iot/model/Action.getCloudwatchMetric:()Lcom/amazonaws/services/iot/model/CloudwatchMetricAction;
     260: aload_2
     261: invokevirtual #42                 // Method com/amazonaws/services/iot/model/transform/CloudwatchMetricActionJsonMarshaller.marshall:(Lcom/amazonaws/services/iot/model/CloudwatchMetricAction;Lcom/amazonaws/protocol/json/StructuredJsonGenerator;)V
     264: aload_1
     265: invokevirtual #43                 // Method com/amazonaws/services/iot/model/Action.getCloudwatchAlarm:()Lcom/amazonaws/services/iot/model/CloudwatchAlarmAction;
     268: ifnull        291
     271: aload_2
     272: ldc           #44                 // String cloudwatchAlarm
     274: invokeinterface #8,  2            // InterfaceMethod com/amazonaws/protocol/json/StructuredJsonGenerator.writeFieldName:(Ljava/lang/String;)Lcom/amazonaws/protocol/json/StructuredJsonGenerator;
     279: pop
     280: invokestatic  #45                 // Method com/amazonaws/services/iot/model/transform/CloudwatchAlarmActionJsonMarshaller.getInstance:()Lcom/amazonaws/services/iot/model/transform/CloudwatchAlarmActionJsonMarshaller;
     283: aload_1
     284: invokevirtual #43                 // Method com/amazonaws/services/iot/model/Action.getCloudwatchAlarm:()Lcom/amazonaws/services/iot/model/CloudwatchAlarmAction;
     287: aload_2
     288: invokevirtual #46                 // Method com/amazonaws/services/iot/model/transform/CloudwatchAlarmActionJsonMarshaller.marshall:(Lcom/amazonaws/services/iot/model/CloudwatchAlarmAction;Lcom/amazonaws/protocol/json/StructuredJsonGenerator;)V
     291: aload_1
     292: invokevirtual #47                 // Method com/amazonaws/services/iot/model/Action.getElasticsearch:()Lcom/amazonaws/services/iot/model/ElasticsearchAction;
     295: ifnull        318
     298: aload_2
     299: ldc           #48                 // String elasticsearch
     301: invokeinterface #8,  2            // InterfaceMethod com/amazonaws/protocol/json/StructuredJsonGenerator.writeFieldName:(Ljava/lang/String;)Lcom/amazonaws/protocol/json/StructuredJsonGenerator;
     306: pop
     307: invokestatic  #49                 // Method com/amazonaws/services/iot/model/transform/ElasticsearchActionJsonMarshaller.getInstance:()Lcom/amazonaws/services/iot/model/transform/ElasticsearchActionJsonMarshaller;
     310: aload_1
     311: invokevirtual #47                 // Method com/amazonaws/services/iot/model/Action.getElasticsearch:()Lcom/amazonaws/services/iot/model/ElasticsearchAction;
     314: aload_2
     315: invokevirtual #50                 // Method com/amazonaws/services/iot/model/transform/ElasticsearchActionJsonMarshaller.marshall:(Lcom/amazonaws/services/iot/model/ElasticsearchAction;Lcom/amazonaws/protocol/json/StructuredJsonGenerator;)V
     318: aload_2
     319: invokeinterface #51,  1           // InterfaceMethod com/amazonaws/protocol/json/StructuredJsonGenerator.writeEndObject:()Lcom/amazonaws/protocol/json/StructuredJsonGenerator;
     324: pop
     325: goto          360
     328: astore_3
     329: new           #2                  // class com/amazonaws/AmazonClientException
     332: dup
     333: new           #53                 // class java/lang/StringBuilder
     336: dup
     337: invokespecial #54                 // Method java/lang/StringBuilder."<init>":()V
     340: ldc           #55                 // String Unable to marshall request to JSON:
     342: invokevirtual #56                 // Method java/lang/StringBuilder.append:(Ljava/lang/String;)Ljava/lang/StringBuilder;
     345: aload_3
     346: invokevirtual #57                 // Method java/lang/Throwable.getMessage:()Ljava/lang/String;
     349: invokevirtual #56                 // Method java/lang/StringBuilder.append:(Ljava/lang/String;)Ljava/lang/StringBuilder;
     352: invokevirtual #58                 // Method java/lang/StringBuilder.toString:()Ljava/lang/String;
     355: aload_3
     356: invokespecial #59                 // Method com/amazonaws/AmazonClientException."<init>":(Ljava/lang/String;Ljava/lang/Throwable;)V
     359: athrow
     360: return
    Exception table:
       from    to  target type
          14   325   328   Class java/lang/Throwable

  public static com.amazonaws.services.iot.model.transform.ActionJsonMarshaller getInstance();
    Code:
       0: getstatic     #60                 // Field instance:Lcom/amazonaws/services/iot/model/transform/ActionJsonMarshaller;
       3: ifnonnull     16
       6: new           #61                 // class com/amazonaws/services/iot/model/transform/ActionJsonMarshaller
       9: dup
      10: invokespecial #62                 // Method "<init>":()V
      13: putstatic     #60                 // Field instance:Lcom/amazonaws/services/iot/model/transform/ActionJsonMarshaller;
      16: getstatic     #60                 // Field instance:Lcom/amazonaws/services/iot/model/transform/ActionJsonMarshaller;
      19: areturn
}
