Compiled from "AttributeContext.java"
public final class com.google.rpc.context.AttributeContext$Auth$Builder extends com.google.protobuf.GeneratedMessageV3$Builder<com.google.rpc.context.AttributeContext$Auth$Builder> implements com.google.rpc.context.AttributeContext$AuthOrBuilder {
  private int bitField0_;

  private java.lang.Object principal_;

  private com.google.protobuf.LazyStringList audiences_;

  private java.lang.Object presenter_;

  private com.google.protobuf.Struct claims_;

  private com.google.protobuf.SingleFieldBuilderV3<com.google.protobuf.Struct, com.google.protobuf.Struct$Builder, com.google.protobuf.StructOrBuilder> claimsBuilder_;

  private com.google.protobuf.LazyStringList accessLevels_;

  public static final com.google.protobuf.Descriptors$Descriptor getDescriptor();
    Code:
       0: getstatic     #3                  // Field com/google/rpc/context/AttributeContextProto.internal_static_google_rpc_context_AttributeContext_Auth_descriptor:Lcom/google/protobuf/Descriptors$Descriptor;
       3: areturn

  protected com.google.protobuf.GeneratedMessageV3$FieldAccessorTable internalGetFieldAccessorTable();
    Code:
       0: getstatic     #4                  // Field com/google/rpc/context/AttributeContextProto.internal_static_google_rpc_context_AttributeContext_Auth_fieldAccessorTable:Lcom/google/protobuf/GeneratedMessageV3$FieldAccessorTable;
       3: ldc           #5                  // class com/google/rpc/context/AttributeContext$Auth
       5: ldc           #6                  // class com/google/rpc/context/AttributeContext$Auth$Builder
       7: invokevirtual #7                  // Method com/google/protobuf/GeneratedMessageV3$FieldAccessorTable.ensureFieldAccessorsInitialized:(Ljava/lang/Class;Ljava/lang/Class;)Lcom/google/protobuf/GeneratedMessageV3$FieldAccessorTable;
      10: areturn

  private com.google.rpc.context.AttributeContext$Auth$Builder();
    Code:
       0: aload_0
       1: invokespecial #8                  // Method com/google/protobuf/GeneratedMessageV3$Builder."<init>":()V
       4: aload_0
       5: ldc           #9                  // String
       7: putfield      #10                 // Field principal_:Ljava/lang/Object;
      10: aload_0
      11: getstatic     #11                 // Field com/google/protobuf/LazyStringArrayList.EMPTY:Lcom/google/protobuf/LazyStringList;
      14: putfield      #12                 // Field audiences_:Lcom/google/protobuf/LazyStringList;
      17: aload_0
      18: ldc           #9                  // String
      20: putfield      #13                 // Field presenter_:Ljava/lang/Object;
      23: aload_0
      24: getstatic     #11                 // Field com/google/protobuf/LazyStringArrayList.EMPTY:Lcom/google/protobuf/LazyStringList;
      27: putfield      #14                 // Field accessLevels_:Lcom/google/protobuf/LazyStringList;
      30: aload_0
      31: invokespecial #15                 // Method maybeForceBuilderInitialization:()V
      34: return

  private com.google.rpc.context.AttributeContext$Auth$Builder(com.google.protobuf.GeneratedMessageV3$BuilderParent);
    Code:
       0: aload_0
       1: aload_1
       2: invokespecial #16                 // Method com/google/protobuf/GeneratedMessageV3$Builder."<init>":(Lcom/google/protobuf/GeneratedMessageV3$BuilderParent;)V
       5: aload_0
       6: ldc           #9                  // String
       8: putfield      #10                 // Field principal_:Ljava/lang/Object;
      11: aload_0
      12: getstatic     #11                 // Field com/google/protobuf/LazyStringArrayList.EMPTY:Lcom/google/protobuf/LazyStringList;
      15: putfield      #12                 // Field audiences_:Lcom/google/protobuf/LazyStringList;
      18: aload_0
      19: ldc           #9                  // String
      21: putfield      #13                 // Field presenter_:Ljava/lang/Object;
      24: aload_0
      25: getstatic     #11                 // Field com/google/protobuf/LazyStringArrayList.EMPTY:Lcom/google/protobuf/LazyStringList;
      28: putfield      #14                 // Field accessLevels_:Lcom/google/protobuf/LazyStringList;
      31: aload_0
      32: invokespecial #15                 // Method maybeForceBuilderInitialization:()V
      35: return

  private void maybeForceBuilderInitialization();
    Code:
       0: invokestatic  #17                 // Method com/google/rpc/context/AttributeContext$Auth.access$3300:()Z
       3: ifeq          6
       6: return

  public com.google.rpc.context.AttributeContext$Auth$Builder clear();
    Code:
       0: aload_0
       1: invokespecial #18                 // Method com/google/protobuf/GeneratedMessageV3$Builder.clear:()Lcom/google/protobuf/GeneratedMessageV3$Builder;
       4: pop
       5: aload_0
       6: ldc           #9                  // String
       8: putfield      #10                 // Field principal_:Ljava/lang/Object;
      11: aload_0
      12: getstatic     #11                 // Field com/google/protobuf/LazyStringArrayList.EMPTY:Lcom/google/protobuf/LazyStringList;
      15: putfield      #12                 // Field audiences_:Lcom/google/protobuf/LazyStringList;
      18: aload_0
      19: aload_0
      20: getfield      #19                 // Field bitField0_:I
      23: bipush        -2
      25: iand
      26: putfield      #19                 // Field bitField0_:I
      29: aload_0
      30: ldc           #9                  // String
      32: putfield      #13                 // Field presenter_:Ljava/lang/Object;
      35: aload_0
      36: getfield      #20                 // Field claimsBuilder_:Lcom/google/protobuf/SingleFieldBuilderV3;
      39: ifnonnull     50
      42: aload_0
      43: aconst_null
      44: putfield      #21                 // Field claims_:Lcom/google/protobuf/Struct;
      47: goto          60
      50: aload_0
      51: aconst_null
      52: putfield      #21                 // Field claims_:Lcom/google/protobuf/Struct;
      55: aload_0
      56: aconst_null
      57: putfield      #20                 // Field claimsBuilder_:Lcom/google/protobuf/SingleFieldBuilderV3;
      60: aload_0
      61: getstatic     #11                 // Field com/google/protobuf/LazyStringArrayList.EMPTY:Lcom/google/protobuf/LazyStringList;
      64: putfield      #14                 // Field accessLevels_:Lcom/google/protobuf/LazyStringList;
      67: aload_0
      68: aload_0
      69: getfield      #19                 // Field bitField0_:I
      72: bipush        -3
      74: iand
      75: putfield      #19                 // Field bitField0_:I
      78: aload_0
      79: areturn

  public com.google.protobuf.Descriptors$Descriptor getDescriptorForType();
    Code:
       0: getstatic     #3                  // Field com/google/rpc/context/AttributeContextProto.internal_static_google_rpc_context_AttributeContext_Auth_descriptor:Lcom/google/protobuf/Descriptors$Descriptor;
       3: areturn

  public com.google.rpc.context.AttributeContext$Auth getDefaultInstanceForType();
    Code:
       0: invokestatic  #22                 // Method com/google/rpc/context/AttributeContext$Auth.getDefaultInstance:()Lcom/google/rpc/context/AttributeContext$Auth;
       3: areturn

  public com.google.rpc.context.AttributeContext$Auth build();
    Code:
       0: aload_0
       1: invokevirtual #23                 // Method buildPartial:()Lcom/google/rpc/context/AttributeContext$Auth;
       4: astore_1
       5: aload_1
       6: invokevirtual #24                 // Method com/google/rpc/context/AttributeContext$Auth.isInitialized:()Z
       9: ifne          17
      12: aload_1
      13: invokestatic  #25                 // Method newUninitializedMessageException:(Lcom/google/protobuf/Message;)Lcom/google/protobuf/UninitializedMessageException;
      16: athrow
      17: aload_1
      18: areturn

  public com.google.rpc.context.AttributeContext$Auth buildPartial();
    Code:
       0: new           #5                  // class com/google/rpc/context/AttributeContext$Auth
       3: dup
       4: aload_0
       5: aconst_null
       6: invokespecial #26                 // Method com/google/rpc/context/AttributeContext$Auth."<init>":(Lcom/google/protobuf/GeneratedMessageV3$Builder;Lcom/google/rpc/context/AttributeContext$1;)V
       9: astore_1
      10: aload_0
      11: getfield      #19                 // Field bitField0_:I
      14: istore_2
      15: aload_1
      16: aload_0
      17: getfield      #10                 // Field principal_:Ljava/lang/Object;
      20: invokestatic  #27                 // Method com/google/rpc/context/AttributeContext$Auth.access$3502:(Lcom/google/rpc/context/AttributeContext$Auth;Ljava/lang/Object;)Ljava/lang/Object;
      23: pop
      24: aload_0
      25: getfield      #19                 // Field bitField0_:I
      28: iconst_1
      29: iand
      30: ifeq          57
      33: aload_0
      34: aload_0
      35: getfield      #12                 // Field audiences_:Lcom/google/protobuf/LazyStringList;
      38: invokeinterface #28,  1           // InterfaceMethod com/google/protobuf/LazyStringList.getUnmodifiableView:()Lcom/google/protobuf/LazyStringList;
      43: putfield      #12                 // Field audiences_:Lcom/google/protobuf/LazyStringList;
      46: aload_0
      47: aload_0
      48: getfield      #19                 // Field bitField0_:I
      51: bipush        -2
      53: iand
      54: putfield      #19                 // Field bitField0_:I
      57: aload_1
      58: aload_0
      59: getfield      #12                 // Field audiences_:Lcom/google/protobuf/LazyStringList;
      62: invokestatic  #29                 // Method com/google/rpc/context/AttributeContext$Auth.access$3602:(Lcom/google/rpc/context/AttributeContext$Auth;Lcom/google/protobuf/LazyStringList;)Lcom/google/protobuf/LazyStringList;
      65: pop
      66: aload_1
      67: aload_0
      68: getfield      #13                 // Field presenter_:Ljava/lang/Object;
      71: invokestatic  #30                 // Method com/google/rpc/context/AttributeContext$Auth.access$3702:(Lcom/google/rpc/context/AttributeContext$Auth;Ljava/lang/Object;)Ljava/lang/Object;
      74: pop
      75: aload_0
      76: getfield      #20                 // Field claimsBuilder_:Lcom/google/protobuf/SingleFieldBuilderV3;
      79: ifnonnull     94
      82: aload_1
      83: aload_0
      84: getfield      #21                 // Field claims_:Lcom/google/protobuf/Struct;
      87: invokestatic  #31                 // Method com/google/rpc/context/AttributeContext$Auth.access$3802:(Lcom/google/rpc/context/AttributeContext$Auth;Lcom/google/protobuf/Struct;)Lcom/google/protobuf/Struct;
      90: pop
      91: goto          109
      94: aload_1
      95: aload_0
      96: getfield      #20                 // Field claimsBuilder_:Lcom/google/protobuf/SingleFieldBuilderV3;
      99: invokevirtual #32                 // Method com/google/protobuf/SingleFieldBuilderV3.build:()Lcom/google/protobuf/AbstractMessage;
     102: checkcast     #33                 // class com/google/protobuf/Struct
     105: invokestatic  #31                 // Method com/google/rpc/context/AttributeContext$Auth.access$3802:(Lcom/google/rpc/context/AttributeContext$Auth;Lcom/google/protobuf/Struct;)Lcom/google/protobuf/Struct;
     108: pop
     109: aload_0
     110: getfield      #19                 // Field bitField0_:I
     113: iconst_2
     114: iand
     115: ifeq          142
     118: aload_0
     119: aload_0
     120: getfield      #14                 // Field accessLevels_:Lcom/google/protobuf/LazyStringList;
     123: invokeinterface #28,  1           // InterfaceMethod com/google/protobuf/LazyStringList.getUnmodifiableView:()Lcom/google/protobuf/LazyStringList;
     128: putfield      #14                 // Field accessLevels_:Lcom/google/protobuf/LazyStringList;
     131: aload_0
     132: aload_0
     133: getfield      #19                 // Field bitField0_:I
     136: bipush        -3
     138: iand
     139: putfield      #19                 // Field bitField0_:I
     142: aload_1
     143: aload_0
     144: getfield      #14                 // Field accessLevels_:Lcom/google/protobuf/LazyStringList;
     147: invokestatic  #34                 // Method com/google/rpc/context/AttributeContext$Auth.access$3902:(Lcom/google/rpc/context/AttributeContext$Auth;Lcom/google/protobuf/LazyStringList;)Lcom/google/protobuf/LazyStringList;
     150: pop
     151: aload_0
     152: invokevirtual #35                 // Method onBuilt:()V
     155: aload_1
     156: areturn

  public com.google.rpc.context.AttributeContext$Auth$Builder clone();
    Code:
       0: aload_0
       1: invokespecial #36                 // Method com/google/protobuf/GeneratedMessageV3$Builder.clone:()Lcom/google/protobuf/GeneratedMessageV3$Builder;
       4: checkcast     #6                  // class com/google/rpc/context/AttributeContext$Auth$Builder
       7: areturn

  public com.google.rpc.context.AttributeContext$Auth$Builder setField(com.google.protobuf.Descriptors$FieldDescriptor, java.lang.Object);
    Code:
       0: aload_0
       1: aload_1
       2: aload_2
       3: invokespecial #37                 // Method com/google/protobuf/GeneratedMessageV3$Builder.setField:(Lcom/google/protobuf/Descriptors$FieldDescriptor;Ljava/lang/Object;)Lcom/google/protobuf/GeneratedMessageV3$Builder;
       6: checkcast     #6                  // class com/google/rpc/context/AttributeContext$Auth$Builder
       9: areturn

  public com.google.rpc.context.AttributeContext$Auth$Builder clearField(com.google.protobuf.Descriptors$FieldDescriptor);
    Code:
       0: aload_0
       1: aload_1
       2: invokespecial #38                 // Method com/google/protobuf/GeneratedMessageV3$Builder.clearField:(Lcom/google/protobuf/Descriptors$FieldDescriptor;)Lcom/google/protobuf/GeneratedMessageV3$Builder;
       5: checkcast     #6                  // class com/google/rpc/context/AttributeContext$Auth$Builder
       8: areturn

  public com.google.rpc.context.AttributeContext$Auth$Builder clearOneof(com.google.protobuf.Descriptors$OneofDescriptor);
    Code:
       0: aload_0
       1: aload_1
       2: invokespecial #39                 // Method com/google/protobuf/GeneratedMessageV3$Builder.clearOneof:(Lcom/google/protobuf/Descriptors$OneofDescriptor;)Lcom/google/protobuf/GeneratedMessageV3$Builder;
       5: checkcast     #6                  // class com/google/rpc/context/AttributeContext$Auth$Builder
       8: areturn

  public com.google.rpc.context.AttributeContext$Auth$Builder setRepeatedField(com.google.protobuf.Descriptors$FieldDescriptor, int, java.lang.Object);
    Code:
       0: aload_0
       1: aload_1
       2: iload_2
       3: aload_3
       4: invokespecial #40                 // Method com/google/protobuf/GeneratedMessageV3$Builder.setRepeatedField:(Lcom/google/protobuf/Descriptors$FieldDescriptor;ILjava/lang/Object;)Lcom/google/protobuf/GeneratedMessageV3$Builder;
       7: checkcast     #6                  // class com/google/rpc/context/AttributeContext$Auth$Builder
      10: areturn

  public com.google.rpc.context.AttributeContext$Auth$Builder addRepeatedField(com.google.protobuf.Descriptors$FieldDescriptor, java.lang.Object);
    Code:
       0: aload_0
       1: aload_1
       2: aload_2
       3: invokespecial #41                 // Method com/google/protobuf/GeneratedMessageV3$Builder.addRepeatedField:(Lcom/google/protobuf/Descriptors$FieldDescriptor;Ljava/lang/Object;)Lcom/google/protobuf/GeneratedMessageV3$Builder;
       6: checkcast     #6                  // class com/google/rpc/context/AttributeContext$Auth$Builder
       9: areturn

  public com.google.rpc.context.AttributeContext$Auth$Builder mergeFrom(com.google.protobuf.Message);
    Code:
       0: aload_1
       1: instanceof    #5                  // class com/google/rpc/context/AttributeContext$Auth
       4: ifeq          16
       7: aload_0
       8: aload_1
       9: checkcast     #5                  // class com/google/rpc/context/AttributeContext$Auth
      12: invokevirtual #42                 // Method mergeFrom:(Lcom/google/rpc/context/AttributeContext$Auth;)Lcom/google/rpc/context/AttributeContext$Auth$Builder;
      15: areturn
      16: aload_0
      17: aload_1
      18: invokespecial #43                 // Method com/google/protobuf/GeneratedMessageV3$Builder.mergeFrom:(Lcom/google/protobuf/Message;)Lcom/google/protobuf/AbstractMessage$Builder;
      21: pop
      22: aload_0
      23: areturn

  public com.google.rpc.context.AttributeContext$Auth$Builder mergeFrom(com.google.rpc.context.AttributeContext$Auth);
    Code:
       0: aload_1
       1: invokestatic  #22                 // Method com/google/rpc/context/AttributeContext$Auth.getDefaultInstance:()Lcom/google/rpc/context/AttributeContext$Auth;
       4: if_acmpne     9
       7: aload_0
       8: areturn
       9: aload_1
      10: invokevirtual #44                 // Method com/google/rpc/context/AttributeContext$Auth.getPrincipal:()Ljava/lang/String;
      13: invokevirtual #45                 // Method java/lang/String.isEmpty:()Z
      16: ifne          31
      19: aload_0
      20: aload_1
      21: invokestatic  #46                 // Method com/google/rpc/context/AttributeContext$Auth.access$3500:(Lcom/google/rpc/context/AttributeContext$Auth;)Ljava/lang/Object;
      24: putfield      #10                 // Field principal_:Ljava/lang/Object;
      27: aload_0
      28: invokevirtual #47                 // Method onChanged:()V
      31: aload_1
      32: invokestatic  #48                 // Method com/google/rpc/context/AttributeContext$Auth.access$3600:(Lcom/google/rpc/context/AttributeContext$Auth;)Lcom/google/protobuf/LazyStringList;
      35: invokeinterface #49,  1           // InterfaceMethod com/google/protobuf/LazyStringList.isEmpty:()Z
      40: ifne          99
      43: aload_0
      44: getfield      #12                 // Field audiences_:Lcom/google/protobuf/LazyStringList;
      47: invokeinterface #49,  1           // InterfaceMethod com/google/protobuf/LazyStringList.isEmpty:()Z
      52: ifeq          77
      55: aload_0
      56: aload_1
      57: invokestatic  #48                 // Method com/google/rpc/context/AttributeContext$Auth.access$3600:(Lcom/google/rpc/context/AttributeContext$Auth;)Lcom/google/protobuf/LazyStringList;
      60: putfield      #12                 // Field audiences_:Lcom/google/protobuf/LazyStringList;
      63: aload_0
      64: aload_0
      65: getfield      #19                 // Field bitField0_:I
      68: bipush        -2
      70: iand
      71: putfield      #19                 // Field bitField0_:I
      74: goto          95
      77: aload_0
      78: invokespecial #50                 // Method ensureAudiencesIsMutable:()V
      81: aload_0
      82: getfield      #12                 // Field audiences_:Lcom/google/protobuf/LazyStringList;
      85: aload_1
      86: invokestatic  #48                 // Method com/google/rpc/context/AttributeContext$Auth.access$3600:(Lcom/google/rpc/context/AttributeContext$Auth;)Lcom/google/protobuf/LazyStringList;
      89: invokeinterface #51,  2           // InterfaceMethod com/google/protobuf/LazyStringList.addAll:(Ljava/util/Collection;)Z
      94: pop
      95: aload_0
      96: invokevirtual #47                 // Method onChanged:()V
      99: aload_1
     100: invokevirtual #52                 // Method com/google/rpc/context/AttributeContext$Auth.getPresenter:()Ljava/lang/String;
     103: invokevirtual #45                 // Method java/lang/String.isEmpty:()Z
     106: ifne          121
     109: aload_0
     110: aload_1
     111: invokestatic  #53                 // Method com/google/rpc/context/AttributeContext$Auth.access$3700:(Lcom/google/rpc/context/AttributeContext$Auth;)Ljava/lang/Object;
     114: putfield      #13                 // Field presenter_:Ljava/lang/Object;
     117: aload_0
     118: invokevirtual #47                 // Method onChanged:()V
     121: aload_1
     122: invokevirtual #54                 // Method com/google/rpc/context/AttributeContext$Auth.hasClaims:()Z
     125: ifeq          137
     128: aload_0
     129: aload_1
     130: invokevirtual #55                 // Method com/google/rpc/context/AttributeContext$Auth.getClaims:()Lcom/google/protobuf/Struct;
     133: invokevirtual #56                 // Method mergeClaims:(Lcom/google/protobuf/Struct;)Lcom/google/rpc/context/AttributeContext$Auth$Builder;
     136: pop
     137: aload_1
     138: invokestatic  #57                 // Method com/google/rpc/context/AttributeContext$Auth.access$3900:(Lcom/google/rpc/context/AttributeContext$Auth;)Lcom/google/protobuf/LazyStringList;
     141: invokeinterface #49,  1           // InterfaceMethod com/google/protobuf/LazyStringList.isEmpty:()Z
     146: ifne          205
     149: aload_0
     150: getfield      #14                 // Field accessLevels_:Lcom/google/protobuf/LazyStringList;
     153: invokeinterface #49,  1           // InterfaceMethod com/google/protobuf/LazyStringList.isEmpty:()Z
     158: ifeq          183
     161: aload_0
     162: aload_1
     163: invokestatic  #57                 // Method com/google/rpc/context/AttributeContext$Auth.access$3900:(Lcom/google/rpc/context/AttributeContext$Auth;)Lcom/google/protobuf/LazyStringList;
     166: putfield      #14                 // Field accessLevels_:Lcom/google/protobuf/LazyStringList;
     169: aload_0
     170: aload_0
     171: getfield      #19                 // Field bitField0_:I
     174: bipush        -3
     176: iand
     177: putfield      #19                 // Field bitField0_:I
     180: goto          201
     183: aload_0
     184: invokespecial #58                 // Method ensureAccessLevelsIsMutable:()V
     187: aload_0
     188: getfield      #14                 // Field accessLevels_:Lcom/google/protobuf/LazyStringList;
     191: aload_1
     192: invokestatic  #57                 // Method com/google/rpc/context/AttributeContext$Auth.access$3900:(Lcom/google/rpc/context/AttributeContext$Auth;)Lcom/google/protobuf/LazyStringList;
     195: invokeinterface #51,  2           // InterfaceMethod com/google/protobuf/LazyStringList.addAll:(Ljava/util/Collection;)Z
     200: pop
     201: aload_0
     202: invokevirtual #47                 // Method onChanged:()V
     205: aload_0
     206: aload_1
     207: invokestatic  #59                 // Method com/google/rpc/context/AttributeContext$Auth.access$4000:(Lcom/google/rpc/context/AttributeContext$Auth;)Lcom/google/protobuf/UnknownFieldSet;
     210: invokevirtual #60                 // Method mergeUnknownFields:(Lcom/google/protobuf/UnknownFieldSet;)Lcom/google/rpc/context/AttributeContext$Auth$Builder;
     213: pop
     214: aload_0
     215: invokevirtual #47                 // Method onChanged:()V
     218: aload_0
     219: areturn

  public final boolean isInitialized();
    Code:
       0: iconst_1
       1: ireturn

  public com.google.rpc.context.AttributeContext$Auth$Builder mergeFrom(com.google.protobuf.CodedInputStream, com.google.protobuf.ExtensionRegistryLite) throws java.io.IOException;
    Code:
       0: aconst_null
       1: astore_3
       2: invokestatic  #61                 // Method com/google/rpc/context/AttributeContext$Auth.access$4100:()Lcom/google/protobuf/Parser;
       5: aload_1
       6: aload_2
       7: invokeinterface #62,  3           // InterfaceMethod com/google/protobuf/Parser.parsePartialFrom:(Lcom/google/protobuf/CodedInputStream;Lcom/google/protobuf/ExtensionRegistryLite;)Ljava/lang/Object;
      12: checkcast     #5                  // class com/google/rpc/context/AttributeContext$Auth
      15: astore_3
      16: aload_3
      17: ifnull        61
      20: aload_0
      21: aload_3
      22: invokevirtual #42                 // Method mergeFrom:(Lcom/google/rpc/context/AttributeContext$Auth;)Lcom/google/rpc/context/AttributeContext$Auth$Builder;
      25: pop
      26: goto          61
      29: astore        4
      31: aload         4
      33: invokevirtual #64                 // Method com/google/protobuf/InvalidProtocolBufferException.getUnfinishedMessage:()Lcom/google/protobuf/MessageLite;
      36: checkcast     #5                  // class com/google/rpc/context/AttributeContext$Auth
      39: astore_3
      40: aload         4
      42: invokevirtual #65                 // Method com/google/protobuf/InvalidProtocolBufferException.unwrapIOException:()Ljava/io/IOException;
      45: athrow
      46: astore        5
      48: aload_3
      49: ifnull        58
      52: aload_0
      53: aload_3
      54: invokevirtual #42                 // Method mergeFrom:(Lcom/google/rpc/context/AttributeContext$Auth;)Lcom/google/rpc/context/AttributeContext$Auth$Builder;
      57: pop
      58: aload         5
      60: athrow
      61: aload_0
      62: areturn
    Exception table:
       from    to  target type
           2    16    29   Class com/google/protobuf/InvalidProtocolBufferException
           2    16    46   any
          29    48    46   any

  public java.lang.String getPrincipal();
    Code:
       0: aload_0
       1: getfield      #10                 // Field principal_:Ljava/lang/Object;
       4: astore_1
       5: aload_1
       6: instanceof    #66                 // class java/lang/String
       9: ifne          29
      12: aload_1
      13: checkcast     #67                 // class com/google/protobuf/ByteString
      16: astore_2
      17: aload_2
      18: invokevirtual #68                 // Method com/google/protobuf/ByteString.toStringUtf8:()Ljava/lang/String;
      21: astore_3
      22: aload_0
      23: aload_3
      24: putfield      #10                 // Field principal_:Ljava/lang/Object;
      27: aload_3
      28: areturn
      29: aload_1
      30: checkcast     #66                 // class java/lang/String
      33: areturn

  public com.google.protobuf.ByteString getPrincipalBytes();
    Code:
       0: aload_0
       1: getfield      #10                 // Field principal_:Ljava/lang/Object;
       4: astore_1
       5: aload_1
       6: instanceof    #66                 // class java/lang/String
       9: ifeq          27
      12: aload_1
      13: checkcast     #66                 // class java/lang/String
      16: invokestatic  #69                 // Method com/google/protobuf/ByteString.copyFromUtf8:(Ljava/lang/String;)Lcom/google/protobuf/ByteString;
      19: astore_2
      20: aload_0
      21: aload_2
      22: putfield      #10                 // Field principal_:Ljava/lang/Object;
      25: aload_2
      26: areturn
      27: aload_1
      28: checkcast     #67                 // class com/google/protobuf/ByteString
      31: areturn

  public com.google.rpc.context.AttributeContext$Auth$Builder setPrincipal(java.lang.String);
    Code:
       0: aload_1
       1: ifnonnull     12
       4: new           #70                 // class java/lang/NullPointerException
       7: dup
       8: invokespecial #71                 // Method java/lang/NullPointerException."<init>":()V
      11: athrow
      12: aload_0
      13: aload_1
      14: putfield      #10                 // Field principal_:Ljava/lang/Object;
      17: aload_0
      18: invokevirtual #47                 // Method onChanged:()V
      21: aload_0
      22: areturn

  public com.google.rpc.context.AttributeContext$Auth$Builder clearPrincipal();
    Code:
       0: aload_0
       1: invokestatic  #22                 // Method com/google/rpc/context/AttributeContext$Auth.getDefaultInstance:()Lcom/google/rpc/context/AttributeContext$Auth;
       4: invokevirtual #44                 // Method com/google/rpc/context/AttributeContext$Auth.getPrincipal:()Ljava/lang/String;
       7: putfield      #10                 // Field principal_:Ljava/lang/Object;
      10: aload_0
      11: invokevirtual #47                 // Method onChanged:()V
      14: aload_0
      15: areturn

  public com.google.rpc.context.AttributeContext$Auth$Builder setPrincipalBytes(com.google.protobuf.ByteString);
    Code:
       0: aload_1
       1: ifnonnull     12
       4: new           #70                 // class java/lang/NullPointerException
       7: dup
       8: invokespecial #71                 // Method java/lang/NullPointerException."<init>":()V
      11: athrow
      12: aload_1
      13: invokestatic  #72                 // Method com/google/rpc/context/AttributeContext$Auth.access$4200:(Lcom/google/protobuf/ByteString;)V
      16: aload_0
      17: aload_1
      18: putfield      #10                 // Field principal_:Ljava/lang/Object;
      21: aload_0
      22: invokevirtual #47                 // Method onChanged:()V
      25: aload_0
      26: areturn

  private void ensureAudiencesIsMutable();
    Code:
       0: aload_0
       1: getfield      #19                 // Field bitField0_:I
       4: iconst_1
       5: iand
       6: ifne          34
       9: aload_0
      10: new           #73                 // class com/google/protobuf/LazyStringArrayList
      13: dup
      14: aload_0
      15: getfield      #12                 // Field audiences_:Lcom/google/protobuf/LazyStringList;
      18: invokespecial #74                 // Method com/google/protobuf/LazyStringArrayList."<init>":(Lcom/google/protobuf/LazyStringList;)V
      21: putfield      #12                 // Field audiences_:Lcom/google/protobuf/LazyStringList;
      24: aload_0
      25: dup
      26: getfield      #19                 // Field bitField0_:I
      29: iconst_1
      30: ior
      31: putfield      #19                 // Field bitField0_:I
      34: return

  public com.google.protobuf.ProtocolStringList getAudiencesList();
    Code:
       0: aload_0
       1: getfield      #12                 // Field audiences_:Lcom/google/protobuf/LazyStringList;
       4: invokeinterface #28,  1           // InterfaceMethod com/google/protobuf/LazyStringList.getUnmodifiableView:()Lcom/google/protobuf/LazyStringList;
       9: areturn

  public int getAudiencesCount();
    Code:
       0: aload_0
       1: getfield      #12                 // Field audiences_:Lcom/google/protobuf/LazyStringList;
       4: invokeinterface #75,  1           // InterfaceMethod com/google/protobuf/LazyStringList.size:()I
       9: ireturn

  public java.lang.String getAudiences(int);
    Code:
       0: aload_0
       1: getfield      #12                 // Field audiences_:Lcom/google/protobuf/LazyStringList;
       4: iload_1
       5: invokeinterface #76,  2           // InterfaceMethod com/google/protobuf/LazyStringList.get:(I)Ljava/lang/Object;
      10: checkcast     #66                 // class java/lang/String
      13: areturn

  public com.google.protobuf.ByteString getAudiencesBytes(int);
    Code:
       0: aload_0
       1: getfield      #12                 // Field audiences_:Lcom/google/protobuf/LazyStringList;
       4: iload_1
       5: invokeinterface #77,  2           // InterfaceMethod com/google/protobuf/LazyStringList.getByteString:(I)Lcom/google/protobuf/ByteString;
      10: areturn

  public com.google.rpc.context.AttributeContext$Auth$Builder setAudiences(int, java.lang.String);
    Code:
       0: aload_2
       1: ifnonnull     12
       4: new           #70                 // class java/lang/NullPointerException
       7: dup
       8: invokespecial #71                 // Method java/lang/NullPointerException."<init>":()V
      11: athrow
      12: aload_0
      13: invokespecial #50                 // Method ensureAudiencesIsMutable:()V
      16: aload_0
      17: getfield      #12                 // Field audiences_:Lcom/google/protobuf/LazyStringList;
      20: iload_1
      21: aload_2
      22: invokeinterface #78,  3           // InterfaceMethod com/google/protobuf/LazyStringList.set:(ILjava/lang/Object;)Ljava/lang/Object;
      27: pop
      28: aload_0
      29: invokevirtual #47                 // Method onChanged:()V
      32: aload_0
      33: areturn

  public com.google.rpc.context.AttributeContext$Auth$Builder addAudiences(java.lang.String);
    Code:
       0: aload_1
       1: ifnonnull     12
       4: new           #70                 // class java/lang/NullPointerException
       7: dup
       8: invokespecial #71                 // Method java/lang/NullPointerException."<init>":()V
      11: athrow
      12: aload_0
      13: invokespecial #50                 // Method ensureAudiencesIsMutable:()V
      16: aload_0
      17: getfield      #12                 // Field audiences_:Lcom/google/protobuf/LazyStringList;
      20: aload_1
      21: invokeinterface #79,  2           // InterfaceMethod com/google/protobuf/LazyStringList.add:(Ljava/lang/Object;)Z
      26: pop
      27: aload_0
      28: invokevirtual #47                 // Method onChanged:()V
      31: aload_0
      32: areturn

  public com.google.rpc.context.AttributeContext$Auth$Builder addAllAudiences(java.lang.Iterable<java.lang.String>);
    Code:
       0: aload_0
       1: invokespecial #50                 // Method ensureAudiencesIsMutable:()V
       4: aload_1
       5: aload_0
       6: getfield      #12                 // Field audiences_:Lcom/google/protobuf/LazyStringList;
       9: invokestatic  #80                 // Method com/google/protobuf/AbstractMessageLite$Builder.addAll:(Ljava/lang/Iterable;Ljava/util/List;)V
      12: aload_0
      13: invokevirtual #47                 // Method onChanged:()V
      16: aload_0
      17: areturn

  public com.google.rpc.context.AttributeContext$Auth$Builder clearAudiences();
    Code:
       0: aload_0
       1: getstatic     #11                 // Field com/google/protobuf/LazyStringArrayList.EMPTY:Lcom/google/protobuf/LazyStringList;
       4: putfield      #12                 // Field audiences_:Lcom/google/protobuf/LazyStringList;
       7: aload_0
       8: aload_0
       9: getfield      #19                 // Field bitField0_:I
      12: bipush        -2
      14: iand
      15: putfield      #19                 // Field bitField0_:I
      18: aload_0
      19: invokevirtual #47                 // Method onChanged:()V
      22: aload_0
      23: areturn

  public com.google.rpc.context.AttributeContext$Auth$Builder addAudiencesBytes(com.google.protobuf.ByteString);
    Code:
       0: aload_1
       1: ifnonnull     12
       4: new           #70                 // class java/lang/NullPointerException
       7: dup
       8: invokespecial #71                 // Method java/lang/NullPointerException."<init>":()V
      11: athrow
      12: aload_1
      13: invokestatic  #81                 // Method com/google/rpc/context/AttributeContext$Auth.access$4300:(Lcom/google/protobuf/ByteString;)V
      16: aload_0
      17: invokespecial #50                 // Method ensureAudiencesIsMutable:()V
      20: aload_0
      21: getfield      #12                 // Field audiences_:Lcom/google/protobuf/LazyStringList;
      24: aload_1
      25: invokeinterface #82,  2           // InterfaceMethod com/google/protobuf/LazyStringList.add:(Lcom/google/protobuf/ByteString;)V
      30: aload_0
      31: invokevirtual #47                 // Method onChanged:()V
      34: aload_0
      35: areturn

  public java.lang.String getPresenter();
    Code:
       0: aload_0
       1: getfield      #13                 // Field presenter_:Ljava/lang/Object;
       4: astore_1
       5: aload_1
       6: instanceof    #66                 // class java/lang/String
       9: ifne          29
      12: aload_1
      13: checkcast     #67                 // class com/google/protobuf/ByteString
      16: astore_2
      17: aload_2
      18: invokevirtual #68                 // Method com/google/protobuf/ByteString.toStringUtf8:()Ljava/lang/String;
      21: astore_3
      22: aload_0
      23: aload_3
      24: putfield      #13                 // Field presenter_:Ljava/lang/Object;
      27: aload_3
      28: areturn
      29: aload_1
      30: checkcast     #66                 // class java/lang/String
      33: areturn

  public com.google.protobuf.ByteString getPresenterBytes();
    Code:
       0: aload_0
       1: getfield      #13                 // Field presenter_:Ljava/lang/Object;
       4: astore_1
       5: aload_1
       6: instanceof    #66                 // class java/lang/String
       9: ifeq          27
      12: aload_1
      13: checkcast     #66                 // class java/lang/String
      16: invokestatic  #69                 // Method com/google/protobuf/ByteString.copyFromUtf8:(Ljava/lang/String;)Lcom/google/protobuf/ByteString;
      19: astore_2
      20: aload_0
      21: aload_2
      22: putfield      #13                 // Field presenter_:Ljava/lang/Object;
      25: aload_2
      26: areturn
      27: aload_1
      28: checkcast     #67                 // class com/google/protobuf/ByteString
      31: areturn

  public com.google.rpc.context.AttributeContext$Auth$Builder setPresenter(java.lang.String);
    Code:
       0: aload_1
       1: ifnonnull     12
       4: new           #70                 // class java/lang/NullPointerException
       7: dup
       8: invokespecial #71                 // Method java/lang/NullPointerException."<init>":()V
      11: athrow
      12: aload_0
      13: aload_1
      14: putfield      #13                 // Field presenter_:Ljava/lang/Object;
      17: aload_0
      18: invokevirtual #47                 // Method onChanged:()V
      21: aload_0
      22: areturn

  public com.google.rpc.context.AttributeContext$Auth$Builder clearPresenter();
    Code:
       0: aload_0
       1: invokestatic  #22                 // Method com/google/rpc/context/AttributeContext$Auth.getDefaultInstance:()Lcom/google/rpc/context/AttributeContext$Auth;
       4: invokevirtual #52                 // Method com/google/rpc/context/AttributeContext$Auth.getPresenter:()Ljava/lang/String;
       7: putfield      #13                 // Field presenter_:Ljava/lang/Object;
      10: aload_0
      11: invokevirtual #47                 // Method onChanged:()V
      14: aload_0
      15: areturn

  public com.google.rpc.context.AttributeContext$Auth$Builder setPresenterBytes(com.google.protobuf.ByteString);
    Code:
       0: aload_1
       1: ifnonnull     12
       4: new           #70                 // class java/lang/NullPointerException
       7: dup
       8: invokespecial #71                 // Method java/lang/NullPointerException."<init>":()V
      11: athrow
      12: aload_1
      13: invokestatic  #83                 // Method com/google/rpc/context/AttributeContext$Auth.access$4400:(Lcom/google/protobuf/ByteString;)V
      16: aload_0
      17: aload_1
      18: putfield      #13                 // Field presenter_:Ljava/lang/Object;
      21: aload_0
      22: invokevirtual #47                 // Method onChanged:()V
      25: aload_0
      26: areturn

  public boolean hasClaims();
    Code:
       0: aload_0
       1: getfield      #20                 // Field claimsBuilder_:Lcom/google/protobuf/SingleFieldBuilderV3;
       4: ifnonnull     14
       7: aload_0
       8: getfield      #21                 // Field claims_:Lcom/google/protobuf/Struct;
      11: ifnull        18
      14: iconst_1
      15: goto          19
      18: iconst_0
      19: ireturn

  public com.google.protobuf.Struct getClaims();
    Code:
       0: aload_0
       1: getfield      #20                 // Field claimsBuilder_:Lcom/google/protobuf/SingleFieldBuilderV3;
       4: ifnonnull     25
       7: aload_0
       8: getfield      #21                 // Field claims_:Lcom/google/protobuf/Struct;
      11: ifnonnull     20
      14: invokestatic  #84                 // Method com/google/protobuf/Struct.getDefaultInstance:()Lcom/google/protobuf/Struct;
      17: goto          24
      20: aload_0
      21: getfield      #21                 // Field claims_:Lcom/google/protobuf/Struct;
      24: areturn
      25: aload_0
      26: getfield      #20                 // Field claimsBuilder_:Lcom/google/protobuf/SingleFieldBuilderV3;
      29: invokevirtual #85                 // Method com/google/protobuf/SingleFieldBuilderV3.getMessage:()Lcom/google/protobuf/AbstractMessage;
      32: checkcast     #33                 // class com/google/protobuf/Struct
      35: areturn

  public com.google.rpc.context.AttributeContext$Auth$Builder setClaims(com.google.protobuf.Struct);
    Code:
       0: aload_0
       1: getfield      #20                 // Field claimsBuilder_:Lcom/google/protobuf/SingleFieldBuilderV3;
       4: ifnonnull     31
       7: aload_1
       8: ifnonnull     19
      11: new           #70                 // class java/lang/NullPointerException
      14: dup
      15: invokespecial #71                 // Method java/lang/NullPointerException."<init>":()V
      18: athrow
      19: aload_0
      20: aload_1
      21: putfield      #21                 // Field claims_:Lcom/google/protobuf/Struct;
      24: aload_0
      25: invokevirtual #47                 // Method onChanged:()V
      28: goto          40
      31: aload_0
      32: getfield      #20                 // Field claimsBuilder_:Lcom/google/protobuf/SingleFieldBuilderV3;
      35: aload_1
      36: invokevirtual #86                 // Method com/google/protobuf/SingleFieldBuilderV3.setMessage:(Lcom/google/protobuf/AbstractMessage;)Lcom/google/protobuf/SingleFieldBuilderV3;
      39: pop
      40: aload_0
      41: areturn

  public com.google.rpc.context.AttributeContext$Auth$Builder setClaims(com.google.protobuf.Struct$Builder);
    Code:
       0: aload_0
       1: getfield      #20                 // Field claimsBuilder_:Lcom/google/protobuf/SingleFieldBuilderV3;
       4: ifnonnull     22
       7: aload_0
       8: aload_1
       9: invokevirtual #87                 // Method com/google/protobuf/Struct$Builder.build:()Lcom/google/protobuf/Struct;
      12: putfield      #21                 // Field claims_:Lcom/google/protobuf/Struct;
      15: aload_0
      16: invokevirtual #47                 // Method onChanged:()V
      19: goto          34
      22: aload_0
      23: getfield      #20                 // Field claimsBuilder_:Lcom/google/protobuf/SingleFieldBuilderV3;
      26: aload_1
      27: invokevirtual #87                 // Method com/google/protobuf/Struct$Builder.build:()Lcom/google/protobuf/Struct;
      30: invokevirtual #86                 // Method com/google/protobuf/SingleFieldBuilderV3.setMessage:(Lcom/google/protobuf/AbstractMessage;)Lcom/google/protobuf/SingleFieldBuilderV3;
      33: pop
      34: aload_0
      35: areturn

  public com.google.rpc.context.AttributeContext$Auth$Builder mergeClaims(com.google.protobuf.Struct);
    Code:
       0: aload_0
       1: getfield      #20                 // Field claimsBuilder_:Lcom/google/protobuf/SingleFieldBuilderV3;
       4: ifnonnull     47
       7: aload_0
       8: getfield      #21                 // Field claims_:Lcom/google/protobuf/Struct;
      11: ifnull        35
      14: aload_0
      15: aload_0
      16: getfield      #21                 // Field claims_:Lcom/google/protobuf/Struct;
      19: invokestatic  #88                 // Method com/google/protobuf/Struct.newBuilder:(Lcom/google/protobuf/Struct;)Lcom/google/protobuf/Struct$Builder;
      22: aload_1
      23: invokevirtual #89                 // Method com/google/protobuf/Struct$Builder.mergeFrom:(Lcom/google/protobuf/Struct;)Lcom/google/protobuf/Struct$Builder;
      26: invokevirtual #90                 // Method com/google/protobuf/Struct$Builder.buildPartial:()Lcom/google/protobuf/Struct;
      29: putfield      #21                 // Field claims_:Lcom/google/protobuf/Struct;
      32: goto          40
      35: aload_0
      36: aload_1
      37: putfield      #21                 // Field claims_:Lcom/google/protobuf/Struct;
      40: aload_0
      41: invokevirtual #47                 // Method onChanged:()V
      44: goto          56
      47: aload_0
      48: getfield      #20                 // Field claimsBuilder_:Lcom/google/protobuf/SingleFieldBuilderV3;
      51: aload_1
      52: invokevirtual #91                 // Method com/google/protobuf/SingleFieldBuilderV3.mergeFrom:(Lcom/google/protobuf/AbstractMessage;)Lcom/google/protobuf/SingleFieldBuilderV3;
      55: pop
      56: aload_0
      57: areturn

  public com.google.rpc.context.AttributeContext$Auth$Builder clearClaims();
    Code:
       0: aload_0
       1: getfield      #20                 // Field claimsBuilder_:Lcom/google/protobuf/SingleFieldBuilderV3;
       4: ifnonnull     19
       7: aload_0
       8: aconst_null
       9: putfield      #21                 // Field claims_:Lcom/google/protobuf/Struct;
      12: aload_0
      13: invokevirtual #47                 // Method onChanged:()V
      16: goto          29
      19: aload_0
      20: aconst_null
      21: putfield      #21                 // Field claims_:Lcom/google/protobuf/Struct;
      24: aload_0
      25: aconst_null
      26: putfield      #20                 // Field claimsBuilder_:Lcom/google/protobuf/SingleFieldBuilderV3;
      29: aload_0
      30: areturn

  public com.google.protobuf.Struct$Builder getClaimsBuilder();
    Code:
       0: aload_0
       1: invokevirtual #47                 // Method onChanged:()V
       4: aload_0
       5: invokespecial #92                 // Method getClaimsFieldBuilder:()Lcom/google/protobuf/SingleFieldBuilderV3;
       8: invokevirtual #93                 // Method com/google/protobuf/SingleFieldBuilderV3.getBuilder:()Lcom/google/protobuf/AbstractMessage$Builder;
      11: checkcast     #94                 // class com/google/protobuf/Struct$Builder
      14: areturn

  public com.google.protobuf.StructOrBuilder getClaimsOrBuilder();
    Code:
       0: aload_0
       1: getfield      #20                 // Field claimsBuilder_:Lcom/google/protobuf/SingleFieldBuilderV3;
       4: ifnull        18
       7: aload_0
       8: getfield      #20                 // Field claimsBuilder_:Lcom/google/protobuf/SingleFieldBuilderV3;
      11: invokevirtual #95                 // Method com/google/protobuf/SingleFieldBuilderV3.getMessageOrBuilder:()Lcom/google/protobuf/MessageOrBuilder;
      14: checkcast     #96                 // class com/google/protobuf/StructOrBuilder
      17: areturn
      18: aload_0
      19: getfield      #21                 // Field claims_:Lcom/google/protobuf/Struct;
      22: ifnonnull     31
      25: invokestatic  #84                 // Method com/google/protobuf/Struct.getDefaultInstance:()Lcom/google/protobuf/Struct;
      28: goto          35
      31: aload_0
      32: getfield      #21                 // Field claims_:Lcom/google/protobuf/Struct;
      35: areturn

  private com.google.protobuf.SingleFieldBuilderV3<com.google.protobuf.Struct, com.google.protobuf.Struct$Builder, com.google.protobuf.StructOrBuilder> getClaimsFieldBuilder();
    Code:
       0: aload_0
       1: getfield      #20                 // Field claimsBuilder_:Lcom/google/protobuf/SingleFieldBuilderV3;
       4: ifnonnull     35
       7: aload_0
       8: new           #97                 // class com/google/protobuf/SingleFieldBuilderV3
      11: dup
      12: aload_0
      13: invokevirtual #98                 // Method getClaims:()Lcom/google/protobuf/Struct;
      16: aload_0
      17: invokevirtual #99                 // Method getParentForChildren:()Lcom/google/protobuf/GeneratedMessageV3$BuilderParent;
      20: aload_0
      21: invokevirtual #100                // Method isClean:()Z
      24: invokespecial #101                // Method com/google/protobuf/SingleFieldBuilderV3."<init>":(Lcom/google/protobuf/AbstractMessage;Lcom/google/protobuf/AbstractMessage$BuilderParent;Z)V
      27: putfield      #20                 // Field claimsBuilder_:Lcom/google/protobuf/SingleFieldBuilderV3;
      30: aload_0
      31: aconst_null
      32: putfield      #21                 // Field claims_:Lcom/google/protobuf/Struct;
      35: aload_0
      36: getfield      #20                 // Field claimsBuilder_:Lcom/google/protobuf/SingleFieldBuilderV3;
      39: areturn

  private void ensureAccessLevelsIsMutable();
    Code:
       0: aload_0
       1: getfield      #19                 // Field bitField0_:I
       4: iconst_2
       5: iand
       6: ifne          34
       9: aload_0
      10: new           #73                 // class com/google/protobuf/LazyStringArrayList
      13: dup
      14: aload_0
      15: getfield      #14                 // Field accessLevels_:Lcom/google/protobuf/LazyStringList;
      18: invokespecial #74                 // Method com/google/protobuf/LazyStringArrayList."<init>":(Lcom/google/protobuf/LazyStringList;)V
      21: putfield      #14                 // Field accessLevels_:Lcom/google/protobuf/LazyStringList;
      24: aload_0
      25: dup
      26: getfield      #19                 // Field bitField0_:I
      29: iconst_2
      30: ior
      31: putfield      #19                 // Field bitField0_:I
      34: return

  public com.google.protobuf.ProtocolStringList getAccessLevelsList();
    Code:
       0: aload_0
       1: getfield      #14                 // Field accessLevels_:Lcom/google/protobuf/LazyStringList;
       4: invokeinterface #28,  1           // InterfaceMethod com/google/protobuf/LazyStringList.getUnmodifiableView:()Lcom/google/protobuf/LazyStringList;
       9: areturn

  public int getAccessLevelsCount();
    Code:
       0: aload_0
       1: getfield      #14                 // Field accessLevels_:Lcom/google/protobuf/LazyStringList;
       4: invokeinterface #75,  1           // InterfaceMethod com/google/protobuf/LazyStringList.size:()I
       9: ireturn

  public java.lang.String getAccessLevels(int);
    Code:
       0: aload_0
       1: getfield      #14                 // Field accessLevels_:Lcom/google/protobuf/LazyStringList;
       4: iload_1
       5: invokeinterface #76,  2           // InterfaceMethod com/google/protobuf/LazyStringList.get:(I)Ljava/lang/Object;
      10: checkcast     #66                 // class java/lang/String
      13: areturn

  public com.google.protobuf.ByteString getAccessLevelsBytes(int);
    Code:
       0: aload_0
       1: getfield      #14                 // Field accessLevels_:Lcom/google/protobuf/LazyStringList;
       4: iload_1
       5: invokeinterface #77,  2           // InterfaceMethod com/google/protobuf/LazyStringList.getByteString:(I)Lcom/google/protobuf/ByteString;
      10: areturn

  public com.google.rpc.context.AttributeContext$Auth$Builder setAccessLevels(int, java.lang.String);
    Code:
       0: aload_2
       1: ifnonnull     12
       4: new           #70                 // class java/lang/NullPointerException
       7: dup
       8: invokespecial #71                 // Method java/lang/NullPointerException."<init>":()V
      11: athrow
      12: aload_0
      13: invokespecial #58                 // Method ensureAccessLevelsIsMutable:()V
      16: aload_0
      17: getfield      #14                 // Field accessLevels_:Lcom/google/protobuf/LazyStringList;
      20: iload_1
      21: aload_2
      22: invokeinterface #78,  3           // InterfaceMethod com/google/protobuf/LazyStringList.set:(ILjava/lang/Object;)Ljava/lang/Object;
      27: pop
      28: aload_0
      29: invokevirtual #47                 // Method onChanged:()V
      32: aload_0
      33: areturn

  public com.google.rpc.context.AttributeContext$Auth$Builder addAccessLevels(java.lang.String);
    Code:
       0: aload_1
       1: ifnonnull     12
       4: new           #70                 // class java/lang/NullPointerException
       7: dup
       8: invokespecial #71                 // Method java/lang/NullPointerException."<init>":()V
      11: athrow
      12: aload_0
      13: invokespecial #58                 // Method ensureAccessLevelsIsMutable:()V
      16: aload_0
      17: getfield      #14                 // Field accessLevels_:Lcom/google/protobuf/LazyStringList;
      20: aload_1
      21: invokeinterface #79,  2           // InterfaceMethod com/google/protobuf/LazyStringList.add:(Ljava/lang/Object;)Z
      26: pop
      27: aload_0
      28: invokevirtual #47                 // Method onChanged:()V
      31: aload_0
      32: areturn

  public com.google.rpc.context.AttributeContext$Auth$Builder addAllAccessLevels(java.lang.Iterable<java.lang.String>);
    Code:
       0: aload_0
       1: invokespecial #58                 // Method ensureAccessLevelsIsMutable:()V
       4: aload_1
       5: aload_0
       6: getfield      #14                 // Field accessLevels_:Lcom/google/protobuf/LazyStringList;
       9: invokestatic  #80                 // Method com/google/protobuf/AbstractMessageLite$Builder.addAll:(Ljava/lang/Iterable;Ljava/util/List;)V
      12: aload_0
      13: invokevirtual #47                 // Method onChanged:()V
      16: aload_0
      17: areturn

  public com.google.rpc.context.AttributeContext$Auth$Builder clearAccessLevels();
    Code:
       0: aload_0
       1: getstatic     #11                 // Field com/google/protobuf/LazyStringArrayList.EMPTY:Lcom/google/protobuf/LazyStringList;
       4: putfield      #14                 // Field accessLevels_:Lcom/google/protobuf/LazyStringList;
       7: aload_0
       8: aload_0
       9: getfield      #19                 // Field bitField0_:I
      12: bipush        -3
      14: iand
      15: putfield      #19                 // Field bitField0_:I
      18: aload_0
      19: invokevirtual #47                 // Method onChanged:()V
      22: aload_0
      23: areturn

  public com.google.rpc.context.AttributeContext$Auth$Builder addAccessLevelsBytes(com.google.protobuf.ByteString);
    Code:
       0: aload_1
       1: ifnonnull     12
       4: new           #70                 // class java/lang/NullPointerException
       7: dup
       8: invokespecial #71                 // Method java/lang/NullPointerException."<init>":()V
      11: athrow
      12: aload_1
      13: invokestatic  #102                // Method com/google/rpc/context/AttributeContext$Auth.access$4500:(Lcom/google/protobuf/ByteString;)V
      16: aload_0
      17: invokespecial #58                 // Method ensureAccessLevelsIsMutable:()V
      20: aload_0
      21: getfield      #14                 // Field accessLevels_:Lcom/google/protobuf/LazyStringList;
      24: aload_1
      25: invokeinterface #82,  2           // InterfaceMethod com/google/protobuf/LazyStringList.add:(Lcom/google/protobuf/ByteString;)V
      30: aload_0
      31: invokevirtual #47                 // Method onChanged:()V
      34: aload_0
      35: areturn

  public final com.google.rpc.context.AttributeContext$Auth$Builder setUnknownFields(com.google.protobuf.UnknownFieldSet);
    Code:
       0: aload_0
       1: aload_1
       2: invokespecial #103                // Method com/google/protobuf/GeneratedMessageV3$Builder.setUnknownFields:(Lcom/google/protobuf/UnknownFieldSet;)Lcom/google/protobuf/GeneratedMessageV3$Builder;
       5: checkcast     #6                  // class com/google/rpc/context/AttributeContext$Auth$Builder
       8: areturn

  public final com.google.rpc.context.AttributeContext$Auth$Builder mergeUnknownFields(com.google.protobuf.UnknownFieldSet);
    Code:
       0: aload_0
       1: aload_1
       2: invokespecial #104                // Method com/google/protobuf/GeneratedMessageV3$Builder.mergeUnknownFields:(Lcom/google/protobuf/UnknownFieldSet;)Lcom/google/protobuf/GeneratedMessageV3$Builder;
       5: checkcast     #6                  // class com/google/rpc/context/AttributeContext$Auth$Builder
       8: areturn

  public com.google.protobuf.GeneratedMessageV3$Builder mergeUnknownFields(com.google.protobuf.UnknownFieldSet);
    Code:
       0: aload_0
       1: aload_1
       2: invokevirtual #60                 // Method mergeUnknownFields:(Lcom/google/protobuf/UnknownFieldSet;)Lcom/google/rpc/context/AttributeContext$Auth$Builder;
       5: areturn

  public com.google.protobuf.GeneratedMessageV3$Builder setUnknownFields(com.google.protobuf.UnknownFieldSet);
    Code:
       0: aload_0
       1: aload_1
       2: invokevirtual #105                // Method setUnknownFields:(Lcom/google/protobuf/UnknownFieldSet;)Lcom/google/rpc/context/AttributeContext$Auth$Builder;
       5: areturn

  public com.google.protobuf.GeneratedMessageV3$Builder addRepeatedField(com.google.protobuf.Descriptors$FieldDescriptor, java.lang.Object);
    Code:
       0: aload_0
       1: aload_1
       2: aload_2
       3: invokevirtual #106                // Method addRepeatedField:(Lcom/google/protobuf/Descriptors$FieldDescriptor;Ljava/lang/Object;)Lcom/google/rpc/context/AttributeContext$Auth$Builder;
       6: areturn

  public com.google.protobuf.GeneratedMessageV3$Builder setRepeatedField(com.google.protobuf.Descriptors$FieldDescriptor, int, java.lang.Object);
    Code:
       0: aload_0
       1: aload_1
       2: iload_2
       3: aload_3
       4: invokevirtual #107                // Method setRepeatedField:(Lcom/google/protobuf/Descriptors$FieldDescriptor;ILjava/lang/Object;)Lcom/google/rpc/context/AttributeContext$Auth$Builder;
       7: areturn

  public com.google.protobuf.GeneratedMessageV3$Builder clearOneof(com.google.protobuf.Descriptors$OneofDescriptor);
    Code:
       0: aload_0
       1: aload_1
       2: invokevirtual #108                // Method clearOneof:(Lcom/google/protobuf/Descriptors$OneofDescriptor;)Lcom/google/rpc/context/AttributeContext$Auth$Builder;
       5: areturn

  public com.google.protobuf.GeneratedMessageV3$Builder clearField(com.google.protobuf.Descriptors$FieldDescriptor);
    Code:
       0: aload_0
       1: aload_1
       2: invokevirtual #109                // Method clearField:(Lcom/google/protobuf/Descriptors$FieldDescriptor;)Lcom/google/rpc/context/AttributeContext$Auth$Builder;
       5: areturn

  public com.google.protobuf.GeneratedMessageV3$Builder setField(com.google.protobuf.Descriptors$FieldDescriptor, java.lang.Object);
    Code:
       0: aload_0
       1: aload_1
       2: aload_2
       3: invokevirtual #110                // Method setField:(Lcom/google/protobuf/Descriptors$FieldDescriptor;Ljava/lang/Object;)Lcom/google/rpc/context/AttributeContext$Auth$Builder;
       6: areturn

  public com.google.protobuf.GeneratedMessageV3$Builder clear();
    Code:
       0: aload_0
       1: invokevirtual #111                // Method clear:()Lcom/google/rpc/context/AttributeContext$Auth$Builder;
       4: areturn

  public com.google.protobuf.GeneratedMessageV3$Builder clone();
    Code:
       0: aload_0
       1: invokevirtual #112                // Method clone:()Lcom/google/rpc/context/AttributeContext$Auth$Builder;
       4: areturn

  public com.google.protobuf.AbstractMessage$Builder mergeUnknownFields(com.google.protobuf.UnknownFieldSet);
    Code:
       0: aload_0
       1: aload_1
       2: invokevirtual #60                 // Method mergeUnknownFields:(Lcom/google/protobuf/UnknownFieldSet;)Lcom/google/rpc/context/AttributeContext$Auth$Builder;
       5: areturn

  public com.google.protobuf.AbstractMessage$Builder mergeFrom(com.google.protobuf.CodedInputStream, com.google.protobuf.ExtensionRegistryLite) throws java.io.IOException;
    Code:
       0: aload_0
       1: aload_1
       2: aload_2
       3: invokevirtual #113                // Method mergeFrom:(Lcom/google/protobuf/CodedInputStream;Lcom/google/protobuf/ExtensionRegistryLite;)Lcom/google/rpc/context/AttributeContext$Auth$Builder;
       6: areturn

  public com.google.protobuf.AbstractMessage$Builder mergeFrom(com.google.protobuf.Message);
    Code:
       0: aload_0
       1: aload_1
       2: invokevirtual #114                // Method mergeFrom:(Lcom/google/protobuf/Message;)Lcom/google/rpc/context/AttributeContext$Auth$Builder;
       5: areturn

  public com.google.protobuf.AbstractMessage$Builder clear();
    Code:
       0: aload_0
       1: invokevirtual #111                // Method clear:()Lcom/google/rpc/context/AttributeContext$Auth$Builder;
       4: areturn

  public com.google.protobuf.AbstractMessage$Builder clearOneof(com.google.protobuf.Descriptors$OneofDescriptor);
    Code:
       0: aload_0
       1: aload_1
       2: invokevirtual #108                // Method clearOneof:(Lcom/google/protobuf/Descriptors$OneofDescriptor;)Lcom/google/rpc/context/AttributeContext$Auth$Builder;
       5: areturn

  public com.google.protobuf.AbstractMessage$Builder clone();
    Code:
       0: aload_0
       1: invokevirtual #112                // Method clone:()Lcom/google/rpc/context/AttributeContext$Auth$Builder;
       4: areturn

  public com.google.protobuf.Message$Builder mergeUnknownFields(com.google.protobuf.UnknownFieldSet);
    Code:
       0: aload_0
       1: aload_1
       2: invokevirtual #60                 // Method mergeUnknownFields:(Lcom/google/protobuf/UnknownFieldSet;)Lcom/google/rpc/context/AttributeContext$Auth$Builder;
       5: areturn

  public com.google.protobuf.Message$Builder setUnknownFields(com.google.protobuf.UnknownFieldSet);
    Code:
       0: aload_0
       1: aload_1
       2: invokevirtual #105                // Method setUnknownFields:(Lcom/google/protobuf/UnknownFieldSet;)Lcom/google/rpc/context/AttributeContext$Auth$Builder;
       5: areturn

  public com.google.protobuf.Message$Builder addRepeatedField(com.google.protobuf.Descriptors$FieldDescriptor, java.lang.Object);
    Code:
       0: aload_0
       1: aload_1
       2: aload_2
       3: invokevirtual #106                // Method addRepeatedField:(Lcom/google/protobuf/Descriptors$FieldDescriptor;Ljava/lang/Object;)Lcom/google/rpc/context/AttributeContext$Auth$Builder;
       6: areturn

  public com.google.protobuf.Message$Builder setRepeatedField(com.google.protobuf.Descriptors$FieldDescriptor, int, java.lang.Object);
    Code:
       0: aload_0
       1: aload_1
       2: iload_2
       3: aload_3
       4: invokevirtual #107                // Method setRepeatedField:(Lcom/google/protobuf/Descriptors$FieldDescriptor;ILjava/lang/Object;)Lcom/google/rpc/context/AttributeContext$Auth$Builder;
       7: areturn

  public com.google.protobuf.Message$Builder clearOneof(com.google.protobuf.Descriptors$OneofDescriptor);
    Code:
       0: aload_0
       1: aload_1
       2: invokevirtual #108                // Method clearOneof:(Lcom/google/protobuf/Descriptors$OneofDescriptor;)Lcom/google/rpc/context/AttributeContext$Auth$Builder;
       5: areturn

  public com.google.protobuf.Message$Builder clearField(com.google.protobuf.Descriptors$FieldDescriptor);
    Code:
       0: aload_0
       1: aload_1
       2: invokevirtual #109                // Method clearField:(Lcom/google/protobuf/Descriptors$FieldDescriptor;)Lcom/google/rpc/context/AttributeContext$Auth$Builder;
       5: areturn

  public com.google.protobuf.Message$Builder setField(com.google.protobuf.Descriptors$FieldDescriptor, java.lang.Object);
    Code:
       0: aload_0
       1: aload_1
       2: aload_2
       3: invokevirtual #110                // Method setField:(Lcom/google/protobuf/Descriptors$FieldDescriptor;Ljava/lang/Object;)Lcom/google/rpc/context/AttributeContext$Auth$Builder;
       6: areturn

  public com.google.protobuf.Message$Builder mergeFrom(com.google.protobuf.CodedInputStream, com.google.protobuf.ExtensionRegistryLite) throws java.io.IOException;
    Code:
       0: aload_0
       1: aload_1
       2: aload_2
       3: invokevirtual #113                // Method mergeFrom:(Lcom/google/protobuf/CodedInputStream;Lcom/google/protobuf/ExtensionRegistryLite;)Lcom/google/rpc/context/AttributeContext$Auth$Builder;
       6: areturn

  public com.google.protobuf.Message$Builder clone();
    Code:
       0: aload_0
       1: invokevirtual #112                // Method clone:()Lcom/google/rpc/context/AttributeContext$Auth$Builder;
       4: areturn

  public com.google.protobuf.Message buildPartial();
    Code:
       0: aload_0
       1: invokevirtual #23                 // Method buildPartial:()Lcom/google/rpc/context/AttributeContext$Auth;
       4: areturn

  public com.google.protobuf.Message build();
    Code:
       0: aload_0
       1: invokevirtual #115                // Method build:()Lcom/google/rpc/context/AttributeContext$Auth;
       4: areturn

  public com.google.protobuf.Message$Builder mergeFrom(com.google.protobuf.Message);
    Code:
       0: aload_0
       1: aload_1
       2: invokevirtual #114                // Method mergeFrom:(Lcom/google/protobuf/Message;)Lcom/google/rpc/context/AttributeContext$Auth$Builder;
       5: areturn

  public com.google.protobuf.Message$Builder clear();
    Code:
       0: aload_0
       1: invokevirtual #111                // Method clear:()Lcom/google/rpc/context/AttributeContext$Auth$Builder;
       4: areturn

  public com.google.protobuf.MessageLite$Builder mergeFrom(com.google.protobuf.CodedInputStream, com.google.protobuf.ExtensionRegistryLite) throws java.io.IOException;
    Code:
       0: aload_0
       1: aload_1
       2: aload_2
       3: invokevirtual #113                // Method mergeFrom:(Lcom/google/protobuf/CodedInputStream;Lcom/google/protobuf/ExtensionRegistryLite;)Lcom/google/rpc/context/AttributeContext$Auth$Builder;
       6: areturn

  public com.google.protobuf.MessageLite$Builder clone();
    Code:
       0: aload_0
       1: invokevirtual #112                // Method clone:()Lcom/google/rpc/context/AttributeContext$Auth$Builder;
       4: areturn

  public com.google.protobuf.MessageLite buildPartial();
    Code:
       0: aload_0
       1: invokevirtual #23                 // Method buildPartial:()Lcom/google/rpc/context/AttributeContext$Auth;
       4: areturn

  public com.google.protobuf.MessageLite build();
    Code:
       0: aload_0
       1: invokevirtual #115                // Method build:()Lcom/google/rpc/context/AttributeContext$Auth;
       4: areturn

  public com.google.protobuf.MessageLite$Builder clear();
    Code:
       0: aload_0
       1: invokevirtual #111                // Method clear:()Lcom/google/rpc/context/AttributeContext$Auth$Builder;
       4: areturn

  public com.google.protobuf.MessageLite getDefaultInstanceForType();
    Code:
       0: aload_0
       1: invokevirtual #116                // Method getDefaultInstanceForType:()Lcom/google/rpc/context/AttributeContext$Auth;
       4: areturn

  public com.google.protobuf.Message getDefaultInstanceForType();
    Code:
       0: aload_0
       1: invokevirtual #116                // Method getDefaultInstanceForType:()Lcom/google/rpc/context/AttributeContext$Auth;
       4: areturn

  public com.google.protobuf.AbstractMessageLite$Builder mergeFrom(com.google.protobuf.CodedInputStream, com.google.protobuf.ExtensionRegistryLite) throws java.io.IOException;
    Code:
       0: aload_0
       1: aload_1
       2: aload_2
       3: invokevirtual #113                // Method mergeFrom:(Lcom/google/protobuf/CodedInputStream;Lcom/google/protobuf/ExtensionRegistryLite;)Lcom/google/rpc/context/AttributeContext$Auth$Builder;
       6: areturn

  public com.google.protobuf.AbstractMessageLite$Builder clone();
    Code:
       0: aload_0
       1: invokevirtual #112                // Method clone:()Lcom/google/rpc/context/AttributeContext$Auth$Builder;
       4: areturn

  public java.lang.Object clone() throws java.lang.CloneNotSupportedException;
    Code:
       0: aload_0
       1: invokevirtual #112                // Method clone:()Lcom/google/rpc/context/AttributeContext$Auth$Builder;
       4: areturn

  public java.util.List getAccessLevelsList();
    Code:
       0: aload_0
       1: invokevirtual #117                // Method getAccessLevelsList:()Lcom/google/protobuf/ProtocolStringList;
       4: areturn

  public java.util.List getAudiencesList();
    Code:
       0: aload_0
       1: invokevirtual #118                // Method getAudiencesList:()Lcom/google/protobuf/ProtocolStringList;
       4: areturn

  com.google.rpc.context.AttributeContext$Auth$Builder(com.google.rpc.context.AttributeContext$1);
    Code:
       0: aload_0
       1: invokespecial #2                  // Method "<init>":()V
       4: return

  com.google.rpc.context.AttributeContext$Auth$Builder(com.google.protobuf.GeneratedMessageV3$BuilderParent, com.google.rpc.context.AttributeContext$1);
    Code:
       0: aload_0
       1: aload_1
       2: invokespecial #1                  // Method "<init>":(Lcom/google/protobuf/GeneratedMessageV3$BuilderParent;)V
       5: return
}
