Compiled from "AttributeContextProto.java"
public final class com.google.rpc.context.AttributeContextProto {
  static final com.google.protobuf.Descriptors$Descriptor internal_static_google_rpc_context_AttributeContext_descriptor;

  static final com.google.protobuf.GeneratedMessageV3$FieldAccessorTable internal_static_google_rpc_context_AttributeContext_fieldAccessorTable;

  static final com.google.protobuf.Descriptors$Descriptor internal_static_google_rpc_context_AttributeContext_Peer_descriptor;

  static final com.google.protobuf.GeneratedMessageV3$FieldAccessorTable internal_static_google_rpc_context_AttributeContext_Peer_fieldAccessorTable;

  static final com.google.protobuf.Descriptors$Descriptor internal_static_google_rpc_context_AttributeContext_Peer_LabelsEntry_descriptor;

  static final com.google.protobuf.GeneratedMessageV3$FieldAccessorTable internal_static_google_rpc_context_AttributeContext_Peer_LabelsEntry_fieldAccessorTable;

  static final com.google.protobuf.Descriptors$Descriptor internal_static_google_rpc_context_AttributeContext_Api_descriptor;

  static final com.google.protobuf.GeneratedMessageV3$FieldAccessorTable internal_static_google_rpc_context_AttributeContext_Api_fieldAccessorTable;

  static final com.google.protobuf.Descriptors$Descriptor internal_static_google_rpc_context_AttributeContext_Auth_descriptor;

  static final com.google.protobuf.GeneratedMessageV3$FieldAccessorTable internal_static_google_rpc_context_AttributeContext_Auth_fieldAccessorTable;

  static final com.google.protobuf.Descriptors$Descriptor internal_static_google_rpc_context_AttributeContext_Request_descriptor;

  static final com.google.protobuf.GeneratedMessageV3$FieldAccessorTable internal_static_google_rpc_context_AttributeContext_Request_fieldAccessorTable;

  static final com.google.protobuf.Descriptors$Descriptor internal_static_google_rpc_context_AttributeContext_Request_HeadersEntry_descriptor;

  static final com.google.protobuf.GeneratedMessageV3$FieldAccessorTable internal_static_google_rpc_context_AttributeContext_Request_HeadersEntry_fieldAccessorTable;

  static final com.google.protobuf.Descriptors$Descriptor internal_static_google_rpc_context_AttributeContext_Response_descriptor;

  static final com.google.protobuf.GeneratedMessageV3$FieldAccessorTable internal_static_google_rpc_context_AttributeContext_Response_fieldAccessorTable;

  static final com.google.protobuf.Descriptors$Descriptor internal_static_google_rpc_context_AttributeContext_Response_HeadersEntry_descriptor;

  static final com.google.protobuf.GeneratedMessageV3$FieldAccessorTable internal_static_google_rpc_context_AttributeContext_Response_HeadersEntry_fieldAccessorTable;

  static final com.google.protobuf.Descriptors$Descriptor internal_static_google_rpc_context_AttributeContext_Resource_descriptor;

  static final com.google.protobuf.GeneratedMessageV3$FieldAccessorTable internal_static_google_rpc_context_AttributeContext_Resource_fieldAccessorTable;

  static final com.google.protobuf.Descriptors$Descriptor internal_static_google_rpc_context_AttributeContext_Resource_LabelsEntry_descriptor;

  static final com.google.protobuf.GeneratedMessageV3$FieldAccessorTable internal_static_google_rpc_context_AttributeContext_Resource_LabelsEntry_fieldAccessorTable;

  private static com.google.protobuf.Descriptors$FileDescriptor descriptor;

  private com.google.rpc.context.AttributeContextProto();
    Code:
       0: aload_0
       1: invokespecial #1                  // Method java/lang/Object."<init>":()V
       4: return

  public static void registerAllExtensions(com.google.protobuf.ExtensionRegistryLite);
    Code:
       0: return

  public static void registerAllExtensions(com.google.protobuf.ExtensionRegistry);
    Code:
       0: aload_0
       1: invokestatic  #2                  // Method registerAllExtensions:(Lcom/google/protobuf/ExtensionRegistryLite;)V
       4: return

  public static com.google.protobuf.Descriptors$FileDescriptor getDescriptor();
    Code:
       0: getstatic     #3                  // Field descriptor:Lcom/google/protobuf/Descriptors$FileDescriptor;
       3: areturn

  static {};
    Code:
       0: iconst_1
       1: anewarray     #4                  // class java/lang/String
       4: dup
       5: iconst_0
       6: ldc           #5                  // String \n*google/rpc/context/attribute_context.proto\u0012\u0012google.rpc.context\u001a\u0019google/protobuf/any.proto\u001a\u001cgoogle/protobuf/struct.proto\u001a\u001fgoogle/protobuf/timestamp.proto\"ð\f\n\u0010AttributeContext\u00129\n\u0006origin\u0018\u0007 \u0001(\u000b2).google.rpc.context.AttributeContext.Peer\u00129\n\u0006source\u0018\u0001 \u0001(\u000b2).google.rpc.context.AttributeContext.Peer\u0012>\n\u000bdestination\u0018\u0002 \u0001(\u000b2).google.rpc.context.AttributeContext.Peer\u0012=\n\u0007request\u0018\u0003 \u0001(\u000b2,.google.rpc.context.AttributeContext.Request\u0012?\n\bresponse\u0018\u0004 \u0001(\u000b2-.google.rpc.context.AttributeContext.Response\u0012?\n\bresource\u0018\u0005 \u0001(\u000b2-.google.rpc.context.AttributeContext.Resource\u00125\n\u0003api\u0018\u0006 \u0001(\u000b2(.google.rpc.context.AttributeContext.Api\u0012(\n\nextensions\u0018\b \u0003(\u000b2\u0014.google.protobuf.Any\u001a¾\u0001\n\u0004Peer\u0012\n\n\u0002ip\u0018\u0001 \u0001(\t\u0012\f\n\u0004port\u0018\u0002 \u0001(\u0003\u0012E\n\u0006labels\u0018\u0006 \u0003(\u000b25.google.rpc.context.AttributeContext.Peer.LabelsEntry\u0012\u0011\n\tprincipal\u0018\u0007 \u0001(\t\u0012\u0013\n\u000bregion_code\u0018\b \u0001(\t\u001a-\n\u000bLabelsEntry\u0012\u000b\n\u0003key\u0018\u0001 \u0001(\t\u0012\r\n\u0005value\u0018\u0002 \u0001(\t:\u00028\u0001\u001aL\n\u0003Api\u0012\u000f\n\u0007service\u0018\u0001 \u0001(\t\u0012\u0011\n\toperation\u0018\u0002 \u0001(\t\u0012\u0010\n\bprotocol\u0018\u0003 \u0001(\t\u0012\u000f\n\u0007version\u0018\u0004 \u0001(\t\u001a\u007f\n\u0004Auth\u0012\u0011\n\tprincipal\u0018\u0001 \u0001(\t\u0012\u0011\n\taudiences\u0018\u0002 \u0003(\t\u0012\u0011\n\tpresenter\u0018\u0003 \u0001(\t\u0012\'\n\u0006claims\u0018\u0004 \u0001(\u000b2\u0017.google.protobuf.Struct\u0012\u0015\n\raccess_levels\u0018\u0005 \u0003(\t\u001aï\u0002\n\u0007Request\u0012\n\n\u0002id\u0018\u0001 \u0001(\t\u0012\u000e\n\u0006method\u0018\u0002 \u0001(\t\u0012J\n\u0007headers\u0018\u0003 \u0003(\u000b29.google.rpc.context.AttributeContext.Request.HeadersEntry\u0012\f\n\u0004path\u0018\u0004 \u0001(\t\u0012\f\n\u0004host\u0018\u0005 \u0001(\t\u0012\u000e\n\u0006scheme\u0018\u0006 \u0001(\t\u0012\r\n\u0005query\u0018\u0007 \u0001(\t\u0012(\n\u0004time\u0018\t \u0001(\u000b2\u001a.google.protobuf.Timestamp\u0012\f\n\u0004size\u0018\n \u0001(\u0003\u0012\u0010\n\bprotocol\u0018\u000b \u0001(\t\u0012\u000e\n\u0006reason\u0018\f \u0001(\t\u00127\n\u0004auth\u0018\r \u0001(\u000b2).google.rpc.context.AttributeContext.Auth\u001a.\n\fHeadersEntry\u0012\u000b\n\u0003key\u0018\u0001 \u0001(\t\u0012\r\n\u0005value\u0018\u0002 \u0001(\t:\u00028\u0001\u001aÍ\u0001\n\bResponse\u0012\f\n\u0004code\u0018\u0001 \u0001(\u0003\u0012\f\n\u0004size\u0018\u0002 \u0001(\u0003\u0012K\n\u0007headers\u0018\u0003 \u0003(\u000b2:.google.rpc.context.AttributeContext.Response.HeadersEntry\u0012(\n\u0004time\u0018\u0004 \u0001(\u000b2\u001a.google.protobuf.Timestamp\u001a.\n\fHeadersEntry\u0012\u000b\n\u0003key\u0018\u0001 \u0001(\t\u0012\r\n\u0005value\u0018\u0002 \u0001(\t:\u00028\u0001\u001a±\u0001\n\bResource\u0012\u000f\n\u0007service\u0018\u0001 \u0001(\t\u0012\f\n\u0004name\u0018\u0002 \u0001(\t\u0012\f\n\u0004type\u0018\u0003 \u0001(\t\u0012I\n\u0006labels\u0018\u0004 \u0003(\u000b29.google.rpc.context.AttributeContext.Resource.LabelsEntry\u001a-\n\u000bLabelsEntry\u0012\u000b\n\u0003key\u0018\u0001 \u0001(\t\u0012\r\n\u0005value\u0018\u0002 \u0001(\t:\u00028\u0001B\u008b\u0001\n\u0016com.google.rpc.contextB\u0015AttributeContextProtoP\u0001ZUgoogle.golang.org/genproto/googleapis/rpc/context/attribute_context;attribute_contextø\u0001\u0001b\u0006proto3
       8: aastore
       9: astore_0
      10: aload_0
      11: iconst_3
      12: anewarray     #6                  // class com/google/protobuf/Descriptors$FileDescriptor
      15: dup
      16: iconst_0
      17: invokestatic  #7                  // Method com/google/protobuf/AnyProto.getDescriptor:()Lcom/google/protobuf/Descriptors$FileDescriptor;
      20: aastore
      21: dup
      22: iconst_1
      23: invokestatic  #8                  // Method com/google/protobuf/StructProto.getDescriptor:()Lcom/google/protobuf/Descriptors$FileDescriptor;
      26: aastore
      27: dup
      28: iconst_2
      29: invokestatic  #9                  // Method com/google/protobuf/TimestampProto.getDescriptor:()Lcom/google/protobuf/Descriptors$FileDescriptor;
      32: aastore
      33: invokestatic  #10                 // Method com/google/protobuf/Descriptors$FileDescriptor.internalBuildGeneratedFileFrom:([Ljava/lang/String;[Lcom/google/protobuf/Descriptors$FileDescriptor;)Lcom/google/protobuf/Descriptors$FileDescriptor;
      36: putstatic     #3                  // Field descriptor:Lcom/google/protobuf/Descriptors$FileDescriptor;
      39: invokestatic  #11                 // Method getDescriptor:()Lcom/google/protobuf/Descriptors$FileDescriptor;
      42: invokevirtual #12                 // Method com/google/protobuf/Descriptors$FileDescriptor.getMessageTypes:()Ljava/util/List;
      45: iconst_0
      46: invokeinterface #13,  2           // InterfaceMethod java/util/List.get:(I)Ljava/lang/Object;
      51: checkcast     #14                 // class com/google/protobuf/Descriptors$Descriptor
      54: putstatic     #15                 // Field internal_static_google_rpc_context_AttributeContext_descriptor:Lcom/google/protobuf/Descriptors$Descriptor;
      57: new           #16                 // class com/google/protobuf/GeneratedMessageV3$FieldAccessorTable
      60: dup
      61: getstatic     #15                 // Field internal_static_google_rpc_context_AttributeContext_descriptor:Lcom/google/protobuf/Descriptors$Descriptor;
      64: bipush        8
      66: anewarray     #4                  // class java/lang/String
      69: dup
      70: iconst_0
      71: ldc           #17                 // String Origin
      73: aastore
      74: dup
      75: iconst_1
      76: ldc           #18                 // String Source
      78: aastore
      79: dup
      80: iconst_2
      81: ldc           #19                 // String Destination
      83: aastore
      84: dup
      85: iconst_3
      86: ldc           #20                 // String Request
      88: aastore
      89: dup
      90: iconst_4
      91: ldc           #21                 // String Response
      93: aastore
      94: dup
      95: iconst_5
      96: ldc           #22                 // String Resource
      98: aastore
      99: dup
     100: bipush        6
     102: ldc           #23                 // String Api
     104: aastore
     105: dup
     106: bipush        7
     108: ldc           #24                 // String Extensions
     110: aastore
     111: invokespecial #25                 // Method com/google/protobuf/GeneratedMessageV3$FieldAccessorTable."<init>":(Lcom/google/protobuf/Descriptors$Descriptor;[Ljava/lang/String;)V
     114: putstatic     #26                 // Field internal_static_google_rpc_context_AttributeContext_fieldAccessorTable:Lcom/google/protobuf/GeneratedMessageV3$FieldAccessorTable;
     117: getstatic     #15                 // Field internal_static_google_rpc_context_AttributeContext_descriptor:Lcom/google/protobuf/Descriptors$Descriptor;
     120: invokevirtual #27                 // Method com/google/protobuf/Descriptors$Descriptor.getNestedTypes:()Ljava/util/List;
     123: iconst_0
     124: invokeinterface #13,  2           // InterfaceMethod java/util/List.get:(I)Ljava/lang/Object;
     129: checkcast     #14                 // class com/google/protobuf/Descriptors$Descriptor
     132: putstatic     #28                 // Field internal_static_google_rpc_context_AttributeContext_Peer_descriptor:Lcom/google/protobuf/Descriptors$Descriptor;
     135: new           #16                 // class com/google/protobuf/GeneratedMessageV3$FieldAccessorTable
     138: dup
     139: getstatic     #28                 // Field internal_static_google_rpc_context_AttributeContext_Peer_descriptor:Lcom/google/protobuf/Descriptors$Descriptor;
     142: iconst_5
     143: anewarray     #4                  // class java/lang/String
     146: dup
     147: iconst_0
     148: ldc           #29                 // String Ip
     150: aastore
     151: dup
     152: iconst_1
     153: ldc           #30                 // String Port
     155: aastore
     156: dup
     157: iconst_2
     158: ldc           #31                 // String Labels
     160: aastore
     161: dup
     162: iconst_3
     163: ldc           #32                 // String Principal
     165: aastore
     166: dup
     167: iconst_4
     168: ldc           #33                 // String RegionCode
     170: aastore
     171: invokespecial #25                 // Method com/google/protobuf/GeneratedMessageV3$FieldAccessorTable."<init>":(Lcom/google/protobuf/Descriptors$Descriptor;[Ljava/lang/String;)V
     174: putstatic     #34                 // Field internal_static_google_rpc_context_AttributeContext_Peer_fieldAccessorTable:Lcom/google/protobuf/GeneratedMessageV3$FieldAccessorTable;
     177: getstatic     #28                 // Field internal_static_google_rpc_context_AttributeContext_Peer_descriptor:Lcom/google/protobuf/Descriptors$Descriptor;
     180: invokevirtual #27                 // Method com/google/protobuf/Descriptors$Descriptor.getNestedTypes:()Ljava/util/List;
     183: iconst_0
     184: invokeinterface #13,  2           // InterfaceMethod java/util/List.get:(I)Ljava/lang/Object;
     189: checkcast     #14                 // class com/google/protobuf/Descriptors$Descriptor
     192: putstatic     #35                 // Field internal_static_google_rpc_context_AttributeContext_Peer_LabelsEntry_descriptor:Lcom/google/protobuf/Descriptors$Descriptor;
     195: new           #16                 // class com/google/protobuf/GeneratedMessageV3$FieldAccessorTable
     198: dup
     199: getstatic     #35                 // Field internal_static_google_rpc_context_AttributeContext_Peer_LabelsEntry_descriptor:Lcom/google/protobuf/Descriptors$Descriptor;
     202: iconst_2
     203: anewarray     #4                  // class java/lang/String
     206: dup
     207: iconst_0
     208: ldc           #36                 // String Key
     210: aastore
     211: dup
     212: iconst_1
     213: ldc           #37                 // String Value
     215: aastore
     216: invokespecial #25                 // Method com/google/protobuf/GeneratedMessageV3$FieldAccessorTable."<init>":(Lcom/google/protobuf/Descriptors$Descriptor;[Ljava/lang/String;)V
     219: putstatic     #38                 // Field internal_static_google_rpc_context_AttributeContext_Peer_LabelsEntry_fieldAccessorTable:Lcom/google/protobuf/GeneratedMessageV3$FieldAccessorTable;
     222: getstatic     #15                 // Field internal_static_google_rpc_context_AttributeContext_descriptor:Lcom/google/protobuf/Descriptors$Descriptor;
     225: invokevirtual #27                 // Method com/google/protobuf/Descriptors$Descriptor.getNestedTypes:()Ljava/util/List;
     228: iconst_1
     229: invokeinterface #13,  2           // InterfaceMethod java/util/List.get:(I)Ljava/lang/Object;
     234: checkcast     #14                 // class com/google/protobuf/Descriptors$Descriptor
     237: putstatic     #39                 // Field internal_static_google_rpc_context_AttributeContext_Api_descriptor:Lcom/google/protobuf/Descriptors$Descriptor;
     240: new           #16                 // class com/google/protobuf/GeneratedMessageV3$FieldAccessorTable
     243: dup
     244: getstatic     #39                 // Field internal_static_google_rpc_context_AttributeContext_Api_descriptor:Lcom/google/protobuf/Descriptors$Descriptor;
     247: iconst_4
     248: anewarray     #4                  // class java/lang/String
     251: dup
     252: iconst_0
     253: ldc           #40                 // String Service
     255: aastore
     256: dup
     257: iconst_1
     258: ldc           #41                 // String Operation
     260: aastore
     261: dup
     262: iconst_2
     263: ldc           #42                 // String Protocol
     265: aastore
     266: dup
     267: iconst_3
     268: ldc           #43                 // String Version
     270: aastore
     271: invokespecial #25                 // Method com/google/protobuf/GeneratedMessageV3$FieldAccessorTable."<init>":(Lcom/google/protobuf/Descriptors$Descriptor;[Ljava/lang/String;)V
     274: putstatic     #44                 // Field internal_static_google_rpc_context_AttributeContext_Api_fieldAccessorTable:Lcom/google/protobuf/GeneratedMessageV3$FieldAccessorTable;
     277: getstatic     #15                 // Field internal_static_google_rpc_context_AttributeContext_descriptor:Lcom/google/protobuf/Descriptors$Descriptor;
     280: invokevirtual #27                 // Method com/google/protobuf/Descriptors$Descriptor.getNestedTypes:()Ljava/util/List;
     283: iconst_2
     284: invokeinterface #13,  2           // InterfaceMethod java/util/List.get:(I)Ljava/lang/Object;
     289: checkcast     #14                 // class com/google/protobuf/Descriptors$Descriptor
     292: putstatic     #45                 // Field internal_static_google_rpc_context_AttributeContext_Auth_descriptor:Lcom/google/protobuf/Descriptors$Descriptor;
     295: new           #16                 // class com/google/protobuf/GeneratedMessageV3$FieldAccessorTable
     298: dup
     299: getstatic     #45                 // Field internal_static_google_rpc_context_AttributeContext_Auth_descriptor:Lcom/google/protobuf/Descriptors$Descriptor;
     302: iconst_5
     303: anewarray     #4                  // class java/lang/String
     306: dup
     307: iconst_0
     308: ldc           #32                 // String Principal
     310: aastore
     311: dup
     312: iconst_1
     313: ldc           #46                 // String Audiences
     315: aastore
     316: dup
     317: iconst_2
     318: ldc           #47                 // String Presenter
     320: aastore
     321: dup
     322: iconst_3
     323: ldc           #48                 // String Claims
     325: aastore
     326: dup
     327: iconst_4
     328: ldc           #49                 // String AccessLevels
     330: aastore
     331: invokespecial #25                 // Method com/google/protobuf/GeneratedMessageV3$FieldAccessorTable."<init>":(Lcom/google/protobuf/Descriptors$Descriptor;[Ljava/lang/String;)V
     334: putstatic     #50                 // Field internal_static_google_rpc_context_AttributeContext_Auth_fieldAccessorTable:Lcom/google/protobuf/GeneratedMessageV3$FieldAccessorTable;
     337: getstatic     #15                 // Field internal_static_google_rpc_context_AttributeContext_descriptor:Lcom/google/protobuf/Descriptors$Descriptor;
     340: invokevirtual #27                 // Method com/google/protobuf/Descriptors$Descriptor.getNestedTypes:()Ljava/util/List;
     343: iconst_3
     344: invokeinterface #13,  2           // InterfaceMethod java/util/List.get:(I)Ljava/lang/Object;
     349: checkcast     #14                 // class com/google/protobuf/Descriptors$Descriptor
     352: putstatic     #51                 // Field internal_static_google_rpc_context_AttributeContext_Request_descriptor:Lcom/google/protobuf/Descriptors$Descriptor;
     355: new           #16                 // class com/google/protobuf/GeneratedMessageV3$FieldAccessorTable
     358: dup
     359: getstatic     #51                 // Field internal_static_google_rpc_context_AttributeContext_Request_descriptor:Lcom/google/protobuf/Descriptors$Descriptor;
     362: bipush        12
     364: anewarray     #4                  // class java/lang/String
     367: dup
     368: iconst_0
     369: ldc           #52                 // String Id
     371: aastore
     372: dup
     373: iconst_1
     374: ldc           #53                 // String Method
     376: aastore
     377: dup
     378: iconst_2
     379: ldc           #54                 // String Headers
     381: aastore
     382: dup
     383: iconst_3
     384: ldc           #55                 // String Path
     386: aastore
     387: dup
     388: iconst_4
     389: ldc           #56                 // String Host
     391: aastore
     392: dup
     393: iconst_5
     394: ldc           #57                 // String Scheme
     396: aastore
     397: dup
     398: bipush        6
     400: ldc           #58                 // String Query
     402: aastore
     403: dup
     404: bipush        7
     406: ldc           #59                 // String Time
     408: aastore
     409: dup
     410: bipush        8
     412: ldc           #60                 // String Size
     414: aastore
     415: dup
     416: bipush        9
     418: ldc           #42                 // String Protocol
     420: aastore
     421: dup
     422: bipush        10
     424: ldc           #61                 // String Reason
     426: aastore
     427: dup
     428: bipush        11
     430: ldc           #62                 // String Auth
     432: aastore
     433: invokespecial #25                 // Method com/google/protobuf/GeneratedMessageV3$FieldAccessorTable."<init>":(Lcom/google/protobuf/Descriptors$Descriptor;[Ljava/lang/String;)V
     436: putstatic     #63                 // Field internal_static_google_rpc_context_AttributeContext_Request_fieldAccessorTable:Lcom/google/protobuf/GeneratedMessageV3$FieldAccessorTable;
     439: getstatic     #51                 // Field internal_static_google_rpc_context_AttributeContext_Request_descriptor:Lcom/google/protobuf/Descriptors$Descriptor;
     442: invokevirtual #27                 // Method com/google/protobuf/Descriptors$Descriptor.getNestedTypes:()Ljava/util/List;
     445: iconst_0
     446: invokeinterface #13,  2           // InterfaceMethod java/util/List.get:(I)Ljava/lang/Object;
     451: checkcast     #14                 // class com/google/protobuf/Descriptors$Descriptor
     454: putstatic     #64                 // Field internal_static_google_rpc_context_AttributeContext_Request_HeadersEntry_descriptor:Lcom/google/protobuf/Descriptors$Descriptor;
     457: new           #16                 // class com/google/protobuf/GeneratedMessageV3$FieldAccessorTable
     460: dup
     461: getstatic     #64                 // Field internal_static_google_rpc_context_AttributeContext_Request_HeadersEntry_descriptor:Lcom/google/protobuf/Descriptors$Descriptor;
     464: iconst_2
     465: anewarray     #4                  // class java/lang/String
     468: dup
     469: iconst_0
     470: ldc           #36                 // String Key
     472: aastore
     473: dup
     474: iconst_1
     475: ldc           #37                 // String Value
     477: aastore
     478: invokespecial #25                 // Method com/google/protobuf/GeneratedMessageV3$FieldAccessorTable."<init>":(Lcom/google/protobuf/Descriptors$Descriptor;[Ljava/lang/String;)V
     481: putstatic     #65                 // Field internal_static_google_rpc_context_AttributeContext_Request_HeadersEntry_fieldAccessorTable:Lcom/google/protobuf/GeneratedMessageV3$FieldAccessorTable;
     484: getstatic     #15                 // Field internal_static_google_rpc_context_AttributeContext_descriptor:Lcom/google/protobuf/Descriptors$Descriptor;
     487: invokevirtual #27                 // Method com/google/protobuf/Descriptors$Descriptor.getNestedTypes:()Ljava/util/List;
     490: iconst_4
     491: invokeinterface #13,  2           // InterfaceMethod java/util/List.get:(I)Ljava/lang/Object;
     496: checkcast     #14                 // class com/google/protobuf/Descriptors$Descriptor
     499: putstatic     #66                 // Field internal_static_google_rpc_context_AttributeContext_Response_descriptor:Lcom/google/protobuf/Descriptors$Descriptor;
     502: new           #16                 // class com/google/protobuf/GeneratedMessageV3$FieldAccessorTable
     505: dup
     506: getstatic     #66                 // Field internal_static_google_rpc_context_AttributeContext_Response_descriptor:Lcom/google/protobuf/Descriptors$Descriptor;
     509: iconst_4
     510: anewarray     #4                  // class java/lang/String
     513: dup
     514: iconst_0
     515: ldc           #67                 // String Code
     517: aastore
     518: dup
     519: iconst_1
     520: ldc           #60                 // String Size
     522: aastore
     523: dup
     524: iconst_2
     525: ldc           #54                 // String Headers
     527: aastore
     528: dup
     529: iconst_3
     530: ldc           #59                 // String Time
     532: aastore
     533: invokespecial #25                 // Method com/google/protobuf/GeneratedMessageV3$FieldAccessorTable."<init>":(Lcom/google/protobuf/Descriptors$Descriptor;[Ljava/lang/String;)V
     536: putstatic     #68                 // Field internal_static_google_rpc_context_AttributeContext_Response_fieldAccessorTable:Lcom/google/protobuf/GeneratedMessageV3$FieldAccessorTable;
     539: getstatic     #66                 // Field internal_static_google_rpc_context_AttributeContext_Response_descriptor:Lcom/google/protobuf/Descriptors$Descriptor;
     542: invokevirtual #27                 // Method com/google/protobuf/Descriptors$Descriptor.getNestedTypes:()Ljava/util/List;
     545: iconst_0
     546: invokeinterface #13,  2           // InterfaceMethod java/util/List.get:(I)Ljava/lang/Object;
     551: checkcast     #14                 // class com/google/protobuf/Descriptors$Descriptor
     554: putstatic     #69                 // Field internal_static_google_rpc_context_AttributeContext_Response_HeadersEntry_descriptor:Lcom/google/protobuf/Descriptors$Descriptor;
     557: new           #16                 // class com/google/protobuf/GeneratedMessageV3$FieldAccessorTable
     560: dup
     561: getstatic     #69                 // Field internal_static_google_rpc_context_AttributeContext_Response_HeadersEntry_descriptor:Lcom/google/protobuf/Descriptors$Descriptor;
     564: iconst_2
     565: anewarray     #4                  // class java/lang/String
     568: dup
     569: iconst_0
     570: ldc           #36                 // String Key
     572: aastore
     573: dup
     574: iconst_1
     575: ldc           #37                 // String Value
     577: aastore
     578: invokespecial #25                 // Method com/google/protobuf/GeneratedMessageV3$FieldAccessorTable."<init>":(Lcom/google/protobuf/Descriptors$Descriptor;[Ljava/lang/String;)V
     581: putstatic     #70                 // Field internal_static_google_rpc_context_AttributeContext_Response_HeadersEntry_fieldAccessorTable:Lcom/google/protobuf/GeneratedMessageV3$FieldAccessorTable;
     584: getstatic     #15                 // Field internal_static_google_rpc_context_AttributeContext_descriptor:Lcom/google/protobuf/Descriptors$Descriptor;
     587: invokevirtual #27                 // Method com/google/protobuf/Descriptors$Descriptor.getNestedTypes:()Ljava/util/List;
     590: iconst_5
     591: invokeinterface #13,  2           // InterfaceMethod java/util/List.get:(I)Ljava/lang/Object;
     596: checkcast     #14                 // class com/google/protobuf/Descriptors$Descriptor
     599: putstatic     #71                 // Field internal_static_google_rpc_context_AttributeContext_Resource_descriptor:Lcom/google/protobuf/Descriptors$Descriptor;
     602: new           #16                 // class com/google/protobuf/GeneratedMessageV3$FieldAccessorTable
     605: dup
     606: getstatic     #71                 // Field internal_static_google_rpc_context_AttributeContext_Resource_descriptor:Lcom/google/protobuf/Descriptors$Descriptor;
     609: iconst_4
     610: anewarray     #4                  // class java/lang/String
     613: dup
     614: iconst_0
     615: ldc           #40                 // String Service
     617: aastore
     618: dup
     619: iconst_1
     620: ldc           #72                 // String Name
     622: aastore
     623: dup
     624: iconst_2
     625: ldc           #73                 // String Type
     627: aastore
     628: dup
     629: iconst_3
     630: ldc           #31                 // String Labels
     632: aastore
     633: invokespecial #25                 // Method com/google/protobuf/GeneratedMessageV3$FieldAccessorTable."<init>":(Lcom/google/protobuf/Descriptors$Descriptor;[Ljava/lang/String;)V
     636: putstatic     #74                 // Field internal_static_google_rpc_context_AttributeContext_Resource_fieldAccessorTable:Lcom/google/protobuf/GeneratedMessageV3$FieldAccessorTable;
     639: getstatic     #71                 // Field internal_static_google_rpc_context_AttributeContext_Resource_descriptor:Lcom/google/protobuf/Descriptors$Descriptor;
     642: invokevirtual #27                 // Method com/google/protobuf/Descriptors$Descriptor.getNestedTypes:()Ljava/util/List;
     645: iconst_0
     646: invokeinterface #13,  2           // InterfaceMethod java/util/List.get:(I)Ljava/lang/Object;
     651: checkcast     #14                 // class com/google/protobuf/Descriptors$Descriptor
     654: putstatic     #75                 // Field internal_static_google_rpc_context_AttributeContext_Resource_LabelsEntry_descriptor:Lcom/google/protobuf/Descriptors$Descriptor;
     657: new           #16                 // class com/google/protobuf/GeneratedMessageV3$FieldAccessorTable
     660: dup
     661: getstatic     #75                 // Field internal_static_google_rpc_context_AttributeContext_Resource_LabelsEntry_descriptor:Lcom/google/protobuf/Descriptors$Descriptor;
     664: iconst_2
     665: anewarray     #4                  // class java/lang/String
     668: dup
     669: iconst_0
     670: ldc           #36                 // String Key
     672: aastore
     673: dup
     674: iconst_1
     675: ldc           #37                 // String Value
     677: aastore
     678: invokespecial #25                 // Method com/google/protobuf/GeneratedMessageV3$FieldAccessorTable."<init>":(Lcom/google/protobuf/Descriptors$Descriptor;[Ljava/lang/String;)V
     681: putstatic     #76                 // Field internal_static_google_rpc_context_AttributeContext_Resource_LabelsEntry_fieldAccessorTable:Lcom/google/protobuf/GeneratedMessageV3$FieldAccessorTable;
     684: invokestatic  #7                  // Method com/google/protobuf/AnyProto.getDescriptor:()Lcom/google/protobuf/Descriptors$FileDescriptor;
     687: pop
     688: invokestatic  #8                  // Method com/google/protobuf/StructProto.getDescriptor:()Lcom/google/protobuf/Descriptors$FileDescriptor;
     691: pop
     692: invokestatic  #9                  // Method com/google/protobuf/TimestampProto.getDescriptor:()Lcom/google/protobuf/Descriptors$FileDescriptor;
     695: pop
     696: return
}
