Compiled from "Scanner.java"
public class net.oneandone.sushi.fs.http.model.Scanner {
  private int pos;

  public net.oneandone.sushi.fs.http.model.Scanner();
    Code:
       0: aload_0
       1: invokespecial #1                  // Method java/lang/Object."<init>":()V
       4: aload_0
       5: iconst_0
       6: putfield      #2                  // Field pos:I
       9: return

  public java.lang.String parseProtocol(java.lang.String);
    Code:
       0: aload_0
       1: aload_1
       2: invokevirtual #3                  // Method skipWhitespace:(Ljava/lang/String;)I
       5: pop
       6: aload_0
       7: getfield      #2                  // Field pos:I
      10: istore_2
      11: aload_1
      12: ldc           #5                  // String HTTP/1.1
      14: iload_2
      15: invokevirtual #6                  // Method java/lang/String.startsWith:(Ljava/lang/String;I)Z
      18: ifeq          35
      21: aload_0
      22: iload_2
      23: ldc           #5                  // String HTTP/1.1
      25: invokevirtual #7                  // Method java/lang/String.length:()I
      28: iadd
      29: putfield      #2                  // Field pos:I
      32: ldc           #5                  // String HTTP/1.1
      34: areturn
      35: aload_0
      36: aload_1
      37: bipush        32
      39: iload_2
      40: invokevirtual #8                  // Method java/lang/String.indexOf:(II)I
      43: putfield      #2                  // Field pos:I
      46: aload_0
      47: getfield      #2                  // Field pos:I
      50: iconst_m1
      51: if_icmpne     62
      54: aload_0
      55: aload_1
      56: invokevirtual #7                  // Method java/lang/String.length:()I
      59: putfield      #2                  // Field pos:I
      62: aload_1
      63: iload_2
      64: aload_0
      65: getfield      #2                  // Field pos:I
      68: invokevirtual #9                  // Method java/lang/String.substring:(II)Ljava/lang/String;
      71: areturn

  public int skipWhitespace(java.lang.String);
    Code:
       0: aload_0
       1: getfield      #2                  // Field pos:I
       4: aload_1
       5: invokevirtual #7                  // Method java/lang/String.length:()I
       8: if_icmpge     38
      11: aload_1
      12: aload_0
      13: getfield      #2                  // Field pos:I
      16: invokevirtual #10                 // Method java/lang/String.charAt:(I)C
      19: invokestatic  #11                 // Method isWhitespace:(C)Z
      22: ifeq          38
      25: aload_0
      26: dup
      27: getfield      #2                  // Field pos:I
      30: iconst_1
      31: iadd
      32: putfield      #2                  // Field pos:I
      35: goto          0
      38: aload_0
      39: getfield      #2                  // Field pos:I
      42: ireturn

  public static boolean isWhitespace(char);
    Code:
       0: iload_0
       1: bipush        32
       3: if_icmpeq     24
       6: iload_0
       7: bipush        9
       9: if_icmpeq     24
      12: iload_0
      13: bipush        10
      15: if_icmpeq     24
      18: iload_0
      19: bipush        13
      21: if_icmpne     28
      24: iconst_1
      25: goto          29
      28: iconst_0
      29: ireturn

  public static java.lang.String substringTrimmed(java.lang.String, int, int);
    Code:
       0: iload_1
       1: istore_3
       2: iload_2
       3: istore        4
       5: iload_3
       6: iload_2
       7: if_icmpge     27
      10: aload_0
      11: iload_3
      12: invokevirtual #10                 // Method java/lang/String.charAt:(I)C
      15: invokestatic  #11                 // Method isWhitespace:(C)Z
      18: ifeq          27
      21: iinc          3, 1
      24: goto          5
      27: iload         4
      29: iload_3
      30: if_icmple     53
      33: aload_0
      34: iload         4
      36: iconst_1
      37: isub
      38: invokevirtual #10                 // Method java/lang/String.charAt:(I)C
      41: invokestatic  #11                 // Method isWhitespace:(C)Z
      44: ifeq          53
      47: iinc          4, -1
      50: goto          27
      53: aload_0
      54: iload_3
      55: iload         4
      57: invokevirtual #9                  // Method java/lang/String.substring:(II)Ljava/lang/String;
      60: areturn
}
