Compiled from "ContainerInitializer.java"
public interface de.theitshop.container.ContainerInitializer {
  public static final org.slf4j.Logger logger;

  public abstract java.util.Map<java.lang.String, java.lang.String> containerEnvironmentVariables(de.theitshop.model.config.Service, de.theitshop.model.container.ProcessedServices);

  public abstract java.lang.Integer[] containerExposedPorts(de.theitshop.model.config.Service);

  public abstract java.lang.String containerStartupCommand(de.theitshop.model.config.Service);

  public abstract java.util.List<de.theitshop.model.config.ContainerVolume> containerAttachedVolumes(de.theitshop.model.config.Service);

  public abstract org.testcontainers.containers.wait.strategy.WaitStrategy containerLogWaiter(de.theitshop.model.config.Service);

  public abstract org.testcontainers.containers.wait.strategy.WaitStrategy containerServiceHTTPWaiter(de.theitshop.model.config.Service);

  public default de.theitshop.model.container.RunningContainer getContainer(org.testcontainers.containers.Network, de.theitshop.model.config.Service, de.theitshop.model.container.ProcessedServices);
    Code:
       0: aload_0
       1: aload_2
       2: aload_3
       3: invokeinterface #1,  3            // InterfaceMethod containerEnvironmentVariables:(Lde/theitshop/model/config/Service;Lde/theitshop/model/container/ProcessedServices;)Ljava/util/Map;
       8: astore        4
      10: aload_0
      11: aload_2
      12: invokeinterface #7,  2            // InterfaceMethod containerStartupCommand:(Lde/theitshop/model/config/Service;)Ljava/lang/String;
      17: astore        5
      19: aload_0
      20: aload_2
      21: invokeinterface #11,  2           // InterfaceMethod containerAttachedVolumes:(Lde/theitshop/model/config/Service;)Ljava/util/List;
      26: astore        6
      28: aload_0
      29: aload_2
      30: invokeinterface #15,  2           // InterfaceMethod containerServiceHTTPWaiter:(Lde/theitshop/model/config/Service;)Lorg/testcontainers/containers/wait/strategy/WaitStrategy;
      35: astore        7
      37: aload_0
      38: aload_2
      39: invokeinterface #19,  2           // InterfaceMethod containerLogWaiter:(Lde/theitshop/model/config/Service;)Lorg/testcontainers/containers/wait/strategy/WaitStrategy;
      44: astore        8
      46: aload_2
      47: invokevirtual #22                 // Method de/theitshop/model/config/Service.getImage:()Ljava/lang/String;
      50: invokestatic  #28                 // Method org/testcontainers/utility/DockerImageName.parse:(Ljava/lang/String;)Lorg/testcontainers/utility/DockerImageName;
      53: astore        9
      55: aconst_null
      56: astore        10
      58: aload_2
      59: invokevirtual #34                 // Method de/theitshop/model/config/Service.getTestContainersModule:()Lde/theitshop/model/config/containermodules/TestContainersModule;
      62: ifnull        89
      65: aload_2
      66: invokevirtual #34                 // Method de/theitshop/model/config/Service.getTestContainersModule:()Lde/theitshop/model/config/containermodules/TestContainersModule;
      69: invokevirtual #38                 // Method de/theitshop/model/config/containermodules/TestContainersModule.getModuleParameters:()Lde/theitshop/model/config/containermodules/ContainerModuleParameters;
      72: aload_2
      73: invokevirtual #44                 // Method de/theitshop/model/config/Service.getName:()Ljava/lang/String;
      76: aload         9
      78: aload_3
      79: invokeinterface #47,  4           // InterfaceMethod de/theitshop/model/config/containermodules/ContainerModuleParameters.moduleContainer:(Ljava/lang/String;Lorg/testcontainers/utility/DockerImageName;Lde/theitshop/model/container/ProcessedServices;)Lorg/testcontainers/containers/GenericContainer;
      84: astore        10
      86: goto          109
      89: new           #53                 // class org/testcontainers/containers/GenericContainer
      92: dup
      93: aload         9
      95: invokespecial #55                 // Method org/testcontainers/containers/GenericContainer."<init>":(Lorg/testcontainers/utility/DockerImageName;)V
      98: astore        10
     100: aload         10
     102: invokestatic  #59                 // Method org/testcontainers/images/PullPolicy.defaultPolicy:()Lorg/testcontainers/images/ImagePullPolicy;
     105: invokevirtual #65                 // Method org/testcontainers/containers/GenericContainer.withImagePullPolicy:(Lorg/testcontainers/images/ImagePullPolicy;)Lorg/testcontainers/containers/GenericContainer;
     108: pop
     109: aload         10
     111: aload_1
     112: invokevirtual #69                 // Method org/testcontainers/containers/GenericContainer.withNetwork:(Lorg/testcontainers/containers/Network;)Lorg/testcontainers/containers/GenericContainer;
     115: pop
     116: aload         10
     118: aload         4
     120: invokevirtual #73                 // Method org/testcontainers/containers/GenericContainer.withEnv:(Ljava/util/Map;)Lorg/testcontainers/containers/GenericContainer;
     123: pop
     124: aload         10
     126: aload_0
     127: aload_2
     128: invokeinterface #77,  2           // InterfaceMethod containerExposedPorts:(Lde/theitshop/model/config/Service;)[Ljava/lang/Integer;
     133: invokevirtual #81                 // Method org/testcontainers/containers/GenericContainer.withExposedPorts:([Ljava/lang/Integer;)Lorg/testcontainers/containers/GenericContainer;
     136: pop
     137: aload         5
     139: ifnull        150
     142: aload         10
     144: aload         5
     146: invokevirtual #85                 // Method org/testcontainers/containers/GenericContainer.withCommand:(Ljava/lang/String;)Lorg/testcontainers/containers/GenericContainer;
     149: pop
     150: aload         6
     152: invokeinterface #89,  1           // InterfaceMethod java/util/List.iterator:()Ljava/util/Iterator;
     157: astore        11
     159: aload         11
     161: invokeinterface #95,  1           // InterfaceMethod java/util/Iterator.hasNext:()Z
     166: ifeq          243
     169: aload         11
     171: invokeinterface #101,  1          // InterfaceMethod java/util/Iterator.next:()Ljava/lang/Object;
     176: checkcast     #105                // class de/theitshop/model/config/ContainerVolume
     179: astore        12
     181: aload         12
     183: invokevirtual #107                // Method de/theitshop/model/config/ContainerVolume.getSource:()Lde/theitshop/model/config/VolumeSourceType;
     186: getstatic     #111                // Field de/theitshop/model/config/VolumeSourceType.RESOURCE_PATH:Lde/theitshop/model/config/VolumeSourceType;
     189: invokevirtual #117                // Method de/theitshop/model/config/VolumeSourceType.equals:(Ljava/lang/Object;)Z
     192: ifeq          219
     195: aload         10
     197: aload         12
     199: invokevirtual #121                // Method de/theitshop/model/config/ContainerVolume.getHost:()Ljava/lang/String;
     202: aload         12
     204: invokevirtual #124                // Method de/theitshop/model/config/ContainerVolume.getContainer:()Ljava/lang/String;
     207: aload         12
     209: invokevirtual #127                // Method de/theitshop/model/config/ContainerVolume.getMode:()Lorg/testcontainers/containers/BindMode;
     212: invokevirtual #131                // Method org/testcontainers/containers/GenericContainer.withClasspathResourceMapping:(Ljava/lang/String;Ljava/lang/String;Lorg/testcontainers/containers/BindMode;)Lorg/testcontainers/containers/GenericContainer;
     215: pop
     216: goto          240
     219: aload         10
     221: aload         12
     223: invokevirtual #121                // Method de/theitshop/model/config/ContainerVolume.getHost:()Ljava/lang/String;
     226: aload         12
     228: invokevirtual #124                // Method de/theitshop/model/config/ContainerVolume.getContainer:()Ljava/lang/String;
     231: aload         12
     233: invokevirtual #127                // Method de/theitshop/model/config/ContainerVolume.getMode:()Lorg/testcontainers/containers/BindMode;
     236: invokevirtual #135                // Method org/testcontainers/containers/GenericContainer.withFileSystemBind:(Ljava/lang/String;Ljava/lang/String;Lorg/testcontainers/containers/BindMode;)Lorg/testcontainers/containers/GenericContainer;
     239: pop
     240: goto          159
     243: aload         10
     245: aload         7
     247: invokevirtual #138                // Method org/testcontainers/containers/GenericContainer.waitingFor:(Lorg/testcontainers/containers/wait/strategy/WaitStrategy;)Lorg/testcontainers/containers/GenericContainer;
     250: pop
     251: aload         10
     253: aload         8
     255: invokevirtual #138                // Method org/testcontainers/containers/GenericContainer.waitingFor:(Lorg/testcontainers/containers/wait/strategy/WaitStrategy;)Lorg/testcontainers/containers/GenericContainer;
     258: pop
     259: aload_2
     260: invokevirtual #142                // Method de/theitshop/model/config/Service.getDependsOn:()Ljava/util/List;
     263: ifnull        332
     266: aload_2
     267: invokevirtual #142                // Method de/theitshop/model/config/Service.getDependsOn:()Ljava/util/List;
     270: invokeinterface #89,  1           // InterfaceMethod java/util/List.iterator:()Ljava/util/Iterator;
     275: astore        11
     277: aload         11
     279: invokeinterface #95,  1           // InterfaceMethod java/util/Iterator.hasNext:()Z
     284: ifeq          332
     287: aload         11
     289: invokeinterface #101,  1          // InterfaceMethod java/util/Iterator.next:()Ljava/lang/Object;
     294: checkcast     #146                // class java/lang/String
     297: astore        12
     299: aload         10
     301: iconst_1
     302: anewarray     #148                // class org/testcontainers/lifecycle/Startable
     305: dup
     306: iconst_0
     307: aload_3
     308: invokevirtual #150                // Method de/theitshop/model/container/ProcessedServices.getProcessedServices:()Ljava/util/Map;
     311: aload         12
     313: invokeinterface #156,  2          // InterfaceMethod java/util/Map.get:(Ljava/lang/Object;)Ljava/lang/Object;
     318: checkcast     #162                // class de/theitshop/model/container/RunningContainer
     321: invokevirtual #164                // Method de/theitshop/model/container/RunningContainer.getContainer:()Lorg/testcontainers/containers/GenericContainer;
     324: aastore
     325: invokevirtual #167                // Method org/testcontainers/containers/GenericContainer.dependsOn:([Lorg/testcontainers/lifecycle/Startable;)Lorg/testcontainers/containers/GenericContainer;
     328: pop
     329: goto          277
     332: aload         10
     334: aload_2
     335: invokedynamic #171,  0            // InvokeDynamic #0:accept:(Lde/theitshop/model/config/Service;)Ljava/util/function/Consumer;
     340: invokevirtual #175                // Method org/testcontainers/containers/GenericContainer.withCreateContainerCmdModifier:(Ljava/util/function/Consumer;)Lorg/testcontainers/containers/GenericContainer;
     343: pop
     344: aload         10
     346: new           #179                // class org/testcontainers/containers/output/Slf4jLogConsumer
     349: dup
     350: getstatic     #181                // Field logger:Lorg/slf4j/Logger;
     353: invokespecial #185                // Method org/testcontainers/containers/output/Slf4jLogConsumer."<init>":(Lorg/slf4j/Logger;)V
     356: invokevirtual #188                // Method org/testcontainers/containers/GenericContainer.withLogConsumer:(Ljava/util/function/Consumer;)Lorg/testcontainers/containers/GenericContainer;
     359: pop
     360: new           #162                // class de/theitshop/model/container/RunningContainer
     363: dup
     364: aload         10
     366: aload         4
     368: aload_2
     369: invokevirtual #44                 // Method de/theitshop/model/config/Service.getName:()Ljava/lang/String;
     372: invokespecial #191                // Method de/theitshop/model/container/RunningContainer."<init>":(Lorg/testcontainers/containers/GenericContainer;Ljava/util/Map;Ljava/lang/String;)V
     375: areturn

  private static void lambda$getContainer$0(de.theitshop.model.config.Service, com.github.dockerjava.api.command.CreateContainerCmd);
    Code:
       0: aload_1
       1: aload_0
       2: invokevirtual #44                 // Method de/theitshop/model/config/Service.getName:()Ljava/lang/String;
       5: invokeinterface #194,  2          // InterfaceMethod com/github/dockerjava/api/command/CreateContainerCmd.withHostName:(Ljava/lang/String;)Lcom/github/dockerjava/api/command/CreateContainerCmd;
      10: pop
      11: return

  static {};
    Code:
       0: ldc           #2                  // class de/theitshop/container/ContainerInitializer
       2: invokestatic  #200                // Method org/slf4j/LoggerFactory.getLogger:(Ljava/lang/Class;)Lorg/slf4j/Logger;
       5: putstatic     #181                // Field logger:Lorg/slf4j/Logger;
       8: return
}
