Compiled from "ResourceCompletor.java"
public class com.arjuna.ats.internal.jts.recovery.recoverycoordinators.ResourceCompletor extends java.lang.Thread {
  public static final int ROLLBACK;

  public static final int COMMIT;

  private org.omg.CosTransactions.Resource _res;

  private int _action;

  public com.arjuna.ats.internal.jts.recovery.recoverycoordinators.ResourceCompletor(org.omg.CosTransactions.Resource, int);
    Code:
       0: aload_0
       1: invokespecial #1                  // Method java/lang/Thread."<init>":()V
       4: aload_0
       5: aconst_null
       6: putfield      #2                  // Field _res:Lorg/omg/CosTransactions/Resource;
       9: aload_0
      10: iconst_0
      11: putfield      #3                  // Field _action:I
      14: aload_0
      15: aload_1
      16: putfield      #2                  // Field _res:Lorg/omg/CosTransactions/Resource;
      19: aload_0
      20: iload_2
      21: putfield      #3                  // Field _action:I
      24: return

  public final void run();
    Code:
       0: aload_0
       1: getfield      #3                  // Field _action:I
       4: ifne          11
       7: aload_0
       8: invokespecial #4                  // Method rollback:()V
      11: return

  private final void rollback();
    Code:
       0: getstatic     #5                  // Field com/arjuna/ats/jts/logging/jtsLogger.logger:Lorg/jboss/logging/Logger;
       3: invokevirtual #6                  // Method org/jboss/logging/Logger.isDebugEnabled:()Z
       6: ifeq          17
       9: getstatic     #5                  // Field com/arjuna/ats/jts/logging/jtsLogger.logger:Lorg/jboss/logging/Logger;
      12: ldc           #7                  // String ResourceCompletor.rollback()
      14: invokevirtual #8                  // Method org/jboss/logging/Logger.debug:(Ljava/lang/Object;)V
      17: aload_0
      18: getfield      #2                  // Field _res:Lorg/omg/CosTransactions/Resource;
      21: invokeinterface #9,  1            // InterfaceMethod org/omg/CosTransactions/Resource.rollback:()V
      26: goto          64
      29: astore_1
      30: getstatic     #5                  // Field com/arjuna/ats/jts/logging/jtsLogger.logger:Lorg/jboss/logging/Logger;
      33: invokevirtual #6                  // Method org/jboss/logging/Logger.isDebugEnabled:()Z
      36: ifeq          64
      39: getstatic     #5                  // Field com/arjuna/ats/jts/logging/jtsLogger.logger:Lorg/jboss/logging/Logger;
      42: new           #11                 // class java/lang/StringBuilder
      45: dup
      46: invokespecial #12                 // Method java/lang/StringBuilder."<init>":()V
      49: ldc           #13                 // String ResourceCompletor.rollback() - rollback failed:
      51: invokevirtual #14                 // Method java/lang/StringBuilder.append:(Ljava/lang/String;)Ljava/lang/StringBuilder;
      54: aload_1
      55: invokevirtual #15                 // Method java/lang/StringBuilder.append:(Ljava/lang/Object;)Ljava/lang/StringBuilder;
      58: invokevirtual #16                 // Method java/lang/StringBuilder.toString:()Ljava/lang/String;
      61: invokevirtual #8                  // Method org/jboss/logging/Logger.debug:(Ljava/lang/Object;)V
      64: return
    Exception table:
       from    to  target type
           0    26    29   Class java/lang/Exception
}
