Compiled from "ConcurrentHistogram.java"
class org.HdrHistogram.ConcurrentHistogram$AtomicLongArrayWithNormalizingOffset extends java.util.concurrent.atomic.AtomicLongArray {
  private int normalizingIndexOffset;

  org.HdrHistogram.ConcurrentHistogram$AtomicLongArrayWithNormalizingOffset(int, int);
    Code:
       0: aload_0
       1: iload_1
       2: invokespecial #1                  // Method java/util/concurrent/atomic/AtomicLongArray."<init>":(I)V
       5: aload_0
       6: iload_2
       7: putfield      #2                  // Field normalizingIndexOffset:I
      10: return

  public int getNormalizingIndexOffset();
    Code:
       0: aload_0
       1: getfield      #2                  // Field normalizingIndexOffset:I
       4: ireturn

  public void setNormalizingIndexOffset(int);
    Code:
       0: aload_0
       1: iload_1
       2: putfield      #2                  // Field normalizingIndexOffset:I
       5: return
}
