Compiled from "DoublePercentileIterator.java"
public class org.HdrHistogram.DoublePercentileIterator implements java.util.Iterator<org.HdrHistogram.DoubleHistogramIterationValue> {
  private final org.HdrHistogram.PercentileIterator integerPercentileIterator;

  private final org.HdrHistogram.DoubleHistogramIterationValue iterationValue;

  org.HdrHistogram.DoubleHistogram histogram;

  public void reset(int);
    Code:
       0: aload_0
       1: getfield      #1                  // Field integerPercentileIterator:Lorg/HdrHistogram/PercentileIterator;
       4: iload_1
       5: invokevirtual #2                  // Method org/HdrHistogram/PercentileIterator.reset:(I)V
       8: return

  public org.HdrHistogram.DoublePercentileIterator(org.HdrHistogram.DoubleHistogram, int);
    Code:
       0: aload_0
       1: invokespecial #3                  // Method java/lang/Object."<init>":()V
       4: aload_0
       5: aload_1
       6: putfield      #4                  // Field histogram:Lorg/HdrHistogram/DoubleHistogram;
       9: aload_0
      10: new           #5                  // class org/HdrHistogram/PercentileIterator
      13: dup
      14: aload_1
      15: getfield      #6                  // Field org/HdrHistogram/DoubleHistogram.integerValuesHistogram:Lorg/HdrHistogram/AbstractHistogram;
      18: iload_2
      19: invokespecial #7                  // Method org/HdrHistogram/PercentileIterator."<init>":(Lorg/HdrHistogram/AbstractHistogram;I)V
      22: putfield      #1                  // Field integerPercentileIterator:Lorg/HdrHistogram/PercentileIterator;
      25: aload_0
      26: new           #8                  // class org/HdrHistogram/DoubleHistogramIterationValue
      29: dup
      30: aload_0
      31: getfield      #1                  // Field integerPercentileIterator:Lorg/HdrHistogram/PercentileIterator;
      34: getfield      #9                  // Field org/HdrHistogram/PercentileIterator.currentIterationValue:Lorg/HdrHistogram/HistogramIterationValue;
      37: invokespecial #10                 // Method org/HdrHistogram/DoubleHistogramIterationValue."<init>":(Lorg/HdrHistogram/HistogramIterationValue;)V
      40: putfield      #11                 // Field iterationValue:Lorg/HdrHistogram/DoubleHistogramIterationValue;
      43: return

  public boolean hasNext();
    Code:
       0: aload_0
       1: getfield      #1                  // Field integerPercentileIterator:Lorg/HdrHistogram/PercentileIterator;
       4: invokevirtual #12                 // Method org/HdrHistogram/PercentileIterator.hasNext:()Z
       7: ireturn

  public org.HdrHistogram.DoubleHistogramIterationValue next();
    Code:
       0: aload_0
       1: getfield      #1                  // Field integerPercentileIterator:Lorg/HdrHistogram/PercentileIterator;
       4: invokevirtual #13                 // Method org/HdrHistogram/PercentileIterator.next:()Lorg/HdrHistogram/HistogramIterationValue;
       7: pop
       8: aload_0
       9: getfield      #11                 // Field iterationValue:Lorg/HdrHistogram/DoubleHistogramIterationValue;
      12: areturn

  public void remove();
    Code:
       0: aload_0
       1: getfield      #1                  // Field integerPercentileIterator:Lorg/HdrHistogram/PercentileIterator;
       4: invokevirtual #14                 // Method org/HdrHistogram/PercentileIterator.remove:()V
       7: return

  public java.lang.Object next();
    Code:
       0: aload_0
       1: invokevirtual #15                 // Method next:()Lorg/HdrHistogram/DoubleHistogramIterationValue;
       4: areturn
}
