Compiled from "EnumType.java"
public class com.google.javascript.jscomp.newtypes.EnumType extends com.google.javascript.jscomp.newtypes.Namespace implements com.google.javascript.jscomp.newtypes.TypeWithProperties {
  private com.google.javascript.jscomp.newtypes.EnumType$State state;

  private com.google.javascript.rhino.JSTypeExpression typeExpr;

  private java.lang.String name;

  private com.google.javascript.jscomp.newtypes.JSType declaredType;

  private com.google.javascript.jscomp.newtypes.JSType enumPropType;

  private com.google.javascript.jscomp.newtypes.JSType enumObjType;

  private com.google.common.collect.ImmutableSet<java.lang.String> props;

  private com.google.javascript.jscomp.newtypes.EnumType(java.lang.String, com.google.javascript.rhino.JSTypeExpression, java.util.Collection<java.lang.String>);
    Code:
       0: aload_0
       1: invokespecial #1                  // Method com/google/javascript/jscomp/newtypes/Namespace."<init>":()V
       4: aload_2
       5: invokestatic  #2                  // Method com/google/common/base/Preconditions.checkNotNull:(Ljava/lang/Object;)Ljava/lang/Object;
       8: pop
       9: aload_0
      10: getstatic     #3                  // Field com/google/javascript/jscomp/newtypes/EnumType$State.NOT_RESOLVED:Lcom/google/javascript/jscomp/newtypes/EnumType$State;
      13: putfield      #4                  // Field state:Lcom/google/javascript/jscomp/newtypes/EnumType$State;
      16: aload_0
      17: aload_1
      18: putfield      #5                  // Field name:Ljava/lang/String;
      21: aload_0
      22: aload_2
      23: putfield      #6                  // Field typeExpr:Lcom/google/javascript/rhino/JSTypeExpression;
      26: aload_0
      27: aload_3
      28: invokestatic  #7                  // Method com/google/common/collect/ImmutableSet.copyOf:(Ljava/util/Collection;)Lcom/google/common/collect/ImmutableSet;
      31: putfield      #8                  // Field props:Lcom/google/common/collect/ImmutableSet;
      34: return

  public static com.google.javascript.jscomp.newtypes.EnumType make(java.lang.String, com.google.javascript.rhino.JSTypeExpression, java.util.Collection<java.lang.String>);
    Code:
       0: new           #9                  // class com/google/javascript/jscomp/newtypes/EnumType
       3: dup
       4: aload_0
       5: aload_1
       6: aload_2
       7: invokespecial #10                 // Method "<init>":(Ljava/lang/String;Lcom/google/javascript/rhino/JSTypeExpression;Ljava/util/Collection;)V
      10: areturn

  public boolean isResolved();
    Code:
       0: aload_0
       1: getfield      #4                  // Field state:Lcom/google/javascript/jscomp/newtypes/EnumType$State;
       4: getstatic     #11                 // Field com/google/javascript/jscomp/newtypes/EnumType$State.RESOLVED:Lcom/google/javascript/jscomp/newtypes/EnumType$State;
       7: if_acmpne     14
      10: iconst_1
      11: goto          15
      14: iconst_0
      15: ireturn

  public com.google.javascript.jscomp.newtypes.JSType getEnumeratedType();
    Code:
       0: aload_0
       1: getfield      #4                  // Field state:Lcom/google/javascript/jscomp/newtypes/EnumType$State;
       4: getstatic     #11                 // Field com/google/javascript/jscomp/newtypes/EnumType$State.RESOLVED:Lcom/google/javascript/jscomp/newtypes/EnumType$State;
       7: if_acmpne     14
      10: iconst_1
      11: goto          15
      14: iconst_0
      15: invokestatic  #12                 // Method com/google/common/base/Preconditions.checkState:(Z)V
      18: aload_0
      19: getfield      #13                 // Field declaredType:Lcom/google/javascript/jscomp/newtypes/JSType;
      22: areturn

  public com.google.javascript.jscomp.newtypes.JSType getPropType();
    Code:
       0: aload_0
       1: getfield      #4                  // Field state:Lcom/google/javascript/jscomp/newtypes/EnumType$State;
       4: getstatic     #11                 // Field com/google/javascript/jscomp/newtypes/EnumType$State.RESOLVED:Lcom/google/javascript/jscomp/newtypes/EnumType$State;
       7: if_acmpne     14
      10: iconst_1
      11: goto          15
      14: iconst_0
      15: invokestatic  #12                 // Method com/google/common/base/Preconditions.checkState:(Z)V
      18: aload_0
      19: getfield      #14                 // Field enumPropType:Lcom/google/javascript/jscomp/newtypes/JSType;
      22: areturn

  public com.google.javascript.jscomp.newtypes.JSType toJSType();
    Code:
       0: aload_0
       1: getfield      #4                  // Field state:Lcom/google/javascript/jscomp/newtypes/EnumType$State;
       4: getstatic     #11                 // Field com/google/javascript/jscomp/newtypes/EnumType$State.RESOLVED:Lcom/google/javascript/jscomp/newtypes/EnumType$State;
       7: if_acmpne     14
      10: iconst_1
      11: goto          15
      14: iconst_0
      15: invokestatic  #12                 // Method com/google/common/base/Preconditions.checkState:(Z)V
      18: aload_0
      19: getfield      #15                 // Field enumObjType:Lcom/google/javascript/jscomp/newtypes/JSType;
      22: ifnonnull     33
      25: aload_0
      26: aload_0
      27: invokespecial #16                 // Method computeObjType:()Lcom/google/javascript/jscomp/newtypes/JSType;
      30: putfield      #15                 // Field enumObjType:Lcom/google/javascript/jscomp/newtypes/JSType;
      33: aload_0
      34: getfield      #15                 // Field enumObjType:Lcom/google/javascript/jscomp/newtypes/JSType;
      37: areturn

  public com.google.javascript.rhino.JSTypeExpression getTypeExpr();
    Code:
       0: aload_0
       1: getfield      #4                  // Field state:Lcom/google/javascript/jscomp/newtypes/EnumType$State;
       4: getstatic     #11                 // Field com/google/javascript/jscomp/newtypes/EnumType$State.RESOLVED:Lcom/google/javascript/jscomp/newtypes/EnumType$State;
       7: if_acmpeq     14
      10: iconst_1
      11: goto          15
      14: iconst_0
      15: invokestatic  #12                 // Method com/google/common/base/Preconditions.checkState:(Z)V
      18: aload_0
      19: getfield      #4                  // Field state:Lcom/google/javascript/jscomp/newtypes/EnumType$State;
      22: getstatic     #17                 // Field com/google/javascript/jscomp/newtypes/EnumType$State.DURING_RESOLUTION:Lcom/google/javascript/jscomp/newtypes/EnumType$State;
      25: if_acmpne     30
      28: aconst_null
      29: areturn
      30: aload_0
      31: getstatic     #17                 // Field com/google/javascript/jscomp/newtypes/EnumType$State.DURING_RESOLUTION:Lcom/google/javascript/jscomp/newtypes/EnumType$State;
      34: putfield      #4                  // Field state:Lcom/google/javascript/jscomp/newtypes/EnumType$State;
      37: aload_0
      38: getfield      #6                  // Field typeExpr:Lcom/google/javascript/rhino/JSTypeExpression;
      41: areturn

  public com.google.javascript.rhino.JSTypeExpression getTypeExprForErrorReporting();
    Code:
       0: aload_0
       1: getfield      #4                  // Field state:Lcom/google/javascript/jscomp/newtypes/EnumType$State;
       4: getstatic     #17                 // Field com/google/javascript/jscomp/newtypes/EnumType$State.DURING_RESOLUTION:Lcom/google/javascript/jscomp/newtypes/EnumType$State;
       7: if_acmpne     14
      10: iconst_1
      11: goto          15
      14: iconst_0
      15: invokestatic  #12                 // Method com/google/common/base/Preconditions.checkState:(Z)V
      18: aload_0
      19: getfield      #6                  // Field typeExpr:Lcom/google/javascript/rhino/JSTypeExpression;
      22: areturn

  void resolveEnum(com.google.javascript.jscomp.newtypes.JSType);
    Code:
       0: aload_1
       1: invokestatic  #2                  // Method com/google/common/base/Preconditions.checkNotNull:(Ljava/lang/Object;)Ljava/lang/Object;
       4: pop
       5: aload_0
       6: getfield      #4                  // Field state:Lcom/google/javascript/jscomp/newtypes/EnumType$State;
       9: getstatic     #11                 // Field com/google/javascript/jscomp/newtypes/EnumType$State.RESOLVED:Lcom/google/javascript/jscomp/newtypes/EnumType$State;
      12: if_acmpne     16
      15: return
      16: aload_0
      17: getfield      #4                  // Field state:Lcom/google/javascript/jscomp/newtypes/EnumType$State;
      20: getstatic     #17                 // Field com/google/javascript/jscomp/newtypes/EnumType$State.DURING_RESOLUTION:Lcom/google/javascript/jscomp/newtypes/EnumType$State;
      23: if_acmpne     30
      26: iconst_1
      27: goto          31
      30: iconst_0
      31: ldc           #18                 // String Expected state DURING_RESOLUTION but found %s
      33: iconst_1
      34: anewarray     #19                 // class java/lang/Object
      37: dup
      38: iconst_0
      39: aload_0
      40: getfield      #4                  // Field state:Lcom/google/javascript/jscomp/newtypes/EnumType$State;
      43: invokevirtual #20                 // Method com/google/javascript/jscomp/newtypes/EnumType$State.toString:()Ljava/lang/String;
      46: aastore
      47: invokestatic  #21                 // Method com/google/common/base/Preconditions.checkState:(ZLjava/lang/String;[Ljava/lang/Object;)V
      50: aload_0
      51: getstatic     #11                 // Field com/google/javascript/jscomp/newtypes/EnumType$State.RESOLVED:Lcom/google/javascript/jscomp/newtypes/EnumType$State;
      54: putfield      #4                  // Field state:Lcom/google/javascript/jscomp/newtypes/EnumType$State;
      57: aload_0
      58: aconst_null
      59: putfield      #6                  // Field typeExpr:Lcom/google/javascript/rhino/JSTypeExpression;
      62: aload_0
      63: aload_1
      64: putfield      #13                 // Field declaredType:Lcom/google/javascript/jscomp/newtypes/JSType;
      67: aload_0
      68: aload_0
      69: invokestatic  #22                 // Method com/google/javascript/jscomp/newtypes/JSType.fromEnum:(Lcom/google/javascript/jscomp/newtypes/EnumType;)Lcom/google/javascript/jscomp/newtypes/JSType;
      72: putfield      #14                 // Field enumPropType:Lcom/google/javascript/jscomp/newtypes/JSType;
      75: return

  private com.google.javascript.jscomp.newtypes.JSType computeObjType();
    Code:
       0: aload_0
       1: getfield      #14                 // Field enumPropType:Lcom/google/javascript/jscomp/newtypes/JSType;
       4: ifnull        11
       7: iconst_1
       8: goto          12
      11: iconst_0
      12: invokestatic  #12                 // Method com/google/common/base/Preconditions.checkState:(Z)V
      15: aload_0
      16: getfield      #23                 // Field otherProps:Lcom/google/javascript/jscomp/newtypes/PersistentMap;
      19: astore_1
      20: aload_0
      21: getfield      #8                  // Field props:Lcom/google/common/collect/ImmutableSet;
      24: invokevirtual #24                 // Method com/google/common/collect/ImmutableSet.iterator:()Lcom/google/common/collect/UnmodifiableIterator;
      27: astore_2
      28: aload_2
      29: invokeinterface #25,  1           // InterfaceMethod java/util/Iterator.hasNext:()Z
      34: ifeq          67
      37: aload_2
      38: invokeinterface #26,  1           // InterfaceMethod java/util/Iterator.next:()Ljava/lang/Object;
      43: checkcast     #27                 // class java/lang/String
      46: astore_3
      47: aload_1
      48: aload_3
      49: aload_0
      50: getfield      #14                 // Field enumPropType:Lcom/google/javascript/jscomp/newtypes/JSType;
      53: aload_0
      54: getfield      #14                 // Field enumPropType:Lcom/google/javascript/jscomp/newtypes/JSType;
      57: invokestatic  #28                 // Method com/google/javascript/jscomp/newtypes/Property.makeConstant:(Lcom/google/javascript/jscomp/newtypes/JSType;Lcom/google/javascript/jscomp/newtypes/JSType;)Lcom/google/javascript/jscomp/newtypes/Property;
      60: invokevirtual #29                 // Method com/google/javascript/jscomp/newtypes/PersistentMap.with:(Ljava/lang/Object;Ljava/lang/Object;)Lcom/google/javascript/jscomp/newtypes/PersistentMap;
      63: astore_1
      64: goto          28
      67: aload_0
      68: aconst_null
      69: aload_1
      70: aconst_null
      71: iconst_0
      72: getstatic     #30                 // Field com/google/javascript/jscomp/newtypes/ObjectKind.UNRESTRICTED:Lcom/google/javascript/jscomp/newtypes/ObjectKind;
      75: invokestatic  #31                 // Method com/google/javascript/jscomp/newtypes/ObjectType.makeObjectType:(Lcom/google/javascript/jscomp/newtypes/NominalType;Lcom/google/javascript/jscomp/newtypes/PersistentMap;Lcom/google/javascript/jscomp/newtypes/FunctionType;ZLcom/google/javascript/jscomp/newtypes/ObjectKind;)Lcom/google/javascript/jscomp/newtypes/ObjectType;
      78: invokevirtual #32                 // Method withNamedTypes:(Lcom/google/javascript/jscomp/newtypes/ObjectType;)Lcom/google/javascript/jscomp/newtypes/JSType;
      81: areturn

  public com.google.javascript.jscomp.newtypes.JSType getProp(com.google.javascript.jscomp.newtypes.QualifiedName);
    Code:
       0: aload_0
       1: getfield      #13                 // Field declaredType:Lcom/google/javascript/jscomp/newtypes/JSType;
       4: aload_1
       5: invokevirtual #33                 // Method com/google/javascript/jscomp/newtypes/JSType.getProp:(Lcom/google/javascript/jscomp/newtypes/QualifiedName;)Lcom/google/javascript/jscomp/newtypes/JSType;
       8: areturn

  public com.google.javascript.jscomp.newtypes.JSType getDeclaredProp(com.google.javascript.jscomp.newtypes.QualifiedName);
    Code:
       0: aload_0
       1: getfield      #13                 // Field declaredType:Lcom/google/javascript/jscomp/newtypes/JSType;
       4: aload_1
       5: invokevirtual #34                 // Method com/google/javascript/jscomp/newtypes/JSType.getDeclaredProp:(Lcom/google/javascript/jscomp/newtypes/QualifiedName;)Lcom/google/javascript/jscomp/newtypes/JSType;
       8: areturn

  public boolean mayHaveProp(com.google.javascript.jscomp.newtypes.QualifiedName);
    Code:
       0: aload_0
       1: getfield      #13                 // Field declaredType:Lcom/google/javascript/jscomp/newtypes/JSType;
       4: aload_1
       5: invokevirtual #35                 // Method com/google/javascript/jscomp/newtypes/JSType.mayHaveProp:(Lcom/google/javascript/jscomp/newtypes/QualifiedName;)Z
       8: ireturn

  public boolean hasProp(com.google.javascript.jscomp.newtypes.QualifiedName);
    Code:
       0: aload_0
       1: getfield      #13                 // Field declaredType:Lcom/google/javascript/jscomp/newtypes/JSType;
       4: aload_1
       5: invokevirtual #36                 // Method com/google/javascript/jscomp/newtypes/JSType.hasProp:(Lcom/google/javascript/jscomp/newtypes/QualifiedName;)Z
       8: ireturn

  public boolean hasConstantProp(com.google.javascript.jscomp.newtypes.QualifiedName);
    Code:
       0: aload_0
       1: getfield      #13                 // Field declaredType:Lcom/google/javascript/jscomp/newtypes/JSType;
       4: aload_1
       5: invokevirtual #37                 // Method com/google/javascript/jscomp/newtypes/JSType.hasConstantProp:(Lcom/google/javascript/jscomp/newtypes/QualifiedName;)Z
       8: ireturn

  public boolean enumLiteralHasKey(java.lang.String);
    Code:
       0: aload_0
       1: getfield      #8                  // Field props:Lcom/google/common/collect/ImmutableSet;
       4: aload_1
       5: invokevirtual #38                 // Method com/google/common/collect/ImmutableSet.contains:(Ljava/lang/Object;)Z
       8: ireturn

  static boolean hasNonScalar(com.google.common.collect.ImmutableSet<com.google.javascript.jscomp.newtypes.EnumType>);
    Code:
       0: aload_0
       1: ifnonnull     6
       4: iconst_0
       5: ireturn
       6: aload_0
       7: invokevirtual #24                 // Method com/google/common/collect/ImmutableSet.iterator:()Lcom/google/common/collect/UnmodifiableIterator;
      10: astore_1
      11: aload_1
      12: invokeinterface #25,  1           // InterfaceMethod java/util/Iterator.hasNext:()Z
      17: ifeq          45
      20: aload_1
      21: invokeinterface #26,  1           // InterfaceMethod java/util/Iterator.next:()Ljava/lang/Object;
      26: checkcast     #9                  // class com/google/javascript/jscomp/newtypes/EnumType
      29: astore_2
      30: aload_2
      31: getfield      #13                 // Field declaredType:Lcom/google/javascript/jscomp/newtypes/JSType;
      34: invokevirtual #39                 // Method com/google/javascript/jscomp/newtypes/JSType.hasNonScalar:()Z
      37: ifeq          42
      40: iconst_1
      41: ireturn
      42: goto          11
      45: iconst_0
      46: ireturn

  static com.google.common.collect.ImmutableSet<com.google.javascript.jscomp.newtypes.EnumType> union(com.google.common.collect.ImmutableSet<com.google.javascript.jscomp.newtypes.EnumType>, com.google.common.collect.ImmutableSet<com.google.javascript.jscomp.newtypes.EnumType>);
    Code:
       0: aload_0
       1: ifnonnull     6
       4: aload_1
       5: areturn
       6: aload_1
       7: ifnull        18
      10: aload_0
      11: aload_1
      12: invokevirtual #40                 // Method com/google/common/collect/ImmutableSet.equals:(Ljava/lang/Object;)Z
      15: ifeq          20
      18: aload_0
      19: areturn
      20: aload_0
      21: aload_1
      22: invokestatic  #41                 // Method com/google/common/collect/Sets.union:(Ljava/util/Set;Ljava/util/Set;)Lcom/google/common/collect/Sets$SetView;
      25: invokevirtual #42                 // Method com/google/common/collect/Sets$SetView.immutableCopy:()Lcom/google/common/collect/ImmutableSet;
      28: areturn

  static com.google.common.collect.ImmutableSet<com.google.javascript.jscomp.newtypes.EnumType> normalizeForJoin(com.google.common.collect.ImmutableSet<com.google.javascript.jscomp.newtypes.EnumType>, com.google.javascript.jscomp.newtypes.JSType);
    Code:
       0: iconst_0
       1: istore_2
       2: aload_0
       3: invokevirtual #24                 // Method com/google/common/collect/ImmutableSet.iterator:()Lcom/google/common/collect/UnmodifiableIterator;
       6: astore_3
       7: aload_3
       8: invokeinterface #25,  1           // InterfaceMethod java/util/Iterator.hasNext:()Z
      13: ifeq          47
      16: aload_3
      17: invokeinterface #26,  1           // InterfaceMethod java/util/Iterator.next:()Ljava/lang/Object;
      22: checkcast     #9                  // class com/google/javascript/jscomp/newtypes/EnumType
      25: astore        4
      27: aload         4
      29: getfield      #13                 // Field declaredType:Lcom/google/javascript/jscomp/newtypes/JSType;
      32: aload_1
      33: invokevirtual #43                 // Method com/google/javascript/jscomp/newtypes/JSType.isSubtypeOf:(Lcom/google/javascript/jscomp/newtypes/JSType;)Z
      36: ifeq          44
      39: iconst_1
      40: istore_2
      41: goto          47
      44: goto          7
      47: iload_2
      48: ifne          53
      51: aload_0
      52: areturn
      53: invokestatic  #44                 // Method com/google/common/collect/ImmutableSet.builder:()Lcom/google/common/collect/ImmutableSet$Builder;
      56: astore_3
      57: aload_0
      58: invokevirtual #24                 // Method com/google/common/collect/ImmutableSet.iterator:()Lcom/google/common/collect/UnmodifiableIterator;
      61: astore        4
      63: aload         4
      65: invokeinterface #25,  1           // InterfaceMethod java/util/Iterator.hasNext:()Z
      70: ifeq          107
      73: aload         4
      75: invokeinterface #26,  1           // InterfaceMethod java/util/Iterator.next:()Ljava/lang/Object;
      80: checkcast     #9                  // class com/google/javascript/jscomp/newtypes/EnumType
      83: astore        5
      85: aload         5
      87: getfield      #13                 // Field declaredType:Lcom/google/javascript/jscomp/newtypes/JSType;
      90: aload_1
      91: invokevirtual #43                 // Method com/google/javascript/jscomp/newtypes/JSType.isSubtypeOf:(Lcom/google/javascript/jscomp/newtypes/JSType;)Z
      94: ifne          104
      97: aload_3
      98: aload         5
     100: invokevirtual #45                 // Method com/google/common/collect/ImmutableSet$Builder.add:(Ljava/lang/Object;)Lcom/google/common/collect/ImmutableSet$Builder;
     103: pop
     104: goto          63
     107: aload_3
     108: invokevirtual #46                 // Method com/google/common/collect/ImmutableSet$Builder.build:()Lcom/google/common/collect/ImmutableSet;
     111: areturn

  static boolean areSubtypes(com.google.javascript.jscomp.newtypes.JSType, com.google.javascript.jscomp.newtypes.JSType);
    Code:
       0: aload_0
       1: invokevirtual #47                 // Method com/google/javascript/jscomp/newtypes/JSType.getEnums:()Lcom/google/common/collect/ImmutableSet;
       4: astore_2
       5: aload_2
       6: ifnonnull     11
       9: iconst_1
      10: ireturn
      11: aload_1
      12: invokevirtual #47                 // Method com/google/javascript/jscomp/newtypes/JSType.getEnums:()Lcom/google/common/collect/ImmutableSet;
      15: astore_3
      16: aload_2
      17: invokevirtual #24                 // Method com/google/common/collect/ImmutableSet.iterator:()Lcom/google/common/collect/UnmodifiableIterator;
      20: astore        4
      22: aload         4
      24: invokeinterface #25,  1           // InterfaceMethod java/util/Iterator.hasNext:()Z
      29: ifeq          77
      32: aload         4
      34: invokeinterface #26,  1           // InterfaceMethod java/util/Iterator.next:()Ljava/lang/Object;
      39: checkcast     #9                  // class com/google/javascript/jscomp/newtypes/EnumType
      42: astore        5
      44: aload_3
      45: ifnull        60
      48: aload_3
      49: aload         5
      51: invokevirtual #38                 // Method com/google/common/collect/ImmutableSet.contains:(Ljava/lang/Object;)Z
      54: ifeq          60
      57: goto          22
      60: aload         5
      62: getfield      #13                 // Field declaredType:Lcom/google/javascript/jscomp/newtypes/JSType;
      65: aload_1
      66: invokevirtual #43                 // Method com/google/javascript/jscomp/newtypes/JSType.isSubtypeOf:(Lcom/google/javascript/jscomp/newtypes/JSType;)Z
      69: ifne          74
      72: iconst_0
      73: ireturn
      74: goto          22
      77: iconst_1
      78: ireturn

  public java.lang.String toString();
    Code:
       0: aload_0
       1: getfield      #5                  // Field name:Ljava/lang/String;
       4: areturn
}
