Compiled from "PersistentSet.java"
public abstract class com.google.javascript.jscomp.newtypes.PersistentSet<K> extends java.util.AbstractSet<K> {
  private static com.google.javascript.jscomp.newtypes.PersistentSet EMPTY;

  public com.google.javascript.jscomp.newtypes.PersistentSet();
    Code:
       0: aload_0
       1: invokespecial #1                  // Method java/util/AbstractSet."<init>":()V
       4: return

  public abstract com.google.javascript.jscomp.newtypes.PersistentSet<K> with(K);

  public abstract com.google.javascript.jscomp.newtypes.PersistentSet<K> without(K);

  public static <K> com.google.javascript.jscomp.newtypes.PersistentSet<K> create();
    Code:
       0: getstatic     #2                  // Field EMPTY:Lcom/google/javascript/jscomp/newtypes/PersistentSet;
       3: areturn

  static {};
    Code:
       0: ldc           #3                  // String clojure.lang.PersistentHashSet
       2: invokestatic  #4                  // Method java/lang/Class.forName:(Ljava/lang/String;)Ljava/lang/Class;
       5: astore_0
       6: aload_0
       7: invokestatic  #5                  // Method com/google/javascript/jscomp/newtypes/ClojurePersistentHashSet.create:(Ljava/lang/Class;)Lcom/google/javascript/jscomp/newtypes/PersistentSet;
      10: putstatic     #2                  // Field EMPTY:Lcom/google/javascript/jscomp/newtypes/PersistentSet;
      13: goto          23
      16: astore_0
      17: invokestatic  #7                  // Method com/google/javascript/jscomp/newtypes/NaivePersistentSet.create:()Lcom/google/javascript/jscomp/newtypes/PersistentSet;
      20: putstatic     #2                  // Field EMPTY:Lcom/google/javascript/jscomp/newtypes/PersistentSet;
      23: return
    Exception table:
       from    to  target type
           0    13    16   Class java/lang/ClassNotFoundException
}
