Compiled from "JSType.java"
final class com.google.javascript.jscomp.newtypes.UnionType extends com.google.javascript.jscomp.newtypes.JSType {
  private final int mask;

  private final com.google.common.collect.ImmutableSet<com.google.javascript.jscomp.newtypes.ObjectType> objs;

  private final java.lang.String typeVar;

  private final com.google.common.collect.ImmutableSet<com.google.javascript.jscomp.newtypes.EnumType> enums;

  com.google.javascript.jscomp.newtypes.UnionType(int, com.google.common.collect.ImmutableSet<com.google.javascript.jscomp.newtypes.ObjectType>, java.lang.String, com.google.common.collect.ImmutableSet<com.google.javascript.jscomp.newtypes.EnumType>);
    Code:
       0: aload_0
       1: invokespecial #1                  // Method com/google/javascript/jscomp/newtypes/JSType."<init>":()V
       4: aload         4
       6: ifnonnull     17
       9: aload_0
      10: aconst_null
      11: putfield      #2                  // Field enums:Lcom/google/common/collect/ImmutableSet;
      14: goto          39
      17: aload         4
      19: invokevirtual #3                  // Method com/google/common/collect/ImmutableSet.isEmpty:()Z
      22: ifeq          33
      25: aload_0
      26: aconst_null
      27: putfield      #2                  // Field enums:Lcom/google/common/collect/ImmutableSet;
      30: goto          39
      33: aload_0
      34: aload         4
      36: putfield      #2                  // Field enums:Lcom/google/common/collect/ImmutableSet;
      39: aload_2
      40: ifnonnull     51
      43: aload_0
      44: aconst_null
      45: putfield      #4                  // Field objs:Lcom/google/common/collect/ImmutableSet;
      48: goto          71
      51: aload_2
      52: invokevirtual #3                  // Method com/google/common/collect/ImmutableSet.isEmpty:()Z
      55: ifeq          66
      58: aload_0
      59: aconst_null
      60: putfield      #4                  // Field objs:Lcom/google/common/collect/ImmutableSet;
      63: goto          71
      66: aload_0
      67: aload_2
      68: putfield      #4                  // Field objs:Lcom/google/common/collect/ImmutableSet;
      71: aload_3
      72: ifnull        79
      75: iload_1
      76: iconst_1
      77: ior
      78: istore_1
      79: aload_0
      80: aload_3
      81: putfield      #6                  // Field typeVar:Ljava/lang/String;
      84: aload_0
      85: iload_1
      86: putfield      #7                  // Field mask:I
      89: aload_0
      90: invokevirtual #8                  // Method isValidType:()Z
      93: ldc           #9                  // String Cannot create type with bits <<<%s>>>, objs <<<%s>>>, typeVar <<<%s>>>, enums <<<%s>>>
      95: iconst_4
      96: anewarray     #10                 // class java/lang/Object
      99: dup
     100: iconst_0
     101: iload_1
     102: invokestatic  #11                 // Method java/lang/Integer.valueOf:(I)Ljava/lang/Integer;
     105: aastore
     106: dup
     107: iconst_1
     108: aload_2
     109: aastore
     110: dup
     111: iconst_2
     112: aload_3
     113: aastore
     114: dup
     115: iconst_3
     116: aload         4
     118: aastore
     119: invokestatic  #12                 // Method com/google/common/base/Preconditions.checkState:(ZLjava/lang/String;[Ljava/lang/Object;)V
     122: return

  com.google.javascript.jscomp.newtypes.UnionType(int);
    Code:
       0: aload_0
       1: iload_1
       2: aconst_null
       3: aconst_null
       4: aconst_null
       5: invokespecial #13                 // Method "<init>":(ILcom/google/common/collect/ImmutableSet;Ljava/lang/String;Lcom/google/common/collect/ImmutableSet;)V
       8: return

  protected int getMask();
    Code:
       0: aload_0
       1: getfield      #7                  // Field mask:I
       4: ireturn

  protected com.google.common.collect.ImmutableSet<com.google.javascript.jscomp.newtypes.ObjectType> getObjs();
    Code:
       0: aload_0
       1: getfield      #4                  // Field objs:Lcom/google/common/collect/ImmutableSet;
       4: areturn

  protected java.lang.String getTypeVar();
    Code:
       0: aload_0
       1: getfield      #6                  // Field typeVar:Ljava/lang/String;
       4: areturn

  protected com.google.common.collect.ImmutableSet<com.google.javascript.jscomp.newtypes.EnumType> getEnums();
    Code:
       0: aload_0
       1: getfield      #2                  // Field enums:Lcom/google/common/collect/ImmutableSet;
       4: areturn
}
