Compiled from "JpaTransactionManager.java"
class org.springframework.orm.jpa.JpaTransactionManager$1 extends org.springframework.transaction.support.DelegatingTransactionDefinition {
  final int val$timeoutToUse;

  final org.springframework.orm.jpa.JpaTransactionManager this$0;

  org.springframework.orm.jpa.JpaTransactionManager$1(org.springframework.orm.jpa.JpaTransactionManager, org.springframework.transaction.TransactionDefinition, int);
    Code:
       0: aload_0
       1: aload_1
       2: putfield      #1                  // Field this$0:Lorg/springframework/orm/jpa/JpaTransactionManager;
       5: aload_0
       6: iload_3
       7: putfield      #2                  // Field val$timeoutToUse:I
      10: aload_0
      11: aload_2
      12: invokespecial #3                  // Method org/springframework/transaction/support/DelegatingTransactionDefinition."<init>":(Lorg/springframework/transaction/TransactionDefinition;)V
      15: return

  public int getTimeout();
    Code:
       0: aload_0
       1: getfield      #2                  // Field val$timeoutToUse:I
       4: ireturn
}
