Compiled from "ArgUtil.java"
public final class com.ctc.wstx.util.ArgUtil {
  private com.ctc.wstx.util.ArgUtil();
    Code:
       0: aload_0
       1: invokespecial #1                  // Method java/lang/Object."<init>":()V
       4: return

  public static boolean convertToBoolean(java.lang.String, java.lang.Object);
    Code:
       0: aload_1
       1: ifnonnull     6
       4: iconst_0
       5: ireturn
       6: aload_1
       7: instanceof    #2                  // class java/lang/Boolean
      10: ifeq          21
      13: aload_1
      14: checkcast     #2                  // class java/lang/Boolean
      17: invokevirtual #3                  // Method java/lang/Boolean.booleanValue:()Z
      20: ireturn
      21: aload_1
      22: instanceof    #4                  // class java/lang/String
      25: ifeq          87
      28: aload_1
      29: checkcast     #4                  // class java/lang/String
      32: astore_2
      33: aload_2
      34: ldc           #5                  // String false
      36: invokevirtual #6                  // Method java/lang/String.equalsIgnoreCase:(Ljava/lang/String;)Z
      39: ifeq          44
      42: iconst_0
      43: ireturn
      44: aload_2
      45: ldc           #7                  // String true
      47: invokevirtual #6                  // Method java/lang/String.equalsIgnoreCase:(Ljava/lang/String;)Z
      50: ifeq          55
      53: iconst_1
      54: ireturn
      55: new           #8                  // class java/lang/IllegalArgumentException
      58: dup
      59: new           #9                  // class java/lang/StringBuffer
      62: dup
      63: invokespecial #10                 // Method java/lang/StringBuffer."<init>":()V
      66: ldc           #11                 // String Invalid String value for property \'
      68: invokevirtual #12                 // Method java/lang/StringBuffer.append:(Ljava/lang/String;)Ljava/lang/StringBuffer;
      71: aload_0
      72: invokevirtual #12                 // Method java/lang/StringBuffer.append:(Ljava/lang/String;)Ljava/lang/StringBuffer;
      75: ldc           #13                 // String \': expected Boolean value.
      77: invokevirtual #12                 // Method java/lang/StringBuffer.append:(Ljava/lang/String;)Ljava/lang/StringBuffer;
      80: invokevirtual #14                 // Method java/lang/StringBuffer.toString:()Ljava/lang/String;
      83: invokespecial #15                 // Method java/lang/IllegalArgumentException."<init>":(Ljava/lang/String;)V
      86: athrow
      87: new           #8                  // class java/lang/IllegalArgumentException
      90: dup
      91: new           #9                  // class java/lang/StringBuffer
      94: dup
      95: invokespecial #10                 // Method java/lang/StringBuffer."<init>":()V
      98: ldc           #16                 // String Invalid value type (
     100: invokevirtual #12                 // Method java/lang/StringBuffer.append:(Ljava/lang/String;)Ljava/lang/StringBuffer;
     103: aload_1
     104: invokevirtual #17                 // Method java/lang/Object.getClass:()Ljava/lang/Class;
     107: invokevirtual #18                 // Method java/lang/StringBuffer.append:(Ljava/lang/Object;)Ljava/lang/StringBuffer;
     110: ldc           #19                 // String ) for property \'
     112: invokevirtual #12                 // Method java/lang/StringBuffer.append:(Ljava/lang/String;)Ljava/lang/StringBuffer;
     115: aload_0
     116: invokevirtual #12                 // Method java/lang/StringBuffer.append:(Ljava/lang/String;)Ljava/lang/StringBuffer;
     119: ldc           #13                 // String \': expected Boolean value.
     121: invokevirtual #12                 // Method java/lang/StringBuffer.append:(Ljava/lang/String;)Ljava/lang/StringBuffer;
     124: invokevirtual #14                 // Method java/lang/StringBuffer.toString:()Ljava/lang/String;
     127: invokespecial #15                 // Method java/lang/IllegalArgumentException."<init>":(Ljava/lang/String;)V
     130: athrow

  public static int convertToInt(java.lang.String, java.lang.Object, int);
    Code:
       0: aload_1
       1: ifnonnull     9
       4: iconst_0
       5: istore_3
       6: goto          158
       9: aload_1
      10: instanceof    #20                 // class java/lang/Number
      13: ifeq          62
      16: aload_1
      17: checkcast     #20                 // class java/lang/Number
      20: invokevirtual #21                 // Method java/lang/Number.longValue:()J
      23: lstore        4
      25: lload         4
      27: ldc2_w        #22                 // long 2147483647l
      30: lcmp
      31: ifle          40
      34: ldc           #24                 // int 2147483647
      36: istore_3
      37: goto          59
      40: lload         4
      42: ldc2_w        #25                 // long -2147483648l
      45: lcmp
      46: ifge          55
      49: ldc           #27                 // int -2147483648
      51: istore_3
      52: goto          59
      55: lload         4
      57: l2i
      58: istore_3
      59: goto          158
      62: aload_1
      63: instanceof    #4                  // class java/lang/String
      66: ifeq          114
      69: aload_1
      70: checkcast     #4                  // class java/lang/String
      73: invokestatic  #28                 // Method java/lang/Integer.parseInt:(Ljava/lang/String;)I
      76: istore_3
      77: goto          158
      80: astore        4
      82: new           #8                  // class java/lang/IllegalArgumentException
      85: dup
      86: new           #9                  // class java/lang/StringBuffer
      89: dup
      90: invokespecial #10                 // Method java/lang/StringBuffer."<init>":()V
      93: ldc           #11                 // String Invalid String value for property \'
      95: invokevirtual #12                 // Method java/lang/StringBuffer.append:(Ljava/lang/String;)Ljava/lang/StringBuffer;
      98: aload_0
      99: invokevirtual #12                 // Method java/lang/StringBuffer.append:(Ljava/lang/String;)Ljava/lang/StringBuffer;
     102: ldc           #30                 // String \': expected a number (Integer).
     104: invokevirtual #12                 // Method java/lang/StringBuffer.append:(Ljava/lang/String;)Ljava/lang/StringBuffer;
     107: invokevirtual #14                 // Method java/lang/StringBuffer.toString:()Ljava/lang/String;
     110: invokespecial #15                 // Method java/lang/IllegalArgumentException."<init>":(Ljava/lang/String;)V
     113: athrow
     114: new           #8                  // class java/lang/IllegalArgumentException
     117: dup
     118: new           #9                  // class java/lang/StringBuffer
     121: dup
     122: invokespecial #10                 // Method java/lang/StringBuffer."<init>":()V
     125: ldc           #16                 // String Invalid value type (
     127: invokevirtual #12                 // Method java/lang/StringBuffer.append:(Ljava/lang/String;)Ljava/lang/StringBuffer;
     130: aload_1
     131: invokevirtual #17                 // Method java/lang/Object.getClass:()Ljava/lang/Class;
     134: invokevirtual #18                 // Method java/lang/StringBuffer.append:(Ljava/lang/Object;)Ljava/lang/StringBuffer;
     137: ldc           #19                 // String ) for property \'
     139: invokevirtual #12                 // Method java/lang/StringBuffer.append:(Ljava/lang/String;)Ljava/lang/StringBuffer;
     142: aload_0
     143: invokevirtual #12                 // Method java/lang/StringBuffer.append:(Ljava/lang/String;)Ljava/lang/StringBuffer;
     146: ldc           #31                 // String \': expected Integer value.
     148: invokevirtual #12                 // Method java/lang/StringBuffer.append:(Ljava/lang/String;)Ljava/lang/StringBuffer;
     151: invokevirtual #14                 // Method java/lang/StringBuffer.toString:()Ljava/lang/String;
     154: invokespecial #15                 // Method java/lang/IllegalArgumentException."<init>":(Ljava/lang/String;)V
     157: athrow
     158: iload_3
     159: iload_2
     160: if_icmpge     213
     163: new           #8                  // class java/lang/IllegalArgumentException
     166: dup
     167: new           #9                  // class java/lang/StringBuffer
     170: dup
     171: invokespecial #10                 // Method java/lang/StringBuffer."<init>":()V
     174: ldc           #32                 // String Invalid numeric value (
     176: invokevirtual #12                 // Method java/lang/StringBuffer.append:(Ljava/lang/String;)Ljava/lang/StringBuffer;
     179: iload_3
     180: invokevirtual #33                 // Method java/lang/StringBuffer.append:(I)Ljava/lang/StringBuffer;
     183: ldc           #19                 // String ) for property \'
     185: invokevirtual #12                 // Method java/lang/StringBuffer.append:(Ljava/lang/String;)Ljava/lang/StringBuffer;
     188: aload_0
     189: invokevirtual #12                 // Method java/lang/StringBuffer.append:(Ljava/lang/String;)Ljava/lang/StringBuffer;
     192: ldc           #34                 // String \': minimum is
     194: invokevirtual #12                 // Method java/lang/StringBuffer.append:(Ljava/lang/String;)Ljava/lang/StringBuffer;
     197: iload_2
     198: invokevirtual #33                 // Method java/lang/StringBuffer.append:(I)Ljava/lang/StringBuffer;
     201: ldc           #35                 // String .
     203: invokevirtual #12                 // Method java/lang/StringBuffer.append:(Ljava/lang/String;)Ljava/lang/StringBuffer;
     206: invokevirtual #14                 // Method java/lang/StringBuffer.toString:()Ljava/lang/String;
     209: invokespecial #15                 // Method java/lang/IllegalArgumentException."<init>":(Ljava/lang/String;)V
     212: athrow
     213: iload_3
     214: ireturn
    Exception table:
       from    to  target type
          69    77    80   Class java/lang/NumberFormatException

  public static long convertToLong(java.lang.String, java.lang.Object, long);
    Code:
       0: aload_1
       1: ifnonnull     10
       4: lconst_0
       5: lstore        4
       7: goto          126
      10: aload_1
      11: instanceof    #20                 // class java/lang/Number
      14: ifeq          29
      17: aload_1
      18: checkcast     #20                 // class java/lang/Number
      21: invokevirtual #21                 // Method java/lang/Number.longValue:()J
      24: lstore        4
      26: goto          126
      29: aload_1
      30: instanceof    #4                  // class java/lang/String
      33: ifeq          82
      36: aload_1
      37: checkcast     #4                  // class java/lang/String
      40: invokestatic  #36                 // Method java/lang/Long.parseLong:(Ljava/lang/String;)J
      43: lstore        4
      45: goto          126
      48: astore        6
      50: new           #8                  // class java/lang/IllegalArgumentException
      53: dup
      54: new           #9                  // class java/lang/StringBuffer
      57: dup
      58: invokespecial #10                 // Method java/lang/StringBuffer."<init>":()V
      61: ldc           #11                 // String Invalid String value for property \'
      63: invokevirtual #12                 // Method java/lang/StringBuffer.append:(Ljava/lang/String;)Ljava/lang/StringBuffer;
      66: aload_0
      67: invokevirtual #12                 // Method java/lang/StringBuffer.append:(Ljava/lang/String;)Ljava/lang/StringBuffer;
      70: ldc           #37                 // String \': expected a number (Long).
      72: invokevirtual #12                 // Method java/lang/StringBuffer.append:(Ljava/lang/String;)Ljava/lang/StringBuffer;
      75: invokevirtual #14                 // Method java/lang/StringBuffer.toString:()Ljava/lang/String;
      78: invokespecial #15                 // Method java/lang/IllegalArgumentException."<init>":(Ljava/lang/String;)V
      81: athrow
      82: new           #8                  // class java/lang/IllegalArgumentException
      85: dup
      86: new           #9                  // class java/lang/StringBuffer
      89: dup
      90: invokespecial #10                 // Method java/lang/StringBuffer."<init>":()V
      93: ldc           #16                 // String Invalid value type (
      95: invokevirtual #12                 // Method java/lang/StringBuffer.append:(Ljava/lang/String;)Ljava/lang/StringBuffer;
      98: aload_1
      99: invokevirtual #17                 // Method java/lang/Object.getClass:()Ljava/lang/Class;
     102: invokevirtual #18                 // Method java/lang/StringBuffer.append:(Ljava/lang/Object;)Ljava/lang/StringBuffer;
     105: ldc           #19                 // String ) for property \'
     107: invokevirtual #12                 // Method java/lang/StringBuffer.append:(Ljava/lang/String;)Ljava/lang/StringBuffer;
     110: aload_0
     111: invokevirtual #12                 // Method java/lang/StringBuffer.append:(Ljava/lang/String;)Ljava/lang/StringBuffer;
     114: ldc           #38                 // String \': expected Long value.
     116: invokevirtual #12                 // Method java/lang/StringBuffer.append:(Ljava/lang/String;)Ljava/lang/StringBuffer;
     119: invokevirtual #14                 // Method java/lang/StringBuffer.toString:()Ljava/lang/String;
     122: invokespecial #15                 // Method java/lang/IllegalArgumentException."<init>":(Ljava/lang/String;)V
     125: athrow
     126: lload         4
     128: lload_2
     129: lcmp
     130: ifge          184
     133: new           #8                  // class java/lang/IllegalArgumentException
     136: dup
     137: new           #9                  // class java/lang/StringBuffer
     140: dup
     141: invokespecial #10                 // Method java/lang/StringBuffer."<init>":()V
     144: ldc           #32                 // String Invalid numeric value (
     146: invokevirtual #12                 // Method java/lang/StringBuffer.append:(Ljava/lang/String;)Ljava/lang/StringBuffer;
     149: lload         4
     151: invokevirtual #39                 // Method java/lang/StringBuffer.append:(J)Ljava/lang/StringBuffer;
     154: ldc           #19                 // String ) for property \'
     156: invokevirtual #12                 // Method java/lang/StringBuffer.append:(Ljava/lang/String;)Ljava/lang/StringBuffer;
     159: aload_0
     160: invokevirtual #12                 // Method java/lang/StringBuffer.append:(Ljava/lang/String;)Ljava/lang/StringBuffer;
     163: ldc           #34                 // String \': minimum is
     165: invokevirtual #12                 // Method java/lang/StringBuffer.append:(Ljava/lang/String;)Ljava/lang/StringBuffer;
     168: lload_2
     169: invokevirtual #39                 // Method java/lang/StringBuffer.append:(J)Ljava/lang/StringBuffer;
     172: ldc           #35                 // String .
     174: invokevirtual #12                 // Method java/lang/StringBuffer.append:(Ljava/lang/String;)Ljava/lang/StringBuffer;
     177: invokevirtual #14                 // Method java/lang/StringBuffer.toString:()Ljava/lang/String;
     180: invokespecial #15                 // Method java/lang/IllegalArgumentException."<init>":(Ljava/lang/String;)V
     183: athrow
     184: lload         4
     186: lreturn
    Exception table:
       from    to  target type
          36    45    48   Class java/lang/NumberFormatException
}
