Compiled from "RetryInvocationHandler.java"
class org.apache.hadoop.io.retry.RetryInvocationHandler$Counters {
  private int retries;

  private int failovers;

  org.apache.hadoop.io.retry.RetryInvocationHandler$Counters();
    Code:
       0: aload_0
       1: invokespecial #3                  // Method java/lang/Object."<init>":()V
       4: return

  boolean isZeros();
    Code:
       0: aload_0
       1: getfield      #2                  // Field retries:I
       4: ifne          18
       7: aload_0
       8: getfield      #1                  // Field failovers:I
      11: ifne          18
      14: iconst_1
      15: goto          19
      18: iconst_0
      19: ireturn

  static int access$508(org.apache.hadoop.io.retry.RetryInvocationHandler$Counters);
    Code:
       0: aload_0
       1: dup
       2: getfield      #2                  // Field retries:I
       5: dup_x1
       6: iconst_1
       7: iadd
       8: putfield      #2                  // Field retries:I
      11: ireturn

  static int access$808(org.apache.hadoop.io.retry.RetryInvocationHandler$Counters);
    Code:
       0: aload_0
       1: dup
       2: getfield      #1                  // Field failovers:I
       5: dup_x1
       6: iconst_1
       7: iadd
       8: putfield      #1                  // Field failovers:I
      11: ireturn

  static int access$500(org.apache.hadoop.io.retry.RetryInvocationHandler$Counters);
    Code:
       0: aload_0
       1: getfield      #2                  // Field retries:I
       4: ireturn

  static int access$800(org.apache.hadoop.io.retry.RetryInvocationHandler$Counters);
    Code:
       0: aload_0
       1: getfield      #1                  // Field failovers:I
       4: ireturn
}
