Compiled from "RetryPolicy.java"
public class org.apache.hadoop.io.retry.RetryPolicy$RetryAction {
  public static final org.apache.hadoop.io.retry.RetryPolicy$RetryAction FAIL;

  public static final org.apache.hadoop.io.retry.RetryPolicy$RetryAction RETRY;

  public static final org.apache.hadoop.io.retry.RetryPolicy$RetryAction FAILOVER_AND_RETRY;

  public final org.apache.hadoop.io.retry.RetryPolicy$RetryAction$RetryDecision action;

  public final long delayMillis;

  public final java.lang.String reason;

  public org.apache.hadoop.io.retry.RetryPolicy$RetryAction(org.apache.hadoop.io.retry.RetryPolicy$RetryAction$RetryDecision);
    Code:
       0: aload_0
       1: aload_1
       2: lconst_0
       3: aconst_null
       4: invokespecial #1                  // Method "<init>":(Lorg/apache/hadoop/io/retry/RetryPolicy$RetryAction$RetryDecision;JLjava/lang/String;)V
       7: return

  public org.apache.hadoop.io.retry.RetryPolicy$RetryAction(org.apache.hadoop.io.retry.RetryPolicy$RetryAction$RetryDecision, long);
    Code:
       0: aload_0
       1: aload_1
       2: lload_2
       3: aconst_null
       4: invokespecial #1                  // Method "<init>":(Lorg/apache/hadoop/io/retry/RetryPolicy$RetryAction$RetryDecision;JLjava/lang/String;)V
       7: return

  public org.apache.hadoop.io.retry.RetryPolicy$RetryAction(org.apache.hadoop.io.retry.RetryPolicy$RetryAction$RetryDecision, long, java.lang.String);
    Code:
       0: aload_0
       1: invokespecial #2                  // Method java/lang/Object."<init>":()V
       4: aload_0
       5: aload_1
       6: putfield      #3                  // Field action:Lorg/apache/hadoop/io/retry/RetryPolicy$RetryAction$RetryDecision;
       9: aload_0
      10: lload_2
      11: putfield      #4                  // Field delayMillis:J
      14: aload_0
      15: aload         4
      17: putfield      #5                  // Field reason:Ljava/lang/String;
      20: return

  public java.lang.String toString();
    Code:
       0: new           #6                  // class java/lang/StringBuilder
       3: dup
       4: invokespecial #7                  // Method java/lang/StringBuilder."<init>":()V
       7: aload_0
       8: invokevirtual #8                  // Method java/lang/Object.getClass:()Ljava/lang/Class;
      11: invokevirtual #9                  // Method java/lang/Class.getSimpleName:()Ljava/lang/String;
      14: invokevirtual #10                 // Method java/lang/StringBuilder.append:(Ljava/lang/String;)Ljava/lang/StringBuilder;
      17: ldc           #11                 // String (action=
      19: invokevirtual #10                 // Method java/lang/StringBuilder.append:(Ljava/lang/String;)Ljava/lang/StringBuilder;
      22: aload_0
      23: getfield      #3                  // Field action:Lorg/apache/hadoop/io/retry/RetryPolicy$RetryAction$RetryDecision;
      26: invokevirtual #12                 // Method java/lang/StringBuilder.append:(Ljava/lang/Object;)Ljava/lang/StringBuilder;
      29: ldc           #13                 // String , delayMillis=
      31: invokevirtual #10                 // Method java/lang/StringBuilder.append:(Ljava/lang/String;)Ljava/lang/StringBuilder;
      34: aload_0
      35: getfield      #4                  // Field delayMillis:J
      38: invokevirtual #14                 // Method java/lang/StringBuilder.append:(J)Ljava/lang/StringBuilder;
      41: ldc           #15                 // String , reason=
      43: invokevirtual #10                 // Method java/lang/StringBuilder.append:(Ljava/lang/String;)Ljava/lang/StringBuilder;
      46: aload_0
      47: getfield      #5                  // Field reason:Ljava/lang/String;
      50: invokevirtual #10                 // Method java/lang/StringBuilder.append:(Ljava/lang/String;)Ljava/lang/StringBuilder;
      53: ldc           #16                 // String )
      55: invokevirtual #10                 // Method java/lang/StringBuilder.append:(Ljava/lang/String;)Ljava/lang/StringBuilder;
      58: invokevirtual #17                 // Method java/lang/StringBuilder.toString:()Ljava/lang/String;
      61: areturn

  static {};
    Code:
       0: new           #18                 // class org/apache/hadoop/io/retry/RetryPolicy$RetryAction
       3: dup
       4: getstatic     #19                 // Field org/apache/hadoop/io/retry/RetryPolicy$RetryAction$RetryDecision.FAIL:Lorg/apache/hadoop/io/retry/RetryPolicy$RetryAction$RetryDecision;
       7: invokespecial #20                 // Method "<init>":(Lorg/apache/hadoop/io/retry/RetryPolicy$RetryAction$RetryDecision;)V
      10: putstatic     #21                 // Field FAIL:Lorg/apache/hadoop/io/retry/RetryPolicy$RetryAction;
      13: new           #18                 // class org/apache/hadoop/io/retry/RetryPolicy$RetryAction
      16: dup
      17: getstatic     #22                 // Field org/apache/hadoop/io/retry/RetryPolicy$RetryAction$RetryDecision.RETRY:Lorg/apache/hadoop/io/retry/RetryPolicy$RetryAction$RetryDecision;
      20: invokespecial #20                 // Method "<init>":(Lorg/apache/hadoop/io/retry/RetryPolicy$RetryAction$RetryDecision;)V
      23: putstatic     #23                 // Field RETRY:Lorg/apache/hadoop/io/retry/RetryPolicy$RetryAction;
      26: new           #18                 // class org/apache/hadoop/io/retry/RetryPolicy$RetryAction
      29: dup
      30: getstatic     #24                 // Field org/apache/hadoop/io/retry/RetryPolicy$RetryAction$RetryDecision.FAILOVER_AND_RETRY:Lorg/apache/hadoop/io/retry/RetryPolicy$RetryAction$RetryDecision;
      33: invokespecial #20                 // Method "<init>":(Lorg/apache/hadoop/io/retry/RetryPolicy$RetryAction$RetryDecision;)V
      36: putstatic     #25                 // Field FAILOVER_AND_RETRY:Lorg/apache/hadoop/io/retry/RetryPolicy$RetryAction;
      39: return
}
