Compiled from "HornetQJMSConnectionFactory.java"
public class org.hornetq.jms.client.HornetQJMSConnectionFactory extends org.hornetq.jms.client.HornetQConnectionFactory implements javax.jms.TopicConnectionFactory,javax.jms.QueueConnectionFactory {
  private static final long serialVersionUID;

  public org.hornetq.jms.client.HornetQJMSConnectionFactory();
    Code:
       0: aload_0
       1: invokespecial #1                  // Method org/hornetq/jms/client/HornetQConnectionFactory."<init>":()V
       4: return

  public org.hornetq.jms.client.HornetQJMSConnectionFactory(org.hornetq.api.core.client.ServerLocator);
    Code:
       0: aload_0
       1: aload_1
       2: invokespecial #2                  // Method org/hornetq/jms/client/HornetQConnectionFactory."<init>":(Lorg/hornetq/api/core/client/ServerLocator;)V
       5: return

  public org.hornetq.jms.client.HornetQJMSConnectionFactory(boolean, org.hornetq.api.core.DiscoveryGroupConfiguration);
    Code:
       0: aload_0
       1: iload_1
       2: aload_2
       3: invokespecial #3                  // Method org/hornetq/jms/client/HornetQConnectionFactory."<init>":(ZLorg/hornetq/api/core/DiscoveryGroupConfiguration;)V
       6: return

  public org.hornetq.jms.client.HornetQJMSConnectionFactory(boolean, org.hornetq.api.core.TransportConfiguration...);
    Code:
       0: aload_0
       1: iload_1
       2: aload_2
       3: invokespecial #4                  // Method org/hornetq/jms/client/HornetQConnectionFactory."<init>":(Z[Lorg/hornetq/api/core/TransportConfiguration;)V
       6: return
}
