Compiled from "SkipListMemTableConfig.java"
public class org.rocksdb.SkipListMemTableConfig extends org.rocksdb.MemTableConfig {
  public static final long DEFAULT_LOOKAHEAD;

  private long lookahead_;

  public org.rocksdb.SkipListMemTableConfig();
    Code:
       0: aload_0
       1: invokespecial #1                  // Method org/rocksdb/MemTableConfig."<init>":()V
       4: aload_0
       5: lconst_0
       6: putfield      #2                  // Field lookahead_:J
       9: return

  public org.rocksdb.SkipListMemTableConfig setLookahead(long);
    Code:
       0: aload_0
       1: lload_1
       2: putfield      #2                  // Field lookahead_:J
       5: aload_0
       6: areturn

  public long lookahead();
    Code:
       0: aload_0
       1: getfield      #2                  // Field lookahead_:J
       4: lreturn

  protected long newMemTableFactoryHandle();
    Code:
       0: aload_0
       1: aload_0
       2: getfield      #2                  // Field lookahead_:J
       5: invokespecial #3                  // Method newMemTableFactoryHandle0:(J)J
       8: lreturn

  private native long newMemTableFactoryHandle0(long) throws java.lang.IllegalArgumentException;
}
