Compiled from "PropertyBuilder.java"
class org.apache.htrace.shaded.fasterxml.jackson.databind.ser.PropertyBuilder$1 {
  static final int[] $SwitchMap$com$fasterxml$jackson$annotation$JsonInclude$Include;

  static {};
    Code:
       0: invokestatic  #22                 // Method org/apache/htrace/shaded/fasterxml/jackson/annotation/JsonInclude$Include.values:()[Lorg/apache/htrace/shaded/fasterxml/jackson/annotation/JsonInclude$Include;
       3: arraylength
       4: newarray       int
       6: putstatic     #24                 // Field $SwitchMap$com$fasterxml$jackson$annotation$JsonInclude$Include:[I
       9: getstatic     #24                 // Field $SwitchMap$com$fasterxml$jackson$annotation$JsonInclude$Include:[I
      12: getstatic     #28                 // Field org/apache/htrace/shaded/fasterxml/jackson/annotation/JsonInclude$Include.NON_DEFAULT:Lorg/apache/htrace/shaded/fasterxml/jackson/annotation/JsonInclude$Include;
      15: invokevirtual #32                 // Method org/apache/htrace/shaded/fasterxml/jackson/annotation/JsonInclude$Include.ordinal:()I
      18: iconst_1
      19: iastore
      20: goto          24
      23: astore_0
      24: getstatic     #24                 // Field $SwitchMap$com$fasterxml$jackson$annotation$JsonInclude$Include:[I
      27: getstatic     #35                 // Field org/apache/htrace/shaded/fasterxml/jackson/annotation/JsonInclude$Include.NON_EMPTY:Lorg/apache/htrace/shaded/fasterxml/jackson/annotation/JsonInclude$Include;
      30: invokevirtual #32                 // Method org/apache/htrace/shaded/fasterxml/jackson/annotation/JsonInclude$Include.ordinal:()I
      33: iconst_2
      34: iastore
      35: goto          39
      38: astore_0
      39: getstatic     #24                 // Field $SwitchMap$com$fasterxml$jackson$annotation$JsonInclude$Include:[I
      42: getstatic     #38                 // Field org/apache/htrace/shaded/fasterxml/jackson/annotation/JsonInclude$Include.NON_NULL:Lorg/apache/htrace/shaded/fasterxml/jackson/annotation/JsonInclude$Include;
      45: invokevirtual #32                 // Method org/apache/htrace/shaded/fasterxml/jackson/annotation/JsonInclude$Include.ordinal:()I
      48: iconst_3
      49: iastore
      50: goto          54
      53: astore_0
      54: getstatic     #24                 // Field $SwitchMap$com$fasterxml$jackson$annotation$JsonInclude$Include:[I
      57: getstatic     #41                 // Field org/apache/htrace/shaded/fasterxml/jackson/annotation/JsonInclude$Include.ALWAYS:Lorg/apache/htrace/shaded/fasterxml/jackson/annotation/JsonInclude$Include;
      60: invokevirtual #32                 // Method org/apache/htrace/shaded/fasterxml/jackson/annotation/JsonInclude$Include.ordinal:()I
      63: iconst_4
      64: iastore
      65: goto          69
      68: astore_0
      69: return
    Exception table:
       from    to  target type
           9    20    23   Class java/lang/NoSuchFieldError
          24    35    38   Class java/lang/NoSuchFieldError
          39    50    53   Class java/lang/NoSuchFieldError
          54    65    68   Class java/lang/NoSuchFieldError
}
