Compiled from "StringArrayDeserializer.java"
public final class org.apache.htrace.shaded.fasterxml.jackson.databind.deser.std.StringArrayDeserializer extends org.apache.htrace.shaded.fasterxml.jackson.databind.deser.std.StdDeserializer<java.lang.String[]> implements org.apache.htrace.shaded.fasterxml.jackson.databind.deser.ContextualDeserializer {
  private static final long serialVersionUID;

  public static final org.apache.htrace.shaded.fasterxml.jackson.databind.deser.std.StringArrayDeserializer instance;

  protected org.apache.htrace.shaded.fasterxml.jackson.databind.JsonDeserializer<java.lang.String> _elementDeserializer;

  public org.apache.htrace.shaded.fasterxml.jackson.databind.deser.std.StringArrayDeserializer();
    Code:
       0: aload_0
       1: ldc           #22                 // class "[Ljava/lang/String;"
       3: invokespecial #25                 // Method org/apache/htrace/shaded/fasterxml/jackson/databind/deser/std/StdDeserializer."<init>":(Ljava/lang/Class;)V
       6: aload_0
       7: aconst_null
       8: putfield      #27                 // Field _elementDeserializer:Lorg/apache/htrace/shaded/fasterxml/jackson/databind/JsonDeserializer;
      11: return

  protected org.apache.htrace.shaded.fasterxml.jackson.databind.deser.std.StringArrayDeserializer(org.apache.htrace.shaded.fasterxml.jackson.databind.JsonDeserializer<?>);
    Code:
       0: aload_0
       1: ldc           #22                 // class "[Ljava/lang/String;"
       3: invokespecial #25                 // Method org/apache/htrace/shaded/fasterxml/jackson/databind/deser/std/StdDeserializer."<init>":(Ljava/lang/Class;)V
       6: aload_0
       7: aload_1
       8: putfield      #27                 // Field _elementDeserializer:Lorg/apache/htrace/shaded/fasterxml/jackson/databind/JsonDeserializer;
      11: return

  public java.lang.String[] deserialize(org.apache.htrace.shaded.fasterxml.jackson.core.JsonParser, org.apache.htrace.shaded.fasterxml.jackson.databind.DeserializationContext) throws java.io.IOException;
    Code:
       0: aload_1
       1: invokevirtual #41                 // Method org/apache/htrace/shaded/fasterxml/jackson/core/JsonParser.isExpectedStartArrayToken:()Z
       4: ifne          14
       7: aload_0
       8: aload_1
       9: aload_2
      10: invokespecial #44                 // Method handleNonArray:(Lorg/apache/htrace/shaded/fasterxml/jackson/core/JsonParser;Lorg/apache/htrace/shaded/fasterxml/jackson/databind/DeserializationContext;)[Ljava/lang/String;
      13: areturn
      14: aload_0
      15: getfield      #27                 // Field _elementDeserializer:Lorg/apache/htrace/shaded/fasterxml/jackson/databind/JsonDeserializer;
      18: ifnull        28
      21: aload_0
      22: aload_1
      23: aload_2
      24: invokevirtual #47                 // Method _deserializeCustom:(Lorg/apache/htrace/shaded/fasterxml/jackson/core/JsonParser;Lorg/apache/htrace/shaded/fasterxml/jackson/databind/DeserializationContext;)[Ljava/lang/String;
      27: areturn
      28: aload_2
      29: invokevirtual #53                 // Method org/apache/htrace/shaded/fasterxml/jackson/databind/DeserializationContext.leaseObjectBuffer:()Lorg/apache/htrace/shaded/fasterxml/jackson/databind/util/ObjectBuffer;
      32: astore_3
      33: aload_3
      34: invokevirtual #59                 // Method org/apache/htrace/shaded/fasterxml/jackson/databind/util/ObjectBuffer.resetAndStart:()[Ljava/lang/Object;
      37: astore        4
      39: iconst_0
      40: istore        5
      42: aload_1
      43: invokevirtual #65                 // Method org/apache/htrace/shaded/fasterxml/jackson/core/JsonParser.nextToken:()Lorg/apache/htrace/shaded/fasterxml/jackson/core/JsonToken;
      46: dup
      47: astore        6
      49: getstatic     #71                 // Field org/apache/htrace/shaded/fasterxml/jackson/core/JsonToken.END_ARRAY:Lorg/apache/htrace/shaded/fasterxml/jackson/core/JsonToken;
      52: if_acmpeq     135
      55: aload         6
      57: getstatic     #74                 // Field org/apache/htrace/shaded/fasterxml/jackson/core/JsonToken.VALUE_STRING:Lorg/apache/htrace/shaded/fasterxml/jackson/core/JsonToken;
      60: if_acmpne     72
      63: aload_1
      64: invokevirtual #78                 // Method org/apache/htrace/shaded/fasterxml/jackson/core/JsonParser.getText:()Ljava/lang/String;
      67: astore        7
      69: goto          103
      72: aload         6
      74: getstatic     #81                 // Field org/apache/htrace/shaded/fasterxml/jackson/core/JsonToken.VALUE_NULL:Lorg/apache/htrace/shaded/fasterxml/jackson/core/JsonToken;
      77: if_acmpne     95
      80: aload_0
      81: getfield      #27                 // Field _elementDeserializer:Lorg/apache/htrace/shaded/fasterxml/jackson/databind/JsonDeserializer;
      84: invokevirtual #87                 // Method org/apache/htrace/shaded/fasterxml/jackson/databind/JsonDeserializer.getNullValue:()Ljava/lang/Object;
      87: checkcast     #89                 // class java/lang/String
      90: astore        7
      92: goto          103
      95: aload_0
      96: aload_1
      97: aload_2
      98: invokevirtual #93                 // Method _parseString:(Lorg/apache/htrace/shaded/fasterxml/jackson/core/JsonParser;Lorg/apache/htrace/shaded/fasterxml/jackson/databind/DeserializationContext;)Ljava/lang/String;
     101: astore        7
     103: iload         5
     105: aload         4
     107: arraylength
     108: if_icmplt     122
     111: aload_3
     112: aload         4
     114: invokevirtual #97                 // Method org/apache/htrace/shaded/fasterxml/jackson/databind/util/ObjectBuffer.appendCompletedChunk:([Ljava/lang/Object;)[Ljava/lang/Object;
     117: astore        4
     119: iconst_0
     120: istore        5
     122: aload         4
     124: iload         5
     126: iinc          5, 1
     129: aload         7
     131: aastore
     132: goto          42
     135: aload_3
     136: aload         4
     138: iload         5
     140: ldc           #89                 // class java/lang/String
     142: invokevirtual #101                // Method org/apache/htrace/shaded/fasterxml/jackson/databind/util/ObjectBuffer.completeAndClearBuffer:([Ljava/lang/Object;ILjava/lang/Class;)[Ljava/lang/Object;
     145: checkcast     #22                 // class "[Ljava/lang/String;"
     148: astore        7
     150: aload_2
     151: aload_3
     152: invokevirtual #105                // Method org/apache/htrace/shaded/fasterxml/jackson/databind/DeserializationContext.returnObjectBuffer:(Lorg/apache/htrace/shaded/fasterxml/jackson/databind/util/ObjectBuffer;)V
     155: aload         7
     157: areturn

  protected final java.lang.String[] _deserializeCustom(org.apache.htrace.shaded.fasterxml.jackson.core.JsonParser, org.apache.htrace.shaded.fasterxml.jackson.databind.DeserializationContext) throws java.io.IOException;
    Code:
       0: aload_2
       1: invokevirtual #53                 // Method org/apache/htrace/shaded/fasterxml/jackson/databind/DeserializationContext.leaseObjectBuffer:()Lorg/apache/htrace/shaded/fasterxml/jackson/databind/util/ObjectBuffer;
       4: astore_3
       5: aload_3
       6: invokevirtual #59                 // Method org/apache/htrace/shaded/fasterxml/jackson/databind/util/ObjectBuffer.resetAndStart:()[Ljava/lang/Object;
       9: astore        4
      11: aload_0
      12: getfield      #27                 // Field _elementDeserializer:Lorg/apache/htrace/shaded/fasterxml/jackson/databind/JsonDeserializer;
      15: astore        5
      17: iconst_0
      18: istore        6
      20: aload_1
      21: invokevirtual #65                 // Method org/apache/htrace/shaded/fasterxml/jackson/core/JsonParser.nextToken:()Lorg/apache/htrace/shaded/fasterxml/jackson/core/JsonToken;
      24: dup
      25: astore        7
      27: getstatic     #71                 // Field org/apache/htrace/shaded/fasterxml/jackson/core/JsonToken.END_ARRAY:Lorg/apache/htrace/shaded/fasterxml/jackson/core/JsonToken;
      30: if_acmpeq     89
      33: aload         7
      35: getstatic     #81                 // Field org/apache/htrace/shaded/fasterxml/jackson/core/JsonToken.VALUE_NULL:Lorg/apache/htrace/shaded/fasterxml/jackson/core/JsonToken;
      38: if_acmpne     45
      41: aconst_null
      42: goto          55
      45: aload         5
      47: aload_1
      48: aload_2
      49: invokevirtual #121                // Method org/apache/htrace/shaded/fasterxml/jackson/databind/JsonDeserializer.deserialize:(Lorg/apache/htrace/shaded/fasterxml/jackson/core/JsonParser;Lorg/apache/htrace/shaded/fasterxml/jackson/databind/DeserializationContext;)Ljava/lang/Object;
      52: checkcast     #89                 // class java/lang/String
      55: astore        8
      57: iload         6
      59: aload         4
      61: arraylength
      62: if_icmplt     76
      65: aload_3
      66: aload         4
      68: invokevirtual #97                 // Method org/apache/htrace/shaded/fasterxml/jackson/databind/util/ObjectBuffer.appendCompletedChunk:([Ljava/lang/Object;)[Ljava/lang/Object;
      71: astore        4
      73: iconst_0
      74: istore        6
      76: aload         4
      78: iload         6
      80: iinc          6, 1
      83: aload         8
      85: aastore
      86: goto          20
      89: aload_3
      90: aload         4
      92: iload         6
      94: ldc           #89                 // class java/lang/String
      96: invokevirtual #101                // Method org/apache/htrace/shaded/fasterxml/jackson/databind/util/ObjectBuffer.completeAndClearBuffer:([Ljava/lang/Object;ILjava/lang/Class;)[Ljava/lang/Object;
      99: checkcast     #22                 // class "[Ljava/lang/String;"
     102: astore        8
     104: aload_2
     105: aload_3
     106: invokevirtual #105                // Method org/apache/htrace/shaded/fasterxml/jackson/databind/DeserializationContext.returnObjectBuffer:(Lorg/apache/htrace/shaded/fasterxml/jackson/databind/util/ObjectBuffer;)V
     109: aload         8
     111: areturn

  public java.lang.Object deserializeWithType(org.apache.htrace.shaded.fasterxml.jackson.core.JsonParser, org.apache.htrace.shaded.fasterxml.jackson.databind.DeserializationContext, org.apache.htrace.shaded.fasterxml.jackson.databind.jsontype.TypeDeserializer) throws java.io.IOException;
    Code:
       0: aload_3
       1: aload_1
       2: aload_2
       3: invokevirtual #128                // Method org/apache/htrace/shaded/fasterxml/jackson/databind/jsontype/TypeDeserializer.deserializeTypedFromArray:(Lorg/apache/htrace/shaded/fasterxml/jackson/core/JsonParser;Lorg/apache/htrace/shaded/fasterxml/jackson/databind/DeserializationContext;)Ljava/lang/Object;
       6: areturn

  private final java.lang.String[] handleNonArray(org.apache.htrace.shaded.fasterxml.jackson.core.JsonParser, org.apache.htrace.shaded.fasterxml.jackson.databind.DeserializationContext) throws java.io.IOException;
    Code:
       0: aload_2
       1: getstatic     #136                // Field org/apache/htrace/shaded/fasterxml/jackson/databind/DeserializationFeature.ACCEPT_SINGLE_VALUE_AS_ARRAY:Lorg/apache/htrace/shaded/fasterxml/jackson/databind/DeserializationFeature;
       4: invokevirtual #140                // Method org/apache/htrace/shaded/fasterxml/jackson/databind/DeserializationContext.isEnabled:(Lorg/apache/htrace/shaded/fasterxml/jackson/databind/DeserializationFeature;)Z
       7: ifne          53
      10: aload_1
      11: invokevirtual #143                // Method org/apache/htrace/shaded/fasterxml/jackson/core/JsonParser.getCurrentToken:()Lorg/apache/htrace/shaded/fasterxml/jackson/core/JsonToken;
      14: getstatic     #74                 // Field org/apache/htrace/shaded/fasterxml/jackson/core/JsonToken.VALUE_STRING:Lorg/apache/htrace/shaded/fasterxml/jackson/core/JsonToken;
      17: if_acmpne     44
      20: aload_2
      21: getstatic     #146                // Field org/apache/htrace/shaded/fasterxml/jackson/databind/DeserializationFeature.ACCEPT_EMPTY_STRING_AS_NULL_OBJECT:Lorg/apache/htrace/shaded/fasterxml/jackson/databind/DeserializationFeature;
      24: invokevirtual #140                // Method org/apache/htrace/shaded/fasterxml/jackson/databind/DeserializationContext.isEnabled:(Lorg/apache/htrace/shaded/fasterxml/jackson/databind/DeserializationFeature;)Z
      27: ifeq          44
      30: aload_1
      31: invokevirtual #78                 // Method org/apache/htrace/shaded/fasterxml/jackson/core/JsonParser.getText:()Ljava/lang/String;
      34: astore_3
      35: aload_3
      36: invokevirtual #150                // Method java/lang/String.length:()I
      39: ifne          44
      42: aconst_null
      43: areturn
      44: aload_2
      45: aload_0
      46: getfield      #154                // Field _valueClass:Ljava/lang/Class;
      49: invokevirtual #158                // Method org/apache/htrace/shaded/fasterxml/jackson/databind/DeserializationContext.mappingException:(Ljava/lang/Class;)Lorg/apache/htrace/shaded/fasterxml/jackson/databind/JsonMappingException;
      52: athrow
      53: iconst_1
      54: anewarray     #89                 // class java/lang/String
      57: dup
      58: iconst_0
      59: aload_1
      60: invokevirtual #143                // Method org/apache/htrace/shaded/fasterxml/jackson/core/JsonParser.getCurrentToken:()Lorg/apache/htrace/shaded/fasterxml/jackson/core/JsonToken;
      63: getstatic     #81                 // Field org/apache/htrace/shaded/fasterxml/jackson/core/JsonToken.VALUE_NULL:Lorg/apache/htrace/shaded/fasterxml/jackson/core/JsonToken;
      66: if_acmpne     73
      69: aconst_null
      70: goto          79
      73: aload_0
      74: aload_1
      75: aload_2
      76: invokevirtual #93                 // Method _parseString:(Lorg/apache/htrace/shaded/fasterxml/jackson/core/JsonParser;Lorg/apache/htrace/shaded/fasterxml/jackson/databind/DeserializationContext;)Ljava/lang/String;
      79: aastore
      80: areturn

  public org.apache.htrace.shaded.fasterxml.jackson.databind.JsonDeserializer<?> createContextual(org.apache.htrace.shaded.fasterxml.jackson.databind.DeserializationContext, org.apache.htrace.shaded.fasterxml.jackson.databind.BeanProperty) throws org.apache.htrace.shaded.fasterxml.jackson.databind.JsonMappingException;
    Code:
       0: aload_0
       1: getfield      #27                 // Field _elementDeserializer:Lorg/apache/htrace/shaded/fasterxml/jackson/databind/JsonDeserializer;
       4: astore_3
       5: aload_0
       6: aload_1
       7: aload_2
       8: aload_3
       9: invokevirtual #167                // Method findConvertingContentDeserializer:(Lorg/apache/htrace/shaded/fasterxml/jackson/databind/DeserializationContext;Lorg/apache/htrace/shaded/fasterxml/jackson/databind/BeanProperty;Lorg/apache/htrace/shaded/fasterxml/jackson/databind/JsonDeserializer;)Lorg/apache/htrace/shaded/fasterxml/jackson/databind/JsonDeserializer;
      12: astore_3
      13: aload_3
      14: ifnonnull     32
      17: aload_1
      18: aload_1
      19: ldc           #89                 // class java/lang/String
      21: invokevirtual #171                // Method org/apache/htrace/shaded/fasterxml/jackson/databind/DeserializationContext.constructType:(Ljava/lang/Class;)Lorg/apache/htrace/shaded/fasterxml/jackson/databind/JavaType;
      24: aload_2
      25: invokevirtual #175                // Method org/apache/htrace/shaded/fasterxml/jackson/databind/DeserializationContext.findContextualValueDeserializer:(Lorg/apache/htrace/shaded/fasterxml/jackson/databind/JavaType;Lorg/apache/htrace/shaded/fasterxml/jackson/databind/BeanProperty;)Lorg/apache/htrace/shaded/fasterxml/jackson/databind/JsonDeserializer;
      28: astore_3
      29: goto          39
      32: aload_1
      33: aload_3
      34: aload_2
      35: invokevirtual #179                // Method org/apache/htrace/shaded/fasterxml/jackson/databind/DeserializationContext.handleSecondaryContextualization:(Lorg/apache/htrace/shaded/fasterxml/jackson/databind/JsonDeserializer;Lorg/apache/htrace/shaded/fasterxml/jackson/databind/BeanProperty;)Lorg/apache/htrace/shaded/fasterxml/jackson/databind/JsonDeserializer;
      38: astore_3
      39: aload_3
      40: ifnull        53
      43: aload_0
      44: aload_3
      45: invokevirtual #183                // Method isDefaultDeserializer:(Lorg/apache/htrace/shaded/fasterxml/jackson/databind/JsonDeserializer;)Z
      48: ifeq          53
      51: aconst_null
      52: astore_3
      53: aload_0
      54: getfield      #27                 // Field _elementDeserializer:Lorg/apache/htrace/shaded/fasterxml/jackson/databind/JsonDeserializer;
      57: aload_3
      58: if_acmpeq     70
      61: new           #2                  // class org/apache/htrace/shaded/fasterxml/jackson/databind/deser/std/StringArrayDeserializer
      64: dup
      65: aload_3
      66: invokespecial #185                // Method "<init>":(Lorg/apache/htrace/shaded/fasterxml/jackson/databind/JsonDeserializer;)V
      69: areturn
      70: aload_0
      71: areturn

  public java.lang.Object deserialize(org.apache.htrace.shaded.fasterxml.jackson.core.JsonParser, org.apache.htrace.shaded.fasterxml.jackson.databind.DeserializationContext) throws java.io.IOException, org.apache.htrace.shaded.fasterxml.jackson.core.JsonProcessingException;
    Code:
       0: aload_0
       1: aload_1
       2: aload_2
       3: invokevirtual #191                // Method deserialize:(Lorg/apache/htrace/shaded/fasterxml/jackson/core/JsonParser;Lorg/apache/htrace/shaded/fasterxml/jackson/databind/DeserializationContext;)[Ljava/lang/String;
       6: areturn

  static {};
    Code:
       0: new           #2                  // class org/apache/htrace/shaded/fasterxml/jackson/databind/deser/std/StringArrayDeserializer
       3: dup
       4: invokespecial #196                // Method "<init>":()V
       7: putstatic     #198                // Field instance:Lorg/apache/htrace/shaded/fasterxml/jackson/databind/deser/std/StringArrayDeserializer;
      10: return
}
