Compiled from "MesosResourceUsageUtils.java"
class io.mantisrx.server.worker.mesos.MesosResourceUsageUtils$4 implements rx.functions.Func1<mantis.io.reactivex.netty.protocol.http.client.HttpClientResponse<io.netty.buffer.ByteBuf>, rx.Observable<io.netty.buffer.ByteBuf>> {
  final io.mantisrx.server.worker.mesos.MesosResourceUsageUtils this$0;

  io.mantisrx.server.worker.mesos.MesosResourceUsageUtils$4(io.mantisrx.server.worker.mesos.MesosResourceUsageUtils);
    Code:
       0: aload_0
       1: aload_1
       2: putfield      #1                  // Field this$0:Lio/mantisrx/server/worker/mesos/MesosResourceUsageUtils;
       5: aload_0
       6: invokespecial #2                  // Method java/lang/Object."<init>":()V
       9: return

  public rx.Observable<io.netty.buffer.ByteBuf> call(mantis.io.reactivex.netty.protocol.http.client.HttpClientResponse<io.netty.buffer.ByteBuf>);
    Code:
       0: aload_1
       1: invokevirtual #3                  // Method mantis/io/reactivex/netty/protocol/http/client/HttpClientResponse.getContent:()Lrx/Observable;
       4: areturn

  public java.lang.Object call(java.lang.Object);
    Code:
       0: aload_0
       1: aload_1
       2: checkcast     #4                  // class mantis/io/reactivex/netty/protocol/http/client/HttpClientResponse
       5: invokevirtual #5                  // Method call:(Lmantis/io/reactivex/netty/protocol/http/client/HttpClientResponse;)Lrx/Observable;
       8: areturn
}
