Compiled from "PasswordCallbackHandler.java"
public class org.jboss.wsf.stack.cxf.extensions.security.PasswordCallbackHandler implements javax.security.auth.callback.CallbackHandler {
  private java.util.Map<java.lang.String, java.lang.String> passwords;

  public org.jboss.wsf.stack.cxf.extensions.security.PasswordCallbackHandler(java.util.Map<java.lang.String, java.lang.String>);
    Code:
       0: aload_0
       1: invokespecial #1                  // Method java/lang/Object."<init>":()V
       4: aload_0
       5: new           #2                  // class java/util/HashMap
       8: dup
       9: invokespecial #3                  // Method java/util/HashMap."<init>":()V
      12: putfield      #4                  // Field passwords:Ljava/util/Map;
      15: aload_0
      16: getfield      #4                  // Field passwords:Ljava/util/Map;
      19: aload_1
      20: invokeinterface #5,  2            // InterfaceMethod java/util/Map.putAll:(Ljava/util/Map;)V
      25: return

  public void handle(javax.security.auth.callback.Callback[]) throws java.io.IOException, javax.security.auth.callback.UnsupportedCallbackException;
    Code:
       0: iconst_0
       1: istore_2
       2: iload_2
       3: aload_1
       4: arraylength
       5: if_icmpge     67
       8: aload_1
       9: iload_2
      10: aaload
      11: astore_3
      12: aload_3
      13: ifnull        61
      16: aload_3
      17: instanceof    #6                  // class org/apache/wss4j/common/ext/WSPasswordCallback
      20: ifeq          61
      23: aload_3
      24: checkcast     #6                  // class org/apache/wss4j/common/ext/WSPasswordCallback
      27: astore        4
      29: aload_0
      30: getfield      #4                  // Field passwords:Ljava/util/Map;
      33: aload         4
      35: invokevirtual #7                  // Method org/apache/wss4j/common/ext/WSPasswordCallback.getIdentifier:()Ljava/lang/String;
      38: invokeinterface #8,  2            // InterfaceMethod java/util/Map.get:(Ljava/lang/Object;)Ljava/lang/Object;
      43: checkcast     #9                  // class java/lang/String
      46: astore        5
      48: aload         5
      50: ifnull        61
      53: aload         4
      55: aload         5
      57: invokevirtual #10                 // Method org/apache/wss4j/common/ext/WSPasswordCallback.setPassword:(Ljava/lang/String;)V
      60: return
      61: iinc          2, 1
      64: goto          2
      67: return

  public void setAliasPassword(java.lang.String, java.lang.String);
    Code:
       0: aload_0
       1: getfield      #4                  // Field passwords:Ljava/util/Map;
       4: aload_1
       5: aload_2
       6: invokeinterface #11,  3           // InterfaceMethod java/util/Map.put:(Ljava/lang/Object;Ljava/lang/Object;)Ljava/lang/Object;
      11: pop
      12: return
}
