Compiled from "Token.java"
class ch.qos.logback.core.pattern.parser.Token {
  static final int PERCENT;

  static final int RIGHT_PARENTHESIS;

  static final int MINUS;

  static final int DOT;

  static final int CURLY_LEFT;

  static final int CURLY_RIGHT;

  static final int LITERAL;

  static final int FORMAT_MODIFIER;

  static final int SIMPLE_KEYWORD;

  static final int COMPOSITE_KEYWORD;

  static final int OPTION;

  static final int EOF;

  static ch.qos.logback.core.pattern.parser.Token EOF_TOKEN;

  static ch.qos.logback.core.pattern.parser.Token RIGHT_PARENTHESIS_TOKEN;

  static ch.qos.logback.core.pattern.parser.Token BARE_COMPOSITE_KEYWORD_TOKEN;

  static ch.qos.logback.core.pattern.parser.Token PERCENT_TOKEN;

  private final int type;

  private final java.lang.Object value;

  public ch.qos.logback.core.pattern.parser.Token(int);
    Code:
       0: aload_0
       1: iload_1
       2: aconst_null
       3: invokespecial #1                  // Method "<init>":(ILjava/lang/Object;)V
       6: return

  public ch.qos.logback.core.pattern.parser.Token(int, java.lang.Object);
    Code:
       0: aload_0
       1: invokespecial #2                  // Method java/lang/Object."<init>":()V
       4: aload_0
       5: iload_1
       6: putfield      #3                  // Field type:I
       9: aload_0
      10: aload_2
      11: putfield      #4                  // Field value:Ljava/lang/Object;
      14: return

  public int getType();
    Code:
       0: aload_0
       1: getfield      #3                  // Field type:I
       4: ireturn

  public java.lang.Object getValue();
    Code:
       0: aload_0
       1: getfield      #4                  // Field value:Ljava/lang/Object;
       4: areturn

  public java.lang.String toString();
    Code:
       0: aconst_null
       1: astore_1
       2: aload_0
       3: getfield      #3                  // Field type:I
       6: lookupswitch  { // 7
                    37: 72
                    41: 108
                  1000: 84
                  1002: 78
                  1004: 96
                  1005: 102
                  1006: 90
               default: 114
          }
      72: ldc           #5                  // String %
      74: astore_1
      75: goto          117
      78: ldc           #6                  // String FormatModifier
      80: astore_1
      81: goto          117
      84: ldc           #7                  // String LITERAL
      86: astore_1
      87: goto          117
      90: ldc           #8                  // String OPTION
      92: astore_1
      93: goto          117
      96: ldc           #9                  // String SIMPLE_KEYWORD
      98: astore_1
      99: goto          117
     102: ldc           #10                 // String COMPOSITE_KEYWORD
     104: astore_1
     105: goto          117
     108: ldc           #11                 // String RIGHT_PARENTHESIS
     110: astore_1
     111: goto          117
     114: ldc           #12                 // String UNKNOWN
     116: astore_1
     117: aload_0
     118: getfield      #4                  // Field value:Ljava/lang/Object;
     121: ifnonnull     149
     124: new           #13                 // class java/lang/StringBuilder
     127: dup
     128: invokespecial #14                 // Method java/lang/StringBuilder."<init>":()V
     131: ldc           #15                 // String Token(
     133: invokevirtual #16                 // Method java/lang/StringBuilder.append:(Ljava/lang/String;)Ljava/lang/StringBuilder;
     136: aload_1
     137: invokevirtual #16                 // Method java/lang/StringBuilder.append:(Ljava/lang/String;)Ljava/lang/StringBuilder;
     140: ldc           #17                 // String )
     142: invokevirtual #16                 // Method java/lang/StringBuilder.append:(Ljava/lang/String;)Ljava/lang/StringBuilder;
     145: invokevirtual #18                 // Method java/lang/StringBuilder.toString:()Ljava/lang/String;
     148: areturn
     149: new           #13                 // class java/lang/StringBuilder
     152: dup
     153: invokespecial #14                 // Method java/lang/StringBuilder."<init>":()V
     156: ldc           #15                 // String Token(
     158: invokevirtual #16                 // Method java/lang/StringBuilder.append:(Ljava/lang/String;)Ljava/lang/StringBuilder;
     161: aload_1
     162: invokevirtual #16                 // Method java/lang/StringBuilder.append:(Ljava/lang/String;)Ljava/lang/StringBuilder;
     165: ldc           #19                 // String , \"
     167: invokevirtual #16                 // Method java/lang/StringBuilder.append:(Ljava/lang/String;)Ljava/lang/StringBuilder;
     170: aload_0
     171: getfield      #4                  // Field value:Ljava/lang/Object;
     174: invokevirtual #20                 // Method java/lang/StringBuilder.append:(Ljava/lang/Object;)Ljava/lang/StringBuilder;
     177: ldc           #21                 // String \")
     179: invokevirtual #16                 // Method java/lang/StringBuilder.append:(Ljava/lang/String;)Ljava/lang/StringBuilder;
     182: invokevirtual #18                 // Method java/lang/StringBuilder.toString:()Ljava/lang/String;
     185: areturn

  public int hashCode();
    Code:
       0: aload_0
       1: getfield      #3                  // Field type:I
       4: istore_1
       5: bipush        29
       7: iload_1
       8: imul
       9: aload_0
      10: getfield      #4                  // Field value:Ljava/lang/Object;
      13: ifnull        26
      16: aload_0
      17: getfield      #4                  // Field value:Ljava/lang/Object;
      20: invokevirtual #22                 // Method java/lang/Object.hashCode:()I
      23: goto          27
      26: iconst_0
      27: iadd
      28: istore_1
      29: iload_1
      30: ireturn

  public boolean equals(java.lang.Object);
    Code:
       0: aload_0
       1: aload_1
       2: if_acmpne     7
       5: iconst_1
       6: ireturn
       7: aload_1
       8: instanceof    #23                 // class ch/qos/logback/core/pattern/parser/Token
      11: ifne          16
      14: iconst_0
      15: ireturn
      16: aload_1
      17: checkcast     #23                 // class ch/qos/logback/core/pattern/parser/Token
      20: astore_2
      21: aload_0
      22: getfield      #3                  // Field type:I
      25: aload_2
      26: getfield      #3                  // Field type:I
      29: if_icmpeq     34
      32: iconst_0
      33: ireturn
      34: aload_0
      35: getfield      #4                  // Field value:Ljava/lang/Object;
      38: ifnull        58
      41: aload_0
      42: getfield      #4                  // Field value:Ljava/lang/Object;
      45: aload_2
      46: getfield      #4                  // Field value:Ljava/lang/Object;
      49: invokevirtual #24                 // Method java/lang/Object.equals:(Ljava/lang/Object;)Z
      52: ifne          67
      55: goto          65
      58: aload_2
      59: getfield      #4                  // Field value:Ljava/lang/Object;
      62: ifnull        67
      65: iconst_0
      66: ireturn
      67: iconst_1
      68: ireturn

  static {};
    Code:
       0: new           #23                 // class ch/qos/logback/core/pattern/parser/Token
       3: dup
       4: ldc           #25                 // int 2147483647
       6: ldc           #26                 // String EOF
       8: invokespecial #1                  // Method "<init>":(ILjava/lang/Object;)V
      11: putstatic     #27                 // Field EOF_TOKEN:Lch/qos/logback/core/pattern/parser/Token;
      14: new           #23                 // class ch/qos/logback/core/pattern/parser/Token
      17: dup
      18: bipush        41
      20: invokespecial #28                 // Method "<init>":(I)V
      23: putstatic     #29                 // Field RIGHT_PARENTHESIS_TOKEN:Lch/qos/logback/core/pattern/parser/Token;
      26: new           #23                 // class ch/qos/logback/core/pattern/parser/Token
      29: dup
      30: sipush        1005
      33: ldc           #30                 // String BARE
      35: invokespecial #1                  // Method "<init>":(ILjava/lang/Object;)V
      38: putstatic     #31                 // Field BARE_COMPOSITE_KEYWORD_TOKEN:Lch/qos/logback/core/pattern/parser/Token;
      41: new           #23                 // class ch/qos/logback/core/pattern/parser/Token
      44: dup
      45: bipush        37
      47: invokespecial #28                 // Method "<init>":(I)V
      50: putstatic     #32                 // Field PERCENT_TOKEN:Lch/qos/logback/core/pattern/parser/Token;
      53: return
}
