Compiled from "TransactionManagerDelegate.java"
public class com.arjuna.ats.jbossatx.jta.TransactionManagerDelegate extends com.arjuna.ats.jbossatx.BaseTransactionManagerDelegate implements javax.naming.spi.ObjectFactory {
  private static final com.arjuna.ats.internal.jta.transaction.arjunacore.TransactionManagerImple TRANSACTION_MANAGER;

  public com.arjuna.ats.jbossatx.jta.TransactionManagerDelegate();
    Code:
       0: aload_0
       1: invokestatic  #1                  // Method getTransactionManager:()Lcom/arjuna/ats/internal/jta/transaction/arjunacore/TransactionManagerImple;
       4: invokespecial #2                  // Method com/arjuna/ats/jbossatx/BaseTransactionManagerDelegate."<init>":(Ljavax/transaction/TransactionManager;)V
       7: return

  public int getTransactionTimeout() throws javax.transaction.SystemException;
    Code:
       0: invokestatic  #1                  // Method getTransactionManager:()Lcom/arjuna/ats/internal/jta/transaction/arjunacore/TransactionManagerImple;
       3: invokevirtual #3                  // Method com/arjuna/ats/internal/jta/transaction/arjunacore/TransactionManagerImple.getTimeout:()I
       6: ireturn

  public long getTimeLeftBeforeTransactionTimeout(boolean) throws javax.transaction.RollbackException;
    Code:
       0: aload_0
       1: invokevirtual #4                  // Method getStatus:()I
       4: tableswitch   { // 0 to 9
                     0: 88
                     1: 60
                     2: 88
                     3: 80
                     4: 60
                     5: 80
                     6: 109
                     7: 88
                     8: 80
                     9: 60
               default: 109
          }
      60: iload_1
      61: ifeq          109
      64: new           #5                  // class javax/transaction/RollbackException
      67: dup
      68: getstatic     #6                  // Field com/arjuna/ats/jbossatx/logging/jbossatxLogger.i18NLogger:Lcom/arjuna/ats/jbossatx/logging/jbossatxI18NLogger;
      71: invokeinterface #7,  1            // InterfaceMethod com/arjuna/ats/jbossatx/logging/jbossatxI18NLogger.get_jta_TransactionManagerDelegate_getTimeLeftBeforeTransactionTimeout_1:()Ljava/lang/String;
      76: invokespecial #8                  // Method javax/transaction/RollbackException."<init>":(Ljava/lang/String;)V
      79: athrow
      80: new           #9                  // class java/lang/IllegalStateException
      83: dup
      84: invokespecial #10                 // Method java/lang/IllegalStateException."<init>":()V
      87: athrow
      88: aload_0
      89: invokevirtual #11                 // Method getTransaction:()Ljavax/transaction/Transaction;
      92: checkcast     #12                 // class com/arjuna/ats/jta/transaction/Transaction
      95: astore_2
      96: aload_2
      97: ifnull        107
     100: aload_2
     101: invokeinterface #13,  1           // InterfaceMethod com/arjuna/ats/jta/transaction/Transaction.getRemainingTimeoutMills:()J
     106: lreturn
     107: lconst_0
     108: lreturn
     109: goto          137
     112: astore_2
     113: new           #5                  // class javax/transaction/RollbackException
     116: dup
     117: getstatic     #6                  // Field com/arjuna/ats/jbossatx/logging/jbossatxLogger.i18NLogger:Lcom/arjuna/ats/jbossatx/logging/jbossatxI18NLogger;
     120: invokeinterface #15,  1           // InterfaceMethod com/arjuna/ats/jbossatx/logging/jbossatxI18NLogger.get_jta_TransactionManagerDelegate_getTimeLeftBeforeTransactionTimeout_2:()Ljava/lang/String;
     125: invokespecial #8                  // Method javax/transaction/RollbackException."<init>":(Ljava/lang/String;)V
     128: astore_3
     129: aload_3
     130: aload_2
     131: invokevirtual #16                 // Method javax/transaction/RollbackException.initCause:(Ljava/lang/Throwable;)Ljava/lang/Throwable;
     134: pop
     135: aload_3
     136: athrow
     137: ldc2_w        #17                 // long -1l
     140: lreturn
    Exception table:
       from    to  target type
           0   106   112   Class javax/transaction/SystemException
         107   108   112   Class javax/transaction/SystemException

  public java.lang.Object getObjectInstance(java.lang.Object, javax.naming.Name, javax.naming.Context, java.util.Hashtable) throws java.lang.Exception;
    Code:
       0: aload_0
       1: areturn

  private static com.arjuna.ats.internal.jta.transaction.arjunacore.TransactionManagerImple getTransactionManager();
    Code:
       0: getstatic     #19                 // Field TRANSACTION_MANAGER:Lcom/arjuna/ats/internal/jta/transaction/arjunacore/TransactionManagerImple;
       3: areturn

  static {};
    Code:
       0: new           #20                 // class com/arjuna/ats/internal/jta/transaction/arjunacore/TransactionManagerImple
       3: dup
       4: invokespecial #21                 // Method com/arjuna/ats/internal/jta/transaction/arjunacore/TransactionManagerImple."<init>":()V
       7: putstatic     #19                 // Field TRANSACTION_MANAGER:Lcom/arjuna/ats/internal/jta/transaction/arjunacore/TransactionManagerImple;
      10: return
}
