Compiled from "LoadedActiveRule.java"
public class org.sonar.api.batch.rule.LoadedActiveRule {
  private org.sonar.api.rule.RuleKey ruleKey;

  private java.lang.String severity;

  private java.lang.String name;

  private java.lang.String language;

  private java.util.Map<java.lang.String, java.lang.String> params;

  private long createdAt;

  private long updatedAt;

  private java.lang.String templateRuleKey;

  private java.lang.String internalKey;

  private java.util.Set<org.sonar.api.rule.RuleKey> deprecatedKeys;

  public org.sonar.api.batch.rule.LoadedActiveRule();
    Code:
       0: aload_0
       1: invokespecial #26                 // Method java/lang/Object."<init>":()V
       4: return

  public org.sonar.api.rule.RuleKey getRuleKey();
    Code:
       0: aload_0
       1: getfield      #32                 // Field ruleKey:Lorg/sonar/api/rule/RuleKey;
       4: areturn

  public void setRuleKey(org.sonar.api.rule.RuleKey);
    Code:
       0: aload_0
       1: aload_1
       2: putfield      #32                 // Field ruleKey:Lorg/sonar/api/rule/RuleKey;
       5: return

  public java.lang.String getName();
    Code:
       0: aload_0
       1: getfield      #38                 // Field name:Ljava/lang/String;
       4: areturn

  public void setName(java.lang.String);
    Code:
       0: aload_0
       1: aload_1
       2: putfield      #38                 // Field name:Ljava/lang/String;
       5: return

  public java.lang.String getSeverity();
    Code:
       0: aload_0
       1: getfield      #43                 // Field severity:Ljava/lang/String;
       4: areturn

  public void setSeverity(java.lang.String);
    Code:
       0: aload_0
       1: aload_1
       2: putfield      #43                 // Field severity:Ljava/lang/String;
       5: return

  public java.lang.String getLanguage();
    Code:
       0: aload_0
       1: getfield      #47                 // Field language:Ljava/lang/String;
       4: areturn

  public void setLanguage(java.lang.String);
    Code:
       0: aload_0
       1: aload_1
       2: putfield      #47                 // Field language:Ljava/lang/String;
       5: return

  public java.util.Map<java.lang.String, java.lang.String> getParams();
    Code:
       0: aload_0
       1: getfield      #53                 // Field params:Ljava/util/Map;
       4: areturn

  public void setParams(java.util.Map<java.lang.String, java.lang.String>);
    Code:
       0: aload_0
       1: aload_1
       2: putfield      #53                 // Field params:Ljava/util/Map;
       5: return

  public long getCreatedAt();
    Code:
       0: aload_0
       1: getfield      #60                 // Field createdAt:J
       4: lreturn

  public void setCreatedAt(long);
    Code:
       0: aload_0
       1: lload_1
       2: putfield      #60                 // Field createdAt:J
       5: return

  public long getUpdatedAt();
    Code:
       0: aload_0
       1: getfield      #65                 // Field updatedAt:J
       4: lreturn

  public void setUpdatedAt(long);
    Code:
       0: aload_0
       1: lload_1
       2: putfield      #65                 // Field updatedAt:J
       5: return

  public java.lang.String getTemplateRuleKey();
    Code:
       0: aload_0
       1: getfield      #70                 // Field templateRuleKey:Ljava/lang/String;
       4: areturn

  public void setTemplateRuleKey(java.lang.String);
    Code:
       0: aload_0
       1: aload_1
       2: putfield      #70                 // Field templateRuleKey:Ljava/lang/String;
       5: return

  public java.lang.String getInternalKey();
    Code:
       0: aload_0
       1: getfield      #75                 // Field internalKey:Ljava/lang/String;
       4: areturn

  public void setInternalKey(java.lang.String);
    Code:
       0: aload_0
       1: aload_1
       2: putfield      #75                 // Field internalKey:Ljava/lang/String;
       5: return

  public java.util.Set<org.sonar.api.rule.RuleKey> getDeprecatedKeys();
    Code:
       0: aload_0
       1: getfield      #81                 // Field deprecatedKeys:Ljava/util/Set;
       4: areturn

  public void setDeprecatedKeys(java.util.Set<org.sonar.api.rule.RuleKey>);
    Code:
       0: aload_0
       1: aload_1
       2: putfield      #81                 // Field deprecatedKeys:Ljava/util/Set;
       5: return
}
