Compiled from "Morph.java"
public class org.assertj.core.internal.bytebuddy.implementation.bind.annotation.Morph$Binder$RedirectionProxy implements org.assertj.core.internal.bytebuddy.implementation.auxiliary.AuxiliaryType,org.assertj.core.internal.bytebuddy.implementation.bytecode.StackManipulation {
  protected static final java.lang.String FIELD_NAME;

  private final org.assertj.core.internal.bytebuddy.description.type.TypeDescription morphingType;

  private final org.assertj.core.internal.bytebuddy.description.type.TypeDescription instrumentedType;

  private final org.assertj.core.internal.bytebuddy.implementation.Implementation$SpecialMethodInvocation specialMethodInvocation;

  private final org.assertj.core.internal.bytebuddy.implementation.bytecode.assign.Assigner assigner;

  private final boolean serializableProxy;

  protected org.assertj.core.internal.bytebuddy.implementation.bind.annotation.Morph$Binder$RedirectionProxy(org.assertj.core.internal.bytebuddy.description.type.TypeDescription, org.assertj.core.internal.bytebuddy.description.type.TypeDescription, org.assertj.core.internal.bytebuddy.implementation.Implementation$SpecialMethodInvocation, org.assertj.core.internal.bytebuddy.implementation.bytecode.assign.Assigner, boolean);
    Code:
       0: aload_0
       1: invokespecial #121                // Method java/lang/Object."<init>":()V
       4: aload_0
       5: aload_1
       6: putfield      #123                // Field morphingType:Lorg/assertj/core/internal/bytebuddy/description/type/TypeDescription;
       9: aload_0
      10: aload_2
      11: putfield      #125                // Field instrumentedType:Lorg/assertj/core/internal/bytebuddy/description/type/TypeDescription;
      14: aload_0
      15: aload_3
      16: putfield      #127                // Field specialMethodInvocation:Lorg/assertj/core/internal/bytebuddy/implementation/Implementation$SpecialMethodInvocation;
      19: aload_0
      20: aload         4
      22: putfield      #129                // Field assigner:Lorg/assertj/core/internal/bytebuddy/implementation/bytecode/assign/Assigner;
      25: aload_0
      26: iload         5
      28: putfield      #131                // Field serializableProxy:Z
      31: return

  public org.assertj.core.internal.bytebuddy.dynamic.DynamicType make(java.lang.String, org.assertj.core.internal.bytebuddy.ClassFileVersion, org.assertj.core.internal.bytebuddy.implementation.MethodAccessorFactory);
    Code:
       0: new           #137                // class org/assertj/core/internal/bytebuddy/ByteBuddy
       3: dup
       4: aload_2
       5: invokespecial #140                // Method org/assertj/core/internal/bytebuddy/ByteBuddy."<init>":(Lorg/assertj/core/internal/bytebuddy/ClassFileVersion;)V
       8: aload_0
       9: getfield      #123                // Field morphingType:Lorg/assertj/core/internal/bytebuddy/description/type/TypeDescription;
      12: getstatic     #144                // Field org/assertj/core/internal/bytebuddy/dynamic/scaffold/subclass/ConstructorStrategy$Default.NO_CONSTRUCTORS:Lorg/assertj/core/internal/bytebuddy/dynamic/scaffold/subclass/ConstructorStrategy$Default;
      15: invokevirtual #148                // Method org/assertj/core/internal/bytebuddy/ByteBuddy.subclass:(Lorg/assertj/core/internal/bytebuddy/description/type/TypeDefinition;Lorg/assertj/core/internal/bytebuddy/dynamic/scaffold/subclass/ConstructorStrategy;)Lorg/assertj/core/internal/bytebuddy/dynamic/DynamicType$Builder;
      18: aload_1
      19: invokeinterface #152,  2          // InterfaceMethod org/assertj/core/internal/bytebuddy/dynamic/DynamicType$Builder.name:(Ljava/lang/String;)Lorg/assertj/core/internal/bytebuddy/dynamic/DynamicType$Builder;
      24: getstatic     #156                // Field DEFAULT_TYPE_MODIFIER:[Lorg/assertj/core/internal/bytebuddy/description/modifier/ModifierContributor$ForType;
      27: invokeinterface #160,  2          // InterfaceMethod org/assertj/core/internal/bytebuddy/dynamic/DynamicType$Builder.modifiers:([Lorg/assertj/core/internal/bytebuddy/description/modifier/ModifierContributor$ForType;)Lorg/assertj/core/internal/bytebuddy/dynamic/DynamicType$Builder;
      32: aload_0
      33: getfield      #131                // Field serializableProxy:Z
      36: ifeq          51
      39: iconst_1
      40: anewarray     #162                // class java/lang/Class
      43: dup
      44: iconst_0
      45: ldc           #164                // class java/io/Serializable
      47: aastore
      48: goto          55
      51: iconst_0
      52: anewarray     #162                // class java/lang/Class
      55: invokeinterface #174,  2          // InterfaceMethod org/assertj/core/internal/bytebuddy/dynamic/DynamicType$Builder.implement:([Ljava/lang/reflect/Type;)Lorg/assertj/core/internal/bytebuddy/dynamic/DynamicType$Builder$MethodDefinition$ImplementationDefinition$Optional;
      60: iconst_0
      61: anewarray     #37                 // class org/assertj/core/internal/bytebuddy/description/modifier/ModifierContributor$ForMethod
      64: invokeinterface #178,  2          // InterfaceMethod org/assertj/core/internal/bytebuddy/dynamic/DynamicType$Builder$MethodDefinition$ImplementationDefinition$Optional.defineConstructor:([Lorg/assertj/core/internal/bytebuddy/description/modifier/ModifierContributor$ForMethod;)Lorg/assertj/core/internal/bytebuddy/dynamic/DynamicType$Builder$MethodDefinition$ParameterDefinition$Initial;
      69: aload_0
      70: getfield      #127                // Field specialMethodInvocation:Lorg/assertj/core/internal/bytebuddy/implementation/Implementation$SpecialMethodInvocation;
      73: invokeinterface #182,  1          // InterfaceMethod org/assertj/core/internal/bytebuddy/implementation/Implementation$SpecialMethodInvocation.getMethodDescription:()Lorg/assertj/core/internal/bytebuddy/description/method/MethodDescription;
      78: invokeinterface #186,  1          // InterfaceMethod org/assertj/core/internal/bytebuddy/description/method/MethodDescription.isStatic:()Z
      83: ifeq          92
      86: invokestatic  #192                // Method java/util/Collections.emptyList:()Ljava/util/List;
      89: goto          99
      92: aload_0
      93: getfield      #125                // Field instrumentedType:Lorg/assertj/core/internal/bytebuddy/description/type/TypeDescription;
      96: invokestatic  #196                // Method java/util/Collections.singletonList:(Ljava/lang/Object;)Ljava/util/List;
      99: invokeinterface #202,  2          // InterfaceMethod org/assertj/core/internal/bytebuddy/dynamic/DynamicType$Builder$MethodDefinition$ParameterDefinition$Initial.withParameters:(Ljava/util/Collection;)Lorg/assertj/core/internal/bytebuddy/dynamic/DynamicType$Builder$MethodDefinition$ExceptionDefinition;
     104: aload_0
     105: getfield      #127                // Field specialMethodInvocation:Lorg/assertj/core/internal/bytebuddy/implementation/Implementation$SpecialMethodInvocation;
     108: invokeinterface #182,  1          // InterfaceMethod org/assertj/core/internal/bytebuddy/implementation/Implementation$SpecialMethodInvocation.getMethodDescription:()Lorg/assertj/core/internal/bytebuddy/description/method/MethodDescription;
     113: invokeinterface #186,  1          // InterfaceMethod org/assertj/core/internal/bytebuddy/description/method/MethodDescription.isStatic:()Z
     118: ifeq          127
     121: getstatic     #206                // Field org/assertj/core/internal/bytebuddy/implementation/bind/annotation/Morph$Binder$RedirectionProxy$StaticFieldConstructor.INSTANCE:Lorg/assertj/core/internal/bytebuddy/implementation/bind/annotation/Morph$Binder$RedirectionProxy$StaticFieldConstructor;
     124: goto          138
     127: new           #20                 // class org/assertj/core/internal/bytebuddy/implementation/bind/annotation/Morph$Binder$RedirectionProxy$InstanceFieldConstructor
     130: dup
     131: aload_0
     132: getfield      #125                // Field instrumentedType:Lorg/assertj/core/internal/bytebuddy/description/type/TypeDescription;
     135: invokespecial #209                // Method org/assertj/core/internal/bytebuddy/implementation/bind/annotation/Morph$Binder$RedirectionProxy$InstanceFieldConstructor."<init>":(Lorg/assertj/core/internal/bytebuddy/description/type/TypeDescription;)V
     138: invokeinterface #213,  2          // InterfaceMethod org/assertj/core/internal/bytebuddy/dynamic/DynamicType$Builder$MethodDefinition$ExceptionDefinition.intercept:(Lorg/assertj/core/internal/bytebuddy/implementation/Implementation;)Lorg/assertj/core/internal/bytebuddy/dynamic/DynamicType$Builder$MethodDefinition$ReceiverTypeDefinition;
     143: invokestatic  #219                // Method org/assertj/core/internal/bytebuddy/matcher/ElementMatchers.isAbstract:()Lorg/assertj/core/internal/bytebuddy/matcher/ElementMatcher$Junction;
     146: aload_0
     147: getfield      #123                // Field morphingType:Lorg/assertj/core/internal/bytebuddy/description/type/TypeDescription;
     150: invokestatic  #223                // Method org/assertj/core/internal/bytebuddy/matcher/ElementMatchers.isDeclaredBy:(Lorg/assertj/core/internal/bytebuddy/description/type/TypeDescription;)Lorg/assertj/core/internal/bytebuddy/matcher/ElementMatcher$Junction;
     153: invokeinterface #227,  2          // InterfaceMethod org/assertj/core/internal/bytebuddy/matcher/ElementMatcher$Junction.and:(Lorg/assertj/core/internal/bytebuddy/matcher/ElementMatcher;)Lorg/assertj/core/internal/bytebuddy/matcher/ElementMatcher$Junction;
     158: invokeinterface #231,  2          // InterfaceMethod org/assertj/core/internal/bytebuddy/dynamic/DynamicType$Builder$MethodDefinition$ReceiverTypeDefinition.method:(Lorg/assertj/core/internal/bytebuddy/matcher/ElementMatcher;)Lorg/assertj/core/internal/bytebuddy/dynamic/DynamicType$Builder$MethodDefinition$ImplementationDefinition;
     163: new           #17                 // class org/assertj/core/internal/bytebuddy/implementation/bind/annotation/Morph$Binder$RedirectionProxy$MethodCall
     166: dup
     167: aload_3
     168: aload_0
     169: getfield      #127                // Field specialMethodInvocation:Lorg/assertj/core/internal/bytebuddy/implementation/Implementation$SpecialMethodInvocation;
     172: getstatic     #235                // Field org/assertj/core/internal/bytebuddy/implementation/MethodAccessorFactory$AccessType.DEFAULT:Lorg/assertj/core/internal/bytebuddy/implementation/MethodAccessorFactory$AccessType;
     175: invokeinterface #239,  3          // InterfaceMethod org/assertj/core/internal/bytebuddy/implementation/MethodAccessorFactory.registerAccessorFor:(Lorg/assertj/core/internal/bytebuddy/implementation/Implementation$SpecialMethodInvocation;Lorg/assertj/core/internal/bytebuddy/implementation/MethodAccessorFactory$AccessType;)Lorg/assertj/core/internal/bytebuddy/description/method/MethodDescription$InDefinedShape;
     180: aload_0
     181: getfield      #129                // Field assigner:Lorg/assertj/core/internal/bytebuddy/implementation/bytecode/assign/Assigner;
     184: invokespecial #242                // Method org/assertj/core/internal/bytebuddy/implementation/bind/annotation/Morph$Binder$RedirectionProxy$MethodCall."<init>":(Lorg/assertj/core/internal/bytebuddy/description/method/MethodDescription;Lorg/assertj/core/internal/bytebuddy/implementation/bytecode/assign/Assigner;)V
     187: invokeinterface #243,  2          // InterfaceMethod org/assertj/core/internal/bytebuddy/dynamic/DynamicType$Builder$MethodDefinition$ImplementationDefinition.intercept:(Lorg/assertj/core/internal/bytebuddy/implementation/Implementation;)Lorg/assertj/core/internal/bytebuddy/dynamic/DynamicType$Builder$MethodDefinition$ReceiverTypeDefinition;
     192: invokeinterface #246,  1          // InterfaceMethod org/assertj/core/internal/bytebuddy/dynamic/DynamicType$Builder$MethodDefinition$ReceiverTypeDefinition.make:()Lorg/assertj/core/internal/bytebuddy/dynamic/DynamicType$Unloaded;
     197: areturn

  public boolean isValid();
    Code:
       0: iconst_1
       1: ireturn

  public org.assertj.core.internal.bytebuddy.implementation.bytecode.StackManipulation$Size apply(org.assertj.core.internal.bytebuddy.jar.asm.MethodVisitor, org.assertj.core.internal.bytebuddy.implementation.Implementation$Context);
    Code:
       0: aload_2
       1: aload_0
       2: invokeinterface #258,  2          // InterfaceMethod org/assertj/core/internal/bytebuddy/implementation/Implementation$Context.register:(Lorg/assertj/core/internal/bytebuddy/implementation/auxiliary/AuxiliaryType;)Lorg/assertj/core/internal/bytebuddy/description/type/TypeDescription;
       7: astore_3
       8: new           #42                 // class org/assertj/core/internal/bytebuddy/implementation/bytecode/StackManipulation$Compound
      11: dup
      12: iconst_4
      13: anewarray     #8                  // class org/assertj/core/internal/bytebuddy/implementation/bytecode/StackManipulation
      16: dup
      17: iconst_0
      18: aload_3
      19: invokestatic  #264                // Method org/assertj/core/internal/bytebuddy/implementation/bytecode/TypeCreation.of:(Lorg/assertj/core/internal/bytebuddy/description/type/TypeDescription;)Lorg/assertj/core/internal/bytebuddy/implementation/bytecode/StackManipulation;
      22: aastore
      23: dup
      24: iconst_1
      25: getstatic     #270                // Field org/assertj/core/internal/bytebuddy/implementation/bytecode/Duplication.SINGLE:Lorg/assertj/core/internal/bytebuddy/implementation/bytecode/Duplication;
      28: aastore
      29: dup
      30: iconst_2
      31: aload_0
      32: getfield      #127                // Field specialMethodInvocation:Lorg/assertj/core/internal/bytebuddy/implementation/Implementation$SpecialMethodInvocation;
      35: invokeinterface #182,  1          // InterfaceMethod org/assertj/core/internal/bytebuddy/implementation/Implementation$SpecialMethodInvocation.getMethodDescription:()Lorg/assertj/core/internal/bytebuddy/description/method/MethodDescription;
      40: invokeinterface #186,  1          // InterfaceMethod org/assertj/core/internal/bytebuddy/description/method/MethodDescription.isStatic:()Z
      45: ifeq          54
      48: getstatic     #273                // Field org/assertj/core/internal/bytebuddy/implementation/bytecode/StackManipulation$Trivial.INSTANCE:Lorg/assertj/core/internal/bytebuddy/implementation/bytecode/StackManipulation$Trivial;
      51: goto          57
      54: invokestatic  #285                // Method org/assertj/core/internal/bytebuddy/implementation/bytecode/member/MethodVariableAccess.loadThis:()Lorg/assertj/core/internal/bytebuddy/implementation/bytecode/StackManipulation;
      57: aastore
      58: dup
      59: iconst_3
      60: aload_3
      61: invokeinterface #289,  1          // InterfaceMethod org/assertj/core/internal/bytebuddy/description/type/TypeDescription.getDeclaredMethods:()Lorg/assertj/core/internal/bytebuddy/description/method/MethodList;
      66: invokestatic  #292                // Method org/assertj/core/internal/bytebuddy/matcher/ElementMatchers.isConstructor:()Lorg/assertj/core/internal/bytebuddy/matcher/ElementMatcher$Junction;
      69: invokeinterface #298,  2          // InterfaceMethod org/assertj/core/internal/bytebuddy/description/method/MethodList.filter:(Lorg/assertj/core/internal/bytebuddy/matcher/ElementMatcher;)Lorg/assertj/core/internal/bytebuddy/matcher/FilterableList;
      74: checkcast     #294                // class org/assertj/core/internal/bytebuddy/description/method/MethodList
      77: invokeinterface #302,  1          // InterfaceMethod org/assertj/core/internal/bytebuddy/description/method/MethodList.getOnly:()Ljava/lang/Object;
      82: checkcast     #45                 // class org/assertj/core/internal/bytebuddy/description/method/MethodDescription$InDefinedShape
      85: invokestatic  #306                // Method org/assertj/core/internal/bytebuddy/implementation/bytecode/member/MethodInvocation.invoke:(Lorg/assertj/core/internal/bytebuddy/description/method/MethodDescription$InDefinedShape;)Lorg/assertj/core/internal/bytebuddy/implementation/bytecode/member/MethodInvocation$WithImplicitInvocationTargetType;
      88: aastore
      89: invokespecial #309                // Method org/assertj/core/internal/bytebuddy/implementation/bytecode/StackManipulation$Compound."<init>":([Lorg/assertj/core/internal/bytebuddy/implementation/bytecode/StackManipulation;)V
      92: aload_1
      93: aload_2
      94: invokevirtual #311                // Method org/assertj/core/internal/bytebuddy/implementation/bytecode/StackManipulation$Compound.apply:(Lorg/assertj/core/internal/bytebuddy/jar/asm/MethodVisitor;Lorg/assertj/core/internal/bytebuddy/implementation/Implementation$Context;)Lorg/assertj/core/internal/bytebuddy/implementation/bytecode/StackManipulation$Size;
      97: areturn

  public boolean equals(java.lang.Object);
    Code:
       0: aload_1
       1: aload_0
       2: if_acmpne     7
       5: iconst_1
       6: ireturn
       7: aload_1
       8: instanceof    #2                  // class org/assertj/core/internal/bytebuddy/implementation/bind/annotation/Morph$Binder$RedirectionProxy
      11: ifne          16
      14: iconst_0
      15: ireturn
      16: aload_1
      17: checkcast     #2                  // class org/assertj/core/internal/bytebuddy/implementation/bind/annotation/Morph$Binder$RedirectionProxy
      20: astore_2
      21: aload_2
      22: aload_0
      23: invokevirtual #321                // Method canEqual:(Ljava/lang/Object;)Z
      26: ifne          31
      29: iconst_0
      30: ireturn
      31: aload_0
      32: getfield      #123                // Field morphingType:Lorg/assertj/core/internal/bytebuddy/description/type/TypeDescription;
      35: astore_3
      36: aload_2
      37: getfield      #123                // Field morphingType:Lorg/assertj/core/internal/bytebuddy/description/type/TypeDescription;
      40: astore        4
      42: aload_3
      43: ifnonnull     54
      46: aload         4
      48: ifnull        65
      51: goto          63
      54: aload_3
      55: aload         4
      57: invokevirtual #323                // Method java/lang/Object.equals:(Ljava/lang/Object;)Z
      60: ifne          65
      63: iconst_0
      64: ireturn
      65: aload_0
      66: getfield      #125                // Field instrumentedType:Lorg/assertj/core/internal/bytebuddy/description/type/TypeDescription;
      69: astore        5
      71: aload_2
      72: getfield      #125                // Field instrumentedType:Lorg/assertj/core/internal/bytebuddy/description/type/TypeDescription;
      75: astore        6
      77: aload         5
      79: ifnonnull     90
      82: aload         6
      84: ifnull        102
      87: goto          100
      90: aload         5
      92: aload         6
      94: invokevirtual #323                // Method java/lang/Object.equals:(Ljava/lang/Object;)Z
      97: ifne          102
     100: iconst_0
     101: ireturn
     102: aload_0
     103: getfield      #127                // Field specialMethodInvocation:Lorg/assertj/core/internal/bytebuddy/implementation/Implementation$SpecialMethodInvocation;
     106: astore        7
     108: aload_2
     109: getfield      #127                // Field specialMethodInvocation:Lorg/assertj/core/internal/bytebuddy/implementation/Implementation$SpecialMethodInvocation;
     112: astore        8
     114: aload         7
     116: ifnonnull     127
     119: aload         8
     121: ifnull        139
     124: goto          137
     127: aload         7
     129: aload         8
     131: invokevirtual #323                // Method java/lang/Object.equals:(Ljava/lang/Object;)Z
     134: ifne          139
     137: iconst_0
     138: ireturn
     139: aload_0
     140: getfield      #129                // Field assigner:Lorg/assertj/core/internal/bytebuddy/implementation/bytecode/assign/Assigner;
     143: astore        9
     145: aload_2
     146: getfield      #129                // Field assigner:Lorg/assertj/core/internal/bytebuddy/implementation/bytecode/assign/Assigner;
     149: astore        10
     151: aload         9
     153: ifnonnull     164
     156: aload         10
     158: ifnull        176
     161: goto          174
     164: aload         9
     166: aload         10
     168: invokevirtual #323                // Method java/lang/Object.equals:(Ljava/lang/Object;)Z
     171: ifne          176
     174: iconst_0
     175: ireturn
     176: aload_0
     177: getfield      #131                // Field serializableProxy:Z
     180: aload_2
     181: getfield      #131                // Field serializableProxy:Z
     184: if_icmpeq     189
     187: iconst_0
     188: ireturn
     189: iconst_1
     190: ireturn

  protected boolean canEqual(java.lang.Object);
    Code:
       0: aload_1
       1: instanceof    #2                  // class org/assertj/core/internal/bytebuddy/implementation/bind/annotation/Morph$Binder$RedirectionProxy
       4: ireturn

  public int hashCode();
    Code:
       0: bipush        59
       2: istore_1
       3: iconst_1
       4: istore_2
       5: aload_0
       6: getfield      #123                // Field morphingType:Lorg/assertj/core/internal/bytebuddy/description/type/TypeDescription;
       9: astore_3
      10: iload_2
      11: bipush        59
      13: imul
      14: aload_3
      15: ifnonnull     23
      18: bipush        43
      20: goto          27
      23: aload_3
      24: invokevirtual #338                // Method java/lang/Object.hashCode:()I
      27: iadd
      28: istore_2
      29: aload_0
      30: getfield      #125                // Field instrumentedType:Lorg/assertj/core/internal/bytebuddy/description/type/TypeDescription;
      33: astore        4
      35: iload_2
      36: bipush        59
      38: imul
      39: aload         4
      41: ifnonnull     49
      44: bipush        43
      46: goto          54
      49: aload         4
      51: invokevirtual #338                // Method java/lang/Object.hashCode:()I
      54: iadd
      55: istore_2
      56: aload_0
      57: getfield      #127                // Field specialMethodInvocation:Lorg/assertj/core/internal/bytebuddy/implementation/Implementation$SpecialMethodInvocation;
      60: astore        5
      62: iload_2
      63: bipush        59
      65: imul
      66: aload         5
      68: ifnonnull     76
      71: bipush        43
      73: goto          81
      76: aload         5
      78: invokevirtual #338                // Method java/lang/Object.hashCode:()I
      81: iadd
      82: istore_2
      83: aload_0
      84: getfield      #129                // Field assigner:Lorg/assertj/core/internal/bytebuddy/implementation/bytecode/assign/Assigner;
      87: astore        6
      89: iload_2
      90: bipush        59
      92: imul
      93: aload         6
      95: ifnonnull     103
      98: bipush        43
     100: goto          108
     103: aload         6
     105: invokevirtual #338                // Method java/lang/Object.hashCode:()I
     108: iadd
     109: istore_2
     110: iload_2
     111: bipush        59
     113: imul
     114: aload_0
     115: getfield      #131                // Field serializableProxy:Z
     118: ifeq          126
     121: bipush        79
     123: goto          128
     126: bipush        97
     128: iadd
     129: istore_2
     130: iload_2
     131: ireturn
}
