Compiled from "Pipe.java"
class org.assertj.core.internal.bytebuddy.implementation.bind.annotation.Pipe$Binder$Redirection$MethodCall$Appender implements org.assertj.core.internal.bytebuddy.implementation.bytecode.ByteCodeAppender {
  private final org.assertj.core.internal.bytebuddy.description.type.TypeDescription instrumentedType;

  final org.assertj.core.internal.bytebuddy.implementation.bind.annotation.Pipe$Binder$Redirection$MethodCall this$0;

  private org.assertj.core.internal.bytebuddy.implementation.bind.annotation.Pipe$Binder$Redirection$MethodCall$Appender(org.assertj.core.internal.bytebuddy.implementation.bind.annotation.Pipe$Binder$Redirection$MethodCall, org.assertj.core.internal.bytebuddy.description.type.TypeDescription);
    Code:
       0: aload_0
       1: aload_1
       2: putfield      #64                 // Field this$0:Lorg/assertj/core/internal/bytebuddy/implementation/bind/annotation/Pipe$Binder$Redirection$MethodCall;
       5: aload_0
       6: invokespecial #67                 // Method java/lang/Object."<init>":()V
       9: aload_0
      10: aload_2
      11: putfield      #69                 // Field instrumentedType:Lorg/assertj/core/internal/bytebuddy/description/type/TypeDescription;
      14: return

  public org.assertj.core.internal.bytebuddy.implementation.bytecode.ByteCodeAppender$Size apply(org.assertj.core.internal.bytebuddy.jar.asm.MethodVisitor, org.assertj.core.internal.bytebuddy.implementation.Implementation$Context, org.assertj.core.internal.bytebuddy.description.method.MethodDescription);
    Code:
       0: aload_0
       1: getfield      #69                 // Field instrumentedType:Lorg/assertj/core/internal/bytebuddy/description/type/TypeDescription;
       4: invokestatic  #79                 // Method org/assertj/core/internal/bytebuddy/implementation/bytecode/member/MethodVariableAccess.of:(Lorg/assertj/core/internal/bytebuddy/description/type/TypeDefinition;)Lorg/assertj/core/internal/bytebuddy/implementation/bytecode/member/MethodVariableAccess;
       7: iconst_0
       8: invokevirtual #83                 // Method org/assertj/core/internal/bytebuddy/implementation/bytecode/member/MethodVariableAccess.loadFrom:(I)Lorg/assertj/core/internal/bytebuddy/implementation/bytecode/StackManipulation;
      11: astore        4
      13: aload_0
      14: getfield      #69                 // Field instrumentedType:Lorg/assertj/core/internal/bytebuddy/description/type/TypeDescription;
      17: invokeinterface #87,  1           // InterfaceMethod org/assertj/core/internal/bytebuddy/description/type/TypeDescription.getDeclaredFields:()Lorg/assertj/core/internal/bytebuddy/description/field/FieldList;
      22: astore        5
      24: aload         5
      26: invokeinterface #93,  1           // InterfaceMethod org/assertj/core/internal/bytebuddy/description/field/FieldList.size:()I
      31: anewarray     #31                 // class org/assertj/core/internal/bytebuddy/implementation/bytecode/StackManipulation
      34: astore        6
      36: iconst_0
      37: istore        7
      39: aload         5
      41: invokeinterface #97,  1           // InterfaceMethod org/assertj/core/internal/bytebuddy/description/field/FieldList.iterator:()Ljava/util/Iterator;
      46: astore        8
      48: aload         8
      50: invokeinterface #109,  1          // InterfaceMethod java/util/Iterator.hasNext:()Z
      55: ifeq          110
      58: aload         8
      60: invokeinterface #113,  1          // InterfaceMethod java/util/Iterator.next:()Ljava/lang/Object;
      65: checkcast     #115                // class org/assertj/core/internal/bytebuddy/description/field/FieldDescription
      68: astore        9
      70: aload         6
      72: iload         7
      74: iinc          7, 1
      77: new           #35                 // class org/assertj/core/internal/bytebuddy/implementation/bytecode/StackManipulation$Compound
      80: dup
      81: iconst_2
      82: anewarray     #31                 // class org/assertj/core/internal/bytebuddy/implementation/bytecode/StackManipulation
      85: dup
      86: iconst_0
      87: aload         4
      89: aastore
      90: dup
      91: iconst_1
      92: aload         9
      94: invokestatic  #119                // Method org/assertj/core/internal/bytebuddy/implementation/bytecode/member/FieldAccess.forField:(Lorg/assertj/core/internal/bytebuddy/description/field/FieldDescription;)Lorg/assertj/core/internal/bytebuddy/implementation/bytecode/member/FieldAccess$Defined;
      97: invokeinterface #123,  1          // InterfaceMethod org/assertj/core/internal/bytebuddy/implementation/bytecode/member/FieldAccess$Defined.read:()Lorg/assertj/core/internal/bytebuddy/implementation/bytecode/StackManipulation;
     102: aastore
     103: invokespecial #126                // Method org/assertj/core/internal/bytebuddy/implementation/bytecode/StackManipulation$Compound."<init>":([Lorg/assertj/core/internal/bytebuddy/implementation/bytecode/StackManipulation;)V
     106: aastore
     107: goto          48
     110: new           #35                 // class org/assertj/core/internal/bytebuddy/implementation/bytecode/StackManipulation$Compound
     113: dup
     114: bipush        6
     116: anewarray     #31                 // class org/assertj/core/internal/bytebuddy/implementation/bytecode/StackManipulation
     119: dup
     120: iconst_0
     121: getstatic     #130                // Field org/assertj/core/internal/bytebuddy/implementation/bytecode/member/MethodVariableAccess.REFERENCE:Lorg/assertj/core/internal/bytebuddy/implementation/bytecode/member/MethodVariableAccess;
     124: iconst_1
     125: invokevirtual #83                 // Method org/assertj/core/internal/bytebuddy/implementation/bytecode/member/MethodVariableAccess.loadFrom:(I)Lorg/assertj/core/internal/bytebuddy/implementation/bytecode/StackManipulation;
     128: aastore
     129: dup
     130: iconst_1
     131: aload_0
     132: getfield      #64                 // Field this$0:Lorg/assertj/core/internal/bytebuddy/implementation/bind/annotation/Pipe$Binder$Redirection$MethodCall;
     135: invokestatic  #134                // Method org/assertj/core/internal/bytebuddy/implementation/bind/annotation/Pipe$Binder$Redirection$MethodCall.access$500:(Lorg/assertj/core/internal/bytebuddy/implementation/bind/annotation/Pipe$Binder$Redirection$MethodCall;)Lorg/assertj/core/internal/bytebuddy/implementation/bytecode/assign/Assigner;
     138: getstatic     #138                // Field org/assertj/core/internal/bytebuddy/description/type/TypeDescription$Generic.OBJECT:Lorg/assertj/core/internal/bytebuddy/description/type/TypeDescription$Generic;
     141: aload_0
     142: getfield      #64                 // Field this$0:Lorg/assertj/core/internal/bytebuddy/implementation/bind/annotation/Pipe$Binder$Redirection$MethodCall;
     145: invokestatic  #142                // Method org/assertj/core/internal/bytebuddy/implementation/bind/annotation/Pipe$Binder$Redirection$MethodCall.access$400:(Lorg/assertj/core/internal/bytebuddy/implementation/bind/annotation/Pipe$Binder$Redirection$MethodCall;)Lorg/assertj/core/internal/bytebuddy/description/method/MethodDescription;
     148: invokeinterface #146,  1          // InterfaceMethod org/assertj/core/internal/bytebuddy/description/method/MethodDescription.getDeclaringType:()Lorg/assertj/core/internal/bytebuddy/description/type/TypeDefinition;
     153: invokeinterface #152,  1          // InterfaceMethod org/assertj/core/internal/bytebuddy/description/type/TypeDefinition.asGenericType:()Lorg/assertj/core/internal/bytebuddy/description/type/TypeDescription$Generic;
     158: getstatic     #156                // Field org/assertj/core/internal/bytebuddy/implementation/bytecode/assign/Assigner$Typing.DYNAMIC:Lorg/assertj/core/internal/bytebuddy/implementation/bytecode/assign/Assigner$Typing;
     161: invokeinterface #160,  4          // InterfaceMethod org/assertj/core/internal/bytebuddy/implementation/bytecode/assign/Assigner.assign:(Lorg/assertj/core/internal/bytebuddy/description/type/TypeDescription$Generic;Lorg/assertj/core/internal/bytebuddy/description/type/TypeDescription$Generic;Lorg/assertj/core/internal/bytebuddy/implementation/bytecode/assign/Assigner$Typing;)Lorg/assertj/core/internal/bytebuddy/implementation/bytecode/StackManipulation;
     166: aastore
     167: dup
     168: iconst_2
     169: new           #35                 // class org/assertj/core/internal/bytebuddy/implementation/bytecode/StackManipulation$Compound
     172: dup
     173: aload         6
     175: invokespecial #126                // Method org/assertj/core/internal/bytebuddy/implementation/bytecode/StackManipulation$Compound."<init>":([Lorg/assertj/core/internal/bytebuddy/implementation/bytecode/StackManipulation;)V
     178: aastore
     179: dup
     180: iconst_3
     181: aload_0
     182: getfield      #64                 // Field this$0:Lorg/assertj/core/internal/bytebuddy/implementation/bind/annotation/Pipe$Binder$Redirection$MethodCall;
     185: invokestatic  #142                // Method org/assertj/core/internal/bytebuddy/implementation/bind/annotation/Pipe$Binder$Redirection$MethodCall.access$400:(Lorg/assertj/core/internal/bytebuddy/implementation/bind/annotation/Pipe$Binder$Redirection$MethodCall;)Lorg/assertj/core/internal/bytebuddy/description/method/MethodDescription;
     188: invokestatic  #164                // Method org/assertj/core/internal/bytebuddy/implementation/bytecode/member/MethodInvocation.invoke:(Lorg/assertj/core/internal/bytebuddy/description/method/MethodDescription;)Lorg/assertj/core/internal/bytebuddy/implementation/bytecode/member/MethodInvocation$WithImplicitInvocationTargetType;
     191: aastore
     192: dup
     193: iconst_4
     194: aload_0
     195: getfield      #64                 // Field this$0:Lorg/assertj/core/internal/bytebuddy/implementation/bind/annotation/Pipe$Binder$Redirection$MethodCall;
     198: invokestatic  #134                // Method org/assertj/core/internal/bytebuddy/implementation/bind/annotation/Pipe$Binder$Redirection$MethodCall.access$500:(Lorg/assertj/core/internal/bytebuddy/implementation/bind/annotation/Pipe$Binder$Redirection$MethodCall;)Lorg/assertj/core/internal/bytebuddy/implementation/bytecode/assign/Assigner;
     201: aload_0
     202: getfield      #64                 // Field this$0:Lorg/assertj/core/internal/bytebuddy/implementation/bind/annotation/Pipe$Binder$Redirection$MethodCall;
     205: invokestatic  #142                // Method org/assertj/core/internal/bytebuddy/implementation/bind/annotation/Pipe$Binder$Redirection$MethodCall.access$400:(Lorg/assertj/core/internal/bytebuddy/implementation/bind/annotation/Pipe$Binder$Redirection$MethodCall;)Lorg/assertj/core/internal/bytebuddy/description/method/MethodDescription;
     208: invokeinterface #167,  1          // InterfaceMethod org/assertj/core/internal/bytebuddy/description/method/MethodDescription.getReturnType:()Lorg/assertj/core/internal/bytebuddy/description/type/TypeDescription$Generic;
     213: aload_3
     214: invokeinterface #167,  1          // InterfaceMethod org/assertj/core/internal/bytebuddy/description/method/MethodDescription.getReturnType:()Lorg/assertj/core/internal/bytebuddy/description/type/TypeDescription$Generic;
     219: getstatic     #156                // Field org/assertj/core/internal/bytebuddy/implementation/bytecode/assign/Assigner$Typing.DYNAMIC:Lorg/assertj/core/internal/bytebuddy/implementation/bytecode/assign/Assigner$Typing;
     222: invokeinterface #160,  4          // InterfaceMethod org/assertj/core/internal/bytebuddy/implementation/bytecode/assign/Assigner.assign:(Lorg/assertj/core/internal/bytebuddy/description/type/TypeDescription$Generic;Lorg/assertj/core/internal/bytebuddy/description/type/TypeDescription$Generic;Lorg/assertj/core/internal/bytebuddy/implementation/bytecode/assign/Assigner$Typing;)Lorg/assertj/core/internal/bytebuddy/implementation/bytecode/StackManipulation;
     227: aastore
     228: dup
     229: iconst_5
     230: getstatic     #172                // Field org/assertj/core/internal/bytebuddy/implementation/bytecode/member/MethodReturn.REFERENCE:Lorg/assertj/core/internal/bytebuddy/implementation/bytecode/member/MethodReturn;
     233: aastore
     234: invokespecial #126                // Method org/assertj/core/internal/bytebuddy/implementation/bytecode/StackManipulation$Compound."<init>":([Lorg/assertj/core/internal/bytebuddy/implementation/bytecode/StackManipulation;)V
     237: aload_1
     238: aload_2
     239: invokevirtual #175                // Method org/assertj/core/internal/bytebuddy/implementation/bytecode/StackManipulation$Compound.apply:(Lorg/assertj/core/internal/bytebuddy/jar/asm/MethodVisitor;Lorg/assertj/core/internal/bytebuddy/implementation/Implementation$Context;)Lorg/assertj/core/internal/bytebuddy/implementation/bytecode/StackManipulation$Size;
     242: astore        8
     244: new           #26                 // class org/assertj/core/internal/bytebuddy/implementation/bytecode/ByteCodeAppender$Size
     247: dup
     248: aload         8
     250: invokevirtual #178                // Method org/assertj/core/internal/bytebuddy/implementation/bytecode/StackManipulation$Size.getMaximalSize:()I
     253: aload_3
     254: invokeinterface #181,  1          // InterfaceMethod org/assertj/core/internal/bytebuddy/description/method/MethodDescription.getStackSize:()I
     259: invokespecial #184                // Method org/assertj/core/internal/bytebuddy/implementation/bytecode/ByteCodeAppender$Size."<init>":(II)V
     262: areturn

  private org.assertj.core.internal.bytebuddy.implementation.bind.annotation.Pipe$Binder$Redirection$MethodCall getMethodCall();
    Code:
       0: aload_0
       1: getfield      #64                 // Field this$0:Lorg/assertj/core/internal/bytebuddy/implementation/bind/annotation/Pipe$Binder$Redirection$MethodCall;
       4: areturn

  public boolean equals(java.lang.Object);
    Code:
       0: aload_0
       1: aload_1
       2: if_acmpeq     54
       5: aload_1
       6: ifnull        58
       9: aload_0
      10: invokevirtual #210                // Method java/lang/Object.getClass:()Ljava/lang/Class;
      13: aload_1
      14: invokevirtual #210                // Method java/lang/Object.getClass:()Ljava/lang/Class;
      17: if_acmpne     58
      20: aload_0
      21: getfield      #69                 // Field instrumentedType:Lorg/assertj/core/internal/bytebuddy/description/type/TypeDescription;
      24: aload_1
      25: checkcast     #2                  // class org/assertj/core/internal/bytebuddy/implementation/bind/annotation/Pipe$Binder$Redirection$MethodCall$Appender
      28: getfield      #69                 // Field instrumentedType:Lorg/assertj/core/internal/bytebuddy/description/type/TypeDescription;
      31: invokevirtual #212                // Method java/lang/Object.equals:(Ljava/lang/Object;)Z
      34: ifeq          58
      37: aload_0
      38: getfield      #64                 // Field this$0:Lorg/assertj/core/internal/bytebuddy/implementation/bind/annotation/Pipe$Binder$Redirection$MethodCall;
      41: aload_1
      42: checkcast     #2                  // class org/assertj/core/internal/bytebuddy/implementation/bind/annotation/Pipe$Binder$Redirection$MethodCall$Appender
      45: invokespecial #214                // Method getMethodCall:()Lorg/assertj/core/internal/bytebuddy/implementation/bind/annotation/Pipe$Binder$Redirection$MethodCall;
      48: invokevirtual #215                // Method org/assertj/core/internal/bytebuddy/implementation/bind/annotation/Pipe$Binder$Redirection$MethodCall.equals:(Ljava/lang/Object;)Z
      51: ifeq          58
      54: iconst_1
      55: goto          59
      58: iconst_0
      59: ireturn

  public int hashCode();
    Code:
       0: bipush        31
       2: aload_0
       3: getfield      #64                 // Field this$0:Lorg/assertj/core/internal/bytebuddy/implementation/bind/annotation/Pipe$Binder$Redirection$MethodCall;
       6: invokevirtual #220                // Method org/assertj/core/internal/bytebuddy/implementation/bind/annotation/Pipe$Binder$Redirection$MethodCall.hashCode:()I
       9: imul
      10: aload_0
      11: getfield      #69                 // Field instrumentedType:Lorg/assertj/core/internal/bytebuddy/description/type/TypeDescription;
      14: invokevirtual #221                // Method java/lang/Object.hashCode:()I
      17: iadd
      18: ireturn

  org.assertj.core.internal.bytebuddy.implementation.bind.annotation.Pipe$Binder$Redirection$MethodCall$Appender(org.assertj.core.internal.bytebuddy.implementation.bind.annotation.Pipe$Binder$Redirection$MethodCall, org.assertj.core.internal.bytebuddy.description.type.TypeDescription, org.assertj.core.internal.bytebuddy.implementation.bind.annotation.Pipe$1);
    Code:
       0: aload_0
       1: aload_1
       2: aload_2
       3: invokespecial #224                // Method "<init>":(Lorg/assertj/core/internal/bytebuddy/implementation/bind/annotation/Pipe$Binder$Redirection$MethodCall;Lorg/assertj/core/internal/bytebuddy/description/type/TypeDescription;)V
       6: return
}
