Compiled from "Super.java"
public abstract class org.assertj.core.internal.bytebuddy.implementation.bind.annotation.Super$Instantiation extends java.lang.Enum<org.assertj.core.internal.bytebuddy.implementation.bind.annotation.Super$Instantiation> {
  public static final org.assertj.core.internal.bytebuddy.implementation.bind.annotation.Super$Instantiation CONSTRUCTOR;

  public static final org.assertj.core.internal.bytebuddy.implementation.bind.annotation.Super$Instantiation UNSAFE;

  private static final org.assertj.core.internal.bytebuddy.description.method.MethodDescription$InDefinedShape IGNORE_FINALIZER;

  private static final org.assertj.core.internal.bytebuddy.description.method.MethodDescription$InDefinedShape SERIALIZABLE_PROXY;

  private static final org.assertj.core.internal.bytebuddy.description.method.MethodDescription$InDefinedShape CONSTRUCTOR_PARAMETERS;

  private static final org.assertj.core.internal.bytebuddy.implementation.bind.annotation.Super$Instantiation[] $VALUES;

  public static org.assertj.core.internal.bytebuddy.implementation.bind.annotation.Super$Instantiation[] values();
    Code:
       0: getstatic     #53                 // Field $VALUES:[Lorg/assertj/core/internal/bytebuddy/implementation/bind/annotation/Super$Instantiation;
       3: invokevirtual #58                 // Method "[Lorg/assertj/core/internal/bytebuddy/implementation/bind/annotation/Super$Instantiation;".clone:()Ljava/lang/Object;
       6: checkcast     #54                 // class "[Lorg/assertj/core/internal/bytebuddy/implementation/bind/annotation/Super$Instantiation;"
       9: areturn

  public static org.assertj.core.internal.bytebuddy.implementation.bind.annotation.Super$Instantiation valueOf(java.lang.String);
    Code:
       0: ldc           #2                  // class org/assertj/core/internal/bytebuddy/implementation/bind/annotation/Super$Instantiation
       2: aload_0
       3: invokestatic  #63                 // Method java/lang/Enum.valueOf:(Ljava/lang/Class;Ljava/lang/String;)Ljava/lang/Enum;
       6: checkcast     #2                  // class org/assertj/core/internal/bytebuddy/implementation/bind/annotation/Super$Instantiation
       9: areturn

  private org.assertj.core.internal.bytebuddy.implementation.bind.annotation.Super$Instantiation();
    Code:
       0: aload_0
       1: aload_1
       2: iload_2
       3: invokespecial #69                 // Method java/lang/Enum."<init>":(Ljava/lang/String;I)V
       6: return

  protected abstract org.assertj.core.internal.bytebuddy.implementation.bytecode.StackManipulation proxyFor(org.assertj.core.internal.bytebuddy.description.type.TypeDescription, org.assertj.core.internal.bytebuddy.implementation.Implementation$Target, org.assertj.core.internal.bytebuddy.description.annotation.AnnotationDescription$Loadable<org.assertj.core.internal.bytebuddy.implementation.bind.annotation.Super>);

  org.assertj.core.internal.bytebuddy.implementation.bind.annotation.Super$Instantiation(java.lang.String, int, org.assertj.core.internal.bytebuddy.implementation.bind.annotation.Super$1);
    Code:
       0: aload_0
       1: aload_1
       2: iload_2
       3: invokespecial #74                 // Method "<init>":(Ljava/lang/String;I)V
       6: return

  static org.assertj.core.internal.bytebuddy.description.method.MethodDescription$InDefinedShape access$100();
    Code:
       0: getstatic     #83                 // Field CONSTRUCTOR_PARAMETERS:Lorg/assertj/core/internal/bytebuddy/description/method/MethodDescription$InDefinedShape;
       3: areturn

  static org.assertj.core.internal.bytebuddy.description.method.MethodDescription$InDefinedShape access$200();
    Code:
       0: getstatic     #86                 // Field IGNORE_FINALIZER:Lorg/assertj/core/internal/bytebuddy/description/method/MethodDescription$InDefinedShape;
       3: areturn

  static org.assertj.core.internal.bytebuddy.description.method.MethodDescription$InDefinedShape access$300();
    Code:
       0: getstatic     #89                 // Field SERIALIZABLE_PROXY:Lorg/assertj/core/internal/bytebuddy/description/method/MethodDescription$InDefinedShape;
       3: areturn

  static {};
    Code:
       0: new           #13                 // class org/assertj/core/internal/bytebuddy/implementation/bind/annotation/Super$Instantiation$1
       3: dup
       4: ldc           #92                 // String CONSTRUCTOR
       6: iconst_0
       7: invokespecial #93                 // Method org/assertj/core/internal/bytebuddy/implementation/bind/annotation/Super$Instantiation$1."<init>":(Ljava/lang/String;I)V
      10: putstatic     #95                 // Field CONSTRUCTOR:Lorg/assertj/core/internal/bytebuddy/implementation/bind/annotation/Super$Instantiation;
      13: new           #11                 // class org/assertj/core/internal/bytebuddy/implementation/bind/annotation/Super$Instantiation$2
      16: dup
      17: ldc           #96                 // String UNSAFE
      19: iconst_1
      20: invokespecial #97                 // Method org/assertj/core/internal/bytebuddy/implementation/bind/annotation/Super$Instantiation$2."<init>":(Ljava/lang/String;I)V
      23: putstatic     #99                 // Field UNSAFE:Lorg/assertj/core/internal/bytebuddy/implementation/bind/annotation/Super$Instantiation;
      26: iconst_2
      27: anewarray     #2                  // class org/assertj/core/internal/bytebuddy/implementation/bind/annotation/Super$Instantiation
      30: dup
      31: iconst_0
      32: getstatic     #95                 // Field CONSTRUCTOR:Lorg/assertj/core/internal/bytebuddy/implementation/bind/annotation/Super$Instantiation;
      35: aastore
      36: dup
      37: iconst_1
      38: getstatic     #99                 // Field UNSAFE:Lorg/assertj/core/internal/bytebuddy/implementation/bind/annotation/Super$Instantiation;
      41: aastore
      42: putstatic     #53                 // Field $VALUES:[Lorg/assertj/core/internal/bytebuddy/implementation/bind/annotation/Super$Instantiation;
      45: new           #32                 // class org/assertj/core/internal/bytebuddy/description/type/TypeDescription$ForLoadedType
      48: dup
      49: ldc           #8                  // class org/assertj/core/internal/bytebuddy/implementation/bind/annotation/Super
      51: invokespecial #102                // Method org/assertj/core/internal/bytebuddy/description/type/TypeDescription$ForLoadedType."<init>":(Ljava/lang/Class;)V
      54: invokevirtual #106                // Method org/assertj/core/internal/bytebuddy/description/type/TypeDescription$ForLoadedType.getDeclaredMethods:()Lorg/assertj/core/internal/bytebuddy/description/method/MethodList;
      57: astore_0
      58: aload_0
      59: ldc           #108                // String ignoreFinalizer
      61: invokestatic  #114                // Method org/assertj/core/internal/bytebuddy/matcher/ElementMatchers.named:(Ljava/lang/String;)Lorg/assertj/core/internal/bytebuddy/matcher/ElementMatcher$Junction;
      64: invokeinterface #120,  2          // InterfaceMethod org/assertj/core/internal/bytebuddy/description/method/MethodList.filter:(Lorg/assertj/core/internal/bytebuddy/matcher/ElementMatcher;)Lorg/assertj/core/internal/bytebuddy/matcher/FilterableList;
      69: checkcast     #116                // class org/assertj/core/internal/bytebuddy/description/method/MethodList
      72: invokeinterface #123,  1          // InterfaceMethod org/assertj/core/internal/bytebuddy/description/method/MethodList.getOnly:()Ljava/lang/Object;
      77: checkcast     #15                 // class org/assertj/core/internal/bytebuddy/description/method/MethodDescription$InDefinedShape
      80: putstatic     #86                 // Field IGNORE_FINALIZER:Lorg/assertj/core/internal/bytebuddy/description/method/MethodDescription$InDefinedShape;
      83: aload_0
      84: ldc           #125                // String serializableProxy
      86: invokestatic  #114                // Method org/assertj/core/internal/bytebuddy/matcher/ElementMatchers.named:(Ljava/lang/String;)Lorg/assertj/core/internal/bytebuddy/matcher/ElementMatcher$Junction;
      89: invokeinterface #120,  2          // InterfaceMethod org/assertj/core/internal/bytebuddy/description/method/MethodList.filter:(Lorg/assertj/core/internal/bytebuddy/matcher/ElementMatcher;)Lorg/assertj/core/internal/bytebuddy/matcher/FilterableList;
      94: checkcast     #116                // class org/assertj/core/internal/bytebuddy/description/method/MethodList
      97: invokeinterface #123,  1          // InterfaceMethod org/assertj/core/internal/bytebuddy/description/method/MethodList.getOnly:()Ljava/lang/Object;
     102: checkcast     #15                 // class org/assertj/core/internal/bytebuddy/description/method/MethodDescription$InDefinedShape
     105: putstatic     #89                 // Field SERIALIZABLE_PROXY:Lorg/assertj/core/internal/bytebuddy/description/method/MethodDescription$InDefinedShape;
     108: aload_0
     109: ldc           #127                // String constructorParameters
     111: invokestatic  #114                // Method org/assertj/core/internal/bytebuddy/matcher/ElementMatchers.named:(Ljava/lang/String;)Lorg/assertj/core/internal/bytebuddy/matcher/ElementMatcher$Junction;
     114: invokeinterface #120,  2          // InterfaceMethod org/assertj/core/internal/bytebuddy/description/method/MethodList.filter:(Lorg/assertj/core/internal/bytebuddy/matcher/ElementMatcher;)Lorg/assertj/core/internal/bytebuddy/matcher/FilterableList;
     119: checkcast     #116                // class org/assertj/core/internal/bytebuddy/description/method/MethodList
     122: invokeinterface #123,  1          // InterfaceMethod org/assertj/core/internal/bytebuddy/description/method/MethodList.getOnly:()Ljava/lang/Object;
     127: checkcast     #15                 // class org/assertj/core/internal/bytebuddy/description/method/MethodDescription$InDefinedShape
     130: putstatic     #83                 // Field CONSTRUCTOR_PARAMETERS:Lorg/assertj/core/internal/bytebuddy/description/method/MethodDescription$InDefinedShape;
     133: return
}
