Compiled from "LittleEndianDataOutputStream.java"
public final class org.apache.jena.ext.com.google.common.io.LittleEndianDataOutputStream extends java.io.FilterOutputStream implements java.io.DataOutput {
  public org.apache.jena.ext.com.google.common.io.LittleEndianDataOutputStream(java.io.OutputStream);
    Code:
       0: aload_0
       1: new           #13                 // class java/io/DataOutputStream
       4: dup
       5: aload_1
       6: invokestatic  #19                 // Method org/apache/jena/ext/com/google/common/base/Preconditions.checkNotNull:(Ljava/lang/Object;)Ljava/lang/Object;
       9: checkcast     #21                 // class java/io/OutputStream
      12: invokespecial #23                 // Method java/io/DataOutputStream."<init>":(Ljava/io/OutputStream;)V
      15: invokespecial #24                 // Method java/io/FilterOutputStream."<init>":(Ljava/io/OutputStream;)V
      18: return

  public void write(byte[], int, int) throws java.io.IOException;
    Code:
       0: aload_0
       1: getfield      #34                 // Field out:Ljava/io/OutputStream;
       4: aload_1
       5: iload_2
       6: iload_3
       7: invokevirtual #36                 // Method java/io/OutputStream.write:([BII)V
      10: return

  public void writeBoolean(boolean) throws java.io.IOException;
    Code:
       0: aload_0
       1: getfield      #34                 // Field out:Ljava/io/OutputStream;
       4: checkcast     #13                 // class java/io/DataOutputStream
       7: iload_1
       8: invokevirtual #45                 // Method java/io/DataOutputStream.writeBoolean:(Z)V
      11: return

  public void writeByte(int) throws java.io.IOException;
    Code:
       0: aload_0
       1: getfield      #34                 // Field out:Ljava/io/OutputStream;
       4: checkcast     #13                 // class java/io/DataOutputStream
       7: iload_1
       8: invokevirtual #51                 // Method java/io/DataOutputStream.writeByte:(I)V
      11: return

  public void writeBytes(java.lang.String) throws java.io.IOException;
    Code:
       0: aload_0
       1: getfield      #34                 // Field out:Ljava/io/OutputStream;
       4: checkcast     #13                 // class java/io/DataOutputStream
       7: aload_1
       8: invokevirtual #56                 // Method java/io/DataOutputStream.writeBytes:(Ljava/lang/String;)V
      11: return

  public void writeChar(int) throws java.io.IOException;
    Code:
       0: aload_0
       1: iload_1
       2: invokevirtual #62                 // Method writeShort:(I)V
       5: return

  public void writeChars(java.lang.String) throws java.io.IOException;
    Code:
       0: iconst_0
       1: istore_2
       2: iload_2
       3: aload_1
       4: invokevirtual #69                 // Method java/lang/String.length:()I
       7: if_icmpge     25
      10: aload_0
      11: aload_1
      12: iload_2
      13: invokevirtual #73                 // Method java/lang/String.charAt:(I)C
      16: invokevirtual #75                 // Method writeChar:(I)V
      19: iinc          2, 1
      22: goto          2
      25: return

  public void writeDouble(double) throws java.io.IOException;
    Code:
       0: aload_0
       1: dload_1
       2: invokestatic  #84                 // Method java/lang/Double.doubleToLongBits:(D)J
       5: invokevirtual #88                 // Method writeLong:(J)V
       8: return

  public void writeFloat(float) throws java.io.IOException;
    Code:
       0: aload_0
       1: fload_1
       2: invokestatic  #97                 // Method java/lang/Float.floatToIntBits:(F)I
       5: invokevirtual #100                // Method writeInt:(I)V
       8: return

  public void writeInt(int) throws java.io.IOException;
    Code:
       0: aload_0
       1: getfield      #34                 // Field out:Ljava/io/OutputStream;
       4: sipush        255
       7: iload_1
       8: iand
       9: invokevirtual #103                // Method java/io/OutputStream.write:(I)V
      12: aload_0
      13: getfield      #34                 // Field out:Ljava/io/OutputStream;
      16: sipush        255
      19: iload_1
      20: bipush        8
      22: ishr
      23: iand
      24: invokevirtual #103                // Method java/io/OutputStream.write:(I)V
      27: aload_0
      28: getfield      #34                 // Field out:Ljava/io/OutputStream;
      31: sipush        255
      34: iload_1
      35: bipush        16
      37: ishr
      38: iand
      39: invokevirtual #103                // Method java/io/OutputStream.write:(I)V
      42: aload_0
      43: getfield      #34                 // Field out:Ljava/io/OutputStream;
      46: sipush        255
      49: iload_1
      50: bipush        24
      52: ishr
      53: iand
      54: invokevirtual #103                // Method java/io/OutputStream.write:(I)V
      57: return

  public void writeLong(long) throws java.io.IOException;
    Code:
       0: lload_1
       1: invokestatic  #109                // Method java/lang/Long.reverseBytes:(J)J
       4: invokestatic  #115                // Method org/apache/jena/ext/com/google/common/primitives/Longs.toByteArray:(J)[B
       7: astore_3
       8: aload_0
       9: aload_3
      10: iconst_0
      11: aload_3
      12: arraylength
      13: invokevirtual #116                // Method write:([BII)V
      16: return

  public void writeShort(int) throws java.io.IOException;
    Code:
       0: aload_0
       1: getfield      #34                 // Field out:Ljava/io/OutputStream;
       4: sipush        255
       7: iload_1
       8: iand
       9: invokevirtual #103                // Method java/io/OutputStream.write:(I)V
      12: aload_0
      13: getfield      #34                 // Field out:Ljava/io/OutputStream;
      16: sipush        255
      19: iload_1
      20: bipush        8
      22: ishr
      23: iand
      24: invokevirtual #103                // Method java/io/OutputStream.write:(I)V
      27: return

  public void writeUTF(java.lang.String) throws java.io.IOException;
    Code:
       0: aload_0
       1: getfield      #34                 // Field out:Ljava/io/OutputStream;
       4: checkcast     #13                 // class java/io/DataOutputStream
       7: aload_1
       8: invokevirtual #121                // Method java/io/DataOutputStream.writeUTF:(Ljava/lang/String;)V
      11: return

  public void close() throws java.io.IOException;
    Code:
       0: aload_0
       1: getfield      #34                 // Field out:Ljava/io/OutputStream;
       4: invokevirtual #126                // Method java/io/OutputStream.close:()V
       7: return
}
