Compiled from "DiskFileUpload.java"
public class io.netty.handler.codec.http.multipart.DiskFileUpload extends io.netty.handler.codec.http.multipart.AbstractDiskHttpData implements io.netty.handler.codec.http.multipart.FileUpload {
  public static java.lang.String baseDirectory;

  public static boolean deleteOnExitTemporaryFile;

  public static final java.lang.String prefix;

  public static final java.lang.String postfix;

  private final java.lang.String baseDir;

  private final boolean deleteOnExit;

  private java.lang.String filename;

  private java.lang.String contentType;

  private java.lang.String contentTransferEncoding;

  public io.netty.handler.codec.http.multipart.DiskFileUpload(java.lang.String, java.lang.String, java.lang.String, java.lang.String, java.nio.charset.Charset, long, java.lang.String, boolean);
    Code:
       0: aload_0
       1: aload_1
       2: aload         5
       4: lload         6
       6: invokespecial #1                  // Method io/netty/handler/codec/http/multipart/AbstractDiskHttpData."<init>":(Ljava/lang/String;Ljava/nio/charset/Charset;J)V
       9: aload_0
      10: aload_2
      11: invokevirtual #2                  // Method setFilename:(Ljava/lang/String;)V
      14: aload_0
      15: aload_3
      16: invokevirtual #3                  // Method setContentType:(Ljava/lang/String;)V
      19: aload_0
      20: aload         4
      22: invokevirtual #4                  // Method setContentTransferEncoding:(Ljava/lang/String;)V
      25: aload_0
      26: aload         8
      28: ifnonnull     37
      31: getstatic     #5                  // Field baseDirectory:Ljava/lang/String;
      34: goto          39
      37: aload         8
      39: putfield      #6                  // Field baseDir:Ljava/lang/String;
      42: aload_0
      43: iload         9
      45: putfield      #7                  // Field deleteOnExit:Z
      48: return

  public io.netty.handler.codec.http.multipart.DiskFileUpload(java.lang.String, java.lang.String, java.lang.String, java.lang.String, java.nio.charset.Charset, long);
    Code:
       0: aload_0
       1: aload_1
       2: aload_2
       3: aload_3
       4: aload         4
       6: aload         5
       8: lload         6
      10: getstatic     #5                  // Field baseDirectory:Ljava/lang/String;
      13: getstatic     #8                  // Field deleteOnExitTemporaryFile:Z
      16: invokespecial #9                  // Method "<init>":(Ljava/lang/String;Ljava/lang/String;Ljava/lang/String;Ljava/lang/String;Ljava/nio/charset/Charset;JLjava/lang/String;Z)V
      19: return

  public io.netty.handler.codec.http.multipart.InterfaceHttpData$HttpDataType getHttpDataType();
    Code:
       0: getstatic     #10                 // Field io/netty/handler/codec/http/multipart/InterfaceHttpData$HttpDataType.FileUpload:Lio/netty/handler/codec/http/multipart/InterfaceHttpData$HttpDataType;
       3: areturn

  public java.lang.String getFilename();
    Code:
       0: aload_0
       1: getfield      #11                 // Field filename:Ljava/lang/String;
       4: areturn

  public void setFilename(java.lang.String);
    Code:
       0: aload_0
       1: aload_1
       2: ldc           #12                 // String filename
       4: invokestatic  #13                 // Method io/netty/util/internal/ObjectUtil.checkNotNull:(Ljava/lang/Object;Ljava/lang/String;)Ljava/lang/Object;
       7: checkcast     #14                 // class java/lang/String
      10: putfield      #11                 // Field filename:Ljava/lang/String;
      13: return

  public int hashCode();
    Code:
       0: aload_0
       1: invokestatic  #15                 // Method io/netty/handler/codec/http/multipart/FileUploadUtil.hashCode:(Lio/netty/handler/codec/http/multipart/FileUpload;)I
       4: ireturn

  public boolean equals(java.lang.Object);
    Code:
       0: aload_1
       1: instanceof    #16                 // class io/netty/handler/codec/http/multipart/FileUpload
       4: ifeq          22
       7: aload_0
       8: aload_1
       9: checkcast     #16                 // class io/netty/handler/codec/http/multipart/FileUpload
      12: invokestatic  #17                 // Method io/netty/handler/codec/http/multipart/FileUploadUtil.equals:(Lio/netty/handler/codec/http/multipart/FileUpload;Lio/netty/handler/codec/http/multipart/FileUpload;)Z
      15: ifeq          22
      18: iconst_1
      19: goto          23
      22: iconst_0
      23: ireturn

  public int compareTo(io.netty.handler.codec.http.multipart.InterfaceHttpData);
    Code:
       0: aload_1
       1: instanceof    #16                 // class io/netty/handler/codec/http/multipart/FileUpload
       4: ifne          51
       7: new           #18                 // class java/lang/ClassCastException
      10: dup
      11: new           #19                 // class java/lang/StringBuilder
      14: dup
      15: invokespecial #20                 // Method java/lang/StringBuilder."<init>":()V
      18: ldc           #21                 // String Cannot compare
      20: invokevirtual #22                 // Method java/lang/StringBuilder.append:(Ljava/lang/String;)Ljava/lang/StringBuilder;
      23: aload_0
      24: invokevirtual #23                 // Method getHttpDataType:()Lio/netty/handler/codec/http/multipart/InterfaceHttpData$HttpDataType;
      27: invokevirtual #24                 // Method java/lang/StringBuilder.append:(Ljava/lang/Object;)Ljava/lang/StringBuilder;
      30: ldc           #25                 // String  with
      32: invokevirtual #22                 // Method java/lang/StringBuilder.append:(Ljava/lang/String;)Ljava/lang/StringBuilder;
      35: aload_1
      36: invokeinterface #26,  1           // InterfaceMethod io/netty/handler/codec/http/multipart/InterfaceHttpData.getHttpDataType:()Lio/netty/handler/codec/http/multipart/InterfaceHttpData$HttpDataType;
      41: invokevirtual #24                 // Method java/lang/StringBuilder.append:(Ljava/lang/Object;)Ljava/lang/StringBuilder;
      44: invokevirtual #27                 // Method java/lang/StringBuilder.toString:()Ljava/lang/String;
      47: invokespecial #28                 // Method java/lang/ClassCastException."<init>":(Ljava/lang/String;)V
      50: athrow
      51: aload_0
      52: aload_1
      53: checkcast     #16                 // class io/netty/handler/codec/http/multipart/FileUpload
      56: invokevirtual #29                 // Method compareTo:(Lio/netty/handler/codec/http/multipart/FileUpload;)I
      59: ireturn

  public int compareTo(io.netty.handler.codec.http.multipart.FileUpload);
    Code:
       0: aload_0
       1: aload_1
       2: invokestatic  #30                 // Method io/netty/handler/codec/http/multipart/FileUploadUtil.compareTo:(Lio/netty/handler/codec/http/multipart/FileUpload;Lio/netty/handler/codec/http/multipart/FileUpload;)I
       5: ireturn

  public void setContentType(java.lang.String);
    Code:
       0: aload_0
       1: aload_1
       2: ldc           #31                 // String contentType
       4: invokestatic  #13                 // Method io/netty/util/internal/ObjectUtil.checkNotNull:(Ljava/lang/Object;Ljava/lang/String;)Ljava/lang/Object;
       7: checkcast     #14                 // class java/lang/String
      10: putfield      #32                 // Field contentType:Ljava/lang/String;
      13: return

  public java.lang.String getContentType();
    Code:
       0: aload_0
       1: getfield      #32                 // Field contentType:Ljava/lang/String;
       4: areturn

  public java.lang.String getContentTransferEncoding();
    Code:
       0: aload_0
       1: getfield      #33                 // Field contentTransferEncoding:Ljava/lang/String;
       4: areturn

  public void setContentTransferEncoding(java.lang.String);
    Code:
       0: aload_0
       1: aload_1
       2: putfield      #33                 // Field contentTransferEncoding:Ljava/lang/String;
       5: return

  public java.lang.String toString();
    Code:
       0: aconst_null
       1: astore_1
       2: aload_0
       3: invokevirtual #34                 // Method getFile:()Ljava/io/File;
       6: astore_1
       7: goto          11
      10: astore_2
      11: new           #19                 // class java/lang/StringBuilder
      14: dup
      15: invokespecial #20                 // Method java/lang/StringBuilder."<init>":()V
      18: getstatic     #36                 // Field io/netty/handler/codec/http/HttpHeaderNames.CONTENT_DISPOSITION:Lio/netty/util/AsciiString;
      21: invokevirtual #24                 // Method java/lang/StringBuilder.append:(Ljava/lang/Object;)Ljava/lang/StringBuilder;
      24: ldc           #37                 // String :
      26: invokevirtual #22                 // Method java/lang/StringBuilder.append:(Ljava/lang/String;)Ljava/lang/StringBuilder;
      29: getstatic     #38                 // Field io/netty/handler/codec/http/HttpHeaderValues.FORM_DATA:Lio/netty/util/AsciiString;
      32: invokevirtual #24                 // Method java/lang/StringBuilder.append:(Ljava/lang/Object;)Ljava/lang/StringBuilder;
      35: ldc           #39                 // String ;
      37: invokevirtual #22                 // Method java/lang/StringBuilder.append:(Ljava/lang/String;)Ljava/lang/StringBuilder;
      40: getstatic     #40                 // Field io/netty/handler/codec/http/HttpHeaderValues.NAME:Lio/netty/util/AsciiString;
      43: invokevirtual #24                 // Method java/lang/StringBuilder.append:(Ljava/lang/Object;)Ljava/lang/StringBuilder;
      46: ldc           #41                 // String =\"
      48: invokevirtual #22                 // Method java/lang/StringBuilder.append:(Ljava/lang/String;)Ljava/lang/StringBuilder;
      51: aload_0
      52: invokevirtual #42                 // Method getName:()Ljava/lang/String;
      55: invokevirtual #22                 // Method java/lang/StringBuilder.append:(Ljava/lang/String;)Ljava/lang/StringBuilder;
      58: ldc           #43                 // String \";
      60: invokevirtual #22                 // Method java/lang/StringBuilder.append:(Ljava/lang/String;)Ljava/lang/StringBuilder;
      63: getstatic     #44                 // Field io/netty/handler/codec/http/HttpHeaderValues.FILENAME:Lio/netty/util/AsciiString;
      66: invokevirtual #24                 // Method java/lang/StringBuilder.append:(Ljava/lang/Object;)Ljava/lang/StringBuilder;
      69: ldc           #41                 // String =\"
      71: invokevirtual #22                 // Method java/lang/StringBuilder.append:(Ljava/lang/String;)Ljava/lang/StringBuilder;
      74: aload_0
      75: getfield      #11                 // Field filename:Ljava/lang/String;
      78: invokevirtual #22                 // Method java/lang/StringBuilder.append:(Ljava/lang/String;)Ljava/lang/StringBuilder;
      81: ldc           #45                 // String \"\r\n
      83: invokevirtual #22                 // Method java/lang/StringBuilder.append:(Ljava/lang/String;)Ljava/lang/StringBuilder;
      86: getstatic     #46                 // Field io/netty/handler/codec/http/HttpHeaderNames.CONTENT_TYPE:Lio/netty/util/AsciiString;
      89: invokevirtual #24                 // Method java/lang/StringBuilder.append:(Ljava/lang/Object;)Ljava/lang/StringBuilder;
      92: ldc           #37                 // String :
      94: invokevirtual #22                 // Method java/lang/StringBuilder.append:(Ljava/lang/String;)Ljava/lang/StringBuilder;
      97: aload_0
      98: getfield      #32                 // Field contentType:Ljava/lang/String;
     101: invokevirtual #22                 // Method java/lang/StringBuilder.append:(Ljava/lang/String;)Ljava/lang/StringBuilder;
     104: aload_0
     105: invokevirtual #47                 // Method getCharset:()Ljava/nio/charset/Charset;
     108: ifnull        155
     111: new           #19                 // class java/lang/StringBuilder
     114: dup
     115: invokespecial #20                 // Method java/lang/StringBuilder."<init>":()V
     118: ldc           #39                 // String ;
     120: invokevirtual #22                 // Method java/lang/StringBuilder.append:(Ljava/lang/String;)Ljava/lang/StringBuilder;
     123: getstatic     #48                 // Field io/netty/handler/codec/http/HttpHeaderValues.CHARSET:Lio/netty/util/AsciiString;
     126: invokevirtual #24                 // Method java/lang/StringBuilder.append:(Ljava/lang/Object;)Ljava/lang/StringBuilder;
     129: bipush        61
     131: invokevirtual #49                 // Method java/lang/StringBuilder.append:(C)Ljava/lang/StringBuilder;
     134: aload_0
     135: invokevirtual #47                 // Method getCharset:()Ljava/nio/charset/Charset;
     138: invokevirtual #50                 // Method java/nio/charset/Charset.name:()Ljava/lang/String;
     141: invokevirtual #22                 // Method java/lang/StringBuilder.append:(Ljava/lang/String;)Ljava/lang/StringBuilder;
     144: ldc           #51                 // String \r\n
     146: invokevirtual #22                 // Method java/lang/StringBuilder.append:(Ljava/lang/String;)Ljava/lang/StringBuilder;
     149: invokevirtual #27                 // Method java/lang/StringBuilder.toString:()Ljava/lang/String;
     152: goto          157
     155: ldc           #51                 // String \r\n
     157: invokevirtual #22                 // Method java/lang/StringBuilder.append:(Ljava/lang/String;)Ljava/lang/StringBuilder;
     160: getstatic     #52                 // Field io/netty/handler/codec/http/HttpHeaderNames.CONTENT_LENGTH:Lio/netty/util/AsciiString;
     163: invokevirtual #24                 // Method java/lang/StringBuilder.append:(Ljava/lang/Object;)Ljava/lang/StringBuilder;
     166: ldc           #37                 // String :
     168: invokevirtual #22                 // Method java/lang/StringBuilder.append:(Ljava/lang/String;)Ljava/lang/StringBuilder;
     171: aload_0
     172: invokevirtual #53                 // Method length:()J
     175: invokevirtual #54                 // Method java/lang/StringBuilder.append:(J)Ljava/lang/StringBuilder;
     178: ldc           #55                 // String \r\nCompleted:
     180: invokevirtual #22                 // Method java/lang/StringBuilder.append:(Ljava/lang/String;)Ljava/lang/StringBuilder;
     183: aload_0
     184: invokevirtual #56                 // Method isCompleted:()Z
     187: invokevirtual #57                 // Method java/lang/StringBuilder.append:(Z)Ljava/lang/StringBuilder;
     190: ldc           #58                 // String \r\nIsInMemory:
     192: invokevirtual #22                 // Method java/lang/StringBuilder.append:(Ljava/lang/String;)Ljava/lang/StringBuilder;
     195: aload_0
     196: invokevirtual #59                 // Method isInMemory:()Z
     199: invokevirtual #57                 // Method java/lang/StringBuilder.append:(Z)Ljava/lang/StringBuilder;
     202: ldc           #60                 // String \r\nRealFile:
     204: invokevirtual #22                 // Method java/lang/StringBuilder.append:(Ljava/lang/String;)Ljava/lang/StringBuilder;
     207: aload_1
     208: ifnull        218
     211: aload_1
     212: invokevirtual #61                 // Method java/io/File.getAbsolutePath:()Ljava/lang/String;
     215: goto          220
     218: ldc           #62                 // String null
     220: invokevirtual #22                 // Method java/lang/StringBuilder.append:(Ljava/lang/String;)Ljava/lang/StringBuilder;
     223: ldc           #63                 // String  DeleteAfter:
     225: invokevirtual #22                 // Method java/lang/StringBuilder.append:(Ljava/lang/String;)Ljava/lang/StringBuilder;
     228: aload_0
     229: getfield      #7                  // Field deleteOnExit:Z
     232: invokevirtual #57                 // Method java/lang/StringBuilder.append:(Z)Ljava/lang/StringBuilder;
     235: invokevirtual #27                 // Method java/lang/StringBuilder.toString:()Ljava/lang/String;
     238: areturn
    Exception table:
       from    to  target type
           2     7    10   Class java/io/IOException

  protected boolean deleteOnExit();
    Code:
       0: aload_0
       1: getfield      #7                  // Field deleteOnExit:Z
       4: ireturn

  protected java.lang.String getBaseDirectory();
    Code:
       0: aload_0
       1: getfield      #6                  // Field baseDir:Ljava/lang/String;
       4: areturn

  protected java.lang.String getDiskFilename();
    Code:
       0: ldc           #64                 // String upload
       2: areturn

  protected java.lang.String getPostfix();
    Code:
       0: ldc           #66                 // String .tmp
       2: areturn

  protected java.lang.String getPrefix();
    Code:
       0: ldc           #67                 // String FUp_
       2: areturn

  public io.netty.handler.codec.http.multipart.FileUpload copy();
    Code:
       0: aload_0
       1: invokevirtual #68                 // Method content:()Lio/netty/buffer/ByteBuf;
       4: astore_1
       5: aload_0
       6: aload_1
       7: ifnull        17
      10: aload_1
      11: invokevirtual #69                 // Method io/netty/buffer/ByteBuf.copy:()Lio/netty/buffer/ByteBuf;
      14: goto          18
      17: aconst_null
      18: invokevirtual #70                 // Method replace:(Lio/netty/buffer/ByteBuf;)Lio/netty/handler/codec/http/multipart/FileUpload;
      21: areturn

  public io.netty.handler.codec.http.multipart.FileUpload duplicate();
    Code:
       0: aload_0
       1: invokevirtual #68                 // Method content:()Lio/netty/buffer/ByteBuf;
       4: astore_1
       5: aload_0
       6: aload_1
       7: ifnull        17
      10: aload_1
      11: invokevirtual #71                 // Method io/netty/buffer/ByteBuf.duplicate:()Lio/netty/buffer/ByteBuf;
      14: goto          18
      17: aconst_null
      18: invokevirtual #70                 // Method replace:(Lio/netty/buffer/ByteBuf;)Lio/netty/handler/codec/http/multipart/FileUpload;
      21: areturn

  public io.netty.handler.codec.http.multipart.FileUpload retainedDuplicate();
    Code:
       0: aload_0
       1: invokevirtual #68                 // Method content:()Lio/netty/buffer/ByteBuf;
       4: astore_1
       5: aload_1
       6: ifnull        53
       9: aload_1
      10: invokevirtual #72                 // Method io/netty/buffer/ByteBuf.retainedDuplicate:()Lio/netty/buffer/ByteBuf;
      13: astore_1
      14: iconst_0
      15: istore_2
      16: aload_0
      17: aload_1
      18: invokevirtual #70                 // Method replace:(Lio/netty/buffer/ByteBuf;)Lio/netty/handler/codec/http/multipart/FileUpload;
      21: astore_3
      22: iconst_1
      23: istore_2
      24: aload_3
      25: astore        4
      27: iload_2
      28: ifne          36
      31: aload_1
      32: invokevirtual #73                 // Method io/netty/buffer/ByteBuf.release:()Z
      35: pop
      36: aload         4
      38: areturn
      39: astore        5
      41: iload_2
      42: ifne          50
      45: aload_1
      46: invokevirtual #73                 // Method io/netty/buffer/ByteBuf.release:()Z
      49: pop
      50: aload         5
      52: athrow
      53: aload_0
      54: aconst_null
      55: invokevirtual #70                 // Method replace:(Lio/netty/buffer/ByteBuf;)Lio/netty/handler/codec/http/multipart/FileUpload;
      58: areturn
    Exception table:
       from    to  target type
          16    27    39   any
          39    41    39   any

  public io.netty.handler.codec.http.multipart.FileUpload replace(io.netty.buffer.ByteBuf);
    Code:
       0: new           #65                 // class io/netty/handler/codec/http/multipart/DiskFileUpload
       3: dup
       4: aload_0
       5: invokevirtual #42                 // Method getName:()Ljava/lang/String;
       8: aload_0
       9: invokevirtual #74                 // Method getFilename:()Ljava/lang/String;
      12: aload_0
      13: invokevirtual #75                 // Method getContentType:()Ljava/lang/String;
      16: aload_0
      17: invokevirtual #76                 // Method getContentTransferEncoding:()Ljava/lang/String;
      20: aload_0
      21: invokevirtual #47                 // Method getCharset:()Ljava/nio/charset/Charset;
      24: aload_0
      25: getfield      #77                 // Field size:J
      28: aload_0
      29: getfield      #6                  // Field baseDir:Ljava/lang/String;
      32: aload_0
      33: getfield      #7                  // Field deleteOnExit:Z
      36: invokespecial #9                  // Method "<init>":(Ljava/lang/String;Ljava/lang/String;Ljava/lang/String;Ljava/lang/String;Ljava/nio/charset/Charset;JLjava/lang/String;Z)V
      39: astore_2
      40: aload_1
      41: ifnull        62
      44: aload_2
      45: aload_1
      46: invokevirtual #78                 // Method setContent:(Lio/netty/buffer/ByteBuf;)V
      49: goto          62
      52: astore_3
      53: new           #79                 // class io/netty/channel/ChannelException
      56: dup
      57: aload_3
      58: invokespecial #80                 // Method io/netty/channel/ChannelException."<init>":(Ljava/lang/Throwable;)V
      61: athrow
      62: aload_2
      63: aload_0
      64: invokevirtual #56                 // Method isCompleted:()Z
      67: invokevirtual #81                 // Method setCompleted:(Z)V
      70: aload_2
      71: areturn
    Exception table:
       from    to  target type
          44    49    52   Class java/io/IOException

  public io.netty.handler.codec.http.multipart.FileUpload retain(int);
    Code:
       0: aload_0
       1: iload_1
       2: invokespecial #82                 // Method io/netty/handler/codec/http/multipart/AbstractDiskHttpData.retain:(I)Lio/netty/handler/codec/http/multipart/HttpData;
       5: pop
       6: aload_0
       7: areturn

  public io.netty.handler.codec.http.multipart.FileUpload retain();
    Code:
       0: aload_0
       1: invokespecial #83                 // Method io/netty/handler/codec/http/multipart/AbstractDiskHttpData.retain:()Lio/netty/handler/codec/http/multipart/HttpData;
       4: pop
       5: aload_0
       6: areturn

  public io.netty.handler.codec.http.multipart.FileUpload touch();
    Code:
       0: aload_0
       1: invokespecial #84                 // Method io/netty/handler/codec/http/multipart/AbstractDiskHttpData.touch:()Lio/netty/handler/codec/http/multipart/HttpData;
       4: pop
       5: aload_0
       6: areturn

  public io.netty.handler.codec.http.multipart.FileUpload touch(java.lang.Object);
    Code:
       0: aload_0
       1: aload_1
       2: invokespecial #85                 // Method io/netty/handler/codec/http/multipart/AbstractDiskHttpData.touch:(Ljava/lang/Object;)Lio/netty/handler/codec/http/multipart/HttpData;
       5: pop
       6: aload_0
       7: areturn

  public io.netty.handler.codec.http.multipart.HttpData touch(java.lang.Object);
    Code:
       0: aload_0
       1: aload_1
       2: invokevirtual #86                 // Method touch:(Ljava/lang/Object;)Lio/netty/handler/codec/http/multipart/FileUpload;
       5: areturn

  public io.netty.handler.codec.http.multipart.HttpData touch();
    Code:
       0: aload_0
       1: invokevirtual #87                 // Method touch:()Lio/netty/handler/codec/http/multipart/FileUpload;
       4: areturn

  public io.netty.handler.codec.http.multipart.HttpData retain(int);
    Code:
       0: aload_0
       1: iload_1
       2: invokevirtual #88                 // Method retain:(I)Lio/netty/handler/codec/http/multipart/FileUpload;
       5: areturn

  public io.netty.handler.codec.http.multipart.HttpData retain();
    Code:
       0: aload_0
       1: invokevirtual #89                 // Method retain:()Lio/netty/handler/codec/http/multipart/FileUpload;
       4: areturn

  public io.netty.handler.codec.http.multipart.HttpData replace(io.netty.buffer.ByteBuf);
    Code:
       0: aload_0
       1: aload_1
       2: invokevirtual #70                 // Method replace:(Lio/netty/buffer/ByteBuf;)Lio/netty/handler/codec/http/multipart/FileUpload;
       5: areturn

  public io.netty.handler.codec.http.multipart.HttpData retainedDuplicate();
    Code:
       0: aload_0
       1: invokevirtual #90                 // Method retainedDuplicate:()Lio/netty/handler/codec/http/multipart/FileUpload;
       4: areturn

  public io.netty.handler.codec.http.multipart.HttpData duplicate();
    Code:
       0: aload_0
       1: invokevirtual #91                 // Method duplicate:()Lio/netty/handler/codec/http/multipart/FileUpload;
       4: areturn

  public io.netty.handler.codec.http.multipart.HttpData copy();
    Code:
       0: aload_0
       1: invokevirtual #92                 // Method copy:()Lio/netty/handler/codec/http/multipart/FileUpload;
       4: areturn

  public io.netty.handler.codec.http.multipart.InterfaceHttpData touch(java.lang.Object);
    Code:
       0: aload_0
       1: aload_1
       2: invokevirtual #86                 // Method touch:(Ljava/lang/Object;)Lio/netty/handler/codec/http/multipart/FileUpload;
       5: areturn

  public io.netty.handler.codec.http.multipart.InterfaceHttpData touch();
    Code:
       0: aload_0
       1: invokevirtual #87                 // Method touch:()Lio/netty/handler/codec/http/multipart/FileUpload;
       4: areturn

  public io.netty.handler.codec.http.multipart.InterfaceHttpData retain(int);
    Code:
       0: aload_0
       1: iload_1
       2: invokevirtual #88                 // Method retain:(I)Lio/netty/handler/codec/http/multipart/FileUpload;
       5: areturn

  public io.netty.handler.codec.http.multipart.InterfaceHttpData retain();
    Code:
       0: aload_0
       1: invokevirtual #89                 // Method retain:()Lio/netty/handler/codec/http/multipart/FileUpload;
       4: areturn

  public int compareTo(java.lang.Object);
    Code:
       0: aload_0
       1: aload_1
       2: checkcast     #93                 // class io/netty/handler/codec/http/multipart/InterfaceHttpData
       5: invokevirtual #94                 // Method compareTo:(Lio/netty/handler/codec/http/multipart/InterfaceHttpData;)I
       8: ireturn

  public io.netty.util.ReferenceCounted touch(java.lang.Object);
    Code:
       0: aload_0
       1: aload_1
       2: invokevirtual #86                 // Method touch:(Ljava/lang/Object;)Lio/netty/handler/codec/http/multipart/FileUpload;
       5: areturn

  public io.netty.util.ReferenceCounted touch();
    Code:
       0: aload_0
       1: invokevirtual #87                 // Method touch:()Lio/netty/handler/codec/http/multipart/FileUpload;
       4: areturn

  public io.netty.util.ReferenceCounted retain(int);
    Code:
       0: aload_0
       1: iload_1
       2: invokevirtual #88                 // Method retain:(I)Lio/netty/handler/codec/http/multipart/FileUpload;
       5: areturn

  public io.netty.util.ReferenceCounted retain();
    Code:
       0: aload_0
       1: invokevirtual #89                 // Method retain:()Lio/netty/handler/codec/http/multipart/FileUpload;
       4: areturn

  public io.netty.buffer.ByteBufHolder touch(java.lang.Object);
    Code:
       0: aload_0
       1: aload_1
       2: invokevirtual #86                 // Method touch:(Ljava/lang/Object;)Lio/netty/handler/codec/http/multipart/FileUpload;
       5: areturn

  public io.netty.buffer.ByteBufHolder touch();
    Code:
       0: aload_0
       1: invokevirtual #87                 // Method touch:()Lio/netty/handler/codec/http/multipart/FileUpload;
       4: areturn

  public io.netty.buffer.ByteBufHolder retain(int);
    Code:
       0: aload_0
       1: iload_1
       2: invokevirtual #88                 // Method retain:(I)Lio/netty/handler/codec/http/multipart/FileUpload;
       5: areturn

  public io.netty.buffer.ByteBufHolder retain();
    Code:
       0: aload_0
       1: invokevirtual #89                 // Method retain:()Lio/netty/handler/codec/http/multipart/FileUpload;
       4: areturn

  public io.netty.buffer.ByteBufHolder replace(io.netty.buffer.ByteBuf);
    Code:
       0: aload_0
       1: aload_1
       2: invokevirtual #70                 // Method replace:(Lio/netty/buffer/ByteBuf;)Lio/netty/handler/codec/http/multipart/FileUpload;
       5: areturn

  public io.netty.buffer.ByteBufHolder retainedDuplicate();
    Code:
       0: aload_0
       1: invokevirtual #90                 // Method retainedDuplicate:()Lio/netty/handler/codec/http/multipart/FileUpload;
       4: areturn

  public io.netty.buffer.ByteBufHolder duplicate();
    Code:
       0: aload_0
       1: invokevirtual #91                 // Method duplicate:()Lio/netty/handler/codec/http/multipart/FileUpload;
       4: areturn

  public io.netty.buffer.ByteBufHolder copy();
    Code:
       0: aload_0
       1: invokevirtual #92                 // Method copy:()Lio/netty/handler/codec/http/multipart/FileUpload;
       4: areturn

  static {};
    Code:
       0: iconst_1
       1: putstatic     #8                  // Field deleteOnExitTemporaryFile:Z
       4: return
}
