Compiled from "DefaultManagedHttpClientConnection.java"
final class org.apache.hc.client5.http.impl.io.DefaultManagedHttpClientConnection extends org.apache.hc.core5.http.impl.io.DefaultBHttpClientConnection implements org.apache.hc.client5.http.io.ManagedHttpClientConnection,org.apache.hc.core5.util.Identifiable {
  private static final org.slf4j.Logger LOG;

  private static final org.slf4j.Logger HEADER_LOG;

  private static final org.slf4j.Logger WIRE_LOG;

  private final java.lang.String id;

  private final java.util.concurrent.atomic.AtomicBoolean closed;

  private org.apache.hc.core5.util.Timeout socketTimeout;

  public org.apache.hc.client5.http.impl.io.DefaultManagedHttpClientConnection(java.lang.String, java.nio.charset.CharsetDecoder, java.nio.charset.CharsetEncoder, org.apache.hc.core5.http.config.Http1Config, org.apache.hc.core5.http.ContentLengthStrategy, org.apache.hc.core5.http.ContentLengthStrategy, org.apache.hc.core5.http.io.ResponseOutOfOrderStrategy, org.apache.hc.core5.http.io.HttpMessageWriterFactory<org.apache.hc.core5.http.ClassicHttpRequest>, org.apache.hc.core5.http.io.HttpMessageParserFactory<org.apache.hc.core5.http.ClassicHttpResponse>);
    Code:
       0: aload_0
       1: aload         4
       3: aload_2
       4: aload_3
       5: aload         5
       7: aload         6
       9: aload         7
      11: aload         8
      13: aload         9
      15: invokespecial #1                  // Method org/apache/hc/core5/http/impl/io/DefaultBHttpClientConnection."<init>":(Lorg/apache/hc/core5/http/config/Http1Config;Ljava/nio/charset/CharsetDecoder;Ljava/nio/charset/CharsetEncoder;Lorg/apache/hc/core5/http/ContentLengthStrategy;Lorg/apache/hc/core5/http/ContentLengthStrategy;Lorg/apache/hc/core5/http/io/ResponseOutOfOrderStrategy;Lorg/apache/hc/core5/http/io/HttpMessageWriterFactory;Lorg/apache/hc/core5/http/io/HttpMessageParserFactory;)V
      18: aload_0
      19: aload_1
      20: putfield      #2                  // Field id:Ljava/lang/String;
      23: aload_0
      24: new           #3                  // class java/util/concurrent/atomic/AtomicBoolean
      27: dup
      28: invokespecial #4                  // Method java/util/concurrent/atomic/AtomicBoolean."<init>":()V
      31: putfield      #5                  // Field closed:Ljava/util/concurrent/atomic/AtomicBoolean;
      34: return

  public org.apache.hc.client5.http.impl.io.DefaultManagedHttpClientConnection(java.lang.String, java.nio.charset.CharsetDecoder, java.nio.charset.CharsetEncoder, org.apache.hc.core5.http.config.Http1Config, org.apache.hc.core5.http.ContentLengthStrategy, org.apache.hc.core5.http.ContentLengthStrategy, org.apache.hc.core5.http.io.HttpMessageWriterFactory<org.apache.hc.core5.http.ClassicHttpRequest>, org.apache.hc.core5.http.io.HttpMessageParserFactory<org.apache.hc.core5.http.ClassicHttpResponse>);
    Code:
       0: aload_0
       1: aload_1
       2: aload_2
       3: aload_3
       4: aload         4
       6: aload         5
       8: aload         6
      10: aconst_null
      11: aload         7
      13: aload         8
      15: invokespecial #6                  // Method "<init>":(Ljava/lang/String;Ljava/nio/charset/CharsetDecoder;Ljava/nio/charset/CharsetEncoder;Lorg/apache/hc/core5/http/config/Http1Config;Lorg/apache/hc/core5/http/ContentLengthStrategy;Lorg/apache/hc/core5/http/ContentLengthStrategy;Lorg/apache/hc/core5/http/io/ResponseOutOfOrderStrategy;Lorg/apache/hc/core5/http/io/HttpMessageWriterFactory;Lorg/apache/hc/core5/http/io/HttpMessageParserFactory;)V
      18: return

  public org.apache.hc.client5.http.impl.io.DefaultManagedHttpClientConnection(java.lang.String);
    Code:
       0: aload_0
       1: aload_1
       2: aconst_null
       3: aconst_null
       4: aconst_null
       5: aconst_null
       6: aconst_null
       7: aconst_null
       8: aconst_null
       9: invokespecial #7                  // Method "<init>":(Ljava/lang/String;Ljava/nio/charset/CharsetDecoder;Ljava/nio/charset/CharsetEncoder;Lorg/apache/hc/core5/http/config/Http1Config;Lorg/apache/hc/core5/http/ContentLengthStrategy;Lorg/apache/hc/core5/http/ContentLengthStrategy;Lorg/apache/hc/core5/http/io/HttpMessageWriterFactory;Lorg/apache/hc/core5/http/io/HttpMessageParserFactory;)V
      12: return

  public java.lang.String getId();
    Code:
       0: aload_0
       1: getfield      #2                  // Field id:Ljava/lang/String;
       4: areturn

  public void bind(org.apache.hc.core5.http.impl.io.SocketHolder) throws java.io.IOException;
    Code:
       0: aload_0
       1: getfield      #5                  // Field closed:Ljava/util/concurrent/atomic/AtomicBoolean;
       4: invokevirtual #8                  // Method java/util/concurrent/atomic/AtomicBoolean.get:()Z
       7: ifeq          29
      10: aload_1
      11: invokevirtual #9                  // Method org/apache/hc/core5/http/impl/io/SocketHolder.getSocket:()Ljava/net/Socket;
      14: astore_2
      15: aload_2
      16: invokevirtual #10                 // Method java/net/Socket.close:()V
      19: new           #11                 // class java/io/InterruptedIOException
      22: dup
      23: ldc           #12                 // String Connection already shutdown
      25: invokespecial #13                 // Method java/io/InterruptedIOException."<init>":(Ljava/lang/String;)V
      28: athrow
      29: aload_0
      30: aload_1
      31: invokespecial #14                 // Method org/apache/hc/core5/http/impl/io/DefaultBHttpClientConnection.bind:(Lorg/apache/hc/core5/http/impl/io/SocketHolder;)V
      34: aload_0
      35: aload_1
      36: invokevirtual #9                  // Method org/apache/hc/core5/http/impl/io/SocketHolder.getSocket:()Ljava/net/Socket;
      39: invokevirtual #15                 // Method java/net/Socket.getSoTimeout:()I
      42: i2l
      43: invokestatic  #16                 // Method org/apache/hc/core5/util/Timeout.ofMilliseconds:(J)Lorg/apache/hc/core5/util/Timeout;
      46: putfield      #17                 // Field socketTimeout:Lorg/apache/hc/core5/util/Timeout;
      49: return

  public java.net.Socket getSocket();
    Code:
       0: aload_0
       1: invokevirtual #18                 // Method getSocketHolder:()Lorg/apache/hc/core5/http/impl/io/SocketHolder;
       4: astore_1
       5: aload_1
       6: ifnull        16
       9: aload_1
      10: invokevirtual #9                  // Method org/apache/hc/core5/http/impl/io/SocketHolder.getSocket:()Ljava/net/Socket;
      13: goto          17
      16: aconst_null
      17: areturn

  public javax.net.ssl.SSLSession getSSLSession();
    Code:
       0: aload_0
       1: invokevirtual #19                 // Method getSocket:()Ljava/net/Socket;
       4: astore_1
       5: aload_1
       6: instanceof    #20                 // class javax/net/ssl/SSLSocket
       9: ifeq          20
      12: aload_1
      13: checkcast     #20                 // class javax/net/ssl/SSLSocket
      16: invokevirtual #21                 // Method javax/net/ssl/SSLSocket.getSession:()Ljavax/net/ssl/SSLSession;
      19: areturn
      20: aconst_null
      21: areturn

  public void close() throws java.io.IOException;
    Code:
       0: aload_0
       1: getfield      #5                  // Field closed:Ljava/util/concurrent/atomic/AtomicBoolean;
       4: iconst_0
       5: iconst_1
       6: invokevirtual #22                 // Method java/util/concurrent/atomic/AtomicBoolean.compareAndSet:(ZZ)Z
       9: ifeq          41
      12: getstatic     #23                 // Field LOG:Lorg/slf4j/Logger;
      15: invokeinterface #24,  1           // InterfaceMethod org/slf4j/Logger.isDebugEnabled:()Z
      20: ifeq          37
      23: getstatic     #23                 // Field LOG:Lorg/slf4j/Logger;
      26: ldc           #25                 // String {} Close connection
      28: aload_0
      29: getfield      #2                  // Field id:Ljava/lang/String;
      32: invokeinterface #26,  3           // InterfaceMethod org/slf4j/Logger.debug:(Ljava/lang/String;Ljava/lang/Object;)V
      37: aload_0
      38: invokespecial #27                 // Method org/apache/hc/core5/http/impl/io/DefaultBHttpClientConnection.close:()V
      41: return

  public void setSocketTimeout(org.apache.hc.core5.util.Timeout);
    Code:
       0: getstatic     #23                 // Field LOG:Lorg/slf4j/Logger;
       3: invokeinterface #24,  1           // InterfaceMethod org/slf4j/Logger.isDebugEnabled:()Z
       8: ifeq          26
      11: getstatic     #23                 // Field LOG:Lorg/slf4j/Logger;
      14: ldc           #28                 // String {} set socket timeout to {}
      16: aload_0
      17: getfield      #2                  // Field id:Ljava/lang/String;
      20: aload_1
      21: invokeinterface #29,  4           // InterfaceMethod org/slf4j/Logger.debug:(Ljava/lang/String;Ljava/lang/Object;Ljava/lang/Object;)V
      26: aload_0
      27: aload_1
      28: invokespecial #30                 // Method org/apache/hc/core5/http/impl/io/DefaultBHttpClientConnection.setSocketTimeout:(Lorg/apache/hc/core5/util/Timeout;)V
      31: return

  public void close(org.apache.hc.core5.io.CloseMode);
    Code:
       0: aload_0
       1: getfield      #5                  // Field closed:Ljava/util/concurrent/atomic/AtomicBoolean;
       4: iconst_0
       5: iconst_1
       6: invokevirtual #22                 // Method java/util/concurrent/atomic/AtomicBoolean.compareAndSet:(ZZ)Z
       9: ifeq          43
      12: getstatic     #23                 // Field LOG:Lorg/slf4j/Logger;
      15: invokeinterface #24,  1           // InterfaceMethod org/slf4j/Logger.isDebugEnabled:()Z
      20: ifeq          38
      23: getstatic     #23                 // Field LOG:Lorg/slf4j/Logger;
      26: ldc           #31                 // String {} close connection {}
      28: aload_0
      29: getfield      #2                  // Field id:Ljava/lang/String;
      32: aload_1
      33: invokeinterface #29,  4           // InterfaceMethod org/slf4j/Logger.debug:(Ljava/lang/String;Ljava/lang/Object;Ljava/lang/Object;)V
      38: aload_0
      39: aload_1
      40: invokespecial #32                 // Method org/apache/hc/core5/http/impl/io/DefaultBHttpClientConnection.close:(Lorg/apache/hc/core5/io/CloseMode;)V
      43: return

  public void bind(java.net.Socket) throws java.io.IOException;
    Code:
       0: aload_0
       1: getstatic     #33                 // Field WIRE_LOG:Lorg/slf4j/Logger;
       4: invokeinterface #24,  1           // InterfaceMethod org/slf4j/Logger.isDebugEnabled:()Z
       9: ifeq          30
      12: new           #34                 // class org/apache/hc/client5/http/impl/io/LoggingSocketHolder
      15: dup
      16: aload_1
      17: aload_0
      18: getfield      #2                  // Field id:Ljava/lang/String;
      21: getstatic     #33                 // Field WIRE_LOG:Lorg/slf4j/Logger;
      24: invokespecial #35                 // Method org/apache/hc/client5/http/impl/io/LoggingSocketHolder."<init>":(Ljava/net/Socket;Ljava/lang/String;Lorg/slf4j/Logger;)V
      27: goto          38
      30: new           #36                 // class org/apache/hc/core5/http/impl/io/SocketHolder
      33: dup
      34: aload_1
      35: invokespecial #37                 // Method org/apache/hc/core5/http/impl/io/SocketHolder."<init>":(Ljava/net/Socket;)V
      38: invokespecial #14                 // Method org/apache/hc/core5/http/impl/io/DefaultBHttpClientConnection.bind:(Lorg/apache/hc/core5/http/impl/io/SocketHolder;)V
      41: aload_0
      42: aload_1
      43: invokevirtual #15                 // Method java/net/Socket.getSoTimeout:()I
      46: i2l
      47: invokestatic  #16                 // Method org/apache/hc/core5/util/Timeout.ofMilliseconds:(J)Lorg/apache/hc/core5/util/Timeout;
      50: putfield      #17                 // Field socketTimeout:Lorg/apache/hc/core5/util/Timeout;
      53: return

  protected void onResponseReceived(org.apache.hc.core5.http.ClassicHttpResponse);
    Code:
       0: aload_1
       1: ifnull        88
       4: getstatic     #38                 // Field HEADER_LOG:Lorg/slf4j/Logger;
       7: invokeinterface #24,  1           // InterfaceMethod org/slf4j/Logger.isDebugEnabled:()Z
      12: ifeq          88
      15: getstatic     #38                 // Field HEADER_LOG:Lorg/slf4j/Logger;
      18: ldc           #39                 // String {} << {}
      20: aload_0
      21: getfield      #2                  // Field id:Ljava/lang/String;
      24: new           #40                 // class org/apache/hc/core5/http/message/StatusLine
      27: dup
      28: aload_1
      29: invokespecial #41                 // Method org/apache/hc/core5/http/message/StatusLine."<init>":(Lorg/apache/hc/core5/http/HttpResponse;)V
      32: invokeinterface #29,  4           // InterfaceMethod org/slf4j/Logger.debug:(Ljava/lang/String;Ljava/lang/Object;Ljava/lang/Object;)V
      37: aload_1
      38: invokeinterface #42,  1           // InterfaceMethod org/apache/hc/core5/http/ClassicHttpResponse.getHeaders:()[Lorg/apache/hc/core5/http/Header;
      43: astore_2
      44: aload_2
      45: astore_3
      46: aload_3
      47: arraylength
      48: istore        4
      50: iconst_0
      51: istore        5
      53: iload         5
      55: iload         4
      57: if_icmpge     88
      60: aload_3
      61: iload         5
      63: aaload
      64: astore        6
      66: getstatic     #38                 // Field HEADER_LOG:Lorg/slf4j/Logger;
      69: ldc           #39                 // String {} << {}
      71: aload_0
      72: getfield      #2                  // Field id:Ljava/lang/String;
      75: aload         6
      77: invokeinterface #29,  4           // InterfaceMethod org/slf4j/Logger.debug:(Ljava/lang/String;Ljava/lang/Object;Ljava/lang/Object;)V
      82: iinc          5, 1
      85: goto          53
      88: return

  protected void onRequestSubmitted(org.apache.hc.core5.http.ClassicHttpRequest);
    Code:
       0: aload_1
       1: ifnull        88
       4: getstatic     #38                 // Field HEADER_LOG:Lorg/slf4j/Logger;
       7: invokeinterface #24,  1           // InterfaceMethod org/slf4j/Logger.isDebugEnabled:()Z
      12: ifeq          88
      15: getstatic     #38                 // Field HEADER_LOG:Lorg/slf4j/Logger;
      18: ldc           #43                 // String {} >> {}
      20: aload_0
      21: getfield      #2                  // Field id:Ljava/lang/String;
      24: new           #44                 // class org/apache/hc/core5/http/message/RequestLine
      27: dup
      28: aload_1
      29: invokespecial #45                 // Method org/apache/hc/core5/http/message/RequestLine."<init>":(Lorg/apache/hc/core5/http/HttpRequest;)V
      32: invokeinterface #29,  4           // InterfaceMethod org/slf4j/Logger.debug:(Ljava/lang/String;Ljava/lang/Object;Ljava/lang/Object;)V
      37: aload_1
      38: invokeinterface #46,  1           // InterfaceMethod org/apache/hc/core5/http/ClassicHttpRequest.getHeaders:()[Lorg/apache/hc/core5/http/Header;
      43: astore_2
      44: aload_2
      45: astore_3
      46: aload_3
      47: arraylength
      48: istore        4
      50: iconst_0
      51: istore        5
      53: iload         5
      55: iload         4
      57: if_icmpge     88
      60: aload_3
      61: iload         5
      63: aaload
      64: astore        6
      66: getstatic     #38                 // Field HEADER_LOG:Lorg/slf4j/Logger;
      69: ldc           #43                 // String {} >> {}
      71: aload_0
      72: getfield      #2                  // Field id:Ljava/lang/String;
      75: aload         6
      77: invokeinterface #29,  4           // InterfaceMethod org/slf4j/Logger.debug:(Ljava/lang/String;Ljava/lang/Object;Ljava/lang/Object;)V
      82: iinc          5, 1
      85: goto          53
      88: return

  public void passivate();
    Code:
       0: aload_0
       1: getstatic     #47                 // Field org/apache/hc/core5/util/Timeout.ZERO_MILLISECONDS:Lorg/apache/hc/core5/util/Timeout;
       4: invokespecial #30                 // Method org/apache/hc/core5/http/impl/io/DefaultBHttpClientConnection.setSocketTimeout:(Lorg/apache/hc/core5/util/Timeout;)V
       7: return

  public void activate();
    Code:
       0: aload_0
       1: aload_0
       2: getfield      #17                 // Field socketTimeout:Lorg/apache/hc/core5/util/Timeout;
       5: invokespecial #30                 // Method org/apache/hc/core5/http/impl/io/DefaultBHttpClientConnection.setSocketTimeout:(Lorg/apache/hc/core5/util/Timeout;)V
       8: return

  static {};
    Code:
       0: ldc_w         #48                 // class org/apache/hc/client5/http/impl/io/DefaultManagedHttpClientConnection
       3: invokestatic  #49                 // Method org/slf4j/LoggerFactory.getLogger:(Ljava/lang/Class;)Lorg/slf4j/Logger;
       6: putstatic     #23                 // Field LOG:Lorg/slf4j/Logger;
       9: ldc           #50                 // String org.apache.hc.client5.http.headers
      11: invokestatic  #51                 // Method org/slf4j/LoggerFactory.getLogger:(Ljava/lang/String;)Lorg/slf4j/Logger;
      14: putstatic     #38                 // Field HEADER_LOG:Lorg/slf4j/Logger;
      17: ldc           #52                 // String org.apache.hc.client5.http.wire
      19: invokestatic  #51                 // Method org/slf4j/LoggerFactory.getLogger:(Ljava/lang/String;)Lorg/slf4j/Logger;
      22: putstatic     #33                 // Field WIRE_LOG:Lorg/slf4j/Logger;
      25: return
}
