Compiled from "ManagedHttpClientConnectionFactory.java"
public class org.apache.hc.client5.http.impl.io.ManagedHttpClientConnectionFactory implements org.apache.hc.core5.http.io.HttpConnectionFactory<org.apache.hc.client5.http.io.ManagedHttpClientConnection> {
  private static final java.util.concurrent.atomic.AtomicLong COUNTER;

  public static final org.apache.hc.client5.http.impl.io.ManagedHttpClientConnectionFactory INSTANCE;

  private final org.apache.hc.core5.http.config.Http1Config h1Config;

  private final org.apache.hc.core5.http.config.CharCodingConfig charCodingConfig;

  private final org.apache.hc.core5.http.io.HttpMessageWriterFactory<org.apache.hc.core5.http.ClassicHttpRequest> requestWriterFactory;

  private final org.apache.hc.core5.http.io.HttpMessageParserFactory<org.apache.hc.core5.http.ClassicHttpResponse> responseParserFactory;

  private final org.apache.hc.core5.http.ContentLengthStrategy incomingContentStrategy;

  private final org.apache.hc.core5.http.ContentLengthStrategy outgoingContentStrategy;

  private final org.apache.hc.core5.http.io.ResponseOutOfOrderStrategy responseOutOfOrderStrategy;

  private org.apache.hc.client5.http.impl.io.ManagedHttpClientConnectionFactory(org.apache.hc.core5.http.config.Http1Config, org.apache.hc.core5.http.config.CharCodingConfig, org.apache.hc.core5.http.io.HttpMessageWriterFactory<org.apache.hc.core5.http.ClassicHttpRequest>, org.apache.hc.core5.http.io.HttpMessageParserFactory<org.apache.hc.core5.http.ClassicHttpResponse>, org.apache.hc.core5.http.ContentLengthStrategy, org.apache.hc.core5.http.ContentLengthStrategy, org.apache.hc.core5.http.io.ResponseOutOfOrderStrategy);
    Code:
       0: aload_0
       1: invokespecial #2                  // Method java/lang/Object."<init>":()V
       4: aload_0
       5: aload_1
       6: ifnull        13
       9: aload_1
      10: goto          16
      13: getstatic     #3                  // Field org/apache/hc/core5/http/config/Http1Config.DEFAULT:Lorg/apache/hc/core5/http/config/Http1Config;
      16: putfield      #4                  // Field h1Config:Lorg/apache/hc/core5/http/config/Http1Config;
      19: aload_0
      20: aload_2
      21: ifnull        28
      24: aload_2
      25: goto          31
      28: getstatic     #5                  // Field org/apache/hc/core5/http/config/CharCodingConfig.DEFAULT:Lorg/apache/hc/core5/http/config/CharCodingConfig;
      31: putfield      #6                  // Field charCodingConfig:Lorg/apache/hc/core5/http/config/CharCodingConfig;
      34: aload_0
      35: aload_3
      36: ifnull        43
      39: aload_3
      40: goto          46
      43: getstatic     #7                  // Field org/apache/hc/core5/http/impl/io/DefaultHttpRequestWriterFactory.INSTANCE:Lorg/apache/hc/core5/http/impl/io/DefaultHttpRequestWriterFactory;
      46: putfield      #8                  // Field requestWriterFactory:Lorg/apache/hc/core5/http/io/HttpMessageWriterFactory;
      49: aload_0
      50: aload         4
      52: ifnull        60
      55: aload         4
      57: goto          63
      60: getstatic     #9                  // Field org/apache/hc/client5/http/impl/io/DefaultHttpResponseParserFactory.INSTANCE:Lorg/apache/hc/client5/http/impl/io/DefaultHttpResponseParserFactory;
      63: putfield      #10                 // Field responseParserFactory:Lorg/apache/hc/core5/http/io/HttpMessageParserFactory;
      66: aload_0
      67: aload         5
      69: ifnull        77
      72: aload         5
      74: goto          80
      77: getstatic     #11                 // Field org/apache/hc/core5/http/impl/DefaultContentLengthStrategy.INSTANCE:Lorg/apache/hc/core5/http/impl/DefaultContentLengthStrategy;
      80: putfield      #12                 // Field incomingContentStrategy:Lorg/apache/hc/core5/http/ContentLengthStrategy;
      83: aload_0
      84: aload         6
      86: ifnull        94
      89: aload         6
      91: goto          97
      94: getstatic     #11                 // Field org/apache/hc/core5/http/impl/DefaultContentLengthStrategy.INSTANCE:Lorg/apache/hc/core5/http/impl/DefaultContentLengthStrategy;
      97: putfield      #13                 // Field outgoingContentStrategy:Lorg/apache/hc/core5/http/ContentLengthStrategy;
     100: aload_0
     101: aload         7
     103: ifnull        111
     106: aload         7
     108: goto          114
     111: getstatic     #14                 // Field org/apache/hc/core5/http/impl/io/NoResponseOutOfOrderStrategy.INSTANCE:Lorg/apache/hc/core5/http/impl/io/NoResponseOutOfOrderStrategy;
     114: putfield      #15                 // Field responseOutOfOrderStrategy:Lorg/apache/hc/core5/http/io/ResponseOutOfOrderStrategy;
     117: return

  public org.apache.hc.client5.http.impl.io.ManagedHttpClientConnectionFactory(org.apache.hc.core5.http.config.Http1Config, org.apache.hc.core5.http.config.CharCodingConfig, org.apache.hc.core5.http.io.HttpMessageWriterFactory<org.apache.hc.core5.http.ClassicHttpRequest>, org.apache.hc.core5.http.io.HttpMessageParserFactory<org.apache.hc.core5.http.ClassicHttpResponse>, org.apache.hc.core5.http.ContentLengthStrategy, org.apache.hc.core5.http.ContentLengthStrategy);
    Code:
       0: aload_0
       1: aload_1
       2: aload_2
       3: aload_3
       4: aload         4
       6: aload         5
       8: aload         6
      10: aconst_null
      11: invokespecial #1                  // Method "<init>":(Lorg/apache/hc/core5/http/config/Http1Config;Lorg/apache/hc/core5/http/config/CharCodingConfig;Lorg/apache/hc/core5/http/io/HttpMessageWriterFactory;Lorg/apache/hc/core5/http/io/HttpMessageParserFactory;Lorg/apache/hc/core5/http/ContentLengthStrategy;Lorg/apache/hc/core5/http/ContentLengthStrategy;Lorg/apache/hc/core5/http/io/ResponseOutOfOrderStrategy;)V
      14: return

  public org.apache.hc.client5.http.impl.io.ManagedHttpClientConnectionFactory(org.apache.hc.core5.http.config.Http1Config, org.apache.hc.core5.http.config.CharCodingConfig, org.apache.hc.core5.http.io.HttpMessageWriterFactory<org.apache.hc.core5.http.ClassicHttpRequest>, org.apache.hc.core5.http.io.HttpMessageParserFactory<org.apache.hc.core5.http.ClassicHttpResponse>);
    Code:
       0: aload_0
       1: aload_1
       2: aload_2
       3: aload_3
       4: aload         4
       6: aconst_null
       7: aconst_null
       8: invokespecial #16                 // Method "<init>":(Lorg/apache/hc/core5/http/config/Http1Config;Lorg/apache/hc/core5/http/config/CharCodingConfig;Lorg/apache/hc/core5/http/io/HttpMessageWriterFactory;Lorg/apache/hc/core5/http/io/HttpMessageParserFactory;Lorg/apache/hc/core5/http/ContentLengthStrategy;Lorg/apache/hc/core5/http/ContentLengthStrategy;)V
      11: return

  public org.apache.hc.client5.http.impl.io.ManagedHttpClientConnectionFactory(org.apache.hc.core5.http.config.Http1Config, org.apache.hc.core5.http.config.CharCodingConfig, org.apache.hc.core5.http.io.HttpMessageParserFactory<org.apache.hc.core5.http.ClassicHttpResponse>);
    Code:
       0: aload_0
       1: aload_1
       2: aload_2
       3: aconst_null
       4: aload_3
       5: invokespecial #17                 // Method "<init>":(Lorg/apache/hc/core5/http/config/Http1Config;Lorg/apache/hc/core5/http/config/CharCodingConfig;Lorg/apache/hc/core5/http/io/HttpMessageWriterFactory;Lorg/apache/hc/core5/http/io/HttpMessageParserFactory;)V
       8: return

  public org.apache.hc.client5.http.impl.io.ManagedHttpClientConnectionFactory();
    Code:
       0: aload_0
       1: aconst_null
       2: aconst_null
       3: aconst_null
       4: invokespecial #18                 // Method "<init>":(Lorg/apache/hc/core5/http/config/Http1Config;Lorg/apache/hc/core5/http/config/CharCodingConfig;Lorg/apache/hc/core5/http/io/HttpMessageParserFactory;)V
       7: return

  public org.apache.hc.client5.http.io.ManagedHttpClientConnection createConnection(java.net.Socket) throws java.io.IOException;
    Code:
       0: aconst_null
       1: astore_2
       2: aconst_null
       3: astore_3
       4: aload_0
       5: getfield      #6                  // Field charCodingConfig:Lorg/apache/hc/core5/http/config/CharCodingConfig;
       8: invokevirtual #19                 // Method org/apache/hc/core5/http/config/CharCodingConfig.getCharset:()Ljava/nio/charset/Charset;
      11: astore        4
      13: aload_0
      14: getfield      #6                  // Field charCodingConfig:Lorg/apache/hc/core5/http/config/CharCodingConfig;
      17: invokevirtual #20                 // Method org/apache/hc/core5/http/config/CharCodingConfig.getMalformedInputAction:()Ljava/nio/charset/CodingErrorAction;
      20: ifnull        33
      23: aload_0
      24: getfield      #6                  // Field charCodingConfig:Lorg/apache/hc/core5/http/config/CharCodingConfig;
      27: invokevirtual #20                 // Method org/apache/hc/core5/http/config/CharCodingConfig.getMalformedInputAction:()Ljava/nio/charset/CodingErrorAction;
      30: goto          36
      33: getstatic     #21                 // Field java/nio/charset/CodingErrorAction.REPORT:Ljava/nio/charset/CodingErrorAction;
      36: astore        5
      38: aload_0
      39: getfield      #6                  // Field charCodingConfig:Lorg/apache/hc/core5/http/config/CharCodingConfig;
      42: invokevirtual #22                 // Method org/apache/hc/core5/http/config/CharCodingConfig.getUnmappableInputAction:()Ljava/nio/charset/CodingErrorAction;
      45: ifnull        58
      48: aload_0
      49: getfield      #6                  // Field charCodingConfig:Lorg/apache/hc/core5/http/config/CharCodingConfig;
      52: invokevirtual #22                 // Method org/apache/hc/core5/http/config/CharCodingConfig.getUnmappableInputAction:()Ljava/nio/charset/CodingErrorAction;
      55: goto          61
      58: getstatic     #21                 // Field java/nio/charset/CodingErrorAction.REPORT:Ljava/nio/charset/CodingErrorAction;
      61: astore        6
      63: aload         4
      65: ifnull        108
      68: aload         4
      70: invokevirtual #23                 // Method java/nio/charset/Charset.newDecoder:()Ljava/nio/charset/CharsetDecoder;
      73: astore_2
      74: aload_2
      75: aload         5
      77: invokevirtual #24                 // Method java/nio/charset/CharsetDecoder.onMalformedInput:(Ljava/nio/charset/CodingErrorAction;)Ljava/nio/charset/CharsetDecoder;
      80: pop
      81: aload_2
      82: aload         6
      84: invokevirtual #25                 // Method java/nio/charset/CharsetDecoder.onUnmappableCharacter:(Ljava/nio/charset/CodingErrorAction;)Ljava/nio/charset/CharsetDecoder;
      87: pop
      88: aload         4
      90: invokevirtual #26                 // Method java/nio/charset/Charset.newEncoder:()Ljava/nio/charset/CharsetEncoder;
      93: astore_3
      94: aload_3
      95: aload         5
      97: invokevirtual #27                 // Method java/nio/charset/CharsetEncoder.onMalformedInput:(Ljava/nio/charset/CodingErrorAction;)Ljava/nio/charset/CharsetEncoder;
     100: pop
     101: aload_3
     102: aload         6
     104: invokevirtual #28                 // Method java/nio/charset/CharsetEncoder.onUnmappableCharacter:(Ljava/nio/charset/CodingErrorAction;)Ljava/nio/charset/CharsetEncoder;
     107: pop
     108: new           #29                 // class java/lang/StringBuilder
     111: dup
     112: invokespecial #30                 // Method java/lang/StringBuilder."<init>":()V
     115: ldc           #31                 // String http-outgoing-
     117: invokevirtual #32                 // Method java/lang/StringBuilder.append:(Ljava/lang/String;)Ljava/lang/StringBuilder;
     120: getstatic     #33                 // Field COUNTER:Ljava/util/concurrent/atomic/AtomicLong;
     123: invokevirtual #34                 // Method java/util/concurrent/atomic/AtomicLong.getAndIncrement:()J
     126: invokevirtual #35                 // Method java/lang/StringBuilder.append:(J)Ljava/lang/StringBuilder;
     129: invokevirtual #36                 // Method java/lang/StringBuilder.toString:()Ljava/lang/String;
     132: astore        7
     134: new           #37                 // class org/apache/hc/client5/http/impl/io/DefaultManagedHttpClientConnection
     137: dup
     138: aload         7
     140: aload_2
     141: aload_3
     142: aload_0
     143: getfield      #4                  // Field h1Config:Lorg/apache/hc/core5/http/config/Http1Config;
     146: aload_0
     147: getfield      #12                 // Field incomingContentStrategy:Lorg/apache/hc/core5/http/ContentLengthStrategy;
     150: aload_0
     151: getfield      #13                 // Field outgoingContentStrategy:Lorg/apache/hc/core5/http/ContentLengthStrategy;
     154: aload_0
     155: getfield      #15                 // Field responseOutOfOrderStrategy:Lorg/apache/hc/core5/http/io/ResponseOutOfOrderStrategy;
     158: aload_0
     159: getfield      #8                  // Field requestWriterFactory:Lorg/apache/hc/core5/http/io/HttpMessageWriterFactory;
     162: aload_0
     163: getfield      #10                 // Field responseParserFactory:Lorg/apache/hc/core5/http/io/HttpMessageParserFactory;
     166: invokespecial #38                 // Method org/apache/hc/client5/http/impl/io/DefaultManagedHttpClientConnection."<init>":(Ljava/lang/String;Ljava/nio/charset/CharsetDecoder;Ljava/nio/charset/CharsetEncoder;Lorg/apache/hc/core5/http/config/Http1Config;Lorg/apache/hc/core5/http/ContentLengthStrategy;Lorg/apache/hc/core5/http/ContentLengthStrategy;Lorg/apache/hc/core5/http/io/ResponseOutOfOrderStrategy;Lorg/apache/hc/core5/http/io/HttpMessageWriterFactory;Lorg/apache/hc/core5/http/io/HttpMessageParserFactory;)V
     169: astore        8
     171: aload_1
     172: ifnull        181
     175: aload         8
     177: aload_1
     178: invokevirtual #39                 // Method org/apache/hc/client5/http/impl/io/DefaultManagedHttpClientConnection.bind:(Ljava/net/Socket;)V
     181: aload         8
     183: areturn

  public static org.apache.hc.client5.http.impl.io.ManagedHttpClientConnectionFactory$Builder builder();
    Code:
       0: new           #40                 // class org/apache/hc/client5/http/impl/io/ManagedHttpClientConnectionFactory$Builder
       3: dup
       4: aconst_null
       5: invokespecial #41                 // Method org/apache/hc/client5/http/impl/io/ManagedHttpClientConnectionFactory$Builder."<init>":(Lorg/apache/hc/client5/http/impl/io/ManagedHttpClientConnectionFactory$1;)V
       8: areturn

  public org.apache.hc.core5.http.HttpConnection createConnection(java.net.Socket) throws java.io.IOException;
    Code:
       0: aload_0
       1: aload_1
       2: invokevirtual #42                 // Method createConnection:(Ljava/net/Socket;)Lorg/apache/hc/client5/http/io/ManagedHttpClientConnection;
       5: areturn

  org.apache.hc.client5.http.impl.io.ManagedHttpClientConnectionFactory(org.apache.hc.core5.http.config.Http1Config, org.apache.hc.core5.http.config.CharCodingConfig, org.apache.hc.core5.http.io.HttpMessageWriterFactory, org.apache.hc.core5.http.io.HttpMessageParserFactory, org.apache.hc.core5.http.ContentLengthStrategy, org.apache.hc.core5.http.ContentLengthStrategy, org.apache.hc.core5.http.io.ResponseOutOfOrderStrategy, org.apache.hc.client5.http.impl.io.ManagedHttpClientConnectionFactory$1);
    Code:
       0: aload_0
       1: aload_1
       2: aload_2
       3: aload_3
       4: aload         4
       6: aload         5
       8: aload         6
      10: aload         7
      12: invokespecial #1                  // Method "<init>":(Lorg/apache/hc/core5/http/config/Http1Config;Lorg/apache/hc/core5/http/config/CharCodingConfig;Lorg/apache/hc/core5/http/io/HttpMessageWriterFactory;Lorg/apache/hc/core5/http/io/HttpMessageParserFactory;Lorg/apache/hc/core5/http/ContentLengthStrategy;Lorg/apache/hc/core5/http/ContentLengthStrategy;Lorg/apache/hc/core5/http/io/ResponseOutOfOrderStrategy;)V
      15: return

  static {};
    Code:
       0: new           #43                 // class java/util/concurrent/atomic/AtomicLong
       3: dup
       4: invokespecial #44                 // Method java/util/concurrent/atomic/AtomicLong."<init>":()V
       7: putstatic     #33                 // Field COUNTER:Ljava/util/concurrent/atomic/AtomicLong;
      10: new           #45                 // class org/apache/hc/client5/http/impl/io/ManagedHttpClientConnectionFactory
      13: dup
      14: invokespecial #46                 // Method "<init>":()V
      17: putstatic     #47                 // Field INSTANCE:Lorg/apache/hc/client5/http/impl/io/ManagedHttpClientConnectionFactory;
      20: return
}
