Compiled from "AbstractMessageChannel.java"
public abstract class org.springframework.messaging.support.AbstractMessageChannel implements org.springframework.messaging.MessageChannel,org.springframework.messaging.support.InterceptableChannel,org.springframework.beans.factory.BeanNameAware {
  protected org.apache.commons.logging.Log logger;

  private java.lang.String beanName;

  private final java.util.List<org.springframework.messaging.support.ChannelInterceptor> interceptors;

  public org.springframework.messaging.support.AbstractMessageChannel();
    Code:
       0: aload_0
       1: invokespecial #2                  // Method java/lang/Object."<init>":()V
       4: aload_0
       5: aload_0
       6: invokevirtual #3                  // Method java/lang/Object.getClass:()Ljava/lang/Class;
       9: invokestatic  #4                  // Method org/apache/commons/logging/LogFactory.getLog:(Ljava/lang/Class;)Lorg/apache/commons/logging/Log;
      12: putfield      #5                  // Field logger:Lorg/apache/commons/logging/Log;
      15: aload_0
      16: new           #6                  // class java/util/ArrayList
      19: dup
      20: iconst_5
      21: invokespecial #7                  // Method java/util/ArrayList."<init>":(I)V
      24: putfield      #1                  // Field interceptors:Ljava/util/List;
      27: aload_0
      28: new           #8                  // class java/lang/StringBuilder
      31: dup
      32: invokespecial #9                  // Method java/lang/StringBuilder."<init>":()V
      35: aload_0
      36: invokevirtual #3                  // Method java/lang/Object.getClass:()Ljava/lang/Class;
      39: invokevirtual #10                 // Method java/lang/Class.getSimpleName:()Ljava/lang/String;
      42: invokevirtual #11                 // Method java/lang/StringBuilder.append:(Ljava/lang/String;)Ljava/lang/StringBuilder;
      45: ldc           #12                 // String @
      47: invokevirtual #11                 // Method java/lang/StringBuilder.append:(Ljava/lang/String;)Ljava/lang/StringBuilder;
      50: aload_0
      51: invokestatic  #13                 // Method org/springframework/util/ObjectUtils.getIdentityHexString:(Ljava/lang/Object;)Ljava/lang/String;
      54: invokevirtual #11                 // Method java/lang/StringBuilder.append:(Ljava/lang/String;)Ljava/lang/StringBuilder;
      57: invokevirtual #14                 // Method java/lang/StringBuilder.toString:()Ljava/lang/String;
      60: putfield      #15                 // Field beanName:Ljava/lang/String;
      63: return

  public void setLogger(org.apache.commons.logging.Log);
    Code:
       0: aload_0
       1: aload_1
       2: putfield      #5                  // Field logger:Lorg/apache/commons/logging/Log;
       5: return

  public org.apache.commons.logging.Log getLogger();
    Code:
       0: aload_0
       1: getfield      #5                  // Field logger:Lorg/apache/commons/logging/Log;
       4: areturn

  public void setBeanName(java.lang.String);
    Code:
       0: aload_0
       1: aload_1
       2: putfield      #15                 // Field beanName:Ljava/lang/String;
       5: return

  public java.lang.String getBeanName();
    Code:
       0: aload_0
       1: getfield      #15                 // Field beanName:Ljava/lang/String;
       4: areturn

  public void setInterceptors(java.util.List<org.springframework.messaging.support.ChannelInterceptor>);
    Code:
       0: aload_0
       1: getfield      #1                  // Field interceptors:Ljava/util/List;
       4: invokeinterface #16,  1           // InterfaceMethod java/util/List.clear:()V
       9: aload_0
      10: getfield      #1                  // Field interceptors:Ljava/util/List;
      13: aload_1
      14: invokeinterface #17,  2           // InterfaceMethod java/util/List.addAll:(Ljava/util/Collection;)Z
      19: pop
      20: return

  public void addInterceptor(org.springframework.messaging.support.ChannelInterceptor);
    Code:
       0: aload_0
       1: getfield      #1                  // Field interceptors:Ljava/util/List;
       4: aload_1
       5: invokeinterface #18,  2           // InterfaceMethod java/util/List.add:(Ljava/lang/Object;)Z
      10: pop
      11: return

  public void addInterceptor(int, org.springframework.messaging.support.ChannelInterceptor);
    Code:
       0: aload_0
       1: getfield      #1                  // Field interceptors:Ljava/util/List;
       4: iload_1
       5: aload_2
       6: invokeinterface #19,  3           // InterfaceMethod java/util/List.add:(ILjava/lang/Object;)V
      11: return

  public java.util.List<org.springframework.messaging.support.ChannelInterceptor> getInterceptors();
    Code:
       0: aload_0
       1: getfield      #1                  // Field interceptors:Ljava/util/List;
       4: invokestatic  #20                 // Method java/util/Collections.unmodifiableList:(Ljava/util/List;)Ljava/util/List;
       7: areturn

  public boolean removeInterceptor(org.springframework.messaging.support.ChannelInterceptor);
    Code:
       0: aload_0
       1: getfield      #1                  // Field interceptors:Ljava/util/List;
       4: aload_1
       5: invokeinterface #21,  2           // InterfaceMethod java/util/List.remove:(Ljava/lang/Object;)Z
      10: ireturn

  public org.springframework.messaging.support.ChannelInterceptor removeInterceptor(int);
    Code:
       0: aload_0
       1: getfield      #1                  // Field interceptors:Ljava/util/List;
       4: iload_1
       5: invokeinterface #22,  2           // InterfaceMethod java/util/List.remove:(I)Ljava/lang/Object;
      10: checkcast     #23                 // class org/springframework/messaging/support/ChannelInterceptor
      13: areturn

  public final boolean send(org.springframework.messaging.Message<?>);
    Code:
       0: aload_0
       1: aload_1
       2: ldc2_w        #25                 // long -1l
       5: invokevirtual #27                 // Method send:(Lorg/springframework/messaging/Message;J)Z
       8: ireturn

  public final boolean send(org.springframework.messaging.Message<?>, long);
    Code:
       0: aload_1
       1: ldc           #28                 // String Message must not be null
       3: invokestatic  #29                 // Method org/springframework/util/Assert.notNull:(Ljava/lang/Object;Ljava/lang/String;)V
       6: aload_1
       7: astore        4
       9: new           #30                 // class org/springframework/messaging/support/AbstractMessageChannel$ChannelInterceptorChain
      12: dup
      13: aload_0
      14: invokespecial #31                 // Method org/springframework/messaging/support/AbstractMessageChannel$ChannelInterceptorChain."<init>":(Lorg/springframework/messaging/support/AbstractMessageChannel;)V
      17: astore        5
      19: iconst_0
      20: istore        6
      22: aload         5
      24: aload         4
      26: aload_0
      27: invokevirtual #32                 // Method org/springframework/messaging/support/AbstractMessageChannel$ChannelInterceptorChain.applyPreSend:(Lorg/springframework/messaging/Message;Lorg/springframework/messaging/MessageChannel;)Lorg/springframework/messaging/Message;
      30: astore        4
      32: aload         4
      34: ifnonnull     39
      37: iconst_0
      38: ireturn
      39: aload_0
      40: aload         4
      42: lload_2
      43: invokevirtual #33                 // Method sendInternal:(Lorg/springframework/messaging/Message;J)Z
      46: istore        6
      48: aload         5
      50: aload         4
      52: aload_0
      53: iload         6
      55: invokevirtual #34                 // Method org/springframework/messaging/support/AbstractMessageChannel$ChannelInterceptorChain.applyPostSend:(Lorg/springframework/messaging/Message;Lorg/springframework/messaging/MessageChannel;Z)V
      58: aload         5
      60: aload         4
      62: aload_0
      63: iload         6
      65: aconst_null
      66: invokevirtual #35                 // Method org/springframework/messaging/support/AbstractMessageChannel$ChannelInterceptorChain.triggerAfterSendCompletion:(Lorg/springframework/messaging/Message;Lorg/springframework/messaging/MessageChannel;ZLjava/lang/Exception;)V
      69: iload         6
      71: ireturn
      72: astore        7
      74: aload         5
      76: aload         4
      78: aload_0
      79: iload         6
      81: aload         7
      83: invokevirtual #35                 // Method org/springframework/messaging/support/AbstractMessageChannel$ChannelInterceptorChain.triggerAfterSendCompletion:(Lorg/springframework/messaging/Message;Lorg/springframework/messaging/MessageChannel;ZLjava/lang/Exception;)V
      86: aload         7
      88: instanceof    #37                 // class org/springframework/messaging/MessagingException
      91: ifeq          100
      94: aload         7
      96: checkcast     #37                 // class org/springframework/messaging/MessagingException
      99: athrow
     100: new           #38                 // class org/springframework/messaging/MessageDeliveryException
     103: dup
     104: aload         4
     106: new           #8                  // class java/lang/StringBuilder
     109: dup
     110: invokespecial #9                  // Method java/lang/StringBuilder."<init>":()V
     113: ldc           #39                 // String Failed to send message to
     115: invokevirtual #11                 // Method java/lang/StringBuilder.append:(Ljava/lang/String;)Ljava/lang/StringBuilder;
     118: aload_0
     119: invokevirtual #40                 // Method java/lang/StringBuilder.append:(Ljava/lang/Object;)Ljava/lang/StringBuilder;
     122: invokevirtual #14                 // Method java/lang/StringBuilder.toString:()Ljava/lang/String;
     125: aload         7
     127: invokespecial #41                 // Method org/springframework/messaging/MessageDeliveryException."<init>":(Lorg/springframework/messaging/Message;Ljava/lang/String;Ljava/lang/Throwable;)V
     130: athrow
     131: astore        7
     133: new           #38                 // class org/springframework/messaging/MessageDeliveryException
     136: dup
     137: aload         4
     139: new           #8                  // class java/lang/StringBuilder
     142: dup
     143: invokespecial #9                  // Method java/lang/StringBuilder."<init>":()V
     146: ldc           #39                 // String Failed to send message to
     148: invokevirtual #11                 // Method java/lang/StringBuilder.append:(Ljava/lang/String;)Ljava/lang/StringBuilder;
     151: aload_0
     152: invokevirtual #40                 // Method java/lang/StringBuilder.append:(Ljava/lang/Object;)Ljava/lang/StringBuilder;
     155: invokevirtual #14                 // Method java/lang/StringBuilder.toString:()Ljava/lang/String;
     158: aload         7
     160: invokespecial #41                 // Method org/springframework/messaging/MessageDeliveryException."<init>":(Lorg/springframework/messaging/Message;Ljava/lang/String;Ljava/lang/Throwable;)V
     163: astore        8
     165: aload         5
     167: aload         4
     169: aload_0
     170: iload         6
     172: aload         8
     174: invokevirtual #35                 // Method org/springframework/messaging/support/AbstractMessageChannel$ChannelInterceptorChain.triggerAfterSendCompletion:(Lorg/springframework/messaging/Message;Lorg/springframework/messaging/MessageChannel;ZLjava/lang/Exception;)V
     177: aload         8
     179: athrow
    Exception table:
       from    to  target type
          22    38    72   Class java/lang/Exception
          39    71    72   Class java/lang/Exception
          22    38   131   Class java/lang/Throwable
          39    71   131   Class java/lang/Throwable

  protected abstract boolean sendInternal(org.springframework.messaging.Message<?>, long);

  public java.lang.String toString();
    Code:
       0: new           #8                  // class java/lang/StringBuilder
       3: dup
       4: invokespecial #9                  // Method java/lang/StringBuilder."<init>":()V
       7: aload_0
       8: invokevirtual #3                  // Method java/lang/Object.getClass:()Ljava/lang/Class;
      11: invokevirtual #10                 // Method java/lang/Class.getSimpleName:()Ljava/lang/String;
      14: invokevirtual #11                 // Method java/lang/StringBuilder.append:(Ljava/lang/String;)Ljava/lang/StringBuilder;
      17: ldc           #43                 // String [
      19: invokevirtual #11                 // Method java/lang/StringBuilder.append:(Ljava/lang/String;)Ljava/lang/StringBuilder;
      22: aload_0
      23: getfield      #15                 // Field beanName:Ljava/lang/String;
      26: invokevirtual #11                 // Method java/lang/StringBuilder.append:(Ljava/lang/String;)Ljava/lang/StringBuilder;
      29: ldc           #44                 // String ]
      31: invokevirtual #11                 // Method java/lang/StringBuilder.append:(Ljava/lang/String;)Ljava/lang/StringBuilder;
      34: invokevirtual #14                 // Method java/lang/StringBuilder.toString:()Ljava/lang/String;
      37: areturn

  static java.util.List access$000(org.springframework.messaging.support.AbstractMessageChannel);
    Code:
       0: aload_0
       1: getfield      #1                  // Field interceptors:Ljava/util/List;
       4: areturn
}
