Compiled from "Event.java"
public class org.apache.hadoop.mapreduce.jobhistory.Event extends org.apache.avro.specific.SpecificRecordBase implements org.apache.avro.specific.SpecificRecord {
  public static final org.apache.avro.Schema SCHEMA$;

  public org.apache.hadoop.mapreduce.jobhistory.EventType type;

  public java.lang.Object event;

  public static org.apache.avro.Schema getClassSchema();
    Code:
       0: getstatic     #1                  // Field SCHEMA$:Lorg/apache/avro/Schema;
       3: areturn

  public org.apache.hadoop.mapreduce.jobhistory.Event();
    Code:
       0: aload_0
       1: invokespecial #2                  // Method org/apache/avro/specific/SpecificRecordBase."<init>":()V
       4: return

  public org.apache.hadoop.mapreduce.jobhistory.Event(org.apache.hadoop.mapreduce.jobhistory.EventType, java.lang.Object);
    Code:
       0: aload_0
       1: invokespecial #2                  // Method org/apache/avro/specific/SpecificRecordBase."<init>":()V
       4: aload_0
       5: aload_1
       6: putfield      #3                  // Field type:Lorg/apache/hadoop/mapreduce/jobhistory/EventType;
       9: aload_0
      10: aload_2
      11: putfield      #4                  // Field event:Ljava/lang/Object;
      14: return

  public org.apache.avro.Schema getSchema();
    Code:
       0: getstatic     #1                  // Field SCHEMA$:Lorg/apache/avro/Schema;
       3: areturn

  public java.lang.Object get(int);
    Code:
       0: iload_1
       1: lookupswitch  { // 2
                     0: 28
                     1: 33
               default: 38
          }
      28: aload_0
      29: getfield      #3                  // Field type:Lorg/apache/hadoop/mapreduce/jobhistory/EventType;
      32: areturn
      33: aload_0
      34: getfield      #4                  // Field event:Ljava/lang/Object;
      37: areturn
      38: new           #5                  // class org/apache/avro/AvroRuntimeException
      41: dup
      42: ldc           #6                  // String Bad index
      44: invokespecial #7                  // Method org/apache/avro/AvroRuntimeException."<init>":(Ljava/lang/String;)V
      47: athrow

  public void put(int, java.lang.Object);
    Code:
       0: iload_1
       1: lookupswitch  { // 2
                     0: 28
                     1: 39
               default: 47
          }
      28: aload_0
      29: aload_2
      30: checkcast     #8                  // class org/apache/hadoop/mapreduce/jobhistory/EventType
      33: putfield      #3                  // Field type:Lorg/apache/hadoop/mapreduce/jobhistory/EventType;
      36: goto          57
      39: aload_0
      40: aload_2
      41: putfield      #4                  // Field event:Ljava/lang/Object;
      44: goto          57
      47: new           #5                  // class org/apache/avro/AvroRuntimeException
      50: dup
      51: ldc           #6                  // String Bad index
      53: invokespecial #7                  // Method org/apache/avro/AvroRuntimeException."<init>":(Ljava/lang/String;)V
      56: athrow
      57: return

  public org.apache.hadoop.mapreduce.jobhistory.EventType getType();
    Code:
       0: aload_0
       1: getfield      #3                  // Field type:Lorg/apache/hadoop/mapreduce/jobhistory/EventType;
       4: areturn

  public void setType(org.apache.hadoop.mapreduce.jobhistory.EventType);
    Code:
       0: aload_0
       1: aload_1
       2: putfield      #3                  // Field type:Lorg/apache/hadoop/mapreduce/jobhistory/EventType;
       5: return

  public java.lang.Object getEvent();
    Code:
       0: aload_0
       1: getfield      #4                  // Field event:Ljava/lang/Object;
       4: areturn

  public void setEvent(java.lang.Object);
    Code:
       0: aload_0
       1: aload_1
       2: putfield      #4                  // Field event:Ljava/lang/Object;
       5: return

  public static org.apache.hadoop.mapreduce.jobhistory.Event$Builder newBuilder();
    Code:
       0: new           #9                  // class org/apache/hadoop/mapreduce/jobhistory/Event$Builder
       3: dup
       4: aconst_null
       5: invokespecial #10                 // Method org/apache/hadoop/mapreduce/jobhistory/Event$Builder."<init>":(Lorg/apache/hadoop/mapreduce/jobhistory/Event$1;)V
       8: areturn

  public static org.apache.hadoop.mapreduce.jobhistory.Event$Builder newBuilder(org.apache.hadoop.mapreduce.jobhistory.Event$Builder);
    Code:
       0: new           #9                  // class org/apache/hadoop/mapreduce/jobhistory/Event$Builder
       3: dup
       4: aload_0
       5: aconst_null
       6: invokespecial #11                 // Method org/apache/hadoop/mapreduce/jobhistory/Event$Builder."<init>":(Lorg/apache/hadoop/mapreduce/jobhistory/Event$Builder;Lorg/apache/hadoop/mapreduce/jobhistory/Event$1;)V
       9: areturn

  public static org.apache.hadoop.mapreduce.jobhistory.Event$Builder newBuilder(org.apache.hadoop.mapreduce.jobhistory.Event);
    Code:
       0: new           #9                  // class org/apache/hadoop/mapreduce/jobhistory/Event$Builder
       3: dup
       4: aload_0
       5: aconst_null
       6: invokespecial #12                 // Method org/apache/hadoop/mapreduce/jobhistory/Event$Builder."<init>":(Lorg/apache/hadoop/mapreduce/jobhistory/Event;Lorg/apache/hadoop/mapreduce/jobhistory/Event$1;)V
       9: areturn

  static {};
    Code:
       0: new           #13                 // class org/apache/avro/Schema$Parser
       3: dup
       4: invokespecial #14                 // Method org/apache/avro/Schema$Parser."<init>":()V
       7: ldc           #15                 // String {\"type\":\"record\",\"name\":\"Event\",\"namespace\":\"org.apache.hadoop.mapreduce.jobhistory\",\"fields\":[{\"name\":\"type\",\"type\":{\"type\":\"enum\",\"name\":\"EventType\",\"symbols\":[\"JOB_SUBMITTED\",\"JOB_INITED\",\"JOB_FINISHED\",\"JOB_PRIORITY_CHANGED\",\"JOB_STATUS_CHANGED\",\"JOB_QUEUE_CHANGED\",\"JOB_FAILED\",\"JOB_KILLED\",\"JOB_ERROR\",\"JOB_INFO_CHANGED\",\"TASK_STARTED\",\"TASK_FINISHED\",\"TASK_FAILED\",\"TASK_UPDATED\",\"NORMALIZED_RESOURCE\",\"MAP_ATTEMPT_STARTED\",\"MAP_ATTEMPT_FINISHED\",\"MAP_ATTEMPT_FAILED\",\"MAP_ATTEMPT_KILLED\",\"REDUCE_ATTEMPT_STARTED\",\"REDUCE_ATTEMPT_FINISHED\",\"REDUCE_ATTEMPT_FAILED\",\"REDUCE_ATTEMPT_KILLED\",\"SETUP_ATTEMPT_STARTED\",\"SETUP_ATTEMPT_FINISHED\",\"SETUP_ATTEMPT_FAILED\",\"SETUP_ATTEMPT_KILLED\",\"CLEANUP_ATTEMPT_STARTED\",\"CLEANUP_ATTEMPT_FINISHED\",\"CLEANUP_ATTEMPT_FAILED\",\"CLEANUP_ATTEMPT_KILLED\",\"AM_STARTED\"]}},{\"name\":\"event\",\"type\":[{\"type\":\"record\",\"name\":\"JobFinished\",\"fields\":[{\"name\":\"jobid\",\"type\":\"string\"},{\"name\":\"finishTime\",\"type\":\"long\"},{\"name\":\"finishedMaps\",\"type\":\"int\"},{\"name\":\"finishedReduces\",\"type\":\"int\"},{\"name\":\"failedMaps\",\"type\":\"int\"},{\"name\":\"failedReduces\",\"type\":\"int\"},{\"name\":\"totalCounters\",\"type\":{\"type\":\"record\",\"name\":\"JhCounters\",\"fields\":[{\"name\":\"name\",\"type\":\"string\"},{\"name\":\"groups\",\"type\":{\"type\":\"array\",\"items\":{\"type\":\"record\",\"name\":\"JhCounterGroup\",\"fields\":[{\"name\":\"name\",\"type\":\"string\"},{\"name\":\"displayName\",\"type\":\"string\"},{\"name\":\"counts\",\"type\":{\"type\":\"array\",\"items\":{\"type\":\"record\",\"name\":\"JhCounter\",\"fields\":[{\"name\":\"name\",\"type\":\"string\"},{\"name\":\"displayName\",\"type\":\"string\"},{\"name\":\"value\",\"type\":\"long\"}]}}}]}}}]}},{\"name\":\"mapCounters\",\"type\":\"JhCounters\"},{\"name\":\"reduceCounters\",\"type\":\"JhCounters\"},{\"name\":\"killedMaps\",\"type\":\"int\",\"default\":-1},{\"name\":\"killedReduces\",\"type\":\"int\",\"default\":-1}]},{\"type\":\"record\",\"name\":\"JobInfoChange\",\"fields\":[{\"name\":\"jobid\",\"type\":\"string\"},{\"name\":\"submitTime\",\"type\":\"long\"},{\"name\":\"launchTime\",\"type\":\"long\"}]},{\"type\":\"record\",\"name\":\"JobInited\",\"fields\":[{\"name\":\"jobid\",\"type\":\"string\"},{\"name\":\"launchTime\",\"type\":\"long\"},{\"name\":\"totalMaps\",\"type\":\"int\"},{\"name\":\"totalReduces\",\"type\":\"int\"},{\"name\":\"jobStatus\",\"type\":\"string\"},{\"name\":\"uberized\",\"type\":\"boolean\"}]},{\"type\":\"record\",\"name\":\"AMStarted\",\"fields\":[{\"name\":\"applicationAttemptId\",\"type\":\"string\"},{\"name\":\"startTime\",\"type\":\"long\"},{\"name\":\"containerId\",\"type\":\"string\"},{\"name\":\"nodeManagerHost\",\"type\":\"string\"},{\"name\":\"nodeManagerPort\",\"type\":\"int\"},{\"name\":\"nodeManagerHttpPort\",\"type\":\"int\"}]},{\"type\":\"record\",\"name\":\"JobPriorityChange\",\"fields\":[{\"name\":\"jobid\",\"type\":\"string\"},{\"name\":\"priority\",\"type\":\"string\"}]},{\"type\":\"record\",\"name\":\"JobQueueChange\",\"fields\":[{\"name\":\"jobid\",\"type\":\"string\"},{\"name\":\"jobQueueName\",\"type\":\"string\"}]},{\"type\":\"record\",\"name\":\"JobStatusChanged\",\"fields\":[{\"name\":\"jobid\",\"type\":\"string\"},{\"name\":\"jobStatus\",\"type\":\"string\"}]},{\"type\":\"record\",\"name\":\"JobSubmitted\",\"fields\":[{\"name\":\"jobid\",\"type\":\"string\"},{\"name\":\"jobName\",\"type\":\"string\"},{\"name\":\"userName\",\"type\":\"string\"},{\"name\":\"submitTime\",\"type\":\"long\"},{\"name\":\"jobConfPath\",\"type\":\"string\"},{\"name\":\"acls\",\"type\":{\"type\":\"map\",\"values\":\"string\"}},{\"name\":\"jobQueueName\",\"type\":\"string\"},{\"name\":\"workflowId\",\"type\":[\"null\",\"string\"],\"default\":null},{\"name\":\"workflowName\",\"type\":[\"null\",\"string\"],\"default\":null},{\"name\":\"workflowNodeName\",\"type\":[\"null\",\"string\"],\"default\":null},{\"name\":\"workflowAdjacencies\",\"type\":[\"null\",\"string\"],\"default\":null},{\"name\":\"workflowTags\",\"type\":[\"null\",\"string\"],\"default\":null}]},{\"type\":\"record\",\"name\":\"JobUnsuccessfulCompletion\",\"fields\":[{\"name\":\"jobid\",\"type\":\"string\"},{\"name\":\"finishTime\",\"type\":\"long\"},{\"name\":\"finishedMaps\",\"type\":\"int\"},{\"name\":\"finishedReduces\",\"type\":\"int\"},{\"name\":\"jobStatus\",\"type\":\"string\"},{\"name\":\"diagnostics\",\"type\":[\"null\",\"string\"],\"default\":null},{\"name\":\"failedMaps\",\"type\":\"int\",\"default\":-1},{\"name\":\"failedReduces\",\"type\":\"int\",\"default\":-1},{\"name\":\"killedMaps\",\"type\":\"int\",\"default\":-1},{\"name\":\"killedReduces\",\"type\":\"int\",\"default\":-1}]},{\"type\":\"record\",\"name\":\"MapAttemptFinished\",\"fields\":[{\"name\":\"taskid\",\"type\":\"string\"},{\"name\":\"attemptId\",\"type\":\"string\"},{\"name\":\"taskType\",\"type\":\"string\"},{\"name\":\"taskStatus\",\"type\":\"string\"},{\"name\":\"mapFinishTime\",\"type\":\"long\"},{\"name\":\"finishTime\",\"type\":\"long\"},{\"name\":\"hostname\",\"type\":\"string\"},{\"name\":\"port\",\"type\":\"int\"},{\"name\":\"rackname\",\"type\":\"string\"},{\"name\":\"state\",\"type\":\"string\"},{\"name\":\"counters\",\"type\":\"JhCounters\"},{\"name\":\"clockSplits\",\"type\":{\"type\":\"array\",\"items\":\"int\"}},{\"name\":\"cpuUsages\",\"type\":{\"type\":\"array\",\"items\":\"int\"}},{\"name\":\"vMemKbytes\",\"type\":{\"type\":\"array\",\"items\":\"int\"}},{\"name\":\"physMemKbytes\",\"type\":{\"type\":\"array\",\"items\":\"int\"}}]},{\"type\":\"record\",\"name\":\"ReduceAttemptFinished\",\"fields\":[{\"name\":\"taskid\",\"type\":\"string\"},{\"name\":\"attemptId\",\"type\":\"string\"},{\"name\":\"taskType\",\"type\":\"string\"},{\"name\":\"taskStatus\",\"type\":\"string\"},{\"name\":\"shuffleFinishTime\",\"type\":\"long\"},{\"name\":\"sortFinishTime\",\"type\":\"long\"},{\"name\":\"finishTime\",\"type\":\"long\"},{\"name\":\"hostname\",\"type\":\"string\"},{\"name\":\"port\",\"type\":\"int\"},{\"name\":\"rackname\",\"type\":\"string\"},{\"name\":\"state\",\"type\":\"string\"},{\"name\":\"counters\",\"type\":\"JhCounters\"},{\"name\":\"clockSplits\",\"type\":{\"type\":\"array\",\"items\":\"int\"}},{\"name\":\"cpuUsages\",\"type\":{\"type\":\"array\",\"items\":\"int\"}},{\"name\":\"vMemKbytes\",\"type\":{\"type\":\"array\",\"items\":\"int\"}},{\"name\":\"physMemKbytes\",\"type\":{\"type\":\"array\",\"items\":\"int\"}}]},{\"type\":\"record\",\"name\":\"TaskAttemptFinished\",\"fields\":[{\"name\":\"taskid\",\"type\":\"string\"},{\"name\":\"attemptId\",\"type\":\"string\"},{\"name\":\"taskType\",\"type\":\"string\"},{\"name\":\"taskStatus\",\"type\":\"string\"},{\"name\":\"finishTime\",\"type\":\"long\"},{\"name\":\"rackname\",\"type\":\"string\"},{\"name\":\"hostname\",\"type\":\"string\"},{\"name\":\"state\",\"type\":\"string\"},{\"name\":\"counters\",\"type\":\"JhCounters\"}]},{\"type\":\"record\",\"name\":\"TaskAttemptStarted\",\"fields\":[{\"name\":\"taskid\",\"type\":\"string\"},{\"name\":\"taskType\",\"type\":\"string\"},{\"name\":\"attemptId\",\"type\":\"string\"},{\"name\":\"startTime\",\"type\":\"long\"},{\"name\":\"trackerName\",\"type\":\"string\"},{\"name\":\"httpPort\",\"type\":\"int\"},{\"name\":\"shufflePort\",\"type\":\"int\"},{\"name\":\"containerId\",\"type\":\"string\"},{\"name\":\"locality\",\"type\":[\"null\",\"string\"],\"default\":null},{\"name\":\"avataar\",\"type\":[\"null\",\"string\"],\"default\":null}]},{\"type\":\"record\",\"name\":\"TaskAttemptUnsuccessfulCompletion\",\"fields\":[{\"name\":\"taskid\",\"type\":\"string\"},{\"name\":\"taskType\",\"type\":\"string\"},{\"name\":\"attemptId\",\"type\":\"string\"},{\"name\":\"finishTime\",\"type\":\"long\"},{\"name\":\"hostname\",\"type\":\"string\"},{\"name\":\"port\",\"type\":\"int\"},{\"name\":\"rackname\",\"type\":\"string\"},{\"name\":\"status\",\"type\":\"string\"},{\"name\":\"error\",\"type\":\"string\"},{\"name\":\"counters\",\"type\":[\"null\",\"JhCounters\"],\"default\":null},{\"name\":\"clockSplits\",\"type\":{\"type\":\"array\",\"items\":\"int\"}},{\"name\":\"cpuUsages\",\"type\":{\"type\":\"array\",\"items\":\"int\"}},{\"name\":\"vMemKbytes\",\"type\":{\"type\":\"array\",\"items\":\"int\"}},{\"name\":\"physMemKbytes\",\"type\":{\"type\":\"array\",\"items\":\"int\"}}]},{\"type\":\"record\",\"name\":\"TaskFailed\",\"fields\":[{\"name\":\"taskid\",\"type\":\"string\"},{\"name\":\"taskType\",\"type\":\"string\"},{\"name\":\"finishTime\",\"type\":\"long\"},{\"name\":\"error\",\"type\":\"string\"},{\"name\":\"failedDueToAttempt\",\"type\":[\"null\",\"string\"]},{\"name\":\"status\",\"type\":\"string\"},{\"name\":\"counters\",\"type\":[\"null\",\"JhCounters\"],\"default\":null}]},{\"type\":\"record\",\"name\":\"TaskFinished\",\"fields\":[{\"name\":\"taskid\",\"type\":\"string\"},{\"name\":\"taskType\",\"type\":\"string\"},{\"name\":\"finishTime\",\"type\":\"long\"},{\"name\":\"status\",\"type\":\"string\"},{\"name\":\"counters\",\"type\":\"JhCounters\"},{\"name\":\"successfulAttemptId\",\"type\":[\"null\",\"string\"],\"default\":null}]},{\"type\":\"record\",\"name\":\"TaskStarted\",\"fields\":[{\"name\":\"taskid\",\"type\":\"string\"},{\"name\":\"taskType\",\"type\":\"string\"},{\"name\":\"startTime\",\"type\":\"long\"},{\"name\":\"splitLocations\",\"type\":\"string\"}]},{\"type\":\"record\",\"name\":\"TaskUpdated\",\"fields\":[{\"name\":\"taskid\",\"type\":\"string\"},{\"name\":\"finishTime\",\"type\":\"long\"}]}]}]}
       9: invokevirtual #16                 // Method org/apache/avro/Schema$Parser.parse:(Ljava/lang/String;)Lorg/apache/avro/Schema;
      12: putstatic     #1                  // Field SCHEMA$:Lorg/apache/avro/Schema;
      15: return
}
