Compiled from "JobHistoryParser.java"
public class org.apache.hadoop.mapreduce.jobhistory.JobHistoryParser$AMInfo {
  org.apache.hadoop.yarn.api.records.ApplicationAttemptId appAttemptId;

  long startTime;

  org.apache.hadoop.yarn.api.records.ContainerId containerId;

  java.lang.String nodeManagerHost;

  int nodeManagerPort;

  int nodeManagerHttpPort;

  public org.apache.hadoop.mapreduce.jobhistory.JobHistoryParser$AMInfo();
    Code:
       0: aload_0
       1: invokespecial #1                  // Method java/lang/Object."<init>":()V
       4: aload_0
       5: ldc2_w        #2                  // long -1l
       8: putfield      #4                  // Field startTime:J
      11: aload_0
      12: ldc           #5                  // String
      14: putfield      #6                  // Field nodeManagerHost:Ljava/lang/String;
      17: aload_0
      18: iconst_m1
      19: putfield      #7                  // Field nodeManagerHttpPort:I
      22: return

  public org.apache.hadoop.mapreduce.jobhistory.JobHistoryParser$AMInfo(org.apache.hadoop.yarn.api.records.ApplicationAttemptId, long, org.apache.hadoop.yarn.api.records.ContainerId, java.lang.String, int, int);
    Code:
       0: aload_0
       1: invokespecial #1                  // Method java/lang/Object."<init>":()V
       4: aload_0
       5: aload_1
       6: putfield      #8                  // Field appAttemptId:Lorg/apache/hadoop/yarn/api/records/ApplicationAttemptId;
       9: aload_0
      10: lload_2
      11: putfield      #4                  // Field startTime:J
      14: aload_0
      15: aload         4
      17: putfield      #9                  // Field containerId:Lorg/apache/hadoop/yarn/api/records/ContainerId;
      20: aload_0
      21: aload         5
      23: putfield      #6                  // Field nodeManagerHost:Ljava/lang/String;
      26: aload_0
      27: iload         6
      29: putfield      #10                 // Field nodeManagerPort:I
      32: aload_0
      33: iload         7
      35: putfield      #7                  // Field nodeManagerHttpPort:I
      38: return

  public void printAll();
    Code:
       0: getstatic     #11                 // Field java/lang/System.out:Ljava/io/PrintStream;
       3: new           #12                 // class java/lang/StringBuilder
       6: dup
       7: invokespecial #13                 // Method java/lang/StringBuilder."<init>":()V
      10: ldc           #14                 // String APPLICATION_ATTEMPT_ID:
      12: invokevirtual #15                 // Method java/lang/StringBuilder.append:(Ljava/lang/String;)Ljava/lang/StringBuilder;
      15: aload_0
      16: getfield      #8                  // Field appAttemptId:Lorg/apache/hadoop/yarn/api/records/ApplicationAttemptId;
      19: invokevirtual #16                 // Method org/apache/hadoop/yarn/api/records/ApplicationAttemptId.toString:()Ljava/lang/String;
      22: invokevirtual #15                 // Method java/lang/StringBuilder.append:(Ljava/lang/String;)Ljava/lang/StringBuilder;
      25: invokevirtual #17                 // Method java/lang/StringBuilder.toString:()Ljava/lang/String;
      28: invokevirtual #18                 // Method java/io/PrintStream.println:(Ljava/lang/String;)V
      31: getstatic     #11                 // Field java/lang/System.out:Ljava/io/PrintStream;
      34: new           #12                 // class java/lang/StringBuilder
      37: dup
      38: invokespecial #13                 // Method java/lang/StringBuilder."<init>":()V
      41: ldc           #19                 // String START_TIME:
      43: invokevirtual #15                 // Method java/lang/StringBuilder.append:(Ljava/lang/String;)Ljava/lang/StringBuilder;
      46: aload_0
      47: getfield      #4                  // Field startTime:J
      50: invokevirtual #20                 // Method java/lang/StringBuilder.append:(J)Ljava/lang/StringBuilder;
      53: invokevirtual #17                 // Method java/lang/StringBuilder.toString:()Ljava/lang/String;
      56: invokevirtual #18                 // Method java/io/PrintStream.println:(Ljava/lang/String;)V
      59: getstatic     #11                 // Field java/lang/System.out:Ljava/io/PrintStream;
      62: new           #12                 // class java/lang/StringBuilder
      65: dup
      66: invokespecial #13                 // Method java/lang/StringBuilder."<init>":()V
      69: ldc           #21                 // String CONTAINER_ID:
      71: invokevirtual #15                 // Method java/lang/StringBuilder.append:(Ljava/lang/String;)Ljava/lang/StringBuilder;
      74: aload_0
      75: getfield      #9                  // Field containerId:Lorg/apache/hadoop/yarn/api/records/ContainerId;
      78: invokevirtual #22                 // Method org/apache/hadoop/yarn/api/records/ContainerId.toString:()Ljava/lang/String;
      81: invokevirtual #15                 // Method java/lang/StringBuilder.append:(Ljava/lang/String;)Ljava/lang/StringBuilder;
      84: invokevirtual #17                 // Method java/lang/StringBuilder.toString:()Ljava/lang/String;
      87: invokevirtual #18                 // Method java/io/PrintStream.println:(Ljava/lang/String;)V
      90: getstatic     #11                 // Field java/lang/System.out:Ljava/io/PrintStream;
      93: new           #12                 // class java/lang/StringBuilder
      96: dup
      97: invokespecial #13                 // Method java/lang/StringBuilder."<init>":()V
     100: ldc           #23                 // String NODE_MANAGER_HOST:
     102: invokevirtual #15                 // Method java/lang/StringBuilder.append:(Ljava/lang/String;)Ljava/lang/StringBuilder;
     105: aload_0
     106: getfield      #6                  // Field nodeManagerHost:Ljava/lang/String;
     109: invokevirtual #15                 // Method java/lang/StringBuilder.append:(Ljava/lang/String;)Ljava/lang/StringBuilder;
     112: invokevirtual #17                 // Method java/lang/StringBuilder.toString:()Ljava/lang/String;
     115: invokevirtual #18                 // Method java/io/PrintStream.println:(Ljava/lang/String;)V
     118: getstatic     #11                 // Field java/lang/System.out:Ljava/io/PrintStream;
     121: new           #12                 // class java/lang/StringBuilder
     124: dup
     125: invokespecial #13                 // Method java/lang/StringBuilder."<init>":()V
     128: ldc           #24                 // String NODE_MANAGER_PORT:
     130: invokevirtual #15                 // Method java/lang/StringBuilder.append:(Ljava/lang/String;)Ljava/lang/StringBuilder;
     133: aload_0
     134: getfield      #10                 // Field nodeManagerPort:I
     137: invokevirtual #25                 // Method java/lang/StringBuilder.append:(I)Ljava/lang/StringBuilder;
     140: invokevirtual #17                 // Method java/lang/StringBuilder.toString:()Ljava/lang/String;
     143: invokevirtual #18                 // Method java/io/PrintStream.println:(Ljava/lang/String;)V
     146: getstatic     #11                 // Field java/lang/System.out:Ljava/io/PrintStream;
     149: new           #12                 // class java/lang/StringBuilder
     152: dup
     153: invokespecial #13                 // Method java/lang/StringBuilder."<init>":()V
     156: ldc           #26                 // String NODE_MANAGER_HTTP_PORT:
     158: invokevirtual #15                 // Method java/lang/StringBuilder.append:(Ljava/lang/String;)Ljava/lang/StringBuilder;
     161: aload_0
     162: getfield      #7                  // Field nodeManagerHttpPort:I
     165: invokevirtual #25                 // Method java/lang/StringBuilder.append:(I)Ljava/lang/StringBuilder;
     168: invokevirtual #17                 // Method java/lang/StringBuilder.toString:()Ljava/lang/String;
     171: invokevirtual #18                 // Method java/io/PrintStream.println:(Ljava/lang/String;)V
     174: return

  public org.apache.hadoop.yarn.api.records.ApplicationAttemptId getAppAttemptId();
    Code:
       0: aload_0
       1: getfield      #8                  // Field appAttemptId:Lorg/apache/hadoop/yarn/api/records/ApplicationAttemptId;
       4: areturn

  public long getStartTime();
    Code:
       0: aload_0
       1: getfield      #4                  // Field startTime:J
       4: lreturn

  public org.apache.hadoop.yarn.api.records.ContainerId getContainerId();
    Code:
       0: aload_0
       1: getfield      #9                  // Field containerId:Lorg/apache/hadoop/yarn/api/records/ContainerId;
       4: areturn

  public java.lang.String getNodeManagerHost();
    Code:
       0: aload_0
       1: getfield      #6                  // Field nodeManagerHost:Ljava/lang/String;
       4: areturn

  public int getNodeManagerPort();
    Code:
       0: aload_0
       1: getfield      #10                 // Field nodeManagerPort:I
       4: ireturn

  public int getNodeManagerHttpPort();
    Code:
       0: aload_0
       1: getfield      #7                  // Field nodeManagerHttpPort:I
       4: ireturn
}
