Compiled from "JobSubmittedEvent.java"
public class org.apache.hadoop.mapreduce.jobhistory.JobSubmittedEvent implements org.apache.hadoop.mapreduce.jobhistory.HistoryEvent {
  private org.apache.hadoop.mapreduce.jobhistory.JobSubmitted datum;

  private org.apache.hadoop.mapred.JobConf jobConf;

  public org.apache.hadoop.mapreduce.jobhistory.JobSubmittedEvent(org.apache.hadoop.mapreduce.JobID, java.lang.String, java.lang.String, long, java.lang.String, java.util.Map<org.apache.hadoop.mapreduce.JobACL, org.apache.hadoop.security.authorize.AccessControlList>, java.lang.String);
    Code:
       0: aload_0
       1: aload_1
       2: aload_2
       3: aload_3
       4: lload         4
       6: aload         6
       8: aload         7
      10: aload         8
      12: ldc           #1                  // String
      14: ldc           #1                  // String
      16: ldc           #1                  // String
      18: ldc           #1                  // String
      20: invokespecial #2                  // Method "<init>":(Lorg/apache/hadoop/mapreduce/JobID;Ljava/lang/String;Ljava/lang/String;JLjava/lang/String;Ljava/util/Map;Ljava/lang/String;Ljava/lang/String;Ljava/lang/String;Ljava/lang/String;Ljava/lang/String;)V
      23: return

  public org.apache.hadoop.mapreduce.jobhistory.JobSubmittedEvent(org.apache.hadoop.mapreduce.JobID, java.lang.String, java.lang.String, long, java.lang.String, java.util.Map<org.apache.hadoop.mapreduce.JobACL, org.apache.hadoop.security.authorize.AccessControlList>, java.lang.String, java.lang.String, java.lang.String, java.lang.String, java.lang.String);
    Code:
       0: aload_0
       1: aload_1
       2: aload_2
       3: aload_3
       4: lload         4
       6: aload         6
       8: aload         7
      10: aload         8
      12: aload         9
      14: aload         10
      16: aload         11
      18: aload         12
      20: ldc           #1                  // String
      22: invokespecial #3                  // Method "<init>":(Lorg/apache/hadoop/mapreduce/JobID;Ljava/lang/String;Ljava/lang/String;JLjava/lang/String;Ljava/util/Map;Ljava/lang/String;Ljava/lang/String;Ljava/lang/String;Ljava/lang/String;Ljava/lang/String;Ljava/lang/String;)V
      25: return

  public org.apache.hadoop.mapreduce.jobhistory.JobSubmittedEvent(org.apache.hadoop.mapreduce.JobID, java.lang.String, java.lang.String, long, java.lang.String, java.util.Map<org.apache.hadoop.mapreduce.JobACL, org.apache.hadoop.security.authorize.AccessControlList>, java.lang.String, java.lang.String, java.lang.String, java.lang.String, java.lang.String, java.lang.String);
    Code:
       0: aload_0
       1: aload_1
       2: aload_2
       3: aload_3
       4: lload         4
       6: aload         6
       8: aload         7
      10: aload         8
      12: aload         9
      14: aload         10
      16: aload         11
      18: aload         12
      20: aload         13
      22: aconst_null
      23: invokespecial #4                  // Method "<init>":(Lorg/apache/hadoop/mapreduce/JobID;Ljava/lang/String;Ljava/lang/String;JLjava/lang/String;Ljava/util/Map;Ljava/lang/String;Ljava/lang/String;Ljava/lang/String;Ljava/lang/String;Ljava/lang/String;Ljava/lang/String;Lorg/apache/hadoop/mapred/JobConf;)V
      26: return

  public org.apache.hadoop.mapreduce.jobhistory.JobSubmittedEvent(org.apache.hadoop.mapreduce.JobID, java.lang.String, java.lang.String, long, java.lang.String, java.util.Map<org.apache.hadoop.mapreduce.JobACL, org.apache.hadoop.security.authorize.AccessControlList>, java.lang.String, java.lang.String, java.lang.String, java.lang.String, java.lang.String, java.lang.String, org.apache.hadoop.mapred.JobConf);
    Code:
       0: aload_0
       1: invokespecial #5                  // Method java/lang/Object."<init>":()V
       4: aload_0
       5: new           #6                  // class org/apache/hadoop/mapreduce/jobhistory/JobSubmitted
       8: dup
       9: invokespecial #7                  // Method org/apache/hadoop/mapreduce/jobhistory/JobSubmitted."<init>":()V
      12: putfield      #8                  // Field datum:Lorg/apache/hadoop/mapreduce/jobhistory/JobSubmitted;
      15: aload_0
      16: aconst_null
      17: putfield      #9                  // Field jobConf:Lorg/apache/hadoop/mapred/JobConf;
      20: aload_0
      21: getfield      #8                  // Field datum:Lorg/apache/hadoop/mapreduce/jobhistory/JobSubmitted;
      24: new           #10                 // class org/apache/avro/util/Utf8
      27: dup
      28: aload_1
      29: invokevirtual #11                 // Method org/apache/hadoop/mapreduce/JobID.toString:()Ljava/lang/String;
      32: invokespecial #12                 // Method org/apache/avro/util/Utf8."<init>":(Ljava/lang/String;)V
      35: invokevirtual #13                 // Method org/apache/hadoop/mapreduce/jobhistory/JobSubmitted.setJobid:(Ljava/lang/CharSequence;)V
      38: aload_0
      39: getfield      #8                  // Field datum:Lorg/apache/hadoop/mapreduce/jobhistory/JobSubmitted;
      42: new           #10                 // class org/apache/avro/util/Utf8
      45: dup
      46: aload_2
      47: invokespecial #12                 // Method org/apache/avro/util/Utf8."<init>":(Ljava/lang/String;)V
      50: invokevirtual #14                 // Method org/apache/hadoop/mapreduce/jobhistory/JobSubmitted.setJobName:(Ljava/lang/CharSequence;)V
      53: aload_0
      54: getfield      #8                  // Field datum:Lorg/apache/hadoop/mapreduce/jobhistory/JobSubmitted;
      57: new           #10                 // class org/apache/avro/util/Utf8
      60: dup
      61: aload_3
      62: invokespecial #12                 // Method org/apache/avro/util/Utf8."<init>":(Ljava/lang/String;)V
      65: invokevirtual #15                 // Method org/apache/hadoop/mapreduce/jobhistory/JobSubmitted.setUserName:(Ljava/lang/CharSequence;)V
      68: aload_0
      69: getfield      #8                  // Field datum:Lorg/apache/hadoop/mapreduce/jobhistory/JobSubmitted;
      72: lload         4
      74: invokestatic  #16                 // Method java/lang/Long.valueOf:(J)Ljava/lang/Long;
      77: invokevirtual #17                 // Method org/apache/hadoop/mapreduce/jobhistory/JobSubmitted.setSubmitTime:(Ljava/lang/Long;)V
      80: aload_0
      81: getfield      #8                  // Field datum:Lorg/apache/hadoop/mapreduce/jobhistory/JobSubmitted;
      84: new           #10                 // class org/apache/avro/util/Utf8
      87: dup
      88: aload         6
      90: invokespecial #12                 // Method org/apache/avro/util/Utf8."<init>":(Ljava/lang/String;)V
      93: invokevirtual #18                 // Method org/apache/hadoop/mapreduce/jobhistory/JobSubmitted.setJobConfPath:(Ljava/lang/CharSequence;)V
      96: new           #19                 // class java/util/HashMap
      99: dup
     100: invokespecial #20                 // Method java/util/HashMap."<init>":()V
     103: astore        15
     105: aload         7
     107: invokeinterface #21,  1           // InterfaceMethod java/util/Map.entrySet:()Ljava/util/Set;
     112: invokeinterface #22,  1           // InterfaceMethod java/util/Set.iterator:()Ljava/util/Iterator;
     117: astore        16
     119: aload         16
     121: invokeinterface #23,  1           // InterfaceMethod java/util/Iterator.hasNext:()Z
     126: ifeq          192
     129: aload         16
     131: invokeinterface #24,  1           // InterfaceMethod java/util/Iterator.next:()Ljava/lang/Object;
     136: checkcast     #25                 // class java/util/Map$Entry
     139: astore        17
     141: aload         15
     143: new           #10                 // class org/apache/avro/util/Utf8
     146: dup
     147: aload         17
     149: invokeinterface #26,  1           // InterfaceMethod java/util/Map$Entry.getKey:()Ljava/lang/Object;
     154: checkcast     #27                 // class org/apache/hadoop/mapreduce/JobACL
     157: invokevirtual #28                 // Method org/apache/hadoop/mapreduce/JobACL.getAclName:()Ljava/lang/String;
     160: invokespecial #12                 // Method org/apache/avro/util/Utf8."<init>":(Ljava/lang/String;)V
     163: new           #10                 // class org/apache/avro/util/Utf8
     166: dup
     167: aload         17
     169: invokeinterface #29,  1           // InterfaceMethod java/util/Map$Entry.getValue:()Ljava/lang/Object;
     174: checkcast     #30                 // class org/apache/hadoop/security/authorize/AccessControlList
     177: invokevirtual #31                 // Method org/apache/hadoop/security/authorize/AccessControlList.getAclString:()Ljava/lang/String;
     180: invokespecial #12                 // Method org/apache/avro/util/Utf8."<init>":(Ljava/lang/String;)V
     183: invokeinterface #32,  3           // InterfaceMethod java/util/Map.put:(Ljava/lang/Object;Ljava/lang/Object;)Ljava/lang/Object;
     188: pop
     189: goto          119
     192: aload_0
     193: getfield      #8                  // Field datum:Lorg/apache/hadoop/mapreduce/jobhistory/JobSubmitted;
     196: aload         15
     198: invokevirtual #33                 // Method org/apache/hadoop/mapreduce/jobhistory/JobSubmitted.setAcls:(Ljava/util/Map;)V
     201: aload         8
     203: ifnull        222
     206: aload_0
     207: getfield      #8                  // Field datum:Lorg/apache/hadoop/mapreduce/jobhistory/JobSubmitted;
     210: new           #10                 // class org/apache/avro/util/Utf8
     213: dup
     214: aload         8
     216: invokespecial #12                 // Method org/apache/avro/util/Utf8."<init>":(Ljava/lang/String;)V
     219: invokevirtual #34                 // Method org/apache/hadoop/mapreduce/jobhistory/JobSubmitted.setJobQueueName:(Ljava/lang/CharSequence;)V
     222: aload         9
     224: ifnull        243
     227: aload_0
     228: getfield      #8                  // Field datum:Lorg/apache/hadoop/mapreduce/jobhistory/JobSubmitted;
     231: new           #10                 // class org/apache/avro/util/Utf8
     234: dup
     235: aload         9
     237: invokespecial #12                 // Method org/apache/avro/util/Utf8."<init>":(Ljava/lang/String;)V
     240: invokevirtual #35                 // Method org/apache/hadoop/mapreduce/jobhistory/JobSubmitted.setWorkflowId:(Ljava/lang/CharSequence;)V
     243: aload         10
     245: ifnull        264
     248: aload_0
     249: getfield      #8                  // Field datum:Lorg/apache/hadoop/mapreduce/jobhistory/JobSubmitted;
     252: new           #10                 // class org/apache/avro/util/Utf8
     255: dup
     256: aload         10
     258: invokespecial #12                 // Method org/apache/avro/util/Utf8."<init>":(Ljava/lang/String;)V
     261: invokevirtual #36                 // Method org/apache/hadoop/mapreduce/jobhistory/JobSubmitted.setWorkflowName:(Ljava/lang/CharSequence;)V
     264: aload         11
     266: ifnull        285
     269: aload_0
     270: getfield      #8                  // Field datum:Lorg/apache/hadoop/mapreduce/jobhistory/JobSubmitted;
     273: new           #10                 // class org/apache/avro/util/Utf8
     276: dup
     277: aload         11
     279: invokespecial #12                 // Method org/apache/avro/util/Utf8."<init>":(Ljava/lang/String;)V
     282: invokevirtual #37                 // Method org/apache/hadoop/mapreduce/jobhistory/JobSubmitted.setWorkflowNodeName:(Ljava/lang/CharSequence;)V
     285: aload         12
     287: ifnull        306
     290: aload_0
     291: getfield      #8                  // Field datum:Lorg/apache/hadoop/mapreduce/jobhistory/JobSubmitted;
     294: new           #10                 // class org/apache/avro/util/Utf8
     297: dup
     298: aload         12
     300: invokespecial #12                 // Method org/apache/avro/util/Utf8."<init>":(Ljava/lang/String;)V
     303: invokevirtual #38                 // Method org/apache/hadoop/mapreduce/jobhistory/JobSubmitted.setWorkflowAdjacencies:(Ljava/lang/CharSequence;)V
     306: aload         13
     308: ifnull        327
     311: aload_0
     312: getfield      #8                  // Field datum:Lorg/apache/hadoop/mapreduce/jobhistory/JobSubmitted;
     315: new           #10                 // class org/apache/avro/util/Utf8
     318: dup
     319: aload         13
     321: invokespecial #12                 // Method org/apache/avro/util/Utf8."<init>":(Ljava/lang/String;)V
     324: invokevirtual #39                 // Method org/apache/hadoop/mapreduce/jobhistory/JobSubmitted.setWorkflowTags:(Ljava/lang/CharSequence;)V
     327: aload_0
     328: aload         14
     330: putfield      #9                  // Field jobConf:Lorg/apache/hadoop/mapred/JobConf;
     333: return

  org.apache.hadoop.mapreduce.jobhistory.JobSubmittedEvent();
    Code:
       0: aload_0
       1: invokespecial #5                  // Method java/lang/Object."<init>":()V
       4: aload_0
       5: new           #6                  // class org/apache/hadoop/mapreduce/jobhistory/JobSubmitted
       8: dup
       9: invokespecial #7                  // Method org/apache/hadoop/mapreduce/jobhistory/JobSubmitted."<init>":()V
      12: putfield      #8                  // Field datum:Lorg/apache/hadoop/mapreduce/jobhistory/JobSubmitted;
      15: aload_0
      16: aconst_null
      17: putfield      #9                  // Field jobConf:Lorg/apache/hadoop/mapred/JobConf;
      20: return

  public java.lang.Object getDatum();
    Code:
       0: aload_0
       1: getfield      #8                  // Field datum:Lorg/apache/hadoop/mapreduce/jobhistory/JobSubmitted;
       4: areturn

  public void setDatum(java.lang.Object);
    Code:
       0: aload_0
       1: aload_1
       2: checkcast     #6                  // class org/apache/hadoop/mapreduce/jobhistory/JobSubmitted
       5: putfield      #8                  // Field datum:Lorg/apache/hadoop/mapreduce/jobhistory/JobSubmitted;
       8: return

  public org.apache.hadoop.mapreduce.JobID getJobId();
    Code:
       0: aload_0
       1: getfield      #8                  // Field datum:Lorg/apache/hadoop/mapreduce/jobhistory/JobSubmitted;
       4: invokevirtual #40                 // Method org/apache/hadoop/mapreduce/jobhistory/JobSubmitted.getJobid:()Ljava/lang/CharSequence;
       7: invokeinterface #41,  1           // InterfaceMethod java/lang/CharSequence.toString:()Ljava/lang/String;
      12: invokestatic  #42                 // Method org/apache/hadoop/mapreduce/JobID.forName:(Ljava/lang/String;)Lorg/apache/hadoop/mapreduce/JobID;
      15: areturn

  public java.lang.String getJobName();
    Code:
       0: aload_0
       1: getfield      #8                  // Field datum:Lorg/apache/hadoop/mapreduce/jobhistory/JobSubmitted;
       4: invokevirtual #43                 // Method org/apache/hadoop/mapreduce/jobhistory/JobSubmitted.getJobName:()Ljava/lang/CharSequence;
       7: invokeinterface #41,  1           // InterfaceMethod java/lang/CharSequence.toString:()Ljava/lang/String;
      12: areturn

  public java.lang.String getJobQueueName();
    Code:
       0: aload_0
       1: getfield      #8                  // Field datum:Lorg/apache/hadoop/mapreduce/jobhistory/JobSubmitted;
       4: invokevirtual #44                 // Method org/apache/hadoop/mapreduce/jobhistory/JobSubmitted.getJobQueueName:()Ljava/lang/CharSequence;
       7: ifnull        23
      10: aload_0
      11: getfield      #8                  // Field datum:Lorg/apache/hadoop/mapreduce/jobhistory/JobSubmitted;
      14: invokevirtual #44                 // Method org/apache/hadoop/mapreduce/jobhistory/JobSubmitted.getJobQueueName:()Ljava/lang/CharSequence;
      17: invokeinterface #41,  1           // InterfaceMethod java/lang/CharSequence.toString:()Ljava/lang/String;
      22: areturn
      23: aconst_null
      24: areturn

  public java.lang.String getUserName();
    Code:
       0: aload_0
       1: getfield      #8                  // Field datum:Lorg/apache/hadoop/mapreduce/jobhistory/JobSubmitted;
       4: invokevirtual #45                 // Method org/apache/hadoop/mapreduce/jobhistory/JobSubmitted.getUserName:()Ljava/lang/CharSequence;
       7: invokeinterface #41,  1           // InterfaceMethod java/lang/CharSequence.toString:()Ljava/lang/String;
      12: areturn

  public long getSubmitTime();
    Code:
       0: aload_0
       1: getfield      #8                  // Field datum:Lorg/apache/hadoop/mapreduce/jobhistory/JobSubmitted;
       4: invokevirtual #46                 // Method org/apache/hadoop/mapreduce/jobhistory/JobSubmitted.getSubmitTime:()Ljava/lang/Long;
       7: invokevirtual #47                 // Method java/lang/Long.longValue:()J
      10: lreturn

  public java.lang.String getJobConfPath();
    Code:
       0: aload_0
       1: getfield      #8                  // Field datum:Lorg/apache/hadoop/mapreduce/jobhistory/JobSubmitted;
       4: invokevirtual #48                 // Method org/apache/hadoop/mapreduce/jobhistory/JobSubmitted.getJobConfPath:()Ljava/lang/CharSequence;
       7: invokeinterface #41,  1           // InterfaceMethod java/lang/CharSequence.toString:()Ljava/lang/String;
      12: areturn

  public java.util.Map<org.apache.hadoop.mapreduce.JobACL, org.apache.hadoop.security.authorize.AccessControlList> getJobAcls();
    Code:
       0: new           #19                 // class java/util/HashMap
       3: dup
       4: invokespecial #20                 // Method java/util/HashMap."<init>":()V
       7: astore_1
       8: invokestatic  #49                 // Method org/apache/hadoop/mapreduce/JobACL.values:()[Lorg/apache/hadoop/mapreduce/JobACL;
      11: astore_2
      12: aload_2
      13: arraylength
      14: istore_3
      15: iconst_0
      16: istore        4
      18: iload         4
      20: iload_3
      21: if_icmpge     105
      24: aload_2
      25: iload         4
      27: aaload
      28: astore        5
      30: new           #10                 // class org/apache/avro/util/Utf8
      33: dup
      34: aload         5
      36: invokevirtual #28                 // Method org/apache/hadoop/mapreduce/JobACL.getAclName:()Ljava/lang/String;
      39: invokespecial #12                 // Method org/apache/avro/util/Utf8."<init>":(Ljava/lang/String;)V
      42: astore        6
      44: aload_0
      45: getfield      #8                  // Field datum:Lorg/apache/hadoop/mapreduce/jobhistory/JobSubmitted;
      48: invokevirtual #50                 // Method org/apache/hadoop/mapreduce/jobhistory/JobSubmitted.getAcls:()Ljava/util/Map;
      51: aload         6
      53: invokeinterface #51,  2           // InterfaceMethod java/util/Map.containsKey:(Ljava/lang/Object;)Z
      58: ifeq          99
      61: aload_1
      62: aload         5
      64: new           #30                 // class org/apache/hadoop/security/authorize/AccessControlList
      67: dup
      68: aload_0
      69: getfield      #8                  // Field datum:Lorg/apache/hadoop/mapreduce/jobhistory/JobSubmitted;
      72: invokevirtual #50                 // Method org/apache/hadoop/mapreduce/jobhistory/JobSubmitted.getAcls:()Ljava/util/Map;
      75: aload         6
      77: invokeinterface #52,  2           // InterfaceMethod java/util/Map.get:(Ljava/lang/Object;)Ljava/lang/Object;
      82: checkcast     #53                 // class java/lang/CharSequence
      85: invokeinterface #41,  1           // InterfaceMethod java/lang/CharSequence.toString:()Ljava/lang/String;
      90: invokespecial #54                 // Method org/apache/hadoop/security/authorize/AccessControlList."<init>":(Ljava/lang/String;)V
      93: invokeinterface #32,  3           // InterfaceMethod java/util/Map.put:(Ljava/lang/Object;Ljava/lang/Object;)Ljava/lang/Object;
      98: pop
      99: iinc          4, 1
     102: goto          18
     105: aload_1
     106: areturn

  public java.lang.String getWorkflowId();
    Code:
       0: aload_0
       1: getfield      #8                  // Field datum:Lorg/apache/hadoop/mapreduce/jobhistory/JobSubmitted;
       4: invokevirtual #55                 // Method org/apache/hadoop/mapreduce/jobhistory/JobSubmitted.getWorkflowId:()Ljava/lang/CharSequence;
       7: ifnull        23
      10: aload_0
      11: getfield      #8                  // Field datum:Lorg/apache/hadoop/mapreduce/jobhistory/JobSubmitted;
      14: invokevirtual #55                 // Method org/apache/hadoop/mapreduce/jobhistory/JobSubmitted.getWorkflowId:()Ljava/lang/CharSequence;
      17: invokeinterface #41,  1           // InterfaceMethod java/lang/CharSequence.toString:()Ljava/lang/String;
      22: areturn
      23: aconst_null
      24: areturn

  public java.lang.String getWorkflowName();
    Code:
       0: aload_0
       1: getfield      #8                  // Field datum:Lorg/apache/hadoop/mapreduce/jobhistory/JobSubmitted;
       4: invokevirtual #56                 // Method org/apache/hadoop/mapreduce/jobhistory/JobSubmitted.getWorkflowName:()Ljava/lang/CharSequence;
       7: ifnull        23
      10: aload_0
      11: getfield      #8                  // Field datum:Lorg/apache/hadoop/mapreduce/jobhistory/JobSubmitted;
      14: invokevirtual #56                 // Method org/apache/hadoop/mapreduce/jobhistory/JobSubmitted.getWorkflowName:()Ljava/lang/CharSequence;
      17: invokeinterface #41,  1           // InterfaceMethod java/lang/CharSequence.toString:()Ljava/lang/String;
      22: areturn
      23: aconst_null
      24: areturn

  public java.lang.String getWorkflowNodeName();
    Code:
       0: aload_0
       1: getfield      #8                  // Field datum:Lorg/apache/hadoop/mapreduce/jobhistory/JobSubmitted;
       4: invokevirtual #57                 // Method org/apache/hadoop/mapreduce/jobhistory/JobSubmitted.getWorkflowNodeName:()Ljava/lang/CharSequence;
       7: ifnull        23
      10: aload_0
      11: getfield      #8                  // Field datum:Lorg/apache/hadoop/mapreduce/jobhistory/JobSubmitted;
      14: invokevirtual #57                 // Method org/apache/hadoop/mapreduce/jobhistory/JobSubmitted.getWorkflowNodeName:()Ljava/lang/CharSequence;
      17: invokeinterface #41,  1           // InterfaceMethod java/lang/CharSequence.toString:()Ljava/lang/String;
      22: areturn
      23: aconst_null
      24: areturn

  public java.lang.String getWorkflowAdjacencies();
    Code:
       0: aload_0
       1: getfield      #8                  // Field datum:Lorg/apache/hadoop/mapreduce/jobhistory/JobSubmitted;
       4: invokevirtual #58                 // Method org/apache/hadoop/mapreduce/jobhistory/JobSubmitted.getWorkflowAdjacencies:()Ljava/lang/CharSequence;
       7: ifnull        23
      10: aload_0
      11: getfield      #8                  // Field datum:Lorg/apache/hadoop/mapreduce/jobhistory/JobSubmitted;
      14: invokevirtual #58                 // Method org/apache/hadoop/mapreduce/jobhistory/JobSubmitted.getWorkflowAdjacencies:()Ljava/lang/CharSequence;
      17: invokeinterface #41,  1           // InterfaceMethod java/lang/CharSequence.toString:()Ljava/lang/String;
      22: areturn
      23: aconst_null
      24: areturn

  public java.lang.String getWorkflowTags();
    Code:
       0: aload_0
       1: getfield      #8                  // Field datum:Lorg/apache/hadoop/mapreduce/jobhistory/JobSubmitted;
       4: invokevirtual #59                 // Method org/apache/hadoop/mapreduce/jobhistory/JobSubmitted.getWorkflowTags:()Ljava/lang/CharSequence;
       7: ifnull        23
      10: aload_0
      11: getfield      #8                  // Field datum:Lorg/apache/hadoop/mapreduce/jobhistory/JobSubmitted;
      14: invokevirtual #59                 // Method org/apache/hadoop/mapreduce/jobhistory/JobSubmitted.getWorkflowTags:()Ljava/lang/CharSequence;
      17: invokeinterface #41,  1           // InterfaceMethod java/lang/CharSequence.toString:()Ljava/lang/String;
      22: areturn
      23: aconst_null
      24: areturn

  public org.apache.hadoop.mapreduce.jobhistory.EventType getEventType();
    Code:
       0: getstatic     #60                 // Field org/apache/hadoop/mapreduce/jobhistory/EventType.JOB_SUBMITTED:Lorg/apache/hadoop/mapreduce/jobhistory/EventType;
       3: areturn

  public org.apache.hadoop.mapred.JobConf getJobConf();
    Code:
       0: aload_0
       1: getfield      #9                  // Field jobConf:Lorg/apache/hadoop/mapred/JobConf;
       4: areturn

  public org.apache.hadoop.yarn.api.records.timelineservice.TimelineEvent toTimelineEvent();
    Code:
       0: new           #61                 // class org/apache/hadoop/yarn/api/records/timelineservice/TimelineEvent
       3: dup
       4: invokespecial #62                 // Method org/apache/hadoop/yarn/api/records/timelineservice/TimelineEvent."<init>":()V
       7: astore_1
       8: aload_1
       9: aload_0
      10: invokevirtual #63                 // Method getEventType:()Lorg/apache/hadoop/mapreduce/jobhistory/EventType;
      13: invokevirtual #64                 // Method org/apache/hadoop/mapreduce/jobhistory/EventType.name:()Ljava/lang/String;
      16: invokestatic  #65                 // Method org/apache/hadoop/util/StringUtils.toUpperCase:(Ljava/lang/String;)Ljava/lang/String;
      19: invokevirtual #66                 // Method org/apache/hadoop/yarn/api/records/timelineservice/TimelineEvent.setId:(Ljava/lang/String;)V
      22: aload_1
      23: ldc           #67                 // String SUBMIT_TIME
      25: aload_0
      26: invokevirtual #68                 // Method getSubmitTime:()J
      29: invokestatic  #16                 // Method java/lang/Long.valueOf:(J)Ljava/lang/Long;
      32: invokevirtual #69                 // Method org/apache/hadoop/yarn/api/records/timelineservice/TimelineEvent.addInfo:(Ljava/lang/String;Ljava/lang/Object;)V
      35: aload_1
      36: ldc           #70                 // String QUEUE_NAME
      38: aload_0
      39: invokevirtual #71                 // Method getJobQueueName:()Ljava/lang/String;
      42: invokevirtual #69                 // Method org/apache/hadoop/yarn/api/records/timelineservice/TimelineEvent.addInfo:(Ljava/lang/String;Ljava/lang/Object;)V
      45: aload_1
      46: ldc           #72                 // String JOB_NAME
      48: aload_0
      49: invokevirtual #73                 // Method getJobName:()Ljava/lang/String;
      52: invokevirtual #69                 // Method org/apache/hadoop/yarn/api/records/timelineservice/TimelineEvent.addInfo:(Ljava/lang/String;Ljava/lang/Object;)V
      55: aload_1
      56: ldc           #74                 // String USER_NAME
      58: aload_0
      59: invokevirtual #75                 // Method getUserName:()Ljava/lang/String;
      62: invokevirtual #69                 // Method org/apache/hadoop/yarn/api/records/timelineservice/TimelineEvent.addInfo:(Ljava/lang/String;Ljava/lang/Object;)V
      65: aload_1
      66: ldc           #76                 // String JOB_CONF_PATH
      68: aload_0
      69: invokevirtual #77                 // Method getJobConfPath:()Ljava/lang/String;
      72: invokevirtual #69                 // Method org/apache/hadoop/yarn/api/records/timelineservice/TimelineEvent.addInfo:(Ljava/lang/String;Ljava/lang/Object;)V
      75: aload_1
      76: ldc           #78                 // String ACLS
      78: aload_0
      79: invokevirtual #79                 // Method getJobAcls:()Ljava/util/Map;
      82: invokevirtual #69                 // Method org/apache/hadoop/yarn/api/records/timelineservice/TimelineEvent.addInfo:(Ljava/lang/String;Ljava/lang/Object;)V
      85: aload_1
      86: ldc           #80                 // String JOB_QUEUE_NAME
      88: aload_0
      89: invokevirtual #71                 // Method getJobQueueName:()Ljava/lang/String;
      92: invokevirtual #69                 // Method org/apache/hadoop/yarn/api/records/timelineservice/TimelineEvent.addInfo:(Ljava/lang/String;Ljava/lang/Object;)V
      95: aload_1
      96: ldc           #81                 // String WORKLFOW_ID
      98: aload_0
      99: invokevirtual #82                 // Method getWorkflowId:()Ljava/lang/String;
     102: invokevirtual #69                 // Method org/apache/hadoop/yarn/api/records/timelineservice/TimelineEvent.addInfo:(Ljava/lang/String;Ljava/lang/Object;)V
     105: aload_1
     106: ldc           #83                 // String WORKFLOW_NAME
     108: aload_0
     109: invokevirtual #84                 // Method getWorkflowName:()Ljava/lang/String;
     112: invokevirtual #69                 // Method org/apache/hadoop/yarn/api/records/timelineservice/TimelineEvent.addInfo:(Ljava/lang/String;Ljava/lang/Object;)V
     115: aload_1
     116: ldc           #85                 // String WORKFLOW_NODE_NAME
     118: aload_0
     119: invokevirtual #86                 // Method getWorkflowNodeName:()Ljava/lang/String;
     122: invokevirtual #69                 // Method org/apache/hadoop/yarn/api/records/timelineservice/TimelineEvent.addInfo:(Ljava/lang/String;Ljava/lang/Object;)V
     125: aload_1
     126: ldc           #87                 // String WORKFLOW_ADJACENCIES
     128: aload_0
     129: invokevirtual #88                 // Method getWorkflowAdjacencies:()Ljava/lang/String;
     132: invokevirtual #69                 // Method org/apache/hadoop/yarn/api/records/timelineservice/TimelineEvent.addInfo:(Ljava/lang/String;Ljava/lang/Object;)V
     135: aload_1
     136: ldc           #89                 // String WORKFLOW_TAGS
     138: aload_0
     139: invokevirtual #90                 // Method getWorkflowTags:()Ljava/lang/String;
     142: invokevirtual #69                 // Method org/apache/hadoop/yarn/api/records/timelineservice/TimelineEvent.addInfo:(Ljava/lang/String;Ljava/lang/Object;)V
     145: aload_1
     146: areturn

  public java.util.Set<org.apache.hadoop.yarn.api.records.timelineservice.TimelineMetric> getTimelineMetrics();
    Code:
       0: aconst_null
       1: areturn
}
