Compiled from "AuthGetTokenRequest.java"
class org.jtb.quickr.AuthGetTokenRequest extends org.jtb.quickr.SignedMethodRequest {
  private org.jtb.quickr.FrobResponse frob;

  protected org.jtb.quickr.AuthGetTokenRequest(java.lang.String, java.lang.String, java.lang.String, org.jtb.quickr.FrobResponse) throws org.jtb.quickr.QuickrException;
    Code:
       0: aload_0
       1: aload_1
       2: aload_2
       3: aload_3
       4: aconst_null
       5: ldc           #1                  // String flickr.auth.getToken
       7: invokespecial #2                  // Method org/jtb/quickr/SignedMethodRequest."<init>":(Ljava/lang/String;Ljava/lang/String;Ljava/lang/String;Lorg/jtb/quickr/AuthResponse$Token;Ljava/lang/String;)V
      10: aload_0
      11: aload         4
      13: putfield      #3                  // Field frob:Lorg/jtb/quickr/FrobResponse;
      16: return

  protected java.util.Map<java.lang.String, java.lang.String> getArgs();
    Code:
       0: aload_0
       1: ldc           #4                  // String frob
       3: aload_0
       4: getfield      #3                  // Field frob:Lorg/jtb/quickr/FrobResponse;
       7: invokevirtual #5                  // Method org/jtb/quickr/FrobResponse.toString:()Ljava/lang/String;
      10: invokevirtual #6                  // Method putArg:(Ljava/lang/String;Ljava/lang/String;)V
      13: aload_0
      14: invokespecial #7                  // Method org/jtb/quickr/SignedMethodRequest.getArgs:()Ljava/util/Map;
      17: areturn

  public org.jtb.quickr.AuthResponse execute() throws org.jtb.quickr.QuickrException;
    Code:
       0: new           #8                  // class org/jtb/quickr/SignedMethodUrl
       3: dup
       4: aload_0
       5: invokevirtual #9                  // Method getBaseUrl:()Ljava/lang/String;
       8: aload_0
       9: invokevirtual #10                 // Method getArgs:()Ljava/util/Map;
      12: aload_0
      13: invokevirtual #11                 // Method getApiKey:()Ljava/lang/String;
      16: aload_0
      17: invokevirtual #12                 // Method getSecret:()Ljava/lang/String;
      20: aload_0
      21: invokevirtual #13                 // Method getMethod:()Ljava/lang/String;
      24: invokespecial #14                 // Method org/jtb/quickr/SignedMethodUrl."<init>":(Ljava/lang/String;Ljava/util/Map;Ljava/lang/String;Ljava/lang/String;Ljava/lang/String;)V
      27: astore_1
      28: new           #15                 // class org/jtb/quickr/Get
      31: dup
      32: aload_1
      33: invokevirtual #16                 // Method org/jtb/quickr/FlickrUrl.getUrl:()Ljava/net/URL;
      36: invokespecial #17                 // Method org/jtb/quickr/Get."<init>":(Ljava/net/URL;)V
      39: astore_2
      40: aload_2
      41: invokevirtual #18                 // Method org/jtb/quickr/Get.execute:()Ljava/io/InputStream;
      44: astore_3
      45: new           #19                 // class org/jtb/quickr/AuthResponse
      48: dup
      49: aload_3
      50: invokespecial #20                 // Method org/jtb/quickr/AuthResponse."<init>":(Ljava/io/InputStream;)V
      53: astore        4
      55: aload         4
      57: areturn

  public org.jtb.quickr.FlickrResponse execute() throws org.jtb.quickr.QuickrException;
    Code:
       0: aload_0
       1: invokevirtual #21                 // Method execute:()Lorg/jtb/quickr/AuthResponse;
       4: areturn
}
