Compiled from "FlickrUrl.java"
class org.jtb.quickr.FlickrUrl {
  private static org.apache.log4j.Logger logger;

  private java.net.URL url;

  private java.lang.String baseUrl;

  private java.util.Map<java.lang.String, java.lang.String> args;

  public org.jtb.quickr.FlickrUrl(java.lang.String);
    Code:
       0: aload_0
       1: aload_1
       2: new           #1                  // class java/util/HashMap
       5: dup
       6: invokespecial #2                  // Method java/util/HashMap."<init>":()V
       9: invokespecial #3                  // Method "<init>":(Ljava/lang/String;Ljava/util/Map;)V
      12: return

  public org.jtb.quickr.FlickrUrl(java.lang.String, java.util.Map<java.lang.String, java.lang.String>);
    Code:
       0: aload_0
       1: invokespecial #4                  // Method java/lang/Object."<init>":()V
       4: aload_0
       5: aload_1
       6: invokespecial #5                  // Method setBaseUrl:(Ljava/lang/String;)V
       9: aload_0
      10: new           #1                  // class java/util/HashMap
      13: dup
      14: aload_2
      15: invokespecial #6                  // Method java/util/HashMap."<init>":(Ljava/util/Map;)V
      18: invokespecial #7                  // Method setArgs:(Ljava/util/Map;)V
      21: return

  protected java.net.URL buildUrl() throws org.jtb.quickr.QuickrException;
    Code:
       0: aload_0
       1: invokevirtual #8                  // Method getArgs:()Ljava/util/Map;
       4: astore_1
       5: new           #9                  // class java/lang/StringBuffer
       8: dup
       9: bipush        32
      11: invokespecial #10                 // Method java/lang/StringBuffer."<init>":(I)V
      14: astore_2
      15: aload_2
      16: aload_0
      17: invokevirtual #11                 // Method getBaseUrl:()Ljava/lang/String;
      20: invokevirtual #12                 // Method java/lang/StringBuffer.append:(Ljava/lang/String;)Ljava/lang/StringBuffer;
      23: pop
      24: aload_1
      25: invokeinterface #13,  1           // InterfaceMethod java/util/Map.size:()I
      30: ifle          40
      33: aload_2
      34: ldc           #14                 // String ?
      36: invokevirtual #12                 // Method java/lang/StringBuffer.append:(Ljava/lang/String;)Ljava/lang/StringBuffer;
      39: pop
      40: aload_1
      41: invokeinterface #15,  1           // InterfaceMethod java/util/Map.keySet:()Ljava/util/Set;
      46: invokeinterface #16,  1           // InterfaceMethod java/util/Set.iterator:()Ljava/util/Iterator;
      51: astore_3
      52: aload_3
      53: invokeinterface #17,  1           // InterfaceMethod java/util/Iterator.hasNext:()Z
      58: ifeq          125
      61: aload_3
      62: invokeinterface #18,  1           // InterfaceMethod java/util/Iterator.next:()Ljava/lang/Object;
      67: checkcast     #19                 // class java/lang/String
      70: astore        4
      72: aload_1
      73: aload         4
      75: invokeinterface #20,  2           // InterfaceMethod java/util/Map.get:(Ljava/lang/Object;)Ljava/lang/Object;
      80: checkcast     #19                 // class java/lang/String
      83: astore        5
      85: aload_2
      86: aload         4
      88: invokevirtual #12                 // Method java/lang/StringBuffer.append:(Ljava/lang/String;)Ljava/lang/StringBuffer;
      91: pop
      92: aload_2
      93: ldc           #21                 // String =
      95: invokevirtual #12                 // Method java/lang/StringBuffer.append:(Ljava/lang/String;)Ljava/lang/StringBuffer;
      98: pop
      99: aload_2
     100: aload         5
     102: invokevirtual #12                 // Method java/lang/StringBuffer.append:(Ljava/lang/String;)Ljava/lang/StringBuffer;
     105: pop
     106: aload_3
     107: invokeinterface #17,  1           // InterfaceMethod java/util/Iterator.hasNext:()Z
     112: ifeq          122
     115: aload_2
     116: ldc           #22                 // String &
     118: invokevirtual #12                 // Method java/lang/StringBuffer.append:(Ljava/lang/String;)Ljava/lang/StringBuffer;
     121: pop
     122: goto          52
     125: new           #23                 // class java/net/URL
     128: dup
     129: aload_2
     130: invokevirtual #24                 // Method java/lang/StringBuffer.toString:()Ljava/lang/String;
     133: invokespecial #25                 // Method java/net/URL."<init>":(Ljava/lang/String;)V
     136: astore_3
     137: getstatic     #26                 // Field logger:Lorg/apache/log4j/Logger;
     140: invokevirtual #27                 // Method org/apache/log4j/Logger.isDebugEnabled:()Z
     143: ifeq          171
     146: getstatic     #26                 // Field logger:Lorg/apache/log4j/Logger;
     149: new           #28                 // class java/lang/StringBuilder
     152: dup
     153: invokespecial #29                 // Method java/lang/StringBuilder."<init>":()V
     156: ldc           #30                 // String url:
     158: invokevirtual #31                 // Method java/lang/StringBuilder.append:(Ljava/lang/String;)Ljava/lang/StringBuilder;
     161: aload_3
     162: invokevirtual #32                 // Method java/lang/StringBuilder.append:(Ljava/lang/Object;)Ljava/lang/StringBuilder;
     165: invokevirtual #33                 // Method java/lang/StringBuilder.toString:()Ljava/lang/String;
     168: invokevirtual #34                 // Method org/apache/log4j/Logger.debug:(Ljava/lang/Object;)V
     171: aload_3
     172: areturn
     173: astore_3
     174: aload_3
     175: invokevirtual #36                 // Method java/net/MalformedURLException.printStackTrace:()V
     178: new           #37                 // class org/jtb/quickr/QuickrException
     181: dup
     182: ldc           #38                 // String could not create URL
     184: aload_3
     185: invokespecial #39                 // Method org/jtb/quickr/QuickrException."<init>":(Ljava/lang/String;Ljava/lang/Throwable;)V
     188: athrow
    Exception table:
       from    to  target type
         125   172   173   Class java/net/MalformedURLException

  public java.net.URL getUrl() throws org.jtb.quickr.QuickrException;
    Code:
       0: aload_0
       1: getfield      #40                 // Field url:Ljava/net/URL;
       4: ifnonnull     15
       7: aload_0
       8: aload_0
       9: invokevirtual #41                 // Method buildUrl:()Ljava/net/URL;
      12: putfield      #40                 // Field url:Ljava/net/URL;
      15: aload_0
      16: getfield      #40                 // Field url:Ljava/net/URL;
      19: areturn

  public java.lang.String toString();
    Code:
       0: aload_0
       1: invokevirtual #42                 // Method getUrl:()Ljava/net/URL;
       4: invokevirtual #43                 // Method java/net/URL.toString:()Ljava/lang/String;
       7: areturn
       8: astore_1
       9: new           #44                 // class java/lang/RuntimeException
      12: dup
      13: aload_1
      14: invokespecial #45                 // Method java/lang/RuntimeException."<init>":(Ljava/lang/Throwable;)V
      17: athrow
    Exception table:
       from    to  target type
           0     7     8   Class org/jtb/quickr/QuickrException

  protected java.lang.String getBaseUrl();
    Code:
       0: aload_0
       1: getfield      #46                 // Field baseUrl:Ljava/lang/String;
       4: areturn

  private void setBaseUrl(java.lang.String);
    Code:
       0: aload_0
       1: aload_1
       2: putfield      #46                 // Field baseUrl:Ljava/lang/String;
       5: return

  protected java.util.Map<java.lang.String, java.lang.String> getArgs();
    Code:
       0: aload_0
       1: getfield      #47                 // Field args:Ljava/util/Map;
       4: invokestatic  #48                 // Method java/util/Collections.unmodifiableMap:(Ljava/util/Map;)Ljava/util/Map;
       7: areturn

  protected void putArg(java.lang.String, java.lang.String);
    Code:
       0: aload_0
       1: getfield      #47                 // Field args:Ljava/util/Map;
       4: aload_1
       5: aload_2
       6: invokeinterface #49,  3           // InterfaceMethod java/util/Map.put:(Ljava/lang/Object;Ljava/lang/Object;)Ljava/lang/Object;
      11: pop
      12: return

  private void setArgs(java.util.Map<java.lang.String, java.lang.String>);
    Code:
       0: aload_0
       1: aload_1
       2: putfield      #47                 // Field args:Ljava/util/Map;
       5: return

  static {};
    Code:
       0: ldc_w         #50                 // class org/jtb/quickr/FlickrUrl
       3: invokevirtual #51                 // Method java/lang/Class.getName:()Ljava/lang/String;
       6: invokestatic  #52                 // Method org/apache/log4j/Logger.getLogger:(Ljava/lang/String;)Lorg/apache/log4j/Logger;
       9: putstatic     #26                 // Field logger:Lorg/apache/log4j/Logger;
      12: return
}
