Compiled from "MultipartPost.java"
class org.jtb.quickr.MultipartPost$PartComparator implements java.util.Comparator {
  private org.jtb.quickr.MultipartPost$PartComparator();
    Code:
       0: aload_0
       1: invokespecial #2                  // Method java/lang/Object."<init>":()V
       4: return

  public int compare(java.lang.Object, java.lang.Object);
    Code:
       0: aload_1
       1: checkcast     #3                  // class org/apache/commons/httpclient/methods/multipart/Part
       4: astore_3
       5: aload_2
       6: checkcast     #3                  // class org/apache/commons/httpclient/methods/multipart/Part
       9: astore        4
      11: aload_3
      12: invokevirtual #4                  // Method org/apache/commons/httpclient/methods/multipart/Part.getName:()Ljava/lang/String;
      15: aload         4
      17: invokevirtual #4                  // Method org/apache/commons/httpclient/methods/multipart/Part.getName:()Ljava/lang/String;
      20: invokevirtual #5                  // Method java/lang/String.compareTo:(Ljava/lang/String;)I
      23: ireturn

  org.jtb.quickr.MultipartPost$PartComparator(org.jtb.quickr.MultipartPost$1);
    Code:
       0: aload_0
       1: invokespecial #1                  // Method "<init>":()V
       4: return
}
