Compiled from "UploadCriteria.java"
public class org.jtb.quickr.UploadCriteria {
  private java.io.File photo;

  private java.lang.String title;

  private java.lang.String description;

  private java.util.Set<java.lang.String> tags;

  private java.lang.Boolean publicPhoto;

  private java.lang.Boolean friendPhoto;

  private java.lang.Boolean familyPhoto;

  public org.jtb.quickr.UploadCriteria();
    Code:
       0: aload_0
       1: invokespecial #1                  // Method java/lang/Object."<init>":()V
       4: return

  public java.io.File getPhoto();
    Code:
       0: aload_0
       1: getfield      #2                  // Field photo:Ljava/io/File;
       4: areturn

  public void setPhoto(java.io.File);
    Code:
       0: aload_0
       1: aload_1
       2: putfield      #2                  // Field photo:Ljava/io/File;
       5: return

  public java.lang.String getTitle();
    Code:
       0: aload_0
       1: getfield      #3                  // Field title:Ljava/lang/String;
       4: areturn

  public void setTitle(java.lang.String);
    Code:
       0: aload_0
       1: aload_1
       2: putfield      #3                  // Field title:Ljava/lang/String;
       5: return

  public java.lang.String getDescription();
    Code:
       0: aload_0
       1: getfield      #4                  // Field description:Ljava/lang/String;
       4: areturn

  public void setDescription(java.lang.String);
    Code:
       0: aload_0
       1: aload_1
       2: putfield      #4                  // Field description:Ljava/lang/String;
       5: return

  public java.util.Set<java.lang.String> getTags();
    Code:
       0: aload_0
       1: getfield      #5                  // Field tags:Ljava/util/Set;
       4: areturn

  public void setTags(java.util.Set<java.lang.String>);
    Code:
       0: aload_0
       1: aload_1
       2: putfield      #5                  // Field tags:Ljava/util/Set;
       5: return

  public java.lang.Boolean getPublicPhoto();
    Code:
       0: aload_0
       1: getfield      #6                  // Field publicPhoto:Ljava/lang/Boolean;
       4: areturn

  public void setPublicPhoto(java.lang.Boolean);
    Code:
       0: aload_0
       1: aload_1
       2: putfield      #6                  // Field publicPhoto:Ljava/lang/Boolean;
       5: return

  public java.lang.Boolean getFriendPhoto();
    Code:
       0: aload_0
       1: getfield      #7                  // Field friendPhoto:Ljava/lang/Boolean;
       4: areturn

  public void setFriendPhoto(java.lang.Boolean);
    Code:
       0: aload_0
       1: aload_1
       2: putfield      #7                  // Field friendPhoto:Ljava/lang/Boolean;
       5: return

  public java.lang.Boolean getFamilyPhoto();
    Code:
       0: aload_0
       1: getfield      #8                  // Field familyPhoto:Ljava/lang/Boolean;
       4: areturn

  public void setFamilyPhoto(java.lang.Boolean);
    Code:
       0: aload_0
       1: aload_1
       2: putfield      #8                  // Field familyPhoto:Ljava/lang/Boolean;
       5: return
}
