Compiled from "SimpleRole.java"
public class org.jboss.security.identity.plugins.SimpleRole implements org.jboss.security.identity.Role,java.lang.Cloneable {
  private static final long serialVersionUID;

  private final java.lang.String roleName;

  private final org.jboss.security.identity.Role parent;

  public static final java.lang.String ANYBODY;

  public static final org.jboss.security.identity.Role ANYBODY_ROLE;

  public org.jboss.security.identity.plugins.SimpleRole(java.lang.String);
    Code:
       0: aload_0
       1: aload_1
       2: aconst_null
       3: invokespecial #1                  // Method "<init>":(Ljava/lang/String;Lorg/jboss/security/identity/Role;)V
       6: return

  public org.jboss.security.identity.plugins.SimpleRole(java.lang.String, org.jboss.security.identity.Role);
    Code:
       0: aload_0
       1: invokespecial #2                  // Method java/lang/Object."<init>":()V
       4: aload_0
       5: aload_1
       6: putfield      #3                  // Field roleName:Ljava/lang/String;
       9: aload_0
      10: aload_2
      11: putfield      #4                  // Field parent:Lorg/jboss/security/identity/Role;
      14: return

  public java.lang.String getRoleName();
    Code:
       0: aload_0
       1: getfield      #3                  // Field roleName:Ljava/lang/String;
       4: areturn

  public org.jboss.security.identity.RoleType getType();
    Code:
       0: getstatic     #5                  // Field org/jboss/security/identity/RoleType.simple:Lorg/jboss/security/identity/RoleType;
       3: areturn

  public boolean containsAll(org.jboss.security.identity.Role);
    Code:
       0: aload_1
       1: invokeinterface #6,  1            // InterfaceMethod org/jboss/security/identity/Role.getType:()Lorg/jboss/security/identity/RoleType;
       6: getstatic     #5                  // Field org/jboss/security/identity/RoleType.simple:Lorg/jboss/security/identity/RoleType;
       9: if_acmpne     40
      12: ldc           #8                  // String <ANYBODY>
      14: aload_0
      15: getfield      #3                  // Field roleName:Ljava/lang/String;
      18: invokevirtual #9                  // Method java/lang/String.equals:(Ljava/lang/Object;)Z
      21: ifeq          26
      24: iconst_1
      25: ireturn
      26: aload_0
      27: getfield      #3                  // Field roleName:Ljava/lang/String;
      30: aload_1
      31: invokeinterface #10,  1           // InterfaceMethod org/jboss/security/identity/Role.getRoleName:()Ljava/lang/String;
      36: invokevirtual #9                  // Method java/lang/String.equals:(Ljava/lang/Object;)Z
      39: ireturn
      40: iconst_0
      41: ireturn

  public org.jboss.security.identity.Role getParent();
    Code:
       0: aload_0
       1: getfield      #4                  // Field parent:Lorg/jboss/security/identity/Role;
       4: areturn

  protected java.lang.Object clone() throws java.lang.CloneNotSupportedException;
    Code:
       0: aload_0
       1: invokespecial #11                 // Method java/lang/Object.clone:()Ljava/lang/Object;
       4: areturn

  public java.lang.String toString();
    Code:
       0: aload_0
       1: getfield      #3                  // Field roleName:Ljava/lang/String;
       4: areturn

  public int hashCode();
    Code:
       0: aload_0
       1: getfield      #3                  // Field roleName:Ljava/lang/String;
       4: invokevirtual #12                 // Method java/lang/String.hashCode:()I
       7: istore_1
       8: aload_0
       9: getfield      #4                  // Field parent:Lorg/jboss/security/identity/Role;
      12: ifnull        25
      15: iload_1
      16: aload_0
      17: getfield      #4                  // Field parent:Lorg/jboss/security/identity/Role;
      20: invokevirtual #13                 // Method java/lang/Object.hashCode:()I
      23: iadd
      24: istore_1
      25: iload_1
      26: ireturn

  public boolean equals(java.lang.Object);
    Code:
       0: aload_1
       1: aload_0
       2: if_acmpne     7
       5: iconst_1
       6: ireturn
       7: aload_1
       8: instanceof    #7                  // class org/jboss/security/identity/plugins/SimpleRole
      11: ifeq          89
      14: aload_1
      15: checkcast     #7                  // class org/jboss/security/identity/plugins/SimpleRole
      18: astore_2
      19: aload_0
      20: getfield      #4                  // Field parent:Lorg/jboss/security/identity/Role;
      23: ifnull        62
      26: aload_0
      27: getfield      #3                  // Field roleName:Ljava/lang/String;
      30: aload_2
      31: getfield      #3                  // Field roleName:Ljava/lang/String;
      34: invokevirtual #9                  // Method java/lang/String.equals:(Ljava/lang/Object;)Z
      37: ifeq          58
      40: aload_0
      41: getfield      #4                  // Field parent:Lorg/jboss/security/identity/Role;
      44: aload_2
      45: getfield      #4                  // Field parent:Lorg/jboss/security/identity/Role;
      48: invokevirtual #14                 // Method java/lang/Object.equals:(Ljava/lang/Object;)Z
      51: ifeq          58
      54: iconst_1
      55: goto          88
      58: iconst_0
      59: goto          88
      62: aload_0
      63: getfield      #3                  // Field roleName:Ljava/lang/String;
      66: aload_2
      67: getfield      #3                  // Field roleName:Ljava/lang/String;
      70: invokevirtual #9                  // Method java/lang/String.equals:(Ljava/lang/Object;)Z
      73: ifeq          87
      76: aload_2
      77: getfield      #4                  // Field parent:Lorg/jboss/security/identity/Role;
      80: ifnonnull     87
      83: iconst_1
      84: goto          88
      87: iconst_0
      88: ireturn
      89: iconst_0
      90: ireturn

  static {};
    Code:
       0: new           #7                  // class org/jboss/security/identity/plugins/SimpleRole
       3: dup
       4: ldc           #8                  // String <ANYBODY>
       6: invokespecial #15                 // Method "<init>":(Ljava/lang/String;)V
       9: putstatic     #16                 // Field ANYBODY_ROLE:Lorg/jboss/security/identity/Role;
      12: return
}
