Compiled from "TypeProxy.java"
public class org.assertj.core.internal.bytebuddy.implementation.auxiliary.TypeProxy$SilentConstruction$Appender implements org.assertj.core.internal.bytebuddy.implementation.bytecode.ByteCodeAppender {
  public static final java.lang.String REFLECTION_FACTORY_INTERNAL_NAME;

  public static final java.lang.String GET_REFLECTION_FACTORY_METHOD_NAME;

  public static final java.lang.String GET_REFLECTION_FACTORY_METHOD_DESCRIPTOR;

  public static final java.lang.String NEW_CONSTRUCTOR_FOR_SERIALIZATION_METHOD_NAME;

  public static final java.lang.String NEW_CONSTRUCTOR_FOR_SERIALIZATION_METHOD_DESCRIPTOR;

  public static final java.lang.String JAVA_LANG_OBJECT_DESCRIPTOR;

  public static final java.lang.String JAVA_LANG_OBJECT_INTERNAL_NAME;

  public static final java.lang.String JAVA_LANG_CONSTRUCTOR_INTERNAL_NAME;

  public static final java.lang.String NEW_INSTANCE_METHOD_NAME;

  public static final java.lang.String NEW_INSTANCE_METHOD_DESCRIPTOR;

  public static final java.lang.String JAVA_LANG_CLASS_INTERNAL_NAME;

  public static final java.lang.String GET_DECLARED_CONSTRUCTOR_METHOD_NAME;

  public static final java.lang.String GET_DECLARED_CONSTRUCTOR_METHOD_DESCRIPTOR;

  private final org.assertj.core.internal.bytebuddy.description.type.TypeDescription instrumentedType;

  private org.assertj.core.internal.bytebuddy.implementation.auxiliary.TypeProxy$SilentConstruction$Appender(org.assertj.core.internal.bytebuddy.description.type.TypeDescription);
    Code:
       0: aload_0
       1: invokespecial #69                 // Method java/lang/Object."<init>":()V
       4: aload_0
       5: aload_1
       6: putfield      #71                 // Field instrumentedType:Lorg/assertj/core/internal/bytebuddy/description/type/TypeDescription;
       9: return

  public org.assertj.core.internal.bytebuddy.implementation.bytecode.ByteCodeAppender$Size apply(org.assertj.core.internal.bytebuddy.jar.asm.MethodVisitor, org.assertj.core.internal.bytebuddy.implementation.Implementation$Context, org.assertj.core.internal.bytebuddy.description.method.MethodDescription);
    Code:
       0: aload_1
       1: sipush        184
       4: ldc           #27                 // String sun/reflect/ReflectionFactory
       6: ldc           #30                 // String getReflectionFactory
       8: ldc           #33                 // String ()Lsun/reflect/ReflectionFactory;
      10: iconst_0
      11: invokevirtual #81                 // Method org/assertj/core/internal/bytebuddy/jar/asm/MethodVisitor.visitMethodInsn:(ILjava/lang/String;Ljava/lang/String;Ljava/lang/String;Z)V
      14: aload_1
      15: aload_0
      16: getfield      #71                 // Field instrumentedType:Lorg/assertj/core/internal/bytebuddy/description/type/TypeDescription;
      19: invokeinterface #87,  1           // InterfaceMethod org/assertj/core/internal/bytebuddy/description/type/TypeDescription.getDescriptor:()Ljava/lang/String;
      24: invokestatic  #93                 // Method org/assertj/core/internal/bytebuddy/jar/asm/Type.getType:(Ljava/lang/String;)Lorg/assertj/core/internal/bytebuddy/jar/asm/Type;
      27: invokevirtual #97                 // Method org/assertj/core/internal/bytebuddy/jar/asm/MethodVisitor.visitLdcInsn:(Ljava/lang/Object;)V
      30: aload_1
      31: ldc           #42                 // String Ljava/lang/Object;
      33: invokestatic  #93                 // Method org/assertj/core/internal/bytebuddy/jar/asm/Type.getType:(Ljava/lang/String;)Lorg/assertj/core/internal/bytebuddy/jar/asm/Type;
      36: invokevirtual #97                 // Method org/assertj/core/internal/bytebuddy/jar/asm/MethodVisitor.visitLdcInsn:(Ljava/lang/Object;)V
      39: aload_1
      40: iconst_3
      41: invokevirtual #101                // Method org/assertj/core/internal/bytebuddy/jar/asm/MethodVisitor.visitInsn:(I)V
      44: aload_1
      45: sipush        189
      48: ldc           #56                 // String java/lang/Class
      50: invokevirtual #105                // Method org/assertj/core/internal/bytebuddy/jar/asm/MethodVisitor.visitTypeInsn:(ILjava/lang/String;)V
      53: aload_1
      54: sipush        182
      57: ldc           #56                 // String java/lang/Class
      59: ldc           #59                 // String getDeclaredConstructor
      61: ldc           #62                 // String ([Ljava/lang/Class;)Ljava/lang/reflect/Constructor;
      63: iconst_0
      64: invokevirtual #81                 // Method org/assertj/core/internal/bytebuddy/jar/asm/MethodVisitor.visitMethodInsn:(ILjava/lang/String;Ljava/lang/String;Ljava/lang/String;Z)V
      67: aload_1
      68: sipush        182
      71: ldc           #27                 // String sun/reflect/ReflectionFactory
      73: ldc           #36                 // String newConstructorForSerialization
      75: ldc           #39                 // String (Ljava/lang/Class;Ljava/lang/reflect/Constructor;)Ljava/lang/reflect/Constructor;
      77: iconst_0
      78: invokevirtual #81                 // Method org/assertj/core/internal/bytebuddy/jar/asm/MethodVisitor.visitMethodInsn:(ILjava/lang/String;Ljava/lang/String;Ljava/lang/String;Z)V
      81: aload_1
      82: iconst_3
      83: invokevirtual #101                // Method org/assertj/core/internal/bytebuddy/jar/asm/MethodVisitor.visitInsn:(I)V
      86: aload_1
      87: sipush        189
      90: ldc           #44                 // String java/lang/Object
      92: invokevirtual #105                // Method org/assertj/core/internal/bytebuddy/jar/asm/MethodVisitor.visitTypeInsn:(ILjava/lang/String;)V
      95: aload_1
      96: sipush        182
      99: ldc           #47                 // String java/lang/reflect/Constructor
     101: ldc           #50                 // String newInstance
     103: ldc           #53                 // String ([Ljava/lang/Object;)Ljava/lang/Object;
     105: iconst_0
     106: invokevirtual #81                 // Method org/assertj/core/internal/bytebuddy/jar/asm/MethodVisitor.visitMethodInsn:(ILjava/lang/String;Ljava/lang/String;Ljava/lang/String;Z)V
     109: aload_1
     110: sipush        192
     113: aload_0
     114: getfield      #71                 // Field instrumentedType:Lorg/assertj/core/internal/bytebuddy/description/type/TypeDescription;
     117: invokeinterface #108,  1          // InterfaceMethod org/assertj/core/internal/bytebuddy/description/type/TypeDescription.getInternalName:()Ljava/lang/String;
     122: invokevirtual #105                // Method org/assertj/core/internal/bytebuddy/jar/asm/MethodVisitor.visitTypeInsn:(ILjava/lang/String;)V
     125: aload_1
     126: sipush        176
     129: invokevirtual #101                // Method org/assertj/core/internal/bytebuddy/jar/asm/MethodVisitor.visitInsn:(I)V
     132: new           #20                 // class org/assertj/core/internal/bytebuddy/implementation/bytecode/ByteCodeAppender$Size
     135: dup
     136: iconst_4
     137: iconst_0
     138: invokespecial #111                // Method org/assertj/core/internal/bytebuddy/implementation/bytecode/ByteCodeAppender$Size."<init>":(II)V
     141: areturn

  public boolean equals(java.lang.Object);
    Code:
       0: aload_1
       1: aload_0
       2: if_acmpne     7
       5: iconst_1
       6: ireturn
       7: aload_1
       8: instanceof    #2                  // class org/assertj/core/internal/bytebuddy/implementation/auxiliary/TypeProxy$SilentConstruction$Appender
      11: ifne          16
      14: iconst_0
      15: ireturn
      16: aload_1
      17: checkcast     #2                  // class org/assertj/core/internal/bytebuddy/implementation/auxiliary/TypeProxy$SilentConstruction$Appender
      20: astore_2
      21: aload_2
      22: aload_0
      23: invokevirtual #122                // Method canEqual:(Ljava/lang/Object;)Z
      26: ifne          31
      29: iconst_0
      30: ireturn
      31: aload_0
      32: getfield      #71                 // Field instrumentedType:Lorg/assertj/core/internal/bytebuddy/description/type/TypeDescription;
      35: astore_3
      36: aload_2
      37: getfield      #71                 // Field instrumentedType:Lorg/assertj/core/internal/bytebuddy/description/type/TypeDescription;
      40: astore        4
      42: aload_3
      43: ifnonnull     54
      46: aload         4
      48: ifnull        65
      51: goto          63
      54: aload_3
      55: aload         4
      57: invokevirtual #124                // Method java/lang/Object.equals:(Ljava/lang/Object;)Z
      60: ifne          65
      63: iconst_0
      64: ireturn
      65: iconst_1
      66: ireturn

  protected boolean canEqual(java.lang.Object);
    Code:
       0: aload_1
       1: instanceof    #2                  // class org/assertj/core/internal/bytebuddy/implementation/auxiliary/TypeProxy$SilentConstruction$Appender
       4: ireturn

  public int hashCode();
    Code:
       0: bipush        59
       2: istore_1
       3: iconst_1
       4: istore_2
       5: aload_0
       6: getfield      #71                 // Field instrumentedType:Lorg/assertj/core/internal/bytebuddy/description/type/TypeDescription;
       9: astore_3
      10: iload_2
      11: bipush        59
      13: imul
      14: aload_3
      15: ifnonnull     23
      18: bipush        43
      20: goto          27
      23: aload_3
      24: invokevirtual #132                // Method java/lang/Object.hashCode:()I
      27: iadd
      28: istore_2
      29: iload_2
      30: ireturn

  org.assertj.core.internal.bytebuddy.implementation.auxiliary.TypeProxy$SilentConstruction$Appender(org.assertj.core.internal.bytebuddy.description.type.TypeDescription, org.assertj.core.internal.bytebuddy.implementation.auxiliary.TypeProxy$1);
    Code:
       0: aload_0
       1: aload_1
       2: invokespecial #139                // Method "<init>":(Lorg/assertj/core/internal/bytebuddy/description/type/TypeDescription;)V
       5: return
}
