Compiled from "ClassFileLocator.java"
public class org.assertj.core.internal.bytebuddy.dynamic.ClassFileLocator$Resolution$Explicit implements org.assertj.core.internal.bytebuddy.dynamic.ClassFileLocator$Resolution {
  private final byte[] binaryRepresentation;

  public org.assertj.core.internal.bytebuddy.dynamic.ClassFileLocator$Resolution$Explicit(byte[]);
    Code:
       0: aload_0
       1: invokespecial #23                 // Method java/lang/Object."<init>":()V
       4: aload_0
       5: aload_1
       6: putfield      #25                 // Field binaryRepresentation:[B
       9: return

  public boolean isResolved();
    Code:
       0: iconst_1
       1: ireturn

  public byte[] resolve();
    Code:
       0: aload_0
       1: getfield      #25                 // Field binaryRepresentation:[B
       4: areturn

  public boolean equals(java.lang.Object);
    Code:
       0: aload_1
       1: aload_0
       2: if_acmpne     7
       5: iconst_1
       6: ireturn
       7: aload_1
       8: instanceof    #2                  // class org/assertj/core/internal/bytebuddy/dynamic/ClassFileLocator$Resolution$Explicit
      11: ifne          16
      14: iconst_0
      15: ireturn
      16: aload_1
      17: checkcast     #2                  // class org/assertj/core/internal/bytebuddy/dynamic/ClassFileLocator$Resolution$Explicit
      20: astore_2
      21: aload_2
      22: aload_0
      23: invokevirtual #37                 // Method canEqual:(Ljava/lang/Object;)Z
      26: ifne          31
      29: iconst_0
      30: ireturn
      31: aload_0
      32: getfield      #25                 // Field binaryRepresentation:[B
      35: aload_2
      36: getfield      #25                 // Field binaryRepresentation:[B
      39: invokestatic  #42                 // Method java/util/Arrays.equals:([B[B)Z
      42: ifne          47
      45: iconst_0
      46: ireturn
      47: iconst_1
      48: ireturn

  protected boolean canEqual(java.lang.Object);
    Code:
       0: aload_1
       1: instanceof    #2                  // class org/assertj/core/internal/bytebuddy/dynamic/ClassFileLocator$Resolution$Explicit
       4: ireturn

  public int hashCode();
    Code:
       0: bipush        59
       2: istore_1
       3: iconst_1
       4: istore_2
       5: iload_2
       6: bipush        59
       8: imul
       9: aload_0
      10: getfield      #25                 // Field binaryRepresentation:[B
      13: invokestatic  #50                 // Method java/util/Arrays.hashCode:([B)I
      16: iadd
      17: istore_2
      18: iload_2
      19: ireturn
}
