Compiled from "DynamicType.java"
public abstract class org.assertj.core.internal.bytebuddy.dynamic.DynamicType$Builder$MethodDefinition$ExceptionDefinition$AbstractBase<V> extends org.assertj.core.internal.bytebuddy.dynamic.DynamicType$Builder$MethodDefinition$TypeVariableDefinition$AbstractBase<V> implements org.assertj.core.internal.bytebuddy.dynamic.DynamicType$Builder$MethodDefinition$ExceptionDefinition<V> {
  public org.assertj.core.internal.bytebuddy.dynamic.DynamicType$Builder$MethodDefinition$ExceptionDefinition$AbstractBase();
    Code:
       0: aload_0
       1: invokespecial #33                 // Method org/assertj/core/internal/bytebuddy/dynamic/DynamicType$Builder$MethodDefinition$TypeVariableDefinition$AbstractBase."<init>":()V
       4: return

  public org.assertj.core.internal.bytebuddy.dynamic.DynamicType$Builder$MethodDefinition$ExceptionDefinition<V> throwing(java.lang.reflect.Type...);
    Code:
       0: aload_0
       1: aload_1
       2: invokestatic  #44                 // Method java/util/Arrays.asList:([Ljava/lang/Object;)Ljava/util/List;
       5: invokevirtual #47                 // Method throwing:(Ljava/util/List;)Lorg/assertj/core/internal/bytebuddy/dynamic/DynamicType$Builder$MethodDefinition$ExceptionDefinition;
       8: areturn

  public org.assertj.core.internal.bytebuddy.dynamic.DynamicType$Builder$MethodDefinition$ExceptionDefinition<V> throwing(java.util.List<? extends java.lang.reflect.Type>);
    Code:
       0: aload_0
       1: new           #28                 // class org/assertj/core/internal/bytebuddy/description/type/TypeList$Generic$ForLoadedTypes
       4: dup
       5: aload_1
       6: invokespecial #52                 // Method org/assertj/core/internal/bytebuddy/description/type/TypeList$Generic$ForLoadedTypes."<init>":(Ljava/util/List;)V
       9: invokevirtual #55                 // Method throwing:(Ljava/util/Collection;)Lorg/assertj/core/internal/bytebuddy/dynamic/DynamicType$Builder$MethodDefinition$ExceptionDefinition;
      12: areturn

  public org.assertj.core.internal.bytebuddy.dynamic.DynamicType$Builder$MethodDefinition$ExceptionDefinition<V> throwing(org.assertj.core.internal.bytebuddy.description.type.TypeDefinition...);
    Code:
       0: aload_0
       1: aload_1
       2: invokestatic  #44                 // Method java/util/Arrays.asList:([Ljava/lang/Object;)Ljava/util/List;
       5: invokevirtual #55                 // Method throwing:(Ljava/util/Collection;)Lorg/assertj/core/internal/bytebuddy/dynamic/DynamicType$Builder$MethodDefinition$ExceptionDefinition;
       8: areturn
}
