Compiled from "JsonWriterSettings.java"
public class org.bson.json.JsonWriterSettings extends org.bson.BsonWriterSettings {
  private static final org.bson.json.JsonNullConverter JSON_NULL_CONVERTER;

  private static final org.bson.json.JsonStringConverter JSON_STRING_CONVERTER;

  private static final org.bson.json.JsonBooleanConverter JSON_BOOLEAN_CONVERTER;

  private static final org.bson.json.JsonDoubleConverter JSON_DOUBLE_CONVERTER;

  private static final org.bson.json.ExtendedJsonDoubleConverter EXTENDED_JSON_DOUBLE_CONVERTER;

  private static final org.bson.json.RelaxedExtendedJsonDoubleConverter RELAXED_EXTENDED_JSON_DOUBLE_CONVERTER;

  private static final org.bson.json.JsonInt32Converter JSON_INT_32_CONVERTER;

  private static final org.bson.json.ExtendedJsonInt32Converter EXTENDED_JSON_INT_32_CONVERTER;

  private static final org.bson.json.JsonSymbolConverter JSON_SYMBOL_CONVERTER;

  private static final org.bson.json.ExtendedJsonMinKeyConverter EXTENDED_JSON_MIN_KEY_CONVERTER;

  private static final org.bson.json.ShellMinKeyConverter SHELL_MIN_KEY_CONVERTER;

  private static final org.bson.json.ExtendedJsonMaxKeyConverter EXTENDED_JSON_MAX_KEY_CONVERTER;

  private static final org.bson.json.ShellMaxKeyConverter SHELL_MAX_KEY_CONVERTER;

  private static final org.bson.json.ExtendedJsonUndefinedConverter EXTENDED_JSON_UNDEFINED_CONVERTER;

  private static final org.bson.json.ShellUndefinedConverter SHELL_UNDEFINED_CONVERTER;

  private static final org.bson.json.LegacyExtendedJsonDateTimeConverter LEGACY_EXTENDED_JSON_DATE_TIME_CONVERTER;

  private static final org.bson.json.ExtendedJsonDateTimeConverter EXTENDED_JSON_DATE_TIME_CONVERTER;

  private static final org.bson.json.RelaxedExtendedJsonDateTimeConverter RELAXED_EXTENDED_JSON_DATE_TIME_CONVERTER;

  private static final org.bson.json.ShellDateTimeConverter SHELL_DATE_TIME_CONVERTER;

  private static final org.bson.json.ExtendedJsonBinaryConverter EXTENDED_JSON_BINARY_CONVERTER;

  private static final org.bson.json.LegacyExtendedJsonBinaryConverter LEGACY_EXTENDED_JSON_BINARY_CONVERTER;

  private static final org.bson.json.ShellBinaryConverter SHELL_BINARY_CONVERTER;

  private static final org.bson.json.ExtendedJsonInt64Converter EXTENDED_JSON_INT_64_CONVERTER;

  private static final org.bson.json.RelaxedExtendedJsonInt64Converter RELAXED_JSON_INT_64_CONVERTER;

  private static final org.bson.json.ShellInt64Converter SHELL_INT_64_CONVERTER;

  private static final org.bson.json.ExtendedJsonDecimal128Converter EXTENDED_JSON_DECIMAL_128_CONVERTER;

  private static final org.bson.json.ShellDecimal128Converter SHELL_DECIMAL_128_CONVERTER;

  private static final org.bson.json.ExtendedJsonObjectIdConverter EXTENDED_JSON_OBJECT_ID_CONVERTER;

  private static final org.bson.json.ShellObjectIdConverter SHELL_OBJECT_ID_CONVERTER;

  private static final org.bson.json.ExtendedJsonTimestampConverter EXTENDED_JSON_TIMESTAMP_CONVERTER;

  private static final org.bson.json.ShellTimestampConverter SHELL_TIMESTAMP_CONVERTER;

  private static final org.bson.json.ExtendedJsonRegularExpressionConverter EXTENDED_JSON_REGULAR_EXPRESSION_CONVERTER;

  private static final org.bson.json.LegacyExtendedJsonRegularExpressionConverter LEGACY_EXTENDED_JSON_REGULAR_EXPRESSION_CONVERTER;

  private static final org.bson.json.ShellRegularExpressionConverter SHELL_REGULAR_EXPRESSION_CONVERTER;

  private final boolean indent;

  private final java.lang.String newLineCharacters;

  private final java.lang.String indentCharacters;

  private final org.bson.json.JsonMode outputMode;

  private final org.bson.json.Converter<org.bson.BsonNull> nullConverter;

  private final org.bson.json.Converter<java.lang.String> stringConverter;

  private final org.bson.json.Converter<java.lang.Long> dateTimeConverter;

  private final org.bson.json.Converter<org.bson.BsonBinary> binaryConverter;

  private final org.bson.json.Converter<java.lang.Boolean> booleanConverter;

  private final org.bson.json.Converter<java.lang.Double> doubleConverter;

  private final org.bson.json.Converter<java.lang.Integer> int32Converter;

  private final org.bson.json.Converter<java.lang.Long> int64Converter;

  private final org.bson.json.Converter<org.bson.types.Decimal128> decimal128Converter;

  private final org.bson.json.Converter<org.bson.types.ObjectId> objectIdConverter;

  private final org.bson.json.Converter<org.bson.BsonTimestamp> timestampConverter;

  private final org.bson.json.Converter<org.bson.BsonRegularExpression> regularExpressionConverter;

  private final org.bson.json.Converter<java.lang.String> symbolConverter;

  private final org.bson.json.Converter<org.bson.BsonUndefined> undefinedConverter;

  private final org.bson.json.Converter<org.bson.BsonMinKey> minKeyConverter;

  private final org.bson.json.Converter<org.bson.BsonMaxKey> maxKeyConverter;

  private final org.bson.json.Converter<java.lang.String> javaScriptConverter;

  public static org.bson.json.JsonWriterSettings$Builder builder();
    Code:
       0: new           #2                  // class org/bson/json/JsonWriterSettings$Builder
       3: dup
       4: aconst_null
       5: invokespecial #3                  // Method org/bson/json/JsonWriterSettings$Builder."<init>":(Lorg/bson/json/JsonWriterSettings$1;)V
       8: areturn

  public org.bson.json.JsonWriterSettings();
    Code:
       0: aload_0
       1: invokestatic  #4                  // Method builder:()Lorg/bson/json/JsonWriterSettings$Builder;
       4: getstatic     #5                  // Field org/bson/json/JsonMode.STRICT:Lorg/bson/json/JsonMode;
       7: invokevirtual #6                  // Method org/bson/json/JsonWriterSettings$Builder.outputMode:(Lorg/bson/json/JsonMode;)Lorg/bson/json/JsonWriterSettings$Builder;
      10: invokespecial #1                  // Method "<init>":(Lorg/bson/json/JsonWriterSettings$Builder;)V
      13: return

  public org.bson.json.JsonWriterSettings(org.bson.json.JsonMode);
    Code:
       0: aload_0
       1: invokestatic  #4                  // Method builder:()Lorg/bson/json/JsonWriterSettings$Builder;
       4: aload_1
       5: invokevirtual #6                  // Method org/bson/json/JsonWriterSettings$Builder.outputMode:(Lorg/bson/json/JsonMode;)Lorg/bson/json/JsonWriterSettings$Builder;
       8: invokespecial #1                  // Method "<init>":(Lorg/bson/json/JsonWriterSettings$Builder;)V
      11: return

  public org.bson.json.JsonWriterSettings(boolean);
    Code:
       0: aload_0
       1: invokestatic  #4                  // Method builder:()Lorg/bson/json/JsonWriterSettings$Builder;
       4: iload_1
       5: invokevirtual #7                  // Method org/bson/json/JsonWriterSettings$Builder.indent:(Z)Lorg/bson/json/JsonWriterSettings$Builder;
       8: invokespecial #1                  // Method "<init>":(Lorg/bson/json/JsonWriterSettings$Builder;)V
      11: return

  public org.bson.json.JsonWriterSettings(org.bson.json.JsonMode, boolean);
    Code:
       0: aload_0
       1: invokestatic  #4                  // Method builder:()Lorg/bson/json/JsonWriterSettings$Builder;
       4: aload_1
       5: invokevirtual #6                  // Method org/bson/json/JsonWriterSettings$Builder.outputMode:(Lorg/bson/json/JsonMode;)Lorg/bson/json/JsonWriterSettings$Builder;
       8: iload_2
       9: invokevirtual #7                  // Method org/bson/json/JsonWriterSettings$Builder.indent:(Z)Lorg/bson/json/JsonWriterSettings$Builder;
      12: invokespecial #1                  // Method "<init>":(Lorg/bson/json/JsonWriterSettings$Builder;)V
      15: return

  public org.bson.json.JsonWriterSettings(org.bson.json.JsonMode, java.lang.String);
    Code:
       0: aload_0
       1: invokestatic  #4                  // Method builder:()Lorg/bson/json/JsonWriterSettings$Builder;
       4: aload_1
       5: invokevirtual #6                  // Method org/bson/json/JsonWriterSettings$Builder.outputMode:(Lorg/bson/json/JsonMode;)Lorg/bson/json/JsonWriterSettings$Builder;
       8: iconst_1
       9: invokevirtual #7                  // Method org/bson/json/JsonWriterSettings$Builder.indent:(Z)Lorg/bson/json/JsonWriterSettings$Builder;
      12: aload_2
      13: invokevirtual #8                  // Method org/bson/json/JsonWriterSettings$Builder.indentCharacters:(Ljava/lang/String;)Lorg/bson/json/JsonWriterSettings$Builder;
      16: invokespecial #1                  // Method "<init>":(Lorg/bson/json/JsonWriterSettings$Builder;)V
      19: return

  public org.bson.json.JsonWriterSettings(org.bson.json.JsonMode, java.lang.String, java.lang.String);
    Code:
       0: aload_0
       1: invokestatic  #4                  // Method builder:()Lorg/bson/json/JsonWriterSettings$Builder;
       4: aload_1
       5: invokevirtual #6                  // Method org/bson/json/JsonWriterSettings$Builder.outputMode:(Lorg/bson/json/JsonMode;)Lorg/bson/json/JsonWriterSettings$Builder;
       8: iconst_1
       9: invokevirtual #7                  // Method org/bson/json/JsonWriterSettings$Builder.indent:(Z)Lorg/bson/json/JsonWriterSettings$Builder;
      12: aload_2
      13: invokevirtual #8                  // Method org/bson/json/JsonWriterSettings$Builder.indentCharacters:(Ljava/lang/String;)Lorg/bson/json/JsonWriterSettings$Builder;
      16: aload_3
      17: invokevirtual #9                  // Method org/bson/json/JsonWriterSettings$Builder.newLineCharacters:(Ljava/lang/String;)Lorg/bson/json/JsonWriterSettings$Builder;
      20: invokespecial #1                  // Method "<init>":(Lorg/bson/json/JsonWriterSettings$Builder;)V
      23: return

  private org.bson.json.JsonWriterSettings(org.bson.json.JsonWriterSettings$Builder);
    Code:
       0: aload_0
       1: invokespecial #10                 // Method org/bson/BsonWriterSettings."<init>":()V
       4: aload_0
       5: aload_1
       6: invokestatic  #11                 // Method org/bson/json/JsonWriterSettings$Builder.access$100:(Lorg/bson/json/JsonWriterSettings$Builder;)Z
       9: putfield      #12                 // Field indent:Z
      12: aload_0
      13: aload_1
      14: invokestatic  #13                 // Method org/bson/json/JsonWriterSettings$Builder.access$200:(Lorg/bson/json/JsonWriterSettings$Builder;)Ljava/lang/String;
      17: ifnull        27
      20: aload_1
      21: invokestatic  #13                 // Method org/bson/json/JsonWriterSettings$Builder.access$200:(Lorg/bson/json/JsonWriterSettings$Builder;)Ljava/lang/String;
      24: goto          32
      27: ldc           #14                 // String line.separator
      29: invokestatic  #15                 // Method java/lang/System.getProperty:(Ljava/lang/String;)Ljava/lang/String;
      32: putfield      #16                 // Field newLineCharacters:Ljava/lang/String;
      35: aload_0
      36: aload_1
      37: invokestatic  #17                 // Method org/bson/json/JsonWriterSettings$Builder.access$300:(Lorg/bson/json/JsonWriterSettings$Builder;)Ljava/lang/String;
      40: putfield      #18                 // Field indentCharacters:Ljava/lang/String;
      43: aload_0
      44: aload_1
      45: invokestatic  #19                 // Method org/bson/json/JsonWriterSettings$Builder.access$400:(Lorg/bson/json/JsonWriterSettings$Builder;)Lorg/bson/json/JsonMode;
      48: putfield      #20                 // Field outputMode:Lorg/bson/json/JsonMode;
      51: aload_1
      52: invokestatic  #21                 // Method org/bson/json/JsonWriterSettings$Builder.access$500:(Lorg/bson/json/JsonWriterSettings$Builder;)Lorg/bson/json/Converter;
      55: ifnull        69
      58: aload_0
      59: aload_1
      60: invokestatic  #21                 // Method org/bson/json/JsonWriterSettings$Builder.access$500:(Lorg/bson/json/JsonWriterSettings$Builder;)Lorg/bson/json/Converter;
      63: putfield      #22                 // Field nullConverter:Lorg/bson/json/Converter;
      66: goto          76
      69: aload_0
      70: getstatic     #23                 // Field JSON_NULL_CONVERTER:Lorg/bson/json/JsonNullConverter;
      73: putfield      #22                 // Field nullConverter:Lorg/bson/json/Converter;
      76: aload_1
      77: invokestatic  #24                 // Method org/bson/json/JsonWriterSettings$Builder.access$600:(Lorg/bson/json/JsonWriterSettings$Builder;)Lorg/bson/json/Converter;
      80: ifnull        94
      83: aload_0
      84: aload_1
      85: invokestatic  #24                 // Method org/bson/json/JsonWriterSettings$Builder.access$600:(Lorg/bson/json/JsonWriterSettings$Builder;)Lorg/bson/json/Converter;
      88: putfield      #25                 // Field stringConverter:Lorg/bson/json/Converter;
      91: goto          101
      94: aload_0
      95: getstatic     #26                 // Field JSON_STRING_CONVERTER:Lorg/bson/json/JsonStringConverter;
      98: putfield      #25                 // Field stringConverter:Lorg/bson/json/Converter;
     101: aload_1
     102: invokestatic  #27                 // Method org/bson/json/JsonWriterSettings$Builder.access$700:(Lorg/bson/json/JsonWriterSettings$Builder;)Lorg/bson/json/Converter;
     105: ifnull        119
     108: aload_0
     109: aload_1
     110: invokestatic  #27                 // Method org/bson/json/JsonWriterSettings$Builder.access$700:(Lorg/bson/json/JsonWriterSettings$Builder;)Lorg/bson/json/Converter;
     113: putfield      #28                 // Field booleanConverter:Lorg/bson/json/Converter;
     116: goto          126
     119: aload_0
     120: getstatic     #29                 // Field JSON_BOOLEAN_CONVERTER:Lorg/bson/json/JsonBooleanConverter;
     123: putfield      #28                 // Field booleanConverter:Lorg/bson/json/Converter;
     126: aload_1
     127: invokestatic  #30                 // Method org/bson/json/JsonWriterSettings$Builder.access$800:(Lorg/bson/json/JsonWriterSettings$Builder;)Lorg/bson/json/Converter;
     130: ifnull        144
     133: aload_0
     134: aload_1
     135: invokestatic  #30                 // Method org/bson/json/JsonWriterSettings$Builder.access$800:(Lorg/bson/json/JsonWriterSettings$Builder;)Lorg/bson/json/Converter;
     138: putfield      #31                 // Field doubleConverter:Lorg/bson/json/Converter;
     141: goto          191
     144: aload_0
     145: getfield      #20                 // Field outputMode:Lorg/bson/json/JsonMode;
     148: getstatic     #32                 // Field org/bson/json/JsonMode.EXTENDED:Lorg/bson/json/JsonMode;
     151: if_acmpne     164
     154: aload_0
     155: getstatic     #33                 // Field EXTENDED_JSON_DOUBLE_CONVERTER:Lorg/bson/json/ExtendedJsonDoubleConverter;
     158: putfield      #31                 // Field doubleConverter:Lorg/bson/json/Converter;
     161: goto          191
     164: aload_0
     165: getfield      #20                 // Field outputMode:Lorg/bson/json/JsonMode;
     168: getstatic     #34                 // Field org/bson/json/JsonMode.RELAXED:Lorg/bson/json/JsonMode;
     171: if_acmpne     184
     174: aload_0
     175: getstatic     #35                 // Field RELAXED_EXTENDED_JSON_DOUBLE_CONVERTER:Lorg/bson/json/RelaxedExtendedJsonDoubleConverter;
     178: putfield      #31                 // Field doubleConverter:Lorg/bson/json/Converter;
     181: goto          191
     184: aload_0
     185: getstatic     #36                 // Field JSON_DOUBLE_CONVERTER:Lorg/bson/json/JsonDoubleConverter;
     188: putfield      #31                 // Field doubleConverter:Lorg/bson/json/Converter;
     191: aload_1
     192: invokestatic  #37                 // Method org/bson/json/JsonWriterSettings$Builder.access$900:(Lorg/bson/json/JsonWriterSettings$Builder;)Lorg/bson/json/Converter;
     195: ifnull        209
     198: aload_0
     199: aload_1
     200: invokestatic  #37                 // Method org/bson/json/JsonWriterSettings$Builder.access$900:(Lorg/bson/json/JsonWriterSettings$Builder;)Lorg/bson/json/Converter;
     203: putfield      #38                 // Field int32Converter:Lorg/bson/json/Converter;
     206: goto          236
     209: aload_0
     210: getfield      #20                 // Field outputMode:Lorg/bson/json/JsonMode;
     213: getstatic     #32                 // Field org/bson/json/JsonMode.EXTENDED:Lorg/bson/json/JsonMode;
     216: if_acmpne     229
     219: aload_0
     220: getstatic     #39                 // Field EXTENDED_JSON_INT_32_CONVERTER:Lorg/bson/json/ExtendedJsonInt32Converter;
     223: putfield      #38                 // Field int32Converter:Lorg/bson/json/Converter;
     226: goto          236
     229: aload_0
     230: getstatic     #40                 // Field JSON_INT_32_CONVERTER:Lorg/bson/json/JsonInt32Converter;
     233: putfield      #38                 // Field int32Converter:Lorg/bson/json/Converter;
     236: aload_1
     237: invokestatic  #41                 // Method org/bson/json/JsonWriterSettings$Builder.access$1000:(Lorg/bson/json/JsonWriterSettings$Builder;)Lorg/bson/json/Converter;
     240: ifnull        254
     243: aload_0
     244: aload_1
     245: invokestatic  #41                 // Method org/bson/json/JsonWriterSettings$Builder.access$1000:(Lorg/bson/json/JsonWriterSettings$Builder;)Lorg/bson/json/Converter;
     248: putfield      #42                 // Field symbolConverter:Lorg/bson/json/Converter;
     251: goto          261
     254: aload_0
     255: getstatic     #43                 // Field JSON_SYMBOL_CONVERTER:Lorg/bson/json/JsonSymbolConverter;
     258: putfield      #42                 // Field symbolConverter:Lorg/bson/json/Converter;
     261: aload_1
     262: invokestatic  #44                 // Method org/bson/json/JsonWriterSettings$Builder.access$1100:(Lorg/bson/json/JsonWriterSettings$Builder;)Lorg/bson/json/Converter;
     265: ifnull        279
     268: aload_0
     269: aload_1
     270: invokestatic  #44                 // Method org/bson/json/JsonWriterSettings$Builder.access$1100:(Lorg/bson/json/JsonWriterSettings$Builder;)Lorg/bson/json/Converter;
     273: putfield      #45                 // Field javaScriptConverter:Lorg/bson/json/Converter;
     276: goto          290
     279: aload_0
     280: new           #46                 // class org/bson/json/JsonJavaScriptConverter
     283: dup
     284: invokespecial #47                 // Method org/bson/json/JsonJavaScriptConverter."<init>":()V
     287: putfield      #45                 // Field javaScriptConverter:Lorg/bson/json/Converter;
     290: aload_1
     291: invokestatic  #48                 // Method org/bson/json/JsonWriterSettings$Builder.access$1200:(Lorg/bson/json/JsonWriterSettings$Builder;)Lorg/bson/json/Converter;
     294: ifnull        308
     297: aload_0
     298: aload_1
     299: invokestatic  #48                 // Method org/bson/json/JsonWriterSettings$Builder.access$1200:(Lorg/bson/json/JsonWriterSettings$Builder;)Lorg/bson/json/Converter;
     302: putfield      #49                 // Field minKeyConverter:Lorg/bson/json/Converter;
     305: goto          355
     308: aload_0
     309: getfield      #20                 // Field outputMode:Lorg/bson/json/JsonMode;
     312: getstatic     #5                  // Field org/bson/json/JsonMode.STRICT:Lorg/bson/json/JsonMode;
     315: if_acmpeq     338
     318: aload_0
     319: getfield      #20                 // Field outputMode:Lorg/bson/json/JsonMode;
     322: getstatic     #32                 // Field org/bson/json/JsonMode.EXTENDED:Lorg/bson/json/JsonMode;
     325: if_acmpeq     338
     328: aload_0
     329: getfield      #20                 // Field outputMode:Lorg/bson/json/JsonMode;
     332: getstatic     #34                 // Field org/bson/json/JsonMode.RELAXED:Lorg/bson/json/JsonMode;
     335: if_acmpne     348
     338: aload_0
     339: getstatic     #50                 // Field EXTENDED_JSON_MIN_KEY_CONVERTER:Lorg/bson/json/ExtendedJsonMinKeyConverter;
     342: putfield      #49                 // Field minKeyConverter:Lorg/bson/json/Converter;
     345: goto          355
     348: aload_0
     349: getstatic     #51                 // Field SHELL_MIN_KEY_CONVERTER:Lorg/bson/json/ShellMinKeyConverter;
     352: putfield      #49                 // Field minKeyConverter:Lorg/bson/json/Converter;
     355: aload_1
     356: invokestatic  #52                 // Method org/bson/json/JsonWriterSettings$Builder.access$1300:(Lorg/bson/json/JsonWriterSettings$Builder;)Lorg/bson/json/Converter;
     359: ifnull        373
     362: aload_0
     363: aload_1
     364: invokestatic  #52                 // Method org/bson/json/JsonWriterSettings$Builder.access$1300:(Lorg/bson/json/JsonWriterSettings$Builder;)Lorg/bson/json/Converter;
     367: putfield      #53                 // Field maxKeyConverter:Lorg/bson/json/Converter;
     370: goto          420
     373: aload_0
     374: getfield      #20                 // Field outputMode:Lorg/bson/json/JsonMode;
     377: getstatic     #5                  // Field org/bson/json/JsonMode.STRICT:Lorg/bson/json/JsonMode;
     380: if_acmpeq     403
     383: aload_0
     384: getfield      #20                 // Field outputMode:Lorg/bson/json/JsonMode;
     387: getstatic     #32                 // Field org/bson/json/JsonMode.EXTENDED:Lorg/bson/json/JsonMode;
     390: if_acmpeq     403
     393: aload_0
     394: getfield      #20                 // Field outputMode:Lorg/bson/json/JsonMode;
     397: getstatic     #34                 // Field org/bson/json/JsonMode.RELAXED:Lorg/bson/json/JsonMode;
     400: if_acmpne     413
     403: aload_0
     404: getstatic     #54                 // Field EXTENDED_JSON_MAX_KEY_CONVERTER:Lorg/bson/json/ExtendedJsonMaxKeyConverter;
     407: putfield      #53                 // Field maxKeyConverter:Lorg/bson/json/Converter;
     410: goto          420
     413: aload_0
     414: getstatic     #55                 // Field SHELL_MAX_KEY_CONVERTER:Lorg/bson/json/ShellMaxKeyConverter;
     417: putfield      #53                 // Field maxKeyConverter:Lorg/bson/json/Converter;
     420: aload_1
     421: invokestatic  #56                 // Method org/bson/json/JsonWriterSettings$Builder.access$1400:(Lorg/bson/json/JsonWriterSettings$Builder;)Lorg/bson/json/Converter;
     424: ifnull        438
     427: aload_0
     428: aload_1
     429: invokestatic  #56                 // Method org/bson/json/JsonWriterSettings$Builder.access$1400:(Lorg/bson/json/JsonWriterSettings$Builder;)Lorg/bson/json/Converter;
     432: putfield      #57                 // Field undefinedConverter:Lorg/bson/json/Converter;
     435: goto          485
     438: aload_0
     439: getfield      #20                 // Field outputMode:Lorg/bson/json/JsonMode;
     442: getstatic     #5                  // Field org/bson/json/JsonMode.STRICT:Lorg/bson/json/JsonMode;
     445: if_acmpeq     468
     448: aload_0
     449: getfield      #20                 // Field outputMode:Lorg/bson/json/JsonMode;
     452: getstatic     #32                 // Field org/bson/json/JsonMode.EXTENDED:Lorg/bson/json/JsonMode;
     455: if_acmpeq     468
     458: aload_0
     459: getfield      #20                 // Field outputMode:Lorg/bson/json/JsonMode;
     462: getstatic     #34                 // Field org/bson/json/JsonMode.RELAXED:Lorg/bson/json/JsonMode;
     465: if_acmpne     478
     468: aload_0
     469: getstatic     #58                 // Field EXTENDED_JSON_UNDEFINED_CONVERTER:Lorg/bson/json/ExtendedJsonUndefinedConverter;
     472: putfield      #57                 // Field undefinedConverter:Lorg/bson/json/Converter;
     475: goto          485
     478: aload_0
     479: getstatic     #59                 // Field SHELL_UNDEFINED_CONVERTER:Lorg/bson/json/ShellUndefinedConverter;
     482: putfield      #57                 // Field undefinedConverter:Lorg/bson/json/Converter;
     485: aload_1
     486: invokestatic  #60                 // Method org/bson/json/JsonWriterSettings$Builder.access$1500:(Lorg/bson/json/JsonWriterSettings$Builder;)Lorg/bson/json/Converter;
     489: ifnull        503
     492: aload_0
     493: aload_1
     494: invokestatic  #60                 // Method org/bson/json/JsonWriterSettings$Builder.access$1500:(Lorg/bson/json/JsonWriterSettings$Builder;)Lorg/bson/json/Converter;
     497: putfield      #61                 // Field dateTimeConverter:Lorg/bson/json/Converter;
     500: goto          570
     503: aload_0
     504: getfield      #20                 // Field outputMode:Lorg/bson/json/JsonMode;
     507: getstatic     #5                  // Field org/bson/json/JsonMode.STRICT:Lorg/bson/json/JsonMode;
     510: if_acmpne     523
     513: aload_0
     514: getstatic     #62                 // Field LEGACY_EXTENDED_JSON_DATE_TIME_CONVERTER:Lorg/bson/json/LegacyExtendedJsonDateTimeConverter;
     517: putfield      #61                 // Field dateTimeConverter:Lorg/bson/json/Converter;
     520: goto          570
     523: aload_0
     524: getfield      #20                 // Field outputMode:Lorg/bson/json/JsonMode;
     527: getstatic     #32                 // Field org/bson/json/JsonMode.EXTENDED:Lorg/bson/json/JsonMode;
     530: if_acmpne     543
     533: aload_0
     534: getstatic     #63                 // Field EXTENDED_JSON_DATE_TIME_CONVERTER:Lorg/bson/json/ExtendedJsonDateTimeConverter;
     537: putfield      #61                 // Field dateTimeConverter:Lorg/bson/json/Converter;
     540: goto          570
     543: aload_0
     544: getfield      #20                 // Field outputMode:Lorg/bson/json/JsonMode;
     547: getstatic     #34                 // Field org/bson/json/JsonMode.RELAXED:Lorg/bson/json/JsonMode;
     550: if_acmpne     563
     553: aload_0
     554: getstatic     #64                 // Field RELAXED_EXTENDED_JSON_DATE_TIME_CONVERTER:Lorg/bson/json/RelaxedExtendedJsonDateTimeConverter;
     557: putfield      #61                 // Field dateTimeConverter:Lorg/bson/json/Converter;
     560: goto          570
     563: aload_0
     564: getstatic     #65                 // Field SHELL_DATE_TIME_CONVERTER:Lorg/bson/json/ShellDateTimeConverter;
     567: putfield      #61                 // Field dateTimeConverter:Lorg/bson/json/Converter;
     570: aload_1
     571: invokestatic  #66                 // Method org/bson/json/JsonWriterSettings$Builder.access$1600:(Lorg/bson/json/JsonWriterSettings$Builder;)Lorg/bson/json/Converter;
     574: ifnull        588
     577: aload_0
     578: aload_1
     579: invokestatic  #66                 // Method org/bson/json/JsonWriterSettings$Builder.access$1600:(Lorg/bson/json/JsonWriterSettings$Builder;)Lorg/bson/json/Converter;
     582: putfield      #67                 // Field binaryConverter:Lorg/bson/json/Converter;
     585: goto          645
     588: aload_0
     589: getfield      #20                 // Field outputMode:Lorg/bson/json/JsonMode;
     592: getstatic     #5                  // Field org/bson/json/JsonMode.STRICT:Lorg/bson/json/JsonMode;
     595: if_acmpne     608
     598: aload_0
     599: getstatic     #68                 // Field LEGACY_EXTENDED_JSON_BINARY_CONVERTER:Lorg/bson/json/LegacyExtendedJsonBinaryConverter;
     602: putfield      #67                 // Field binaryConverter:Lorg/bson/json/Converter;
     605: goto          645
     608: aload_0
     609: getfield      #20                 // Field outputMode:Lorg/bson/json/JsonMode;
     612: getstatic     #32                 // Field org/bson/json/JsonMode.EXTENDED:Lorg/bson/json/JsonMode;
     615: if_acmpeq     628
     618: aload_0
     619: getfield      #20                 // Field outputMode:Lorg/bson/json/JsonMode;
     622: getstatic     #34                 // Field org/bson/json/JsonMode.RELAXED:Lorg/bson/json/JsonMode;
     625: if_acmpne     638
     628: aload_0
     629: getstatic     #69                 // Field EXTENDED_JSON_BINARY_CONVERTER:Lorg/bson/json/ExtendedJsonBinaryConverter;
     632: putfield      #67                 // Field binaryConverter:Lorg/bson/json/Converter;
     635: goto          645
     638: aload_0
     639: getstatic     #70                 // Field SHELL_BINARY_CONVERTER:Lorg/bson/json/ShellBinaryConverter;
     642: putfield      #67                 // Field binaryConverter:Lorg/bson/json/Converter;
     645: aload_1
     646: invokestatic  #71                 // Method org/bson/json/JsonWriterSettings$Builder.access$1700:(Lorg/bson/json/JsonWriterSettings$Builder;)Lorg/bson/json/Converter;
     649: ifnull        663
     652: aload_0
     653: aload_1
     654: invokestatic  #71                 // Method org/bson/json/JsonWriterSettings$Builder.access$1700:(Lorg/bson/json/JsonWriterSettings$Builder;)Lorg/bson/json/Converter;
     657: putfield      #72                 // Field int64Converter:Lorg/bson/json/Converter;
     660: goto          720
     663: aload_0
     664: getfield      #20                 // Field outputMode:Lorg/bson/json/JsonMode;
     667: getstatic     #5                  // Field org/bson/json/JsonMode.STRICT:Lorg/bson/json/JsonMode;
     670: if_acmpeq     683
     673: aload_0
     674: getfield      #20                 // Field outputMode:Lorg/bson/json/JsonMode;
     677: getstatic     #32                 // Field org/bson/json/JsonMode.EXTENDED:Lorg/bson/json/JsonMode;
     680: if_acmpne     693
     683: aload_0
     684: getstatic     #73                 // Field EXTENDED_JSON_INT_64_CONVERTER:Lorg/bson/json/ExtendedJsonInt64Converter;
     687: putfield      #72                 // Field int64Converter:Lorg/bson/json/Converter;
     690: goto          720
     693: aload_0
     694: getfield      #20                 // Field outputMode:Lorg/bson/json/JsonMode;
     697: getstatic     #34                 // Field org/bson/json/JsonMode.RELAXED:Lorg/bson/json/JsonMode;
     700: if_acmpne     713
     703: aload_0
     704: getstatic     #74                 // Field RELAXED_JSON_INT_64_CONVERTER:Lorg/bson/json/RelaxedExtendedJsonInt64Converter;
     707: putfield      #72                 // Field int64Converter:Lorg/bson/json/Converter;
     710: goto          720
     713: aload_0
     714: getstatic     #75                 // Field SHELL_INT_64_CONVERTER:Lorg/bson/json/ShellInt64Converter;
     717: putfield      #72                 // Field int64Converter:Lorg/bson/json/Converter;
     720: aload_1
     721: invokestatic  #76                 // Method org/bson/json/JsonWriterSettings$Builder.access$1800:(Lorg/bson/json/JsonWriterSettings$Builder;)Lorg/bson/json/Converter;
     724: ifnull        738
     727: aload_0
     728: aload_1
     729: invokestatic  #76                 // Method org/bson/json/JsonWriterSettings$Builder.access$1800:(Lorg/bson/json/JsonWriterSettings$Builder;)Lorg/bson/json/Converter;
     732: putfield      #77                 // Field decimal128Converter:Lorg/bson/json/Converter;
     735: goto          785
     738: aload_0
     739: getfield      #20                 // Field outputMode:Lorg/bson/json/JsonMode;
     742: getstatic     #5                  // Field org/bson/json/JsonMode.STRICT:Lorg/bson/json/JsonMode;
     745: if_acmpeq     768
     748: aload_0
     749: getfield      #20                 // Field outputMode:Lorg/bson/json/JsonMode;
     752: getstatic     #32                 // Field org/bson/json/JsonMode.EXTENDED:Lorg/bson/json/JsonMode;
     755: if_acmpeq     768
     758: aload_0
     759: getfield      #20                 // Field outputMode:Lorg/bson/json/JsonMode;
     762: getstatic     #34                 // Field org/bson/json/JsonMode.RELAXED:Lorg/bson/json/JsonMode;
     765: if_acmpne     778
     768: aload_0
     769: getstatic     #78                 // Field EXTENDED_JSON_DECIMAL_128_CONVERTER:Lorg/bson/json/ExtendedJsonDecimal128Converter;
     772: putfield      #77                 // Field decimal128Converter:Lorg/bson/json/Converter;
     775: goto          785
     778: aload_0
     779: getstatic     #79                 // Field SHELL_DECIMAL_128_CONVERTER:Lorg/bson/json/ShellDecimal128Converter;
     782: putfield      #77                 // Field decimal128Converter:Lorg/bson/json/Converter;
     785: aload_1
     786: invokestatic  #80                 // Method org/bson/json/JsonWriterSettings$Builder.access$1900:(Lorg/bson/json/JsonWriterSettings$Builder;)Lorg/bson/json/Converter;
     789: ifnull        803
     792: aload_0
     793: aload_1
     794: invokestatic  #80                 // Method org/bson/json/JsonWriterSettings$Builder.access$1900:(Lorg/bson/json/JsonWriterSettings$Builder;)Lorg/bson/json/Converter;
     797: putfield      #81                 // Field objectIdConverter:Lorg/bson/json/Converter;
     800: goto          850
     803: aload_0
     804: getfield      #20                 // Field outputMode:Lorg/bson/json/JsonMode;
     807: getstatic     #5                  // Field org/bson/json/JsonMode.STRICT:Lorg/bson/json/JsonMode;
     810: if_acmpeq     833
     813: aload_0
     814: getfield      #20                 // Field outputMode:Lorg/bson/json/JsonMode;
     817: getstatic     #32                 // Field org/bson/json/JsonMode.EXTENDED:Lorg/bson/json/JsonMode;
     820: if_acmpeq     833
     823: aload_0
     824: getfield      #20                 // Field outputMode:Lorg/bson/json/JsonMode;
     827: getstatic     #34                 // Field org/bson/json/JsonMode.RELAXED:Lorg/bson/json/JsonMode;
     830: if_acmpne     843
     833: aload_0
     834: getstatic     #82                 // Field EXTENDED_JSON_OBJECT_ID_CONVERTER:Lorg/bson/json/ExtendedJsonObjectIdConverter;
     837: putfield      #81                 // Field objectIdConverter:Lorg/bson/json/Converter;
     840: goto          850
     843: aload_0
     844: getstatic     #83                 // Field SHELL_OBJECT_ID_CONVERTER:Lorg/bson/json/ShellObjectIdConverter;
     847: putfield      #81                 // Field objectIdConverter:Lorg/bson/json/Converter;
     850: aload_1
     851: invokestatic  #84                 // Method org/bson/json/JsonWriterSettings$Builder.access$2000:(Lorg/bson/json/JsonWriterSettings$Builder;)Lorg/bson/json/Converter;
     854: ifnull        868
     857: aload_0
     858: aload_1
     859: invokestatic  #84                 // Method org/bson/json/JsonWriterSettings$Builder.access$2000:(Lorg/bson/json/JsonWriterSettings$Builder;)Lorg/bson/json/Converter;
     862: putfield      #85                 // Field timestampConverter:Lorg/bson/json/Converter;
     865: goto          915
     868: aload_0
     869: getfield      #20                 // Field outputMode:Lorg/bson/json/JsonMode;
     872: getstatic     #5                  // Field org/bson/json/JsonMode.STRICT:Lorg/bson/json/JsonMode;
     875: if_acmpeq     898
     878: aload_0
     879: getfield      #20                 // Field outputMode:Lorg/bson/json/JsonMode;
     882: getstatic     #32                 // Field org/bson/json/JsonMode.EXTENDED:Lorg/bson/json/JsonMode;
     885: if_acmpeq     898
     888: aload_0
     889: getfield      #20                 // Field outputMode:Lorg/bson/json/JsonMode;
     892: getstatic     #34                 // Field org/bson/json/JsonMode.RELAXED:Lorg/bson/json/JsonMode;
     895: if_acmpne     908
     898: aload_0
     899: getstatic     #86                 // Field EXTENDED_JSON_TIMESTAMP_CONVERTER:Lorg/bson/json/ExtendedJsonTimestampConverter;
     902: putfield      #85                 // Field timestampConverter:Lorg/bson/json/Converter;
     905: goto          915
     908: aload_0
     909: getstatic     #87                 // Field SHELL_TIMESTAMP_CONVERTER:Lorg/bson/json/ShellTimestampConverter;
     912: putfield      #85                 // Field timestampConverter:Lorg/bson/json/Converter;
     915: aload_1
     916: invokestatic  #88                 // Method org/bson/json/JsonWriterSettings$Builder.access$2100:(Lorg/bson/json/JsonWriterSettings$Builder;)Lorg/bson/json/Converter;
     919: ifnull        933
     922: aload_0
     923: aload_1
     924: invokestatic  #88                 // Method org/bson/json/JsonWriterSettings$Builder.access$2100:(Lorg/bson/json/JsonWriterSettings$Builder;)Lorg/bson/json/Converter;
     927: putfield      #89                 // Field regularExpressionConverter:Lorg/bson/json/Converter;
     930: goto          990
     933: aload_0
     934: getfield      #20                 // Field outputMode:Lorg/bson/json/JsonMode;
     937: getstatic     #32                 // Field org/bson/json/JsonMode.EXTENDED:Lorg/bson/json/JsonMode;
     940: if_acmpeq     953
     943: aload_0
     944: getfield      #20                 // Field outputMode:Lorg/bson/json/JsonMode;
     947: getstatic     #34                 // Field org/bson/json/JsonMode.RELAXED:Lorg/bson/json/JsonMode;
     950: if_acmpne     963
     953: aload_0
     954: getstatic     #90                 // Field EXTENDED_JSON_REGULAR_EXPRESSION_CONVERTER:Lorg/bson/json/ExtendedJsonRegularExpressionConverter;
     957: putfield      #89                 // Field regularExpressionConverter:Lorg/bson/json/Converter;
     960: goto          990
     963: aload_0
     964: getfield      #20                 // Field outputMode:Lorg/bson/json/JsonMode;
     967: getstatic     #5                  // Field org/bson/json/JsonMode.STRICT:Lorg/bson/json/JsonMode;
     970: if_acmpne     983
     973: aload_0
     974: getstatic     #91                 // Field LEGACY_EXTENDED_JSON_REGULAR_EXPRESSION_CONVERTER:Lorg/bson/json/LegacyExtendedJsonRegularExpressionConverter;
     977: putfield      #89                 // Field regularExpressionConverter:Lorg/bson/json/Converter;
     980: goto          990
     983: aload_0
     984: getstatic     #92                 // Field SHELL_REGULAR_EXPRESSION_CONVERTER:Lorg/bson/json/ShellRegularExpressionConverter;
     987: putfield      #89                 // Field regularExpressionConverter:Lorg/bson/json/Converter;
     990: return

  public boolean isIndent();
    Code:
       0: aload_0
       1: getfield      #12                 // Field indent:Z
       4: ireturn

  public java.lang.String getNewLineCharacters();
    Code:
       0: aload_0
       1: getfield      #16                 // Field newLineCharacters:Ljava/lang/String;
       4: areturn

  public java.lang.String getIndentCharacters();
    Code:
       0: aload_0
       1: getfield      #18                 // Field indentCharacters:Ljava/lang/String;
       4: areturn

  public org.bson.json.JsonMode getOutputMode();
    Code:
       0: aload_0
       1: getfield      #20                 // Field outputMode:Lorg/bson/json/JsonMode;
       4: areturn

  public org.bson.json.Converter<org.bson.BsonNull> getNullConverter();
    Code:
       0: aload_0
       1: getfield      #22                 // Field nullConverter:Lorg/bson/json/Converter;
       4: areturn

  public org.bson.json.Converter<java.lang.String> getStringConverter();
    Code:
       0: aload_0
       1: getfield      #25                 // Field stringConverter:Lorg/bson/json/Converter;
       4: areturn

  public org.bson.json.Converter<org.bson.BsonBinary> getBinaryConverter();
    Code:
       0: aload_0
       1: getfield      #67                 // Field binaryConverter:Lorg/bson/json/Converter;
       4: areturn

  public org.bson.json.Converter<java.lang.Boolean> getBooleanConverter();
    Code:
       0: aload_0
       1: getfield      #28                 // Field booleanConverter:Lorg/bson/json/Converter;
       4: areturn

  public org.bson.json.Converter<java.lang.Long> getDateTimeConverter();
    Code:
       0: aload_0
       1: getfield      #61                 // Field dateTimeConverter:Lorg/bson/json/Converter;
       4: areturn

  public org.bson.json.Converter<java.lang.Double> getDoubleConverter();
    Code:
       0: aload_0
       1: getfield      #31                 // Field doubleConverter:Lorg/bson/json/Converter;
       4: areturn

  public org.bson.json.Converter<java.lang.Integer> getInt32Converter();
    Code:
       0: aload_0
       1: getfield      #38                 // Field int32Converter:Lorg/bson/json/Converter;
       4: areturn

  public org.bson.json.Converter<java.lang.Long> getInt64Converter();
    Code:
       0: aload_0
       1: getfield      #72                 // Field int64Converter:Lorg/bson/json/Converter;
       4: areturn

  public org.bson.json.Converter<org.bson.types.Decimal128> getDecimal128Converter();
    Code:
       0: aload_0
       1: getfield      #77                 // Field decimal128Converter:Lorg/bson/json/Converter;
       4: areturn

  public org.bson.json.Converter<org.bson.types.ObjectId> getObjectIdConverter();
    Code:
       0: aload_0
       1: getfield      #81                 // Field objectIdConverter:Lorg/bson/json/Converter;
       4: areturn

  public org.bson.json.Converter<org.bson.BsonRegularExpression> getRegularExpressionConverter();
    Code:
       0: aload_0
       1: getfield      #89                 // Field regularExpressionConverter:Lorg/bson/json/Converter;
       4: areturn

  public org.bson.json.Converter<org.bson.BsonTimestamp> getTimestampConverter();
    Code:
       0: aload_0
       1: getfield      #85                 // Field timestampConverter:Lorg/bson/json/Converter;
       4: areturn

  public org.bson.json.Converter<java.lang.String> getSymbolConverter();
    Code:
       0: aload_0
       1: getfield      #42                 // Field symbolConverter:Lorg/bson/json/Converter;
       4: areturn

  public org.bson.json.Converter<org.bson.BsonMinKey> getMinKeyConverter();
    Code:
       0: aload_0
       1: getfield      #49                 // Field minKeyConverter:Lorg/bson/json/Converter;
       4: areturn

  public org.bson.json.Converter<org.bson.BsonMaxKey> getMaxKeyConverter();
    Code:
       0: aload_0
       1: getfield      #53                 // Field maxKeyConverter:Lorg/bson/json/Converter;
       4: areturn

  public org.bson.json.Converter<org.bson.BsonUndefined> getUndefinedConverter();
    Code:
       0: aload_0
       1: getfield      #57                 // Field undefinedConverter:Lorg/bson/json/Converter;
       4: areturn

  public org.bson.json.Converter<java.lang.String> getJavaScriptConverter();
    Code:
       0: aload_0
       1: getfield      #45                 // Field javaScriptConverter:Lorg/bson/json/Converter;
       4: areturn

  org.bson.json.JsonWriterSettings(org.bson.json.JsonWriterSettings$Builder, org.bson.json.JsonWriterSettings$1);
    Code:
       0: aload_0
       1: aload_1
       2: invokespecial #1                  // Method "<init>":(Lorg/bson/json/JsonWriterSettings$Builder;)V
       5: return

  static {};
    Code:
       0: new           #93                 // class org/bson/json/JsonNullConverter
       3: dup
       4: invokespecial #94                 // Method org/bson/json/JsonNullConverter."<init>":()V
       7: putstatic     #23                 // Field JSON_NULL_CONVERTER:Lorg/bson/json/JsonNullConverter;
      10: new           #95                 // class org/bson/json/JsonStringConverter
      13: dup
      14: invokespecial #96                 // Method org/bson/json/JsonStringConverter."<init>":()V
      17: putstatic     #26                 // Field JSON_STRING_CONVERTER:Lorg/bson/json/JsonStringConverter;
      20: new           #97                 // class org/bson/json/JsonBooleanConverter
      23: dup
      24: invokespecial #98                 // Method org/bson/json/JsonBooleanConverter."<init>":()V
      27: putstatic     #29                 // Field JSON_BOOLEAN_CONVERTER:Lorg/bson/json/JsonBooleanConverter;
      30: new           #99                 // class org/bson/json/JsonDoubleConverter
      33: dup
      34: invokespecial #100                // Method org/bson/json/JsonDoubleConverter."<init>":()V
      37: putstatic     #36                 // Field JSON_DOUBLE_CONVERTER:Lorg/bson/json/JsonDoubleConverter;
      40: new           #101                // class org/bson/json/ExtendedJsonDoubleConverter
      43: dup
      44: invokespecial #102                // Method org/bson/json/ExtendedJsonDoubleConverter."<init>":()V
      47: putstatic     #33                 // Field EXTENDED_JSON_DOUBLE_CONVERTER:Lorg/bson/json/ExtendedJsonDoubleConverter;
      50: new           #103                // class org/bson/json/RelaxedExtendedJsonDoubleConverter
      53: dup
      54: invokespecial #104                // Method org/bson/json/RelaxedExtendedJsonDoubleConverter."<init>":()V
      57: putstatic     #35                 // Field RELAXED_EXTENDED_JSON_DOUBLE_CONVERTER:Lorg/bson/json/RelaxedExtendedJsonDoubleConverter;
      60: new           #105                // class org/bson/json/JsonInt32Converter
      63: dup
      64: invokespecial #106                // Method org/bson/json/JsonInt32Converter."<init>":()V
      67: putstatic     #40                 // Field JSON_INT_32_CONVERTER:Lorg/bson/json/JsonInt32Converter;
      70: new           #107                // class org/bson/json/ExtendedJsonInt32Converter
      73: dup
      74: invokespecial #108                // Method org/bson/json/ExtendedJsonInt32Converter."<init>":()V
      77: putstatic     #39                 // Field EXTENDED_JSON_INT_32_CONVERTER:Lorg/bson/json/ExtendedJsonInt32Converter;
      80: new           #109                // class org/bson/json/JsonSymbolConverter
      83: dup
      84: invokespecial #110                // Method org/bson/json/JsonSymbolConverter."<init>":()V
      87: putstatic     #43                 // Field JSON_SYMBOL_CONVERTER:Lorg/bson/json/JsonSymbolConverter;
      90: new           #111                // class org/bson/json/ExtendedJsonMinKeyConverter
      93: dup
      94: invokespecial #112                // Method org/bson/json/ExtendedJsonMinKeyConverter."<init>":()V
      97: putstatic     #50                 // Field EXTENDED_JSON_MIN_KEY_CONVERTER:Lorg/bson/json/ExtendedJsonMinKeyConverter;
     100: new           #113                // class org/bson/json/ShellMinKeyConverter
     103: dup
     104: invokespecial #114                // Method org/bson/json/ShellMinKeyConverter."<init>":()V
     107: putstatic     #51                 // Field SHELL_MIN_KEY_CONVERTER:Lorg/bson/json/ShellMinKeyConverter;
     110: new           #115                // class org/bson/json/ExtendedJsonMaxKeyConverter
     113: dup
     114: invokespecial #116                // Method org/bson/json/ExtendedJsonMaxKeyConverter."<init>":()V
     117: putstatic     #54                 // Field EXTENDED_JSON_MAX_KEY_CONVERTER:Lorg/bson/json/ExtendedJsonMaxKeyConverter;
     120: new           #117                // class org/bson/json/ShellMaxKeyConverter
     123: dup
     124: invokespecial #118                // Method org/bson/json/ShellMaxKeyConverter."<init>":()V
     127: putstatic     #55                 // Field SHELL_MAX_KEY_CONVERTER:Lorg/bson/json/ShellMaxKeyConverter;
     130: new           #119                // class org/bson/json/ExtendedJsonUndefinedConverter
     133: dup
     134: invokespecial #120                // Method org/bson/json/ExtendedJsonUndefinedConverter."<init>":()V
     137: putstatic     #58                 // Field EXTENDED_JSON_UNDEFINED_CONVERTER:Lorg/bson/json/ExtendedJsonUndefinedConverter;
     140: new           #121                // class org/bson/json/ShellUndefinedConverter
     143: dup
     144: invokespecial #122                // Method org/bson/json/ShellUndefinedConverter."<init>":()V
     147: putstatic     #59                 // Field SHELL_UNDEFINED_CONVERTER:Lorg/bson/json/ShellUndefinedConverter;
     150: new           #123                // class org/bson/json/LegacyExtendedJsonDateTimeConverter
     153: dup
     154: invokespecial #124                // Method org/bson/json/LegacyExtendedJsonDateTimeConverter."<init>":()V
     157: putstatic     #62                 // Field LEGACY_EXTENDED_JSON_DATE_TIME_CONVERTER:Lorg/bson/json/LegacyExtendedJsonDateTimeConverter;
     160: new           #125                // class org/bson/json/ExtendedJsonDateTimeConverter
     163: dup
     164: invokespecial #126                // Method org/bson/json/ExtendedJsonDateTimeConverter."<init>":()V
     167: putstatic     #63                 // Field EXTENDED_JSON_DATE_TIME_CONVERTER:Lorg/bson/json/ExtendedJsonDateTimeConverter;
     170: new           #127                // class org/bson/json/RelaxedExtendedJsonDateTimeConverter
     173: dup
     174: invokespecial #128                // Method org/bson/json/RelaxedExtendedJsonDateTimeConverter."<init>":()V
     177: putstatic     #64                 // Field RELAXED_EXTENDED_JSON_DATE_TIME_CONVERTER:Lorg/bson/json/RelaxedExtendedJsonDateTimeConverter;
     180: new           #129                // class org/bson/json/ShellDateTimeConverter
     183: dup
     184: invokespecial #130                // Method org/bson/json/ShellDateTimeConverter."<init>":()V
     187: putstatic     #65                 // Field SHELL_DATE_TIME_CONVERTER:Lorg/bson/json/ShellDateTimeConverter;
     190: new           #131                // class org/bson/json/ExtendedJsonBinaryConverter
     193: dup
     194: invokespecial #132                // Method org/bson/json/ExtendedJsonBinaryConverter."<init>":()V
     197: putstatic     #69                 // Field EXTENDED_JSON_BINARY_CONVERTER:Lorg/bson/json/ExtendedJsonBinaryConverter;
     200: new           #133                // class org/bson/json/LegacyExtendedJsonBinaryConverter
     203: dup
     204: invokespecial #134                // Method org/bson/json/LegacyExtendedJsonBinaryConverter."<init>":()V
     207: putstatic     #68                 // Field LEGACY_EXTENDED_JSON_BINARY_CONVERTER:Lorg/bson/json/LegacyExtendedJsonBinaryConverter;
     210: new           #135                // class org/bson/json/ShellBinaryConverter
     213: dup
     214: invokespecial #136                // Method org/bson/json/ShellBinaryConverter."<init>":()V
     217: putstatic     #70                 // Field SHELL_BINARY_CONVERTER:Lorg/bson/json/ShellBinaryConverter;
     220: new           #137                // class org/bson/json/ExtendedJsonInt64Converter
     223: dup
     224: invokespecial #138                // Method org/bson/json/ExtendedJsonInt64Converter."<init>":()V
     227: putstatic     #73                 // Field EXTENDED_JSON_INT_64_CONVERTER:Lorg/bson/json/ExtendedJsonInt64Converter;
     230: new           #139                // class org/bson/json/RelaxedExtendedJsonInt64Converter
     233: dup
     234: invokespecial #140                // Method org/bson/json/RelaxedExtendedJsonInt64Converter."<init>":()V
     237: putstatic     #74                 // Field RELAXED_JSON_INT_64_CONVERTER:Lorg/bson/json/RelaxedExtendedJsonInt64Converter;
     240: new           #141                // class org/bson/json/ShellInt64Converter
     243: dup
     244: invokespecial #142                // Method org/bson/json/ShellInt64Converter."<init>":()V
     247: putstatic     #75                 // Field SHELL_INT_64_CONVERTER:Lorg/bson/json/ShellInt64Converter;
     250: new           #143                // class org/bson/json/ExtendedJsonDecimal128Converter
     253: dup
     254: invokespecial #144                // Method org/bson/json/ExtendedJsonDecimal128Converter."<init>":()V
     257: putstatic     #78                 // Field EXTENDED_JSON_DECIMAL_128_CONVERTER:Lorg/bson/json/ExtendedJsonDecimal128Converter;
     260: new           #145                // class org/bson/json/ShellDecimal128Converter
     263: dup
     264: invokespecial #146                // Method org/bson/json/ShellDecimal128Converter."<init>":()V
     267: putstatic     #79                 // Field SHELL_DECIMAL_128_CONVERTER:Lorg/bson/json/ShellDecimal128Converter;
     270: new           #147                // class org/bson/json/ExtendedJsonObjectIdConverter
     273: dup
     274: invokespecial #148                // Method org/bson/json/ExtendedJsonObjectIdConverter."<init>":()V
     277: putstatic     #82                 // Field EXTENDED_JSON_OBJECT_ID_CONVERTER:Lorg/bson/json/ExtendedJsonObjectIdConverter;
     280: new           #149                // class org/bson/json/ShellObjectIdConverter
     283: dup
     284: invokespecial #150                // Method org/bson/json/ShellObjectIdConverter."<init>":()V
     287: putstatic     #83                 // Field SHELL_OBJECT_ID_CONVERTER:Lorg/bson/json/ShellObjectIdConverter;
     290: new           #151                // class org/bson/json/ExtendedJsonTimestampConverter
     293: dup
     294: invokespecial #152                // Method org/bson/json/ExtendedJsonTimestampConverter."<init>":()V
     297: putstatic     #86                 // Field EXTENDED_JSON_TIMESTAMP_CONVERTER:Lorg/bson/json/ExtendedJsonTimestampConverter;
     300: new           #153                // class org/bson/json/ShellTimestampConverter
     303: dup
     304: invokespecial #154                // Method org/bson/json/ShellTimestampConverter."<init>":()V
     307: putstatic     #87                 // Field SHELL_TIMESTAMP_CONVERTER:Lorg/bson/json/ShellTimestampConverter;
     310: new           #155                // class org/bson/json/ExtendedJsonRegularExpressionConverter
     313: dup
     314: invokespecial #156                // Method org/bson/json/ExtendedJsonRegularExpressionConverter."<init>":()V
     317: putstatic     #90                 // Field EXTENDED_JSON_REGULAR_EXPRESSION_CONVERTER:Lorg/bson/json/ExtendedJsonRegularExpressionConverter;
     320: new           #157                // class org/bson/json/LegacyExtendedJsonRegularExpressionConverter
     323: dup
     324: invokespecial #158                // Method org/bson/json/LegacyExtendedJsonRegularExpressionConverter."<init>":()V
     327: putstatic     #91                 // Field LEGACY_EXTENDED_JSON_REGULAR_EXPRESSION_CONVERTER:Lorg/bson/json/LegacyExtendedJsonRegularExpressionConverter;
     330: new           #159                // class org/bson/json/ShellRegularExpressionConverter
     333: dup
     334: invokespecial #160                // Method org/bson/json/ShellRegularExpressionConverter."<init>":()V
     337: putstatic     #92                 // Field SHELL_REGULAR_EXPRESSION_CONVERTER:Lorg/bson/json/ShellRegularExpressionConverter;
     340: return
}
