Compiled from "JsonReader.java"
public class org.bson.json.JsonReader$Mark extends org.bson.AbstractBsonReader$Mark {
  private final org.bson.json.JsonToken pushedToken;

  private final java.lang.Object currentValue;

  private final int position;

  final org.bson.json.JsonReader this$0;

  protected org.bson.json.JsonReader$Mark(org.bson.json.JsonReader);
    Code:
       0: aload_0
       1: aload_1
       2: putfield      #1                  // Field this$0:Lorg/bson/json/JsonReader;
       5: aload_0
       6: aload_1
       7: invokespecial #2                  // Method org/bson/AbstractBsonReader$Mark."<init>":(Lorg/bson/AbstractBsonReader;)V
      10: aload_0
      11: aload_1
      12: invokestatic  #3                  // Method org/bson/json/JsonReader.access$000:(Lorg/bson/json/JsonReader;)Lorg/bson/json/JsonToken;
      15: putfield      #4                  // Field pushedToken:Lorg/bson/json/JsonToken;
      18: aload_0
      19: aload_1
      20: invokestatic  #5                  // Method org/bson/json/JsonReader.access$100:(Lorg/bson/json/JsonReader;)Ljava/lang/Object;
      23: putfield      #6                  // Field currentValue:Ljava/lang/Object;
      26: aload_0
      27: aload_1
      28: invokestatic  #7                  // Method org/bson/json/JsonReader.access$200:(Lorg/bson/json/JsonReader;)Lorg/bson/json/JsonScanner;
      31: invokevirtual #8                  // Method org/bson/json/JsonScanner.getBufferPosition:()I
      34: putfield      #9                  // Field position:I
      37: return

  public void reset();
    Code:
       0: aload_0
       1: invokespecial #10                 // Method org/bson/AbstractBsonReader$Mark.reset:()V
       4: aload_0
       5: getfield      #1                  // Field this$0:Lorg/bson/json/JsonReader;
       8: aload_0
       9: getfield      #4                  // Field pushedToken:Lorg/bson/json/JsonToken;
      12: invokestatic  #11                 // Method org/bson/json/JsonReader.access$002:(Lorg/bson/json/JsonReader;Lorg/bson/json/JsonToken;)Lorg/bson/json/JsonToken;
      15: pop
      16: aload_0
      17: getfield      #1                  // Field this$0:Lorg/bson/json/JsonReader;
      20: aload_0
      21: getfield      #6                  // Field currentValue:Ljava/lang/Object;
      24: invokestatic  #12                 // Method org/bson/json/JsonReader.access$102:(Lorg/bson/json/JsonReader;Ljava/lang/Object;)Ljava/lang/Object;
      27: pop
      28: aload_0
      29: getfield      #1                  // Field this$0:Lorg/bson/json/JsonReader;
      32: invokestatic  #7                  // Method org/bson/json/JsonReader.access$200:(Lorg/bson/json/JsonReader;)Lorg/bson/json/JsonScanner;
      35: aload_0
      36: getfield      #9                  // Field position:I
      39: invokevirtual #13                 // Method org/bson/json/JsonScanner.setBufferPosition:(I)V
      42: aload_0
      43: getfield      #1                  // Field this$0:Lorg/bson/json/JsonReader;
      46: new           #14                 // class org/bson/json/JsonReader$Context
      49: dup
      50: aload_0
      51: getfield      #1                  // Field this$0:Lorg/bson/json/JsonReader;
      54: aload_0
      55: invokevirtual #15                 // Method getParentContext:()Lorg/bson/AbstractBsonReader$Context;
      58: aload_0
      59: invokevirtual #16                 // Method getContextType:()Lorg/bson/BsonContextType;
      62: invokespecial #17                 // Method org/bson/json/JsonReader$Context."<init>":(Lorg/bson/json/JsonReader;Lorg/bson/AbstractBsonReader$Context;Lorg/bson/BsonContextType;)V
      65: invokestatic  #18                 // Method org/bson/json/JsonReader.access$300:(Lorg/bson/json/JsonReader;Lorg/bson/AbstractBsonReader$Context;)V
      68: return
}
