Compiled from "RelaxedExtendedJsonDoubleConverter.java"
class org.bson.json.RelaxedExtendedJsonDoubleConverter implements org.bson.json.Converter<java.lang.Double> {
  private static final org.bson.json.Converter<java.lang.Double> FALLBACK_CONVERTER;

  org.bson.json.RelaxedExtendedJsonDoubleConverter();
    Code:
       0: aload_0
       1: invokespecial #1                  // Method java/lang/Object."<init>":()V
       4: return

  public void convert(java.lang.Double, org.bson.json.StrictJsonWriter);
    Code:
       0: aload_1
       1: invokevirtual #2                  // Method java/lang/Double.isNaN:()Z
       4: ifne          14
       7: aload_1
       8: invokevirtual #3                  // Method java/lang/Double.isInfinite:()Z
      11: ifeq          27
      14: getstatic     #4                  // Field FALLBACK_CONVERTER:Lorg/bson/json/Converter;
      17: aload_1
      18: aload_2
      19: invokeinterface #5,  3            // InterfaceMethod org/bson/json/Converter.convert:(Ljava/lang/Object;Lorg/bson/json/StrictJsonWriter;)V
      24: goto          40
      27: aload_2
      28: aload_1
      29: invokevirtual #6                  // Method java/lang/Double.doubleValue:()D
      32: invokestatic  #7                  // Method java/lang/Double.toString:(D)Ljava/lang/String;
      35: invokeinterface #8,  2            // InterfaceMethod org/bson/json/StrictJsonWriter.writeNumber:(Ljava/lang/String;)V
      40: return

  public void convert(java.lang.Object, org.bson.json.StrictJsonWriter);
    Code:
       0: aload_0
       1: aload_1
       2: checkcast     #9                  // class java/lang/Double
       5: aload_2
       6: invokevirtual #10                 // Method convert:(Ljava/lang/Double;Lorg/bson/json/StrictJsonWriter;)V
       9: return

  static {};
    Code:
       0: new           #11                 // class org/bson/json/ExtendedJsonDoubleConverter
       3: dup
       4: invokespecial #12                 // Method org/bson/json/ExtendedJsonDoubleConverter."<init>":()V
       7: putstatic     #4                  // Field FALLBACK_CONVERTER:Lorg/bson/json/Converter;
      10: return
}
