Compiled from "ArrayUtil.java"
class org.apache.bookkeeper.bookie.storage.ldb.ArrayUtil {
  private static final boolean UNALIGNED;

  private static final boolean HAS_UNSAFE;

  private static final boolean BIG_ENDIAN_NATIVE_ORDER;

  org.apache.bookkeeper.bookie.storage.ldb.ArrayUtil();
    Code:
       0: aload_0
       1: invokespecial #1                  // Method java/lang/Object."<init>":()V
       4: return

  public static long getLong(byte[], int);
    Code:
       0: getstatic     #2                  // Field HAS_UNSAFE:Z
       3: ifeq          33
       6: getstatic     #3                  // Field UNALIGNED:Z
       9: ifeq          33
      12: aload_0
      13: iload_1
      14: invokestatic  #4                  // Method io/netty/util/internal/PlatformDependent.getLong:([BI)J
      17: lstore_2
      18: getstatic     #5                  // Field BIG_ENDIAN_NATIVE_ORDER:Z
      21: ifeq          28
      24: lload_2
      25: goto          32
      28: lload_2
      29: invokestatic  #6                  // Method java/lang/Long.reverseBytes:(J)J
      32: lreturn
      33: aload_0
      34: iload_1
      35: baload
      36: i2l
      37: ldc2_w        #7                  // long 255l
      40: land
      41: bipush        56
      43: lshl
      44: aload_0
      45: iload_1
      46: iconst_1
      47: iadd
      48: baload
      49: i2l
      50: ldc2_w        #7                  // long 255l
      53: land
      54: bipush        48
      56: lshl
      57: lor
      58: aload_0
      59: iload_1
      60: iconst_2
      61: iadd
      62: baload
      63: i2l
      64: ldc2_w        #7                  // long 255l
      67: land
      68: bipush        40
      70: lshl
      71: lor
      72: aload_0
      73: iload_1
      74: iconst_3
      75: iadd
      76: baload
      77: i2l
      78: ldc2_w        #7                  // long 255l
      81: land
      82: bipush        32
      84: lshl
      85: lor
      86: aload_0
      87: iload_1
      88: iconst_4
      89: iadd
      90: baload
      91: i2l
      92: ldc2_w        #7                  // long 255l
      95: land
      96: bipush        24
      98: lshl
      99: lor
     100: aload_0
     101: iload_1
     102: iconst_5
     103: iadd
     104: baload
     105: i2l
     106: ldc2_w        #7                  // long 255l
     109: land
     110: bipush        16
     112: lshl
     113: lor
     114: aload_0
     115: iload_1
     116: bipush        6
     118: iadd
     119: baload
     120: i2l
     121: ldc2_w        #7                  // long 255l
     124: land
     125: bipush        8
     127: lshl
     128: lor
     129: aload_0
     130: iload_1
     131: bipush        7
     133: iadd
     134: baload
     135: i2l
     136: ldc2_w        #7                  // long 255l
     139: land
     140: lor
     141: lreturn

  public static void setLong(byte[], int, long);
    Code:
       0: getstatic     #2                  // Field HAS_UNSAFE:Z
       3: ifeq          34
       6: getstatic     #3                  // Field UNALIGNED:Z
       9: ifeq          34
      12: aload_0
      13: iload_1
      14: getstatic     #5                  // Field BIG_ENDIAN_NATIVE_ORDER:Z
      17: ifeq          24
      20: lload_2
      21: goto          28
      24: lload_2
      25: invokestatic  #6                  // Method java/lang/Long.reverseBytes:(J)J
      28: invokestatic  #9                  // Method io/netty/util/internal/PlatformDependent.putLong:([BIJ)V
      31: goto          119
      34: aload_0
      35: iload_1
      36: lload_2
      37: bipush        56
      39: lushr
      40: l2i
      41: i2b
      42: bastore
      43: aload_0
      44: iload_1
      45: iconst_1
      46: iadd
      47: lload_2
      48: bipush        48
      50: lushr
      51: l2i
      52: i2b
      53: bastore
      54: aload_0
      55: iload_1
      56: iconst_2
      57: iadd
      58: lload_2
      59: bipush        40
      61: lushr
      62: l2i
      63: i2b
      64: bastore
      65: aload_0
      66: iload_1
      67: iconst_3
      68: iadd
      69: lload_2
      70: bipush        32
      72: lushr
      73: l2i
      74: i2b
      75: bastore
      76: aload_0
      77: iload_1
      78: iconst_4
      79: iadd
      80: lload_2
      81: bipush        24
      83: lushr
      84: l2i
      85: i2b
      86: bastore
      87: aload_0
      88: iload_1
      89: iconst_5
      90: iadd
      91: lload_2
      92: bipush        16
      94: lushr
      95: l2i
      96: i2b
      97: bastore
      98: aload_0
      99: iload_1
     100: bipush        6
     102: iadd
     103: lload_2
     104: bipush        8
     106: lushr
     107: l2i
     108: i2b
     109: bastore
     110: aload_0
     111: iload_1
     112: bipush        7
     114: iadd
     115: lload_2
     116: l2i
     117: i2b
     118: bastore
     119: return

  public static final boolean isArrayAllZeros(byte[]);
    Code:
       0: aload_0
       1: iconst_0
       2: aload_0
       3: arraylength
       4: invokestatic  #10                 // Method io/netty/util/internal/PlatformDependent.isZero:([BII)Z
       7: ireturn

  static {};
    Code:
       0: invokestatic  #11                 // Method io/netty/util/internal/PlatformDependent.isUnaligned:()Z
       3: putstatic     #3                  // Field UNALIGNED:Z
       6: invokestatic  #12                 // Method io/netty/util/internal/PlatformDependent.hasUnsafe:()Z
       9: putstatic     #2                  // Field HAS_UNSAFE:Z
      12: invokestatic  #13                 // Method java/nio/ByteOrder.nativeOrder:()Ljava/nio/ByteOrder;
      15: getstatic     #14                 // Field java/nio/ByteOrder.BIG_ENDIAN:Ljava/nio/ByteOrder;
      18: if_acmpne     25
      21: iconst_1
      22: goto          26
      25: iconst_0
      26: putstatic     #5                  // Field BIG_ENDIAN_NATIVE_ORDER:Z
      29: return
}
