Compiled from "Properties.java"
final class springfox.documentation.swagger2.mappers.Properties$2 implements com.google.common.base.Function<java.lang.String, T> {
  final java.lang.Class val$clazz;

  springfox.documentation.swagger2.mappers.Properties$2(java.lang.Class);
    Code:
       0: aload_0
       1: aload_1
       2: putfield      #1                  // Field val$clazz:Ljava/lang/Class;
       5: aload_0
       6: invokespecial #2                  // Method java/lang/Object."<init>":()V
       9: return

  public T apply(java.lang.String);
    Code:
       0: aload_0
       1: getfield      #1                  // Field val$clazz:Ljava/lang/Class;
       4: invokevirtual #3                  // Method java/lang/Class.newInstance:()Ljava/lang/Object;
       7: checkcast     #4                  // class io/swagger/models/properties/Property
      10: areturn
      11: astore_2
      12: new           #6                  // class java/lang/IllegalStateException
      15: dup
      16: aload_2
      17: invokespecial #7                  // Method java/lang/IllegalStateException."<init>":(Ljava/lang/Throwable;)V
      20: athrow
    Exception table:
       from    to  target type
           0    10    11   Class java/lang/Exception

  public java.lang.Object apply(java.lang.Object);
    Code:
       0: aload_0
       1: aload_1
       2: checkcast     #8                  // class java/lang/String
       5: invokevirtual #9                  // Method apply:(Ljava/lang/String;)Lio/swagger/models/properties/Property;
       8: areturn
}
