Compiled from "SerializableParameterFactories.java"
class springfox.documentation.swagger2.mappers.SerializableParameterFactories$HeaderSerializableParameterFactory implements springfox.documentation.swagger2.mappers.SerializableParameterFactory {
  springfox.documentation.swagger2.mappers.SerializableParameterFactories$HeaderSerializableParameterFactory();
    Code:
       0: aload_0
       1: invokespecial #1                  // Method java/lang/Object."<init>":()V
       4: return

  public io.swagger.models.parameters.SerializableParameter create(springfox.documentation.service.Parameter);
    Code:
       0: new           #2                  // class io/swagger/models/parameters/HeaderParameter
       3: dup
       4: invokespecial #3                  // Method io/swagger/models/parameters/HeaderParameter."<init>":()V
       7: astore_2
       8: aload_2
       9: aload_1
      10: invokevirtual #4                  // Method springfox/documentation/service/Parameter.getDefaultValue:()Ljava/lang/String;
      13: invokevirtual #5                  // Method io/swagger/models/parameters/HeaderParameter.setDefaultValue:(Ljava/lang/String;)V
      16: aload_2
      17: areturn
}
