Compiled from "ServiceModelToSwagger2Mapper.java"
public abstract class springfox.documentation.swagger2.mappers.ServiceModelToSwagger2Mapper {
  public springfox.documentation.swagger2.mappers.ServiceModelToSwagger2Mapper();
    Code:
       0: aload_0
       1: invokespecial #1                  // Method java/lang/Object."<init>":()V
       4: return

  public abstract io.swagger.models.Swagger mapDocumentation(springfox.documentation.service.Documentation);

  protected abstract io.swagger.models.Info mapApiInfo(springfox.documentation.service.ApiInfo);

  protected abstract io.swagger.models.Contact map(springfox.documentation.service.Contact);

  protected abstract io.swagger.models.Operation mapOperation(springfox.documentation.service.Operation);

  protected abstract io.swagger.models.Tag mapTag(springfox.documentation.service.Tag);

  protected java.util.List<io.swagger.models.Scheme> mapSchemes(java.util.List<java.lang.String>);
    Code:
       0: aload_1
       1: invokestatic  #2                  // Method com/google/common/collect/FluentIterable.from:(Ljava/lang/Iterable;)Lcom/google/common/collect/FluentIterable;
       4: aload_0
       5: invokespecial #3                  // Method toScheme:()Lcom/google/common/base/Function;
       8: invokevirtual #4                  // Method com/google/common/collect/FluentIterable.transform:(Lcom/google/common/base/Function;)Lcom/google/common/collect/FluentIterable;
      11: invokevirtual #5                  // Method com/google/common/collect/FluentIterable.toList:()Lcom/google/common/collect/ImmutableList;
      14: areturn

  protected java.util.List<java.util.Map<java.lang.String, java.util.List<java.lang.String>>> mapAuthorizations(java.util.Map<java.lang.String, java.util.List<springfox.documentation.service.AuthorizationScope>>);
    Code:
       0: invokestatic  #6                  // Method com/google/common/collect/Lists.newArrayList:()Ljava/util/ArrayList;
       3: astore_2
       4: aload_1
       5: invokeinterface #7,  1            // InterfaceMethod java/util/Map.entrySet:()Ljava/util/Set;
      10: invokeinterface #8,  1            // InterfaceMethod java/util/Set.iterator:()Ljava/util/Iterator;
      15: astore_3
      16: aload_3
      17: invokeinterface #9,  1            // InterfaceMethod java/util/Iterator.hasNext:()Z
      22: ifeq          91
      25: aload_3
      26: invokeinterface #10,  1           // InterfaceMethod java/util/Iterator.next:()Ljava/lang/Object;
      31: checkcast     #11                 // class java/util/Map$Entry
      34: astore        4
      36: invokestatic  #12                 // Method com/google/common/collect/Maps.newHashMap:()Ljava/util/HashMap;
      39: astore        5
      41: aload         5
      43: aload         4
      45: invokeinterface #13,  1           // InterfaceMethod java/util/Map$Entry.getKey:()Ljava/lang/Object;
      50: aload         4
      52: invokeinterface #14,  1           // InterfaceMethod java/util/Map$Entry.getValue:()Ljava/lang/Object;
      57: checkcast     #15                 // class java/lang/Iterable
      60: invokestatic  #2                  // Method com/google/common/collect/FluentIterable.from:(Ljava/lang/Iterable;)Lcom/google/common/collect/FluentIterable;
      63: aload_0
      64: invokespecial #16                 // Method scopeToString:()Lcom/google/common/base/Function;
      67: invokevirtual #4                  // Method com/google/common/collect/FluentIterable.transform:(Lcom/google/common/base/Function;)Lcom/google/common/collect/FluentIterable;
      70: invokevirtual #5                  // Method com/google/common/collect/FluentIterable.toList:()Lcom/google/common/collect/ImmutableList;
      73: invokeinterface #17,  3           // InterfaceMethod java/util/Map.put:(Ljava/lang/Object;Ljava/lang/Object;)Ljava/lang/Object;
      78: pop
      79: aload_2
      80: aload         5
      82: invokeinterface #18,  2           // InterfaceMethod java/util/List.add:(Ljava/lang/Object;)Z
      87: pop
      88: goto          16
      91: aload_2
      92: areturn

  protected java.util.Map<java.lang.String, io.swagger.models.Response> mapResponseMessages(java.util.Set<springfox.documentation.service.ResponseMessage>);
    Code:
       0: invokestatic  #19                 // Method com/google/common/collect/Maps.newTreeMap:()Ljava/util/TreeMap;
       3: astore_2
       4: aload_1
       5: invokeinterface #8,  1            // InterfaceMethod java/util/Set.iterator:()Ljava/util/Iterator;
      10: astore_3
      11: aload_3
      12: invokeinterface #9,  1            // InterfaceMethod java/util/Iterator.hasNext:()Z
      17: ifeq          141
      20: aload_3
      21: invokeinterface #10,  1           // InterfaceMethod java/util/Iterator.next:()Ljava/lang/Object;
      26: checkcast     #20                 // class springfox/documentation/service/ResponseMessage
      29: astore        4
      31: aload         4
      33: invokevirtual #21                 // Method springfox/documentation/service/ResponseMessage.getResponseModel:()Lspringfox/documentation/schema/ModelReference;
      36: astore        6
      38: aload         6
      40: invokestatic  #22                 // Method springfox/documentation/swagger2/mappers/ModelMapper.modelRefToProperty:(Lspringfox/documentation/schema/ModelReference;)Lio/swagger/models/properties/Property;
      43: astore        5
      45: new           #23                 // class io/swagger/models/Response
      48: dup
      49: invokespecial #24                 // Method io/swagger/models/Response."<init>":()V
      52: aload         4
      54: invokevirtual #25                 // Method springfox/documentation/service/ResponseMessage.getMessage:()Ljava/lang/String;
      57: invokevirtual #26                 // Method io/swagger/models/Response.description:(Ljava/lang/String;)Lio/swagger/models/Response;
      60: aload         5
      62: invokevirtual #27                 // Method io/swagger/models/Response.schema:(Lio/swagger/models/properties/Property;)Lio/swagger/models/Response;
      65: astore        7
      67: aload         7
      69: invokestatic  #12                 // Method com/google/common/collect/Maps.newHashMap:()Ljava/util/HashMap;
      72: invokevirtual #28                 // Method io/swagger/models/Response.setExamples:(Ljava/util/Map;)V
      75: aload         7
      77: aload         4
      79: invokevirtual #29                 // Method springfox/documentation/service/ResponseMessage.getHeaders:()Ljava/util/Map;
      82: aload_0
      83: invokespecial #30                 // Method toPropertyEntry:()Lcom/google/common/collect/Maps$EntryTransformer;
      86: invokestatic  #31                 // Method com/google/common/collect/Maps.transformEntries:(Ljava/util/Map;Lcom/google/common/collect/Maps$EntryTransformer;)Ljava/util/Map;
      89: invokevirtual #32                 // Method io/swagger/models/Response.setHeaders:(Ljava/util/Map;)V
      92: new           #33                 // class springfox/documentation/swagger2/mappers/VendorExtensionsMapper
      95: dup
      96: invokespecial #34                 // Method springfox/documentation/swagger2/mappers/VendorExtensionsMapper."<init>":()V
      99: aload         4
     101: invokevirtual #35                 // Method springfox/documentation/service/ResponseMessage.getVendorExtensions:()Ljava/util/List;
     104: invokevirtual #36                 // Method springfox/documentation/swagger2/mappers/VendorExtensionsMapper.mapExtensions:(Ljava/util/List;)Ljava/util/Map;
     107: astore        8
     109: aload         7
     111: invokevirtual #37                 // Method io/swagger/models/Response.getVendorExtensions:()Ljava/util/Map;
     114: aload         8
     116: invokeinterface #38,  2           // InterfaceMethod java/util/Map.putAll:(Ljava/util/Map;)V
     121: aload_2
     122: aload         4
     124: invokevirtual #39                 // Method springfox/documentation/service/ResponseMessage.getCode:()I
     127: invokestatic  #40                 // Method java/lang/String.valueOf:(I)Ljava/lang/String;
     130: aload         7
     132: invokeinterface #17,  3           // InterfaceMethod java/util/Map.put:(Ljava/lang/Object;Ljava/lang/Object;)Ljava/lang/Object;
     137: pop
     138: goto          11
     141: aload_2
     142: areturn

  private com.google.common.collect.Maps$EntryTransformer<java.lang.String, springfox.documentation.service.Header, io.swagger.models.properties.Property> toPropertyEntry();
    Code:
       0: new           #41                 // class springfox/documentation/swagger2/mappers/ServiceModelToSwagger2Mapper$1
       3: dup
       4: aload_0
       5: invokespecial #42                 // Method springfox/documentation/swagger2/mappers/ServiceModelToSwagger2Mapper$1."<init>":(Lspringfox/documentation/swagger2/mappers/ServiceModelToSwagger2Mapper;)V
       8: areturn

  protected java.util.Map<java.lang.String, io.swagger.models.Path> mapApiListings(com.google.common.collect.Multimap<java.lang.String, springfox.documentation.service.ApiListing>);
    Code:
       0: invokestatic  #19                 // Method com/google/common/collect/Maps.newTreeMap:()Ljava/util/TreeMap;
       3: astore_2
       4: aload_1
       5: invokeinterface #43,  1           // InterfaceMethod com/google/common/collect/Multimap.values:()Ljava/util/Collection;
      10: invokeinterface #44,  1           // InterfaceMethod java/util/Collection.iterator:()Ljava/util/Iterator;
      15: astore_3
      16: aload_3
      17: invokeinterface #9,  1            // InterfaceMethod java/util/Iterator.hasNext:()Z
      22: ifeq          108
      25: aload_3
      26: invokeinterface #10,  1           // InterfaceMethod java/util/Iterator.next:()Ljava/lang/Object;
      31: checkcast     #45                 // class springfox/documentation/service/ApiListing
      34: astore        4
      36: aload         4
      38: invokevirtual #46                 // Method springfox/documentation/service/ApiListing.getApis:()Ljava/util/List;
      41: invokeinterface #47,  1           // InterfaceMethod java/util/List.iterator:()Ljava/util/Iterator;
      46: astore        5
      48: aload         5
      50: invokeinterface #9,  1            // InterfaceMethod java/util/Iterator.hasNext:()Z
      55: ifeq          105
      58: aload         5
      60: invokeinterface #10,  1           // InterfaceMethod java/util/Iterator.next:()Ljava/lang/Object;
      65: checkcast     #48                 // class springfox/documentation/service/ApiDescription
      68: astore        6
      70: aload_2
      71: aload         6
      73: invokevirtual #49                 // Method springfox/documentation/service/ApiDescription.getPath:()Ljava/lang/String;
      76: aload_0
      77: aload         6
      79: aload_2
      80: aload         6
      82: invokevirtual #49                 // Method springfox/documentation/service/ApiDescription.getPath:()Ljava/lang/String;
      85: invokeinterface #50,  2           // InterfaceMethod java/util/Map.get:(Ljava/lang/Object;)Ljava/lang/Object;
      90: invokestatic  #51                 // Method com/google/common/base/Optional.fromNullable:(Ljava/lang/Object;)Lcom/google/common/base/Optional;
      93: invokespecial #52                 // Method mapOperations:(Lspringfox/documentation/service/ApiDescription;Lcom/google/common/base/Optional;)Lio/swagger/models/Path;
      96: invokeinterface #17,  3           // InterfaceMethod java/util/Map.put:(Ljava/lang/Object;Ljava/lang/Object;)Ljava/lang/Object;
     101: pop
     102: goto          48
     105: goto          16
     108: aload_2
     109: areturn

  private com.google.common.base.Function<springfox.documentation.service.AuthorizationScope, java.lang.String> scopeToString();
    Code:
       0: new           #53                 // class springfox/documentation/swagger2/mappers/ServiceModelToSwagger2Mapper$2
       3: dup
       4: aload_0
       5: invokespecial #54                 // Method springfox/documentation/swagger2/mappers/ServiceModelToSwagger2Mapper$2."<init>":(Lspringfox/documentation/swagger2/mappers/ServiceModelToSwagger2Mapper;)V
       8: areturn

  private io.swagger.models.Path mapOperations(springfox.documentation.service.ApiDescription, com.google.common.base.Optional<io.swagger.models.Path>);
    Code:
       0: aload_2
       1: new           #55                 // class io/swagger/models/Path
       4: dup
       5: invokespecial #56                 // Method io/swagger/models/Path."<init>":()V
       8: invokevirtual #57                 // Method com/google/common/base/Optional.or:(Ljava/lang/Object;)Ljava/lang/Object;
      11: checkcast     #55                 // class io/swagger/models/Path
      14: astore_3
      15: aload_1
      16: invokevirtual #58                 // Method springfox/documentation/service/ApiDescription.getOperations:()Ljava/util/List;
      19: invokestatic  #59                 // Method springfox/documentation/builders/BuilderDefaults.nullToEmptyList:(Ljava/util/Collection;)Ljava/util/List;
      22: invokeinterface #47,  1           // InterfaceMethod java/util/List.iterator:()Ljava/util/Iterator;
      27: astore        4
      29: aload         4
      31: invokeinterface #9,  1            // InterfaceMethod java/util/Iterator.hasNext:()Z
      36: ifeq          80
      39: aload         4
      41: invokeinterface #10,  1           // InterfaceMethod java/util/Iterator.next:()Ljava/lang/Object;
      46: checkcast     #60                 // class springfox/documentation/service/Operation
      49: astore        5
      51: aload_0
      52: aload         5
      54: invokevirtual #61                 // Method mapOperation:(Lspringfox/documentation/service/Operation;)Lio/swagger/models/Operation;
      57: astore        6
      59: aload_3
      60: aload         5
      62: invokevirtual #62                 // Method springfox/documentation/service/Operation.getMethod:()Lorg/springframework/http/HttpMethod;
      65: invokevirtual #63                 // Method org/springframework/http/HttpMethod.toString:()Ljava/lang/String;
      68: invokevirtual #64                 // Method java/lang/String.toLowerCase:()Ljava/lang/String;
      71: aload         6
      73: invokevirtual #65                 // Method io/swagger/models/Path.set:(Ljava/lang/String;Lio/swagger/models/Operation;)Lio/swagger/models/Path;
      76: pop
      77: goto          29
      80: aload_3
      81: areturn

  private com.google.common.base.Function<java.lang.String, io.swagger.models.Scheme> toScheme();
    Code:
       0: new           #66                 // class springfox/documentation/swagger2/mappers/ServiceModelToSwagger2Mapper$3
       3: dup
       4: aload_0
       5: invokespecial #67                 // Method springfox/documentation/swagger2/mappers/ServiceModelToSwagger2Mapper$3."<init>":(Lspringfox/documentation/swagger2/mappers/ServiceModelToSwagger2Mapper;)V
       8: areturn
}
