Compiled from "IndexFieldTypesService.java"
public class org.graylog2.indexer.fieldtypes.IndexFieldTypesService {
  private static final java.lang.String FIELDS_FIELD_NAMES;

  private final org.mongojack.JacksonDBCollection<org.graylog2.indexer.fieldtypes.IndexFieldTypesDTO, org.bson.types.ObjectId> db;

  public org.graylog2.indexer.fieldtypes.IndexFieldTypesService(org.graylog2.database.MongoConnection, org.graylog2.bindings.providers.MongoJackObjectMapperProvider);
    Code:
       0: aload_0
       1: invokespecial #1                  // Method java/lang/Object."<init>":()V
       4: aload_0
       5: aload_1
       6: invokeinterface #2,  1            // InterfaceMethod org/graylog2/database/MongoConnection.getDatabase:()Lcom/mongodb/DB;
      11: ldc           #3                  // String index_field_types
      13: invokevirtual #4                  // Method com/mongodb/DB.getCollection:(Ljava/lang/String;)Lcom/mongodb/DBCollection;
      16: ldc           #5                  // class org/graylog2/indexer/fieldtypes/IndexFieldTypesDTO
      18: ldc           #6                  // class org/bson/types/ObjectId
      20: aload_2
      21: invokevirtual #7                  // Method org/graylog2/bindings/providers/MongoJackObjectMapperProvider.get:()Lcom/fasterxml/jackson/databind/ObjectMapper;
      24: invokestatic  #8                  // Method org/mongojack/JacksonDBCollection.wrap:(Lcom/mongodb/DBCollection;Ljava/lang/Class;Ljava/lang/Class;Lcom/fasterxml/jackson/databind/ObjectMapper;)Lorg/mongojack/JacksonDBCollection;
      27: putfield      #9                  // Field db:Lorg/mongojack/JacksonDBCollection;
      30: aload_0
      31: getfield      #9                  // Field db:Lorg/mongojack/JacksonDBCollection;
      34: new           #10                 // class com/mongodb/BasicDBObject
      37: dup
      38: ldc           #11                 // String index_name
      40: iconst_1
      41: invokestatic  #12                 // Method java/lang/Integer.valueOf:(I)Ljava/lang/Integer;
      44: ldc           #13                 // String index_set_id
      46: iconst_1
      47: invokestatic  #12                 // Method java/lang/Integer.valueOf:(I)Ljava/lang/Integer;
      50: invokestatic  #14                 // Method com/google/common/collect/ImmutableMap.of:(Ljava/lang/Object;Ljava/lang/Object;Ljava/lang/Object;Ljava/lang/Object;)Lcom/google/common/collect/ImmutableMap;
      53: invokespecial #15                 // Method com/mongodb/BasicDBObject."<init>":(Ljava/util/Map;)V
      56: new           #10                 // class com/mongodb/BasicDBObject
      59: dup
      60: ldc           #16                 // String unique
      62: iconst_1
      63: invokestatic  #17                 // Method java/lang/Boolean.valueOf:(Z)Ljava/lang/Boolean;
      66: invokespecial #18                 // Method com/mongodb/BasicDBObject."<init>":(Ljava/lang/String;Ljava/lang/Object;)V
      69: invokevirtual #19                 // Method org/mongojack/JacksonDBCollection.createIndex:(Lcom/mongodb/DBObject;Lcom/mongodb/DBObject;)V
      72: aload_0
      73: getfield      #9                  // Field db:Lorg/mongojack/JacksonDBCollection;
      76: new           #10                 // class com/mongodb/BasicDBObject
      79: dup
      80: ldc           #11                 // String index_name
      82: iconst_1
      83: invokestatic  #12                 // Method java/lang/Integer.valueOf:(I)Ljava/lang/Integer;
      86: invokespecial #18                 // Method com/mongodb/BasicDBObject."<init>":(Ljava/lang/String;Ljava/lang/Object;)V
      89: new           #10                 // class com/mongodb/BasicDBObject
      92: dup
      93: ldc           #16                 // String unique
      95: iconst_1
      96: invokestatic  #17                 // Method java/lang/Boolean.valueOf:(Z)Ljava/lang/Boolean;
      99: invokespecial #18                 // Method com/mongodb/BasicDBObject."<init>":(Ljava/lang/String;Ljava/lang/Object;)V
     102: invokevirtual #19                 // Method org/mongojack/JacksonDBCollection.createIndex:(Lcom/mongodb/DBObject;Lcom/mongodb/DBObject;)V
     105: aload_0
     106: getfield      #9                  // Field db:Lorg/mongojack/JacksonDBCollection;
     109: new           #10                 // class com/mongodb/BasicDBObject
     112: dup
     113: getstatic     #20                 // Field FIELDS_FIELD_NAMES:Ljava/lang/String;
     116: iconst_1
     117: invokestatic  #12                 // Method java/lang/Integer.valueOf:(I)Ljava/lang/Integer;
     120: invokespecial #18                 // Method com/mongodb/BasicDBObject."<init>":(Ljava/lang/String;Ljava/lang/Object;)V
     123: invokevirtual #21                 // Method org/mongojack/JacksonDBCollection.createIndex:(Lcom/mongodb/DBObject;)V
     126: return

  public java.util.Optional<org.graylog2.indexer.fieldtypes.IndexFieldTypesDTO> get(java.lang.String);
    Code:
       0: aload_0
       1: getfield      #9                  // Field db:Lorg/mongojack/JacksonDBCollection;
       4: new           #6                  // class org/bson/types/ObjectId
       7: dup
       8: aload_1
       9: invokespecial #22                 // Method org/bson/types/ObjectId."<init>":(Ljava/lang/String;)V
      12: invokevirtual #23                 // Method org/mongojack/JacksonDBCollection.findOneById:(Ljava/lang/Object;)Ljava/lang/Object;
      15: checkcast     #5                  // class org/graylog2/indexer/fieldtypes/IndexFieldTypesDTO
      18: invokestatic  #24                 // Method java/util/Optional.ofNullable:(Ljava/lang/Object;)Ljava/util/Optional;
      21: areturn
      22: astore_2
      23: aload_0
      24: getfield      #9                  // Field db:Lorg/mongojack/JacksonDBCollection;
      27: ldc           #11                 // String index_name
      29: aload_1
      30: invokestatic  #26                 // Method org/mongojack/DBQuery.is:(Ljava/lang/String;Ljava/lang/Object;)Lorg/mongojack/DBQuery$Query;
      33: invokevirtual #27                 // Method org/mongojack/JacksonDBCollection.findOne:(Lorg/mongojack/DBQuery$Query;)Ljava/lang/Object;
      36: checkcast     #5                  // class org/graylog2/indexer/fieldtypes/IndexFieldTypesDTO
      39: invokestatic  #24                 // Method java/util/Optional.ofNullable:(Ljava/lang/Object;)Ljava/util/Optional;
      42: areturn
    Exception table:
       from    to  target type
           0    21    22   Class java/lang/IllegalArgumentException

  public org.graylog2.indexer.fieldtypes.IndexFieldTypesDTO save(org.graylog2.indexer.fieldtypes.IndexFieldTypesDTO);
    Code:
       0: aload_0
       1: getfield      #9                  // Field db:Lorg/mongojack/JacksonDBCollection;
       4: aload_1
       5: invokevirtual #28                 // Method org/mongojack/JacksonDBCollection.save:(Ljava/lang/Object;)Lorg/mongojack/WriteResult;
       8: astore_2
       9: aload_2
      10: invokevirtual #29                 // Method org/mongojack/WriteResult.getSavedObject:()Ljava/lang/Object;
      13: checkcast     #5                  // class org/graylog2/indexer/fieldtypes/IndexFieldTypesDTO
      16: areturn

  public java.util.Optional<org.graylog2.indexer.fieldtypes.IndexFieldTypesDTO> upsert(org.graylog2.indexer.fieldtypes.IndexFieldTypesDTO);
    Code:
       0: aload_0
       1: getfield      #9                  // Field db:Lorg/mongojack/JacksonDBCollection;
       4: iconst_2
       5: anewarray     #30                 // class org/mongojack/DBQuery$Query
       8: dup
       9: iconst_0
      10: ldc           #11                 // String index_name
      12: aload_1
      13: invokevirtual #31                 // Method org/graylog2/indexer/fieldtypes/IndexFieldTypesDTO.indexName:()Ljava/lang/String;
      16: invokestatic  #26                 // Method org/mongojack/DBQuery.is:(Ljava/lang/String;Ljava/lang/Object;)Lorg/mongojack/DBQuery$Query;
      19: aastore
      20: dup
      21: iconst_1
      22: ldc           #13                 // String index_set_id
      24: aload_1
      25: invokevirtual #32                 // Method org/graylog2/indexer/fieldtypes/IndexFieldTypesDTO.indexSetId:()Ljava/lang/String;
      28: invokestatic  #26                 // Method org/mongojack/DBQuery.is:(Ljava/lang/String;Ljava/lang/Object;)Lorg/mongojack/DBQuery$Query;
      31: aastore
      32: invokestatic  #33                 // Method org/mongojack/DBQuery.and:([Lorg/mongojack/DBQuery$Query;)Lorg/mongojack/DBQuery$Query;
      35: aload_1
      36: iconst_1
      37: iconst_0
      38: invokevirtual #34                 // Method org/mongojack/JacksonDBCollection.update:(Lorg/mongojack/DBQuery$Query;Ljava/lang/Object;ZZ)Lorg/mongojack/WriteResult;
      41: astore_2
      42: aload_2
      43: invokevirtual #35                 // Method org/mongojack/WriteResult.getUpsertedId:()Ljava/lang/Object;
      46: astore_3
      47: aload_3
      48: instanceof    #6                  // class org/bson/types/ObjectId
      51: ifeq          66
      54: aload_0
      55: aload_3
      56: checkcast     #6                  // class org/bson/types/ObjectId
      59: invokevirtual #36                 // Method org/bson/types/ObjectId.toHexString:()Ljava/lang/String;
      62: invokevirtual #37                 // Method get:(Ljava/lang/String;)Ljava/util/Optional;
      65: areturn
      66: aload_3
      67: instanceof    #38                 // class java/lang/String
      70: ifeq          82
      73: aload_0
      74: aload_3
      75: checkcast     #38                 // class java/lang/String
      78: invokevirtual #37                 // Method get:(Ljava/lang/String;)Ljava/util/Optional;
      81: areturn
      82: invokestatic  #39                 // Method java/util/Optional.empty:()Ljava/util/Optional;
      85: areturn

  public void delete(java.lang.String);
    Code:
       0: aload_0
       1: getfield      #9                  // Field db:Lorg/mongojack/JacksonDBCollection;
       4: new           #6                  // class org/bson/types/ObjectId
       7: dup
       8: aload_1
       9: invokespecial #22                 // Method org/bson/types/ObjectId."<init>":(Ljava/lang/String;)V
      12: invokevirtual #40                 // Method org/mongojack/JacksonDBCollection.removeById:(Ljava/lang/Object;)Lorg/mongojack/WriteResult;
      15: pop
      16: goto          34
      19: astore_2
      20: aload_0
      21: getfield      #9                  // Field db:Lorg/mongojack/JacksonDBCollection;
      24: ldc           #11                 // String index_name
      26: aload_1
      27: invokestatic  #26                 // Method org/mongojack/DBQuery.is:(Ljava/lang/String;Ljava/lang/Object;)Lorg/mongojack/DBQuery$Query;
      30: invokevirtual #41                 // Method org/mongojack/JacksonDBCollection.remove:(Lorg/mongojack/DBQuery$Query;)Lorg/mongojack/WriteResult;
      33: pop
      34: return
    Exception table:
       from    to  target type
           0    16    19   Class java/lang/IllegalArgumentException

  public java.util.Collection<org.graylog2.indexer.fieldtypes.IndexFieldTypesDTO> findForIndexSet(java.lang.String);
    Code:
       0: aload_0
       1: ldc           #13                 // String index_set_id
       3: aload_1
       4: invokestatic  #26                 // Method org/mongojack/DBQuery.is:(Ljava/lang/String;Ljava/lang/Object;)Lorg/mongojack/DBQuery$Query;
       7: invokespecial #42                 // Method findByQuery:(Lorg/mongojack/DBQuery$Query;)Ljava/util/Collection;
      10: areturn

  public java.util.Collection<org.graylog2.indexer.fieldtypes.IndexFieldTypesDTO> findForFieldNames(java.util.Collection<java.lang.String>);
    Code:
       0: aload_0
       1: getstatic     #20                 // Field FIELDS_FIELD_NAMES:Ljava/lang/String;
       4: aload_1
       5: invokestatic  #43                 // Method org/mongojack/DBQuery.in:(Ljava/lang/String;Ljava/util/Collection;)Lorg/mongojack/DBQuery$Query;
       8: invokespecial #42                 // Method findByQuery:(Lorg/mongojack/DBQuery$Query;)Ljava/util/Collection;
      11: areturn

  public java.util.Collection<org.graylog2.indexer.fieldtypes.IndexFieldTypesDTO> findForFieldNamesAndIndices(java.util.Collection<java.lang.String>, java.util.Collection<java.lang.String>);
    Code:
       0: iconst_2
       1: anewarray     #30                 // class org/mongojack/DBQuery$Query
       4: dup
       5: iconst_0
       6: ldc           #11                 // String index_name
       8: aload_2
       9: invokestatic  #43                 // Method org/mongojack/DBQuery.in:(Ljava/lang/String;Ljava/util/Collection;)Lorg/mongojack/DBQuery$Query;
      12: aastore
      13: dup
      14: iconst_1
      15: getstatic     #20                 // Field FIELDS_FIELD_NAMES:Ljava/lang/String;
      18: aload_1
      19: invokestatic  #43                 // Method org/mongojack/DBQuery.in:(Ljava/lang/String;Ljava/util/Collection;)Lorg/mongojack/DBQuery$Query;
      22: aastore
      23: invokestatic  #33                 // Method org/mongojack/DBQuery.and:([Lorg/mongojack/DBQuery$Query;)Lorg/mongojack/DBQuery$Query;
      26: astore_3
      27: aload_0
      28: aload_3
      29: invokespecial #42                 // Method findByQuery:(Lorg/mongojack/DBQuery$Query;)Ljava/util/Collection;
      32: areturn

  public java.util.Collection<org.graylog2.indexer.fieldtypes.IndexFieldTypesDTO> findAll();
    Code:
       0: aload_0
       1: invokestatic  #44                 // Method org/mongojack/DBQuery.empty:()Lorg/mongojack/DBQuery$Query;
       4: invokespecial #42                 // Method findByQuery:(Lorg/mongojack/DBQuery$Query;)Ljava/util/Collection;
       7: areturn

  private java.util.Collection<org.graylog2.indexer.fieldtypes.IndexFieldTypesDTO> findByQuery(org.mongojack.DBQuery$Query);
    Code:
       0: aload_0
       1: getfield      #9                  // Field db:Lorg/mongojack/JacksonDBCollection;
       4: aload_1
       5: invokevirtual #45                 // Method org/mongojack/JacksonDBCollection.find:(Lorg/mongojack/DBQuery$Query;)Lorg/mongojack/DBCursor;
       8: invokestatic  #46                 // Method com/google/common/collect/ImmutableList.copyOf:(Ljava/lang/Iterable;)Lcom/google/common/collect/ImmutableList;
      11: areturn

  static {};
    Code:
       0: getstatic     #47                 // Field java/util/Locale.US:Ljava/util/Locale;
       3: ldc           #48                 // String %s.%s
       5: iconst_2
       6: anewarray     #49                 // class java/lang/Object
       9: dup
      10: iconst_0
      11: ldc           #50                 // String fields
      13: aastore
      14: dup
      15: iconst_1
      16: ldc           #52                 // String field_name
      18: aastore
      19: invokestatic  #53                 // Method java/lang/String.format:(Ljava/util/Locale;Ljava/lang/String;[Ljava/lang/Object;)Ljava/lang/String;
      22: putstatic     #20                 // Field FIELDS_FIELD_NAMES:Ljava/lang/String;
      25: return
}
