Compiled from "DistributionSummary.java"
public interface io.micrometer.core.instrument.DistributionSummary extends io.micrometer.core.instrument.Meter,io.micrometer.core.instrument.distribution.HistogramSupport {
  public static io.micrometer.core.instrument.DistributionSummary$Builder builder(java.lang.String);
    Code:
       0: new           #1                  // class io/micrometer/core/instrument/DistributionSummary$Builder
       3: dup
       4: aload_0
       5: aconst_null
       6: invokespecial #3                  // Method io/micrometer/core/instrument/DistributionSummary$Builder."<init>":(Ljava/lang/String;Lio/micrometer/core/instrument/DistributionSummary$1;)V
       9: areturn

  public abstract void record(double);

  public abstract long count();

  public abstract double totalAmount();

  public default double mean();
    Code:
       0: aload_0
       1: invokeinterface #7,  1            // InterfaceMethod count:()J
       6: lconst_0
       7: lcmp
       8: ifne          15
      11: dconst_0
      12: goto          29
      15: aload_0
      16: invokeinterface #13,  1           // InterfaceMethod totalAmount:()D
      21: aload_0
      22: invokeinterface #7,  1            // InterfaceMethod count:()J
      27: l2d
      28: ddiv
      29: dreturn

  public abstract double max();

  public default double histogramCountAtValue(long);
    Code:
       0: aload_0
       1: invokeinterface #17,  1           // InterfaceMethod takeSnapshot:()Lio/micrometer/core/instrument/distribution/HistogramSnapshot;
       6: invokevirtual #21                 // Method io/micrometer/core/instrument/distribution/HistogramSnapshot.histogramCounts:()[Lio/micrometer/core/instrument/distribution/CountAtBucket;
       9: astore_3
      10: aload_3
      11: arraylength
      12: istore        4
      14: iconst_0
      15: istore        5
      17: iload         5
      19: iload         4
      21: if_icmpge     56
      24: aload_3
      25: iload         5
      27: aaload
      28: astore        6
      30: aload         6
      32: getstatic     #27                 // Field java/util/concurrent/TimeUnit.NANOSECONDS:Ljava/util/concurrent/TimeUnit;
      35: invokevirtual #33                 // Method io/micrometer/core/instrument/distribution/CountAtBucket.bucket:(Ljava/util/concurrent/TimeUnit;)D
      38: d2l
      39: lload_1
      40: lcmp
      41: ifne          50
      44: aload         6
      46: invokevirtual #39                 // Method io/micrometer/core/instrument/distribution/CountAtBucket.count:()D
      49: dreturn
      50: iinc          5, 1
      53: goto          17
      56: ldc2_w        #43                 // double NaNd
      59: dreturn

  public default double percentile(double);
    Code:
       0: aload_0
       1: invokeinterface #17,  1           // InterfaceMethod takeSnapshot:()Lio/micrometer/core/instrument/distribution/HistogramSnapshot;
       6: invokevirtual #45                 // Method io/micrometer/core/instrument/distribution/HistogramSnapshot.percentileValues:()[Lio/micrometer/core/instrument/distribution/ValueAtPercentile;
       9: astore_3
      10: aload_3
      11: arraylength
      12: istore        4
      14: iconst_0
      15: istore        5
      17: iload         5
      19: iload         4
      21: if_icmpge     52
      24: aload_3
      25: iload         5
      27: aaload
      28: astore        6
      30: aload         6
      32: invokevirtual #49                 // Method io/micrometer/core/instrument/distribution/ValueAtPercentile.percentile:()D
      35: dload_1
      36: dcmpl
      37: ifne          46
      40: aload         6
      42: invokevirtual #54                 // Method io/micrometer/core/instrument/distribution/ValueAtPercentile.value:()D
      45: dreturn
      46: iinc          5, 1
      49: goto          17
      52: ldc2_w        #43                 // double NaNd
      55: dreturn

  public default java.lang.Iterable<io.micrometer.core.instrument.Measurement> measure();
    Code:
       0: iconst_2
       1: anewarray     #57                 // class io/micrometer/core/instrument/Measurement
       4: dup
       5: iconst_0
       6: new           #57                 // class io/micrometer/core/instrument/Measurement
       9: dup
      10: aload_0
      11: invokedynamic #59,  0             // InvokeDynamic #0:get:(Lio/micrometer/core/instrument/DistributionSummary;)Ljava/util/function/Supplier;
      16: getstatic     #63                 // Field io/micrometer/core/instrument/Statistic.COUNT:Lio/micrometer/core/instrument/Statistic;
      19: invokespecial #69                 // Method io/micrometer/core/instrument/Measurement."<init>":(Ljava/util/function/Supplier;Lio/micrometer/core/instrument/Statistic;)V
      22: aastore
      23: dup
      24: iconst_1
      25: new           #57                 // class io/micrometer/core/instrument/Measurement
      28: dup
      29: aload_0
      30: invokedynamic #72,  0             // InvokeDynamic #1:get:(Lio/micrometer/core/instrument/DistributionSummary;)Ljava/util/function/Supplier;
      35: getstatic     #73                 // Field io/micrometer/core/instrument/Statistic.TOTAL:Lio/micrometer/core/instrument/Statistic;
      38: invokespecial #69                 // Method io/micrometer/core/instrument/Measurement."<init>":(Ljava/util/function/Supplier;Lio/micrometer/core/instrument/Statistic;)V
      41: aastore
      42: invokestatic  #76                 // Method java/util/Arrays.asList:([Ljava/lang/Object;)Ljava/util/List;
      45: areturn

  private java.lang.Double lambda$measure$0();
    Code:
       0: aload_0
       1: invokeinterface #7,  1            // InterfaceMethod count:()J
       6: l2d
       7: invokestatic  #82                 // Method java/lang/Double.valueOf:(D)Ljava/lang/Double;
      10: areturn
}
