Compiled from "TimeGauge.java"
public interface io.micrometer.core.instrument.TimeGauge extends io.micrometer.core.instrument.Gauge {
  public static <T> io.micrometer.core.instrument.TimeGauge$Builder<T> builder(java.lang.String, T, java.util.concurrent.TimeUnit, java.util.function.ToDoubleFunction<T>);
    Code:
       0: new           #1                  // class io/micrometer/core/instrument/TimeGauge$Builder
       3: dup
       4: aload_0
       5: aload_1
       6: aload_2
       7: aload_3
       8: aconst_null
       9: invokespecial #3                  // Method io/micrometer/core/instrument/TimeGauge$Builder."<init>":(Ljava/lang/String;Ljava/lang/Object;Ljava/util/concurrent/TimeUnit;Ljava/util/function/ToDoubleFunction;Lio/micrometer/core/instrument/TimeGauge$1;)V
      12: areturn

  public abstract java.util.concurrent.TimeUnit baseTimeUnit();

  public default double value(java.util.concurrent.TimeUnit);
    Code:
       0: aload_0
       1: invokeinterface #7,  1            // InterfaceMethod value:()D
       6: aload_0
       7: invokeinterface #13,  1           // InterfaceMethod baseTimeUnit:()Ljava/util/concurrent/TimeUnit;
      12: aload_1
      13: invokestatic  #17                 // Method io/micrometer/core/instrument/util/TimeUtils.convert:(DLjava/util/concurrent/TimeUnit;Ljava/util/concurrent/TimeUnit;)D
      16: dreturn
}
