Compiled from "BinaryWire.java"
final class net.openhft.chronicle.wire.BinaryWire$AnyCodeMatch extends java.lang.Enum<net.openhft.chronicle.wire.BinaryWire$AnyCodeMatch> implements net.openhft.chronicle.wire.WireKey {
  public static final net.openhft.chronicle.wire.BinaryWire$AnyCodeMatch ANY_CODE_MATCH;

  private static final net.openhft.chronicle.wire.BinaryWire$AnyCodeMatch[] $VALUES;

  public static net.openhft.chronicle.wire.BinaryWire$AnyCodeMatch[] values();
    Code:
       0: getstatic     #1                  // Field $VALUES:[Lnet/openhft/chronicle/wire/BinaryWire$AnyCodeMatch;
       3: invokevirtual #2                  // Method "[Lnet/openhft/chronicle/wire/BinaryWire$AnyCodeMatch;".clone:()Ljava/lang/Object;
       6: checkcast     #3                  // class "[Lnet/openhft/chronicle/wire/BinaryWire$AnyCodeMatch;"
       9: areturn

  public static net.openhft.chronicle.wire.BinaryWire$AnyCodeMatch valueOf(java.lang.String);
    Code:
       0: ldc           #4                  // class net/openhft/chronicle/wire/BinaryWire$AnyCodeMatch
       2: aload_0
       3: invokestatic  #5                  // Method java/lang/Enum.valueOf:(Ljava/lang/Class;Ljava/lang/String;)Ljava/lang/Enum;
       6: checkcast     #4                  // class net/openhft/chronicle/wire/BinaryWire$AnyCodeMatch
       9: areturn

  private net.openhft.chronicle.wire.BinaryWire$AnyCodeMatch();
    Code:
       0: aload_0
       1: aload_1
       2: iload_2
       3: invokespecial #6                  // Method java/lang/Enum."<init>":(Ljava/lang/String;I)V
       6: return

  public int code();
    Code:
       0: ldc           #8                  // int -2147483648
       2: ireturn

  public java.lang.CharSequence name();
    Code:
       0: aload_0
       1: invokespecial #9                  // Method java/lang/Enum.name:()Ljava/lang/String;
       4: areturn

  static {};
    Code:
       0: new           #4                  // class net/openhft/chronicle/wire/BinaryWire$AnyCodeMatch
       3: dup
       4: ldc           #10                 // String ANY_CODE_MATCH
       6: iconst_0
       7: invokespecial #11                 // Method "<init>":(Ljava/lang/String;I)V
      10: putstatic     #12                 // Field ANY_CODE_MATCH:Lnet/openhft/chronicle/wire/BinaryWire$AnyCodeMatch;
      13: iconst_1
      14: anewarray     #4                  // class net/openhft/chronicle/wire/BinaryWire$AnyCodeMatch
      17: dup
      18: iconst_0
      19: getstatic     #12                 // Field ANY_CODE_MATCH:Lnet/openhft/chronicle/wire/BinaryWire$AnyCodeMatch;
      22: aastore
      23: putstatic     #1                  // Field $VALUES:[Lnet/openhft/chronicle/wire/BinaryWire$AnyCodeMatch;
      26: return
}
