Compiled from "MicroDurationLongConverter.java"
public class net.openhft.chronicle.wire.MicroDurationLongConverter implements net.openhft.chronicle.wire.LongConverter {
  public net.openhft.chronicle.wire.MicroDurationLongConverter();
    Code:
       0: aload_0
       1: invokespecial #1                  // Method java/lang/Object."<init>":()V
       4: return

  public long parse(java.lang.CharSequence);
    Code:
       0: aload_1
       1: invokestatic  #2                  // Method java/time/Duration.parse:(Ljava/lang/CharSequence;)Ljava/time/Duration;
       4: astore_2
       5: aload_2
       6: invokevirtual #3                  // Method java/time/Duration.getSeconds:()J
       9: ldc2_w        #4                  // long 1000000l
      12: lmul
      13: aload_2
      14: invokevirtual #6                  // Method java/time/Duration.getNano:()I
      17: sipush        1000
      20: idiv
      21: i2l
      22: ladd
      23: lstore_3
      24: lload_3
      25: lreturn

  public void append(java.lang.StringBuilder, long);
    Code:
       0: lload_2
       1: ldc2_w        #4                  // long 1000000l
       4: ldiv
       5: lload_2
       6: ldc2_w        #4                  // long 1000000l
       9: lrem
      10: ldc2_w        #7                  // long 1000l
      13: lmul
      14: invokestatic  #9                  // Method java/time/Duration.ofSeconds:(JJ)Ljava/time/Duration;
      17: astore        4
      19: aload_1
      20: aload         4
      22: invokevirtual #10                 // Method java/lang/StringBuilder.append:(Ljava/lang/Object;)Ljava/lang/StringBuilder;
      25: pop
      26: return
}
