Compiled from "ReadAnyWire.java"
class net.openhft.chronicle.wire.ReadAnyWire$ReadAnyWireAcquisition implements net.openhft.chronicle.wire.AbstractAnyWire$WireAcquisition {
  private final net.openhft.chronicle.bytes.Bytes bytes;

  net.openhft.chronicle.wire.WireType wireType;

  net.openhft.chronicle.wire.Wire wire;

  private net.openhft.chronicle.core.pool.ClassLookup classLookup;

  public net.openhft.chronicle.wire.ReadAnyWire$ReadAnyWireAcquisition(net.openhft.chronicle.bytes.Bytes);
    Code:
       0: aload_0
       1: invokespecial #1                  // Method java/lang/Object."<init>":()V
       4: aload_0
       5: aconst_null
       6: putfield      #2                  // Field wire:Lnet/openhft/chronicle/wire/Wire;
       9: aload_0
      10: getstatic     #3                  // Field net/openhft/chronicle/core/pool/ClassAliasPool.CLASS_ALIASES:Lnet/openhft/chronicle/core/pool/ClassAliasPool;
      13: putfield      #4                  // Field classLookup:Lnet/openhft/chronicle/core/pool/ClassLookup;
      16: aload_0
      17: aload_1
      18: putfield      #5                  // Field bytes:Lnet/openhft/chronicle/bytes/Bytes;
      21: return

  public void classLookup(net.openhft.chronicle.core.pool.ClassLookup);
    Code:
       0: aload_0
       1: aload_1
       2: putfield      #4                  // Field classLookup:Lnet/openhft/chronicle/core/pool/ClassLookup;
       5: aload_0
       6: getfield      #2                  // Field wire:Lnet/openhft/chronicle/wire/Wire;
       9: ifnull        22
      12: aload_0
      13: getfield      #2                  // Field wire:Lnet/openhft/chronicle/wire/Wire;
      16: aload_1
      17: invokeinterface #6,  2            // InterfaceMethod net/openhft/chronicle/wire/Wire.classLookup:(Lnet/openhft/chronicle/core/pool/ClassLookup;)V
      22: return

  public net.openhft.chronicle.core.pool.ClassLookup classLookup();
    Code:
       0: aload_0
       1: getfield      #4                  // Field classLookup:Lnet/openhft/chronicle/core/pool/ClassLookup;
       4: areturn

  public java.util.function.Supplier<net.openhft.chronicle.wire.WireType> underlyingType();
    Code:
       0: aload_0
       1: invokedynamic #7,  0              // InvokeDynamic #0:get:(Lnet/openhft/chronicle/wire/ReadAnyWire$ReadAnyWireAcquisition;)Ljava/util/function/Supplier;
       6: areturn

  public net.openhft.chronicle.wire.Wire acquireWire();
    Code:
       0: aload_0
       1: getfield      #2                  // Field wire:Lnet/openhft/chronicle/wire/Wire;
       4: ifnull        12
       7: aload_0
       8: getfield      #2                  // Field wire:Lnet/openhft/chronicle/wire/Wire;
      11: areturn
      12: aload_0
      13: getfield      #5                  // Field bytes:Lnet/openhft/chronicle/bytes/Bytes;
      16: invokeinterface #8,  1            // InterfaceMethod net/openhft/chronicle/bytes/Bytes.readRemaining:()J
      21: ldc2_w        #9                  // long 8l
      24: lcmp
      25: iflt          175
      28: aload_0
      29: getfield      #5                  // Field bytes:Lnet/openhft/chronicle/bytes/Bytes;
      32: aload_0
      33: getfield      #5                  // Field bytes:Lnet/openhft/chronicle/bytes/Bytes;
      36: invokeinterface #11,  1           // InterfaceMethod net/openhft/chronicle/bytes/Bytes.readPosition:()J
      41: invokeinterface #12,  3           // InterfaceMethod net/openhft/chronicle/bytes/Bytes.readInt:(J)I
      46: aload_0
      47: getfield      #5                  // Field bytes:Lnet/openhft/chronicle/bytes/Bytes;
      50: aload_0
      51: getfield      #5                  // Field bytes:Lnet/openhft/chronicle/bytes/Bytes;
      54: invokeinterface #11,  1           // InterfaceMethod net/openhft/chronicle/bytes/Bytes.readPosition:()J
      59: ldc2_w        #13                 // long 4l
      62: ladd
      63: invokeinterface #12,  3           // InterfaceMethod net/openhft/chronicle/bytes/Bytes.readInt:(J)I
      68: ior
      69: istore_1
      70: iload_1
      71: iload_1
      72: bipush        16
      74: ishr
      75: ior
      76: istore_1
      77: iload_1
      78: iload_1
      79: bipush        8
      81: ishr
      82: ior
      83: istore_1
      84: iload_1
      85: sipush        128
      88: iand
      89: ifne          102
      92: aload_0
      93: getstatic     #15                 // Field net/openhft/chronicle/wire/WireType.TEXT:Lnet/openhft/chronicle/wire/WireType;
      96: putfield      #16                 // Field wireType:Lnet/openhft/chronicle/wire/WireType;
      99: goto          143
     102: aload_0
     103: getfield      #5                  // Field bytes:Lnet/openhft/chronicle/bytes/Bytes;
     106: aload_0
     107: getfield      #5                  // Field bytes:Lnet/openhft/chronicle/bytes/Bytes;
     110: invokeinterface #11,  1           // InterfaceMethod net/openhft/chronicle/bytes/Bytes.readPosition:()J
     115: invokeinterface #17,  3           // InterfaceMethod net/openhft/chronicle/bytes/Bytes.readByte:(J)B
     120: invokestatic  #18                 // Method net/openhft/chronicle/wire/BinaryWireCode.isFieldCode:(I)Z
     123: ifeq          136
     126: aload_0
     127: getstatic     #19                 // Field net/openhft/chronicle/wire/WireType.FIELDLESS_BINARY:Lnet/openhft/chronicle/wire/WireType;
     130: putfield      #16                 // Field wireType:Lnet/openhft/chronicle/wire/WireType;
     133: goto          143
     136: aload_0
     137: getstatic     #20                 // Field net/openhft/chronicle/wire/WireType.BINARY:Lnet/openhft/chronicle/wire/WireType;
     140: putfield      #16                 // Field wireType:Lnet/openhft/chronicle/wire/WireType;
     143: aload_0
     144: getfield      #16                 // Field wireType:Lnet/openhft/chronicle/wire/WireType;
     147: aload_0
     148: getfield      #5                  // Field bytes:Lnet/openhft/chronicle/bytes/Bytes;
     151: invokevirtual #21                 // Method net/openhft/chronicle/wire/WireType.apply:(Ljava/lang/Object;)Ljava/lang/Object;
     154: checkcast     #22                 // class net/openhft/chronicle/wire/Wire
     157: astore_2
     158: aload_2
     159: aload_0
     160: getfield      #4                  // Field classLookup:Lnet/openhft/chronicle/core/pool/ClassLookup;
     163: invokeinterface #6,  2            // InterfaceMethod net/openhft/chronicle/wire/Wire.classLookup:(Lnet/openhft/chronicle/core/pool/ClassLookup;)V
     168: aload_0
     169: aload_2
     170: dup_x1
     171: putfield      #2                  // Field wire:Lnet/openhft/chronicle/wire/Wire;
     174: areturn
     175: aconst_null
     176: areturn

  public net.openhft.chronicle.bytes.Bytes bytes();
    Code:
       0: aload_0
       1: getfield      #5                  // Field bytes:Lnet/openhft/chronicle/bytes/Bytes;
       4: areturn

  private net.openhft.chronicle.wire.WireType lambda$underlyingType$0();
    Code:
       0: aload_0
       1: getfield      #16                 // Field wireType:Lnet/openhft/chronicle/wire/WireType;
       4: areturn
}
