Compiled from "WireMarshaller.java"
class net.openhft.chronicle.wire.WireMarshaller$CollectionFieldAccess extends net.openhft.chronicle.wire.WireMarshaller$FieldAccess {
  final java.util.function.Supplier<java.util.Collection> collectionSupplier;

  private final java.lang.Class componentType;

  private final java.lang.Class<?> type;

  private java.util.function.BiConsumer<java.lang.Object, net.openhft.chronicle.wire.ValueOut> sequenceGetter;

  public net.openhft.chronicle.wire.WireMarshaller$CollectionFieldAccess(java.lang.reflect.Field, java.lang.Boolean, java.util.function.Supplier<java.util.Collection>, java.lang.Class, java.lang.Class<?>);
    Code:
       0: aload_0
       1: aload_1
       2: aload_2
       3: invokespecial #1                  // Method net/openhft/chronicle/wire/WireMarshaller$FieldAccess."<init>":(Ljava/lang/reflect/Field;Ljava/lang/Boolean;)V
       6: aload_0
       7: aload_3
       8: ifnonnull     18
      11: aload_0
      12: invokespecial #2                  // Method newInstance:()Ljava/util/function/Supplier;
      15: goto          19
      18: aload_3
      19: putfield      #3                  // Field collectionSupplier:Ljava/util/function/Supplier;
      22: aload_0
      23: aload         4
      25: putfield      #4                  // Field componentType:Ljava/lang/Class;
      28: aload_0
      29: aload         5
      31: putfield      #5                  // Field type:Ljava/lang/Class;
      34: aload_0
      35: aload_1
      36: aload         4
      38: invokedynamic #6,  0              // InvokeDynamic #0:accept:(Ljava/lang/reflect/Field;Ljava/lang/Class;)Ljava/util/function/BiConsumer;
      43: putfield      #7                  // Field sequenceGetter:Ljava/util/function/BiConsumer;
      46: return

  static net.openhft.chronicle.wire.WireMarshaller$FieldAccess of(java.lang.reflect.Field);
    Code:
       0: aconst_null
       1: astore        4
       3: aload_0
       4: invokevirtual #8                  // Method java/lang/reflect/Field.getType:()Ljava/lang/Class;
       7: astore_3
       8: aload_3
       9: ldc           #9                  // class java/util/List
      11: if_acmpeq     20
      14: aload_3
      15: ldc           #10                 // class java/util/Collection
      17: if_acmpne     29
      20: invokedynamic #11,  0             // InvokeDynamic #1:get:()Ljava/util/function/Supplier;
      25: astore_1
      26: goto          67
      29: aload_3
      30: ldc           #12                 // class java/util/SortedSet
      32: if_acmpeq     41
      35: aload_3
      36: ldc           #13                 // class java/util/NavigableSet
      38: if_acmpne     50
      41: invokedynamic #14,  0             // InvokeDynamic #2:get:()Ljava/util/function/Supplier;
      46: astore_1
      47: goto          67
      50: aload_3
      51: ldc           #15                 // class java/util/Set
      53: if_acmpne     65
      56: invokedynamic #16,  0             // InvokeDynamic #3:get:()Ljava/util/function/Supplier;
      61: astore_1
      62: goto          67
      65: aconst_null
      66: astore_1
      67: aload_0
      68: invokevirtual #17                 // Method java/lang/reflect/Field.getGenericType:()Ljava/lang/reflect/Type;
      71: astore        5
      73: aload         5
      75: instanceof    #18                 // class java/lang/reflect/ParameterizedType
      78: ifeq          143
      81: aload         5
      83: checkcast     #18                 // class java/lang/reflect/ParameterizedType
      86: astore        6
      88: aload         6
      90: invokeinterface #19,  1           // InterfaceMethod java/lang/reflect/ParameterizedType.getActualTypeArguments:()[Ljava/lang/reflect/Type;
      95: iconst_0
      96: aaload
      97: astore        7
      99: aload         7
     101: invokestatic  #20                 // Method extractClass:(Ljava/lang/reflect/Type;)Ljava/lang/Class;
     104: astore_2
     105: ldc           #21                 // class java/lang/Throwable
     107: aload_2
     108: invokevirtual #22                 // Method java/lang/Class.isAssignableFrom:(Ljava/lang/Class;)Z
     111: ifne          134
     114: getstatic     #23                 // Field net/openhft/chronicle/wire/WireMarshaller.WIRE_MARSHALLER_CL:Lnet/openhft/chronicle/core/ClassLocal;
     117: aload_2
     118: invokevirtual #24                 // Method net/openhft/chronicle/core/ClassLocal.get:(Ljava/lang/Class;)Ljava/lang/Object;
     121: checkcast     #25                 // class net/openhft/chronicle/wire/WireMarshaller
     124: invokestatic  #26                 // Method net/openhft/chronicle/wire/WireMarshaller.access$000:(Lnet/openhft/chronicle/wire/WireMarshaller;)Z
     127: ifeq          134
     130: iconst_1
     131: goto          135
     134: iconst_0
     135: invokestatic  #27                 // Method java/lang/Boolean.valueOf:(Z)Ljava/lang/Boolean;
     138: astore        4
     140: goto          146
     143: ldc           #28                 // class java/lang/Object
     145: astore_2
     146: aload_2
     147: ldc           #29                 // class java/lang/String
     149: if_acmpne     169
     152: new           #30                 // class net/openhft/chronicle/wire/WireMarshaller$StringCollectionFieldAccess
     155: dup
     156: aload_0
     157: iconst_1
     158: invokestatic  #27                 // Method java/lang/Boolean.valueOf:(Z)Ljava/lang/Boolean;
     161: aload_1
     162: aload_3
     163: invokespecial #31                 // Method net/openhft/chronicle/wire/WireMarshaller$StringCollectionFieldAccess."<init>":(Ljava/lang/reflect/Field;Ljava/lang/Boolean;Ljava/util/function/Supplier;Ljava/lang/Class;)V
     166: goto          182
     169: new           #32                 // class net/openhft/chronicle/wire/WireMarshaller$CollectionFieldAccess
     172: dup
     173: aload_0
     174: aload         4
     176: aload_1
     177: aload_2
     178: aload_3
     179: invokespecial #33                 // Method "<init>":(Ljava/lang/reflect/Field;Ljava/lang/Boolean;Ljava/util/function/Supplier;Ljava/lang/Class;Ljava/lang/Class;)V
     182: areturn

  private java.util.function.Supplier<java.util.Collection> newInstance();
    Code:
       0: aload_0
       1: invokedynamic #34,  0             // InvokeDynamic #4:get:(Lnet/openhft/chronicle/wire/WireMarshaller$CollectionFieldAccess;)Ljava/util/function/Supplier;
       6: areturn

  protected void getValue(java.lang.Object, net.openhft.chronicle.wire.ValueOut, java.lang.Object) throws java.lang.IllegalAccessException;
    Code:
       0: aload_0
       1: getfield      #35                 // Field field:Ljava/lang/reflect/Field;
       4: aload_1
       5: invokevirtual #36                 // Method java/lang/reflect/Field.get:(Ljava/lang/Object;)Ljava/lang/Object;
       8: checkcast     #10                 // class java/util/Collection
      11: astore        4
      13: aload         4
      15: ifnonnull     26
      18: aload_2
      19: invokeinterface #37,  1           // InterfaceMethod net/openhft/chronicle/wire/ValueOut.nu11:()Lnet/openhft/chronicle/wire/WireOut;
      24: pop
      25: return
      26: aload_2
      27: aload_1
      28: aload_0
      29: getfield      #7                  // Field sequenceGetter:Ljava/util/function/BiConsumer;
      32: invokeinterface #38,  3           // InterfaceMethod net/openhft/chronicle/wire/ValueOut.sequence:(Ljava/lang/Object;Ljava/util/function/BiConsumer;)Lnet/openhft/chronicle/wire/WireOut;
      37: pop
      38: return

  protected void copy(java.lang.Object, java.lang.Object) throws java.lang.IllegalAccessException;
    Code:
       0: aload_0
       1: getfield      #35                 // Field field:Ljava/lang/reflect/Field;
       4: aload_1
       5: invokevirtual #36                 // Method java/lang/reflect/Field.get:(Ljava/lang/Object;)Ljava/lang/Object;
       8: checkcast     #10                 // class java/util/Collection
      11: astore_3
      12: aload_3
      13: ifnonnull     26
      16: aload_0
      17: getfield      #35                 // Field field:Ljava/lang/reflect/Field;
      20: aload_2
      21: aconst_null
      22: invokevirtual #39                 // Method java/lang/reflect/Field.set:(Ljava/lang/Object;Ljava/lang/Object;)V
      25: return
      26: aload_0
      27: getfield      #35                 // Field field:Ljava/lang/reflect/Field;
      30: aload_2
      31: invokevirtual #36                 // Method java/lang/reflect/Field.get:(Ljava/lang/Object;)Ljava/lang/Object;
      34: checkcast     #10                 // class java/util/Collection
      37: astore        4
      39: aload         4
      41: ifnonnull     68
      44: aload_0
      45: getfield      #3                  // Field collectionSupplier:Ljava/util/function/Supplier;
      48: invokeinterface #40,  1           // InterfaceMethod java/util/function/Supplier.get:()Ljava/lang/Object;
      53: checkcast     #10                 // class java/util/Collection
      56: astore        4
      58: aload_0
      59: getfield      #35                 // Field field:Ljava/lang/reflect/Field;
      62: aload_2
      63: aload         4
      65: invokevirtual #39                 // Method java/lang/reflect/Field.set:(Ljava/lang/Object;Ljava/lang/Object;)V
      68: aload         4
      70: invokeinterface #41,  1           // InterfaceMethod java/util/Collection.clear:()V
      75: aload         4
      77: aload_3
      78: invokeinterface #42,  2           // InterfaceMethod java/util/Collection.addAll:(Ljava/util/Collection;)Z
      83: pop
      84: return

  protected void readValue(java.lang.Object, java.lang.Object, net.openhft.chronicle.wire.ValueIn, boolean) throws java.lang.IllegalAccessException;
    Code:
       0: aload_0
       1: getfield      #35                 // Field field:Ljava/lang/reflect/Field;
       4: aload_1
       5: invokevirtual #36                 // Method java/lang/reflect/Field.get:(Ljava/lang/Object;)Ljava/lang/Object;
       8: checkcast     #10                 // class java/util/Collection
      11: astore        5
      13: aload         5
      15: ifnonnull     42
      18: aload_0
      19: getfield      #3                  // Field collectionSupplier:Ljava/util/function/Supplier;
      22: invokeinterface #40,  1           // InterfaceMethod java/util/function/Supplier.get:()Ljava/lang/Object;
      27: checkcast     #10                 // class java/util/Collection
      30: astore        5
      32: aload_0
      33: getfield      #35                 // Field field:Ljava/lang/reflect/Field;
      36: aload_1
      37: aload         5
      39: invokevirtual #39                 // Method java/lang/reflect/Field.set:(Ljava/lang/Object;Ljava/lang/Object;)V
      42: aload_3
      43: aload         5
      45: aload_0
      46: invokedynamic #43,  0             // InvokeDynamic #5:accept:(Lnet/openhft/chronicle/wire/WireMarshaller$CollectionFieldAccess;)Ljava/util/function/BiConsumer;
      51: invokeinterface #44,  3           // InterfaceMethod net/openhft/chronicle/wire/ValueIn.sequence:(Ljava/lang/Object;Ljava/util/function/BiConsumer;)Z
      56: ifne          116
      59: aload_0
      60: getfield      #35                 // Field field:Ljava/lang/reflect/Field;
      63: aload_2
      64: invokevirtual #36                 // Method java/lang/reflect/Field.get:(Ljava/lang/Object;)Ljava/lang/Object;
      67: checkcast     #10                 // class java/util/Collection
      70: astore        6
      72: aload         6
      74: ifnonnull     89
      77: aload_0
      78: getfield      #35                 // Field field:Ljava/lang/reflect/Field;
      81: aload_1
      82: aconst_null
      83: invokevirtual #39                 // Method java/lang/reflect/Field.set:(Ljava/lang/Object;Ljava/lang/Object;)V
      86: goto          116
      89: aload         5
      91: invokeinterface #41,  1           // InterfaceMethod java/util/Collection.clear:()V
      96: aload         6
      98: invokeinterface #45,  1           // InterfaceMethod java/util/Collection.isEmpty:()Z
     103: ifne          116
     106: aload         5
     108: aload         6
     110: invokeinterface #42,  2           // InterfaceMethod java/util/Collection.addAll:(Ljava/util/Collection;)Z
     115: pop
     116: return

  protected void setValue(java.lang.Object, net.openhft.chronicle.wire.ValueIn, boolean);
    Code:
       0: new           #46                 // class java/lang/UnsupportedOperationException
       3: dup
       4: invokespecial #47                 // Method java/lang/UnsupportedOperationException."<init>":()V
       7: athrow

  public void getAsBytes(java.lang.Object, net.openhft.chronicle.bytes.Bytes);
    Code:
       0: new           #46                 // class java/lang/UnsupportedOperationException
       3: dup
       4: invokespecial #47                 // Method java/lang/UnsupportedOperationException."<init>":()V
       7: athrow

  protected boolean sameValue(java.lang.Object, java.lang.Object) throws java.lang.IllegalAccessException;
    Code:
       0: aload_0
       1: aload_1
       2: aload_2
       3: invokespecial #48                 // Method net/openhft/chronicle/wire/WireMarshaller$FieldAccess.sameValue:(Ljava/lang/Object;Ljava/lang/Object;)Z
       6: ireturn

  private void lambda$readValue$2(java.util.Collection, net.openhft.chronicle.wire.ValueIn);
    Code:
       0: aload_1
       1: invokeinterface #45,  1           // InterfaceMethod java/util/Collection.isEmpty:()Z
       6: ifne          15
       9: aload_1
      10: invokeinterface #41,  1           // InterfaceMethod java/util/Collection.clear:()V
      15: aload_2
      16: invokeinterface #49,  1           // InterfaceMethod net/openhft/chronicle/wire/ValueIn.hasNextSequenceItem:()Z
      21: ifeq          44
      24: aload_1
      25: aload_2
      26: aload_0
      27: getfield      #4                  // Field componentType:Ljava/lang/Class;
      30: invokeinterface #50,  2           // InterfaceMethod net/openhft/chronicle/wire/ValueIn.object:(Ljava/lang/Class;)Ljava/lang/Object;
      35: invokeinterface #51,  2           // InterfaceMethod java/util/Collection.add:(Ljava/lang/Object;)Z
      40: pop
      41: goto          15
      44: return

  private java.util.Collection lambda$newInstance$1();
    Code:
       0: aload_0
       1: getfield      #5                  // Field type:Ljava/lang/Class;
       4: invokestatic  #52                 // Method net/openhft/chronicle/core/util/ObjectUtils.newInstance:(Ljava/lang/Class;)Ljava/lang/Object;
       7: checkcast     #10                 // class java/util/Collection
      10: areturn

  private static void lambda$new$0(java.lang.reflect.Field, java.lang.Class, java.lang.Object, net.openhft.chronicle.wire.ValueOut);
    Code:
       0: aload_0
       1: aload_2
       2: invokevirtual #36                 // Method java/lang/reflect/Field.get:(Ljava/lang/Object;)Ljava/lang/Object;
       5: checkcast     #10                 // class java/util/Collection
       8: astore        4
      10: goto          25
      13: astore        5
      15: new           #54                 // class java/lang/AssertionError
      18: dup
      19: aload         5
      21: invokespecial #55                 // Method java/lang/AssertionError."<init>":(Ljava/lang/Object;)V
      24: athrow
      25: aload         4
      27: instanceof    #56                 // class java/util/RandomAccess
      30: ifeq          85
      33: aload         4
      35: checkcast     #9                  // class java/util/List
      38: astore        5
      40: iconst_0
      41: istore        6
      43: aload         5
      45: invokeinterface #57,  1           // InterfaceMethod java/util/List.size:()I
      50: istore        7
      52: iload         6
      54: iload         7
      56: if_icmpge     82
      59: aload_3
      60: aload_1
      61: aload         5
      63: iload         6
      65: invokeinterface #58,  2           // InterfaceMethod java/util/List.get:(I)Ljava/lang/Object;
      70: invokeinterface #59,  3           // InterfaceMethod net/openhft/chronicle/wire/ValueOut.object:(Ljava/lang/Class;Ljava/lang/Object;)Lnet/openhft/chronicle/wire/WireOut;
      75: pop
      76: iinc          6, 1
      79: goto          52
      82: goto          153
      85: aload         4
      87: ifnonnull     112
      90: aload_0
      91: aload         4
      93: aconst_null
      94: invokevirtual #39                 // Method java/lang/reflect/Field.set:(Ljava/lang/Object;Ljava/lang/Object;)V
      97: goto          153
     100: astore        5
     102: new           #54                 // class java/lang/AssertionError
     105: dup
     106: aload         5
     108: invokespecial #55                 // Method java/lang/AssertionError."<init>":(Ljava/lang/Object;)V
     111: athrow
     112: aload         4
     114: invokeinterface #60,  1           // InterfaceMethod java/util/Collection.iterator:()Ljava/util/Iterator;
     119: astore        5
     121: aload         5
     123: invokeinterface #61,  1           // InterfaceMethod java/util/Iterator.hasNext:()Z
     128: ifeq          153
     131: aload         5
     133: invokeinterface #62,  1           // InterfaceMethod java/util/Iterator.next:()Ljava/lang/Object;
     138: astore        6
     140: aload_3
     141: aload_1
     142: aload         6
     144: invokeinterface #63,  3           // InterfaceMethod net/openhft/chronicle/wire/ValueOut.object:(Ljava/lang/Class;Ljava/lang/Object;)Lnet/openhft/chronicle/wire/WireOut;
     149: pop
     150: goto          121
     153: return
    Exception table:
       from    to  target type
           0    10    13   Class java/lang/IllegalAccessException
          90    97   100   Class java/lang/IllegalAccessException
}
