Compiled from "WireType.java"
class net.openhft.chronicle.wire.WireType$13 extends java.util.Spliterators$AbstractSpliterator<T> {
  final net.openhft.chronicle.wire.Wire val$wire;

  final net.openhft.chronicle.wire.ValueIn val$valueIn;

  final java.lang.Class val$expectedType;

  final net.openhft.chronicle.wire.WireType this$0;

  net.openhft.chronicle.wire.WireType$13(net.openhft.chronicle.wire.WireType, long, int, net.openhft.chronicle.wire.Wire, net.openhft.chronicle.wire.ValueIn, java.lang.Class);
    Code:
       0: aload_0
       1: aload_1
       2: putfield      #1                  // Field this$0:Lnet/openhft/chronicle/wire/WireType;
       5: aload_0
       6: aload         5
       8: putfield      #2                  // Field val$wire:Lnet/openhft/chronicle/wire/Wire;
      11: aload_0
      12: aload         6
      14: putfield      #3                  // Field val$valueIn:Lnet/openhft/chronicle/wire/ValueIn;
      17: aload_0
      18: aload         7
      20: putfield      #4                  // Field val$expectedType:Ljava/lang/Class;
      23: aload_0
      24: lload_2
      25: iload         4
      27: invokespecial #5                  // Method java/util/Spliterators$AbstractSpliterator."<init>":(JI)V
      30: return

  public boolean tryAdvance(java.util.function.Consumer<? super T>);
    Code:
       0: aload_0
       1: getfield      #2                  // Field val$wire:Lnet/openhft/chronicle/wire/Wire;
       4: invokeinterface #6,  1            // InterfaceMethod net/openhft/chronicle/wire/Wire.bytes:()Lnet/openhft/chronicle/bytes/Bytes;
       9: astore_2
      10: aload_0
      11: getfield      #3                  // Field val$valueIn:Lnet/openhft/chronicle/wire/ValueIn;
      14: invokeinterface #7,  1            // InterfaceMethod net/openhft/chronicle/wire/ValueIn.hasNext:()Z
      19: ifeq          145
      22: aload_1
      23: aload_0
      24: getfield      #3                  // Field val$valueIn:Lnet/openhft/chronicle/wire/ValueIn;
      27: aload_0
      28: getfield      #4                  // Field val$expectedType:Ljava/lang/Class;
      31: invokeinterface #8,  2            // InterfaceMethod net/openhft/chronicle/wire/ValueIn.object:(Ljava/lang/Class;)Ljava/lang/Object;
      36: invokeinterface #9,  2            // InterfaceMethod java/util/function/Consumer.accept:(Ljava/lang/Object;)V
      41: aload_0
      42: getfield      #2                  // Field val$wire:Lnet/openhft/chronicle/wire/Wire;
      45: instanceof    #10                 // class net/openhft/chronicle/wire/TextWire
      48: ifeq          143
      51: aload_0
      52: getfield      #2                  // Field val$wire:Lnet/openhft/chronicle/wire/Wire;
      55: invokeinterface #11,  1           // InterfaceMethod net/openhft/chronicle/wire/Wire.consumePadding:()V
      60: aload_2
      61: invokeinterface #12,  1           // InterfaceMethod net/openhft/chronicle/bytes/Bytes.peekUnsignedByte:()I
      66: bipush        45
      68: if_icmpne     143
      71: aload_2
      72: aload_2
      73: invokeinterface #13,  1           // InterfaceMethod net/openhft/chronicle/bytes/Bytes.readPosition:()J
      78: lconst_1
      79: ladd
      80: invokeinterface #14,  3           // InterfaceMethod net/openhft/chronicle/bytes/Bytes.peekUnsignedByte:(J)I
      85: bipush        45
      87: if_icmpne     143
      90: aload_2
      91: aload_2
      92: invokeinterface #13,  1           // InterfaceMethod net/openhft/chronicle/bytes/Bytes.readPosition:()J
      97: ldc2_w        #15                 // long 2l
     100: ladd
     101: invokeinterface #14,  3           // InterfaceMethod net/openhft/chronicle/bytes/Bytes.peekUnsignedByte:(J)I
     106: bipush        45
     108: if_icmpne     143
     111: aload_2
     112: ldc2_w        #17                 // long 3l
     115: invokeinterface #19,  3           // InterfaceMethod net/openhft/chronicle/bytes/Bytes.readSkip:(J)Lnet/openhft/chronicle/bytes/StreamingDataInput;
     120: pop
     121: aload_2
     122: invokeinterface #12,  1           // InterfaceMethod net/openhft/chronicle/bytes/Bytes.peekUnsignedByte:()I
     127: bipush        45
     129: if_icmpne     143
     132: aload_2
     133: lconst_1
     134: invokeinterface #19,  3           // InterfaceMethod net/openhft/chronicle/bytes/Bytes.readSkip:(J)Lnet/openhft/chronicle/bytes/StreamingDataInput;
     139: pop
     140: goto          121
     143: iconst_1
     144: ireturn
     145: aload_2
     146: invokeinterface #20,  1           // InterfaceMethod net/openhft/chronicle/bytes/Bytes.refCount:()I
     151: ifle          160
     154: aload_2
     155: invokeinterface #21,  1           // InterfaceMethod net/openhft/chronicle/bytes/Bytes.releaseLast:()V
     160: iconst_0
     161: ireturn
}
