Compiled from "WireMarshaller.java"
class net.openhft.chronicle.wire.WireMarshaller$CharConversionFieldAccess extends net.openhft.chronicle.wire.WireMarshaller$CharFieldAccess {
  private final net.openhft.chronicle.wire.CharConverter intConverter;

  net.openhft.chronicle.wire.WireMarshaller$CharConversionFieldAccess(java.lang.reflect.Field, net.openhft.chronicle.wire.CharConversion);
    Code:
       0: aload_0
       1: aload_1
       2: invokespecial #1                  // Method net/openhft/chronicle/wire/WireMarshaller$CharFieldAccess."<init>":(Ljava/lang/reflect/Field;)V
       5: aload_0
       6: aload_2
       7: invokeinterface #2,  1            // InterfaceMethod net/openhft/chronicle/wire/CharConversion.value:()Ljava/lang/Class;
      12: invokestatic  #3                  // Method net/openhft/chronicle/core/util/ObjectUtils.newInstance:(Ljava/lang/Class;)Ljava/lang/Object;
      15: checkcast     #4                  // class net/openhft/chronicle/wire/CharConverter
      18: putfield      #5                  // Field intConverter:Lnet/openhft/chronicle/wire/CharConverter;
      21: return

  protected void getValue(java.lang.Object, net.openhft.chronicle.wire.ValueOut, java.lang.Object);
    Code:
       0: invokestatic  #6                  // Method net/openhft/chronicle/wire/WireMarshaller.access$300:()Lnet/openhft/chronicle/core/pool/StringBuilderPool;
       3: invokevirtual #7                  // Method net/openhft/chronicle/core/pool/StringBuilderPool.acquireStringBuilder:()Ljava/lang/StringBuilder;
       6: astore        4
       8: aload_0
       9: getfield      #5                  // Field intConverter:Lnet/openhft/chronicle/wire/CharConverter;
      12: aload         4
      14: aload_0
      15: aload_1
      16: invokevirtual #8                  // Method getChar:(Ljava/lang/Object;)C
      19: invokeinterface #9,  3            // InterfaceMethod net/openhft/chronicle/wire/CharConverter.append:(Ljava/lang/StringBuilder;C)V
      24: aload_2
      25: aload         4
      27: invokeinterface #10,  2           // InterfaceMethod net/openhft/chronicle/wire/ValueOut.rawText:(Ljava/lang/CharSequence;)Lnet/openhft/chronicle/wire/WireOut;
      32: pop
      33: return

  protected char getChar(java.lang.Object);
    Code:
       0: aload_1
       1: aload_0
       2: getfield      #11                 // Field offset:J
       5: invokestatic  #12                 // Method net/openhft/chronicle/core/UnsafeMemory.unsafeGetChar:(Ljava/lang/Object;J)C
       8: ireturn

  protected void setValue(java.lang.Object, net.openhft.chronicle.wire.ValueIn, boolean);
    Code:
       0: invokestatic  #13                 // Method net/openhft/chronicle/wire/WireMarshaller.access$200:()Lnet/openhft/chronicle/core/pool/StringBuilderPool;
       3: invokevirtual #7                  // Method net/openhft/chronicle/core/pool/StringBuilderPool.acquireStringBuilder:()Ljava/lang/StringBuilder;
       6: astore        4
       8: aload_2
       9: aload         4
      11: invokeinterface #14,  2           // InterfaceMethod net/openhft/chronicle/wire/ValueIn.text:(Ljava/lang/StringBuilder;)Lnet/openhft/chronicle/wire/WireIn;
      16: pop
      17: aload_0
      18: getfield      #5                  // Field intConverter:Lnet/openhft/chronicle/wire/CharConverter;
      21: aload         4
      23: invokeinterface #15,  2           // InterfaceMethod net/openhft/chronicle/wire/CharConverter.parse:(Ljava/lang/CharSequence;)C
      28: istore        5
      30: aload_0
      31: aload_1
      32: iload         5
      34: invokevirtual #16                 // Method putChar:(Ljava/lang/Object;C)V
      37: return

  protected void putChar(java.lang.Object, char);
    Code:
       0: aload_1
       1: aload_0
       2: getfield      #11                 // Field offset:J
       5: iload_2
       6: invokestatic  #17                 // Method net/openhft/chronicle/core/UnsafeMemory.unsafePutChar:(Ljava/lang/Object;JC)V
       9: return

  public void getAsBytes(java.lang.Object, net.openhft.chronicle.bytes.Bytes);
    Code:
       0: invokestatic  #6                  // Method net/openhft/chronicle/wire/WireMarshaller.access$300:()Lnet/openhft/chronicle/core/pool/StringBuilderPool;
       3: invokevirtual #7                  // Method net/openhft/chronicle/core/pool/StringBuilderPool.acquireStringBuilder:()Ljava/lang/StringBuilder;
       6: astore_3
       7: aload_2
       8: aload_3
       9: invokeinterface #18,  2           // InterfaceMethod net/openhft/chronicle/bytes/Bytes.readUtf8:(Ljava/lang/StringBuilder;)Z
      14: pop
      15: aload_0
      16: getfield      #5                  // Field intConverter:Lnet/openhft/chronicle/wire/CharConverter;
      19: aload_3
      20: invokeinterface #15,  2           // InterfaceMethod net/openhft/chronicle/wire/CharConverter.parse:(Ljava/lang/CharSequence;)C
      25: istore        4
      27: aload_2
      28: iload         4
      30: invokeinterface #19,  2           // InterfaceMethod net/openhft/chronicle/bytes/Bytes.writeInt:(I)Lnet/openhft/chronicle/bytes/StreamingDataOutput;
      35: pop
      36: return

  protected boolean sameValue(java.lang.Object, java.lang.Object);
    Code:
       0: aload_0
       1: aload_1
       2: invokevirtual #8                  // Method getChar:(Ljava/lang/Object;)C
       5: aload_0
       6: aload_2
       7: invokevirtual #8                  // Method getChar:(Ljava/lang/Object;)C
      10: if_icmpne     17
      13: iconst_1
      14: goto          18
      17: iconst_0
      18: ireturn

  protected void copy(java.lang.Object, java.lang.Object);
    Code:
       0: aload_0
       1: aload_2
       2: aload_0
       3: aload_1
       4: invokevirtual #8                  // Method getChar:(Ljava/lang/Object;)C
       7: invokevirtual #16                 // Method putChar:(Ljava/lang/Object;C)V
      10: return
}
