Compiled from "UseExistingMongoDbRule.java"
public class org.sdase.commons.server.mongo.testing.UseExistingMongoDbRule extends org.junit.rules.ExternalResource implements org.sdase.commons.server.mongo.testing.MongoDbRule {
  private org.sdase.commons.server.mongo.testing.UseExistingMongoDb mongoDb;

  public org.sdase.commons.server.mongo.testing.UseExistingMongoDbRule(java.lang.String);
    Code:
       0: aload_0
       1: invokespecial #1                  // Method org/junit/rules/ExternalResource."<init>":()V
       4: aload_0
       5: new           #2                  // class org/sdase/commons/server/mongo/testing/UseExistingMongoDb
       8: dup
       9: aload_1
      10: invokespecial #3                  // Method org/sdase/commons/server/mongo/testing/UseExistingMongoDb."<init>":(Ljava/lang/String;)V
      13: putfield      #4                  // Field mongoDb:Lorg/sdase/commons/server/mongo/testing/UseExistingMongoDb;
      16: return

  protected void before();
    Code:
       0: aload_0
       1: getfield      #4                  // Field mongoDb:Lorg/sdase/commons/server/mongo/testing/UseExistingMongoDb;
       4: invokevirtual #5                  // Method org/sdase/commons/server/mongo/testing/UseExistingMongoDb.logConnection:()V
       7: return

  public java.lang.String getHosts();
    Code:
       0: aload_0
       1: getfield      #4                  // Field mongoDb:Lorg/sdase/commons/server/mongo/testing/UseExistingMongoDb;
       4: invokevirtual #6                  // Method org/sdase/commons/server/mongo/testing/UseExistingMongoDb.getHosts:()Ljava/lang/String;
       7: areturn

  public java.lang.String getUsername();
    Code:
       0: aload_0
       1: getfield      #4                  // Field mongoDb:Lorg/sdase/commons/server/mongo/testing/UseExistingMongoDb;
       4: invokevirtual #7                  // Method org/sdase/commons/server/mongo/testing/UseExistingMongoDb.getUsername:()Ljava/lang/String;
       7: areturn

  public java.lang.String getPassword();
    Code:
       0: aload_0
       1: getfield      #4                  // Field mongoDb:Lorg/sdase/commons/server/mongo/testing/UseExistingMongoDb;
       4: invokevirtual #8                  // Method org/sdase/commons/server/mongo/testing/UseExistingMongoDb.getPassword:()Ljava/lang/String;
       7: areturn

  public java.lang.String getDatabase();
    Code:
       0: aload_0
       1: getfield      #4                  // Field mongoDb:Lorg/sdase/commons/server/mongo/testing/UseExistingMongoDb;
       4: invokevirtual #9                  // Method org/sdase/commons/server/mongo/testing/UseExistingMongoDb.getDatabase:()Ljava/lang/String;
       7: areturn

  public java.lang.String getOptions();
    Code:
       0: aload_0
       1: getfield      #4                  // Field mongoDb:Lorg/sdase/commons/server/mongo/testing/UseExistingMongoDb;
       4: invokevirtual #10                 // Method org/sdase/commons/server/mongo/testing/UseExistingMongoDb.getOptions:()Ljava/lang/String;
       7: areturn

  public com.mongodb.MongoClient createClient();
    Code:
       0: aload_0
       1: getfield      #4                  // Field mongoDb:Lorg/sdase/commons/server/mongo/testing/UseExistingMongoDb;
       4: invokevirtual #11                 // Method org/sdase/commons/server/mongo/testing/UseExistingMongoDb.createClient:()Lcom/mongodb/MongoClient;
       7: areturn
}
