Compiled from "ConstraintHelper.java"
class org.hibernate.validator.internal.metadata.core.ConstraintHelper$ValidatorClassMap {
  private final java.util.concurrent.ConcurrentMap<java.lang.Class<? extends java.lang.annotation.Annotation>, java.util.List<? extends java.lang.Class<?>>> constraintValidatorClasses;

  private org.hibernate.validator.internal.metadata.core.ConstraintHelper$ValidatorClassMap();
    Code:
       0: aload_0
       1: invokespecial #5                  // Method java/lang/Object."<init>":()V
       4: aload_0
       5: invokestatic  #6                  // Method org/hibernate/validator/internal/util/CollectionHelper.newConcurrentHashMap:()Ljava/util/concurrent/ConcurrentHashMap;
       8: putfield      #7                  // Field constraintValidatorClasses:Ljava/util/concurrent/ConcurrentMap;
      11: return

  private <A extends java.lang.annotation.Annotation> java.util.List<java.lang.Class<? extends javax.validation.ConstraintValidator<A, ?>>> get(java.lang.Class<A>);
    Code:
       0: aload_0
       1: getfield      #7                  // Field constraintValidatorClasses:Ljava/util/concurrent/ConcurrentMap;
       4: aload_1
       5: invokeinterface #8,  2            // InterfaceMethod java/util/concurrent/ConcurrentMap.get:(Ljava/lang/Object;)Ljava/lang/Object;
      10: checkcast     #9                  // class java/util/List
      13: areturn

  private <A extends java.lang.annotation.Annotation> void put(java.lang.Class<A>, java.util.List<java.lang.Class<? extends javax.validation.ConstraintValidator<A, ?>>>);
    Code:
       0: aload_0
       1: getfield      #7                  // Field constraintValidatorClasses:Ljava/util/concurrent/ConcurrentMap;
       4: aload_1
       5: aload_2
       6: invokeinterface #10,  3           // InterfaceMethod java/util/concurrent/ConcurrentMap.put:(Ljava/lang/Object;Ljava/lang/Object;)Ljava/lang/Object;
      11: pop
      12: return

  private <A extends java.lang.annotation.Annotation> java.util.List<java.lang.Class<? extends javax.validation.ConstraintValidator<A, ?>>> putIfAbsent(java.lang.Class<A>, java.util.List<java.lang.Class<? extends javax.validation.ConstraintValidator<A, ?>>>);
    Code:
       0: aload_0
       1: getfield      #7                  // Field constraintValidatorClasses:Ljava/util/concurrent/ConcurrentMap;
       4: aload_1
       5: aload_2
       6: invokeinterface #11,  3           // InterfaceMethod java/util/concurrent/ConcurrentMap.putIfAbsent:(Ljava/lang/Object;Ljava/lang/Object;)Ljava/lang/Object;
      11: checkcast     #9                  // class java/util/List
      14: areturn

  org.hibernate.validator.internal.metadata.core.ConstraintHelper$ValidatorClassMap(org.hibernate.validator.internal.metadata.core.ConstraintHelper$1);
    Code:
       0: aload_0
       1: invokespecial #4                  // Method "<init>":()V
       4: return

  static java.util.List access$100(org.hibernate.validator.internal.metadata.core.ConstraintHelper$ValidatorClassMap, java.lang.Class);
    Code:
       0: aload_0
       1: aload_1
       2: invokespecial #3                  // Method get:(Ljava/lang/Class;)Ljava/util/List;
       5: areturn

  static java.util.List access$200(org.hibernate.validator.internal.metadata.core.ConstraintHelper$ValidatorClassMap, java.lang.Class, java.util.List);
    Code:
       0: aload_0
       1: aload_1
       2: aload_2
       3: invokespecial #2                  // Method putIfAbsent:(Ljava/lang/Class;Ljava/util/List;)Ljava/util/List;
       6: areturn

  static void access$300(org.hibernate.validator.internal.metadata.core.ConstraintHelper$ValidatorClassMap, java.lang.Class, java.util.List);
    Code:
       0: aload_0
       1: aload_1
       2: aload_2
       3: invokespecial #1                  // Method put:(Ljava/lang/Class;Ljava/util/List;)V
       6: return
}
