Compiled from "NativeIO.java"
public class org.apache.hadoop.io.nativeio.NativeIO$Windows {
  public static final long GENERIC_READ;

  public static final long GENERIC_WRITE;

  public static final long FILE_SHARE_READ;

  public static final long FILE_SHARE_WRITE;

  public static final long FILE_SHARE_DELETE;

  public static final long CREATE_NEW;

  public static final long CREATE_ALWAYS;

  public static final long OPEN_EXISTING;

  public static final long OPEN_ALWAYS;

  public static final long TRUNCATE_EXISTING;

  public static final long FILE_BEGIN;

  public static final long FILE_CURRENT;

  public static final long FILE_END;

  public static final long FILE_ATTRIBUTE_NORMAL;

  public org.apache.hadoop.io.nativeio.NativeIO$Windows();
    Code:
       0: aload_0
       1: invokespecial #2                  // Method java/lang/Object."<init>":()V
       4: return

  public static void createDirectoryWithMode(java.io.File, int) throws java.io.IOException;
    Code:
       0: aload_0
       1: invokevirtual #3                  // Method java/io/File.getAbsolutePath:()Ljava/lang/String;
       4: iload_1
       5: invokestatic  #4                  // Method createDirectoryWithMode0:(Ljava/lang/String;I)V
       8: return

  private static native void createDirectoryWithMode0(java.lang.String, int) throws org.apache.hadoop.io.nativeio.NativeIOException;

  public static native java.io.FileDescriptor createFile(java.lang.String, long, long, long) throws java.io.IOException;

  public static java.io.FileOutputStream createFileOutputStreamWithMode(java.io.File, boolean, int) throws java.io.IOException;
    Code:
       0: ldc2_w        #6                  // long 1073741824l
       3: lstore_3
       4: ldc2_w        #8                  // long 3l
       7: lstore        5
       9: iload_1
      10: ifeq          19
      13: ldc2_w        #10                 // long 4l
      16: goto          22
      19: ldc2_w        #12                 // long 2l
      22: lstore        7
      24: new           #14                 // class java/io/FileOutputStream
      27: dup
      28: aload_0
      29: invokevirtual #3                  // Method java/io/File.getAbsolutePath:()Ljava/lang/String;
      32: lload_3
      33: lload         5
      35: lload         7
      37: iload_2
      38: invokestatic  #15                 // Method createFileWithMode0:(Ljava/lang/String;JJJI)Ljava/io/FileDescriptor;
      41: invokespecial #16                 // Method java/io/FileOutputStream."<init>":(Ljava/io/FileDescriptor;)V
      44: areturn

  private static native java.io.FileDescriptor createFileWithMode0(java.lang.String, long, long, long, int) throws org.apache.hadoop.io.nativeio.NativeIOException;

  public static native long setFilePointer(java.io.FileDescriptor, long, long) throws java.io.IOException;

  private static native java.lang.String getOwner(java.io.FileDescriptor) throws java.io.IOException;

  private static native boolean access0(java.lang.String, int);

  public static boolean access(java.lang.String, org.apache.hadoop.io.nativeio.NativeIO$Windows$AccessRight) throws java.io.IOException;
    Code:
       0: aload_0
       1: aload_1
       2: invokevirtual #17                 // Method org/apache/hadoop/io/nativeio/NativeIO$Windows$AccessRight.accessRight:()I
       5: invokestatic  #18                 // Method access0:(Ljava/lang/String;I)Z
       8: ireturn

  public static native void extendWorkingSetSize(long) throws java.io.IOException;

  static java.lang.String access$1600(java.io.FileDescriptor) throws java.io.IOException;
    Code:
       0: aload_0
       1: invokestatic  #1                  // Method getOwner:(Ljava/io/FileDescriptor;)Ljava/lang/String;
       4: areturn

  static {};
    Code:
       0: invokestatic  #19                 // Method org/apache/hadoop/util/NativeCodeLoader.isNativeCodeLoaded:()Z
       3: ifeq          29
       6: invokestatic  #20                 // Method org/apache/hadoop/io/nativeio/NativeIO.access$900:()V
       9: iconst_1
      10: invokestatic  #21                 // Method org/apache/hadoop/io/nativeio/NativeIO.access$1502:(Z)Z
      13: pop
      14: goto          29
      17: astore_0
      18: getstatic     #23                 // Field org/apache/hadoop/util/PerformanceAdvisory.LOG:Lorg/slf4j/Logger;
      21: ldc           #24                 // String Unable to initialize NativeIO libraries
      23: aload_0
      24: invokeinterface #25,  3           // InterfaceMethod org/slf4j/Logger.debug:(Ljava/lang/String;Ljava/lang/Throwable;)V
      29: return
    Exception table:
       from    to  target type
           6    14    17   Class java/lang/Throwable
}
