Compiled from "LatchedWriter.java"
public class com.github.mustachejava.util.LatchedWriter extends java.io.Writer {
  private final java.util.concurrent.CountDownLatch latch;

  private final java.lang.StringBuilder buffer;

  private final java.io.Writer writer;

  private volatile java.lang.Throwable e;

  public com.github.mustachejava.util.LatchedWriter(java.io.Writer);
    Code:
       0: aload_0
       1: invokespecial #1                  // Method java/io/Writer."<init>":()V
       4: aload_0
       5: new           #2                  // class java/util/concurrent/CountDownLatch
       8: dup
       9: iconst_1
      10: invokespecial #3                  // Method java/util/concurrent/CountDownLatch."<init>":(I)V
      13: putfield      #4                  // Field latch:Ljava/util/concurrent/CountDownLatch;
      16: aload_0
      17: new           #5                  // class java/lang/StringBuilder
      20: dup
      21: invokespecial #6                  // Method java/lang/StringBuilder."<init>":()V
      24: putfield      #7                  // Field buffer:Ljava/lang/StringBuilder;
      27: aload_0
      28: aload_1
      29: putfield      #8                  // Field writer:Ljava/io/Writer;
      32: return

  public synchronized void done() throws java.io.IOException;
    Code:
       0: aload_0
       1: getfield      #8                  // Field writer:Ljava/io/Writer;
       4: aload_0
       5: getfield      #7                  // Field buffer:Ljava/lang/StringBuilder;
       8: invokevirtual #9                  // Method java/io/Writer.append:(Ljava/lang/CharSequence;)Ljava/io/Writer;
      11: pop
      12: aload_0
      13: getfield      #4                  // Field latch:Ljava/util/concurrent/CountDownLatch;
      16: invokevirtual #10                 // Method java/util/concurrent/CountDownLatch.countDown:()V
      19: return

  public void failed(java.lang.Throwable);
    Code:
       0: aload_0
       1: aload_1
       2: putfield      #11                 // Field e:Ljava/lang/Throwable;
       5: aload_0
       6: getfield      #4                  // Field latch:Ljava/util/concurrent/CountDownLatch;
       9: invokevirtual #10                 // Method java/util/concurrent/CountDownLatch.countDown:()V
      12: return

  public synchronized void write(char[], int, int) throws java.io.IOException;
    Code:
       0: aload_0
       1: invokespecial #12                 // Method checkException:()V
       4: aload_0
       5: getfield      #4                  // Field latch:Ljava/util/concurrent/CountDownLatch;
       8: invokevirtual #13                 // Method java/util/concurrent/CountDownLatch.getCount:()J
      11: lconst_0
      12: lcmp
      13: ifne          29
      16: aload_0
      17: getfield      #8                  // Field writer:Ljava/io/Writer;
      20: aload_1
      21: iload_2
      22: iload_3
      23: invokevirtual #14                 // Method java/io/Writer.write:([CII)V
      26: goto          40
      29: aload_0
      30: getfield      #7                  // Field buffer:Ljava/lang/StringBuilder;
      33: aload_1
      34: iload_2
      35: iload_3
      36: invokevirtual #15                 // Method java/lang/StringBuilder.append:([CII)Ljava/lang/StringBuilder;
      39: pop
      40: return

  private void checkException() throws java.io.IOException;
    Code:
       0: aload_0
       1: getfield      #11                 // Field e:Ljava/lang/Throwable;
       4: ifnull        37
       7: aload_0
       8: getfield      #11                 // Field e:Ljava/lang/Throwable;
      11: instanceof    #16                 // class java/io/IOException
      14: ifeq          25
      17: aload_0
      18: getfield      #11                 // Field e:Ljava/lang/Throwable;
      21: checkcast     #16                 // class java/io/IOException
      24: athrow
      25: new           #16                 // class java/io/IOException
      28: dup
      29: aload_0
      30: getfield      #11                 // Field e:Ljava/lang/Throwable;
      33: invokespecial #17                 // Method java/io/IOException."<init>":(Ljava/lang/Throwable;)V
      36: athrow
      37: return

  public void flush() throws java.io.IOException;
    Code:
       0: aload_0
       1: invokespecial #12                 // Method checkException:()V
       4: aload_0
       5: getfield      #4                  // Field latch:Ljava/util/concurrent/CountDownLatch;
       8: invokevirtual #13                 // Method java/util/concurrent/CountDownLatch.getCount:()J
      11: lconst_0
      12: lcmp
      13: ifne          37
      16: aload_0
      17: dup
      18: astore_1
      19: monitorenter
      20: aload_0
      21: getfield      #8                  // Field writer:Ljava/io/Writer;
      24: invokevirtual #18                 // Method java/io/Writer.flush:()V
      27: aload_1
      28: monitorexit
      29: goto          37
      32: astore_2
      33: aload_1
      34: monitorexit
      35: aload_2
      36: athrow
      37: return
    Exception table:
       from    to  target type
          20    29    32   any
          32    35    32   any

  public void close() throws java.io.IOException;
    Code:
       0: aload_0
       1: invokespecial #12                 // Method checkException:()V
       4: aload_0
       5: invokevirtual #19                 // Method await:()V
       8: aload_0
       9: invokevirtual #20                 // Method flush:()V
      12: aload_0
      13: getfield      #8                  // Field writer:Ljava/io/Writer;
      16: invokevirtual #21                 // Method java/io/Writer.close:()V
      19: return

  public void await();
    Code:
       0: aload_0
       1: getfield      #4                  // Field latch:Ljava/util/concurrent/CountDownLatch;
       4: invokevirtual #22                 // Method java/util/concurrent/CountDownLatch.await:()V
       7: goto          22
      10: astore_1
      11: new           #24                 // class com/github/mustachejava/MustacheException
      14: dup
      15: ldc           #25                 // String Interrupted while waiting for completion
      17: aload_1
      18: invokespecial #26                 // Method com/github/mustachejava/MustacheException."<init>":(Ljava/lang/String;Ljava/lang/Throwable;)V
      21: athrow
      22: return
    Exception table:
       from    to  target type
           0     7    10   Class java/lang/InterruptedException
}
