Compiled from "UByteArray.kt"
public final class kotlin.UByteArray implements java.util.Collection<kotlin.UByte>, kotlin.jvm.internal.markers.KMappedMarker {
  private final byte[] storage;

  public int getSize();
    Code:
       0: aload_0
       1: getfield      #22                 // Field storage:[B
       4: invokestatic  #26                 // Method "getSize-impl":([B)I
       7: ireturn

  public final int size();
    Code:
       0: aload_0
       1: invokevirtual #18                 // Method getSize:()I
       4: ireturn

  public kotlin.collections.UByteIterator iterator();
    Code:
       0: aload_0
       1: getfield      #22                 // Field storage:[B
       4: invokestatic  #38                 // Method "iterator-impl":([B)Lkotlin/collections/UByteIterator;
       7: areturn

  public java.util.Iterator iterator();
    Code:
       0: aload_0
       1: invokevirtual #31                 // Method iterator:()Lkotlin/collections/UByteIterator;
       4: checkcast     #33                 // class java/util/Iterator
       7: areturn

  public boolean contains-7apg3OU(byte);
    Code:
       0: aload_0
       1: getfield      #22                 // Field storage:[B
       4: iload_1
       5: invokestatic  #53                 // Method "contains-7apg3OU":([BB)Z
       8: ireturn

  public final boolean contains(java.lang.Object);
    Code:
       0: aload_1
       1: instanceof    #44                 // class kotlin/UByte
       4: ifeq          10
       7: goto          12
      10: iconst_0
      11: ireturn
      12: aload_0
      13: aload_1
      14: checkcast     #44                 // class kotlin/UByte
      17: invokevirtual #48                 // Method kotlin/UByte."unbox-impl":()B
      20: invokevirtual #50                 // Method "contains-7apg3OU":(B)Z
      23: ireturn

  public boolean containsAll(java.util.Collection<? extends java.lang.Object>);
    Code:
       0: aload_0
       1: getfield      #22                 // Field storage:[B
       4: aload_1
       5: invokestatic  #60                 // Method "containsAll-impl":([BLjava/util/Collection;)Z
       8: ireturn

  public boolean isEmpty();
    Code:
       0: aload_0
       1: getfield      #22                 // Field storage:[B
       4: invokestatic  #66                 // Method "isEmpty-impl":([B)Z
       7: ireturn

  public static void getStorage$annotations();
    Code:
       0: return

  private kotlin.UByteArray(byte[]);
    Code:
       0: aload_1
       1: ldc           #72                 // String storage
       3: invokestatic  #78                 // Method kotlin/jvm/internal/Intrinsics.checkNotNullParameter:(Ljava/lang/Object;Ljava/lang/String;)V
       6: aload_0
       7: invokespecial #80                 // Method java/lang/Object."<init>":()V
      10: aload_0
      11: aload_1
      12: putfield      #22                 // Field storage:[B
      15: return

  public static final byte get-w2LRezQ(byte[], int);
    Code:
       0: aload_0
       1: iload_1
       2: baload
       3: istore_2
       4: iconst_0
       5: istore_3
       6: iload_2
       7: invokestatic  #88                 // Method kotlin/UByte."constructor-impl":(B)B
      10: ireturn

  public static final void set-VurrAj0(byte[], int, byte);
    Code:
       0: aload_0
       1: iload_1
       2: iload_2
       3: istore_3
       4: iconst_0
       5: istore        4
       7: iload_3
       8: bastore
       9: return

  public static int getSize-impl(byte[]);
    Code:
       0: aload_0
       1: arraylength
       2: ireturn

  public static kotlin.collections.UByteIterator iterator-impl(byte[]);
    Code:
       0: new           #97                 // class kotlin/UByteArray$Iterator
       3: dup
       4: aload_0
       5: invokespecial #99                 // Method kotlin/UByteArray$Iterator."<init>":([B)V
       8: checkcast     #101                // class kotlin/collections/UByteIterator
      11: areturn

  public static boolean contains-7apg3OU(byte[], byte);
    Code:
       0: nop
       1: aload_0
       2: iload_1
       3: istore_2
       4: iconst_0
       5: istore_3
       6: iload_2
       7: invokestatic  #105                // Method kotlin/collections/ArraysKt.contains:([BB)Z
      10: ireturn

  public static boolean containsAll-impl(byte[], java.util.Collection<kotlin.UByte>);
    Code:
       0: aload_1
       1: ldc           #109                // String elements
       3: invokestatic  #78                 // Method kotlin/jvm/internal/Intrinsics.checkNotNullParameter:(Ljava/lang/Object;Ljava/lang/String;)V
       6: aload_1
       7: checkcast     #111                // class java/lang/Iterable
      10: astore_2
      11: iconst_0
      12: istore_3
      13: aload_2
      14: checkcast     #7                  // class java/util/Collection
      17: invokeinterface #113,  1          // InterfaceMethod java/util/Collection.isEmpty:()Z
      22: ifeq          29
      25: iconst_1
      26: goto          106
      29: aload_2
      30: invokeinterface #115,  1          // InterfaceMethod java/lang/Iterable.iterator:()Ljava/util/Iterator;
      35: astore        4
      37: aload         4
      39: invokeinterface #118,  1          // InterfaceMethod java/util/Iterator.hasNext:()Z
      44: ifeq          105
      47: aload         4
      49: invokeinterface #122,  1          // InterfaceMethod java/util/Iterator.next:()Ljava/lang/Object;
      54: astore        5
      56: aload         5
      58: astore        6
      60: iconst_0
      61: istore        7
      63: aload         6
      65: instanceof    #44                 // class kotlin/UByte
      68: ifeq          97
      71: aload_0
      72: aload         6
      74: checkcast     #44                 // class kotlin/UByte
      77: invokevirtual #48                 // Method kotlin/UByte."unbox-impl":()B
      80: istore        8
      82: iconst_0
      83: istore        9
      85: iload         8
      87: invokestatic  #105                // Method kotlin/collections/ArraysKt.contains:([BB)Z
      90: ifeq          97
      93: iconst_1
      94: goto          98
      97: iconst_0
      98: ifne          37
     101: iconst_0
     102: goto          106
     105: iconst_1
     106: ireturn

  public static boolean isEmpty-impl(byte[]);
    Code:
       0: aload_0
       1: arraylength
       2: ifne          9
       5: iconst_1
       6: goto          10
       9: iconst_0
      10: ireturn

  public static byte[] constructor-impl(byte[]);
    Code:
       0: aload_0
       1: ldc           #72                 // String storage
       3: invokestatic  #78                 // Method kotlin/jvm/internal/Intrinsics.checkNotNullParameter:(Ljava/lang/Object;Ljava/lang/String;)V
       6: aload_0
       7: areturn

  public static byte[] constructor-impl(int);
    Code:
       0: iload_0
       1: newarray       byte
       3: invokestatic  #135                // Method "constructor-impl":([B)[B
       6: areturn

  public static final kotlin.UByteArray box-impl(byte[]);
    Code:
       0: aload_0
       1: ldc           #139                // String v
       3: invokestatic  #78                 // Method kotlin/jvm/internal/Intrinsics.checkNotNullParameter:(Ljava/lang/Object;Ljava/lang/String;)V
       6: new           #2                  // class kotlin/UByteArray
       9: dup
      10: aload_0
      11: invokespecial #140                // Method "<init>":([B)V
      14: areturn

  public static java.lang.String toString-impl(byte[]);
    Code:
       0: new           #144                // class java/lang/StringBuilder
       3: dup
       4: invokespecial #145                // Method java/lang/StringBuilder."<init>":()V
       7: ldc           #147                // String UByteArray(storage=
       9: invokevirtual #151                // Method java/lang/StringBuilder.append:(Ljava/lang/String;)Ljava/lang/StringBuilder;
      12: aload_0
      13: invokestatic  #156                // Method java/util/Arrays.toString:([B)Ljava/lang/String;
      16: invokevirtual #151                // Method java/lang/StringBuilder.append:(Ljava/lang/String;)Ljava/lang/StringBuilder;
      19: ldc           #158                // String )
      21: invokevirtual #151                // Method java/lang/StringBuilder.append:(Ljava/lang/String;)Ljava/lang/StringBuilder;
      24: invokevirtual #161                // Method java/lang/StringBuilder.toString:()Ljava/lang/String;
      27: areturn

  public static int hashCode-impl(byte[]);
    Code:
       0: aload_0
       1: dup
       2: ifnull        11
       5: invokestatic  #165                // Method java/util/Arrays.hashCode:([B)I
       8: goto          13
      11: pop
      12: iconst_0
      13: ireturn

  public static boolean equals-impl(byte[], java.lang.Object);
    Code:
       0: aload_1
       1: instanceof    #2                  // class kotlin/UByteArray
       4: ifeq          25
       7: aload_1
       8: checkcast     #2                  // class kotlin/UByteArray
      11: invokevirtual #170                // Method "unbox-impl":()[B
      14: astore_2
      15: aload_0
      16: aload_2
      17: invokestatic  #174                // Method kotlin/jvm/internal/Intrinsics.areEqual:(Ljava/lang/Object;Ljava/lang/Object;)Z
      20: ifeq          25
      23: iconst_1
      24: ireturn
      25: iconst_0
      26: ireturn

  public static final boolean equals-impl0(byte[], byte[]);
    Code:
       0: aload_0
       1: aload_1
       2: invokestatic  #174                // Method kotlin/jvm/internal/Intrinsics.areEqual:(Ljava/lang/Object;Ljava/lang/Object;)Z
       5: ifeq          12
       8: iconst_1
       9: goto          13
      12: iconst_0
      13: ireturn

  public final byte[] unbox-impl();
    Code:
       0: aload_0
       1: getfield      #22                 // Field storage:[B
       4: areturn

  public java.lang.String toString();
    Code:
       0: aload_0
       1: getfield      #22                 // Field storage:[B
       4: invokestatic  #180                // Method "toString-impl":([B)Ljava/lang/String;
       7: areturn

  public int hashCode();
    Code:
       0: aload_0
       1: getfield      #22                 // Field storage:[B
       4: invokestatic  #182                // Method "hashCode-impl":([B)I
       7: ireturn

  public boolean equals(java.lang.Object);
    Code:
       0: aload_0
       1: getfield      #22                 // Field storage:[B
       4: aload_1
       5: invokestatic  #185                // Method "equals-impl":([BLjava/lang/Object;)Z
       8: ireturn

  public boolean add-7apg3OU(byte);
    Code:
       0: new           #188                // class java/lang/UnsupportedOperationException
       3: dup
       4: ldc           #190                // String Operation is not supported for read-only collection
       6: invokespecial #193                // Method java/lang/UnsupportedOperationException."<init>":(Ljava/lang/String;)V
       9: athrow

  public boolean addAll(java.util.Collection<? extends kotlin.UByte>);
    Code:
       0: new           #188                // class java/lang/UnsupportedOperationException
       3: dup
       4: ldc           #190                // String Operation is not supported for read-only collection
       6: invokespecial #193                // Method java/lang/UnsupportedOperationException."<init>":(Ljava/lang/String;)V
       9: athrow

  public void clear();
    Code:
       0: new           #188                // class java/lang/UnsupportedOperationException
       3: dup
       4: ldc           #190                // String Operation is not supported for read-only collection
       6: invokespecial #193                // Method java/lang/UnsupportedOperationException."<init>":(Ljava/lang/String;)V
       9: athrow

  public boolean remove(java.lang.Object);
    Code:
       0: new           #188                // class java/lang/UnsupportedOperationException
       3: dup
       4: ldc           #190                // String Operation is not supported for read-only collection
       6: invokespecial #193                // Method java/lang/UnsupportedOperationException."<init>":(Ljava/lang/String;)V
       9: athrow

  public boolean removeAll(java.util.Collection<? extends java.lang.Object>);
    Code:
       0: new           #188                // class java/lang/UnsupportedOperationException
       3: dup
       4: ldc           #190                // String Operation is not supported for read-only collection
       6: invokespecial #193                // Method java/lang/UnsupportedOperationException."<init>":(Ljava/lang/String;)V
       9: athrow

  public boolean retainAll(java.util.Collection<? extends java.lang.Object>);
    Code:
       0: new           #188                // class java/lang/UnsupportedOperationException
       3: dup
       4: ldc           #190                // String Operation is not supported for read-only collection
       6: invokespecial #193                // Method java/lang/UnsupportedOperationException."<init>":(Ljava/lang/String;)V
       9: athrow

  public boolean add(java.lang.Object);
    Code:
       0: new           #188                // class java/lang/UnsupportedOperationException
       3: dup
       4: ldc           #190                // String Operation is not supported for read-only collection
       6: invokespecial #193                // Method java/lang/UnsupportedOperationException."<init>":(Ljava/lang/String;)V
       9: athrow

  public java.lang.Object[] toArray();
    Code:
       0: aload_0
       1: invokestatic  #207                // Method kotlin/jvm/internal/CollectionToArray.toArray:(Ljava/util/Collection;)[Ljava/lang/Object;
       4: areturn

  public <T> T[] toArray(T[]);
    Code:
       0: aload_0
       1: aload_1
       2: invokestatic  #212                // Method kotlin/jvm/internal/CollectionToArray.toArray:(Ljava/util/Collection;[Ljava/lang/Object;)[Ljava/lang/Object;
       5: areturn
}
