Compiled from "AbstractReceiveListener.java"
public abstract class io.undertow.websockets.core.AbstractReceiveListener implements org.xnio.ChannelListener<io.undertow.websockets.core.WebSocketChannel> {
  public io.undertow.websockets.core.AbstractReceiveListener();
    Code:
       0: aload_0
       1: invokespecial #1                  // Method java/lang/Object."<init>":()V
       4: return

  public void handleEvent(io.undertow.websockets.core.WebSocketChannel);
    Code:
       0: aload_1
       1: invokevirtual #2                  // Method io/undertow/websockets/core/WebSocketChannel.receive:()Lio/undertow/server/protocol/framed/AbstractFramedStreamSourceChannel;
       4: checkcast     #3                  // class io/undertow/websockets/core/StreamSourceFrameChannel
       7: astore_2
       8: aload_2
       9: ifnonnull     13
      12: return
      13: aload_2
      14: invokevirtual #4                  // Method io/undertow/websockets/core/StreamSourceFrameChannel.getType:()Lio/undertow/websockets/core/WebSocketFrameType;
      17: getstatic     #5                  // Field io/undertow/websockets/core/WebSocketFrameType.BINARY:Lio/undertow/websockets/core/WebSocketFrameType;
      20: if_acmpne     32
      23: aload_0
      24: aload_1
      25: aload_2
      26: invokevirtual #6                  // Method onBinary:(Lio/undertow/websockets/core/WebSocketChannel;Lio/undertow/websockets/core/StreamSourceFrameChannel;)V
      29: goto          105
      32: aload_2
      33: invokevirtual #4                  // Method io/undertow/websockets/core/StreamSourceFrameChannel.getType:()Lio/undertow/websockets/core/WebSocketFrameType;
      36: getstatic     #7                  // Field io/undertow/websockets/core/WebSocketFrameType.TEXT:Lio/undertow/websockets/core/WebSocketFrameType;
      39: if_acmpne     51
      42: aload_0
      43: aload_1
      44: aload_2
      45: invokevirtual #8                  // Method onText:(Lio/undertow/websockets/core/WebSocketChannel;Lio/undertow/websockets/core/StreamSourceFrameChannel;)V
      48: goto          105
      51: aload_2
      52: invokevirtual #4                  // Method io/undertow/websockets/core/StreamSourceFrameChannel.getType:()Lio/undertow/websockets/core/WebSocketFrameType;
      55: getstatic     #9                  // Field io/undertow/websockets/core/WebSocketFrameType.PONG:Lio/undertow/websockets/core/WebSocketFrameType;
      58: if_acmpne     70
      61: aload_0
      62: aload_1
      63: aload_2
      64: invokevirtual #10                 // Method onPong:(Lio/undertow/websockets/core/WebSocketChannel;Lio/undertow/websockets/core/StreamSourceFrameChannel;)V
      67: goto          105
      70: aload_2
      71: invokevirtual #4                  // Method io/undertow/websockets/core/StreamSourceFrameChannel.getType:()Lio/undertow/websockets/core/WebSocketFrameType;
      74: getstatic     #11                 // Field io/undertow/websockets/core/WebSocketFrameType.PING:Lio/undertow/websockets/core/WebSocketFrameType;
      77: if_acmpne     89
      80: aload_0
      81: aload_1
      82: aload_2
      83: invokevirtual #12                 // Method onPing:(Lio/undertow/websockets/core/WebSocketChannel;Lio/undertow/websockets/core/StreamSourceFrameChannel;)V
      86: goto          105
      89: aload_2
      90: invokevirtual #4                  // Method io/undertow/websockets/core/StreamSourceFrameChannel.getType:()Lio/undertow/websockets/core/WebSocketFrameType;
      93: getstatic     #13                 // Field io/undertow/websockets/core/WebSocketFrameType.CLOSE:Lio/undertow/websockets/core/WebSocketFrameType;
      96: if_acmpne     105
      99: aload_0
     100: aload_1
     101: aload_2
     102: invokevirtual #14                 // Method onClose:(Lio/undertow/websockets/core/WebSocketChannel;Lio/undertow/websockets/core/StreamSourceFrameChannel;)V
     105: goto          115
     108: astore_2
     109: aload_0
     110: aload_1
     111: aload_2
     112: invokevirtual #16                 // Method onError:(Lio/undertow/websockets/core/WebSocketChannel;Ljava/lang/Throwable;)V
     115: return
    Exception table:
       from    to  target type
           0    12   108   Class java/io/IOException
          13   105   108   Class java/io/IOException

  protected void onPing(io.undertow.websockets.core.WebSocketChannel, io.undertow.websockets.core.StreamSourceFrameChannel) throws java.io.IOException;
    Code:
       0: aload_0
       1: aload_2
       2: invokevirtual #17                 // Method bufferFullMessage:(Lio/undertow/websockets/core/StreamSourceFrameChannel;)V
       5: return

  protected void onClose(io.undertow.websockets.core.WebSocketChannel, io.undertow.websockets.core.StreamSourceFrameChannel) throws java.io.IOException;
    Code:
       0: aload_0
       1: aload_2
       2: invokevirtual #17                 // Method bufferFullMessage:(Lio/undertow/websockets/core/StreamSourceFrameChannel;)V
       5: return

  protected void onPong(io.undertow.websockets.core.WebSocketChannel, io.undertow.websockets.core.StreamSourceFrameChannel) throws java.io.IOException;
    Code:
       0: aload_0
       1: aload_2
       2: invokevirtual #17                 // Method bufferFullMessage:(Lio/undertow/websockets/core/StreamSourceFrameChannel;)V
       5: return

  protected void onText(io.undertow.websockets.core.WebSocketChannel, io.undertow.websockets.core.StreamSourceFrameChannel) throws java.io.IOException;
    Code:
       0: aload_0
       1: aload_2
       2: invokevirtual #17                 // Method bufferFullMessage:(Lio/undertow/websockets/core/StreamSourceFrameChannel;)V
       5: return

  protected void onBinary(io.undertow.websockets.core.WebSocketChannel, io.undertow.websockets.core.StreamSourceFrameChannel) throws java.io.IOException;
    Code:
       0: aload_0
       1: aload_2
       2: invokevirtual #17                 // Method bufferFullMessage:(Lio/undertow/websockets/core/StreamSourceFrameChannel;)V
       5: return

  protected void onError(io.undertow.websockets.core.WebSocketChannel, java.lang.Throwable);
    Code:
       0: aload_1
       1: invokestatic  #18                 // Method org/xnio/IoUtils.safeClose:(Ljava/io/Closeable;)V
       4: return

  protected final void bufferFullMessage(io.undertow.websockets.core.StreamSourceFrameChannel);
    Code:
       0: aload_1
       1: invokevirtual #4                  // Method io/undertow/websockets/core/StreamSourceFrameChannel.getType:()Lio/undertow/websockets/core/WebSocketFrameType;
       4: getstatic     #7                  // Field io/undertow/websockets/core/WebSocketFrameType.TEXT:Lio/undertow/websockets/core/WebSocketFrameType;
       7: if_acmpne     30
      10: aload_0
      11: aload_1
      12: new           #19                 // class io/undertow/websockets/core/BufferedTextMessage
      15: dup
      16: aload_0
      17: invokevirtual #20                 // Method getMaxTextBufferSize:()J
      20: iconst_1
      21: invokespecial #21                 // Method io/undertow/websockets/core/BufferedTextMessage."<init>":(JZ)V
      24: invokespecial #22                 // Method readBufferedText:(Lio/undertow/websockets/core/StreamSourceFrameChannel;Lio/undertow/websockets/core/BufferedTextMessage;)V
      27: goto          151
      30: aload_1
      31: invokevirtual #4                  // Method io/undertow/websockets/core/StreamSourceFrameChannel.getType:()Lio/undertow/websockets/core/WebSocketFrameType;
      34: getstatic     #5                  // Field io/undertow/websockets/core/WebSocketFrameType.BINARY:Lio/undertow/websockets/core/WebSocketFrameType;
      37: if_acmpne     61
      40: aload_0
      41: aload_1
      42: iconst_0
      43: new           #23                 // class io/undertow/websockets/core/BufferedBinaryMessage
      46: dup
      47: aload_0
      48: invokevirtual #24                 // Method getMaxBinaryBufferSize:()J
      51: iconst_1
      52: invokespecial #25                 // Method io/undertow/websockets/core/BufferedBinaryMessage."<init>":(JZ)V
      55: invokespecial #26                 // Method readBufferedBinary:(Lio/undertow/websockets/core/StreamSourceFrameChannel;ZLio/undertow/websockets/core/BufferedBinaryMessage;)V
      58: goto          151
      61: aload_1
      62: invokevirtual #4                  // Method io/undertow/websockets/core/StreamSourceFrameChannel.getType:()Lio/undertow/websockets/core/WebSocketFrameType;
      65: getstatic     #9                  // Field io/undertow/websockets/core/WebSocketFrameType.PONG:Lio/undertow/websockets/core/WebSocketFrameType;
      68: if_acmpne     92
      71: aload_0
      72: aload_1
      73: iconst_1
      74: new           #23                 // class io/undertow/websockets/core/BufferedBinaryMessage
      77: dup
      78: aload_0
      79: invokevirtual #27                 // Method getMaxPongBufferSize:()J
      82: iconst_1
      83: invokespecial #25                 // Method io/undertow/websockets/core/BufferedBinaryMessage."<init>":(JZ)V
      86: invokespecial #26                 // Method readBufferedBinary:(Lio/undertow/websockets/core/StreamSourceFrameChannel;ZLio/undertow/websockets/core/BufferedBinaryMessage;)V
      89: goto          151
      92: aload_1
      93: invokevirtual #4                  // Method io/undertow/websockets/core/StreamSourceFrameChannel.getType:()Lio/undertow/websockets/core/WebSocketFrameType;
      96: getstatic     #11                 // Field io/undertow/websockets/core/WebSocketFrameType.PING:Lio/undertow/websockets/core/WebSocketFrameType;
      99: if_acmpne     123
     102: aload_0
     103: aload_1
     104: iconst_1
     105: new           #23                 // class io/undertow/websockets/core/BufferedBinaryMessage
     108: dup
     109: aload_0
     110: invokevirtual #28                 // Method getMaxPingBufferSize:()J
     113: iconst_1
     114: invokespecial #25                 // Method io/undertow/websockets/core/BufferedBinaryMessage."<init>":(JZ)V
     117: invokespecial #26                 // Method readBufferedBinary:(Lio/undertow/websockets/core/StreamSourceFrameChannel;ZLio/undertow/websockets/core/BufferedBinaryMessage;)V
     120: goto          151
     123: aload_1
     124: invokevirtual #4                  // Method io/undertow/websockets/core/StreamSourceFrameChannel.getType:()Lio/undertow/websockets/core/WebSocketFrameType;
     127: getstatic     #13                 // Field io/undertow/websockets/core/WebSocketFrameType.CLOSE:Lio/undertow/websockets/core/WebSocketFrameType;
     130: if_acmpne     151
     133: aload_0
     134: aload_1
     135: iconst_1
     136: new           #23                 // class io/undertow/websockets/core/BufferedBinaryMessage
     139: dup
     140: aload_0
     141: invokevirtual #29                 // Method getMaxCloseBufferSize:()J
     144: iconst_1
     145: invokespecial #25                 // Method io/undertow/websockets/core/BufferedBinaryMessage."<init>":(JZ)V
     148: invokespecial #26                 // Method readBufferedBinary:(Lio/undertow/websockets/core/StreamSourceFrameChannel;ZLio/undertow/websockets/core/BufferedBinaryMessage;)V
     151: return

  protected long getMaxBinaryBufferSize();
    Code:
       0: ldc2_w        #30                 // long -1l
       3: lreturn

  protected long getMaxPongBufferSize();
    Code:
       0: ldc2_w        #30                 // long -1l
       3: lreturn

  protected long getMaxCloseBufferSize();
    Code:
       0: ldc2_w        #30                 // long -1l
       3: lreturn

  protected long getMaxPingBufferSize();
    Code:
       0: ldc2_w        #30                 // long -1l
       3: lreturn

  protected long getMaxTextBufferSize();
    Code:
       0: ldc2_w        #30                 // long -1l
       3: lreturn

  private void readBufferedBinary(io.undertow.websockets.core.StreamSourceFrameChannel, boolean, io.undertow.websockets.core.BufferedBinaryMessage);
    Code:
       0: aload_3
       1: aload_1
       2: new           #32                 // class io/undertow/websockets/core/AbstractReceiveListener$1
       5: dup
       6: aload_0
       7: aload_1
       8: iload_2
       9: aload_3
      10: invokespecial #33                 // Method io/undertow/websockets/core/AbstractReceiveListener$1."<init>":(Lio/undertow/websockets/core/AbstractReceiveListener;Lio/undertow/websockets/core/StreamSourceFrameChannel;ZLio/undertow/websockets/core/BufferedBinaryMessage;)V
      13: invokevirtual #34                 // Method io/undertow/websockets/core/BufferedBinaryMessage.read:(Lio/undertow/websockets/core/StreamSourceFrameChannel;Lio/undertow/websockets/core/WebSocketCallback;)V
      16: return

  private void readBufferedText(io.undertow.websockets.core.StreamSourceFrameChannel, io.undertow.websockets.core.BufferedTextMessage);
    Code:
       0: aload_2
       1: aload_1
       2: new           #35                 // class io/undertow/websockets/core/AbstractReceiveListener$2
       5: dup
       6: aload_0
       7: aload_2
       8: invokespecial #36                 // Method io/undertow/websockets/core/AbstractReceiveListener$2."<init>":(Lio/undertow/websockets/core/AbstractReceiveListener;Lio/undertow/websockets/core/BufferedTextMessage;)V
      11: invokevirtual #37                 // Method io/undertow/websockets/core/BufferedTextMessage.read:(Lio/undertow/websockets/core/StreamSourceFrameChannel;Lio/undertow/websockets/core/WebSocketCallback;)V
      14: return

  protected void onFullTextMessage(io.undertow.websockets.core.WebSocketChannel, io.undertow.websockets.core.BufferedTextMessage) throws java.io.IOException;
    Code:
       0: return

  protected void onFullBinaryMessage(io.undertow.websockets.core.WebSocketChannel, io.undertow.websockets.core.BufferedBinaryMessage) throws java.io.IOException;
    Code:
       0: aload_2
       1: invokevirtual #38                 // Method io/undertow/websockets/core/BufferedBinaryMessage.getData:()Lorg/xnio/Pooled;
       4: invokeinterface #39,  1           // InterfaceMethod org/xnio/Pooled.free:()V
       9: return

  protected void onFullPingMessage(io.undertow.websockets.core.WebSocketChannel, io.undertow.websockets.core.BufferedBinaryMessage) throws java.io.IOException;
    Code:
       0: aload_2
       1: invokevirtual #38                 // Method io/undertow/websockets/core/BufferedBinaryMessage.getData:()Lorg/xnio/Pooled;
       4: astore_3
       5: aload_3
       6: invokeinterface #40,  1           // InterfaceMethod org/xnio/Pooled.getResource:()Ljava/lang/Object;
      11: checkcast     #41                 // class "[Ljava/nio/ByteBuffer;"
      14: aload_1
      15: new           #42                 // class io/undertow/websockets/core/AbstractReceiveListener$FreeDataCallback
      18: dup
      19: aload_3
      20: invokespecial #43                 // Method io/undertow/websockets/core/AbstractReceiveListener$FreeDataCallback."<init>":(Lorg/xnio/Pooled;)V
      23: invokestatic  #44                 // Method io/undertow/websockets/core/WebSockets.sendPong:([Ljava/nio/ByteBuffer;Lio/undertow/websockets/core/WebSocketChannel;Lio/undertow/websockets/core/WebSocketCallback;)V
      26: return

  protected void onFullPongMessage(io.undertow.websockets.core.WebSocketChannel, io.undertow.websockets.core.BufferedBinaryMessage) throws java.io.IOException;
    Code:
       0: aload_2
       1: invokevirtual #38                 // Method io/undertow/websockets/core/BufferedBinaryMessage.getData:()Lorg/xnio/Pooled;
       4: invokeinterface #39,  1           // InterfaceMethod org/xnio/Pooled.free:()V
       9: return

  protected void onFullCloseMessage(io.undertow.websockets.core.WebSocketChannel, io.undertow.websockets.core.BufferedBinaryMessage) throws java.io.IOException;
    Code:
       0: aload_2
       1: invokevirtual #38                 // Method io/undertow/websockets/core/BufferedBinaryMessage.getData:()Lorg/xnio/Pooled;
       4: astore_3
       5: new           #45                 // class io/undertow/websockets/core/CloseMessage
       8: dup
       9: aload_3
      10: invokeinterface #40,  1           // InterfaceMethod org/xnio/Pooled.getResource:()Ljava/lang/Object;
      15: checkcast     #41                 // class "[Ljava/nio/ByteBuffer;"
      18: invokespecial #46                 // Method io/undertow/websockets/core/CloseMessage."<init>":([Ljava/nio/ByteBuffer;)V
      21: astore        4
      23: aload_0
      24: aload         4
      26: aload_1
      27: invokevirtual #47                 // Method onCloseMessage:(Lio/undertow/websockets/core/CloseMessage;Lio/undertow/websockets/core/WebSocketChannel;)V
      30: aload_1
      31: invokevirtual #48                 // Method io/undertow/websockets/core/WebSocketChannel.isCloseFrameSent:()Z
      34: ifne          44
      37: aload         4
      39: aload_1
      40: aconst_null
      41: invokestatic  #49                 // Method io/undertow/websockets/core/WebSockets.sendClose:(Lio/undertow/websockets/core/CloseMessage;Lio/undertow/websockets/core/WebSocketChannel;Lio/undertow/websockets/core/WebSocketCallback;)V
      44: aload_3
      45: invokeinterface #50,  1           // InterfaceMethod org/xnio/Pooled.close:()V
      50: goto          64
      53: astore        5
      55: aload_3
      56: invokeinterface #50,  1           // InterfaceMethod org/xnio/Pooled.close:()V
      61: aload         5
      63: athrow
      64: return
    Exception table:
       from    to  target type
           5    44    53   any
          53    55    53   any

  protected void onCloseMessage(io.undertow.websockets.core.CloseMessage, io.undertow.websockets.core.WebSocketChannel);
    Code:
       0: return

  public void handleEvent(java.nio.channels.Channel);
    Code:
       0: aload_0
       1: aload_1
       2: checkcast     #51                 // class io/undertow/websockets/core/WebSocketChannel
       5: invokevirtual #52                 // Method handleEvent:(Lio/undertow/websockets/core/WebSocketChannel;)V
       8: return
}
