Compiled from "FutureEventListener.java"
public interface org.apache.bookkeeper.common.concurrent.FutureEventListener<T> extends java.util.function.BiConsumer<T, java.lang.Throwable> {
  public abstract void onSuccess(T);

  public abstract void onFailure(java.lang.Throwable);

  public default void accept(T, java.lang.Throwable);
    Code:
       0: aconst_null
       1: aload_2
       2: if_acmpeq     41
       5: aload_2
       6: instanceof    #1                  // class java/util/concurrent/CompletionException
       9: ifeq          33
      12: aconst_null
      13: aload_2
      14: invokevirtual #2                  // Method java/lang/Throwable.getCause:()Ljava/lang/Throwable;
      17: if_acmpeq     33
      20: aload_0
      21: aload_2
      22: invokevirtual #2                  // Method java/lang/Throwable.getCause:()Ljava/lang/Throwable;
      25: invokeinterface #3,  2            // InterfaceMethod onFailure:(Ljava/lang/Throwable;)V
      30: goto          40
      33: aload_0
      34: aload_2
      35: invokeinterface #3,  2            // InterfaceMethod onFailure:(Ljava/lang/Throwable;)V
      40: return
      41: aload_0
      42: aload_1
      43: invokeinterface #4,  2            // InterfaceMethod onSuccess:(Ljava/lang/Object;)V
      48: return

  public default void accept(java.lang.Object, java.lang.Object);
    Code:
       0: aload_0
       1: aload_1
       2: aload_2
       3: checkcast     #5                  // class java/lang/Throwable
       6: invokeinterface #6,  3            // InterfaceMethod accept:(Ljava/lang/Object;Ljava/lang/Throwable;)V
      11: return
}
