Compiled from "ProducerAck.java"
public class org.apache.activemq.command.ProducerAck extends org.apache.activemq.command.BaseCommand {
  public static final byte DATA_STRUCTURE_TYPE;

  protected org.apache.activemq.command.ProducerId producerId;

  protected int size;

  public org.apache.activemq.command.ProducerAck();
    Code:
       0: aload_0
       1: invokespecial #1                  // Method org/apache/activemq/command/BaseCommand."<init>":()V
       4: return

  public org.apache.activemq.command.ProducerAck(org.apache.activemq.command.ProducerId, int);
    Code:
       0: aload_0
       1: invokespecial #1                  // Method org/apache/activemq/command/BaseCommand."<init>":()V
       4: aload_0
       5: aload_1
       6: putfield      #2                  // Field producerId:Lorg/apache/activemq/command/ProducerId;
       9: aload_0
      10: iload_2
      11: putfield      #3                  // Field size:I
      14: return

  public void copy(org.apache.activemq.command.ProducerAck);
    Code:
       0: aload_0
       1: aload_1
       2: invokespecial #4                  // Method org/apache/activemq/command/BaseCommand.copy:(Lorg/apache/activemq/command/BaseCommand;)V
       5: aload_1
       6: aload_0
       7: getfield      #2                  // Field producerId:Lorg/apache/activemq/command/ProducerId;
      10: putfield      #2                  // Field producerId:Lorg/apache/activemq/command/ProducerId;
      13: aload_1
      14: aload_0
      15: getfield      #3                  // Field size:I
      18: putfield      #3                  // Field size:I
      21: return

  public byte getDataStructureType();
    Code:
       0: bipush        19
       2: ireturn

  public org.apache.activemq.command.Response visit(org.apache.activemq.state.CommandVisitor) throws java.lang.Exception;
    Code:
       0: aload_1
       1: aload_0
       2: invokeinterface #5,  2            // InterfaceMethod org/apache/activemq/state/CommandVisitor.processProducerAck:(Lorg/apache/activemq/command/ProducerAck;)Lorg/apache/activemq/command/Response;
       7: areturn

  public org.apache.activemq.command.ProducerId getProducerId();
    Code:
       0: aload_0
       1: getfield      #2                  // Field producerId:Lorg/apache/activemq/command/ProducerId;
       4: areturn

  public void setProducerId(org.apache.activemq.command.ProducerId);
    Code:
       0: aload_0
       1: aload_1
       2: putfield      #2                  // Field producerId:Lorg/apache/activemq/command/ProducerId;
       5: return

  public int getSize();
    Code:
       0: aload_0
       1: getfield      #3                  // Field size:I
       4: ireturn

  public void setSize(int);
    Code:
       0: aload_0
       1: iload_1
       2: putfield      #3                  // Field size:I
       5: return
}
