Compiled from "NoSuchService.java"
public class org.wildfly.clustering.server.dispatcher.NoSuchService implements java.io.Serializable {
  private static final long serialVersionUID;

  public static final org.wildfly.clustering.server.dispatcher.NoSuchService INSTANCE;

  private org.wildfly.clustering.server.dispatcher.NoSuchService();
    Code:
       0: aload_0
       1: invokespecial #1                  // Method java/lang/Object."<init>":()V
       4: return

  static {};
    Code:
       0: new           #2                  // class org/wildfly/clustering/server/dispatcher/NoSuchService
       3: dup
       4: invokespecial #3                  // Method "<init>":()V
       7: putstatic     #4                  // Field INSTANCE:Lorg/wildfly/clustering/server/dispatcher/NoSuchService;
      10: return
}
