Compiled from "SimplifierMarkupHandler.java"
public final class org.attoparser.simple.SimplifierMarkupHandler extends org.attoparser.AbstractMarkupHandler {
  private final org.attoparser.simple.ISimpleMarkupHandler handler;

  private java.lang.String currentElementName;

  private java.util.Map<java.lang.String, java.lang.String> currentElementAttributes;

  private int currentElementLine;

  private int currentElementCol;

  public org.attoparser.simple.SimplifierMarkupHandler(org.attoparser.simple.ISimpleMarkupHandler);
    Code:
       0: aload_0
       1: invokespecial #1                  // Method org/attoparser/AbstractMarkupHandler."<init>":()V
       4: aload_1
       5: ifnonnull     18
       8: new           #2                  // class java/lang/IllegalArgumentException
      11: dup
      12: ldc           #3                  // String Delegate handler cannot be null
      14: invokespecial #4                  // Method java/lang/IllegalArgumentException."<init>":(Ljava/lang/String;)V
      17: athrow
      18: aload_0
      19: aload_1
      20: putfield      #5                  // Field handler:Lorg/attoparser/simple/ISimpleMarkupHandler;
      23: return

  public void handleDocumentStart(long, int, int) throws org.attoparser.ParseException;
    Code:
       0: aload_0
       1: getfield      #5                  // Field handler:Lorg/attoparser/simple/ISimpleMarkupHandler;
       4: lload_1
       5: iload_3
       6: iload         4
       8: invokeinterface #6,  5            // InterfaceMethod org/attoparser/simple/ISimpleMarkupHandler.handleDocumentStart:(JII)V
      13: return

  public void handleDocumentEnd(long, long, int, int) throws org.attoparser.ParseException;
    Code:
       0: aload_0
       1: getfield      #5                  // Field handler:Lorg/attoparser/simple/ISimpleMarkupHandler;
       4: lload_1
       5: lload_3
       6: iload         5
       8: iload         6
      10: invokeinterface #7,  7            // InterfaceMethod org/attoparser/simple/ISimpleMarkupHandler.handleDocumentEnd:(JJII)V
      15: return

  public void handleXmlDeclaration(char[], int, int, int, int, int, int, int, int, int, int, int, int, int, int, int, int, int, int, int, int) throws org.attoparser.ParseException;
    Code:
       0: new           #8                  // class java/lang/String
       3: dup
       4: aload_1
       5: iload         6
       7: iload         7
       9: invokespecial #9                  // Method java/lang/String."<init>":([CII)V
      12: astore        22
      14: iload         10
      16: ifle          34
      19: new           #8                  // class java/lang/String
      22: dup
      23: aload_1
      24: iload         10
      26: iload         11
      28: invokespecial #9                  // Method java/lang/String."<init>":([CII)V
      31: goto          35
      34: aconst_null
      35: astore        23
      37: iload         14
      39: ifle          57
      42: new           #8                  // class java/lang/String
      45: dup
      46: aload_1
      47: iload         14
      49: iload         15
      51: invokespecial #9                  // Method java/lang/String."<init>":([CII)V
      54: goto          58
      57: aconst_null
      58: astore        24
      60: aload_0
      61: getfield      #5                  // Field handler:Lorg/attoparser/simple/ISimpleMarkupHandler;
      64: aload         22
      66: aload         23
      68: aload         24
      70: iload         20
      72: iload         21
      74: invokeinterface #10,  6           // InterfaceMethod org/attoparser/simple/ISimpleMarkupHandler.handleXmlDeclaration:(Ljava/lang/String;Ljava/lang/String;Ljava/lang/String;II)V
      79: return

  public void handleDocType(char[], int, int, int, int, int, int, int, int, int, int, int, int, int, int, int, int, int, int, int, int, int, int, int, int, int, int, int, int) throws org.attoparser.ParseException;
    Code:
       0: aload_0
       1: getfield      #5                  // Field handler:Lorg/attoparser/simple/ISimpleMarkupHandler;
       4: new           #8                  // class java/lang/String
       7: dup
       8: aload_1
       9: iload         6
      11: iload         7
      13: invokespecial #9                  // Method java/lang/String."<init>":([CII)V
      16: iload         14
      18: ifgt          25
      21: aconst_null
      22: goto          37
      25: new           #8                  // class java/lang/String
      28: dup
      29: aload_1
      30: iload         14
      32: iload         15
      34: invokespecial #9                  // Method java/lang/String."<init>":([CII)V
      37: iload         18
      39: ifgt          46
      42: aconst_null
      43: goto          58
      46: new           #8                  // class java/lang/String
      49: dup
      50: aload_1
      51: iload         18
      53: iload         19
      55: invokespecial #9                  // Method java/lang/String."<init>":([CII)V
      58: iload         22
      60: ifgt          67
      63: aconst_null
      64: goto          79
      67: new           #8                  // class java/lang/String
      70: dup
      71: aload_1
      72: iload         22
      74: iload         23
      76: invokespecial #9                  // Method java/lang/String."<init>":([CII)V
      79: iload         28
      81: iload         29
      83: invokeinterface #11,  7           // InterfaceMethod org/attoparser/simple/ISimpleMarkupHandler.handleDocType:(Ljava/lang/String;Ljava/lang/String;Ljava/lang/String;Ljava/lang/String;II)V
      88: return

  public void handleCDATASection(char[], int, int, int, int, int, int) throws org.attoparser.ParseException;
    Code:
       0: aload_0
       1: getfield      #5                  // Field handler:Lorg/attoparser/simple/ISimpleMarkupHandler;
       4: aload_1
       5: iload_2
       6: iload_3
       7: iload         6
       9: iload         7
      11: invokeinterface #12,  6           // InterfaceMethod org/attoparser/simple/ISimpleMarkupHandler.handleCDATASection:([CIIII)V
      16: return

  public void handleComment(char[], int, int, int, int, int, int) throws org.attoparser.ParseException;
    Code:
       0: aload_0
       1: getfield      #5                  // Field handler:Lorg/attoparser/simple/ISimpleMarkupHandler;
       4: aload_1
       5: iload_2
       6: iload_3
       7: iload         6
       9: iload         7
      11: invokeinterface #13,  6           // InterfaceMethod org/attoparser/simple/ISimpleMarkupHandler.handleComment:([CIIII)V
      16: return

  public void handleText(char[], int, int, int, int) throws org.attoparser.ParseException;
    Code:
       0: aload_0
       1: getfield      #5                  // Field handler:Lorg/attoparser/simple/ISimpleMarkupHandler;
       4: aload_1
       5: iload_2
       6: iload_3
       7: iload         4
       9: iload         5
      11: invokeinterface #14,  6           // InterfaceMethod org/attoparser/simple/ISimpleMarkupHandler.handleText:([CIIII)V
      16: return

  public void handleStandaloneElementStart(char[], int, int, boolean, int, int) throws org.attoparser.ParseException;
    Code:
       0: aload_0
       1: aload_1
       2: iload_2
       3: iload_3
       4: invokestatic  #15                 // Method org/attoparser/simple/StructureTextsRepository.getStructureName:([CII)Ljava/lang/String;
       7: putfield      #16                 // Field currentElementName:Ljava/lang/String;
      10: aload_0
      11: aconst_null
      12: putfield      #17                 // Field currentElementAttributes:Ljava/util/Map;
      15: aload_0
      16: iload         5
      18: putfield      #18                 // Field currentElementLine:I
      21: aload_0
      22: iload         6
      24: putfield      #19                 // Field currentElementCol:I
      27: return

  public void handleStandaloneElementEnd(char[], int, int, boolean, int, int) throws org.attoparser.ParseException;
    Code:
       0: aload_0
       1: getfield      #5                  // Field handler:Lorg/attoparser/simple/ISimpleMarkupHandler;
       4: aload_0
       5: getfield      #16                 // Field currentElementName:Ljava/lang/String;
       8: aload_0
       9: getfield      #17                 // Field currentElementAttributes:Ljava/util/Map;
      12: iload         4
      14: aload_0
      15: getfield      #18                 // Field currentElementLine:I
      18: aload_0
      19: getfield      #19                 // Field currentElementCol:I
      22: invokeinterface #20,  6           // InterfaceMethod org/attoparser/simple/ISimpleMarkupHandler.handleStandaloneElement:(Ljava/lang/String;Ljava/util/Map;ZII)V
      27: return

  public void handleOpenElementStart(char[], int, int, int, int) throws org.attoparser.ParseException;
    Code:
       0: aload_0
       1: aload_1
       2: iload_2
       3: iload_3
       4: invokestatic  #15                 // Method org/attoparser/simple/StructureTextsRepository.getStructureName:([CII)Ljava/lang/String;
       7: putfield      #16                 // Field currentElementName:Ljava/lang/String;
      10: aload_0
      11: aconst_null
      12: putfield      #17                 // Field currentElementAttributes:Ljava/util/Map;
      15: aload_0
      16: iload         4
      18: putfield      #18                 // Field currentElementLine:I
      21: aload_0
      22: iload         5
      24: putfield      #19                 // Field currentElementCol:I
      27: return

  public void handleOpenElementEnd(char[], int, int, int, int) throws org.attoparser.ParseException;
    Code:
       0: aload_0
       1: getfield      #5                  // Field handler:Lorg/attoparser/simple/ISimpleMarkupHandler;
       4: aload_0
       5: getfield      #16                 // Field currentElementName:Ljava/lang/String;
       8: aload_0
       9: getfield      #17                 // Field currentElementAttributes:Ljava/util/Map;
      12: aload_0
      13: getfield      #18                 // Field currentElementLine:I
      16: aload_0
      17: getfield      #19                 // Field currentElementCol:I
      20: invokeinterface #21,  5           // InterfaceMethod org/attoparser/simple/ISimpleMarkupHandler.handleOpenElement:(Ljava/lang/String;Ljava/util/Map;II)V
      25: return

  public void handleAutoOpenElementStart(char[], int, int, int, int) throws org.attoparser.ParseException;
    Code:
       0: aload_0
       1: aload_1
       2: iload_2
       3: iload_3
       4: invokestatic  #15                 // Method org/attoparser/simple/StructureTextsRepository.getStructureName:([CII)Ljava/lang/String;
       7: putfield      #16                 // Field currentElementName:Ljava/lang/String;
      10: aload_0
      11: aconst_null
      12: putfield      #17                 // Field currentElementAttributes:Ljava/util/Map;
      15: aload_0
      16: iload         4
      18: putfield      #18                 // Field currentElementLine:I
      21: aload_0
      22: iload         5
      24: putfield      #19                 // Field currentElementCol:I
      27: return

  public void handleAutoOpenElementEnd(char[], int, int, int, int) throws org.attoparser.ParseException;
    Code:
       0: aload_0
       1: getfield      #5                  // Field handler:Lorg/attoparser/simple/ISimpleMarkupHandler;
       4: aload_0
       5: getfield      #16                 // Field currentElementName:Ljava/lang/String;
       8: aload_0
       9: getfield      #17                 // Field currentElementAttributes:Ljava/util/Map;
      12: aload_0
      13: getfield      #18                 // Field currentElementLine:I
      16: aload_0
      17: getfield      #19                 // Field currentElementCol:I
      20: invokeinterface #22,  5           // InterfaceMethod org/attoparser/simple/ISimpleMarkupHandler.handleAutoOpenElement:(Ljava/lang/String;Ljava/util/Map;II)V
      25: return

  public void handleCloseElementStart(char[], int, int, int, int) throws org.attoparser.ParseException;
    Code:
       0: aload_0
       1: aload_1
       2: iload_2
       3: iload_3
       4: invokestatic  #15                 // Method org/attoparser/simple/StructureTextsRepository.getStructureName:([CII)Ljava/lang/String;
       7: putfield      #16                 // Field currentElementName:Ljava/lang/String;
      10: aload_0
      11: aconst_null
      12: putfield      #17                 // Field currentElementAttributes:Ljava/util/Map;
      15: aload_0
      16: iload         4
      18: putfield      #18                 // Field currentElementLine:I
      21: aload_0
      22: iload         5
      24: putfield      #19                 // Field currentElementCol:I
      27: return

  public void handleCloseElementEnd(char[], int, int, int, int) throws org.attoparser.ParseException;
    Code:
       0: aload_0
       1: getfield      #5                  // Field handler:Lorg/attoparser/simple/ISimpleMarkupHandler;
       4: aload_0
       5: getfield      #16                 // Field currentElementName:Ljava/lang/String;
       8: aload_0
       9: getfield      #18                 // Field currentElementLine:I
      12: aload_0
      13: getfield      #19                 // Field currentElementCol:I
      16: invokeinterface #23,  4           // InterfaceMethod org/attoparser/simple/ISimpleMarkupHandler.handleCloseElement:(Ljava/lang/String;II)V
      21: return

  public void handleAutoCloseElementStart(char[], int, int, int, int) throws org.attoparser.ParseException;
    Code:
       0: aload_0
       1: aload_1
       2: iload_2
       3: iload_3
       4: invokestatic  #15                 // Method org/attoparser/simple/StructureTextsRepository.getStructureName:([CII)Ljava/lang/String;
       7: putfield      #16                 // Field currentElementName:Ljava/lang/String;
      10: aload_0
      11: aconst_null
      12: putfield      #17                 // Field currentElementAttributes:Ljava/util/Map;
      15: aload_0
      16: iload         4
      18: putfield      #18                 // Field currentElementLine:I
      21: aload_0
      22: iload         5
      24: putfield      #19                 // Field currentElementCol:I
      27: return

  public void handleAutoCloseElementEnd(char[], int, int, int, int) throws org.attoparser.ParseException;
    Code:
       0: aload_0
       1: getfield      #5                  // Field handler:Lorg/attoparser/simple/ISimpleMarkupHandler;
       4: aload_0
       5: getfield      #16                 // Field currentElementName:Ljava/lang/String;
       8: aload_0
       9: getfield      #18                 // Field currentElementLine:I
      12: aload_0
      13: getfield      #19                 // Field currentElementCol:I
      16: invokeinterface #24,  4           // InterfaceMethod org/attoparser/simple/ISimpleMarkupHandler.handleAutoCloseElement:(Ljava/lang/String;II)V
      21: return

  public void handleUnmatchedCloseElementStart(char[], int, int, int, int) throws org.attoparser.ParseException;
    Code:
       0: aload_0
       1: aload_1
       2: iload_2
       3: iload_3
       4: invokestatic  #15                 // Method org/attoparser/simple/StructureTextsRepository.getStructureName:([CII)Ljava/lang/String;
       7: putfield      #16                 // Field currentElementName:Ljava/lang/String;
      10: aload_0
      11: aconst_null
      12: putfield      #17                 // Field currentElementAttributes:Ljava/util/Map;
      15: aload_0
      16: iload         4
      18: putfield      #18                 // Field currentElementLine:I
      21: aload_0
      22: iload         5
      24: putfield      #19                 // Field currentElementCol:I
      27: return

  public void handleUnmatchedCloseElementEnd(char[], int, int, int, int) throws org.attoparser.ParseException;
    Code:
       0: aload_0
       1: getfield      #5                  // Field handler:Lorg/attoparser/simple/ISimpleMarkupHandler;
       4: aload_0
       5: getfield      #16                 // Field currentElementName:Ljava/lang/String;
       8: aload_0
       9: getfield      #18                 // Field currentElementLine:I
      12: aload_0
      13: getfield      #19                 // Field currentElementCol:I
      16: invokeinterface #25,  4           // InterfaceMethod org/attoparser/simple/ISimpleMarkupHandler.handleUnmatchedCloseElement:(Ljava/lang/String;II)V
      21: return

  public void handleAttribute(char[], int, int, int, int, int, int, int, int, int, int, int, int, int, int) throws org.attoparser.ParseException;
    Code:
       0: aload_1
       1: iload_2
       2: iload_3
       3: invokestatic  #15                 // Method org/attoparser/simple/StructureTextsRepository.getStructureName:([CII)Ljava/lang/String;
       6: astore        16
       8: iload         11
      10: ifgt          18
      13: ldc           #26                 // String
      15: goto          30
      18: new           #8                  // class java/lang/String
      21: dup
      22: aload_1
      23: iload         10
      25: iload         11
      27: invokespecial #9                  // Method java/lang/String."<init>":([CII)V
      30: astore        17
      32: aload_0
      33: getfield      #17                 // Field currentElementAttributes:Ljava/util/Map;
      36: ifnonnull     52
      39: aload_0
      40: new           #27                 // class java/util/LinkedHashMap
      43: dup
      44: iconst_3
      45: fconst_1
      46: invokespecial #28                 // Method java/util/LinkedHashMap."<init>":(IF)V
      49: putfield      #17                 // Field currentElementAttributes:Ljava/util/Map;
      52: aload_0
      53: getfield      #17                 // Field currentElementAttributes:Ljava/util/Map;
      56: aload         16
      58: aload         17
      60: invokeinterface #29,  3           // InterfaceMethod java/util/Map.put:(Ljava/lang/Object;Ljava/lang/Object;)Ljava/lang/Object;
      65: pop
      66: return

  public void handleInnerWhiteSpace(char[], int, int, int, int) throws org.attoparser.ParseException;
    Code:
       0: return

  public void handleProcessingInstruction(char[], int, int, int, int, int, int, int, int, int, int, int, int) throws org.attoparser.ParseException;
    Code:
       0: aload_0
       1: getfield      #5                  // Field handler:Lorg/attoparser/simple/ISimpleMarkupHandler;
       4: new           #8                  // class java/lang/String
       7: dup
       8: aload_1
       9: iload_2
      10: iload_3
      11: invokespecial #9                  // Method java/lang/String."<init>":([CII)V
      14: iload         6
      16: ifgt          23
      19: aconst_null
      20: goto          35
      23: new           #8                  // class java/lang/String
      26: dup
      27: aload_1
      28: iload         6
      30: iload         7
      32: invokespecial #9                  // Method java/lang/String."<init>":([CII)V
      35: iload         12
      37: iload         13
      39: invokeinterface #30,  5           // InterfaceMethod org/attoparser/simple/ISimpleMarkupHandler.handleProcessingInstruction:(Ljava/lang/String;Ljava/lang/String;II)V
      44: return
}
