Compiled from "JarWarResourceSet.java"
final class org.apache.catalina.webresources.JarWarResourceSet$VersionedJarEntry {
  private final int version;

  private final java.util.jar.JarEntry jarEntry;

  public org.apache.catalina.webresources.JarWarResourceSet$VersionedJarEntry(int, java.util.jar.JarEntry);
    Code:
       0: aload_0
       1: invokespecial #1                  // Method java/lang/Object."<init>":()V
       4: aload_0
       5: iload_1
       6: putfield      #2                  // Field version:I
       9: aload_0
      10: aload_2
      11: putfield      #3                  // Field jarEntry:Ljava/util/jar/JarEntry;
      14: return

  public int getVersion();
    Code:
       0: aload_0
       1: getfield      #2                  // Field version:I
       4: ireturn

  public java.util.jar.JarEntry getJarEntry();
    Code:
       0: aload_0
       1: getfield      #3                  // Field jarEntry:Ljava/util/jar/JarEntry;
       4: areturn
}
