Compiled from "MvcUriComponentsBuilder.java"
public class org.springframework.web.servlet.mvc.method.annotation.MvcUriComponentsBuilder$MethodArgumentBuilder {
  private final java.lang.Class<?> controllerType;

  private final java.lang.reflect.Method method;

  private final java.lang.Object[] argumentValues;

  private final org.springframework.web.util.UriComponentsBuilder baseUrl;

  public org.springframework.web.servlet.mvc.method.annotation.MvcUriComponentsBuilder$MethodArgumentBuilder(java.lang.Class<?>, java.lang.reflect.Method);
    Code:
       0: aload_0
       1: aconst_null
       2: aload_1
       3: aload_2
       4: invokespecial #1                  // Method "<init>":(Lorg/springframework/web/util/UriComponentsBuilder;Ljava/lang/Class;Ljava/lang/reflect/Method;)V
       7: return

  public org.springframework.web.servlet.mvc.method.annotation.MvcUriComponentsBuilder$MethodArgumentBuilder(org.springframework.web.util.UriComponentsBuilder, java.lang.Class<?>, java.lang.reflect.Method);
    Code:
       0: aload_0
       1: invokespecial #2                  // Method java/lang/Object."<init>":()V
       4: aload_2
       5: ldc           #3                  // String \'controllerType\' is required
       7: invokestatic  #4                  // Method org/springframework/util/Assert.notNull:(Ljava/lang/Object;Ljava/lang/String;)V
      10: aload_3
      11: ldc           #5                  // String \'method\' is required
      13: invokestatic  #4                  // Method org/springframework/util/Assert.notNull:(Ljava/lang/Object;Ljava/lang/String;)V
      16: aload_0
      17: aload_1
      18: ifnull        25
      21: aload_1
      22: goto          28
      25: invokestatic  #6                  // Method initBaseUrl:()Lorg/springframework/web/util/UriComponentsBuilder;
      28: putfield      #7                  // Field baseUrl:Lorg/springframework/web/util/UriComponentsBuilder;
      31: aload_0
      32: aload_2
      33: putfield      #8                  // Field controllerType:Ljava/lang/Class;
      36: aload_0
      37: aload_3
      38: putfield      #9                  // Field method:Ljava/lang/reflect/Method;
      41: aload_0
      42: aload_3
      43: invokevirtual #10                 // Method java/lang/reflect/Method.getParameterTypes:()[Ljava/lang/Class;
      46: arraylength
      47: anewarray     #11                 // class java/lang/Object
      50: putfield      #12                 // Field argumentValues:[Ljava/lang/Object;
      53: iconst_0
      54: istore        4
      56: iload         4
      58: aload_0
      59: getfield      #12                 // Field argumentValues:[Ljava/lang/Object;
      62: arraylength
      63: if_icmpge     80
      66: aload_0
      67: getfield      #12                 // Field argumentValues:[Ljava/lang/Object;
      70: iload         4
      72: aconst_null
      73: aastore
      74: iinc          4, 1
      77: goto          56
      80: return

  public org.springframework.web.servlet.mvc.method.annotation.MvcUriComponentsBuilder$MethodArgumentBuilder(java.lang.reflect.Method);
    Code:
       0: aload_0
       1: aload_1
       2: invokevirtual #13                 // Method java/lang/reflect/Method.getDeclaringClass:()Ljava/lang/Class;
       5: aload_1
       6: invokespecial #14                 // Method "<init>":(Ljava/lang/Class;Ljava/lang/reflect/Method;)V
       9: return

  private static org.springframework.web.util.UriComponentsBuilder initBaseUrl();
    Code:
       0: invokestatic  #15                 // Method org/springframework/web/servlet/support/ServletUriComponentsBuilder.fromCurrentServletMapping:()Lorg/springframework/web/servlet/support/ServletUriComponentsBuilder;
       3: astore_0
       4: aload_0
       5: invokevirtual #16                 // Method org/springframework/web/util/UriComponentsBuilder.build:()Lorg/springframework/web/util/UriComponents;
       8: invokevirtual #17                 // Method org/springframework/web/util/UriComponents.getPath:()Ljava/lang/String;
      11: invokestatic  #18                 // Method org/springframework/web/util/UriComponentsBuilder.fromPath:(Ljava/lang/String;)Lorg/springframework/web/util/UriComponentsBuilder;
      14: areturn

  public org.springframework.web.servlet.mvc.method.annotation.MvcUriComponentsBuilder$MethodArgumentBuilder arg(int, java.lang.Object);
    Code:
       0: aload_0
       1: getfield      #12                 // Field argumentValues:[Ljava/lang/Object;
       4: iload_1
       5: aload_2
       6: aastore
       7: aload_0
       8: areturn

  public java.lang.String build();
    Code:
       0: aload_0
       1: getfield      #7                  // Field baseUrl:Lorg/springframework/web/util/UriComponentsBuilder;
       4: aload_0
       5: getfield      #8                  // Field controllerType:Ljava/lang/Class;
       8: aload_0
       9: getfield      #9                  // Field method:Ljava/lang/reflect/Method;
      12: aload_0
      13: getfield      #12                 // Field argumentValues:[Ljava/lang/Object;
      16: invokestatic  #19                 // Method org/springframework/web/servlet/mvc/method/annotation/MvcUriComponentsBuilder.access$100:(Lorg/springframework/web/util/UriComponentsBuilder;Ljava/lang/Class;Ljava/lang/reflect/Method;[Ljava/lang/Object;)Lorg/springframework/web/util/UriComponentsBuilder;
      19: iconst_0
      20: invokevirtual #20                 // Method org/springframework/web/util/UriComponentsBuilder.build:(Z)Lorg/springframework/web/util/UriComponents;
      23: invokevirtual #21                 // Method org/springframework/web/util/UriComponents.encode:()Lorg/springframework/web/util/UriComponents;
      26: invokevirtual #22                 // Method org/springframework/web/util/UriComponents.toUriString:()Ljava/lang/String;
      29: areturn

  public java.lang.String buildAndExpand(java.lang.Object...);
    Code:
       0: aload_0
       1: getfield      #7                  // Field baseUrl:Lorg/springframework/web/util/UriComponentsBuilder;
       4: aload_0
       5: getfield      #8                  // Field controllerType:Ljava/lang/Class;
       8: aload_0
       9: getfield      #9                  // Field method:Ljava/lang/reflect/Method;
      12: aload_0
      13: getfield      #12                 // Field argumentValues:[Ljava/lang/Object;
      16: invokestatic  #19                 // Method org/springframework/web/servlet/mvc/method/annotation/MvcUriComponentsBuilder.access$100:(Lorg/springframework/web/util/UriComponentsBuilder;Ljava/lang/Class;Ljava/lang/reflect/Method;[Ljava/lang/Object;)Lorg/springframework/web/util/UriComponentsBuilder;
      19: iconst_0
      20: invokevirtual #20                 // Method org/springframework/web/util/UriComponentsBuilder.build:(Z)Lorg/springframework/web/util/UriComponents;
      23: aload_1
      24: invokevirtual #23                 // Method org/springframework/web/util/UriComponents.expand:([Ljava/lang/Object;)Lorg/springframework/web/util/UriComponents;
      27: invokevirtual #21                 // Method org/springframework/web/util/UriComponents.encode:()Lorg/springframework/web/util/UriComponents;
      30: invokevirtual #24                 // Method org/springframework/web/util/UriComponents.toString:()Ljava/lang/String;
      33: areturn
}
