Compiled from "OWLObjectRenderingComparator.java"
public class org.protege.editor.owl.ui.OWLObjectRenderingComparator<E extends org.semanticweb.owlapi.model.OWLObject> extends org.protege.editor.owl.ui.OWLObjectComparator<E> {
  public org.protege.editor.owl.ui.OWLObjectRenderingComparator(org.protege.editor.owl.model.OWLModelManager);
    Code:
       0: aload_0
       1: aload_1
       2: invokespecial #1                  // Method org/protege/editor/owl/ui/OWLObjectComparator."<init>":(Lorg/protege/editor/owl/model/OWLModelManager;)V
       5: return

  public int compare(E, E);
    Code:
       0: aload_0
       1: invokevirtual #2                  // Method getOWLModelManager:()Lorg/protege/editor/owl/model/OWLModelManager;
       4: astore_3
       5: aload_3
       6: aload_1
       7: invokeinterface #3,  2            // InterfaceMethod org/protege/editor/owl/model/OWLModelManager.getRendering:(Lorg/semanticweb/owlapi/model/OWLObject;)Ljava/lang/String;
      12: astore        4
      14: aload         4
      16: ldc           #4                  // String \'
      18: invokevirtual #5                  // Method java/lang/String.startsWith:(Ljava/lang/String;)Z
      21: ifeq          39
      24: aload         4
      26: iconst_1
      27: aload         4
      29: invokevirtual #6                  // Method java/lang/String.length:()I
      32: iconst_1
      33: isub
      34: invokevirtual #7                  // Method java/lang/String.substring:(II)Ljava/lang/String;
      37: astore        4
      39: aload_3
      40: aload_2
      41: invokeinterface #3,  2            // InterfaceMethod org/protege/editor/owl/model/OWLModelManager.getRendering:(Lorg/semanticweb/owlapi/model/OWLObject;)Ljava/lang/String;
      46: astore        5
      48: aload         5
      50: ldc           #4                  // String \'
      52: invokevirtual #5                  // Method java/lang/String.startsWith:(Ljava/lang/String;)Z
      55: ifeq          73
      58: aload         5
      60: iconst_1
      61: aload         5
      63: invokevirtual #6                  // Method java/lang/String.length:()I
      66: iconst_1
      67: isub
      68: invokevirtual #7                  // Method java/lang/String.substring:(II)Ljava/lang/String;
      71: astore        5
      73: aload         4
      75: aload         5
      77: invokevirtual #8                  // Method java/lang/String.compareToIgnoreCase:(Ljava/lang/String;)I
      80: istore        6
      82: iload         6
      84: ifne          96
      87: aload_1
      88: aload_2
      89: invokeinterface #9,  2            // InterfaceMethod org/semanticweb/owlapi/model/OWLObject.compareTo:(Ljava/lang/Object;)I
      94: istore        6
      96: iload         6
      98: ireturn

  public int compare(java.lang.Object, java.lang.Object);
    Code:
       0: aload_0
       1: aload_1
       2: checkcast     #10                 // class org/semanticweb/owlapi/model/OWLObject
       5: aload_2
       6: checkcast     #10                 // class org/semanticweb/owlapi/model/OWLObject
       9: invokevirtual #11                 // Method compare:(Lorg/semanticweb/owlapi/model/OWLObject;Lorg/semanticweb/owlapi/model/OWLObject;)I
      12: ireturn
}
