Compiled from "OWLWorkspaceViewsTab.java"
public class org.protege.editor.owl.ui.OWLWorkspaceViewsTab extends org.protege.editor.core.ui.workspace.WorkspaceViewsTab implements org.protege.editor.owl.model.selection.SelectionPlane {
  private java.util.Optional<javax.swing.JComponent> lastEntityDisplayCandidate;

  private org.protege.editor.owl.model.OWLEntityDisplayProvider provider;

  private org.protege.editor.owl.model.selection.SelectionPlane selectionPlaneDelegate;

  public org.protege.editor.owl.ui.OWLWorkspaceViewsTab();
    Code:
       0: aload_0
       1: invokespecial #3                  // Method org/protege/editor/core/ui/workspace/WorkspaceViewsTab."<init>":()V
       4: aload_0
       5: invokestatic  #4                  // Method java/util/Optional.empty:()Ljava/util/Optional;
       8: putfield      #1                  // Field lastEntityDisplayCandidate:Ljava/util/Optional;
      11: aload_0
      12: new           #5                  // class org/protege/editor/owl/ui/OWLWorkspaceViewsTab$1
      15: dup
      16: aload_0
      17: invokespecial #6                  // Method org/protege/editor/owl/ui/OWLWorkspaceViewsTab$1."<init>":(Lorg/protege/editor/owl/ui/OWLWorkspaceViewsTab;)V
      20: putfield      #7                  // Field provider:Lorg/protege/editor/owl/model/OWLEntityDisplayProvider;
      23: return

  private boolean canDisplay(org.semanticweb.owlapi.model.OWLEntity);
    Code:
       0: new           #8                  // class org/protege/editor/owl/ui/OWLWorkspaceViewsTab$NavFinder
       3: dup
       4: aload_0
       5: invokespecial #9                  // Method org/protege/editor/owl/ui/OWLWorkspaceViewsTab$NavFinder."<init>":(Lorg/protege/editor/owl/ui/OWLWorkspaceViewsTab;)V
       8: aload_1
       9: invokevirtual #10                 // Method org/protege/editor/owl/ui/OWLWorkspaceViewsTab$NavFinder.getNav:(Lorg/semanticweb/owlapi/model/OWLEntity;)Ljava/lang/String;
      12: astore_2
      13: aload_0
      14: invokevirtual #11                 // Method getViewsPane:()Lorg/protege/editor/core/ui/view/ViewsPane;
      17: invokevirtual #12                 // Method org/protege/editor/core/ui/view/ViewsPane.getViews:()Ljava/util/Set;
      20: invokeinterface #13,  1           // InterfaceMethod java/util/Set.iterator:()Ljava/util/Iterator;
      25: astore_3
      26: aload_3
      27: invokeinterface #14,  1           // InterfaceMethod java/util/Iterator.hasNext:()Z
      32: ifeq          188
      35: aload_3
      36: invokeinterface #15,  1           // InterfaceMethod java/util/Iterator.next:()Ljava/lang/Object;
      41: checkcast     #16                 // class org/protege/editor/core/ui/view/View
      44: astore        4
      46: aload         4
      48: invokevirtual #17                 // Method org/protege/editor/core/ui/view/View.getViewComponent:()Lorg/protege/editor/core/ui/view/ViewComponent;
      51: astore        5
      53: aload         5
      55: ifnull        104
      58: aload         5
      60: instanceof    #18                 // class org/protege/editor/owl/ui/view/AbstractOWLSelectionViewComponent
      63: ifeq          185
      66: aload         5
      68: instanceof    #19                 // class org/protege/editor/owl/model/selection/SelectionDriver
      71: ifeq          185
      74: aload         5
      76: checkcast     #18                 // class org/protege/editor/owl/ui/view/AbstractOWLSelectionViewComponent
      79: astore        6
      81: aload         6
      83: aload_1
      84: invokevirtual #20                 // Method org/protege/editor/owl/ui/view/AbstractOWLSelectionViewComponent.canShowEntity:(Lorg/semanticweb/owlapi/model/OWLEntity;)Z
      87: ifeq          101
      90: aload_0
      91: aload         4
      93: invokestatic  #21                 // Method java/util/Optional.of:(Ljava/lang/Object;)Ljava/util/Optional;
      96: putfield      #1                  // Field lastEntityDisplayCandidate:Ljava/util/Optional;
      99: iconst_1
     100: ireturn
     101: goto          185
     104: aload_0
     105: invokevirtual #22                 // Method getWorkspace:()Lorg/protege/editor/core/ui/workspace/TabbedWorkspace;
     108: invokevirtual #23                 // Method org/protege/editor/core/ui/workspace/TabbedWorkspace.getViewManager:()Lorg/protege/editor/core/ui/workspace/WorkspaceViewManager;
     111: aload         4
     113: invokevirtual #24                 // Method org/protege/editor/core/ui/view/View.getId:()Ljava/lang/String;
     116: invokevirtual #25                 // Method org/protege/editor/core/ui/workspace/WorkspaceViewManager.getViewComponentPlugin:(Ljava/lang/String;)Lorg/protege/editor/core/ui/view/ViewComponentPlugin;
     119: astore        6
     121: aload         6
     123: ifnull        185
     126: aload         6
     128: invokeinterface #26,  1           // InterfaceMethod org/protege/editor/core/ui/view/ViewComponentPlugin.getNavigates:()Ljava/util/Set;
     133: invokeinterface #13,  1           // InterfaceMethod java/util/Set.iterator:()Ljava/util/Iterator;
     138: astore        7
     140: aload         7
     142: invokeinterface #14,  1           // InterfaceMethod java/util/Iterator.hasNext:()Z
     147: ifeq          185
     150: aload         7
     152: invokeinterface #15,  1           // InterfaceMethod java/util/Iterator.next:()Ljava/lang/Object;
     157: checkcast     #27                 // class java/lang/String
     160: astore        8
     162: aload_2
     163: aload         8
     165: invokevirtual #28                 // Method java/lang/String.equals:(Ljava/lang/Object;)Z
     168: ifeq          182
     171: aload_0
     172: aload         4
     174: invokestatic  #21                 // Method java/util/Optional.of:(Ljava/lang/Object;)Ljava/util/Optional;
     177: putfield      #1                  // Field lastEntityDisplayCandidate:Ljava/util/Optional;
     180: iconst_1
     181: ireturn
     182: goto          140
     185: goto          26
     188: iconst_0
     189: ireturn

  public void initialise();
    Code:
       0: aload_0
       1: invokespecial #29                 // Method org/protege/editor/core/ui/workspace/WorkspaceViewsTab.initialise:()V
       4: aload_0
       5: new           #30                 // class org/protege/editor/owl/model/selection/SelectionPlaneImpl
       8: dup
       9: aload_0
      10: invokevirtual #31                 // Method getOWLEditorKit:()Lorg/protege/editor/owl/OWLEditorKit;
      13: invokevirtual #32                 // Method org/protege/editor/owl/OWLEditorKit.getOWLWorkspace:()Lorg/protege/editor/owl/model/OWLWorkspace;
      16: invokevirtual #33                 // Method org/protege/editor/owl/model/OWLWorkspace.getOWLSelectionModel:()Lorg/protege/editor/owl/model/selection/OWLSelectionModel;
      19: invokespecial #34                 // Method org/protege/editor/owl/model/selection/SelectionPlaneImpl."<init>":(Lorg/protege/editor/owl/model/selection/OWLSelectionModel;)V
      22: putfield      #35                 // Field selectionPlaneDelegate:Lorg/protege/editor/owl/model/selection/SelectionPlane;
      25: aload_0
      26: invokevirtual #31                 // Method getOWLEditorKit:()Lorg/protege/editor/owl/OWLEditorKit;
      29: invokevirtual #36                 // Method org/protege/editor/owl/OWLEditorKit.getWorkspace:()Lorg/protege/editor/owl/model/OWLWorkspace;
      32: aload_0
      33: getfield      #7                  // Field provider:Lorg/protege/editor/owl/model/OWLEntityDisplayProvider;
      36: invokevirtual #37                 // Method org/protege/editor/owl/model/OWLWorkspace.registerOWLEntityDisplayProvider:(Lorg/protege/editor/owl/model/OWLEntityDisplayProvider;)V
      39: return

  public void dispose();
    Code:
       0: aload_0
       1: invokevirtual #31                 // Method getOWLEditorKit:()Lorg/protege/editor/owl/OWLEditorKit;
       4: invokevirtual #36                 // Method org/protege/editor/owl/OWLEditorKit.getWorkspace:()Lorg/protege/editor/owl/model/OWLWorkspace;
       7: aload_0
       8: getfield      #7                  // Field provider:Lorg/protege/editor/owl/model/OWLEntityDisplayProvider;
      11: invokevirtual #38                 // Method org/protege/editor/owl/model/OWLWorkspace.unregisterOWLEntityDisplayProvider:(Lorg/protege/editor/owl/model/OWLEntityDisplayProvider;)V
      14: aload_0
      15: invokespecial #39                 // Method org/protege/editor/core/ui/workspace/WorkspaceViewsTab.dispose:()V
      18: return

  public org.protege.editor.core.util.HandlerRegistration registerSelectionDriver(org.protege.editor.owl.model.selection.SelectionDriver);
    Code:
       0: aload_0
       1: getfield      #35                 // Field selectionPlaneDelegate:Lorg/protege/editor/owl/model/selection/SelectionPlane;
       4: aload_1
       5: invokeinterface #40,  2           // InterfaceMethod org/protege/editor/owl/model/selection/SelectionPlane.registerSelectionDriver:(Lorg/protege/editor/owl/model/selection/SelectionDriver;)Lorg/protege/editor/core/util/HandlerRegistration;
      10: areturn

  public void transmitSelection(org.protege.editor.owl.model.selection.SelectionDriver, org.semanticweb.owlapi.model.OWLObject);
    Code:
       0: aload_0
       1: getfield      #35                 // Field selectionPlaneDelegate:Lorg/protege/editor/owl/model/selection/SelectionPlane;
       4: aload_1
       5: aload_2
       6: invokeinterface #41,  3           // InterfaceMethod org/protege/editor/owl/model/selection/SelectionPlane.transmitSelection:(Lorg/protege/editor/owl/model/selection/SelectionDriver;Lorg/semanticweb/owlapi/model/OWLObject;)V
      11: return

  public org.protege.editor.owl.model.OWLModelManager getOWLModelManager();
    Code:
       0: aload_0
       1: invokevirtual #22                 // Method getWorkspace:()Lorg/protege/editor/core/ui/workspace/TabbedWorkspace;
       4: invokevirtual #42                 // Method org/protege/editor/core/ui/workspace/TabbedWorkspace.getEditorKit:()Lorg/protege/editor/core/editorkit/EditorKit;
       7: invokeinterface #43,  1           // InterfaceMethod org/protege/editor/core/editorkit/EditorKit.getModelManager:()Lorg/protege/editor/core/ModelManager;
      12: checkcast     #44                 // class org/protege/editor/owl/model/OWLModelManager
      15: areturn

  public org.protege.editor.owl.OWLEditorKit getOWLEditorKit();
    Code:
       0: aload_0
       1: invokevirtual #22                 // Method getWorkspace:()Lorg/protege/editor/core/ui/workspace/TabbedWorkspace;
       4: invokevirtual #42                 // Method org/protege/editor/core/ui/workspace/TabbedWorkspace.getEditorKit:()Lorg/protege/editor/core/editorkit/EditorKit;
       7: checkcast     #45                 // class org/protege/editor/owl/OWLEditorKit
      10: areturn

  static boolean access$000(org.protege.editor.owl.ui.OWLWorkspaceViewsTab, org.semanticweb.owlapi.model.OWLEntity);
    Code:
       0: aload_0
       1: aload_1
       2: invokespecial #2                  // Method canDisplay:(Lorg/semanticweb/owlapi/model/OWLEntity;)Z
       5: ireturn

  static java.util.Optional access$100(org.protege.editor.owl.ui.OWLWorkspaceViewsTab);
    Code:
       0: aload_0
       1: getfield      #1                  // Field lastEntityDisplayCandidate:Ljava/util/Optional;
       4: areturn
}
