Compiled from "ConstructorInjector.java"
final class org.sonarsource.sonarlint.shaded.org.picocontainer.injectors.ConstructorInjector$ResolverKey {
  private final java.lang.reflect.Type expectedType;

  private final java.lang.String pName;

  private final boolean useNames;

  private final java.lang.annotation.Annotation binding;

  private final org.sonarsource.sonarlint.shaded.org.picocontainer.Parameter currentParameter;

  private org.sonarsource.sonarlint.shaded.org.picocontainer.injectors.ConstructorInjector$ResolverKey(java.lang.reflect.Type, java.lang.String, boolean, java.lang.annotation.Annotation, org.sonarsource.sonarlint.shaded.org.picocontainer.Parameter);
    Code:
       0: aload_0
       1: invokespecial #25                 // Method java/lang/Object."<init>":()V
       4: aload_0
       5: aload_1
       6: putfield      #27                 // Field expectedType:Ljava/lang/reflect/Type;
       9: aload_0
      10: aload_2
      11: putfield      #29                 // Field pName:Ljava/lang/String;
      14: aload_0
      15: iload_3
      16: putfield      #31                 // Field useNames:Z
      19: aload_0
      20: aload         4
      22: putfield      #33                 // Field binding:Ljava/lang/annotation/Annotation;
      25: aload_0
      26: aload         5
      28: putfield      #35                 // Field currentParameter:Lorg/sonarsource/sonarlint/shaded/org/picocontainer/Parameter;
      31: return

  public boolean equals(java.lang.Object);
    Code:
       0: aload_0
       1: aload_1
       2: if_acmpne     7
       5: iconst_1
       6: ireturn
       7: aload_1
       8: ifnull        22
      11: aload_0
      12: invokevirtual #43                 // Method java/lang/Object.getClass:()Ljava/lang/Class;
      15: aload_1
      16: invokevirtual #43                 // Method java/lang/Object.getClass:()Ljava/lang/Class;
      19: if_acmpeq     24
      22: iconst_0
      23: ireturn
      24: aload_1
      25: checkcast     #2                  // class org/sonarsource/sonarlint/shaded/org/picocontainer/injectors/ConstructorInjector$ResolverKey
      28: astore_2
      29: aload_0
      30: getfield      #31                 // Field useNames:Z
      33: aload_2
      34: getfield      #31                 // Field useNames:Z
      37: if_icmpeq     42
      40: iconst_0
      41: ireturn
      42: aload_0
      43: getfield      #33                 // Field binding:Ljava/lang/annotation/Annotation;
      46: ifnull        68
      49: aload_0
      50: getfield      #33                 // Field binding:Ljava/lang/annotation/Annotation;
      53: aload_2
      54: getfield      #33                 // Field binding:Ljava/lang/annotation/Annotation;
      57: invokeinterface #47,  2           // InterfaceMethod java/lang/annotation/Annotation.equals:(Ljava/lang/Object;)Z
      62: ifne          77
      65: goto          75
      68: aload_2
      69: getfield      #33                 // Field binding:Ljava/lang/annotation/Annotation;
      72: ifnull        77
      75: iconst_0
      76: ireturn
      77: aload_0
      78: getfield      #35                 // Field currentParameter:Lorg/sonarsource/sonarlint/shaded/org/picocontainer/Parameter;
      81: aload_2
      82: getfield      #35                 // Field currentParameter:Lorg/sonarsource/sonarlint/shaded/org/picocontainer/Parameter;
      85: invokevirtual #48                 // Method java/lang/Object.equals:(Ljava/lang/Object;)Z
      88: ifne          93
      91: iconst_0
      92: ireturn
      93: aload_0
      94: getfield      #27                 // Field expectedType:Ljava/lang/reflect/Type;
      97: aload_2
      98: getfield      #27                 // Field expectedType:Ljava/lang/reflect/Type;
     101: invokevirtual #48                 // Method java/lang/Object.equals:(Ljava/lang/Object;)Z
     104: ifne          109
     107: iconst_0
     108: ireturn
     109: aload_0
     110: getfield      #29                 // Field pName:Ljava/lang/String;
     113: ifnull        133
     116: aload_0
     117: getfield      #29                 // Field pName:Ljava/lang/String;
     120: aload_2
     121: getfield      #29                 // Field pName:Ljava/lang/String;
     124: invokevirtual #51                 // Method java/lang/String.equals:(Ljava/lang/Object;)Z
     127: ifne          142
     130: goto          140
     133: aload_2
     134: getfield      #29                 // Field pName:Ljava/lang/String;
     137: ifnull        142
     140: iconst_0
     141: ireturn
     142: iconst_1
     143: ireturn

  public int hashCode();
    Code:
       0: aload_0
       1: getfield      #27                 // Field expectedType:Ljava/lang/reflect/Type;
       4: invokevirtual #58                 // Method java/lang/Object.hashCode:()I
       7: istore_1
       8: bipush        31
      10: iload_1
      11: imul
      12: aload_0
      13: getfield      #29                 // Field pName:Ljava/lang/String;
      16: ifnull        29
      19: aload_0
      20: getfield      #29                 // Field pName:Ljava/lang/String;
      23: invokevirtual #59                 // Method java/lang/String.hashCode:()I
      26: goto          30
      29: iconst_0
      30: iadd
      31: istore_1
      32: bipush        31
      34: iload_1
      35: imul
      36: aload_0
      37: getfield      #31                 // Field useNames:Z
      40: ifeq          47
      43: iconst_1
      44: goto          48
      47: iconst_0
      48: iadd
      49: istore_1
      50: bipush        31
      52: iload_1
      53: imul
      54: aload_0
      55: getfield      #33                 // Field binding:Ljava/lang/annotation/Annotation;
      58: ifnull        73
      61: aload_0
      62: getfield      #33                 // Field binding:Ljava/lang/annotation/Annotation;
      65: invokeinterface #60,  1           // InterfaceMethod java/lang/annotation/Annotation.hashCode:()I
      70: goto          74
      73: iconst_0
      74: iadd
      75: istore_1
      76: bipush        31
      78: iload_1
      79: imul
      80: aload_0
      81: getfield      #35                 // Field currentParameter:Lorg/sonarsource/sonarlint/shaded/org/picocontainer/Parameter;
      84: invokevirtual #58                 // Method java/lang/Object.hashCode:()I
      87: iadd
      88: istore_1
      89: iload_1
      90: ireturn

  org.sonarsource.sonarlint.shaded.org.picocontainer.injectors.ConstructorInjector$ResolverKey(java.lang.reflect.Type, java.lang.String, boolean, java.lang.annotation.Annotation, org.sonarsource.sonarlint.shaded.org.picocontainer.Parameter, org.sonarsource.sonarlint.shaded.org.picocontainer.injectors.ConstructorInjector$1);
    Code:
       0: aload_0
       1: aload_1
       2: aload_2
       3: iload_3
       4: aload         4
       6: aload         5
       8: invokespecial #65                 // Method "<init>":(Ljava/lang/reflect/Type;Ljava/lang/String;ZLjava/lang/annotation/Annotation;Lorg/sonarsource/sonarlint/shaded/org/picocontainer/Parameter;)V
      11: return
}
