Compiled from "FactoryInjector.java"
public abstract class org.sonarsource.sonarlint.shaded.org.picocontainer.injectors.FactoryInjector<T> implements org.sonarsource.sonarlint.shaded.org.picocontainer.Injector<T> {
  private java.lang.Class key;

  public org.sonarsource.sonarlint.shaded.org.picocontainer.injectors.FactoryInjector() throws org.sonarsource.sonarlint.shaded.org.picocontainer.PicoCompositionException;
    Code:
       0: aload_0
       1: invokespecial #19                 // Method java/lang/Object."<init>":()V
       4: aload_0
       5: ldc           #2                  // class org/sonarsource/sonarlint/shaded/org/picocontainer/injectors/FactoryInjector
       7: aload_0
       8: invokevirtual #23                 // Method java/lang/Object.getClass:()Ljava/lang/Class;
      11: invokestatic  #27                 // Method getTypeArguments:(Ljava/lang/Class;Ljava/lang/Class;)Ljava/util/List;
      14: iconst_0
      15: invokeinterface #33,  2           // InterfaceMethod java/util/List.get:(I)Ljava/lang/Object;
      20: checkcast     #35                 // class java/lang/Class
      23: putfield      #37                 // Field key:Ljava/lang/Class;
      26: aload_0
      27: getfield      #37                 // Field key:Ljava/lang/Class;
      30: ifnonnull     39
      33: aload_0
      34: ldc           #10                 // class org/sonarsource/sonarlint/shaded/org/picocontainer/injectors/FactoryInjector$CantWorkItOut
      36: putfield      #37                 // Field key:Ljava/lang/Class;
      39: return

  public org.sonarsource.sonarlint.shaded.org.picocontainer.injectors.FactoryInjector(java.lang.Class<T>);
    Code:
       0: aload_0
       1: invokespecial #19                 // Method java/lang/Object."<init>":()V
       4: aload_0
       5: aload_1
       6: putfield      #37                 // Field key:Ljava/lang/Class;
       9: return

  public static java.lang.Class<?> getClass(java.lang.reflect.Type);
    Code:
       0: aload_0
       1: instanceof    #35                 // class java/lang/Class
       4: ifeq          12
       7: aload_0
       8: checkcast     #35                 // class java/lang/Class
      11: areturn
      12: aload_0
      13: instanceof    #47                 // class java/lang/reflect/ParameterizedType
      16: ifeq          32
      19: aload_0
      20: checkcast     #47                 // class java/lang/reflect/ParameterizedType
      23: invokeinterface #51,  1           // InterfaceMethod java/lang/reflect/ParameterizedType.getRawType:()Ljava/lang/reflect/Type;
      28: invokestatic  #53                 // Method getClass:(Ljava/lang/reflect/Type;)Ljava/lang/Class;
      31: areturn
      32: aload_0
      33: instanceof    #55                 // class java/lang/reflect/GenericArrayType
      36: ifeq          69
      39: aload_0
      40: checkcast     #55                 // class java/lang/reflect/GenericArrayType
      43: invokeinterface #58,  1           // InterfaceMethod java/lang/reflect/GenericArrayType.getGenericComponentType:()Ljava/lang/reflect/Type;
      48: astore_1
      49: aload_1
      50: invokestatic  #53                 // Method getClass:(Ljava/lang/reflect/Type;)Ljava/lang/Class;
      53: astore_2
      54: aload_2
      55: ifnull        67
      58: aload_2
      59: iconst_0
      60: invokestatic  #64                 // Method java/lang/reflect/Array.newInstance:(Ljava/lang/Class;I)Ljava/lang/Object;
      63: invokevirtual #23                 // Method java/lang/Object.getClass:()Ljava/lang/Class;
      66: areturn
      67: aconst_null
      68: areturn
      69: aconst_null
      70: areturn

  public static <T> java.util.List<java.lang.Class<?>> getTypeArguments(java.lang.Class<org.sonarsource.sonarlint.shaded.org.picocontainer.injectors.FactoryInjector>, java.lang.Class<? extends java.lang.Object>);
    Code:
       0: new           #72                 // class java/util/HashMap
       3: dup
       4: invokespecial #73                 // Method java/util/HashMap."<init>":()V
       7: astore_2
       8: aload_1
       9: astore_3
      10: aload_3
      11: invokestatic  #53                 // Method getClass:(Ljava/lang/reflect/Type;)Ljava/lang/Class;
      14: aload_0
      15: invokevirtual #77                 // Method java/lang/Object.equals:(Ljava/lang/Object;)Z
      18: ifne          125
      21: aload_3
      22: instanceof    #35                 // class java/lang/Class
      25: ifeq          39
      28: aload_3
      29: checkcast     #35                 // class java/lang/Class
      32: invokevirtual #80                 // Method java/lang/Class.getGenericSuperclass:()Ljava/lang/reflect/Type;
      35: astore_3
      36: goto          10
      39: aload_3
      40: checkcast     #47                 // class java/lang/reflect/ParameterizedType
      43: astore        4
      45: aload         4
      47: invokeinterface #51,  1           // InterfaceMethod java/lang/reflect/ParameterizedType.getRawType:()Ljava/lang/reflect/Type;
      52: checkcast     #35                 // class java/lang/Class
      55: astore        5
      57: aload         4
      59: invokeinterface #84,  1           // InterfaceMethod java/lang/reflect/ParameterizedType.getActualTypeArguments:()[Ljava/lang/reflect/Type;
      64: astore        6
      66: aload         5
      68: invokevirtual #88                 // Method java/lang/Class.getTypeParameters:()[Ljava/lang/reflect/TypeVariable;
      71: astore        7
      73: iconst_0
      74: istore        8
      76: iload         8
      78: aload         6
      80: arraylength
      81: if_icmpge     107
      84: aload_2
      85: aload         7
      87: iload         8
      89: aaload
      90: aload         6
      92: iload         8
      94: aaload
      95: invokeinterface #94,  3           // InterfaceMethod java/util/Map.put:(Ljava/lang/Object;Ljava/lang/Object;)Ljava/lang/Object;
     100: pop
     101: iinc          8, 1
     104: goto          76
     107: aload         5
     109: aload_0
     110: invokevirtual #77                 // Method java/lang/Object.equals:(Ljava/lang/Object;)Z
     113: ifne          122
     116: aload         5
     118: invokevirtual #80                 // Method java/lang/Class.getGenericSuperclass:()Ljava/lang/reflect/Type;
     121: astore_3
     122: goto          10
     125: aload_3
     126: instanceof    #35                 // class java/lang/Class
     129: ifeq          144
     132: aload_3
     133: checkcast     #35                 // class java/lang/Class
     136: invokevirtual #88                 // Method java/lang/Class.getTypeParameters:()[Ljava/lang/reflect/TypeVariable;
     139: astore        4
     141: goto          155
     144: aload_3
     145: checkcast     #47                 // class java/lang/reflect/ParameterizedType
     148: invokeinterface #84,  1           // InterfaceMethod java/lang/reflect/ParameterizedType.getActualTypeArguments:()[Ljava/lang/reflect/Type;
     153: astore        4
     155: new           #96                 // class java/util/ArrayList
     158: dup
     159: invokespecial #97                 // Method java/util/ArrayList."<init>":()V
     162: astore        5
     164: aload         4
     166: astore        6
     168: aload         6
     170: arraylength
     171: istore        7
     173: iconst_0
     174: istore        8
     176: iload         8
     178: iload         7
     180: if_icmpge     236
     183: aload         6
     185: iload         8
     187: aaload
     188: astore        9
     190: aload_2
     191: aload         9
     193: invokeinterface #100,  2          // InterfaceMethod java/util/Map.containsKey:(Ljava/lang/Object;)Z
     198: ifeq          217
     201: aload_2
     202: aload         9
     204: invokeinterface #103,  2          // InterfaceMethod java/util/Map.get:(Ljava/lang/Object;)Ljava/lang/Object;
     209: checkcast     #105                // class java/lang/reflect/Type
     212: astore        9
     214: goto          190
     217: aload         5
     219: aload         9
     221: invokestatic  #53                 // Method getClass:(Ljava/lang/reflect/Type;)Ljava/lang/Class;
     224: invokeinterface #108,  2          // InterfaceMethod java/util/List.add:(Ljava/lang/Object;)Z
     229: pop
     230: iinc          8, 1
     233: goto          176
     236: aload         5
     238: areturn

  public java.lang.Object getComponentKey();
    Code:
       0: aload_0
       1: getfield      #37                 // Field key:Ljava/lang/Class;
       4: areturn

  public java.lang.Class<? extends T> getComponentImplementation();
    Code:
       0: aload_0
       1: getfield      #37                 // Field key:Ljava/lang/Class;
       4: areturn

  public void accept(org.sonarsource.sonarlint.shaded.org.picocontainer.PicoVisitor);
    Code:
       0: aload_1
       1: aload_0
       2: invokeinterface #144,  2          // InterfaceMethod org/sonarsource/sonarlint/shaded/org/picocontainer/PicoVisitor.visitComponentAdapter:(Lorg/sonarsource/sonarlint/shaded/org/picocontainer/ComponentAdapter;)V
       7: return

  public org.sonarsource.sonarlint.shaded.org.picocontainer.ComponentAdapter<T> getDelegate();
    Code:
       0: aconst_null
       1: areturn

  public <U extends org.sonarsource.sonarlint.shaded.org.picocontainer.ComponentAdapter> U findAdapterOfType(java.lang.Class<U>);
    Code:
       0: aconst_null
       1: areturn

  public T getComponentInstance(org.sonarsource.sonarlint.shaded.org.picocontainer.PicoContainer);
    Code:
       0: new           #159                // class java/lang/UnsupportedOperationException
       3: dup
       4: invokespecial #160                // Method java/lang/UnsupportedOperationException."<init>":()V
       7: athrow

  public abstract T getComponentInstance(org.sonarsource.sonarlint.shaded.org.picocontainer.PicoContainer, java.lang.reflect.Type);

  public java.lang.Object decorateComponentInstance(org.sonarsource.sonarlint.shaded.org.picocontainer.PicoContainer, java.lang.reflect.Type, T);
    Code:
       0: aconst_null
       1: areturn

  public void verify(org.sonarsource.sonarlint.shaded.org.picocontainer.PicoContainer);
    Code:
       0: return

  public java.lang.String getDescriptor();
    Code:
       0: ldc           #177                // String FactoryInjector-
       2: areturn

  public void start(org.sonarsource.sonarlint.shaded.org.picocontainer.PicoContainer);
    Code:
       0: return

  public void stop(org.sonarsource.sonarlint.shaded.org.picocontainer.PicoContainer);
    Code:
       0: return

  public void dispose(org.sonarsource.sonarlint.shaded.org.picocontainer.PicoContainer);
    Code:
       0: return

  public boolean componentHasLifecycle();
    Code:
       0: iconst_0
       1: ireturn
}
