Compiled from "AbstractAlertCondition.java"
public abstract class org.graylog2.alerts.AbstractAlertCondition implements org.graylog2.plugin.database.EmbeddedPersistable,org.graylog2.plugin.alarms.AlertCondition {
  protected static final java.lang.String CK_QUERY;

  protected static final java.lang.String CK_QUERY_DEFAULT_VALUE;

  protected final java.lang.String id;

  protected final org.graylog2.plugin.streams.Stream stream;

  protected final java.lang.String type;

  protected final org.joda.time.DateTime createdAt;

  protected final java.lang.String creatorUserId;

  protected final int grace;

  protected final int backlog;

  protected final boolean repeatNotifications;

  protected final java.lang.String title;

  private java.util.Map<java.lang.String, java.lang.Object> parameters;

  protected org.graylog2.alerts.AbstractAlertCondition(org.graylog2.plugin.streams.Stream, java.lang.String, java.lang.String, org.joda.time.DateTime, java.lang.String, java.util.Map<java.lang.String, java.lang.Object>, java.lang.String);
    Code:
       0: aload_0
       1: invokespecial #1                  // Method java/lang/Object."<init>":()V
       4: aload_0
       5: aload         7
       7: putfield      #2                  // Field title:Ljava/lang/String;
      10: aload_2
      11: ifnonnull     27
      14: aload_0
      15: invokestatic  #3                  // Method java/util/UUID.randomUUID:()Ljava/util/UUID;
      18: invokevirtual #4                  // Method java/util/UUID.toString:()Ljava/lang/String;
      21: putfield      #5                  // Field id:Ljava/lang/String;
      24: goto          32
      27: aload_0
      28: aload_2
      29: putfield      #5                  // Field id:Ljava/lang/String;
      32: aload_0
      33: aload_1
      34: putfield      #6                  // Field stream:Lorg/graylog2/plugin/streams/Stream;
      37: aload_0
      38: aload_3
      39: putfield      #7                  // Field type:Ljava/lang/String;
      42: aload_0
      43: aload         4
      45: putfield      #8                  // Field createdAt:Lorg/joda/time/DateTime;
      48: aload_0
      49: aload         5
      51: putfield      #9                  // Field creatorUserId:Ljava/lang/String;
      54: aload_0
      55: aload         6
      57: invokestatic  #10                 // Method com/google/common/collect/ImmutableMap.copyOf:(Ljava/util/Map;)Lcom/google/common/collect/ImmutableMap;
      60: putfield      #11                 // Field parameters:Ljava/util/Map;
      63: aload_0
      64: aload_0
      65: getfield      #11                 // Field parameters:Ljava/util/Map;
      68: ldc           #12                 // String grace
      70: invokeinterface #13,  2           // InterfaceMethod java/util/Map.get:(Ljava/lang/Object;)Ljava/lang/Object;
      75: iconst_0
      76: invokestatic  #14                 // Method java/lang/Integer.valueOf:(I)Ljava/lang/Integer;
      79: invokestatic  #15                 // Method org/graylog2/plugin/Tools.getNumber:(Ljava/lang/Object;Ljava/lang/Number;)Ljava/lang/Number;
      82: invokevirtual #16                 // Method java/lang/Number.intValue:()I
      85: putfield      #17                 // Field grace:I
      88: aload_0
      89: aload_0
      90: getfield      #11                 // Field parameters:Ljava/util/Map;
      93: ldc           #18                 // String backlog
      95: invokeinterface #13,  2           // InterfaceMethod java/util/Map.get:(Ljava/lang/Object;)Ljava/lang/Object;
     100: iconst_0
     101: invokestatic  #14                 // Method java/lang/Integer.valueOf:(I)Ljava/lang/Integer;
     104: invokestatic  #15                 // Method org/graylog2/plugin/Tools.getNumber:(Ljava/lang/Object;Ljava/lang/Number;)Ljava/lang/Number;
     107: invokevirtual #16                 // Method java/lang/Number.intValue:()I
     110: putfield      #19                 // Field backlog:I
     113: aload_0
     114: aload_0
     115: getfield      #11                 // Field parameters:Ljava/util/Map;
     118: ldc           #20                 // String repeat_notifications
     120: iconst_0
     121: invokestatic  #21                 // Method java/lang/Boolean.valueOf:(Z)Ljava/lang/Boolean;
     124: invokeinterface #22,  3           // InterfaceMethod java/util/Map.getOrDefault:(Ljava/lang/Object;Ljava/lang/Object;)Ljava/lang/Object;
     129: checkcast     #23                 // class java/lang/Boolean
     132: invokevirtual #24                 // Method java/lang/Boolean.booleanValue:()Z
     135: putfield      #25                 // Field repeatNotifications:Z
     138: return

  public java.lang.String getId();
    Code:
       0: aload_0
       1: getfield      #5                  // Field id:Ljava/lang/String;
       4: areturn

  public java.lang.String getType();
    Code:
       0: aload_0
       1: getfield      #7                  // Field type:Ljava/lang/String;
       4: areturn

  public java.lang.String getTitle();
    Code:
       0: aload_0
       1: getfield      #2                  // Field title:Ljava/lang/String;
       4: areturn

  public org.joda.time.DateTime getCreatedAt();
    Code:
       0: aload_0
       1: getfield      #8                  // Field createdAt:Lorg/joda/time/DateTime;
       4: areturn

  public java.lang.String getCreatorUserId();
    Code:
       0: aload_0
       1: getfield      #9                  // Field creatorUserId:Ljava/lang/String;
       4: areturn

  public org.graylog2.plugin.streams.Stream getStream();
    Code:
       0: aload_0
       1: getfield      #6                  // Field stream:Lorg/graylog2/plugin/streams/Stream;
       4: areturn

  protected void setParameters(java.util.Map<java.lang.String, java.lang.Object>);
    Code:
       0: aload_0
       1: aload_1
       2: invokestatic  #10                 // Method com/google/common/collect/ImmutableMap.copyOf:(Ljava/util/Map;)Lcom/google/common/collect/ImmutableMap;
       5: putfield      #11                 // Field parameters:Ljava/util/Map;
       8: return

  public java.util.Map<java.lang.String, java.lang.Object> getParameters();
    Code:
       0: aload_0
       1: getfield      #11                 // Field parameters:Ljava/util/Map;
       4: areturn

  public java.lang.Integer getBacklog();
    Code:
       0: aload_0
       1: getfield      #19                 // Field backlog:I
       4: invokestatic  #14                 // Method java/lang/Integer.valueOf:(I)Ljava/lang/Integer;
       7: areturn

  public java.lang.String toString();
    Code:
       0: new           #26                 // class java/lang/StringBuilder
       3: dup
       4: invokespecial #27                 // Method java/lang/StringBuilder."<init>":()V
       7: aload_0
       8: getfield      #5                  // Field id:Ljava/lang/String;
      11: invokevirtual #28                 // Method java/lang/StringBuilder.append:(Ljava/lang/String;)Ljava/lang/StringBuilder;
      14: ldc           #29                 // String :
      16: invokevirtual #28                 // Method java/lang/StringBuilder.append:(Ljava/lang/String;)Ljava/lang/StringBuilder;
      19: aload_0
      20: getfield      #7                  // Field type:Ljava/lang/String;
      23: invokevirtual #28                 // Method java/lang/StringBuilder.append:(Ljava/lang/String;)Ljava/lang/StringBuilder;
      26: ldc           #30                 // String ={
      28: invokevirtual #28                 // Method java/lang/StringBuilder.append:(Ljava/lang/String;)Ljava/lang/StringBuilder;
      31: aload_0
      32: invokevirtual #31                 // Method getDescription:()Ljava/lang/String;
      35: invokevirtual #28                 // Method java/lang/StringBuilder.append:(Ljava/lang/String;)Ljava/lang/StringBuilder;
      38: ldc           #32                 // String }, stream:={
      40: invokevirtual #28                 // Method java/lang/StringBuilder.append:(Ljava/lang/String;)Ljava/lang/StringBuilder;
      43: aload_0
      44: getfield      #6                  // Field stream:Lorg/graylog2/plugin/streams/Stream;
      47: invokevirtual #33                 // Method java/lang/StringBuilder.append:(Ljava/lang/Object;)Ljava/lang/StringBuilder;
      50: ldc           #34                 // String }
      52: invokevirtual #28                 // Method java/lang/StringBuilder.append:(Ljava/lang/String;)Ljava/lang/StringBuilder;
      55: invokevirtual #35                 // Method java/lang/StringBuilder.toString:()Ljava/lang/String;
      58: areturn

  public java.util.Map<java.lang.String, java.lang.Object> getPersistedFields();
    Code:
       0: invokestatic  #36                 // Method com/google/common/collect/ImmutableMap.builder:()Lcom/google/common/collect/ImmutableMap$Builder;
       3: ldc           #37                 // String id
       5: aload_0
       6: getfield      #5                  // Field id:Ljava/lang/String;
       9: invokevirtual #38                 // Method com/google/common/collect/ImmutableMap$Builder.put:(Ljava/lang/Object;Ljava/lang/Object;)Lcom/google/common/collect/ImmutableMap$Builder;
      12: ldc           #39                 // String type
      14: aload_0
      15: getfield      #7                  // Field type:Ljava/lang/String;
      18: invokevirtual #38                 // Method com/google/common/collect/ImmutableMap$Builder.put:(Ljava/lang/Object;Ljava/lang/Object;)Lcom/google/common/collect/ImmutableMap$Builder;
      21: ldc           #40                 // String creator_user_id
      23: aload_0
      24: getfield      #9                  // Field creatorUserId:Ljava/lang/String;
      27: invokevirtual #38                 // Method com/google/common/collect/ImmutableMap$Builder.put:(Ljava/lang/Object;Ljava/lang/Object;)Lcom/google/common/collect/ImmutableMap$Builder;
      30: ldc           #41                 // String created_at
      32: aload_0
      33: getfield      #8                  // Field createdAt:Lorg/joda/time/DateTime;
      36: invokestatic  #42                 // Method org/graylog2/plugin/Tools.getISO8601String:(Lorg/joda/time/DateTime;)Ljava/lang/String;
      39: invokevirtual #38                 // Method com/google/common/collect/ImmutableMap$Builder.put:(Ljava/lang/Object;Ljava/lang/Object;)Lcom/google/common/collect/ImmutableMap$Builder;
      42: ldc           #43                 // String parameters
      44: aload_0
      45: getfield      #11                 // Field parameters:Ljava/util/Map;
      48: invokevirtual #38                 // Method com/google/common/collect/ImmutableMap$Builder.put:(Ljava/lang/Object;Ljava/lang/Object;)Lcom/google/common/collect/ImmutableMap$Builder;
      51: ldc           #44                 // String title
      53: aload_0
      54: getfield      #2                  // Field title:Ljava/lang/String;
      57: invokevirtual #38                 // Method com/google/common/collect/ImmutableMap$Builder.put:(Ljava/lang/Object;Ljava/lang/Object;)Lcom/google/common/collect/ImmutableMap$Builder;
      60: invokevirtual #45                 // Method com/google/common/collect/ImmutableMap$Builder.build:()Lcom/google/common/collect/ImmutableMap;
      63: areturn

  public int getGrace();
    Code:
       0: aload_0
       1: getfield      #17                 // Field grace:I
       4: ireturn

  public boolean shouldRepeatNotifications();
    Code:
       0: aload_0
       1: getfield      #25                 // Field repeatNotifications:Z
       4: ireturn

  protected java.lang.String buildQueryFilter(java.lang.String, java.lang.String);
    Code:
       0: aload_1
       1: ifnull        8
       4: iconst_1
       5: goto          9
       8: iconst_0
       9: ldc           #46                 // String streamId parameter cannot be null
      11: invokestatic  #47                 // Method com/google/common/base/Preconditions.checkArgument:(ZLjava/lang/Object;)V
      14: aload_1
      15: invokevirtual #48                 // Method java/lang/String.trim:()Ljava/lang/String;
      18: astore_3
      19: aload_3
      20: invokevirtual #49                 // Method java/lang/String.isEmpty:()Z
      23: ifne          30
      26: iconst_1
      27: goto          31
      30: iconst_0
      31: ldc           #50                 // String streamId parameter cannot be empty
      33: invokestatic  #47                 // Method com/google/common/base/Preconditions.checkArgument:(ZLjava/lang/Object;)V
      36: new           #26                 // class java/lang/StringBuilder
      39: dup
      40: invokespecial #27                 // Method java/lang/StringBuilder."<init>":()V
      43: ldc           #51                 // String streams:
      45: invokevirtual #28                 // Method java/lang/StringBuilder.append:(Ljava/lang/String;)Ljava/lang/StringBuilder;
      48: aload_3
      49: invokevirtual #28                 // Method java/lang/StringBuilder.append:(Ljava/lang/String;)Ljava/lang/StringBuilder;
      52: astore        4
      54: aload_2
      55: ifnull        100
      58: aload_2
      59: invokevirtual #48                 // Method java/lang/String.trim:()Ljava/lang/String;
      62: astore        5
      64: aload         5
      66: invokevirtual #49                 // Method java/lang/String.isEmpty:()Z
      69: ifne          100
      72: ldc           #52                 // String *
      74: aload         5
      76: invokevirtual #53                 // Method java/lang/String.equals:(Ljava/lang/Object;)Z
      79: ifne          100
      82: aload         4
      84: ldc           #54                 // String  AND (
      86: invokevirtual #28                 // Method java/lang/StringBuilder.append:(Ljava/lang/String;)Ljava/lang/StringBuilder;
      89: aload         5
      91: invokevirtual #28                 // Method java/lang/StringBuilder.append:(Ljava/lang/String;)Ljava/lang/StringBuilder;
      94: ldc           #55                 // String )
      96: invokevirtual #28                 // Method java/lang/StringBuilder.append:(Ljava/lang/String;)Ljava/lang/StringBuilder;
      99: pop
     100: aload         4
     102: invokevirtual #35                 // Method java/lang/StringBuilder.toString:()Ljava/lang/String;
     105: areturn

  public static java.util.List<org.graylog2.plugin.configuration.fields.ConfigurationField> getDefaultConfigurationFields();
    Code:
       0: iconst_4
       1: anewarray     #56                 // class org/graylog2/plugin/configuration/fields/ConfigurationField
       4: dup
       5: iconst_0
       6: new           #57                 // class org/graylog2/plugin/configuration/fields/TextField
       9: dup
      10: ldc           #59                 // String query
      12: ldc           #60                 // String Search Query
      14: ldc           #52                 // String *
      16: ldc           #61                 // String Query string that should be used to filter messages in the stream
      18: getstatic     #62                 // Field org/graylog2/plugin/configuration/fields/ConfigurationField$Optional.OPTIONAL:Lorg/graylog2/plugin/configuration/fields/ConfigurationField$Optional;
      21: invokespecial #63                 // Method org/graylog2/plugin/configuration/fields/TextField."<init>":(Ljava/lang/String;Ljava/lang/String;Ljava/lang/String;Ljava/lang/String;Lorg/graylog2/plugin/configuration/fields/ConfigurationField$Optional;)V
      24: aastore
      25: dup
      26: iconst_1
      27: new           #64                 // class org/graylog2/plugin/configuration/fields/NumberField
      30: dup
      31: ldc           #12                 // String grace
      33: ldc           #65                 // String Grace Period
      35: iconst_0
      36: ldc           #66                 // String Number of minutes to wait after an alert is resolved, to trigger another alert
      38: getstatic     #67                 // Field org/graylog2/plugin/configuration/fields/ConfigurationField$Optional.NOT_OPTIONAL:Lorg/graylog2/plugin/configuration/fields/ConfigurationField$Optional;
      41: invokespecial #68                 // Method org/graylog2/plugin/configuration/fields/NumberField."<init>":(Ljava/lang/String;Ljava/lang/String;ILjava/lang/String;Lorg/graylog2/plugin/configuration/fields/ConfigurationField$Optional;)V
      44: aastore
      45: dup
      46: iconst_2
      47: new           #64                 // class org/graylog2/plugin/configuration/fields/NumberField
      50: dup
      51: ldc           #18                 // String backlog
      53: ldc           #69                 // String Message Backlog
      55: iconst_0
      56: ldc           #70                 // String The number of messages to be included in alert notifications
      58: getstatic     #67                 // Field org/graylog2/plugin/configuration/fields/ConfigurationField$Optional.NOT_OPTIONAL:Lorg/graylog2/plugin/configuration/fields/ConfigurationField$Optional;
      61: invokespecial #68                 // Method org/graylog2/plugin/configuration/fields/NumberField."<init>":(Ljava/lang/String;Ljava/lang/String;ILjava/lang/String;Lorg/graylog2/plugin/configuration/fields/ConfigurationField$Optional;)V
      64: aastore
      65: dup
      66: iconst_3
      67: new           #71                 // class org/graylog2/plugin/configuration/fields/BooleanField
      70: dup
      71: ldc           #20                 // String repeat_notifications
      73: ldc           #72                 // String Repeat notifications
      75: iconst_0
      76: ldc           #73                 // String Check this box to send notifications every time the alert condition is evaluated and satisfied regardless of its state.
      78: invokespecial #74                 // Method org/graylog2/plugin/configuration/fields/BooleanField."<init>":(Ljava/lang/String;Ljava/lang/String;ZLjava/lang/String;)V
      81: aastore
      82: invokestatic  #75                 // Method com/google/common/collect/Lists.newArrayList:([Ljava/lang/Object;)Ljava/util/ArrayList;
      85: areturn
}
