Compiled from "AbstractAlertCondition.java"
public class org.graylog2.alerts.AbstractAlertCondition$NegativeCheckResult extends org.graylog2.alerts.AbstractAlertCondition$CheckResult {
  public org.graylog2.alerts.AbstractAlertCondition$NegativeCheckResult();
    Code:
       0: aload_0
       1: iconst_0
       2: aconst_null
       3: aconst_null
       4: aconst_null
       5: aconst_null
       6: invokespecial #1                  // Method org/graylog2/alerts/AbstractAlertCondition$CheckResult."<init>":(ZLorg/graylog2/plugin/alarms/AlertCondition;Ljava/lang/String;Lorg/joda/time/DateTime;Ljava/util/List;)V
       9: return
}
