Compiled from "CometdEvent.java"
public class org.wicketstuff.push.cometd.CometdEvent extends org.wicketstuff.push.ChannelEvent {
  public org.wicketstuff.push.cometd.CometdEvent(java.lang.String);
    Code:
       0: aload_0
       1: aload_1
       2: invokespecial #1                  // Method org/wicketstuff/push/ChannelEvent."<init>":(Ljava/lang/String;)V
       5: return

  public final java.util.Map<java.lang.String, java.lang.String> getData();
    Code:
       0: aload_0
       1: ldc           #2                  // String proxy
       3: ldc           #3                  // String true
       5: invokevirtual #4                  // Method addData:(Ljava/lang/String;Ljava/lang/String;)V
       8: aload_0
       9: invokespecial #5                  // Method org/wicketstuff/push/ChannelEvent.getData:()Ljava/util/Map;
      12: areturn
}
