Compiled from "S3ControlEndpointParams.java"
public final class software.amazon.awssdk.services.s3control.endpoints.S3ControlEndpointParams {
  private final software.amazon.awssdk.regions.Region region;

  private final java.lang.Boolean useFIPS;

  private final java.lang.Boolean useDualStack;

  private final java.lang.String endpoint;

  private final java.lang.String accountId;

  private final java.lang.Boolean requiresAccountId;

  private final java.lang.String outpostId;

  private final java.lang.String bucket;

  private final java.lang.String accessPointName;

  private final java.lang.Boolean useArnRegion;

  private software.amazon.awssdk.services.s3control.endpoints.S3ControlEndpointParams(software.amazon.awssdk.services.s3control.endpoints.S3ControlEndpointParams$BuilderImpl);
    Code:
       0: aload_0
       1: invokespecial #2                  // Method java/lang/Object."<init>":()V
       4: aload_0
       5: aload_1
       6: invokestatic  #3                  // Method software/amazon/awssdk/services/s3control/endpoints/S3ControlEndpointParams$BuilderImpl.access$000:(Lsoftware/amazon/awssdk/services/s3control/endpoints/S3ControlEndpointParams$BuilderImpl;)Lsoftware/amazon/awssdk/regions/Region;
       9: putfield      #4                  // Field region:Lsoftware/amazon/awssdk/regions/Region;
      12: aload_0
      13: aload_1
      14: invokestatic  #5                  // Method software/amazon/awssdk/services/s3control/endpoints/S3ControlEndpointParams$BuilderImpl.access$100:(Lsoftware/amazon/awssdk/services/s3control/endpoints/S3ControlEndpointParams$BuilderImpl;)Ljava/lang/Boolean;
      17: putfield      #6                  // Field useFIPS:Ljava/lang/Boolean;
      20: aload_0
      21: aload_1
      22: invokestatic  #7                  // Method software/amazon/awssdk/services/s3control/endpoints/S3ControlEndpointParams$BuilderImpl.access$200:(Lsoftware/amazon/awssdk/services/s3control/endpoints/S3ControlEndpointParams$BuilderImpl;)Ljava/lang/Boolean;
      25: putfield      #8                  // Field useDualStack:Ljava/lang/Boolean;
      28: aload_0
      29: aload_1
      30: invokestatic  #9                  // Method software/amazon/awssdk/services/s3control/endpoints/S3ControlEndpointParams$BuilderImpl.access$300:(Lsoftware/amazon/awssdk/services/s3control/endpoints/S3ControlEndpointParams$BuilderImpl;)Ljava/lang/String;
      33: putfield      #10                 // Field endpoint:Ljava/lang/String;
      36: aload_0
      37: aload_1
      38: invokestatic  #11                 // Method software/amazon/awssdk/services/s3control/endpoints/S3ControlEndpointParams$BuilderImpl.access$400:(Lsoftware/amazon/awssdk/services/s3control/endpoints/S3ControlEndpointParams$BuilderImpl;)Ljava/lang/String;
      41: putfield      #12                 // Field accountId:Ljava/lang/String;
      44: aload_0
      45: aload_1
      46: invokestatic  #13                 // Method software/amazon/awssdk/services/s3control/endpoints/S3ControlEndpointParams$BuilderImpl.access$500:(Lsoftware/amazon/awssdk/services/s3control/endpoints/S3ControlEndpointParams$BuilderImpl;)Ljava/lang/Boolean;
      49: putfield      #14                 // Field requiresAccountId:Ljava/lang/Boolean;
      52: aload_0
      53: aload_1
      54: invokestatic  #15                 // Method software/amazon/awssdk/services/s3control/endpoints/S3ControlEndpointParams$BuilderImpl.access$600:(Lsoftware/amazon/awssdk/services/s3control/endpoints/S3ControlEndpointParams$BuilderImpl;)Ljava/lang/String;
      57: putfield      #16                 // Field outpostId:Ljava/lang/String;
      60: aload_0
      61: aload_1
      62: invokestatic  #17                 // Method software/amazon/awssdk/services/s3control/endpoints/S3ControlEndpointParams$BuilderImpl.access$700:(Lsoftware/amazon/awssdk/services/s3control/endpoints/S3ControlEndpointParams$BuilderImpl;)Ljava/lang/String;
      65: putfield      #18                 // Field bucket:Ljava/lang/String;
      68: aload_0
      69: aload_1
      70: invokestatic  #19                 // Method software/amazon/awssdk/services/s3control/endpoints/S3ControlEndpointParams$BuilderImpl.access$800:(Lsoftware/amazon/awssdk/services/s3control/endpoints/S3ControlEndpointParams$BuilderImpl;)Ljava/lang/String;
      73: putfield      #20                 // Field accessPointName:Ljava/lang/String;
      76: aload_0
      77: aload_1
      78: invokestatic  #21                 // Method software/amazon/awssdk/services/s3control/endpoints/S3ControlEndpointParams$BuilderImpl.access$900:(Lsoftware/amazon/awssdk/services/s3control/endpoints/S3ControlEndpointParams$BuilderImpl;)Ljava/lang/Boolean;
      81: putfield      #22                 // Field useArnRegion:Ljava/lang/Boolean;
      84: return

  public static software.amazon.awssdk.services.s3control.endpoints.S3ControlEndpointParams$Builder builder();
    Code:
       0: new           #23                 // class software/amazon/awssdk/services/s3control/endpoints/S3ControlEndpointParams$BuilderImpl
       3: dup
       4: aconst_null
       5: invokespecial #24                 // Method software/amazon/awssdk/services/s3control/endpoints/S3ControlEndpointParams$BuilderImpl."<init>":(Lsoftware/amazon/awssdk/services/s3control/endpoints/S3ControlEndpointParams$1;)V
       8: areturn

  public software.amazon.awssdk.regions.Region region();
    Code:
       0: aload_0
       1: getfield      #4                  // Field region:Lsoftware/amazon/awssdk/regions/Region;
       4: areturn

  public java.lang.Boolean useFips();
    Code:
       0: aload_0
       1: getfield      #6                  // Field useFIPS:Ljava/lang/Boolean;
       4: areturn

  public java.lang.Boolean useDualStack();
    Code:
       0: aload_0
       1: getfield      #8                  // Field useDualStack:Ljava/lang/Boolean;
       4: areturn

  public java.lang.String endpoint();
    Code:
       0: aload_0
       1: getfield      #10                 // Field endpoint:Ljava/lang/String;
       4: areturn

  public java.lang.String accountId();
    Code:
       0: aload_0
       1: getfield      #12                 // Field accountId:Ljava/lang/String;
       4: areturn

  public java.lang.Boolean requiresAccountId();
    Code:
       0: aload_0
       1: getfield      #14                 // Field requiresAccountId:Ljava/lang/Boolean;
       4: areturn

  public java.lang.String outpostId();
    Code:
       0: aload_0
       1: getfield      #16                 // Field outpostId:Ljava/lang/String;
       4: areturn

  public java.lang.String bucket();
    Code:
       0: aload_0
       1: getfield      #18                 // Field bucket:Ljava/lang/String;
       4: areturn

  public java.lang.String accessPointName();
    Code:
       0: aload_0
       1: getfield      #20                 // Field accessPointName:Ljava/lang/String;
       4: areturn

  public java.lang.Boolean useArnRegion();
    Code:
       0: aload_0
       1: getfield      #22                 // Field useArnRegion:Ljava/lang/Boolean;
       4: areturn

  software.amazon.awssdk.services.s3control.endpoints.S3ControlEndpointParams(software.amazon.awssdk.services.s3control.endpoints.S3ControlEndpointParams$BuilderImpl, software.amazon.awssdk.services.s3control.endpoints.S3ControlEndpointParams$1);
    Code:
       0: aload_0
       1: aload_1
       2: invokespecial #1                  // Method "<init>":(Lsoftware/amazon/awssdk/services/s3control/endpoints/S3ControlEndpointParams$BuilderImpl;)V
       5: return
}
