Compiled from "ChannelMatchers.java"
final class io.netty.channel.group.ChannelMatchers$InvertMatcher implements io.netty.channel.group.ChannelMatcher {
  private final io.netty.channel.group.ChannelMatcher matcher;

  io.netty.channel.group.ChannelMatchers$InvertMatcher(io.netty.channel.group.ChannelMatcher);
    Code:
       0: aload_0
       1: invokespecial #1                  // Method java/lang/Object."<init>":()V
       4: aload_0
       5: aload_1
       6: putfield      #2                  // Field matcher:Lio/netty/channel/group/ChannelMatcher;
       9: return

  public boolean matches(io.netty.channel.Channel);
    Code:
       0: aload_0
       1: getfield      #2                  // Field matcher:Lio/netty/channel/group/ChannelMatcher;
       4: aload_1
       5: invokeinterface #3,  2            // InterfaceMethod io/netty/channel/group/ChannelMatcher.matches:(Lio/netty/channel/Channel;)Z
      10: ifne          17
      13: iconst_1
      14: goto          18
      17: iconst_0
      18: ireturn
}
