Compiled from "CompanionObjectMappingUtils.kt"
public final class kotlin.reflect.jvm.internal.impl.builtins.CompanionObjectMappingUtilsKt {
  public static final boolean isMappedIntrinsicCompanionObject(kotlin.reflect.jvm.internal.impl.builtins.CompanionObjectMapping, kotlin.reflect.jvm.internal.impl.descriptors.ClassDescriptor);
    Code:
       0: aload_0
       1: ldc           #1                  // String <this>
       3: invokestatic  #16                 // Method kotlin/jvm/internal/Intrinsics.checkNotNullParameter:(Ljava/lang/Object;Ljava/lang/String;)V
       6: aload_1
       7: ldc           #2                  // String classDescriptor
       9: invokestatic  #16                 // Method kotlin/jvm/internal/Intrinsics.checkNotNullParameter:(Ljava/lang/Object;Ljava/lang/String;)V
      12: aload_1
      13: checkcast     #11                 // class kotlin/reflect/jvm/internal/impl/descriptors/DeclarationDescriptor
      16: invokestatic  #19                 // Method kotlin/reflect/jvm/internal/impl/resolve/DescriptorUtils.isCompanionObject:(Lkotlin/reflect/jvm/internal/impl/descriptors/DeclarationDescriptor;)Z
      19: ifeq          58
      22: aload_0
      23: invokevirtual #17                 // Method kotlin/reflect/jvm/internal/impl/builtins/CompanionObjectMapping.getClassIds:()Ljava/util/Set;
      26: checkcast     #3                  // class java/lang/Iterable
      29: aload_1
      30: checkcast     #10                 // class kotlin/reflect/jvm/internal/impl/descriptors/ClassifierDescriptor
      33: invokestatic  #20                 // Method kotlin/reflect/jvm/internal/impl/resolve/descriptorUtil/DescriptorUtilsKt.getClassId:(Lkotlin/reflect/jvm/internal/impl/descriptors/ClassifierDescriptor;)Lkotlin/reflect/jvm/internal/impl/name/ClassId;
      36: dup
      37: ifnull        46
      40: invokevirtual #18                 // Method kotlin/reflect/jvm/internal/impl/name/ClassId.getOuterClassId:()Lkotlin/reflect/jvm/internal/impl/name/ClassId;
      43: goto          48
      46: pop
      47: aconst_null
      48: invokestatic  #15                 // Method kotlin/collections/CollectionsKt.contains:(Ljava/lang/Iterable;Ljava/lang/Object;)Z
      51: ifeq          58
      54: iconst_1
      55: goto          59
      58: iconst_0
      59: ireturn
}
