Compiled from "CClassNode.java"
class org.joni.ast.CClassNode$1 {
  static final int[] $SwitchMap$org$joni$constants$CCSTATE;

  static {};
    Code:
       0: invokestatic  #1                  // Method org/joni/constants/CCSTATE.values:()[Lorg/joni/constants/CCSTATE;
       3: arraylength
       4: newarray       int
       6: putstatic     #2                  // Field $SwitchMap$org$joni$constants$CCSTATE:[I
       9: getstatic     #2                  // Field $SwitchMap$org$joni$constants$CCSTATE:[I
      12: getstatic     #3                  // Field org/joni/constants/CCSTATE.VALUE:Lorg/joni/constants/CCSTATE;
      15: invokevirtual #4                  // Method org/joni/constants/CCSTATE.ordinal:()I
      18: iconst_1
      19: iastore
      20: goto          24
      23: astore_0
      24: getstatic     #2                  // Field $SwitchMap$org$joni$constants$CCSTATE:[I
      27: getstatic     #6                  // Field org/joni/constants/CCSTATE.RANGE:Lorg/joni/constants/CCSTATE;
      30: invokevirtual #4                  // Method org/joni/constants/CCSTATE.ordinal:()I
      33: iconst_2
      34: iastore
      35: goto          39
      38: astore_0
      39: getstatic     #2                  // Field $SwitchMap$org$joni$constants$CCSTATE:[I
      42: getstatic     #7                  // Field org/joni/constants/CCSTATE.COMPLETE:Lorg/joni/constants/CCSTATE;
      45: invokevirtual #4                  // Method org/joni/constants/CCSTATE.ordinal:()I
      48: iconst_3
      49: iastore
      50: goto          54
      53: astore_0
      54: getstatic     #2                  // Field $SwitchMap$org$joni$constants$CCSTATE:[I
      57: getstatic     #8                  // Field org/joni/constants/CCSTATE.START:Lorg/joni/constants/CCSTATE;
      60: invokevirtual #4                  // Method org/joni/constants/CCSTATE.ordinal:()I
      63: iconst_4
      64: iastore
      65: goto          69
      68: astore_0
      69: return
    Exception table:
       from    to  target type
           9    20    23   Class java/lang/NoSuchFieldError
          24    35    38   Class java/lang/NoSuchFieldError
          39    50    53   Class java/lang/NoSuchFieldError
          54    65    68   Class java/lang/NoSuchFieldError
}
