Compiled from "TailCalls.scala"
public abstract class scala.util.control.TailCalls$TailRec<A> {
  public final <B> scala.util.control.TailCalls$TailRec<B> map(scala.Function1<A, B>);
    Code:
       0: new           #10                 // class scala/util/control/TailCalls$TailRec$$anonfun$map$1
       3: dup
       4: aload_0
       5: aload_1
       6: invokespecial #14                 // Method scala/util/control/TailCalls$TailRec$$anonfun$map$1."<init>":(Lscala/util/control/TailCalls$TailRec;Lscala/Function1;)V
       9: astore        4
      11: aload_0
      12: instanceof    #16                 // class scala/util/control/TailCalls$Done
      15: ifeq          46
      18: aload_0
      19: checkcast     #16                 // class scala/util/control/TailCalls$Done
      22: astore_2
      23: new           #18                 // class scala/util/control/TailCalls$Call
      26: dup
      27: new           #20                 // class scala/util/control/TailCalls$TailRec$$anonfun$flatMap$1
      30: dup
      31: aload_0
      32: aload         4
      34: aload_2
      35: invokespecial #23                 // Method scala/util/control/TailCalls$TailRec$$anonfun$flatMap$1."<init>":(Lscala/util/control/TailCalls$TailRec;Lscala/Function1;Lscala/util/control/TailCalls$Done;)V
      38: invokespecial #26                 // Method scala/util/control/TailCalls$Call."<init>":(Lscala/Function0;)V
      41: astore        6
      43: goto          112
      46: aload_0
      47: instanceof    #18                 // class scala/util/control/TailCalls$Call
      50: ifeq          73
      53: aload_0
      54: checkcast     #18                 // class scala/util/control/TailCalls$Call
      57: astore_3
      58: new           #28                 // class scala/util/control/TailCalls$Cont
      61: dup
      62: aload_3
      63: aload         4
      65: invokespecial #29                 // Method scala/util/control/TailCalls$Cont."<init>":(Lscala/util/control/TailCalls$TailRec;Lscala/Function1;)V
      68: astore        6
      70: goto          112
      73: aload_0
      74: instanceof    #28                 // class scala/util/control/TailCalls$Cont
      77: ifeq          115
      80: aload_0
      81: checkcast     #28                 // class scala/util/control/TailCalls$Cont
      84: astore        5
      86: new           #28                 // class scala/util/control/TailCalls$Cont
      89: dup
      90: aload         5
      92: invokevirtual #33                 // Method scala/util/control/TailCalls$Cont.a:()Lscala/util/control/TailCalls$TailRec;
      95: new           #35                 // class scala/util/control/TailCalls$TailRec$$anonfun$flatMap$2
      98: dup
      99: aload_0
     100: aload         4
     102: aload         5
     104: invokespecial #38                 // Method scala/util/control/TailCalls$TailRec$$anonfun$flatMap$2."<init>":(Lscala/util/control/TailCalls$TailRec;Lscala/Function1;Lscala/util/control/TailCalls$Cont;)V
     107: invokespecial #29                 // Method scala/util/control/TailCalls$Cont."<init>":(Lscala/util/control/TailCalls$TailRec;Lscala/Function1;)V
     110: astore        6
     112: aload         6
     114: areturn
     115: new           #40                 // class scala/MatchError
     118: dup
     119: aload_0
     120: invokespecial #43                 // Method scala/MatchError."<init>":(Ljava/lang/Object;)V
     123: athrow

  public final <B> scala.util.control.TailCalls$TailRec<B> flatMap(scala.Function1<A, scala.util.control.TailCalls$TailRec<B>>);
    Code:
       0: aload_0
       1: instanceof    #16                 // class scala/util/control/TailCalls$Done
       4: ifeq          34
       7: aload_0
       8: checkcast     #16                 // class scala/util/control/TailCalls$Done
      11: astore_2
      12: new           #18                 // class scala/util/control/TailCalls$Call
      15: dup
      16: new           #20                 // class scala/util/control/TailCalls$TailRec$$anonfun$flatMap$1
      19: dup
      20: aload_0
      21: aload_1
      22: aload_2
      23: invokespecial #23                 // Method scala/util/control/TailCalls$TailRec$$anonfun$flatMap$1."<init>":(Lscala/util/control/TailCalls$TailRec;Lscala/Function1;Lscala/util/control/TailCalls$Done;)V
      26: invokespecial #26                 // Method scala/util/control/TailCalls$Call."<init>":(Lscala/Function0;)V
      29: astore        5
      31: goto          98
      34: aload_0
      35: instanceof    #18                 // class scala/util/control/TailCalls$Call
      38: ifeq          60
      41: aload_0
      42: checkcast     #18                 // class scala/util/control/TailCalls$Call
      45: astore_3
      46: new           #28                 // class scala/util/control/TailCalls$Cont
      49: dup
      50: aload_3
      51: aload_1
      52: invokespecial #29                 // Method scala/util/control/TailCalls$Cont."<init>":(Lscala/util/control/TailCalls$TailRec;Lscala/Function1;)V
      55: astore        5
      57: goto          98
      60: aload_0
      61: instanceof    #28                 // class scala/util/control/TailCalls$Cont
      64: ifeq          101
      67: aload_0
      68: checkcast     #28                 // class scala/util/control/TailCalls$Cont
      71: astore        4
      73: new           #28                 // class scala/util/control/TailCalls$Cont
      76: dup
      77: aload         4
      79: invokevirtual #33                 // Method scala/util/control/TailCalls$Cont.a:()Lscala/util/control/TailCalls$TailRec;
      82: new           #35                 // class scala/util/control/TailCalls$TailRec$$anonfun$flatMap$2
      85: dup
      86: aload_0
      87: aload_1
      88: aload         4
      90: invokespecial #38                 // Method scala/util/control/TailCalls$TailRec$$anonfun$flatMap$2."<init>":(Lscala/util/control/TailCalls$TailRec;Lscala/Function1;Lscala/util/control/TailCalls$Cont;)V
      93: invokespecial #29                 // Method scala/util/control/TailCalls$Cont."<init>":(Lscala/util/control/TailCalls$TailRec;Lscala/Function1;)V
      96: astore        5
      98: aload         5
     100: areturn
     101: new           #40                 // class scala/MatchError
     104: dup
     105: aload_0
     106: invokespecial #43                 // Method scala/MatchError."<init>":(Ljava/lang/Object;)V
     109: athrow

  public final scala.util.Either<scala.Function0<scala.util.control.TailCalls$TailRec<A>>, A> resume();
    Code:
       0: aload_0
       1: instanceof    #16                 // class scala/util/control/TailCalls$Done
       4: ifeq          34
       7: aload_0
       8: checkcast     #16                 // class scala/util/control/TailCalls$Done
      11: astore_1
      12: getstatic     #64                 // Field scala/package$.MODULE$:Lscala/package$;
      15: pop
      16: aload_1
      17: invokevirtual #68                 // Method scala/util/control/TailCalls$Done.value:()Ljava/lang/Object;
      20: astore_2
      21: new           #70                 // class scala/util/Right
      24: dup
      25: aload_2
      26: invokespecial #71                 // Method scala/util/Right."<init>":(Ljava/lang/Object;)V
      29: astore        8
      31: goto          171
      34: aload_0
      35: instanceof    #18                 // class scala/util/control/TailCalls$Call
      38: ifeq          70
      41: aload_0
      42: checkcast     #18                 // class scala/util/control/TailCalls$Call
      45: astore_3
      46: getstatic     #64                 // Field scala/package$.MODULE$:Lscala/package$;
      49: pop
      50: aload_3
      51: invokevirtual #75                 // Method scala/util/control/TailCalls$Call.rest:()Lscala/Function0;
      54: astore        4
      56: new           #77                 // class scala/util/Left
      59: dup
      60: aload         4
      62: invokespecial #78                 // Method scala/util/Left."<init>":(Ljava/lang/Object;)V
      65: astore        8
      67: goto          171
      70: aload_0
      71: instanceof    #28                 // class scala/util/control/TailCalls$Cont
      74: ifeq          349
      77: aload_0
      78: checkcast     #28                 // class scala/util/control/TailCalls$Cont
      81: astore        10
      83: aload         10
      85: invokevirtual #33                 // Method scala/util/control/TailCalls$Cont.a:()Lscala/util/control/TailCalls$TailRec;
      88: astore        17
      90: aload         17
      92: instanceof    #16                 // class scala/util/control/TailCalls$Done
      95: ifeq          127
      98: aload         17
     100: checkcast     #16                 // class scala/util/control/TailCalls$Done
     103: astore        5
     105: aload         10
     107: invokevirtual #81                 // Method scala/util/control/TailCalls$Cont.f:()Lscala/Function1;
     110: aload         5
     112: invokevirtual #68                 // Method scala/util/control/TailCalls$Done.value:()Ljava/lang/Object;
     115: invokeinterface #85,  2           // InterfaceMethod scala/Function1.apply:(Ljava/lang/Object;)Ljava/lang/Object;
     120: checkcast     #2                  // class scala/util/control/TailCalls$TailRec
     123: astore_0
     124: goto          0
     127: aload         17
     129: instanceof    #18                 // class scala/util/control/TailCalls$Call
     132: ifeq          174
     135: aload         17
     137: checkcast     #18                 // class scala/util/control/TailCalls$Call
     140: astore        6
     142: getstatic     #64                 // Field scala/package$.MODULE$:Lscala/package$;
     145: pop
     146: new           #87                 // class scala/util/control/TailCalls$TailRec$$anonfun$resume$1
     149: dup
     150: aload_0
     151: aload         6
     153: aload         10
     155: invokespecial #90                 // Method scala/util/control/TailCalls$TailRec$$anonfun$resume$1."<init>":(Lscala/util/control/TailCalls$TailRec;Lscala/util/control/TailCalls$Call;Lscala/util/control/TailCalls$Cont;)V
     158: astore        7
     160: new           #77                 // class scala/util/Left
     163: dup
     164: aload         7
     166: invokespecial #78                 // Method scala/util/Left."<init>":(Ljava/lang/Object;)V
     169: astore        8
     171: aload         8
     173: areturn
     174: aload         17
     176: instanceof    #28                 // class scala/util/control/TailCalls$Cont
     179: ifeq          339
     182: aload         17
     184: checkcast     #28                 // class scala/util/control/TailCalls$Cont
     187: astore        9
     189: aload         9
     191: invokevirtual #33                 // Method scala/util/control/TailCalls$Cont.a:()Lscala/util/control/TailCalls$TailRec;
     194: new           #92                 // class scala/util/control/TailCalls$TailRec$$anonfun$resume$2
     197: dup
     198: aload_0
     199: aload         9
     201: aload         10
     203: invokespecial #95                 // Method scala/util/control/TailCalls$TailRec$$anonfun$resume$2."<init>":(Lscala/util/control/TailCalls$TailRec;Lscala/util/control/TailCalls$Cont;Lscala/util/control/TailCalls$Cont;)V
     206: astore        13
     208: astore        16
     210: aload         16
     212: instanceof    #16                 // class scala/util/control/TailCalls$Done
     215: ifeq          250
     218: aload         16
     220: checkcast     #16                 // class scala/util/control/TailCalls$Done
     223: astore        11
     225: new           #18                 // class scala/util/control/TailCalls$Call
     228: dup
     229: new           #20                 // class scala/util/control/TailCalls$TailRec$$anonfun$flatMap$1
     232: dup
     233: aload         16
     235: aload         13
     237: aload         11
     239: invokespecial #23                 // Method scala/util/control/TailCalls$TailRec$$anonfun$flatMap$1."<init>":(Lscala/util/control/TailCalls$TailRec;Lscala/Function1;Lscala/util/control/TailCalls$Done;)V
     242: invokespecial #26                 // Method scala/util/control/TailCalls$Call."<init>":(Lscala/Function0;)V
     245: astore        15
     247: goto          323
     250: aload         16
     252: instanceof    #18                 // class scala/util/control/TailCalls$Call
     255: ifeq          281
     258: aload         16
     260: checkcast     #18                 // class scala/util/control/TailCalls$Call
     263: astore        12
     265: new           #28                 // class scala/util/control/TailCalls$Cont
     268: dup
     269: aload         12
     271: aload         13
     273: invokespecial #29                 // Method scala/util/control/TailCalls$Cont."<init>":(Lscala/util/control/TailCalls$TailRec;Lscala/Function1;)V
     276: astore        15
     278: goto          323
     281: aload         16
     283: instanceof    #28                 // class scala/util/control/TailCalls$Cont
     286: ifeq          329
     289: aload         16
     291: checkcast     #28                 // class scala/util/control/TailCalls$Cont
     294: astore        14
     296: new           #28                 // class scala/util/control/TailCalls$Cont
     299: dup
     300: aload         14
     302: invokevirtual #33                 // Method scala/util/control/TailCalls$Cont.a:()Lscala/util/control/TailCalls$TailRec;
     305: new           #35                 // class scala/util/control/TailCalls$TailRec$$anonfun$flatMap$2
     308: dup
     309: aload         16
     311: aload         13
     313: aload         14
     315: invokespecial #38                 // Method scala/util/control/TailCalls$TailRec$$anonfun$flatMap$2."<init>":(Lscala/util/control/TailCalls$TailRec;Lscala/Function1;Lscala/util/control/TailCalls$Cont;)V
     318: invokespecial #29                 // Method scala/util/control/TailCalls$Cont."<init>":(Lscala/util/control/TailCalls$TailRec;Lscala/Function1;)V
     321: astore        15
     323: aload         15
     325: astore_0
     326: goto          0
     329: new           #40                 // class scala/MatchError
     332: dup
     333: aload         16
     335: invokespecial #43                 // Method scala/MatchError."<init>":(Ljava/lang/Object;)V
     338: athrow
     339: new           #40                 // class scala/MatchError
     342: dup
     343: aload         17
     345: invokespecial #43                 // Method scala/MatchError."<init>":(Ljava/lang/Object;)V
     348: athrow
     349: new           #40                 // class scala/MatchError
     352: dup
     353: aload_0
     354: invokespecial #43                 // Method scala/MatchError."<init>":(Ljava/lang/Object;)V
     357: athrow

  public final A result();
    Code:
       0: aload_0
       1: instanceof    #16                 // class scala/util/control/TailCalls$Done
       4: ifeq          19
       7: aload_0
       8: checkcast     #16                 // class scala/util/control/TailCalls$Done
      11: astore_1
      12: aload_1
      13: invokevirtual #68                 // Method scala/util/control/TailCalls$Done.value:()Ljava/lang/Object;
      16: astore_2
      17: aload_2
      18: areturn
      19: aload_0
      20: instanceof    #18                 // class scala/util/control/TailCalls$Call
      23: ifeq          47
      26: aload_0
      27: checkcast     #18                 // class scala/util/control/TailCalls$Call
      30: astore_3
      31: aload_3
      32: invokevirtual #75                 // Method scala/util/control/TailCalls$Call.rest:()Lscala/Function0;
      35: invokeinterface #102,  1          // InterfaceMethod scala/Function0.apply:()Ljava/lang/Object;
      40: checkcast     #2                  // class scala/util/control/TailCalls$TailRec
      43: astore_0
      44: goto          0
      47: aload_0
      48: instanceof    #28                 // class scala/util/control/TailCalls$Cont
      51: ifeq          445
      54: aload_0
      55: checkcast     #28                 // class scala/util/control/TailCalls$Cont
      58: astore        13
      60: aload         13
      62: invokevirtual #33                 // Method scala/util/control/TailCalls$Cont.a:()Lscala/util/control/TailCalls$TailRec;
      65: astore        20
      67: aload         20
      69: instanceof    #16                 // class scala/util/control/TailCalls$Done
      72: ifeq          104
      75: aload         20
      77: checkcast     #16                 // class scala/util/control/TailCalls$Done
      80: astore        4
      82: aload         13
      84: invokevirtual #81                 // Method scala/util/control/TailCalls$Cont.f:()Lscala/Function1;
      87: aload         4
      89: invokevirtual #68                 // Method scala/util/control/TailCalls$Done.value:()Ljava/lang/Object;
      92: invokeinterface #85,  2           // InterfaceMethod scala/Function1.apply:(Ljava/lang/Object;)Ljava/lang/Object;
      97: checkcast     #2                  // class scala/util/control/TailCalls$TailRec
     100: astore_0
     101: goto          0
     104: aload         20
     106: instanceof    #18                 // class scala/util/control/TailCalls$Call
     109: ifeq          270
     112: aload         20
     114: checkcast     #18                 // class scala/util/control/TailCalls$Call
     117: astore        5
     119: aload         5
     121: invokevirtual #75                 // Method scala/util/control/TailCalls$Call.rest:()Lscala/Function0;
     124: invokeinterface #102,  1          // InterfaceMethod scala/Function0.apply:()Ljava/lang/Object;
     129: checkcast     #2                  // class scala/util/control/TailCalls$TailRec
     132: aload         13
     134: invokevirtual #81                 // Method scala/util/control/TailCalls$Cont.f:()Lscala/Function1;
     137: astore        8
     139: astore        11
     141: aload         11
     143: instanceof    #16                 // class scala/util/control/TailCalls$Done
     146: ifeq          181
     149: aload         11
     151: checkcast     #16                 // class scala/util/control/TailCalls$Done
     154: astore        6
     156: new           #18                 // class scala/util/control/TailCalls$Call
     159: dup
     160: new           #20                 // class scala/util/control/TailCalls$TailRec$$anonfun$flatMap$1
     163: dup
     164: aload         11
     166: aload         8
     168: aload         6
     170: invokespecial #23                 // Method scala/util/control/TailCalls$TailRec$$anonfun$flatMap$1."<init>":(Lscala/util/control/TailCalls$TailRec;Lscala/Function1;Lscala/util/control/TailCalls$Done;)V
     173: invokespecial #26                 // Method scala/util/control/TailCalls$Call."<init>":(Lscala/Function0;)V
     176: astore        10
     178: goto          254
     181: aload         11
     183: instanceof    #18                 // class scala/util/control/TailCalls$Call
     186: ifeq          212
     189: aload         11
     191: checkcast     #18                 // class scala/util/control/TailCalls$Call
     194: astore        7
     196: new           #28                 // class scala/util/control/TailCalls$Cont
     199: dup
     200: aload         7
     202: aload         8
     204: invokespecial #29                 // Method scala/util/control/TailCalls$Cont."<init>":(Lscala/util/control/TailCalls$TailRec;Lscala/Function1;)V
     207: astore        10
     209: goto          254
     212: aload         11
     214: instanceof    #28                 // class scala/util/control/TailCalls$Cont
     217: ifeq          260
     220: aload         11
     222: checkcast     #28                 // class scala/util/control/TailCalls$Cont
     225: astore        9
     227: new           #28                 // class scala/util/control/TailCalls$Cont
     230: dup
     231: aload         9
     233: invokevirtual #33                 // Method scala/util/control/TailCalls$Cont.a:()Lscala/util/control/TailCalls$TailRec;
     236: new           #35                 // class scala/util/control/TailCalls$TailRec$$anonfun$flatMap$2
     239: dup
     240: aload         11
     242: aload         8
     244: aload         9
     246: invokespecial #38                 // Method scala/util/control/TailCalls$TailRec$$anonfun$flatMap$2."<init>":(Lscala/util/control/TailCalls$TailRec;Lscala/Function1;Lscala/util/control/TailCalls$Cont;)V
     249: invokespecial #29                 // Method scala/util/control/TailCalls$Cont."<init>":(Lscala/util/control/TailCalls$TailRec;Lscala/Function1;)V
     252: astore        10
     254: aload         10
     256: astore_0
     257: goto          0
     260: new           #40                 // class scala/MatchError
     263: dup
     264: aload         11
     266: invokespecial #43                 // Method scala/MatchError."<init>":(Ljava/lang/Object;)V
     269: athrow
     270: aload         20
     272: instanceof    #28                 // class scala/util/control/TailCalls$Cont
     275: ifeq          435
     278: aload         20
     280: checkcast     #28                 // class scala/util/control/TailCalls$Cont
     283: astore        12
     285: aload         12
     287: invokevirtual #33                 // Method scala/util/control/TailCalls$Cont.a:()Lscala/util/control/TailCalls$TailRec;
     290: new           #104                // class scala/util/control/TailCalls$TailRec$$anonfun$result$1
     293: dup
     294: aload_0
     295: aload         12
     297: aload         13
     299: invokespecial #105                // Method scala/util/control/TailCalls$TailRec$$anonfun$result$1."<init>":(Lscala/util/control/TailCalls$TailRec;Lscala/util/control/TailCalls$Cont;Lscala/util/control/TailCalls$Cont;)V
     302: astore        16
     304: astore        19
     306: aload         19
     308: instanceof    #16                 // class scala/util/control/TailCalls$Done
     311: ifeq          346
     314: aload         19
     316: checkcast     #16                 // class scala/util/control/TailCalls$Done
     319: astore        14
     321: new           #18                 // class scala/util/control/TailCalls$Call
     324: dup
     325: new           #20                 // class scala/util/control/TailCalls$TailRec$$anonfun$flatMap$1
     328: dup
     329: aload         19
     331: aload         16
     333: aload         14
     335: invokespecial #23                 // Method scala/util/control/TailCalls$TailRec$$anonfun$flatMap$1."<init>":(Lscala/util/control/TailCalls$TailRec;Lscala/Function1;Lscala/util/control/TailCalls$Done;)V
     338: invokespecial #26                 // Method scala/util/control/TailCalls$Call."<init>":(Lscala/Function0;)V
     341: astore        18
     343: goto          419
     346: aload         19
     348: instanceof    #18                 // class scala/util/control/TailCalls$Call
     351: ifeq          377
     354: aload         19
     356: checkcast     #18                 // class scala/util/control/TailCalls$Call
     359: astore        15
     361: new           #28                 // class scala/util/control/TailCalls$Cont
     364: dup
     365: aload         15
     367: aload         16
     369: invokespecial #29                 // Method scala/util/control/TailCalls$Cont."<init>":(Lscala/util/control/TailCalls$TailRec;Lscala/Function1;)V
     372: astore        18
     374: goto          419
     377: aload         19
     379: instanceof    #28                 // class scala/util/control/TailCalls$Cont
     382: ifeq          425
     385: aload         19
     387: checkcast     #28                 // class scala/util/control/TailCalls$Cont
     390: astore        17
     392: new           #28                 // class scala/util/control/TailCalls$Cont
     395: dup
     396: aload         17
     398: invokevirtual #33                 // Method scala/util/control/TailCalls$Cont.a:()Lscala/util/control/TailCalls$TailRec;
     401: new           #35                 // class scala/util/control/TailCalls$TailRec$$anonfun$flatMap$2
     404: dup
     405: aload         19
     407: aload         16
     409: aload         17
     411: invokespecial #38                 // Method scala/util/control/TailCalls$TailRec$$anonfun$flatMap$2."<init>":(Lscala/util/control/TailCalls$TailRec;Lscala/Function1;Lscala/util/control/TailCalls$Cont;)V
     414: invokespecial #29                 // Method scala/util/control/TailCalls$Cont."<init>":(Lscala/util/control/TailCalls$TailRec;Lscala/Function1;)V
     417: astore        18
     419: aload         18
     421: astore_0
     422: goto          0
     425: new           #40                 // class scala/MatchError
     428: dup
     429: aload         19
     431: invokespecial #43                 // Method scala/MatchError."<init>":(Ljava/lang/Object;)V
     434: athrow
     435: new           #40                 // class scala/MatchError
     438: dup
     439: aload         20
     441: invokespecial #43                 // Method scala/MatchError."<init>":(Ljava/lang/Object;)V
     444: athrow
     445: new           #40                 // class scala/MatchError
     448: dup
     449: aload_0
     450: invokespecial #43                 // Method scala/MatchError."<init>":(Ljava/lang/Object;)V
     453: athrow

  public scala.util.control.TailCalls$TailRec();
    Code:
       0: aload_0
       1: invokespecial #111                // Method java/lang/Object."<init>":()V
       4: return
}
