Compiled from "CoroutineContextImpl.kt"
public final class kotlin.coroutines.experimental.EmptyCoroutineContext implements kotlin.coroutines.experimental.CoroutineContext {
  public static final kotlin.coroutines.experimental.EmptyCoroutineContext INSTANCE;

  public <E extends kotlin.coroutines.experimental.CoroutineContext$Element> E get(kotlin.coroutines.experimental.CoroutineContext$Key<E>);
    Code:
       0: aload_1
       1: ldc           #15                 // String key
       3: invokestatic  #21                 // Method kotlin/jvm/internal/Intrinsics.checkParameterIsNotNull:(Ljava/lang/Object;Ljava/lang/String;)V
       6: aconst_null
       7: areturn

  public <R> R fold(R, kotlin.jvm.functions.Function2<? super R, ? super kotlin.coroutines.experimental.CoroutineContext$Element, ? extends R>);
    Code:
       0: aload_2
       1: ldc           #28                 // String operation
       3: invokestatic  #21                 // Method kotlin/jvm/internal/Intrinsics.checkParameterIsNotNull:(Ljava/lang/Object;Ljava/lang/String;)V
       6: aload_1
       7: areturn

  public kotlin.coroutines.experimental.CoroutineContext plus(kotlin.coroutines.experimental.CoroutineContext);
    Code:
       0: aload_1
       1: ldc           #35                 // String context
       3: invokestatic  #21                 // Method kotlin/jvm/internal/Intrinsics.checkParameterIsNotNull:(Ljava/lang/Object;Ljava/lang/String;)V
       6: aload_1
       7: areturn

  public kotlin.coroutines.experimental.CoroutineContext minusKey(kotlin.coroutines.experimental.CoroutineContext$Key<?>);
    Code:
       0: aload_1
       1: ldc           #15                 // String key
       3: invokestatic  #21                 // Method kotlin/jvm/internal/Intrinsics.checkParameterIsNotNull:(Ljava/lang/Object;Ljava/lang/String;)V
       6: aload_0
       7: checkcast     #6                  // class kotlin/coroutines/experimental/CoroutineContext
      10: areturn

  public int hashCode();
    Code:
       0: iconst_0
       1: ireturn

  public java.lang.String toString();
    Code:
       0: ldc           #44                 // String EmptyCoroutineContext
       2: areturn

  private kotlin.coroutines.experimental.EmptyCoroutineContext();
    Code:
       0: aload_0
       1: invokespecial #48                 // Method java/lang/Object."<init>":()V
       4: return

  static {};
    Code:
       0: new           #2                  // class kotlin/coroutines/experimental/EmptyCoroutineContext
       3: dup
       4: invokespecial #68                 // Method "<init>":()V
       7: astore_0
       8: aload_0
       9: putstatic     #70                 // Field INSTANCE:Lkotlin/coroutines/experimental/EmptyCoroutineContext;
      12: return
}
