Compiled from "SafeContinuationJvm.kt"
final class kotlin.coroutines.experimental.SafeContinuation$Fail {
  private final java.lang.Throwable exception;

  public final java.lang.Throwable getException();
    Code:
       0: aload_0
       1: getfield      #11                 // Field exception:Ljava/lang/Throwable;
       4: areturn

  public kotlin.coroutines.experimental.SafeContinuation$Fail(java.lang.Throwable);
    Code:
       0: aload_1
       1: ldc           #16                 // String exception
       3: invokestatic  #22                 // Method kotlin/jvm/internal/Intrinsics.checkParameterIsNotNull:(Ljava/lang/Object;Ljava/lang/String;)V
       6: aload_0
       7: invokespecial #25                 // Method java/lang/Object."<init>":()V
      10: aload_0
      11: aload_1
      12: putfield      #11                 // Field exception:Ljava/lang/Throwable;
      15: return
}
