Compiled from "CreateConnectionResult.java"
public class com.amazonaws.services.directconnect.model.CreateConnectionResult implements java.io.Serializable,java.lang.Cloneable {
  private java.lang.String ownerAccount;

  private java.lang.String connectionId;

  private java.lang.String connectionName;

  private java.lang.String connectionState;

  private java.lang.String region;

  private java.lang.String location;

  private java.lang.String bandwidth;

  private java.lang.Integer vlan;

  private java.lang.String partnerName;

  private java.util.Date loaIssueTime;

  public com.amazonaws.services.directconnect.model.CreateConnectionResult();
    Code:
       0: aload_0
       1: invokespecial #1                  // Method java/lang/Object."<init>":()V
       4: return

  public void setOwnerAccount(java.lang.String);
    Code:
       0: aload_0
       1: aload_1
       2: putfield      #2                  // Field ownerAccount:Ljava/lang/String;
       5: return

  public java.lang.String getOwnerAccount();
    Code:
       0: aload_0
       1: getfield      #2                  // Field ownerAccount:Ljava/lang/String;
       4: areturn

  public com.amazonaws.services.directconnect.model.CreateConnectionResult withOwnerAccount(java.lang.String);
    Code:
       0: aload_0
       1: aload_1
       2: invokevirtual #3                  // Method setOwnerAccount:(Ljava/lang/String;)V
       5: aload_0
       6: areturn

  public void setConnectionId(java.lang.String);
    Code:
       0: aload_0
       1: aload_1
       2: putfield      #4                  // Field connectionId:Ljava/lang/String;
       5: return

  public java.lang.String getConnectionId();
    Code:
       0: aload_0
       1: getfield      #4                  // Field connectionId:Ljava/lang/String;
       4: areturn

  public com.amazonaws.services.directconnect.model.CreateConnectionResult withConnectionId(java.lang.String);
    Code:
       0: aload_0
       1: aload_1
       2: invokevirtual #5                  // Method setConnectionId:(Ljava/lang/String;)V
       5: aload_0
       6: areturn

  public void setConnectionName(java.lang.String);
    Code:
       0: aload_0
       1: aload_1
       2: putfield      #6                  // Field connectionName:Ljava/lang/String;
       5: return

  public java.lang.String getConnectionName();
    Code:
       0: aload_0
       1: getfield      #6                  // Field connectionName:Ljava/lang/String;
       4: areturn

  public com.amazonaws.services.directconnect.model.CreateConnectionResult withConnectionName(java.lang.String);
    Code:
       0: aload_0
       1: aload_1
       2: invokevirtual #7                  // Method setConnectionName:(Ljava/lang/String;)V
       5: aload_0
       6: areturn

  public void setConnectionState(java.lang.String);
    Code:
       0: aload_0
       1: aload_1
       2: putfield      #8                  // Field connectionState:Ljava/lang/String;
       5: return

  public java.lang.String getConnectionState();
    Code:
       0: aload_0
       1: getfield      #8                  // Field connectionState:Ljava/lang/String;
       4: areturn

  public com.amazonaws.services.directconnect.model.CreateConnectionResult withConnectionState(java.lang.String);
    Code:
       0: aload_0
       1: aload_1
       2: invokevirtual #9                  // Method setConnectionState:(Ljava/lang/String;)V
       5: aload_0
       6: areturn

  public void setConnectionState(com.amazonaws.services.directconnect.model.ConnectionState);
    Code:
       0: aload_0
       1: aload_1
       2: invokevirtual #10                 // Method com/amazonaws/services/directconnect/model/ConnectionState.toString:()Ljava/lang/String;
       5: putfield      #8                  // Field connectionState:Ljava/lang/String;
       8: return

  public com.amazonaws.services.directconnect.model.CreateConnectionResult withConnectionState(com.amazonaws.services.directconnect.model.ConnectionState);
    Code:
       0: aload_0
       1: aload_1
       2: invokevirtual #11                 // Method setConnectionState:(Lcom/amazonaws/services/directconnect/model/ConnectionState;)V
       5: aload_0
       6: areturn

  public void setRegion(java.lang.String);
    Code:
       0: aload_0
       1: aload_1
       2: putfield      #12                 // Field region:Ljava/lang/String;
       5: return

  public java.lang.String getRegion();
    Code:
       0: aload_0
       1: getfield      #12                 // Field region:Ljava/lang/String;
       4: areturn

  public com.amazonaws.services.directconnect.model.CreateConnectionResult withRegion(java.lang.String);
    Code:
       0: aload_0
       1: aload_1
       2: invokevirtual #13                 // Method setRegion:(Ljava/lang/String;)V
       5: aload_0
       6: areturn

  public void setLocation(java.lang.String);
    Code:
       0: aload_0
       1: aload_1
       2: putfield      #14                 // Field location:Ljava/lang/String;
       5: return

  public java.lang.String getLocation();
    Code:
       0: aload_0
       1: getfield      #14                 // Field location:Ljava/lang/String;
       4: areturn

  public com.amazonaws.services.directconnect.model.CreateConnectionResult withLocation(java.lang.String);
    Code:
       0: aload_0
       1: aload_1
       2: invokevirtual #15                 // Method setLocation:(Ljava/lang/String;)V
       5: aload_0
       6: areturn

  public void setBandwidth(java.lang.String);
    Code:
       0: aload_0
       1: aload_1
       2: putfield      #16                 // Field bandwidth:Ljava/lang/String;
       5: return

  public java.lang.String getBandwidth();
    Code:
       0: aload_0
       1: getfield      #16                 // Field bandwidth:Ljava/lang/String;
       4: areturn

  public com.amazonaws.services.directconnect.model.CreateConnectionResult withBandwidth(java.lang.String);
    Code:
       0: aload_0
       1: aload_1
       2: invokevirtual #17                 // Method setBandwidth:(Ljava/lang/String;)V
       5: aload_0
       6: areturn

  public void setVlan(java.lang.Integer);
    Code:
       0: aload_0
       1: aload_1
       2: putfield      #18                 // Field vlan:Ljava/lang/Integer;
       5: return

  public java.lang.Integer getVlan();
    Code:
       0: aload_0
       1: getfield      #18                 // Field vlan:Ljava/lang/Integer;
       4: areturn

  public com.amazonaws.services.directconnect.model.CreateConnectionResult withVlan(java.lang.Integer);
    Code:
       0: aload_0
       1: aload_1
       2: invokevirtual #19                 // Method setVlan:(Ljava/lang/Integer;)V
       5: aload_0
       6: areturn

  public void setPartnerName(java.lang.String);
    Code:
       0: aload_0
       1: aload_1
       2: putfield      #20                 // Field partnerName:Ljava/lang/String;
       5: return

  public java.lang.String getPartnerName();
    Code:
       0: aload_0
       1: getfield      #20                 // Field partnerName:Ljava/lang/String;
       4: areturn

  public com.amazonaws.services.directconnect.model.CreateConnectionResult withPartnerName(java.lang.String);
    Code:
       0: aload_0
       1: aload_1
       2: invokevirtual #21                 // Method setPartnerName:(Ljava/lang/String;)V
       5: aload_0
       6: areturn

  public void setLoaIssueTime(java.util.Date);
    Code:
       0: aload_0
       1: aload_1
       2: putfield      #22                 // Field loaIssueTime:Ljava/util/Date;
       5: return

  public java.util.Date getLoaIssueTime();
    Code:
       0: aload_0
       1: getfield      #22                 // Field loaIssueTime:Ljava/util/Date;
       4: areturn

  public com.amazonaws.services.directconnect.model.CreateConnectionResult withLoaIssueTime(java.util.Date);
    Code:
       0: aload_0
       1: aload_1
       2: invokevirtual #23                 // Method setLoaIssueTime:(Ljava/util/Date;)V
       5: aload_0
       6: areturn

  public java.lang.String toString();
    Code:
       0: new           #24                 // class java/lang/StringBuilder
       3: dup
       4: invokespecial #25                 // Method java/lang/StringBuilder."<init>":()V
       7: astore_1
       8: aload_1
       9: ldc           #26                 // String {
      11: invokevirtual #27                 // Method java/lang/StringBuilder.append:(Ljava/lang/String;)Ljava/lang/StringBuilder;
      14: pop
      15: aload_0
      16: invokevirtual #28                 // Method getOwnerAccount:()Ljava/lang/String;
      19: ifnull        54
      22: aload_1
      23: new           #24                 // class java/lang/StringBuilder
      26: dup
      27: invokespecial #25                 // Method java/lang/StringBuilder."<init>":()V
      30: ldc           #29                 // String OwnerAccount:
      32: invokevirtual #27                 // Method java/lang/StringBuilder.append:(Ljava/lang/String;)Ljava/lang/StringBuilder;
      35: aload_0
      36: invokevirtual #28                 // Method getOwnerAccount:()Ljava/lang/String;
      39: invokevirtual #27                 // Method java/lang/StringBuilder.append:(Ljava/lang/String;)Ljava/lang/StringBuilder;
      42: ldc           #30                 // String ,
      44: invokevirtual #27                 // Method java/lang/StringBuilder.append:(Ljava/lang/String;)Ljava/lang/StringBuilder;
      47: invokevirtual #31                 // Method java/lang/StringBuilder.toString:()Ljava/lang/String;
      50: invokevirtual #27                 // Method java/lang/StringBuilder.append:(Ljava/lang/String;)Ljava/lang/StringBuilder;
      53: pop
      54: aload_0
      55: invokevirtual #32                 // Method getConnectionId:()Ljava/lang/String;
      58: ifnull        93
      61: aload_1
      62: new           #24                 // class java/lang/StringBuilder
      65: dup
      66: invokespecial #25                 // Method java/lang/StringBuilder."<init>":()V
      69: ldc           #33                 // String ConnectionId:
      71: invokevirtual #27                 // Method java/lang/StringBuilder.append:(Ljava/lang/String;)Ljava/lang/StringBuilder;
      74: aload_0
      75: invokevirtual #32                 // Method getConnectionId:()Ljava/lang/String;
      78: invokevirtual #27                 // Method java/lang/StringBuilder.append:(Ljava/lang/String;)Ljava/lang/StringBuilder;
      81: ldc           #30                 // String ,
      83: invokevirtual #27                 // Method java/lang/StringBuilder.append:(Ljava/lang/String;)Ljava/lang/StringBuilder;
      86: invokevirtual #31                 // Method java/lang/StringBuilder.toString:()Ljava/lang/String;
      89: invokevirtual #27                 // Method java/lang/StringBuilder.append:(Ljava/lang/String;)Ljava/lang/StringBuilder;
      92: pop
      93: aload_0
      94: invokevirtual #34                 // Method getConnectionName:()Ljava/lang/String;
      97: ifnull        132
     100: aload_1
     101: new           #24                 // class java/lang/StringBuilder
     104: dup
     105: invokespecial #25                 // Method java/lang/StringBuilder."<init>":()V
     108: ldc           #35                 // String ConnectionName:
     110: invokevirtual #27                 // Method java/lang/StringBuilder.append:(Ljava/lang/String;)Ljava/lang/StringBuilder;
     113: aload_0
     114: invokevirtual #34                 // Method getConnectionName:()Ljava/lang/String;
     117: invokevirtual #27                 // Method java/lang/StringBuilder.append:(Ljava/lang/String;)Ljava/lang/StringBuilder;
     120: ldc           #30                 // String ,
     122: invokevirtual #27                 // Method java/lang/StringBuilder.append:(Ljava/lang/String;)Ljava/lang/StringBuilder;
     125: invokevirtual #31                 // Method java/lang/StringBuilder.toString:()Ljava/lang/String;
     128: invokevirtual #27                 // Method java/lang/StringBuilder.append:(Ljava/lang/String;)Ljava/lang/StringBuilder;
     131: pop
     132: aload_0
     133: invokevirtual #36                 // Method getConnectionState:()Ljava/lang/String;
     136: ifnull        171
     139: aload_1
     140: new           #24                 // class java/lang/StringBuilder
     143: dup
     144: invokespecial #25                 // Method java/lang/StringBuilder."<init>":()V
     147: ldc           #37                 // String ConnectionState:
     149: invokevirtual #27                 // Method java/lang/StringBuilder.append:(Ljava/lang/String;)Ljava/lang/StringBuilder;
     152: aload_0
     153: invokevirtual #36                 // Method getConnectionState:()Ljava/lang/String;
     156: invokevirtual #27                 // Method java/lang/StringBuilder.append:(Ljava/lang/String;)Ljava/lang/StringBuilder;
     159: ldc           #30                 // String ,
     161: invokevirtual #27                 // Method java/lang/StringBuilder.append:(Ljava/lang/String;)Ljava/lang/StringBuilder;
     164: invokevirtual #31                 // Method java/lang/StringBuilder.toString:()Ljava/lang/String;
     167: invokevirtual #27                 // Method java/lang/StringBuilder.append:(Ljava/lang/String;)Ljava/lang/StringBuilder;
     170: pop
     171: aload_0
     172: invokevirtual #38                 // Method getRegion:()Ljava/lang/String;
     175: ifnull        210
     178: aload_1
     179: new           #24                 // class java/lang/StringBuilder
     182: dup
     183: invokespecial #25                 // Method java/lang/StringBuilder."<init>":()V
     186: ldc           #39                 // String Region:
     188: invokevirtual #27                 // Method java/lang/StringBuilder.append:(Ljava/lang/String;)Ljava/lang/StringBuilder;
     191: aload_0
     192: invokevirtual #38                 // Method getRegion:()Ljava/lang/String;
     195: invokevirtual #27                 // Method java/lang/StringBuilder.append:(Ljava/lang/String;)Ljava/lang/StringBuilder;
     198: ldc           #30                 // String ,
     200: invokevirtual #27                 // Method java/lang/StringBuilder.append:(Ljava/lang/String;)Ljava/lang/StringBuilder;
     203: invokevirtual #31                 // Method java/lang/StringBuilder.toString:()Ljava/lang/String;
     206: invokevirtual #27                 // Method java/lang/StringBuilder.append:(Ljava/lang/String;)Ljava/lang/StringBuilder;
     209: pop
     210: aload_0
     211: invokevirtual #40                 // Method getLocation:()Ljava/lang/String;
     214: ifnull        249
     217: aload_1
     218: new           #24                 // class java/lang/StringBuilder
     221: dup
     222: invokespecial #25                 // Method java/lang/StringBuilder."<init>":()V
     225: ldc           #41                 // String Location:
     227: invokevirtual #27                 // Method java/lang/StringBuilder.append:(Ljava/lang/String;)Ljava/lang/StringBuilder;
     230: aload_0
     231: invokevirtual #40                 // Method getLocation:()Ljava/lang/String;
     234: invokevirtual #27                 // Method java/lang/StringBuilder.append:(Ljava/lang/String;)Ljava/lang/StringBuilder;
     237: ldc           #30                 // String ,
     239: invokevirtual #27                 // Method java/lang/StringBuilder.append:(Ljava/lang/String;)Ljava/lang/StringBuilder;
     242: invokevirtual #31                 // Method java/lang/StringBuilder.toString:()Ljava/lang/String;
     245: invokevirtual #27                 // Method java/lang/StringBuilder.append:(Ljava/lang/String;)Ljava/lang/StringBuilder;
     248: pop
     249: aload_0
     250: invokevirtual #42                 // Method getBandwidth:()Ljava/lang/String;
     253: ifnull        288
     256: aload_1
     257: new           #24                 // class java/lang/StringBuilder
     260: dup
     261: invokespecial #25                 // Method java/lang/StringBuilder."<init>":()V
     264: ldc           #43                 // String Bandwidth:
     266: invokevirtual #27                 // Method java/lang/StringBuilder.append:(Ljava/lang/String;)Ljava/lang/StringBuilder;
     269: aload_0
     270: invokevirtual #42                 // Method getBandwidth:()Ljava/lang/String;
     273: invokevirtual #27                 // Method java/lang/StringBuilder.append:(Ljava/lang/String;)Ljava/lang/StringBuilder;
     276: ldc           #30                 // String ,
     278: invokevirtual #27                 // Method java/lang/StringBuilder.append:(Ljava/lang/String;)Ljava/lang/StringBuilder;
     281: invokevirtual #31                 // Method java/lang/StringBuilder.toString:()Ljava/lang/String;
     284: invokevirtual #27                 // Method java/lang/StringBuilder.append:(Ljava/lang/String;)Ljava/lang/StringBuilder;
     287: pop
     288: aload_0
     289: invokevirtual #44                 // Method getVlan:()Ljava/lang/Integer;
     292: ifnull        327
     295: aload_1
     296: new           #24                 // class java/lang/StringBuilder
     299: dup
     300: invokespecial #25                 // Method java/lang/StringBuilder."<init>":()V
     303: ldc           #45                 // String Vlan:
     305: invokevirtual #27                 // Method java/lang/StringBuilder.append:(Ljava/lang/String;)Ljava/lang/StringBuilder;
     308: aload_0
     309: invokevirtual #44                 // Method getVlan:()Ljava/lang/Integer;
     312: invokevirtual #46                 // Method java/lang/StringBuilder.append:(Ljava/lang/Object;)Ljava/lang/StringBuilder;
     315: ldc           #30                 // String ,
     317: invokevirtual #27                 // Method java/lang/StringBuilder.append:(Ljava/lang/String;)Ljava/lang/StringBuilder;
     320: invokevirtual #31                 // Method java/lang/StringBuilder.toString:()Ljava/lang/String;
     323: invokevirtual #27                 // Method java/lang/StringBuilder.append:(Ljava/lang/String;)Ljava/lang/StringBuilder;
     326: pop
     327: aload_0
     328: invokevirtual #47                 // Method getPartnerName:()Ljava/lang/String;
     331: ifnull        366
     334: aload_1
     335: new           #24                 // class java/lang/StringBuilder
     338: dup
     339: invokespecial #25                 // Method java/lang/StringBuilder."<init>":()V
     342: ldc           #48                 // String PartnerName:
     344: invokevirtual #27                 // Method java/lang/StringBuilder.append:(Ljava/lang/String;)Ljava/lang/StringBuilder;
     347: aload_0
     348: invokevirtual #47                 // Method getPartnerName:()Ljava/lang/String;
     351: invokevirtual #27                 // Method java/lang/StringBuilder.append:(Ljava/lang/String;)Ljava/lang/StringBuilder;
     354: ldc           #30                 // String ,
     356: invokevirtual #27                 // Method java/lang/StringBuilder.append:(Ljava/lang/String;)Ljava/lang/StringBuilder;
     359: invokevirtual #31                 // Method java/lang/StringBuilder.toString:()Ljava/lang/String;
     362: invokevirtual #27                 // Method java/lang/StringBuilder.append:(Ljava/lang/String;)Ljava/lang/StringBuilder;
     365: pop
     366: aload_0
     367: invokevirtual #49                 // Method getLoaIssueTime:()Ljava/util/Date;
     370: ifnull        400
     373: aload_1
     374: new           #24                 // class java/lang/StringBuilder
     377: dup
     378: invokespecial #25                 // Method java/lang/StringBuilder."<init>":()V
     381: ldc           #50                 // String LoaIssueTime:
     383: invokevirtual #27                 // Method java/lang/StringBuilder.append:(Ljava/lang/String;)Ljava/lang/StringBuilder;
     386: aload_0
     387: invokevirtual #49                 // Method getLoaIssueTime:()Ljava/util/Date;
     390: invokevirtual #46                 // Method java/lang/StringBuilder.append:(Ljava/lang/Object;)Ljava/lang/StringBuilder;
     393: invokevirtual #31                 // Method java/lang/StringBuilder.toString:()Ljava/lang/String;
     396: invokevirtual #27                 // Method java/lang/StringBuilder.append:(Ljava/lang/String;)Ljava/lang/StringBuilder;
     399: pop
     400: aload_1
     401: ldc           #51                 // String }
     403: invokevirtual #27                 // Method java/lang/StringBuilder.append:(Ljava/lang/String;)Ljava/lang/StringBuilder;
     406: pop
     407: aload_1
     408: invokevirtual #31                 // Method java/lang/StringBuilder.toString:()Ljava/lang/String;
     411: areturn

  public boolean equals(java.lang.Object);
    Code:
       0: aload_0
       1: aload_1
       2: if_acmpne     7
       5: iconst_1
       6: ireturn
       7: aload_1
       8: ifnonnull     13
      11: iconst_0
      12: ireturn
      13: aload_1
      14: instanceof    #52                 // class com/amazonaws/services/directconnect/model/CreateConnectionResult
      17: ifne          22
      20: iconst_0
      21: ireturn
      22: aload_1
      23: checkcast     #52                 // class com/amazonaws/services/directconnect/model/CreateConnectionResult
      26: astore_2
      27: aload_2
      28: invokevirtual #28                 // Method getOwnerAccount:()Ljava/lang/String;
      31: ifnonnull     38
      34: iconst_1
      35: goto          39
      38: iconst_0
      39: aload_0
      40: invokevirtual #28                 // Method getOwnerAccount:()Ljava/lang/String;
      43: ifnonnull     50
      46: iconst_1
      47: goto          51
      50: iconst_0
      51: ixor
      52: ifeq          57
      55: iconst_0
      56: ireturn
      57: aload_2
      58: invokevirtual #28                 // Method getOwnerAccount:()Ljava/lang/String;
      61: ifnull        80
      64: aload_2
      65: invokevirtual #28                 // Method getOwnerAccount:()Ljava/lang/String;
      68: aload_0
      69: invokevirtual #28                 // Method getOwnerAccount:()Ljava/lang/String;
      72: invokevirtual #53                 // Method java/lang/String.equals:(Ljava/lang/Object;)Z
      75: ifne          80
      78: iconst_0
      79: ireturn
      80: aload_2
      81: invokevirtual #32                 // Method getConnectionId:()Ljava/lang/String;
      84: ifnonnull     91
      87: iconst_1
      88: goto          92
      91: iconst_0
      92: aload_0
      93: invokevirtual #32                 // Method getConnectionId:()Ljava/lang/String;
      96: ifnonnull     103
      99: iconst_1
     100: goto          104
     103: iconst_0
     104: ixor
     105: ifeq          110
     108: iconst_0
     109: ireturn
     110: aload_2
     111: invokevirtual #32                 // Method getConnectionId:()Ljava/lang/String;
     114: ifnull        133
     117: aload_2
     118: invokevirtual #32                 // Method getConnectionId:()Ljava/lang/String;
     121: aload_0
     122: invokevirtual #32                 // Method getConnectionId:()Ljava/lang/String;
     125: invokevirtual #53                 // Method java/lang/String.equals:(Ljava/lang/Object;)Z
     128: ifne          133
     131: iconst_0
     132: ireturn
     133: aload_2
     134: invokevirtual #34                 // Method getConnectionName:()Ljava/lang/String;
     137: ifnonnull     144
     140: iconst_1
     141: goto          145
     144: iconst_0
     145: aload_0
     146: invokevirtual #34                 // Method getConnectionName:()Ljava/lang/String;
     149: ifnonnull     156
     152: iconst_1
     153: goto          157
     156: iconst_0
     157: ixor
     158: ifeq          163
     161: iconst_0
     162: ireturn
     163: aload_2
     164: invokevirtual #34                 // Method getConnectionName:()Ljava/lang/String;
     167: ifnull        186
     170: aload_2
     171: invokevirtual #34                 // Method getConnectionName:()Ljava/lang/String;
     174: aload_0
     175: invokevirtual #34                 // Method getConnectionName:()Ljava/lang/String;
     178: invokevirtual #53                 // Method java/lang/String.equals:(Ljava/lang/Object;)Z
     181: ifne          186
     184: iconst_0
     185: ireturn
     186: aload_2
     187: invokevirtual #36                 // Method getConnectionState:()Ljava/lang/String;
     190: ifnonnull     197
     193: iconst_1
     194: goto          198
     197: iconst_0
     198: aload_0
     199: invokevirtual #36                 // Method getConnectionState:()Ljava/lang/String;
     202: ifnonnull     209
     205: iconst_1
     206: goto          210
     209: iconst_0
     210: ixor
     211: ifeq          216
     214: iconst_0
     215: ireturn
     216: aload_2
     217: invokevirtual #36                 // Method getConnectionState:()Ljava/lang/String;
     220: ifnull        239
     223: aload_2
     224: invokevirtual #36                 // Method getConnectionState:()Ljava/lang/String;
     227: aload_0
     228: invokevirtual #36                 // Method getConnectionState:()Ljava/lang/String;
     231: invokevirtual #53                 // Method java/lang/String.equals:(Ljava/lang/Object;)Z
     234: ifne          239
     237: iconst_0
     238: ireturn
     239: aload_2
     240: invokevirtual #38                 // Method getRegion:()Ljava/lang/String;
     243: ifnonnull     250
     246: iconst_1
     247: goto          251
     250: iconst_0
     251: aload_0
     252: invokevirtual #38                 // Method getRegion:()Ljava/lang/String;
     255: ifnonnull     262
     258: iconst_1
     259: goto          263
     262: iconst_0
     263: ixor
     264: ifeq          269
     267: iconst_0
     268: ireturn
     269: aload_2
     270: invokevirtual #38                 // Method getRegion:()Ljava/lang/String;
     273: ifnull        292
     276: aload_2
     277: invokevirtual #38                 // Method getRegion:()Ljava/lang/String;
     280: aload_0
     281: invokevirtual #38                 // Method getRegion:()Ljava/lang/String;
     284: invokevirtual #53                 // Method java/lang/String.equals:(Ljava/lang/Object;)Z
     287: ifne          292
     290: iconst_0
     291: ireturn
     292: aload_2
     293: invokevirtual #40                 // Method getLocation:()Ljava/lang/String;
     296: ifnonnull     303
     299: iconst_1
     300: goto          304
     303: iconst_0
     304: aload_0
     305: invokevirtual #40                 // Method getLocation:()Ljava/lang/String;
     308: ifnonnull     315
     311: iconst_1
     312: goto          316
     315: iconst_0
     316: ixor
     317: ifeq          322
     320: iconst_0
     321: ireturn
     322: aload_2
     323: invokevirtual #40                 // Method getLocation:()Ljava/lang/String;
     326: ifnull        345
     329: aload_2
     330: invokevirtual #40                 // Method getLocation:()Ljava/lang/String;
     333: aload_0
     334: invokevirtual #40                 // Method getLocation:()Ljava/lang/String;
     337: invokevirtual #53                 // Method java/lang/String.equals:(Ljava/lang/Object;)Z
     340: ifne          345
     343: iconst_0
     344: ireturn
     345: aload_2
     346: invokevirtual #42                 // Method getBandwidth:()Ljava/lang/String;
     349: ifnonnull     356
     352: iconst_1
     353: goto          357
     356: iconst_0
     357: aload_0
     358: invokevirtual #42                 // Method getBandwidth:()Ljava/lang/String;
     361: ifnonnull     368
     364: iconst_1
     365: goto          369
     368: iconst_0
     369: ixor
     370: ifeq          375
     373: iconst_0
     374: ireturn
     375: aload_2
     376: invokevirtual #42                 // Method getBandwidth:()Ljava/lang/String;
     379: ifnull        398
     382: aload_2
     383: invokevirtual #42                 // Method getBandwidth:()Ljava/lang/String;
     386: aload_0
     387: invokevirtual #42                 // Method getBandwidth:()Ljava/lang/String;
     390: invokevirtual #53                 // Method java/lang/String.equals:(Ljava/lang/Object;)Z
     393: ifne          398
     396: iconst_0
     397: ireturn
     398: aload_2
     399: invokevirtual #44                 // Method getVlan:()Ljava/lang/Integer;
     402: ifnonnull     409
     405: iconst_1
     406: goto          410
     409: iconst_0
     410: aload_0
     411: invokevirtual #44                 // Method getVlan:()Ljava/lang/Integer;
     414: ifnonnull     421
     417: iconst_1
     418: goto          422
     421: iconst_0
     422: ixor
     423: ifeq          428
     426: iconst_0
     427: ireturn
     428: aload_2
     429: invokevirtual #44                 // Method getVlan:()Ljava/lang/Integer;
     432: ifnull        451
     435: aload_2
     436: invokevirtual #44                 // Method getVlan:()Ljava/lang/Integer;
     439: aload_0
     440: invokevirtual #44                 // Method getVlan:()Ljava/lang/Integer;
     443: invokevirtual #54                 // Method java/lang/Integer.equals:(Ljava/lang/Object;)Z
     446: ifne          451
     449: iconst_0
     450: ireturn
     451: aload_2
     452: invokevirtual #47                 // Method getPartnerName:()Ljava/lang/String;
     455: ifnonnull     462
     458: iconst_1
     459: goto          463
     462: iconst_0
     463: aload_0
     464: invokevirtual #47                 // Method getPartnerName:()Ljava/lang/String;
     467: ifnonnull     474
     470: iconst_1
     471: goto          475
     474: iconst_0
     475: ixor
     476: ifeq          481
     479: iconst_0
     480: ireturn
     481: aload_2
     482: invokevirtual #47                 // Method getPartnerName:()Ljava/lang/String;
     485: ifnull        504
     488: aload_2
     489: invokevirtual #47                 // Method getPartnerName:()Ljava/lang/String;
     492: aload_0
     493: invokevirtual #47                 // Method getPartnerName:()Ljava/lang/String;
     496: invokevirtual #53                 // Method java/lang/String.equals:(Ljava/lang/Object;)Z
     499: ifne          504
     502: iconst_0
     503: ireturn
     504: aload_2
     505: invokevirtual #49                 // Method getLoaIssueTime:()Ljava/util/Date;
     508: ifnonnull     515
     511: iconst_1
     512: goto          516
     515: iconst_0
     516: aload_0
     517: invokevirtual #49                 // Method getLoaIssueTime:()Ljava/util/Date;
     520: ifnonnull     527
     523: iconst_1
     524: goto          528
     527: iconst_0
     528: ixor
     529: ifeq          534
     532: iconst_0
     533: ireturn
     534: aload_2
     535: invokevirtual #49                 // Method getLoaIssueTime:()Ljava/util/Date;
     538: ifnull        557
     541: aload_2
     542: invokevirtual #49                 // Method getLoaIssueTime:()Ljava/util/Date;
     545: aload_0
     546: invokevirtual #49                 // Method getLoaIssueTime:()Ljava/util/Date;
     549: invokevirtual #55                 // Method java/util/Date.equals:(Ljava/lang/Object;)Z
     552: ifne          557
     555: iconst_0
     556: ireturn
     557: iconst_1
     558: ireturn

  public int hashCode();
    Code:
       0: bipush        31
       2: istore_1
       3: iconst_1
       4: istore_2
       5: bipush        31
       7: iload_2
       8: imul
       9: aload_0
      10: invokevirtual #28                 // Method getOwnerAccount:()Ljava/lang/String;
      13: ifnonnull     20
      16: iconst_0
      17: goto          27
      20: aload_0
      21: invokevirtual #28                 // Method getOwnerAccount:()Ljava/lang/String;
      24: invokevirtual #56                 // Method java/lang/String.hashCode:()I
      27: iadd
      28: istore_2
      29: bipush        31
      31: iload_2
      32: imul
      33: aload_0
      34: invokevirtual #32                 // Method getConnectionId:()Ljava/lang/String;
      37: ifnonnull     44
      40: iconst_0
      41: goto          51
      44: aload_0
      45: invokevirtual #32                 // Method getConnectionId:()Ljava/lang/String;
      48: invokevirtual #56                 // Method java/lang/String.hashCode:()I
      51: iadd
      52: istore_2
      53: bipush        31
      55: iload_2
      56: imul
      57: aload_0
      58: invokevirtual #34                 // Method getConnectionName:()Ljava/lang/String;
      61: ifnonnull     68
      64: iconst_0
      65: goto          75
      68: aload_0
      69: invokevirtual #34                 // Method getConnectionName:()Ljava/lang/String;
      72: invokevirtual #56                 // Method java/lang/String.hashCode:()I
      75: iadd
      76: istore_2
      77: bipush        31
      79: iload_2
      80: imul
      81: aload_0
      82: invokevirtual #36                 // Method getConnectionState:()Ljava/lang/String;
      85: ifnonnull     92
      88: iconst_0
      89: goto          99
      92: aload_0
      93: invokevirtual #36                 // Method getConnectionState:()Ljava/lang/String;
      96: invokevirtual #56                 // Method java/lang/String.hashCode:()I
      99: iadd
     100: istore_2
     101: bipush        31
     103: iload_2
     104: imul
     105: aload_0
     106: invokevirtual #38                 // Method getRegion:()Ljava/lang/String;
     109: ifnonnull     116
     112: iconst_0
     113: goto          123
     116: aload_0
     117: invokevirtual #38                 // Method getRegion:()Ljava/lang/String;
     120: invokevirtual #56                 // Method java/lang/String.hashCode:()I
     123: iadd
     124: istore_2
     125: bipush        31
     127: iload_2
     128: imul
     129: aload_0
     130: invokevirtual #40                 // Method getLocation:()Ljava/lang/String;
     133: ifnonnull     140
     136: iconst_0
     137: goto          147
     140: aload_0
     141: invokevirtual #40                 // Method getLocation:()Ljava/lang/String;
     144: invokevirtual #56                 // Method java/lang/String.hashCode:()I
     147: iadd
     148: istore_2
     149: bipush        31
     151: iload_2
     152: imul
     153: aload_0
     154: invokevirtual #42                 // Method getBandwidth:()Ljava/lang/String;
     157: ifnonnull     164
     160: iconst_0
     161: goto          171
     164: aload_0
     165: invokevirtual #42                 // Method getBandwidth:()Ljava/lang/String;
     168: invokevirtual #56                 // Method java/lang/String.hashCode:()I
     171: iadd
     172: istore_2
     173: bipush        31
     175: iload_2
     176: imul
     177: aload_0
     178: invokevirtual #44                 // Method getVlan:()Ljava/lang/Integer;
     181: ifnonnull     188
     184: iconst_0
     185: goto          195
     188: aload_0
     189: invokevirtual #44                 // Method getVlan:()Ljava/lang/Integer;
     192: invokevirtual #57                 // Method java/lang/Integer.hashCode:()I
     195: iadd
     196: istore_2
     197: bipush        31
     199: iload_2
     200: imul
     201: aload_0
     202: invokevirtual #47                 // Method getPartnerName:()Ljava/lang/String;
     205: ifnonnull     212
     208: iconst_0
     209: goto          219
     212: aload_0
     213: invokevirtual #47                 // Method getPartnerName:()Ljava/lang/String;
     216: invokevirtual #56                 // Method java/lang/String.hashCode:()I
     219: iadd
     220: istore_2
     221: bipush        31
     223: iload_2
     224: imul
     225: aload_0
     226: invokevirtual #49                 // Method getLoaIssueTime:()Ljava/util/Date;
     229: ifnonnull     236
     232: iconst_0
     233: goto          243
     236: aload_0
     237: invokevirtual #49                 // Method getLoaIssueTime:()Ljava/util/Date;
     240: invokevirtual #58                 // Method java/util/Date.hashCode:()I
     243: iadd
     244: istore_2
     245: iload_2
     246: ireturn

  public com.amazonaws.services.directconnect.model.CreateConnectionResult clone();
    Code:
       0: aload_0
       1: invokespecial #59                 // Method java/lang/Object.clone:()Ljava/lang/Object;
       4: checkcast     #52                 // class com/amazonaws/services/directconnect/model/CreateConnectionResult
       7: areturn
       8: astore_1
       9: new           #61                 // class java/lang/IllegalStateException
      12: dup
      13: ldc           #62                 // String Got a CloneNotSupportedException from Object.clone() even though we\'re Cloneable!
      15: aload_1
      16: invokespecial #63                 // Method java/lang/IllegalStateException."<init>":(Ljava/lang/String;Ljava/lang/Throwable;)V
      19: athrow
    Exception table:
       from    to  target type
           0     7     8   Class java/lang/CloneNotSupportedException

  public java.lang.Object clone() throws java.lang.CloneNotSupportedException;
    Code:
       0: aload_0
       1: invokevirtual #64                 // Method clone:()Lcom/amazonaws/services/directconnect/model/CreateConnectionResult;
       4: areturn
}
