Compiled from "EitherOps.scala"
public final class scalaz.syntax.std.LeftOps$ {
  public static final scalaz.syntax.std.LeftOps$ MODULE$;

  public static {};
    Code:
       0: new           #2                  // class scalaz/syntax/std/LeftOps$
       3: dup
       4: invokespecial #12                 // Method "<init>":()V
       7: putstatic     #14                 // Field MODULE$:Lscalaz/syntax/std/LeftOps$;
      10: return

  public final <C, A, B> scala.util.Either<A, C> coerceRight$extension(scala.util.Left<A, B>);
    Code:
       0: aload_1
       1: areturn

  public final <A, B> int hashCode$extension(scala.util.Left<A, B>);
    Code:
       0: aload_1
       1: invokevirtual #29                 // Method scala/util/Left.hashCode:()I
       4: ireturn

  public final <A, B> boolean equals$extension(scala.util.Left<A, B>, java.lang.Object);
    Code:
       0: aload_2
       1: instanceof    #35                 // class scalaz/syntax/std/LeftOps
       4: ifeq          11
       7: iconst_1
       8: goto          12
      11: iconst_0
      12: ifeq          53
      15: aload_2
      16: ifnonnull     23
      19: aconst_null
      20: goto          30
      23: aload_2
      24: checkcast     #35                 // class scalaz/syntax/std/LeftOps
      27: invokevirtual #39                 // Method scalaz/syntax/std/LeftOps.scalaz$syntax$std$LeftOps$$self:()Lscala/util/Left;
      30: astore_3
      31: aload_1
      32: dup
      33: ifnonnull     44
      36: pop
      37: aload_3
      38: ifnull        51
      41: goto          53
      44: aload_3
      45: invokevirtual #43                 // Method java/lang/Object.equals:(Ljava/lang/Object;)Z
      48: ifeq          53
      51: iconst_1
      52: ireturn
      53: iconst_0
      54: ireturn

  private scalaz.syntax.std.LeftOps$();
    Code:
       0: aload_0
       1: invokespecial #45                 // Method java/lang/Object."<init>":()V
       4: return
}
