Compiled from "SortedMapOps.scala"
public final class scalaz.syntax.std.SortedMapOps$ {
  public static final scalaz.syntax.std.SortedMapOps$ MODULE$;

  public static {};
    Code:
       0: new           #2                  // class scalaz/syntax/std/SortedMapOps$
       3: dup
       4: invokespecial #19                 // Method "<init>":()V
       7: putstatic     #21                 // Field MODULE$:Lscalaz/syntax/std/SortedMapOps$;
      10: return

  public final <K, A> scala.collection.immutable.SortedMap<K, A> alter$extension(scala.collection.immutable.SortedMap<K, A>, K, scala.Function1<scala.Option<A>, scala.Option<A>>);
    Code:
       0: getstatic     #32                 // Field scalaz/std/sortedMap$.MODULE$:Lscalaz/std/sortedMap$;
       3: pop
       4: aload_3
       5: aload_1
       6: aload_2
       7: invokeinterface #38,  2           // InterfaceMethod scala/collection/immutable/SortedMap.get:(Ljava/lang/Object;)Lscala/Option;
      12: invokeinterface #44,  2           // InterfaceMethod scala/Function1.apply:(Ljava/lang/Object;)Ljava/lang/Object;
      17: checkcast     #46                 // class scala/Option
      20: aload_1
      21: aload_2
      22: invokedynamic #68,  0             // InvokeDynamic #0:apply:(Lscala/collection/immutable/SortedMap;Ljava/lang/Object;)Lscala/Function1;
      27: invokevirtual #72                 // Method scala/Option.map:(Lscala/Function1;)Lscala/Option;
      30: aload_1
      31: aload_2
      32: invokedynamic #84,  0             // InvokeDynamic #1:apply:(Lscala/collection/immutable/SortedMap;Ljava/lang/Object;)Lscala/Function0;
      37: invokevirtual #88                 // Method scala/Option.getOrElse:(Lscala/Function0;)Ljava/lang/Object;
      40: checkcast     #34                 // class scala/collection/immutable/SortedMap
      43: areturn

  public final <B, C, K, A> scala.collection.immutable.SortedMap<K, C> intersectWithKey$extension(scala.collection.immutable.SortedMap<K, A>, scala.collection.immutable.SortedMap<K, B>, scala.Function3<K, A, B, C>, scala.math.Ordering<K>);
    Code:
       0: getstatic     #32                 // Field scalaz/std/sortedMap$.MODULE$:Lscalaz/std/sortedMap$;
       3: pop
       4: aload_1
       5: new           #12                 // class scalaz/std/SortedMapFunctions$$anonfun$intersectWithKey$1
       8: dup
       9: aconst_null
      10: aload_2
      11: aload_3
      12: invokespecial #100                // Method scalaz/std/SortedMapFunctions$$anonfun$intersectWithKey$1."<init>":(Lscalaz/std/SortedMapFunctions;Lscala/collection/immutable/SortedMap;Lscala/Function3;)V
      15: aload         4
      17: invokeinterface #104,  3          // InterfaceMethod scala/collection/immutable/SortedMap.collect:(Lscala/PartialFunction;Lscala/math/Ordering;)Lscala/collection/Map;
      22: checkcast     #34                 // class scala/collection/immutable/SortedMap
      25: areturn

  public final <B, C, K, A> scala.collection.immutable.SortedMap<K, C> intersectWith$extension(scala.collection.immutable.SortedMap<K, A>, scala.collection.immutable.SortedMap<K, B>, scala.Function2<A, B, C>, scala.math.Ordering<K>);
    Code:
       0: getstatic     #32                 // Field scalaz/std/sortedMap$.MODULE$:Lscalaz/std/sortedMap$;
       3: pop
       4: aload_3
       5: invokedynamic #119,  0            // InvokeDynamic #2:apply:(Lscala/Function2;)Lscala/Function3;
      10: astore        5
      12: aload_1
      13: new           #12                 // class scalaz/std/SortedMapFunctions$$anonfun$intersectWithKey$1
      16: dup
      17: aconst_null
      18: aload_2
      19: aload         5
      21: invokespecial #100                // Method scalaz/std/SortedMapFunctions$$anonfun$intersectWithKey$1."<init>":(Lscalaz/std/SortedMapFunctions;Lscala/collection/immutable/SortedMap;Lscala/Function3;)V
      24: aload         4
      26: invokeinterface #104,  3          // InterfaceMethod scala/collection/immutable/SortedMap.collect:(Lscala/PartialFunction;Lscala/math/Ordering;)Lscala/collection/Map;
      31: checkcast     #34                 // class scala/collection/immutable/SortedMap
      34: areturn

  public final <K2, K, A> scala.collection.immutable.SortedMap<K2, A> mapKeys$extension(scala.collection.immutable.SortedMap<K, A>, scala.Function1<K, K2>, scala.math.Ordering<K2>);
    Code:
       0: getstatic     #32                 // Field scalaz/std/sortedMap$.MODULE$:Lscalaz/std/sortedMap$;
       3: pop
       4: aload_1
       5: aload_2
       6: invokedynamic #135,  0            // InvokeDynamic #3:apply:(Lscala/Function1;)Lscala/Function1;
      11: aload_3
      12: invokeinterface #138,  3          // InterfaceMethod scala/collection/immutable/SortedMap.map:(Lscala/Function1;Lscala/math/Ordering;)Lscala/collection/Map;
      17: checkcast     #34                 // class scala/collection/immutable/SortedMap
      20: areturn

  public final <K, A> scala.collection.immutable.SortedMap<K, A> unionWithKey$extension(scala.collection.immutable.SortedMap<K, A>, scala.collection.immutable.SortedMap<K, A>, scala.Function3<K, A, A, A>, scala.math.Ordering<K>);
    Code:
       0: getstatic     #32                 // Field scalaz/std/sortedMap$.MODULE$:Lscalaz/std/sortedMap$;
       3: pop
       4: aload_2
       5: aload_1
       6: invokeinterface #144,  1          // InterfaceMethod scala/collection/immutable/SortedMap.keySet:()Lscala/collection/immutable/SortedSet;
      11: invokeinterface #148,  2          // InterfaceMethod scala/collection/immutable/SortedMap.$minus$minus:(Lscala/collection/IterableOnce;)Lscala/collection/immutable/MapOps;
      16: checkcast     #34                 // class scala/collection/immutable/SortedMap
      19: astore        5
      21: aload_1
      22: aload_2
      23: aload_3
      24: invokedynamic #156,  0            // InvokeDynamic #4:apply:(Lscala/collection/immutable/SortedMap;Lscala/Function3;)Lscala/Function1;
      29: aload         4
      31: invokeinterface #138,  3          // InterfaceMethod scala/collection/immutable/SortedMap.map:(Lscala/Function1;Lscala/math/Ordering;)Lscala/collection/Map;
      36: checkcast     #34                 // class scala/collection/immutable/SortedMap
      39: aload         5
      41: invokeinterface #160,  2          // InterfaceMethod scala/collection/immutable/SortedMap.$plus$plus:(Lscala/collection/IterableOnce;)Lscala/collection/Map;
      46: checkcast     #34                 // class scala/collection/immutable/SortedMap
      49: areturn

  public final <K, A> scala.collection.immutable.SortedMap<K, A> unionWith$extension(scala.collection.immutable.SortedMap<K, A>, scala.collection.immutable.SortedMap<K, A>, scala.Function2<A, A, A>, scala.math.Ordering<K>);
    Code:
       0: getstatic     #32                 // Field scalaz/std/sortedMap$.MODULE$:Lscalaz/std/sortedMap$;
       3: pop
       4: aload_3
       5: invokedynamic #168,  0            // InvokeDynamic #5:apply:(Lscala/Function2;)Lscala/Function3;
      10: astore        5
      12: aload_2
      13: aload_1
      14: invokeinterface #144,  1          // InterfaceMethod scala/collection/immutable/SortedMap.keySet:()Lscala/collection/immutable/SortedSet;
      19: invokeinterface #148,  2          // InterfaceMethod scala/collection/immutable/SortedMap.$minus$minus:(Lscala/collection/IterableOnce;)Lscala/collection/immutable/MapOps;
      24: checkcast     #34                 // class scala/collection/immutable/SortedMap
      27: astore        6
      29: aload_1
      30: aload_2
      31: aload         5
      33: invokedynamic #156,  0            // InvokeDynamic #4:apply:(Lscala/collection/immutable/SortedMap;Lscala/Function3;)Lscala/Function1;
      38: aload         4
      40: invokeinterface #138,  3          // InterfaceMethod scala/collection/immutable/SortedMap.map:(Lscala/Function1;Lscala/math/Ordering;)Lscala/collection/Map;
      45: checkcast     #34                 // class scala/collection/immutable/SortedMap
      48: aload         6
      50: invokeinterface #160,  2          // InterfaceMethod scala/collection/immutable/SortedMap.$plus$plus:(Lscala/collection/IterableOnce;)Lscala/collection/Map;
      55: checkcast     #34                 // class scala/collection/immutable/SortedMap
      58: areturn

  public final <K, A> scala.collection.immutable.SortedMap<K, A> insertWith$extension(scala.collection.immutable.SortedMap<K, A>, K, A, scala.Function2<A, A, A>);
    Code:
       0: getstatic     #32                 // Field scalaz/std/sortedMap$.MODULE$:Lscalaz/std/sortedMap$;
       3: pop
       4: aload_1
       5: aload_2
       6: invokeinterface #178,  2          // InterfaceMethod scala/collection/immutable/SortedMap.contains:(Ljava/lang/Object;)Z
      11: ifeq          47
      14: aload_1
      15: new           #180                // class scala/Tuple2
      18: dup
      19: aload_2
      20: aload         4
      22: aload_1
      23: aload_2
      24: invokeinterface #181,  2          // InterfaceMethod scala/collection/immutable/SortedMap.apply:(Ljava/lang/Object;)Ljava/lang/Object;
      29: aload_3
      30: invokeinterface #186,  3          // InterfaceMethod scala/Function2.apply:(Ljava/lang/Object;Ljava/lang/Object;)Ljava/lang/Object;
      35: invokespecial #189                // Method scala/Tuple2."<init>":(Ljava/lang/Object;Ljava/lang/Object;)V
      38: invokeinterface #193,  2          // InterfaceMethod scala/collection/immutable/SortedMap.$plus:(Lscala/Tuple2;)Lscala/collection/immutable/Map;
      43: checkcast     #34                 // class scala/collection/immutable/SortedMap
      46: areturn
      47: aload_1
      48: new           #180                // class scala/Tuple2
      51: dup
      52: aload_2
      53: aload_3
      54: invokespecial #189                // Method scala/Tuple2."<init>":(Ljava/lang/Object;Ljava/lang/Object;)V
      57: invokeinterface #193,  2          // InterfaceMethod scala/collection/immutable/SortedMap.$plus:(Lscala/Tuple2;)Lscala/collection/immutable/Map;
      62: checkcast     #34                 // class scala/collection/immutable/SortedMap
      65: areturn

  public final <F, K, A> F getOrAdd$extension(scala.collection.immutable.SortedMap<K, A>, K, scala.Function0<F>, scalaz.Applicative<F>);
    Code:
       0: getstatic     #32                 // Field scalaz/std/sortedMap$.MODULE$:Lscalaz/std/sortedMap$;
       3: pop
       4: aload_1
       5: aload_2
       6: invokeinterface #38,  2           // InterfaceMethod scala/collection/immutable/SortedMap.get:(Ljava/lang/Object;)Lscala/Option;
      11: aload         4
      13: aload_3
      14: aload_1
      15: aload_2
      16: invokedynamic #206,  0            // InvokeDynamic #6:apply:(Lscalaz/Applicative;Lscala/Function0;Lscala/collection/immutable/SortedMap;Ljava/lang/Object;)Lscala/Function0;
      21: aload         4
      23: aload_1
      24: invokedynamic #214,  0            // InvokeDynamic #7:apply:(Lscalaz/Applicative;Lscala/collection/immutable/SortedMap;)Lscala/Function1;
      29: invokevirtual #218                // Method scala/Option.fold:(Lscala/Function0;Lscala/Function1;)Ljava/lang/Object;
      32: areturn

  public final <K, A> int hashCode$extension(scala.collection.immutable.SortedMap<K, A>);
    Code:
       0: aload_1
       1: invokeinterface #229,  1          // InterfaceMethod scala/collection/Map.hashCode:()I
       6: ireturn

  public final <K, A> boolean equals$extension(scala.collection.immutable.SortedMap<K, A>, java.lang.Object);
    Code:
       0: aload_2
       1: instanceof    #235                // class scalaz/syntax/std/SortedMapOps
       4: ifeq          11
       7: iconst_1
       8: goto          12
      11: iconst_0
      12: ifeq          53
      15: aload_2
      16: ifnonnull     23
      19: aconst_null
      20: goto          30
      23: aload_2
      24: checkcast     #235                // class scalaz/syntax/std/SortedMapOps
      27: invokevirtual #238                // Method scalaz/syntax/std/SortedMapOps.scalaz$syntax$std$SortedMapOps$$self:()Lscala/collection/immutable/SortedMap;
      30: astore_3
      31: aload_1
      32: dup
      33: ifnonnull     44
      36: pop
      37: aload_3
      38: ifnull        51
      41: goto          53
      44: aload_3
      45: invokevirtual #241                // Method java/lang/Object.equals:(Ljava/lang/Object;)Z
      48: ifeq          53
      51: iconst_1
      52: ireturn
      53: iconst_0
      54: ireturn

  private scalaz.syntax.std.SortedMapOps$();
    Code:
       0: aload_0
       1: invokespecial #242                // Method java/lang/Object."<init>":()V
       4: return

  private static java.lang.Object $deserializeLambda$(java.lang.invoke.SerializedLambda);
    Code:
       0: aload_0
       1: invokedynamic #254,  0            // InvokeDynamic #8:lambdaDeserialize:(Ljava/lang/invoke/SerializedLambda;)Ljava/lang/Object;
       6: areturn
}
