Compiled from "StaxBuilder.java"
public class org.apache.cxf.aegis.util.jdom.StaxBuilder {
  private static final java.util.Map<java.lang.String, java.lang.Integer> ATTR_TYPES;

  protected boolean cfgIgnoreWS;

  private org.jdom.JDOMFactory factory;

  private java.util.Map<java.lang.String, java.lang.String> additionalNamespaces;

  private boolean isReadingMidStream;

  public org.apache.cxf.aegis.util.jdom.StaxBuilder();
    Code:
       0: aload_0
       1: invokespecial #1                  // Method java/lang/Object."<init>":()V
       4: return

  public org.apache.cxf.aegis.util.jdom.StaxBuilder(java.util.Map<java.lang.String, java.lang.String>);
    Code:
       0: aload_0
       1: invokespecial #1                  // Method java/lang/Object."<init>":()V
       4: aload_0
       5: aload_1
       6: putfield      #2                  // Field additionalNamespaces:Ljava/util/Map;
       9: return

  public java.util.Map<java.lang.String, java.lang.String> getAdditionalNamespaces();
    Code:
       0: aload_0
       1: getfield      #2                  // Field additionalNamespaces:Ljava/util/Map;
       4: areturn

  public void setAdditionalNamespaces(java.util.Map<java.lang.String, java.lang.String>);
    Code:
       0: aload_0
       1: aload_1
       2: putfield      #2                  // Field additionalNamespaces:Ljava/util/Map;
       5: return

  public void setFactory(org.jdom.JDOMFactory);
    Code:
       0: aload_0
       1: aload_1
       2: putfield      #3                  // Field factory:Lorg/jdom/JDOMFactory;
       5: return

  public void setIgnoreWhitespace(boolean);
    Code:
       0: aload_0
       1: iload_1
       2: putfield      #4                  // Field cfgIgnoreWS:Z
       5: return

  public org.jdom.JDOMFactory getFactory();
    Code:
       0: aload_0
       1: getfield      #3                  // Field factory:Lorg/jdom/JDOMFactory;
       4: areturn

  public org.jdom.Document build(javax.xml.stream.XMLStreamReader) throws javax.xml.stream.XMLStreamException;
    Code:
       0: aload_0
       1: iconst_1
       2: putfield      #5                  // Field isReadingMidStream:Z
       5: aload_0
       6: aload_1
       7: invokespecial #6                  // Method buildInternal:(Ljavax/xml/stream/XMLStreamReader;)Lorg/jdom/Document;
      10: areturn

  public org.jdom.Document build(java.io.InputStream) throws javax.xml.stream.XMLStreamException;
    Code:
       0: aload_0
       1: iconst_0
       2: putfield      #5                  // Field isReadingMidStream:Z
       5: aconst_null
       6: astore_2
       7: aload_1
       8: invokestatic  #7                  // Method org/apache/cxf/staxutils/StaxUtils.createXMLStreamReader:(Ljava/io/InputStream;)Ljavax/xml/stream/XMLStreamReader;
      11: astore_2
      12: aload_0
      13: aload_2
      14: invokespecial #6                  // Method buildInternal:(Ljavax/xml/stream/XMLStreamReader;)Lorg/jdom/Document;
      17: astore_3
      18: aload_2
      19: invokestatic  #8                  // Method org/apache/cxf/staxutils/StaxUtils.close:(Ljavax/xml/stream/XMLStreamReader;)V
      22: aload_3
      23: areturn
      24: astore        4
      26: aload_2
      27: invokestatic  #8                  // Method org/apache/cxf/staxutils/StaxUtils.close:(Ljavax/xml/stream/XMLStreamReader;)V
      30: aload         4
      32: athrow
    Exception table:
       from    to  target type
           7    18    24   any
          24    26    24   any

  public org.jdom.Document build(java.io.Reader) throws javax.xml.stream.XMLStreamException;
    Code:
       0: aload_0
       1: iconst_0
       2: putfield      #5                  // Field isReadingMidStream:Z
       5: aconst_null
       6: astore_2
       7: aload_1
       8: invokestatic  #9                  // Method org/apache/cxf/staxutils/StaxUtils.createXMLStreamReader:(Ljava/io/Reader;)Ljavax/xml/stream/XMLStreamReader;
      11: astore_2
      12: aload_0
      13: aload_2
      14: invokespecial #6                  // Method buildInternal:(Ljavax/xml/stream/XMLStreamReader;)Lorg/jdom/Document;
      17: astore_3
      18: aload_2
      19: invokestatic  #8                  // Method org/apache/cxf/staxutils/StaxUtils.close:(Ljavax/xml/stream/XMLStreamReader;)V
      22: aload_3
      23: areturn
      24: astore        4
      26: aload_2
      27: invokestatic  #8                  // Method org/apache/cxf/staxutils/StaxUtils.close:(Ljavax/xml/stream/XMLStreamReader;)V
      30: aload         4
      32: athrow
    Exception table:
       from    to  target type
           7    18    24   any
          24    26    24   any

  private org.jdom.Document buildInternal(javax.xml.stream.XMLStreamReader) throws javax.xml.stream.XMLStreamException;
    Code:
       0: aload_0
       1: getfield      #3                  // Field factory:Lorg/jdom/JDOMFactory;
       4: astore_2
       5: aload_2
       6: ifnonnull     17
       9: new           #10                 // class org/jdom/UncheckedJDOMFactory
      12: dup
      13: invokespecial #11                 // Method org/jdom/UncheckedJDOMFactory."<init>":()V
      16: astore_2
      17: aload_2
      18: aconst_null
      19: invokeinterface #12,  2           // InterfaceMethod org/jdom/JDOMFactory.document:(Lorg/jdom/Element;)Lorg/jdom/Document;
      24: astore_3
      25: aload_0
      26: aload_2
      27: aload_1
      28: aload_3
      29: invokespecial #13                 // Method buildTree:(Lorg/jdom/JDOMFactory;Ljavax/xml/stream/XMLStreamReader;Lorg/jdom/Document;)V
      32: aload_3
      33: areturn

  private void buildTree(org.jdom.JDOMFactory, javax.xml.stream.XMLStreamReader, org.jdom.Document) throws javax.xml.stream.XMLStreamException;
    Code:
       0: aconst_null
       1: astore        4
       3: aload_2
       4: invokeinterface #14,  1           // InterfaceMethod javax/xml/stream/XMLStreamReader.getEventType:()I
       9: istore        5
      11: iload         5
      13: iconst_m1
      14: if_icmpne     25
      17: aload_2
      18: invokeinterface #15,  1           // InterfaceMethod javax/xml/stream/XMLStreamReader.next:()I
      23: istore        5
      25: iconst_0
      26: istore        6
      28: aconst_null
      29: astore        7
      31: iload         5
      33: tableswitch   { // 1 to 15
                     1: 258
                     2: 184
                     3: 235
                     4: 138
                     5: 166
                     6: 125
                     7: 654
                     8: 183
                     9: 218
                    10: 654
                    11: 654
                    12: 108
                    13: 654
                    14: 212
                    15: 212
               default: 654
          }
     108: aload_1
     109: aload_2
     110: invokeinterface #16,  1           // InterfaceMethod javax/xml/stream/XMLStreamReader.getText:()Ljava/lang/String;
     115: invokeinterface #17,  2           // InterfaceMethod org/jdom/JDOMFactory.cdata:(Ljava/lang/String;)Lorg/jdom/CDATA;
     120: astore        7
     122: goto          654
     125: aload_0
     126: getfield      #4                  // Field cfgIgnoreWS:Z
     129: ifeq          138
     132: iconst_1
     133: istore        6
     135: goto          654
     138: aload         4
     140: ifnonnull     149
     143: iconst_1
     144: istore        6
     146: goto          654
     149: aload_1
     150: aload_2
     151: invokeinterface #16,  1           // InterfaceMethod javax/xml/stream/XMLStreamReader.getText:()Ljava/lang/String;
     156: invokeinterface #18,  2           // InterfaceMethod org/jdom/JDOMFactory.text:(Ljava/lang/String;)Lorg/jdom/Text;
     161: astore        7
     163: goto          654
     166: aload_1
     167: aload_2
     168: invokeinterface #16,  1           // InterfaceMethod javax/xml/stream/XMLStreamReader.getText:()Ljava/lang/String;
     173: invokeinterface #19,  2           // InterfaceMethod org/jdom/JDOMFactory.comment:(Ljava/lang/String;)Lorg/jdom/Comment;
     178: astore        7
     180: goto          654
     183: return
     184: aload         4
     186: ifnull        196
     189: aload         4
     191: invokevirtual #20                 // Method org/jdom/Element.getParentElement:()Lorg/jdom/Element;
     194: astore        4
     196: iconst_1
     197: istore        6
     199: aload_0
     200: getfield      #5                  // Field isReadingMidStream:Z
     203: ifeq          654
     206: aload         4
     208: ifnonnull     654
     211: return
     212: iconst_1
     213: istore        6
     215: goto          654
     218: aload_1
     219: aload_2
     220: invokeinterface #21,  1           // InterfaceMethod javax/xml/stream/XMLStreamReader.getLocalName:()Ljava/lang/String;
     225: invokeinterface #22,  2           // InterfaceMethod org/jdom/JDOMFactory.entityRef:(Ljava/lang/String;)Lorg/jdom/EntityRef;
     230: astore        7
     232: goto          654
     235: aload_1
     236: aload_2
     237: invokeinterface #23,  1           // InterfaceMethod javax/xml/stream/XMLStreamReader.getPITarget:()Ljava/lang/String;
     242: aload_2
     243: invokeinterface #24,  1           // InterfaceMethod javax/xml/stream/XMLStreamReader.getPIData:()Ljava/lang/String;
     248: invokeinterface #25,  3           // InterfaceMethod org/jdom/JDOMFactory.processingInstruction:(Ljava/lang/String;Ljava/lang/String;)Lorg/jdom/ProcessingInstruction;
     253: astore        7
     255: goto          654
     258: aconst_null
     259: astore        8
     261: aload_2
     262: invokeinterface #26,  1           // InterfaceMethod javax/xml/stream/XMLStreamReader.getNamespaceURI:()Ljava/lang/String;
     267: astore        9
     269: aload_2
     270: invokeinterface #27,  1           // InterfaceMethod javax/xml/stream/XMLStreamReader.getPrefix:()Ljava/lang/String;
     275: astore        10
     277: aload_2
     278: invokeinterface #21,  1           // InterfaceMethod javax/xml/stream/XMLStreamReader.getLocalName:()Ljava/lang/String;
     283: astore        11
     285: aload         9
     287: ifnull        298
     290: aload         9
     292: invokevirtual #28                 // Method java/lang/String.length:()I
     295: ifne          341
     298: aload         10
     300: ifnull        311
     303: aload         10
     305: invokevirtual #28                 // Method java/lang/String.length:()I
     308: ifne          324
     311: aload_1
     312: aload         11
     314: invokeinterface #29,  2           // InterfaceMethod org/jdom/JDOMFactory.element:(Ljava/lang/String;)Lorg/jdom/Element;
     319: astore        8
     321: goto          355
     324: aload_1
     325: aload         11
     327: aload         10
     329: ldc           #30                 // String
     331: invokeinterface #31,  4           // InterfaceMethod org/jdom/JDOMFactory.element:(Ljava/lang/String;Ljava/lang/String;Ljava/lang/String;)Lorg/jdom/Element;
     336: astore        8
     338: goto          355
     341: aload_1
     342: aload         11
     344: aload         10
     346: aload         9
     348: invokeinterface #31,  4           // InterfaceMethod org/jdom/JDOMFactory.element:(Ljava/lang/String;Ljava/lang/String;Ljava/lang/String;)Lorg/jdom/Element;
     353: astore        8
     355: aload         4
     357: ifnonnull     446
     360: aload_3
     361: aload         8
     363: invokevirtual #32                 // Method org/jdom/Document.setRootElement:(Lorg/jdom/Element;)Lorg/jdom/Document;
     366: pop
     367: aload_0
     368: getfield      #2                  // Field additionalNamespaces:Ljava/util/Map;
     371: ifnull        456
     374: aload_0
     375: getfield      #2                  // Field additionalNamespaces:Ljava/util/Map;
     378: invokeinterface #33,  1           // InterfaceMethod java/util/Map.keySet:()Ljava/util/Set;
     383: invokeinterface #34,  1           // InterfaceMethod java/util/Set.iterator:()Ljava/util/Iterator;
     388: astore        12
     390: aload         12
     392: invokeinterface #35,  1           // InterfaceMethod java/util/Iterator.hasNext:()Z
     397: ifeq          443
     400: aload         12
     402: invokeinterface #36,  1           // InterfaceMethod java/util/Iterator.next:()Ljava/lang/Object;
     407: checkcast     #37                 // class java/lang/String
     410: astore        13
     412: aload_0
     413: getfield      #2                  // Field additionalNamespaces:Ljava/util/Map;
     416: aload         13
     418: invokeinterface #38,  2           // InterfaceMethod java/util/Map.get:(Ljava/lang/Object;)Ljava/lang/Object;
     423: checkcast     #37                 // class java/lang/String
     426: astore        14
     428: aload         8
     430: aload         13
     432: aload         14
     434: invokestatic  #39                 // Method org/jdom/Namespace.getNamespace:(Ljava/lang/String;Ljava/lang/String;)Lorg/jdom/Namespace;
     437: invokevirtual #40                 // Method org/jdom/Element.addNamespaceDeclaration:(Lorg/jdom/Namespace;)V
     440: goto          390
     443: goto          456
     446: aload_1
     447: aload         4
     449: aload         8
     451: invokeinterface #41,  3           // InterfaceMethod org/jdom/JDOMFactory.addContent:(Lorg/jdom/Parent;Lorg/jdom/Content;)V
     456: iconst_0
     457: istore        12
     459: aload_2
     460: invokeinterface #42,  1           // InterfaceMethod javax/xml/stream/XMLStreamReader.getNamespaceCount:()I
     465: istore        13
     467: iload         12
     469: iload         13
     471: if_icmpge     533
     474: aload_2
     475: iload         12
     477: invokeinterface #43,  2           // InterfaceMethod javax/xml/stream/XMLStreamReader.getNamespacePrefix:(I)Ljava/lang/String;
     482: astore        14
     484: aload         14
     486: aload_2
     487: iload         12
     489: invokeinterface #44,  2           // InterfaceMethod javax/xml/stream/XMLStreamReader.getNamespaceURI:(I)Ljava/lang/String;
     494: invokestatic  #39                 // Method org/jdom/Namespace.getNamespace:(Ljava/lang/String;Ljava/lang/String;)Lorg/jdom/Namespace;
     497: astore        15
     499: aload         14
     501: ifnull        517
     504: aload         14
     506: aload         10
     508: invokevirtual #45                 // Method java/lang/String.equals:(Ljava/lang/Object;)Z
     511: ifeq          517
     514: goto          527
     517: aload_1
     518: aload         8
     520: aload         15
     522: invokeinterface #46,  3           // InterfaceMethod org/jdom/JDOMFactory.addNamespaceDeclaration:(Lorg/jdom/Element;Lorg/jdom/Namespace;)V
     527: iinc          12, 1
     530: goto          467
     533: iconst_0
     534: istore        12
     536: aload_2
     537: invokeinterface #47,  1           // InterfaceMethod javax/xml/stream/XMLStreamReader.getAttributeCount:()I
     542: istore        13
     544: iload         12
     546: iload         13
     548: if_icmpge     644
     551: aload_2
     552: iload         12
     554: invokeinterface #48,  2           // InterfaceMethod javax/xml/stream/XMLStreamReader.getAttributePrefix:(I)Ljava/lang/String;
     559: astore        14
     561: aload         14
     563: ifnull        574
     566: aload         14
     568: invokevirtual #28                 // Method java/lang/String.length:()I
     571: ifne          582
     574: getstatic     #49                 // Field org/jdom/Namespace.NO_NAMESPACE:Lorg/jdom/Namespace;
     577: astore        15
     579: goto          591
     582: aload         8
     584: aload         14
     586: invokevirtual #50                 // Method org/jdom/Element.getNamespace:(Ljava/lang/String;)Lorg/jdom/Namespace;
     589: astore        15
     591: aload_1
     592: aload_2
     593: iload         12
     595: invokeinterface #51,  2           // InterfaceMethod javax/xml/stream/XMLStreamReader.getAttributeLocalName:(I)Ljava/lang/String;
     600: aload_2
     601: iload         12
     603: invokeinterface #52,  2           // InterfaceMethod javax/xml/stream/XMLStreamReader.getAttributeValue:(I)Ljava/lang/String;
     608: aload_2
     609: iload         12
     611: invokeinterface #53,  2           // InterfaceMethod javax/xml/stream/XMLStreamReader.getAttributeType:(I)Ljava/lang/String;
     616: invokestatic  #54                 // Method resolveAttrType:(Ljava/lang/String;)I
     619: aload         15
     621: invokeinterface #55,  5           // InterfaceMethod org/jdom/JDOMFactory.attribute:(Ljava/lang/String;Ljava/lang/String;ILorg/jdom/Namespace;)Lorg/jdom/Attribute;
     626: astore        16
     628: aload_1
     629: aload         8
     631: aload         16
     633: invokeinterface #56,  3           // InterfaceMethod org/jdom/JDOMFactory.setAttribute:(Lorg/jdom/Element;Lorg/jdom/Attribute;)V
     638: iinc          12, 1
     641: goto          544
     644: aload         8
     646: astore        4
     648: iconst_1
     649: istore        6
     651: goto          654
     654: iload         6
     656: ifne          691
     659: aload         7
     661: ifnull        691
     664: aload         4
     666: ifnonnull     681
     669: aload_1
     670: aload_3
     671: aload         7
     673: invokeinterface #41,  3           // InterfaceMethod org/jdom/JDOMFactory.addContent:(Lorg/jdom/Parent;Lorg/jdom/Content;)V
     678: goto          691
     681: aload_1
     682: aload         4
     684: aload         7
     686: invokeinterface #41,  3           // InterfaceMethod org/jdom/JDOMFactory.addContent:(Lorg/jdom/Parent;Lorg/jdom/Content;)V
     691: aload_2
     692: invokeinterface #57,  1           // InterfaceMethod javax/xml/stream/XMLStreamReader.hasNext:()Z
     697: ifeq          711
     700: aload_2
     701: invokeinterface #15,  1           // InterfaceMethod javax/xml/stream/XMLStreamReader.next:()I
     706: istore        5
     708: goto          25
     711: return

  private static int resolveAttrType(java.lang.String);
    Code:
       0: aload_0
       1: ifnull        33
       4: aload_0
       5: invokevirtual #28                 // Method java/lang/String.length:()I
       8: ifle          33
      11: getstatic     #58                 // Field ATTR_TYPES:Ljava/util/Map;
      14: aload_0
      15: invokeinterface #38,  2           // InterfaceMethod java/util/Map.get:(Ljava/lang/Object;)Ljava/lang/Object;
      20: checkcast     #59                 // class java/lang/Integer
      23: astore_1
      24: aload_1
      25: ifnull        33
      28: aload_1
      29: invokevirtual #60                 // Method java/lang/Integer.intValue:()I
      32: ireturn
      33: iconst_0
      34: ireturn

  static {};
    Code:
       0: new           #61                 // class java/util/HashMap
       3: dup
       4: bipush        32
       6: invokespecial #62                 // Method java/util/HashMap."<init>":(I)V
       9: putstatic     #58                 // Field ATTR_TYPES:Ljava/util/Map;
      12: getstatic     #58                 // Field ATTR_TYPES:Ljava/util/Map;
      15: ldc           #63                 // String CDATA
      17: new           #59                 // class java/lang/Integer
      20: dup
      21: iconst_1
      22: invokespecial #64                 // Method java/lang/Integer."<init>":(I)V
      25: invokeinterface #65,  3           // InterfaceMethod java/util/Map.put:(Ljava/lang/Object;Ljava/lang/Object;)Ljava/lang/Object;
      30: pop
      31: getstatic     #58                 // Field ATTR_TYPES:Ljava/util/Map;
      34: ldc           #66                 // String cdata
      36: new           #59                 // class java/lang/Integer
      39: dup
      40: iconst_1
      41: invokespecial #64                 // Method java/lang/Integer."<init>":(I)V
      44: invokeinterface #65,  3           // InterfaceMethod java/util/Map.put:(Ljava/lang/Object;Ljava/lang/Object;)Ljava/lang/Object;
      49: pop
      50: getstatic     #58                 // Field ATTR_TYPES:Ljava/util/Map;
      53: ldc           #67                 // String ID
      55: new           #59                 // class java/lang/Integer
      58: dup
      59: iconst_2
      60: invokespecial #64                 // Method java/lang/Integer."<init>":(I)V
      63: invokeinterface #65,  3           // InterfaceMethod java/util/Map.put:(Ljava/lang/Object;Ljava/lang/Object;)Ljava/lang/Object;
      68: pop
      69: getstatic     #58                 // Field ATTR_TYPES:Ljava/util/Map;
      72: ldc           #68                 // String id
      74: new           #59                 // class java/lang/Integer
      77: dup
      78: iconst_2
      79: invokespecial #64                 // Method java/lang/Integer."<init>":(I)V
      82: invokeinterface #65,  3           // InterfaceMethod java/util/Map.put:(Ljava/lang/Object;Ljava/lang/Object;)Ljava/lang/Object;
      87: pop
      88: getstatic     #58                 // Field ATTR_TYPES:Ljava/util/Map;
      91: ldc           #69                 // String IDREF
      93: new           #59                 // class java/lang/Integer
      96: dup
      97: iconst_3
      98: invokespecial #64                 // Method java/lang/Integer."<init>":(I)V
     101: invokeinterface #65,  3           // InterfaceMethod java/util/Map.put:(Ljava/lang/Object;Ljava/lang/Object;)Ljava/lang/Object;
     106: pop
     107: getstatic     #58                 // Field ATTR_TYPES:Ljava/util/Map;
     110: ldc           #70                 // String idref
     112: new           #59                 // class java/lang/Integer
     115: dup
     116: iconst_3
     117: invokespecial #64                 // Method java/lang/Integer."<init>":(I)V
     120: invokeinterface #65,  3           // InterfaceMethod java/util/Map.put:(Ljava/lang/Object;Ljava/lang/Object;)Ljava/lang/Object;
     125: pop
     126: getstatic     #58                 // Field ATTR_TYPES:Ljava/util/Map;
     129: ldc           #71                 // String IDREFS
     131: new           #59                 // class java/lang/Integer
     134: dup
     135: iconst_4
     136: invokespecial #64                 // Method java/lang/Integer."<init>":(I)V
     139: invokeinterface #65,  3           // InterfaceMethod java/util/Map.put:(Ljava/lang/Object;Ljava/lang/Object;)Ljava/lang/Object;
     144: pop
     145: getstatic     #58                 // Field ATTR_TYPES:Ljava/util/Map;
     148: ldc           #72                 // String idrefs
     150: new           #59                 // class java/lang/Integer
     153: dup
     154: iconst_4
     155: invokespecial #64                 // Method java/lang/Integer."<init>":(I)V
     158: invokeinterface #65,  3           // InterfaceMethod java/util/Map.put:(Ljava/lang/Object;Ljava/lang/Object;)Ljava/lang/Object;
     163: pop
     164: getstatic     #58                 // Field ATTR_TYPES:Ljava/util/Map;
     167: ldc           #73                 // String ENTITY
     169: new           #59                 // class java/lang/Integer
     172: dup
     173: iconst_5
     174: invokespecial #64                 // Method java/lang/Integer."<init>":(I)V
     177: invokeinterface #65,  3           // InterfaceMethod java/util/Map.put:(Ljava/lang/Object;Ljava/lang/Object;)Ljava/lang/Object;
     182: pop
     183: getstatic     #58                 // Field ATTR_TYPES:Ljava/util/Map;
     186: ldc           #74                 // String entity
     188: new           #59                 // class java/lang/Integer
     191: dup
     192: iconst_5
     193: invokespecial #64                 // Method java/lang/Integer."<init>":(I)V
     196: invokeinterface #65,  3           // InterfaceMethod java/util/Map.put:(Ljava/lang/Object;Ljava/lang/Object;)Ljava/lang/Object;
     201: pop
     202: getstatic     #58                 // Field ATTR_TYPES:Ljava/util/Map;
     205: ldc           #75                 // String ENTITIES
     207: new           #59                 // class java/lang/Integer
     210: dup
     211: bipush        6
     213: invokespecial #64                 // Method java/lang/Integer."<init>":(I)V
     216: invokeinterface #65,  3           // InterfaceMethod java/util/Map.put:(Ljava/lang/Object;Ljava/lang/Object;)Ljava/lang/Object;
     221: pop
     222: getstatic     #58                 // Field ATTR_TYPES:Ljava/util/Map;
     225: ldc           #76                 // String entities
     227: new           #59                 // class java/lang/Integer
     230: dup
     231: bipush        6
     233: invokespecial #64                 // Method java/lang/Integer."<init>":(I)V
     236: invokeinterface #65,  3           // InterfaceMethod java/util/Map.put:(Ljava/lang/Object;Ljava/lang/Object;)Ljava/lang/Object;
     241: pop
     242: getstatic     #58                 // Field ATTR_TYPES:Ljava/util/Map;
     245: ldc           #77                 // String NMTOKEN
     247: new           #59                 // class java/lang/Integer
     250: dup
     251: bipush        7
     253: invokespecial #64                 // Method java/lang/Integer."<init>":(I)V
     256: invokeinterface #65,  3           // InterfaceMethod java/util/Map.put:(Ljava/lang/Object;Ljava/lang/Object;)Ljava/lang/Object;
     261: pop
     262: getstatic     #58                 // Field ATTR_TYPES:Ljava/util/Map;
     265: ldc           #78                 // String nmtoken
     267: new           #59                 // class java/lang/Integer
     270: dup
     271: bipush        7
     273: invokespecial #64                 // Method java/lang/Integer."<init>":(I)V
     276: invokeinterface #65,  3           // InterfaceMethod java/util/Map.put:(Ljava/lang/Object;Ljava/lang/Object;)Ljava/lang/Object;
     281: pop
     282: getstatic     #58                 // Field ATTR_TYPES:Ljava/util/Map;
     285: ldc           #79                 // String NMTOKENS
     287: new           #59                 // class java/lang/Integer
     290: dup
     291: bipush        8
     293: invokespecial #64                 // Method java/lang/Integer."<init>":(I)V
     296: invokeinterface #65,  3           // InterfaceMethod java/util/Map.put:(Ljava/lang/Object;Ljava/lang/Object;)Ljava/lang/Object;
     301: pop
     302: getstatic     #58                 // Field ATTR_TYPES:Ljava/util/Map;
     305: ldc           #80                 // String nmtokens
     307: new           #59                 // class java/lang/Integer
     310: dup
     311: bipush        8
     313: invokespecial #64                 // Method java/lang/Integer."<init>":(I)V
     316: invokeinterface #65,  3           // InterfaceMethod java/util/Map.put:(Ljava/lang/Object;Ljava/lang/Object;)Ljava/lang/Object;
     321: pop
     322: getstatic     #58                 // Field ATTR_TYPES:Ljava/util/Map;
     325: ldc           #81                 // String NOTATION
     327: new           #59                 // class java/lang/Integer
     330: dup
     331: bipush        9
     333: invokespecial #64                 // Method java/lang/Integer."<init>":(I)V
     336: invokeinterface #65,  3           // InterfaceMethod java/util/Map.put:(Ljava/lang/Object;Ljava/lang/Object;)Ljava/lang/Object;
     341: pop
     342: getstatic     #58                 // Field ATTR_TYPES:Ljava/util/Map;
     345: ldc           #82                 // String notation
     347: new           #59                 // class java/lang/Integer
     350: dup
     351: bipush        9
     353: invokespecial #64                 // Method java/lang/Integer."<init>":(I)V
     356: invokeinterface #65,  3           // InterfaceMethod java/util/Map.put:(Ljava/lang/Object;Ljava/lang/Object;)Ljava/lang/Object;
     361: pop
     362: getstatic     #58                 // Field ATTR_TYPES:Ljava/util/Map;
     365: ldc           #83                 // String ENUMERATED
     367: new           #59                 // class java/lang/Integer
     370: dup
     371: bipush        10
     373: invokespecial #64                 // Method java/lang/Integer."<init>":(I)V
     376: invokeinterface #65,  3           // InterfaceMethod java/util/Map.put:(Ljava/lang/Object;Ljava/lang/Object;)Ljava/lang/Object;
     381: pop
     382: getstatic     #58                 // Field ATTR_TYPES:Ljava/util/Map;
     385: ldc           #84                 // String enumerated
     387: new           #59                 // class java/lang/Integer
     390: dup
     391: bipush        10
     393: invokespecial #64                 // Method java/lang/Integer."<init>":(I)V
     396: invokeinterface #65,  3           // InterfaceMethod java/util/Map.put:(Ljava/lang/Object;Ljava/lang/Object;)Ljava/lang/Object;
     401: pop
     402: return
}
