Compiled from "TpClusterWrapper.java"
public class org.hpccsystems.ws.client.wrappers.gen.wstopology.TpClusterWrapper {
  protected java.lang.String local_type;

  protected java.lang.String local_name;

  protected java.lang.String local_queueName;

  protected java.lang.String local_build;

  protected java.lang.String local_directory;

  protected java.lang.String local_logDirectory;

  protected java.lang.String local_desc;

  protected java.lang.String local_path;

  protected java.lang.String local_dataModel;

  protected int local_oS;

  protected boolean local_hasThorSpareProcess;

  protected org.hpccsystems.ws.client.wrappers.gen.wstopology.ArrayOfTpMachineWrapper local_tpMachines;

  public org.hpccsystems.ws.client.wrappers.gen.wstopology.TpClusterWrapper();
    Code:
       0: aload_0
       1: invokespecial #1                  // Method java/lang/Object."<init>":()V
       4: return

  public org.hpccsystems.ws.client.wrappers.gen.wstopology.TpClusterWrapper(org.hpccsystems.ws.client.gen.axis2.wstopology.v1_30.TpCluster);
    Code:
       0: aload_0
       1: invokespecial #1                  // Method java/lang/Object."<init>":()V
       4: aload_0
       5: aload_1
       6: invokespecial #2                  // Method copy:(Lorg/hpccsystems/ws/client/gen/axis2/wstopology/v1_30/TpCluster;)V
       9: return

  public org.hpccsystems.ws.client.wrappers.gen.wstopology.TpClusterWrapper(java.lang.String, java.lang.String, java.lang.String, java.lang.String, java.lang.String, java.lang.String, java.lang.String, java.lang.String, java.lang.String, int, boolean, org.hpccsystems.ws.client.wrappers.gen.wstopology.ArrayOfTpMachineWrapper);
    Code:
       0: aload_0
       1: invokespecial #1                  // Method java/lang/Object."<init>":()V
       4: aload_0
       5: aload_1
       6: putfield      #3                  // Field local_type:Ljava/lang/String;
       9: aload_0
      10: aload_2
      11: putfield      #4                  // Field local_name:Ljava/lang/String;
      14: aload_0
      15: aload_3
      16: putfield      #5                  // Field local_queueName:Ljava/lang/String;
      19: aload_0
      20: aload         4
      22: putfield      #6                  // Field local_build:Ljava/lang/String;
      25: aload_0
      26: aload         5
      28: putfield      #7                  // Field local_directory:Ljava/lang/String;
      31: aload_0
      32: aload         6
      34: putfield      #8                  // Field local_logDirectory:Ljava/lang/String;
      37: aload_0
      38: aload         7
      40: putfield      #9                  // Field local_desc:Ljava/lang/String;
      43: aload_0
      44: aload         8
      46: putfield      #10                 // Field local_path:Ljava/lang/String;
      49: aload_0
      50: aload         9
      52: putfield      #11                 // Field local_dataModel:Ljava/lang/String;
      55: aload_0
      56: iload         10
      58: putfield      #12                 // Field local_oS:I
      61: aload_0
      62: iload         11
      64: putfield      #13                 // Field local_hasThorSpareProcess:Z
      67: aload_0
      68: aload         12
      70: putfield      #14                 // Field local_tpMachines:Lorg/hpccsystems/ws/client/wrappers/gen/wstopology/ArrayOfTpMachineWrapper;
      73: return

  private void copy(org.hpccsystems.ws.client.gen.axis2.wstopology.v1_30.TpCluster);
    Code:
       0: aload_1
       1: ifnonnull     5
       4: return
       5: aload_0
       6: aload_1
       7: invokevirtual #15                 // Method org/hpccsystems/ws/client/gen/axis2/wstopology/v1_30/TpCluster.getType:()Ljava/lang/String;
      10: putfield      #3                  // Field local_type:Ljava/lang/String;
      13: aload_0
      14: aload_1
      15: invokevirtual #16                 // Method org/hpccsystems/ws/client/gen/axis2/wstopology/v1_30/TpCluster.getName:()Ljava/lang/String;
      18: putfield      #4                  // Field local_name:Ljava/lang/String;
      21: aload_0
      22: aload_1
      23: invokevirtual #17                 // Method org/hpccsystems/ws/client/gen/axis2/wstopology/v1_30/TpCluster.getQueueName:()Ljava/lang/String;
      26: putfield      #5                  // Field local_queueName:Ljava/lang/String;
      29: aload_0
      30: aload_1
      31: invokevirtual #18                 // Method org/hpccsystems/ws/client/gen/axis2/wstopology/v1_30/TpCluster.getBuild:()Ljava/lang/String;
      34: putfield      #6                  // Field local_build:Ljava/lang/String;
      37: aload_0
      38: aload_1
      39: invokevirtual #19                 // Method org/hpccsystems/ws/client/gen/axis2/wstopology/v1_30/TpCluster.getDirectory:()Ljava/lang/String;
      42: putfield      #7                  // Field local_directory:Ljava/lang/String;
      45: aload_0
      46: aload_1
      47: invokevirtual #20                 // Method org/hpccsystems/ws/client/gen/axis2/wstopology/v1_30/TpCluster.getLogDirectory:()Ljava/lang/String;
      50: putfield      #8                  // Field local_logDirectory:Ljava/lang/String;
      53: aload_0
      54: aload_1
      55: invokevirtual #21                 // Method org/hpccsystems/ws/client/gen/axis2/wstopology/v1_30/TpCluster.getDesc:()Ljava/lang/String;
      58: putfield      #9                  // Field local_desc:Ljava/lang/String;
      61: aload_0
      62: aload_1
      63: invokevirtual #22                 // Method org/hpccsystems/ws/client/gen/axis2/wstopology/v1_30/TpCluster.getPath:()Ljava/lang/String;
      66: putfield      #10                 // Field local_path:Ljava/lang/String;
      69: aload_0
      70: aload_1
      71: invokevirtual #23                 // Method org/hpccsystems/ws/client/gen/axis2/wstopology/v1_30/TpCluster.getDataModel:()Ljava/lang/String;
      74: putfield      #11                 // Field local_dataModel:Ljava/lang/String;
      77: aload_0
      78: aload_1
      79: invokevirtual #24                 // Method org/hpccsystems/ws/client/gen/axis2/wstopology/v1_30/TpCluster.getOS:()I
      82: putfield      #12                 // Field local_oS:I
      85: aload_0
      86: aload_1
      87: invokevirtual #25                 // Method org/hpccsystems/ws/client/gen/axis2/wstopology/v1_30/TpCluster.getHasThorSpareProcess:()Z
      90: putfield      #13                 // Field local_hasThorSpareProcess:Z
      93: aload_1
      94: invokevirtual #26                 // Method org/hpccsystems/ws/client/gen/axis2/wstopology/v1_30/TpCluster.getTpMachines:()Lorg/hpccsystems/ws/client/gen/axis2/wstopology/v1_30/ArrayOfTpMachine;
      97: ifnull        115
     100: aload_0
     101: new           #27                 // class org/hpccsystems/ws/client/wrappers/gen/wstopology/ArrayOfTpMachineWrapper
     104: dup
     105: aload_1
     106: invokevirtual #26                 // Method org/hpccsystems/ws/client/gen/axis2/wstopology/v1_30/TpCluster.getTpMachines:()Lorg/hpccsystems/ws/client/gen/axis2/wstopology/v1_30/ArrayOfTpMachine;
     109: invokespecial #28                 // Method org/hpccsystems/ws/client/wrappers/gen/wstopology/ArrayOfTpMachineWrapper."<init>":(Lorg/hpccsystems/ws/client/gen/axis2/wstopology/v1_30/ArrayOfTpMachine;)V
     112: putfield      #14                 // Field local_tpMachines:Lorg/hpccsystems/ws/client/wrappers/gen/wstopology/ArrayOfTpMachineWrapper;
     115: return

  public java.lang.String toString();
    Code:
       0: new           #29                 // class java/lang/StringBuilder
       3: dup
       4: invokespecial #30                 // Method java/lang/StringBuilder."<init>":()V
       7: ldc           #31                 // String TpClusterWrapper [type =
       9: invokevirtual #32                 // Method java/lang/StringBuilder.append:(Ljava/lang/String;)Ljava/lang/StringBuilder;
      12: aload_0
      13: getfield      #3                  // Field local_type:Ljava/lang/String;
      16: invokevirtual #32                 // Method java/lang/StringBuilder.append:(Ljava/lang/String;)Ljava/lang/StringBuilder;
      19: ldc           #33                 // String , name =
      21: invokevirtual #32                 // Method java/lang/StringBuilder.append:(Ljava/lang/String;)Ljava/lang/StringBuilder;
      24: aload_0
      25: getfield      #4                  // Field local_name:Ljava/lang/String;
      28: invokevirtual #32                 // Method java/lang/StringBuilder.append:(Ljava/lang/String;)Ljava/lang/StringBuilder;
      31: ldc           #34                 // String , queueName =
      33: invokevirtual #32                 // Method java/lang/StringBuilder.append:(Ljava/lang/String;)Ljava/lang/StringBuilder;
      36: aload_0
      37: getfield      #5                  // Field local_queueName:Ljava/lang/String;
      40: invokevirtual #32                 // Method java/lang/StringBuilder.append:(Ljava/lang/String;)Ljava/lang/StringBuilder;
      43: ldc           #35                 // String , build =
      45: invokevirtual #32                 // Method java/lang/StringBuilder.append:(Ljava/lang/String;)Ljava/lang/StringBuilder;
      48: aload_0
      49: getfield      #6                  // Field local_build:Ljava/lang/String;
      52: invokevirtual #32                 // Method java/lang/StringBuilder.append:(Ljava/lang/String;)Ljava/lang/StringBuilder;
      55: ldc           #36                 // String , directory =
      57: invokevirtual #32                 // Method java/lang/StringBuilder.append:(Ljava/lang/String;)Ljava/lang/StringBuilder;
      60: aload_0
      61: getfield      #7                  // Field local_directory:Ljava/lang/String;
      64: invokevirtual #32                 // Method java/lang/StringBuilder.append:(Ljava/lang/String;)Ljava/lang/StringBuilder;
      67: ldc           #37                 // String , logDirectory =
      69: invokevirtual #32                 // Method java/lang/StringBuilder.append:(Ljava/lang/String;)Ljava/lang/StringBuilder;
      72: aload_0
      73: getfield      #8                  // Field local_logDirectory:Ljava/lang/String;
      76: invokevirtual #32                 // Method java/lang/StringBuilder.append:(Ljava/lang/String;)Ljava/lang/StringBuilder;
      79: ldc           #38                 // String , desc =
      81: invokevirtual #32                 // Method java/lang/StringBuilder.append:(Ljava/lang/String;)Ljava/lang/StringBuilder;
      84: aload_0
      85: getfield      #9                  // Field local_desc:Ljava/lang/String;
      88: invokevirtual #32                 // Method java/lang/StringBuilder.append:(Ljava/lang/String;)Ljava/lang/StringBuilder;
      91: ldc           #39                 // String , path =
      93: invokevirtual #32                 // Method java/lang/StringBuilder.append:(Ljava/lang/String;)Ljava/lang/StringBuilder;
      96: aload_0
      97: getfield      #10                 // Field local_path:Ljava/lang/String;
     100: invokevirtual #32                 // Method java/lang/StringBuilder.append:(Ljava/lang/String;)Ljava/lang/StringBuilder;
     103: ldc           #40                 // String , dataModel =
     105: invokevirtual #32                 // Method java/lang/StringBuilder.append:(Ljava/lang/String;)Ljava/lang/StringBuilder;
     108: aload_0
     109: getfield      #11                 // Field local_dataModel:Ljava/lang/String;
     112: invokevirtual #32                 // Method java/lang/StringBuilder.append:(Ljava/lang/String;)Ljava/lang/StringBuilder;
     115: ldc           #41                 // String , oS =
     117: invokevirtual #32                 // Method java/lang/StringBuilder.append:(Ljava/lang/String;)Ljava/lang/StringBuilder;
     120: aload_0
     121: getfield      #12                 // Field local_oS:I
     124: invokevirtual #42                 // Method java/lang/StringBuilder.append:(I)Ljava/lang/StringBuilder;
     127: ldc           #43                 // String , hasThorSpareProcess =
     129: invokevirtual #32                 // Method java/lang/StringBuilder.append:(Ljava/lang/String;)Ljava/lang/StringBuilder;
     132: aload_0
     133: getfield      #13                 // Field local_hasThorSpareProcess:Z
     136: invokevirtual #44                 // Method java/lang/StringBuilder.append:(Z)Ljava/lang/StringBuilder;
     139: ldc           #45                 // String , tpMachines =
     141: invokevirtual #32                 // Method java/lang/StringBuilder.append:(Ljava/lang/String;)Ljava/lang/StringBuilder;
     144: aload_0
     145: getfield      #14                 // Field local_tpMachines:Lorg/hpccsystems/ws/client/wrappers/gen/wstopology/ArrayOfTpMachineWrapper;
     148: invokevirtual #46                 // Method java/lang/StringBuilder.append:(Ljava/lang/Object;)Ljava/lang/StringBuilder;
     151: ldc           #47                 // String ]
     153: invokevirtual #32                 // Method java/lang/StringBuilder.append:(Ljava/lang/String;)Ljava/lang/StringBuilder;
     156: invokevirtual #48                 // Method java/lang/StringBuilder.toString:()Ljava/lang/String;
     159: areturn

  public org.hpccsystems.ws.client.gen.axis2.wstopology.v1_30.TpCluster getRaw();
    Code:
       0: new           #49                 // class org/hpccsystems/ws/client/gen/axis2/wstopology/v1_30/TpCluster
       3: dup
       4: invokespecial #50                 // Method org/hpccsystems/ws/client/gen/axis2/wstopology/v1_30/TpCluster."<init>":()V
       7: astore_1
       8: aload_1
       9: aload_0
      10: getfield      #3                  // Field local_type:Ljava/lang/String;
      13: invokevirtual #51                 // Method org/hpccsystems/ws/client/gen/axis2/wstopology/v1_30/TpCluster.setType:(Ljava/lang/String;)V
      16: aload_1
      17: aload_0
      18: getfield      #4                  // Field local_name:Ljava/lang/String;
      21: invokevirtual #52                 // Method org/hpccsystems/ws/client/gen/axis2/wstopology/v1_30/TpCluster.setName:(Ljava/lang/String;)V
      24: aload_1
      25: aload_0
      26: getfield      #5                  // Field local_queueName:Ljava/lang/String;
      29: invokevirtual #53                 // Method org/hpccsystems/ws/client/gen/axis2/wstopology/v1_30/TpCluster.setQueueName:(Ljava/lang/String;)V
      32: aload_1
      33: aload_0
      34: getfield      #6                  // Field local_build:Ljava/lang/String;
      37: invokevirtual #54                 // Method org/hpccsystems/ws/client/gen/axis2/wstopology/v1_30/TpCluster.setBuild:(Ljava/lang/String;)V
      40: aload_1
      41: aload_0
      42: getfield      #7                  // Field local_directory:Ljava/lang/String;
      45: invokevirtual #55                 // Method org/hpccsystems/ws/client/gen/axis2/wstopology/v1_30/TpCluster.setDirectory:(Ljava/lang/String;)V
      48: aload_1
      49: aload_0
      50: getfield      #8                  // Field local_logDirectory:Ljava/lang/String;
      53: invokevirtual #56                 // Method org/hpccsystems/ws/client/gen/axis2/wstopology/v1_30/TpCluster.setLogDirectory:(Ljava/lang/String;)V
      56: aload_1
      57: aload_0
      58: getfield      #9                  // Field local_desc:Ljava/lang/String;
      61: invokevirtual #57                 // Method org/hpccsystems/ws/client/gen/axis2/wstopology/v1_30/TpCluster.setDesc:(Ljava/lang/String;)V
      64: aload_1
      65: aload_0
      66: getfield      #10                 // Field local_path:Ljava/lang/String;
      69: invokevirtual #58                 // Method org/hpccsystems/ws/client/gen/axis2/wstopology/v1_30/TpCluster.setPath:(Ljava/lang/String;)V
      72: aload_1
      73: aload_0
      74: getfield      #11                 // Field local_dataModel:Ljava/lang/String;
      77: invokevirtual #59                 // Method org/hpccsystems/ws/client/gen/axis2/wstopology/v1_30/TpCluster.setDataModel:(Ljava/lang/String;)V
      80: aload_1
      81: aload_0
      82: getfield      #12                 // Field local_oS:I
      85: invokevirtual #60                 // Method org/hpccsystems/ws/client/gen/axis2/wstopology/v1_30/TpCluster.setOS:(I)V
      88: aload_1
      89: aload_0
      90: getfield      #13                 // Field local_hasThorSpareProcess:Z
      93: invokevirtual #61                 // Method org/hpccsystems/ws/client/gen/axis2/wstopology/v1_30/TpCluster.setHasThorSpareProcess:(Z)V
      96: aload_1
      97: areturn

  public void setType(java.lang.String);
    Code:
       0: aload_0
       1: aload_1
       2: putfield      #3                  // Field local_type:Ljava/lang/String;
       5: return

  public java.lang.String getType();
    Code:
       0: aload_0
       1: getfield      #3                  // Field local_type:Ljava/lang/String;
       4: areturn

  public void setName(java.lang.String);
    Code:
       0: aload_0
       1: aload_1
       2: putfield      #4                  // Field local_name:Ljava/lang/String;
       5: return

  public java.lang.String getName();
    Code:
       0: aload_0
       1: getfield      #4                  // Field local_name:Ljava/lang/String;
       4: areturn

  public void setQueueName(java.lang.String);
    Code:
       0: aload_0
       1: aload_1
       2: putfield      #5                  // Field local_queueName:Ljava/lang/String;
       5: return

  public java.lang.String getQueueName();
    Code:
       0: aload_0
       1: getfield      #5                  // Field local_queueName:Ljava/lang/String;
       4: areturn

  public void setBuild(java.lang.String);
    Code:
       0: aload_0
       1: aload_1
       2: putfield      #6                  // Field local_build:Ljava/lang/String;
       5: return

  public java.lang.String getBuild();
    Code:
       0: aload_0
       1: getfield      #6                  // Field local_build:Ljava/lang/String;
       4: areturn

  public void setDirectory(java.lang.String);
    Code:
       0: aload_0
       1: aload_1
       2: putfield      #7                  // Field local_directory:Ljava/lang/String;
       5: return

  public java.lang.String getDirectory();
    Code:
       0: aload_0
       1: getfield      #7                  // Field local_directory:Ljava/lang/String;
       4: areturn

  public void setLogDirectory(java.lang.String);
    Code:
       0: aload_0
       1: aload_1
       2: putfield      #8                  // Field local_logDirectory:Ljava/lang/String;
       5: return

  public java.lang.String getLogDirectory();
    Code:
       0: aload_0
       1: getfield      #8                  // Field local_logDirectory:Ljava/lang/String;
       4: areturn

  public void setDesc(java.lang.String);
    Code:
       0: aload_0
       1: aload_1
       2: putfield      #9                  // Field local_desc:Ljava/lang/String;
       5: return

  public java.lang.String getDesc();
    Code:
       0: aload_0
       1: getfield      #9                  // Field local_desc:Ljava/lang/String;
       4: areturn

  public void setPath(java.lang.String);
    Code:
       0: aload_0
       1: aload_1
       2: putfield      #10                 // Field local_path:Ljava/lang/String;
       5: return

  public java.lang.String getPath();
    Code:
       0: aload_0
       1: getfield      #10                 // Field local_path:Ljava/lang/String;
       4: areturn

  public void setDataModel(java.lang.String);
    Code:
       0: aload_0
       1: aload_1
       2: putfield      #11                 // Field local_dataModel:Ljava/lang/String;
       5: return

  public java.lang.String getDataModel();
    Code:
       0: aload_0
       1: getfield      #11                 // Field local_dataModel:Ljava/lang/String;
       4: areturn

  public void setOS(int);
    Code:
       0: aload_0
       1: iload_1
       2: putfield      #12                 // Field local_oS:I
       5: return

  public int getOS();
    Code:
       0: aload_0
       1: getfield      #12                 // Field local_oS:I
       4: ireturn

  public void setHasThorSpareProcess(boolean);
    Code:
       0: aload_0
       1: iload_1
       2: putfield      #13                 // Field local_hasThorSpareProcess:Z
       5: return

  public boolean getHasThorSpareProcess();
    Code:
       0: aload_0
       1: getfield      #13                 // Field local_hasThorSpareProcess:Z
       4: ireturn

  public void setTpMachines(org.hpccsystems.ws.client.wrappers.gen.wstopology.ArrayOfTpMachineWrapper);
    Code:
       0: aload_0
       1: aload_1
       2: putfield      #14                 // Field local_tpMachines:Lorg/hpccsystems/ws/client/wrappers/gen/wstopology/ArrayOfTpMachineWrapper;
       5: return

  public org.hpccsystems.ws.client.wrappers.gen.wstopology.ArrayOfTpMachineWrapper getTpMachines();
    Code:
       0: aload_0
       1: getfield      #14                 // Field local_tpMachines:Lorg/hpccsystems/ws/client/wrappers/gen/wstopology/ArrayOfTpMachineWrapper;
       4: areturn
}
