Compiled from "ValidatorHttpHandler.scala"
public final class io.youi.server.handler.ValidatorHttpHandler$$anonfun$1 extends scala.runtime.AbstractPartialFunction<io.youi.server.validation.ValidationResult, io.youi.server.validation.ValidationResult> implements scala.Serializable {
  public static final long serialVersionUID;

  public final <A1 extends io.youi.server.validation.ValidationResult, B1> B1 applyOrElse(A1, scala.Function1<A1, B1>);
    Code:
       0: aload_1
       1: astore_3
       2: aload_3
       3: getstatic     #25                 // Field io/youi/server/validation/ValidationResult$Continue$.MODULE$:Lio/youi/server/validation/ValidationResult$Continue$;
       6: astore        4
       8: dup
       9: ifnonnull     21
      12: pop
      13: aload         4
      15: ifnull        29
      18: goto          41
      21: aload         4
      23: invokevirtual #31                 // Method java/lang/Object.equals:(Ljava/lang/Object;)Z
      26: ifeq          41
      29: aload_2
      30: aload_1
      31: invokeinterface #37,  2           // InterfaceMethod scala/Function1.apply:(Ljava/lang/Object;)Ljava/lang/Object;
      36: astore        5
      38: goto          44
      41: aload_3
      42: astore        5
      44: aload         5
      46: areturn

  public final boolean isDefinedAt(io.youi.server.validation.ValidationResult);
    Code:
       0: aload_1
       1: astore_2
       2: aload_2
       3: getstatic     #25                 // Field io/youi/server/validation/ValidationResult$Continue$.MODULE$:Lio/youi/server/validation/ValidationResult$Continue$;
       6: astore_3
       7: dup
       8: ifnonnull     19
      11: pop
      12: aload_3
      13: ifnull        26
      16: goto          32
      19: aload_3
      20: invokevirtual #31                 // Method java/lang/Object.equals:(Ljava/lang/Object;)Z
      23: ifeq          32
      26: iconst_0
      27: istore        4
      29: goto          35
      32: iconst_1
      33: istore        4
      35: iload         4
      37: ireturn

  public final boolean isDefinedAt(java.lang.Object);
    Code:
       0: aload_0
       1: aload_1
       2: checkcast     #45                 // class io/youi/server/validation/ValidationResult
       5: invokevirtual #49                 // Method isDefinedAt:(Lio/youi/server/validation/ValidationResult;)Z
       8: ireturn

  public final java.lang.Object applyOrElse(java.lang.Object, scala.Function1);
    Code:
       0: aload_0
       1: aload_1
       2: checkcast     #45                 // class io/youi/server/validation/ValidationResult
       5: aload_2
       6: invokevirtual #54                 // Method applyOrElse:(Lio/youi/server/validation/ValidationResult;Lscala/Function1;)Ljava/lang/Object;
       9: areturn

  public io.youi.server.handler.ValidatorHttpHandler$$anonfun$1();
    Code:
       0: aload_0
       1: invokespecial #58                 // Method scala/runtime/AbstractPartialFunction."<init>":()V
       4: return
}
