Compiled from "MvcRequestMatcherProvider.java"
public class org.springframework.boot.autoconfigure.security.servlet.MvcRequestMatcherProvider implements org.springframework.boot.autoconfigure.security.servlet.RequestMatcherProvider {
  private final org.springframework.web.servlet.handler.HandlerMappingIntrospector introspector;

  public org.springframework.boot.autoconfigure.security.servlet.MvcRequestMatcherProvider(org.springframework.web.servlet.handler.HandlerMappingIntrospector);
    Code:
       0: aload_0
       1: invokespecial #1                  // Method java/lang/Object."<init>":()V
       4: aload_0
       5: aload_1
       6: putfield      #2                  // Field introspector:Lorg/springframework/web/servlet/handler/HandlerMappingIntrospector;
       9: return

  public org.springframework.security.web.util.matcher.RequestMatcher getRequestMatcher(java.lang.String);
    Code:
       0: new           #3                  // class org/springframework/security/web/servlet/util/matcher/MvcRequestMatcher
       3: dup
       4: aload_0
       5: getfield      #2                  // Field introspector:Lorg/springframework/web/servlet/handler/HandlerMappingIntrospector;
       8: aload_1
       9: invokespecial #4                  // Method org/springframework/security/web/servlet/util/matcher/MvcRequestMatcher."<init>":(Lorg/springframework/web/servlet/handler/HandlerMappingIntrospector;Ljava/lang/String;)V
      12: areturn
}
