Compiled from "ReceiveQueueBuffer.java"
class com.amazonaws.services.sqs.buffered.ReceiveQueueBuffer$ReceiveMessageBatchTask implements java.lang.Runnable {
  private java.lang.Exception exception;

  private java.util.List<com.amazonaws.services.sqs.model.Message> messages;

  private long visibilityDeadlineNano;

  private boolean open;

  private com.amazonaws.services.sqs.buffered.ReceiveQueueBuffer parentBuffer;

  final com.amazonaws.services.sqs.buffered.ReceiveQueueBuffer this$0;

  com.amazonaws.services.sqs.buffered.ReceiveQueueBuffer$ReceiveMessageBatchTask(com.amazonaws.services.sqs.buffered.ReceiveQueueBuffer, com.amazonaws.services.sqs.buffered.ReceiveQueueBuffer);
    Code:
       0: aload_0
       1: aload_1
       2: putfield      #1                  // Field this$0:Lcom/amazonaws/services/sqs/buffered/ReceiveQueueBuffer;
       5: aload_0
       6: invokespecial #2                  // Method java/lang/Object."<init>":()V
       9: aload_0
      10: aconst_null
      11: putfield      #3                  // Field exception:Ljava/lang/Exception;
      14: aload_0
      15: iconst_0
      16: putfield      #4                  // Field open:Z
      19: aload_0
      20: aload_2
      21: putfield      #5                  // Field parentBuffer:Lcom/amazonaws/services/sqs/buffered/ReceiveQueueBuffer;
      24: aload_0
      25: invokestatic  #6                  // Method java/util/Collections.emptyList:()Ljava/util/List;
      28: putfield      #7                  // Field messages:Ljava/util/List;
      31: return

  synchronized boolean isEmpty();
    Code:
       0: aload_0
       1: getfield      #4                  // Field open:Z
       4: ifne          17
       7: new           #8                  // class java/lang/IllegalStateException
      10: dup
      11: ldc           #9                  // String batch is not open
      13: invokespecial #10                 // Method java/lang/IllegalStateException."<init>":(Ljava/lang/String;)V
      16: athrow
      17: aload_0
      18: getfield      #7                  // Field messages:Ljava/util/List;
      21: invokeinterface #11,  1           // InterfaceMethod java/util/List.isEmpty:()Z
      26: ireturn

  synchronized java.lang.Exception getException();
    Code:
       0: aload_0
       1: getfield      #4                  // Field open:Z
       4: ifne          17
       7: new           #8                  // class java/lang/IllegalStateException
      10: dup
      11: ldc           #9                  // String batch is not open
      13: invokespecial #10                 // Method java/lang/IllegalStateException."<init>":(Ljava/lang/String;)V
      16: athrow
      17: aload_0
      18: getfield      #3                  // Field exception:Ljava/lang/Exception;
      21: areturn

  synchronized com.amazonaws.services.sqs.model.Message removeMessage();
    Code:
       0: aload_0
       1: getfield      #4                  // Field open:Z
       4: ifne          17
       7: new           #8                  // class java/lang/IllegalStateException
      10: dup
      11: ldc           #9                  // String batch is not open
      13: invokespecial #10                 // Method java/lang/IllegalStateException."<init>":(Ljava/lang/String;)V
      16: athrow
      17: aload_0
      18: invokevirtual #12                 // Method isExpired:()Z
      21: ifeq          35
      24: aload_0
      25: getfield      #7                  // Field messages:Ljava/util/List;
      28: invokeinterface #13,  1           // InterfaceMethod java/util/List.clear:()V
      33: aconst_null
      34: areturn
      35: aload_0
      36: getfield      #7                  // Field messages:Ljava/util/List;
      39: invokeinterface #11,  1           // InterfaceMethod java/util/List.isEmpty:()Z
      44: ifeq          49
      47: aconst_null
      48: areturn
      49: aload_0
      50: getfield      #7                  // Field messages:Ljava/util/List;
      53: aload_0
      54: getfield      #7                  // Field messages:Ljava/util/List;
      57: invokeinterface #14,  1           // InterfaceMethod java/util/List.size:()I
      62: iconst_1
      63: isub
      64: invokeinterface #15,  2           // InterfaceMethod java/util/List.remove:(I)Ljava/lang/Object;
      69: checkcast     #16                 // class com/amazonaws/services/sqs/model/Message
      72: areturn

  boolean isExpired();
    Code:
       0: invokestatic  #17                 // Method java/lang/System.nanoTime:()J
       3: aload_0
       4: getfield      #18                 // Field visibilityDeadlineNano:J
       7: lcmp
       8: ifle          15
      11: iconst_1
      12: goto          16
      15: iconst_0
      16: ireturn

  synchronized void clear();
    Code:
       0: aload_0
       1: getfield      #4                  // Field open:Z
       4: ifne          17
       7: new           #8                  // class java/lang/IllegalStateException
      10: dup
      11: ldc           #9                  // String batch is not open
      13: invokespecial #10                 // Method java/lang/IllegalStateException."<init>":(Ljava/lang/String;)V
      16: athrow
      17: aload_0
      18: invokevirtual #12                 // Method isExpired:()Z
      21: ifne          196
      24: new           #19                 // class com/amazonaws/services/sqs/model/ChangeMessageVisibilityBatchRequest
      27: dup
      28: invokespecial #20                 // Method com/amazonaws/services/sqs/model/ChangeMessageVisibilityBatchRequest."<init>":()V
      31: aload_0
      32: getfield      #1                  // Field this$0:Lcom/amazonaws/services/sqs/buffered/ReceiveQueueBuffer;
      35: invokestatic  #21                 // Method com/amazonaws/services/sqs/buffered/ReceiveQueueBuffer.access$000:(Lcom/amazonaws/services/sqs/buffered/ReceiveQueueBuffer;)Ljava/lang/String;
      38: invokevirtual #22                 // Method com/amazonaws/services/sqs/model/ChangeMessageVisibilityBatchRequest.withQueueUrl:(Ljava/lang/String;)Lcom/amazonaws/services/sqs/model/ChangeMessageVisibilityBatchRequest;
      41: astore_1
      42: aload_1
      43: getstatic     #23                 // Field com/amazonaws/services/sqs/buffered/AmazonSQSBufferedAsyncClient.USER_AGENT:Ljava/lang/String;
      46: invokestatic  #24                 // Method com/amazonaws/services/sqs/buffered/ResultConverter.appendUserAgent:(Lcom/amazonaws/AmazonWebServiceRequest;Ljava/lang/String;)Lcom/amazonaws/AmazonWebServiceRequest;
      49: pop
      50: new           #25                 // class java/util/ArrayList
      53: dup
      54: aload_0
      55: getfield      #7                  // Field messages:Ljava/util/List;
      58: invokeinterface #14,  1           // InterfaceMethod java/util/List.size:()I
      63: invokespecial #26                 // Method java/util/ArrayList."<init>":(I)V
      66: astore_2
      67: iconst_0
      68: istore_3
      69: aload_0
      70: getfield      #7                  // Field messages:Ljava/util/List;
      73: invokeinterface #27,  1           // InterfaceMethod java/util/List.iterator:()Ljava/util/Iterator;
      78: astore        4
      80: aload         4
      82: invokeinterface #28,  1           // InterfaceMethod java/util/Iterator.hasNext:()Z
      87: ifeq          144
      90: aload         4
      92: invokeinterface #29,  1           // InterfaceMethod java/util/Iterator.next:()Ljava/lang/Object;
      97: checkcast     #16                 // class com/amazonaws/services/sqs/model/Message
     100: astore        5
     102: aload_2
     103: new           #30                 // class com/amazonaws/services/sqs/model/ChangeMessageVisibilityBatchRequestEntry
     106: dup
     107: invokespecial #31                 // Method com/amazonaws/services/sqs/model/ChangeMessageVisibilityBatchRequestEntry."<init>":()V
     110: iload_3
     111: invokestatic  #32                 // Method java/lang/Integer.toString:(I)Ljava/lang/String;
     114: invokevirtual #33                 // Method com/amazonaws/services/sqs/model/ChangeMessageVisibilityBatchRequestEntry.withId:(Ljava/lang/String;)Lcom/amazonaws/services/sqs/model/ChangeMessageVisibilityBatchRequestEntry;
     117: aload         5
     119: invokevirtual #34                 // Method com/amazonaws/services/sqs/model/Message.getReceiptHandle:()Ljava/lang/String;
     122: invokevirtual #35                 // Method com/amazonaws/services/sqs/model/ChangeMessageVisibilityBatchRequestEntry.withReceiptHandle:(Ljava/lang/String;)Lcom/amazonaws/services/sqs/model/ChangeMessageVisibilityBatchRequestEntry;
     125: iconst_0
     126: invokestatic  #36                 // Method java/lang/Integer.valueOf:(I)Ljava/lang/Integer;
     129: invokevirtual #37                 // Method com/amazonaws/services/sqs/model/ChangeMessageVisibilityBatchRequestEntry.withVisibilityTimeout:(Ljava/lang/Integer;)Lcom/amazonaws/services/sqs/model/ChangeMessageVisibilityBatchRequestEntry;
     132: invokeinterface #38,  2           // InterfaceMethod java/util/List.add:(Ljava/lang/Object;)Z
     137: pop
     138: iinc          3, 1
     141: goto          80
     144: aload_1
     145: aload_2
     146: invokevirtual #39                 // Method com/amazonaws/services/sqs/model/ChangeMessageVisibilityBatchRequest.setEntries:(Ljava/util/Collection;)V
     149: aload_0
     150: getfield      #1                  // Field this$0:Lcom/amazonaws/services/sqs/buffered/ReceiveQueueBuffer;
     153: invokestatic  #40                 // Method com/amazonaws/services/sqs/buffered/ReceiveQueueBuffer.access$100:(Lcom/amazonaws/services/sqs/buffered/ReceiveQueueBuffer;)Lcom/amazonaws/services/sqs/AmazonSQS;
     156: aload_1
     157: invokeinterface #41,  2           // InterfaceMethod com/amazonaws/services/sqs/AmazonSQS.changeMessageVisibilityBatch:(Lcom/amazonaws/services/sqs/model/ChangeMessageVisibilityBatchRequest;)Lcom/amazonaws/services/sqs/model/ChangeMessageVisibilityBatchResult;
     162: pop
     163: goto          196
     166: astore        4
     168: invokestatic  #43                 // Method com/amazonaws/services/sqs/buffered/ReceiveQueueBuffer.access$200:()Lorg/apache/commons/logging/Log;
     171: new           #44                 // class java/lang/StringBuilder
     174: dup
     175: invokespecial #45                 // Method java/lang/StringBuilder."<init>":()V
     178: ldc           #46                 // String ReceiveMessageBatchTask: changeMessageVisibility failed
     180: invokevirtual #47                 // Method java/lang/StringBuilder.append:(Ljava/lang/String;)Ljava/lang/StringBuilder;
     183: aload         4
     185: invokevirtual #48                 // Method java/lang/StringBuilder.append:(Ljava/lang/Object;)Ljava/lang/StringBuilder;
     188: invokevirtual #49                 // Method java/lang/StringBuilder.toString:()Ljava/lang/String;
     191: invokeinterface #50,  2           // InterfaceMethod org/apache/commons/logging/Log.warn:(Ljava/lang/Object;)V
     196: aload_0
     197: getfield      #7                  // Field messages:Ljava/util/List;
     200: invokeinterface #13,  1           // InterfaceMethod java/util/List.clear:()V
     205: return
    Exception table:
       from    to  target type
         144   163   166   Class com/amazonaws/AmazonClientException

  public void run();
    Code:
       0: aload_0
       1: invokestatic  #17                 // Method java/lang/System.nanoTime:()J
       4: aload_0
       5: getfield      #1                  // Field this$0:Lcom/amazonaws/services/sqs/buffered/ReceiveQueueBuffer;
       8: invokestatic  #51                 // Method com/amazonaws/services/sqs/buffered/ReceiveQueueBuffer.access$300:(Lcom/amazonaws/services/sqs/buffered/ReceiveQueueBuffer;)J
      11: ladd
      12: putfield      #18                 // Field visibilityDeadlineNano:J
      15: new           #52                 // class com/amazonaws/services/sqs/model/ReceiveMessageRequest
      18: dup
      19: aload_0
      20: getfield      #1                  // Field this$0:Lcom/amazonaws/services/sqs/buffered/ReceiveQueueBuffer;
      23: invokestatic  #21                 // Method com/amazonaws/services/sqs/buffered/ReceiveQueueBuffer.access$000:(Lcom/amazonaws/services/sqs/buffered/ReceiveQueueBuffer;)Ljava/lang/String;
      26: invokespecial #53                 // Method com/amazonaws/services/sqs/model/ReceiveMessageRequest."<init>":(Ljava/lang/String;)V
      29: aload_0
      30: getfield      #1                  // Field this$0:Lcom/amazonaws/services/sqs/buffered/ReceiveQueueBuffer;
      33: invokestatic  #54                 // Method com/amazonaws/services/sqs/buffered/ReceiveQueueBuffer.access$400:(Lcom/amazonaws/services/sqs/buffered/ReceiveQueueBuffer;)Lcom/amazonaws/services/sqs/buffered/QueueBufferConfig;
      36: invokevirtual #55                 // Method com/amazonaws/services/sqs/buffered/QueueBufferConfig.getMaxBatchSize:()I
      39: invokestatic  #36                 // Method java/lang/Integer.valueOf:(I)Ljava/lang/Integer;
      42: invokevirtual #56                 // Method com/amazonaws/services/sqs/model/ReceiveMessageRequest.withMaxNumberOfMessages:(Ljava/lang/Integer;)Lcom/amazonaws/services/sqs/model/ReceiveMessageRequest;
      45: astore_1
      46: aload_1
      47: getstatic     #23                 // Field com/amazonaws/services/sqs/buffered/AmazonSQSBufferedAsyncClient.USER_AGENT:Ljava/lang/String;
      50: invokestatic  #24                 // Method com/amazonaws/services/sqs/buffered/ResultConverter.appendUserAgent:(Lcom/amazonaws/AmazonWebServiceRequest;Ljava/lang/String;)Lcom/amazonaws/AmazonWebServiceRequest;
      53: pop
      54: aload_0
      55: getfield      #1                  // Field this$0:Lcom/amazonaws/services/sqs/buffered/ReceiveQueueBuffer;
      58: invokestatic  #54                 // Method com/amazonaws/services/sqs/buffered/ReceiveQueueBuffer.access$400:(Lcom/amazonaws/services/sqs/buffered/ReceiveQueueBuffer;)Lcom/amazonaws/services/sqs/buffered/QueueBufferConfig;
      61: invokevirtual #57                 // Method com/amazonaws/services/sqs/buffered/QueueBufferConfig.getVisibilityTimeoutSeconds:()I
      64: ifle          112
      67: aload_1
      68: aload_0
      69: getfield      #1                  // Field this$0:Lcom/amazonaws/services/sqs/buffered/ReceiveQueueBuffer;
      72: invokestatic  #54                 // Method com/amazonaws/services/sqs/buffered/ReceiveQueueBuffer.access$400:(Lcom/amazonaws/services/sqs/buffered/ReceiveQueueBuffer;)Lcom/amazonaws/services/sqs/buffered/QueueBufferConfig;
      75: invokevirtual #57                 // Method com/amazonaws/services/sqs/buffered/QueueBufferConfig.getVisibilityTimeoutSeconds:()I
      78: invokestatic  #36                 // Method java/lang/Integer.valueOf:(I)Ljava/lang/Integer;
      81: invokevirtual #58                 // Method com/amazonaws/services/sqs/model/ReceiveMessageRequest.setVisibilityTimeout:(Ljava/lang/Integer;)V
      84: aload_0
      85: invokestatic  #17                 // Method java/lang/System.nanoTime:()J
      88: getstatic     #59                 // Field java/util/concurrent/TimeUnit.NANOSECONDS:Ljava/util/concurrent/TimeUnit;
      91: aload_0
      92: getfield      #1                  // Field this$0:Lcom/amazonaws/services/sqs/buffered/ReceiveQueueBuffer;
      95: invokestatic  #54                 // Method com/amazonaws/services/sqs/buffered/ReceiveQueueBuffer.access$400:(Lcom/amazonaws/services/sqs/buffered/ReceiveQueueBuffer;)Lcom/amazonaws/services/sqs/buffered/QueueBufferConfig;
      98: invokevirtual #57                 // Method com/amazonaws/services/sqs/buffered/QueueBufferConfig.getVisibilityTimeoutSeconds:()I
     101: i2l
     102: getstatic     #60                 // Field java/util/concurrent/TimeUnit.SECONDS:Ljava/util/concurrent/TimeUnit;
     105: invokevirtual #61                 // Method java/util/concurrent/TimeUnit.convert:(JLjava/util/concurrent/TimeUnit;)J
     108: ladd
     109: putfield      #18                 // Field visibilityDeadlineNano:J
     112: aload_0
     113: getfield      #1                  // Field this$0:Lcom/amazonaws/services/sqs/buffered/ReceiveQueueBuffer;
     116: invokestatic  #54                 // Method com/amazonaws/services/sqs/buffered/ReceiveQueueBuffer.access$400:(Lcom/amazonaws/services/sqs/buffered/ReceiveQueueBuffer;)Lcom/amazonaws/services/sqs/buffered/QueueBufferConfig;
     119: invokevirtual #62                 // Method com/amazonaws/services/sqs/buffered/QueueBufferConfig.isLongPoll:()Z
     122: ifeq          143
     125: aload_1
     126: aload_0
     127: getfield      #1                  // Field this$0:Lcom/amazonaws/services/sqs/buffered/ReceiveQueueBuffer;
     130: invokestatic  #54                 // Method com/amazonaws/services/sqs/buffered/ReceiveQueueBuffer.access$400:(Lcom/amazonaws/services/sqs/buffered/ReceiveQueueBuffer;)Lcom/amazonaws/services/sqs/buffered/QueueBufferConfig;
     133: invokevirtual #63                 // Method com/amazonaws/services/sqs/buffered/QueueBufferConfig.getLongPollWaitTimeoutSeconds:()I
     136: invokestatic  #36                 // Method java/lang/Integer.valueOf:(I)Ljava/lang/Integer;
     139: invokevirtual #64                 // Method com/amazonaws/services/sqs/model/ReceiveMessageRequest.withWaitTimeSeconds:(Ljava/lang/Integer;)Lcom/amazonaws/services/sqs/model/ReceiveMessageRequest;
     142: pop
     143: aload_0
     144: aload_0
     145: getfield      #1                  // Field this$0:Lcom/amazonaws/services/sqs/buffered/ReceiveQueueBuffer;
     148: invokestatic  #40                 // Method com/amazonaws/services/sqs/buffered/ReceiveQueueBuffer.access$100:(Lcom/amazonaws/services/sqs/buffered/ReceiveQueueBuffer;)Lcom/amazonaws/services/sqs/AmazonSQS;
     151: aload_1
     152: invokeinterface #65,  2           // InterfaceMethod com/amazonaws/services/sqs/AmazonSQS.receiveMessage:(Lcom/amazonaws/services/sqs/model/ReceiveMessageRequest;)Lcom/amazonaws/services/sqs/model/ReceiveMessageResult;
     157: invokevirtual #66                 // Method com/amazonaws/services/sqs/model/ReceiveMessageResult.getMessages:()Ljava/util/List;
     160: putfield      #7                  // Field messages:Ljava/util/List;
     163: aload_0
     164: iconst_1
     165: putfield      #4                  // Field open:Z
     168: aload_0
     169: getfield      #5                  // Field parentBuffer:Lcom/amazonaws/services/sqs/buffered/ReceiveQueueBuffer;
     172: aload_0
     173: invokevirtual #67                 // Method com/amazonaws/services/sqs/buffered/ReceiveQueueBuffer.reportBatchFinished:(Lcom/amazonaws/services/sqs/buffered/ReceiveQueueBuffer$ReceiveMessageBatchTask;)V
     176: goto          217
     179: astore_1
     180: aload_0
     181: aload_1
     182: putfield      #3                  // Field exception:Ljava/lang/Exception;
     185: aload_0
     186: iconst_1
     187: putfield      #4                  // Field open:Z
     190: aload_0
     191: getfield      #5                  // Field parentBuffer:Lcom/amazonaws/services/sqs/buffered/ReceiveQueueBuffer;
     194: aload_0
     195: invokevirtual #67                 // Method com/amazonaws/services/sqs/buffered/ReceiveQueueBuffer.reportBatchFinished:(Lcom/amazonaws/services/sqs/buffered/ReceiveQueueBuffer$ReceiveMessageBatchTask;)V
     198: goto          217
     201: astore_2
     202: aload_0
     203: iconst_1
     204: putfield      #4                  // Field open:Z
     207: aload_0
     208: getfield      #5                  // Field parentBuffer:Lcom/amazonaws/services/sqs/buffered/ReceiveQueueBuffer;
     211: aload_0
     212: invokevirtual #67                 // Method com/amazonaws/services/sqs/buffered/ReceiveQueueBuffer.reportBatchFinished:(Lcom/amazonaws/services/sqs/buffered/ReceiveQueueBuffer$ReceiveMessageBatchTask;)V
     215: aload_2
     216: athrow
     217: return
    Exception table:
       from    to  target type
           0   163   179   Class com/amazonaws/AmazonClientException
           0   163   201   any
         179   185   201   any
}
