Compiled from "WSDLHelper.java"
public class org.apache.cxf.wsdl.WSDLHelper {
  public org.apache.cxf.wsdl.WSDLHelper();
    Code:
       0: aload_0
       1: invokespecial #1                  // Method java/lang/Object."<init>":()V
       4: return

  public javax.wsdl.BindingOperation getBindingOperation(javax.wsdl.Definition, java.lang.String);
    Code:
       0: aload_2
       1: ifnonnull     6
       4: aconst_null
       5: areturn
       6: aload_1
       7: invokeinterface #2,  1            // InterfaceMethod javax/wsdl/Definition.getBindings:()Ljava/util/Map;
      12: invokeinterface #3,  1            // InterfaceMethod java/util/Map.values:()Ljava/util/Collection;
      17: invokeinterface #4,  1            // InterfaceMethod java/util/Collection.iterator:()Ljava/util/Iterator;
      22: invokestatic  #5                  // Method org/apache/cxf/helpers/CastUtils.cast:(Ljava/util/Iterator;)Ljava/util/Iterator;
      25: astore_3
      26: aload_3
      27: invokeinterface #6,  1            // InterfaceMethod java/util/Iterator.hasNext:()Z
      32: ifeq          108
      35: aload_3
      36: invokeinterface #7,  1            // InterfaceMethod java/util/Iterator.next:()Ljava/lang/Object;
      41: checkcast     #8                  // class javax/wsdl/Binding
      44: astore        4
      46: aload         4
      48: invokeinterface #9,  1            // InterfaceMethod javax/wsdl/Binding.getBindingOperations:()Ljava/util/List;
      53: invokeinterface #10,  1           // InterfaceMethod java/util/List.iterator:()Ljava/util/Iterator;
      58: invokestatic  #5                  // Method org/apache/cxf/helpers/CastUtils.cast:(Ljava/util/Iterator;)Ljava/util/Iterator;
      61: astore        5
      63: aload         5
      65: invokeinterface #6,  1            // InterfaceMethod java/util/Iterator.hasNext:()Z
      70: ifeq          105
      73: aload         5
      75: invokeinterface #7,  1            // InterfaceMethod java/util/Iterator.next:()Ljava/lang/Object;
      80: checkcast     #11                 // class javax/wsdl/BindingOperation
      83: astore        6
      85: aload         6
      87: invokeinterface #12,  1           // InterfaceMethod javax/wsdl/BindingOperation.getName:()Ljava/lang/String;
      92: aload_2
      93: invokevirtual #13                 // Method java/lang/String.equals:(Ljava/lang/Object;)Z
      96: ifeq          102
      99: aload         6
     101: areturn
     102: goto          63
     105: goto          26
     108: aconst_null
     109: areturn

  public static java.lang.String writeQName(javax.wsdl.Definition, javax.xml.namespace.QName);
    Code:
       0: new           #14                 // class java/lang/StringBuilder
       3: dup
       4: invokespecial #15                 // Method java/lang/StringBuilder."<init>":()V
       7: aload_0
       8: aload_1
       9: invokevirtual #16                 // Method javax/xml/namespace/QName.getNamespaceURI:()Ljava/lang/String;
      12: invokeinterface #17,  2           // InterfaceMethod javax/wsdl/Definition.getPrefix:(Ljava/lang/String;)Ljava/lang/String;
      17: invokevirtual #18                 // Method java/lang/StringBuilder.append:(Ljava/lang/String;)Ljava/lang/StringBuilder;
      20: ldc           #19                 // String :
      22: invokevirtual #18                 // Method java/lang/StringBuilder.append:(Ljava/lang/String;)Ljava/lang/StringBuilder;
      25: aload_1
      26: invokevirtual #20                 // Method javax/xml/namespace/QName.getLocalPart:()Ljava/lang/String;
      29: invokevirtual #18                 // Method java/lang/StringBuilder.append:(Ljava/lang/String;)Ljava/lang/StringBuilder;
      32: invokevirtual #21                 // Method java/lang/StringBuilder.toString:()Ljava/lang/String;
      35: areturn

  public javax.wsdl.BindingOperation getBindingOperation(javax.wsdl.Binding, java.lang.String);
    Code:
       0: aload_2
       1: ifnonnull     6
       4: aconst_null
       5: areturn
       6: aload_1
       7: invokeinterface #9,  1            // InterfaceMethod javax/wsdl/Binding.getBindingOperations:()Ljava/util/List;
      12: invokestatic  #22                 // Method org/apache/cxf/helpers/CastUtils.cast:(Ljava/util/List;)Ljava/util/List;
      15: astore_3
      16: aload_3
      17: invokeinterface #23,  1           // InterfaceMethod java/util/List.iterator:()Ljava/util/Iterator;
      22: astore        4
      24: aload         4
      26: invokeinterface #6,  1            // InterfaceMethod java/util/Iterator.hasNext:()Z
      31: ifeq          66
      34: aload         4
      36: invokeinterface #7,  1            // InterfaceMethod java/util/Iterator.next:()Ljava/lang/Object;
      41: checkcast     #11                 // class javax/wsdl/BindingOperation
      44: astore        5
      46: aload_2
      47: aload         5
      49: invokeinterface #12,  1           // InterfaceMethod javax/wsdl/BindingOperation.getName:()Ljava/lang/String;
      54: invokevirtual #13                 // Method java/lang/String.equals:(Ljava/lang/Object;)Z
      57: ifeq          63
      60: aload         5
      62: areturn
      63: goto          24
      66: aconst_null
      67: areturn

  public java.util.List<javax.wsdl.PortType> getPortTypes(javax.wsdl.Definition);
    Code:
       0: new           #24                 // class java/util/ArrayList
       3: dup
       4: invokespecial #25                 // Method java/util/ArrayList."<init>":()V
       7: astore_2
       8: aload_1
       9: invokeinterface #26,  1           // InterfaceMethod javax/wsdl/Definition.getPortTypes:()Ljava/util/Map;
      14: invokeinterface #3,  1            // InterfaceMethod java/util/Map.values:()Ljava/util/Collection;
      19: invokestatic  #27                 // Method org/apache/cxf/helpers/CastUtils.cast:(Ljava/util/Collection;)Ljava/util/Collection;
      22: astore_3
      23: aload_3
      24: invokeinterface #28,  1           // InterfaceMethod java/util/Collection.iterator:()Ljava/util/Iterator;
      29: astore        4
      31: aload         4
      33: invokeinterface #6,  1            // InterfaceMethod java/util/Iterator.hasNext:()Z
      38: ifeq          65
      41: aload         4
      43: invokeinterface #7,  1            // InterfaceMethod java/util/Iterator.next:()Ljava/lang/Object;
      48: checkcast     #29                 // class javax/wsdl/PortType
      51: astore        5
      53: aload_2
      54: aload         5
      56: invokeinterface #30,  2           // InterfaceMethod java/util/List.add:(Ljava/lang/Object;)Z
      61: pop
      62: goto          31
      65: aload_2
      66: areturn

  public java.util.List<javax.wsdl.Part> getInMessageParts(javax.wsdl.Operation);
    Code:
       0: aload_1
       1: invokeinterface #31,  1           // InterfaceMethod javax/wsdl/Operation.getInput:()Ljavax/wsdl/Input;
       6: astore_2
       7: new           #24                 // class java/util/ArrayList
      10: dup
      11: invokespecial #25                 // Method java/util/ArrayList."<init>":()V
      14: astore_3
      15: aload_2
      16: ifnull        92
      19: aload_2
      20: invokeinterface #32,  1           // InterfaceMethod javax/wsdl/Input.getMessage:()Ljavax/wsdl/Message;
      25: ifnull        92
      28: aload_2
      29: invokeinterface #32,  1           // InterfaceMethod javax/wsdl/Input.getMessage:()Ljavax/wsdl/Message;
      34: invokeinterface #33,  1           // InterfaceMethod javax/wsdl/Message.getParts:()Ljava/util/Map;
      39: invokeinterface #3,  1            // InterfaceMethod java/util/Map.values:()Ljava/util/Collection;
      44: invokestatic  #27                 // Method org/apache/cxf/helpers/CastUtils.cast:(Ljava/util/Collection;)Ljava/util/Collection;
      47: astore        4
      49: aload         4
      51: invokeinterface #28,  1           // InterfaceMethod java/util/Collection.iterator:()Ljava/util/Iterator;
      56: astore        5
      58: aload         5
      60: invokeinterface #6,  1            // InterfaceMethod java/util/Iterator.hasNext:()Z
      65: ifeq          92
      68: aload         5
      70: invokeinterface #7,  1            // InterfaceMethod java/util/Iterator.next:()Ljava/lang/Object;
      75: checkcast     #34                 // class javax/wsdl/Part
      78: astore        6
      80: aload_3
      81: aload         6
      83: invokeinterface #30,  2           // InterfaceMethod java/util/List.add:(Ljava/lang/Object;)Z
      88: pop
      89: goto          58
      92: aload_3
      93: areturn

  public java.util.List<javax.wsdl.Part> getOutMessageParts(javax.wsdl.Operation);
    Code:
       0: aload_1
       1: invokeinterface #35,  1           // InterfaceMethod javax/wsdl/Operation.getOutput:()Ljavax/wsdl/Output;
       6: astore_2
       7: new           #24                 // class java/util/ArrayList
      10: dup
      11: invokespecial #25                 // Method java/util/ArrayList."<init>":()V
      14: astore_3
      15: aload_2
      16: ifnull        92
      19: aload_2
      20: invokeinterface #36,  1           // InterfaceMethod javax/wsdl/Output.getMessage:()Ljavax/wsdl/Message;
      25: ifnull        92
      28: aload_2
      29: invokeinterface #36,  1           // InterfaceMethod javax/wsdl/Output.getMessage:()Ljavax/wsdl/Message;
      34: invokeinterface #33,  1           // InterfaceMethod javax/wsdl/Message.getParts:()Ljava/util/Map;
      39: invokeinterface #3,  1            // InterfaceMethod java/util/Map.values:()Ljava/util/Collection;
      44: invokestatic  #27                 // Method org/apache/cxf/helpers/CastUtils.cast:(Ljava/util/Collection;)Ljava/util/Collection;
      47: astore        4
      49: aload         4
      51: invokeinterface #28,  1           // InterfaceMethod java/util/Collection.iterator:()Ljava/util/Iterator;
      56: astore        5
      58: aload         5
      60: invokeinterface #6,  1            // InterfaceMethod java/util/Iterator.hasNext:()Z
      65: ifeq          92
      68: aload         5
      70: invokeinterface #7,  1            // InterfaceMethod java/util/Iterator.next:()Ljava/lang/Object;
      75: checkcast     #34                 // class javax/wsdl/Part
      78: astore        6
      80: aload_3
      81: aload         6
      83: invokeinterface #30,  2           // InterfaceMethod java/util/List.add:(Ljava/lang/Object;)Z
      88: pop
      89: goto          58
      92: aload_3
      93: areturn

  public javax.wsdl.Binding getBinding(javax.wsdl.BindingOperation, javax.wsdl.Definition);
    Code:
       0: aload_2
       1: invokeinterface #2,  1            // InterfaceMethod javax/wsdl/Definition.getBindings:()Ljava/util/Map;
       6: invokeinterface #3,  1            // InterfaceMethod java/util/Map.values:()Ljava/util/Collection;
      11: invokestatic  #27                 // Method org/apache/cxf/helpers/CastUtils.cast:(Ljava/util/Collection;)Ljava/util/Collection;
      14: astore_3
      15: aload_3
      16: invokeinterface #28,  1           // InterfaceMethod java/util/Collection.iterator:()Ljava/util/Iterator;
      21: astore        4
      23: aload         4
      25: invokeinterface #6,  1            // InterfaceMethod java/util/Iterator.hasNext:()Z
      30: ifeq          116
      33: aload         4
      35: invokeinterface #7,  1            // InterfaceMethod java/util/Iterator.next:()Ljava/lang/Object;
      40: checkcast     #8                  // class javax/wsdl/Binding
      43: astore        5
      45: aload         5
      47: invokeinterface #9,  1            // InterfaceMethod javax/wsdl/Binding.getBindingOperations:()Ljava/util/List;
      52: invokestatic  #22                 // Method org/apache/cxf/helpers/CastUtils.cast:(Ljava/util/List;)Ljava/util/List;
      55: astore        6
      57: aload         6
      59: invokeinterface #23,  1           // InterfaceMethod java/util/List.iterator:()Ljava/util/Iterator;
      64: astore        7
      66: aload         7
      68: invokeinterface #6,  1            // InterfaceMethod java/util/Iterator.hasNext:()Z
      73: ifeq          113
      76: aload         7
      78: invokeinterface #7,  1            // InterfaceMethod java/util/Iterator.next:()Ljava/lang/Object;
      83: checkcast     #11                 // class javax/wsdl/BindingOperation
      86: astore        8
      88: aload         8
      90: invokeinterface #12,  1           // InterfaceMethod javax/wsdl/BindingOperation.getName:()Ljava/lang/String;
      95: aload_1
      96: invokeinterface #12,  1           // InterfaceMethod javax/wsdl/BindingOperation.getName:()Ljava/lang/String;
     101: invokevirtual #13                 // Method java/lang/String.equals:(Ljava/lang/Object;)Z
     104: ifeq          110
     107: aload         5
     109: areturn
     110: goto          66
     113: goto          23
     116: aconst_null
     117: areturn

  public javax.wsdl.Definition getDefinition(java.io.File) throws java.lang.Exception;
    Code:
       0: invokestatic  #37                 // Method javax/wsdl/factory/WSDLFactory.newInstance:()Ljavax/wsdl/factory/WSDLFactory;
       3: astore_2
       4: aload_2
       5: invokevirtual #38                 // Method javax/wsdl/factory/WSDLFactory.newWSDLReader:()Ljavax/wsdl/xml/WSDLReader;
       8: astore_3
       9: aload_3
      10: ldc           #39                 // String javax.wsdl.verbose
      12: iconst_0
      13: invokeinterface #40,  3           // InterfaceMethod javax/wsdl/xml/WSDLReader.setFeature:(Ljava/lang/String;Z)V
      18: aload_3
      19: aload_1
      20: invokevirtual #41                 // Method java/io/File.toURI:()Ljava/net/URI;
      23: invokevirtual #42                 // Method java/net/URI.toURL:()Ljava/net/URL;
      26: invokevirtual #43                 // Method java/net/URL.toString:()Ljava/lang/String;
      29: invokeinterface #44,  2           // InterfaceMethod javax/wsdl/xml/WSDLReader.readWSDL:(Ljava/lang/String;)Ljavax/wsdl/Definition;
      34: areturn
}
