Compiled from "WSDLConstants.java"
public final class org.apache.cxf.wsdl.WSDLConstants$WSDLVersion extends java.lang.Enum<org.apache.cxf.wsdl.WSDLConstants$WSDLVersion> {
  public static final org.apache.cxf.wsdl.WSDLConstants$WSDLVersion WSDL11;

  public static final org.apache.cxf.wsdl.WSDLConstants$WSDLVersion WSDL20;

  public static final org.apache.cxf.wsdl.WSDLConstants$WSDLVersion UNKNOWN;

  private static final org.apache.cxf.wsdl.WSDLConstants$WSDLVersion[] $VALUES;

  public static org.apache.cxf.wsdl.WSDLConstants$WSDLVersion[] values();
    Code:
       0: getstatic     #1                  // Field $VALUES:[Lorg/apache/cxf/wsdl/WSDLConstants$WSDLVersion;
       3: invokevirtual #2                  // Method "[Lorg/apache/cxf/wsdl/WSDLConstants$WSDLVersion;".clone:()Ljava/lang/Object;
       6: checkcast     #3                  // class "[Lorg/apache/cxf/wsdl/WSDLConstants$WSDLVersion;"
       9: areturn

  public static org.apache.cxf.wsdl.WSDLConstants$WSDLVersion valueOf(java.lang.String);
    Code:
       0: ldc_w         #4                  // class org/apache/cxf/wsdl/WSDLConstants$WSDLVersion
       3: aload_0
       4: invokestatic  #5                  // Method java/lang/Enum.valueOf:(Ljava/lang/Class;Ljava/lang/String;)Ljava/lang/Enum;
       7: checkcast     #4                  // class org/apache/cxf/wsdl/WSDLConstants$WSDLVersion
      10: areturn

  private org.apache.cxf.wsdl.WSDLConstants$WSDLVersion();
    Code:
       0: aload_0
       1: aload_1
       2: iload_2
       3: invokespecial #6                  // Method java/lang/Enum."<init>":(Ljava/lang/String;I)V
       6: return

  static {};
    Code:
       0: new           #4                  // class org/apache/cxf/wsdl/WSDLConstants$WSDLVersion
       3: dup
       4: ldc           #7                  // String WSDL11
       6: iconst_0
       7: invokespecial #8                  // Method "<init>":(Ljava/lang/String;I)V
      10: putstatic     #9                  // Field WSDL11:Lorg/apache/cxf/wsdl/WSDLConstants$WSDLVersion;
      13: new           #4                  // class org/apache/cxf/wsdl/WSDLConstants$WSDLVersion
      16: dup
      17: ldc           #10                 // String WSDL20
      19: iconst_1
      20: invokespecial #8                  // Method "<init>":(Ljava/lang/String;I)V
      23: putstatic     #11                 // Field WSDL20:Lorg/apache/cxf/wsdl/WSDLConstants$WSDLVersion;
      26: new           #4                  // class org/apache/cxf/wsdl/WSDLConstants$WSDLVersion
      29: dup
      30: ldc           #12                 // String UNKNOWN
      32: iconst_2
      33: invokespecial #8                  // Method "<init>":(Ljava/lang/String;I)V
      36: putstatic     #13                 // Field UNKNOWN:Lorg/apache/cxf/wsdl/WSDLConstants$WSDLVersion;
      39: iconst_3
      40: anewarray     #4                  // class org/apache/cxf/wsdl/WSDLConstants$WSDLVersion
      43: dup
      44: iconst_0
      45: getstatic     #9                  // Field WSDL11:Lorg/apache/cxf/wsdl/WSDLConstants$WSDLVersion;
      48: aastore
      49: dup
      50: iconst_1
      51: getstatic     #11                 // Field WSDL20:Lorg/apache/cxf/wsdl/WSDLConstants$WSDLVersion;
      54: aastore
      55: dup
      56: iconst_2
      57: getstatic     #13                 // Field UNKNOWN:Lorg/apache/cxf/wsdl/WSDLConstants$WSDLVersion;
      60: aastore
      61: putstatic     #1                  // Field $VALUES:[Lorg/apache/cxf/wsdl/WSDLConstants$WSDLVersion;
      64: return
}
