Compiled from "TomcatJarInputStream.java"
public class org.apache.catalina.webresources.TomcatJarInputStream extends java.util.jar.JarInputStream {
  private java.util.jar.JarEntry metaInfEntry;

  private java.util.jar.JarEntry manifestEntry;

  org.apache.catalina.webresources.TomcatJarInputStream(java.io.InputStream) throws java.io.IOException;
    Code:
       0: aload_0
       1: aload_1
       2: invokespecial #1                  // Method java/util/jar/JarInputStream."<init>":(Ljava/io/InputStream;)V
       5: return

  protected java.util.zip.ZipEntry createZipEntry(java.lang.String);
    Code:
       0: aload_0
       1: aload_1
       2: invokespecial #2                  // Method java/util/jar/JarInputStream.createZipEntry:(Ljava/lang/String;)Ljava/util/zip/ZipEntry;
       5: astore_2
       6: aload_0
       7: getfield      #3                  // Field metaInfEntry:Ljava/util/jar/JarEntry;
      10: ifnonnull     33
      13: ldc           #4                  // String META-INF/
      15: aload_1
      16: invokevirtual #5                  // Method java/lang/String.equals:(Ljava/lang/Object;)Z
      19: ifeq          33
      22: aload_0
      23: aload_2
      24: checkcast     #6                  // class java/util/jar/JarEntry
      27: putfield      #3                  // Field metaInfEntry:Ljava/util/jar/JarEntry;
      30: goto          57
      33: aload_0
      34: getfield      #7                  // Field manifestEntry:Ljava/util/jar/JarEntry;
      37: ifnonnull     57
      40: ldc           #8                  // String META-INF/MANIFESR.MF
      42: aload_1
      43: invokevirtual #5                  // Method java/lang/String.equals:(Ljava/lang/Object;)Z
      46: ifeq          57
      49: aload_0
      50: aload_2
      51: checkcast     #6                  // class java/util/jar/JarEntry
      54: putfield      #7                  // Field manifestEntry:Ljava/util/jar/JarEntry;
      57: aload_2
      58: areturn

  java.util.jar.JarEntry getMetaInfEntry();
    Code:
       0: aload_0
       1: getfield      #3                  // Field metaInfEntry:Ljava/util/jar/JarEntry;
       4: areturn

  java.util.jar.JarEntry getManifestEntry();
    Code:
       0: aload_0
       1: getfield      #7                  // Field manifestEntry:Ljava/util/jar/JarEntry;
       4: areturn
}
