Compiled from "BasicSessionID.java"
public final class org.jboss.ejb.client.BasicSessionID extends org.jboss.ejb.client.SessionID {
  private static final long serialVersionUID;

  org.jboss.ejb.client.BasicSessionID(byte[]);
    Code:
       0: aload_0
       1: aload_1
       2: invokespecial #1                  // Method org/jboss/ejb/client/SessionID."<init>":([B)V
       5: aload_1
       6: iconst_0
       7: baload
       8: bipush        7
      10: if_icmpeq     17
      13: invokestatic  #2                  // Method wrongFormat:()Ljava/lang/IllegalArgumentException;
      16: athrow
      17: return

  private static java.lang.IllegalArgumentException wrongFormat();
    Code:
       0: new           #3                  // class java/lang/IllegalArgumentException
       3: dup
       4: ldc           #4                  // String Wrong session ID format
       6: invokespecial #5                  // Method java/lang/IllegalArgumentException."<init>":(Ljava/lang/String;)V
       9: areturn
}
