Compiled from "EJBInvocationHandler.java"
final class org.jboss.ejb.client.EJBInvocationHandler$CompressionHintAnnotationScanner implements org.jboss.ejb.client.EJBInvocationHandler$AnnotationScanner {
  final org.jboss.ejb.client.EJBInvocationHandler this$0;

  private org.jboss.ejb.client.EJBInvocationHandler$CompressionHintAnnotationScanner(org.jboss.ejb.client.EJBInvocationHandler);
    Code:
       0: aload_0
       1: aload_1
       2: putfield      #2                  // Field this$0:Lorg/jboss/ejb/client/EJBInvocationHandler;
       5: aload_0
       6: invokespecial #3                  // Method java/lang/Object."<init>":()V
       9: return

  public void scanClass(java.lang.Class<?>);
    Code:
       0: aload_1
       1: ldc_w         #4                  // class org/jboss/ejb/client/annotation/CompressionHint
       4: invokevirtual #5                  // Method java/lang/Class.getAnnotation:(Ljava/lang/Class;)Ljava/lang/annotation/Annotation;
       7: checkcast     #4                  // class org/jboss/ejb/client/annotation/CompressionHint
      10: astore_2
      11: aload_2
      12: ifnonnull     16
      15: return
      16: aload_0
      17: getfield      #2                  // Field this$0:Lorg/jboss/ejb/client/EJBInvocationHandler;
      20: getstatic     #6                  // Field org/jboss/ejb/client/AttachmentKeys.VIEW_CLASS_DATA_COMPRESSION_HINT_ATTACHMENT_KEY:Lorg/jboss/ejb/client/AttachmentKey;
      23: aload_2
      24: invokevirtual #7                  // Method org/jboss/ejb/client/EJBInvocationHandler.putAttachment:(Lorg/jboss/ejb/client/AttachmentKey;Ljava/lang/Object;)Ljava/lang/Object;
      27: pop
      28: return

  public void scanMethod(java.lang.reflect.Method);
    Code:
       0: aload_1
       1: ldc_w         #4                  // class org/jboss/ejb/client/annotation/CompressionHint
       4: invokevirtual #8                  // Method java/lang/reflect/Method.getAnnotation:(Ljava/lang/Class;)Ljava/lang/annotation/Annotation;
       7: checkcast     #4                  // class org/jboss/ejb/client/annotation/CompressionHint
      10: astore_2
      11: aload_2
      12: ifnonnull     16
      15: return
      16: aload_0
      17: getfield      #2                  // Field this$0:Lorg/jboss/ejb/client/EJBInvocationHandler;
      20: getstatic     #9                  // Field org/jboss/ejb/client/AttachmentKeys.VIEW_METHOD_DATA_COMPRESSION_HINT_ATTACHMENT_KEY:Lorg/jboss/ejb/client/AttachmentKey;
      23: invokevirtual #10                 // Method org/jboss/ejb/client/EJBInvocationHandler.getAttachment:(Lorg/jboss/ejb/client/AttachmentKey;)Ljava/lang/Object;
      26: checkcast     #11                 // class java/util/Map
      29: astore_3
      30: aload_3
      31: ifnonnull     54
      34: new           #12                 // class java/util/HashMap
      37: dup
      38: invokespecial #13                 // Method java/util/HashMap."<init>":()V
      41: astore_3
      42: aload_0
      43: getfield      #2                  // Field this$0:Lorg/jboss/ejb/client/EJBInvocationHandler;
      46: getstatic     #9                  // Field org/jboss/ejb/client/AttachmentKeys.VIEW_METHOD_DATA_COMPRESSION_HINT_ATTACHMENT_KEY:Lorg/jboss/ejb/client/AttachmentKey;
      49: aload_3
      50: invokevirtual #7                  // Method org/jboss/ejb/client/EJBInvocationHandler.putAttachment:(Lorg/jboss/ejb/client/AttachmentKey;Ljava/lang/Object;)Ljava/lang/Object;
      53: pop
      54: aload_3
      55: aload_1
      56: aload_2
      57: invokeinterface #14,  3           // InterfaceMethod java/util/Map.put:(Ljava/lang/Object;Ljava/lang/Object;)Ljava/lang/Object;
      62: pop
      63: return

  org.jboss.ejb.client.EJBInvocationHandler$CompressionHintAnnotationScanner(org.jboss.ejb.client.EJBInvocationHandler, org.jboss.ejb.client.EJBInvocationHandler$1);
    Code:
       0: aload_0
       1: aload_1
       2: invokespecial #1                  // Method "<init>":(Lorg/jboss/ejb/client/EJBInvocationHandler;)V
       5: return
}
