Compiled from "ValueExpressionResolver.java"
public class org.jboss.dmr.ValueExpressionResolver {
  public static final org.jboss.dmr.ValueExpressionResolver DEFAULT_RESOLVER;

  private static final int INITIAL;

  private static final int GOT_DOLLAR;

  private static final int GOT_OPEN_BRACE;

  private static final int RESOLVED;

  private static final int DEFAULT;

  public org.jboss.dmr.ValueExpressionResolver();
    Code:
       0: aload_0
       1: invokespecial #1                  // Method java/lang/Object."<init>":()V
       4: return

  public java.lang.String resolve(org.jboss.dmr.ValueExpression);
    Code:
       0: aload_1
       1: invokevirtual #2                  // Method org/jboss/dmr/ValueExpression.getExpressionString:()Ljava/lang/String;
       4: astore_2
       5: new           #3                  // class java/lang/StringBuilder
       8: dup
       9: invokespecial #4                  // Method java/lang/StringBuilder."<init>":()V
      12: astore_3
      13: aload_2
      14: invokevirtual #5                  // Method java/lang/String.length:()I
      17: istore        4
      19: iconst_0
      20: istore        5
      22: iconst_m1
      23: istore        6
      25: iconst_0
      26: istore        7
      28: iconst_m1
      29: istore        8
      31: iconst_0
      32: istore        9
      34: iload         9
      36: iload         4
      38: if_icmpge     532
      41: aload_2
      42: iload         9
      44: invokevirtual #6                  // Method java/lang/String.codePointAt:(I)I
      47: istore        10
      49: iload         5
      51: tableswitch   { // 0 to 4
                     0: 84
                     1: 120
                     2: 195
                     3: 405
                     4: 442
               default: 492
          }
      84: iload         10
      86: lookupswitch  { // 1
                    36: 104
               default: 110
          }
     104: iconst_1
     105: istore        5
     107: goto          520
     110: aload_3
     111: iload         10
     113: invokevirtual #7                  // Method java/lang/StringBuilder.appendCodePoint:(I)Ljava/lang/StringBuilder;
     116: pop
     117: goto          520
     120: iload         10
     122: lookupswitch  { // 2
                    36: 148
                   123: 161
               default: 177
          }
     148: aload_3
     149: iload         10
     151: invokevirtual #7                  // Method java/lang/StringBuilder.appendCodePoint:(I)Ljava/lang/StringBuilder;
     154: pop
     155: iconst_0
     156: istore        5
     158: goto          520
     161: iload         9
     163: iconst_1
     164: iadd
     165: istore        6
     167: iload         6
     169: istore        8
     171: iconst_2
     172: istore        5
     174: goto          520
     177: aload_3
     178: bipush        36
     180: invokevirtual #8                  // Method java/lang/StringBuilder.append:(C)Ljava/lang/StringBuilder;
     183: iload         10
     185: invokevirtual #7                  // Method java/lang/StringBuilder.appendCodePoint:(I)Ljava/lang/StringBuilder;
     188: pop
     189: iconst_0
     190: istore        5
     192: goto          520
     195: iload         10
     197: lookupswitch  { // 4
                    44: 256
                    58: 246
                   123: 240
                   125: 256
               default: 402
          }
     240: iinc          7, 1
     243: goto          520
     246: iload         8
     248: iload         9
     250: if_icmpne     256
     253: goto          520
     256: iload         7
     258: ifle          274
     261: iload         10
     263: bipush        125
     265: if_icmpne     520
     268: iinc          7, -1
     271: goto          520
     274: aload_0
     275: aload_2
     276: iload         8
     278: iload         9
     280: invokevirtual #9                  // Method java/lang/String.substring:(II)Ljava/lang/String;
     283: invokevirtual #10                 // Method java/lang/String.trim:()Ljava/lang/String;
     286: invokevirtual #11                 // Method resolvePart:(Ljava/lang/String;)Ljava/lang/String;
     289: astore        11
     291: aload         11
     293: ifnull        329
     296: aload         11
     298: aload_2
     299: invokevirtual #12                 // Method java/lang/String.equals:(Ljava/lang/Object;)Z
     302: ifne          329
     305: aload_3
     306: aload         11
     308: invokevirtual #13                 // Method java/lang/StringBuilder.append:(Ljava/lang/String;)Ljava/lang/StringBuilder;
     311: pop
     312: iload         10
     314: bipush        125
     316: if_icmpne     323
     319: iconst_0
     320: goto          324
     323: iconst_3
     324: istore        5
     326: goto          520
     329: iload         10
     331: bipush        44
     333: if_icmpne     345
     336: iload         9
     338: iconst_1
     339: iadd
     340: istore        8
     342: goto          520
     345: iload         10
     347: bipush        58
     349: if_icmpne     364
     352: iload         9
     354: iconst_1
     355: iadd
     356: istore        6
     358: iconst_4
     359: istore        5
     361: goto          520
     364: new           #14                 // class java/lang/IllegalStateException
     367: dup
     368: new           #3                  // class java/lang/StringBuilder
     371: dup
     372: invokespecial #4                  // Method java/lang/StringBuilder."<init>":()V
     375: ldc           #15                 // String Failed to resolve expression:
     377: invokevirtual #13                 // Method java/lang/StringBuilder.append:(Ljava/lang/String;)Ljava/lang/StringBuilder;
     380: aload_2
     381: iload         6
     383: iconst_2
     384: isub
     385: iload         9
     387: iconst_1
     388: iadd
     389: invokevirtual #9                  // Method java/lang/String.substring:(II)Ljava/lang/String;
     392: invokevirtual #13                 // Method java/lang/StringBuilder.append:(Ljava/lang/String;)Ljava/lang/StringBuilder;
     395: invokevirtual #16                 // Method java/lang/StringBuilder.toString:()Ljava/lang/String;
     398: invokespecial #17                 // Method java/lang/IllegalStateException."<init>":(Ljava/lang/String;)V
     401: athrow
     402: goto          520
     405: iload         10
     407: bipush        123
     409: if_icmpne     418
     412: iinc          7, 1
     415: goto          520
     418: iload         10
     420: bipush        125
     422: if_icmpne     520
     425: iload         7
     427: ifle          436
     430: iinc          7, -1
     433: goto          520
     436: iconst_0
     437: istore        5
     439: goto          520
     442: iload         10
     444: bipush        123
     446: if_icmpne     455
     449: iinc          7, 1
     452: goto          520
     455: iload         10
     457: bipush        125
     459: if_icmpne     520
     462: iload         7
     464: ifle          473
     467: iinc          7, -1
     470: goto          520
     473: iconst_0
     474: istore        5
     476: aload_3
     477: aload_2
     478: iload         6
     480: iload         9
     482: invokevirtual #9                  // Method java/lang/String.substring:(II)Ljava/lang/String;
     485: invokevirtual #13                 // Method java/lang/StringBuilder.append:(Ljava/lang/String;)Ljava/lang/StringBuilder;
     488: pop
     489: goto          520
     492: new           #14                 // class java/lang/IllegalStateException
     495: dup
     496: new           #3                  // class java/lang/StringBuilder
     499: dup
     500: invokespecial #4                  // Method java/lang/StringBuilder."<init>":()V
     503: ldc           #18                 // String Unexpected char seen:
     505: invokevirtual #13                 // Method java/lang/StringBuilder.append:(Ljava/lang/String;)Ljava/lang/StringBuilder;
     508: iload         10
     510: invokevirtual #19                 // Method java/lang/StringBuilder.append:(I)Ljava/lang/StringBuilder;
     513: invokevirtual #16                 // Method java/lang/StringBuilder.toString:()Ljava/lang/String;
     516: invokespecial #17                 // Method java/lang/IllegalStateException."<init>":(Ljava/lang/String;)V
     519: athrow
     520: aload_2
     521: iload         9
     523: iconst_1
     524: invokevirtual #20                 // Method java/lang/String.offsetByCodePoints:(II)I
     527: istore        9
     529: goto          34
     532: iload         5
     534: tableswitch   { // 1 to 4
                     1: 564
                     2: 590
                     3: 620
                     4: 574
               default: 620
          }
     564: aload_3
     565: bipush        36
     567: invokevirtual #8                  // Method java/lang/StringBuilder.append:(C)Ljava/lang/StringBuilder;
     570: pop
     571: goto          620
     574: aload_3
     575: aload_2
     576: iload         6
     578: iconst_2
     579: isub
     580: invokevirtual #21                 // Method java/lang/String.substring:(I)Ljava/lang/String;
     583: invokevirtual #13                 // Method java/lang/StringBuilder.append:(Ljava/lang/String;)Ljava/lang/StringBuilder;
     586: pop
     587: goto          620
     590: new           #14                 // class java/lang/IllegalStateException
     593: dup
     594: new           #3                  // class java/lang/StringBuilder
     597: dup
     598: invokespecial #4                  // Method java/lang/StringBuilder."<init>":()V
     601: ldc           #22                 // String Incomplete expression:
     603: invokevirtual #13                 // Method java/lang/StringBuilder.append:(Ljava/lang/String;)Ljava/lang/StringBuilder;
     606: aload_3
     607: invokevirtual #16                 // Method java/lang/StringBuilder.toString:()Ljava/lang/String;
     610: invokevirtual #13                 // Method java/lang/StringBuilder.append:(Ljava/lang/String;)Ljava/lang/StringBuilder;
     613: invokevirtual #16                 // Method java/lang/StringBuilder.toString:()Ljava/lang/String;
     616: invokespecial #17                 // Method java/lang/IllegalStateException."<init>":(Ljava/lang/String;)V
     619: athrow
     620: aload_3
     621: invokevirtual #16                 // Method java/lang/StringBuilder.toString:()Ljava/lang/String;
     624: areturn

  protected java.lang.String resolvePart(java.lang.String);
    Code:
       0: ldc           #23                 // String /
       2: aload_1
       3: invokevirtual #12                 // Method java/lang/String.equals:(Ljava/lang/Object;)Z
       6: ifeq          13
       9: getstatic     #24                 // Field java/io/File.separator:Ljava/lang/String;
      12: areturn
      13: ldc           #25                 // String :
      15: aload_1
      16: invokevirtual #12                 // Method java/lang/String.equals:(Ljava/lang/Object;)Z
      19: ifeq          26
      22: getstatic     #26                 // Field java/io/File.pathSeparator:Ljava/lang/String;
      25: areturn
      26: aload_1
      27: invokestatic  #27                 // Method java/lang/System.getProperty:(Ljava/lang/String;)Ljava/lang/String;
      30: astore_2
      31: aload_2
      32: ifnonnull     53
      35: aload_1
      36: ldc           #28                 // String env.
      38: invokevirtual #29                 // Method java/lang/String.startsWith:(Ljava/lang/String;)Z
      41: ifeq          53
      44: aload_1
      45: iconst_4
      46: invokevirtual #21                 // Method java/lang/String.substring:(I)Ljava/lang/String;
      49: invokestatic  #30                 // Method java/lang/System.getenv:(Ljava/lang/String;)Ljava/lang/String;
      52: astore_2
      53: aload_2
      54: areturn

  static {};
    Code:
       0: new           #31                 // class org/jboss/dmr/ValueExpressionResolver
       3: dup
       4: invokespecial #32                 // Method "<init>":()V
       7: putstatic     #33                 // Field DEFAULT_RESOLVER:Lorg/jboss/dmr/ValueExpressionResolver;
      10: return
}
