Compiled from "AbstractDataSourceAdd.java"
final class org.jboss.as.connector.subsystems.datasources.AbstractDataSourceAdd$2 extends org.jboss.msc.service.AbstractServiceListener<java.lang.Object> {
  final java.lang.String val$jndiName;

  org.jboss.as.connector.subsystems.datasources.AbstractDataSourceAdd$2(java.lang.String);
    Code:
       0: aload_0
       1: aload_1
       2: putfield      #1                  // Field val$jndiName:Ljava/lang/String;
       5: aload_0
       6: invokespecial #2                  // Method org/jboss/msc/service/AbstractServiceListener."<init>":()V
       9: return

  public void transition(org.jboss.msc.service.ServiceController<? extends java.lang.Object>, org.jboss.msc.service.ServiceController$Transition);
    Code:
       0: getstatic     #3                  // Field org/jboss/as/connector/subsystems/datasources/AbstractDataSourceAdd$3.$SwitchMap$org$jboss$msc$service$ServiceController$Transition:[I
       3: aload_2
       4: invokevirtual #4                  // Method org/jboss/msc/service/ServiceController$Transition.ordinal:()I
       7: iaload
       8: tableswitch   { // 1 to 3
                     1: 36
                     2: 51
                     3: 66
               default: 80
          }
      36: getstatic     #5                  // Field org/jboss/as/connector/logging/ConnectorLogger.SUBSYSTEM_DATASOURCES_LOGGER:Lorg/jboss/as/connector/logging/ConnectorLogger;
      39: aload_0
      40: getfield      #1                  // Field val$jndiName:Ljava/lang/String;
      43: invokeinterface #6,  2            // InterfaceMethod org/jboss/as/connector/logging/ConnectorLogger.boundDataSource:(Ljava/lang/String;)V
      48: goto          80
      51: getstatic     #5                  // Field org/jboss/as/connector/logging/ConnectorLogger.SUBSYSTEM_DATASOURCES_LOGGER:Lorg/jboss/as/connector/logging/ConnectorLogger;
      54: aload_0
      55: getfield      #1                  // Field val$jndiName:Ljava/lang/String;
      58: invokeinterface #7,  2            // InterfaceMethod org/jboss/as/connector/logging/ConnectorLogger.unboundDataSource:(Ljava/lang/String;)V
      63: goto          80
      66: getstatic     #5                  // Field org/jboss/as/connector/logging/ConnectorLogger.SUBSYSTEM_DATASOURCES_LOGGER:Lorg/jboss/as/connector/logging/ConnectorLogger;
      69: ldc           #8                  // String Removed JDBC Data-source [%s]
      71: aload_0
      72: getfield      #1                  // Field val$jndiName:Ljava/lang/String;
      75: invokeinterface #9,  3            // InterfaceMethod org/jboss/as/connector/logging/ConnectorLogger.debugf:(Ljava/lang/String;Ljava/lang/Object;)V
      80: return
}
