Compiled from "FastDatePrinter.java"
class net.logstash.logback.encoder.org.apache.commons.lang3.time.FastDatePrinter$TimeZoneNumberRule implements net.logstash.logback.encoder.org.apache.commons.lang3.time.FastDatePrinter$Rule {
  static final net.logstash.logback.encoder.org.apache.commons.lang3.time.FastDatePrinter$TimeZoneNumberRule INSTANCE_COLON;

  static final net.logstash.logback.encoder.org.apache.commons.lang3.time.FastDatePrinter$TimeZoneNumberRule INSTANCE_NO_COLON;

  final boolean mColon;

  net.logstash.logback.encoder.org.apache.commons.lang3.time.FastDatePrinter$TimeZoneNumberRule(boolean);
    Code:
       0: aload_0
       1: invokespecial #21                 // Method java/lang/Object."<init>":()V
       4: aload_0
       5: iload_1
       6: putfield      #23                 // Field mColon:Z
       9: return

  public int estimateLength();
    Code:
       0: iconst_5
       1: ireturn

  public void appendTo(java.lang.Appendable, java.util.Calendar) throws java.io.IOException;
    Code:
       0: aload_2
       1: bipush        15
       3: invokevirtual #37                 // Method java/util/Calendar.get:(I)I
       6: aload_2
       7: bipush        16
       9: invokevirtual #37                 // Method java/util/Calendar.get:(I)I
      12: iadd
      13: istore_3
      14: iload_3
      15: ifge          33
      18: aload_1
      19: bipush        45
      21: invokeinterface #43,  2           // InterfaceMethod java/lang/Appendable.append:(C)Ljava/lang/Appendable;
      26: pop
      27: iload_3
      28: ineg
      29: istore_3
      30: goto          42
      33: aload_1
      34: bipush        43
      36: invokeinterface #43,  2           // InterfaceMethod java/lang/Appendable.append:(C)Ljava/lang/Appendable;
      41: pop
      42: iload_3
      43: ldc           #44                 // int 3600000
      45: idiv
      46: istore        4
      48: aload_1
      49: iload         4
      51: invokestatic  #48                 // Method net/logstash/logback/encoder/org/apache/commons/lang3/time/FastDatePrinter.access$000:(Ljava/lang/Appendable;I)V
      54: aload_0
      55: getfield      #23                 // Field mColon:Z
      58: ifeq          70
      61: aload_1
      62: bipush        58
      64: invokeinterface #43,  2           // InterfaceMethod java/lang/Appendable.append:(C)Ljava/lang/Appendable;
      69: pop
      70: iload_3
      71: ldc           #49                 // int 60000
      73: idiv
      74: bipush        60
      76: iload         4
      78: imul
      79: isub
      80: istore        5
      82: aload_1
      83: iload         5
      85: invokestatic  #48                 // Method net/logstash/logback/encoder/org/apache/commons/lang3/time/FastDatePrinter.access$000:(Ljava/lang/Appendable;I)V
      88: return

  static {};
    Code:
       0: new           #2                  // class net/logstash/logback/encoder/org/apache/commons/lang3/time/FastDatePrinter$TimeZoneNumberRule
       3: dup
       4: iconst_1
       5: invokespecial #60                 // Method "<init>":(Z)V
       8: putstatic     #62                 // Field INSTANCE_COLON:Lnet/logstash/logback/encoder/org/apache/commons/lang3/time/FastDatePrinter$TimeZoneNumberRule;
      11: new           #2                  // class net/logstash/logback/encoder/org/apache/commons/lang3/time/FastDatePrinter$TimeZoneNumberRule
      14: dup
      15: iconst_0
      16: invokespecial #60                 // Method "<init>":(Z)V
      19: putstatic     #64                 // Field INSTANCE_NO_COLON:Lnet/logstash/logback/encoder/org/apache/commons/lang3/time/FastDatePrinter$TimeZoneNumberRule;
      22: return
}
