Compiled from "ClientInterceptorRepositoryImpl.java"
public class org.jboss.resteasy.client.core.ClientInterceptorRepositoryImpl implements org.jboss.resteasy.client.core.ClientInterceptorRepository {
  private java.util.Map<org.jboss.resteasy.client.core.ClientInterceptorRepositoryImpl$InterceptorType, java.util.LinkedList<?>> interceptorLists;

  public org.jboss.resteasy.client.core.ClientInterceptorRepositoryImpl();
    Code:
       0: aload_0
       1: invokespecial #1                  // Method java/lang/Object."<init>":()V
       4: aload_0
       5: new           #2                  // class java/util/HashMap
       8: dup
       9: invokespecial #3                  // Method java/util/HashMap."<init>":()V
      12: putfield      #4                  // Field interceptorLists:Ljava/util/Map;
      15: return

  protected javax.ws.rs.ext.ReaderInterceptor[] getReaderInterceptors();
    Code:
       0: aload_0
       1: ldc           #5                  // class javax/ws/rs/ext/ReaderInterceptor
       3: invokespecial #6                  // Method getArray:(Ljava/lang/Class;)[Ljava/lang/Object;
       6: checkcast     #7                  // class "[Ljavax/ws/rs/ext/ReaderInterceptor;"
       9: areturn

  protected javax.ws.rs.ext.WriterInterceptor[] getWriterInterceptors();
    Code:
       0: aload_0
       1: ldc           #8                  // class javax/ws/rs/ext/WriterInterceptor
       3: invokespecial #6                  // Method getArray:(Ljava/lang/Class;)[Ljava/lang/Object;
       6: checkcast     #9                  // class "[Ljavax/ws/rs/ext/WriterInterceptor;"
       9: areturn

  protected org.jboss.resteasy.spi.interception.ClientExecutionInterceptor[] getExecutionInterceptors();
    Code:
       0: aload_0
       1: ldc           #10                 // class org/jboss/resteasy/spi/interception/ClientExecutionInterceptor
       3: invokespecial #6                  // Method getArray:(Ljava/lang/Class;)[Ljava/lang/Object;
       6: checkcast     #11                 // class "[Lorg/jboss/resteasy/spi/interception/ClientExecutionInterceptor;"
       9: areturn

  private <T> T[] getArray(java.lang.Class<T>);
    Code:
       0: aload_0
       1: aload_1
       2: invokevirtual #12                 // Method getInterceptors:(Ljava/lang/Class;)Ljava/util/LinkedList;
       5: astore_2
       6: aload_2
       7: aload_1
       8: aload_2
       9: invokevirtual #13                 // Method java/util/LinkedList.size:()I
      12: invokestatic  #14                 // Method java/lang/reflect/Array.newInstance:(Ljava/lang/Class;I)Ljava/lang/Object;
      15: checkcast     #15                 // class "[Ljava/lang/Object;"
      18: checkcast     #15                 // class "[Ljava/lang/Object;"
      21: invokevirtual #16                 // Method java/util/LinkedList.toArray:([Ljava/lang/Object;)[Ljava/lang/Object;
      24: checkcast     #15                 // class "[Ljava/lang/Object;"
      27: areturn

  protected void setReaderInterceptors(javax.ws.rs.ext.ReaderInterceptor[]);
    Code:
       0: aload_0
       1: getstatic     #17                 // Field org/jboss/resteasy/client/core/ClientInterceptorRepositoryImpl$InterceptorType.MessageBodyReader:Lorg/jboss/resteasy/client/core/ClientInterceptorRepositoryImpl$InterceptorType;
       4: aload_1
       5: invokespecial #18                 // Method setData:(Lorg/jboss/resteasy/client/core/ClientInterceptorRepositoryImpl$InterceptorType;[Ljava/lang/Object;)V
       8: return

  protected void setWriterInterceptors(javax.ws.rs.ext.WriterInterceptor[]);
    Code:
       0: aload_0
       1: getstatic     #19                 // Field org/jboss/resteasy/client/core/ClientInterceptorRepositoryImpl$InterceptorType.MessageBodyWriter:Lorg/jboss/resteasy/client/core/ClientInterceptorRepositoryImpl$InterceptorType;
       4: aload_1
       5: invokespecial #18                 // Method setData:(Lorg/jboss/resteasy/client/core/ClientInterceptorRepositoryImpl$InterceptorType;[Ljava/lang/Object;)V
       8: return

  protected void setExecutionInterceptors(org.jboss.resteasy.spi.interception.ClientExecutionInterceptor[]);
    Code:
       0: aload_0
       1: getstatic     #20                 // Field org/jboss/resteasy/client/core/ClientInterceptorRepositoryImpl$InterceptorType.ClientExecution:Lorg/jboss/resteasy/client/core/ClientInterceptorRepositoryImpl$InterceptorType;
       4: aload_1
       5: invokespecial #18                 // Method setData:(Lorg/jboss/resteasy/client/core/ClientInterceptorRepositoryImpl$InterceptorType;[Ljava/lang/Object;)V
       8: return

  protected void setExecutionInterceptors(java.util.Collection<org.jboss.resteasy.spi.interception.ClientExecutionInterceptor>);
    Code:
       0: aload_0
       1: getstatic     #20                 // Field org/jboss/resteasy/client/core/ClientInterceptorRepositoryImpl$InterceptorType.ClientExecution:Lorg/jboss/resteasy/client/core/ClientInterceptorRepositoryImpl$InterceptorType;
       4: aload_1
       5: invokespecial #21                 // Method setData:(Lorg/jboss/resteasy/client/core/ClientInterceptorRepositoryImpl$InterceptorType;Ljava/util/Collection;)V
       8: return

  public java.util.LinkedList<javax.ws.rs.ext.ReaderInterceptor> getReaderInterceptorList();
    Code:
       0: aload_0
       1: getstatic     #17                 // Field org/jboss/resteasy/client/core/ClientInterceptorRepositoryImpl$InterceptorType.MessageBodyReader:Lorg/jboss/resteasy/client/core/ClientInterceptorRepositoryImpl$InterceptorType;
       4: invokevirtual #22                 // Method getInterceptors:(Lorg/jboss/resteasy/client/core/ClientInterceptorRepositoryImpl$InterceptorType;)Ljava/util/LinkedList;
       7: areturn

  public java.util.LinkedList<javax.ws.rs.ext.WriterInterceptor> getWriterInterceptorList();
    Code:
       0: aload_0
       1: getstatic     #19                 // Field org/jboss/resteasy/client/core/ClientInterceptorRepositoryImpl$InterceptorType.MessageBodyWriter:Lorg/jboss/resteasy/client/core/ClientInterceptorRepositoryImpl$InterceptorType;
       4: invokevirtual #22                 // Method getInterceptors:(Lorg/jboss/resteasy/client/core/ClientInterceptorRepositoryImpl$InterceptorType;)Ljava/util/LinkedList;
       7: areturn

  public java.util.LinkedList<org.jboss.resteasy.spi.interception.ClientExecutionInterceptor> getExecutionInterceptorList();
    Code:
       0: aload_0
       1: getstatic     #20                 // Field org/jboss/resteasy/client/core/ClientInterceptorRepositoryImpl$InterceptorType.ClientExecution:Lorg/jboss/resteasy/client/core/ClientInterceptorRepositoryImpl$InterceptorType;
       4: invokevirtual #22                 // Method getInterceptors:(Lorg/jboss/resteasy/client/core/ClientInterceptorRepositoryImpl$InterceptorType;)Ljava/util/LinkedList;
       7: areturn

  protected <T> java.util.LinkedList<T> getInterceptors(java.lang.Class<T>);
    Code:
       0: aload_1
       1: invokestatic  #23                 // Method org/jboss/resteasy/client/core/ClientInterceptorRepositoryImpl$InterceptorType.getInterceptorTypeFor:(Ljava/lang/Class;)Lorg/jboss/resteasy/client/core/ClientInterceptorRepositoryImpl$InterceptorType;
       4: astore_2
       5: aload_2
       6: ifnonnull     11
       9: aconst_null
      10: areturn
      11: aload_0
      12: aload_2
      13: invokevirtual #22                 // Method getInterceptors:(Lorg/jboss/resteasy/client/core/ClientInterceptorRepositoryImpl$InterceptorType;)Ljava/util/LinkedList;
      16: areturn

  protected synchronized java.util.LinkedList getInterceptors(org.jboss.resteasy.client.core.ClientInterceptorRepositoryImpl$InterceptorType);
    Code:
       0: aload_0
       1: getfield      #4                  // Field interceptorLists:Ljava/util/Map;
       4: aload_1
       5: invokeinterface #24,  2           // InterfaceMethod java/util/Map.get:(Ljava/lang/Object;)Ljava/lang/Object;
      10: checkcast     #25                 // class java/util/LinkedList
      13: astore_2
      14: aload_2
      15: ifnonnull     38
      18: aload_0
      19: getfield      #4                  // Field interceptorLists:Ljava/util/Map;
      22: aload_1
      23: new           #25                 // class java/util/LinkedList
      26: dup
      27: invokespecial #26                 // Method java/util/LinkedList."<init>":()V
      30: dup
      31: astore_2
      32: invokeinterface #27,  3           // InterfaceMethod java/util/Map.put:(Ljava/lang/Object;Ljava/lang/Object;)Ljava/lang/Object;
      37: pop
      38: aload_2
      39: areturn

  private void setData(org.jboss.resteasy.client.core.ClientInterceptorRepositoryImpl$InterceptorType, java.lang.Object[]);
    Code:
       0: aload_0
       1: aload_1
       2: aload_2
       3: invokestatic  #28                 // Method java/util/Arrays.asList:([Ljava/lang/Object;)Ljava/util/List;
       6: invokespecial #21                 // Method setData:(Lorg/jboss/resteasy/client/core/ClientInterceptorRepositoryImpl$InterceptorType;Ljava/util/Collection;)V
       9: return

  private void setData(org.jboss.resteasy.client.core.ClientInterceptorRepositoryImpl$InterceptorType, java.util.Collection);
    Code:
       0: aload_0
       1: aload_1
       2: invokevirtual #22                 // Method getInterceptors:(Lorg/jboss/resteasy/client/core/ClientInterceptorRepositoryImpl$InterceptorType;)Ljava/util/LinkedList;
       5: astore_3
       6: aload_3
       7: invokevirtual #29                 // Method java/util/LinkedList.clear:()V
      10: aload_3
      11: aload_2
      12: invokevirtual #30                 // Method java/util/LinkedList.addAll:(Ljava/util/Collection;)Z
      15: pop
      16: return

  public void copyClientInterceptorsTo(org.jboss.resteasy.client.core.ClientInterceptorRepositoryImpl);
    Code:
       0: aload_0
       1: getfield      #4                  // Field interceptorLists:Ljava/util/Map;
       4: invokeinterface #31,  1           // InterfaceMethod java/util/Map.entrySet:()Ljava/util/Set;
       9: invokeinterface #32,  1           // InterfaceMethod java/util/Set.iterator:()Ljava/util/Iterator;
      14: astore_2
      15: aload_2
      16: invokeinterface #33,  1           // InterfaceMethod java/util/Iterator.hasNext:()Z
      21: ifeq          75
      24: aload_2
      25: invokeinterface #34,  1           // InterfaceMethod java/util/Iterator.next:()Ljava/lang/Object;
      30: checkcast     #35                 // class java/util/Map$Entry
      33: astore_3
      34: aload_1
      35: aload_3
      36: invokeinterface #36,  1           // InterfaceMethod java/util/Map$Entry.getKey:()Ljava/lang/Object;
      41: checkcast     #37                 // class org/jboss/resteasy/client/core/ClientInterceptorRepositoryImpl$InterceptorType
      44: invokevirtual #22                 // Method getInterceptors:(Lorg/jboss/resteasy/client/core/ClientInterceptorRepositoryImpl$InterceptorType;)Ljava/util/LinkedList;
      47: astore        4
      49: aload_0
      50: aload_3
      51: invokeinterface #36,  1           // InterfaceMethod java/util/Map$Entry.getKey:()Ljava/lang/Object;
      56: checkcast     #37                 // class org/jboss/resteasy/client/core/ClientInterceptorRepositoryImpl$InterceptorType
      59: invokevirtual #22                 // Method getInterceptors:(Lorg/jboss/resteasy/client/core/ClientInterceptorRepositoryImpl$InterceptorType;)Ljava/util/LinkedList;
      62: astore        5
      64: aload         4
      66: aload         5
      68: invokevirtual #30                 // Method java/util/LinkedList.addAll:(Ljava/util/Collection;)Z
      71: pop
      72: goto          15
      75: return

  public void prefixClientInterceptorsTo(org.jboss.resteasy.client.core.ClientInterceptorRepositoryImpl);
    Code:
       0: aload_0
       1: getfield      #4                  // Field interceptorLists:Ljava/util/Map;
       4: invokeinterface #31,  1           // InterfaceMethod java/util/Map.entrySet:()Ljava/util/Set;
       9: invokeinterface #32,  1           // InterfaceMethod java/util/Set.iterator:()Ljava/util/Iterator;
      14: astore_2
      15: aload_2
      16: invokeinterface #33,  1           // InterfaceMethod java/util/Iterator.hasNext:()Z
      21: ifeq          103
      24: aload_2
      25: invokeinterface #34,  1           // InterfaceMethod java/util/Iterator.next:()Ljava/lang/Object;
      30: checkcast     #35                 // class java/util/Map$Entry
      33: astore_3
      34: aload_1
      35: aload_3
      36: invokeinterface #36,  1           // InterfaceMethod java/util/Map$Entry.getKey:()Ljava/lang/Object;
      41: checkcast     #37                 // class org/jboss/resteasy/client/core/ClientInterceptorRepositoryImpl$InterceptorType
      44: invokevirtual #22                 // Method getInterceptors:(Lorg/jboss/resteasy/client/core/ClientInterceptorRepositoryImpl$InterceptorType;)Ljava/util/LinkedList;
      47: astore        4
      49: aload_0
      50: aload_3
      51: invokeinterface #36,  1           // InterfaceMethod java/util/Map$Entry.getKey:()Ljava/lang/Object;
      56: checkcast     #37                 // class org/jboss/resteasy/client/core/ClientInterceptorRepositoryImpl$InterceptorType
      59: invokevirtual #22                 // Method getInterceptors:(Lorg/jboss/resteasy/client/core/ClientInterceptorRepositoryImpl$InterceptorType;)Ljava/util/LinkedList;
      62: astore        5
      64: aload         5
      66: invokevirtual #38                 // Method java/util/LinkedList.iterator:()Ljava/util/Iterator;
      69: astore        6
      71: aload         6
      73: invokeinterface #33,  1           // InterfaceMethod java/util/Iterator.hasNext:()Z
      78: ifeq          100
      81: aload         6
      83: invokeinterface #34,  1           // InterfaceMethod java/util/Iterator.next:()Ljava/lang/Object;
      88: astore        7
      90: aload         4
      92: aload         7
      94: invokevirtual #39                 // Method java/util/LinkedList.addFirst:(Ljava/lang/Object;)V
      97: goto          71
     100: goto          15
     103: return

  public void registerInterceptor(java.lang.Object);
    Code:
       0: iconst_0
       1: istore_2
       2: aload_1
       3: instanceof    #10                 // class org/jboss/resteasy/spi/interception/ClientExecutionInterceptor
       6: ifeq          23
       9: aload_0
      10: invokevirtual #40                 // Method getExecutionInterceptorList:()Ljava/util/LinkedList;
      13: aload_1
      14: checkcast     #10                 // class org/jboss/resteasy/spi/interception/ClientExecutionInterceptor
      17: invokevirtual #41                 // Method java/util/LinkedList.add:(Ljava/lang/Object;)Z
      20: pop
      21: iconst_1
      22: istore_2
      23: aload_1
      24: instanceof    #42                 // class org/jboss/resteasy/spi/interception/MessageBodyReaderInterceptor
      27: ifeq          51
      30: aload_0
      31: invokevirtual #43                 // Method getReaderInterceptorList:()Ljava/util/LinkedList;
      34: new           #44                 // class org/jboss/resteasy/core/interception/ReaderInterceptorRegistry$ReaderInterceptorFacade
      37: dup
      38: aload_1
      39: checkcast     #42                 // class org/jboss/resteasy/spi/interception/MessageBodyReaderInterceptor
      42: invokespecial #45                 // Method org/jboss/resteasy/core/interception/ReaderInterceptorRegistry$ReaderInterceptorFacade."<init>":(Lorg/jboss/resteasy/spi/interception/MessageBodyReaderInterceptor;)V
      45: invokevirtual #41                 // Method java/util/LinkedList.add:(Ljava/lang/Object;)Z
      48: pop
      49: iconst_1
      50: istore_2
      51: aload_1
      52: instanceof    #46                 // class org/jboss/resteasy/spi/interception/MessageBodyWriterInterceptor
      55: ifeq          79
      58: aload_0
      59: invokevirtual #47                 // Method getWriterInterceptorList:()Ljava/util/LinkedList;
      62: new           #48                 // class org/jboss/resteasy/core/interception/WriterInterceptorRegistry$WriterInterceptorFacade
      65: dup
      66: aload_1
      67: checkcast     #46                 // class org/jboss/resteasy/spi/interception/MessageBodyWriterInterceptor
      70: invokespecial #49                 // Method org/jboss/resteasy/core/interception/WriterInterceptorRegistry$WriterInterceptorFacade."<init>":(Lorg/jboss/resteasy/spi/interception/MessageBodyWriterInterceptor;)V
      73: invokevirtual #41                 // Method java/util/LinkedList.add:(Ljava/lang/Object;)Z
      76: pop
      77: iconst_1
      78: istore_2
      79: iload_2
      80: ifne          99
      83: new           #50                 // class java/lang/RuntimeException
      86: dup
      87: getstatic     #51                 // Field org/jboss/resteasy/resteasy_jaxrs/i18n/Messages.MESSAGES:Lorg/jboss/resteasy/resteasy_jaxrs/i18n/Messages;
      90: invokeinterface #52,  1           // InterfaceMethod org/jboss/resteasy/resteasy_jaxrs/i18n/Messages.entityNotOfUnderstoodType:()Ljava/lang/String;
      95: invokespecial #53                 // Method java/lang/RuntimeException."<init>":(Ljava/lang/String;)V
      98: athrow
      99: return
}
