Compiled from "DynamoDBv2Actions.java"
public final class com.amazonaws.auth.policy.actions.DynamoDBv2Actions extends java.lang.Enum<com.amazonaws.auth.policy.actions.DynamoDBv2Actions> implements com.amazonaws.auth.policy.Action {
  public static final com.amazonaws.auth.policy.actions.DynamoDBv2Actions AllDynamoDBv2Actions;

  public static final com.amazonaws.auth.policy.actions.DynamoDBv2Actions BatchGetItem;

  public static final com.amazonaws.auth.policy.actions.DynamoDBv2Actions BatchWriteItem;

  public static final com.amazonaws.auth.policy.actions.DynamoDBv2Actions CreateTable;

  public static final com.amazonaws.auth.policy.actions.DynamoDBv2Actions DeleteItem;

  public static final com.amazonaws.auth.policy.actions.DynamoDBv2Actions DeleteTable;

  public static final com.amazonaws.auth.policy.actions.DynamoDBv2Actions DescribeLimits;

  public static final com.amazonaws.auth.policy.actions.DynamoDBv2Actions DescribeTable;

  public static final com.amazonaws.auth.policy.actions.DynamoDBv2Actions GetItem;

  public static final com.amazonaws.auth.policy.actions.DynamoDBv2Actions ListTables;

  public static final com.amazonaws.auth.policy.actions.DynamoDBv2Actions PutItem;

  public static final com.amazonaws.auth.policy.actions.DynamoDBv2Actions Query;

  public static final com.amazonaws.auth.policy.actions.DynamoDBv2Actions Scan;

  public static final com.amazonaws.auth.policy.actions.DynamoDBv2Actions UpdateItem;

  public static final com.amazonaws.auth.policy.actions.DynamoDBv2Actions UpdateTable;

  private final java.lang.String action;

  private static final com.amazonaws.auth.policy.actions.DynamoDBv2Actions[] $VALUES;

  public static com.amazonaws.auth.policy.actions.DynamoDBv2Actions[] values();
    Code:
       0: getstatic     #1                  // Field $VALUES:[Lcom/amazonaws/auth/policy/actions/DynamoDBv2Actions;
       3: invokevirtual #2                  // Method "[Lcom/amazonaws/auth/policy/actions/DynamoDBv2Actions;".clone:()Ljava/lang/Object;
       6: checkcast     #3                  // class "[Lcom/amazonaws/auth/policy/actions/DynamoDBv2Actions;"
       9: areturn

  public static com.amazonaws.auth.policy.actions.DynamoDBv2Actions valueOf(java.lang.String);
    Code:
       0: ldc           #4                  // class com/amazonaws/auth/policy/actions/DynamoDBv2Actions
       2: aload_0
       3: invokestatic  #5                  // Method java/lang/Enum.valueOf:(Ljava/lang/Class;Ljava/lang/String;)Ljava/lang/Enum;
       6: checkcast     #4                  // class com/amazonaws/auth/policy/actions/DynamoDBv2Actions
       9: areturn

  private com.amazonaws.auth.policy.actions.DynamoDBv2Actions(java.lang.String);
    Code:
       0: aload_0
       1: aload_1
       2: iload_2
       3: invokespecial #6                  // Method java/lang/Enum."<init>":(Ljava/lang/String;I)V
       6: aload_0
       7: aload_3
       8: putfield      #7                  // Field action:Ljava/lang/String;
      11: return

  public java.lang.String getActionName();
    Code:
       0: aload_0
       1: getfield      #7                  // Field action:Ljava/lang/String;
       4: areturn

  static {};
    Code:
       0: new           #4                  // class com/amazonaws/auth/policy/actions/DynamoDBv2Actions
       3: dup
       4: ldc           #8                  // String AllDynamoDBv2Actions
       6: iconst_0
       7: ldc           #9                  // String dynamodb:*
       9: invokespecial #10                 // Method "<init>":(Ljava/lang/String;ILjava/lang/String;)V
      12: putstatic     #11                 // Field AllDynamoDBv2Actions:Lcom/amazonaws/auth/policy/actions/DynamoDBv2Actions;
      15: new           #4                  // class com/amazonaws/auth/policy/actions/DynamoDBv2Actions
      18: dup
      19: ldc           #12                 // String BatchGetItem
      21: iconst_1
      22: ldc           #13                 // String dynamodb:BatchGetItem
      24: invokespecial #10                 // Method "<init>":(Ljava/lang/String;ILjava/lang/String;)V
      27: putstatic     #14                 // Field BatchGetItem:Lcom/amazonaws/auth/policy/actions/DynamoDBv2Actions;
      30: new           #4                  // class com/amazonaws/auth/policy/actions/DynamoDBv2Actions
      33: dup
      34: ldc           #15                 // String BatchWriteItem
      36: iconst_2
      37: ldc           #16                 // String dynamodb:BatchWriteItem
      39: invokespecial #10                 // Method "<init>":(Ljava/lang/String;ILjava/lang/String;)V
      42: putstatic     #17                 // Field BatchWriteItem:Lcom/amazonaws/auth/policy/actions/DynamoDBv2Actions;
      45: new           #4                  // class com/amazonaws/auth/policy/actions/DynamoDBv2Actions
      48: dup
      49: ldc           #18                 // String CreateTable
      51: iconst_3
      52: ldc           #19                 // String dynamodb:CreateTable
      54: invokespecial #10                 // Method "<init>":(Ljava/lang/String;ILjava/lang/String;)V
      57: putstatic     #20                 // Field CreateTable:Lcom/amazonaws/auth/policy/actions/DynamoDBv2Actions;
      60: new           #4                  // class com/amazonaws/auth/policy/actions/DynamoDBv2Actions
      63: dup
      64: ldc           #21                 // String DeleteItem
      66: iconst_4
      67: ldc           #22                 // String dynamodb:DeleteItem
      69: invokespecial #10                 // Method "<init>":(Ljava/lang/String;ILjava/lang/String;)V
      72: putstatic     #23                 // Field DeleteItem:Lcom/amazonaws/auth/policy/actions/DynamoDBv2Actions;
      75: new           #4                  // class com/amazonaws/auth/policy/actions/DynamoDBv2Actions
      78: dup
      79: ldc           #24                 // String DeleteTable
      81: iconst_5
      82: ldc           #25                 // String dynamodb:DeleteTable
      84: invokespecial #10                 // Method "<init>":(Ljava/lang/String;ILjava/lang/String;)V
      87: putstatic     #26                 // Field DeleteTable:Lcom/amazonaws/auth/policy/actions/DynamoDBv2Actions;
      90: new           #4                  // class com/amazonaws/auth/policy/actions/DynamoDBv2Actions
      93: dup
      94: ldc           #27                 // String DescribeLimits
      96: bipush        6
      98: ldc           #28                 // String dynamodb:DescribeLimits
     100: invokespecial #10                 // Method "<init>":(Ljava/lang/String;ILjava/lang/String;)V
     103: putstatic     #29                 // Field DescribeLimits:Lcom/amazonaws/auth/policy/actions/DynamoDBv2Actions;
     106: new           #4                  // class com/amazonaws/auth/policy/actions/DynamoDBv2Actions
     109: dup
     110: ldc           #30                 // String DescribeTable
     112: bipush        7
     114: ldc           #31                 // String dynamodb:DescribeTable
     116: invokespecial #10                 // Method "<init>":(Ljava/lang/String;ILjava/lang/String;)V
     119: putstatic     #32                 // Field DescribeTable:Lcom/amazonaws/auth/policy/actions/DynamoDBv2Actions;
     122: new           #4                  // class com/amazonaws/auth/policy/actions/DynamoDBv2Actions
     125: dup
     126: ldc           #33                 // String GetItem
     128: bipush        8
     130: ldc           #34                 // String dynamodb:GetItem
     132: invokespecial #10                 // Method "<init>":(Ljava/lang/String;ILjava/lang/String;)V
     135: putstatic     #35                 // Field GetItem:Lcom/amazonaws/auth/policy/actions/DynamoDBv2Actions;
     138: new           #4                  // class com/amazonaws/auth/policy/actions/DynamoDBv2Actions
     141: dup
     142: ldc           #36                 // String ListTables
     144: bipush        9
     146: ldc           #37                 // String dynamodb:ListTables
     148: invokespecial #10                 // Method "<init>":(Ljava/lang/String;ILjava/lang/String;)V
     151: putstatic     #38                 // Field ListTables:Lcom/amazonaws/auth/policy/actions/DynamoDBv2Actions;
     154: new           #4                  // class com/amazonaws/auth/policy/actions/DynamoDBv2Actions
     157: dup
     158: ldc           #39                 // String PutItem
     160: bipush        10
     162: ldc           #40                 // String dynamodb:PutItem
     164: invokespecial #10                 // Method "<init>":(Ljava/lang/String;ILjava/lang/String;)V
     167: putstatic     #41                 // Field PutItem:Lcom/amazonaws/auth/policy/actions/DynamoDBv2Actions;
     170: new           #4                  // class com/amazonaws/auth/policy/actions/DynamoDBv2Actions
     173: dup
     174: ldc           #42                 // String Query
     176: bipush        11
     178: ldc           #43                 // String dynamodb:Query
     180: invokespecial #10                 // Method "<init>":(Ljava/lang/String;ILjava/lang/String;)V
     183: putstatic     #44                 // Field Query:Lcom/amazonaws/auth/policy/actions/DynamoDBv2Actions;
     186: new           #4                  // class com/amazonaws/auth/policy/actions/DynamoDBv2Actions
     189: dup
     190: ldc           #45                 // String Scan
     192: bipush        12
     194: ldc           #46                 // String dynamodb:Scan
     196: invokespecial #10                 // Method "<init>":(Ljava/lang/String;ILjava/lang/String;)V
     199: putstatic     #47                 // Field Scan:Lcom/amazonaws/auth/policy/actions/DynamoDBv2Actions;
     202: new           #4                  // class com/amazonaws/auth/policy/actions/DynamoDBv2Actions
     205: dup
     206: ldc           #48                 // String UpdateItem
     208: bipush        13
     210: ldc           #49                 // String dynamodb:UpdateItem
     212: invokespecial #10                 // Method "<init>":(Ljava/lang/String;ILjava/lang/String;)V
     215: putstatic     #50                 // Field UpdateItem:Lcom/amazonaws/auth/policy/actions/DynamoDBv2Actions;
     218: new           #4                  // class com/amazonaws/auth/policy/actions/DynamoDBv2Actions
     221: dup
     222: ldc           #51                 // String UpdateTable
     224: bipush        14
     226: ldc           #52                 // String dynamodb:UpdateTable
     228: invokespecial #10                 // Method "<init>":(Ljava/lang/String;ILjava/lang/String;)V
     231: putstatic     #53                 // Field UpdateTable:Lcom/amazonaws/auth/policy/actions/DynamoDBv2Actions;
     234: bipush        15
     236: anewarray     #4                  // class com/amazonaws/auth/policy/actions/DynamoDBv2Actions
     239: dup
     240: iconst_0
     241: getstatic     #11                 // Field AllDynamoDBv2Actions:Lcom/amazonaws/auth/policy/actions/DynamoDBv2Actions;
     244: aastore
     245: dup
     246: iconst_1
     247: getstatic     #14                 // Field BatchGetItem:Lcom/amazonaws/auth/policy/actions/DynamoDBv2Actions;
     250: aastore
     251: dup
     252: iconst_2
     253: getstatic     #17                 // Field BatchWriteItem:Lcom/amazonaws/auth/policy/actions/DynamoDBv2Actions;
     256: aastore
     257: dup
     258: iconst_3
     259: getstatic     #20                 // Field CreateTable:Lcom/amazonaws/auth/policy/actions/DynamoDBv2Actions;
     262: aastore
     263: dup
     264: iconst_4
     265: getstatic     #23                 // Field DeleteItem:Lcom/amazonaws/auth/policy/actions/DynamoDBv2Actions;
     268: aastore
     269: dup
     270: iconst_5
     271: getstatic     #26                 // Field DeleteTable:Lcom/amazonaws/auth/policy/actions/DynamoDBv2Actions;
     274: aastore
     275: dup
     276: bipush        6
     278: getstatic     #29                 // Field DescribeLimits:Lcom/amazonaws/auth/policy/actions/DynamoDBv2Actions;
     281: aastore
     282: dup
     283: bipush        7
     285: getstatic     #32                 // Field DescribeTable:Lcom/amazonaws/auth/policy/actions/DynamoDBv2Actions;
     288: aastore
     289: dup
     290: bipush        8
     292: getstatic     #35                 // Field GetItem:Lcom/amazonaws/auth/policy/actions/DynamoDBv2Actions;
     295: aastore
     296: dup
     297: bipush        9
     299: getstatic     #38                 // Field ListTables:Lcom/amazonaws/auth/policy/actions/DynamoDBv2Actions;
     302: aastore
     303: dup
     304: bipush        10
     306: getstatic     #41                 // Field PutItem:Lcom/amazonaws/auth/policy/actions/DynamoDBv2Actions;
     309: aastore
     310: dup
     311: bipush        11
     313: getstatic     #44                 // Field Query:Lcom/amazonaws/auth/policy/actions/DynamoDBv2Actions;
     316: aastore
     317: dup
     318: bipush        12
     320: getstatic     #47                 // Field Scan:Lcom/amazonaws/auth/policy/actions/DynamoDBv2Actions;
     323: aastore
     324: dup
     325: bipush        13
     327: getstatic     #50                 // Field UpdateItem:Lcom/amazonaws/auth/policy/actions/DynamoDBv2Actions;
     330: aastore
     331: dup
     332: bipush        14
     334: getstatic     #53                 // Field UpdateTable:Lcom/amazonaws/auth/policy/actions/DynamoDBv2Actions;
     337: aastore
     338: putstatic     #1                  // Field $VALUES:[Lcom/amazonaws/auth/policy/actions/DynamoDBv2Actions;
     341: return
}
