Compiled from "BrokerNamespaceIsolationDataImpl.java"
public class org.apache.pulsar.common.policies.data.BrokerNamespaceIsolationDataImpl$BrokerNamespaceIsolationDataImplBuilder implements org.apache.pulsar.common.policies.data.BrokerNamespaceIsolationData$Builder {
  private java.lang.String brokerName;

  private java.lang.String policyName;

  private boolean isPrimary;

  private java.util.List<java.lang.String> namespaceRegex;

  public org.apache.pulsar.common.policies.data.BrokerNamespaceIsolationDataImpl$BrokerNamespaceIsolationDataImplBuilder();
    Code:
       0: aload_0
       1: invokespecial #1                  // Method java/lang/Object."<init>":()V
       4: return

  public org.apache.pulsar.common.policies.data.BrokerNamespaceIsolationDataImpl$BrokerNamespaceIsolationDataImplBuilder brokerName(java.lang.String);
    Code:
       0: aload_0
       1: aload_1
       2: putfield      #2                  // Field brokerName:Ljava/lang/String;
       5: aload_0
       6: areturn

  public org.apache.pulsar.common.policies.data.BrokerNamespaceIsolationDataImpl$BrokerNamespaceIsolationDataImplBuilder policyName(java.lang.String);
    Code:
       0: aload_0
       1: aload_1
       2: putfield      #3                  // Field policyName:Ljava/lang/String;
       5: aload_0
       6: areturn

  public org.apache.pulsar.common.policies.data.BrokerNamespaceIsolationDataImpl$BrokerNamespaceIsolationDataImplBuilder primary(boolean);
    Code:
       0: aload_0
       1: iload_1
       2: putfield      #4                  // Field isPrimary:Z
       5: aload_0
       6: areturn

  public org.apache.pulsar.common.policies.data.BrokerNamespaceIsolationDataImpl$BrokerNamespaceIsolationDataImplBuilder namespaceRegex(java.util.List<java.lang.String>);
    Code:
       0: aload_0
       1: aload_1
       2: putfield      #5                  // Field namespaceRegex:Ljava/util/List;
       5: aload_0
       6: areturn

  public org.apache.pulsar.common.policies.data.BrokerNamespaceIsolationDataImpl build();
    Code:
       0: new           #6                  // class org/apache/pulsar/common/policies/data/BrokerNamespaceIsolationDataImpl
       3: dup
       4: aload_0
       5: getfield      #2                  // Field brokerName:Ljava/lang/String;
       8: aload_0
       9: getfield      #3                  // Field policyName:Ljava/lang/String;
      12: aload_0
      13: getfield      #4                  // Field isPrimary:Z
      16: aload_0
      17: getfield      #5                  // Field namespaceRegex:Ljava/util/List;
      20: invokespecial #7                  // Method org/apache/pulsar/common/policies/data/BrokerNamespaceIsolationDataImpl."<init>":(Ljava/lang/String;Ljava/lang/String;ZLjava/util/List;)V
      23: areturn

  public org.apache.pulsar.common.policies.data.BrokerNamespaceIsolationData build();
    Code:
       0: aload_0
       1: invokevirtual #8                  // Method build:()Lorg/apache/pulsar/common/policies/data/BrokerNamespaceIsolationDataImpl;
       4: areturn

  public org.apache.pulsar.common.policies.data.BrokerNamespaceIsolationData$Builder namespaceRegex(java.util.List);
    Code:
       0: aload_0
       1: aload_1
       2: invokevirtual #9                  // Method namespaceRegex:(Ljava/util/List;)Lorg/apache/pulsar/common/policies/data/BrokerNamespaceIsolationDataImpl$BrokerNamespaceIsolationDataImplBuilder;
       5: areturn

  public org.apache.pulsar.common.policies.data.BrokerNamespaceIsolationData$Builder primary(boolean);
    Code:
       0: aload_0
       1: iload_1
       2: invokevirtual #10                 // Method primary:(Z)Lorg/apache/pulsar/common/policies/data/BrokerNamespaceIsolationDataImpl$BrokerNamespaceIsolationDataImplBuilder;
       5: areturn

  public org.apache.pulsar.common.policies.data.BrokerNamespaceIsolationData$Builder policyName(java.lang.String);
    Code:
       0: aload_0
       1: aload_1
       2: invokevirtual #11                 // Method policyName:(Ljava/lang/String;)Lorg/apache/pulsar/common/policies/data/BrokerNamespaceIsolationDataImpl$BrokerNamespaceIsolationDataImplBuilder;
       5: areturn

  public org.apache.pulsar.common.policies.data.BrokerNamespaceIsolationData$Builder brokerName(java.lang.String);
    Code:
       0: aload_0
       1: aload_1
       2: invokevirtual #12                 // Method brokerName:(Ljava/lang/String;)Lorg/apache/pulsar/common/policies/data/BrokerNamespaceIsolationDataImpl$BrokerNamespaceIsolationDataImplBuilder;
       5: areturn
}
