Compiled from "PolicyName.java"
public final class org.apache.pulsar.common.policies.data.PolicyName extends java.lang.Enum<org.apache.pulsar.common.policies.data.PolicyName> {
  public static final org.apache.pulsar.common.policies.data.PolicyName ALL;

  public static final org.apache.pulsar.common.policies.data.PolicyName ANTI_AFFINITY;

  public static final org.apache.pulsar.common.policies.data.PolicyName AUTO_SUBSCRIPTION_CREATION;

  public static final org.apache.pulsar.common.policies.data.PolicyName AUTO_TOPIC_CREATION;

  public static final org.apache.pulsar.common.policies.data.PolicyName BACKLOG;

  public static final org.apache.pulsar.common.policies.data.PolicyName COMPACTION;

  public static final org.apache.pulsar.common.policies.data.PolicyName DELAYED_DELIVERY;

  public static final org.apache.pulsar.common.policies.data.PolicyName INACTIVE_TOPIC;

  public static final org.apache.pulsar.common.policies.data.PolicyName DEDUPLICATION;

  public static final org.apache.pulsar.common.policies.data.PolicyName MAX_CONSUMERS;

  public static final org.apache.pulsar.common.policies.data.PolicyName MAX_PRODUCERS;

  public static final org.apache.pulsar.common.policies.data.PolicyName DEDUPLICATION_SNAPSHOT;

  public static final org.apache.pulsar.common.policies.data.PolicyName MAX_UNACKED;

  public static final org.apache.pulsar.common.policies.data.PolicyName MAX_SUBSCRIPTIONS;

  public static final org.apache.pulsar.common.policies.data.PolicyName OFFLOAD;

  public static final org.apache.pulsar.common.policies.data.PolicyName PARTITION;

  public static final org.apache.pulsar.common.policies.data.PolicyName PERSISTENCE;

  public static final org.apache.pulsar.common.policies.data.PolicyName RATE;

  public static final org.apache.pulsar.common.policies.data.PolicyName RETENTION;

  public static final org.apache.pulsar.common.policies.data.PolicyName REPLICATION;

  public static final org.apache.pulsar.common.policies.data.PolicyName REPLICATION_RATE;

  public static final org.apache.pulsar.common.policies.data.PolicyName SCHEMA_COMPATIBILITY_STRATEGY;

  public static final org.apache.pulsar.common.policies.data.PolicyName SUBSCRIPTION_AUTH_MODE;

  public static final org.apache.pulsar.common.policies.data.PolicyName SUBSCRIPTION_EXPIRATION_TIME;

  public static final org.apache.pulsar.common.policies.data.PolicyName ENCRYPTION;

  public static final org.apache.pulsar.common.policies.data.PolicyName TTL;

  public static final org.apache.pulsar.common.policies.data.PolicyName MAX_TOPICS;

  public static final org.apache.pulsar.common.policies.data.PolicyName RESOURCEGROUP;

  private static final org.apache.pulsar.common.policies.data.PolicyName[] $VALUES;

  public static org.apache.pulsar.common.policies.data.PolicyName[] values();
    Code:
       0: getstatic     #1                  // Field $VALUES:[Lorg/apache/pulsar/common/policies/data/PolicyName;
       3: invokevirtual #2                  // Method "[Lorg/apache/pulsar/common/policies/data/PolicyName;".clone:()Ljava/lang/Object;
       6: checkcast     #3                  // class "[Lorg/apache/pulsar/common/policies/data/PolicyName;"
       9: areturn

  public static org.apache.pulsar.common.policies.data.PolicyName valueOf(java.lang.String);
    Code:
       0: ldc           #4                  // class org/apache/pulsar/common/policies/data/PolicyName
       2: aload_0
       3: invokestatic  #5                  // Method java/lang/Enum.valueOf:(Ljava/lang/Class;Ljava/lang/String;)Ljava/lang/Enum;
       6: checkcast     #4                  // class org/apache/pulsar/common/policies/data/PolicyName
       9: areturn

  private org.apache.pulsar.common.policies.data.PolicyName();
    Code:
       0: aload_0
       1: aload_1
       2: iload_2
       3: invokespecial #6                  // Method java/lang/Enum."<init>":(Ljava/lang/String;I)V
       6: return

  static {};
    Code:
       0: new           #4                  // class org/apache/pulsar/common/policies/data/PolicyName
       3: dup
       4: ldc           #7                  // String ALL
       6: iconst_0
       7: invokespecial #8                  // Method "<init>":(Ljava/lang/String;I)V
      10: putstatic     #9                  // Field ALL:Lorg/apache/pulsar/common/policies/data/PolicyName;
      13: new           #4                  // class org/apache/pulsar/common/policies/data/PolicyName
      16: dup
      17: ldc           #10                 // String ANTI_AFFINITY
      19: iconst_1
      20: invokespecial #8                  // Method "<init>":(Ljava/lang/String;I)V
      23: putstatic     #11                 // Field ANTI_AFFINITY:Lorg/apache/pulsar/common/policies/data/PolicyName;
      26: new           #4                  // class org/apache/pulsar/common/policies/data/PolicyName
      29: dup
      30: ldc           #12                 // String AUTO_SUBSCRIPTION_CREATION
      32: iconst_2
      33: invokespecial #8                  // Method "<init>":(Ljava/lang/String;I)V
      36: putstatic     #13                 // Field AUTO_SUBSCRIPTION_CREATION:Lorg/apache/pulsar/common/policies/data/PolicyName;
      39: new           #4                  // class org/apache/pulsar/common/policies/data/PolicyName
      42: dup
      43: ldc           #14                 // String AUTO_TOPIC_CREATION
      45: iconst_3
      46: invokespecial #8                  // Method "<init>":(Ljava/lang/String;I)V
      49: putstatic     #15                 // Field AUTO_TOPIC_CREATION:Lorg/apache/pulsar/common/policies/data/PolicyName;
      52: new           #4                  // class org/apache/pulsar/common/policies/data/PolicyName
      55: dup
      56: ldc           #16                 // String BACKLOG
      58: iconst_4
      59: invokespecial #8                  // Method "<init>":(Ljava/lang/String;I)V
      62: putstatic     #17                 // Field BACKLOG:Lorg/apache/pulsar/common/policies/data/PolicyName;
      65: new           #4                  // class org/apache/pulsar/common/policies/data/PolicyName
      68: dup
      69: ldc           #18                 // String COMPACTION
      71: iconst_5
      72: invokespecial #8                  // Method "<init>":(Ljava/lang/String;I)V
      75: putstatic     #19                 // Field COMPACTION:Lorg/apache/pulsar/common/policies/data/PolicyName;
      78: new           #4                  // class org/apache/pulsar/common/policies/data/PolicyName
      81: dup
      82: ldc           #20                 // String DELAYED_DELIVERY
      84: bipush        6
      86: invokespecial #8                  // Method "<init>":(Ljava/lang/String;I)V
      89: putstatic     #21                 // Field DELAYED_DELIVERY:Lorg/apache/pulsar/common/policies/data/PolicyName;
      92: new           #4                  // class org/apache/pulsar/common/policies/data/PolicyName
      95: dup
      96: ldc           #22                 // String INACTIVE_TOPIC
      98: bipush        7
     100: invokespecial #8                  // Method "<init>":(Ljava/lang/String;I)V
     103: putstatic     #23                 // Field INACTIVE_TOPIC:Lorg/apache/pulsar/common/policies/data/PolicyName;
     106: new           #4                  // class org/apache/pulsar/common/policies/data/PolicyName
     109: dup
     110: ldc           #24                 // String DEDUPLICATION
     112: bipush        8
     114: invokespecial #8                  // Method "<init>":(Ljava/lang/String;I)V
     117: putstatic     #25                 // Field DEDUPLICATION:Lorg/apache/pulsar/common/policies/data/PolicyName;
     120: new           #4                  // class org/apache/pulsar/common/policies/data/PolicyName
     123: dup
     124: ldc           #26                 // String MAX_CONSUMERS
     126: bipush        9
     128: invokespecial #8                  // Method "<init>":(Ljava/lang/String;I)V
     131: putstatic     #27                 // Field MAX_CONSUMERS:Lorg/apache/pulsar/common/policies/data/PolicyName;
     134: new           #4                  // class org/apache/pulsar/common/policies/data/PolicyName
     137: dup
     138: ldc           #28                 // String MAX_PRODUCERS
     140: bipush        10
     142: invokespecial #8                  // Method "<init>":(Ljava/lang/String;I)V
     145: putstatic     #29                 // Field MAX_PRODUCERS:Lorg/apache/pulsar/common/policies/data/PolicyName;
     148: new           #4                  // class org/apache/pulsar/common/policies/data/PolicyName
     151: dup
     152: ldc           #30                 // String DEDUPLICATION_SNAPSHOT
     154: bipush        11
     156: invokespecial #8                  // Method "<init>":(Ljava/lang/String;I)V
     159: putstatic     #31                 // Field DEDUPLICATION_SNAPSHOT:Lorg/apache/pulsar/common/policies/data/PolicyName;
     162: new           #4                  // class org/apache/pulsar/common/policies/data/PolicyName
     165: dup
     166: ldc           #32                 // String MAX_UNACKED
     168: bipush        12
     170: invokespecial #8                  // Method "<init>":(Ljava/lang/String;I)V
     173: putstatic     #33                 // Field MAX_UNACKED:Lorg/apache/pulsar/common/policies/data/PolicyName;
     176: new           #4                  // class org/apache/pulsar/common/policies/data/PolicyName
     179: dup
     180: ldc           #34                 // String MAX_SUBSCRIPTIONS
     182: bipush        13
     184: invokespecial #8                  // Method "<init>":(Ljava/lang/String;I)V
     187: putstatic     #35                 // Field MAX_SUBSCRIPTIONS:Lorg/apache/pulsar/common/policies/data/PolicyName;
     190: new           #4                  // class org/apache/pulsar/common/policies/data/PolicyName
     193: dup
     194: ldc           #36                 // String OFFLOAD
     196: bipush        14
     198: invokespecial #8                  // Method "<init>":(Ljava/lang/String;I)V
     201: putstatic     #37                 // Field OFFLOAD:Lorg/apache/pulsar/common/policies/data/PolicyName;
     204: new           #4                  // class org/apache/pulsar/common/policies/data/PolicyName
     207: dup
     208: ldc           #38                 // String PARTITION
     210: bipush        15
     212: invokespecial #8                  // Method "<init>":(Ljava/lang/String;I)V
     215: putstatic     #39                 // Field PARTITION:Lorg/apache/pulsar/common/policies/data/PolicyName;
     218: new           #4                  // class org/apache/pulsar/common/policies/data/PolicyName
     221: dup
     222: ldc           #40                 // String PERSISTENCE
     224: bipush        16
     226: invokespecial #8                  // Method "<init>":(Ljava/lang/String;I)V
     229: putstatic     #41                 // Field PERSISTENCE:Lorg/apache/pulsar/common/policies/data/PolicyName;
     232: new           #4                  // class org/apache/pulsar/common/policies/data/PolicyName
     235: dup
     236: ldc           #42                 // String RATE
     238: bipush        17
     240: invokespecial #8                  // Method "<init>":(Ljava/lang/String;I)V
     243: putstatic     #43                 // Field RATE:Lorg/apache/pulsar/common/policies/data/PolicyName;
     246: new           #4                  // class org/apache/pulsar/common/policies/data/PolicyName
     249: dup
     250: ldc           #44                 // String RETENTION
     252: bipush        18
     254: invokespecial #8                  // Method "<init>":(Ljava/lang/String;I)V
     257: putstatic     #45                 // Field RETENTION:Lorg/apache/pulsar/common/policies/data/PolicyName;
     260: new           #4                  // class org/apache/pulsar/common/policies/data/PolicyName
     263: dup
     264: ldc           #46                 // String REPLICATION
     266: bipush        19
     268: invokespecial #8                  // Method "<init>":(Ljava/lang/String;I)V
     271: putstatic     #47                 // Field REPLICATION:Lorg/apache/pulsar/common/policies/data/PolicyName;
     274: new           #4                  // class org/apache/pulsar/common/policies/data/PolicyName
     277: dup
     278: ldc           #48                 // String REPLICATION_RATE
     280: bipush        20
     282: invokespecial #8                  // Method "<init>":(Ljava/lang/String;I)V
     285: putstatic     #49                 // Field REPLICATION_RATE:Lorg/apache/pulsar/common/policies/data/PolicyName;
     288: new           #4                  // class org/apache/pulsar/common/policies/data/PolicyName
     291: dup
     292: ldc           #50                 // String SCHEMA_COMPATIBILITY_STRATEGY
     294: bipush        21
     296: invokespecial #8                  // Method "<init>":(Ljava/lang/String;I)V
     299: putstatic     #51                 // Field SCHEMA_COMPATIBILITY_STRATEGY:Lorg/apache/pulsar/common/policies/data/PolicyName;
     302: new           #4                  // class org/apache/pulsar/common/policies/data/PolicyName
     305: dup
     306: ldc           #52                 // String SUBSCRIPTION_AUTH_MODE
     308: bipush        22
     310: invokespecial #8                  // Method "<init>":(Ljava/lang/String;I)V
     313: putstatic     #53                 // Field SUBSCRIPTION_AUTH_MODE:Lorg/apache/pulsar/common/policies/data/PolicyName;
     316: new           #4                  // class org/apache/pulsar/common/policies/data/PolicyName
     319: dup
     320: ldc           #54                 // String SUBSCRIPTION_EXPIRATION_TIME
     322: bipush        23
     324: invokespecial #8                  // Method "<init>":(Ljava/lang/String;I)V
     327: putstatic     #55                 // Field SUBSCRIPTION_EXPIRATION_TIME:Lorg/apache/pulsar/common/policies/data/PolicyName;
     330: new           #4                  // class org/apache/pulsar/common/policies/data/PolicyName
     333: dup
     334: ldc           #56                 // String ENCRYPTION
     336: bipush        24
     338: invokespecial #8                  // Method "<init>":(Ljava/lang/String;I)V
     341: putstatic     #57                 // Field ENCRYPTION:Lorg/apache/pulsar/common/policies/data/PolicyName;
     344: new           #4                  // class org/apache/pulsar/common/policies/data/PolicyName
     347: dup
     348: ldc           #58                 // String TTL
     350: bipush        25
     352: invokespecial #8                  // Method "<init>":(Ljava/lang/String;I)V
     355: putstatic     #59                 // Field TTL:Lorg/apache/pulsar/common/policies/data/PolicyName;
     358: new           #4                  // class org/apache/pulsar/common/policies/data/PolicyName
     361: dup
     362: ldc           #60                 // String MAX_TOPICS
     364: bipush        26
     366: invokespecial #8                  // Method "<init>":(Ljava/lang/String;I)V
     369: putstatic     #61                 // Field MAX_TOPICS:Lorg/apache/pulsar/common/policies/data/PolicyName;
     372: new           #4                  // class org/apache/pulsar/common/policies/data/PolicyName
     375: dup
     376: ldc           #62                 // String RESOURCEGROUP
     378: bipush        27
     380: invokespecial #8                  // Method "<init>":(Ljava/lang/String;I)V
     383: putstatic     #63                 // Field RESOURCEGROUP:Lorg/apache/pulsar/common/policies/data/PolicyName;
     386: bipush        28
     388: anewarray     #4                  // class org/apache/pulsar/common/policies/data/PolicyName
     391: dup
     392: iconst_0
     393: getstatic     #9                  // Field ALL:Lorg/apache/pulsar/common/policies/data/PolicyName;
     396: aastore
     397: dup
     398: iconst_1
     399: getstatic     #11                 // Field ANTI_AFFINITY:Lorg/apache/pulsar/common/policies/data/PolicyName;
     402: aastore
     403: dup
     404: iconst_2
     405: getstatic     #13                 // Field AUTO_SUBSCRIPTION_CREATION:Lorg/apache/pulsar/common/policies/data/PolicyName;
     408: aastore
     409: dup
     410: iconst_3
     411: getstatic     #15                 // Field AUTO_TOPIC_CREATION:Lorg/apache/pulsar/common/policies/data/PolicyName;
     414: aastore
     415: dup
     416: iconst_4
     417: getstatic     #17                 // Field BACKLOG:Lorg/apache/pulsar/common/policies/data/PolicyName;
     420: aastore
     421: dup
     422: iconst_5
     423: getstatic     #19                 // Field COMPACTION:Lorg/apache/pulsar/common/policies/data/PolicyName;
     426: aastore
     427: dup
     428: bipush        6
     430: getstatic     #21                 // Field DELAYED_DELIVERY:Lorg/apache/pulsar/common/policies/data/PolicyName;
     433: aastore
     434: dup
     435: bipush        7
     437: getstatic     #23                 // Field INACTIVE_TOPIC:Lorg/apache/pulsar/common/policies/data/PolicyName;
     440: aastore
     441: dup
     442: bipush        8
     444: getstatic     #25                 // Field DEDUPLICATION:Lorg/apache/pulsar/common/policies/data/PolicyName;
     447: aastore
     448: dup
     449: bipush        9
     451: getstatic     #27                 // Field MAX_CONSUMERS:Lorg/apache/pulsar/common/policies/data/PolicyName;
     454: aastore
     455: dup
     456: bipush        10
     458: getstatic     #29                 // Field MAX_PRODUCERS:Lorg/apache/pulsar/common/policies/data/PolicyName;
     461: aastore
     462: dup
     463: bipush        11
     465: getstatic     #31                 // Field DEDUPLICATION_SNAPSHOT:Lorg/apache/pulsar/common/policies/data/PolicyName;
     468: aastore
     469: dup
     470: bipush        12
     472: getstatic     #33                 // Field MAX_UNACKED:Lorg/apache/pulsar/common/policies/data/PolicyName;
     475: aastore
     476: dup
     477: bipush        13
     479: getstatic     #35                 // Field MAX_SUBSCRIPTIONS:Lorg/apache/pulsar/common/policies/data/PolicyName;
     482: aastore
     483: dup
     484: bipush        14
     486: getstatic     #37                 // Field OFFLOAD:Lorg/apache/pulsar/common/policies/data/PolicyName;
     489: aastore
     490: dup
     491: bipush        15
     493: getstatic     #39                 // Field PARTITION:Lorg/apache/pulsar/common/policies/data/PolicyName;
     496: aastore
     497: dup
     498: bipush        16
     500: getstatic     #41                 // Field PERSISTENCE:Lorg/apache/pulsar/common/policies/data/PolicyName;
     503: aastore
     504: dup
     505: bipush        17
     507: getstatic     #43                 // Field RATE:Lorg/apache/pulsar/common/policies/data/PolicyName;
     510: aastore
     511: dup
     512: bipush        18
     514: getstatic     #45                 // Field RETENTION:Lorg/apache/pulsar/common/policies/data/PolicyName;
     517: aastore
     518: dup
     519: bipush        19
     521: getstatic     #47                 // Field REPLICATION:Lorg/apache/pulsar/common/policies/data/PolicyName;
     524: aastore
     525: dup
     526: bipush        20
     528: getstatic     #49                 // Field REPLICATION_RATE:Lorg/apache/pulsar/common/policies/data/PolicyName;
     531: aastore
     532: dup
     533: bipush        21
     535: getstatic     #51                 // Field SCHEMA_COMPATIBILITY_STRATEGY:Lorg/apache/pulsar/common/policies/data/PolicyName;
     538: aastore
     539: dup
     540: bipush        22
     542: getstatic     #53                 // Field SUBSCRIPTION_AUTH_MODE:Lorg/apache/pulsar/common/policies/data/PolicyName;
     545: aastore
     546: dup
     547: bipush        23
     549: getstatic     #55                 // Field SUBSCRIPTION_EXPIRATION_TIME:Lorg/apache/pulsar/common/policies/data/PolicyName;
     552: aastore
     553: dup
     554: bipush        24
     556: getstatic     #57                 // Field ENCRYPTION:Lorg/apache/pulsar/common/policies/data/PolicyName;
     559: aastore
     560: dup
     561: bipush        25
     563: getstatic     #59                 // Field TTL:Lorg/apache/pulsar/common/policies/data/PolicyName;
     566: aastore
     567: dup
     568: bipush        26
     570: getstatic     #61                 // Field MAX_TOPICS:Lorg/apache/pulsar/common/policies/data/PolicyName;
     573: aastore
     574: dup
     575: bipush        27
     577: getstatic     #63                 // Field RESOURCEGROUP:Lorg/apache/pulsar/common/policies/data/PolicyName;
     580: aastore
     581: putstatic     #1                  // Field $VALUES:[Lorg/apache/pulsar/common/policies/data/PolicyName;
     584: return
}
