Compiled from "ObjectDataType.java"
class org.h2.mvstore.type.ObjectDataType$LongType extends org.h2.mvstore.type.ObjectDataType$AutoDetectDataType {
  org.h2.mvstore.type.ObjectDataType$LongType(org.h2.mvstore.type.ObjectDataType);
    Code:
       0: aload_0
       1: aload_1
       2: iconst_5
       3: invokespecial #1                  // Method org/h2/mvstore/type/ObjectDataType$AutoDetectDataType."<init>":(Lorg/h2/mvstore/type/ObjectDataType;I)V
       6: return

  public int compare(java.lang.Object, java.lang.Object);
    Code:
       0: aload_1
       1: instanceof    #2                  // class java/lang/Long
       4: ifeq          32
       7: aload_2
       8: instanceof    #2                  // class java/lang/Long
      11: ifeq          32
      14: aload_1
      15: checkcast     #2                  // class java/lang/Long
      18: astore_3
      19: aload_2
      20: checkcast     #2                  // class java/lang/Long
      23: astore        4
      25: aload_3
      26: aload         4
      28: invokevirtual #3                  // Method java/lang/Long.compareTo:(Ljava/lang/Long;)I
      31: ireturn
      32: aload_0
      33: aload_1
      34: aload_2
      35: invokespecial #4                  // Method org/h2/mvstore/type/ObjectDataType$AutoDetectDataType.compare:(Ljava/lang/Object;Ljava/lang/Object;)I
      38: ireturn

  public int getMemory(java.lang.Object);
    Code:
       0: aload_1
       1: instanceof    #2                  // class java/lang/Long
       4: ifeq          12
       7: bipush        30
       9: goto          17
      12: aload_0
      13: aload_1
      14: invokespecial #5                  // Method org/h2/mvstore/type/ObjectDataType$AutoDetectDataType.getMemory:(Ljava/lang/Object;)I
      17: ireturn

  public void write(org.h2.mvstore.WriteBuffer, java.lang.Object);
    Code:
       0: aload_2
       1: instanceof    #2                  // class java/lang/Long
       4: ifne          14
       7: aload_0
       8: aload_1
       9: aload_2
      10: invokespecial #6                  // Method org/h2/mvstore/type/ObjectDataType$AutoDetectDataType.write:(Lorg/h2/mvstore/WriteBuffer;Ljava/lang/Object;)V
      13: return
      14: aload_2
      15: checkcast     #2                  // class java/lang/Long
      18: invokevirtual #7                  // Method java/lang/Long.longValue:()J
      21: lstore_3
      22: lload_3
      23: lconst_0
      24: lcmp
      25: ifge          77
      28: lload_3
      29: lneg
      30: lconst_0
      31: lcmp
      32: iflt          44
      35: lload_3
      36: lneg
      37: ldc2_w        #8                  // long 562949953421311l
      40: lcmp
      41: ifle          60
      44: aload_1
      45: bipush        36
      47: invokevirtual #10                 // Method org/h2/mvstore/WriteBuffer.put:(B)Lorg/h2/mvstore/WriteBuffer;
      50: pop
      51: aload_1
      52: lload_3
      53: invokevirtual #11                 // Method org/h2/mvstore/WriteBuffer.putLong:(J)Lorg/h2/mvstore/WriteBuffer;
      56: pop
      57: goto          136
      60: aload_1
      61: bipush        35
      63: invokevirtual #10                 // Method org/h2/mvstore/WriteBuffer.put:(B)Lorg/h2/mvstore/WriteBuffer;
      66: pop
      67: aload_1
      68: lload_3
      69: lneg
      70: invokevirtual #12                 // Method org/h2/mvstore/WriteBuffer.putVarLong:(J)Lorg/h2/mvstore/WriteBuffer;
      73: pop
      74: goto          136
      77: lload_3
      78: ldc2_w        #13                 // long 7l
      81: lcmp
      82: ifgt          100
      85: aload_1
      86: ldc2_w        #15                 // long 80l
      89: lload_3
      90: ladd
      91: l2i
      92: i2b
      93: invokevirtual #10                 // Method org/h2/mvstore/WriteBuffer.put:(B)Lorg/h2/mvstore/WriteBuffer;
      96: pop
      97: goto          136
     100: lload_3
     101: ldc2_w        #8                  // long 562949953421311l
     104: lcmp
     105: ifgt          123
     108: aload_1
     109: iconst_5
     110: invokevirtual #10                 // Method org/h2/mvstore/WriteBuffer.put:(B)Lorg/h2/mvstore/WriteBuffer;
     113: pop
     114: aload_1
     115: lload_3
     116: invokevirtual #12                 // Method org/h2/mvstore/WriteBuffer.putVarLong:(J)Lorg/h2/mvstore/WriteBuffer;
     119: pop
     120: goto          136
     123: aload_1
     124: bipush        36
     126: invokevirtual #10                 // Method org/h2/mvstore/WriteBuffer.put:(B)Lorg/h2/mvstore/WriteBuffer;
     129: pop
     130: aload_1
     131: lload_3
     132: invokevirtual #11                 // Method org/h2/mvstore/WriteBuffer.putLong:(J)Lorg/h2/mvstore/WriteBuffer;
     135: pop
     136: return

  public java.lang.Object read(java.nio.ByteBuffer, int);
    Code:
       0: iload_2
       1: lookupswitch  { // 3
                     5: 36
                    35: 44
                    36: 53
               default: 61
          }
      36: aload_1
      37: invokestatic  #17                 // Method org/h2/mvstore/DataUtils.readVarLong:(Ljava/nio/ByteBuffer;)J
      40: invokestatic  #18                 // Method java/lang/Long.valueOf:(J)Ljava/lang/Long;
      43: areturn
      44: aload_1
      45: invokestatic  #17                 // Method org/h2/mvstore/DataUtils.readVarLong:(Ljava/nio/ByteBuffer;)J
      48: lneg
      49: invokestatic  #18                 // Method java/lang/Long.valueOf:(J)Ljava/lang/Long;
      52: areturn
      53: aload_1
      54: invokevirtual #19                 // Method java/nio/ByteBuffer.getLong:()J
      57: invokestatic  #18                 // Method java/lang/Long.valueOf:(J)Ljava/lang/Long;
      60: areturn
      61: iload_2
      62: bipush        80
      64: isub
      65: i2l
      66: invokestatic  #18                 // Method java/lang/Long.valueOf:(J)Ljava/lang/Long;
      69: areturn
}
