Compiled from "JPAUserTransactionListener.java"
public class org.jboss.as.jpa.container.JPAUserTransactionListener implements org.jboss.tm.usertx.UserTransactionListener {
  public org.jboss.as.jpa.container.JPAUserTransactionListener();
    Code:
       0: aload_0
       1: invokespecial #1                  // Method java/lang/Object."<init>":()V
       4: return

  public void userTransactionStarted() throws javax.transaction.SystemException;
    Code:
       0: invokestatic  #2                  // Method org/jboss/as/jpa/container/SFSBCallStack.currentSFSBCallStackInvocation:()Ljava/util/Map;
       3: astore_1
       4: aload_1
       5: ifnull        55
       8: aload_1
       9: invokeinterface #3,  1            // InterfaceMethod java/util/Map.size:()I
      14: ifle          55
      17: aload_1
      18: invokeinterface #4,  1            // InterfaceMethod java/util/Map.values:()Ljava/util/Collection;
      23: invokeinterface #5,  1            // InterfaceMethod java/util/Collection.iterator:()Ljava/util/Iterator;
      28: astore_2
      29: aload_2
      30: invokeinterface #6,  1            // InterfaceMethod java/util/Iterator.hasNext:()Z
      35: ifeq          55
      38: aload_2
      39: invokeinterface #7,  1            // InterfaceMethod java/util/Iterator.next:()Ljava/lang/Object;
      44: checkcast     #8                  // class org/jboss/as/jpa/container/ExtendedEntityManager
      47: astore_3
      48: aload_3
      49: invokevirtual #9                  // Method org/jboss/as/jpa/container/ExtendedEntityManager.internalAssociateWithJtaTx:()V
      52: goto          29
      55: return
}
