Compiled from "M2AsyncClient.java"
public interface software.amazon.awssdk.services.m2.M2AsyncClient extends software.amazon.awssdk.awscore.AwsClient {
  public static final java.lang.String SERVICE_NAME;

  public static final java.lang.String SERVICE_METADATA_ID;

  public default java.util.concurrent.CompletableFuture<software.amazon.awssdk.services.m2.model.CancelBatchJobExecutionResponse> cancelBatchJobExecution(software.amazon.awssdk.services.m2.model.CancelBatchJobExecutionRequest);
    Code:
       0: new           #1                  // class java/lang/UnsupportedOperationException
       3: dup
       4: invokespecial #2                  // Method java/lang/UnsupportedOperationException."<init>":()V
       7: athrow

  public default java.util.concurrent.CompletableFuture<software.amazon.awssdk.services.m2.model.CancelBatchJobExecutionResponse> cancelBatchJobExecution(java.util.function.Consumer<software.amazon.awssdk.services.m2.model.CancelBatchJobExecutionRequest$Builder>);
    Code:
       0: aload_0
       1: invokestatic  #3                  // Method software/amazon/awssdk/services/m2/model/CancelBatchJobExecutionRequest.builder:()Lsoftware/amazon/awssdk/services/m2/model/CancelBatchJobExecutionRequest$Builder;
       4: aload_1
       5: invokeinterface #4,  2            // InterfaceMethod software/amazon/awssdk/services/m2/model/CancelBatchJobExecutionRequest$Builder.applyMutation:(Ljava/util/function/Consumer;)Lsoftware/amazon/awssdk/utils/builder/SdkBuilder;
      10: checkcast     #5                  // class software/amazon/awssdk/services/m2/model/CancelBatchJobExecutionRequest$Builder
      13: invokeinterface #6,  1            // InterfaceMethod software/amazon/awssdk/services/m2/model/CancelBatchJobExecutionRequest$Builder.build:()Ljava/lang/Object;
      18: checkcast     #7                  // class software/amazon/awssdk/services/m2/model/CancelBatchJobExecutionRequest
      21: invokeinterface #8,  2            // InterfaceMethod cancelBatchJobExecution:(Lsoftware/amazon/awssdk/services/m2/model/CancelBatchJobExecutionRequest;)Ljava/util/concurrent/CompletableFuture;
      26: areturn

  public default java.util.concurrent.CompletableFuture<software.amazon.awssdk.services.m2.model.CreateApplicationResponse> createApplication(software.amazon.awssdk.services.m2.model.CreateApplicationRequest);
    Code:
       0: new           #1                  // class java/lang/UnsupportedOperationException
       3: dup
       4: invokespecial #2                  // Method java/lang/UnsupportedOperationException."<init>":()V
       7: athrow

  public default java.util.concurrent.CompletableFuture<software.amazon.awssdk.services.m2.model.CreateApplicationResponse> createApplication(java.util.function.Consumer<software.amazon.awssdk.services.m2.model.CreateApplicationRequest$Builder>);
    Code:
       0: aload_0
       1: invokestatic  #9                  // Method software/amazon/awssdk/services/m2/model/CreateApplicationRequest.builder:()Lsoftware/amazon/awssdk/services/m2/model/CreateApplicationRequest$Builder;
       4: aload_1
       5: invokeinterface #10,  2           // InterfaceMethod software/amazon/awssdk/services/m2/model/CreateApplicationRequest$Builder.applyMutation:(Ljava/util/function/Consumer;)Lsoftware/amazon/awssdk/utils/builder/SdkBuilder;
      10: checkcast     #11                 // class software/amazon/awssdk/services/m2/model/CreateApplicationRequest$Builder
      13: invokeinterface #12,  1           // InterfaceMethod software/amazon/awssdk/services/m2/model/CreateApplicationRequest$Builder.build:()Ljava/lang/Object;
      18: checkcast     #13                 // class software/amazon/awssdk/services/m2/model/CreateApplicationRequest
      21: invokeinterface #14,  2           // InterfaceMethod createApplication:(Lsoftware/amazon/awssdk/services/m2/model/CreateApplicationRequest;)Ljava/util/concurrent/CompletableFuture;
      26: areturn

  public default java.util.concurrent.CompletableFuture<software.amazon.awssdk.services.m2.model.CreateDataSetImportTaskResponse> createDataSetImportTask(software.amazon.awssdk.services.m2.model.CreateDataSetImportTaskRequest);
    Code:
       0: new           #1                  // class java/lang/UnsupportedOperationException
       3: dup
       4: invokespecial #2                  // Method java/lang/UnsupportedOperationException."<init>":()V
       7: athrow

  public default java.util.concurrent.CompletableFuture<software.amazon.awssdk.services.m2.model.CreateDataSetImportTaskResponse> createDataSetImportTask(java.util.function.Consumer<software.amazon.awssdk.services.m2.model.CreateDataSetImportTaskRequest$Builder>);
    Code:
       0: aload_0
       1: invokestatic  #15                 // Method software/amazon/awssdk/services/m2/model/CreateDataSetImportTaskRequest.builder:()Lsoftware/amazon/awssdk/services/m2/model/CreateDataSetImportTaskRequest$Builder;
       4: aload_1
       5: invokeinterface #16,  2           // InterfaceMethod software/amazon/awssdk/services/m2/model/CreateDataSetImportTaskRequest$Builder.applyMutation:(Ljava/util/function/Consumer;)Lsoftware/amazon/awssdk/utils/builder/SdkBuilder;
      10: checkcast     #17                 // class software/amazon/awssdk/services/m2/model/CreateDataSetImportTaskRequest$Builder
      13: invokeinterface #18,  1           // InterfaceMethod software/amazon/awssdk/services/m2/model/CreateDataSetImportTaskRequest$Builder.build:()Ljava/lang/Object;
      18: checkcast     #19                 // class software/amazon/awssdk/services/m2/model/CreateDataSetImportTaskRequest
      21: invokeinterface #20,  2           // InterfaceMethod createDataSetImportTask:(Lsoftware/amazon/awssdk/services/m2/model/CreateDataSetImportTaskRequest;)Ljava/util/concurrent/CompletableFuture;
      26: areturn

  public default java.util.concurrent.CompletableFuture<software.amazon.awssdk.services.m2.model.CreateDeploymentResponse> createDeployment(software.amazon.awssdk.services.m2.model.CreateDeploymentRequest);
    Code:
       0: new           #1                  // class java/lang/UnsupportedOperationException
       3: dup
       4: invokespecial #2                  // Method java/lang/UnsupportedOperationException."<init>":()V
       7: athrow

  public default java.util.concurrent.CompletableFuture<software.amazon.awssdk.services.m2.model.CreateDeploymentResponse> createDeployment(java.util.function.Consumer<software.amazon.awssdk.services.m2.model.CreateDeploymentRequest$Builder>);
    Code:
       0: aload_0
       1: invokestatic  #21                 // Method software/amazon/awssdk/services/m2/model/CreateDeploymentRequest.builder:()Lsoftware/amazon/awssdk/services/m2/model/CreateDeploymentRequest$Builder;
       4: aload_1
       5: invokeinterface #22,  2           // InterfaceMethod software/amazon/awssdk/services/m2/model/CreateDeploymentRequest$Builder.applyMutation:(Ljava/util/function/Consumer;)Lsoftware/amazon/awssdk/utils/builder/SdkBuilder;
      10: checkcast     #23                 // class software/amazon/awssdk/services/m2/model/CreateDeploymentRequest$Builder
      13: invokeinterface #24,  1           // InterfaceMethod software/amazon/awssdk/services/m2/model/CreateDeploymentRequest$Builder.build:()Ljava/lang/Object;
      18: checkcast     #25                 // class software/amazon/awssdk/services/m2/model/CreateDeploymentRequest
      21: invokeinterface #26,  2           // InterfaceMethod createDeployment:(Lsoftware/amazon/awssdk/services/m2/model/CreateDeploymentRequest;)Ljava/util/concurrent/CompletableFuture;
      26: areturn

  public default java.util.concurrent.CompletableFuture<software.amazon.awssdk.services.m2.model.CreateEnvironmentResponse> createEnvironment(software.amazon.awssdk.services.m2.model.CreateEnvironmentRequest);
    Code:
       0: new           #1                  // class java/lang/UnsupportedOperationException
       3: dup
       4: invokespecial #2                  // Method java/lang/UnsupportedOperationException."<init>":()V
       7: athrow

  public default java.util.concurrent.CompletableFuture<software.amazon.awssdk.services.m2.model.CreateEnvironmentResponse> createEnvironment(java.util.function.Consumer<software.amazon.awssdk.services.m2.model.CreateEnvironmentRequest$Builder>);
    Code:
       0: aload_0
       1: invokestatic  #27                 // Method software/amazon/awssdk/services/m2/model/CreateEnvironmentRequest.builder:()Lsoftware/amazon/awssdk/services/m2/model/CreateEnvironmentRequest$Builder;
       4: aload_1
       5: invokeinterface #28,  2           // InterfaceMethod software/amazon/awssdk/services/m2/model/CreateEnvironmentRequest$Builder.applyMutation:(Ljava/util/function/Consumer;)Lsoftware/amazon/awssdk/utils/builder/SdkBuilder;
      10: checkcast     #29                 // class software/amazon/awssdk/services/m2/model/CreateEnvironmentRequest$Builder
      13: invokeinterface #30,  1           // InterfaceMethod software/amazon/awssdk/services/m2/model/CreateEnvironmentRequest$Builder.build:()Ljava/lang/Object;
      18: checkcast     #31                 // class software/amazon/awssdk/services/m2/model/CreateEnvironmentRequest
      21: invokeinterface #32,  2           // InterfaceMethod createEnvironment:(Lsoftware/amazon/awssdk/services/m2/model/CreateEnvironmentRequest;)Ljava/util/concurrent/CompletableFuture;
      26: areturn

  public default java.util.concurrent.CompletableFuture<software.amazon.awssdk.services.m2.model.DeleteApplicationResponse> deleteApplication(software.amazon.awssdk.services.m2.model.DeleteApplicationRequest);
    Code:
       0: new           #1                  // class java/lang/UnsupportedOperationException
       3: dup
       4: invokespecial #2                  // Method java/lang/UnsupportedOperationException."<init>":()V
       7: athrow

  public default java.util.concurrent.CompletableFuture<software.amazon.awssdk.services.m2.model.DeleteApplicationResponse> deleteApplication(java.util.function.Consumer<software.amazon.awssdk.services.m2.model.DeleteApplicationRequest$Builder>);
    Code:
       0: aload_0
       1: invokestatic  #33                 // Method software/amazon/awssdk/services/m2/model/DeleteApplicationRequest.builder:()Lsoftware/amazon/awssdk/services/m2/model/DeleteApplicationRequest$Builder;
       4: aload_1
       5: invokeinterface #34,  2           // InterfaceMethod software/amazon/awssdk/services/m2/model/DeleteApplicationRequest$Builder.applyMutation:(Ljava/util/function/Consumer;)Lsoftware/amazon/awssdk/utils/builder/SdkBuilder;
      10: checkcast     #35                 // class software/amazon/awssdk/services/m2/model/DeleteApplicationRequest$Builder
      13: invokeinterface #36,  1           // InterfaceMethod software/amazon/awssdk/services/m2/model/DeleteApplicationRequest$Builder.build:()Ljava/lang/Object;
      18: checkcast     #37                 // class software/amazon/awssdk/services/m2/model/DeleteApplicationRequest
      21: invokeinterface #38,  2           // InterfaceMethod deleteApplication:(Lsoftware/amazon/awssdk/services/m2/model/DeleteApplicationRequest;)Ljava/util/concurrent/CompletableFuture;
      26: areturn

  public default java.util.concurrent.CompletableFuture<software.amazon.awssdk.services.m2.model.DeleteApplicationFromEnvironmentResponse> deleteApplicationFromEnvironment(software.amazon.awssdk.services.m2.model.DeleteApplicationFromEnvironmentRequest);
    Code:
       0: new           #1                  // class java/lang/UnsupportedOperationException
       3: dup
       4: invokespecial #2                  // Method java/lang/UnsupportedOperationException."<init>":()V
       7: athrow

  public default java.util.concurrent.CompletableFuture<software.amazon.awssdk.services.m2.model.DeleteApplicationFromEnvironmentResponse> deleteApplicationFromEnvironment(java.util.function.Consumer<software.amazon.awssdk.services.m2.model.DeleteApplicationFromEnvironmentRequest$Builder>);
    Code:
       0: aload_0
       1: invokestatic  #39                 // Method software/amazon/awssdk/services/m2/model/DeleteApplicationFromEnvironmentRequest.builder:()Lsoftware/amazon/awssdk/services/m2/model/DeleteApplicationFromEnvironmentRequest$Builder;
       4: aload_1
       5: invokeinterface #40,  2           // InterfaceMethod software/amazon/awssdk/services/m2/model/DeleteApplicationFromEnvironmentRequest$Builder.applyMutation:(Ljava/util/function/Consumer;)Lsoftware/amazon/awssdk/utils/builder/SdkBuilder;
      10: checkcast     #41                 // class software/amazon/awssdk/services/m2/model/DeleteApplicationFromEnvironmentRequest$Builder
      13: invokeinterface #42,  1           // InterfaceMethod software/amazon/awssdk/services/m2/model/DeleteApplicationFromEnvironmentRequest$Builder.build:()Ljava/lang/Object;
      18: checkcast     #43                 // class software/amazon/awssdk/services/m2/model/DeleteApplicationFromEnvironmentRequest
      21: invokeinterface #44,  2           // InterfaceMethod deleteApplicationFromEnvironment:(Lsoftware/amazon/awssdk/services/m2/model/DeleteApplicationFromEnvironmentRequest;)Ljava/util/concurrent/CompletableFuture;
      26: areturn

  public default java.util.concurrent.CompletableFuture<software.amazon.awssdk.services.m2.model.DeleteEnvironmentResponse> deleteEnvironment(software.amazon.awssdk.services.m2.model.DeleteEnvironmentRequest);
    Code:
       0: new           #1                  // class java/lang/UnsupportedOperationException
       3: dup
       4: invokespecial #2                  // Method java/lang/UnsupportedOperationException."<init>":()V
       7: athrow

  public default java.util.concurrent.CompletableFuture<software.amazon.awssdk.services.m2.model.DeleteEnvironmentResponse> deleteEnvironment(java.util.function.Consumer<software.amazon.awssdk.services.m2.model.DeleteEnvironmentRequest$Builder>);
    Code:
       0: aload_0
       1: invokestatic  #45                 // Method software/amazon/awssdk/services/m2/model/DeleteEnvironmentRequest.builder:()Lsoftware/amazon/awssdk/services/m2/model/DeleteEnvironmentRequest$Builder;
       4: aload_1
       5: invokeinterface #46,  2           // InterfaceMethod software/amazon/awssdk/services/m2/model/DeleteEnvironmentRequest$Builder.applyMutation:(Ljava/util/function/Consumer;)Lsoftware/amazon/awssdk/utils/builder/SdkBuilder;
      10: checkcast     #47                 // class software/amazon/awssdk/services/m2/model/DeleteEnvironmentRequest$Builder
      13: invokeinterface #48,  1           // InterfaceMethod software/amazon/awssdk/services/m2/model/DeleteEnvironmentRequest$Builder.build:()Ljava/lang/Object;
      18: checkcast     #49                 // class software/amazon/awssdk/services/m2/model/DeleteEnvironmentRequest
      21: invokeinterface #50,  2           // InterfaceMethod deleteEnvironment:(Lsoftware/amazon/awssdk/services/m2/model/DeleteEnvironmentRequest;)Ljava/util/concurrent/CompletableFuture;
      26: areturn

  public default java.util.concurrent.CompletableFuture<software.amazon.awssdk.services.m2.model.GetApplicationResponse> getApplication(software.amazon.awssdk.services.m2.model.GetApplicationRequest);
    Code:
       0: new           #1                  // class java/lang/UnsupportedOperationException
       3: dup
       4: invokespecial #2                  // Method java/lang/UnsupportedOperationException."<init>":()V
       7: athrow

  public default java.util.concurrent.CompletableFuture<software.amazon.awssdk.services.m2.model.GetApplicationResponse> getApplication(java.util.function.Consumer<software.amazon.awssdk.services.m2.model.GetApplicationRequest$Builder>);
    Code:
       0: aload_0
       1: invokestatic  #51                 // Method software/amazon/awssdk/services/m2/model/GetApplicationRequest.builder:()Lsoftware/amazon/awssdk/services/m2/model/GetApplicationRequest$Builder;
       4: aload_1
       5: invokeinterface #52,  2           // InterfaceMethod software/amazon/awssdk/services/m2/model/GetApplicationRequest$Builder.applyMutation:(Ljava/util/function/Consumer;)Lsoftware/amazon/awssdk/utils/builder/SdkBuilder;
      10: checkcast     #53                 // class software/amazon/awssdk/services/m2/model/GetApplicationRequest$Builder
      13: invokeinterface #54,  1           // InterfaceMethod software/amazon/awssdk/services/m2/model/GetApplicationRequest$Builder.build:()Ljava/lang/Object;
      18: checkcast     #55                 // class software/amazon/awssdk/services/m2/model/GetApplicationRequest
      21: invokeinterface #56,  2           // InterfaceMethod getApplication:(Lsoftware/amazon/awssdk/services/m2/model/GetApplicationRequest;)Ljava/util/concurrent/CompletableFuture;
      26: areturn

  public default java.util.concurrent.CompletableFuture<software.amazon.awssdk.services.m2.model.GetApplicationVersionResponse> getApplicationVersion(software.amazon.awssdk.services.m2.model.GetApplicationVersionRequest);
    Code:
       0: new           #1                  // class java/lang/UnsupportedOperationException
       3: dup
       4: invokespecial #2                  // Method java/lang/UnsupportedOperationException."<init>":()V
       7: athrow

  public default java.util.concurrent.CompletableFuture<software.amazon.awssdk.services.m2.model.GetApplicationVersionResponse> getApplicationVersion(java.util.function.Consumer<software.amazon.awssdk.services.m2.model.GetApplicationVersionRequest$Builder>);
    Code:
       0: aload_0
       1: invokestatic  #57                 // Method software/amazon/awssdk/services/m2/model/GetApplicationVersionRequest.builder:()Lsoftware/amazon/awssdk/services/m2/model/GetApplicationVersionRequest$Builder;
       4: aload_1
       5: invokeinterface #58,  2           // InterfaceMethod software/amazon/awssdk/services/m2/model/GetApplicationVersionRequest$Builder.applyMutation:(Ljava/util/function/Consumer;)Lsoftware/amazon/awssdk/utils/builder/SdkBuilder;
      10: checkcast     #59                 // class software/amazon/awssdk/services/m2/model/GetApplicationVersionRequest$Builder
      13: invokeinterface #60,  1           // InterfaceMethod software/amazon/awssdk/services/m2/model/GetApplicationVersionRequest$Builder.build:()Ljava/lang/Object;
      18: checkcast     #61                 // class software/amazon/awssdk/services/m2/model/GetApplicationVersionRequest
      21: invokeinterface #62,  2           // InterfaceMethod getApplicationVersion:(Lsoftware/amazon/awssdk/services/m2/model/GetApplicationVersionRequest;)Ljava/util/concurrent/CompletableFuture;
      26: areturn

  public default java.util.concurrent.CompletableFuture<software.amazon.awssdk.services.m2.model.GetBatchJobExecutionResponse> getBatchJobExecution(software.amazon.awssdk.services.m2.model.GetBatchJobExecutionRequest);
    Code:
       0: new           #1                  // class java/lang/UnsupportedOperationException
       3: dup
       4: invokespecial #2                  // Method java/lang/UnsupportedOperationException."<init>":()V
       7: athrow

  public default java.util.concurrent.CompletableFuture<software.amazon.awssdk.services.m2.model.GetBatchJobExecutionResponse> getBatchJobExecution(java.util.function.Consumer<software.amazon.awssdk.services.m2.model.GetBatchJobExecutionRequest$Builder>);
    Code:
       0: aload_0
       1: invokestatic  #63                 // Method software/amazon/awssdk/services/m2/model/GetBatchJobExecutionRequest.builder:()Lsoftware/amazon/awssdk/services/m2/model/GetBatchJobExecutionRequest$Builder;
       4: aload_1
       5: invokeinterface #64,  2           // InterfaceMethod software/amazon/awssdk/services/m2/model/GetBatchJobExecutionRequest$Builder.applyMutation:(Ljava/util/function/Consumer;)Lsoftware/amazon/awssdk/utils/builder/SdkBuilder;
      10: checkcast     #65                 // class software/amazon/awssdk/services/m2/model/GetBatchJobExecutionRequest$Builder
      13: invokeinterface #66,  1           // InterfaceMethod software/amazon/awssdk/services/m2/model/GetBatchJobExecutionRequest$Builder.build:()Ljava/lang/Object;
      18: checkcast     #67                 // class software/amazon/awssdk/services/m2/model/GetBatchJobExecutionRequest
      21: invokeinterface #68,  2           // InterfaceMethod getBatchJobExecution:(Lsoftware/amazon/awssdk/services/m2/model/GetBatchJobExecutionRequest;)Ljava/util/concurrent/CompletableFuture;
      26: areturn

  public default java.util.concurrent.CompletableFuture<software.amazon.awssdk.services.m2.model.GetDataSetDetailsResponse> getDataSetDetails(software.amazon.awssdk.services.m2.model.GetDataSetDetailsRequest);
    Code:
       0: new           #1                  // class java/lang/UnsupportedOperationException
       3: dup
       4: invokespecial #2                  // Method java/lang/UnsupportedOperationException."<init>":()V
       7: athrow

  public default java.util.concurrent.CompletableFuture<software.amazon.awssdk.services.m2.model.GetDataSetDetailsResponse> getDataSetDetails(java.util.function.Consumer<software.amazon.awssdk.services.m2.model.GetDataSetDetailsRequest$Builder>);
    Code:
       0: aload_0
       1: invokestatic  #69                 // Method software/amazon/awssdk/services/m2/model/GetDataSetDetailsRequest.builder:()Lsoftware/amazon/awssdk/services/m2/model/GetDataSetDetailsRequest$Builder;
       4: aload_1
       5: invokeinterface #70,  2           // InterfaceMethod software/amazon/awssdk/services/m2/model/GetDataSetDetailsRequest$Builder.applyMutation:(Ljava/util/function/Consumer;)Lsoftware/amazon/awssdk/utils/builder/SdkBuilder;
      10: checkcast     #71                 // class software/amazon/awssdk/services/m2/model/GetDataSetDetailsRequest$Builder
      13: invokeinterface #72,  1           // InterfaceMethod software/amazon/awssdk/services/m2/model/GetDataSetDetailsRequest$Builder.build:()Ljava/lang/Object;
      18: checkcast     #73                 // class software/amazon/awssdk/services/m2/model/GetDataSetDetailsRequest
      21: invokeinterface #74,  2           // InterfaceMethod getDataSetDetails:(Lsoftware/amazon/awssdk/services/m2/model/GetDataSetDetailsRequest;)Ljava/util/concurrent/CompletableFuture;
      26: areturn

  public default java.util.concurrent.CompletableFuture<software.amazon.awssdk.services.m2.model.GetDataSetImportTaskResponse> getDataSetImportTask(software.amazon.awssdk.services.m2.model.GetDataSetImportTaskRequest);
    Code:
       0: new           #1                  // class java/lang/UnsupportedOperationException
       3: dup
       4: invokespecial #2                  // Method java/lang/UnsupportedOperationException."<init>":()V
       7: athrow

  public default java.util.concurrent.CompletableFuture<software.amazon.awssdk.services.m2.model.GetDataSetImportTaskResponse> getDataSetImportTask(java.util.function.Consumer<software.amazon.awssdk.services.m2.model.GetDataSetImportTaskRequest$Builder>);
    Code:
       0: aload_0
       1: invokestatic  #75                 // Method software/amazon/awssdk/services/m2/model/GetDataSetImportTaskRequest.builder:()Lsoftware/amazon/awssdk/services/m2/model/GetDataSetImportTaskRequest$Builder;
       4: aload_1
       5: invokeinterface #76,  2           // InterfaceMethod software/amazon/awssdk/services/m2/model/GetDataSetImportTaskRequest$Builder.applyMutation:(Ljava/util/function/Consumer;)Lsoftware/amazon/awssdk/utils/builder/SdkBuilder;
      10: checkcast     #77                 // class software/amazon/awssdk/services/m2/model/GetDataSetImportTaskRequest$Builder
      13: invokeinterface #78,  1           // InterfaceMethod software/amazon/awssdk/services/m2/model/GetDataSetImportTaskRequest$Builder.build:()Ljava/lang/Object;
      18: checkcast     #79                 // class software/amazon/awssdk/services/m2/model/GetDataSetImportTaskRequest
      21: invokeinterface #80,  2           // InterfaceMethod getDataSetImportTask:(Lsoftware/amazon/awssdk/services/m2/model/GetDataSetImportTaskRequest;)Ljava/util/concurrent/CompletableFuture;
      26: areturn

  public default java.util.concurrent.CompletableFuture<software.amazon.awssdk.services.m2.model.GetDeploymentResponse> getDeployment(software.amazon.awssdk.services.m2.model.GetDeploymentRequest);
    Code:
       0: new           #1                  // class java/lang/UnsupportedOperationException
       3: dup
       4: invokespecial #2                  // Method java/lang/UnsupportedOperationException."<init>":()V
       7: athrow

  public default java.util.concurrent.CompletableFuture<software.amazon.awssdk.services.m2.model.GetDeploymentResponse> getDeployment(java.util.function.Consumer<software.amazon.awssdk.services.m2.model.GetDeploymentRequest$Builder>);
    Code:
       0: aload_0
       1: invokestatic  #81                 // Method software/amazon/awssdk/services/m2/model/GetDeploymentRequest.builder:()Lsoftware/amazon/awssdk/services/m2/model/GetDeploymentRequest$Builder;
       4: aload_1
       5: invokeinterface #82,  2           // InterfaceMethod software/amazon/awssdk/services/m2/model/GetDeploymentRequest$Builder.applyMutation:(Ljava/util/function/Consumer;)Lsoftware/amazon/awssdk/utils/builder/SdkBuilder;
      10: checkcast     #83                 // class software/amazon/awssdk/services/m2/model/GetDeploymentRequest$Builder
      13: invokeinterface #84,  1           // InterfaceMethod software/amazon/awssdk/services/m2/model/GetDeploymentRequest$Builder.build:()Ljava/lang/Object;
      18: checkcast     #85                 // class software/amazon/awssdk/services/m2/model/GetDeploymentRequest
      21: invokeinterface #86,  2           // InterfaceMethod getDeployment:(Lsoftware/amazon/awssdk/services/m2/model/GetDeploymentRequest;)Ljava/util/concurrent/CompletableFuture;
      26: areturn

  public default java.util.concurrent.CompletableFuture<software.amazon.awssdk.services.m2.model.GetEnvironmentResponse> getEnvironment(software.amazon.awssdk.services.m2.model.GetEnvironmentRequest);
    Code:
       0: new           #1                  // class java/lang/UnsupportedOperationException
       3: dup
       4: invokespecial #2                  // Method java/lang/UnsupportedOperationException."<init>":()V
       7: athrow

  public default java.util.concurrent.CompletableFuture<software.amazon.awssdk.services.m2.model.GetEnvironmentResponse> getEnvironment(java.util.function.Consumer<software.amazon.awssdk.services.m2.model.GetEnvironmentRequest$Builder>);
    Code:
       0: aload_0
       1: invokestatic  #87                 // Method software/amazon/awssdk/services/m2/model/GetEnvironmentRequest.builder:()Lsoftware/amazon/awssdk/services/m2/model/GetEnvironmentRequest$Builder;
       4: aload_1
       5: invokeinterface #88,  2           // InterfaceMethod software/amazon/awssdk/services/m2/model/GetEnvironmentRequest$Builder.applyMutation:(Ljava/util/function/Consumer;)Lsoftware/amazon/awssdk/utils/builder/SdkBuilder;
      10: checkcast     #89                 // class software/amazon/awssdk/services/m2/model/GetEnvironmentRequest$Builder
      13: invokeinterface #90,  1           // InterfaceMethod software/amazon/awssdk/services/m2/model/GetEnvironmentRequest$Builder.build:()Ljava/lang/Object;
      18: checkcast     #91                 // class software/amazon/awssdk/services/m2/model/GetEnvironmentRequest
      21: invokeinterface #92,  2           // InterfaceMethod getEnvironment:(Lsoftware/amazon/awssdk/services/m2/model/GetEnvironmentRequest;)Ljava/util/concurrent/CompletableFuture;
      26: areturn

  public default java.util.concurrent.CompletableFuture<software.amazon.awssdk.services.m2.model.ListApplicationVersionsResponse> listApplicationVersions(software.amazon.awssdk.services.m2.model.ListApplicationVersionsRequest);
    Code:
       0: new           #1                  // class java/lang/UnsupportedOperationException
       3: dup
       4: invokespecial #2                  // Method java/lang/UnsupportedOperationException."<init>":()V
       7: athrow

  public default java.util.concurrent.CompletableFuture<software.amazon.awssdk.services.m2.model.ListApplicationVersionsResponse> listApplicationVersions(java.util.function.Consumer<software.amazon.awssdk.services.m2.model.ListApplicationVersionsRequest$Builder>);
    Code:
       0: aload_0
       1: invokestatic  #93                 // Method software/amazon/awssdk/services/m2/model/ListApplicationVersionsRequest.builder:()Lsoftware/amazon/awssdk/services/m2/model/ListApplicationVersionsRequest$Builder;
       4: aload_1
       5: invokeinterface #94,  2           // InterfaceMethod software/amazon/awssdk/services/m2/model/ListApplicationVersionsRequest$Builder.applyMutation:(Ljava/util/function/Consumer;)Lsoftware/amazon/awssdk/utils/builder/SdkBuilder;
      10: checkcast     #95                 // class software/amazon/awssdk/services/m2/model/ListApplicationVersionsRequest$Builder
      13: invokeinterface #96,  1           // InterfaceMethod software/amazon/awssdk/services/m2/model/ListApplicationVersionsRequest$Builder.build:()Ljava/lang/Object;
      18: checkcast     #97                 // class software/amazon/awssdk/services/m2/model/ListApplicationVersionsRequest
      21: invokeinterface #98,  2           // InterfaceMethod listApplicationVersions:(Lsoftware/amazon/awssdk/services/m2/model/ListApplicationVersionsRequest;)Ljava/util/concurrent/CompletableFuture;
      26: areturn

  public default software.amazon.awssdk.services.m2.paginators.ListApplicationVersionsPublisher listApplicationVersionsPaginator(software.amazon.awssdk.services.m2.model.ListApplicationVersionsRequest);
    Code:
       0: new           #1                  // class java/lang/UnsupportedOperationException
       3: dup
       4: invokespecial #2                  // Method java/lang/UnsupportedOperationException."<init>":()V
       7: athrow

  public default software.amazon.awssdk.services.m2.paginators.ListApplicationVersionsPublisher listApplicationVersionsPaginator(java.util.function.Consumer<software.amazon.awssdk.services.m2.model.ListApplicationVersionsRequest$Builder>);
    Code:
       0: aload_0
       1: invokestatic  #93                 // Method software/amazon/awssdk/services/m2/model/ListApplicationVersionsRequest.builder:()Lsoftware/amazon/awssdk/services/m2/model/ListApplicationVersionsRequest$Builder;
       4: aload_1
       5: invokeinterface #94,  2           // InterfaceMethod software/amazon/awssdk/services/m2/model/ListApplicationVersionsRequest$Builder.applyMutation:(Ljava/util/function/Consumer;)Lsoftware/amazon/awssdk/utils/builder/SdkBuilder;
      10: checkcast     #95                 // class software/amazon/awssdk/services/m2/model/ListApplicationVersionsRequest$Builder
      13: invokeinterface #96,  1           // InterfaceMethod software/amazon/awssdk/services/m2/model/ListApplicationVersionsRequest$Builder.build:()Ljava/lang/Object;
      18: checkcast     #97                 // class software/amazon/awssdk/services/m2/model/ListApplicationVersionsRequest
      21: invokeinterface #99,  2           // InterfaceMethod listApplicationVersionsPaginator:(Lsoftware/amazon/awssdk/services/m2/model/ListApplicationVersionsRequest;)Lsoftware/amazon/awssdk/services/m2/paginators/ListApplicationVersionsPublisher;
      26: areturn

  public default java.util.concurrent.CompletableFuture<software.amazon.awssdk.services.m2.model.ListApplicationsResponse> listApplications(software.amazon.awssdk.services.m2.model.ListApplicationsRequest);
    Code:
       0: new           #1                  // class java/lang/UnsupportedOperationException
       3: dup
       4: invokespecial #2                  // Method java/lang/UnsupportedOperationException."<init>":()V
       7: athrow

  public default java.util.concurrent.CompletableFuture<software.amazon.awssdk.services.m2.model.ListApplicationsResponse> listApplications(java.util.function.Consumer<software.amazon.awssdk.services.m2.model.ListApplicationsRequest$Builder>);
    Code:
       0: aload_0
       1: invokestatic  #100                // Method software/amazon/awssdk/services/m2/model/ListApplicationsRequest.builder:()Lsoftware/amazon/awssdk/services/m2/model/ListApplicationsRequest$Builder;
       4: aload_1
       5: invokeinterface #101,  2          // InterfaceMethod software/amazon/awssdk/services/m2/model/ListApplicationsRequest$Builder.applyMutation:(Ljava/util/function/Consumer;)Lsoftware/amazon/awssdk/utils/builder/SdkBuilder;
      10: checkcast     #102                // class software/amazon/awssdk/services/m2/model/ListApplicationsRequest$Builder
      13: invokeinterface #103,  1          // InterfaceMethod software/amazon/awssdk/services/m2/model/ListApplicationsRequest$Builder.build:()Ljava/lang/Object;
      18: checkcast     #104                // class software/amazon/awssdk/services/m2/model/ListApplicationsRequest
      21: invokeinterface #105,  2          // InterfaceMethod listApplications:(Lsoftware/amazon/awssdk/services/m2/model/ListApplicationsRequest;)Ljava/util/concurrent/CompletableFuture;
      26: areturn

  public default software.amazon.awssdk.services.m2.paginators.ListApplicationsPublisher listApplicationsPaginator(software.amazon.awssdk.services.m2.model.ListApplicationsRequest);
    Code:
       0: new           #1                  // class java/lang/UnsupportedOperationException
       3: dup
       4: invokespecial #2                  // Method java/lang/UnsupportedOperationException."<init>":()V
       7: athrow

  public default software.amazon.awssdk.services.m2.paginators.ListApplicationsPublisher listApplicationsPaginator(java.util.function.Consumer<software.amazon.awssdk.services.m2.model.ListApplicationsRequest$Builder>);
    Code:
       0: aload_0
       1: invokestatic  #100                // Method software/amazon/awssdk/services/m2/model/ListApplicationsRequest.builder:()Lsoftware/amazon/awssdk/services/m2/model/ListApplicationsRequest$Builder;
       4: aload_1
       5: invokeinterface #101,  2          // InterfaceMethod software/amazon/awssdk/services/m2/model/ListApplicationsRequest$Builder.applyMutation:(Ljava/util/function/Consumer;)Lsoftware/amazon/awssdk/utils/builder/SdkBuilder;
      10: checkcast     #102                // class software/amazon/awssdk/services/m2/model/ListApplicationsRequest$Builder
      13: invokeinterface #103,  1          // InterfaceMethod software/amazon/awssdk/services/m2/model/ListApplicationsRequest$Builder.build:()Ljava/lang/Object;
      18: checkcast     #104                // class software/amazon/awssdk/services/m2/model/ListApplicationsRequest
      21: invokeinterface #106,  2          // InterfaceMethod listApplicationsPaginator:(Lsoftware/amazon/awssdk/services/m2/model/ListApplicationsRequest;)Lsoftware/amazon/awssdk/services/m2/paginators/ListApplicationsPublisher;
      26: areturn

  public default java.util.concurrent.CompletableFuture<software.amazon.awssdk.services.m2.model.ListBatchJobDefinitionsResponse> listBatchJobDefinitions(software.amazon.awssdk.services.m2.model.ListBatchJobDefinitionsRequest);
    Code:
       0: new           #1                  // class java/lang/UnsupportedOperationException
       3: dup
       4: invokespecial #2                  // Method java/lang/UnsupportedOperationException."<init>":()V
       7: athrow

  public default java.util.concurrent.CompletableFuture<software.amazon.awssdk.services.m2.model.ListBatchJobDefinitionsResponse> listBatchJobDefinitions(java.util.function.Consumer<software.amazon.awssdk.services.m2.model.ListBatchJobDefinitionsRequest$Builder>);
    Code:
       0: aload_0
       1: invokestatic  #107                // Method software/amazon/awssdk/services/m2/model/ListBatchJobDefinitionsRequest.builder:()Lsoftware/amazon/awssdk/services/m2/model/ListBatchJobDefinitionsRequest$Builder;
       4: aload_1
       5: invokeinterface #108,  2          // InterfaceMethod software/amazon/awssdk/services/m2/model/ListBatchJobDefinitionsRequest$Builder.applyMutation:(Ljava/util/function/Consumer;)Lsoftware/amazon/awssdk/utils/builder/SdkBuilder;
      10: checkcast     #109                // class software/amazon/awssdk/services/m2/model/ListBatchJobDefinitionsRequest$Builder
      13: invokeinterface #110,  1          // InterfaceMethod software/amazon/awssdk/services/m2/model/ListBatchJobDefinitionsRequest$Builder.build:()Ljava/lang/Object;
      18: checkcast     #111                // class software/amazon/awssdk/services/m2/model/ListBatchJobDefinitionsRequest
      21: invokeinterface #112,  2          // InterfaceMethod listBatchJobDefinitions:(Lsoftware/amazon/awssdk/services/m2/model/ListBatchJobDefinitionsRequest;)Ljava/util/concurrent/CompletableFuture;
      26: areturn

  public default software.amazon.awssdk.services.m2.paginators.ListBatchJobDefinitionsPublisher listBatchJobDefinitionsPaginator(software.amazon.awssdk.services.m2.model.ListBatchJobDefinitionsRequest);
    Code:
       0: new           #1                  // class java/lang/UnsupportedOperationException
       3: dup
       4: invokespecial #2                  // Method java/lang/UnsupportedOperationException."<init>":()V
       7: athrow

  public default software.amazon.awssdk.services.m2.paginators.ListBatchJobDefinitionsPublisher listBatchJobDefinitionsPaginator(java.util.function.Consumer<software.amazon.awssdk.services.m2.model.ListBatchJobDefinitionsRequest$Builder>);
    Code:
       0: aload_0
       1: invokestatic  #107                // Method software/amazon/awssdk/services/m2/model/ListBatchJobDefinitionsRequest.builder:()Lsoftware/amazon/awssdk/services/m2/model/ListBatchJobDefinitionsRequest$Builder;
       4: aload_1
       5: invokeinterface #108,  2          // InterfaceMethod software/amazon/awssdk/services/m2/model/ListBatchJobDefinitionsRequest$Builder.applyMutation:(Ljava/util/function/Consumer;)Lsoftware/amazon/awssdk/utils/builder/SdkBuilder;
      10: checkcast     #109                // class software/amazon/awssdk/services/m2/model/ListBatchJobDefinitionsRequest$Builder
      13: invokeinterface #110,  1          // InterfaceMethod software/amazon/awssdk/services/m2/model/ListBatchJobDefinitionsRequest$Builder.build:()Ljava/lang/Object;
      18: checkcast     #111                // class software/amazon/awssdk/services/m2/model/ListBatchJobDefinitionsRequest
      21: invokeinterface #113,  2          // InterfaceMethod listBatchJobDefinitionsPaginator:(Lsoftware/amazon/awssdk/services/m2/model/ListBatchJobDefinitionsRequest;)Lsoftware/amazon/awssdk/services/m2/paginators/ListBatchJobDefinitionsPublisher;
      26: areturn

  public default java.util.concurrent.CompletableFuture<software.amazon.awssdk.services.m2.model.ListBatchJobExecutionsResponse> listBatchJobExecutions(software.amazon.awssdk.services.m2.model.ListBatchJobExecutionsRequest);
    Code:
       0: new           #1                  // class java/lang/UnsupportedOperationException
       3: dup
       4: invokespecial #2                  // Method java/lang/UnsupportedOperationException."<init>":()V
       7: athrow

  public default java.util.concurrent.CompletableFuture<software.amazon.awssdk.services.m2.model.ListBatchJobExecutionsResponse> listBatchJobExecutions(java.util.function.Consumer<software.amazon.awssdk.services.m2.model.ListBatchJobExecutionsRequest$Builder>);
    Code:
       0: aload_0
       1: invokestatic  #114                // Method software/amazon/awssdk/services/m2/model/ListBatchJobExecutionsRequest.builder:()Lsoftware/amazon/awssdk/services/m2/model/ListBatchJobExecutionsRequest$Builder;
       4: aload_1
       5: invokeinterface #115,  2          // InterfaceMethod software/amazon/awssdk/services/m2/model/ListBatchJobExecutionsRequest$Builder.applyMutation:(Ljava/util/function/Consumer;)Lsoftware/amazon/awssdk/utils/builder/SdkBuilder;
      10: checkcast     #116                // class software/amazon/awssdk/services/m2/model/ListBatchJobExecutionsRequest$Builder
      13: invokeinterface #117,  1          // InterfaceMethod software/amazon/awssdk/services/m2/model/ListBatchJobExecutionsRequest$Builder.build:()Ljava/lang/Object;
      18: checkcast     #118                // class software/amazon/awssdk/services/m2/model/ListBatchJobExecutionsRequest
      21: invokeinterface #119,  2          // InterfaceMethod listBatchJobExecutions:(Lsoftware/amazon/awssdk/services/m2/model/ListBatchJobExecutionsRequest;)Ljava/util/concurrent/CompletableFuture;
      26: areturn

  public default software.amazon.awssdk.services.m2.paginators.ListBatchJobExecutionsPublisher listBatchJobExecutionsPaginator(software.amazon.awssdk.services.m2.model.ListBatchJobExecutionsRequest);
    Code:
       0: new           #1                  // class java/lang/UnsupportedOperationException
       3: dup
       4: invokespecial #2                  // Method java/lang/UnsupportedOperationException."<init>":()V
       7: athrow

  public default software.amazon.awssdk.services.m2.paginators.ListBatchJobExecutionsPublisher listBatchJobExecutionsPaginator(java.util.function.Consumer<software.amazon.awssdk.services.m2.model.ListBatchJobExecutionsRequest$Builder>);
    Code:
       0: aload_0
       1: invokestatic  #114                // Method software/amazon/awssdk/services/m2/model/ListBatchJobExecutionsRequest.builder:()Lsoftware/amazon/awssdk/services/m2/model/ListBatchJobExecutionsRequest$Builder;
       4: aload_1
       5: invokeinterface #115,  2          // InterfaceMethod software/amazon/awssdk/services/m2/model/ListBatchJobExecutionsRequest$Builder.applyMutation:(Ljava/util/function/Consumer;)Lsoftware/amazon/awssdk/utils/builder/SdkBuilder;
      10: checkcast     #116                // class software/amazon/awssdk/services/m2/model/ListBatchJobExecutionsRequest$Builder
      13: invokeinterface #117,  1          // InterfaceMethod software/amazon/awssdk/services/m2/model/ListBatchJobExecutionsRequest$Builder.build:()Ljava/lang/Object;
      18: checkcast     #118                // class software/amazon/awssdk/services/m2/model/ListBatchJobExecutionsRequest
      21: invokeinterface #120,  2          // InterfaceMethod listBatchJobExecutionsPaginator:(Lsoftware/amazon/awssdk/services/m2/model/ListBatchJobExecutionsRequest;)Lsoftware/amazon/awssdk/services/m2/paginators/ListBatchJobExecutionsPublisher;
      26: areturn

  public default java.util.concurrent.CompletableFuture<software.amazon.awssdk.services.m2.model.ListDataSetImportHistoryResponse> listDataSetImportHistory(software.amazon.awssdk.services.m2.model.ListDataSetImportHistoryRequest);
    Code:
       0: new           #1                  // class java/lang/UnsupportedOperationException
       3: dup
       4: invokespecial #2                  // Method java/lang/UnsupportedOperationException."<init>":()V
       7: athrow

  public default java.util.concurrent.CompletableFuture<software.amazon.awssdk.services.m2.model.ListDataSetImportHistoryResponse> listDataSetImportHistory(java.util.function.Consumer<software.amazon.awssdk.services.m2.model.ListDataSetImportHistoryRequest$Builder>);
    Code:
       0: aload_0
       1: invokestatic  #121                // Method software/amazon/awssdk/services/m2/model/ListDataSetImportHistoryRequest.builder:()Lsoftware/amazon/awssdk/services/m2/model/ListDataSetImportHistoryRequest$Builder;
       4: aload_1
       5: invokeinterface #122,  2          // InterfaceMethod software/amazon/awssdk/services/m2/model/ListDataSetImportHistoryRequest$Builder.applyMutation:(Ljava/util/function/Consumer;)Lsoftware/amazon/awssdk/utils/builder/SdkBuilder;
      10: checkcast     #123                // class software/amazon/awssdk/services/m2/model/ListDataSetImportHistoryRequest$Builder
      13: invokeinterface #124,  1          // InterfaceMethod software/amazon/awssdk/services/m2/model/ListDataSetImportHistoryRequest$Builder.build:()Ljava/lang/Object;
      18: checkcast     #125                // class software/amazon/awssdk/services/m2/model/ListDataSetImportHistoryRequest
      21: invokeinterface #126,  2          // InterfaceMethod listDataSetImportHistory:(Lsoftware/amazon/awssdk/services/m2/model/ListDataSetImportHistoryRequest;)Ljava/util/concurrent/CompletableFuture;
      26: areturn

  public default software.amazon.awssdk.services.m2.paginators.ListDataSetImportHistoryPublisher listDataSetImportHistoryPaginator(software.amazon.awssdk.services.m2.model.ListDataSetImportHistoryRequest);
    Code:
       0: new           #1                  // class java/lang/UnsupportedOperationException
       3: dup
       4: invokespecial #2                  // Method java/lang/UnsupportedOperationException."<init>":()V
       7: athrow

  public default software.amazon.awssdk.services.m2.paginators.ListDataSetImportHistoryPublisher listDataSetImportHistoryPaginator(java.util.function.Consumer<software.amazon.awssdk.services.m2.model.ListDataSetImportHistoryRequest$Builder>);
    Code:
       0: aload_0
       1: invokestatic  #121                // Method software/amazon/awssdk/services/m2/model/ListDataSetImportHistoryRequest.builder:()Lsoftware/amazon/awssdk/services/m2/model/ListDataSetImportHistoryRequest$Builder;
       4: aload_1
       5: invokeinterface #122,  2          // InterfaceMethod software/amazon/awssdk/services/m2/model/ListDataSetImportHistoryRequest$Builder.applyMutation:(Ljava/util/function/Consumer;)Lsoftware/amazon/awssdk/utils/builder/SdkBuilder;
      10: checkcast     #123                // class software/amazon/awssdk/services/m2/model/ListDataSetImportHistoryRequest$Builder
      13: invokeinterface #124,  1          // InterfaceMethod software/amazon/awssdk/services/m2/model/ListDataSetImportHistoryRequest$Builder.build:()Ljava/lang/Object;
      18: checkcast     #125                // class software/amazon/awssdk/services/m2/model/ListDataSetImportHistoryRequest
      21: invokeinterface #127,  2          // InterfaceMethod listDataSetImportHistoryPaginator:(Lsoftware/amazon/awssdk/services/m2/model/ListDataSetImportHistoryRequest;)Lsoftware/amazon/awssdk/services/m2/paginators/ListDataSetImportHistoryPublisher;
      26: areturn

  public default java.util.concurrent.CompletableFuture<software.amazon.awssdk.services.m2.model.ListDataSetsResponse> listDataSets(software.amazon.awssdk.services.m2.model.ListDataSetsRequest);
    Code:
       0: new           #1                  // class java/lang/UnsupportedOperationException
       3: dup
       4: invokespecial #2                  // Method java/lang/UnsupportedOperationException."<init>":()V
       7: athrow

  public default java.util.concurrent.CompletableFuture<software.amazon.awssdk.services.m2.model.ListDataSetsResponse> listDataSets(java.util.function.Consumer<software.amazon.awssdk.services.m2.model.ListDataSetsRequest$Builder>);
    Code:
       0: aload_0
       1: invokestatic  #128                // Method software/amazon/awssdk/services/m2/model/ListDataSetsRequest.builder:()Lsoftware/amazon/awssdk/services/m2/model/ListDataSetsRequest$Builder;
       4: aload_1
       5: invokeinterface #129,  2          // InterfaceMethod software/amazon/awssdk/services/m2/model/ListDataSetsRequest$Builder.applyMutation:(Ljava/util/function/Consumer;)Lsoftware/amazon/awssdk/utils/builder/SdkBuilder;
      10: checkcast     #130                // class software/amazon/awssdk/services/m2/model/ListDataSetsRequest$Builder
      13: invokeinterface #131,  1          // InterfaceMethod software/amazon/awssdk/services/m2/model/ListDataSetsRequest$Builder.build:()Ljava/lang/Object;
      18: checkcast     #132                // class software/amazon/awssdk/services/m2/model/ListDataSetsRequest
      21: invokeinterface #133,  2          // InterfaceMethod listDataSets:(Lsoftware/amazon/awssdk/services/m2/model/ListDataSetsRequest;)Ljava/util/concurrent/CompletableFuture;
      26: areturn

  public default software.amazon.awssdk.services.m2.paginators.ListDataSetsPublisher listDataSetsPaginator(software.amazon.awssdk.services.m2.model.ListDataSetsRequest);
    Code:
       0: new           #1                  // class java/lang/UnsupportedOperationException
       3: dup
       4: invokespecial #2                  // Method java/lang/UnsupportedOperationException."<init>":()V
       7: athrow

  public default software.amazon.awssdk.services.m2.paginators.ListDataSetsPublisher listDataSetsPaginator(java.util.function.Consumer<software.amazon.awssdk.services.m2.model.ListDataSetsRequest$Builder>);
    Code:
       0: aload_0
       1: invokestatic  #128                // Method software/amazon/awssdk/services/m2/model/ListDataSetsRequest.builder:()Lsoftware/amazon/awssdk/services/m2/model/ListDataSetsRequest$Builder;
       4: aload_1
       5: invokeinterface #129,  2          // InterfaceMethod software/amazon/awssdk/services/m2/model/ListDataSetsRequest$Builder.applyMutation:(Ljava/util/function/Consumer;)Lsoftware/amazon/awssdk/utils/builder/SdkBuilder;
      10: checkcast     #130                // class software/amazon/awssdk/services/m2/model/ListDataSetsRequest$Builder
      13: invokeinterface #131,  1          // InterfaceMethod software/amazon/awssdk/services/m2/model/ListDataSetsRequest$Builder.build:()Ljava/lang/Object;
      18: checkcast     #132                // class software/amazon/awssdk/services/m2/model/ListDataSetsRequest
      21: invokeinterface #134,  2          // InterfaceMethod listDataSetsPaginator:(Lsoftware/amazon/awssdk/services/m2/model/ListDataSetsRequest;)Lsoftware/amazon/awssdk/services/m2/paginators/ListDataSetsPublisher;
      26: areturn

  public default java.util.concurrent.CompletableFuture<software.amazon.awssdk.services.m2.model.ListDeploymentsResponse> listDeployments(software.amazon.awssdk.services.m2.model.ListDeploymentsRequest);
    Code:
       0: new           #1                  // class java/lang/UnsupportedOperationException
       3: dup
       4: invokespecial #2                  // Method java/lang/UnsupportedOperationException."<init>":()V
       7: athrow

  public default java.util.concurrent.CompletableFuture<software.amazon.awssdk.services.m2.model.ListDeploymentsResponse> listDeployments(java.util.function.Consumer<software.amazon.awssdk.services.m2.model.ListDeploymentsRequest$Builder>);
    Code:
       0: aload_0
       1: invokestatic  #135                // Method software/amazon/awssdk/services/m2/model/ListDeploymentsRequest.builder:()Lsoftware/amazon/awssdk/services/m2/model/ListDeploymentsRequest$Builder;
       4: aload_1
       5: invokeinterface #136,  2          // InterfaceMethod software/amazon/awssdk/services/m2/model/ListDeploymentsRequest$Builder.applyMutation:(Ljava/util/function/Consumer;)Lsoftware/amazon/awssdk/utils/builder/SdkBuilder;
      10: checkcast     #137                // class software/amazon/awssdk/services/m2/model/ListDeploymentsRequest$Builder
      13: invokeinterface #138,  1          // InterfaceMethod software/amazon/awssdk/services/m2/model/ListDeploymentsRequest$Builder.build:()Ljava/lang/Object;
      18: checkcast     #139                // class software/amazon/awssdk/services/m2/model/ListDeploymentsRequest
      21: invokeinterface #140,  2          // InterfaceMethod listDeployments:(Lsoftware/amazon/awssdk/services/m2/model/ListDeploymentsRequest;)Ljava/util/concurrent/CompletableFuture;
      26: areturn

  public default software.amazon.awssdk.services.m2.paginators.ListDeploymentsPublisher listDeploymentsPaginator(software.amazon.awssdk.services.m2.model.ListDeploymentsRequest);
    Code:
       0: new           #1                  // class java/lang/UnsupportedOperationException
       3: dup
       4: invokespecial #2                  // Method java/lang/UnsupportedOperationException."<init>":()V
       7: athrow

  public default software.amazon.awssdk.services.m2.paginators.ListDeploymentsPublisher listDeploymentsPaginator(java.util.function.Consumer<software.amazon.awssdk.services.m2.model.ListDeploymentsRequest$Builder>);
    Code:
       0: aload_0
       1: invokestatic  #135                // Method software/amazon/awssdk/services/m2/model/ListDeploymentsRequest.builder:()Lsoftware/amazon/awssdk/services/m2/model/ListDeploymentsRequest$Builder;
       4: aload_1
       5: invokeinterface #136,  2          // InterfaceMethod software/amazon/awssdk/services/m2/model/ListDeploymentsRequest$Builder.applyMutation:(Ljava/util/function/Consumer;)Lsoftware/amazon/awssdk/utils/builder/SdkBuilder;
      10: checkcast     #137                // class software/amazon/awssdk/services/m2/model/ListDeploymentsRequest$Builder
      13: invokeinterface #138,  1          // InterfaceMethod software/amazon/awssdk/services/m2/model/ListDeploymentsRequest$Builder.build:()Ljava/lang/Object;
      18: checkcast     #139                // class software/amazon/awssdk/services/m2/model/ListDeploymentsRequest
      21: invokeinterface #141,  2          // InterfaceMethod listDeploymentsPaginator:(Lsoftware/amazon/awssdk/services/m2/model/ListDeploymentsRequest;)Lsoftware/amazon/awssdk/services/m2/paginators/ListDeploymentsPublisher;
      26: areturn

  public default java.util.concurrent.CompletableFuture<software.amazon.awssdk.services.m2.model.ListEngineVersionsResponse> listEngineVersions(software.amazon.awssdk.services.m2.model.ListEngineVersionsRequest);
    Code:
       0: new           #1                  // class java/lang/UnsupportedOperationException
       3: dup
       4: invokespecial #2                  // Method java/lang/UnsupportedOperationException."<init>":()V
       7: athrow

  public default java.util.concurrent.CompletableFuture<software.amazon.awssdk.services.m2.model.ListEngineVersionsResponse> listEngineVersions(java.util.function.Consumer<software.amazon.awssdk.services.m2.model.ListEngineVersionsRequest$Builder>);
    Code:
       0: aload_0
       1: invokestatic  #142                // Method software/amazon/awssdk/services/m2/model/ListEngineVersionsRequest.builder:()Lsoftware/amazon/awssdk/services/m2/model/ListEngineVersionsRequest$Builder;
       4: aload_1
       5: invokeinterface #143,  2          // InterfaceMethod software/amazon/awssdk/services/m2/model/ListEngineVersionsRequest$Builder.applyMutation:(Ljava/util/function/Consumer;)Lsoftware/amazon/awssdk/utils/builder/SdkBuilder;
      10: checkcast     #144                // class software/amazon/awssdk/services/m2/model/ListEngineVersionsRequest$Builder
      13: invokeinterface #145,  1          // InterfaceMethod software/amazon/awssdk/services/m2/model/ListEngineVersionsRequest$Builder.build:()Ljava/lang/Object;
      18: checkcast     #146                // class software/amazon/awssdk/services/m2/model/ListEngineVersionsRequest
      21: invokeinterface #147,  2          // InterfaceMethod listEngineVersions:(Lsoftware/amazon/awssdk/services/m2/model/ListEngineVersionsRequest;)Ljava/util/concurrent/CompletableFuture;
      26: areturn

  public default software.amazon.awssdk.services.m2.paginators.ListEngineVersionsPublisher listEngineVersionsPaginator(software.amazon.awssdk.services.m2.model.ListEngineVersionsRequest);
    Code:
       0: new           #1                  // class java/lang/UnsupportedOperationException
       3: dup
       4: invokespecial #2                  // Method java/lang/UnsupportedOperationException."<init>":()V
       7: athrow

  public default software.amazon.awssdk.services.m2.paginators.ListEngineVersionsPublisher listEngineVersionsPaginator(java.util.function.Consumer<software.amazon.awssdk.services.m2.model.ListEngineVersionsRequest$Builder>);
    Code:
       0: aload_0
       1: invokestatic  #142                // Method software/amazon/awssdk/services/m2/model/ListEngineVersionsRequest.builder:()Lsoftware/amazon/awssdk/services/m2/model/ListEngineVersionsRequest$Builder;
       4: aload_1
       5: invokeinterface #143,  2          // InterfaceMethod software/amazon/awssdk/services/m2/model/ListEngineVersionsRequest$Builder.applyMutation:(Ljava/util/function/Consumer;)Lsoftware/amazon/awssdk/utils/builder/SdkBuilder;
      10: checkcast     #144                // class software/amazon/awssdk/services/m2/model/ListEngineVersionsRequest$Builder
      13: invokeinterface #145,  1          // InterfaceMethod software/amazon/awssdk/services/m2/model/ListEngineVersionsRequest$Builder.build:()Ljava/lang/Object;
      18: checkcast     #146                // class software/amazon/awssdk/services/m2/model/ListEngineVersionsRequest
      21: invokeinterface #148,  2          // InterfaceMethod listEngineVersionsPaginator:(Lsoftware/amazon/awssdk/services/m2/model/ListEngineVersionsRequest;)Lsoftware/amazon/awssdk/services/m2/paginators/ListEngineVersionsPublisher;
      26: areturn

  public default java.util.concurrent.CompletableFuture<software.amazon.awssdk.services.m2.model.ListEnvironmentsResponse> listEnvironments(software.amazon.awssdk.services.m2.model.ListEnvironmentsRequest);
    Code:
       0: new           #1                  // class java/lang/UnsupportedOperationException
       3: dup
       4: invokespecial #2                  // Method java/lang/UnsupportedOperationException."<init>":()V
       7: athrow

  public default java.util.concurrent.CompletableFuture<software.amazon.awssdk.services.m2.model.ListEnvironmentsResponse> listEnvironments(java.util.function.Consumer<software.amazon.awssdk.services.m2.model.ListEnvironmentsRequest$Builder>);
    Code:
       0: aload_0
       1: invokestatic  #149                // Method software/amazon/awssdk/services/m2/model/ListEnvironmentsRequest.builder:()Lsoftware/amazon/awssdk/services/m2/model/ListEnvironmentsRequest$Builder;
       4: aload_1
       5: invokeinterface #150,  2          // InterfaceMethod software/amazon/awssdk/services/m2/model/ListEnvironmentsRequest$Builder.applyMutation:(Ljava/util/function/Consumer;)Lsoftware/amazon/awssdk/utils/builder/SdkBuilder;
      10: checkcast     #151                // class software/amazon/awssdk/services/m2/model/ListEnvironmentsRequest$Builder
      13: invokeinterface #152,  1          // InterfaceMethod software/amazon/awssdk/services/m2/model/ListEnvironmentsRequest$Builder.build:()Ljava/lang/Object;
      18: checkcast     #153                // class software/amazon/awssdk/services/m2/model/ListEnvironmentsRequest
      21: invokeinterface #154,  2          // InterfaceMethod listEnvironments:(Lsoftware/amazon/awssdk/services/m2/model/ListEnvironmentsRequest;)Ljava/util/concurrent/CompletableFuture;
      26: areturn

  public default software.amazon.awssdk.services.m2.paginators.ListEnvironmentsPublisher listEnvironmentsPaginator(software.amazon.awssdk.services.m2.model.ListEnvironmentsRequest);
    Code:
       0: new           #1                  // class java/lang/UnsupportedOperationException
       3: dup
       4: invokespecial #2                  // Method java/lang/UnsupportedOperationException."<init>":()V
       7: athrow

  public default software.amazon.awssdk.services.m2.paginators.ListEnvironmentsPublisher listEnvironmentsPaginator(java.util.function.Consumer<software.amazon.awssdk.services.m2.model.ListEnvironmentsRequest$Builder>);
    Code:
       0: aload_0
       1: invokestatic  #149                // Method software/amazon/awssdk/services/m2/model/ListEnvironmentsRequest.builder:()Lsoftware/amazon/awssdk/services/m2/model/ListEnvironmentsRequest$Builder;
       4: aload_1
       5: invokeinterface #150,  2          // InterfaceMethod software/amazon/awssdk/services/m2/model/ListEnvironmentsRequest$Builder.applyMutation:(Ljava/util/function/Consumer;)Lsoftware/amazon/awssdk/utils/builder/SdkBuilder;
      10: checkcast     #151                // class software/amazon/awssdk/services/m2/model/ListEnvironmentsRequest$Builder
      13: invokeinterface #152,  1          // InterfaceMethod software/amazon/awssdk/services/m2/model/ListEnvironmentsRequest$Builder.build:()Ljava/lang/Object;
      18: checkcast     #153                // class software/amazon/awssdk/services/m2/model/ListEnvironmentsRequest
      21: invokeinterface #155,  2          // InterfaceMethod listEnvironmentsPaginator:(Lsoftware/amazon/awssdk/services/m2/model/ListEnvironmentsRequest;)Lsoftware/amazon/awssdk/services/m2/paginators/ListEnvironmentsPublisher;
      26: areturn

  public default java.util.concurrent.CompletableFuture<software.amazon.awssdk.services.m2.model.ListTagsForResourceResponse> listTagsForResource(software.amazon.awssdk.services.m2.model.ListTagsForResourceRequest);
    Code:
       0: new           #1                  // class java/lang/UnsupportedOperationException
       3: dup
       4: invokespecial #2                  // Method java/lang/UnsupportedOperationException."<init>":()V
       7: athrow

  public default java.util.concurrent.CompletableFuture<software.amazon.awssdk.services.m2.model.ListTagsForResourceResponse> listTagsForResource(java.util.function.Consumer<software.amazon.awssdk.services.m2.model.ListTagsForResourceRequest$Builder>);
    Code:
       0: aload_0
       1: invokestatic  #156                // Method software/amazon/awssdk/services/m2/model/ListTagsForResourceRequest.builder:()Lsoftware/amazon/awssdk/services/m2/model/ListTagsForResourceRequest$Builder;
       4: aload_1
       5: invokeinterface #157,  2          // InterfaceMethod software/amazon/awssdk/services/m2/model/ListTagsForResourceRequest$Builder.applyMutation:(Ljava/util/function/Consumer;)Lsoftware/amazon/awssdk/utils/builder/SdkBuilder;
      10: checkcast     #158                // class software/amazon/awssdk/services/m2/model/ListTagsForResourceRequest$Builder
      13: invokeinterface #159,  1          // InterfaceMethod software/amazon/awssdk/services/m2/model/ListTagsForResourceRequest$Builder.build:()Ljava/lang/Object;
      18: checkcast     #160                // class software/amazon/awssdk/services/m2/model/ListTagsForResourceRequest
      21: invokeinterface #161,  2          // InterfaceMethod listTagsForResource:(Lsoftware/amazon/awssdk/services/m2/model/ListTagsForResourceRequest;)Ljava/util/concurrent/CompletableFuture;
      26: areturn

  public default java.util.concurrent.CompletableFuture<software.amazon.awssdk.services.m2.model.StartApplicationResponse> startApplication(software.amazon.awssdk.services.m2.model.StartApplicationRequest);
    Code:
       0: new           #1                  // class java/lang/UnsupportedOperationException
       3: dup
       4: invokespecial #2                  // Method java/lang/UnsupportedOperationException."<init>":()V
       7: athrow

  public default java.util.concurrent.CompletableFuture<software.amazon.awssdk.services.m2.model.StartApplicationResponse> startApplication(java.util.function.Consumer<software.amazon.awssdk.services.m2.model.StartApplicationRequest$Builder>);
    Code:
       0: aload_0
       1: invokestatic  #162                // Method software/amazon/awssdk/services/m2/model/StartApplicationRequest.builder:()Lsoftware/amazon/awssdk/services/m2/model/StartApplicationRequest$Builder;
       4: aload_1
       5: invokeinterface #163,  2          // InterfaceMethod software/amazon/awssdk/services/m2/model/StartApplicationRequest$Builder.applyMutation:(Ljava/util/function/Consumer;)Lsoftware/amazon/awssdk/utils/builder/SdkBuilder;
      10: checkcast     #164                // class software/amazon/awssdk/services/m2/model/StartApplicationRequest$Builder
      13: invokeinterface #165,  1          // InterfaceMethod software/amazon/awssdk/services/m2/model/StartApplicationRequest$Builder.build:()Ljava/lang/Object;
      18: checkcast     #166                // class software/amazon/awssdk/services/m2/model/StartApplicationRequest
      21: invokeinterface #167,  2          // InterfaceMethod startApplication:(Lsoftware/amazon/awssdk/services/m2/model/StartApplicationRequest;)Ljava/util/concurrent/CompletableFuture;
      26: areturn

  public default java.util.concurrent.CompletableFuture<software.amazon.awssdk.services.m2.model.StartBatchJobResponse> startBatchJob(software.amazon.awssdk.services.m2.model.StartBatchJobRequest);
    Code:
       0: new           #1                  // class java/lang/UnsupportedOperationException
       3: dup
       4: invokespecial #2                  // Method java/lang/UnsupportedOperationException."<init>":()V
       7: athrow

  public default java.util.concurrent.CompletableFuture<software.amazon.awssdk.services.m2.model.StartBatchJobResponse> startBatchJob(java.util.function.Consumer<software.amazon.awssdk.services.m2.model.StartBatchJobRequest$Builder>);
    Code:
       0: aload_0
       1: invokestatic  #168                // Method software/amazon/awssdk/services/m2/model/StartBatchJobRequest.builder:()Lsoftware/amazon/awssdk/services/m2/model/StartBatchJobRequest$Builder;
       4: aload_1
       5: invokeinterface #169,  2          // InterfaceMethod software/amazon/awssdk/services/m2/model/StartBatchJobRequest$Builder.applyMutation:(Ljava/util/function/Consumer;)Lsoftware/amazon/awssdk/utils/builder/SdkBuilder;
      10: checkcast     #170                // class software/amazon/awssdk/services/m2/model/StartBatchJobRequest$Builder
      13: invokeinterface #171,  1          // InterfaceMethod software/amazon/awssdk/services/m2/model/StartBatchJobRequest$Builder.build:()Ljava/lang/Object;
      18: checkcast     #172                // class software/amazon/awssdk/services/m2/model/StartBatchJobRequest
      21: invokeinterface #173,  2          // InterfaceMethod startBatchJob:(Lsoftware/amazon/awssdk/services/m2/model/StartBatchJobRequest;)Ljava/util/concurrent/CompletableFuture;
      26: areturn

  public default java.util.concurrent.CompletableFuture<software.amazon.awssdk.services.m2.model.StopApplicationResponse> stopApplication(software.amazon.awssdk.services.m2.model.StopApplicationRequest);
    Code:
       0: new           #1                  // class java/lang/UnsupportedOperationException
       3: dup
       4: invokespecial #2                  // Method java/lang/UnsupportedOperationException."<init>":()V
       7: athrow

  public default java.util.concurrent.CompletableFuture<software.amazon.awssdk.services.m2.model.StopApplicationResponse> stopApplication(java.util.function.Consumer<software.amazon.awssdk.services.m2.model.StopApplicationRequest$Builder>);
    Code:
       0: aload_0
       1: invokestatic  #174                // Method software/amazon/awssdk/services/m2/model/StopApplicationRequest.builder:()Lsoftware/amazon/awssdk/services/m2/model/StopApplicationRequest$Builder;
       4: aload_1
       5: invokeinterface #175,  2          // InterfaceMethod software/amazon/awssdk/services/m2/model/StopApplicationRequest$Builder.applyMutation:(Ljava/util/function/Consumer;)Lsoftware/amazon/awssdk/utils/builder/SdkBuilder;
      10: checkcast     #176                // class software/amazon/awssdk/services/m2/model/StopApplicationRequest$Builder
      13: invokeinterface #177,  1          // InterfaceMethod software/amazon/awssdk/services/m2/model/StopApplicationRequest$Builder.build:()Ljava/lang/Object;
      18: checkcast     #178                // class software/amazon/awssdk/services/m2/model/StopApplicationRequest
      21: invokeinterface #179,  2          // InterfaceMethod stopApplication:(Lsoftware/amazon/awssdk/services/m2/model/StopApplicationRequest;)Ljava/util/concurrent/CompletableFuture;
      26: areturn

  public default java.util.concurrent.CompletableFuture<software.amazon.awssdk.services.m2.model.TagResourceResponse> tagResource(software.amazon.awssdk.services.m2.model.TagResourceRequest);
    Code:
       0: new           #1                  // class java/lang/UnsupportedOperationException
       3: dup
       4: invokespecial #2                  // Method java/lang/UnsupportedOperationException."<init>":()V
       7: athrow

  public default java.util.concurrent.CompletableFuture<software.amazon.awssdk.services.m2.model.TagResourceResponse> tagResource(java.util.function.Consumer<software.amazon.awssdk.services.m2.model.TagResourceRequest$Builder>);
    Code:
       0: aload_0
       1: invokestatic  #180                // Method software/amazon/awssdk/services/m2/model/TagResourceRequest.builder:()Lsoftware/amazon/awssdk/services/m2/model/TagResourceRequest$Builder;
       4: aload_1
       5: invokeinterface #181,  2          // InterfaceMethod software/amazon/awssdk/services/m2/model/TagResourceRequest$Builder.applyMutation:(Ljava/util/function/Consumer;)Lsoftware/amazon/awssdk/utils/builder/SdkBuilder;
      10: checkcast     #182                // class software/amazon/awssdk/services/m2/model/TagResourceRequest$Builder
      13: invokeinterface #183,  1          // InterfaceMethod software/amazon/awssdk/services/m2/model/TagResourceRequest$Builder.build:()Ljava/lang/Object;
      18: checkcast     #184                // class software/amazon/awssdk/services/m2/model/TagResourceRequest
      21: invokeinterface #185,  2          // InterfaceMethod tagResource:(Lsoftware/amazon/awssdk/services/m2/model/TagResourceRequest;)Ljava/util/concurrent/CompletableFuture;
      26: areturn

  public default java.util.concurrent.CompletableFuture<software.amazon.awssdk.services.m2.model.UntagResourceResponse> untagResource(software.amazon.awssdk.services.m2.model.UntagResourceRequest);
    Code:
       0: new           #1                  // class java/lang/UnsupportedOperationException
       3: dup
       4: invokespecial #2                  // Method java/lang/UnsupportedOperationException."<init>":()V
       7: athrow

  public default java.util.concurrent.CompletableFuture<software.amazon.awssdk.services.m2.model.UntagResourceResponse> untagResource(java.util.function.Consumer<software.amazon.awssdk.services.m2.model.UntagResourceRequest$Builder>);
    Code:
       0: aload_0
       1: invokestatic  #186                // Method software/amazon/awssdk/services/m2/model/UntagResourceRequest.builder:()Lsoftware/amazon/awssdk/services/m2/model/UntagResourceRequest$Builder;
       4: aload_1
       5: invokeinterface #187,  2          // InterfaceMethod software/amazon/awssdk/services/m2/model/UntagResourceRequest$Builder.applyMutation:(Ljava/util/function/Consumer;)Lsoftware/amazon/awssdk/utils/builder/SdkBuilder;
      10: checkcast     #188                // class software/amazon/awssdk/services/m2/model/UntagResourceRequest$Builder
      13: invokeinterface #189,  1          // InterfaceMethod software/amazon/awssdk/services/m2/model/UntagResourceRequest$Builder.build:()Ljava/lang/Object;
      18: checkcast     #190                // class software/amazon/awssdk/services/m2/model/UntagResourceRequest
      21: invokeinterface #191,  2          // InterfaceMethod untagResource:(Lsoftware/amazon/awssdk/services/m2/model/UntagResourceRequest;)Ljava/util/concurrent/CompletableFuture;
      26: areturn

  public default java.util.concurrent.CompletableFuture<software.amazon.awssdk.services.m2.model.UpdateApplicationResponse> updateApplication(software.amazon.awssdk.services.m2.model.UpdateApplicationRequest);
    Code:
       0: new           #1                  // class java/lang/UnsupportedOperationException
       3: dup
       4: invokespecial #2                  // Method java/lang/UnsupportedOperationException."<init>":()V
       7: athrow

  public default java.util.concurrent.CompletableFuture<software.amazon.awssdk.services.m2.model.UpdateApplicationResponse> updateApplication(java.util.function.Consumer<software.amazon.awssdk.services.m2.model.UpdateApplicationRequest$Builder>);
    Code:
       0: aload_0
       1: invokestatic  #192                // Method software/amazon/awssdk/services/m2/model/UpdateApplicationRequest.builder:()Lsoftware/amazon/awssdk/services/m2/model/UpdateApplicationRequest$Builder;
       4: aload_1
       5: invokeinterface #193,  2          // InterfaceMethod software/amazon/awssdk/services/m2/model/UpdateApplicationRequest$Builder.applyMutation:(Ljava/util/function/Consumer;)Lsoftware/amazon/awssdk/utils/builder/SdkBuilder;
      10: checkcast     #194                // class software/amazon/awssdk/services/m2/model/UpdateApplicationRequest$Builder
      13: invokeinterface #195,  1          // InterfaceMethod software/amazon/awssdk/services/m2/model/UpdateApplicationRequest$Builder.build:()Ljava/lang/Object;
      18: checkcast     #196                // class software/amazon/awssdk/services/m2/model/UpdateApplicationRequest
      21: invokeinterface #197,  2          // InterfaceMethod updateApplication:(Lsoftware/amazon/awssdk/services/m2/model/UpdateApplicationRequest;)Ljava/util/concurrent/CompletableFuture;
      26: areturn

  public default java.util.concurrent.CompletableFuture<software.amazon.awssdk.services.m2.model.UpdateEnvironmentResponse> updateEnvironment(software.amazon.awssdk.services.m2.model.UpdateEnvironmentRequest);
    Code:
       0: new           #1                  // class java/lang/UnsupportedOperationException
       3: dup
       4: invokespecial #2                  // Method java/lang/UnsupportedOperationException."<init>":()V
       7: athrow

  public default java.util.concurrent.CompletableFuture<software.amazon.awssdk.services.m2.model.UpdateEnvironmentResponse> updateEnvironment(java.util.function.Consumer<software.amazon.awssdk.services.m2.model.UpdateEnvironmentRequest$Builder>);
    Code:
       0: aload_0
       1: invokestatic  #198                // Method software/amazon/awssdk/services/m2/model/UpdateEnvironmentRequest.builder:()Lsoftware/amazon/awssdk/services/m2/model/UpdateEnvironmentRequest$Builder;
       4: aload_1
       5: invokeinterface #199,  2          // InterfaceMethod software/amazon/awssdk/services/m2/model/UpdateEnvironmentRequest$Builder.applyMutation:(Ljava/util/function/Consumer;)Lsoftware/amazon/awssdk/utils/builder/SdkBuilder;
      10: checkcast     #200                // class software/amazon/awssdk/services/m2/model/UpdateEnvironmentRequest$Builder
      13: invokeinterface #201,  1          // InterfaceMethod software/amazon/awssdk/services/m2/model/UpdateEnvironmentRequest$Builder.build:()Ljava/lang/Object;
      18: checkcast     #202                // class software/amazon/awssdk/services/m2/model/UpdateEnvironmentRequest
      21: invokeinterface #203,  2          // InterfaceMethod updateEnvironment:(Lsoftware/amazon/awssdk/services/m2/model/UpdateEnvironmentRequest;)Ljava/util/concurrent/CompletableFuture;
      26: areturn

  public default software.amazon.awssdk.services.m2.M2ServiceClientConfiguration serviceClientConfiguration();
    Code:
       0: new           #1                  // class java/lang/UnsupportedOperationException
       3: dup
       4: invokespecial #2                  // Method java/lang/UnsupportedOperationException."<init>":()V
       7: athrow

  public static software.amazon.awssdk.services.m2.M2AsyncClient create();
    Code:
       0: invokestatic  #204                // InterfaceMethod builder:()Lsoftware/amazon/awssdk/services/m2/M2AsyncClientBuilder;
       3: invokeinterface #205,  1          // InterfaceMethod software/amazon/awssdk/services/m2/M2AsyncClientBuilder.build:()Ljava/lang/Object;
       8: checkcast     #206                // class software/amazon/awssdk/services/m2/M2AsyncClient
      11: areturn

  public static software.amazon.awssdk.services.m2.M2AsyncClientBuilder builder();
    Code:
       0: new           #207                // class software/amazon/awssdk/services/m2/DefaultM2AsyncClientBuilder
       3: dup
       4: invokespecial #208                // Method software/amazon/awssdk/services/m2/DefaultM2AsyncClientBuilder."<init>":()V
       7: areturn

  public default software.amazon.awssdk.awscore.AwsServiceClientConfiguration serviceClientConfiguration();
    Code:
       0: aload_0
       1: invokeinterface #209,  1          // InterfaceMethod serviceClientConfiguration:()Lsoftware/amazon/awssdk/services/m2/M2ServiceClientConfiguration;
       6: areturn

  public default software.amazon.awssdk.core.SdkServiceClientConfiguration serviceClientConfiguration();
    Code:
       0: aload_0
       1: invokeinterface #209,  1          // InterfaceMethod serviceClientConfiguration:()Lsoftware/amazon/awssdk/services/m2/M2ServiceClientConfiguration;
       6: areturn
}
