Compiled from "DelegatingCustomizer.java"
public abstract class org.codehaus.groovy.control.customizers.DelegatingCustomizer extends org.codehaus.groovy.control.customizers.CompilationCustomizer {
  protected final org.codehaus.groovy.control.customizers.CompilationCustomizer delegate;

  public org.codehaus.groovy.control.customizers.DelegatingCustomizer(org.codehaus.groovy.control.customizers.CompilationCustomizer);
    Code:
       0: aload_0
       1: aload_1
       2: invokevirtual #13                 // Method org/codehaus/groovy/control/customizers/CompilationCustomizer.getPhase:()Lorg/codehaus/groovy/control/CompilePhase;
       5: invokespecial #16                 // Method org/codehaus/groovy/control/customizers/CompilationCustomizer."<init>":(Lorg/codehaus/groovy/control/CompilePhase;)V
       8: aload_0
       9: aload_1
      10: putfield      #18                 // Field delegate:Lorg/codehaus/groovy/control/customizers/CompilationCustomizer;
      13: return

  public void call(org.codehaus.groovy.control.SourceUnit, org.codehaus.groovy.classgen.GeneratorContext, org.codehaus.groovy.ast.ClassNode) throws org.codehaus.groovy.control.CompilationFailedException;
    Code:
       0: aload_0
       1: getfield      #18                 // Field delegate:Lorg/codehaus/groovy/control/customizers/CompilationCustomizer;
       4: aload_1
       5: aload_2
       6: aload_3
       7: invokevirtual #26                 // Method org/codehaus/groovy/control/customizers/CompilationCustomizer.call:(Lorg/codehaus/groovy/control/SourceUnit;Lorg/codehaus/groovy/classgen/GeneratorContext;Lorg/codehaus/groovy/ast/ClassNode;)V
      10: return
}
