Compiled from "PermissionEntry.java"
final class software.amazon.awssdk.services.grafana.model.PermissionEntry$BuilderImpl implements software.amazon.awssdk.services.grafana.model.PermissionEntry$Builder {
  private java.lang.String role;

  private software.amazon.awssdk.services.grafana.model.User user;

  private software.amazon.awssdk.services.grafana.model.PermissionEntry$BuilderImpl();
    Code:
       0: aload_0
       1: invokespecial #5                  // Method java/lang/Object."<init>":()V
       4: return

  private software.amazon.awssdk.services.grafana.model.PermissionEntry$BuilderImpl(software.amazon.awssdk.services.grafana.model.PermissionEntry);
    Code:
       0: aload_0
       1: invokespecial #5                  // Method java/lang/Object."<init>":()V
       4: aload_0
       5: aload_1
       6: invokestatic  #6                  // Method software/amazon/awssdk/services/grafana/model/PermissionEntry.access$400:(Lsoftware/amazon/awssdk/services/grafana/model/PermissionEntry;)Ljava/lang/String;
       9: invokevirtual #7                  // Method role:(Ljava/lang/String;)Lsoftware/amazon/awssdk/services/grafana/model/PermissionEntry$Builder;
      12: pop
      13: aload_0
      14: aload_1
      15: invokestatic  #8                  // Method software/amazon/awssdk/services/grafana/model/PermissionEntry.access$500:(Lsoftware/amazon/awssdk/services/grafana/model/PermissionEntry;)Lsoftware/amazon/awssdk/services/grafana/model/User;
      18: invokevirtual #9                  // Method user:(Lsoftware/amazon/awssdk/services/grafana/model/User;)Lsoftware/amazon/awssdk/services/grafana/model/PermissionEntry$Builder;
      21: pop
      22: return

  public final java.lang.String getRole();
    Code:
       0: aload_0
       1: getfield      #4                  // Field role:Ljava/lang/String;
       4: areturn

  public final void setRole(java.lang.String);
    Code:
       0: aload_0
       1: aload_1
       2: putfield      #4                  // Field role:Ljava/lang/String;
       5: return

  public final software.amazon.awssdk.services.grafana.model.PermissionEntry$Builder role(java.lang.String);
    Code:
       0: aload_0
       1: aload_1
       2: putfield      #4                  // Field role:Ljava/lang/String;
       5: aload_0
       6: areturn

  public final software.amazon.awssdk.services.grafana.model.PermissionEntry$Builder role(software.amazon.awssdk.services.grafana.model.Role);
    Code:
       0: aload_0
       1: aload_1
       2: ifnonnull     9
       5: aconst_null
       6: goto          13
       9: aload_1
      10: invokevirtual #10                 // Method software/amazon/awssdk/services/grafana/model/Role.toString:()Ljava/lang/String;
      13: invokevirtual #7                  // Method role:(Ljava/lang/String;)Lsoftware/amazon/awssdk/services/grafana/model/PermissionEntry$Builder;
      16: pop
      17: aload_0
      18: areturn

  public final software.amazon.awssdk.services.grafana.model.User$Builder getUser();
    Code:
       0: aload_0
       1: getfield      #3                  // Field user:Lsoftware/amazon/awssdk/services/grafana/model/User;
       4: ifnull        17
       7: aload_0
       8: getfield      #3                  // Field user:Lsoftware/amazon/awssdk/services/grafana/model/User;
      11: invokevirtual #11                 // Method software/amazon/awssdk/services/grafana/model/User.toBuilder:()Lsoftware/amazon/awssdk/services/grafana/model/User$Builder;
      14: goto          18
      17: aconst_null
      18: areturn

  public final void setUser(software.amazon.awssdk.services.grafana.model.User$BuilderImpl);
    Code:
       0: aload_0
       1: aload_1
       2: ifnull        12
       5: aload_1
       6: invokevirtual #12                 // Method software/amazon/awssdk/services/grafana/model/User$BuilderImpl.build:()Lsoftware/amazon/awssdk/services/grafana/model/User;
       9: goto          13
      12: aconst_null
      13: putfield      #3                  // Field user:Lsoftware/amazon/awssdk/services/grafana/model/User;
      16: return

  public final software.amazon.awssdk.services.grafana.model.PermissionEntry$Builder user(software.amazon.awssdk.services.grafana.model.User);
    Code:
       0: aload_0
       1: aload_1
       2: putfield      #3                  // Field user:Lsoftware/amazon/awssdk/services/grafana/model/User;
       5: aload_0
       6: areturn

  public software.amazon.awssdk.services.grafana.model.PermissionEntry build();
    Code:
       0: new           #13                 // class software/amazon/awssdk/services/grafana/model/PermissionEntry
       3: dup
       4: aload_0
       5: aconst_null
       6: invokespecial #14                 // Method software/amazon/awssdk/services/grafana/model/PermissionEntry."<init>":(Lsoftware/amazon/awssdk/services/grafana/model/PermissionEntry$BuilderImpl;Lsoftware/amazon/awssdk/services/grafana/model/PermissionEntry$1;)V
       9: areturn

  public java.util.List<software.amazon.awssdk.core.SdkField<?>> sdkFields();
    Code:
       0: invokestatic  #15                 // Method software/amazon/awssdk/services/grafana/model/PermissionEntry.access$700:()Ljava/util/List;
       3: areturn

  public java.lang.Object build();
    Code:
       0: aload_0
       1: invokevirtual #16                 // Method build:()Lsoftware/amazon/awssdk/services/grafana/model/PermissionEntry;
       4: areturn

  static java.lang.String access$000(software.amazon.awssdk.services.grafana.model.PermissionEntry$BuilderImpl);
    Code:
       0: aload_0
       1: getfield      #4                  // Field role:Ljava/lang/String;
       4: areturn

  static software.amazon.awssdk.services.grafana.model.User access$100(software.amazon.awssdk.services.grafana.model.PermissionEntry$BuilderImpl);
    Code:
       0: aload_0
       1: getfield      #3                  // Field user:Lsoftware/amazon/awssdk/services/grafana/model/User;
       4: areturn

  software.amazon.awssdk.services.grafana.model.PermissionEntry$BuilderImpl(software.amazon.awssdk.services.grafana.model.PermissionEntry, software.amazon.awssdk.services.grafana.model.PermissionEntry$1);
    Code:
       0: aload_0
       1: aload_1
       2: invokespecial #2                  // Method "<init>":(Lsoftware/amazon/awssdk/services/grafana/model/PermissionEntry;)V
       5: return

  software.amazon.awssdk.services.grafana.model.PermissionEntry$BuilderImpl(software.amazon.awssdk.services.grafana.model.PermissionEntry$1);
    Code:
       0: aload_0
       1: invokespecial #1                  // Method "<init>":()V
       4: return
}
