Compiled from "WorkspaceDescription.java"
public interface software.amazon.awssdk.services.grafana.model.WorkspaceDescription$Builder extends software.amazon.awssdk.core.SdkPojo, software.amazon.awssdk.utils.builder.CopyableBuilder<software.amazon.awssdk.services.grafana.model.WorkspaceDescription$Builder, software.amazon.awssdk.services.grafana.model.WorkspaceDescription> {
  public abstract software.amazon.awssdk.services.grafana.model.WorkspaceDescription$Builder accountAccessType(java.lang.String);

  public abstract software.amazon.awssdk.services.grafana.model.WorkspaceDescription$Builder accountAccessType(software.amazon.awssdk.services.grafana.model.AccountAccessType);

  public abstract software.amazon.awssdk.services.grafana.model.WorkspaceDescription$Builder authentication(software.amazon.awssdk.services.grafana.model.AuthenticationSummary);

  public default software.amazon.awssdk.services.grafana.model.WorkspaceDescription$Builder authentication(java.util.function.Consumer<software.amazon.awssdk.services.grafana.model.AuthenticationSummary$Builder>);
    Code:
       0: aload_0
       1: invokestatic  #1                  // Method software/amazon/awssdk/services/grafana/model/AuthenticationSummary.builder:()Lsoftware/amazon/awssdk/services/grafana/model/AuthenticationSummary$Builder;
       4: aload_1
       5: invokeinterface #2,  2            // InterfaceMethod software/amazon/awssdk/services/grafana/model/AuthenticationSummary$Builder.applyMutation:(Ljava/util/function/Consumer;)Lsoftware/amazon/awssdk/utils/builder/SdkBuilder;
      10: checkcast     #3                  // class software/amazon/awssdk/services/grafana/model/AuthenticationSummary$Builder
      13: invokeinterface #4,  1            // InterfaceMethod software/amazon/awssdk/services/grafana/model/AuthenticationSummary$Builder.build:()Ljava/lang/Object;
      18: checkcast     #5                  // class software/amazon/awssdk/services/grafana/model/AuthenticationSummary
      21: invokeinterface #6,  2            // InterfaceMethod authentication:(Lsoftware/amazon/awssdk/services/grafana/model/AuthenticationSummary;)Lsoftware/amazon/awssdk/services/grafana/model/WorkspaceDescription$Builder;
      26: areturn

  public abstract software.amazon.awssdk.services.grafana.model.WorkspaceDescription$Builder created(java.time.Instant);

  public abstract software.amazon.awssdk.services.grafana.model.WorkspaceDescription$Builder dataSourcesWithStrings(java.util.Collection<java.lang.String>);

  public abstract software.amazon.awssdk.services.grafana.model.WorkspaceDescription$Builder dataSourcesWithStrings(java.lang.String...);

  public abstract software.amazon.awssdk.services.grafana.model.WorkspaceDescription$Builder dataSources(java.util.Collection<software.amazon.awssdk.services.grafana.model.DataSourceType>);

  public abstract software.amazon.awssdk.services.grafana.model.WorkspaceDescription$Builder dataSources(software.amazon.awssdk.services.grafana.model.DataSourceType...);

  public abstract software.amazon.awssdk.services.grafana.model.WorkspaceDescription$Builder description(java.lang.String);

  public abstract software.amazon.awssdk.services.grafana.model.WorkspaceDescription$Builder endpoint(java.lang.String);

  public abstract software.amazon.awssdk.services.grafana.model.WorkspaceDescription$Builder freeTrialConsumed(java.lang.Boolean);

  public abstract software.amazon.awssdk.services.grafana.model.WorkspaceDescription$Builder freeTrialExpiration(java.time.Instant);

  public abstract software.amazon.awssdk.services.grafana.model.WorkspaceDescription$Builder grafanaVersion(java.lang.String);

  public abstract software.amazon.awssdk.services.grafana.model.WorkspaceDescription$Builder id(java.lang.String);

  public abstract software.amazon.awssdk.services.grafana.model.WorkspaceDescription$Builder licenseExpiration(java.time.Instant);

  public abstract software.amazon.awssdk.services.grafana.model.WorkspaceDescription$Builder licenseType(java.lang.String);

  public abstract software.amazon.awssdk.services.grafana.model.WorkspaceDescription$Builder licenseType(software.amazon.awssdk.services.grafana.model.LicenseType);

  public abstract software.amazon.awssdk.services.grafana.model.WorkspaceDescription$Builder modified(java.time.Instant);

  public abstract software.amazon.awssdk.services.grafana.model.WorkspaceDescription$Builder name(java.lang.String);

  public abstract software.amazon.awssdk.services.grafana.model.WorkspaceDescription$Builder notificationDestinationsWithStrings(java.util.Collection<java.lang.String>);

  public abstract software.amazon.awssdk.services.grafana.model.WorkspaceDescription$Builder notificationDestinationsWithStrings(java.lang.String...);

  public abstract software.amazon.awssdk.services.grafana.model.WorkspaceDescription$Builder notificationDestinations(java.util.Collection<software.amazon.awssdk.services.grafana.model.NotificationDestinationType>);

  public abstract software.amazon.awssdk.services.grafana.model.WorkspaceDescription$Builder notificationDestinations(software.amazon.awssdk.services.grafana.model.NotificationDestinationType...);

  public abstract software.amazon.awssdk.services.grafana.model.WorkspaceDescription$Builder organizationRoleName(java.lang.String);

  public abstract software.amazon.awssdk.services.grafana.model.WorkspaceDescription$Builder organizationalUnits(java.util.Collection<java.lang.String>);

  public abstract software.amazon.awssdk.services.grafana.model.WorkspaceDescription$Builder organizationalUnits(java.lang.String...);

  public abstract software.amazon.awssdk.services.grafana.model.WorkspaceDescription$Builder permissionType(java.lang.String);

  public abstract software.amazon.awssdk.services.grafana.model.WorkspaceDescription$Builder permissionType(software.amazon.awssdk.services.grafana.model.PermissionType);

  public abstract software.amazon.awssdk.services.grafana.model.WorkspaceDescription$Builder stackSetName(java.lang.String);

  public abstract software.amazon.awssdk.services.grafana.model.WorkspaceDescription$Builder status(java.lang.String);

  public abstract software.amazon.awssdk.services.grafana.model.WorkspaceDescription$Builder status(software.amazon.awssdk.services.grafana.model.WorkspaceStatus);

  public abstract software.amazon.awssdk.services.grafana.model.WorkspaceDescription$Builder tags(java.util.Map<java.lang.String, java.lang.String>);

  public abstract software.amazon.awssdk.services.grafana.model.WorkspaceDescription$Builder workspaceRoleArn(java.lang.String);
}
