Compiled from "PulsarLedgerManagerFactory.java"
public class org.apache.pulsar.metadata.bookkeeper.PulsarLedgerManagerFactory implements org.apache.bookkeeper.meta.LedgerManagerFactory {
  private static final org.slf4j.Logger log;

  private static final int CUR_VERSION;

  private org.apache.bookkeeper.conf.AbstractConfiguration conf;

  private org.apache.pulsar.metadata.api.extended.MetadataStoreExtended store;

  private java.lang.String ledgerRootPath;

  public org.apache.pulsar.metadata.bookkeeper.PulsarLedgerManagerFactory();
    Code:
       0: aload_0
       1: invokespecial #1                  // Method java/lang/Object."<init>":()V
       4: return

  public org.apache.bookkeeper.meta.LedgerManagerFactory initialize(org.apache.bookkeeper.conf.AbstractConfiguration, org.apache.bookkeeper.meta.LayoutManager, int) throws java.io.IOException;
    Code:
       0: aload_2
       1: instanceof    #2                  // class org/apache/pulsar/metadata/bookkeeper/PulsarLayoutManager
       4: invokestatic  #3                  // Method com/google/common/base/Preconditions.checkArgument:(Z)V
       7: aload_2
       8: checkcast     #2                  // class org/apache/pulsar/metadata/bookkeeper/PulsarLayoutManager
      11: astore        4
      13: iconst_1
      14: iload_3
      15: if_icmpeq     45
      18: new           #5                  // class java/io/IOException
      21: dup
      22: new           #6                  // class java/lang/StringBuilder
      25: dup
      26: invokespecial #7                  // Method java/lang/StringBuilder."<init>":()V
      29: ldc           #8                  // String Incompatible layout version found :
      31: invokevirtual #9                  // Method java/lang/StringBuilder.append:(Ljava/lang/String;)Ljava/lang/StringBuilder;
      34: iload_3
      35: invokevirtual #10                 // Method java/lang/StringBuilder.append:(I)Ljava/lang/StringBuilder;
      38: invokevirtual #11                 // Method java/lang/StringBuilder.toString:()Ljava/lang/String;
      41: invokespecial #12                 // Method java/io/IOException."<init>":(Ljava/lang/String;)V
      44: athrow
      45: aload_0
      46: aload_1
      47: putfield      #13                 // Field conf:Lorg/apache/bookkeeper/conf/AbstractConfiguration;
      50: aload_0
      51: aload         4
      53: invokevirtual #14                 // Method org/apache/pulsar/metadata/bookkeeper/PulsarLayoutManager.getStore:()Lorg/apache/pulsar/metadata/api/extended/MetadataStoreExtended;
      56: putfield      #15                 // Field store:Lorg/apache/pulsar/metadata/api/extended/MetadataStoreExtended;
      59: aload_0
      60: aload         4
      62: invokevirtual #16                 // Method org/apache/pulsar/metadata/bookkeeper/PulsarLayoutManager.getLedgersRootPath:()Ljava/lang/String;
      65: putfield      #17                 // Field ledgerRootPath:Ljava/lang/String;
      68: aload_0
      69: areturn

  public void close() throws java.io.IOException;
    Code:
       0: return

  public int getCurrentVersion();
    Code:
       0: iconst_1
       1: ireturn

  public org.apache.bookkeeper.meta.LedgerIdGenerator newLedgerIdGenerator();
    Code:
       0: new           #18                 // class org/apache/pulsar/metadata/bookkeeper/PulsarLedgerIdGenerator
       3: dup
       4: aload_0
       5: getfield      #15                 // Field store:Lorg/apache/pulsar/metadata/api/extended/MetadataStoreExtended;
       8: aload_0
       9: getfield      #17                 // Field ledgerRootPath:Ljava/lang/String;
      12: invokespecial #19                 // Method org/apache/pulsar/metadata/bookkeeper/PulsarLedgerIdGenerator."<init>":(Lorg/apache/pulsar/metadata/api/extended/MetadataStoreExtended;Ljava/lang/String;)V
      15: areturn

  public org.apache.bookkeeper.meta.LedgerManager newLedgerManager();
    Code:
       0: new           #20                 // class org/apache/pulsar/metadata/bookkeeper/PulsarLedgerManager
       3: dup
       4: aload_0
       5: getfield      #15                 // Field store:Lorg/apache/pulsar/metadata/api/extended/MetadataStoreExtended;
       8: aload_0
       9: getfield      #17                 // Field ledgerRootPath:Ljava/lang/String;
      12: invokespecial #21                 // Method org/apache/pulsar/metadata/bookkeeper/PulsarLedgerManager."<init>":(Lorg/apache/pulsar/metadata/api/MetadataStore;Ljava/lang/String;)V
      15: areturn

  public org.apache.bookkeeper.meta.LedgerUnderreplicationManager newLedgerUnderreplicationManager() throws org.apache.bookkeeper.replication.ReplicationException$CompatibilityException;
    Code:
       0: new           #22                 // class org/apache/pulsar/metadata/bookkeeper/PulsarLedgerUnderreplicationManager
       3: dup
       4: aload_0
       5: getfield      #13                 // Field conf:Lorg/apache/bookkeeper/conf/AbstractConfiguration;
       8: aload_0
       9: getfield      #15                 // Field store:Lorg/apache/pulsar/metadata/api/extended/MetadataStoreExtended;
      12: aload_0
      13: getfield      #17                 // Field ledgerRootPath:Ljava/lang/String;
      16: invokespecial #23                 // Method org/apache/pulsar/metadata/bookkeeper/PulsarLedgerUnderreplicationManager."<init>":(Lorg/apache/bookkeeper/conf/AbstractConfiguration;Lorg/apache/pulsar/metadata/api/extended/MetadataStoreExtended;Ljava/lang/String;)V
      19: areturn

  public org.apache.bookkeeper.meta.LedgerAuditorManager newLedgerAuditorManager() throws java.io.IOException, java.lang.InterruptedException;
    Code:
       0: new           #24                 // class org/apache/pulsar/metadata/bookkeeper/PulsarLedgerAuditorManager
       3: dup
       4: aload_0
       5: getfield      #15                 // Field store:Lorg/apache/pulsar/metadata/api/extended/MetadataStoreExtended;
       8: aload_0
       9: getfield      #17                 // Field ledgerRootPath:Ljava/lang/String;
      12: invokespecial #25                 // Method org/apache/pulsar/metadata/bookkeeper/PulsarLedgerAuditorManager."<init>":(Lorg/apache/pulsar/metadata/api/extended/MetadataStoreExtended;Ljava/lang/String;)V
      15: areturn

  public void format(org.apache.bookkeeper.conf.AbstractConfiguration<?>, org.apache.bookkeeper.meta.LayoutManager) throws java.lang.InterruptedException, java.io.IOException;
    Code:
       0: return

  public boolean validateAndNukeExistingCluster(org.apache.bookkeeper.conf.AbstractConfiguration<?>, org.apache.bookkeeper.meta.LayoutManager) throws java.lang.InterruptedException, java.io.IOException;
    Code:
       0: new           #20                 // class org/apache/pulsar/metadata/bookkeeper/PulsarLedgerManager
       3: dup
       4: aload_0
       5: getfield      #15                 // Field store:Lorg/apache/pulsar/metadata/api/extended/MetadataStoreExtended;
       8: aload_0
       9: getfield      #17                 // Field ledgerRootPath:Ljava/lang/String;
      12: invokespecial #21                 // Method org/apache/pulsar/metadata/bookkeeper/PulsarLedgerManager."<init>":(Lorg/apache/pulsar/metadata/api/MetadataStore;Ljava/lang/String;)V
      15: astore_3
      16: aload_0
      17: getfield      #15                 // Field store:Lorg/apache/pulsar/metadata/api/extended/MetadataStoreExtended;
      20: aload_0
      21: getfield      #17                 // Field ledgerRootPath:Ljava/lang/String;
      24: invokeinterface #26,  2           // InterfaceMethod org/apache/pulsar/metadata/api/extended/MetadataStoreExtended.getChildren:(Ljava/lang/String;)Ljava/util/concurrent/CompletableFuture;
      29: invokevirtual #27                 // Method java/util/concurrent/CompletableFuture.join:()Ljava/lang/Object;
      32: checkcast     #28                 // class java/util/List
      35: astore        4
      37: aload         4
      39: invokeinterface #29,  1           // InterfaceMethod java/util/List.iterator:()Ljava/util/Iterator;
      44: astore        5
      46: aload         5
      48: invokeinterface #30,  1           // InterfaceMethod java/util/Iterator.hasNext:()Z
      53: ifeq          127
      56: aload         5
      58: invokeinterface #31,  1           // InterfaceMethod java/util/Iterator.next:()Ljava/lang/Object;
      63: checkcast     #32                 // class java/lang/String
      66: astore        6
      68: aload         6
      70: invokestatic  #33                 // Method org/apache/bookkeeper/meta/AbstractZkLedgerManager.isSpecialZnode:(Ljava/lang/String;)Z
      73: ifne          124
      76: aload_3
      77: aload         6
      79: invokevirtual #34                 // Method org/apache/pulsar/metadata/bookkeeper/PulsarLedgerManager.isLedgerParentNode:(Ljava/lang/String;)Z
      82: ifne          124
      85: getstatic     #35                 // Field log:Lorg/slf4j/Logger;
      88: ldc           #36                 // String Found unexpected node : {} under ledgersRootPath : {} so exiting nuke operation
      90: aload         6
      92: aload_0
      93: getfield      #17                 // Field ledgerRootPath:Ljava/lang/String;
      96: invokeinterface #37,  4           // InterfaceMethod org/slf4j/Logger.error:(Ljava/lang/String;Ljava/lang/Object;Ljava/lang/Object;)V
     101: iconst_0
     102: istore        7
     104: aload_3
     105: invokestatic  #38                 // Method java/util/Collections.singletonList:(Ljava/lang/Object;)Ljava/util/List;
     108: iconst_0
     109: invokeinterface #39,  2           // InterfaceMethod java/util/List.get:(I)Ljava/lang/Object;
     114: ifnull        121
     117: aload_3
     118: invokevirtual #40                 // Method org/apache/pulsar/metadata/bookkeeper/PulsarLedgerManager.close:()V
     121: iload         7
     123: ireturn
     124: goto          46
     127: aload_0
     128: aload_1
     129: aload_2
     130: invokevirtual #41                 // Method format:(Lorg/apache/bookkeeper/conf/AbstractConfiguration;Lorg/apache/bookkeeper/meta/LayoutManager;)V
     133: aload_0
     134: getfield      #15                 // Field store:Lorg/apache/pulsar/metadata/api/extended/MetadataStoreExtended;
     137: aload_0
     138: getfield      #17                 // Field ledgerRootPath:Ljava/lang/String;
     141: invokeinterface #26,  2           // InterfaceMethod org/apache/pulsar/metadata/api/extended/MetadataStoreExtended.getChildren:(Ljava/lang/String;)Ljava/util/concurrent/CompletableFuture;
     146: invokevirtual #27                 // Method java/util/concurrent/CompletableFuture.join:()Ljava/lang/Object;
     149: checkcast     #28                 // class java/util/List
     152: invokeinterface #29,  1           // InterfaceMethod java/util/List.iterator:()Ljava/util/Iterator;
     157: astore        5
     159: aload         5
     161: invokeinterface #30,  1           // InterfaceMethod java/util/Iterator.hasNext:()Z
     166: ifeq          274
     169: aload         5
     171: invokeinterface #31,  1           // InterfaceMethod java/util/Iterator.next:()Ljava/lang/Object;
     176: checkcast     #32                 // class java/lang/String
     179: astore        6
     181: aload         6
     183: invokestatic  #33                 // Method org/apache/bookkeeper/meta/AbstractZkLedgerManager.isSpecialZnode:(Ljava/lang/String;)Z
     186: ifeq          232
     189: aload_0
     190: getfield      #15                 // Field store:Lorg/apache/pulsar/metadata/api/extended/MetadataStoreExtended;
     193: new           #6                  // class java/lang/StringBuilder
     196: dup
     197: invokespecial #7                  // Method java/lang/StringBuilder."<init>":()V
     200: aload_0
     201: getfield      #17                 // Field ledgerRootPath:Ljava/lang/String;
     204: invokevirtual #9                  // Method java/lang/StringBuilder.append:(Ljava/lang/String;)Ljava/lang/StringBuilder;
     207: ldc           #42                 // String /
     209: invokevirtual #9                  // Method java/lang/StringBuilder.append:(Ljava/lang/String;)Ljava/lang/StringBuilder;
     212: aload         6
     214: invokevirtual #9                  // Method java/lang/StringBuilder.append:(Ljava/lang/String;)Ljava/lang/StringBuilder;
     217: invokevirtual #11                 // Method java/lang/StringBuilder.toString:()Ljava/lang/String;
     220: invokeinterface #43,  2           // InterfaceMethod org/apache/pulsar/metadata/api/extended/MetadataStoreExtended.deleteRecursive:(Ljava/lang/String;)Ljava/util/concurrent/CompletableFuture;
     225: invokevirtual #27                 // Method java/util/concurrent/CompletableFuture.join:()Ljava/lang/Object;
     228: pop
     229: goto          271
     232: getstatic     #35                 // Field log:Lorg/slf4j/Logger;
     235: ldc           #36                 // String Found unexpected node : {} under ledgersRootPath : {} so exiting nuke operation
     237: aload         6
     239: aload_0
     240: getfield      #17                 // Field ledgerRootPath:Ljava/lang/String;
     243: invokeinterface #37,  4           // InterfaceMethod org/slf4j/Logger.error:(Ljava/lang/String;Ljava/lang/Object;Ljava/lang/Object;)V
     248: iconst_0
     249: istore        7
     251: aload_3
     252: invokestatic  #38                 // Method java/util/Collections.singletonList:(Ljava/lang/Object;)Ljava/util/List;
     255: iconst_0
     256: invokeinterface #39,  2           // InterfaceMethod java/util/List.get:(I)Ljava/lang/Object;
     261: ifnull        268
     264: aload_3
     265: invokevirtual #40                 // Method org/apache/pulsar/metadata/bookkeeper/PulsarLedgerManager.close:()V
     268: iload         7
     270: ireturn
     271: goto          159
     274: aload_0
     275: getfield      #15                 // Field store:Lorg/apache/pulsar/metadata/api/extended/MetadataStoreExtended;
     278: aload_0
     279: getfield      #17                 // Field ledgerRootPath:Ljava/lang/String;
     282: invokeinterface #43,  2           // InterfaceMethod org/apache/pulsar/metadata/api/extended/MetadataStoreExtended.deleteRecursive:(Ljava/lang/String;)Ljava/util/concurrent/CompletableFuture;
     287: invokevirtual #27                 // Method java/util/concurrent/CompletableFuture.join:()Ljava/lang/Object;
     290: pop
     291: getstatic     #35                 // Field log:Lorg/slf4j/Logger;
     294: ldc           #44                 // String Successfully nuked existing cluster
     296: invokeinterface #45,  2           // InterfaceMethod org/slf4j/Logger.info:(Ljava/lang/String;)V
     301: iconst_1
     302: istore        5
     304: aload_3
     305: invokestatic  #38                 // Method java/util/Collections.singletonList:(Ljava/lang/Object;)Ljava/util/List;
     308: iconst_0
     309: invokeinterface #39,  2           // InterfaceMethod java/util/List.get:(I)Ljava/lang/Object;
     314: ifnull        321
     317: aload_3
     318: invokevirtual #40                 // Method org/apache/pulsar/metadata/bookkeeper/PulsarLedgerManager.close:()V
     321: iload         5
     323: ireturn
     324: astore        8
     326: aload_3
     327: invokestatic  #38                 // Method java/util/Collections.singletonList:(Ljava/lang/Object;)Ljava/util/List;
     330: iconst_0
     331: invokeinterface #39,  2           // InterfaceMethod java/util/List.get:(I)Ljava/lang/Object;
     336: ifnull        343
     339: aload_3
     340: invokevirtual #40                 // Method org/apache/pulsar/metadata/bookkeeper/PulsarLedgerManager.close:()V
     343: aload         8
     345: athrow
    Exception table:
       from    to  target type
          16   104   324   any
         124   251   324   any
         271   304   324   any
         324   326   324   any

  static {};
    Code:
       0: ldc           #4                  // class org/apache/pulsar/metadata/bookkeeper/PulsarLedgerManagerFactory
       2: invokestatic  #46                 // Method org/slf4j/LoggerFactory.getLogger:(Ljava/lang/Class;)Lorg/slf4j/Logger;
       5: putstatic     #35                 // Field log:Lorg/slf4j/Logger;
       8: return
}
