Compiled from "AddablePersistenceUnit.java"
public class org.sakaiproject.springframework.orm.hibernate.AddablePersistenceUnit implements org.springframework.orm.jpa.persistenceunit.PersistenceUnitPostProcessor,org.springframework.context.ApplicationContextAware {
  private static final org.slf4j.Logger log;

  private org.springframework.context.ApplicationContext applicationContext;

  public org.sakaiproject.springframework.orm.hibernate.AddablePersistenceUnit();
    Code:
       0: aload_0
       1: invokespecial #1                  // Method java/lang/Object."<init>":()V
       4: return

  public void postProcessPersistenceUnitInfo(org.springframework.orm.jpa.persistenceunit.MutablePersistenceUnitInfo);
    Code:
       0: new           #2                  // class java/util/ArrayList
       3: dup
       4: invokespecial #3                  // Method java/util/ArrayList."<init>":()V
       7: astore_2
       8: aload_0
       9: getfield      #4                  // Field applicationContext:Lorg/springframework/context/ApplicationContext;
      12: ldc           #5                  // class org/sakaiproject/springframework/orm/hibernate/AdditionalHibernateMappings
      14: iconst_0
      15: iconst_0
      16: invokeinterface #6,  4            // InterfaceMethod org/springframework/context/ApplicationContext.getBeanNamesForType:(Ljava/lang/Class;ZZ)[Ljava/lang/String;
      21: astore_3
      22: aload_3
      23: astore        4
      25: aload         4
      27: arraylength
      28: istore        5
      30: iconst_0
      31: istore        6
      33: iload         6
      35: iload         5
      37: if_icmpge     74
      40: aload         4
      42: iload         6
      44: aaload
      45: astore        7
      47: aload_2
      48: aload_0
      49: getfield      #4                  // Field applicationContext:Lorg/springframework/context/ApplicationContext;
      52: aload         7
      54: invokeinterface #7,  2            // InterfaceMethod org/springframework/context/ApplicationContext.getBean:(Ljava/lang/String;)Ljava/lang/Object;
      59: checkcast     #5                  // class org/sakaiproject/springframework/orm/hibernate/AdditionalHibernateMappings
      62: invokeinterface #8,  2            // InterfaceMethod java/util/List.add:(Ljava/lang/Object;)Z
      67: pop
      68: iinc          6, 1
      71: goto          33
      74: aload_2
      75: invokestatic  #9                  // Method java/util/Collections.sort:(Ljava/util/List;)V
      78: aload_2
      79: aload_1
      80: invokedynamic #10,  0             // InvokeDynamic #0:accept:(Lorg/springframework/orm/jpa/persistenceunit/MutablePersistenceUnitInfo;)Ljava/util/function/Consumer;
      85: invokeinterface #11,  2           // InterfaceMethod java/util/List.forEach:(Ljava/util/function/Consumer;)V
      90: return

  public void setApplicationContext(org.springframework.context.ApplicationContext);
    Code:
       0: aload_0
       1: aload_1
       2: putfield      #4                  // Field applicationContext:Lorg/springframework/context/ApplicationContext;
       5: return

  private static void lambda$postProcessPersistenceUnitInfo$0(org.springframework.orm.jpa.persistenceunit.MutablePersistenceUnitInfo, org.sakaiproject.springframework.orm.hibernate.AdditionalHibernateMappings);
    Code:
       0: aload_1
       1: aload_0
       2: invokeinterface #12,  2           // InterfaceMethod org/sakaiproject/springframework/orm/hibernate/AdditionalHibernateMappings.processAdditionalUnit:(Lorg/springframework/orm/jpa/persistenceunit/MutablePersistenceUnitInfo;)V
       7: return

  static {};
    Code:
       0: ldc           #13                 // class org/sakaiproject/springframework/orm/hibernate/AddablePersistenceUnit
       2: invokestatic  #14                 // Method org/slf4j/LoggerFactory.getLogger:(Ljava/lang/Class;)Lorg/slf4j/Logger;
       5: putstatic     #15                 // Field log:Lorg/slf4j/Logger;
       8: return
}
