Compiled from "Attachments.java"
public final class org.jboss.as.server.deployment.Attachments {
  public static final org.jboss.as.server.deployment.AttachmentKey<org.jboss.as.server.deployment.AttachmentList<org.jboss.msc.service.ServiceName>> NEXT_PHASE_DEPS;

  public static final org.jboss.as.server.deployment.AttachmentKey<org.jboss.as.server.deployment.AttachmentList<org.jboss.as.server.deployment.AttachableDependency>> NEXT_PHASE_ATTACHABLE_DEPS;

  public static final org.jboss.as.server.deployment.AttachmentKey<java.util.Set<java.lang.String>> EXCLUDED_SUBSYSTEMS;

  public static final org.jboss.as.server.deployment.AttachmentKey<java.lang.String> RUNTIME_NAME;

  public static final org.jboss.as.server.deployment.AttachmentKey<java.lang.String> MANAGEMENT_NAME;

  public static final org.jboss.as.server.deployment.AttachmentKey<org.jboss.vfs.VirtualFile> DEPLOYMENT_CONTENTS;

  public static final org.jboss.as.server.deployment.AttachmentKey<org.jboss.as.controller.ServiceVerificationHandler> SERVICE_VERIFICATION_HANDLER;

  public static final org.jboss.as.server.deployment.AttachmentKey<java.lang.Boolean> ALLOW_PHASE_RESTART;

  public static final org.jboss.as.server.deployment.AttachmentKey<org.jboss.as.server.deployment.DeploymentUnitPhaseBuilder> DEPLOYMENT_UNIT_PHASE_BUILDER;

  public static final org.jboss.as.server.deployment.AttachmentKey<org.jboss.as.controller.services.path.PathManager> PATH_MANAGER;

  public static final org.jboss.as.server.deployment.AttachmentKey<org.jboss.as.server.deploymentoverlay.DeploymentOverlayIndex> DEPLOYMENT_OVERLAY_INDEX;

  public static final org.jboss.as.server.deployment.AttachmentKey<org.jboss.as.server.deployment.module.ResourceRoot> DEPLOYMENT_ROOT;

  public static final org.jboss.as.server.deployment.AttachmentKey<org.jboss.as.server.deployment.module.ModuleSpecification> MODULE_SPECIFICATION;

  public static final org.jboss.as.server.deployment.AttachmentKey<org.jboss.as.server.deployment.AttachmentList<org.jboss.as.server.deployment.module.ResourceRoot>> RESOURCE_ROOTS;

  public static final org.jboss.as.server.deployment.AttachmentKey<java.util.jar.Manifest> MANIFEST;

  public static final org.jboss.as.server.deployment.AttachmentKey<java.util.jar.Manifest> OSGI_MANIFEST;

  public static final org.jboss.as.server.deployment.AttachmentKey<org.jboss.as.server.deployment.AttachmentList<org.jboss.modules.ModuleIdentifier>> CLASS_PATH_ENTRIES;

  public static final org.jboss.as.server.deployment.AttachmentKey<org.jboss.as.server.deployment.AttachmentList<org.jboss.as.server.deployment.module.ResourceRoot>> CLASS_PATH_RESOURCE_ROOTS;

  public static final org.jboss.as.server.deployment.AttachmentKey<org.jboss.as.server.deployment.AttachmentList<org.jboss.as.server.deployment.module.ExtensionListEntry>> EXTENSION_LIST_ENTRIES;

  public static final org.jboss.as.server.deployment.AttachmentKey<org.jboss.as.server.deployment.module.ExtensionInfo> EXTENSION_INFORMATION;

  public static final org.jboss.as.server.deployment.AttachmentKey<org.jboss.as.server.deployment.DeploymentMountProvider> SERVER_DEPLOYMENT_REPOSITORY;

  public static final org.jboss.as.server.deployment.AttachmentKey<org.jboss.jandex.Index> ANNOTATION_INDEX;

  public static final org.jboss.as.server.deployment.AttachmentKey<org.jboss.as.server.deployment.annotation.CompositeIndex> COMPOSITE_ANNOTATION_INDEX;

  public static final org.jboss.as.server.deployment.AttachmentKey<java.lang.Boolean> COMPUTE_COMPOSITE_ANNOTATION_INDEX;

  public static final org.jboss.as.server.deployment.AttachmentKey<java.lang.Boolean> INDEX_RESOURCE_ROOT;

  public static final org.jboss.as.server.deployment.AttachmentKey<org.jboss.as.server.deployment.AttachmentList<java.lang.String>> INDEX_IGNORE_PATHS;

  public static final org.jboss.as.server.deployment.AttachmentKey<org.jboss.as.server.deployment.AttachmentList<org.jboss.as.server.deployment.DeploymentUnit>> SUB_DEPLOYMENTS;

  public static final org.jboss.as.server.deployment.AttachmentKey<org.jboss.as.server.deployment.AttachmentList<org.jboss.as.server.deployment.module.AdditionalModuleSpecification>> ADDITIONAL_MODULES;

  public static final org.jboss.as.server.deployment.AttachmentKey<org.jboss.as.server.deployment.AttachmentList<org.jboss.modules.ModuleIdentifier>> ADDITIONAL_ANNOTATION_INDEXES;

  public static final org.jboss.as.server.deployment.AttachmentKey<java.util.Map<org.jboss.modules.ModuleIdentifier, org.jboss.as.server.deployment.annotation.CompositeIndex>> ADDITIONAL_ANNOTATION_INDEXES_BY_MODULE;

  public static final org.jboss.as.server.deployment.AttachmentKey<java.util.Map<java.lang.String, org.jboss.as.server.deployment.MountedDeploymentOverlay>> DEPLOYMENT_OVERLAY_LOCATIONS;

  public static final org.jboss.as.server.deployment.AttachmentKey<org.jboss.as.server.deployment.DeploymentResourceSupport> DEPLOYMENT_RESOURCE_SUPPORT;

  public static final org.jboss.as.server.deployment.AttachmentKey<org.jboss.as.controller.capability.CapabilityServiceSupport> CAPABILITY_SERVICE_SUPPORT;

  public static final org.jboss.as.server.deployment.AttachmentKey<org.jboss.as.server.services.security.AbstractVaultReader> VAULT_READER_ATTACHMENT_KEY;

  public static final org.jboss.as.server.deployment.AttachmentKey<org.jboss.as.server.deployment.Attachments$BundleState> BUNDLE_STATE_KEY;

  public static final org.jboss.as.server.deployment.AttachmentKey<org.jboss.as.server.deployment.AttachmentList<org.jboss.as.server.deployment.module.ModuleDependency>> MANIFEST_DEPENDENCIES;

  public static final org.jboss.as.server.deployment.AttachmentKey<org.jboss.modules.ModuleIdentifier> MODULE_IDENTIFIER;

  public static final org.jboss.as.server.deployment.AttachmentKey<org.jboss.as.server.deployment.AttachmentList<java.lang.String>> DEFERRED_MODULES;

  public static final org.jboss.as.server.deployment.AttachmentKey<java.util.concurrent.atomic.AtomicInteger> DEFERRED_ACTIVATION_COUNT;

  public static final org.jboss.as.server.deployment.AttachmentKey<org.jboss.modules.Module> MODULE;

  public static final org.jboss.as.server.deployment.AttachmentKey<org.jboss.as.server.moduleservice.ServiceModuleLoader> SERVICE_MODULE_LOADER;

  public static final org.jboss.as.server.deployment.AttachmentKey<org.jboss.as.server.moduleservice.ExternalModuleService> EXTERNAL_MODULE_SERVICE;

  public static final org.jboss.as.server.deployment.AttachmentKey<org.jboss.as.server.deployment.ServicesAttachment> SERVICES;

  public static final org.jboss.as.server.deployment.AttachmentKey<org.jboss.as.server.deployment.AttachmentList<org.jboss.as.server.deployment.DeploymentUnit>> ACCESSIBLE_SUB_DEPLOYMENTS;

  public static final org.jboss.as.server.deployment.AttachmentKey<java.security.PermissionCollection> MODULE_PERMISSIONS;

  public static final org.jboss.as.server.deployment.AttachmentKey<org.jboss.as.server.deployment.AttachmentList<org.jboss.msc.service.ServiceName>> WEB_DEPENDENCIES;

  public static final org.jboss.as.server.deployment.AttachmentKey<org.jboss.as.server.deployment.AttachmentList<org.jboss.msc.service.ServiceName>> JNDI_DEPENDENCIES;

  public static final org.jboss.as.server.deployment.AttachmentKey<org.jboss.as.server.deployment.reflect.DeploymentReflectionIndex> REFLECTION_INDEX;

  public static final org.jboss.as.server.deployment.AttachmentKey<org.jboss.as.server.deployment.reflect.ProxyMetadataSource> PROXY_REFLECTION_INDEX;

  public static final org.jboss.as.server.deployment.AttachmentKey<org.jboss.as.server.deployment.AttachmentList<org.jboss.as.server.deployment.SetupAction>> SETUP_ACTIONS;

  public static final org.jboss.as.server.deployment.AttachmentKey<org.jboss.as.server.deployment.AttachmentList<org.jboss.msc.service.ServiceName>> BUNDLE_ACTIVE_DEPENDENCIES;

  public static final org.jboss.as.server.deployment.AttachmentKey<org.jboss.as.server.deployment.AttachmentList<org.jboss.msc.service.ServiceName>> DEPLOYMENT_COMPLETE_SERVICES;

  private org.jboss.as.server.deployment.Attachments();
    Code:
       0: aload_0
       1: invokespecial #1                  // Method java/lang/Object."<init>":()V
       4: return

  static {};
    Code:
       0: ldc           #2                  // class org/jboss/msc/service/ServiceName
       2: invokestatic  #3                  // Method org/jboss/as/server/deployment/AttachmentKey.createList:(Ljava/lang/Class;)Lorg/jboss/as/server/deployment/AttachmentKey;
       5: putstatic     #4                  // Field NEXT_PHASE_DEPS:Lorg/jboss/as/server/deployment/AttachmentKey;
       8: ldc           #5                  // class org/jboss/as/server/deployment/AttachableDependency
      10: invokestatic  #3                  // Method org/jboss/as/server/deployment/AttachmentKey.createList:(Ljava/lang/Class;)Lorg/jboss/as/server/deployment/AttachmentKey;
      13: putstatic     #6                  // Field NEXT_PHASE_ATTACHABLE_DEPS:Lorg/jboss/as/server/deployment/AttachmentKey;
      16: ldc           #7                  // class java/util/Set
      18: invokestatic  #8                  // Method org/jboss/as/server/deployment/AttachmentKey.create:(Ljava/lang/Class;)Lorg/jboss/as/server/deployment/AttachmentKey;
      21: putstatic     #9                  // Field EXCLUDED_SUBSYSTEMS:Lorg/jboss/as/server/deployment/AttachmentKey;
      24: ldc           #10                 // class java/lang/String
      26: invokestatic  #8                  // Method org/jboss/as/server/deployment/AttachmentKey.create:(Ljava/lang/Class;)Lorg/jboss/as/server/deployment/AttachmentKey;
      29: putstatic     #11                 // Field RUNTIME_NAME:Lorg/jboss/as/server/deployment/AttachmentKey;
      32: ldc           #10                 // class java/lang/String
      34: invokestatic  #8                  // Method org/jboss/as/server/deployment/AttachmentKey.create:(Ljava/lang/Class;)Lorg/jboss/as/server/deployment/AttachmentKey;
      37: putstatic     #12                 // Field MANAGEMENT_NAME:Lorg/jboss/as/server/deployment/AttachmentKey;
      40: ldc           #13                 // class org/jboss/vfs/VirtualFile
      42: invokestatic  #8                  // Method org/jboss/as/server/deployment/AttachmentKey.create:(Ljava/lang/Class;)Lorg/jboss/as/server/deployment/AttachmentKey;
      45: putstatic     #14                 // Field DEPLOYMENT_CONTENTS:Lorg/jboss/as/server/deployment/AttachmentKey;
      48: ldc           #15                 // class org/jboss/as/controller/ServiceVerificationHandler
      50: invokestatic  #8                  // Method org/jboss/as/server/deployment/AttachmentKey.create:(Ljava/lang/Class;)Lorg/jboss/as/server/deployment/AttachmentKey;
      53: putstatic     #16                 // Field SERVICE_VERIFICATION_HANDLER:Lorg/jboss/as/server/deployment/AttachmentKey;
      56: ldc           #17                 // class java/lang/Boolean
      58: invokestatic  #8                  // Method org/jboss/as/server/deployment/AttachmentKey.create:(Ljava/lang/Class;)Lorg/jboss/as/server/deployment/AttachmentKey;
      61: putstatic     #18                 // Field ALLOW_PHASE_RESTART:Lorg/jboss/as/server/deployment/AttachmentKey;
      64: ldc           #19                 // class org/jboss/as/server/deployment/DeploymentUnitPhaseBuilder
      66: invokestatic  #8                  // Method org/jboss/as/server/deployment/AttachmentKey.create:(Ljava/lang/Class;)Lorg/jboss/as/server/deployment/AttachmentKey;
      69: putstatic     #20                 // Field DEPLOYMENT_UNIT_PHASE_BUILDER:Lorg/jboss/as/server/deployment/AttachmentKey;
      72: ldc           #21                 // class org/jboss/as/controller/services/path/PathManager
      74: invokestatic  #8                  // Method org/jboss/as/server/deployment/AttachmentKey.create:(Ljava/lang/Class;)Lorg/jboss/as/server/deployment/AttachmentKey;
      77: putstatic     #22                 // Field PATH_MANAGER:Lorg/jboss/as/server/deployment/AttachmentKey;
      80: ldc           #23                 // class org/jboss/as/server/deploymentoverlay/DeploymentOverlayIndex
      82: invokestatic  #8                  // Method org/jboss/as/server/deployment/AttachmentKey.create:(Ljava/lang/Class;)Lorg/jboss/as/server/deployment/AttachmentKey;
      85: putstatic     #24                 // Field DEPLOYMENT_OVERLAY_INDEX:Lorg/jboss/as/server/deployment/AttachmentKey;
      88: ldc           #25                 // class org/jboss/as/server/deployment/module/ResourceRoot
      90: invokestatic  #8                  // Method org/jboss/as/server/deployment/AttachmentKey.create:(Ljava/lang/Class;)Lorg/jboss/as/server/deployment/AttachmentKey;
      93: putstatic     #26                 // Field DEPLOYMENT_ROOT:Lorg/jboss/as/server/deployment/AttachmentKey;
      96: ldc           #27                 // class org/jboss/as/server/deployment/module/ModuleSpecification
      98: invokestatic  #8                  // Method org/jboss/as/server/deployment/AttachmentKey.create:(Ljava/lang/Class;)Lorg/jboss/as/server/deployment/AttachmentKey;
     101: putstatic     #28                 // Field MODULE_SPECIFICATION:Lorg/jboss/as/server/deployment/AttachmentKey;
     104: ldc           #25                 // class org/jboss/as/server/deployment/module/ResourceRoot
     106: invokestatic  #3                  // Method org/jboss/as/server/deployment/AttachmentKey.createList:(Ljava/lang/Class;)Lorg/jboss/as/server/deployment/AttachmentKey;
     109: putstatic     #29                 // Field RESOURCE_ROOTS:Lorg/jboss/as/server/deployment/AttachmentKey;
     112: ldc           #30                 // class java/util/jar/Manifest
     114: invokestatic  #8                  // Method org/jboss/as/server/deployment/AttachmentKey.create:(Ljava/lang/Class;)Lorg/jboss/as/server/deployment/AttachmentKey;
     117: putstatic     #31                 // Field MANIFEST:Lorg/jboss/as/server/deployment/AttachmentKey;
     120: ldc           #30                 // class java/util/jar/Manifest
     122: invokestatic  #8                  // Method org/jboss/as/server/deployment/AttachmentKey.create:(Ljava/lang/Class;)Lorg/jboss/as/server/deployment/AttachmentKey;
     125: putstatic     #32                 // Field OSGI_MANIFEST:Lorg/jboss/as/server/deployment/AttachmentKey;
     128: ldc           #33                 // class org/jboss/modules/ModuleIdentifier
     130: invokestatic  #3                  // Method org/jboss/as/server/deployment/AttachmentKey.createList:(Ljava/lang/Class;)Lorg/jboss/as/server/deployment/AttachmentKey;
     133: putstatic     #34                 // Field CLASS_PATH_ENTRIES:Lorg/jboss/as/server/deployment/AttachmentKey;
     136: ldc           #25                 // class org/jboss/as/server/deployment/module/ResourceRoot
     138: invokestatic  #3                  // Method org/jboss/as/server/deployment/AttachmentKey.createList:(Ljava/lang/Class;)Lorg/jboss/as/server/deployment/AttachmentKey;
     141: putstatic     #35                 // Field CLASS_PATH_RESOURCE_ROOTS:Lorg/jboss/as/server/deployment/AttachmentKey;
     144: ldc           #36                 // class org/jboss/as/server/deployment/module/ExtensionListEntry
     146: invokestatic  #3                  // Method org/jboss/as/server/deployment/AttachmentKey.createList:(Ljava/lang/Class;)Lorg/jboss/as/server/deployment/AttachmentKey;
     149: putstatic     #37                 // Field EXTENSION_LIST_ENTRIES:Lorg/jboss/as/server/deployment/AttachmentKey;
     152: ldc           #38                 // class org/jboss/as/server/deployment/module/ExtensionInfo
     154: invokestatic  #8                  // Method org/jboss/as/server/deployment/AttachmentKey.create:(Ljava/lang/Class;)Lorg/jboss/as/server/deployment/AttachmentKey;
     157: putstatic     #39                 // Field EXTENSION_INFORMATION:Lorg/jboss/as/server/deployment/AttachmentKey;
     160: ldc           #40                 // class org/jboss/as/server/deployment/DeploymentMountProvider
     162: invokestatic  #8                  // Method org/jboss/as/server/deployment/AttachmentKey.create:(Ljava/lang/Class;)Lorg/jboss/as/server/deployment/AttachmentKey;
     165: putstatic     #41                 // Field SERVER_DEPLOYMENT_REPOSITORY:Lorg/jboss/as/server/deployment/AttachmentKey;
     168: ldc           #42                 // class org/jboss/jandex/Index
     170: invokestatic  #8                  // Method org/jboss/as/server/deployment/AttachmentKey.create:(Ljava/lang/Class;)Lorg/jboss/as/server/deployment/AttachmentKey;
     173: putstatic     #43                 // Field ANNOTATION_INDEX:Lorg/jboss/as/server/deployment/AttachmentKey;
     176: ldc           #44                 // class org/jboss/as/server/deployment/annotation/CompositeIndex
     178: invokestatic  #8                  // Method org/jboss/as/server/deployment/AttachmentKey.create:(Ljava/lang/Class;)Lorg/jboss/as/server/deployment/AttachmentKey;
     181: putstatic     #45                 // Field COMPOSITE_ANNOTATION_INDEX:Lorg/jboss/as/server/deployment/AttachmentKey;
     184: ldc           #17                 // class java/lang/Boolean
     186: invokestatic  #8                  // Method org/jboss/as/server/deployment/AttachmentKey.create:(Ljava/lang/Class;)Lorg/jboss/as/server/deployment/AttachmentKey;
     189: putstatic     #46                 // Field COMPUTE_COMPOSITE_ANNOTATION_INDEX:Lorg/jboss/as/server/deployment/AttachmentKey;
     192: ldc           #17                 // class java/lang/Boolean
     194: invokestatic  #8                  // Method org/jboss/as/server/deployment/AttachmentKey.create:(Ljava/lang/Class;)Lorg/jboss/as/server/deployment/AttachmentKey;
     197: putstatic     #47                 // Field INDEX_RESOURCE_ROOT:Lorg/jboss/as/server/deployment/AttachmentKey;
     200: ldc           #10                 // class java/lang/String
     202: invokestatic  #3                  // Method org/jboss/as/server/deployment/AttachmentKey.createList:(Ljava/lang/Class;)Lorg/jboss/as/server/deployment/AttachmentKey;
     205: putstatic     #48                 // Field INDEX_IGNORE_PATHS:Lorg/jboss/as/server/deployment/AttachmentKey;
     208: ldc           #49                 // class org/jboss/as/server/deployment/DeploymentUnit
     210: invokestatic  #3                  // Method org/jboss/as/server/deployment/AttachmentKey.createList:(Ljava/lang/Class;)Lorg/jboss/as/server/deployment/AttachmentKey;
     213: putstatic     #50                 // Field SUB_DEPLOYMENTS:Lorg/jboss/as/server/deployment/AttachmentKey;
     216: ldc           #51                 // class org/jboss/as/server/deployment/module/AdditionalModuleSpecification
     218: invokestatic  #3                  // Method org/jboss/as/server/deployment/AttachmentKey.createList:(Ljava/lang/Class;)Lorg/jboss/as/server/deployment/AttachmentKey;
     221: putstatic     #52                 // Field ADDITIONAL_MODULES:Lorg/jboss/as/server/deployment/AttachmentKey;
     224: ldc           #33                 // class org/jboss/modules/ModuleIdentifier
     226: invokestatic  #3                  // Method org/jboss/as/server/deployment/AttachmentKey.createList:(Ljava/lang/Class;)Lorg/jboss/as/server/deployment/AttachmentKey;
     229: putstatic     #53                 // Field ADDITIONAL_ANNOTATION_INDEXES:Lorg/jboss/as/server/deployment/AttachmentKey;
     232: ldc           #54                 // class java/util/Map
     234: invokestatic  #8                  // Method org/jboss/as/server/deployment/AttachmentKey.create:(Ljava/lang/Class;)Lorg/jboss/as/server/deployment/AttachmentKey;
     237: putstatic     #55                 // Field ADDITIONAL_ANNOTATION_INDEXES_BY_MODULE:Lorg/jboss/as/server/deployment/AttachmentKey;
     240: ldc           #54                 // class java/util/Map
     242: invokestatic  #8                  // Method org/jboss/as/server/deployment/AttachmentKey.create:(Ljava/lang/Class;)Lorg/jboss/as/server/deployment/AttachmentKey;
     245: putstatic     #56                 // Field DEPLOYMENT_OVERLAY_LOCATIONS:Lorg/jboss/as/server/deployment/AttachmentKey;
     248: ldc           #57                 // class org/jboss/as/server/deployment/DeploymentResourceSupport
     250: invokestatic  #8                  // Method org/jboss/as/server/deployment/AttachmentKey.create:(Ljava/lang/Class;)Lorg/jboss/as/server/deployment/AttachmentKey;
     253: putstatic     #58                 // Field DEPLOYMENT_RESOURCE_SUPPORT:Lorg/jboss/as/server/deployment/AttachmentKey;
     256: ldc           #59                 // class org/jboss/as/controller/capability/CapabilityServiceSupport
     258: invokestatic  #8                  // Method org/jboss/as/server/deployment/AttachmentKey.create:(Ljava/lang/Class;)Lorg/jboss/as/server/deployment/AttachmentKey;
     261: putstatic     #60                 // Field CAPABILITY_SERVICE_SUPPORT:Lorg/jboss/as/server/deployment/AttachmentKey;
     264: ldc           #61                 // class org/jboss/as/server/services/security/AbstractVaultReader
     266: invokestatic  #8                  // Method org/jboss/as/server/deployment/AttachmentKey.create:(Ljava/lang/Class;)Lorg/jboss/as/server/deployment/AttachmentKey;
     269: putstatic     #62                 // Field VAULT_READER_ATTACHMENT_KEY:Lorg/jboss/as/server/deployment/AttachmentKey;
     272: ldc           #63                 // class org/jboss/as/server/deployment/Attachments$BundleState
     274: invokestatic  #8                  // Method org/jboss/as/server/deployment/AttachmentKey.create:(Ljava/lang/Class;)Lorg/jboss/as/server/deployment/AttachmentKey;
     277: putstatic     #64                 // Field BUNDLE_STATE_KEY:Lorg/jboss/as/server/deployment/AttachmentKey;
     280: ldc           #65                 // class org/jboss/as/server/deployment/module/ModuleDependency
     282: invokestatic  #3                  // Method org/jboss/as/server/deployment/AttachmentKey.createList:(Ljava/lang/Class;)Lorg/jboss/as/server/deployment/AttachmentKey;
     285: putstatic     #66                 // Field MANIFEST_DEPENDENCIES:Lorg/jboss/as/server/deployment/AttachmentKey;
     288: ldc           #33                 // class org/jboss/modules/ModuleIdentifier
     290: invokestatic  #8                  // Method org/jboss/as/server/deployment/AttachmentKey.create:(Ljava/lang/Class;)Lorg/jboss/as/server/deployment/AttachmentKey;
     293: putstatic     #67                 // Field MODULE_IDENTIFIER:Lorg/jboss/as/server/deployment/AttachmentKey;
     296: ldc           #10                 // class java/lang/String
     298: invokestatic  #3                  // Method org/jboss/as/server/deployment/AttachmentKey.createList:(Ljava/lang/Class;)Lorg/jboss/as/server/deployment/AttachmentKey;
     301: putstatic     #68                 // Field DEFERRED_MODULES:Lorg/jboss/as/server/deployment/AttachmentKey;
     304: ldc           #69                 // class java/util/concurrent/atomic/AtomicInteger
     306: invokestatic  #8                  // Method org/jboss/as/server/deployment/AttachmentKey.create:(Ljava/lang/Class;)Lorg/jboss/as/server/deployment/AttachmentKey;
     309: putstatic     #70                 // Field DEFERRED_ACTIVATION_COUNT:Lorg/jboss/as/server/deployment/AttachmentKey;
     312: ldc           #71                 // class org/jboss/modules/Module
     314: invokestatic  #8                  // Method org/jboss/as/server/deployment/AttachmentKey.create:(Ljava/lang/Class;)Lorg/jboss/as/server/deployment/AttachmentKey;
     317: putstatic     #72                 // Field MODULE:Lorg/jboss/as/server/deployment/AttachmentKey;
     320: ldc           #73                 // class org/jboss/as/server/moduleservice/ServiceModuleLoader
     322: invokestatic  #8                  // Method org/jboss/as/server/deployment/AttachmentKey.create:(Ljava/lang/Class;)Lorg/jboss/as/server/deployment/AttachmentKey;
     325: putstatic     #74                 // Field SERVICE_MODULE_LOADER:Lorg/jboss/as/server/deployment/AttachmentKey;
     328: ldc           #75                 // class org/jboss/as/server/moduleservice/ExternalModuleService
     330: invokestatic  #8                  // Method org/jboss/as/server/deployment/AttachmentKey.create:(Ljava/lang/Class;)Lorg/jboss/as/server/deployment/AttachmentKey;
     333: putstatic     #76                 // Field EXTERNAL_MODULE_SERVICE:Lorg/jboss/as/server/deployment/AttachmentKey;
     336: ldc           #77                 // class org/jboss/as/server/deployment/ServicesAttachment
     338: invokestatic  #8                  // Method org/jboss/as/server/deployment/AttachmentKey.create:(Ljava/lang/Class;)Lorg/jboss/as/server/deployment/AttachmentKey;
     341: putstatic     #78                 // Field SERVICES:Lorg/jboss/as/server/deployment/AttachmentKey;
     344: ldc           #49                 // class org/jboss/as/server/deployment/DeploymentUnit
     346: invokestatic  #3                  // Method org/jboss/as/server/deployment/AttachmentKey.createList:(Ljava/lang/Class;)Lorg/jboss/as/server/deployment/AttachmentKey;
     349: putstatic     #79                 // Field ACCESSIBLE_SUB_DEPLOYMENTS:Lorg/jboss/as/server/deployment/AttachmentKey;
     352: ldc           #80                 // class java/security/PermissionCollection
     354: invokestatic  #8                  // Method org/jboss/as/server/deployment/AttachmentKey.create:(Ljava/lang/Class;)Lorg/jboss/as/server/deployment/AttachmentKey;
     357: putstatic     #81                 // Field MODULE_PERMISSIONS:Lorg/jboss/as/server/deployment/AttachmentKey;
     360: ldc           #2                  // class org/jboss/msc/service/ServiceName
     362: invokestatic  #3                  // Method org/jboss/as/server/deployment/AttachmentKey.createList:(Ljava/lang/Class;)Lorg/jboss/as/server/deployment/AttachmentKey;
     365: putstatic     #82                 // Field WEB_DEPENDENCIES:Lorg/jboss/as/server/deployment/AttachmentKey;
     368: ldc           #2                  // class org/jboss/msc/service/ServiceName
     370: invokestatic  #3                  // Method org/jboss/as/server/deployment/AttachmentKey.createList:(Ljava/lang/Class;)Lorg/jboss/as/server/deployment/AttachmentKey;
     373: putstatic     #83                 // Field JNDI_DEPENDENCIES:Lorg/jboss/as/server/deployment/AttachmentKey;
     376: ldc           #84                 // class org/jboss/as/server/deployment/reflect/DeploymentReflectionIndex
     378: invokestatic  #8                  // Method org/jboss/as/server/deployment/AttachmentKey.create:(Ljava/lang/Class;)Lorg/jboss/as/server/deployment/AttachmentKey;
     381: putstatic     #85                 // Field REFLECTION_INDEX:Lorg/jboss/as/server/deployment/AttachmentKey;
     384: ldc           #86                 // class org/jboss/as/server/deployment/reflect/ProxyMetadataSource
     386: invokestatic  #8                  // Method org/jboss/as/server/deployment/AttachmentKey.create:(Ljava/lang/Class;)Lorg/jboss/as/server/deployment/AttachmentKey;
     389: putstatic     #87                 // Field PROXY_REFLECTION_INDEX:Lorg/jboss/as/server/deployment/AttachmentKey;
     392: ldc           #88                 // class org/jboss/as/server/deployment/SetupAction
     394: invokestatic  #3                  // Method org/jboss/as/server/deployment/AttachmentKey.createList:(Ljava/lang/Class;)Lorg/jboss/as/server/deployment/AttachmentKey;
     397: putstatic     #89                 // Field SETUP_ACTIONS:Lorg/jboss/as/server/deployment/AttachmentKey;
     400: ldc           #2                  // class org/jboss/msc/service/ServiceName
     402: invokestatic  #3                  // Method org/jboss/as/server/deployment/AttachmentKey.createList:(Ljava/lang/Class;)Lorg/jboss/as/server/deployment/AttachmentKey;
     405: putstatic     #90                 // Field BUNDLE_ACTIVE_DEPENDENCIES:Lorg/jboss/as/server/deployment/AttachmentKey;
     408: ldc           #2                  // class org/jboss/msc/service/ServiceName
     410: invokestatic  #3                  // Method org/jboss/as/server/deployment/AttachmentKey.createList:(Ljava/lang/Class;)Lorg/jboss/as/server/deployment/AttachmentKey;
     413: putstatic     #91                 // Field DEPLOYMENT_COMPLETE_SERVICES:Lorg/jboss/as/server/deployment/AttachmentKey;
     416: return
}
