Compiled from "DeploymentHandlerUtil.java"
final class org.jboss.as.server.deployment.DeploymentHandlerUtil$3 implements org.jboss.as.controller.OperationStepHandler {
  final java.lang.String val$deploymentUnitName;

  final java.lang.String val$managementName;

  final org.jboss.as.controller.registry.Resource val$deployment;

  final org.jboss.as.controller.registry.ImmutableManagementResourceRegistration val$registration;

  final org.jboss.as.controller.registry.ManagementResourceRegistration val$mutableRegistration;

  final org.jboss.as.server.services.security.AbstractVaultReader val$vaultReader;

  final org.jboss.as.server.deployment.DeploymentHandlerUtil$ContentItem[] val$contents;

  org.jboss.as.server.deployment.DeploymentHandlerUtil$3(java.lang.String, java.lang.String, org.jboss.as.controller.registry.Resource, org.jboss.as.controller.registry.ImmutableManagementResourceRegistration, org.jboss.as.controller.registry.ManagementResourceRegistration, org.jboss.as.server.services.security.AbstractVaultReader, org.jboss.as.server.deployment.DeploymentHandlerUtil$ContentItem[]);
    Code:
       0: aload_0
       1: aload_1
       2: putfield      #1                  // Field val$deploymentUnitName:Ljava/lang/String;
       5: aload_0
       6: aload_2
       7: putfield      #2                  // Field val$managementName:Ljava/lang/String;
      10: aload_0
      11: aload_3
      12: putfield      #3                  // Field val$deployment:Lorg/jboss/as/controller/registry/Resource;
      15: aload_0
      16: aload         4
      18: putfield      #4                  // Field val$registration:Lorg/jboss/as/controller/registry/ImmutableManagementResourceRegistration;
      21: aload_0
      22: aload         5
      24: putfield      #5                  // Field val$mutableRegistration:Lorg/jboss/as/controller/registry/ManagementResourceRegistration;
      27: aload_0
      28: aload         6
      30: putfield      #6                  // Field val$vaultReader:Lorg/jboss/as/server/services/security/AbstractVaultReader;
      33: aload_0
      34: aload         7
      36: putfield      #7                  // Field val$contents:[Lorg/jboss/as/server/deployment/DeploymentHandlerUtil$ContentItem;
      39: aload_0
      40: invokespecial #8                  // Method java/lang/Object."<init>":()V
      43: return

  public void execute(org.jboss.as.controller.OperationContext, org.jboss.dmr.ModelNode) throws org.jboss.as.controller.OperationFailedException;
    Code:
       0: aload_0
       1: getfield      #1                  // Field val$deploymentUnitName:Ljava/lang/String;
       4: invokestatic  #9                  // Method org/jboss/as/server/deployment/Services.deploymentUnitName:(Ljava/lang/String;)Lorg/jboss/msc/service/ServiceName;
       7: astore_3
       8: aload_1
       9: aload_3
      10: invokeinterface #10,  2           // InterfaceMethod org/jboss/as/controller/OperationContext.removeService:(Lorg/jboss/msc/service/ServiceName;)Lorg/jboss/msc/service/ServiceController;
      15: pop
      16: aload_1
      17: aload_3
      18: iconst_1
      19: anewarray     #11                 // class java/lang/String
      22: dup
      23: iconst_0
      24: ldc           #12                 // String contents
      26: aastore
      27: invokevirtual #13                 // Method org/jboss/msc/service/ServiceName.append:([Ljava/lang/String;)Lorg/jboss/msc/service/ServiceName;
      30: invokeinterface #10,  2           // InterfaceMethod org/jboss/as/controller/OperationContext.removeService:(Lorg/jboss/msc/service/ServiceName;)Lorg/jboss/msc/service/ServiceController;
      35: pop
      36: new           #14                 // class java/util/concurrent/atomic/AtomicBoolean
      39: dup
      40: iconst_0
      41: invokespecial #15                 // Method java/util/concurrent/atomic/AtomicBoolean."<init>":(Z)V
      44: astore        4
      46: aload_1
      47: new           #16                 // class org/jboss/as/server/deployment/DeploymentHandlerUtil$3$1
      50: dup
      51: aload_0
      52: aload         4
      54: invokespecial #17                 // Method org/jboss/as/server/deployment/DeploymentHandlerUtil$3$1."<init>":(Lorg/jboss/as/server/deployment/DeploymentHandlerUtil$3;Ljava/util/concurrent/atomic/AtomicBoolean;)V
      57: getstatic     #18                 // Field org/jboss/as/controller/OperationContext$Stage.RUNTIME:Lorg/jboss/as/controller/OperationContext$Stage;
      60: iconst_1
      61: invokeinterface #19,  4           // InterfaceMethod org/jboss/as/controller/OperationContext.addStep:(Lorg/jboss/as/controller/OperationStepHandler;Lorg/jboss/as/controller/OperationContext$Stage;Z)V
      66: aload_1
      67: new           #20                 // class org/jboss/as/server/deployment/DeploymentHandlerUtil$3$2
      70: dup
      71: aload_0
      72: aload         4
      74: invokespecial #21                 // Method org/jboss/as/server/deployment/DeploymentHandlerUtil$3$2."<init>":(Lorg/jboss/as/server/deployment/DeploymentHandlerUtil$3;Ljava/util/concurrent/atomic/AtomicBoolean;)V
      77: invokeinterface #22,  2           // InterfaceMethod org/jboss/as/controller/OperationContext.completeStep:(Lorg/jboss/as/controller/OperationContext$RollbackHandler;)V
      82: return
}
