Compiled from "DeploymentMountProvider.java"
public class org.jboss.as.server.deployment.DeploymentMountProvider$Factory {
  public org.jboss.as.server.deployment.DeploymentMountProvider$Factory();
    Code:
       0: aload_0
       1: invokespecial #1                  // Method java/lang/Object."<init>":()V
       4: return

  public static void addService(org.jboss.msc.service.ServiceTarget);
    Code:
       0: new           #2                  // class org/jboss/as/server/deployment/DeploymentMountProvider$Factory$ServerDeploymentRepositoryImpl
       3: dup
       4: aconst_null
       5: invokespecial #3                  // Method org/jboss/as/server/deployment/DeploymentMountProvider$Factory$ServerDeploymentRepositoryImpl."<init>":(Lorg/jboss/as/server/deployment/DeploymentMountProvider$1;)V
       8: astore_1
       9: aload_0
      10: getstatic     #4                  // Field org/jboss/as/server/deployment/DeploymentMountProvider.SERVICE_NAME:Lorg/jboss/msc/service/ServiceName;
      13: aload_1
      14: invokeinterface #5,  3            // InterfaceMethod org/jboss/msc/service/ServiceTarget.addService:(Lorg/jboss/msc/service/ServiceName;Lorg/jboss/msc/service/Service;)Lorg/jboss/msc/service/ServiceBuilder;
      19: aload_1
      20: invokestatic  #6                  // Method org/jboss/as/server/deployment/DeploymentMountProvider$Factory$ServerDeploymentRepositoryImpl.access$100:(Lorg/jboss/as/server/deployment/DeploymentMountProvider$Factory$ServerDeploymentRepositoryImpl;)Lorg/jboss/msc/value/InjectedValue;
      23: iconst_0
      24: invokestatic  #7                  // Method org/jboss/as/server/Services.addServerExecutorDependency:(Lorg/jboss/msc/service/ServiceBuilder;Lorg/jboss/msc/inject/Injector;Z)Lorg/jboss/msc/service/ServiceBuilder;
      27: invokeinterface #8,  1            // InterfaceMethod org/jboss/msc/service/ServiceBuilder.install:()Lorg/jboss/msc/service/ServiceController;
      32: pop
      33: return
}
