Compiled from "ArjunaTransactionImpleWrapper.java"
class com.arjuna.ats.internal.jta.tools.osb.mbean.jts.ArjunaTransactionImpleWrapper$1 {
  static final int[] $SwitchMap$com$arjuna$ats$arjuna$tools$osb$mbean$ParticipantStatus;

  static {};
    Code:
       0: invokestatic  #1                  // Method com/arjuna/ats/arjuna/tools/osb/mbean/ParticipantStatus.values:()[Lcom/arjuna/ats/arjuna/tools/osb/mbean/ParticipantStatus;
       3: arraylength
       4: newarray       int
       6: putstatic     #2                  // Field $SwitchMap$com$arjuna$ats$arjuna$tools$osb$mbean$ParticipantStatus:[I
       9: getstatic     #2                  // Field $SwitchMap$com$arjuna$ats$arjuna$tools$osb$mbean$ParticipantStatus:[I
      12: getstatic     #3                  // Field com/arjuna/ats/arjuna/tools/osb/mbean/ParticipantStatus.PREPARED:Lcom/arjuna/ats/arjuna/tools/osb/mbean/ParticipantStatus;
      15: invokevirtual #4                  // Method com/arjuna/ats/arjuna/tools/osb/mbean/ParticipantStatus.ordinal:()I
      18: iconst_1
      19: iastore
      20: goto          24
      23: astore_0
      24: getstatic     #2                  // Field $SwitchMap$com$arjuna$ats$arjuna$tools$osb$mbean$ParticipantStatus:[I
      27: getstatic     #6                  // Field com/arjuna/ats/arjuna/tools/osb/mbean/ParticipantStatus.FAILED:Lcom/arjuna/ats/arjuna/tools/osb/mbean/ParticipantStatus;
      30: invokevirtual #4                  // Method com/arjuna/ats/arjuna/tools/osb/mbean/ParticipantStatus.ordinal:()I
      33: iconst_2
      34: iastore
      35: goto          39
      38: astore_0
      39: getstatic     #2                  // Field $SwitchMap$com$arjuna$ats$arjuna$tools$osb$mbean$ParticipantStatus:[I
      42: getstatic     #7                  // Field com/arjuna/ats/arjuna/tools/osb/mbean/ParticipantStatus.HEURISTIC:Lcom/arjuna/ats/arjuna/tools/osb/mbean/ParticipantStatus;
      45: invokevirtual #4                  // Method com/arjuna/ats/arjuna/tools/osb/mbean/ParticipantStatus.ordinal:()I
      48: iconst_3
      49: iastore
      50: goto          54
      53: astore_0
      54: getstatic     #2                  // Field $SwitchMap$com$arjuna$ats$arjuna$tools$osb$mbean$ParticipantStatus:[I
      57: getstatic     #8                  // Field com/arjuna/ats/arjuna/tools/osb/mbean/ParticipantStatus.PENDING:Lcom/arjuna/ats/arjuna/tools/osb/mbean/ParticipantStatus;
      60: invokevirtual #4                  // Method com/arjuna/ats/arjuna/tools/osb/mbean/ParticipantStatus.ordinal:()I
      63: iconst_4
      64: iastore
      65: goto          69
      68: astore_0
      69: getstatic     #2                  // Field $SwitchMap$com$arjuna$ats$arjuna$tools$osb$mbean$ParticipantStatus:[I
      72: getstatic     #9                  // Field com/arjuna/ats/arjuna/tools/osb/mbean/ParticipantStatus.READONLY:Lcom/arjuna/ats/arjuna/tools/osb/mbean/ParticipantStatus;
      75: invokevirtual #4                  // Method com/arjuna/ats/arjuna/tools/osb/mbean/ParticipantStatus.ordinal:()I
      78: iconst_5
      79: iastore
      80: goto          84
      83: astore_0
      84: return
    Exception table:
       from    to  target type
           9    20    23   Class java/lang/NoSuchFieldError
          24    35    38   Class java/lang/NoSuchFieldError
          39    50    53   Class java/lang/NoSuchFieldError
          54    65    68   Class java/lang/NoSuchFieldError
          69    80    83   Class java/lang/NoSuchFieldError
}
