Compiled from "ControllerResolver.java"
public final class org.jboss.as.controller.descriptions.common.ControllerResolver {
  public static final java.lang.String RESOURCE_NAME;

  public org.jboss.as.controller.descriptions.common.ControllerResolver();
    Code:
       0: aload_0
       1: invokespecial #1                  // Method java/lang/Object."<init>":()V
       4: return

  public static org.jboss.as.controller.descriptions.ResourceDescriptionResolver getResolver(java.lang.String...);
    Code:
       0: iconst_0
       1: aload_0
       2: invokestatic  #2                  // Method getResolver:(Z[Ljava/lang/String;)Lorg/jboss/as/controller/descriptions/ResourceDescriptionResolver;
       5: areturn

  public static org.jboss.as.controller.descriptions.ResourceDescriptionResolver getDeprecatedResolver(java.lang.String, java.lang.String...);
    Code:
       0: aload_1
       1: invokestatic  #3                  // Method getPrefix:([Ljava/lang/String;)Ljava/lang/String;
       4: astore_2
       5: new           #4                  // class org/jboss/as/controller/descriptions/DeprecatedResourceDescriptionResolver
       8: dup
       9: aload_0
      10: aload_2
      11: getstatic     #5                  // Field RESOURCE_NAME:Ljava/lang/String;
      14: ldc           #6                  // class org/jboss/as/controller/descriptions/common/ControllerResolver
      16: invokevirtual #7                  // Method java/lang/Class.getClassLoader:()Ljava/lang/ClassLoader;
      19: iconst_1
      20: iconst_0
      21: invokespecial #8                  // Method org/jboss/as/controller/descriptions/DeprecatedResourceDescriptionResolver."<init>":(Ljava/lang/String;Ljava/lang/String;Ljava/lang/String;Ljava/lang/ClassLoader;ZZ)V
      24: areturn

  public static org.jboss.as.controller.descriptions.ResourceDescriptionResolver getResolver(boolean, java.lang.String...);
    Code:
       0: aload_1
       1: invokestatic  #3                  // Method getPrefix:([Ljava/lang/String;)Ljava/lang/String;
       4: astore_2
       5: new           #9                  // class org/jboss/as/controller/descriptions/StandardResourceDescriptionResolver
       8: dup
       9: aload_2
      10: getstatic     #5                  // Field RESOURCE_NAME:Ljava/lang/String;
      13: ldc           #6                  // class org/jboss/as/controller/descriptions/common/ControllerResolver
      15: invokevirtual #7                  // Method java/lang/Class.getClassLoader:()Ljava/lang/ClassLoader;
      18: iconst_1
      19: iload_0
      20: invokespecial #10                 // Method org/jboss/as/controller/descriptions/StandardResourceDescriptionResolver."<init>":(Ljava/lang/String;Ljava/lang/String;Ljava/lang/ClassLoader;ZZ)V
      23: areturn

  private static java.lang.String getPrefix(java.lang.String...);
    Code:
       0: new           #11                 // class java/lang/StringBuilder
       3: dup
       4: invokespecial #12                 // Method java/lang/StringBuilder."<init>":()V
       7: astore_1
       8: aload_0
       9: astore_2
      10: aload_2
      11: arraylength
      12: istore_3
      13: iconst_0
      14: istore        4
      16: iload         4
      18: iload_3
      19: if_icmpge     63
      22: aload_2
      23: iload         4
      25: aaload
      26: astore        5
      28: aload_1
      29: invokevirtual #13                 // Method java/lang/StringBuilder.length:()I
      32: ifle          50
      35: aload_1
      36: bipush        46
      38: invokevirtual #14                 // Method java/lang/StringBuilder.append:(C)Ljava/lang/StringBuilder;
      41: aload         5
      43: invokevirtual #15                 // Method java/lang/StringBuilder.append:(Ljava/lang/String;)Ljava/lang/StringBuilder;
      46: pop
      47: goto          57
      50: aload_1
      51: aload         5
      53: invokevirtual #15                 // Method java/lang/StringBuilder.append:(Ljava/lang/String;)Ljava/lang/StringBuilder;
      56: pop
      57: iinc          4, 1
      60: goto          16
      63: aload_1
      64: invokevirtual #16                 // Method java/lang/StringBuilder.toString:()Ljava/lang/String;
      67: areturn

  static {};
    Code:
       0: new           #11                 // class java/lang/StringBuilder
       3: dup
       4: invokespecial #12                 // Method java/lang/StringBuilder."<init>":()V
       7: ldc           #6                  // class org/jboss/as/controller/descriptions/common/ControllerResolver
       9: invokevirtual #17                 // Method java/lang/Class.getPackage:()Ljava/lang/Package;
      12: invokevirtual #18                 // Method java/lang/Package.getName:()Ljava/lang/String;
      15: invokevirtual #15                 // Method java/lang/StringBuilder.append:(Ljava/lang/String;)Ljava/lang/StringBuilder;
      18: ldc           #19                 // String .LocalDescriptions
      20: invokevirtual #15                 // Method java/lang/StringBuilder.append:(Ljava/lang/String;)Ljava/lang/StringBuilder;
      23: invokevirtual #16                 // Method java/lang/StringBuilder.toString:()Ljava/lang/String;
      26: putstatic     #5                  // Field RESOURCE_NAME:Ljava/lang/String;
      29: return
}
