Compiled from "InternalConfigJsonHelper.java"
public class com.amazonaws.internal.config.InternalConfigJsonHelper {
  private com.amazonaws.internal.config.SignerConfigJsonHelper defaultSigner;

  private com.amazonaws.internal.config.JsonIndex<com.amazonaws.internal.config.SignerConfigJsonHelper, com.amazonaws.internal.config.SignerConfig>[] serviceSigners;

  private com.amazonaws.internal.config.JsonIndex<com.amazonaws.internal.config.SignerConfigJsonHelper, com.amazonaws.internal.config.SignerConfig>[] regionSigners;

  private com.amazonaws.internal.config.JsonIndex<com.amazonaws.internal.config.SignerConfigJsonHelper, com.amazonaws.internal.config.SignerConfig>[] serviceRegionSigners;

  private com.amazonaws.internal.config.JsonIndex<com.amazonaws.internal.config.HttpClientConfigJsonHelper, com.amazonaws.internal.config.HttpClientConfig>[] httpClients;

  private com.amazonaws.internal.config.HostRegexToRegionMappingJsonHelper[] hostRegexToRegionMappings;

  private java.lang.String userAgentTemplate;

  public com.amazonaws.internal.config.InternalConfigJsonHelper();
    Code:
       0: aload_0
       1: invokespecial #1                  // Method java/lang/Object."<init>":()V
       4: return

  public com.amazonaws.internal.config.SignerConfigJsonHelper getDefaultSigner();
    Code:
       0: aload_0
       1: getfield      #2                  // Field defaultSigner:Lcom/amazonaws/internal/config/SignerConfigJsonHelper;
       4: areturn

  public void setDefaultSigner(com.amazonaws.internal.config.SignerConfigJsonHelper);
    Code:
       0: aload_0
       1: aload_1
       2: putfield      #2                  // Field defaultSigner:Lcom/amazonaws/internal/config/SignerConfigJsonHelper;
       5: return

  public com.amazonaws.internal.config.JsonIndex<com.amazonaws.internal.config.SignerConfigJsonHelper, com.amazonaws.internal.config.SignerConfig>[] getServiceSigners();
    Code:
       0: aload_0
       1: getfield      #3                  // Field serviceSigners:[Lcom/amazonaws/internal/config/JsonIndex;
       4: areturn

  public void setServiceSigners(com.amazonaws.internal.config.JsonIndex<com.amazonaws.internal.config.SignerConfigJsonHelper, com.amazonaws.internal.config.SignerConfig>...);
    Code:
       0: aload_0
       1: aload_1
       2: putfield      #3                  // Field serviceSigners:[Lcom/amazonaws/internal/config/JsonIndex;
       5: return

  public com.amazonaws.internal.config.JsonIndex<com.amazonaws.internal.config.SignerConfigJsonHelper, com.amazonaws.internal.config.SignerConfig>[] getRegionSigners();
    Code:
       0: aload_0
       1: getfield      #4                  // Field regionSigners:[Lcom/amazonaws/internal/config/JsonIndex;
       4: areturn

  public void setRegionSigners(com.amazonaws.internal.config.JsonIndex<com.amazonaws.internal.config.SignerConfigJsonHelper, com.amazonaws.internal.config.SignerConfig>...);
    Code:
       0: aload_0
       1: aload_1
       2: putfield      #4                  // Field regionSigners:[Lcom/amazonaws/internal/config/JsonIndex;
       5: return

  public com.amazonaws.internal.config.JsonIndex<com.amazonaws.internal.config.SignerConfigJsonHelper, com.amazonaws.internal.config.SignerConfig>[] getServiceRegionSigners();
    Code:
       0: aload_0
       1: getfield      #5                  // Field serviceRegionSigners:[Lcom/amazonaws/internal/config/JsonIndex;
       4: areturn

  public void setServiceRegionSigners(com.amazonaws.internal.config.JsonIndex<com.amazonaws.internal.config.SignerConfigJsonHelper, com.amazonaws.internal.config.SignerConfig>...);
    Code:
       0: aload_0
       1: aload_1
       2: putfield      #5                  // Field serviceRegionSigners:[Lcom/amazonaws/internal/config/JsonIndex;
       5: return

  public com.amazonaws.internal.config.JsonIndex<com.amazonaws.internal.config.HttpClientConfigJsonHelper, com.amazonaws.internal.config.HttpClientConfig>[] getHttpClients();
    Code:
       0: aload_0
       1: getfield      #6                  // Field httpClients:[Lcom/amazonaws/internal/config/JsonIndex;
       4: areturn

  public void setHttpClients(com.amazonaws.internal.config.JsonIndex<com.amazonaws.internal.config.HttpClientConfigJsonHelper, com.amazonaws.internal.config.HttpClientConfig>...);
    Code:
       0: aload_0
       1: aload_1
       2: putfield      #6                  // Field httpClients:[Lcom/amazonaws/internal/config/JsonIndex;
       5: return

  public com.amazonaws.internal.config.HostRegexToRegionMappingJsonHelper[] getHostRegexToRegionMappings();
    Code:
       0: aload_0
       1: getfield      #7                  // Field hostRegexToRegionMappings:[Lcom/amazonaws/internal/config/HostRegexToRegionMappingJsonHelper;
       4: areturn

  public void setHostRegexToRegionMappings(com.amazonaws.internal.config.HostRegexToRegionMappingJsonHelper[]);
    Code:
       0: aload_0
       1: aload_1
       2: putfield      #7                  // Field hostRegexToRegionMappings:[Lcom/amazonaws/internal/config/HostRegexToRegionMappingJsonHelper;
       5: return

  public java.lang.String getUserAgentTemplate();
    Code:
       0: aload_0
       1: getfield      #8                  // Field userAgentTemplate:Ljava/lang/String;
       4: areturn

  public void setUserAgentTemplate(java.lang.String);
    Code:
       0: aload_0
       1: aload_1
       2: putfield      #8                  // Field userAgentTemplate:Ljava/lang/String;
       5: return
}
