Compiled from "TransportProtocol.java"
public final class org.littleshoot.proxy.TransportProtocol extends java.lang.Enum<org.littleshoot.proxy.TransportProtocol> {
  public static final org.littleshoot.proxy.TransportProtocol TCP;

  public static final org.littleshoot.proxy.TransportProtocol UDT;

  private static final org.littleshoot.proxy.TransportProtocol[] $VALUES;

  public static org.littleshoot.proxy.TransportProtocol[] values();
    Code:
       0: getstatic     #1                  // Field $VALUES:[Lorg/littleshoot/proxy/TransportProtocol;
       3: invokevirtual #2                  // Method "[Lorg/littleshoot/proxy/TransportProtocol;".clone:()Ljava/lang/Object;
       6: checkcast     #3                  // class "[Lorg/littleshoot/proxy/TransportProtocol;"
       9: areturn

  public static org.littleshoot.proxy.TransportProtocol valueOf(java.lang.String);
    Code:
       0: ldc           #4                  // class org/littleshoot/proxy/TransportProtocol
       2: aload_0
       3: invokestatic  #5                  // Method java/lang/Enum.valueOf:(Ljava/lang/Class;Ljava/lang/String;)Ljava/lang/Enum;
       6: checkcast     #4                  // class org/littleshoot/proxy/TransportProtocol
       9: areturn

  private org.littleshoot.proxy.TransportProtocol();
    Code:
       0: aload_0
       1: aload_1
       2: iload_2
       3: invokespecial #6                  // Method java/lang/Enum."<init>":(Ljava/lang/String;I)V
       6: return

  static {};
    Code:
       0: new           #4                  // class org/littleshoot/proxy/TransportProtocol
       3: dup
       4: ldc           #7                  // String TCP
       6: iconst_0
       7: invokespecial #8                  // Method "<init>":(Ljava/lang/String;I)V
      10: putstatic     #9                  // Field TCP:Lorg/littleshoot/proxy/TransportProtocol;
      13: new           #4                  // class org/littleshoot/proxy/TransportProtocol
      16: dup
      17: ldc           #10                 // String UDT
      19: iconst_1
      20: invokespecial #8                  // Method "<init>":(Ljava/lang/String;I)V
      23: putstatic     #11                 // Field UDT:Lorg/littleshoot/proxy/TransportProtocol;
      26: iconst_2
      27: anewarray     #4                  // class org/littleshoot/proxy/TransportProtocol
      30: dup
      31: iconst_0
      32: getstatic     #9                  // Field TCP:Lorg/littleshoot/proxy/TransportProtocol;
      35: aastore
      36: dup
      37: iconst_1
      38: getstatic     #11                 // Field UDT:Lorg/littleshoot/proxy/TransportProtocol;
      41: aastore
      42: putstatic     #1                  // Field $VALUES:[Lorg/littleshoot/proxy/TransportProtocol;
      45: return
}
