Compiled from "IntegrationProperties.java"
public final class org.springframework.integration.context.IntegrationProperties {
  public static final java.lang.String INTEGRATION_PROPERTIES_PREFIX;

  public static final java.lang.String CHANNELS_AUTOCREATE;

  public static final java.lang.String CHANNELS_MAX_UNICAST_SUBSCRIBERS;

  public static final java.lang.String CHANNELS_MAX_BROADCAST_SUBSCRIBERS;

  public static final java.lang.String TASK_SCHEDULER_POOL_SIZE;

  public static final java.lang.String THROW_EXCEPTION_ON_LATE_REPLY;

  public static final java.lang.String READ_ONLY_HEADERS;

  public static final java.lang.String ENDPOINTS_NO_AUTO_STARTUP;

  private static java.util.Properties defaults;

  public static java.util.Properties defaults();
    Code:
       0: getstatic     #2                  // Field defaults:Ljava/util/Properties;
       3: areturn

  public static java.lang.String getExpressionFor(java.lang.String);
    Code:
       0: getstatic     #2                  // Field defaults:Ljava/util/Properties;
       3: aload_0
       4: invokevirtual #3                  // Method java/util/Properties.containsKey:(Ljava/lang/Object;)Z
       7: ifeq          35
      10: new           #4                  // class java/lang/StringBuilder
      13: dup
      14: invokespecial #5                  // Method java/lang/StringBuilder."<init>":()V
      17: ldc           #6                  // String #{T(org.springframework.integration.context.IntegrationContextUtils).getIntegrationProperties(beanFactory).getProperty(\'
      19: invokevirtual #7                  // Method java/lang/StringBuilder.append:(Ljava/lang/String;)Ljava/lang/StringBuilder;
      22: aload_0
      23: invokevirtual #7                  // Method java/lang/StringBuilder.append:(Ljava/lang/String;)Ljava/lang/StringBuilder;
      26: ldc           #8                  // String \')}
      28: invokevirtual #7                  // Method java/lang/StringBuilder.append:(Ljava/lang/String;)Ljava/lang/StringBuilder;
      31: invokevirtual #9                  // Method java/lang/StringBuilder.toString:()Ljava/lang/String;
      34: areturn
      35: new           #10                 // class java/lang/IllegalArgumentException
      38: dup
      39: new           #4                  // class java/lang/StringBuilder
      42: dup
      43: invokespecial #5                  // Method java/lang/StringBuilder."<init>":()V
      46: ldc           #11                 // String The provided key [
      48: invokevirtual #7                  // Method java/lang/StringBuilder.append:(Ljava/lang/String;)Ljava/lang/StringBuilder;
      51: aload_0
      52: invokevirtual #7                  // Method java/lang/StringBuilder.append:(Ljava/lang/String;)Ljava/lang/StringBuilder;
      55: ldc           #12                 // String ] isn\'t the one of Integration properties:
      57: invokevirtual #7                  // Method java/lang/StringBuilder.append:(Ljava/lang/String;)Ljava/lang/StringBuilder;
      60: getstatic     #2                  // Field defaults:Ljava/util/Properties;
      63: invokevirtual #13                 // Method java/util/Properties.keySet:()Ljava/util/Set;
      66: invokevirtual #14                 // Method java/lang/StringBuilder.append:(Ljava/lang/Object;)Ljava/lang/StringBuilder;
      69: invokevirtual #9                  // Method java/lang/StringBuilder.toString:()Ljava/lang/String;
      72: invokespecial #15                 // Method java/lang/IllegalArgumentException."<init>":(Ljava/lang/String;)V
      75: athrow

  private org.springframework.integration.context.IntegrationProperties();
    Code:
       0: aload_0
       1: invokespecial #16                 // Method java/lang/Object."<init>":()V
       4: return

  static {};
    Code:
       0: ldc           #17                 // String classpath*:META-INF/spring.integration.default.properties
       2: astore_0
       3: new           #18                 // class org/springframework/core/io/support/PathMatchingResourcePatternResolver
       6: dup
       7: ldc           #1                  // class org/springframework/integration/context/IntegrationProperties
       9: invokevirtual #19                 // Method java/lang/Class.getClassLoader:()Ljava/lang/ClassLoader;
      12: invokespecial #20                 // Method org/springframework/core/io/support/PathMatchingResourcePatternResolver."<init>":(Ljava/lang/ClassLoader;)V
      15: astore_1
      16: aload_1
      17: aload_0
      18: invokeinterface #21,  2           // InterfaceMethod org/springframework/core/io/support/ResourcePatternResolver.getResources:(Ljava/lang/String;)[Lorg/springframework/core/io/Resource;
      23: astore_2
      24: new           #22                 // class org/springframework/beans/factory/config/PropertiesFactoryBean
      27: dup
      28: invokespecial #23                 // Method org/springframework/beans/factory/config/PropertiesFactoryBean."<init>":()V
      31: astore_3
      32: aload_3
      33: aload_2
      34: invokevirtual #24                 // Method org/springframework/beans/factory/config/PropertiesFactoryBean.setLocations:([Lorg/springframework/core/io/Resource;)V
      37: aload_3
      38: invokevirtual #25                 // Method org/springframework/beans/factory/config/PropertiesFactoryBean.afterPropertiesSet:()V
      41: aload_3
      42: invokevirtual #26                 // Method org/springframework/beans/factory/config/PropertiesFactoryBean.getObject:()Ljava/util/Properties;
      45: putstatic     #2                  // Field defaults:Ljava/util/Properties;
      48: goto          85
      51: astore_1
      52: new           #28                 // class java/lang/IllegalStateException
      55: dup
      56: new           #4                  // class java/lang/StringBuilder
      59: dup
      60: invokespecial #5                  // Method java/lang/StringBuilder."<init>":()V
      63: ldc           #29                 // String Can\'t load \'
      65: invokevirtual #7                  // Method java/lang/StringBuilder.append:(Ljava/lang/String;)Ljava/lang/StringBuilder;
      68: aload_0
      69: invokevirtual #7                  // Method java/lang/StringBuilder.append:(Ljava/lang/String;)Ljava/lang/StringBuilder;
      72: ldc           #30                 // String \' resources.
      74: invokevirtual #7                  // Method java/lang/StringBuilder.append:(Ljava/lang/String;)Ljava/lang/StringBuilder;
      77: invokevirtual #9                  // Method java/lang/StringBuilder.toString:()Ljava/lang/String;
      80: aload_1
      81: invokespecial #31                 // Method java/lang/IllegalStateException."<init>":(Ljava/lang/String;Ljava/lang/Throwable;)V
      84: athrow
      85: return
    Exception table:
       from    to  target type
           3    48    51   Class java/io/IOException
}
