Compiled from "JSONWriter.scala"
public final class edu.psu.sagnik.research.inkscapesvgprocessing.writer.impl.JSONWriter$$anonfun$1 extends scala.runtime.AbstractFunction1<edu.psu.sagnik.research.inkscapesvgprocessing.model.SVGPath, edu.psu.sagnik.research.inkscapesvgprocessing.writer.model.SVGPathJson> implements scala.Serializable {
  public static final long serialVersionUID;

  public final edu.psu.sagnik.research.inkscapesvgprocessing.writer.model.SVGPathJson apply(edu.psu.sagnik.research.inkscapesvgprocessing.model.SVGPath);
    Code:
       0: new           #20                 // class edu/psu/sagnik/research/inkscapesvgprocessing/writer/model/SVGPathJson
       3: dup
       4: aload_1
       5: invokevirtual #26                 // Method edu/psu/sagnik/research/inkscapesvgprocessing/model/SVGPath.bb:()Lscala/Option;
       8: astore_2
       9: aload_2
      10: instanceof    #28                 // class scala/Some
      13: ifeq          37
      16: aload_2
      17: checkcast     #28                 // class scala/Some
      20: astore_3
      21: aload_3
      22: invokevirtual #32                 // Method scala/Some.x:()Ljava/lang/Object;
      25: checkcast     #34                 // class edu/psu/sagnik/research/inkscapesvgprocessing/model/Rectangle
      28: astore        4
      30: aload         4
      32: astore        5
      34: goto          60
      37: getstatic     #40                 // Field scala/None$.MODULE$:Lscala/None$;
      40: aload_2
      41: invokevirtual #46                 // Method java/lang/Object.equals:(Ljava/lang/Object;)Z
      44: ifeq          263
      47: new           #34                 // class edu/psu/sagnik/research/inkscapesvgprocessing/model/Rectangle
      50: dup
      51: fconst_0
      52: fconst_0
      53: fconst_0
      54: fconst_0
      55: invokespecial #50                 // Method edu/psu/sagnik/research/inkscapesvgprocessing/model/Rectangle."<init>":(FFFF)V
      58: astore        5
      60: aload         5
      62: aload_1
      63: invokevirtual #54                 // Method edu/psu/sagnik/research/inkscapesvgprocessing/model/SVGPath.pdContent:()Ljava/lang/String;
      66: new           #56                 // class edu/psu/sagnik/research/inkscapesvgprocessing/writer/model/PathStyle
      69: dup
      70: getstatic     #59                 // Field edu/psu/sagnik/research/inkscapesvgprocessing/writer/impl/JSONWriter$.MODULE$:Ledu/psu/sagnik/research/inkscapesvgprocessing/writer/impl/JSONWriter$;
      73: aload_1
      74: invokevirtual #62                 // Method edu/psu/sagnik/research/inkscapesvgprocessing/model/SVGPath.pContent:()Ljava/lang/String;
      77: ldc           #64                 // String fill:
      79: invokevirtual #68                 // Method edu/psu/sagnik/research/inkscapesvgprocessing/writer/impl/JSONWriter$.returnPattern:(Ljava/lang/String;Ljava/lang/String;)Ljava/lang/String;
      82: getstatic     #59                 // Field edu/psu/sagnik/research/inkscapesvgprocessing/writer/impl/JSONWriter$.MODULE$:Ledu/psu/sagnik/research/inkscapesvgprocessing/writer/impl/JSONWriter$;
      85: aload_1
      86: invokevirtual #62                 // Method edu/psu/sagnik/research/inkscapesvgprocessing/model/SVGPath.pContent:()Ljava/lang/String;
      89: ldc           #70                 // String stroke:
      91: invokevirtual #68                 // Method edu/psu/sagnik/research/inkscapesvgprocessing/writer/impl/JSONWriter$.returnPattern:(Ljava/lang/String;Ljava/lang/String;)Ljava/lang/String;
      94: ldc           #72                 // String -1
      96: getstatic     #59                 // Field edu/psu/sagnik/research/inkscapesvgprocessing/writer/impl/JSONWriter$.MODULE$:Ledu/psu/sagnik/research/inkscapesvgprocessing/writer/impl/JSONWriter$;
      99: aload_1
     100: invokevirtual #62                 // Method edu/psu/sagnik/research/inkscapesvgprocessing/model/SVGPath.pContent:()Ljava/lang/String;
     103: ldc           #74                 // String stroke-width:
     105: invokevirtual #68                 // Method edu/psu/sagnik/research/inkscapesvgprocessing/writer/impl/JSONWriter$.returnPattern:(Ljava/lang/String;Ljava/lang/String;)Ljava/lang/String;
     108: invokevirtual #77                 // Method java/lang/String.equals:(Ljava/lang/Object;)Z
     111: ifeq          119
     114: ldc           #78                 // float -1.0f
     116: goto          147
     119: new           #80                 // class scala/collection/immutable/StringOps
     122: dup
     123: getstatic     #85                 // Field scala/Predef$.MODULE$:Lscala/Predef$;
     126: getstatic     #59                 // Field edu/psu/sagnik/research/inkscapesvgprocessing/writer/impl/JSONWriter$.MODULE$:Ledu/psu/sagnik/research/inkscapesvgprocessing/writer/impl/JSONWriter$;
     129: aload_1
     130: invokevirtual #62                 // Method edu/psu/sagnik/research/inkscapesvgprocessing/model/SVGPath.pContent:()Ljava/lang/String;
     133: ldc           #74                 // String stroke-width:
     135: invokevirtual #68                 // Method edu/psu/sagnik/research/inkscapesvgprocessing/writer/impl/JSONWriter$.returnPattern:(Ljava/lang/String;Ljava/lang/String;)Ljava/lang/String;
     138: invokevirtual #89                 // Method scala/Predef$.augmentString:(Ljava/lang/String;)Ljava/lang/String;
     141: invokespecial #92                 // Method scala/collection/immutable/StringOps."<init>":(Ljava/lang/String;)V
     144: invokevirtual #96                 // Method scala/collection/immutable/StringOps.toFloat:()F
     147: getstatic     #59                 // Field edu/psu/sagnik/research/inkscapesvgprocessing/writer/impl/JSONWriter$.MODULE$:Ledu/psu/sagnik/research/inkscapesvgprocessing/writer/impl/JSONWriter$;
     150: aload_1
     151: invokevirtual #62                 // Method edu/psu/sagnik/research/inkscapesvgprocessing/model/SVGPath.pContent:()Ljava/lang/String;
     154: ldc           #98                 // String stroke-linecap:
     156: invokevirtual #68                 // Method edu/psu/sagnik/research/inkscapesvgprocessing/writer/impl/JSONWriter$.returnPattern:(Ljava/lang/String;Ljava/lang/String;)Ljava/lang/String;
     159: getstatic     #59                 // Field edu/psu/sagnik/research/inkscapesvgprocessing/writer/impl/JSONWriter$.MODULE$:Ledu/psu/sagnik/research/inkscapesvgprocessing/writer/impl/JSONWriter$;
     162: aload_1
     163: invokevirtual #62                 // Method edu/psu/sagnik/research/inkscapesvgprocessing/model/SVGPath.pContent:()Ljava/lang/String;
     166: ldc           #100                // String stroke-linejoin:
     168: invokevirtual #68                 // Method edu/psu/sagnik/research/inkscapesvgprocessing/writer/impl/JSONWriter$.returnPattern:(Ljava/lang/String;Ljava/lang/String;)Ljava/lang/String;
     171: getstatic     #59                 // Field edu/psu/sagnik/research/inkscapesvgprocessing/writer/impl/JSONWriter$.MODULE$:Ledu/psu/sagnik/research/inkscapesvgprocessing/writer/impl/JSONWriter$;
     174: aload_1
     175: invokevirtual #62                 // Method edu/psu/sagnik/research/inkscapesvgprocessing/model/SVGPath.pContent:()Ljava/lang/String;
     178: ldc           #102                // String stroke-miterlimit:
     180: invokevirtual #68                 // Method edu/psu/sagnik/research/inkscapesvgprocessing/writer/impl/JSONWriter$.returnPattern:(Ljava/lang/String;Ljava/lang/String;)Ljava/lang/String;
     183: getstatic     #59                 // Field edu/psu/sagnik/research/inkscapesvgprocessing/writer/impl/JSONWriter$.MODULE$:Ledu/psu/sagnik/research/inkscapesvgprocessing/writer/impl/JSONWriter$;
     186: aload_1
     187: invokevirtual #62                 // Method edu/psu/sagnik/research/inkscapesvgprocessing/model/SVGPath.pContent:()Ljava/lang/String;
     190: ldc           #104                // String stroke-dasharray:
     192: invokevirtual #68                 // Method edu/psu/sagnik/research/inkscapesvgprocessing/writer/impl/JSONWriter$.returnPattern:(Ljava/lang/String;Ljava/lang/String;)Ljava/lang/String;
     195: ldc           #72                 // String -1
     197: getstatic     #59                 // Field edu/psu/sagnik/research/inkscapesvgprocessing/writer/impl/JSONWriter$.MODULE$:Ledu/psu/sagnik/research/inkscapesvgprocessing/writer/impl/JSONWriter$;
     200: aload_1
     201: invokevirtual #62                 // Method edu/psu/sagnik/research/inkscapesvgprocessing/model/SVGPath.pContent:()Ljava/lang/String;
     204: ldc           #106                // String stroke-opacity:
     206: ldc           #108                // String
     208: invokevirtual #111                // Method edu/psu/sagnik/research/inkscapesvgprocessing/writer/impl/JSONWriter$.returnPattern:(Ljava/lang/String;Ljava/lang/String;Ljava/lang/String;)Ljava/lang/String;
     211: invokevirtual #77                 // Method java/lang/String.equals:(Ljava/lang/Object;)Z
     214: ifeq          222
     217: ldc           #78                 // float -1.0f
     219: goto          252
     222: new           #80                 // class scala/collection/immutable/StringOps
     225: dup
     226: getstatic     #85                 // Field scala/Predef$.MODULE$:Lscala/Predef$;
     229: getstatic     #59                 // Field edu/psu/sagnik/research/inkscapesvgprocessing/writer/impl/JSONWriter$.MODULE$:Ledu/psu/sagnik/research/inkscapesvgprocessing/writer/impl/JSONWriter$;
     232: aload_1
     233: invokevirtual #62                 // Method edu/psu/sagnik/research/inkscapesvgprocessing/model/SVGPath.pContent:()Ljava/lang/String;
     236: ldc           #106                // String stroke-opacity:
     238: ldc           #108                // String
     240: invokevirtual #111                // Method edu/psu/sagnik/research/inkscapesvgprocessing/writer/impl/JSONWriter$.returnPattern:(Ljava/lang/String;Ljava/lang/String;Ljava/lang/String;)Ljava/lang/String;
     243: invokevirtual #89                 // Method scala/Predef$.augmentString:(Ljava/lang/String;)Ljava/lang/String;
     246: invokespecial #92                 // Method scala/collection/immutable/StringOps."<init>":(Ljava/lang/String;)V
     249: invokevirtual #96                 // Method scala/collection/immutable/StringOps.toFloat:()F
     252: invokespecial #114                // Method edu/psu/sagnik/research/inkscapesvgprocessing/writer/model/PathStyle."<init>":(Ljava/lang/String;Ljava/lang/String;FLjava/lang/String;Ljava/lang/String;Ljava/lang/String;Ljava/lang/String;F)V
     255: aload_1
     256: invokevirtual #62                 // Method edu/psu/sagnik/research/inkscapesvgprocessing/model/SVGPath.pContent:()Ljava/lang/String;
     259: invokespecial #117                // Method edu/psu/sagnik/research/inkscapesvgprocessing/writer/model/SVGPathJson."<init>":(Ledu/psu/sagnik/research/inkscapesvgprocessing/model/Rectangle;Ljava/lang/String;Ledu/psu/sagnik/research/inkscapesvgprocessing/writer/model/PathStyle;Ljava/lang/String;)V
     262: areturn
     263: new           #119                // class scala/MatchError
     266: dup
     267: aload_2
     268: invokespecial #122                // Method scala/MatchError."<init>":(Ljava/lang/Object;)V
     271: athrow

  public final java.lang.Object apply(java.lang.Object);
    Code:
       0: aload_0
       1: aload_1
       2: checkcast     #22                 // class edu/psu/sagnik/research/inkscapesvgprocessing/model/SVGPath
       5: invokevirtual #131                // Method apply:(Ledu/psu/sagnik/research/inkscapesvgprocessing/model/SVGPath;)Ledu/psu/sagnik/research/inkscapesvgprocessing/writer/model/SVGPathJson;
       8: areturn

  public edu.psu.sagnik.research.inkscapesvgprocessing.writer.impl.JSONWriter$$anonfun$1();
    Code:
       0: aload_0
       1: invokespecial #136                // Method scala/runtime/AbstractFunction1."<init>":()V
       4: return
}
