Compiled from "AbstractValidationContext.java"
abstract class org.hibernate.validator.internal.engine.validationcontext.AbstractValidationContext<T> implements org.hibernate.validator.internal.engine.validationcontext.BaseBeanValidationContext<T> {
  private static final org.hibernate.validator.internal.util.logging.Log LOG;

  private final org.hibernate.validator.internal.engine.constraintvalidation.ConstraintValidatorManager constraintValidatorManager;

  private final T rootBean;

  private final java.lang.Class<T> rootBeanClass;

  private final org.hibernate.validator.internal.metadata.aggregated.BeanMetaData<T> rootBeanMetaData;

  private final jakarta.validation.ConstraintValidatorFactory constraintValidatorFactory;

  protected final org.hibernate.validator.internal.engine.validationcontext.ValidatorScopedContext validatorScopedContext;

  private final jakarta.validation.TraversableResolver traversableResolver;

  private final org.hibernate.validator.constraintvalidation.HibernateConstraintValidatorInitializationContext constraintValidatorInitializationContext;

  private final boolean disableAlreadyValidatedBeanTracking;

  private java.util.Set<org.hibernate.validator.internal.engine.validationcontext.AbstractValidationContext$BeanPathMetaConstraintProcessedUnit> processedPathUnits;

  private java.util.Set<org.hibernate.validator.internal.engine.validationcontext.AbstractValidationContext$BeanGroupProcessedUnit> processedGroupUnits;

  private java.util.Map<java.lang.Object, java.util.Set<org.hibernate.validator.internal.engine.path.PathImpl>> processedPathsPerBean;

  private java.util.Set<jakarta.validation.ConstraintViolation<T>> failingConstraintViolations;

  protected org.hibernate.validator.internal.engine.validationcontext.AbstractValidationContext(org.hibernate.validator.internal.engine.constraintvalidation.ConstraintValidatorManager, jakarta.validation.ConstraintValidatorFactory, org.hibernate.validator.internal.engine.validationcontext.ValidatorScopedContext, jakarta.validation.TraversableResolver, org.hibernate.validator.constraintvalidation.HibernateConstraintValidatorInitializationContext, T, java.lang.Class<T>, org.hibernate.validator.internal.metadata.aggregated.BeanMetaData<T>, boolean);
    Code:
       0: aload_0
       1: invokespecial #1                  // Method java/lang/Object."<init>":()V
       4: aload_0
       5: aload_1
       6: putfield      #7                  // Field constraintValidatorManager:Lorg/hibernate/validator/internal/engine/constraintvalidation/ConstraintValidatorManager;
       9: aload_0
      10: aload_3
      11: putfield      #13                 // Field validatorScopedContext:Lorg/hibernate/validator/internal/engine/validationcontext/ValidatorScopedContext;
      14: aload_0
      15: aload_2
      16: putfield      #17                 // Field constraintValidatorFactory:Ljakarta/validation/ConstraintValidatorFactory;
      19: aload_0
      20: aload         4
      22: putfield      #21                 // Field traversableResolver:Ljakarta/validation/TraversableResolver;
      25: aload_0
      26: aload         5
      28: putfield      #25                 // Field constraintValidatorInitializationContext:Lorg/hibernate/validator/constraintvalidation/HibernateConstraintValidatorInitializationContext;
      31: aload_0
      32: aload         6
      34: putfield      #29                 // Field rootBean:Ljava/lang/Object;
      37: aload_0
      38: aload         7
      40: putfield      #33                 // Field rootBeanClass:Ljava/lang/Class;
      43: aload_0
      44: aload         8
      46: putfield      #37                 // Field rootBeanMetaData:Lorg/hibernate/validator/internal/metadata/aggregated/BeanMetaData;
      49: aload_0
      50: iload         9
      52: putfield      #41                 // Field disableAlreadyValidatedBeanTracking:Z
      55: return

  public T getRootBean();
    Code:
       0: aload_0
       1: getfield      #29                 // Field rootBean:Ljava/lang/Object;
       4: areturn

  public java.lang.Class<T> getRootBeanClass();
    Code:
       0: aload_0
       1: getfield      #33                 // Field rootBeanClass:Ljava/lang/Class;
       4: areturn

  public org.hibernate.validator.internal.metadata.aggregated.BeanMetaData<T> getRootBeanMetaData();
    Code:
       0: aload_0
       1: getfield      #37                 // Field rootBeanMetaData:Lorg/hibernate/validator/internal/metadata/aggregated/BeanMetaData;
       4: areturn

  public jakarta.validation.TraversableResolver getTraversableResolver();
    Code:
       0: aload_0
       1: getfield      #21                 // Field traversableResolver:Ljakarta/validation/TraversableResolver;
       4: areturn

  public boolean isFailFastModeEnabled();
    Code:
       0: aload_0
       1: getfield      #13                 // Field validatorScopedContext:Lorg/hibernate/validator/internal/engine/validationcontext/ValidatorScopedContext;
       4: invokevirtual #45                 // Method org/hibernate/validator/internal/engine/validationcontext/ValidatorScopedContext.isFailFast:()Z
       7: ireturn

  public boolean isShowValidatedValuesInTraceLogs();
    Code:
       0: aload_0
       1: getfield      #13                 // Field validatorScopedContext:Lorg/hibernate/validator/internal/engine/validationcontext/ValidatorScopedContext;
       4: invokevirtual #51                 // Method org/hibernate/validator/internal/engine/validationcontext/ValidatorScopedContext.isShowValidatedValuesInTraceLogs:()Z
       7: ireturn

  public org.hibernate.validator.internal.engine.constraintvalidation.ConstraintValidatorManager getConstraintValidatorManager();
    Code:
       0: aload_0
       1: getfield      #7                  // Field constraintValidatorManager:Lorg/hibernate/validator/internal/engine/constraintvalidation/ConstraintValidatorManager;
       4: areturn

  public org.hibernate.validator.constraintvalidation.HibernateConstraintValidatorInitializationContext getConstraintValidatorInitializationContext();
    Code:
       0: aload_0
       1: getfield      #25                 // Field constraintValidatorInitializationContext:Lorg/hibernate/validator/constraintvalidation/HibernateConstraintValidatorInitializationContext;
       4: areturn

  public jakarta.validation.ConstraintValidatorFactory getConstraintValidatorFactory();
    Code:
       0: aload_0
       1: getfield      #17                 // Field constraintValidatorFactory:Ljakarta/validation/ConstraintValidatorFactory;
       4: areturn

  public boolean isBeanAlreadyValidated(java.lang.Object, java.lang.Class<?>, org.hibernate.validator.internal.engine.path.PathImpl);
    Code:
       0: aload_0
       1: getfield      #41                 // Field disableAlreadyValidatedBeanTracking:Z
       4: ifeq          9
       7: iconst_0
       8: ireturn
       9: aload_0
      10: aload_1
      11: aload_2
      12: invokevirtual #54                 // Method isAlreadyValidatedForCurrentGroup:(Ljava/lang/Object;Ljava/lang/Class;)Z
      15: istore        4
      17: iload         4
      19: ifeq          30
      22: aload_0
      23: aload_1
      24: aload_3
      25: invokevirtual #58                 // Method isAlreadyValidatedForPath:(Ljava/lang/Object;Lorg/hibernate/validator/internal/engine/path/PathImpl;)Z
      28: istore        4
      30: iload         4
      32: ireturn

  public void markCurrentBeanAsProcessed(org.hibernate.validator.internal.engine.valuecontext.ValueContext<?, ?>);
    Code:
       0: aload_0
       1: getfield      #41                 // Field disableAlreadyValidatedBeanTracking:Z
       4: ifeq          8
       7: return
       8: aload_0
       9: aload_1
      10: invokevirtual #62                 // Method org/hibernate/validator/internal/engine/valuecontext/ValueContext.getCurrentBean:()Ljava/lang/Object;
      13: aload_1
      14: invokevirtual #68                 // Method org/hibernate/validator/internal/engine/valuecontext/ValueContext.getCurrentGroup:()Ljava/lang/Class;
      17: invokevirtual #72                 // Method markCurrentBeanAsProcessedForCurrentGroup:(Ljava/lang/Object;Ljava/lang/Class;)V
      20: aload_0
      21: aload_1
      22: invokevirtual #62                 // Method org/hibernate/validator/internal/engine/valuecontext/ValueContext.getCurrentBean:()Ljava/lang/Object;
      25: aload_1
      26: invokevirtual #76                 // Method org/hibernate/validator/internal/engine/valuecontext/ValueContext.getPropertyPath:()Lorg/hibernate/validator/internal/engine/path/PathImpl;
      29: invokevirtual #80                 // Method markCurrentBeanAsProcessedForCurrentPath:(Ljava/lang/Object;Lorg/hibernate/validator/internal/engine/path/PathImpl;)V
      32: return

  public java.util.Set<jakarta.validation.ConstraintViolation<T>> getFailingConstraints();
    Code:
       0: aload_0
       1: getfield      #84                 // Field failingConstraintViolations:Ljava/util/Set;
       4: ifnonnull     11
       7: invokestatic  #88                 // Method java/util/Collections.emptySet:()Ljava/util/Set;
      10: areturn
      11: aload_0
      12: getfield      #84                 // Field failingConstraintViolations:Ljava/util/Set;
      15: areturn

  public void addConstraintFailure(org.hibernate.validator.internal.engine.valuecontext.ValueContext<?, ?>, org.hibernate.validator.internal.engine.constraintvalidation.ConstraintViolationCreationContext, jakarta.validation.metadata.ConstraintDescriptor<?>);
    Code:
       0: aload_2
       1: invokevirtual #94                 // Method org/hibernate/validator/internal/engine/constraintvalidation/ConstraintViolationCreationContext.getMessage:()Ljava/lang/String;
       4: astore        4
       6: aload_0
       7: aload         4
       9: aload_2
      10: invokevirtual #100                // Method org/hibernate/validator/internal/engine/constraintvalidation/ConstraintViolationCreationContext.getExpressionLanguageFeatureLevel:()Lorg/hibernate/validator/messageinterpolation/ExpressionLanguageFeatureLevel;
      13: aload_2
      14: invokevirtual #104                // Method org/hibernate/validator/internal/engine/constraintvalidation/ConstraintViolationCreationContext.isCustomViolation:()Z
      17: aload_1
      18: invokevirtual #107                // Method org/hibernate/validator/internal/engine/valuecontext/ValueContext.getCurrentValidatedValue:()Ljava/lang/Object;
      21: aload_3
      22: aload_2
      23: invokevirtual #110                // Method org/hibernate/validator/internal/engine/constraintvalidation/ConstraintViolationCreationContext.getPath:()Lorg/hibernate/validator/internal/engine/path/PathImpl;
      26: aload_2
      27: invokevirtual #113                // Method org/hibernate/validator/internal/engine/constraintvalidation/ConstraintViolationCreationContext.getMessageParameters:()Ljava/util/Map;
      30: aload_2
      31: invokevirtual #117                // Method org/hibernate/validator/internal/engine/constraintvalidation/ConstraintViolationCreationContext.getExpressionVariables:()Ljava/util/Map;
      34: invokevirtual #120                // Method interpolate:(Ljava/lang/String;Lorg/hibernate/validator/messageinterpolation/ExpressionLanguageFeatureLevel;ZLjava/lang/Object;Ljakarta/validation/metadata/ConstraintDescriptor;Ljakarta/validation/Path;Ljava/util/Map;Ljava/util/Map;)Ljava/lang/String;
      37: astore        5
      39: aload_2
      40: invokevirtual #110                // Method org/hibernate/validator/internal/engine/constraintvalidation/ConstraintViolationCreationContext.getPath:()Lorg/hibernate/validator/internal/engine/path/PathImpl;
      43: invokestatic  #124                // Method org/hibernate/validator/internal/engine/path/PathImpl.createCopy:(Lorg/hibernate/validator/internal/engine/path/PathImpl;)Lorg/hibernate/validator/internal/engine/path/PathImpl;
      46: astore        6
      48: aload_0
      49: invokevirtual #130                // Method getInitializedFailingConstraintViolations:()Ljava/util/Set;
      52: aload_0
      53: aload         4
      55: aload         5
      57: aload         6
      59: aload_3
      60: aload_1
      61: aload_2
      62: invokevirtual #133                // Method createConstraintViolation:(Ljava/lang/String;Ljava/lang/String;Ljakarta/validation/Path;Ljakarta/validation/metadata/ConstraintDescriptor;Lorg/hibernate/validator/internal/engine/valuecontext/ValueContext;Lorg/hibernate/validator/internal/engine/constraintvalidation/ConstraintViolationCreationContext;)Ljakarta/validation/ConstraintViolation;
      65: invokeinterface #137,  2          // InterfaceMethod java/util/Set.add:(Ljava/lang/Object;)Z
      70: pop
      71: return

  protected abstract jakarta.validation.ConstraintViolation<T> createConstraintViolation(java.lang.String, java.lang.String, jakarta.validation.Path, jakarta.validation.metadata.ConstraintDescriptor<?>, org.hibernate.validator.internal.engine.valuecontext.ValueContext<?, ?>, org.hibernate.validator.internal.engine.constraintvalidation.ConstraintViolationCreationContext);

  public boolean hasMetaConstraintBeenProcessed(java.lang.Object, jakarta.validation.Path, org.hibernate.validator.internal.metadata.core.MetaConstraint<?>);
    Code:
       0: aload_3
       1: invokevirtual #143                // Method org/hibernate/validator/internal/metadata/core/MetaConstraint.isDefinedForOneGroupOnly:()Z
       4: ifeq          9
       7: iconst_0
       8: ireturn
       9: aload_0
      10: invokevirtual #148                // Method getInitializedProcessedPathUnits:()Ljava/util/Set;
      13: new           #151                // class org/hibernate/validator/internal/engine/validationcontext/AbstractValidationContext$BeanPathMetaConstraintProcessedUnit
      16: dup
      17: aload_1
      18: aload_2
      19: aload_3
      20: invokespecial #153                // Method org/hibernate/validator/internal/engine/validationcontext/AbstractValidationContext$BeanPathMetaConstraintProcessedUnit."<init>":(Ljava/lang/Object;Ljakarta/validation/Path;Lorg/hibernate/validator/internal/metadata/core/MetaConstraint;)V
      23: invokeinterface #156,  2          // InterfaceMethod java/util/Set.contains:(Ljava/lang/Object;)Z
      28: ireturn

  public void markConstraintProcessed(java.lang.Object, jakarta.validation.Path, org.hibernate.validator.internal.metadata.core.MetaConstraint<?>);
    Code:
       0: aload_3
       1: invokevirtual #143                // Method org/hibernate/validator/internal/metadata/core/MetaConstraint.isDefinedForOneGroupOnly:()Z
       4: ifeq          8
       7: return
       8: aload_0
       9: invokevirtual #148                // Method getInitializedProcessedPathUnits:()Ljava/util/Set;
      12: new           #151                // class org/hibernate/validator/internal/engine/validationcontext/AbstractValidationContext$BeanPathMetaConstraintProcessedUnit
      15: dup
      16: aload_1
      17: aload_2
      18: aload_3
      19: invokespecial #153                // Method org/hibernate/validator/internal/engine/validationcontext/AbstractValidationContext$BeanPathMetaConstraintProcessedUnit."<init>":(Ljava/lang/Object;Ljakarta/validation/Path;Lorg/hibernate/validator/internal/metadata/core/MetaConstraint;)V
      22: invokeinterface #137,  2          // InterfaceMethod java/util/Set.add:(Ljava/lang/Object;)Z
      27: pop
      28: return

  public org.hibernate.validator.internal.engine.constraintvalidation.ConstraintValidatorContextImpl createConstraintValidatorContextFor(org.hibernate.validator.internal.metadata.descriptor.ConstraintDescriptorImpl<?>, org.hibernate.validator.internal.engine.path.PathImpl);
    Code:
       0: new           #159                // class org/hibernate/validator/internal/engine/constraintvalidation/ConstraintValidatorContextImpl
       3: dup
       4: aload_0
       5: getfield      #13                 // Field validatorScopedContext:Lorg/hibernate/validator/internal/engine/validationcontext/ValidatorScopedContext;
       8: invokevirtual #161                // Method org/hibernate/validator/internal/engine/validationcontext/ValidatorScopedContext.getClockProvider:()Ljakarta/validation/ClockProvider;
      11: aload_2
      12: aload_1
      13: aload_0
      14: getfield      #13                 // Field validatorScopedContext:Lorg/hibernate/validator/internal/engine/validationcontext/ValidatorScopedContext;
      17: invokevirtual #165                // Method org/hibernate/validator/internal/engine/validationcontext/ValidatorScopedContext.getConstraintValidatorPayload:()Ljava/lang/Object;
      20: aload_0
      21: getfield      #13                 // Field validatorScopedContext:Lorg/hibernate/validator/internal/engine/validationcontext/ValidatorScopedContext;
      24: invokevirtual #168                // Method org/hibernate/validator/internal/engine/validationcontext/ValidatorScopedContext.getConstraintExpressionLanguageFeatureLevel:()Lorg/hibernate/validator/messageinterpolation/ExpressionLanguageFeatureLevel;
      27: aload_0
      28: getfield      #13                 // Field validatorScopedContext:Lorg/hibernate/validator/internal/engine/validationcontext/ValidatorScopedContext;
      31: invokevirtual #171                // Method org/hibernate/validator/internal/engine/validationcontext/ValidatorScopedContext.getCustomViolationExpressionLanguageFeatureLevel:()Lorg/hibernate/validator/messageinterpolation/ExpressionLanguageFeatureLevel;
      34: invokespecial #174                // Method org/hibernate/validator/internal/engine/constraintvalidation/ConstraintValidatorContextImpl."<init>":(Ljakarta/validation/ClockProvider;Lorg/hibernate/validator/internal/engine/path/PathImpl;Ljakarta/validation/metadata/ConstraintDescriptor;Ljava/lang/Object;Lorg/hibernate/validator/messageinterpolation/ExpressionLanguageFeatureLevel;Lorg/hibernate/validator/messageinterpolation/ExpressionLanguageFeatureLevel;)V
      37: areturn

  public abstract java.lang.String toString();

  private java.lang.String interpolate(java.lang.String, org.hibernate.validator.messageinterpolation.ExpressionLanguageFeatureLevel, boolean, java.lang.Object, jakarta.validation.metadata.ConstraintDescriptor<?>, jakarta.validation.Path, java.util.Map<java.lang.String, java.lang.Object>, java.util.Map<java.lang.String, java.lang.Object>);
    Code:
       0: new           #177                // class org/hibernate/validator/internal/engine/MessageInterpolatorContext
       3: dup
       4: aload         5
       6: aload         4
       8: aload_0
       9: invokevirtual #179                // Method getRootBeanClass:()Ljava/lang/Class;
      12: aload         6
      14: aload         7
      16: aload         8
      18: aload_2
      19: iload_3
      20: invokespecial #182                // Method org/hibernate/validator/internal/engine/MessageInterpolatorContext."<init>":(Ljakarta/validation/metadata/ConstraintDescriptor;Ljava/lang/Object;Ljava/lang/Class;Ljakarta/validation/Path;Ljava/util/Map;Ljava/util/Map;Lorg/hibernate/validator/messageinterpolation/ExpressionLanguageFeatureLevel;Z)V
      23: astore        9
      25: aload_0
      26: getfield      #13                 // Field validatorScopedContext:Lorg/hibernate/validator/internal/engine/validationcontext/ValidatorScopedContext;
      29: invokevirtual #185                // Method org/hibernate/validator/internal/engine/validationcontext/ValidatorScopedContext.getMessageInterpolator:()Ljakarta/validation/MessageInterpolator;
      32: aload_1
      33: aload         9
      35: invokeinterface #189,  3          // InterfaceMethod jakarta/validation/MessageInterpolator.interpolate:(Ljava/lang/String;Ljakarta/validation/MessageInterpolator$Context;)Ljava/lang/String;
      40: areturn
      41: astore        10
      43: aload         10
      45: athrow
      46: astore        10
      48: getstatic     #198                // Field LOG:Lorg/hibernate/validator/internal/util/logging/Log;
      51: aload         10
      53: invokeinterface #202,  2          // InterfaceMethod org/hibernate/validator/internal/util/logging/Log.getExceptionOccurredDuringMessageInterpolationException:(Ljava/lang/Exception;)Ljakarta/validation/ValidationException;
      58: athrow
    Exception table:
       from    to  target type
          25    40    41   Class jakarta/validation/ValidationException
          25    40    46   Class java/lang/Exception

  private boolean isAlreadyValidatedForPath(java.lang.Object, org.hibernate.validator.internal.engine.path.PathImpl);
    Code:
       0: aload_0
       1: invokevirtual #208                // Method getInitializedProcessedPathsPerBean:()Ljava/util/Map;
       4: aload_1
       5: invokeinterface #211,  2          // InterfaceMethod java/util/Map.get:(Ljava/lang/Object;)Ljava/lang/Object;
      10: checkcast     #138                // class java/util/Set
      13: astore_3
      14: aload_3
      15: ifnonnull     20
      18: iconst_0
      19: ireturn
      20: aload_3
      21: invokeinterface #217,  1          // InterfaceMethod java/util/Set.iterator:()Ljava/util/Iterator;
      26: astore        4
      28: aload         4
      30: invokeinterface #221,  1          // InterfaceMethod java/util/Iterator.hasNext:()Z
      35: ifeq          90
      38: aload         4
      40: invokeinterface #226,  1          // InterfaceMethod java/util/Iterator.next:()Ljava/lang/Object;
      45: checkcast     #125                // class org/hibernate/validator/internal/engine/path/PathImpl
      48: astore        5
      50: aload_2
      51: invokevirtual #229                // Method org/hibernate/validator/internal/engine/path/PathImpl.isRootPath:()Z
      54: ifne          85
      57: aload         5
      59: invokevirtual #229                // Method org/hibernate/validator/internal/engine/path/PathImpl.isRootPath:()Z
      62: ifne          85
      65: aload_0
      66: aload_2
      67: aload         5
      69: invokevirtual #232                // Method isSubPathOf:(Ljakarta/validation/Path;Ljakarta/validation/Path;)Z
      72: ifne          85
      75: aload_0
      76: aload         5
      78: aload_2
      79: invokevirtual #232                // Method isSubPathOf:(Ljakarta/validation/Path;Ljakarta/validation/Path;)Z
      82: ifeq          87
      85: iconst_1
      86: ireturn
      87: goto          28
      90: iconst_0
      91: ireturn

  private boolean isSubPathOf(jakarta.validation.Path, jakarta.validation.Path);
    Code:
       0: aload_1
       1: invokeinterface #236,  1          // InterfaceMethod jakarta/validation/Path.iterator:()Ljava/util/Iterator;
       6: astore_3
       7: aload_2
       8: invokeinterface #236,  1          // InterfaceMethod jakarta/validation/Path.iterator:()Ljava/util/Iterator;
      13: astore        4
      15: aload_3
      16: invokeinterface #221,  1          // InterfaceMethod java/util/Iterator.hasNext:()Z
      21: ifeq          74
      24: aload_3
      25: invokeinterface #226,  1          // InterfaceMethod java/util/Iterator.next:()Ljava/lang/Object;
      30: checkcast     #239                // class jakarta/validation/Path$Node
      33: astore        5
      35: aload         4
      37: invokeinterface #221,  1          // InterfaceMethod java/util/Iterator.hasNext:()Z
      42: ifne          47
      45: iconst_0
      46: ireturn
      47: aload         4
      49: invokeinterface #226,  1          // InterfaceMethod java/util/Iterator.next:()Ljava/lang/Object;
      54: checkcast     #239                // class jakarta/validation/Path$Node
      57: astore        6
      59: aload         5
      61: aload         6
      63: invokevirtual #241                // Method java/lang/Object.equals:(Ljava/lang/Object;)Z
      66: ifne          71
      69: iconst_0
      70: ireturn
      71: goto          15
      74: iconst_1
      75: ireturn

  private boolean isAlreadyValidatedForCurrentGroup(java.lang.Object, java.lang.Class<?>);
    Code:
       0: aload_0
       1: invokevirtual #244                // Method getInitializedProcessedGroupUnits:()Ljava/util/Set;
       4: new           #247                // class org/hibernate/validator/internal/engine/validationcontext/AbstractValidationContext$BeanGroupProcessedUnit
       7: dup
       8: aload_1
       9: aload_2
      10: invokespecial #249                // Method org/hibernate/validator/internal/engine/validationcontext/AbstractValidationContext$BeanGroupProcessedUnit."<init>":(Ljava/lang/Object;Ljava/lang/Class;)V
      13: invokeinterface #156,  2          // InterfaceMethod java/util/Set.contains:(Ljava/lang/Object;)Z
      18: ireturn

  private void markCurrentBeanAsProcessedForCurrentPath(java.lang.Object, org.hibernate.validator.internal.engine.path.PathImpl);
    Code:
       0: aload_0
       1: invokevirtual #208                // Method getInitializedProcessedPathsPerBean:()Ljava/util/Map;
       4: astore_3
       5: aload_3
       6: aload_1
       7: invokeinterface #211,  2          // InterfaceMethod java/util/Map.get:(Ljava/lang/Object;)Ljava/lang/Object;
      12: checkcast     #138                // class java/util/Set
      15: astore        4
      17: aload         4
      19: ifnonnull     41
      22: new           #251                // class java/util/HashSet
      25: dup
      26: invokespecial #253                // Method java/util/HashSet."<init>":()V
      29: astore        4
      31: aload_3
      32: aload_1
      33: aload         4
      35: invokeinterface #254,  3          // InterfaceMethod java/util/Map.put:(Ljava/lang/Object;Ljava/lang/Object;)Ljava/lang/Object;
      40: pop
      41: aload         4
      43: aload_2
      44: invokestatic  #124                // Method org/hibernate/validator/internal/engine/path/PathImpl.createCopy:(Lorg/hibernate/validator/internal/engine/path/PathImpl;)Lorg/hibernate/validator/internal/engine/path/PathImpl;
      47: invokeinterface #137,  2          // InterfaceMethod java/util/Set.add:(Ljava/lang/Object;)Z
      52: pop
      53: return

  private void markCurrentBeanAsProcessedForCurrentGroup(java.lang.Object, java.lang.Class<?>);
    Code:
       0: aload_0
       1: invokevirtual #244                // Method getInitializedProcessedGroupUnits:()Ljava/util/Set;
       4: new           #247                // class org/hibernate/validator/internal/engine/validationcontext/AbstractValidationContext$BeanGroupProcessedUnit
       7: dup
       8: aload_1
       9: aload_2
      10: invokespecial #249                // Method org/hibernate/validator/internal/engine/validationcontext/AbstractValidationContext$BeanGroupProcessedUnit."<init>":(Ljava/lang/Object;Ljava/lang/Class;)V
      13: invokeinterface #137,  2          // InterfaceMethod java/util/Set.add:(Ljava/lang/Object;)Z
      18: pop
      19: return

  private java.util.Set<org.hibernate.validator.internal.engine.validationcontext.AbstractValidationContext$BeanPathMetaConstraintProcessedUnit> getInitializedProcessedPathUnits();
    Code:
       0: aload_0
       1: getfield      #258                // Field processedPathUnits:Ljava/util/Set;
       4: ifnonnull     18
       7: aload_0
       8: new           #251                // class java/util/HashSet
      11: dup
      12: invokespecial #253                // Method java/util/HashSet."<init>":()V
      15: putfield      #258                // Field processedPathUnits:Ljava/util/Set;
      18: aload_0
      19: getfield      #258                // Field processedPathUnits:Ljava/util/Set;
      22: areturn

  private java.util.Set<org.hibernate.validator.internal.engine.validationcontext.AbstractValidationContext$BeanGroupProcessedUnit> getInitializedProcessedGroupUnits();
    Code:
       0: aload_0
       1: getfield      #261                // Field processedGroupUnits:Ljava/util/Set;
       4: ifnonnull     18
       7: aload_0
       8: new           #251                // class java/util/HashSet
      11: dup
      12: invokespecial #253                // Method java/util/HashSet."<init>":()V
      15: putfield      #261                // Field processedGroupUnits:Ljava/util/Set;
      18: aload_0
      19: getfield      #261                // Field processedGroupUnits:Ljava/util/Set;
      22: areturn

  private java.util.Map<java.lang.Object, java.util.Set<org.hibernate.validator.internal.engine.path.PathImpl>> getInitializedProcessedPathsPerBean();
    Code:
       0: aload_0
       1: getfield      #264                // Field processedPathsPerBean:Ljava/util/Map;
       4: ifnonnull     18
       7: aload_0
       8: new           #268                // class java/util/IdentityHashMap
      11: dup
      12: invokespecial #270                // Method java/util/IdentityHashMap."<init>":()V
      15: putfield      #264                // Field processedPathsPerBean:Ljava/util/Map;
      18: aload_0
      19: getfield      #264                // Field processedPathsPerBean:Ljava/util/Map;
      22: areturn

  private java.util.Set<jakarta.validation.ConstraintViolation<T>> getInitializedFailingConstraintViolations();
    Code:
       0: aload_0
       1: getfield      #84                 // Field failingConstraintViolations:Ljava/util/Set;
       4: ifnonnull     18
       7: aload_0
       8: new           #251                // class java/util/HashSet
      11: dup
      12: invokespecial #253                // Method java/util/HashSet."<init>":()V
      15: putfield      #84                 // Field failingConstraintViolations:Ljava/util/Set;
      18: aload_0
      19: getfield      #84                 // Field failingConstraintViolations:Ljava/util/Set;
      22: areturn

  static {};
    Code:
       0: invokestatic  #271                // Method java/lang/invoke/MethodHandles.lookup:()Ljava/lang/invoke/MethodHandles$Lookup;
       3: invokestatic  #277                // Method org/hibernate/validator/internal/util/logging/LoggerFactory.make:(Ljava/lang/invoke/MethodHandles$Lookup;)Lorg/hibernate/validator/internal/util/logging/Log;
       6: putstatic     #198                // Field LOG:Lorg/hibernate/validator/internal/util/logging/Log;
       9: return
}
