Compiled from "BlockMgrSync.java"
public class org.apache.jena.tdb.base.block.BlockMgrSync implements org.apache.jena.tdb.base.block.BlockMgr {
  protected final org.apache.jena.tdb.base.block.BlockMgr blockMgr;

  public org.apache.jena.tdb.base.block.BlockMgrSync(org.apache.jena.tdb.base.block.BlockMgr);
    Code:
       0: aload_0
       1: invokespecial #1                  // Method java/lang/Object."<init>":()V
       4: aload_0
       5: aload_1
       6: putfield      #2                  // Field blockMgr:Lorg/apache/jena/tdb/base/block/BlockMgr;
       9: return

  public org.apache.jena.tdb.base.block.BlockMgr getWrapped();
    Code:
       0: aload_0
       1: getfield      #2                  // Field blockMgr:Lorg/apache/jena/tdb/base/block/BlockMgr;
       4: areturn

  public synchronized org.apache.jena.tdb.base.block.Block allocate(int);
    Code:
       0: aload_0
       1: getfield      #2                  // Field blockMgr:Lorg/apache/jena/tdb/base/block/BlockMgr;
       4: iload_1
       5: invokeinterface #3,  2            // InterfaceMethod org/apache/jena/tdb/base/block/BlockMgr.allocate:(I)Lorg/apache/jena/tdb/base/block/Block;
      10: areturn

  public synchronized org.apache.jena.tdb.base.block.Block getRead(long);
    Code:
       0: aload_0
       1: getfield      #2                  // Field blockMgr:Lorg/apache/jena/tdb/base/block/BlockMgr;
       4: lload_1
       5: invokeinterface #4,  3            // InterfaceMethod org/apache/jena/tdb/base/block/BlockMgr.getRead:(J)Lorg/apache/jena/tdb/base/block/Block;
      10: areturn

  public synchronized org.apache.jena.tdb.base.block.Block getReadIterator(long);
    Code:
       0: aload_0
       1: getfield      #2                  // Field blockMgr:Lorg/apache/jena/tdb/base/block/BlockMgr;
       4: lload_1
       5: invokeinterface #5,  3            // InterfaceMethod org/apache/jena/tdb/base/block/BlockMgr.getReadIterator:(J)Lorg/apache/jena/tdb/base/block/Block;
      10: areturn

  public synchronized org.apache.jena.tdb.base.block.Block getWrite(long);
    Code:
       0: aload_0
       1: getfield      #2                  // Field blockMgr:Lorg/apache/jena/tdb/base/block/BlockMgr;
       4: lload_1
       5: invokeinterface #6,  3            // InterfaceMethod org/apache/jena/tdb/base/block/BlockMgr.getWrite:(J)Lorg/apache/jena/tdb/base/block/Block;
      10: areturn

  public synchronized org.apache.jena.tdb.base.block.Block promote(org.apache.jena.tdb.base.block.Block);
    Code:
       0: aload_0
       1: getfield      #2                  // Field blockMgr:Lorg/apache/jena/tdb/base/block/BlockMgr;
       4: aload_1
       5: invokeinterface #7,  2            // InterfaceMethod org/apache/jena/tdb/base/block/BlockMgr.promote:(Lorg/apache/jena/tdb/base/block/Block;)Lorg/apache/jena/tdb/base/block/Block;
      10: areturn

  public synchronized void release(org.apache.jena.tdb.base.block.Block);
    Code:
       0: aload_0
       1: getfield      #2                  // Field blockMgr:Lorg/apache/jena/tdb/base/block/BlockMgr;
       4: aload_1
       5: invokeinterface #8,  2            // InterfaceMethod org/apache/jena/tdb/base/block/BlockMgr.release:(Lorg/apache/jena/tdb/base/block/Block;)V
      10: return

  public synchronized void write(org.apache.jena.tdb.base.block.Block);
    Code:
       0: aload_0
       1: getfield      #2                  // Field blockMgr:Lorg/apache/jena/tdb/base/block/BlockMgr;
       4: aload_1
       5: invokeinterface #9,  2            // InterfaceMethod org/apache/jena/tdb/base/block/BlockMgr.write:(Lorg/apache/jena/tdb/base/block/Block;)V
      10: return

  public synchronized void overwrite(org.apache.jena.tdb.base.block.Block);
    Code:
       0: aload_0
       1: getfield      #2                  // Field blockMgr:Lorg/apache/jena/tdb/base/block/BlockMgr;
       4: aload_1
       5: invokeinterface #10,  2           // InterfaceMethod org/apache/jena/tdb/base/block/BlockMgr.overwrite:(Lorg/apache/jena/tdb/base/block/Block;)V
      10: return

  public synchronized void free(org.apache.jena.tdb.base.block.Block);
    Code:
       0: aload_0
       1: getfield      #2                  // Field blockMgr:Lorg/apache/jena/tdb/base/block/BlockMgr;
       4: aload_1
       5: invokeinterface #11,  2           // InterfaceMethod org/apache/jena/tdb/base/block/BlockMgr.free:(Lorg/apache/jena/tdb/base/block/Block;)V
      10: return

  public synchronized void sync();
    Code:
       0: aload_0
       1: getfield      #2                  // Field blockMgr:Lorg/apache/jena/tdb/base/block/BlockMgr;
       4: invokeinterface #12,  1           // InterfaceMethod org/apache/jena/tdb/base/block/BlockMgr.sync:()V
       9: return

  public synchronized void syncForce();
    Code:
       0: aload_0
       1: getfield      #2                  // Field blockMgr:Lorg/apache/jena/tdb/base/block/BlockMgr;
       4: invokeinterface #13,  1           // InterfaceMethod org/apache/jena/tdb/base/block/BlockMgr.syncForce:()V
       9: return

  public synchronized void close();
    Code:
       0: aload_0
       1: getfield      #2                  // Field blockMgr:Lorg/apache/jena/tdb/base/block/BlockMgr;
       4: invokeinterface #14,  1           // InterfaceMethod org/apache/jena/tdb/base/block/BlockMgr.close:()V
       9: return

  public synchronized boolean isEmpty();
    Code:
       0: aload_0
       1: getfield      #2                  // Field blockMgr:Lorg/apache/jena/tdb/base/block/BlockMgr;
       4: invokeinterface #15,  1           // InterfaceMethod org/apache/jena/tdb/base/block/BlockMgr.isEmpty:()Z
       9: ireturn

  public synchronized void beginIterator(java.util.Iterator<?>);
    Code:
       0: aload_0
       1: getfield      #2                  // Field blockMgr:Lorg/apache/jena/tdb/base/block/BlockMgr;
       4: aload_1
       5: invokeinterface #16,  2           // InterfaceMethod org/apache/jena/tdb/base/block/BlockMgr.beginIterator:(Ljava/util/Iterator;)V
      10: return

  public synchronized void endIterator(java.util.Iterator<?>);
    Code:
       0: aload_0
       1: getfield      #2                  // Field blockMgr:Lorg/apache/jena/tdb/base/block/BlockMgr;
       4: aload_1
       5: invokeinterface #17,  2           // InterfaceMethod org/apache/jena/tdb/base/block/BlockMgr.endIterator:(Ljava/util/Iterator;)V
      10: return

  public synchronized void beginRead();
    Code:
       0: aload_0
       1: getfield      #2                  // Field blockMgr:Lorg/apache/jena/tdb/base/block/BlockMgr;
       4: invokeinterface #18,  1           // InterfaceMethod org/apache/jena/tdb/base/block/BlockMgr.beginRead:()V
       9: return

  public synchronized void endRead();
    Code:
       0: aload_0
       1: getfield      #2                  // Field blockMgr:Lorg/apache/jena/tdb/base/block/BlockMgr;
       4: invokeinterface #19,  1           // InterfaceMethod org/apache/jena/tdb/base/block/BlockMgr.endRead:()V
       9: return

  public synchronized void beginUpdate();
    Code:
       0: aload_0
       1: getfield      #2                  // Field blockMgr:Lorg/apache/jena/tdb/base/block/BlockMgr;
       4: invokeinterface #20,  1           // InterfaceMethod org/apache/jena/tdb/base/block/BlockMgr.beginUpdate:()V
       9: return

  public synchronized void endUpdate();
    Code:
       0: aload_0
       1: getfield      #2                  // Field blockMgr:Lorg/apache/jena/tdb/base/block/BlockMgr;
       4: invokeinterface #21,  1           // InterfaceMethod org/apache/jena/tdb/base/block/BlockMgr.endUpdate:()V
       9: return

  public synchronized boolean valid(int);
    Code:
       0: aload_0
       1: getfield      #2                  // Field blockMgr:Lorg/apache/jena/tdb/base/block/BlockMgr;
       4: iload_1
       5: invokeinterface #22,  2           // InterfaceMethod org/apache/jena/tdb/base/block/BlockMgr.valid:(I)Z
      10: ireturn

  public synchronized boolean isClosed();
    Code:
       0: aload_0
       1: getfield      #2                  // Field blockMgr:Lorg/apache/jena/tdb/base/block/BlockMgr;
       4: invokeinterface #23,  1           // InterfaceMethod org/apache/jena/tdb/base/block/BlockMgr.isClosed:()Z
       9: ireturn

  public synchronized java.lang.String getLabel();
    Code:
       0: aload_0
       1: getfield      #2                  // Field blockMgr:Lorg/apache/jena/tdb/base/block/BlockMgr;
       4: invokeinterface #24,  1           // InterfaceMethod org/apache/jena/tdb/base/block/BlockMgr.getLabel:()Ljava/lang/String;
       9: areturn

  public java.lang.String toString();
    Code:
       0: new           #25                 // class java/lang/StringBuilder
       3: dup
       4: invokespecial #26                 // Method java/lang/StringBuilder."<init>":()V
       7: ldc           #27                 // String Sync:
       9: invokevirtual #28                 // Method java/lang/StringBuilder.append:(Ljava/lang/String;)Ljava/lang/StringBuilder;
      12: aload_0
      13: getfield      #2                  // Field blockMgr:Lorg/apache/jena/tdb/base/block/BlockMgr;
      16: invokevirtual #29                 // Method java/lang/Object.toString:()Ljava/lang/String;
      19: invokevirtual #28                 // Method java/lang/StringBuilder.append:(Ljava/lang/String;)Ljava/lang/StringBuilder;
      22: invokevirtual #30                 // Method java/lang/StringBuilder.toString:()Ljava/lang/String;
      25: areturn
}
