Compiled from "IdentifiableResourceAssemblerSupport.java"
public abstract class org.springframework.hateoas.mvc.IdentifiableResourceAssemblerSupport<T extends org.springframework.hateoas.Identifiable<?>, D extends org.springframework.hateoas.ResourceSupport> extends org.springframework.hateoas.mvc.ResourceAssemblerSupport<T, D> {
  private final java.lang.Class<?> controllerClass;

  public org.springframework.hateoas.mvc.IdentifiableResourceAssemblerSupport(java.lang.Class<?>, java.lang.Class<D>);
    Code:
       0: aload_0
       1: aload_1
       2: aload_2
       3: invokespecial #1                  // Method org/springframework/hateoas/mvc/ResourceAssemblerSupport."<init>":(Ljava/lang/Class;Ljava/lang/Class;)V
       6: aload_0
       7: aload_1
       8: putfield      #2                  // Field controllerClass:Ljava/lang/Class;
      11: return

  protected D createResource(T);
    Code:
       0: aload_0
       1: aload_1
       2: iconst_0
       3: anewarray     #3                  // class java/lang/Object
       6: invokevirtual #4                  // Method createResource:(Lorg/springframework/hateoas/Identifiable;[Ljava/lang/Object;)Lorg/springframework/hateoas/ResourceSupport;
       9: areturn

  protected D createResource(T, java.lang.Object...);
    Code:
       0: aload_0
       1: aload_1
       2: invokeinterface #5,  1            // InterfaceMethod org/springframework/hateoas/Identifiable.getId:()Ljava/io/Serializable;
       7: aload_1
       8: aload_2
       9: invokevirtual #6                  // Method createResourceWithId:(Ljava/lang/Object;Lorg/springframework/hateoas/Identifiable;[Ljava/lang/Object;)Lorg/springframework/hateoas/ResourceSupport;
      12: areturn

  protected D createResourceWithId(java.lang.Object, T, java.lang.Object...);
    Code:
       0: aload_2
       1: ldc           #7                  // String Entity must not be null!
       3: invokestatic  #8                  // Method org/springframework/util/Assert.notNull:(Ljava/lang/Object;Ljava/lang/String;)V
       6: aload_1
       7: ldc           #9                  // String Id must not be null!
       9: invokestatic  #8                  // Method org/springframework/util/Assert.notNull:(Ljava/lang/Object;Ljava/lang/String;)V
      12: aload_0
      13: aload_2
      14: invokevirtual #10                 // Method instantiateResource:(Ljava/lang/Object;)Lorg/springframework/hateoas/ResourceSupport;
      17: astore        4
      19: aload         4
      21: aload_0
      22: getfield      #2                  // Field controllerClass:Ljava/lang/Class;
      25: aload_0
      26: aload_3
      27: invokespecial #11                 // Method unwrapIdentifyables:([Ljava/lang/Object;)[Ljava/lang/Object;
      30: invokestatic  #12                 // Method org/springframework/hateoas/mvc/ControllerLinkBuilder.linkTo:(Ljava/lang/Class;[Ljava/lang/Object;)Lorg/springframework/hateoas/mvc/ControllerLinkBuilder;
      33: aload_1
      34: invokevirtual #13                 // Method org/springframework/hateoas/mvc/ControllerLinkBuilder.slash:(Ljava/lang/Object;)Lorg/springframework/hateoas/LinkBuilder;
      37: checkcast     #14                 // class org/springframework/hateoas/mvc/ControllerLinkBuilder
      40: invokevirtual #15                 // Method org/springframework/hateoas/mvc/ControllerLinkBuilder.withSelfRel:()Lorg/springframework/hateoas/Link;
      43: invokevirtual #16                 // Method org/springframework/hateoas/ResourceSupport.add:(Lorg/springframework/hateoas/Link;)V
      46: aload         4
      48: areturn

  private java.lang.Object[] unwrapIdentifyables(java.lang.Object[]);
    Code:
       0: new           #17                 // class java/util/ArrayList
       3: dup
       4: aload_1
       5: arraylength
       6: invokespecial #18                 // Method java/util/ArrayList."<init>":(I)V
       9: astore_2
      10: aload_1
      11: invokestatic  #19                 // Method java/util/Arrays.asList:([Ljava/lang/Object;)Ljava/util/List;
      14: invokeinterface #20,  1           // InterfaceMethod java/util/List.iterator:()Ljava/util/Iterator;
      19: astore_3
      20: aload_3
      21: invokeinterface #21,  1           // InterfaceMethod java/util/Iterator.hasNext:()Z
      26: ifeq          70
      29: aload_3
      30: invokeinterface #22,  1           // InterfaceMethod java/util/Iterator.next:()Ljava/lang/Object;
      35: astore        4
      37: aload_2
      38: aload         4
      40: instanceof    #23                 // class org/springframework/hateoas/Identifiable
      43: ifeq          59
      46: aload         4
      48: checkcast     #23                 // class org/springframework/hateoas/Identifiable
      51: invokeinterface #5,  1            // InterfaceMethod org/springframework/hateoas/Identifiable.getId:()Ljava/io/Serializable;
      56: goto          61
      59: aload         4
      61: invokeinterface #24,  2           // InterfaceMethod java/util/List.add:(Ljava/lang/Object;)Z
      66: pop
      67: goto          20
      70: aload_2
      71: invokeinterface #25,  1           // InterfaceMethod java/util/List.toArray:()[Ljava/lang/Object;
      76: areturn

  protected org.springframework.hateoas.ResourceSupport createResourceWithId(java.lang.Object, java.lang.Object, java.lang.Object[]);
    Code:
       0: aload_0
       1: aload_1
       2: aload_2
       3: checkcast     #23                 // class org/springframework/hateoas/Identifiable
       6: aload_3
       7: invokevirtual #6                  // Method createResourceWithId:(Ljava/lang/Object;Lorg/springframework/hateoas/Identifiable;[Ljava/lang/Object;)Lorg/springframework/hateoas/ResourceSupport;
      10: areturn
}
