Compiled from "ResteasyConstraintViolation.java"
public class org.jboss.resteasy.api.validation.ResteasyConstraintViolation implements java.io.Serializable {
  private static final long serialVersionUID;

  private org.jboss.resteasy.api.validation.ConstraintType$Type constraintType;

  private java.lang.String path;

  private java.lang.String message;

  private java.lang.String value;

  public org.jboss.resteasy.api.validation.ResteasyConstraintViolation(org.jboss.resteasy.api.validation.ConstraintType$Type, java.lang.String, java.lang.String, java.lang.String);
    Code:
       0: aload_0
       1: invokespecial #1                  // Method java/lang/Object."<init>":()V
       4: aload_0
       5: aload_1
       6: putfield      #2                  // Field constraintType:Lorg/jboss/resteasy/api/validation/ConstraintType$Type;
       9: aload_0
      10: aload_2
      11: putfield      #3                  // Field path:Ljava/lang/String;
      14: aload_0
      15: aload_3
      16: putfield      #4                  // Field message:Ljava/lang/String;
      19: aload_0
      20: aload         4
      22: putfield      #5                  // Field value:Ljava/lang/String;
      25: return

  public org.jboss.resteasy.api.validation.ResteasyConstraintViolation();
    Code:
       0: aload_0
       1: invokespecial #1                  // Method java/lang/Object."<init>":()V
       4: return

  public org.jboss.resteasy.api.validation.ConstraintType$Type getConstraintType();
    Code:
       0: aload_0
       1: getfield      #2                  // Field constraintType:Lorg/jboss/resteasy/api/validation/ConstraintType$Type;
       4: areturn

  public java.lang.String getPath();
    Code:
       0: aload_0
       1: getfield      #3                  // Field path:Ljava/lang/String;
       4: areturn

  public java.lang.String getMessage();
    Code:
       0: aload_0
       1: getfield      #4                  // Field message:Ljava/lang/String;
       4: areturn

  public java.lang.String getValue();
    Code:
       0: aload_0
       1: getfield      #5                  // Field value:Ljava/lang/String;
       4: areturn

  public java.lang.String toString();
    Code:
       0: new           #6                  // class java/lang/StringBuilder
       3: dup
       4: invokespecial #7                  // Method java/lang/StringBuilder."<init>":()V
       7: ldc           #8                  // String [
       9: invokevirtual #9                  // Method java/lang/StringBuilder.append:(Ljava/lang/String;)Ljava/lang/StringBuilder;
      12: aload_0
      13: invokevirtual #10                 // Method type:()Ljava/lang/String;
      16: invokevirtual #9                  // Method java/lang/StringBuilder.append:(Ljava/lang/String;)Ljava/lang/StringBuilder;
      19: ldc           #11                 // String ]\r[
      21: invokevirtual #9                  // Method java/lang/StringBuilder.append:(Ljava/lang/String;)Ljava/lang/StringBuilder;
      24: aload_0
      25: getfield      #3                  // Field path:Ljava/lang/String;
      28: invokevirtual #9                  // Method java/lang/StringBuilder.append:(Ljava/lang/String;)Ljava/lang/StringBuilder;
      31: ldc           #11                 // String ]\r[
      33: invokevirtual #9                  // Method java/lang/StringBuilder.append:(Ljava/lang/String;)Ljava/lang/StringBuilder;
      36: aload_0
      37: getfield      #4                  // Field message:Ljava/lang/String;
      40: invokevirtual #9                  // Method java/lang/StringBuilder.append:(Ljava/lang/String;)Ljava/lang/StringBuilder;
      43: ldc           #11                 // String ]\r[
      45: invokevirtual #9                  // Method java/lang/StringBuilder.append:(Ljava/lang/String;)Ljava/lang/StringBuilder;
      48: aload_0
      49: getfield      #5                  // Field value:Ljava/lang/String;
      52: invokevirtual #9                  // Method java/lang/StringBuilder.append:(Ljava/lang/String;)Ljava/lang/StringBuilder;
      55: ldc           #12                 // String ]\r
      57: invokevirtual #9                  // Method java/lang/StringBuilder.append:(Ljava/lang/String;)Ljava/lang/StringBuilder;
      60: invokevirtual #13                 // Method java/lang/StringBuilder.toString:()Ljava/lang/String;
      63: areturn

  public java.lang.String type();
    Code:
       0: aload_0
       1: getfield      #2                  // Field constraintType:Lorg/jboss/resteasy/api/validation/ConstraintType$Type;
       4: invokevirtual #14                 // Method org/jboss/resteasy/api/validation/ConstraintType$Type.toString:()Ljava/lang/String;
       7: areturn
}
