Compiled from "Replacer.java"
public final class org.javasimon.utils.Replacer$Modificator extends java.lang.Enum<org.javasimon.utils.Replacer$Modificator> {
  public static final org.javasimon.utils.Replacer$Modificator REPEAT_UNTIL_UNCHANGED;

  public static final org.javasimon.utils.Replacer$Modificator IGNORE_CASE;

  private static final org.javasimon.utils.Replacer$Modificator[] $VALUES;

  public static org.javasimon.utils.Replacer$Modificator[] values();
    Code:
       0: getstatic     #1                  // Field $VALUES:[Lorg/javasimon/utils/Replacer$Modificator;
       3: invokevirtual #2                  // Method "[Lorg/javasimon/utils/Replacer$Modificator;".clone:()Ljava/lang/Object;
       6: checkcast     #3                  // class "[Lorg/javasimon/utils/Replacer$Modificator;"
       9: areturn

  public static org.javasimon.utils.Replacer$Modificator valueOf(java.lang.String);
    Code:
       0: ldc_w         #4                  // class org/javasimon/utils/Replacer$Modificator
       3: aload_0
       4: invokestatic  #5                  // Method java/lang/Enum.valueOf:(Ljava/lang/Class;Ljava/lang/String;)Ljava/lang/Enum;
       7: checkcast     #4                  // class org/javasimon/utils/Replacer$Modificator
      10: areturn

  private org.javasimon.utils.Replacer$Modificator();
    Code:
       0: aload_0
       1: aload_1
       2: iload_2
       3: invokespecial #6                  // Method java/lang/Enum."<init>":(Ljava/lang/String;I)V
       6: return

  static {};
    Code:
       0: new           #4                  // class org/javasimon/utils/Replacer$Modificator
       3: dup
       4: ldc           #7                  // String REPEAT_UNTIL_UNCHANGED
       6: iconst_0
       7: invokespecial #8                  // Method "<init>":(Ljava/lang/String;I)V
      10: putstatic     #9                  // Field REPEAT_UNTIL_UNCHANGED:Lorg/javasimon/utils/Replacer$Modificator;
      13: new           #4                  // class org/javasimon/utils/Replacer$Modificator
      16: dup
      17: ldc           #10                 // String IGNORE_CASE
      19: iconst_1
      20: invokespecial #8                  // Method "<init>":(Ljava/lang/String;I)V
      23: putstatic     #11                 // Field IGNORE_CASE:Lorg/javasimon/utils/Replacer$Modificator;
      26: iconst_2
      27: anewarray     #4                  // class org/javasimon/utils/Replacer$Modificator
      30: dup
      31: iconst_0
      32: getstatic     #9                  // Field REPEAT_UNTIL_UNCHANGED:Lorg/javasimon/utils/Replacer$Modificator;
      35: aastore
      36: dup
      37: iconst_1
      38: getstatic     #11                 // Field IGNORE_CASE:Lorg/javasimon/utils/Replacer$Modificator;
      41: aastore
      42: putstatic     #1                  // Field $VALUES:[Lorg/javasimon/utils/Replacer$Modificator;
      45: return
}
