Compiled from "Cal10nError.java"
final class ch.qos.cal10n.verifier.Cal10nError$ErrorType extends java.lang.Enum<ch.qos.cal10n.verifier.Cal10nError$ErrorType> {
  public static final ch.qos.cal10n.verifier.Cal10nError$ErrorType MISSING_BN_ANNOTATION;

  public static final ch.qos.cal10n.verifier.Cal10nError$ErrorType MISSING_LOCALE_DATA_ANNOTATION;

  public static final ch.qos.cal10n.verifier.Cal10nError$ErrorType FAILED_TO_FIND_RB;

  public static final ch.qos.cal10n.verifier.Cal10nError$ErrorType EMPTY_RB;

  public static final ch.qos.cal10n.verifier.Cal10nError$ErrorType EMPTY_ENUM;

  public static final ch.qos.cal10n.verifier.Cal10nError$ErrorType ABSENT_IN_RB;

  public static final ch.qos.cal10n.verifier.Cal10nError$ErrorType ABSENT_IN_ENUM;

  private static final ch.qos.cal10n.verifier.Cal10nError$ErrorType[] $VALUES;

  public static ch.qos.cal10n.verifier.Cal10nError$ErrorType[] values();
    Code:
       0: getstatic     #1                  // Field $VALUES:[Lch/qos/cal10n/verifier/Cal10nError$ErrorType;
       3: invokevirtual #2                  // Method "[Lch/qos/cal10n/verifier/Cal10nError$ErrorType;".clone:()Ljava/lang/Object;
       6: checkcast     #3                  // class "[Lch/qos/cal10n/verifier/Cal10nError$ErrorType;"
       9: areturn

  public static ch.qos.cal10n.verifier.Cal10nError$ErrorType valueOf(java.lang.String);
    Code:
       0: ldc_w         #4                  // class ch/qos/cal10n/verifier/Cal10nError$ErrorType
       3: aload_0
       4: invokestatic  #5                  // Method java/lang/Enum.valueOf:(Ljava/lang/Class;Ljava/lang/String;)Ljava/lang/Enum;
       7: checkcast     #4                  // class ch/qos/cal10n/verifier/Cal10nError$ErrorType
      10: areturn

  private ch.qos.cal10n.verifier.Cal10nError$ErrorType();
    Code:
       0: aload_0
       1: aload_1
       2: iload_2
       3: invokespecial #6                  // Method java/lang/Enum."<init>":(Ljava/lang/String;I)V
       6: return

  static {};
    Code:
       0: new           #4                  // class ch/qos/cal10n/verifier/Cal10nError$ErrorType
       3: dup
       4: ldc           #7                  // String MISSING_BN_ANNOTATION
       6: iconst_0
       7: invokespecial #8                  // Method "<init>":(Ljava/lang/String;I)V
      10: putstatic     #9                  // Field MISSING_BN_ANNOTATION:Lch/qos/cal10n/verifier/Cal10nError$ErrorType;
      13: new           #4                  // class ch/qos/cal10n/verifier/Cal10nError$ErrorType
      16: dup
      17: ldc           #10                 // String MISSING_LOCALE_DATA_ANNOTATION
      19: iconst_1
      20: invokespecial #8                  // Method "<init>":(Ljava/lang/String;I)V
      23: putstatic     #11                 // Field MISSING_LOCALE_DATA_ANNOTATION:Lch/qos/cal10n/verifier/Cal10nError$ErrorType;
      26: new           #4                  // class ch/qos/cal10n/verifier/Cal10nError$ErrorType
      29: dup
      30: ldc           #12                 // String FAILED_TO_FIND_RB
      32: iconst_2
      33: invokespecial #8                  // Method "<init>":(Ljava/lang/String;I)V
      36: putstatic     #13                 // Field FAILED_TO_FIND_RB:Lch/qos/cal10n/verifier/Cal10nError$ErrorType;
      39: new           #4                  // class ch/qos/cal10n/verifier/Cal10nError$ErrorType
      42: dup
      43: ldc           #14                 // String EMPTY_RB
      45: iconst_3
      46: invokespecial #8                  // Method "<init>":(Ljava/lang/String;I)V
      49: putstatic     #15                 // Field EMPTY_RB:Lch/qos/cal10n/verifier/Cal10nError$ErrorType;
      52: new           #4                  // class ch/qos/cal10n/verifier/Cal10nError$ErrorType
      55: dup
      56: ldc           #16                 // String EMPTY_ENUM
      58: iconst_4
      59: invokespecial #8                  // Method "<init>":(Ljava/lang/String;I)V
      62: putstatic     #17                 // Field EMPTY_ENUM:Lch/qos/cal10n/verifier/Cal10nError$ErrorType;
      65: new           #4                  // class ch/qos/cal10n/verifier/Cal10nError$ErrorType
      68: dup
      69: ldc           #18                 // String ABSENT_IN_RB
      71: iconst_5
      72: invokespecial #8                  // Method "<init>":(Ljava/lang/String;I)V
      75: putstatic     #19                 // Field ABSENT_IN_RB:Lch/qos/cal10n/verifier/Cal10nError$ErrorType;
      78: new           #4                  // class ch/qos/cal10n/verifier/Cal10nError$ErrorType
      81: dup
      82: ldc           #20                 // String ABSENT_IN_ENUM
      84: bipush        6
      86: invokespecial #8                  // Method "<init>":(Ljava/lang/String;I)V
      89: putstatic     #21                 // Field ABSENT_IN_ENUM:Lch/qos/cal10n/verifier/Cal10nError$ErrorType;
      92: bipush        7
      94: anewarray     #4                  // class ch/qos/cal10n/verifier/Cal10nError$ErrorType
      97: dup
      98: iconst_0
      99: getstatic     #9                  // Field MISSING_BN_ANNOTATION:Lch/qos/cal10n/verifier/Cal10nError$ErrorType;
     102: aastore
     103: dup
     104: iconst_1
     105: getstatic     #11                 // Field MISSING_LOCALE_DATA_ANNOTATION:Lch/qos/cal10n/verifier/Cal10nError$ErrorType;
     108: aastore
     109: dup
     110: iconst_2
     111: getstatic     #13                 // Field FAILED_TO_FIND_RB:Lch/qos/cal10n/verifier/Cal10nError$ErrorType;
     114: aastore
     115: dup
     116: iconst_3
     117: getstatic     #15                 // Field EMPTY_RB:Lch/qos/cal10n/verifier/Cal10nError$ErrorType;
     120: aastore
     121: dup
     122: iconst_4
     123: getstatic     #17                 // Field EMPTY_ENUM:Lch/qos/cal10n/verifier/Cal10nError$ErrorType;
     126: aastore
     127: dup
     128: iconst_5
     129: getstatic     #19                 // Field ABSENT_IN_RB:Lch/qos/cal10n/verifier/Cal10nError$ErrorType;
     132: aastore
     133: dup
     134: bipush        6
     136: getstatic     #21                 // Field ABSENT_IN_ENUM:Lch/qos/cal10n/verifier/Cal10nError$ErrorType;
     139: aastore
     140: putstatic     #1                  // Field $VALUES:[Lch/qos/cal10n/verifier/Cal10nError$ErrorType;
     143: return
}
