Compiled from "Cal10nError.java"
public class ch.qos.cal10n.verifier.Cal10nError {
  final ch.qos.cal10n.verifier.Cal10nError$ErrorType errorType;

  final java.lang.String key;

  final java.util.Locale locale;

  final java.lang.String enumClassName;

  final java.lang.String baseName;

  ch.qos.cal10n.verifier.Cal10nError(ch.qos.cal10n.verifier.Cal10nError$ErrorType, java.lang.String, java.lang.String, java.util.Locale, java.lang.String);
    Code:
       0: aload_0
       1: invokespecial #1                  // Method java/lang/Object."<init>":()V
       4: aload_0
       5: aload_1
       6: putfield      #2                  // Field errorType:Lch/qos/cal10n/verifier/Cal10nError$ErrorType;
       9: aload_0
      10: aload_2
      11: putfield      #3                  // Field key:Ljava/lang/String;
      14: aload_0
      15: aload_3
      16: putfield      #4                  // Field enumClassName:Ljava/lang/String;
      19: aload_0
      20: aload         4
      22: putfield      #5                  // Field locale:Ljava/util/Locale;
      25: aload_0
      26: aload         5
      28: putfield      #6                  // Field baseName:Ljava/lang/String;
      31: return

  public ch.qos.cal10n.verifier.Cal10nError$ErrorType getErrorType();
    Code:
       0: aload_0
       1: getfield      #2                  // Field errorType:Lch/qos/cal10n/verifier/Cal10nError$ErrorType;
       4: areturn

  public java.lang.String getKey();
    Code:
       0: aload_0
       1: getfield      #3                  // Field key:Ljava/lang/String;
       4: areturn

  public java.util.Locale getLocale();
    Code:
       0: aload_0
       1: getfield      #5                  // Field locale:Ljava/util/Locale;
       4: areturn

  public java.lang.String toString();
    Code:
       0: getstatic     #7                  // Field ch/qos/cal10n/verifier/Cal10nError$1.$SwitchMap$ch$qos$cal10n$verifier$Cal10nError$ErrorType:[I
       3: aload_0
       4: getfield      #2                  // Field errorType:Lch/qos/cal10n/verifier/Cal10nError$ErrorType;
       7: invokevirtual #8                  // Method ch/qos/cal10n/verifier/Cal10nError$ErrorType.ordinal:()I
      10: iaload
      11: tableswitch   { // 1 to 7
                     1: 52
                     2: 80
                     3: 113
                     4: 165
                     5: 205
                     6: 233
                     7: 297
               default: 361
          }
      52: new           #9                  // class java/lang/StringBuilder
      55: dup
      56: invokespecial #10                 // Method java/lang/StringBuilder."<init>":()V
      59: ldc           #11                 // String Missing @BaseName annotation in enum type [
      61: invokevirtual #12                 // Method java/lang/StringBuilder.append:(Ljava/lang/String;)Ljava/lang/StringBuilder;
      64: aload_0
      65: getfield      #4                  // Field enumClassName:Ljava/lang/String;
      68: invokevirtual #12                 // Method java/lang/StringBuilder.append:(Ljava/lang/String;)Ljava/lang/StringBuilder;
      71: ldc           #13                 // String ]
      73: invokevirtual #12                 // Method java/lang/StringBuilder.append:(Ljava/lang/String;)Ljava/lang/StringBuilder;
      76: invokevirtual #14                 // Method java/lang/StringBuilder.toString:()Ljava/lang/String;
      79: areturn
      80: new           #9                  // class java/lang/StringBuilder
      83: dup
      84: invokespecial #10                 // Method java/lang/StringBuilder."<init>":()V
      87: ldc           #15                 // String Missing or empty @LocaleData annotation in enum type [
      89: invokevirtual #12                 // Method java/lang/StringBuilder.append:(Ljava/lang/String;)Ljava/lang/StringBuilder;
      92: aload_0
      93: getfield      #4                  // Field enumClassName:Ljava/lang/String;
      96: invokevirtual #12                 // Method java/lang/StringBuilder.append:(Ljava/lang/String;)Ljava/lang/StringBuilder;
      99: ldc           #16                 // String ]. See
     101: invokevirtual #12                 // Method java/lang/StringBuilder.append:(Ljava/lang/String;)Ljava/lang/StringBuilder;
     104: ldc           #17                 // String http://cal10n.qos.ch/codes.html#missingLDAnnotation
     106: invokevirtual #12                 // Method java/lang/StringBuilder.append:(Ljava/lang/String;)Ljava/lang/StringBuilder;
     109: invokevirtual #14                 // Method java/lang/StringBuilder.toString:()Ljava/lang/String;
     112: areturn
     113: new           #9                  // class java/lang/StringBuilder
     116: dup
     117: invokespecial #10                 // Method java/lang/StringBuilder."<init>":()V
     120: ldc           #18                 // String Failed to locate resource bundle [
     122: invokevirtual #12                 // Method java/lang/StringBuilder.append:(Ljava/lang/String;)Ljava/lang/StringBuilder;
     125: aload_0
     126: getfield      #6                  // Field baseName:Ljava/lang/String;
     129: invokevirtual #12                 // Method java/lang/StringBuilder.append:(Ljava/lang/String;)Ljava/lang/StringBuilder;
     132: ldc           #19                 // String ] for locale [
     134: invokevirtual #12                 // Method java/lang/StringBuilder.append:(Ljava/lang/String;)Ljava/lang/StringBuilder;
     137: aload_0
     138: getfield      #5                  // Field locale:Ljava/util/Locale;
     141: invokevirtual #20                 // Method java/lang/StringBuilder.append:(Ljava/lang/Object;)Ljava/lang/StringBuilder;
     144: ldc           #21                 // String ] for enum type [
     146: invokevirtual #12                 // Method java/lang/StringBuilder.append:(Ljava/lang/String;)Ljava/lang/StringBuilder;
     149: aload_0
     150: getfield      #4                  // Field enumClassName:Ljava/lang/String;
     153: invokevirtual #12                 // Method java/lang/StringBuilder.append:(Ljava/lang/String;)Ljava/lang/StringBuilder;
     156: ldc           #13                 // String ]
     158: invokevirtual #12                 // Method java/lang/StringBuilder.append:(Ljava/lang/String;)Ljava/lang/StringBuilder;
     161: invokevirtual #14                 // Method java/lang/StringBuilder.toString:()Ljava/lang/String;
     164: areturn
     165: new           #9                  // class java/lang/StringBuilder
     168: dup
     169: invokespecial #10                 // Method java/lang/StringBuilder."<init>":()V
     172: ldc           #22                 // String Empty resource bundle named [
     174: invokevirtual #12                 // Method java/lang/StringBuilder.append:(Ljava/lang/String;)Ljava/lang/StringBuilder;
     177: aload_0
     178: getfield      #6                  // Field baseName:Ljava/lang/String;
     181: invokevirtual #12                 // Method java/lang/StringBuilder.append:(Ljava/lang/String;)Ljava/lang/StringBuilder;
     184: ldc           #19                 // String ] for locale [
     186: invokevirtual #12                 // Method java/lang/StringBuilder.append:(Ljava/lang/String;)Ljava/lang/StringBuilder;
     189: aload_0
     190: getfield      #5                  // Field locale:Ljava/util/Locale;
     193: invokevirtual #20                 // Method java/lang/StringBuilder.append:(Ljava/lang/Object;)Ljava/lang/StringBuilder;
     196: ldc           #13                 // String ]
     198: invokevirtual #12                 // Method java/lang/StringBuilder.append:(Ljava/lang/String;)Ljava/lang/StringBuilder;
     201: invokevirtual #14                 // Method java/lang/StringBuilder.toString:()Ljava/lang/String;
     204: areturn
     205: new           #9                  // class java/lang/StringBuilder
     208: dup
     209: invokespecial #10                 // Method java/lang/StringBuilder."<init>":()V
     212: ldc           #23                 // String Empty enum type [
     214: invokevirtual #12                 // Method java/lang/StringBuilder.append:(Ljava/lang/String;)Ljava/lang/StringBuilder;
     217: aload_0
     218: getfield      #4                  // Field enumClassName:Ljava/lang/String;
     221: invokevirtual #12                 // Method java/lang/StringBuilder.append:(Ljava/lang/String;)Ljava/lang/StringBuilder;
     224: ldc           #13                 // String ]
     226: invokevirtual #12                 // Method java/lang/StringBuilder.append:(Ljava/lang/String;)Ljava/lang/StringBuilder;
     229: invokevirtual #14                 // Method java/lang/StringBuilder.toString:()Ljava/lang/String;
     232: areturn
     233: new           #9                  // class java/lang/StringBuilder
     236: dup
     237: invokespecial #10                 // Method java/lang/StringBuilder."<init>":()V
     240: ldc           #24                 // String Key [
     242: invokevirtual #12                 // Method java/lang/StringBuilder.append:(Ljava/lang/String;)Ljava/lang/StringBuilder;
     245: aload_0
     246: getfield      #3                  // Field key:Ljava/lang/String;
     249: invokevirtual #12                 // Method java/lang/StringBuilder.append:(Ljava/lang/String;)Ljava/lang/StringBuilder;
     252: ldc           #25                 // String ] present in resource bundle named [
     254: invokevirtual #12                 // Method java/lang/StringBuilder.append:(Ljava/lang/String;)Ljava/lang/StringBuilder;
     257: aload_0
     258: getfield      #6                  // Field baseName:Ljava/lang/String;
     261: invokevirtual #12                 // Method java/lang/StringBuilder.append:(Ljava/lang/String;)Ljava/lang/StringBuilder;
     264: ldc           #19                 // String ] for locale [
     266: invokevirtual #12                 // Method java/lang/StringBuilder.append:(Ljava/lang/String;)Ljava/lang/StringBuilder;
     269: aload_0
     270: getfield      #5                  // Field locale:Ljava/util/Locale;
     273: invokevirtual #20                 // Method java/lang/StringBuilder.append:(Ljava/lang/Object;)Ljava/lang/StringBuilder;
     276: ldc           #26                 // String ] but absent in enum type [
     278: invokevirtual #12                 // Method java/lang/StringBuilder.append:(Ljava/lang/String;)Ljava/lang/StringBuilder;
     281: aload_0
     282: getfield      #4                  // Field enumClassName:Ljava/lang/String;
     285: invokevirtual #12                 // Method java/lang/StringBuilder.append:(Ljava/lang/String;)Ljava/lang/StringBuilder;
     288: ldc           #13                 // String ]
     290: invokevirtual #12                 // Method java/lang/StringBuilder.append:(Ljava/lang/String;)Ljava/lang/StringBuilder;
     293: invokevirtual #14                 // Method java/lang/StringBuilder.toString:()Ljava/lang/String;
     296: areturn
     297: new           #9                  // class java/lang/StringBuilder
     300: dup
     301: invokespecial #10                 // Method java/lang/StringBuilder."<init>":()V
     304: ldc           #24                 // String Key [
     306: invokevirtual #12                 // Method java/lang/StringBuilder.append:(Ljava/lang/String;)Ljava/lang/StringBuilder;
     309: aload_0
     310: getfield      #3                  // Field key:Ljava/lang/String;
     313: invokevirtual #12                 // Method java/lang/StringBuilder.append:(Ljava/lang/String;)Ljava/lang/StringBuilder;
     316: ldc           #27                 // String ] present in enum type [
     318: invokevirtual #12                 // Method java/lang/StringBuilder.append:(Ljava/lang/String;)Ljava/lang/StringBuilder;
     321: aload_0
     322: getfield      #4                  // Field enumClassName:Ljava/lang/String;
     325: invokevirtual #12                 // Method java/lang/StringBuilder.append:(Ljava/lang/String;)Ljava/lang/StringBuilder;
     328: ldc           #28                 // String ] but absent in resource bundle named [
     330: invokevirtual #12                 // Method java/lang/StringBuilder.append:(Ljava/lang/String;)Ljava/lang/StringBuilder;
     333: aload_0
     334: getfield      #6                  // Field baseName:Ljava/lang/String;
     337: invokevirtual #12                 // Method java/lang/StringBuilder.append:(Ljava/lang/String;)Ljava/lang/StringBuilder;
     340: ldc           #19                 // String ] for locale [
     342: invokevirtual #12                 // Method java/lang/StringBuilder.append:(Ljava/lang/String;)Ljava/lang/StringBuilder;
     345: aload_0
     346: getfield      #5                  // Field locale:Ljava/util/Locale;
     349: invokevirtual #20                 // Method java/lang/StringBuilder.append:(Ljava/lang/Object;)Ljava/lang/StringBuilder;
     352: ldc           #13                 // String ]
     354: invokevirtual #12                 // Method java/lang/StringBuilder.append:(Ljava/lang/String;)Ljava/lang/StringBuilder;
     357: invokevirtual #14                 // Method java/lang/StringBuilder.toString:()Ljava/lang/String;
     360: areturn
     361: new           #29                 // class java/lang/IllegalStateException
     364: dup
     365: ldc           #30                 // String Impossible to reach here
     367: invokespecial #31                 // Method java/lang/IllegalStateException."<init>":(Ljava/lang/String;)V
     370: athrow
}
