Compiled from "JavaMetadataProvider.java"
public class org.hibernate.annotations.common.reflection.java.JavaMetadataProvider implements org.hibernate.annotations.common.reflection.MetadataProvider {
  public org.hibernate.annotations.common.reflection.java.JavaMetadataProvider();
    Code:
       0: aload_0
       1: invokespecial #1                  // Method java/lang/Object."<init>":()V
       4: return

  public java.util.Map<java.lang.Object, java.lang.Object> getDefaults();
    Code:
       0: invokestatic  #2                  // Method java/util/Collections.emptyMap:()Ljava/util/Map;
       3: areturn

  public org.hibernate.annotations.common.reflection.AnnotationReader getAnnotationReader(java.lang.reflect.AnnotatedElement);
    Code:
       0: new           #3                  // class org/hibernate/annotations/common/reflection/java/JavaAnnotationReader
       3: dup
       4: aload_1
       5: invokespecial #4                  // Method org/hibernate/annotations/common/reflection/java/JavaAnnotationReader."<init>":(Ljava/lang/reflect/AnnotatedElement;)V
       8: areturn
}
