Compiled from "StandardIndexExporter.java"
public class org.hibernate.tool.schema.internal.StandardIndexExporter implements org.hibernate.tool.schema.spi.Exporter<org.hibernate.mapping.Index> {
  private final org.hibernate.dialect.Dialect dialect;

  public org.hibernate.tool.schema.internal.StandardIndexExporter(org.hibernate.dialect.Dialect);
    Code:
       0: aload_0
       1: invokespecial #1                  // Method java/lang/Object."<init>":()V
       4: aload_0
       5: aload_1
       6: putfield      #2                  // Field dialect:Lorg/hibernate/dialect/Dialect;
       9: return

  public java.lang.String[] getSqlCreateStrings(org.hibernate.mapping.Index, org.hibernate.boot.Metadata);
    Code:
       0: aload_2
       1: invokeinterface #3,  1            // InterfaceMethod org/hibernate/boot/Metadata.getDatabase:()Lorg/hibernate/boot/model/relational/Database;
       6: invokevirtual #4                  // Method org/hibernate/boot/model/relational/Database.getJdbcEnvironment:()Lorg/hibernate/engine/jdbc/env/spi/JdbcEnvironment;
       9: astore_3
      10: aload_3
      11: invokeinterface #5,  1            // InterfaceMethod org/hibernate/engine/jdbc/env/spi/JdbcEnvironment.getQualifiedObjectNameFormatter:()Lorg/hibernate/engine/jdbc/env/spi/QualifiedObjectNameFormatter;
      16: aload_1
      17: invokevirtual #6                  // Method org/hibernate/mapping/Index.getTable:()Lorg/hibernate/mapping/Table;
      20: invokevirtual #7                  // Method org/hibernate/mapping/Table.getQualifiedTableName:()Lorg/hibernate/boot/model/relational/QualifiedTableName;
      23: aload_0
      24: getfield      #2                  // Field dialect:Lorg/hibernate/dialect/Dialect;
      27: invokeinterface #8,  3            // InterfaceMethod org/hibernate/engine/jdbc/env/spi/QualifiedObjectNameFormatter.format:(Lorg/hibernate/boot/model/relational/QualifiedTableName;Lorg/hibernate/dialect/Dialect;)Ljava/lang/String;
      32: astore        4
      34: aload_0
      35: getfield      #2                  // Field dialect:Lorg/hibernate/dialect/Dialect;
      38: invokevirtual #9                  // Method org/hibernate/dialect/Dialect.qualifyIndexName:()Z
      41: ifeq          112
      44: aload_3
      45: invokeinterface #5,  1            // InterfaceMethod org/hibernate/engine/jdbc/env/spi/JdbcEnvironment.getQualifiedObjectNameFormatter:()Lorg/hibernate/engine/jdbc/env/spi/QualifiedObjectNameFormatter;
      50: new           #10                 // class org/hibernate/boot/model/relational/QualifiedNameImpl
      53: dup
      54: aload_1
      55: invokevirtual #6                  // Method org/hibernate/mapping/Index.getTable:()Lorg/hibernate/mapping/Table;
      58: invokevirtual #7                  // Method org/hibernate/mapping/Table.getQualifiedTableName:()Lorg/hibernate/boot/model/relational/QualifiedTableName;
      61: invokevirtual #11                 // Method org/hibernate/boot/model/relational/QualifiedTableName.getCatalogName:()Lorg/hibernate/boot/model/naming/Identifier;
      64: aload_1
      65: invokevirtual #6                  // Method org/hibernate/mapping/Index.getTable:()Lorg/hibernate/mapping/Table;
      68: invokevirtual #7                  // Method org/hibernate/mapping/Table.getQualifiedTableName:()Lorg/hibernate/boot/model/relational/QualifiedTableName;
      71: invokevirtual #12                 // Method org/hibernate/boot/model/relational/QualifiedTableName.getSchemaName:()Lorg/hibernate/boot/model/naming/Identifier;
      74: aload_3
      75: invokeinterface #13,  1           // InterfaceMethod org/hibernate/engine/jdbc/env/spi/JdbcEnvironment.getIdentifierHelper:()Lorg/hibernate/engine/jdbc/env/spi/IdentifierHelper;
      80: aload_1
      81: aload_0
      82: getfield      #2                  // Field dialect:Lorg/hibernate/dialect/Dialect;
      85: invokevirtual #14                 // Method org/hibernate/mapping/Index.getQuotedName:(Lorg/hibernate/dialect/Dialect;)Ljava/lang/String;
      88: invokeinterface #15,  2           // InterfaceMethod org/hibernate/engine/jdbc/env/spi/IdentifierHelper.toIdentifier:(Ljava/lang/String;)Lorg/hibernate/boot/model/naming/Identifier;
      93: invokespecial #16                 // Method org/hibernate/boot/model/relational/QualifiedNameImpl."<init>":(Lorg/hibernate/boot/model/naming/Identifier;Lorg/hibernate/boot/model/naming/Identifier;Lorg/hibernate/boot/model/naming/Identifier;)V
      96: aload_3
      97: invokeinterface #17,  1           // InterfaceMethod org/hibernate/engine/jdbc/env/spi/JdbcEnvironment.getDialect:()Lorg/hibernate/dialect/Dialect;
     102: invokeinterface #18,  3           // InterfaceMethod org/hibernate/engine/jdbc/env/spi/QualifiedObjectNameFormatter.format:(Lorg/hibernate/boot/model/relational/QualifiedName;Lorg/hibernate/dialect/Dialect;)Ljava/lang/String;
     107: astore        5
     109: goto          118
     112: aload_1
     113: invokevirtual #19                 // Method org/hibernate/mapping/Index.getName:()Ljava/lang/String;
     116: astore        5
     118: new           #20                 // class java/lang/StringBuilder
     121: dup
     122: invokespecial #21                 // Method java/lang/StringBuilder."<init>":()V
     125: ldc           #22                 // String create index
     127: invokevirtual #23                 // Method java/lang/StringBuilder.append:(Ljava/lang/String;)Ljava/lang/StringBuilder;
     130: aload         5
     132: invokevirtual #23                 // Method java/lang/StringBuilder.append:(Ljava/lang/String;)Ljava/lang/StringBuilder;
     135: ldc           #24                 // String  on
     137: invokevirtual #23                 // Method java/lang/StringBuilder.append:(Ljava/lang/String;)Ljava/lang/StringBuilder;
     140: aload         4
     142: invokevirtual #23                 // Method java/lang/StringBuilder.append:(Ljava/lang/String;)Ljava/lang/StringBuilder;
     145: ldc           #25                 // String  (
     147: invokevirtual #23                 // Method java/lang/StringBuilder.append:(Ljava/lang/String;)Ljava/lang/StringBuilder;
     150: astore        6
     152: iconst_1
     153: istore        7
     155: aload_1
     156: invokevirtual #26                 // Method org/hibernate/mapping/Index.getColumnIterator:()Ljava/util/Iterator;
     159: astore        8
     161: aload_1
     162: invokevirtual #27                 // Method org/hibernate/mapping/Index.getColumnOrderMap:()Ljava/util/Map;
     165: astore        9
     167: aload         8
     169: invokeinterface #28,  1           // InterfaceMethod java/util/Iterator.hasNext:()Z
     174: ifeq          261
     177: aload         8
     179: invokeinterface #29,  1           // InterfaceMethod java/util/Iterator.next:()Ljava/lang/Object;
     184: checkcast     #30                 // class org/hibernate/mapping/Column
     187: astore        10
     189: iload         7
     191: ifeq          200
     194: iconst_0
     195: istore        7
     197: goto          208
     200: aload         6
     202: ldc           #31                 // String ,
     204: invokevirtual #23                 // Method java/lang/StringBuilder.append:(Ljava/lang/String;)Ljava/lang/StringBuilder;
     207: pop
     208: aload         6
     210: aload         10
     212: aload_0
     213: getfield      #2                  // Field dialect:Lorg/hibernate/dialect/Dialect;
     216: invokevirtual #32                 // Method org/hibernate/mapping/Column.getQuotedName:(Lorg/hibernate/dialect/Dialect;)Ljava/lang/String;
     219: invokevirtual #23                 // Method java/lang/StringBuilder.append:(Ljava/lang/String;)Ljava/lang/StringBuilder;
     222: pop
     223: aload         9
     225: aload         10
     227: invokeinterface #33,  2           // InterfaceMethod java/util/Map.containsKey:(Ljava/lang/Object;)Z
     232: ifeq          258
     235: aload         6
     237: ldc           #34                 // String
     239: invokevirtual #23                 // Method java/lang/StringBuilder.append:(Ljava/lang/String;)Ljava/lang/StringBuilder;
     242: aload         9
     244: aload         10
     246: invokeinterface #35,  2           // InterfaceMethod java/util/Map.get:(Ljava/lang/Object;)Ljava/lang/Object;
     251: checkcast     #36                 // class java/lang/String
     254: invokevirtual #23                 // Method java/lang/StringBuilder.append:(Ljava/lang/String;)Ljava/lang/StringBuilder;
     257: pop
     258: goto          167
     261: aload         6
     263: ldc           #37                 // String )
     265: invokevirtual #23                 // Method java/lang/StringBuilder.append:(Ljava/lang/String;)Ljava/lang/StringBuilder;
     268: pop
     269: iconst_1
     270: anewarray     #36                 // class java/lang/String
     273: dup
     274: iconst_0
     275: aload         6
     277: invokevirtual #38                 // Method java/lang/StringBuilder.toString:()Ljava/lang/String;
     280: aastore
     281: areturn

  public java.lang.String[] getSqlDropStrings(org.hibernate.mapping.Index, org.hibernate.boot.Metadata);
    Code:
       0: aload_0
       1: getfield      #2                  // Field dialect:Lorg/hibernate/dialect/Dialect;
       4: invokevirtual #39                 // Method org/hibernate/dialect/Dialect.dropConstraints:()Z
       7: ifne          14
      10: getstatic     #40                 // Field NO_COMMANDS:[Ljava/lang/String;
      13: areturn
      14: aload_2
      15: invokeinterface #3,  1            // InterfaceMethod org/hibernate/boot/Metadata.getDatabase:()Lorg/hibernate/boot/model/relational/Database;
      20: invokevirtual #4                  // Method org/hibernate/boot/model/relational/Database.getJdbcEnvironment:()Lorg/hibernate/engine/jdbc/env/spi/JdbcEnvironment;
      23: astore_3
      24: aload_3
      25: invokeinterface #5,  1            // InterfaceMethod org/hibernate/engine/jdbc/env/spi/JdbcEnvironment.getQualifiedObjectNameFormatter:()Lorg/hibernate/engine/jdbc/env/spi/QualifiedObjectNameFormatter;
      30: aload_1
      31: invokevirtual #6                  // Method org/hibernate/mapping/Index.getTable:()Lorg/hibernate/mapping/Table;
      34: invokevirtual #7                  // Method org/hibernate/mapping/Table.getQualifiedTableName:()Lorg/hibernate/boot/model/relational/QualifiedTableName;
      37: aload_0
      38: getfield      #2                  // Field dialect:Lorg/hibernate/dialect/Dialect;
      41: invokeinterface #8,  3            // InterfaceMethod org/hibernate/engine/jdbc/env/spi/QualifiedObjectNameFormatter.format:(Lorg/hibernate/boot/model/relational/QualifiedTableName;Lorg/hibernate/dialect/Dialect;)Ljava/lang/String;
      46: astore        4
      48: aload_0
      49: getfield      #2                  // Field dialect:Lorg/hibernate/dialect/Dialect;
      52: invokevirtual #9                  // Method org/hibernate/dialect/Dialect.qualifyIndexName:()Z
      55: ifeq          72
      58: aload         4
      60: aload_1
      61: invokevirtual #19                 // Method org/hibernate/mapping/Index.getName:()Ljava/lang/String;
      64: invokestatic  #41                 // Method org/hibernate/internal/util/StringHelper.qualify:(Ljava/lang/String;Ljava/lang/String;)Ljava/lang/String;
      67: astore        5
      69: goto          78
      72: aload_1
      73: invokevirtual #19                 // Method org/hibernate/mapping/Index.getName:()Ljava/lang/String;
      76: astore        5
      78: iconst_1
      79: anewarray     #36                 // class java/lang/String
      82: dup
      83: iconst_0
      84: new           #20                 // class java/lang/StringBuilder
      87: dup
      88: invokespecial #21                 // Method java/lang/StringBuilder."<init>":()V
      91: ldc           #42                 // String drop index
      93: invokevirtual #23                 // Method java/lang/StringBuilder.append:(Ljava/lang/String;)Ljava/lang/StringBuilder;
      96: aload         5
      98: invokevirtual #23                 // Method java/lang/StringBuilder.append:(Ljava/lang/String;)Ljava/lang/StringBuilder;
     101: invokevirtual #38                 // Method java/lang/StringBuilder.toString:()Ljava/lang/String;
     104: aastore
     105: areturn

  public java.lang.String[] getSqlDropStrings(org.hibernate.boot.model.relational.Exportable, org.hibernate.boot.Metadata);
    Code:
       0: aload_0
       1: aload_1
       2: checkcast     #43                 // class org/hibernate/mapping/Index
       5: aload_2
       6: invokevirtual #44                 // Method getSqlDropStrings:(Lorg/hibernate/mapping/Index;Lorg/hibernate/boot/Metadata;)[Ljava/lang/String;
       9: areturn

  public java.lang.String[] getSqlCreateStrings(org.hibernate.boot.model.relational.Exportable, org.hibernate.boot.Metadata);
    Code:
       0: aload_0
       1: aload_1
       2: checkcast     #43                 // class org/hibernate/mapping/Index
       5: aload_2
       6: invokevirtual #45                 // Method getSqlCreateStrings:(Lorg/hibernate/mapping/Index;Lorg/hibernate/boot/Metadata;)[Ljava/lang/String;
       9: areturn
}
