Compiled from "DynamicRouterDefinition.java"
public class org.apache.camel.model.DynamicRouterDefinition<Type extends org.apache.camel.model.ProcessorDefinition<Type>> extends org.apache.camel.model.NoOutputExpressionNode {
  public static final java.lang.String DEFAULT_DELIMITER;

  private java.lang.String uriDelimiter;

  private java.lang.Boolean ignoreInvalidEndpoints;

  public org.apache.camel.model.DynamicRouterDefinition();
    Code:
       0: aload_0
       1: invokespecial #25                 // Method org/apache/camel/model/NoOutputExpressionNode."<init>":()V
       4: return

  public org.apache.camel.model.DynamicRouterDefinition(org.apache.camel.Expression);
    Code:
       0: aload_0
       1: aload_1
       2: invokespecial #31                 // Method org/apache/camel/model/NoOutputExpressionNode."<init>":(Lorg/apache/camel/Expression;)V
       5: return

  public java.lang.String toString();
    Code:
       0: new           #37                 // class java/lang/StringBuilder
       3: dup
       4: invokespecial #38                 // Method java/lang/StringBuilder."<init>":()V
       7: ldc           #40                 // String DynamicRouter[
       9: invokevirtual #44                 // Method java/lang/StringBuilder.append:(Ljava/lang/String;)Ljava/lang/StringBuilder;
      12: aload_0
      13: invokevirtual #48                 // Method getExpression:()Lorg/apache/camel/model/language/ExpressionDefinition;
      16: invokevirtual #51                 // Method java/lang/StringBuilder.append:(Ljava/lang/Object;)Ljava/lang/StringBuilder;
      19: ldc           #53                 // String ]
      21: invokevirtual #44                 // Method java/lang/StringBuilder.append:(Ljava/lang/String;)Ljava/lang/StringBuilder;
      24: invokevirtual #55                 // Method java/lang/StringBuilder.toString:()Ljava/lang/String;
      27: areturn

  public java.lang.String getLabel();
    Code:
       0: new           #37                 // class java/lang/StringBuilder
       3: dup
       4: invokespecial #38                 // Method java/lang/StringBuilder."<init>":()V
       7: ldc           #58                 // String dynamicRouter[
       9: invokevirtual #44                 // Method java/lang/StringBuilder.append:(Ljava/lang/String;)Ljava/lang/StringBuilder;
      12: aload_0
      13: invokevirtual #48                 // Method getExpression:()Lorg/apache/camel/model/language/ExpressionDefinition;
      16: invokevirtual #51                 // Method java/lang/StringBuilder.append:(Ljava/lang/Object;)Ljava/lang/StringBuilder;
      19: ldc           #53                 // String ]
      21: invokevirtual #44                 // Method java/lang/StringBuilder.append:(Ljava/lang/String;)Ljava/lang/StringBuilder;
      24: invokevirtual #55                 // Method java/lang/StringBuilder.toString:()Ljava/lang/String;
      27: areturn

  public java.lang.String getShortName();
    Code:
       0: ldc           #60                 // String dynamicRouter
       2: areturn

  public java.util.List<org.apache.camel.model.ProcessorDefinition<?>> getOutputs();
    Code:
       0: invokestatic  #67                 // Method java/util/Collections.emptyList:()Ljava/util/List;
       3: areturn

  public org.apache.camel.Processor createProcessor(org.apache.camel.spi.RouteContext) throws java.lang.Exception;
    Code:
       0: aload_0
       1: invokevirtual #48                 // Method getExpression:()Lorg/apache/camel/model/language/ExpressionDefinition;
       4: aload_1
       5: invokevirtual #77                 // Method org/apache/camel/model/language/ExpressionDefinition.createExpression:(Lorg/apache/camel/spi/RouteContext;)Lorg/apache/camel/Expression;
       8: astore_2
       9: aload_0
      10: invokevirtual #80                 // Method getUriDelimiter:()Ljava/lang/String;
      13: ifnull        23
      16: aload_0
      17: invokevirtual #80                 // Method getUriDelimiter:()Ljava/lang/String;
      20: goto          25
      23: ldc           #17                 // String ,
      25: astore_3
      26: new           #86                 // class org/apache/camel/processor/DynamicRouter
      29: dup
      30: aload_1
      31: invokeinterface #92,  1           // InterfaceMethod org/apache/camel/spi/RouteContext.getCamelContext:()Lorg/apache/camel/CamelContext;
      36: aload_2
      37: aload_3
      38: invokespecial #95                 // Method org/apache/camel/processor/DynamicRouter."<init>":(Lorg/apache/camel/CamelContext;Lorg/apache/camel/Expression;Ljava/lang/String;)V
      41: astore        4
      43: aload_0
      44: invokevirtual #99                 // Method getIgnoreInvalidEndpoints:()Ljava/lang/Boolean;
      47: ifnull        62
      50: aload         4
      52: aload_0
      53: invokevirtual #99                 // Method getIgnoreInvalidEndpoints:()Ljava/lang/Boolean;
      56: invokevirtual #105                // Method java/lang/Boolean.booleanValue:()Z
      59: invokevirtual #109                // Method org/apache/camel/processor/DynamicRouter.setIgnoreInvalidEndpoints:(Z)V
      62: aload         4
      64: areturn

  public void setUriDelimiter(java.lang.String);
    Code:
       0: aload_0
       1: aload_1
       2: putfield      #117                // Field uriDelimiter:Ljava/lang/String;
       5: return

  public java.lang.String getUriDelimiter();
    Code:
       0: aload_0
       1: getfield      #117                // Field uriDelimiter:Ljava/lang/String;
       4: areturn

  public void setIgnoreInvalidEndpoints(java.lang.Boolean);
    Code:
       0: aload_0
       1: aload_1
       2: putfield      #120                // Field ignoreInvalidEndpoints:Ljava/lang/Boolean;
       5: return

  public java.lang.Boolean getIgnoreInvalidEndpoints();
    Code:
       0: aload_0
       1: getfield      #120                // Field ignoreInvalidEndpoints:Ljava/lang/Boolean;
       4: areturn

  public Type end();
    Code:
       0: aload_0
       1: invokespecial #124                // Method org/apache/camel/model/NoOutputExpressionNode.end:()Lorg/apache/camel/model/ProcessorDefinition;
       4: areturn

  public org.apache.camel.model.DynamicRouterDefinition<Type> ignoreInvalidEndpoints();
    Code:
       0: aload_0
       1: iconst_1
       2: invokestatic  #129                // Method java/lang/Boolean.valueOf:(Z)Ljava/lang/Boolean;
       5: invokevirtual #131                // Method setIgnoreInvalidEndpoints:(Ljava/lang/Boolean;)V
       8: aload_0
       9: areturn

  public org.apache.camel.model.DynamicRouterDefinition<Type> uriDelimiter(java.lang.String);
    Code:
       0: aload_0
       1: aload_1
       2: invokevirtual #134                // Method setUriDelimiter:(Ljava/lang/String;)V
       5: aload_0
       6: areturn
}
