Compiled from "ProcessDefinition.java"
public class org.apache.camel.model.ProcessDefinition extends org.apache.camel.model.NoOutputDefinition<org.apache.camel.model.ProcessDefinition> {
  private java.lang.String ref;

  private org.apache.camel.Processor processor;

  public org.apache.camel.model.ProcessDefinition();
    Code:
       0: aload_0
       1: invokespecial #25                 // Method org/apache/camel/model/NoOutputDefinition."<init>":()V
       4: return

  public org.apache.camel.model.ProcessDefinition(org.apache.camel.Processor);
    Code:
       0: aload_0
       1: invokespecial #25                 // Method org/apache/camel/model/NoOutputDefinition."<init>":()V
       4: aload_0
       5: aload_1
       6: putfield      #30                 // Field processor:Lorg/apache/camel/Processor;
       9: return

  public java.lang.String getShortName();
    Code:
       0: ldc           #33                 // String process
       2: areturn

  public java.lang.String toString();
    Code:
       0: new           #36                 // class java/lang/StringBuilder
       3: dup
       4: invokespecial #37                 // Method java/lang/StringBuilder."<init>":()V
       7: ldc           #39                 // String process[
       9: invokevirtual #43                 // Method java/lang/StringBuilder.append:(Ljava/lang/String;)Ljava/lang/StringBuilder;
      12: aload_0
      13: getfield      #45                 // Field ref:Ljava/lang/String;
      16: ifnull        44
      19: new           #36                 // class java/lang/StringBuilder
      22: dup
      23: invokespecial #37                 // Method java/lang/StringBuilder."<init>":()V
      26: ldc           #47                 // String ref:
      28: invokevirtual #43                 // Method java/lang/StringBuilder.append:(Ljava/lang/String;)Ljava/lang/StringBuilder;
      31: aload_0
      32: getfield      #45                 // Field ref:Ljava/lang/String;
      35: invokevirtual #43                 // Method java/lang/StringBuilder.append:(Ljava/lang/String;)Ljava/lang/StringBuilder;
      38: invokevirtual #49                 // Method java/lang/StringBuilder.toString:()Ljava/lang/String;
      41: goto          48
      44: aload_0
      45: getfield      #30                 // Field processor:Lorg/apache/camel/Processor;
      48: invokevirtual #54                 // Method java/lang/StringBuilder.append:(Ljava/lang/Object;)Ljava/lang/StringBuilder;
      51: ldc           #56                 // String ]
      53: invokevirtual #43                 // Method java/lang/StringBuilder.append:(Ljava/lang/String;)Ljava/lang/StringBuilder;
      56: invokevirtual #49                 // Method java/lang/StringBuilder.toString:()Ljava/lang/String;
      59: areturn

  public java.lang.String getLabel();
    Code:
       0: aload_0
       1: getfield      #45                 // Field ref:Ljava/lang/String;
       4: ifnull        30
       7: new           #36                 // class java/lang/StringBuilder
      10: dup
      11: invokespecial #37                 // Method java/lang/StringBuilder."<init>":()V
      14: ldc           #47                 // String ref:
      16: invokevirtual #43                 // Method java/lang/StringBuilder.append:(Ljava/lang/String;)Ljava/lang/StringBuilder;
      19: aload_0
      20: getfield      #45                 // Field ref:Ljava/lang/String;
      23: invokevirtual #43                 // Method java/lang/StringBuilder.append:(Ljava/lang/String;)Ljava/lang/StringBuilder;
      26: invokevirtual #49                 // Method java/lang/StringBuilder.toString:()Ljava/lang/String;
      29: areturn
      30: aload_0
      31: getfield      #30                 // Field processor:Lorg/apache/camel/Processor;
      34: ifnull        45
      37: aload_0
      38: getfield      #30                 // Field processor:Lorg/apache/camel/Processor;
      41: invokevirtual #58                 // Method java/lang/Object.toString:()Ljava/lang/String;
      44: areturn
      45: ldc           #60                 // String
      47: areturn

  public java.lang.String getRef();
    Code:
       0: aload_0
       1: getfield      #45                 // Field ref:Ljava/lang/String;
       4: areturn

  public void setRef(java.lang.String);
    Code:
       0: aload_0
       1: aload_1
       2: putfield      #45                 // Field ref:Ljava/lang/String;
       5: return

  public org.apache.camel.Processor createProcessor(org.apache.camel.spi.RouteContext);
    Code:
       0: aload_0
       1: getfield      #30                 // Field processor:Lorg/apache/camel/Processor;
       4: astore_2
       5: aload_0
       6: getfield      #30                 // Field processor:Lorg/apache/camel/Processor;
       9: ifnonnull     39
      12: aload_0
      13: getfield      #45                 // Field ref:Ljava/lang/String;
      16: ldc           #67                 // String ref
      18: aload_0
      19: invokestatic  #73                 // Method org/apache/camel/util/ObjectHelper.notNull:(Ljava/lang/Object;Ljava/lang/String;Ljava/lang/Object;)Ljava/lang/Object;
      22: pop
      23: aload_1
      24: aload_0
      25: invokevirtual #75                 // Method getRef:()Ljava/lang/String;
      28: ldc           #77                 // class org/apache/camel/Processor
      30: invokeinterface #83,  3           // InterfaceMethod org/apache/camel/spi/RouteContext.mandatoryLookup:(Ljava/lang/String;Ljava/lang/Class;)Ljava/lang/Object;
      35: checkcast     #77                 // class org/apache/camel/Processor
      38: astore_2
      39: aload_2
      40: instanceof    #85                 // class org/apache/camel/Service
      43: ifne          74
      46: aload_2
      47: instanceof    #87                 // class org/apache/camel/AsyncProcessor
      50: ifeq          65
      53: new           #89                 // class org/apache/camel/processor/DelegateAsyncProcessor
      56: dup
      57: aload_2
      58: invokespecial #91                 // Method org/apache/camel/processor/DelegateAsyncProcessor."<init>":(Lorg/apache/camel/Processor;)V
      61: astore_2
      62: goto          74
      65: new           #93                 // class org/apache/camel/processor/DelegateSyncProcessor
      68: dup
      69: aload_2
      70: invokespecial #94                 // Method org/apache/camel/processor/DelegateSyncProcessor."<init>":(Lorg/apache/camel/Processor;)V
      73: astore_2
      74: aload_2
      75: areturn
}
