Compiled from "RollbackDefinition.java"
public class org.apache.camel.model.RollbackDefinition extends org.apache.camel.model.NoOutputDefinition<org.apache.camel.model.RollbackDefinition> {
  private java.lang.Boolean markRollbackOnly;

  private java.lang.Boolean markRollbackOnlyLast;

  private java.lang.String message;

  public org.apache.camel.model.RollbackDefinition();
    Code:
       0: aload_0
       1: invokespecial #23                 // Method org/apache/camel/model/NoOutputDefinition."<init>":()V
       4: return

  public org.apache.camel.model.RollbackDefinition(java.lang.String);
    Code:
       0: aload_0
       1: invokespecial #23                 // Method org/apache/camel/model/NoOutputDefinition."<init>":()V
       4: aload_0
       5: aload_1
       6: putfield      #28                 // Field message:Ljava/lang/String;
       9: return

  public java.lang.String getShortName();
    Code:
       0: ldc           #31                 // String rollback
       2: areturn

  public java.lang.String toString();
    Code:
       0: aload_0
       1: getfield      #28                 // Field message:Ljava/lang/String;
       4: ifnull        35
       7: new           #34                 // class java/lang/StringBuilder
      10: dup
      11: invokespecial #35                 // Method java/lang/StringBuilder."<init>":()V
      14: ldc           #37                 // String Rollback[
      16: invokevirtual #41                 // Method java/lang/StringBuilder.append:(Ljava/lang/String;)Ljava/lang/StringBuilder;
      19: aload_0
      20: getfield      #28                 // Field message:Ljava/lang/String;
      23: invokevirtual #41                 // Method java/lang/StringBuilder.append:(Ljava/lang/String;)Ljava/lang/StringBuilder;
      26: ldc           #43                 // String ]
      28: invokevirtual #41                 // Method java/lang/StringBuilder.append:(Ljava/lang/String;)Ljava/lang/StringBuilder;
      31: invokevirtual #45                 // Method java/lang/StringBuilder.toString:()Ljava/lang/String;
      34: areturn
      35: ldc           #47                 // String Rollback
      37: areturn

  public java.lang.String getLabel();
    Code:
       0: ldc           #31                 // String rollback
       2: areturn

  public org.apache.camel.Processor createProcessor(org.apache.camel.spi.RouteContext);
    Code:
       0: aload_0
       1: invokevirtual #54                 // Method isMarkRollbackOnly:()Z
       4: ifeq          24
       7: aload_0
       8: invokevirtual #57                 // Method isMarkRollbackOnlyLast:()Z
      11: ifeq          24
      14: new           #59                 // class java/lang/IllegalArgumentException
      17: dup
      18: ldc           #61                 // String Only either one of markRollbackOnly and markRollbackOnlyLast is possible to select as true
      20: invokespecial #63                 // Method java/lang/IllegalArgumentException."<init>":(Ljava/lang/String;)V
      23: athrow
      24: new           #65                 // class org/apache/camel/processor/RollbackProcessor
      27: dup
      28: aload_0
      29: getfield      #28                 // Field message:Ljava/lang/String;
      32: invokespecial #66                 // Method org/apache/camel/processor/RollbackProcessor."<init>":(Ljava/lang/String;)V
      35: astore_2
      36: aload_2
      37: aload_0
      38: invokevirtual #54                 // Method isMarkRollbackOnly:()Z
      41: invokevirtual #70                 // Method org/apache/camel/processor/RollbackProcessor.setMarkRollbackOnly:(Z)V
      44: aload_2
      45: aload_0
      46: invokevirtual #57                 // Method isMarkRollbackOnlyLast:()Z
      49: invokevirtual #73                 // Method org/apache/camel/processor/RollbackProcessor.setMarkRollbackOnlyLast:(Z)V
      52: aload_2
      53: areturn

  public java.lang.String getMessage();
    Code:
       0: aload_0
       1: getfield      #28                 // Field message:Ljava/lang/String;
       4: areturn

  public void setMessage(java.lang.String);
    Code:
       0: aload_0
       1: aload_1
       2: putfield      #28                 // Field message:Ljava/lang/String;
       5: return

  public java.lang.Boolean getMarkRollbackOnly();
    Code:
       0: aload_0
       1: getfield      #83                 // Field markRollbackOnly:Ljava/lang/Boolean;
       4: areturn

  public void setMarkRollbackOnly(java.lang.Boolean);
    Code:
       0: aload_0
       1: aload_1
       2: putfield      #83                 // Field markRollbackOnly:Ljava/lang/Boolean;
       5: return

  public boolean isMarkRollbackOnly();
    Code:
       0: aload_0
       1: getfield      #83                 // Field markRollbackOnly:Ljava/lang/Boolean;
       4: ifnull        21
       7: aload_0
       8: getfield      #83                 // Field markRollbackOnly:Ljava/lang/Boolean;
      11: invokevirtual #89                 // Method java/lang/Boolean.booleanValue:()Z
      14: ifeq          21
      17: iconst_1
      18: goto          22
      21: iconst_0
      22: ireturn

  public java.lang.Boolean getMarkRollbackOnlyLast();
    Code:
       0: aload_0
       1: getfield      #92                 // Field markRollbackOnlyLast:Ljava/lang/Boolean;
       4: areturn

  public void setMarkRollbackOnlyLast(java.lang.Boolean);
    Code:
       0: aload_0
       1: aload_1
       2: putfield      #92                 // Field markRollbackOnlyLast:Ljava/lang/Boolean;
       5: return

  public boolean isMarkRollbackOnlyLast();
    Code:
       0: aload_0
       1: getfield      #92                 // Field markRollbackOnlyLast:Ljava/lang/Boolean;
       4: ifnull        21
       7: aload_0
       8: getfield      #92                 // Field markRollbackOnlyLast:Ljava/lang/Boolean;
      11: invokevirtual #89                 // Method java/lang/Boolean.booleanValue:()Z
      14: ifeq          21
      17: iconst_1
      18: goto          22
      21: iconst_0
      22: ireturn
}
