Compiled from "PatchDataDeserializer.java"
public class pl.allegro.tech.hermes.api.jackson.PatchDataDeserializer extends com.fasterxml.jackson.databind.JsonDeserializer<pl.allegro.tech.hermes.api.PatchData> {
  public pl.allegro.tech.hermes.api.jackson.PatchDataDeserializer();
    Code:
       0: aload_0
       1: invokespecial #1                  // Method com/fasterxml/jackson/databind/JsonDeserializer."<init>":()V
       4: return

  public pl.allegro.tech.hermes.api.PatchData deserialize(com.fasterxml.jackson.core.JsonParser, com.fasterxml.jackson.databind.DeserializationContext) throws java.io.IOException;
    Code:
       0: aload_1
       1: invokevirtual #2                  // Method com/fasterxml/jackson/core/JsonParser.getCodec:()Lcom/fasterxml/jackson/core/ObjectCodec;
       4: aload_1
       5: new           #3                  // class pl/allegro/tech/hermes/api/jackson/PatchDataDeserializer$1
       8: dup
       9: aload_0
      10: invokespecial #4                  // Method pl/allegro/tech/hermes/api/jackson/PatchDataDeserializer$1."<init>":(Lpl/allegro/tech/hermes/api/jackson/PatchDataDeserializer;)V
      13: invokevirtual #5                  // Method com/fasterxml/jackson/core/ObjectCodec.readValue:(Lcom/fasterxml/jackson/core/JsonParser;Lcom/fasterxml/jackson/core/type/TypeReference;)Ljava/lang/Object;
      16: checkcast     #6                  // class java/util/Map
      19: astore_3
      20: new           #7                  // class pl/allegro/tech/hermes/api/PatchData
      23: dup
      24: aload_3
      25: invokespecial #8                  // Method pl/allegro/tech/hermes/api/PatchData."<init>":(Ljava/util/Map;)V
      28: areturn

  public java.lang.Object deserialize(com.fasterxml.jackson.core.JsonParser, com.fasterxml.jackson.databind.DeserializationContext) throws java.io.IOException, com.fasterxml.jackson.core.JsonProcessingException;
    Code:
       0: aload_0
       1: aload_1
       2: aload_2
       3: invokevirtual #9                  // Method deserialize:(Lcom/fasterxml/jackson/core/JsonParser;Lcom/fasterxml/jackson/databind/DeserializationContext;)Lpl/allegro/tech/hermes/api/PatchData;
       6: areturn
}
