Compiled from "ArchiveEvent.java"
public class org.jboss.shrinkwrap.api.ArchiveEvent {
  private final org.jboss.shrinkwrap.api.asset.Asset asset;

  private final org.jboss.shrinkwrap.api.ArchivePath path;

  private org.jboss.shrinkwrap.api.asset.Asset handledAsset;

  public org.jboss.shrinkwrap.api.ArchiveEvent(org.jboss.shrinkwrap.api.ArchivePath, org.jboss.shrinkwrap.api.asset.Asset);
    Code:
       0: aload_0
       1: invokespecial #1                  // Method java/lang/Object."<init>":()V
       4: aload_0
       5: aload_1
       6: putfield      #2                  // Field path:Lorg/jboss/shrinkwrap/api/ArchivePath;
       9: aload_0
      10: aload_2
      11: putfield      #3                  // Field asset:Lorg/jboss/shrinkwrap/api/asset/Asset;
      14: aload_0
      15: aload_2
      16: putfield      #4                  // Field handledAsset:Lorg/jboss/shrinkwrap/api/asset/Asset;
      19: return

  public org.jboss.shrinkwrap.api.asset.Asset getAsset();
    Code:
       0: aload_0
       1: getfield      #3                  // Field asset:Lorg/jboss/shrinkwrap/api/asset/Asset;
       4: areturn

  public org.jboss.shrinkwrap.api.ArchivePath getPath();
    Code:
       0: aload_0
       1: getfield      #2                  // Field path:Lorg/jboss/shrinkwrap/api/ArchivePath;
       4: areturn

  public org.jboss.shrinkwrap.api.asset.Asset getHandledAsset();
    Code:
       0: aload_0
       1: getfield      #4                  // Field handledAsset:Lorg/jboss/shrinkwrap/api/asset/Asset;
       4: areturn

  public void setHandledAsset(org.jboss.shrinkwrap.api.asset.Asset);
    Code:
       0: aload_0
       1: aload_1
       2: putfield      #4                  // Field handledAsset:Lorg/jboss/shrinkwrap/api/asset/Asset;
       5: return
}
