Compiled from "LookupInjectionSource.java"
class org.jboss.as.ee.component.LookupInjectionSource$2 implements org.jboss.as.naming.ManagedReferenceFactory {
  final org.jboss.as.ee.component.LookupInjectionSource this$0;

  org.jboss.as.ee.component.LookupInjectionSource$2(org.jboss.as.ee.component.LookupInjectionSource);
    Code:
       0: aload_0
       1: aload_1
       2: putfield      #1                  // Field this$0:Lorg/jboss/as/ee/component/LookupInjectionSource;
       5: aload_0
       6: invokespecial #2                  // Method java/lang/Object."<init>":()V
       9: return

  public org.jboss.as.naming.ManagedReference getReference();
    Code:
       0: new           #3                  // class org/jboss/as/naming/ImmediateManagedReference
       3: dup
       4: new           #4                  // class javax/naming/InitialContext
       7: dup
       8: invokespecial #5                  // Method javax/naming/InitialContext."<init>":()V
      11: aload_0
      12: getfield      #1                  // Field this$0:Lorg/jboss/as/ee/component/LookupInjectionSource;
      15: invokestatic  #6                  // Method org/jboss/as/ee/component/LookupInjectionSource.access$000:(Lorg/jboss/as/ee/component/LookupInjectionSource;)Ljava/lang/String;
      18: invokevirtual #7                  // Method javax/naming/InitialContext.lookup:(Ljava/lang/String;)Ljava/lang/Object;
      21: invokespecial #8                  // Method org/jboss/as/naming/ImmediateManagedReference."<init>":(Ljava/lang/Object;)V
      24: areturn
      25: astore_1
      26: getstatic     #10                 // Field org/jboss/as/ee/logging/EeLogger.ROOT_LOGGER:Lorg/jboss/as/ee/logging/EeLogger;
      29: aload_1
      30: ldc           #11                 // String failed to lookup %s
      32: aload_0
      33: getfield      #1                  // Field this$0:Lorg/jboss/as/ee/component/LookupInjectionSource;
      36: invokestatic  #6                  // Method org/jboss/as/ee/component/LookupInjectionSource.access$000:(Lorg/jboss/as/ee/component/LookupInjectionSource;)Ljava/lang/String;
      39: invokeinterface #12,  4           // InterfaceMethod org/jboss/as/ee/logging/EeLogger.tracef:(Ljava/lang/Throwable;Ljava/lang/String;Ljava/lang/Object;)V
      44: aconst_null
      45: areturn
    Exception table:
       from    to  target type
           0    24    25   Class javax/naming/NamingException
}
