Compiled from "ViewService.java"
final class org.jboss.as.ee.component.ViewService$View$MethodDescription {
  private final java.lang.String name;

  private final java.lang.String descriptor;

  final org.jboss.as.ee.component.ViewService$View this$1;

  public org.jboss.as.ee.component.ViewService$View$MethodDescription(org.jboss.as.ee.component.ViewService$View, java.lang.String, java.lang.String);
    Code:
       0: aload_0
       1: aload_1
       2: putfield      #1                  // Field this$1:Lorg/jboss/as/ee/component/ViewService$View;
       5: aload_0
       6: invokespecial #2                  // Method java/lang/Object."<init>":()V
       9: aload_0
      10: aload_2
      11: putfield      #3                  // Field name:Ljava/lang/String;
      14: aload_0
      15: aload_3
      16: putfield      #4                  // Field descriptor:Ljava/lang/String;
      19: return

  public boolean equals(java.lang.Object);
    Code:
       0: aload_0
       1: aload_1
       2: if_acmpne     7
       5: iconst_1
       6: ireturn
       7: aload_1
       8: ifnull        22
      11: aload_0
      12: invokevirtual #5                  // Method java/lang/Object.getClass:()Ljava/lang/Class;
      15: aload_1
      16: invokevirtual #5                  // Method java/lang/Object.getClass:()Ljava/lang/Class;
      19: if_acmpeq     24
      22: iconst_0
      23: ireturn
      24: aload_1
      25: checkcast     #6                  // class org/jboss/as/ee/component/ViewService$View$MethodDescription
      28: astore_2
      29: aload_0
      30: getfield      #4                  // Field descriptor:Ljava/lang/String;
      33: aload_2
      34: getfield      #4                  // Field descriptor:Ljava/lang/String;
      37: invokevirtual #7                  // Method java/lang/String.equals:(Ljava/lang/Object;)Z
      40: ifne          45
      43: iconst_0
      44: ireturn
      45: aload_0
      46: getfield      #3                  // Field name:Ljava/lang/String;
      49: aload_2
      50: getfield      #3                  // Field name:Ljava/lang/String;
      53: invokevirtual #7                  // Method java/lang/String.equals:(Ljava/lang/Object;)Z
      56: ifne          61
      59: iconst_0
      60: ireturn
      61: iconst_1
      62: ireturn

  public int hashCode();
    Code:
       0: aload_0
       1: getfield      #3                  // Field name:Ljava/lang/String;
       4: invokevirtual #8                  // Method java/lang/String.hashCode:()I
       7: istore_1
       8: bipush        31
      10: iload_1
      11: imul
      12: aload_0
      13: getfield      #4                  // Field descriptor:Ljava/lang/String;
      16: invokevirtual #8                  // Method java/lang/String.hashCode:()I
      19: iadd
      20: istore_1
      21: iload_1
      22: ireturn
}
