Compiled from "HttpClientConfiguration.java"
class org.springframework.cloud.commons.httpclient.HttpClientConfiguration$OkHttpClientConfiguration {
  org.springframework.cloud.commons.httpclient.HttpClientConfiguration$OkHttpClientConfiguration();
    Code:
       0: aload_0
       1: invokespecial #1                  // Method java/lang/Object."<init>":()V
       4: return

  public org.springframework.cloud.commons.httpclient.OkHttpClientConnectionPoolFactory connPoolFactory();
    Code:
       0: new           #2                  // class org/springframework/cloud/commons/httpclient/DefaultOkHttpClientConnectionPoolFactory
       3: dup
       4: invokespecial #3                  // Method org/springframework/cloud/commons/httpclient/DefaultOkHttpClientConnectionPoolFactory."<init>":()V
       7: areturn

  public okhttp3.OkHttpClient$Builder okHttpClientBuilder();
    Code:
       0: new           #4                  // class okhttp3/OkHttpClient$Builder
       3: dup
       4: invokespecial #5                  // Method okhttp3/OkHttpClient$Builder."<init>":()V
       7: areturn

  public org.springframework.cloud.commons.httpclient.OkHttpClientFactory okHttpClientFactory(okhttp3.OkHttpClient$Builder);
    Code:
       0: new           #6                  // class org/springframework/cloud/commons/httpclient/DefaultOkHttpClientFactory
       3: dup
       4: aload_1
       5: invokespecial #7                  // Method org/springframework/cloud/commons/httpclient/DefaultOkHttpClientFactory."<init>":(Lokhttp3/OkHttpClient$Builder;)V
       8: areturn
}
