Compiled from "ThreadContextDescriptor.java"
public class org.apache.axis2.classloader.ThreadContextDescriptor {
  private java.lang.ClassLoader oldClassLoader;

  private org.apache.axis2.context.MessageContext oldMessageContext;

  public org.apache.axis2.classloader.ThreadContextDescriptor();
    Code:
       0: aload_0
       1: invokespecial #1                  // Method java/lang/Object."<init>":()V
       4: return

  public java.lang.ClassLoader getOldClassLoader();
    Code:
       0: aload_0
       1: getfield      #2                  // Field oldClassLoader:Ljava/lang/ClassLoader;
       4: areturn

  public void setOldClassLoader(java.lang.ClassLoader);
    Code:
       0: aload_0
       1: aload_1
       2: putfield      #2                  // Field oldClassLoader:Ljava/lang/ClassLoader;
       5: return

  public org.apache.axis2.context.MessageContext getOldMessageContext();
    Code:
       0: aload_0
       1: getfield      #3                  // Field oldMessageContext:Lorg/apache/axis2/context/MessageContext;
       4: areturn

  public void setOldMessageContext(org.apache.axis2.context.MessageContext);
    Code:
       0: aload_0
       1: aload_1
       2: putfield      #3                  // Field oldMessageContext:Lorg/apache/axis2/context/MessageContext;
       5: return

  public static org.apache.axis2.classloader.ThreadContextDescriptor setThreadContext(org.apache.axis2.description.AxisService);
    Code:
       0: new           #4                  // class org/apache/axis2/classloader/ThreadContextDescriptor
       3: dup
       4: invokespecial #5                  // Method "<init>":()V
       7: astore_1
       8: aload_1
       9: getstatic     #6                  // Field org/apache/axis2/context/MessageContext.currentMessageContext:Ljava/lang/ThreadLocal;
      12: invokevirtual #7                  // Method java/lang/ThreadLocal.get:()Ljava/lang/Object;
      15: checkcast     #8                  // class org/apache/axis2/context/MessageContext
      18: putfield      #3                  // Field oldMessageContext:Lorg/apache/axis2/context/MessageContext;
      21: invokestatic  #9                  // Method getContextClassLoader_doPriv:()Ljava/lang/ClassLoader;
      24: astore_2
      25: aload_1
      26: aload_2
      27: putfield      #2                  // Field oldClassLoader:Ljava/lang/ClassLoader;
      30: aload_0
      31: ldc           #11                 // String ServiceTCCL
      33: invokevirtual #12                 // Method org/apache/axis2/description/AxisService.getParameterValue:(Ljava/lang/String;)Ljava/lang/Object;
      36: checkcast     #13                 // class java/lang/String
      39: astore_3
      40: aload_3
      41: ifnull        115
      44: aload_3
      45: invokevirtual #14                 // Method java/lang/String.trim:()Ljava/lang/String;
      48: invokevirtual #15                 // Method java/lang/String.toLowerCase:()Ljava/lang/String;
      51: astore_3
      52: aload_3
      53: ldc           #16                 // String composite
      55: invokevirtual #17                 // Method java/lang/String.equals:(Ljava/lang/Object;)Z
      58: ifeq          94
      61: new           #18                 // class org/apache/axis2/classloader/ThreadContextDescriptor$1
      64: dup
      65: aload_0
      66: aload_2
      67: invokespecial #19                 // Method org/apache/axis2/classloader/ThreadContextDescriptor$1."<init>":(Lorg/apache/axis2/description/AxisService;Ljava/lang/ClassLoader;)V
      70: invokestatic  #20                 // Method java/security/AccessController.doPrivileged:(Ljava/security/PrivilegedAction;)Ljava/lang/Object;
      73: checkcast     #21                 // class java/lang/ClassLoader
      76: astore        4
      78: new           #22                 // class org/apache/axis2/classloader/ThreadContextDescriptor$2
      81: dup
      82: aload         4
      84: invokespecial #23                 // Method org/apache/axis2/classloader/ThreadContextDescriptor$2."<init>":(Ljava/lang/ClassLoader;)V
      87: invokestatic  #24                 // Method org/apache/axis2/java/security/AccessController.doPrivileged:(Ljava/security/PrivilegedAction;)Ljava/lang/Object;
      90: pop
      91: goto          115
      94: aload_3
      95: ldc           #25                 // String service
      97: invokevirtual #17                 // Method java/lang/String.equals:(Ljava/lang/Object;)Z
     100: ifeq          115
     103: new           #26                 // class org/apache/axis2/classloader/ThreadContextDescriptor$3
     106: dup
     107: aload_0
     108: invokespecial #27                 // Method org/apache/axis2/classloader/ThreadContextDescriptor$3."<init>":(Lorg/apache/axis2/description/AxisService;)V
     111: invokestatic  #24                 // Method org/apache/axis2/java/security/AccessController.doPrivileged:(Ljava/security/PrivilegedAction;)Ljava/lang/Object;
     114: pop
     115: aload_1
     116: areturn

  public static org.apache.axis2.classloader.ThreadContextDescriptor setThreadContext(org.apache.axis2.context.MessageContext);
    Code:
       0: aload_0
       1: invokevirtual #28                 // Method org/apache/axis2/context/MessageContext.getAxisService:()Lorg/apache/axis2/description/AxisService;
       4: astore_1
       5: aload_1
       6: invokestatic  #29                 // Method setThreadContext:(Lorg/apache/axis2/description/AxisService;)Lorg/apache/axis2/classloader/ThreadContextDescriptor;
       9: astore_2
      10: aload_0
      11: invokestatic  #30                 // Method org/apache/axis2/context/MessageContext.setCurrentMessageContext:(Lorg/apache/axis2/context/MessageContext;)V
      14: aload_2
      15: areturn

  private static java.lang.ClassLoader getContextClassLoader_doPriv();
    Code:
       0: new           #31                 // class org/apache/axis2/classloader/ThreadContextDescriptor$4
       3: dup
       4: invokespecial #32                 // Method org/apache/axis2/classloader/ThreadContextDescriptor$4."<init>":()V
       7: invokestatic  #24                 // Method org/apache/axis2/java/security/AccessController.doPrivileged:(Ljava/security/PrivilegedAction;)Ljava/lang/Object;
      10: checkcast     #21                 // class java/lang/ClassLoader
      13: areturn
}
