Compiled from "Any.java"
public final class com.google.protobuf.Any extends com.google.protobuf.GeneratedMessageV3 implements com.google.protobuf.AnyOrBuilder {
  private static final long serialVersionUID;

  private volatile com.google.protobuf.Message cachedUnpackValue;

  public static final int TYPE_URL_FIELD_NUMBER;

  private volatile java.lang.Object typeUrl_;

  public static final int VALUE_FIELD_NUMBER;

  private com.google.protobuf.ByteString value_;

  private byte memoizedIsInitialized;

  private static final com.google.protobuf.Any DEFAULT_INSTANCE;

  private static final com.google.protobuf.Parser<com.google.protobuf.Any> PARSER;

  private com.google.protobuf.Any(com.google.protobuf.GeneratedMessageV3$Builder<?>);
    Code:
       0: aload_0
       1: aload_1
       2: invokespecial #4                  // Method com/google/protobuf/GeneratedMessageV3."<init>":(Lcom/google/protobuf/GeneratedMessageV3$Builder;)V
       5: aload_0
       6: iconst_m1
       7: putfield      #5                  // Field memoizedIsInitialized:B
      10: return

  private com.google.protobuf.Any();
    Code:
       0: aload_0
       1: invokespecial #6                  // Method com/google/protobuf/GeneratedMessageV3."<init>":()V
       4: aload_0
       5: iconst_m1
       6: putfield      #5                  // Field memoizedIsInitialized:B
       9: aload_0
      10: ldc           #7                  // String
      12: putfield      #2                  // Field typeUrl_:Ljava/lang/Object;
      15: aload_0
      16: getstatic     #8                  // Field com/google/protobuf/ByteString.EMPTY:Lcom/google/protobuf/ByteString;
      19: putfield      #1                  // Field value_:Lcom/google/protobuf/ByteString;
      22: return

  protected java.lang.Object newInstance(com.google.protobuf.GeneratedMessageV3$UnusedPrivateParameter);
    Code:
       0: new           #9                  // class com/google/protobuf/Any
       3: dup
       4: invokespecial #10                 // Method "<init>":()V
       7: areturn

  public final com.google.protobuf.UnknownFieldSet getUnknownFields();
    Code:
       0: aload_0
       1: getfield      #11                 // Field unknownFields:Lcom/google/protobuf/UnknownFieldSet;
       4: areturn

  public static final com.google.protobuf.Descriptors$Descriptor getDescriptor();
    Code:
       0: getstatic     #12                 // Field com/google/protobuf/AnyProto.internal_static_google_protobuf_Any_descriptor:Lcom/google/protobuf/Descriptors$Descriptor;
       3: areturn

  protected com.google.protobuf.GeneratedMessageV3$FieldAccessorTable internalGetFieldAccessorTable();
    Code:
       0: getstatic     #13                 // Field com/google/protobuf/AnyProto.internal_static_google_protobuf_Any_fieldAccessorTable:Lcom/google/protobuf/GeneratedMessageV3$FieldAccessorTable;
       3: ldc           #9                  // class com/google/protobuf/Any
       5: ldc           #14                 // class com/google/protobuf/Any$Builder
       7: invokevirtual #15                 // Method com/google/protobuf/GeneratedMessageV3$FieldAccessorTable.ensureFieldAccessorsInitialized:(Ljava/lang/Class;Ljava/lang/Class;)Lcom/google/protobuf/GeneratedMessageV3$FieldAccessorTable;
      10: areturn

  private static java.lang.String getTypeUrl(java.lang.String, com.google.protobuf.Descriptors$Descriptor);
    Code:
       0: aload_0
       1: ldc           #16                 // String /
       3: invokevirtual #17                 // Method java/lang/String.endsWith:(Ljava/lang/String;)Z
       6: ifeq          33
       9: new           #18                 // class java/lang/StringBuilder
      12: dup
      13: invokespecial #19                 // Method java/lang/StringBuilder."<init>":()V
      16: aload_0
      17: invokevirtual #20                 // Method java/lang/StringBuilder.append:(Ljava/lang/String;)Ljava/lang/StringBuilder;
      20: aload_1
      21: invokevirtual #21                 // Method com/google/protobuf/Descriptors$Descriptor.getFullName:()Ljava/lang/String;
      24: invokevirtual #20                 // Method java/lang/StringBuilder.append:(Ljava/lang/String;)Ljava/lang/StringBuilder;
      27: invokevirtual #22                 // Method java/lang/StringBuilder.toString:()Ljava/lang/String;
      30: goto          59
      33: new           #18                 // class java/lang/StringBuilder
      36: dup
      37: invokespecial #19                 // Method java/lang/StringBuilder."<init>":()V
      40: aload_0
      41: invokevirtual #20                 // Method java/lang/StringBuilder.append:(Ljava/lang/String;)Ljava/lang/StringBuilder;
      44: ldc           #16                 // String /
      46: invokevirtual #20                 // Method java/lang/StringBuilder.append:(Ljava/lang/String;)Ljava/lang/StringBuilder;
      49: aload_1
      50: invokevirtual #21                 // Method com/google/protobuf/Descriptors$Descriptor.getFullName:()Ljava/lang/String;
      53: invokevirtual #20                 // Method java/lang/StringBuilder.append:(Ljava/lang/String;)Ljava/lang/StringBuilder;
      56: invokevirtual #22                 // Method java/lang/StringBuilder.toString:()Ljava/lang/String;
      59: areturn

  private static java.lang.String getTypeNameFromTypeUrl(java.lang.String);
    Code:
       0: aload_0
       1: bipush        47
       3: invokevirtual #23                 // Method java/lang/String.lastIndexOf:(I)I
       6: istore_1
       7: iload_1
       8: iconst_m1
       9: if_icmpne     17
      12: ldc           #7                  // String
      14: goto          24
      17: aload_0
      18: iload_1
      19: iconst_1
      20: iadd
      21: invokevirtual #24                 // Method java/lang/String.substring:(I)Ljava/lang/String;
      24: areturn

  public static <T extends com.google.protobuf.Message> com.google.protobuf.Any pack(T);
    Code:
       0: invokestatic  #25                 // Method newBuilder:()Lcom/google/protobuf/Any$Builder;
       3: ldc           #26                 // String type.googleapis.com
       5: aload_0
       6: invokeinterface #27,  1           // InterfaceMethod com/google/protobuf/Message.getDescriptorForType:()Lcom/google/protobuf/Descriptors$Descriptor;
      11: invokestatic  #28                 // Method getTypeUrl:(Ljava/lang/String;Lcom/google/protobuf/Descriptors$Descriptor;)Ljava/lang/String;
      14: invokevirtual #29                 // Method com/google/protobuf/Any$Builder.setTypeUrl:(Ljava/lang/String;)Lcom/google/protobuf/Any$Builder;
      17: aload_0
      18: invokeinterface #30,  1           // InterfaceMethod com/google/protobuf/Message.toByteString:()Lcom/google/protobuf/ByteString;
      23: invokevirtual #31                 // Method com/google/protobuf/Any$Builder.setValue:(Lcom/google/protobuf/ByteString;)Lcom/google/protobuf/Any$Builder;
      26: invokevirtual #32                 // Method com/google/protobuf/Any$Builder.build:()Lcom/google/protobuf/Any;
      29: areturn

  public static <T extends com.google.protobuf.Message> com.google.protobuf.Any pack(T, java.lang.String);
    Code:
       0: invokestatic  #25                 // Method newBuilder:()Lcom/google/protobuf/Any$Builder;
       3: aload_1
       4: aload_0
       5: invokeinterface #27,  1           // InterfaceMethod com/google/protobuf/Message.getDescriptorForType:()Lcom/google/protobuf/Descriptors$Descriptor;
      10: invokestatic  #28                 // Method getTypeUrl:(Ljava/lang/String;Lcom/google/protobuf/Descriptors$Descriptor;)Ljava/lang/String;
      13: invokevirtual #29                 // Method com/google/protobuf/Any$Builder.setTypeUrl:(Ljava/lang/String;)Lcom/google/protobuf/Any$Builder;
      16: aload_0
      17: invokeinterface #30,  1           // InterfaceMethod com/google/protobuf/Message.toByteString:()Lcom/google/protobuf/ByteString;
      22: invokevirtual #31                 // Method com/google/protobuf/Any$Builder.setValue:(Lcom/google/protobuf/ByteString;)Lcom/google/protobuf/Any$Builder;
      25: invokevirtual #32                 // Method com/google/protobuf/Any$Builder.build:()Lcom/google/protobuf/Any;
      28: areturn

  public <T extends com.google.protobuf.Message> boolean is(java.lang.Class<T>);
    Code:
       0: aload_1
       1: invokestatic  #33                 // Method com/google/protobuf/Internal.getDefaultInstance:(Ljava/lang/Class;)Lcom/google/protobuf/MessageLite;
       4: checkcast     #34                 // class com/google/protobuf/Message
       7: astore_2
       8: aload_0
       9: invokevirtual #35                 // Method getTypeUrl:()Ljava/lang/String;
      12: invokestatic  #36                 // Method getTypeNameFromTypeUrl:(Ljava/lang/String;)Ljava/lang/String;
      15: aload_2
      16: invokeinterface #27,  1           // InterfaceMethod com/google/protobuf/Message.getDescriptorForType:()Lcom/google/protobuf/Descriptors$Descriptor;
      21: invokevirtual #21                 // Method com/google/protobuf/Descriptors$Descriptor.getFullName:()Ljava/lang/String;
      24: invokevirtual #37                 // Method java/lang/String.equals:(Ljava/lang/Object;)Z
      27: ireturn

  public <T extends com.google.protobuf.Message> T unpack(java.lang.Class<T>) throws com.google.protobuf.InvalidProtocolBufferException;
    Code:
       0: iconst_0
       1: istore_2
       2: aload_0
       3: getfield      #38                 // Field cachedUnpackValue:Lcom/google/protobuf/Message;
       6: ifnull        27
       9: aload_0
      10: getfield      #38                 // Field cachedUnpackValue:Lcom/google/protobuf/Message;
      13: invokevirtual #39                 // Method java/lang/Object.getClass:()Ljava/lang/Class;
      16: aload_1
      17: if_acmpne     25
      20: aload_0
      21: getfield      #38                 // Field cachedUnpackValue:Lcom/google/protobuf/Message;
      24: areturn
      25: iconst_1
      26: istore_2
      27: iload_2
      28: ifne          39
      31: aload_0
      32: aload_1
      33: invokevirtual #40                 // Method is:(Ljava/lang/Class;)Z
      36: ifne          49
      39: new           #41                 // class com/google/protobuf/InvalidProtocolBufferException
      42: dup
      43: ldc           #42                 // String Type of the Any message does not match the given class.
      45: invokespecial #43                 // Method com/google/protobuf/InvalidProtocolBufferException."<init>":(Ljava/lang/String;)V
      48: athrow
      49: aload_1
      50: invokestatic  #33                 // Method com/google/protobuf/Internal.getDefaultInstance:(Ljava/lang/Class;)Lcom/google/protobuf/MessageLite;
      53: checkcast     #34                 // class com/google/protobuf/Message
      56: astore_3
      57: aload_3
      58: invokeinterface #44,  1           // InterfaceMethod com/google/protobuf/Message.getParserForType:()Lcom/google/protobuf/Parser;
      63: aload_0
      64: invokevirtual #45                 // Method getValue:()Lcom/google/protobuf/ByteString;
      67: invokeinterface #46,  2           // InterfaceMethod com/google/protobuf/Parser.parseFrom:(Lcom/google/protobuf/ByteString;)Ljava/lang/Object;
      72: checkcast     #34                 // class com/google/protobuf/Message
      75: astore        4
      77: aload_0
      78: aload         4
      80: putfield      #38                 // Field cachedUnpackValue:Lcom/google/protobuf/Message;
      83: aload         4
      85: areturn

  public java.lang.String getTypeUrl();
    Code:
       0: aload_0
       1: getfield      #2                  // Field typeUrl_:Ljava/lang/Object;
       4: astore_1
       5: aload_1
       6: instanceof    #47                 // class java/lang/String
       9: ifeq          17
      12: aload_1
      13: checkcast     #47                 // class java/lang/String
      16: areturn
      17: aload_1
      18: checkcast     #48                 // class com/google/protobuf/ByteString
      21: astore_2
      22: aload_2
      23: invokevirtual #49                 // Method com/google/protobuf/ByteString.toStringUtf8:()Ljava/lang/String;
      26: astore_3
      27: aload_0
      28: aload_3
      29: putfield      #2                  // Field typeUrl_:Ljava/lang/Object;
      32: aload_3
      33: areturn

  public com.google.protobuf.ByteString getTypeUrlBytes();
    Code:
       0: aload_0
       1: getfield      #2                  // Field typeUrl_:Ljava/lang/Object;
       4: astore_1
       5: aload_1
       6: instanceof    #47                 // class java/lang/String
       9: ifeq          27
      12: aload_1
      13: checkcast     #47                 // class java/lang/String
      16: invokestatic  #50                 // Method com/google/protobuf/ByteString.copyFromUtf8:(Ljava/lang/String;)Lcom/google/protobuf/ByteString;
      19: astore_2
      20: aload_0
      21: aload_2
      22: putfield      #2                  // Field typeUrl_:Ljava/lang/Object;
      25: aload_2
      26: areturn
      27: aload_1
      28: checkcast     #48                 // class com/google/protobuf/ByteString
      31: areturn

  public com.google.protobuf.ByteString getValue();
    Code:
       0: aload_0
       1: getfield      #1                  // Field value_:Lcom/google/protobuf/ByteString;
       4: areturn

  public final boolean isInitialized();
    Code:
       0: aload_0
       1: getfield      #5                  // Field memoizedIsInitialized:B
       4: istore_1
       5: iload_1
       6: iconst_1
       7: if_icmpne     12
      10: iconst_1
      11: ireturn
      12: iload_1
      13: ifne          18
      16: iconst_0
      17: ireturn
      18: aload_0
      19: iconst_1
      20: putfield      #5                  // Field memoizedIsInitialized:B
      23: iconst_1
      24: ireturn

  public void writeTo(com.google.protobuf.CodedOutputStream) throws java.io.IOException;
    Code:
       0: aload_0
       1: getfield      #2                  // Field typeUrl_:Ljava/lang/Object;
       4: invokestatic  #51                 // Method com/google/protobuf/GeneratedMessageV3.isStringEmpty:(Ljava/lang/Object;)Z
       7: ifne          19
      10: aload_1
      11: iconst_1
      12: aload_0
      13: getfield      #2                  // Field typeUrl_:Ljava/lang/Object;
      16: invokestatic  #52                 // Method com/google/protobuf/GeneratedMessageV3.writeString:(Lcom/google/protobuf/CodedOutputStream;ILjava/lang/Object;)V
      19: aload_0
      20: getfield      #1                  // Field value_:Lcom/google/protobuf/ByteString;
      23: invokevirtual #53                 // Method com/google/protobuf/ByteString.isEmpty:()Z
      26: ifne          38
      29: aload_1
      30: iconst_2
      31: aload_0
      32: getfield      #1                  // Field value_:Lcom/google/protobuf/ByteString;
      35: invokevirtual #54                 // Method com/google/protobuf/CodedOutputStream.writeBytes:(ILcom/google/protobuf/ByteString;)V
      38: aload_0
      39: invokevirtual #55                 // Method getUnknownFields:()Lcom/google/protobuf/UnknownFieldSet;
      42: aload_1
      43: invokevirtual #56                 // Method com/google/protobuf/UnknownFieldSet.writeTo:(Lcom/google/protobuf/CodedOutputStream;)V
      46: return

  public int getSerializedSize();
    Code:
       0: aload_0
       1: getfield      #57                 // Field memoizedSize:I
       4: istore_1
       5: iload_1
       6: iconst_m1
       7: if_icmpeq     12
      10: iload_1
      11: ireturn
      12: iconst_0
      13: istore_1
      14: aload_0
      15: getfield      #2                  // Field typeUrl_:Ljava/lang/Object;
      18: invokestatic  #51                 // Method com/google/protobuf/GeneratedMessageV3.isStringEmpty:(Ljava/lang/Object;)Z
      21: ifne          35
      24: iload_1
      25: iconst_1
      26: aload_0
      27: getfield      #2                  // Field typeUrl_:Ljava/lang/Object;
      30: invokestatic  #58                 // Method com/google/protobuf/GeneratedMessageV3.computeStringSize:(ILjava/lang/Object;)I
      33: iadd
      34: istore_1
      35: aload_0
      36: getfield      #1                  // Field value_:Lcom/google/protobuf/ByteString;
      39: invokevirtual #53                 // Method com/google/protobuf/ByteString.isEmpty:()Z
      42: ifne          56
      45: iload_1
      46: iconst_2
      47: aload_0
      48: getfield      #1                  // Field value_:Lcom/google/protobuf/ByteString;
      51: invokestatic  #59                 // Method com/google/protobuf/CodedOutputStream.computeBytesSize:(ILcom/google/protobuf/ByteString;)I
      54: iadd
      55: istore_1
      56: iload_1
      57: aload_0
      58: invokevirtual #55                 // Method getUnknownFields:()Lcom/google/protobuf/UnknownFieldSet;
      61: invokevirtual #60                 // Method com/google/protobuf/UnknownFieldSet.getSerializedSize:()I
      64: iadd
      65: istore_1
      66: aload_0
      67: iload_1
      68: putfield      #57                 // Field memoizedSize:I
      71: iload_1
      72: ireturn

  public boolean equals(java.lang.Object);
    Code:
       0: aload_1
       1: aload_0
       2: if_acmpne     7
       5: iconst_1
       6: ireturn
       7: aload_1
       8: instanceof    #9                  // class com/google/protobuf/Any
      11: ifne          20
      14: aload_0
      15: aload_1
      16: invokespecial #61                 // Method com/google/protobuf/GeneratedMessageV3.equals:(Ljava/lang/Object;)Z
      19: ireturn
      20: aload_1
      21: checkcast     #9                  // class com/google/protobuf/Any
      24: astore_2
      25: aload_0
      26: invokevirtual #35                 // Method getTypeUrl:()Ljava/lang/String;
      29: aload_2
      30: invokevirtual #35                 // Method getTypeUrl:()Ljava/lang/String;
      33: invokevirtual #37                 // Method java/lang/String.equals:(Ljava/lang/Object;)Z
      36: ifne          41
      39: iconst_0
      40: ireturn
      41: aload_0
      42: invokevirtual #45                 // Method getValue:()Lcom/google/protobuf/ByteString;
      45: aload_2
      46: invokevirtual #45                 // Method getValue:()Lcom/google/protobuf/ByteString;
      49: invokevirtual #62                 // Method com/google/protobuf/ByteString.equals:(Ljava/lang/Object;)Z
      52: ifne          57
      55: iconst_0
      56: ireturn
      57: aload_0
      58: invokevirtual #55                 // Method getUnknownFields:()Lcom/google/protobuf/UnknownFieldSet;
      61: aload_2
      62: invokevirtual #55                 // Method getUnknownFields:()Lcom/google/protobuf/UnknownFieldSet;
      65: invokevirtual #63                 // Method com/google/protobuf/UnknownFieldSet.equals:(Ljava/lang/Object;)Z
      68: ifne          73
      71: iconst_0
      72: ireturn
      73: iconst_1
      74: ireturn

  public int hashCode();
    Code:
       0: aload_0
       1: getfield      #64                 // Field memoizedHashCode:I
       4: ifeq          12
       7: aload_0
       8: getfield      #64                 // Field memoizedHashCode:I
      11: ireturn
      12: bipush        41
      14: istore_1
      15: bipush        19
      17: iload_1
      18: imul
      19: invokestatic  #65                 // Method getDescriptor:()Lcom/google/protobuf/Descriptors$Descriptor;
      22: invokevirtual #66                 // Method java/lang/Object.hashCode:()I
      25: iadd
      26: istore_1
      27: bipush        37
      29: iload_1
      30: imul
      31: iconst_1
      32: iadd
      33: istore_1
      34: bipush        53
      36: iload_1
      37: imul
      38: aload_0
      39: invokevirtual #35                 // Method getTypeUrl:()Ljava/lang/String;
      42: invokevirtual #67                 // Method java/lang/String.hashCode:()I
      45: iadd
      46: istore_1
      47: bipush        37
      49: iload_1
      50: imul
      51: iconst_2
      52: iadd
      53: istore_1
      54: bipush        53
      56: iload_1
      57: imul
      58: aload_0
      59: invokevirtual #45                 // Method getValue:()Lcom/google/protobuf/ByteString;
      62: invokevirtual #68                 // Method com/google/protobuf/ByteString.hashCode:()I
      65: iadd
      66: istore_1
      67: bipush        29
      69: iload_1
      70: imul
      71: aload_0
      72: invokevirtual #55                 // Method getUnknownFields:()Lcom/google/protobuf/UnknownFieldSet;
      75: invokevirtual #69                 // Method com/google/protobuf/UnknownFieldSet.hashCode:()I
      78: iadd
      79: istore_1
      80: aload_0
      81: iload_1
      82: putfield      #64                 // Field memoizedHashCode:I
      85: iload_1
      86: ireturn

  public static com.google.protobuf.Any parseFrom(java.nio.ByteBuffer) throws com.google.protobuf.InvalidProtocolBufferException;
    Code:
       0: getstatic     #70                 // Field PARSER:Lcom/google/protobuf/Parser;
       3: aload_0
       4: invokeinterface #71,  2           // InterfaceMethod com/google/protobuf/Parser.parseFrom:(Ljava/nio/ByteBuffer;)Ljava/lang/Object;
       9: checkcast     #9                  // class com/google/protobuf/Any
      12: areturn

  public static com.google.protobuf.Any parseFrom(java.nio.ByteBuffer, com.google.protobuf.ExtensionRegistryLite) throws com.google.protobuf.InvalidProtocolBufferException;
    Code:
       0: getstatic     #70                 // Field PARSER:Lcom/google/protobuf/Parser;
       3: aload_0
       4: aload_1
       5: invokeinterface #72,  3           // InterfaceMethod com/google/protobuf/Parser.parseFrom:(Ljava/nio/ByteBuffer;Lcom/google/protobuf/ExtensionRegistryLite;)Ljava/lang/Object;
      10: checkcast     #9                  // class com/google/protobuf/Any
      13: areturn

  public static com.google.protobuf.Any parseFrom(com.google.protobuf.ByteString) throws com.google.protobuf.InvalidProtocolBufferException;
    Code:
       0: getstatic     #70                 // Field PARSER:Lcom/google/protobuf/Parser;
       3: aload_0
       4: invokeinterface #46,  2           // InterfaceMethod com/google/protobuf/Parser.parseFrom:(Lcom/google/protobuf/ByteString;)Ljava/lang/Object;
       9: checkcast     #9                  // class com/google/protobuf/Any
      12: areturn

  public static com.google.protobuf.Any parseFrom(com.google.protobuf.ByteString, com.google.protobuf.ExtensionRegistryLite) throws com.google.protobuf.InvalidProtocolBufferException;
    Code:
       0: getstatic     #70                 // Field PARSER:Lcom/google/protobuf/Parser;
       3: aload_0
       4: aload_1
       5: invokeinterface #73,  3           // InterfaceMethod com/google/protobuf/Parser.parseFrom:(Lcom/google/protobuf/ByteString;Lcom/google/protobuf/ExtensionRegistryLite;)Ljava/lang/Object;
      10: checkcast     #9                  // class com/google/protobuf/Any
      13: areturn

  public static com.google.protobuf.Any parseFrom(byte[]) throws com.google.protobuf.InvalidProtocolBufferException;
    Code:
       0: getstatic     #70                 // Field PARSER:Lcom/google/protobuf/Parser;
       3: aload_0
       4: invokeinterface #74,  2           // InterfaceMethod com/google/protobuf/Parser.parseFrom:([B)Ljava/lang/Object;
       9: checkcast     #9                  // class com/google/protobuf/Any
      12: areturn

  public static com.google.protobuf.Any parseFrom(byte[], com.google.protobuf.ExtensionRegistryLite) throws com.google.protobuf.InvalidProtocolBufferException;
    Code:
       0: getstatic     #70                 // Field PARSER:Lcom/google/protobuf/Parser;
       3: aload_0
       4: aload_1
       5: invokeinterface #75,  3           // InterfaceMethod com/google/protobuf/Parser.parseFrom:([BLcom/google/protobuf/ExtensionRegistryLite;)Ljava/lang/Object;
      10: checkcast     #9                  // class com/google/protobuf/Any
      13: areturn

  public static com.google.protobuf.Any parseFrom(java.io.InputStream) throws java.io.IOException;
    Code:
       0: getstatic     #70                 // Field PARSER:Lcom/google/protobuf/Parser;
       3: aload_0
       4: invokestatic  #76                 // Method com/google/protobuf/GeneratedMessageV3.parseWithIOException:(Lcom/google/protobuf/Parser;Ljava/io/InputStream;)Lcom/google/protobuf/Message;
       7: checkcast     #9                  // class com/google/protobuf/Any
      10: areturn

  public static com.google.protobuf.Any parseFrom(java.io.InputStream, com.google.protobuf.ExtensionRegistryLite) throws java.io.IOException;
    Code:
       0: getstatic     #70                 // Field PARSER:Lcom/google/protobuf/Parser;
       3: aload_0
       4: aload_1
       5: invokestatic  #77                 // Method com/google/protobuf/GeneratedMessageV3.parseWithIOException:(Lcom/google/protobuf/Parser;Ljava/io/InputStream;Lcom/google/protobuf/ExtensionRegistryLite;)Lcom/google/protobuf/Message;
       8: checkcast     #9                  // class com/google/protobuf/Any
      11: areturn

  public static com.google.protobuf.Any parseDelimitedFrom(java.io.InputStream) throws java.io.IOException;
    Code:
       0: getstatic     #70                 // Field PARSER:Lcom/google/protobuf/Parser;
       3: aload_0
       4: invokestatic  #78                 // Method com/google/protobuf/GeneratedMessageV3.parseDelimitedWithIOException:(Lcom/google/protobuf/Parser;Ljava/io/InputStream;)Lcom/google/protobuf/Message;
       7: checkcast     #9                  // class com/google/protobuf/Any
      10: areturn

  public static com.google.protobuf.Any parseDelimitedFrom(java.io.InputStream, com.google.protobuf.ExtensionRegistryLite) throws java.io.IOException;
    Code:
       0: getstatic     #70                 // Field PARSER:Lcom/google/protobuf/Parser;
       3: aload_0
       4: aload_1
       5: invokestatic  #79                 // Method com/google/protobuf/GeneratedMessageV3.parseDelimitedWithIOException:(Lcom/google/protobuf/Parser;Ljava/io/InputStream;Lcom/google/protobuf/ExtensionRegistryLite;)Lcom/google/protobuf/Message;
       8: checkcast     #9                  // class com/google/protobuf/Any
      11: areturn

  public static com.google.protobuf.Any parseFrom(com.google.protobuf.CodedInputStream) throws java.io.IOException;
    Code:
       0: getstatic     #70                 // Field PARSER:Lcom/google/protobuf/Parser;
       3: aload_0
       4: invokestatic  #80                 // Method com/google/protobuf/GeneratedMessageV3.parseWithIOException:(Lcom/google/protobuf/Parser;Lcom/google/protobuf/CodedInputStream;)Lcom/google/protobuf/Message;
       7: checkcast     #9                  // class com/google/protobuf/Any
      10: areturn

  public static com.google.protobuf.Any parseFrom(com.google.protobuf.CodedInputStream, com.google.protobuf.ExtensionRegistryLite) throws java.io.IOException;
    Code:
       0: getstatic     #70                 // Field PARSER:Lcom/google/protobuf/Parser;
       3: aload_0
       4: aload_1
       5: invokestatic  #81                 // Method com/google/protobuf/GeneratedMessageV3.parseWithIOException:(Lcom/google/protobuf/Parser;Lcom/google/protobuf/CodedInputStream;Lcom/google/protobuf/ExtensionRegistryLite;)Lcom/google/protobuf/Message;
       8: checkcast     #9                  // class com/google/protobuf/Any
      11: areturn

  public com.google.protobuf.Any$Builder newBuilderForType();
    Code:
       0: invokestatic  #25                 // Method newBuilder:()Lcom/google/protobuf/Any$Builder;
       3: areturn

  public static com.google.protobuf.Any$Builder newBuilder();
    Code:
       0: getstatic     #82                 // Field DEFAULT_INSTANCE:Lcom/google/protobuf/Any;
       3: invokevirtual #83                 // Method toBuilder:()Lcom/google/protobuf/Any$Builder;
       6: areturn

  public static com.google.protobuf.Any$Builder newBuilder(com.google.protobuf.Any);
    Code:
       0: getstatic     #82                 // Field DEFAULT_INSTANCE:Lcom/google/protobuf/Any;
       3: invokevirtual #83                 // Method toBuilder:()Lcom/google/protobuf/Any$Builder;
       6: aload_0
       7: invokevirtual #84                 // Method com/google/protobuf/Any$Builder.mergeFrom:(Lcom/google/protobuf/Any;)Lcom/google/protobuf/Any$Builder;
      10: areturn

  public com.google.protobuf.Any$Builder toBuilder();
    Code:
       0: aload_0
       1: getstatic     #82                 // Field DEFAULT_INSTANCE:Lcom/google/protobuf/Any;
       4: if_acmpne     18
       7: new           #14                 // class com/google/protobuf/Any$Builder
      10: dup
      11: aconst_null
      12: invokespecial #85                 // Method com/google/protobuf/Any$Builder."<init>":(Lcom/google/protobuf/Any$1;)V
      15: goto          30
      18: new           #14                 // class com/google/protobuf/Any$Builder
      21: dup
      22: aconst_null
      23: invokespecial #85                 // Method com/google/protobuf/Any$Builder."<init>":(Lcom/google/protobuf/Any$1;)V
      26: aload_0
      27: invokevirtual #84                 // Method com/google/protobuf/Any$Builder.mergeFrom:(Lcom/google/protobuf/Any;)Lcom/google/protobuf/Any$Builder;
      30: areturn

  protected com.google.protobuf.Any$Builder newBuilderForType(com.google.protobuf.GeneratedMessageV3$BuilderParent);
    Code:
       0: new           #14                 // class com/google/protobuf/Any$Builder
       3: dup
       4: aload_1
       5: aconst_null
       6: invokespecial #86                 // Method com/google/protobuf/Any$Builder."<init>":(Lcom/google/protobuf/GeneratedMessageV3$BuilderParent;Lcom/google/protobuf/Any$1;)V
       9: astore_2
      10: aload_2
      11: areturn

  public static com.google.protobuf.Any getDefaultInstance();
    Code:
       0: getstatic     #82                 // Field DEFAULT_INSTANCE:Lcom/google/protobuf/Any;
       3: areturn

  public static com.google.protobuf.Parser<com.google.protobuf.Any> parser();
    Code:
       0: getstatic     #70                 // Field PARSER:Lcom/google/protobuf/Parser;
       3: areturn

  public com.google.protobuf.Parser<com.google.protobuf.Any> getParserForType();
    Code:
       0: getstatic     #70                 // Field PARSER:Lcom/google/protobuf/Parser;
       3: areturn

  public com.google.protobuf.Any getDefaultInstanceForType();
    Code:
       0: getstatic     #82                 // Field DEFAULT_INSTANCE:Lcom/google/protobuf/Any;
       3: areturn

  protected com.google.protobuf.Message$Builder newBuilderForType(com.google.protobuf.GeneratedMessageV3$BuilderParent);
    Code:
       0: aload_0
       1: aload_1
       2: invokevirtual #87                 // Method newBuilderForType:(Lcom/google/protobuf/GeneratedMessageV3$BuilderParent;)Lcom/google/protobuf/Any$Builder;
       5: areturn

  public com.google.protobuf.Message$Builder toBuilder();
    Code:
       0: aload_0
       1: invokevirtual #83                 // Method toBuilder:()Lcom/google/protobuf/Any$Builder;
       4: areturn

  public com.google.protobuf.Message$Builder newBuilderForType();
    Code:
       0: aload_0
       1: invokevirtual #88                 // Method newBuilderForType:()Lcom/google/protobuf/Any$Builder;
       4: areturn

  public com.google.protobuf.MessageLite$Builder toBuilder();
    Code:
       0: aload_0
       1: invokevirtual #83                 // Method toBuilder:()Lcom/google/protobuf/Any$Builder;
       4: areturn

  public com.google.protobuf.MessageLite$Builder newBuilderForType();
    Code:
       0: aload_0
       1: invokevirtual #88                 // Method newBuilderForType:()Lcom/google/protobuf/Any$Builder;
       4: areturn

  public com.google.protobuf.MessageLite getDefaultInstanceForType();
    Code:
       0: aload_0
       1: invokevirtual #89                 // Method getDefaultInstanceForType:()Lcom/google/protobuf/Any;
       4: areturn

  public com.google.protobuf.Message getDefaultInstanceForType();
    Code:
       0: aload_0
       1: invokevirtual #89                 // Method getDefaultInstanceForType:()Lcom/google/protobuf/Any;
       4: areturn

  com.google.protobuf.Any(com.google.protobuf.GeneratedMessageV3$Builder, com.google.protobuf.Any$1);
    Code:
       0: aload_0
       1: aload_1
       2: invokespecial #3                  // Method "<init>":(Lcom/google/protobuf/GeneratedMessageV3$Builder;)V
       5: return

  static java.lang.Object access$302(com.google.protobuf.Any, java.lang.Object);
    Code:
       0: aload_0
       1: aload_1
       2: dup_x1
       3: putfield      #2                  // Field typeUrl_:Ljava/lang/Object;
       6: areturn

  static com.google.protobuf.ByteString access$402(com.google.protobuf.Any, com.google.protobuf.ByteString);
    Code:
       0: aload_0
       1: aload_1
       2: dup_x1
       3: putfield      #1                  // Field value_:Lcom/google/protobuf/ByteString;
       6: areturn

  static java.lang.Object access$300(com.google.protobuf.Any);
    Code:
       0: aload_0
       1: getfield      #2                  // Field typeUrl_:Ljava/lang/Object;
       4: areturn

  static {};
    Code:
       0: new           #9                  // class com/google/protobuf/Any
       3: dup
       4: invokespecial #10                 // Method "<init>":()V
       7: putstatic     #82                 // Field DEFAULT_INSTANCE:Lcom/google/protobuf/Any;
      10: new           #90                 // class com/google/protobuf/Any$1
      13: dup
      14: invokespecial #91                 // Method com/google/protobuf/Any$1."<init>":()V
      17: putstatic     #70                 // Field PARSER:Lcom/google/protobuf/Parser;
      20: return
}
