Compiled from "DescriptorProtos.java"
public final class com.google.protobuf.DescriptorProtos$FileOptions$Builder extends com.google.protobuf.GeneratedMessageV3$ExtendableBuilder<com.google.protobuf.DescriptorProtos$FileOptions, com.google.protobuf.DescriptorProtos$FileOptions$Builder> implements com.google.protobuf.DescriptorProtos$FileOptionsOrBuilder {
  private int bitField0_;

  private java.lang.Object javaPackage_;

  private java.lang.Object javaOuterClassname_;

  private boolean javaMultipleFiles_;

  private boolean javaGenerateEqualsAndHash_;

  private boolean javaStringCheckUtf8_;

  private int optimizeFor_;

  private java.lang.Object goPackage_;

  private boolean ccGenericServices_;

  private boolean javaGenericServices_;

  private boolean pyGenericServices_;

  private boolean phpGenericServices_;

  private boolean deprecated_;

  private boolean ccEnableArenas_;

  private java.lang.Object objcClassPrefix_;

  private java.lang.Object csharpNamespace_;

  private java.lang.Object swiftPrefix_;

  private java.lang.Object phpClassPrefix_;

  private java.lang.Object phpNamespace_;

  private java.lang.Object phpMetadataNamespace_;

  private java.lang.Object rubyPackage_;

  private java.util.List<com.google.protobuf.DescriptorProtos$UninterpretedOption> uninterpretedOption_;

  private com.google.protobuf.RepeatedFieldBuilderV3<com.google.protobuf.DescriptorProtos$UninterpretedOption, com.google.protobuf.DescriptorProtos$UninterpretedOption$Builder, com.google.protobuf.DescriptorProtos$UninterpretedOptionOrBuilder> uninterpretedOptionBuilder_;

  public static final com.google.protobuf.Descriptors$Descriptor getDescriptor();
    Code:
       0: invokestatic  #3                  // Method com/google/protobuf/DescriptorProtos.access$13700:()Lcom/google/protobuf/Descriptors$Descriptor;
       3: areturn

  protected com.google.protobuf.GeneratedMessageV3$FieldAccessorTable internalGetFieldAccessorTable();
    Code:
       0: invokestatic  #4                  // Method com/google/protobuf/DescriptorProtos.access$13800:()Lcom/google/protobuf/GeneratedMessageV3$FieldAccessorTable;
       3: ldc           #5                  // class com/google/protobuf/DescriptorProtos$FileOptions
       5: ldc           #6                  // class com/google/protobuf/DescriptorProtos$FileOptions$Builder
       7: invokevirtual #7                  // Method com/google/protobuf/GeneratedMessageV3$FieldAccessorTable.ensureFieldAccessorsInitialized:(Ljava/lang/Class;Ljava/lang/Class;)Lcom/google/protobuf/GeneratedMessageV3$FieldAccessorTable;
      10: areturn

  private com.google.protobuf.DescriptorProtos$FileOptions$Builder();
    Code:
       0: aload_0
       1: invokespecial #8                  // Method com/google/protobuf/GeneratedMessageV3$ExtendableBuilder."<init>":()V
       4: aload_0
       5: ldc           #9                  // String
       7: putfield      #10                 // Field javaPackage_:Ljava/lang/Object;
      10: aload_0
      11: ldc           #9                  // String
      13: putfield      #11                 // Field javaOuterClassname_:Ljava/lang/Object;
      16: aload_0
      17: iconst_1
      18: putfield      #12                 // Field optimizeFor_:I
      21: aload_0
      22: ldc           #9                  // String
      24: putfield      #13                 // Field goPackage_:Ljava/lang/Object;
      27: aload_0
      28: iconst_1
      29: putfield      #14                 // Field ccEnableArenas_:Z
      32: aload_0
      33: ldc           #9                  // String
      35: putfield      #15                 // Field objcClassPrefix_:Ljava/lang/Object;
      38: aload_0
      39: ldc           #9                  // String
      41: putfield      #16                 // Field csharpNamespace_:Ljava/lang/Object;
      44: aload_0
      45: ldc           #9                  // String
      47: putfield      #17                 // Field swiftPrefix_:Ljava/lang/Object;
      50: aload_0
      51: ldc           #9                  // String
      53: putfield      #18                 // Field phpClassPrefix_:Ljava/lang/Object;
      56: aload_0
      57: ldc           #9                  // String
      59: putfield      #19                 // Field phpNamespace_:Ljava/lang/Object;
      62: aload_0
      63: ldc           #9                  // String
      65: putfield      #20                 // Field phpMetadataNamespace_:Ljava/lang/Object;
      68: aload_0
      69: ldc           #9                  // String
      71: putfield      #21                 // Field rubyPackage_:Ljava/lang/Object;
      74: aload_0
      75: invokestatic  #22                 // Method java/util/Collections.emptyList:()Ljava/util/List;
      78: putfield      #23                 // Field uninterpretedOption_:Ljava/util/List;
      81: return

  private com.google.protobuf.DescriptorProtos$FileOptions$Builder(com.google.protobuf.GeneratedMessageV3$BuilderParent);
    Code:
       0: aload_0
       1: aload_1
       2: invokespecial #24                 // Method com/google/protobuf/GeneratedMessageV3$ExtendableBuilder."<init>":(Lcom/google/protobuf/GeneratedMessageV3$BuilderParent;)V
       5: aload_0
       6: ldc           #9                  // String
       8: putfield      #10                 // Field javaPackage_:Ljava/lang/Object;
      11: aload_0
      12: ldc           #9                  // String
      14: putfield      #11                 // Field javaOuterClassname_:Ljava/lang/Object;
      17: aload_0
      18: iconst_1
      19: putfield      #12                 // Field optimizeFor_:I
      22: aload_0
      23: ldc           #9                  // String
      25: putfield      #13                 // Field goPackage_:Ljava/lang/Object;
      28: aload_0
      29: iconst_1
      30: putfield      #14                 // Field ccEnableArenas_:Z
      33: aload_0
      34: ldc           #9                  // String
      36: putfield      #15                 // Field objcClassPrefix_:Ljava/lang/Object;
      39: aload_0
      40: ldc           #9                  // String
      42: putfield      #16                 // Field csharpNamespace_:Ljava/lang/Object;
      45: aload_0
      46: ldc           #9                  // String
      48: putfield      #17                 // Field swiftPrefix_:Ljava/lang/Object;
      51: aload_0
      52: ldc           #9                  // String
      54: putfield      #18                 // Field phpClassPrefix_:Ljava/lang/Object;
      57: aload_0
      58: ldc           #9                  // String
      60: putfield      #19                 // Field phpNamespace_:Ljava/lang/Object;
      63: aload_0
      64: ldc           #9                  // String
      66: putfield      #20                 // Field phpMetadataNamespace_:Ljava/lang/Object;
      69: aload_0
      70: ldc           #9                  // String
      72: putfield      #21                 // Field rubyPackage_:Ljava/lang/Object;
      75: aload_0
      76: invokestatic  #22                 // Method java/util/Collections.emptyList:()Ljava/util/List;
      79: putfield      #23                 // Field uninterpretedOption_:Ljava/util/List;
      82: return

  public com.google.protobuf.DescriptorProtos$FileOptions$Builder clear();
    Code:
       0: aload_0
       1: invokespecial #25                 // Method com/google/protobuf/GeneratedMessageV3$ExtendableBuilder.clear:()Lcom/google/protobuf/GeneratedMessageV3$ExtendableBuilder;
       4: pop
       5: aload_0
       6: ldc           #9                  // String
       8: putfield      #10                 // Field javaPackage_:Ljava/lang/Object;
      11: aload_0
      12: aload_0
      13: getfield      #26                 // Field bitField0_:I
      16: bipush        -2
      18: iand
      19: putfield      #26                 // Field bitField0_:I
      22: aload_0
      23: ldc           #9                  // String
      25: putfield      #11                 // Field javaOuterClassname_:Ljava/lang/Object;
      28: aload_0
      29: aload_0
      30: getfield      #26                 // Field bitField0_:I
      33: bipush        -3
      35: iand
      36: putfield      #26                 // Field bitField0_:I
      39: aload_0
      40: iconst_0
      41: putfield      #27                 // Field javaMultipleFiles_:Z
      44: aload_0
      45: aload_0
      46: getfield      #26                 // Field bitField0_:I
      49: bipush        -5
      51: iand
      52: putfield      #26                 // Field bitField0_:I
      55: aload_0
      56: iconst_0
      57: putfield      #28                 // Field javaGenerateEqualsAndHash_:Z
      60: aload_0
      61: aload_0
      62: getfield      #26                 // Field bitField0_:I
      65: bipush        -9
      67: iand
      68: putfield      #26                 // Field bitField0_:I
      71: aload_0
      72: iconst_0
      73: putfield      #29                 // Field javaStringCheckUtf8_:Z
      76: aload_0
      77: aload_0
      78: getfield      #26                 // Field bitField0_:I
      81: bipush        -17
      83: iand
      84: putfield      #26                 // Field bitField0_:I
      87: aload_0
      88: iconst_1
      89: putfield      #12                 // Field optimizeFor_:I
      92: aload_0
      93: aload_0
      94: getfield      #26                 // Field bitField0_:I
      97: bipush        -33
      99: iand
     100: putfield      #26                 // Field bitField0_:I
     103: aload_0
     104: ldc           #9                  // String
     106: putfield      #13                 // Field goPackage_:Ljava/lang/Object;
     109: aload_0
     110: aload_0
     111: getfield      #26                 // Field bitField0_:I
     114: bipush        -65
     116: iand
     117: putfield      #26                 // Field bitField0_:I
     120: aload_0
     121: iconst_0
     122: putfield      #30                 // Field ccGenericServices_:Z
     125: aload_0
     126: aload_0
     127: getfield      #26                 // Field bitField0_:I
     130: sipush        -129
     133: iand
     134: putfield      #26                 // Field bitField0_:I
     137: aload_0
     138: iconst_0
     139: putfield      #31                 // Field javaGenericServices_:Z
     142: aload_0
     143: aload_0
     144: getfield      #26                 // Field bitField0_:I
     147: sipush        -257
     150: iand
     151: putfield      #26                 // Field bitField0_:I
     154: aload_0
     155: iconst_0
     156: putfield      #32                 // Field pyGenericServices_:Z
     159: aload_0
     160: aload_0
     161: getfield      #26                 // Field bitField0_:I
     164: sipush        -513
     167: iand
     168: putfield      #26                 // Field bitField0_:I
     171: aload_0
     172: iconst_0
     173: putfield      #33                 // Field phpGenericServices_:Z
     176: aload_0
     177: aload_0
     178: getfield      #26                 // Field bitField0_:I
     181: sipush        -1025
     184: iand
     185: putfield      #26                 // Field bitField0_:I
     188: aload_0
     189: iconst_0
     190: putfield      #34                 // Field deprecated_:Z
     193: aload_0
     194: aload_0
     195: getfield      #26                 // Field bitField0_:I
     198: sipush        -2049
     201: iand
     202: putfield      #26                 // Field bitField0_:I
     205: aload_0
     206: iconst_1
     207: putfield      #14                 // Field ccEnableArenas_:Z
     210: aload_0
     211: aload_0
     212: getfield      #26                 // Field bitField0_:I
     215: sipush        -4097
     218: iand
     219: putfield      #26                 // Field bitField0_:I
     222: aload_0
     223: ldc           #9                  // String
     225: putfield      #15                 // Field objcClassPrefix_:Ljava/lang/Object;
     228: aload_0
     229: aload_0
     230: getfield      #26                 // Field bitField0_:I
     233: sipush        -8193
     236: iand
     237: putfield      #26                 // Field bitField0_:I
     240: aload_0
     241: ldc           #9                  // String
     243: putfield      #16                 // Field csharpNamespace_:Ljava/lang/Object;
     246: aload_0
     247: aload_0
     248: getfield      #26                 // Field bitField0_:I
     251: sipush        -16385
     254: iand
     255: putfield      #26                 // Field bitField0_:I
     258: aload_0
     259: ldc           #9                  // String
     261: putfield      #17                 // Field swiftPrefix_:Ljava/lang/Object;
     264: aload_0
     265: aload_0
     266: getfield      #26                 // Field bitField0_:I
     269: ldc           #35                 // int -32769
     271: iand
     272: putfield      #26                 // Field bitField0_:I
     275: aload_0
     276: ldc           #9                  // String
     278: putfield      #18                 // Field phpClassPrefix_:Ljava/lang/Object;
     281: aload_0
     282: aload_0
     283: getfield      #26                 // Field bitField0_:I
     286: ldc           #36                 // int -65537
     288: iand
     289: putfield      #26                 // Field bitField0_:I
     292: aload_0
     293: ldc           #9                  // String
     295: putfield      #19                 // Field phpNamespace_:Ljava/lang/Object;
     298: aload_0
     299: aload_0
     300: getfield      #26                 // Field bitField0_:I
     303: ldc           #37                 // int -131073
     305: iand
     306: putfield      #26                 // Field bitField0_:I
     309: aload_0
     310: ldc           #9                  // String
     312: putfield      #20                 // Field phpMetadataNamespace_:Ljava/lang/Object;
     315: aload_0
     316: aload_0
     317: getfield      #26                 // Field bitField0_:I
     320: ldc           #38                 // int -262145
     322: iand
     323: putfield      #26                 // Field bitField0_:I
     326: aload_0
     327: ldc           #9                  // String
     329: putfield      #21                 // Field rubyPackage_:Ljava/lang/Object;
     332: aload_0
     333: aload_0
     334: getfield      #26                 // Field bitField0_:I
     337: ldc           #39                 // int -524289
     339: iand
     340: putfield      #26                 // Field bitField0_:I
     343: aload_0
     344: getfield      #40                 // Field uninterpretedOptionBuilder_:Lcom/google/protobuf/RepeatedFieldBuilderV3;
     347: ifnonnull     360
     350: aload_0
     351: invokestatic  #22                 // Method java/util/Collections.emptyList:()Ljava/util/List;
     354: putfield      #23                 // Field uninterpretedOption_:Ljava/util/List;
     357: goto          372
     360: aload_0
     361: aconst_null
     362: putfield      #23                 // Field uninterpretedOption_:Ljava/util/List;
     365: aload_0
     366: getfield      #40                 // Field uninterpretedOptionBuilder_:Lcom/google/protobuf/RepeatedFieldBuilderV3;
     369: invokevirtual #41                 // Method com/google/protobuf/RepeatedFieldBuilderV3.clear:()V
     372: aload_0
     373: aload_0
     374: getfield      #26                 // Field bitField0_:I
     377: ldc           #42                 // int -1048577
     379: iand
     380: putfield      #26                 // Field bitField0_:I
     383: aload_0
     384: areturn

  public com.google.protobuf.Descriptors$Descriptor getDescriptorForType();
    Code:
       0: invokestatic  #3                  // Method com/google/protobuf/DescriptorProtos.access$13700:()Lcom/google/protobuf/Descriptors$Descriptor;
       3: areturn

  public com.google.protobuf.DescriptorProtos$FileOptions getDefaultInstanceForType();
    Code:
       0: invokestatic  #43                 // Method com/google/protobuf/DescriptorProtos$FileOptions.getDefaultInstance:()Lcom/google/protobuf/DescriptorProtos$FileOptions;
       3: areturn

  public com.google.protobuf.DescriptorProtos$FileOptions build();
    Code:
       0: aload_0
       1: invokevirtual #44                 // Method buildPartial:()Lcom/google/protobuf/DescriptorProtos$FileOptions;
       4: astore_1
       5: aload_1
       6: invokevirtual #45                 // Method com/google/protobuf/DescriptorProtos$FileOptions.isInitialized:()Z
       9: ifne          17
      12: aload_1
      13: invokestatic  #46                 // Method newUninitializedMessageException:(Lcom/google/protobuf/Message;)Lcom/google/protobuf/UninitializedMessageException;
      16: athrow
      17: aload_1
      18: areturn

  public com.google.protobuf.DescriptorProtos$FileOptions buildPartial();
    Code:
       0: new           #5                  // class com/google/protobuf/DescriptorProtos$FileOptions
       3: dup
       4: aload_0
       5: aconst_null
       6: invokespecial #47                 // Method com/google/protobuf/DescriptorProtos$FileOptions."<init>":(Lcom/google/protobuf/GeneratedMessageV3$ExtendableBuilder;Lcom/google/protobuf/DescriptorProtos$1;)V
       9: astore_1
      10: aload_0
      11: getfield      #26                 // Field bitField0_:I
      14: istore_2
      15: iconst_0
      16: istore_3
      17: iload_2
      18: iconst_1
      19: iand
      20: ifeq          27
      23: iload_3
      24: iconst_1
      25: ior
      26: istore_3
      27: aload_1
      28: aload_0
      29: getfield      #10                 // Field javaPackage_:Ljava/lang/Object;
      32: invokestatic  #48                 // Method com/google/protobuf/DescriptorProtos$FileOptions.access$14202:(Lcom/google/protobuf/DescriptorProtos$FileOptions;Ljava/lang/Object;)Ljava/lang/Object;
      35: pop
      36: iload_2
      37: iconst_2
      38: iand
      39: ifeq          46
      42: iload_3
      43: iconst_2
      44: ior
      45: istore_3
      46: aload_1
      47: aload_0
      48: getfield      #11                 // Field javaOuterClassname_:Ljava/lang/Object;
      51: invokestatic  #49                 // Method com/google/protobuf/DescriptorProtos$FileOptions.access$14302:(Lcom/google/protobuf/DescriptorProtos$FileOptions;Ljava/lang/Object;)Ljava/lang/Object;
      54: pop
      55: iload_2
      56: iconst_4
      57: iand
      58: ifeq          74
      61: aload_1
      62: aload_0
      63: getfield      #27                 // Field javaMultipleFiles_:Z
      66: invokestatic  #50                 // Method com/google/protobuf/DescriptorProtos$FileOptions.access$14402:(Lcom/google/protobuf/DescriptorProtos$FileOptions;Z)Z
      69: pop
      70: iload_3
      71: iconst_4
      72: ior
      73: istore_3
      74: iload_2
      75: bipush        8
      77: iand
      78: ifeq          95
      81: aload_1
      82: aload_0
      83: getfield      #28                 // Field javaGenerateEqualsAndHash_:Z
      86: invokestatic  #51                 // Method com/google/protobuf/DescriptorProtos$FileOptions.access$14502:(Lcom/google/protobuf/DescriptorProtos$FileOptions;Z)Z
      89: pop
      90: iload_3
      91: bipush        8
      93: ior
      94: istore_3
      95: iload_2
      96: bipush        16
      98: iand
      99: ifeq          116
     102: aload_1
     103: aload_0
     104: getfield      #29                 // Field javaStringCheckUtf8_:Z
     107: invokestatic  #52                 // Method com/google/protobuf/DescriptorProtos$FileOptions.access$14602:(Lcom/google/protobuf/DescriptorProtos$FileOptions;Z)Z
     110: pop
     111: iload_3
     112: bipush        16
     114: ior
     115: istore_3
     116: iload_2
     117: bipush        32
     119: iand
     120: ifeq          128
     123: iload_3
     124: bipush        32
     126: ior
     127: istore_3
     128: aload_1
     129: aload_0
     130: getfield      #12                 // Field optimizeFor_:I
     133: invokestatic  #53                 // Method com/google/protobuf/DescriptorProtos$FileOptions.access$14702:(Lcom/google/protobuf/DescriptorProtos$FileOptions;I)I
     136: pop
     137: iload_2
     138: bipush        64
     140: iand
     141: ifeq          149
     144: iload_3
     145: bipush        64
     147: ior
     148: istore_3
     149: aload_1
     150: aload_0
     151: getfield      #13                 // Field goPackage_:Ljava/lang/Object;
     154: invokestatic  #54                 // Method com/google/protobuf/DescriptorProtos$FileOptions.access$14802:(Lcom/google/protobuf/DescriptorProtos$FileOptions;Ljava/lang/Object;)Ljava/lang/Object;
     157: pop
     158: iload_2
     159: sipush        128
     162: iand
     163: ifeq          181
     166: aload_1
     167: aload_0
     168: getfield      #30                 // Field ccGenericServices_:Z
     171: invokestatic  #55                 // Method com/google/protobuf/DescriptorProtos$FileOptions.access$14902:(Lcom/google/protobuf/DescriptorProtos$FileOptions;Z)Z
     174: pop
     175: iload_3
     176: sipush        128
     179: ior
     180: istore_3
     181: iload_2
     182: sipush        256
     185: iand
     186: ifeq          204
     189: aload_1
     190: aload_0
     191: getfield      #31                 // Field javaGenericServices_:Z
     194: invokestatic  #56                 // Method com/google/protobuf/DescriptorProtos$FileOptions.access$15002:(Lcom/google/protobuf/DescriptorProtos$FileOptions;Z)Z
     197: pop
     198: iload_3
     199: sipush        256
     202: ior
     203: istore_3
     204: iload_2
     205: sipush        512
     208: iand
     209: ifeq          227
     212: aload_1
     213: aload_0
     214: getfield      #32                 // Field pyGenericServices_:Z
     217: invokestatic  #57                 // Method com/google/protobuf/DescriptorProtos$FileOptions.access$15102:(Lcom/google/protobuf/DescriptorProtos$FileOptions;Z)Z
     220: pop
     221: iload_3
     222: sipush        512
     225: ior
     226: istore_3
     227: iload_2
     228: sipush        1024
     231: iand
     232: ifeq          250
     235: aload_1
     236: aload_0
     237: getfield      #33                 // Field phpGenericServices_:Z
     240: invokestatic  #58                 // Method com/google/protobuf/DescriptorProtos$FileOptions.access$15202:(Lcom/google/protobuf/DescriptorProtos$FileOptions;Z)Z
     243: pop
     244: iload_3
     245: sipush        1024
     248: ior
     249: istore_3
     250: iload_2
     251: sipush        2048
     254: iand
     255: ifeq          273
     258: aload_1
     259: aload_0
     260: getfield      #34                 // Field deprecated_:Z
     263: invokestatic  #59                 // Method com/google/protobuf/DescriptorProtos$FileOptions.access$15302:(Lcom/google/protobuf/DescriptorProtos$FileOptions;Z)Z
     266: pop
     267: iload_3
     268: sipush        2048
     271: ior
     272: istore_3
     273: iload_2
     274: sipush        4096
     277: iand
     278: ifeq          287
     281: iload_3
     282: sipush        4096
     285: ior
     286: istore_3
     287: aload_1
     288: aload_0
     289: getfield      #14                 // Field ccEnableArenas_:Z
     292: invokestatic  #60                 // Method com/google/protobuf/DescriptorProtos$FileOptions.access$15402:(Lcom/google/protobuf/DescriptorProtos$FileOptions;Z)Z
     295: pop
     296: iload_2
     297: sipush        8192
     300: iand
     301: ifeq          310
     304: iload_3
     305: sipush        8192
     308: ior
     309: istore_3
     310: aload_1
     311: aload_0
     312: getfield      #15                 // Field objcClassPrefix_:Ljava/lang/Object;
     315: invokestatic  #61                 // Method com/google/protobuf/DescriptorProtos$FileOptions.access$15502:(Lcom/google/protobuf/DescriptorProtos$FileOptions;Ljava/lang/Object;)Ljava/lang/Object;
     318: pop
     319: iload_2
     320: sipush        16384
     323: iand
     324: ifeq          333
     327: iload_3
     328: sipush        16384
     331: ior
     332: istore_3
     333: aload_1
     334: aload_0
     335: getfield      #16                 // Field csharpNamespace_:Ljava/lang/Object;
     338: invokestatic  #62                 // Method com/google/protobuf/DescriptorProtos$FileOptions.access$15602:(Lcom/google/protobuf/DescriptorProtos$FileOptions;Ljava/lang/Object;)Ljava/lang/Object;
     341: pop
     342: iload_2
     343: ldc           #63                 // int 32768
     345: iand
     346: ifeq          354
     349: iload_3
     350: ldc           #63                 // int 32768
     352: ior
     353: istore_3
     354: aload_1
     355: aload_0
     356: getfield      #17                 // Field swiftPrefix_:Ljava/lang/Object;
     359: invokestatic  #64                 // Method com/google/protobuf/DescriptorProtos$FileOptions.access$15702:(Lcom/google/protobuf/DescriptorProtos$FileOptions;Ljava/lang/Object;)Ljava/lang/Object;
     362: pop
     363: iload_2
     364: ldc           #65                 // int 65536
     366: iand
     367: ifeq          375
     370: iload_3
     371: ldc           #65                 // int 65536
     373: ior
     374: istore_3
     375: aload_1
     376: aload_0
     377: getfield      #18                 // Field phpClassPrefix_:Ljava/lang/Object;
     380: invokestatic  #66                 // Method com/google/protobuf/DescriptorProtos$FileOptions.access$15802:(Lcom/google/protobuf/DescriptorProtos$FileOptions;Ljava/lang/Object;)Ljava/lang/Object;
     383: pop
     384: iload_2
     385: ldc           #67                 // int 131072
     387: iand
     388: ifeq          396
     391: iload_3
     392: ldc           #67                 // int 131072
     394: ior
     395: istore_3
     396: aload_1
     397: aload_0
     398: getfield      #19                 // Field phpNamespace_:Ljava/lang/Object;
     401: invokestatic  #68                 // Method com/google/protobuf/DescriptorProtos$FileOptions.access$15902:(Lcom/google/protobuf/DescriptorProtos$FileOptions;Ljava/lang/Object;)Ljava/lang/Object;
     404: pop
     405: iload_2
     406: ldc           #69                 // int 262144
     408: iand
     409: ifeq          417
     412: iload_3
     413: ldc           #69                 // int 262144
     415: ior
     416: istore_3
     417: aload_1
     418: aload_0
     419: getfield      #20                 // Field phpMetadataNamespace_:Ljava/lang/Object;
     422: invokestatic  #70                 // Method com/google/protobuf/DescriptorProtos$FileOptions.access$16002:(Lcom/google/protobuf/DescriptorProtos$FileOptions;Ljava/lang/Object;)Ljava/lang/Object;
     425: pop
     426: iload_2
     427: ldc           #71                 // int 524288
     429: iand
     430: ifeq          438
     433: iload_3
     434: ldc           #71                 // int 524288
     436: ior
     437: istore_3
     438: aload_1
     439: aload_0
     440: getfield      #21                 // Field rubyPackage_:Ljava/lang/Object;
     443: invokestatic  #72                 // Method com/google/protobuf/DescriptorProtos$FileOptions.access$16102:(Lcom/google/protobuf/DescriptorProtos$FileOptions;Ljava/lang/Object;)Ljava/lang/Object;
     446: pop
     447: aload_0
     448: getfield      #40                 // Field uninterpretedOptionBuilder_:Lcom/google/protobuf/RepeatedFieldBuilderV3;
     451: ifnonnull     498
     454: aload_0
     455: getfield      #26                 // Field bitField0_:I
     458: ldc           #73                 // int 1048576
     460: iand
     461: ifeq          486
     464: aload_0
     465: aload_0
     466: getfield      #23                 // Field uninterpretedOption_:Ljava/util/List;
     469: invokestatic  #74                 // Method java/util/Collections.unmodifiableList:(Ljava/util/List;)Ljava/util/List;
     472: putfield      #23                 // Field uninterpretedOption_:Ljava/util/List;
     475: aload_0
     476: aload_0
     477: getfield      #26                 // Field bitField0_:I
     480: ldc           #42                 // int -1048577
     482: iand
     483: putfield      #26                 // Field bitField0_:I
     486: aload_1
     487: aload_0
     488: getfield      #23                 // Field uninterpretedOption_:Ljava/util/List;
     491: invokestatic  #75                 // Method com/google/protobuf/DescriptorProtos$FileOptions.access$16202:(Lcom/google/protobuf/DescriptorProtos$FileOptions;Ljava/util/List;)Ljava/util/List;
     494: pop
     495: goto          510
     498: aload_1
     499: aload_0
     500: getfield      #40                 // Field uninterpretedOptionBuilder_:Lcom/google/protobuf/RepeatedFieldBuilderV3;
     503: invokevirtual #76                 // Method com/google/protobuf/RepeatedFieldBuilderV3.build:()Ljava/util/List;
     506: invokestatic  #75                 // Method com/google/protobuf/DescriptorProtos$FileOptions.access$16202:(Lcom/google/protobuf/DescriptorProtos$FileOptions;Ljava/util/List;)Ljava/util/List;
     509: pop
     510: aload_1
     511: iload_3
     512: invokestatic  #77                 // Method com/google/protobuf/DescriptorProtos$FileOptions.access$16302:(Lcom/google/protobuf/DescriptorProtos$FileOptions;I)I
     515: pop
     516: aload_0
     517: invokevirtual #78                 // Method onBuilt:()V
     520: aload_1
     521: areturn

  public com.google.protobuf.DescriptorProtos$FileOptions$Builder clone();
    Code:
       0: aload_0
       1: invokespecial #79                 // Method com/google/protobuf/GeneratedMessageV3$ExtendableBuilder.clone:()Lcom/google/protobuf/GeneratedMessageV3$Builder;
       4: checkcast     #6                  // class com/google/protobuf/DescriptorProtos$FileOptions$Builder
       7: areturn

  public com.google.protobuf.DescriptorProtos$FileOptions$Builder setField(com.google.protobuf.Descriptors$FieldDescriptor, java.lang.Object);
    Code:
       0: aload_0
       1: aload_1
       2: aload_2
       3: invokespecial #80                 // Method com/google/protobuf/GeneratedMessageV3$ExtendableBuilder.setField:(Lcom/google/protobuf/Descriptors$FieldDescriptor;Ljava/lang/Object;)Lcom/google/protobuf/GeneratedMessageV3$ExtendableBuilder;
       6: checkcast     #6                  // class com/google/protobuf/DescriptorProtos$FileOptions$Builder
       9: areturn

  public com.google.protobuf.DescriptorProtos$FileOptions$Builder clearField(com.google.protobuf.Descriptors$FieldDescriptor);
    Code:
       0: aload_0
       1: aload_1
       2: invokespecial #81                 // Method com/google/protobuf/GeneratedMessageV3$ExtendableBuilder.clearField:(Lcom/google/protobuf/Descriptors$FieldDescriptor;)Lcom/google/protobuf/GeneratedMessageV3$ExtendableBuilder;
       5: checkcast     #6                  // class com/google/protobuf/DescriptorProtos$FileOptions$Builder
       8: areturn

  public com.google.protobuf.DescriptorProtos$FileOptions$Builder clearOneof(com.google.protobuf.Descriptors$OneofDescriptor);
    Code:
       0: aload_0
       1: aload_1
       2: invokespecial #82                 // Method com/google/protobuf/GeneratedMessageV3$ExtendableBuilder.clearOneof:(Lcom/google/protobuf/Descriptors$OneofDescriptor;)Lcom/google/protobuf/GeneratedMessageV3$Builder;
       5: checkcast     #6                  // class com/google/protobuf/DescriptorProtos$FileOptions$Builder
       8: areturn

  public com.google.protobuf.DescriptorProtos$FileOptions$Builder setRepeatedField(com.google.protobuf.Descriptors$FieldDescriptor, int, java.lang.Object);
    Code:
       0: aload_0
       1: aload_1
       2: iload_2
       3: aload_3
       4: invokespecial #83                 // Method com/google/protobuf/GeneratedMessageV3$ExtendableBuilder.setRepeatedField:(Lcom/google/protobuf/Descriptors$FieldDescriptor;ILjava/lang/Object;)Lcom/google/protobuf/GeneratedMessageV3$ExtendableBuilder;
       7: checkcast     #6                  // class com/google/protobuf/DescriptorProtos$FileOptions$Builder
      10: areturn

  public com.google.protobuf.DescriptorProtos$FileOptions$Builder addRepeatedField(com.google.protobuf.Descriptors$FieldDescriptor, java.lang.Object);
    Code:
       0: aload_0
       1: aload_1
       2: aload_2
       3: invokespecial #84                 // Method com/google/protobuf/GeneratedMessageV3$ExtendableBuilder.addRepeatedField:(Lcom/google/protobuf/Descriptors$FieldDescriptor;Ljava/lang/Object;)Lcom/google/protobuf/GeneratedMessageV3$ExtendableBuilder;
       6: checkcast     #6                  // class com/google/protobuf/DescriptorProtos$FileOptions$Builder
       9: areturn

  public <Type> com.google.protobuf.DescriptorProtos$FileOptions$Builder setExtension(com.google.protobuf.GeneratedMessage$GeneratedExtension<com.google.protobuf.DescriptorProtos$FileOptions, Type>, Type);
    Code:
       0: aload_0
       1: aload_1
       2: aload_2
       3: invokespecial #85                 // Method com/google/protobuf/GeneratedMessageV3$ExtendableBuilder.setExtension:(Lcom/google/protobuf/GeneratedMessage$GeneratedExtension;Ljava/lang/Object;)Lcom/google/protobuf/GeneratedMessageV3$ExtendableBuilder;
       6: checkcast     #6                  // class com/google/protobuf/DescriptorProtos$FileOptions$Builder
       9: areturn

  public <Type> com.google.protobuf.DescriptorProtos$FileOptions$Builder setExtension(com.google.protobuf.GeneratedMessage$GeneratedExtension<com.google.protobuf.DescriptorProtos$FileOptions, java.util.List<Type>>, int, Type);
    Code:
       0: aload_0
       1: aload_1
       2: iload_2
       3: aload_3
       4: invokespecial #86                 // Method com/google/protobuf/GeneratedMessageV3$ExtendableBuilder.setExtension:(Lcom/google/protobuf/GeneratedMessage$GeneratedExtension;ILjava/lang/Object;)Lcom/google/protobuf/GeneratedMessageV3$ExtendableBuilder;
       7: checkcast     #6                  // class com/google/protobuf/DescriptorProtos$FileOptions$Builder
      10: areturn

  public <Type> com.google.protobuf.DescriptorProtos$FileOptions$Builder addExtension(com.google.protobuf.GeneratedMessage$GeneratedExtension<com.google.protobuf.DescriptorProtos$FileOptions, java.util.List<Type>>, Type);
    Code:
       0: aload_0
       1: aload_1
       2: aload_2
       3: invokespecial #87                 // Method com/google/protobuf/GeneratedMessageV3$ExtendableBuilder.addExtension:(Lcom/google/protobuf/GeneratedMessage$GeneratedExtension;Ljava/lang/Object;)Lcom/google/protobuf/GeneratedMessageV3$ExtendableBuilder;
       6: checkcast     #6                  // class com/google/protobuf/DescriptorProtos$FileOptions$Builder
       9: areturn

  public <Type> com.google.protobuf.DescriptorProtos$FileOptions$Builder clearExtension(com.google.protobuf.GeneratedMessage$GeneratedExtension<com.google.protobuf.DescriptorProtos$FileOptions, ?>);
    Code:
       0: aload_0
       1: aload_1
       2: invokespecial #88                 // Method com/google/protobuf/GeneratedMessageV3$ExtendableBuilder.clearExtension:(Lcom/google/protobuf/GeneratedMessage$GeneratedExtension;)Lcom/google/protobuf/GeneratedMessageV3$ExtendableBuilder;
       5: checkcast     #6                  // class com/google/protobuf/DescriptorProtos$FileOptions$Builder
       8: areturn

  public com.google.protobuf.DescriptorProtos$FileOptions$Builder mergeFrom(com.google.protobuf.Message);
    Code:
       0: aload_1
       1: instanceof    #5                  // class com/google/protobuf/DescriptorProtos$FileOptions
       4: ifeq          16
       7: aload_0
       8: aload_1
       9: checkcast     #5                  // class com/google/protobuf/DescriptorProtos$FileOptions
      12: invokevirtual #89                 // Method mergeFrom:(Lcom/google/protobuf/DescriptorProtos$FileOptions;)Lcom/google/protobuf/DescriptorProtos$FileOptions$Builder;
      15: areturn
      16: aload_0
      17: aload_1
      18: invokespecial #90                 // Method com/google/protobuf/GeneratedMessageV3$ExtendableBuilder.mergeFrom:(Lcom/google/protobuf/Message;)Lcom/google/protobuf/AbstractMessage$Builder;
      21: pop
      22: aload_0
      23: areturn

  public com.google.protobuf.DescriptorProtos$FileOptions$Builder mergeFrom(com.google.protobuf.DescriptorProtos$FileOptions);
    Code:
       0: aload_1
       1: invokestatic  #43                 // Method com/google/protobuf/DescriptorProtos$FileOptions.getDefaultInstance:()Lcom/google/protobuf/DescriptorProtos$FileOptions;
       4: if_acmpne     9
       7: aload_0
       8: areturn
       9: aload_1
      10: invokevirtual #91                 // Method com/google/protobuf/DescriptorProtos$FileOptions.hasJavaPackage:()Z
      13: ifeq          38
      16: aload_0
      17: dup
      18: getfield      #26                 // Field bitField0_:I
      21: iconst_1
      22: ior
      23: putfield      #26                 // Field bitField0_:I
      26: aload_0
      27: aload_1
      28: invokestatic  #92                 // Method com/google/protobuf/DescriptorProtos$FileOptions.access$14200:(Lcom/google/protobuf/DescriptorProtos$FileOptions;)Ljava/lang/Object;
      31: putfield      #10                 // Field javaPackage_:Ljava/lang/Object;
      34: aload_0
      35: invokevirtual #93                 // Method onChanged:()V
      38: aload_1
      39: invokevirtual #94                 // Method com/google/protobuf/DescriptorProtos$FileOptions.hasJavaOuterClassname:()Z
      42: ifeq          67
      45: aload_0
      46: dup
      47: getfield      #26                 // Field bitField0_:I
      50: iconst_2
      51: ior
      52: putfield      #26                 // Field bitField0_:I
      55: aload_0
      56: aload_1
      57: invokestatic  #95                 // Method com/google/protobuf/DescriptorProtos$FileOptions.access$14300:(Lcom/google/protobuf/DescriptorProtos$FileOptions;)Ljava/lang/Object;
      60: putfield      #11                 // Field javaOuterClassname_:Ljava/lang/Object;
      63: aload_0
      64: invokevirtual #93                 // Method onChanged:()V
      67: aload_1
      68: invokevirtual #96                 // Method com/google/protobuf/DescriptorProtos$FileOptions.hasJavaMultipleFiles:()Z
      71: ifeq          83
      74: aload_0
      75: aload_1
      76: invokevirtual #97                 // Method com/google/protobuf/DescriptorProtos$FileOptions.getJavaMultipleFiles:()Z
      79: invokevirtual #98                 // Method setJavaMultipleFiles:(Z)Lcom/google/protobuf/DescriptorProtos$FileOptions$Builder;
      82: pop
      83: aload_1
      84: invokevirtual #99                 // Method com/google/protobuf/DescriptorProtos$FileOptions.hasJavaGenerateEqualsAndHash:()Z
      87: ifeq          99
      90: aload_0
      91: aload_1
      92: invokevirtual #100                // Method com/google/protobuf/DescriptorProtos$FileOptions.getJavaGenerateEqualsAndHash:()Z
      95: invokevirtual #101                // Method setJavaGenerateEqualsAndHash:(Z)Lcom/google/protobuf/DescriptorProtos$FileOptions$Builder;
      98: pop
      99: aload_1
     100: invokevirtual #102                // Method com/google/protobuf/DescriptorProtos$FileOptions.hasJavaStringCheckUtf8:()Z
     103: ifeq          115
     106: aload_0
     107: aload_1
     108: invokevirtual #103                // Method com/google/protobuf/DescriptorProtos$FileOptions.getJavaStringCheckUtf8:()Z
     111: invokevirtual #104                // Method setJavaStringCheckUtf8:(Z)Lcom/google/protobuf/DescriptorProtos$FileOptions$Builder;
     114: pop
     115: aload_1
     116: invokevirtual #105                // Method com/google/protobuf/DescriptorProtos$FileOptions.hasOptimizeFor:()Z
     119: ifeq          131
     122: aload_0
     123: aload_1
     124: invokevirtual #106                // Method com/google/protobuf/DescriptorProtos$FileOptions.getOptimizeFor:()Lcom/google/protobuf/DescriptorProtos$FileOptions$OptimizeMode;
     127: invokevirtual #107                // Method setOptimizeFor:(Lcom/google/protobuf/DescriptorProtos$FileOptions$OptimizeMode;)Lcom/google/protobuf/DescriptorProtos$FileOptions$Builder;
     130: pop
     131: aload_1
     132: invokevirtual #108                // Method com/google/protobuf/DescriptorProtos$FileOptions.hasGoPackage:()Z
     135: ifeq          161
     138: aload_0
     139: dup
     140: getfield      #26                 // Field bitField0_:I
     143: bipush        64
     145: ior
     146: putfield      #26                 // Field bitField0_:I
     149: aload_0
     150: aload_1
     151: invokestatic  #109                // Method com/google/protobuf/DescriptorProtos$FileOptions.access$14800:(Lcom/google/protobuf/DescriptorProtos$FileOptions;)Ljava/lang/Object;
     154: putfield      #13                 // Field goPackage_:Ljava/lang/Object;
     157: aload_0
     158: invokevirtual #93                 // Method onChanged:()V
     161: aload_1
     162: invokevirtual #110                // Method com/google/protobuf/DescriptorProtos$FileOptions.hasCcGenericServices:()Z
     165: ifeq          177
     168: aload_0
     169: aload_1
     170: invokevirtual #111                // Method com/google/protobuf/DescriptorProtos$FileOptions.getCcGenericServices:()Z
     173: invokevirtual #112                // Method setCcGenericServices:(Z)Lcom/google/protobuf/DescriptorProtos$FileOptions$Builder;
     176: pop
     177: aload_1
     178: invokevirtual #113                // Method com/google/protobuf/DescriptorProtos$FileOptions.hasJavaGenericServices:()Z
     181: ifeq          193
     184: aload_0
     185: aload_1
     186: invokevirtual #114                // Method com/google/protobuf/DescriptorProtos$FileOptions.getJavaGenericServices:()Z
     189: invokevirtual #115                // Method setJavaGenericServices:(Z)Lcom/google/protobuf/DescriptorProtos$FileOptions$Builder;
     192: pop
     193: aload_1
     194: invokevirtual #116                // Method com/google/protobuf/DescriptorProtos$FileOptions.hasPyGenericServices:()Z
     197: ifeq          209
     200: aload_0
     201: aload_1
     202: invokevirtual #117                // Method com/google/protobuf/DescriptorProtos$FileOptions.getPyGenericServices:()Z
     205: invokevirtual #118                // Method setPyGenericServices:(Z)Lcom/google/protobuf/DescriptorProtos$FileOptions$Builder;
     208: pop
     209: aload_1
     210: invokevirtual #119                // Method com/google/protobuf/DescriptorProtos$FileOptions.hasPhpGenericServices:()Z
     213: ifeq          225
     216: aload_0
     217: aload_1
     218: invokevirtual #120                // Method com/google/protobuf/DescriptorProtos$FileOptions.getPhpGenericServices:()Z
     221: invokevirtual #121                // Method setPhpGenericServices:(Z)Lcom/google/protobuf/DescriptorProtos$FileOptions$Builder;
     224: pop
     225: aload_1
     226: invokevirtual #122                // Method com/google/protobuf/DescriptorProtos$FileOptions.hasDeprecated:()Z
     229: ifeq          241
     232: aload_0
     233: aload_1
     234: invokevirtual #123                // Method com/google/protobuf/DescriptorProtos$FileOptions.getDeprecated:()Z
     237: invokevirtual #124                // Method setDeprecated:(Z)Lcom/google/protobuf/DescriptorProtos$FileOptions$Builder;
     240: pop
     241: aload_1
     242: invokevirtual #125                // Method com/google/protobuf/DescriptorProtos$FileOptions.hasCcEnableArenas:()Z
     245: ifeq          257
     248: aload_0
     249: aload_1
     250: invokevirtual #126                // Method com/google/protobuf/DescriptorProtos$FileOptions.getCcEnableArenas:()Z
     253: invokevirtual #127                // Method setCcEnableArenas:(Z)Lcom/google/protobuf/DescriptorProtos$FileOptions$Builder;
     256: pop
     257: aload_1
     258: invokevirtual #128                // Method com/google/protobuf/DescriptorProtos$FileOptions.hasObjcClassPrefix:()Z
     261: ifeq          288
     264: aload_0
     265: dup
     266: getfield      #26                 // Field bitField0_:I
     269: sipush        8192
     272: ior
     273: putfield      #26                 // Field bitField0_:I
     276: aload_0
     277: aload_1
     278: invokestatic  #129                // Method com/google/protobuf/DescriptorProtos$FileOptions.access$15500:(Lcom/google/protobuf/DescriptorProtos$FileOptions;)Ljava/lang/Object;
     281: putfield      #15                 // Field objcClassPrefix_:Ljava/lang/Object;
     284: aload_0
     285: invokevirtual #93                 // Method onChanged:()V
     288: aload_1
     289: invokevirtual #130                // Method com/google/protobuf/DescriptorProtos$FileOptions.hasCsharpNamespace:()Z
     292: ifeq          319
     295: aload_0
     296: dup
     297: getfield      #26                 // Field bitField0_:I
     300: sipush        16384
     303: ior
     304: putfield      #26                 // Field bitField0_:I
     307: aload_0
     308: aload_1
     309: invokestatic  #131                // Method com/google/protobuf/DescriptorProtos$FileOptions.access$15600:(Lcom/google/protobuf/DescriptorProtos$FileOptions;)Ljava/lang/Object;
     312: putfield      #16                 // Field csharpNamespace_:Ljava/lang/Object;
     315: aload_0
     316: invokevirtual #93                 // Method onChanged:()V
     319: aload_1
     320: invokevirtual #132                // Method com/google/protobuf/DescriptorProtos$FileOptions.hasSwiftPrefix:()Z
     323: ifeq          349
     326: aload_0
     327: dup
     328: getfield      #26                 // Field bitField0_:I
     331: ldc           #63                 // int 32768
     333: ior
     334: putfield      #26                 // Field bitField0_:I
     337: aload_0
     338: aload_1
     339: invokestatic  #133                // Method com/google/protobuf/DescriptorProtos$FileOptions.access$15700:(Lcom/google/protobuf/DescriptorProtos$FileOptions;)Ljava/lang/Object;
     342: putfield      #17                 // Field swiftPrefix_:Ljava/lang/Object;
     345: aload_0
     346: invokevirtual #93                 // Method onChanged:()V
     349: aload_1
     350: invokevirtual #134                // Method com/google/protobuf/DescriptorProtos$FileOptions.hasPhpClassPrefix:()Z
     353: ifeq          379
     356: aload_0
     357: dup
     358: getfield      #26                 // Field bitField0_:I
     361: ldc           #65                 // int 65536
     363: ior
     364: putfield      #26                 // Field bitField0_:I
     367: aload_0
     368: aload_1
     369: invokestatic  #135                // Method com/google/protobuf/DescriptorProtos$FileOptions.access$15800:(Lcom/google/protobuf/DescriptorProtos$FileOptions;)Ljava/lang/Object;
     372: putfield      #18                 // Field phpClassPrefix_:Ljava/lang/Object;
     375: aload_0
     376: invokevirtual #93                 // Method onChanged:()V
     379: aload_1
     380: invokevirtual #136                // Method com/google/protobuf/DescriptorProtos$FileOptions.hasPhpNamespace:()Z
     383: ifeq          409
     386: aload_0
     387: dup
     388: getfield      #26                 // Field bitField0_:I
     391: ldc           #67                 // int 131072
     393: ior
     394: putfield      #26                 // Field bitField0_:I
     397: aload_0
     398: aload_1
     399: invokestatic  #137                // Method com/google/protobuf/DescriptorProtos$FileOptions.access$15900:(Lcom/google/protobuf/DescriptorProtos$FileOptions;)Ljava/lang/Object;
     402: putfield      #19                 // Field phpNamespace_:Ljava/lang/Object;
     405: aload_0
     406: invokevirtual #93                 // Method onChanged:()V
     409: aload_1
     410: invokevirtual #138                // Method com/google/protobuf/DescriptorProtos$FileOptions.hasPhpMetadataNamespace:()Z
     413: ifeq          439
     416: aload_0
     417: dup
     418: getfield      #26                 // Field bitField0_:I
     421: ldc           #69                 // int 262144
     423: ior
     424: putfield      #26                 // Field bitField0_:I
     427: aload_0
     428: aload_1
     429: invokestatic  #139                // Method com/google/protobuf/DescriptorProtos$FileOptions.access$16000:(Lcom/google/protobuf/DescriptorProtos$FileOptions;)Ljava/lang/Object;
     432: putfield      #20                 // Field phpMetadataNamespace_:Ljava/lang/Object;
     435: aload_0
     436: invokevirtual #93                 // Method onChanged:()V
     439: aload_1
     440: invokevirtual #140                // Method com/google/protobuf/DescriptorProtos$FileOptions.hasRubyPackage:()Z
     443: ifeq          469
     446: aload_0
     447: dup
     448: getfield      #26                 // Field bitField0_:I
     451: ldc           #71                 // int 524288
     453: ior
     454: putfield      #26                 // Field bitField0_:I
     457: aload_0
     458: aload_1
     459: invokestatic  #141                // Method com/google/protobuf/DescriptorProtos$FileOptions.access$16100:(Lcom/google/protobuf/DescriptorProtos$FileOptions;)Ljava/lang/Object;
     462: putfield      #21                 // Field rubyPackage_:Ljava/lang/Object;
     465: aload_0
     466: invokevirtual #93                 // Method onChanged:()V
     469: aload_0
     470: getfield      #40                 // Field uninterpretedOptionBuilder_:Lcom/google/protobuf/RepeatedFieldBuilderV3;
     473: ifnonnull     547
     476: aload_1
     477: invokestatic  #142                // Method com/google/protobuf/DescriptorProtos$FileOptions.access$16200:(Lcom/google/protobuf/DescriptorProtos$FileOptions;)Ljava/util/List;
     480: invokeinterface #143,  1          // InterfaceMethod java/util/List.isEmpty:()Z
     485: ifne          633
     488: aload_0
     489: getfield      #23                 // Field uninterpretedOption_:Ljava/util/List;
     492: invokeinterface #143,  1          // InterfaceMethod java/util/List.isEmpty:()Z
     497: ifeq          522
     500: aload_0
     501: aload_1
     502: invokestatic  #142                // Method com/google/protobuf/DescriptorProtos$FileOptions.access$16200:(Lcom/google/protobuf/DescriptorProtos$FileOptions;)Ljava/util/List;
     505: putfield      #23                 // Field uninterpretedOption_:Ljava/util/List;
     508: aload_0
     509: aload_0
     510: getfield      #26                 // Field bitField0_:I
     513: ldc           #42                 // int -1048577
     515: iand
     516: putfield      #26                 // Field bitField0_:I
     519: goto          540
     522: aload_0
     523: invokespecial #144                // Method ensureUninterpretedOptionIsMutable:()V
     526: aload_0
     527: getfield      #23                 // Field uninterpretedOption_:Ljava/util/List;
     530: aload_1
     531: invokestatic  #142                // Method com/google/protobuf/DescriptorProtos$FileOptions.access$16200:(Lcom/google/protobuf/DescriptorProtos$FileOptions;)Ljava/util/List;
     534: invokeinterface #145,  2          // InterfaceMethod java/util/List.addAll:(Ljava/util/Collection;)Z
     539: pop
     540: aload_0
     541: invokevirtual #93                 // Method onChanged:()V
     544: goto          633
     547: aload_1
     548: invokestatic  #142                // Method com/google/protobuf/DescriptorProtos$FileOptions.access$16200:(Lcom/google/protobuf/DescriptorProtos$FileOptions;)Ljava/util/List;
     551: invokeinterface #143,  1          // InterfaceMethod java/util/List.isEmpty:()Z
     556: ifne          633
     559: aload_0
     560: getfield      #40                 // Field uninterpretedOptionBuilder_:Lcom/google/protobuf/RepeatedFieldBuilderV3;
     563: invokevirtual #146                // Method com/google/protobuf/RepeatedFieldBuilderV3.isEmpty:()Z
     566: ifeq          621
     569: aload_0
     570: getfield      #40                 // Field uninterpretedOptionBuilder_:Lcom/google/protobuf/RepeatedFieldBuilderV3;
     573: invokevirtual #147                // Method com/google/protobuf/RepeatedFieldBuilderV3.dispose:()V
     576: aload_0
     577: aconst_null
     578: putfield      #40                 // Field uninterpretedOptionBuilder_:Lcom/google/protobuf/RepeatedFieldBuilderV3;
     581: aload_0
     582: aload_1
     583: invokestatic  #142                // Method com/google/protobuf/DescriptorProtos$FileOptions.access$16200:(Lcom/google/protobuf/DescriptorProtos$FileOptions;)Ljava/util/List;
     586: putfield      #23                 // Field uninterpretedOption_:Ljava/util/List;
     589: aload_0
     590: aload_0
     591: getfield      #26                 // Field bitField0_:I
     594: ldc           #42                 // int -1048577
     596: iand
     597: putfield      #26                 // Field bitField0_:I
     600: aload_0
     601: getstatic     #148                // Field com/google/protobuf/GeneratedMessageV3.alwaysUseFieldBuilders:Z
     604: ifeq          614
     607: aload_0
     608: invokespecial #149                // Method getUninterpretedOptionFieldBuilder:()Lcom/google/protobuf/RepeatedFieldBuilderV3;
     611: goto          615
     614: aconst_null
     615: putfield      #40                 // Field uninterpretedOptionBuilder_:Lcom/google/protobuf/RepeatedFieldBuilderV3;
     618: goto          633
     621: aload_0
     622: getfield      #40                 // Field uninterpretedOptionBuilder_:Lcom/google/protobuf/RepeatedFieldBuilderV3;
     625: aload_1
     626: invokestatic  #142                // Method com/google/protobuf/DescriptorProtos$FileOptions.access$16200:(Lcom/google/protobuf/DescriptorProtos$FileOptions;)Ljava/util/List;
     629: invokevirtual #150                // Method com/google/protobuf/RepeatedFieldBuilderV3.addAllMessages:(Ljava/lang/Iterable;)Lcom/google/protobuf/RepeatedFieldBuilderV3;
     632: pop
     633: aload_0
     634: aload_1
     635: invokevirtual #151                // Method mergeExtensionFields:(Lcom/google/protobuf/GeneratedMessageV3$ExtendableMessage;)V
     638: aload_0
     639: aload_1
     640: invokevirtual #152                // Method com/google/protobuf/DescriptorProtos$FileOptions.getUnknownFields:()Lcom/google/protobuf/UnknownFieldSet;
     643: invokevirtual #153                // Method mergeUnknownFields:(Lcom/google/protobuf/UnknownFieldSet;)Lcom/google/protobuf/DescriptorProtos$FileOptions$Builder;
     646: pop
     647: aload_0
     648: invokevirtual #93                 // Method onChanged:()V
     651: aload_0
     652: areturn

  public final boolean isInitialized();
    Code:
       0: iconst_0
       1: istore_1
       2: iload_1
       3: aload_0
       4: invokevirtual #154                // Method getUninterpretedOptionCount:()I
       7: if_icmpge     29
      10: aload_0
      11: iload_1
      12: invokevirtual #155                // Method getUninterpretedOption:(I)Lcom/google/protobuf/DescriptorProtos$UninterpretedOption;
      15: invokevirtual #156                // Method com/google/protobuf/DescriptorProtos$UninterpretedOption.isInitialized:()Z
      18: ifne          23
      21: iconst_0
      22: ireturn
      23: iinc          1, 1
      26: goto          2
      29: aload_0
      30: invokevirtual #157                // Method extensionsAreInitialized:()Z
      33: ifne          38
      36: iconst_0
      37: ireturn
      38: iconst_1
      39: ireturn

  public com.google.protobuf.DescriptorProtos$FileOptions$Builder mergeFrom(com.google.protobuf.CodedInputStream, com.google.protobuf.ExtensionRegistryLite) throws java.io.IOException;
    Code:
       0: aload_2
       1: ifnonnull     12
       4: new           #158                // class java/lang/NullPointerException
       7: dup
       8: invokespecial #159                // Method java/lang/NullPointerException."<init>":()V
      11: athrow
      12: iconst_0
      13: istore_3
      14: iload_3
      15: ifne          757
      18: aload_1
      19: invokevirtual #160                // Method com/google/protobuf/CodedInputStream.readTag:()I
      22: istore        4
      24: iload         4
      26: lookupswitch  { // 22
                     0: 212
                    10: 217
                    66: 238
                    72: 259
                    80: 308
                    90: 329
                   128: 351
                   136: 374
                   144: 397
                   160: 420
                   184: 442
                   216: 465
                   248: 487
                   290: 510
                   298: 533
                   314: 556
                   322: 578
                   330: 600
                   336: 622
                   354: 645
                   362: 667
                  7994: 689
               default: 741
          }
     212: iconst_1
     213: istore_3
     214: goto          754
     217: aload_0
     218: aload_1
     219: invokevirtual #161                // Method com/google/protobuf/CodedInputStream.readBytes:()Lcom/google/protobuf/ByteString;
     222: putfield      #10                 // Field javaPackage_:Ljava/lang/Object;
     225: aload_0
     226: dup
     227: getfield      #26                 // Field bitField0_:I
     230: iconst_1
     231: ior
     232: putfield      #26                 // Field bitField0_:I
     235: goto          754
     238: aload_0
     239: aload_1
     240: invokevirtual #161                // Method com/google/protobuf/CodedInputStream.readBytes:()Lcom/google/protobuf/ByteString;
     243: putfield      #11                 // Field javaOuterClassname_:Ljava/lang/Object;
     246: aload_0
     247: dup
     248: getfield      #26                 // Field bitField0_:I
     251: iconst_2
     252: ior
     253: putfield      #26                 // Field bitField0_:I
     256: goto          754
     259: aload_1
     260: invokevirtual #162                // Method com/google/protobuf/CodedInputStream.readEnum:()I
     263: istore        5
     265: iload         5
     267: invokestatic  #163                // Method com/google/protobuf/DescriptorProtos$FileOptions$OptimizeMode.forNumber:(I)Lcom/google/protobuf/DescriptorProtos$FileOptions$OptimizeMode;
     270: astore        6
     272: aload         6
     274: ifnonnull     288
     277: aload_0
     278: bipush        9
     280: iload         5
     282: invokevirtual #164                // Method mergeUnknownVarintField:(II)V
     285: goto          754
     288: aload_0
     289: iload         5
     291: putfield      #12                 // Field optimizeFor_:I
     294: aload_0
     295: dup
     296: getfield      #26                 // Field bitField0_:I
     299: bipush        32
     301: ior
     302: putfield      #26                 // Field bitField0_:I
     305: goto          754
     308: aload_0
     309: aload_1
     310: invokevirtual #165                // Method com/google/protobuf/CodedInputStream.readBool:()Z
     313: putfield      #27                 // Field javaMultipleFiles_:Z
     316: aload_0
     317: dup
     318: getfield      #26                 // Field bitField0_:I
     321: iconst_4
     322: ior
     323: putfield      #26                 // Field bitField0_:I
     326: goto          754
     329: aload_0
     330: aload_1
     331: invokevirtual #161                // Method com/google/protobuf/CodedInputStream.readBytes:()Lcom/google/protobuf/ByteString;
     334: putfield      #13                 // Field goPackage_:Ljava/lang/Object;
     337: aload_0
     338: dup
     339: getfield      #26                 // Field bitField0_:I
     342: bipush        64
     344: ior
     345: putfield      #26                 // Field bitField0_:I
     348: goto          754
     351: aload_0
     352: aload_1
     353: invokevirtual #165                // Method com/google/protobuf/CodedInputStream.readBool:()Z
     356: putfield      #30                 // Field ccGenericServices_:Z
     359: aload_0
     360: dup
     361: getfield      #26                 // Field bitField0_:I
     364: sipush        128
     367: ior
     368: putfield      #26                 // Field bitField0_:I
     371: goto          754
     374: aload_0
     375: aload_1
     376: invokevirtual #165                // Method com/google/protobuf/CodedInputStream.readBool:()Z
     379: putfield      #31                 // Field javaGenericServices_:Z
     382: aload_0
     383: dup
     384: getfield      #26                 // Field bitField0_:I
     387: sipush        256
     390: ior
     391: putfield      #26                 // Field bitField0_:I
     394: goto          754
     397: aload_0
     398: aload_1
     399: invokevirtual #165                // Method com/google/protobuf/CodedInputStream.readBool:()Z
     402: putfield      #32                 // Field pyGenericServices_:Z
     405: aload_0
     406: dup
     407: getfield      #26                 // Field bitField0_:I
     410: sipush        512
     413: ior
     414: putfield      #26                 // Field bitField0_:I
     417: goto          754
     420: aload_0
     421: aload_1
     422: invokevirtual #165                // Method com/google/protobuf/CodedInputStream.readBool:()Z
     425: putfield      #28                 // Field javaGenerateEqualsAndHash_:Z
     428: aload_0
     429: dup
     430: getfield      #26                 // Field bitField0_:I
     433: bipush        8
     435: ior
     436: putfield      #26                 // Field bitField0_:I
     439: goto          754
     442: aload_0
     443: aload_1
     444: invokevirtual #165                // Method com/google/protobuf/CodedInputStream.readBool:()Z
     447: putfield      #34                 // Field deprecated_:Z
     450: aload_0
     451: dup
     452: getfield      #26                 // Field bitField0_:I
     455: sipush        2048
     458: ior
     459: putfield      #26                 // Field bitField0_:I
     462: goto          754
     465: aload_0
     466: aload_1
     467: invokevirtual #165                // Method com/google/protobuf/CodedInputStream.readBool:()Z
     470: putfield      #29                 // Field javaStringCheckUtf8_:Z
     473: aload_0
     474: dup
     475: getfield      #26                 // Field bitField0_:I
     478: bipush        16
     480: ior
     481: putfield      #26                 // Field bitField0_:I
     484: goto          754
     487: aload_0
     488: aload_1
     489: invokevirtual #165                // Method com/google/protobuf/CodedInputStream.readBool:()Z
     492: putfield      #14                 // Field ccEnableArenas_:Z
     495: aload_0
     496: dup
     497: getfield      #26                 // Field bitField0_:I
     500: sipush        4096
     503: ior
     504: putfield      #26                 // Field bitField0_:I
     507: goto          754
     510: aload_0
     511: aload_1
     512: invokevirtual #161                // Method com/google/protobuf/CodedInputStream.readBytes:()Lcom/google/protobuf/ByteString;
     515: putfield      #15                 // Field objcClassPrefix_:Ljava/lang/Object;
     518: aload_0
     519: dup
     520: getfield      #26                 // Field bitField0_:I
     523: sipush        8192
     526: ior
     527: putfield      #26                 // Field bitField0_:I
     530: goto          754
     533: aload_0
     534: aload_1
     535: invokevirtual #161                // Method com/google/protobuf/CodedInputStream.readBytes:()Lcom/google/protobuf/ByteString;
     538: putfield      #16                 // Field csharpNamespace_:Ljava/lang/Object;
     541: aload_0
     542: dup
     543: getfield      #26                 // Field bitField0_:I
     546: sipush        16384
     549: ior
     550: putfield      #26                 // Field bitField0_:I
     553: goto          754
     556: aload_0
     557: aload_1
     558: invokevirtual #161                // Method com/google/protobuf/CodedInputStream.readBytes:()Lcom/google/protobuf/ByteString;
     561: putfield      #17                 // Field swiftPrefix_:Ljava/lang/Object;
     564: aload_0
     565: dup
     566: getfield      #26                 // Field bitField0_:I
     569: ldc           #63                 // int 32768
     571: ior
     572: putfield      #26                 // Field bitField0_:I
     575: goto          754
     578: aload_0
     579: aload_1
     580: invokevirtual #161                // Method com/google/protobuf/CodedInputStream.readBytes:()Lcom/google/protobuf/ByteString;
     583: putfield      #18                 // Field phpClassPrefix_:Ljava/lang/Object;
     586: aload_0
     587: dup
     588: getfield      #26                 // Field bitField0_:I
     591: ldc           #65                 // int 65536
     593: ior
     594: putfield      #26                 // Field bitField0_:I
     597: goto          754
     600: aload_0
     601: aload_1
     602: invokevirtual #161                // Method com/google/protobuf/CodedInputStream.readBytes:()Lcom/google/protobuf/ByteString;
     605: putfield      #19                 // Field phpNamespace_:Ljava/lang/Object;
     608: aload_0
     609: dup
     610: getfield      #26                 // Field bitField0_:I
     613: ldc           #67                 // int 131072
     615: ior
     616: putfield      #26                 // Field bitField0_:I
     619: goto          754
     622: aload_0
     623: aload_1
     624: invokevirtual #165                // Method com/google/protobuf/CodedInputStream.readBool:()Z
     627: putfield      #33                 // Field phpGenericServices_:Z
     630: aload_0
     631: dup
     632: getfield      #26                 // Field bitField0_:I
     635: sipush        1024
     638: ior
     639: putfield      #26                 // Field bitField0_:I
     642: goto          754
     645: aload_0
     646: aload_1
     647: invokevirtual #161                // Method com/google/protobuf/CodedInputStream.readBytes:()Lcom/google/protobuf/ByteString;
     650: putfield      #20                 // Field phpMetadataNamespace_:Ljava/lang/Object;
     653: aload_0
     654: dup
     655: getfield      #26                 // Field bitField0_:I
     658: ldc           #69                 // int 262144
     660: ior
     661: putfield      #26                 // Field bitField0_:I
     664: goto          754
     667: aload_0
     668: aload_1
     669: invokevirtual #161                // Method com/google/protobuf/CodedInputStream.readBytes:()Lcom/google/protobuf/ByteString;
     672: putfield      #21                 // Field rubyPackage_:Ljava/lang/Object;
     675: aload_0
     676: dup
     677: getfield      #26                 // Field bitField0_:I
     680: ldc           #71                 // int 524288
     682: ior
     683: putfield      #26                 // Field bitField0_:I
     686: goto          754
     689: aload_1
     690: getstatic     #166                // Field com/google/protobuf/DescriptorProtos$UninterpretedOption.PARSER:Lcom/google/protobuf/Parser;
     693: aload_2
     694: invokevirtual #167                // Method com/google/protobuf/CodedInputStream.readMessage:(Lcom/google/protobuf/Parser;Lcom/google/protobuf/ExtensionRegistryLite;)Lcom/google/protobuf/MessageLite;
     697: checkcast     #168                // class com/google/protobuf/DescriptorProtos$UninterpretedOption
     700: astore        5
     702: aload_0
     703: getfield      #40                 // Field uninterpretedOptionBuilder_:Lcom/google/protobuf/RepeatedFieldBuilderV3;
     706: ifnonnull     728
     709: aload_0
     710: invokespecial #144                // Method ensureUninterpretedOptionIsMutable:()V
     713: aload_0
     714: getfield      #23                 // Field uninterpretedOption_:Ljava/util/List;
     717: aload         5
     719: invokeinterface #169,  2          // InterfaceMethod java/util/List.add:(Ljava/lang/Object;)Z
     724: pop
     725: goto          754
     728: aload_0
     729: getfield      #40                 // Field uninterpretedOptionBuilder_:Lcom/google/protobuf/RepeatedFieldBuilderV3;
     732: aload         5
     734: invokevirtual #170                // Method com/google/protobuf/RepeatedFieldBuilderV3.addMessage:(Lcom/google/protobuf/AbstractMessage;)Lcom/google/protobuf/RepeatedFieldBuilderV3;
     737: pop
     738: goto          754
     741: aload_0
     742: aload_1
     743: aload_2
     744: iload         4
     746: invokespecial #171                // Method com/google/protobuf/GeneratedMessageV3$ExtendableBuilder.parseUnknownField:(Lcom/google/protobuf/CodedInputStream;Lcom/google/protobuf/ExtensionRegistryLite;I)Z
     749: ifne          754
     752: iconst_1
     753: istore_3
     754: goto          14
     757: aload_0
     758: invokevirtual #93                 // Method onChanged:()V
     761: goto          779
     764: astore_3
     765: aload_3
     766: invokevirtual #173                // Method com/google/protobuf/InvalidProtocolBufferException.unwrapIOException:()Ljava/io/IOException;
     769: athrow
     770: astore        7
     772: aload_0
     773: invokevirtual #93                 // Method onChanged:()V
     776: aload         7
     778: athrow
     779: aload_0
     780: areturn
    Exception table:
       from    to  target type
          12   757   764   Class com/google/protobuf/InvalidProtocolBufferException
          12   757   770   any
         764   772   770   any

  public boolean hasJavaPackage();
    Code:
       0: aload_0
       1: getfield      #26                 // Field bitField0_:I
       4: iconst_1
       5: iand
       6: ifeq          13
       9: iconst_1
      10: goto          14
      13: iconst_0
      14: ireturn

  public java.lang.String getJavaPackage();
    Code:
       0: aload_0
       1: getfield      #10                 // Field javaPackage_:Ljava/lang/Object;
       4: astore_1
       5: aload_1
       6: instanceof    #174                // class java/lang/String
       9: ifne          36
      12: aload_1
      13: checkcast     #175                // class com/google/protobuf/ByteString
      16: astore_2
      17: aload_2
      18: invokevirtual #176                // Method com/google/protobuf/ByteString.toStringUtf8:()Ljava/lang/String;
      21: astore_3
      22: aload_2
      23: invokevirtual #177                // Method com/google/protobuf/ByteString.isValidUtf8:()Z
      26: ifeq          34
      29: aload_0
      30: aload_3
      31: putfield      #10                 // Field javaPackage_:Ljava/lang/Object;
      34: aload_3
      35: areturn
      36: aload_1
      37: checkcast     #174                // class java/lang/String
      40: areturn

  public com.google.protobuf.ByteString getJavaPackageBytes();
    Code:
       0: aload_0
       1: getfield      #10                 // Field javaPackage_:Ljava/lang/Object;
       4: astore_1
       5: aload_1
       6: instanceof    #174                // class java/lang/String
       9: ifeq          27
      12: aload_1
      13: checkcast     #174                // class java/lang/String
      16: invokestatic  #178                // Method com/google/protobuf/ByteString.copyFromUtf8:(Ljava/lang/String;)Lcom/google/protobuf/ByteString;
      19: astore_2
      20: aload_0
      21: aload_2
      22: putfield      #10                 // Field javaPackage_:Ljava/lang/Object;
      25: aload_2
      26: areturn
      27: aload_1
      28: checkcast     #175                // class com/google/protobuf/ByteString
      31: areturn

  public com.google.protobuf.DescriptorProtos$FileOptions$Builder setJavaPackage(java.lang.String);
    Code:
       0: aload_1
       1: ifnonnull     12
       4: new           #158                // class java/lang/NullPointerException
       7: dup
       8: invokespecial #159                // Method java/lang/NullPointerException."<init>":()V
      11: athrow
      12: aload_0
      13: dup
      14: getfield      #26                 // Field bitField0_:I
      17: iconst_1
      18: ior
      19: putfield      #26                 // Field bitField0_:I
      22: aload_0
      23: aload_1
      24: putfield      #10                 // Field javaPackage_:Ljava/lang/Object;
      27: aload_0
      28: invokevirtual #93                 // Method onChanged:()V
      31: aload_0
      32: areturn

  public com.google.protobuf.DescriptorProtos$FileOptions$Builder clearJavaPackage();
    Code:
       0: aload_0
       1: aload_0
       2: getfield      #26                 // Field bitField0_:I
       5: bipush        -2
       7: iand
       8: putfield      #26                 // Field bitField0_:I
      11: aload_0
      12: invokestatic  #43                 // Method com/google/protobuf/DescriptorProtos$FileOptions.getDefaultInstance:()Lcom/google/protobuf/DescriptorProtos$FileOptions;
      15: invokevirtual #179                // Method com/google/protobuf/DescriptorProtos$FileOptions.getJavaPackage:()Ljava/lang/String;
      18: putfield      #10                 // Field javaPackage_:Ljava/lang/Object;
      21: aload_0
      22: invokevirtual #93                 // Method onChanged:()V
      25: aload_0
      26: areturn

  public com.google.protobuf.DescriptorProtos$FileOptions$Builder setJavaPackageBytes(com.google.protobuf.ByteString);
    Code:
       0: aload_1
       1: ifnonnull     12
       4: new           #158                // class java/lang/NullPointerException
       7: dup
       8: invokespecial #159                // Method java/lang/NullPointerException."<init>":()V
      11: athrow
      12: aload_0
      13: dup
      14: getfield      #26                 // Field bitField0_:I
      17: iconst_1
      18: ior
      19: putfield      #26                 // Field bitField0_:I
      22: aload_0
      23: aload_1
      24: putfield      #10                 // Field javaPackage_:Ljava/lang/Object;
      27: aload_0
      28: invokevirtual #93                 // Method onChanged:()V
      31: aload_0
      32: areturn

  public boolean hasJavaOuterClassname();
    Code:
       0: aload_0
       1: getfield      #26                 // Field bitField0_:I
       4: iconst_2
       5: iand
       6: ifeq          13
       9: iconst_1
      10: goto          14
      13: iconst_0
      14: ireturn

  public java.lang.String getJavaOuterClassname();
    Code:
       0: aload_0
       1: getfield      #11                 // Field javaOuterClassname_:Ljava/lang/Object;
       4: astore_1
       5: aload_1
       6: instanceof    #174                // class java/lang/String
       9: ifne          36
      12: aload_1
      13: checkcast     #175                // class com/google/protobuf/ByteString
      16: astore_2
      17: aload_2
      18: invokevirtual #176                // Method com/google/protobuf/ByteString.toStringUtf8:()Ljava/lang/String;
      21: astore_3
      22: aload_2
      23: invokevirtual #177                // Method com/google/protobuf/ByteString.isValidUtf8:()Z
      26: ifeq          34
      29: aload_0
      30: aload_3
      31: putfield      #11                 // Field javaOuterClassname_:Ljava/lang/Object;
      34: aload_3
      35: areturn
      36: aload_1
      37: checkcast     #174                // class java/lang/String
      40: areturn

  public com.google.protobuf.ByteString getJavaOuterClassnameBytes();
    Code:
       0: aload_0
       1: getfield      #11                 // Field javaOuterClassname_:Ljava/lang/Object;
       4: astore_1
       5: aload_1
       6: instanceof    #174                // class java/lang/String
       9: ifeq          27
      12: aload_1
      13: checkcast     #174                // class java/lang/String
      16: invokestatic  #178                // Method com/google/protobuf/ByteString.copyFromUtf8:(Ljava/lang/String;)Lcom/google/protobuf/ByteString;
      19: astore_2
      20: aload_0
      21: aload_2
      22: putfield      #11                 // Field javaOuterClassname_:Ljava/lang/Object;
      25: aload_2
      26: areturn
      27: aload_1
      28: checkcast     #175                // class com/google/protobuf/ByteString
      31: areturn

  public com.google.protobuf.DescriptorProtos$FileOptions$Builder setJavaOuterClassname(java.lang.String);
    Code:
       0: aload_1
       1: ifnonnull     12
       4: new           #158                // class java/lang/NullPointerException
       7: dup
       8: invokespecial #159                // Method java/lang/NullPointerException."<init>":()V
      11: athrow
      12: aload_0
      13: dup
      14: getfield      #26                 // Field bitField0_:I
      17: iconst_2
      18: ior
      19: putfield      #26                 // Field bitField0_:I
      22: aload_0
      23: aload_1
      24: putfield      #11                 // Field javaOuterClassname_:Ljava/lang/Object;
      27: aload_0
      28: invokevirtual #93                 // Method onChanged:()V
      31: aload_0
      32: areturn

  public com.google.protobuf.DescriptorProtos$FileOptions$Builder clearJavaOuterClassname();
    Code:
       0: aload_0
       1: aload_0
       2: getfield      #26                 // Field bitField0_:I
       5: bipush        -3
       7: iand
       8: putfield      #26                 // Field bitField0_:I
      11: aload_0
      12: invokestatic  #43                 // Method com/google/protobuf/DescriptorProtos$FileOptions.getDefaultInstance:()Lcom/google/protobuf/DescriptorProtos$FileOptions;
      15: invokevirtual #180                // Method com/google/protobuf/DescriptorProtos$FileOptions.getJavaOuterClassname:()Ljava/lang/String;
      18: putfield      #11                 // Field javaOuterClassname_:Ljava/lang/Object;
      21: aload_0
      22: invokevirtual #93                 // Method onChanged:()V
      25: aload_0
      26: areturn

  public com.google.protobuf.DescriptorProtos$FileOptions$Builder setJavaOuterClassnameBytes(com.google.protobuf.ByteString);
    Code:
       0: aload_1
       1: ifnonnull     12
       4: new           #158                // class java/lang/NullPointerException
       7: dup
       8: invokespecial #159                // Method java/lang/NullPointerException."<init>":()V
      11: athrow
      12: aload_0
      13: dup
      14: getfield      #26                 // Field bitField0_:I
      17: iconst_2
      18: ior
      19: putfield      #26                 // Field bitField0_:I
      22: aload_0
      23: aload_1
      24: putfield      #11                 // Field javaOuterClassname_:Ljava/lang/Object;
      27: aload_0
      28: invokevirtual #93                 // Method onChanged:()V
      31: aload_0
      32: areturn

  public boolean hasJavaMultipleFiles();
    Code:
       0: aload_0
       1: getfield      #26                 // Field bitField0_:I
       4: iconst_4
       5: iand
       6: ifeq          13
       9: iconst_1
      10: goto          14
      13: iconst_0
      14: ireturn

  public boolean getJavaMultipleFiles();
    Code:
       0: aload_0
       1: getfield      #27                 // Field javaMultipleFiles_:Z
       4: ireturn

  public com.google.protobuf.DescriptorProtos$FileOptions$Builder setJavaMultipleFiles(boolean);
    Code:
       0: aload_0
       1: dup
       2: getfield      #26                 // Field bitField0_:I
       5: iconst_4
       6: ior
       7: putfield      #26                 // Field bitField0_:I
      10: aload_0
      11: iload_1
      12: putfield      #27                 // Field javaMultipleFiles_:Z
      15: aload_0
      16: invokevirtual #93                 // Method onChanged:()V
      19: aload_0
      20: areturn

  public com.google.protobuf.DescriptorProtos$FileOptions$Builder clearJavaMultipleFiles();
    Code:
       0: aload_0
       1: aload_0
       2: getfield      #26                 // Field bitField0_:I
       5: bipush        -5
       7: iand
       8: putfield      #26                 // Field bitField0_:I
      11: aload_0
      12: iconst_0
      13: putfield      #27                 // Field javaMultipleFiles_:Z
      16: aload_0
      17: invokevirtual #93                 // Method onChanged:()V
      20: aload_0
      21: areturn

  public boolean hasJavaGenerateEqualsAndHash();
    Code:
       0: aload_0
       1: getfield      #26                 // Field bitField0_:I
       4: bipush        8
       6: iand
       7: ifeq          14
      10: iconst_1
      11: goto          15
      14: iconst_0
      15: ireturn

  public boolean getJavaGenerateEqualsAndHash();
    Code:
       0: aload_0
       1: getfield      #28                 // Field javaGenerateEqualsAndHash_:Z
       4: ireturn

  public com.google.protobuf.DescriptorProtos$FileOptions$Builder setJavaGenerateEqualsAndHash(boolean);
    Code:
       0: aload_0
       1: dup
       2: getfield      #26                 // Field bitField0_:I
       5: bipush        8
       7: ior
       8: putfield      #26                 // Field bitField0_:I
      11: aload_0
      12: iload_1
      13: putfield      #28                 // Field javaGenerateEqualsAndHash_:Z
      16: aload_0
      17: invokevirtual #93                 // Method onChanged:()V
      20: aload_0
      21: areturn

  public com.google.protobuf.DescriptorProtos$FileOptions$Builder clearJavaGenerateEqualsAndHash();
    Code:
       0: aload_0
       1: aload_0
       2: getfield      #26                 // Field bitField0_:I
       5: bipush        -9
       7: iand
       8: putfield      #26                 // Field bitField0_:I
      11: aload_0
      12: iconst_0
      13: putfield      #28                 // Field javaGenerateEqualsAndHash_:Z
      16: aload_0
      17: invokevirtual #93                 // Method onChanged:()V
      20: aload_0
      21: areturn

  public boolean hasJavaStringCheckUtf8();
    Code:
       0: aload_0
       1: getfield      #26                 // Field bitField0_:I
       4: bipush        16
       6: iand
       7: ifeq          14
      10: iconst_1
      11: goto          15
      14: iconst_0
      15: ireturn

  public boolean getJavaStringCheckUtf8();
    Code:
       0: aload_0
       1: getfield      #29                 // Field javaStringCheckUtf8_:Z
       4: ireturn

  public com.google.protobuf.DescriptorProtos$FileOptions$Builder setJavaStringCheckUtf8(boolean);
    Code:
       0: aload_0
       1: dup
       2: getfield      #26                 // Field bitField0_:I
       5: bipush        16
       7: ior
       8: putfield      #26                 // Field bitField0_:I
      11: aload_0
      12: iload_1
      13: putfield      #29                 // Field javaStringCheckUtf8_:Z
      16: aload_0
      17: invokevirtual #93                 // Method onChanged:()V
      20: aload_0
      21: areturn

  public com.google.protobuf.DescriptorProtos$FileOptions$Builder clearJavaStringCheckUtf8();
    Code:
       0: aload_0
       1: aload_0
       2: getfield      #26                 // Field bitField0_:I
       5: bipush        -17
       7: iand
       8: putfield      #26                 // Field bitField0_:I
      11: aload_0
      12: iconst_0
      13: putfield      #29                 // Field javaStringCheckUtf8_:Z
      16: aload_0
      17: invokevirtual #93                 // Method onChanged:()V
      20: aload_0
      21: areturn

  public boolean hasOptimizeFor();
    Code:
       0: aload_0
       1: getfield      #26                 // Field bitField0_:I
       4: bipush        32
       6: iand
       7: ifeq          14
      10: iconst_1
      11: goto          15
      14: iconst_0
      15: ireturn

  public com.google.protobuf.DescriptorProtos$FileOptions$OptimizeMode getOptimizeFor();
    Code:
       0: aload_0
       1: getfield      #12                 // Field optimizeFor_:I
       4: invokestatic  #181                // Method com/google/protobuf/DescriptorProtos$FileOptions$OptimizeMode.valueOf:(I)Lcom/google/protobuf/DescriptorProtos$FileOptions$OptimizeMode;
       7: astore_1
       8: aload_1
       9: ifnonnull     18
      12: getstatic     #182                // Field com/google/protobuf/DescriptorProtos$FileOptions$OptimizeMode.SPEED:Lcom/google/protobuf/DescriptorProtos$FileOptions$OptimizeMode;
      15: goto          19
      18: aload_1
      19: areturn

  public com.google.protobuf.DescriptorProtos$FileOptions$Builder setOptimizeFor(com.google.protobuf.DescriptorProtos$FileOptions$OptimizeMode);
    Code:
       0: aload_1
       1: ifnonnull     12
       4: new           #158                // class java/lang/NullPointerException
       7: dup
       8: invokespecial #159                // Method java/lang/NullPointerException."<init>":()V
      11: athrow
      12: aload_0
      13: dup
      14: getfield      #26                 // Field bitField0_:I
      17: bipush        32
      19: ior
      20: putfield      #26                 // Field bitField0_:I
      23: aload_0
      24: aload_1
      25: invokevirtual #183                // Method com/google/protobuf/DescriptorProtos$FileOptions$OptimizeMode.getNumber:()I
      28: putfield      #12                 // Field optimizeFor_:I
      31: aload_0
      32: invokevirtual #93                 // Method onChanged:()V
      35: aload_0
      36: areturn

  public com.google.protobuf.DescriptorProtos$FileOptions$Builder clearOptimizeFor();
    Code:
       0: aload_0
       1: aload_0
       2: getfield      #26                 // Field bitField0_:I
       5: bipush        -33
       7: iand
       8: putfield      #26                 // Field bitField0_:I
      11: aload_0
      12: iconst_1
      13: putfield      #12                 // Field optimizeFor_:I
      16: aload_0
      17: invokevirtual #93                 // Method onChanged:()V
      20: aload_0
      21: areturn

  public boolean hasGoPackage();
    Code:
       0: aload_0
       1: getfield      #26                 // Field bitField0_:I
       4: bipush        64
       6: iand
       7: ifeq          14
      10: iconst_1
      11: goto          15
      14: iconst_0
      15: ireturn

  public java.lang.String getGoPackage();
    Code:
       0: aload_0
       1: getfield      #13                 // Field goPackage_:Ljava/lang/Object;
       4: astore_1
       5: aload_1
       6: instanceof    #174                // class java/lang/String
       9: ifne          36
      12: aload_1
      13: checkcast     #175                // class com/google/protobuf/ByteString
      16: astore_2
      17: aload_2
      18: invokevirtual #176                // Method com/google/protobuf/ByteString.toStringUtf8:()Ljava/lang/String;
      21: astore_3
      22: aload_2
      23: invokevirtual #177                // Method com/google/protobuf/ByteString.isValidUtf8:()Z
      26: ifeq          34
      29: aload_0
      30: aload_3
      31: putfield      #13                 // Field goPackage_:Ljava/lang/Object;
      34: aload_3
      35: areturn
      36: aload_1
      37: checkcast     #174                // class java/lang/String
      40: areturn

  public com.google.protobuf.ByteString getGoPackageBytes();
    Code:
       0: aload_0
       1: getfield      #13                 // Field goPackage_:Ljava/lang/Object;
       4: astore_1
       5: aload_1
       6: instanceof    #174                // class java/lang/String
       9: ifeq          27
      12: aload_1
      13: checkcast     #174                // class java/lang/String
      16: invokestatic  #178                // Method com/google/protobuf/ByteString.copyFromUtf8:(Ljava/lang/String;)Lcom/google/protobuf/ByteString;
      19: astore_2
      20: aload_0
      21: aload_2
      22: putfield      #13                 // Field goPackage_:Ljava/lang/Object;
      25: aload_2
      26: areturn
      27: aload_1
      28: checkcast     #175                // class com/google/protobuf/ByteString
      31: areturn

  public com.google.protobuf.DescriptorProtos$FileOptions$Builder setGoPackage(java.lang.String);
    Code:
       0: aload_1
       1: ifnonnull     12
       4: new           #158                // class java/lang/NullPointerException
       7: dup
       8: invokespecial #159                // Method java/lang/NullPointerException."<init>":()V
      11: athrow
      12: aload_0
      13: dup
      14: getfield      #26                 // Field bitField0_:I
      17: bipush        64
      19: ior
      20: putfield      #26                 // Field bitField0_:I
      23: aload_0
      24: aload_1
      25: putfield      #13                 // Field goPackage_:Ljava/lang/Object;
      28: aload_0
      29: invokevirtual #93                 // Method onChanged:()V
      32: aload_0
      33: areturn

  public com.google.protobuf.DescriptorProtos$FileOptions$Builder clearGoPackage();
    Code:
       0: aload_0
       1: aload_0
       2: getfield      #26                 // Field bitField0_:I
       5: bipush        -65
       7: iand
       8: putfield      #26                 // Field bitField0_:I
      11: aload_0
      12: invokestatic  #43                 // Method com/google/protobuf/DescriptorProtos$FileOptions.getDefaultInstance:()Lcom/google/protobuf/DescriptorProtos$FileOptions;
      15: invokevirtual #184                // Method com/google/protobuf/DescriptorProtos$FileOptions.getGoPackage:()Ljava/lang/String;
      18: putfield      #13                 // Field goPackage_:Ljava/lang/Object;
      21: aload_0
      22: invokevirtual #93                 // Method onChanged:()V
      25: aload_0
      26: areturn

  public com.google.protobuf.DescriptorProtos$FileOptions$Builder setGoPackageBytes(com.google.protobuf.ByteString);
    Code:
       0: aload_1
       1: ifnonnull     12
       4: new           #158                // class java/lang/NullPointerException
       7: dup
       8: invokespecial #159                // Method java/lang/NullPointerException."<init>":()V
      11: athrow
      12: aload_0
      13: dup
      14: getfield      #26                 // Field bitField0_:I
      17: bipush        64
      19: ior
      20: putfield      #26                 // Field bitField0_:I
      23: aload_0
      24: aload_1
      25: putfield      #13                 // Field goPackage_:Ljava/lang/Object;
      28: aload_0
      29: invokevirtual #93                 // Method onChanged:()V
      32: aload_0
      33: areturn

  public boolean hasCcGenericServices();
    Code:
       0: aload_0
       1: getfield      #26                 // Field bitField0_:I
       4: sipush        128
       7: iand
       8: ifeq          15
      11: iconst_1
      12: goto          16
      15: iconst_0
      16: ireturn

  public boolean getCcGenericServices();
    Code:
       0: aload_0
       1: getfield      #30                 // Field ccGenericServices_:Z
       4: ireturn

  public com.google.protobuf.DescriptorProtos$FileOptions$Builder setCcGenericServices(boolean);
    Code:
       0: aload_0
       1: dup
       2: getfield      #26                 // Field bitField0_:I
       5: sipush        128
       8: ior
       9: putfield      #26                 // Field bitField0_:I
      12: aload_0
      13: iload_1
      14: putfield      #30                 // Field ccGenericServices_:Z
      17: aload_0
      18: invokevirtual #93                 // Method onChanged:()V
      21: aload_0
      22: areturn

  public com.google.protobuf.DescriptorProtos$FileOptions$Builder clearCcGenericServices();
    Code:
       0: aload_0
       1: aload_0
       2: getfield      #26                 // Field bitField0_:I
       5: sipush        -129
       8: iand
       9: putfield      #26                 // Field bitField0_:I
      12: aload_0
      13: iconst_0
      14: putfield      #30                 // Field ccGenericServices_:Z
      17: aload_0
      18: invokevirtual #93                 // Method onChanged:()V
      21: aload_0
      22: areturn

  public boolean hasJavaGenericServices();
    Code:
       0: aload_0
       1: getfield      #26                 // Field bitField0_:I
       4: sipush        256
       7: iand
       8: ifeq          15
      11: iconst_1
      12: goto          16
      15: iconst_0
      16: ireturn

  public boolean getJavaGenericServices();
    Code:
       0: aload_0
       1: getfield      #31                 // Field javaGenericServices_:Z
       4: ireturn

  public com.google.protobuf.DescriptorProtos$FileOptions$Builder setJavaGenericServices(boolean);
    Code:
       0: aload_0
       1: dup
       2: getfield      #26                 // Field bitField0_:I
       5: sipush        256
       8: ior
       9: putfield      #26                 // Field bitField0_:I
      12: aload_0
      13: iload_1
      14: putfield      #31                 // Field javaGenericServices_:Z
      17: aload_0
      18: invokevirtual #93                 // Method onChanged:()V
      21: aload_0
      22: areturn

  public com.google.protobuf.DescriptorProtos$FileOptions$Builder clearJavaGenericServices();
    Code:
       0: aload_0
       1: aload_0
       2: getfield      #26                 // Field bitField0_:I
       5: sipush        -257
       8: iand
       9: putfield      #26                 // Field bitField0_:I
      12: aload_0
      13: iconst_0
      14: putfield      #31                 // Field javaGenericServices_:Z
      17: aload_0
      18: invokevirtual #93                 // Method onChanged:()V
      21: aload_0
      22: areturn

  public boolean hasPyGenericServices();
    Code:
       0: aload_0
       1: getfield      #26                 // Field bitField0_:I
       4: sipush        512
       7: iand
       8: ifeq          15
      11: iconst_1
      12: goto          16
      15: iconst_0
      16: ireturn

  public boolean getPyGenericServices();
    Code:
       0: aload_0
       1: getfield      #32                 // Field pyGenericServices_:Z
       4: ireturn

  public com.google.protobuf.DescriptorProtos$FileOptions$Builder setPyGenericServices(boolean);
    Code:
       0: aload_0
       1: dup
       2: getfield      #26                 // Field bitField0_:I
       5: sipush        512
       8: ior
       9: putfield      #26                 // Field bitField0_:I
      12: aload_0
      13: iload_1
      14: putfield      #32                 // Field pyGenericServices_:Z
      17: aload_0
      18: invokevirtual #93                 // Method onChanged:()V
      21: aload_0
      22: areturn

  public com.google.protobuf.DescriptorProtos$FileOptions$Builder clearPyGenericServices();
    Code:
       0: aload_0
       1: aload_0
       2: getfield      #26                 // Field bitField0_:I
       5: sipush        -513
       8: iand
       9: putfield      #26                 // Field bitField0_:I
      12: aload_0
      13: iconst_0
      14: putfield      #32                 // Field pyGenericServices_:Z
      17: aload_0
      18: invokevirtual #93                 // Method onChanged:()V
      21: aload_0
      22: areturn

  public boolean hasPhpGenericServices();
    Code:
       0: aload_0
       1: getfield      #26                 // Field bitField0_:I
       4: sipush        1024
       7: iand
       8: ifeq          15
      11: iconst_1
      12: goto          16
      15: iconst_0
      16: ireturn

  public boolean getPhpGenericServices();
    Code:
       0: aload_0
       1: getfield      #33                 // Field phpGenericServices_:Z
       4: ireturn

  public com.google.protobuf.DescriptorProtos$FileOptions$Builder setPhpGenericServices(boolean);
    Code:
       0: aload_0
       1: dup
       2: getfield      #26                 // Field bitField0_:I
       5: sipush        1024
       8: ior
       9: putfield      #26                 // Field bitField0_:I
      12: aload_0
      13: iload_1
      14: putfield      #33                 // Field phpGenericServices_:Z
      17: aload_0
      18: invokevirtual #93                 // Method onChanged:()V
      21: aload_0
      22: areturn

  public com.google.protobuf.DescriptorProtos$FileOptions$Builder clearPhpGenericServices();
    Code:
       0: aload_0
       1: aload_0
       2: getfield      #26                 // Field bitField0_:I
       5: sipush        -1025
       8: iand
       9: putfield      #26                 // Field bitField0_:I
      12: aload_0
      13: iconst_0
      14: putfield      #33                 // Field phpGenericServices_:Z
      17: aload_0
      18: invokevirtual #93                 // Method onChanged:()V
      21: aload_0
      22: areturn

  public boolean hasDeprecated();
    Code:
       0: aload_0
       1: getfield      #26                 // Field bitField0_:I
       4: sipush        2048
       7: iand
       8: ifeq          15
      11: iconst_1
      12: goto          16
      15: iconst_0
      16: ireturn

  public boolean getDeprecated();
    Code:
       0: aload_0
       1: getfield      #34                 // Field deprecated_:Z
       4: ireturn

  public com.google.protobuf.DescriptorProtos$FileOptions$Builder setDeprecated(boolean);
    Code:
       0: aload_0
       1: dup
       2: getfield      #26                 // Field bitField0_:I
       5: sipush        2048
       8: ior
       9: putfield      #26                 // Field bitField0_:I
      12: aload_0
      13: iload_1
      14: putfield      #34                 // Field deprecated_:Z
      17: aload_0
      18: invokevirtual #93                 // Method onChanged:()V
      21: aload_0
      22: areturn

  public com.google.protobuf.DescriptorProtos$FileOptions$Builder clearDeprecated();
    Code:
       0: aload_0
       1: aload_0
       2: getfield      #26                 // Field bitField0_:I
       5: sipush        -2049
       8: iand
       9: putfield      #26                 // Field bitField0_:I
      12: aload_0
      13: iconst_0
      14: putfield      #34                 // Field deprecated_:Z
      17: aload_0
      18: invokevirtual #93                 // Method onChanged:()V
      21: aload_0
      22: areturn

  public boolean hasCcEnableArenas();
    Code:
       0: aload_0
       1: getfield      #26                 // Field bitField0_:I
       4: sipush        4096
       7: iand
       8: ifeq          15
      11: iconst_1
      12: goto          16
      15: iconst_0
      16: ireturn

  public boolean getCcEnableArenas();
    Code:
       0: aload_0
       1: getfield      #14                 // Field ccEnableArenas_:Z
       4: ireturn

  public com.google.protobuf.DescriptorProtos$FileOptions$Builder setCcEnableArenas(boolean);
    Code:
       0: aload_0
       1: dup
       2: getfield      #26                 // Field bitField0_:I
       5: sipush        4096
       8: ior
       9: putfield      #26                 // Field bitField0_:I
      12: aload_0
      13: iload_1
      14: putfield      #14                 // Field ccEnableArenas_:Z
      17: aload_0
      18: invokevirtual #93                 // Method onChanged:()V
      21: aload_0
      22: areturn

  public com.google.protobuf.DescriptorProtos$FileOptions$Builder clearCcEnableArenas();
    Code:
       0: aload_0
       1: aload_0
       2: getfield      #26                 // Field bitField0_:I
       5: sipush        -4097
       8: iand
       9: putfield      #26                 // Field bitField0_:I
      12: aload_0
      13: iconst_1
      14: putfield      #14                 // Field ccEnableArenas_:Z
      17: aload_0
      18: invokevirtual #93                 // Method onChanged:()V
      21: aload_0
      22: areturn

  public boolean hasObjcClassPrefix();
    Code:
       0: aload_0
       1: getfield      #26                 // Field bitField0_:I
       4: sipush        8192
       7: iand
       8: ifeq          15
      11: iconst_1
      12: goto          16
      15: iconst_0
      16: ireturn

  public java.lang.String getObjcClassPrefix();
    Code:
       0: aload_0
       1: getfield      #15                 // Field objcClassPrefix_:Ljava/lang/Object;
       4: astore_1
       5: aload_1
       6: instanceof    #174                // class java/lang/String
       9: ifne          36
      12: aload_1
      13: checkcast     #175                // class com/google/protobuf/ByteString
      16: astore_2
      17: aload_2
      18: invokevirtual #176                // Method com/google/protobuf/ByteString.toStringUtf8:()Ljava/lang/String;
      21: astore_3
      22: aload_2
      23: invokevirtual #177                // Method com/google/protobuf/ByteString.isValidUtf8:()Z
      26: ifeq          34
      29: aload_0
      30: aload_3
      31: putfield      #15                 // Field objcClassPrefix_:Ljava/lang/Object;
      34: aload_3
      35: areturn
      36: aload_1
      37: checkcast     #174                // class java/lang/String
      40: areturn

  public com.google.protobuf.ByteString getObjcClassPrefixBytes();
    Code:
       0: aload_0
       1: getfield      #15                 // Field objcClassPrefix_:Ljava/lang/Object;
       4: astore_1
       5: aload_1
       6: instanceof    #174                // class java/lang/String
       9: ifeq          27
      12: aload_1
      13: checkcast     #174                // class java/lang/String
      16: invokestatic  #178                // Method com/google/protobuf/ByteString.copyFromUtf8:(Ljava/lang/String;)Lcom/google/protobuf/ByteString;
      19: astore_2
      20: aload_0
      21: aload_2
      22: putfield      #15                 // Field objcClassPrefix_:Ljava/lang/Object;
      25: aload_2
      26: areturn
      27: aload_1
      28: checkcast     #175                // class com/google/protobuf/ByteString
      31: areturn

  public com.google.protobuf.DescriptorProtos$FileOptions$Builder setObjcClassPrefix(java.lang.String);
    Code:
       0: aload_1
       1: ifnonnull     12
       4: new           #158                // class java/lang/NullPointerException
       7: dup
       8: invokespecial #159                // Method java/lang/NullPointerException."<init>":()V
      11: athrow
      12: aload_0
      13: dup
      14: getfield      #26                 // Field bitField0_:I
      17: sipush        8192
      20: ior
      21: putfield      #26                 // Field bitField0_:I
      24: aload_0
      25: aload_1
      26: putfield      #15                 // Field objcClassPrefix_:Ljava/lang/Object;
      29: aload_0
      30: invokevirtual #93                 // Method onChanged:()V
      33: aload_0
      34: areturn

  public com.google.protobuf.DescriptorProtos$FileOptions$Builder clearObjcClassPrefix();
    Code:
       0: aload_0
       1: aload_0
       2: getfield      #26                 // Field bitField0_:I
       5: sipush        -8193
       8: iand
       9: putfield      #26                 // Field bitField0_:I
      12: aload_0
      13: invokestatic  #43                 // Method com/google/protobuf/DescriptorProtos$FileOptions.getDefaultInstance:()Lcom/google/protobuf/DescriptorProtos$FileOptions;
      16: invokevirtual #185                // Method com/google/protobuf/DescriptorProtos$FileOptions.getObjcClassPrefix:()Ljava/lang/String;
      19: putfield      #15                 // Field objcClassPrefix_:Ljava/lang/Object;
      22: aload_0
      23: invokevirtual #93                 // Method onChanged:()V
      26: aload_0
      27: areturn

  public com.google.protobuf.DescriptorProtos$FileOptions$Builder setObjcClassPrefixBytes(com.google.protobuf.ByteString);
    Code:
       0: aload_1
       1: ifnonnull     12
       4: new           #158                // class java/lang/NullPointerException
       7: dup
       8: invokespecial #159                // Method java/lang/NullPointerException."<init>":()V
      11: athrow
      12: aload_0
      13: dup
      14: getfield      #26                 // Field bitField0_:I
      17: sipush        8192
      20: ior
      21: putfield      #26                 // Field bitField0_:I
      24: aload_0
      25: aload_1
      26: putfield      #15                 // Field objcClassPrefix_:Ljava/lang/Object;
      29: aload_0
      30: invokevirtual #93                 // Method onChanged:()V
      33: aload_0
      34: areturn

  public boolean hasCsharpNamespace();
    Code:
       0: aload_0
       1: getfield      #26                 // Field bitField0_:I
       4: sipush        16384
       7: iand
       8: ifeq          15
      11: iconst_1
      12: goto          16
      15: iconst_0
      16: ireturn

  public java.lang.String getCsharpNamespace();
    Code:
       0: aload_0
       1: getfield      #16                 // Field csharpNamespace_:Ljava/lang/Object;
       4: astore_1
       5: aload_1
       6: instanceof    #174                // class java/lang/String
       9: ifne          36
      12: aload_1
      13: checkcast     #175                // class com/google/protobuf/ByteString
      16: astore_2
      17: aload_2
      18: invokevirtual #176                // Method com/google/protobuf/ByteString.toStringUtf8:()Ljava/lang/String;
      21: astore_3
      22: aload_2
      23: invokevirtual #177                // Method com/google/protobuf/ByteString.isValidUtf8:()Z
      26: ifeq          34
      29: aload_0
      30: aload_3
      31: putfield      #16                 // Field csharpNamespace_:Ljava/lang/Object;
      34: aload_3
      35: areturn
      36: aload_1
      37: checkcast     #174                // class java/lang/String
      40: areturn

  public com.google.protobuf.ByteString getCsharpNamespaceBytes();
    Code:
       0: aload_0
       1: getfield      #16                 // Field csharpNamespace_:Ljava/lang/Object;
       4: astore_1
       5: aload_1
       6: instanceof    #174                // class java/lang/String
       9: ifeq          27
      12: aload_1
      13: checkcast     #174                // class java/lang/String
      16: invokestatic  #178                // Method com/google/protobuf/ByteString.copyFromUtf8:(Ljava/lang/String;)Lcom/google/protobuf/ByteString;
      19: astore_2
      20: aload_0
      21: aload_2
      22: putfield      #16                 // Field csharpNamespace_:Ljava/lang/Object;
      25: aload_2
      26: areturn
      27: aload_1
      28: checkcast     #175                // class com/google/protobuf/ByteString
      31: areturn

  public com.google.protobuf.DescriptorProtos$FileOptions$Builder setCsharpNamespace(java.lang.String);
    Code:
       0: aload_1
       1: ifnonnull     12
       4: new           #158                // class java/lang/NullPointerException
       7: dup
       8: invokespecial #159                // Method java/lang/NullPointerException."<init>":()V
      11: athrow
      12: aload_0
      13: dup
      14: getfield      #26                 // Field bitField0_:I
      17: sipush        16384
      20: ior
      21: putfield      #26                 // Field bitField0_:I
      24: aload_0
      25: aload_1
      26: putfield      #16                 // Field csharpNamespace_:Ljava/lang/Object;
      29: aload_0
      30: invokevirtual #93                 // Method onChanged:()V
      33: aload_0
      34: areturn

  public com.google.protobuf.DescriptorProtos$FileOptions$Builder clearCsharpNamespace();
    Code:
       0: aload_0
       1: aload_0
       2: getfield      #26                 // Field bitField0_:I
       5: sipush        -16385
       8: iand
       9: putfield      #26                 // Field bitField0_:I
      12: aload_0
      13: invokestatic  #43                 // Method com/google/protobuf/DescriptorProtos$FileOptions.getDefaultInstance:()Lcom/google/protobuf/DescriptorProtos$FileOptions;
      16: invokevirtual #186                // Method com/google/protobuf/DescriptorProtos$FileOptions.getCsharpNamespace:()Ljava/lang/String;
      19: putfield      #16                 // Field csharpNamespace_:Ljava/lang/Object;
      22: aload_0
      23: invokevirtual #93                 // Method onChanged:()V
      26: aload_0
      27: areturn

  public com.google.protobuf.DescriptorProtos$FileOptions$Builder setCsharpNamespaceBytes(com.google.protobuf.ByteString);
    Code:
       0: aload_1
       1: ifnonnull     12
       4: new           #158                // class java/lang/NullPointerException
       7: dup
       8: invokespecial #159                // Method java/lang/NullPointerException."<init>":()V
      11: athrow
      12: aload_0
      13: dup
      14: getfield      #26                 // Field bitField0_:I
      17: sipush        16384
      20: ior
      21: putfield      #26                 // Field bitField0_:I
      24: aload_0
      25: aload_1
      26: putfield      #16                 // Field csharpNamespace_:Ljava/lang/Object;
      29: aload_0
      30: invokevirtual #93                 // Method onChanged:()V
      33: aload_0
      34: areturn

  public boolean hasSwiftPrefix();
    Code:
       0: aload_0
       1: getfield      #26                 // Field bitField0_:I
       4: ldc           #63                 // int 32768
       6: iand
       7: ifeq          14
      10: iconst_1
      11: goto          15
      14: iconst_0
      15: ireturn

  public java.lang.String getSwiftPrefix();
    Code:
       0: aload_0
       1: getfield      #17                 // Field swiftPrefix_:Ljava/lang/Object;
       4: astore_1
       5: aload_1
       6: instanceof    #174                // class java/lang/String
       9: ifne          36
      12: aload_1
      13: checkcast     #175                // class com/google/protobuf/ByteString
      16: astore_2
      17: aload_2
      18: invokevirtual #176                // Method com/google/protobuf/ByteString.toStringUtf8:()Ljava/lang/String;
      21: astore_3
      22: aload_2
      23: invokevirtual #177                // Method com/google/protobuf/ByteString.isValidUtf8:()Z
      26: ifeq          34
      29: aload_0
      30: aload_3
      31: putfield      #17                 // Field swiftPrefix_:Ljava/lang/Object;
      34: aload_3
      35: areturn
      36: aload_1
      37: checkcast     #174                // class java/lang/String
      40: areturn

  public com.google.protobuf.ByteString getSwiftPrefixBytes();
    Code:
       0: aload_0
       1: getfield      #17                 // Field swiftPrefix_:Ljava/lang/Object;
       4: astore_1
       5: aload_1
       6: instanceof    #174                // class java/lang/String
       9: ifeq          27
      12: aload_1
      13: checkcast     #174                // class java/lang/String
      16: invokestatic  #178                // Method com/google/protobuf/ByteString.copyFromUtf8:(Ljava/lang/String;)Lcom/google/protobuf/ByteString;
      19: astore_2
      20: aload_0
      21: aload_2
      22: putfield      #17                 // Field swiftPrefix_:Ljava/lang/Object;
      25: aload_2
      26: areturn
      27: aload_1
      28: checkcast     #175                // class com/google/protobuf/ByteString
      31: areturn

  public com.google.protobuf.DescriptorProtos$FileOptions$Builder setSwiftPrefix(java.lang.String);
    Code:
       0: aload_1
       1: ifnonnull     12
       4: new           #158                // class java/lang/NullPointerException
       7: dup
       8: invokespecial #159                // Method java/lang/NullPointerException."<init>":()V
      11: athrow
      12: aload_0
      13: dup
      14: getfield      #26                 // Field bitField0_:I
      17: ldc           #63                 // int 32768
      19: ior
      20: putfield      #26                 // Field bitField0_:I
      23: aload_0
      24: aload_1
      25: putfield      #17                 // Field swiftPrefix_:Ljava/lang/Object;
      28: aload_0
      29: invokevirtual #93                 // Method onChanged:()V
      32: aload_0
      33: areturn

  public com.google.protobuf.DescriptorProtos$FileOptions$Builder clearSwiftPrefix();
    Code:
       0: aload_0
       1: aload_0
       2: getfield      #26                 // Field bitField0_:I
       5: ldc           #35                 // int -32769
       7: iand
       8: putfield      #26                 // Field bitField0_:I
      11: aload_0
      12: invokestatic  #43                 // Method com/google/protobuf/DescriptorProtos$FileOptions.getDefaultInstance:()Lcom/google/protobuf/DescriptorProtos$FileOptions;
      15: invokevirtual #187                // Method com/google/protobuf/DescriptorProtos$FileOptions.getSwiftPrefix:()Ljava/lang/String;
      18: putfield      #17                 // Field swiftPrefix_:Ljava/lang/Object;
      21: aload_0
      22: invokevirtual #93                 // Method onChanged:()V
      25: aload_0
      26: areturn

  public com.google.protobuf.DescriptorProtos$FileOptions$Builder setSwiftPrefixBytes(com.google.protobuf.ByteString);
    Code:
       0: aload_1
       1: ifnonnull     12
       4: new           #158                // class java/lang/NullPointerException
       7: dup
       8: invokespecial #159                // Method java/lang/NullPointerException."<init>":()V
      11: athrow
      12: aload_0
      13: dup
      14: getfield      #26                 // Field bitField0_:I
      17: ldc           #63                 // int 32768
      19: ior
      20: putfield      #26                 // Field bitField0_:I
      23: aload_0
      24: aload_1
      25: putfield      #17                 // Field swiftPrefix_:Ljava/lang/Object;
      28: aload_0
      29: invokevirtual #93                 // Method onChanged:()V
      32: aload_0
      33: areturn

  public boolean hasPhpClassPrefix();
    Code:
       0: aload_0
       1: getfield      #26                 // Field bitField0_:I
       4: ldc           #65                 // int 65536
       6: iand
       7: ifeq          14
      10: iconst_1
      11: goto          15
      14: iconst_0
      15: ireturn

  public java.lang.String getPhpClassPrefix();
    Code:
       0: aload_0
       1: getfield      #18                 // Field phpClassPrefix_:Ljava/lang/Object;
       4: astore_1
       5: aload_1
       6: instanceof    #174                // class java/lang/String
       9: ifne          36
      12: aload_1
      13: checkcast     #175                // class com/google/protobuf/ByteString
      16: astore_2
      17: aload_2
      18: invokevirtual #176                // Method com/google/protobuf/ByteString.toStringUtf8:()Ljava/lang/String;
      21: astore_3
      22: aload_2
      23: invokevirtual #177                // Method com/google/protobuf/ByteString.isValidUtf8:()Z
      26: ifeq          34
      29: aload_0
      30: aload_3
      31: putfield      #18                 // Field phpClassPrefix_:Ljava/lang/Object;
      34: aload_3
      35: areturn
      36: aload_1
      37: checkcast     #174                // class java/lang/String
      40: areturn

  public com.google.protobuf.ByteString getPhpClassPrefixBytes();
    Code:
       0: aload_0
       1: getfield      #18                 // Field phpClassPrefix_:Ljava/lang/Object;
       4: astore_1
       5: aload_1
       6: instanceof    #174                // class java/lang/String
       9: ifeq          27
      12: aload_1
      13: checkcast     #174                // class java/lang/String
      16: invokestatic  #178                // Method com/google/protobuf/ByteString.copyFromUtf8:(Ljava/lang/String;)Lcom/google/protobuf/ByteString;
      19: astore_2
      20: aload_0
      21: aload_2
      22: putfield      #18                 // Field phpClassPrefix_:Ljava/lang/Object;
      25: aload_2
      26: areturn
      27: aload_1
      28: checkcast     #175                // class com/google/protobuf/ByteString
      31: areturn

  public com.google.protobuf.DescriptorProtos$FileOptions$Builder setPhpClassPrefix(java.lang.String);
    Code:
       0: aload_1
       1: ifnonnull     12
       4: new           #158                // class java/lang/NullPointerException
       7: dup
       8: invokespecial #159                // Method java/lang/NullPointerException."<init>":()V
      11: athrow
      12: aload_0
      13: dup
      14: getfield      #26                 // Field bitField0_:I
      17: ldc           #65                 // int 65536
      19: ior
      20: putfield      #26                 // Field bitField0_:I
      23: aload_0
      24: aload_1
      25: putfield      #18                 // Field phpClassPrefix_:Ljava/lang/Object;
      28: aload_0
      29: invokevirtual #93                 // Method onChanged:()V
      32: aload_0
      33: areturn

  public com.google.protobuf.DescriptorProtos$FileOptions$Builder clearPhpClassPrefix();
    Code:
       0: aload_0
       1: aload_0
       2: getfield      #26                 // Field bitField0_:I
       5: ldc           #36                 // int -65537
       7: iand
       8: putfield      #26                 // Field bitField0_:I
      11: aload_0
      12: invokestatic  #43                 // Method com/google/protobuf/DescriptorProtos$FileOptions.getDefaultInstance:()Lcom/google/protobuf/DescriptorProtos$FileOptions;
      15: invokevirtual #188                // Method com/google/protobuf/DescriptorProtos$FileOptions.getPhpClassPrefix:()Ljava/lang/String;
      18: putfield      #18                 // Field phpClassPrefix_:Ljava/lang/Object;
      21: aload_0
      22: invokevirtual #93                 // Method onChanged:()V
      25: aload_0
      26: areturn

  public com.google.protobuf.DescriptorProtos$FileOptions$Builder setPhpClassPrefixBytes(com.google.protobuf.ByteString);
    Code:
       0: aload_1
       1: ifnonnull     12
       4: new           #158                // class java/lang/NullPointerException
       7: dup
       8: invokespecial #159                // Method java/lang/NullPointerException."<init>":()V
      11: athrow
      12: aload_0
      13: dup
      14: getfield      #26                 // Field bitField0_:I
      17: ldc           #65                 // int 65536
      19: ior
      20: putfield      #26                 // Field bitField0_:I
      23: aload_0
      24: aload_1
      25: putfield      #18                 // Field phpClassPrefix_:Ljava/lang/Object;
      28: aload_0
      29: invokevirtual #93                 // Method onChanged:()V
      32: aload_0
      33: areturn

  public boolean hasPhpNamespace();
    Code:
       0: aload_0
       1: getfield      #26                 // Field bitField0_:I
       4: ldc           #67                 // int 131072
       6: iand
       7: ifeq          14
      10: iconst_1
      11: goto          15
      14: iconst_0
      15: ireturn

  public java.lang.String getPhpNamespace();
    Code:
       0: aload_0
       1: getfield      #19                 // Field phpNamespace_:Ljava/lang/Object;
       4: astore_1
       5: aload_1
       6: instanceof    #174                // class java/lang/String
       9: ifne          36
      12: aload_1
      13: checkcast     #175                // class com/google/protobuf/ByteString
      16: astore_2
      17: aload_2
      18: invokevirtual #176                // Method com/google/protobuf/ByteString.toStringUtf8:()Ljava/lang/String;
      21: astore_3
      22: aload_2
      23: invokevirtual #177                // Method com/google/protobuf/ByteString.isValidUtf8:()Z
      26: ifeq          34
      29: aload_0
      30: aload_3
      31: putfield      #19                 // Field phpNamespace_:Ljava/lang/Object;
      34: aload_3
      35: areturn
      36: aload_1
      37: checkcast     #174                // class java/lang/String
      40: areturn

  public com.google.protobuf.ByteString getPhpNamespaceBytes();
    Code:
       0: aload_0
       1: getfield      #19                 // Field phpNamespace_:Ljava/lang/Object;
       4: astore_1
       5: aload_1
       6: instanceof    #174                // class java/lang/String
       9: ifeq          27
      12: aload_1
      13: checkcast     #174                // class java/lang/String
      16: invokestatic  #178                // Method com/google/protobuf/ByteString.copyFromUtf8:(Ljava/lang/String;)Lcom/google/protobuf/ByteString;
      19: astore_2
      20: aload_0
      21: aload_2
      22: putfield      #19                 // Field phpNamespace_:Ljava/lang/Object;
      25: aload_2
      26: areturn
      27: aload_1
      28: checkcast     #175                // class com/google/protobuf/ByteString
      31: areturn

  public com.google.protobuf.DescriptorProtos$FileOptions$Builder setPhpNamespace(java.lang.String);
    Code:
       0: aload_1
       1: ifnonnull     12
       4: new           #158                // class java/lang/NullPointerException
       7: dup
       8: invokespecial #159                // Method java/lang/NullPointerException."<init>":()V
      11: athrow
      12: aload_0
      13: dup
      14: getfield      #26                 // Field bitField0_:I
      17: ldc           #67                 // int 131072
      19: ior
      20: putfield      #26                 // Field bitField0_:I
      23: aload_0
      24: aload_1
      25: putfield      #19                 // Field phpNamespace_:Ljava/lang/Object;
      28: aload_0
      29: invokevirtual #93                 // Method onChanged:()V
      32: aload_0
      33: areturn

  public com.google.protobuf.DescriptorProtos$FileOptions$Builder clearPhpNamespace();
    Code:
       0: aload_0
       1: aload_0
       2: getfield      #26                 // Field bitField0_:I
       5: ldc           #37                 // int -131073
       7: iand
       8: putfield      #26                 // Field bitField0_:I
      11: aload_0
      12: invokestatic  #43                 // Method com/google/protobuf/DescriptorProtos$FileOptions.getDefaultInstance:()Lcom/google/protobuf/DescriptorProtos$FileOptions;
      15: invokevirtual #189                // Method com/google/protobuf/DescriptorProtos$FileOptions.getPhpNamespace:()Ljava/lang/String;
      18: putfield      #19                 // Field phpNamespace_:Ljava/lang/Object;
      21: aload_0
      22: invokevirtual #93                 // Method onChanged:()V
      25: aload_0
      26: areturn

  public com.google.protobuf.DescriptorProtos$FileOptions$Builder setPhpNamespaceBytes(com.google.protobuf.ByteString);
    Code:
       0: aload_1
       1: ifnonnull     12
       4: new           #158                // class java/lang/NullPointerException
       7: dup
       8: invokespecial #159                // Method java/lang/NullPointerException."<init>":()V
      11: athrow
      12: aload_0
      13: dup
      14: getfield      #26                 // Field bitField0_:I
      17: ldc           #67                 // int 131072
      19: ior
      20: putfield      #26                 // Field bitField0_:I
      23: aload_0
      24: aload_1
      25: putfield      #19                 // Field phpNamespace_:Ljava/lang/Object;
      28: aload_0
      29: invokevirtual #93                 // Method onChanged:()V
      32: aload_0
      33: areturn

  public boolean hasPhpMetadataNamespace();
    Code:
       0: aload_0
       1: getfield      #26                 // Field bitField0_:I
       4: ldc           #69                 // int 262144
       6: iand
       7: ifeq          14
      10: iconst_1
      11: goto          15
      14: iconst_0
      15: ireturn

  public java.lang.String getPhpMetadataNamespace();
    Code:
       0: aload_0
       1: getfield      #20                 // Field phpMetadataNamespace_:Ljava/lang/Object;
       4: astore_1
       5: aload_1
       6: instanceof    #174                // class java/lang/String
       9: ifne          36
      12: aload_1
      13: checkcast     #175                // class com/google/protobuf/ByteString
      16: astore_2
      17: aload_2
      18: invokevirtual #176                // Method com/google/protobuf/ByteString.toStringUtf8:()Ljava/lang/String;
      21: astore_3
      22: aload_2
      23: invokevirtual #177                // Method com/google/protobuf/ByteString.isValidUtf8:()Z
      26: ifeq          34
      29: aload_0
      30: aload_3
      31: putfield      #20                 // Field phpMetadataNamespace_:Ljava/lang/Object;
      34: aload_3
      35: areturn
      36: aload_1
      37: checkcast     #174                // class java/lang/String
      40: areturn

  public com.google.protobuf.ByteString getPhpMetadataNamespaceBytes();
    Code:
       0: aload_0
       1: getfield      #20                 // Field phpMetadataNamespace_:Ljava/lang/Object;
       4: astore_1
       5: aload_1
       6: instanceof    #174                // class java/lang/String
       9: ifeq          27
      12: aload_1
      13: checkcast     #174                // class java/lang/String
      16: invokestatic  #178                // Method com/google/protobuf/ByteString.copyFromUtf8:(Ljava/lang/String;)Lcom/google/protobuf/ByteString;
      19: astore_2
      20: aload_0
      21: aload_2
      22: putfield      #20                 // Field phpMetadataNamespace_:Ljava/lang/Object;
      25: aload_2
      26: areturn
      27: aload_1
      28: checkcast     #175                // class com/google/protobuf/ByteString
      31: areturn

  public com.google.protobuf.DescriptorProtos$FileOptions$Builder setPhpMetadataNamespace(java.lang.String);
    Code:
       0: aload_1
       1: ifnonnull     12
       4: new           #158                // class java/lang/NullPointerException
       7: dup
       8: invokespecial #159                // Method java/lang/NullPointerException."<init>":()V
      11: athrow
      12: aload_0
      13: dup
      14: getfield      #26                 // Field bitField0_:I
      17: ldc           #69                 // int 262144
      19: ior
      20: putfield      #26                 // Field bitField0_:I
      23: aload_0
      24: aload_1
      25: putfield      #20                 // Field phpMetadataNamespace_:Ljava/lang/Object;
      28: aload_0
      29: invokevirtual #93                 // Method onChanged:()V
      32: aload_0
      33: areturn

  public com.google.protobuf.DescriptorProtos$FileOptions$Builder clearPhpMetadataNamespace();
    Code:
       0: aload_0
       1: aload_0
       2: getfield      #26                 // Field bitField0_:I
       5: ldc           #38                 // int -262145
       7: iand
       8: putfield      #26                 // Field bitField0_:I
      11: aload_0
      12: invokestatic  #43                 // Method com/google/protobuf/DescriptorProtos$FileOptions.getDefaultInstance:()Lcom/google/protobuf/DescriptorProtos$FileOptions;
      15: invokevirtual #190                // Method com/google/protobuf/DescriptorProtos$FileOptions.getPhpMetadataNamespace:()Ljava/lang/String;
      18: putfield      #20                 // Field phpMetadataNamespace_:Ljava/lang/Object;
      21: aload_0
      22: invokevirtual #93                 // Method onChanged:()V
      25: aload_0
      26: areturn

  public com.google.protobuf.DescriptorProtos$FileOptions$Builder setPhpMetadataNamespaceBytes(com.google.protobuf.ByteString);
    Code:
       0: aload_1
       1: ifnonnull     12
       4: new           #158                // class java/lang/NullPointerException
       7: dup
       8: invokespecial #159                // Method java/lang/NullPointerException."<init>":()V
      11: athrow
      12: aload_0
      13: dup
      14: getfield      #26                 // Field bitField0_:I
      17: ldc           #69                 // int 262144
      19: ior
      20: putfield      #26                 // Field bitField0_:I
      23: aload_0
      24: aload_1
      25: putfield      #20                 // Field phpMetadataNamespace_:Ljava/lang/Object;
      28: aload_0
      29: invokevirtual #93                 // Method onChanged:()V
      32: aload_0
      33: areturn

  public boolean hasRubyPackage();
    Code:
       0: aload_0
       1: getfield      #26                 // Field bitField0_:I
       4: ldc           #71                 // int 524288
       6: iand
       7: ifeq          14
      10: iconst_1
      11: goto          15
      14: iconst_0
      15: ireturn

  public java.lang.String getRubyPackage();
    Code:
       0: aload_0
       1: getfield      #21                 // Field rubyPackage_:Ljava/lang/Object;
       4: astore_1
       5: aload_1
       6: instanceof    #174                // class java/lang/String
       9: ifne          36
      12: aload_1
      13: checkcast     #175                // class com/google/protobuf/ByteString
      16: astore_2
      17: aload_2
      18: invokevirtual #176                // Method com/google/protobuf/ByteString.toStringUtf8:()Ljava/lang/String;
      21: astore_3
      22: aload_2
      23: invokevirtual #177                // Method com/google/protobuf/ByteString.isValidUtf8:()Z
      26: ifeq          34
      29: aload_0
      30: aload_3
      31: putfield      #21                 // Field rubyPackage_:Ljava/lang/Object;
      34: aload_3
      35: areturn
      36: aload_1
      37: checkcast     #174                // class java/lang/String
      40: areturn

  public com.google.protobuf.ByteString getRubyPackageBytes();
    Code:
       0: aload_0
       1: getfield      #21                 // Field rubyPackage_:Ljava/lang/Object;
       4: astore_1
       5: aload_1
       6: instanceof    #174                // class java/lang/String
       9: ifeq          27
      12: aload_1
      13: checkcast     #174                // class java/lang/String
      16: invokestatic  #178                // Method com/google/protobuf/ByteString.copyFromUtf8:(Ljava/lang/String;)Lcom/google/protobuf/ByteString;
      19: astore_2
      20: aload_0
      21: aload_2
      22: putfield      #21                 // Field rubyPackage_:Ljava/lang/Object;
      25: aload_2
      26: areturn
      27: aload_1
      28: checkcast     #175                // class com/google/protobuf/ByteString
      31: areturn

  public com.google.protobuf.DescriptorProtos$FileOptions$Builder setRubyPackage(java.lang.String);
    Code:
       0: aload_1
       1: ifnonnull     12
       4: new           #158                // class java/lang/NullPointerException
       7: dup
       8: invokespecial #159                // Method java/lang/NullPointerException."<init>":()V
      11: athrow
      12: aload_0
      13: dup
      14: getfield      #26                 // Field bitField0_:I
      17: ldc           #71                 // int 524288
      19: ior
      20: putfield      #26                 // Field bitField0_:I
      23: aload_0
      24: aload_1
      25: putfield      #21                 // Field rubyPackage_:Ljava/lang/Object;
      28: aload_0
      29: invokevirtual #93                 // Method onChanged:()V
      32: aload_0
      33: areturn

  public com.google.protobuf.DescriptorProtos$FileOptions$Builder clearRubyPackage();
    Code:
       0: aload_0
       1: aload_0
       2: getfield      #26                 // Field bitField0_:I
       5: ldc           #39                 // int -524289
       7: iand
       8: putfield      #26                 // Field bitField0_:I
      11: aload_0
      12: invokestatic  #43                 // Method com/google/protobuf/DescriptorProtos$FileOptions.getDefaultInstance:()Lcom/google/protobuf/DescriptorProtos$FileOptions;
      15: invokevirtual #191                // Method com/google/protobuf/DescriptorProtos$FileOptions.getRubyPackage:()Ljava/lang/String;
      18: putfield      #21                 // Field rubyPackage_:Ljava/lang/Object;
      21: aload_0
      22: invokevirtual #93                 // Method onChanged:()V
      25: aload_0
      26: areturn

  public com.google.protobuf.DescriptorProtos$FileOptions$Builder setRubyPackageBytes(com.google.protobuf.ByteString);
    Code:
       0: aload_1
       1: ifnonnull     12
       4: new           #158                // class java/lang/NullPointerException
       7: dup
       8: invokespecial #159                // Method java/lang/NullPointerException."<init>":()V
      11: athrow
      12: aload_0
      13: dup
      14: getfield      #26                 // Field bitField0_:I
      17: ldc           #71                 // int 524288
      19: ior
      20: putfield      #26                 // Field bitField0_:I
      23: aload_0
      24: aload_1
      25: putfield      #21                 // Field rubyPackage_:Ljava/lang/Object;
      28: aload_0
      29: invokevirtual #93                 // Method onChanged:()V
      32: aload_0
      33: areturn

  private void ensureUninterpretedOptionIsMutable();
    Code:
       0: aload_0
       1: getfield      #26                 // Field bitField0_:I
       4: ldc           #73                 // int 1048576
       6: iand
       7: ifne          36
      10: aload_0
      11: new           #192                // class java/util/ArrayList
      14: dup
      15: aload_0
      16: getfield      #23                 // Field uninterpretedOption_:Ljava/util/List;
      19: invokespecial #193                // Method java/util/ArrayList."<init>":(Ljava/util/Collection;)V
      22: putfield      #23                 // Field uninterpretedOption_:Ljava/util/List;
      25: aload_0
      26: dup
      27: getfield      #26                 // Field bitField0_:I
      30: ldc           #73                 // int 1048576
      32: ior
      33: putfield      #26                 // Field bitField0_:I
      36: return

  public java.util.List<com.google.protobuf.DescriptorProtos$UninterpretedOption> getUninterpretedOptionList();
    Code:
       0: aload_0
       1: getfield      #40                 // Field uninterpretedOptionBuilder_:Lcom/google/protobuf/RepeatedFieldBuilderV3;
       4: ifnonnull     15
       7: aload_0
       8: getfield      #23                 // Field uninterpretedOption_:Ljava/util/List;
      11: invokestatic  #74                 // Method java/util/Collections.unmodifiableList:(Ljava/util/List;)Ljava/util/List;
      14: areturn
      15: aload_0
      16: getfield      #40                 // Field uninterpretedOptionBuilder_:Lcom/google/protobuf/RepeatedFieldBuilderV3;
      19: invokevirtual #194                // Method com/google/protobuf/RepeatedFieldBuilderV3.getMessageList:()Ljava/util/List;
      22: areturn

  public int getUninterpretedOptionCount();
    Code:
       0: aload_0
       1: getfield      #40                 // Field uninterpretedOptionBuilder_:Lcom/google/protobuf/RepeatedFieldBuilderV3;
       4: ifnonnull     17
       7: aload_0
       8: getfield      #23                 // Field uninterpretedOption_:Ljava/util/List;
      11: invokeinterface #195,  1          // InterfaceMethod java/util/List.size:()I
      16: ireturn
      17: aload_0
      18: getfield      #40                 // Field uninterpretedOptionBuilder_:Lcom/google/protobuf/RepeatedFieldBuilderV3;
      21: invokevirtual #196                // Method com/google/protobuf/RepeatedFieldBuilderV3.getCount:()I
      24: ireturn

  public com.google.protobuf.DescriptorProtos$UninterpretedOption getUninterpretedOption(int);
    Code:
       0: aload_0
       1: getfield      #40                 // Field uninterpretedOptionBuilder_:Lcom/google/protobuf/RepeatedFieldBuilderV3;
       4: ifnonnull     21
       7: aload_0
       8: getfield      #23                 // Field uninterpretedOption_:Ljava/util/List;
      11: iload_1
      12: invokeinterface #197,  2          // InterfaceMethod java/util/List.get:(I)Ljava/lang/Object;
      17: checkcast     #168                // class com/google/protobuf/DescriptorProtos$UninterpretedOption
      20: areturn
      21: aload_0
      22: getfield      #40                 // Field uninterpretedOptionBuilder_:Lcom/google/protobuf/RepeatedFieldBuilderV3;
      25: iload_1
      26: invokevirtual #198                // Method com/google/protobuf/RepeatedFieldBuilderV3.getMessage:(I)Lcom/google/protobuf/AbstractMessage;
      29: checkcast     #168                // class com/google/protobuf/DescriptorProtos$UninterpretedOption
      32: areturn

  public com.google.protobuf.DescriptorProtos$FileOptions$Builder setUninterpretedOption(int, com.google.protobuf.DescriptorProtos$UninterpretedOption);
    Code:
       0: aload_0
       1: getfield      #40                 // Field uninterpretedOptionBuilder_:Lcom/google/protobuf/RepeatedFieldBuilderV3;
       4: ifnonnull     42
       7: aload_2
       8: ifnonnull     19
      11: new           #158                // class java/lang/NullPointerException
      14: dup
      15: invokespecial #159                // Method java/lang/NullPointerException."<init>":()V
      18: athrow
      19: aload_0
      20: invokespecial #144                // Method ensureUninterpretedOptionIsMutable:()V
      23: aload_0
      24: getfield      #23                 // Field uninterpretedOption_:Ljava/util/List;
      27: iload_1
      28: aload_2
      29: invokeinterface #199,  3          // InterfaceMethod java/util/List.set:(ILjava/lang/Object;)Ljava/lang/Object;
      34: pop
      35: aload_0
      36: invokevirtual #93                 // Method onChanged:()V
      39: goto          52
      42: aload_0
      43: getfield      #40                 // Field uninterpretedOptionBuilder_:Lcom/google/protobuf/RepeatedFieldBuilderV3;
      46: iload_1
      47: aload_2
      48: invokevirtual #200                // Method com/google/protobuf/RepeatedFieldBuilderV3.setMessage:(ILcom/google/protobuf/AbstractMessage;)Lcom/google/protobuf/RepeatedFieldBuilderV3;
      51: pop
      52: aload_0
      53: areturn

  public com.google.protobuf.DescriptorProtos$FileOptions$Builder setUninterpretedOption(int, com.google.protobuf.DescriptorProtos$UninterpretedOption$Builder);
    Code:
       0: aload_0
       1: getfield      #40                 // Field uninterpretedOptionBuilder_:Lcom/google/protobuf/RepeatedFieldBuilderV3;
       4: ifnonnull     33
       7: aload_0
       8: invokespecial #144                // Method ensureUninterpretedOptionIsMutable:()V
      11: aload_0
      12: getfield      #23                 // Field uninterpretedOption_:Ljava/util/List;
      15: iload_1
      16: aload_2
      17: invokevirtual #201                // Method com/google/protobuf/DescriptorProtos$UninterpretedOption$Builder.build:()Lcom/google/protobuf/DescriptorProtos$UninterpretedOption;
      20: invokeinterface #199,  3          // InterfaceMethod java/util/List.set:(ILjava/lang/Object;)Ljava/lang/Object;
      25: pop
      26: aload_0
      27: invokevirtual #93                 // Method onChanged:()V
      30: goto          46
      33: aload_0
      34: getfield      #40                 // Field uninterpretedOptionBuilder_:Lcom/google/protobuf/RepeatedFieldBuilderV3;
      37: iload_1
      38: aload_2
      39: invokevirtual #201                // Method com/google/protobuf/DescriptorProtos$UninterpretedOption$Builder.build:()Lcom/google/protobuf/DescriptorProtos$UninterpretedOption;
      42: invokevirtual #200                // Method com/google/protobuf/RepeatedFieldBuilderV3.setMessage:(ILcom/google/protobuf/AbstractMessage;)Lcom/google/protobuf/RepeatedFieldBuilderV3;
      45: pop
      46: aload_0
      47: areturn

  public com.google.protobuf.DescriptorProtos$FileOptions$Builder addUninterpretedOption(com.google.protobuf.DescriptorProtos$UninterpretedOption);
    Code:
       0: aload_0
       1: getfield      #40                 // Field uninterpretedOptionBuilder_:Lcom/google/protobuf/RepeatedFieldBuilderV3;
       4: ifnonnull     41
       7: aload_1
       8: ifnonnull     19
      11: new           #158                // class java/lang/NullPointerException
      14: dup
      15: invokespecial #159                // Method java/lang/NullPointerException."<init>":()V
      18: athrow
      19: aload_0
      20: invokespecial #144                // Method ensureUninterpretedOptionIsMutable:()V
      23: aload_0
      24: getfield      #23                 // Field uninterpretedOption_:Ljava/util/List;
      27: aload_1
      28: invokeinterface #169,  2          // InterfaceMethod java/util/List.add:(Ljava/lang/Object;)Z
      33: pop
      34: aload_0
      35: invokevirtual #93                 // Method onChanged:()V
      38: goto          50
      41: aload_0
      42: getfield      #40                 // Field uninterpretedOptionBuilder_:Lcom/google/protobuf/RepeatedFieldBuilderV3;
      45: aload_1
      46: invokevirtual #170                // Method com/google/protobuf/RepeatedFieldBuilderV3.addMessage:(Lcom/google/protobuf/AbstractMessage;)Lcom/google/protobuf/RepeatedFieldBuilderV3;
      49: pop
      50: aload_0
      51: areturn

  public com.google.protobuf.DescriptorProtos$FileOptions$Builder addUninterpretedOption(int, com.google.protobuf.DescriptorProtos$UninterpretedOption);
    Code:
       0: aload_0
       1: getfield      #40                 // Field uninterpretedOptionBuilder_:Lcom/google/protobuf/RepeatedFieldBuilderV3;
       4: ifnonnull     41
       7: aload_2
       8: ifnonnull     19
      11: new           #158                // class java/lang/NullPointerException
      14: dup
      15: invokespecial #159                // Method java/lang/NullPointerException."<init>":()V
      18: athrow
      19: aload_0
      20: invokespecial #144                // Method ensureUninterpretedOptionIsMutable:()V
      23: aload_0
      24: getfield      #23                 // Field uninterpretedOption_:Ljava/util/List;
      27: iload_1
      28: aload_2
      29: invokeinterface #202,  3          // InterfaceMethod java/util/List.add:(ILjava/lang/Object;)V
      34: aload_0
      35: invokevirtual #93                 // Method onChanged:()V
      38: goto          51
      41: aload_0
      42: getfield      #40                 // Field uninterpretedOptionBuilder_:Lcom/google/protobuf/RepeatedFieldBuilderV3;
      45: iload_1
      46: aload_2
      47: invokevirtual #203                // Method com/google/protobuf/RepeatedFieldBuilderV3.addMessage:(ILcom/google/protobuf/AbstractMessage;)Lcom/google/protobuf/RepeatedFieldBuilderV3;
      50: pop
      51: aload_0
      52: areturn

  public com.google.protobuf.DescriptorProtos$FileOptions$Builder addUninterpretedOption(com.google.protobuf.DescriptorProtos$UninterpretedOption$Builder);
    Code:
       0: aload_0
       1: getfield      #40                 // Field uninterpretedOptionBuilder_:Lcom/google/protobuf/RepeatedFieldBuilderV3;
       4: ifnonnull     32
       7: aload_0
       8: invokespecial #144                // Method ensureUninterpretedOptionIsMutable:()V
      11: aload_0
      12: getfield      #23                 // Field uninterpretedOption_:Ljava/util/List;
      15: aload_1
      16: invokevirtual #201                // Method com/google/protobuf/DescriptorProtos$UninterpretedOption$Builder.build:()Lcom/google/protobuf/DescriptorProtos$UninterpretedOption;
      19: invokeinterface #169,  2          // InterfaceMethod java/util/List.add:(Ljava/lang/Object;)Z
      24: pop
      25: aload_0
      26: invokevirtual #93                 // Method onChanged:()V
      29: goto          44
      32: aload_0
      33: getfield      #40                 // Field uninterpretedOptionBuilder_:Lcom/google/protobuf/RepeatedFieldBuilderV3;
      36: aload_1
      37: invokevirtual #201                // Method com/google/protobuf/DescriptorProtos$UninterpretedOption$Builder.build:()Lcom/google/protobuf/DescriptorProtos$UninterpretedOption;
      40: invokevirtual #170                // Method com/google/protobuf/RepeatedFieldBuilderV3.addMessage:(Lcom/google/protobuf/AbstractMessage;)Lcom/google/protobuf/RepeatedFieldBuilderV3;
      43: pop
      44: aload_0
      45: areturn

  public com.google.protobuf.DescriptorProtos$FileOptions$Builder addUninterpretedOption(int, com.google.protobuf.DescriptorProtos$UninterpretedOption$Builder);
    Code:
       0: aload_0
       1: getfield      #40                 // Field uninterpretedOptionBuilder_:Lcom/google/protobuf/RepeatedFieldBuilderV3;
       4: ifnonnull     32
       7: aload_0
       8: invokespecial #144                // Method ensureUninterpretedOptionIsMutable:()V
      11: aload_0
      12: getfield      #23                 // Field uninterpretedOption_:Ljava/util/List;
      15: iload_1
      16: aload_2
      17: invokevirtual #201                // Method com/google/protobuf/DescriptorProtos$UninterpretedOption$Builder.build:()Lcom/google/protobuf/DescriptorProtos$UninterpretedOption;
      20: invokeinterface #202,  3          // InterfaceMethod java/util/List.add:(ILjava/lang/Object;)V
      25: aload_0
      26: invokevirtual #93                 // Method onChanged:()V
      29: goto          45
      32: aload_0
      33: getfield      #40                 // Field uninterpretedOptionBuilder_:Lcom/google/protobuf/RepeatedFieldBuilderV3;
      36: iload_1
      37: aload_2
      38: invokevirtual #201                // Method com/google/protobuf/DescriptorProtos$UninterpretedOption$Builder.build:()Lcom/google/protobuf/DescriptorProtos$UninterpretedOption;
      41: invokevirtual #203                // Method com/google/protobuf/RepeatedFieldBuilderV3.addMessage:(ILcom/google/protobuf/AbstractMessage;)Lcom/google/protobuf/RepeatedFieldBuilderV3;
      44: pop
      45: aload_0
      46: areturn

  public com.google.protobuf.DescriptorProtos$FileOptions$Builder addAllUninterpretedOption(java.lang.Iterable<? extends com.google.protobuf.DescriptorProtos$UninterpretedOption>);
    Code:
       0: aload_0
       1: getfield      #40                 // Field uninterpretedOptionBuilder_:Lcom/google/protobuf/RepeatedFieldBuilderV3;
       4: ifnonnull     26
       7: aload_0
       8: invokespecial #144                // Method ensureUninterpretedOptionIsMutable:()V
      11: aload_1
      12: aload_0
      13: getfield      #23                 // Field uninterpretedOption_:Ljava/util/List;
      16: invokestatic  #204                // Method com/google/protobuf/AbstractMessageLite$Builder.addAll:(Ljava/lang/Iterable;Ljava/util/List;)V
      19: aload_0
      20: invokevirtual #93                 // Method onChanged:()V
      23: goto          35
      26: aload_0
      27: getfield      #40                 // Field uninterpretedOptionBuilder_:Lcom/google/protobuf/RepeatedFieldBuilderV3;
      30: aload_1
      31: invokevirtual #150                // Method com/google/protobuf/RepeatedFieldBuilderV3.addAllMessages:(Ljava/lang/Iterable;)Lcom/google/protobuf/RepeatedFieldBuilderV3;
      34: pop
      35: aload_0
      36: areturn

  public com.google.protobuf.DescriptorProtos$FileOptions$Builder clearUninterpretedOption();
    Code:
       0: aload_0
       1: getfield      #40                 // Field uninterpretedOptionBuilder_:Lcom/google/protobuf/RepeatedFieldBuilderV3;
       4: ifnonnull     32
       7: aload_0
       8: invokestatic  #22                 // Method java/util/Collections.emptyList:()Ljava/util/List;
      11: putfield      #23                 // Field uninterpretedOption_:Ljava/util/List;
      14: aload_0
      15: aload_0
      16: getfield      #26                 // Field bitField0_:I
      19: ldc           #42                 // int -1048577
      21: iand
      22: putfield      #26                 // Field bitField0_:I
      25: aload_0
      26: invokevirtual #93                 // Method onChanged:()V
      29: goto          39
      32: aload_0
      33: getfield      #40                 // Field uninterpretedOptionBuilder_:Lcom/google/protobuf/RepeatedFieldBuilderV3;
      36: invokevirtual #41                 // Method com/google/protobuf/RepeatedFieldBuilderV3.clear:()V
      39: aload_0
      40: areturn

  public com.google.protobuf.DescriptorProtos$FileOptions$Builder removeUninterpretedOption(int);
    Code:
       0: aload_0
       1: getfield      #40                 // Field uninterpretedOptionBuilder_:Lcom/google/protobuf/RepeatedFieldBuilderV3;
       4: ifnonnull     29
       7: aload_0
       8: invokespecial #144                // Method ensureUninterpretedOptionIsMutable:()V
      11: aload_0
      12: getfield      #23                 // Field uninterpretedOption_:Ljava/util/List;
      15: iload_1
      16: invokeinterface #205,  2          // InterfaceMethod java/util/List.remove:(I)Ljava/lang/Object;
      21: pop
      22: aload_0
      23: invokevirtual #93                 // Method onChanged:()V
      26: goto          37
      29: aload_0
      30: getfield      #40                 // Field uninterpretedOptionBuilder_:Lcom/google/protobuf/RepeatedFieldBuilderV3;
      33: iload_1
      34: invokevirtual #206                // Method com/google/protobuf/RepeatedFieldBuilderV3.remove:(I)V
      37: aload_0
      38: areturn

  public com.google.protobuf.DescriptorProtos$UninterpretedOption$Builder getUninterpretedOptionBuilder(int);
    Code:
       0: aload_0
       1: invokespecial #149                // Method getUninterpretedOptionFieldBuilder:()Lcom/google/protobuf/RepeatedFieldBuilderV3;
       4: iload_1
       5: invokevirtual #207                // Method com/google/protobuf/RepeatedFieldBuilderV3.getBuilder:(I)Lcom/google/protobuf/AbstractMessage$Builder;
       8: checkcast     #208                // class com/google/protobuf/DescriptorProtos$UninterpretedOption$Builder
      11: areturn

  public com.google.protobuf.DescriptorProtos$UninterpretedOptionOrBuilder getUninterpretedOptionOrBuilder(int);
    Code:
       0: aload_0
       1: getfield      #40                 // Field uninterpretedOptionBuilder_:Lcom/google/protobuf/RepeatedFieldBuilderV3;
       4: ifnonnull     21
       7: aload_0
       8: getfield      #23                 // Field uninterpretedOption_:Ljava/util/List;
      11: iload_1
      12: invokeinterface #197,  2          // InterfaceMethod java/util/List.get:(I)Ljava/lang/Object;
      17: checkcast     #209                // class com/google/protobuf/DescriptorProtos$UninterpretedOptionOrBuilder
      20: areturn
      21: aload_0
      22: getfield      #40                 // Field uninterpretedOptionBuilder_:Lcom/google/protobuf/RepeatedFieldBuilderV3;
      25: iload_1
      26: invokevirtual #210                // Method com/google/protobuf/RepeatedFieldBuilderV3.getMessageOrBuilder:(I)Lcom/google/protobuf/MessageOrBuilder;
      29: checkcast     #209                // class com/google/protobuf/DescriptorProtos$UninterpretedOptionOrBuilder
      32: areturn

  public java.util.List<? extends com.google.protobuf.DescriptorProtos$UninterpretedOptionOrBuilder> getUninterpretedOptionOrBuilderList();
    Code:
       0: aload_0
       1: getfield      #40                 // Field uninterpretedOptionBuilder_:Lcom/google/protobuf/RepeatedFieldBuilderV3;
       4: ifnull        15
       7: aload_0
       8: getfield      #40                 // Field uninterpretedOptionBuilder_:Lcom/google/protobuf/RepeatedFieldBuilderV3;
      11: invokevirtual #211                // Method com/google/protobuf/RepeatedFieldBuilderV3.getMessageOrBuilderList:()Ljava/util/List;
      14: areturn
      15: aload_0
      16: getfield      #23                 // Field uninterpretedOption_:Ljava/util/List;
      19: invokestatic  #74                 // Method java/util/Collections.unmodifiableList:(Ljava/util/List;)Ljava/util/List;
      22: areturn

  public com.google.protobuf.DescriptorProtos$UninterpretedOption$Builder addUninterpretedOptionBuilder();
    Code:
       0: aload_0
       1: invokespecial #149                // Method getUninterpretedOptionFieldBuilder:()Lcom/google/protobuf/RepeatedFieldBuilderV3;
       4: invokestatic  #212                // Method com/google/protobuf/DescriptorProtos$UninterpretedOption.getDefaultInstance:()Lcom/google/protobuf/DescriptorProtos$UninterpretedOption;
       7: invokevirtual #213                // Method com/google/protobuf/RepeatedFieldBuilderV3.addBuilder:(Lcom/google/protobuf/AbstractMessage;)Lcom/google/protobuf/AbstractMessage$Builder;
      10: checkcast     #208                // class com/google/protobuf/DescriptorProtos$UninterpretedOption$Builder
      13: areturn

  public com.google.protobuf.DescriptorProtos$UninterpretedOption$Builder addUninterpretedOptionBuilder(int);
    Code:
       0: aload_0
       1: invokespecial #149                // Method getUninterpretedOptionFieldBuilder:()Lcom/google/protobuf/RepeatedFieldBuilderV3;
       4: iload_1
       5: invokestatic  #212                // Method com/google/protobuf/DescriptorProtos$UninterpretedOption.getDefaultInstance:()Lcom/google/protobuf/DescriptorProtos$UninterpretedOption;
       8: invokevirtual #214                // Method com/google/protobuf/RepeatedFieldBuilderV3.addBuilder:(ILcom/google/protobuf/AbstractMessage;)Lcom/google/protobuf/AbstractMessage$Builder;
      11: checkcast     #208                // class com/google/protobuf/DescriptorProtos$UninterpretedOption$Builder
      14: areturn

  public java.util.List<com.google.protobuf.DescriptorProtos$UninterpretedOption$Builder> getUninterpretedOptionBuilderList();
    Code:
       0: aload_0
       1: invokespecial #149                // Method getUninterpretedOptionFieldBuilder:()Lcom/google/protobuf/RepeatedFieldBuilderV3;
       4: invokevirtual #215                // Method com/google/protobuf/RepeatedFieldBuilderV3.getBuilderList:()Ljava/util/List;
       7: areturn

  private com.google.protobuf.RepeatedFieldBuilderV3<com.google.protobuf.DescriptorProtos$UninterpretedOption, com.google.protobuf.DescriptorProtos$UninterpretedOption$Builder, com.google.protobuf.DescriptorProtos$UninterpretedOptionOrBuilder> getUninterpretedOptionFieldBuilder();
    Code:
       0: aload_0
       1: getfield      #40                 // Field uninterpretedOptionBuilder_:Lcom/google/protobuf/RepeatedFieldBuilderV3;
       4: ifnonnull     50
       7: aload_0
       8: new           #216                // class com/google/protobuf/RepeatedFieldBuilderV3
      11: dup
      12: aload_0
      13: getfield      #23                 // Field uninterpretedOption_:Ljava/util/List;
      16: aload_0
      17: getfield      #26                 // Field bitField0_:I
      20: ldc           #73                 // int 1048576
      22: iand
      23: ifeq          30
      26: iconst_1
      27: goto          31
      30: iconst_0
      31: aload_0
      32: invokevirtual #217                // Method getParentForChildren:()Lcom/google/protobuf/GeneratedMessageV3$BuilderParent;
      35: aload_0
      36: invokevirtual #218                // Method isClean:()Z
      39: invokespecial #219                // Method com/google/protobuf/RepeatedFieldBuilderV3."<init>":(Ljava/util/List;ZLcom/google/protobuf/AbstractMessage$BuilderParent;Z)V
      42: putfield      #40                 // Field uninterpretedOptionBuilder_:Lcom/google/protobuf/RepeatedFieldBuilderV3;
      45: aload_0
      46: aconst_null
      47: putfield      #23                 // Field uninterpretedOption_:Ljava/util/List;
      50: aload_0
      51: getfield      #40                 // Field uninterpretedOptionBuilder_:Lcom/google/protobuf/RepeatedFieldBuilderV3;
      54: areturn

  public final com.google.protobuf.DescriptorProtos$FileOptions$Builder setUnknownFields(com.google.protobuf.UnknownFieldSet);
    Code:
       0: aload_0
       1: aload_1
       2: invokespecial #220                // Method com/google/protobuf/GeneratedMessageV3$ExtendableBuilder.setUnknownFields:(Lcom/google/protobuf/UnknownFieldSet;)Lcom/google/protobuf/GeneratedMessageV3$Builder;
       5: checkcast     #6                  // class com/google/protobuf/DescriptorProtos$FileOptions$Builder
       8: areturn

  public final com.google.protobuf.DescriptorProtos$FileOptions$Builder mergeUnknownFields(com.google.protobuf.UnknownFieldSet);
    Code:
       0: aload_0
       1: aload_1
       2: invokespecial #221                // Method com/google/protobuf/GeneratedMessageV3$ExtendableBuilder.mergeUnknownFields:(Lcom/google/protobuf/UnknownFieldSet;)Lcom/google/protobuf/GeneratedMessageV3$Builder;
       5: checkcast     #6                  // class com/google/protobuf/DescriptorProtos$FileOptions$Builder
       8: areturn

  public com.google.protobuf.GeneratedMessageV3$ExtendableBuilder addRepeatedField(com.google.protobuf.Descriptors$FieldDescriptor, java.lang.Object);
    Code:
       0: aload_0
       1: aload_1
       2: aload_2
       3: invokevirtual #222                // Method addRepeatedField:(Lcom/google/protobuf/Descriptors$FieldDescriptor;Ljava/lang/Object;)Lcom/google/protobuf/DescriptorProtos$FileOptions$Builder;
       6: areturn

  public com.google.protobuf.GeneratedMessageV3$ExtendableBuilder setRepeatedField(com.google.protobuf.Descriptors$FieldDescriptor, int, java.lang.Object);
    Code:
       0: aload_0
       1: aload_1
       2: iload_2
       3: aload_3
       4: invokevirtual #223                // Method setRepeatedField:(Lcom/google/protobuf/Descriptors$FieldDescriptor;ILjava/lang/Object;)Lcom/google/protobuf/DescriptorProtos$FileOptions$Builder;
       7: areturn

  public com.google.protobuf.GeneratedMessageV3$ExtendableBuilder clearField(com.google.protobuf.Descriptors$FieldDescriptor);
    Code:
       0: aload_0
       1: aload_1
       2: invokevirtual #224                // Method clearField:(Lcom/google/protobuf/Descriptors$FieldDescriptor;)Lcom/google/protobuf/DescriptorProtos$FileOptions$Builder;
       5: areturn

  public com.google.protobuf.GeneratedMessageV3$ExtendableBuilder setField(com.google.protobuf.Descriptors$FieldDescriptor, java.lang.Object);
    Code:
       0: aload_0
       1: aload_1
       2: aload_2
       3: invokevirtual #225                // Method setField:(Lcom/google/protobuf/Descriptors$FieldDescriptor;Ljava/lang/Object;)Lcom/google/protobuf/DescriptorProtos$FileOptions$Builder;
       6: areturn

  public com.google.protobuf.GeneratedMessageV3$ExtendableBuilder clearExtension(com.google.protobuf.GeneratedMessage$GeneratedExtension);
    Code:
       0: aload_0
       1: aload_1
       2: invokevirtual #226                // Method clearExtension:(Lcom/google/protobuf/GeneratedMessage$GeneratedExtension;)Lcom/google/protobuf/DescriptorProtos$FileOptions$Builder;
       5: areturn

  public com.google.protobuf.GeneratedMessageV3$ExtendableBuilder addExtension(com.google.protobuf.GeneratedMessage$GeneratedExtension, java.lang.Object);
    Code:
       0: aload_0
       1: aload_1
       2: aload_2
       3: invokevirtual #227                // Method addExtension:(Lcom/google/protobuf/GeneratedMessage$GeneratedExtension;Ljava/lang/Object;)Lcom/google/protobuf/DescriptorProtos$FileOptions$Builder;
       6: areturn

  public com.google.protobuf.GeneratedMessageV3$ExtendableBuilder setExtension(com.google.protobuf.GeneratedMessage$GeneratedExtension, int, java.lang.Object);
    Code:
       0: aload_0
       1: aload_1
       2: iload_2
       3: aload_3
       4: invokevirtual #228                // Method setExtension:(Lcom/google/protobuf/GeneratedMessage$GeneratedExtension;ILjava/lang/Object;)Lcom/google/protobuf/DescriptorProtos$FileOptions$Builder;
       7: areturn

  public com.google.protobuf.GeneratedMessageV3$ExtendableBuilder setExtension(com.google.protobuf.GeneratedMessage$GeneratedExtension, java.lang.Object);
    Code:
       0: aload_0
       1: aload_1
       2: aload_2
       3: invokevirtual #229                // Method setExtension:(Lcom/google/protobuf/GeneratedMessage$GeneratedExtension;Ljava/lang/Object;)Lcom/google/protobuf/DescriptorProtos$FileOptions$Builder;
       6: areturn

  public com.google.protobuf.GeneratedMessageV3$ExtendableBuilder clear();
    Code:
       0: aload_0
       1: invokevirtual #230                // Method clear:()Lcom/google/protobuf/DescriptorProtos$FileOptions$Builder;
       4: areturn

  public com.google.protobuf.Message getDefaultInstanceForType();
    Code:
       0: aload_0
       1: invokevirtual #231                // Method getDefaultInstanceForType:()Lcom/google/protobuf/DescriptorProtos$FileOptions;
       4: areturn

  public com.google.protobuf.MessageLite getDefaultInstanceForType();
    Code:
       0: aload_0
       1: invokevirtual #231                // Method getDefaultInstanceForType:()Lcom/google/protobuf/DescriptorProtos$FileOptions;
       4: areturn

  public com.google.protobuf.GeneratedMessageV3$Builder mergeUnknownFields(com.google.protobuf.UnknownFieldSet);
    Code:
       0: aload_0
       1: aload_1
       2: invokevirtual #153                // Method mergeUnknownFields:(Lcom/google/protobuf/UnknownFieldSet;)Lcom/google/protobuf/DescriptorProtos$FileOptions$Builder;
       5: areturn

  public com.google.protobuf.GeneratedMessageV3$Builder setUnknownFields(com.google.protobuf.UnknownFieldSet);
    Code:
       0: aload_0
       1: aload_1
       2: invokevirtual #232                // Method setUnknownFields:(Lcom/google/protobuf/UnknownFieldSet;)Lcom/google/protobuf/DescriptorProtos$FileOptions$Builder;
       5: areturn

  public com.google.protobuf.GeneratedMessageV3$Builder addRepeatedField(com.google.protobuf.Descriptors$FieldDescriptor, java.lang.Object);
    Code:
       0: aload_0
       1: aload_1
       2: aload_2
       3: invokevirtual #222                // Method addRepeatedField:(Lcom/google/protobuf/Descriptors$FieldDescriptor;Ljava/lang/Object;)Lcom/google/protobuf/DescriptorProtos$FileOptions$Builder;
       6: areturn

  public com.google.protobuf.GeneratedMessageV3$Builder setRepeatedField(com.google.protobuf.Descriptors$FieldDescriptor, int, java.lang.Object);
    Code:
       0: aload_0
       1: aload_1
       2: iload_2
       3: aload_3
       4: invokevirtual #223                // Method setRepeatedField:(Lcom/google/protobuf/Descriptors$FieldDescriptor;ILjava/lang/Object;)Lcom/google/protobuf/DescriptorProtos$FileOptions$Builder;
       7: areturn

  public com.google.protobuf.GeneratedMessageV3$Builder clearOneof(com.google.protobuf.Descriptors$OneofDescriptor);
    Code:
       0: aload_0
       1: aload_1
       2: invokevirtual #233                // Method clearOneof:(Lcom/google/protobuf/Descriptors$OneofDescriptor;)Lcom/google/protobuf/DescriptorProtos$FileOptions$Builder;
       5: areturn

  public com.google.protobuf.GeneratedMessageV3$Builder clearField(com.google.protobuf.Descriptors$FieldDescriptor);
    Code:
       0: aload_0
       1: aload_1
       2: invokevirtual #224                // Method clearField:(Lcom/google/protobuf/Descriptors$FieldDescriptor;)Lcom/google/protobuf/DescriptorProtos$FileOptions$Builder;
       5: areturn

  public com.google.protobuf.GeneratedMessageV3$Builder setField(com.google.protobuf.Descriptors$FieldDescriptor, java.lang.Object);
    Code:
       0: aload_0
       1: aload_1
       2: aload_2
       3: invokevirtual #225                // Method setField:(Lcom/google/protobuf/Descriptors$FieldDescriptor;Ljava/lang/Object;)Lcom/google/protobuf/DescriptorProtos$FileOptions$Builder;
       6: areturn

  public com.google.protobuf.GeneratedMessageV3$Builder clear();
    Code:
       0: aload_0
       1: invokevirtual #230                // Method clear:()Lcom/google/protobuf/DescriptorProtos$FileOptions$Builder;
       4: areturn

  public com.google.protobuf.GeneratedMessageV3$Builder clone();
    Code:
       0: aload_0
       1: invokevirtual #234                // Method clone:()Lcom/google/protobuf/DescriptorProtos$FileOptions$Builder;
       4: areturn

  public com.google.protobuf.AbstractMessage$Builder mergeUnknownFields(com.google.protobuf.UnknownFieldSet);
    Code:
       0: aload_0
       1: aload_1
       2: invokevirtual #153                // Method mergeUnknownFields:(Lcom/google/protobuf/UnknownFieldSet;)Lcom/google/protobuf/DescriptorProtos$FileOptions$Builder;
       5: areturn

  public com.google.protobuf.AbstractMessage$Builder mergeFrom(com.google.protobuf.CodedInputStream, com.google.protobuf.ExtensionRegistryLite) throws java.io.IOException;
    Code:
       0: aload_0
       1: aload_1
       2: aload_2
       3: invokevirtual #235                // Method mergeFrom:(Lcom/google/protobuf/CodedInputStream;Lcom/google/protobuf/ExtensionRegistryLite;)Lcom/google/protobuf/DescriptorProtos$FileOptions$Builder;
       6: areturn

  public com.google.protobuf.AbstractMessage$Builder mergeFrom(com.google.protobuf.Message);
    Code:
       0: aload_0
       1: aload_1
       2: invokevirtual #236                // Method mergeFrom:(Lcom/google/protobuf/Message;)Lcom/google/protobuf/DescriptorProtos$FileOptions$Builder;
       5: areturn

  public com.google.protobuf.AbstractMessage$Builder clear();
    Code:
       0: aload_0
       1: invokevirtual #230                // Method clear:()Lcom/google/protobuf/DescriptorProtos$FileOptions$Builder;
       4: areturn

  public com.google.protobuf.AbstractMessage$Builder clearOneof(com.google.protobuf.Descriptors$OneofDescriptor);
    Code:
       0: aload_0
       1: aload_1
       2: invokevirtual #233                // Method clearOneof:(Lcom/google/protobuf/Descriptors$OneofDescriptor;)Lcom/google/protobuf/DescriptorProtos$FileOptions$Builder;
       5: areturn

  public com.google.protobuf.AbstractMessage$Builder clone();
    Code:
       0: aload_0
       1: invokevirtual #234                // Method clone:()Lcom/google/protobuf/DescriptorProtos$FileOptions$Builder;
       4: areturn

  public com.google.protobuf.Message$Builder mergeUnknownFields(com.google.protobuf.UnknownFieldSet);
    Code:
       0: aload_0
       1: aload_1
       2: invokevirtual #153                // Method mergeUnknownFields:(Lcom/google/protobuf/UnknownFieldSet;)Lcom/google/protobuf/DescriptorProtos$FileOptions$Builder;
       5: areturn

  public com.google.protobuf.Message$Builder setUnknownFields(com.google.protobuf.UnknownFieldSet);
    Code:
       0: aload_0
       1: aload_1
       2: invokevirtual #232                // Method setUnknownFields:(Lcom/google/protobuf/UnknownFieldSet;)Lcom/google/protobuf/DescriptorProtos$FileOptions$Builder;
       5: areturn

  public com.google.protobuf.Message$Builder addRepeatedField(com.google.protobuf.Descriptors$FieldDescriptor, java.lang.Object);
    Code:
       0: aload_0
       1: aload_1
       2: aload_2
       3: invokevirtual #222                // Method addRepeatedField:(Lcom/google/protobuf/Descriptors$FieldDescriptor;Ljava/lang/Object;)Lcom/google/protobuf/DescriptorProtos$FileOptions$Builder;
       6: areturn

  public com.google.protobuf.Message$Builder setRepeatedField(com.google.protobuf.Descriptors$FieldDescriptor, int, java.lang.Object);
    Code:
       0: aload_0
       1: aload_1
       2: iload_2
       3: aload_3
       4: invokevirtual #223                // Method setRepeatedField:(Lcom/google/protobuf/Descriptors$FieldDescriptor;ILjava/lang/Object;)Lcom/google/protobuf/DescriptorProtos$FileOptions$Builder;
       7: areturn

  public com.google.protobuf.Message$Builder clearOneof(com.google.protobuf.Descriptors$OneofDescriptor);
    Code:
       0: aload_0
       1: aload_1
       2: invokevirtual #233                // Method clearOneof:(Lcom/google/protobuf/Descriptors$OneofDescriptor;)Lcom/google/protobuf/DescriptorProtos$FileOptions$Builder;
       5: areturn

  public com.google.protobuf.Message$Builder clearField(com.google.protobuf.Descriptors$FieldDescriptor);
    Code:
       0: aload_0
       1: aload_1
       2: invokevirtual #224                // Method clearField:(Lcom/google/protobuf/Descriptors$FieldDescriptor;)Lcom/google/protobuf/DescriptorProtos$FileOptions$Builder;
       5: areturn

  public com.google.protobuf.Message$Builder setField(com.google.protobuf.Descriptors$FieldDescriptor, java.lang.Object);
    Code:
       0: aload_0
       1: aload_1
       2: aload_2
       3: invokevirtual #225                // Method setField:(Lcom/google/protobuf/Descriptors$FieldDescriptor;Ljava/lang/Object;)Lcom/google/protobuf/DescriptorProtos$FileOptions$Builder;
       6: areturn

  public com.google.protobuf.Message$Builder mergeFrom(com.google.protobuf.CodedInputStream, com.google.protobuf.ExtensionRegistryLite) throws java.io.IOException;
    Code:
       0: aload_0
       1: aload_1
       2: aload_2
       3: invokevirtual #235                // Method mergeFrom:(Lcom/google/protobuf/CodedInputStream;Lcom/google/protobuf/ExtensionRegistryLite;)Lcom/google/protobuf/DescriptorProtos$FileOptions$Builder;
       6: areturn

  public com.google.protobuf.Message$Builder clone();
    Code:
       0: aload_0
       1: invokevirtual #234                // Method clone:()Lcom/google/protobuf/DescriptorProtos$FileOptions$Builder;
       4: areturn

  public com.google.protobuf.Message buildPartial();
    Code:
       0: aload_0
       1: invokevirtual #44                 // Method buildPartial:()Lcom/google/protobuf/DescriptorProtos$FileOptions;
       4: areturn

  public com.google.protobuf.Message build();
    Code:
       0: aload_0
       1: invokevirtual #237                // Method build:()Lcom/google/protobuf/DescriptorProtos$FileOptions;
       4: areturn

  public com.google.protobuf.Message$Builder mergeFrom(com.google.protobuf.Message);
    Code:
       0: aload_0
       1: aload_1
       2: invokevirtual #236                // Method mergeFrom:(Lcom/google/protobuf/Message;)Lcom/google/protobuf/DescriptorProtos$FileOptions$Builder;
       5: areturn

  public com.google.protobuf.Message$Builder clear();
    Code:
       0: aload_0
       1: invokevirtual #230                // Method clear:()Lcom/google/protobuf/DescriptorProtos$FileOptions$Builder;
       4: areturn

  public com.google.protobuf.MessageLite$Builder mergeFrom(com.google.protobuf.CodedInputStream, com.google.protobuf.ExtensionRegistryLite) throws java.io.IOException;
    Code:
       0: aload_0
       1: aload_1
       2: aload_2
       3: invokevirtual #235                // Method mergeFrom:(Lcom/google/protobuf/CodedInputStream;Lcom/google/protobuf/ExtensionRegistryLite;)Lcom/google/protobuf/DescriptorProtos$FileOptions$Builder;
       6: areturn

  public com.google.protobuf.MessageLite$Builder clone();
    Code:
       0: aload_0
       1: invokevirtual #234                // Method clone:()Lcom/google/protobuf/DescriptorProtos$FileOptions$Builder;
       4: areturn

  public com.google.protobuf.MessageLite buildPartial();
    Code:
       0: aload_0
       1: invokevirtual #44                 // Method buildPartial:()Lcom/google/protobuf/DescriptorProtos$FileOptions;
       4: areturn

  public com.google.protobuf.MessageLite build();
    Code:
       0: aload_0
       1: invokevirtual #237                // Method build:()Lcom/google/protobuf/DescriptorProtos$FileOptions;
       4: areturn

  public com.google.protobuf.MessageLite$Builder clear();
    Code:
       0: aload_0
       1: invokevirtual #230                // Method clear:()Lcom/google/protobuf/DescriptorProtos$FileOptions$Builder;
       4: areturn

  public com.google.protobuf.AbstractMessageLite$Builder mergeFrom(com.google.protobuf.CodedInputStream, com.google.protobuf.ExtensionRegistryLite) throws java.io.IOException;
    Code:
       0: aload_0
       1: aload_1
       2: aload_2
       3: invokevirtual #235                // Method mergeFrom:(Lcom/google/protobuf/CodedInputStream;Lcom/google/protobuf/ExtensionRegistryLite;)Lcom/google/protobuf/DescriptorProtos$FileOptions$Builder;
       6: areturn

  public com.google.protobuf.AbstractMessageLite$Builder clone();
    Code:
       0: aload_0
       1: invokevirtual #234                // Method clone:()Lcom/google/protobuf/DescriptorProtos$FileOptions$Builder;
       4: areturn

  public java.lang.Object clone() throws java.lang.CloneNotSupportedException;
    Code:
       0: aload_0
       1: invokevirtual #234                // Method clone:()Lcom/google/protobuf/DescriptorProtos$FileOptions$Builder;
       4: areturn

  com.google.protobuf.DescriptorProtos$FileOptions$Builder(com.google.protobuf.DescriptorProtos$1);
    Code:
       0: aload_0
       1: invokespecial #2                  // Method "<init>":()V
       4: return

  com.google.protobuf.DescriptorProtos$FileOptions$Builder(com.google.protobuf.GeneratedMessageV3$BuilderParent, com.google.protobuf.DescriptorProtos$1);
    Code:
       0: aload_0
       1: aload_1
       2: invokespecial #1                  // Method "<init>":(Lcom/google/protobuf/GeneratedMessageV3$BuilderParent;)V
       5: return
}
