Compiled from "MethodDelegationBinder.java"
public final class org.assertj.core.internal.bytebuddy.implementation.bind.MethodDelegationBinder$MethodInvoker$Simple extends java.lang.Enum<org.assertj.core.internal.bytebuddy.implementation.bind.MethodDelegationBinder$MethodInvoker$Simple> implements org.assertj.core.internal.bytebuddy.implementation.bind.MethodDelegationBinder$MethodInvoker {
  public static final org.assertj.core.internal.bytebuddy.implementation.bind.MethodDelegationBinder$MethodInvoker$Simple INSTANCE;

  private static final org.assertj.core.internal.bytebuddy.implementation.bind.MethodDelegationBinder$MethodInvoker$Simple[] $VALUES;

  public static org.assertj.core.internal.bytebuddy.implementation.bind.MethodDelegationBinder$MethodInvoker$Simple[] values();
    Code:
       0: getstatic     #25                 // Field $VALUES:[Lorg/assertj/core/internal/bytebuddy/implementation/bind/MethodDelegationBinder$MethodInvoker$Simple;
       3: invokevirtual #30                 // Method "[Lorg/assertj/core/internal/bytebuddy/implementation/bind/MethodDelegationBinder$MethodInvoker$Simple;".clone:()Ljava/lang/Object;
       6: checkcast     #26                 // class "[Lorg/assertj/core/internal/bytebuddy/implementation/bind/MethodDelegationBinder$MethodInvoker$Simple;"
       9: areturn

  public static org.assertj.core.internal.bytebuddy.implementation.bind.MethodDelegationBinder$MethodInvoker$Simple valueOf(java.lang.String);
    Code:
       0: ldc           #2                  // class org/assertj/core/internal/bytebuddy/implementation/bind/MethodDelegationBinder$MethodInvoker$Simple
       2: aload_0
       3: invokestatic  #35                 // Method java/lang/Enum.valueOf:(Ljava/lang/Class;Ljava/lang/String;)Ljava/lang/Enum;
       6: checkcast     #2                  // class org/assertj/core/internal/bytebuddy/implementation/bind/MethodDelegationBinder$MethodInvoker$Simple
       9: areturn

  private org.assertj.core.internal.bytebuddy.implementation.bind.MethodDelegationBinder$MethodInvoker$Simple();
    Code:
       0: aload_0
       1: aload_1
       2: iload_2
       3: invokespecial #41                 // Method java/lang/Enum."<init>":(Ljava/lang/String;I)V
       6: return

  public org.assertj.core.internal.bytebuddy.implementation.bytecode.StackManipulation invoke(org.assertj.core.internal.bytebuddy.description.method.MethodDescription);
    Code:
       0: aload_1
       1: invokestatic  #47                 // Method org/assertj/core/internal/bytebuddy/implementation/bytecode/member/MethodInvocation.invoke:(Lorg/assertj/core/internal/bytebuddy/description/method/MethodDescription;)Lorg/assertj/core/internal/bytebuddy/implementation/bytecode/member/MethodInvocation$WithImplicitInvocationTargetType;
       4: areturn

  static {};
    Code:
       0: new           #2                  // class org/assertj/core/internal/bytebuddy/implementation/bind/MethodDelegationBinder$MethodInvoker$Simple
       3: dup
       4: ldc           #52                 // String INSTANCE
       6: iconst_0
       7: invokespecial #53                 // Method "<init>":(Ljava/lang/String;I)V
      10: putstatic     #55                 // Field INSTANCE:Lorg/assertj/core/internal/bytebuddy/implementation/bind/MethodDelegationBinder$MethodInvoker$Simple;
      13: iconst_1
      14: anewarray     #2                  // class org/assertj/core/internal/bytebuddy/implementation/bind/MethodDelegationBinder$MethodInvoker$Simple
      17: dup
      18: iconst_0
      19: getstatic     #55                 // Field INSTANCE:Lorg/assertj/core/internal/bytebuddy/implementation/bind/MethodDelegationBinder$MethodInvoker$Simple;
      22: aastore
      23: putstatic     #25                 // Field $VALUES:[Lorg/assertj/core/internal/bytebuddy/implementation/bind/MethodDelegationBinder$MethodInvoker$Simple;
      26: return
}
