Compiled from "MetadataNotFoundException.java"
public class org.sonatype.aether.transfer.MetadataNotFoundException extends org.sonatype.aether.transfer.MetadataTransferException {
  public org.sonatype.aether.transfer.MetadataNotFoundException(org.sonatype.aether.metadata.Metadata, org.sonatype.aether.repository.LocalRepository);
    Code:
       0: aload_0
       1: aload_1
       2: aconst_null
       3: new           #1                  // class java/lang/StringBuilder
       6: dup
       7: invokespecial #2                  // Method java/lang/StringBuilder."<init>":()V
      10: ldc           #3                  // String Could not find metadata
      12: invokevirtual #4                  // Method java/lang/StringBuilder.append:(Ljava/lang/String;)Ljava/lang/StringBuilder;
      15: aload_1
      16: invokevirtual #5                  // Method java/lang/StringBuilder.append:(Ljava/lang/Object;)Ljava/lang/StringBuilder;
      19: ldc           #6                  // String  in
      21: aload_2
      22: invokestatic  #7                  // Method getString:(Ljava/lang/String;Lorg/sonatype/aether/repository/LocalRepository;)Ljava/lang/String;
      25: invokevirtual #4                  // Method java/lang/StringBuilder.append:(Ljava/lang/String;)Ljava/lang/StringBuilder;
      28: invokevirtual #8                  // Method java/lang/StringBuilder.toString:()Ljava/lang/String;
      31: invokespecial #9                  // Method org/sonatype/aether/transfer/MetadataTransferException."<init>":(Lorg/sonatype/aether/metadata/Metadata;Lorg/sonatype/aether/repository/RemoteRepository;Ljava/lang/String;)V
      34: return

  private static java.lang.String getString(java.lang.String, org.sonatype.aether.repository.LocalRepository);
    Code:
       0: aload_1
       1: ifnonnull     7
       4: ldc           #10                 // String
       6: areturn
       7: new           #1                  // class java/lang/StringBuilder
      10: dup
      11: invokespecial #2                  // Method java/lang/StringBuilder."<init>":()V
      14: aload_0
      15: invokevirtual #4                  // Method java/lang/StringBuilder.append:(Ljava/lang/String;)Ljava/lang/StringBuilder;
      18: aload_1
      19: invokevirtual #11                 // Method org/sonatype/aether/repository/LocalRepository.getId:()Ljava/lang/String;
      22: invokevirtual #4                  // Method java/lang/StringBuilder.append:(Ljava/lang/String;)Ljava/lang/StringBuilder;
      25: ldc           #12                 // String  (
      27: invokevirtual #4                  // Method java/lang/StringBuilder.append:(Ljava/lang/String;)Ljava/lang/StringBuilder;
      30: aload_1
      31: invokevirtual #13                 // Method org/sonatype/aether/repository/LocalRepository.getBasedir:()Ljava/io/File;
      34: invokevirtual #5                  // Method java/lang/StringBuilder.append:(Ljava/lang/Object;)Ljava/lang/StringBuilder;
      37: ldc           #14                 // String )
      39: invokevirtual #4                  // Method java/lang/StringBuilder.append:(Ljava/lang/String;)Ljava/lang/StringBuilder;
      42: invokevirtual #8                  // Method java/lang/StringBuilder.toString:()Ljava/lang/String;
      45: areturn

  public org.sonatype.aether.transfer.MetadataNotFoundException(org.sonatype.aether.metadata.Metadata, org.sonatype.aether.repository.RemoteRepository);
    Code:
       0: aload_0
       1: aload_1
       2: aload_2
       3: new           #1                  // class java/lang/StringBuilder
       6: dup
       7: invokespecial #2                  // Method java/lang/StringBuilder."<init>":()V
      10: ldc           #3                  // String Could not find metadata
      12: invokevirtual #4                  // Method java/lang/StringBuilder.append:(Ljava/lang/String;)Ljava/lang/StringBuilder;
      15: aload_1
      16: invokevirtual #5                  // Method java/lang/StringBuilder.append:(Ljava/lang/Object;)Ljava/lang/StringBuilder;
      19: ldc           #6                  // String  in
      21: aload_2
      22: invokestatic  #15                 // Method getString:(Ljava/lang/String;Lorg/sonatype/aether/repository/RemoteRepository;)Ljava/lang/String;
      25: invokevirtual #4                  // Method java/lang/StringBuilder.append:(Ljava/lang/String;)Ljava/lang/StringBuilder;
      28: invokevirtual #8                  // Method java/lang/StringBuilder.toString:()Ljava/lang/String;
      31: invokespecial #9                  // Method org/sonatype/aether/transfer/MetadataTransferException."<init>":(Lorg/sonatype/aether/metadata/Metadata;Lorg/sonatype/aether/repository/RemoteRepository;Ljava/lang/String;)V
      34: return

  public org.sonatype.aether.transfer.MetadataNotFoundException(org.sonatype.aether.metadata.Metadata, org.sonatype.aether.repository.RemoteRepository, java.lang.String);
    Code:
       0: aload_0
       1: aload_1
       2: aload_2
       3: aload_3
       4: invokespecial #9                  // Method org/sonatype/aether/transfer/MetadataTransferException."<init>":(Lorg/sonatype/aether/metadata/Metadata;Lorg/sonatype/aether/repository/RemoteRepository;Ljava/lang/String;)V
       7: return
}
