Compiled from "WSSConstants.java"
public class org.apache.wss4j.stax.ext.WSSConstants extends org.apache.xml.security.stax.ext.XMLSecurityConstants {
  public static final java.lang.String TRANSPORT_SECURITY_ACTIVE;

  public static final java.lang.String TIMESTAMP_PROCESSED;

  public static final java.lang.String PROP_ALLOW_RSA15_KEYTRANSPORT_ALGORITHM;

  public static final java.lang.String PROP_ALLOW_USERNAMETOKEN_NOPASSWORD;

  public static final java.lang.String NS_WSSE10;

  public static final java.lang.String NS_WSSE11;

  public static final java.lang.String NS_WSU10;

  public static final java.lang.String NS_SOAP11;

  public static final java.lang.String NS_SOAP12;

  public static final java.lang.String NS_WST;

  public static final java.lang.String NS_WST_05_12;

  public static final java.lang.String NS_WSC_SCT;

  public static final java.lang.String NS_SAML;

  public static final java.lang.String NS_SAML2;

  public static final java.lang.String PREFIX_SOAPENV;

  public static final java.lang.String TAG_soap_Envelope_LocalName;

  public static final java.lang.String TAG_soap_Header_LocalName;

  public static final java.lang.String TAG_soap_Body_LocalName;

  public static final javax.xml.namespace.QName TAG_soap11_Envelope;

  public static final javax.xml.namespace.QName TAG_soap11_Header;

  public static final javax.xml.namespace.QName TAG_soap11_Body;

  public static final javax.xml.namespace.QName ATT_soap11_Actor;

  public static final javax.xml.namespace.QName ATT_soap11_MustUnderstand;

  public static final javax.xml.namespace.QName TAG_soap12_Envelope;

  public static final javax.xml.namespace.QName TAG_soap12_Header;

  public static final javax.xml.namespace.QName TAG_soap12_Body;

  public static final javax.xml.namespace.QName ATT_soap12_Role;

  public static final javax.xml.namespace.QName ATT_soap12_MustUnderstand;

  public static final java.lang.String PREFIX_WSSE;

  public static final java.lang.String PREFIX_WSSE11;

  public static final javax.xml.namespace.QName TAG_wsse_Security;

  public static final javax.xml.namespace.QName TAG_wsse_SecurityTokenReference;

  public static final javax.xml.namespace.QName TAG_wsse_Reference;

  public static final javax.xml.namespace.QName ATT_wsse_Usage;

  public static final javax.xml.namespace.QName ATT_wsse11_TokenType;

  public static final javax.xml.namespace.QName TAG_wsse_KeyIdentifier;

  public static final javax.xml.namespace.QName ATT_NULL_EncodingType;

  public static final javax.xml.namespace.QName ATT_NULL_ValueType;

  public static final javax.xml.namespace.QName TAG_wsse_BinarySecurityToken;

  public static final java.lang.String PREFIX_WSU;

  public static final javax.xml.namespace.QName ATT_wsu_Id;

  public static final javax.xml.namespace.QName TAG_wsse11_EncryptedHeader;

  public static final javax.xml.namespace.QName TAG_wsse_TransformationParameters;

  public static final javax.xml.namespace.QName TAG_wsu_Timestamp;

  public static final javax.xml.namespace.QName TAG_wsu_Created;

  public static final javax.xml.namespace.QName TAG_wsu_Expires;

  public static final java.lang.String NS10_SOAPMESSAGE_SECURITY;

  public static final java.lang.String NS11_SOAPMESSAGE_SECURITY;

  public static final java.lang.String NS_X509TOKEN_PROFILE;

  public static final java.lang.String NS_X509_V3_TYPE;

  public static final java.lang.String NS_X509PKIPathv1;

  public static final java.lang.String NS_X509SubjectKeyIdentifier;

  public static final java.lang.String NS_THUMBPRINT;

  public static final java.lang.String NS_ENCRYPTED_KEY_SHA1;

  public static final java.lang.String SOAPMESSAGE_NS10_BASE64_ENCODING;

  public static final javax.xml.namespace.QName TAG_wsse_UsernameToken;

  public static final javax.xml.namespace.QName TAG_wsse_Username;

  public static final javax.xml.namespace.QName TAG_wsse_Password;

  public static final javax.xml.namespace.QName TAG_wsse_Nonce;

  public static final javax.xml.namespace.QName TAG_wsse11_Salt;

  public static final javax.xml.namespace.QName TAG_wsse11_Iteration;

  public static final java.lang.String NS_USERNAMETOKEN_PROFILE11;

  public static final java.lang.String NS_PASSWORD_DIGEST;

  public static final java.lang.String NS_PASSWORD_TEXT;

  public static final java.lang.String NS_USERNAMETOKEN_PROFILE_UsernameToken;

  public static final javax.xml.namespace.QName TAG_wsse11_SignatureConfirmation;

  public static final javax.xml.namespace.QName ATT_NULL_Value;

  public static final java.lang.String NS_C14N_EXCL;

  public static final java.lang.String PREFIX_C14N_EXCL;

  public static final javax.xml.namespace.QName TAG_wst_BinarySecret;

  public static final javax.xml.namespace.QName TAG_wst0512_BinarySecret;

  public static final java.lang.String SOAPMESSAGE_NS10_STRTransform;

  public static final java.lang.String SWA_ATTACHMENT_CONTENT_SIG_TRANS;

  public static final java.lang.String SWA_ATTACHMENT_COMPLETE_SIG_TRANS;

  public static final java.lang.String SWA_ATTACHMENT_CIPHERTEXT_TRANS;

  public static final java.lang.String SWA_ATTACHMENT_ENCRYPTED_DATA_TYPE_CONTENT_ONLY;

  public static final java.lang.String SWA_ATTACHMENT_ENCRYPTED_DATA_TYPE_COMPLETE;

  public static final javax.xml.namespace.QName TAG_saml_Assertion;

  public static final javax.xml.namespace.QName TAG_saml2_Assertion;

  public static final javax.xml.namespace.QName TAG_saml2_EncryptedAssertion;

  public static final java.lang.String NS_SAML10_TOKEN_PROFILE;

  public static final java.lang.String NS_SAML11_TOKEN_PROFILE;

  public static final java.lang.String NS_SAML10_TYPE;

  public static final java.lang.String NS_SAML20_TYPE;

  public static final java.lang.String NS_SAML11_TOKEN_PROFILE_TYPE;

  public static final java.lang.String NS_SAML20_TOKEN_PROFILE_TYPE;

  public static final java.lang.String NS_KERBEROS11_TOKEN_PROFILE;

  public static final java.lang.String NS_GSS_Kerberos5_AP_REQ;

  public static final java.lang.String NS_GSS_Kerberos5_AP_REQ1510;

  public static final java.lang.String NS_GSS_Kerberos5_AP_REQ4120;

  public static final java.lang.String NS_Kerberos5_AP_REQ;

  public static final java.lang.String NS_Kerberos5_AP_REQ_SHA1;

  public static final java.lang.String NS_Kerberos5_AP_REQ1510;

  public static final java.lang.String NS_Kerberos5_AP_REQ4120;

  public static final javax.xml.namespace.QName ATT_NULL_AssertionID;

  public static final javax.xml.namespace.QName ATT_NULL_ID;

  public static final java.lang.String NS_WSC_05_02;

  public static final java.lang.String NS_WSC_05_12;

  public static final java.lang.String PREFIX_WSC;

  public static final javax.xml.namespace.QName TAG_wsc0502_SecurityContextToken;

  public static final javax.xml.namespace.QName TAG_wsc0512_SecurityContextToken;

  public static final javax.xml.namespace.QName TAG_wsc0502_Identifier;

  public static final javax.xml.namespace.QName TAG_wsc0512_Identifier;

  public static final javax.xml.namespace.QName TAG_wsc0502_DerivedKeyToken;

  public static final javax.xml.namespace.QName TAG_wsc0512_DerivedKeyToken;

  public static final javax.xml.namespace.QName TAG_wsc0502_Properties;

  public static final javax.xml.namespace.QName TAG_wsc0512_Properties;

  public static final javax.xml.namespace.QName TAG_wsc0502_Length;

  public static final javax.xml.namespace.QName TAG_wsc0512_Length;

  public static final javax.xml.namespace.QName TAG_wsc0502_Generation;

  public static final javax.xml.namespace.QName TAG_wsc0512_Generation;

  public static final javax.xml.namespace.QName TAG_wsc0502_Offset;

  public static final javax.xml.namespace.QName TAG_wsc0512_Offset;

  public static final javax.xml.namespace.QName TAG_wsc0502_Label;

  public static final javax.xml.namespace.QName TAG_wsc0512_Label;

  public static final javax.xml.namespace.QName TAG_wsc0502_Nonce;

  public static final javax.xml.namespace.QName TAG_wsc0512_Nonce;

  public static final java.lang.String P_SHA_1;

  public static final java.lang.String P_SHA_1_2005_12;

  public static final java.lang.String WS_SecureConversation_DEFAULT_LABEL;

  public static final java.lang.String NS_WSS_ENC_KEY_VALUE_TYPE;

  public static final java.lang.String PROP_USE_THIS_TOKEN_ID_FOR_KERBEROS;

  public static final java.lang.String PROP_USE_THIS_TOKEN_ID_FOR_DERIVED_KEY;

  public static final java.lang.String PROP_USE_THIS_TOKEN_ID_FOR_SECURITYCONTEXTTOKEN;

  public static final java.lang.String PROP_USE_THIS_TOKEN_ID_FOR_CUSTOM_TOKEN;

  public static final java.lang.String PROP_TIMESTAMP_SECURITYEVENT;

  public static final java.lang.String PROP_ENCRYPTED_DATA_REFS;

  public static final org.apache.xml.security.stax.ext.XMLSecurityConstants$Action TIMESTAMP;

  public static final org.apache.xml.security.stax.ext.XMLSecurityConstants$Action USERNAMETOKEN;

  public static final org.apache.xml.security.stax.ext.XMLSecurityConstants$Action USERNAMETOKEN_SIGNED;

  public static final org.apache.xml.security.stax.ext.XMLSecurityConstants$Action SIGNATURE_CONFIRMATION;

  public static final org.apache.xml.security.stax.ext.XMLSecurityConstants$Action SIGNATURE_WITH_DERIVED_KEY;

  public static final org.apache.xml.security.stax.ext.XMLSecurityConstants$Action ENCRYPT_WITH_DERIVED_KEY;

  public static final org.apache.xml.security.stax.ext.XMLSecurityConstants$Action SAML_TOKEN_SIGNED;

  public static final org.apache.xml.security.stax.ext.XMLSecurityConstants$Action SAML_TOKEN_UNSIGNED;

  public static final org.apache.xml.security.stax.ext.XMLSecurityConstants$Action SIGNATURE_WITH_KERBEROS_TOKEN;

  public static final org.apache.xml.security.stax.ext.XMLSecurityConstants$Action ENCRYPT_WITH_KERBEROS_TOKEN;

  public static final org.apache.xml.security.stax.ext.XMLSecurityConstants$Action KERBEROS_TOKEN;

  public static final org.apache.xml.security.stax.ext.XMLSecurityConstants$Action CUSTOM_TOKEN;

  public static final org.apache.xml.security.stax.ext.XMLSecurityConstants$AlgorithmUsage Comp_Key;

  public static final org.apache.xml.security.stax.ext.XMLSecurityConstants$AlgorithmUsage Enc_KD;

  public static final org.apache.xml.security.stax.ext.XMLSecurityConstants$AlgorithmUsage Sig_KD;

  public static final org.apache.xml.security.stax.ext.XMLSecurityConstants$AlgorithmUsage Soap_Norm;

  public static final org.apache.xml.security.stax.ext.XMLSecurityConstants$AlgorithmUsage STR_Trans;

  public static final org.apache.xml.security.stax.ext.XMLSecurityConstants$AlgorithmUsage XPath;

  public static final java.util.List<javax.xml.namespace.QName> SOAP_11_BODY_PATH;

  public static final java.util.List<javax.xml.namespace.QName> SOAP_11_HEADER_PATH;

  public static final java.util.List<javax.xml.namespace.QName> WSSE_SECURITY_HEADER_PATH;

  protected org.apache.wss4j.stax.ext.WSSConstants();
    Code:
       0: aload_0
       1: invokespecial #1                  // Method org/apache/xml/security/stax/ext/XMLSecurityConstants."<init>":()V
       4: return

  static {};
    Code:
       0: new           #2                  // class javax/xml/namespace/QName
       3: dup
       4: ldc           #3                  // String http://schemas.xmlsoap.org/soap/envelope/
       6: ldc           #4                  // String Envelope
       8: ldc           #5                  // String soap
      10: invokespecial #6                  // Method javax/xml/namespace/QName."<init>":(Ljava/lang/String;Ljava/lang/String;Ljava/lang/String;)V
      13: putstatic     #7                  // Field TAG_soap11_Envelope:Ljavax/xml/namespace/QName;
      16: new           #2                  // class javax/xml/namespace/QName
      19: dup
      20: ldc           #3                  // String http://schemas.xmlsoap.org/soap/envelope/
      22: ldc           #8                  // String Header
      24: ldc           #5                  // String soap
      26: invokespecial #6                  // Method javax/xml/namespace/QName."<init>":(Ljava/lang/String;Ljava/lang/String;Ljava/lang/String;)V
      29: putstatic     #9                  // Field TAG_soap11_Header:Ljavax/xml/namespace/QName;
      32: new           #2                  // class javax/xml/namespace/QName
      35: dup
      36: ldc           #3                  // String http://schemas.xmlsoap.org/soap/envelope/
      38: ldc           #10                 // String Body
      40: ldc           #5                  // String soap
      42: invokespecial #6                  // Method javax/xml/namespace/QName."<init>":(Ljava/lang/String;Ljava/lang/String;Ljava/lang/String;)V
      45: putstatic     #11                 // Field TAG_soap11_Body:Ljavax/xml/namespace/QName;
      48: new           #2                  // class javax/xml/namespace/QName
      51: dup
      52: ldc           #3                  // String http://schemas.xmlsoap.org/soap/envelope/
      54: ldc           #12                 // String actor
      56: ldc           #5                  // String soap
      58: invokespecial #6                  // Method javax/xml/namespace/QName."<init>":(Ljava/lang/String;Ljava/lang/String;Ljava/lang/String;)V
      61: putstatic     #13                 // Field ATT_soap11_Actor:Ljavax/xml/namespace/QName;
      64: new           #2                  // class javax/xml/namespace/QName
      67: dup
      68: ldc           #3                  // String http://schemas.xmlsoap.org/soap/envelope/
      70: ldc           #14                 // String mustUnderstand
      72: ldc           #5                  // String soap
      74: invokespecial #6                  // Method javax/xml/namespace/QName."<init>":(Ljava/lang/String;Ljava/lang/String;Ljava/lang/String;)V
      77: putstatic     #15                 // Field ATT_soap11_MustUnderstand:Ljavax/xml/namespace/QName;
      80: new           #2                  // class javax/xml/namespace/QName
      83: dup
      84: ldc           #16                 // String http://www.w3.org/2003/05/soap-envelope
      86: ldc           #4                  // String Envelope
      88: ldc           #5                  // String soap
      90: invokespecial #6                  // Method javax/xml/namespace/QName."<init>":(Ljava/lang/String;Ljava/lang/String;Ljava/lang/String;)V
      93: putstatic     #17                 // Field TAG_soap12_Envelope:Ljavax/xml/namespace/QName;
      96: new           #2                  // class javax/xml/namespace/QName
      99: dup
     100: ldc           #16                 // String http://www.w3.org/2003/05/soap-envelope
     102: ldc           #8                  // String Header
     104: ldc           #5                  // String soap
     106: invokespecial #6                  // Method javax/xml/namespace/QName."<init>":(Ljava/lang/String;Ljava/lang/String;Ljava/lang/String;)V
     109: putstatic     #18                 // Field TAG_soap12_Header:Ljavax/xml/namespace/QName;
     112: new           #2                  // class javax/xml/namespace/QName
     115: dup
     116: ldc           #16                 // String http://www.w3.org/2003/05/soap-envelope
     118: ldc           #10                 // String Body
     120: ldc           #5                  // String soap
     122: invokespecial #6                  // Method javax/xml/namespace/QName."<init>":(Ljava/lang/String;Ljava/lang/String;Ljava/lang/String;)V
     125: putstatic     #19                 // Field TAG_soap12_Body:Ljavax/xml/namespace/QName;
     128: new           #2                  // class javax/xml/namespace/QName
     131: dup
     132: ldc           #16                 // String http://www.w3.org/2003/05/soap-envelope
     134: ldc           #20                 // String role
     136: ldc           #5                  // String soap
     138: invokespecial #6                  // Method javax/xml/namespace/QName."<init>":(Ljava/lang/String;Ljava/lang/String;Ljava/lang/String;)V
     141: putstatic     #21                 // Field ATT_soap12_Role:Ljavax/xml/namespace/QName;
     144: new           #2                  // class javax/xml/namespace/QName
     147: dup
     148: ldc           #16                 // String http://www.w3.org/2003/05/soap-envelope
     150: ldc           #14                 // String mustUnderstand
     152: ldc           #5                  // String soap
     154: invokespecial #6                  // Method javax/xml/namespace/QName."<init>":(Ljava/lang/String;Ljava/lang/String;Ljava/lang/String;)V
     157: putstatic     #22                 // Field ATT_soap12_MustUnderstand:Ljavax/xml/namespace/QName;
     160: new           #2                  // class javax/xml/namespace/QName
     163: dup
     164: ldc           #23                 // String http://docs.oasis-open.org/wss/2004/01/oasis-200401-wss-wssecurity-secext-1.0.xsd
     166: ldc           #24                 // String Security
     168: ldc           #25                 // String wsse
     170: invokespecial #6                  // Method javax/xml/namespace/QName."<init>":(Ljava/lang/String;Ljava/lang/String;Ljava/lang/String;)V
     173: putstatic     #26                 // Field TAG_wsse_Security:Ljavax/xml/namespace/QName;
     176: new           #2                  // class javax/xml/namespace/QName
     179: dup
     180: ldc           #23                 // String http://docs.oasis-open.org/wss/2004/01/oasis-200401-wss-wssecurity-secext-1.0.xsd
     182: ldc           #27                 // String SecurityTokenReference
     184: ldc           #25                 // String wsse
     186: invokespecial #6                  // Method javax/xml/namespace/QName."<init>":(Ljava/lang/String;Ljava/lang/String;Ljava/lang/String;)V
     189: putstatic     #28                 // Field TAG_wsse_SecurityTokenReference:Ljavax/xml/namespace/QName;
     192: new           #2                  // class javax/xml/namespace/QName
     195: dup
     196: ldc           #23                 // String http://docs.oasis-open.org/wss/2004/01/oasis-200401-wss-wssecurity-secext-1.0.xsd
     198: ldc           #29                 // String Reference
     200: ldc           #25                 // String wsse
     202: invokespecial #6                  // Method javax/xml/namespace/QName."<init>":(Ljava/lang/String;Ljava/lang/String;Ljava/lang/String;)V
     205: putstatic     #30                 // Field TAG_wsse_Reference:Ljavax/xml/namespace/QName;
     208: new           #2                  // class javax/xml/namespace/QName
     211: dup
     212: ldc           #23                 // String http://docs.oasis-open.org/wss/2004/01/oasis-200401-wss-wssecurity-secext-1.0.xsd
     214: ldc           #31                 // String Usage
     216: ldc           #25                 // String wsse
     218: invokespecial #6                  // Method javax/xml/namespace/QName."<init>":(Ljava/lang/String;Ljava/lang/String;Ljava/lang/String;)V
     221: putstatic     #32                 // Field ATT_wsse_Usage:Ljavax/xml/namespace/QName;
     224: new           #2                  // class javax/xml/namespace/QName
     227: dup
     228: ldc           #33                 // String http://docs.oasis-open.org/wss/oasis-wss-wssecurity-secext-1.1.xsd
     230: ldc           #34                 // String TokenType
     232: ldc           #35                 // String wsse11
     234: invokespecial #6                  // Method javax/xml/namespace/QName."<init>":(Ljava/lang/String;Ljava/lang/String;Ljava/lang/String;)V
     237: putstatic     #36                 // Field ATT_wsse11_TokenType:Ljavax/xml/namespace/QName;
     240: new           #2                  // class javax/xml/namespace/QName
     243: dup
     244: ldc           #23                 // String http://docs.oasis-open.org/wss/2004/01/oasis-200401-wss-wssecurity-secext-1.0.xsd
     246: ldc           #37                 // String KeyIdentifier
     248: ldc           #25                 // String wsse
     250: invokespecial #6                  // Method javax/xml/namespace/QName."<init>":(Ljava/lang/String;Ljava/lang/String;Ljava/lang/String;)V
     253: putstatic     #38                 // Field TAG_wsse_KeyIdentifier:Ljavax/xml/namespace/QName;
     256: new           #2                  // class javax/xml/namespace/QName
     259: dup
     260: aconst_null
     261: ldc           #39                 // String EncodingType
     263: invokespecial #40                 // Method javax/xml/namespace/QName."<init>":(Ljava/lang/String;Ljava/lang/String;)V
     266: putstatic     #41                 // Field ATT_NULL_EncodingType:Ljavax/xml/namespace/QName;
     269: new           #2                  // class javax/xml/namespace/QName
     272: dup
     273: aconst_null
     274: ldc           #42                 // String ValueType
     276: invokespecial #40                 // Method javax/xml/namespace/QName."<init>":(Ljava/lang/String;Ljava/lang/String;)V
     279: putstatic     #43                 // Field ATT_NULL_ValueType:Ljavax/xml/namespace/QName;
     282: new           #2                  // class javax/xml/namespace/QName
     285: dup
     286: ldc           #23                 // String http://docs.oasis-open.org/wss/2004/01/oasis-200401-wss-wssecurity-secext-1.0.xsd
     288: ldc           #44                 // String BinarySecurityToken
     290: ldc           #25                 // String wsse
     292: invokespecial #6                  // Method javax/xml/namespace/QName."<init>":(Ljava/lang/String;Ljava/lang/String;Ljava/lang/String;)V
     295: putstatic     #45                 // Field TAG_wsse_BinarySecurityToken:Ljavax/xml/namespace/QName;
     298: new           #2                  // class javax/xml/namespace/QName
     301: dup
     302: ldc           #46                 // String http://docs.oasis-open.org/wss/2004/01/oasis-200401-wss-wssecurity-utility-1.0.xsd
     304: ldc           #47                 // String Id
     306: ldc           #48                 // String wsu
     308: invokespecial #6                  // Method javax/xml/namespace/QName."<init>":(Ljava/lang/String;Ljava/lang/String;Ljava/lang/String;)V
     311: putstatic     #49                 // Field ATT_wsu_Id:Ljavax/xml/namespace/QName;
     314: new           #2                  // class javax/xml/namespace/QName
     317: dup
     318: ldc           #33                 // String http://docs.oasis-open.org/wss/oasis-wss-wssecurity-secext-1.1.xsd
     320: ldc           #50                 // String EncryptedHeader
     322: ldc           #35                 // String wsse11
     324: invokespecial #6                  // Method javax/xml/namespace/QName."<init>":(Ljava/lang/String;Ljava/lang/String;Ljava/lang/String;)V
     327: putstatic     #51                 // Field TAG_wsse11_EncryptedHeader:Ljavax/xml/namespace/QName;
     330: new           #2                  // class javax/xml/namespace/QName
     333: dup
     334: ldc           #23                 // String http://docs.oasis-open.org/wss/2004/01/oasis-200401-wss-wssecurity-secext-1.0.xsd
     336: ldc           #52                 // String TransformationParameters
     338: ldc           #25                 // String wsse
     340: invokespecial #6                  // Method javax/xml/namespace/QName."<init>":(Ljava/lang/String;Ljava/lang/String;Ljava/lang/String;)V
     343: putstatic     #53                 // Field TAG_wsse_TransformationParameters:Ljavax/xml/namespace/QName;
     346: new           #2                  // class javax/xml/namespace/QName
     349: dup
     350: ldc           #46                 // String http://docs.oasis-open.org/wss/2004/01/oasis-200401-wss-wssecurity-utility-1.0.xsd
     352: ldc           #54                 // String Timestamp
     354: ldc           #48                 // String wsu
     356: invokespecial #6                  // Method javax/xml/namespace/QName."<init>":(Ljava/lang/String;Ljava/lang/String;Ljava/lang/String;)V
     359: putstatic     #55                 // Field TAG_wsu_Timestamp:Ljavax/xml/namespace/QName;
     362: new           #2                  // class javax/xml/namespace/QName
     365: dup
     366: ldc           #46                 // String http://docs.oasis-open.org/wss/2004/01/oasis-200401-wss-wssecurity-utility-1.0.xsd
     368: ldc           #56                 // String Created
     370: ldc           #48                 // String wsu
     372: invokespecial #6                  // Method javax/xml/namespace/QName."<init>":(Ljava/lang/String;Ljava/lang/String;Ljava/lang/String;)V
     375: putstatic     #57                 // Field TAG_wsu_Created:Ljavax/xml/namespace/QName;
     378: new           #2                  // class javax/xml/namespace/QName
     381: dup
     382: ldc           #46                 // String http://docs.oasis-open.org/wss/2004/01/oasis-200401-wss-wssecurity-utility-1.0.xsd
     384: ldc           #58                 // String Expires
     386: ldc           #48                 // String wsu
     388: invokespecial #6                  // Method javax/xml/namespace/QName."<init>":(Ljava/lang/String;Ljava/lang/String;Ljava/lang/String;)V
     391: putstatic     #59                 // Field TAG_wsu_Expires:Ljavax/xml/namespace/QName;
     394: new           #2                  // class javax/xml/namespace/QName
     397: dup
     398: ldc           #23                 // String http://docs.oasis-open.org/wss/2004/01/oasis-200401-wss-wssecurity-secext-1.0.xsd
     400: ldc           #60                 // String UsernameToken
     402: ldc           #25                 // String wsse
     404: invokespecial #6                  // Method javax/xml/namespace/QName."<init>":(Ljava/lang/String;Ljava/lang/String;Ljava/lang/String;)V
     407: putstatic     #61                 // Field TAG_wsse_UsernameToken:Ljavax/xml/namespace/QName;
     410: new           #2                  // class javax/xml/namespace/QName
     413: dup
     414: ldc           #23                 // String http://docs.oasis-open.org/wss/2004/01/oasis-200401-wss-wssecurity-secext-1.0.xsd
     416: ldc           #62                 // String Username
     418: ldc           #25                 // String wsse
     420: invokespecial #6                  // Method javax/xml/namespace/QName."<init>":(Ljava/lang/String;Ljava/lang/String;Ljava/lang/String;)V
     423: putstatic     #63                 // Field TAG_wsse_Username:Ljavax/xml/namespace/QName;
     426: new           #2                  // class javax/xml/namespace/QName
     429: dup
     430: ldc           #23                 // String http://docs.oasis-open.org/wss/2004/01/oasis-200401-wss-wssecurity-secext-1.0.xsd
     432: ldc           #64                 // String Password
     434: ldc           #25                 // String wsse
     436: invokespecial #6                  // Method javax/xml/namespace/QName."<init>":(Ljava/lang/String;Ljava/lang/String;Ljava/lang/String;)V
     439: putstatic     #65                 // Field TAG_wsse_Password:Ljavax/xml/namespace/QName;
     442: new           #2                  // class javax/xml/namespace/QName
     445: dup
     446: ldc           #23                 // String http://docs.oasis-open.org/wss/2004/01/oasis-200401-wss-wssecurity-secext-1.0.xsd
     448: ldc           #66                 // String Nonce
     450: ldc           #25                 // String wsse
     452: invokespecial #6                  // Method javax/xml/namespace/QName."<init>":(Ljava/lang/String;Ljava/lang/String;Ljava/lang/String;)V
     455: putstatic     #67                 // Field TAG_wsse_Nonce:Ljavax/xml/namespace/QName;
     458: new           #2                  // class javax/xml/namespace/QName
     461: dup
     462: ldc           #33                 // String http://docs.oasis-open.org/wss/oasis-wss-wssecurity-secext-1.1.xsd
     464: ldc           #68                 // String Salt
     466: ldc           #35                 // String wsse11
     468: invokespecial #6                  // Method javax/xml/namespace/QName."<init>":(Ljava/lang/String;Ljava/lang/String;Ljava/lang/String;)V
     471: putstatic     #69                 // Field TAG_wsse11_Salt:Ljavax/xml/namespace/QName;
     474: new           #2                  // class javax/xml/namespace/QName
     477: dup
     478: ldc           #33                 // String http://docs.oasis-open.org/wss/oasis-wss-wssecurity-secext-1.1.xsd
     480: ldc           #70                 // String Iteration
     482: ldc           #35                 // String wsse11
     484: invokespecial #6                  // Method javax/xml/namespace/QName."<init>":(Ljava/lang/String;Ljava/lang/String;Ljava/lang/String;)V
     487: putstatic     #71                 // Field TAG_wsse11_Iteration:Ljavax/xml/namespace/QName;
     490: new           #2                  // class javax/xml/namespace/QName
     493: dup
     494: ldc           #33                 // String http://docs.oasis-open.org/wss/oasis-wss-wssecurity-secext-1.1.xsd
     496: ldc           #72                 // String SignatureConfirmation
     498: ldc           #35                 // String wsse11
     500: invokespecial #6                  // Method javax/xml/namespace/QName."<init>":(Ljava/lang/String;Ljava/lang/String;Ljava/lang/String;)V
     503: putstatic     #73                 // Field TAG_wsse11_SignatureConfirmation:Ljavax/xml/namespace/QName;
     506: new           #2                  // class javax/xml/namespace/QName
     509: dup
     510: aconst_null
     511: ldc           #74                 // String Value
     513: invokespecial #40                 // Method javax/xml/namespace/QName."<init>":(Ljava/lang/String;Ljava/lang/String;)V
     516: putstatic     #75                 // Field ATT_NULL_Value:Ljavax/xml/namespace/QName;
     519: new           #2                  // class javax/xml/namespace/QName
     522: dup
     523: ldc           #76                 // String http://schemas.xmlsoap.org/ws/2005/02/trust
     525: ldc           #77                 // String BinarySecret
     527: invokespecial #40                 // Method javax/xml/namespace/QName."<init>":(Ljava/lang/String;Ljava/lang/String;)V
     530: putstatic     #78                 // Field TAG_wst_BinarySecret:Ljavax/xml/namespace/QName;
     533: new           #2                  // class javax/xml/namespace/QName
     536: dup
     537: ldc           #79                 // String http://docs.oasis-open.org/ws-sx/ws-trust/200512
     539: ldc           #77                 // String BinarySecret
     541: invokespecial #40                 // Method javax/xml/namespace/QName."<init>":(Ljava/lang/String;Ljava/lang/String;)V
     544: putstatic     #80                 // Field TAG_wst0512_BinarySecret:Ljavax/xml/namespace/QName;
     547: new           #2                  // class javax/xml/namespace/QName
     550: dup
     551: ldc           #81                 // String urn:oasis:names:tc:SAML:1.0:assertion
     553: ldc           #82                 // String Assertion
     555: invokespecial #40                 // Method javax/xml/namespace/QName."<init>":(Ljava/lang/String;Ljava/lang/String;)V
     558: putstatic     #83                 // Field TAG_saml_Assertion:Ljavax/xml/namespace/QName;
     561: new           #2                  // class javax/xml/namespace/QName
     564: dup
     565: ldc           #84                 // String urn:oasis:names:tc:SAML:2.0:assertion
     567: ldc           #82                 // String Assertion
     569: invokespecial #40                 // Method javax/xml/namespace/QName."<init>":(Ljava/lang/String;Ljava/lang/String;)V
     572: putstatic     #85                 // Field TAG_saml2_Assertion:Ljavax/xml/namespace/QName;
     575: new           #2                  // class javax/xml/namespace/QName
     578: dup
     579: ldc           #84                 // String urn:oasis:names:tc:SAML:2.0:assertion
     581: ldc           #86                 // String EncryptedAssertion
     583: invokespecial #40                 // Method javax/xml/namespace/QName."<init>":(Ljava/lang/String;Ljava/lang/String;)V
     586: putstatic     #87                 // Field TAG_saml2_EncryptedAssertion:Ljavax/xml/namespace/QName;
     589: new           #2                  // class javax/xml/namespace/QName
     592: dup
     593: aconst_null
     594: ldc           #88                 // String AssertionID
     596: invokespecial #40                 // Method javax/xml/namespace/QName."<init>":(Ljava/lang/String;Ljava/lang/String;)V
     599: putstatic     #89                 // Field ATT_NULL_AssertionID:Ljavax/xml/namespace/QName;
     602: new           #2                  // class javax/xml/namespace/QName
     605: dup
     606: aconst_null
     607: ldc           #90                 // String ID
     609: invokespecial #40                 // Method javax/xml/namespace/QName."<init>":(Ljava/lang/String;Ljava/lang/String;)V
     612: putstatic     #91                 // Field ATT_NULL_ID:Ljavax/xml/namespace/QName;
     615: new           #2                  // class javax/xml/namespace/QName
     618: dup
     619: ldc           #92                 // String http://schemas.xmlsoap.org/ws/2005/02/sc
     621: ldc           #93                 // String SecurityContextToken
     623: ldc           #94                 // String wsc
     625: invokespecial #6                  // Method javax/xml/namespace/QName."<init>":(Ljava/lang/String;Ljava/lang/String;Ljava/lang/String;)V
     628: putstatic     #95                 // Field TAG_wsc0502_SecurityContextToken:Ljavax/xml/namespace/QName;
     631: new           #2                  // class javax/xml/namespace/QName
     634: dup
     635: ldc           #96                 // String http://docs.oasis-open.org/ws-sx/ws-secureconversation/200512
     637: ldc           #93                 // String SecurityContextToken
     639: ldc           #94                 // String wsc
     641: invokespecial #6                  // Method javax/xml/namespace/QName."<init>":(Ljava/lang/String;Ljava/lang/String;Ljava/lang/String;)V
     644: putstatic     #97                 // Field TAG_wsc0512_SecurityContextToken:Ljavax/xml/namespace/QName;
     647: new           #2                  // class javax/xml/namespace/QName
     650: dup
     651: ldc           #92                 // String http://schemas.xmlsoap.org/ws/2005/02/sc
     653: ldc           #98                 // String Identifier
     655: ldc           #94                 // String wsc
     657: invokespecial #6                  // Method javax/xml/namespace/QName."<init>":(Ljava/lang/String;Ljava/lang/String;Ljava/lang/String;)V
     660: putstatic     #99                 // Field TAG_wsc0502_Identifier:Ljavax/xml/namespace/QName;
     663: new           #2                  // class javax/xml/namespace/QName
     666: dup
     667: ldc           #96                 // String http://docs.oasis-open.org/ws-sx/ws-secureconversation/200512
     669: ldc           #98                 // String Identifier
     671: ldc           #94                 // String wsc
     673: invokespecial #6                  // Method javax/xml/namespace/QName."<init>":(Ljava/lang/String;Ljava/lang/String;Ljava/lang/String;)V
     676: putstatic     #100                // Field TAG_wsc0512_Identifier:Ljavax/xml/namespace/QName;
     679: new           #2                  // class javax/xml/namespace/QName
     682: dup
     683: ldc           #92                 // String http://schemas.xmlsoap.org/ws/2005/02/sc
     685: ldc           #101                // String DerivedKeyToken
     687: ldc           #94                 // String wsc
     689: invokespecial #6                  // Method javax/xml/namespace/QName."<init>":(Ljava/lang/String;Ljava/lang/String;Ljava/lang/String;)V
     692: putstatic     #102                // Field TAG_wsc0502_DerivedKeyToken:Ljavax/xml/namespace/QName;
     695: new           #2                  // class javax/xml/namespace/QName
     698: dup
     699: ldc           #96                 // String http://docs.oasis-open.org/ws-sx/ws-secureconversation/200512
     701: ldc           #101                // String DerivedKeyToken
     703: ldc           #94                 // String wsc
     705: invokespecial #6                  // Method javax/xml/namespace/QName."<init>":(Ljava/lang/String;Ljava/lang/String;Ljava/lang/String;)V
     708: putstatic     #103                // Field TAG_wsc0512_DerivedKeyToken:Ljavax/xml/namespace/QName;
     711: new           #2                  // class javax/xml/namespace/QName
     714: dup
     715: ldc           #92                 // String http://schemas.xmlsoap.org/ws/2005/02/sc
     717: ldc           #104                // String Properties
     719: ldc           #94                 // String wsc
     721: invokespecial #6                  // Method javax/xml/namespace/QName."<init>":(Ljava/lang/String;Ljava/lang/String;Ljava/lang/String;)V
     724: putstatic     #105                // Field TAG_wsc0502_Properties:Ljavax/xml/namespace/QName;
     727: new           #2                  // class javax/xml/namespace/QName
     730: dup
     731: ldc           #96                 // String http://docs.oasis-open.org/ws-sx/ws-secureconversation/200512
     733: ldc           #104                // String Properties
     735: ldc           #94                 // String wsc
     737: invokespecial #6                  // Method javax/xml/namespace/QName."<init>":(Ljava/lang/String;Ljava/lang/String;Ljava/lang/String;)V
     740: putstatic     #106                // Field TAG_wsc0512_Properties:Ljavax/xml/namespace/QName;
     743: new           #2                  // class javax/xml/namespace/QName
     746: dup
     747: ldc           #92                 // String http://schemas.xmlsoap.org/ws/2005/02/sc
     749: ldc           #107                // String Length
     751: ldc           #94                 // String wsc
     753: invokespecial #6                  // Method javax/xml/namespace/QName."<init>":(Ljava/lang/String;Ljava/lang/String;Ljava/lang/String;)V
     756: putstatic     #108                // Field TAG_wsc0502_Length:Ljavax/xml/namespace/QName;
     759: new           #2                  // class javax/xml/namespace/QName
     762: dup
     763: ldc           #96                 // String http://docs.oasis-open.org/ws-sx/ws-secureconversation/200512
     765: ldc           #107                // String Length
     767: ldc           #94                 // String wsc
     769: invokespecial #6                  // Method javax/xml/namespace/QName."<init>":(Ljava/lang/String;Ljava/lang/String;Ljava/lang/String;)V
     772: putstatic     #109                // Field TAG_wsc0512_Length:Ljavax/xml/namespace/QName;
     775: new           #2                  // class javax/xml/namespace/QName
     778: dup
     779: ldc           #92                 // String http://schemas.xmlsoap.org/ws/2005/02/sc
     781: ldc           #110                // String Generation
     783: ldc           #94                 // String wsc
     785: invokespecial #6                  // Method javax/xml/namespace/QName."<init>":(Ljava/lang/String;Ljava/lang/String;Ljava/lang/String;)V
     788: putstatic     #111                // Field TAG_wsc0502_Generation:Ljavax/xml/namespace/QName;
     791: new           #2                  // class javax/xml/namespace/QName
     794: dup
     795: ldc           #96                 // String http://docs.oasis-open.org/ws-sx/ws-secureconversation/200512
     797: ldc           #110                // String Generation
     799: ldc           #94                 // String wsc
     801: invokespecial #6                  // Method javax/xml/namespace/QName."<init>":(Ljava/lang/String;Ljava/lang/String;Ljava/lang/String;)V
     804: putstatic     #112                // Field TAG_wsc0512_Generation:Ljavax/xml/namespace/QName;
     807: new           #2                  // class javax/xml/namespace/QName
     810: dup
     811: ldc           #92                 // String http://schemas.xmlsoap.org/ws/2005/02/sc
     813: ldc           #113                // String Offset
     815: ldc           #94                 // String wsc
     817: invokespecial #6                  // Method javax/xml/namespace/QName."<init>":(Ljava/lang/String;Ljava/lang/String;Ljava/lang/String;)V
     820: putstatic     #114                // Field TAG_wsc0502_Offset:Ljavax/xml/namespace/QName;
     823: new           #2                  // class javax/xml/namespace/QName
     826: dup
     827: ldc           #96                 // String http://docs.oasis-open.org/ws-sx/ws-secureconversation/200512
     829: ldc           #113                // String Offset
     831: ldc           #94                 // String wsc
     833: invokespecial #6                  // Method javax/xml/namespace/QName."<init>":(Ljava/lang/String;Ljava/lang/String;Ljava/lang/String;)V
     836: putstatic     #115                // Field TAG_wsc0512_Offset:Ljavax/xml/namespace/QName;
     839: new           #2                  // class javax/xml/namespace/QName
     842: dup
     843: ldc           #92                 // String http://schemas.xmlsoap.org/ws/2005/02/sc
     845: ldc           #116                // String Label
     847: ldc           #94                 // String wsc
     849: invokespecial #6                  // Method javax/xml/namespace/QName."<init>":(Ljava/lang/String;Ljava/lang/String;Ljava/lang/String;)V
     852: putstatic     #117                // Field TAG_wsc0502_Label:Ljavax/xml/namespace/QName;
     855: new           #2                  // class javax/xml/namespace/QName
     858: dup
     859: ldc           #96                 // String http://docs.oasis-open.org/ws-sx/ws-secureconversation/200512
     861: ldc           #116                // String Label
     863: ldc           #94                 // String wsc
     865: invokespecial #6                  // Method javax/xml/namespace/QName."<init>":(Ljava/lang/String;Ljava/lang/String;Ljava/lang/String;)V
     868: putstatic     #118                // Field TAG_wsc0512_Label:Ljavax/xml/namespace/QName;
     871: new           #2                  // class javax/xml/namespace/QName
     874: dup
     875: ldc           #92                 // String http://schemas.xmlsoap.org/ws/2005/02/sc
     877: ldc           #66                 // String Nonce
     879: ldc           #94                 // String wsc
     881: invokespecial #6                  // Method javax/xml/namespace/QName."<init>":(Ljava/lang/String;Ljava/lang/String;Ljava/lang/String;)V
     884: putstatic     #119                // Field TAG_wsc0502_Nonce:Ljavax/xml/namespace/QName;
     887: new           #2                  // class javax/xml/namespace/QName
     890: dup
     891: ldc           #96                 // String http://docs.oasis-open.org/ws-sx/ws-secureconversation/200512
     893: ldc           #66                 // String Nonce
     895: ldc           #94                 // String wsc
     897: invokespecial #6                  // Method javax/xml/namespace/QName."<init>":(Ljava/lang/String;Ljava/lang/String;Ljava/lang/String;)V
     900: putstatic     #120                // Field TAG_wsc0512_Nonce:Ljavax/xml/namespace/QName;
     903: new           #121                // class org/apache/xml/security/stax/ext/XMLSecurityConstants$Action
     906: dup
     907: ldc           #54                 // String Timestamp
     909: invokespecial #122                // Method org/apache/xml/security/stax/ext/XMLSecurityConstants$Action."<init>":(Ljava/lang/String;)V
     912: putstatic     #123                // Field TIMESTAMP:Lorg/apache/xml/security/stax/ext/XMLSecurityConstants$Action;
     915: new           #121                // class org/apache/xml/security/stax/ext/XMLSecurityConstants$Action
     918: dup
     919: ldc           #60                 // String UsernameToken
     921: invokespecial #122                // Method org/apache/xml/security/stax/ext/XMLSecurityConstants$Action."<init>":(Ljava/lang/String;)V
     924: putstatic     #124                // Field USERNAMETOKEN:Lorg/apache/xml/security/stax/ext/XMLSecurityConstants$Action;
     927: new           #121                // class org/apache/xml/security/stax/ext/XMLSecurityConstants$Action
     930: dup
     931: ldc           #125                // String UsernameTokenSignature
     933: invokespecial #122                // Method org/apache/xml/security/stax/ext/XMLSecurityConstants$Action."<init>":(Ljava/lang/String;)V
     936: putstatic     #126                // Field USERNAMETOKEN_SIGNED:Lorg/apache/xml/security/stax/ext/XMLSecurityConstants$Action;
     939: new           #121                // class org/apache/xml/security/stax/ext/XMLSecurityConstants$Action
     942: dup
     943: ldc           #72                 // String SignatureConfirmation
     945: invokespecial #122                // Method org/apache/xml/security/stax/ext/XMLSecurityConstants$Action."<init>":(Ljava/lang/String;)V
     948: putstatic     #127                // Field SIGNATURE_CONFIRMATION:Lorg/apache/xml/security/stax/ext/XMLSecurityConstants$Action;
     951: new           #121                // class org/apache/xml/security/stax/ext/XMLSecurityConstants$Action
     954: dup
     955: ldc           #128                // String SignatureWithDerivedKey
     957: invokespecial #122                // Method org/apache/xml/security/stax/ext/XMLSecurityConstants$Action."<init>":(Ljava/lang/String;)V
     960: putstatic     #129                // Field SIGNATURE_WITH_DERIVED_KEY:Lorg/apache/xml/security/stax/ext/XMLSecurityConstants$Action;
     963: new           #121                // class org/apache/xml/security/stax/ext/XMLSecurityConstants$Action
     966: dup
     967: ldc           #130                // String EncryptWithDerivedKey
     969: invokespecial #122                // Method org/apache/xml/security/stax/ext/XMLSecurityConstants$Action."<init>":(Ljava/lang/String;)V
     972: putstatic     #131                // Field ENCRYPT_WITH_DERIVED_KEY:Lorg/apache/xml/security/stax/ext/XMLSecurityConstants$Action;
     975: new           #121                // class org/apache/xml/security/stax/ext/XMLSecurityConstants$Action
     978: dup
     979: ldc           #132                // String SAMLTokenSigned
     981: invokespecial #122                // Method org/apache/xml/security/stax/ext/XMLSecurityConstants$Action."<init>":(Ljava/lang/String;)V
     984: putstatic     #133                // Field SAML_TOKEN_SIGNED:Lorg/apache/xml/security/stax/ext/XMLSecurityConstants$Action;
     987: new           #121                // class org/apache/xml/security/stax/ext/XMLSecurityConstants$Action
     990: dup
     991: ldc           #134                // String SAMLTokenUnsigned
     993: invokespecial #122                // Method org/apache/xml/security/stax/ext/XMLSecurityConstants$Action."<init>":(Ljava/lang/String;)V
     996: putstatic     #135                // Field SAML_TOKEN_UNSIGNED:Lorg/apache/xml/security/stax/ext/XMLSecurityConstants$Action;
     999: new           #121                // class org/apache/xml/security/stax/ext/XMLSecurityConstants$Action
    1002: dup
    1003: ldc           #136                // String SignatureWithKerberosToken
    1005: invokespecial #122                // Method org/apache/xml/security/stax/ext/XMLSecurityConstants$Action."<init>":(Ljava/lang/String;)V
    1008: putstatic     #137                // Field SIGNATURE_WITH_KERBEROS_TOKEN:Lorg/apache/xml/security/stax/ext/XMLSecurityConstants$Action;
    1011: new           #121                // class org/apache/xml/security/stax/ext/XMLSecurityConstants$Action
    1014: dup
    1015: ldc           #138                // String EncryptWithKerberosToken
    1017: invokespecial #122                // Method org/apache/xml/security/stax/ext/XMLSecurityConstants$Action."<init>":(Ljava/lang/String;)V
    1020: putstatic     #139                // Field ENCRYPT_WITH_KERBEROS_TOKEN:Lorg/apache/xml/security/stax/ext/XMLSecurityConstants$Action;
    1023: new           #121                // class org/apache/xml/security/stax/ext/XMLSecurityConstants$Action
    1026: dup
    1027: ldc           #140                // String KerberosToken
    1029: invokespecial #122                // Method org/apache/xml/security/stax/ext/XMLSecurityConstants$Action."<init>":(Ljava/lang/String;)V
    1032: putstatic     #141                // Field KERBEROS_TOKEN:Lorg/apache/xml/security/stax/ext/XMLSecurityConstants$Action;
    1035: new           #121                // class org/apache/xml/security/stax/ext/XMLSecurityConstants$Action
    1038: dup
    1039: ldc           #142                // String CustomToken
    1041: invokespecial #122                // Method org/apache/xml/security/stax/ext/XMLSecurityConstants$Action."<init>":(Ljava/lang/String;)V
    1044: putstatic     #143                // Field CUSTOM_TOKEN:Lorg/apache/xml/security/stax/ext/XMLSecurityConstants$Action;
    1047: new           #144                // class org/apache/xml/security/stax/ext/XMLSecurityConstants$AlgorithmUsage
    1050: dup
    1051: ldc           #145                // String Comp_Key
    1053: invokespecial #146                // Method org/apache/xml/security/stax/ext/XMLSecurityConstants$AlgorithmUsage."<init>":(Ljava/lang/String;)V
    1056: putstatic     #147                // Field Comp_Key:Lorg/apache/xml/security/stax/ext/XMLSecurityConstants$AlgorithmUsage;
    1059: new           #144                // class org/apache/xml/security/stax/ext/XMLSecurityConstants$AlgorithmUsage
    1062: dup
    1063: ldc           #148                // String Enc_KD
    1065: invokespecial #146                // Method org/apache/xml/security/stax/ext/XMLSecurityConstants$AlgorithmUsage."<init>":(Ljava/lang/String;)V
    1068: putstatic     #149                // Field Enc_KD:Lorg/apache/xml/security/stax/ext/XMLSecurityConstants$AlgorithmUsage;
    1071: new           #144                // class org/apache/xml/security/stax/ext/XMLSecurityConstants$AlgorithmUsage
    1074: dup
    1075: ldc           #150                // String Sig_KD
    1077: invokespecial #146                // Method org/apache/xml/security/stax/ext/XMLSecurityConstants$AlgorithmUsage."<init>":(Ljava/lang/String;)V
    1080: putstatic     #151                // Field Sig_KD:Lorg/apache/xml/security/stax/ext/XMLSecurityConstants$AlgorithmUsage;
    1083: new           #144                // class org/apache/xml/security/stax/ext/XMLSecurityConstants$AlgorithmUsage
    1086: dup
    1087: ldc           #152                // String Soap_Norm
    1089: invokespecial #146                // Method org/apache/xml/security/stax/ext/XMLSecurityConstants$AlgorithmUsage."<init>":(Ljava/lang/String;)V
    1092: putstatic     #153                // Field Soap_Norm:Lorg/apache/xml/security/stax/ext/XMLSecurityConstants$AlgorithmUsage;
    1095: new           #144                // class org/apache/xml/security/stax/ext/XMLSecurityConstants$AlgorithmUsage
    1098: dup
    1099: ldc           #154                // String STR_Trans
    1101: invokespecial #146                // Method org/apache/xml/security/stax/ext/XMLSecurityConstants$AlgorithmUsage."<init>":(Ljava/lang/String;)V
    1104: putstatic     #155                // Field STR_Trans:Lorg/apache/xml/security/stax/ext/XMLSecurityConstants$AlgorithmUsage;
    1107: new           #144                // class org/apache/xml/security/stax/ext/XMLSecurityConstants$AlgorithmUsage
    1110: dup
    1111: ldc           #156                // String XPath
    1113: invokespecial #146                // Method org/apache/xml/security/stax/ext/XMLSecurityConstants$AlgorithmUsage."<init>":(Ljava/lang/String;)V
    1116: putstatic     #157                // Field XPath:Lorg/apache/xml/security/stax/ext/XMLSecurityConstants$AlgorithmUsage;
    1119: new           #158                // class java/util/ArrayList
    1122: dup
    1123: iconst_2
    1124: invokespecial #159                // Method java/util/ArrayList."<init>":(I)V
    1127: putstatic     #160                // Field SOAP_11_BODY_PATH:Ljava/util/List;
    1130: new           #158                // class java/util/ArrayList
    1133: dup
    1134: iconst_2
    1135: invokespecial #159                // Method java/util/ArrayList."<init>":(I)V
    1138: putstatic     #161                // Field SOAP_11_HEADER_PATH:Ljava/util/List;
    1141: new           #158                // class java/util/ArrayList
    1144: dup
    1145: iconst_3
    1146: invokespecial #159                // Method java/util/ArrayList."<init>":(I)V
    1149: putstatic     #162                // Field WSSE_SECURITY_HEADER_PATH:Ljava/util/List;
    1152: getstatic     #160                // Field SOAP_11_BODY_PATH:Ljava/util/List;
    1155: getstatic     #7                  // Field TAG_soap11_Envelope:Ljavax/xml/namespace/QName;
    1158: invokeinterface #163,  2          // InterfaceMethod java/util/List.add:(Ljava/lang/Object;)Z
    1163: pop
    1164: getstatic     #160                // Field SOAP_11_BODY_PATH:Ljava/util/List;
    1167: getstatic     #11                 // Field TAG_soap11_Body:Ljavax/xml/namespace/QName;
    1170: invokeinterface #163,  2          // InterfaceMethod java/util/List.add:(Ljava/lang/Object;)Z
    1175: pop
    1176: getstatic     #161                // Field SOAP_11_HEADER_PATH:Ljava/util/List;
    1179: getstatic     #7                  // Field TAG_soap11_Envelope:Ljavax/xml/namespace/QName;
    1182: invokeinterface #163,  2          // InterfaceMethod java/util/List.add:(Ljava/lang/Object;)Z
    1187: pop
    1188: getstatic     #161                // Field SOAP_11_HEADER_PATH:Ljava/util/List;
    1191: getstatic     #9                  // Field TAG_soap11_Header:Ljavax/xml/namespace/QName;
    1194: invokeinterface #163,  2          // InterfaceMethod java/util/List.add:(Ljava/lang/Object;)Z
    1199: pop
    1200: getstatic     #162                // Field WSSE_SECURITY_HEADER_PATH:Ljava/util/List;
    1203: getstatic     #161                // Field SOAP_11_HEADER_PATH:Ljava/util/List;
    1206: invokeinterface #164,  2          // InterfaceMethod java/util/List.addAll:(Ljava/util/Collection;)Z
    1211: pop
    1212: getstatic     #162                // Field WSSE_SECURITY_HEADER_PATH:Ljava/util/List;
    1215: getstatic     #26                 // Field TAG_wsse_Security:Ljavax/xml/namespace/QName;
    1218: invokeinterface #163,  2          // InterfaceMethod java/util/List.add:(Ljava/lang/Object;)Z
    1223: pop
    1224: return
}
