Compiled from "ApiKeyVehicle.java"
public final class springfox.documentation.swagger.web.ApiKeyVehicle extends java.lang.Enum<springfox.documentation.swagger.web.ApiKeyVehicle> {
  public static final springfox.documentation.swagger.web.ApiKeyVehicle HEADER;

  public static final springfox.documentation.swagger.web.ApiKeyVehicle QUERY_PARAM;

  private final java.lang.String value;

  private static final springfox.documentation.swagger.web.ApiKeyVehicle[] $VALUES;

  public static springfox.documentation.swagger.web.ApiKeyVehicle[] values();
    Code:
       0: getstatic     #1                  // Field $VALUES:[Lspringfox/documentation/swagger/web/ApiKeyVehicle;
       3: invokevirtual #2                  // Method "[Lspringfox/documentation/swagger/web/ApiKeyVehicle;".clone:()Ljava/lang/Object;
       6: checkcast     #3                  // class "[Lspringfox/documentation/swagger/web/ApiKeyVehicle;"
       9: areturn

  public static springfox.documentation.swagger.web.ApiKeyVehicle valueOf(java.lang.String);
    Code:
       0: ldc_w         #4                  // class springfox/documentation/swagger/web/ApiKeyVehicle
       3: aload_0
       4: invokestatic  #5                  // Method java/lang/Enum.valueOf:(Ljava/lang/Class;Ljava/lang/String;)Ljava/lang/Enum;
       7: checkcast     #4                  // class springfox/documentation/swagger/web/ApiKeyVehicle
      10: areturn

  private springfox.documentation.swagger.web.ApiKeyVehicle(java.lang.String);
    Code:
       0: aload_0
       1: aload_1
       2: iload_2
       3: invokespecial #6                  // Method java/lang/Enum."<init>":(Ljava/lang/String;I)V
       6: aload_0
       7: aload_3
       8: putfield      #7                  // Field value:Ljava/lang/String;
      11: return

  public java.lang.String getValue();
    Code:
       0: aload_0
       1: getfield      #7                  // Field value:Ljava/lang/String;
       4: areturn

  static {};
    Code:
       0: new           #4                  // class springfox/documentation/swagger/web/ApiKeyVehicle
       3: dup
       4: ldc           #8                  // String HEADER
       6: iconst_0
       7: ldc           #9                  // String header
       9: invokespecial #10                 // Method "<init>":(Ljava/lang/String;ILjava/lang/String;)V
      12: putstatic     #11                 // Field HEADER:Lspringfox/documentation/swagger/web/ApiKeyVehicle;
      15: new           #4                  // class springfox/documentation/swagger/web/ApiKeyVehicle
      18: dup
      19: ldc           #12                 // String QUERY_PARAM
      21: iconst_1
      22: ldc           #13                 // String query
      24: invokespecial #10                 // Method "<init>":(Ljava/lang/String;ILjava/lang/String;)V
      27: putstatic     #14                 // Field QUERY_PARAM:Lspringfox/documentation/swagger/web/ApiKeyVehicle;
      30: iconst_2
      31: anewarray     #4                  // class springfox/documentation/swagger/web/ApiKeyVehicle
      34: dup
      35: iconst_0
      36: getstatic     #11                 // Field HEADER:Lspringfox/documentation/swagger/web/ApiKeyVehicle;
      39: aastore
      40: dup
      41: iconst_1
      42: getstatic     #14                 // Field QUERY_PARAM:Lspringfox/documentation/swagger/web/ApiKeyVehicle;
      45: aastore
      46: putstatic     #1                  // Field $VALUES:[Lspringfox/documentation/swagger/web/ApiKeyVehicle;
      49: return
}
