Compiled from "TypeSafeEnum.java"
public class org.aspectj.util.TypeSafeEnum {
  private byte key;

  private java.lang.String name;

  public org.aspectj.util.TypeSafeEnum(java.lang.String, int);
    Code:
       0: aload_0
       1: invokespecial #1                  // Method java/lang/Object."<init>":()V
       4: aload_0
       5: aload_1
       6: putfield      #2                  // Field name:Ljava/lang/String;
       9: iload_2
      10: bipush        127
      12: if_icmpgt     21
      15: iload_2
      16: bipush        -128
      18: if_icmpge     48
      21: new           #4                  // class java/lang/IllegalArgumentException
      24: dup
      25: new           #5                  // class java/lang/StringBuilder
      28: dup
      29: invokespecial #6                  // Method java/lang/StringBuilder."<init>":()V
      32: ldc           #7                  // String key doesn\'t fit into a byte:
      34: invokevirtual #8                  // Method java/lang/StringBuilder.append:(Ljava/lang/String;)Ljava/lang/StringBuilder;
      37: iload_2
      38: invokevirtual #9                  // Method java/lang/StringBuilder.append:(I)Ljava/lang/StringBuilder;
      41: invokevirtual #10                 // Method java/lang/StringBuilder.toString:()Ljava/lang/String;
      44: invokespecial #11                 // Method java/lang/IllegalArgumentException."<init>":(Ljava/lang/String;)V
      47: athrow
      48: aload_0
      49: iload_2
      50: i2b
      51: putfield      #12                 // Field key:B
      54: return

  public java.lang.String toString();
    Code:
       0: aload_0
       1: getfield      #2                  // Field name:Ljava/lang/String;
       4: areturn

  public java.lang.String getName();
    Code:
       0: aload_0
       1: getfield      #2                  // Field name:Ljava/lang/String;
       4: areturn

  public byte getKey();
    Code:
       0: aload_0
       1: getfield      #12                 // Field key:B
       4: ireturn

  public void write(java.io.DataOutputStream) throws java.io.IOException;
    Code:
       0: aload_1
       1: aload_0
       2: getfield      #12                 // Field key:B
       5: invokevirtual #13                 // Method java/io/DataOutputStream.writeByte:(I)V
       8: return

  public int hashCode();
    Code:
       0: aload_0
       1: getfield      #2                  // Field name:Ljava/lang/String;
       4: invokevirtual #14                 // Method java/lang/String.hashCode:()I
       7: bipush        37
       9: imul
      10: aload_0
      11: getfield      #12                 // Field key:B
      14: iadd
      15: ireturn

  public boolean equals(java.lang.Object);
    Code:
       0: aload_1
       1: instanceof    #15                 // class org/aspectj/util/TypeSafeEnum
       4: ifeq          42
       7: aload_1
       8: checkcast     #15                 // class org/aspectj/util/TypeSafeEnum
      11: getfield      #12                 // Field key:B
      14: aload_0
      15: getfield      #12                 // Field key:B
      18: if_icmpne     42
      21: aload_1
      22: checkcast     #15                 // class org/aspectj/util/TypeSafeEnum
      25: getfield      #2                  // Field name:Ljava/lang/String;
      28: aload_0
      29: getfield      #2                  // Field name:Ljava/lang/String;
      32: invokevirtual #16                 // Method java/lang/String.equals:(Ljava/lang/Object;)Z
      35: ifeq          42
      38: iconst_1
      39: goto          43
      42: iconst_0
      43: ireturn
}
