Compiled from "ResultMatchers.java"
public class org.junit.experimental.results.ResultMatchers {
  public org.junit.experimental.results.ResultMatchers();
    Code:
       0: aload_0
       1: invokespecial #1                  // Method java/lang/Object."<init>":()V
       4: return

  public static org.hamcrest.Matcher<org.junit.experimental.results.PrintableResult> isSuccessful();
    Code:
       0: iconst_0
       1: invokestatic  #2                  // Method failureCountIs:(I)Lorg/hamcrest/Matcher;
       4: areturn

  public static org.hamcrest.Matcher<org.junit.experimental.results.PrintableResult> failureCountIs(int);
    Code:
       0: new           #3                  // class org/junit/experimental/results/ResultMatchers$1
       3: dup
       4: iload_0
       5: invokespecial #4                  // Method org/junit/experimental/results/ResultMatchers$1."<init>":(I)V
       8: areturn

  public static org.hamcrest.Matcher<java.lang.Object> hasSingleFailureContaining(java.lang.String);
    Code:
       0: new           #5                  // class org/junit/experimental/results/ResultMatchers$2
       3: dup
       4: aload_0
       5: invokespecial #6                  // Method org/junit/experimental/results/ResultMatchers$2."<init>":(Ljava/lang/String;)V
       8: areturn

  public static org.hamcrest.Matcher<org.junit.experimental.results.PrintableResult> hasSingleFailureMatching(org.hamcrest.Matcher<java.lang.Throwable>);
    Code:
       0: new           #7                  // class org/junit/experimental/results/ResultMatchers$3
       3: dup
       4: aload_0
       5: invokespecial #8                  // Method org/junit/experimental/results/ResultMatchers$3."<init>":(Lorg/hamcrest/Matcher;)V
       8: areturn

  public static org.hamcrest.Matcher<org.junit.experimental.results.PrintableResult> hasFailureContaining(java.lang.String);
    Code:
       0: new           #9                  // class org/junit/experimental/results/ResultMatchers$4
       3: dup
       4: aload_0
       5: invokespecial #10                 // Method org/junit/experimental/results/ResultMatchers$4."<init>":(Ljava/lang/String;)V
       8: areturn
}
