Compiled from "ResourceManagersMetaDataMerger.java"
public class org.jboss.metadata.merge.ejb.jboss.ResourceManagersMetaDataMerger {
  public org.jboss.metadata.merge.ejb.jboss.ResourceManagersMetaDataMerger();
    Code:
       0: aload_0
       1: invokespecial #1                  // Method java/lang/Object."<init>":()V
       4: return

  public static void merge(org.jboss.metadata.ejb.jboss.ResourceManagersMetaData, org.jboss.metadata.ejb.jboss.ResourceManagersMetaData);
    Code:
       0: aload_1
       1: ifnull        37
       4: aload_1
       5: invokevirtual #2                  // Method org/jboss/metadata/ejb/jboss/ResourceManagersMetaData.iterator:()Ljava/util/Iterator;
       8: astore_2
       9: aload_2
      10: invokeinterface #3,  1            // InterfaceMethod java/util/Iterator.hasNext:()Z
      15: ifeq          37
      18: aload_2
      19: invokeinterface #4,  1            // InterfaceMethod java/util/Iterator.next:()Ljava/lang/Object;
      24: checkcast     #5                  // class org/jboss/metadata/ejb/jboss/ResourceManagerMetaData
      27: astore_3
      28: aload_0
      29: aload_3
      30: invokevirtual #6                  // Method org/jboss/metadata/ejb/jboss/ResourceManagersMetaData.add:(Lorg/jboss/metadata/javaee/support/MappableMetaData;)Z
      33: pop
      34: goto          9
      37: return
}
