Compiled from "HttpHeaders.java"
public final class io.dekorate.deps.okhttp3.internal.http.HttpHeaders {
  private static final io.dekorate.deps.okio.ByteString QUOTED_STRING_DELIMITERS;

  private static final io.dekorate.deps.okio.ByteString TOKEN_DELIMITERS;

  private io.dekorate.deps.okhttp3.internal.http.HttpHeaders();
    Code:
       0: aload_0
       1: invokespecial #17                 // Method java/lang/Object."<init>":()V
       4: return

  public static long contentLength(io.dekorate.deps.okhttp3.Response);
    Code:
       0: aload_0
       1: invokevirtual #27                 // Method io/dekorate/deps/okhttp3/Response.headers:()Lio/dekorate/deps/okhttp3/Headers;
       4: invokestatic  #30                 // Method contentLength:(Lio/dekorate/deps/okhttp3/Headers;)J
       7: lreturn

  public static long contentLength(io.dekorate.deps.okhttp3.Headers);
    Code:
       0: aload_0
       1: ldc           #34                 // String Content-Length
       3: invokevirtual #38                 // Method io/dekorate/deps/okhttp3/Headers.get:(Ljava/lang/String;)Ljava/lang/String;
       6: invokestatic  #42                 // Method stringToLong:(Ljava/lang/String;)J
       9: lreturn

  private static long stringToLong(java.lang.String);
    Code:
       0: aload_0
       1: ifnonnull     8
       4: ldc2_w        #46                 // long -1l
       7: lreturn
       8: aload_0
       9: invokestatic  #52                 // Method java/lang/Long.parseLong:(Ljava/lang/String;)J
      12: lreturn
      13: astore_1
      14: ldc2_w        #46                 // long -1l
      17: lreturn
    Exception table:
       from    to  target type
           8    12    13   Class java/lang/NumberFormatException

  public static boolean varyMatches(io.dekorate.deps.okhttp3.Response, io.dekorate.deps.okhttp3.Headers, io.dekorate.deps.okhttp3.Request);
    Code:
       0: aload_0
       1: invokestatic  #62                 // Method varyFields:(Lio/dekorate/deps/okhttp3/Response;)Ljava/util/Set;
       4: invokeinterface #68,  1           // InterfaceMethod java/util/Set.iterator:()Ljava/util/Iterator;
       9: astore_3
      10: aload_3
      11: invokeinterface #74,  1           // InterfaceMethod java/util/Iterator.hasNext:()Z
      16: ifeq          53
      19: aload_3
      20: invokeinterface #78,  1           // InterfaceMethod java/util/Iterator.next:()Ljava/lang/Object;
      25: checkcast     #80                 // class java/lang/String
      28: astore        4
      30: aload_1
      31: aload         4
      33: invokevirtual #84                 // Method io/dekorate/deps/okhttp3/Headers.values:(Ljava/lang/String;)Ljava/util/List;
      36: aload_2
      37: aload         4
      39: invokevirtual #88                 // Method io/dekorate/deps/okhttp3/Request.headers:(Ljava/lang/String;)Ljava/util/List;
      42: invokestatic  #94                 // Method io/dekorate/deps/okhttp3/internal/Util.equal:(Ljava/lang/Object;Ljava/lang/Object;)Z
      45: ifne          50
      48: iconst_0
      49: ireturn
      50: goto          10
      53: iconst_1
      54: ireturn

  public static boolean hasVaryAll(io.dekorate.deps.okhttp3.Response);
    Code:
       0: aload_0
       1: invokevirtual #27                 // Method io/dekorate/deps/okhttp3/Response.headers:()Lio/dekorate/deps/okhttp3/Headers;
       4: invokestatic  #104                // Method hasVaryAll:(Lio/dekorate/deps/okhttp3/Headers;)Z
       7: ireturn

  public static boolean hasVaryAll(io.dekorate.deps.okhttp3.Headers);
    Code:
       0: aload_0
       1: invokestatic  #107                // Method varyFields:(Lio/dekorate/deps/okhttp3/Headers;)Ljava/util/Set;
       4: ldc           #109                // String *
       6: invokeinterface #113,  2          // InterfaceMethod java/util/Set.contains:(Ljava/lang/Object;)Z
      11: ireturn

  private static java.util.Set<java.lang.String> varyFields(io.dekorate.deps.okhttp3.Response);
    Code:
       0: aload_0
       1: invokevirtual #27                 // Method io/dekorate/deps/okhttp3/Response.headers:()Lio/dekorate/deps/okhttp3/Headers;
       4: invokestatic  #107                // Method varyFields:(Lio/dekorate/deps/okhttp3/Headers;)Ljava/util/Set;
       7: areturn

  public static java.util.Set<java.lang.String> varyFields(io.dekorate.deps.okhttp3.Headers);
    Code:
       0: invokestatic  #122                // Method java/util/Collections.emptySet:()Ljava/util/Set;
       3: astore_1
       4: iconst_0
       5: istore_2
       6: aload_0
       7: invokevirtual #126                // Method io/dekorate/deps/okhttp3/Headers.size:()I
      10: istore_3
      11: iload_2
      12: iload_3
      13: if_icmpge     114
      16: ldc           #128                // String Vary
      18: aload_0
      19: iload_2
      20: invokevirtual #132                // Method io/dekorate/deps/okhttp3/Headers.name:(I)Ljava/lang/String;
      23: invokevirtual #136                // Method java/lang/String.equalsIgnoreCase:(Ljava/lang/String;)Z
      26: ifne          32
      29: goto          108
      32: aload_0
      33: iload_2
      34: invokevirtual #139                // Method io/dekorate/deps/okhttp3/Headers.value:(I)Ljava/lang/String;
      37: astore        4
      39: aload_1
      40: invokeinterface #142,  1          // InterfaceMethod java/util/Set.isEmpty:()Z
      45: ifeq          59
      48: new           #144                // class java/util/TreeSet
      51: dup
      52: getstatic     #148                // Field java/lang/String.CASE_INSENSITIVE_ORDER:Ljava/util/Comparator;
      55: invokespecial #151                // Method java/util/TreeSet."<init>":(Ljava/util/Comparator;)V
      58: astore_1
      59: aload         4
      61: ldc           #153                // String ,
      63: invokevirtual #157                // Method java/lang/String.split:(Ljava/lang/String;)[Ljava/lang/String;
      66: astore        5
      68: aload         5
      70: arraylength
      71: istore        6
      73: iconst_0
      74: istore        7
      76: iload         7
      78: iload         6
      80: if_icmpge     108
      83: aload         5
      85: iload         7
      87: aaload
      88: astore        8
      90: aload_1
      91: aload         8
      93: invokevirtual #163                // Method java/lang/String.trim:()Ljava/lang/String;
      96: invokeinterface #166,  2          // InterfaceMethod java/util/Set.add:(Ljava/lang/Object;)Z
     101: pop
     102: iinc          7, 1
     105: goto          76
     108: iinc          2, 1
     111: goto          11
     114: aload_1
     115: areturn

  public static io.dekorate.deps.okhttp3.Headers varyHeaders(io.dekorate.deps.okhttp3.Response);
    Code:
       0: aload_0
       1: invokevirtual #178                // Method io/dekorate/deps/okhttp3/Response.networkResponse:()Lio/dekorate/deps/okhttp3/Response;
       4: invokevirtual #182                // Method io/dekorate/deps/okhttp3/Response.request:()Lio/dekorate/deps/okhttp3/Request;
       7: invokevirtual #183                // Method io/dekorate/deps/okhttp3/Request.headers:()Lio/dekorate/deps/okhttp3/Headers;
      10: astore_1
      11: aload_0
      12: invokevirtual #27                 // Method io/dekorate/deps/okhttp3/Response.headers:()Lio/dekorate/deps/okhttp3/Headers;
      15: astore_2
      16: aload_1
      17: aload_2
      18: invokestatic  #186                // Method varyHeaders:(Lio/dekorate/deps/okhttp3/Headers;Lio/dekorate/deps/okhttp3/Headers;)Lio/dekorate/deps/okhttp3/Headers;
      21: areturn

  public static io.dekorate.deps.okhttp3.Headers varyHeaders(io.dekorate.deps.okhttp3.Headers, io.dekorate.deps.okhttp3.Headers);
    Code:
       0: aload_1
       1: invokestatic  #107                // Method varyFields:(Lio/dekorate/deps/okhttp3/Headers;)Ljava/util/Set;
       4: astore_2
       5: aload_2
       6: invokeinterface #142,  1          // InterfaceMethod java/util/Set.isEmpty:()Z
      11: ifeq          25
      14: new           #7                  // class io/dekorate/deps/okhttp3/Headers$Builder
      17: dup
      18: invokespecial #188                // Method io/dekorate/deps/okhttp3/Headers$Builder."<init>":()V
      21: invokevirtual #191                // Method io/dekorate/deps/okhttp3/Headers$Builder.build:()Lio/dekorate/deps/okhttp3/Headers;
      24: areturn
      25: new           #7                  // class io/dekorate/deps/okhttp3/Headers$Builder
      28: dup
      29: invokespecial #188                // Method io/dekorate/deps/okhttp3/Headers$Builder."<init>":()V
      32: astore_3
      33: iconst_0
      34: istore        4
      36: aload_0
      37: invokevirtual #126                // Method io/dekorate/deps/okhttp3/Headers.size:()I
      40: istore        5
      42: iload         4
      44: iload         5
      46: if_icmpge     87
      49: aload_0
      50: iload         4
      52: invokevirtual #132                // Method io/dekorate/deps/okhttp3/Headers.name:(I)Ljava/lang/String;
      55: astore        6
      57: aload_2
      58: aload         6
      60: invokeinterface #113,  2          // InterfaceMethod java/util/Set.contains:(Ljava/lang/Object;)Z
      65: ifeq          81
      68: aload_3
      69: aload         6
      71: aload_0
      72: iload         4
      74: invokevirtual #139                // Method io/dekorate/deps/okhttp3/Headers.value:(I)Ljava/lang/String;
      77: invokevirtual #194                // Method io/dekorate/deps/okhttp3/Headers$Builder.add:(Ljava/lang/String;Ljava/lang/String;)Lio/dekorate/deps/okhttp3/Headers$Builder;
      80: pop
      81: iinc          4, 1
      84: goto          42
      87: aload_3
      88: invokevirtual #191                // Method io/dekorate/deps/okhttp3/Headers$Builder.build:()Lio/dekorate/deps/okhttp3/Headers;
      91: areturn

  public static java.util.List<io.dekorate.deps.okhttp3.Challenge> parseChallenges(io.dekorate.deps.okhttp3.Headers, java.lang.String);
    Code:
       0: new           #201                // class java/util/ArrayList
       3: dup
       4: invokespecial #202                // Method java/util/ArrayList."<init>":()V
       7: astore_2
       8: iconst_0
       9: istore_3
      10: iload_3
      11: aload_0
      12: invokevirtual #126                // Method io/dekorate/deps/okhttp3/Headers.size:()I
      15: if_icmpge     59
      18: aload_1
      19: aload_0
      20: iload_3
      21: invokevirtual #132                // Method io/dekorate/deps/okhttp3/Headers.name:(I)Ljava/lang/String;
      24: invokevirtual #136                // Method java/lang/String.equalsIgnoreCase:(Ljava/lang/String;)Z
      27: ifeq          53
      30: new           #206                // class io/dekorate/deps/okio/Buffer
      33: dup
      34: invokespecial #207                // Method io/dekorate/deps/okio/Buffer."<init>":()V
      37: aload_0
      38: iload_3
      39: invokevirtual #139                // Method io/dekorate/deps/okhttp3/Headers.value:(I)Ljava/lang/String;
      42: invokevirtual #211                // Method io/dekorate/deps/okio/Buffer.writeUtf8:(Ljava/lang/String;)Lio/dekorate/deps/okio/Buffer;
      45: astore        4
      47: aload_2
      48: aload         4
      50: invokestatic  #215                // Method parseChallengeHeader:(Ljava/util/List;Lio/dekorate/deps/okio/Buffer;)V
      53: iinc          3, 1
      56: goto          10
      59: aload_2
      60: areturn

  private static void parseChallengeHeader(java.util.List<io.dekorate.deps.okhttp3.Challenge>, io.dekorate.deps.okio.Buffer);
    Code:
       0: aconst_null
       1: astore_2
       2: aload_2
       3: ifnonnull     21
       6: aload_1
       7: invokestatic  #226                // Method skipWhitespaceAndCommas:(Lio/dekorate/deps/okio/Buffer;)Z
      10: pop
      11: aload_1
      12: invokestatic  #230                // Method readToken:(Lio/dekorate/deps/okio/Buffer;)Ljava/lang/String;
      15: astore_2
      16: aload_2
      17: ifnonnull     21
      20: return
      21: aload_2
      22: astore_3
      23: aload_1
      24: invokestatic  #226                // Method skipWhitespaceAndCommas:(Lio/dekorate/deps/okio/Buffer;)Z
      27: istore        4
      29: aload_1
      30: invokestatic  #230                // Method readToken:(Lio/dekorate/deps/okio/Buffer;)Ljava/lang/String;
      33: astore_2
      34: aload_2
      35: ifnonnull     65
      38: aload_1
      39: invokevirtual #233                // Method io/dekorate/deps/okio/Buffer.exhausted:()Z
      42: ifne          46
      45: return
      46: aload_0
      47: new           #235                // class io/dekorate/deps/okhttp3/Challenge
      50: dup
      51: aload_3
      52: invokestatic  #239                // Method java/util/Collections.emptyMap:()Ljava/util/Map;
      55: invokespecial #242                // Method io/dekorate/deps/okhttp3/Challenge."<init>":(Ljava/lang/String;Ljava/util/Map;)V
      58: invokeinterface #243,  2          // InterfaceMethod java/util/List.add:(Ljava/lang/Object;)Z
      63: pop
      64: return
      65: aload_1
      66: bipush        61
      68: invokestatic  #247                // Method skipAll:(Lio/dekorate/deps/okio/Buffer;B)I
      71: istore        5
      73: aload_1
      74: invokestatic  #226                // Method skipWhitespaceAndCommas:(Lio/dekorate/deps/okio/Buffer;)Z
      77: istore        6
      79: iload         4
      81: ifne          147
      84: iload         6
      86: ifne          96
      89: aload_1
      90: invokevirtual #233                // Method io/dekorate/deps/okio/Buffer.exhausted:()Z
      93: ifeq          147
      96: aload_0
      97: new           #235                // class io/dekorate/deps/okhttp3/Challenge
     100: dup
     101: aload_3
     102: aconst_null
     103: checkcast     #80                 // class java/lang/String
     106: new           #249                // class java/lang/StringBuilder
     109: dup
     110: invokespecial #250                // Method java/lang/StringBuilder."<init>":()V
     113: aload_2
     114: invokevirtual #254                // Method java/lang/StringBuilder.append:(Ljava/lang/String;)Ljava/lang/StringBuilder;
     117: bipush        61
     119: iload         5
     121: invokestatic  #258                // Method repeat:(CI)Ljava/lang/String;
     124: invokevirtual #254                // Method java/lang/StringBuilder.append:(Ljava/lang/String;)Ljava/lang/StringBuilder;
     127: invokevirtual #261                // Method java/lang/StringBuilder.toString:()Ljava/lang/String;
     130: invokestatic  #265                // Method java/util/Collections.singletonMap:(Ljava/lang/Object;Ljava/lang/Object;)Ljava/util/Map;
     133: invokespecial #242                // Method io/dekorate/deps/okhttp3/Challenge."<init>":(Ljava/lang/String;Ljava/util/Map;)V
     136: invokeinterface #243,  2          // InterfaceMethod java/util/List.add:(Ljava/lang/Object;)Z
     141: pop
     142: aconst_null
     143: astore_2
     144: goto          2
     147: new           #267                // class java/util/LinkedHashMap
     150: dup
     151: invokespecial #268                // Method java/util/LinkedHashMap."<init>":()V
     154: astore        7
     156: iload         5
     158: aload_1
     159: bipush        61
     161: invokestatic  #247                // Method skipAll:(Lio/dekorate/deps/okio/Buffer;B)I
     164: iadd
     165: istore        5
     167: aload_2
     168: ifnonnull     194
     171: aload_1
     172: invokestatic  #230                // Method readToken:(Lio/dekorate/deps/okio/Buffer;)Ljava/lang/String;
     175: astore_2
     176: aload_1
     177: invokestatic  #226                // Method skipWhitespaceAndCommas:(Lio/dekorate/deps/okio/Buffer;)Z
     180: ifeq          186
     183: goto          294
     186: aload_1
     187: bipush        61
     189: invokestatic  #247                // Method skipAll:(Lio/dekorate/deps/okio/Buffer;B)I
     192: istore        5
     194: iload         5
     196: ifne          202
     199: goto          294
     202: iload         5
     204: iconst_1
     205: if_icmple     209
     208: return
     209: aload_1
     210: invokestatic  #226                // Method skipWhitespaceAndCommas:(Lio/dekorate/deps/okio/Buffer;)Z
     213: ifeq          217
     216: return
     217: aload_1
     218: invokevirtual #233                // Method io/dekorate/deps/okio/Buffer.exhausted:()Z
     221: ifne          241
     224: aload_1
     225: lconst_0
     226: invokevirtual #274                // Method io/dekorate/deps/okio/Buffer.getByte:(J)B
     229: bipush        34
     231: if_icmpne     241
     234: aload_1
     235: invokestatic  #277                // Method readQuotedString:(Lio/dekorate/deps/okio/Buffer;)Ljava/lang/String;
     238: goto          245
     241: aload_1
     242: invokestatic  #230                // Method readToken:(Lio/dekorate/deps/okio/Buffer;)Ljava/lang/String;
     245: astore        8
     247: aload         8
     249: ifnonnull     253
     252: return
     253: aload         7
     255: aload_2
     256: aload         8
     258: invokeinterface #281,  3          // InterfaceMethod java/util/Map.put:(Ljava/lang/Object;Ljava/lang/Object;)Ljava/lang/Object;
     263: checkcast     #80                 // class java/lang/String
     266: astore        9
     268: aconst_null
     269: astore_2
     270: aload         9
     272: ifnull        276
     275: return
     276: aload_1
     277: invokestatic  #226                // Method skipWhitespaceAndCommas:(Lio/dekorate/deps/okio/Buffer;)Z
     280: ifne          291
     283: aload_1
     284: invokevirtual #233                // Method io/dekorate/deps/okio/Buffer.exhausted:()Z
     287: ifne          291
     290: return
     291: goto          167
     294: aload_0
     295: new           #235                // class io/dekorate/deps/okhttp3/Challenge
     298: dup
     299: aload_3
     300: aload         7
     302: invokespecial #242                // Method io/dekorate/deps/okhttp3/Challenge."<init>":(Ljava/lang/String;Ljava/util/Map;)V
     305: invokeinterface #243,  2          // InterfaceMethod java/util/List.add:(Ljava/lang/Object;)Z
     310: pop
     311: goto          2

  private static boolean skipWhitespaceAndCommas(io.dekorate.deps.okio.Buffer);
    Code:
       0: iconst_0
       1: istore_1
       2: aload_0
       3: invokevirtual #233                // Method io/dekorate/deps/okio/Buffer.exhausted:()Z
       6: ifne          51
       9: aload_0
      10: lconst_0
      11: invokevirtual #274                // Method io/dekorate/deps/okio/Buffer.getByte:(J)B
      14: istore_2
      15: iload_2
      16: bipush        44
      18: if_icmpne     31
      21: aload_0
      22: invokevirtual #296                // Method io/dekorate/deps/okio/Buffer.readByte:()B
      25: pop
      26: iconst_1
      27: istore_1
      28: goto          48
      31: iload_2
      32: bipush        32
      34: if_icmpeq     43
      37: iload_2
      38: bipush        9
      40: if_icmpne     51
      43: aload_0
      44: invokevirtual #296                // Method io/dekorate/deps/okio/Buffer.readByte:()B
      47: pop
      48: goto          2
      51: iload_1
      52: ireturn

  private static int skipAll(io.dekorate.deps.okio.Buffer, byte);
    Code:
       0: iconst_0
       1: istore_2
       2: aload_0
       3: invokevirtual #233                // Method io/dekorate/deps/okio/Buffer.exhausted:()Z
       6: ifne          29
       9: aload_0
      10: lconst_0
      11: invokevirtual #274                // Method io/dekorate/deps/okio/Buffer.getByte:(J)B
      14: iload_1
      15: if_icmpne     29
      18: iinc          2, 1
      21: aload_0
      22: invokevirtual #296                // Method io/dekorate/deps/okio/Buffer.readByte:()B
      25: pop
      26: goto          2
      29: iload_2
      30: ireturn

  private static java.lang.String readQuotedString(io.dekorate.deps.okio.Buffer);
    Code:
       0: aload_0
       1: invokevirtual #296                // Method io/dekorate/deps/okio/Buffer.readByte:()B
       4: bipush        34
       6: if_icmpeq     17
       9: new           #303                // class java/lang/IllegalArgumentException
      12: dup
      13: invokespecial #304                // Method java/lang/IllegalArgumentException."<init>":()V
      16: athrow
      17: new           #206                // class io/dekorate/deps/okio/Buffer
      20: dup
      21: invokespecial #207                // Method io/dekorate/deps/okio/Buffer."<init>":()V
      24: astore_1
      25: aload_0
      26: getstatic     #306                // Field QUOTED_STRING_DELIMITERS:Lio/dekorate/deps/okio/ByteString;
      29: invokevirtual #310                // Method io/dekorate/deps/okio/Buffer.indexOfElement:(Lio/dekorate/deps/okio/ByteString;)J
      32: lstore_2
      33: lload_2
      34: ldc2_w        #46                 // long -1l
      37: lcmp
      38: ifne          43
      41: aconst_null
      42: areturn
      43: aload_0
      44: lload_2
      45: invokevirtual #274                // Method io/dekorate/deps/okio/Buffer.getByte:(J)B
      48: bipush        34
      50: if_icmpne     69
      53: aload_1
      54: aload_0
      55: lload_2
      56: invokevirtual #314                // Method io/dekorate/deps/okio/Buffer.write:(Lio/dekorate/deps/okio/Buffer;J)V
      59: aload_0
      60: invokevirtual #296                // Method io/dekorate/deps/okio/Buffer.readByte:()B
      63: pop
      64: aload_1
      65: invokevirtual #317                // Method io/dekorate/deps/okio/Buffer.readUtf8:()Ljava/lang/String;
      68: areturn
      69: aload_0
      70: invokevirtual #320                // Method io/dekorate/deps/okio/Buffer.size:()J
      73: lload_2
      74: lconst_1
      75: ladd
      76: lcmp
      77: ifne          82
      80: aconst_null
      81: areturn
      82: aload_1
      83: aload_0
      84: lload_2
      85: invokevirtual #314                // Method io/dekorate/deps/okio/Buffer.write:(Lio/dekorate/deps/okio/Buffer;J)V
      88: aload_0
      89: invokevirtual #296                // Method io/dekorate/deps/okio/Buffer.readByte:()B
      92: pop
      93: aload_1
      94: aload_0
      95: lconst_1
      96: invokevirtual #314                // Method io/dekorate/deps/okio/Buffer.write:(Lio/dekorate/deps/okio/Buffer;J)V
      99: goto          25

  private static java.lang.String readToken(io.dekorate.deps.okio.Buffer);
    Code:
       0: aload_0
       1: getstatic     #325                // Field TOKEN_DELIMITERS:Lio/dekorate/deps/okio/ByteString;
       4: invokevirtual #310                // Method io/dekorate/deps/okio/Buffer.indexOfElement:(Lio/dekorate/deps/okio/ByteString;)J
       7: lstore_1
       8: lload_1
       9: ldc2_w        #46                 // long -1l
      12: lcmp
      13: ifne          21
      16: aload_0
      17: invokevirtual #320                // Method io/dekorate/deps/okio/Buffer.size:()J
      20: lstore_1
      21: lload_1
      22: lconst_0
      23: lcmp
      24: ifeq          35
      27: aload_0
      28: lload_1
      29: invokevirtual #328                // Method io/dekorate/deps/okio/Buffer.readUtf8:(J)Ljava/lang/String;
      32: goto          36
      35: aconst_null
      36: areturn
      37: astore_1
      38: new           #330                // class java/lang/AssertionError
      41: dup
      42: invokespecial #331                // Method java/lang/AssertionError."<init>":()V
      45: athrow
    Exception table:
       from    to  target type
           0    36    37   Class java/io/EOFException

  private static java.lang.String repeat(char, int);
    Code:
       0: iload_1
       1: newarray       char
       3: astore_2
       4: aload_2
       5: iload_0
       6: invokestatic  #339                // Method java/util/Arrays.fill:([CC)V
       9: new           #80                 // class java/lang/String
      12: dup
      13: aload_2
      14: invokespecial #342                // Method java/lang/String."<init>":([C)V
      17: areturn

  public static void receiveHeaders(io.dekorate.deps.okhttp3.CookieJar, io.dekorate.deps.okhttp3.HttpUrl, io.dekorate.deps.okhttp3.Headers);
    Code:
       0: aload_0
       1: getstatic     #354                // Field io/dekorate/deps/okhttp3/CookieJar.NO_COOKIES:Lio/dekorate/deps/okhttp3/CookieJar;
       4: if_acmpne     8
       7: return
       8: aload_1
       9: aload_2
      10: invokestatic  #360                // Method io/dekorate/deps/okhttp3/Cookie.parseAll:(Lio/dekorate/deps/okhttp3/HttpUrl;Lio/dekorate/deps/okhttp3/Headers;)Ljava/util/List;
      13: astore_3
      14: aload_3
      15: invokeinterface #361,  1          // InterfaceMethod java/util/List.isEmpty:()Z
      20: ifeq          24
      23: return
      24: aload_0
      25: aload_1
      26: aload_3
      27: invokeinterface #365,  3          // InterfaceMethod io/dekorate/deps/okhttp3/CookieJar.saveFromResponse:(Lio/dekorate/deps/okhttp3/HttpUrl;Ljava/util/List;)V
      32: return

  public static boolean hasBody(io.dekorate.deps.okhttp3.Response);
    Code:
       0: aload_0
       1: invokevirtual #182                // Method io/dekorate/deps/okhttp3/Response.request:()Lio/dekorate/deps/okhttp3/Request;
       4: invokevirtual #374                // Method io/dekorate/deps/okhttp3/Request.method:()Ljava/lang/String;
       7: ldc_w         #376                // String HEAD
      10: invokevirtual #379                // Method java/lang/String.equals:(Ljava/lang/Object;)Z
      13: ifeq          18
      16: iconst_0
      17: ireturn
      18: aload_0
      19: invokevirtual #382                // Method io/dekorate/deps/okhttp3/Response.code:()I
      22: istore_1
      23: iload_1
      24: bipush        100
      26: if_icmplt     36
      29: iload_1
      30: sipush        200
      33: if_icmplt     52
      36: iload_1
      37: sipush        204
      40: if_icmpeq     52
      43: iload_1
      44: sipush        304
      47: if_icmpeq     52
      50: iconst_1
      51: ireturn
      52: aload_0
      53: invokestatic  #384                // Method contentLength:(Lio/dekorate/deps/okhttp3/Response;)J
      56: ldc2_w        #46                 // long -1l
      59: lcmp
      60: ifne          79
      63: ldc_w         #386                // String chunked
      66: aload_0
      67: ldc_w         #388                // String Transfer-Encoding
      70: invokevirtual #390                // Method io/dekorate/deps/okhttp3/Response.header:(Ljava/lang/String;)Ljava/lang/String;
      73: invokevirtual #136                // Method java/lang/String.equalsIgnoreCase:(Ljava/lang/String;)Z
      76: ifeq          81
      79: iconst_1
      80: ireturn
      81: iconst_0
      82: ireturn

  public static int skipUntil(java.lang.String, int, java.lang.String);
    Code:
       0: iload_1
       1: aload_0
       2: invokevirtual #396                // Method java/lang/String.length:()I
       5: if_icmpge     30
       8: aload_2
       9: aload_0
      10: iload_1
      11: invokevirtual #400                // Method java/lang/String.charAt:(I)C
      14: invokevirtual #404                // Method java/lang/String.indexOf:(I)I
      17: iconst_m1
      18: if_icmpeq     24
      21: goto          30
      24: iinc          1, 1
      27: goto          0
      30: iload_1
      31: ireturn

  public static int skipWhitespace(java.lang.String, int);
    Code:
       0: iload_1
       1: aload_0
       2: invokevirtual #396                // Method java/lang/String.length:()I
       5: if_icmpge     35
       8: aload_0
       9: iload_1
      10: invokevirtual #400                // Method java/lang/String.charAt:(I)C
      13: istore_2
      14: iload_2
      15: bipush        32
      17: if_icmpeq     29
      20: iload_2
      21: bipush        9
      23: if_icmpeq     29
      26: goto          35
      29: iinc          1, 1
      32: goto          0
      35: iload_1
      36: ireturn

  public static int parseSeconds(java.lang.String, int);
    Code:
       0: aload_0
       1: invokestatic  #52                 // Method java/lang/Long.parseLong:(Ljava/lang/String;)J
       4: lstore_2
       5: lload_2
       6: ldc2_w        #411                // long 2147483647l
       9: lcmp
      10: ifle          17
      13: ldc_w         #413                // int 2147483647
      16: ireturn
      17: lload_2
      18: lconst_0
      19: lcmp
      20: ifge          25
      23: iconst_0
      24: ireturn
      25: lload_2
      26: l2i
      27: ireturn
      28: astore_2
      29: iload_1
      30: ireturn
    Exception table:
       from    to  target type
           0    16    28   Class java/lang/NumberFormatException
          17    24    28   Class java/lang/NumberFormatException
          25    27    28   Class java/lang/NumberFormatException

  static {};
    Code:
       0: ldc_w         #418                // String \"\\
       3: invokestatic  #424                // Method io/dekorate/deps/okio/ByteString.encodeUtf8:(Ljava/lang/String;)Lio/dekorate/deps/okio/ByteString;
       6: putstatic     #306                // Field QUOTED_STRING_DELIMITERS:Lio/dekorate/deps/okio/ByteString;
       9: ldc_w         #426                // String \t ,=
      12: invokestatic  #424                // Method io/dekorate/deps/okio/ByteString.encodeUtf8:(Ljava/lang/String;)Lio/dekorate/deps/okio/ByteString;
      15: putstatic     #325                // Field TOKEN_DELIMITERS:Lio/dekorate/deps/okio/ByteString;
      18: return
}
