Compiled from "HttpMethod.java"
public final class io.dekorate.deps.okhttp3.internal.http.HttpMethod {
  public static boolean invalidatesCache(java.lang.String);
    Code:
       0: aload_0
       1: ldc           #9                  // String POST
       3: invokevirtual #15                 // Method java/lang/String.equals:(Ljava/lang/Object;)Z
       6: ifne          45
       9: aload_0
      10: ldc           #17                 // String PATCH
      12: invokevirtual #15                 // Method java/lang/String.equals:(Ljava/lang/Object;)Z
      15: ifne          45
      18: aload_0
      19: ldc           #19                 // String PUT
      21: invokevirtual #15                 // Method java/lang/String.equals:(Ljava/lang/Object;)Z
      24: ifne          45
      27: aload_0
      28: ldc           #21                 // String DELETE
      30: invokevirtual #15                 // Method java/lang/String.equals:(Ljava/lang/Object;)Z
      33: ifne          45
      36: aload_0
      37: ldc           #23                 // String MOVE
      39: invokevirtual #15                 // Method java/lang/String.equals:(Ljava/lang/Object;)Z
      42: ifeq          49
      45: iconst_1
      46: goto          50
      49: iconst_0
      50: ireturn

  public static boolean requiresRequestBody(java.lang.String);
    Code:
       0: aload_0
       1: ldc           #9                  // String POST
       3: invokevirtual #15                 // Method java/lang/String.equals:(Ljava/lang/Object;)Z
       6: ifne          45
       9: aload_0
      10: ldc           #19                 // String PUT
      12: invokevirtual #15                 // Method java/lang/String.equals:(Ljava/lang/Object;)Z
      15: ifne          45
      18: aload_0
      19: ldc           #17                 // String PATCH
      21: invokevirtual #15                 // Method java/lang/String.equals:(Ljava/lang/Object;)Z
      24: ifne          45
      27: aload_0
      28: ldc           #28                 // String PROPPATCH
      30: invokevirtual #15                 // Method java/lang/String.equals:(Ljava/lang/Object;)Z
      33: ifne          45
      36: aload_0
      37: ldc           #30                 // String REPORT
      39: invokevirtual #15                 // Method java/lang/String.equals:(Ljava/lang/Object;)Z
      42: ifeq          49
      45: iconst_1
      46: goto          50
      49: iconst_0
      50: ireturn

  public static boolean permitsRequestBody(java.lang.String);
    Code:
       0: aload_0
       1: ldc           #33                 // String GET
       3: invokevirtual #15                 // Method java/lang/String.equals:(Ljava/lang/Object;)Z
       6: ifne          22
       9: aload_0
      10: ldc           #35                 // String HEAD
      12: invokevirtual #15                 // Method java/lang/String.equals:(Ljava/lang/Object;)Z
      15: ifne          22
      18: iconst_1
      19: goto          23
      22: iconst_0
      23: ireturn

  public static boolean redirectsWithBody(java.lang.String);
    Code:
       0: aload_0
       1: ldc           #38                 // String PROPFIND
       3: invokevirtual #15                 // Method java/lang/String.equals:(Ljava/lang/Object;)Z
       6: ireturn

  public static boolean redirectsToGet(java.lang.String);
    Code:
       0: aload_0
       1: ldc           #38                 // String PROPFIND
       3: invokevirtual #15                 // Method java/lang/String.equals:(Ljava/lang/Object;)Z
       6: ifne          13
       9: iconst_1
      10: goto          14
      13: iconst_0
      14: ireturn

  private io.dekorate.deps.okhttp3.internal.http.HttpMethod();
    Code:
       0: aload_0
       1: invokespecial #43                 // Method java/lang/Object."<init>":()V
       4: return
}
