Compiled from "SearchMetadataImportManager.java"
public class org.protege.editor.owl.model.search.SearchMetadataImportManager {
  public org.protege.editor.owl.model.search.SearchMetadataImportManager();
    Code:
       0: aload_0
       1: invokespecial #1                  // Method java/lang/Object."<init>":()V
       4: return

  public java.util.List<org.protege.editor.owl.model.search.SearchMetadataImporter> getImporters();
    Code:
       0: new           #2                  // class java/util/ArrayList
       3: dup
       4: invokespecial #3                  // Method java/util/ArrayList."<init>":()V
       7: astore_1
       8: aload_1
       9: new           #4                  // class org/protege/editor/owl/model/search/DefaultSearchMetadataImporter
      12: dup
      13: invokespecial #5                  // Method org/protege/editor/owl/model/search/DefaultSearchMetadataImporter."<init>":()V
      16: invokeinterface #6,  2            // InterfaceMethod java/util/List.add:(Ljava/lang/Object;)Z
      21: pop
      22: aload_1
      23: areturn
}
