Compiled from "BucketNotificationConfiguration.java"
public class com.amazonaws.services.s3.model.BucketNotificationConfiguration implements java.io.Serializable {
  private java.util.Map<java.lang.String, com.amazonaws.services.s3.model.NotificationConfiguration> configurations;

  public com.amazonaws.services.s3.model.BucketNotificationConfiguration();
    Code:
       0: aload_0
       1: invokespecial #1                  // Method java/lang/Object."<init>":()V
       4: aload_0
       5: aconst_null
       6: putfield      #2                  // Field configurations:Ljava/util/Map;
       9: aload_0
      10: new           #3                  // class java/util/HashMap
      13: dup
      14: invokespecial #4                  // Method java/util/HashMap."<init>":()V
      17: putfield      #2                  // Field configurations:Ljava/util/Map;
      20: return

  public com.amazonaws.services.s3.model.BucketNotificationConfiguration(java.lang.String, com.amazonaws.services.s3.model.NotificationConfiguration);
    Code:
       0: aload_0
       1: invokespecial #1                  // Method java/lang/Object."<init>":()V
       4: aload_0
       5: aconst_null
       6: putfield      #2                  // Field configurations:Ljava/util/Map;
       9: aload_0
      10: new           #3                  // class java/util/HashMap
      13: dup
      14: invokespecial #4                  // Method java/util/HashMap."<init>":()V
      17: putfield      #2                  // Field configurations:Ljava/util/Map;
      20: aload_0
      21: aload_1
      22: aload_2
      23: invokevirtual #5                  // Method addConfiguration:(Ljava/lang/String;Lcom/amazonaws/services/s3/model/NotificationConfiguration;)Lcom/amazonaws/services/s3/model/BucketNotificationConfiguration;
      26: pop
      27: return

  public com.amazonaws.services.s3.model.BucketNotificationConfiguration withNotificationConfiguration(java.util.Map<java.lang.String, com.amazonaws.services.s3.model.NotificationConfiguration>);
    Code:
       0: aload_0
       1: getfield      #2                  // Field configurations:Ljava/util/Map;
       4: invokeinterface #6,  1            // InterfaceMethod java/util/Map.clear:()V
       9: aload_0
      10: getfield      #2                  // Field configurations:Ljava/util/Map;
      13: aload_1
      14: invokeinterface #7,  2            // InterfaceMethod java/util/Map.putAll:(Ljava/util/Map;)V
      19: aload_0
      20: areturn

  public com.amazonaws.services.s3.model.BucketNotificationConfiguration addConfiguration(java.lang.String, com.amazonaws.services.s3.model.NotificationConfiguration);
    Code:
       0: aload_0
       1: getfield      #2                  // Field configurations:Ljava/util/Map;
       4: aload_1
       5: aload_2
       6: invokeinterface #8,  3            // InterfaceMethod java/util/Map.put:(Ljava/lang/Object;Ljava/lang/Object;)Ljava/lang/Object;
      11: pop
      12: aload_0
      13: areturn

  public java.util.Map<java.lang.String, com.amazonaws.services.s3.model.NotificationConfiguration> getConfigurations();
    Code:
       0: aload_0
       1: getfield      #2                  // Field configurations:Ljava/util/Map;
       4: areturn

  public void setConfigurations(java.util.Map<java.lang.String, com.amazonaws.services.s3.model.NotificationConfiguration>);
    Code:
       0: aload_0
       1: aload_1
       2: putfield      #2                  // Field configurations:Ljava/util/Map;
       5: return

  public com.amazonaws.services.s3.model.NotificationConfiguration getConfigurationByName(java.lang.String);
    Code:
       0: aload_0
       1: getfield      #2                  // Field configurations:Ljava/util/Map;
       4: aload_1
       5: invokeinterface #9,  2            // InterfaceMethod java/util/Map.get:(Ljava/lang/Object;)Ljava/lang/Object;
      10: checkcast     #10                 // class com/amazonaws/services/s3/model/NotificationConfiguration
      13: areturn

  public com.amazonaws.services.s3.model.NotificationConfiguration removeConfiguration(java.lang.String);
    Code:
       0: aload_0
       1: getfield      #2                  // Field configurations:Ljava/util/Map;
       4: aload_1
       5: invokeinterface #11,  2           // InterfaceMethod java/util/Map.remove:(Ljava/lang/Object;)Ljava/lang/Object;
      10: checkcast     #10                 // class com/amazonaws/services/s3/model/NotificationConfiguration
      13: areturn

  public com.amazonaws.services.s3.model.BucketNotificationConfiguration(java.util.Collection<com.amazonaws.services.s3.model.BucketNotificationConfiguration$TopicConfiguration>);
    Code:
       0: aload_0
       1: invokespecial #1                  // Method java/lang/Object."<init>":()V
       4: aload_0
       5: aconst_null
       6: putfield      #2                  // Field configurations:Ljava/util/Map;
       9: aload_0
      10: new           #3                  // class java/util/HashMap
      13: dup
      14: invokespecial #4                  // Method java/util/HashMap."<init>":()V
      17: putfield      #2                  // Field configurations:Ljava/util/Map;
      20: aload_1
      21: ifnull        65
      24: aload_1
      25: invokeinterface #12,  1           // InterfaceMethod java/util/Collection.iterator:()Ljava/util/Iterator;
      30: astore_2
      31: aload_2
      32: invokeinterface #13,  1           // InterfaceMethod java/util/Iterator.hasNext:()Z
      37: ifeq          65
      40: aload_2
      41: invokeinterface #14,  1           // InterfaceMethod java/util/Iterator.next:()Ljava/lang/Object;
      46: checkcast     #15                 // class com/amazonaws/services/s3/model/BucketNotificationConfiguration$TopicConfiguration
      49: astore_3
      50: aload_0
      51: invokestatic  #16                 // Method java/util/UUID.randomUUID:()Ljava/util/UUID;
      54: invokevirtual #17                 // Method java/util/UUID.toString:()Ljava/lang/String;
      57: aload_3
      58: invokevirtual #5                  // Method addConfiguration:(Ljava/lang/String;Lcom/amazonaws/services/s3/model/NotificationConfiguration;)Lcom/amazonaws/services/s3/model/BucketNotificationConfiguration;
      61: pop
      62: goto          31
      65: return

  public com.amazonaws.services.s3.model.BucketNotificationConfiguration withTopicConfigurations(com.amazonaws.services.s3.model.BucketNotificationConfiguration$TopicConfiguration...);
    Code:
       0: aload_0
       1: aload_1
       2: invokestatic  #18                 // Method java/util/Arrays.asList:([Ljava/lang/Object;)Ljava/util/List;
       5: invokevirtual #19                 // Method setTopicConfigurations:(Ljava/util/Collection;)V
       8: aload_0
       9: areturn

  public void setTopicConfigurations(java.util.Collection<com.amazonaws.services.s3.model.BucketNotificationConfiguration$TopicConfiguration>);
    Code:
       0: aload_0
       1: getfield      #2                  // Field configurations:Ljava/util/Map;
       4: invokeinterface #6,  1            // InterfaceMethod java/util/Map.clear:()V
       9: aload_1
      10: ifnull        54
      13: aload_1
      14: invokeinterface #12,  1           // InterfaceMethod java/util/Collection.iterator:()Ljava/util/Iterator;
      19: astore_2
      20: aload_2
      21: invokeinterface #13,  1           // InterfaceMethod java/util/Iterator.hasNext:()Z
      26: ifeq          54
      29: aload_2
      30: invokeinterface #14,  1           // InterfaceMethod java/util/Iterator.next:()Ljava/lang/Object;
      35: checkcast     #15                 // class com/amazonaws/services/s3/model/BucketNotificationConfiguration$TopicConfiguration
      38: astore_3
      39: aload_0
      40: invokestatic  #16                 // Method java/util/UUID.randomUUID:()Ljava/util/UUID;
      43: invokevirtual #17                 // Method java/util/UUID.toString:()Ljava/lang/String;
      46: aload_3
      47: invokevirtual #5                  // Method addConfiguration:(Ljava/lang/String;Lcom/amazonaws/services/s3/model/NotificationConfiguration;)Lcom/amazonaws/services/s3/model/BucketNotificationConfiguration;
      50: pop
      51: goto          20
      54: return

  public java.util.List<com.amazonaws.services.s3.model.BucketNotificationConfiguration$TopicConfiguration> getTopicConfigurations();
    Code:
       0: new           #20                 // class java/util/ArrayList
       3: dup
       4: invokespecial #21                 // Method java/util/ArrayList."<init>":()V
       7: astore_1
       8: aload_0
       9: getfield      #2                  // Field configurations:Ljava/util/Map;
      12: invokeinterface #22,  1           // InterfaceMethod java/util/Map.entrySet:()Ljava/util/Set;
      17: invokeinterface #23,  1           // InterfaceMethod java/util/Set.iterator:()Ljava/util/Iterator;
      22: astore_2
      23: aload_2
      24: invokeinterface #13,  1           // InterfaceMethod java/util/Iterator.hasNext:()Z
      29: ifeq          73
      32: aload_2
      33: invokeinterface #14,  1           // InterfaceMethod java/util/Iterator.next:()Ljava/lang/Object;
      38: checkcast     #24                 // class java/util/Map$Entry
      41: astore_3
      42: aload_3
      43: invokeinterface #25,  1           // InterfaceMethod java/util/Map$Entry.getValue:()Ljava/lang/Object;
      48: instanceof    #15                 // class com/amazonaws/services/s3/model/BucketNotificationConfiguration$TopicConfiguration
      51: ifeq          70
      54: aload_1
      55: aload_3
      56: invokeinterface #25,  1           // InterfaceMethod java/util/Map$Entry.getValue:()Ljava/lang/Object;
      61: checkcast     #15                 // class com/amazonaws/services/s3/model/BucketNotificationConfiguration$TopicConfiguration
      64: invokeinterface #26,  2           // InterfaceMethod java/util/List.add:(Ljava/lang/Object;)Z
      69: pop
      70: goto          23
      73: aload_1
      74: areturn

  public java.lang.String toString();
    Code:
       0: aload_0
       1: invokevirtual #27                 // Method getConfigurations:()Ljava/util/Map;
       4: invokestatic  #28                 // Method com/amazonaws/util/json/Jackson.toJsonString:(Ljava/lang/Object;)Ljava/lang/String;
       7: areturn
}
