Compiled from "CannedAccessControlList.java"
public final class com.amazonaws.services.s3.model.CannedAccessControlList extends java.lang.Enum<com.amazonaws.services.s3.model.CannedAccessControlList> {
  public static final com.amazonaws.services.s3.model.CannedAccessControlList Private;

  public static final com.amazonaws.services.s3.model.CannedAccessControlList PublicRead;

  public static final com.amazonaws.services.s3.model.CannedAccessControlList PublicReadWrite;

  public static final com.amazonaws.services.s3.model.CannedAccessControlList AuthenticatedRead;

  public static final com.amazonaws.services.s3.model.CannedAccessControlList LogDeliveryWrite;

  public static final com.amazonaws.services.s3.model.CannedAccessControlList BucketOwnerRead;

  public static final com.amazonaws.services.s3.model.CannedAccessControlList BucketOwnerFullControl;

  public static final com.amazonaws.services.s3.model.CannedAccessControlList AwsExecRead;

  private final java.lang.String cannedAclHeader;

  private static final com.amazonaws.services.s3.model.CannedAccessControlList[] $VALUES;

  public static com.amazonaws.services.s3.model.CannedAccessControlList[] values();
    Code:
       0: getstatic     #1                  // Field $VALUES:[Lcom/amazonaws/services/s3/model/CannedAccessControlList;
       3: invokevirtual #2                  // Method "[Lcom/amazonaws/services/s3/model/CannedAccessControlList;".clone:()Ljava/lang/Object;
       6: checkcast     #3                  // class "[Lcom/amazonaws/services/s3/model/CannedAccessControlList;"
       9: areturn

  public static com.amazonaws.services.s3.model.CannedAccessControlList valueOf(java.lang.String);
    Code:
       0: ldc           #4                  // class com/amazonaws/services/s3/model/CannedAccessControlList
       2: aload_0
       3: invokestatic  #5                  // Method java/lang/Enum.valueOf:(Ljava/lang/Class;Ljava/lang/String;)Ljava/lang/Enum;
       6: checkcast     #4                  // class com/amazonaws/services/s3/model/CannedAccessControlList
       9: areturn

  private com.amazonaws.services.s3.model.CannedAccessControlList(java.lang.String);
    Code:
       0: aload_0
       1: aload_1
       2: iload_2
       3: invokespecial #6                  // Method java/lang/Enum."<init>":(Ljava/lang/String;I)V
       6: aload_0
       7: aload_3
       8: putfield      #7                  // Field cannedAclHeader:Ljava/lang/String;
      11: return

  public java.lang.String toString();
    Code:
       0: aload_0
       1: getfield      #7                  // Field cannedAclHeader:Ljava/lang/String;
       4: areturn

  static {};
    Code:
       0: new           #4                  // class com/amazonaws/services/s3/model/CannedAccessControlList
       3: dup
       4: ldc           #8                  // String Private
       6: iconst_0
       7: ldc           #9                  // String private
       9: invokespecial #10                 // Method "<init>":(Ljava/lang/String;ILjava/lang/String;)V
      12: putstatic     #11                 // Field Private:Lcom/amazonaws/services/s3/model/CannedAccessControlList;
      15: new           #4                  // class com/amazonaws/services/s3/model/CannedAccessControlList
      18: dup
      19: ldc           #12                 // String PublicRead
      21: iconst_1
      22: ldc           #13                 // String public-read
      24: invokespecial #10                 // Method "<init>":(Ljava/lang/String;ILjava/lang/String;)V
      27: putstatic     #14                 // Field PublicRead:Lcom/amazonaws/services/s3/model/CannedAccessControlList;
      30: new           #4                  // class com/amazonaws/services/s3/model/CannedAccessControlList
      33: dup
      34: ldc           #15                 // String PublicReadWrite
      36: iconst_2
      37: ldc           #16                 // String public-read-write
      39: invokespecial #10                 // Method "<init>":(Ljava/lang/String;ILjava/lang/String;)V
      42: putstatic     #17                 // Field PublicReadWrite:Lcom/amazonaws/services/s3/model/CannedAccessControlList;
      45: new           #4                  // class com/amazonaws/services/s3/model/CannedAccessControlList
      48: dup
      49: ldc           #18                 // String AuthenticatedRead
      51: iconst_3
      52: ldc           #19                 // String authenticated-read
      54: invokespecial #10                 // Method "<init>":(Ljava/lang/String;ILjava/lang/String;)V
      57: putstatic     #20                 // Field AuthenticatedRead:Lcom/amazonaws/services/s3/model/CannedAccessControlList;
      60: new           #4                  // class com/amazonaws/services/s3/model/CannedAccessControlList
      63: dup
      64: ldc           #21                 // String LogDeliveryWrite
      66: iconst_4
      67: ldc           #22                 // String log-delivery-write
      69: invokespecial #10                 // Method "<init>":(Ljava/lang/String;ILjava/lang/String;)V
      72: putstatic     #23                 // Field LogDeliveryWrite:Lcom/amazonaws/services/s3/model/CannedAccessControlList;
      75: new           #4                  // class com/amazonaws/services/s3/model/CannedAccessControlList
      78: dup
      79: ldc           #24                 // String BucketOwnerRead
      81: iconst_5
      82: ldc           #25                 // String bucket-owner-read
      84: invokespecial #10                 // Method "<init>":(Ljava/lang/String;ILjava/lang/String;)V
      87: putstatic     #26                 // Field BucketOwnerRead:Lcom/amazonaws/services/s3/model/CannedAccessControlList;
      90: new           #4                  // class com/amazonaws/services/s3/model/CannedAccessControlList
      93: dup
      94: ldc           #27                 // String BucketOwnerFullControl
      96: bipush        6
      98: ldc           #28                 // String bucket-owner-full-control
     100: invokespecial #10                 // Method "<init>":(Ljava/lang/String;ILjava/lang/String;)V
     103: putstatic     #29                 // Field BucketOwnerFullControl:Lcom/amazonaws/services/s3/model/CannedAccessControlList;
     106: new           #4                  // class com/amazonaws/services/s3/model/CannedAccessControlList
     109: dup
     110: ldc           #30                 // String AwsExecRead
     112: bipush        7
     114: ldc           #31                 // String aws-exec-read
     116: invokespecial #10                 // Method "<init>":(Ljava/lang/String;ILjava/lang/String;)V
     119: putstatic     #32                 // Field AwsExecRead:Lcom/amazonaws/services/s3/model/CannedAccessControlList;
     122: bipush        8
     124: anewarray     #4                  // class com/amazonaws/services/s3/model/CannedAccessControlList
     127: dup
     128: iconst_0
     129: getstatic     #11                 // Field Private:Lcom/amazonaws/services/s3/model/CannedAccessControlList;
     132: aastore
     133: dup
     134: iconst_1
     135: getstatic     #14                 // Field PublicRead:Lcom/amazonaws/services/s3/model/CannedAccessControlList;
     138: aastore
     139: dup
     140: iconst_2
     141: getstatic     #17                 // Field PublicReadWrite:Lcom/amazonaws/services/s3/model/CannedAccessControlList;
     144: aastore
     145: dup
     146: iconst_3
     147: getstatic     #20                 // Field AuthenticatedRead:Lcom/amazonaws/services/s3/model/CannedAccessControlList;
     150: aastore
     151: dup
     152: iconst_4
     153: getstatic     #23                 // Field LogDeliveryWrite:Lcom/amazonaws/services/s3/model/CannedAccessControlList;
     156: aastore
     157: dup
     158: iconst_5
     159: getstatic     #26                 // Field BucketOwnerRead:Lcom/amazonaws/services/s3/model/CannedAccessControlList;
     162: aastore
     163: dup
     164: bipush        6
     166: getstatic     #29                 // Field BucketOwnerFullControl:Lcom/amazonaws/services/s3/model/CannedAccessControlList;
     169: aastore
     170: dup
     171: bipush        7
     173: getstatic     #32                 // Field AwsExecRead:Lcom/amazonaws/services/s3/model/CannedAccessControlList;
     176: aastore
     177: putstatic     #1                  // Field $VALUES:[Lcom/amazonaws/services/s3/model/CannedAccessControlList;
     180: return
}
