Compiled from "DeleteObjectsResult.java"
public class com.amazonaws.services.s3.model.DeleteObjectsResult$DeletedObject implements java.io.Serializable {
  private java.lang.String key;

  private java.lang.String versionId;

  private boolean deleteMarker;

  private java.lang.String deleteMarkerVersionId;

  public com.amazonaws.services.s3.model.DeleteObjectsResult$DeletedObject();
    Code:
       0: aload_0
       1: invokespecial #1                  // Method java/lang/Object."<init>":()V
       4: return

  public java.lang.String getKey();
    Code:
       0: aload_0
       1: getfield      #2                  // Field key:Ljava/lang/String;
       4: areturn

  public void setKey(java.lang.String);
    Code:
       0: aload_0
       1: aload_1
       2: putfield      #2                  // Field key:Ljava/lang/String;
       5: return

  public java.lang.String getVersionId();
    Code:
       0: aload_0
       1: getfield      #3                  // Field versionId:Ljava/lang/String;
       4: areturn

  public void setVersionId(java.lang.String);
    Code:
       0: aload_0
       1: aload_1
       2: putfield      #3                  // Field versionId:Ljava/lang/String;
       5: return

  public boolean isDeleteMarker();
    Code:
       0: aload_0
       1: getfield      #4                  // Field deleteMarker:Z
       4: ireturn

  public void setDeleteMarker(boolean);
    Code:
       0: aload_0
       1: iload_1
       2: putfield      #4                  // Field deleteMarker:Z
       5: return

  public java.lang.String getDeleteMarkerVersionId();
    Code:
       0: aload_0
       1: getfield      #5                  // Field deleteMarkerVersionId:Ljava/lang/String;
       4: areturn

  public void setDeleteMarkerVersionId(java.lang.String);
    Code:
       0: aload_0
       1: aload_1
       2: putfield      #5                  // Field deleteMarkerVersionId:Ljava/lang/String;
       5: return
}
