Compiled from "HeadBucketResult.java"
public class com.amazonaws.services.s3.model.HeadBucketResult implements java.io.Serializable {
  private java.lang.String bucketRegion;

  public com.amazonaws.services.s3.model.HeadBucketResult();
    Code:
       0: aload_0
       1: invokespecial #1                  // Method java/lang/Object."<init>":()V
       4: return

  public java.lang.String getBucketRegion();
    Code:
       0: aload_0
       1: getfield      #2                  // Field bucketRegion:Ljava/lang/String;
       4: areturn

  public void setBucketRegion(java.lang.String);
    Code:
       0: aload_0
       1: aload_1
       2: putfield      #2                  // Field bucketRegion:Ljava/lang/String;
       5: return

  public com.amazonaws.services.s3.model.HeadBucketResult withBucketRegion(java.lang.String);
    Code:
       0: aload_0
       1: aload_1
       2: invokevirtual #3                  // Method setBucketRegion:(Ljava/lang/String;)V
       5: aload_0
       6: areturn
}
