Compiled from "JdrConsumer.java"
public interface org.wildfly.swarm.config.JdrConsumer<T extends org.wildfly.swarm.config.Jdr<T>> {
  public abstract void accept(T);

  public default org.wildfly.swarm.config.JdrConsumer<T> andThen(org.wildfly.swarm.config.JdrConsumer<T>);
    Code:
       0: aload_0
       1: aload_1
       2: invokedynamic #1,  0              // InvokeDynamic #0:accept:(Lorg/wildfly/swarm/config/JdrConsumer;Lorg/wildfly/swarm/config/JdrConsumer;)Lorg/wildfly/swarm/config/JdrConsumer;
       7: areturn

  private void lambda$andThen$521(org.wildfly.swarm.config.JdrConsumer, org.wildfly.swarm.config.Jdr);
    Code:
       0: aload_0
       1: aload_2
       2: invokeinterface #2,  2            // InterfaceMethod accept:(Lorg/wildfly/swarm/config/Jdr;)V
       7: aload_1
       8: aload_2
       9: invokeinterface #2,  2            // InterfaceMethod accept:(Lorg/wildfly/swarm/config/Jdr;)V
      14: return
}
