Compiled from "Security.java"
public class org.wildfly.swarm.config.Security<T extends org.wildfly.swarm.config.Security<T>> extends java.util.HashMap {
  private java.lang.String key;

  private java.beans.PropertyChangeSupport pcs;

  private org.wildfly.swarm.config.Security$SecurityResources subresources;

  private java.lang.Boolean deepCopySubjectMode;

  public org.wildfly.swarm.config.Security();
    Code:
       0: aload_0
       1: invokespecial #1                  // Method java/util/HashMap."<init>":()V
       4: aload_0
       5: new           #2                  // class org/wildfly/swarm/config/Security$SecurityResources
       8: dup
       9: invokespecial #3                  // Method org/wildfly/swarm/config/Security$SecurityResources."<init>":()V
      12: putfield      #4                  // Field subresources:Lorg/wildfly/swarm/config/Security$SecurityResources;
      15: aload_0
      16: ldc           #5                  // String security
      18: putfield      #6                  // Field key:Ljava/lang/String;
      21: aload_0
      22: new           #7                  // class java/beans/PropertyChangeSupport
      25: dup
      26: aload_0
      27: invokespecial #8                  // Method java/beans/PropertyChangeSupport."<init>":(Ljava/lang/Object;)V
      30: putfield      #9                  // Field pcs:Ljava/beans/PropertyChangeSupport;
      33: return

  public java.lang.String getKey();
    Code:
       0: aload_0
       1: getfield      #6                  // Field key:Ljava/lang/String;
       4: areturn

  public void addPropertyChangeListener(java.beans.PropertyChangeListener);
    Code:
       0: aconst_null
       1: aload_0
       2: getfield      #9                  // Field pcs:Ljava/beans/PropertyChangeSupport;
       5: if_acmpne     20
       8: aload_0
       9: new           #7                  // class java/beans/PropertyChangeSupport
      12: dup
      13: aload_0
      14: invokespecial #8                  // Method java/beans/PropertyChangeSupport."<init>":(Ljava/lang/Object;)V
      17: putfield      #9                  // Field pcs:Ljava/beans/PropertyChangeSupport;
      20: aload_0
      21: getfield      #9                  // Field pcs:Ljava/beans/PropertyChangeSupport;
      24: aload_1
      25: invokevirtual #10                 // Method java/beans/PropertyChangeSupport.addPropertyChangeListener:(Ljava/beans/PropertyChangeListener;)V
      28: return

  public void removePropertyChangeListener(java.beans.PropertyChangeListener);
    Code:
       0: aload_0
       1: getfield      #9                  // Field pcs:Ljava/beans/PropertyChangeSupport;
       4: ifnull        15
       7: aload_0
       8: getfield      #9                  // Field pcs:Ljava/beans/PropertyChangeSupport;
      11: aload_1
      12: invokevirtual #11                 // Method java/beans/PropertyChangeSupport.removePropertyChangeListener:(Ljava/beans/PropertyChangeListener;)V
      15: return

  public org.wildfly.swarm.config.Security$SecurityResources subresources();
    Code:
       0: aload_0
       1: getfield      #4                  // Field subresources:Lorg/wildfly/swarm/config/Security$SecurityResources;
       4: areturn

  public T securityDomains(java.util.List<org.wildfly.swarm.config.security.SecurityDomain>);
    Code:
       0: aload_0
       1: getfield      #4                  // Field subresources:Lorg/wildfly/swarm/config/Security$SecurityResources;
       4: aload_1
       5: invokestatic  #12                 // Method org/wildfly/swarm/config/Security$SecurityResources.access$002:(Lorg/wildfly/swarm/config/Security$SecurityResources;Ljava/util/List;)Ljava/util/List;
       8: pop
       9: aload_0
      10: areturn

  public T securityDomain(org.wildfly.swarm.config.security.SecurityDomain);
    Code:
       0: aload_0
       1: getfield      #4                  // Field subresources:Lorg/wildfly/swarm/config/Security$SecurityResources;
       4: invokestatic  #13                 // Method org/wildfly/swarm/config/Security$SecurityResources.access$000:(Lorg/wildfly/swarm/config/Security$SecurityResources;)Ljava/util/List;
       7: aload_1
       8: invokeinterface #14,  2           // InterfaceMethod java/util/List.add:(Ljava/lang/Object;)Z
      13: pop
      14: aload_0
      15: areturn

  public T securityDomain(java.lang.String, org.wildfly.swarm.config.security.SecurityDomainConsumer);
    Code:
       0: new           #15                 // class org/wildfly/swarm/config/security/SecurityDomain
       3: dup
       4: aload_1
       5: invokespecial #16                 // Method org/wildfly/swarm/config/security/SecurityDomain."<init>":(Ljava/lang/String;)V
       8: astore_3
       9: aload_2
      10: ifnull        20
      13: aload_2
      14: aload_3
      15: invokeinterface #17,  2           // InterfaceMethod org/wildfly/swarm/config/security/SecurityDomainConsumer.accept:(Lorg/wildfly/swarm/config/security/SecurityDomain;)V
      20: aload_0
      21: aload_3
      22: invokevirtual #18                 // Method securityDomain:(Lorg/wildfly/swarm/config/security/SecurityDomain;)Lorg/wildfly/swarm/config/Security;
      25: pop
      26: aload_0
      27: areturn

  public T securityDomain(java.lang.String);
    Code:
       0: aload_0
       1: aload_1
       2: aconst_null
       3: invokevirtual #19                 // Method securityDomain:(Ljava/lang/String;Lorg/wildfly/swarm/config/security/SecurityDomainConsumer;)Lorg/wildfly/swarm/config/Security;
       6: pop
       7: aload_0
       8: areturn

  public T securityDomain(org.wildfly.swarm.config.security.SecurityDomainSupplier);
    Code:
       0: aload_0
       1: aload_1
       2: invokeinterface #20,  1           // InterfaceMethod org/wildfly/swarm/config/security/SecurityDomainSupplier.get:()Lorg/wildfly/swarm/config/security/SecurityDomain;
       7: invokevirtual #18                 // Method securityDomain:(Lorg/wildfly/swarm/config/security/SecurityDomain;)Lorg/wildfly/swarm/config/Security;
      10: pop
      11: aload_0
      12: areturn

  public T classicVault(org.wildfly.swarm.config.security.ClassicVault);
    Code:
       0: aload_0
       1: getfield      #4                  // Field subresources:Lorg/wildfly/swarm/config/Security$SecurityResources;
       4: aload_1
       5: invokestatic  #21                 // Method org/wildfly/swarm/config/Security$SecurityResources.access$102:(Lorg/wildfly/swarm/config/Security$SecurityResources;Lorg/wildfly/swarm/config/security/ClassicVault;)Lorg/wildfly/swarm/config/security/ClassicVault;
       8: pop
       9: aload_0
      10: areturn

  public T classicVault(org.wildfly.swarm.config.security.ClassicVaultConsumer);
    Code:
       0: new           #22                 // class org/wildfly/swarm/config/security/ClassicVault
       3: dup
       4: invokespecial #23                 // Method org/wildfly/swarm/config/security/ClassicVault."<init>":()V
       7: astore_2
       8: aload_1
       9: ifnull        19
      12: aload_1
      13: aload_2
      14: invokeinterface #24,  2           // InterfaceMethod org/wildfly/swarm/config/security/ClassicVaultConsumer.accept:(Lorg/wildfly/swarm/config/security/ClassicVault;)V
      19: aload_0
      20: getfield      #4                  // Field subresources:Lorg/wildfly/swarm/config/Security$SecurityResources;
      23: aload_2
      24: invokestatic  #21                 // Method org/wildfly/swarm/config/Security$SecurityResources.access$102:(Lorg/wildfly/swarm/config/Security$SecurityResources;Lorg/wildfly/swarm/config/security/ClassicVault;)Lorg/wildfly/swarm/config/security/ClassicVault;
      27: pop
      28: aload_0
      29: areturn

  public T classicVault();
    Code:
       0: new           #22                 // class org/wildfly/swarm/config/security/ClassicVault
       3: dup
       4: invokespecial #23                 // Method org/wildfly/swarm/config/security/ClassicVault."<init>":()V
       7: astore_1
       8: aload_0
       9: getfield      #4                  // Field subresources:Lorg/wildfly/swarm/config/Security$SecurityResources;
      12: aload_1
      13: invokestatic  #21                 // Method org/wildfly/swarm/config/Security$SecurityResources.access$102:(Lorg/wildfly/swarm/config/Security$SecurityResources;Lorg/wildfly/swarm/config/security/ClassicVault;)Lorg/wildfly/swarm/config/security/ClassicVault;
      16: pop
      17: aload_0
      18: areturn

  public T classicVault(org.wildfly.swarm.config.security.ClassicVaultSupplier);
    Code:
       0: aload_0
       1: getfield      #4                  // Field subresources:Lorg/wildfly/swarm/config/Security$SecurityResources;
       4: aload_1
       5: invokeinterface #25,  1           // InterfaceMethod org/wildfly/swarm/config/security/ClassicVaultSupplier.get:()Lorg/wildfly/swarm/config/security/ClassicVault;
      10: invokestatic  #21                 // Method org/wildfly/swarm/config/Security$SecurityResources.access$102:(Lorg/wildfly/swarm/config/Security$SecurityResources;Lorg/wildfly/swarm/config/security/ClassicVault;)Lorg/wildfly/swarm/config/security/ClassicVault;
      13: pop
      14: aload_0
      15: areturn

  public java.lang.Boolean deepCopySubjectMode();
    Code:
       0: aload_0
       1: getfield      #26                 // Field deepCopySubjectMode:Ljava/lang/Boolean;
       4: areturn

  public T deepCopySubjectMode(java.lang.Boolean);
    Code:
       0: aload_0
       1: getfield      #26                 // Field deepCopySubjectMode:Ljava/lang/Boolean;
       4: astore_2
       5: aload_0
       6: aload_1
       7: putfield      #26                 // Field deepCopySubjectMode:Ljava/lang/Boolean;
      10: aload_0
      11: getfield      #9                  // Field pcs:Ljava/beans/PropertyChangeSupport;
      14: ifnull        28
      17: aload_0
      18: getfield      #9                  // Field pcs:Ljava/beans/PropertyChangeSupport;
      21: ldc           #27                 // String deepCopySubjectMode
      23: aload_2
      24: aload_1
      25: invokevirtual #28                 // Method java/beans/PropertyChangeSupport.firePropertyChange:(Ljava/lang/String;Ljava/lang/Object;Ljava/lang/Object;)V
      28: aload_0
      29: areturn
}
