Compiled from "ServiceRegistries.java"
final class org.jboss.weld.bootstrap.api.helpers.ServiceRegistries$1 extends org.jboss.weld.bootstrap.api.helpers.ForwardingServiceRegistry {
  final org.jboss.weld.bootstrap.api.ServiceRegistry val$serviceRegistry;

  org.jboss.weld.bootstrap.api.helpers.ServiceRegistries$1(org.jboss.weld.bootstrap.api.ServiceRegistry);
    Code:
       0: aload_0
       1: aload_1
       2: putfield      #1                  // Field val$serviceRegistry:Lorg/jboss/weld/bootstrap/api/ServiceRegistry;
       5: aload_0
       6: invokespecial #2                  // Method org/jboss/weld/bootstrap/api/helpers/ForwardingServiceRegistry."<init>":()V
       9: return

  public <S extends org.jboss.weld.bootstrap.api.Service> void add(java.lang.Class<S>, S);
    Code:
       0: new           #3                  // class java/lang/UnsupportedOperationException
       3: dup
       4: ldc           #4                  // String This service registry is unmodifiable
       6: invokespecial #5                  // Method java/lang/UnsupportedOperationException."<init>":(Ljava/lang/String;)V
       9: athrow

  protected org.jboss.weld.bootstrap.api.ServiceRegistry delegate();
    Code:
       0: aload_0
       1: getfield      #1                  // Field val$serviceRegistry:Lorg/jboss/weld/bootstrap/api/ServiceRegistry;
       4: areturn
}
