Compiled from "JarFileEntries.java"
class org.springframework.boot.loader.jar.JarFileEntries$1 extends java.util.LinkedHashMap<java.lang.Integer, org.springframework.boot.loader.jar.FileHeader> {
  final org.springframework.boot.loader.jar.JarFileEntries this$0;

  org.springframework.boot.loader.jar.JarFileEntries$1(org.springframework.boot.loader.jar.JarFileEntries, int, float, boolean);
    Code:
       0: aload_0
       1: aload_1
       2: putfield      #2                  // Field this$0:Lorg/springframework/boot/loader/jar/JarFileEntries;
       5: aload_0
       6: iload_2
       7: fload_3
       8: iload         4
      10: invokespecial #3                  // Method java/util/LinkedHashMap."<init>":(IFZ)V
      13: return

  protected boolean removeEldestEntry(java.util.Map$Entry<java.lang.Integer, org.springframework.boot.loader.jar.FileHeader>);
    Code:
       0: aload_0
       1: getfield      #2                  // Field this$0:Lorg/springframework/boot/loader/jar/JarFileEntries;
       4: invokestatic  #4                  // Method org/springframework/boot/loader/jar/JarFileEntries.access$000:(Lorg/springframework/boot/loader/jar/JarFileEntries;)Lorg/springframework/boot/loader/jar/JarFile;
       7: invokevirtual #5                  // Method org/springframework/boot/loader/jar/JarFile.isSigned:()Z
      10: ifeq          15
      13: iconst_0
      14: ireturn
      15: aload_0
      16: invokevirtual #6                  // Method size:()I
      19: bipush        25
      21: if_icmplt     28
      24: iconst_1
      25: goto          29
      28: iconst_0
      29: ireturn
}
