Compiled from "DateTypeAdapter.java"
public final class org.sonar.api.internal.google.gson.internal.bind.DateTypeAdapter extends org.sonar.api.internal.google.gson.TypeAdapter<java.util.Date> {
  public static final org.sonar.api.internal.google.gson.TypeAdapterFactory FACTORY;

  private final java.text.DateFormat enUsFormat;

  private final java.text.DateFormat localFormat;

  private final java.text.DateFormat iso8601Format;

  public org.sonar.api.internal.google.gson.internal.bind.DateTypeAdapter();
    Code:
       0: aload_0
       1: invokespecial #18                 // Method org/sonar/api/internal/google/gson/TypeAdapter."<init>":()V
       4: aload_0
       5: iconst_2
       6: iconst_2
       7: getstatic     #24                 // Field java/util/Locale.US:Ljava/util/Locale;
      10: invokestatic  #30                 // Method java/text/DateFormat.getDateTimeInstance:(IILjava/util/Locale;)Ljava/text/DateFormat;
      13: putfield      #32                 // Field enUsFormat:Ljava/text/DateFormat;
      16: aload_0
      17: iconst_2
      18: iconst_2
      19: invokestatic  #35                 // Method java/text/DateFormat.getDateTimeInstance:(II)Ljava/text/DateFormat;
      22: putfield      #37                 // Field localFormat:Ljava/text/DateFormat;
      25: aload_0
      26: invokestatic  #41                 // Method buildIso8601Format:()Ljava/text/DateFormat;
      29: putfield      #43                 // Field iso8601Format:Ljava/text/DateFormat;
      32: return

  private static java.text.DateFormat buildIso8601Format();
    Code:
       0: new           #47                 // class java/text/SimpleDateFormat
       3: dup
       4: ldc           #49                 // String yyyy-MM-dd\'T\'HH:mm:ss\'Z\'
       6: getstatic     #24                 // Field java/util/Locale.US:Ljava/util/Locale;
       9: invokespecial #52                 // Method java/text/SimpleDateFormat."<init>":(Ljava/lang/String;Ljava/util/Locale;)V
      12: astore_0
      13: aload_0
      14: ldc           #54                 // String UTC
      16: invokestatic  #60                 // Method java/util/TimeZone.getTimeZone:(Ljava/lang/String;)Ljava/util/TimeZone;
      19: invokevirtual #64                 // Method java/text/DateFormat.setTimeZone:(Ljava/util/TimeZone;)V
      22: aload_0
      23: areturn

  public java.util.Date read(org.sonar.api.internal.google.gson.stream.JsonReader) throws java.io.IOException;
    Code:
       0: aload_1
       1: invokevirtual #74                 // Method org/sonar/api/internal/google/gson/stream/JsonReader.peek:()Lorg/sonar/api/internal/google/gson/stream/JsonToken;
       4: getstatic     #80                 // Field org/sonar/api/internal/google/gson/stream/JsonToken.NULL:Lorg/sonar/api/internal/google/gson/stream/JsonToken;
       7: if_acmpne     16
      10: aload_1
      11: invokevirtual #83                 // Method org/sonar/api/internal/google/gson/stream/JsonReader.nextNull:()V
      14: aconst_null
      15: areturn
      16: aload_0
      17: aload_1
      18: invokevirtual #87                 // Method org/sonar/api/internal/google/gson/stream/JsonReader.nextString:()Ljava/lang/String;
      21: invokespecial #91                 // Method deserializeToDate:(Ljava/lang/String;)Ljava/util/Date;
      24: areturn

  private synchronized java.util.Date deserializeToDate(java.lang.String);
    Code:
       0: aload_0
       1: getfield      #37                 // Field localFormat:Ljava/text/DateFormat;
       4: aload_1
       5: invokevirtual #98                 // Method java/text/DateFormat.parse:(Ljava/lang/String;)Ljava/util/Date;
       8: areturn
       9: astore_2
      10: aload_0
      11: getfield      #32                 // Field enUsFormat:Ljava/text/DateFormat;
      14: aload_1
      15: invokevirtual #98                 // Method java/text/DateFormat.parse:(Ljava/lang/String;)Ljava/util/Date;
      18: areturn
      19: astore_2
      20: aload_0
      21: getfield      #43                 // Field iso8601Format:Ljava/text/DateFormat;
      24: aload_1
      25: invokevirtual #98                 // Method java/text/DateFormat.parse:(Ljava/lang/String;)Ljava/util/Date;
      28: areturn
      29: astore_2
      30: new           #100                // class org/sonar/api/internal/google/gson/JsonSyntaxException
      33: dup
      34: aload_1
      35: aload_2
      36: invokespecial #103                // Method org/sonar/api/internal/google/gson/JsonSyntaxException."<init>":(Ljava/lang/String;Ljava/lang/Throwable;)V
      39: athrow
    Exception table:
       from    to  target type
           0     8     9   Class java/text/ParseException
          10    18    19   Class java/text/ParseException
          20    28    29   Class java/text/ParseException

  public synchronized void write(org.sonar.api.internal.google.gson.stream.JsonWriter, java.util.Date) throws java.io.IOException;
    Code:
       0: aload_2
       1: ifnonnull     10
       4: aload_1
       5: invokevirtual #116                // Method org/sonar/api/internal/google/gson/stream/JsonWriter.nullValue:()Lorg/sonar/api/internal/google/gson/stream/JsonWriter;
       8: pop
       9: return
      10: aload_0
      11: getfield      #32                 // Field enUsFormat:Ljava/text/DateFormat;
      14: aload_2
      15: invokevirtual #120                // Method java/text/DateFormat.format:(Ljava/util/Date;)Ljava/lang/String;
      18: astore_3
      19: aload_1
      20: aload_3
      21: invokevirtual #124                // Method org/sonar/api/internal/google/gson/stream/JsonWriter.value:(Ljava/lang/String;)Lorg/sonar/api/internal/google/gson/stream/JsonWriter;
      24: pop
      25: return

  public java.lang.Object read(org.sonar.api.internal.google.gson.stream.JsonReader) throws java.io.IOException;
    Code:
       0: aload_0
       1: aload_1
       2: invokevirtual #131                // Method read:(Lorg/sonar/api/internal/google/gson/stream/JsonReader;)Ljava/util/Date;
       5: areturn

  public void write(org.sonar.api.internal.google.gson.stream.JsonWriter, java.lang.Object) throws java.io.IOException;
    Code:
       0: aload_0
       1: aload_1
       2: aload_2
       3: checkcast     #135                // class java/util/Date
       6: invokevirtual #137                // Method write:(Lorg/sonar/api/internal/google/gson/stream/JsonWriter;Ljava/util/Date;)V
       9: return

  static {};
    Code:
       0: new           #8                  // class org/sonar/api/internal/google/gson/internal/bind/DateTypeAdapter$1
       3: dup
       4: invokespecial #141                // Method org/sonar/api/internal/google/gson/internal/bind/DateTypeAdapter$1."<init>":()V
       7: putstatic     #143                // Field FACTORY:Lorg/sonar/api/internal/google/gson/TypeAdapterFactory;
      10: return
}
