Compiled from "FunctionEnvBase.java"
public class org.apache.jena.sparql.function.FunctionEnvBase implements org.apache.jena.sparql.function.FunctionEnv {
  private org.apache.jena.sparql.util.Context context;

  private org.apache.jena.graph.Graph activeGraph;

  private org.apache.jena.sparql.core.DatasetGraph dataset;

  private org.apache.jena.sparql.engine.ExecutionContext execContext;

  public static org.apache.jena.sparql.function.FunctionEnv createTest();
    Code:
       0: new           #1                  // class org/apache/jena/sparql/function/FunctionEnvBase
       3: dup
       4: invokestatic  #2                  // Method org/apache/jena/query/ARQ.getContext:()Lorg/apache/jena/sparql/util/Context;
       7: invokespecial #3                  // Method "<init>":(Lorg/apache/jena/sparql/util/Context;)V
      10: areturn

  public org.apache.jena.sparql.function.FunctionEnvBase();
    Code:
       0: aload_0
       1: invokestatic  #2                  // Method org/apache/jena/query/ARQ.getContext:()Lorg/apache/jena/sparql/util/Context;
       4: aconst_null
       5: aconst_null
       6: invokespecial #4                  // Method "<init>":(Lorg/apache/jena/sparql/util/Context;Lorg/apache/jena/graph/Graph;Lorg/apache/jena/sparql/core/DatasetGraph;)V
       9: return

  public org.apache.jena.sparql.function.FunctionEnvBase(org.apache.jena.sparql.util.Context);
    Code:
       0: aload_0
       1: aload_1
       2: aconst_null
       3: aconst_null
       4: invokespecial #4                  // Method "<init>":(Lorg/apache/jena/sparql/util/Context;Lorg/apache/jena/graph/Graph;Lorg/apache/jena/sparql/core/DatasetGraph;)V
       7: return

  public org.apache.jena.sparql.function.FunctionEnvBase(org.apache.jena.sparql.engine.ExecutionContext);
    Code:
       0: aload_0
       1: aload_1
       2: invokevirtual #5                  // Method org/apache/jena/sparql/engine/ExecutionContext.getContext:()Lorg/apache/jena/sparql/util/Context;
       5: aload_1
       6: invokevirtual #6                  // Method org/apache/jena/sparql/engine/ExecutionContext.getActiveGraph:()Lorg/apache/jena/graph/Graph;
       9: aload_1
      10: invokevirtual #7                  // Method org/apache/jena/sparql/engine/ExecutionContext.getDataset:()Lorg/apache/jena/sparql/core/DatasetGraph;
      13: invokespecial #4                  // Method "<init>":(Lorg/apache/jena/sparql/util/Context;Lorg/apache/jena/graph/Graph;Lorg/apache/jena/sparql/core/DatasetGraph;)V
      16: aload_0
      17: aload_1
      18: putfield      #8                  // Field execContext:Lorg/apache/jena/sparql/engine/ExecutionContext;
      21: return

  public org.apache.jena.sparql.function.FunctionEnvBase(org.apache.jena.sparql.util.Context, org.apache.jena.graph.Graph, org.apache.jena.sparql.core.DatasetGraph);
    Code:
       0: aload_0
       1: invokespecial #9                  // Method java/lang/Object."<init>":()V
       4: aload_0
       5: aconst_null
       6: putfield      #8                  // Field execContext:Lorg/apache/jena/sparql/engine/ExecutionContext;
       9: aload_0
      10: aload_1
      11: putfield      #10                 // Field context:Lorg/apache/jena/sparql/util/Context;
      14: aload_0
      15: aload_2
      16: putfield      #11                 // Field activeGraph:Lorg/apache/jena/graph/Graph;
      19: aload_0
      20: aload_3
      21: putfield      #12                 // Field dataset:Lorg/apache/jena/sparql/core/DatasetGraph;
      24: return

  public org.apache.jena.graph.Graph getActiveGraph();
    Code:
       0: aload_0
       1: getfield      #11                 // Field activeGraph:Lorg/apache/jena/graph/Graph;
       4: areturn

  public org.apache.jena.sparql.util.Context getContext();
    Code:
       0: aload_0
       1: getfield      #10                 // Field context:Lorg/apache/jena/sparql/util/Context;
       4: areturn

  public org.apache.jena.sparql.core.DatasetGraph getDataset();
    Code:
       0: aload_0
       1: getfield      #12                 // Field dataset:Lorg/apache/jena/sparql/core/DatasetGraph;
       4: areturn
}
