Compiled from "BasicMaxAgeHandler.java"
public class org.apache.http.impl.cookie.BasicMaxAgeHandler extends org.apache.http.impl.cookie.AbstractCookieAttributeHandler {
  public org.apache.http.impl.cookie.BasicMaxAgeHandler();
    Code:
       0: aload_0
       1: invokespecial #1                  // Method org/apache/http/impl/cookie/AbstractCookieAttributeHandler."<init>":()V
       4: return

  public void parse(org.apache.http.cookie.SetCookie, java.lang.String) throws org.apache.http.cookie.MalformedCookieException;
    Code:
       0: aload_1
       1: ifnonnull     14
       4: new           #2                  // class java/lang/IllegalArgumentException
       7: dup
       8: ldc           #3                  // String Cookie may not be null
      10: invokespecial #4                  // Method java/lang/IllegalArgumentException."<init>":(Ljava/lang/String;)V
      13: athrow
      14: aload_2
      15: ifnonnull     28
      18: new           #5                  // class org/apache/http/cookie/MalformedCookieException
      21: dup
      22: ldc           #6                  // String Missing value for max-age attribute
      24: invokespecial #7                  // Method org/apache/http/cookie/MalformedCookieException."<init>":(Ljava/lang/String;)V
      27: athrow
      28: aload_2
      29: invokestatic  #8                  // Method java/lang/Integer.parseInt:(Ljava/lang/String;)I
      32: istore_3
      33: goto          65
      36: astore        4
      38: new           #5                  // class org/apache/http/cookie/MalformedCookieException
      41: dup
      42: new           #10                 // class java/lang/StringBuilder
      45: dup
      46: invokespecial #11                 // Method java/lang/StringBuilder."<init>":()V
      49: ldc           #12                 // String Invalid max-age attribute:
      51: invokevirtual #13                 // Method java/lang/StringBuilder.append:(Ljava/lang/String;)Ljava/lang/StringBuilder;
      54: aload_2
      55: invokevirtual #13                 // Method java/lang/StringBuilder.append:(Ljava/lang/String;)Ljava/lang/StringBuilder;
      58: invokevirtual #14                 // Method java/lang/StringBuilder.toString:()Ljava/lang/String;
      61: invokespecial #7                  // Method org/apache/http/cookie/MalformedCookieException."<init>":(Ljava/lang/String;)V
      64: athrow
      65: iload_3
      66: ifge          96
      69: new           #5                  // class org/apache/http/cookie/MalformedCookieException
      72: dup
      73: new           #10                 // class java/lang/StringBuilder
      76: dup
      77: invokespecial #11                 // Method java/lang/StringBuilder."<init>":()V
      80: ldc           #15                 // String Negative max-age attribute:
      82: invokevirtual #13                 // Method java/lang/StringBuilder.append:(Ljava/lang/String;)Ljava/lang/StringBuilder;
      85: aload_2
      86: invokevirtual #13                 // Method java/lang/StringBuilder.append:(Ljava/lang/String;)Ljava/lang/StringBuilder;
      89: invokevirtual #14                 // Method java/lang/StringBuilder.toString:()Ljava/lang/String;
      92: invokespecial #7                  // Method org/apache/http/cookie/MalformedCookieException."<init>":(Ljava/lang/String;)V
      95: athrow
      96: aload_1
      97: new           #16                 // class java/util/Date
     100: dup
     101: invokestatic  #17                 // Method java/lang/System.currentTimeMillis:()J
     104: iload_3
     105: i2l
     106: ldc2_w        #18                 // long 1000l
     109: lmul
     110: ladd
     111: invokespecial #20                 // Method java/util/Date."<init>":(J)V
     114: invokeinterface #21,  2           // InterfaceMethod org/apache/http/cookie/SetCookie.setExpiryDate:(Ljava/util/Date;)V
     119: return
    Exception table:
       from    to  target type
          28    33    36   Class java/lang/NumberFormatException
}
