Compiled from "View.scala"
public final class slinky.native.LayoutChangeEvent$ extends scala.runtime.AbstractFunction1<slinky.native.LayoutRectangle, slinky.native.LayoutChangeEvent> implements scala.Serializable {
  public static slinky.native.LayoutChangeEvent$ MODULE$;

  public static {};
    Code:
       0: new           #2                  // class slinky/native/LayoutChangeEvent$
       3: invokespecial #15                 // Method "<init>":()V
       6: return

  public final java.lang.String toString();
    Code:
       0: ldc           #19                 // String LayoutChangeEvent
       2: areturn

  public slinky.native.LayoutChangeEvent apply(slinky.native.LayoutRectangle);
    Code:
       0: new           #25                 // class slinky/native/LayoutChangeEvent
       3: dup
       4: aload_1
       5: invokespecial #28                 // Method slinky/native/LayoutChangeEvent."<init>":(Lslinky/native/LayoutRectangle;)V
       8: areturn

  public scala.Option<slinky.native.LayoutRectangle> unapply(slinky.native.LayoutChangeEvent);
    Code:
       0: aload_1
       1: ifnonnull     10
       4: getstatic     #37                 // Field scala/None$.MODULE$:Lscala/None$;
       7: goto          21
      10: new           #39                 // class scala/Some
      13: dup
      14: aload_1
      15: invokevirtual #42                 // Method slinky/native/LayoutChangeEvent.layout:()Lslinky/native/LayoutRectangle;
      18: invokespecial #45                 // Method scala/Some."<init>":(Ljava/lang/Object;)V
      21: areturn

  private java.lang.Object readResolve();
    Code:
       0: getstatic     #52                 // Field MODULE$:Lslinky/native/LayoutChangeEvent$;
       3: areturn

  public java.lang.Object apply(java.lang.Object);
    Code:
       0: aload_0
       1: aload_1
       2: checkcast     #56                 // class slinky/native/LayoutRectangle
       5: invokevirtual #58                 // Method apply:(Lslinky/native/LayoutRectangle;)Lslinky/native/LayoutChangeEvent;
       8: areturn

  private slinky.native.LayoutChangeEvent$();
    Code:
       0: aload_0
       1: invokespecial #60                 // Method scala/runtime/AbstractFunction1."<init>":()V
       4: aload_0
       5: putstatic     #52                 // Field MODULE$:Lslinky/native/LayoutChangeEvent$;
       8: return
}
