Compiled from "FlatList.scala"
public class slinky.native.ScrollToItemParams<T> implements scala.Product, scala.Serializable {
  private final T item;

  private final scala.scalajs.js.UndefOr<java.lang.Object> animated;

  private final scala.scalajs.js.UndefOr<java.lang.Object> viewPosition;

  public static <T> scala.scalajs.js.UndefOr<java.lang.Object> apply$default$3();
    Code:
       0: getstatic     #28                 // Field slinky/native/ScrollToItemParams$.MODULE$:Lslinky/native/ScrollToItemParams$;
       3: invokevirtual #30                 // Method slinky/native/ScrollToItemParams$.apply$default$3:()Lscala/scalajs/js/UndefOr;
       6: areturn

  public static <T> scala.scalajs.js.UndefOr<java.lang.Object> apply$default$2();
    Code:
       0: getstatic     #28                 // Field slinky/native/ScrollToItemParams$.MODULE$:Lslinky/native/ScrollToItemParams$;
       3: invokevirtual #33                 // Method slinky/native/ScrollToItemParams$.apply$default$2:()Lscala/scalajs/js/UndefOr;
       6: areturn

  public static <T> scala.scalajs.js.UndefOr<java.lang.Object> $lessinit$greater$default$3();
    Code:
       0: getstatic     #28                 // Field slinky/native/ScrollToItemParams$.MODULE$:Lslinky/native/ScrollToItemParams$;
       3: invokevirtual #36                 // Method slinky/native/ScrollToItemParams$.$lessinit$greater$default$3:()Lscala/scalajs/js/UndefOr;
       6: areturn

  public static <T> scala.scalajs.js.UndefOr<java.lang.Object> $lessinit$greater$default$2();
    Code:
       0: getstatic     #28                 // Field slinky/native/ScrollToItemParams$.MODULE$:Lslinky/native/ScrollToItemParams$;
       3: invokevirtual #39                 // Method slinky/native/ScrollToItemParams$.$lessinit$greater$default$2:()Lscala/scalajs/js/UndefOr;
       6: areturn

  public static <T> scala.Option<scala.Tuple3<T, scala.scalajs.js.UndefOr<java.lang.Object>, scala.scalajs.js.UndefOr<java.lang.Object>>> unapply(slinky.native.ScrollToItemParams<T>);
    Code:
       0: getstatic     #28                 // Field slinky/native/ScrollToItemParams$.MODULE$:Lslinky/native/ScrollToItemParams$;
       3: aload_0
       4: invokevirtual #44                 // Method slinky/native/ScrollToItemParams$.unapply:(Lslinky/native/ScrollToItemParams;)Lscala/Option;
       7: areturn

  public static <T> slinky.native.ScrollToItemParams<T> apply(T, scala.scalajs.js.UndefOr<java.lang.Object>, scala.scalajs.js.UndefOr<java.lang.Object>);
    Code:
       0: getstatic     #28                 // Field slinky/native/ScrollToItemParams$.MODULE$:Lslinky/native/ScrollToItemParams$;
       3: aload_0
       4: aload_1
       5: aload_2
       6: invokevirtual #48                 // Method slinky/native/ScrollToItemParams$.apply:(Ljava/lang/Object;Lscala/scalajs/js/UndefOr;Lscala/scalajs/js/UndefOr;)Lslinky/native/ScrollToItemParams;
       9: areturn

  public T item();
    Code:
       0: aload_0
       1: getfield      #51                 // Field item:Ljava/lang/Object;
       4: areturn

  public scala.scalajs.js.UndefOr<java.lang.Object> animated();
    Code:
       0: aload_0
       1: getfield      #55                 // Field animated:Lscala/scalajs/js/UndefOr;
       4: areturn

  public scala.scalajs.js.UndefOr<java.lang.Object> viewPosition();
    Code:
       0: aload_0
       1: getfield      #57                 // Field viewPosition:Lscala/scalajs/js/UndefOr;
       4: areturn

  public <T> slinky.native.ScrollToItemParams<T> copy(T, scala.scalajs.js.UndefOr<java.lang.Object>, scala.scalajs.js.UndefOr<java.lang.Object>);
    Code:
       0: new           #2                  // class slinky/native/ScrollToItemParams
       3: dup
       4: aload_1
       5: aload_2
       6: aload_3
       7: invokespecial #62                 // Method "<init>":(Ljava/lang/Object;Lscala/scalajs/js/UndefOr;Lscala/scalajs/js/UndefOr;)V
      10: areturn

  public <T> T copy$default$1();
    Code:
       0: aload_0
       1: invokevirtual #65                 // Method item:()Ljava/lang/Object;
       4: areturn

  public <T> scala.scalajs.js.UndefOr<java.lang.Object> copy$default$2();
    Code:
       0: aload_0
       1: invokevirtual #68                 // Method animated:()Lscala/scalajs/js/UndefOr;
       4: areturn

  public <T> scala.scalajs.js.UndefOr<java.lang.Object> copy$default$3();
    Code:
       0: aload_0
       1: invokevirtual #71                 // Method viewPosition:()Lscala/scalajs/js/UndefOr;
       4: areturn

  public java.lang.String productPrefix();
    Code:
       0: ldc           #75                 // String ScrollToItemParams
       2: areturn

  public int productArity();
    Code:
       0: iconst_3
       1: ireturn

  public java.lang.Object productElement(int);
    Code:
       0: iload_1
       1: istore_2
       2: iload_2
       3: tableswitch   { // 0 to 2
                     0: 28
                     1: 35
                     2: 42
               default: 49
          }
      28: aload_0
      29: invokevirtual #65                 // Method item:()Ljava/lang/Object;
      32: goto          64
      35: aload_0
      36: invokevirtual #68                 // Method animated:()Lscala/scalajs/js/UndefOr;
      39: goto          64
      42: aload_0
      43: invokevirtual #71                 // Method viewPosition:()Lscala/scalajs/js/UndefOr;
      46: goto          64
      49: new           #82                 // class java/lang/IndexOutOfBoundsException
      52: dup
      53: iload_1
      54: invokestatic  #88                 // Method scala/runtime/BoxesRunTime.boxToInteger:(I)Ljava/lang/Integer;
      57: invokevirtual #91                 // Method java/lang/Object.toString:()Ljava/lang/String;
      60: invokespecial #94                 // Method java/lang/IndexOutOfBoundsException."<init>":(Ljava/lang/String;)V
      63: athrow
      64: areturn

  public scala.collection.Iterator<java.lang.Object> productIterator();
    Code:
       0: getstatic     #102                // Field scala/runtime/ScalaRunTime$.MODULE$:Lscala/runtime/ScalaRunTime$;
       3: aload_0
       4: invokevirtual #106                // Method scala/runtime/ScalaRunTime$.typedProductIterator:(Lscala/Product;)Lscala/collection/Iterator;
       7: areturn

  public boolean canEqual(java.lang.Object);
    Code:
       0: aload_1
       1: instanceof    #2                  // class slinky/native/ScrollToItemParams
       4: ireturn

  public int hashCode();
    Code:
       0: getstatic     #102                // Field scala/runtime/ScalaRunTime$.MODULE$:Lscala/runtime/ScalaRunTime$;
       3: aload_0
       4: invokevirtual #113                // Method scala/runtime/ScalaRunTime$._hashCode:(Lscala/Product;)I
       7: ireturn

  public java.lang.String toString();
    Code:
       0: getstatic     #102                // Field scala/runtime/ScalaRunTime$.MODULE$:Lscala/runtime/ScalaRunTime$;
       3: aload_0
       4: invokevirtual #117                // Method scala/runtime/ScalaRunTime$._toString:(Lscala/Product;)Ljava/lang/String;
       7: areturn

  public boolean equals(java.lang.Object);
    Code:
       0: aload_0
       1: aload_1
       2: if_acmpeq     133
       5: aload_1
       6: astore_3
       7: aload_3
       8: instanceof    #2                  // class slinky/native/ScrollToItemParams
      11: ifeq          19
      14: iconst_1
      15: istore_2
      16: goto          27
      19: goto          22
      22: iconst_0
      23: istore_2
      24: goto          27
      27: iload_2
      28: ifeq          137
      31: aload_1
      32: checkcast     #2                  // class slinky/native/ScrollToItemParams
      35: astore        4
      37: aload_0
      38: invokevirtual #65                 // Method item:()Ljava/lang/Object;
      41: aload         4
      43: invokevirtual #65                 // Method item:()Ljava/lang/Object;
      46: invokestatic  #121                // Method scala/runtime/BoxesRunTime.equals:(Ljava/lang/Object;Ljava/lang/Object;)Z
      49: ifeq          129
      52: aload_0
      53: invokevirtual #68                 // Method animated:()Lscala/scalajs/js/UndefOr;
      56: aload         4
      58: invokevirtual #68                 // Method animated:()Lscala/scalajs/js/UndefOr;
      61: astore        5
      63: dup
      64: ifnonnull     76
      67: pop
      68: aload         5
      70: ifnull        84
      73: goto          129
      76: aload         5
      78: invokevirtual #123                // Method java/lang/Object.equals:(Ljava/lang/Object;)Z
      81: ifeq          129
      84: aload_0
      85: invokevirtual #71                 // Method viewPosition:()Lscala/scalajs/js/UndefOr;
      88: aload         4
      90: invokevirtual #71                 // Method viewPosition:()Lscala/scalajs/js/UndefOr;
      93: astore        6
      95: dup
      96: ifnonnull     108
      99: pop
     100: aload         6
     102: ifnull        116
     105: goto          129
     108: aload         6
     110: invokevirtual #123                // Method java/lang/Object.equals:(Ljava/lang/Object;)Z
     113: ifeq          129
     116: aload         4
     118: aload_0
     119: invokevirtual #125                // Method canEqual:(Ljava/lang/Object;)Z
     122: ifeq          129
     125: iconst_1
     126: goto          130
     129: iconst_0
     130: ifeq          137
     133: iconst_1
     134: goto          138
     137: iconst_0
     138: ireturn

  public slinky.native.ScrollToItemParams(T, scala.scalajs.js.UndefOr<java.lang.Object>, scala.scalajs.js.UndefOr<java.lang.Object>);
    Code:
       0: aload_0
       1: aload_1
       2: putfield      #51                 // Field item:Ljava/lang/Object;
       5: aload_0
       6: aload_2
       7: putfield      #55                 // Field animated:Lscala/scalajs/js/UndefOr;
      10: aload_0
      11: aload_3
      12: putfield      #57                 // Field viewPosition:Lscala/scalajs/js/UndefOr;
      15: aload_0
      16: invokespecial #130                // Method java/lang/Object."<init>":()V
      19: aload_0
      20: invokestatic  #134                // InterfaceMethod scala/Product.$init$:(Lscala/Product;)V
      23: return
}
