Compiled from "DigesterRuleParser.java"
class org.apache.commons.digester.xmlrules.DigesterRuleParser$RulesPrefixAdapter implements org.apache.commons.digester.Rules {
  private org.apache.commons.digester.Rules delegate;

  private java.lang.String prefix;

  private final org.apache.commons.digester.xmlrules.DigesterRuleParser this$0;

  public org.apache.commons.digester.xmlrules.DigesterRuleParser$RulesPrefixAdapter(org.apache.commons.digester.xmlrules.DigesterRuleParser, java.lang.String, org.apache.commons.digester.Rules);
    Code:
       0: aload_0
       1: invokespecial #1                  // Method java/lang/Object."<init>":()V
       4: aload_0
       5: aload_1
       6: putfield      #2                  // Field this$0:Lorg/apache/commons/digester/xmlrules/DigesterRuleParser;
       9: aload_0
      10: aload_2
      11: putfield      #3                  // Field prefix:Ljava/lang/String;
      14: aload_0
      15: aload_3
      16: putfield      #4                  // Field delegate:Lorg/apache/commons/digester/Rules;
      19: return

  public void add(java.lang.String, org.apache.commons.digester.Rule);
    Code:
       0: new           #5                  // class java/lang/StringBuffer
       3: dup
       4: invokespecial #6                  // Method java/lang/StringBuffer."<init>":()V
       7: astore_3
       8: aload_3
       9: aload_0
      10: getfield      #3                  // Field prefix:Ljava/lang/String;
      13: invokevirtual #7                  // Method java/lang/StringBuffer.append:(Ljava/lang/String;)Ljava/lang/StringBuffer;
      16: pop
      17: aload_1
      18: ldc           #8                  // String /
      20: invokevirtual #9                  // Method java/lang/String.startsWith:(Ljava/lang/String;)Z
      23: ifne          33
      26: aload_3
      27: bipush        47
      29: invokevirtual #10                 // Method java/lang/StringBuffer.append:(C)Ljava/lang/StringBuffer;
      32: pop
      33: aload_3
      34: aload_1
      35: invokevirtual #7                  // Method java/lang/StringBuffer.append:(Ljava/lang/String;)Ljava/lang/StringBuffer;
      38: pop
      39: aload_0
      40: getfield      #4                  // Field delegate:Lorg/apache/commons/digester/Rules;
      43: aload_3
      44: invokevirtual #11                 // Method java/lang/StringBuffer.toString:()Ljava/lang/String;
      47: aload_2
      48: invokeinterface #12,  3           // InterfaceMethod org/apache/commons/digester/Rules.add:(Ljava/lang/String;Lorg/apache/commons/digester/Rule;)V
      53: return

  public void clear();
    Code:
       0: aload_0
       1: getfield      #4                  // Field delegate:Lorg/apache/commons/digester/Rules;
       4: invokeinterface #13,  1           // InterfaceMethod org/apache/commons/digester/Rules.clear:()V
       9: return

  public org.apache.commons.digester.Digester getDigester();
    Code:
       0: aload_0
       1: getfield      #4                  // Field delegate:Lorg/apache/commons/digester/Rules;
       4: invokeinterface #14,  1           // InterfaceMethod org/apache/commons/digester/Rules.getDigester:()Lorg/apache/commons/digester/Digester;
       9: areturn

  public java.lang.String getNamespaceURI();
    Code:
       0: aload_0
       1: getfield      #4                  // Field delegate:Lorg/apache/commons/digester/Rules;
       4: invokeinterface #15,  1           // InterfaceMethod org/apache/commons/digester/Rules.getNamespaceURI:()Ljava/lang/String;
       9: areturn

  public java.util.List match(java.lang.String);
    Code:
       0: aload_0
       1: getfield      #4                  // Field delegate:Lorg/apache/commons/digester/Rules;
       4: aload_1
       5: invokeinterface #16,  2           // InterfaceMethod org/apache/commons/digester/Rules.match:(Ljava/lang/String;)Ljava/util/List;
      10: areturn

  public java.util.List match(java.lang.String, java.lang.String);
    Code:
       0: aload_0
       1: getfield      #4                  // Field delegate:Lorg/apache/commons/digester/Rules;
       4: aload_1
       5: aload_2
       6: invokeinterface #17,  3           // InterfaceMethod org/apache/commons/digester/Rules.match:(Ljava/lang/String;Ljava/lang/String;)Ljava/util/List;
      11: areturn

  public java.util.List rules();
    Code:
       0: aload_0
       1: getfield      #4                  // Field delegate:Lorg/apache/commons/digester/Rules;
       4: invokeinterface #18,  1           // InterfaceMethod org/apache/commons/digester/Rules.rules:()Ljava/util/List;
       9: areturn

  public void setDigester(org.apache.commons.digester.Digester);
    Code:
       0: aload_0
       1: getfield      #4                  // Field delegate:Lorg/apache/commons/digester/Rules;
       4: aload_1
       5: invokeinterface #19,  2           // InterfaceMethod org/apache/commons/digester/Rules.setDigester:(Lorg/apache/commons/digester/Digester;)V
      10: return

  public void setNamespaceURI(java.lang.String);
    Code:
       0: aload_0
       1: getfield      #4                  // Field delegate:Lorg/apache/commons/digester/Rules;
       4: aload_1
       5: invokeinterface #20,  2           // InterfaceMethod org/apache/commons/digester/Rules.setNamespaceURI:(Ljava/lang/String;)V
      10: return
}
