Compiled from "DigesterRuleParser.java"
public class org.apache.commons.digester.xmlrules.DigesterRuleParser$NodeCreateRuleFactory extends org.apache.commons.digester.AbstractObjectCreationFactory {
  private final org.apache.commons.digester.xmlrules.DigesterRuleParser this$0;

  protected org.apache.commons.digester.xmlrules.DigesterRuleParser$NodeCreateRuleFactory(org.apache.commons.digester.xmlrules.DigesterRuleParser);
    Code:
       0: aload_0
       1: invokespecial #1                  // Method org/apache/commons/digester/AbstractObjectCreationFactory."<init>":()V
       4: aload_0
       5: aload_1
       6: putfield      #2                  // Field this$0:Lorg/apache/commons/digester/xmlrules/DigesterRuleParser;
       9: return

  public java.lang.Object createObject(org.xml.sax.Attributes) throws java.lang.Exception;
    Code:
       0: aload_1
       1: ldc           #3                  // String type
       3: invokeinterface #4,  2            // InterfaceMethod org/xml/sax/Attributes.getValue:(Ljava/lang/String;)Ljava/lang/String;
       8: astore_2
       9: aload_2
      10: ifnull        22
      13: ldc           #5                  // String
      15: aload_2
      16: invokevirtual #6                  // Method java/lang/String.equals:(Ljava/lang/Object;)Z
      19: ifeq          30
      22: new           #7                  // class org/apache/commons/digester/NodeCreateRule
      25: dup
      26: invokespecial #8                  // Method org/apache/commons/digester/NodeCreateRule."<init>":()V
      29: areturn
      30: ldc           #9                  // String element
      32: aload_2
      33: invokevirtual #6                  // Method java/lang/String.equals:(Ljava/lang/Object;)Z
      36: ifeq          48
      39: new           #7                  // class org/apache/commons/digester/NodeCreateRule
      42: dup
      43: iconst_1
      44: invokespecial #10                 // Method org/apache/commons/digester/NodeCreateRule."<init>":(I)V
      47: areturn
      48: ldc           #11                 // String fragment
      50: aload_2
      51: invokevirtual #6                  // Method java/lang/String.equals:(Ljava/lang/Object;)Z
      54: ifeq          67
      57: new           #7                  // class org/apache/commons/digester/NodeCreateRule
      60: dup
      61: bipush        11
      63: invokespecial #10                 // Method org/apache/commons/digester/NodeCreateRule."<init>":(I)V
      66: areturn
      67: new           #12                 // class java/lang/RuntimeException
      70: dup
      71: new           #13                 // class java/lang/StringBuffer
      74: dup
      75: invokespecial #14                 // Method java/lang/StringBuffer."<init>":()V
      78: ldc           #15                 // String Unrecognized node type:
      80: invokevirtual #16                 // Method java/lang/StringBuffer.append:(Ljava/lang/String;)Ljava/lang/StringBuffer;
      83: aload_2
      84: invokevirtual #16                 // Method java/lang/StringBuffer.append:(Ljava/lang/String;)Ljava/lang/StringBuffer;
      87: ldc           #17                 // String .  This attribute is optional or can have a value of element|fragment.
      89: invokevirtual #16                 // Method java/lang/StringBuffer.append:(Ljava/lang/String;)Ljava/lang/StringBuffer;
      92: invokevirtual #18                 // Method java/lang/StringBuffer.toString:()Ljava/lang/String;
      95: invokespecial #19                 // Method java/lang/RuntimeException."<init>":(Ljava/lang/String;)V
      98: athrow
}
