Compiled from "PrefabMDCTurboFilterTest.java"
class cloud.prefab.client.config.logging.PrefabMDCTurboFilterTest {
  cloud.prefab.client.ConfigClient configClient;

  cloud.prefab.client.config.logging.PrefabMDCTurboFilter logbackTurboFilter;

  cloud.prefab.client.config.logging.PrefabMDCTurboFilterTest();
    Code:
       0: aload_0
       1: invokespecial #1                  // Method java/lang/Object."<init>":()V
       4: return

  void itReportsLoggingAndAsksForLogLevelReturnsNeutral();
    Code:
       0: ldc           #7                  // String com.example.factory.FactoryFactory
       2: invokestatic  #9                  // Method org/slf4j/LoggerFactory.getLogger:(Ljava/lang/String;)Lorg/slf4j/Logger;
       5: checkcast     #15                 // class ch/qos/logback/classic/Logger
       8: astore_1
       9: aload_0
      10: getfield      #17                 // Field configClient:Lcloud/prefab/client/ConfigClient;
      13: invokeinterface #23,  1           // InterfaceMethod cloud/prefab/client/ConfigClient.isReady:()Z
      18: invokestatic  #29                 // Method java/lang/Boolean.valueOf:(Z)Ljava/lang/Boolean;
      21: invokestatic  #35                 // Method org/mockito/Mockito.when:(Ljava/lang/Object;)Lorg/mockito/stubbing/OngoingStubbing;
      24: iconst_1
      25: invokestatic  #29                 // Method java/lang/Boolean.valueOf:(Z)Ljava/lang/Boolean;
      28: invokeinterface #41,  2           // InterfaceMethod org/mockito/stubbing/OngoingStubbing.thenReturn:(Ljava/lang/Object;)Lorg/mockito/stubbing/OngoingStubbing;
      33: pop
      34: aload_0
      35: getfield      #17                 // Field configClient:Lcloud/prefab/client/ConfigClient;
      38: aload_1
      39: invokevirtual #46                 // Method ch/qos/logback/classic/Logger.getName:()Ljava/lang/String;
      42: invokestatic  #50                 // Method java/util/Collections.emptyMap:()Ljava/util/Map;
      45: invokestatic  #56                 // Method cloud/prefab/context/PrefabContext.unnamedFromMap:(Ljava/util/Map;)Lcloud/prefab/context/PrefabContext;
      48: invokeinterface #62,  3           // InterfaceMethod cloud/prefab/client/ConfigClient.getLogLevel:(Ljava/lang/String;Lcloud/prefab/context/PrefabContextSetReadable;)Ljava/util/Optional;
      53: invokestatic  #35                 // Method org/mockito/Mockito.when:(Ljava/lang/Object;)Lorg/mockito/stubbing/OngoingStubbing;
      56: invokestatic  #66                 // Method java/util/Optional.empty:()Ljava/util/Optional;
      59: invokeinterface #41,  2           // InterfaceMethod org/mockito/stubbing/OngoingStubbing.thenReturn:(Ljava/lang/Object;)Lorg/mockito/stubbing/OngoingStubbing;
      64: pop
      65: aload_0
      66: getfield      #72                 // Field logbackTurboFilter:Lcloud/prefab/client/config/logging/PrefabMDCTurboFilter;
      69: aconst_null
      70: aload_1
      71: getstatic     #76                 // Field ch/qos/logback/classic/Level.DEBUG:Lch/qos/logback/classic/Level;
      74: ldc           #82                 // String
      76: iconst_0
      77: anewarray     #2                  // class java/lang/Object
      80: aconst_null
      81: invokevirtual #84                 // Method cloud/prefab/client/config/logging/PrefabMDCTurboFilter.decide:(Lorg/slf4j/Marker;Lch/qos/logback/classic/Logger;Lch/qos/logback/classic/Level;Ljava/lang/String;[Ljava/lang/Object;Ljava/lang/Throwable;)Lch/qos/logback/core/spi/FilterReply;
      84: invokestatic  #90                 // Method org/assertj/core/api/Assertions.assertThat:(Ljava/lang/Comparable;)Lorg/assertj/core/api/AbstractComparableAssert;
      87: getstatic     #96                 // Field ch/qos/logback/core/spi/FilterReply.NEUTRAL:Lch/qos/logback/core/spi/FilterReply;
      90: invokevirtual #102                // Method org/assertj/core/api/AbstractComparableAssert.isEqualTo:(Ljava/lang/Object;)Lorg/assertj/core/api/AbstractAssert;
      93: pop
      94: aload_0
      95: getfield      #17                 // Field configClient:Lcloud/prefab/client/ConfigClient;
      98: invokestatic  #108                // Method org/mockito/Mockito.verify:(Ljava/lang/Object;)Ljava/lang/Object;
     101: checkcast     #24                 // class cloud/prefab/client/ConfigClient
     104: aload_1
     105: invokevirtual #46                 // Method ch/qos/logback/classic/Logger.getName:()Ljava/lang/String;
     108: getstatic     #112                // Field cloud/prefab/domain/Prefab$LogLevel.DEBUG:Lcloud/prefab/domain/Prefab$LogLevel;
     111: lconst_1
     112: invokeinterface #117,  5          // InterfaceMethod cloud/prefab/client/ConfigClient.reportLoggerUsage:(Ljava/lang/String;Lcloud/prefab/domain/Prefab$LogLevel;J)V
     117: return

  void itReportsLoggingAndAsksForLogLevelReturnsAccept();
    Code:
       0: ldc           #7                  // String com.example.factory.FactoryFactory
       2: invokestatic  #9                  // Method org/slf4j/LoggerFactory.getLogger:(Ljava/lang/String;)Lorg/slf4j/Logger;
       5: checkcast     #15                 // class ch/qos/logback/classic/Logger
       8: astore_1
       9: aload_0
      10: getfield      #17                 // Field configClient:Lcloud/prefab/client/ConfigClient;
      13: invokeinterface #23,  1           // InterfaceMethod cloud/prefab/client/ConfigClient.isReady:()Z
      18: invokestatic  #29                 // Method java/lang/Boolean.valueOf:(Z)Ljava/lang/Boolean;
      21: invokestatic  #35                 // Method org/mockito/Mockito.when:(Ljava/lang/Object;)Lorg/mockito/stubbing/OngoingStubbing;
      24: iconst_1
      25: invokestatic  #29                 // Method java/lang/Boolean.valueOf:(Z)Ljava/lang/Boolean;
      28: invokeinterface #41,  2           // InterfaceMethod org/mockito/stubbing/OngoingStubbing.thenReturn:(Ljava/lang/Object;)Lorg/mockito/stubbing/OngoingStubbing;
      33: pop
      34: aload_0
      35: getfield      #17                 // Field configClient:Lcloud/prefab/client/ConfigClient;
      38: aload_1
      39: invokevirtual #46                 // Method ch/qos/logback/classic/Logger.getName:()Ljava/lang/String;
      42: invokestatic  #50                 // Method java/util/Collections.emptyMap:()Ljava/util/Map;
      45: invokestatic  #56                 // Method cloud/prefab/context/PrefabContext.unnamedFromMap:(Ljava/util/Map;)Lcloud/prefab/context/PrefabContext;
      48: invokeinterface #62,  3           // InterfaceMethod cloud/prefab/client/ConfigClient.getLogLevel:(Ljava/lang/String;Lcloud/prefab/context/PrefabContextSetReadable;)Ljava/util/Optional;
      53: invokestatic  #35                 // Method org/mockito/Mockito.when:(Ljava/lang/Object;)Lorg/mockito/stubbing/OngoingStubbing;
      56: getstatic     #112                // Field cloud/prefab/domain/Prefab$LogLevel.DEBUG:Lcloud/prefab/domain/Prefab$LogLevel;
      59: invokestatic  #121                // Method java/util/Optional.of:(Ljava/lang/Object;)Ljava/util/Optional;
      62: invokeinterface #41,  2           // InterfaceMethod org/mockito/stubbing/OngoingStubbing.thenReturn:(Ljava/lang/Object;)Lorg/mockito/stubbing/OngoingStubbing;
      67: pop
      68: aload_0
      69: getfield      #72                 // Field logbackTurboFilter:Lcloud/prefab/client/config/logging/PrefabMDCTurboFilter;
      72: aconst_null
      73: aload_1
      74: getstatic     #76                 // Field ch/qos/logback/classic/Level.DEBUG:Lch/qos/logback/classic/Level;
      77: ldc           #82                 // String
      79: iconst_0
      80: anewarray     #2                  // class java/lang/Object
      83: aconst_null
      84: invokevirtual #84                 // Method cloud/prefab/client/config/logging/PrefabMDCTurboFilter.decide:(Lorg/slf4j/Marker;Lch/qos/logback/classic/Logger;Lch/qos/logback/classic/Level;Ljava/lang/String;[Ljava/lang/Object;Ljava/lang/Throwable;)Lch/qos/logback/core/spi/FilterReply;
      87: invokestatic  #90                 // Method org/assertj/core/api/Assertions.assertThat:(Ljava/lang/Comparable;)Lorg/assertj/core/api/AbstractComparableAssert;
      90: getstatic     #125                // Field ch/qos/logback/core/spi/FilterReply.ACCEPT:Lch/qos/logback/core/spi/FilterReply;
      93: invokevirtual #102                // Method org/assertj/core/api/AbstractComparableAssert.isEqualTo:(Ljava/lang/Object;)Lorg/assertj/core/api/AbstractAssert;
      96: pop
      97: aload_0
      98: getfield      #17                 // Field configClient:Lcloud/prefab/client/ConfigClient;
     101: invokestatic  #108                // Method org/mockito/Mockito.verify:(Ljava/lang/Object;)Ljava/lang/Object;
     104: checkcast     #24                 // class cloud/prefab/client/ConfigClient
     107: aload_1
     108: invokevirtual #46                 // Method ch/qos/logback/classic/Logger.getName:()Ljava/lang/String;
     111: getstatic     #112                // Field cloud/prefab/domain/Prefab$LogLevel.DEBUG:Lcloud/prefab/domain/Prefab$LogLevel;
     114: lconst_1
     115: invokeinterface #117,  5          // InterfaceMethod cloud/prefab/client/ConfigClient.reportLoggerUsage:(Ljava/lang/String;Lcloud/prefab/domain/Prefab$LogLevel;J)V
     120: return

  void itReportsLoggingAndAsksForLogLevelReturnsDeny();
    Code:
       0: ldc           #7                  // String com.example.factory.FactoryFactory
       2: invokestatic  #9                  // Method org/slf4j/LoggerFactory.getLogger:(Ljava/lang/String;)Lorg/slf4j/Logger;
       5: checkcast     #15                 // class ch/qos/logback/classic/Logger
       8: astore_1
       9: aload_0
      10: getfield      #17                 // Field configClient:Lcloud/prefab/client/ConfigClient;
      13: invokeinterface #23,  1           // InterfaceMethod cloud/prefab/client/ConfigClient.isReady:()Z
      18: invokestatic  #29                 // Method java/lang/Boolean.valueOf:(Z)Ljava/lang/Boolean;
      21: invokestatic  #35                 // Method org/mockito/Mockito.when:(Ljava/lang/Object;)Lorg/mockito/stubbing/OngoingStubbing;
      24: iconst_1
      25: invokestatic  #29                 // Method java/lang/Boolean.valueOf:(Z)Ljava/lang/Boolean;
      28: invokeinterface #41,  2           // InterfaceMethod org/mockito/stubbing/OngoingStubbing.thenReturn:(Ljava/lang/Object;)Lorg/mockito/stubbing/OngoingStubbing;
      33: pop
      34: aload_0
      35: getfield      #17                 // Field configClient:Lcloud/prefab/client/ConfigClient;
      38: aload_1
      39: invokevirtual #46                 // Method ch/qos/logback/classic/Logger.getName:()Ljava/lang/String;
      42: invokestatic  #50                 // Method java/util/Collections.emptyMap:()Ljava/util/Map;
      45: invokestatic  #56                 // Method cloud/prefab/context/PrefabContext.unnamedFromMap:(Ljava/util/Map;)Lcloud/prefab/context/PrefabContext;
      48: invokeinterface #62,  3           // InterfaceMethod cloud/prefab/client/ConfigClient.getLogLevel:(Ljava/lang/String;Lcloud/prefab/context/PrefabContextSetReadable;)Ljava/util/Optional;
      53: invokestatic  #35                 // Method org/mockito/Mockito.when:(Ljava/lang/Object;)Lorg/mockito/stubbing/OngoingStubbing;
      56: getstatic     #128                // Field cloud/prefab/domain/Prefab$LogLevel.WARN:Lcloud/prefab/domain/Prefab$LogLevel;
      59: invokestatic  #121                // Method java/util/Optional.of:(Ljava/lang/Object;)Ljava/util/Optional;
      62: invokeinterface #41,  2           // InterfaceMethod org/mockito/stubbing/OngoingStubbing.thenReturn:(Ljava/lang/Object;)Lorg/mockito/stubbing/OngoingStubbing;
      67: pop
      68: aload_0
      69: getfield      #72                 // Field logbackTurboFilter:Lcloud/prefab/client/config/logging/PrefabMDCTurboFilter;
      72: aconst_null
      73: aload_1
      74: getstatic     #76                 // Field ch/qos/logback/classic/Level.DEBUG:Lch/qos/logback/classic/Level;
      77: ldc           #82                 // String
      79: iconst_0
      80: anewarray     #2                  // class java/lang/Object
      83: aconst_null
      84: invokevirtual #84                 // Method cloud/prefab/client/config/logging/PrefabMDCTurboFilter.decide:(Lorg/slf4j/Marker;Lch/qos/logback/classic/Logger;Lch/qos/logback/classic/Level;Ljava/lang/String;[Ljava/lang/Object;Ljava/lang/Throwable;)Lch/qos/logback/core/spi/FilterReply;
      87: invokestatic  #90                 // Method org/assertj/core/api/Assertions.assertThat:(Ljava/lang/Comparable;)Lorg/assertj/core/api/AbstractComparableAssert;
      90: getstatic     #131                // Field ch/qos/logback/core/spi/FilterReply.DENY:Lch/qos/logback/core/spi/FilterReply;
      93: invokevirtual #102                // Method org/assertj/core/api/AbstractComparableAssert.isEqualTo:(Ljava/lang/Object;)Lorg/assertj/core/api/AbstractAssert;
      96: pop
      97: aload_0
      98: getfield      #17                 // Field configClient:Lcloud/prefab/client/ConfigClient;
     101: invokestatic  #108                // Method org/mockito/Mockito.verify:(Ljava/lang/Object;)Ljava/lang/Object;
     104: checkcast     #24                 // class cloud/prefab/client/ConfigClient
     107: aload_1
     108: invokevirtual #46                 // Method ch/qos/logback/classic/Logger.getName:()Ljava/lang/String;
     111: getstatic     #112                // Field cloud/prefab/domain/Prefab$LogLevel.DEBUG:Lcloud/prefab/domain/Prefab$LogLevel;
     114: lconst_1
     115: invokeinterface #117,  5          // InterfaceMethod cloud/prefab/client/ConfigClient.reportLoggerUsage:(Ljava/lang/String;Lcloud/prefab/domain/Prefab$LogLevel;J)V
     120: return

  void itSendsAvailableMdcData();
    Code:
       0: ldc           #7                  // String com.example.factory.FactoryFactory
       2: invokestatic  #9                  // Method org/slf4j/LoggerFactory.getLogger:(Ljava/lang/String;)Lorg/slf4j/Logger;
       5: checkcast     #15                 // class ch/qos/logback/classic/Logger
       8: astore_1
       9: aload_0
      10: getfield      #17                 // Field configClient:Lcloud/prefab/client/ConfigClient;
      13: invokeinterface #23,  1           // InterfaceMethod cloud/prefab/client/ConfigClient.isReady:()Z
      18: invokestatic  #29                 // Method java/lang/Boolean.valueOf:(Z)Ljava/lang/Boolean;
      21: invokestatic  #35                 // Method org/mockito/Mockito.when:(Ljava/lang/Object;)Lorg/mockito/stubbing/OngoingStubbing;
      24: iconst_1
      25: invokestatic  #29                 // Method java/lang/Boolean.valueOf:(Z)Ljava/lang/Boolean;
      28: invokeinterface #41,  2           // InterfaceMethod org/mockito/stubbing/OngoingStubbing.thenReturn:(Ljava/lang/Object;)Lorg/mockito/stubbing/OngoingStubbing;
      33: pop
      34: ldc           #134                // String key1
      36: ldc           #136                // String val1
      38: ldc           #138                // String key2
      40: ldc           #140                // String val2
      42: invokestatic  #142                // InterfaceMethod java/util/Map.of:(Ljava/lang/Object;Ljava/lang/Object;Ljava/lang/Object;Ljava/lang/Object;)Ljava/util/Map;
      45: astore_2
      46: aload_2
      47: invokestatic  #147                // Method org/slf4j/MDC.setContextMap:(Ljava/util/Map;)V
      50: aload_0
      51: getfield      #17                 // Field configClient:Lcloud/prefab/client/ConfigClient;
      54: aload_1
      55: invokevirtual #46                 // Method ch/qos/logback/classic/Logger.getName:()Ljava/lang/String;
      58: aload_2
      59: invokestatic  #153                // Method cloud/prefab/client/config/ConfigValueUtils.fromStringMap:(Ljava/util/Map;)Ljava/util/Map;
      62: invokestatic  #56                 // Method cloud/prefab/context/PrefabContext.unnamedFromMap:(Ljava/util/Map;)Lcloud/prefab/context/PrefabContext;
      65: invokeinterface #62,  3           // InterfaceMethod cloud/prefab/client/ConfigClient.getLogLevel:(Ljava/lang/String;Lcloud/prefab/context/PrefabContextSetReadable;)Ljava/util/Optional;
      70: invokestatic  #35                 // Method org/mockito/Mockito.when:(Ljava/lang/Object;)Lorg/mockito/stubbing/OngoingStubbing;
      73: getstatic     #112                // Field cloud/prefab/domain/Prefab$LogLevel.DEBUG:Lcloud/prefab/domain/Prefab$LogLevel;
      76: invokestatic  #121                // Method java/util/Optional.of:(Ljava/lang/Object;)Ljava/util/Optional;
      79: invokeinterface #41,  2           // InterfaceMethod org/mockito/stubbing/OngoingStubbing.thenReturn:(Ljava/lang/Object;)Lorg/mockito/stubbing/OngoingStubbing;
      84: pop
      85: aload_0
      86: getfield      #72                 // Field logbackTurboFilter:Lcloud/prefab/client/config/logging/PrefabMDCTurboFilter;
      89: aconst_null
      90: aload_1
      91: getstatic     #76                 // Field ch/qos/logback/classic/Level.DEBUG:Lch/qos/logback/classic/Level;
      94: ldc           #82                 // String
      96: iconst_0
      97: anewarray     #2                  // class java/lang/Object
     100: aconst_null
     101: invokevirtual #84                 // Method cloud/prefab/client/config/logging/PrefabMDCTurboFilter.decide:(Lorg/slf4j/Marker;Lch/qos/logback/classic/Logger;Lch/qos/logback/classic/Level;Ljava/lang/String;[Ljava/lang/Object;Ljava/lang/Throwable;)Lch/qos/logback/core/spi/FilterReply;
     104: invokestatic  #90                 // Method org/assertj/core/api/Assertions.assertThat:(Ljava/lang/Comparable;)Lorg/assertj/core/api/AbstractComparableAssert;
     107: getstatic     #125                // Field ch/qos/logback/core/spi/FilterReply.ACCEPT:Lch/qos/logback/core/spi/FilterReply;
     110: invokevirtual #102                // Method org/assertj/core/api/AbstractComparableAssert.isEqualTo:(Ljava/lang/Object;)Lorg/assertj/core/api/AbstractAssert;
     113: pop
     114: aload_0
     115: getfield      #17                 // Field configClient:Lcloud/prefab/client/ConfigClient;
     118: invokestatic  #108                // Method org/mockito/Mockito.verify:(Ljava/lang/Object;)Ljava/lang/Object;
     121: checkcast     #24                 // class cloud/prefab/client/ConfigClient
     124: aload_1
     125: invokevirtual #46                 // Method ch/qos/logback/classic/Logger.getName:()Ljava/lang/String;
     128: getstatic     #112                // Field cloud/prefab/domain/Prefab$LogLevel.DEBUG:Lcloud/prefab/domain/Prefab$LogLevel;
     131: lconst_1
     132: invokeinterface #117,  5          // InterfaceMethod cloud/prefab/client/ConfigClient.reportLoggerUsage:(Ljava/lang/String;Lcloud/prefab/domain/Prefab$LogLevel;J)V
     137: invokestatic  #159                // Method org/slf4j/MDC.clear:()V
     140: goto          149
     143: astore_3
     144: invokestatic  #159                // Method org/slf4j/MDC.clear:()V
     147: aload_3
     148: athrow
     149: return
    Exception table:
       from    to  target type
          46   137   143   any

  void itEarlyOutsIfClientUnready();
    Code:
       0: ldc           #7                  // String com.example.factory.FactoryFactory
       2: invokestatic  #9                  // Method org/slf4j/LoggerFactory.getLogger:(Ljava/lang/String;)Lorg/slf4j/Logger;
       5: checkcast     #15                 // class ch/qos/logback/classic/Logger
       8: astore_1
       9: aload_0
      10: getfield      #17                 // Field configClient:Lcloud/prefab/client/ConfigClient;
      13: invokeinterface #23,  1           // InterfaceMethod cloud/prefab/client/ConfigClient.isReady:()Z
      18: invokestatic  #29                 // Method java/lang/Boolean.valueOf:(Z)Ljava/lang/Boolean;
      21: invokestatic  #35                 // Method org/mockito/Mockito.when:(Ljava/lang/Object;)Lorg/mockito/stubbing/OngoingStubbing;
      24: iconst_0
      25: invokestatic  #29                 // Method java/lang/Boolean.valueOf:(Z)Ljava/lang/Boolean;
      28: invokeinterface #41,  2           // InterfaceMethod org/mockito/stubbing/OngoingStubbing.thenReturn:(Ljava/lang/Object;)Lorg/mockito/stubbing/OngoingStubbing;
      33: pop
      34: aload_0
      35: getfield      #72                 // Field logbackTurboFilter:Lcloud/prefab/client/config/logging/PrefabMDCTurboFilter;
      38: aconst_null
      39: aload_1
      40: getstatic     #76                 // Field ch/qos/logback/classic/Level.DEBUG:Lch/qos/logback/classic/Level;
      43: ldc           #82                 // String
      45: iconst_0
      46: anewarray     #2                  // class java/lang/Object
      49: aconst_null
      50: invokevirtual #84                 // Method cloud/prefab/client/config/logging/PrefabMDCTurboFilter.decide:(Lorg/slf4j/Marker;Lch/qos/logback/classic/Logger;Lch/qos/logback/classic/Level;Ljava/lang/String;[Ljava/lang/Object;Ljava/lang/Throwable;)Lch/qos/logback/core/spi/FilterReply;
      53: invokestatic  #90                 // Method org/assertj/core/api/Assertions.assertThat:(Ljava/lang/Comparable;)Lorg/assertj/core/api/AbstractComparableAssert;
      56: getstatic     #96                 // Field ch/qos/logback/core/spi/FilterReply.NEUTRAL:Lch/qos/logback/core/spi/FilterReply;
      59: invokevirtual #102                // Method org/assertj/core/api/AbstractComparableAssert.isEqualTo:(Ljava/lang/Object;)Lorg/assertj/core/api/AbstractAssert;
      62: pop
      63: iconst_1
      64: anewarray     #2                  // class java/lang/Object
      67: dup
      68: iconst_0
      69: aload_0
      70: getfield      #17                 // Field configClient:Lcloud/prefab/client/ConfigClient;
      73: aastore
      74: invokestatic  #162                // Method org/mockito/Mockito.verifyNoMoreInteractions:([Ljava/lang/Object;)V
      77: return
}
