Compiled from "FileTypeConverter.java"
public final class org.sonatype.guice.bean.converters.FileTypeConverter extends org.sonatype.guice.bean.converters.AbstractTypeConverter<java.io.File> {
  public org.sonatype.guice.bean.converters.FileTypeConverter();
    Code:
       0: aload_0
       1: invokespecial #1                  // Method org/sonatype/guice/bean/converters/AbstractTypeConverter."<init>":()V
       4: return

  public java.lang.Object convert(java.lang.String, com.google.inject.TypeLiteral<?>);
    Code:
       0: new           #2                  // class java/io/File
       3: dup
       4: aload_1
       5: invokespecial #3                  // Method java/io/File."<init>":(Ljava/lang/String;)V
       8: areturn
}
