Compiled from "ProcessedCommand.java"
public final class org.jboss.aesh.cl.internal.ProcessedCommand<C extends org.jboss.aesh.console.command.Command> {
  private java.lang.String name;

  private java.lang.String description;

  private org.jboss.aesh.cl.validator.CommandValidator validator;

  private org.jboss.aesh.cl.result.ResultHandler resultHandler;

  private org.jboss.aesh.cl.populator.CommandPopulator populator;

  private java.util.List<org.jboss.aesh.cl.internal.ProcessedOption> options;

  private org.jboss.aesh.cl.internal.ProcessedOption argument;

  private C command;

  public org.jboss.aesh.cl.internal.ProcessedCommand(java.lang.String, C, java.lang.String, org.jboss.aesh.cl.validator.CommandValidator, org.jboss.aesh.cl.result.ResultHandler, org.jboss.aesh.cl.internal.ProcessedOption, java.util.List<org.jboss.aesh.cl.internal.ProcessedOption>, org.jboss.aesh.cl.populator.CommandPopulator) throws org.jboss.aesh.cl.parser.OptionParserException;
    Code:
       0: aload_0
       1: invokespecial #1                  // Method java/lang/Object."<init>":()V
       4: aload_0
       5: new           #2                  // class org/jboss/aesh/cl/result/NullResultHandler
       8: dup
       9: invokespecial #3                  // Method org/jboss/aesh/cl/result/NullResultHandler."<init>":()V
      12: putfield      #4                  // Field resultHandler:Lorg/jboss/aesh/cl/result/ResultHandler;
      15: aload_0
      16: aload_1
      17: invokespecial #5                  // Method setName:(Ljava/lang/String;)V
      20: aload_0
      21: aload_3
      22: invokespecial #6                  // Method setDescription:(Ljava/lang/String;)V
      25: aload_0
      26: aload         4
      28: putfield      #7                  // Field validator:Lorg/jboss/aesh/cl/validator/CommandValidator;
      31: aload_0
      32: aload         5
      34: putfield      #4                  // Field resultHandler:Lorg/jboss/aesh/cl/result/ResultHandler;
      37: aload_0
      38: aload         6
      40: putfield      #8                  // Field argument:Lorg/jboss/aesh/cl/internal/ProcessedOption;
      43: aload_0
      44: new           #9                  // class java/util/ArrayList
      47: dup
      48: invokespecial #10                 // Method java/util/ArrayList."<init>":()V
      51: putfield      #11                 // Field options:Ljava/util/List;
      54: aload_0
      55: aload_2
      56: putfield      #12                 // Field command:Lorg/jboss/aesh/console/command/Command;
      59: aload         8
      61: ifnonnull     82
      64: aload_0
      65: new           #13                 // class org/jboss/aesh/cl/populator/AeshCommandPopulator
      68: dup
      69: aload_0
      70: getfield      #12                 // Field command:Lorg/jboss/aesh/console/command/Command;
      73: invokespecial #14                 // Method org/jboss/aesh/cl/populator/AeshCommandPopulator."<init>":(Ljava/lang/Object;)V
      76: putfield      #15                 // Field populator:Lorg/jboss/aesh/cl/populator/CommandPopulator;
      79: goto          88
      82: aload_0
      83: aload         8
      85: putfield      #15                 // Field populator:Lorg/jboss/aesh/cl/populator/CommandPopulator;
      88: aload_0
      89: aload         7
      91: invokespecial #16                 // Method setOptions:(Ljava/util/List;)V
      94: return

  public java.util.List<org.jboss.aesh.cl.internal.ProcessedOption> getOptions();
    Code:
       0: aload_0
       1: getfield      #11                 // Field options:Ljava/util/List;
       4: areturn

  public void addOption(org.jboss.aesh.cl.internal.ProcessedOption) throws org.jboss.aesh.cl.parser.OptionParserException;
    Code:
       0: aload_0
       1: getfield      #11                 // Field options:Ljava/util/List;
       4: new           #17                 // class org/jboss/aesh/cl/internal/ProcessedOption
       7: dup
       8: aload_0
       9: aload_1
      10: invokevirtual #18                 // Method org/jboss/aesh/cl/internal/ProcessedOption.getShortName:()Ljava/lang/String;
      13: aload_1
      14: invokevirtual #19                 // Method org/jboss/aesh/cl/internal/ProcessedOption.getName:()Ljava/lang/String;
      17: invokespecial #20                 // Method verifyThatNamesAreUnique:(Ljava/lang/String;Ljava/lang/String;)C
      20: aload_1
      21: invokevirtual #19                 // Method org/jboss/aesh/cl/internal/ProcessedOption.getName:()Ljava/lang/String;
      24: aload_1
      25: invokevirtual #21                 // Method org/jboss/aesh/cl/internal/ProcessedOption.getDescription:()Ljava/lang/String;
      28: aload_1
      29: invokevirtual #22                 // Method org/jboss/aesh/cl/internal/ProcessedOption.getArgument:()Ljava/lang/String;
      32: aload_1
      33: invokevirtual #23                 // Method org/jboss/aesh/cl/internal/ProcessedOption.isRequired:()Z
      36: aload_1
      37: invokevirtual #24                 // Method org/jboss/aesh/cl/internal/ProcessedOption.getValueSeparator:()C
      40: aload_1
      41: invokevirtual #25                 // Method org/jboss/aesh/cl/internal/ProcessedOption.getDefaultValues:()Ljava/util/List;
      44: aload_1
      45: invokevirtual #26                 // Method org/jboss/aesh/cl/internal/ProcessedOption.getType:()Ljava/lang/Class;
      48: aload_1
      49: invokevirtual #27                 // Method org/jboss/aesh/cl/internal/ProcessedOption.getFieldName:()Ljava/lang/String;
      52: aload_1
      53: invokevirtual #28                 // Method org/jboss/aesh/cl/internal/ProcessedOption.getOptionType:()Lorg/jboss/aesh/cl/internal/OptionType;
      56: aload_1
      57: invokevirtual #29                 // Method org/jboss/aesh/cl/internal/ProcessedOption.getConverter:()Lorg/jboss/aesh/cl/converter/Converter;
      60: aload_1
      61: invokevirtual #30                 // Method org/jboss/aesh/cl/internal/ProcessedOption.getCompleter:()Lorg/jboss/aesh/cl/completer/OptionCompleter;
      64: aload_1
      65: invokevirtual #31                 // Method org/jboss/aesh/cl/internal/ProcessedOption.getValidator:()Lorg/jboss/aesh/cl/validator/OptionValidator;
      68: aload_1
      69: invokevirtual #32                 // Method org/jboss/aesh/cl/internal/ProcessedOption.getActivator:()Lorg/jboss/aesh/cl/activation/OptionActivator;
      72: aload_1
      73: invokevirtual #33                 // Method org/jboss/aesh/cl/internal/ProcessedOption.getRenderer:()Lorg/jboss/aesh/cl/renderer/OptionRenderer;
      76: aload_1
      77: invokevirtual #34                 // Method org/jboss/aesh/cl/internal/ProcessedOption.doOverrideRequired:()Z
      80: invokespecial #35                 // Method org/jboss/aesh/cl/internal/ProcessedOption."<init>":(CLjava/lang/String;Ljava/lang/String;Ljava/lang/String;ZCLjava/util/List;Ljava/lang/Class;Ljava/lang/String;Lorg/jboss/aesh/cl/internal/OptionType;Lorg/jboss/aesh/cl/converter/Converter;Lorg/jboss/aesh/cl/completer/OptionCompleter;Lorg/jboss/aesh/cl/validator/OptionValidator;Lorg/jboss/aesh/cl/activation/OptionActivator;Lorg/jboss/aesh/cl/renderer/OptionRenderer;Z)V
      83: invokeinterface #36,  2           // InterfaceMethod java/util/List.add:(Ljava/lang/Object;)Z
      88: pop
      89: return

  private void setOptions(java.util.List<org.jboss.aesh.cl.internal.ProcessedOption>) throws org.jboss.aesh.cl.parser.OptionParserException;
    Code:
       0: aload_1
       1: invokeinterface #37,  1           // InterfaceMethod java/util/List.iterator:()Ljava/util/Iterator;
       6: astore_2
       7: aload_2
       8: invokeinterface #38,  1           // InterfaceMethod java/util/Iterator.hasNext:()Z
      13: ifeq          118
      16: aload_2
      17: invokeinterface #39,  1           // InterfaceMethod java/util/Iterator.next:()Ljava/lang/Object;
      22: checkcast     #17                 // class org/jboss/aesh/cl/internal/ProcessedOption
      25: astore_3
      26: aload_0
      27: getfield      #11                 // Field options:Ljava/util/List;
      30: new           #17                 // class org/jboss/aesh/cl/internal/ProcessedOption
      33: dup
      34: aload_0
      35: aload_3
      36: invokevirtual #18                 // Method org/jboss/aesh/cl/internal/ProcessedOption.getShortName:()Ljava/lang/String;
      39: aload_3
      40: invokevirtual #19                 // Method org/jboss/aesh/cl/internal/ProcessedOption.getName:()Ljava/lang/String;
      43: invokespecial #20                 // Method verifyThatNamesAreUnique:(Ljava/lang/String;Ljava/lang/String;)C
      46: aload_3
      47: invokevirtual #19                 // Method org/jboss/aesh/cl/internal/ProcessedOption.getName:()Ljava/lang/String;
      50: aload_3
      51: invokevirtual #21                 // Method org/jboss/aesh/cl/internal/ProcessedOption.getDescription:()Ljava/lang/String;
      54: aload_3
      55: invokevirtual #22                 // Method org/jboss/aesh/cl/internal/ProcessedOption.getArgument:()Ljava/lang/String;
      58: aload_3
      59: invokevirtual #23                 // Method org/jboss/aesh/cl/internal/ProcessedOption.isRequired:()Z
      62: aload_3
      63: invokevirtual #24                 // Method org/jboss/aesh/cl/internal/ProcessedOption.getValueSeparator:()C
      66: aload_3
      67: invokevirtual #25                 // Method org/jboss/aesh/cl/internal/ProcessedOption.getDefaultValues:()Ljava/util/List;
      70: aload_3
      71: invokevirtual #26                 // Method org/jboss/aesh/cl/internal/ProcessedOption.getType:()Ljava/lang/Class;
      74: aload_3
      75: invokevirtual #27                 // Method org/jboss/aesh/cl/internal/ProcessedOption.getFieldName:()Ljava/lang/String;
      78: aload_3
      79: invokevirtual #28                 // Method org/jboss/aesh/cl/internal/ProcessedOption.getOptionType:()Lorg/jboss/aesh/cl/internal/OptionType;
      82: aload_3
      83: invokevirtual #29                 // Method org/jboss/aesh/cl/internal/ProcessedOption.getConverter:()Lorg/jboss/aesh/cl/converter/Converter;
      86: aload_3
      87: invokevirtual #30                 // Method org/jboss/aesh/cl/internal/ProcessedOption.getCompleter:()Lorg/jboss/aesh/cl/completer/OptionCompleter;
      90: aload_3
      91: invokevirtual #31                 // Method org/jboss/aesh/cl/internal/ProcessedOption.getValidator:()Lorg/jboss/aesh/cl/validator/OptionValidator;
      94: aload_3
      95: invokevirtual #32                 // Method org/jboss/aesh/cl/internal/ProcessedOption.getActivator:()Lorg/jboss/aesh/cl/activation/OptionActivator;
      98: aload_3
      99: invokevirtual #33                 // Method org/jboss/aesh/cl/internal/ProcessedOption.getRenderer:()Lorg/jboss/aesh/cl/renderer/OptionRenderer;
     102: aload_3
     103: invokevirtual #34                 // Method org/jboss/aesh/cl/internal/ProcessedOption.doOverrideRequired:()Z
     106: invokespecial #35                 // Method org/jboss/aesh/cl/internal/ProcessedOption."<init>":(CLjava/lang/String;Ljava/lang/String;Ljava/lang/String;ZCLjava/util/List;Ljava/lang/Class;Ljava/lang/String;Lorg/jboss/aesh/cl/internal/OptionType;Lorg/jboss/aesh/cl/converter/Converter;Lorg/jboss/aesh/cl/completer/OptionCompleter;Lorg/jboss/aesh/cl/validator/OptionValidator;Lorg/jboss/aesh/cl/activation/OptionActivator;Lorg/jboss/aesh/cl/renderer/OptionRenderer;Z)V
     109: invokeinterface #36,  2           // InterfaceMethod java/util/List.add:(Ljava/lang/Object;)Z
     114: pop
     115: goto          7
     118: return

  public java.lang.String getName();
    Code:
       0: aload_0
       1: getfield      #40                 // Field name:Ljava/lang/String;
       4: areturn

  private void setName(java.lang.String);
    Code:
       0: aload_0
       1: aload_1
       2: putfield      #40                 // Field name:Ljava/lang/String;
       5: return

  public java.lang.String getDescription();
    Code:
       0: aload_0
       1: getfield      #41                 // Field description:Ljava/lang/String;
       4: areturn

  private void setDescription(java.lang.String);
    Code:
       0: aload_0
       1: aload_1
       2: putfield      #41                 // Field description:Ljava/lang/String;
       5: return

  public org.jboss.aesh.cl.validator.CommandValidator getValidator();
    Code:
       0: aload_0
       1: getfield      #7                  // Field validator:Lorg/jboss/aesh/cl/validator/CommandValidator;
       4: areturn

  public org.jboss.aesh.cl.result.ResultHandler getResultHandler();
    Code:
       0: aload_0
       1: getfield      #4                  // Field resultHandler:Lorg/jboss/aesh/cl/result/ResultHandler;
       4: areturn

  public boolean hasArgument();
    Code:
       0: aload_0
       1: getfield      #8                  // Field argument:Lorg/jboss/aesh/cl/internal/ProcessedOption;
       4: ifnull        21
       7: aload_0
       8: getfield      #8                  // Field argument:Lorg/jboss/aesh/cl/internal/ProcessedOption;
      11: invokevirtual #42                 // Method org/jboss/aesh/cl/internal/ProcessedOption.hasMultipleValues:()Z
      14: ifeq          21
      17: iconst_1
      18: goto          22
      21: iconst_0
      22: ireturn

  public org.jboss.aesh.cl.internal.ProcessedOption getArgument();
    Code:
       0: aload_0
       1: getfield      #8                  // Field argument:Lorg/jboss/aesh/cl/internal/ProcessedOption;
       4: areturn

  public void setArgument(org.jboss.aesh.cl.internal.ProcessedOption);
    Code:
       0: aload_0
       1: aload_1
       2: putfield      #8                  // Field argument:Lorg/jboss/aesh/cl/internal/ProcessedOption;
       5: return

  public org.jboss.aesh.cl.populator.CommandPopulator getCommandPopulator();
    Code:
       0: aload_0
       1: getfield      #15                 // Field populator:Lorg/jboss/aesh/cl/populator/CommandPopulator;
       4: areturn

  public C getCommand();
    Code:
       0: aload_0
       1: getfield      #12                 // Field command:Lorg/jboss/aesh/console/command/Command;
       4: areturn

  private char verifyThatNamesAreUnique(java.lang.String, java.lang.String) throws org.jboss.aesh.cl.parser.OptionParserException;
    Code:
       0: aload_1
       1: ifnull        15
       4: aload_0
       5: aload_1
       6: iconst_0
       7: invokevirtual #43                 // Method java/lang/String.charAt:(I)C
      10: aload_2
      11: invokespecial #44                 // Method verifyThatNamesAreUnique:(CLjava/lang/String;)C
      14: ireturn
      15: aload_0
      16: iconst_0
      17: aload_2
      18: invokespecial #44                 // Method verifyThatNamesAreUnique:(CLjava/lang/String;)C
      21: ireturn

  private char verifyThatNamesAreUnique(char, java.lang.String) throws org.jboss.aesh.cl.parser.OptionParserException;
    Code:
       0: aload_2
       1: ifnull        58
       4: aload_2
       5: invokevirtual #45                 // Method java/lang/String.length:()I
       8: ifle          58
      11: aload_0
      12: aload_2
      13: invokevirtual #46                 // Method findLongOption:(Ljava/lang/String;)Lorg/jboss/aesh/cl/internal/ProcessedOption;
      16: ifnull        58
      19: new           #47                 // class org/jboss/aesh/cl/parser/OptionParserException
      22: dup
      23: new           #48                 // class java/lang/StringBuilder
      26: dup
      27: invokespecial #49                 // Method java/lang/StringBuilder."<init>":()V
      30: ldc           #50                 // String Option --
      32: invokevirtual #51                 // Method java/lang/StringBuilder.append:(Ljava/lang/String;)Ljava/lang/StringBuilder;
      35: aload_2
      36: invokevirtual #51                 // Method java/lang/StringBuilder.append:(Ljava/lang/String;)Ljava/lang/StringBuilder;
      39: ldc           #52                 // String  is already added to Param:
      41: invokevirtual #51                 // Method java/lang/StringBuilder.append:(Ljava/lang/String;)Ljava/lang/StringBuilder;
      44: aload_0
      45: invokevirtual #53                 // Method toString:()Ljava/lang/String;
      48: invokevirtual #51                 // Method java/lang/StringBuilder.append:(Ljava/lang/String;)Ljava/lang/StringBuilder;
      51: invokevirtual #54                 // Method java/lang/StringBuilder.toString:()Ljava/lang/String;
      54: invokespecial #55                 // Method org/jboss/aesh/cl/parser/OptionParserException."<init>":(Ljava/lang/String;)V
      57: athrow
      58: iload_1
      59: ifeq          112
      62: aload_0
      63: iload_1
      64: invokestatic  #56                 // Method java/lang/String.valueOf:(C)Ljava/lang/String;
      67: invokevirtual #57                 // Method findOption:(Ljava/lang/String;)Lorg/jboss/aesh/cl/internal/ProcessedOption;
      70: ifnull        112
      73: new           #47                 // class org/jboss/aesh/cl/parser/OptionParserException
      76: dup
      77: new           #48                 // class java/lang/StringBuilder
      80: dup
      81: invokespecial #49                 // Method java/lang/StringBuilder."<init>":()V
      84: ldc           #58                 // String Option -
      86: invokevirtual #51                 // Method java/lang/StringBuilder.append:(Ljava/lang/String;)Ljava/lang/StringBuilder;
      89: iload_1
      90: invokevirtual #59                 // Method java/lang/StringBuilder.append:(C)Ljava/lang/StringBuilder;
      93: ldc           #52                 // String  is already added to Param:
      95: invokevirtual #51                 // Method java/lang/StringBuilder.append:(Ljava/lang/String;)Ljava/lang/StringBuilder;
      98: aload_0
      99: invokevirtual #53                 // Method toString:()Ljava/lang/String;
     102: invokevirtual #51                 // Method java/lang/StringBuilder.append:(Ljava/lang/String;)Ljava/lang/StringBuilder;
     105: invokevirtual #54                 // Method java/lang/StringBuilder.toString:()Ljava/lang/String;
     108: invokespecial #55                 // Method org/jboss/aesh/cl/parser/OptionParserException."<init>":(Ljava/lang/String;)V
     111: athrow
     112: iload_1
     113: ifne          137
     116: aload_2
     117: ifnull        127
     120: aload_2
     121: invokevirtual #45                 // Method java/lang/String.length:()I
     124: ifne          137
     127: new           #47                 // class org/jboss/aesh/cl/parser/OptionParserException
     130: dup
     131: ldc           #60                 // String Neither option name and option long name can be both null
     133: invokespecial #55                 // Method org/jboss/aesh/cl/parser/OptionParserException."<init>":(Ljava/lang/String;)V
     136: athrow
     137: iload_1
     138: ireturn

  private char findPossibleName(java.lang.String) throws org.jboss.aesh.cl.parser.OptionParserException;
    Code:
       0: iconst_0
       1: istore_2
       2: iload_2
       3: aload_1
       4: invokevirtual #45                 // Method java/lang/String.length:()I
       7: if_icmpge     37
      10: aload_0
      11: aload_1
      12: iload_2
      13: invokevirtual #43                 // Method java/lang/String.charAt:(I)C
      16: invokestatic  #56                 // Method java/lang/String.valueOf:(C)Ljava/lang/String;
      19: invokevirtual #57                 // Method findOption:(Ljava/lang/String;)Lorg/jboss/aesh/cl/internal/ProcessedOption;
      22: ifnonnull     31
      25: aload_1
      26: iload_2
      27: invokevirtual #43                 // Method java/lang/String.charAt:(I)C
      30: ireturn
      31: iinc          2, 1
      34: goto          2
      37: new           #47                 // class org/jboss/aesh/cl/parser/OptionParserException
      40: dup
      41: ldc           #61                 // String All option names are taken, please specify a unique name
      43: invokespecial #55                 // Method org/jboss/aesh/cl/parser/OptionParserException."<init>":(Ljava/lang/String;)V
      46: athrow

  public org.jboss.aesh.cl.internal.ProcessedOption findOption(java.lang.String);
    Code:
       0: aload_0
       1: getfield      #11                 // Field options:Ljava/util/List;
       4: invokeinterface #37,  1           // InterfaceMethod java/util/List.iterator:()Ljava/util/Iterator;
       9: astore_2
      10: aload_2
      11: invokeinterface #38,  1           // InterfaceMethod java/util/Iterator.hasNext:()Z
      16: ifeq          65
      19: aload_2
      20: invokeinterface #39,  1           // InterfaceMethod java/util/Iterator.next:()Ljava/lang/Object;
      25: checkcast     #17                 // class org/jboss/aesh/cl/internal/ProcessedOption
      28: astore_3
      29: aload_3
      30: invokevirtual #18                 // Method org/jboss/aesh/cl/internal/ProcessedOption.getShortName:()Ljava/lang/String;
      33: ifnull        62
      36: aload_3
      37: invokevirtual #18                 // Method org/jboss/aesh/cl/internal/ProcessedOption.getShortName:()Ljava/lang/String;
      40: aload_1
      41: invokevirtual #62                 // Method java/lang/String.equals:(Ljava/lang/Object;)Z
      44: ifeq          62
      47: aload_3
      48: invokevirtual #32                 // Method org/jboss/aesh/cl/internal/ProcessedOption.getActivator:()Lorg/jboss/aesh/cl/activation/OptionActivator;
      51: aload_0
      52: invokeinterface #63,  2           // InterfaceMethod org/jboss/aesh/cl/activation/OptionActivator.isActivated:(Lorg/jboss/aesh/cl/internal/ProcessedCommand;)Z
      57: ifeq          62
      60: aload_3
      61: areturn
      62: goto          10
      65: aconst_null
      66: areturn

  public org.jboss.aesh.cl.internal.ProcessedOption findOptionNoActivatorCheck(java.lang.String);
    Code:
       0: aload_0
       1: getfield      #11                 // Field options:Ljava/util/List;
       4: invokeinterface #37,  1           // InterfaceMethod java/util/List.iterator:()Ljava/util/Iterator;
       9: astore_2
      10: aload_2
      11: invokeinterface #38,  1           // InterfaceMethod java/util/Iterator.hasNext:()Z
      16: ifeq          52
      19: aload_2
      20: invokeinterface #39,  1           // InterfaceMethod java/util/Iterator.next:()Ljava/lang/Object;
      25: checkcast     #17                 // class org/jboss/aesh/cl/internal/ProcessedOption
      28: astore_3
      29: aload_3
      30: invokevirtual #18                 // Method org/jboss/aesh/cl/internal/ProcessedOption.getShortName:()Ljava/lang/String;
      33: ifnull        49
      36: aload_3
      37: invokevirtual #18                 // Method org/jboss/aesh/cl/internal/ProcessedOption.getShortName:()Ljava/lang/String;
      40: aload_1
      41: invokevirtual #62                 // Method java/lang/String.equals:(Ljava/lang/Object;)Z
      44: ifeq          49
      47: aload_3
      48: areturn
      49: goto          10
      52: aconst_null
      53: areturn

  public org.jboss.aesh.cl.internal.ProcessedOption findLongOption(java.lang.String);
    Code:
       0: aload_0
       1: getfield      #11                 // Field options:Ljava/util/List;
       4: invokeinterface #37,  1           // InterfaceMethod java/util/List.iterator:()Ljava/util/Iterator;
       9: astore_2
      10: aload_2
      11: invokeinterface #38,  1           // InterfaceMethod java/util/Iterator.hasNext:()Z
      16: ifeq          65
      19: aload_2
      20: invokeinterface #39,  1           // InterfaceMethod java/util/Iterator.next:()Ljava/lang/Object;
      25: checkcast     #17                 // class org/jboss/aesh/cl/internal/ProcessedOption
      28: astore_3
      29: aload_3
      30: invokevirtual #19                 // Method org/jboss/aesh/cl/internal/ProcessedOption.getName:()Ljava/lang/String;
      33: ifnull        62
      36: aload_3
      37: invokevirtual #19                 // Method org/jboss/aesh/cl/internal/ProcessedOption.getName:()Ljava/lang/String;
      40: aload_1
      41: invokevirtual #62                 // Method java/lang/String.equals:(Ljava/lang/Object;)Z
      44: ifeq          62
      47: aload_3
      48: invokevirtual #32                 // Method org/jboss/aesh/cl/internal/ProcessedOption.getActivator:()Lorg/jboss/aesh/cl/activation/OptionActivator;
      51: aload_0
      52: invokeinterface #63,  2           // InterfaceMethod org/jboss/aesh/cl/activation/OptionActivator.isActivated:(Lorg/jboss/aesh/cl/internal/ProcessedCommand;)Z
      57: ifeq          62
      60: aload_3
      61: areturn
      62: goto          10
      65: aconst_null
      66: areturn

  public org.jboss.aesh.cl.internal.ProcessedOption findLongOptionNoActivatorCheck(java.lang.String);
    Code:
       0: aload_0
       1: getfield      #11                 // Field options:Ljava/util/List;
       4: invokeinterface #37,  1           // InterfaceMethod java/util/List.iterator:()Ljava/util/Iterator;
       9: astore_2
      10: aload_2
      11: invokeinterface #38,  1           // InterfaceMethod java/util/Iterator.hasNext:()Z
      16: ifeq          52
      19: aload_2
      20: invokeinterface #39,  1           // InterfaceMethod java/util/Iterator.next:()Ljava/lang/Object;
      25: checkcast     #17                 // class org/jboss/aesh/cl/internal/ProcessedOption
      28: astore_3
      29: aload_3
      30: invokevirtual #19                 // Method org/jboss/aesh/cl/internal/ProcessedOption.getName:()Ljava/lang/String;
      33: ifnull        49
      36: aload_3
      37: invokevirtual #19                 // Method org/jboss/aesh/cl/internal/ProcessedOption.getName:()Ljava/lang/String;
      40: aload_1
      41: invokevirtual #62                 // Method java/lang/String.equals:(Ljava/lang/Object;)Z
      44: ifeq          49
      47: aload_3
      48: areturn
      49: goto          10
      52: aconst_null
      53: areturn

  public org.jboss.aesh.cl.internal.ProcessedOption startWithOption(java.lang.String);
    Code:
       0: aload_0
       1: getfield      #11                 // Field options:Ljava/util/List;
       4: invokeinterface #37,  1           // InterfaceMethod java/util/List.iterator:()Ljava/util/Iterator;
       9: astore_2
      10: aload_2
      11: invokeinterface #38,  1           // InterfaceMethod java/util/Iterator.hasNext:()Z
      16: ifeq          65
      19: aload_2
      20: invokeinterface #39,  1           // InterfaceMethod java/util/Iterator.next:()Ljava/lang/Object;
      25: checkcast     #17                 // class org/jboss/aesh/cl/internal/ProcessedOption
      28: astore_3
      29: aload_3
      30: invokevirtual #18                 // Method org/jboss/aesh/cl/internal/ProcessedOption.getShortName:()Ljava/lang/String;
      33: ifnull        62
      36: aload_1
      37: aload_3
      38: invokevirtual #18                 // Method org/jboss/aesh/cl/internal/ProcessedOption.getShortName:()Ljava/lang/String;
      41: invokevirtual #64                 // Method java/lang/String.startsWith:(Ljava/lang/String;)Z
      44: ifeq          62
      47: aload_3
      48: invokevirtual #32                 // Method org/jboss/aesh/cl/internal/ProcessedOption.getActivator:()Lorg/jboss/aesh/cl/activation/OptionActivator;
      51: aload_0
      52: invokeinterface #63,  2           // InterfaceMethod org/jboss/aesh/cl/activation/OptionActivator.isActivated:(Lorg/jboss/aesh/cl/internal/ProcessedCommand;)Z
      57: ifeq          62
      60: aload_3
      61: areturn
      62: goto          10
      65: aconst_null
      66: areturn

  public org.jboss.aesh.cl.internal.ProcessedOption startWithLongOption(java.lang.String);
    Code:
       0: aload_0
       1: getfield      #11                 // Field options:Ljava/util/List;
       4: invokeinterface #37,  1           // InterfaceMethod java/util/List.iterator:()Ljava/util/Iterator;
       9: astore_2
      10: aload_2
      11: invokeinterface #38,  1           // InterfaceMethod java/util/Iterator.hasNext:()Z
      16: ifeq          58
      19: aload_2
      20: invokeinterface #39,  1           // InterfaceMethod java/util/Iterator.next:()Ljava/lang/Object;
      25: checkcast     #17                 // class org/jboss/aesh/cl/internal/ProcessedOption
      28: astore_3
      29: aload_1
      30: aload_3
      31: invokevirtual #19                 // Method org/jboss/aesh/cl/internal/ProcessedOption.getName:()Ljava/lang/String;
      34: invokevirtual #64                 // Method java/lang/String.startsWith:(Ljava/lang/String;)Z
      37: ifeq          55
      40: aload_3
      41: invokevirtual #32                 // Method org/jboss/aesh/cl/internal/ProcessedOption.getActivator:()Lorg/jboss/aesh/cl/activation/OptionActivator;
      44: aload_0
      45: invokeinterface #63,  2           // InterfaceMethod org/jboss/aesh/cl/activation/OptionActivator.isActivated:(Lorg/jboss/aesh/cl/internal/ProcessedCommand;)Z
      50: ifeq          55
      53: aload_3
      54: areturn
      55: goto          10
      58: aconst_null
      59: areturn

  public void clear();
    Code:
       0: aload_0
       1: getfield      #11                 // Field options:Ljava/util/List;
       4: invokeinterface #37,  1           // InterfaceMethod java/util/List.iterator:()Ljava/util/Iterator;
       9: astore_1
      10: aload_1
      11: invokeinterface #38,  1           // InterfaceMethod java/util/Iterator.hasNext:()Z
      16: ifeq          36
      19: aload_1
      20: invokeinterface #39,  1           // InterfaceMethod java/util/Iterator.next:()Ljava/lang/Object;
      25: checkcast     #17                 // class org/jboss/aesh/cl/internal/ProcessedOption
      28: astore_2
      29: aload_2
      30: invokevirtual #65                 // Method org/jboss/aesh/cl/internal/ProcessedOption.clear:()V
      33: goto          10
      36: aload_0
      37: getfield      #8                  // Field argument:Lorg/jboss/aesh/cl/internal/ProcessedOption;
      40: ifnull        50
      43: aload_0
      44: getfield      #8                  // Field argument:Lorg/jboss/aesh/cl/internal/ProcessedOption;
      47: invokevirtual #65                 // Method org/jboss/aesh/cl/internal/ProcessedOption.clear:()V
      50: return

  public java.util.List<org.jboss.aesh.terminal.TerminalString> getOptionLongNamesWithDash();
    Code:
       0: new           #9                  // class java/util/ArrayList
       3: dup
       4: aload_0
       5: getfield      #11                 // Field options:Ljava/util/List;
       8: invokeinterface #66,  1           // InterfaceMethod java/util/List.size:()I
      13: invokespecial #67                 // Method java/util/ArrayList."<init>":(I)V
      16: astore_1
      17: aload_0
      18: getfield      #11                 // Field options:Ljava/util/List;
      21: invokeinterface #37,  1           // InterfaceMethod java/util/List.iterator:()Ljava/util/Iterator;
      26: astore_2
      27: aload_2
      28: invokeinterface #38,  1           // InterfaceMethod java/util/Iterator.hasNext:()Z
      33: ifeq          85
      36: aload_2
      37: invokeinterface #39,  1           // InterfaceMethod java/util/Iterator.next:()Ljava/lang/Object;
      42: checkcast     #17                 // class org/jboss/aesh/cl/internal/ProcessedOption
      45: astore_3
      46: aload_3
      47: invokevirtual #68                 // Method org/jboss/aesh/cl/internal/ProcessedOption.getValues:()Ljava/util/List;
      50: invokeinterface #66,  1           // InterfaceMethod java/util/List.size:()I
      55: ifne          82
      58: aload_3
      59: invokevirtual #32                 // Method org/jboss/aesh/cl/internal/ProcessedOption.getActivator:()Lorg/jboss/aesh/cl/activation/OptionActivator;
      62: aload_0
      63: invokeinterface #63,  2           // InterfaceMethod org/jboss/aesh/cl/activation/OptionActivator.isActivated:(Lorg/jboss/aesh/cl/internal/ProcessedCommand;)Z
      68: ifeq          82
      71: aload_1
      72: aload_3
      73: invokevirtual #69                 // Method org/jboss/aesh/cl/internal/ProcessedOption.getRenderedNameWithDashes:()Lorg/jboss/aesh/terminal/TerminalString;
      76: invokeinterface #36,  2           // InterfaceMethod java/util/List.add:(Ljava/lang/Object;)Z
      81: pop
      82: goto          27
      85: aload_1
      86: areturn

  public java.util.List<org.jboss.aesh.terminal.TerminalString> findPossibleLongNamesWitdDash(java.lang.String);
    Code:
       0: new           #9                  // class java/util/ArrayList
       3: dup
       4: aload_0
       5: getfield      #11                 // Field options:Ljava/util/List;
       8: invokeinterface #66,  1           // InterfaceMethod java/util/List.size:()I
      13: invokespecial #67                 // Method java/util/ArrayList."<init>":(I)V
      16: astore_2
      17: aload_0
      18: getfield      #11                 // Field options:Ljava/util/List;
      21: invokeinterface #37,  1           // InterfaceMethod java/util/List.iterator:()Ljava/util/Iterator;
      26: astore_3
      27: aload_3
      28: invokeinterface #38,  1           // InterfaceMethod java/util/Iterator.hasNext:()Z
      33: ifeq          142
      36: aload_3
      37: invokeinterface #39,  1           // InterfaceMethod java/util/Iterator.next:()Ljava/lang/Object;
      42: checkcast     #17                 // class org/jboss/aesh/cl/internal/ProcessedOption
      45: astore        4
      47: aload         4
      49: invokevirtual #18                 // Method org/jboss/aesh/cl/internal/ProcessedOption.getShortName:()Ljava/lang/String;
      52: ifnull        88
      55: aload         4
      57: invokevirtual #18                 // Method org/jboss/aesh/cl/internal/ProcessedOption.getShortName:()Ljava/lang/String;
      60: aload_1
      61: invokevirtual #62                 // Method java/lang/String.equals:(Ljava/lang/Object;)Z
      64: ifeq          88
      67: aload         4
      69: invokevirtual #70                 // Method org/jboss/aesh/cl/internal/ProcessedOption.isLongNameUsed:()Z
      72: ifne          88
      75: aload         4
      77: invokevirtual #68                 // Method org/jboss/aesh/cl/internal/ProcessedOption.getValues:()Ljava/util/List;
      80: invokeinterface #66,  1           // InterfaceMethod java/util/List.size:()I
      85: ifeq          113
      88: aload         4
      90: invokevirtual #19                 // Method org/jboss/aesh/cl/internal/ProcessedOption.getName:()Ljava/lang/String;
      93: aload_1
      94: invokevirtual #64                 // Method java/lang/String.startsWith:(Ljava/lang/String;)Z
      97: ifeq          139
     100: aload         4
     102: invokevirtual #68                 // Method org/jboss/aesh/cl/internal/ProcessedOption.getValues:()Ljava/util/List;
     105: invokeinterface #66,  1           // InterfaceMethod java/util/List.size:()I
     110: ifne          139
     113: aload         4
     115: invokevirtual #32                 // Method org/jboss/aesh/cl/internal/ProcessedOption.getActivator:()Lorg/jboss/aesh/cl/activation/OptionActivator;
     118: aload_0
     119: invokeinterface #63,  2           // InterfaceMethod org/jboss/aesh/cl/activation/OptionActivator.isActivated:(Lorg/jboss/aesh/cl/internal/ProcessedCommand;)Z
     124: ifeq          139
     127: aload_2
     128: aload         4
     130: invokevirtual #69                 // Method org/jboss/aesh/cl/internal/ProcessedOption.getRenderedNameWithDashes:()Lorg/jboss/aesh/terminal/TerminalString;
     133: invokeinterface #36,  2           // InterfaceMethod java/util/List.add:(Ljava/lang/Object;)Z
     138: pop
     139: goto          27
     142: aload_2
     143: areturn

  public java.lang.String printHelp();
    Code:
       0: iconst_0
       1: istore_1
       2: bipush        80
       4: istore_2
       5: aload_0
       6: invokevirtual #71                 // Method getOptions:()Ljava/util/List;
       9: invokeinterface #37,  1           // InterfaceMethod java/util/List.iterator:()Ljava/util/Iterator;
      14: astore_3
      15: aload_3
      16: invokeinterface #38,  1           // InterfaceMethod java/util/Iterator.hasNext:()Z
      21: ifeq          53
      24: aload_3
      25: invokeinterface #39,  1           // InterfaceMethod java/util/Iterator.next:()Ljava/lang/Object;
      30: checkcast     #17                 // class org/jboss/aesh/cl/internal/ProcessedOption
      33: astore        4
      35: aload         4
      37: invokevirtual #72                 // Method org/jboss/aesh/cl/internal/ProcessedOption.getFormattedLength:()I
      40: iload_1
      41: if_icmple     50
      44: aload         4
      46: invokevirtual #72                 // Method org/jboss/aesh/cl/internal/ProcessedOption.getFormattedLength:()I
      49: istore_1
      50: goto          15
      53: new           #48                 // class java/lang/StringBuilder
      56: dup
      57: invokespecial #49                 // Method java/lang/StringBuilder."<init>":()V
      60: astore_3
      61: aload_0
      62: invokevirtual #71                 // Method getOptions:()Ljava/util/List;
      65: invokeinterface #66,  1           // InterfaceMethod java/util/List.size:()I
      70: ifle          92
      73: aload_3
      74: invokestatic  #73                 // Method org/jboss/aesh/console/Config.getLineSeparator:()Ljava/lang/String;
      77: invokevirtual #51                 // Method java/lang/StringBuilder.append:(Ljava/lang/String;)Ljava/lang/StringBuilder;
      80: ldc           #74                 // String Options:
      82: invokevirtual #51                 // Method java/lang/StringBuilder.append:(Ljava/lang/String;)Ljava/lang/StringBuilder;
      85: invokestatic  #73                 // Method org/jboss/aesh/console/Config.getLineSeparator:()Ljava/lang/String;
      88: invokevirtual #51                 // Method java/lang/StringBuilder.append:(Ljava/lang/String;)Ljava/lang/StringBuilder;
      91: pop
      92: aload_0
      93: invokevirtual #71                 // Method getOptions:()Ljava/util/List;
      96: invokeinterface #37,  1           // InterfaceMethod java/util/List.iterator:()Ljava/util/Iterator;
     101: astore        4
     103: aload         4
     105: invokeinterface #38,  1           // InterfaceMethod java/util/Iterator.hasNext:()Z
     110: ifeq          149
     113: aload         4
     115: invokeinterface #39,  1           // InterfaceMethod java/util/Iterator.next:()Ljava/lang/Object;
     120: checkcast     #17                 // class org/jboss/aesh/cl/internal/ProcessedOption
     123: astore        5
     125: aload_3
     126: aload         5
     128: iconst_2
     129: iload_1
     130: iconst_4
     131: iadd
     132: iload_2
     133: invokevirtual #75                 // Method org/jboss/aesh/cl/internal/ProcessedOption.getFormattedOption:(III)Ljava/lang/String;
     136: invokevirtual #51                 // Method java/lang/StringBuilder.append:(Ljava/lang/String;)Ljava/lang/StringBuilder;
     139: invokestatic  #73                 // Method org/jboss/aesh/console/Config.getLineSeparator:()Ljava/lang/String;
     142: invokevirtual #51                 // Method java/lang/StringBuilder.append:(Ljava/lang/String;)Ljava/lang/StringBuilder;
     145: pop
     146: goto          103
     149: aload_0
     150: getfield      #8                  // Field argument:Lorg/jboss/aesh/cl/internal/ProcessedOption;
     153: ifnull        198
     156: aload_3
     157: invokestatic  #73                 // Method org/jboss/aesh/console/Config.getLineSeparator:()Ljava/lang/String;
     160: invokevirtual #51                 // Method java/lang/StringBuilder.append:(Ljava/lang/String;)Ljava/lang/StringBuilder;
     163: ldc           #76                 // String Arguments:
     165: invokevirtual #51                 // Method java/lang/StringBuilder.append:(Ljava/lang/String;)Ljava/lang/StringBuilder;
     168: invokestatic  #73                 // Method org/jboss/aesh/console/Config.getLineSeparator:()Ljava/lang/String;
     171: invokevirtual #51                 // Method java/lang/StringBuilder.append:(Ljava/lang/String;)Ljava/lang/StringBuilder;
     174: pop
     175: aload_3
     176: aload_0
     177: getfield      #8                  // Field argument:Lorg/jboss/aesh/cl/internal/ProcessedOption;
     180: iconst_2
     181: iload_1
     182: iconst_4
     183: iadd
     184: iload_2
     185: invokevirtual #75                 // Method org/jboss/aesh/cl/internal/ProcessedOption.getFormattedOption:(III)Ljava/lang/String;
     188: invokevirtual #51                 // Method java/lang/StringBuilder.append:(Ljava/lang/String;)Ljava/lang/StringBuilder;
     191: invokestatic  #73                 // Method org/jboss/aesh/console/Config.getLineSeparator:()Ljava/lang/String;
     194: invokevirtual #51                 // Method java/lang/StringBuilder.append:(Ljava/lang/String;)Ljava/lang/StringBuilder;
     197: pop
     198: new           #48                 // class java/lang/StringBuilder
     201: dup
     202: invokespecial #49                 // Method java/lang/StringBuilder."<init>":()V
     205: ldc           #77                 // String Usage:
     207: invokevirtual #51                 // Method java/lang/StringBuilder.append:(Ljava/lang/String;)Ljava/lang/StringBuilder;
     210: aload_0
     211: invokevirtual #78                 // Method getName:()Ljava/lang/String;
     214: invokevirtual #51                 // Method java/lang/StringBuilder.append:(Ljava/lang/String;)Ljava/lang/StringBuilder;
     217: ldc           #79                 // String
     219: invokevirtual #51                 // Method java/lang/StringBuilder.append:(Ljava/lang/String;)Ljava/lang/StringBuilder;
     222: aload_0
     223: invokevirtual #80                 // Method getDescription:()Ljava/lang/String;
     226: invokevirtual #51                 // Method java/lang/StringBuilder.append:(Ljava/lang/String;)Ljava/lang/StringBuilder;
     229: invokestatic  #73                 // Method org/jboss/aesh/console/Config.getLineSeparator:()Ljava/lang/String;
     232: invokevirtual #51                 // Method java/lang/StringBuilder.append:(Ljava/lang/String;)Ljava/lang/StringBuilder;
     235: aload_3
     236: invokevirtual #54                 // Method java/lang/StringBuilder.toString:()Ljava/lang/String;
     239: invokevirtual #51                 // Method java/lang/StringBuilder.append:(Ljava/lang/String;)Ljava/lang/StringBuilder;
     242: invokevirtual #54                 // Method java/lang/StringBuilder.toString:()Ljava/lang/String;
     245: areturn

  public java.lang.String toString();
    Code:
       0: new           #48                 // class java/lang/StringBuilder
       3: dup
       4: invokespecial #49                 // Method java/lang/StringBuilder."<init>":()V
       7: ldc           #81                 // String ProcessedCommand{name=\'
       9: invokevirtual #51                 // Method java/lang/StringBuilder.append:(Ljava/lang/String;)Ljava/lang/StringBuilder;
      12: aload_0
      13: getfield      #40                 // Field name:Ljava/lang/String;
      16: invokevirtual #51                 // Method java/lang/StringBuilder.append:(Ljava/lang/String;)Ljava/lang/StringBuilder;
      19: bipush        39
      21: invokevirtual #59                 // Method java/lang/StringBuilder.append:(C)Ljava/lang/StringBuilder;
      24: ldc           #82                 // String , description=\'
      26: invokevirtual #51                 // Method java/lang/StringBuilder.append:(Ljava/lang/String;)Ljava/lang/StringBuilder;
      29: aload_0
      30: getfield      #41                 // Field description:Ljava/lang/String;
      33: invokevirtual #51                 // Method java/lang/StringBuilder.append:(Ljava/lang/String;)Ljava/lang/StringBuilder;
      36: bipush        39
      38: invokevirtual #59                 // Method java/lang/StringBuilder.append:(C)Ljava/lang/StringBuilder;
      41: ldc           #83                 // String , options=
      43: invokevirtual #51                 // Method java/lang/StringBuilder.append:(Ljava/lang/String;)Ljava/lang/StringBuilder;
      46: aload_0
      47: getfield      #11                 // Field options:Ljava/util/List;
      50: invokevirtual #84                 // Method java/lang/StringBuilder.append:(Ljava/lang/Object;)Ljava/lang/StringBuilder;
      53: bipush        125
      55: invokevirtual #59                 // Method java/lang/StringBuilder.append:(C)Ljava/lang/StringBuilder;
      58: invokevirtual #54                 // Method java/lang/StringBuilder.toString:()Ljava/lang/String;
      61: areturn

  public boolean equals(java.lang.Object);
    Code:
       0: aload_0
       1: aload_1
       2: if_acmpne     7
       5: iconst_1
       6: ireturn
       7: aload_1
       8: instanceof    #85                 // class org/jboss/aesh/cl/internal/ProcessedCommand
      11: ifne          16
      14: iconst_0
      15: ireturn
      16: aload_1
      17: checkcast     #85                 // class org/jboss/aesh/cl/internal/ProcessedCommand
      20: astore_2
      21: aload_0
      22: getfield      #40                 // Field name:Ljava/lang/String;
      25: aload_2
      26: getfield      #40                 // Field name:Ljava/lang/String;
      29: invokevirtual #62                 // Method java/lang/String.equals:(Ljava/lang/Object;)Z
      32: ifne          37
      35: iconst_0
      36: ireturn
      37: aload_0
      38: getfield      #41                 // Field description:Ljava/lang/String;
      41: ifnull        61
      44: aload_0
      45: getfield      #41                 // Field description:Ljava/lang/String;
      48: aload_2
      49: getfield      #41                 // Field description:Ljava/lang/String;
      52: invokevirtual #62                 // Method java/lang/String.equals:(Ljava/lang/Object;)Z
      55: ifne          70
      58: goto          68
      61: aload_2
      62: getfield      #41                 // Field description:Ljava/lang/String;
      65: ifnull        70
      68: iconst_0
      69: ireturn
      70: iconst_1
      71: ireturn

  public int hashCode();
    Code:
       0: aload_0
       1: getfield      #40                 // Field name:Ljava/lang/String;
       4: invokevirtual #86                 // Method java/lang/String.hashCode:()I
       7: istore_1
       8: bipush        31
      10: iload_1
      11: imul
      12: aload_0
      13: getfield      #41                 // Field description:Ljava/lang/String;
      16: ifnull        29
      19: aload_0
      20: getfield      #41                 // Field description:Ljava/lang/String;
      23: invokevirtual #86                 // Method java/lang/String.hashCode:()I
      26: goto          30
      29: iconst_0
      30: iadd
      31: istore_1
      32: iload_1
      33: ireturn

  public boolean hasLongOption(java.lang.String);
    Code:
       0: aload_0
       1: invokevirtual #71                 // Method getOptions:()Ljava/util/List;
       4: invokeinterface #37,  1           // InterfaceMethod java/util/List.iterator:()Ljava/util/Iterator;
       9: astore_2
      10: aload_2
      11: invokeinterface #38,  1           // InterfaceMethod java/util/Iterator.hasNext:()Z
      16: ifeq          45
      19: aload_2
      20: invokeinterface #39,  1           // InterfaceMethod java/util/Iterator.next:()Ljava/lang/Object;
      25: checkcast     #17                 // class org/jboss/aesh/cl/internal/ProcessedOption
      28: astore_3
      29: aload_3
      30: invokevirtual #19                 // Method org/jboss/aesh/cl/internal/ProcessedOption.getName:()Ljava/lang/String;
      33: aload_1
      34: invokevirtual #62                 // Method java/lang/String.equals:(Ljava/lang/Object;)Z
      37: ifeq          42
      40: iconst_1
      41: ireturn
      42: goto          10
      45: iconst_0
      46: ireturn

  public boolean hasOptions();
    Code:
       0: aload_0
       1: invokevirtual #71                 // Method getOptions:()Ljava/util/List;
       4: ifnull        23
       7: aload_0
       8: invokevirtual #71                 // Method getOptions:()Ljava/util/List;
      11: invokeinterface #66,  1           // InterfaceMethod java/util/List.size:()I
      16: ifle          23
      19: iconst_1
      20: goto          24
      23: iconst_0
      24: ireturn

  public boolean hasUniqueLongOption(java.lang.String);
    Code:
       0: aload_0
       1: aload_1
       2: invokevirtual #87                 // Method hasLongOption:(Ljava/lang/String;)Z
       5: ifeq          66
       8: aload_0
       9: invokevirtual #71                 // Method getOptions:()Ljava/util/List;
      12: invokeinterface #37,  1           // InterfaceMethod java/util/List.iterator:()Ljava/util/Iterator;
      17: astore_2
      18: aload_2
      19: invokeinterface #38,  1           // InterfaceMethod java/util/Iterator.hasNext:()Z
      24: ifeq          64
      27: aload_2
      28: invokeinterface #39,  1           // InterfaceMethod java/util/Iterator.next:()Ljava/lang/Object;
      33: checkcast     #17                 // class org/jboss/aesh/cl/internal/ProcessedOption
      36: astore_3
      37: aload_3
      38: invokevirtual #19                 // Method org/jboss/aesh/cl/internal/ProcessedOption.getName:()Ljava/lang/String;
      41: aload_1
      42: invokevirtual #64                 // Method java/lang/String.startsWith:(Ljava/lang/String;)Z
      45: ifeq          61
      48: aload_3
      49: invokevirtual #19                 // Method org/jboss/aesh/cl/internal/ProcessedOption.getName:()Ljava/lang/String;
      52: aload_1
      53: invokevirtual #62                 // Method java/lang/String.equals:(Ljava/lang/Object;)Z
      56: ifne          61
      59: iconst_0
      60: ireturn
      61: goto          18
      64: iconst_1
      65: ireturn
      66: iconst_0
      67: ireturn

  public void updateInvocationProviders(org.jboss.aesh.console.InvocationProviders);
    Code:
       0: aload_0
       1: getfield      #11                 // Field options:Ljava/util/List;
       4: invokeinterface #37,  1           // InterfaceMethod java/util/List.iterator:()Ljava/util/Iterator;
       9: astore_2
      10: aload_2
      11: invokeinterface #38,  1           // InterfaceMethod java/util/Iterator.hasNext:()Z
      16: ifeq          37
      19: aload_2
      20: invokeinterface #39,  1           // InterfaceMethod java/util/Iterator.next:()Ljava/lang/Object;
      25: checkcast     #17                 // class org/jboss/aesh/cl/internal/ProcessedOption
      28: astore_3
      29: aload_3
      30: aload_1
      31: invokevirtual #88                 // Method org/jboss/aesh/cl/internal/ProcessedOption.updateInvocationProviders:(Lorg/jboss/aesh/console/InvocationProviders;)V
      34: goto          10
      37: return

  public void updateSettings(org.jboss.aesh.console.settings.Settings);
    Code:
       0: aload_0
       1: getfield      #11                 // Field options:Ljava/util/List;
       4: invokeinterface #37,  1           // InterfaceMethod java/util/List.iterator:()Ljava/util/Iterator;
       9: astore_2
      10: aload_2
      11: invokeinterface #38,  1           // InterfaceMethod java/util/Iterator.hasNext:()Z
      16: ifeq          42
      19: aload_2
      20: invokeinterface #39,  1           // InterfaceMethod java/util/Iterator.next:()Ljava/lang/Object;
      25: checkcast     #17                 // class org/jboss/aesh/cl/internal/ProcessedOption
      28: astore_3
      29: aload_3
      30: aload_1
      31: invokeinterface #89,  1           // InterfaceMethod org/jboss/aesh/console/settings/Settings.isAnsiConsole:()Z
      36: invokevirtual #90                 // Method org/jboss/aesh/cl/internal/ProcessedOption.updateAnsiMode:(Z)V
      39: goto          10
      42: return

  public boolean containsArgumentWithDefaultValues();
    Code:
       0: aload_0
       1: invokevirtual #91                 // Method getArgument:()Lorg/jboss/aesh/cl/internal/ProcessedOption;
       4: ifnull        21
       7: aload_0
       8: invokevirtual #91                 // Method getArgument:()Lorg/jboss/aesh/cl/internal/ProcessedOption;
      11: invokevirtual #92                 // Method org/jboss/aesh/cl/internal/ProcessedOption.hasDefaultValue:()Z
      14: ifeq          21
      17: iconst_1
      18: goto          22
      21: iconst_0
      22: ireturn
}
