Compiled from "AbstractConfiguration.java"
class org.apache.commons.configuration2.AbstractConfiguration$1 implements org.apache.commons.configuration2.event.EventListener<org.apache.commons.configuration2.event.ConfigurationErrorEvent> {
  final org.apache.commons.configuration2.AbstractConfiguration this$0;

  org.apache.commons.configuration2.AbstractConfiguration$1(org.apache.commons.configuration2.AbstractConfiguration);
    Code:
       0: aload_0
       1: aload_1
       2: putfield      #1                  // Field this$0:Lorg/apache/commons/configuration2/AbstractConfiguration;
       5: aload_0
       6: invokespecial #2                  // Method java/lang/Object."<init>":()V
       9: return

  public void onEvent(org.apache.commons.configuration2.event.ConfigurationErrorEvent);
    Code:
       0: aload_0
       1: getfield      #1                  // Field this$0:Lorg/apache/commons/configuration2/AbstractConfiguration;
       4: invokevirtual #3                  // Method org/apache/commons/configuration2/AbstractConfiguration.getLogger:()Lorg/apache/commons/configuration2/io/ConfigurationLogger;
       7: ldc           #4                  // String Internal error
       9: aload_1
      10: invokevirtual #5                  // Method org/apache/commons/configuration2/event/ConfigurationErrorEvent.getCause:()Ljava/lang/Throwable;
      13: invokevirtual #6                  // Method org/apache/commons/configuration2/io/ConfigurationLogger.warn:(Ljava/lang/String;Ljava/lang/Throwable;)V
      16: return

  public void onEvent(org.apache.commons.configuration2.event.Event);
    Code:
       0: aload_0
       1: aload_1
       2: checkcast     #7                  // class org/apache/commons/configuration2/event/ConfigurationErrorEvent
       5: invokevirtual #8                  // Method onEvent:(Lorg/apache/commons/configuration2/event/ConfigurationErrorEvent;)V
       8: return
}
