Compiled from "XMLConfiguration.java"
public class org.apache.commons.configuration2.XMLConfiguration extends org.apache.commons.configuration2.BaseHierarchicalConfiguration implements org.apache.commons.configuration2.FileBasedConfiguration,org.apache.commons.configuration2.io.FileLocatorAware,org.apache.commons.configuration2.io.InputStreamSupport {
  private static final java.lang.String DEFAULT_ROOT_NAME;

  private static final java.lang.String ATTR_SPACE;

  private static final java.lang.String ATTR_SPACE_INTERNAL;

  private static final java.lang.String VALUE_PRESERVE;

  private static final java.lang.String JAXP_SCHEMA_LANGUAGE;

  private static final java.lang.String W3C_XML_SCHEMA;

  private java.lang.String rootElementName;

  private java.lang.String publicID;

  private java.lang.String systemID;

  private javax.xml.parsers.DocumentBuilder documentBuilder;

  private boolean validating;

  private boolean schemaValidation;

  private org.xml.sax.EntityResolver entityResolver;

  private org.apache.commons.configuration2.io.FileLocator locator;

  public org.apache.commons.configuration2.XMLConfiguration();
    Code:
       0: aload_0
       1: invokespecial #1                  // Method org/apache/commons/configuration2/BaseHierarchicalConfiguration."<init>":()V
       4: aload_0
       5: new           #2                  // class org/apache/commons/configuration2/resolver/DefaultEntityResolver
       8: dup
       9: invokespecial #3                  // Method org/apache/commons/configuration2/resolver/DefaultEntityResolver."<init>":()V
      12: putfield      #4                  // Field entityResolver:Lorg/xml/sax/EntityResolver;
      15: aload_0
      16: new           #5                  // class org/apache/commons/configuration2/io/ConfigurationLogger
      19: dup
      20: ldc           #6                  // class org/apache/commons/configuration2/XMLConfiguration
      22: invokespecial #7                  // Method org/apache/commons/configuration2/io/ConfigurationLogger."<init>":(Ljava/lang/Class;)V
      25: invokevirtual #8                  // Method initLogger:(Lorg/apache/commons/configuration2/io/ConfigurationLogger;)V
      28: return

  public org.apache.commons.configuration2.XMLConfiguration(org.apache.commons.configuration2.HierarchicalConfiguration<org.apache.commons.configuration2.tree.ImmutableNode>);
    Code:
       0: aload_0
       1: aload_1
       2: invokespecial #9                  // Method org/apache/commons/configuration2/BaseHierarchicalConfiguration."<init>":(Lorg/apache/commons/configuration2/HierarchicalConfiguration;)V
       5: aload_0
       6: new           #2                  // class org/apache/commons/configuration2/resolver/DefaultEntityResolver
       9: dup
      10: invokespecial #3                  // Method org/apache/commons/configuration2/resolver/DefaultEntityResolver."<init>":()V
      13: putfield      #4                  // Field entityResolver:Lorg/xml/sax/EntityResolver;
      16: aload_0
      17: aload_1
      18: ifnull        30
      21: aload_1
      22: invokeinterface #10,  1           // InterfaceMethod org/apache/commons/configuration2/HierarchicalConfiguration.getRootElementName:()Ljava/lang/String;
      27: goto          31
      30: aconst_null
      31: putfield      #11                 // Field rootElementName:Ljava/lang/String;
      34: aload_0
      35: new           #5                  // class org/apache/commons/configuration2/io/ConfigurationLogger
      38: dup
      39: ldc           #6                  // class org/apache/commons/configuration2/XMLConfiguration
      41: invokespecial #7                  // Method org/apache/commons/configuration2/io/ConfigurationLogger."<init>":(Ljava/lang/Class;)V
      44: invokevirtual #8                  // Method initLogger:(Lorg/apache/commons/configuration2/io/ConfigurationLogger;)V
      47: return

  protected java.lang.String getRootElementNameInternal();
    Code:
       0: aload_0
       1: invokevirtual #12                 // Method getDocument:()Lorg/w3c/dom/Document;
       4: astore_1
       5: aload_1
       6: ifnonnull     26
       9: aload_0
      10: getfield      #11                 // Field rootElementName:Ljava/lang/String;
      13: ifnonnull     21
      16: ldc           #13                 // String configuration
      18: goto          25
      21: aload_0
      22: getfield      #11                 // Field rootElementName:Ljava/lang/String;
      25: areturn
      26: aload_1
      27: invokeinterface #14,  1           // InterfaceMethod org/w3c/dom/Document.getDocumentElement:()Lorg/w3c/dom/Element;
      32: invokeinterface #15,  1           // InterfaceMethod org/w3c/dom/Element.getNodeName:()Ljava/lang/String;
      37: areturn

  public void setRootElementName(java.lang.String);
    Code:
       0: aload_0
       1: iconst_1
       2: invokevirtual #16                 // Method beginRead:(Z)V
       5: aload_0
       6: invokevirtual #12                 // Method getDocument:()Lorg/w3c/dom/Document;
       9: ifnull        22
      12: new           #17                 // class java/lang/UnsupportedOperationException
      15: dup
      16: ldc           #18                 // String The name of the root element cannot be changed when loaded from an XML document!
      18: invokespecial #19                 // Method java/lang/UnsupportedOperationException."<init>":(Ljava/lang/String;)V
      21: athrow
      22: aload_0
      23: aload_1
      24: putfield      #11                 // Field rootElementName:Ljava/lang/String;
      27: aload_0
      28: invokevirtual #20                 // Method endRead:()V
      31: goto          41
      34: astore_2
      35: aload_0
      36: invokevirtual #20                 // Method endRead:()V
      39: aload_2
      40: athrow
      41: return
    Exception table:
       from    to  target type
           5    27    34   any

  public javax.xml.parsers.DocumentBuilder getDocumentBuilder();
    Code:
       0: aload_0
       1: getfield      #21                 // Field documentBuilder:Ljavax/xml/parsers/DocumentBuilder;
       4: areturn

  public void setDocumentBuilder(javax.xml.parsers.DocumentBuilder);
    Code:
       0: aload_0
       1: aload_1
       2: putfield      #21                 // Field documentBuilder:Ljavax/xml/parsers/DocumentBuilder;
       5: return

  public java.lang.String getPublicID();
    Code:
       0: aload_0
       1: iconst_0
       2: invokevirtual #16                 // Method beginRead:(Z)V
       5: aload_0
       6: getfield      #22                 // Field publicID:Ljava/lang/String;
       9: astore_1
      10: aload_0
      11: invokevirtual #20                 // Method endRead:()V
      14: aload_1
      15: areturn
      16: astore_2
      17: aload_0
      18: invokevirtual #20                 // Method endRead:()V
      21: aload_2
      22: athrow
    Exception table:
       from    to  target type
           5    10    16   any

  public void setPublicID(java.lang.String);
    Code:
       0: aload_0
       1: iconst_0
       2: invokevirtual #23                 // Method beginWrite:(Z)V
       5: aload_0
       6: aload_1
       7: putfield      #22                 // Field publicID:Ljava/lang/String;
      10: aload_0
      11: invokevirtual #24                 // Method endWrite:()V
      14: goto          24
      17: astore_2
      18: aload_0
      19: invokevirtual #24                 // Method endWrite:()V
      22: aload_2
      23: athrow
      24: return
    Exception table:
       from    to  target type
           5    10    17   any

  public java.lang.String getSystemID();
    Code:
       0: aload_0
       1: iconst_0
       2: invokevirtual #16                 // Method beginRead:(Z)V
       5: aload_0
       6: getfield      #25                 // Field systemID:Ljava/lang/String;
       9: astore_1
      10: aload_0
      11: invokevirtual #20                 // Method endRead:()V
      14: aload_1
      15: areturn
      16: astore_2
      17: aload_0
      18: invokevirtual #20                 // Method endRead:()V
      21: aload_2
      22: athrow
    Exception table:
       from    to  target type
           5    10    16   any

  public void setSystemID(java.lang.String);
    Code:
       0: aload_0
       1: iconst_0
       2: invokevirtual #23                 // Method beginWrite:(Z)V
       5: aload_0
       6: aload_1
       7: putfield      #25                 // Field systemID:Ljava/lang/String;
      10: aload_0
      11: invokevirtual #24                 // Method endWrite:()V
      14: goto          24
      17: astore_2
      18: aload_0
      19: invokevirtual #24                 // Method endWrite:()V
      22: aload_2
      23: athrow
      24: return
    Exception table:
       from    to  target type
           5    10    17   any

  public boolean isValidating();
    Code:
       0: aload_0
       1: getfield      #26                 // Field validating:Z
       4: ireturn

  public void setValidating(boolean);
    Code:
       0: aload_0
       1: getfield      #27                 // Field schemaValidation:Z
       4: ifne          12
       7: aload_0
       8: iload_1
       9: putfield      #26                 // Field validating:Z
      12: return

  public boolean isSchemaValidation();
    Code:
       0: aload_0
       1: getfield      #27                 // Field schemaValidation:Z
       4: ireturn

  public void setSchemaValidation(boolean);
    Code:
       0: aload_0
       1: iload_1
       2: putfield      #27                 // Field schemaValidation:Z
       5: iload_1
       6: ifeq          14
       9: aload_0
      10: iconst_1
      11: putfield      #26                 // Field validating:Z
      14: return

  public void setEntityResolver(org.xml.sax.EntityResolver);
    Code:
       0: aload_0
       1: aload_1
       2: putfield      #4                  // Field entityResolver:Lorg/xml/sax/EntityResolver;
       5: return

  public org.xml.sax.EntityResolver getEntityResolver();
    Code:
       0: aload_0
       1: getfield      #4                  // Field entityResolver:Lorg/xml/sax/EntityResolver;
       4: areturn

  public org.w3c.dom.Document getDocument();
    Code:
       0: aload_0
       1: invokespecial #28                 // Method getDocumentHelper:()Lorg/apache/commons/configuration2/XMLDocumentHelper;
       4: astore_1
       5: aload_1
       6: ifnull        16
       9: aload_1
      10: invokevirtual #29                 // Method org/apache/commons/configuration2/XMLDocumentHelper.getDocument:()Lorg/w3c/dom/Document;
      13: goto          17
      16: aconst_null
      17: areturn

  private org.apache.commons.configuration2.XMLDocumentHelper getDocumentHelper();
    Code:
       0: aload_0
       1: invokespecial #30                 // Method getReferenceHandler:()Lorg/apache/commons/configuration2/tree/ReferenceNodeHandler;
       4: astore_1
       5: aload_1
       6: aload_1
       7: invokeinterface #31,  1           // InterfaceMethod org/apache/commons/configuration2/tree/ReferenceNodeHandler.getRootNode:()Ljava/lang/Object;
      12: checkcast     #32                 // class org/apache/commons/configuration2/tree/ImmutableNode
      15: invokeinterface #33,  2           // InterfaceMethod org/apache/commons/configuration2/tree/ReferenceNodeHandler.getReference:(Lorg/apache/commons/configuration2/tree/ImmutableNode;)Ljava/lang/Object;
      20: checkcast     #34                 // class org/apache/commons/configuration2/XMLDocumentHelper
      23: areturn

  private org.apache.commons.configuration2.tree.ReferenceNodeHandler getReferenceHandler();
    Code:
       0: aload_0
       1: invokevirtual #35                 // Method getSubConfigurationParentModel:()Lorg/apache/commons/configuration2/tree/InMemoryNodeModel;
       4: invokevirtual #36                 // Method org/apache/commons/configuration2/tree/InMemoryNodeModel.getReferenceNodeHandler:()Lorg/apache/commons/configuration2/tree/ReferenceNodeHandler;
       7: areturn

  private void initProperties(org.apache.commons.configuration2.XMLDocumentHelper, boolean);
    Code:
       0: aload_1
       1: invokevirtual #29                 // Method org/apache/commons/configuration2/XMLDocumentHelper.getDocument:()Lorg/w3c/dom/Document;
       4: astore_3
       5: aload_0
       6: aload_1
       7: invokevirtual #37                 // Method org/apache/commons/configuration2/XMLDocumentHelper.getSourcePublicID:()Ljava/lang/String;
      10: invokevirtual #38                 // Method setPublicID:(Ljava/lang/String;)V
      13: aload_0
      14: aload_1
      15: invokevirtual #39                 // Method org/apache/commons/configuration2/XMLDocumentHelper.getSourceSystemID:()Ljava/lang/String;
      18: invokevirtual #40                 // Method setSystemID:(Ljava/lang/String;)V
      21: new           #41                 // class org/apache/commons/configuration2/tree/ImmutableNode$Builder
      24: dup
      25: invokespecial #42                 // Method org/apache/commons/configuration2/tree/ImmutableNode$Builder."<init>":()V
      28: astore        4
      30: new           #43                 // class org/apache/commons/lang3/mutable/MutableObject
      33: dup
      34: invokespecial #44                 // Method org/apache/commons/lang3/mutable/MutableObject."<init>":()V
      37: astore        5
      39: iload_2
      40: ifeq          53
      43: new           #45                 // class java/util/HashMap
      46: dup
      47: invokespecial #46                 // Method java/util/HashMap."<init>":()V
      50: goto          54
      53: aconst_null
      54: astore        6
      56: aload_0
      57: aload         4
      59: aload         5
      61: aload_3
      62: invokeinterface #14,  1           // InterfaceMethod org/w3c/dom/Document.getDocumentElement:()Lorg/w3c/dom/Element;
      67: aload         6
      69: iconst_1
      70: iconst_0
      71: invokespecial #47                 // Method constructHierarchy:(Lorg/apache/commons/configuration2/tree/ImmutableNode$Builder;Lorg/apache/commons/lang3/mutable/MutableObject;Lorg/w3c/dom/Element;Ljava/util/Map;ZI)Ljava/util/Map;
      74: astore        7
      76: aload         7
      78: ldc           #48                 // String config-xml:space
      80: invokeinterface #49,  2           // InterfaceMethod java/util/Map.remove:(Ljava/lang/Object;)Ljava/lang/Object;
      85: pop
      86: aload         4
      88: aload         5
      90: invokevirtual #50                 // Method org/apache/commons/lang3/mutable/MutableObject.getValue:()Ljava/lang/Object;
      93: invokevirtual #51                 // Method org/apache/commons/configuration2/tree/ImmutableNode$Builder.value:(Ljava/lang/Object;)Lorg/apache/commons/configuration2/tree/ImmutableNode$Builder;
      96: aload         7
      98: invokevirtual #52                 // Method org/apache/commons/configuration2/tree/ImmutableNode$Builder.addAttributes:(Ljava/util/Map;)Lorg/apache/commons/configuration2/tree/ImmutableNode$Builder;
     101: invokevirtual #53                 // Method org/apache/commons/configuration2/tree/ImmutableNode$Builder.create:()Lorg/apache/commons/configuration2/tree/ImmutableNode;
     104: astore        8
     106: aload_0
     107: invokevirtual #35                 // Method getSubConfigurationParentModel:()Lorg/apache/commons/configuration2/tree/InMemoryNodeModel;
     110: aload         8
     112: aload_3
     113: invokeinterface #14,  1           // InterfaceMethod org/w3c/dom/Document.getDocumentElement:()Lorg/w3c/dom/Element;
     118: invokeinterface #54,  1           // InterfaceMethod org/w3c/dom/Element.getTagName:()Ljava/lang/String;
     123: aload         6
     125: iload_2
     126: ifeq          133
     129: aload_1
     130: goto          134
     133: aconst_null
     134: aload_0
     135: invokevirtual #55                 // Method org/apache/commons/configuration2/tree/InMemoryNodeModel.mergeRoot:(Lorg/apache/commons/configuration2/tree/ImmutableNode;Ljava/lang/String;Ljava/util/Map;Ljava/lang/Object;Lorg/apache/commons/configuration2/tree/NodeKeyResolver;)V
     138: return

  private java.util.Map<java.lang.String, java.lang.String> constructHierarchy(org.apache.commons.configuration2.tree.ImmutableNode$Builder, org.apache.commons.lang3.mutable.MutableObject<java.lang.String>, org.w3c.dom.Element, java.util.Map<org.apache.commons.configuration2.tree.ImmutableNode, java.lang.Object>, boolean, int);
    Code:
       0: aload_3
       1: iload         5
       3: invokestatic  #56                 // Method shouldTrim:(Lorg/w3c/dom/Element;Z)Z
       6: istore        7
       8: aload_3
       9: invokestatic  #57                 // Method processAttributes:(Lorg/w3c/dom/Element;)Ljava/util/Map;
      12: astore        8
      14: aload         8
      16: ldc           #48                 // String config-xml:space
      18: iload         7
      20: invokestatic  #58                 // Method java/lang/String.valueOf:(Z)Ljava/lang/String;
      23: invokeinterface #59,  3           // InterfaceMethod java/util/Map.put:(Ljava/lang/Object;Ljava/lang/Object;)Ljava/lang/Object;
      28: pop
      29: new           #60                 // class java/lang/StringBuilder
      32: dup
      33: invokespecial #61                 // Method java/lang/StringBuilder."<init>":()V
      36: astore        9
      38: aload_3
      39: invokeinterface #62,  1           // InterfaceMethod org/w3c/dom/Element.getChildNodes:()Lorg/w3c/dom/NodeList;
      44: astore        10
      46: iconst_0
      47: istore        11
      49: iconst_0
      50: istore        12
      52: iload         12
      54: aload         10
      56: invokeinterface #63,  1           // InterfaceMethod org/w3c/dom/NodeList.getLength:()I
      61: if_icmpge     263
      64: aload         10
      66: iload         12
      68: invokeinterface #64,  2           // InterfaceMethod org/w3c/dom/NodeList.item:(I)Lorg/w3c/dom/Node;
      73: astore        13
      75: aload         13
      77: instanceof    #65                 // class org/w3c/dom/Element
      80: ifeq          229
      83: aload         13
      85: checkcast     #65                 // class org/w3c/dom/Element
      88: astore        14
      90: new           #41                 // class org/apache/commons/configuration2/tree/ImmutableNode$Builder
      93: dup
      94: invokespecial #42                 // Method org/apache/commons/configuration2/tree/ImmutableNode$Builder."<init>":()V
      97: astore        15
      99: aload         15
     101: aload         14
     103: invokeinterface #54,  1           // InterfaceMethod org/w3c/dom/Element.getTagName:()Ljava/lang/String;
     108: invokevirtual #66                 // Method org/apache/commons/configuration2/tree/ImmutableNode$Builder.name:(Ljava/lang/String;)Lorg/apache/commons/configuration2/tree/ImmutableNode$Builder;
     111: pop
     112: new           #43                 // class org/apache/commons/lang3/mutable/MutableObject
     115: dup
     116: invokespecial #44                 // Method org/apache/commons/lang3/mutable/MutableObject."<init>":()V
     119: astore        16
     121: aload_0
     122: aload         15
     124: aload         16
     126: aload         14
     128: aload         4
     130: iload         7
     132: iload         6
     134: iconst_1
     135: iadd
     136: invokespecial #47                 // Method constructHierarchy:(Lorg/apache/commons/configuration2/tree/ImmutableNode$Builder;Lorg/apache/commons/lang3/mutable/MutableObject;Lorg/w3c/dom/Element;Ljava/util/Map;ZI)Ljava/util/Map;
     139: astore        17
     141: aload         17
     143: ldc           #48                 // String config-xml:space
     145: invokeinterface #49,  2           // InterfaceMethod java/util/Map.remove:(Ljava/lang/Object;)Ljava/lang/Object;
     150: checkcast     #67                 // class java/lang/String
     153: invokestatic  #68                 // Method java/lang/Boolean.valueOf:(Ljava/lang/String;)Ljava/lang/Boolean;
     156: astore        18
     158: aload         15
     160: aload         17
     162: invokevirtual #52                 // Method org/apache/commons/configuration2/tree/ImmutableNode$Builder.addAttributes:(Ljava/util/Map;)Lorg/apache/commons/configuration2/tree/ImmutableNode$Builder;
     165: pop
     166: aload_0
     167: aload_1
     168: aload         15
     170: aload         14
     172: aload         16
     174: invokevirtual #50                 // Method org/apache/commons/lang3/mutable/MutableObject.getValue:()Ljava/lang/Object;
     177: checkcast     #67                 // class java/lang/String
     180: aload         18
     182: invokevirtual #69                 // Method java/lang/Boolean.booleanValue:()Z
     185: aload         17
     187: aload         4
     189: invokespecial #70                 // Method createChildNodeWithValue:(Lorg/apache/commons/configuration2/tree/ImmutableNode$Builder;Lorg/apache/commons/configuration2/tree/ImmutableNode$Builder;Lorg/w3c/dom/Element;Ljava/lang/String;ZLjava/util/Map;Ljava/util/Map;)Lorg/apache/commons/configuration2/tree/ImmutableNode;
     192: astore        19
     194: aload         4
     196: ifnull        223
     199: aload         4
     201: aload         19
     203: invokeinterface #71,  2           // InterfaceMethod java/util/Map.containsKey:(Ljava/lang/Object;)Z
     208: ifne          223
     211: aload         4
     213: aload         19
     215: aload         14
     217: invokeinterface #59,  3           // InterfaceMethod java/util/Map.put:(Ljava/lang/Object;Ljava/lang/Object;)Ljava/lang/Object;
     222: pop
     223: iconst_1
     224: istore        11
     226: goto          257
     229: aload         13
     231: instanceof    #72                 // class org/w3c/dom/Text
     234: ifeq          257
     237: aload         13
     239: checkcast     #72                 // class org/w3c/dom/Text
     242: astore        14
     244: aload         9
     246: aload         14
     248: invokeinterface #73,  1           // InterfaceMethod org/w3c/dom/Text.getData:()Ljava/lang/String;
     253: invokevirtual #74                 // Method java/lang/StringBuilder.append:(Ljava/lang/String;)Ljava/lang/StringBuilder;
     256: pop
     257: iinc          12, 1
     260: goto          52
     263: iload         11
     265: ifne          279
     268: aload         8
     270: invokeinterface #75,  1           // InterfaceMethod java/util/Map.size:()I
     275: iconst_1
     276: if_icmple     283
     279: iconst_1
     280: goto          284
     283: iconst_0
     284: istore        12
     286: aload         9
     288: invokevirtual #76                 // Method java/lang/StringBuilder.toString:()Ljava/lang/String;
     291: iload         12
     293: iload         7
     295: invokestatic  #77                 // Method determineValue:(Ljava/lang/String;ZZ)Ljava/lang/String;
     298: astore        13
     300: aload         13
     302: invokevirtual #78                 // Method java/lang/String.length:()I
     305: ifgt          318
     308: iload         12
     310: ifne          324
     313: iload         6
     315: ifeq          324
     318: aload_2
     319: aload         13
     321: invokevirtual #79                 // Method org/apache/commons/lang3/mutable/MutableObject.setValue:(Ljava/lang/Object;)V
     324: aload         8
     326: areturn

  private static java.lang.String determineValue(java.lang.String, boolean, boolean);
    Code:
       0: iload_2
       1: ifne          15
       4: aload_0
       5: invokestatic  #80                 // Method org/apache/commons/lang3/StringUtils.isBlank:(Ljava/lang/CharSequence;)Z
       8: ifeq          19
      11: iload_1
      12: ifeq          19
      15: iconst_1
      16: goto          20
      19: iconst_0
      20: istore_3
      21: iload_3
      22: ifeq          32
      25: aload_0
      26: invokevirtual #81                 // Method java/lang/String.trim:()Ljava/lang/String;
      29: goto          33
      32: aload_0
      33: areturn

  private static java.util.Map<java.lang.String, java.lang.String> processAttributes(org.w3c.dom.Element);
    Code:
       0: aload_0
       1: invokeinterface #82,  1           // InterfaceMethod org/w3c/dom/Element.getAttributes:()Lorg/w3c/dom/NamedNodeMap;
       6: astore_1
       7: new           #45                 // class java/util/HashMap
      10: dup
      11: invokespecial #46                 // Method java/util/HashMap."<init>":()V
      14: astore_2
      15: iconst_0
      16: istore_3
      17: iload_3
      18: aload_1
      19: invokeinterface #83,  1           // InterfaceMethod org/w3c/dom/NamedNodeMap.getLength:()I
      24: if_icmpge     78
      27: aload_1
      28: iload_3
      29: invokeinterface #84,  2           // InterfaceMethod org/w3c/dom/NamedNodeMap.item:(I)Lorg/w3c/dom/Node;
      34: astore        4
      36: aload         4
      38: instanceof    #85                 // class org/w3c/dom/Attr
      41: ifeq          72
      44: aload         4
      46: checkcast     #85                 // class org/w3c/dom/Attr
      49: astore        5
      51: aload_2
      52: aload         5
      54: invokeinterface #86,  1           // InterfaceMethod org/w3c/dom/Attr.getName:()Ljava/lang/String;
      59: aload         5
      61: invokeinterface #87,  1           // InterfaceMethod org/w3c/dom/Attr.getValue:()Ljava/lang/String;
      66: invokeinterface #59,  3           // InterfaceMethod java/util/Map.put:(Ljava/lang/Object;Ljava/lang/Object;)Ljava/lang/Object;
      71: pop
      72: iinc          3, 1
      75: goto          17
      78: aload_2
      79: areturn

  private org.apache.commons.configuration2.tree.ImmutableNode createChildNodeWithValue(org.apache.commons.configuration2.tree.ImmutableNode$Builder, org.apache.commons.configuration2.tree.ImmutableNode$Builder, org.w3c.dom.Element, java.lang.String, boolean, java.util.Map<java.lang.String, java.lang.String>, java.util.Map<org.apache.commons.configuration2.tree.ImmutableNode, java.lang.Object>);
    Code:
       0: aload         4
       2: ifnull        23
       5: aload_0
       6: invokevirtual #88                 // Method getListDelimiterHandler:()Lorg/apache/commons/configuration2/convert/ListDelimiterHandler;
       9: aload         4
      11: iload         5
      13: invokeinterface #89,  3           // InterfaceMethod org/apache/commons/configuration2/convert/ListDelimiterHandler.split:(Ljava/lang/String;Z)Ljava/util/Collection;
      18: astore        9
      20: goto          28
      23: invokestatic  #90                 // Method java/util/Collections.emptyList:()Ljava/util/List;
      26: astore        9
      28: aload         9
      30: invokeinterface #91,  1           // InterfaceMethod java/util/Collection.size:()I
      35: iconst_1
      36: if_icmple     175
      39: aload_3
      40: invokestatic  #92                 // Method isSingleElementList:(Lorg/w3c/dom/Element;)Z
      43: ifeq          51
      46: aload         7
      48: goto          52
      51: aconst_null
      52: astore        10
      54: aload         9
      56: invokeinterface #93,  1           // InterfaceMethod java/util/Collection.iterator:()Ljava/util/Iterator;
      61: astore        11
      63: aload_2
      64: aload         11
      66: invokeinterface #94,  1           // InterfaceMethod java/util/Iterator.next:()Ljava/lang/Object;
      71: invokevirtual #51                 // Method org/apache/commons/configuration2/tree/ImmutableNode$Builder.value:(Ljava/lang/Object;)Lorg/apache/commons/configuration2/tree/ImmutableNode$Builder;
      74: pop
      75: aload_2
      76: invokevirtual #53                 // Method org/apache/commons/configuration2/tree/ImmutableNode$Builder.create:()Lorg/apache/commons/configuration2/tree/ImmutableNode;
      79: astore        8
      81: aload_1
      82: aload         8
      84: invokevirtual #95                 // Method org/apache/commons/configuration2/tree/ImmutableNode$Builder.addChild:(Lorg/apache/commons/configuration2/tree/ImmutableNode;)Lorg/apache/commons/configuration2/tree/ImmutableNode$Builder;
      87: pop
      88: aload         10
      90: aload         8
      92: aload_3
      93: invokestatic  #96                 // Method org/apache/commons/configuration2/XMLListReference.assignListReference:(Ljava/util/Map;Lorg/apache/commons/configuration2/tree/ImmutableNode;Lorg/w3c/dom/Element;)V
      96: aload         11
      98: invokeinterface #97,  1           // InterfaceMethod java/util/Iterator.hasNext:()Z
     103: ifeq          172
     106: new           #41                 // class org/apache/commons/configuration2/tree/ImmutableNode$Builder
     109: dup
     110: invokespecial #42                 // Method org/apache/commons/configuration2/tree/ImmutableNode$Builder."<init>":()V
     113: astore        12
     115: aload         12
     117: aload         8
     119: invokevirtual #98                 // Method org/apache/commons/configuration2/tree/ImmutableNode.getNodeName:()Ljava/lang/String;
     122: invokevirtual #66                 // Method org/apache/commons/configuration2/tree/ImmutableNode$Builder.name:(Ljava/lang/String;)Lorg/apache/commons/configuration2/tree/ImmutableNode$Builder;
     125: pop
     126: aload         12
     128: aload         11
     130: invokeinterface #94,  1           // InterfaceMethod java/util/Iterator.next:()Ljava/lang/Object;
     135: invokevirtual #51                 // Method org/apache/commons/configuration2/tree/ImmutableNode$Builder.value:(Ljava/lang/Object;)Lorg/apache/commons/configuration2/tree/ImmutableNode$Builder;
     138: pop
     139: aload         12
     141: aload         6
     143: invokevirtual #52                 // Method org/apache/commons/configuration2/tree/ImmutableNode$Builder.addAttributes:(Ljava/util/Map;)Lorg/apache/commons/configuration2/tree/ImmutableNode$Builder;
     146: pop
     147: aload         12
     149: invokevirtual #53                 // Method org/apache/commons/configuration2/tree/ImmutableNode$Builder.create:()Lorg/apache/commons/configuration2/tree/ImmutableNode;
     152: astore        13
     154: aload_1
     155: aload         13
     157: invokevirtual #95                 // Method org/apache/commons/configuration2/tree/ImmutableNode$Builder.addChild:(Lorg/apache/commons/configuration2/tree/ImmutableNode;)Lorg/apache/commons/configuration2/tree/ImmutableNode$Builder;
     160: pop
     161: aload         10
     163: aload         13
     165: aconst_null
     166: invokestatic  #96                 // Method org/apache/commons/configuration2/XMLListReference.assignListReference:(Ljava/util/Map;Lorg/apache/commons/configuration2/tree/ImmutableNode;Lorg/w3c/dom/Element;)V
     169: goto          96
     172: goto          232
     175: aload         9
     177: invokeinterface #91,  1           // InterfaceMethod java/util/Collection.size:()I
     182: iconst_1
     183: if_icmpne     219
     186: aload_2
     187: aload         9
     189: invokeinterface #93,  1           // InterfaceMethod java/util/Collection.iterator:()Ljava/util/Iterator;
     194: invokeinterface #94,  1           // InterfaceMethod java/util/Iterator.next:()Ljava/lang/Object;
     199: invokevirtual #51                 // Method org/apache/commons/configuration2/tree/ImmutableNode$Builder.value:(Ljava/lang/Object;)Lorg/apache/commons/configuration2/tree/ImmutableNode$Builder;
     202: pop
     203: aload_2
     204: invokevirtual #53                 // Method org/apache/commons/configuration2/tree/ImmutableNode$Builder.create:()Lorg/apache/commons/configuration2/tree/ImmutableNode;
     207: astore        8
     209: aload_1
     210: aload         8
     212: invokevirtual #95                 // Method org/apache/commons/configuration2/tree/ImmutableNode$Builder.addChild:(Lorg/apache/commons/configuration2/tree/ImmutableNode;)Lorg/apache/commons/configuration2/tree/ImmutableNode$Builder;
     215: pop
     216: goto          232
     219: aload_2
     220: invokevirtual #53                 // Method org/apache/commons/configuration2/tree/ImmutableNode$Builder.create:()Lorg/apache/commons/configuration2/tree/ImmutableNode;
     223: astore        8
     225: aload_1
     226: aload         8
     228: invokevirtual #95                 // Method org/apache/commons/configuration2/tree/ImmutableNode$Builder.addChild:(Lorg/apache/commons/configuration2/tree/ImmutableNode;)Lorg/apache/commons/configuration2/tree/ImmutableNode$Builder;
     231: pop
     232: aload         8
     234: areturn

  private static boolean isSingleElementList(org.w3c.dom.Element);
    Code:
       0: aload_0
       1: invokeinterface #99,  1           // InterfaceMethod org/w3c/dom/Element.getParentNode:()Lorg/w3c/dom/Node;
       6: astore_1
       7: aload_1
       8: aload_0
       9: invokeinterface #54,  1           // InterfaceMethod org/w3c/dom/Element.getTagName:()Ljava/lang/String;
      14: invokestatic  #100                // Method countChildElements:(Lorg/w3c/dom/Node;Ljava/lang/String;)I
      17: iconst_1
      18: if_icmpne     25
      21: iconst_1
      22: goto          26
      25: iconst_0
      26: ireturn

  private static int countChildElements(org.w3c.dom.Node, java.lang.String);
    Code:
       0: aload_0
       1: invokeinterface #101,  1          // InterfaceMethod org/w3c/dom/Node.getChildNodes:()Lorg/w3c/dom/NodeList;
       6: astore_2
       7: iconst_0
       8: istore_3
       9: iconst_0
      10: istore        4
      12: iload         4
      14: aload_2
      15: invokeinterface #63,  1           // InterfaceMethod org/w3c/dom/NodeList.getLength:()I
      20: if_icmpge     67
      23: aload_2
      24: iload         4
      26: invokeinterface #64,  2           // InterfaceMethod org/w3c/dom/NodeList.item:(I)Lorg/w3c/dom/Node;
      31: astore        5
      33: aload         5
      35: instanceof    #65                 // class org/w3c/dom/Element
      38: ifeq          61
      41: aload_1
      42: aload         5
      44: checkcast     #65                 // class org/w3c/dom/Element
      47: invokeinterface #54,  1           // InterfaceMethod org/w3c/dom/Element.getTagName:()Ljava/lang/String;
      52: invokevirtual #102                // Method java/lang/String.equals:(Ljava/lang/Object;)Z
      55: ifeq          61
      58: iinc          3, 1
      61: iinc          4, 1
      64: goto          12
      67: iload_3
      68: ireturn

  private static boolean shouldTrim(org.w3c.dom.Element, boolean);
    Code:
       0: aload_0
       1: ldc           #103                // String xml:space
       3: invokeinterface #104,  2          // InterfaceMethod org/w3c/dom/Element.getAttributeNode:(Ljava/lang/String;)Lorg/w3c/dom/Attr;
       8: astore_2
       9: aload_2
      10: ifnonnull     15
      13: iload_1
      14: ireturn
      15: ldc           #105                // String preserve
      17: aload_2
      18: invokeinterface #87,  1           // InterfaceMethod org/w3c/dom/Attr.getValue:()Ljava/lang/String;
      23: invokevirtual #102                // Method java/lang/String.equals:(Ljava/lang/Object;)Z
      26: ifne          33
      29: iconst_1
      30: goto          34
      33: iconst_0
      34: ireturn

  protected javax.xml.parsers.DocumentBuilder createDocumentBuilder() throws javax.xml.parsers.ParserConfigurationException;
    Code:
       0: aload_0
       1: invokevirtual #106                // Method getDocumentBuilder:()Ljavax/xml/parsers/DocumentBuilder;
       4: ifnull        12
       7: aload_0
       8: invokevirtual #106                // Method getDocumentBuilder:()Ljavax/xml/parsers/DocumentBuilder;
      11: areturn
      12: invokestatic  #107                // Method javax/xml/parsers/DocumentBuilderFactory.newInstance:()Ljavax/xml/parsers/DocumentBuilderFactory;
      15: astore_1
      16: aload_0
      17: invokevirtual #108                // Method isValidating:()Z
      20: ifeq          48
      23: aload_1
      24: iconst_1
      25: invokevirtual #109                // Method javax/xml/parsers/DocumentBuilderFactory.setValidating:(Z)V
      28: aload_0
      29: invokevirtual #110                // Method isSchemaValidation:()Z
      32: ifeq          48
      35: aload_1
      36: iconst_1
      37: invokevirtual #111                // Method javax/xml/parsers/DocumentBuilderFactory.setNamespaceAware:(Z)V
      40: aload_1
      41: ldc           #112                // String http://java.sun.com/xml/jaxp/properties/schemaLanguage
      43: ldc           #113                // String http://www.w3.org/2001/XMLSchema
      45: invokevirtual #114                // Method javax/xml/parsers/DocumentBuilderFactory.setAttribute:(Ljava/lang/String;Ljava/lang/Object;)V
      48: aload_1
      49: invokevirtual #115                // Method javax/xml/parsers/DocumentBuilderFactory.newDocumentBuilder:()Ljavax/xml/parsers/DocumentBuilder;
      52: astore_2
      53: aload_2
      54: aload_0
      55: getfield      #4                  // Field entityResolver:Lorg/xml/sax/EntityResolver;
      58: invokevirtual #116                // Method javax/xml/parsers/DocumentBuilder.setEntityResolver:(Lorg/xml/sax/EntityResolver;)V
      61: aload_0
      62: invokevirtual #108                // Method isValidating:()Z
      65: ifeq          80
      68: aload_2
      69: new           #117                // class org/apache/commons/configuration2/XMLConfiguration$1
      72: dup
      73: aload_0
      74: invokespecial #118                // Method org/apache/commons/configuration2/XMLConfiguration$1."<init>":(Lorg/apache/commons/configuration2/XMLConfiguration;)V
      77: invokevirtual #119                // Method javax/xml/parsers/DocumentBuilder.setErrorHandler:(Lorg/xml/sax/ErrorHandler;)V
      80: aload_2
      81: areturn

  protected javax.xml.transform.Transformer createTransformer() throws org.apache.commons.configuration2.ex.ConfigurationException;
    Code:
       0: invokestatic  #120                // Method org/apache/commons/configuration2/XMLDocumentHelper.createTransformer:()Ljavax/xml/transform/Transformer;
       3: astore_1
       4: aload_1
       5: ldc           #122                // String indent
       7: ldc           #123                // String yes
       9: invokevirtual #124                // Method javax/xml/transform/Transformer.setOutputProperty:(Ljava/lang/String;Ljava/lang/String;)V
      12: aload_0
      13: getfield      #125                // Field locator:Lorg/apache/commons/configuration2/io/FileLocator;
      16: invokevirtual #126                // Method org/apache/commons/configuration2/io/FileLocator.getEncoding:()Ljava/lang/String;
      19: ifnull        35
      22: aload_1
      23: ldc           #127                // String encoding
      25: aload_0
      26: getfield      #125                // Field locator:Lorg/apache/commons/configuration2/io/FileLocator;
      29: invokevirtual #126                // Method org/apache/commons/configuration2/io/FileLocator.getEncoding:()Ljava/lang/String;
      32: invokevirtual #124                // Method javax/xml/transform/Transformer.setOutputProperty:(Ljava/lang/String;Ljava/lang/String;)V
      35: aload_0
      36: getfield      #22                 // Field publicID:Ljava/lang/String;
      39: ifnull        52
      42: aload_1
      43: ldc           #128                // String doctype-public
      45: aload_0
      46: getfield      #22                 // Field publicID:Ljava/lang/String;
      49: invokevirtual #124                // Method javax/xml/transform/Transformer.setOutputProperty:(Ljava/lang/String;Ljava/lang/String;)V
      52: aload_0
      53: getfield      #25                 // Field systemID:Ljava/lang/String;
      56: ifnull        69
      59: aload_1
      60: ldc           #129                // String doctype-system
      62: aload_0
      63: getfield      #25                 // Field systemID:Ljava/lang/String;
      66: invokevirtual #124                // Method javax/xml/transform/Transformer.setOutputProperty:(Ljava/lang/String;Ljava/lang/String;)V
      69: aload_1
      70: areturn

  private org.w3c.dom.Document createDocument() throws org.apache.commons.configuration2.ex.ConfigurationException;
    Code:
       0: aload_0
       1: invokespecial #30                 // Method getReferenceHandler:()Lorg/apache/commons/configuration2/tree/ReferenceNodeHandler;
       4: astore_1
       5: aload_1
       6: aload_1
       7: invokeinterface #31,  1           // InterfaceMethod org/apache/commons/configuration2/tree/ReferenceNodeHandler.getRootNode:()Ljava/lang/Object;
      12: checkcast     #32                 // class org/apache/commons/configuration2/tree/ImmutableNode
      15: invokeinterface #33,  2           // InterfaceMethod org/apache/commons/configuration2/tree/ReferenceNodeHandler.getReference:(Lorg/apache/commons/configuration2/tree/ImmutableNode;)Ljava/lang/Object;
      20: checkcast     #34                 // class org/apache/commons/configuration2/XMLDocumentHelper
      23: astore_2
      24: aload_2
      25: ifnonnull     38
      28: aload_0
      29: invokevirtual #130                // Method getRootElementName:()Ljava/lang/String;
      32: invokestatic  #131                // Method org/apache/commons/configuration2/XMLDocumentHelper.forNewDocument:(Ljava/lang/String;)Lorg/apache/commons/configuration2/XMLDocumentHelper;
      35: goto          42
      38: aload_2
      39: invokevirtual #132                // Method org/apache/commons/configuration2/XMLDocumentHelper.createCopy:()Lorg/apache/commons/configuration2/XMLDocumentHelper;
      42: astore_3
      43: new           #133                // class org/apache/commons/configuration2/XMLConfiguration$XMLBuilderVisitor
      46: dup
      47: aload_3
      48: aload_0
      49: invokevirtual #88                 // Method getListDelimiterHandler:()Lorg/apache/commons/configuration2/convert/ListDelimiterHandler;
      52: invokespecial #134                // Method org/apache/commons/configuration2/XMLConfiguration$XMLBuilderVisitor."<init>":(Lorg/apache/commons/configuration2/XMLDocumentHelper;Lorg/apache/commons/configuration2/convert/ListDelimiterHandler;)V
      55: astore        4
      57: aload         4
      59: aload_1
      60: invokevirtual #135                // Method org/apache/commons/configuration2/XMLConfiguration$XMLBuilderVisitor.handleRemovedNodes:(Lorg/apache/commons/configuration2/tree/ReferenceNodeHandler;)V
      63: aload         4
      65: aload_1
      66: invokevirtual #136                // Method org/apache/commons/configuration2/XMLConfiguration$XMLBuilderVisitor.processDocument:(Lorg/apache/commons/configuration2/tree/ReferenceNodeHandler;)V
      69: aload_0
      70: aload_3
      71: invokevirtual #29                 // Method org/apache/commons/configuration2/XMLDocumentHelper.getDocument:()Lorg/w3c/dom/Document;
      74: aload_0
      75: invokevirtual #137                // Method getModel:()Lorg/apache/commons/configuration2/tree/NodeModel;
      78: invokeinterface #138,  1          // InterfaceMethod org/apache/commons/configuration2/tree/NodeModel.getNodeHandler:()Lorg/apache/commons/configuration2/tree/NodeHandler;
      83: invokeinterface #139,  1          // InterfaceMethod org/apache/commons/configuration2/tree/NodeHandler.getRootNode:()Ljava/lang/Object;
      88: checkcast     #32                 // class org/apache/commons/configuration2/tree/ImmutableNode
      91: invokevirtual #140                // Method org/apache/commons/configuration2/tree/ImmutableNode.getValue:()Ljava/lang/Object;
      94: invokespecial #141                // Method initRootElementText:(Lorg/w3c/dom/Document;Ljava/lang/Object;)V
      97: aload_3
      98: invokevirtual #29                 // Method org/apache/commons/configuration2/XMLDocumentHelper.getDocument:()Lorg/w3c/dom/Document;
     101: areturn

  private void initRootElementText(org.w3c.dom.Document, java.lang.Object);
    Code:
       0: aload_1
       1: invokeinterface #14,  1           // InterfaceMethod org/w3c/dom/Document.getDocumentElement:()Lorg/w3c/dom/Element;
       6: astore_3
       7: aload_3
       8: invokeinterface #62,  1           // InterfaceMethod org/w3c/dom/Element.getChildNodes:()Lorg/w3c/dom/NodeList;
      13: astore        4
      15: iconst_0
      16: istore        5
      18: iload         5
      20: aload         4
      22: invokeinterface #63,  1           // InterfaceMethod org/w3c/dom/NodeList.getLength:()I
      27: if_icmpge     67
      30: aload         4
      32: iload         5
      34: invokeinterface #64,  2           // InterfaceMethod org/w3c/dom/NodeList.item:(I)Lorg/w3c/dom/Node;
      39: astore        6
      41: aload         6
      43: invokeinterface #142,  1          // InterfaceMethod org/w3c/dom/Node.getNodeType:()S
      48: iconst_3
      49: if_icmpne     61
      52: aload_3
      53: aload         6
      55: invokeinterface #144,  2          // InterfaceMethod org/w3c/dom/Element.removeChild:(Lorg/w3c/dom/Node;)Lorg/w3c/dom/Node;
      60: pop
      61: iinc          5, 1
      64: goto          18
      67: aload_2
      68: ifnull        88
      71: aload_3
      72: aload_1
      73: aload_2
      74: invokestatic  #145                // Method java/lang/String.valueOf:(Ljava/lang/Object;)Ljava/lang/String;
      77: invokeinterface #146,  2          // InterfaceMethod org/w3c/dom/Document.createTextNode:(Ljava/lang/String;)Lorg/w3c/dom/Text;
      82: invokeinterface #147,  2          // InterfaceMethod org/w3c/dom/Element.appendChild:(Lorg/w3c/dom/Node;)Lorg/w3c/dom/Node;
      87: pop
      88: return

  public void initFileLocator(org.apache.commons.configuration2.io.FileLocator);
    Code:
       0: aload_0
       1: aload_1
       2: putfield      #125                // Field locator:Lorg/apache/commons/configuration2/io/FileLocator;
       5: return

  public void read(java.io.Reader) throws org.apache.commons.configuration2.ex.ConfigurationException, java.io.IOException;
    Code:
       0: aload_0
       1: new           #148                // class org/xml/sax/InputSource
       4: dup
       5: aload_1
       6: invokespecial #149                // Method org/xml/sax/InputSource."<init>":(Ljava/io/Reader;)V
       9: invokespecial #150                // Method load:(Lorg/xml/sax/InputSource;)V
      12: return

  public void read(java.io.InputStream) throws org.apache.commons.configuration2.ex.ConfigurationException, java.io.IOException;
    Code:
       0: aload_0
       1: new           #148                // class org/xml/sax/InputSource
       4: dup
       5: aload_1
       6: invokespecial #151                // Method org/xml/sax/InputSource."<init>":(Ljava/io/InputStream;)V
       9: invokespecial #150                // Method load:(Lorg/xml/sax/InputSource;)V
      12: return

  private void load(org.xml.sax.InputSource) throws org.apache.commons.configuration2.ex.ConfigurationException;
    Code:
       0: aload_0
       1: getfield      #125                // Field locator:Lorg/apache/commons/configuration2/io/FileLocator;
       4: ifnonnull     17
       7: new           #152                // class org/apache/commons/configuration2/ex/ConfigurationException
      10: dup
      11: ldc           #153                // String Load operation not properly initialized! Do not call read(InputStream) directly, but use a FileHandler to load a configuration.
      13: invokespecial #154                // Method org/apache/commons/configuration2/ex/ConfigurationException."<init>":(Ljava/lang/String;)V
      16: athrow
      17: aload_0
      18: getfield      #125                // Field locator:Lorg/apache/commons/configuration2/io/FileLocator;
      21: invokevirtual #155                // Method org/apache/commons/configuration2/io/FileLocator.getSourceURL:()Ljava/net/URL;
      24: astore_2
      25: aload_2
      26: ifnull        37
      29: aload_1
      30: aload_2
      31: invokevirtual #156                // Method java/net/URL.toString:()Ljava/lang/String;
      34: invokevirtual #157                // Method org/xml/sax/InputSource.setSystemId:(Ljava/lang/String;)V
      37: aload_0
      38: invokevirtual #158                // Method createDocumentBuilder:()Ljavax/xml/parsers/DocumentBuilder;
      41: astore_3
      42: aload_3
      43: aload_1
      44: invokevirtual #159                // Method javax/xml/parsers/DocumentBuilder.parse:(Lorg/xml/sax/InputSource;)Lorg/w3c/dom/Document;
      47: astore        4
      49: aload_0
      50: invokevirtual #12                 // Method getDocument:()Lorg/w3c/dom/Document;
      53: astore        5
      55: aload_0
      56: aload         4
      58: invokestatic  #160                // Method org/apache/commons/configuration2/XMLDocumentHelper.forSourceDocument:(Lorg/w3c/dom/Document;)Lorg/apache/commons/configuration2/XMLDocumentHelper;
      61: aload         5
      63: ifnonnull     70
      66: iconst_1
      67: goto          71
      70: iconst_0
      71: invokespecial #161                // Method initProperties:(Lorg/apache/commons/configuration2/XMLDocumentHelper;Z)V
      74: goto          147
      77: astore_2
      78: new           #152                // class org/apache/commons/configuration2/ex/ConfigurationException
      81: dup
      82: new           #60                 // class java/lang/StringBuilder
      85: dup
      86: invokespecial #61                 // Method java/lang/StringBuilder."<init>":()V
      89: ldc           #163                // String Error parsing
      91: invokevirtual #74                 // Method java/lang/StringBuilder.append:(Ljava/lang/String;)Ljava/lang/StringBuilder;
      94: aload_1
      95: invokevirtual #164                // Method org/xml/sax/InputSource.getSystemId:()Ljava/lang/String;
      98: invokevirtual #74                 // Method java/lang/StringBuilder.append:(Ljava/lang/String;)Ljava/lang/StringBuilder;
     101: invokevirtual #76                 // Method java/lang/StringBuilder.toString:()Ljava/lang/String;
     104: aload_2
     105: invokespecial #165                // Method org/apache/commons/configuration2/ex/ConfigurationException."<init>":(Ljava/lang/String;Ljava/lang/Throwable;)V
     108: athrow
     109: astore_2
     110: aload_0
     111: invokevirtual #167                // Method getLogger:()Lorg/apache/commons/configuration2/io/ConfigurationLogger;
     114: new           #60                 // class java/lang/StringBuilder
     117: dup
     118: invokespecial #61                 // Method java/lang/StringBuilder."<init>":()V
     121: ldc           #168                // String Unable to load the configuration:
     123: invokevirtual #74                 // Method java/lang/StringBuilder.append:(Ljava/lang/String;)Ljava/lang/StringBuilder;
     126: aload_2
     127: invokevirtual #169                // Method java/lang/StringBuilder.append:(Ljava/lang/Object;)Ljava/lang/StringBuilder;
     130: invokevirtual #76                 // Method java/lang/StringBuilder.toString:()Ljava/lang/String;
     133: invokevirtual #170                // Method org/apache/commons/configuration2/io/ConfigurationLogger.debug:(Ljava/lang/String;)V
     136: new           #152                // class org/apache/commons/configuration2/ex/ConfigurationException
     139: dup
     140: ldc           #171                // String Unable to load the configuration
     142: aload_2
     143: invokespecial #165                // Method org/apache/commons/configuration2/ex/ConfigurationException."<init>":(Ljava/lang/String;Ljava/lang/Throwable;)V
     146: athrow
     147: return
    Exception table:
       from    to  target type
          17    74    77   Class org/xml/sax/SAXParseException
          17    74   109   Class java/lang/Exception

  public void write(java.io.Writer) throws org.apache.commons.configuration2.ex.ConfigurationException, java.io.IOException;
    Code:
       0: aload_0
       1: invokevirtual #172                // Method createTransformer:()Ljavax/xml/transform/Transformer;
       4: astore_2
       5: new           #173                // class javax/xml/transform/dom/DOMSource
       8: dup
       9: aload_0
      10: invokespecial #174                // Method createDocument:()Lorg/w3c/dom/Document;
      13: invokespecial #175                // Method javax/xml/transform/dom/DOMSource."<init>":(Lorg/w3c/dom/Node;)V
      16: astore_3
      17: new           #176                // class javax/xml/transform/stream/StreamResult
      20: dup
      21: aload_1
      22: invokespecial #177                // Method javax/xml/transform/stream/StreamResult."<init>":(Ljava/io/Writer;)V
      25: astore        4
      27: aload_2
      28: aload_3
      29: aload         4
      31: invokestatic  #178                // Method org/apache/commons/configuration2/XMLDocumentHelper.transform:(Ljavax/xml/transform/Transformer;Ljavax/xml/transform/Source;Ljavax/xml/transform/Result;)V
      34: return

  public void validate() throws org.apache.commons.configuration2.ex.ConfigurationException;
    Code:
       0: aload_0
       1: iconst_0
       2: invokevirtual #23                 // Method beginWrite:(Z)V
       5: aload_0
       6: invokevirtual #172                // Method createTransformer:()Ljavax/xml/transform/Transformer;
       9: astore_1
      10: new           #173                // class javax/xml/transform/dom/DOMSource
      13: dup
      14: aload_0
      15: invokespecial #174                // Method createDocument:()Lorg/w3c/dom/Document;
      18: invokespecial #175                // Method javax/xml/transform/dom/DOMSource."<init>":(Lorg/w3c/dom/Node;)V
      21: astore_2
      22: new           #179                // class java/io/StringWriter
      25: dup
      26: invokespecial #180                // Method java/io/StringWriter."<init>":()V
      29: astore_3
      30: new           #176                // class javax/xml/transform/stream/StreamResult
      33: dup
      34: aload_3
      35: invokespecial #177                // Method javax/xml/transform/stream/StreamResult."<init>":(Ljava/io/Writer;)V
      38: astore        4
      40: aload_1
      41: aload_2
      42: aload         4
      44: invokestatic  #178                // Method org/apache/commons/configuration2/XMLDocumentHelper.transform:(Ljavax/xml/transform/Transformer;Ljavax/xml/transform/Source;Ljavax/xml/transform/Result;)V
      47: new           #181                // class java/io/StringReader
      50: dup
      51: aload_3
      52: invokevirtual #182                // Method java/io/StringWriter.getBuffer:()Ljava/lang/StringBuffer;
      55: invokevirtual #183                // Method java/lang/StringBuffer.toString:()Ljava/lang/String;
      58: invokespecial #184                // Method java/io/StringReader."<init>":(Ljava/lang/String;)V
      61: astore        5
      63: aload_0
      64: invokevirtual #158                // Method createDocumentBuilder:()Ljavax/xml/parsers/DocumentBuilder;
      67: astore        6
      69: aload         6
      71: new           #148                // class org/xml/sax/InputSource
      74: dup
      75: aload         5
      77: invokespecial #149                // Method org/xml/sax/InputSource."<init>":(Ljava/io/Reader;)V
      80: invokevirtual #159                // Method javax/xml/parsers/DocumentBuilder.parse:(Lorg/xml/sax/InputSource;)Lorg/w3c/dom/Document;
      83: pop
      84: aload_0
      85: invokevirtual #24                 // Method endWrite:()V
      88: goto          136
      91: astore_1
      92: new           #152                // class org/apache/commons/configuration2/ex/ConfigurationException
      95: dup
      96: ldc           #186                // String Validation failed
      98: aload_1
      99: invokespecial #165                // Method org/apache/commons/configuration2/ex/ConfigurationException."<init>":(Ljava/lang/String;Ljava/lang/Throwable;)V
     102: athrow
     103: astore_1
     104: new           #152                // class org/apache/commons/configuration2/ex/ConfigurationException
     107: dup
     108: ldc           #186                // String Validation failed
     110: aload_1
     111: invokespecial #165                // Method org/apache/commons/configuration2/ex/ConfigurationException."<init>":(Ljava/lang/String;Ljava/lang/Throwable;)V
     114: athrow
     115: astore_1
     116: new           #152                // class org/apache/commons/configuration2/ex/ConfigurationException
     119: dup
     120: ldc           #186                // String Validation failed
     122: aload_1
     123: invokespecial #165                // Method org/apache/commons/configuration2/ex/ConfigurationException."<init>":(Ljava/lang/String;Ljava/lang/Throwable;)V
     126: athrow
     127: astore        7
     129: aload_0
     130: invokevirtual #24                 // Method endWrite:()V
     133: aload         7
     135: athrow
     136: return
    Exception table:
       from    to  target type
           5    84    91   Class org/xml/sax/SAXException
           5    84   103   Class java/io/IOException
           5    84   115   Class javax/xml/parsers/ParserConfigurationException
           5    84   127   any
          91   129   127   any
}
