Compiled from "DirectoryBrowserSupport.java"
final class hudson.model.DirectoryBrowserSupport$FileComparator implements java.util.Comparator<java.io.File> {
  private hudson.model.DirectoryBrowserSupport$FileComparator();
    Code:
       0: aload_0
       1: invokespecial #2                  // Method java/lang/Object."<init>":()V
       4: return

  public int compare(java.io.File, java.io.File);
    Code:
       0: aload_0
       1: aload_1
       2: invokespecial #3                  // Method dirRank:(Ljava/io/File;)I
       5: aload_0
       6: aload_2
       7: invokespecial #3                  // Method dirRank:(Ljava/io/File;)I
      10: isub
      11: istore_3
      12: iload_3
      13: ifeq          18
      16: iload_3
      17: ireturn
      18: aload_1
      19: invokevirtual #4                  // Method java/io/File.getName:()Ljava/lang/String;
      22: aload_2
      23: invokevirtual #4                  // Method java/io/File.getName:()Ljava/lang/String;
      26: invokevirtual #5                  // Method java/lang/String.compareTo:(Ljava/lang/String;)I
      29: ireturn

  private int dirRank(java.io.File);
    Code:
       0: aload_1
       1: invokevirtual #6                  // Method java/io/File.isDirectory:()Z
       4: ifeq          9
       7: iconst_0
       8: ireturn
       9: iconst_1
      10: ireturn

  public int compare(java.lang.Object, java.lang.Object);
    Code:
       0: aload_0
       1: aload_1
       2: checkcast     #7                  // class java/io/File
       5: aload_2
       6: checkcast     #7                  // class java/io/File
       9: invokevirtual #8                  // Method compare:(Ljava/io/File;Ljava/io/File;)I
      12: ireturn

  hudson.model.DirectoryBrowserSupport$FileComparator(hudson.model.DirectoryBrowserSupport$1);
    Code:
       0: aload_0
       1: invokespecial #1                  // Method "<init>":()V
       4: return
}
