Compiled from "ExternalJob.java"
final class hudson.model.ExternalJob$1 implements hudson.model.RunMap$Constructor<hudson.model.ExternalRun> {
  final hudson.model.ExternalJob this$0;

  hudson.model.ExternalJob$1(hudson.model.ExternalJob);
    Code:
       0: aload_0
       1: aload_1
       2: putfield      #1                  // Field this$0:Lhudson/model/ExternalJob;
       5: aload_0
       6: invokespecial #2                  // Method java/lang/Object."<init>":()V
       9: return

  public hudson.model.ExternalRun create(java.io.File) throws java.io.IOException;
    Code:
       0: new           #3                  // class hudson/model/ExternalRun
       3: dup
       4: aload_0
       5: getfield      #1                  // Field this$0:Lhudson/model/ExternalJob;
       8: aload_1
       9: invokespecial #4                  // Method hudson/model/ExternalRun."<init>":(Lhudson/model/ExternalJob;Ljava/io/File;)V
      12: areturn

  public hudson.model.Run create(java.io.File) throws java.io.IOException;
    Code:
       0: aload_0
       1: aload_1
       2: invokevirtual #5                  // Method create:(Ljava/io/File;)Lhudson/model/ExternalRun;
       5: areturn
}
