Compiled from "Job.java"
class hudson.model.Job$1ChartLabel implements java.lang.Comparable<hudson.model.Job$1ChartLabel> {
  final hudson.model.Run run;

  final hudson.model.Job this$0;

  public hudson.model.Job$1ChartLabel(hudson.model.Job, hudson.model.Run);
    Code:
       0: aload_0
       1: aload_1
       2: putfield      #1                  // Field this$0:Lhudson/model/Job;
       5: aload_0
       6: invokespecial #2                  // Method java/lang/Object."<init>":()V
       9: aload_0
      10: aload_2
      11: putfield      #3                  // Field run:Lhudson/model/Run;
      14: return

  public int compareTo(hudson.model.Job$1ChartLabel);
    Code:
       0: aload_0
       1: getfield      #3                  // Field run:Lhudson/model/Run;
       4: getfield      #4                  // Field hudson/model/Run.number:I
       7: aload_1
       8: getfield      #3                  // Field run:Lhudson/model/Run;
      11: getfield      #4                  // Field hudson/model/Run.number:I
      14: isub
      15: ireturn

  public boolean equals(java.lang.Object);
    Code:
       0: aload_1
       1: checkcast     #5                  // class hudson/model/Job$1ChartLabel
       4: astore_2
       5: aload_0
       6: getfield      #3                  // Field run:Lhudson/model/Run;
       9: aload_2
      10: getfield      #3                  // Field run:Lhudson/model/Run;
      13: if_acmpne     20
      16: iconst_1
      17: goto          21
      20: iconst_0
      21: ireturn

  public java.awt.Color getColor();
    Code:
       0: aload_0
       1: getfield      #3                  // Field run:Lhudson/model/Run;
       4: invokevirtual #6                  // Method hudson/model/Run.getResult:()Lhudson/model/Result;
       7: astore_1
       8: aload_1
       9: getstatic     #7                  // Field hudson/model/Result.FAILURE:Lhudson/model/Result;
      12: if_acmpeq     22
      15: aload_1
      16: getstatic     #8                  // Field hudson/model/Result.ABORTED:Lhudson/model/Result;
      19: if_acmpne     26
      22: getstatic     #9                  // Field hudson/util/ColorPalette.RED:Ljava/awt/Color;
      25: areturn
      26: getstatic     #10                 // Field hudson/util/ColorPalette.BLUE:Ljava/awt/Color;
      29: areturn

  public int hashCode();
    Code:
       0: aload_0
       1: getfield      #3                  // Field run:Lhudson/model/Run;
       4: invokevirtual #11                 // Method java/lang/Object.hashCode:()I
       7: ireturn

  public java.lang.String toString();
    Code:
       0: aload_0
       1: getfield      #3                  // Field run:Lhudson/model/Run;
       4: invokevirtual #12                 // Method hudson/model/Run.getDisplayName:()Ljava/lang/String;
       7: astore_1
       8: aload_0
       9: getfield      #3                  // Field run:Lhudson/model/Run;
      12: instanceof    #13                 // class hudson/model/Build
      15: ifeq          57
      18: aload_0
      19: getfield      #3                  // Field run:Lhudson/model/Run;
      22: checkcast     #13                 // class hudson/model/Build
      25: invokevirtual #14                 // Method hudson/model/Build.getBuiltOnStr:()Ljava/lang/String;
      28: astore_2
      29: aload_2
      30: ifnull        57
      33: new           #15                 // class java/lang/StringBuilder
      36: dup
      37: invokespecial #16                 // Method java/lang/StringBuilder."<init>":()V
      40: aload_1
      41: invokevirtual #17                 // Method java/lang/StringBuilder.append:(Ljava/lang/String;)Ljava/lang/StringBuilder;
      44: bipush        32
      46: invokevirtual #18                 // Method java/lang/StringBuilder.append:(C)Ljava/lang/StringBuilder;
      49: aload_2
      50: invokevirtual #17                 // Method java/lang/StringBuilder.append:(Ljava/lang/String;)Ljava/lang/StringBuilder;
      53: invokevirtual #19                 // Method java/lang/StringBuilder.toString:()Ljava/lang/String;
      56: astore_1
      57: aload_1
      58: areturn

  public int compareTo(java.lang.Object);
    Code:
       0: aload_0
       1: aload_1
       2: checkcast     #5                  // class hudson/model/Job$1ChartLabel
       5: invokevirtual #20                 // Method compareTo:(Lhudson/model/Job$1ChartLabel;)I
       8: ireturn
}
