Compiled from "ListView.java"
public class hudson.model.ListView extends hudson.model.View {
  private final hudson.model.Hudson owner;

  final java.util.Set<java.lang.String> jobNames;

  private java.lang.String name;

  private java.lang.String description;

  private java.lang.String includeRegex;

  private transient java.util.regex.Pattern includePattern;

  public hudson.model.ListView(hudson.model.Hudson, java.lang.String);
    Code:
       0: aload_0
       1: invokespecial #1                  // Method hudson/model/View."<init>":()V
       4: aload_0
       5: new           #2                  // class java/util/TreeSet
       8: dup
       9: getstatic     #3                  // Field hudson/util/CaseInsensitiveComparator.INSTANCE:Ljava/util/Comparator;
      12: invokespecial #4                  // Method java/util/TreeSet."<init>":(Ljava/util/Comparator;)V
      15: putfield      #5                  // Field jobNames:Ljava/util/Set;
      18: aload_0
      19: aload_2
      20: putfield      #6                  // Field name:Ljava/lang/String;
      23: aload_0
      24: aload_1
      25: putfield      #7                  // Field owner:Lhudson/model/Hudson;
      28: return

  public synchronized java.util.List<hudson.model.TopLevelItem> getItems();
    Code:
       0: aload_0
       1: getfield      #5                  // Field jobNames:Ljava/util/Set;
       4: checkcast     #2                  // class java/util/TreeSet
       7: invokevirtual #8                  // Method java/util/TreeSet.clone:()Ljava/lang/Object;
      10: checkcast     #9                  // class java/util/Set
      13: astore_1
      14: aload_0
      15: getfield      #10                 // Field includeRegex:Ljava/lang/String;
      18: ifnull        110
      21: aload_0
      22: getfield      #11                 // Field includePattern:Ljava/util/regex/Pattern;
      25: ifnonnull     39
      28: aload_0
      29: aload_0
      30: getfield      #10                 // Field includeRegex:Ljava/lang/String;
      33: invokestatic  #12                 // Method java/util/regex/Pattern.compile:(Ljava/lang/String;)Ljava/util/regex/Pattern;
      36: putfield      #11                 // Field includePattern:Ljava/util/regex/Pattern;
      39: aload_0
      40: getfield      #7                  // Field owner:Lhudson/model/Hudson;
      43: invokevirtual #13                 // Method hudson/model/Hudson.getItems:()Ljava/util/List;
      46: invokeinterface #14,  1           // InterfaceMethod java/util/List.iterator:()Ljava/util/Iterator;
      51: astore_2
      52: aload_2
      53: invokeinterface #15,  1           // InterfaceMethod java/util/Iterator.hasNext:()Z
      58: ifeq          106
      61: aload_2
      62: invokeinterface #16,  1           // InterfaceMethod java/util/Iterator.next:()Ljava/lang/Object;
      67: checkcast     #17                 // class hudson/model/TopLevelItem
      70: astore_3
      71: aload_3
      72: invokeinterface #18,  1           // InterfaceMethod hudson/model/TopLevelItem.getName:()Ljava/lang/String;
      77: astore        4
      79: aload_0
      80: getfield      #11                 // Field includePattern:Ljava/util/regex/Pattern;
      83: aload         4
      85: invokevirtual #19                 // Method java/util/regex/Pattern.matcher:(Ljava/lang/CharSequence;)Ljava/util/regex/Matcher;
      88: invokevirtual #20                 // Method java/util/regex/Matcher.matches:()Z
      91: ifeq          103
      94: aload_1
      95: aload         4
      97: invokeinterface #21,  2           // InterfaceMethod java/util/Set.add:(Ljava/lang/Object;)Z
     102: pop
     103: goto          52
     106: goto          110
     109: astore_2
     110: aload_1
     111: invokeinterface #23,  1           // InterfaceMethod java/util/Set.size:()I
     116: anewarray     #17                 // class hudson/model/TopLevelItem
     119: astore_2
     120: iconst_0
     121: istore_3
     122: aload_1
     123: invokeinterface #24,  1           // InterfaceMethod java/util/Set.iterator:()Ljava/util/Iterator;
     128: astore        4
     130: aload         4
     132: invokeinterface #15,  1           // InterfaceMethod java/util/Iterator.hasNext:()Z
     137: ifeq          170
     140: aload         4
     142: invokeinterface #16,  1           // InterfaceMethod java/util/Iterator.next:()Ljava/lang/Object;
     147: checkcast     #25                 // class java/lang/String
     150: astore        5
     152: aload_2
     153: iload_3
     154: iinc          3, 1
     157: aload_0
     158: getfield      #7                  // Field owner:Lhudson/model/Hudson;
     161: aload         5
     163: invokevirtual #26                 // Method hudson/model/Hudson.getItem:(Ljava/lang/String;)Lhudson/model/TopLevelItem;
     166: aastore
     167: goto          130
     170: aload_2
     171: invokestatic  #27                 // Method java/util/Arrays.asList:([Ljava/lang/Object;)Ljava/util/List;
     174: areturn
    Exception table:
       from    to  target type
          21   106   109   Class java/util/regex/PatternSyntaxException

  public hudson.model.TopLevelItem getItem(java.lang.String);
    Code:
       0: aload_0
       1: getfield      #7                  // Field owner:Lhudson/model/Hudson;
       4: aload_1
       5: invokevirtual #26                 // Method hudson/model/Hudson.getItem:(Ljava/lang/String;)Lhudson/model/TopLevelItem;
       8: areturn

  public hudson.model.TopLevelItem getJob(java.lang.String);
    Code:
       0: aload_0
       1: aload_1
       2: invokevirtual #28                 // Method getItem:(Ljava/lang/String;)Lhudson/model/TopLevelItem;
       5: areturn

  public boolean contains(hudson.model.TopLevelItem);
    Code:
       0: aload_0
       1: getfield      #5                  // Field jobNames:Ljava/util/Set;
       4: aload_1
       5: invokeinterface #18,  1           // InterfaceMethod hudson/model/TopLevelItem.getName:()Ljava/lang/String;
      10: invokeinterface #29,  2           // InterfaceMethod java/util/Set.contains:(Ljava/lang/Object;)Z
      15: ireturn

  public java.lang.String getViewName();
    Code:
       0: aload_0
       1: getfield      #6                  // Field name:Ljava/lang/String;
       4: areturn

  public java.lang.String getDescription();
    Code:
       0: aload_0
       1: getfield      #30                 // Field description:Ljava/lang/String;
       4: areturn

  public java.lang.String getDisplayName();
    Code:
       0: aload_0
       1: getfield      #6                  // Field name:Ljava/lang/String;
       4: areturn

  public java.lang.String getIncludeRegex();
    Code:
       0: aload_0
       1: getfield      #10                 // Field includeRegex:Ljava/lang/String;
       4: areturn

  public hudson.model.Item doCreateItem(org.kohsuke.stapler.StaplerRequest, org.kohsuke.stapler.StaplerResponse) throws java.io.IOException, javax.servlet.ServletException;
    Code:
       0: aload_0
       1: getfield      #7                  // Field owner:Lhudson/model/Hudson;
       4: aload_1
       5: aload_2
       6: invokevirtual #31                 // Method hudson/model/Hudson.doCreateItem:(Lorg/kohsuke/stapler/StaplerRequest;Lorg/kohsuke/stapler/StaplerResponse;)Lhudson/model/Item;
       9: astore_3
      10: aload_3
      11: ifnull        37
      14: aload_0
      15: getfield      #5                  // Field jobNames:Ljava/util/Set;
      18: aload_3
      19: invokeinterface #32,  1           // InterfaceMethod hudson/model/Item.getName:()Ljava/lang/String;
      24: invokeinterface #21,  2           // InterfaceMethod java/util/Set.add:(Ljava/lang/Object;)Z
      29: pop
      30: aload_0
      31: getfield      #7                  // Field owner:Lhudson/model/Hudson;
      34: invokevirtual #33                 // Method hudson/model/Hudson.save:()V
      37: aload_3
      38: areturn

  public java.lang.String getUrl();
    Code:
       0: new           #34                 // class java/lang/StringBuilder
       3: dup
       4: invokespecial #35                 // Method java/lang/StringBuilder."<init>":()V
       7: ldc           #36                 // String view/
       9: invokevirtual #37                 // Method java/lang/StringBuilder.append:(Ljava/lang/String;)Ljava/lang/StringBuilder;
      12: aload_0
      13: getfield      #6                  // Field name:Ljava/lang/String;
      16: invokevirtual #37                 // Method java/lang/StringBuilder.append:(Ljava/lang/String;)Ljava/lang/StringBuilder;
      19: bipush        47
      21: invokevirtual #38                 // Method java/lang/StringBuilder.append:(C)Ljava/lang/StringBuilder;
      24: invokevirtual #39                 // Method java/lang/StringBuilder.toString:()Ljava/lang/String;
      27: areturn

  public synchronized void doConfigSubmit(org.kohsuke.stapler.StaplerRequest, org.kohsuke.stapler.StaplerResponse) throws java.io.IOException, javax.servlet.ServletException;
    Code:
       0: aload_0
       1: getstatic     #40                 // Field CONFIGURE:Lhudson/security/Permission;
       4: invokevirtual #41                 // Method checkPermission:(Lhudson/security/Permission;)V
       7: aload_1
       8: ldc           #42                 // String UTF-8
      10: invokeinterface #43,  2           // InterfaceMethod org/kohsuke/stapler/StaplerRequest.setCharacterEncoding:(Ljava/lang/String;)V
      15: aload_0
      16: getfield      #5                  // Field jobNames:Ljava/util/Set;
      19: invokeinterface #44,  1           // InterfaceMethod java/util/Set.clear:()V
      24: aload_0
      25: getfield      #7                  // Field owner:Lhudson/model/Hudson;
      28: invokevirtual #13                 // Method hudson/model/Hudson.getItems:()Ljava/util/List;
      31: invokeinterface #14,  1           // InterfaceMethod java/util/List.iterator:()Ljava/util/Iterator;
      36: astore_3
      37: aload_3
      38: invokeinterface #15,  1           // InterfaceMethod java/util/Iterator.hasNext:()Z
      43: ifeq          93
      46: aload_3
      47: invokeinterface #16,  1           // InterfaceMethod java/util/Iterator.next:()Ljava/lang/Object;
      52: checkcast     #17                 // class hudson/model/TopLevelItem
      55: astore        4
      57: aload_1
      58: aload         4
      60: invokeinterface #18,  1           // InterfaceMethod hudson/model/TopLevelItem.getName:()Ljava/lang/String;
      65: invokeinterface #45,  2           // InterfaceMethod org/kohsuke/stapler/StaplerRequest.getParameter:(Ljava/lang/String;)Ljava/lang/String;
      70: ifnull        90
      73: aload_0
      74: getfield      #5                  // Field jobNames:Ljava/util/Set;
      77: aload         4
      79: invokeinterface #18,  1           // InterfaceMethod hudson/model/TopLevelItem.getName:()Ljava/lang/String;
      84: invokeinterface #21,  2           // InterfaceMethod java/util/Set.add:(Ljava/lang/Object;)Z
      89: pop
      90: goto          37
      93: aload_0
      94: aload_1
      95: ldc           #46                 // String description
      97: invokeinterface #45,  2           // InterfaceMethod org/kohsuke/stapler/StaplerRequest.getParameter:(Ljava/lang/String;)Ljava/lang/String;
     102: invokestatic  #47                 // Method hudson/Util.nullify:(Ljava/lang/String;)Ljava/lang/String;
     105: putfield      #30                 // Field description:Ljava/lang/String;
     108: aload_1
     109: ldc           #48                 // String useincluderegex
     111: invokeinterface #45,  2           // InterfaceMethod org/kohsuke/stapler/StaplerRequest.getParameter:(Ljava/lang/String;)Ljava/lang/String;
     116: ifnull        137
     119: aload_0
     120: aload_1
     121: ldc           #49                 // String includeregex
     123: invokeinterface #45,  2           // InterfaceMethod org/kohsuke/stapler/StaplerRequest.getParameter:(Ljava/lang/String;)Ljava/lang/String;
     128: invokestatic  #47                 // Method hudson/Util.nullify:(Ljava/lang/String;)Ljava/lang/String;
     131: putfield      #10                 // Field includeRegex:Ljava/lang/String;
     134: goto          142
     137: aload_0
     138: aconst_null
     139: putfield      #10                 // Field includeRegex:Ljava/lang/String;
     142: aload_0
     143: aconst_null
     144: putfield      #11                 // Field includePattern:Ljava/util/regex/Pattern;
     147: aload_1
     148: ldc           #50                 // String name
     150: invokeinterface #45,  2           // InterfaceMethod org/kohsuke/stapler/StaplerRequest.getParameter:(Ljava/lang/String;)Ljava/lang/String;
     155: astore_3
     156: aload_3
     157: invokestatic  #51                 // Method hudson/model/Hudson.checkGoodName:(Ljava/lang/String;)V
     160: aload_0
     161: aload_3
     162: putfield      #6                  // Field name:Ljava/lang/String;
     165: goto          177
     168: astore_3
     169: aload_0
     170: aload_3
     171: aload_1
     172: aload_2
     173: invokevirtual #53                 // Method sendError:(Ljava/lang/Exception;Lorg/kohsuke/stapler/StaplerRequest;Lorg/kohsuke/stapler/StaplerResponse;)V
     176: return
     177: aload_0
     178: getfield      #7                  // Field owner:Lhudson/model/Hudson;
     181: invokevirtual #33                 // Method hudson/model/Hudson.save:()V
     184: aload_2
     185: new           #34                 // class java/lang/StringBuilder
     188: dup
     189: invokespecial #35                 // Method java/lang/StringBuilder."<init>":()V
     192: ldc           #54                 // String ../
     194: invokevirtual #37                 // Method java/lang/StringBuilder.append:(Ljava/lang/String;)Ljava/lang/StringBuilder;
     197: aload_0
     198: getfield      #6                  // Field name:Ljava/lang/String;
     201: invokevirtual #37                 // Method java/lang/StringBuilder.append:(Ljava/lang/String;)Ljava/lang/StringBuilder;
     204: invokevirtual #39                 // Method java/lang/StringBuilder.toString:()Ljava/lang/String;
     207: invokeinterface #55,  2           // InterfaceMethod org/kohsuke/stapler/StaplerResponse.sendRedirect:(Ljava/lang/String;)V
     212: return
    Exception table:
       from    to  target type
         147   165   168   Class java/text/ParseException

  public synchronized void doSubmitDescription(org.kohsuke.stapler.StaplerRequest, org.kohsuke.stapler.StaplerResponse) throws java.io.IOException, javax.servlet.ServletException;
    Code:
       0: aload_0
       1: getstatic     #40                 // Field CONFIGURE:Lhudson/security/Permission;
       4: invokevirtual #41                 // Method checkPermission:(Lhudson/security/Permission;)V
       7: aload_1
       8: ldc           #42                 // String UTF-8
      10: invokeinterface #43,  2           // InterfaceMethod org/kohsuke/stapler/StaplerRequest.setCharacterEncoding:(Ljava/lang/String;)V
      15: aload_0
      16: aload_1
      17: ldc           #46                 // String description
      19: invokeinterface #45,  2           // InterfaceMethod org/kohsuke/stapler/StaplerRequest.getParameter:(Ljava/lang/String;)Ljava/lang/String;
      24: putfield      #30                 // Field description:Ljava/lang/String;
      27: aload_0
      28: getfield      #7                  // Field owner:Lhudson/model/Hudson;
      31: invokevirtual #33                 // Method hudson/model/Hudson.save:()V
      34: aload_2
      35: ldc           #56                 // String .
      37: invokeinterface #55,  2           // InterfaceMethod org/kohsuke/stapler/StaplerResponse.sendRedirect:(Ljava/lang/String;)V
      42: return

  public synchronized void doDoDelete(org.kohsuke.stapler.StaplerRequest, org.kohsuke.stapler.StaplerResponse) throws java.io.IOException;
    Code:
       0: aload_0
       1: getstatic     #57                 // Field DELETE:Lhudson/security/Permission;
       4: invokevirtual #41                 // Method checkPermission:(Lhudson/security/Permission;)V
       7: aload_0
       8: getfield      #7                  // Field owner:Lhudson/model/Hudson;
      11: aload_0
      12: invokevirtual #58                 // Method hudson/model/Hudson.deleteView:(Lhudson/model/ListView;)V
      15: aload_2
      16: new           #34                 // class java/lang/StringBuilder
      19: dup
      20: invokespecial #35                 // Method java/lang/StringBuilder."<init>":()V
      23: aload_1
      24: invokeinterface #59,  1           // InterfaceMethod org/kohsuke/stapler/StaplerRequest.getContextPath:()Ljava/lang/String;
      29: invokevirtual #37                 // Method java/lang/StringBuilder.append:(Ljava/lang/String;)Ljava/lang/StringBuilder;
      32: ldc           #60                 // String /
      34: invokevirtual #37                 // Method java/lang/StringBuilder.append:(Ljava/lang/String;)Ljava/lang/StringBuilder;
      37: invokevirtual #39                 // Method java/lang/StringBuilder.toString:()Ljava/lang/String;
      40: invokeinterface #61,  2           // InterfaceMethod org/kohsuke/stapler/StaplerResponse.sendRedirect2:(Ljava/lang/String;)V
      45: return

  public synchronized void doIncludeRegexCheck(org.kohsuke.stapler.StaplerRequest, org.kohsuke.stapler.StaplerResponse) throws java.io.IOException, javax.servlet.ServletException, java.lang.InterruptedException;
    Code:
       0: new           #62                 // class hudson/model/ListView$1
       3: dup
       4: aload_0
       5: aload_1
       6: aload_2
       7: iconst_0
       8: invokespecial #63                 // Method hudson/model/ListView$1."<init>":(Lhudson/model/ListView;Lorg/kohsuke/stapler/StaplerRequest;Lorg/kohsuke/stapler/StaplerResponse;Z)V
      11: invokevirtual #64                 // Method hudson/model/ListView$1.process:()V
      14: return

  public java.util.Collection getItems();
    Code:
       0: aload_0
       1: invokevirtual #65                 // Method getItems:()Ljava/util/List;
       4: areturn
}
