Compiled from "Slave.java"
final class hudson.model.Slave$ComputerImpl$DetectOS implements hudson.remoting.Callable<java.lang.Boolean, java.io.IOException> {
  private hudson.model.Slave$ComputerImpl$DetectOS();
    Code:
       0: aload_0
       1: invokespecial #2                  // Method java/lang/Object."<init>":()V
       4: return

  public java.lang.Boolean call() throws java.io.IOException;
    Code:
       0: getstatic     #3                  // Field java/io/File.pathSeparatorChar:C
       3: bipush        58
       5: if_icmpne     12
       8: iconst_1
       9: goto          13
      12: iconst_0
      13: invokestatic  #4                  // Method java/lang/Boolean.valueOf:(Z)Ljava/lang/Boolean;
      16: areturn

  public java.lang.Object call() throws java.lang.Throwable;
    Code:
       0: aload_0
       1: invokevirtual #5                  // Method call:()Ljava/lang/Boolean;
       4: areturn

  hudson.model.Slave$ComputerImpl$DetectOS(hudson.model.Slave$1);
    Code:
       0: aload_0
       1: invokespecial #1                  // Method "<init>":()V
       4: return
}
