Compiled from "TaskThread.java"
public abstract class hudson.model.TaskThread extends java.lang.Thread {
  private final hudson.model.LargeText text;

  private hudson.model.TaskListener listener;

  private final hudson.model.TaskAction owner;

  protected hudson.model.TaskThread(hudson.model.TaskAction, hudson.model.TaskThread$ListenerAndText);
    Code:
       0: aload_0
       1: aload_1
       2: invokevirtual #1                  // Method hudson/model/TaskAction.getDisplayName:()Ljava/lang/String;
       5: invokespecial #2                  // Method java/lang/Thread."<init>":(Ljava/lang/String;)V
       8: aload_0
       9: aload_1
      10: putfield      #3                  // Field owner:Lhudson/model/TaskAction;
      13: aload_0
      14: aload_2
      15: getfield      #4                  // Field hudson/model/TaskThread$ListenerAndText.text:Lhudson/model/LargeText;
      18: putfield      #5                  // Field text:Lhudson/model/LargeText;
      21: aload_0
      22: aload_2
      23: getfield      #6                  // Field hudson/model/TaskThread$ListenerAndText.listener:Lhudson/model/TaskListener;
      26: putfield      #7                  // Field listener:Lhudson/model/TaskListener;
      29: return

  public java.io.Reader readAll() throws java.io.IOException;
    Code:
       0: aload_0
       1: getfield      #5                  // Field text:Lhudson/model/LargeText;
       4: invokevirtual #8                  // Method hudson/model/LargeText.readAll:()Ljava/io/Reader;
       7: areturn

  protected final void associateWith(hudson.model.TaskAction);
    Code:
       0: aload_1
       1: aload_0
       2: putfield      #9                  // Field hudson/model/TaskAction.workerThread:Lhudson/model/TaskThread;
       5: aload_1
       6: new           #10                 // class java/lang/ref/WeakReference
       9: dup
      10: aload_0
      11: getfield      #5                  // Field text:Lhudson/model/LargeText;
      14: invokespecial #11                 // Method java/lang/ref/WeakReference."<init>":(Ljava/lang/Object;)V
      17: putfield      #12                 // Field hudson/model/TaskAction.log:Ljava/lang/ref/WeakReference;
      20: return

  public synchronized void start();
    Code:
       0: aload_0
       1: aload_0
       2: getfield      #3                  // Field owner:Lhudson/model/TaskAction;
       5: invokevirtual #13                 // Method associateWith:(Lhudson/model/TaskAction;)V
       8: aload_0
       9: invokespecial #14                 // Method java/lang/Thread.start:()V
      12: return

  protected hudson.model.TaskThread$ListenerAndText createListener() throws java.io.IOException;
    Code:
       0: invokestatic  #15                 // Method hudson/model/TaskThread$ListenerAndText.forMemory:()Lhudson/model/TaskThread$ListenerAndText;
       3: areturn

  public final void run();
    Code:
       0: aload_0
       1: aload_0
       2: getfield      #7                  // Field listener:Lhudson/model/TaskListener;
       5: invokevirtual #16                 // Method perform:(Lhudson/model/TaskListener;)V
       8: aload_0
       9: getfield      #7                  // Field listener:Lhudson/model/TaskListener;
      12: invokeinterface #17,  1           // InterfaceMethod hudson/model/TaskListener.getLogger:()Ljava/io/PrintStream;
      17: ldc           #18                 // String Completed
      19: invokevirtual #19                 // Method java/io/PrintStream.println:(Ljava/lang/String;)V
      22: aload_0
      23: getfield      #3                  // Field owner:Lhudson/model/TaskAction;
      26: aconst_null
      27: putfield      #9                  // Field hudson/model/TaskAction.workerThread:Lhudson/model/TaskThread;
      30: aload_0
      31: aconst_null
      32: putfield      #7                  // Field listener:Lhudson/model/TaskListener;
      35: goto          91
      38: astore_1
      39: aload_0
      40: getfield      #7                  // Field listener:Lhudson/model/TaskListener;
      43: invokeinterface #17,  1           // InterfaceMethod hudson/model/TaskListener.getLogger:()Ljava/io/PrintStream;
      48: ldc           #21                 // String Aborted
      50: invokevirtual #19                 // Method java/io/PrintStream.println:(Ljava/lang/String;)V
      53: aload_0
      54: aconst_null
      55: putfield      #7                  // Field listener:Lhudson/model/TaskListener;
      58: goto          91
      61: astore_1
      62: aload_1
      63: aload_0
      64: getfield      #7                  // Field listener:Lhudson/model/TaskListener;
      67: invokeinterface #17,  1           // InterfaceMethod hudson/model/TaskListener.getLogger:()Ljava/io/PrintStream;
      72: invokevirtual #23                 // Method java/lang/Exception.printStackTrace:(Ljava/io/PrintStream;)V
      75: aload_0
      76: aconst_null
      77: putfield      #7                  // Field listener:Lhudson/model/TaskListener;
      80: goto          91
      83: astore_2
      84: aload_0
      85: aconst_null
      86: putfield      #7                  // Field listener:Lhudson/model/TaskListener;
      89: aload_2
      90: athrow
      91: aload_0
      92: getfield      #5                  // Field text:Lhudson/model/LargeText;
      95: invokevirtual #24                 // Method hudson/model/LargeText.markAsComplete:()V
      98: return
    Exception table:
       from    to  target type
           0    30    38   Class java/lang/InterruptedException
           0    30    61   Class java/lang/Exception
           0    30    83   any
          38    53    83   any
          61    75    83   any
          83    84    83   any

  protected abstract void perform(hudson.model.TaskListener) throws java.lang.Exception;
}
