Compiled from "WorkspaceCleanupThread.java"
public class hudson.model.WorkspaceCleanupThread extends hudson.model.PeriodicWork {
  private static hudson.model.WorkspaceCleanupThread theInstance;

  private hudson.util.StreamTaskListener listener;

  private static final java.io.FileFilter DIR_FILTER;

  private static final long DAY;

  private static final java.util.logging.Logger LOGGER;

  public hudson.model.WorkspaceCleanupThread();
    Code:
       0: aload_0
       1: ldc           #1                  // String Workspace clean-up
       3: invokespecial #2                  // Method hudson/model/PeriodicWork."<init>":(Ljava/lang/String;)V
       6: aload_0
       7: putstatic     #3                  // Field theInstance:Lhudson/model/WorkspaceCleanupThread;
      10: return

  public static void invoke();
    Code:
       0: getstatic     #3                  // Field theInstance:Lhudson/model/WorkspaceCleanupThread;
       3: invokevirtual #4                  // Method run:()V
       6: return

  protected void execute();
    Code:
       0: invokestatic  #5                  // Method hudson/model/Hudson.getInstance:()Lhudson/model/Hudson;
       3: astore_1
       4: aload_0
       5: new           #6                  // class hudson/util/StreamTaskListener
       8: dup
       9: new           #7                  // class java/io/File
      12: dup
      13: aload_1
      14: invokevirtual #8                  // Method hudson/model/Hudson.getRootDir:()Ljava/io/File;
      17: ldc           #9                  // String workspace-cleanup.log
      19: invokespecial #10                 // Method java/io/File."<init>":(Ljava/io/File;Ljava/lang/String;)V
      22: invokespecial #11                 // Method hudson/util/StreamTaskListener."<init>":(Ljava/io/File;)V
      25: putfield      #12                 // Field listener:Lhudson/util/StreamTaskListener;
      28: aload_1
      29: invokevirtual #13                 // Method hudson/model/Hudson.getSlaves:()Ljava/util/List;
      32: invokeinterface #14,  1           // InterfaceMethod java/util/List.iterator:()Ljava/util/Iterator;
      37: astore_2
      38: aload_2
      39: invokeinterface #15,  1           // InterfaceMethod java/util/Iterator.hasNext:()Z
      44: ifeq          65
      47: aload_2
      48: invokeinterface #16,  1           // InterfaceMethod java/util/Iterator.next:()Ljava/lang/Object;
      53: checkcast     #17                 // class hudson/model/Slave
      56: astore_3
      57: aload_0
      58: aload_3
      59: invokespecial #18                 // Method process:(Lhudson/model/Slave;)V
      62: goto          38
      65: aload_0
      66: aload_1
      67: invokespecial #19                 // Method process:(Lhudson/model/Hudson;)V
      70: aload_0
      71: getfield      #12                 // Field listener:Lhudson/util/StreamTaskListener;
      74: ifnull        84
      77: aload_0
      78: getfield      #12                 // Field listener:Lhudson/util/StreamTaskListener;
      81: invokevirtual #20                 // Method hudson/util/StreamTaskListener.close:()V
      84: aload_0
      85: aconst_null
      86: putfield      #12                 // Field listener:Lhudson/util/StreamTaskListener;
      89: goto          152
      92: astore_2
      93: aload_2
      94: aload_0
      95: getfield      #12                 // Field listener:Lhudson/util/StreamTaskListener;
      98: ldc           #22                 // String aborted
     100: invokevirtual #23                 // Method hudson/util/StreamTaskListener.fatalError:(Ljava/lang/String;)Ljava/io/PrintWriter;
     103: invokevirtual #24                 // Method java/lang/InterruptedException.printStackTrace:(Ljava/io/PrintWriter;)V
     106: aload_0
     107: getfield      #12                 // Field listener:Lhudson/util/StreamTaskListener;
     110: ifnull        120
     113: aload_0
     114: getfield      #12                 // Field listener:Lhudson/util/StreamTaskListener;
     117: invokevirtual #20                 // Method hudson/util/StreamTaskListener.close:()V
     120: aload_0
     121: aconst_null
     122: putfield      #12                 // Field listener:Lhudson/util/StreamTaskListener;
     125: goto          152
     128: astore        4
     130: aload_0
     131: getfield      #12                 // Field listener:Lhudson/util/StreamTaskListener;
     134: ifnull        144
     137: aload_0
     138: getfield      #12                 // Field listener:Lhudson/util/StreamTaskListener;
     141: invokevirtual #20                 // Method hudson/util/StreamTaskListener.close:()V
     144: aload_0
     145: aconst_null
     146: putfield      #12                 // Field listener:Lhudson/util/StreamTaskListener;
     149: aload         4
     151: athrow
     152: goto          169
     155: astore_2
     156: aload_0
     157: getfield      #26                 // Field logger:Ljava/util/logging/Logger;
     160: getstatic     #27                 // Field java/util/logging/Level.SEVERE:Ljava/util/logging/Level;
     163: ldc           #28                 // String Failed to access log file
     165: aload_2
     166: invokevirtual #29                 // Method java/util/logging/Logger.log:(Ljava/util/logging/Level;Ljava/lang/String;Ljava/lang/Throwable;)V
     169: return
    Exception table:
       from    to  target type
           4    70    92   Class java/lang/InterruptedException
           4    70   128   any
          92   106   128   any
         128   130   128   any
           4   152   155   Class java/io/IOException

  private void process(hudson.model.Hudson) throws java.io.IOException, java.lang.InterruptedException;
    Code:
       0: new           #7                  // class java/io/File
       3: dup
       4: aload_1
       5: invokevirtual #8                  // Method hudson/model/Hudson.getRootDir:()Ljava/io/File;
       8: ldc           #30                 // String jobs
      10: invokespecial #10                 // Method java/io/File."<init>":(Ljava/io/File;Ljava/lang/String;)V
      13: astore_2
      14: aload_2
      15: getstatic     #31                 // Field DIR_FILTER:Ljava/io/FileFilter;
      18: invokevirtual #32                 // Method java/io/File.listFiles:(Ljava/io/FileFilter;)[Ljava/io/File;
      21: astore_3
      22: aload_3
      23: ifnonnull     27
      26: return
      27: aload_3
      28: astore        4
      30: aload         4
      32: arraylength
      33: istore        5
      35: iconst_0
      36: istore        6
      38: iload         6
      40: iload         5
      42: if_icmpge     99
      45: aload         4
      47: iload         6
      49: aaload
      50: astore        7
      52: new           #33                 // class hudson/FilePath
      55: dup
      56: new           #7                  // class java/io/File
      59: dup
      60: aload         7
      62: ldc           #34                 // String workspace
      64: invokespecial #10                 // Method java/io/File."<init>":(Ljava/io/File;Ljava/lang/String;)V
      67: invokespecial #35                 // Method hudson/FilePath."<init>":(Ljava/io/File;)V
      70: astore        8
      72: aload_0
      73: aload         7
      75: invokevirtual #36                 // Method java/io/File.getName:()Ljava/lang/String;
      78: aload         8
      80: aload_1
      81: invokespecial #37                 // Method shouldBeDeleted:(Ljava/lang/String;Lhudson/FilePath;Lhudson/model/Node;)Z
      84: ifeq          93
      87: aload_0
      88: aload         8
      90: invokespecial #38                 // Method delete:(Lhudson/FilePath;)V
      93: iinc          6, 1
      96: goto          38
      99: return

  private boolean shouldBeDeleted(java.lang.String, hudson.FilePath, hudson.model.Node) throws java.io.IOException, java.lang.InterruptedException;
    Code:
       0: invokestatic  #5                  // Method hudson/model/Hudson.getInstance:()Lhudson/model/Hudson;
       3: aload_1
       4: invokevirtual #39                 // Method hudson/model/Hudson.getItem:(Ljava/lang/String;)Lhudson/model/TopLevelItem;
       7: astore        4
       9: aload         4
      11: ifnonnull     46
      14: getstatic     #40                 // Field LOGGER:Ljava/util/logging/Logger;
      17: new           #41                 // class java/lang/StringBuilder
      20: dup
      21: invokespecial #42                 // Method java/lang/StringBuilder."<init>":()V
      24: ldc           #43                 // String Directory
      26: invokevirtual #44                 // Method java/lang/StringBuilder.append:(Ljava/lang/String;)Ljava/lang/StringBuilder;
      29: aload_2
      30: invokevirtual #45                 // Method java/lang/StringBuilder.append:(Ljava/lang/Object;)Ljava/lang/StringBuilder;
      33: ldc           #46                 // String  is not owned by any project
      35: invokevirtual #44                 // Method java/lang/StringBuilder.append:(Ljava/lang/String;)Ljava/lang/StringBuilder;
      38: invokevirtual #47                 // Method java/lang/StringBuilder.toString:()Ljava/lang/String;
      41: invokevirtual #48                 // Method java/util/logging/Logger.fine:(Ljava/lang/String;)V
      44: iconst_1
      45: ireturn
      46: aload_2
      47: invokevirtual #49                 // Method hudson/FilePath.exists:()Z
      50: ifne          55
      53: iconst_0
      54: ireturn
      55: aload         4
      57: instanceof    #50                 // class hudson/model/AbstractProject
      60: ifeq          128
      63: aload         4
      65: checkcast     #50                 // class hudson/model/AbstractProject
      68: astore        5
      70: aload         5
      72: invokevirtual #51                 // Method hudson/model/AbstractProject.getLastBuiltOn:()Lhudson/model/Node;
      75: astore        6
      77: aload         6
      79: ifnull        128
      82: aload         6
      84: aload_3
      85: invokevirtual #52                 // Method java/lang/Object.equals:(Ljava/lang/Object;)Z
      88: ifeq          128
      91: getstatic     #40                 // Field LOGGER:Ljava/util/logging/Logger;
      94: new           #41                 // class java/lang/StringBuilder
      97: dup
      98: invokespecial #42                 // Method java/lang/StringBuilder."<init>":()V
     101: ldc           #43                 // String Directory
     103: invokevirtual #44                 // Method java/lang/StringBuilder.append:(Ljava/lang/String;)Ljava/lang/StringBuilder;
     106: aload_2
     107: invokevirtual #45                 // Method java/lang/StringBuilder.append:(Ljava/lang/Object;)Ljava/lang/StringBuilder;
     110: ldc           #53                 // String  is the last workspace for
     112: invokevirtual #44                 // Method java/lang/StringBuilder.append:(Ljava/lang/String;)Ljava/lang/StringBuilder;
     115: aload         5
     117: invokevirtual #45                 // Method java/lang/StringBuilder.append:(Ljava/lang/Object;)Ljava/lang/StringBuilder;
     120: invokevirtual #47                 // Method java/lang/StringBuilder.toString:()Ljava/lang/String;
     123: invokevirtual #48                 // Method java/util/logging/Logger.fine:(Ljava/lang/String;)V
     126: iconst_0
     127: ireturn
     128: new           #54                 // class java/util/Date
     131: dup
     132: invokespecial #55                 // Method java/util/Date."<init>":()V
     135: invokevirtual #56                 // Method java/util/Date.getTime:()J
     138: lstore        5
     140: aload_2
     141: invokevirtual #57                 // Method hudson/FilePath.lastModified:()J
     144: ldc2_w        #58                 // long 2592000000l
     147: ladd
     148: lload         5
     150: lcmp
     151: ifge          158
     154: iconst_1
     155: goto          159
     158: iconst_0
     159: istore        7
     161: getstatic     #40                 // Field LOGGER:Ljava/util/logging/Logger;
     164: getstatic     #60                 // Field java/util/logging/Level.FINE:Ljava/util/logging/Level;
     167: invokevirtual #61                 // Method java/util/logging/Logger.isLoggable:(Ljava/util/logging/Level;)Z
     170: ifeq          241
     173: getstatic     #40                 // Field LOGGER:Ljava/util/logging/Logger;
     176: new           #41                 // class java/lang/StringBuilder
     179: dup
     180: invokespecial #42                 // Method java/lang/StringBuilder."<init>":()V
     183: ldc           #43                 // String Directory
     185: invokevirtual #44                 // Method java/lang/StringBuilder.append:(Ljava/lang/String;)Ljava/lang/StringBuilder;
     188: aload_2
     189: invokevirtual #45                 // Method java/lang/StringBuilder.append:(Ljava/lang/Object;)Ljava/lang/StringBuilder;
     192: ldc           #62                 // String  is
     194: invokevirtual #44                 // Method java/lang/StringBuilder.append:(Ljava/lang/String;)Ljava/lang/StringBuilder;
     197: lload         5
     199: aload_2
     200: invokevirtual #57                 // Method hudson/FilePath.lastModified:()J
     203: lsub
     204: invokestatic  #63                 // Method hudson/Util.getTimeSpanString:(J)Ljava/lang/String;
     207: invokevirtual #44                 // Method java/lang/StringBuilder.append:(Ljava/lang/String;)Ljava/lang/StringBuilder;
     210: ldc           #64                 // String  old, so
     212: invokevirtual #44                 // Method java/lang/StringBuilder.append:(Ljava/lang/String;)Ljava/lang/StringBuilder;
     215: iload         7
     217: ifeq          225
     220: ldc           #65                 // String
     222: goto          227
     225: ldc           #66                 // String NOT
     227: invokevirtual #44                 // Method java/lang/StringBuilder.append:(Ljava/lang/String;)Ljava/lang/StringBuilder;
     230: ldc           #67                 // String deleting
     232: invokevirtual #44                 // Method java/lang/StringBuilder.append:(Ljava/lang/String;)Ljava/lang/StringBuilder;
     235: invokevirtual #47                 // Method java/lang/StringBuilder.toString:()Ljava/lang/String;
     238: invokevirtual #48                 // Method java/util/logging/Logger.fine:(Ljava/lang/String;)V
     241: iload         7
     243: ireturn

  private void process(hudson.model.Slave) throws java.lang.InterruptedException;
    Code:
       0: aload_0
       1: getfield      #12                 // Field listener:Lhudson/util/StreamTaskListener;
       4: invokevirtual #68                 // Method hudson/util/StreamTaskListener.getLogger:()Ljava/io/PrintStream;
       7: new           #41                 // class java/lang/StringBuilder
      10: dup
      11: invokespecial #42                 // Method java/lang/StringBuilder."<init>":()V
      14: ldc           #69                 // String Scanning
      16: invokevirtual #44                 // Method java/lang/StringBuilder.append:(Ljava/lang/String;)Ljava/lang/StringBuilder;
      19: aload_1
      20: invokevirtual #70                 // Method hudson/model/Slave.getNodeName:()Ljava/lang/String;
      23: invokevirtual #44                 // Method java/lang/StringBuilder.append:(Ljava/lang/String;)Ljava/lang/StringBuilder;
      26: invokevirtual #47                 // Method java/lang/StringBuilder.toString:()Ljava/lang/String;
      29: invokevirtual #71                 // Method java/io/PrintStream.println:(Ljava/lang/String;)V
      32: aload_1
      33: invokevirtual #72                 // Method hudson/model/Slave.getWorkspaceRoot:()Lhudson/FilePath;
      36: getstatic     #31                 // Field DIR_FILTER:Ljava/io/FileFilter;
      39: invokevirtual #73                 // Method hudson/FilePath.list:(Ljava/io/FileFilter;)Ljava/util/List;
      42: astore_2
      43: aload_2
      44: ifnonnull     48
      47: return
      48: aload_2
      49: invokeinterface #14,  1           // InterfaceMethod java/util/List.iterator:()Ljava/util/Iterator;
      54: astore_3
      55: aload_3
      56: invokeinterface #15,  1           // InterfaceMethod java/util/Iterator.hasNext:()Z
      61: ifeq          99
      64: aload_3
      65: invokeinterface #16,  1           // InterfaceMethod java/util/Iterator.next:()Ljava/lang/Object;
      70: checkcast     #33                 // class hudson/FilePath
      73: astore        4
      75: aload_0
      76: aload         4
      78: invokevirtual #74                 // Method hudson/FilePath.getName:()Ljava/lang/String;
      81: aload         4
      83: aload_1
      84: invokespecial #37                 // Method shouldBeDeleted:(Ljava/lang/String;Lhudson/FilePath;Lhudson/model/Node;)Z
      87: ifeq          96
      90: aload_0
      91: aload         4
      93: invokespecial #38                 // Method delete:(Lhudson/FilePath;)V
      96: goto          55
      99: goto          136
     102: astore_2
     103: aload_2
     104: aload_0
     105: getfield      #12                 // Field listener:Lhudson/util/StreamTaskListener;
     108: new           #41                 // class java/lang/StringBuilder
     111: dup
     112: invokespecial #42                 // Method java/lang/StringBuilder."<init>":()V
     115: ldc           #75                 // String Failed on
     117: invokevirtual #44                 // Method java/lang/StringBuilder.append:(Ljava/lang/String;)Ljava/lang/StringBuilder;
     120: aload_1
     121: invokevirtual #70                 // Method hudson/model/Slave.getNodeName:()Ljava/lang/String;
     124: invokevirtual #44                 // Method java/lang/StringBuilder.append:(Ljava/lang/String;)Ljava/lang/StringBuilder;
     127: invokevirtual #47                 // Method java/lang/StringBuilder.toString:()Ljava/lang/String;
     130: invokevirtual #76                 // Method hudson/util/StreamTaskListener.error:(Ljava/lang/String;)Ljava/io/PrintWriter;
     133: invokevirtual #77                 // Method java/io/IOException.printStackTrace:(Ljava/io/PrintWriter;)V
     136: return
    Exception table:
       from    to  target type
          32    47   102   Class java/io/IOException
          48    99   102   Class java/io/IOException

  private void delete(hudson.FilePath) throws java.lang.InterruptedException;
    Code:
       0: aload_0
       1: getfield      #12                 // Field listener:Lhudson/util/StreamTaskListener;
       4: invokevirtual #68                 // Method hudson/util/StreamTaskListener.getLogger:()Ljava/io/PrintStream;
       7: new           #41                 // class java/lang/StringBuilder
      10: dup
      11: invokespecial #42                 // Method java/lang/StringBuilder."<init>":()V
      14: ldc           #78                 // String Deleting
      16: invokevirtual #44                 // Method java/lang/StringBuilder.append:(Ljava/lang/String;)Ljava/lang/StringBuilder;
      19: aload_1
      20: invokevirtual #45                 // Method java/lang/StringBuilder.append:(Ljava/lang/Object;)Ljava/lang/StringBuilder;
      23: invokevirtual #47                 // Method java/lang/StringBuilder.toString:()Ljava/lang/String;
      26: invokevirtual #71                 // Method java/io/PrintStream.println:(Ljava/lang/String;)V
      29: aload_1
      30: invokevirtual #79                 // Method hudson/FilePath.deleteRecursive:()V
      33: goto          67
      36: astore_2
      37: aload_2
      38: aload_0
      39: getfield      #12                 // Field listener:Lhudson/util/StreamTaskListener;
      42: new           #41                 // class java/lang/StringBuilder
      45: dup
      46: invokespecial #42                 // Method java/lang/StringBuilder."<init>":()V
      49: ldc           #80                 // String Failed to delete
      51: invokevirtual #44                 // Method java/lang/StringBuilder.append:(Ljava/lang/String;)Ljava/lang/StringBuilder;
      54: aload_1
      55: invokevirtual #45                 // Method java/lang/StringBuilder.append:(Ljava/lang/Object;)Ljava/lang/StringBuilder;
      58: invokevirtual #47                 // Method java/lang/StringBuilder.toString:()Ljava/lang/String;
      61: invokevirtual #76                 // Method hudson/util/StreamTaskListener.error:(Ljava/lang/String;)Ljava/io/PrintWriter;
      64: invokevirtual #77                 // Method java/io/IOException.printStackTrace:(Ljava/io/PrintWriter;)V
      67: return
    Exception table:
       from    to  target type
           0    33    36   Class java/io/IOException

  static {};
    Code:
       0: new           #81                 // class hudson/model/WorkspaceCleanupThread$DirectoryFilter
       3: dup
       4: aconst_null
       5: invokespecial #82                 // Method hudson/model/WorkspaceCleanupThread$DirectoryFilter."<init>":(Lhudson/model/WorkspaceCleanupThread$1;)V
       8: putstatic     #31                 // Field DIR_FILTER:Ljava/io/FileFilter;
      11: ldc_w         #83                 // class hudson/model/WorkspaceCleanupThread
      14: invokevirtual #84                 // Method java/lang/Class.getName:()Ljava/lang/String;
      17: invokestatic  #85                 // Method java/util/logging/Logger.getLogger:(Ljava/lang/String;)Ljava/util/logging/Logger;
      20: putstatic     #40                 // Field LOGGER:Ljava/util/logging/Logger;
      23: return
}
