Compiled from "AbstractIdleService.java"
class com.google.common.util.concurrent.AbstractIdleService$DelegateService$2 implements java.lang.Runnable {
  final com.google.common.util.concurrent.AbstractIdleService$DelegateService this$1;

  com.google.common.util.concurrent.AbstractIdleService$DelegateService$2(com.google.common.util.concurrent.AbstractIdleService$DelegateService);
    Code:
       0: aload_0
       1: aload_1
       2: putfield      #1                  // Field this$1:Lcom/google/common/util/concurrent/AbstractIdleService$DelegateService;
       5: aload_0
       6: invokespecial #2                  // Method java/lang/Object."<init>":()V
       9: return

  public void run();
    Code:
       0: aload_0
       1: getfield      #1                  // Field this$1:Lcom/google/common/util/concurrent/AbstractIdleService$DelegateService;
       4: getfield      #3                  // Field com/google/common/util/concurrent/AbstractIdleService$DelegateService.this$0:Lcom/google/common/util/concurrent/AbstractIdleService;
       7: invokevirtual #4                  // Method com/google/common/util/concurrent/AbstractIdleService.shutDown:()V
      10: aload_0
      11: getfield      #1                  // Field this$1:Lcom/google/common/util/concurrent/AbstractIdleService$DelegateService;
      14: invokevirtual #5                  // Method com/google/common/util/concurrent/AbstractIdleService$DelegateService.notifyStopped:()V
      17: goto          29
      20: astore_1
      21: aload_0
      22: getfield      #1                  // Field this$1:Lcom/google/common/util/concurrent/AbstractIdleService$DelegateService;
      25: aload_1
      26: invokevirtual #7                  // Method com/google/common/util/concurrent/AbstractIdleService$DelegateService.notifyFailed:(Ljava/lang/Throwable;)V
      29: return
    Exception table:
       from    to  target type
           0    17    20   Class java/lang/Throwable
}
