Compiled from "LogFactor5ErrorDialog.java"
class org.apache.log4j.lf5.viewer.LogFactor5ErrorDialog$1 implements java.awt.event.ActionListener {
  private final org.apache.log4j.lf5.viewer.LogFactor5ErrorDialog this$0;

  org.apache.log4j.lf5.viewer.LogFactor5ErrorDialog$1(org.apache.log4j.lf5.viewer.LogFactor5ErrorDialog);
    Code:
       0: aload_0
       1: aload_1
       2: putfield      #1                  // Field this$0:Lorg/apache/log4j/lf5/viewer/LogFactor5ErrorDialog;
       5: aload_0
       6: invokespecial #2                  // Method java/lang/Object."<init>":()V
       9: return

  public void actionPerformed(java.awt.event.ActionEvent);
    Code:
       0: aload_0
       1: getfield      #1                  // Field this$0:Lorg/apache/log4j/lf5/viewer/LogFactor5ErrorDialog;
       4: invokevirtual #3                  // Method org/apache/log4j/lf5/viewer/LogFactor5ErrorDialog.hide:()V
       7: return
}
