Compiled from "CompositeCancelable.scala"
public final class monix.execution.cancelables.CompositeCancelable$ implements scala.Serializable {
  public static final monix.execution.cancelables.CompositeCancelable$ MODULE$;

  public static {};
    Code:
       0: new           #2                  // class monix/execution/cancelables/CompositeCancelable$
       3: invokespecial #14                 // Method "<init>":()V
       6: return

  public monix.execution.cancelables.CompositeCancelable apply(scala.collection.Seq<monix.execution.Cancelable>);
    Code:
       0: aload_1
       1: invokeinterface #22,  1           // InterfaceMethod scala/collection/Seq.nonEmpty:()Z
       6: ifeq          25
       9: new           #24                 // class monix/execution/cancelables/CompositeCancelable
      12: dup
      13: aload_1
      14: invokeinterface #28,  1           // InterfaceMethod scala/collection/Seq.toSet:()Lscala/collection/immutable/Set;
      19: invokespecial #31                 // Method monix/execution/cancelables/CompositeCancelable."<init>":(Lscala/collection/immutable/Set;)V
      22: goto          41
      25: new           #24                 // class monix/execution/cancelables/CompositeCancelable
      28: dup
      29: getstatic     #36                 // Field scala/Predef$.MODULE$:Lscala/Predef$;
      32: invokevirtual #40                 // Method scala/Predef$.Set:()Lscala/collection/immutable/Set$;
      35: invokevirtual #45                 // Method scala/collection/immutable/Set$.empty:()Lscala/collection/immutable/Set;
      38: invokespecial #31                 // Method monix/execution/cancelables/CompositeCancelable."<init>":(Lscala/collection/immutable/Set;)V
      41: areturn

  private java.lang.Object readResolve();
    Code:
       0: getstatic     #52                 // Field MODULE$:Lmonix/execution/cancelables/CompositeCancelable$;
       3: areturn

  private monix.execution.cancelables.CompositeCancelable$();
    Code:
       0: aload_0
       1: invokespecial #53                 // Method java/lang/Object."<init>":()V
       4: aload_0
       5: putstatic     #52                 // Field MODULE$:Lmonix/execution/cancelables/CompositeCancelable$;
       8: return
}
