Compiled from "IntHyperRectangleN.scala"
public final class de.sciss.lucre.geom.IntHyperRectangleN implements de.sciss.lucre.geom.IntHyperRectangleNLike,scala.Product,java.io.Serializable {
  private final scala.collection.immutable.IndexedSeq<scala.Tuple2<java.lang.Object, java.lang.Object>> components;

  public static scala.Option<scala.collection.immutable.IndexedSeq<scala.Tuple2<java.lang.Object, java.lang.Object>>> unapply(de.sciss.lucre.geom.IntHyperRectangleN);
    Code:
       0: getstatic     #27                 // Field de/sciss/lucre/geom/IntHyperRectangleN$.MODULE$:Lde/sciss/lucre/geom/IntHyperRectangleN$;
       3: aload_0
       4: invokevirtual #29                 // Method de/sciss/lucre/geom/IntHyperRectangleN$.unapply:(Lde/sciss/lucre/geom/IntHyperRectangleN;)Lscala/Option;
       7: areturn

  public static de.sciss.lucre.geom.IntHyperRectangleN apply(scala.collection.immutable.IndexedSeq<scala.Tuple2<java.lang.Object, java.lang.Object>>);
    Code:
       0: getstatic     #27                 // Field de/sciss/lucre/geom/IntHyperRectangleN$.MODULE$:Lde/sciss/lucre/geom/IntHyperRectangleN$;
       3: aload_0
       4: invokevirtual #35                 // Method de/sciss/lucre/geom/IntHyperRectangleN$.apply:(Lscala/collection/immutable/IndexedSeq;)Lde/sciss/lucre/geom/IntHyperRectangleN;
       7: areturn

  public static <A> scala.Function1<scala.collection.immutable.IndexedSeq<scala.Tuple2<java.lang.Object, java.lang.Object>>, A> andThen(scala.Function1<de.sciss.lucre.geom.IntHyperRectangleN, A>);
    Code:
       0: getstatic     #27                 // Field de/sciss/lucre/geom/IntHyperRectangleN$.MODULE$:Lde/sciss/lucre/geom/IntHyperRectangleN$;
       3: aload_0
       4: invokevirtual #41                 // Method de/sciss/lucre/geom/IntHyperRectangleN$.andThen:(Lscala/Function1;)Lscala/Function1;
       7: areturn

  public static <A> scala.Function1<A, de.sciss.lucre.geom.IntHyperRectangleN> compose(scala.Function1<A, scala.collection.immutable.IndexedSeq<scala.Tuple2<java.lang.Object, java.lang.Object>>>);
    Code:
       0: getstatic     #27                 // Field de/sciss/lucre/geom/IntHyperRectangleN$.MODULE$:Lde/sciss/lucre/geom/IntHyperRectangleN$;
       3: aload_0
       4: invokevirtual #46                 // Method de/sciss/lucre/geom/IntHyperRectangleN$.compose:(Lscala/Function1;)Lscala/Function1;
       7: areturn

  public scala.collection.Iterator<java.lang.String> productElementNames();
    Code:
       0: aload_0
       1: invokestatic  #53                 // InterfaceMethod scala/Product.productElementNames$:(Lscala/Product;)Lscala/collection/Iterator;
       4: areturn

  public final boolean containsP(de.sciss.lucre.geom.IntPointNLike);
    Code:
       0: aload_0
       1: aload_1
       2: invokestatic  #61                 // InterfaceMethod de/sciss/lucre/geom/IntHyperRectangleNLike.containsP$:(Lde/sciss/lucre/geom/IntHyperRectangleNLike;Lde/sciss/lucre/geom/IntPointNLike;)Z
       5: ireturn

  public final scala.math.BigInt overlapArea(de.sciss.lucre.geom.IntHyperCubeN);
    Code:
       0: aload_0
       1: aload_1
       2: invokestatic  #69                 // InterfaceMethod de/sciss/lucre/geom/IntHyperRectangleNLike.overlapArea$:(Lde/sciss/lucre/geom/IntHyperRectangleNLike;Lde/sciss/lucre/geom/IntHyperCubeN;)Lscala/math/BigInt;
       5: areturn

  public final boolean isAreaGreater(de.sciss.lucre.geom.IntHyperCubeN, scala.math.BigInt);
    Code:
       0: aload_0
       1: aload_1
       2: aload_2
       3: invokestatic  #77                 // InterfaceMethod de/sciss/lucre/geom/IntHyperRectangleNLike.isAreaGreater$:(Lde/sciss/lucre/geom/IntHyperRectangleNLike;Lde/sciss/lucre/geom/IntHyperCubeN;Lscala/math/BigInt;)Z
       6: ireturn

  public final boolean isAreaNonEmpty(scala.math.BigInt);
    Code:
       0: aload_0
       1: aload_1
       2: invokestatic  #85                 // InterfaceMethod de/sciss/lucre/geom/IntHyperRectangleNLike.isAreaNonEmpty$:(Lde/sciss/lucre/geom/IntHyperRectangleNLike;Lscala/math/BigInt;)Z
       5: ireturn

  public scala.collection.immutable.IndexedSeq<scala.Tuple2<java.lang.Object, java.lang.Object>> components();
    Code:
       0: aload_0
       1: getfield      #89                 // Field components:Lscala/collection/immutable/IndexedSeq;
       4: areturn

  public int dim();
    Code:
       0: aload_0
       1: invokevirtual #93                 // Method components:()Lscala/collection/immutable/IndexedSeq;
       4: invokeinterface #98,  1           // InterfaceMethod scala/collection/immutable/IndexedSeq.size:()I
       9: ireturn

  public int min(int);
    Code:
       0: aload_0
       1: invokevirtual #93                 // Method components:()Lscala/collection/immutable/IndexedSeq;
       4: iload_1
       5: invokeinterface #103,  2          // InterfaceMethod scala/collection/immutable/IndexedSeq.apply:(I)Ljava/lang/Object;
      10: checkcast     #105                // class scala/Tuple2
      13: invokevirtual #108                // Method scala/Tuple2._1$mcI$sp:()I
      16: ireturn

  public int max(int);
    Code:
       0: aload_0
       1: invokevirtual #93                 // Method components:()Lscala/collection/immutable/IndexedSeq;
       4: iload_1
       5: invokeinterface #103,  2          // InterfaceMethod scala/collection/immutable/IndexedSeq.apply:(I)Ljava/lang/Object;
      10: checkcast     #105                // class scala/Tuple2
      13: invokevirtual #108                // Method scala/Tuple2._1$mcI$sp:()I
      16: ireturn

  public de.sciss.lucre.geom.IntHyperRectangleN copy(scala.collection.immutable.IndexedSeq<scala.Tuple2<java.lang.Object, java.lang.Object>>);
    Code:
       0: new           #2                  // class de/sciss/lucre/geom/IntHyperRectangleN
       3: dup
       4: aload_1
       5: invokespecial #115                // Method "<init>":(Lscala/collection/immutable/IndexedSeq;)V
       8: areturn

  public scala.collection.immutable.IndexedSeq<scala.Tuple2<java.lang.Object, java.lang.Object>> copy$default$1();
    Code:
       0: aload_0
       1: invokevirtual #93                 // Method components:()Lscala/collection/immutable/IndexedSeq;
       4: areturn

  public java.lang.String productPrefix();
    Code:
       0: ldc           #120                // String IntHyperRectangleN
       2: areturn

  public int productArity();
    Code:
       0: iconst_1
       1: ireturn

  public java.lang.Object productElement(int);
    Code:
       0: iload_1
       1: istore_2
       2: iload_2
       3: tableswitch   { // 0 to 0
                     0: 20
               default: 27
          }
      20: aload_0
      21: invokevirtual #93                 // Method components:()Lscala/collection/immutable/IndexedSeq;
      24: goto          34
      27: iload_1
      28: invokestatic  #128                // Method scala/runtime/Statics.ioobe:(I)Ljava/lang/Object;
      31: goto          34
      34: areturn

  public scala.collection.Iterator<java.lang.Object> productIterator();
    Code:
       0: getstatic     #135                // Field scala/runtime/ScalaRunTime$.MODULE$:Lscala/runtime/ScalaRunTime$;
       3: aload_0
       4: invokevirtual #138                // Method scala/runtime/ScalaRunTime$.typedProductIterator:(Lscala/Product;)Lscala/collection/Iterator;
       7: areturn

  public boolean canEqual(java.lang.Object);
    Code:
       0: aload_1
       1: instanceof    #2                  // class de/sciss/lucre/geom/IntHyperRectangleN
       4: ireturn

  public java.lang.String productElementName(int);
    Code:
       0: iload_1
       1: istore_2
       2: iload_2
       3: tableswitch   { // 0 to 0
                     0: 20
               default: 25
          }
      20: ldc           #144                // String components
      22: goto          35
      25: iload_1
      26: invokestatic  #128                // Method scala/runtime/Statics.ioobe:(I)Ljava/lang/Object;
      29: checkcast     #146                // class java/lang/String
      32: goto          35
      35: areturn

  public int hashCode();
    Code:
       0: getstatic     #135                // Field scala/runtime/ScalaRunTime$.MODULE$:Lscala/runtime/ScalaRunTime$;
       3: aload_0
       4: invokevirtual #151                // Method scala/runtime/ScalaRunTime$._hashCode:(Lscala/Product;)I
       7: ireturn

  public java.lang.String toString();
    Code:
       0: getstatic     #135                // Field scala/runtime/ScalaRunTime$.MODULE$:Lscala/runtime/ScalaRunTime$;
       3: aload_0
       4: invokevirtual #156                // Method scala/runtime/ScalaRunTime$._toString:(Lscala/Product;)Ljava/lang/String;
       7: areturn

  public boolean equals(java.lang.Object);
    Code:
       0: aload_0
       1: aload_1
       2: if_acmpeq     77
       5: aload_1
       6: astore_3
       7: aload_3
       8: instanceof    #2                  // class de/sciss/lucre/geom/IntHyperRectangleN
      11: ifeq          19
      14: iconst_1
      15: istore_2
      16: goto          27
      19: goto          22
      22: iconst_0
      23: istore_2
      24: goto          27
      27: iload_2
      28: ifeq          81
      31: aload_1
      32: checkcast     #2                  // class de/sciss/lucre/geom/IntHyperRectangleN
      35: astore        4
      37: aload_0
      38: invokevirtual #93                 // Method components:()Lscala/collection/immutable/IndexedSeq;
      41: aload         4
      43: invokevirtual #93                 // Method components:()Lscala/collection/immutable/IndexedSeq;
      46: astore        5
      48: dup
      49: ifnonnull     61
      52: pop
      53: aload         5
      55: ifnull        69
      58: goto          73
      61: aload         5
      63: invokevirtual #159                // Method java/lang/Object.equals:(Ljava/lang/Object;)Z
      66: ifeq          73
      69: iconst_1
      70: goto          74
      73: iconst_0
      74: ifeq          81
      77: iconst_1
      78: goto          82
      81: iconst_0
      82: ireturn

  public final boolean isAreaNonEmpty(java.lang.Object);
    Code:
       0: aload_0
       1: aload_1
       2: checkcast     #161                // class scala/math/BigInt
       5: invokevirtual #163                // Method isAreaNonEmpty:(Lscala/math/BigInt;)Z
       8: ireturn

  public final boolean isAreaGreater(java.lang.Object, java.lang.Object);
    Code:
       0: aload_0
       1: aload_1
       2: checkcast     #166                // class de/sciss/lucre/geom/IntHyperCubeN
       5: aload_2
       6: checkcast     #161                // class scala/math/BigInt
       9: invokevirtual #168                // Method isAreaGreater:(Lde/sciss/lucre/geom/IntHyperCubeN;Lscala/math/BigInt;)Z
      12: ireturn

  public final java.lang.Object overlapArea(java.lang.Object);
    Code:
       0: aload_0
       1: aload_1
       2: checkcast     #166                // class de/sciss/lucre/geom/IntHyperCubeN
       5: invokevirtual #172                // Method overlapArea:(Lde/sciss/lucre/geom/IntHyperCubeN;)Lscala/math/BigInt;
       8: areturn

  public final boolean containsP(java.lang.Object);
    Code:
       0: aload_0
       1: aload_1
       2: checkcast     #175                // class de/sciss/lucre/geom/IntPointNLike
       5: invokevirtual #177                // Method containsP:(Lde/sciss/lucre/geom/IntPointNLike;)Z
       8: ireturn

  public de.sciss.lucre.geom.IntHyperRectangleN(scala.collection.immutable.IndexedSeq<scala.Tuple2<java.lang.Object, java.lang.Object>>);
    Code:
       0: aload_0
       1: aload_1
       2: putfield      #89                 // Field components:Lscala/collection/immutable/IndexedSeq;
       5: aload_0
       6: invokespecial #181                // Method java/lang/Object."<init>":()V
       9: aload_0
      10: invokestatic  #185                // InterfaceMethod de/sciss/lucre/geom/IntHyperRectangleNLike.$init$:(Lde/sciss/lucre/geom/IntHyperRectangleNLike;)V
      13: aload_0
      14: invokestatic  #188                // InterfaceMethod scala/Product.$init$:(Lscala/Product;)V
      17: return
}
