Compiled from "IntSpace.scala"
public class de.sciss.lucre.geom.IntSpace$TwoDim$ implements de.sciss.lucre.geom.IntSpace$TwoDim {
  public static final de.sciss.lucre.geom.IntSpace$TwoDim$ MODULE$;

  private static final de.sciss.lucre.geom.IntPoint2D maxPoint;

  public static {};
    Code:
       0: new           #2                  // class de/sciss/lucre/geom/IntSpace$TwoDim$
       3: dup
       4: invokespecial #29                 // Method "<init>":()V
       7: putstatic     #31                 // Field MODULE$:Lde/sciss/lucre/geom/IntSpace$TwoDim$;
      10: new           #33                 // class de/sciss/lucre/geom/IntPoint2D
      13: dup
      14: ldc           #34                 // int 2147483647
      16: ldc           #34                 // int 2147483647
      18: invokespecial #37                 // Method de/sciss/lucre/geom/IntPoint2D."<init>":(II)V
      21: putstatic     #39                 // Field maxPoint:Lde/sciss/lucre/geom/IntPoint2D;
      24: return

  public de.sciss.lucre.geom.IntSpace$TwoDim$lexicalOrder$ lexicalOrder();
    Code:
       0: getstatic     #44                 // Field de/sciss/lucre/geom/IntSpace$TwoDim$lexicalOrder$.MODULE$:Lde/sciss/lucre/geom/IntSpace$TwoDim$lexicalOrder$;
       3: areturn

  public de.sciss.lucre.geom.IntSpace$TwoDim$pointFormat$ pointFormat();
    Code:
       0: getstatic     #50                 // Field de/sciss/lucre/geom/IntSpace$TwoDim$pointFormat$.MODULE$:Lde/sciss/lucre/geom/IntSpace$TwoDim$pointFormat$;
       3: areturn

  public de.sciss.lucre.geom.IntSpace$TwoDim$hyperCubeFormat$ hyperCubeFormat();
    Code:
       0: getstatic     #55                 // Field de/sciss/lucre/geom/IntSpace$TwoDim$hyperCubeFormat$.MODULE$:Lde/sciss/lucre/geom/IntSpace$TwoDim$hyperCubeFormat$;
       3: areturn

  public final de.sciss.lucre.geom.IntPoint2D maxPoint();
    Code:
       0: getstatic     #39                 // Field maxPoint:Lde/sciss/lucre/geom/IntPoint2D;
       3: areturn

  public final int dim();
    Code:
       0: iconst_2
       1: ireturn

  public final java.lang.Object maxPoint();
    Code:
       0: aload_0
       1: invokevirtual #61                 // Method maxPoint:()Lde/sciss/lucre/geom/IntPoint2D;
       4: areturn

  public de.sciss.serial.ConstFormat hyperCubeFormat();
    Code:
       0: aload_0
       1: invokevirtual #64                 // Method hyperCubeFormat:()Lde/sciss/lucre/geom/IntSpace$TwoDim$hyperCubeFormat$;
       4: areturn

  public de.sciss.serial.ConstFormat pointFormat();
    Code:
       0: aload_0
       1: invokevirtual #66                 // Method pointFormat:()Lde/sciss/lucre/geom/IntSpace$TwoDim$pointFormat$;
       4: areturn

  public scala.math.Ordering lexicalOrder();
    Code:
       0: aload_0
       1: invokevirtual #69                 // Method lexicalOrder:()Lde/sciss/lucre/geom/IntSpace$TwoDim$lexicalOrder$;
       4: areturn

  public de.sciss.lucre.geom.IntSpace$TwoDim$();
    Code:
       0: aload_0
       1: invokespecial #70                 // Method java/lang/Object."<init>":()V
       4: return
}
