Compiled from "JsonSmartMappingProvider.java"
class com.jayway.jsonpath.spi.mapper.JsonSmartMappingProvider$1 implements java.util.concurrent.Callable<net.minidev.json.writer.JsonReader> {
  final net.minidev.json.writer.JsonReader val$jsonReader;

  com.jayway.jsonpath.spi.mapper.JsonSmartMappingProvider$1(net.minidev.json.writer.JsonReader);
    Code:
       0: aload_0
       1: aload_1
       2: putfield      #1                  // Field val$jsonReader:Lnet/minidev/json/writer/JsonReader;
       5: aload_0
       6: invokespecial #2                  // Method java/lang/Object."<init>":()V
       9: return

  public net.minidev.json.writer.JsonReader call();
    Code:
       0: aload_0
       1: getfield      #1                  // Field val$jsonReader:Lnet/minidev/json/writer/JsonReader;
       4: areturn

  public java.lang.Object call() throws java.lang.Exception;
    Code:
       0: aload_0
       1: invokevirtual #3                  // Method call:()Lnet/minidev/json/writer/JsonReader;
       4: areturn
}
