Compiled from "AttributeExtensibleImpl.java"
public class org.apache.woden.internal.wsdl20.extensions.AttributeExtensibleImpl implements org.apache.woden.wsdl20.extensions.AttributeExtensible {
  private java.util.Map fExtAttributes;

  public org.apache.woden.internal.wsdl20.extensions.AttributeExtensibleImpl();
    Code:
       0: aload_0
       1: invokespecial #1                  // Method java/lang/Object."<init>":()V
       4: aload_0
       5: new           #2                  // class java/util/HashMap
       8: dup
       9: invokespecial #3                  // Method java/util/HashMap."<init>":()V
      12: putfield      #4                  // Field fExtAttributes:Ljava/util/Map;
      15: return

  public void setExtensionAttribute(javax.xml.namespace.QName, org.apache.woden.xml.XMLAttr);
    Code:
       0: aload_1
       1: ifnull        34
       4: aload_2
       5: ifnull        23
       8: aload_0
       9: getfield      #4                  // Field fExtAttributes:Ljava/util/Map;
      12: aload_1
      13: aload_2
      14: invokeinterface #5,  3            // InterfaceMethod java/util/Map.put:(Ljava/lang/Object;Ljava/lang/Object;)Ljava/lang/Object;
      19: pop
      20: goto          34
      23: aload_0
      24: getfield      #4                  // Field fExtAttributes:Ljava/util/Map;
      27: aload_1
      28: invokeinterface #6,  2            // InterfaceMethod java/util/Map.remove:(Ljava/lang/Object;)Ljava/lang/Object;
      33: pop
      34: return

  public org.apache.woden.xml.XMLAttr getExtensionAttribute(javax.xml.namespace.QName);
    Code:
       0: aload_1
       1: ifnull        18
       4: aload_0
       5: getfield      #4                  // Field fExtAttributes:Ljava/util/Map;
       8: aload_1
       9: invokeinterface #7,  2            // InterfaceMethod java/util/Map.get:(Ljava/lang/Object;)Ljava/lang/Object;
      14: checkcast     #8                  // class org/apache/woden/xml/XMLAttr
      17: areturn
      18: aconst_null
      19: areturn

  public org.apache.woden.xml.XMLAttr[] getExtensionAttributesForNamespace(java.net.URI);
    Code:
       0: aload_1
       1: ifnull        115
       4: aload_1
       5: invokevirtual #9                  // Method java/net/URI.toString:()Ljava/lang/String;
       8: astore_2
       9: new           #10                 // class java/util/Vector
      12: dup
      13: invokespecial #11                 // Method java/util/Vector."<init>":()V
      16: astore_3
      17: aload_0
      18: getfield      #4                  // Field fExtAttributes:Ljava/util/Map;
      21: invokeinterface #12,  1           // InterfaceMethod java/util/Map.keySet:()Ljava/util/Set;
      26: astore        4
      28: aload         4
      30: invokeinterface #13,  1           // InterfaceMethod java/util/Collection.iterator:()Ljava/util/Iterator;
      35: astore        5
      37: aload         5
      39: invokeinterface #14,  1           // InterfaceMethod java/util/Iterator.hasNext:()Z
      44: ifeq          92
      47: aload         5
      49: invokeinterface #15,  1           // InterfaceMethod java/util/Iterator.next:()Ljava/lang/Object;
      54: checkcast     #16                 // class javax/xml/namespace/QName
      57: astore        6
      59: aload         6
      61: invokevirtual #17                 // Method javax/xml/namespace/QName.getNamespaceURI:()Ljava/lang/String;
      64: aload_2
      65: invokevirtual #18                 // Method java/lang/String.equals:(Ljava/lang/Object;)Z
      68: ifeq          89
      71: aload_3
      72: aload_0
      73: getfield      #4                  // Field fExtAttributes:Ljava/util/Map;
      76: aload         6
      78: invokeinterface #7,  2            // InterfaceMethod java/util/Map.get:(Ljava/lang/Object;)Ljava/lang/Object;
      83: invokeinterface #19,  2           // InterfaceMethod java/util/List.add:(Ljava/lang/Object;)Z
      88: pop
      89: goto          37
      92: aload_3
      93: invokeinterface #20,  1           // InterfaceMethod java/util/List.size:()I
      98: anewarray     #8                  // class org/apache/woden/xml/XMLAttr
     101: astore        5
     103: aload_3
     104: aload         5
     106: invokeinterface #21,  2           // InterfaceMethod java/util/List.toArray:([Ljava/lang/Object;)[Ljava/lang/Object;
     111: pop
     112: aload         5
     114: areturn
     115: iconst_0
     116: anewarray     #8                  // class org/apache/woden/xml/XMLAttr
     119: areturn

  public org.apache.woden.xml.XMLAttr[] getExtensionAttributes();
    Code:
       0: aload_0
       1: getfield      #4                  // Field fExtAttributes:Ljava/util/Map;
       4: invokeinterface #22,  1           // InterfaceMethod java/util/Map.values:()Ljava/util/Collection;
       9: astore_1
      10: aload_1
      11: invokeinterface #23,  1           // InterfaceMethod java/util/Collection.size:()I
      16: anewarray     #8                  // class org/apache/woden/xml/XMLAttr
      19: astore_2
      20: aload_1
      21: aload_2
      22: invokeinterface #24,  2           // InterfaceMethod java/util/Collection.toArray:([Ljava/lang/Object;)[Ljava/lang/Object;
      27: pop
      28: aload_2
      29: areturn

  public boolean hasExtensionAttributesForNamespace(java.net.URI);
    Code:
       0: iconst_0
       1: istore_2
       2: aload_1
       3: ifnull        73
       6: aload_1
       7: invokevirtual #9                  // Method java/net/URI.toString:()Ljava/lang/String;
      10: astore_3
      11: aload_0
      12: getfield      #4                  // Field fExtAttributes:Ljava/util/Map;
      15: invokeinterface #12,  1           // InterfaceMethod java/util/Map.keySet:()Ljava/util/Set;
      20: astore        4
      22: aload         4
      24: invokeinterface #13,  1           // InterfaceMethod java/util/Collection.iterator:()Ljava/util/Iterator;
      29: astore        5
      31: aload         5
      33: invokeinterface #14,  1           // InterfaceMethod java/util/Iterator.hasNext:()Z
      38: ifeq          73
      41: aload         5
      43: invokeinterface #15,  1           // InterfaceMethod java/util/Iterator.next:()Ljava/lang/Object;
      48: checkcast     #16                 // class javax/xml/namespace/QName
      51: astore        6
      53: aload_3
      54: aload         6
      56: invokevirtual #17                 // Method javax/xml/namespace/QName.getNamespaceURI:()Ljava/lang/String;
      59: invokevirtual #18                 // Method java/lang/String.equals:(Ljava/lang/Object;)Z
      62: ifeq          70
      65: iconst_1
      66: istore_2
      67: goto          73
      70: goto          31
      73: iload_2
      74: ireturn
}
