Compiled from "MyCurrency.java"
public final class org.apache.camel.component.bean.MyCurrency {
  private java.lang.String symbol;

  public org.apache.camel.component.bean.MyCurrency(java.lang.String);
    Code:
       0: aload_0
       1: invokespecial #12                 // Method java/lang/Object."<init>":()V
       4: aload_0
       5: aload_1
       6: putfield      #14                 // Field symbol:Ljava/lang/String;
       9: return

  public java.lang.String getSymbol();
    Code:
       0: aload_0
       1: getfield      #14                 // Field symbol:Ljava/lang/String;
       4: areturn
}
