Compiled from "PackageDefinitionStrategy.java"
public final class net.bytebuddy.dynamic.loading.PackageDefinitionStrategy$ManifestReading$SealBaseLocator$NonSealing extends java.lang.Enum<net.bytebuddy.dynamic.loading.PackageDefinitionStrategy$ManifestReading$SealBaseLocator$NonSealing> implements net.bytebuddy.dynamic.loading.PackageDefinitionStrategy$ManifestReading$SealBaseLocator {
  public static final net.bytebuddy.dynamic.loading.PackageDefinitionStrategy$ManifestReading$SealBaseLocator$NonSealing INSTANCE;

  private static final net.bytebuddy.dynamic.loading.PackageDefinitionStrategy$ManifestReading$SealBaseLocator$NonSealing[] $VALUES;

  public static net.bytebuddy.dynamic.loading.PackageDefinitionStrategy$ManifestReading$SealBaseLocator$NonSealing[] values();
    Code:
       0: getstatic     #23                 // Field $VALUES:[Lnet/bytebuddy/dynamic/loading/PackageDefinitionStrategy$ManifestReading$SealBaseLocator$NonSealing;
       3: invokevirtual #28                 // Method "[Lnet/bytebuddy/dynamic/loading/PackageDefinitionStrategy$ManifestReading$SealBaseLocator$NonSealing;".clone:()Ljava/lang/Object;
       6: checkcast     #24                 // class "[Lnet/bytebuddy/dynamic/loading/PackageDefinitionStrategy$ManifestReading$SealBaseLocator$NonSealing;"
       9: areturn

  public static net.bytebuddy.dynamic.loading.PackageDefinitionStrategy$ManifestReading$SealBaseLocator$NonSealing valueOf(java.lang.String);
    Code:
       0: ldc           #2                  // class net/bytebuddy/dynamic/loading/PackageDefinitionStrategy$ManifestReading$SealBaseLocator$NonSealing
       2: aload_0
       3: invokestatic  #33                 // Method java/lang/Enum.valueOf:(Ljava/lang/Class;Ljava/lang/String;)Ljava/lang/Enum;
       6: checkcast     #2                  // class net/bytebuddy/dynamic/loading/PackageDefinitionStrategy$ManifestReading$SealBaseLocator$NonSealing
       9: areturn

  private net.bytebuddy.dynamic.loading.PackageDefinitionStrategy$ManifestReading$SealBaseLocator$NonSealing();
    Code:
       0: aload_0
       1: aload_1
       2: iload_2
       3: invokespecial #39                 // Method java/lang/Enum."<init>":(Ljava/lang/String;I)V
       6: return

  public java.net.URL findSealBase(java.lang.ClassLoader, java.lang.String);
    Code:
       0: invokestatic  #46                 // Method net/bytebuddy/dynamic/loading/PackageDefinitionStrategy$ManifestReading.access$000:()Ljava/net/URL;
       3: areturn

  static {};
    Code:
       0: new           #2                  // class net/bytebuddy/dynamic/loading/PackageDefinitionStrategy$ManifestReading$SealBaseLocator$NonSealing
       3: dup
       4: ldc           #52                 // String INSTANCE
       6: iconst_0
       7: invokespecial #53                 // Method "<init>":(Ljava/lang/String;I)V
      10: putstatic     #55                 // Field INSTANCE:Lnet/bytebuddy/dynamic/loading/PackageDefinitionStrategy$ManifestReading$SealBaseLocator$NonSealing;
      13: iconst_1
      14: anewarray     #2                  // class net/bytebuddy/dynamic/loading/PackageDefinitionStrategy$ManifestReading$SealBaseLocator$NonSealing
      17: dup
      18: iconst_0
      19: getstatic     #55                 // Field INSTANCE:Lnet/bytebuddy/dynamic/loading/PackageDefinitionStrategy$ManifestReading$SealBaseLocator$NonSealing;
      22: aastore
      23: putstatic     #23                 // Field $VALUES:[Lnet/bytebuddy/dynamic/loading/PackageDefinitionStrategy$ManifestReading$SealBaseLocator$NonSealing;
      26: return
}
