Compiled from "ByteProcessor.java"
final class io.netty.util.ByteProcessor$2 implements io.netty.util.ByteProcessor {
  io.netty.util.ByteProcessor$2();
    Code:
       0: aload_0
       1: invokespecial #11                 // Method java/lang/Object."<init>":()V
       4: return

  public boolean process(byte);
    Code:
       0: iload_1
       1: bipush        13
       3: if_icmpeq     12
       6: iload_1
       7: bipush        10
       9: if_icmpne     16
      12: iconst_1
      13: goto          17
      16: iconst_0
      17: ireturn
}
