Compiled from "JSONValue.java"
public class org.jose4j.json.internal.json_simple.JSONValue {
  public org.jose4j.json.internal.json_simple.JSONValue();
    Code:
       0: aload_0
       1: invokespecial #1                  // Method java/lang/Object."<init>":()V
       4: return

  public static java.lang.Object parse(java.io.Reader);
    Code:
       0: new           #2                  // class org/jose4j/json/internal/json_simple/parser/JSONParser
       3: dup
       4: invokespecial #3                  // Method org/jose4j/json/internal/json_simple/parser/JSONParser."<init>":()V
       7: astore_1
       8: aload_1
       9: aload_0
      10: invokevirtual #4                  // Method org/jose4j/json/internal/json_simple/parser/JSONParser.parse:(Ljava/io/Reader;)Ljava/lang/Object;
      13: areturn
      14: astore_1
      15: aconst_null
      16: areturn
    Exception table:
       from    to  target type
           0    13    14   Class java/lang/Exception

  public static java.lang.Object parse(java.lang.String);
    Code:
       0: new           #6                  // class java/io/StringReader
       3: dup
       4: aload_0
       5: invokespecial #7                  // Method java/io/StringReader."<init>":(Ljava/lang/String;)V
       8: astore_1
       9: aload_1
      10: invokestatic  #8                  // Method parse:(Ljava/io/Reader;)Ljava/lang/Object;
      13: areturn

  public static java.lang.Object parseWithException(java.io.Reader) throws java.io.IOException, org.jose4j.json.internal.json_simple.parser.ParseException;
    Code:
       0: new           #2                  // class org/jose4j/json/internal/json_simple/parser/JSONParser
       3: dup
       4: invokespecial #3                  // Method org/jose4j/json/internal/json_simple/parser/JSONParser."<init>":()V
       7: astore_1
       8: aload_1
       9: aload_0
      10: invokevirtual #4                  // Method org/jose4j/json/internal/json_simple/parser/JSONParser.parse:(Ljava/io/Reader;)Ljava/lang/Object;
      13: areturn

  public static java.lang.Object parseWithException(java.lang.String) throws org.jose4j.json.internal.json_simple.parser.ParseException;
    Code:
       0: new           #2                  // class org/jose4j/json/internal/json_simple/parser/JSONParser
       3: dup
       4: invokespecial #3                  // Method org/jose4j/json/internal/json_simple/parser/JSONParser."<init>":()V
       7: astore_1
       8: aload_1
       9: aload_0
      10: invokevirtual #9                  // Method org/jose4j/json/internal/json_simple/parser/JSONParser.parse:(Ljava/lang/String;)Ljava/lang/Object;
      13: areturn

  public static void writeJSONString(java.lang.Object, java.io.Writer) throws java.io.IOException;
    Code:
       0: aload_0
       1: ifnonnull     11
       4: aload_1
       5: ldc           #10                 // String null
       7: invokevirtual #11                 // Method java/io/Writer.write:(Ljava/lang/String;)V
      10: return
      11: aload_0
      12: instanceof    #12                 // class java/lang/String
      15: ifeq          42
      18: aload_1
      19: bipush        34
      21: invokevirtual #13                 // Method java/io/Writer.write:(I)V
      24: aload_1
      25: aload_0
      26: checkcast     #12                 // class java/lang/String
      29: invokestatic  #14                 // Method escape:(Ljava/lang/String;)Ljava/lang/String;
      32: invokevirtual #11                 // Method java/io/Writer.write:(Ljava/lang/String;)V
      35: aload_1
      36: bipush        34
      38: invokevirtual #13                 // Method java/io/Writer.write:(I)V
      41: return
      42: aload_0
      43: instanceof    #15                 // class java/lang/Double
      46: ifeq          87
      49: aload_0
      50: checkcast     #15                 // class java/lang/Double
      53: invokevirtual #16                 // Method java/lang/Double.isInfinite:()Z
      56: ifne          69
      59: aload_0
      60: checkcast     #15                 // class java/lang/Double
      63: invokevirtual #17                 // Method java/lang/Double.isNaN:()Z
      66: ifeq          78
      69: aload_1
      70: ldc           #10                 // String null
      72: invokevirtual #11                 // Method java/io/Writer.write:(Ljava/lang/String;)V
      75: goto          86
      78: aload_1
      79: aload_0
      80: invokevirtual #18                 // Method java/lang/Object.toString:()Ljava/lang/String;
      83: invokevirtual #11                 // Method java/io/Writer.write:(Ljava/lang/String;)V
      86: return
      87: aload_0
      88: instanceof    #19                 // class java/lang/Float
      91: ifeq          132
      94: aload_0
      95: checkcast     #19                 // class java/lang/Float
      98: invokevirtual #20                 // Method java/lang/Float.isInfinite:()Z
     101: ifne          114
     104: aload_0
     105: checkcast     #19                 // class java/lang/Float
     108: invokevirtual #21                 // Method java/lang/Float.isNaN:()Z
     111: ifeq          123
     114: aload_1
     115: ldc           #10                 // String null
     117: invokevirtual #11                 // Method java/io/Writer.write:(Ljava/lang/String;)V
     120: goto          131
     123: aload_1
     124: aload_0
     125: invokevirtual #18                 // Method java/lang/Object.toString:()Ljava/lang/String;
     128: invokevirtual #11                 // Method java/io/Writer.write:(Ljava/lang/String;)V
     131: return
     132: aload_0
     133: instanceof    #22                 // class java/lang/Number
     136: ifeq          148
     139: aload_1
     140: aload_0
     141: invokevirtual #18                 // Method java/lang/Object.toString:()Ljava/lang/String;
     144: invokevirtual #11                 // Method java/io/Writer.write:(Ljava/lang/String;)V
     147: return
     148: aload_0
     149: instanceof    #23                 // class java/lang/Boolean
     152: ifeq          164
     155: aload_1
     156: aload_0
     157: invokevirtual #18                 // Method java/lang/Object.toString:()Ljava/lang/String;
     160: invokevirtual #11                 // Method java/io/Writer.write:(Ljava/lang/String;)V
     163: return
     164: aload_0
     165: instanceof    #24                 // class org/jose4j/json/internal/json_simple/JSONStreamAware
     168: ifeq          182
     171: aload_0
     172: checkcast     #24                 // class org/jose4j/json/internal/json_simple/JSONStreamAware
     175: aload_1
     176: invokeinterface #25,  2           // InterfaceMethod org/jose4j/json/internal/json_simple/JSONStreamAware.writeJSONString:(Ljava/io/Writer;)V
     181: return
     182: aload_0
     183: instanceof    #26                 // class org/jose4j/json/internal/json_simple/JSONAware
     186: ifeq          203
     189: aload_1
     190: aload_0
     191: checkcast     #26                 // class org/jose4j/json/internal/json_simple/JSONAware
     194: invokeinterface #27,  1           // InterfaceMethod org/jose4j/json/internal/json_simple/JSONAware.toJSONString:()Ljava/lang/String;
     199: invokevirtual #11                 // Method java/io/Writer.write:(Ljava/lang/String;)V
     202: return
     203: aload_0
     204: instanceof    #28                 // class java/util/Map
     207: ifeq          219
     210: aload_0
     211: checkcast     #28                 // class java/util/Map
     214: aload_1
     215: invokestatic  #29                 // Method org/jose4j/json/internal/json_simple/JSONObject.writeJSONString:(Ljava/util/Map;Ljava/io/Writer;)V
     218: return
     219: aload_0
     220: instanceof    #30                 // class java/util/Collection
     223: ifeq          235
     226: aload_0
     227: checkcast     #30                 // class java/util/Collection
     230: aload_1
     231: invokestatic  #31                 // Method org/jose4j/json/internal/json_simple/JSONArray.writeJSONString:(Ljava/util/Collection;Ljava/io/Writer;)V
     234: return
     235: aload_0
     236: instanceof    #32                 // class "[B"
     239: ifeq          254
     242: aload_0
     243: checkcast     #32                 // class "[B"
     246: checkcast     #32                 // class "[B"
     249: aload_1
     250: invokestatic  #33                 // Method org/jose4j/json/internal/json_simple/JSONArray.writeJSONString:([BLjava/io/Writer;)V
     253: return
     254: aload_0
     255: instanceof    #34                 // class "[S"
     258: ifeq          273
     261: aload_0
     262: checkcast     #34                 // class "[S"
     265: checkcast     #34                 // class "[S"
     268: aload_1
     269: invokestatic  #35                 // Method org/jose4j/json/internal/json_simple/JSONArray.writeJSONString:([SLjava/io/Writer;)V
     272: return
     273: aload_0
     274: instanceof    #36                 // class "[I"
     277: ifeq          292
     280: aload_0
     281: checkcast     #36                 // class "[I"
     284: checkcast     #36                 // class "[I"
     287: aload_1
     288: invokestatic  #37                 // Method org/jose4j/json/internal/json_simple/JSONArray.writeJSONString:([ILjava/io/Writer;)V
     291: return
     292: aload_0
     293: instanceof    #38                 // class "[J"
     296: ifeq          311
     299: aload_0
     300: checkcast     #38                 // class "[J"
     303: checkcast     #38                 // class "[J"
     306: aload_1
     307: invokestatic  #39                 // Method org/jose4j/json/internal/json_simple/JSONArray.writeJSONString:([JLjava/io/Writer;)V
     310: return
     311: aload_0
     312: instanceof    #40                 // class "[F"
     315: ifeq          330
     318: aload_0
     319: checkcast     #40                 // class "[F"
     322: checkcast     #40                 // class "[F"
     325: aload_1
     326: invokestatic  #41                 // Method org/jose4j/json/internal/json_simple/JSONArray.writeJSONString:([FLjava/io/Writer;)V
     329: return
     330: aload_0
     331: instanceof    #42                 // class "[D"
     334: ifeq          349
     337: aload_0
     338: checkcast     #42                 // class "[D"
     341: checkcast     #42                 // class "[D"
     344: aload_1
     345: invokestatic  #43                 // Method org/jose4j/json/internal/json_simple/JSONArray.writeJSONString:([DLjava/io/Writer;)V
     348: return
     349: aload_0
     350: instanceof    #44                 // class "[Z"
     353: ifeq          368
     356: aload_0
     357: checkcast     #44                 // class "[Z"
     360: checkcast     #44                 // class "[Z"
     363: aload_1
     364: invokestatic  #45                 // Method org/jose4j/json/internal/json_simple/JSONArray.writeJSONString:([ZLjava/io/Writer;)V
     367: return
     368: aload_0
     369: instanceof    #46                 // class "[C"
     372: ifeq          387
     375: aload_0
     376: checkcast     #46                 // class "[C"
     379: checkcast     #46                 // class "[C"
     382: aload_1
     383: invokestatic  #47                 // Method org/jose4j/json/internal/json_simple/JSONArray.writeJSONString:([CLjava/io/Writer;)V
     386: return
     387: aload_0
     388: instanceof    #48                 // class "[Ljava/lang/Object;"
     391: ifeq          406
     394: aload_0
     395: checkcast     #48                 // class "[Ljava/lang/Object;"
     398: checkcast     #48                 // class "[Ljava/lang/Object;"
     401: aload_1
     402: invokestatic  #49                 // Method org/jose4j/json/internal/json_simple/JSONArray.writeJSONString:([Ljava/lang/Object;Ljava/io/Writer;)V
     405: return
     406: aload_0
     407: invokevirtual #18                 // Method java/lang/Object.toString:()Ljava/lang/String;
     410: aload_1
     411: invokestatic  #50                 // Method writeJSONString:(Ljava/lang/Object;Ljava/io/Writer;)V
     414: return

  public static java.lang.String toJSONString(java.lang.Object);
    Code:
       0: new           #51                 // class java/io/StringWriter
       3: dup
       4: invokespecial #52                 // Method java/io/StringWriter."<init>":()V
       7: astore_1
       8: aload_0
       9: aload_1
      10: invokestatic  #50                 // Method writeJSONString:(Ljava/lang/Object;Ljava/io/Writer;)V
      13: aload_1
      14: invokevirtual #53                 // Method java/io/StringWriter.toString:()Ljava/lang/String;
      17: areturn
      18: astore_2
      19: new           #55                 // class java/lang/RuntimeException
      22: dup
      23: aload_2
      24: invokespecial #56                 // Method java/lang/RuntimeException."<init>":(Ljava/lang/Throwable;)V
      27: athrow
    Exception table:
       from    to  target type
           8    17    18   Class java/io/IOException

  public static java.lang.String escape(java.lang.String);
    Code:
       0: aload_0
       1: ifnonnull     6
       4: aconst_null
       5: areturn
       6: new           #57                 // class java/lang/StringBuilder
       9: dup
      10: invokespecial #58                 // Method java/lang/StringBuilder."<init>":()V
      13: astore_1
      14: aload_0
      15: aload_1
      16: invokestatic  #59                 // Method escape:(Ljava/lang/String;Ljava/lang/StringBuilder;)V
      19: aload_1
      20: invokevirtual #60                 // Method java/lang/StringBuilder.toString:()Ljava/lang/String;
      23: areturn

  static void escape(java.lang.String, java.lang.StringBuilder);
    Code:
       0: aload_0
       1: invokevirtual #61                 // Method java/lang/String.length:()I
       4: istore_2
       5: iconst_0
       6: istore_3
       7: iload_3
       8: iload_2
       9: if_icmpge     269
      12: aload_0
      13: iload_3
      14: invokevirtual #62                 // Method java/lang/String.charAt:(I)C
      17: istore        4
      19: iload         4
      21: lookupswitch  { // 7
                     8: 108
                     9: 148
                    10: 128
                    12: 118
                    13: 138
                    34: 88
                    92: 98
               default: 158
          }
      88: aload_1
      89: ldc           #63                 // String \\\"
      91: invokevirtual #64                 // Method java/lang/StringBuilder.append:(Ljava/lang/String;)Ljava/lang/StringBuilder;
      94: pop
      95: goto          263
      98: aload_1
      99: ldc           #65                 // String \\\\
     101: invokevirtual #64                 // Method java/lang/StringBuilder.append:(Ljava/lang/String;)Ljava/lang/StringBuilder;
     104: pop
     105: goto          263
     108: aload_1
     109: ldc           #66                 // String \\b
     111: invokevirtual #64                 // Method java/lang/StringBuilder.append:(Ljava/lang/String;)Ljava/lang/StringBuilder;
     114: pop
     115: goto          263
     118: aload_1
     119: ldc           #67                 // String \\f
     121: invokevirtual #64                 // Method java/lang/StringBuilder.append:(Ljava/lang/String;)Ljava/lang/StringBuilder;
     124: pop
     125: goto          263
     128: aload_1
     129: ldc           #68                 // String \\n
     131: invokevirtual #64                 // Method java/lang/StringBuilder.append:(Ljava/lang/String;)Ljava/lang/StringBuilder;
     134: pop
     135: goto          263
     138: aload_1
     139: ldc           #69                 // String \\r
     141: invokevirtual #64                 // Method java/lang/StringBuilder.append:(Ljava/lang/String;)Ljava/lang/StringBuilder;
     144: pop
     145: goto          263
     148: aload_1
     149: ldc           #70                 // String \\t
     151: invokevirtual #64                 // Method java/lang/StringBuilder.append:(Ljava/lang/String;)Ljava/lang/StringBuilder;
     154: pop
     155: goto          263
     158: iload         4
     160: iflt          170
     163: iload         4
     165: bipush        31
     167: if_icmple     201
     170: iload         4
     172: bipush        127
     174: if_icmplt     185
     177: iload         4
     179: sipush        159
     182: if_icmple     201
     185: iload         4
     187: sipush        8192
     190: if_icmplt     256
     193: iload         4
     195: sipush        8447
     198: if_icmpgt     256
     201: iload         4
     203: invokestatic  #71                 // Method java/lang/Integer.toHexString:(I)Ljava/lang/String;
     206: astore        5
     208: aload_1
     209: ldc           #72                 // String \\u
     211: invokevirtual #64                 // Method java/lang/StringBuilder.append:(Ljava/lang/String;)Ljava/lang/StringBuilder;
     214: pop
     215: iconst_0
     216: istore        6
     218: iload         6
     220: iconst_4
     221: aload         5
     223: invokevirtual #61                 // Method java/lang/String.length:()I
     226: isub
     227: if_icmpge     243
     230: aload_1
     231: bipush        48
     233: invokevirtual #73                 // Method java/lang/StringBuilder.append:(C)Ljava/lang/StringBuilder;
     236: pop
     237: iinc          6, 1
     240: goto          218
     243: aload_1
     244: aload         5
     246: invokevirtual #74                 // Method java/lang/String.toUpperCase:()Ljava/lang/String;
     249: invokevirtual #64                 // Method java/lang/StringBuilder.append:(Ljava/lang/String;)Ljava/lang/StringBuilder;
     252: pop
     253: goto          263
     256: aload_1
     257: iload         4
     259: invokevirtual #73                 // Method java/lang/StringBuilder.append:(C)Ljava/lang/StringBuilder;
     262: pop
     263: iinc          3, 1
     266: goto          7
     269: return
}
