Compiled from "SqlGenerator.java"
class org.hibernate.hql.internal.ast.SqlGenerator$StandardFunctionArguments implements org.hibernate.hql.internal.ast.SqlGenerator$FunctionArgumentsCollectingWriter {
  private int argInd;

  private final java.util.List<java.lang.String> args;

  org.hibernate.hql.internal.ast.SqlGenerator$StandardFunctionArguments();
    Code:
       0: aload_0
       1: invokespecial #1                  // Method java/lang/Object."<init>":()V
       4: aload_0
       5: new           #2                  // class java/util/ArrayList
       8: dup
       9: iconst_3
      10: invokespecial #3                  // Method java/util/ArrayList."<init>":(I)V
      13: putfield      #4                  // Field args:Ljava/util/List;
      16: return

  public void clause(java.lang.String);
    Code:
       0: aload_0
       1: getfield      #5                  // Field argInd:I
       4: aload_0
       5: getfield      #4                  // Field args:Ljava/util/List;
       8: invokeinterface #6,  1            // InterfaceMethod java/util/List.size:()I
      13: if_icmpne     30
      16: aload_0
      17: getfield      #4                  // Field args:Ljava/util/List;
      20: aload_1
      21: invokeinterface #7,  2            // InterfaceMethod java/util/List.add:(Ljava/lang/Object;)Z
      26: pop
      27: goto          77
      30: aload_0
      31: getfield      #4                  // Field args:Ljava/util/List;
      34: aload_0
      35: getfield      #5                  // Field argInd:I
      38: new           #8                  // class java/lang/StringBuilder
      41: dup
      42: invokespecial #9                  // Method java/lang/StringBuilder."<init>":()V
      45: aload_0
      46: getfield      #4                  // Field args:Ljava/util/List;
      49: aload_0
      50: getfield      #5                  // Field argInd:I
      53: invokeinterface #10,  2           // InterfaceMethod java/util/List.get:(I)Ljava/lang/Object;
      58: checkcast     #11                 // class java/lang/String
      61: invokevirtual #12                 // Method java/lang/StringBuilder.append:(Ljava/lang/String;)Ljava/lang/StringBuilder;
      64: aload_1
      65: invokevirtual #12                 // Method java/lang/StringBuilder.append:(Ljava/lang/String;)Ljava/lang/StringBuilder;
      68: invokevirtual #13                 // Method java/lang/StringBuilder.toString:()Ljava/lang/String;
      71: invokeinterface #14,  3           // InterfaceMethod java/util/List.set:(ILjava/lang/Object;)Ljava/lang/Object;
      76: pop
      77: return

  public void betweenFunctionArguments();
    Code:
       0: aload_0
       1: dup
       2: getfield      #5                  // Field argInd:I
       5: iconst_1
       6: iadd
       7: putfield      #5                  // Field argInd:I
      10: return

  public java.util.List getArgs();
    Code:
       0: aload_0
       1: getfield      #4                  // Field args:Ljava/util/List;
       4: areturn
}
