Compiled from "AuthorizationService.java"
public interface org.eclipse.jetty.security.authentication.AuthorizationService {
  public abstract org.eclipse.jetty.server.UserIdentity getUserIdentity(javax.servlet.http.HttpServletRequest, java.lang.String);

  public static org.eclipse.jetty.security.authentication.AuthorizationService from(org.eclipse.jetty.security.LoginService, java.lang.Object);
    Code:
       0: aload_0
       1: aload_1
       2: invokedynamic #1,  0              // InvokeDynamic #0:getUserIdentity:(Lorg/eclipse/jetty/security/LoginService;Ljava/lang/Object;)Lorg/eclipse/jetty/security/authentication/AuthorizationService;
       7: areturn

  private static org.eclipse.jetty.server.UserIdentity lambda$from$0(org.eclipse.jetty.security.LoginService, java.lang.Object, javax.servlet.http.HttpServletRequest, java.lang.String);
    Code:
       0: aload_0
       1: aload_3
       2: aload_1
       3: aload_2
       4: invokeinterface #2,  4            // InterfaceMethod org/eclipse/jetty/security/LoginService.login:(Ljava/lang/String;Ljava/lang/Object;Ljavax/servlet/ServletRequest;)Lorg/eclipse/jetty/server/UserIdentity;
       9: areturn
}
