Compiled from "BasicAuthenticator.java"
public class org.eclipse.jetty.security.authentication.BasicAuthenticator extends org.eclipse.jetty.security.authentication.LoginAuthenticator {
  private java.nio.charset.Charset _charset;

  public org.eclipse.jetty.security.authentication.BasicAuthenticator();
    Code:
       0: aload_0
       1: invokespecial #1                  // Method org/eclipse/jetty/security/authentication/LoginAuthenticator."<init>":()V
       4: return

  public java.nio.charset.Charset getCharset();
    Code:
       0: aload_0
       1: getfield      #2                  // Field _charset:Ljava/nio/charset/Charset;
       4: areturn

  public void setCharset(java.nio.charset.Charset);
    Code:
       0: aload_0
       1: aload_1
       2: putfield      #2                  // Field _charset:Ljava/nio/charset/Charset;
       5: return

  public java.lang.String getAuthMethod();
    Code:
       0: ldc           #4                  // String BASIC
       2: areturn

  public org.eclipse.jetty.server.Authentication validateRequest(javax.servlet.ServletRequest, javax.servlet.ServletResponse, boolean) throws org.eclipse.jetty.security.ServerAuthException;
    Code:
       0: aload_1
       1: checkcast     #5                  // class javax/servlet/http/HttpServletRequest
       4: astore        4
       6: aload_2
       7: checkcast     #6                  // class javax/servlet/http/HttpServletResponse
      10: astore        5
      12: aload         4
      14: getstatic     #7                  // Field org/eclipse/jetty/http/HttpHeader.AUTHORIZATION:Lorg/eclipse/jetty/http/HttpHeader;
      17: invokevirtual #8                  // Method org/eclipse/jetty/http/HttpHeader.asString:()Ljava/lang/String;
      20: invokeinterface #9,  2            // InterfaceMethod javax/servlet/http/HttpServletRequest.getHeader:(Ljava/lang/String;)Ljava/lang/String;
      25: astore        6
      27: iload_3
      28: ifne          40
      31: new           #10                 // class org/eclipse/jetty/security/authentication/DeferredAuthentication
      34: dup
      35: aload_0
      36: invokespecial #11                 // Method org/eclipse/jetty/security/authentication/DeferredAuthentication."<init>":(Lorg/eclipse/jetty/security/authentication/LoginAuthenticator;)V
      39: areturn
      40: aload         6
      42: ifnull        191
      45: aload         6
      47: bipush        32
      49: invokevirtual #12                 // Method java/lang/String.indexOf:(I)I
      52: istore        7
      54: iload         7
      56: ifle          191
      59: aload         6
      61: iconst_0
      62: iload         7
      64: invokevirtual #13                 // Method java/lang/String.substring:(II)Ljava/lang/String;
      67: astore        8
      69: ldc           #14                 // String basic
      71: aload         8
      73: invokevirtual #15                 // Method java/lang/String.equalsIgnoreCase:(Ljava/lang/String;)Z
      76: ifeq          191
      79: aload         6
      81: iload         7
      83: iconst_1
      84: iadd
      85: invokevirtual #16                 // Method java/lang/String.substring:(I)Ljava/lang/String;
      88: astore        6
      90: aload_0
      91: invokevirtual #17                 // Method getCharset:()Ljava/nio/charset/Charset;
      94: astore        9
      96: aload         9
      98: ifnonnull     106
     101: getstatic     #18                 // Field java/nio/charset/StandardCharsets.ISO_8859_1:Ljava/nio/charset/Charset;
     104: astore        9
     106: new           #19                 // class java/lang/String
     109: dup
     110: invokestatic  #20                 // Method java/util/Base64.getDecoder:()Ljava/util/Base64$Decoder;
     113: aload         6
     115: invokevirtual #21                 // Method java/util/Base64$Decoder.decode:(Ljava/lang/String;)[B
     118: aload         9
     120: invokespecial #22                 // Method java/lang/String."<init>":([BLjava/nio/charset/Charset;)V
     123: astore        6
     125: aload         6
     127: bipush        58
     129: invokevirtual #12                 // Method java/lang/String.indexOf:(I)I
     132: istore        10
     134: iload         10
     136: ifle          191
     139: aload         6
     141: iconst_0
     142: iload         10
     144: invokevirtual #13                 // Method java/lang/String.substring:(II)Ljava/lang/String;
     147: astore        11
     149: aload         6
     151: iload         10
     153: iconst_1
     154: iadd
     155: invokevirtual #16                 // Method java/lang/String.substring:(I)Ljava/lang/String;
     158: astore        12
     160: aload_0
     161: aload         11
     163: aload         12
     165: aload         4
     167: invokevirtual #23                 // Method login:(Ljava/lang/String;Ljava/lang/Object;Ljavax/servlet/ServletRequest;)Lorg/eclipse/jetty/server/UserIdentity;
     170: astore        13
     172: aload         13
     174: ifnull        191
     177: new           #24                 // class org/eclipse/jetty/security/UserAuthentication
     180: dup
     181: aload_0
     182: invokevirtual #25                 // Method getAuthMethod:()Ljava/lang/String;
     185: aload         13
     187: invokespecial #26                 // Method org/eclipse/jetty/security/UserAuthentication."<init>":(Ljava/lang/String;Lorg/eclipse/jetty/server/UserIdentity;)V
     190: areturn
     191: aload         5
     193: invokestatic  #27                 // Method org/eclipse/jetty/security/authentication/DeferredAuthentication.isDeferred:(Ljavax/servlet/http/HttpServletResponse;)Z
     196: ifeq          203
     199: getstatic     #28                 // Field org/eclipse/jetty/server/Authentication.UNAUTHENTICATED:Lorg/eclipse/jetty/server/Authentication;
     202: areturn
     203: new           #29                 // class java/lang/StringBuilder
     206: dup
     207: invokespecial #30                 // Method java/lang/StringBuilder."<init>":()V
     210: ldc           #31                 // String basic realm=\"
     212: invokevirtual #32                 // Method java/lang/StringBuilder.append:(Ljava/lang/String;)Ljava/lang/StringBuilder;
     215: aload_0
     216: getfield      #33                 // Field _loginService:Lorg/eclipse/jetty/security/LoginService;
     219: invokeinterface #34,  1           // InterfaceMethod org/eclipse/jetty/security/LoginService.getName:()Ljava/lang/String;
     224: invokevirtual #32                 // Method java/lang/StringBuilder.append:(Ljava/lang/String;)Ljava/lang/StringBuilder;
     227: ldc           #35                 // String \"
     229: invokevirtual #32                 // Method java/lang/StringBuilder.append:(Ljava/lang/String;)Ljava/lang/StringBuilder;
     232: invokevirtual #36                 // Method java/lang/StringBuilder.toString:()Ljava/lang/String;
     235: astore        7
     237: aload_0
     238: invokevirtual #17                 // Method getCharset:()Ljava/nio/charset/Charset;
     241: astore        8
     243: aload         8
     245: ifnull        283
     248: new           #29                 // class java/lang/StringBuilder
     251: dup
     252: invokespecial #30                 // Method java/lang/StringBuilder."<init>":()V
     255: aload         7
     257: invokevirtual #32                 // Method java/lang/StringBuilder.append:(Ljava/lang/String;)Ljava/lang/StringBuilder;
     260: ldc           #37                 // String , charset=\"
     262: invokevirtual #32                 // Method java/lang/StringBuilder.append:(Ljava/lang/String;)Ljava/lang/StringBuilder;
     265: aload         8
     267: invokevirtual #38                 // Method java/nio/charset/Charset.name:()Ljava/lang/String;
     270: invokevirtual #32                 // Method java/lang/StringBuilder.append:(Ljava/lang/String;)Ljava/lang/StringBuilder;
     273: ldc           #35                 // String \"
     275: invokevirtual #32                 // Method java/lang/StringBuilder.append:(Ljava/lang/String;)Ljava/lang/StringBuilder;
     278: invokevirtual #36                 // Method java/lang/StringBuilder.toString:()Ljava/lang/String;
     281: astore        7
     283: aload         5
     285: getstatic     #39                 // Field org/eclipse/jetty/http/HttpHeader.WWW_AUTHENTICATE:Lorg/eclipse/jetty/http/HttpHeader;
     288: invokevirtual #8                  // Method org/eclipse/jetty/http/HttpHeader.asString:()Ljava/lang/String;
     291: aload         7
     293: invokeinterface #40,  3           // InterfaceMethod javax/servlet/http/HttpServletResponse.setHeader:(Ljava/lang/String;Ljava/lang/String;)V
     298: aload         5
     300: sipush        401
     303: invokeinterface #41,  2           // InterfaceMethod javax/servlet/http/HttpServletResponse.sendError:(I)V
     308: getstatic     #42                 // Field org/eclipse/jetty/server/Authentication.SEND_CONTINUE:Lorg/eclipse/jetty/server/Authentication;
     311: areturn
     312: astore        7
     314: new           #44                 // class org/eclipse/jetty/security/ServerAuthException
     317: dup
     318: aload         7
     320: invokespecial #45                 // Method org/eclipse/jetty/security/ServerAuthException."<init>":(Ljava/lang/Throwable;)V
     323: athrow
    Exception table:
       from    to  target type
          27    39   312   Class java/io/IOException
          40   190   312   Class java/io/IOException
         191   202   312   Class java/io/IOException
         203   311   312   Class java/io/IOException

  public boolean secureResponse(javax.servlet.ServletRequest, javax.servlet.ServletResponse, boolean, org.eclipse.jetty.server.Authentication$User) throws org.eclipse.jetty.security.ServerAuthException;
    Code:
       0: iconst_1
       1: ireturn
}
