Compiled from "DeferredAuthentication.java"
class org.eclipse.jetty.security.authentication.DeferredAuthentication$1 implements javax.servlet.http.HttpServletResponse {
  org.eclipse.jetty.security.authentication.DeferredAuthentication$1();
    Code:
       0: aload_0
       1: invokespecial #1                  // Method java/lang/Object."<init>":()V
       4: return

  public void addCookie(javax.servlet.http.Cookie);
    Code:
       0: return

  public void addDateHeader(java.lang.String, long);
    Code:
       0: return

  public void addHeader(java.lang.String, java.lang.String);
    Code:
       0: return

  public void addIntHeader(java.lang.String, int);
    Code:
       0: return

  public boolean containsHeader(java.lang.String);
    Code:
       0: iconst_0
       1: ireturn

  public java.lang.String encodeRedirectURL(java.lang.String);
    Code:
       0: aconst_null
       1: areturn

  public java.lang.String encodeRedirectUrl(java.lang.String);
    Code:
       0: aconst_null
       1: areturn

  public java.lang.String encodeURL(java.lang.String);
    Code:
       0: aconst_null
       1: areturn

  public java.lang.String encodeUrl(java.lang.String);
    Code:
       0: aconst_null
       1: areturn

  public void sendError(int) throws java.io.IOException;
    Code:
       0: return

  public void sendError(int, java.lang.String) throws java.io.IOException;
    Code:
       0: return

  public void sendRedirect(java.lang.String) throws java.io.IOException;
    Code:
       0: return

  public void setDateHeader(java.lang.String, long);
    Code:
       0: return

  public void setHeader(java.lang.String, java.lang.String);
    Code:
       0: return

  public void setIntHeader(java.lang.String, int);
    Code:
       0: return

  public void setStatus(int);
    Code:
       0: return

  public void setStatus(int, java.lang.String);
    Code:
       0: return

  public void flushBuffer() throws java.io.IOException;
    Code:
       0: return

  public int getBufferSize();
    Code:
       0: sipush        1024
       3: ireturn

  public java.lang.String getCharacterEncoding();
    Code:
       0: aconst_null
       1: areturn

  public java.lang.String getContentType();
    Code:
       0: aconst_null
       1: areturn

  public java.util.Locale getLocale();
    Code:
       0: aconst_null
       1: areturn

  public javax.servlet.ServletOutputStream getOutputStream() throws java.io.IOException;
    Code:
       0: invokestatic  #2                  // Method org/eclipse/jetty/security/authentication/DeferredAuthentication.access$000:()Ljavax/servlet/ServletOutputStream;
       3: areturn

  public java.io.PrintWriter getWriter() throws java.io.IOException;
    Code:
       0: invokestatic  #3                  // Method org/eclipse/jetty/util/IO.getNullPrintWriter:()Ljava/io/PrintWriter;
       3: areturn

  public boolean isCommitted();
    Code:
       0: iconst_1
       1: ireturn

  public void reset();
    Code:
       0: return

  public void resetBuffer();
    Code:
       0: return

  public void setBufferSize(int);
    Code:
       0: return

  public void setCharacterEncoding(java.lang.String);
    Code:
       0: return

  public void setContentLength(int);
    Code:
       0: return

  public void setContentLengthLong(long);
    Code:
       0: return

  public void setContentType(java.lang.String);
    Code:
       0: return

  public void setLocale(java.util.Locale);
    Code:
       0: return

  public java.util.Collection<java.lang.String> getHeaderNames();
    Code:
       0: invokestatic  #4                  // Method java/util/Collections.emptyList:()Ljava/util/List;
       3: areturn

  public java.lang.String getHeader(java.lang.String);
    Code:
       0: aconst_null
       1: areturn

  public java.util.Collection<java.lang.String> getHeaders(java.lang.String);
    Code:
       0: invokestatic  #4                  // Method java/util/Collections.emptyList:()Ljava/util/List;
       3: areturn

  public int getStatus();
    Code:
       0: iconst_0
       1: ireturn
}
