Compiled from "FormAuthenticator.java"
public class org.eclipse.jetty.security.authentication.FormAuthenticator extends org.eclipse.jetty.security.authentication.LoginAuthenticator {
  private static final org.eclipse.jetty.util.log.Logger LOG;

  public static final java.lang.String __FORM_LOGIN_PAGE;

  public static final java.lang.String __FORM_ERROR_PAGE;

  public static final java.lang.String __FORM_DISPATCH;

  public static final java.lang.String __J_URI;

  public static final java.lang.String __J_POST;

  public static final java.lang.String __J_METHOD;

  public static final java.lang.String __J_SECURITY_CHECK;

  public static final java.lang.String __J_USERNAME;

  public static final java.lang.String __J_PASSWORD;

  private java.lang.String _formErrorPage;

  private java.lang.String _formErrorPath;

  private java.lang.String _formLoginPage;

  private java.lang.String _formLoginPath;

  private boolean _dispatch;

  private boolean _alwaysSaveUri;

  public org.eclipse.jetty.security.authentication.FormAuthenticator();
    Code:
       0: aload_0
       1: invokespecial #1                  // Method org/eclipse/jetty/security/authentication/LoginAuthenticator."<init>":()V
       4: return

  public org.eclipse.jetty.security.authentication.FormAuthenticator(java.lang.String, java.lang.String, boolean);
    Code:
       0: aload_0
       1: invokespecial #2                  // Method "<init>":()V
       4: aload_1
       5: ifnull        13
       8: aload_0
       9: aload_1
      10: invokespecial #3                  // Method setLoginPage:(Ljava/lang/String;)V
      13: aload_2
      14: ifnull        22
      17: aload_0
      18: aload_2
      19: invokespecial #4                  // Method setErrorPage:(Ljava/lang/String;)V
      22: aload_0
      23: iload_3
      24: putfield      #5                  // Field _dispatch:Z
      27: return

  public void setAlwaysSaveUri(boolean);
    Code:
       0: aload_0
       1: iload_1
       2: putfield      #6                  // Field _alwaysSaveUri:Z
       5: return

  public boolean getAlwaysSaveUri();
    Code:
       0: aload_0
       1: getfield      #6                  // Field _alwaysSaveUri:Z
       4: ireturn

  public void setConfiguration(org.eclipse.jetty.security.Authenticator$AuthConfiguration);
    Code:
       0: aload_0
       1: aload_1
       2: invokespecial #7                  // Method org/eclipse/jetty/security/authentication/LoginAuthenticator.setConfiguration:(Lorg/eclipse/jetty/security/Authenticator$AuthConfiguration;)V
       5: aload_1
       6: ldc           #9                  // String org.eclipse.jetty.security.form_login_page
       8: invokeinterface #10,  2           // InterfaceMethod org/eclipse/jetty/security/Authenticator$AuthConfiguration.getInitParameter:(Ljava/lang/String;)Ljava/lang/String;
      13: astore_2
      14: aload_2
      15: ifnull        23
      18: aload_0
      19: aload_2
      20: invokespecial #3                  // Method setLoginPage:(Ljava/lang/String;)V
      23: aload_1
      24: ldc           #11                 // String org.eclipse.jetty.security.form_error_page
      26: invokeinterface #10,  2           // InterfaceMethod org/eclipse/jetty/security/Authenticator$AuthConfiguration.getInitParameter:(Ljava/lang/String;)Ljava/lang/String;
      31: astore_3
      32: aload_3
      33: ifnull        41
      36: aload_0
      37: aload_3
      38: invokespecial #4                  // Method setErrorPage:(Ljava/lang/String;)V
      41: aload_1
      42: ldc           #12                 // String org.eclipse.jetty.security.dispatch
      44: invokeinterface #10,  2           // InterfaceMethod org/eclipse/jetty/security/Authenticator$AuthConfiguration.getInitParameter:(Ljava/lang/String;)Ljava/lang/String;
      49: astore        4
      51: aload_0
      52: aload         4
      54: ifnonnull     64
      57: aload_0
      58: getfield      #5                  // Field _dispatch:Z
      61: goto          69
      64: aload         4
      66: invokestatic  #13                 // Method java/lang/Boolean.parseBoolean:(Ljava/lang/String;)Z
      69: putfield      #5                  // Field _dispatch:Z
      72: return

  public java.lang.String getAuthMethod();
    Code:
       0: ldc           #15                 // String FORM
       2: areturn

  private void setLoginPage(java.lang.String);
    Code:
       0: aload_1
       1: ldc           #16                 // String /
       3: invokevirtual #17                 // Method java/lang/String.startsWith:(Ljava/lang/String;)Z
       6: ifne          43
       9: getstatic     #18                 // Field LOG:Lorg/eclipse/jetty/util/log/Logger;
      12: ldc           #19                 // String form-login-page must start with /
      14: iconst_0
      15: anewarray     #20                 // class java/lang/Object
      18: invokeinterface #21,  3           // InterfaceMethod org/eclipse/jetty/util/log/Logger.warn:(Ljava/lang/String;[Ljava/lang/Object;)V
      23: new           #22                 // class java/lang/StringBuilder
      26: dup
      27: invokespecial #23                 // Method java/lang/StringBuilder."<init>":()V
      30: ldc           #16                 // String /
      32: invokevirtual #24                 // Method java/lang/StringBuilder.append:(Ljava/lang/String;)Ljava/lang/StringBuilder;
      35: aload_1
      36: invokevirtual #24                 // Method java/lang/StringBuilder.append:(Ljava/lang/String;)Ljava/lang/StringBuilder;
      39: invokevirtual #25                 // Method java/lang/StringBuilder.toString:()Ljava/lang/String;
      42: astore_1
      43: aload_0
      44: aload_1
      45: putfield      #26                 // Field _formLoginPage:Ljava/lang/String;
      48: aload_0
      49: aload_1
      50: putfield      #27                 // Field _formLoginPath:Ljava/lang/String;
      53: aload_0
      54: getfield      #27                 // Field _formLoginPath:Ljava/lang/String;
      57: bipush        63
      59: invokevirtual #28                 // Method java/lang/String.indexOf:(I)I
      62: ifle          86
      65: aload_0
      66: aload_0
      67: getfield      #27                 // Field _formLoginPath:Ljava/lang/String;
      70: iconst_0
      71: aload_0
      72: getfield      #27                 // Field _formLoginPath:Ljava/lang/String;
      75: bipush        63
      77: invokevirtual #28                 // Method java/lang/String.indexOf:(I)I
      80: invokevirtual #29                 // Method java/lang/String.substring:(II)Ljava/lang/String;
      83: putfield      #27                 // Field _formLoginPath:Ljava/lang/String;
      86: return

  private void setErrorPage(java.lang.String);
    Code:
       0: aload_1
       1: ifnull        14
       4: aload_1
       5: invokevirtual #30                 // Method java/lang/String.trim:()Ljava/lang/String;
       8: invokevirtual #31                 // Method java/lang/String.length:()I
      11: ifne          27
      14: aload_0
      15: aconst_null
      16: putfield      #32                 // Field _formErrorPath:Ljava/lang/String;
      19: aload_0
      20: aconst_null
      21: putfield      #33                 // Field _formErrorPage:Ljava/lang/String;
      24: goto          113
      27: aload_1
      28: ldc           #16                 // String /
      30: invokevirtual #17                 // Method java/lang/String.startsWith:(Ljava/lang/String;)Z
      33: ifne          70
      36: getstatic     #18                 // Field LOG:Lorg/eclipse/jetty/util/log/Logger;
      39: ldc           #34                 // String form-error-page must start with /
      41: iconst_0
      42: anewarray     #20                 // class java/lang/Object
      45: invokeinterface #21,  3           // InterfaceMethod org/eclipse/jetty/util/log/Logger.warn:(Ljava/lang/String;[Ljava/lang/Object;)V
      50: new           #22                 // class java/lang/StringBuilder
      53: dup
      54: invokespecial #23                 // Method java/lang/StringBuilder."<init>":()V
      57: ldc           #16                 // String /
      59: invokevirtual #24                 // Method java/lang/StringBuilder.append:(Ljava/lang/String;)Ljava/lang/StringBuilder;
      62: aload_1
      63: invokevirtual #24                 // Method java/lang/StringBuilder.append:(Ljava/lang/String;)Ljava/lang/StringBuilder;
      66: invokevirtual #25                 // Method java/lang/StringBuilder.toString:()Ljava/lang/String;
      69: astore_1
      70: aload_0
      71: aload_1
      72: putfield      #33                 // Field _formErrorPage:Ljava/lang/String;
      75: aload_0
      76: aload_1
      77: putfield      #32                 // Field _formErrorPath:Ljava/lang/String;
      80: aload_0
      81: getfield      #32                 // Field _formErrorPath:Ljava/lang/String;
      84: bipush        63
      86: invokevirtual #28                 // Method java/lang/String.indexOf:(I)I
      89: ifle          113
      92: aload_0
      93: aload_0
      94: getfield      #32                 // Field _formErrorPath:Ljava/lang/String;
      97: iconst_0
      98: aload_0
      99: getfield      #32                 // Field _formErrorPath:Ljava/lang/String;
     102: bipush        63
     104: invokevirtual #28                 // Method java/lang/String.indexOf:(I)I
     107: invokevirtual #29                 // Method java/lang/String.substring:(II)Ljava/lang/String;
     110: putfield      #32                 // Field _formErrorPath:Ljava/lang/String;
     113: return

  public org.eclipse.jetty.server.UserIdentity login(java.lang.String, java.lang.Object, javax.servlet.ServletRequest);
    Code:
       0: aload_0
       1: aload_1
       2: aload_2
       3: aload_3
       4: invokespecial #35                 // Method org/eclipse/jetty/security/authentication/LoginAuthenticator.login:(Ljava/lang/String;Ljava/lang/Object;Ljavax/servlet/ServletRequest;)Lorg/eclipse/jetty/server/UserIdentity;
       7: astore        4
       9: aload         4
      11: ifnull        53
      14: aload_3
      15: checkcast     #36                 // class javax/servlet/http/HttpServletRequest
      18: iconst_1
      19: invokeinterface #37,  2           // InterfaceMethod javax/servlet/http/HttpServletRequest.getSession:(Z)Ljavax/servlet/http/HttpSession;
      24: astore        5
      26: new           #38                 // class org/eclipse/jetty/security/authentication/SessionAuthentication
      29: dup
      30: aload_0
      31: invokevirtual #39                 // Method getAuthMethod:()Ljava/lang/String;
      34: aload         4
      36: aload_2
      37: invokespecial #40                 // Method org/eclipse/jetty/security/authentication/SessionAuthentication."<init>":(Ljava/lang/String;Lorg/eclipse/jetty/server/UserIdentity;Ljava/lang/Object;)V
      40: astore        6
      42: aload         5
      44: ldc           #41                 // String org.eclipse.jetty.security.UserIdentity
      46: aload         6
      48: invokeinterface #42,  3           // InterfaceMethod javax/servlet/http/HttpSession.setAttribute:(Ljava/lang/String;Ljava/lang/Object;)V
      53: aload         4
      55: areturn

  public void logout(javax.servlet.ServletRequest);
    Code:
       0: aload_0
       1: aload_1
       2: invokespecial #43                 // Method org/eclipse/jetty/security/authentication/LoginAuthenticator.logout:(Ljavax/servlet/ServletRequest;)V
       5: aload_1
       6: checkcast     #36                 // class javax/servlet/http/HttpServletRequest
       9: astore_2
      10: aload_2
      11: iconst_0
      12: invokeinterface #37,  2           // InterfaceMethod javax/servlet/http/HttpServletRequest.getSession:(Z)Ljavax/servlet/http/HttpSession;
      17: astore_3
      18: aload_3
      19: ifnonnull     23
      22: return
      23: aload_3
      24: ldc           #41                 // String org.eclipse.jetty.security.UserIdentity
      26: invokeinterface #44,  2           // InterfaceMethod javax/servlet/http/HttpSession.removeAttribute:(Ljava/lang/String;)V
      31: return

  public void prepareRequest(javax.servlet.ServletRequest);
    Code:
       0: aload_1
       1: checkcast     #36                 // class javax/servlet/http/HttpServletRequest
       4: astore_2
       5: aload_2
       6: iconst_0
       7: invokeinterface #37,  2           // InterfaceMethod javax/servlet/http/HttpServletRequest.getSession:(Z)Ljavax/servlet/http/HttpSession;
      12: astore_3
      13: aload_3
      14: ifnull        28
      17: aload_3
      18: ldc           #41                 // String org.eclipse.jetty.security.UserIdentity
      20: invokeinterface #45,  2           // InterfaceMethod javax/servlet/http/HttpSession.getAttribute:(Ljava/lang/String;)Ljava/lang/Object;
      25: ifnonnull     29
      28: return
      29: aload_3
      30: ldc           #46                 // String org.eclipse.jetty.security.form_URI
      32: invokeinterface #45,  2           // InterfaceMethod javax/servlet/http/HttpSession.getAttribute:(Ljava/lang/String;)Ljava/lang/Object;
      37: checkcast     #47                 // class java/lang/String
      40: astore        4
      42: aload         4
      44: ifnull        55
      47: aload         4
      49: invokevirtual #31                 // Method java/lang/String.length:()I
      52: ifne          56
      55: return
      56: aload_3
      57: ldc           #48                 // String org.eclipse.jetty.security.form_METHOD
      59: invokeinterface #45,  2           // InterfaceMethod javax/servlet/http/HttpSession.getAttribute:(Ljava/lang/String;)Ljava/lang/Object;
      64: checkcast     #47                 // class java/lang/String
      67: astore        5
      69: aload         5
      71: ifnull        82
      74: aload         5
      76: invokevirtual #31                 // Method java/lang/String.length:()I
      79: ifne          83
      82: return
      83: aload_2
      84: invokeinterface #49,  1           // InterfaceMethod javax/servlet/http/HttpServletRequest.getRequestURL:()Ljava/lang/StringBuffer;
      89: astore        6
      91: aload_2
      92: invokeinterface #50,  1           // InterfaceMethod javax/servlet/http/HttpServletRequest.getQueryString:()Ljava/lang/String;
      97: ifnull        117
     100: aload         6
     102: ldc           #51                 // String ?
     104: invokevirtual #52                 // Method java/lang/StringBuffer.append:(Ljava/lang/String;)Ljava/lang/StringBuffer;
     107: aload_2
     108: invokeinterface #50,  1           // InterfaceMethod javax/servlet/http/HttpServletRequest.getQueryString:()Ljava/lang/String;
     113: invokevirtual #52                 // Method java/lang/StringBuffer.append:(Ljava/lang/String;)Ljava/lang/StringBuffer;
     116: pop
     117: aload         4
     119: aload         6
     121: invokevirtual #53                 // Method java/lang/StringBuffer.toString:()Ljava/lang/String;
     124: invokevirtual #54                 // Method java/lang/String.equals:(Ljava/lang/Object;)Z
     127: ifne          131
     130: return
     131: getstatic     #18                 // Field LOG:Lorg/eclipse/jetty/util/log/Logger;
     134: invokeinterface #55,  1           // InterfaceMethod org/eclipse/jetty/util/log/Logger.isDebugEnabled:()Z
     139: ifeq          175
     142: getstatic     #18                 // Field LOG:Lorg/eclipse/jetty/util/log/Logger;
     145: ldc           #56                 // String Restoring original method {} for {} with method {}
     147: iconst_3
     148: anewarray     #20                 // class java/lang/Object
     151: dup
     152: iconst_0
     153: aload         5
     155: aastore
     156: dup
     157: iconst_1
     158: aload         4
     160: aastore
     161: dup
     162: iconst_2
     163: aload_2
     164: invokeinterface #57,  1           // InterfaceMethod javax/servlet/http/HttpServletRequest.getMethod:()Ljava/lang/String;
     169: aastore
     170: invokeinterface #58,  3           // InterfaceMethod org/eclipse/jetty/util/log/Logger.debug:(Ljava/lang/String;[Ljava/lang/Object;)V
     175: aload_1
     176: invokestatic  #59                 // Method org/eclipse/jetty/server/Request.getBaseRequest:(Ljavax/servlet/ServletRequest;)Lorg/eclipse/jetty/server/Request;
     179: astore        7
     181: aload         7
     183: aload         5
     185: invokevirtual #60                 // Method org/eclipse/jetty/server/Request.setMethod:(Ljava/lang/String;)V
     188: return

  public org.eclipse.jetty.server.Authentication validateRequest(javax.servlet.ServletRequest, javax.servlet.ServletResponse, boolean) throws org.eclipse.jetty.security.ServerAuthException;
    Code:
       0: aload_1
       1: checkcast     #36                 // class javax/servlet/http/HttpServletRequest
       4: astore        4
       6: aload_2
       7: checkcast     #61                 // class javax/servlet/http/HttpServletResponse
      10: astore        5
      12: aload         4
      14: invokestatic  #59                 // Method org/eclipse/jetty/server/Request.getBaseRequest:(Ljavax/servlet/ServletRequest;)Lorg/eclipse/jetty/server/Request;
      17: astore        6
      19: aload         6
      21: invokevirtual #62                 // Method org/eclipse/jetty/server/Request.getResponse:()Lorg/eclipse/jetty/server/Response;
      24: astore        7
      26: aload         4
      28: invokeinterface #63,  1           // InterfaceMethod javax/servlet/http/HttpServletRequest.getRequestURI:()Ljava/lang/String;
      33: astore        8
      35: aload         8
      37: ifnonnull     44
      40: ldc           #16                 // String /
      42: astore        8
      44: iload_3
      45: aload_0
      46: aload         8
      48: invokevirtual #65                 // Method isJSecurityCheck:(Ljava/lang/String;)Z
      51: ior
      52: istore_3
      53: iload_3
      54: ifne          66
      57: new           #66                 // class org/eclipse/jetty/security/authentication/DeferredAuthentication
      60: dup
      61: aload_0
      62: invokespecial #67                 // Method org/eclipse/jetty/security/authentication/DeferredAuthentication."<init>":(Lorg/eclipse/jetty/security/authentication/LoginAuthenticator;)V
      65: areturn
      66: aload_0
      67: aload         4
      69: invokeinterface #68,  1           // InterfaceMethod javax/servlet/http/HttpServletRequest.getServletPath:()Ljava/lang/String;
      74: aload         4
      76: invokeinterface #69,  1           // InterfaceMethod javax/servlet/http/HttpServletRequest.getPathInfo:()Ljava/lang/String;
      81: invokestatic  #70                 // Method org/eclipse/jetty/util/URIUtil.addPaths:(Ljava/lang/String;Ljava/lang/String;)Ljava/lang/String;
      84: invokevirtual #71                 // Method isLoginOrErrorPage:(Ljava/lang/String;)Z
      87: ifeq          107
      90: aload         5
      92: invokestatic  #72                 // Method org/eclipse/jetty/security/authentication/DeferredAuthentication.isDeferred:(Ljavax/servlet/http/HttpServletResponse;)Z
      95: ifne          107
      98: new           #66                 // class org/eclipse/jetty/security/authentication/DeferredAuthentication
     101: dup
     102: aload_0
     103: invokespecial #67                 // Method org/eclipse/jetty/security/authentication/DeferredAuthentication."<init>":(Lorg/eclipse/jetty/security/authentication/LoginAuthenticator;)V
     106: areturn
     107: aload_0
     108: aload         8
     110: invokevirtual #65                 // Method isJSecurityCheck:(Ljava/lang/String;)Z
     113: ifeq          576
     116: aload         4
     118: ldc           #73                 // String j_username
     120: invokeinterface #74,  2           // InterfaceMethod javax/servlet/http/HttpServletRequest.getParameter:(Ljava/lang/String;)Ljava/lang/String;
     125: astore        9
     127: aload         4
     129: ldc           #75                 // String j_password
     131: invokeinterface #74,  2           // InterfaceMethod javax/servlet/http/HttpServletRequest.getParameter:(Ljava/lang/String;)Ljava/lang/String;
     136: astore        10
     138: aload_0
     139: aload         9
     141: aload         10
     143: aload         4
     145: invokevirtual #76                 // Method login:(Ljava/lang/String;Ljava/lang/Object;Ljavax/servlet/ServletRequest;)Lorg/eclipse/jetty/server/UserIdentity;
     148: astore        11
     150: getstatic     #18                 // Field LOG:Lorg/eclipse/jetty/util/log/Logger;
     153: ldc           #77                 // String jsecuritycheck {} {}
     155: iconst_2
     156: anewarray     #20                 // class java/lang/Object
     159: dup
     160: iconst_0
     161: aload         9
     163: aastore
     164: dup
     165: iconst_1
     166: aload         11
     168: aastore
     169: invokeinterface #58,  3           // InterfaceMethod org/eclipse/jetty/util/log/Logger.debug:(Ljava/lang/String;[Ljava/lang/Object;)V
     174: aload         4
     176: iconst_0
     177: invokeinterface #37,  2           // InterfaceMethod javax/servlet/http/HttpServletRequest.getSession:(Z)Ljavax/servlet/http/HttpSession;
     182: astore        12
     184: aload         11
     186: ifnull        322
     189: aload         12
     191: dup
     192: astore        15
     194: monitorenter
     195: aload         12
     197: ldc           #46                 // String org.eclipse.jetty.security.form_URI
     199: invokeinterface #45,  2           // InterfaceMethod javax/servlet/http/HttpSession.getAttribute:(Ljava/lang/String;)Ljava/lang/Object;
     204: checkcast     #47                 // class java/lang/String
     207: astore        13
     209: aload         13
     211: ifnull        222
     214: aload         13
     216: invokevirtual #31                 // Method java/lang/String.length:()I
     219: ifne          243
     222: aload         4
     224: invokeinterface #78,  1           // InterfaceMethod javax/servlet/http/HttpServletRequest.getContextPath:()Ljava/lang/String;
     229: astore        13
     231: aload         13
     233: invokevirtual #31                 // Method java/lang/String.length:()I
     236: ifne          243
     239: ldc           #16                 // String /
     241: astore        13
     243: new           #79                 // class org/eclipse/jetty/security/authentication/FormAuthenticator$FormAuthentication
     246: dup
     247: aload_0
     248: invokevirtual #39                 // Method getAuthMethod:()Ljava/lang/String;
     251: aload         11
     253: invokespecial #80                 // Method org/eclipse/jetty/security/authentication/FormAuthenticator$FormAuthentication."<init>":(Ljava/lang/String;Lorg/eclipse/jetty/server/UserIdentity;)V
     256: astore        14
     258: aload         15
     260: monitorexit
     261: goto          272
     264: astore        16
     266: aload         15
     268: monitorexit
     269: aload         16
     271: athrow
     272: getstatic     #18                 // Field LOG:Lorg/eclipse/jetty/util/log/Logger;
     275: ldc           #81                 // String authenticated {}->{}
     277: iconst_2
     278: anewarray     #20                 // class java/lang/Object
     281: dup
     282: iconst_0
     283: aload         14
     285: aastore
     286: dup
     287: iconst_1
     288: aload         13
     290: aastore
     291: invokeinterface #58,  3           // InterfaceMethod org/eclipse/jetty/util/log/Logger.debug:(Ljava/lang/String;[Ljava/lang/Object;)V
     296: aload         5
     298: iconst_0
     299: invokeinterface #82,  2           // InterfaceMethod javax/servlet/http/HttpServletResponse.setContentLength:(I)V
     304: aload         7
     306: aload         5
     308: aload         13
     310: invokeinterface #83,  2           // InterfaceMethod javax/servlet/http/HttpServletResponse.encodeRedirectURL:(Ljava/lang/String;)Ljava/lang/String;
     315: iconst_1
     316: invokevirtual #84                 // Method org/eclipse/jetty/server/Response.sendRedirect:(Ljava/lang/String;Z)V
     319: aload         14
     321: areturn
     322: getstatic     #18                 // Field LOG:Lorg/eclipse/jetty/util/log/Logger;
     325: invokeinterface #55,  1           // InterfaceMethod org/eclipse/jetty/util/log/Logger.isDebugEnabled:()Z
     330: ifeq          368
     333: getstatic     #18                 // Field LOG:Lorg/eclipse/jetty/util/log/Logger;
     336: new           #22                 // class java/lang/StringBuilder
     339: dup
     340: invokespecial #23                 // Method java/lang/StringBuilder."<init>":()V
     343: ldc           #85                 // String Form authentication FAILED for
     345: invokevirtual #24                 // Method java/lang/StringBuilder.append:(Ljava/lang/String;)Ljava/lang/StringBuilder;
     348: aload         9
     350: invokestatic  #86                 // Method org/eclipse/jetty/util/StringUtil.printable:(Ljava/lang/String;)Ljava/lang/String;
     353: invokevirtual #24                 // Method java/lang/StringBuilder.append:(Ljava/lang/String;)Ljava/lang/StringBuilder;
     356: invokevirtual #25                 // Method java/lang/StringBuilder.toString:()Ljava/lang/String;
     359: iconst_0
     360: anewarray     #20                 // class java/lang/Object
     363: invokeinterface #58,  3           // InterfaceMethod org/eclipse/jetty/util/log/Logger.debug:(Ljava/lang/String;[Ljava/lang/Object;)V
     368: aload_0
     369: getfield      #33                 // Field _formErrorPage:Ljava/lang/String;
     372: ifnonnull     412
     375: getstatic     #18                 // Field LOG:Lorg/eclipse/jetty/util/log/Logger;
     378: ldc           #87                 // String auth failed {}->403
     380: iconst_1
     381: anewarray     #20                 // class java/lang/Object
     384: dup
     385: iconst_0
     386: aload         9
     388: aastore
     389: invokeinterface #58,  3           // InterfaceMethod org/eclipse/jetty/util/log/Logger.debug:(Ljava/lang/String;[Ljava/lang/Object;)V
     394: aload         5
     396: ifnull        572
     399: aload         5
     401: sipush        403
     404: invokeinterface #88,  2           // InterfaceMethod javax/servlet/http/HttpServletResponse.sendError:(I)V
     409: goto          572
     412: aload_0
     413: getfield      #5                  // Field _dispatch:Z
     416: ifeq          519
     419: getstatic     #18                 // Field LOG:Lorg/eclipse/jetty/util/log/Logger;
     422: ldc           #89                 // String auth failed {}=={}
     424: iconst_2
     425: anewarray     #20                 // class java/lang/Object
     428: dup
     429: iconst_0
     430: aload         9
     432: aastore
     433: dup
     434: iconst_1
     435: aload_0
     436: getfield      #33                 // Field _formErrorPage:Ljava/lang/String;
     439: aastore
     440: invokeinterface #58,  3           // InterfaceMethod org/eclipse/jetty/util/log/Logger.debug:(Ljava/lang/String;[Ljava/lang/Object;)V
     445: aload         4
     447: aload_0
     448: getfield      #33                 // Field _formErrorPage:Ljava/lang/String;
     451: invokeinterface #90,  2           // InterfaceMethod javax/servlet/http/HttpServletRequest.getRequestDispatcher:(Ljava/lang/String;)Ljavax/servlet/RequestDispatcher;
     456: astore        13
     458: aload         5
     460: getstatic     #91                 // Field org/eclipse/jetty/http/HttpHeader.CACHE_CONTROL:Lorg/eclipse/jetty/http/HttpHeader;
     463: invokevirtual #92                 // Method org/eclipse/jetty/http/HttpHeader.asString:()Ljava/lang/String;
     466: getstatic     #93                 // Field org/eclipse/jetty/http/HttpHeaderValue.NO_CACHE:Lorg/eclipse/jetty/http/HttpHeaderValue;
     469: invokevirtual #94                 // Method org/eclipse/jetty/http/HttpHeaderValue.asString:()Ljava/lang/String;
     472: invokeinterface #95,  3           // InterfaceMethod javax/servlet/http/HttpServletResponse.setHeader:(Ljava/lang/String;Ljava/lang/String;)V
     477: aload         5
     479: getstatic     #96                 // Field org/eclipse/jetty/http/HttpHeader.EXPIRES:Lorg/eclipse/jetty/http/HttpHeader;
     482: invokevirtual #92                 // Method org/eclipse/jetty/http/HttpHeader.asString:()Ljava/lang/String;
     485: lconst_1
     486: invokeinterface #97,  4           // InterfaceMethod javax/servlet/http/HttpServletResponse.setDateHeader:(Ljava/lang/String;J)V
     491: aload         13
     493: new           #98                 // class org/eclipse/jetty/security/authentication/FormAuthenticator$FormRequest
     496: dup
     497: aload         4
     499: invokespecial #99                 // Method org/eclipse/jetty/security/authentication/FormAuthenticator$FormRequest."<init>":(Ljavax/servlet/http/HttpServletRequest;)V
     502: new           #100                // class org/eclipse/jetty/security/authentication/FormAuthenticator$FormResponse
     505: dup
     506: aload         5
     508: invokespecial #101                // Method org/eclipse/jetty/security/authentication/FormAuthenticator$FormResponse."<init>":(Ljavax/servlet/http/HttpServletResponse;)V
     511: invokeinterface #102,  3          // InterfaceMethod javax/servlet/RequestDispatcher.forward:(Ljavax/servlet/ServletRequest;Ljavax/servlet/ServletResponse;)V
     516: goto          572
     519: getstatic     #18                 // Field LOG:Lorg/eclipse/jetty/util/log/Logger;
     522: ldc           #103                // String auth failed {}->{}
     524: iconst_2
     525: anewarray     #20                 // class java/lang/Object
     528: dup
     529: iconst_0
     530: aload         9
     532: aastore
     533: dup
     534: iconst_1
     535: aload_0
     536: getfield      #33                 // Field _formErrorPage:Ljava/lang/String;
     539: aastore
     540: invokeinterface #58,  3           // InterfaceMethod org/eclipse/jetty/util/log/Logger.debug:(Ljava/lang/String;[Ljava/lang/Object;)V
     545: aload         7
     547: aload         5
     549: aload         4
     551: invokeinterface #78,  1           // InterfaceMethod javax/servlet/http/HttpServletRequest.getContextPath:()Ljava/lang/String;
     556: aload_0
     557: getfield      #33                 // Field _formErrorPage:Ljava/lang/String;
     560: invokestatic  #70                 // Method org/eclipse/jetty/util/URIUtil.addPaths:(Ljava/lang/String;Ljava/lang/String;)Ljava/lang/String;
     563: invokeinterface #83,  2           // InterfaceMethod javax/servlet/http/HttpServletResponse.encodeRedirectURL:(Ljava/lang/String;)Ljava/lang/String;
     568: iconst_1
     569: invokevirtual #84                 // Method org/eclipse/jetty/server/Response.sendRedirect:(Ljava/lang/String;Z)V
     572: getstatic     #104                // Field org/eclipse/jetty/server/Authentication.SEND_FAILURE:Lorg/eclipse/jetty/server/Authentication;
     575: areturn
     576: aload         4
     578: iconst_0
     579: invokeinterface #37,  2           // InterfaceMethod javax/servlet/http/HttpServletRequest.getSession:(Z)Ljavax/servlet/http/HttpSession;
     584: astore        9
     586: aload         9
     588: ifnonnull     595
     591: aconst_null
     592: goto          607
     595: aload         9
     597: ldc           #41                 // String org.eclipse.jetty.security.UserIdentity
     599: invokeinterface #45,  2           // InterfaceMethod javax/servlet/http/HttpSession.getAttribute:(Ljava/lang/String;)Ljava/lang/Object;
     604: checkcast     #105                // class org/eclipse/jetty/server/Authentication
     607: astore        10
     609: aload         10
     611: ifnull        894
     614: aload         10
     616: instanceof    #106                // class org/eclipse/jetty/server/Authentication$User
     619: ifeq          682
     622: aload_0
     623: getfield      #107                // Field _loginService:Lorg/eclipse/jetty/security/LoginService;
     626: ifnull        682
     629: aload_0
     630: getfield      #107                // Field _loginService:Lorg/eclipse/jetty/security/LoginService;
     633: aload         10
     635: checkcast     #106                // class org/eclipse/jetty/server/Authentication$User
     638: invokeinterface #108,  1          // InterfaceMethod org/eclipse/jetty/server/Authentication$User.getUserIdentity:()Lorg/eclipse/jetty/server/UserIdentity;
     643: invokeinterface #109,  2          // InterfaceMethod org/eclipse/jetty/security/LoginService.validate:(Lorg/eclipse/jetty/server/UserIdentity;)Z
     648: ifne          682
     651: getstatic     #18                 // Field LOG:Lorg/eclipse/jetty/util/log/Logger;
     654: ldc           #110                // String auth revoked {}
     656: iconst_1
     657: anewarray     #20                 // class java/lang/Object
     660: dup
     661: iconst_0
     662: aload         10
     664: aastore
     665: invokeinterface #58,  3           // InterfaceMethod org/eclipse/jetty/util/log/Logger.debug:(Ljava/lang/String;[Ljava/lang/Object;)V
     670: aload         9
     672: ldc           #41                 // String org.eclipse.jetty.security.UserIdentity
     674: invokeinterface #44,  2           // InterfaceMethod javax/servlet/http/HttpSession.removeAttribute:(Ljava/lang/String;)V
     679: goto          894
     682: aload         9
     684: dup
     685: astore        11
     687: monitorenter
     688: aload         9
     690: ldc           #46                 // String org.eclipse.jetty.security.form_URI
     692: invokeinterface #45,  2           // InterfaceMethod javax/servlet/http/HttpSession.getAttribute:(Ljava/lang/String;)Ljava/lang/Object;
     697: checkcast     #47                 // class java/lang/String
     700: astore        12
     702: aload         12
     704: ifnull        858
     707: getstatic     #18                 // Field LOG:Lorg/eclipse/jetty/util/log/Logger;
     710: ldc           #111                // String auth retry {}->{}
     712: iconst_2
     713: anewarray     #20                 // class java/lang/Object
     716: dup
     717: iconst_0
     718: aload         10
     720: aastore
     721: dup
     722: iconst_1
     723: aload         12
     725: aastore
     726: invokeinterface #58,  3           // InterfaceMethod org/eclipse/jetty/util/log/Logger.debug:(Ljava/lang/String;[Ljava/lang/Object;)V
     731: aload         4
     733: invokeinterface #49,  1           // InterfaceMethod javax/servlet/http/HttpServletRequest.getRequestURL:()Ljava/lang/StringBuffer;
     738: astore        13
     740: aload         4
     742: invokeinterface #50,  1           // InterfaceMethod javax/servlet/http/HttpServletRequest.getQueryString:()Ljava/lang/String;
     747: ifnull        768
     750: aload         13
     752: ldc           #51                 // String ?
     754: invokevirtual #52                 // Method java/lang/StringBuffer.append:(Ljava/lang/String;)Ljava/lang/StringBuffer;
     757: aload         4
     759: invokeinterface #50,  1           // InterfaceMethod javax/servlet/http/HttpServletRequest.getQueryString:()Ljava/lang/String;
     764: invokevirtual #52                 // Method java/lang/StringBuffer.append:(Ljava/lang/String;)Ljava/lang/StringBuffer;
     767: pop
     768: aload         12
     770: aload         13
     772: invokevirtual #53                 // Method java/lang/StringBuffer.toString:()Ljava/lang/String;
     775: invokevirtual #54                 // Method java/lang/String.equals:(Ljava/lang/Object;)Z
     778: ifeq          858
     781: aload         9
     783: ldc           #112                // String org.eclipse.jetty.security.form_POST
     785: invokeinterface #45,  2           // InterfaceMethod javax/servlet/http/HttpSession.getAttribute:(Ljava/lang/String;)Ljava/lang/Object;
     790: checkcast     #113                // class org/eclipse/jetty/util/MultiMap
     793: astore        14
     795: aload         14
     797: ifnull        831
     800: getstatic     #18                 // Field LOG:Lorg/eclipse/jetty/util/log/Logger;
     803: ldc           #114                // String auth rePOST {}->{}
     805: iconst_2
     806: anewarray     #20                 // class java/lang/Object
     809: dup
     810: iconst_0
     811: aload         10
     813: aastore
     814: dup
     815: iconst_1
     816: aload         12
     818: aastore
     819: invokeinterface #58,  3           // InterfaceMethod org/eclipse/jetty/util/log/Logger.debug:(Ljava/lang/String;[Ljava/lang/Object;)V
     824: aload         6
     826: aload         14
     828: invokevirtual #115                // Method org/eclipse/jetty/server/Request.setContentParameters:(Lorg/eclipse/jetty/util/MultiMap;)V
     831: aload         9
     833: ldc           #46                 // String org.eclipse.jetty.security.form_URI
     835: invokeinterface #44,  2           // InterfaceMethod javax/servlet/http/HttpSession.removeAttribute:(Ljava/lang/String;)V
     840: aload         9
     842: ldc           #48                 // String org.eclipse.jetty.security.form_METHOD
     844: invokeinterface #44,  2           // InterfaceMethod javax/servlet/http/HttpSession.removeAttribute:(Ljava/lang/String;)V
     849: aload         9
     851: ldc           #112                // String org.eclipse.jetty.security.form_POST
     853: invokeinterface #44,  2           // InterfaceMethod javax/servlet/http/HttpSession.removeAttribute:(Ljava/lang/String;)V
     858: aload         11
     860: monitorexit
     861: goto          872
     864: astore        17
     866: aload         11
     868: monitorexit
     869: aload         17
     871: athrow
     872: getstatic     #18                 // Field LOG:Lorg/eclipse/jetty/util/log/Logger;
     875: ldc           #116                // String auth {}
     877: iconst_1
     878: anewarray     #20                 // class java/lang/Object
     881: dup
     882: iconst_0
     883: aload         10
     885: aastore
     886: invokeinterface #58,  3           // InterfaceMethod org/eclipse/jetty/util/log/Logger.debug:(Ljava/lang/String;[Ljava/lang/Object;)V
     891: aload         10
     893: areturn
     894: aload         5
     896: invokestatic  #72                 // Method org/eclipse/jetty/security/authentication/DeferredAuthentication.isDeferred:(Ljavax/servlet/http/HttpServletResponse;)Z
     899: ifeq          939
     902: getstatic     #18                 // Field LOG:Lorg/eclipse/jetty/util/log/Logger;
     905: ldc           #117                // String auth deferred {}
     907: iconst_1
     908: anewarray     #20                 // class java/lang/Object
     911: dup
     912: iconst_0
     913: aload         9
     915: ifnonnull     922
     918: aconst_null
     919: goto          929
     922: aload         9
     924: invokeinterface #118,  1          // InterfaceMethod javax/servlet/http/HttpSession.getId:()Ljava/lang/String;
     929: aastore
     930: invokeinterface #58,  3           // InterfaceMethod org/eclipse/jetty/util/log/Logger.debug:(Ljava/lang/String;[Ljava/lang/Object;)V
     935: getstatic     #119                // Field org/eclipse/jetty/server/Authentication.UNAUTHENTICATED:Lorg/eclipse/jetty/server/Authentication;
     938: areturn
     939: aload         9
     941: ifnull        949
     944: aload         9
     946: goto          957
     949: aload         4
     951: iconst_1
     952: invokeinterface #37,  2           // InterfaceMethod javax/servlet/http/HttpServletRequest.getSession:(Z)Ljavax/servlet/http/HttpSession;
     957: astore        9
     959: aload         9
     961: dup
     962: astore        11
     964: monitorenter
     965: aload         9
     967: ldc           #46                 // String org.eclipse.jetty.security.form_URI
     969: invokeinterface #45,  2           // InterfaceMethod javax/servlet/http/HttpSession.getAttribute:(Ljava/lang/String;)Ljava/lang/Object;
     974: ifnull        984
     977: aload_0
     978: getfield      #6                  // Field _alwaysSaveUri:Z
     981: ifeq          1109
     984: aload         4
     986: invokeinterface #49,  1           // InterfaceMethod javax/servlet/http/HttpServletRequest.getRequestURL:()Ljava/lang/StringBuffer;
     991: astore        12
     993: aload         4
     995: invokeinterface #50,  1           // InterfaceMethod javax/servlet/http/HttpServletRequest.getQueryString:()Ljava/lang/String;
    1000: ifnull        1021
    1003: aload         12
    1005: ldc           #51                 // String ?
    1007: invokevirtual #52                 // Method java/lang/StringBuffer.append:(Ljava/lang/String;)Ljava/lang/StringBuffer;
    1010: aload         4
    1012: invokeinterface #50,  1           // InterfaceMethod javax/servlet/http/HttpServletRequest.getQueryString:()Ljava/lang/String;
    1017: invokevirtual #52                 // Method java/lang/StringBuffer.append:(Ljava/lang/String;)Ljava/lang/StringBuffer;
    1020: pop
    1021: aload         9
    1023: ldc           #46                 // String org.eclipse.jetty.security.form_URI
    1025: aload         12
    1027: invokevirtual #53                 // Method java/lang/StringBuffer.toString:()Ljava/lang/String;
    1030: invokeinterface #42,  3           // InterfaceMethod javax/servlet/http/HttpSession.setAttribute:(Ljava/lang/String;Ljava/lang/Object;)V
    1035: aload         9
    1037: ldc           #48                 // String org.eclipse.jetty.security.form_METHOD
    1039: aload         4
    1041: invokeinterface #57,  1           // InterfaceMethod javax/servlet/http/HttpServletRequest.getMethod:()Ljava/lang/String;
    1046: invokeinterface #42,  3           // InterfaceMethod javax/servlet/http/HttpSession.setAttribute:(Ljava/lang/String;Ljava/lang/Object;)V
    1051: getstatic     #120                // Field org/eclipse/jetty/http/MimeTypes$Type.FORM_ENCODED:Lorg/eclipse/jetty/http/MimeTypes$Type;
    1054: aload_1
    1055: invokeinterface #121,  1          // InterfaceMethod javax/servlet/ServletRequest.getContentType:()Ljava/lang/String;
    1060: invokevirtual #122                // Method org/eclipse/jetty/http/MimeTypes$Type.is:(Ljava/lang/String;)Z
    1063: ifeq          1109
    1066: getstatic     #123                // Field org/eclipse/jetty/http/HttpMethod.POST:Lorg/eclipse/jetty/http/HttpMethod;
    1069: aload         4
    1071: invokeinterface #57,  1           // InterfaceMethod javax/servlet/http/HttpServletRequest.getMethod:()Ljava/lang/String;
    1076: invokevirtual #124                // Method org/eclipse/jetty/http/HttpMethod.is:(Ljava/lang/String;)Z
    1079: ifeq          1109
    1082: new           #113                // class org/eclipse/jetty/util/MultiMap
    1085: dup
    1086: invokespecial #125                // Method org/eclipse/jetty/util/MultiMap."<init>":()V
    1089: astore        13
    1091: aload         6
    1093: aload         13
    1095: invokevirtual #126                // Method org/eclipse/jetty/server/Request.extractFormParameters:(Lorg/eclipse/jetty/util/MultiMap;)V
    1098: aload         9
    1100: ldc           #112                // String org.eclipse.jetty.security.form_POST
    1102: aload         13
    1104: invokeinterface #42,  3           // InterfaceMethod javax/servlet/http/HttpSession.setAttribute:(Ljava/lang/String;Ljava/lang/Object;)V
    1109: aload         11
    1111: monitorexit
    1112: goto          1123
    1115: astore        18
    1117: aload         11
    1119: monitorexit
    1120: aload         18
    1122: athrow
    1123: aload_0
    1124: getfield      #5                  // Field _dispatch:Z
    1127: ifeq          1235
    1130: getstatic     #18                 // Field LOG:Lorg/eclipse/jetty/util/log/Logger;
    1133: ldc           #127                // String challenge {}=={}
    1135: iconst_2
    1136: anewarray     #20                 // class java/lang/Object
    1139: dup
    1140: iconst_0
    1141: aload         9
    1143: invokeinterface #118,  1          // InterfaceMethod javax/servlet/http/HttpSession.getId:()Ljava/lang/String;
    1148: aastore
    1149: dup
    1150: iconst_1
    1151: aload_0
    1152: getfield      #26                 // Field _formLoginPage:Ljava/lang/String;
    1155: aastore
    1156: invokeinterface #58,  3           // InterfaceMethod org/eclipse/jetty/util/log/Logger.debug:(Ljava/lang/String;[Ljava/lang/Object;)V
    1161: aload         4
    1163: aload_0
    1164: getfield      #26                 // Field _formLoginPage:Ljava/lang/String;
    1167: invokeinterface #90,  2           // InterfaceMethod javax/servlet/http/HttpServletRequest.getRequestDispatcher:(Ljava/lang/String;)Ljavax/servlet/RequestDispatcher;
    1172: astore        11
    1174: aload         5
    1176: getstatic     #91                 // Field org/eclipse/jetty/http/HttpHeader.CACHE_CONTROL:Lorg/eclipse/jetty/http/HttpHeader;
    1179: invokevirtual #92                 // Method org/eclipse/jetty/http/HttpHeader.asString:()Ljava/lang/String;
    1182: getstatic     #93                 // Field org/eclipse/jetty/http/HttpHeaderValue.NO_CACHE:Lorg/eclipse/jetty/http/HttpHeaderValue;
    1185: invokevirtual #94                 // Method org/eclipse/jetty/http/HttpHeaderValue.asString:()Ljava/lang/String;
    1188: invokeinterface #95,  3           // InterfaceMethod javax/servlet/http/HttpServletResponse.setHeader:(Ljava/lang/String;Ljava/lang/String;)V
    1193: aload         5
    1195: getstatic     #96                 // Field org/eclipse/jetty/http/HttpHeader.EXPIRES:Lorg/eclipse/jetty/http/HttpHeader;
    1198: invokevirtual #92                 // Method org/eclipse/jetty/http/HttpHeader.asString:()Ljava/lang/String;
    1201: lconst_1
    1202: invokeinterface #97,  4           // InterfaceMethod javax/servlet/http/HttpServletResponse.setDateHeader:(Ljava/lang/String;J)V
    1207: aload         11
    1209: new           #98                 // class org/eclipse/jetty/security/authentication/FormAuthenticator$FormRequest
    1212: dup
    1213: aload         4
    1215: invokespecial #99                 // Method org/eclipse/jetty/security/authentication/FormAuthenticator$FormRequest."<init>":(Ljavax/servlet/http/HttpServletRequest;)V
    1218: new           #100                // class org/eclipse/jetty/security/authentication/FormAuthenticator$FormResponse
    1221: dup
    1222: aload         5
    1224: invokespecial #101                // Method org/eclipse/jetty/security/authentication/FormAuthenticator$FormResponse."<init>":(Ljavax/servlet/http/HttpServletResponse;)V
    1227: invokeinterface #102,  3          // InterfaceMethod javax/servlet/RequestDispatcher.forward:(Ljavax/servlet/ServletRequest;Ljavax/servlet/ServletResponse;)V
    1232: goto          1293
    1235: getstatic     #18                 // Field LOG:Lorg/eclipse/jetty/util/log/Logger;
    1238: ldc           #128                // String challenge {}->{}
    1240: iconst_2
    1241: anewarray     #20                 // class java/lang/Object
    1244: dup
    1245: iconst_0
    1246: aload         9
    1248: invokeinterface #118,  1          // InterfaceMethod javax/servlet/http/HttpSession.getId:()Ljava/lang/String;
    1253: aastore
    1254: dup
    1255: iconst_1
    1256: aload_0
    1257: getfield      #26                 // Field _formLoginPage:Ljava/lang/String;
    1260: aastore
    1261: invokeinterface #58,  3           // InterfaceMethod org/eclipse/jetty/util/log/Logger.debug:(Ljava/lang/String;[Ljava/lang/Object;)V
    1266: aload         7
    1268: aload         5
    1270: aload         4
    1272: invokeinterface #78,  1           // InterfaceMethod javax/servlet/http/HttpServletRequest.getContextPath:()Ljava/lang/String;
    1277: aload_0
    1278: getfield      #26                 // Field _formLoginPage:Ljava/lang/String;
    1281: invokestatic  #70                 // Method org/eclipse/jetty/util/URIUtil.addPaths:(Ljava/lang/String;Ljava/lang/String;)Ljava/lang/String;
    1284: invokeinterface #83,  2           // InterfaceMethod javax/servlet/http/HttpServletResponse.encodeRedirectURL:(Ljava/lang/String;)Ljava/lang/String;
    1289: iconst_1
    1290: invokevirtual #84                 // Method org/eclipse/jetty/server/Response.sendRedirect:(Ljava/lang/String;Z)V
    1293: getstatic     #129                // Field org/eclipse/jetty/server/Authentication.SEND_CONTINUE:Lorg/eclipse/jetty/server/Authentication;
    1296: areturn
    1297: astore        9
    1299: new           #132                // class org/eclipse/jetty/security/ServerAuthException
    1302: dup
    1303: aload         9
    1305: invokespecial #133                // Method org/eclipse/jetty/security/ServerAuthException."<init>":(Ljava/lang/Throwable;)V
    1308: athrow
    Exception table:
       from    to  target type
         195   261   264   any
         264   269   264   any
         688   861   864   any
         864   869   864   any
         965  1112  1115   any
        1115  1120  1115   any
         107   321  1297   Class java/io/IOException
         107   321  1297   Class javax/servlet/ServletException
         322   575  1297   Class java/io/IOException
         322   575  1297   Class javax/servlet/ServletException
         576   893  1297   Class java/io/IOException
         576   893  1297   Class javax/servlet/ServletException
         894   938  1297   Class java/io/IOException
         894   938  1297   Class javax/servlet/ServletException
         939  1296  1297   Class java/io/IOException
         939  1296  1297   Class javax/servlet/ServletException

  public boolean isJSecurityCheck(java.lang.String);
    Code:
       0: aload_1
       1: ldc           #134                // String /j_security_check
       3: invokevirtual #135                // Method java/lang/String.indexOf:(Ljava/lang/String;)I
       6: istore_2
       7: iload_2
       8: ifge          13
      11: iconst_0
      12: ireturn
      13: iload_2
      14: ldc           #134                // String /j_security_check
      16: invokevirtual #31                 // Method java/lang/String.length:()I
      19: iadd
      20: istore_3
      21: iload_3
      22: aload_1
      23: invokevirtual #31                 // Method java/lang/String.length:()I
      26: if_icmpne     31
      29: iconst_1
      30: ireturn
      31: aload_1
      32: iload_3
      33: invokevirtual #136                // Method java/lang/String.charAt:(I)C
      36: istore        4
      38: iload         4
      40: bipush        59
      42: if_icmpeq     66
      45: iload         4
      47: bipush        35
      49: if_icmpeq     66
      52: iload         4
      54: bipush        47
      56: if_icmpeq     66
      59: iload         4
      61: bipush        63
      63: if_icmpne     70
      66: iconst_1
      67: goto          71
      70: iconst_0
      71: ireturn

  public boolean isLoginOrErrorPage(java.lang.String);
    Code:
       0: aload_1
       1: ifnull        30
       4: aload_1
       5: aload_0
       6: getfield      #32                 // Field _formErrorPath:Ljava/lang/String;
       9: invokevirtual #54                 // Method java/lang/String.equals:(Ljava/lang/Object;)Z
      12: ifne          26
      15: aload_1
      16: aload_0
      17: getfield      #27                 // Field _formLoginPath:Ljava/lang/String;
      20: invokevirtual #54                 // Method java/lang/String.equals:(Ljava/lang/Object;)Z
      23: ifeq          30
      26: iconst_1
      27: goto          31
      30: iconst_0
      31: ireturn

  public boolean secureResponse(javax.servlet.ServletRequest, javax.servlet.ServletResponse, boolean, org.eclipse.jetty.server.Authentication$User) throws org.eclipse.jetty.security.ServerAuthException;
    Code:
       0: iconst_1
       1: ireturn

  static {};
    Code:
       0: ldc           #8                  // class org/eclipse/jetty/security/authentication/FormAuthenticator
       2: invokestatic  #137                // Method org/eclipse/jetty/util/log/Log.getLogger:(Ljava/lang/Class;)Lorg/eclipse/jetty/util/log/Logger;
       5: putstatic     #18                 // Field LOG:Lorg/eclipse/jetty/util/log/Logger;
       8: return
}
