Compiled from "AbstractReflectionConverter.java"
public abstract class com.thoughtworks.xstream.converters.reflection.AbstractReflectionConverter implements com.thoughtworks.xstream.converters.Converter,com.thoughtworks.xstream.core.Caching {
  protected final com.thoughtworks.xstream.converters.reflection.ReflectionProvider reflectionProvider;

  protected final com.thoughtworks.xstream.mapper.Mapper mapper;

  protected transient com.thoughtworks.xstream.converters.reflection.SerializationMethodInvoker serializationMethodInvoker;

  private transient com.thoughtworks.xstream.converters.reflection.ReflectionProvider pureJavaReflectionProvider;

  public com.thoughtworks.xstream.converters.reflection.AbstractReflectionConverter(com.thoughtworks.xstream.mapper.Mapper, com.thoughtworks.xstream.converters.reflection.ReflectionProvider);
    Code:
       0: aload_0
       1: invokespecial #1                  // Method java/lang/Object."<init>":()V
       4: aload_0
       5: aload_1
       6: putfield      #2                  // Field mapper:Lcom/thoughtworks/xstream/mapper/Mapper;
       9: aload_0
      10: aload_2
      11: putfield      #3                  // Field reflectionProvider:Lcom/thoughtworks/xstream/converters/reflection/ReflectionProvider;
      14: aload_0
      15: new           #4                  // class com/thoughtworks/xstream/converters/reflection/SerializationMethodInvoker
      18: dup
      19: invokespecial #5                  // Method com/thoughtworks/xstream/converters/reflection/SerializationMethodInvoker."<init>":()V
      22: putfield      #6                  // Field serializationMethodInvoker:Lcom/thoughtworks/xstream/converters/reflection/SerializationMethodInvoker;
      25: return

  public void marshal(java.lang.Object, com.thoughtworks.xstream.io.HierarchicalStreamWriter, com.thoughtworks.xstream.converters.MarshallingContext);
    Code:
       0: aload_0
       1: getfield      #6                  // Field serializationMethodInvoker:Lcom/thoughtworks/xstream/converters/reflection/SerializationMethodInvoker;
       4: aload_1
       5: invokevirtual #7                  // Method com/thoughtworks/xstream/converters/reflection/SerializationMethodInvoker.callWriteReplace:(Ljava/lang/Object;)Ljava/lang/Object;
       8: astore        4
      10: aload         4
      12: aload_1
      13: if_acmpeq     35
      16: aload_3
      17: instanceof    #8                  // class com/thoughtworks/xstream/core/ReferencingMarshallingContext
      20: ifeq          35
      23: aload_3
      24: checkcast     #8                  // class com/thoughtworks/xstream/core/ReferencingMarshallingContext
      27: aload_1
      28: aload         4
      30: invokeinterface #9,  3            // InterfaceMethod com/thoughtworks/xstream/core/ReferencingMarshallingContext.replace:(Ljava/lang/Object;Ljava/lang/Object;)V
      35: aload         4
      37: invokevirtual #10                 // Method java/lang/Object.getClass:()Ljava/lang/Class;
      40: aload_1
      41: invokevirtual #10                 // Method java/lang/Object.getClass:()Ljava/lang/Class;
      44: if_acmpeq     98
      47: aload_0
      48: getfield      #2                  // Field mapper:Lcom/thoughtworks/xstream/mapper/Mapper;
      51: ldc           #11                 // String resolves-to
      53: invokeinterface #12,  2           // InterfaceMethod com/thoughtworks/xstream/mapper/Mapper.aliasForSystemAttribute:(Ljava/lang/String;)Ljava/lang/String;
      58: astore        5
      60: aload         5
      62: ifnull        87
      65: aload_2
      66: aload         5
      68: aload_0
      69: getfield      #2                  // Field mapper:Lcom/thoughtworks/xstream/mapper/Mapper;
      72: aload         4
      74: invokevirtual #10                 // Method java/lang/Object.getClass:()Ljava/lang/Class;
      77: invokeinterface #13,  2           // InterfaceMethod com/thoughtworks/xstream/mapper/Mapper.serializedClass:(Ljava/lang/Class;)Ljava/lang/String;
      82: invokeinterface #14,  3           // InterfaceMethod com/thoughtworks/xstream/io/HierarchicalStreamWriter.addAttribute:(Ljava/lang/String;Ljava/lang/String;)V
      87: aload_3
      88: aload         4
      90: invokeinterface #15,  2           // InterfaceMethod com/thoughtworks/xstream/converters/MarshallingContext.convertAnother:(Ljava/lang/Object;)V
      95: goto          106
      98: aload_0
      99: aload         4
     101: aload_2
     102: aload_3
     103: invokevirtual #16                 // Method doMarshal:(Ljava/lang/Object;Lcom/thoughtworks/xstream/io/HierarchicalStreamWriter;Lcom/thoughtworks/xstream/converters/MarshallingContext;)V
     106: return

  protected void doMarshal(java.lang.Object, com.thoughtworks.xstream.io.HierarchicalStreamWriter, com.thoughtworks.xstream.converters.MarshallingContext);
    Code:
       0: new           #17                 // class java/util/ArrayList
       3: dup
       4: invokespecial #18                 // Method java/util/ArrayList."<init>":()V
       7: astore        4
       9: new           #19                 // class java/util/HashMap
      12: dup
      13: invokespecial #20                 // Method java/util/HashMap."<init>":()V
      16: astore        5
      18: aload_0
      19: getfield      #3                  // Field reflectionProvider:Lcom/thoughtworks/xstream/converters/reflection/ReflectionProvider;
      22: aload_1
      23: new           #21                 // class com/thoughtworks/xstream/converters/reflection/AbstractReflectionConverter$1
      26: dup
      27: aload_0
      28: aload         5
      30: aload_1
      31: aload_2
      32: aload         4
      34: invokespecial #22                 // Method com/thoughtworks/xstream/converters/reflection/AbstractReflectionConverter$1."<init>":(Lcom/thoughtworks/xstream/converters/reflection/AbstractReflectionConverter;Ljava/util/Map;Ljava/lang/Object;Lcom/thoughtworks/xstream/io/HierarchicalStreamWriter;Ljava/util/List;)V
      37: invokeinterface #23,  3           // InterfaceMethod com/thoughtworks/xstream/converters/reflection/ReflectionProvider.visitSerializableFields:(Ljava/lang/Object;Lcom/thoughtworks/xstream/converters/reflection/ReflectionProvider$Visitor;)V
      42: new           #24                 // class com/thoughtworks/xstream/converters/reflection/AbstractReflectionConverter$2
      45: dup
      46: aload_0
      47: aload         4
      49: aload_1
      50: aload_3
      51: aload_2
      52: aload         5
      54: invokespecial #25                 // Method com/thoughtworks/xstream/converters/reflection/AbstractReflectionConverter$2."<init>":(Lcom/thoughtworks/xstream/converters/reflection/AbstractReflectionConverter;Ljava/util/List;Ljava/lang/Object;Lcom/thoughtworks/xstream/converters/MarshallingContext;Lcom/thoughtworks/xstream/io/HierarchicalStreamWriter;Ljava/util/Map;)V
      57: pop
      58: return

  protected void marshallField(com.thoughtworks.xstream.converters.MarshallingContext, java.lang.Object, java.lang.reflect.Field);
    Code:
       0: aload_1
       1: aload_2
       2: aload_0
       3: getfield      #2                  // Field mapper:Lcom/thoughtworks/xstream/mapper/Mapper;
       6: aload_3
       7: invokevirtual #26                 // Method java/lang/reflect/Field.getDeclaringClass:()Ljava/lang/Class;
      10: aload_3
      11: invokevirtual #27                 // Method java/lang/reflect/Field.getName:()Ljava/lang/String;
      14: invokeinterface #28,  3           // InterfaceMethod com/thoughtworks/xstream/mapper/Mapper.getLocalConverter:(Ljava/lang/Class;Ljava/lang/String;)Lcom/thoughtworks/xstream/converters/Converter;
      19: invokeinterface #29,  3           // InterfaceMethod com/thoughtworks/xstream/converters/MarshallingContext.convertAnother:(Ljava/lang/Object;Lcom/thoughtworks/xstream/converters/Converter;)V
      24: return

  public java.lang.Object unmarshal(com.thoughtworks.xstream.io.HierarchicalStreamReader, com.thoughtworks.xstream.converters.UnmarshallingContext);
    Code:
       0: aload_0
       1: aload_1
       2: aload_2
       3: invokevirtual #30                 // Method instantiateNewInstance:(Lcom/thoughtworks/xstream/io/HierarchicalStreamReader;Lcom/thoughtworks/xstream/converters/UnmarshallingContext;)Ljava/lang/Object;
       6: astore_3
       7: aload_0
       8: aload_3
       9: aload_1
      10: aload_2
      11: invokevirtual #31                 // Method doUnmarshal:(Ljava/lang/Object;Lcom/thoughtworks/xstream/io/HierarchicalStreamReader;Lcom/thoughtworks/xstream/converters/UnmarshallingContext;)Ljava/lang/Object;
      14: astore_3
      15: aload_0
      16: getfield      #6                  // Field serializationMethodInvoker:Lcom/thoughtworks/xstream/converters/reflection/SerializationMethodInvoker;
      19: aload_3
      20: invokevirtual #32                 // Method com/thoughtworks/xstream/converters/reflection/SerializationMethodInvoker.callReadResolve:(Ljava/lang/Object;)Ljava/lang/Object;
      23: areturn

  public java.lang.Object doUnmarshal(java.lang.Object, com.thoughtworks.xstream.io.HierarchicalStreamReader, com.thoughtworks.xstream.converters.UnmarshallingContext);
    Code:
       0: new           #33                 // class com/thoughtworks/xstream/converters/reflection/AbstractReflectionConverter$3
       3: dup
       4: aload_0
       5: invokespecial #34                 // Method com/thoughtworks/xstream/converters/reflection/AbstractReflectionConverter$3."<init>":(Lcom/thoughtworks/xstream/converters/reflection/AbstractReflectionConverter;)V
       8: astore        4
      10: aload_2
      11: invokeinterface #35,  1           // InterfaceMethod com/thoughtworks/xstream/io/HierarchicalStreamReader.getAttributeNames:()Ljava/util/Iterator;
      16: astore        5
      18: aload         5
      20: invokeinterface #36,  1           // InterfaceMethod java/util/Iterator.hasNext:()Z
      25: ifeq          319
      28: aload         5
      30: invokeinterface #37,  1           // InterfaceMethod java/util/Iterator.next:()Ljava/lang/Object;
      35: checkcast     #38                 // class java/lang/String
      38: astore        6
      40: aload_0
      41: getfield      #2                  // Field mapper:Lcom/thoughtworks/xstream/mapper/Mapper;
      44: aload_1
      45: invokevirtual #10                 // Method java/lang/Object.getClass:()Ljava/lang/Class;
      48: aload_0
      49: getfield      #2                  // Field mapper:Lcom/thoughtworks/xstream/mapper/Mapper;
      52: aload         6
      54: invokeinterface #39,  2           // InterfaceMethod com/thoughtworks/xstream/mapper/Mapper.attributeForAlias:(Ljava/lang/String;)Ljava/lang/String;
      59: invokeinterface #40,  3           // InterfaceMethod com/thoughtworks/xstream/mapper/Mapper.realMember:(Ljava/lang/Class;Ljava/lang/String;)Ljava/lang/String;
      64: astore        7
      66: aload_0
      67: getfield      #3                  // Field reflectionProvider:Lcom/thoughtworks/xstream/converters/reflection/ReflectionProvider;
      70: aload         7
      72: aload_1
      73: invokevirtual #10                 // Method java/lang/Object.getClass:()Ljava/lang/Class;
      76: invokeinterface #41,  3           // InterfaceMethod com/thoughtworks/xstream/converters/reflection/ReflectionProvider.fieldDefinedInClass:(Ljava/lang/String;Ljava/lang/Class;)Z
      81: istore        8
      83: iload         8
      85: ifeq          316
      88: aload_0
      89: getfield      #3                  // Field reflectionProvider:Lcom/thoughtworks/xstream/converters/reflection/ReflectionProvider;
      92: aload_1
      93: invokevirtual #10                 // Method java/lang/Object.getClass:()Ljava/lang/Class;
      96: aload         7
      98: invokeinterface #42,  3           // InterfaceMethod com/thoughtworks/xstream/converters/reflection/ReflectionProvider.getField:(Ljava/lang/Class;Ljava/lang/String;)Ljava/lang/reflect/Field;
     103: astore        9
     105: aload         9
     107: invokevirtual #43                 // Method java/lang/reflect/Field.getModifiers:()I
     110: invokestatic  #44                 // Method java/lang/reflect/Modifier.isTransient:(I)Z
     113: ifeq          126
     116: aload_0
     117: invokevirtual #45                 // Method shouldUnmarshalTransientFields:()Z
     120: ifne          126
     123: goto          18
     126: aload         9
     128: invokevirtual #26                 // Method java/lang/reflect/Field.getDeclaringClass:()Ljava/lang/Class;
     131: astore        10
     133: aload_0
     134: getfield      #2                  // Field mapper:Lcom/thoughtworks/xstream/mapper/Mapper;
     137: aload         10
     139: aload         7
     141: invokeinterface #46,  3           // InterfaceMethod com/thoughtworks/xstream/mapper/Mapper.shouldSerializeMember:(Ljava/lang/Class;Ljava/lang/String;)Z
     146: ifne          152
     149: goto          18
     152: aload_0
     153: getfield      #2                  // Field mapper:Lcom/thoughtworks/xstream/mapper/Mapper;
     156: aload         10
     158: aload         7
     160: aload         9
     162: invokevirtual #47                 // Method java/lang/reflect/Field.getType:()Ljava/lang/Class;
     165: invokeinterface #48,  4           // InterfaceMethod com/thoughtworks/xstream/mapper/Mapper.getConverterFromAttribute:(Ljava/lang/Class;Ljava/lang/String;Ljava/lang/Class;)Lcom/thoughtworks/xstream/converters/SingleValueConverter;
     170: astore        11
     172: aload         9
     174: invokevirtual #47                 // Method java/lang/reflect/Field.getType:()Ljava/lang/Class;
     177: astore        12
     179: aload         11
     181: ifnull        316
     184: aload         11
     186: aload_2
     187: aload         6
     189: invokeinterface #49,  2           // InterfaceMethod com/thoughtworks/xstream/io/HierarchicalStreamReader.getAttribute:(Ljava/lang/String;)Ljava/lang/String;
     194: invokeinterface #50,  2           // InterfaceMethod com/thoughtworks/xstream/converters/SingleValueConverter.fromString:(Ljava/lang/String;)Ljava/lang/Object;
     199: astore        13
     201: aload         12
     203: invokevirtual #51                 // Method java/lang/Class.isPrimitive:()Z
     206: ifeq          216
     209: aload         12
     211: invokestatic  #52                 // Method com/thoughtworks/xstream/core/util/Primitives.box:(Ljava/lang/Class;)Ljava/lang/Class;
     214: astore        12
     216: aload         13
     218: ifnull        281
     221: aload         12
     223: aload         13
     225: invokevirtual #10                 // Method java/lang/Object.getClass:()Ljava/lang/Class;
     228: invokevirtual #53                 // Method java/lang/Class.isAssignableFrom:(Ljava/lang/Class;)Z
     231: ifne          281
     234: new           #54                 // class com/thoughtworks/xstream/converters/ConversionException
     237: dup
     238: new           #55                 // class java/lang/StringBuilder
     241: dup
     242: invokespecial #56                 // Method java/lang/StringBuilder."<init>":()V
     245: ldc           #57                 // String Cannot convert type
     247: invokevirtual #58                 // Method java/lang/StringBuilder.append:(Ljava/lang/String;)Ljava/lang/StringBuilder;
     250: aload         13
     252: invokevirtual #10                 // Method java/lang/Object.getClass:()Ljava/lang/Class;
     255: invokevirtual #59                 // Method java/lang/Class.getName:()Ljava/lang/String;
     258: invokevirtual #58                 // Method java/lang/StringBuilder.append:(Ljava/lang/String;)Ljava/lang/StringBuilder;
     261: ldc           #60                 // String  to type
     263: invokevirtual #58                 // Method java/lang/StringBuilder.append:(Ljava/lang/String;)Ljava/lang/StringBuilder;
     266: aload         12
     268: invokevirtual #59                 // Method java/lang/Class.getName:()Ljava/lang/String;
     271: invokevirtual #58                 // Method java/lang/StringBuilder.append:(Ljava/lang/String;)Ljava/lang/StringBuilder;
     274: invokevirtual #61                 // Method java/lang/StringBuilder.toString:()Ljava/lang/String;
     277: invokespecial #62                 // Method com/thoughtworks/xstream/converters/ConversionException."<init>":(Ljava/lang/String;)V
     280: athrow
     281: aload         4
     283: new           #63                 // class com/thoughtworks/xstream/core/util/FastField
     286: dup
     287: aload         10
     289: aload         7
     291: invokespecial #64                 // Method com/thoughtworks/xstream/core/util/FastField."<init>":(Ljava/lang/Class;Ljava/lang/String;)V
     294: invokeinterface #65,  2           // InterfaceMethod java/util/Set.add:(Ljava/lang/Object;)Z
     299: pop
     300: aload_0
     301: getfield      #3                  // Field reflectionProvider:Lcom/thoughtworks/xstream/converters/reflection/ReflectionProvider;
     304: aload_1
     305: aload         7
     307: aload         13
     309: aload         10
     311: invokeinterface #66,  5           // InterfaceMethod com/thoughtworks/xstream/converters/reflection/ReflectionProvider.writeField:(Ljava/lang/Object;Ljava/lang/String;Ljava/lang/Object;Ljava/lang/Class;)V
     316: goto          18
     319: aconst_null
     320: astore        6
     322: aload_2
     323: invokeinterface #67,  1           // InterfaceMethod com/thoughtworks/xstream/io/HierarchicalStreamReader.hasMoreChildren:()Z
     328: ifeq          838
     331: aload_2
     332: invokeinterface #68,  1           // InterfaceMethod com/thoughtworks/xstream/io/HierarchicalStreamReader.moveDown:()V
     337: aload_2
     338: invokeinterface #69,  1           // InterfaceMethod com/thoughtworks/xstream/io/HierarchicalStreamReader.getNodeName:()Ljava/lang/String;
     343: astore        7
     345: aload_0
     346: aload_2
     347: invokespecial #70                 // Method determineWhichClassDefinesField:(Lcom/thoughtworks/xstream/io/HierarchicalStreamReader;)Ljava/lang/Class;
     350: astore        8
     352: aload         8
     354: ifnonnull     364
     357: aload_1
     358: invokevirtual #10                 // Method java/lang/Object.getClass:()Ljava/lang/Class;
     361: goto          366
     364: aload         8
     366: astore        9
     368: aload_0
     369: getfield      #2                  // Field mapper:Lcom/thoughtworks/xstream/mapper/Mapper;
     372: aload         9
     374: aload         7
     376: invokeinterface #40,  3           // InterfaceMethod com/thoughtworks/xstream/mapper/Mapper.realMember:(Ljava/lang/Class;Ljava/lang/String;)Ljava/lang/String;
     381: astore        10
     383: aload_0
     384: getfield      #2                  // Field mapper:Lcom/thoughtworks/xstream/mapper/Mapper;
     387: aload         9
     389: aload         10
     391: invokeinterface #71,  3           // InterfaceMethod com/thoughtworks/xstream/mapper/Mapper.getImplicitCollectionDefForFieldName:(Ljava/lang/Class;Ljava/lang/String;)Lcom/thoughtworks/xstream/mapper/Mapper$ImplicitCollectionMapping;
     396: astore        11
     398: aload         11
     400: ifnonnull     423
     403: aload_0
     404: getfield      #3                  // Field reflectionProvider:Lcom/thoughtworks/xstream/converters/reflection/ReflectionProvider;
     407: aload         10
     409: aload         9
     411: invokeinterface #41,  3           // InterfaceMethod com/thoughtworks/xstream/converters/reflection/ReflectionProvider.fieldDefinedInClass:(Ljava/lang/String;Ljava/lang/Class;)Z
     416: ifeq          423
     419: iconst_1
     420: goto          424
     423: iconst_0
     424: istore        12
     426: aload         11
     428: ifnull        441
     431: aload         11
     433: invokeinterface #72,  1           // InterfaceMethod com/thoughtworks/xstream/mapper/Mapper$ImplicitCollectionMapping.getItemType:()Ljava/lang/Class;
     438: ifnonnull     456
     441: aload_0
     442: aload_2
     443: iload         12
     445: aload_1
     446: aload         10
     448: aload         8
     450: invokespecial #73                 // Method determineType:(Lcom/thoughtworks/xstream/io/HierarchicalStreamReader;ZLjava/lang/Object;Ljava/lang/String;Ljava/lang/Class;)Ljava/lang/Class;
     453: goto          463
     456: aload         11
     458: invokeinterface #72,  1           // InterfaceMethod com/thoughtworks/xstream/mapper/Mapper$ImplicitCollectionMapping.getItemType:()Ljava/lang/Class;
     463: astore        13
     465: iload         12
     467: ifeq          586
     470: aload_0
     471: getfield      #3                  // Field reflectionProvider:Lcom/thoughtworks/xstream/converters/reflection/ReflectionProvider;
     474: aload         8
     476: ifnull        484
     479: aload         8
     481: goto          488
     484: aload_1
     485: invokevirtual #10                 // Method java/lang/Object.getClass:()Ljava/lang/Class;
     488: aload         10
     490: invokeinterface #42,  3           // InterfaceMethod com/thoughtworks/xstream/converters/reflection/ReflectionProvider.getField:(Ljava/lang/Class;Ljava/lang/String;)Ljava/lang/reflect/Field;
     495: astore        15
     497: aload         15
     499: invokevirtual #43                 // Method java/lang/reflect/Field.getModifiers:()I
     502: invokestatic  #44                 // Method java/lang/reflect/Modifier.isTransient:(I)Z
     505: ifeq          515
     508: aload_0
     509: invokevirtual #45                 // Method shouldUnmarshalTransientFields:()Z
     512: ifeq          534
     515: aload_0
     516: getfield      #2                  // Field mapper:Lcom/thoughtworks/xstream/mapper/Mapper;
     519: aload         15
     521: invokevirtual #26                 // Method java/lang/reflect/Field.getDeclaringClass:()Ljava/lang/Class;
     524: aload         10
     526: invokeinterface #46,  3           // InterfaceMethod com/thoughtworks/xstream/mapper/Mapper.shouldSerializeMember:(Ljava/lang/Class;Ljava/lang/String;)Z
     531: ifne          543
     534: aload_2
     535: invokeinterface #74,  1           // InterfaceMethod com/thoughtworks/xstream/io/HierarchicalStreamReader.moveUp:()V
     540: goto          322
     543: aload_0
     544: aload_3
     545: aload_1
     546: aload         13
     548: aload         15
     550: invokevirtual #75                 // Method unmarshallField:(Lcom/thoughtworks/xstream/converters/UnmarshallingContext;Ljava/lang/Object;Ljava/lang/Class;Ljava/lang/reflect/Field;)Ljava/lang/Object;
     553: astore        14
     555: aload_0
     556: getfield      #3                  // Field reflectionProvider:Lcom/thoughtworks/xstream/converters/reflection/ReflectionProvider;
     559: aload_1
     560: aload         10
     562: aload         8
     564: invokeinterface #76,  4           // InterfaceMethod com/thoughtworks/xstream/converters/reflection/ReflectionProvider.getFieldType:(Ljava/lang/Object;Ljava/lang/String;Ljava/lang/Class;)Ljava/lang/Class;
     569: astore        16
     571: aload         16
     573: invokevirtual #51                 // Method java/lang/Class.isPrimitive:()Z
     576: ifne          583
     579: aload         16
     581: astore        13
     583: goto          702
     586: ldc_w         #77                 // class java/util/Map$Entry
     589: aload         13
     591: invokevirtual #78                 // Method java/lang/Object.equals:(Ljava/lang/Object;)Z
     594: ifeq          682
     597: aload_2
     598: invokeinterface #68,  1           // InterfaceMethod com/thoughtworks/xstream/io/HierarchicalStreamReader.moveDown:()V
     603: aload_3
     604: aload_1
     605: aload_2
     606: aload_0
     607: getfield      #2                  // Field mapper:Lcom/thoughtworks/xstream/mapper/Mapper;
     610: invokestatic  #79                 // Method com/thoughtworks/xstream/core/util/HierarchicalStreams.readClassType:(Lcom/thoughtworks/xstream/io/HierarchicalStreamReader;Lcom/thoughtworks/xstream/mapper/Mapper;)Ljava/lang/Class;
     613: invokeinterface #80,  3           // InterfaceMethod com/thoughtworks/xstream/converters/UnmarshallingContext.convertAnother:(Ljava/lang/Object;Ljava/lang/Class;)Ljava/lang/Object;
     618: astore        15
     620: aload_2
     621: invokeinterface #74,  1           // InterfaceMethod com/thoughtworks/xstream/io/HierarchicalStreamReader.moveUp:()V
     626: aload_2
     627: invokeinterface #68,  1           // InterfaceMethod com/thoughtworks/xstream/io/HierarchicalStreamReader.moveDown:()V
     632: aload_3
     633: aload_1
     634: aload_2
     635: aload_0
     636: getfield      #2                  // Field mapper:Lcom/thoughtworks/xstream/mapper/Mapper;
     639: invokestatic  #79                 // Method com/thoughtworks/xstream/core/util/HierarchicalStreams.readClassType:(Lcom/thoughtworks/xstream/io/HierarchicalStreamReader;Lcom/thoughtworks/xstream/mapper/Mapper;)Ljava/lang/Class;
     642: invokeinterface #80,  3           // InterfaceMethod com/thoughtworks/xstream/converters/UnmarshallingContext.convertAnother:(Ljava/lang/Object;Ljava/lang/Class;)Ljava/lang/Object;
     647: astore        16
     649: aload_2
     650: invokeinterface #74,  1           // InterfaceMethod com/thoughtworks/xstream/io/HierarchicalStreamReader.moveUp:()V
     655: aload         15
     657: aload         16
     659: invokestatic  #81                 // Method java/util/Collections.singletonMap:(Ljava/lang/Object;Ljava/lang/Object;)Ljava/util/Map;
     662: invokeinterface #82,  1           // InterfaceMethod java/util/Map.entrySet:()Ljava/util/Set;
     667: invokeinterface #83,  1           // InterfaceMethod java/util/Set.iterator:()Ljava/util/Iterator;
     672: invokeinterface #37,  1           // InterfaceMethod java/util/Iterator.next:()Ljava/lang/Object;
     677: astore        14
     679: goto          702
     682: aload         13
     684: ifnull        699
     687: aload_3
     688: aload_1
     689: aload         13
     691: invokeinterface #80,  3           // InterfaceMethod com/thoughtworks/xstream/converters/UnmarshallingContext.convertAnother:(Ljava/lang/Object;Ljava/lang/Class;)Ljava/lang/Object;
     696: goto          700
     699: aconst_null
     700: astore        14
     702: aload         14
     704: ifnull        767
     707: aload         13
     709: aload         14
     711: invokevirtual #10                 // Method java/lang/Object.getClass:()Ljava/lang/Class;
     714: invokevirtual #53                 // Method java/lang/Class.isAssignableFrom:(Ljava/lang/Class;)Z
     717: ifne          767
     720: new           #54                 // class com/thoughtworks/xstream/converters/ConversionException
     723: dup
     724: new           #55                 // class java/lang/StringBuilder
     727: dup
     728: invokespecial #56                 // Method java/lang/StringBuilder."<init>":()V
     731: ldc           #57                 // String Cannot convert type
     733: invokevirtual #58                 // Method java/lang/StringBuilder.append:(Ljava/lang/String;)Ljava/lang/StringBuilder;
     736: aload         14
     738: invokevirtual #10                 // Method java/lang/Object.getClass:()Ljava/lang/Class;
     741: invokevirtual #59                 // Method java/lang/Class.getName:()Ljava/lang/String;
     744: invokevirtual #58                 // Method java/lang/StringBuilder.append:(Ljava/lang/String;)Ljava/lang/StringBuilder;
     747: ldc           #60                 // String  to type
     749: invokevirtual #58                 // Method java/lang/StringBuilder.append:(Ljava/lang/String;)Ljava/lang/StringBuilder;
     752: aload         13
     754: invokevirtual #59                 // Method java/lang/Class.getName:()Ljava/lang/String;
     757: invokevirtual #58                 // Method java/lang/StringBuilder.append:(Ljava/lang/String;)Ljava/lang/StringBuilder;
     760: invokevirtual #61                 // Method java/lang/StringBuilder.toString:()Ljava/lang/String;
     763: invokespecial #62                 // Method com/thoughtworks/xstream/converters/ConversionException."<init>":(Ljava/lang/String;)V
     766: athrow
     767: iload         12
     769: ifeq          810
     772: aload_0
     773: getfield      #3                  // Field reflectionProvider:Lcom/thoughtworks/xstream/converters/reflection/ReflectionProvider;
     776: aload_1
     777: aload         10
     779: aload         14
     781: aload         8
     783: invokeinterface #66,  5           // InterfaceMethod com/thoughtworks/xstream/converters/reflection/ReflectionProvider.writeField:(Ljava/lang/Object;Ljava/lang/String;Ljava/lang/Object;Ljava/lang/Class;)V
     788: aload         4
     790: new           #63                 // class com/thoughtworks/xstream/core/util/FastField
     793: dup
     794: aload         8
     796: aload         10
     798: invokespecial #64                 // Method com/thoughtworks/xstream/core/util/FastField."<init>":(Ljava/lang/Class;Ljava/lang/String;)V
     801: invokeinterface #65,  2           // InterfaceMethod java/util/Set.add:(Ljava/lang/Object;)Z
     806: pop
     807: goto          829
     810: aload         13
     812: ifnull        829
     815: aload_0
     816: aload_3
     817: aload         14
     819: aload         6
     821: aload_1
     822: aload         7
     824: invokespecial #84                 // Method writeValueToImplicitCollection:(Lcom/thoughtworks/xstream/converters/UnmarshallingContext;Ljava/lang/Object;Ljava/util/Map;Ljava/lang/Object;Ljava/lang/String;)Ljava/util/Map;
     827: astore        6
     829: aload_2
     830: invokeinterface #74,  1           // InterfaceMethod com/thoughtworks/xstream/io/HierarchicalStreamReader.moveUp:()V
     835: goto          322
     838: aload         6
     840: ifnull        932
     843: aload         6
     845: invokeinterface #82,  1           // InterfaceMethod java/util/Map.entrySet:()Ljava/util/Set;
     850: invokeinterface #83,  1           // InterfaceMethod java/util/Set.iterator:()Ljava/util/Iterator;
     855: astore        7
     857: aload         7
     859: invokeinterface #36,  1           // InterfaceMethod java/util/Iterator.hasNext:()Z
     864: ifeq          932
     867: aload         7
     869: invokeinterface #37,  1           // InterfaceMethod java/util/Iterator.next:()Ljava/lang/Object;
     874: checkcast     #77                 // class java/util/Map$Entry
     877: astore        8
     879: aload         8
     881: invokeinterface #85,  1           // InterfaceMethod java/util/Map$Entry.getValue:()Ljava/lang/Object;
     886: astore        9
     888: aload         9
     890: instanceof    #86                 // class com/thoughtworks/xstream/converters/reflection/AbstractReflectionConverter$ArraysList
     893: ifeq          929
     896: aload         9
     898: checkcast     #86                 // class com/thoughtworks/xstream/converters/reflection/AbstractReflectionConverter$ArraysList
     901: invokevirtual #87                 // Method com/thoughtworks/xstream/converters/reflection/AbstractReflectionConverter$ArraysList.toPhysicalArray:()Ljava/lang/Object;
     904: astore        10
     906: aload_0
     907: getfield      #3                  // Field reflectionProvider:Lcom/thoughtworks/xstream/converters/reflection/ReflectionProvider;
     910: aload_1
     911: aload         8
     913: invokeinterface #88,  1           // InterfaceMethod java/util/Map$Entry.getKey:()Ljava/lang/Object;
     918: checkcast     #38                 // class java/lang/String
     921: aload         10
     923: aconst_null
     924: invokeinterface #66,  5           // InterfaceMethod com/thoughtworks/xstream/converters/reflection/ReflectionProvider.writeField:(Ljava/lang/Object;Ljava/lang/String;Ljava/lang/Object;Ljava/lang/Class;)V
     929: goto          857
     932: aload_1
     933: areturn

  protected java.lang.Object unmarshallField(com.thoughtworks.xstream.converters.UnmarshallingContext, java.lang.Object, java.lang.Class, java.lang.reflect.Field);
    Code:
       0: aload_1
       1: aload_2
       2: aload_3
       3: aload_0
       4: getfield      #2                  // Field mapper:Lcom/thoughtworks/xstream/mapper/Mapper;
       7: aload         4
       9: invokevirtual #26                 // Method java/lang/reflect/Field.getDeclaringClass:()Ljava/lang/Class;
      12: aload         4
      14: invokevirtual #27                 // Method java/lang/reflect/Field.getName:()Ljava/lang/String;
      17: invokeinterface #28,  3           // InterfaceMethod com/thoughtworks/xstream/mapper/Mapper.getLocalConverter:(Ljava/lang/Class;Ljava/lang/String;)Lcom/thoughtworks/xstream/converters/Converter;
      22: invokeinterface #89,  4           // InterfaceMethod com/thoughtworks/xstream/converters/UnmarshallingContext.convertAnother:(Ljava/lang/Object;Ljava/lang/Class;Lcom/thoughtworks/xstream/converters/Converter;)Ljava/lang/Object;
      27: areturn

  protected boolean shouldUnmarshalTransientFields();
    Code:
       0: iconst_0
       1: ireturn

  private java.util.Map writeValueToImplicitCollection(com.thoughtworks.xstream.converters.UnmarshallingContext, java.lang.Object, java.util.Map, java.lang.Object, java.lang.String);
    Code:
       0: aload_0
       1: getfield      #2                  // Field mapper:Lcom/thoughtworks/xstream/mapper/Mapper;
       4: aload_1
       5: invokeinterface #90,  1           // InterfaceMethod com/thoughtworks/xstream/converters/UnmarshallingContext.getRequiredType:()Ljava/lang/Class;
      10: aload_2
      11: ifnull        21
      14: aload_2
      15: invokevirtual #10                 // Method java/lang/Object.getClass:()Ljava/lang/Class;
      18: goto          24
      21: ldc_w         #91                 // class com/thoughtworks/xstream/mapper/Mapper$Null
      24: aload         5
      26: invokeinterface #92,  4           // InterfaceMethod com/thoughtworks/xstream/mapper/Mapper.getFieldNameForItemTypeAndName:(Ljava/lang/Class;Ljava/lang/Class;Ljava/lang/String;)Ljava/lang/String;
      31: astore        6
      33: aload         6
      35: ifnull        326
      38: aload_3
      39: ifnonnull     50
      42: new           #19                 // class java/util/HashMap
      45: dup
      46: invokespecial #20                 // Method java/util/HashMap."<init>":()V
      49: astore_3
      50: aload_3
      51: aload         6
      53: invokeinterface #93,  2           // InterfaceMethod java/util/Map.get:(Ljava/lang/Object;)Ljava/lang/Object;
      58: checkcast     #94                 // class java/util/Collection
      61: astore        7
      63: aload         7
      65: ifnonnull     314
      68: aload_0
      69: getfield      #3                  // Field reflectionProvider:Lcom/thoughtworks/xstream/converters/reflection/ReflectionProvider;
      72: aload         4
      74: aload         6
      76: aconst_null
      77: invokeinterface #76,  4           // InterfaceMethod com/thoughtworks/xstream/converters/reflection/ReflectionProvider.getFieldType:(Ljava/lang/Object;Ljava/lang/String;Ljava/lang/Class;)Ljava/lang/Class;
      82: astore        8
      84: aload         8
      86: invokevirtual #95                 // Method java/lang/Class.isArray:()Z
      89: ifeq          106
      92: new           #86                 // class com/thoughtworks/xstream/converters/reflection/AbstractReflectionConverter$ArraysList
      95: dup
      96: aload         8
      98: invokespecial #96                 // Method com/thoughtworks/xstream/converters/reflection/AbstractReflectionConverter$ArraysList."<init>":(Ljava/lang/Class;)V
     101: astore        7
     103: goto          303
     106: aload_0
     107: getfield      #2                  // Field mapper:Lcom/thoughtworks/xstream/mapper/Mapper;
     110: aload         8
     112: invokeinterface #97,  2           // InterfaceMethod com/thoughtworks/xstream/mapper/Mapper.defaultImplementationOf:(Ljava/lang/Class;)Ljava/lang/Class;
     117: astore        9
     119: ldc_w         #94                 // class java/util/Collection
     122: aload         9
     124: invokevirtual #53                 // Method java/lang/Class.isAssignableFrom:(Ljava/lang/Class;)Z
     127: ifne          198
     130: ldc_w         #98                 // class java/util/Map
     133: aload         9
     135: invokevirtual #53                 // Method java/lang/Class.isAssignableFrom:(Ljava/lang/Class;)Z
     138: ifne          198
     141: new           #99                 // class com/thoughtworks/xstream/converters/reflection/ObjectAccessException
     144: dup
     145: new           #55                 // class java/lang/StringBuilder
     148: dup
     149: invokespecial #56                 // Method java/lang/StringBuilder."<init>":()V
     152: ldc           #100                // String Field
     154: invokevirtual #58                 // Method java/lang/StringBuilder.append:(Ljava/lang/String;)Ljava/lang/StringBuilder;
     157: aload         6
     159: invokevirtual #58                 // Method java/lang/StringBuilder.append:(Ljava/lang/String;)Ljava/lang/StringBuilder;
     162: ldc           #101                // String  of
     164: invokevirtual #58                 // Method java/lang/StringBuilder.append:(Ljava/lang/String;)Ljava/lang/StringBuilder;
     167: aload         4
     169: invokevirtual #10                 // Method java/lang/Object.getClass:()Ljava/lang/Class;
     172: invokevirtual #59                 // Method java/lang/Class.getName:()Ljava/lang/String;
     175: invokevirtual #58                 // Method java/lang/StringBuilder.append:(Ljava/lang/String;)Ljava/lang/StringBuilder;
     178: ldc           #102                // String  is configured for an implicit Collection or Map, but field is of type
     180: invokevirtual #58                 // Method java/lang/StringBuilder.append:(Ljava/lang/String;)Ljava/lang/StringBuilder;
     183: aload         9
     185: invokevirtual #59                 // Method java/lang/Class.getName:()Ljava/lang/String;
     188: invokevirtual #58                 // Method java/lang/StringBuilder.append:(Ljava/lang/String;)Ljava/lang/StringBuilder;
     191: invokevirtual #61                 // Method java/lang/StringBuilder.toString:()Ljava/lang/String;
     194: invokespecial #103                // Method com/thoughtworks/xstream/converters/reflection/ObjectAccessException."<init>":(Ljava/lang/String;)V
     197: athrow
     198: aload_0
     199: getfield      #104                // Field pureJavaReflectionProvider:Lcom/thoughtworks/xstream/converters/reflection/ReflectionProvider;
     202: ifnonnull     216
     205: aload_0
     206: new           #105                // class com/thoughtworks/xstream/converters/reflection/PureJavaReflectionProvider
     209: dup
     210: invokespecial #106                // Method com/thoughtworks/xstream/converters/reflection/PureJavaReflectionProvider."<init>":()V
     213: putfield      #104                // Field pureJavaReflectionProvider:Lcom/thoughtworks/xstream/converters/reflection/ReflectionProvider;
     216: aload_0
     217: getfield      #104                // Field pureJavaReflectionProvider:Lcom/thoughtworks/xstream/converters/reflection/ReflectionProvider;
     220: aload         9
     222: invokeinterface #107,  2          // InterfaceMethod com/thoughtworks/xstream/converters/reflection/ReflectionProvider.newInstance:(Ljava/lang/Class;)Ljava/lang/Object;
     227: astore        10
     229: aload         10
     231: instanceof    #94                 // class java/util/Collection
     234: ifeq          247
     237: aload         10
     239: checkcast     #94                 // class java/util/Collection
     242: astore        7
     244: goto          287
     247: aload_0
     248: getfield      #2                  // Field mapper:Lcom/thoughtworks/xstream/mapper/Mapper;
     251: aload         4
     253: invokevirtual #10                 // Method java/lang/Object.getClass:()Ljava/lang/Class;
     256: aload         6
     258: invokeinterface #71,  3           // InterfaceMethod com/thoughtworks/xstream/mapper/Mapper.getImplicitCollectionDefForFieldName:(Ljava/lang/Class;Ljava/lang/String;)Lcom/thoughtworks/xstream/mapper/Mapper$ImplicitCollectionMapping;
     263: astore        11
     265: new           #108                // class com/thoughtworks/xstream/converters/reflection/AbstractReflectionConverter$MappingList
     268: dup
     269: aload_0
     270: aload         10
     272: checkcast     #98                 // class java/util/Map
     275: aload         11
     277: invokeinterface #109,  1          // InterfaceMethod com/thoughtworks/xstream/mapper/Mapper$ImplicitCollectionMapping.getKeyFieldName:()Ljava/lang/String;
     282: invokespecial #110                // Method com/thoughtworks/xstream/converters/reflection/AbstractReflectionConverter$MappingList."<init>":(Lcom/thoughtworks/xstream/converters/reflection/AbstractReflectionConverter;Ljava/util/Map;Ljava/lang/String;)V
     285: astore        7
     287: aload_0
     288: getfield      #3                  // Field reflectionProvider:Lcom/thoughtworks/xstream/converters/reflection/ReflectionProvider;
     291: aload         4
     293: aload         6
     295: aload         10
     297: aconst_null
     298: invokeinterface #66,  5           // InterfaceMethod com/thoughtworks/xstream/converters/reflection/ReflectionProvider.writeField:(Ljava/lang/Object;Ljava/lang/String;Ljava/lang/Object;Ljava/lang/Class;)V
     303: aload_3
     304: aload         6
     306: aload         7
     308: invokeinterface #111,  3          // InterfaceMethod java/util/Map.put:(Ljava/lang/Object;Ljava/lang/Object;)Ljava/lang/Object;
     313: pop
     314: aload         7
     316: aload_2
     317: invokeinterface #112,  2          // InterfaceMethod java/util/Collection.add:(Ljava/lang/Object;)Z
     322: pop
     323: goto          385
     326: new           #54                 // class com/thoughtworks/xstream/converters/ConversionException
     329: dup
     330: new           #55                 // class java/lang/StringBuilder
     333: dup
     334: invokespecial #56                 // Method java/lang/StringBuilder."<init>":()V
     337: ldc           #113                // String Element
     339: invokevirtual #58                 // Method java/lang/StringBuilder.append:(Ljava/lang/String;)Ljava/lang/StringBuilder;
     342: aload         5
     344: invokevirtual #58                 // Method java/lang/StringBuilder.append:(Ljava/lang/String;)Ljava/lang/StringBuilder;
     347: ldc           #114                // String  of type
     349: invokevirtual #58                 // Method java/lang/StringBuilder.append:(Ljava/lang/String;)Ljava/lang/StringBuilder;
     352: aload_2
     353: invokevirtual #10                 // Method java/lang/Object.getClass:()Ljava/lang/Class;
     356: invokevirtual #59                 // Method java/lang/Class.getName:()Ljava/lang/String;
     359: invokevirtual #58                 // Method java/lang/StringBuilder.append:(Ljava/lang/String;)Ljava/lang/StringBuilder;
     362: ldc           #115                // String  is not defined as field in type
     364: invokevirtual #58                 // Method java/lang/StringBuilder.append:(Ljava/lang/String;)Ljava/lang/StringBuilder;
     367: aload         4
     369: invokevirtual #10                 // Method java/lang/Object.getClass:()Ljava/lang/Class;
     372: invokevirtual #59                 // Method java/lang/Class.getName:()Ljava/lang/String;
     375: invokevirtual #58                 // Method java/lang/StringBuilder.append:(Ljava/lang/String;)Ljava/lang/StringBuilder;
     378: invokevirtual #61                 // Method java/lang/StringBuilder.toString:()Ljava/lang/String;
     381: invokespecial #62                 // Method com/thoughtworks/xstream/converters/ConversionException."<init>":(Ljava/lang/String;)V
     384: athrow
     385: aload_3
     386: areturn

  private java.lang.Class determineWhichClassDefinesField(com.thoughtworks.xstream.io.HierarchicalStreamReader);
    Code:
       0: aload_0
       1: getfield      #2                  // Field mapper:Lcom/thoughtworks/xstream/mapper/Mapper;
       4: ldc           #116                // String defined-in
       6: invokeinterface #12,  2           // InterfaceMethod com/thoughtworks/xstream/mapper/Mapper.aliasForSystemAttribute:(Ljava/lang/String;)Ljava/lang/String;
      11: astore_2
      12: aload_2
      13: ifnonnull     20
      16: aconst_null
      17: goto          27
      20: aload_1
      21: aload_2
      22: invokeinterface #49,  2           // InterfaceMethod com/thoughtworks/xstream/io/HierarchicalStreamReader.getAttribute:(Ljava/lang/String;)Ljava/lang/String;
      27: astore_3
      28: aload_3
      29: ifnonnull     36
      32: aconst_null
      33: goto          46
      36: aload_0
      37: getfield      #2                  // Field mapper:Lcom/thoughtworks/xstream/mapper/Mapper;
      40: aload_3
      41: invokeinterface #117,  2          // InterfaceMethod com/thoughtworks/xstream/mapper/Mapper.realClass:(Ljava/lang/String;)Ljava/lang/Class;
      46: areturn

  protected java.lang.Object instantiateNewInstance(com.thoughtworks.xstream.io.HierarchicalStreamReader, com.thoughtworks.xstream.converters.UnmarshallingContext);
    Code:
       0: aload_0
       1: getfield      #2                  // Field mapper:Lcom/thoughtworks/xstream/mapper/Mapper;
       4: ldc           #11                 // String resolves-to
       6: invokeinterface #12,  2           // InterfaceMethod com/thoughtworks/xstream/mapper/Mapper.aliasForSystemAttribute:(Ljava/lang/String;)Ljava/lang/String;
      11: astore_3
      12: aload_3
      13: ifnonnull     20
      16: aconst_null
      17: goto          27
      20: aload_1
      21: aload_3
      22: invokeinterface #49,  2           // InterfaceMethod com/thoughtworks/xstream/io/HierarchicalStreamReader.getAttribute:(Ljava/lang/String;)Ljava/lang/String;
      27: astore        4
      29: aload_2
      30: invokeinterface #118,  1          // InterfaceMethod com/thoughtworks/xstream/converters/UnmarshallingContext.currentObject:()Ljava/lang/Object;
      35: astore        5
      37: aload         5
      39: ifnull        45
      42: aload         5
      44: areturn
      45: aload         4
      47: ifnull        71
      50: aload_0
      51: getfield      #3                  // Field reflectionProvider:Lcom/thoughtworks/xstream/converters/reflection/ReflectionProvider;
      54: aload_0
      55: getfield      #2                  // Field mapper:Lcom/thoughtworks/xstream/mapper/Mapper;
      58: aload         4
      60: invokeinterface #117,  2          // InterfaceMethod com/thoughtworks/xstream/mapper/Mapper.realClass:(Ljava/lang/String;)Ljava/lang/Class;
      65: invokeinterface #107,  2          // InterfaceMethod com/thoughtworks/xstream/converters/reflection/ReflectionProvider.newInstance:(Ljava/lang/Class;)Ljava/lang/Object;
      70: areturn
      71: aload_0
      72: getfield      #3                  // Field reflectionProvider:Lcom/thoughtworks/xstream/converters/reflection/ReflectionProvider;
      75: aload_2
      76: invokeinterface #90,  1           // InterfaceMethod com/thoughtworks/xstream/converters/UnmarshallingContext.getRequiredType:()Ljava/lang/Class;
      81: invokeinterface #107,  2          // InterfaceMethod com/thoughtworks/xstream/converters/reflection/ReflectionProvider.newInstance:(Ljava/lang/Class;)Ljava/lang/Object;
      86: areturn

  private java.lang.Class determineType(com.thoughtworks.xstream.io.HierarchicalStreamReader, boolean, java.lang.Object, java.lang.String, java.lang.Class);
    Code:
       0: aload_1
       1: aload_0
       2: getfield      #2                  // Field mapper:Lcom/thoughtworks/xstream/mapper/Mapper;
       5: invokestatic  #119                // Method com/thoughtworks/xstream/core/util/HierarchicalStreams.readClassAttribute:(Lcom/thoughtworks/xstream/io/HierarchicalStreamReader;Lcom/thoughtworks/xstream/mapper/Mapper;)Ljava/lang/String;
       8: astore        6
      10: iload_2
      11: ifne          139
      14: aload_0
      15: getfield      #2                  // Field mapper:Lcom/thoughtworks/xstream/mapper/Mapper;
      18: aload_3
      19: invokevirtual #10                 // Method java/lang/Object.getClass:()Ljava/lang/Class;
      22: aload         4
      24: invokeinterface #120,  3          // InterfaceMethod com/thoughtworks/xstream/mapper/Mapper.getItemTypeForItemFieldName:(Ljava/lang/Class;Ljava/lang/String;)Ljava/lang/Class;
      29: astore        7
      31: aload         7
      33: ifnull        56
      36: aload         6
      38: ifnull        53
      41: aload_0
      42: getfield      #2                  // Field mapper:Lcom/thoughtworks/xstream/mapper/Mapper;
      45: aload         6
      47: invokeinterface #117,  2          // InterfaceMethod com/thoughtworks/xstream/mapper/Mapper.realClass:(Ljava/lang/String;)Ljava/lang/Class;
      52: areturn
      53: aload         7
      55: areturn
      56: aload_1
      57: invokeinterface #69,  1           // InterfaceMethod com/thoughtworks/xstream/io/HierarchicalStreamReader.getNodeName:()Ljava/lang/String;
      62: astore        8
      64: aload         5
      66: ifnonnull     108
      69: aload_3
      70: invokevirtual #10                 // Method java/lang/Object.getClass:()Ljava/lang/Class;
      73: astore        5
      75: aload         5
      77: ifnull        108
      80: aload_0
      81: getfield      #2                  // Field mapper:Lcom/thoughtworks/xstream/mapper/Mapper;
      84: aload         5
      86: aload         8
      88: invokeinterface #46,  3           // InterfaceMethod com/thoughtworks/xstream/mapper/Mapper.shouldSerializeMember:(Ljava/lang/Class;Ljava/lang/String;)Z
      93: ifne          98
      96: aconst_null
      97: areturn
      98: aload         5
     100: invokevirtual #121                // Method java/lang/Class.getSuperclass:()Ljava/lang/Class;
     103: astore        5
     105: goto          75
     108: aload_0
     109: getfield      #2                  // Field mapper:Lcom/thoughtworks/xstream/mapper/Mapper;
     112: aload         8
     114: invokeinterface #117,  2          // InterfaceMethod com/thoughtworks/xstream/mapper/Mapper.realClass:(Ljava/lang/String;)Ljava/lang/Class;
     119: areturn
     120: astore        9
     122: new           #123                // class com/thoughtworks/xstream/converters/reflection/AbstractReflectionConverter$UnknownFieldException
     125: dup
     126: aload_3
     127: invokevirtual #10                 // Method java/lang/Object.getClass:()Ljava/lang/Class;
     130: invokevirtual #59                 // Method java/lang/Class.getName:()Ljava/lang/String;
     133: aload         4
     135: invokespecial #124                // Method com/thoughtworks/xstream/converters/reflection/AbstractReflectionConverter$UnknownFieldException."<init>":(Ljava/lang/String;Ljava/lang/String;)V
     138: athrow
     139: aload         6
     141: ifnull        156
     144: aload_0
     145: getfield      #2                  // Field mapper:Lcom/thoughtworks/xstream/mapper/Mapper;
     148: aload         6
     150: invokeinterface #117,  2          // InterfaceMethod com/thoughtworks/xstream/mapper/Mapper.realClass:(Ljava/lang/String;)Ljava/lang/Class;
     155: areturn
     156: aload_0
     157: getfield      #2                  // Field mapper:Lcom/thoughtworks/xstream/mapper/Mapper;
     160: aload_0
     161: getfield      #3                  // Field reflectionProvider:Lcom/thoughtworks/xstream/converters/reflection/ReflectionProvider;
     164: aload_3
     165: aload         4
     167: aload         5
     169: invokeinterface #76,  4           // InterfaceMethod com/thoughtworks/xstream/converters/reflection/ReflectionProvider.getFieldType:(Ljava/lang/Object;Ljava/lang/String;Ljava/lang/Class;)Ljava/lang/Class;
     174: invokeinterface #97,  2           // InterfaceMethod com/thoughtworks/xstream/mapper/Mapper.defaultImplementationOf:(Ljava/lang/Class;)Ljava/lang/Class;
     179: areturn
    Exception table:
       from    to  target type
         108   119   120   Class com/thoughtworks/xstream/mapper/CannotResolveClassException

  public void flushCache();
    Code:
       0: aload_0
       1: getfield      #6                  // Field serializationMethodInvoker:Lcom/thoughtworks/xstream/converters/reflection/SerializationMethodInvoker;
       4: invokevirtual #125                // Method com/thoughtworks/xstream/converters/reflection/SerializationMethodInvoker.flushCache:()V
       7: return

  private java.lang.Object readResolve();
    Code:
       0: aload_0
       1: new           #4                  // class com/thoughtworks/xstream/converters/reflection/SerializationMethodInvoker
       4: dup
       5: invokespecial #5                  // Method com/thoughtworks/xstream/converters/reflection/SerializationMethodInvoker."<init>":()V
       8: putfield      #6                  // Field serializationMethodInvoker:Lcom/thoughtworks/xstream/converters/reflection/SerializationMethodInvoker;
      11: aload_0
      12: areturn
}
