Compiled from "HealthConfiguration.java"
public class de.otto.edison.health.configuration.HealthConfiguration {
  private long timeBeforeIndicateError;

  private long timeForPhaseOut;

  public de.otto.edison.health.configuration.HealthConfiguration();
    Code:
       0: aload_0
       1: invokespecial #1                  // Method java/lang/Object."<init>":()V
       4: return

  public de.otto.edison.health.indicator.GracefulShutdownHealthIndicator gracefulShutdownHealthIndicator();
    Code:
       0: new           #2                  // class de/otto/edison/health/indicator/GracefulShutdownHealthIndicator
       3: dup
       4: aload_0
       5: getfield      #3                  // Field timeBeforeIndicateError:J
       8: aload_0
       9: getfield      #4                  // Field timeForPhaseOut:J
      12: invokespecial #5                  // Method de/otto/edison/health/indicator/GracefulShutdownHealthIndicator."<init>":(JJ)V
      15: areturn

  public de.otto.edison.health.indicator.ApplicationHealthIndicator applicationHealthIndicator();
    Code:
       0: new           #6                  // class de/otto/edison/health/indicator/ApplicationHealthIndicator
       3: dup
       4: invokespecial #7                  // Method de/otto/edison/health/indicator/ApplicationHealthIndicator."<init>":()V
       7: areturn
}
