Compiled from "emit.java"
public class java_cup.emit {
  public static java.lang.String prefix;

  public static java.lang.String package_name;

  public static java.lang.String symbol_const_class_name;

  public static java.lang.String parser_class_name;

  public static java.lang.String action_code;

  public static java.lang.String parser_code;

  public static java.lang.String init_code;

  public static java.lang.String scan_code;

  public static java_cup.production start_production;

  public static java.util.Stack import_list;

  public static int num_conflicts;

  public static boolean nowarn;

  public static int not_reduced;

  public static int unused_term;

  public static int unused_non_term;

  public static long symbols_time;

  public static long parser_time;

  public static long action_code_time;

  public static long production_table_time;

  public static long action_table_time;

  public static long goto_table_time;

  protected static boolean _lr_values;

  private java_cup.emit();
    Code:
       0: aload_0
       1: invokespecial #1                  // Method java/lang/Object."<init>":()V
       4: return

  public static boolean lr_values();
    Code:
       0: getstatic     #2                  // Field _lr_values:Z
       3: ireturn

  protected static void set_lr_values(boolean);
    Code:
       0: iload_0
       1: putstatic     #2                  // Field _lr_values:Z
       4: return

  protected static java.lang.String pre(java.lang.String);
    Code:
       0: new           #3                  // class java/lang/StringBuffer
       3: dup
       4: invokespecial #4                  // Method java/lang/StringBuffer."<init>":()V
       7: getstatic     #5                  // Field prefix:Ljava/lang/String;
      10: invokevirtual #6                  // Method java/lang/StringBuffer.append:(Ljava/lang/String;)Ljava/lang/StringBuffer;
      13: getstatic     #7                  // Field parser_class_name:Ljava/lang/String;
      16: invokevirtual #6                  // Method java/lang/StringBuffer.append:(Ljava/lang/String;)Ljava/lang/StringBuffer;
      19: ldc           #8                  // String $
      21: invokevirtual #6                  // Method java/lang/StringBuffer.append:(Ljava/lang/String;)Ljava/lang/StringBuffer;
      24: aload_0
      25: invokevirtual #6                  // Method java/lang/StringBuffer.append:(Ljava/lang/String;)Ljava/lang/StringBuffer;
      28: invokevirtual #9                  // Method java/lang/StringBuffer.toString:()Ljava/lang/String;
      31: areturn

  protected static void emit_package(java.io.PrintWriter);
    Code:
       0: getstatic     #10                 // Field package_name:Ljava/lang/String;
       3: ifnull        40
       6: aload_0
       7: new           #3                  // class java/lang/StringBuffer
      10: dup
      11: invokespecial #4                  // Method java/lang/StringBuffer."<init>":()V
      14: ldc           #11                 // String package
      16: invokevirtual #6                  // Method java/lang/StringBuffer.append:(Ljava/lang/String;)Ljava/lang/StringBuffer;
      19: getstatic     #10                 // Field package_name:Ljava/lang/String;
      22: invokevirtual #6                  // Method java/lang/StringBuffer.append:(Ljava/lang/String;)Ljava/lang/StringBuffer;
      25: ldc           #12                 // String ;
      27: invokevirtual #6                  // Method java/lang/StringBuffer.append:(Ljava/lang/String;)Ljava/lang/StringBuffer;
      30: invokevirtual #9                  // Method java/lang/StringBuffer.toString:()Ljava/lang/String;
      33: invokevirtual #13                 // Method java/io/PrintWriter.println:(Ljava/lang/String;)V
      36: aload_0
      37: invokevirtual #14                 // Method java/io/PrintWriter.println:()V
      40: return

  public static void symbols(java.io.PrintWriter, boolean, boolean);
    Code:
       0: iload_2
       1: ifeq          9
       4: ldc           #15                 // String interface
       6: goto          11
       9: ldc           #16                 // String class
      11: astore        5
      13: invokestatic  #17                 // Method java/lang/System.currentTimeMillis:()J
      16: lstore        6
      18: aload_0
      19: invokevirtual #14                 // Method java/io/PrintWriter.println:()V
      22: aload_0
      23: ldc           #18                 // String //----------------------------------------------------
      25: invokevirtual #13                 // Method java/io/PrintWriter.println:(Ljava/lang/String;)V
      28: aload_0
      29: ldc           #19                 // String // The following code was generated by CUP v0.10k
      31: invokevirtual #13                 // Method java/io/PrintWriter.println:(Ljava/lang/String;)V
      34: aload_0
      35: new           #3                  // class java/lang/StringBuffer
      38: dup
      39: invokespecial #4                  // Method java/lang/StringBuffer."<init>":()V
      42: ldc           #20                 // String //
      44: invokevirtual #6                  // Method java/lang/StringBuffer.append:(Ljava/lang/String;)Ljava/lang/StringBuffer;
      47: new           #21                 // class java/util/Date
      50: dup
      51: invokespecial #22                 // Method java/util/Date."<init>":()V
      54: invokevirtual #23                 // Method java/lang/StringBuffer.append:(Ljava/lang/Object;)Ljava/lang/StringBuffer;
      57: invokevirtual #9                  // Method java/lang/StringBuffer.toString:()Ljava/lang/String;
      60: invokevirtual #13                 // Method java/io/PrintWriter.println:(Ljava/lang/String;)V
      63: aload_0
      64: ldc           #18                 // String //----------------------------------------------------
      66: invokevirtual #13                 // Method java/io/PrintWriter.println:(Ljava/lang/String;)V
      69: aload_0
      70: invokevirtual #14                 // Method java/io/PrintWriter.println:()V
      73: aload_0
      74: invokestatic  #24                 // Method emit_package:(Ljava/io/PrintWriter;)V
      77: aload_0
      78: new           #3                  // class java/lang/StringBuffer
      81: dup
      82: invokespecial #4                  // Method java/lang/StringBuffer."<init>":()V
      85: ldc           #25                 // String /** CUP generated
      87: invokevirtual #6                  // Method java/lang/StringBuffer.append:(Ljava/lang/String;)Ljava/lang/StringBuffer;
      90: aload         5
      92: invokevirtual #6                  // Method java/lang/StringBuffer.append:(Ljava/lang/String;)Ljava/lang/StringBuffer;
      95: ldc           #26                 // String  containing symbol constants. */
      97: invokevirtual #6                  // Method java/lang/StringBuffer.append:(Ljava/lang/String;)Ljava/lang/StringBuffer;
     100: invokevirtual #9                  // Method java/lang/StringBuffer.toString:()Ljava/lang/String;
     103: invokevirtual #13                 // Method java/io/PrintWriter.println:(Ljava/lang/String;)V
     106: aload_0
     107: new           #3                  // class java/lang/StringBuffer
     110: dup
     111: invokespecial #4                  // Method java/lang/StringBuffer."<init>":()V
     114: ldc           #27                 // String public
     116: invokevirtual #6                  // Method java/lang/StringBuffer.append:(Ljava/lang/String;)Ljava/lang/StringBuffer;
     119: aload         5
     121: invokevirtual #6                  // Method java/lang/StringBuffer.append:(Ljava/lang/String;)Ljava/lang/StringBuffer;
     124: ldc           #28                 // String
     126: invokevirtual #6                  // Method java/lang/StringBuffer.append:(Ljava/lang/String;)Ljava/lang/StringBuffer;
     129: getstatic     #29                 // Field symbol_const_class_name:Ljava/lang/String;
     132: invokevirtual #6                  // Method java/lang/StringBuffer.append:(Ljava/lang/String;)Ljava/lang/StringBuffer;
     135: ldc           #30                 // String  {
     137: invokevirtual #6                  // Method java/lang/StringBuffer.append:(Ljava/lang/String;)Ljava/lang/StringBuffer;
     140: invokevirtual #9                  // Method java/lang/StringBuffer.toString:()Ljava/lang/String;
     143: invokevirtual #13                 // Method java/io/PrintWriter.println:(Ljava/lang/String;)V
     146: aload_0
     147: ldc           #31                 // String   /* terminals */
     149: invokevirtual #13                 // Method java/io/PrintWriter.println:(Ljava/lang/String;)V
     152: invokestatic  #32                 // Method java_cup/terminal.all:()Ljava/util/Enumeration;
     155: astore        8
     157: aload         8
     159: invokeinterface #33,  1           // InterfaceMethod java/util/Enumeration.hasMoreElements:()Z
     164: ifeq          224
     167: aload         8
     169: invokeinterface #34,  1           // InterfaceMethod java/util/Enumeration.nextElement:()Ljava/lang/Object;
     174: checkcast     #35                 // class java_cup/terminal
     177: astore_3
     178: aload_0
     179: new           #3                  // class java/lang/StringBuffer
     182: dup
     183: invokespecial #4                  // Method java/lang/StringBuffer."<init>":()V
     186: ldc           #36                 // String   public static final int
     188: invokevirtual #6                  // Method java/lang/StringBuffer.append:(Ljava/lang/String;)Ljava/lang/StringBuffer;
     191: aload_3
     192: invokevirtual #37                 // Method java_cup/terminal.name:()Ljava/lang/String;
     195: invokevirtual #6                  // Method java/lang/StringBuffer.append:(Ljava/lang/String;)Ljava/lang/StringBuffer;
     198: ldc           #38                 // String  =
     200: invokevirtual #6                  // Method java/lang/StringBuffer.append:(Ljava/lang/String;)Ljava/lang/StringBuffer;
     203: aload_3
     204: invokevirtual #39                 // Method java_cup/terminal.index:()I
     207: invokevirtual #40                 // Method java/lang/StringBuffer.append:(I)Ljava/lang/StringBuffer;
     210: ldc           #12                 // String ;
     212: invokevirtual #6                  // Method java/lang/StringBuffer.append:(Ljava/lang/String;)Ljava/lang/StringBuffer;
     215: invokevirtual #9                  // Method java/lang/StringBuffer.toString:()Ljava/lang/String;
     218: invokevirtual #13                 // Method java/io/PrintWriter.println:(Ljava/lang/String;)V
     221: goto          157
     224: iload_1
     225: ifeq          313
     228: aload_0
     229: invokevirtual #14                 // Method java/io/PrintWriter.println:()V
     232: aload_0
     233: ldc           #41                 // String   /* non terminals */
     235: invokevirtual #13                 // Method java/io/PrintWriter.println:(Ljava/lang/String;)V
     238: invokestatic  #42                 // Method java_cup/non_terminal.all:()Ljava/util/Enumeration;
     241: astore        8
     243: aload         8
     245: invokeinterface #33,  1           // InterfaceMethod java/util/Enumeration.hasMoreElements:()Z
     250: ifeq          313
     253: aload         8
     255: invokeinterface #34,  1           // InterfaceMethod java/util/Enumeration.nextElement:()Ljava/lang/Object;
     260: checkcast     #43                 // class java_cup/non_terminal
     263: astore        4
     265: aload_0
     266: new           #3                  // class java/lang/StringBuffer
     269: dup
     270: invokespecial #4                  // Method java/lang/StringBuffer."<init>":()V
     273: ldc           #44                 // String   static final int
     275: invokevirtual #6                  // Method java/lang/StringBuffer.append:(Ljava/lang/String;)Ljava/lang/StringBuffer;
     278: aload         4
     280: invokevirtual #45                 // Method java_cup/non_terminal.name:()Ljava/lang/String;
     283: invokevirtual #6                  // Method java/lang/StringBuffer.append:(Ljava/lang/String;)Ljava/lang/StringBuffer;
     286: ldc           #38                 // String  =
     288: invokevirtual #6                  // Method java/lang/StringBuffer.append:(Ljava/lang/String;)Ljava/lang/StringBuffer;
     291: aload         4
     293: invokevirtual #46                 // Method java_cup/non_terminal.index:()I
     296: invokevirtual #40                 // Method java/lang/StringBuffer.append:(I)Ljava/lang/StringBuffer;
     299: ldc           #12                 // String ;
     301: invokevirtual #6                  // Method java/lang/StringBuffer.append:(Ljava/lang/String;)Ljava/lang/StringBuffer;
     304: invokevirtual #9                  // Method java/lang/StringBuffer.toString:()Ljava/lang/String;
     307: invokevirtual #13                 // Method java/io/PrintWriter.println:(Ljava/lang/String;)V
     310: goto          243
     313: aload_0
     314: ldc           #47                 // String }
     316: invokevirtual #13                 // Method java/io/PrintWriter.println:(Ljava/lang/String;)V
     319: aload_0
     320: invokevirtual #14                 // Method java/io/PrintWriter.println:()V
     323: invokestatic  #17                 // Method java/lang/System.currentTimeMillis:()J
     326: lload         6
     328: lsub
     329: putstatic     #48                 // Field symbols_time:J
     332: return

  protected static void emit_action_code(java.io.PrintWriter, java_cup.production) throws java_cup.internal_error;
    Code:
       0: invokestatic  #17                 // Method java/lang/System.currentTimeMillis:()J
       3: lstore_3
       4: aload_0
       5: invokevirtual #14                 // Method java/io/PrintWriter.println:()V
       8: aload_0
       9: ldc           #49                 // String /** Cup generated class to encapsulate user supplied action code.*/
      11: invokevirtual #13                 // Method java/io/PrintWriter.println:(Ljava/lang/String;)V
      14: aload_0
      15: new           #3                  // class java/lang/StringBuffer
      18: dup
      19: invokespecial #4                  // Method java/lang/StringBuffer."<init>":()V
      22: ldc           #50                 // String class
      24: invokevirtual #6                  // Method java/lang/StringBuffer.append:(Ljava/lang/String;)Ljava/lang/StringBuffer;
      27: ldc           #51                 // String actions
      29: invokestatic  #52                 // Method pre:(Ljava/lang/String;)Ljava/lang/String;
      32: invokevirtual #6                  // Method java/lang/StringBuffer.append:(Ljava/lang/String;)Ljava/lang/StringBuffer;
      35: ldc           #30                 // String  {
      37: invokevirtual #6                  // Method java/lang/StringBuffer.append:(Ljava/lang/String;)Ljava/lang/StringBuffer;
      40: invokevirtual #9                  // Method java/lang/StringBuffer.toString:()Ljava/lang/String;
      43: invokevirtual #13                 // Method java/io/PrintWriter.println:(Ljava/lang/String;)V
      46: getstatic     #53                 // Field action_code:Ljava/lang/String;
      49: ifnull        63
      52: aload_0
      53: invokevirtual #14                 // Method java/io/PrintWriter.println:()V
      56: aload_0
      57: getstatic     #53                 // Field action_code:Ljava/lang/String;
      60: invokevirtual #13                 // Method java/io/PrintWriter.println:(Ljava/lang/String;)V
      63: aload_0
      64: new           #3                  // class java/lang/StringBuffer
      67: dup
      68: invokespecial #4                  // Method java/lang/StringBuffer."<init>":()V
      71: ldc           #54                 // String   private final
      73: invokevirtual #6                  // Method java/lang/StringBuffer.append:(Ljava/lang/String;)Ljava/lang/StringBuffer;
      76: getstatic     #7                  // Field parser_class_name:Ljava/lang/String;
      79: invokevirtual #6                  // Method java/lang/StringBuffer.append:(Ljava/lang/String;)Ljava/lang/StringBuffer;
      82: ldc           #55                 // String  parser;
      84: invokevirtual #6                  // Method java/lang/StringBuffer.append:(Ljava/lang/String;)Ljava/lang/StringBuffer;
      87: invokevirtual #9                  // Method java/lang/StringBuffer.toString:()Ljava/lang/String;
      90: invokevirtual #13                 // Method java/io/PrintWriter.println:(Ljava/lang/String;)V
      93: aload_0
      94: invokevirtual #14                 // Method java/io/PrintWriter.println:()V
      97: aload_0
      98: ldc           #56                 // String   /** Constructor */
     100: invokevirtual #13                 // Method java/io/PrintWriter.println:(Ljava/lang/String;)V
     103: aload_0
     104: new           #3                  // class java/lang/StringBuffer
     107: dup
     108: invokespecial #4                  // Method java/lang/StringBuffer."<init>":()V
     111: ldc           #57                 // String
     113: invokevirtual #6                  // Method java/lang/StringBuffer.append:(Ljava/lang/String;)Ljava/lang/StringBuffer;
     116: ldc           #51                 // String actions
     118: invokestatic  #52                 // Method pre:(Ljava/lang/String;)Ljava/lang/String;
     121: invokevirtual #6                  // Method java/lang/StringBuffer.append:(Ljava/lang/String;)Ljava/lang/StringBuffer;
     124: ldc           #58                 // String (
     126: invokevirtual #6                  // Method java/lang/StringBuffer.append:(Ljava/lang/String;)Ljava/lang/StringBuffer;
     129: getstatic     #7                  // Field parser_class_name:Ljava/lang/String;
     132: invokevirtual #6                  // Method java/lang/StringBuffer.append:(Ljava/lang/String;)Ljava/lang/StringBuffer;
     135: ldc           #59                 // String  parser) {
     137: invokevirtual #6                  // Method java/lang/StringBuffer.append:(Ljava/lang/String;)Ljava/lang/StringBuffer;
     140: invokevirtual #9                  // Method java/lang/StringBuffer.toString:()Ljava/lang/String;
     143: invokevirtual #13                 // Method java/io/PrintWriter.println:(Ljava/lang/String;)V
     146: aload_0
     147: ldc           #60                 // String     this.parser = parser;
     149: invokevirtual #13                 // Method java/io/PrintWriter.println:(Ljava/lang/String;)V
     152: aload_0
     153: ldc           #61                 // String   }
     155: invokevirtual #13                 // Method java/io/PrintWriter.println:(Ljava/lang/String;)V
     158: aload_0
     159: invokevirtual #14                 // Method java/io/PrintWriter.println:()V
     162: aload_0
     163: ldc           #62                 // String   /** Method with the actual generated action code. */
     165: invokevirtual #13                 // Method java/io/PrintWriter.println:(Ljava/lang/String;)V
     168: aload_0
     169: new           #3                  // class java/lang/StringBuffer
     172: dup
     173: invokespecial #4                  // Method java/lang/StringBuffer."<init>":()V
     176: ldc           #63                 // String   public final java_cup.runtime.Symbol
     178: invokevirtual #6                  // Method java/lang/StringBuffer.append:(Ljava/lang/String;)Ljava/lang/StringBuffer;
     181: ldc           #64                 // String do_action
     183: invokestatic  #52                 // Method pre:(Ljava/lang/String;)Ljava/lang/String;
     186: invokevirtual #6                  // Method java/lang/StringBuffer.append:(Ljava/lang/String;)Ljava/lang/StringBuffer;
     189: ldc           #58                 // String (
     191: invokevirtual #6                  // Method java/lang/StringBuffer.append:(Ljava/lang/String;)Ljava/lang/StringBuffer;
     194: invokevirtual #9                  // Method java/lang/StringBuffer.toString:()Ljava/lang/String;
     197: invokevirtual #13                 // Method java/io/PrintWriter.println:(Ljava/lang/String;)V
     200: aload_0
     201: new           #3                  // class java/lang/StringBuffer
     204: dup
     205: invokespecial #4                  // Method java/lang/StringBuffer."<init>":()V
     208: ldc           #65                 // String     int
     210: invokevirtual #6                  // Method java/lang/StringBuffer.append:(Ljava/lang/String;)Ljava/lang/StringBuffer;
     213: ldc           #66                 // String act_num,
     215: invokestatic  #52                 // Method pre:(Ljava/lang/String;)Ljava/lang/String;
     218: invokevirtual #6                  // Method java/lang/StringBuffer.append:(Ljava/lang/String;)Ljava/lang/StringBuffer;
     221: invokevirtual #9                  // Method java/lang/StringBuffer.toString:()Ljava/lang/String;
     224: invokevirtual #13                 // Method java/io/PrintWriter.println:(Ljava/lang/String;)V
     227: aload_0
     228: new           #3                  // class java/lang/StringBuffer
     231: dup
     232: invokespecial #4                  // Method java/lang/StringBuffer."<init>":()V
     235: ldc           #67                 // String     java_cup.runtime.lr_parser
     237: invokevirtual #6                  // Method java/lang/StringBuffer.append:(Ljava/lang/String;)Ljava/lang/StringBuffer;
     240: ldc           #68                 // String parser,
     242: invokestatic  #52                 // Method pre:(Ljava/lang/String;)Ljava/lang/String;
     245: invokevirtual #6                  // Method java/lang/StringBuffer.append:(Ljava/lang/String;)Ljava/lang/StringBuffer;
     248: invokevirtual #9                  // Method java/lang/StringBuffer.toString:()Ljava/lang/String;
     251: invokevirtual #13                 // Method java/io/PrintWriter.println:(Ljava/lang/String;)V
     254: aload_0
     255: new           #3                  // class java/lang/StringBuffer
     258: dup
     259: invokespecial #4                  // Method java/lang/StringBuffer."<init>":()V
     262: ldc           #69                 // String     java.util.Stack
     264: invokevirtual #6                  // Method java/lang/StringBuffer.append:(Ljava/lang/String;)Ljava/lang/StringBuffer;
     267: ldc           #70                 // String stack,
     269: invokestatic  #52                 // Method pre:(Ljava/lang/String;)Ljava/lang/String;
     272: invokevirtual #6                  // Method java/lang/StringBuffer.append:(Ljava/lang/String;)Ljava/lang/StringBuffer;
     275: invokevirtual #9                  // Method java/lang/StringBuffer.toString:()Ljava/lang/String;
     278: invokevirtual #13                 // Method java/io/PrintWriter.println:(Ljava/lang/String;)V
     281: aload_0
     282: new           #3                  // class java/lang/StringBuffer
     285: dup
     286: invokespecial #4                  // Method java/lang/StringBuffer."<init>":()V
     289: ldc           #65                 // String     int
     291: invokevirtual #6                  // Method java/lang/StringBuffer.append:(Ljava/lang/String;)Ljava/lang/StringBuffer;
     294: ldc           #71                 // String top)
     296: invokestatic  #52                 // Method pre:(Ljava/lang/String;)Ljava/lang/String;
     299: invokevirtual #6                  // Method java/lang/StringBuffer.append:(Ljava/lang/String;)Ljava/lang/StringBuffer;
     302: invokevirtual #9                  // Method java/lang/StringBuffer.toString:()Ljava/lang/String;
     305: invokevirtual #13                 // Method java/io/PrintWriter.println:(Ljava/lang/String;)V
     308: aload_0
     309: ldc           #72                 // String     throws java.lang.Exception
     311: invokevirtual #13                 // Method java/io/PrintWriter.println:(Ljava/lang/String;)V
     314: aload_0
     315: ldc           #73                 // String     {
     317: invokevirtual #13                 // Method java/io/PrintWriter.println:(Ljava/lang/String;)V
     320: aload_0
     321: ldc           #74                 // String       /* Symbol object for return from actions */
     323: invokevirtual #13                 // Method java/io/PrintWriter.println:(Ljava/lang/String;)V
     326: aload_0
     327: new           #3                  // class java/lang/StringBuffer
     330: dup
     331: invokespecial #4                  // Method java/lang/StringBuffer."<init>":()V
     334: ldc           #75                 // String       java_cup.runtime.Symbol
     336: invokevirtual #6                  // Method java/lang/StringBuffer.append:(Ljava/lang/String;)Ljava/lang/StringBuffer;
     339: ldc           #76                 // String result
     341: invokestatic  #52                 // Method pre:(Ljava/lang/String;)Ljava/lang/String;
     344: invokevirtual #6                  // Method java/lang/StringBuffer.append:(Ljava/lang/String;)Ljava/lang/StringBuffer;
     347: ldc           #12                 // String ;
     349: invokevirtual #6                  // Method java/lang/StringBuffer.append:(Ljava/lang/String;)Ljava/lang/StringBuffer;
     352: invokevirtual #9                  // Method java/lang/StringBuffer.toString:()Ljava/lang/String;
     355: invokevirtual #13                 // Method java/io/PrintWriter.println:(Ljava/lang/String;)V
     358: aload_0
     359: invokevirtual #14                 // Method java/io/PrintWriter.println:()V
     362: aload_0
     363: ldc           #77                 // String       /* select the action based on the action number */
     365: invokevirtual #13                 // Method java/io/PrintWriter.println:(Ljava/lang/String;)V
     368: aload_0
     369: new           #3                  // class java/lang/StringBuffer
     372: dup
     373: invokespecial #4                  // Method java/lang/StringBuffer."<init>":()V
     376: ldc           #78                 // String       switch (
     378: invokevirtual #6                  // Method java/lang/StringBuffer.append:(Ljava/lang/String;)Ljava/lang/StringBuffer;
     381: ldc           #79                 // String act_num
     383: invokestatic  #52                 // Method pre:(Ljava/lang/String;)Ljava/lang/String;
     386: invokevirtual #6                  // Method java/lang/StringBuffer.append:(Ljava/lang/String;)Ljava/lang/StringBuffer;
     389: ldc           #80                 // String )
     391: invokevirtual #6                  // Method java/lang/StringBuffer.append:(Ljava/lang/String;)Ljava/lang/StringBuffer;
     394: invokevirtual #9                  // Method java/lang/StringBuffer.toString:()Ljava/lang/String;
     397: invokevirtual #13                 // Method java/io/PrintWriter.println:(Ljava/lang/String;)V
     400: aload_0
     401: ldc           #81                 // String         {
     403: invokevirtual #13                 // Method java/io/PrintWriter.println:(Ljava/lang/String;)V
     406: invokestatic  #82                 // Method java_cup/production.all:()Ljava/util/Enumeration;
     409: astore        5
     411: aload         5
     413: invokeinterface #33,  1           // InterfaceMethod java/util/Enumeration.hasMoreElements:()Z
     418: ifeq          1196
     421: aload         5
     423: invokeinterface #34,  1           // InterfaceMethod java/util/Enumeration.nextElement:()Ljava/lang/Object;
     428: checkcast     #83                 // class java_cup/production
     431: astore_2
     432: aload_0
     433: ldc           #84                 // String           /*. . . . . . . . . . . . . . . . . . . .*/
     435: invokevirtual #13                 // Method java/io/PrintWriter.println:(Ljava/lang/String;)V
     438: aload_0
     439: new           #3                  // class java/lang/StringBuffer
     442: dup
     443: invokespecial #4                  // Method java/lang/StringBuffer."<init>":()V
     446: ldc           #85                 // String           case
     448: invokevirtual #6                  // Method java/lang/StringBuffer.append:(Ljava/lang/String;)Ljava/lang/StringBuffer;
     451: aload_2
     452: invokevirtual #86                 // Method java_cup/production.index:()I
     455: invokevirtual #40                 // Method java/lang/StringBuffer.append:(I)Ljava/lang/StringBuffer;
     458: ldc           #87                 // String : //
     460: invokevirtual #6                  // Method java/lang/StringBuffer.append:(Ljava/lang/String;)Ljava/lang/StringBuffer;
     463: aload_2
     464: invokevirtual #88                 // Method java_cup/production.to_simple_string:()Ljava/lang/String;
     467: invokevirtual #6                  // Method java/lang/StringBuffer.append:(Ljava/lang/String;)Ljava/lang/StringBuffer;
     470: invokevirtual #9                  // Method java/lang/StringBuffer.toString:()Ljava/lang/String;
     473: invokevirtual #13                 // Method java/io/PrintWriter.println:(Ljava/lang/String;)V
     476: aload_0
     477: ldc           #89                 // String             {
     479: invokevirtual #13                 // Method java/io/PrintWriter.println:(Ljava/lang/String;)V
     482: aload_0
     483: new           #3                  // class java/lang/StringBuffer
     486: dup
     487: invokespecial #4                  // Method java/lang/StringBuffer."<init>":()V
     490: ldc           #90                 // String
     492: invokevirtual #6                  // Method java/lang/StringBuffer.append:(Ljava/lang/String;)Ljava/lang/StringBuffer;
     495: aload_2
     496: invokevirtual #91                 // Method java_cup/production.lhs:()Ljava_cup/symbol_part;
     499: invokevirtual #92                 // Method java_cup/symbol_part.the_symbol:()Ljava_cup/symbol;
     502: invokevirtual #93                 // Method java_cup/symbol.stack_type:()Ljava/lang/String;
     505: invokevirtual #6                  // Method java/lang/StringBuffer.append:(Ljava/lang/String;)Ljava/lang/StringBuffer;
     508: ldc           #94                 // String  RESULT = null;
     510: invokevirtual #6                  // Method java/lang/StringBuffer.append:(Ljava/lang/String;)Ljava/lang/StringBuffer;
     513: invokevirtual #9                  // Method java/lang/StringBuffer.toString:()Ljava/lang/String;
     516: invokevirtual #13                 // Method java/io/PrintWriter.println:(Ljava/lang/String;)V
     519: iconst_0
     520: istore        6
     522: iload         6
     524: aload_2
     525: invokevirtual #95                 // Method java_cup/production.rhs_length:()I
     528: if_icmpge     762
     531: aload_2
     532: iload         6
     534: invokevirtual #96                 // Method java_cup/production.rhs:(I)Ljava_cup/production_part;
     537: instanceof    #97                 // class java_cup/symbol_part
     540: ifne          546
     543: goto          756
     546: aload_2
     547: iload         6
     549: invokevirtual #96                 // Method java_cup/production.rhs:(I)Ljava_cup/production_part;
     552: checkcast     #97                 // class java_cup/symbol_part
     555: invokevirtual #92                 // Method java_cup/symbol_part.the_symbol:()Ljava_cup/symbol;
     558: astore        7
     560: aload         7
     562: instanceof    #43                 // class java_cup/non_terminal
     565: ifne          571
     568: goto          756
     571: aload         7
     573: checkcast     #43                 // class java_cup/non_terminal
     576: getfield      #98                 // Field java_cup/non_terminal.is_embedded_action:Z
     579: ifne          585
     582: goto          756
     585: aload_2
     586: invokevirtual #95                 // Method java_cup/production.rhs_length:()I
     589: iload         6
     591: isub
     592: iconst_1
     593: isub
     594: istore        8
     596: aload_0
     597: new           #3                  // class java/lang/StringBuffer
     600: dup
     601: invokespecial #4                  // Method java/lang/StringBuffer."<init>":()V
     604: ldc           #99                 // String               // propagate RESULT from
     606: invokevirtual #6                  // Method java/lang/StringBuffer.append:(Ljava/lang/String;)Ljava/lang/StringBuffer;
     609: aload         7
     611: invokevirtual #100                // Method java_cup/symbol.name:()Ljava/lang/String;
     614: invokevirtual #6                  // Method java/lang/StringBuffer.append:(Ljava/lang/String;)Ljava/lang/StringBuffer;
     617: invokevirtual #9                  // Method java/lang/StringBuffer.toString:()Ljava/lang/String;
     620: invokevirtual #13                 // Method java/io/PrintWriter.println:(Ljava/lang/String;)V
     623: aload_0
     624: new           #3                  // class java/lang/StringBuffer
     627: dup
     628: invokespecial #4                  // Method java/lang/StringBuffer."<init>":()V
     631: ldc           #101                // String               if ( ((java_cup.runtime.Symbol)
     633: invokevirtual #6                  // Method java/lang/StringBuffer.append:(Ljava/lang/String;)Ljava/lang/StringBuffer;
     636: ldc           #102                // String stack
     638: invokestatic  #52                 // Method pre:(Ljava/lang/String;)Ljava/lang/String;
     641: invokevirtual #6                  // Method java/lang/StringBuffer.append:(Ljava/lang/String;)Ljava/lang/StringBuffer;
     644: ldc           #103                // String .elementAt(
     646: invokevirtual #6                  // Method java/lang/StringBuffer.append:(Ljava/lang/String;)Ljava/lang/StringBuffer;
     649: ldc           #104                // String top
     651: invokestatic  #52                 // Method pre:(Ljava/lang/String;)Ljava/lang/String;
     654: invokevirtual #6                  // Method java/lang/StringBuffer.append:(Ljava/lang/String;)Ljava/lang/StringBuffer;
     657: ldc           #105                // String -
     659: invokevirtual #6                  // Method java/lang/StringBuffer.append:(Ljava/lang/String;)Ljava/lang/StringBuffer;
     662: iload         8
     664: invokevirtual #40                 // Method java/lang/StringBuffer.append:(I)Ljava/lang/StringBuffer;
     667: ldc           #106                // String )).value != null )
     669: invokevirtual #6                  // Method java/lang/StringBuffer.append:(Ljava/lang/String;)Ljava/lang/StringBuffer;
     672: invokevirtual #9                  // Method java/lang/StringBuffer.toString:()Ljava/lang/String;
     675: invokevirtual #13                 // Method java/io/PrintWriter.println:(Ljava/lang/String;)V
     678: aload_0
     679: new           #3                  // class java/lang/StringBuffer
     682: dup
     683: invokespecial #4                  // Method java/lang/StringBuffer."<init>":()V
     686: ldc           #107                // String                 RESULT = (
     688: invokevirtual #6                  // Method java/lang/StringBuffer.append:(Ljava/lang/String;)Ljava/lang/StringBuffer;
     691: aload_2
     692: invokevirtual #91                 // Method java_cup/production.lhs:()Ljava_cup/symbol_part;
     695: invokevirtual #92                 // Method java_cup/symbol_part.the_symbol:()Ljava_cup/symbol;
     698: invokevirtual #93                 // Method java_cup/symbol.stack_type:()Ljava/lang/String;
     701: invokevirtual #6                  // Method java/lang/StringBuffer.append:(Ljava/lang/String;)Ljava/lang/StringBuffer;
     704: ldc           #108                // String )
     706: invokevirtual #6                  // Method java/lang/StringBuffer.append:(Ljava/lang/String;)Ljava/lang/StringBuffer;
     709: ldc           #109                // String ((java_cup.runtime.Symbol)
     711: invokevirtual #6                  // Method java/lang/StringBuffer.append:(Ljava/lang/String;)Ljava/lang/StringBuffer;
     714: ldc           #102                // String stack
     716: invokestatic  #52                 // Method pre:(Ljava/lang/String;)Ljava/lang/String;
     719: invokevirtual #6                  // Method java/lang/StringBuffer.append:(Ljava/lang/String;)Ljava/lang/StringBuffer;
     722: ldc           #103                // String .elementAt(
     724: invokevirtual #6                  // Method java/lang/StringBuffer.append:(Ljava/lang/String;)Ljava/lang/StringBuffer;
     727: ldc           #104                // String top
     729: invokestatic  #52                 // Method pre:(Ljava/lang/String;)Ljava/lang/String;
     732: invokevirtual #6                  // Method java/lang/StringBuffer.append:(Ljava/lang/String;)Ljava/lang/StringBuffer;
     735: ldc           #105                // String -
     737: invokevirtual #6                  // Method java/lang/StringBuffer.append:(Ljava/lang/String;)Ljava/lang/StringBuffer;
     740: iload         8
     742: invokevirtual #40                 // Method java/lang/StringBuffer.append:(I)Ljava/lang/StringBuffer;
     745: ldc           #110                // String )).value;
     747: invokevirtual #6                  // Method java/lang/StringBuffer.append:(Ljava/lang/String;)Ljava/lang/StringBuffer;
     750: invokevirtual #9                  // Method java/lang/StringBuffer.toString:()Ljava/lang/String;
     753: invokevirtual #13                 // Method java/io/PrintWriter.println:(Ljava/lang/String;)V
     756: iinc          6, 1
     759: goto          522
     762: aload_2
     763: invokevirtual #111                // Method java_cup/production.action:()Ljava_cup/action_part;
     766: ifnull        802
     769: aload_2
     770: invokevirtual #111                // Method java_cup/production.action:()Ljava_cup/action_part;
     773: invokevirtual #112                // Method java_cup/action_part.code_string:()Ljava/lang/String;
     776: ifnull        802
     779: aload_2
     780: invokevirtual #111                // Method java_cup/production.action:()Ljava_cup/action_part;
     783: ldc           #113                // String
     785: invokevirtual #114                // Method java_cup/action_part.equals:(Ljava/lang/Object;)Z
     788: ifne          802
     791: aload_0
     792: aload_2
     793: invokevirtual #111                // Method java_cup/production.action:()Ljava_cup/action_part;
     796: invokevirtual #112                // Method java_cup/action_part.code_string:()Ljava/lang/String;
     799: invokevirtual #13                 // Method java/io/PrintWriter.println:(Ljava/lang/String;)V
     802: invokestatic  #115                // Method lr_values:()Z
     805: ifeq          1035
     808: iconst_0
     809: istore        9
     811: new           #3                  // class java/lang/StringBuffer
     814: dup
     815: invokespecial #4                  // Method java/lang/StringBuffer."<init>":()V
     818: ldc           #116                // String ((java_cup.runtime.Symbol)
     820: invokevirtual #6                  // Method java/lang/StringBuffer.append:(Ljava/lang/String;)Ljava/lang/StringBuffer;
     823: ldc           #102                // String stack
     825: invokestatic  #52                 // Method pre:(Ljava/lang/String;)Ljava/lang/String;
     828: invokevirtual #6                  // Method java/lang/StringBuffer.append:(Ljava/lang/String;)Ljava/lang/StringBuffer;
     831: ldc           #103                // String .elementAt(
     833: invokevirtual #6                  // Method java/lang/StringBuffer.append:(Ljava/lang/String;)Ljava/lang/StringBuffer;
     836: ldc           #104                // String top
     838: invokestatic  #52                 // Method pre:(Ljava/lang/String;)Ljava/lang/String;
     841: invokevirtual #6                  // Method java/lang/StringBuffer.append:(Ljava/lang/String;)Ljava/lang/StringBuffer;
     844: ldc           #105                // String -
     846: invokevirtual #6                  // Method java/lang/StringBuffer.append:(Ljava/lang/String;)Ljava/lang/StringBuffer;
     849: iload         9
     851: invokevirtual #40                 // Method java/lang/StringBuffer.append:(I)Ljava/lang/StringBuffer;
     854: ldc           #117                // String )).right
     856: invokevirtual #6                  // Method java/lang/StringBuffer.append:(Ljava/lang/String;)Ljava/lang/StringBuffer;
     859: invokevirtual #9                  // Method java/lang/StringBuffer.toString:()Ljava/lang/String;
     862: astore        8
     864: aload_2
     865: invokevirtual #95                 // Method java_cup/production.rhs_length:()I
     868: ifne          878
     871: aload         8
     873: astore        7
     875: goto          939
     878: aload_2
     879: invokevirtual #95                 // Method java_cup/production.rhs_length:()I
     882: iconst_1
     883: isub
     884: istore        6
     886: new           #3                  // class java/lang/StringBuffer
     889: dup
     890: invokespecial #4                  // Method java/lang/StringBuffer."<init>":()V
     893: ldc           #116                // String ((java_cup.runtime.Symbol)
     895: invokevirtual #6                  // Method java/lang/StringBuffer.append:(Ljava/lang/String;)Ljava/lang/StringBuffer;
     898: ldc           #102                // String stack
     900: invokestatic  #52                 // Method pre:(Ljava/lang/String;)Ljava/lang/String;
     903: invokevirtual #6                  // Method java/lang/StringBuffer.append:(Ljava/lang/String;)Ljava/lang/StringBuffer;
     906: ldc           #103                // String .elementAt(
     908: invokevirtual #6                  // Method java/lang/StringBuffer.append:(Ljava/lang/String;)Ljava/lang/StringBuffer;
     911: ldc           #104                // String top
     913: invokestatic  #52                 // Method pre:(Ljava/lang/String;)Ljava/lang/String;
     916: invokevirtual #6                  // Method java/lang/StringBuffer.append:(Ljava/lang/String;)Ljava/lang/StringBuffer;
     919: ldc           #105                // String -
     921: invokevirtual #6                  // Method java/lang/StringBuffer.append:(Ljava/lang/String;)Ljava/lang/StringBuffer;
     924: iload         6
     926: invokevirtual #40                 // Method java/lang/StringBuffer.append:(I)Ljava/lang/StringBuffer;
     929: ldc           #118                // String )).left
     931: invokevirtual #6                  // Method java/lang/StringBuffer.append:(Ljava/lang/String;)Ljava/lang/StringBuffer;
     934: invokevirtual #9                  // Method java/lang/StringBuffer.toString:()Ljava/lang/String;
     937: astore        7
     939: aload_0
     940: new           #3                  // class java/lang/StringBuffer
     943: dup
     944: invokespecial #4                  // Method java/lang/StringBuffer."<init>":()V
     947: ldc           #90                 // String
     949: invokevirtual #6                  // Method java/lang/StringBuffer.append:(Ljava/lang/String;)Ljava/lang/StringBuffer;
     952: ldc           #76                 // String result
     954: invokestatic  #52                 // Method pre:(Ljava/lang/String;)Ljava/lang/String;
     957: invokevirtual #6                  // Method java/lang/StringBuffer.append:(Ljava/lang/String;)Ljava/lang/StringBuffer;
     960: ldc           #119                // String  = new java_cup.runtime.Symbol(
     962: invokevirtual #6                  // Method java/lang/StringBuffer.append:(Ljava/lang/String;)Ljava/lang/StringBuffer;
     965: aload_2
     966: invokevirtual #91                 // Method java_cup/production.lhs:()Ljava_cup/symbol_part;
     969: invokevirtual #92                 // Method java_cup/symbol_part.the_symbol:()Ljava_cup/symbol;
     972: invokevirtual #120                // Method java_cup/symbol.index:()I
     975: invokevirtual #40                 // Method java/lang/StringBuffer.append:(I)Ljava/lang/StringBuffer;
     978: ldc           #121                // String /*
     980: invokevirtual #6                  // Method java/lang/StringBuffer.append:(Ljava/lang/String;)Ljava/lang/StringBuffer;
     983: aload_2
     984: invokevirtual #91                 // Method java_cup/production.lhs:()Ljava_cup/symbol_part;
     987: invokevirtual #92                 // Method java_cup/symbol_part.the_symbol:()Ljava_cup/symbol;
     990: invokevirtual #100                // Method java_cup/symbol.name:()Ljava/lang/String;
     993: invokevirtual #6                  // Method java/lang/StringBuffer.append:(Ljava/lang/String;)Ljava/lang/StringBuffer;
     996: ldc           #122                // String */
     998: invokevirtual #6                  // Method java/lang/StringBuffer.append:(Ljava/lang/String;)Ljava/lang/StringBuffer;
    1001: ldc           #123                // String ,
    1003: invokevirtual #6                  // Method java/lang/StringBuffer.append:(Ljava/lang/String;)Ljava/lang/StringBuffer;
    1006: aload         7
    1008: invokevirtual #6                  // Method java/lang/StringBuffer.append:(Ljava/lang/String;)Ljava/lang/StringBuffer;
    1011: ldc           #123                // String ,
    1013: invokevirtual #6                  // Method java/lang/StringBuffer.append:(Ljava/lang/String;)Ljava/lang/StringBuffer;
    1016: aload         8
    1018: invokevirtual #6                  // Method java/lang/StringBuffer.append:(Ljava/lang/String;)Ljava/lang/StringBuffer;
    1021: ldc           #124                // String , RESULT);
    1023: invokevirtual #6                  // Method java/lang/StringBuffer.append:(Ljava/lang/String;)Ljava/lang/StringBuffer;
    1026: invokevirtual #9                  // Method java/lang/StringBuffer.toString:()Ljava/lang/String;
    1029: invokevirtual #13                 // Method java/io/PrintWriter.println:(Ljava/lang/String;)V
    1032: goto          1108
    1035: aload_0
    1036: new           #3                  // class java/lang/StringBuffer
    1039: dup
    1040: invokespecial #4                  // Method java/lang/StringBuffer."<init>":()V
    1043: ldc           #90                 // String
    1045: invokevirtual #6                  // Method java/lang/StringBuffer.append:(Ljava/lang/String;)Ljava/lang/StringBuffer;
    1048: ldc           #76                 // String result
    1050: invokestatic  #52                 // Method pre:(Ljava/lang/String;)Ljava/lang/String;
    1053: invokevirtual #6                  // Method java/lang/StringBuffer.append:(Ljava/lang/String;)Ljava/lang/StringBuffer;
    1056: ldc           #119                // String  = new java_cup.runtime.Symbol(
    1058: invokevirtual #6                  // Method java/lang/StringBuffer.append:(Ljava/lang/String;)Ljava/lang/StringBuffer;
    1061: aload_2
    1062: invokevirtual #91                 // Method java_cup/production.lhs:()Ljava_cup/symbol_part;
    1065: invokevirtual #92                 // Method java_cup/symbol_part.the_symbol:()Ljava_cup/symbol;
    1068: invokevirtual #120                // Method java_cup/symbol.index:()I
    1071: invokevirtual #40                 // Method java/lang/StringBuffer.append:(I)Ljava/lang/StringBuffer;
    1074: ldc           #121                // String /*
    1076: invokevirtual #6                  // Method java/lang/StringBuffer.append:(Ljava/lang/String;)Ljava/lang/StringBuffer;
    1079: aload_2
    1080: invokevirtual #91                 // Method java_cup/production.lhs:()Ljava_cup/symbol_part;
    1083: invokevirtual #92                 // Method java_cup/symbol_part.the_symbol:()Ljava_cup/symbol;
    1086: invokevirtual #100                // Method java_cup/symbol.name:()Ljava/lang/String;
    1089: invokevirtual #6                  // Method java/lang/StringBuffer.append:(Ljava/lang/String;)Ljava/lang/StringBuffer;
    1092: ldc           #122                // String */
    1094: invokevirtual #6                  // Method java/lang/StringBuffer.append:(Ljava/lang/String;)Ljava/lang/StringBuffer;
    1097: ldc           #124                // String , RESULT);
    1099: invokevirtual #6                  // Method java/lang/StringBuffer.append:(Ljava/lang/String;)Ljava/lang/StringBuffer;
    1102: invokevirtual #9                  // Method java/lang/StringBuffer.toString:()Ljava/lang/String;
    1105: invokevirtual #13                 // Method java/io/PrintWriter.println:(Ljava/lang/String;)V
    1108: aload_0
    1109: ldc           #125                // String             }
    1111: invokevirtual #13                 // Method java/io/PrintWriter.println:(Ljava/lang/String;)V
    1114: aload_2
    1115: aload_1
    1116: if_acmpne     1157
    1119: aload_0
    1120: ldc           #126                // String           /* ACCEPT */
    1122: invokevirtual #13                 // Method java/io/PrintWriter.println:(Ljava/lang/String;)V
    1125: aload_0
    1126: new           #3                  // class java/lang/StringBuffer
    1129: dup
    1130: invokespecial #4                  // Method java/lang/StringBuffer."<init>":()V
    1133: ldc           #127                // String
    1135: invokevirtual #6                  // Method java/lang/StringBuffer.append:(Ljava/lang/String;)Ljava/lang/StringBuffer;
    1138: ldc           #128                // String parser
    1140: invokestatic  #52                 // Method pre:(Ljava/lang/String;)Ljava/lang/String;
    1143: invokevirtual #6                  // Method java/lang/StringBuffer.append:(Ljava/lang/String;)Ljava/lang/StringBuffer;
    1146: ldc           #129                // String .done_parsing();
    1148: invokevirtual #6                  // Method java/lang/StringBuffer.append:(Ljava/lang/String;)Ljava/lang/StringBuffer;
    1151: invokevirtual #9                  // Method java/lang/StringBuffer.toString:()Ljava/lang/String;
    1154: invokevirtual #13                 // Method java/io/PrintWriter.println:(Ljava/lang/String;)V
    1157: aload_0
    1158: new           #3                  // class java/lang/StringBuffer
    1161: dup
    1162: invokespecial #4                  // Method java/lang/StringBuffer."<init>":()V
    1165: ldc           #130                // String           return
    1167: invokevirtual #6                  // Method java/lang/StringBuffer.append:(Ljava/lang/String;)Ljava/lang/StringBuffer;
    1170: ldc           #76                 // String result
    1172: invokestatic  #52                 // Method pre:(Ljava/lang/String;)Ljava/lang/String;
    1175: invokevirtual #6                  // Method java/lang/StringBuffer.append:(Ljava/lang/String;)Ljava/lang/StringBuffer;
    1178: ldc           #12                 // String ;
    1180: invokevirtual #6                  // Method java/lang/StringBuffer.append:(Ljava/lang/String;)Ljava/lang/StringBuffer;
    1183: invokevirtual #9                  // Method java/lang/StringBuffer.toString:()Ljava/lang/String;
    1186: invokevirtual #13                 // Method java/io/PrintWriter.println:(Ljava/lang/String;)V
    1189: aload_0
    1190: invokevirtual #14                 // Method java/io/PrintWriter.println:()V
    1193: goto          411
    1196: aload_0
    1197: ldc           #131                // String           /* . . . . . .*/
    1199: invokevirtual #13                 // Method java/io/PrintWriter.println:(Ljava/lang/String;)V
    1202: aload_0
    1203: ldc           #132                // String           default:
    1205: invokevirtual #13                 // Method java/io/PrintWriter.println:(Ljava/lang/String;)V
    1208: aload_0
    1209: ldc           #133                // String             throw new Exception(
    1211: invokevirtual #13                 // Method java/io/PrintWriter.println:(Ljava/lang/String;)V
    1214: aload_0
    1215: ldc           #134                // String                \"Invalid action number found in internal parse table\");
    1217: invokevirtual #13                 // Method java/io/PrintWriter.println:(Ljava/lang/String;)V
    1220: aload_0
    1221: invokevirtual #14                 // Method java/io/PrintWriter.println:()V
    1224: aload_0
    1225: ldc           #135                // String         }
    1227: invokevirtual #13                 // Method java/io/PrintWriter.println:(Ljava/lang/String;)V
    1230: aload_0
    1231: ldc           #136                // String     }
    1233: invokevirtual #13                 // Method java/io/PrintWriter.println:(Ljava/lang/String;)V
    1236: aload_0
    1237: ldc           #47                 // String }
    1239: invokevirtual #13                 // Method java/io/PrintWriter.println:(Ljava/lang/String;)V
    1242: aload_0
    1243: invokevirtual #14                 // Method java/io/PrintWriter.println:()V
    1246: invokestatic  #17                 // Method java/lang/System.currentTimeMillis:()J
    1249: lload_3
    1250: lsub
    1251: putstatic     #137                // Field action_code_time:J
    1254: return

  protected static void emit_production_table(java.io.PrintWriter);
    Code:
       0: invokestatic  #17                 // Method java/lang/System.currentTimeMillis:()J
       3: lstore_3
       4: invokestatic  #138                // Method java_cup/production.number:()I
       7: anewarray     #83                 // class java_cup/production
      10: astore_1
      11: invokestatic  #82                 // Method java_cup/production.all:()Ljava/util/Enumeration;
      14: astore        5
      16: aload         5
      18: invokeinterface #33,  1           // InterfaceMethod java/util/Enumeration.hasMoreElements:()Z
      23: ifeq          47
      26: aload         5
      28: invokeinterface #34,  1           // InterfaceMethod java/util/Enumeration.nextElement:()Ljava/lang/Object;
      33: checkcast     #83                 // class java_cup/production
      36: astore_2
      37: aload_1
      38: aload_2
      39: invokevirtual #86                 // Method java_cup/production.index:()I
      42: aload_2
      43: aastore
      44: goto          16
      47: invokestatic  #138                // Method java_cup/production.number:()I
      50: iconst_2
      51: multianewarray #139,  2           // class "[[S"
      55: astore        5
      57: iconst_0
      58: istore        6
      60: iload         6
      62: invokestatic  #138                // Method java_cup/production.number:()I
      65: if_icmpge     109
      68: aload_1
      69: iload         6
      71: aaload
      72: astore_2
      73: aload         5
      75: iload         6
      77: aaload
      78: iconst_0
      79: aload_2
      80: invokevirtual #91                 // Method java_cup/production.lhs:()Ljava_cup/symbol_part;
      83: invokevirtual #92                 // Method java_cup/symbol_part.the_symbol:()Ljava_cup/symbol;
      86: invokevirtual #120                // Method java_cup/symbol.index:()I
      89: i2s
      90: sastore
      91: aload         5
      93: iload         6
      95: aaload
      96: iconst_1
      97: aload_2
      98: invokevirtual #95                 // Method java_cup/production.rhs_length:()I
     101: i2s
     102: sastore
     103: iinc          6, 1
     106: goto          60
     109: aload_0
     110: invokevirtual #14                 // Method java/io/PrintWriter.println:()V
     113: aload_0
     114: ldc           #140                // String   /** Production table. */
     116: invokevirtual #13                 // Method java/io/PrintWriter.println:(Ljava/lang/String;)V
     119: aload_0
     120: ldc           #141                // String   protected static final short _production_table[][] =
     122: invokevirtual #13                 // Method java/io/PrintWriter.println:(Ljava/lang/String;)V
     125: aload_0
     126: ldc           #142                // String     unpackFromStrings(
     128: invokevirtual #143                // Method java/io/PrintWriter.print:(Ljava/lang/String;)V
     131: aload_0
     132: aload         5
     134: invokestatic  #144                // Method do_table_as_string:(Ljava/io/PrintWriter;[[S)V
     137: aload_0
     138: ldc           #145                // String );
     140: invokevirtual #13                 // Method java/io/PrintWriter.println:(Ljava/lang/String;)V
     143: aload_0
     144: invokevirtual #14                 // Method java/io/PrintWriter.println:()V
     147: aload_0
     148: ldc           #146                // String   /** Access to production table. */
     150: invokevirtual #13                 // Method java/io/PrintWriter.println:(Ljava/lang/String;)V
     153: aload_0
     154: ldc           #147                // String   public short[][] production_table() {return _production_table;}
     156: invokevirtual #13                 // Method java/io/PrintWriter.println:(Ljava/lang/String;)V
     159: invokestatic  #17                 // Method java/lang/System.currentTimeMillis:()J
     162: lload_3
     163: lsub
     164: putstatic     #148                // Field production_table_time:J
     167: return

  protected static void do_action_table(java.io.PrintWriter, java_cup.parse_action_table, boolean) throws java_cup.internal_error;
    Code:
       0: invokestatic  #17                 // Method java/lang/System.currentTimeMillis:()J
       3: lstore        6
       5: aload_1
       6: invokevirtual #149                // Method java_cup/parse_action_table.num_states:()I
       9: anewarray     #150                // class "[S"
      12: astore        8
      14: iconst_0
      15: istore        9
      17: iload         9
      19: aload_1
      20: invokevirtual #149                // Method java_cup/parse_action_table.num_states:()I
      23: if_icmpge     337
      26: aload_1
      27: getfield      #151                // Field java_cup/parse_action_table.under_state:[Ljava_cup/parse_action_row;
      30: iload         9
      32: aaload
      33: astore_3
      34: iload_2
      35: ifeq          45
      38: aload_3
      39: invokevirtual #152                // Method java_cup/parse_action_row.compute_default:()V
      42: goto          50
      45: aload_3
      46: iconst_m1
      47: putfield      #153                // Field java_cup/parse_action_row.default_reduce:I
      50: iconst_2
      51: aload_3
      52: pop
      53: invokestatic  #154                // Method java_cup/parse_action_row.size:()I
      56: imul
      57: newarray       short
      59: astore        10
      61: iconst_0
      62: istore        11
      64: iconst_0
      65: istore        12
      67: iload         12
      69: aload_3
      70: pop
      71: invokestatic  #154                // Method java_cup/parse_action_row.size:()I
      74: if_icmpge     252
      77: aload_3
      78: getfield      #155                // Field java_cup/parse_action_row.under_term:[Ljava_cup/parse_action;
      81: iload         12
      83: aaload
      84: astore        4
      86: aload         4
      88: invokevirtual #156                // Method java_cup/parse_action.kind:()I
      91: ifeq          246
      94: aload         4
      96: invokevirtual #156                // Method java_cup/parse_action.kind:()I
      99: iconst_1
     100: if_icmpne     139
     103: aload         10
     105: iload         11
     107: iinc          11, 1
     110: iload         12
     112: i2s
     113: sastore
     114: aload         10
     116: iload         11
     118: iinc          11, 1
     121: aload         4
     123: checkcast     #157                // class java_cup/shift_action
     126: invokevirtual #158                // Method java_cup/shift_action.shift_to:()Ljava_cup/lalr_state;
     129: invokevirtual #159                // Method java_cup/lalr_state.index:()I
     132: iconst_1
     133: iadd
     134: i2s
     135: sastore
     136: goto          246
     139: aload         4
     141: invokevirtual #156                // Method java_cup/parse_action.kind:()I
     144: iconst_2
     145: if_icmpne     198
     148: aload         4
     150: checkcast     #160                // class java_cup/reduce_action
     153: invokevirtual #161                // Method java_cup/reduce_action.reduce_with:()Ljava_cup/production;
     156: invokevirtual #86                 // Method java_cup/production.index:()I
     159: istore        5
     161: iload         5
     163: aload_3
     164: getfield      #153                // Field java_cup/parse_action_row.default_reduce:I
     167: if_icmpeq     246
     170: aload         10
     172: iload         11
     174: iinc          11, 1
     177: iload         12
     179: i2s
     180: sastore
     181: aload         10
     183: iload         11
     185: iinc          11, 1
     188: iload         5
     190: iconst_1
     191: iadd
     192: ineg
     193: i2s
     194: sastore
     195: goto          246
     198: aload         4
     200: invokevirtual #156                // Method java_cup/parse_action.kind:()I
     203: iconst_3
     204: if_icmpne     210
     207: goto          246
     210: new           #162                // class java_cup/internal_error
     213: dup
     214: new           #3                  // class java/lang/StringBuffer
     217: dup
     218: invokespecial #4                  // Method java/lang/StringBuffer."<init>":()V
     221: ldc           #163                // String Unrecognized action code
     223: invokevirtual #6                  // Method java/lang/StringBuffer.append:(Ljava/lang/String;)Ljava/lang/StringBuffer;
     226: aload         4
     228: invokevirtual #156                // Method java_cup/parse_action.kind:()I
     231: invokevirtual #40                 // Method java/lang/StringBuffer.append:(I)Ljava/lang/StringBuffer;
     234: ldc           #164                // String  found in parse table
     236: invokevirtual #6                  // Method java/lang/StringBuffer.append:(Ljava/lang/String;)Ljava/lang/StringBuffer;
     239: invokevirtual #9                  // Method java/lang/StringBuffer.toString:()Ljava/lang/String;
     242: invokespecial #165                // Method java_cup/internal_error."<init>":(Ljava/lang/String;)V
     245: athrow
     246: iinc          12, 1
     249: goto          67
     252: aload         8
     254: iload         9
     256: iload         11
     258: iconst_2
     259: iadd
     260: newarray       short
     262: aastore
     263: aload         10
     265: iconst_0
     266: aload         8
     268: iload         9
     270: aaload
     271: iconst_0
     272: iload         11
     274: invokestatic  #166                // Method java/lang/System.arraycopy:(Ljava/lang/Object;ILjava/lang/Object;II)V
     277: aload         8
     279: iload         9
     281: aaload
     282: iload         11
     284: iinc          11, 1
     287: iconst_m1
     288: sastore
     289: aload_3
     290: getfield      #153                // Field java_cup/parse_action_row.default_reduce:I
     293: iconst_m1
     294: if_icmpeq     319
     297: aload         8
     299: iload         9
     301: aaload
     302: iload         11
     304: iinc          11, 1
     307: aload_3
     308: getfield      #153                // Field java_cup/parse_action_row.default_reduce:I
     311: iconst_1
     312: iadd
     313: ineg
     314: i2s
     315: sastore
     316: goto          331
     319: aload         8
     321: iload         9
     323: aaload
     324: iload         11
     326: iinc          11, 1
     329: iconst_0
     330: sastore
     331: iinc          9, 1
     334: goto          17
     337: aload_0
     338: invokevirtual #14                 // Method java/io/PrintWriter.println:()V
     341: aload_0
     342: ldc           #167                // String   /** Parse-action table. */
     344: invokevirtual #13                 // Method java/io/PrintWriter.println:(Ljava/lang/String;)V
     347: aload_0
     348: ldc           #168                // String   protected static final short[][] _action_table =
     350: invokevirtual #13                 // Method java/io/PrintWriter.println:(Ljava/lang/String;)V
     353: aload_0
     354: ldc           #142                // String     unpackFromStrings(
     356: invokevirtual #143                // Method java/io/PrintWriter.print:(Ljava/lang/String;)V
     359: aload_0
     360: aload         8
     362: invokestatic  #144                // Method do_table_as_string:(Ljava/io/PrintWriter;[[S)V
     365: aload_0
     366: ldc           #145                // String );
     368: invokevirtual #13                 // Method java/io/PrintWriter.println:(Ljava/lang/String;)V
     371: aload_0
     372: invokevirtual #14                 // Method java/io/PrintWriter.println:()V
     375: aload_0
     376: ldc           #169                // String   /** Access to parse-action table. */
     378: invokevirtual #13                 // Method java/io/PrintWriter.println:(Ljava/lang/String;)V
     381: aload_0
     382: ldc           #170                // String   public short[][] action_table() {return _action_table;}
     384: invokevirtual #13                 // Method java/io/PrintWriter.println:(Ljava/lang/String;)V
     387: invokestatic  #17                 // Method java/lang/System.currentTimeMillis:()J
     390: lload         6
     392: lsub
     393: putstatic     #171                // Field action_table_time:J
     396: return

  protected static void do_reduce_table(java.io.PrintWriter, java_cup.parse_reduce_table);
    Code:
       0: invokestatic  #17                 // Method java/lang/System.currentTimeMillis:()J
       3: lstore        4
       5: aload_1
       6: invokevirtual #172                // Method java_cup/parse_reduce_table.num_states:()I
       9: anewarray     #150                // class "[S"
      12: astore        6
      14: iconst_0
      15: istore        7
      17: iload         7
      19: aload_1
      20: invokevirtual #172                // Method java_cup/parse_reduce_table.num_states:()I
      23: if_icmpge     168
      26: iconst_2
      27: aload_1
      28: getfield      #173                // Field java_cup/parse_reduce_table.under_state:[Ljava_cup/parse_reduce_row;
      31: iload         7
      33: aaload
      34: pop
      35: invokestatic  #174                // Method java_cup/parse_reduce_row.size:()I
      38: imul
      39: newarray       short
      41: astore        8
      43: iconst_0
      44: istore        9
      46: iconst_0
      47: istore        10
      49: iload         10
      51: aload_1
      52: getfield      #173                // Field java_cup/parse_reduce_table.under_state:[Ljava_cup/parse_reduce_row;
      55: iload         7
      57: aaload
      58: pop
      59: invokestatic  #174                // Method java_cup/parse_reduce_row.size:()I
      62: if_icmpge     113
      65: aload_1
      66: getfield      #173                // Field java_cup/parse_reduce_table.under_state:[Ljava_cup/parse_reduce_row;
      69: iload         7
      71: aaload
      72: getfield      #175                // Field java_cup/parse_reduce_row.under_non_term:[Ljava_cup/lalr_state;
      75: iload         10
      77: aaload
      78: astore_2
      79: aload_2
      80: ifnull        107
      83: aload         8
      85: iload         9
      87: iinc          9, 1
      90: iload         10
      92: i2s
      93: sastore
      94: aload         8
      96: iload         9
      98: iinc          9, 1
     101: aload_2
     102: invokevirtual #159                // Method java_cup/lalr_state.index:()I
     105: i2s
     106: sastore
     107: iinc          10, 1
     110: goto          49
     113: aload         6
     115: iload         7
     117: iload         9
     119: iconst_2
     120: iadd
     121: newarray       short
     123: aastore
     124: aload         8
     126: iconst_0
     127: aload         6
     129: iload         7
     131: aaload
     132: iconst_0
     133: iload         9
     135: invokestatic  #166                // Method java/lang/System.arraycopy:(Ljava/lang/Object;ILjava/lang/Object;II)V
     138: aload         6
     140: iload         7
     142: aaload
     143: iload         9
     145: iinc          9, 1
     148: iconst_m1
     149: sastore
     150: aload         6
     152: iload         7
     154: aaload
     155: iload         9
     157: iinc          9, 1
     160: iconst_m1
     161: sastore
     162: iinc          7, 1
     165: goto          17
     168: aload_0
     169: invokevirtual #14                 // Method java/io/PrintWriter.println:()V
     172: aload_0
     173: ldc           #176                // String   /** <code>reduce_goto</code> table. */
     175: invokevirtual #13                 // Method java/io/PrintWriter.println:(Ljava/lang/String;)V
     178: aload_0
     179: ldc           #177                // String   protected static final short[][] _reduce_table =
     181: invokevirtual #13                 // Method java/io/PrintWriter.println:(Ljava/lang/String;)V
     184: aload_0
     185: ldc           #142                // String     unpackFromStrings(
     187: invokevirtual #143                // Method java/io/PrintWriter.print:(Ljava/lang/String;)V
     190: aload_0
     191: aload         6
     193: invokestatic  #144                // Method do_table_as_string:(Ljava/io/PrintWriter;[[S)V
     196: aload_0
     197: ldc           #145                // String );
     199: invokevirtual #13                 // Method java/io/PrintWriter.println:(Ljava/lang/String;)V
     202: aload_0
     203: invokevirtual #14                 // Method java/io/PrintWriter.println:()V
     206: aload_0
     207: ldc           #178                // String   /** Access to <code>reduce_goto</code> table. */
     209: invokevirtual #13                 // Method java/io/PrintWriter.println:(Ljava/lang/String;)V
     212: aload_0
     213: ldc           #179                // String   public short[][] reduce_table() {return _reduce_table;}
     215: invokevirtual #13                 // Method java/io/PrintWriter.println:(Ljava/lang/String;)V
     218: aload_0
     219: invokevirtual #14                 // Method java/io/PrintWriter.println:()V
     222: invokestatic  #17                 // Method java/lang/System.currentTimeMillis:()J
     225: lload         4
     227: lsub
     228: putstatic     #180                // Field goto_table_time:J
     231: return

  protected static void do_table_as_string(java.io.PrintWriter, short[][]);
    Code:
       0: aload_0
       1: ldc           #181                // String new String[] {
       3: invokevirtual #13                 // Method java/io/PrintWriter.println:(Ljava/lang/String;)V
       6: aload_0
       7: ldc           #182                // String     \"
       9: invokevirtual #143                // Method java/io/PrintWriter.print:(Ljava/lang/String;)V
      12: iconst_0
      13: istore_2
      14: iconst_0
      15: istore_3
      16: iload_3
      17: aload_0
      18: aload_1
      19: arraylength
      20: bipush        16
      22: ishr
      23: i2c
      24: invokestatic  #183                // Method do_escaped:(Ljava/io/PrintWriter;C)I
      27: iadd
      28: istore_3
      29: aload_0
      30: iload_2
      31: iload_3
      32: invokestatic  #184                // Method do_newline:(Ljava/io/PrintWriter;II)I
      35: istore_2
      36: iload_3
      37: aload_0
      38: aload_1
      39: arraylength
      40: ldc           #185                // int 65535
      42: iand
      43: i2c
      44: invokestatic  #183                // Method do_escaped:(Ljava/io/PrintWriter;C)I
      47: iadd
      48: istore_3
      49: aload_0
      50: iload_2
      51: iload_3
      52: invokestatic  #184                // Method do_newline:(Ljava/io/PrintWriter;II)I
      55: istore_2
      56: iconst_0
      57: istore        4
      59: iload         4
      61: aload_1
      62: arraylength
      63: if_icmpge     161
      66: iload_3
      67: aload_0
      68: aload_1
      69: iload         4
      71: aaload
      72: arraylength
      73: bipush        16
      75: ishr
      76: i2c
      77: invokestatic  #183                // Method do_escaped:(Ljava/io/PrintWriter;C)I
      80: iadd
      81: istore_3
      82: aload_0
      83: iload_2
      84: iload_3
      85: invokestatic  #184                // Method do_newline:(Ljava/io/PrintWriter;II)I
      88: istore_2
      89: iload_3
      90: aload_0
      91: aload_1
      92: iload         4
      94: aaload
      95: arraylength
      96: ldc           #185                // int 65535
      98: iand
      99: i2c
     100: invokestatic  #183                // Method do_escaped:(Ljava/io/PrintWriter;C)I
     103: iadd
     104: istore_3
     105: aload_0
     106: iload_2
     107: iload_3
     108: invokestatic  #184                // Method do_newline:(Ljava/io/PrintWriter;II)I
     111: istore_2
     112: iconst_0
     113: istore        5
     115: iload         5
     117: aload_1
     118: iload         4
     120: aaload
     121: arraylength
     122: if_icmpge     155
     125: iload_3
     126: aload_0
     127: iconst_2
     128: aload_1
     129: iload         4
     131: aaload
     132: iload         5
     134: saload
     135: iadd
     136: i2c
     137: invokestatic  #183                // Method do_escaped:(Ljava/io/PrintWriter;C)I
     140: iadd
     141: istore_3
     142: aload_0
     143: iload_2
     144: iload_3
     145: invokestatic  #184                // Method do_newline:(Ljava/io/PrintWriter;II)I
     148: istore_2
     149: iinc          5, 1
     152: goto          115
     155: iinc          4, 1
     158: goto          59
     161: aload_0
     162: ldc           #186                // String \" }
     164: invokevirtual #143                // Method java/io/PrintWriter.print:(Ljava/lang/String;)V
     167: return

  protected static int do_newline(java.io.PrintWriter, int, int);
    Code:
       0: iload_2
       1: ldc           #187                // int 65500
       3: if_icmple     21
       6: aload_0
       7: ldc           #188                // String \",
       9: invokevirtual #13                 // Method java/io/PrintWriter.println:(Ljava/lang/String;)V
      12: aload_0
      13: ldc           #182                // String     \"
      15: invokevirtual #143                // Method java/io/PrintWriter.print:(Ljava/lang/String;)V
      18: goto          46
      21: iload_1
      22: bipush        11
      24: if_icmple     42
      27: aload_0
      28: ldc           #189                // String \" +
      30: invokevirtual #13                 // Method java/io/PrintWriter.println:(Ljava/lang/String;)V
      33: aload_0
      34: ldc           #182                // String     \"
      36: invokevirtual #143                // Method java/io/PrintWriter.print:(Ljava/lang/String;)V
      39: goto          46
      42: iload_1
      43: iconst_1
      44: iadd
      45: ireturn
      46: iconst_0
      47: ireturn

  protected static int do_escaped(java.io.PrintWriter, char);
    Code:
       0: new           #3                  // class java/lang/StringBuffer
       3: dup
       4: invokespecial #4                  // Method java/lang/StringBuffer."<init>":()V
       7: astore_2
       8: iload_1
       9: sipush        255
      12: if_icmpgt     43
      15: aload_2
      16: iload_1
      17: invokestatic  #190                // Method java/lang/Integer.toOctalString:(I)Ljava/lang/String;
      20: invokevirtual #6                  // Method java/lang/StringBuffer.append:(Ljava/lang/String;)Ljava/lang/StringBuffer;
      23: pop
      24: aload_2
      25: invokevirtual #191                // Method java/lang/StringBuffer.length:()I
      28: iconst_3
      29: if_icmpge     79
      32: aload_2
      33: iconst_0
      34: bipush        48
      36: invokevirtual #192                // Method java/lang/StringBuffer.insert:(IC)Ljava/lang/StringBuffer;
      39: pop
      40: goto          24
      43: aload_2
      44: iload_1
      45: invokestatic  #193                // Method java/lang/Integer.toHexString:(I)Ljava/lang/String;
      48: invokevirtual #6                  // Method java/lang/StringBuffer.append:(Ljava/lang/String;)Ljava/lang/StringBuffer;
      51: pop
      52: aload_2
      53: invokevirtual #191                // Method java/lang/StringBuffer.length:()I
      56: iconst_4
      57: if_icmpge     71
      60: aload_2
      61: iconst_0
      62: bipush        48
      64: invokevirtual #192                // Method java/lang/StringBuffer.insert:(IC)Ljava/lang/StringBuffer;
      67: pop
      68: goto          52
      71: aload_2
      72: iconst_0
      73: bipush        117
      75: invokevirtual #192                // Method java/lang/StringBuffer.insert:(IC)Ljava/lang/StringBuffer;
      78: pop
      79: aload_2
      80: iconst_0
      81: bipush        92
      83: invokevirtual #192                // Method java/lang/StringBuffer.insert:(IC)Ljava/lang/StringBuffer;
      86: pop
      87: aload_0
      88: aload_2
      89: invokevirtual #9                  // Method java/lang/StringBuffer.toString:()Ljava/lang/String;
      92: invokevirtual #143                // Method java/io/PrintWriter.print:(Ljava/lang/String;)V
      95: iload_1
      96: ifne          101
      99: iconst_2
     100: ireturn
     101: iload_1
     102: iconst_1
     103: if_icmplt     114
     106: iload_1
     107: bipush        127
     109: if_icmpgt     114
     112: iconst_1
     113: ireturn
     114: iload_1
     115: sipush        128
     118: if_icmplt     130
     121: iload_1
     122: sipush        2047
     125: if_icmpgt     130
     128: iconst_2
     129: ireturn
     130: iconst_3
     131: ireturn

  public static void parser(java.io.PrintWriter, java_cup.parse_action_table, java_cup.parse_reduce_table, int, java_cup.production, boolean, boolean) throws java_cup.internal_error;
    Code:
       0: invokestatic  #17                 // Method java/lang/System.currentTimeMillis:()J
       3: lstore        7
       5: aload_0
       6: invokevirtual #14                 // Method java/io/PrintWriter.println:()V
       9: aload_0
      10: ldc           #18                 // String //----------------------------------------------------
      12: invokevirtual #13                 // Method java/io/PrintWriter.println:(Ljava/lang/String;)V
      15: aload_0
      16: ldc           #19                 // String // The following code was generated by CUP v0.10k
      18: invokevirtual #13                 // Method java/io/PrintWriter.println:(Ljava/lang/String;)V
      21: aload_0
      22: new           #3                  // class java/lang/StringBuffer
      25: dup
      26: invokespecial #4                  // Method java/lang/StringBuffer."<init>":()V
      29: ldc           #20                 // String //
      31: invokevirtual #6                  // Method java/lang/StringBuffer.append:(Ljava/lang/String;)Ljava/lang/StringBuffer;
      34: new           #21                 // class java/util/Date
      37: dup
      38: invokespecial #22                 // Method java/util/Date."<init>":()V
      41: invokevirtual #23                 // Method java/lang/StringBuffer.append:(Ljava/lang/Object;)Ljava/lang/StringBuffer;
      44: invokevirtual #9                  // Method java/lang/StringBuffer.toString:()Ljava/lang/String;
      47: invokevirtual #13                 // Method java/io/PrintWriter.println:(Ljava/lang/String;)V
      50: aload_0
      51: ldc           #18                 // String //----------------------------------------------------
      53: invokevirtual #13                 // Method java/io/PrintWriter.println:(Ljava/lang/String;)V
      56: aload_0
      57: invokevirtual #14                 // Method java/io/PrintWriter.println:()V
      60: aload_0
      61: invokestatic  #24                 // Method emit_package:(Ljava/io/PrintWriter;)V
      64: iconst_0
      65: istore        9
      67: iload         9
      69: getstatic     #194                // Field import_list:Ljava/util/Stack;
      72: invokevirtual #195                // Method java/util/Stack.size:()I
      75: if_icmpge     119
      78: aload_0
      79: new           #3                  // class java/lang/StringBuffer
      82: dup
      83: invokespecial #4                  // Method java/lang/StringBuffer."<init>":()V
      86: ldc           #196                // String import
      88: invokevirtual #6                  // Method java/lang/StringBuffer.append:(Ljava/lang/String;)Ljava/lang/StringBuffer;
      91: getstatic     #194                // Field import_list:Ljava/util/Stack;
      94: iload         9
      96: invokevirtual #197                // Method java/util/Stack.elementAt:(I)Ljava/lang/Object;
      99: invokevirtual #23                 // Method java/lang/StringBuffer.append:(Ljava/lang/Object;)Ljava/lang/StringBuffer;
     102: ldc           #12                 // String ;
     104: invokevirtual #6                  // Method java/lang/StringBuffer.append:(Ljava/lang/String;)Ljava/lang/StringBuffer;
     107: invokevirtual #9                  // Method java/lang/StringBuffer.toString:()Ljava/lang/String;
     110: invokevirtual #13                 // Method java/io/PrintWriter.println:(Ljava/lang/String;)V
     113: iinc          9, 1
     116: goto          67
     119: aload_0
     120: invokevirtual #14                 // Method java/io/PrintWriter.println:()V
     123: aload_0
     124: ldc           #198                // String /** CUP v0.10k generated parser.
     126: invokevirtual #13                 // Method java/io/PrintWriter.println:(Ljava/lang/String;)V
     129: aload_0
     130: new           #3                  // class java/lang/StringBuffer
     133: dup
     134: invokespecial #4                  // Method java/lang/StringBuffer."<init>":()V
     137: ldc           #199                // String   * @version
     139: invokevirtual #6                  // Method java/lang/StringBuffer.append:(Ljava/lang/String;)Ljava/lang/StringBuffer;
     142: new           #21                 // class java/util/Date
     145: dup
     146: invokespecial #22                 // Method java/util/Date."<init>":()V
     149: invokevirtual #23                 // Method java/lang/StringBuffer.append:(Ljava/lang/Object;)Ljava/lang/StringBuffer;
     152: invokevirtual #9                  // Method java/lang/StringBuffer.toString:()Ljava/lang/String;
     155: invokevirtual #13                 // Method java/io/PrintWriter.println:(Ljava/lang/String;)V
     158: aload_0
     159: ldc           #200                // String   */
     161: invokevirtual #13                 // Method java/io/PrintWriter.println:(Ljava/lang/String;)V
     164: aload_0
     165: new           #3                  // class java/lang/StringBuffer
     168: dup
     169: invokespecial #4                  // Method java/lang/StringBuffer."<init>":()V
     172: ldc           #201                // String public class
     174: invokevirtual #6                  // Method java/lang/StringBuffer.append:(Ljava/lang/String;)Ljava/lang/StringBuffer;
     177: getstatic     #7                  // Field parser_class_name:Ljava/lang/String;
     180: invokevirtual #6                  // Method java/lang/StringBuffer.append:(Ljava/lang/String;)Ljava/lang/StringBuffer;
     183: ldc           #202                // String  extends java_cup.runtime.lr_parser {
     185: invokevirtual #6                  // Method java/lang/StringBuffer.append:(Ljava/lang/String;)Ljava/lang/StringBuffer;
     188: invokevirtual #9                  // Method java/lang/StringBuffer.toString:()Ljava/lang/String;
     191: invokevirtual #13                 // Method java/io/PrintWriter.println:(Ljava/lang/String;)V
     194: aload_0
     195: invokevirtual #14                 // Method java/io/PrintWriter.println:()V
     198: aload_0
     199: ldc           #203                // String   /** Default constructor. */
     201: invokevirtual #13                 // Method java/io/PrintWriter.println:(Ljava/lang/String;)V
     204: aload_0
     205: new           #3                  // class java/lang/StringBuffer
     208: dup
     209: invokespecial #4                  // Method java/lang/StringBuffer."<init>":()V
     212: ldc           #204                // String   public
     214: invokevirtual #6                  // Method java/lang/StringBuffer.append:(Ljava/lang/String;)Ljava/lang/StringBuffer;
     217: getstatic     #7                  // Field parser_class_name:Ljava/lang/String;
     220: invokevirtual #6                  // Method java/lang/StringBuffer.append:(Ljava/lang/String;)Ljava/lang/StringBuffer;
     223: ldc           #205                // String () {super();}
     225: invokevirtual #6                  // Method java/lang/StringBuffer.append:(Ljava/lang/String;)Ljava/lang/StringBuffer;
     228: invokevirtual #9                  // Method java/lang/StringBuffer.toString:()Ljava/lang/String;
     231: invokevirtual #13                 // Method java/io/PrintWriter.println:(Ljava/lang/String;)V
     234: iload         6
     236: ifne          279
     239: aload_0
     240: invokevirtual #14                 // Method java/io/PrintWriter.println:()V
     243: aload_0
     244: ldc           #206                // String   /** Constructor which sets the default scanner. */
     246: invokevirtual #13                 // Method java/io/PrintWriter.println:(Ljava/lang/String;)V
     249: aload_0
     250: new           #3                  // class java/lang/StringBuffer
     253: dup
     254: invokespecial #4                  // Method java/lang/StringBuffer."<init>":()V
     257: ldc           #204                // String   public
     259: invokevirtual #6                  // Method java/lang/StringBuffer.append:(Ljava/lang/String;)Ljava/lang/StringBuffer;
     262: getstatic     #7                  // Field parser_class_name:Ljava/lang/String;
     265: invokevirtual #6                  // Method java/lang/StringBuffer.append:(Ljava/lang/String;)Ljava/lang/StringBuffer;
     268: ldc           #207                // String (java_cup.runtime.Scanner s) {super(s);}
     270: invokevirtual #6                  // Method java/lang/StringBuffer.append:(Ljava/lang/String;)Ljava/lang/StringBuffer;
     273: invokevirtual #9                  // Method java/lang/StringBuffer.toString:()Ljava/lang/String;
     276: invokevirtual #13                 // Method java/io/PrintWriter.println:(Ljava/lang/String;)V
     279: aload_0
     280: invokestatic  #208                // Method emit_production_table:(Ljava/io/PrintWriter;)V
     283: aload_0
     284: aload_1
     285: iload         5
     287: invokestatic  #209                // Method do_action_table:(Ljava/io/PrintWriter;Ljava_cup/parse_action_table;Z)V
     290: aload_0
     291: aload_2
     292: invokestatic  #210                // Method do_reduce_table:(Ljava/io/PrintWriter;Ljava_cup/parse_reduce_table;)V
     295: aload_0
     296: ldc           #211                // String   /** Instance of action encapsulation class. */
     298: invokevirtual #13                 // Method java/io/PrintWriter.println:(Ljava/lang/String;)V
     301: aload_0
     302: new           #3                  // class java/lang/StringBuffer
     305: dup
     306: invokespecial #4                  // Method java/lang/StringBuffer."<init>":()V
     309: ldc           #212                // String   protected
     311: invokevirtual #6                  // Method java/lang/StringBuffer.append:(Ljava/lang/String;)Ljava/lang/StringBuffer;
     314: ldc           #51                 // String actions
     316: invokestatic  #52                 // Method pre:(Ljava/lang/String;)Ljava/lang/String;
     319: invokevirtual #6                  // Method java/lang/StringBuffer.append:(Ljava/lang/String;)Ljava/lang/StringBuffer;
     322: ldc           #213                // String  action_obj;
     324: invokevirtual #6                  // Method java/lang/StringBuffer.append:(Ljava/lang/String;)Ljava/lang/StringBuffer;
     327: invokevirtual #9                  // Method java/lang/StringBuffer.toString:()Ljava/lang/String;
     330: invokevirtual #13                 // Method java/io/PrintWriter.println:(Ljava/lang/String;)V
     333: aload_0
     334: invokevirtual #14                 // Method java/io/PrintWriter.println:()V
     337: aload_0
     338: ldc           #214                // String   /** Action encapsulation object initializer. */
     340: invokevirtual #13                 // Method java/io/PrintWriter.println:(Ljava/lang/String;)V
     343: aload_0
     344: ldc           #215                // String   protected void init_actions()
     346: invokevirtual #13                 // Method java/io/PrintWriter.println:(Ljava/lang/String;)V
     349: aload_0
     350: ldc           #73                 // String     {
     352: invokevirtual #13                 // Method java/io/PrintWriter.println:(Ljava/lang/String;)V
     355: aload_0
     356: new           #3                  // class java/lang/StringBuffer
     359: dup
     360: invokespecial #4                  // Method java/lang/StringBuffer."<init>":()V
     363: ldc           #216                // String       action_obj = new
     365: invokevirtual #6                  // Method java/lang/StringBuffer.append:(Ljava/lang/String;)Ljava/lang/StringBuffer;
     368: ldc           #51                 // String actions
     370: invokestatic  #52                 // Method pre:(Ljava/lang/String;)Ljava/lang/String;
     373: invokevirtual #6                  // Method java/lang/StringBuffer.append:(Ljava/lang/String;)Ljava/lang/StringBuffer;
     376: ldc           #217                // String (this);
     378: invokevirtual #6                  // Method java/lang/StringBuffer.append:(Ljava/lang/String;)Ljava/lang/StringBuffer;
     381: invokevirtual #9                  // Method java/lang/StringBuffer.toString:()Ljava/lang/String;
     384: invokevirtual #13                 // Method java/io/PrintWriter.println:(Ljava/lang/String;)V
     387: aload_0
     388: ldc           #136                // String     }
     390: invokevirtual #13                 // Method java/io/PrintWriter.println:(Ljava/lang/String;)V
     393: aload_0
     394: invokevirtual #14                 // Method java/io/PrintWriter.println:()V
     397: aload_0
     398: ldc           #218                // String   /** Invoke a user supplied parse action. */
     400: invokevirtual #13                 // Method java/io/PrintWriter.println:(Ljava/lang/String;)V
     403: aload_0
     404: ldc           #219                // String   public java_cup.runtime.Symbol do_action(
     406: invokevirtual #13                 // Method java/io/PrintWriter.println:(Ljava/lang/String;)V
     409: aload_0
     410: ldc           #220                // String     int                        act_num,
     412: invokevirtual #13                 // Method java/io/PrintWriter.println:(Ljava/lang/String;)V
     415: aload_0
     416: ldc           #221                // String     java_cup.runtime.lr_parser parser,
     418: invokevirtual #13                 // Method java/io/PrintWriter.println:(Ljava/lang/String;)V
     421: aload_0
     422: ldc           #222                // String     java.util.Stack            stack,
     424: invokevirtual #13                 // Method java/io/PrintWriter.println:(Ljava/lang/String;)V
     427: aload_0
     428: ldc           #223                // String     int                        top)
     430: invokevirtual #13                 // Method java/io/PrintWriter.println:(Ljava/lang/String;)V
     433: aload_0
     434: ldc           #72                 // String     throws java.lang.Exception
     436: invokevirtual #13                 // Method java/io/PrintWriter.println:(Ljava/lang/String;)V
     439: aload_0
     440: ldc           #224                // String   {
     442: invokevirtual #13                 // Method java/io/PrintWriter.println:(Ljava/lang/String;)V
     445: aload_0
     446: ldc           #225                // String     /* call code in generated class */
     448: invokevirtual #13                 // Method java/io/PrintWriter.println:(Ljava/lang/String;)V
     451: aload_0
     452: new           #3                  // class java/lang/StringBuffer
     455: dup
     456: invokespecial #4                  // Method java/lang/StringBuffer."<init>":()V
     459: ldc           #226                // String     return action_obj.
     461: invokevirtual #6                  // Method java/lang/StringBuffer.append:(Ljava/lang/String;)Ljava/lang/StringBuffer;
     464: ldc           #227                // String do_action(
     466: invokestatic  #52                 // Method pre:(Ljava/lang/String;)Ljava/lang/String;
     469: invokevirtual #6                  // Method java/lang/StringBuffer.append:(Ljava/lang/String;)Ljava/lang/StringBuffer;
     472: ldc           #228                // String act_num, parser, stack, top);
     474: invokevirtual #6                  // Method java/lang/StringBuffer.append:(Ljava/lang/String;)Ljava/lang/StringBuffer;
     477: invokevirtual #9                  // Method java/lang/StringBuffer.toString:()Ljava/lang/String;
     480: invokevirtual #13                 // Method java/io/PrintWriter.println:(Ljava/lang/String;)V
     483: aload_0
     484: ldc           #61                 // String   }
     486: invokevirtual #13                 // Method java/io/PrintWriter.println:(Ljava/lang/String;)V
     489: aload_0
     490: ldc           #113                // String
     492: invokevirtual #13                 // Method java/io/PrintWriter.println:(Ljava/lang/String;)V
     495: aload_0
     496: ldc           #229                // String   /** Indicates start state. */
     498: invokevirtual #13                 // Method java/io/PrintWriter.println:(Ljava/lang/String;)V
     501: aload_0
     502: new           #3                  // class java/lang/StringBuffer
     505: dup
     506: invokespecial #4                  // Method java/lang/StringBuffer."<init>":()V
     509: ldc           #230                // String   public int start_state() {return
     511: invokevirtual #6                  // Method java/lang/StringBuffer.append:(Ljava/lang/String;)Ljava/lang/StringBuffer;
     514: iload_3
     515: invokevirtual #40                 // Method java/lang/StringBuffer.append:(I)Ljava/lang/StringBuffer;
     518: ldc           #231                // String ;}
     520: invokevirtual #6                  // Method java/lang/StringBuffer.append:(Ljava/lang/String;)Ljava/lang/StringBuffer;
     523: invokevirtual #9                  // Method java/lang/StringBuffer.toString:()Ljava/lang/String;
     526: invokevirtual #13                 // Method java/io/PrintWriter.println:(Ljava/lang/String;)V
     529: aload_0
     530: ldc           #232                // String   /** Indicates start production. */
     532: invokevirtual #13                 // Method java/io/PrintWriter.println:(Ljava/lang/String;)V
     535: aload_0
     536: new           #3                  // class java/lang/StringBuffer
     539: dup
     540: invokespecial #4                  // Method java/lang/StringBuffer."<init>":()V
     543: ldc           #233                // String   public int start_production() {return
     545: invokevirtual #6                  // Method java/lang/StringBuffer.append:(Ljava/lang/String;)Ljava/lang/StringBuffer;
     548: getstatic     #234                // Field start_production:Ljava_cup/production;
     551: invokevirtual #86                 // Method java_cup/production.index:()I
     554: invokevirtual #40                 // Method java/lang/StringBuffer.append:(I)Ljava/lang/StringBuffer;
     557: ldc           #231                // String ;}
     559: invokevirtual #6                  // Method java/lang/StringBuffer.append:(Ljava/lang/String;)Ljava/lang/StringBuffer;
     562: invokevirtual #9                  // Method java/lang/StringBuffer.toString:()Ljava/lang/String;
     565: invokevirtual #13                 // Method java/io/PrintWriter.println:(Ljava/lang/String;)V
     568: aload_0
     569: invokevirtual #14                 // Method java/io/PrintWriter.println:()V
     572: aload_0
     573: ldc           #235                // String   /** <code>EOF</code> Symbol index. */
     575: invokevirtual #13                 // Method java/io/PrintWriter.println:(Ljava/lang/String;)V
     578: aload_0
     579: new           #3                  // class java/lang/StringBuffer
     582: dup
     583: invokespecial #4                  // Method java/lang/StringBuffer."<init>":()V
     586: ldc           #236                // String   public int EOF_sym() {return
     588: invokevirtual #6                  // Method java/lang/StringBuffer.append:(Ljava/lang/String;)Ljava/lang/StringBuffer;
     591: getstatic     #237                // Field java_cup/terminal.EOF:Ljava_cup/terminal;
     594: invokevirtual #39                 // Method java_cup/terminal.index:()I
     597: invokevirtual #40                 // Method java/lang/StringBuffer.append:(I)Ljava/lang/StringBuffer;
     600: ldc           #231                // String ;}
     602: invokevirtual #6                  // Method java/lang/StringBuffer.append:(Ljava/lang/String;)Ljava/lang/StringBuffer;
     605: invokevirtual #9                  // Method java/lang/StringBuffer.toString:()Ljava/lang/String;
     608: invokevirtual #13                 // Method java/io/PrintWriter.println:(Ljava/lang/String;)V
     611: aload_0
     612: invokevirtual #14                 // Method java/io/PrintWriter.println:()V
     615: aload_0
     616: ldc           #238                // String   /** <code>error</code> Symbol index. */
     618: invokevirtual #13                 // Method java/io/PrintWriter.println:(Ljava/lang/String;)V
     621: aload_0
     622: new           #3                  // class java/lang/StringBuffer
     625: dup
     626: invokespecial #4                  // Method java/lang/StringBuffer."<init>":()V
     629: ldc           #239                // String   public int error_sym() {return
     631: invokevirtual #6                  // Method java/lang/StringBuffer.append:(Ljava/lang/String;)Ljava/lang/StringBuffer;
     634: getstatic     #240                // Field java_cup/terminal.error:Ljava_cup/terminal;
     637: invokevirtual #39                 // Method java_cup/terminal.index:()I
     640: invokevirtual #40                 // Method java/lang/StringBuffer.append:(I)Ljava/lang/StringBuffer;
     643: ldc           #231                // String ;}
     645: invokevirtual #6                  // Method java/lang/StringBuffer.append:(Ljava/lang/String;)Ljava/lang/StringBuffer;
     648: invokevirtual #9                  // Method java/lang/StringBuffer.toString:()Ljava/lang/String;
     651: invokevirtual #13                 // Method java/io/PrintWriter.println:(Ljava/lang/String;)V
     654: aload_0
     655: invokevirtual #14                 // Method java/io/PrintWriter.println:()V
     658: getstatic     #241                // Field init_code:Ljava/lang/String;
     661: ifnull        699
     664: aload_0
     665: invokevirtual #14                 // Method java/io/PrintWriter.println:()V
     668: aload_0
     669: ldc           #242                // String   /** User initialization code. */
     671: invokevirtual #13                 // Method java/io/PrintWriter.println:(Ljava/lang/String;)V
     674: aload_0
     675: ldc           #243                // String   public void user_init() throws java.lang.Exception
     677: invokevirtual #13                 // Method java/io/PrintWriter.println:(Ljava/lang/String;)V
     680: aload_0
     681: ldc           #73                 // String     {
     683: invokevirtual #13                 // Method java/io/PrintWriter.println:(Ljava/lang/String;)V
     686: aload_0
     687: getstatic     #241                // Field init_code:Ljava/lang/String;
     690: invokevirtual #13                 // Method java/io/PrintWriter.println:(Ljava/lang/String;)V
     693: aload_0
     694: ldc           #136                // String     }
     696: invokevirtual #13                 // Method java/io/PrintWriter.println:(Ljava/lang/String;)V
     699: getstatic     #244                // Field scan_code:Ljava/lang/String;
     702: ifnull        746
     705: aload_0
     706: invokevirtual #14                 // Method java/io/PrintWriter.println:()V
     709: aload_0
     710: ldc           #245                // String   /** Scan to get the next Symbol. */
     712: invokevirtual #13                 // Method java/io/PrintWriter.println:(Ljava/lang/String;)V
     715: aload_0
     716: ldc           #246                // String   public java_cup.runtime.Symbol scan()
     718: invokevirtual #13                 // Method java/io/PrintWriter.println:(Ljava/lang/String;)V
     721: aload_0
     722: ldc           #72                 // String     throws java.lang.Exception
     724: invokevirtual #13                 // Method java/io/PrintWriter.println:(Ljava/lang/String;)V
     727: aload_0
     728: ldc           #73                 // String     {
     730: invokevirtual #13                 // Method java/io/PrintWriter.println:(Ljava/lang/String;)V
     733: aload_0
     734: getstatic     #244                // Field scan_code:Ljava/lang/String;
     737: invokevirtual #13                 // Method java/io/PrintWriter.println:(Ljava/lang/String;)V
     740: aload_0
     741: ldc           #136                // String     }
     743: invokevirtual #13                 // Method java/io/PrintWriter.println:(Ljava/lang/String;)V
     746: getstatic     #247                // Field parser_code:Ljava/lang/String;
     749: ifnull        763
     752: aload_0
     753: invokevirtual #14                 // Method java/io/PrintWriter.println:()V
     756: aload_0
     757: getstatic     #247                // Field parser_code:Ljava/lang/String;
     760: invokevirtual #13                 // Method java/io/PrintWriter.println:(Ljava/lang/String;)V
     763: aload_0
     764: ldc           #47                 // String }
     766: invokevirtual #13                 // Method java/io/PrintWriter.println:(Ljava/lang/String;)V
     769: aload_0
     770: aload         4
     772: invokestatic  #248                // Method emit_action_code:(Ljava/io/PrintWriter;Ljava_cup/production;)V
     775: invokestatic  #17                 // Method java/lang/System.currentTimeMillis:()J
     778: lload         7
     780: lsub
     781: putstatic     #249                // Field parser_time:J
     784: return

  static {};
    Code:
       0: ldc           #250                // String CUP$
       2: putstatic     #5                  // Field prefix:Ljava/lang/String;
       5: aconst_null
       6: putstatic     #10                 // Field package_name:Ljava/lang/String;
       9: ldc           #251                // String sym
      11: putstatic     #29                 // Field symbol_const_class_name:Ljava/lang/String;
      14: ldc           #128                // String parser
      16: putstatic     #7                  // Field parser_class_name:Ljava/lang/String;
      19: aconst_null
      20: putstatic     #53                 // Field action_code:Ljava/lang/String;
      23: aconst_null
      24: putstatic     #247                // Field parser_code:Ljava/lang/String;
      27: aconst_null
      28: putstatic     #241                // Field init_code:Ljava/lang/String;
      31: aconst_null
      32: putstatic     #244                // Field scan_code:Ljava/lang/String;
      35: aconst_null
      36: putstatic     #234                // Field start_production:Ljava_cup/production;
      39: new           #252                // class java/util/Stack
      42: dup
      43: invokespecial #253                // Method java/util/Stack."<init>":()V
      46: putstatic     #194                // Field import_list:Ljava/util/Stack;
      49: iconst_0
      50: putstatic     #254                // Field num_conflicts:I
      53: iconst_0
      54: putstatic     #255                // Field nowarn:Z
      57: iconst_0
      58: putstatic     #256                // Field not_reduced:I
      61: iconst_0
      62: putstatic     #257                // Field unused_term:I
      65: iconst_0
      66: putstatic     #258                // Field unused_non_term:I
      69: lconst_0
      70: putstatic     #48                 // Field symbols_time:J
      73: lconst_0
      74: putstatic     #249                // Field parser_time:J
      77: lconst_0
      78: putstatic     #137                // Field action_code_time:J
      81: lconst_0
      82: putstatic     #148                // Field production_table_time:J
      85: lconst_0
      86: putstatic     #171                // Field action_table_time:J
      89: lconst_0
      90: putstatic     #180                // Field goto_table_time:J
      93: return
}
