Compiled from "production_part.java"
public abstract class java_cup.production_part {
  protected java.lang.String _label;

  public java_cup.production_part(java.lang.String);
    Code:
       0: aload_0
       1: invokespecial #1                  // Method java/lang/Object."<init>":()V
       4: aload_0
       5: aload_1
       6: putfield      #2                  // Field _label:Ljava/lang/String;
       9: return

  public java.lang.String label();
    Code:
       0: aload_0
       1: getfield      #2                  // Field _label:Ljava/lang/String;
       4: areturn

  public abstract boolean is_action();

  public boolean equals(java_cup.production_part);
    Code:
       0: aload_1
       1: ifnonnull     6
       4: iconst_0
       5: ireturn
       6: aload_0
       7: invokevirtual #3                  // Method label:()Ljava/lang/String;
      10: ifnull        25
      13: aload_0
      14: invokevirtual #3                  // Method label:()Ljava/lang/String;
      17: aload_1
      18: invokevirtual #3                  // Method label:()Ljava/lang/String;
      21: invokevirtual #4                  // Method java/lang/String.equals:(Ljava/lang/Object;)Z
      24: ireturn
      25: aload_1
      26: invokevirtual #3                  // Method label:()Ljava/lang/String;
      29: ifnonnull     36
      32: iconst_1
      33: goto          37
      36: iconst_0
      37: ireturn

  public boolean equals(java.lang.Object);
    Code:
       0: aload_1
       1: instanceof    #5                  // class java_cup/production_part
       4: ifne          9
       7: iconst_0
       8: ireturn
       9: aload_0
      10: aload_1
      11: checkcast     #5                  // class java_cup/production_part
      14: invokevirtual #6                  // Method equals:(Ljava_cup/production_part;)Z
      17: ireturn

  public int hashCode();
    Code:
       0: aload_0
       1: invokevirtual #3                  // Method label:()Ljava/lang/String;
       4: ifnonnull     11
       7: iconst_0
       8: goto          18
      11: aload_0
      12: invokevirtual #3                  // Method label:()Ljava/lang/String;
      15: invokevirtual #7                  // Method java/lang/String.hashCode:()I
      18: ireturn

  public java.lang.String toString();
    Code:
       0: aload_0
       1: invokevirtual #3                  // Method label:()Ljava/lang/String;
       4: ifnull        30
       7: new           #8                  // class java/lang/StringBuffer
      10: dup
      11: invokespecial #9                  // Method java/lang/StringBuffer."<init>":()V
      14: aload_0
      15: invokevirtual #3                  // Method label:()Ljava/lang/String;
      18: invokevirtual #10                 // Method java/lang/StringBuffer.append:(Ljava/lang/String;)Ljava/lang/StringBuffer;
      21: ldc           #11                 // String :
      23: invokevirtual #10                 // Method java/lang/StringBuffer.append:(Ljava/lang/String;)Ljava/lang/StringBuffer;
      26: invokevirtual #12                 // Method java/lang/StringBuffer.toString:()Ljava/lang/String;
      29: areturn
      30: ldc           #13                 // String
      32: areturn
}
