Compiled from "ListFindingsRequest.java"
public interface software.amazon.awssdk.services.inspector2.model.ListFindingsRequest$Builder extends software.amazon.awssdk.services.inspector2.model.Inspector2Request$Builder, software.amazon.awssdk.core.SdkPojo, software.amazon.awssdk.utils.builder.CopyableBuilder<software.amazon.awssdk.services.inspector2.model.ListFindingsRequest$Builder, software.amazon.awssdk.services.inspector2.model.ListFindingsRequest> {
  public abstract software.amazon.awssdk.services.inspector2.model.ListFindingsRequest$Builder filterCriteria(software.amazon.awssdk.services.inspector2.model.FilterCriteria);

  public default software.amazon.awssdk.services.inspector2.model.ListFindingsRequest$Builder filterCriteria(java.util.function.Consumer<software.amazon.awssdk.services.inspector2.model.FilterCriteria$Builder>);
    Code:
       0: aload_0
       1: invokestatic  #1                  // Method software/amazon/awssdk/services/inspector2/model/FilterCriteria.builder:()Lsoftware/amazon/awssdk/services/inspector2/model/FilterCriteria$Builder;
       4: aload_1
       5: invokeinterface #2,  2            // InterfaceMethod software/amazon/awssdk/services/inspector2/model/FilterCriteria$Builder.applyMutation:(Ljava/util/function/Consumer;)Lsoftware/amazon/awssdk/utils/builder/SdkBuilder;
      10: checkcast     #3                  // class software/amazon/awssdk/services/inspector2/model/FilterCriteria$Builder
      13: invokeinterface #4,  1            // InterfaceMethod software/amazon/awssdk/services/inspector2/model/FilterCriteria$Builder.build:()Ljava/lang/Object;
      18: checkcast     #5                  // class software/amazon/awssdk/services/inspector2/model/FilterCriteria
      21: invokeinterface #6,  2            // InterfaceMethod filterCriteria:(Lsoftware/amazon/awssdk/services/inspector2/model/FilterCriteria;)Lsoftware/amazon/awssdk/services/inspector2/model/ListFindingsRequest$Builder;
      26: areturn

  public abstract software.amazon.awssdk.services.inspector2.model.ListFindingsRequest$Builder maxResults(java.lang.Integer);

  public abstract software.amazon.awssdk.services.inspector2.model.ListFindingsRequest$Builder nextToken(java.lang.String);

  public abstract software.amazon.awssdk.services.inspector2.model.ListFindingsRequest$Builder sortCriteria(software.amazon.awssdk.services.inspector2.model.SortCriteria);

  public default software.amazon.awssdk.services.inspector2.model.ListFindingsRequest$Builder sortCriteria(java.util.function.Consumer<software.amazon.awssdk.services.inspector2.model.SortCriteria$Builder>);
    Code:
       0: aload_0
       1: invokestatic  #7                  // Method software/amazon/awssdk/services/inspector2/model/SortCriteria.builder:()Lsoftware/amazon/awssdk/services/inspector2/model/SortCriteria$Builder;
       4: aload_1
       5: invokeinterface #8,  2            // InterfaceMethod software/amazon/awssdk/services/inspector2/model/SortCriteria$Builder.applyMutation:(Ljava/util/function/Consumer;)Lsoftware/amazon/awssdk/utils/builder/SdkBuilder;
      10: checkcast     #9                  // class software/amazon/awssdk/services/inspector2/model/SortCriteria$Builder
      13: invokeinterface #10,  1           // InterfaceMethod software/amazon/awssdk/services/inspector2/model/SortCriteria$Builder.build:()Ljava/lang/Object;
      18: checkcast     #11                 // class software/amazon/awssdk/services/inspector2/model/SortCriteria
      21: invokeinterface #12,  2           // InterfaceMethod sortCriteria:(Lsoftware/amazon/awssdk/services/inspector2/model/SortCriteria;)Lsoftware/amazon/awssdk/services/inspector2/model/ListFindingsRequest$Builder;
      26: areturn

  public abstract software.amazon.awssdk.services.inspector2.model.ListFindingsRequest$Builder overrideConfiguration(software.amazon.awssdk.awscore.AwsRequestOverrideConfiguration);

  public abstract software.amazon.awssdk.services.inspector2.model.ListFindingsRequest$Builder overrideConfiguration(java.util.function.Consumer<software.amazon.awssdk.awscore.AwsRequestOverrideConfiguration$Builder>);

  public default software.amazon.awssdk.awscore.AwsRequest$Builder overrideConfiguration(java.util.function.Consumer);
    Code:
       0: aload_0
       1: aload_1
       2: invokeinterface #13,  2           // InterfaceMethod overrideConfiguration:(Ljava/util/function/Consumer;)Lsoftware/amazon/awssdk/services/inspector2/model/ListFindingsRequest$Builder;
       7: areturn

  public default software.amazon.awssdk.awscore.AwsRequest$Builder overrideConfiguration(software.amazon.awssdk.awscore.AwsRequestOverrideConfiguration);
    Code:
       0: aload_0
       1: aload_1
       2: invokeinterface #14,  2           // InterfaceMethod overrideConfiguration:(Lsoftware/amazon/awssdk/awscore/AwsRequestOverrideConfiguration;)Lsoftware/amazon/awssdk/services/inspector2/model/ListFindingsRequest$Builder;
       7: areturn
}
