Compiled from "PackageFilter.java"
final class software.amazon.awssdk.services.inspector2.model.PackageFilter$BuilderImpl implements software.amazon.awssdk.services.inspector2.model.PackageFilter$Builder {
  private software.amazon.awssdk.services.inspector2.model.StringFilter architecture;

  private software.amazon.awssdk.services.inspector2.model.NumberFilter epoch;

  private software.amazon.awssdk.services.inspector2.model.StringFilter name;

  private software.amazon.awssdk.services.inspector2.model.StringFilter release;

  private software.amazon.awssdk.services.inspector2.model.StringFilter sourceLayerHash;

  private software.amazon.awssdk.services.inspector2.model.StringFilter version;

  private software.amazon.awssdk.services.inspector2.model.PackageFilter$BuilderImpl();
    Code:
       0: aload_0
       1: invokespecial #9                  // Method java/lang/Object."<init>":()V
       4: return

  private software.amazon.awssdk.services.inspector2.model.PackageFilter$BuilderImpl(software.amazon.awssdk.services.inspector2.model.PackageFilter);
    Code:
       0: aload_0
       1: invokespecial #9                  // Method java/lang/Object."<init>":()V
       4: aload_0
       5: aload_1
       6: invokestatic  #10                 // Method software/amazon/awssdk/services/inspector2/model/PackageFilter.access$800:(Lsoftware/amazon/awssdk/services/inspector2/model/PackageFilter;)Lsoftware/amazon/awssdk/services/inspector2/model/StringFilter;
       9: invokevirtual #11                 // Method architecture:(Lsoftware/amazon/awssdk/services/inspector2/model/StringFilter;)Lsoftware/amazon/awssdk/services/inspector2/model/PackageFilter$Builder;
      12: pop
      13: aload_0
      14: aload_1
      15: invokestatic  #12                 // Method software/amazon/awssdk/services/inspector2/model/PackageFilter.access$900:(Lsoftware/amazon/awssdk/services/inspector2/model/PackageFilter;)Lsoftware/amazon/awssdk/services/inspector2/model/NumberFilter;
      18: invokevirtual #13                 // Method epoch:(Lsoftware/amazon/awssdk/services/inspector2/model/NumberFilter;)Lsoftware/amazon/awssdk/services/inspector2/model/PackageFilter$Builder;
      21: pop
      22: aload_0
      23: aload_1
      24: invokestatic  #14                 // Method software/amazon/awssdk/services/inspector2/model/PackageFilter.access$1000:(Lsoftware/amazon/awssdk/services/inspector2/model/PackageFilter;)Lsoftware/amazon/awssdk/services/inspector2/model/StringFilter;
      27: invokevirtual #15                 // Method name:(Lsoftware/amazon/awssdk/services/inspector2/model/StringFilter;)Lsoftware/amazon/awssdk/services/inspector2/model/PackageFilter$Builder;
      30: pop
      31: aload_0
      32: aload_1
      33: invokestatic  #16                 // Method software/amazon/awssdk/services/inspector2/model/PackageFilter.access$1100:(Lsoftware/amazon/awssdk/services/inspector2/model/PackageFilter;)Lsoftware/amazon/awssdk/services/inspector2/model/StringFilter;
      36: invokevirtual #17                 // Method release:(Lsoftware/amazon/awssdk/services/inspector2/model/StringFilter;)Lsoftware/amazon/awssdk/services/inspector2/model/PackageFilter$Builder;
      39: pop
      40: aload_0
      41: aload_1
      42: invokestatic  #18                 // Method software/amazon/awssdk/services/inspector2/model/PackageFilter.access$1200:(Lsoftware/amazon/awssdk/services/inspector2/model/PackageFilter;)Lsoftware/amazon/awssdk/services/inspector2/model/StringFilter;
      45: invokevirtual #19                 // Method sourceLayerHash:(Lsoftware/amazon/awssdk/services/inspector2/model/StringFilter;)Lsoftware/amazon/awssdk/services/inspector2/model/PackageFilter$Builder;
      48: pop
      49: aload_0
      50: aload_1
      51: invokestatic  #20                 // Method software/amazon/awssdk/services/inspector2/model/PackageFilter.access$1300:(Lsoftware/amazon/awssdk/services/inspector2/model/PackageFilter;)Lsoftware/amazon/awssdk/services/inspector2/model/StringFilter;
      54: invokevirtual #21                 // Method version:(Lsoftware/amazon/awssdk/services/inspector2/model/StringFilter;)Lsoftware/amazon/awssdk/services/inspector2/model/PackageFilter$Builder;
      57: pop
      58: return

  public final software.amazon.awssdk.services.inspector2.model.StringFilter$Builder getArchitecture();
    Code:
       0: aload_0
       1: getfield      #8                  // Field architecture:Lsoftware/amazon/awssdk/services/inspector2/model/StringFilter;
       4: ifnull        17
       7: aload_0
       8: getfield      #8                  // Field architecture:Lsoftware/amazon/awssdk/services/inspector2/model/StringFilter;
      11: invokevirtual #22                 // Method software/amazon/awssdk/services/inspector2/model/StringFilter.toBuilder:()Lsoftware/amazon/awssdk/services/inspector2/model/StringFilter$Builder;
      14: goto          18
      17: aconst_null
      18: areturn

  public final void setArchitecture(software.amazon.awssdk.services.inspector2.model.StringFilter$BuilderImpl);
    Code:
       0: aload_0
       1: aload_1
       2: ifnull        12
       5: aload_1
       6: invokevirtual #23                 // Method software/amazon/awssdk/services/inspector2/model/StringFilter$BuilderImpl.build:()Lsoftware/amazon/awssdk/services/inspector2/model/StringFilter;
       9: goto          13
      12: aconst_null
      13: putfield      #8                  // Field architecture:Lsoftware/amazon/awssdk/services/inspector2/model/StringFilter;
      16: return

  public final software.amazon.awssdk.services.inspector2.model.PackageFilter$Builder architecture(software.amazon.awssdk.services.inspector2.model.StringFilter);
    Code:
       0: aload_0
       1: aload_1
       2: putfield      #8                  // Field architecture:Lsoftware/amazon/awssdk/services/inspector2/model/StringFilter;
       5: aload_0
       6: areturn

  public final software.amazon.awssdk.services.inspector2.model.NumberFilter$Builder getEpoch();
    Code:
       0: aload_0
       1: getfield      #7                  // Field epoch:Lsoftware/amazon/awssdk/services/inspector2/model/NumberFilter;
       4: ifnull        17
       7: aload_0
       8: getfield      #7                  // Field epoch:Lsoftware/amazon/awssdk/services/inspector2/model/NumberFilter;
      11: invokevirtual #24                 // Method software/amazon/awssdk/services/inspector2/model/NumberFilter.toBuilder:()Lsoftware/amazon/awssdk/services/inspector2/model/NumberFilter$Builder;
      14: goto          18
      17: aconst_null
      18: areturn

  public final void setEpoch(software.amazon.awssdk.services.inspector2.model.NumberFilter$BuilderImpl);
    Code:
       0: aload_0
       1: aload_1
       2: ifnull        12
       5: aload_1
       6: invokevirtual #25                 // Method software/amazon/awssdk/services/inspector2/model/NumberFilter$BuilderImpl.build:()Lsoftware/amazon/awssdk/services/inspector2/model/NumberFilter;
       9: goto          13
      12: aconst_null
      13: putfield      #7                  // Field epoch:Lsoftware/amazon/awssdk/services/inspector2/model/NumberFilter;
      16: return

  public final software.amazon.awssdk.services.inspector2.model.PackageFilter$Builder epoch(software.amazon.awssdk.services.inspector2.model.NumberFilter);
    Code:
       0: aload_0
       1: aload_1
       2: putfield      #7                  // Field epoch:Lsoftware/amazon/awssdk/services/inspector2/model/NumberFilter;
       5: aload_0
       6: areturn

  public final software.amazon.awssdk.services.inspector2.model.StringFilter$Builder getName();
    Code:
       0: aload_0
       1: getfield      #6                  // Field name:Lsoftware/amazon/awssdk/services/inspector2/model/StringFilter;
       4: ifnull        17
       7: aload_0
       8: getfield      #6                  // Field name:Lsoftware/amazon/awssdk/services/inspector2/model/StringFilter;
      11: invokevirtual #22                 // Method software/amazon/awssdk/services/inspector2/model/StringFilter.toBuilder:()Lsoftware/amazon/awssdk/services/inspector2/model/StringFilter$Builder;
      14: goto          18
      17: aconst_null
      18: areturn

  public final void setName(software.amazon.awssdk.services.inspector2.model.StringFilter$BuilderImpl);
    Code:
       0: aload_0
       1: aload_1
       2: ifnull        12
       5: aload_1
       6: invokevirtual #23                 // Method software/amazon/awssdk/services/inspector2/model/StringFilter$BuilderImpl.build:()Lsoftware/amazon/awssdk/services/inspector2/model/StringFilter;
       9: goto          13
      12: aconst_null
      13: putfield      #6                  // Field name:Lsoftware/amazon/awssdk/services/inspector2/model/StringFilter;
      16: return

  public final software.amazon.awssdk.services.inspector2.model.PackageFilter$Builder name(software.amazon.awssdk.services.inspector2.model.StringFilter);
    Code:
       0: aload_0
       1: aload_1
       2: putfield      #6                  // Field name:Lsoftware/amazon/awssdk/services/inspector2/model/StringFilter;
       5: aload_0
       6: areturn

  public final software.amazon.awssdk.services.inspector2.model.StringFilter$Builder getRelease();
    Code:
       0: aload_0
       1: getfield      #5                  // Field release:Lsoftware/amazon/awssdk/services/inspector2/model/StringFilter;
       4: ifnull        17
       7: aload_0
       8: getfield      #5                  // Field release:Lsoftware/amazon/awssdk/services/inspector2/model/StringFilter;
      11: invokevirtual #22                 // Method software/amazon/awssdk/services/inspector2/model/StringFilter.toBuilder:()Lsoftware/amazon/awssdk/services/inspector2/model/StringFilter$Builder;
      14: goto          18
      17: aconst_null
      18: areturn

  public final void setRelease(software.amazon.awssdk.services.inspector2.model.StringFilter$BuilderImpl);
    Code:
       0: aload_0
       1: aload_1
       2: ifnull        12
       5: aload_1
       6: invokevirtual #23                 // Method software/amazon/awssdk/services/inspector2/model/StringFilter$BuilderImpl.build:()Lsoftware/amazon/awssdk/services/inspector2/model/StringFilter;
       9: goto          13
      12: aconst_null
      13: putfield      #5                  // Field release:Lsoftware/amazon/awssdk/services/inspector2/model/StringFilter;
      16: return

  public final software.amazon.awssdk.services.inspector2.model.PackageFilter$Builder release(software.amazon.awssdk.services.inspector2.model.StringFilter);
    Code:
       0: aload_0
       1: aload_1
       2: putfield      #5                  // Field release:Lsoftware/amazon/awssdk/services/inspector2/model/StringFilter;
       5: aload_0
       6: areturn

  public final software.amazon.awssdk.services.inspector2.model.StringFilter$Builder getSourceLayerHash();
    Code:
       0: aload_0
       1: getfield      #4                  // Field sourceLayerHash:Lsoftware/amazon/awssdk/services/inspector2/model/StringFilter;
       4: ifnull        17
       7: aload_0
       8: getfield      #4                  // Field sourceLayerHash:Lsoftware/amazon/awssdk/services/inspector2/model/StringFilter;
      11: invokevirtual #22                 // Method software/amazon/awssdk/services/inspector2/model/StringFilter.toBuilder:()Lsoftware/amazon/awssdk/services/inspector2/model/StringFilter$Builder;
      14: goto          18
      17: aconst_null
      18: areturn

  public final void setSourceLayerHash(software.amazon.awssdk.services.inspector2.model.StringFilter$BuilderImpl);
    Code:
       0: aload_0
       1: aload_1
       2: ifnull        12
       5: aload_1
       6: invokevirtual #23                 // Method software/amazon/awssdk/services/inspector2/model/StringFilter$BuilderImpl.build:()Lsoftware/amazon/awssdk/services/inspector2/model/StringFilter;
       9: goto          13
      12: aconst_null
      13: putfield      #4                  // Field sourceLayerHash:Lsoftware/amazon/awssdk/services/inspector2/model/StringFilter;
      16: return

  public final software.amazon.awssdk.services.inspector2.model.PackageFilter$Builder sourceLayerHash(software.amazon.awssdk.services.inspector2.model.StringFilter);
    Code:
       0: aload_0
       1: aload_1
       2: putfield      #4                  // Field sourceLayerHash:Lsoftware/amazon/awssdk/services/inspector2/model/StringFilter;
       5: aload_0
       6: areturn

  public final software.amazon.awssdk.services.inspector2.model.StringFilter$Builder getVersion();
    Code:
       0: aload_0
       1: getfield      #3                  // Field version:Lsoftware/amazon/awssdk/services/inspector2/model/StringFilter;
       4: ifnull        17
       7: aload_0
       8: getfield      #3                  // Field version:Lsoftware/amazon/awssdk/services/inspector2/model/StringFilter;
      11: invokevirtual #22                 // Method software/amazon/awssdk/services/inspector2/model/StringFilter.toBuilder:()Lsoftware/amazon/awssdk/services/inspector2/model/StringFilter$Builder;
      14: goto          18
      17: aconst_null
      18: areturn

  public final void setVersion(software.amazon.awssdk.services.inspector2.model.StringFilter$BuilderImpl);
    Code:
       0: aload_0
       1: aload_1
       2: ifnull        12
       5: aload_1
       6: invokevirtual #23                 // Method software/amazon/awssdk/services/inspector2/model/StringFilter$BuilderImpl.build:()Lsoftware/amazon/awssdk/services/inspector2/model/StringFilter;
       9: goto          13
      12: aconst_null
      13: putfield      #3                  // Field version:Lsoftware/amazon/awssdk/services/inspector2/model/StringFilter;
      16: return

  public final software.amazon.awssdk.services.inspector2.model.PackageFilter$Builder version(software.amazon.awssdk.services.inspector2.model.StringFilter);
    Code:
       0: aload_0
       1: aload_1
       2: putfield      #3                  // Field version:Lsoftware/amazon/awssdk/services/inspector2/model/StringFilter;
       5: aload_0
       6: areturn

  public software.amazon.awssdk.services.inspector2.model.PackageFilter build();
    Code:
       0: new           #26                 // class software/amazon/awssdk/services/inspector2/model/PackageFilter
       3: dup
       4: aload_0
       5: aconst_null
       6: invokespecial #27                 // Method software/amazon/awssdk/services/inspector2/model/PackageFilter."<init>":(Lsoftware/amazon/awssdk/services/inspector2/model/PackageFilter$BuilderImpl;Lsoftware/amazon/awssdk/services/inspector2/model/PackageFilter$1;)V
       9: areturn

  public java.util.List<software.amazon.awssdk.core.SdkField<?>> sdkFields();
    Code:
       0: invokestatic  #28                 // Method software/amazon/awssdk/services/inspector2/model/PackageFilter.access$1500:()Ljava/util/List;
       3: areturn

  public java.lang.Object build();
    Code:
       0: aload_0
       1: invokevirtual #29                 // Method build:()Lsoftware/amazon/awssdk/services/inspector2/model/PackageFilter;
       4: areturn

  static software.amazon.awssdk.services.inspector2.model.StringFilter access$000(software.amazon.awssdk.services.inspector2.model.PackageFilter$BuilderImpl);
    Code:
       0: aload_0
       1: getfield      #8                  // Field architecture:Lsoftware/amazon/awssdk/services/inspector2/model/StringFilter;
       4: areturn

  static software.amazon.awssdk.services.inspector2.model.NumberFilter access$100(software.amazon.awssdk.services.inspector2.model.PackageFilter$BuilderImpl);
    Code:
       0: aload_0
       1: getfield      #7                  // Field epoch:Lsoftware/amazon/awssdk/services/inspector2/model/NumberFilter;
       4: areturn

  static software.amazon.awssdk.services.inspector2.model.StringFilter access$200(software.amazon.awssdk.services.inspector2.model.PackageFilter$BuilderImpl);
    Code:
       0: aload_0
       1: getfield      #6                  // Field name:Lsoftware/amazon/awssdk/services/inspector2/model/StringFilter;
       4: areturn

  static software.amazon.awssdk.services.inspector2.model.StringFilter access$300(software.amazon.awssdk.services.inspector2.model.PackageFilter$BuilderImpl);
    Code:
       0: aload_0
       1: getfield      #5                  // Field release:Lsoftware/amazon/awssdk/services/inspector2/model/StringFilter;
       4: areturn

  static software.amazon.awssdk.services.inspector2.model.StringFilter access$400(software.amazon.awssdk.services.inspector2.model.PackageFilter$BuilderImpl);
    Code:
       0: aload_0
       1: getfield      #4                  // Field sourceLayerHash:Lsoftware/amazon/awssdk/services/inspector2/model/StringFilter;
       4: areturn

  static software.amazon.awssdk.services.inspector2.model.StringFilter access$500(software.amazon.awssdk.services.inspector2.model.PackageFilter$BuilderImpl);
    Code:
       0: aload_0
       1: getfield      #3                  // Field version:Lsoftware/amazon/awssdk/services/inspector2/model/StringFilter;
       4: areturn

  software.amazon.awssdk.services.inspector2.model.PackageFilter$BuilderImpl(software.amazon.awssdk.services.inspector2.model.PackageFilter, software.amazon.awssdk.services.inspector2.model.PackageFilter$1);
    Code:
       0: aload_0
       1: aload_1
       2: invokespecial #2                  // Method "<init>":(Lsoftware/amazon/awssdk/services/inspector2/model/PackageFilter;)V
       5: return

  software.amazon.awssdk.services.inspector2.model.PackageFilter$BuilderImpl(software.amazon.awssdk.services.inspector2.model.PackageFilter$1);
    Code:
       0: aload_0
       1: invokespecial #1                  // Method "<init>":()V
       4: return
}
