Compiled from "UriUtils.java"
public abstract class org.springframework.web.util.UriUtils {
  public org.springframework.web.util.UriUtils();
    Code:
       0: aload_0
       1: invokespecial #1                  // Method java/lang/Object."<init>":()V
       4: return

  public static java.lang.String encodeScheme(java.lang.String, java.lang.String);
    Code:
       0: aload_0
       1: aload_1
       2: getstatic     #2                  // Field org/springframework/web/util/HierarchicalUriComponents$Type.SCHEME:Lorg/springframework/web/util/HierarchicalUriComponents$Type;
       5: invokestatic  #3                  // Method encode:(Ljava/lang/String;Ljava/lang/String;Lorg/springframework/web/util/HierarchicalUriComponents$Type;)Ljava/lang/String;
       8: areturn

  public static java.lang.String encodeScheme(java.lang.String, java.nio.charset.Charset);
    Code:
       0: aload_0
       1: aload_1
       2: getstatic     #2                  // Field org/springframework/web/util/HierarchicalUriComponents$Type.SCHEME:Lorg/springframework/web/util/HierarchicalUriComponents$Type;
       5: invokestatic  #4                  // Method encode:(Ljava/lang/String;Ljava/nio/charset/Charset;Lorg/springframework/web/util/HierarchicalUriComponents$Type;)Ljava/lang/String;
       8: areturn

  public static java.lang.String encodeAuthority(java.lang.String, java.lang.String);
    Code:
       0: aload_0
       1: aload_1
       2: getstatic     #5                  // Field org/springframework/web/util/HierarchicalUriComponents$Type.AUTHORITY:Lorg/springframework/web/util/HierarchicalUriComponents$Type;
       5: invokestatic  #3                  // Method encode:(Ljava/lang/String;Ljava/lang/String;Lorg/springframework/web/util/HierarchicalUriComponents$Type;)Ljava/lang/String;
       8: areturn

  public static java.lang.String encodeAuthority(java.lang.String, java.nio.charset.Charset);
    Code:
       0: aload_0
       1: aload_1
       2: getstatic     #5                  // Field org/springframework/web/util/HierarchicalUriComponents$Type.AUTHORITY:Lorg/springframework/web/util/HierarchicalUriComponents$Type;
       5: invokestatic  #4                  // Method encode:(Ljava/lang/String;Ljava/nio/charset/Charset;Lorg/springframework/web/util/HierarchicalUriComponents$Type;)Ljava/lang/String;
       8: areturn

  public static java.lang.String encodeUserInfo(java.lang.String, java.lang.String);
    Code:
       0: aload_0
       1: aload_1
       2: getstatic     #6                  // Field org/springframework/web/util/HierarchicalUriComponents$Type.USER_INFO:Lorg/springframework/web/util/HierarchicalUriComponents$Type;
       5: invokestatic  #3                  // Method encode:(Ljava/lang/String;Ljava/lang/String;Lorg/springframework/web/util/HierarchicalUriComponents$Type;)Ljava/lang/String;
       8: areturn

  public static java.lang.String encodeUserInfo(java.lang.String, java.nio.charset.Charset);
    Code:
       0: aload_0
       1: aload_1
       2: getstatic     #6                  // Field org/springframework/web/util/HierarchicalUriComponents$Type.USER_INFO:Lorg/springframework/web/util/HierarchicalUriComponents$Type;
       5: invokestatic  #4                  // Method encode:(Ljava/lang/String;Ljava/nio/charset/Charset;Lorg/springframework/web/util/HierarchicalUriComponents$Type;)Ljava/lang/String;
       8: areturn

  public static java.lang.String encodeHost(java.lang.String, java.lang.String);
    Code:
       0: aload_0
       1: aload_1
       2: getstatic     #7                  // Field org/springframework/web/util/HierarchicalUriComponents$Type.HOST_IPV4:Lorg/springframework/web/util/HierarchicalUriComponents$Type;
       5: invokestatic  #3                  // Method encode:(Ljava/lang/String;Ljava/lang/String;Lorg/springframework/web/util/HierarchicalUriComponents$Type;)Ljava/lang/String;
       8: areturn

  public static java.lang.String encodeHost(java.lang.String, java.nio.charset.Charset);
    Code:
       0: aload_0
       1: aload_1
       2: getstatic     #7                  // Field org/springframework/web/util/HierarchicalUriComponents$Type.HOST_IPV4:Lorg/springframework/web/util/HierarchicalUriComponents$Type;
       5: invokestatic  #4                  // Method encode:(Ljava/lang/String;Ljava/nio/charset/Charset;Lorg/springframework/web/util/HierarchicalUriComponents$Type;)Ljava/lang/String;
       8: areturn

  public static java.lang.String encodePort(java.lang.String, java.lang.String);
    Code:
       0: aload_0
       1: aload_1
       2: getstatic     #8                  // Field org/springframework/web/util/HierarchicalUriComponents$Type.PORT:Lorg/springframework/web/util/HierarchicalUriComponents$Type;
       5: invokestatic  #3                  // Method encode:(Ljava/lang/String;Ljava/lang/String;Lorg/springframework/web/util/HierarchicalUriComponents$Type;)Ljava/lang/String;
       8: areturn

  public static java.lang.String encodePort(java.lang.String, java.nio.charset.Charset);
    Code:
       0: aload_0
       1: aload_1
       2: getstatic     #8                  // Field org/springframework/web/util/HierarchicalUriComponents$Type.PORT:Lorg/springframework/web/util/HierarchicalUriComponents$Type;
       5: invokestatic  #4                  // Method encode:(Ljava/lang/String;Ljava/nio/charset/Charset;Lorg/springframework/web/util/HierarchicalUriComponents$Type;)Ljava/lang/String;
       8: areturn

  public static java.lang.String encodePath(java.lang.String, java.lang.String);
    Code:
       0: aload_0
       1: aload_1
       2: getstatic     #9                  // Field org/springframework/web/util/HierarchicalUriComponents$Type.PATH:Lorg/springframework/web/util/HierarchicalUriComponents$Type;
       5: invokestatic  #3                  // Method encode:(Ljava/lang/String;Ljava/lang/String;Lorg/springframework/web/util/HierarchicalUriComponents$Type;)Ljava/lang/String;
       8: areturn

  public static java.lang.String encodePath(java.lang.String, java.nio.charset.Charset);
    Code:
       0: aload_0
       1: aload_1
       2: getstatic     #9                  // Field org/springframework/web/util/HierarchicalUriComponents$Type.PATH:Lorg/springframework/web/util/HierarchicalUriComponents$Type;
       5: invokestatic  #4                  // Method encode:(Ljava/lang/String;Ljava/nio/charset/Charset;Lorg/springframework/web/util/HierarchicalUriComponents$Type;)Ljava/lang/String;
       8: areturn

  public static java.lang.String encodePathSegment(java.lang.String, java.lang.String);
    Code:
       0: aload_0
       1: aload_1
       2: getstatic     #10                 // Field org/springframework/web/util/HierarchicalUriComponents$Type.PATH_SEGMENT:Lorg/springframework/web/util/HierarchicalUriComponents$Type;
       5: invokestatic  #3                  // Method encode:(Ljava/lang/String;Ljava/lang/String;Lorg/springframework/web/util/HierarchicalUriComponents$Type;)Ljava/lang/String;
       8: areturn

  public static java.lang.String encodePathSegment(java.lang.String, java.nio.charset.Charset);
    Code:
       0: aload_0
       1: aload_1
       2: getstatic     #10                 // Field org/springframework/web/util/HierarchicalUriComponents$Type.PATH_SEGMENT:Lorg/springframework/web/util/HierarchicalUriComponents$Type;
       5: invokestatic  #4                  // Method encode:(Ljava/lang/String;Ljava/nio/charset/Charset;Lorg/springframework/web/util/HierarchicalUriComponents$Type;)Ljava/lang/String;
       8: areturn

  public static java.lang.String encodeQuery(java.lang.String, java.lang.String);
    Code:
       0: aload_0
       1: aload_1
       2: getstatic     #11                 // Field org/springframework/web/util/HierarchicalUriComponents$Type.QUERY:Lorg/springframework/web/util/HierarchicalUriComponents$Type;
       5: invokestatic  #3                  // Method encode:(Ljava/lang/String;Ljava/lang/String;Lorg/springframework/web/util/HierarchicalUriComponents$Type;)Ljava/lang/String;
       8: areturn

  public static java.lang.String encodeQuery(java.lang.String, java.nio.charset.Charset);
    Code:
       0: aload_0
       1: aload_1
       2: getstatic     #11                 // Field org/springframework/web/util/HierarchicalUriComponents$Type.QUERY:Lorg/springframework/web/util/HierarchicalUriComponents$Type;
       5: invokestatic  #4                  // Method encode:(Ljava/lang/String;Ljava/nio/charset/Charset;Lorg/springframework/web/util/HierarchicalUriComponents$Type;)Ljava/lang/String;
       8: areturn

  public static java.lang.String encodeQueryParam(java.lang.String, java.lang.String);
    Code:
       0: aload_0
       1: aload_1
       2: getstatic     #12                 // Field org/springframework/web/util/HierarchicalUriComponents$Type.QUERY_PARAM:Lorg/springframework/web/util/HierarchicalUriComponents$Type;
       5: invokestatic  #3                  // Method encode:(Ljava/lang/String;Ljava/lang/String;Lorg/springframework/web/util/HierarchicalUriComponents$Type;)Ljava/lang/String;
       8: areturn

  public static java.lang.String encodeQueryParam(java.lang.String, java.nio.charset.Charset);
    Code:
       0: aload_0
       1: aload_1
       2: getstatic     #12                 // Field org/springframework/web/util/HierarchicalUriComponents$Type.QUERY_PARAM:Lorg/springframework/web/util/HierarchicalUriComponents$Type;
       5: invokestatic  #4                  // Method encode:(Ljava/lang/String;Ljava/nio/charset/Charset;Lorg/springframework/web/util/HierarchicalUriComponents$Type;)Ljava/lang/String;
       8: areturn

  public static java.lang.String encodeFragment(java.lang.String, java.lang.String);
    Code:
       0: aload_0
       1: aload_1
       2: getstatic     #13                 // Field org/springframework/web/util/HierarchicalUriComponents$Type.FRAGMENT:Lorg/springframework/web/util/HierarchicalUriComponents$Type;
       5: invokestatic  #3                  // Method encode:(Ljava/lang/String;Ljava/lang/String;Lorg/springframework/web/util/HierarchicalUriComponents$Type;)Ljava/lang/String;
       8: areturn

  public static java.lang.String encodeFragment(java.lang.String, java.nio.charset.Charset);
    Code:
       0: aload_0
       1: aload_1
       2: getstatic     #13                 // Field org/springframework/web/util/HierarchicalUriComponents$Type.FRAGMENT:Lorg/springframework/web/util/HierarchicalUriComponents$Type;
       5: invokestatic  #4                  // Method encode:(Ljava/lang/String;Ljava/nio/charset/Charset;Lorg/springframework/web/util/HierarchicalUriComponents$Type;)Ljava/lang/String;
       8: areturn

  public static java.lang.String encode(java.lang.String, java.lang.String);
    Code:
       0: aload_0
       1: aload_1
       2: getstatic     #14                 // Field org/springframework/web/util/HierarchicalUriComponents$Type.URI:Lorg/springframework/web/util/HierarchicalUriComponents$Type;
       5: invokestatic  #3                  // Method encode:(Ljava/lang/String;Ljava/lang/String;Lorg/springframework/web/util/HierarchicalUriComponents$Type;)Ljava/lang/String;
       8: areturn

  public static java.lang.String encode(java.lang.String, java.nio.charset.Charset);
    Code:
       0: aload_0
       1: aload_1
       2: getstatic     #14                 // Field org/springframework/web/util/HierarchicalUriComponents$Type.URI:Lorg/springframework/web/util/HierarchicalUriComponents$Type;
       5: invokestatic  #4                  // Method encode:(Ljava/lang/String;Ljava/nio/charset/Charset;Lorg/springframework/web/util/HierarchicalUriComponents$Type;)Ljava/lang/String;
       8: areturn

  public static java.util.Map<java.lang.String, java.lang.String> encodeUriVariables(java.util.Map<java.lang.String, ?>);
    Code:
       0: new           #15                 // class java/util/LinkedHashMap
       3: dup
       4: aload_0
       5: invokeinterface #16,  1           // InterfaceMethod java/util/Map.size:()I
      10: invokespecial #17                 // Method java/util/LinkedHashMap."<init>":(I)V
      13: astore_1
      14: aload_0
      15: aload_1
      16: invokedynamic #18,  0             // InvokeDynamic #0:accept:(Ljava/util/Map;)Ljava/util/function/BiConsumer;
      21: invokeinterface #19,  2           // InterfaceMethod java/util/Map.forEach:(Ljava/util/function/BiConsumer;)V
      26: aload_1
      27: areturn

  public static java.lang.Object[] encodeUriVariables(java.lang.Object...);
    Code:
       0: aload_0
       1: invokestatic  #20                 // Method java/util/Arrays.stream:([Ljava/lang/Object;)Ljava/util/stream/Stream;
       4: invokedynamic #21,  0             // InvokeDynamic #1:apply:()Ljava/util/function/Function;
       9: invokeinterface #22,  2           // InterfaceMethod java/util/stream/Stream.map:(Ljava/util/function/Function;)Ljava/util/stream/Stream;
      14: invokeinterface #23,  1           // InterfaceMethod java/util/stream/Stream.toArray:()[Ljava/lang/Object;
      19: areturn

  private static java.lang.String encode(java.lang.String, java.lang.String, org.springframework.web.util.HierarchicalUriComponents$Type);
    Code:
       0: aload_0
       1: aload_1
       2: aload_2
       3: invokestatic  #24                 // Method org/springframework/web/util/HierarchicalUriComponents.encodeUriComponent:(Ljava/lang/String;Ljava/lang/String;Lorg/springframework/web/util/HierarchicalUriComponents$Type;)Ljava/lang/String;
       6: areturn

  private static java.lang.String encode(java.lang.String, java.nio.charset.Charset, org.springframework.web.util.HierarchicalUriComponents$Type);
    Code:
       0: aload_0
       1: aload_1
       2: aload_2
       3: invokestatic  #25                 // Method org/springframework/web/util/HierarchicalUriComponents.encodeUriComponent:(Ljava/lang/String;Ljava/nio/charset/Charset;Lorg/springframework/web/util/HierarchicalUriComponents$Type;)Ljava/lang/String;
       6: areturn

  public static java.lang.String decode(java.lang.String, java.lang.String);
    Code:
       0: aload_0
       1: aload_1
       2: invokestatic  #26                 // Method java/nio/charset/Charset.forName:(Ljava/lang/String;)Ljava/nio/charset/Charset;
       5: invokestatic  #27                 // Method org/springframework/util/StringUtils.uriDecode:(Ljava/lang/String;Ljava/nio/charset/Charset;)Ljava/lang/String;
       8: areturn

  public static java.lang.String decode(java.lang.String, java.nio.charset.Charset);
    Code:
       0: aload_0
       1: aload_1
       2: invokestatic  #27                 // Method org/springframework/util/StringUtils.uriDecode:(Ljava/lang/String;Ljava/nio/charset/Charset;)Ljava/lang/String;
       5: areturn

  public static java.lang.String extractFileExtension(java.lang.String);
    Code:
       0: aload_0
       1: bipush        63
       3: invokevirtual #28                 // Method java/lang/String.indexOf:(I)I
       6: istore_1
       7: aload_0
       8: bipush        35
      10: invokevirtual #28                 // Method java/lang/String.indexOf:(I)I
      13: istore_2
      14: iload_2
      15: iconst_m1
      16: if_icmpeq     31
      19: iload_1
      20: iconst_m1
      21: if_icmpeq     29
      24: iload_2
      25: iload_1
      26: if_icmpge     31
      29: iload_2
      30: istore_1
      31: iload_1
      32: iconst_m1
      33: if_icmpne     41
      36: aload_0
      37: invokevirtual #29                 // Method java/lang/String.length:()I
      40: istore_1
      41: aload_0
      42: bipush        47
      44: iload_1
      45: invokevirtual #30                 // Method java/lang/String.lastIndexOf:(II)I
      48: iconst_1
      49: iadd
      50: istore_3
      51: aload_0
      52: bipush        59
      54: iload_3
      55: invokevirtual #31                 // Method java/lang/String.indexOf:(II)I
      58: istore        4
      60: iload         4
      62: iconst_m1
      63: if_icmpeq     77
      66: iload         4
      68: iload_1
      69: if_icmpge     77
      72: iload         4
      74: goto          78
      77: iload_1
      78: istore_1
      79: aload_0
      80: bipush        46
      82: iload_1
      83: invokevirtual #30                 // Method java/lang/String.lastIndexOf:(II)I
      86: istore        5
      88: iload         5
      90: iconst_m1
      91: if_icmpeq     110
      94: iload         5
      96: iload_3
      97: if_icmple     110
     100: aload_0
     101: iload         5
     103: iconst_1
     104: iadd
     105: iload_1
     106: invokevirtual #32                 // Method java/lang/String.substring:(II)Ljava/lang/String;
     109: areturn
     110: aconst_null
     111: areturn

  private static java.lang.String lambda$encodeUriVariables$1(java.lang.Object);
    Code:
       0: aload_0
       1: ifnull        11
       4: aload_0
       5: invokevirtual #33                 // Method java/lang/Object.toString:()Ljava/lang/String;
       8: goto          13
      11: ldc           #34                 // String
      13: astore_1
      14: aload_1
      15: getstatic     #35                 // Field java/nio/charset/StandardCharsets.UTF_8:Ljava/nio/charset/Charset;
      18: invokestatic  #36                 // Method encode:(Ljava/lang/String;Ljava/nio/charset/Charset;)Ljava/lang/String;
      21: areturn

  private static void lambda$encodeUriVariables$0(java.util.Map, java.lang.String, java.lang.Object);
    Code:
       0: aload_2
       1: ifnull        11
       4: aload_2
       5: invokevirtual #33                 // Method java/lang/Object.toString:()Ljava/lang/String;
       8: goto          13
      11: ldc           #34                 // String
      13: astore_3
      14: aload_0
      15: aload_1
      16: aload_3
      17: getstatic     #35                 // Field java/nio/charset/StandardCharsets.UTF_8:Ljava/nio/charset/Charset;
      20: invokestatic  #36                 // Method encode:(Ljava/lang/String;Ljava/nio/charset/Charset;)Ljava/lang/String;
      23: invokeinterface #37,  3           // InterfaceMethod java/util/Map.put:(Ljava/lang/Object;Ljava/lang/Object;)Ljava/lang/Object;
      28: pop
      29: return
}
