Compiled from "CreateResiliencyPolicyRequest.kt"
public final class aws.sdk.kotlin.services.resiliencehub.model.CreateResiliencyPolicyRequest$Builder {
  private java.lang.String clientToken;

  private aws.sdk.kotlin.services.resiliencehub.model.DataLocationConstraint dataLocationConstraint;

  private java.util.Map<java.lang.String, aws.sdk.kotlin.services.resiliencehub.model.FailurePolicy> policy;

  private java.lang.String policyDescription;

  private java.lang.String policyName;

  private java.util.Map<java.lang.String, java.lang.String> tags;

  private aws.sdk.kotlin.services.resiliencehub.model.ResiliencyPolicyTier tier;

  public final java.lang.String getClientToken();
    Code:
       0: aload_0
       1: getfield      #11                 // Field clientToken:Ljava/lang/String;
       4: areturn

  public final void setClientToken(java.lang.String);
    Code:
       0: aload_0
       1: aload_1
       2: putfield      #11                 // Field clientToken:Ljava/lang/String;
       5: return

  public final aws.sdk.kotlin.services.resiliencehub.model.DataLocationConstraint getDataLocationConstraint();
    Code:
       0: aload_0
       1: getfield      #22                 // Field dataLocationConstraint:Laws/sdk/kotlin/services/resiliencehub/model/DataLocationConstraint;
       4: areturn

  public final void setDataLocationConstraint(aws.sdk.kotlin.services.resiliencehub.model.DataLocationConstraint);
    Code:
       0: aload_0
       1: aload_1
       2: putfield      #22                 // Field dataLocationConstraint:Laws/sdk/kotlin/services/resiliencehub/model/DataLocationConstraint;
       5: return

  public final java.util.Map<java.lang.String, aws.sdk.kotlin.services.resiliencehub.model.FailurePolicy> getPolicy();
    Code:
       0: aload_0
       1: getfield      #31                 // Field policy:Ljava/util/Map;
       4: areturn

  public final void setPolicy(java.util.Map<java.lang.String, aws.sdk.kotlin.services.resiliencehub.model.FailurePolicy>);
    Code:
       0: aload_0
       1: aload_1
       2: putfield      #31                 // Field policy:Ljava/util/Map;
       5: return

  public final java.lang.String getPolicyDescription();
    Code:
       0: aload_0
       1: getfield      #38                 // Field policyDescription:Ljava/lang/String;
       4: areturn

  public final void setPolicyDescription(java.lang.String);
    Code:
       0: aload_0
       1: aload_1
       2: putfield      #38                 // Field policyDescription:Ljava/lang/String;
       5: return

  public final java.lang.String getPolicyName();
    Code:
       0: aload_0
       1: getfield      #43                 // Field policyName:Ljava/lang/String;
       4: areturn

  public final void setPolicyName(java.lang.String);
    Code:
       0: aload_0
       1: aload_1
       2: putfield      #43                 // Field policyName:Ljava/lang/String;
       5: return

  public final java.util.Map<java.lang.String, java.lang.String> getTags();
    Code:
       0: aload_0
       1: getfield      #49                 // Field tags:Ljava/util/Map;
       4: areturn

  public final void setTags(java.util.Map<java.lang.String, java.lang.String>);
    Code:
       0: aload_0
       1: aload_1
       2: putfield      #49                 // Field tags:Ljava/util/Map;
       5: return

  public final aws.sdk.kotlin.services.resiliencehub.model.ResiliencyPolicyTier getTier();
    Code:
       0: aload_0
       1: getfield      #57                 // Field tier:Laws/sdk/kotlin/services/resiliencehub/model/ResiliencyPolicyTier;
       4: areturn

  public final void setTier(aws.sdk.kotlin.services.resiliencehub.model.ResiliencyPolicyTier);
    Code:
       0: aload_0
       1: aload_1
       2: putfield      #57                 // Field tier:Laws/sdk/kotlin/services/resiliencehub/model/ResiliencyPolicyTier;
       5: return

  public aws.sdk.kotlin.services.resiliencehub.model.CreateResiliencyPolicyRequest$Builder();
    Code:
       0: aload_0
       1: invokespecial #64                 // Method java/lang/Object."<init>":()V
       4: return

  public aws.sdk.kotlin.services.resiliencehub.model.CreateResiliencyPolicyRequest$Builder(aws.sdk.kotlin.services.resiliencehub.model.CreateResiliencyPolicyRequest);
    Code:
       0: aload_1
       1: ldc           #68                 // String x
       3: invokestatic  #74                 // Method kotlin/jvm/internal/Intrinsics.checkNotNullParameter:(Ljava/lang/Object;Ljava/lang/String;)V
       6: aload_0
       7: invokespecial #75                 // Method "<init>":()V
      10: aload_0
      11: aload_1
      12: invokevirtual #79                 // Method aws/sdk/kotlin/services/resiliencehub/model/CreateResiliencyPolicyRequest.getClientToken:()Ljava/lang/String;
      15: putfield      #11                 // Field clientToken:Ljava/lang/String;
      18: aload_0
      19: aload_1
      20: invokevirtual #81                 // Method aws/sdk/kotlin/services/resiliencehub/model/CreateResiliencyPolicyRequest.getDataLocationConstraint:()Laws/sdk/kotlin/services/resiliencehub/model/DataLocationConstraint;
      23: putfield      #22                 // Field dataLocationConstraint:Laws/sdk/kotlin/services/resiliencehub/model/DataLocationConstraint;
      26: aload_0
      27: aload_1
      28: invokevirtual #83                 // Method aws/sdk/kotlin/services/resiliencehub/model/CreateResiliencyPolicyRequest.getPolicy:()Ljava/util/Map;
      31: putfield      #31                 // Field policy:Ljava/util/Map;
      34: aload_0
      35: aload_1
      36: invokevirtual #85                 // Method aws/sdk/kotlin/services/resiliencehub/model/CreateResiliencyPolicyRequest.getPolicyDescription:()Ljava/lang/String;
      39: putfield      #38                 // Field policyDescription:Ljava/lang/String;
      42: aload_0
      43: aload_1
      44: invokevirtual #87                 // Method aws/sdk/kotlin/services/resiliencehub/model/CreateResiliencyPolicyRequest.getPolicyName:()Ljava/lang/String;
      47: putfield      #43                 // Field policyName:Ljava/lang/String;
      50: aload_0
      51: aload_1
      52: invokevirtual #89                 // Method aws/sdk/kotlin/services/resiliencehub/model/CreateResiliencyPolicyRequest.getTags:()Ljava/util/Map;
      55: putfield      #49                 // Field tags:Ljava/util/Map;
      58: aload_0
      59: aload_1
      60: invokevirtual #91                 // Method aws/sdk/kotlin/services/resiliencehub/model/CreateResiliencyPolicyRequest.getTier:()Laws/sdk/kotlin/services/resiliencehub/model/ResiliencyPolicyTier;
      63: putfield      #57                 // Field tier:Laws/sdk/kotlin/services/resiliencehub/model/ResiliencyPolicyTier;
      66: return

  public final aws.sdk.kotlin.services.resiliencehub.model.CreateResiliencyPolicyRequest build();
    Code:
       0: new           #77                 // class aws/sdk/kotlin/services/resiliencehub/model/CreateResiliencyPolicyRequest
       3: dup
       4: aload_0
       5: aconst_null
       6: invokespecial #97                 // Method aws/sdk/kotlin/services/resiliencehub/model/CreateResiliencyPolicyRequest."<init>":(Laws/sdk/kotlin/services/resiliencehub/model/CreateResiliencyPolicyRequest$Builder;Lkotlin/jvm/internal/DefaultConstructorMarker;)V
       9: areturn
}
