Compiled from "Attachments.java"
class org.apache.axiom.attachments.Attachments$2 implements org.apache.axiom.blob.WritableBlobFactory {
  final org.apache.axiom.attachments.Attachments this$0;

  org.apache.axiom.attachments.Attachments$2(org.apache.axiom.attachments.Attachments);
    Code:
       0: aload_0
       1: aload_1
       2: putfield      #1                  // Field this$0:Lorg/apache/axiom/attachments/Attachments;
       5: aload_0
       6: invokespecial #2                  // Method java/lang/Object."<init>":()V
       9: return

  public org.apache.axiom.blob.WritableBlob createBlob();
    Code:
       0: invokestatic  #3                  // Method org/apache/axiom/blob/Blobs.createMemoryBlob:()Lorg/apache/axiom/blob/MemoryBlob;
       3: areturn
}
