Compiled from "DefaultClientResources.java"
public class io.lettuce.core.resource.DefaultClientResources implements io.lettuce.core.resource.ClientResources {
  protected static final io.netty.util.internal.logging.InternalLogger logger;

  public static final int MIN_IO_THREADS;

  public static final int MIN_COMPUTATION_THREADS;

  public static final int DEFAULT_IO_THREADS;

  public static final int DEFAULT_COMPUTATION_THREADS;

  public static final java.util.function.Supplier<io.lettuce.core.resource.Delay> DEFAULT_RECONNECT_DELAY;

  public static final io.lettuce.core.resource.NettyCustomizer DEFAULT_NETTY_CUSTOMIZER;

  private final boolean sharedEventLoopGroupProvider;

  private final io.lettuce.core.resource.EventLoopGroupProvider eventLoopGroupProvider;

  private final boolean sharedEventExecutor;

  private final io.netty.util.concurrent.EventExecutorGroup eventExecutorGroup;

  private final io.netty.util.Timer timer;

  private final boolean sharedTimer;

  private final io.lettuce.core.event.EventBus eventBus;

  private final io.lettuce.core.metrics.CommandLatencyCollector commandLatencyCollector;

  private final boolean sharedCommandLatencyCollector;

  private final io.lettuce.core.event.EventPublisherOptions commandLatencyPublisherOptions;

  private final io.lettuce.core.event.metrics.MetricEventPublisher metricEventPublisher;

  private final io.lettuce.core.resource.DnsResolver dnsResolver;

  private final java.util.function.Supplier<io.lettuce.core.resource.Delay> reconnectDelay;

  private final io.lettuce.core.resource.NettyCustomizer nettyCustomizer;

  private volatile boolean shutdownCalled;

  protected io.lettuce.core.resource.DefaultClientResources(io.lettuce.core.resource.DefaultClientResources$Builder);
    Code:
       0: aload_0
       1: invokespecial #1                  // Method java/lang/Object."<init>":()V
       4: aload_0
       5: iconst_0
       6: putfield      #2                  // Field shutdownCalled:Z
       9: aload_1
      10: invokestatic  #3                  // Method io/lettuce/core/resource/DefaultClientResources$Builder.access$000:(Lio/lettuce/core/resource/DefaultClientResources$Builder;)Lio/lettuce/core/resource/EventLoopGroupProvider;
      13: ifnonnull     83
      16: aload_1
      17: invokestatic  #4                  // Method io/lettuce/core/resource/DefaultClientResources$Builder.access$100:(Lio/lettuce/core/resource/DefaultClientResources$Builder;)I
      20: istore_2
      21: iload_2
      22: iconst_3
      23: if_icmpge     63
      26: getstatic     #6                  // Field logger:Lio/netty/util/internal/logging/InternalLogger;
      29: ldc           #7                  // String ioThreadPoolSize is less than {} ({}), setting to: {}
      31: iconst_3
      32: anewarray     #8                  // class java/lang/Object
      35: dup
      36: iconst_0
      37: iconst_3
      38: invokestatic  #9                  // Method java/lang/Integer.valueOf:(I)Ljava/lang/Integer;
      41: aastore
      42: dup
      43: iconst_1
      44: iload_2
      45: invokestatic  #9                  // Method java/lang/Integer.valueOf:(I)Ljava/lang/Integer;
      48: aastore
      49: dup
      50: iconst_2
      51: iconst_3
      52: invokestatic  #9                  // Method java/lang/Integer.valueOf:(I)Ljava/lang/Integer;
      55: aastore
      56: invokeinterface #10,  3           // InterfaceMethod io/netty/util/internal/logging/InternalLogger.info:(Ljava/lang/String;[Ljava/lang/Object;)V
      61: iconst_3
      62: istore_2
      63: aload_0
      64: iconst_0
      65: putfield      #11                 // Field sharedEventLoopGroupProvider:Z
      68: aload_0
      69: new           #12                 // class io/lettuce/core/resource/DefaultEventLoopGroupProvider
      72: dup
      73: iload_2
      74: invokespecial #13                 // Method io/lettuce/core/resource/DefaultEventLoopGroupProvider."<init>":(I)V
      77: putfield      #14                 // Field eventLoopGroupProvider:Lio/lettuce/core/resource/EventLoopGroupProvider;
      80: goto          96
      83: aload_0
      84: iconst_1
      85: putfield      #11                 // Field sharedEventLoopGroupProvider:Z
      88: aload_0
      89: aload_1
      90: invokestatic  #3                  // Method io/lettuce/core/resource/DefaultClientResources$Builder.access$000:(Lio/lettuce/core/resource/DefaultClientResources$Builder;)Lio/lettuce/core/resource/EventLoopGroupProvider;
      93: putfield      #14                 // Field eventLoopGroupProvider:Lio/lettuce/core/resource/EventLoopGroupProvider;
      96: aload_1
      97: invokestatic  #15                 // Method io/lettuce/core/resource/DefaultClientResources$Builder.access$200:(Lio/lettuce/core/resource/DefaultClientResources$Builder;)Lio/netty/util/concurrent/EventExecutorGroup;
     100: ifnonnull     168
     103: aload_1
     104: invokestatic  #16                 // Method io/lettuce/core/resource/DefaultClientResources$Builder.access$300:(Lio/lettuce/core/resource/DefaultClientResources$Builder;)I
     107: istore_2
     108: iload_2
     109: iconst_3
     110: if_icmpge     150
     113: getstatic     #6                  // Field logger:Lio/netty/util/internal/logging/InternalLogger;
     116: ldc           #17                 // String computationThreadPoolSize is less than {} ({}), setting to: {}
     118: iconst_3
     119: anewarray     #8                  // class java/lang/Object
     122: dup
     123: iconst_0
     124: iconst_3
     125: invokestatic  #9                  // Method java/lang/Integer.valueOf:(I)Ljava/lang/Integer;
     128: aastore
     129: dup
     130: iconst_1
     131: iload_2
     132: invokestatic  #9                  // Method java/lang/Integer.valueOf:(I)Ljava/lang/Integer;
     135: aastore
     136: dup
     137: iconst_2
     138: iconst_3
     139: invokestatic  #9                  // Method java/lang/Integer.valueOf:(I)Ljava/lang/Integer;
     142: aastore
     143: invokeinterface #10,  3           // InterfaceMethod io/netty/util/internal/logging/InternalLogger.info:(Ljava/lang/String;[Ljava/lang/Object;)V
     148: iconst_3
     149: istore_2
     150: aload_0
     151: ldc           #18                 // class io/netty/util/concurrent/DefaultEventExecutorGroup
     153: iload_2
     154: invokestatic  #19                 // Method io/lettuce/core/resource/DefaultEventLoopGroupProvider.createEventLoopGroup:(Ljava/lang/Class;I)Lio/netty/util/concurrent/EventExecutorGroup;
     157: putfield      #20                 // Field eventExecutorGroup:Lio/netty/util/concurrent/EventExecutorGroup;
     160: aload_0
     161: iconst_0
     162: putfield      #21                 // Field sharedEventExecutor:Z
     165: goto          181
     168: aload_0
     169: iconst_1
     170: putfield      #21                 // Field sharedEventExecutor:Z
     173: aload_0
     174: aload_1
     175: invokestatic  #15                 // Method io/lettuce/core/resource/DefaultClientResources$Builder.access$200:(Lio/lettuce/core/resource/DefaultClientResources$Builder;)Lio/netty/util/concurrent/EventExecutorGroup;
     178: putfield      #20                 // Field eventExecutorGroup:Lio/netty/util/concurrent/EventExecutorGroup;
     181: aload_1
     182: invokestatic  #22                 // Method io/lettuce/core/resource/DefaultClientResources$Builder.access$400:(Lio/lettuce/core/resource/DefaultClientResources$Builder;)Lio/netty/util/Timer;
     185: ifnonnull     216
     188: aload_0
     189: new           #23                 // class io/netty/util/HashedWheelTimer
     192: dup
     193: new           #24                 // class io/netty/util/concurrent/DefaultThreadFactory
     196: dup
     197: ldc           #25                 // String lettuce-timer
     199: invokespecial #26                 // Method io/netty/util/concurrent/DefaultThreadFactory."<init>":(Ljava/lang/String;)V
     202: invokespecial #27                 // Method io/netty/util/HashedWheelTimer."<init>":(Ljava/util/concurrent/ThreadFactory;)V
     205: putfield      #28                 // Field timer:Lio/netty/util/Timer;
     208: aload_0
     209: iconst_0
     210: putfield      #29                 // Field sharedTimer:Z
     213: goto          229
     216: aload_0
     217: aload_1
     218: invokestatic  #22                 // Method io/lettuce/core/resource/DefaultClientResources$Builder.access$400:(Lio/lettuce/core/resource/DefaultClientResources$Builder;)Lio/netty/util/Timer;
     221: putfield      #28                 // Field timer:Lio/netty/util/Timer;
     224: aload_0
     225: iconst_1
     226: putfield      #29                 // Field sharedTimer:Z
     229: aload_1
     230: invokestatic  #30                 // Method io/lettuce/core/resource/DefaultClientResources$Builder.access$500:(Lio/lettuce/core/resource/DefaultClientResources$Builder;)Lio/lettuce/core/event/EventBus;
     233: ifnonnull     257
     236: aload_0
     237: new           #31                 // class io/lettuce/core/event/DefaultEventBus
     240: dup
     241: aload_0
     242: getfield      #20                 // Field eventExecutorGroup:Lio/netty/util/concurrent/EventExecutorGroup;
     245: invokestatic  #32                 // Method reactor/core/scheduler/Schedulers.fromExecutor:(Ljava/util/concurrent/Executor;)Lreactor/core/scheduler/Scheduler;
     248: invokespecial #33                 // Method io/lettuce/core/event/DefaultEventBus."<init>":(Lreactor/core/scheduler/Scheduler;)V
     251: putfield      #34                 // Field eventBus:Lio/lettuce/core/event/EventBus;
     254: goto          265
     257: aload_0
     258: aload_1
     259: invokestatic  #30                 // Method io/lettuce/core/resource/DefaultClientResources$Builder.access$500:(Lio/lettuce/core/resource/DefaultClientResources$Builder;)Lio/lettuce/core/event/EventBus;
     262: putfield      #34                 // Field eventBus:Lio/lettuce/core/event/EventBus;
     265: aload_1
     266: invokestatic  #35                 // Method io/lettuce/core/resource/DefaultClientResources$Builder.access$600:(Lio/lettuce/core/resource/DefaultClientResources$Builder;)Lio/lettuce/core/metrics/CommandLatencyCollector;
     269: ifnonnull     353
     272: invokestatic  #36                 // Method io/lettuce/core/metrics/DefaultCommandLatencyCollector.isAvailable:()Z
     275: ifeq          320
     278: aload_1
     279: invokestatic  #37                 // Method io/lettuce/core/resource/DefaultClientResources$Builder.access$700:(Lio/lettuce/core/resource/DefaultClientResources$Builder;)Lio/lettuce/core/metrics/CommandLatencyCollectorOptions;
     282: ifnull        303
     285: aload_0
     286: new           #38                 // class io/lettuce/core/metrics/DefaultCommandLatencyCollector
     289: dup
     290: aload_1
     291: invokestatic  #37                 // Method io/lettuce/core/resource/DefaultClientResources$Builder.access$700:(Lio/lettuce/core/resource/DefaultClientResources$Builder;)Lio/lettuce/core/metrics/CommandLatencyCollectorOptions;
     294: invokespecial #39                 // Method io/lettuce/core/metrics/DefaultCommandLatencyCollector."<init>":(Lio/lettuce/core/metrics/CommandLatencyCollectorOptions;)V
     297: putfield      #40                 // Field commandLatencyCollector:Lio/lettuce/core/metrics/CommandLatencyCollector;
     300: goto          345
     303: aload_0
     304: new           #38                 // class io/lettuce/core/metrics/DefaultCommandLatencyCollector
     307: dup
     308: invokestatic  #41                 // Method io/lettuce/core/metrics/DefaultCommandLatencyCollectorOptions.create:()Lio/lettuce/core/metrics/DefaultCommandLatencyCollectorOptions;
     311: invokespecial #39                 // Method io/lettuce/core/metrics/DefaultCommandLatencyCollector."<init>":(Lio/lettuce/core/metrics/CommandLatencyCollectorOptions;)V
     314: putfield      #40                 // Field commandLatencyCollector:Lio/lettuce/core/metrics/CommandLatencyCollector;
     317: goto          345
     320: getstatic     #6                  // Field logger:Lio/netty/util/internal/logging/InternalLogger;
     323: ldc           #42                 // String LatencyUtils/HdrUtils are not available, metrics are disabled
     325: invokeinterface #43,  2           // InterfaceMethod io/netty/util/internal/logging/InternalLogger.debug:(Ljava/lang/String;)V
     330: aload_1
     331: invokestatic  #44                 // Method io/lettuce/core/metrics/DefaultCommandLatencyCollectorOptions.disabled:()Lio/lettuce/core/metrics/DefaultCommandLatencyCollectorOptions;
     334: invokestatic  #45                 // Method io/lettuce/core/resource/DefaultClientResources$Builder.access$702:(Lio/lettuce/core/resource/DefaultClientResources$Builder;Lio/lettuce/core/metrics/CommandLatencyCollectorOptions;)Lio/lettuce/core/metrics/CommandLatencyCollectorOptions;
     337: pop
     338: aload_0
     339: invokestatic  #46                 // Method io/lettuce/core/metrics/DefaultCommandLatencyCollector.disabled:()Lio/lettuce/core/metrics/CommandLatencyCollector;
     342: putfield      #40                 // Field commandLatencyCollector:Lio/lettuce/core/metrics/CommandLatencyCollector;
     345: aload_0
     346: iconst_0
     347: putfield      #47                 // Field sharedCommandLatencyCollector:Z
     350: goto          366
     353: aload_0
     354: iconst_1
     355: putfield      #47                 // Field sharedCommandLatencyCollector:Z
     358: aload_0
     359: aload_1
     360: invokestatic  #35                 // Method io/lettuce/core/resource/DefaultClientResources$Builder.access$600:(Lio/lettuce/core/resource/DefaultClientResources$Builder;)Lio/lettuce/core/metrics/CommandLatencyCollector;
     363: putfield      #40                 // Field commandLatencyCollector:Lio/lettuce/core/metrics/CommandLatencyCollector;
     366: aload_0
     367: aload_1
     368: invokestatic  #48                 // Method io/lettuce/core/resource/DefaultClientResources$Builder.access$800:(Lio/lettuce/core/resource/DefaultClientResources$Builder;)Lio/lettuce/core/event/EventPublisherOptions;
     371: putfield      #49                 // Field commandLatencyPublisherOptions:Lio/lettuce/core/event/EventPublisherOptions;
     374: aload_0
     375: getfield      #40                 // Field commandLatencyCollector:Lio/lettuce/core/metrics/CommandLatencyCollector;
     378: invokeinterface #50,  1           // InterfaceMethod io/lettuce/core/metrics/CommandLatencyCollector.isEnabled:()Z
     383: ifeq          423
     386: aload_0
     387: getfield      #49                 // Field commandLatencyPublisherOptions:Lio/lettuce/core/event/EventPublisherOptions;
     390: ifnull        423
     393: aload_0
     394: new           #51                 // class io/lettuce/core/event/metrics/DefaultCommandLatencyEventPublisher
     397: dup
     398: aload_0
     399: getfield      #20                 // Field eventExecutorGroup:Lio/netty/util/concurrent/EventExecutorGroup;
     402: aload_0
     403: getfield      #49                 // Field commandLatencyPublisherOptions:Lio/lettuce/core/event/EventPublisherOptions;
     406: aload_0
     407: getfield      #34                 // Field eventBus:Lio/lettuce/core/event/EventBus;
     410: aload_0
     411: getfield      #40                 // Field commandLatencyCollector:Lio/lettuce/core/metrics/CommandLatencyCollector;
     414: invokespecial #52                 // Method io/lettuce/core/event/metrics/DefaultCommandLatencyEventPublisher."<init>":(Lio/netty/util/concurrent/EventExecutorGroup;Lio/lettuce/core/event/EventPublisherOptions;Lio/lettuce/core/event/EventBus;Lio/lettuce/core/metrics/CommandLatencyCollector;)V
     417: putfield      #53                 // Field metricEventPublisher:Lio/lettuce/core/event/metrics/MetricEventPublisher;
     420: goto          428
     423: aload_0
     424: aconst_null
     425: putfield      #53                 // Field metricEventPublisher:Lio/lettuce/core/event/metrics/MetricEventPublisher;
     428: aload_1
     429: invokestatic  #54                 // Method io/lettuce/core/resource/DefaultClientResources$Builder.access$900:(Lio/lettuce/core/resource/DefaultClientResources$Builder;)Lio/lettuce/core/resource/DnsResolver;
     432: ifnonnull     445
     435: aload_0
     436: getstatic     #55                 // Field io/lettuce/core/resource/DnsResolvers.UNRESOLVED:Lio/lettuce/core/resource/DnsResolvers;
     439: putfield      #56                 // Field dnsResolver:Lio/lettuce/core/resource/DnsResolver;
     442: goto          453
     445: aload_0
     446: aload_1
     447: invokestatic  #54                 // Method io/lettuce/core/resource/DefaultClientResources$Builder.access$900:(Lio/lettuce/core/resource/DefaultClientResources$Builder;)Lio/lettuce/core/resource/DnsResolver;
     450: putfield      #56                 // Field dnsResolver:Lio/lettuce/core/resource/DnsResolver;
     453: aload_0
     454: aload_1
     455: invokestatic  #57                 // Method io/lettuce/core/resource/DefaultClientResources$Builder.access$1000:(Lio/lettuce/core/resource/DefaultClientResources$Builder;)Ljava/util/function/Supplier;
     458: putfield      #58                 // Field reconnectDelay:Ljava/util/function/Supplier;
     461: aload_0
     462: aload_1
     463: invokestatic  #59                 // Method io/lettuce/core/resource/DefaultClientResources$Builder.access$1100:(Lio/lettuce/core/resource/DefaultClientResources$Builder;)Lio/lettuce/core/resource/NettyCustomizer;
     466: putfield      #60                 // Field nettyCustomizer:Lio/lettuce/core/resource/NettyCustomizer;
     469: return

  public static io.lettuce.core.resource.DefaultClientResources$Builder builder();
    Code:
       0: new           #61                 // class io/lettuce/core/resource/DefaultClientResources$Builder
       3: dup
       4: aconst_null
       5: invokespecial #62                 // Method io/lettuce/core/resource/DefaultClientResources$Builder."<init>":(Lio/lettuce/core/resource/DefaultClientResources$1;)V
       8: areturn

  public static io.lettuce.core.resource.DefaultClientResources create();
    Code:
       0: invokestatic  #63                 // Method builder:()Lio/lettuce/core/resource/DefaultClientResources$Builder;
       3: invokevirtual #64                 // Method io/lettuce/core/resource/DefaultClientResources$Builder.build:()Lio/lettuce/core/resource/DefaultClientResources;
       6: areturn

  protected void finalize() throws java.lang.Throwable;
    Code:
       0: aload_0
       1: getfield      #2                  // Field shutdownCalled:Z
       4: ifne          40
       7: getstatic     #6                  // Field logger:Lio/netty/util/internal/logging/InternalLogger;
      10: new           #65                 // class java/lang/StringBuilder
      13: dup
      14: invokespecial #66                 // Method java/lang/StringBuilder."<init>":()V
      17: aload_0
      18: invokevirtual #67                 // Method java/lang/Object.getClass:()Ljava/lang/Class;
      21: invokevirtual #68                 // Method java/lang/Class.getName:()Ljava/lang/String;
      24: invokevirtual #69                 // Method java/lang/StringBuilder.append:(Ljava/lang/String;)Ljava/lang/StringBuilder;
      27: ldc           #70                 // String  was not shut down properly, shutdown() was not called before it\'s garbage-collected. Call shutdown() or shutdown(long,long,TimeUnit)
      29: invokevirtual #69                 // Method java/lang/StringBuilder.append:(Ljava/lang/String;)Ljava/lang/StringBuilder;
      32: invokevirtual #71                 // Method java/lang/StringBuilder.toString:()Ljava/lang/String;
      35: invokeinterface #72,  2           // InterfaceMethod io/netty/util/internal/logging/InternalLogger.warn:(Ljava/lang/String;)V
      40: aload_0
      41: invokespecial #73                 // Method java/lang/Object.finalize:()V
      44: return

  public io.netty.util.concurrent.Future<java.lang.Boolean> shutdown();
    Code:
       0: aload_0
       1: lconst_0
       2: ldc2_w        #74                 // long 2l
       5: getstatic     #76                 // Field java/util/concurrent/TimeUnit.SECONDS:Ljava/util/concurrent/TimeUnit;
       8: invokevirtual #77                 // Method shutdown:(JJLjava/util/concurrent/TimeUnit;)Lio/netty/util/concurrent/Future;
      11: areturn

  public io.netty.util.concurrent.Future<java.lang.Boolean> shutdown(long, long, java.util.concurrent.TimeUnit);
    Code:
       0: aload_0
       1: iconst_1
       2: putfield      #2                  // Field shutdownCalled:Z
       5: new           #78                 // class io/netty/util/concurrent/DefaultPromise
       8: dup
       9: getstatic     #79                 // Field io/netty/util/concurrent/GlobalEventExecutor.INSTANCE:Lio/netty/util/concurrent/GlobalEventExecutor;
      12: invokespecial #80                 // Method io/netty/util/concurrent/DefaultPromise."<init>":(Lio/netty/util/concurrent/EventExecutor;)V
      15: astore        6
      17: new           #78                 // class io/netty/util/concurrent/DefaultPromise
      20: dup
      21: getstatic     #79                 // Field io/netty/util/concurrent/GlobalEventExecutor.INSTANCE:Lio/netty/util/concurrent/GlobalEventExecutor;
      24: invokespecial #80                 // Method io/netty/util/concurrent/DefaultPromise."<init>":(Lio/netty/util/concurrent/EventExecutor;)V
      27: astore        7
      29: new           #81                 // class io/lettuce/core/resource/Futures$PromiseAggregator
      32: dup
      33: aload         6
      35: invokespecial #82                 // Method io/lettuce/core/resource/Futures$PromiseAggregator."<init>":(Lio/netty/util/concurrent/Promise;)V
      38: astore        8
      40: aload         8
      42: iconst_1
      43: invokevirtual #83                 // Method io/lettuce/core/resource/Futures$PromiseAggregator.expectMore:(I)V
      46: aload_0
      47: getfield      #11                 // Field sharedEventLoopGroupProvider:Z
      50: ifne          59
      53: aload         8
      55: iconst_1
      56: invokevirtual #83                 // Method io/lettuce/core/resource/Futures$PromiseAggregator.expectMore:(I)V
      59: aload_0
      60: getfield      #21                 // Field sharedEventExecutor:Z
      63: ifne          72
      66: aload         8
      68: iconst_1
      69: invokevirtual #83                 // Method io/lettuce/core/resource/Futures$PromiseAggregator.expectMore:(I)V
      72: aload         8
      74: invokevirtual #84                 // Method io/lettuce/core/resource/Futures$PromiseAggregator.arm:()V
      77: aload_0
      78: getfield      #53                 // Field metricEventPublisher:Lio/lettuce/core/event/metrics/MetricEventPublisher;
      81: ifnull        93
      84: aload_0
      85: getfield      #53                 // Field metricEventPublisher:Lio/lettuce/core/event/metrics/MetricEventPublisher;
      88: invokeinterface #85,  1           // InterfaceMethod io/lettuce/core/event/metrics/MetricEventPublisher.shutdown:()V
      93: aload_0
      94: getfield      #29                 // Field sharedTimer:Z
      97: ifne          110
     100: aload_0
     101: getfield      #28                 // Field timer:Lio/netty/util/Timer;
     104: invokeinterface #86,  1           // InterfaceMethod io/netty/util/Timer.stop:()Ljava/util/Set;
     109: pop
     110: aload_0
     111: getfield      #11                 // Field sharedEventLoopGroupProvider:Z
     114: ifne          179
     117: aload_0
     118: getfield      #14                 // Field eventLoopGroupProvider:Lio/lettuce/core/resource/EventLoopGroupProvider;
     121: lload_1
     122: lload_3
     123: aload         5
     125: invokeinterface #87,  6           // InterfaceMethod io/lettuce/core/resource/EventLoopGroupProvider.shutdown:(JJLjava/util/concurrent/TimeUnit;)Lio/netty/util/concurrent/Future;
     130: astore        9
     132: aload         9
     134: instanceof    #88                 // class io/netty/util/concurrent/Promise
     137: ifeq          161
     140: aload         8
     142: iconst_1
     143: anewarray     #88                 // class io/netty/util/concurrent/Promise
     146: dup
     147: iconst_0
     148: aload         9
     150: checkcast     #88                 // class io/netty/util/concurrent/Promise
     153: aastore
     154: invokevirtual #89                 // Method io/lettuce/core/resource/Futures$PromiseAggregator.add:([Lio/netty/util/concurrent/Promise;)Lio/lettuce/core/resource/Futures$PromiseAggregator;
     157: pop
     158: goto          179
     161: aload         8
     163: iconst_1
     164: anewarray     #88                 // class io/netty/util/concurrent/Promise
     167: dup
     168: iconst_0
     169: aload         9
     171: invokestatic  #90                 // Method io/lettuce/core/resource/Futures.toBooleanPromise:(Lio/netty/util/concurrent/Future;)Lio/netty/util/concurrent/Promise;
     174: aastore
     175: invokevirtual #89                 // Method io/lettuce/core/resource/Futures$PromiseAggregator.add:([Lio/netty/util/concurrent/Promise;)Lio/lettuce/core/resource/Futures$PromiseAggregator;
     178: pop
     179: aload_0
     180: getfield      #21                 // Field sharedEventExecutor:Z
     183: ifne          219
     186: aload_0
     187: getfield      #20                 // Field eventExecutorGroup:Lio/netty/util/concurrent/EventExecutorGroup;
     190: lload_1
     191: lload_3
     192: aload         5
     194: invokeinterface #91,  6           // InterfaceMethod io/netty/util/concurrent/EventExecutorGroup.shutdownGracefully:(JJLjava/util/concurrent/TimeUnit;)Lio/netty/util/concurrent/Future;
     199: astore        9
     201: aload         8
     203: iconst_1
     204: anewarray     #88                 // class io/netty/util/concurrent/Promise
     207: dup
     208: iconst_0
     209: aload         9
     211: invokestatic  #90                 // Method io/lettuce/core/resource/Futures.toBooleanPromise:(Lio/netty/util/concurrent/Future;)Lio/netty/util/concurrent/Promise;
     214: aastore
     215: invokevirtual #89                 // Method io/lettuce/core/resource/Futures$PromiseAggregator.add:([Lio/netty/util/concurrent/Promise;)Lio/lettuce/core/resource/Futures$PromiseAggregator;
     218: pop
     219: aload_0
     220: getfield      #47                 // Field sharedCommandLatencyCollector:Z
     223: ifne          235
     226: aload_0
     227: getfield      #40                 // Field commandLatencyCollector:Lio/lettuce/core/metrics/CommandLatencyCollector;
     230: invokeinterface #92,  1           // InterfaceMethod io/lettuce/core/metrics/CommandLatencyCollector.shutdown:()V
     235: aload         8
     237: iconst_1
     238: anewarray     #88                 // class io/netty/util/concurrent/Promise
     241: dup
     242: iconst_0
     243: aload         7
     245: aastore
     246: invokevirtual #89                 // Method io/lettuce/core/resource/Futures$PromiseAggregator.add:([Lio/netty/util/concurrent/Promise;)Lio/lettuce/core/resource/Futures$PromiseAggregator;
     249: pop
     250: aload         7
     252: aconst_null
     253: invokevirtual #93                 // Method io/netty/util/concurrent/DefaultPromise.setSuccess:(Ljava/lang/Object;)Lio/netty/util/concurrent/Promise;
     256: pop
     257: aload         6
     259: invokestatic  #90                 // Method io/lettuce/core/resource/Futures.toBooleanPromise:(Lio/netty/util/concurrent/Future;)Lio/netty/util/concurrent/Promise;
     262: areturn

  public io.lettuce.core.resource.EventLoopGroupProvider eventLoopGroupProvider();
    Code:
       0: aload_0
       1: getfield      #14                 // Field eventLoopGroupProvider:Lio/lettuce/core/resource/EventLoopGroupProvider;
       4: areturn

  public io.netty.util.concurrent.EventExecutorGroup eventExecutorGroup();
    Code:
       0: aload_0
       1: getfield      #20                 // Field eventExecutorGroup:Lio/netty/util/concurrent/EventExecutorGroup;
       4: areturn

  public int ioThreadPoolSize();
    Code:
       0: aload_0
       1: getfield      #14                 // Field eventLoopGroupProvider:Lio/lettuce/core/resource/EventLoopGroupProvider;
       4: invokeinterface #94,  1           // InterfaceMethod io/lettuce/core/resource/EventLoopGroupProvider.threadPoolSize:()I
       9: ireturn

  public int computationThreadPoolSize();
    Code:
       0: aload_0
       1: getfield      #20                 // Field eventExecutorGroup:Lio/netty/util/concurrent/EventExecutorGroup;
       4: invokeinterface #95,  1           // InterfaceMethod io/netty/util/concurrent/EventExecutorGroup.iterator:()Ljava/util/Iterator;
       9: invokestatic  #96                 // Method io/lettuce/core/internal/LettuceLists.newList:(Ljava/util/Iterator;)Ljava/util/List;
      12: invokeinterface #97,  1           // InterfaceMethod java/util/List.size:()I
      17: ireturn

  public io.lettuce.core.event.EventBus eventBus();
    Code:
       0: aload_0
       1: getfield      #34                 // Field eventBus:Lio/lettuce/core/event/EventBus;
       4: areturn

  public io.netty.util.Timer timer();
    Code:
       0: aload_0
       1: getfield      #28                 // Field timer:Lio/netty/util/Timer;
       4: areturn

  public io.lettuce.core.metrics.CommandLatencyCollector commandLatencyCollector();
    Code:
       0: aload_0
       1: getfield      #40                 // Field commandLatencyCollector:Lio/lettuce/core/metrics/CommandLatencyCollector;
       4: areturn

  public io.lettuce.core.event.EventPublisherOptions commandLatencyPublisherOptions();
    Code:
       0: aload_0
       1: getfield      #49                 // Field commandLatencyPublisherOptions:Lio/lettuce/core/event/EventPublisherOptions;
       4: areturn

  public io.lettuce.core.resource.DnsResolver dnsResolver();
    Code:
       0: aload_0
       1: getfield      #56                 // Field dnsResolver:Lio/lettuce/core/resource/DnsResolver;
       4: areturn

  public io.lettuce.core.resource.Delay reconnectDelay();
    Code:
       0: aload_0
       1: getfield      #58                 // Field reconnectDelay:Ljava/util/function/Supplier;
       4: invokeinterface #98,  1           // InterfaceMethod java/util/function/Supplier.get:()Ljava/lang/Object;
       9: checkcast     #99                 // class io/lettuce/core/resource/Delay
      12: areturn

  public io.lettuce.core.resource.NettyCustomizer nettyCustomizer();
    Code:
       0: aload_0
       1: getfield      #60                 // Field nettyCustomizer:Lio/lettuce/core/resource/NettyCustomizer;
       4: areturn

  static {};
    Code:
       0: ldc           #5                  // class io/lettuce/core/resource/DefaultClientResources
       2: invokestatic  #100                // Method io/netty/util/internal/logging/InternalLoggerFactory.getInstance:(Ljava/lang/Class;)Lio/netty/util/internal/logging/InternalLogger;
       5: putstatic     #6                  // Field logger:Lio/netty/util/internal/logging/InternalLogger;
       8: invokedynamic #101,  0            // InvokeDynamic #0:get:()Ljava/util/function/Supplier;
      13: putstatic     #102                // Field DEFAULT_RECONNECT_DELAY:Ljava/util/function/Supplier;
      16: getstatic     #103                // Field io/lettuce/core/resource/DefaultNettyCustomizer.INSTANCE:Lio/lettuce/core/resource/DefaultNettyCustomizer;
      19: putstatic     #104                // Field DEFAULT_NETTY_CUSTOMIZER:Lio/lettuce/core/resource/NettyCustomizer;
      22: iconst_1
      23: ldc           #105                // String io.netty.eventLoopThreads
      25: iconst_3
      26: invokestatic  #106                // Method java/lang/Runtime.getRuntime:()Ljava/lang/Runtime;
      29: invokevirtual #107                // Method java/lang/Runtime.availableProcessors:()I
      32: invokestatic  #108                // Method java/lang/Math.max:(II)I
      35: invokestatic  #109                // Method io/netty/util/internal/SystemPropertyUtil.getInt:(Ljava/lang/String;I)I
      38: invokestatic  #108                // Method java/lang/Math.max:(II)I
      41: istore_0
      42: iload_0
      43: putstatic     #110                // Field DEFAULT_IO_THREADS:I
      46: iload_0
      47: putstatic     #111                // Field DEFAULT_COMPUTATION_THREADS:I
      50: getstatic     #6                  // Field logger:Lio/netty/util/internal/logging/InternalLogger;
      53: invokeinterface #112,  1          // InterfaceMethod io/netty/util/internal/logging/InternalLogger.isDebugEnabled:()Z
      58: ifeq          75
      61: getstatic     #6                  // Field logger:Lio/netty/util/internal/logging/InternalLogger;
      64: ldc           #113                // String -Dio.netty.eventLoopThreads: {}
      66: iload_0
      67: invokestatic  #9                  // Method java/lang/Integer.valueOf:(I)Ljava/lang/Integer;
      70: invokeinterface #114,  3          // InterfaceMethod io/netty/util/internal/logging/InternalLogger.debug:(Ljava/lang/String;Ljava/lang/Object;)V
      75: return
}
