Compiled from "DnsResolvers.java"
public abstract class io.lettuce.core.resource.DnsResolvers extends java.lang.Enum<io.lettuce.core.resource.DnsResolvers> implements io.lettuce.core.resource.DnsResolver {
  public static final io.lettuce.core.resource.DnsResolvers JVM_DEFAULT;

  public static final io.lettuce.core.resource.DnsResolvers UNRESOLVED;

  private static final io.lettuce.core.resource.DnsResolvers[] $VALUES;

  public static io.lettuce.core.resource.DnsResolvers[] values();
    Code:
       0: getstatic     #2                  // Field $VALUES:[Lio/lettuce/core/resource/DnsResolvers;
       3: invokevirtual #3                  // Method "[Lio/lettuce/core/resource/DnsResolvers;".clone:()Ljava/lang/Object;
       6: checkcast     #4                  // class "[Lio/lettuce/core/resource/DnsResolvers;"
       9: areturn

  public static io.lettuce.core.resource.DnsResolvers valueOf(java.lang.String);
    Code:
       0: ldc           #5                  // class io/lettuce/core/resource/DnsResolvers
       2: aload_0
       3: invokestatic  #6                  // Method java/lang/Enum.valueOf:(Ljava/lang/Class;Ljava/lang/String;)Ljava/lang/Enum;
       6: checkcast     #5                  // class io/lettuce/core/resource/DnsResolvers
       9: areturn

  private io.lettuce.core.resource.DnsResolvers();
    Code:
       0: aload_0
       1: aload_1
       2: iload_2
       3: invokespecial #7                  // Method java/lang/Enum."<init>":(Ljava/lang/String;I)V
       6: return

  io.lettuce.core.resource.DnsResolvers(java.lang.String, int, io.lettuce.core.resource.DnsResolvers$1);
    Code:
       0: aload_0
       1: aload_1
       2: iload_2
       3: invokespecial #1                  // Method "<init>":(Ljava/lang/String;I)V
       6: return

  static {};
    Code:
       0: new           #8                  // class io/lettuce/core/resource/DnsResolvers$1
       3: dup
       4: ldc           #9                  // String JVM_DEFAULT
       6: iconst_0
       7: invokespecial #10                 // Method io/lettuce/core/resource/DnsResolvers$1."<init>":(Ljava/lang/String;I)V
      10: putstatic     #11                 // Field JVM_DEFAULT:Lio/lettuce/core/resource/DnsResolvers;
      13: new           #12                 // class io/lettuce/core/resource/DnsResolvers$2
      16: dup
      17: ldc           #13                 // String UNRESOLVED
      19: iconst_1
      20: invokespecial #14                 // Method io/lettuce/core/resource/DnsResolvers$2."<init>":(Ljava/lang/String;I)V
      23: putstatic     #15                 // Field UNRESOLVED:Lio/lettuce/core/resource/DnsResolvers;
      26: iconst_2
      27: anewarray     #5                  // class io/lettuce/core/resource/DnsResolvers
      30: dup
      31: iconst_0
      32: getstatic     #11                 // Field JVM_DEFAULT:Lio/lettuce/core/resource/DnsResolvers;
      35: aastore
      36: dup
      37: iconst_1
      38: getstatic     #15                 // Field UNRESOLVED:Lio/lettuce/core/resource/DnsResolvers;
      41: aastore
      42: putstatic     #2                  // Field $VALUES:[Lio/lettuce/core/resource/DnsResolvers;
      45: return
}
