Compiled from "DataFileWriter.java"
class org.apache.avro.file.DataFileWriter$BufferedFileOutputStream extends java.io.BufferedOutputStream {
  private long position;

  final org.apache.avro.file.DataFileWriter this$0;

  public org.apache.avro.file.DataFileWriter$BufferedFileOutputStream(org.apache.avro.file.DataFileWriter, java.io.OutputStream) throws java.io.IOException;
    Code:
       0: aload_0
       1: aload_1
       2: putfield      #2                  // Field this$0:Lorg/apache/avro/file/DataFileWriter;
       5: aload_0
       6: aconst_null
       7: invokespecial #3                  // Method java/io/BufferedOutputStream."<init>":(Ljava/io/OutputStream;)V
      10: aload_0
      11: new           #4                  // class org/apache/avro/file/DataFileWriter$BufferedFileOutputStream$PositionFilter
      14: dup
      15: aload_0
      16: aload_2
      17: invokespecial #5                  // Method org/apache/avro/file/DataFileWriter$BufferedFileOutputStream$PositionFilter."<init>":(Lorg/apache/avro/file/DataFileWriter$BufferedFileOutputStream;Ljava/io/OutputStream;)V
      20: putfield      #6                  // Field out:Ljava/io/OutputStream;
      23: return

  public long tell();
    Code:
       0: aload_0
       1: getfield      #1                  // Field position:J
       4: aload_0
       5: getfield      #7                  // Field count:I
       8: i2l
       9: ladd
      10: lreturn

  static long access$014(org.apache.avro.file.DataFileWriter$BufferedFileOutputStream, long);
    Code:
       0: aload_0
       1: dup
       2: getfield      #1                  // Field position:J
       5: lload_1
       6: ladd
       7: dup2_x1
       8: putfield      #1                  // Field position:J
      11: lreturn
}
