Compiled from "TServer.java"
public abstract class org.apache.thrift.server.TServer$AbstractServerArgs<T extends org.apache.thrift.server.TServer$AbstractServerArgs<T>> {
  final org.apache.thrift.transport.TServerTransport serverTransport;

  org.apache.thrift.TProcessorFactory processorFactory;

  org.apache.thrift.transport.TTransportFactory inputTransportFactory;

  org.apache.thrift.transport.TTransportFactory outputTransportFactory;

  org.apache.thrift.protocol.TProtocolFactory inputProtocolFactory;

  org.apache.thrift.protocol.TProtocolFactory outputProtocolFactory;

  public org.apache.thrift.server.TServer$AbstractServerArgs(org.apache.thrift.transport.TServerTransport);
    Code:
       0: aload_0
       1: invokespecial #1                  // Method java/lang/Object."<init>":()V
       4: aload_0
       5: new           #2                  // class org/apache/thrift/transport/TTransportFactory
       8: dup
       9: invokespecial #3                  // Method org/apache/thrift/transport/TTransportFactory."<init>":()V
      12: putfield      #4                  // Field inputTransportFactory:Lorg/apache/thrift/transport/TTransportFactory;
      15: aload_0
      16: new           #2                  // class org/apache/thrift/transport/TTransportFactory
      19: dup
      20: invokespecial #3                  // Method org/apache/thrift/transport/TTransportFactory."<init>":()V
      23: putfield      #5                  // Field outputTransportFactory:Lorg/apache/thrift/transport/TTransportFactory;
      26: aload_0
      27: new           #6                  // class org/apache/thrift/protocol/TBinaryProtocol$Factory
      30: dup
      31: invokespecial #7                  // Method org/apache/thrift/protocol/TBinaryProtocol$Factory."<init>":()V
      34: putfield      #8                  // Field inputProtocolFactory:Lorg/apache/thrift/protocol/TProtocolFactory;
      37: aload_0
      38: new           #6                  // class org/apache/thrift/protocol/TBinaryProtocol$Factory
      41: dup
      42: invokespecial #7                  // Method org/apache/thrift/protocol/TBinaryProtocol$Factory."<init>":()V
      45: putfield      #9                  // Field outputProtocolFactory:Lorg/apache/thrift/protocol/TProtocolFactory;
      48: aload_0
      49: aload_1
      50: putfield      #10                 // Field serverTransport:Lorg/apache/thrift/transport/TServerTransport;
      53: return

  public T processorFactory(org.apache.thrift.TProcessorFactory);
    Code:
       0: aload_0
       1: aload_1
       2: putfield      #11                 // Field processorFactory:Lorg/apache/thrift/TProcessorFactory;
       5: aload_0
       6: areturn

  public T processor(org.apache.thrift.TProcessor);
    Code:
       0: aload_0
       1: new           #12                 // class org/apache/thrift/TProcessorFactory
       4: dup
       5: aload_1
       6: invokespecial #13                 // Method org/apache/thrift/TProcessorFactory."<init>":(Lorg/apache/thrift/TProcessor;)V
       9: putfield      #11                 // Field processorFactory:Lorg/apache/thrift/TProcessorFactory;
      12: aload_0
      13: areturn

  public T transportFactory(org.apache.thrift.transport.TTransportFactory);
    Code:
       0: aload_0
       1: aload_1
       2: putfield      #4                  // Field inputTransportFactory:Lorg/apache/thrift/transport/TTransportFactory;
       5: aload_0
       6: aload_1
       7: putfield      #5                  // Field outputTransportFactory:Lorg/apache/thrift/transport/TTransportFactory;
      10: aload_0
      11: areturn

  public T inputTransportFactory(org.apache.thrift.transport.TTransportFactory);
    Code:
       0: aload_0
       1: aload_1
       2: putfield      #4                  // Field inputTransportFactory:Lorg/apache/thrift/transport/TTransportFactory;
       5: aload_0
       6: areturn

  public T outputTransportFactory(org.apache.thrift.transport.TTransportFactory);
    Code:
       0: aload_0
       1: aload_1
       2: putfield      #5                  // Field outputTransportFactory:Lorg/apache/thrift/transport/TTransportFactory;
       5: aload_0
       6: areturn

  public T protocolFactory(org.apache.thrift.protocol.TProtocolFactory);
    Code:
       0: aload_0
       1: aload_1
       2: putfield      #8                  // Field inputProtocolFactory:Lorg/apache/thrift/protocol/TProtocolFactory;
       5: aload_0
       6: aload_1
       7: putfield      #9                  // Field outputProtocolFactory:Lorg/apache/thrift/protocol/TProtocolFactory;
      10: aload_0
      11: areturn

  public T inputProtocolFactory(org.apache.thrift.protocol.TProtocolFactory);
    Code:
       0: aload_0
       1: aload_1
       2: putfield      #8                  // Field inputProtocolFactory:Lorg/apache/thrift/protocol/TProtocolFactory;
       5: aload_0
       6: areturn

  public T outputProtocolFactory(org.apache.thrift.protocol.TProtocolFactory);
    Code:
       0: aload_0
       1: aload_1
       2: putfield      #9                  // Field outputProtocolFactory:Lorg/apache/thrift/protocol/TProtocolFactory;
       5: aload_0
       6: areturn
}
