Compiled from "JsonCodec.java"
public final class zipkin2.internal.JsonCodec {
  static final java.nio.charset.Charset UTF_8;

  public zipkin2.internal.JsonCodec();
    Code:
       0: aload_0
       1: invokespecial #22                 // Method java/lang/Object."<init>":()V
       4: return

  public static <T> boolean read(zipkin2.internal.JsonCodec$JsonReaderAdapter<T>, byte[], java.util.Collection<T>);
    Code:
       0: aload_1
       1: arraylength
       2: ifne          7
       5: iconst_0
       6: ireturn
       7: aload_2
       8: aload_0
       9: new           #10                 // class zipkin2/internal/JsonCodec$JsonReader
      12: dup
      13: aload_1
      14: invokespecial #32                 // Method zipkin2/internal/JsonCodec$JsonReader."<init>":([B)V
      17: invokeinterface #36,  2           // InterfaceMethod zipkin2/internal/JsonCodec$JsonReaderAdapter.fromJson:(Lzipkin2/internal/JsonCodec$JsonReader;)Ljava/lang/Object;
      22: invokeinterface #42,  2           // InterfaceMethod java/util/Collection.add:(Ljava/lang/Object;)Z
      27: pop
      28: iconst_1
      29: ireturn
      30: astore_3
      31: aload_0
      32: invokevirtual #46                 // Method java/lang/Object.toString:()Ljava/lang/String;
      35: aload_3
      36: invokestatic  #50                 // Method exceptionReading:(Ljava/lang/String;Ljava/lang/Exception;)Ljava/lang/IllegalArgumentException;
      39: athrow
    Exception table:
       from    to  target type
           7    29    30   Class java/lang/Exception

  public static <T> T readOne(zipkin2.internal.JsonCodec$JsonReaderAdapter<T>, byte[]);
    Code:
       0: new           #66                 // class java/util/ArrayList
       3: dup
       4: iconst_1
       5: invokespecial #69                 // Method java/util/ArrayList."<init>":(I)V
       8: astore_2
       9: aload_0
      10: aload_1
      11: aload_2
      12: invokestatic  #71                 // Method read:(Lzipkin2/internal/JsonCodec$JsonReaderAdapter;[BLjava/util/Collection;)Z
      15: ifne          20
      18: aconst_null
      19: areturn
      20: aload_2
      21: iconst_0
      22: invokeinterface #77,  2           // InterfaceMethod java/util/List.get:(I)Ljava/lang/Object;
      27: areturn

  public static <T> boolean readList(zipkin2.internal.JsonCodec$JsonReaderAdapter<T>, byte[], java.util.Collection<T>);
    Code:
       0: aload_1
       1: arraylength
       2: ifne          7
       5: iconst_0
       6: ireturn
       7: new           #10                 // class zipkin2/internal/JsonCodec$JsonReader
      10: dup
      11: aload_1
      12: invokespecial #32                 // Method zipkin2/internal/JsonCodec$JsonReader."<init>":([B)V
      15: astore_3
      16: aload_3
      17: invokevirtual #83                 // Method zipkin2/internal/JsonCodec$JsonReader.beginArray:()V
      20: aload_3
      21: invokevirtual #87                 // Method zipkin2/internal/JsonCodec$JsonReader.hasNext:()Z
      24: ifne          29
      27: iconst_0
      28: ireturn
      29: aload_3
      30: invokevirtual #87                 // Method zipkin2/internal/JsonCodec$JsonReader.hasNext:()Z
      33: ifeq          53
      36: aload_2
      37: aload_0
      38: aload_3
      39: invokeinterface #36,  2           // InterfaceMethod zipkin2/internal/JsonCodec$JsonReaderAdapter.fromJson:(Lzipkin2/internal/JsonCodec$JsonReader;)Ljava/lang/Object;
      44: invokeinterface #42,  2           // InterfaceMethod java/util/Collection.add:(Ljava/lang/Object;)Z
      49: pop
      50: goto          29
      53: aload_3
      54: invokevirtual #90                 // Method zipkin2/internal/JsonCodec$JsonReader.endArray:()V
      57: iconst_1
      58: ireturn
      59: astore        4
      61: new           #92                 // class java/lang/StringBuilder
      64: dup
      65: invokespecial #93                 // Method java/lang/StringBuilder."<init>":()V
      68: ldc           #95                 // String List<
      70: invokevirtual #99                 // Method java/lang/StringBuilder.append:(Ljava/lang/String;)Ljava/lang/StringBuilder;
      73: aload_0
      74: invokevirtual #102                // Method java/lang/StringBuilder.append:(Ljava/lang/Object;)Ljava/lang/StringBuilder;
      77: ldc           #104                // String >
      79: invokevirtual #99                 // Method java/lang/StringBuilder.append:(Ljava/lang/String;)Ljava/lang/StringBuilder;
      82: invokevirtual #105                // Method java/lang/StringBuilder.toString:()Ljava/lang/String;
      85: aload         4
      87: invokestatic  #50                 // Method exceptionReading:(Ljava/lang/String;Ljava/lang/Exception;)Ljava/lang/IllegalArgumentException;
      90: athrow
    Exception table:
       from    to  target type
          16    28    59   Class java/lang/Exception
          29    58    59   Class java/lang/Exception

  static <T> int sizeInBytes(zipkin2.internal.Buffer$Writer<T>, java.util.List<T>);
    Code:
       0: aload_1
       1: invokeinterface #114,  1          // InterfaceMethod java/util/List.size:()I
       6: istore_2
       7: iconst_2
       8: istore_3
       9: iload_2
      10: iconst_1
      11: if_icmple     20
      14: iload_3
      15: iload_2
      16: iconst_1
      17: isub
      18: iadd
      19: istore_3
      20: iconst_0
      21: istore        4
      23: iload         4
      25: iload_2
      26: if_icmpge     52
      29: iload_3
      30: aload_0
      31: aload_1
      32: iload         4
      34: invokeinterface #77,  2           // InterfaceMethod java/util/List.get:(I)Ljava/lang/Object;
      39: invokeinterface #117,  2          // InterfaceMethod zipkin2/internal/Buffer$Writer.sizeInBytes:(Ljava/lang/Object;)I
      44: iadd
      45: istore_3
      46: iinc          4, 1
      49: goto          23
      52: iload_3
      53: ireturn

  public static <T> byte[] write(zipkin2.internal.Buffer$Writer<T>, T);
    Code:
       0: new           #15                 // class zipkin2/internal/Buffer
       3: dup
       4: aload_0
       5: aload_1
       6: invokeinterface #117,  2          // InterfaceMethod zipkin2/internal/Buffer$Writer.sizeInBytes:(Ljava/lang/Object;)I
      11: invokespecial #130                // Method zipkin2/internal/Buffer."<init>":(I)V
      14: astore_2
      15: aload_0
      16: aload_1
      17: aload_2
      18: invokeinterface #133,  3          // InterfaceMethod zipkin2/internal/Buffer$Writer.write:(Ljava/lang/Object;Lzipkin2/internal/Buffer;)V
      23: goto          179
      26: astore_3
      27: aload_2
      28: invokevirtual #137                // Method zipkin2/internal/Buffer.toByteArray:()[B
      31: astore        4
      33: aload         4
      35: arraylength
      36: istore        5
      38: iconst_0
      39: istore        6
      41: iload         6
      43: aload         4
      45: arraylength
      46: if_icmpge     70
      49: aload         4
      51: iload         6
      53: baload
      54: ifne          64
      57: iload         6
      59: istore        5
      61: goto          70
      64: iinc          6, 1
      67: goto          41
      70: iload         5
      72: aload         4
      74: arraylength
      75: if_icmpne     85
      78: aload         4
      80: astore        6
      82: goto          102
      85: iload         5
      87: newarray       byte
      89: astore        6
      91: aload         4
      93: iconst_0
      94: aload         6
      96: iconst_0
      97: iload         5
      99: invokestatic  #144                // Method java/lang/System.arraycopy:(Ljava/lang/Object;ILjava/lang/Object;II)V
     102: new           #146                // class java/lang/String
     105: dup
     106: aload         6
     108: getstatic     #148                // Field UTF_8:Ljava/nio/charset/Charset;
     111: invokespecial #151                // Method java/lang/String."<init>":([BLjava/nio/charset/Charset;)V
     114: astore        7
     116: ldc           #153                // String Bug found using %s to write %s as json. Wrote %s/%s bytes: %s
     118: iconst_5
     119: anewarray     #4                  // class java/lang/Object
     122: dup
     123: iconst_0
     124: aload_0
     125: invokevirtual #157                // Method java/lang/Object.getClass:()Ljava/lang/Class;
     128: invokevirtual #162                // Method java/lang/Class.getSimpleName:()Ljava/lang/String;
     131: aastore
     132: dup
     133: iconst_1
     134: aload_1
     135: invokevirtual #157                // Method java/lang/Object.getClass:()Ljava/lang/Class;
     138: invokevirtual #162                // Method java/lang/Class.getSimpleName:()Ljava/lang/String;
     141: aastore
     142: dup
     143: iconst_2
     144: iload         5
     146: invokestatic  #168                // Method java/lang/Integer.valueOf:(I)Ljava/lang/Integer;
     149: aastore
     150: dup
     151: iconst_3
     152: aload         4
     154: arraylength
     155: invokestatic  #168                // Method java/lang/Integer.valueOf:(I)Ljava/lang/Integer;
     158: aastore
     159: dup
     160: iconst_4
     161: aload         7
     163: aastore
     164: invokestatic  #172                // Method java/lang/String.format:(Ljava/lang/String;[Ljava/lang/Object;)Ljava/lang/String;
     167: astore        8
     169: invokestatic  #177                // Method zipkin2/internal/Platform.get:()Lzipkin2/internal/Platform;
     172: aload         8
     174: aload_3
     175: invokevirtual #181                // Method zipkin2/internal/Platform.assertionError:(Ljava/lang/String;Ljava/lang/Throwable;)Ljava/lang/AssertionError;
     178: athrow
     179: aload_2
     180: invokevirtual #137                // Method zipkin2/internal/Buffer.toByteArray:()[B
     183: areturn
    Exception table:
       from    to  target type
          15    23    26   Class java/lang/RuntimeException

  public static <T> byte[] writeList(zipkin2.internal.Buffer$Writer<T>, java.util.List<T>);
    Code:
       0: aload_1
       1: invokeinterface #197,  1          // InterfaceMethod java/util/List.isEmpty:()Z
       6: ifeq          23
       9: iconst_2
      10: newarray       byte
      12: dup
      13: iconst_0
      14: bipush        91
      16: bastore
      17: dup
      18: iconst_1
      19: bipush        93
      21: bastore
      22: areturn
      23: new           #15                 // class zipkin2/internal/Buffer
      26: dup
      27: aload_0
      28: aload_1
      29: invokestatic  #199                // Method sizeInBytes:(Lzipkin2/internal/Buffer$Writer;Ljava/util/List;)I
      32: invokespecial #130                // Method zipkin2/internal/Buffer."<init>":(I)V
      35: astore_2
      36: aload_0
      37: aload_1
      38: aload_2
      39: invokestatic  #202                // Method writeList:(Lzipkin2/internal/Buffer$Writer;Ljava/util/List;Lzipkin2/internal/Buffer;)V
      42: aload_2
      43: invokevirtual #137                // Method zipkin2/internal/Buffer.toByteArray:()[B
      46: areturn

  public static <T> int writeList(zipkin2.internal.Buffer$Writer<T>, java.util.List<T>, byte[], int);
    Code:
       0: aload_1
       1: invokeinterface #197,  1          // InterfaceMethod java/util/List.isEmpty:()Z
       6: ifeq          27
       9: aload_2
      10: iload_3
      11: iinc          3, 1
      14: bipush        91
      16: bastore
      17: aload_2
      18: iload_3
      19: iinc          3, 1
      22: bipush        93
      24: bastore
      25: iconst_2
      26: ireturn
      27: iload_3
      28: istore        4
      30: new           #15                 // class zipkin2/internal/Buffer
      33: dup
      34: aload_2
      35: iload_3
      36: invokespecial #208                // Method zipkin2/internal/Buffer."<init>":([BI)V
      39: astore        5
      41: aload_0
      42: aload_1
      43: aload         5
      45: invokestatic  #202                // Method writeList:(Lzipkin2/internal/Buffer$Writer;Ljava/util/List;Lzipkin2/internal/Buffer;)V
      48: aload         5
      50: getfield      #211                // Field zipkin2/internal/Buffer.pos:I
      53: iload         4
      55: isub
      56: ireturn

  public static <T> void writeList(zipkin2.internal.Buffer$Writer<T>, java.util.List<T>, zipkin2.internal.Buffer);
    Code:
       0: aload_2
       1: bipush        91
       3: invokevirtual #217                // Method zipkin2/internal/Buffer.writeByte:(I)Lzipkin2/internal/Buffer;
       6: pop
       7: iconst_0
       8: istore_3
       9: aload_1
      10: invokeinterface #114,  1          // InterfaceMethod java/util/List.size:()I
      15: istore        4
      17: iload_3
      18: iload         4
      20: if_icmpge     56
      23: aload_0
      24: aload_1
      25: iload_3
      26: iinc          3, 1
      29: invokeinterface #77,  2           // InterfaceMethod java/util/List.get:(I)Ljava/lang/Object;
      34: aload_2
      35: invokeinterface #133,  3          // InterfaceMethod zipkin2/internal/Buffer$Writer.write:(Ljava/lang/Object;Lzipkin2/internal/Buffer;)V
      40: iload_3
      41: iload         4
      43: if_icmpge     17
      46: aload_2
      47: bipush        44
      49: invokevirtual #217                // Method zipkin2/internal/Buffer.writeByte:(I)Lzipkin2/internal/Buffer;
      52: pop
      53: goto          17
      56: aload_2
      57: bipush        93
      59: invokevirtual #217                // Method zipkin2/internal/Buffer.writeByte:(I)Lzipkin2/internal/Buffer;
      62: pop
      63: return

  static java.lang.IllegalArgumentException exceptionReading(java.lang.String, java.lang.Exception);
    Code:
       0: aload_1
       1: invokevirtual #220                // Method java/lang/Exception.getMessage:()Ljava/lang/String;
       4: ifnonnull     12
       7: ldc           #222                // String Error
       9: goto          16
      12: aload_1
      13: invokevirtual #220                // Method java/lang/Exception.getMessage:()Ljava/lang/String;
      16: astore_2
      17: aload_2
      18: ldc           #224                // String malformed
      20: invokevirtual #228                // Method java/lang/String.indexOf:(Ljava/lang/String;)I
      23: iconst_m1
      24: if_icmpeq     30
      27: ldc           #230                // String Malformed
      29: astore_2
      30: ldc           #232                // String %s reading %s from json
      32: iconst_2
      33: anewarray     #4                  // class java/lang/Object
      36: dup
      37: iconst_0
      38: aload_2
      39: aastore
      40: dup
      41: iconst_1
      42: aload_0
      43: aastore
      44: invokestatic  #172                // Method java/lang/String.format:(Ljava/lang/String;[Ljava/lang/Object;)Ljava/lang/String;
      47: astore_3
      48: new           #234                // class java/lang/IllegalArgumentException
      51: dup
      52: aload_3
      53: aload_1
      54: invokespecial #237                // Method java/lang/IllegalArgumentException."<init>":(Ljava/lang/String;Ljava/lang/Throwable;)V
      57: athrow

  static {};
    Code:
       0: ldc           #242                // String UTF-8
       2: invokestatic  #248                // Method java/nio/charset/Charset.forName:(Ljava/lang/String;)Ljava/nio/charset/Charset;
       5: putstatic     #148                // Field UTF_8:Ljava/nio/charset/Charset;
       8: return
}
