Compiled from "Platform.java"
final class zipkin2.internal.Platform$Jre8 extends zipkin2.internal.Platform$Jre7 {
  zipkin2.internal.Platform$Jre8();
    Code:
       0: aload_0
       1: invokespecial #13                 // Method zipkin2/internal/Platform$Jre7."<init>":()V
       4: return

  static zipkin2.internal.Platform$Jre8 buildIfSupported();
    Code:
       0: ldc           #21                 // String java.io.UncheckedIOException
       2: invokestatic  #27                 // Method java/lang/Class.forName:(Ljava/lang/String;)Ljava/lang/Class;
       5: pop
       6: new           #2                  // class zipkin2/internal/Platform$Jre8
       9: dup
      10: invokespecial #28                 // Method "<init>":()V
      13: areturn
      14: astore_0
      15: aconst_null
      16: areturn
    Exception table:
       from    to  target type
           0    13    14   Class java/lang/ClassNotFoundException

  public java.lang.RuntimeException uncheckedIOException(java.io.IOException);
    Code:
       0: new           #33                 // class java/io/UncheckedIOException
       3: dup
       4: aload_1
       5: invokespecial #36                 // Method java/io/UncheckedIOException."<init>":(Ljava/io/IOException;)V
       8: areturn
}
