Compiled from "V1SpanWriter.java"
public final class zipkin2.internal.V1SpanWriter implements zipkin2.internal.Buffer$Writer<zipkin2.v1.V1Span> {
  public zipkin2.internal.V1SpanWriter();
    Code:
       0: aload_0
       1: invokespecial #15                 // Method java/lang/Object."<init>":()V
       4: return

  public int sizeInBytes(zipkin2.v1.V1Span);
    Code:
       0: bipush        29
       2: istore_2
       3: aload_1
       4: invokevirtual #25                 // Method zipkin2/v1/V1Span.traceIdHigh:()J
       7: lconst_0
       8: lcmp
       9: ifeq          15
      12: iinc          2, 16
      15: aload_1
      16: invokevirtual #28                 // Method zipkin2/v1/V1Span.parentId:()J
      19: lconst_0
      20: lcmp
      21: ifeq          27
      24: iinc          2, 30
      27: iinc          2, 24
      30: iinc          2, 10
      33: aload_1
      34: invokevirtual #32                 // Method zipkin2/v1/V1Span.name:()Ljava/lang/String;
      37: ifnull        50
      40: iload_2
      41: aload_1
      42: invokevirtual #32                 // Method zipkin2/v1/V1Span.name:()Ljava/lang/String;
      45: invokestatic  #38                 // Method zipkin2/internal/JsonEscaper.jsonEscapedSizeInBytes:(Ljava/lang/String;)I
      48: iadd
      49: istore_2
      50: aload_1
      51: invokevirtual #41                 // Method zipkin2/v1/V1Span.timestamp:()J
      54: lconst_0
      55: lcmp
      56: ifeq          72
      59: iinc          2, 13
      62: iload_2
      63: aload_1
      64: invokevirtual #41                 // Method zipkin2/v1/V1Span.timestamp:()J
      67: invokestatic  #45                 // Method zipkin2/internal/Buffer.asciiSizeInBytes:(J)I
      70: iadd
      71: istore_2
      72: aload_1
      73: invokevirtual #48                 // Method zipkin2/v1/V1Span.duration:()J
      76: lconst_0
      77: lcmp
      78: ifeq          94
      81: iinc          2, 12
      84: iload_2
      85: aload_1
      86: invokevirtual #48                 // Method zipkin2/v1/V1Span.duration:()J
      89: invokestatic  #45                 // Method zipkin2/internal/Buffer.asciiSizeInBytes:(J)I
      92: iadd
      93: istore_2
      94: aload_1
      95: invokevirtual #52                 // Method zipkin2/v1/V1Span.annotations:()Ljava/util/List;
      98: invokeinterface #58,  1           // InterfaceMethod java/util/List.size:()I
     103: istore_3
     104: aconst_null
     105: astore        4
     107: iconst_0
     108: istore        5
     110: iload_3
     111: ifle          227
     114: iinc          2, 17
     117: iload_3
     118: iconst_1
     119: if_icmple     128
     122: iload_2
     123: iload_3
     124: iconst_1
     125: isub
     126: iadd
     127: istore_2
     128: iconst_0
     129: istore        6
     131: iload         6
     133: iload_3
     134: if_icmpge     227
     137: aload_1
     138: invokevirtual #52                 // Method zipkin2/v1/V1Span.annotations:()Ljava/util/List;
     141: iload         6
     143: invokeinterface #64,  2           // InterfaceMethod java/util/List.get:(I)Ljava/lang/Object;
     148: checkcast     #66                 // class zipkin2/v1/V1Annotation
     151: astore        7
     153: aload         7
     155: invokevirtual #70                 // Method zipkin2/v1/V1Annotation.endpoint:()Lzipkin2/Endpoint;
     158: astore        8
     160: aload         8
     162: ifnonnull     171
     165: iconst_0
     166: istore        9
     168: goto          203
     171: aload         8
     173: aload         4
     175: invokevirtual #74                 // Method zipkin2/Endpoint.equals:(Ljava/lang/Object;)Z
     178: ifeq          188
     181: iload         5
     183: istore        9
     185: goto          203
     188: aload         8
     190: astore        4
     192: aload         8
     194: iconst_1
     195: invokestatic  #80                 // Method zipkin2/internal/V2SpanWriter.endpointSizeInBytes:(Lzipkin2/Endpoint;Z)I
     198: dup
     199: istore        5
     201: istore        9
     203: iload_2
     204: aload         7
     206: invokevirtual #81                 // Method zipkin2/v1/V1Annotation.timestamp:()J
     209: aload         7
     211: invokevirtual #84                 // Method zipkin2/v1/V1Annotation.value:()Ljava/lang/String;
     214: iload         9
     216: invokestatic  #88                 // Method zipkin2/internal/V2SpanWriter.annotationSizeInBytes:(JLjava/lang/String;I)I
     219: iadd
     220: istore_2
     221: iinc          6, 1
     224: goto          131
     227: aload_1
     228: invokevirtual #91                 // Method zipkin2/v1/V1Span.binaryAnnotations:()Ljava/util/List;
     231: invokeinterface #58,  1           // InterfaceMethod java/util/List.size:()I
     236: istore        6
     238: iload         6
     240: ifle          378
     243: iinc          2, 23
     246: iload         6
     248: iconst_1
     249: if_icmple     259
     252: iload_2
     253: iload         6
     255: iconst_1
     256: isub
     257: iadd
     258: istore_2
     259: iconst_0
     260: istore        7
     262: iload         7
     264: iload         6
     266: if_icmpge     378
     269: aload_1
     270: invokevirtual #91                 // Method zipkin2/v1/V1Span.binaryAnnotations:()Ljava/util/List;
     273: iload         7
     275: iinc          7, 1
     278: invokeinterface #64,  2           // InterfaceMethod java/util/List.get:(I)Ljava/lang/Object;
     283: checkcast     #93                 // class zipkin2/v1/V1BinaryAnnotation
     286: astore        8
     288: aload         8
     290: invokevirtual #94                 // Method zipkin2/v1/V1BinaryAnnotation.endpoint:()Lzipkin2/Endpoint;
     293: astore        9
     295: aload         9
     297: ifnonnull     306
     300: iconst_0
     301: istore        10
     303: goto          338
     306: aload         9
     308: aload         4
     310: invokevirtual #74                 // Method zipkin2/Endpoint.equals:(Ljava/lang/Object;)Z
     313: ifeq          323
     316: iload         5
     318: istore        10
     320: goto          338
     323: aload         9
     325: astore        4
     327: aload         9
     329: iconst_1
     330: invokestatic  #80                 // Method zipkin2/internal/V2SpanWriter.endpointSizeInBytes:(Lzipkin2/Endpoint;Z)I
     333: dup
     334: istore        5
     336: istore        10
     338: aload         8
     340: invokevirtual #97                 // Method zipkin2/v1/V1BinaryAnnotation.stringValue:()Ljava/lang/String;
     343: ifnull        367
     346: iload_2
     347: aload         8
     349: invokevirtual #100                // Method zipkin2/v1/V1BinaryAnnotation.key:()Ljava/lang/String;
     352: aload         8
     354: invokevirtual #97                 // Method zipkin2/v1/V1BinaryAnnotation.stringValue:()Ljava/lang/String;
     357: iload         10
     359: invokestatic  #104                // Method binaryAnnotationSizeInBytes:(Ljava/lang/String;Ljava/lang/String;I)I
     362: iadd
     363: istore_2
     364: goto          375
     367: iinc          2, 37
     370: iload_2
     371: iload         10
     373: iadd
     374: istore_2
     375: goto          262
     378: getstatic     #110                // Field java/lang/Boolean.TRUE:Ljava/lang/Boolean;
     381: aload_1
     382: invokevirtual #114                // Method zipkin2/v1/V1Span.debug:()Ljava/lang/Boolean;
     385: invokevirtual #115                // Method java/lang/Boolean.equals:(Ljava/lang/Object;)Z
     388: ifeq          394
     391: iinc          2, 13
     394: iinc          2, 1
     397: iload_2
     398: ireturn

  public void write(zipkin2.v1.V1Span, zipkin2.internal.Buffer);
    Code:
       0: aload_2
       1: ldc           #131                // String {\"traceId\":\"
       3: invokevirtual #135                // Method zipkin2/internal/Buffer.writeAscii:(Ljava/lang/String;)Lzipkin2/internal/Buffer;
       6: pop
       7: aload_1
       8: invokevirtual #25                 // Method zipkin2/v1/V1Span.traceIdHigh:()J
      11: lconst_0
      12: lcmp
      13: ifeq          25
      16: aload_2
      17: aload_1
      18: invokevirtual #25                 // Method zipkin2/v1/V1Span.traceIdHigh:()J
      21: invokevirtual #139                // Method zipkin2/internal/Buffer.writeLongHex:(J)Lzipkin2/internal/Buffer;
      24: pop
      25: aload_2
      26: aload_1
      27: invokevirtual #142                // Method zipkin2/v1/V1Span.traceId:()J
      30: invokevirtual #139                // Method zipkin2/internal/Buffer.writeLongHex:(J)Lzipkin2/internal/Buffer;
      33: bipush        34
      35: invokevirtual #146                // Method zipkin2/internal/Buffer.writeByte:(I)Lzipkin2/internal/Buffer;
      38: pop
      39: aload_1
      40: invokevirtual #28                 // Method zipkin2/v1/V1Span.parentId:()J
      43: lconst_0
      44: lcmp
      45: ifeq          67
      48: aload_2
      49: ldc           #148                // String ,\"parentId\":\"
      51: invokevirtual #135                // Method zipkin2/internal/Buffer.writeAscii:(Ljava/lang/String;)Lzipkin2/internal/Buffer;
      54: aload_1
      55: invokevirtual #28                 // Method zipkin2/v1/V1Span.parentId:()J
      58: invokevirtual #139                // Method zipkin2/internal/Buffer.writeLongHex:(J)Lzipkin2/internal/Buffer;
      61: bipush        34
      63: invokevirtual #146                // Method zipkin2/internal/Buffer.writeByte:(I)Lzipkin2/internal/Buffer;
      66: pop
      67: aload_2
      68: ldc           #150                // String ,\"id\":\"
      70: invokevirtual #135                // Method zipkin2/internal/Buffer.writeAscii:(Ljava/lang/String;)Lzipkin2/internal/Buffer;
      73: aload_1
      74: invokevirtual #153                // Method zipkin2/v1/V1Span.id:()J
      77: invokevirtual #139                // Method zipkin2/internal/Buffer.writeLongHex:(J)Lzipkin2/internal/Buffer;
      80: bipush        34
      82: invokevirtual #146                // Method zipkin2/internal/Buffer.writeByte:(I)Lzipkin2/internal/Buffer;
      85: pop
      86: aload_2
      87: ldc           #155                // String ,\"name\":\"
      89: invokevirtual #135                // Method zipkin2/internal/Buffer.writeAscii:(Ljava/lang/String;)Lzipkin2/internal/Buffer;
      92: pop
      93: aload_1
      94: invokevirtual #32                 // Method zipkin2/v1/V1Span.name:()Ljava/lang/String;
      97: ifnull        112
     100: aload_2
     101: aload_1
     102: invokevirtual #32                 // Method zipkin2/v1/V1Span.name:()Ljava/lang/String;
     105: invokestatic  #159                // Method zipkin2/internal/JsonEscaper.jsonEscape:(Ljava/lang/String;)Ljava/lang/String;
     108: invokevirtual #162                // Method zipkin2/internal/Buffer.writeUtf8:(Ljava/lang/String;)Lzipkin2/internal/Buffer;
     111: pop
     112: aload_2
     113: bipush        34
     115: invokevirtual #146                // Method zipkin2/internal/Buffer.writeByte:(I)Lzipkin2/internal/Buffer;
     118: pop
     119: aload_1
     120: invokevirtual #41                 // Method zipkin2/v1/V1Span.timestamp:()J
     123: lconst_0
     124: lcmp
     125: ifeq          142
     128: aload_2
     129: ldc           #164                // String ,\"timestamp\":
     131: invokevirtual #135                // Method zipkin2/internal/Buffer.writeAscii:(Ljava/lang/String;)Lzipkin2/internal/Buffer;
     134: aload_1
     135: invokevirtual #41                 // Method zipkin2/v1/V1Span.timestamp:()J
     138: invokevirtual #166                // Method zipkin2/internal/Buffer.writeAscii:(J)Lzipkin2/internal/Buffer;
     141: pop
     142: aload_1
     143: invokevirtual #48                 // Method zipkin2/v1/V1Span.duration:()J
     146: lconst_0
     147: lcmp
     148: ifeq          165
     151: aload_2
     152: ldc           #168                // String ,\"duration\":
     154: invokevirtual #135                // Method zipkin2/internal/Buffer.writeAscii:(Ljava/lang/String;)Lzipkin2/internal/Buffer;
     157: aload_1
     158: invokevirtual #48                 // Method zipkin2/v1/V1Span.duration:()J
     161: invokevirtual #166                // Method zipkin2/internal/Buffer.writeAscii:(J)Lzipkin2/internal/Buffer;
     164: pop
     165: aload_1
     166: invokevirtual #52                 // Method zipkin2/v1/V1Span.annotations:()Ljava/util/List;
     169: invokeinterface #58,  1           // InterfaceMethod java/util/List.size:()I
     174: istore_3
     175: aconst_null
     176: astore        4
     178: aconst_null
     179: astore        5
     181: iload_3
     182: ifle          308
     185: aload_2
     186: ldc           #170                // String ,\"annotations\":[
     188: invokevirtual #135                // Method zipkin2/internal/Buffer.writeAscii:(Ljava/lang/String;)Lzipkin2/internal/Buffer;
     191: pop
     192: iconst_0
     193: istore        6
     195: iload         6
     197: iload_3
     198: if_icmpge     301
     201: aload_1
     202: invokevirtual #52                 // Method zipkin2/v1/V1Span.annotations:()Ljava/util/List;
     205: iload         6
     207: iinc          6, 1
     210: invokeinterface #64,  2           // InterfaceMethod java/util/List.get:(I)Ljava/lang/Object;
     215: checkcast     #66                 // class zipkin2/v1/V1Annotation
     218: astore        7
     220: aload         7
     222: invokevirtual #70                 // Method zipkin2/v1/V1Annotation.endpoint:()Lzipkin2/Endpoint;
     225: astore        8
     227: aload         8
     229: ifnonnull     238
     232: aconst_null
     233: astore        9
     235: goto          269
     238: aload         8
     240: aload         4
     242: invokevirtual #74                 // Method zipkin2/Endpoint.equals:(Ljava/lang/Object;)Z
     245: ifeq          255
     248: aload         5
     250: astore        9
     252: goto          269
     255: aload         8
     257: astore        4
     259: aload         8
     261: invokestatic  #176                // Method legacyEndpointBytes:(Lzipkin2/Endpoint;)[B
     264: dup
     265: astore        5
     267: astore        9
     269: aload         7
     271: invokevirtual #81                 // Method zipkin2/v1/V1Annotation.timestamp:()J
     274: aload         7
     276: invokevirtual #84                 // Method zipkin2/v1/V1Annotation.value:()Ljava/lang/String;
     279: aload         9
     281: aload_2
     282: invokestatic  #180                // Method zipkin2/internal/V2SpanWriter.writeAnnotation:(JLjava/lang/String;[BLzipkin2/internal/Buffer;)V
     285: iload         6
     287: iload_3
     288: if_icmpge     298
     291: aload_2
     292: bipush        44
     294: invokevirtual #146                // Method zipkin2/internal/Buffer.writeByte:(I)Lzipkin2/internal/Buffer;
     297: pop
     298: goto          195
     301: aload_2
     302: bipush        93
     304: invokevirtual #146                // Method zipkin2/internal/Buffer.writeByte:(I)Lzipkin2/internal/Buffer;
     307: pop
     308: aload_1
     309: invokevirtual #91                 // Method zipkin2/v1/V1Span.binaryAnnotations:()Ljava/util/List;
     312: invokeinterface #58,  1           // InterfaceMethod java/util/List.size:()I
     317: istore        6
     319: iload         6
     321: ifle          496
     324: aload_2
     325: ldc           #182                // String ,\"binaryAnnotations\":[
     327: invokevirtual #135                // Method zipkin2/internal/Buffer.writeAscii:(Ljava/lang/String;)Lzipkin2/internal/Buffer;
     330: pop
     331: iconst_0
     332: istore        7
     334: iload         7
     336: iload         6
     338: if_icmpge     489
     341: aload_1
     342: invokevirtual #91                 // Method zipkin2/v1/V1Span.binaryAnnotations:()Ljava/util/List;
     345: iload         7
     347: iinc          7, 1
     350: invokeinterface #64,  2           // InterfaceMethod java/util/List.get:(I)Ljava/lang/Object;
     355: checkcast     #93                 // class zipkin2/v1/V1BinaryAnnotation
     358: astore        8
     360: aload         8
     362: invokevirtual #94                 // Method zipkin2/v1/V1BinaryAnnotation.endpoint:()Lzipkin2/Endpoint;
     365: astore        9
     367: aload         9
     369: ifnonnull     378
     372: aconst_null
     373: astore        10
     375: goto          409
     378: aload         9
     380: aload         4
     382: invokevirtual #74                 // Method zipkin2/Endpoint.equals:(Ljava/lang/Object;)Z
     385: ifeq          395
     388: aload         5
     390: astore        10
     392: goto          409
     395: aload         9
     397: astore        4
     399: aload         9
     401: invokestatic  #176                // Method legacyEndpointBytes:(Lzipkin2/Endpoint;)[B
     404: dup
     405: astore        5
     407: astore        10
     409: aload         8
     411: invokevirtual #97                 // Method zipkin2/v1/V1BinaryAnnotation.stringValue:()Ljava/lang/String;
     414: ifnull        436
     417: aload         8
     419: invokevirtual #100                // Method zipkin2/v1/V1BinaryAnnotation.key:()Ljava/lang/String;
     422: aload         8
     424: invokevirtual #97                 // Method zipkin2/v1/V1BinaryAnnotation.stringValue:()Ljava/lang/String;
     427: aload         10
     429: aload_2
     430: invokestatic  #186                // Method writeBinaryAnnotation:(Ljava/lang/String;Ljava/lang/String;[BLzipkin2/internal/Buffer;)V
     433: goto          472
     436: aload_2
     437: ldc           #188                // String {\"key\":\"
     439: invokevirtual #135                // Method zipkin2/internal/Buffer.writeAscii:(Ljava/lang/String;)Lzipkin2/internal/Buffer;
     442: aload         8
     444: invokevirtual #100                // Method zipkin2/v1/V1BinaryAnnotation.key:()Ljava/lang/String;
     447: invokevirtual #135                // Method zipkin2/internal/Buffer.writeAscii:(Ljava/lang/String;)Lzipkin2/internal/Buffer;
     450: pop
     451: aload_2
     452: ldc           #190                // String \",\"value\":true,\"endpoint\":
     454: invokevirtual #135                // Method zipkin2/internal/Buffer.writeAscii:(Ljava/lang/String;)Lzipkin2/internal/Buffer;
     457: pop
     458: aload_2
     459: aload         10
     461: invokevirtual #193                // Method zipkin2/internal/Buffer.write:([B)Lzipkin2/internal/Buffer;
     464: pop
     465: aload_2
     466: bipush        125
     468: invokevirtual #146                // Method zipkin2/internal/Buffer.writeByte:(I)Lzipkin2/internal/Buffer;
     471: pop
     472: iload         7
     474: iload         6
     476: if_icmpge     486
     479: aload_2
     480: bipush        44
     482: invokevirtual #146                // Method zipkin2/internal/Buffer.writeByte:(I)Lzipkin2/internal/Buffer;
     485: pop
     486: goto          334
     489: aload_2
     490: bipush        93
     492: invokevirtual #146                // Method zipkin2/internal/Buffer.writeByte:(I)Lzipkin2/internal/Buffer;
     495: pop
     496: getstatic     #110                // Field java/lang/Boolean.TRUE:Ljava/lang/Boolean;
     499: aload_1
     500: invokevirtual #114                // Method zipkin2/v1/V1Span.debug:()Ljava/lang/Boolean;
     503: invokevirtual #115                // Method java/lang/Boolean.equals:(Ljava/lang/Object;)Z
     506: ifeq          516
     509: aload_2
     510: ldc           #195                // String ,\"debug\":true
     512: invokevirtual #135                // Method zipkin2/internal/Buffer.writeAscii:(Ljava/lang/String;)Lzipkin2/internal/Buffer;
     515: pop
     516: aload_2
     517: bipush        125
     519: invokevirtual #146                // Method zipkin2/internal/Buffer.writeByte:(I)Lzipkin2/internal/Buffer;
     522: pop
     523: return

  public java.lang.String toString();
    Code:
       0: ldc           #202                // String Span
       2: areturn

  static byte[] legacyEndpointBytes(zipkin2.Endpoint);
    Code:
       0: aload_0
       1: ifnonnull     6
       4: aconst_null
       5: areturn
       6: new           #10                 // class zipkin2/internal/Buffer
       9: dup
      10: aload_0
      11: iconst_1
      12: invokestatic  #80                 // Method zipkin2/internal/V2SpanWriter.endpointSizeInBytes:(Lzipkin2/Endpoint;Z)I
      15: invokespecial #206                // Method zipkin2/internal/Buffer."<init>":(I)V
      18: astore_1
      19: aload_0
      20: aload_1
      21: iconst_1
      22: invokestatic  #210                // Method zipkin2/internal/V2SpanWriter.writeEndpoint:(Lzipkin2/Endpoint;Lzipkin2/internal/Buffer;Z)V
      25: aload_1
      26: invokevirtual #214                // Method zipkin2/internal/Buffer.toByteArray:()[B
      29: areturn

  static int binaryAnnotationSizeInBytes(java.lang.String, java.lang.String, int);
    Code:
       0: bipush        21
       2: istore_3
       3: iload_3
       4: aload_0
       5: invokestatic  #38                 // Method zipkin2/internal/JsonEscaper.jsonEscapedSizeInBytes:(Ljava/lang/String;)I
       8: iadd
       9: istore_3
      10: iload_3
      11: aload_1
      12: invokestatic  #38                 // Method zipkin2/internal/JsonEscaper.jsonEscapedSizeInBytes:(Ljava/lang/String;)I
      15: iadd
      16: istore_3
      17: iload_2
      18: ifeq          28
      21: iinc          3, 12
      24: iload_3
      25: iload_2
      26: iadd
      27: istore_3
      28: iload_3
      29: ireturn

  static void writeBinaryAnnotation(java.lang.String, java.lang.String, byte[], zipkin2.internal.Buffer);
    Code:
       0: aload_3
       1: ldc           #188                // String {\"key\":\"
       3: invokevirtual #135                // Method zipkin2/internal/Buffer.writeAscii:(Ljava/lang/String;)Lzipkin2/internal/Buffer;
       6: aload_0
       7: invokestatic  #159                // Method zipkin2/internal/JsonEscaper.jsonEscape:(Ljava/lang/String;)Ljava/lang/String;
      10: invokevirtual #162                // Method zipkin2/internal/Buffer.writeUtf8:(Ljava/lang/String;)Lzipkin2/internal/Buffer;
      13: pop
      14: aload_3
      15: ldc           #219                // String \",\"value\":\"
      17: invokevirtual #135                // Method zipkin2/internal/Buffer.writeAscii:(Ljava/lang/String;)Lzipkin2/internal/Buffer;
      20: aload_1
      21: invokestatic  #159                // Method zipkin2/internal/JsonEscaper.jsonEscape:(Ljava/lang/String;)Ljava/lang/String;
      24: invokevirtual #162                // Method zipkin2/internal/Buffer.writeUtf8:(Ljava/lang/String;)Lzipkin2/internal/Buffer;
      27: bipush        34
      29: invokevirtual #146                // Method zipkin2/internal/Buffer.writeByte:(I)Lzipkin2/internal/Buffer;
      32: pop
      33: aload_2
      34: ifnull        48
      37: aload_3
      38: ldc           #221                // String ,\"endpoint\":
      40: invokevirtual #135                // Method zipkin2/internal/Buffer.writeAscii:(Ljava/lang/String;)Lzipkin2/internal/Buffer;
      43: aload_2
      44: invokevirtual #193                // Method zipkin2/internal/Buffer.write:([B)Lzipkin2/internal/Buffer;
      47: pop
      48: aload_3
      49: ldc           #223                // String }
      51: invokevirtual #135                // Method zipkin2/internal/Buffer.writeAscii:(Ljava/lang/String;)Lzipkin2/internal/Buffer;
      54: pop
      55: return

  public void write(java.lang.Object, zipkin2.internal.Buffer);
    Code:
       0: aload_0
       1: aload_1
       2: checkcast     #21                 // class zipkin2/v1/V1Span
       5: aload_2
       6: invokevirtual #226                // Method write:(Lzipkin2/v1/V1Span;Lzipkin2/internal/Buffer;)V
       9: return

  public int sizeInBytes(java.lang.Object);
    Code:
       0: aload_0
       1: aload_1
       2: checkcast     #21                 // class zipkin2/v1/V1Span
       5: invokevirtual #229                // Method sizeInBytes:(Lzipkin2/v1/V1Span;)I
       8: ireturn
}
