Compiled from "Buffer.java"
abstract class org.springframework.boot.actuate.metrics.buffer.Buffer<T extends java.lang.Number> {
  private volatile long timestamp;

  org.springframework.boot.actuate.metrics.buffer.Buffer(long);
    Code:
       0: aload_0
       1: invokespecial #1                  // Method java/lang/Object."<init>":()V
       4: aload_0
       5: lload_1
       6: putfield      #2                  // Field timestamp:J
       9: return

  public long getTimestamp();
    Code:
       0: aload_0
       1: getfield      #2                  // Field timestamp:J
       4: lreturn

  public void setTimestamp(long);
    Code:
       0: aload_0
       1: lload_1
       2: putfield      #2                  // Field timestamp:J
       5: return

  public abstract T getValue();
}
