Compiled from "DescriptorProtos.java"
public final class com.google.protobuf.DescriptorProtos$FileDescriptorProto extends com.google.protobuf.GeneratedMessageV3 implements com.google.protobuf.DescriptorProtos$FileDescriptorProtoOrBuilder {
  private static final long serialVersionUID;

  private int bitField0_;

  public static final int NAME_FIELD_NUMBER;

  private volatile java.lang.Object name_;

  public static final int PACKAGE_FIELD_NUMBER;

  private volatile java.lang.Object package_;

  public static final int DEPENDENCY_FIELD_NUMBER;

  private com.google.protobuf.LazyStringList dependency_;

  public static final int PUBLIC_DEPENDENCY_FIELD_NUMBER;

  private java.util.List<java.lang.Integer> publicDependency_;

  public static final int WEAK_DEPENDENCY_FIELD_NUMBER;

  private java.util.List<java.lang.Integer> weakDependency_;

  public static final int MESSAGE_TYPE_FIELD_NUMBER;

  private java.util.List<com.google.protobuf.DescriptorProtos$DescriptorProto> messageType_;

  public static final int ENUM_TYPE_FIELD_NUMBER;

  private java.util.List<com.google.protobuf.DescriptorProtos$EnumDescriptorProto> enumType_;

  public static final int SERVICE_FIELD_NUMBER;

  private java.util.List<com.google.protobuf.DescriptorProtos$ServiceDescriptorProto> service_;

  public static final int EXTENSION_FIELD_NUMBER;

  private java.util.List<com.google.protobuf.DescriptorProtos$FieldDescriptorProto> extension_;

  public static final int OPTIONS_FIELD_NUMBER;

  private com.google.protobuf.DescriptorProtos$FileOptions options_;

  public static final int SOURCE_CODE_INFO_FIELD_NUMBER;

  private com.google.protobuf.DescriptorProtos$SourceCodeInfo sourceCodeInfo_;

  public static final int SYNTAX_FIELD_NUMBER;

  private volatile java.lang.Object syntax_;

  private byte memoizedIsInitialized;

  private static final com.google.protobuf.DescriptorProtos$FileDescriptorProto DEFAULT_INSTANCE;

  public static final com.google.protobuf.Parser<com.google.protobuf.DescriptorProtos$FileDescriptorProto> PARSER;

  private com.google.protobuf.DescriptorProtos$FileDescriptorProto(com.google.protobuf.GeneratedMessageV3$Builder<?>);
    Code:
       0: aload_0
       1: aload_1
       2: invokespecial #16                 // Method com/google/protobuf/GeneratedMessageV3."<init>":(Lcom/google/protobuf/GeneratedMessageV3$Builder;)V
       5: aload_0
       6: iconst_m1
       7: putfield      #17                 // Field memoizedIsInitialized:B
      10: return

  private com.google.protobuf.DescriptorProtos$FileDescriptorProto();
    Code:
       0: aload_0
       1: invokespecial #18                 // Method com/google/protobuf/GeneratedMessageV3."<init>":()V
       4: aload_0
       5: iconst_m1
       6: putfield      #17                 // Field memoizedIsInitialized:B
       9: aload_0
      10: ldc           #19                 // String
      12: putfield      #14                 // Field name_:Ljava/lang/Object;
      15: aload_0
      16: ldc           #19                 // String
      18: putfield      #13                 // Field package_:Ljava/lang/Object;
      21: aload_0
      22: getstatic     #20                 // Field com/google/protobuf/LazyStringArrayList.EMPTY:Lcom/google/protobuf/LazyStringList;
      25: putfield      #12                 // Field dependency_:Lcom/google/protobuf/LazyStringList;
      28: aload_0
      29: invokestatic  #21                 // Method java/util/Collections.emptyList:()Ljava/util/List;
      32: putfield      #11                 // Field publicDependency_:Ljava/util/List;
      35: aload_0
      36: invokestatic  #21                 // Method java/util/Collections.emptyList:()Ljava/util/List;
      39: putfield      #10                 // Field weakDependency_:Ljava/util/List;
      42: aload_0
      43: invokestatic  #21                 // Method java/util/Collections.emptyList:()Ljava/util/List;
      46: putfield      #9                  // Field messageType_:Ljava/util/List;
      49: aload_0
      50: invokestatic  #21                 // Method java/util/Collections.emptyList:()Ljava/util/List;
      53: putfield      #8                  // Field enumType_:Ljava/util/List;
      56: aload_0
      57: invokestatic  #21                 // Method java/util/Collections.emptyList:()Ljava/util/List;
      60: putfield      #7                  // Field service_:Ljava/util/List;
      63: aload_0
      64: invokestatic  #21                 // Method java/util/Collections.emptyList:()Ljava/util/List;
      67: putfield      #6                  // Field extension_:Ljava/util/List;
      70: aload_0
      71: ldc           #19                 // String
      73: putfield      #3                  // Field syntax_:Ljava/lang/Object;
      76: return

  public final com.google.protobuf.UnknownFieldSet getUnknownFields();
    Code:
       0: aload_0
       1: getfield      #22                 // Field unknownFields:Lcom/google/protobuf/UnknownFieldSet;
       4: areturn

  private com.google.protobuf.DescriptorProtos$FileDescriptorProto(com.google.protobuf.CodedInputStream, com.google.protobuf.ExtensionRegistryLite) throws com.google.protobuf.InvalidProtocolBufferException;
    Code:
       0: aload_0
       1: invokespecial #23                 // Method "<init>":()V
       4: iconst_0
       5: istore_3
       6: invokestatic  #24                 // Method com/google/protobuf/UnknownFieldSet.newBuilder:()Lcom/google/protobuf/UnknownFieldSet$Builder;
       9: astore        4
      11: iconst_0
      12: istore        5
      14: iload         5
      16: ifne          897
      19: aload_1
      20: invokevirtual #25                 // Method com/google/protobuf/CodedInputStream.readTag:()I
      23: istore        6
      25: iload         6
      27: lookupswitch  { // 15
                     0: 156
                    10: 181
                    18: 206
                    26: 231
                    34: 273
                    42: 319
                    50: 365
                    58: 414
                    66: 463
                    74: 537
                    80: 614
                    82: 659
                    88: 741
                    90: 786
                    98: 868
               default: 162
          }
     156: iconst_1
     157: istore        5
     159: goto          894
     162: aload_0
     163: aload_1
     164: aload         4
     166: aload_2
     167: iload         6
     169: invokevirtual #26                 // Method parseUnknownField:(Lcom/google/protobuf/CodedInputStream;Lcom/google/protobuf/UnknownFieldSet$Builder;Lcom/google/protobuf/ExtensionRegistryLite;I)Z
     172: ifne          894
     175: iconst_1
     176: istore        5
     178: goto          894
     181: aload_1
     182: invokevirtual #27                 // Method com/google/protobuf/CodedInputStream.readBytes:()Lcom/google/protobuf/ByteString;
     185: astore        7
     187: aload_0
     188: dup
     189: getfield      #2                  // Field bitField0_:I
     192: iconst_1
     193: ior
     194: putfield      #2                  // Field bitField0_:I
     197: aload_0
     198: aload         7
     200: putfield      #14                 // Field name_:Ljava/lang/Object;
     203: goto          894
     206: aload_1
     207: invokevirtual #27                 // Method com/google/protobuf/CodedInputStream.readBytes:()Lcom/google/protobuf/ByteString;
     210: astore        7
     212: aload_0
     213: dup
     214: getfield      #2                  // Field bitField0_:I
     217: iconst_2
     218: ior
     219: putfield      #2                  // Field bitField0_:I
     222: aload_0
     223: aload         7
     225: putfield      #13                 // Field package_:Ljava/lang/Object;
     228: goto          894
     231: aload_1
     232: invokevirtual #27                 // Method com/google/protobuf/CodedInputStream.readBytes:()Lcom/google/protobuf/ByteString;
     235: astore        7
     237: iload_3
     238: iconst_4
     239: iand
     240: iconst_4
     241: if_icmpeq     259
     244: aload_0
     245: new           #28                 // class com/google/protobuf/LazyStringArrayList
     248: dup
     249: invokespecial #29                 // Method com/google/protobuf/LazyStringArrayList."<init>":()V
     252: putfield      #12                 // Field dependency_:Lcom/google/protobuf/LazyStringList;
     255: iload_3
     256: iconst_4
     257: ior
     258: istore_3
     259: aload_0
     260: getfield      #12                 // Field dependency_:Lcom/google/protobuf/LazyStringList;
     263: aload         7
     265: invokeinterface #30,  2           // InterfaceMethod com/google/protobuf/LazyStringList.add:(Lcom/google/protobuf/ByteString;)V
     270: goto          894
     273: iload_3
     274: bipush        32
     276: iand
     277: bipush        32
     279: if_icmpeq     298
     282: aload_0
     283: new           #31                 // class java/util/ArrayList
     286: dup
     287: invokespecial #32                 // Method java/util/ArrayList."<init>":()V
     290: putfield      #9                  // Field messageType_:Ljava/util/List;
     293: iload_3
     294: bipush        32
     296: ior
     297: istore_3
     298: aload_0
     299: getfield      #9                  // Field messageType_:Ljava/util/List;
     302: aload_1
     303: getstatic     #33                 // Field com/google/protobuf/DescriptorProtos$DescriptorProto.PARSER:Lcom/google/protobuf/Parser;
     306: aload_2
     307: invokevirtual #34                 // Method com/google/protobuf/CodedInputStream.readMessage:(Lcom/google/protobuf/Parser;Lcom/google/protobuf/ExtensionRegistryLite;)Lcom/google/protobuf/MessageLite;
     310: invokeinterface #35,  2           // InterfaceMethod java/util/List.add:(Ljava/lang/Object;)Z
     315: pop
     316: goto          894
     319: iload_3
     320: bipush        64
     322: iand
     323: bipush        64
     325: if_icmpeq     344
     328: aload_0
     329: new           #31                 // class java/util/ArrayList
     332: dup
     333: invokespecial #32                 // Method java/util/ArrayList."<init>":()V
     336: putfield      #8                  // Field enumType_:Ljava/util/List;
     339: iload_3
     340: bipush        64
     342: ior
     343: istore_3
     344: aload_0
     345: getfield      #8                  // Field enumType_:Ljava/util/List;
     348: aload_1
     349: getstatic     #36                 // Field com/google/protobuf/DescriptorProtos$EnumDescriptorProto.PARSER:Lcom/google/protobuf/Parser;
     352: aload_2
     353: invokevirtual #34                 // Method com/google/protobuf/CodedInputStream.readMessage:(Lcom/google/protobuf/Parser;Lcom/google/protobuf/ExtensionRegistryLite;)Lcom/google/protobuf/MessageLite;
     356: invokeinterface #35,  2           // InterfaceMethod java/util/List.add:(Ljava/lang/Object;)Z
     361: pop
     362: goto          894
     365: iload_3
     366: sipush        128
     369: iand
     370: sipush        128
     373: if_icmpeq     393
     376: aload_0
     377: new           #31                 // class java/util/ArrayList
     380: dup
     381: invokespecial #32                 // Method java/util/ArrayList."<init>":()V
     384: putfield      #7                  // Field service_:Ljava/util/List;
     387: iload_3
     388: sipush        128
     391: ior
     392: istore_3
     393: aload_0
     394: getfield      #7                  // Field service_:Ljava/util/List;
     397: aload_1
     398: getstatic     #37                 // Field com/google/protobuf/DescriptorProtos$ServiceDescriptorProto.PARSER:Lcom/google/protobuf/Parser;
     401: aload_2
     402: invokevirtual #34                 // Method com/google/protobuf/CodedInputStream.readMessage:(Lcom/google/protobuf/Parser;Lcom/google/protobuf/ExtensionRegistryLite;)Lcom/google/protobuf/MessageLite;
     405: invokeinterface #35,  2           // InterfaceMethod java/util/List.add:(Ljava/lang/Object;)Z
     410: pop
     411: goto          894
     414: iload_3
     415: sipush        256
     418: iand
     419: sipush        256
     422: if_icmpeq     442
     425: aload_0
     426: new           #31                 // class java/util/ArrayList
     429: dup
     430: invokespecial #32                 // Method java/util/ArrayList."<init>":()V
     433: putfield      #6                  // Field extension_:Ljava/util/List;
     436: iload_3
     437: sipush        256
     440: ior
     441: istore_3
     442: aload_0
     443: getfield      #6                  // Field extension_:Ljava/util/List;
     446: aload_1
     447: getstatic     #38                 // Field com/google/protobuf/DescriptorProtos$FieldDescriptorProto.PARSER:Lcom/google/protobuf/Parser;
     450: aload_2
     451: invokevirtual #34                 // Method com/google/protobuf/CodedInputStream.readMessage:(Lcom/google/protobuf/Parser;Lcom/google/protobuf/ExtensionRegistryLite;)Lcom/google/protobuf/MessageLite;
     454: invokeinterface #35,  2           // InterfaceMethod java/util/List.add:(Ljava/lang/Object;)Z
     459: pop
     460: goto          894
     463: aconst_null
     464: astore        7
     466: aload_0
     467: getfield      #2                  // Field bitField0_:I
     470: iconst_4
     471: iand
     472: iconst_4
     473: if_icmpne     485
     476: aload_0
     477: getfield      #5                  // Field options_:Lcom/google/protobuf/DescriptorProtos$FileOptions;
     480: invokevirtual #39                 // Method com/google/protobuf/DescriptorProtos$FileOptions.toBuilder:()Lcom/google/protobuf/DescriptorProtos$FileOptions$Builder;
     483: astore        7
     485: aload_0
     486: aload_1
     487: getstatic     #40                 // Field com/google/protobuf/DescriptorProtos$FileOptions.PARSER:Lcom/google/protobuf/Parser;
     490: aload_2
     491: invokevirtual #34                 // Method com/google/protobuf/CodedInputStream.readMessage:(Lcom/google/protobuf/Parser;Lcom/google/protobuf/ExtensionRegistryLite;)Lcom/google/protobuf/MessageLite;
     494: checkcast     #41                 // class com/google/protobuf/DescriptorProtos$FileOptions
     497: putfield      #5                  // Field options_:Lcom/google/protobuf/DescriptorProtos$FileOptions;
     500: aload         7
     502: ifnull        524
     505: aload         7
     507: aload_0
     508: getfield      #5                  // Field options_:Lcom/google/protobuf/DescriptorProtos$FileOptions;
     511: invokevirtual #42                 // Method com/google/protobuf/DescriptorProtos$FileOptions$Builder.mergeFrom:(Lcom/google/protobuf/DescriptorProtos$FileOptions;)Lcom/google/protobuf/DescriptorProtos$FileOptions$Builder;
     514: pop
     515: aload_0
     516: aload         7
     518: invokevirtual #43                 // Method com/google/protobuf/DescriptorProtos$FileOptions$Builder.buildPartial:()Lcom/google/protobuf/DescriptorProtos$FileOptions;
     521: putfield      #5                  // Field options_:Lcom/google/protobuf/DescriptorProtos$FileOptions;
     524: aload_0
     525: dup
     526: getfield      #2                  // Field bitField0_:I
     529: iconst_4
     530: ior
     531: putfield      #2                  // Field bitField0_:I
     534: goto          894
     537: aconst_null
     538: astore        7
     540: aload_0
     541: getfield      #2                  // Field bitField0_:I
     544: bipush        8
     546: iand
     547: bipush        8
     549: if_icmpne     561
     552: aload_0
     553: getfield      #4                  // Field sourceCodeInfo_:Lcom/google/protobuf/DescriptorProtos$SourceCodeInfo;
     556: invokevirtual #44                 // Method com/google/protobuf/DescriptorProtos$SourceCodeInfo.toBuilder:()Lcom/google/protobuf/DescriptorProtos$SourceCodeInfo$Builder;
     559: astore        7
     561: aload_0
     562: aload_1
     563: getstatic     #45                 // Field com/google/protobuf/DescriptorProtos$SourceCodeInfo.PARSER:Lcom/google/protobuf/Parser;
     566: aload_2
     567: invokevirtual #34                 // Method com/google/protobuf/CodedInputStream.readMessage:(Lcom/google/protobuf/Parser;Lcom/google/protobuf/ExtensionRegistryLite;)Lcom/google/protobuf/MessageLite;
     570: checkcast     #46                 // class com/google/protobuf/DescriptorProtos$SourceCodeInfo
     573: putfield      #4                  // Field sourceCodeInfo_:Lcom/google/protobuf/DescriptorProtos$SourceCodeInfo;
     576: aload         7
     578: ifnull        600
     581: aload         7
     583: aload_0
     584: getfield      #4                  // Field sourceCodeInfo_:Lcom/google/protobuf/DescriptorProtos$SourceCodeInfo;
     587: invokevirtual #47                 // Method com/google/protobuf/DescriptorProtos$SourceCodeInfo$Builder.mergeFrom:(Lcom/google/protobuf/DescriptorProtos$SourceCodeInfo;)Lcom/google/protobuf/DescriptorProtos$SourceCodeInfo$Builder;
     590: pop
     591: aload_0
     592: aload         7
     594: invokevirtual #48                 // Method com/google/protobuf/DescriptorProtos$SourceCodeInfo$Builder.buildPartial:()Lcom/google/protobuf/DescriptorProtos$SourceCodeInfo;
     597: putfield      #4                  // Field sourceCodeInfo_:Lcom/google/protobuf/DescriptorProtos$SourceCodeInfo;
     600: aload_0
     601: dup
     602: getfield      #2                  // Field bitField0_:I
     605: bipush        8
     607: ior
     608: putfield      #2                  // Field bitField0_:I
     611: goto          894
     614: iload_3
     615: bipush        8
     617: iand
     618: bipush        8
     620: if_icmpeq     639
     623: aload_0
     624: new           #31                 // class java/util/ArrayList
     627: dup
     628: invokespecial #32                 // Method java/util/ArrayList."<init>":()V
     631: putfield      #11                 // Field publicDependency_:Ljava/util/List;
     634: iload_3
     635: bipush        8
     637: ior
     638: istore_3
     639: aload_0
     640: getfield      #11                 // Field publicDependency_:Ljava/util/List;
     643: aload_1
     644: invokevirtual #49                 // Method com/google/protobuf/CodedInputStream.readInt32:()I
     647: invokestatic  #50                 // Method java/lang/Integer.valueOf:(I)Ljava/lang/Integer;
     650: invokeinterface #35,  2           // InterfaceMethod java/util/List.add:(Ljava/lang/Object;)Z
     655: pop
     656: goto          894
     659: aload_1
     660: invokevirtual #51                 // Method com/google/protobuf/CodedInputStream.readRawVarint32:()I
     663: istore        7
     665: aload_1
     666: iload         7
     668: invokevirtual #52                 // Method com/google/protobuf/CodedInputStream.pushLimit:(I)I
     671: istore        8
     673: iload_3
     674: bipush        8
     676: iand
     677: bipush        8
     679: if_icmpeq     705
     682: aload_1
     683: invokevirtual #53                 // Method com/google/protobuf/CodedInputStream.getBytesUntilLimit:()I
     686: ifle          705
     689: aload_0
     690: new           #31                 // class java/util/ArrayList
     693: dup
     694: invokespecial #32                 // Method java/util/ArrayList."<init>":()V
     697: putfield      #11                 // Field publicDependency_:Ljava/util/List;
     700: iload_3
     701: bipush        8
     703: ior
     704: istore_3
     705: aload_1
     706: invokevirtual #53                 // Method com/google/protobuf/CodedInputStream.getBytesUntilLimit:()I
     709: ifle          732
     712: aload_0
     713: getfield      #11                 // Field publicDependency_:Ljava/util/List;
     716: aload_1
     717: invokevirtual #49                 // Method com/google/protobuf/CodedInputStream.readInt32:()I
     720: invokestatic  #50                 // Method java/lang/Integer.valueOf:(I)Ljava/lang/Integer;
     723: invokeinterface #35,  2           // InterfaceMethod java/util/List.add:(Ljava/lang/Object;)Z
     728: pop
     729: goto          705
     732: aload_1
     733: iload         8
     735: invokevirtual #54                 // Method com/google/protobuf/CodedInputStream.popLimit:(I)V
     738: goto          894
     741: iload_3
     742: bipush        16
     744: iand
     745: bipush        16
     747: if_icmpeq     766
     750: aload_0
     751: new           #31                 // class java/util/ArrayList
     754: dup
     755: invokespecial #32                 // Method java/util/ArrayList."<init>":()V
     758: putfield      #10                 // Field weakDependency_:Ljava/util/List;
     761: iload_3
     762: bipush        16
     764: ior
     765: istore_3
     766: aload_0
     767: getfield      #10                 // Field weakDependency_:Ljava/util/List;
     770: aload_1
     771: invokevirtual #49                 // Method com/google/protobuf/CodedInputStream.readInt32:()I
     774: invokestatic  #50                 // Method java/lang/Integer.valueOf:(I)Ljava/lang/Integer;
     777: invokeinterface #35,  2           // InterfaceMethod java/util/List.add:(Ljava/lang/Object;)Z
     782: pop
     783: goto          894
     786: aload_1
     787: invokevirtual #51                 // Method com/google/protobuf/CodedInputStream.readRawVarint32:()I
     790: istore        7
     792: aload_1
     793: iload         7
     795: invokevirtual #52                 // Method com/google/protobuf/CodedInputStream.pushLimit:(I)I
     798: istore        8
     800: iload_3
     801: bipush        16
     803: iand
     804: bipush        16
     806: if_icmpeq     832
     809: aload_1
     810: invokevirtual #53                 // Method com/google/protobuf/CodedInputStream.getBytesUntilLimit:()I
     813: ifle          832
     816: aload_0
     817: new           #31                 // class java/util/ArrayList
     820: dup
     821: invokespecial #32                 // Method java/util/ArrayList."<init>":()V
     824: putfield      #10                 // Field weakDependency_:Ljava/util/List;
     827: iload_3
     828: bipush        16
     830: ior
     831: istore_3
     832: aload_1
     833: invokevirtual #53                 // Method com/google/protobuf/CodedInputStream.getBytesUntilLimit:()I
     836: ifle          859
     839: aload_0
     840: getfield      #10                 // Field weakDependency_:Ljava/util/List;
     843: aload_1
     844: invokevirtual #49                 // Method com/google/protobuf/CodedInputStream.readInt32:()I
     847: invokestatic  #50                 // Method java/lang/Integer.valueOf:(I)Ljava/lang/Integer;
     850: invokeinterface #35,  2           // InterfaceMethod java/util/List.add:(Ljava/lang/Object;)Z
     855: pop
     856: goto          832
     859: aload_1
     860: iload         8
     862: invokevirtual #54                 // Method com/google/protobuf/CodedInputStream.popLimit:(I)V
     865: goto          894
     868: aload_1
     869: invokevirtual #27                 // Method com/google/protobuf/CodedInputStream.readBytes:()Lcom/google/protobuf/ByteString;
     872: astore        7
     874: aload_0
     875: dup
     876: getfield      #2                  // Field bitField0_:I
     879: bipush        16
     881: ior
     882: putfield      #2                  // Field bitField0_:I
     885: aload_0
     886: aload         7
     888: putfield      #3                  // Field syntax_:Ljava/lang/Object;
     891: goto          894
     894: goto          14
     897: iload_3
     898: iconst_4
     899: iand
     900: iconst_4
     901: if_icmpne     917
     904: aload_0
     905: aload_0
     906: getfield      #12                 // Field dependency_:Lcom/google/protobuf/LazyStringList;
     909: invokeinterface #55,  1           // InterfaceMethod com/google/protobuf/LazyStringList.getUnmodifiableView:()Lcom/google/protobuf/LazyStringList;
     914: putfield      #12                 // Field dependency_:Lcom/google/protobuf/LazyStringList;
     917: iload_3
     918: bipush        32
     920: iand
     921: bipush        32
     923: if_icmpne     937
     926: aload_0
     927: aload_0
     928: getfield      #9                  // Field messageType_:Ljava/util/List;
     931: invokestatic  #56                 // Method java/util/Collections.unmodifiableList:(Ljava/util/List;)Ljava/util/List;
     934: putfield      #9                  // Field messageType_:Ljava/util/List;
     937: iload_3
     938: bipush        64
     940: iand
     941: bipush        64
     943: if_icmpne     957
     946: aload_0
     947: aload_0
     948: getfield      #8                  // Field enumType_:Ljava/util/List;
     951: invokestatic  #56                 // Method java/util/Collections.unmodifiableList:(Ljava/util/List;)Ljava/util/List;
     954: putfield      #8                  // Field enumType_:Ljava/util/List;
     957: iload_3
     958: sipush        128
     961: iand
     962: sipush        128
     965: if_icmpne     979
     968: aload_0
     969: aload_0
     970: getfield      #7                  // Field service_:Ljava/util/List;
     973: invokestatic  #56                 // Method java/util/Collections.unmodifiableList:(Ljava/util/List;)Ljava/util/List;
     976: putfield      #7                  // Field service_:Ljava/util/List;
     979: iload_3
     980: sipush        256
     983: iand
     984: sipush        256
     987: if_icmpne     1001
     990: aload_0
     991: aload_0
     992: getfield      #6                  // Field extension_:Ljava/util/List;
     995: invokestatic  #56                 // Method java/util/Collections.unmodifiableList:(Ljava/util/List;)Ljava/util/List;
     998: putfield      #6                  // Field extension_:Ljava/util/List;
    1001: iload_3
    1002: bipush        8
    1004: iand
    1005: bipush        8
    1007: if_icmpne     1021
    1010: aload_0
    1011: aload_0
    1012: getfield      #11                 // Field publicDependency_:Ljava/util/List;
    1015: invokestatic  #56                 // Method java/util/Collections.unmodifiableList:(Ljava/util/List;)Ljava/util/List;
    1018: putfield      #11                 // Field publicDependency_:Ljava/util/List;
    1021: iload_3
    1022: bipush        16
    1024: iand
    1025: bipush        16
    1027: if_icmpne     1041
    1030: aload_0
    1031: aload_0
    1032: getfield      #10                 // Field weakDependency_:Ljava/util/List;
    1035: invokestatic  #56                 // Method java/util/Collections.unmodifiableList:(Ljava/util/List;)Ljava/util/List;
    1038: putfield      #10                 // Field weakDependency_:Ljava/util/List;
    1041: aload_0
    1042: aload         4
    1044: invokevirtual #57                 // Method com/google/protobuf/UnknownFieldSet$Builder.build:()Lcom/google/protobuf/UnknownFieldSet;
    1047: putfield      #22                 // Field unknownFields:Lcom/google/protobuf/UnknownFieldSet;
    1050: aload_0
    1051: invokevirtual #58                 // Method makeExtensionsImmutable:()V
    1054: goto          1244
    1057: astore        5
    1059: aload         5
    1061: aload_0
    1062: invokevirtual #60                 // Method com/google/protobuf/InvalidProtocolBufferException.setUnfinishedMessage:(Lcom/google/protobuf/MessageLite;)Lcom/google/protobuf/InvalidProtocolBufferException;
    1065: athrow
    1066: astore        5
    1068: new           #59                 // class com/google/protobuf/InvalidProtocolBufferException
    1071: dup
    1072: aload         5
    1074: invokespecial #62                 // Method com/google/protobuf/InvalidProtocolBufferException."<init>":(Ljava/io/IOException;)V
    1077: aload_0
    1078: invokevirtual #60                 // Method com/google/protobuf/InvalidProtocolBufferException.setUnfinishedMessage:(Lcom/google/protobuf/MessageLite;)Lcom/google/protobuf/InvalidProtocolBufferException;
    1081: athrow
    1082: astore        9
    1084: iload_3
    1085: iconst_4
    1086: iand
    1087: iconst_4
    1088: if_icmpne     1104
    1091: aload_0
    1092: aload_0
    1093: getfield      #12                 // Field dependency_:Lcom/google/protobuf/LazyStringList;
    1096: invokeinterface #55,  1           // InterfaceMethod com/google/protobuf/LazyStringList.getUnmodifiableView:()Lcom/google/protobuf/LazyStringList;
    1101: putfield      #12                 // Field dependency_:Lcom/google/protobuf/LazyStringList;
    1104: iload_3
    1105: bipush        32
    1107: iand
    1108: bipush        32
    1110: if_icmpne     1124
    1113: aload_0
    1114: aload_0
    1115: getfield      #9                  // Field messageType_:Ljava/util/List;
    1118: invokestatic  #56                 // Method java/util/Collections.unmodifiableList:(Ljava/util/List;)Ljava/util/List;
    1121: putfield      #9                  // Field messageType_:Ljava/util/List;
    1124: iload_3
    1125: bipush        64
    1127: iand
    1128: bipush        64
    1130: if_icmpne     1144
    1133: aload_0
    1134: aload_0
    1135: getfield      #8                  // Field enumType_:Ljava/util/List;
    1138: invokestatic  #56                 // Method java/util/Collections.unmodifiableList:(Ljava/util/List;)Ljava/util/List;
    1141: putfield      #8                  // Field enumType_:Ljava/util/List;
    1144: iload_3
    1145: sipush        128
    1148: iand
    1149: sipush        128
    1152: if_icmpne     1166
    1155: aload_0
    1156: aload_0
    1157: getfield      #7                  // Field service_:Ljava/util/List;
    1160: invokestatic  #56                 // Method java/util/Collections.unmodifiableList:(Ljava/util/List;)Ljava/util/List;
    1163: putfield      #7                  // Field service_:Ljava/util/List;
    1166: iload_3
    1167: sipush        256
    1170: iand
    1171: sipush        256
    1174: if_icmpne     1188
    1177: aload_0
    1178: aload_0
    1179: getfield      #6                  // Field extension_:Ljava/util/List;
    1182: invokestatic  #56                 // Method java/util/Collections.unmodifiableList:(Ljava/util/List;)Ljava/util/List;
    1185: putfield      #6                  // Field extension_:Ljava/util/List;
    1188: iload_3
    1189: bipush        8
    1191: iand
    1192: bipush        8
    1194: if_icmpne     1208
    1197: aload_0
    1198: aload_0
    1199: getfield      #11                 // Field publicDependency_:Ljava/util/List;
    1202: invokestatic  #56                 // Method java/util/Collections.unmodifiableList:(Ljava/util/List;)Ljava/util/List;
    1205: putfield      #11                 // Field publicDependency_:Ljava/util/List;
    1208: iload_3
    1209: bipush        16
    1211: iand
    1212: bipush        16
    1214: if_icmpne     1228
    1217: aload_0
    1218: aload_0
    1219: getfield      #10                 // Field weakDependency_:Ljava/util/List;
    1222: invokestatic  #56                 // Method java/util/Collections.unmodifiableList:(Ljava/util/List;)Ljava/util/List;
    1225: putfield      #10                 // Field weakDependency_:Ljava/util/List;
    1228: aload_0
    1229: aload         4
    1231: invokevirtual #57                 // Method com/google/protobuf/UnknownFieldSet$Builder.build:()Lcom/google/protobuf/UnknownFieldSet;
    1234: putfield      #22                 // Field unknownFields:Lcom/google/protobuf/UnknownFieldSet;
    1237: aload_0
    1238: invokevirtual #58                 // Method makeExtensionsImmutable:()V
    1241: aload         9
    1243: athrow
    1244: return
    Exception table:
       from    to  target type
          11   897  1057   Class com/google/protobuf/InvalidProtocolBufferException
          11   897  1066   Class java/io/IOException
          11   897  1082   any
        1057  1084  1082   any

  public static final com.google.protobuf.Descriptors$Descriptor getDescriptor();
    Code:
       0: invokestatic  #63                 // Method com/google/protobuf/DescriptorProtos.access$700:()Lcom/google/protobuf/Descriptors$Descriptor;
       3: areturn

  protected com.google.protobuf.GeneratedMessageV3$FieldAccessorTable internalGetFieldAccessorTable();
    Code:
       0: invokestatic  #64                 // Method com/google/protobuf/DescriptorProtos.access$800:()Lcom/google/protobuf/GeneratedMessageV3$FieldAccessorTable;
       3: ldc           #65                 // class com/google/protobuf/DescriptorProtos$FileDescriptorProto
       5: ldc           #66                 // class com/google/protobuf/DescriptorProtos$FileDescriptorProto$Builder
       7: invokevirtual #67                 // Method com/google/protobuf/GeneratedMessageV3$FieldAccessorTable.ensureFieldAccessorsInitialized:(Ljava/lang/Class;Ljava/lang/Class;)Lcom/google/protobuf/GeneratedMessageV3$FieldAccessorTable;
      10: areturn

  public boolean hasName();
    Code:
       0: aload_0
       1: getfield      #2                  // Field bitField0_:I
       4: iconst_1
       5: iand
       6: iconst_1
       7: if_icmpne     14
      10: iconst_1
      11: goto          15
      14: iconst_0
      15: ireturn

  public java.lang.String getName();
    Code:
       0: aload_0
       1: getfield      #14                 // Field name_:Ljava/lang/Object;
       4: astore_1
       5: aload_1
       6: instanceof    #68                 // class java/lang/String
       9: ifeq          17
      12: aload_1
      13: checkcast     #68                 // class java/lang/String
      16: areturn
      17: aload_1
      18: checkcast     #69                 // class com/google/protobuf/ByteString
      21: astore_2
      22: aload_2
      23: invokevirtual #70                 // Method com/google/protobuf/ByteString.toStringUtf8:()Ljava/lang/String;
      26: astore_3
      27: aload_2
      28: invokevirtual #71                 // Method com/google/protobuf/ByteString.isValidUtf8:()Z
      31: ifeq          39
      34: aload_0
      35: aload_3
      36: putfield      #14                 // Field name_:Ljava/lang/Object;
      39: aload_3
      40: areturn

  public com.google.protobuf.ByteString getNameBytes();
    Code:
       0: aload_0
       1: getfield      #14                 // Field name_:Ljava/lang/Object;
       4: astore_1
       5: aload_1
       6: instanceof    #68                 // class java/lang/String
       9: ifeq          27
      12: aload_1
      13: checkcast     #68                 // class java/lang/String
      16: invokestatic  #72                 // Method com/google/protobuf/ByteString.copyFromUtf8:(Ljava/lang/String;)Lcom/google/protobuf/ByteString;
      19: astore_2
      20: aload_0
      21: aload_2
      22: putfield      #14                 // Field name_:Ljava/lang/Object;
      25: aload_2
      26: areturn
      27: aload_1
      28: checkcast     #69                 // class com/google/protobuf/ByteString
      31: areturn

  public boolean hasPackage();
    Code:
       0: aload_0
       1: getfield      #2                  // Field bitField0_:I
       4: iconst_2
       5: iand
       6: iconst_2
       7: if_icmpne     14
      10: iconst_1
      11: goto          15
      14: iconst_0
      15: ireturn

  public java.lang.String getPackage();
    Code:
       0: aload_0
       1: getfield      #13                 // Field package_:Ljava/lang/Object;
       4: astore_1
       5: aload_1
       6: instanceof    #68                 // class java/lang/String
       9: ifeq          17
      12: aload_1
      13: checkcast     #68                 // class java/lang/String
      16: areturn
      17: aload_1
      18: checkcast     #69                 // class com/google/protobuf/ByteString
      21: astore_2
      22: aload_2
      23: invokevirtual #70                 // Method com/google/protobuf/ByteString.toStringUtf8:()Ljava/lang/String;
      26: astore_3
      27: aload_2
      28: invokevirtual #71                 // Method com/google/protobuf/ByteString.isValidUtf8:()Z
      31: ifeq          39
      34: aload_0
      35: aload_3
      36: putfield      #13                 // Field package_:Ljava/lang/Object;
      39: aload_3
      40: areturn

  public com.google.protobuf.ByteString getPackageBytes();
    Code:
       0: aload_0
       1: getfield      #13                 // Field package_:Ljava/lang/Object;
       4: astore_1
       5: aload_1
       6: instanceof    #68                 // class java/lang/String
       9: ifeq          27
      12: aload_1
      13: checkcast     #68                 // class java/lang/String
      16: invokestatic  #72                 // Method com/google/protobuf/ByteString.copyFromUtf8:(Ljava/lang/String;)Lcom/google/protobuf/ByteString;
      19: astore_2
      20: aload_0
      21: aload_2
      22: putfield      #13                 // Field package_:Ljava/lang/Object;
      25: aload_2
      26: areturn
      27: aload_1
      28: checkcast     #69                 // class com/google/protobuf/ByteString
      31: areturn

  public com.google.protobuf.ProtocolStringList getDependencyList();
    Code:
       0: aload_0
       1: getfield      #12                 // Field dependency_:Lcom/google/protobuf/LazyStringList;
       4: areturn

  public int getDependencyCount();
    Code:
       0: aload_0
       1: getfield      #12                 // Field dependency_:Lcom/google/protobuf/LazyStringList;
       4: invokeinterface #73,  1           // InterfaceMethod com/google/protobuf/LazyStringList.size:()I
       9: ireturn

  public java.lang.String getDependency(int);
    Code:
       0: aload_0
       1: getfield      #12                 // Field dependency_:Lcom/google/protobuf/LazyStringList;
       4: iload_1
       5: invokeinterface #74,  2           // InterfaceMethod com/google/protobuf/LazyStringList.get:(I)Ljava/lang/Object;
      10: checkcast     #68                 // class java/lang/String
      13: areturn

  public com.google.protobuf.ByteString getDependencyBytes(int);
    Code:
       0: aload_0
       1: getfield      #12                 // Field dependency_:Lcom/google/protobuf/LazyStringList;
       4: iload_1
       5: invokeinterface #75,  2           // InterfaceMethod com/google/protobuf/LazyStringList.getByteString:(I)Lcom/google/protobuf/ByteString;
      10: areturn

  public java.util.List<java.lang.Integer> getPublicDependencyList();
    Code:
       0: aload_0
       1: getfield      #11                 // Field publicDependency_:Ljava/util/List;
       4: areturn

  public int getPublicDependencyCount();
    Code:
       0: aload_0
       1: getfield      #11                 // Field publicDependency_:Ljava/util/List;
       4: invokeinterface #76,  1           // InterfaceMethod java/util/List.size:()I
       9: ireturn

  public int getPublicDependency(int);
    Code:
       0: aload_0
       1: getfield      #11                 // Field publicDependency_:Ljava/util/List;
       4: iload_1
       5: invokeinterface #77,  2           // InterfaceMethod java/util/List.get:(I)Ljava/lang/Object;
      10: checkcast     #78                 // class java/lang/Integer
      13: invokevirtual #79                 // Method java/lang/Integer.intValue:()I
      16: ireturn

  public java.util.List<java.lang.Integer> getWeakDependencyList();
    Code:
       0: aload_0
       1: getfield      #10                 // Field weakDependency_:Ljava/util/List;
       4: areturn

  public int getWeakDependencyCount();
    Code:
       0: aload_0
       1: getfield      #10                 // Field weakDependency_:Ljava/util/List;
       4: invokeinterface #76,  1           // InterfaceMethod java/util/List.size:()I
       9: ireturn

  public int getWeakDependency(int);
    Code:
       0: aload_0
       1: getfield      #10                 // Field weakDependency_:Ljava/util/List;
       4: iload_1
       5: invokeinterface #77,  2           // InterfaceMethod java/util/List.get:(I)Ljava/lang/Object;
      10: checkcast     #78                 // class java/lang/Integer
      13: invokevirtual #79                 // Method java/lang/Integer.intValue:()I
      16: ireturn

  public java.util.List<com.google.protobuf.DescriptorProtos$DescriptorProto> getMessageTypeList();
    Code:
       0: aload_0
       1: getfield      #9                  // Field messageType_:Ljava/util/List;
       4: areturn

  public java.util.List<? extends com.google.protobuf.DescriptorProtos$DescriptorProtoOrBuilder> getMessageTypeOrBuilderList();
    Code:
       0: aload_0
       1: getfield      #9                  // Field messageType_:Ljava/util/List;
       4: areturn

  public int getMessageTypeCount();
    Code:
       0: aload_0
       1: getfield      #9                  // Field messageType_:Ljava/util/List;
       4: invokeinterface #76,  1           // InterfaceMethod java/util/List.size:()I
       9: ireturn

  public com.google.protobuf.DescriptorProtos$DescriptorProto getMessageType(int);
    Code:
       0: aload_0
       1: getfield      #9                  // Field messageType_:Ljava/util/List;
       4: iload_1
       5: invokeinterface #77,  2           // InterfaceMethod java/util/List.get:(I)Ljava/lang/Object;
      10: checkcast     #80                 // class com/google/protobuf/DescriptorProtos$DescriptorProto
      13: areturn

  public com.google.protobuf.DescriptorProtos$DescriptorProtoOrBuilder getMessageTypeOrBuilder(int);
    Code:
       0: aload_0
       1: getfield      #9                  // Field messageType_:Ljava/util/List;
       4: iload_1
       5: invokeinterface #77,  2           // InterfaceMethod java/util/List.get:(I)Ljava/lang/Object;
      10: checkcast     #81                 // class com/google/protobuf/DescriptorProtos$DescriptorProtoOrBuilder
      13: areturn

  public java.util.List<com.google.protobuf.DescriptorProtos$EnumDescriptorProto> getEnumTypeList();
    Code:
       0: aload_0
       1: getfield      #8                  // Field enumType_:Ljava/util/List;
       4: areturn

  public java.util.List<? extends com.google.protobuf.DescriptorProtos$EnumDescriptorProtoOrBuilder> getEnumTypeOrBuilderList();
    Code:
       0: aload_0
       1: getfield      #8                  // Field enumType_:Ljava/util/List;
       4: areturn

  public int getEnumTypeCount();
    Code:
       0: aload_0
       1: getfield      #8                  // Field enumType_:Ljava/util/List;
       4: invokeinterface #76,  1           // InterfaceMethod java/util/List.size:()I
       9: ireturn

  public com.google.protobuf.DescriptorProtos$EnumDescriptorProto getEnumType(int);
    Code:
       0: aload_0
       1: getfield      #8                  // Field enumType_:Ljava/util/List;
       4: iload_1
       5: invokeinterface #77,  2           // InterfaceMethod java/util/List.get:(I)Ljava/lang/Object;
      10: checkcast     #82                 // class com/google/protobuf/DescriptorProtos$EnumDescriptorProto
      13: areturn

  public com.google.protobuf.DescriptorProtos$EnumDescriptorProtoOrBuilder getEnumTypeOrBuilder(int);
    Code:
       0: aload_0
       1: getfield      #8                  // Field enumType_:Ljava/util/List;
       4: iload_1
       5: invokeinterface #77,  2           // InterfaceMethod java/util/List.get:(I)Ljava/lang/Object;
      10: checkcast     #83                 // class com/google/protobuf/DescriptorProtos$EnumDescriptorProtoOrBuilder
      13: areturn

  public java.util.List<com.google.protobuf.DescriptorProtos$ServiceDescriptorProto> getServiceList();
    Code:
       0: aload_0
       1: getfield      #7                  // Field service_:Ljava/util/List;
       4: areturn

  public java.util.List<? extends com.google.protobuf.DescriptorProtos$ServiceDescriptorProtoOrBuilder> getServiceOrBuilderList();
    Code:
       0: aload_0
       1: getfield      #7                  // Field service_:Ljava/util/List;
       4: areturn

  public int getServiceCount();
    Code:
       0: aload_0
       1: getfield      #7                  // Field service_:Ljava/util/List;
       4: invokeinterface #76,  1           // InterfaceMethod java/util/List.size:()I
       9: ireturn

  public com.google.protobuf.DescriptorProtos$ServiceDescriptorProto getService(int);
    Code:
       0: aload_0
       1: getfield      #7                  // Field service_:Ljava/util/List;
       4: iload_1
       5: invokeinterface #77,  2           // InterfaceMethod java/util/List.get:(I)Ljava/lang/Object;
      10: checkcast     #84                 // class com/google/protobuf/DescriptorProtos$ServiceDescriptorProto
      13: areturn

  public com.google.protobuf.DescriptorProtos$ServiceDescriptorProtoOrBuilder getServiceOrBuilder(int);
    Code:
       0: aload_0
       1: getfield      #7                  // Field service_:Ljava/util/List;
       4: iload_1
       5: invokeinterface #77,  2           // InterfaceMethod java/util/List.get:(I)Ljava/lang/Object;
      10: checkcast     #85                 // class com/google/protobuf/DescriptorProtos$ServiceDescriptorProtoOrBuilder
      13: areturn

  public java.util.List<com.google.protobuf.DescriptorProtos$FieldDescriptorProto> getExtensionList();
    Code:
       0: aload_0
       1: getfield      #6                  // Field extension_:Ljava/util/List;
       4: areturn

  public java.util.List<? extends com.google.protobuf.DescriptorProtos$FieldDescriptorProtoOrBuilder> getExtensionOrBuilderList();
    Code:
       0: aload_0
       1: getfield      #6                  // Field extension_:Ljava/util/List;
       4: areturn

  public int getExtensionCount();
    Code:
       0: aload_0
       1: getfield      #6                  // Field extension_:Ljava/util/List;
       4: invokeinterface #76,  1           // InterfaceMethod java/util/List.size:()I
       9: ireturn

  public com.google.protobuf.DescriptorProtos$FieldDescriptorProto getExtension(int);
    Code:
       0: aload_0
       1: getfield      #6                  // Field extension_:Ljava/util/List;
       4: iload_1
       5: invokeinterface #77,  2           // InterfaceMethod java/util/List.get:(I)Ljava/lang/Object;
      10: checkcast     #86                 // class com/google/protobuf/DescriptorProtos$FieldDescriptorProto
      13: areturn

  public com.google.protobuf.DescriptorProtos$FieldDescriptorProtoOrBuilder getExtensionOrBuilder(int);
    Code:
       0: aload_0
       1: getfield      #6                  // Field extension_:Ljava/util/List;
       4: iload_1
       5: invokeinterface #77,  2           // InterfaceMethod java/util/List.get:(I)Ljava/lang/Object;
      10: checkcast     #87                 // class com/google/protobuf/DescriptorProtos$FieldDescriptorProtoOrBuilder
      13: areturn

  public boolean hasOptions();
    Code:
       0: aload_0
       1: getfield      #2                  // Field bitField0_:I
       4: iconst_4
       5: iand
       6: iconst_4
       7: if_icmpne     14
      10: iconst_1
      11: goto          15
      14: iconst_0
      15: ireturn

  public com.google.protobuf.DescriptorProtos$FileOptions getOptions();
    Code:
       0: aload_0
       1: getfield      #5                  // Field options_:Lcom/google/protobuf/DescriptorProtos$FileOptions;
       4: ifnonnull     13
       7: invokestatic  #88                 // Method com/google/protobuf/DescriptorProtos$FileOptions.getDefaultInstance:()Lcom/google/protobuf/DescriptorProtos$FileOptions;
      10: goto          17
      13: aload_0
      14: getfield      #5                  // Field options_:Lcom/google/protobuf/DescriptorProtos$FileOptions;
      17: areturn

  public com.google.protobuf.DescriptorProtos$FileOptionsOrBuilder getOptionsOrBuilder();
    Code:
       0: aload_0
       1: getfield      #5                  // Field options_:Lcom/google/protobuf/DescriptorProtos$FileOptions;
       4: ifnonnull     13
       7: invokestatic  #88                 // Method com/google/protobuf/DescriptorProtos$FileOptions.getDefaultInstance:()Lcom/google/protobuf/DescriptorProtos$FileOptions;
      10: goto          17
      13: aload_0
      14: getfield      #5                  // Field options_:Lcom/google/protobuf/DescriptorProtos$FileOptions;
      17: areturn

  public boolean hasSourceCodeInfo();
    Code:
       0: aload_0
       1: getfield      #2                  // Field bitField0_:I
       4: bipush        8
       6: iand
       7: bipush        8
       9: if_icmpne     16
      12: iconst_1
      13: goto          17
      16: iconst_0
      17: ireturn

  public com.google.protobuf.DescriptorProtos$SourceCodeInfo getSourceCodeInfo();
    Code:
       0: aload_0
       1: getfield      #4                  // Field sourceCodeInfo_:Lcom/google/protobuf/DescriptorProtos$SourceCodeInfo;
       4: ifnonnull     13
       7: invokestatic  #89                 // Method com/google/protobuf/DescriptorProtos$SourceCodeInfo.getDefaultInstance:()Lcom/google/protobuf/DescriptorProtos$SourceCodeInfo;
      10: goto          17
      13: aload_0
      14: getfield      #4                  // Field sourceCodeInfo_:Lcom/google/protobuf/DescriptorProtos$SourceCodeInfo;
      17: areturn

  public com.google.protobuf.DescriptorProtos$SourceCodeInfoOrBuilder getSourceCodeInfoOrBuilder();
    Code:
       0: aload_0
       1: getfield      #4                  // Field sourceCodeInfo_:Lcom/google/protobuf/DescriptorProtos$SourceCodeInfo;
       4: ifnonnull     13
       7: invokestatic  #89                 // Method com/google/protobuf/DescriptorProtos$SourceCodeInfo.getDefaultInstance:()Lcom/google/protobuf/DescriptorProtos$SourceCodeInfo;
      10: goto          17
      13: aload_0
      14: getfield      #4                  // Field sourceCodeInfo_:Lcom/google/protobuf/DescriptorProtos$SourceCodeInfo;
      17: areturn

  public boolean hasSyntax();
    Code:
       0: aload_0
       1: getfield      #2                  // Field bitField0_:I
       4: bipush        16
       6: iand
       7: bipush        16
       9: if_icmpne     16
      12: iconst_1
      13: goto          17
      16: iconst_0
      17: ireturn

  public java.lang.String getSyntax();
    Code:
       0: aload_0
       1: getfield      #3                  // Field syntax_:Ljava/lang/Object;
       4: astore_1
       5: aload_1
       6: instanceof    #68                 // class java/lang/String
       9: ifeq          17
      12: aload_1
      13: checkcast     #68                 // class java/lang/String
      16: areturn
      17: aload_1
      18: checkcast     #69                 // class com/google/protobuf/ByteString
      21: astore_2
      22: aload_2
      23: invokevirtual #70                 // Method com/google/protobuf/ByteString.toStringUtf8:()Ljava/lang/String;
      26: astore_3
      27: aload_2
      28: invokevirtual #71                 // Method com/google/protobuf/ByteString.isValidUtf8:()Z
      31: ifeq          39
      34: aload_0
      35: aload_3
      36: putfield      #3                  // Field syntax_:Ljava/lang/Object;
      39: aload_3
      40: areturn

  public com.google.protobuf.ByteString getSyntaxBytes();
    Code:
       0: aload_0
       1: getfield      #3                  // Field syntax_:Ljava/lang/Object;
       4: astore_1
       5: aload_1
       6: instanceof    #68                 // class java/lang/String
       9: ifeq          27
      12: aload_1
      13: checkcast     #68                 // class java/lang/String
      16: invokestatic  #72                 // Method com/google/protobuf/ByteString.copyFromUtf8:(Ljava/lang/String;)Lcom/google/protobuf/ByteString;
      19: astore_2
      20: aload_0
      21: aload_2
      22: putfield      #3                  // Field syntax_:Ljava/lang/Object;
      25: aload_2
      26: areturn
      27: aload_1
      28: checkcast     #69                 // class com/google/protobuf/ByteString
      31: areturn

  public final boolean isInitialized();
    Code:
       0: aload_0
       1: getfield      #17                 // Field memoizedIsInitialized:B
       4: istore_1
       5: iload_1
       6: iconst_1
       7: if_icmpne     12
      10: iconst_1
      11: ireturn
      12: iload_1
      13: ifne          18
      16: iconst_0
      17: ireturn
      18: iconst_0
      19: istore_2
      20: iload_2
      21: aload_0
      22: invokevirtual #90                 // Method getMessageTypeCount:()I
      25: if_icmpge     52
      28: aload_0
      29: iload_2
      30: invokevirtual #91                 // Method getMessageType:(I)Lcom/google/protobuf/DescriptorProtos$DescriptorProto;
      33: invokevirtual #92                 // Method com/google/protobuf/DescriptorProtos$DescriptorProto.isInitialized:()Z
      36: ifne          46
      39: aload_0
      40: iconst_0
      41: putfield      #17                 // Field memoizedIsInitialized:B
      44: iconst_0
      45: ireturn
      46: iinc          2, 1
      49: goto          20
      52: iconst_0
      53: istore_2
      54: iload_2
      55: aload_0
      56: invokevirtual #93                 // Method getEnumTypeCount:()I
      59: if_icmpge     86
      62: aload_0
      63: iload_2
      64: invokevirtual #94                 // Method getEnumType:(I)Lcom/google/protobuf/DescriptorProtos$EnumDescriptorProto;
      67: invokevirtual #95                 // Method com/google/protobuf/DescriptorProtos$EnumDescriptorProto.isInitialized:()Z
      70: ifne          80
      73: aload_0
      74: iconst_0
      75: putfield      #17                 // Field memoizedIsInitialized:B
      78: iconst_0
      79: ireturn
      80: iinc          2, 1
      83: goto          54
      86: iconst_0
      87: istore_2
      88: iload_2
      89: aload_0
      90: invokevirtual #96                 // Method getServiceCount:()I
      93: if_icmpge     120
      96: aload_0
      97: iload_2
      98: invokevirtual #97                 // Method getService:(I)Lcom/google/protobuf/DescriptorProtos$ServiceDescriptorProto;
     101: invokevirtual #98                 // Method com/google/protobuf/DescriptorProtos$ServiceDescriptorProto.isInitialized:()Z
     104: ifne          114
     107: aload_0
     108: iconst_0
     109: putfield      #17                 // Field memoizedIsInitialized:B
     112: iconst_0
     113: ireturn
     114: iinc          2, 1
     117: goto          88
     120: iconst_0
     121: istore_2
     122: iload_2
     123: aload_0
     124: invokevirtual #99                 // Method getExtensionCount:()I
     127: if_icmpge     154
     130: aload_0
     131: iload_2
     132: invokevirtual #100                // Method getExtension:(I)Lcom/google/protobuf/DescriptorProtos$FieldDescriptorProto;
     135: invokevirtual #101                // Method com/google/protobuf/DescriptorProtos$FieldDescriptorProto.isInitialized:()Z
     138: ifne          148
     141: aload_0
     142: iconst_0
     143: putfield      #17                 // Field memoizedIsInitialized:B
     146: iconst_0
     147: ireturn
     148: iinc          2, 1
     151: goto          122
     154: aload_0
     155: invokevirtual #102                // Method hasOptions:()Z
     158: ifeq          178
     161: aload_0
     162: invokevirtual #103                // Method getOptions:()Lcom/google/protobuf/DescriptorProtos$FileOptions;
     165: invokevirtual #104                // Method com/google/protobuf/DescriptorProtos$FileOptions.isInitialized:()Z
     168: ifne          178
     171: aload_0
     172: iconst_0
     173: putfield      #17                 // Field memoizedIsInitialized:B
     176: iconst_0
     177: ireturn
     178: aload_0
     179: iconst_1
     180: putfield      #17                 // Field memoizedIsInitialized:B
     183: iconst_1
     184: ireturn

  public void writeTo(com.google.protobuf.CodedOutputStream) throws java.io.IOException;
    Code:
       0: aload_0
       1: getfield      #2                  // Field bitField0_:I
       4: iconst_1
       5: iand
       6: iconst_1
       7: if_icmpne     19
      10: aload_1
      11: iconst_1
      12: aload_0
      13: getfield      #14                 // Field name_:Ljava/lang/Object;
      16: invokestatic  #105                // Method com/google/protobuf/GeneratedMessageV3.writeString:(Lcom/google/protobuf/CodedOutputStream;ILjava/lang/Object;)V
      19: aload_0
      20: getfield      #2                  // Field bitField0_:I
      23: iconst_2
      24: iand
      25: iconst_2
      26: if_icmpne     38
      29: aload_1
      30: iconst_2
      31: aload_0
      32: getfield      #13                 // Field package_:Ljava/lang/Object;
      35: invokestatic  #105                // Method com/google/protobuf/GeneratedMessageV3.writeString:(Lcom/google/protobuf/CodedOutputStream;ILjava/lang/Object;)V
      38: iconst_0
      39: istore_2
      40: iload_2
      41: aload_0
      42: getfield      #12                 // Field dependency_:Lcom/google/protobuf/LazyStringList;
      45: invokeinterface #73,  1           // InterfaceMethod com/google/protobuf/LazyStringList.size:()I
      50: if_icmpge     74
      53: aload_1
      54: iconst_3
      55: aload_0
      56: getfield      #12                 // Field dependency_:Lcom/google/protobuf/LazyStringList;
      59: iload_2
      60: invokeinterface #106,  2          // InterfaceMethod com/google/protobuf/LazyStringList.getRaw:(I)Ljava/lang/Object;
      65: invokestatic  #105                // Method com/google/protobuf/GeneratedMessageV3.writeString:(Lcom/google/protobuf/CodedOutputStream;ILjava/lang/Object;)V
      68: iinc          2, 1
      71: goto          40
      74: iconst_0
      75: istore_2
      76: iload_2
      77: aload_0
      78: getfield      #9                  // Field messageType_:Ljava/util/List;
      81: invokeinterface #76,  1           // InterfaceMethod java/util/List.size:()I
      86: if_icmpge     113
      89: aload_1
      90: iconst_4
      91: aload_0
      92: getfield      #9                  // Field messageType_:Ljava/util/List;
      95: iload_2
      96: invokeinterface #77,  2           // InterfaceMethod java/util/List.get:(I)Ljava/lang/Object;
     101: checkcast     #107                // class com/google/protobuf/MessageLite
     104: invokevirtual #108                // Method com/google/protobuf/CodedOutputStream.writeMessage:(ILcom/google/protobuf/MessageLite;)V
     107: iinc          2, 1
     110: goto          76
     113: iconst_0
     114: istore_2
     115: iload_2
     116: aload_0
     117: getfield      #8                  // Field enumType_:Ljava/util/List;
     120: invokeinterface #76,  1           // InterfaceMethod java/util/List.size:()I
     125: if_icmpge     152
     128: aload_1
     129: iconst_5
     130: aload_0
     131: getfield      #8                  // Field enumType_:Ljava/util/List;
     134: iload_2
     135: invokeinterface #77,  2           // InterfaceMethod java/util/List.get:(I)Ljava/lang/Object;
     140: checkcast     #107                // class com/google/protobuf/MessageLite
     143: invokevirtual #108                // Method com/google/protobuf/CodedOutputStream.writeMessage:(ILcom/google/protobuf/MessageLite;)V
     146: iinc          2, 1
     149: goto          115
     152: iconst_0
     153: istore_2
     154: iload_2
     155: aload_0
     156: getfield      #7                  // Field service_:Ljava/util/List;
     159: invokeinterface #76,  1           // InterfaceMethod java/util/List.size:()I
     164: if_icmpge     192
     167: aload_1
     168: bipush        6
     170: aload_0
     171: getfield      #7                  // Field service_:Ljava/util/List;
     174: iload_2
     175: invokeinterface #77,  2           // InterfaceMethod java/util/List.get:(I)Ljava/lang/Object;
     180: checkcast     #107                // class com/google/protobuf/MessageLite
     183: invokevirtual #108                // Method com/google/protobuf/CodedOutputStream.writeMessage:(ILcom/google/protobuf/MessageLite;)V
     186: iinc          2, 1
     189: goto          154
     192: iconst_0
     193: istore_2
     194: iload_2
     195: aload_0
     196: getfield      #6                  // Field extension_:Ljava/util/List;
     199: invokeinterface #76,  1           // InterfaceMethod java/util/List.size:()I
     204: if_icmpge     232
     207: aload_1
     208: bipush        7
     210: aload_0
     211: getfield      #6                  // Field extension_:Ljava/util/List;
     214: iload_2
     215: invokeinterface #77,  2           // InterfaceMethod java/util/List.get:(I)Ljava/lang/Object;
     220: checkcast     #107                // class com/google/protobuf/MessageLite
     223: invokevirtual #108                // Method com/google/protobuf/CodedOutputStream.writeMessage:(ILcom/google/protobuf/MessageLite;)V
     226: iinc          2, 1
     229: goto          194
     232: aload_0
     233: getfield      #2                  // Field bitField0_:I
     236: iconst_4
     237: iand
     238: iconst_4
     239: if_icmpne     252
     242: aload_1
     243: bipush        8
     245: aload_0
     246: invokevirtual #103                // Method getOptions:()Lcom/google/protobuf/DescriptorProtos$FileOptions;
     249: invokevirtual #108                // Method com/google/protobuf/CodedOutputStream.writeMessage:(ILcom/google/protobuf/MessageLite;)V
     252: aload_0
     253: getfield      #2                  // Field bitField0_:I
     256: bipush        8
     258: iand
     259: bipush        8
     261: if_icmpne     274
     264: aload_1
     265: bipush        9
     267: aload_0
     268: invokevirtual #109                // Method getSourceCodeInfo:()Lcom/google/protobuf/DescriptorProtos$SourceCodeInfo;
     271: invokevirtual #108                // Method com/google/protobuf/CodedOutputStream.writeMessage:(ILcom/google/protobuf/MessageLite;)V
     274: iconst_0
     275: istore_2
     276: iload_2
     277: aload_0
     278: getfield      #11                 // Field publicDependency_:Ljava/util/List;
     281: invokeinterface #76,  1           // InterfaceMethod java/util/List.size:()I
     286: if_icmpge     317
     289: aload_1
     290: bipush        10
     292: aload_0
     293: getfield      #11                 // Field publicDependency_:Ljava/util/List;
     296: iload_2
     297: invokeinterface #77,  2           // InterfaceMethod java/util/List.get:(I)Ljava/lang/Object;
     302: checkcast     #78                 // class java/lang/Integer
     305: invokevirtual #79                 // Method java/lang/Integer.intValue:()I
     308: invokevirtual #110                // Method com/google/protobuf/CodedOutputStream.writeInt32:(II)V
     311: iinc          2, 1
     314: goto          276
     317: iconst_0
     318: istore_2
     319: iload_2
     320: aload_0
     321: getfield      #10                 // Field weakDependency_:Ljava/util/List;
     324: invokeinterface #76,  1           // InterfaceMethod java/util/List.size:()I
     329: if_icmpge     360
     332: aload_1
     333: bipush        11
     335: aload_0
     336: getfield      #10                 // Field weakDependency_:Ljava/util/List;
     339: iload_2
     340: invokeinterface #77,  2           // InterfaceMethod java/util/List.get:(I)Ljava/lang/Object;
     345: checkcast     #78                 // class java/lang/Integer
     348: invokevirtual #79                 // Method java/lang/Integer.intValue:()I
     351: invokevirtual #110                // Method com/google/protobuf/CodedOutputStream.writeInt32:(II)V
     354: iinc          2, 1
     357: goto          319
     360: aload_0
     361: getfield      #2                  // Field bitField0_:I
     364: bipush        16
     366: iand
     367: bipush        16
     369: if_icmpne     382
     372: aload_1
     373: bipush        12
     375: aload_0
     376: getfield      #3                  // Field syntax_:Ljava/lang/Object;
     379: invokestatic  #105                // Method com/google/protobuf/GeneratedMessageV3.writeString:(Lcom/google/protobuf/CodedOutputStream;ILjava/lang/Object;)V
     382: aload_0
     383: getfield      #22                 // Field unknownFields:Lcom/google/protobuf/UnknownFieldSet;
     386: aload_1
     387: invokevirtual #111                // Method com/google/protobuf/UnknownFieldSet.writeTo:(Lcom/google/protobuf/CodedOutputStream;)V
     390: return

  public int getSerializedSize();
    Code:
       0: aload_0
       1: getfield      #112                // Field memoizedSize:I
       4: istore_1
       5: iload_1
       6: iconst_m1
       7: if_icmpeq     12
      10: iload_1
      11: ireturn
      12: iconst_0
      13: istore_1
      14: aload_0
      15: getfield      #2                  // Field bitField0_:I
      18: iconst_1
      19: iand
      20: iconst_1
      21: if_icmpne     35
      24: iload_1
      25: iconst_1
      26: aload_0
      27: getfield      #14                 // Field name_:Ljava/lang/Object;
      30: invokestatic  #113                // Method com/google/protobuf/GeneratedMessageV3.computeStringSize:(ILjava/lang/Object;)I
      33: iadd
      34: istore_1
      35: aload_0
      36: getfield      #2                  // Field bitField0_:I
      39: iconst_2
      40: iand
      41: iconst_2
      42: if_icmpne     56
      45: iload_1
      46: iconst_2
      47: aload_0
      48: getfield      #13                 // Field package_:Ljava/lang/Object;
      51: invokestatic  #113                // Method com/google/protobuf/GeneratedMessageV3.computeStringSize:(ILjava/lang/Object;)I
      54: iadd
      55: istore_1
      56: iconst_0
      57: istore_2
      58: iconst_0
      59: istore_3
      60: iload_3
      61: aload_0
      62: getfield      #12                 // Field dependency_:Lcom/google/protobuf/LazyStringList;
      65: invokeinterface #73,  1           // InterfaceMethod com/google/protobuf/LazyStringList.size:()I
      70: if_icmpge     95
      73: iload_2
      74: aload_0
      75: getfield      #12                 // Field dependency_:Lcom/google/protobuf/LazyStringList;
      78: iload_3
      79: invokeinterface #106,  2          // InterfaceMethod com/google/protobuf/LazyStringList.getRaw:(I)Ljava/lang/Object;
      84: invokestatic  #114                // Method computeStringSizeNoTag:(Ljava/lang/Object;)I
      87: iadd
      88: istore_2
      89: iinc          3, 1
      92: goto          60
      95: iload_1
      96: iload_2
      97: iadd
      98: istore_1
      99: iload_1
     100: iconst_1
     101: aload_0
     102: invokevirtual #115                // Method getDependencyList:()Lcom/google/protobuf/ProtocolStringList;
     105: invokeinterface #116,  1          // InterfaceMethod com/google/protobuf/ProtocolStringList.size:()I
     110: imul
     111: iadd
     112: istore_1
     113: iconst_0
     114: istore_2
     115: iload_2
     116: aload_0
     117: getfield      #9                  // Field messageType_:Ljava/util/List;
     120: invokeinterface #76,  1           // InterfaceMethod java/util/List.size:()I
     125: if_icmpge     154
     128: iload_1
     129: iconst_4
     130: aload_0
     131: getfield      #9                  // Field messageType_:Ljava/util/List;
     134: iload_2
     135: invokeinterface #77,  2           // InterfaceMethod java/util/List.get:(I)Ljava/lang/Object;
     140: checkcast     #107                // class com/google/protobuf/MessageLite
     143: invokestatic  #117                // Method com/google/protobuf/CodedOutputStream.computeMessageSize:(ILcom/google/protobuf/MessageLite;)I
     146: iadd
     147: istore_1
     148: iinc          2, 1
     151: goto          115
     154: iconst_0
     155: istore_2
     156: iload_2
     157: aload_0
     158: getfield      #8                  // Field enumType_:Ljava/util/List;
     161: invokeinterface #76,  1           // InterfaceMethod java/util/List.size:()I
     166: if_icmpge     195
     169: iload_1
     170: iconst_5
     171: aload_0
     172: getfield      #8                  // Field enumType_:Ljava/util/List;
     175: iload_2
     176: invokeinterface #77,  2           // InterfaceMethod java/util/List.get:(I)Ljava/lang/Object;
     181: checkcast     #107                // class com/google/protobuf/MessageLite
     184: invokestatic  #117                // Method com/google/protobuf/CodedOutputStream.computeMessageSize:(ILcom/google/protobuf/MessageLite;)I
     187: iadd
     188: istore_1
     189: iinc          2, 1
     192: goto          156
     195: iconst_0
     196: istore_2
     197: iload_2
     198: aload_0
     199: getfield      #7                  // Field service_:Ljava/util/List;
     202: invokeinterface #76,  1           // InterfaceMethod java/util/List.size:()I
     207: if_icmpge     237
     210: iload_1
     211: bipush        6
     213: aload_0
     214: getfield      #7                  // Field service_:Ljava/util/List;
     217: iload_2
     218: invokeinterface #77,  2           // InterfaceMethod java/util/List.get:(I)Ljava/lang/Object;
     223: checkcast     #107                // class com/google/protobuf/MessageLite
     226: invokestatic  #117                // Method com/google/protobuf/CodedOutputStream.computeMessageSize:(ILcom/google/protobuf/MessageLite;)I
     229: iadd
     230: istore_1
     231: iinc          2, 1
     234: goto          197
     237: iconst_0
     238: istore_2
     239: iload_2
     240: aload_0
     241: getfield      #6                  // Field extension_:Ljava/util/List;
     244: invokeinterface #76,  1           // InterfaceMethod java/util/List.size:()I
     249: if_icmpge     279
     252: iload_1
     253: bipush        7
     255: aload_0
     256: getfield      #6                  // Field extension_:Ljava/util/List;
     259: iload_2
     260: invokeinterface #77,  2           // InterfaceMethod java/util/List.get:(I)Ljava/lang/Object;
     265: checkcast     #107                // class com/google/protobuf/MessageLite
     268: invokestatic  #117                // Method com/google/protobuf/CodedOutputStream.computeMessageSize:(ILcom/google/protobuf/MessageLite;)I
     271: iadd
     272: istore_1
     273: iinc          2, 1
     276: goto          239
     279: aload_0
     280: getfield      #2                  // Field bitField0_:I
     283: iconst_4
     284: iand
     285: iconst_4
     286: if_icmpne     301
     289: iload_1
     290: bipush        8
     292: aload_0
     293: invokevirtual #103                // Method getOptions:()Lcom/google/protobuf/DescriptorProtos$FileOptions;
     296: invokestatic  #117                // Method com/google/protobuf/CodedOutputStream.computeMessageSize:(ILcom/google/protobuf/MessageLite;)I
     299: iadd
     300: istore_1
     301: aload_0
     302: getfield      #2                  // Field bitField0_:I
     305: bipush        8
     307: iand
     308: bipush        8
     310: if_icmpne     325
     313: iload_1
     314: bipush        9
     316: aload_0
     317: invokevirtual #109                // Method getSourceCodeInfo:()Lcom/google/protobuf/DescriptorProtos$SourceCodeInfo;
     320: invokestatic  #117                // Method com/google/protobuf/CodedOutputStream.computeMessageSize:(ILcom/google/protobuf/MessageLite;)I
     323: iadd
     324: istore_1
     325: iconst_0
     326: istore_2
     327: iconst_0
     328: istore_3
     329: iload_3
     330: aload_0
     331: getfield      #11                 // Field publicDependency_:Ljava/util/List;
     334: invokeinterface #76,  1           // InterfaceMethod java/util/List.size:()I
     339: if_icmpge     370
     342: iload_2
     343: aload_0
     344: getfield      #11                 // Field publicDependency_:Ljava/util/List;
     347: iload_3
     348: invokeinterface #77,  2           // InterfaceMethod java/util/List.get:(I)Ljava/lang/Object;
     353: checkcast     #78                 // class java/lang/Integer
     356: invokevirtual #79                 // Method java/lang/Integer.intValue:()I
     359: invokestatic  #118                // Method com/google/protobuf/CodedOutputStream.computeInt32SizeNoTag:(I)I
     362: iadd
     363: istore_2
     364: iinc          3, 1
     367: goto          329
     370: iload_1
     371: iload_2
     372: iadd
     373: istore_1
     374: iload_1
     375: iconst_1
     376: aload_0
     377: invokevirtual #119                // Method getPublicDependencyList:()Ljava/util/List;
     380: invokeinterface #76,  1           // InterfaceMethod java/util/List.size:()I
     385: imul
     386: iadd
     387: istore_1
     388: iconst_0
     389: istore_2
     390: iconst_0
     391: istore_3
     392: iload_3
     393: aload_0
     394: getfield      #10                 // Field weakDependency_:Ljava/util/List;
     397: invokeinterface #76,  1           // InterfaceMethod java/util/List.size:()I
     402: if_icmpge     433
     405: iload_2
     406: aload_0
     407: getfield      #10                 // Field weakDependency_:Ljava/util/List;
     410: iload_3
     411: invokeinterface #77,  2           // InterfaceMethod java/util/List.get:(I)Ljava/lang/Object;
     416: checkcast     #78                 // class java/lang/Integer
     419: invokevirtual #79                 // Method java/lang/Integer.intValue:()I
     422: invokestatic  #118                // Method com/google/protobuf/CodedOutputStream.computeInt32SizeNoTag:(I)I
     425: iadd
     426: istore_2
     427: iinc          3, 1
     430: goto          392
     433: iload_1
     434: iload_2
     435: iadd
     436: istore_1
     437: iload_1
     438: iconst_1
     439: aload_0
     440: invokevirtual #120                // Method getWeakDependencyList:()Ljava/util/List;
     443: invokeinterface #76,  1           // InterfaceMethod java/util/List.size:()I
     448: imul
     449: iadd
     450: istore_1
     451: aload_0
     452: getfield      #2                  // Field bitField0_:I
     455: bipush        16
     457: iand
     458: bipush        16
     460: if_icmpne     475
     463: iload_1
     464: bipush        12
     466: aload_0
     467: getfield      #3                  // Field syntax_:Ljava/lang/Object;
     470: invokestatic  #113                // Method com/google/protobuf/GeneratedMessageV3.computeStringSize:(ILjava/lang/Object;)I
     473: iadd
     474: istore_1
     475: iload_1
     476: aload_0
     477: getfield      #22                 // Field unknownFields:Lcom/google/protobuf/UnknownFieldSet;
     480: invokevirtual #121                // Method com/google/protobuf/UnknownFieldSet.getSerializedSize:()I
     483: iadd
     484: istore_1
     485: aload_0
     486: iload_1
     487: putfield      #112                // Field memoizedSize:I
     490: iload_1
     491: ireturn

  public boolean equals(java.lang.Object);
    Code:
       0: aload_1
       1: aload_0
       2: if_acmpne     7
       5: iconst_1
       6: ireturn
       7: aload_1
       8: instanceof    #65                 // class com/google/protobuf/DescriptorProtos$FileDescriptorProto
      11: ifne          20
      14: aload_0
      15: aload_1
      16: invokespecial #122                // Method com/google/protobuf/GeneratedMessageV3.equals:(Ljava/lang/Object;)Z
      19: ireturn
      20: aload_1
      21: checkcast     #65                 // class com/google/protobuf/DescriptorProtos$FileDescriptorProto
      24: astore_2
      25: iconst_1
      26: istore_3
      27: iload_3
      28: ifeq          46
      31: aload_0
      32: invokevirtual #123                // Method hasName:()Z
      35: aload_2
      36: invokevirtual #123                // Method hasName:()Z
      39: if_icmpne     46
      42: iconst_1
      43: goto          47
      46: iconst_0
      47: istore_3
      48: aload_0
      49: invokevirtual #123                // Method hasName:()Z
      52: ifeq          79
      55: iload_3
      56: ifeq          77
      59: aload_0
      60: invokevirtual #124                // Method getName:()Ljava/lang/String;
      63: aload_2
      64: invokevirtual #124                // Method getName:()Ljava/lang/String;
      67: invokevirtual #125                // Method java/lang/String.equals:(Ljava/lang/Object;)Z
      70: ifeq          77
      73: iconst_1
      74: goto          78
      77: iconst_0
      78: istore_3
      79: iload_3
      80: ifeq          98
      83: aload_0
      84: invokevirtual #126                // Method hasPackage:()Z
      87: aload_2
      88: invokevirtual #126                // Method hasPackage:()Z
      91: if_icmpne     98
      94: iconst_1
      95: goto          99
      98: iconst_0
      99: istore_3
     100: aload_0
     101: invokevirtual #126                // Method hasPackage:()Z
     104: ifeq          131
     107: iload_3
     108: ifeq          129
     111: aload_0
     112: invokevirtual #127                // Method getPackage:()Ljava/lang/String;
     115: aload_2
     116: invokevirtual #127                // Method getPackage:()Ljava/lang/String;
     119: invokevirtual #125                // Method java/lang/String.equals:(Ljava/lang/Object;)Z
     122: ifeq          129
     125: iconst_1
     126: goto          130
     129: iconst_0
     130: istore_3
     131: iload_3
     132: ifeq          153
     135: aload_0
     136: invokevirtual #115                // Method getDependencyList:()Lcom/google/protobuf/ProtocolStringList;
     139: aload_2
     140: invokevirtual #115                // Method getDependencyList:()Lcom/google/protobuf/ProtocolStringList;
     143: invokevirtual #128                // Method java/lang/Object.equals:(Ljava/lang/Object;)Z
     146: ifeq          153
     149: iconst_1
     150: goto          154
     153: iconst_0
     154: istore_3
     155: iload_3
     156: ifeq          179
     159: aload_0
     160: invokevirtual #119                // Method getPublicDependencyList:()Ljava/util/List;
     163: aload_2
     164: invokevirtual #119                // Method getPublicDependencyList:()Ljava/util/List;
     167: invokeinterface #129,  2          // InterfaceMethod java/util/List.equals:(Ljava/lang/Object;)Z
     172: ifeq          179
     175: iconst_1
     176: goto          180
     179: iconst_0
     180: istore_3
     181: iload_3
     182: ifeq          205
     185: aload_0
     186: invokevirtual #120                // Method getWeakDependencyList:()Ljava/util/List;
     189: aload_2
     190: invokevirtual #120                // Method getWeakDependencyList:()Ljava/util/List;
     193: invokeinterface #129,  2          // InterfaceMethod java/util/List.equals:(Ljava/lang/Object;)Z
     198: ifeq          205
     201: iconst_1
     202: goto          206
     205: iconst_0
     206: istore_3
     207: iload_3
     208: ifeq          231
     211: aload_0
     212: invokevirtual #130                // Method getMessageTypeList:()Ljava/util/List;
     215: aload_2
     216: invokevirtual #130                // Method getMessageTypeList:()Ljava/util/List;
     219: invokeinterface #129,  2          // InterfaceMethod java/util/List.equals:(Ljava/lang/Object;)Z
     224: ifeq          231
     227: iconst_1
     228: goto          232
     231: iconst_0
     232: istore_3
     233: iload_3
     234: ifeq          257
     237: aload_0
     238: invokevirtual #131                // Method getEnumTypeList:()Ljava/util/List;
     241: aload_2
     242: invokevirtual #131                // Method getEnumTypeList:()Ljava/util/List;
     245: invokeinterface #129,  2          // InterfaceMethod java/util/List.equals:(Ljava/lang/Object;)Z
     250: ifeq          257
     253: iconst_1
     254: goto          258
     257: iconst_0
     258: istore_3
     259: iload_3
     260: ifeq          283
     263: aload_0
     264: invokevirtual #132                // Method getServiceList:()Ljava/util/List;
     267: aload_2
     268: invokevirtual #132                // Method getServiceList:()Ljava/util/List;
     271: invokeinterface #129,  2          // InterfaceMethod java/util/List.equals:(Ljava/lang/Object;)Z
     276: ifeq          283
     279: iconst_1
     280: goto          284
     283: iconst_0
     284: istore_3
     285: iload_3
     286: ifeq          309
     289: aload_0
     290: invokevirtual #133                // Method getExtensionList:()Ljava/util/List;
     293: aload_2
     294: invokevirtual #133                // Method getExtensionList:()Ljava/util/List;
     297: invokeinterface #129,  2          // InterfaceMethod java/util/List.equals:(Ljava/lang/Object;)Z
     302: ifeq          309
     305: iconst_1
     306: goto          310
     309: iconst_0
     310: istore_3
     311: iload_3
     312: ifeq          330
     315: aload_0
     316: invokevirtual #102                // Method hasOptions:()Z
     319: aload_2
     320: invokevirtual #102                // Method hasOptions:()Z
     323: if_icmpne     330
     326: iconst_1
     327: goto          331
     330: iconst_0
     331: istore_3
     332: aload_0
     333: invokevirtual #102                // Method hasOptions:()Z
     336: ifeq          363
     339: iload_3
     340: ifeq          361
     343: aload_0
     344: invokevirtual #103                // Method getOptions:()Lcom/google/protobuf/DescriptorProtos$FileOptions;
     347: aload_2
     348: invokevirtual #103                // Method getOptions:()Lcom/google/protobuf/DescriptorProtos$FileOptions;
     351: invokevirtual #134                // Method com/google/protobuf/DescriptorProtos$FileOptions.equals:(Ljava/lang/Object;)Z
     354: ifeq          361
     357: iconst_1
     358: goto          362
     361: iconst_0
     362: istore_3
     363: iload_3
     364: ifeq          382
     367: aload_0
     368: invokevirtual #135                // Method hasSourceCodeInfo:()Z
     371: aload_2
     372: invokevirtual #135                // Method hasSourceCodeInfo:()Z
     375: if_icmpne     382
     378: iconst_1
     379: goto          383
     382: iconst_0
     383: istore_3
     384: aload_0
     385: invokevirtual #135                // Method hasSourceCodeInfo:()Z
     388: ifeq          415
     391: iload_3
     392: ifeq          413
     395: aload_0
     396: invokevirtual #109                // Method getSourceCodeInfo:()Lcom/google/protobuf/DescriptorProtos$SourceCodeInfo;
     399: aload_2
     400: invokevirtual #109                // Method getSourceCodeInfo:()Lcom/google/protobuf/DescriptorProtos$SourceCodeInfo;
     403: invokevirtual #136                // Method com/google/protobuf/DescriptorProtos$SourceCodeInfo.equals:(Ljava/lang/Object;)Z
     406: ifeq          413
     409: iconst_1
     410: goto          414
     413: iconst_0
     414: istore_3
     415: iload_3
     416: ifeq          434
     419: aload_0
     420: invokevirtual #137                // Method hasSyntax:()Z
     423: aload_2
     424: invokevirtual #137                // Method hasSyntax:()Z
     427: if_icmpne     434
     430: iconst_1
     431: goto          435
     434: iconst_0
     435: istore_3
     436: aload_0
     437: invokevirtual #137                // Method hasSyntax:()Z
     440: ifeq          467
     443: iload_3
     444: ifeq          465
     447: aload_0
     448: invokevirtual #138                // Method getSyntax:()Ljava/lang/String;
     451: aload_2
     452: invokevirtual #138                // Method getSyntax:()Ljava/lang/String;
     455: invokevirtual #125                // Method java/lang/String.equals:(Ljava/lang/Object;)Z
     458: ifeq          465
     461: iconst_1
     462: goto          466
     465: iconst_0
     466: istore_3
     467: iload_3
     468: ifeq          489
     471: aload_0
     472: getfield      #22                 // Field unknownFields:Lcom/google/protobuf/UnknownFieldSet;
     475: aload_2
     476: getfield      #22                 // Field unknownFields:Lcom/google/protobuf/UnknownFieldSet;
     479: invokevirtual #139                // Method com/google/protobuf/UnknownFieldSet.equals:(Ljava/lang/Object;)Z
     482: ifeq          489
     485: iconst_1
     486: goto          490
     489: iconst_0
     490: istore_3
     491: iload_3
     492: ireturn

  public int hashCode();
    Code:
       0: aload_0
       1: getfield      #140                // Field memoizedHashCode:I
       4: ifeq          12
       7: aload_0
       8: getfield      #140                // Field memoizedHashCode:I
      11: ireturn
      12: bipush        41
      14: istore_1
      15: bipush        19
      17: iload_1
      18: imul
      19: invokestatic  #141                // Method getDescriptor:()Lcom/google/protobuf/Descriptors$Descriptor;
      22: invokevirtual #142                // Method java/lang/Object.hashCode:()I
      25: iadd
      26: istore_1
      27: aload_0
      28: invokevirtual #123                // Method hasName:()Z
      31: ifeq          54
      34: bipush        37
      36: iload_1
      37: imul
      38: iconst_1
      39: iadd
      40: istore_1
      41: bipush        53
      43: iload_1
      44: imul
      45: aload_0
      46: invokevirtual #124                // Method getName:()Ljava/lang/String;
      49: invokevirtual #143                // Method java/lang/String.hashCode:()I
      52: iadd
      53: istore_1
      54: aload_0
      55: invokevirtual #126                // Method hasPackage:()Z
      58: ifeq          81
      61: bipush        37
      63: iload_1
      64: imul
      65: iconst_2
      66: iadd
      67: istore_1
      68: bipush        53
      70: iload_1
      71: imul
      72: aload_0
      73: invokevirtual #127                // Method getPackage:()Ljava/lang/String;
      76: invokevirtual #143                // Method java/lang/String.hashCode:()I
      79: iadd
      80: istore_1
      81: aload_0
      82: invokevirtual #144                // Method getDependencyCount:()I
      85: ifle          108
      88: bipush        37
      90: iload_1
      91: imul
      92: iconst_3
      93: iadd
      94: istore_1
      95: bipush        53
      97: iload_1
      98: imul
      99: aload_0
     100: invokevirtual #115                // Method getDependencyList:()Lcom/google/protobuf/ProtocolStringList;
     103: invokevirtual #142                // Method java/lang/Object.hashCode:()I
     106: iadd
     107: istore_1
     108: aload_0
     109: invokevirtual #145                // Method getPublicDependencyCount:()I
     112: ifle          138
     115: bipush        37
     117: iload_1
     118: imul
     119: bipush        10
     121: iadd
     122: istore_1
     123: bipush        53
     125: iload_1
     126: imul
     127: aload_0
     128: invokevirtual #119                // Method getPublicDependencyList:()Ljava/util/List;
     131: invokeinterface #146,  1          // InterfaceMethod java/util/List.hashCode:()I
     136: iadd
     137: istore_1
     138: aload_0
     139: invokevirtual #147                // Method getWeakDependencyCount:()I
     142: ifle          168
     145: bipush        37
     147: iload_1
     148: imul
     149: bipush        11
     151: iadd
     152: istore_1
     153: bipush        53
     155: iload_1
     156: imul
     157: aload_0
     158: invokevirtual #120                // Method getWeakDependencyList:()Ljava/util/List;
     161: invokeinterface #146,  1          // InterfaceMethod java/util/List.hashCode:()I
     166: iadd
     167: istore_1
     168: aload_0
     169: invokevirtual #90                 // Method getMessageTypeCount:()I
     172: ifle          197
     175: bipush        37
     177: iload_1
     178: imul
     179: iconst_4
     180: iadd
     181: istore_1
     182: bipush        53
     184: iload_1
     185: imul
     186: aload_0
     187: invokevirtual #130                // Method getMessageTypeList:()Ljava/util/List;
     190: invokeinterface #146,  1          // InterfaceMethod java/util/List.hashCode:()I
     195: iadd
     196: istore_1
     197: aload_0
     198: invokevirtual #93                 // Method getEnumTypeCount:()I
     201: ifle          226
     204: bipush        37
     206: iload_1
     207: imul
     208: iconst_5
     209: iadd
     210: istore_1
     211: bipush        53
     213: iload_1
     214: imul
     215: aload_0
     216: invokevirtual #131                // Method getEnumTypeList:()Ljava/util/List;
     219: invokeinterface #146,  1          // InterfaceMethod java/util/List.hashCode:()I
     224: iadd
     225: istore_1
     226: aload_0
     227: invokevirtual #96                 // Method getServiceCount:()I
     230: ifle          256
     233: bipush        37
     235: iload_1
     236: imul
     237: bipush        6
     239: iadd
     240: istore_1
     241: bipush        53
     243: iload_1
     244: imul
     245: aload_0
     246: invokevirtual #132                // Method getServiceList:()Ljava/util/List;
     249: invokeinterface #146,  1          // InterfaceMethod java/util/List.hashCode:()I
     254: iadd
     255: istore_1
     256: aload_0
     257: invokevirtual #99                 // Method getExtensionCount:()I
     260: ifle          286
     263: bipush        37
     265: iload_1
     266: imul
     267: bipush        7
     269: iadd
     270: istore_1
     271: bipush        53
     273: iload_1
     274: imul
     275: aload_0
     276: invokevirtual #133                // Method getExtensionList:()Ljava/util/List;
     279: invokeinterface #146,  1          // InterfaceMethod java/util/List.hashCode:()I
     284: iadd
     285: istore_1
     286: aload_0
     287: invokevirtual #102                // Method hasOptions:()Z
     290: ifeq          314
     293: bipush        37
     295: iload_1
     296: imul
     297: bipush        8
     299: iadd
     300: istore_1
     301: bipush        53
     303: iload_1
     304: imul
     305: aload_0
     306: invokevirtual #103                // Method getOptions:()Lcom/google/protobuf/DescriptorProtos$FileOptions;
     309: invokevirtual #148                // Method com/google/protobuf/DescriptorProtos$FileOptions.hashCode:()I
     312: iadd
     313: istore_1
     314: aload_0
     315: invokevirtual #135                // Method hasSourceCodeInfo:()Z
     318: ifeq          342
     321: bipush        37
     323: iload_1
     324: imul
     325: bipush        9
     327: iadd
     328: istore_1
     329: bipush        53
     331: iload_1
     332: imul
     333: aload_0
     334: invokevirtual #109                // Method getSourceCodeInfo:()Lcom/google/protobuf/DescriptorProtos$SourceCodeInfo;
     337: invokevirtual #149                // Method com/google/protobuf/DescriptorProtos$SourceCodeInfo.hashCode:()I
     340: iadd
     341: istore_1
     342: aload_0
     343: invokevirtual #137                // Method hasSyntax:()Z
     346: ifeq          370
     349: bipush        37
     351: iload_1
     352: imul
     353: bipush        12
     355: iadd
     356: istore_1
     357: bipush        53
     359: iload_1
     360: imul
     361: aload_0
     362: invokevirtual #138                // Method getSyntax:()Ljava/lang/String;
     365: invokevirtual #143                // Method java/lang/String.hashCode:()I
     368: iadd
     369: istore_1
     370: bipush        29
     372: iload_1
     373: imul
     374: aload_0
     375: getfield      #22                 // Field unknownFields:Lcom/google/protobuf/UnknownFieldSet;
     378: invokevirtual #150                // Method com/google/protobuf/UnknownFieldSet.hashCode:()I
     381: iadd
     382: istore_1
     383: aload_0
     384: iload_1
     385: putfield      #140                // Field memoizedHashCode:I
     388: iload_1
     389: ireturn

  public static com.google.protobuf.DescriptorProtos$FileDescriptorProto parseFrom(java.nio.ByteBuffer) throws com.google.protobuf.InvalidProtocolBufferException;
    Code:
       0: getstatic     #151                // Field PARSER:Lcom/google/protobuf/Parser;
       3: aload_0
       4: invokeinterface #152,  2          // InterfaceMethod com/google/protobuf/Parser.parseFrom:(Ljava/nio/ByteBuffer;)Ljava/lang/Object;
       9: checkcast     #65                 // class com/google/protobuf/DescriptorProtos$FileDescriptorProto
      12: areturn

  public static com.google.protobuf.DescriptorProtos$FileDescriptorProto parseFrom(java.nio.ByteBuffer, com.google.protobuf.ExtensionRegistryLite) throws com.google.protobuf.InvalidProtocolBufferException;
    Code:
       0: getstatic     #151                // Field PARSER:Lcom/google/protobuf/Parser;
       3: aload_0
       4: aload_1
       5: invokeinterface #153,  3          // InterfaceMethod com/google/protobuf/Parser.parseFrom:(Ljava/nio/ByteBuffer;Lcom/google/protobuf/ExtensionRegistryLite;)Ljava/lang/Object;
      10: checkcast     #65                 // class com/google/protobuf/DescriptorProtos$FileDescriptorProto
      13: areturn

  public static com.google.protobuf.DescriptorProtos$FileDescriptorProto parseFrom(com.google.protobuf.ByteString) throws com.google.protobuf.InvalidProtocolBufferException;
    Code:
       0: getstatic     #151                // Field PARSER:Lcom/google/protobuf/Parser;
       3: aload_0
       4: invokeinterface #154,  2          // InterfaceMethod com/google/protobuf/Parser.parseFrom:(Lcom/google/protobuf/ByteString;)Ljava/lang/Object;
       9: checkcast     #65                 // class com/google/protobuf/DescriptorProtos$FileDescriptorProto
      12: areturn

  public static com.google.protobuf.DescriptorProtos$FileDescriptorProto parseFrom(com.google.protobuf.ByteString, com.google.protobuf.ExtensionRegistryLite) throws com.google.protobuf.InvalidProtocolBufferException;
    Code:
       0: getstatic     #151                // Field PARSER:Lcom/google/protobuf/Parser;
       3: aload_0
       4: aload_1
       5: invokeinterface #155,  3          // InterfaceMethod com/google/protobuf/Parser.parseFrom:(Lcom/google/protobuf/ByteString;Lcom/google/protobuf/ExtensionRegistryLite;)Ljava/lang/Object;
      10: checkcast     #65                 // class com/google/protobuf/DescriptorProtos$FileDescriptorProto
      13: areturn

  public static com.google.protobuf.DescriptorProtos$FileDescriptorProto parseFrom(byte[]) throws com.google.protobuf.InvalidProtocolBufferException;
    Code:
       0: getstatic     #151                // Field PARSER:Lcom/google/protobuf/Parser;
       3: aload_0
       4: invokeinterface #156,  2          // InterfaceMethod com/google/protobuf/Parser.parseFrom:([B)Ljava/lang/Object;
       9: checkcast     #65                 // class com/google/protobuf/DescriptorProtos$FileDescriptorProto
      12: areturn

  public static com.google.protobuf.DescriptorProtos$FileDescriptorProto parseFrom(byte[], com.google.protobuf.ExtensionRegistryLite) throws com.google.protobuf.InvalidProtocolBufferException;
    Code:
       0: getstatic     #151                // Field PARSER:Lcom/google/protobuf/Parser;
       3: aload_0
       4: aload_1
       5: invokeinterface #157,  3          // InterfaceMethod com/google/protobuf/Parser.parseFrom:([BLcom/google/protobuf/ExtensionRegistryLite;)Ljava/lang/Object;
      10: checkcast     #65                 // class com/google/protobuf/DescriptorProtos$FileDescriptorProto
      13: areturn

  public static com.google.protobuf.DescriptorProtos$FileDescriptorProto parseFrom(java.io.InputStream) throws java.io.IOException;
    Code:
       0: getstatic     #151                // Field PARSER:Lcom/google/protobuf/Parser;
       3: aload_0
       4: invokestatic  #158                // Method com/google/protobuf/GeneratedMessageV3.parseWithIOException:(Lcom/google/protobuf/Parser;Ljava/io/InputStream;)Lcom/google/protobuf/Message;
       7: checkcast     #65                 // class com/google/protobuf/DescriptorProtos$FileDescriptorProto
      10: areturn

  public static com.google.protobuf.DescriptorProtos$FileDescriptorProto parseFrom(java.io.InputStream, com.google.protobuf.ExtensionRegistryLite) throws java.io.IOException;
    Code:
       0: getstatic     #151                // Field PARSER:Lcom/google/protobuf/Parser;
       3: aload_0
       4: aload_1
       5: invokestatic  #159                // Method com/google/protobuf/GeneratedMessageV3.parseWithIOException:(Lcom/google/protobuf/Parser;Ljava/io/InputStream;Lcom/google/protobuf/ExtensionRegistryLite;)Lcom/google/protobuf/Message;
       8: checkcast     #65                 // class com/google/protobuf/DescriptorProtos$FileDescriptorProto
      11: areturn

  public static com.google.protobuf.DescriptorProtos$FileDescriptorProto parseDelimitedFrom(java.io.InputStream) throws java.io.IOException;
    Code:
       0: getstatic     #151                // Field PARSER:Lcom/google/protobuf/Parser;
       3: aload_0
       4: invokestatic  #160                // Method com/google/protobuf/GeneratedMessageV3.parseDelimitedWithIOException:(Lcom/google/protobuf/Parser;Ljava/io/InputStream;)Lcom/google/protobuf/Message;
       7: checkcast     #65                 // class com/google/protobuf/DescriptorProtos$FileDescriptorProto
      10: areturn

  public static com.google.protobuf.DescriptorProtos$FileDescriptorProto parseDelimitedFrom(java.io.InputStream, com.google.protobuf.ExtensionRegistryLite) throws java.io.IOException;
    Code:
       0: getstatic     #151                // Field PARSER:Lcom/google/protobuf/Parser;
       3: aload_0
       4: aload_1
       5: invokestatic  #161                // Method com/google/protobuf/GeneratedMessageV3.parseDelimitedWithIOException:(Lcom/google/protobuf/Parser;Ljava/io/InputStream;Lcom/google/protobuf/ExtensionRegistryLite;)Lcom/google/protobuf/Message;
       8: checkcast     #65                 // class com/google/protobuf/DescriptorProtos$FileDescriptorProto
      11: areturn

  public static com.google.protobuf.DescriptorProtos$FileDescriptorProto parseFrom(com.google.protobuf.CodedInputStream) throws java.io.IOException;
    Code:
       0: getstatic     #151                // Field PARSER:Lcom/google/protobuf/Parser;
       3: aload_0
       4: invokestatic  #162                // Method com/google/protobuf/GeneratedMessageV3.parseWithIOException:(Lcom/google/protobuf/Parser;Lcom/google/protobuf/CodedInputStream;)Lcom/google/protobuf/Message;
       7: checkcast     #65                 // class com/google/protobuf/DescriptorProtos$FileDescriptorProto
      10: areturn

  public static com.google.protobuf.DescriptorProtos$FileDescriptorProto parseFrom(com.google.protobuf.CodedInputStream, com.google.protobuf.ExtensionRegistryLite) throws java.io.IOException;
    Code:
       0: getstatic     #151                // Field PARSER:Lcom/google/protobuf/Parser;
       3: aload_0
       4: aload_1
       5: invokestatic  #163                // Method com/google/protobuf/GeneratedMessageV3.parseWithIOException:(Lcom/google/protobuf/Parser;Lcom/google/protobuf/CodedInputStream;Lcom/google/protobuf/ExtensionRegistryLite;)Lcom/google/protobuf/Message;
       8: checkcast     #65                 // class com/google/protobuf/DescriptorProtos$FileDescriptorProto
      11: areturn

  public com.google.protobuf.DescriptorProtos$FileDescriptorProto$Builder newBuilderForType();
    Code:
       0: invokestatic  #164                // Method newBuilder:()Lcom/google/protobuf/DescriptorProtos$FileDescriptorProto$Builder;
       3: areturn

  public static com.google.protobuf.DescriptorProtos$FileDescriptorProto$Builder newBuilder();
    Code:
       0: getstatic     #165                // Field DEFAULT_INSTANCE:Lcom/google/protobuf/DescriptorProtos$FileDescriptorProto;
       3: invokevirtual #166                // Method toBuilder:()Lcom/google/protobuf/DescriptorProtos$FileDescriptorProto$Builder;
       6: areturn

  public static com.google.protobuf.DescriptorProtos$FileDescriptorProto$Builder newBuilder(com.google.protobuf.DescriptorProtos$FileDescriptorProto);
    Code:
       0: getstatic     #165                // Field DEFAULT_INSTANCE:Lcom/google/protobuf/DescriptorProtos$FileDescriptorProto;
       3: invokevirtual #166                // Method toBuilder:()Lcom/google/protobuf/DescriptorProtos$FileDescriptorProto$Builder;
       6: aload_0
       7: invokevirtual #167                // Method com/google/protobuf/DescriptorProtos$FileDescriptorProto$Builder.mergeFrom:(Lcom/google/protobuf/DescriptorProtos$FileDescriptorProto;)Lcom/google/protobuf/DescriptorProtos$FileDescriptorProto$Builder;
      10: areturn

  public com.google.protobuf.DescriptorProtos$FileDescriptorProto$Builder toBuilder();
    Code:
       0: aload_0
       1: getstatic     #165                // Field DEFAULT_INSTANCE:Lcom/google/protobuf/DescriptorProtos$FileDescriptorProto;
       4: if_acmpne     18
       7: new           #66                 // class com/google/protobuf/DescriptorProtos$FileDescriptorProto$Builder
      10: dup
      11: aconst_null
      12: invokespecial #168                // Method com/google/protobuf/DescriptorProtos$FileDescriptorProto$Builder."<init>":(Lcom/google/protobuf/DescriptorProtos$1;)V
      15: goto          30
      18: new           #66                 // class com/google/protobuf/DescriptorProtos$FileDescriptorProto$Builder
      21: dup
      22: aconst_null
      23: invokespecial #168                // Method com/google/protobuf/DescriptorProtos$FileDescriptorProto$Builder."<init>":(Lcom/google/protobuf/DescriptorProtos$1;)V
      26: aload_0
      27: invokevirtual #167                // Method com/google/protobuf/DescriptorProtos$FileDescriptorProto$Builder.mergeFrom:(Lcom/google/protobuf/DescriptorProtos$FileDescriptorProto;)Lcom/google/protobuf/DescriptorProtos$FileDescriptorProto$Builder;
      30: areturn

  protected com.google.protobuf.DescriptorProtos$FileDescriptorProto$Builder newBuilderForType(com.google.protobuf.GeneratedMessageV3$BuilderParent);
    Code:
       0: new           #66                 // class com/google/protobuf/DescriptorProtos$FileDescriptorProto$Builder
       3: dup
       4: aload_1
       5: aconst_null
       6: invokespecial #169                // Method com/google/protobuf/DescriptorProtos$FileDescriptorProto$Builder."<init>":(Lcom/google/protobuf/GeneratedMessageV3$BuilderParent;Lcom/google/protobuf/DescriptorProtos$1;)V
       9: astore_2
      10: aload_2
      11: areturn

  public static com.google.protobuf.DescriptorProtos$FileDescriptorProto getDefaultInstance();
    Code:
       0: getstatic     #165                // Field DEFAULT_INSTANCE:Lcom/google/protobuf/DescriptorProtos$FileDescriptorProto;
       3: areturn

  public static com.google.protobuf.Parser<com.google.protobuf.DescriptorProtos$FileDescriptorProto> parser();
    Code:
       0: getstatic     #151                // Field PARSER:Lcom/google/protobuf/Parser;
       3: areturn

  public com.google.protobuf.Parser<com.google.protobuf.DescriptorProtos$FileDescriptorProto> getParserForType();
    Code:
       0: getstatic     #151                // Field PARSER:Lcom/google/protobuf/Parser;
       3: areturn

  public com.google.protobuf.DescriptorProtos$FileDescriptorProto getDefaultInstanceForType();
    Code:
       0: getstatic     #165                // Field DEFAULT_INSTANCE:Lcom/google/protobuf/DescriptorProtos$FileDescriptorProto;
       3: areturn

  protected com.google.protobuf.Message$Builder newBuilderForType(com.google.protobuf.GeneratedMessageV3$BuilderParent);
    Code:
       0: aload_0
       1: aload_1
       2: invokevirtual #170                // Method newBuilderForType:(Lcom/google/protobuf/GeneratedMessageV3$BuilderParent;)Lcom/google/protobuf/DescriptorProtos$FileDescriptorProto$Builder;
       5: areturn

  public com.google.protobuf.Message$Builder toBuilder();
    Code:
       0: aload_0
       1: invokevirtual #166                // Method toBuilder:()Lcom/google/protobuf/DescriptorProtos$FileDescriptorProto$Builder;
       4: areturn

  public com.google.protobuf.Message$Builder newBuilderForType();
    Code:
       0: aload_0
       1: invokevirtual #171                // Method newBuilderForType:()Lcom/google/protobuf/DescriptorProtos$FileDescriptorProto$Builder;
       4: areturn

  public com.google.protobuf.MessageLite$Builder toBuilder();
    Code:
       0: aload_0
       1: invokevirtual #166                // Method toBuilder:()Lcom/google/protobuf/DescriptorProtos$FileDescriptorProto$Builder;
       4: areturn

  public com.google.protobuf.MessageLite$Builder newBuilderForType();
    Code:
       0: aload_0
       1: invokevirtual #171                // Method newBuilderForType:()Lcom/google/protobuf/DescriptorProtos$FileDescriptorProto$Builder;
       4: areturn

  public com.google.protobuf.MessageLite getDefaultInstanceForType();
    Code:
       0: aload_0
       1: invokevirtual #172                // Method getDefaultInstanceForType:()Lcom/google/protobuf/DescriptorProtos$FileDescriptorProto;
       4: areturn

  public com.google.protobuf.Message getDefaultInstanceForType();
    Code:
       0: aload_0
       1: invokevirtual #172                // Method getDefaultInstanceForType:()Lcom/google/protobuf/DescriptorProtos$FileDescriptorProto;
       4: areturn

  public java.util.List getDependencyList();
    Code:
       0: aload_0
       1: invokevirtual #115                // Method getDependencyList:()Lcom/google/protobuf/ProtocolStringList;
       4: areturn

  com.google.protobuf.DescriptorProtos$FileDescriptorProto(com.google.protobuf.GeneratedMessageV3$Builder, com.google.protobuf.DescriptorProtos$1);
    Code:
       0: aload_0
       1: aload_1
       2: invokespecial #15                 // Method "<init>":(Lcom/google/protobuf/GeneratedMessageV3$Builder;)V
       5: return

  static java.lang.Object access$1202(com.google.protobuf.DescriptorProtos$FileDescriptorProto, java.lang.Object);
    Code:
       0: aload_0
       1: aload_1
       2: dup_x1
       3: putfield      #14                 // Field name_:Ljava/lang/Object;
       6: areturn

  static java.lang.Object access$1302(com.google.protobuf.DescriptorProtos$FileDescriptorProto, java.lang.Object);
    Code:
       0: aload_0
       1: aload_1
       2: dup_x1
       3: putfield      #13                 // Field package_:Ljava/lang/Object;
       6: areturn

  static com.google.protobuf.LazyStringList access$1402(com.google.protobuf.DescriptorProtos$FileDescriptorProto, com.google.protobuf.LazyStringList);
    Code:
       0: aload_0
       1: aload_1
       2: dup_x1
       3: putfield      #12                 // Field dependency_:Lcom/google/protobuf/LazyStringList;
       6: areturn

  static java.util.List access$1502(com.google.protobuf.DescriptorProtos$FileDescriptorProto, java.util.List);
    Code:
       0: aload_0
       1: aload_1
       2: dup_x1
       3: putfield      #11                 // Field publicDependency_:Ljava/util/List;
       6: areturn

  static java.util.List access$1602(com.google.protobuf.DescriptorProtos$FileDescriptorProto, java.util.List);
    Code:
       0: aload_0
       1: aload_1
       2: dup_x1
       3: putfield      #10                 // Field weakDependency_:Ljava/util/List;
       6: areturn

  static java.util.List access$1702(com.google.protobuf.DescriptorProtos$FileDescriptorProto, java.util.List);
    Code:
       0: aload_0
       1: aload_1
       2: dup_x1
       3: putfield      #9                  // Field messageType_:Ljava/util/List;
       6: areturn

  static java.util.List access$1802(com.google.protobuf.DescriptorProtos$FileDescriptorProto, java.util.List);
    Code:
       0: aload_0
       1: aload_1
       2: dup_x1
       3: putfield      #8                  // Field enumType_:Ljava/util/List;
       6: areturn

  static java.util.List access$1902(com.google.protobuf.DescriptorProtos$FileDescriptorProto, java.util.List);
    Code:
       0: aload_0
       1: aload_1
       2: dup_x1
       3: putfield      #7                  // Field service_:Ljava/util/List;
       6: areturn

  static java.util.List access$2002(com.google.protobuf.DescriptorProtos$FileDescriptorProto, java.util.List);
    Code:
       0: aload_0
       1: aload_1
       2: dup_x1
       3: putfield      #6                  // Field extension_:Ljava/util/List;
       6: areturn

  static com.google.protobuf.DescriptorProtos$FileOptions access$2102(com.google.protobuf.DescriptorProtos$FileDescriptorProto, com.google.protobuf.DescriptorProtos$FileOptions);
    Code:
       0: aload_0
       1: aload_1
       2: dup_x1
       3: putfield      #5                  // Field options_:Lcom/google/protobuf/DescriptorProtos$FileOptions;
       6: areturn

  static com.google.protobuf.DescriptorProtos$SourceCodeInfo access$2202(com.google.protobuf.DescriptorProtos$FileDescriptorProto, com.google.protobuf.DescriptorProtos$SourceCodeInfo);
    Code:
       0: aload_0
       1: aload_1
       2: dup_x1
       3: putfield      #4                  // Field sourceCodeInfo_:Lcom/google/protobuf/DescriptorProtos$SourceCodeInfo;
       6: areturn

  static java.lang.Object access$2302(com.google.protobuf.DescriptorProtos$FileDescriptorProto, java.lang.Object);
    Code:
       0: aload_0
       1: aload_1
       2: dup_x1
       3: putfield      #3                  // Field syntax_:Ljava/lang/Object;
       6: areturn

  static int access$2402(com.google.protobuf.DescriptorProtos$FileDescriptorProto, int);
    Code:
       0: aload_0
       1: iload_1
       2: dup_x1
       3: putfield      #2                  // Field bitField0_:I
       6: ireturn

  static java.lang.Object access$1200(com.google.protobuf.DescriptorProtos$FileDescriptorProto);
    Code:
       0: aload_0
       1: getfield      #14                 // Field name_:Ljava/lang/Object;
       4: areturn

  static java.lang.Object access$1300(com.google.protobuf.DescriptorProtos$FileDescriptorProto);
    Code:
       0: aload_0
       1: getfield      #13                 // Field package_:Ljava/lang/Object;
       4: areturn

  static com.google.protobuf.LazyStringList access$1400(com.google.protobuf.DescriptorProtos$FileDescriptorProto);
    Code:
       0: aload_0
       1: getfield      #12                 // Field dependency_:Lcom/google/protobuf/LazyStringList;
       4: areturn

  static java.util.List access$1500(com.google.protobuf.DescriptorProtos$FileDescriptorProto);
    Code:
       0: aload_0
       1: getfield      #11                 // Field publicDependency_:Ljava/util/List;
       4: areturn

  static java.util.List access$1600(com.google.protobuf.DescriptorProtos$FileDescriptorProto);
    Code:
       0: aload_0
       1: getfield      #10                 // Field weakDependency_:Ljava/util/List;
       4: areturn

  static java.util.List access$1700(com.google.protobuf.DescriptorProtos$FileDescriptorProto);
    Code:
       0: aload_0
       1: getfield      #9                  // Field messageType_:Ljava/util/List;
       4: areturn

  static java.util.List access$1800(com.google.protobuf.DescriptorProtos$FileDescriptorProto);
    Code:
       0: aload_0
       1: getfield      #8                  // Field enumType_:Ljava/util/List;
       4: areturn

  static java.util.List access$1900(com.google.protobuf.DescriptorProtos$FileDescriptorProto);
    Code:
       0: aload_0
       1: getfield      #7                  // Field service_:Ljava/util/List;
       4: areturn

  static java.util.List access$2000(com.google.protobuf.DescriptorProtos$FileDescriptorProto);
    Code:
       0: aload_0
       1: getfield      #6                  // Field extension_:Ljava/util/List;
       4: areturn

  static java.lang.Object access$2300(com.google.protobuf.DescriptorProtos$FileDescriptorProto);
    Code:
       0: aload_0
       1: getfield      #3                  // Field syntax_:Ljava/lang/Object;
       4: areturn

  com.google.protobuf.DescriptorProtos$FileDescriptorProto(com.google.protobuf.CodedInputStream, com.google.protobuf.ExtensionRegistryLite, com.google.protobuf.DescriptorProtos$1) throws com.google.protobuf.InvalidProtocolBufferException;
    Code:
       0: aload_0
       1: aload_1
       2: aload_2
       3: invokespecial #1                  // Method "<init>":(Lcom/google/protobuf/CodedInputStream;Lcom/google/protobuf/ExtensionRegistryLite;)V
       6: return

  static {};
    Code:
       0: new           #65                 // class com/google/protobuf/DescriptorProtos$FileDescriptorProto
       3: dup
       4: invokespecial #23                 // Method "<init>":()V
       7: putstatic     #165                // Field DEFAULT_INSTANCE:Lcom/google/protobuf/DescriptorProtos$FileDescriptorProto;
      10: new           #173                // class com/google/protobuf/DescriptorProtos$FileDescriptorProto$1
      13: dup
      14: invokespecial #174                // Method com/google/protobuf/DescriptorProtos$FileDescriptorProto$1."<init>":()V
      17: putstatic     #151                // Field PARSER:Lcom/google/protobuf/Parser;
      20: return
}
