Compiled from "RpcUtil.java"
public final class com.google.protobuf.RpcUtil {
  private com.google.protobuf.RpcUtil();
    Code:
       0: aload_0
       1: invokespecial #2                  // Method java/lang/Object."<init>":()V
       4: return

  public static <Type extends com.google.protobuf.Message> com.google.protobuf.RpcCallback<Type> specializeCallback(com.google.protobuf.RpcCallback<com.google.protobuf.Message>);
    Code:
       0: aload_0
       1: areturn

  public static <Type extends com.google.protobuf.Message> com.google.protobuf.RpcCallback<com.google.protobuf.Message> generalizeCallback(com.google.protobuf.RpcCallback<Type>, java.lang.Class<Type>, Type);
    Code:
       0: new           #3                  // class com/google/protobuf/RpcUtil$1
       3: dup
       4: aload_1
       5: aload_2
       6: aload_0
       7: invokespecial #4                  // Method com/google/protobuf/RpcUtil$1."<init>":(Ljava/lang/Class;Lcom/google/protobuf/Message;Lcom/google/protobuf/RpcCallback;)V
      10: areturn

  private static <Type extends com.google.protobuf.Message> Type copyAsType(Type, com.google.protobuf.Message);
    Code:
       0: aload_0
       1: invokeinterface #5,  1            // InterfaceMethod com/google/protobuf/Message.newBuilderForType:()Lcom/google/protobuf/Message$Builder;
       6: aload_1
       7: invokeinterface #6,  2            // InterfaceMethod com/google/protobuf/Message$Builder.mergeFrom:(Lcom/google/protobuf/Message;)Lcom/google/protobuf/Message$Builder;
      12: invokeinterface #7,  1            // InterfaceMethod com/google/protobuf/Message$Builder.build:()Lcom/google/protobuf/Message;
      17: areturn

  public static <ParameterType> com.google.protobuf.RpcCallback<ParameterType> newOneTimeCallback(com.google.protobuf.RpcCallback<ParameterType>);
    Code:
       0: new           #8                  // class com/google/protobuf/RpcUtil$2
       3: dup
       4: aload_0
       5: invokespecial #9                  // Method com/google/protobuf/RpcUtil$2."<init>":(Lcom/google/protobuf/RpcCallback;)V
       8: areturn

  static com.google.protobuf.Message access$000(com.google.protobuf.Message, com.google.protobuf.Message);
    Code:
       0: aload_0
       1: aload_1
       2: invokestatic  #1                  // Method copyAsType:(Lcom/google/protobuf/Message;Lcom/google/protobuf/Message;)Lcom/google/protobuf/Message;
       5: areturn
}
