Compiled from "Struct.java"
public final class com.google.protobuf.Struct$Builder extends com.google.protobuf.GeneratedMessageV3$Builder<com.google.protobuf.Struct$Builder> implements com.google.protobuf.StructOrBuilder {
  private int bitField0_;

  private com.google.protobuf.MapField<java.lang.String, com.google.protobuf.Value> fields_;

  public static final com.google.protobuf.Descriptors$Descriptor getDescriptor();
    Code:
       0: getstatic     #3                  // Field com/google/protobuf/StructProto.internal_static_google_protobuf_Struct_descriptor:Lcom/google/protobuf/Descriptors$Descriptor;
       3: areturn

  protected com.google.protobuf.MapField internalGetMapField(int);
    Code:
       0: iload_1
       1: lookupswitch  { // 1
                     1: 20
               default: 25
          }
      20: aload_0
      21: invokespecial #4                  // Method internalGetFields:()Lcom/google/protobuf/MapField;
      24: areturn
      25: new           #5                  // class java/lang/RuntimeException
      28: dup
      29: new           #6                  // class java/lang/StringBuilder
      32: dup
      33: invokespecial #7                  // Method java/lang/StringBuilder."<init>":()V
      36: ldc           #8                  // String Invalid map field number:
      38: invokevirtual #9                  // Method java/lang/StringBuilder.append:(Ljava/lang/String;)Ljava/lang/StringBuilder;
      41: iload_1
      42: invokevirtual #10                 // Method java/lang/StringBuilder.append:(I)Ljava/lang/StringBuilder;
      45: invokevirtual #11                 // Method java/lang/StringBuilder.toString:()Ljava/lang/String;
      48: invokespecial #12                 // Method java/lang/RuntimeException."<init>":(Ljava/lang/String;)V
      51: athrow

  protected com.google.protobuf.MapField internalGetMutableMapField(int);
    Code:
       0: iload_1
       1: lookupswitch  { // 1
                     1: 20
               default: 25
          }
      20: aload_0
      21: invokespecial #13                 // Method internalGetMutableFields:()Lcom/google/protobuf/MapField;
      24: areturn
      25: new           #5                  // class java/lang/RuntimeException
      28: dup
      29: new           #6                  // class java/lang/StringBuilder
      32: dup
      33: invokespecial #7                  // Method java/lang/StringBuilder."<init>":()V
      36: ldc           #8                  // String Invalid map field number:
      38: invokevirtual #9                  // Method java/lang/StringBuilder.append:(Ljava/lang/String;)Ljava/lang/StringBuilder;
      41: iload_1
      42: invokevirtual #10                 // Method java/lang/StringBuilder.append:(I)Ljava/lang/StringBuilder;
      45: invokevirtual #11                 // Method java/lang/StringBuilder.toString:()Ljava/lang/String;
      48: invokespecial #12                 // Method java/lang/RuntimeException."<init>":(Ljava/lang/String;)V
      51: athrow

  protected com.google.protobuf.GeneratedMessageV3$FieldAccessorTable internalGetFieldAccessorTable();
    Code:
       0: getstatic     #14                 // Field com/google/protobuf/StructProto.internal_static_google_protobuf_Struct_fieldAccessorTable:Lcom/google/protobuf/GeneratedMessageV3$FieldAccessorTable;
       3: ldc           #15                 // class com/google/protobuf/Struct
       5: ldc           #16                 // class com/google/protobuf/Struct$Builder
       7: invokevirtual #17                 // Method com/google/protobuf/GeneratedMessageV3$FieldAccessorTable.ensureFieldAccessorsInitialized:(Ljava/lang/Class;Ljava/lang/Class;)Lcom/google/protobuf/GeneratedMessageV3$FieldAccessorTable;
      10: areturn

  private com.google.protobuf.Struct$Builder();
    Code:
       0: aload_0
       1: invokespecial #18                 // Method com/google/protobuf/GeneratedMessageV3$Builder."<init>":()V
       4: aload_0
       5: invokespecial #19                 // Method maybeForceBuilderInitialization:()V
       8: return

  private com.google.protobuf.Struct$Builder(com.google.protobuf.GeneratedMessageV3$BuilderParent);
    Code:
       0: aload_0
       1: aload_1
       2: invokespecial #20                 // Method com/google/protobuf/GeneratedMessageV3$Builder."<init>":(Lcom/google/protobuf/GeneratedMessageV3$BuilderParent;)V
       5: aload_0
       6: invokespecial #19                 // Method maybeForceBuilderInitialization:()V
       9: return

  private void maybeForceBuilderInitialization();
    Code:
       0: getstatic     #21                 // Field com/google/protobuf/GeneratedMessageV3.alwaysUseFieldBuilders:Z
       3: ifeq          6
       6: return

  public com.google.protobuf.Struct$Builder clear();
    Code:
       0: aload_0
       1: invokespecial #22                 // Method com/google/protobuf/GeneratedMessageV3$Builder.clear:()Lcom/google/protobuf/GeneratedMessageV3$Builder;
       4: pop
       5: aload_0
       6: invokespecial #13                 // Method internalGetMutableFields:()Lcom/google/protobuf/MapField;
       9: invokevirtual #23                 // Method com/google/protobuf/MapField.clear:()V
      12: aload_0
      13: areturn

  public com.google.protobuf.Descriptors$Descriptor getDescriptorForType();
    Code:
       0: getstatic     #3                  // Field com/google/protobuf/StructProto.internal_static_google_protobuf_Struct_descriptor:Lcom/google/protobuf/Descriptors$Descriptor;
       3: areturn

  public com.google.protobuf.Struct getDefaultInstanceForType();
    Code:
       0: invokestatic  #24                 // Method com/google/protobuf/Struct.getDefaultInstance:()Lcom/google/protobuf/Struct;
       3: areturn

  public com.google.protobuf.Struct build();
    Code:
       0: aload_0
       1: invokevirtual #25                 // Method buildPartial:()Lcom/google/protobuf/Struct;
       4: astore_1
       5: aload_1
       6: invokevirtual #26                 // Method com/google/protobuf/Struct.isInitialized:()Z
       9: ifne          17
      12: aload_1
      13: invokestatic  #27                 // Method newUninitializedMessageException:(Lcom/google/protobuf/Message;)Lcom/google/protobuf/UninitializedMessageException;
      16: athrow
      17: aload_1
      18: areturn

  public com.google.protobuf.Struct buildPartial();
    Code:
       0: new           #15                 // class com/google/protobuf/Struct
       3: dup
       4: aload_0
       5: aconst_null
       6: invokespecial #28                 // Method com/google/protobuf/Struct."<init>":(Lcom/google/protobuf/GeneratedMessageV3$Builder;Lcom/google/protobuf/Struct$1;)V
       9: astore_1
      10: aload_0
      11: getfield      #29                 // Field bitField0_:I
      14: istore_2
      15: aload_1
      16: aload_0
      17: invokespecial #4                  // Method internalGetFields:()Lcom/google/protobuf/MapField;
      20: invokestatic  #30                 // Method com/google/protobuf/Struct.access$302:(Lcom/google/protobuf/Struct;Lcom/google/protobuf/MapField;)Lcom/google/protobuf/MapField;
      23: pop
      24: aload_1
      25: invokestatic  #31                 // Method com/google/protobuf/Struct.access$300:(Lcom/google/protobuf/Struct;)Lcom/google/protobuf/MapField;
      28: invokevirtual #32                 // Method com/google/protobuf/MapField.makeImmutable:()V
      31: aload_0
      32: invokevirtual #33                 // Method onBuilt:()V
      35: aload_1
      36: areturn

  public com.google.protobuf.Struct$Builder clone();
    Code:
       0: aload_0
       1: invokespecial #34                 // Method com/google/protobuf/GeneratedMessageV3$Builder.clone:()Lcom/google/protobuf/GeneratedMessageV3$Builder;
       4: checkcast     #16                 // class com/google/protobuf/Struct$Builder
       7: areturn

  public com.google.protobuf.Struct$Builder setField(com.google.protobuf.Descriptors$FieldDescriptor, java.lang.Object);
    Code:
       0: aload_0
       1: aload_1
       2: aload_2
       3: invokespecial #35                 // Method com/google/protobuf/GeneratedMessageV3$Builder.setField:(Lcom/google/protobuf/Descriptors$FieldDescriptor;Ljava/lang/Object;)Lcom/google/protobuf/GeneratedMessageV3$Builder;
       6: checkcast     #16                 // class com/google/protobuf/Struct$Builder
       9: areturn

  public com.google.protobuf.Struct$Builder clearField(com.google.protobuf.Descriptors$FieldDescriptor);
    Code:
       0: aload_0
       1: aload_1
       2: invokespecial #36                 // Method com/google/protobuf/GeneratedMessageV3$Builder.clearField:(Lcom/google/protobuf/Descriptors$FieldDescriptor;)Lcom/google/protobuf/GeneratedMessageV3$Builder;
       5: checkcast     #16                 // class com/google/protobuf/Struct$Builder
       8: areturn

  public com.google.protobuf.Struct$Builder clearOneof(com.google.protobuf.Descriptors$OneofDescriptor);
    Code:
       0: aload_0
       1: aload_1
       2: invokespecial #37                 // Method com/google/protobuf/GeneratedMessageV3$Builder.clearOneof:(Lcom/google/protobuf/Descriptors$OneofDescriptor;)Lcom/google/protobuf/GeneratedMessageV3$Builder;
       5: checkcast     #16                 // class com/google/protobuf/Struct$Builder
       8: areturn

  public com.google.protobuf.Struct$Builder setRepeatedField(com.google.protobuf.Descriptors$FieldDescriptor, int, java.lang.Object);
    Code:
       0: aload_0
       1: aload_1
       2: iload_2
       3: aload_3
       4: invokespecial #38                 // Method com/google/protobuf/GeneratedMessageV3$Builder.setRepeatedField:(Lcom/google/protobuf/Descriptors$FieldDescriptor;ILjava/lang/Object;)Lcom/google/protobuf/GeneratedMessageV3$Builder;
       7: checkcast     #16                 // class com/google/protobuf/Struct$Builder
      10: areturn

  public com.google.protobuf.Struct$Builder addRepeatedField(com.google.protobuf.Descriptors$FieldDescriptor, java.lang.Object);
    Code:
       0: aload_0
       1: aload_1
       2: aload_2
       3: invokespecial #39                 // Method com/google/protobuf/GeneratedMessageV3$Builder.addRepeatedField:(Lcom/google/protobuf/Descriptors$FieldDescriptor;Ljava/lang/Object;)Lcom/google/protobuf/GeneratedMessageV3$Builder;
       6: checkcast     #16                 // class com/google/protobuf/Struct$Builder
       9: areturn

  public com.google.protobuf.Struct$Builder mergeFrom(com.google.protobuf.Message);
    Code:
       0: aload_1
       1: instanceof    #15                 // class com/google/protobuf/Struct
       4: ifeq          16
       7: aload_0
       8: aload_1
       9: checkcast     #15                 // class com/google/protobuf/Struct
      12: invokevirtual #40                 // Method mergeFrom:(Lcom/google/protobuf/Struct;)Lcom/google/protobuf/Struct$Builder;
      15: areturn
      16: aload_0
      17: aload_1
      18: invokespecial #41                 // Method com/google/protobuf/GeneratedMessageV3$Builder.mergeFrom:(Lcom/google/protobuf/Message;)Lcom/google/protobuf/AbstractMessage$Builder;
      21: pop
      22: aload_0
      23: areturn

  public com.google.protobuf.Struct$Builder mergeFrom(com.google.protobuf.Struct);
    Code:
       0: aload_1
       1: invokestatic  #24                 // Method com/google/protobuf/Struct.getDefaultInstance:()Lcom/google/protobuf/Struct;
       4: if_acmpne     9
       7: aload_0
       8: areturn
       9: aload_0
      10: invokespecial #13                 // Method internalGetMutableFields:()Lcom/google/protobuf/MapField;
      13: aload_1
      14: invokestatic  #42                 // Method com/google/protobuf/Struct.access$400:(Lcom/google/protobuf/Struct;)Lcom/google/protobuf/MapField;
      17: invokevirtual #43                 // Method com/google/protobuf/MapField.mergeFrom:(Lcom/google/protobuf/MapField;)V
      20: aload_0
      21: aload_1
      22: getfield      #44                 // Field com/google/protobuf/Struct.unknownFields:Lcom/google/protobuf/UnknownFieldSet;
      25: invokevirtual #45                 // Method mergeUnknownFields:(Lcom/google/protobuf/UnknownFieldSet;)Lcom/google/protobuf/Struct$Builder;
      28: pop
      29: aload_0
      30: invokevirtual #46                 // Method onChanged:()V
      33: aload_0
      34: areturn

  public final boolean isInitialized();
    Code:
       0: iconst_1
       1: ireturn

  public com.google.protobuf.Struct$Builder mergeFrom(com.google.protobuf.CodedInputStream, com.google.protobuf.ExtensionRegistryLite) throws java.io.IOException;
    Code:
       0: aconst_null
       1: astore_3
       2: invokestatic  #47                 // Method com/google/protobuf/Struct.access$500:()Lcom/google/protobuf/Parser;
       5: aload_1
       6: aload_2
       7: invokeinterface #48,  3           // InterfaceMethod com/google/protobuf/Parser.parsePartialFrom:(Lcom/google/protobuf/CodedInputStream;Lcom/google/protobuf/ExtensionRegistryLite;)Ljava/lang/Object;
      12: checkcast     #15                 // class com/google/protobuf/Struct
      15: astore_3
      16: aload_3
      17: ifnull        61
      20: aload_0
      21: aload_3
      22: invokevirtual #40                 // Method mergeFrom:(Lcom/google/protobuf/Struct;)Lcom/google/protobuf/Struct$Builder;
      25: pop
      26: goto          61
      29: astore        4
      31: aload         4
      33: invokevirtual #50                 // Method com/google/protobuf/InvalidProtocolBufferException.getUnfinishedMessage:()Lcom/google/protobuf/MessageLite;
      36: checkcast     #15                 // class com/google/protobuf/Struct
      39: astore_3
      40: aload         4
      42: invokevirtual #51                 // Method com/google/protobuf/InvalidProtocolBufferException.unwrapIOException:()Ljava/io/IOException;
      45: athrow
      46: astore        5
      48: aload_3
      49: ifnull        58
      52: aload_0
      53: aload_3
      54: invokevirtual #40                 // Method mergeFrom:(Lcom/google/protobuf/Struct;)Lcom/google/protobuf/Struct$Builder;
      57: pop
      58: aload         5
      60: athrow
      61: aload_0
      62: areturn
    Exception table:
       from    to  target type
           2    16    29   Class com/google/protobuf/InvalidProtocolBufferException
           2    16    46   any
          29    48    46   any

  private com.google.protobuf.MapField<java.lang.String, com.google.protobuf.Value> internalGetFields();
    Code:
       0: aload_0
       1: getfield      #52                 // Field fields_:Lcom/google/protobuf/MapField;
       4: ifnonnull     14
       7: getstatic     #53                 // Field com/google/protobuf/Struct$FieldsDefaultEntryHolder.defaultEntry:Lcom/google/protobuf/MapEntry;
      10: invokestatic  #54                 // Method com/google/protobuf/MapField.emptyMapField:(Lcom/google/protobuf/MapEntry;)Lcom/google/protobuf/MapField;
      13: areturn
      14: aload_0
      15: getfield      #52                 // Field fields_:Lcom/google/protobuf/MapField;
      18: areturn

  private com.google.protobuf.MapField<java.lang.String, com.google.protobuf.Value> internalGetMutableFields();
    Code:
       0: aload_0
       1: invokevirtual #46                 // Method onChanged:()V
       4: aload_0
       5: getfield      #52                 // Field fields_:Lcom/google/protobuf/MapField;
       8: ifnonnull     21
      11: aload_0
      12: getstatic     #53                 // Field com/google/protobuf/Struct$FieldsDefaultEntryHolder.defaultEntry:Lcom/google/protobuf/MapEntry;
      15: invokestatic  #55                 // Method com/google/protobuf/MapField.newMapField:(Lcom/google/protobuf/MapEntry;)Lcom/google/protobuf/MapField;
      18: putfield      #52                 // Field fields_:Lcom/google/protobuf/MapField;
      21: aload_0
      22: getfield      #52                 // Field fields_:Lcom/google/protobuf/MapField;
      25: invokevirtual #56                 // Method com/google/protobuf/MapField.isMutable:()Z
      28: ifne          42
      31: aload_0
      32: aload_0
      33: getfield      #52                 // Field fields_:Lcom/google/protobuf/MapField;
      36: invokevirtual #57                 // Method com/google/protobuf/MapField.copy:()Lcom/google/protobuf/MapField;
      39: putfield      #52                 // Field fields_:Lcom/google/protobuf/MapField;
      42: aload_0
      43: getfield      #52                 // Field fields_:Lcom/google/protobuf/MapField;
      46: areturn

  public int getFieldsCount();
    Code:
       0: aload_0
       1: invokespecial #4                  // Method internalGetFields:()Lcom/google/protobuf/MapField;
       4: invokevirtual #58                 // Method com/google/protobuf/MapField.getMap:()Ljava/util/Map;
       7: invokeinterface #59,  1           // InterfaceMethod java/util/Map.size:()I
      12: ireturn

  public boolean containsFields(java.lang.String);
    Code:
       0: aload_1
       1: ifnonnull     12
       4: new           #60                 // class java/lang/NullPointerException
       7: dup
       8: invokespecial #61                 // Method java/lang/NullPointerException."<init>":()V
      11: athrow
      12: aload_0
      13: invokespecial #4                  // Method internalGetFields:()Lcom/google/protobuf/MapField;
      16: invokevirtual #58                 // Method com/google/protobuf/MapField.getMap:()Ljava/util/Map;
      19: aload_1
      20: invokeinterface #62,  2           // InterfaceMethod java/util/Map.containsKey:(Ljava/lang/Object;)Z
      25: ireturn

  public java.util.Map<java.lang.String, com.google.protobuf.Value> getFields();
    Code:
       0: aload_0
       1: invokevirtual #63                 // Method getFieldsMap:()Ljava/util/Map;
       4: areturn

  public java.util.Map<java.lang.String, com.google.protobuf.Value> getFieldsMap();
    Code:
       0: aload_0
       1: invokespecial #4                  // Method internalGetFields:()Lcom/google/protobuf/MapField;
       4: invokevirtual #58                 // Method com/google/protobuf/MapField.getMap:()Ljava/util/Map;
       7: areturn

  public com.google.protobuf.Value getFieldsOrDefault(java.lang.String, com.google.protobuf.Value);
    Code:
       0: aload_1
       1: ifnonnull     12
       4: new           #60                 // class java/lang/NullPointerException
       7: dup
       8: invokespecial #61                 // Method java/lang/NullPointerException."<init>":()V
      11: athrow
      12: aload_0
      13: invokespecial #4                  // Method internalGetFields:()Lcom/google/protobuf/MapField;
      16: invokevirtual #58                 // Method com/google/protobuf/MapField.getMap:()Ljava/util/Map;
      19: astore_3
      20: aload_3
      21: aload_1
      22: invokeinterface #62,  2           // InterfaceMethod java/util/Map.containsKey:(Ljava/lang/Object;)Z
      27: ifeq          43
      30: aload_3
      31: aload_1
      32: invokeinterface #64,  2           // InterfaceMethod java/util/Map.get:(Ljava/lang/Object;)Ljava/lang/Object;
      37: checkcast     #65                 // class com/google/protobuf/Value
      40: goto          44
      43: aload_2
      44: areturn

  public com.google.protobuf.Value getFieldsOrThrow(java.lang.String);
    Code:
       0: aload_1
       1: ifnonnull     12
       4: new           #60                 // class java/lang/NullPointerException
       7: dup
       8: invokespecial #61                 // Method java/lang/NullPointerException."<init>":()V
      11: athrow
      12: aload_0
      13: invokespecial #4                  // Method internalGetFields:()Lcom/google/protobuf/MapField;
      16: invokevirtual #58                 // Method com/google/protobuf/MapField.getMap:()Ljava/util/Map;
      19: astore_2
      20: aload_2
      21: aload_1
      22: invokeinterface #62,  2           // InterfaceMethod java/util/Map.containsKey:(Ljava/lang/Object;)Z
      27: ifne          38
      30: new           #66                 // class java/lang/IllegalArgumentException
      33: dup
      34: invokespecial #67                 // Method java/lang/IllegalArgumentException."<init>":()V
      37: athrow
      38: aload_2
      39: aload_1
      40: invokeinterface #64,  2           // InterfaceMethod java/util/Map.get:(Ljava/lang/Object;)Ljava/lang/Object;
      45: checkcast     #65                 // class com/google/protobuf/Value
      48: areturn

  public com.google.protobuf.Struct$Builder clearFields();
    Code:
       0: aload_0
       1: invokespecial #13                 // Method internalGetMutableFields:()Lcom/google/protobuf/MapField;
       4: invokevirtual #68                 // Method com/google/protobuf/MapField.getMutableMap:()Ljava/util/Map;
       7: invokeinterface #69,  1           // InterfaceMethod java/util/Map.clear:()V
      12: aload_0
      13: areturn

  public com.google.protobuf.Struct$Builder removeFields(java.lang.String);
    Code:
       0: aload_1
       1: ifnonnull     12
       4: new           #60                 // class java/lang/NullPointerException
       7: dup
       8: invokespecial #61                 // Method java/lang/NullPointerException."<init>":()V
      11: athrow
      12: aload_0
      13: invokespecial #13                 // Method internalGetMutableFields:()Lcom/google/protobuf/MapField;
      16: invokevirtual #68                 // Method com/google/protobuf/MapField.getMutableMap:()Ljava/util/Map;
      19: aload_1
      20: invokeinterface #70,  2           // InterfaceMethod java/util/Map.remove:(Ljava/lang/Object;)Ljava/lang/Object;
      25: pop
      26: aload_0
      27: areturn

  public java.util.Map<java.lang.String, com.google.protobuf.Value> getMutableFields();
    Code:
       0: aload_0
       1: invokespecial #13                 // Method internalGetMutableFields:()Lcom/google/protobuf/MapField;
       4: invokevirtual #68                 // Method com/google/protobuf/MapField.getMutableMap:()Ljava/util/Map;
       7: areturn

  public com.google.protobuf.Struct$Builder putFields(java.lang.String, com.google.protobuf.Value);
    Code:
       0: aload_1
       1: ifnonnull     12
       4: new           #60                 // class java/lang/NullPointerException
       7: dup
       8: invokespecial #61                 // Method java/lang/NullPointerException."<init>":()V
      11: athrow
      12: aload_2
      13: ifnonnull     24
      16: new           #60                 // class java/lang/NullPointerException
      19: dup
      20: invokespecial #61                 // Method java/lang/NullPointerException."<init>":()V
      23: athrow
      24: aload_0
      25: invokespecial #13                 // Method internalGetMutableFields:()Lcom/google/protobuf/MapField;
      28: invokevirtual #68                 // Method com/google/protobuf/MapField.getMutableMap:()Ljava/util/Map;
      31: aload_1
      32: aload_2
      33: invokeinterface #71,  3           // InterfaceMethod java/util/Map.put:(Ljava/lang/Object;Ljava/lang/Object;)Ljava/lang/Object;
      38: pop
      39: aload_0
      40: areturn

  public com.google.protobuf.Struct$Builder putAllFields(java.util.Map<java.lang.String, com.google.protobuf.Value>);
    Code:
       0: aload_0
       1: invokespecial #13                 // Method internalGetMutableFields:()Lcom/google/protobuf/MapField;
       4: invokevirtual #68                 // Method com/google/protobuf/MapField.getMutableMap:()Ljava/util/Map;
       7: aload_1
       8: invokeinterface #72,  2           // InterfaceMethod java/util/Map.putAll:(Ljava/util/Map;)V
      13: aload_0
      14: areturn

  public final com.google.protobuf.Struct$Builder setUnknownFields(com.google.protobuf.UnknownFieldSet);
    Code:
       0: aload_0
       1: aload_1
       2: invokespecial #73                 // Method com/google/protobuf/GeneratedMessageV3$Builder.setUnknownFieldsProto3:(Lcom/google/protobuf/UnknownFieldSet;)Lcom/google/protobuf/GeneratedMessageV3$Builder;
       5: checkcast     #16                 // class com/google/protobuf/Struct$Builder
       8: areturn

  public final com.google.protobuf.Struct$Builder mergeUnknownFields(com.google.protobuf.UnknownFieldSet);
    Code:
       0: aload_0
       1: aload_1
       2: invokespecial #74                 // Method com/google/protobuf/GeneratedMessageV3$Builder.mergeUnknownFields:(Lcom/google/protobuf/UnknownFieldSet;)Lcom/google/protobuf/GeneratedMessageV3$Builder;
       5: checkcast     #16                 // class com/google/protobuf/Struct$Builder
       8: areturn

  public com.google.protobuf.GeneratedMessageV3$Builder mergeUnknownFields(com.google.protobuf.UnknownFieldSet);
    Code:
       0: aload_0
       1: aload_1
       2: invokevirtual #45                 // Method mergeUnknownFields:(Lcom/google/protobuf/UnknownFieldSet;)Lcom/google/protobuf/Struct$Builder;
       5: areturn

  public com.google.protobuf.GeneratedMessageV3$Builder setUnknownFields(com.google.protobuf.UnknownFieldSet);
    Code:
       0: aload_0
       1: aload_1
       2: invokevirtual #75                 // Method setUnknownFields:(Lcom/google/protobuf/UnknownFieldSet;)Lcom/google/protobuf/Struct$Builder;
       5: areturn

  public com.google.protobuf.GeneratedMessageV3$Builder addRepeatedField(com.google.protobuf.Descriptors$FieldDescriptor, java.lang.Object);
    Code:
       0: aload_0
       1: aload_1
       2: aload_2
       3: invokevirtual #76                 // Method addRepeatedField:(Lcom/google/protobuf/Descriptors$FieldDescriptor;Ljava/lang/Object;)Lcom/google/protobuf/Struct$Builder;
       6: areturn

  public com.google.protobuf.GeneratedMessageV3$Builder setRepeatedField(com.google.protobuf.Descriptors$FieldDescriptor, int, java.lang.Object);
    Code:
       0: aload_0
       1: aload_1
       2: iload_2
       3: aload_3
       4: invokevirtual #77                 // Method setRepeatedField:(Lcom/google/protobuf/Descriptors$FieldDescriptor;ILjava/lang/Object;)Lcom/google/protobuf/Struct$Builder;
       7: areturn

  public com.google.protobuf.GeneratedMessageV3$Builder clearOneof(com.google.protobuf.Descriptors$OneofDescriptor);
    Code:
       0: aload_0
       1: aload_1
       2: invokevirtual #78                 // Method clearOneof:(Lcom/google/protobuf/Descriptors$OneofDescriptor;)Lcom/google/protobuf/Struct$Builder;
       5: areturn

  public com.google.protobuf.GeneratedMessageV3$Builder clearField(com.google.protobuf.Descriptors$FieldDescriptor);
    Code:
       0: aload_0
       1: aload_1
       2: invokevirtual #79                 // Method clearField:(Lcom/google/protobuf/Descriptors$FieldDescriptor;)Lcom/google/protobuf/Struct$Builder;
       5: areturn

  public com.google.protobuf.GeneratedMessageV3$Builder setField(com.google.protobuf.Descriptors$FieldDescriptor, java.lang.Object);
    Code:
       0: aload_0
       1: aload_1
       2: aload_2
       3: invokevirtual #80                 // Method setField:(Lcom/google/protobuf/Descriptors$FieldDescriptor;Ljava/lang/Object;)Lcom/google/protobuf/Struct$Builder;
       6: areturn

  public com.google.protobuf.GeneratedMessageV3$Builder clear();
    Code:
       0: aload_0
       1: invokevirtual #81                 // Method clear:()Lcom/google/protobuf/Struct$Builder;
       4: areturn

  public com.google.protobuf.GeneratedMessageV3$Builder clone();
    Code:
       0: aload_0
       1: invokevirtual #82                 // Method clone:()Lcom/google/protobuf/Struct$Builder;
       4: areturn

  public com.google.protobuf.AbstractMessage$Builder mergeUnknownFields(com.google.protobuf.UnknownFieldSet);
    Code:
       0: aload_0
       1: aload_1
       2: invokevirtual #45                 // Method mergeUnknownFields:(Lcom/google/protobuf/UnknownFieldSet;)Lcom/google/protobuf/Struct$Builder;
       5: areturn

  public com.google.protobuf.AbstractMessage$Builder mergeFrom(com.google.protobuf.CodedInputStream, com.google.protobuf.ExtensionRegistryLite) throws java.io.IOException;
    Code:
       0: aload_0
       1: aload_1
       2: aload_2
       3: invokevirtual #83                 // Method mergeFrom:(Lcom/google/protobuf/CodedInputStream;Lcom/google/protobuf/ExtensionRegistryLite;)Lcom/google/protobuf/Struct$Builder;
       6: areturn

  public com.google.protobuf.AbstractMessage$Builder mergeFrom(com.google.protobuf.Message);
    Code:
       0: aload_0
       1: aload_1
       2: invokevirtual #84                 // Method mergeFrom:(Lcom/google/protobuf/Message;)Lcom/google/protobuf/Struct$Builder;
       5: areturn

  public com.google.protobuf.AbstractMessage$Builder clear();
    Code:
       0: aload_0
       1: invokevirtual #81                 // Method clear:()Lcom/google/protobuf/Struct$Builder;
       4: areturn

  public com.google.protobuf.AbstractMessage$Builder clearOneof(com.google.protobuf.Descriptors$OneofDescriptor);
    Code:
       0: aload_0
       1: aload_1
       2: invokevirtual #78                 // Method clearOneof:(Lcom/google/protobuf/Descriptors$OneofDescriptor;)Lcom/google/protobuf/Struct$Builder;
       5: areturn

  public com.google.protobuf.AbstractMessage$Builder clone();
    Code:
       0: aload_0
       1: invokevirtual #82                 // Method clone:()Lcom/google/protobuf/Struct$Builder;
       4: areturn

  public com.google.protobuf.Message$Builder mergeUnknownFields(com.google.protobuf.UnknownFieldSet);
    Code:
       0: aload_0
       1: aload_1
       2: invokevirtual #45                 // Method mergeUnknownFields:(Lcom/google/protobuf/UnknownFieldSet;)Lcom/google/protobuf/Struct$Builder;
       5: areturn

  public com.google.protobuf.Message$Builder setUnknownFields(com.google.protobuf.UnknownFieldSet);
    Code:
       0: aload_0
       1: aload_1
       2: invokevirtual #75                 // Method setUnknownFields:(Lcom/google/protobuf/UnknownFieldSet;)Lcom/google/protobuf/Struct$Builder;
       5: areturn

  public com.google.protobuf.Message$Builder addRepeatedField(com.google.protobuf.Descriptors$FieldDescriptor, java.lang.Object);
    Code:
       0: aload_0
       1: aload_1
       2: aload_2
       3: invokevirtual #76                 // Method addRepeatedField:(Lcom/google/protobuf/Descriptors$FieldDescriptor;Ljava/lang/Object;)Lcom/google/protobuf/Struct$Builder;
       6: areturn

  public com.google.protobuf.Message$Builder setRepeatedField(com.google.protobuf.Descriptors$FieldDescriptor, int, java.lang.Object);
    Code:
       0: aload_0
       1: aload_1
       2: iload_2
       3: aload_3
       4: invokevirtual #77                 // Method setRepeatedField:(Lcom/google/protobuf/Descriptors$FieldDescriptor;ILjava/lang/Object;)Lcom/google/protobuf/Struct$Builder;
       7: areturn

  public com.google.protobuf.Message$Builder clearOneof(com.google.protobuf.Descriptors$OneofDescriptor);
    Code:
       0: aload_0
       1: aload_1
       2: invokevirtual #78                 // Method clearOneof:(Lcom/google/protobuf/Descriptors$OneofDescriptor;)Lcom/google/protobuf/Struct$Builder;
       5: areturn

  public com.google.protobuf.Message$Builder clearField(com.google.protobuf.Descriptors$FieldDescriptor);
    Code:
       0: aload_0
       1: aload_1
       2: invokevirtual #79                 // Method clearField:(Lcom/google/protobuf/Descriptors$FieldDescriptor;)Lcom/google/protobuf/Struct$Builder;
       5: areturn

  public com.google.protobuf.Message$Builder setField(com.google.protobuf.Descriptors$FieldDescriptor, java.lang.Object);
    Code:
       0: aload_0
       1: aload_1
       2: aload_2
       3: invokevirtual #80                 // Method setField:(Lcom/google/protobuf/Descriptors$FieldDescriptor;Ljava/lang/Object;)Lcom/google/protobuf/Struct$Builder;
       6: areturn

  public com.google.protobuf.Message$Builder mergeFrom(com.google.protobuf.CodedInputStream, com.google.protobuf.ExtensionRegistryLite) throws java.io.IOException;
    Code:
       0: aload_0
       1: aload_1
       2: aload_2
       3: invokevirtual #83                 // Method mergeFrom:(Lcom/google/protobuf/CodedInputStream;Lcom/google/protobuf/ExtensionRegistryLite;)Lcom/google/protobuf/Struct$Builder;
       6: areturn

  public com.google.protobuf.Message$Builder clone();
    Code:
       0: aload_0
       1: invokevirtual #82                 // Method clone:()Lcom/google/protobuf/Struct$Builder;
       4: areturn

  public com.google.protobuf.Message buildPartial();
    Code:
       0: aload_0
       1: invokevirtual #25                 // Method buildPartial:()Lcom/google/protobuf/Struct;
       4: areturn

  public com.google.protobuf.Message build();
    Code:
       0: aload_0
       1: invokevirtual #85                 // Method build:()Lcom/google/protobuf/Struct;
       4: areturn

  public com.google.protobuf.Message$Builder mergeFrom(com.google.protobuf.Message);
    Code:
       0: aload_0
       1: aload_1
       2: invokevirtual #84                 // Method mergeFrom:(Lcom/google/protobuf/Message;)Lcom/google/protobuf/Struct$Builder;
       5: areturn

  public com.google.protobuf.Message$Builder clear();
    Code:
       0: aload_0
       1: invokevirtual #81                 // Method clear:()Lcom/google/protobuf/Struct$Builder;
       4: areturn

  public com.google.protobuf.MessageLite$Builder mergeFrom(com.google.protobuf.CodedInputStream, com.google.protobuf.ExtensionRegistryLite) throws java.io.IOException;
    Code:
       0: aload_0
       1: aload_1
       2: aload_2
       3: invokevirtual #83                 // Method mergeFrom:(Lcom/google/protobuf/CodedInputStream;Lcom/google/protobuf/ExtensionRegistryLite;)Lcom/google/protobuf/Struct$Builder;
       6: areturn

  public com.google.protobuf.MessageLite$Builder clone();
    Code:
       0: aload_0
       1: invokevirtual #82                 // Method clone:()Lcom/google/protobuf/Struct$Builder;
       4: areturn

  public com.google.protobuf.MessageLite buildPartial();
    Code:
       0: aload_0
       1: invokevirtual #25                 // Method buildPartial:()Lcom/google/protobuf/Struct;
       4: areturn

  public com.google.protobuf.MessageLite build();
    Code:
       0: aload_0
       1: invokevirtual #85                 // Method build:()Lcom/google/protobuf/Struct;
       4: areturn

  public com.google.protobuf.MessageLite$Builder clear();
    Code:
       0: aload_0
       1: invokevirtual #81                 // Method clear:()Lcom/google/protobuf/Struct$Builder;
       4: areturn

  public com.google.protobuf.MessageLite getDefaultInstanceForType();
    Code:
       0: aload_0
       1: invokevirtual #86                 // Method getDefaultInstanceForType:()Lcom/google/protobuf/Struct;
       4: areturn

  public com.google.protobuf.Message getDefaultInstanceForType();
    Code:
       0: aload_0
       1: invokevirtual #86                 // Method getDefaultInstanceForType:()Lcom/google/protobuf/Struct;
       4: areturn

  public com.google.protobuf.AbstractMessageLite$Builder mergeFrom(com.google.protobuf.CodedInputStream, com.google.protobuf.ExtensionRegistryLite) throws java.io.IOException;
    Code:
       0: aload_0
       1: aload_1
       2: aload_2
       3: invokevirtual #83                 // Method mergeFrom:(Lcom/google/protobuf/CodedInputStream;Lcom/google/protobuf/ExtensionRegistryLite;)Lcom/google/protobuf/Struct$Builder;
       6: areturn

  public com.google.protobuf.AbstractMessageLite$Builder clone();
    Code:
       0: aload_0
       1: invokevirtual #82                 // Method clone:()Lcom/google/protobuf/Struct$Builder;
       4: areturn

  public java.lang.Object clone() throws java.lang.CloneNotSupportedException;
    Code:
       0: aload_0
       1: invokevirtual #82                 // Method clone:()Lcom/google/protobuf/Struct$Builder;
       4: areturn

  com.google.protobuf.Struct$Builder(com.google.protobuf.Struct$1);
    Code:
       0: aload_0
       1: invokespecial #2                  // Method "<init>":()V
       4: return

  com.google.protobuf.Struct$Builder(com.google.protobuf.GeneratedMessageV3$BuilderParent, com.google.protobuf.Struct$1);
    Code:
       0: aload_0
       1: aload_1
       2: invokespecial #1                  // Method "<init>":(Lcom/google/protobuf/GeneratedMessageV3$BuilderParent;)V
       5: return
}
