Compiled from "$AutoValue_SourcesList.java"
abstract class org.graylog2.rest.models.sources.responses.$AutoValue_SourcesList extends org.graylog2.rest.models.sources.responses.SourcesList {
  private final int total;

  private final java.util.Map<java.lang.String, java.lang.Long> sources;

  private final long tookMs;

  private final int range;

  org.graylog2.rest.models.sources.responses.$AutoValue_SourcesList(int, java.util.Map<java.lang.String, java.lang.Long>, long, int);
    Code:
       0: aload_0
       1: invokespecial #1                  // Method org/graylog2/rest/models/sources/responses/SourcesList."<init>":()V
       4: aload_0
       5: iload_1
       6: putfield      #2                  // Field total:I
       9: aload_2
      10: ifnonnull     23
      13: new           #3                  // class java/lang/NullPointerException
      16: dup
      17: ldc           #4                  // String Null sources
      19: invokespecial #5                  // Method java/lang/NullPointerException."<init>":(Ljava/lang/String;)V
      22: athrow
      23: aload_0
      24: aload_2
      25: putfield      #6                  // Field sources:Ljava/util/Map;
      28: aload_0
      29: lload_3
      30: putfield      #7                  // Field tookMs:J
      33: aload_0
      34: iload         5
      36: putfield      #8                  // Field range:I
      39: return

  public int total();
    Code:
       0: aload_0
       1: getfield      #2                  // Field total:I
       4: ireturn

  public java.util.Map<java.lang.String, java.lang.Long> sources();
    Code:
       0: aload_0
       1: getfield      #6                  // Field sources:Ljava/util/Map;
       4: areturn

  public long tookMs();
    Code:
       0: aload_0
       1: getfield      #7                  // Field tookMs:J
       4: lreturn

  public int range();
    Code:
       0: aload_0
       1: getfield      #8                  // Field range:I
       4: ireturn

  public java.lang.String toString();
    Code:
       0: new           #9                  // class java/lang/StringBuilder
       3: dup
       4: invokespecial #10                 // Method java/lang/StringBuilder."<init>":()V
       7: ldc           #11                 // String SourcesList{total=
       9: invokevirtual #12                 // Method java/lang/StringBuilder.append:(Ljava/lang/String;)Ljava/lang/StringBuilder;
      12: aload_0
      13: getfield      #2                  // Field total:I
      16: invokevirtual #13                 // Method java/lang/StringBuilder.append:(I)Ljava/lang/StringBuilder;
      19: ldc           #14                 // String , sources=
      21: invokevirtual #12                 // Method java/lang/StringBuilder.append:(Ljava/lang/String;)Ljava/lang/StringBuilder;
      24: aload_0
      25: getfield      #6                  // Field sources:Ljava/util/Map;
      28: invokevirtual #15                 // Method java/lang/StringBuilder.append:(Ljava/lang/Object;)Ljava/lang/StringBuilder;
      31: ldc           #16                 // String , tookMs=
      33: invokevirtual #12                 // Method java/lang/StringBuilder.append:(Ljava/lang/String;)Ljava/lang/StringBuilder;
      36: aload_0
      37: getfield      #7                  // Field tookMs:J
      40: invokevirtual #17                 // Method java/lang/StringBuilder.append:(J)Ljava/lang/StringBuilder;
      43: ldc           #18                 // String , range=
      45: invokevirtual #12                 // Method java/lang/StringBuilder.append:(Ljava/lang/String;)Ljava/lang/StringBuilder;
      48: aload_0
      49: getfield      #8                  // Field range:I
      52: invokevirtual #13                 // Method java/lang/StringBuilder.append:(I)Ljava/lang/StringBuilder;
      55: ldc           #19                 // String }
      57: invokevirtual #12                 // Method java/lang/StringBuilder.append:(Ljava/lang/String;)Ljava/lang/StringBuilder;
      60: invokevirtual #20                 // Method java/lang/StringBuilder.toString:()Ljava/lang/String;
      63: areturn

  public boolean equals(java.lang.Object);
    Code:
       0: aload_1
       1: aload_0
       2: if_acmpne     7
       5: iconst_1
       6: ireturn
       7: aload_1
       8: instanceof    #21                 // class org/graylog2/rest/models/sources/responses/SourcesList
      11: ifeq          75
      14: aload_1
      15: checkcast     #21                 // class org/graylog2/rest/models/sources/responses/SourcesList
      18: astore_2
      19: aload_0
      20: getfield      #2                  // Field total:I
      23: aload_2
      24: invokevirtual #22                 // Method org/graylog2/rest/models/sources/responses/SourcesList.total:()I
      27: if_icmpne     73
      30: aload_0
      31: getfield      #6                  // Field sources:Ljava/util/Map;
      34: aload_2
      35: invokevirtual #23                 // Method org/graylog2/rest/models/sources/responses/SourcesList.sources:()Ljava/util/Map;
      38: invokeinterface #24,  2           // InterfaceMethod java/util/Map.equals:(Ljava/lang/Object;)Z
      43: ifeq          73
      46: aload_0
      47: getfield      #7                  // Field tookMs:J
      50: aload_2
      51: invokevirtual #25                 // Method org/graylog2/rest/models/sources/responses/SourcesList.tookMs:()J
      54: lcmp
      55: ifne          73
      58: aload_0
      59: getfield      #8                  // Field range:I
      62: aload_2
      63: invokevirtual #26                 // Method org/graylog2/rest/models/sources/responses/SourcesList.range:()I
      66: if_icmpne     73
      69: iconst_1
      70: goto          74
      73: iconst_0
      74: ireturn
      75: iconst_0
      76: ireturn

  public int hashCode();
    Code:
       0: iconst_1
       1: istore_1
       2: iload_1
       3: ldc           #27                 // int 1000003
       5: imul
       6: istore_1
       7: iload_1
       8: aload_0
       9: getfield      #2                  // Field total:I
      12: ixor
      13: istore_1
      14: iload_1
      15: ldc           #27                 // int 1000003
      17: imul
      18: istore_1
      19: iload_1
      20: aload_0
      21: getfield      #6                  // Field sources:Ljava/util/Map;
      24: invokeinterface #28,  1           // InterfaceMethod java/util/Map.hashCode:()I
      29: ixor
      30: istore_1
      31: iload_1
      32: ldc           #27                 // int 1000003
      34: imul
      35: istore_1
      36: iload_1
      37: aload_0
      38: getfield      #7                  // Field tookMs:J
      41: bipush        32
      43: lushr
      44: aload_0
      45: getfield      #7                  // Field tookMs:J
      48: lxor
      49: l2i
      50: ixor
      51: istore_1
      52: iload_1
      53: ldc           #27                 // int 1000003
      55: imul
      56: istore_1
      57: iload_1
      58: aload_0
      59: getfield      #8                  // Field range:I
      62: ixor
      63: istore_1
      64: iload_1
      65: ireturn
}
