Compiled from "EncryptAttributes.java"
public class org.opensaml.saml.saml2.profile.impl.EncryptAttributes extends org.opensaml.saml.saml2.profile.impl.AbstractEncryptAction {
  private final org.slf4j.Logger log;

  private com.google.common.base.Function<org.opensaml.profile.context.ProfileRequestContext, org.opensaml.saml.saml2.core.StatusResponseType> responseLookupStrategy;

  private org.opensaml.saml.saml2.core.Response response;

  public org.opensaml.saml.saml2.profile.impl.EncryptAttributes();
    Code:
       0: aload_0
       1: invokespecial #1                  // Method org/opensaml/saml/saml2/profile/impl/AbstractEncryptAction."<init>":()V
       4: aload_0
       5: ldc_w         #2                  // class org/opensaml/saml/saml2/profile/impl/EncryptAttributes
       8: invokestatic  #3                  // Method org/slf4j/LoggerFactory.getLogger:(Ljava/lang/Class;)Lorg/slf4j/Logger;
      11: putfield      #4                  // Field log:Lorg/slf4j/Logger;
      14: aload_0
      15: new           #5                  // class org/opensaml/messaging/context/navigate/MessageLookup
      18: dup
      19: ldc_w         #6                  // class org/opensaml/saml/saml2/core/StatusResponseType
      22: invokespecial #7                  // Method org/opensaml/messaging/context/navigate/MessageLookup."<init>":(Ljava/lang/Class;)V
      25: new           #8                  // class org/opensaml/profile/context/navigate/OutboundMessageContextLookup
      28: dup
      29: invokespecial #9                  // Method org/opensaml/profile/context/navigate/OutboundMessageContextLookup."<init>":()V
      32: invokestatic  #10                 // Method com/google/common/base/Functions.compose:(Lcom/google/common/base/Function;Lcom/google/common/base/Function;)Lcom/google/common/base/Function;
      35: putfield      #11                 // Field responseLookupStrategy:Lcom/google/common/base/Function;
      38: return

  public void setResponseLookupStrategy(com.google.common.base.Function<org.opensaml.profile.context.ProfileRequestContext, org.opensaml.saml.saml2.core.StatusResponseType>);
    Code:
       0: aload_0
       1: invokestatic  #12                 // Method net/shibboleth/utilities/java/support/component/ComponentSupport.ifInitializedThrowUnmodifiabledComponentException:(Lnet/shibboleth/utilities/java/support/component/InitializableComponent;)V
       4: aload_0
       5: aload_1
       6: ldc           #13                 // String Response lookup strategy cannot be null
       8: invokestatic  #14                 // Method net/shibboleth/utilities/java/support/logic/Constraint.isNotNull:(Ljava/lang/Object;Ljava/lang/String;)Ljava/lang/Object;
      11: checkcast     #15                 // class com/google/common/base/Function
      14: putfield      #11                 // Field responseLookupStrategy:Lcom/google/common/base/Function;
      17: return

  protected org.opensaml.xmlsec.EncryptionParameters getApplicableParameters(org.opensaml.saml.saml2.profile.context.EncryptionContext);
    Code:
       0: aload_1
       1: ifnull        9
       4: aload_1
       5: invokevirtual #16                 // Method org/opensaml/saml/saml2/profile/context/EncryptionContext.getAttributeEncryptionParameters:()Lorg/opensaml/xmlsec/EncryptionParameters;
       8: areturn
       9: aconst_null
      10: areturn

  protected boolean doPreExecute(org.opensaml.profile.context.ProfileRequestContext);
    Code:
       0: aload_0
       1: getfield      #11                 // Field responseLookupStrategy:Lcom/google/common/base/Function;
       4: aload_1
       5: invokeinterface #17,  2           // InterfaceMethod com/google/common/base/Function.apply:(Ljava/lang/Object;)Ljava/lang/Object;
      10: checkcast     #6                  // class org/opensaml/saml/saml2/core/StatusResponseType
      13: astore_2
      14: aload_2
      15: ifnull        74
      18: aload_2
      19: instanceof    #18                 // class org/opensaml/saml/saml2/core/Response
      22: ifeq          36
      25: aload_0
      26: aload_2
      27: checkcast     #18                 // class org/opensaml/saml/saml2/core/Response
      30: putfield      #19                 // Field response:Lorg/opensaml/saml/saml2/core/Response;
      33: goto          74
      36: aload_2
      37: instanceof    #20                 // class org/opensaml/saml/saml2/core/ArtifactResponse
      40: ifeq          74
      43: aload_2
      44: checkcast     #20                 // class org/opensaml/saml/saml2/core/ArtifactResponse
      47: invokeinterface #21,  1           // InterfaceMethod org/opensaml/saml/saml2/core/ArtifactResponse.getMessage:()Lorg/opensaml/saml/common/SAMLObject;
      52: instanceof    #18                 // class org/opensaml/saml/saml2/core/Response
      55: ifeq          74
      58: aload_0
      59: aload_2
      60: checkcast     #20                 // class org/opensaml/saml/saml2/core/ArtifactResponse
      63: invokeinterface #21,  1           // InterfaceMethod org/opensaml/saml/saml2/core/ArtifactResponse.getMessage:()Lorg/opensaml/saml/common/SAMLObject;
      68: checkcast     #18                 // class org/opensaml/saml/saml2/core/Response
      71: putfield      #19                 // Field response:Lorg/opensaml/saml/saml2/core/Response;
      74: aload_0
      75: getfield      #19                 // Field response:Lorg/opensaml/saml/saml2/core/Response;
      78: ifnull        98
      81: aload_0
      82: getfield      #19                 // Field response:Lorg/opensaml/saml/saml2/core/Response;
      85: invokeinterface #22,  1           // InterfaceMethod org/opensaml/saml/saml2/core/Response.getAssertions:()Ljava/util/List;
      90: invokeinterface #23,  1           // InterfaceMethod java/util/List.isEmpty:()Z
      95: ifeq          115
      98: aload_0
      99: getfield      #4                  // Field log:Lorg/slf4j/Logger;
     102: ldc           #24                 // String {} Response was not present or contained no assertions, nothing to do
     104: aload_0
     105: invokevirtual #25                 // Method getLogPrefix:()Ljava/lang/String;
     108: invokeinterface #26,  3           // InterfaceMethod org/slf4j/Logger.debug:(Ljava/lang/String;Ljava/lang/Object;)V
     113: iconst_0
     114: ireturn
     115: aload_0
     116: aload_1
     117: invokespecial #27                 // Method org/opensaml/saml/saml2/profile/impl/AbstractEncryptAction.doPreExecute:(Lorg/opensaml/profile/context/ProfileRequestContext;)Z
     120: ireturn

  protected void doExecute(org.opensaml.profile.context.ProfileRequestContext);
    Code:
       0: aload_0
       1: getfield      #19                 // Field response:Lorg/opensaml/saml/saml2/core/Response;
       4: invokeinterface #22,  1           // InterfaceMethod org/opensaml/saml/saml2/core/Response.getAssertions:()Ljava/util/List;
       9: invokeinterface #28,  1           // InterfaceMethod java/util/List.iterator:()Ljava/util/Iterator;
      14: astore_2
      15: aload_2
      16: invokeinterface #29,  1           // InterfaceMethod java/util/Iterator.hasNext:()Z
      21: ifeq          269
      24: aload_2
      25: invokeinterface #30,  1           // InterfaceMethod java/util/Iterator.next:()Ljava/lang/Object;
      30: checkcast     #31                 // class org/opensaml/saml/saml2/core/Assertion
      33: astore_3
      34: aload_3
      35: invokeinterface #32,  1           // InterfaceMethod org/opensaml/saml/saml2/core/Assertion.getAttributeStatements:()Ljava/util/List;
      40: invokeinterface #28,  1           // InterfaceMethod java/util/List.iterator:()Ljava/util/Iterator;
      45: astore        4
      47: aload         4
      49: invokeinterface #29,  1           // InterfaceMethod java/util/Iterator.hasNext:()Z
      54: ifeq          266
      57: aload         4
      59: invokeinterface #30,  1           // InterfaceMethod java/util/Iterator.next:()Ljava/lang/Object;
      64: checkcast     #33                 // class org/opensaml/saml/saml2/core/AttributeStatement
      67: astore        5
      69: new           #34                 // class java/util/ArrayList
      72: dup
      73: aload         5
      75: invokeinterface #35,  1           // InterfaceMethod org/opensaml/saml/saml2/core/AttributeStatement.getAttributes:()Ljava/util/List;
      80: invokeinterface #36,  1           // InterfaceMethod java/util/List.size:()I
      85: invokespecial #37                 // Method java/util/ArrayList."<init>":(I)V
      88: astore        6
      90: aload         5
      92: invokeinterface #35,  1           // InterfaceMethod org/opensaml/saml/saml2/core/AttributeStatement.getAttributes:()Ljava/util/List;
      97: invokeinterface #28,  1           // InterfaceMethod java/util/List.iterator:()Ljava/util/Iterator;
     102: astore        7
     104: aload         7
     106: invokeinterface #29,  1           // InterfaceMethod java/util/Iterator.hasNext:()Z
     111: ifeq          236
     114: aload         7
     116: invokeinterface #30,  1           // InterfaceMethod java/util/Iterator.next:()Ljava/lang/Object;
     121: checkcast     #38                 // class org/opensaml/saml/saml2/core/Attribute
     124: astore        8
     126: aload_0
     127: getfield      #4                  // Field log:Lorg/slf4j/Logger;
     130: invokeinterface #39,  1           // InterfaceMethod org/slf4j/Logger.isDebugEnabled:()Z
     135: ifeq          187
     138: aload         8
     140: invokestatic  #40                 // Method org/opensaml/core/xml/util/XMLObjectSupport.marshall:(Lorg/opensaml/core/xml/XMLObject;)Lorg/w3c/dom/Element;
     143: astore        9
     145: aload_0
     146: getfield      #4                  // Field log:Lorg/slf4j/Logger;
     149: ldc           #41                 // String {} Attribute before encryption:\n{}
     151: aload_0
     152: invokevirtual #25                 // Method getLogPrefix:()Ljava/lang/String;
     155: aload         9
     157: invokestatic  #42                 // Method net/shibboleth/utilities/java/support/xml/SerializeSupport.prettyPrintXML:(Lorg/w3c/dom/Node;)Ljava/lang/String;
     160: invokeinterface #43,  4           // InterfaceMethod org/slf4j/Logger.debug:(Ljava/lang/String;Ljava/lang/Object;Ljava/lang/Object;)V
     165: goto          187
     168: astore        9
     170: aload_0
     171: getfield      #4                  // Field log:Lorg/slf4j/Logger;
     174: ldc           #45                 // String {} Unable to marshall Attribute for logging purposes
     176: aload_0
     177: invokevirtual #25                 // Method getLogPrefix:()Ljava/lang/String;
     180: aload         9
     182: invokeinterface #46,  4           // InterfaceMethod org/slf4j/Logger.error:(Ljava/lang/String;Ljava/lang/Object;Ljava/lang/Object;)V
     187: aload         6
     189: aload_0
     190: invokevirtual #47                 // Method getEncrypter:()Lorg/opensaml/saml/saml2/encryption/Encrypter;
     193: aload         8
     195: invokevirtual #48                 // Method org/opensaml/saml/saml2/encryption/Encrypter.encrypt:(Lorg/opensaml/saml/saml2/core/Attribute;)Lorg/opensaml/saml/saml2/core/EncryptedAttribute;
     198: invokeinterface #49,  2           // InterfaceMethod java/util/List.add:(Ljava/lang/Object;)Z
     203: pop
     204: goto          233
     207: astore        9
     209: aload_0
     210: getfield      #4                  // Field log:Lorg/slf4j/Logger;
     213: ldc           #51                 // String {} Error encrypting attribute
     215: aload_0
     216: invokevirtual #25                 // Method getLogPrefix:()Ljava/lang/String;
     219: aload         9
     221: invokeinterface #52,  4           // InterfaceMethod org/slf4j/Logger.warn:(Ljava/lang/String;Ljava/lang/Object;Ljava/lang/Object;)V
     226: aload_1
     227: ldc           #53                 // String UnableToEncrypt
     229: invokestatic  #54                 // Method org/opensaml/profile/action/ActionSupport.buildEvent:(Lorg/opensaml/profile/context/ProfileRequestContext;Ljava/lang/String;)V
     232: return
     233: goto          104
     236: aload         5
     238: invokeinterface #55,  1           // InterfaceMethod org/opensaml/saml/saml2/core/AttributeStatement.getEncryptedAttributes:()Ljava/util/List;
     243: aload         6
     245: invokeinterface #56,  2           // InterfaceMethod java/util/List.addAll:(Ljava/util/Collection;)Z
     250: pop
     251: aload         5
     253: invokeinterface #35,  1           // InterfaceMethod org/opensaml/saml/saml2/core/AttributeStatement.getAttributes:()Ljava/util/List;
     258: invokeinterface #57,  1           // InterfaceMethod java/util/List.clear:()V
     263: goto          47
     266: goto          15
     269: return
    Exception table:
       from    to  target type
         138   165   168   Class org/opensaml/core/xml/io/MarshallingException
         126   204   207   Class org/opensaml/xmlsec/encryption/support/EncryptionException
}
