Compiled from "WsFilter.java"
public class org.apache.tomcat.websocket.server.WsFilter implements javax.servlet.Filter {
  private org.apache.tomcat.websocket.server.WsServerContainer sc;

  public org.apache.tomcat.websocket.server.WsFilter();
    Code:
       0: aload_0
       1: invokespecial #1                  // Method java/lang/Object."<init>":()V
       4: return

  public void init(javax.servlet.FilterConfig) throws javax.servlet.ServletException;
    Code:
       0: aload_0
       1: aload_1
       2: invokeinterface #2,  1            // InterfaceMethod javax/servlet/FilterConfig.getServletContext:()Ljavax/servlet/ServletContext;
       7: ldc           #3                  // String javax.websocket.server.ServerContainer
       9: invokeinterface #4,  2            // InterfaceMethod javax/servlet/ServletContext.getAttribute:(Ljava/lang/String;)Ljava/lang/Object;
      14: checkcast     #5                  // class org/apache/tomcat/websocket/server/WsServerContainer
      17: putfield      #6                  // Field sc:Lorg/apache/tomcat/websocket/server/WsServerContainer;
      20: return

  public void doFilter(javax.servlet.ServletRequest, javax.servlet.ServletResponse, javax.servlet.FilterChain) throws java.io.IOException, javax.servlet.ServletException;
    Code:
       0: aload_0
       1: getfield      #6                  // Field sc:Lorg/apache/tomcat/websocket/server/WsServerContainer;
       4: invokevirtual #7                  // Method org/apache/tomcat/websocket/server/WsServerContainer.areEndpointsRegistered:()Z
       7: ifeq          18
      10: aload_1
      11: aload_2
      12: invokestatic  #8                  // Method org/apache/tomcat/websocket/server/UpgradeUtil.isWebSocketUpgradeRequest:(Ljavax/servlet/ServletRequest;Ljavax/servlet/ServletResponse;)Z
      15: ifne          27
      18: aload_3
      19: aload_1
      20: aload_2
      21: invokeinterface #9,  3            // InterfaceMethod javax/servlet/FilterChain.doFilter:(Ljavax/servlet/ServletRequest;Ljavax/servlet/ServletResponse;)V
      26: return
      27: aload_1
      28: checkcast     #10                 // class javax/servlet/http/HttpServletRequest
      31: astore        4
      33: aload_2
      34: checkcast     #11                 // class javax/servlet/http/HttpServletResponse
      37: astore        5
      39: aload         4
      41: invokeinterface #12,  1           // InterfaceMethod javax/servlet/http/HttpServletRequest.getPathInfo:()Ljava/lang/String;
      46: astore        7
      48: aload         7
      50: ifnonnull     65
      53: aload         4
      55: invokeinterface #13,  1           // InterfaceMethod javax/servlet/http/HttpServletRequest.getServletPath:()Ljava/lang/String;
      60: astore        6
      62: goto          92
      65: new           #14                 // class java/lang/StringBuilder
      68: dup
      69: invokespecial #15                 // Method java/lang/StringBuilder."<init>":()V
      72: aload         4
      74: invokeinterface #13,  1           // InterfaceMethod javax/servlet/http/HttpServletRequest.getServletPath:()Ljava/lang/String;
      79: invokevirtual #16                 // Method java/lang/StringBuilder.append:(Ljava/lang/String;)Ljava/lang/StringBuilder;
      82: aload         7
      84: invokevirtual #16                 // Method java/lang/StringBuilder.append:(Ljava/lang/String;)Ljava/lang/StringBuilder;
      87: invokevirtual #17                 // Method java/lang/StringBuilder.toString:()Ljava/lang/String;
      90: astore        6
      92: aload_0
      93: getfield      #6                  // Field sc:Lorg/apache/tomcat/websocket/server/WsServerContainer;
      96: aload         6
      98: invokevirtual #18                 // Method org/apache/tomcat/websocket/server/WsServerContainer.findMapping:(Ljava/lang/String;)Lorg/apache/tomcat/websocket/server/WsMappingResult;
     101: astore        8
     103: aload         8
     105: ifnonnull     117
     108: aload_3
     109: aload_1
     110: aload_2
     111: invokeinterface #9,  3            // InterfaceMethod javax/servlet/FilterChain.doFilter:(Ljavax/servlet/ServletRequest;Ljavax/servlet/ServletResponse;)V
     116: return
     117: aload_0
     118: getfield      #6                  // Field sc:Lorg/apache/tomcat/websocket/server/WsServerContainer;
     121: aload         4
     123: aload         5
     125: aload         8
     127: invokevirtual #19                 // Method org/apache/tomcat/websocket/server/WsMappingResult.getConfig:()Ljavax/websocket/server/ServerEndpointConfig;
     130: aload         8
     132: invokevirtual #20                 // Method org/apache/tomcat/websocket/server/WsMappingResult.getPathParams:()Ljava/util/Map;
     135: invokestatic  #21                 // Method org/apache/tomcat/websocket/server/UpgradeUtil.doUpgrade:(Lorg/apache/tomcat/websocket/server/WsServerContainer;Ljavax/servlet/http/HttpServletRequest;Ljavax/servlet/http/HttpServletResponse;Ljavax/websocket/server/ServerEndpointConfig;Ljava/util/Map;)V
     138: return

  public void destroy();
    Code:
       0: return
}
