Compiled from "ChannelServiceName.java"
public abstract class org.wildfly.clustering.jgroups.spi.service.ChannelServiceName extends java.lang.Enum<org.wildfly.clustering.jgroups.spi.service.ChannelServiceName> implements org.wildfly.clustering.jgroups.spi.service.ChannelServiceNameFactory {
  public static final org.wildfly.clustering.jgroups.spi.service.ChannelServiceName CHANNEL;

  public static final org.wildfly.clustering.jgroups.spi.service.ChannelServiceName FACTORY;

  public static final org.wildfly.clustering.jgroups.spi.service.ChannelServiceName CONNECTOR;

  private static final org.wildfly.clustering.jgroups.spi.service.ChannelServiceName[] $VALUES;

  public static org.wildfly.clustering.jgroups.spi.service.ChannelServiceName[] values();
    Code:
       0: getstatic     #2                  // Field $VALUES:[Lorg/wildfly/clustering/jgroups/spi/service/ChannelServiceName;
       3: invokevirtual #3                  // Method "[Lorg/wildfly/clustering/jgroups/spi/service/ChannelServiceName;".clone:()Ljava/lang/Object;
       6: checkcast     #4                  // class "[Lorg/wildfly/clustering/jgroups/spi/service/ChannelServiceName;"
       9: areturn

  public static org.wildfly.clustering.jgroups.spi.service.ChannelServiceName valueOf(java.lang.String);
    Code:
       0: ldc           #5                  // class org/wildfly/clustering/jgroups/spi/service/ChannelServiceName
       2: aload_0
       3: invokestatic  #6                  // Method java/lang/Enum.valueOf:(Ljava/lang/Class;Ljava/lang/String;)Ljava/lang/Enum;
       6: checkcast     #5                  // class org/wildfly/clustering/jgroups/spi/service/ChannelServiceName
       9: areturn

  private org.wildfly.clustering.jgroups.spi.service.ChannelServiceName();
    Code:
       0: aload_0
       1: aload_1
       2: iload_2
       3: invokespecial #7                  // Method java/lang/Enum."<init>":(Ljava/lang/String;I)V
       6: return

  public org.jboss.msc.service.ServiceName getServiceName();
    Code:
       0: aload_0
       1: ldc           #9                  // String default
       3: invokevirtual #10                 // Method getServiceName:(Ljava/lang/String;)Lorg/jboss/msc/service/ServiceName;
       6: areturn

  org.wildfly.clustering.jgroups.spi.service.ChannelServiceName(java.lang.String, int, org.wildfly.clustering.jgroups.spi.service.ChannelServiceName$1);
    Code:
       0: aload_0
       1: aload_1
       2: iload_2
       3: invokespecial #1                  // Method "<init>":(Ljava/lang/String;I)V
       6: return

  static {};
    Code:
       0: new           #11                 // class org/wildfly/clustering/jgroups/spi/service/ChannelServiceName$1
       3: dup
       4: ldc           #12                 // String CHANNEL
       6: iconst_0
       7: invokespecial #13                 // Method org/wildfly/clustering/jgroups/spi/service/ChannelServiceName$1."<init>":(Ljava/lang/String;I)V
      10: putstatic     #14                 // Field CHANNEL:Lorg/wildfly/clustering/jgroups/spi/service/ChannelServiceName;
      13: new           #15                 // class org/wildfly/clustering/jgroups/spi/service/ChannelServiceName$2
      16: dup
      17: ldc           #16                 // String FACTORY
      19: iconst_1
      20: invokespecial #17                 // Method org/wildfly/clustering/jgroups/spi/service/ChannelServiceName$2."<init>":(Ljava/lang/String;I)V
      23: putstatic     #18                 // Field FACTORY:Lorg/wildfly/clustering/jgroups/spi/service/ChannelServiceName;
      26: new           #19                 // class org/wildfly/clustering/jgroups/spi/service/ChannelServiceName$3
      29: dup
      30: ldc           #20                 // String CONNECTOR
      32: iconst_2
      33: invokespecial #21                 // Method org/wildfly/clustering/jgroups/spi/service/ChannelServiceName$3."<init>":(Ljava/lang/String;I)V
      36: putstatic     #22                 // Field CONNECTOR:Lorg/wildfly/clustering/jgroups/spi/service/ChannelServiceName;
      39: iconst_3
      40: anewarray     #5                  // class org/wildfly/clustering/jgroups/spi/service/ChannelServiceName
      43: dup
      44: iconst_0
      45: getstatic     #14                 // Field CHANNEL:Lorg/wildfly/clustering/jgroups/spi/service/ChannelServiceName;
      48: aastore
      49: dup
      50: iconst_1
      51: getstatic     #18                 // Field FACTORY:Lorg/wildfly/clustering/jgroups/spi/service/ChannelServiceName;
      54: aastore
      55: dup
      56: iconst_2
      57: getstatic     #22                 // Field CONNECTOR:Lorg/wildfly/clustering/jgroups/spi/service/ChannelServiceName;
      60: aastore
      61: putstatic     #2                  // Field $VALUES:[Lorg/wildfly/clustering/jgroups/spi/service/ChannelServiceName;
      64: return
}
