Compiled from "GridFSFindIterableImpl.java"
class com.mongodb.client.gridfs.GridFSFindIterableImpl implements com.mongodb.client.gridfs.GridFSFindIterable {
  private final com.mongodb.client.FindIterable<com.mongodb.client.gridfs.model.GridFSFile> underlying;

  com.mongodb.client.gridfs.GridFSFindIterableImpl(com.mongodb.client.FindIterable<com.mongodb.client.gridfs.model.GridFSFile>);
    Code:
       0: aload_0
       1: invokespecial #1                  // Method java/lang/Object."<init>":()V
       4: aload_0
       5: aload_1
       6: putfield      #2                  // Field underlying:Lcom/mongodb/client/FindIterable;
       9: return

  public com.mongodb.client.gridfs.GridFSFindIterable sort(org.bson.conversions.Bson);
    Code:
       0: aload_0
       1: getfield      #2                  // Field underlying:Lcom/mongodb/client/FindIterable;
       4: aload_1
       5: invokeinterface #3,  2            // InterfaceMethod com/mongodb/client/FindIterable.sort:(Lorg/bson/conversions/Bson;)Lcom/mongodb/client/FindIterable;
      10: pop
      11: aload_0
      12: areturn

  public com.mongodb.client.gridfs.GridFSFindIterable skip(int);
    Code:
       0: aload_0
       1: getfield      #2                  // Field underlying:Lcom/mongodb/client/FindIterable;
       4: iload_1
       5: invokeinterface #4,  2            // InterfaceMethod com/mongodb/client/FindIterable.skip:(I)Lcom/mongodb/client/FindIterable;
      10: pop
      11: aload_0
      12: areturn

  public com.mongodb.client.gridfs.GridFSFindIterable limit(int);
    Code:
       0: aload_0
       1: getfield      #2                  // Field underlying:Lcom/mongodb/client/FindIterable;
       4: iload_1
       5: invokeinterface #5,  2            // InterfaceMethod com/mongodb/client/FindIterable.limit:(I)Lcom/mongodb/client/FindIterable;
      10: pop
      11: aload_0
      12: areturn

  public com.mongodb.client.gridfs.GridFSFindIterable filter(org.bson.conversions.Bson);
    Code:
       0: aload_0
       1: getfield      #2                  // Field underlying:Lcom/mongodb/client/FindIterable;
       4: aload_1
       5: invokeinterface #6,  2            // InterfaceMethod com/mongodb/client/FindIterable.filter:(Lorg/bson/conversions/Bson;)Lcom/mongodb/client/FindIterable;
      10: pop
      11: aload_0
      12: areturn

  public com.mongodb.client.gridfs.GridFSFindIterable maxTime(long, java.util.concurrent.TimeUnit);
    Code:
       0: aload_0
       1: getfield      #2                  // Field underlying:Lcom/mongodb/client/FindIterable;
       4: lload_1
       5: aload_3
       6: invokeinterface #7,  4            // InterfaceMethod com/mongodb/client/FindIterable.maxTime:(JLjava/util/concurrent/TimeUnit;)Lcom/mongodb/client/FindIterable;
      11: pop
      12: aload_0
      13: areturn

  public com.mongodb.client.gridfs.GridFSFindIterable batchSize(int);
    Code:
       0: aload_0
       1: getfield      #2                  // Field underlying:Lcom/mongodb/client/FindIterable;
       4: iload_1
       5: invokeinterface #8,  2            // InterfaceMethod com/mongodb/client/FindIterable.batchSize:(I)Lcom/mongodb/client/FindIterable;
      10: pop
      11: aload_0
      12: areturn

  public com.mongodb.client.gridfs.GridFSFindIterable collation(com.mongodb.client.model.Collation);
    Code:
       0: aload_0
       1: getfield      #2                  // Field underlying:Lcom/mongodb/client/FindIterable;
       4: aload_1
       5: invokeinterface #9,  2            // InterfaceMethod com/mongodb/client/FindIterable.collation:(Lcom/mongodb/client/model/Collation;)Lcom/mongodb/client/FindIterable;
      10: pop
      11: aload_0
      12: areturn

  public com.mongodb.client.gridfs.GridFSFindIterable noCursorTimeout(boolean);
    Code:
       0: aload_0
       1: getfield      #2                  // Field underlying:Lcom/mongodb/client/FindIterable;
       4: iload_1
       5: invokeinterface #10,  2           // InterfaceMethod com/mongodb/client/FindIterable.noCursorTimeout:(Z)Lcom/mongodb/client/FindIterable;
      10: pop
      11: aload_0
      12: areturn

  public com.mongodb.client.MongoCursor<com.mongodb.client.gridfs.model.GridFSFile> iterator();
    Code:
       0: aload_0
       1: getfield      #2                  // Field underlying:Lcom/mongodb/client/FindIterable;
       4: invokeinterface #11,  1           // InterfaceMethod com/mongodb/client/FindIterable.iterator:()Lcom/mongodb/client/MongoCursor;
       9: areturn

  public com.mongodb.client.gridfs.model.GridFSFile first();
    Code:
       0: aload_0
       1: getfield      #2                  // Field underlying:Lcom/mongodb/client/FindIterable;
       4: invokeinterface #12,  1           // InterfaceMethod com/mongodb/client/FindIterable.first:()Ljava/lang/Object;
       9: checkcast     #13                 // class com/mongodb/client/gridfs/model/GridFSFile
      12: areturn

  public <U> com.mongodb.client.MongoIterable<U> map(com.mongodb.Function<com.mongodb.client.gridfs.model.GridFSFile, U>);
    Code:
       0: aload_0
       1: getfield      #2                  // Field underlying:Lcom/mongodb/client/FindIterable;
       4: aload_1
       5: invokeinterface #14,  2           // InterfaceMethod com/mongodb/client/FindIterable.map:(Lcom/mongodb/Function;)Lcom/mongodb/client/MongoIterable;
      10: areturn

  public void forEach(com.mongodb.Block<? super com.mongodb.client.gridfs.model.GridFSFile>);
    Code:
       0: aload_0
       1: getfield      #2                  // Field underlying:Lcom/mongodb/client/FindIterable;
       4: aload_1
       5: invokeinterface #15,  2           // InterfaceMethod com/mongodb/client/FindIterable.forEach:(Lcom/mongodb/Block;)V
      10: return

  public <A extends java.util.Collection<? super com.mongodb.client.gridfs.model.GridFSFile>> A into(A);
    Code:
       0: aload_0
       1: getfield      #2                  // Field underlying:Lcom/mongodb/client/FindIterable;
       4: aload_1
       5: invokeinterface #16,  2           // InterfaceMethod com/mongodb/client/FindIterable.into:(Ljava/util/Collection;)Ljava/util/Collection;
      10: areturn

  public com.mongodb.client.MongoIterable batchSize(int);
    Code:
       0: aload_0
       1: iload_1
       2: invokevirtual #17                 // Method batchSize:(I)Lcom/mongodb/client/gridfs/GridFSFindIterable;
       5: areturn

  public java.lang.Object first();
    Code:
       0: aload_0
       1: invokevirtual #18                 // Method first:()Lcom/mongodb/client/gridfs/model/GridFSFile;
       4: areturn

  public java.util.Iterator iterator();
    Code:
       0: aload_0
       1: invokevirtual #19                 // Method iterator:()Lcom/mongodb/client/MongoCursor;
       4: areturn
}
