Compiled from "TimelineDomains.java"
public class org.apache.hadoop.yarn.api.records.timeline.TimelineDomains {
  private java.util.List<org.apache.hadoop.yarn.api.records.timeline.TimelineDomain> domains;

  public org.apache.hadoop.yarn.api.records.timeline.TimelineDomains();
    Code:
       0: aload_0
       1: invokespecial #1                  // Method java/lang/Object."<init>":()V
       4: aload_0
       5: new           #2                  // class java/util/ArrayList
       8: dup
       9: invokespecial #3                  // Method java/util/ArrayList."<init>":()V
      12: putfield      #4                  // Field domains:Ljava/util/List;
      15: return

  public java.util.List<org.apache.hadoop.yarn.api.records.timeline.TimelineDomain> getDomains();
    Code:
       0: aload_0
       1: getfield      #4                  // Field domains:Ljava/util/List;
       4: areturn

  public void addDomain(org.apache.hadoop.yarn.api.records.timeline.TimelineDomain);
    Code:
       0: aload_0
       1: getfield      #4                  // Field domains:Ljava/util/List;
       4: aload_1
       5: invokeinterface #5,  2            // InterfaceMethod java/util/List.add:(Ljava/lang/Object;)Z
      10: pop
      11: return

  public void addDomains(java.util.List<org.apache.hadoop.yarn.api.records.timeline.TimelineDomain>);
    Code:
       0: aload_0
       1: getfield      #4                  // Field domains:Ljava/util/List;
       4: aload_1
       5: invokeinterface #6,  2            // InterfaceMethod java/util/List.addAll:(Ljava/util/Collection;)Z
      10: pop
      11: return

  public void setDomains(java.util.List<org.apache.hadoop.yarn.api.records.timeline.TimelineDomain>);
    Code:
       0: aload_0
       1: aload_1
       2: putfield      #4                  // Field domains:Ljava/util/List;
       5: return
}
