Compiled from "TimelineEvent.java"
public class org.apache.hadoop.yarn.api.records.timeline.TimelineEvent implements java.lang.Comparable<org.apache.hadoop.yarn.api.records.timeline.TimelineEvent> {
  private long timestamp;

  private java.lang.String eventType;

  private java.util.HashMap<java.lang.String, java.lang.Object> eventInfo;

  public org.apache.hadoop.yarn.api.records.timeline.TimelineEvent();
    Code:
       0: aload_0
       1: invokespecial #1                  // Method java/lang/Object."<init>":()V
       4: aload_0
       5: new           #2                  // class java/util/HashMap
       8: dup
       9: invokespecial #3                  // Method java/util/HashMap."<init>":()V
      12: putfield      #4                  // Field eventInfo:Ljava/util/HashMap;
      15: return

  public long getTimestamp();
    Code:
       0: aload_0
       1: getfield      #5                  // Field timestamp:J
       4: lreturn

  public void setTimestamp(long);
    Code:
       0: aload_0
       1: lload_1
       2: putfield      #5                  // Field timestamp:J
       5: return

  public java.lang.String getEventType();
    Code:
       0: aload_0
       1: getfield      #6                  // Field eventType:Ljava/lang/String;
       4: areturn

  public void setEventType(java.lang.String);
    Code:
       0: aload_0
       1: aload_1
       2: putfield      #6                  // Field eventType:Ljava/lang/String;
       5: return

  public java.util.Map<java.lang.String, java.lang.Object> getEventInfo();
    Code:
       0: aload_0
       1: getfield      #4                  // Field eventInfo:Ljava/util/HashMap;
       4: areturn

  public java.util.HashMap<java.lang.String, java.lang.Object> getEventInfoJAXB();
    Code:
       0: aload_0
       1: getfield      #4                  // Field eventInfo:Ljava/util/HashMap;
       4: areturn

  public void addEventInfo(java.lang.String, java.lang.Object);
    Code:
       0: aload_0
       1: getfield      #4                  // Field eventInfo:Ljava/util/HashMap;
       4: aload_1
       5: aload_2
       6: invokevirtual #7                  // Method java/util/HashMap.put:(Ljava/lang/Object;Ljava/lang/Object;)Ljava/lang/Object;
       9: pop
      10: return

  public void addEventInfo(java.util.Map<java.lang.String, java.lang.Object>);
    Code:
       0: aload_0
       1: getfield      #4                  // Field eventInfo:Ljava/util/HashMap;
       4: aload_1
       5: invokevirtual #8                  // Method java/util/HashMap.putAll:(Ljava/util/Map;)V
       8: return

  public void setEventInfo(java.util.Map<java.lang.String, java.lang.Object>);
    Code:
       0: aload_0
       1: aload_1
       2: invokestatic  #9                  // Method org/apache/hadoop/yarn/util/TimelineServiceHelper.mapCastToHashMap:(Ljava/util/Map;)Ljava/util/HashMap;
       5: putfield      #4                  // Field eventInfo:Ljava/util/HashMap;
       8: return

  public int compareTo(org.apache.hadoop.yarn.api.records.timeline.TimelineEvent);
    Code:
       0: aload_0
       1: getfield      #5                  // Field timestamp:J
       4: aload_1
       5: getfield      #5                  // Field timestamp:J
       8: lcmp
       9: ifle          14
      12: iconst_m1
      13: ireturn
      14: aload_0
      15: getfield      #5                  // Field timestamp:J
      18: aload_1
      19: getfield      #5                  // Field timestamp:J
      22: lcmp
      23: ifge          28
      26: iconst_1
      27: ireturn
      28: aload_0
      29: getfield      #6                  // Field eventType:Ljava/lang/String;
      32: aload_1
      33: getfield      #6                  // Field eventType:Ljava/lang/String;
      36: invokevirtual #10                 // Method java/lang/String.compareTo:(Ljava/lang/String;)I
      39: ireturn

  public boolean equals(java.lang.Object);
    Code:
       0: aload_0
       1: aload_1
       2: if_acmpne     7
       5: iconst_1
       6: ireturn
       7: aload_1
       8: ifnull        22
      11: aload_0
      12: invokevirtual #11                 // Method java/lang/Object.getClass:()Ljava/lang/Class;
      15: aload_1
      16: invokevirtual #11                 // Method java/lang/Object.getClass:()Ljava/lang/Class;
      19: if_acmpeq     24
      22: iconst_0
      23: ireturn
      24: aload_1
      25: checkcast     #12                 // class org/apache/hadoop/yarn/api/records/timeline/TimelineEvent
      28: astore_2
      29: aload_0
      30: getfield      #5                  // Field timestamp:J
      33: aload_2
      34: getfield      #5                  // Field timestamp:J
      37: lcmp
      38: ifeq          43
      41: iconst_0
      42: ireturn
      43: aload_0
      44: getfield      #6                  // Field eventType:Ljava/lang/String;
      47: aload_2
      48: getfield      #6                  // Field eventType:Ljava/lang/String;
      51: invokevirtual #13                 // Method java/lang/String.equals:(Ljava/lang/Object;)Z
      54: ifne          59
      57: iconst_0
      58: ireturn
      59: aload_0
      60: getfield      #4                  // Field eventInfo:Ljava/util/HashMap;
      63: ifnull        83
      66: aload_0
      67: getfield      #4                  // Field eventInfo:Ljava/util/HashMap;
      70: aload_2
      71: getfield      #4                  // Field eventInfo:Ljava/util/HashMap;
      74: invokevirtual #14                 // Method java/util/HashMap.equals:(Ljava/lang/Object;)Z
      77: ifne          92
      80: goto          90
      83: aload_2
      84: getfield      #4                  // Field eventInfo:Ljava/util/HashMap;
      87: ifnull        92
      90: iconst_0
      91: ireturn
      92: iconst_1
      93: ireturn

  public int hashCode();
    Code:
       0: aload_0
       1: getfield      #5                  // Field timestamp:J
       4: aload_0
       5: getfield      #5                  // Field timestamp:J
       8: bipush        32
      10: lushr
      11: lxor
      12: l2i
      13: istore_1
      14: bipush        31
      16: iload_1
      17: imul
      18: aload_0
      19: getfield      #6                  // Field eventType:Ljava/lang/String;
      22: invokevirtual #15                 // Method java/lang/String.hashCode:()I
      25: iadd
      26: istore_1
      27: bipush        31
      29: iload_1
      30: imul
      31: aload_0
      32: getfield      #4                  // Field eventInfo:Ljava/util/HashMap;
      35: ifnull        48
      38: aload_0
      39: getfield      #4                  // Field eventInfo:Ljava/util/HashMap;
      42: invokevirtual #16                 // Method java/util/HashMap.hashCode:()I
      45: goto          49
      48: iconst_0
      49: iadd
      50: istore_1
      51: iload_1
      52: ireturn

  public int compareTo(java.lang.Object);
    Code:
       0: aload_0
       1: aload_1
       2: checkcast     #12                 // class org/apache/hadoop/yarn/api/records/timeline/TimelineEvent
       5: invokevirtual #17                 // Method compareTo:(Lorg/apache/hadoop/yarn/api/records/timeline/TimelineEvent;)I
       8: ireturn
}
