Compiled from "DefaultKnativeClient.java"
public class io.dekorate.deps.knative.client.DefaultKnativeClient extends io.dekorate.deps.kubernetes.client.BaseClient implements io.dekorate.deps.knative.client.NamespacedKnativeClient {
  public io.dekorate.deps.knative.client.DefaultKnativeClient();
    Code:
       0: aload_0
       1: invokespecial #11                 // Method io/dekorate/deps/kubernetes/client/BaseClient."<init>":()V
       4: return

  public io.dekorate.deps.knative.client.DefaultKnativeClient(io.dekorate.deps.kubernetes.client.Config);
    Code:
       0: aload_0
       1: aload_1
       2: invokespecial #16                 // Method io/dekorate/deps/kubernetes/client/BaseClient."<init>":(Lio/dekorate/deps/kubernetes/client/Config;)V
       5: return

  public io.dekorate.deps.knative.client.DefaultKnativeClient(io.dekorate.deps.okhttp3.OkHttpClient, io.dekorate.deps.kubernetes.client.Config);
    Code:
       0: aload_0
       1: aload_1
       2: aload_2
       3: invokespecial #21                 // Method io/dekorate/deps/kubernetes/client/BaseClient."<init>":(Lio/dekorate/deps/okhttp3/OkHttpClient;Lio/dekorate/deps/kubernetes/client/Config;)V
       6: return

  public io.dekorate.deps.knative.client.NamespacedKnativeClient inAnyNamespace();
    Code:
       0: aload_0
       1: aconst_null
       2: invokevirtual #29                 // Method inNamespace:(Ljava/lang/String;)Lio/dekorate/deps/knative/client/NamespacedKnativeClient;
       5: areturn

  public io.dekorate.deps.knative.client.NamespacedKnativeClient inNamespace(java.lang.String);
    Code:
       0: new           #31                 // class io/dekorate/deps/kubernetes/client/ConfigBuilder
       3: dup
       4: aload_0
       5: invokevirtual #35                 // Method getConfiguration:()Lio/dekorate/deps/kubernetes/client/Config;
       8: invokespecial #36                 // Method io/dekorate/deps/kubernetes/client/ConfigBuilder."<init>":(Lio/dekorate/deps/kubernetes/client/Config;)V
      11: aload_1
      12: invokevirtual #40                 // Method io/dekorate/deps/kubernetes/client/ConfigBuilder.withNamespace:(Ljava/lang/String;)Lio/dekorate/deps/kubernetes/client/ConfigFluent;
      15: checkcast     #31                 // class io/dekorate/deps/kubernetes/client/ConfigBuilder
      18: invokevirtual #43                 // Method io/dekorate/deps/kubernetes/client/ConfigBuilder.build:()Lio/dekorate/deps/kubernetes/client/Config;
      21: astore_2
      22: new           #2                  // class io/dekorate/deps/knative/client/DefaultKnativeClient
      25: dup
      26: aload_0
      27: invokevirtual #47                 // Method getHttpClient:()Lio/dekorate/deps/okhttp3/OkHttpClient;
      30: aload_2
      31: invokespecial #48                 // Method "<init>":(Lio/dekorate/deps/okhttp3/OkHttpClient;Lio/dekorate/deps/kubernetes/client/Config;)V
      34: areturn

  public io.dekorate.deps.kubernetes.client.dsl.FunctionCallable<io.dekorate.deps.knative.client.NamespacedKnativeClient> withRequestConfig(io.dekorate.deps.kubernetes.client.RequestConfig);
    Code:
       0: new           #56                 // class io/dekorate/deps/kubernetes/client/WithRequestCallable
       3: dup
       4: aload_0
       5: aload_1
       6: invokespecial #59                 // Method io/dekorate/deps/kubernetes/client/WithRequestCallable."<init>":(Lio/dekorate/deps/kubernetes/client/Client;Lio/dekorate/deps/kubernetes/client/RequestConfig;)V
       9: areturn

  public io.dekorate.deps.kubernetes.client.dsl.MixedOperation<io.dekorate.deps.knative.serving.v1.Service, io.dekorate.deps.knative.serving.v1.ServiceList, io.dekorate.deps.knative.serving.v1.DoneableService, io.dekorate.deps.kubernetes.client.dsl.Resource<io.dekorate.deps.knative.serving.v1.Service, io.dekorate.deps.knative.serving.v1.DoneableService>> services();
    Code:
       0: new           #66                 // class io/dekorate/deps/knative/client/serving/v1/internal/ServiceOperationsImpl
       3: dup
       4: aload_0
       5: invokevirtual #47                 // Method getHttpClient:()Lio/dekorate/deps/okhttp3/OkHttpClient;
       8: aload_0
       9: invokevirtual #35                 // Method getConfiguration:()Lio/dekorate/deps/kubernetes/client/Config;
      12: invokespecial #67                 // Method io/dekorate/deps/knative/client/serving/v1/internal/ServiceOperationsImpl."<init>":(Lio/dekorate/deps/okhttp3/OkHttpClient;Lio/dekorate/deps/kubernetes/client/Config;)V
      15: areturn

  public io.dekorate.deps.kubernetes.client.dsl.MixedOperation<io.dekorate.deps.knative.serving.v1.Route, io.dekorate.deps.knative.serving.v1.RouteList, io.dekorate.deps.knative.serving.v1.DoneableRoute, io.dekorate.deps.kubernetes.client.dsl.Resource<io.dekorate.deps.knative.serving.v1.Route, io.dekorate.deps.knative.serving.v1.DoneableRoute>> routes();
    Code:
       0: new           #71                 // class io/dekorate/deps/knative/client/serving/v1/internal/RouteOperationsImpl
       3: dup
       4: aload_0
       5: invokevirtual #47                 // Method getHttpClient:()Lio/dekorate/deps/okhttp3/OkHttpClient;
       8: aload_0
       9: invokevirtual #35                 // Method getConfiguration:()Lio/dekorate/deps/kubernetes/client/Config;
      12: invokespecial #72                 // Method io/dekorate/deps/knative/client/serving/v1/internal/RouteOperationsImpl."<init>":(Lio/dekorate/deps/okhttp3/OkHttpClient;Lio/dekorate/deps/kubernetes/client/Config;)V
      15: areturn

  public io.dekorate.deps.kubernetes.client.dsl.MixedOperation<io.dekorate.deps.knative.serving.v1.Revision, io.dekorate.deps.knative.serving.v1.RevisionList, io.dekorate.deps.knative.serving.v1.DoneableRevision, io.dekorate.deps.kubernetes.client.dsl.Resource<io.dekorate.deps.knative.serving.v1.Revision, io.dekorate.deps.knative.serving.v1.DoneableRevision>> revisions();
    Code:
       0: new           #76                 // class io/dekorate/deps/knative/client/serving/v1/internal/RevisionOperationsImpl
       3: dup
       4: aload_0
       5: invokevirtual #47                 // Method getHttpClient:()Lio/dekorate/deps/okhttp3/OkHttpClient;
       8: aload_0
       9: invokevirtual #35                 // Method getConfiguration:()Lio/dekorate/deps/kubernetes/client/Config;
      12: invokespecial #77                 // Method io/dekorate/deps/knative/client/serving/v1/internal/RevisionOperationsImpl."<init>":(Lio/dekorate/deps/okhttp3/OkHttpClient;Lio/dekorate/deps/kubernetes/client/Config;)V
      15: areturn

  public io.dekorate.deps.kubernetes.client.dsl.MixedOperation<io.dekorate.deps.knative.serving.v1.Configuration, io.dekorate.deps.knative.serving.v1.ConfigurationList, io.dekorate.deps.knative.serving.v1.DoneableConfiguration, io.dekorate.deps.kubernetes.client.dsl.Resource<io.dekorate.deps.knative.serving.v1.Configuration, io.dekorate.deps.knative.serving.v1.DoneableConfiguration>> configurations();
    Code:
       0: new           #81                 // class io/dekorate/deps/knative/client/serving/v1/internal/ConfigurationOperationsImpl
       3: dup
       4: aload_0
       5: invokevirtual #47                 // Method getHttpClient:()Lio/dekorate/deps/okhttp3/OkHttpClient;
       8: aload_0
       9: invokevirtual #35                 // Method getConfiguration:()Lio/dekorate/deps/kubernetes/client/Config;
      12: invokespecial #82                 // Method io/dekorate/deps/knative/client/serving/v1/internal/ConfigurationOperationsImpl."<init>":(Lio/dekorate/deps/okhttp3/OkHttpClient;Lio/dekorate/deps/kubernetes/client/Config;)V
      15: areturn

  public io.dekorate.deps.kubernetes.client.dsl.MixedOperation<io.dekorate.deps.knative.eventing.v1alpha1.Broker, io.dekorate.deps.knative.eventing.v1alpha1.BrokerList, io.dekorate.deps.knative.eventing.v1alpha1.DoneableBroker, io.dekorate.deps.kubernetes.client.dsl.Resource<io.dekorate.deps.knative.eventing.v1alpha1.Broker, io.dekorate.deps.knative.eventing.v1alpha1.DoneableBroker>> brokers();
    Code:
       0: new           #86                 // class io/dekorate/deps/knative/client/eventing/v1alpha1/internal/BrokerOperationsImpl
       3: dup
       4: aload_0
       5: invokevirtual #47                 // Method getHttpClient:()Lio/dekorate/deps/okhttp3/OkHttpClient;
       8: aload_0
       9: invokevirtual #35                 // Method getConfiguration:()Lio/dekorate/deps/kubernetes/client/Config;
      12: invokespecial #87                 // Method io/dekorate/deps/knative/client/eventing/v1alpha1/internal/BrokerOperationsImpl."<init>":(Lio/dekorate/deps/okhttp3/OkHttpClient;Lio/dekorate/deps/kubernetes/client/Config;)V
      15: areturn

  public io.dekorate.deps.kubernetes.client.dsl.MixedOperation<io.dekorate.deps.knative.eventing.v1alpha1.Trigger, io.dekorate.deps.knative.eventing.v1alpha1.TriggerList, io.dekorate.deps.knative.eventing.v1alpha1.DoneableTrigger, io.dekorate.deps.kubernetes.client.dsl.Resource<io.dekorate.deps.knative.eventing.v1alpha1.Trigger, io.dekorate.deps.knative.eventing.v1alpha1.DoneableTrigger>> triggers();
    Code:
       0: new           #91                 // class io/dekorate/deps/knative/client/eventing/v1alpha1/internal/TriggerOperationsImpl
       3: dup
       4: aload_0
       5: invokevirtual #47                 // Method getHttpClient:()Lio/dekorate/deps/okhttp3/OkHttpClient;
       8: aload_0
       9: invokevirtual #35                 // Method getConfiguration:()Lio/dekorate/deps/kubernetes/client/Config;
      12: invokespecial #92                 // Method io/dekorate/deps/knative/client/eventing/v1alpha1/internal/TriggerOperationsImpl."<init>":(Lio/dekorate/deps/okhttp3/OkHttpClient;Lio/dekorate/deps/kubernetes/client/Config;)V
      15: areturn

  public io.dekorate.deps.kubernetes.client.dsl.MixedOperation<io.dekorate.deps.knative.messaging.v1alpha1.Channel, io.dekorate.deps.knative.messaging.v1alpha1.ChannelList, io.dekorate.deps.knative.messaging.v1alpha1.DoneableChannel, io.dekorate.deps.kubernetes.client.dsl.Resource<io.dekorate.deps.knative.messaging.v1alpha1.Channel, io.dekorate.deps.knative.messaging.v1alpha1.DoneableChannel>> channels();
    Code:
       0: new           #96                 // class io/dekorate/deps/knative/client/messaging/v1alpha1/internal/ChannelOperationsImpl
       3: dup
       4: aload_0
       5: invokevirtual #47                 // Method getHttpClient:()Lio/dekorate/deps/okhttp3/OkHttpClient;
       8: aload_0
       9: invokevirtual #35                 // Method getConfiguration:()Lio/dekorate/deps/kubernetes/client/Config;
      12: invokespecial #97                 // Method io/dekorate/deps/knative/client/messaging/v1alpha1/internal/ChannelOperationsImpl."<init>":(Lio/dekorate/deps/okhttp3/OkHttpClient;Lio/dekorate/deps/kubernetes/client/Config;)V
      15: areturn

  public io.dekorate.deps.kubernetes.client.dsl.MixedOperation<io.dekorate.deps.knative.messaging.v1alpha1.Subscription, io.dekorate.deps.knative.messaging.v1alpha1.SubscriptionList, io.dekorate.deps.knative.messaging.v1alpha1.DoneableSubscription, io.dekorate.deps.kubernetes.client.dsl.Resource<io.dekorate.deps.knative.messaging.v1alpha1.Subscription, io.dekorate.deps.knative.messaging.v1alpha1.DoneableSubscription>> subscriptions();
    Code:
       0: new           #101                // class io/dekorate/deps/knative/client/messaging/v1alpha1/internal/SubscriptionOperationsImpl
       3: dup
       4: aload_0
       5: invokevirtual #47                 // Method getHttpClient:()Lio/dekorate/deps/okhttp3/OkHttpClient;
       8: aload_0
       9: invokevirtual #35                 // Method getConfiguration:()Lio/dekorate/deps/kubernetes/client/Config;
      12: invokespecial #102                // Method io/dekorate/deps/knative/client/messaging/v1alpha1/internal/SubscriptionOperationsImpl."<init>":(Lio/dekorate/deps/okhttp3/OkHttpClient;Lio/dekorate/deps/kubernetes/client/Config;)V
      15: areturn

  public io.dekorate.deps.kubernetes.client.dsl.MixedOperation<io.dekorate.deps.knative.eventing.v1alpha1.EventType, io.dekorate.deps.knative.eventing.v1alpha1.EventTypeList, io.dekorate.deps.knative.eventing.v1alpha1.DoneableEventType, io.dekorate.deps.kubernetes.client.dsl.Resource<io.dekorate.deps.knative.eventing.v1alpha1.EventType, io.dekorate.deps.knative.eventing.v1alpha1.DoneableEventType>> eventTypes();
    Code:
       0: new           #106                // class io/dekorate/deps/knative/client/eventing/v1alpha1/internal/EventTypeOperationsImpl
       3: dup
       4: aload_0
       5: invokevirtual #47                 // Method getHttpClient:()Lio/dekorate/deps/okhttp3/OkHttpClient;
       8: aload_0
       9: invokevirtual #35                 // Method getConfiguration:()Lio/dekorate/deps/kubernetes/client/Config;
      12: invokespecial #107                // Method io/dekorate/deps/knative/client/eventing/v1alpha1/internal/EventTypeOperationsImpl."<init>":(Lio/dekorate/deps/okhttp3/OkHttpClient;Lio/dekorate/deps/kubernetes/client/Config;)V
      15: areturn

  public io.dekorate.deps.kubernetes.client.dsl.MixedOperation<io.dekorate.deps.knative.flows.v1alpha1.Sequence, io.dekorate.deps.knative.flows.v1alpha1.SequenceList, io.dekorate.deps.knative.flows.v1alpha1.DoneableSequence, io.dekorate.deps.kubernetes.client.dsl.Resource<io.dekorate.deps.knative.flows.v1alpha1.Sequence, io.dekorate.deps.knative.flows.v1alpha1.DoneableSequence>> sequences();
    Code:
       0: new           #111                // class io/dekorate/deps/knative/client/flows/v1alpha1/internal/SequenceOperationsImpl
       3: dup
       4: aload_0
       5: invokevirtual #47                 // Method getHttpClient:()Lio/dekorate/deps/okhttp3/OkHttpClient;
       8: aload_0
       9: invokevirtual #35                 // Method getConfiguration:()Lio/dekorate/deps/kubernetes/client/Config;
      12: invokespecial #112                // Method io/dekorate/deps/knative/client/flows/v1alpha1/internal/SequenceOperationsImpl."<init>":(Lio/dekorate/deps/okhttp3/OkHttpClient;Lio/dekorate/deps/kubernetes/client/Config;)V
      15: areturn

  public io.dekorate.deps.kubernetes.client.dsl.MixedOperation<io.dekorate.deps.knative.messaging.v1alpha1.InMemoryChannel, io.dekorate.deps.knative.messaging.v1alpha1.InMemoryChannelList, io.dekorate.deps.knative.messaging.v1alpha1.DoneableInMemoryChannel, io.dekorate.deps.kubernetes.client.dsl.Resource<io.dekorate.deps.knative.messaging.v1alpha1.InMemoryChannel, io.dekorate.deps.knative.messaging.v1alpha1.DoneableInMemoryChannel>> inMemoryChannels();
    Code:
       0: new           #116                // class io/dekorate/deps/knative/client/messaging/v1alpha1/internal/InMemoryChannelOperationsImpl
       3: dup
       4: aload_0
       5: invokevirtual #47                 // Method getHttpClient:()Lio/dekorate/deps/okhttp3/OkHttpClient;
       8: aload_0
       9: invokevirtual #35                 // Method getConfiguration:()Lio/dekorate/deps/kubernetes/client/Config;
      12: invokespecial #117                // Method io/dekorate/deps/knative/client/messaging/v1alpha1/internal/InMemoryChannelOperationsImpl."<init>":(Lio/dekorate/deps/okhttp3/OkHttpClient;Lio/dekorate/deps/kubernetes/client/Config;)V
      15: areturn

  public java.lang.Object inNamespace(java.lang.String);
    Code:
       0: aload_0
       1: aload_1
       2: invokevirtual #29                 // Method inNamespace:(Ljava/lang/String;)Lio/dekorate/deps/knative/client/NamespacedKnativeClient;
       5: areturn

  public java.lang.Object inAnyNamespace();
    Code:
       0: aload_0
       1: invokevirtual #121                // Method inAnyNamespace:()Lio/dekorate/deps/knative/client/NamespacedKnativeClient;
       4: areturn
}
