Compiled from "ParserImpl.java"
class org.yaml.snakeyaml.parser.ParserImpl$ParseDocumentStart implements org.yaml.snakeyaml.parser.Production {
  final org.yaml.snakeyaml.parser.ParserImpl this$0;

  private org.yaml.snakeyaml.parser.ParserImpl$ParseDocumentStart(org.yaml.snakeyaml.parser.ParserImpl);
    Code:
       0: aload_0
       1: aload_1
       2: putfield      #2                  // Field this$0:Lorg/yaml/snakeyaml/parser/ParserImpl;
       5: aload_0
       6: invokespecial #3                  // Method java/lang/Object."<init>":()V
       9: return

  public org.yaml.snakeyaml.events.Event produce();
    Code:
       0: aload_0
       1: getfield      #2                  // Field this$0:Lorg/yaml/snakeyaml/parser/ParserImpl;
       4: getfield      #4                  // Field org/yaml/snakeyaml/parser/ParserImpl.scanner:Lorg/yaml/snakeyaml/scanner/Scanner;
       7: iconst_1
       8: anewarray     #5                  // class org/yaml/snakeyaml/tokens/Token$ID
      11: dup
      12: iconst_0
      13: getstatic     #6                  // Field org/yaml/snakeyaml/tokens/Token$ID.Comment:Lorg/yaml/snakeyaml/tokens/Token$ID;
      16: aastore
      17: invokeinterface #7,  2            // InterfaceMethod org/yaml/snakeyaml/scanner/Scanner.checkToken:([Lorg/yaml/snakeyaml/tokens/Token$ID;)Z
      22: ifeq          67
      25: aload_0
      26: getfield      #2                  // Field this$0:Lorg/yaml/snakeyaml/parser/ParserImpl;
      29: new           #8                  // class org/yaml/snakeyaml/parser/ParserImpl$ParseDocumentStart
      32: dup
      33: aload_0
      34: getfield      #2                  // Field this$0:Lorg/yaml/snakeyaml/parser/ParserImpl;
      37: invokespecial #1                  // Method "<init>":(Lorg/yaml/snakeyaml/parser/ParserImpl;)V
      40: invokestatic  #9                  // Method org/yaml/snakeyaml/parser/ParserImpl.access$102:(Lorg/yaml/snakeyaml/parser/ParserImpl;Lorg/yaml/snakeyaml/parser/Production;)Lorg/yaml/snakeyaml/parser/Production;
      43: pop
      44: aload_0
      45: getfield      #2                  // Field this$0:Lorg/yaml/snakeyaml/parser/ParserImpl;
      48: aload_0
      49: getfield      #2                  // Field this$0:Lorg/yaml/snakeyaml/parser/ParserImpl;
      52: getfield      #4                  // Field org/yaml/snakeyaml/parser/ParserImpl.scanner:Lorg/yaml/snakeyaml/scanner/Scanner;
      55: invokeinterface #10,  1           // InterfaceMethod org/yaml/snakeyaml/scanner/Scanner.getToken:()Lorg/yaml/snakeyaml/tokens/Token;
      60: checkcast     #11                 // class org/yaml/snakeyaml/tokens/CommentToken
      63: invokestatic  #12                 // Method org/yaml/snakeyaml/parser/ParserImpl.access$300:(Lorg/yaml/snakeyaml/parser/ParserImpl;Lorg/yaml/snakeyaml/tokens/CommentToken;)Lorg/yaml/snakeyaml/events/CommentEvent;
      66: areturn
      67: aload_0
      68: getfield      #2                  // Field this$0:Lorg/yaml/snakeyaml/parser/ParserImpl;
      71: getfield      #4                  // Field org/yaml/snakeyaml/parser/ParserImpl.scanner:Lorg/yaml/snakeyaml/scanner/Scanner;
      74: iconst_1
      75: anewarray     #5                  // class org/yaml/snakeyaml/tokens/Token$ID
      78: dup
      79: iconst_0
      80: getstatic     #13                 // Field org/yaml/snakeyaml/tokens/Token$ID.DocumentEnd:Lorg/yaml/snakeyaml/tokens/Token$ID;
      83: aastore
      84: invokeinterface #7,  2            // InterfaceMethod org/yaml/snakeyaml/scanner/Scanner.checkToken:([Lorg/yaml/snakeyaml/tokens/Token$ID;)Z
      89: ifeq          108
      92: aload_0
      93: getfield      #2                  // Field this$0:Lorg/yaml/snakeyaml/parser/ParserImpl;
      96: getfield      #4                  // Field org/yaml/snakeyaml/parser/ParserImpl.scanner:Lorg/yaml/snakeyaml/scanner/Scanner;
      99: invokeinterface #10,  1           // InterfaceMethod org/yaml/snakeyaml/scanner/Scanner.getToken:()Lorg/yaml/snakeyaml/tokens/Token;
     104: pop
     105: goto          67
     108: aload_0
     109: getfield      #2                  // Field this$0:Lorg/yaml/snakeyaml/parser/ParserImpl;
     112: getfield      #4                  // Field org/yaml/snakeyaml/parser/ParserImpl.scanner:Lorg/yaml/snakeyaml/scanner/Scanner;
     115: iconst_1
     116: anewarray     #5                  // class org/yaml/snakeyaml/tokens/Token$ID
     119: dup
     120: iconst_0
     121: getstatic     #6                  // Field org/yaml/snakeyaml/tokens/Token$ID.Comment:Lorg/yaml/snakeyaml/tokens/Token$ID;
     124: aastore
     125: invokeinterface #7,  2            // InterfaceMethod org/yaml/snakeyaml/scanner/Scanner.checkToken:([Lorg/yaml/snakeyaml/tokens/Token$ID;)Z
     130: ifeq          175
     133: aload_0
     134: getfield      #2                  // Field this$0:Lorg/yaml/snakeyaml/parser/ParserImpl;
     137: new           #8                  // class org/yaml/snakeyaml/parser/ParserImpl$ParseDocumentStart
     140: dup
     141: aload_0
     142: getfield      #2                  // Field this$0:Lorg/yaml/snakeyaml/parser/ParserImpl;
     145: invokespecial #1                  // Method "<init>":(Lorg/yaml/snakeyaml/parser/ParserImpl;)V
     148: invokestatic  #9                  // Method org/yaml/snakeyaml/parser/ParserImpl.access$102:(Lorg/yaml/snakeyaml/parser/ParserImpl;Lorg/yaml/snakeyaml/parser/Production;)Lorg/yaml/snakeyaml/parser/Production;
     151: pop
     152: aload_0
     153: getfield      #2                  // Field this$0:Lorg/yaml/snakeyaml/parser/ParserImpl;
     156: aload_0
     157: getfield      #2                  // Field this$0:Lorg/yaml/snakeyaml/parser/ParserImpl;
     160: getfield      #4                  // Field org/yaml/snakeyaml/parser/ParserImpl.scanner:Lorg/yaml/snakeyaml/scanner/Scanner;
     163: invokeinterface #10,  1           // InterfaceMethod org/yaml/snakeyaml/scanner/Scanner.getToken:()Lorg/yaml/snakeyaml/tokens/Token;
     168: checkcast     #11                 // class org/yaml/snakeyaml/tokens/CommentToken
     171: invokestatic  #12                 // Method org/yaml/snakeyaml/parser/ParserImpl.access$300:(Lorg/yaml/snakeyaml/parser/ParserImpl;Lorg/yaml/snakeyaml/tokens/CommentToken;)Lorg/yaml/snakeyaml/events/CommentEvent;
     174: areturn
     175: aload_0
     176: getfield      #2                  // Field this$0:Lorg/yaml/snakeyaml/parser/ParserImpl;
     179: getfield      #4                  // Field org/yaml/snakeyaml/parser/ParserImpl.scanner:Lorg/yaml/snakeyaml/scanner/Scanner;
     182: iconst_1
     183: anewarray     #5                  // class org/yaml/snakeyaml/tokens/Token$ID
     186: dup
     187: iconst_0
     188: getstatic     #14                 // Field org/yaml/snakeyaml/tokens/Token$ID.StreamEnd:Lorg/yaml/snakeyaml/tokens/Token$ID;
     191: aastore
     192: invokeinterface #7,  2            // InterfaceMethod org/yaml/snakeyaml/scanner/Scanner.checkToken:([Lorg/yaml/snakeyaml/tokens/Token$ID;)Z
     197: ifne          466
     200: aload_0
     201: getfield      #2                  // Field this$0:Lorg/yaml/snakeyaml/parser/ParserImpl;
     204: getfield      #4                  // Field org/yaml/snakeyaml/parser/ParserImpl.scanner:Lorg/yaml/snakeyaml/scanner/Scanner;
     207: invokeinterface #15,  1           // InterfaceMethod org/yaml/snakeyaml/scanner/Scanner.peekToken:()Lorg/yaml/snakeyaml/tokens/Token;
     212: astore_2
     213: aload_2
     214: invokevirtual #16                 // Method org/yaml/snakeyaml/tokens/Token.getStartMark:()Lorg/yaml/snakeyaml/error/Mark;
     217: astore_3
     218: aload_0
     219: getfield      #2                  // Field this$0:Lorg/yaml/snakeyaml/parser/ParserImpl;
     222: invokestatic  #17                 // Method org/yaml/snakeyaml/parser/ParserImpl.access$1000:(Lorg/yaml/snakeyaml/parser/ParserImpl;)Lorg/yaml/snakeyaml/parser/VersionTagsTuple;
     225: astore        4
     227: aload_0
     228: getfield      #2                  // Field this$0:Lorg/yaml/snakeyaml/parser/ParserImpl;
     231: getfield      #4                  // Field org/yaml/snakeyaml/parser/ParserImpl.scanner:Lorg/yaml/snakeyaml/scanner/Scanner;
     234: iconst_1
     235: anewarray     #5                  // class org/yaml/snakeyaml/tokens/Token$ID
     238: dup
     239: iconst_0
     240: getstatic     #6                  // Field org/yaml/snakeyaml/tokens/Token$ID.Comment:Lorg/yaml/snakeyaml/tokens/Token$ID;
     243: aastore
     244: invokeinterface #7,  2            // InterfaceMethod org/yaml/snakeyaml/scanner/Scanner.checkToken:([Lorg/yaml/snakeyaml/tokens/Token$ID;)Z
     249: ifeq          268
     252: aload_0
     253: getfield      #2                  // Field this$0:Lorg/yaml/snakeyaml/parser/ParserImpl;
     256: getfield      #4                  // Field org/yaml/snakeyaml/parser/ParserImpl.scanner:Lorg/yaml/snakeyaml/scanner/Scanner;
     259: invokeinterface #10,  1           // InterfaceMethod org/yaml/snakeyaml/scanner/Scanner.getToken:()Lorg/yaml/snakeyaml/tokens/Token;
     264: pop
     265: goto          227
     268: aload_0
     269: getfield      #2                  // Field this$0:Lorg/yaml/snakeyaml/parser/ParserImpl;
     272: getfield      #4                  // Field org/yaml/snakeyaml/parser/ParserImpl.scanner:Lorg/yaml/snakeyaml/scanner/Scanner;
     275: iconst_1
     276: anewarray     #5                  // class org/yaml/snakeyaml/tokens/Token$ID
     279: dup
     280: iconst_0
     281: getstatic     #14                 // Field org/yaml/snakeyaml/tokens/Token$ID.StreamEnd:Lorg/yaml/snakeyaml/tokens/Token$ID;
     284: aastore
     285: invokeinterface #7,  2            // InterfaceMethod org/yaml/snakeyaml/scanner/Scanner.checkToken:([Lorg/yaml/snakeyaml/tokens/Token$ID;)Z
     290: ifne          466
     293: aload_0
     294: getfield      #2                  // Field this$0:Lorg/yaml/snakeyaml/parser/ParserImpl;
     297: getfield      #4                  // Field org/yaml/snakeyaml/parser/ParserImpl.scanner:Lorg/yaml/snakeyaml/scanner/Scanner;
     300: iconst_1
     301: anewarray     #5                  // class org/yaml/snakeyaml/tokens/Token$ID
     304: dup
     305: iconst_0
     306: getstatic     #18                 // Field org/yaml/snakeyaml/tokens/Token$ID.DocumentStart:Lorg/yaml/snakeyaml/tokens/Token$ID;
     309: aastore
     310: invokeinterface #7,  2            // InterfaceMethod org/yaml/snakeyaml/scanner/Scanner.checkToken:([Lorg/yaml/snakeyaml/tokens/Token$ID;)Z
     315: ifne          381
     318: new           #19                 // class org/yaml/snakeyaml/parser/ParserException
     321: dup
     322: aconst_null
     323: aconst_null
     324: new           #20                 // class java/lang/StringBuilder
     327: dup
     328: invokespecial #21                 // Method java/lang/StringBuilder."<init>":()V
     331: ldc           #22                 // String expected \'<document start>\', but found \'
     333: invokevirtual #23                 // Method java/lang/StringBuilder.append:(Ljava/lang/String;)Ljava/lang/StringBuilder;
     336: aload_0
     337: getfield      #2                  // Field this$0:Lorg/yaml/snakeyaml/parser/ParserImpl;
     340: getfield      #4                  // Field org/yaml/snakeyaml/parser/ParserImpl.scanner:Lorg/yaml/snakeyaml/scanner/Scanner;
     343: invokeinterface #15,  1           // InterfaceMethod org/yaml/snakeyaml/scanner/Scanner.peekToken:()Lorg/yaml/snakeyaml/tokens/Token;
     348: invokevirtual #24                 // Method org/yaml/snakeyaml/tokens/Token.getTokenId:()Lorg/yaml/snakeyaml/tokens/Token$ID;
     351: invokevirtual #25                 // Method java/lang/StringBuilder.append:(Ljava/lang/Object;)Ljava/lang/StringBuilder;
     354: ldc           #26                 // String \'
     356: invokevirtual #23                 // Method java/lang/StringBuilder.append:(Ljava/lang/String;)Ljava/lang/StringBuilder;
     359: invokevirtual #27                 // Method java/lang/StringBuilder.toString:()Ljava/lang/String;
     362: aload_0
     363: getfield      #2                  // Field this$0:Lorg/yaml/snakeyaml/parser/ParserImpl;
     366: getfield      #4                  // Field org/yaml/snakeyaml/parser/ParserImpl.scanner:Lorg/yaml/snakeyaml/scanner/Scanner;
     369: invokeinterface #15,  1           // InterfaceMethod org/yaml/snakeyaml/scanner/Scanner.peekToken:()Lorg/yaml/snakeyaml/tokens/Token;
     374: invokevirtual #16                 // Method org/yaml/snakeyaml/tokens/Token.getStartMark:()Lorg/yaml/snakeyaml/error/Mark;
     377: invokespecial #28                 // Method org/yaml/snakeyaml/parser/ParserException."<init>":(Ljava/lang/String;Lorg/yaml/snakeyaml/error/Mark;Ljava/lang/String;Lorg/yaml/snakeyaml/error/Mark;)V
     380: athrow
     381: aload_0
     382: getfield      #2                  // Field this$0:Lorg/yaml/snakeyaml/parser/ParserImpl;
     385: getfield      #4                  // Field org/yaml/snakeyaml/parser/ParserImpl.scanner:Lorg/yaml/snakeyaml/scanner/Scanner;
     388: invokeinterface #10,  1           // InterfaceMethod org/yaml/snakeyaml/scanner/Scanner.getToken:()Lorg/yaml/snakeyaml/tokens/Token;
     393: astore_2
     394: aload_2
     395: invokevirtual #29                 // Method org/yaml/snakeyaml/tokens/Token.getEndMark:()Lorg/yaml/snakeyaml/error/Mark;
     398: astore        5
     400: new           #30                 // class org/yaml/snakeyaml/events/DocumentStartEvent
     403: dup
     404: aload_3
     405: aload         5
     407: iconst_1
     408: aload         4
     410: invokevirtual #31                 // Method org/yaml/snakeyaml/parser/VersionTagsTuple.getVersion:()Lorg/yaml/snakeyaml/DumperOptions$Version;
     413: aload         4
     415: invokevirtual #32                 // Method org/yaml/snakeyaml/parser/VersionTagsTuple.getTags:()Ljava/util/Map;
     418: invokespecial #33                 // Method org/yaml/snakeyaml/events/DocumentStartEvent."<init>":(Lorg/yaml/snakeyaml/error/Mark;Lorg/yaml/snakeyaml/error/Mark;ZLorg/yaml/snakeyaml/DumperOptions$Version;Ljava/util/Map;)V
     421: astore_1
     422: aload_0
     423: getfield      #2                  // Field this$0:Lorg/yaml/snakeyaml/parser/ParserImpl;
     426: invokestatic  #34                 // Method org/yaml/snakeyaml/parser/ParserImpl.access$700:(Lorg/yaml/snakeyaml/parser/ParserImpl;)Lorg/yaml/snakeyaml/util/ArrayStack;
     429: new           #35                 // class org/yaml/snakeyaml/parser/ParserImpl$ParseDocumentEnd
     432: dup
     433: aload_0
     434: getfield      #2                  // Field this$0:Lorg/yaml/snakeyaml/parser/ParserImpl;
     437: aconst_null
     438: invokespecial #36                 // Method org/yaml/snakeyaml/parser/ParserImpl$ParseDocumentEnd."<init>":(Lorg/yaml/snakeyaml/parser/ParserImpl;Lorg/yaml/snakeyaml/parser/ParserImpl$1;)V
     441: invokevirtual #37                 // Method org/yaml/snakeyaml/util/ArrayStack.push:(Ljava/lang/Object;)V
     444: aload_0
     445: getfield      #2                  // Field this$0:Lorg/yaml/snakeyaml/parser/ParserImpl;
     448: new           #38                 // class org/yaml/snakeyaml/parser/ParserImpl$ParseDocumentContent
     451: dup
     452: aload_0
     453: getfield      #2                  // Field this$0:Lorg/yaml/snakeyaml/parser/ParserImpl;
     456: aconst_null
     457: invokespecial #39                 // Method org/yaml/snakeyaml/parser/ParserImpl$ParseDocumentContent."<init>":(Lorg/yaml/snakeyaml/parser/ParserImpl;Lorg/yaml/snakeyaml/parser/ParserImpl$1;)V
     460: invokestatic  #9                  // Method org/yaml/snakeyaml/parser/ParserImpl.access$102:(Lorg/yaml/snakeyaml/parser/ParserImpl;Lorg/yaml/snakeyaml/parser/Production;)Lorg/yaml/snakeyaml/parser/Production;
     463: pop
     464: aload_1
     465: areturn
     466: aload_0
     467: getfield      #2                  // Field this$0:Lorg/yaml/snakeyaml/parser/ParserImpl;
     470: getfield      #4                  // Field org/yaml/snakeyaml/parser/ParserImpl.scanner:Lorg/yaml/snakeyaml/scanner/Scanner;
     473: invokeinterface #10,  1           // InterfaceMethod org/yaml/snakeyaml/scanner/Scanner.getToken:()Lorg/yaml/snakeyaml/tokens/Token;
     478: checkcast     #40                 // class org/yaml/snakeyaml/tokens/StreamEndToken
     481: astore_2
     482: new           #41                 // class org/yaml/snakeyaml/events/StreamEndEvent
     485: dup
     486: aload_2
     487: invokevirtual #42                 // Method org/yaml/snakeyaml/tokens/StreamEndToken.getStartMark:()Lorg/yaml/snakeyaml/error/Mark;
     490: aload_2
     491: invokevirtual #43                 // Method org/yaml/snakeyaml/tokens/StreamEndToken.getEndMark:()Lorg/yaml/snakeyaml/error/Mark;
     494: invokespecial #44                 // Method org/yaml/snakeyaml/events/StreamEndEvent."<init>":(Lorg/yaml/snakeyaml/error/Mark;Lorg/yaml/snakeyaml/error/Mark;)V
     497: astore_1
     498: aload_0
     499: getfield      #2                  // Field this$0:Lorg/yaml/snakeyaml/parser/ParserImpl;
     502: invokestatic  #34                 // Method org/yaml/snakeyaml/parser/ParserImpl.access$700:(Lorg/yaml/snakeyaml/parser/ParserImpl;)Lorg/yaml/snakeyaml/util/ArrayStack;
     505: invokevirtual #45                 // Method org/yaml/snakeyaml/util/ArrayStack.isEmpty:()Z
     508: ifne          544
     511: new           #46                 // class org/yaml/snakeyaml/error/YAMLException
     514: dup
     515: new           #20                 // class java/lang/StringBuilder
     518: dup
     519: invokespecial #21                 // Method java/lang/StringBuilder."<init>":()V
     522: ldc           #47                 // String Unexpected end of stream. States left:
     524: invokevirtual #23                 // Method java/lang/StringBuilder.append:(Ljava/lang/String;)Ljava/lang/StringBuilder;
     527: aload_0
     528: getfield      #2                  // Field this$0:Lorg/yaml/snakeyaml/parser/ParserImpl;
     531: invokestatic  #34                 // Method org/yaml/snakeyaml/parser/ParserImpl.access$700:(Lorg/yaml/snakeyaml/parser/ParserImpl;)Lorg/yaml/snakeyaml/util/ArrayStack;
     534: invokevirtual #25                 // Method java/lang/StringBuilder.append:(Ljava/lang/Object;)Ljava/lang/StringBuilder;
     537: invokevirtual #27                 // Method java/lang/StringBuilder.toString:()Ljava/lang/String;
     540: invokespecial #48                 // Method org/yaml/snakeyaml/error/YAMLException."<init>":(Ljava/lang/String;)V
     543: athrow
     544: aload_0
     545: getfield      #2                  // Field this$0:Lorg/yaml/snakeyaml/parser/ParserImpl;
     548: invokestatic  #49                 // Method org/yaml/snakeyaml/parser/ParserImpl.access$1200:(Lorg/yaml/snakeyaml/parser/ParserImpl;)Lorg/yaml/snakeyaml/util/ArrayStack;
     551: invokevirtual #45                 // Method org/yaml/snakeyaml/util/ArrayStack.isEmpty:()Z
     554: ifne          590
     557: new           #46                 // class org/yaml/snakeyaml/error/YAMLException
     560: dup
     561: new           #20                 // class java/lang/StringBuilder
     564: dup
     565: invokespecial #21                 // Method java/lang/StringBuilder."<init>":()V
     568: ldc           #50                 // String Unexpected end of stream. Marks left:
     570: invokevirtual #23                 // Method java/lang/StringBuilder.append:(Ljava/lang/String;)Ljava/lang/StringBuilder;
     573: aload_0
     574: getfield      #2                  // Field this$0:Lorg/yaml/snakeyaml/parser/ParserImpl;
     577: invokestatic  #49                 // Method org/yaml/snakeyaml/parser/ParserImpl.access$1200:(Lorg/yaml/snakeyaml/parser/ParserImpl;)Lorg/yaml/snakeyaml/util/ArrayStack;
     580: invokevirtual #25                 // Method java/lang/StringBuilder.append:(Ljava/lang/Object;)Ljava/lang/StringBuilder;
     583: invokevirtual #27                 // Method java/lang/StringBuilder.toString:()Ljava/lang/String;
     586: invokespecial #48                 // Method org/yaml/snakeyaml/error/YAMLException."<init>":(Ljava/lang/String;)V
     589: athrow
     590: aload_0
     591: getfield      #2                  // Field this$0:Lorg/yaml/snakeyaml/parser/ParserImpl;
     594: aconst_null
     595: invokestatic  #9                  // Method org/yaml/snakeyaml/parser/ParserImpl.access$102:(Lorg/yaml/snakeyaml/parser/ParserImpl;Lorg/yaml/snakeyaml/parser/Production;)Lorg/yaml/snakeyaml/parser/Production;
     598: pop
     599: aload_1
     600: areturn

  org.yaml.snakeyaml.parser.ParserImpl$ParseDocumentStart(org.yaml.snakeyaml.parser.ParserImpl, org.yaml.snakeyaml.parser.ParserImpl$1);
    Code:
       0: aload_0
       1: aload_1
       2: invokespecial #1                  // Method "<init>":(Lorg/yaml/snakeyaml/parser/ParserImpl;)V
       5: return
}
