Compiled from "CookieProcessorBase.java"
public abstract class org.apache.tomcat.util.http.CookieProcessorBase implements org.apache.tomcat.util.http.CookieProcessor {
  private static final java.lang.String COOKIE_DATE_PATTERN;

  protected static final java.lang.ThreadLocal<java.text.DateFormat> COOKIE_DATE_FORMAT;

  protected static final java.lang.String ANCIENT_DATE;

  private org.apache.tomcat.util.http.SameSiteCookies sameSiteCookies;

  public org.apache.tomcat.util.http.CookieProcessorBase();
    Code:
       0: aload_0
       1: invokespecial #1                  // Method java/lang/Object."<init>":()V
       4: aload_0
       5: getstatic     #2                  // Field org/apache/tomcat/util/http/SameSiteCookies.UNSET:Lorg/apache/tomcat/util/http/SameSiteCookies;
       8: putfield      #3                  // Field sameSiteCookies:Lorg/apache/tomcat/util/http/SameSiteCookies;
      11: return

  public org.apache.tomcat.util.http.SameSiteCookies getSameSiteCookies();
    Code:
       0: aload_0
       1: getfield      #3                  // Field sameSiteCookies:Lorg/apache/tomcat/util/http/SameSiteCookies;
       4: areturn

  public void setSameSiteCookies(java.lang.String);
    Code:
       0: aload_0
       1: aload_1
       2: invokestatic  #4                  // Method org/apache/tomcat/util/http/SameSiteCookies.fromString:(Ljava/lang/String;)Lorg/apache/tomcat/util/http/SameSiteCookies;
       5: putfield      #3                  // Field sameSiteCookies:Lorg/apache/tomcat/util/http/SameSiteCookies;
       8: return

  static {};
    Code:
       0: new           #5                  // class org/apache/tomcat/util/http/CookieProcessorBase$1
       3: dup
       4: invokespecial #6                  // Method org/apache/tomcat/util/http/CookieProcessorBase$1."<init>":()V
       7: putstatic     #7                  // Field COOKIE_DATE_FORMAT:Ljava/lang/ThreadLocal;
      10: getstatic     #7                  // Field COOKIE_DATE_FORMAT:Ljava/lang/ThreadLocal;
      13: invokevirtual #8                  // Method java/lang/ThreadLocal.get:()Ljava/lang/Object;
      16: checkcast     #9                  // class java/text/DateFormat
      19: new           #10                 // class java/util/Date
      22: dup
      23: ldc2_w        #11                 // long 10000l
      26: invokespecial #13                 // Method java/util/Date."<init>":(J)V
      29: invokevirtual #14                 // Method java/text/DateFormat.format:(Ljava/util/Date;)Ljava/lang/String;
      32: putstatic     #15                 // Field ANCIENT_DATE:Ljava/lang/String;
      35: return
}
