Compiled from "RequestUtil.java"
public class org.apache.tomcat.util.http.RequestUtil {
  private org.apache.tomcat.util.http.RequestUtil();
    Code:
       0: aload_0
       1: invokespecial #1                  // Method java/lang/Object."<init>":()V
       4: return

  public static java.lang.String normalize(java.lang.String);
    Code:
       0: aload_0
       1: iconst_1
       2: invokestatic  #2                  // Method normalize:(Ljava/lang/String;Z)Ljava/lang/String;
       5: areturn

  public static java.lang.String normalize(java.lang.String, boolean);
    Code:
       0: aload_0
       1: ifnonnull     6
       4: aconst_null
       5: areturn
       6: aload_0
       7: astore_2
       8: iload_1
       9: ifeq          30
      12: aload_2
      13: bipush        92
      15: invokevirtual #3                  // Method java/lang/String.indexOf:(I)I
      18: iflt          30
      21: aload_2
      22: bipush        92
      24: bipush        47
      26: invokevirtual #4                  // Method java/lang/String.replace:(CC)Ljava/lang/String;
      29: astore_2
      30: aload_2
      31: ldc           #5                  // String /
      33: invokevirtual #6                  // Method java/lang/String.startsWith:(Ljava/lang/String;)Z
      36: ifne          59
      39: new           #7                  // class java/lang/StringBuilder
      42: dup
      43: invokespecial #8                  // Method java/lang/StringBuilder."<init>":()V
      46: ldc           #5                  // String /
      48: invokevirtual #9                  // Method java/lang/StringBuilder.append:(Ljava/lang/String;)Ljava/lang/StringBuilder;
      51: aload_2
      52: invokevirtual #9                  // Method java/lang/StringBuilder.append:(Ljava/lang/String;)Ljava/lang/StringBuilder;
      55: invokevirtual #10                 // Method java/lang/StringBuilder.toString:()Ljava/lang/String;
      58: astore_2
      59: iconst_0
      60: istore_3
      61: aload_2
      62: ldc           #11                 // String /.
      64: invokevirtual #12                 // Method java/lang/String.endsWith:(Ljava/lang/String;)Z
      67: ifne          79
      70: aload_2
      71: ldc           #13                 // String /..
      73: invokevirtual #12                 // Method java/lang/String.endsWith:(Ljava/lang/String;)Z
      76: ifeq          101
      79: new           #7                  // class java/lang/StringBuilder
      82: dup
      83: invokespecial #8                  // Method java/lang/StringBuilder."<init>":()V
      86: aload_2
      87: invokevirtual #9                  // Method java/lang/StringBuilder.append:(Ljava/lang/String;)Ljava/lang/StringBuilder;
      90: ldc           #5                  // String /
      92: invokevirtual #9                  // Method java/lang/StringBuilder.append:(Ljava/lang/String;)Ljava/lang/StringBuilder;
      95: invokevirtual #10                 // Method java/lang/StringBuilder.toString:()Ljava/lang/String;
      98: astore_2
      99: iconst_1
     100: istore_3
     101: aload_2
     102: ldc           #14                 // String //
     104: invokevirtual #15                 // Method java/lang/String.indexOf:(Ljava/lang/String;)I
     107: istore        4
     109: iload         4
     111: ifge          117
     114: goto          152
     117: new           #7                  // class java/lang/StringBuilder
     120: dup
     121: invokespecial #8                  // Method java/lang/StringBuilder."<init>":()V
     124: aload_2
     125: iconst_0
     126: iload         4
     128: invokevirtual #16                 // Method java/lang/String.substring:(II)Ljava/lang/String;
     131: invokevirtual #9                  // Method java/lang/StringBuilder.append:(Ljava/lang/String;)Ljava/lang/StringBuilder;
     134: aload_2
     135: iload         4
     137: iconst_1
     138: iadd
     139: invokevirtual #17                 // Method java/lang/String.substring:(I)Ljava/lang/String;
     142: invokevirtual #9                  // Method java/lang/StringBuilder.append:(Ljava/lang/String;)Ljava/lang/StringBuilder;
     145: invokevirtual #10                 // Method java/lang/StringBuilder.toString:()Ljava/lang/String;
     148: astore_2
     149: goto          101
     152: aload_2
     153: ldc           #18                 // String /./
     155: invokevirtual #15                 // Method java/lang/String.indexOf:(Ljava/lang/String;)I
     158: istore        4
     160: iload         4
     162: ifge          168
     165: goto          203
     168: new           #7                  // class java/lang/StringBuilder
     171: dup
     172: invokespecial #8                  // Method java/lang/StringBuilder."<init>":()V
     175: aload_2
     176: iconst_0
     177: iload         4
     179: invokevirtual #16                 // Method java/lang/String.substring:(II)Ljava/lang/String;
     182: invokevirtual #9                  // Method java/lang/StringBuilder.append:(Ljava/lang/String;)Ljava/lang/StringBuilder;
     185: aload_2
     186: iload         4
     188: iconst_2
     189: iadd
     190: invokevirtual #17                 // Method java/lang/String.substring:(I)Ljava/lang/String;
     193: invokevirtual #9                  // Method java/lang/StringBuilder.append:(Ljava/lang/String;)Ljava/lang/StringBuilder;
     196: invokevirtual #10                 // Method java/lang/StringBuilder.toString:()Ljava/lang/String;
     199: astore_2
     200: goto          152
     203: aload_2
     204: ldc           #19                 // String /../
     206: invokevirtual #15                 // Method java/lang/String.indexOf:(Ljava/lang/String;)I
     209: istore        4
     211: iload         4
     213: ifge          219
     216: goto          273
     219: iload         4
     221: ifne          226
     224: aconst_null
     225: areturn
     226: aload_2
     227: bipush        47
     229: iload         4
     231: iconst_1
     232: isub
     233: invokevirtual #20                 // Method java/lang/String.lastIndexOf:(II)I
     236: istore        5
     238: new           #7                  // class java/lang/StringBuilder
     241: dup
     242: invokespecial #8                  // Method java/lang/StringBuilder."<init>":()V
     245: aload_2
     246: iconst_0
     247: iload         5
     249: invokevirtual #16                 // Method java/lang/String.substring:(II)Ljava/lang/String;
     252: invokevirtual #9                  // Method java/lang/StringBuilder.append:(Ljava/lang/String;)Ljava/lang/StringBuilder;
     255: aload_2
     256: iload         4
     258: iconst_3
     259: iadd
     260: invokevirtual #17                 // Method java/lang/String.substring:(I)Ljava/lang/String;
     263: invokevirtual #9                  // Method java/lang/StringBuilder.append:(Ljava/lang/String;)Ljava/lang/StringBuilder;
     266: invokevirtual #10                 // Method java/lang/StringBuilder.toString:()Ljava/lang/String;
     269: astore_2
     270: goto          203
     273: aload_2
     274: invokevirtual #21                 // Method java/lang/String.length:()I
     277: iconst_1
     278: if_icmple     297
     281: iload_3
     282: ifeq          297
     285: aload_2
     286: iconst_0
     287: aload_2
     288: invokevirtual #21                 // Method java/lang/String.length:()I
     291: iconst_1
     292: isub
     293: invokevirtual #16                 // Method java/lang/String.substring:(II)Ljava/lang/String;
     296: astore_2
     297: aload_2
     298: areturn

  public static boolean isSameOrigin(javax.servlet.http.HttpServletRequest, java.lang.String);
    Code:
       0: new           #7                  // class java/lang/StringBuilder
       3: dup
       4: invokespecial #8                  // Method java/lang/StringBuilder."<init>":()V
       7: astore_2
       8: aload_0
       9: invokeinterface #22,  1           // InterfaceMethod javax/servlet/http/HttpServletRequest.getScheme:()Ljava/lang/String;
      14: astore_3
      15: aload_3
      16: ifnonnull     21
      19: iconst_0
      20: ireturn
      21: aload_3
      22: getstatic     #23                 // Field java/util/Locale.ENGLISH:Ljava/util/Locale;
      25: invokevirtual #24                 // Method java/lang/String.toLowerCase:(Ljava/util/Locale;)Ljava/lang/String;
      28: astore_3
      29: aload_2
      30: aload_3
      31: invokevirtual #9                  // Method java/lang/StringBuilder.append:(Ljava/lang/String;)Ljava/lang/StringBuilder;
      34: pop
      35: aload_2
      36: ldc           #25                 // String ://
      38: invokevirtual #9                  // Method java/lang/StringBuilder.append:(Ljava/lang/String;)Ljava/lang/StringBuilder;
      41: pop
      42: aload_0
      43: invokeinterface #26,  1           // InterfaceMethod javax/servlet/http/HttpServletRequest.getServerName:()Ljava/lang/String;
      48: astore        4
      50: aload         4
      52: ifnonnull     57
      55: iconst_0
      56: ireturn
      57: aload_2
      58: aload         4
      60: invokevirtual #9                  // Method java/lang/StringBuilder.append:(Ljava/lang/String;)Ljava/lang/StringBuilder;
      63: pop
      64: aload_0
      65: invokeinterface #27,  1           // InterfaceMethod javax/servlet/http/HttpServletRequest.getServerPort:()I
      70: istore        5
      72: aload_2
      73: invokevirtual #28                 // Method java/lang/StringBuilder.length:()I
      76: aload_1
      77: invokevirtual #21                 // Method java/lang/String.length:()I
      80: if_icmpne     151
      83: ldc           #29                 // String http
      85: aload_3
      86: invokevirtual #30                 // Method java/lang/String.equals:(Ljava/lang/Object;)Z
      89: ifne          101
      92: ldc           #31                 // String ws
      94: aload_3
      95: invokevirtual #30                 // Method java/lang/String.equals:(Ljava/lang/Object;)Z
      98: ifeq          108
     101: iload         5
     103: bipush        80
     105: if_icmpne     134
     108: ldc           #32                 // String https
     110: aload_3
     111: invokevirtual #30                 // Method java/lang/String.equals:(Ljava/lang/Object;)Z
     114: ifne          126
     117: ldc           #33                 // String wss
     119: aload_3
     120: invokevirtual #30                 // Method java/lang/String.equals:(Ljava/lang/Object;)Z
     123: ifeq          165
     126: iload         5
     128: sipush        443
     131: if_icmpeq     165
     134: aload_2
     135: bipush        58
     137: invokevirtual #34                 // Method java/lang/StringBuilder.append:(C)Ljava/lang/StringBuilder;
     140: pop
     141: aload_2
     142: iload         5
     144: invokevirtual #35                 // Method java/lang/StringBuilder.append:(I)Ljava/lang/StringBuilder;
     147: pop
     148: goto          165
     151: aload_2
     152: bipush        58
     154: invokevirtual #34                 // Method java/lang/StringBuilder.append:(C)Ljava/lang/StringBuilder;
     157: pop
     158: aload_2
     159: iload         5
     161: invokevirtual #35                 // Method java/lang/StringBuilder.append:(I)Ljava/lang/StringBuilder;
     164: pop
     165: aload_1
     166: aload_2
     167: invokevirtual #10                 // Method java/lang/StringBuilder.toString:()Ljava/lang/String;
     170: invokevirtual #30                 // Method java/lang/String.equals:(Ljava/lang/Object;)Z
     173: ireturn

  public static boolean isValidOrigin(java.lang.String);
    Code:
       0: aload_0
       1: ldc           #36                 // String %
       3: invokevirtual #37                 // Method java/lang/String.contains:(Ljava/lang/CharSequence;)Z
       6: ifeq          11
       9: iconst_0
      10: ireturn
      11: ldc           #38                 // String null
      13: aload_0
      14: invokevirtual #30                 // Method java/lang/String.equals:(Ljava/lang/Object;)Z
      17: ifeq          22
      20: iconst_1
      21: ireturn
      22: aload_0
      23: ldc           #39                 // String file://
      25: invokevirtual #6                  // Method java/lang/String.startsWith:(Ljava/lang/String;)Z
      28: ifeq          33
      31: iconst_1
      32: ireturn
      33: new           #40                 // class java/net/URI
      36: dup
      37: aload_0
      38: invokespecial #41                 // Method java/net/URI."<init>":(Ljava/lang/String;)V
      41: astore_1
      42: goto          48
      45: astore_2
      46: iconst_0
      47: ireturn
      48: aload_1
      49: invokevirtual #43                 // Method java/net/URI.getScheme:()Ljava/lang/String;
      52: ifnull        59
      55: iconst_1
      56: goto          60
      59: iconst_0
      60: ireturn
    Exception table:
       from    to  target type
          33    42    45   Class java/net/URISyntaxException
}
