Compiled from "PagesAnnotatedField.java"
public class net.serenitybdd.core.pages.PagesAnnotatedField {
  private java.lang.reflect.Field field;

  private net.thucydides.core.annotations.ManagedPages annotation;

  public static java.util.Optional<net.serenitybdd.core.pages.PagesAnnotatedField> findFirstAnnotatedField(java.lang.Class<?>);
    Code:
       0: aload_0
       1: invokestatic  #1                  // Method findOptionalAnnotatedField:(Ljava/lang/Class;)Ljava/util/Optional;
       4: areturn

  public static java.util.Optional<net.serenitybdd.core.pages.PagesAnnotatedField> findOptionalAnnotatedField(java.lang.Class<?>);
    Code:
       0: aload_0
       1: invokestatic  #2                  // Method net/thucydides/core/annotations/Fields.of:(Ljava/lang/Class;)Lnet/thucydides/core/annotations/Fields;
       4: invokevirtual #3                  // Method net/thucydides/core/annotations/Fields.allFields:()Ljava/util/Set;
       7: invokeinterface #4,  1            // InterfaceMethod java/util/Set.iterator:()Ljava/util/Iterator;
      12: astore_1
      13: aload_1
      14: invokeinterface #5,  1            // InterfaceMethod java/util/Iterator.hasNext:()Z
      19: ifeq          57
      22: aload_1
      23: invokeinterface #6,  1            // InterfaceMethod java/util/Iterator.next:()Ljava/lang/Object;
      28: checkcast     #7                  // class java/lang/reflect/Field
      31: astore_2
      32: aload_2
      33: invokestatic  #8                  // Method annotationFrom:(Ljava/lang/reflect/Field;)Lnet/thucydides/core/annotations/ManagedPages;
      36: astore_3
      37: aload_3
      38: ifnull        54
      41: new           #9                  // class net/serenitybdd/core/pages/PagesAnnotatedField
      44: dup
      45: aload_2
      46: aload_3
      47: invokespecial #10                 // Method "<init>":(Ljava/lang/reflect/Field;Lnet/thucydides/core/annotations/ManagedPages;)V
      50: invokestatic  #11                 // Method java/util/Optional.of:(Ljava/lang/Object;)Ljava/util/Optional;
      53: areturn
      54: goto          13
      57: invokestatic  #12                 // Method java/util/Optional.empty:()Ljava/util/Optional;
      60: areturn

  private static net.thucydides.core.annotations.ManagedPages annotationFrom(java.lang.reflect.Field);
    Code:
       0: aconst_null
       1: astore_1
       2: aload_0
       3: invokestatic  #13                 // Method fieldIsAnnotatedCorrectly:(Ljava/lang/reflect/Field;)Z
       6: ifeq          36
       9: aload_0
      10: invokestatic  #14                 // Method fieldIsRightType:(Ljava/lang/reflect/Field;)Z
      13: ifne          26
      16: new           #15                 // class net/thucydides/core/steps/InvalidManagedPagesFieldException
      19: dup
      20: ldc           #16                 // String @ManagedPages field must be of type Pages
      22: invokespecial #17                 // Method net/thucydides/core/steps/InvalidManagedPagesFieldException."<init>":(Ljava/lang/String;)V
      25: athrow
      26: aload_0
      27: ldc           #18                 // class net/thucydides/core/annotations/ManagedPages
      29: invokevirtual #19                 // Method java/lang/reflect/Field.getAnnotation:(Ljava/lang/Class;)Ljava/lang/annotation/Annotation;
      32: checkcast     #18                 // class net/thucydides/core/annotations/ManagedPages
      35: astore_1
      36: aload_1
      37: areturn

  static boolean fieldIsRightType(java.lang.reflect.Field);
    Code:
       0: ldc           #20                 // class net/thucydides/core/pages/Pages
       2: aload_0
       3: invokevirtual #21                 // Method java/lang/reflect/Field.getType:()Ljava/lang/Class;
       6: invokevirtual #22                 // Method java/lang/Class.isAssignableFrom:(Ljava/lang/Class;)Z
       9: ireturn

  private static boolean fieldIsAnnotatedCorrectly(java.lang.reflect.Field);
    Code:
       0: iconst_0
       1: istore_1
       2: aload_0
       3: invokevirtual #23                 // Method java/lang/reflect/Field.getAnnotations:()[Ljava/lang/annotation/Annotation;
       6: astore_2
       7: aload_2
       8: arraylength
       9: istore_3
      10: iconst_0
      11: istore        4
      13: iload         4
      15: iload_3
      16: if_icmpge     44
      19: aload_2
      20: iload         4
      22: aaload
      23: astore        5
      25: aload         5
      27: instanceof    #18                 // class net/thucydides/core/annotations/ManagedPages
      30: ifeq          38
      33: iconst_1
      34: istore_1
      35: goto          44
      38: iinc          4, 1
      41: goto          13
      44: iload_1
      45: ireturn

  protected net.serenitybdd.core.pages.PagesAnnotatedField(java.lang.reflect.Field, net.thucydides.core.annotations.ManagedPages);
    Code:
       0: aload_0
       1: invokespecial #24                 // Method java/lang/Object."<init>":()V
       4: aload_0
       5: aload_1
       6: putfield      #25                 // Field field:Ljava/lang/reflect/Field;
       9: aload_0
      10: aload_2
      11: putfield      #26                 // Field annotation:Lnet/thucydides/core/annotations/ManagedPages;
      14: return

  public java.lang.Class<?> getFieldType();
    Code:
       0: aload_0
       1: getfield      #25                 // Field field:Ljava/lang/reflect/Field;
       4: invokevirtual #21                 // Method java/lang/reflect/Field.getType:()Ljava/lang/Class;
       7: areturn

  public void setValue(java.lang.Object, net.thucydides.core.pages.Pages);
    Code:
       0: aload_0
       1: aload_1
       2: invokevirtual #27                 // Method set:(Ljava/lang/Object;)Lnet/thucydides/core/reflection/FieldSetter;
       5: aload_2
       6: invokevirtual #28                 // Method net/thucydides/core/reflection/FieldSetter.to:(Ljava/lang/Object;)V
       9: goto          44
      12: astore_3
      13: new           #15                 // class net/thucydides/core/steps/InvalidManagedPagesFieldException
      16: dup
      17: new           #30                 // class java/lang/StringBuilder
      20: dup
      21: invokespecial #31                 // Method java/lang/StringBuilder."<init>":()V
      24: ldc           #32                 // String Could not access or set managed pages field:
      26: invokevirtual #33                 // Method java/lang/StringBuilder.append:(Ljava/lang/String;)Ljava/lang/StringBuilder;
      29: aload_0
      30: getfield      #25                 // Field field:Ljava/lang/reflect/Field;
      33: invokevirtual #34                 // Method java/lang/StringBuilder.append:(Ljava/lang/Object;)Ljava/lang/StringBuilder;
      36: invokevirtual #35                 // Method java/lang/StringBuilder.toString:()Ljava/lang/String;
      39: aload_3
      40: invokespecial #36                 // Method net/thucydides/core/steps/InvalidManagedPagesFieldException."<init>":(Ljava/lang/String;Ljava/lang/IllegalAccessException;)V
      43: athrow
      44: return
    Exception table:
       from    to  target type
           0     9    12   Class java/lang/IllegalAccessException

  protected net.thucydides.core.reflection.FieldSetter set(java.lang.Object);
    Code:
       0: new           #37                 // class net/thucydides/core/reflection/FieldSetter
       3: dup
       4: aload_0
       5: getfield      #25                 // Field field:Ljava/lang/reflect/Field;
       8: aload_1
       9: invokespecial #38                 // Method net/thucydides/core/reflection/FieldSetter."<init>":(Ljava/lang/reflect/Field;Ljava/lang/Object;)V
      12: areturn

  public java.lang.String getDefaultBaseUrl();
    Code:
       0: aload_0
       1: getfield      #26                 // Field annotation:Lnet/thucydides/core/annotations/ManagedPages;
       4: invokeinterface #39,  1           // InterfaceMethod net/thucydides/core/annotations/ManagedPages.defaultUrl:()Ljava/lang/String;
       9: areturn
}
