Compiled from "WebElementExpectations.java"
final class net.serenitybdd.core.pages.WebElementExpectations$4 implements org.openqa.selenium.support.ui.ExpectedCondition<java.lang.Boolean> {
  private net.serenitybdd.core.pages.WebElementFacadeImpl element;

  net.serenitybdd.core.pages.WebElementExpectations$4();
    Code:
       0: aload_0
       1: invokespecial #1                  // Method java/lang/Object."<init>":()V
       4: return

  public org.openqa.selenium.support.ui.ExpectedCondition<java.lang.Boolean> forElement(net.serenitybdd.core.pages.WebElementFacadeImpl);
    Code:
       0: aload_0
       1: aload_1
       2: putfield      #2                  // Field element:Lnet/serenitybdd/core/pages/WebElementFacadeImpl;
       5: aload_0
       6: areturn

  public java.lang.Boolean apply(org.openqa.selenium.WebDriver);
    Code:
       0: aload_0
       1: getfield      #2                  // Field element:Lnet/serenitybdd/core/pages/WebElementFacadeImpl;
       4: invokevirtual #3                  // Method net/serenitybdd/core/pages/WebElementFacadeImpl.getElement:()Lorg/openqa/selenium/WebElement;
       7: astore_2
       8: aload_2
       9: ifnull        25
      12: aload_2
      13: invokeinterface #4,  1            // InterfaceMethod org/openqa/selenium/WebElement.isEnabled:()Z
      18: ifne          25
      21: iconst_1
      22: goto          26
      25: iconst_0
      26: invokestatic  #5                  // Method java/lang/Boolean.valueOf:(Z)Ljava/lang/Boolean;
      29: areturn

  public java.lang.String toString();
    Code:
       0: new           #6                  // class java/lang/StringBuilder
       3: dup
       4: invokespecial #7                  // Method java/lang/StringBuilder."<init>":()V
       7: aload_0
       8: getfield      #2                  // Field element:Lnet/serenitybdd/core/pages/WebElementFacadeImpl;
      11: invokevirtual #8                  // Method net/serenitybdd/core/pages/WebElementFacadeImpl.toString:()Ljava/lang/String;
      14: invokevirtual #9                  // Method java/lang/StringBuilder.append:(Ljava/lang/String;)Ljava/lang/StringBuilder;
      17: ldc           #10                 // String  to not be enabled
      19: invokevirtual #9                  // Method java/lang/StringBuilder.append:(Ljava/lang/String;)Ljava/lang/StringBuilder;
      22: invokevirtual #11                 // Method java/lang/StringBuilder.toString:()Ljava/lang/String;
      25: areturn

  public java.lang.Object apply(java.lang.Object);
    Code:
       0: aload_0
       1: aload_1
       2: checkcast     #12                 // class org/openqa/selenium/WebDriver
       5: invokevirtual #13                 // Method apply:(Lorg/openqa/selenium/WebDriver;)Ljava/lang/Boolean;
       8: areturn
}
