Compiled from "Types.java"
final class com.google.common.reflect.Types$ClassOwnership$2 extends com.google.common.reflect.Types$ClassOwnership {
  com.google.common.reflect.Types$ClassOwnership$2(java.lang.String, int);
    Code:
       0: aload_0
       1: aload_1
       2: iload_2
       3: aconst_null
       4: invokespecial #1                  // Method com/google/common/reflect/Types$ClassOwnership."<init>":(Ljava/lang/String;ILcom/google/common/reflect/Types$1;)V
       7: return

  java.lang.Class<?> getOwnerType(java.lang.Class<?>);
    Code:
       0: aload_1
       1: invokevirtual #2                  // Method java/lang/Class.isLocalClass:()Z
       4: ifeq          9
       7: aconst_null
       8: areturn
       9: aload_1
      10: invokevirtual #3                  // Method java/lang/Class.getEnclosingClass:()Ljava/lang/Class;
      13: areturn
}
