Compiled from "NormalizeNewlines.java"
public class freemarker.template.utility.NormalizeNewlines implements freemarker.template.TemplateTransformModel {
  public freemarker.template.utility.NormalizeNewlines();
    Code:
       0: aload_0
       1: invokespecial #1                  // Method java/lang/Object."<init>":()V
       4: return

  public java.io.Writer getWriter(java.io.Writer, java.util.Map);
    Code:
       0: new           #2                  // class java/lang/StringBuilder
       3: dup
       4: invokespecial #3                  // Method java/lang/StringBuilder."<init>":()V
       7: astore_3
       8: new           #4                  // class freemarker/template/utility/NormalizeNewlines$1
      11: dup
      12: aload_0
      13: aload_3
      14: aload_1
      15: invokespecial #5                  // Method freemarker/template/utility/NormalizeNewlines$1."<init>":(Lfreemarker/template/utility/NormalizeNewlines;Ljava/lang/StringBuilder;Ljava/io/Writer;)V
      18: areturn

  public void transform(java.io.Reader, java.io.Writer) throws java.io.IOException;
    Code:
       0: aload_1
       1: instanceof    #6                  // class java/io/BufferedReader
       4: ifeq          14
       7: aload_1
       8: checkcast     #6                  // class java/io/BufferedReader
      11: goto          22
      14: new           #6                  // class java/io/BufferedReader
      17: dup
      18: aload_1
      19: invokespecial #7                  // Method java/io/BufferedReader."<init>":(Ljava/io/Reader;)V
      22: astore_3
      23: aload_2
      24: instanceof    #8                  // class java/io/PrintWriter
      27: ifeq          37
      30: aload_2
      31: checkcast     #8                  // class java/io/PrintWriter
      34: goto          45
      37: new           #8                  // class java/io/PrintWriter
      40: dup
      41: aload_2
      42: invokespecial #9                  // Method java/io/PrintWriter."<init>":(Ljava/io/Writer;)V
      45: astore        4
      47: aload_3
      48: invokevirtual #10                 // Method java/io/BufferedReader.readLine:()Ljava/lang/String;
      51: astore        5
      53: aload         5
      55: ifnull        73
      58: aload         5
      60: invokevirtual #11                 // Method java/lang/String.length:()I
      63: ifle          73
      66: aload         4
      68: aload         5
      70: invokevirtual #12                 // Method java/io/PrintWriter.println:(Ljava/lang/String;)V
      73: aload_3
      74: invokevirtual #10                 // Method java/io/BufferedReader.readLine:()Ljava/lang/String;
      77: dup
      78: astore        5
      80: ifnull        93
      83: aload         4
      85: aload         5
      87: invokevirtual #12                 // Method java/io/PrintWriter.println:(Ljava/lang/String;)V
      90: goto          73
      93: return
}
