Compiled from "UnrecognizedTimeZoneException.java"
public class freemarker.template.utility.UnrecognizedTimeZoneException extends java.lang.Exception {
  private final java.lang.String timeZoneName;

  public freemarker.template.utility.UnrecognizedTimeZoneException(java.lang.String);
    Code:
       0: aload_0
       1: new           #1                  // class java/lang/StringBuilder
       4: dup
       5: invokespecial #2                  // Method java/lang/StringBuilder."<init>":()V
       8: ldc           #3                  // String Unrecognized time zone:
      10: invokevirtual #4                  // Method java/lang/StringBuilder.append:(Ljava/lang/String;)Ljava/lang/StringBuilder;
      13: aload_1
      14: invokestatic  #5                  // Method freemarker/template/utility/StringUtil.jQuote:(Ljava/lang/String;)Ljava/lang/String;
      17: invokevirtual #4                  // Method java/lang/StringBuilder.append:(Ljava/lang/String;)Ljava/lang/StringBuilder;
      20: invokevirtual #6                  // Method java/lang/StringBuilder.toString:()Ljava/lang/String;
      23: invokespecial #7                  // Method java/lang/Exception."<init>":(Ljava/lang/String;)V
      26: aload_0
      27: aload_1
      28: putfield      #8                  // Field timeZoneName:Ljava/lang/String;
      31: return

  public java.lang.String getTimeZoneName();
    Code:
       0: aload_0
       1: getfield      #8                  // Field timeZoneName:Ljava/lang/String;
       4: areturn
}
