Compiled from "RulesProfile.java"
final class org.sonar.api.profiles.RulesProfile$CloneFunction extends java.lang.Enum<org.sonar.api.profiles.RulesProfile$CloneFunction> implements org.sonar.api.internal.google.common.base.Function<org.sonar.api.rules.ActiveRule, org.sonar.api.rules.ActiveRule> {
  public static final org.sonar.api.profiles.RulesProfile$CloneFunction INSTANCE;

  private static final org.sonar.api.profiles.RulesProfile$CloneFunction[] $VALUES;

  public static org.sonar.api.profiles.RulesProfile$CloneFunction[] values();
    Code:
       0: getstatic     #19                 // Field $VALUES:[Lorg/sonar/api/profiles/RulesProfile$CloneFunction;
       3: invokevirtual #24                 // Method "[Lorg/sonar/api/profiles/RulesProfile$CloneFunction;".clone:()Ljava/lang/Object;
       6: checkcast     #20                 // class "[Lorg/sonar/api/profiles/RulesProfile$CloneFunction;"
       9: areturn

  public static org.sonar.api.profiles.RulesProfile$CloneFunction valueOf(java.lang.String);
    Code:
       0: ldc           #2                  // class org/sonar/api/profiles/RulesProfile$CloneFunction
       2: aload_0
       3: invokestatic  #29                 // Method java/lang/Enum.valueOf:(Ljava/lang/Class;Ljava/lang/String;)Ljava/lang/Enum;
       6: checkcast     #2                  // class org/sonar/api/profiles/RulesProfile$CloneFunction
       9: areturn

  private org.sonar.api.profiles.RulesProfile$CloneFunction();
    Code:
       0: aload_0
       1: aload_1
       2: iload_2
       3: invokespecial #35                 // Method java/lang/Enum."<init>":(Ljava/lang/String;I)V
       6: return

  public org.sonar.api.rules.ActiveRule apply(org.sonar.api.rules.ActiveRule);
    Code:
       0: aload_1
       1: invokevirtual #41                 // Method org/sonar/api/rules/ActiveRule.clone:()Ljava/lang/Object;
       4: checkcast     #40                 // class org/sonar/api/rules/ActiveRule
       7: areturn

  public java.lang.Object apply(java.lang.Object);
    Code:
       0: aload_0
       1: aload_1
       2: checkcast     #40                 // class org/sonar/api/rules/ActiveRule
       5: invokevirtual #46                 // Method apply:(Lorg/sonar/api/rules/ActiveRule;)Lorg/sonar/api/rules/ActiveRule;
       8: areturn

  static {};
    Code:
       0: new           #2                  // class org/sonar/api/profiles/RulesProfile$CloneFunction
       3: dup
       4: ldc           #49                 // String INSTANCE
       6: iconst_0
       7: invokespecial #50                 // Method "<init>":(Ljava/lang/String;I)V
      10: putstatic     #52                 // Field INSTANCE:Lorg/sonar/api/profiles/RulesProfile$CloneFunction;
      13: iconst_1
      14: anewarray     #2                  // class org/sonar/api/profiles/RulesProfile$CloneFunction
      17: dup
      18: iconst_0
      19: getstatic     #52                 // Field INSTANCE:Lorg/sonar/api/profiles/RulesProfile$CloneFunction;
      22: aastore
      23: putstatic     #19                 // Field $VALUES:[Lorg/sonar/api/profiles/RulesProfile$CloneFunction;
      26: return
}
