Compiled from "YAMLParser.java"
public final class com.fasterxml.jackson.dataformat.yaml.YAMLParser$Feature extends java.lang.Enum<com.fasterxml.jackson.dataformat.yaml.YAMLParser$Feature> implements com.fasterxml.jackson.core.FormatFeature {
  public static final com.fasterxml.jackson.dataformat.yaml.YAMLParser$Feature EMPTY_STRING_AS_NULL;

  final boolean _defaultState;

  final int _mask;

  private static final com.fasterxml.jackson.dataformat.yaml.YAMLParser$Feature[] $VALUES;

  public static com.fasterxml.jackson.dataformat.yaml.YAMLParser$Feature[] values();
    Code:
       0: getstatic     #1                  // Field $VALUES:[Lcom/fasterxml/jackson/dataformat/yaml/YAMLParser$Feature;
       3: invokevirtual #2                  // Method "[Lcom/fasterxml/jackson/dataformat/yaml/YAMLParser$Feature;".clone:()Ljava/lang/Object;
       6: checkcast     #3                  // class "[Lcom/fasterxml/jackson/dataformat/yaml/YAMLParser$Feature;"
       9: areturn

  public static com.fasterxml.jackson.dataformat.yaml.YAMLParser$Feature valueOf(java.lang.String);
    Code:
       0: ldc           #4                  // class com/fasterxml/jackson/dataformat/yaml/YAMLParser$Feature
       2: aload_0
       3: invokestatic  #5                  // Method java/lang/Enum.valueOf:(Ljava/lang/Class;Ljava/lang/String;)Ljava/lang/Enum;
       6: checkcast     #4                  // class com/fasterxml/jackson/dataformat/yaml/YAMLParser$Feature
       9: areturn

  public static int collectDefaults();
    Code:
       0: iconst_0
       1: istore_0
       2: invokestatic  #6                  // Method values:()[Lcom/fasterxml/jackson/dataformat/yaml/YAMLParser$Feature;
       5: astore_1
       6: aload_1
       7: arraylength
       8: istore_2
       9: iconst_0
      10: istore_3
      11: iload_3
      12: iload_2
      13: if_icmpge     43
      16: aload_1
      17: iload_3
      18: aaload
      19: astore        4
      21: aload         4
      23: invokevirtual #7                  // Method enabledByDefault:()Z
      26: ifeq          37
      29: iload_0
      30: aload         4
      32: invokevirtual #8                  // Method getMask:()I
      35: ior
      36: istore_0
      37: iinc          3, 1
      40: goto          11
      43: iload_0
      44: ireturn

  private com.fasterxml.jackson.dataformat.yaml.YAMLParser$Feature(boolean);
    Code:
       0: aload_0
       1: aload_1
       2: iload_2
       3: invokespecial #9                  // Method java/lang/Enum."<init>":(Ljava/lang/String;I)V
       6: aload_0
       7: iload_3
       8: putfield      #10                 // Field _defaultState:Z
      11: aload_0
      12: iconst_1
      13: aload_0
      14: invokevirtual #11                 // Method ordinal:()I
      17: ishl
      18: putfield      #12                 // Field _mask:I
      21: return

  public boolean enabledByDefault();
    Code:
       0: aload_0
       1: getfield      #10                 // Field _defaultState:Z
       4: ireturn

  public boolean enabledIn(int);
    Code:
       0: iload_1
       1: aload_0
       2: getfield      #12                 // Field _mask:I
       5: iand
       6: ifeq          13
       9: iconst_1
      10: goto          14
      13: iconst_0
      14: ireturn

  public int getMask();
    Code:
       0: aload_0
       1: getfield      #12                 // Field _mask:I
       4: ireturn

  static {};
    Code:
       0: new           #4                  // class com/fasterxml/jackson/dataformat/yaml/YAMLParser$Feature
       3: dup
       4: ldc           #13                 // String EMPTY_STRING_AS_NULL
       6: iconst_0
       7: iconst_1
       8: invokespecial #14                 // Method "<init>":(Ljava/lang/String;IZ)V
      11: putstatic     #15                 // Field EMPTY_STRING_AS_NULL:Lcom/fasterxml/jackson/dataformat/yaml/YAMLParser$Feature;
      14: iconst_1
      15: anewarray     #4                  // class com/fasterxml/jackson/dataformat/yaml/YAMLParser$Feature
      18: dup
      19: iconst_0
      20: getstatic     #15                 // Field EMPTY_STRING_AS_NULL:Lcom/fasterxml/jackson/dataformat/yaml/YAMLParser$Feature;
      23: aastore
      24: putstatic     #1                  // Field $VALUES:[Lcom/fasterxml/jackson/dataformat/yaml/YAMLParser$Feature;
      27: return
}
