Compiled from "MAPCodec.java"
public class org.apache.cxf.ws.addressing.soap.MAPCodec extends org.apache.cxf.binding.soap.interceptor.AbstractSoapInterceptor {
  private static final java.util.logging.Logger LOG;

  private static final java.lang.String IS_REFERENCE_PARAM_ATTR_NAME;

  private static final java.util.ResourceBundle BUNDLE;

  private static final java.lang.String DECOUPLED_FAULT_SUPPORT;

  protected final java.util.Map<java.lang.String, org.apache.cxf.message.Exchange> uncorrelatedExchanges;

  private org.apache.cxf.ws.addressing.soap.VersionTransformer transformer;

  private org.apache.cxf.ws.addressing.soap.MAPCodec$HeaderFactory headerFactory;

  public org.apache.cxf.ws.addressing.soap.MAPCodec();
    Code:
       0: aload_0
       1: ldc           #1                  // String pre-protocol
       3: invokespecial #2                  // Method org/apache/cxf/binding/soap/interceptor/AbstractSoapInterceptor."<init>":(Ljava/lang/String;)V
       6: aload_0
       7: new           #3                  // class java/util/concurrent/ConcurrentHashMap
      10: dup
      11: invokespecial #4                  // Method java/util/concurrent/ConcurrentHashMap."<init>":()V
      14: putfield      #5                  // Field uncorrelatedExchanges:Ljava/util/Map;
      17: aload_0
      18: new           #6                  // class org/apache/cxf/ws/addressing/soap/VersionTransformer
      21: dup
      22: aload_0
      23: invokespecial #7                  // Method org/apache/cxf/ws/addressing/soap/VersionTransformer."<init>":(Lorg/apache/cxf/ws/addressing/soap/MAPCodec;)V
      26: putfield      #8                  // Field transformer:Lorg/apache/cxf/ws/addressing/soap/VersionTransformer;
      29: return

  public java.util.Map<java.lang.String, org.apache.cxf.message.Exchange> getUncorrelatedExchanges();
    Code:
       0: aload_0
       1: getfield      #5                  // Field uncorrelatedExchanges:Ljava/util/Map;
       4: areturn

  public java.util.Set<javax.xml.namespace.QName> getUnderstoodHeaders();
    Code:
       0: getstatic     #9                  // Field org/apache/cxf/ws/addressing/soap/VersionTransformer.HEADERS:Ljava/util/Set;
       3: areturn

  public void handleMessage(org.apache.cxf.binding.soap.SoapMessage);
    Code:
       0: aload_0
       1: aload_1
       2: invokespecial #10                 // Method mediate:(Lorg/apache/cxf/binding/soap/SoapMessage;)V
       5: return

  public void handleFault(org.apache.cxf.binding.soap.SoapMessage);
    Code:
       0: aload_1
       1: invokevirtual #11                 // Method org/apache/cxf/binding/soap/SoapMessage.getExchange:()Lorg/apache/cxf/message/Exchange;
       4: invokeinterface #12,  1           // InterfaceMethod org/apache/cxf/message/Exchange.isOneWay:()Z
       9: ifne          135
      12: aload_1
      13: iconst_0
      14: iconst_1
      15: iconst_0
      16: invokestatic  #13                 // Method org/apache/cxf/ws/addressing/ContextUtils.retrieveMAPs:(Lorg/apache/cxf/message/Message;ZZZ)Lorg/apache/cxf/ws/addressing/AddressingProperties;
      19: astore_2
      20: aload_1
      21: invokestatic  #14                 // Method org/apache/cxf/ws/addressing/ContextUtils.isRequestor:(Lorg/apache/cxf/message/Message;)Z
      24: ifeq          51
      27: aload_2
      28: ifnull        51
      31: aload_0
      32: getfield      #5                  // Field uncorrelatedExchanges:Ljava/util/Map;
      35: aload_2
      36: invokevirtual #15                 // Method org/apache/cxf/ws/addressing/AddressingProperties.getMessageID:()Lorg/apache/cxf/ws/addressing/AttributedURIType;
      39: invokevirtual #16                 // Method org/apache/cxf/ws/addressing/AttributedURIType.getValue:()Ljava/lang/String;
      42: invokeinterface #17,  2           // InterfaceMethod java/util/Map.remove:(Ljava/lang/Object;)Ljava/lang/Object;
      47: pop
      48: goto          135
      51: aload_1
      52: invokestatic  #14                 // Method org/apache/cxf/ws/addressing/ContextUtils.isRequestor:(Lorg/apache/cxf/message/Message;)Z
      55: ifne          135
      58: aload_2
      59: ifnonnull     135
      62: aload_1
      63: ldc_w         #18                 // class org/apache/cxf/ws/addressing/MAPAggregator
      66: invokevirtual #19                 // Method java/lang/Class.getName:()Ljava/lang/String;
      69: invokevirtual #20                 // Method org/apache/cxf/binding/soap/SoapMessage.containsKey:(Ljava/lang/Object;)Z
      72: ifne          135
      75: aload_1
      76: invokevirtual #21                 // Method org/apache/cxf/binding/soap/SoapMessage.getInterceptorChain:()Lorg/apache/cxf/interceptor/InterceptorChain;
      79: invokeinterface #22,  1           // InterfaceMethod org/apache/cxf/interceptor/InterceptorChain.iterator:()Ljava/util/Iterator;
      84: astore_3
      85: aload_3
      86: invokeinterface #23,  1           // InterfaceMethod java/util/Iterator.hasNext:()Z
      91: ifeq          135
      94: aload_3
      95: invokeinterface #24,  1           // InterfaceMethod java/util/Iterator.next:()Ljava/lang/Object;
     100: checkcast     #25                 // class org/apache/cxf/interceptor/Interceptor
     103: astore        4
     105: aload         4
     107: instanceof    #18                 // class org/apache/cxf/ws/addressing/MAPAggregator
     110: ifeq          132
     113: aload         4
     115: checkcast     #18                 // class org/apache/cxf/ws/addressing/MAPAggregator
     118: astore        5
     120: aload         5
     122: aload_1
     123: invokevirtual #26                 // Method org/apache/cxf/ws/addressing/MAPAggregator.handleMessage:(Lorg/apache/cxf/message/Message;)V
     126: goto          131
     129: astore        5
     131: return
     132: goto          85
     135: aload_1
     136: ldc           #28                 // String org.apache.cxf.ws.addressing.decoupled_fault_support
     138: iconst_0
     139: invokestatic  #29                 // Method org/apache/cxf/message/MessageUtils.getContextualBoolean:(Lorg/apache/cxf/message/Message;Ljava/lang/String;Z)Z
     142: ifeq          156
     145: new           #30                 // class org/apache/cxf/ws/addressing/soap/DecoupledFaultHandler
     148: dup
     149: invokespecial #31                 // Method org/apache/cxf/ws/addressing/soap/DecoupledFaultHandler."<init>":()V
     152: aload_1
     153: invokevirtual #32                 // Method org/apache/cxf/ws/addressing/soap/DecoupledFaultHandler.handleFault:(Lorg/apache/cxf/binding/soap/SoapMessage;)V
     156: return
    Exception table:
       from    to  target type
         113   126   129   Class java/lang/Throwable

  private void mediate(org.apache.cxf.binding.soap.SoapMessage);
    Code:
       0: aload_1
       1: getstatic     #33                 // Field org/apache/cxf/ws/addressing/MAPAggregator.ADDRESSING_DISABLED:Ljava/lang/String;
       4: iconst_0
       5: invokestatic  #29                 // Method org/apache/cxf/message/MessageUtils.getContextualBoolean:(Lorg/apache/cxf/message/Message;Ljava/lang/String;Z)Z
       8: ifne          132
      11: aload_1
      12: invokestatic  #34                 // Method org/apache/cxf/ws/addressing/ContextUtils.isOutbound:(Lorg/apache/cxf/message/Message;)Z
      15: ifeq          32
      18: aload_0
      19: aload_1
      20: aload_1
      21: iconst_0
      22: iconst_1
      23: invokestatic  #35                 // Method org/apache/cxf/ws/addressing/ContextUtils.retrieveMAPs:(Lorg/apache/cxf/message/Message;ZZ)Lorg/apache/cxf/ws/addressing/AddressingProperties;
      26: invokespecial #36                 // Method encode:(Lorg/apache/cxf/binding/soap/SoapMessage;Lorg/apache/cxf/ws/addressing/AddressingProperties;)V
      29: goto          132
      32: aconst_null
      33: aload_1
      34: iconst_0
      35: iconst_0
      36: iconst_0
      37: invokestatic  #13                 // Method org/apache/cxf/ws/addressing/ContextUtils.retrieveMAPs:(Lorg/apache/cxf/message/Message;ZZZ)Lorg/apache/cxf/ws/addressing/AddressingProperties;
      40: if_acmpne     132
      43: aload_0
      44: aload_1
      45: invokespecial #37                 // Method decode:(Lorg/apache/cxf/binding/soap/SoapMessage;)Lorg/apache/cxf/ws/addressing/AddressingProperties;
      48: astore_2
      49: aload_2
      50: aload_1
      51: iconst_0
      52: invokestatic  #38                 // Method org/apache/cxf/ws/addressing/ContextUtils.storeMAPs:(Lorg/apache/cxf/ws/addressing/AddressingProperties;Lorg/apache/cxf/message/Message;Z)V
      55: aload_0
      56: aload_1
      57: aload_2
      58: invokespecial #39                 // Method markPartialResponse:(Lorg/apache/cxf/binding/soap/SoapMessage;Lorg/apache/cxf/ws/addressing/AddressingProperties;)V
      61: aload_0
      62: aload_1
      63: aload_2
      64: invokespecial #40                 // Method restoreExchange:(Lorg/apache/cxf/binding/soap/SoapMessage;Lorg/apache/cxf/ws/addressing/AddressingProperties;)V
      67: aload_2
      68: ifnull        132
      71: aload_1
      72: invokestatic  #41                 // Method org/apache/cxf/message/MessageUtils.isRequestor:(Lorg/apache/cxf/message/Message;)Z
      75: ifne          132
      78: aload_1
      79: invokevirtual #11                 // Method org/apache/cxf/binding/soap/SoapMessage.getExchange:()Lorg/apache/cxf/message/Exchange;
      82: invokeinterface #42,  1           // InterfaceMethod org/apache/cxf/message/Exchange.getBindingOperationInfo:()Lorg/apache/cxf/service/model/BindingOperationInfo;
      87: ifnonnull     132
      90: aload_1
      91: invokestatic  #43                 // Method org/apache/cxf/message/MessageUtils.isOutbound:(Lorg/apache/cxf/message/Message;)Z
      94: ifne          132
      97: aload_2
      98: invokevirtual #44                 // Method org/apache/cxf/ws/addressing/AddressingProperties.getAction:()Lorg/apache/cxf/ws/addressing/AttributedURIType;
     101: ifnull        132
     104: aload_2
     105: invokevirtual #44                 // Method org/apache/cxf/ws/addressing/AddressingProperties.getAction:()Lorg/apache/cxf/ws/addressing/AttributedURIType;
     108: invokevirtual #16                 // Method org/apache/cxf/ws/addressing/AttributedURIType.getValue:()Ljava/lang/String;
     111: astore_3
     112: aload_3
     113: ifnull        132
     116: aload_1
     117: ldc           #45                 // String ws-addressing.strict.action.checking
     119: iconst_0
     120: invokestatic  #29                 // Method org/apache/cxf/message/MessageUtils.getContextualBoolean:(Lorg/apache/cxf/message/Message;Ljava/lang/String;Z)Z
     123: istore        4
     125: aload_1
     126: aload_3
     127: iload         4
     129: invokestatic  #46                 // Method org/apache/cxf/binding/soap/interceptor/SoapActionInInterceptor.getAndSetOperation:(Lorg/apache/cxf/binding/soap/SoapMessage;Ljava/lang/String;Z)V
     132: return

  private void encode(org.apache.cxf.binding.soap.SoapMessage, org.apache.cxf.ws.addressing.AddressingProperties);
    Code:
       0: aload_2
       1: ifnull        436
       4: aload_0
       5: aload_1
       6: aload_2
       7: invokespecial #47                 // Method cacheExchange:(Lorg/apache/cxf/binding/soap/SoapMessage;Lorg/apache/cxf/ws/addressing/AddressingProperties;)V
      10: getstatic     #48                 // Field LOG:Ljava/util/logging/Logger;
      13: getstatic     #49                 // Field java/util/logging/Level.FINE:Ljava/util/logging/Level;
      16: ldc           #50                 // String Outbound WS-Addressing headers
      18: invokevirtual #51                 // Method java/util/logging/Logger.log:(Ljava/util/logging/Level;Ljava/lang/String;)V
      21: aload_1
      22: invokevirtual #52                 // Method org/apache/cxf/binding/soap/SoapMessage.getHeaders:()Ljava/util/List;
      25: astore_3
      26: aload_0
      27: aload_3
      28: aload_2
      29: invokespecial #53                 // Method discardMAPs:(Ljava/util/List;Lorg/apache/cxf/ws/addressing/AddressingProperties;)V
      32: aload_2
      33: invokevirtual #54                 // Method org/apache/cxf/ws/addressing/AddressingProperties.getNamespaceURI:()Ljava/lang/String;
      36: invokestatic  #55                 // Method org/apache/cxf/ws/addressing/soap/VersionTransformer.getExposedJAXBContext:(Ljava/lang/String;)Ljavax/xml/bind/JAXBContext;
      39: astore        4
      41: aload_2
      42: invokevirtual #56                 // Method org/apache/cxf/ws/addressing/AddressingProperties.getDuplicate:()Ljavax/xml/namespace/QName;
      45: astore        5
      47: aload_0
      48: aload_2
      49: aload_1
      50: aload_2
      51: invokevirtual #44                 // Method org/apache/cxf/ws/addressing/AddressingProperties.getAction:()Lorg/apache/cxf/ws/addressing/AttributedURIType;
      54: getstatic     #57                 // Field org/apache/cxf/ws/addressing/Names.WSA_ACTION_QNAME:Ljavax/xml/namespace/QName;
      57: ldc_w         #58                 // class org/apache/cxf/ws/addressing/AttributedURIType
      60: aload         4
      62: invokespecial #59                 // Method encodeAsExposed:(Lorg/apache/cxf/ws/addressing/AddressingProperties;Lorg/apache/cxf/binding/soap/SoapMessage;Ljava/lang/Object;Ljavax/xml/namespace/QName;Ljava/lang/Class;Ljavax/xml/bind/JAXBContext;)V
      65: getstatic     #57                 // Field org/apache/cxf/ws/addressing/Names.WSA_ACTION_QNAME:Ljavax/xml/namespace/QName;
      68: aload         5
      70: invokevirtual #60                 // Method javax/xml/namespace/QName.equals:(Ljava/lang/Object;)Z
      73: ifeq          94
      76: aload_0
      77: aload_2
      78: aload_1
      79: aload_2
      80: invokevirtual #44                 // Method org/apache/cxf/ws/addressing/AddressingProperties.getAction:()Lorg/apache/cxf/ws/addressing/AttributedURIType;
      83: getstatic     #57                 // Field org/apache/cxf/ws/addressing/Names.WSA_ACTION_QNAME:Ljavax/xml/namespace/QName;
      86: ldc_w         #58                 // class org/apache/cxf/ws/addressing/AttributedURIType
      89: aload         4
      91: invokespecial #59                 // Method encodeAsExposed:(Lorg/apache/cxf/ws/addressing/AddressingProperties;Lorg/apache/cxf/binding/soap/SoapMessage;Ljava/lang/Object;Ljavax/xml/namespace/QName;Ljava/lang/Class;Ljavax/xml/bind/JAXBContext;)V
      94: aload_0
      95: aload_2
      96: aload_1
      97: aload_2
      98: invokevirtual #15                 // Method org/apache/cxf/ws/addressing/AddressingProperties.getMessageID:()Lorg/apache/cxf/ws/addressing/AttributedURIType;
     101: getstatic     #61                 // Field org/apache/cxf/ws/addressing/Names.WSA_MESSAGEID_QNAME:Ljavax/xml/namespace/QName;
     104: ldc_w         #58                 // class org/apache/cxf/ws/addressing/AttributedURIType
     107: aload         4
     109: invokespecial #59                 // Method encodeAsExposed:(Lorg/apache/cxf/ws/addressing/AddressingProperties;Lorg/apache/cxf/binding/soap/SoapMessage;Ljava/lang/Object;Ljavax/xml/namespace/QName;Ljava/lang/Class;Ljavax/xml/bind/JAXBContext;)V
     112: getstatic     #61                 // Field org/apache/cxf/ws/addressing/Names.WSA_MESSAGEID_QNAME:Ljavax/xml/namespace/QName;
     115: aload         5
     117: invokevirtual #60                 // Method javax/xml/namespace/QName.equals:(Ljava/lang/Object;)Z
     120: ifeq          141
     123: aload_0
     124: aload_2
     125: aload_1
     126: aload_2
     127: invokevirtual #15                 // Method org/apache/cxf/ws/addressing/AddressingProperties.getMessageID:()Lorg/apache/cxf/ws/addressing/AttributedURIType;
     130: getstatic     #61                 // Field org/apache/cxf/ws/addressing/Names.WSA_MESSAGEID_QNAME:Ljavax/xml/namespace/QName;
     133: ldc_w         #58                 // class org/apache/cxf/ws/addressing/AttributedURIType
     136: aload         4
     138: invokespecial #59                 // Method encodeAsExposed:(Lorg/apache/cxf/ws/addressing/AddressingProperties;Lorg/apache/cxf/binding/soap/SoapMessage;Ljava/lang/Object;Ljavax/xml/namespace/QName;Ljava/lang/Class;Ljavax/xml/bind/JAXBContext;)V
     141: aload_0
     142: aload_2
     143: aload_1
     144: aload_2
     145: invokevirtual #62                 // Method org/apache/cxf/ws/addressing/AddressingProperties.getTo:()Lorg/apache/cxf/ws/addressing/AttributedURIType;
     148: getstatic     #63                 // Field org/apache/cxf/ws/addressing/Names.WSA_TO_QNAME:Ljavax/xml/namespace/QName;
     151: ldc_w         #58                 // class org/apache/cxf/ws/addressing/AttributedURIType
     154: aload         4
     156: invokespecial #59                 // Method encodeAsExposed:(Lorg/apache/cxf/ws/addressing/AddressingProperties;Lorg/apache/cxf/binding/soap/SoapMessage;Ljava/lang/Object;Ljavax/xml/namespace/QName;Ljava/lang/Class;Ljavax/xml/bind/JAXBContext;)V
     159: getstatic     #63                 // Field org/apache/cxf/ws/addressing/Names.WSA_TO_QNAME:Ljavax/xml/namespace/QName;
     162: aload         5
     164: invokevirtual #60                 // Method javax/xml/namespace/QName.equals:(Ljava/lang/Object;)Z
     167: ifeq          188
     170: aload_0
     171: aload_2
     172: aload_1
     173: aload_2
     174: invokevirtual #62                 // Method org/apache/cxf/ws/addressing/AddressingProperties.getTo:()Lorg/apache/cxf/ws/addressing/AttributedURIType;
     177: getstatic     #63                 // Field org/apache/cxf/ws/addressing/Names.WSA_TO_QNAME:Ljavax/xml/namespace/QName;
     180: ldc_w         #58                 // class org/apache/cxf/ws/addressing/AttributedURIType
     183: aload         4
     185: invokespecial #59                 // Method encodeAsExposed:(Lorg/apache/cxf/ws/addressing/AddressingProperties;Lorg/apache/cxf/binding/soap/SoapMessage;Ljava/lang/Object;Ljavax/xml/namespace/QName;Ljava/lang/Class;Ljavax/xml/bind/JAXBContext;)V
     188: aload_0
     189: aload_2
     190: aload_1
     191: invokespecial #64                 // Method needsReplyTo:(Lorg/apache/cxf/ws/addressing/AddressingProperties;Lorg/apache/cxf/binding/soap/SoapMessage;)Z
     194: ifeq          244
     197: aload_0
     198: aload_2
     199: aload_1
     200: aload_2
     201: invokevirtual #65                 // Method org/apache/cxf/ws/addressing/AddressingProperties.getReplyTo:()Lorg/apache/cxf/ws/addressing/EndpointReferenceType;
     204: getstatic     #66                 // Field org/apache/cxf/ws/addressing/Names.WSA_REPLYTO_QNAME:Ljavax/xml/namespace/QName;
     207: ldc_w         #67                 // class org/apache/cxf/ws/addressing/EndpointReferenceType
     210: aload         4
     212: invokespecial #59                 // Method encodeAsExposed:(Lorg/apache/cxf/ws/addressing/AddressingProperties;Lorg/apache/cxf/binding/soap/SoapMessage;Ljava/lang/Object;Ljavax/xml/namespace/QName;Ljava/lang/Class;Ljavax/xml/bind/JAXBContext;)V
     215: getstatic     #66                 // Field org/apache/cxf/ws/addressing/Names.WSA_REPLYTO_QNAME:Ljavax/xml/namespace/QName;
     218: aload         5
     220: invokevirtual #60                 // Method javax/xml/namespace/QName.equals:(Ljava/lang/Object;)Z
     223: ifeq          244
     226: aload_0
     227: aload_2
     228: aload_1
     229: aload_2
     230: invokevirtual #65                 // Method org/apache/cxf/ws/addressing/AddressingProperties.getReplyTo:()Lorg/apache/cxf/ws/addressing/EndpointReferenceType;
     233: getstatic     #66                 // Field org/apache/cxf/ws/addressing/Names.WSA_REPLYTO_QNAME:Ljavax/xml/namespace/QName;
     236: ldc_w         #67                 // class org/apache/cxf/ws/addressing/EndpointReferenceType
     239: aload         4
     241: invokespecial #59                 // Method encodeAsExposed:(Lorg/apache/cxf/ws/addressing/AddressingProperties;Lorg/apache/cxf/binding/soap/SoapMessage;Ljava/lang/Object;Ljavax/xml/namespace/QName;Ljava/lang/Class;Ljavax/xml/bind/JAXBContext;)V
     244: aload_0
     245: aload_2
     246: aload_1
     247: aload_2
     248: invokevirtual #68                 // Method org/apache/cxf/ws/addressing/AddressingProperties.getRelatesTo:()Lorg/apache/cxf/ws/addressing/RelatesToType;
     251: getstatic     #69                 // Field org/apache/cxf/ws/addressing/Names.WSA_RELATESTO_QNAME:Ljavax/xml/namespace/QName;
     254: ldc_w         #70                 // class org/apache/cxf/ws/addressing/RelatesToType
     257: aload         4
     259: invokespecial #59                 // Method encodeAsExposed:(Lorg/apache/cxf/ws/addressing/AddressingProperties;Lorg/apache/cxf/binding/soap/SoapMessage;Ljava/lang/Object;Ljavax/xml/namespace/QName;Ljava/lang/Class;Ljavax/xml/bind/JAXBContext;)V
     262: getstatic     #69                 // Field org/apache/cxf/ws/addressing/Names.WSA_RELATESTO_QNAME:Ljavax/xml/namespace/QName;
     265: aload         5
     267: invokevirtual #60                 // Method javax/xml/namespace/QName.equals:(Ljava/lang/Object;)Z
     270: ifeq          291
     273: aload_0
     274: aload_2
     275: aload_1
     276: aload_2
     277: invokevirtual #68                 // Method org/apache/cxf/ws/addressing/AddressingProperties.getRelatesTo:()Lorg/apache/cxf/ws/addressing/RelatesToType;
     280: getstatic     #69                 // Field org/apache/cxf/ws/addressing/Names.WSA_RELATESTO_QNAME:Ljavax/xml/namespace/QName;
     283: ldc_w         #70                 // class org/apache/cxf/ws/addressing/RelatesToType
     286: aload         4
     288: invokespecial #59                 // Method encodeAsExposed:(Lorg/apache/cxf/ws/addressing/AddressingProperties;Lorg/apache/cxf/binding/soap/SoapMessage;Ljava/lang/Object;Ljavax/xml/namespace/QName;Ljava/lang/Class;Ljavax/xml/bind/JAXBContext;)V
     291: aload_0
     292: aload_2
     293: aload_1
     294: aload_2
     295: invokevirtual #71                 // Method org/apache/cxf/ws/addressing/AddressingProperties.getFrom:()Lorg/apache/cxf/ws/addressing/EndpointReferenceType;
     298: getstatic     #72                 // Field org/apache/cxf/ws/addressing/Names.WSA_FROM_QNAME:Ljavax/xml/namespace/QName;
     301: ldc_w         #67                 // class org/apache/cxf/ws/addressing/EndpointReferenceType
     304: aload         4
     306: invokespecial #59                 // Method encodeAsExposed:(Lorg/apache/cxf/ws/addressing/AddressingProperties;Lorg/apache/cxf/binding/soap/SoapMessage;Ljava/lang/Object;Ljavax/xml/namespace/QName;Ljava/lang/Class;Ljavax/xml/bind/JAXBContext;)V
     309: getstatic     #72                 // Field org/apache/cxf/ws/addressing/Names.WSA_FROM_QNAME:Ljavax/xml/namespace/QName;
     312: aload         5
     314: invokevirtual #60                 // Method javax/xml/namespace/QName.equals:(Ljava/lang/Object;)Z
     317: ifeq          338
     320: aload_0
     321: aload_2
     322: aload_1
     323: aload_2
     324: invokevirtual #71                 // Method org/apache/cxf/ws/addressing/AddressingProperties.getFrom:()Lorg/apache/cxf/ws/addressing/EndpointReferenceType;
     327: getstatic     #72                 // Field org/apache/cxf/ws/addressing/Names.WSA_FROM_QNAME:Ljavax/xml/namespace/QName;
     330: ldc_w         #67                 // class org/apache/cxf/ws/addressing/EndpointReferenceType
     333: aload         4
     335: invokespecial #59                 // Method encodeAsExposed:(Lorg/apache/cxf/ws/addressing/AddressingProperties;Lorg/apache/cxf/binding/soap/SoapMessage;Ljava/lang/Object;Ljavax/xml/namespace/QName;Ljava/lang/Class;Ljavax/xml/bind/JAXBContext;)V
     338: aload_0
     339: aload_2
     340: invokespecial #73                 // Method needsFaultTo:(Lorg/apache/cxf/ws/addressing/AddressingProperties;)Z
     343: ifeq          393
     346: aload_0
     347: aload_2
     348: aload_1
     349: aload_2
     350: invokevirtual #74                 // Method org/apache/cxf/ws/addressing/AddressingProperties.getFaultTo:()Lorg/apache/cxf/ws/addressing/EndpointReferenceType;
     353: getstatic     #75                 // Field org/apache/cxf/ws/addressing/Names.WSA_FAULTTO_QNAME:Ljavax/xml/namespace/QName;
     356: ldc_w         #67                 // class org/apache/cxf/ws/addressing/EndpointReferenceType
     359: aload         4
     361: invokespecial #59                 // Method encodeAsExposed:(Lorg/apache/cxf/ws/addressing/AddressingProperties;Lorg/apache/cxf/binding/soap/SoapMessage;Ljava/lang/Object;Ljavax/xml/namespace/QName;Ljava/lang/Class;Ljavax/xml/bind/JAXBContext;)V
     364: getstatic     #75                 // Field org/apache/cxf/ws/addressing/Names.WSA_FAULTTO_QNAME:Ljavax/xml/namespace/QName;
     367: aload         5
     369: invokevirtual #60                 // Method javax/xml/namespace/QName.equals:(Ljava/lang/Object;)Z
     372: ifeq          393
     375: aload_0
     376: aload_2
     377: aload_1
     378: aload_2
     379: invokevirtual #74                 // Method org/apache/cxf/ws/addressing/AddressingProperties.getFaultTo:()Lorg/apache/cxf/ws/addressing/EndpointReferenceType;
     382: getstatic     #75                 // Field org/apache/cxf/ws/addressing/Names.WSA_FAULTTO_QNAME:Ljavax/xml/namespace/QName;
     385: ldc_w         #67                 // class org/apache/cxf/ws/addressing/EndpointReferenceType
     388: aload         4
     390: invokespecial #59                 // Method encodeAsExposed:(Lorg/apache/cxf/ws/addressing/AddressingProperties;Lorg/apache/cxf/binding/soap/SoapMessage;Ljava/lang/Object;Ljavax/xml/namespace/QName;Ljava/lang/Class;Ljavax/xml/bind/JAXBContext;)V
     393: aload_0
     394: aload_2
     395: aload_1
     396: aload         4
     398: invokespecial #76                 // Method encodeReferenceParameters:(Lorg/apache/cxf/ws/addressing/AddressingProperties;Lorg/apache/cxf/binding/soap/SoapMessage;Ljavax/xml/bind/JAXBContext;)V
     401: aload_2
     402: aconst_null
     403: invokevirtual #77                 // Method org/apache/cxf/ws/addressing/AddressingProperties.setDuplicate:(Ljavax/xml/namespace/QName;)V
     406: aload_0
     407: aload_2
     408: invokevirtual #44                 // Method org/apache/cxf/ws/addressing/AddressingProperties.getAction:()Lorg/apache/cxf/ws/addressing/AttributedURIType;
     411: aload_1
     412: invokespecial #78                 // Method propogateAction:(Lorg/apache/cxf/ws/addressing/AttributedURIType;Lorg/apache/cxf/binding/soap/SoapMessage;)V
     415: aload_0
     416: aload_1
     417: invokespecial #79                 // Method applyMAPValidation:(Lorg/apache/cxf/binding/soap/SoapMessage;)V
     420: goto          436
     423: astore_3
     424: getstatic     #48                 // Field LOG:Ljava/util/logging/Logger;
     427: getstatic     #81                 // Field java/util/logging/Level.WARNING:Ljava/util/logging/Level;
     430: ldc           #82                 // String SOAP_HEADER_ENCODE_FAILURE_MSG
     432: aload_3
     433: invokevirtual #83                 // Method java/util/logging/Logger.log:(Ljava/util/logging/Level;Ljava/lang/String;Ljava/lang/Throwable;)V
     436: return
    Exception table:
       from    to  target type
          21   420   423   Class javax/xml/bind/JAXBException

  private boolean needsReplyTo(org.apache.cxf.ws.addressing.AddressingProperties, org.apache.cxf.binding.soap.SoapMessage);
    Code:
       0: aload_2
       1: ldc           #84                 // String ws-addressing.write.optional.replyto
       3: iconst_1
       4: invokestatic  #29                 // Method org/apache/cxf/message/MessageUtils.getContextualBoolean:(Lorg/apache/cxf/message/Message;Ljava/lang/String;Z)Z
       7: ifne          46
      10: aload_1
      11: invokevirtual #65                 // Method org/apache/cxf/ws/addressing/AddressingProperties.getReplyTo:()Lorg/apache/cxf/ws/addressing/EndpointReferenceType;
      14: invokestatic  #85                 // Method org/apache/cxf/ws/addressing/ContextUtils.isNoneAddress:(Lorg/apache/cxf/ws/addressing/EndpointReferenceType;)Z
      17: ifeq          34
      20: aload_2
      21: invokevirtual #11                 // Method org/apache/cxf/binding/soap/SoapMessage.getExchange:()Lorg/apache/cxf/message/Exchange;
      24: invokeinterface #12,  1           // InterfaceMethod org/apache/cxf/message/Exchange.isOneWay:()Z
      29: ifeq          34
      32: iconst_0
      33: ireturn
      34: aload_1
      35: invokevirtual #65                 // Method org/apache/cxf/ws/addressing/AddressingProperties.getReplyTo:()Lorg/apache/cxf/ws/addressing/EndpointReferenceType;
      38: invokestatic  #86                 // Method org/apache/cxf/ws/addressing/ContextUtils.isAnonymousAddress:(Lorg/apache/cxf/ws/addressing/EndpointReferenceType;)Z
      41: ifeq          46
      44: iconst_0
      45: ireturn
      46: aload_1
      47: invokevirtual #65                 // Method org/apache/cxf/ws/addressing/AddressingProperties.getReplyTo:()Lorg/apache/cxf/ws/addressing/EndpointReferenceType;
      50: ifnull        117
      53: aload_1
      54: invokevirtual #65                 // Method org/apache/cxf/ws/addressing/AddressingProperties.getReplyTo:()Lorg/apache/cxf/ws/addressing/EndpointReferenceType;
      57: invokevirtual #87                 // Method org/apache/cxf/ws/addressing/EndpointReferenceType.getAddress:()Lorg/apache/cxf/ws/addressing/AttributedURIType;
      60: ifnull        117
      63: aload_1
      64: invokevirtual #65                 // Method org/apache/cxf/ws/addressing/AddressingProperties.getReplyTo:()Lorg/apache/cxf/ws/addressing/EndpointReferenceType;
      67: invokevirtual #87                 // Method org/apache/cxf/ws/addressing/EndpointReferenceType.getAddress:()Lorg/apache/cxf/ws/addressing/AttributedURIType;
      70: invokevirtual #16                 // Method org/apache/cxf/ws/addressing/AttributedURIType.getValue:()Ljava/lang/String;
      73: ifnull        117
      76: ldc           #88                 // String http://schemas.xmlsoap.org/ws/2004/08/addressing
      78: aload_1
      79: invokevirtual #54                 // Method org/apache/cxf/ws/addressing/AddressingProperties.getNamespaceURI:()Ljava/lang/String;
      82: invokevirtual #89                 // Method java/lang/String.equals:(Ljava/lang/Object;)Z
      85: ifeq          113
      88: aload_1
      89: invokevirtual #65                 // Method org/apache/cxf/ws/addressing/AddressingProperties.getReplyTo:()Lorg/apache/cxf/ws/addressing/EndpointReferenceType;
      92: invokevirtual #87                 // Method org/apache/cxf/ws/addressing/EndpointReferenceType.getAddress:()Lorg/apache/cxf/ws/addressing/AttributedURIType;
      95: invokevirtual #16                 // Method org/apache/cxf/ws/addressing/AttributedURIType.getValue:()Ljava/lang/String;
      98: invokestatic  #90                 // Method org/apache/cxf/ws/addressing/ContextUtils.getNoneEndpointReference:()Lorg/apache/cxf/ws/addressing/EndpointReferenceType;
     101: invokevirtual #87                 // Method org/apache/cxf/ws/addressing/EndpointReferenceType.getAddress:()Lorg/apache/cxf/ws/addressing/AttributedURIType;
     104: invokevirtual #16                 // Method org/apache/cxf/ws/addressing/AttributedURIType.getValue:()Ljava/lang/String;
     107: invokevirtual #89                 // Method java/lang/String.equals:(Ljava/lang/Object;)Z
     110: ifne          117
     113: iconst_1
     114: goto          118
     117: iconst_0
     118: ireturn

  private boolean needsFaultTo(org.apache.cxf.ws.addressing.AddressingProperties);
    Code:
       0: aload_1
       1: invokevirtual #74                 // Method org/apache/cxf/ws/addressing/AddressingProperties.getFaultTo:()Lorg/apache/cxf/ws/addressing/EndpointReferenceType;
       4: ifnull        60
       7: aload_1
       8: invokevirtual #74                 // Method org/apache/cxf/ws/addressing/AddressingProperties.getFaultTo:()Lorg/apache/cxf/ws/addressing/EndpointReferenceType;
      11: invokevirtual #87                 // Method org/apache/cxf/ws/addressing/EndpointReferenceType.getAddress:()Lorg/apache/cxf/ws/addressing/AttributedURIType;
      14: ifnull        60
      17: aload_1
      18: invokevirtual #74                 // Method org/apache/cxf/ws/addressing/AddressingProperties.getFaultTo:()Lorg/apache/cxf/ws/addressing/EndpointReferenceType;
      21: invokevirtual #87                 // Method org/apache/cxf/ws/addressing/EndpointReferenceType.getAddress:()Lorg/apache/cxf/ws/addressing/AttributedURIType;
      24: invokevirtual #16                 // Method org/apache/cxf/ws/addressing/AttributedURIType.getValue:()Ljava/lang/String;
      27: ifnull        60
      30: aload_1
      31: invokevirtual #74                 // Method org/apache/cxf/ws/addressing/AddressingProperties.getFaultTo:()Lorg/apache/cxf/ws/addressing/EndpointReferenceType;
      34: invokevirtual #87                 // Method org/apache/cxf/ws/addressing/EndpointReferenceType.getAddress:()Lorg/apache/cxf/ws/addressing/AttributedURIType;
      37: invokevirtual #16                 // Method org/apache/cxf/ws/addressing/AttributedURIType.getValue:()Ljava/lang/String;
      40: aload_1
      41: invokevirtual #65                 // Method org/apache/cxf/ws/addressing/AddressingProperties.getReplyTo:()Lorg/apache/cxf/ws/addressing/EndpointReferenceType;
      44: invokevirtual #87                 // Method org/apache/cxf/ws/addressing/EndpointReferenceType.getAddress:()Lorg/apache/cxf/ws/addressing/AttributedURIType;
      47: invokevirtual #16                 // Method org/apache/cxf/ws/addressing/AttributedURIType.getValue:()Ljava/lang/String;
      50: invokevirtual #89                 // Method java/lang/String.equals:(Ljava/lang/Object;)Z
      53: ifne          60
      56: iconst_1
      57: goto          61
      60: iconst_0
      61: ireturn

  private void encodeReferenceParameters(org.apache.cxf.ws.addressing.AddressingProperties, org.apache.cxf.binding.soap.SoapMessage, javax.xml.bind.JAXBContext) throws javax.xml.bind.JAXBException;
    Code:
       0: aconst_null
       1: astore        4
       3: aload_1
       4: invokevirtual #91                 // Method org/apache/cxf/ws/addressing/AddressingProperties.getToEndpointReference:()Lorg/apache/cxf/ws/addressing/EndpointReferenceType;
       7: astore        5
       9: aconst_null
      10: aload         5
      12: if_acmpeq     258
      15: aload         5
      17: invokevirtual #92                 // Method org/apache/cxf/ws/addressing/EndpointReferenceType.getReferenceParameters:()Lorg/apache/cxf/ws/addressing/ReferenceParametersType;
      20: astore        6
      22: aconst_null
      23: aload         6
      25: if_acmpeq     258
      28: aload         6
      30: invokevirtual #93                 // Method org/apache/cxf/ws/addressing/ReferenceParametersType.getAny:()Ljava/util/List;
      33: invokeinterface #94,  1           // InterfaceMethod java/util/List.iterator:()Ljava/util/Iterator;
      38: astore        7
      40: aload         7
      42: invokeinterface #23,  1           // InterfaceMethod java/util/Iterator.hasNext:()Z
      47: ifeq          258
      50: aload         7
      52: invokeinterface #24,  1           // InterfaceMethod java/util/Iterator.next:()Ljava/lang/Object;
      57: astore        8
      59: aload         8
      61: instanceof    #95                 // class org/w3c/dom/Element
      64: ifne          75
      67: aload         8
      69: instanceof    #96                 // class javax/xml/bind/JAXBElement
      72: ifeq          242
      75: aload         4
      77: ifnonnull     95
      80: aload_0
      81: invokevirtual #97                 // Method getHeaderFactory:()Lorg/apache/cxf/ws/addressing/soap/MAPCodec$HeaderFactory;
      84: aload_2
      85: invokevirtual #98                 // Method org/apache/cxf/binding/soap/SoapMessage.getVersion:()Lorg/apache/cxf/binding/soap/SoapVersion;
      88: invokeinterface #99,  2           // InterfaceMethod org/apache/cxf/ws/addressing/soap/MAPCodec$HeaderFactory.getHeader:(Lorg/apache/cxf/binding/soap/SoapVersion;)Lorg/w3c/dom/Element;
      93: astore        4
      95: aconst_null
      96: astore        9
      98: aload         8
     100: instanceof    #95                 // class org/w3c/dom/Element
     103: ifeq          143
     106: aload         8
     108: checkcast     #95                 // class org/w3c/dom/Element
     111: astore        10
     113: aload         4
     115: invokeinterface #100,  1          // InterfaceMethod org/w3c/dom/Element.getOwnerDocument:()Lorg/w3c/dom/Document;
     120: aload         10
     122: iconst_1
     123: invokeinterface #101,  3          // InterfaceMethod org/w3c/dom/Document.importNode:(Lorg/w3c/dom/Node;Z)Lorg/w3c/dom/Node;
     128: astore        11
     130: aload         4
     132: aload         11
     134: invokeinterface #102,  2          // InterfaceMethod org/w3c/dom/Element.appendChild:(Lorg/w3c/dom/Node;)Lorg/w3c/dom/Node;
     139: pop
     140: goto          163
     143: aload         8
     145: checkcast     #96                 // class javax/xml/bind/JAXBElement
     148: astore        9
     150: aload_3
     151: invokevirtual #103                // Method javax/xml/bind/JAXBContext.createMarshaller:()Ljavax/xml/bind/Marshaller;
     154: aload         9
     156: aload         4
     158: invokeinterface #104,  3          // InterfaceMethod javax/xml/bind/Marshaller.marshal:(Ljava/lang/Object;Lorg/w3c/dom/Node;)V
     163: aload         4
     165: invokeinterface #105,  1          // InterfaceMethod org/w3c/dom/Element.getLastChild:()Lorg/w3c/dom/Node;
     170: checkcast     #95                 // class org/w3c/dom/Element
     173: astore        10
     175: aload         4
     177: aload         10
     179: invokeinterface #106,  2          // InterfaceMethod org/w3c/dom/Element.removeChild:(Lorg/w3c/dom/Node;)Lorg/w3c/dom/Node;
     184: pop
     185: aload_0
     186: aload         10
     188: aload_1
     189: invokevirtual #54                 // Method org/apache/cxf/ws/addressing/AddressingProperties.getNamespaceURI:()Ljava/lang/String;
     192: invokespecial #107                // Method addIsReferenceParameterMarkerAttribute:(Lorg/w3c/dom/Element;Ljava/lang/String;)V
     195: new           #108                // class org/apache/cxf/headers/Header
     198: dup
     199: new           #109                // class javax/xml/namespace/QName
     202: dup
     203: aload         10
     205: invokeinterface #110,  1          // InterfaceMethod org/w3c/dom/Element.getNamespaceURI:()Ljava/lang/String;
     210: aload         10
     212: invokeinterface #111,  1          // InterfaceMethod org/w3c/dom/Element.getLocalName:()Ljava/lang/String;
     217: invokespecial #112                // Method javax/xml/namespace/QName."<init>":(Ljava/lang/String;Ljava/lang/String;)V
     220: aload         10
     222: invokespecial #113                // Method org/apache/cxf/headers/Header."<init>":(Ljavax/xml/namespace/QName;Ljava/lang/Object;)V
     225: astore        11
     227: aload_2
     228: invokevirtual #52                 // Method org/apache/cxf/binding/soap/SoapMessage.getHeaders:()Ljava/util/List;
     231: aload         11
     233: invokeinterface #114,  2          // InterfaceMethod java/util/List.add:(Ljava/lang/Object;)Z
     238: pop
     239: goto          255
     242: getstatic     #48                 // Field LOG:Ljava/util/logging/Logger;
     245: getstatic     #81                 // Field java/util/logging/Level.WARNING:Ljava/util/logging/Level;
     248: ldc           #115                // String IGNORE_NON_ELEMENT_REF_PARAM_MSG
     250: aload         8
     252: invokevirtual #116                // Method java/util/logging/Logger.log:(Ljava/util/logging/Level;Ljava/lang/String;Ljava/lang/Object;)V
     255: goto          40
     258: return

  private void addIsReferenceParameterMarkerAttribute(org.w3c.dom.Element, java.lang.String);
    Code:
       0: aload_1
       1: aload_2
       2: invokeinterface #117,  2          // InterfaceMethod org/w3c/dom/Element.lookupPrefix:(Ljava/lang/String;)Ljava/lang/String;
       7: astore_3
       8: aload_3
       9: invokestatic  #118                // Method org/apache/cxf/common/util/StringUtils.isEmpty:(Ljava/lang/String;)Z
      12: ifeq          198
      15: aload_1
      16: ldc           #119                // String wsa
      18: invokeinterface #120,  2          // InterfaceMethod org/w3c/dom/Element.lookupNamespaceURI:(Ljava/lang/String;)Ljava/lang/String;
      23: ifnonnull     66
      26: ldc           #119                // String wsa
      28: astore_3
      29: aload_1
      30: invokeinterface #100,  1          // InterfaceMethod org/w3c/dom/Element.getOwnerDocument:()Lorg/w3c/dom/Document;
      35: ldc           #121                // String http://www.w3.org/2000/xmlns/
      37: ldc           #122                // String xmlns:wsa
      39: invokeinterface #123,  3          // InterfaceMethod org/w3c/dom/Document.createAttributeNS:(Ljava/lang/String;Ljava/lang/String;)Lorg/w3c/dom/Attr;
      44: astore        4
      46: aload         4
      48: aload_2
      49: invokeinterface #124,  2          // InterfaceMethod org/w3c/dom/Attr.setValue:(Ljava/lang/String;)V
      54: aload_1
      55: aload         4
      57: invokeinterface #125,  2          // InterfaceMethod org/w3c/dom/Element.setAttributeNodeNS:(Lorg/w3c/dom/Attr;)Lorg/w3c/dom/Attr;
      62: pop
      63: goto          198
      66: aload_1
      67: ldc           #119                // String wsa
      69: invokeinterface #120,  2          // InterfaceMethod org/w3c/dom/Element.lookupNamespaceURI:(Ljava/lang/String;)Ljava/lang/String;
      74: aload_2
      75: invokevirtual #89                 // Method java/lang/String.equals:(Ljava/lang/Object;)Z
      78: ifeq          87
      81: ldc           #119                // String wsa
      83: astore_3
      84: goto          198
      87: iconst_1
      88: istore        4
      90: aload_1
      91: new           #126                // class java/lang/StringBuilder
      94: dup
      95: invokespecial #127                // Method java/lang/StringBuilder."<init>":()V
      98: ldc           #119                // String wsa
     100: invokevirtual #128                // Method java/lang/StringBuilder.append:(Ljava/lang/String;)Ljava/lang/StringBuilder;
     103: iload         4
     105: invokevirtual #129                // Method java/lang/StringBuilder.append:(I)Ljava/lang/StringBuilder;
     108: invokevirtual #130                // Method java/lang/StringBuilder.toString:()Ljava/lang/String;
     111: invokeinterface #120,  2          // InterfaceMethod org/w3c/dom/Element.lookupNamespaceURI:(Ljava/lang/String;)Ljava/lang/String;
     116: ifnull        125
     119: iinc          4, 1
     122: goto          90
     125: new           #126                // class java/lang/StringBuilder
     128: dup
     129: invokespecial #127                // Method java/lang/StringBuilder."<init>":()V
     132: ldc           #119                // String wsa
     134: invokevirtual #128                // Method java/lang/StringBuilder.append:(Ljava/lang/String;)Ljava/lang/StringBuilder;
     137: iload         4
     139: invokevirtual #129                // Method java/lang/StringBuilder.append:(I)Ljava/lang/StringBuilder;
     142: invokevirtual #130                // Method java/lang/StringBuilder.toString:()Ljava/lang/String;
     145: astore_3
     146: aload_1
     147: invokeinterface #100,  1          // InterfaceMethod org/w3c/dom/Element.getOwnerDocument:()Lorg/w3c/dom/Document;
     152: ldc           #121                // String http://www.w3.org/2000/xmlns/
     154: new           #126                // class java/lang/StringBuilder
     157: dup
     158: invokespecial #127                // Method java/lang/StringBuilder."<init>":()V
     161: ldc           #122                // String xmlns:wsa
     163: invokevirtual #128                // Method java/lang/StringBuilder.append:(Ljava/lang/String;)Ljava/lang/StringBuilder;
     166: iload         4
     168: invokevirtual #129                // Method java/lang/StringBuilder.append:(I)Ljava/lang/StringBuilder;
     171: invokevirtual #130                // Method java/lang/StringBuilder.toString:()Ljava/lang/String;
     174: invokeinterface #123,  3          // InterfaceMethod org/w3c/dom/Document.createAttributeNS:(Ljava/lang/String;Ljava/lang/String;)Lorg/w3c/dom/Attr;
     179: astore        5
     181: aload         5
     183: aload_2
     184: invokeinterface #124,  2          // InterfaceMethod org/w3c/dom/Attr.setValue:(Ljava/lang/String;)V
     189: aload_1
     190: aload         5
     192: invokeinterface #125,  2          // InterfaceMethod org/w3c/dom/Element.setAttributeNodeNS:(Lorg/w3c/dom/Attr;)Lorg/w3c/dom/Attr;
     197: pop
     198: aload_1
     199: invokeinterface #100,  1          // InterfaceMethod org/w3c/dom/Element.getOwnerDocument:()Lorg/w3c/dom/Document;
     204: aload_2
     205: new           #126                // class java/lang/StringBuilder
     208: dup
     209: invokespecial #127                // Method java/lang/StringBuilder."<init>":()V
     212: aload_3
     213: invokevirtual #128                // Method java/lang/StringBuilder.append:(Ljava/lang/String;)Ljava/lang/StringBuilder;
     216: ldc           #131                // String :
     218: invokevirtual #128                // Method java/lang/StringBuilder.append:(Ljava/lang/String;)Ljava/lang/StringBuilder;
     221: ldc           #132                // String IsReferenceParameter
     223: invokevirtual #128                // Method java/lang/StringBuilder.append:(Ljava/lang/String;)Ljava/lang/StringBuilder;
     226: invokevirtual #130                // Method java/lang/StringBuilder.toString:()Ljava/lang/String;
     229: invokeinterface #123,  3          // InterfaceMethod org/w3c/dom/Document.createAttributeNS:(Ljava/lang/String;Ljava/lang/String;)Lorg/w3c/dom/Attr;
     234: astore        4
     236: aload         4
     238: ldc           #133                // String 1
     240: invokeinterface #134,  2          // InterfaceMethod org/w3c/dom/Attr.setTextContent:(Ljava/lang/String;)V
     245: aload_1
     246: aload         4
     248: invokeinterface #125,  2          // InterfaceMethod org/w3c/dom/Element.setAttributeNodeNS:(Lorg/w3c/dom/Attr;)Lorg/w3c/dom/Attr;
     253: pop
     254: return

  private <T> void encodeAsExposed(org.apache.cxf.ws.addressing.AddressingProperties, org.apache.cxf.binding.soap.SoapMessage, T, javax.xml.namespace.QName, java.lang.Class<T>, javax.xml.bind.JAXBContext) throws javax.xml.bind.JAXBException;
    Code:
       0: aload_3
       1: ifnull        72
       4: getstatic     #48                 // Field LOG:Ljava/util/logging/Logger;
       7: getstatic     #49                 // Field java/util/logging/Level.FINE:Ljava/util/logging/Level;
      10: ldc           #135                // String {0} : {1}
      12: iconst_2
      13: anewarray     #136                // class java/lang/Object
      16: dup
      17: iconst_0
      18: aload         4
      20: invokevirtual #137                // Method javax/xml/namespace/QName.getLocalPart:()Ljava/lang/String;
      23: aastore
      24: dup
      25: iconst_1
      26: aload_0
      27: aload_3
      28: invokespecial #138                // Method getLogText:(Ljava/lang/Object;)Ljava/lang/String;
      31: aastore
      32: invokevirtual #139                // Method java/util/logging/Logger.log:(Ljava/util/logging/Level;Ljava/lang/String;[Ljava/lang/Object;)V
      35: aload_1
      36: invokevirtual #140                // Method org/apache/cxf/ws/addressing/AddressingProperties.getMustUnderstand:()Ljava/util/List;
      39: aload         4
      41: invokeinterface #141,  2          // InterfaceMethod java/util/List.contains:(Ljava/lang/Object;)Z
      46: istore        7
      48: aload_0
      49: getfield      #8                  // Field transformer:Lorg/apache/cxf/ws/addressing/soap/VersionTransformer;
      52: aload_2
      53: aload_1
      54: invokevirtual #54                 // Method org/apache/cxf/ws/addressing/AddressingProperties.getNamespaceURI:()Ljava/lang/String;
      57: aload_3
      58: aload         4
      60: invokevirtual #137                // Method javax/xml/namespace/QName.getLocalPart:()Ljava/lang/String;
      63: aload         5
      65: aload         6
      67: iload         7
      69: invokevirtual #142                // Method org/apache/cxf/ws/addressing/soap/VersionTransformer.encodeAsExposed:(Lorg/apache/cxf/binding/soap/SoapMessage;Ljava/lang/String;Ljava/lang/Object;Ljava/lang/String;Ljava/lang/Class;Ljavax/xml/bind/JAXBContext;Z)V
      72: return

  public org.apache.cxf.ws.addressing.AddressingProperties unmarshalMAPs(org.apache.cxf.binding.soap.SoapMessage);
    Code:
       0: aconst_null
       1: astore_2
       2: aconst_null
       3: astore_3
       4: aload_1
       5: invokevirtual #52                 // Method org/apache/cxf/binding/soap/SoapMessage.getHeaders:()Ljava/util/List;
       8: astore        4
      10: aload         4
      12: ifnull        623
      15: getstatic     #48                 // Field LOG:Ljava/util/logging/Logger;
      18: getstatic     #49                 // Field java/util/logging/Level.FINE:Ljava/util/logging/Level;
      21: ldc           #143                // String Inbound WS-Addressing headers
      23: invokevirtual #51                 // Method java/util/logging/Logger.log:(Ljava/util/logging/Level;Ljava/lang/String;)V
      26: aconst_null
      27: astore        5
      29: aconst_null
      30: astore        6
      32: aload         4
      34: invokeinterface #144,  1          // InterfaceMethod java/util/List.iterator:()Ljava/util/Iterator;
      39: astore        7
      41: aload         7
      43: invokeinterface #23,  1           // InterfaceMethod java/util/Iterator.hasNext:()Z
      48: ifeq          546
      51: aload         7
      53: invokeinterface #24,  1           // InterfaceMethod java/util/Iterator.next:()Ljava/lang/Object;
      58: checkcast     #108                // class org/apache/cxf/headers/Header
      61: astore        8
      63: aload         8
      65: invokevirtual #145                // Method org/apache/cxf/headers/Header.getObject:()Ljava/lang/Object;
      68: instanceof    #95                 // class org/w3c/dom/Element
      71: ifeq          543
      74: aload         8
      76: invokevirtual #145                // Method org/apache/cxf/headers/Header.getObject:()Ljava/lang/Object;
      79: checkcast     #95                 // class org/w3c/dom/Element
      82: astore        9
      84: aload         9
      86: invokeinterface #110,  1          // InterfaceMethod org/w3c/dom/Element.getNamespaceURI:()Ljava/lang/String;
      91: astore        10
      93: aload         10
      95: invokestatic  #146                // Method org/apache/cxf/ws/addressing/soap/VersionTransformer.isSupported:(Ljava/lang/String;)Z
      98: ifeq          479
     101: aload_3
     102: ifnonnull     125
     105: aload         10
     107: invokestatic  #55                 // Method org/apache/cxf/ws/addressing/soap/VersionTransformer.getExposedJAXBContext:(Ljava/lang/String;)Ljavax/xml/bind/JAXBContext;
     110: astore        11
     112: aload         11
     114: invokevirtual #147                // Method javax/xml/bind/JAXBContext.createUnmarshaller:()Ljavax/xml/bind/Unmarshaller;
     117: astore_3
     118: aload_3
     119: aconst_null
     120: invokeinterface #148,  2          // InterfaceMethod javax/xml/bind/Unmarshaller.setEventHandler:(Ljavax/xml/bind/ValidationEventHandler;)V
     125: aload_2
     126: ifnonnull     143
     129: new           #149                // class org/apache/cxf/ws/addressing/AddressingProperties
     132: dup
     133: invokespecial #150                // Method org/apache/cxf/ws/addressing/AddressingProperties."<init>":()V
     136: astore_2
     137: aload_2
     138: aload         10
     140: invokevirtual #151                // Method org/apache/cxf/ws/addressing/AddressingProperties.exposeAs:(Ljava/lang/String;)V
     143: aload         9
     145: invokeinterface #111,  1          // InterfaceMethod org/w3c/dom/Element.getLocalName:()Ljava/lang/String;
     150: astore        11
     152: ldc           #152                // String MessageID
     154: aload         11
     156: invokevirtual #89                 // Method java/lang/String.equals:(Ljava/lang/Object;)Z
     159: ifeq          200
     162: aload_2
     163: invokevirtual #15                 // Method org/apache/cxf/ws/addressing/AddressingProperties.getMessageID:()Lorg/apache/cxf/ws/addressing/AttributedURIType;
     166: ifnull        175
     169: getstatic     #61                 // Field org/apache/cxf/ws/addressing/Names.WSA_MESSAGEID_QNAME:Ljavax/xml/namespace/QName;
     172: goto          176
     175: aconst_null
     176: astore        6
     178: aload_2
     179: aload_0
     180: aload         10
     182: ldc_w         #58                 // class org/apache/cxf/ws/addressing/AttributedURIType
     185: aload         9
     187: aload_3
     188: invokevirtual #153                // Method decodeAsNative:(Ljava/lang/String;Ljava/lang/Class;Lorg/w3c/dom/Element;Ljavax/xml/bind/Unmarshaller;)Ljava/lang/Object;
     191: checkcast     #58                 // class org/apache/cxf/ws/addressing/AttributedURIType
     194: invokevirtual #154                // Method org/apache/cxf/ws/addressing/AddressingProperties.setMessageID:(Lorg/apache/cxf/ws/addressing/AttributedURIType;)V
     197: goto          476
     200: ldc           #155                // String To
     202: aload         11
     204: invokevirtual #89                 // Method java/lang/String.equals:(Ljava/lang/Object;)Z
     207: ifeq          255
     210: aload_2
     211: invokevirtual #62                 // Method org/apache/cxf/ws/addressing/AddressingProperties.getTo:()Lorg/apache/cxf/ws/addressing/AttributedURIType;
     214: ifnull        223
     217: getstatic     #63                 // Field org/apache/cxf/ws/addressing/Names.WSA_TO_QNAME:Ljavax/xml/namespace/QName;
     220: goto          224
     223: aconst_null
     224: astore        6
     226: aload_0
     227: aload         10
     229: ldc_w         #58                 // class org/apache/cxf/ws/addressing/AttributedURIType
     232: aload         9
     234: aload_3
     235: invokevirtual #153                // Method decodeAsNative:(Ljava/lang/String;Ljava/lang/Class;Lorg/w3c/dom/Element;Ljavax/xml/bind/Unmarshaller;)Ljava/lang/Object;
     238: checkcast     #58                 // class org/apache/cxf/ws/addressing/AttributedURIType
     241: astore        12
     243: aload_2
     244: aload         12
     246: invokestatic  #156                // Method org/apache/cxf/ws/addressing/EndpointReferenceUtils.getEndpointReference:(Lorg/apache/cxf/ws/addressing/AttributedURIType;)Lorg/apache/cxf/ws/addressing/EndpointReferenceType;
     249: invokevirtual #157                // Method org/apache/cxf/ws/addressing/AddressingProperties.setTo:(Lorg/apache/cxf/ws/addressing/EndpointReferenceType;)V
     252: goto          476
     255: ldc           #158                // String From
     257: aload         11
     259: invokevirtual #89                 // Method java/lang/String.equals:(Ljava/lang/Object;)Z
     262: ifeq          303
     265: aload_2
     266: invokevirtual #71                 // Method org/apache/cxf/ws/addressing/AddressingProperties.getFrom:()Lorg/apache/cxf/ws/addressing/EndpointReferenceType;
     269: ifnull        278
     272: getstatic     #72                 // Field org/apache/cxf/ws/addressing/Names.WSA_FROM_QNAME:Ljavax/xml/namespace/QName;
     275: goto          279
     278: aconst_null
     279: astore        6
     281: aload_2
     282: aload_0
     283: aload         10
     285: ldc_w         #67                 // class org/apache/cxf/ws/addressing/EndpointReferenceType
     288: aload         9
     290: aload_3
     291: invokevirtual #153                // Method decodeAsNative:(Ljava/lang/String;Ljava/lang/Class;Lorg/w3c/dom/Element;Ljavax/xml/bind/Unmarshaller;)Ljava/lang/Object;
     294: checkcast     #67                 // class org/apache/cxf/ws/addressing/EndpointReferenceType
     297: invokevirtual #159                // Method org/apache/cxf/ws/addressing/AddressingProperties.setFrom:(Lorg/apache/cxf/ws/addressing/EndpointReferenceType;)V
     300: goto          476
     303: ldc           #160                // String ReplyTo
     305: aload         11
     307: invokevirtual #89                 // Method java/lang/String.equals:(Ljava/lang/Object;)Z
     310: ifeq          351
     313: aload_2
     314: invokevirtual #65                 // Method org/apache/cxf/ws/addressing/AddressingProperties.getReplyTo:()Lorg/apache/cxf/ws/addressing/EndpointReferenceType;
     317: ifnull        326
     320: getstatic     #66                 // Field org/apache/cxf/ws/addressing/Names.WSA_REPLYTO_QNAME:Ljavax/xml/namespace/QName;
     323: goto          327
     326: aconst_null
     327: astore        6
     329: aload_2
     330: aload_0
     331: aload         10
     333: ldc_w         #67                 // class org/apache/cxf/ws/addressing/EndpointReferenceType
     336: aload         9
     338: aload_3
     339: invokevirtual #153                // Method decodeAsNative:(Ljava/lang/String;Ljava/lang/Class;Lorg/w3c/dom/Element;Ljavax/xml/bind/Unmarshaller;)Ljava/lang/Object;
     342: checkcast     #67                 // class org/apache/cxf/ws/addressing/EndpointReferenceType
     345: invokevirtual #161                // Method org/apache/cxf/ws/addressing/AddressingProperties.setReplyTo:(Lorg/apache/cxf/ws/addressing/EndpointReferenceType;)V
     348: goto          476
     351: ldc           #162                // String FaultTo
     353: aload         11
     355: invokevirtual #89                 // Method java/lang/String.equals:(Ljava/lang/Object;)Z
     358: ifeq          399
     361: aload_2
     362: invokevirtual #74                 // Method org/apache/cxf/ws/addressing/AddressingProperties.getFaultTo:()Lorg/apache/cxf/ws/addressing/EndpointReferenceType;
     365: ifnull        374
     368: getstatic     #75                 // Field org/apache/cxf/ws/addressing/Names.WSA_FAULTTO_QNAME:Ljavax/xml/namespace/QName;
     371: goto          375
     374: aconst_null
     375: astore        6
     377: aload_2
     378: aload_0
     379: aload         10
     381: ldc_w         #67                 // class org/apache/cxf/ws/addressing/EndpointReferenceType
     384: aload         9
     386: aload_3
     387: invokevirtual #153                // Method decodeAsNative:(Ljava/lang/String;Ljava/lang/Class;Lorg/w3c/dom/Element;Ljavax/xml/bind/Unmarshaller;)Ljava/lang/Object;
     390: checkcast     #67                 // class org/apache/cxf/ws/addressing/EndpointReferenceType
     393: invokevirtual #163                // Method org/apache/cxf/ws/addressing/AddressingProperties.setFaultTo:(Lorg/apache/cxf/ws/addressing/EndpointReferenceType;)V
     396: goto          476
     399: ldc           #164                // String RelatesTo
     401: aload         11
     403: invokevirtual #89                 // Method java/lang/String.equals:(Ljava/lang/Object;)Z
     406: ifeq          431
     409: aload_2
     410: aload_0
     411: aload         10
     413: ldc_w         #70                 // class org/apache/cxf/ws/addressing/RelatesToType
     416: aload         9
     418: aload_3
     419: invokevirtual #153                // Method decodeAsNative:(Ljava/lang/String;Ljava/lang/Class;Lorg/w3c/dom/Element;Ljavax/xml/bind/Unmarshaller;)Ljava/lang/Object;
     422: checkcast     #70                 // class org/apache/cxf/ws/addressing/RelatesToType
     425: invokevirtual #165                // Method org/apache/cxf/ws/addressing/AddressingProperties.setRelatesTo:(Lorg/apache/cxf/ws/addressing/RelatesToType;)V
     428: goto          476
     431: ldc           #166                // String Action
     433: aload         11
     435: invokevirtual #89                 // Method java/lang/String.equals:(Ljava/lang/Object;)Z
     438: ifeq          476
     441: aload_2
     442: invokevirtual #44                 // Method org/apache/cxf/ws/addressing/AddressingProperties.getAction:()Lorg/apache/cxf/ws/addressing/AttributedURIType;
     445: ifnull        454
     448: getstatic     #57                 // Field org/apache/cxf/ws/addressing/Names.WSA_ACTION_QNAME:Ljavax/xml/namespace/QName;
     451: goto          455
     454: aconst_null
     455: astore        6
     457: aload_2
     458: aload_0
     459: aload         10
     461: ldc_w         #58                 // class org/apache/cxf/ws/addressing/AttributedURIType
     464: aload         9
     466: aload_3
     467: invokevirtual #153                // Method decodeAsNative:(Ljava/lang/String;Ljava/lang/Class;Lorg/w3c/dom/Element;Ljavax/xml/bind/Unmarshaller;)Ljava/lang/Object;
     470: checkcast     #58                 // class org/apache/cxf/ws/addressing/AttributedURIType
     473: invokevirtual #167                // Method org/apache/cxf/ws/addressing/AddressingProperties.setAction:(Lorg/apache/cxf/ws/addressing/AttributedURIType;)V
     476: goto          543
     479: aconst_null
     480: aload         9
     482: ldc           #132                // String IsReferenceParameter
     484: invokeinterface #168,  2          // InterfaceMethod org/w3c/dom/Element.getAttribute:(Ljava/lang/String;)Ljava/lang/String;
     489: if_acmpeq     520
     492: aconst_null
     493: aload         5
     495: if_acmpne     507
     498: new           #169                // class java/util/HashSet
     501: dup
     502: invokespecial #170                // Method java/util/HashSet."<init>":()V
     505: astore        5
     507: aload         5
     509: aload         9
     511: invokeinterface #171,  2          // InterfaceMethod java/util/Set.add:(Ljava/lang/Object;)Z
     516: pop
     517: goto          543
     520: aload         10
     522: ldc           #172                // String /addressing
     524: invokevirtual #173                // Method java/lang/String.contains:(Ljava/lang/CharSequence;)Z
     527: ifeq          543
     530: getstatic     #48                 // Field LOG:Ljava/util/logging/Logger;
     533: getstatic     #81                 // Field java/util/logging/Level.WARNING:Ljava/util/logging/Level;
     536: ldc           #174                // String UNSUPPORTED_VERSION_MSG
     538: aload         10
     540: invokevirtual #116                // Method java/util/logging/Logger.log:(Ljava/util/logging/Level;Ljava/lang/String;Ljava/lang/Object;)V
     543: goto          41
     546: aload_2
     547: ifnull        592
     550: aload_1
     551: invokestatic  #41                 // Method org/apache/cxf/message/MessageUtils.isRequestor:(Lorg/apache/cxf/message/Message;)Z
     554: ifne          592
     557: aload_2
     558: invokevirtual #65                 // Method org/apache/cxf/ws/addressing/AddressingProperties.getReplyTo:()Lorg/apache/cxf/ws/addressing/EndpointReferenceType;
     561: ifnonnull     592
     564: ldc           #175                // String http://www.w3.org/2005/08/addressing/anonymous
     566: invokestatic  #176                // Method org/apache/cxf/ws/addressing/ContextUtils.getAttributedURI:(Ljava/lang/String;)Lorg/apache/cxf/ws/addressing/AttributedURIType;
     569: astore        8
     571: getstatic     #177                // Field org/apache/cxf/ws/addressing/ContextUtils.WSA_OBJECT_FACTORY:Lorg/apache/cxf/ws/addressing/ObjectFactory;
     574: invokevirtual #178                // Method org/apache/cxf/ws/addressing/ObjectFactory.createEndpointReferenceType:()Lorg/apache/cxf/ws/addressing/EndpointReferenceType;
     577: astore        9
     579: aload         9
     581: aload         8
     583: invokevirtual #179                // Method org/apache/cxf/ws/addressing/EndpointReferenceType.setAddress:(Lorg/apache/cxf/ws/addressing/AttributedURIType;)V
     586: aload_2
     587: aload         9
     589: invokevirtual #161                // Method org/apache/cxf/ws/addressing/AddressingProperties.setReplyTo:(Lorg/apache/cxf/ws/addressing/EndpointReferenceType;)V
     592: aconst_null
     593: aload         5
     595: if_acmpeq     611
     598: aconst_null
     599: aload_2
     600: if_acmpeq     611
     603: aload_0
     604: aload         5
     606: aload_2
     607: aload_3
     608: invokespecial #180                // Method decodeReferenceParameters:(Ljava/util/Set;Lorg/apache/cxf/ws/addressing/AddressingProperties;Ljavax/xml/bind/Unmarshaller;)V
     611: aload         6
     613: ifnull        623
     616: aload_0
     617: aload_1
     618: aload         6
     620: invokespecial #181                // Method storeInvalidCardinalityFault:(Lorg/apache/cxf/binding/soap/SoapMessage;Ljavax/xml/namespace/QName;)V
     623: aload_3
     624: invokestatic  #182                // Method org/apache/cxf/common/jaxb/JAXBUtils.closeUnmarshaller:(Ljavax/xml/bind/Unmarshaller;)V
     627: goto          661
     630: astore        4
     632: getstatic     #48                 // Field LOG:Ljava/util/logging/Logger;
     635: getstatic     #81                 // Field java/util/logging/Level.WARNING:Ljava/util/logging/Level;
     638: ldc           #183                // String SOAP_HEADER_DECODE_FAILURE_MSG
     640: aload         4
     642: invokevirtual #83                 // Method java/util/logging/Logger.log:(Ljava/util/logging/Level;Ljava/lang/String;Ljava/lang/Throwable;)V
     645: aload_3
     646: invokestatic  #182                // Method org/apache/cxf/common/jaxb/JAXBUtils.closeUnmarshaller:(Ljavax/xml/bind/Unmarshaller;)V
     649: goto          661
     652: astore        13
     654: aload_3
     655: invokestatic  #182                // Method org/apache/cxf/common/jaxb/JAXBUtils.closeUnmarshaller:(Ljavax/xml/bind/Unmarshaller;)V
     658: aload         13
     660: athrow
     661: aload_2
     662: areturn
    Exception table:
       from    to  target type
           4   623   630   Class javax/xml/bind/JAXBException
           4   623   652   any
         630   645   652   any
         652   654   652   any

  private void storeInvalidCardinalityFault(org.apache.cxf.binding.soap.SoapMessage, javax.xml.namespace.QName);
    Code:
       0: getstatic     #48                 // Field LOG:Ljava/util/logging/Logger;
       3: getstatic     #81                 // Field java/util/logging/Level.WARNING:Ljava/util/logging/Level;
       6: ldc           #184                // String INVALID_CARDINALITY_MESSAGE
       8: aload_2
       9: invokevirtual #116                // Method java/util/logging/Logger.log:(Ljava/util/logging/Level;Ljava/lang/String;Ljava/lang/Object;)V
      12: getstatic     #185                // Field BUNDLE:Ljava/util/ResourceBundle;
      15: ldc           #186                // String INVALID_ADDRESSING_PROPERTY_MESSAGE
      17: invokevirtual #187                // Method java/util/ResourceBundle.getString:(Ljava/lang/String;)Ljava/lang/String;
      20: astore_3
      21: ldc           #188                // String InvalidCardinality
      23: aload_1
      24: invokestatic  #189                // Method org/apache/cxf/ws/addressing/ContextUtils.storeMAPFaultName:(Ljava/lang/String;Lorg/apache/cxf/message/Message;)V
      27: aload_3
      28: aload_1
      29: invokestatic  #190                // Method org/apache/cxf/ws/addressing/ContextUtils.storeMAPFaultReason:(Ljava/lang/String;Lorg/apache/cxf/message/Message;)V
      32: return

  private void decodeReferenceParameters(java.util.Set<org.w3c.dom.Element>, org.apache.cxf.ws.addressing.AddressingProperties, javax.xml.bind.Unmarshaller) throws javax.xml.bind.JAXBException;
    Code:
       0: aload_2
       1: invokevirtual #91                 // Method org/apache/cxf/ws/addressing/AddressingProperties.getToEndpointReference:()Lorg/apache/cxf/ws/addressing/EndpointReferenceType;
       4: astore        4
       6: aconst_null
       7: aload         4
       9: if_acmpeq     84
      12: aload_1
      13: invokeinterface #191,  1          // InterfaceMethod java/util/Set.iterator:()Ljava/util/Iterator;
      18: astore        5
      20: aload         5
      22: invokeinterface #23,  1           // InterfaceMethod java/util/Iterator.hasNext:()Z
      27: ifeq          84
      30: aload         5
      32: invokeinterface #24,  1           // InterfaceMethod java/util/Iterator.next:()Ljava/lang/Object;
      37: checkcast     #95                 // class org/w3c/dom/Element
      40: astore        6
      42: aload         6
      44: iconst_1
      45: invokestatic  #192                // Method org/apache/cxf/helpers/DOMUtils.getChild:(Lorg/w3c/dom/Node;I)Lorg/w3c/dom/Node;
      48: ifnonnull     74
      51: aload_3
      52: aload         6
      54: ldc_w         #193                // class java/lang/String
      57: invokeinterface #194,  3          // InterfaceMethod javax/xml/bind/Unmarshaller.unmarshal:(Lorg/w3c/dom/Node;Ljava/lang/Class;)Ljavax/xml/bind/JAXBElement;
      62: astore        7
      64: aload         4
      66: aload         7
      68: invokestatic  #195                // Method org/apache/cxf/ws/addressing/ContextUtils.applyReferenceParam:(Lorg/apache/cxf/ws/addressing/EndpointReferenceType;Ljava/lang/Object;)V
      71: goto          81
      74: aload         4
      76: aload         6
      78: invokestatic  #195                // Method org/apache/cxf/ws/addressing/ContextUtils.applyReferenceParam:(Lorg/apache/cxf/ws/addressing/EndpointReferenceType;Ljava/lang/Object;)V
      81: goto          20
      84: return

  public <T> T decodeAsNative(java.lang.String, java.lang.Class<T>, org.w3c.dom.Element, javax.xml.bind.Unmarshaller) throws javax.xml.bind.JAXBException;
    Code:
       0: aload_2
       1: aload_0
       2: getfield      #8                  // Field transformer:Lorg/apache/cxf/ws/addressing/soap/VersionTransformer;
       5: aload_1
       6: aload_2
       7: aload_3
       8: aload         4
      10: invokevirtual #196                // Method org/apache/cxf/ws/addressing/soap/VersionTransformer.decodeAsNative:(Ljava/lang/String;Ljava/lang/Class;Lorg/w3c/dom/Element;Ljavax/xml/bind/Unmarshaller;)Ljava/lang/Object;
      13: invokevirtual #197                // Method java/lang/Class.cast:(Ljava/lang/Object;)Ljava/lang/Object;
      16: astore        5
      18: getstatic     #48                 // Field LOG:Ljava/util/logging/Logger;
      21: getstatic     #49                 // Field java/util/logging/Level.FINE:Ljava/util/logging/Level;
      24: ldc           #135                // String {0} : {1}
      26: iconst_2
      27: anewarray     #136                // class java/lang/Object
      30: dup
      31: iconst_0
      32: aload_3
      33: invokeinterface #111,  1          // InterfaceMethod org/w3c/dom/Element.getLocalName:()Ljava/lang/String;
      38: aastore
      39: dup
      40: iconst_1
      41: aload_0
      42: aload         5
      44: invokespecial #138                // Method getLogText:(Ljava/lang/Object;)Ljava/lang/String;
      47: aastore
      48: invokevirtual #139                // Method java/util/logging/Logger.log:(Ljava/util/logging/Level;Ljava/lang/String;[Ljava/lang/Object;)V
      51: aload         5
      53: areturn

  private <T> java.lang.String getLogText(T);
    Code:
       0: ldc           #198                // String unknown
       2: astore_2
       3: aload_1
       4: ifnonnull     13
       7: ldc           #199                // String null
       9: astore_2
      10: goto          82
      13: aload_1
      14: instanceof    #58                 // class org/apache/cxf/ws/addressing/AttributedURIType
      17: ifeq          31
      20: aload_1
      21: checkcast     #58                 // class org/apache/cxf/ws/addressing/AttributedURIType
      24: invokevirtual #16                 // Method org/apache/cxf/ws/addressing/AttributedURIType.getValue:()Ljava/lang/String;
      27: astore_2
      28: goto          82
      31: aload_1
      32: instanceof    #67                 // class org/apache/cxf/ws/addressing/EndpointReferenceType
      35: ifeq          67
      38: aload_1
      39: checkcast     #67                 // class org/apache/cxf/ws/addressing/EndpointReferenceType
      42: invokevirtual #87                 // Method org/apache/cxf/ws/addressing/EndpointReferenceType.getAddress:()Lorg/apache/cxf/ws/addressing/AttributedURIType;
      45: ifnull        61
      48: aload_1
      49: checkcast     #67                 // class org/apache/cxf/ws/addressing/EndpointReferenceType
      52: invokevirtual #87                 // Method org/apache/cxf/ws/addressing/EndpointReferenceType.getAddress:()Lorg/apache/cxf/ws/addressing/AttributedURIType;
      55: invokevirtual #16                 // Method org/apache/cxf/ws/addressing/AttributedURIType.getValue:()Ljava/lang/String;
      58: goto          63
      61: ldc           #199                // String null
      63: astore_2
      64: goto          82
      67: aload_1
      68: instanceof    #70                 // class org/apache/cxf/ws/addressing/RelatesToType
      71: ifeq          82
      74: aload_1
      75: checkcast     #70                 // class org/apache/cxf/ws/addressing/RelatesToType
      78: invokevirtual #200                // Method org/apache/cxf/ws/addressing/RelatesToType.getValue:()Ljava/lang/String;
      81: astore_2
      82: aload_2
      83: areturn

  private org.apache.cxf.ws.addressing.AddressingProperties decode(org.apache.cxf.binding.soap.SoapMessage);
    Code:
       0: aload_0
       1: aload_1
       2: invokevirtual #201                // Method unmarshalMAPs:(Lorg/apache/cxf/binding/soap/SoapMessage;)Lorg/apache/cxf/ws/addressing/AddressingProperties;
       5: areturn

  protected <T> void encodeMAP(org.apache.cxf.binding.soap.SoapMessage, T, javax.xml.namespace.QName, java.lang.Class<T>, javax.xml.bind.JAXBContext, boolean) throws javax.xml.bind.JAXBException;
    Code:
       0: new           #202                // class org/apache/cxf/binding/soap/SoapHeader
       3: dup
       4: aload_3
       5: new           #96                 // class javax/xml/bind/JAXBElement
       8: dup
       9: aload_3
      10: aload         4
      12: aload_2
      13: invokespecial #203                // Method javax/xml/bind/JAXBElement."<init>":(Ljavax/xml/namespace/QName;Ljava/lang/Class;Ljava/lang/Object;)V
      16: new           #204                // class org/apache/cxf/jaxb/JAXBDataBinding
      19: dup
      20: aload         5
      22: invokespecial #205                // Method org/apache/cxf/jaxb/JAXBDataBinding."<init>":(Ljavax/xml/bind/JAXBContext;)V
      25: invokespecial #206                // Method org/apache/cxf/binding/soap/SoapHeader."<init>":(Ljavax/xml/namespace/QName;Ljava/lang/Object;Lorg/apache/cxf/databinding/DataBinding;)V
      28: astore        7
      30: aload         7
      32: iload         6
      34: invokevirtual #207                // Method org/apache/cxf/binding/soap/SoapHeader.setMustUnderstand:(Z)V
      37: aload_1
      38: invokevirtual #52                 // Method org/apache/cxf/binding/soap/SoapMessage.getHeaders:()Ljava/util/List;
      41: aload         7
      43: invokeinterface #114,  2          // InterfaceMethod java/util/List.add:(Ljava/lang/Object;)Z
      48: pop
      49: return

  protected <T> T decodeMAP(java.lang.Class<T>, org.w3c.dom.Element, javax.xml.bind.Unmarshaller) throws javax.xml.bind.JAXBException;
    Code:
       0: aload_3
       1: aload_2
       2: aload_1
       3: invokeinterface #194,  3          // InterfaceMethod javax/xml/bind/Unmarshaller.unmarshal:(Lorg/w3c/dom/Node;Ljava/lang/Class;)Ljavax/xml/bind/JAXBElement;
       8: astore        4
      10: aload         4
      12: invokevirtual #208                // Method javax/xml/bind/JAXBElement.getValue:()Ljava/lang/Object;
      15: areturn

  private void discardMAPs(java.util.List<org.apache.cxf.headers.Header>, org.apache.cxf.ws.addressing.AddressingProperties);
    Code:
       0: aload_1
       1: invokeinterface #144,  1          // InterfaceMethod java/util/List.iterator:()Ljava/util/Iterator;
       6: astore_3
       7: aload_3
       8: invokeinterface #23,  1           // InterfaceMethod java/util/Iterator.hasNext:()Z
      13: ifeq          68
      16: aload_3
      17: invokeinterface #24,  1           // InterfaceMethod java/util/Iterator.next:()Ljava/lang/Object;
      22: checkcast     #108                // class org/apache/cxf/headers/Header
      25: astore        4
      27: ldc           #209                // String http://www.w3.org/2005/08/addressing
      29: aload         4
      31: invokevirtual #210                // Method org/apache/cxf/headers/Header.getName:()Ljavax/xml/namespace/QName;
      34: invokevirtual #211                // Method javax/xml/namespace/QName.getNamespaceURI:()Ljava/lang/String;
      37: invokevirtual #89                 // Method java/lang/String.equals:(Ljava/lang/Object;)Z
      40: ifne          59
      43: ldc           #88                 // String http://schemas.xmlsoap.org/ws/2004/08/addressing
      45: aload         4
      47: invokevirtual #210                // Method org/apache/cxf/headers/Header.getName:()Ljavax/xml/namespace/QName;
      50: invokevirtual #211                // Method javax/xml/namespace/QName.getNamespaceURI:()Ljava/lang/String;
      53: invokevirtual #89                 // Method java/lang/String.equals:(Ljava/lang/Object;)Z
      56: ifeq          65
      59: aload_3
      60: invokeinterface #212,  1          // InterfaceMethod java/util/Iterator.remove:()V
      65: goto          7
      68: return

  private void propogateAction(org.apache.cxf.ws.addressing.AttributedURIType, org.apache.cxf.binding.soap.SoapMessage);
    Code:
       0: aload_1
       1: ifnull        134
       4: ldc           #213                // String
       6: aload_1
       7: invokevirtual #16                 // Method org/apache/cxf/ws/addressing/AttributedURIType.getValue:()Ljava/lang/String;
      10: invokevirtual #89                 // Method java/lang/String.equals:(Ljava/lang/Object;)Z
      13: ifne          134
      16: aload_2
      17: ldc           #214                // String org.apache.cxf.mime.headers
      19: invokevirtual #215                // Method org/apache/cxf/binding/soap/SoapMessage.get:(Ljava/lang/Object;)Ljava/lang/Object;
      22: checkcast     #216                // class java/util/Map
      25: invokestatic  #217                // Method org/apache/cxf/helpers/CastUtils.cast:(Ljava/util/Map;)Ljava/util/Map;
      28: astore_3
      29: aload_3
      30: ifnull        134
      33: aload_3
      34: ldc           #218                // String SOAPAction
      36: invokeinterface #219,  2          // InterfaceMethod java/util/Map.get:(Ljava/lang/Object;)Ljava/lang/Object;
      41: checkcast     #220                // class java/util/List
      44: astore        4
      46: aload         4
      48: ifnull        134
      51: aload         4
      53: invokeinterface #221,  1          // InterfaceMethod java/util/List.size:()I
      58: ifeq          134
      61: ldc           #213                // String
      63: aload         4
      65: iconst_0
      66: invokeinterface #222,  2          // InterfaceMethod java/util/List.get:(I)Ljava/lang/Object;
      71: invokevirtual #89                 // Method java/lang/String.equals:(Ljava/lang/Object;)Z
      74: ifne          134
      77: getstatic     #48                 // Field LOG:Ljava/util/logging/Logger;
      80: getstatic     #49                 // Field java/util/logging/Level.FINE:Ljava/util/logging/Level;
      83: ldc           #223                // String encoding wsa:Action in SOAPAction header {0}
      85: aload_1
      86: invokevirtual #16                 // Method org/apache/cxf/ws/addressing/AttributedURIType.getValue:()Ljava/lang/String;
      89: invokevirtual #116                // Method java/util/logging/Logger.log:(Ljava/util/logging/Level;Ljava/lang/String;Ljava/lang/Object;)V
      92: aload         4
      94: invokeinterface #224,  1          // InterfaceMethod java/util/List.clear:()V
      99: aload         4
     101: new           #126                // class java/lang/StringBuilder
     104: dup
     105: invokespecial #127                // Method java/lang/StringBuilder."<init>":()V
     108: ldc           #225                // String \"
     110: invokevirtual #128                // Method java/lang/StringBuilder.append:(Ljava/lang/String;)Ljava/lang/StringBuilder;
     113: aload_1
     114: invokevirtual #16                 // Method org/apache/cxf/ws/addressing/AttributedURIType.getValue:()Ljava/lang/String;
     117: invokevirtual #128                // Method java/lang/StringBuilder.append:(Ljava/lang/String;)Ljava/lang/StringBuilder;
     120: ldc           #225                // String \"
     122: invokevirtual #128                // Method java/lang/StringBuilder.append:(Ljava/lang/String;)Ljava/lang/StringBuilder;
     125: invokevirtual #130                // Method java/lang/StringBuilder.toString:()Ljava/lang/String;
     128: invokeinterface #114,  2          // InterfaceMethod java/util/List.add:(Ljava/lang/Object;)Z
     133: pop
     134: return

  private void applyMAPValidation(org.apache.cxf.binding.soap.SoapMessage);
    Code:
       0: aload_1
       1: invokestatic  #226                // Method org/apache/cxf/ws/addressing/ContextUtils.retrieveMAPFaultName:(Lorg/apache/cxf/message/Message;)Ljava/lang/String;
       4: astore_2
       5: aload_2
       6: ifnull        23
       9: aload_1
      10: invokestatic  #227                // Method org/apache/cxf/ws/addressing/ContextUtils.retrieveMAPFaultReason:(Lorg/apache/cxf/message/Message;)Ljava/lang/String;
      13: astore_3
      14: aload_0
      15: aload_2
      16: ldc           #209                // String http://www.w3.org/2005/08/addressing
      18: aload_3
      19: invokespecial #228                // Method createSOAPFaut:(Ljava/lang/String;Ljava/lang/String;Ljava/lang/String;)Lorg/apache/cxf/binding/soap/SoapFault;
      22: athrow
      23: return

  private org.apache.cxf.binding.soap.SoapFault createSOAPFaut(java.lang.String, java.lang.String, java.lang.String);
    Code:
       0: new           #229                // class org/apache/cxf/binding/soap/SoapFault
       3: dup
       4: aload_3
       5: new           #109                // class javax/xml/namespace/QName
       8: dup
       9: aload_2
      10: aload_1
      11: invokespecial #112                // Method javax/xml/namespace/QName."<init>":(Ljava/lang/String;Ljava/lang/String;)V
      14: invokespecial #230                // Method org/apache/cxf/binding/soap/SoapFault."<init>":(Ljava/lang/String;Ljavax/xml/namespace/QName;)V
      17: areturn

  private void cacheExchange(org.apache.cxf.binding.soap.SoapMessage, org.apache.cxf.ws.addressing.AddressingProperties);
    Code:
       0: aload_1
       1: invokestatic  #14                 // Method org/apache/cxf/ws/addressing/ContextUtils.isRequestor:(Lorg/apache/cxf/message/Message;)Z
       4: ifeq          40
       7: aload_1
       8: invokevirtual #11                 // Method org/apache/cxf/binding/soap/SoapMessage.getExchange:()Lorg/apache/cxf/message/Exchange;
      11: invokeinterface #12,  1           // InterfaceMethod org/apache/cxf/message/Exchange.isOneWay:()Z
      16: ifne          40
      19: aload_0
      20: getfield      #5                  // Field uncorrelatedExchanges:Ljava/util/Map;
      23: aload_2
      24: invokevirtual #15                 // Method org/apache/cxf/ws/addressing/AddressingProperties.getMessageID:()Lorg/apache/cxf/ws/addressing/AttributedURIType;
      27: invokevirtual #16                 // Method org/apache/cxf/ws/addressing/AttributedURIType.getValue:()Ljava/lang/String;
      30: aload_1
      31: invokevirtual #11                 // Method org/apache/cxf/binding/soap/SoapMessage.getExchange:()Lorg/apache/cxf/message/Exchange;
      34: invokeinterface #231,  3          // InterfaceMethod java/util/Map.put:(Ljava/lang/Object;Ljava/lang/Object;)Ljava/lang/Object;
      39: pop
      40: return

  private void restoreExchange(org.apache.cxf.binding.soap.SoapMessage, org.apache.cxf.ws.addressing.AddressingProperties);
    Code:
       0: aload_2
       1: ifnull        218
       4: aload_2
       5: invokevirtual #68                 // Method org/apache/cxf/ws/addressing/AddressingProperties.getRelatesTo:()Lorg/apache/cxf/ws/addressing/RelatesToType;
       8: ifnull        218
      11: ldc           #232                // String http://www.w3.org/2005/08/addressing/unspecified
      13: aload_2
      14: invokevirtual #68                 // Method org/apache/cxf/ws/addressing/AddressingProperties.getRelatesTo:()Lorg/apache/cxf/ws/addressing/RelatesToType;
      17: invokevirtual #200                // Method org/apache/cxf/ws/addressing/RelatesToType.getValue:()Ljava/lang/String;
      20: invokevirtual #89                 // Method java/lang/String.equals:(Ljava/lang/Object;)Z
      23: ifne          218
      26: aload_0
      27: aload_2
      28: invokevirtual #68                 // Method org/apache/cxf/ws/addressing/AddressingProperties.getRelatesTo:()Lorg/apache/cxf/ws/addressing/RelatesToType;
      31: invokespecial #233                // Method isRelationshipReply:(Lorg/apache/cxf/ws/addressing/RelatesToType;)Z
      34: ifeq          218
      37: aload_0
      38: getfield      #5                  // Field uncorrelatedExchanges:Ljava/util/Map;
      41: aload_2
      42: invokevirtual #68                 // Method org/apache/cxf/ws/addressing/AddressingProperties.getRelatesTo:()Lorg/apache/cxf/ws/addressing/RelatesToType;
      45: invokevirtual #200                // Method org/apache/cxf/ws/addressing/RelatesToType.getValue:()Ljava/lang/String;
      48: invokeinterface #17,  2           // InterfaceMethod java/util/Map.remove:(Ljava/lang/Object;)Ljava/lang/Object;
      53: checkcast     #234                // class org/apache/cxf/message/Exchange
      56: astore_3
      57: aload_3
      58: ifnull        88
      61: aload_3
      62: dup
      63: astore        4
      65: monitorenter
      66: aload_1
      67: aload_3
      68: invokevirtual #235                // Method org/apache/cxf/binding/soap/SoapMessage.setExchange:(Lorg/apache/cxf/message/Exchange;)V
      71: aload         4
      73: monitorexit
      74: goto          85
      77: astore        5
      79: aload         4
      81: monitorexit
      82: aload         5
      84: athrow
      85: goto          215
      88: aload_1
      89: invokestatic  #14                 // Method org/apache/cxf/ws/addressing/ContextUtils.isRequestor:(Lorg/apache/cxf/message/Message;)Z
      92: ifeq          215
      95: aload_1
      96: invokevirtual #11                 // Method org/apache/cxf/binding/soap/SoapMessage.getExchange:()Lorg/apache/cxf/message/Exchange;
      99: invokeinterface #12,  1           // InterfaceMethod org/apache/cxf/message/Exchange.isOneWay:()Z
     104: ifne          215
     107: aload_1
     108: invokestatic  #236                // Method org/apache/cxf/ws/addressing/ContextUtils.retrieveDeferUncorrelatedMessageAbort:(Lorg/apache/cxf/message/Message;)Z
     111: ifeq          129
     114: getstatic     #48                 // Field LOG:Ljava/util/logging/Logger;
     117: ldc           #237                // String deferring uncorrelated message abort
     119: invokevirtual #238                // Method java/util/logging/Logger.fine:(Ljava/lang/String;)V
     122: aload_1
     123: invokestatic  #239                // Method org/apache/cxf/ws/addressing/ContextUtils.storeDeferredUncorrelatedMessageAbort:(Lorg/apache/cxf/message/Message;)V
     126: goto          215
     129: aload_1
     130: ldc           #240                // String org.apache.cxf.ws.addressing.MAPAggregator.addressingDisabled
     132: iconst_0
     133: invokestatic  #29                 // Method org/apache/cxf/message/MessageUtils.getContextualBoolean:(Lorg/apache/cxf/message/Message;Ljava/lang/String;Z)Z
     136: ifne          215
     139: aload_1
     140: invokevirtual #11                 // Method org/apache/cxf/binding/soap/SoapMessage.getExchange:()Lorg/apache/cxf/message/Exchange;
     143: invokeinterface #241,  1          // InterfaceMethod org/apache/cxf/message/Exchange.getOutMessage:()Lorg/apache/cxf/message/Message;
     148: astore        4
     150: aload         4
     152: ifnull        166
     155: aload         4
     157: iconst_0
     158: iconst_1
     159: iconst_0
     160: invokestatic  #13                 // Method org/apache/cxf/ws/addressing/ContextUtils.retrieveMAPs:(Lorg/apache/cxf/message/Message;ZZZ)Lorg/apache/cxf/ws/addressing/AddressingProperties;
     163: goto          167
     166: aconst_null
     167: astore        5
     169: aload         5
     171: ifnull        195
     174: aload         5
     176: invokevirtual #15                 // Method org/apache/cxf/ws/addressing/AddressingProperties.getMessageID:()Lorg/apache/cxf/ws/addressing/AttributedURIType;
     179: invokevirtual #16                 // Method org/apache/cxf/ws/addressing/AttributedURIType.getValue:()Ljava/lang/String;
     182: aload_2
     183: invokevirtual #68                 // Method org/apache/cxf/ws/addressing/AddressingProperties.getRelatesTo:()Lorg/apache/cxf/ws/addressing/RelatesToType;
     186: invokevirtual #200                // Method org/apache/cxf/ws/addressing/RelatesToType.getValue:()Ljava/lang/String;
     189: invokevirtual #89                 // Method java/lang/String.equals:(Ljava/lang/Object;)Z
     192: ifne          215
     195: getstatic     #48                 // Field LOG:Ljava/util/logging/Logger;
     198: getstatic     #81                 // Field java/util/logging/Level.WARNING:Ljava/util/logging/Level;
     201: ldc           #242                // String CORRELATION_FAILURE_MSG
     203: invokevirtual #51                 // Method java/util/logging/Logger.log:(Ljava/util/logging/Level;Ljava/lang/String;)V
     206: aload_1
     207: invokevirtual #21                 // Method org/apache/cxf/binding/soap/SoapMessage.getInterceptorChain:()Lorg/apache/cxf/interceptor/InterceptorChain;
     210: invokeinterface #243,  1          // InterfaceMethod org/apache/cxf/interceptor/InterceptorChain.abort:()V
     215: goto          381
     218: aload_0
     219: aload_1
     220: invokevirtual #244                // Method isRequestor:(Lorg/apache/cxf/message/Message;)Z
     223: ifeq          381
     226: aload_2
     227: ifnonnull     313
     230: aload_1
     231: invokevirtual #11                 // Method org/apache/cxf/binding/soap/SoapMessage.getExchange:()Lorg/apache/cxf/message/Exchange;
     234: invokeinterface #241,  1          // InterfaceMethod org/apache/cxf/message/Exchange.getOutMessage:()Lorg/apache/cxf/message/Message;
     239: astore_3
     240: aload_3
     241: iconst_0
     242: iconst_1
     243: iconst_0
     244: invokestatic  #13                 // Method org/apache/cxf/ws/addressing/ContextUtils.retrieveMAPs:(Lorg/apache/cxf/message/Message;ZZZ)Lorg/apache/cxf/ws/addressing/AddressingProperties;
     247: astore_2
     248: aload_2
     249: ifnull        310
     252: aload_0
     253: getfield      #5                  // Field uncorrelatedExchanges:Ljava/util/Map;
     256: aload_2
     257: invokevirtual #15                 // Method org/apache/cxf/ws/addressing/AddressingProperties.getMessageID:()Lorg/apache/cxf/ws/addressing/AttributedURIType;
     260: invokevirtual #16                 // Method org/apache/cxf/ws/addressing/AttributedURIType.getValue:()Ljava/lang/String;
     263: invokeinterface #219,  2          // InterfaceMethod java/util/Map.get:(Ljava/lang/Object;)Ljava/lang/Object;
     268: checkcast     #234                // class org/apache/cxf/message/Exchange
     271: astore        4
     273: aload         4
     275: aload_1
     276: invokevirtual #11                 // Method org/apache/cxf/binding/soap/SoapMessage.getExchange:()Lorg/apache/cxf/message/Exchange;
     279: if_acmpne     310
     282: aload_0
     283: getfield      #5                  // Field uncorrelatedExchanges:Ljava/util/Map;
     286: aload_2
     287: invokevirtual #15                 // Method org/apache/cxf/ws/addressing/AddressingProperties.getMessageID:()Lorg/apache/cxf/ws/addressing/AttributedURIType;
     290: invokevirtual #16                 // Method org/apache/cxf/ws/addressing/AttributedURIType.getValue:()Ljava/lang/String;
     293: invokeinterface #17,  2           // InterfaceMethod java/util/Map.remove:(Ljava/lang/Object;)Ljava/lang/Object;
     298: pop
     299: getstatic     #48                 // Field LOG:Ljava/util/logging/Logger;
     302: getstatic     #81                 // Field java/util/logging/Level.WARNING:Ljava/util/logging/Level;
     305: ldc           #245                // String RESPONSE_NOT_USING_WSADDRESSING
     307: invokevirtual #51                 // Method java/util/logging/Logger.log:(Ljava/util/logging/Level;Ljava/lang/String;)V
     310: goto          381
     313: aload_2
     314: invokevirtual #68                 // Method org/apache/cxf/ws/addressing/AddressingProperties.getRelatesTo:()Lorg/apache/cxf/ws/addressing/RelatesToType;
     317: ifnonnull     381
     320: aload_2
     321: invokevirtual #44                 // Method org/apache/cxf/ws/addressing/AddressingProperties.getAction:()Lorg/apache/cxf/ws/addressing/AttributedURIType;
     324: ifnull        381
     327: ldc           #246                // String http://www.w3.org/2005/08/addressing/fault
     329: aload_2
     330: invokevirtual #44                 // Method org/apache/cxf/ws/addressing/AddressingProperties.getAction:()Lorg/apache/cxf/ws/addressing/AttributedURIType;
     333: invokevirtual #16                 // Method org/apache/cxf/ws/addressing/AttributedURIType.getValue:()Ljava/lang/String;
     336: invokevirtual #89                 // Method java/lang/String.equals:(Ljava/lang/Object;)Z
     339: ifeq          381
     342: aload_1
     343: invokevirtual #11                 // Method org/apache/cxf/binding/soap/SoapMessage.getExchange:()Lorg/apache/cxf/message/Exchange;
     346: invokeinterface #241,  1          // InterfaceMethod org/apache/cxf/message/Exchange.getOutMessage:()Lorg/apache/cxf/message/Message;
     351: astore_3
     352: aload_3
     353: iconst_0
     354: iconst_1
     355: iconst_0
     356: invokestatic  #13                 // Method org/apache/cxf/ws/addressing/ContextUtils.retrieveMAPs:(Lorg/apache/cxf/message/Message;ZZZ)Lorg/apache/cxf/ws/addressing/AddressingProperties;
     359: astore_2
     360: aload_2
     361: ifnull        381
     364: aload_0
     365: getfield      #5                  // Field uncorrelatedExchanges:Ljava/util/Map;
     368: aload_2
     369: invokevirtual #15                 // Method org/apache/cxf/ws/addressing/AddressingProperties.getMessageID:()Lorg/apache/cxf/ws/addressing/AttributedURIType;
     372: invokevirtual #16                 // Method org/apache/cxf/ws/addressing/AttributedURIType.getValue:()Ljava/lang/String;
     375: invokeinterface #17,  2           // InterfaceMethod java/util/Map.remove:(Ljava/lang/Object;)Ljava/lang/Object;
     380: pop
     381: return
    Exception table:
       from    to  target type
          66    74    77   any
          77    82    77   any

  private boolean isRelationshipReply(org.apache.cxf.ws.addressing.RelatesToType);
    Code:
       0: ldc           #247                // String http://www.w3.org/2005/08/addressing/reply
       2: aload_1
       3: invokevirtual #248                // Method org/apache/cxf/ws/addressing/RelatesToType.getRelationshipType:()Ljava/lang/String;
       6: invokevirtual #89                 // Method java/lang/String.equals:(Ljava/lang/Object;)Z
       9: ireturn

  private void markPartialResponse(org.apache.cxf.binding.soap.SoapMessage, org.apache.cxf.ws.addressing.AddressingProperties);
    Code:
       0: aload_1
       1: invokestatic  #14                 // Method org/apache/cxf/ws/addressing/ContextUtils.isRequestor:(Lorg/apache/cxf/message/Message;)Z
       4: ifeq          53
       7: aconst_null
       8: aload_2
       9: if_acmpeq     53
      12: aconst_null
      13: aload_2
      14: invokevirtual #68                 // Method org/apache/cxf/ws/addressing/AddressingProperties.getRelatesTo:()Lorg/apache/cxf/ws/addressing/RelatesToType;
      17: if_acmpeq     43
      20: aconst_null
      21: aload_2
      22: invokevirtual #68                 // Method org/apache/cxf/ws/addressing/AddressingProperties.getRelatesTo:()Lorg/apache/cxf/ws/addressing/RelatesToType;
      25: if_acmpeq     53
      28: ldc           #232                // String http://www.w3.org/2005/08/addressing/unspecified
      30: aload_2
      31: invokevirtual #68                 // Method org/apache/cxf/ws/addressing/AddressingProperties.getRelatesTo:()Lorg/apache/cxf/ws/addressing/RelatesToType;
      34: invokevirtual #200                // Method org/apache/cxf/ws/addressing/RelatesToType.getValue:()Ljava/lang/String;
      37: invokevirtual #89                 // Method java/lang/String.equals:(Ljava/lang/Object;)Z
      40: ifeq          53
      43: aload_1
      44: ldc           #249                // String org.apache.cxf.partial.response
      46: getstatic     #250                // Field java/lang/Boolean.TRUE:Ljava/lang/Boolean;
      49: invokevirtual #251                // Method org/apache/cxf/binding/soap/SoapMessage.put:(Ljava/lang/String;Ljava/lang/Object;)Ljava/lang/Object;
      52: pop
      53: return

  protected org.apache.cxf.ws.addressing.soap.MAPCodec$HeaderFactory getHeaderFactory();
    Code:
       0: aload_0
       1: getfield      #252                // Field headerFactory:Lorg/apache/cxf/ws/addressing/soap/MAPCodec$HeaderFactory;
       4: ifnonnull     19
       7: aload_0
       8: new           #253                // class org/apache/cxf/ws/addressing/soap/MAPCodec$1
      11: dup
      12: aload_0
      13: invokespecial #254                // Method org/apache/cxf/ws/addressing/soap/MAPCodec$1."<init>":(Lorg/apache/cxf/ws/addressing/soap/MAPCodec;)V
      16: putfield      #252                // Field headerFactory:Lorg/apache/cxf/ws/addressing/soap/MAPCodec$HeaderFactory;
      19: aload_0
      20: getfield      #252                // Field headerFactory:Lorg/apache/cxf/ws/addressing/soap/MAPCodec$HeaderFactory;
      23: areturn

  protected void setHeaderFactory(org.apache.cxf.ws.addressing.soap.MAPCodec$HeaderFactory);
    Code:
       0: aload_0
       1: aload_1
       2: putfield      #252                // Field headerFactory:Lorg/apache/cxf/ws/addressing/soap/MAPCodec$HeaderFactory;
       5: return

  public void handleFault(org.apache.cxf.message.Message);
    Code:
       0: aload_0
       1: aload_1
       2: checkcast     #255                // class org/apache/cxf/binding/soap/SoapMessage
       5: invokevirtual #256                // Method handleFault:(Lorg/apache/cxf/binding/soap/SoapMessage;)V
       8: return

  public void handleMessage(org.apache.cxf.message.Message) throws org.apache.cxf.interceptor.Fault;
    Code:
       0: aload_0
       1: aload_1
       2: checkcast     #255                // class org/apache/cxf/binding/soap/SoapMessage
       5: invokevirtual #257                // Method handleMessage:(Lorg/apache/cxf/binding/soap/SoapMessage;)V
       8: return

  static {};
    Code:
       0: ldc_w         #258                // class org/apache/cxf/ws/addressing/soap/MAPCodec
       3: invokestatic  #259                // Method org/apache/cxf/common/logging/LogUtils.getL7dLogger:(Ljava/lang/Class;)Ljava/util/logging/Logger;
       6: putstatic     #48                 // Field LOG:Ljava/util/logging/Logger;
       9: getstatic     #48                 // Field LOG:Ljava/util/logging/Logger;
      12: invokevirtual #260                // Method java/util/logging/Logger.getResourceBundle:()Ljava/util/ResourceBundle;
      15: putstatic     #185                // Field BUNDLE:Ljava/util/ResourceBundle;
      18: return
}
