Compiled from "DefaultHeaderChannelRegistry.java"
final class org.springframework.integration.channel.DefaultHeaderChannelRegistry$MessageChannelWrapper {
  private final org.springframework.messaging.MessageChannel channel;

  private final long expireAt;

  org.springframework.integration.channel.DefaultHeaderChannelRegistry$MessageChannelWrapper(org.springframework.messaging.MessageChannel, long);
    Code:
       0: aload_0
       1: invokespecial #1                  // Method java/lang/Object."<init>":()V
       4: aload_0
       5: aload_1
       6: putfield      #2                  // Field channel:Lorg/springframework/messaging/MessageChannel;
       9: aload_0
      10: lload_2
      11: putfield      #3                  // Field expireAt:J
      14: return

  public long getExpireAt();
    Code:
       0: aload_0
       1: getfield      #3                  // Field expireAt:J
       4: lreturn

  public org.springframework.messaging.MessageChannel getChannel();
    Code:
       0: aload_0
       1: getfield      #2                  // Field channel:Lorg/springframework/messaging/MessageChannel;
       4: areturn
}
