Compiled from "QueueChannel.java"
public class org.springframework.integration.channel.QueueChannel extends org.springframework.integration.channel.AbstractPollableChannel implements org.springframework.integration.channel.QueueChannelOperations,org.springframework.integration.support.management.QueueChannelManagement {
  private final java.util.Queue<org.springframework.messaging.Message<?>> queue;

  protected final java.util.concurrent.Semaphore queueSemaphore;

  public org.springframework.integration.channel.QueueChannel(java.util.Queue<org.springframework.messaging.Message<?>>);
    Code:
       0: aload_0
       1: invokespecial #1                  // Method org/springframework/integration/channel/AbstractPollableChannel."<init>":()V
       4: aload_0
       5: new           #2                  // class java/util/concurrent/Semaphore
       8: dup
       9: iconst_0
      10: invokespecial #3                  // Method java/util/concurrent/Semaphore."<init>":(I)V
      13: putfield      #4                  // Field queueSemaphore:Ljava/util/concurrent/Semaphore;
      16: aload_1
      17: ldc           #5                  // String \'queue\' must not be null
      19: invokestatic  #6                  // Method org/springframework/util/Assert.notNull:(Ljava/lang/Object;Ljava/lang/String;)V
      22: aload_0
      23: aload_1
      24: putfield      #7                  // Field queue:Ljava/util/Queue;
      27: return

  public org.springframework.integration.channel.QueueChannel(int);
    Code:
       0: aload_0
       1: invokespecial #1                  // Method org/springframework/integration/channel/AbstractPollableChannel."<init>":()V
       4: aload_0
       5: new           #2                  // class java/util/concurrent/Semaphore
       8: dup
       9: iconst_0
      10: invokespecial #3                  // Method java/util/concurrent/Semaphore."<init>":(I)V
      13: putfield      #4                  // Field queueSemaphore:Ljava/util/concurrent/Semaphore;
      16: iload_1
      17: ifle          24
      20: iconst_1
      21: goto          25
      24: iconst_0
      25: ldc           #8                  // String The capacity must be a positive integer. For a zero-capacity alternative, consider using a \'RendezvousChannel\'.
      27: invokestatic  #9                  // Method org/springframework/util/Assert.isTrue:(ZLjava/lang/String;)V
      30: aload_0
      31: new           #10                 // class java/util/concurrent/LinkedBlockingQueue
      34: dup
      35: iload_1
      36: invokespecial #11                 // Method java/util/concurrent/LinkedBlockingQueue."<init>":(I)V
      39: putfield      #7                  // Field queue:Ljava/util/Queue;
      42: return

  public org.springframework.integration.channel.QueueChannel();
    Code:
       0: aload_0
       1: new           #10                 // class java/util/concurrent/LinkedBlockingQueue
       4: dup
       5: invokespecial #12                 // Method java/util/concurrent/LinkedBlockingQueue."<init>":()V
       8: invokespecial #13                 // Method "<init>":(Ljava/util/Queue;)V
      11: return

  protected boolean doSend(org.springframework.messaging.Message<?>, long);
    Code:
       0: aload_1
       1: ldc           #14                 // String \'message\' must not be null
       3: invokestatic  #6                  // Method org/springframework/util/Assert.notNull:(Ljava/lang/Object;Ljava/lang/String;)V
       6: aload_0
       7: getfield      #7                  // Field queue:Ljava/util/Queue;
      10: instanceof    #15                 // class java/util/concurrent/BlockingQueue
      13: ifeq          69
      16: aload_0
      17: getfield      #7                  // Field queue:Ljava/util/Queue;
      20: checkcast     #15                 // class java/util/concurrent/BlockingQueue
      23: astore        4
      25: lload_2
      26: lconst_0
      27: lcmp
      28: ifle          44
      31: aload         4
      33: aload_1
      34: lload_2
      35: getstatic     #16                 // Field java/util/concurrent/TimeUnit.MILLISECONDS:Ljava/util/concurrent/TimeUnit;
      38: invokeinterface #17,  5           // InterfaceMethod java/util/concurrent/BlockingQueue.offer:(Ljava/lang/Object;JLjava/util/concurrent/TimeUnit;)Z
      43: ireturn
      44: lload_2
      45: lconst_0
      46: lcmp
      47: ifne          59
      50: aload         4
      52: aload_1
      53: invokeinterface #18,  2           // InterfaceMethod java/util/concurrent/BlockingQueue.offer:(Ljava/lang/Object;)Z
      58: ireturn
      59: aload         4
      61: aload_1
      62: invokeinterface #19,  2           // InterfaceMethod java/util/concurrent/BlockingQueue.put:(Ljava/lang/Object;)V
      67: iconst_1
      68: ireturn
      69: aload_0
      70: getfield      #7                  // Field queue:Ljava/util/Queue;
      73: aload_1
      74: invokeinterface #20,  2           // InterfaceMethod java/util/Queue.offer:(Ljava/lang/Object;)Z
      79: istore        4
      81: aload_0
      82: getfield      #4                  // Field queueSemaphore:Ljava/util/concurrent/Semaphore;
      85: invokevirtual #21                 // Method java/util/concurrent/Semaphore.release:()V
      88: iload         4
      90: ireturn
      91: astore        5
      93: aload_0
      94: getfield      #4                  // Field queueSemaphore:Ljava/util/concurrent/Semaphore;
      97: invokevirtual #21                 // Method java/util/concurrent/Semaphore.release:()V
     100: aload         5
     102: athrow
     103: astore        4
     105: invokestatic  #23                 // Method java/lang/Thread.currentThread:()Ljava/lang/Thread;
     108: invokevirtual #24                 // Method java/lang/Thread.interrupt:()V
     111: iconst_0
     112: ireturn
    Exception table:
       from    to  target type
          69    81    91   any
          91    93    91   any
           6    43   103   Class java/lang/InterruptedException
          44    58   103   Class java/lang/InterruptedException
          59    68   103   Class java/lang/InterruptedException
          69    88   103   Class java/lang/InterruptedException
          91   103   103   Class java/lang/InterruptedException

  protected org.springframework.messaging.Message<?> doReceive(long);
    Code:
       0: lload_1
       1: lconst_0
       2: lcmp
       3: ifle          42
       6: aload_0
       7: getfield      #7                  // Field queue:Ljava/util/Queue;
      10: instanceof    #15                 // class java/util/concurrent/BlockingQueue
      13: ifeq          36
      16: aload_0
      17: getfield      #7                  // Field queue:Ljava/util/Queue;
      20: checkcast     #15                 // class java/util/concurrent/BlockingQueue
      23: lload_1
      24: getstatic     #16                 // Field java/util/concurrent/TimeUnit.MILLISECONDS:Ljava/util/concurrent/TimeUnit;
      27: invokeinterface #25,  4           // InterfaceMethod java/util/concurrent/BlockingQueue.poll:(JLjava/util/concurrent/TimeUnit;)Ljava/lang/Object;
      32: checkcast     #26                 // class org/springframework/messaging/Message
      35: areturn
      36: aload_0
      37: lload_1
      38: invokespecial #27                 // Method pollNonBlockingQueue:(J)Lorg/springframework/messaging/Message;
      41: areturn
      42: lload_1
      43: lconst_0
      44: lcmp
      45: ifne          61
      48: aload_0
      49: getfield      #7                  // Field queue:Ljava/util/Queue;
      52: invokeinterface #28,  1           // InterfaceMethod java/util/Queue.poll:()Ljava/lang/Object;
      57: checkcast     #26                 // class org/springframework/messaging/Message
      60: areturn
      61: aload_0
      62: getfield      #7                  // Field queue:Ljava/util/Queue;
      65: instanceof    #15                 // class java/util/concurrent/BlockingQueue
      68: ifeq          87
      71: aload_0
      72: getfield      #7                  // Field queue:Ljava/util/Queue;
      75: checkcast     #15                 // class java/util/concurrent/BlockingQueue
      78: invokeinterface #29,  1           // InterfaceMethod java/util/concurrent/BlockingQueue.take:()Ljava/lang/Object;
      83: checkcast     #26                 // class org/springframework/messaging/Message
      86: areturn
      87: aload_0
      88: getfield      #7                  // Field queue:Ljava/util/Queue;
      91: invokeinterface #28,  1           // InterfaceMethod java/util/Queue.poll:()Ljava/lang/Object;
      96: checkcast     #26                 // class org/springframework/messaging/Message
      99: astore_3
     100: aload_3
     101: ifnonnull     134
     104: aload_0
     105: getfield      #4                  // Field queueSemaphore:Ljava/util/concurrent/Semaphore;
     108: ldc2_w        #30                 // long 50l
     111: getstatic     #16                 // Field java/util/concurrent/TimeUnit.MILLISECONDS:Ljava/util/concurrent/TimeUnit;
     114: invokevirtual #32                 // Method java/util/concurrent/Semaphore.tryAcquire:(JLjava/util/concurrent/TimeUnit;)Z
     117: pop
     118: aload_0
     119: getfield      #7                  // Field queue:Ljava/util/Queue;
     122: invokeinterface #28,  1           // InterfaceMethod java/util/Queue.poll:()Ljava/lang/Object;
     127: checkcast     #26                 // class org/springframework/messaging/Message
     130: astore_3
     131: goto          100
     134: aload_3
     135: areturn
     136: astore_3
     137: invokestatic  #23                 // Method java/lang/Thread.currentThread:()Ljava/lang/Thread;
     140: invokevirtual #24                 // Method java/lang/Thread.interrupt:()V
     143: aconst_null
     144: areturn
    Exception table:
       from    to  target type
           0    35   136   Class java/lang/InterruptedException
          36    41   136   Class java/lang/InterruptedException
          42    60   136   Class java/lang/InterruptedException
          61    86   136   Class java/lang/InterruptedException
          87   135   136   Class java/lang/InterruptedException

  private org.springframework.messaging.Message<?> pollNonBlockingQueue(long) throws java.lang.InterruptedException;
    Code:
       0: aload_0
       1: getfield      #7                  // Field queue:Ljava/util/Queue;
       4: invokeinterface #28,  1           // InterfaceMethod java/util/Queue.poll:()Ljava/lang/Object;
       9: checkcast     #26                 // class org/springframework/messaging/Message
      12: astore_3
      13: aload_3
      14: ifnonnull     86
      17: getstatic     #16                 // Field java/util/concurrent/TimeUnit.MILLISECONDS:Ljava/util/concurrent/TimeUnit;
      20: lload_1
      21: invokevirtual #33                 // Method java/util/concurrent/TimeUnit.toNanos:(J)J
      24: lstore        4
      26: invokestatic  #34                 // Method java/lang/System.nanoTime:()J
      29: lload         4
      31: ladd
      32: lstore        6
      34: aload_3
      35: ifnonnull     86
      38: lload         4
      40: lconst_0
      41: lcmp
      42: ifle          86
      45: aload_0
      46: getfield      #4                  // Field queueSemaphore:Ljava/util/concurrent/Semaphore;
      49: lload         4
      51: getstatic     #35                 // Field java/util/concurrent/TimeUnit.NANOSECONDS:Ljava/util/concurrent/TimeUnit;
      54: invokevirtual #32                 // Method java/util/concurrent/Semaphore.tryAcquire:(JLjava/util/concurrent/TimeUnit;)Z
      57: pop
      58: aload_0
      59: getfield      #7                  // Field queue:Ljava/util/Queue;
      62: invokeinterface #28,  1           // InterfaceMethod java/util/Queue.poll:()Ljava/lang/Object;
      67: checkcast     #26                 // class org/springframework/messaging/Message
      70: astore_3
      71: aload_3
      72: ifnonnull     34
      75: lload         6
      77: invokestatic  #34                 // Method java/lang/System.nanoTime:()J
      80: lsub
      81: lstore        4
      83: goto          34
      86: aload_3
      87: areturn

  public java.util.List<org.springframework.messaging.Message<?>> clear();
    Code:
       0: new           #36                 // class java/util/ArrayList
       3: dup
       4: invokespecial #37                 // Method java/util/ArrayList."<init>":()V
       7: astore_1
       8: aload_0
       9: getfield      #7                  // Field queue:Ljava/util/Queue;
      12: instanceof    #15                 // class java/util/concurrent/BlockingQueue
      15: ifeq          35
      18: aload_0
      19: getfield      #7                  // Field queue:Ljava/util/Queue;
      22: checkcast     #15                 // class java/util/concurrent/BlockingQueue
      25: aload_1
      26: invokeinterface #38,  2           // InterfaceMethod java/util/concurrent/BlockingQueue.drainTo:(Ljava/util/Collection;)I
      31: pop
      32: goto          65
      35: aconst_null
      36: astore_2
      37: aload_0
      38: getfield      #7                  // Field queue:Ljava/util/Queue;
      41: invokeinterface #28,  1           // InterfaceMethod java/util/Queue.poll:()Ljava/lang/Object;
      46: checkcast     #26                 // class org/springframework/messaging/Message
      49: dup
      50: astore_2
      51: ifnull        65
      54: aload_1
      55: aload_2
      56: invokeinterface #39,  2           // InterfaceMethod java/util/List.add:(Ljava/lang/Object;)Z
      61: pop
      62: goto          37
      65: aload_1
      66: areturn

  public java.util.List<org.springframework.messaging.Message<?>> purge(org.springframework.integration.core.MessageSelector);
    Code:
       0: aload_1
       1: ifnonnull     9
       4: aload_0
       5: invokevirtual #40                 // Method clear:()Ljava/util/List;
       8: areturn
       9: new           #36                 // class java/util/ArrayList
      12: dup
      13: invokespecial #37                 // Method java/util/ArrayList."<init>":()V
      16: astore_2
      17: aload_0
      18: getfield      #7                  // Field queue:Ljava/util/Queue;
      21: invokeinterface #41,  1           // InterfaceMethod java/util/Queue.toArray:()[Ljava/lang/Object;
      26: astore_3
      27: aload_3
      28: astore        4
      30: aload         4
      32: arraylength
      33: istore        5
      35: iconst_0
      36: istore        6
      38: iload         6
      40: iload         5
      42: if_icmpge     99
      45: aload         4
      47: iload         6
      49: aaload
      50: astore        7
      52: aload         7
      54: checkcast     #26                 // class org/springframework/messaging/Message
      57: astore        8
      59: aload_1
      60: aload         8
      62: invokeinterface #42,  2           // InterfaceMethod org/springframework/integration/core/MessageSelector.accept:(Lorg/springframework/messaging/Message;)Z
      67: ifne          93
      70: aload_0
      71: getfield      #7                  // Field queue:Ljava/util/Queue;
      74: aload         8
      76: invokeinterface #43,  2           // InterfaceMethod java/util/Queue.remove:(Ljava/lang/Object;)Z
      81: ifeq          93
      84: aload_2
      85: aload         8
      87: invokeinterface #39,  2           // InterfaceMethod java/util/List.add:(Ljava/lang/Object;)Z
      92: pop
      93: iinc          6, 1
      96: goto          38
      99: aload_2
     100: areturn

  public int getQueueSize();
    Code:
       0: aload_0
       1: getfield      #7                  // Field queue:Ljava/util/Queue;
       4: invokeinterface #44,  1           // InterfaceMethod java/util/Queue.size:()I
       9: ireturn

  public int getRemainingCapacity();
    Code:
       0: aload_0
       1: getfield      #7                  // Field queue:Ljava/util/Queue;
       4: instanceof    #15                 // class java/util/concurrent/BlockingQueue
       7: ifeq          23
      10: aload_0
      11: getfield      #7                  // Field queue:Ljava/util/Queue;
      14: checkcast     #15                 // class java/util/concurrent/BlockingQueue
      17: invokeinterface #45,  1           // InterfaceMethod java/util/concurrent/BlockingQueue.remainingCapacity:()I
      22: ireturn
      23: ldc           #47                 // int 2147483647
      25: ireturn
}
