Compiled from "ParameterizedSparqlString.java"
public class org.apache.jena.query.ParameterizedSparqlString implements org.apache.jena.shared.PrefixMapping {
  private org.apache.jena.rdf.model.Model model;

  private java.lang.StringBuilder cmd;

  private java.lang.String baseUri;

  private java.util.Map<java.lang.String, org.apache.jena.graph.Node> params;

  private java.util.Map<java.lang.Integer, org.apache.jena.graph.Node> positionalParams;

  private org.apache.jena.shared.PrefixMapping prefixes;

  public org.apache.jena.query.ParameterizedSparqlString(java.lang.String, org.apache.jena.query.QuerySolutionMap, java.lang.String, org.apache.jena.shared.PrefixMapping);
    Code:
       0: aload_0
       1: invokespecial #1                  // Method java/lang/Object."<init>":()V
       4: aload_0
       5: invokestatic  #2                  // Method org/apache/jena/rdf/model/ModelFactory.createDefaultModel:()Lorg/apache/jena/rdf/model/Model;
       8: putfield      #3                  // Field model:Lorg/apache/jena/rdf/model/Model;
      11: aload_0
      12: new           #4                  // class java/lang/StringBuilder
      15: dup
      16: invokespecial #5                  // Method java/lang/StringBuilder."<init>":()V
      19: putfield      #6                  // Field cmd:Ljava/lang/StringBuilder;
      22: aload_0
      23: new           #7                  // class java/util/HashMap
      26: dup
      27: invokespecial #8                  // Method java/util/HashMap."<init>":()V
      30: putfield      #9                  // Field params:Ljava/util/Map;
      33: aload_0
      34: new           #7                  // class java/util/HashMap
      37: dup
      38: invokespecial #8                  // Method java/util/HashMap."<init>":()V
      41: putfield      #10                 // Field positionalParams:Ljava/util/Map;
      44: aload_1
      45: ifnull        57
      48: aload_0
      49: getfield      #6                  // Field cmd:Ljava/lang/StringBuilder;
      52: aload_1
      53: invokevirtual #11                 // Method java/lang/StringBuilder.append:(Ljava/lang/String;)Ljava/lang/StringBuilder;
      56: pop
      57: aload_0
      58: aload_2
      59: invokevirtual #12                 // Method setParams:(Lorg/apache/jena/query/QuerySolutionMap;)V
      62: aload_0
      63: aload_3
      64: ifnull        80
      67: aload_3
      68: ldc           #13                 // String
      70: invokevirtual #14                 // Method java/lang/String.equals:(Ljava/lang/Object;)Z
      73: ifne          80
      76: aload_3
      77: goto          81
      80: aconst_null
      81: putfield      #15                 // Field baseUri:Ljava/lang/String;
      84: aload_0
      85: new           #16                 // class org/apache/jena/shared/impl/PrefixMappingImpl
      88: dup
      89: invokespecial #17                 // Method org/apache/jena/shared/impl/PrefixMappingImpl."<init>":()V
      92: putfield      #18                 // Field prefixes:Lorg/apache/jena/shared/PrefixMapping;
      95: aload         4
      97: ifnull        112
     100: aload_0
     101: getfield      #18                 // Field prefixes:Lorg/apache/jena/shared/PrefixMapping;
     104: aload         4
     106: invokeinterface #19,  2           // InterfaceMethod org/apache/jena/shared/PrefixMapping.setNsPrefixes:(Lorg/apache/jena/shared/PrefixMapping;)Lorg/apache/jena/shared/PrefixMapping;
     111: pop
     112: return

  public org.apache.jena.query.ParameterizedSparqlString(java.lang.String, org.apache.jena.query.QuerySolutionMap, java.lang.String);
    Code:
       0: aload_0
       1: aload_1
       2: aload_2
       3: aload_3
       4: aconst_null
       5: invokespecial #20                 // Method "<init>":(Ljava/lang/String;Lorg/apache/jena/query/QuerySolutionMap;Ljava/lang/String;Lorg/apache/jena/shared/PrefixMapping;)V
       8: return

  public org.apache.jena.query.ParameterizedSparqlString(java.lang.String, org.apache.jena.query.QuerySolutionMap, org.apache.jena.shared.PrefixMapping);
    Code:
       0: aload_0
       1: aload_1
       2: aload_2
       3: aconst_null
       4: aload_3
       5: invokespecial #20                 // Method "<init>":(Ljava/lang/String;Lorg/apache/jena/query/QuerySolutionMap;Ljava/lang/String;Lorg/apache/jena/shared/PrefixMapping;)V
       8: return

  public org.apache.jena.query.ParameterizedSparqlString(java.lang.String, org.apache.jena.query.QuerySolutionMap);
    Code:
       0: aload_0
       1: aload_1
       2: aload_2
       3: aconst_null
       4: aconst_null
       5: invokespecial #20                 // Method "<init>":(Ljava/lang/String;Lorg/apache/jena/query/QuerySolutionMap;Ljava/lang/String;Lorg/apache/jena/shared/PrefixMapping;)V
       8: return

  public org.apache.jena.query.ParameterizedSparqlString(java.lang.String, java.lang.String, org.apache.jena.shared.PrefixMapping);
    Code:
       0: aload_0
       1: aload_1
       2: aconst_null
       3: aload_2
       4: aload_3
       5: invokespecial #20                 // Method "<init>":(Ljava/lang/String;Lorg/apache/jena/query/QuerySolutionMap;Ljava/lang/String;Lorg/apache/jena/shared/PrefixMapping;)V
       8: return

  public org.apache.jena.query.ParameterizedSparqlString(java.lang.String, org.apache.jena.shared.PrefixMapping);
    Code:
       0: aload_0
       1: aload_1
       2: aconst_null
       3: aconst_null
       4: aload_2
       5: invokespecial #20                 // Method "<init>":(Ljava/lang/String;Lorg/apache/jena/query/QuerySolutionMap;Ljava/lang/String;Lorg/apache/jena/shared/PrefixMapping;)V
       8: return

  public org.apache.jena.query.ParameterizedSparqlString(java.lang.String, java.lang.String);
    Code:
       0: aload_0
       1: aload_1
       2: aconst_null
       3: aload_2
       4: aconst_null
       5: invokespecial #20                 // Method "<init>":(Ljava/lang/String;Lorg/apache/jena/query/QuerySolutionMap;Ljava/lang/String;Lorg/apache/jena/shared/PrefixMapping;)V
       8: return

  public org.apache.jena.query.ParameterizedSparqlString(java.lang.String);
    Code:
       0: aload_0
       1: aload_1
       2: aconst_null
       3: aconst_null
       4: aconst_null
       5: invokespecial #20                 // Method "<init>":(Ljava/lang/String;Lorg/apache/jena/query/QuerySolutionMap;Ljava/lang/String;Lorg/apache/jena/shared/PrefixMapping;)V
       8: return

  public org.apache.jena.query.ParameterizedSparqlString(org.apache.jena.query.QuerySolutionMap, org.apache.jena.shared.PrefixMapping);
    Code:
       0: aload_0
       1: aconst_null
       2: aload_1
       3: aconst_null
       4: aload_2
       5: invokespecial #20                 // Method "<init>":(Ljava/lang/String;Lorg/apache/jena/query/QuerySolutionMap;Ljava/lang/String;Lorg/apache/jena/shared/PrefixMapping;)V
       8: return

  public org.apache.jena.query.ParameterizedSparqlString(org.apache.jena.query.QuerySolutionMap);
    Code:
       0: aload_0
       1: aconst_null
       2: aload_1
       3: aconst_null
       4: aconst_null
       5: invokespecial #20                 // Method "<init>":(Ljava/lang/String;Lorg/apache/jena/query/QuerySolutionMap;Ljava/lang/String;Lorg/apache/jena/shared/PrefixMapping;)V
       8: return

  public org.apache.jena.query.ParameterizedSparqlString(org.apache.jena.shared.PrefixMapping);
    Code:
       0: aload_0
       1: aconst_null
       2: aconst_null
       3: aconst_null
       4: aload_1
       5: invokespecial #20                 // Method "<init>":(Ljava/lang/String;Lorg/apache/jena/query/QuerySolutionMap;Ljava/lang/String;Lorg/apache/jena/shared/PrefixMapping;)V
       8: return

  public org.apache.jena.query.ParameterizedSparqlString();
    Code:
       0: aload_0
       1: ldc           #13                 // String
       3: aconst_null
       4: aconst_null
       5: aconst_null
       6: invokespecial #20                 // Method "<init>":(Ljava/lang/String;Lorg/apache/jena/query/QuerySolutionMap;Ljava/lang/String;Lorg/apache/jena/shared/PrefixMapping;)V
       9: return

  public void setCommandText(java.lang.String);
    Code:
       0: aload_0
       1: new           #4                  // class java/lang/StringBuilder
       4: dup
       5: invokespecial #5                  // Method java/lang/StringBuilder."<init>":()V
       8: putfield      #6                  // Field cmd:Ljava/lang/StringBuilder;
      11: aload_0
      12: getfield      #6                  // Field cmd:Ljava/lang/StringBuilder;
      15: aload_1
      16: invokevirtual #11                 // Method java/lang/StringBuilder.append:(Ljava/lang/String;)Ljava/lang/StringBuilder;
      19: pop
      20: return

  public void append(java.lang.String);
    Code:
       0: aload_0
       1: getfield      #6                  // Field cmd:Ljava/lang/StringBuilder;
       4: aload_1
       5: invokevirtual #11                 // Method java/lang/StringBuilder.append:(Ljava/lang/String;)Ljava/lang/StringBuilder;
       8: pop
       9: return

  public void append(char);
    Code:
       0: aload_0
       1: getfield      #6                  // Field cmd:Ljava/lang/StringBuilder;
       4: iload_1
       5: invokevirtual #21                 // Method java/lang/StringBuilder.append:(C)Ljava/lang/StringBuilder;
       8: pop
       9: return

  public void append(boolean);
    Code:
       0: aload_0
       1: getfield      #6                  // Field cmd:Ljava/lang/StringBuilder;
       4: iload_1
       5: invokevirtual #22                 // Method java/lang/StringBuilder.append:(Z)Ljava/lang/StringBuilder;
       8: pop
       9: return

  public void append(double);
    Code:
       0: aload_0
       1: getfield      #6                  // Field cmd:Ljava/lang/StringBuilder;
       4: dload_1
       5: invokevirtual #23                 // Method java/lang/StringBuilder.append:(D)Ljava/lang/StringBuilder;
       8: pop
       9: return

  public void append(float);
    Code:
       0: aload_0
       1: getfield      #6                  // Field cmd:Ljava/lang/StringBuilder;
       4: fload_1
       5: invokevirtual #24                 // Method java/lang/StringBuilder.append:(F)Ljava/lang/StringBuilder;
       8: pop
       9: return

  public void append(int);
    Code:
       0: aload_0
       1: getfield      #6                  // Field cmd:Ljava/lang/StringBuilder;
       4: iload_1
       5: invokevirtual #25                 // Method java/lang/StringBuilder.append:(I)Ljava/lang/StringBuilder;
       8: pop
       9: return

  public void append(long);
    Code:
       0: aload_0
       1: getfield      #6                  // Field cmd:Ljava/lang/StringBuilder;
       4: lload_1
       5: invokevirtual #26                 // Method java/lang/StringBuilder.append:(J)Ljava/lang/StringBuilder;
       8: pop
       9: return

  public void append(java.lang.Object);
    Code:
       0: aload_0
       1: getfield      #6                  // Field cmd:Ljava/lang/StringBuilder;
       4: aload_1
       5: invokevirtual #27                 // Method java/lang/StringBuilder.append:(Ljava/lang/Object;)Ljava/lang/StringBuilder;
       8: pop
       9: return

  public void appendNode(org.apache.jena.graph.Node);
    Code:
       0: new           #28                 // class org/apache/jena/sparql/serializer/SerializationContext
       3: dup
       4: aload_0
       5: getfield      #18                 // Field prefixes:Lorg/apache/jena/shared/PrefixMapping;
       8: invokespecial #29                 // Method org/apache/jena/sparql/serializer/SerializationContext."<init>":(Lorg/apache/jena/shared/PrefixMapping;)V
      11: astore_2
      12: aload_2
      13: aload_0
      14: getfield      #15                 // Field baseUri:Ljava/lang/String;
      17: invokevirtual #30                 // Method org/apache/jena/sparql/serializer/SerializationContext.setBaseIRI:(Ljava/lang/String;)V
      20: aload_0
      21: getfield      #6                  // Field cmd:Ljava/lang/StringBuilder;
      24: aload_0
      25: aload_1
      26: aload_2
      27: invokevirtual #31                 // Method stringForNode:(Lorg/apache/jena/graph/Node;Lorg/apache/jena/sparql/serializer/SerializationContext;)Ljava/lang/String;
      30: invokevirtual #11                 // Method java/lang/StringBuilder.append:(Ljava/lang/String;)Ljava/lang/StringBuilder;
      33: pop
      34: return

  public void appendNode(org.apache.jena.rdf.model.RDFNode);
    Code:
       0: aload_0
       1: aload_1
       2: invokeinterface #32,  1           // InterfaceMethod org/apache/jena/rdf/model/RDFNode.asNode:()Lorg/apache/jena/graph/Node;
       7: invokevirtual #33                 // Method appendNode:(Lorg/apache/jena/graph/Node;)V
      10: return

  public void appendIri(java.lang.String);
    Code:
       0: aload_0
       1: aload_1
       2: invokestatic  #34                 // Method org/apache/jena/graph/NodeFactory.createURI:(Ljava/lang/String;)Lorg/apache/jena/graph/Node;
       5: invokevirtual #33                 // Method appendNode:(Lorg/apache/jena/graph/Node;)V
       8: return

  public void appendIri(org.apache.jena.iri.IRI);
    Code:
       0: aload_0
       1: aload_1
       2: invokevirtual #35                 // Method org/apache/jena/iri/IRI.toString:()Ljava/lang/String;
       5: invokestatic  #34                 // Method org/apache/jena/graph/NodeFactory.createURI:(Ljava/lang/String;)Lorg/apache/jena/graph/Node;
       8: invokevirtual #33                 // Method appendNode:(Lorg/apache/jena/graph/Node;)V
      11: return

  public void appendLiteral(java.lang.String);
    Code:
       0: aload_0
       1: aload_1
       2: aconst_null
       3: aconst_null
       4: invokestatic  #36                 // Method org/apache/jena/sparql/util/NodeFactoryExtra.createLiteralNode:(Ljava/lang/String;Ljava/lang/String;Ljava/lang/String;)Lorg/apache/jena/graph/Node;
       7: invokevirtual #33                 // Method appendNode:(Lorg/apache/jena/graph/Node;)V
      10: return

  public void appendLiteral(java.lang.String, java.lang.String);
    Code:
       0: aload_0
       1: aload_1
       2: aload_2
       3: aconst_null
       4: invokestatic  #36                 // Method org/apache/jena/sparql/util/NodeFactoryExtra.createLiteralNode:(Ljava/lang/String;Ljava/lang/String;Ljava/lang/String;)Lorg/apache/jena/graph/Node;
       7: invokevirtual #33                 // Method appendNode:(Lorg/apache/jena/graph/Node;)V
      10: return

  public void appendLiteral(java.lang.String, org.apache.jena.datatypes.RDFDatatype);
    Code:
       0: aload_0
       1: aload_1
       2: aconst_null
       3: aload_2
       4: invokeinterface #37,  1           // InterfaceMethod org/apache/jena/datatypes/RDFDatatype.getURI:()Ljava/lang/String;
       9: invokestatic  #36                 // Method org/apache/jena/sparql/util/NodeFactoryExtra.createLiteralNode:(Ljava/lang/String;Ljava/lang/String;Ljava/lang/String;)Lorg/apache/jena/graph/Node;
      12: invokevirtual #33                 // Method appendNode:(Lorg/apache/jena/graph/Node;)V
      15: return

  public void appendLiteral(boolean);
    Code:
       0: aload_0
       1: aload_0
       2: getfield      #3                  // Field model:Lorg/apache/jena/rdf/model/Model;
       5: iload_1
       6: invokeinterface #38,  2           // InterfaceMethod org/apache/jena/rdf/model/Model.createTypedLiteral:(Z)Lorg/apache/jena/rdf/model/Literal;
      11: invokevirtual #39                 // Method appendNode:(Lorg/apache/jena/rdf/model/RDFNode;)V
      14: return

  public void appendLiteral(int);
    Code:
       0: aload_0
       1: iload_1
       2: invokestatic  #40                 // Method org/apache/jena/sparql/util/NodeFactoryExtra.intToNode:(I)Lorg/apache/jena/graph/Node;
       5: invokevirtual #33                 // Method appendNode:(Lorg/apache/jena/graph/Node;)V
       8: return

  public void appendLiteral(long);
    Code:
       0: aload_0
       1: lload_1
       2: invokestatic  #41                 // Method org/apache/jena/sparql/util/NodeFactoryExtra.intToNode:(J)Lorg/apache/jena/graph/Node;
       5: invokevirtual #33                 // Method appendNode:(Lorg/apache/jena/graph/Node;)V
       8: return

  public void appendLiteral(float);
    Code:
       0: aload_0
       1: aload_0
       2: getfield      #3                  // Field model:Lorg/apache/jena/rdf/model/Model;
       5: fload_1
       6: invokeinterface #42,  2           // InterfaceMethod org/apache/jena/rdf/model/Model.createTypedLiteral:(F)Lorg/apache/jena/rdf/model/Literal;
      11: invokevirtual #39                 // Method appendNode:(Lorg/apache/jena/rdf/model/RDFNode;)V
      14: return

  public void appendLiteral(double);
    Code:
       0: aload_0
       1: aload_0
       2: getfield      #3                  // Field model:Lorg/apache/jena/rdf/model/Model;
       5: dload_1
       6: invokeinterface #43,  3           // InterfaceMethod org/apache/jena/rdf/model/Model.createTypedLiteral:(D)Lorg/apache/jena/rdf/model/Literal;
      11: invokevirtual #39                 // Method appendNode:(Lorg/apache/jena/rdf/model/RDFNode;)V
      14: return

  public void appendLiteral(java.util.Calendar);
    Code:
       0: aload_0
       1: aload_0
       2: getfield      #3                  // Field model:Lorg/apache/jena/rdf/model/Model;
       5: aload_1
       6: invokeinterface #44,  2           // InterfaceMethod org/apache/jena/rdf/model/Model.createTypedLiteral:(Ljava/util/Calendar;)Lorg/apache/jena/rdf/model/Literal;
      11: invokevirtual #39                 // Method appendNode:(Lorg/apache/jena/rdf/model/RDFNode;)V
      14: return

  public java.lang.String getCommandText();
    Code:
       0: aload_0
       1: getfield      #6                  // Field cmd:Ljava/lang/StringBuilder;
       4: invokevirtual #45                 // Method java/lang/StringBuilder.toString:()Ljava/lang/String;
       7: areturn

  public void setBaseUri(java.lang.String);
    Code:
       0: aload_0
       1: aload_1
       2: putfield      #15                 // Field baseUri:Ljava/lang/String;
       5: return

  public java.lang.String getBaseUri();
    Code:
       0: aload_0
       1: getfield      #15                 // Field baseUri:Ljava/lang/String;
       4: areturn

  protected void validateParameterValue(org.apache.jena.graph.Node);
    Code:
       0: aload_1
       1: invokevirtual #46                 // Method org/apache/jena/graph/Node.isURI:()Z
       4: ifeq          29
       7: aload_1
       8: invokevirtual #47                 // Method org/apache/jena/graph/Node.getURI:()Ljava/lang/String;
      11: ldc           #48                 // String >
      13: invokevirtual #49                 // Method java/lang/String.contains:(Ljava/lang/CharSequence;)Z
      16: ifeq          29
      19: new           #50                 // class org/apache/jena/sparql/ARQException
      22: dup
      23: ldc           #51                 // String Value for the parameter contains a SPARQL injection risk
      25: invokespecial #52                 // Method org/apache/jena/sparql/ARQException."<init>":(Ljava/lang/String;)V
      28: athrow
      29: return

  public void setParams(org.apache.jena.query.QuerySolutionMap);
    Code:
       0: aload_1
       1: ifnull        46
       4: aload_1
       5: invokevirtual #53                 // Method org/apache/jena/query/QuerySolutionMap.varNames:()Ljava/util/Iterator;
       8: astore_2
       9: aload_2
      10: invokeinterface #54,  1           // InterfaceMethod java/util/Iterator.hasNext:()Z
      15: ifeq          46
      18: aload_2
      19: invokeinterface #55,  1           // InterfaceMethod java/util/Iterator.next:()Ljava/lang/Object;
      24: checkcast     #56                 // class java/lang/String
      27: astore_3
      28: aload_0
      29: aload_3
      30: aload_1
      31: aload_3
      32: invokevirtual #57                 // Method org/apache/jena/query/QuerySolutionMap.get:(Ljava/lang/String;)Lorg/apache/jena/rdf/model/RDFNode;
      35: invokeinterface #32,  1           // InterfaceMethod org/apache/jena/rdf/model/RDFNode.asNode:()Lorg/apache/jena/graph/Node;
      40: invokevirtual #58                 // Method setParam:(Ljava/lang/String;Lorg/apache/jena/graph/Node;)V
      43: goto          9
      46: return

  public void setParam(int, org.apache.jena.graph.Node);
    Code:
       0: iload_1
       1: ifge          12
       4: new           #59                 // class java/lang/IndexOutOfBoundsException
       7: dup
       8: invokespecial #60                 // Method java/lang/IndexOutOfBoundsException."<init>":()V
      11: athrow
      12: aload_2
      13: ifnull        39
      16: aload_0
      17: aload_2
      18: invokevirtual #61                 // Method validateParameterValue:(Lorg/apache/jena/graph/Node;)V
      21: aload_0
      22: getfield      #10                 // Field positionalParams:Ljava/util/Map;
      25: iload_1
      26: invokestatic  #62                 // Method java/lang/Integer.valueOf:(I)Ljava/lang/Integer;
      29: aload_2
      30: invokeinterface #63,  3           // InterfaceMethod java/util/Map.put:(Ljava/lang/Object;Ljava/lang/Object;)Ljava/lang/Object;
      35: pop
      36: goto          53
      39: aload_0
      40: getfield      #10                 // Field positionalParams:Ljava/util/Map;
      43: iload_1
      44: invokestatic  #62                 // Method java/lang/Integer.valueOf:(I)Ljava/lang/Integer;
      47: invokeinterface #64,  2           // InterfaceMethod java/util/Map.remove:(Ljava/lang/Object;)Ljava/lang/Object;
      52: pop
      53: return

  public void setParam(java.lang.String, org.apache.jena.graph.Node);
    Code:
       0: aload_1
       1: ifnonnull     14
       4: new           #65                 // class java/lang/IllegalArgumentException
       7: dup
       8: ldc           #66                 // String var cannot be null
      10: invokespecial #67                 // Method java/lang/IllegalArgumentException."<init>":(Ljava/lang/String;)V
      13: athrow
      14: aload_1
      15: ldc           #68                 // String ?
      17: invokevirtual #69                 // Method java/lang/String.startsWith:(Ljava/lang/String;)Z
      20: ifne          32
      23: aload_1
      24: ldc           #70                 // String $
      26: invokevirtual #69                 // Method java/lang/String.startsWith:(Ljava/lang/String;)Z
      29: ifeq          38
      32: aload_1
      33: iconst_1
      34: invokevirtual #71                 // Method java/lang/String.substring:(I)Ljava/lang/String;
      37: astore_1
      38: aload_2
      39: ifnull        62
      42: aload_0
      43: aload_2
      44: invokevirtual #61                 // Method validateParameterValue:(Lorg/apache/jena/graph/Node;)V
      47: aload_0
      48: getfield      #9                  // Field params:Ljava/util/Map;
      51: aload_1
      52: aload_2
      53: invokeinterface #63,  3           // InterfaceMethod java/util/Map.put:(Ljava/lang/Object;Ljava/lang/Object;)Ljava/lang/Object;
      58: pop
      59: goto          73
      62: aload_0
      63: getfield      #9                  // Field params:Ljava/util/Map;
      66: aload_1
      67: invokeinterface #64,  2           // InterfaceMethod java/util/Map.remove:(Ljava/lang/Object;)Ljava/lang/Object;
      72: pop
      73: return

  public void setParam(int, org.apache.jena.rdf.model.RDFNode);
    Code:
       0: aload_0
       1: iload_1
       2: aload_2
       3: invokeinterface #32,  1           // InterfaceMethod org/apache/jena/rdf/model/RDFNode.asNode:()Lorg/apache/jena/graph/Node;
       8: invokevirtual #72                 // Method setParam:(ILorg/apache/jena/graph/Node;)V
      11: return

  public void setParam(java.lang.String, org.apache.jena.rdf.model.RDFNode);
    Code:
       0: aload_0
       1: aload_1
       2: aload_2
       3: invokeinterface #32,  1           // InterfaceMethod org/apache/jena/rdf/model/RDFNode.asNode:()Lorg/apache/jena/graph/Node;
       8: invokevirtual #58                 // Method setParam:(Ljava/lang/String;Lorg/apache/jena/graph/Node;)V
      11: return

  public void setIri(int, java.lang.String);
    Code:
       0: aload_0
       1: iload_1
       2: aload_2
       3: invokestatic  #34                 // Method org/apache/jena/graph/NodeFactory.createURI:(Ljava/lang/String;)Lorg/apache/jena/graph/Node;
       6: invokevirtual #72                 // Method setParam:(ILorg/apache/jena/graph/Node;)V
       9: return

  public void setIri(java.lang.String, java.lang.String);
    Code:
       0: aload_0
       1: aload_1
       2: aload_2
       3: invokestatic  #34                 // Method org/apache/jena/graph/NodeFactory.createURI:(Ljava/lang/String;)Lorg/apache/jena/graph/Node;
       6: invokevirtual #58                 // Method setParam:(Ljava/lang/String;Lorg/apache/jena/graph/Node;)V
       9: return

  public void setIri(int, org.apache.jena.iri.IRI);
    Code:
       0: aload_0
       1: iload_1
       2: aload_2
       3: invokevirtual #35                 // Method org/apache/jena/iri/IRI.toString:()Ljava/lang/String;
       6: invokevirtual #73                 // Method setIri:(ILjava/lang/String;)V
       9: return

  public void setIri(java.lang.String, org.apache.jena.iri.IRI);
    Code:
       0: aload_0
       1: aload_1
       2: aload_2
       3: invokevirtual #35                 // Method org/apache/jena/iri/IRI.toString:()Ljava/lang/String;
       6: invokevirtual #74                 // Method setIri:(Ljava/lang/String;Ljava/lang/String;)V
       9: return

  public void setIri(int, java.net.URL);
    Code:
       0: aload_0
       1: iload_1
       2: aload_2
       3: invokevirtual #75                 // Method java/net/URL.toString:()Ljava/lang/String;
       6: invokevirtual #73                 // Method setIri:(ILjava/lang/String;)V
       9: return

  public void setIri(java.lang.String, java.net.URL);
    Code:
       0: aload_0
       1: aload_1
       2: aload_2
       3: invokevirtual #75                 // Method java/net/URL.toString:()Ljava/lang/String;
       6: invokevirtual #74                 // Method setIri:(Ljava/lang/String;Ljava/lang/String;)V
       9: return

  public void setLiteral(int, org.apache.jena.rdf.model.Literal);
    Code:
       0: aload_0
       1: iload_1
       2: aload_2
       3: invokeinterface #76,  1           // InterfaceMethod org/apache/jena/rdf/model/Literal.asNode:()Lorg/apache/jena/graph/Node;
       8: invokevirtual #72                 // Method setParam:(ILorg/apache/jena/graph/Node;)V
      11: return

  public void setLiteral(java.lang.String, org.apache.jena.rdf.model.Literal);
    Code:
       0: aload_0
       1: aload_1
       2: aload_2
       3: invokeinterface #76,  1           // InterfaceMethod org/apache/jena/rdf/model/Literal.asNode:()Lorg/apache/jena/graph/Node;
       8: invokevirtual #58                 // Method setParam:(Ljava/lang/String;Lorg/apache/jena/graph/Node;)V
      11: return

  public void setLiteral(int, java.lang.String);
    Code:
       0: aload_0
       1: iload_1
       2: aload_2
       3: aconst_null
       4: aconst_null
       5: invokestatic  #36                 // Method org/apache/jena/sparql/util/NodeFactoryExtra.createLiteralNode:(Ljava/lang/String;Ljava/lang/String;Ljava/lang/String;)Lorg/apache/jena/graph/Node;
       8: invokevirtual #72                 // Method setParam:(ILorg/apache/jena/graph/Node;)V
      11: return

  public void setLiteral(java.lang.String, java.lang.String);
    Code:
       0: aload_0
       1: aload_1
       2: aload_2
       3: aconst_null
       4: aconst_null
       5: invokestatic  #36                 // Method org/apache/jena/sparql/util/NodeFactoryExtra.createLiteralNode:(Ljava/lang/String;Ljava/lang/String;Ljava/lang/String;)Lorg/apache/jena/graph/Node;
       8: invokevirtual #58                 // Method setParam:(Ljava/lang/String;Lorg/apache/jena/graph/Node;)V
      11: return

  public void setLiteral(int, java.lang.String, java.lang.String);
    Code:
       0: aload_0
       1: iload_1
       2: aload_2
       3: aload_3
       4: aconst_null
       5: invokestatic  #36                 // Method org/apache/jena/sparql/util/NodeFactoryExtra.createLiteralNode:(Ljava/lang/String;Ljava/lang/String;Ljava/lang/String;)Lorg/apache/jena/graph/Node;
       8: invokevirtual #72                 // Method setParam:(ILorg/apache/jena/graph/Node;)V
      11: return

  public void setLiteral(java.lang.String, java.lang.String, java.lang.String);
    Code:
       0: aload_0
       1: aload_1
       2: aload_2
       3: aload_3
       4: aconst_null
       5: invokestatic  #36                 // Method org/apache/jena/sparql/util/NodeFactoryExtra.createLiteralNode:(Ljava/lang/String;Ljava/lang/String;Ljava/lang/String;)Lorg/apache/jena/graph/Node;
       8: invokevirtual #58                 // Method setParam:(Ljava/lang/String;Lorg/apache/jena/graph/Node;)V
      11: return

  public void setLiteral(int, java.lang.String, org.apache.jena.datatypes.RDFDatatype);
    Code:
       0: aload_0
       1: iload_1
       2: aload_0
       3: getfield      #3                  // Field model:Lorg/apache/jena/rdf/model/Model;
       6: aload_2
       7: aload_3
       8: invokeinterface #77,  3           // InterfaceMethod org/apache/jena/rdf/model/Model.createTypedLiteral:(Ljava/lang/String;Lorg/apache/jena/datatypes/RDFDatatype;)Lorg/apache/jena/rdf/model/Literal;
      13: invokevirtual #78                 // Method setParam:(ILorg/apache/jena/rdf/model/RDFNode;)V
      16: return

  public void setLiteral(java.lang.String, java.lang.String, org.apache.jena.datatypes.RDFDatatype);
    Code:
       0: aload_0
       1: aload_1
       2: aload_0
       3: getfield      #3                  // Field model:Lorg/apache/jena/rdf/model/Model;
       6: aload_2
       7: aload_3
       8: invokeinterface #77,  3           // InterfaceMethod org/apache/jena/rdf/model/Model.createTypedLiteral:(Ljava/lang/String;Lorg/apache/jena/datatypes/RDFDatatype;)Lorg/apache/jena/rdf/model/Literal;
      13: invokevirtual #79                 // Method setParam:(Ljava/lang/String;Lorg/apache/jena/rdf/model/RDFNode;)V
      16: return

  public void setLiteral(int, boolean);
    Code:
       0: aload_0
       1: iload_1
       2: aload_0
       3: getfield      #3                  // Field model:Lorg/apache/jena/rdf/model/Model;
       6: iload_2
       7: invokeinterface #38,  2           // InterfaceMethod org/apache/jena/rdf/model/Model.createTypedLiteral:(Z)Lorg/apache/jena/rdf/model/Literal;
      12: invokevirtual #78                 // Method setParam:(ILorg/apache/jena/rdf/model/RDFNode;)V
      15: return

  public void setLiteral(java.lang.String, boolean);
    Code:
       0: aload_0
       1: aload_1
       2: aload_0
       3: getfield      #3                  // Field model:Lorg/apache/jena/rdf/model/Model;
       6: iload_2
       7: invokeinterface #38,  2           // InterfaceMethod org/apache/jena/rdf/model/Model.createTypedLiteral:(Z)Lorg/apache/jena/rdf/model/Literal;
      12: invokevirtual #79                 // Method setParam:(Ljava/lang/String;Lorg/apache/jena/rdf/model/RDFNode;)V
      15: return

  public void setLiteral(int, int);
    Code:
       0: aload_0
       1: iload_1
       2: iload_2
       3: invokestatic  #40                 // Method org/apache/jena/sparql/util/NodeFactoryExtra.intToNode:(I)Lorg/apache/jena/graph/Node;
       6: invokevirtual #72                 // Method setParam:(ILorg/apache/jena/graph/Node;)V
       9: return

  public void setLiteral(java.lang.String, int);
    Code:
       0: aload_0
       1: aload_1
       2: iload_2
       3: invokestatic  #40                 // Method org/apache/jena/sparql/util/NodeFactoryExtra.intToNode:(I)Lorg/apache/jena/graph/Node;
       6: invokevirtual #58                 // Method setParam:(Ljava/lang/String;Lorg/apache/jena/graph/Node;)V
       9: return

  public void setLiteral(int, long);
    Code:
       0: aload_0
       1: iload_1
       2: lload_2
       3: invokestatic  #41                 // Method org/apache/jena/sparql/util/NodeFactoryExtra.intToNode:(J)Lorg/apache/jena/graph/Node;
       6: invokevirtual #72                 // Method setParam:(ILorg/apache/jena/graph/Node;)V
       9: return

  public void setLiteral(java.lang.String, long);
    Code:
       0: aload_0
       1: aload_1
       2: lload_2
       3: invokestatic  #41                 // Method org/apache/jena/sparql/util/NodeFactoryExtra.intToNode:(J)Lorg/apache/jena/graph/Node;
       6: invokevirtual #58                 // Method setParam:(Ljava/lang/String;Lorg/apache/jena/graph/Node;)V
       9: return

  public void setLiteral(int, float);
    Code:
       0: aload_0
       1: iload_1
       2: fload_2
       3: invokestatic  #80                 // Method org/apache/jena/sparql/util/NodeFactoryExtra.floatToNode:(F)Lorg/apache/jena/graph/Node;
       6: invokevirtual #72                 // Method setParam:(ILorg/apache/jena/graph/Node;)V
       9: return

  public void setLiteral(java.lang.String, float);
    Code:
       0: aload_0
       1: aload_1
       2: fload_2
       3: invokestatic  #80                 // Method org/apache/jena/sparql/util/NodeFactoryExtra.floatToNode:(F)Lorg/apache/jena/graph/Node;
       6: invokevirtual #58                 // Method setParam:(Ljava/lang/String;Lorg/apache/jena/graph/Node;)V
       9: return

  public void setLiteral(int, double);
    Code:
       0: aload_0
       1: iload_1
       2: aload_0
       3: getfield      #3                  // Field model:Lorg/apache/jena/rdf/model/Model;
       6: dload_2
       7: invokeinterface #43,  3           // InterfaceMethod org/apache/jena/rdf/model/Model.createTypedLiteral:(D)Lorg/apache/jena/rdf/model/Literal;
      12: invokevirtual #78                 // Method setParam:(ILorg/apache/jena/rdf/model/RDFNode;)V
      15: return

  public void setLiteral(java.lang.String, double);
    Code:
       0: aload_0
       1: aload_1
       2: aload_0
       3: getfield      #3                  // Field model:Lorg/apache/jena/rdf/model/Model;
       6: dload_2
       7: invokeinterface #43,  3           // InterfaceMethod org/apache/jena/rdf/model/Model.createTypedLiteral:(D)Lorg/apache/jena/rdf/model/Literal;
      12: invokevirtual #79                 // Method setParam:(Ljava/lang/String;Lorg/apache/jena/rdf/model/RDFNode;)V
      15: return

  public void setLiteral(int, java.util.Calendar);
    Code:
       0: aload_0
       1: iload_1
       2: aload_0
       3: getfield      #3                  // Field model:Lorg/apache/jena/rdf/model/Model;
       6: aload_2
       7: invokeinterface #44,  2           // InterfaceMethod org/apache/jena/rdf/model/Model.createTypedLiteral:(Ljava/util/Calendar;)Lorg/apache/jena/rdf/model/Literal;
      12: invokevirtual #78                 // Method setParam:(ILorg/apache/jena/rdf/model/RDFNode;)V
      15: return

  public void setLiteral(java.lang.String, java.util.Calendar);
    Code:
       0: aload_0
       1: aload_1
       2: aload_0
       3: getfield      #3                  // Field model:Lorg/apache/jena/rdf/model/Model;
       6: aload_2
       7: invokeinterface #44,  2           // InterfaceMethod org/apache/jena/rdf/model/Model.createTypedLiteral:(Ljava/util/Calendar;)Lorg/apache/jena/rdf/model/Literal;
      12: invokevirtual #79                 // Method setParam:(Ljava/lang/String;Lorg/apache/jena/rdf/model/RDFNode;)V
      15: return

  public org.apache.jena.graph.Node getParam(java.lang.String);
    Code:
       0: aload_0
       1: getfield      #9                  // Field params:Ljava/util/Map;
       4: aload_1
       5: invokeinterface #81,  2           // InterfaceMethod java/util/Map.get:(Ljava/lang/Object;)Ljava/lang/Object;
      10: checkcast     #82                 // class org/apache/jena/graph/Node
      13: areturn

  public org.apache.jena.graph.Node getParam(int);
    Code:
       0: aload_0
       1: getfield      #10                 // Field positionalParams:Ljava/util/Map;
       4: iload_1
       5: invokestatic  #62                 // Method java/lang/Integer.valueOf:(I)Ljava/lang/Integer;
       8: invokeinterface #81,  2           // InterfaceMethod java/util/Map.get:(Ljava/lang/Object;)Ljava/lang/Object;
      13: checkcast     #82                 // class org/apache/jena/graph/Node
      16: areturn

  public java.util.Iterator<java.lang.String> getVars();
    Code:
       0: aload_0
       1: getfield      #9                  // Field params:Ljava/util/Map;
       4: invokeinterface #83,  1           // InterfaceMethod java/util/Map.keySet:()Ljava/util/Set;
       9: invokeinterface #84,  1           // InterfaceMethod java/util/Set.iterator:()Ljava/util/Iterator;
      14: areturn

  public java.util.Map<java.lang.String, org.apache.jena.graph.Node> getVariableParameters();
    Code:
       0: aload_0
       1: getfield      #9                  // Field params:Ljava/util/Map;
       4: invokestatic  #85                 // Method java/util/Collections.unmodifiableMap:(Ljava/util/Map;)Ljava/util/Map;
       7: areturn

  public java.util.Map<java.lang.Integer, org.apache.jena.graph.Node> getPositionalParameters();
    Code:
       0: aload_0
       1: getfield      #10                 // Field positionalParams:Ljava/util/Map;
       4: invokestatic  #85                 // Method java/util/Collections.unmodifiableMap:(Ljava/util/Map;)Ljava/util/Map;
       7: areturn

  public java.util.Iterator<java.lang.Integer> getEligiblePositionalParameters();
    Code:
       0: ldc           #86                 // String (\\?)[\\s;,.]
       2: invokestatic  #87                 // Method java/util/regex/Pattern.compile:(Ljava/lang/String;)Ljava/util/regex/Pattern;
       5: astore_1
       6: new           #88                 // class java/util/ArrayList
       9: dup
      10: invokespecial #89                 // Method java/util/ArrayList."<init>":()V
      13: astore_2
      14: iconst_0
      15: istore_3
      16: aload_1
      17: aload_0
      18: getfield      #6                  // Field cmd:Ljava/lang/StringBuilder;
      21: invokevirtual #45                 // Method java/lang/StringBuilder.toString:()Ljava/lang/String;
      24: invokevirtual #90                 // Method java/util/regex/Pattern.matcher:(Ljava/lang/CharSequence;)Ljava/util/regex/Matcher;
      27: astore        4
      29: aload         4
      31: invokevirtual #91                 // Method java/util/regex/Matcher.find:()Z
      34: ifeq          54
      37: aload_2
      38: iload_3
      39: invokestatic  #62                 // Method java/lang/Integer.valueOf:(I)Ljava/lang/Integer;
      42: invokeinterface #92,  2           // InterfaceMethod java/util/List.add:(Ljava/lang/Object;)Z
      47: pop
      48: iinc          3, 1
      51: goto          29
      54: aload_2
      55: invokeinterface #93,  1           // InterfaceMethod java/util/List.iterator:()Ljava/util/Iterator;
      60: areturn

  public void clearParam(java.lang.String);
    Code:
       0: aload_0
       1: getfield      #9                  // Field params:Ljava/util/Map;
       4: aload_1
       5: invokeinterface #64,  2           // InterfaceMethod java/util/Map.remove:(Ljava/lang/Object;)Ljava/lang/Object;
      10: pop
      11: return

  public void clearParam(int);
    Code:
       0: aload_0
       1: getfield      #10                 // Field positionalParams:Ljava/util/Map;
       4: iload_1
       5: invokestatic  #62                 // Method java/lang/Integer.valueOf:(I)Ljava/lang/Integer;
       8: invokeinterface #64,  2           // InterfaceMethod java/util/Map.remove:(Ljava/lang/Object;)Ljava/lang/Object;
      13: pop
      14: return

  public void clearParams();
    Code:
       0: aload_0
       1: getfield      #9                  // Field params:Ljava/util/Map;
       4: invokeinterface #94,  1           // InterfaceMethod java/util/Map.clear:()V
       9: aload_0
      10: getfield      #10                 // Field positionalParams:Ljava/util/Map;
      13: invokeinterface #94,  1           // InterfaceMethod java/util/Map.clear:()V
      18: return

  protected void validateSafeToInject(java.lang.String, java.lang.String, org.apache.jena.graph.Node) throws org.apache.jena.sparql.ARQException;
    Code:
       0: new           #4                  // class java/lang/StringBuilder
       3: dup
       4: invokespecial #5                  // Method java/lang/StringBuilder."<init>":()V
       7: ldc           #95                 // String \"[?$]
       9: invokevirtual #11                 // Method java/lang/StringBuilder.append:(Ljava/lang/String;)Ljava/lang/StringBuilder;
      12: aload_2
      13: invokevirtual #11                 // Method java/lang/StringBuilder.append:(Ljava/lang/String;)Ljava/lang/StringBuilder;
      16: ldc           #96                 // String \"|\'[?$]
      18: invokevirtual #11                 // Method java/lang/StringBuilder.append:(Ljava/lang/String;)Ljava/lang/StringBuilder;
      21: aload_2
      22: invokevirtual #11                 // Method java/lang/StringBuilder.append:(Ljava/lang/String;)Ljava/lang/StringBuilder;
      25: ldc           #97                 // String \'
      27: invokevirtual #11                 // Method java/lang/StringBuilder.append:(Ljava/lang/String;)Ljava/lang/StringBuilder;
      30: invokevirtual #45                 // Method java/lang/StringBuilder.toString:()Ljava/lang/String;
      33: invokestatic  #87                 // Method java/util/regex/Pattern.compile:(Ljava/lang/String;)Ljava/util/regex/Pattern;
      36: astore        4
      38: aload         4
      40: aload_1
      41: invokevirtual #90                 // Method java/util/regex/Pattern.matcher:(Ljava/lang/CharSequence;)Ljava/util/regex/Matcher;
      44: invokevirtual #91                 // Method java/util/regex/Matcher.find:()Z
      47: ifeq          89
      50: aload_3
      51: invokevirtual #98                 // Method org/apache/jena/graph/Node.isLiteral:()Z
      54: ifeq          89
      57: new           #50                 // class org/apache/jena/sparql/ARQException
      60: dup
      61: new           #4                  // class java/lang/StringBuilder
      64: dup
      65: invokespecial #5                  // Method java/lang/StringBuilder."<init>":()V
      68: ldc           #99                 // String Command string is vunerable to injection attack, variable ?
      70: invokevirtual #11                 // Method java/lang/StringBuilder.append:(Ljava/lang/String;)Ljava/lang/StringBuilder;
      73: aload_2
      74: invokevirtual #11                 // Method java/lang/StringBuilder.append:(Ljava/lang/String;)Ljava/lang/StringBuilder;
      77: ldc           #100                // String  appears surrounded directly by quotes and is bound to a literal which provides a SPARQL injection attack vector
      79: invokevirtual #11                 // Method java/lang/StringBuilder.append:(Ljava/lang/String;)Ljava/lang/StringBuilder;
      82: invokevirtual #45                 // Method java/lang/StringBuilder.toString:()Ljava/lang/String;
      85: invokespecial #52                 // Method org/apache/jena/sparql/ARQException."<init>":(Ljava/lang/String;)V
      88: athrow
      89: aload_0
      90: aload_1
      91: invokevirtual #101                // Method findDelimiters:(Ljava/lang/String;)Lorg/apache/jena/query/ParameterizedSparqlString$DelimiterInfo;
      94: astore        5
      96: new           #4                  // class java/lang/StringBuilder
      99: dup
     100: invokespecial #5                  // Method java/lang/StringBuilder."<init>":()V
     103: ldc           #102                // String ([?$]
     105: invokevirtual #11                 // Method java/lang/StringBuilder.append:(Ljava/lang/String;)Ljava/lang/StringBuilder;
     108: aload_2
     109: invokevirtual #11                 // Method java/lang/StringBuilder.append:(Ljava/lang/String;)Ljava/lang/StringBuilder;
     112: ldc           #103                // String )([^\\w]|$)
     114: invokevirtual #11                 // Method java/lang/StringBuilder.append:(Ljava/lang/String;)Ljava/lang/StringBuilder;
     117: invokevirtual #45                 // Method java/lang/StringBuilder.toString:()Ljava/lang/String;
     120: invokestatic  #87                 // Method java/util/regex/Pattern.compile:(Ljava/lang/String;)Ljava/util/regex/Pattern;
     123: astore        4
     125: aload         4
     127: aload_1
     128: invokevirtual #90                 // Method java/util/regex/Pattern.matcher:(Ljava/lang/CharSequence;)Ljava/util/regex/Matcher;
     131: astore        6
     133: aload         6
     135: invokevirtual #91                 // Method java/util/regex/Matcher.find:()Z
     138: ifeq          214
     141: aload         6
     143: invokevirtual #104                // Method java/util/regex/Matcher.toMatchResult:()Ljava/util/regex/MatchResult;
     146: astore        7
     148: aload_3
     149: invokevirtual #98                 // Method org/apache/jena/graph/Node.isLiteral:()Z
     152: ifeq          211
     155: aload         5
     157: aload         7
     159: iconst_1
     160: invokeinterface #105,  2          // InterfaceMethod java/util/regex/MatchResult.start:(I)I
     165: aload         7
     167: iconst_1
     168: invokeinterface #106,  2          // InterfaceMethod java/util/regex/MatchResult.end:(I)I
     173: invokevirtual #107                // Method org/apache/jena/query/ParameterizedSparqlString$DelimiterInfo.isInsideLiteral:(II)Z
     176: ifeq          211
     179: new           #50                 // class org/apache/jena/sparql/ARQException
     182: dup
     183: new           #4                  // class java/lang/StringBuilder
     186: dup
     187: invokespecial #5                  // Method java/lang/StringBuilder."<init>":()V
     190: ldc           #99                 // String Command string is vunerable to injection attack, variable ?
     192: invokevirtual #11                 // Method java/lang/StringBuilder.append:(Ljava/lang/String;)Ljava/lang/StringBuilder;
     195: aload_2
     196: invokevirtual #11                 // Method java/lang/StringBuilder.append:(Ljava/lang/String;)Ljava/lang/StringBuilder;
     199: ldc           #108                // String  appears inside of a literal and is bound to a literal which provides a SPARQL injection attack vector
     201: invokevirtual #11                 // Method java/lang/StringBuilder.append:(Ljava/lang/String;)Ljava/lang/StringBuilder;
     204: invokevirtual #45                 // Method java/lang/StringBuilder.toString:()Ljava/lang/String;
     207: invokespecial #52                 // Method org/apache/jena/sparql/ARQException."<init>":(Ljava/lang/String;)V
     210: athrow
     211: goto          133
     214: return

  protected void validateSafeToInject(java.lang.String, int, int, org.apache.jena.graph.Node) throws org.apache.jena.sparql.ARQException;
    Code:
       0: aload_0
       1: aload_1
       2: invokevirtual #101                // Method findDelimiters:(Ljava/lang/String;)Lorg/apache/jena/query/ParameterizedSparqlString$DelimiterInfo;
       5: astore        5
       7: aload         4
       9: invokevirtual #98                 // Method org/apache/jena/graph/Node.isLiteral:()Z
      12: ifeq          57
      15: aload         5
      17: iload_3
      18: iload_3
      19: invokevirtual #107                // Method org/apache/jena/query/ParameterizedSparqlString$DelimiterInfo.isInsideLiteral:(II)Z
      22: ifeq          57
      25: new           #50                 // class org/apache/jena/sparql/ARQException
      28: dup
      29: new           #4                  // class java/lang/StringBuilder
      32: dup
      33: invokespecial #5                  // Method java/lang/StringBuilder."<init>":()V
      36: ldc           #109                // String Command string is vunerable to injection attack, a positional paramter (index
      38: invokevirtual #11                 // Method java/lang/StringBuilder.append:(Ljava/lang/String;)Ljava/lang/StringBuilder;
      41: iload_2
      42: invokevirtual #25                 // Method java/lang/StringBuilder.append:(I)Ljava/lang/StringBuilder;
      45: ldc           #110                // String ) appears inside of a literal and is bound to a literal which provides a SPARQL injection attack vector
      47: invokevirtual #11                 // Method java/lang/StringBuilder.append:(Ljava/lang/String;)Ljava/lang/StringBuilder;
      50: invokevirtual #45                 // Method java/lang/StringBuilder.toString:()Ljava/lang/String;
      53: invokespecial #52                 // Method org/apache/jena/sparql/ARQException."<init>":(Ljava/lang/String;)V
      56: athrow
      57: return

  protected final org.apache.jena.query.ParameterizedSparqlString$DelimiterInfo findDelimiters(java.lang.String);
    Code:
       0: new           #111                // class org/apache/jena/query/ParameterizedSparqlString$DelimiterInfo
       3: dup
       4: aload_0
       5: aconst_null
       6: invokespecial #112                // Method org/apache/jena/query/ParameterizedSparqlString$DelimiterInfo."<init>":(Lorg/apache/jena/query/ParameterizedSparqlString;Lorg/apache/jena/query/ParameterizedSparqlString$1;)V
       9: astore_2
      10: aload_2
      11: aload_1
      12: invokevirtual #113                // Method org/apache/jena/query/ParameterizedSparqlString$DelimiterInfo.parseFrom:(Ljava/lang/String;)V
      15: aload_2
      16: areturn

  protected final java.lang.String stringForNode(org.apache.jena.graph.Node, org.apache.jena.sparql.serializer.SerializationContext);
    Code:
       0: aload_1
       1: aload_2
       2: invokestatic  #114                // Method org/apache/jena/sparql/util/FmtUtils.stringForNode:(Lorg/apache/jena/graph/Node;Lorg/apache/jena/sparql/serializer/SerializationContext;)Ljava/lang/String;
       5: astore_3
       6: aload_1
       7: invokevirtual #98                 // Method org/apache/jena/graph/Node.isLiteral:()Z
      10: ifeq          31
      13: aload_3
      14: ldc           #97                 // String \'
      16: invokevirtual #49                 // Method java/lang/String.contains:(Ljava/lang/CharSequence;)Z
      19: ifeq          31
      22: aload_3
      23: ldc           #97                 // String \'
      25: ldc           #115                // String \\\'
      27: invokevirtual #116                // Method java/lang/String.replace:(Ljava/lang/CharSequence;Ljava/lang/CharSequence;)Ljava/lang/String;
      30: astore_3
      31: aload_3
      32: areturn

  public java.lang.String toString();
    Code:
       0: aload_0
       1: getfield      #6                  // Field cmd:Ljava/lang/StringBuilder;
       4: invokevirtual #45                 // Method java/lang/StringBuilder.toString:()Ljava/lang/String;
       7: astore_1
       8: new           #28                 // class org/apache/jena/sparql/serializer/SerializationContext
      11: dup
      12: aload_0
      13: getfield      #18                 // Field prefixes:Lorg/apache/jena/shared/PrefixMapping;
      16: invokespecial #29                 // Method org/apache/jena/sparql/serializer/SerializationContext."<init>":(Lorg/apache/jena/shared/PrefixMapping;)V
      19: astore_3
      20: aload_3
      21: aload_0
      22: getfield      #15                 // Field baseUri:Ljava/lang/String;
      25: invokevirtual #30                 // Method org/apache/jena/sparql/serializer/SerializationContext.setBaseIRI:(Ljava/lang/String;)V
      28: aload_0
      29: getfield      #9                  // Field params:Ljava/util/Map;
      32: invokeinterface #83,  1           // InterfaceMethod java/util/Map.keySet:()Ljava/util/Set;
      37: invokeinterface #84,  1           // InterfaceMethod java/util/Set.iterator:()Ljava/util/Iterator;
      42: astore        4
      44: aload         4
      46: invokeinterface #54,  1           // InterfaceMethod java/util/Iterator.hasNext:()Z
      51: ifeq          168
      54: aload         4
      56: invokeinterface #55,  1           // InterfaceMethod java/util/Iterator.next:()Ljava/lang/Object;
      61: checkcast     #56                 // class java/lang/String
      64: astore        5
      66: aload_0
      67: getfield      #9                  // Field params:Ljava/util/Map;
      70: aload         5
      72: invokeinterface #81,  2           // InterfaceMethod java/util/Map.get:(Ljava/lang/Object;)Ljava/lang/Object;
      77: checkcast     #82                 // class org/apache/jena/graph/Node
      80: astore        6
      82: aload         6
      84: ifnonnull     90
      87: goto          44
      90: aload_0
      91: aload_1
      92: aload         5
      94: aload         6
      96: invokevirtual #117                // Method validateSafeToInject:(Ljava/lang/String;Ljava/lang/String;Lorg/apache/jena/graph/Node;)V
      99: new           #4                  // class java/lang/StringBuilder
     102: dup
     103: invokespecial #5                  // Method java/lang/StringBuilder."<init>":()V
     106: ldc           #102                // String ([?$]
     108: invokevirtual #11                 // Method java/lang/StringBuilder.append:(Ljava/lang/String;)Ljava/lang/StringBuilder;
     111: aload         5
     113: invokevirtual #11                 // Method java/lang/StringBuilder.append:(Ljava/lang/String;)Ljava/lang/StringBuilder;
     116: ldc           #103                // String )([^\\w]|$)
     118: invokevirtual #11                 // Method java/lang/StringBuilder.append:(Ljava/lang/String;)Ljava/lang/StringBuilder;
     121: invokevirtual #45                 // Method java/lang/StringBuilder.toString:()Ljava/lang/String;
     124: invokestatic  #87                 // Method java/util/regex/Pattern.compile:(Ljava/lang/String;)Ljava/util/regex/Pattern;
     127: astore_2
     128: aload_2
     129: aload_1
     130: invokevirtual #90                 // Method java/util/regex/Pattern.matcher:(Ljava/lang/CharSequence;)Ljava/util/regex/Matcher;
     133: new           #4                  // class java/lang/StringBuilder
     136: dup
     137: invokespecial #5                  // Method java/lang/StringBuilder."<init>":()V
     140: aload_0
     141: aload         6
     143: aload_3
     144: invokevirtual #31                 // Method stringForNode:(Lorg/apache/jena/graph/Node;Lorg/apache/jena/sparql/serializer/SerializationContext;)Ljava/lang/String;
     147: invokestatic  #118                // Method java/util/regex/Matcher.quoteReplacement:(Ljava/lang/String;)Ljava/lang/String;
     150: invokevirtual #11                 // Method java/lang/StringBuilder.append:(Ljava/lang/String;)Ljava/lang/StringBuilder;
     153: ldc           #119                // String $2
     155: invokevirtual #11                 // Method java/lang/StringBuilder.append:(Ljava/lang/String;)Ljava/lang/StringBuilder;
     158: invokevirtual #45                 // Method java/lang/StringBuilder.toString:()Ljava/lang/String;
     161: invokevirtual #120                // Method java/util/regex/Matcher.replaceAll:(Ljava/lang/String;)Ljava/lang/String;
     164: astore_1
     165: goto          44
     168: ldc           #86                 // String (\\?)[\\s;,.]
     170: invokestatic  #87                 // Method java/util/regex/Pattern.compile:(Ljava/lang/String;)Ljava/util/regex/Pattern;
     173: astore_2
     174: iconst_m1
     175: istore        4
     177: iconst_0
     178: istore        5
     180: aload_2
     181: aload_1
     182: invokevirtual #90                 // Method java/util/regex/Pattern.matcher:(Ljava/lang/CharSequence;)Ljava/util/regex/Matcher;
     185: astore        6
     187: aload         6
     189: invokevirtual #91                 // Method java/util/regex/Matcher.find:()Z
     192: ifeq          329
     195: iinc          4, 1
     198: aload         6
     200: invokevirtual #104                // Method java/util/regex/Matcher.toMatchResult:()Ljava/util/regex/MatchResult;
     203: astore        7
     205: aload_0
     206: getfield      #10                 // Field positionalParams:Ljava/util/Map;
     209: iload         4
     211: invokestatic  #62                 // Method java/lang/Integer.valueOf:(I)Ljava/lang/Integer;
     214: invokeinterface #81,  2           // InterfaceMethod java/util/Map.get:(Ljava/lang/Object;)Ljava/lang/Object;
     219: checkcast     #82                 // class org/apache/jena/graph/Node
     222: astore        8
     224: aload         8
     226: ifnonnull     232
     229: goto          187
     232: aload_0
     233: aload_1
     234: iload         4
     236: aload         7
     238: iconst_1
     239: invokeinterface #105,  2          // InterfaceMethod java/util/regex/MatchResult.start:(I)I
     244: iload         5
     246: iadd
     247: aload         8
     249: invokevirtual #121                // Method validateSafeToInject:(Ljava/lang/String;IILorg/apache/jena/graph/Node;)V
     252: aload_0
     253: aload         8
     255: aload_3
     256: invokevirtual #31                 // Method stringForNode:(Lorg/apache/jena/graph/Node;Lorg/apache/jena/sparql/serializer/SerializationContext;)Ljava/lang/String;
     259: astore        9
     261: new           #4                  // class java/lang/StringBuilder
     264: dup
     265: invokespecial #5                  // Method java/lang/StringBuilder."<init>":()V
     268: aload_1
     269: iconst_0
     270: aload         7
     272: invokeinterface #122,  1          // InterfaceMethod java/util/regex/MatchResult.start:()I
     277: iload         5
     279: iadd
     280: invokevirtual #123                // Method java/lang/String.substring:(II)Ljava/lang/String;
     283: invokevirtual #11                 // Method java/lang/StringBuilder.append:(Ljava/lang/String;)Ljava/lang/StringBuilder;
     286: aload         9
     288: invokevirtual #11                 // Method java/lang/StringBuilder.append:(Ljava/lang/String;)Ljava/lang/StringBuilder;
     291: aload_1
     292: aload         7
     294: invokeinterface #122,  1          // InterfaceMethod java/util/regex/MatchResult.start:()I
     299: iload         5
     301: iadd
     302: iconst_1
     303: iadd
     304: invokevirtual #71                 // Method java/lang/String.substring:(I)Ljava/lang/String;
     307: invokevirtual #11                 // Method java/lang/StringBuilder.append:(Ljava/lang/String;)Ljava/lang/StringBuilder;
     310: invokevirtual #45                 // Method java/lang/StringBuilder.toString:()Ljava/lang/String;
     313: astore_1
     314: iload         5
     316: aload         9
     318: invokevirtual #124                // Method java/lang/String.length:()I
     321: iconst_1
     322: isub
     323: iadd
     324: istore        5
     326: goto          187
     329: new           #4                  // class java/lang/StringBuilder
     332: dup
     333: invokespecial #5                  // Method java/lang/StringBuilder."<init>":()V
     336: astore        7
     338: aload_0
     339: getfield      #15                 // Field baseUri:Ljava/lang/String;
     342: ifnull        376
     345: aload         7
     347: ldc           #125                // String BASE
     349: invokevirtual #11                 // Method java/lang/StringBuilder.append:(Ljava/lang/String;)Ljava/lang/StringBuilder;
     352: pop
     353: aload         7
     355: aload_0
     356: getfield      #15                 // Field baseUri:Ljava/lang/String;
     359: aconst_null
     360: aconst_null
     361: invokestatic  #126                // Method org/apache/jena/sparql/util/FmtUtils.stringForURI:(Ljava/lang/String;Ljava/lang/String;Lorg/apache/jena/shared/PrefixMapping;)Ljava/lang/String;
     364: invokevirtual #11                 // Method java/lang/StringBuilder.append:(Ljava/lang/String;)Ljava/lang/StringBuilder;
     367: pop
     368: aload         7
     370: bipush        10
     372: invokevirtual #21                 // Method java/lang/StringBuilder.append:(C)Ljava/lang/StringBuilder;
     375: pop
     376: aload_0
     377: getfield      #18                 // Field prefixes:Lorg/apache/jena/shared/PrefixMapping;
     380: invokeinterface #127,  1          // InterfaceMethod org/apache/jena/shared/PrefixMapping.getNsPrefixMap:()Ljava/util/Map;
     385: invokeinterface #83,  1           // InterfaceMethod java/util/Map.keySet:()Ljava/util/Set;
     390: invokeinterface #84,  1           // InterfaceMethod java/util/Set.iterator:()Ljava/util/Iterator;
     395: astore        8
     397: aload         8
     399: invokeinterface #54,  1           // InterfaceMethod java/util/Iterator.hasNext:()Z
     404: ifeq          476
     407: aload         8
     409: invokeinterface #55,  1           // InterfaceMethod java/util/Iterator.next:()Ljava/lang/Object;
     414: checkcast     #56                 // class java/lang/String
     417: astore        9
     419: aload         7
     421: ldc           #128                // String PREFIX
     423: invokevirtual #11                 // Method java/lang/StringBuilder.append:(Ljava/lang/String;)Ljava/lang/StringBuilder;
     426: pop
     427: aload         7
     429: aload         9
     431: invokevirtual #11                 // Method java/lang/StringBuilder.append:(Ljava/lang/String;)Ljava/lang/StringBuilder;
     434: pop
     435: aload         7
     437: ldc           #129                // String :
     439: invokevirtual #11                 // Method java/lang/StringBuilder.append:(Ljava/lang/String;)Ljava/lang/StringBuilder;
     442: pop
     443: aload         7
     445: aload_0
     446: getfield      #18                 // Field prefixes:Lorg/apache/jena/shared/PrefixMapping;
     449: aload         9
     451: invokeinterface #130,  2          // InterfaceMethod org/apache/jena/shared/PrefixMapping.getNsPrefixURI:(Ljava/lang/String;)Ljava/lang/String;
     456: aconst_null
     457: aconst_null
     458: invokestatic  #126                // Method org/apache/jena/sparql/util/FmtUtils.stringForURI:(Ljava/lang/String;Ljava/lang/String;Lorg/apache/jena/shared/PrefixMapping;)Ljava/lang/String;
     461: invokevirtual #11                 // Method java/lang/StringBuilder.append:(Ljava/lang/String;)Ljava/lang/StringBuilder;
     464: pop
     465: aload         7
     467: bipush        10
     469: invokevirtual #21                 // Method java/lang/StringBuilder.append:(C)Ljava/lang/StringBuilder;
     472: pop
     473: goto          397
     476: aload         7
     478: aload_1
     479: invokevirtual #11                 // Method java/lang/StringBuilder.append:(Ljava/lang/String;)Ljava/lang/StringBuilder;
     482: pop
     483: aload         7
     485: invokevirtual #45                 // Method java/lang/StringBuilder.toString:()Ljava/lang/String;
     488: areturn

  public org.apache.jena.query.Query asQuery() throws org.apache.jena.query.QueryException;
    Code:
       0: aload_0
       1: invokevirtual #131                // Method toString:()Ljava/lang/String;
       4: invokestatic  #132                // Method org/apache/jena/query/QueryFactory.create:(Ljava/lang/String;)Lorg/apache/jena/query/Query;
       7: areturn

  public org.apache.jena.update.UpdateRequest asUpdate();
    Code:
       0: aload_0
       1: invokevirtual #131                // Method toString:()Ljava/lang/String;
       4: invokestatic  #133                // Method org/apache/jena/update/UpdateFactory.create:(Ljava/lang/String;)Lorg/apache/jena/update/UpdateRequest;
       7: areturn

  public org.apache.jena.query.ParameterizedSparqlString copy();
    Code:
       0: aload_0
       1: iconst_1
       2: iconst_1
       3: iconst_1
       4: invokevirtual #134                // Method copy:(ZZZ)Lorg/apache/jena/query/ParameterizedSparqlString;
       7: areturn

  public org.apache.jena.query.ParameterizedSparqlString copy(boolean);
    Code:
       0: aload_0
       1: iload_1
       2: iconst_1
       3: iconst_1
       4: invokevirtual #134                // Method copy:(ZZZ)Lorg/apache/jena/query/ParameterizedSparqlString;
       7: areturn

  public org.apache.jena.query.ParameterizedSparqlString copy(boolean, boolean, boolean);
    Code:
       0: new           #135                // class org/apache/jena/query/ParameterizedSparqlString
       3: dup
       4: aload_0
       5: getfield      #6                  // Field cmd:Ljava/lang/StringBuilder;
       8: invokevirtual #45                 // Method java/lang/StringBuilder.toString:()Ljava/lang/String;
      11: aconst_null
      12: iload_2
      13: ifeq          23
      16: aload_0
      17: getfield      #15                 // Field baseUri:Ljava/lang/String;
      20: goto          24
      23: aconst_null
      24: iload_3
      25: ifeq          35
      28: aload_0
      29: getfield      #18                 // Field prefixes:Lorg/apache/jena/shared/PrefixMapping;
      32: goto          36
      35: aconst_null
      36: invokespecial #20                 // Method "<init>":(Ljava/lang/String;Lorg/apache/jena/query/QuerySolutionMap;Ljava/lang/String;Lorg/apache/jena/shared/PrefixMapping;)V
      39: astore        4
      41: iload_1
      42: ifeq          158
      45: aload_0
      46: invokevirtual #136                // Method getVars:()Ljava/util/Iterator;
      49: astore        5
      51: aload         5
      53: invokeinterface #54,  1           // InterfaceMethod java/util/Iterator.hasNext:()Z
      58: ifeq          89
      61: aload         5
      63: invokeinterface #55,  1           // InterfaceMethod java/util/Iterator.next:()Ljava/lang/Object;
      68: checkcast     #56                 // class java/lang/String
      71: astore        6
      73: aload         4
      75: aload         6
      77: aload_0
      78: aload         6
      80: invokevirtual #137                // Method getParam:(Ljava/lang/String;)Lorg/apache/jena/graph/Node;
      83: invokevirtual #58                 // Method setParam:(Ljava/lang/String;Lorg/apache/jena/graph/Node;)V
      86: goto          51
      89: aload_0
      90: getfield      #10                 // Field positionalParams:Ljava/util/Map;
      93: invokeinterface #138,  1          // InterfaceMethod java/util/Map.entrySet:()Ljava/util/Set;
      98: invokeinterface #84,  1           // InterfaceMethod java/util/Set.iterator:()Ljava/util/Iterator;
     103: astore        6
     105: aload         6
     107: invokeinterface #54,  1           // InterfaceMethod java/util/Iterator.hasNext:()Z
     112: ifeq          158
     115: aload         6
     117: invokeinterface #55,  1           // InterfaceMethod java/util/Iterator.next:()Ljava/lang/Object;
     122: checkcast     #139                // class java/util/Map$Entry
     125: astore        7
     127: aload         4
     129: aload         7
     131: invokeinterface #140,  1          // InterfaceMethod java/util/Map$Entry.getKey:()Ljava/lang/Object;
     136: checkcast     #141                // class java/lang/Integer
     139: invokevirtual #142                // Method java/lang/Integer.intValue:()I
     142: aload         7
     144: invokeinterface #143,  1          // InterfaceMethod java/util/Map$Entry.getValue:()Ljava/lang/Object;
     149: checkcast     #82                 // class org/apache/jena/graph/Node
     152: invokevirtual #72                 // Method setParam:(ILorg/apache/jena/graph/Node;)V
     155: goto          105
     158: aload         4
     160: areturn

  public org.apache.jena.shared.PrefixMapping setNsPrefix(java.lang.String, java.lang.String);
    Code:
       0: aload_0
       1: getfield      #18                 // Field prefixes:Lorg/apache/jena/shared/PrefixMapping;
       4: aload_1
       5: aload_2
       6: invokeinterface #144,  3          // InterfaceMethod org/apache/jena/shared/PrefixMapping.setNsPrefix:(Ljava/lang/String;Ljava/lang/String;)Lorg/apache/jena/shared/PrefixMapping;
      11: areturn

  public org.apache.jena.shared.PrefixMapping removeNsPrefix(java.lang.String);
    Code:
       0: aload_0
       1: getfield      #18                 // Field prefixes:Lorg/apache/jena/shared/PrefixMapping;
       4: aload_1
       5: invokeinterface #145,  2          // InterfaceMethod org/apache/jena/shared/PrefixMapping.removeNsPrefix:(Ljava/lang/String;)Lorg/apache/jena/shared/PrefixMapping;
      10: areturn

  public org.apache.jena.shared.PrefixMapping clearNsPrefixMap();
    Code:
       0: aload_0
       1: getfield      #18                 // Field prefixes:Lorg/apache/jena/shared/PrefixMapping;
       4: invokeinterface #146,  1          // InterfaceMethod org/apache/jena/shared/PrefixMapping.clearNsPrefixMap:()Lorg/apache/jena/shared/PrefixMapping;
       9: areturn

  public org.apache.jena.shared.PrefixMapping setNsPrefixes(org.apache.jena.shared.PrefixMapping);
    Code:
       0: aload_0
       1: getfield      #18                 // Field prefixes:Lorg/apache/jena/shared/PrefixMapping;
       4: aload_1
       5: invokeinterface #19,  2           // InterfaceMethod org/apache/jena/shared/PrefixMapping.setNsPrefixes:(Lorg/apache/jena/shared/PrefixMapping;)Lorg/apache/jena/shared/PrefixMapping;
      10: areturn

  public org.apache.jena.shared.PrefixMapping setNsPrefixes(java.util.Map<java.lang.String, java.lang.String>);
    Code:
       0: aload_0
       1: getfield      #18                 // Field prefixes:Lorg/apache/jena/shared/PrefixMapping;
       4: aload_1
       5: invokeinterface #147,  2          // InterfaceMethod org/apache/jena/shared/PrefixMapping.setNsPrefixes:(Ljava/util/Map;)Lorg/apache/jena/shared/PrefixMapping;
      10: areturn

  public org.apache.jena.shared.PrefixMapping withDefaultMappings(org.apache.jena.shared.PrefixMapping);
    Code:
       0: aload_0
       1: getfield      #18                 // Field prefixes:Lorg/apache/jena/shared/PrefixMapping;
       4: aload_1
       5: invokeinterface #148,  2          // InterfaceMethod org/apache/jena/shared/PrefixMapping.withDefaultMappings:(Lorg/apache/jena/shared/PrefixMapping;)Lorg/apache/jena/shared/PrefixMapping;
      10: areturn

  public java.lang.String getNsPrefixURI(java.lang.String);
    Code:
       0: aload_0
       1: getfield      #18                 // Field prefixes:Lorg/apache/jena/shared/PrefixMapping;
       4: aload_1
       5: invokeinterface #130,  2          // InterfaceMethod org/apache/jena/shared/PrefixMapping.getNsPrefixURI:(Ljava/lang/String;)Ljava/lang/String;
      10: areturn

  public java.lang.String getNsURIPrefix(java.lang.String);
    Code:
       0: aload_0
       1: getfield      #18                 // Field prefixes:Lorg/apache/jena/shared/PrefixMapping;
       4: aload_1
       5: invokeinterface #149,  2          // InterfaceMethod org/apache/jena/shared/PrefixMapping.getNsURIPrefix:(Ljava/lang/String;)Ljava/lang/String;
      10: areturn

  public java.util.Map<java.lang.String, java.lang.String> getNsPrefixMap();
    Code:
       0: aload_0
       1: getfield      #18                 // Field prefixes:Lorg/apache/jena/shared/PrefixMapping;
       4: invokeinterface #127,  1          // InterfaceMethod org/apache/jena/shared/PrefixMapping.getNsPrefixMap:()Ljava/util/Map;
       9: areturn

  public java.lang.String expandPrefix(java.lang.String);
    Code:
       0: aload_0
       1: getfield      #18                 // Field prefixes:Lorg/apache/jena/shared/PrefixMapping;
       4: aload_1
       5: invokeinterface #150,  2          // InterfaceMethod org/apache/jena/shared/PrefixMapping.expandPrefix:(Ljava/lang/String;)Ljava/lang/String;
      10: areturn

  public java.lang.String shortForm(java.lang.String);
    Code:
       0: aload_0
       1: getfield      #18                 // Field prefixes:Lorg/apache/jena/shared/PrefixMapping;
       4: aload_1
       5: invokeinterface #151,  2          // InterfaceMethod org/apache/jena/shared/PrefixMapping.shortForm:(Ljava/lang/String;)Ljava/lang/String;
      10: areturn

  public java.lang.String qnameFor(java.lang.String);
    Code:
       0: aload_0
       1: getfield      #18                 // Field prefixes:Lorg/apache/jena/shared/PrefixMapping;
       4: aload_1
       5: invokeinterface #152,  2          // InterfaceMethod org/apache/jena/shared/PrefixMapping.qnameFor:(Ljava/lang/String;)Ljava/lang/String;
      10: areturn

  public boolean hasNoMappings();
    Code:
       0: aload_0
       1: getfield      #18                 // Field prefixes:Lorg/apache/jena/shared/PrefixMapping;
       4: invokeinterface #153,  1          // InterfaceMethod org/apache/jena/shared/PrefixMapping.hasNoMappings:()Z
       9: ireturn

  public int numPrefixes();
    Code:
       0: aload_0
       1: getfield      #18                 // Field prefixes:Lorg/apache/jena/shared/PrefixMapping;
       4: invokeinterface #154,  1          // InterfaceMethod org/apache/jena/shared/PrefixMapping.numPrefixes:()I
       9: ireturn

  public org.apache.jena.shared.PrefixMapping lock();
    Code:
       0: aload_0
       1: getfield      #18                 // Field prefixes:Lorg/apache/jena/shared/PrefixMapping;
       4: invokeinterface #155,  1          // InterfaceMethod org/apache/jena/shared/PrefixMapping.lock:()Lorg/apache/jena/shared/PrefixMapping;
       9: areturn

  public boolean samePrefixMappingAs(org.apache.jena.shared.PrefixMapping);
    Code:
       0: aload_0
       1: getfield      #18                 // Field prefixes:Lorg/apache/jena/shared/PrefixMapping;
       4: aload_1
       5: invokeinterface #156,  2          // InterfaceMethod org/apache/jena/shared/PrefixMapping.samePrefixMappingAs:(Lorg/apache/jena/shared/PrefixMapping;)Z
      10: ireturn
}
