Compiled from "QueryFactory.java"
public class org.apache.jena.query.QueryFactory {
  public org.apache.jena.query.QueryFactory();
    Code:
       0: aload_0
       1: invokespecial #1                  // Method java/lang/Object."<init>":()V
       4: return

  public static org.apache.jena.query.Query create(java.lang.String);
    Code:
       0: aload_0
       1: getstatic     #2                  // Field org/apache/jena/query/Syntax.defaultQuerySyntax:Lorg/apache/jena/query/Syntax;
       4: invokestatic  #3                  // Method create:(Ljava/lang/String;Lorg/apache/jena/query/Syntax;)Lorg/apache/jena/query/Query;
       7: areturn

  public static org.apache.jena.query.Query create(java.lang.String, org.apache.jena.query.Syntax);
    Code:
       0: aload_0
       1: aconst_null
       2: aload_1
       3: invokestatic  #4                  // Method create:(Ljava/lang/String;Ljava/lang/String;Lorg/apache/jena/query/Syntax;)Lorg/apache/jena/query/Query;
       6: areturn

  public static org.apache.jena.query.Query create(java.lang.String, java.lang.String);
    Code:
       0: new           #5                  // class org/apache/jena/query/Query
       3: dup
       4: invokespecial #6                  // Method org/apache/jena/query/Query."<init>":()V
       7: astore_2
       8: aload_2
       9: aload_0
      10: aload_1
      11: getstatic     #2                  // Field org/apache/jena/query/Syntax.defaultQuerySyntax:Lorg/apache/jena/query/Syntax;
      14: invokestatic  #7                  // Method parse:(Lorg/apache/jena/query/Query;Ljava/lang/String;Ljava/lang/String;Lorg/apache/jena/query/Syntax;)Lorg/apache/jena/query/Query;
      17: areturn

  public static org.apache.jena.query.Query create(java.lang.String, java.lang.String, org.apache.jena.query.Syntax);
    Code:
       0: new           #5                  // class org/apache/jena/query/Query
       3: dup
       4: invokespecial #6                  // Method org/apache/jena/query/Query."<init>":()V
       7: astore_3
       8: aload_3
       9: aload_0
      10: aload_1
      11: aload_2
      12: invokestatic  #7                  // Method parse:(Lorg/apache/jena/query/Query;Ljava/lang/String;Ljava/lang/String;Lorg/apache/jena/query/Syntax;)Lorg/apache/jena/query/Query;
      15: areturn

  public static org.apache.jena.query.Query create();
    Code:
       0: new           #5                  // class org/apache/jena/query/Query
       3: dup
       4: invokespecial #6                  // Method org/apache/jena/query/Query."<init>":()V
       7: areturn

  public static org.apache.jena.query.Query make();
    Code:
       0: invokestatic  #8                  // Method create:()Lorg/apache/jena/query/Query;
       3: areturn

  public static org.apache.jena.query.Query create(org.apache.jena.query.Query);
    Code:
       0: aload_0
       1: invokevirtual #9                  // Method org/apache/jena/query/Query.cloneQuery:()Lorg/apache/jena/query/Query;
       4: areturn

  public static org.apache.jena.query.Query parse(org.apache.jena.query.Query, java.lang.String, java.lang.String, org.apache.jena.query.Syntax);
    Code:
       0: aload_3
       1: ifnonnull     12
       4: aload_0
       5: invokevirtual #10                 // Method org/apache/jena/query/Query.getSyntax:()Lorg/apache/jena/query/Syntax;
       8: astore_3
       9: goto          17
      12: aload_0
      13: aload_3
      14: invokevirtual #11                 // Method org/apache/jena/query/Query.setSyntax:(Lorg/apache/jena/query/Syntax;)V
      17: aload_3
      18: invokestatic  #12                 // Method org/apache/jena/sparql/lang/SPARQLParser.createParser:(Lorg/apache/jena/query/Syntax;)Lorg/apache/jena/sparql/lang/SPARQLParser;
      21: astore        4
      23: aload         4
      25: ifnonnull     55
      28: new           #13                 // class java/lang/UnsupportedOperationException
      31: dup
      32: new           #14                 // class java/lang/StringBuilder
      35: dup
      36: invokespecial #15                 // Method java/lang/StringBuilder."<init>":()V
      39: ldc           #16                 // String Unrecognized syntax for parsing:
      41: invokevirtual #17                 // Method java/lang/StringBuilder.append:(Ljava/lang/String;)Ljava/lang/StringBuilder;
      44: aload_3
      45: invokevirtual #18                 // Method java/lang/StringBuilder.append:(Ljava/lang/Object;)Ljava/lang/StringBuilder;
      48: invokevirtual #19                 // Method java/lang/StringBuilder.toString:()Ljava/lang/String;
      51: invokespecial #20                 // Method java/lang/UnsupportedOperationException."<init>":(Ljava/lang/String;)V
      54: athrow
      55: aload_0
      56: invokevirtual #21                 // Method org/apache/jena/query/Query.getResolver:()Lorg/apache/jena/riot/system/IRIResolver;
      59: ifnonnull     106
      62: aconst_null
      63: astore        5
      65: aload_2
      66: ifnull        78
      69: aload_2
      70: invokestatic  #22                 // Method org/apache/jena/riot/system/IRIResolver.create:(Ljava/lang/String;)Lorg/apache/jena/riot/system/IRIResolver;
      73: astore        5
      75: goto          83
      78: invokestatic  #23                 // Method org/apache/jena/riot/system/IRIResolver.create:()Lorg/apache/jena/riot/system/IRIResolver;
      81: astore        5
      83: goto          88
      86: astore        6
      88: aload         5
      90: ifnonnull     100
      93: ldc           #25                 // String http://localhost/query/defaultBase#
      95: invokestatic  #22                 // Method org/apache/jena/riot/system/IRIResolver.create:(Ljava/lang/String;)Lorg/apache/jena/riot/system/IRIResolver;
      98: astore        5
     100: aload_0
     101: aload         5
     103: invokevirtual #26                 // Method org/apache/jena/query/Query.setResolver:(Lorg/apache/jena/riot/system/IRIResolver;)V
     106: aload         4
     108: aload_0
     109: aload_1
     110: invokevirtual #27                 // Method org/apache/jena/sparql/lang/SPARQLParser.parse:(Lorg/apache/jena/query/Query;Ljava/lang/String;)Lorg/apache/jena/query/Query;
     113: areturn
    Exception table:
       from    to  target type
          65    83    86   Class java/lang/Exception

  static boolean knownParserSyntax(org.apache.jena.query.Syntax);
    Code:
       0: invokestatic  #28                 // Method org/apache/jena/sparql/lang/SPARQLParserRegistry.get:()Lorg/apache/jena/sparql/lang/SPARQLParserRegistry;
       3: aload_0
       4: invokevirtual #29                 // Method org/apache/jena/sparql/lang/SPARQLParserRegistry.containsFactory:(Lorg/apache/jena/query/Syntax;)Z
       7: ireturn

  public static org.apache.jena.query.Query read(java.lang.String);
    Code:
       0: aload_0
       1: aconst_null
       2: aconst_null
       3: aconst_null
       4: invokestatic  #30                 // Method read:(Ljava/lang/String;Lorg/apache/jena/util/FileManager;Ljava/lang/String;Lorg/apache/jena/query/Syntax;)Lorg/apache/jena/query/Query;
       7: areturn

  public static org.apache.jena.query.Query read(java.lang.String, java.lang.String);
    Code:
       0: aload_0
       1: aconst_null
       2: aload_1
       3: aconst_null
       4: invokestatic  #30                 // Method read:(Ljava/lang/String;Lorg/apache/jena/util/FileManager;Ljava/lang/String;Lorg/apache/jena/query/Syntax;)Lorg/apache/jena/query/Query;
       7: areturn

  public static org.apache.jena.query.Query read(java.lang.String, org.apache.jena.query.Syntax);
    Code:
       0: aload_0
       1: aconst_null
       2: aconst_null
       3: aload_1
       4: invokestatic  #30                 // Method read:(Ljava/lang/String;Lorg/apache/jena/util/FileManager;Ljava/lang/String;Lorg/apache/jena/query/Syntax;)Lorg/apache/jena/query/Query;
       7: areturn

  public static org.apache.jena.query.Query read(java.lang.String, java.lang.String, org.apache.jena.query.Syntax);
    Code:
       0: aload_0
       1: aconst_null
       2: aload_1
       3: aload_2
       4: invokestatic  #30                 // Method read:(Ljava/lang/String;Lorg/apache/jena/util/FileManager;Ljava/lang/String;Lorg/apache/jena/query/Syntax;)Lorg/apache/jena/query/Query;
       7: areturn

  public static org.apache.jena.query.Query read(java.lang.String, org.apache.jena.util.FileManager, java.lang.String, org.apache.jena.query.Syntax);
    Code:
       0: aload_1
       1: ifnonnull     8
       4: invokestatic  #31                 // Method org/apache/jena/util/FileManager.get:()Lorg/apache/jena/util/FileManager;
       7: astore_1
       8: aload_1
       9: aload_0
      10: invokevirtual #32                 // Method org/apache/jena/util/FileManager.readWholeFileAsUTF8:(Ljava/lang/String;)Ljava/lang/String;
      13: astore        4
      15: aload_2
      16: ifnonnull     21
      19: aload_0
      20: astore_2
      21: aload_3
      22: ifnonnull     30
      25: aload_0
      26: invokestatic  #33                 // Method org/apache/jena/query/Syntax.guessFileSyntax:(Ljava/lang/String;)Lorg/apache/jena/query/Syntax;
      29: astore_3
      30: aload         4
      32: aload_2
      33: aload_3
      34: invokestatic  #4                  // Method create:(Ljava/lang/String;Ljava/lang/String;Lorg/apache/jena/query/Syntax;)Lorg/apache/jena/query/Query;
      37: areturn

  public static org.apache.jena.sparql.syntax.Element createElement(java.lang.String);
    Code:
       0: aload_0
       1: invokestatic  #34                 // Method org/apache/jena/sparql/lang/ParserARQ.parseElement:(Ljava/lang/String;)Lorg/apache/jena/sparql/syntax/Element;
       4: areturn

  public static org.apache.jena.sparql.syntax.Template createTemplate(java.lang.String);
    Code:
       0: aload_0
       1: invokestatic  #35                 // Method org/apache/jena/sparql/lang/ParserARQ.parseTemplate:(Ljava/lang/String;)Lorg/apache/jena/sparql/syntax/Template;
       4: areturn
}
