Compiled from "JettyFactory.java"
class io.micronaut.servlet.jetty.JettyFactory$2 extends org.eclipse.jetty.servlet.ServletContextHandler {
  final org.eclipse.jetty.util.resource.ResourceCollection val$resourceCollection;

  final io.micronaut.servlet.jetty.JettyFactory this$0;

  io.micronaut.servlet.jetty.JettyFactory$2(io.micronaut.servlet.jetty.JettyFactory, org.eclipse.jetty.server.HandlerContainer, java.lang.String, boolean, boolean, org.eclipse.jetty.util.resource.ResourceCollection);
    Code:
       0: aload_0
       1: aload_1
       2: putfield      #3                  // Field this$0:Lio/micronaut/servlet/jetty/JettyFactory;
       5: aload_0
       6: aload         6
       8: putfield      #9                  // Field val$resourceCollection:Lorg/eclipse/jetty/util/resource/ResourceCollection;
      11: aload_0
      12: aload_2
      13: aload_3
      14: iload         4
      16: iload         5
      18: invokespecial #13                 // Method org/eclipse/jetty/servlet/ServletContextHandler."<init>":(Lorg/eclipse/jetty/server/HandlerContainer;Ljava/lang/String;ZZ)V
      21: return

  public org.eclipse.jetty.util.resource.Resource newResource(java.lang.String) throws java.io.IOException;
    Code:
       0: aload_0
       1: getfield      #9                  // Field val$resourceCollection:Lorg/eclipse/jetty/util/resource/ResourceCollection;
       4: ifnull        21
       7: ldc           #19                 // String resourceBase
       9: aload_1
      10: invokevirtual #21                 // Method java/lang/String.endsWith:(Ljava/lang/String;)Z
      13: ifeq          21
      16: aload_0
      17: getfield      #9                  // Field val$resourceCollection:Lorg/eclipse/jetty/util/resource/ResourceCollection;
      20: areturn
      21: aload_0
      22: aload_1
      23: invokespecial #27                 // Method org/eclipse/jetty/servlet/ServletContextHandler.newResource:(Ljava/lang/String;)Lorg/eclipse/jetty/util/resource/Resource;
      26: areturn
}
