Compiled from "JmsTemplate.java"
class org.springframework.jms.core.JmsTemplate$4 implements org.springframework.jms.core.SessionCallback<java.lang.Object> {
  final java.lang.String val$destinationName;

  final org.springframework.jms.core.MessageCreator val$messageCreator;

  final org.springframework.jms.core.JmsTemplate this$0;

  org.springframework.jms.core.JmsTemplate$4(org.springframework.jms.core.JmsTemplate, java.lang.String, org.springframework.jms.core.MessageCreator);
    Code:
       0: aload_0
       1: aload_1
       2: putfield      #1                  // Field this$0:Lorg/springframework/jms/core/JmsTemplate;
       5: aload_0
       6: aload_2
       7: putfield      #2                  // Field val$destinationName:Ljava/lang/String;
      10: aload_0
      11: aload_3
      12: putfield      #3                  // Field val$messageCreator:Lorg/springframework/jms/core/MessageCreator;
      15: aload_0
      16: invokespecial #4                  // Method java/lang/Object."<init>":()V
      19: return

  public java.lang.Object doInJms(javax.jms.Session) throws javax.jms.JMSException;
    Code:
       0: aload_0
       1: getfield      #1                  // Field this$0:Lorg/springframework/jms/core/JmsTemplate;
       4: aload_1
       5: aload_0
       6: getfield      #2                  // Field val$destinationName:Ljava/lang/String;
       9: invokestatic  #5                  // Method org/springframework/jms/core/JmsTemplate.access$200:(Lorg/springframework/jms/core/JmsTemplate;Ljavax/jms/Session;Ljava/lang/String;)Ljavax/jms/Destination;
      12: astore_2
      13: aload_0
      14: getfield      #1                  // Field this$0:Lorg/springframework/jms/core/JmsTemplate;
      17: aload_1
      18: aload_2
      19: aload_0
      20: getfield      #3                  // Field val$messageCreator:Lorg/springframework/jms/core/MessageCreator;
      23: invokevirtual #6                  // Method org/springframework/jms/core/JmsTemplate.doSend:(Ljavax/jms/Session;Ljavax/jms/Destination;Lorg/springframework/jms/core/MessageCreator;)V
      26: aconst_null
      27: areturn
}
