Compiled from "TimeoutExceededException.java"
public class net.jodah.failsafe.TimeoutExceededException extends net.jodah.failsafe.FailsafeException {
  private static final long serialVersionUID;

  private final net.jodah.failsafe.Timeout timeout;

  public net.jodah.failsafe.TimeoutExceededException(net.jodah.failsafe.Timeout);
    Code:
       0: aload_0
       1: invokespecial #1                  // Method net/jodah/failsafe/FailsafeException."<init>":()V
       4: aload_0
       5: aload_1
       6: putfield      #2                  // Field timeout:Lnet/jodah/failsafe/Timeout;
       9: return

  public net.jodah.failsafe.Timeout getTimeout();
    Code:
       0: aload_0
       1: getfield      #2                  // Field timeout:Lnet/jodah/failsafe/Timeout;
       4: areturn
}
