Compiled from "CreateEndpointRequestMarshaller.java"
public class com.amazonaws.services.databasemigrationservice.model.transform.CreateEndpointRequestMarshaller implements com.amazonaws.transform.Marshaller<com.amazonaws.Request<com.amazonaws.services.databasemigrationservice.model.CreateEndpointRequest>, com.amazonaws.services.databasemigrationservice.model.CreateEndpointRequest> {
  private final com.amazonaws.protocol.json.SdkJsonProtocolFactory protocolFactory;

  public com.amazonaws.services.databasemigrationservice.model.transform.CreateEndpointRequestMarshaller(com.amazonaws.protocol.json.SdkJsonProtocolFactory);
    Code:
       0: aload_0
       1: invokespecial #1                  // Method java/lang/Object."<init>":()V
       4: aload_0
       5: aload_1
       6: putfield      #2                  // Field protocolFactory:Lcom/amazonaws/protocol/json/SdkJsonProtocolFactory;
       9: return

  public com.amazonaws.Request<com.amazonaws.services.databasemigrationservice.model.CreateEndpointRequest> marshall(com.amazonaws.services.databasemigrationservice.model.CreateEndpointRequest);
    Code:
       0: aload_1
       1: ifnonnull     14
       4: new           #3                  // class com/amazonaws/AmazonClientException
       7: dup
       8: ldc           #4                  // String Invalid argument passed to marshall(...)
      10: invokespecial #5                  // Method com/amazonaws/AmazonClientException."<init>":(Ljava/lang/String;)V
      13: athrow
      14: new           #6                  // class com/amazonaws/DefaultRequest
      17: dup
      18: aload_1
      19: ldc           #7                  // String AWSDatabaseMigrationService
      21: invokespecial #8                  // Method com/amazonaws/DefaultRequest."<init>":(Lcom/amazonaws/AmazonWebServiceRequest;Ljava/lang/String;)V
      24: astore_2
      25: aload_2
      26: ldc           #9                  // String X-Amz-Target
      28: ldc           #10                 // String AmazonDMSv20160101.CreateEndpoint
      30: invokeinterface #11,  3           // InterfaceMethod com/amazonaws/Request.addHeader:(Ljava/lang/String;Ljava/lang/String;)V
      35: aload_2
      36: getstatic     #12                 // Field com/amazonaws/http/HttpMethodName.POST:Lcom/amazonaws/http/HttpMethodName;
      39: invokeinterface #13,  2           // InterfaceMethod com/amazonaws/Request.setHttpMethod:(Lcom/amazonaws/http/HttpMethodName;)V
      44: aload_2
      45: ldc           #14                 // String
      47: invokeinterface #15,  2           // InterfaceMethod com/amazonaws/Request.setResourcePath:(Ljava/lang/String;)V
      52: aload_0
      53: getfield      #2                  // Field protocolFactory:Lcom/amazonaws/protocol/json/SdkJsonProtocolFactory;
      56: invokevirtual #16                 // Method com/amazonaws/protocol/json/SdkJsonProtocolFactory.createGenerator:()Lcom/amazonaws/protocol/json/StructuredJsonGenerator;
      59: astore_3
      60: aload_3
      61: invokeinterface #17,  1           // InterfaceMethod com/amazonaws/protocol/json/StructuredJsonGenerator.writeStartObject:()Lcom/amazonaws/protocol/json/StructuredJsonGenerator;
      66: pop
      67: aload_1
      68: invokevirtual #18                 // Method com/amazonaws/services/databasemigrationservice/model/CreateEndpointRequest.getEndpointIdentifier:()Ljava/lang/String;
      71: ifnull        92
      74: aload_3
      75: ldc           #19                 // String EndpointIdentifier
      77: invokeinterface #20,  2           // InterfaceMethod com/amazonaws/protocol/json/StructuredJsonGenerator.writeFieldName:(Ljava/lang/String;)Lcom/amazonaws/protocol/json/StructuredJsonGenerator;
      82: aload_1
      83: invokevirtual #18                 // Method com/amazonaws/services/databasemigrationservice/model/CreateEndpointRequest.getEndpointIdentifier:()Ljava/lang/String;
      86: invokeinterface #21,  2           // InterfaceMethod com/amazonaws/protocol/json/StructuredJsonGenerator.writeValue:(Ljava/lang/String;)Lcom/amazonaws/protocol/json/StructuredJsonGenerator;
      91: pop
      92: aload_1
      93: invokevirtual #22                 // Method com/amazonaws/services/databasemigrationservice/model/CreateEndpointRequest.getEndpointType:()Ljava/lang/String;
      96: ifnull        117
      99: aload_3
     100: ldc           #23                 // String EndpointType
     102: invokeinterface #20,  2           // InterfaceMethod com/amazonaws/protocol/json/StructuredJsonGenerator.writeFieldName:(Ljava/lang/String;)Lcom/amazonaws/protocol/json/StructuredJsonGenerator;
     107: aload_1
     108: invokevirtual #22                 // Method com/amazonaws/services/databasemigrationservice/model/CreateEndpointRequest.getEndpointType:()Ljava/lang/String;
     111: invokeinterface #21,  2           // InterfaceMethod com/amazonaws/protocol/json/StructuredJsonGenerator.writeValue:(Ljava/lang/String;)Lcom/amazonaws/protocol/json/StructuredJsonGenerator;
     116: pop
     117: aload_1
     118: invokevirtual #24                 // Method com/amazonaws/services/databasemigrationservice/model/CreateEndpointRequest.getEngineName:()Ljava/lang/String;
     121: ifnull        142
     124: aload_3
     125: ldc           #25                 // String EngineName
     127: invokeinterface #20,  2           // InterfaceMethod com/amazonaws/protocol/json/StructuredJsonGenerator.writeFieldName:(Ljava/lang/String;)Lcom/amazonaws/protocol/json/StructuredJsonGenerator;
     132: aload_1
     133: invokevirtual #24                 // Method com/amazonaws/services/databasemigrationservice/model/CreateEndpointRequest.getEngineName:()Ljava/lang/String;
     136: invokeinterface #21,  2           // InterfaceMethod com/amazonaws/protocol/json/StructuredJsonGenerator.writeValue:(Ljava/lang/String;)Lcom/amazonaws/protocol/json/StructuredJsonGenerator;
     141: pop
     142: aload_1
     143: invokevirtual #26                 // Method com/amazonaws/services/databasemigrationservice/model/CreateEndpointRequest.getUsername:()Ljava/lang/String;
     146: ifnull        167
     149: aload_3
     150: ldc           #27                 // String Username
     152: invokeinterface #20,  2           // InterfaceMethod com/amazonaws/protocol/json/StructuredJsonGenerator.writeFieldName:(Ljava/lang/String;)Lcom/amazonaws/protocol/json/StructuredJsonGenerator;
     157: aload_1
     158: invokevirtual #26                 // Method com/amazonaws/services/databasemigrationservice/model/CreateEndpointRequest.getUsername:()Ljava/lang/String;
     161: invokeinterface #21,  2           // InterfaceMethod com/amazonaws/protocol/json/StructuredJsonGenerator.writeValue:(Ljava/lang/String;)Lcom/amazonaws/protocol/json/StructuredJsonGenerator;
     166: pop
     167: aload_1
     168: invokevirtual #28                 // Method com/amazonaws/services/databasemigrationservice/model/CreateEndpointRequest.getPassword:()Ljava/lang/String;
     171: ifnull        192
     174: aload_3
     175: ldc           #29                 // String Password
     177: invokeinterface #20,  2           // InterfaceMethod com/amazonaws/protocol/json/StructuredJsonGenerator.writeFieldName:(Ljava/lang/String;)Lcom/amazonaws/protocol/json/StructuredJsonGenerator;
     182: aload_1
     183: invokevirtual #28                 // Method com/amazonaws/services/databasemigrationservice/model/CreateEndpointRequest.getPassword:()Ljava/lang/String;
     186: invokeinterface #21,  2           // InterfaceMethod com/amazonaws/protocol/json/StructuredJsonGenerator.writeValue:(Ljava/lang/String;)Lcom/amazonaws/protocol/json/StructuredJsonGenerator;
     191: pop
     192: aload_1
     193: invokevirtual #30                 // Method com/amazonaws/services/databasemigrationservice/model/CreateEndpointRequest.getServerName:()Ljava/lang/String;
     196: ifnull        217
     199: aload_3
     200: ldc           #31                 // String ServerName
     202: invokeinterface #20,  2           // InterfaceMethod com/amazonaws/protocol/json/StructuredJsonGenerator.writeFieldName:(Ljava/lang/String;)Lcom/amazonaws/protocol/json/StructuredJsonGenerator;
     207: aload_1
     208: invokevirtual #30                 // Method com/amazonaws/services/databasemigrationservice/model/CreateEndpointRequest.getServerName:()Ljava/lang/String;
     211: invokeinterface #21,  2           // InterfaceMethod com/amazonaws/protocol/json/StructuredJsonGenerator.writeValue:(Ljava/lang/String;)Lcom/amazonaws/protocol/json/StructuredJsonGenerator;
     216: pop
     217: aload_1
     218: invokevirtual #32                 // Method com/amazonaws/services/databasemigrationservice/model/CreateEndpointRequest.getPort:()Ljava/lang/Integer;
     221: ifnull        245
     224: aload_3
     225: ldc           #33                 // String Port
     227: invokeinterface #20,  2           // InterfaceMethod com/amazonaws/protocol/json/StructuredJsonGenerator.writeFieldName:(Ljava/lang/String;)Lcom/amazonaws/protocol/json/StructuredJsonGenerator;
     232: aload_1
     233: invokevirtual #32                 // Method com/amazonaws/services/databasemigrationservice/model/CreateEndpointRequest.getPort:()Ljava/lang/Integer;
     236: invokevirtual #34                 // Method java/lang/Integer.intValue:()I
     239: invokeinterface #35,  2           // InterfaceMethod com/amazonaws/protocol/json/StructuredJsonGenerator.writeValue:(I)Lcom/amazonaws/protocol/json/StructuredJsonGenerator;
     244: pop
     245: aload_1
     246: invokevirtual #36                 // Method com/amazonaws/services/databasemigrationservice/model/CreateEndpointRequest.getDatabaseName:()Ljava/lang/String;
     249: ifnull        270
     252: aload_3
     253: ldc           #37                 // String DatabaseName
     255: invokeinterface #20,  2           // InterfaceMethod com/amazonaws/protocol/json/StructuredJsonGenerator.writeFieldName:(Ljava/lang/String;)Lcom/amazonaws/protocol/json/StructuredJsonGenerator;
     260: aload_1
     261: invokevirtual #36                 // Method com/amazonaws/services/databasemigrationservice/model/CreateEndpointRequest.getDatabaseName:()Ljava/lang/String;
     264: invokeinterface #21,  2           // InterfaceMethod com/amazonaws/protocol/json/StructuredJsonGenerator.writeValue:(Ljava/lang/String;)Lcom/amazonaws/protocol/json/StructuredJsonGenerator;
     269: pop
     270: aload_1
     271: invokevirtual #38                 // Method com/amazonaws/services/databasemigrationservice/model/CreateEndpointRequest.getExtraConnectionAttributes:()Ljava/lang/String;
     274: ifnull        295
     277: aload_3
     278: ldc           #39                 // String ExtraConnectionAttributes
     280: invokeinterface #20,  2           // InterfaceMethod com/amazonaws/protocol/json/StructuredJsonGenerator.writeFieldName:(Ljava/lang/String;)Lcom/amazonaws/protocol/json/StructuredJsonGenerator;
     285: aload_1
     286: invokevirtual #38                 // Method com/amazonaws/services/databasemigrationservice/model/CreateEndpointRequest.getExtraConnectionAttributes:()Ljava/lang/String;
     289: invokeinterface #21,  2           // InterfaceMethod com/amazonaws/protocol/json/StructuredJsonGenerator.writeValue:(Ljava/lang/String;)Lcom/amazonaws/protocol/json/StructuredJsonGenerator;
     294: pop
     295: aload_1
     296: invokevirtual #40                 // Method com/amazonaws/services/databasemigrationservice/model/CreateEndpointRequest.getKmsKeyId:()Ljava/lang/String;
     299: ifnull        320
     302: aload_3
     303: ldc           #41                 // String KmsKeyId
     305: invokeinterface #20,  2           // InterfaceMethod com/amazonaws/protocol/json/StructuredJsonGenerator.writeFieldName:(Ljava/lang/String;)Lcom/amazonaws/protocol/json/StructuredJsonGenerator;
     310: aload_1
     311: invokevirtual #40                 // Method com/amazonaws/services/databasemigrationservice/model/CreateEndpointRequest.getKmsKeyId:()Ljava/lang/String;
     314: invokeinterface #21,  2           // InterfaceMethod com/amazonaws/protocol/json/StructuredJsonGenerator.writeValue:(Ljava/lang/String;)Lcom/amazonaws/protocol/json/StructuredJsonGenerator;
     319: pop
     320: aload_1
     321: invokevirtual #42                 // Method com/amazonaws/services/databasemigrationservice/model/CreateEndpointRequest.getTags:()Ljava/util/List;
     324: astore        4
     326: aload         4
     328: ifnull        402
     331: aload_3
     332: ldc           #43                 // String Tags
     334: invokeinterface #20,  2           // InterfaceMethod com/amazonaws/protocol/json/StructuredJsonGenerator.writeFieldName:(Ljava/lang/String;)Lcom/amazonaws/protocol/json/StructuredJsonGenerator;
     339: pop
     340: aload_3
     341: invokeinterface #44,  1           // InterfaceMethod com/amazonaws/protocol/json/StructuredJsonGenerator.writeStartArray:()Lcom/amazonaws/protocol/json/StructuredJsonGenerator;
     346: pop
     347: aload         4
     349: invokeinterface #45,  1           // InterfaceMethod java/util/List.iterator:()Ljava/util/Iterator;
     354: astore        5
     356: aload         5
     358: invokeinterface #46,  1           // InterfaceMethod java/util/Iterator.hasNext:()Z
     363: ifeq          395
     366: aload         5
     368: invokeinterface #47,  1           // InterfaceMethod java/util/Iterator.next:()Ljava/lang/Object;
     373: checkcast     #48                 // class com/amazonaws/services/databasemigrationservice/model/Tag
     376: astore        6
     378: aload         6
     380: ifnull        392
     383: invokestatic  #49                 // Method com/amazonaws/services/databasemigrationservice/model/transform/TagJsonMarshaller.getInstance:()Lcom/amazonaws/services/databasemigrationservice/model/transform/TagJsonMarshaller;
     386: aload         6
     388: aload_3
     389: invokevirtual #50                 // Method com/amazonaws/services/databasemigrationservice/model/transform/TagJsonMarshaller.marshall:(Lcom/amazonaws/services/databasemigrationservice/model/Tag;Lcom/amazonaws/protocol/json/StructuredJsonGenerator;)V
     392: goto          356
     395: aload_3
     396: invokeinterface #51,  1           // InterfaceMethod com/amazonaws/protocol/json/StructuredJsonGenerator.writeEndArray:()Lcom/amazonaws/protocol/json/StructuredJsonGenerator;
     401: pop
     402: aload_1
     403: invokevirtual #52                 // Method com/amazonaws/services/databasemigrationservice/model/CreateEndpointRequest.getCertificateArn:()Ljava/lang/String;
     406: ifnull        427
     409: aload_3
     410: ldc           #53                 // String CertificateArn
     412: invokeinterface #20,  2           // InterfaceMethod com/amazonaws/protocol/json/StructuredJsonGenerator.writeFieldName:(Ljava/lang/String;)Lcom/amazonaws/protocol/json/StructuredJsonGenerator;
     417: aload_1
     418: invokevirtual #52                 // Method com/amazonaws/services/databasemigrationservice/model/CreateEndpointRequest.getCertificateArn:()Ljava/lang/String;
     421: invokeinterface #21,  2           // InterfaceMethod com/amazonaws/protocol/json/StructuredJsonGenerator.writeValue:(Ljava/lang/String;)Lcom/amazonaws/protocol/json/StructuredJsonGenerator;
     426: pop
     427: aload_1
     428: invokevirtual #54                 // Method com/amazonaws/services/databasemigrationservice/model/CreateEndpointRequest.getSslMode:()Ljava/lang/String;
     431: ifnull        452
     434: aload_3
     435: ldc           #55                 // String SslMode
     437: invokeinterface #20,  2           // InterfaceMethod com/amazonaws/protocol/json/StructuredJsonGenerator.writeFieldName:(Ljava/lang/String;)Lcom/amazonaws/protocol/json/StructuredJsonGenerator;
     442: aload_1
     443: invokevirtual #54                 // Method com/amazonaws/services/databasemigrationservice/model/CreateEndpointRequest.getSslMode:()Ljava/lang/String;
     446: invokeinterface #21,  2           // InterfaceMethod com/amazonaws/protocol/json/StructuredJsonGenerator.writeValue:(Ljava/lang/String;)Lcom/amazonaws/protocol/json/StructuredJsonGenerator;
     451: pop
     452: aload_3
     453: invokeinterface #56,  1           // InterfaceMethod com/amazonaws/protocol/json/StructuredJsonGenerator.writeEndObject:()Lcom/amazonaws/protocol/json/StructuredJsonGenerator;
     458: pop
     459: aload_3
     460: invokeinterface #57,  1           // InterfaceMethod com/amazonaws/protocol/json/StructuredJsonGenerator.getBytes:()[B
     465: astore        5
     467: aload_2
     468: new           #58                 // class java/io/ByteArrayInputStream
     471: dup
     472: aload         5
     474: invokespecial #59                 // Method java/io/ByteArrayInputStream."<init>":([B)V
     477: invokeinterface #60,  2           // InterfaceMethod com/amazonaws/Request.setContent:(Ljava/io/InputStream;)V
     482: aload_2
     483: ldc           #61                 // String Content-Length
     485: aload         5
     487: arraylength
     488: invokestatic  #62                 // Method java/lang/Integer.toString:(I)Ljava/lang/String;
     491: invokeinterface #11,  3           // InterfaceMethod com/amazonaws/Request.addHeader:(Ljava/lang/String;Ljava/lang/String;)V
     496: aload_2
     497: ldc           #63                 // String Content-Type
     499: aload_0
     500: getfield      #2                  // Field protocolFactory:Lcom/amazonaws/protocol/json/SdkJsonProtocolFactory;
     503: invokevirtual #64                 // Method com/amazonaws/protocol/json/SdkJsonProtocolFactory.getContentType:()Ljava/lang/String;
     506: invokeinterface #11,  3           // InterfaceMethod com/amazonaws/Request.addHeader:(Ljava/lang/String;Ljava/lang/String;)V
     511: goto          546
     514: astore_3
     515: new           #3                  // class com/amazonaws/AmazonClientException
     518: dup
     519: new           #66                 // class java/lang/StringBuilder
     522: dup
     523: invokespecial #67                 // Method java/lang/StringBuilder."<init>":()V
     526: ldc           #68                 // String Unable to marshall request to JSON:
     528: invokevirtual #69                 // Method java/lang/StringBuilder.append:(Ljava/lang/String;)Ljava/lang/StringBuilder;
     531: aload_3
     532: invokevirtual #70                 // Method java/lang/Throwable.getMessage:()Ljava/lang/String;
     535: invokevirtual #69                 // Method java/lang/StringBuilder.append:(Ljava/lang/String;)Ljava/lang/StringBuilder;
     538: invokevirtual #71                 // Method java/lang/StringBuilder.toString:()Ljava/lang/String;
     541: aload_3
     542: invokespecial #72                 // Method com/amazonaws/AmazonClientException."<init>":(Ljava/lang/String;Ljava/lang/Throwable;)V
     545: athrow
     546: aload_2
     547: areturn
    Exception table:
       from    to  target type
          52   511   514   Class java/lang/Throwable

  public java.lang.Object marshall(java.lang.Object) throws java.lang.Exception;
    Code:
       0: aload_0
       1: aload_1
       2: checkcast     #73                 // class com/amazonaws/services/databasemigrationservice/model/CreateEndpointRequest
       5: invokevirtual #74                 // Method marshall:(Lcom/amazonaws/services/databasemigrationservice/model/CreateEndpointRequest;)Lcom/amazonaws/Request;
       8: areturn
}
