Compiled from "RawMessageIdImpl.java"
public class org.apache.pulsar.common.api.raw.RawMessageIdImpl implements org.apache.pulsar.common.api.raw.RawMessageId {
  long ledgerId;

  long entryId;

  long batchIndex;

  public org.apache.pulsar.common.api.raw.RawMessageIdImpl();
    Code:
       0: aload_0
       1: invokespecial #1                  // Method java/lang/Object."<init>":()V
       4: return

  public java.lang.String toString();
    Code:
       0: new           #2                  // class java/lang/StringBuilder
       3: dup
       4: invokespecial #3                  // Method java/lang/StringBuilder."<init>":()V
       7: bipush        40
       9: invokevirtual #4                  // Method java/lang/StringBuilder.append:(C)Ljava/lang/StringBuilder;
      12: aload_0
      13: getfield      #5                  // Field ledgerId:J
      16: invokevirtual #6                  // Method java/lang/StringBuilder.append:(J)Ljava/lang/StringBuilder;
      19: bipush        44
      21: invokevirtual #4                  // Method java/lang/StringBuilder.append:(C)Ljava/lang/StringBuilder;
      24: aload_0
      25: getfield      #7                  // Field entryId:J
      28: invokevirtual #6                  // Method java/lang/StringBuilder.append:(J)Ljava/lang/StringBuilder;
      31: bipush        44
      33: invokevirtual #4                  // Method java/lang/StringBuilder.append:(C)Ljava/lang/StringBuilder;
      36: aload_0
      37: getfield      #8                  // Field batchIndex:J
      40: invokevirtual #6                  // Method java/lang/StringBuilder.append:(J)Ljava/lang/StringBuilder;
      43: bipush        41
      45: invokevirtual #4                  // Method java/lang/StringBuilder.append:(C)Ljava/lang/StringBuilder;
      48: invokevirtual #9                  // Method java/lang/StringBuilder.toString:()Ljava/lang/String;
      51: areturn

  public long getLedgerId();
    Code:
       0: aload_0
       1: getfield      #5                  // Field ledgerId:J
       4: lreturn

  public long getEntryId();
    Code:
       0: aload_0
       1: getfield      #7                  // Field entryId:J
       4: lreturn

  public long getBatchIndex();
    Code:
       0: aload_0
       1: getfield      #8                  // Field batchIndex:J
       4: lreturn
}
