Compiled from "ConfigurationBuilderEvent.java"
public class org.apache.commons.configuration2.builder.ConfigurationBuilderEvent extends org.apache.commons.configuration2.event.Event {
  public static final org.apache.commons.configuration2.event.EventType<org.apache.commons.configuration2.builder.ConfigurationBuilderEvent> ANY;

  public static final org.apache.commons.configuration2.event.EventType<org.apache.commons.configuration2.builder.ConfigurationBuilderEvent> RESET;

  public static final org.apache.commons.configuration2.event.EventType<org.apache.commons.configuration2.builder.ConfigurationBuilderEvent> CONFIGURATION_REQUEST;

  public org.apache.commons.configuration2.builder.ConfigurationBuilderEvent(org.apache.commons.configuration2.builder.ConfigurationBuilder<?>, org.apache.commons.configuration2.event.EventType<? extends org.apache.commons.configuration2.builder.ConfigurationBuilderEvent>);
    Code:
       0: aload_0
       1: aload_1
       2: aload_2
       3: invokespecial #1                  // Method org/apache/commons/configuration2/event/Event."<init>":(Ljava/lang/Object;Lorg/apache/commons/configuration2/event/EventType;)V
       6: return

  public org.apache.commons.configuration2.builder.ConfigurationBuilder<?> getSource();
    Code:
       0: aload_0
       1: invokespecial #2                  // Method org/apache/commons/configuration2/event/Event.getSource:()Ljava/lang/Object;
       4: checkcast     #3                  // class org/apache/commons/configuration2/builder/ConfigurationBuilder
       7: areturn

  public java.lang.Object getSource();
    Code:
       0: aload_0
       1: invokevirtual #4                  // Method getSource:()Lorg/apache/commons/configuration2/builder/ConfigurationBuilder;
       4: areturn

  static {};
    Code:
       0: new           #5                  // class org/apache/commons/configuration2/event/EventType
       3: dup
       4: getstatic     #6                  // Field org/apache/commons/configuration2/event/Event.ANY:Lorg/apache/commons/configuration2/event/EventType;
       7: ldc           #7                  // String BUILDER
       9: invokespecial #8                  // Method org/apache/commons/configuration2/event/EventType."<init>":(Lorg/apache/commons/configuration2/event/EventType;Ljava/lang/String;)V
      12: putstatic     #9                  // Field ANY:Lorg/apache/commons/configuration2/event/EventType;
      15: new           #5                  // class org/apache/commons/configuration2/event/EventType
      18: dup
      19: getstatic     #9                  // Field ANY:Lorg/apache/commons/configuration2/event/EventType;
      22: ldc           #10                 // String RESET
      24: invokespecial #8                  // Method org/apache/commons/configuration2/event/EventType."<init>":(Lorg/apache/commons/configuration2/event/EventType;Ljava/lang/String;)V
      27: putstatic     #11                 // Field RESET:Lorg/apache/commons/configuration2/event/EventType;
      30: new           #5                  // class org/apache/commons/configuration2/event/EventType
      33: dup
      34: getstatic     #9                  // Field ANY:Lorg/apache/commons/configuration2/event/EventType;
      37: ldc           #12                 // String CONFIGURATION_REQUEST
      39: invokespecial #8                  // Method org/apache/commons/configuration2/event/EventType."<init>":(Lorg/apache/commons/configuration2/event/EventType;Ljava/lang/String;)V
      42: putstatic     #13                 // Field CONFIGURATION_REQUEST:Lorg/apache/commons/configuration2/event/EventType;
      45: return
}
