Compiled from "FileBasedConfigurationBuilder.java"
public class org.apache.commons.configuration2.builder.FileBasedConfigurationBuilder<T extends org.apache.commons.configuration2.FileBasedConfiguration> extends org.apache.commons.configuration2.builder.BasicConfigurationBuilder<T> {
  private static final java.util.Map<java.lang.Class<?>, java.lang.String> DEFAULT_ENCODINGS;

  private org.apache.commons.configuration2.io.FileHandler currentFileHandler;

  private org.apache.commons.configuration2.builder.AutoSaveListener autoSaveListener;

  private boolean resetParameters;

  public org.apache.commons.configuration2.builder.FileBasedConfigurationBuilder(java.lang.Class<? extends T>);
    Code:
       0: aload_0
       1: aload_1
       2: invokespecial #1                  // Method org/apache/commons/configuration2/builder/BasicConfigurationBuilder."<init>":(Ljava/lang/Class;)V
       5: return

  public org.apache.commons.configuration2.builder.FileBasedConfigurationBuilder(java.lang.Class<? extends T>, java.util.Map<java.lang.String, java.lang.Object>);
    Code:
       0: aload_0
       1: aload_1
       2: aload_2
       3: invokespecial #2                  // Method org/apache/commons/configuration2/builder/BasicConfigurationBuilder."<init>":(Ljava/lang/Class;Ljava/util/Map;)V
       6: return

  public org.apache.commons.configuration2.builder.FileBasedConfigurationBuilder(java.lang.Class<? extends T>, java.util.Map<java.lang.String, java.lang.Object>, boolean);
    Code:
       0: aload_0
       1: aload_1
       2: aload_2
       3: iload_3
       4: invokespecial #3                  // Method org/apache/commons/configuration2/builder/BasicConfigurationBuilder."<init>":(Ljava/lang/Class;Ljava/util/Map;Z)V
       7: return

  public static java.lang.String getDefaultEncoding(java.lang.Class<?>);
    Code:
       0: getstatic     #4                  // Field DEFAULT_ENCODINGS:Ljava/util/Map;
       3: aload_0
       4: invokeinterface #5,  2            // InterfaceMethod java/util/Map.get:(Ljava/lang/Object;)Ljava/lang/Object;
       9: checkcast     #6                  // class java/lang/String
      12: astore_1
      13: aload_1
      14: ifnonnull     21
      17: aload_0
      18: ifnonnull     23
      21: aload_1
      22: areturn
      23: aload_0
      24: invokestatic  #7                  // Method org/apache/commons/lang3/ClassUtils.getAllSuperclasses:(Ljava/lang/Class;)Ljava/util/List;
      27: astore_2
      28: aload_2
      29: invokeinterface #8,  1            // InterfaceMethod java/util/List.iterator:()Ljava/util/Iterator;
      34: astore_3
      35: aload_3
      36: invokeinterface #9,  1            // InterfaceMethod java/util/Iterator.hasNext:()Z
      41: ifeq          78
      44: aload_3
      45: invokeinterface #10,  1           // InterfaceMethod java/util/Iterator.next:()Ljava/lang/Object;
      50: checkcast     #11                 // class java/lang/Class
      53: astore        4
      55: getstatic     #4                  // Field DEFAULT_ENCODINGS:Ljava/util/Map;
      58: aload         4
      60: invokeinterface #5,  2            // InterfaceMethod java/util/Map.get:(Ljava/lang/Object;)Ljava/lang/Object;
      65: checkcast     #6                  // class java/lang/String
      68: astore_1
      69: aload_1
      70: ifnull        75
      73: aload_1
      74: areturn
      75: goto          35
      78: aload_0
      79: invokestatic  #12                 // Method org/apache/commons/lang3/ClassUtils.getAllInterfaces:(Ljava/lang/Class;)Ljava/util/List;
      82: astore_3
      83: aload_3
      84: invokeinterface #8,  1            // InterfaceMethod java/util/List.iterator:()Ljava/util/Iterator;
      89: astore        4
      91: aload         4
      93: invokeinterface #9,  1            // InterfaceMethod java/util/Iterator.hasNext:()Z
      98: ifeq          136
     101: aload         4
     103: invokeinterface #10,  1           // InterfaceMethod java/util/Iterator.next:()Ljava/lang/Object;
     108: checkcast     #11                 // class java/lang/Class
     111: astore        5
     113: getstatic     #4                  // Field DEFAULT_ENCODINGS:Ljava/util/Map;
     116: aload         5
     118: invokeinterface #5,  2            // InterfaceMethod java/util/Map.get:(Ljava/lang/Object;)Ljava/lang/Object;
     123: checkcast     #6                  // class java/lang/String
     126: astore_1
     127: aload_1
     128: ifnull        133
     131: aload_1
     132: areturn
     133: goto          91
     136: aconst_null
     137: areturn

  public static void setDefaultEncoding(java.lang.Class<?>, java.lang.String);
    Code:
       0: aload_0
       1: ifnonnull     14
       4: new           #13                 // class java/lang/IllegalArgumentException
       7: dup
       8: ldc           #14                 // String Configuration class must not be null!
      10: invokespecial #15                 // Method java/lang/IllegalArgumentException."<init>":(Ljava/lang/String;)V
      13: athrow
      14: aload_1
      15: ifnonnull     31
      18: getstatic     #4                  // Field DEFAULT_ENCODINGS:Ljava/util/Map;
      21: aload_0
      22: invokeinterface #16,  2           // InterfaceMethod java/util/Map.remove:(Ljava/lang/Object;)Ljava/lang/Object;
      27: pop
      28: goto          42
      31: getstatic     #4                  // Field DEFAULT_ENCODINGS:Ljava/util/Map;
      34: aload_0
      35: aload_1
      36: invokeinterface #17,  3           // InterfaceMethod java/util/Map.put:(Ljava/lang/Object;Ljava/lang/Object;)Ljava/lang/Object;
      41: pop
      42: return

  public org.apache.commons.configuration2.builder.FileBasedConfigurationBuilder<T> configure(org.apache.commons.configuration2.builder.BuilderParameters...);
    Code:
       0: aload_0
       1: aload_1
       2: invokespecial #18                 // Method org/apache/commons/configuration2/builder/BasicConfigurationBuilder.configure:([Lorg/apache/commons/configuration2/builder/BuilderParameters;)Lorg/apache/commons/configuration2/builder/BasicConfigurationBuilder;
       5: pop
       6: aload_0
       7: areturn

  public synchronized org.apache.commons.configuration2.io.FileHandler getFileHandler();
    Code:
       0: aload_0
       1: getfield      #19                 // Field currentFileHandler:Lorg/apache/commons/configuration2/io/FileHandler;
       4: ifnull        14
       7: aload_0
       8: getfield      #19                 // Field currentFileHandler:Lorg/apache/commons/configuration2/io/FileHandler;
      11: goto          18
      14: aload_0
      15: invokespecial #20                 // Method fetchFileHandlerFromParameters:()Lorg/apache/commons/configuration2/io/FileHandler;
      18: areturn

  public synchronized org.apache.commons.configuration2.builder.BasicConfigurationBuilder<T> setParameters(java.util.Map<java.lang.String, java.lang.Object>);
    Code:
       0: aload_0
       1: aload_1
       2: invokespecial #21                 // Method org/apache/commons/configuration2/builder/BasicConfigurationBuilder.setParameters:(Ljava/util/Map;)Lorg/apache/commons/configuration2/builder/BasicConfigurationBuilder;
       5: pop
       6: aload_0
       7: iconst_1
       8: putfield      #22                 // Field resetParameters:Z
      11: aload_0
      12: areturn

  public void save() throws org.apache.commons.configuration2.ex.ConfigurationException;
    Code:
       0: aload_0
       1: invokevirtual #23                 // Method getFileHandler:()Lorg/apache/commons/configuration2/io/FileHandler;
       4: invokevirtual #24                 // Method org/apache/commons/configuration2/io/FileHandler.save:()V
       7: return

  public synchronized boolean isAutoSave();
    Code:
       0: aload_0
       1: getfield      #25                 // Field autoSaveListener:Lorg/apache/commons/configuration2/builder/AutoSaveListener;
       4: ifnull        11
       7: iconst_1
       8: goto          12
      11: iconst_0
      12: ireturn

  public synchronized void setAutoSave(boolean);
    Code:
       0: iload_1
       1: ifeq          11
       4: aload_0
       5: invokespecial #26                 // Method installAutoSaveListener:()V
       8: goto          15
      11: aload_0
      12: invokespecial #27                 // Method removeAutoSaveListener:()V
      15: return

  protected void initResultInstance(T) throws org.apache.commons.configuration2.ex.ConfigurationException;
    Code:
       0: aload_0
       1: aload_1
       2: invokespecial #28                 // Method org/apache/commons/configuration2/builder/BasicConfigurationBuilder.initResultInstance:(Lorg/apache/commons/configuration2/ImmutableConfiguration;)V
       5: aload_0
       6: getfield      #19                 // Field currentFileHandler:Lorg/apache/commons/configuration2/io/FileHandler;
       9: ifnull        26
      12: aload_0
      13: getfield      #22                 // Field resetParameters:Z
      16: ifne          26
      19: aload_0
      20: getfield      #19                 // Field currentFileHandler:Lorg/apache/commons/configuration2/io/FileHandler;
      23: goto          30
      26: aload_0
      27: invokespecial #20                 // Method fetchFileHandlerFromParameters:()Lorg/apache/commons/configuration2/io/FileHandler;
      30: astore_2
      31: aload_0
      32: new           #29                 // class org/apache/commons/configuration2/io/FileHandler
      35: dup
      36: aload_1
      37: aload_2
      38: invokespecial #30                 // Method org/apache/commons/configuration2/io/FileHandler."<init>":(Lorg/apache/commons/configuration2/io/FileBased;Lorg/apache/commons/configuration2/io/FileHandler;)V
      41: putfield      #19                 // Field currentFileHandler:Lorg/apache/commons/configuration2/io/FileHandler;
      44: aload_0
      45: getfield      #25                 // Field autoSaveListener:Lorg/apache/commons/configuration2/builder/AutoSaveListener;
      48: ifnull        62
      51: aload_0
      52: getfield      #25                 // Field autoSaveListener:Lorg/apache/commons/configuration2/builder/AutoSaveListener;
      55: aload_0
      56: getfield      #19                 // Field currentFileHandler:Lorg/apache/commons/configuration2/io/FileHandler;
      59: invokevirtual #31                 // Method org/apache/commons/configuration2/builder/AutoSaveListener.updateFileHandler:(Lorg/apache/commons/configuration2/io/FileHandler;)V
      62: aload_0
      63: aload_0
      64: getfield      #19                 // Field currentFileHandler:Lorg/apache/commons/configuration2/io/FileHandler;
      67: invokevirtual #32                 // Method initFileHandler:(Lorg/apache/commons/configuration2/io/FileHandler;)V
      70: aload_0
      71: iconst_0
      72: putfield      #22                 // Field resetParameters:Z
      75: return

  protected void initFileHandler(org.apache.commons.configuration2.io.FileHandler) throws org.apache.commons.configuration2.ex.ConfigurationException;
    Code:
       0: aload_0
       1: aload_1
       2: invokespecial #33                 // Method initEncoding:(Lorg/apache/commons/configuration2/io/FileHandler;)V
       5: aload_1
       6: invokevirtual #34                 // Method org/apache/commons/configuration2/io/FileHandler.isLocationDefined:()Z
       9: ifeq          21
      12: aload_1
      13: invokevirtual #35                 // Method org/apache/commons/configuration2/io/FileHandler.locate:()Z
      16: pop
      17: aload_1
      18: invokevirtual #36                 // Method org/apache/commons/configuration2/io/FileHandler.load:()V
      21: return

  private org.apache.commons.configuration2.io.FileHandler fetchFileHandlerFromParameters();
    Code:
       0: aload_0
       1: invokevirtual #37                 // Method getParameters:()Ljava/util/Map;
       4: iconst_0
       5: invokestatic  #38                 // Method org/apache/commons/configuration2/builder/FileBasedBuilderParametersImpl.fromParameters:(Ljava/util/Map;Z)Lorg/apache/commons/configuration2/builder/FileBasedBuilderParametersImpl;
       8: astore_1
       9: aload_1
      10: ifnonnull     30
      13: new           #39                 // class org/apache/commons/configuration2/builder/FileBasedBuilderParametersImpl
      16: dup
      17: invokespecial #40                 // Method org/apache/commons/configuration2/builder/FileBasedBuilderParametersImpl."<init>":()V
      20: astore_1
      21: aload_0
      22: aload_1
      23: invokevirtual #41                 // Method org/apache/commons/configuration2/builder/FileBasedBuilderParametersImpl.getParameters:()Ljava/util/Map;
      26: invokevirtual #42                 // Method addParameters:(Ljava/util/Map;)Lorg/apache/commons/configuration2/builder/BasicConfigurationBuilder;
      29: pop
      30: aload_1
      31: invokevirtual #43                 // Method org/apache/commons/configuration2/builder/FileBasedBuilderParametersImpl.getFileHandler:()Lorg/apache/commons/configuration2/io/FileHandler;
      34: areturn

  private void installAutoSaveListener();
    Code:
       0: aload_0
       1: getfield      #25                 // Field autoSaveListener:Lorg/apache/commons/configuration2/builder/AutoSaveListener;
       4: ifnonnull     41
       7: aload_0
       8: new           #44                 // class org/apache/commons/configuration2/builder/AutoSaveListener
      11: dup
      12: aload_0
      13: invokespecial #45                 // Method org/apache/commons/configuration2/builder/AutoSaveListener."<init>":(Lorg/apache/commons/configuration2/builder/FileBasedConfigurationBuilder;)V
      16: putfield      #25                 // Field autoSaveListener:Lorg/apache/commons/configuration2/builder/AutoSaveListener;
      19: aload_0
      20: getstatic     #46                 // Field org/apache/commons/configuration2/event/ConfigurationEvent.ANY:Lorg/apache/commons/configuration2/event/EventType;
      23: aload_0
      24: getfield      #25                 // Field autoSaveListener:Lorg/apache/commons/configuration2/builder/AutoSaveListener;
      27: invokevirtual #47                 // Method addEventListener:(Lorg/apache/commons/configuration2/event/EventType;Lorg/apache/commons/configuration2/event/EventListener;)V
      30: aload_0
      31: getfield      #25                 // Field autoSaveListener:Lorg/apache/commons/configuration2/builder/AutoSaveListener;
      34: aload_0
      35: invokevirtual #23                 // Method getFileHandler:()Lorg/apache/commons/configuration2/io/FileHandler;
      38: invokevirtual #31                 // Method org/apache/commons/configuration2/builder/AutoSaveListener.updateFileHandler:(Lorg/apache/commons/configuration2/io/FileHandler;)V
      41: return

  private void removeAutoSaveListener();
    Code:
       0: aload_0
       1: getfield      #25                 // Field autoSaveListener:Lorg/apache/commons/configuration2/builder/AutoSaveListener;
       4: ifnull        32
       7: aload_0
       8: getstatic     #46                 // Field org/apache/commons/configuration2/event/ConfigurationEvent.ANY:Lorg/apache/commons/configuration2/event/EventType;
      11: aload_0
      12: getfield      #25                 // Field autoSaveListener:Lorg/apache/commons/configuration2/builder/AutoSaveListener;
      15: invokevirtual #48                 // Method removeEventListener:(Lorg/apache/commons/configuration2/event/EventType;Lorg/apache/commons/configuration2/event/EventListener;)Z
      18: pop
      19: aload_0
      20: getfield      #25                 // Field autoSaveListener:Lorg/apache/commons/configuration2/builder/AutoSaveListener;
      23: aconst_null
      24: invokevirtual #31                 // Method org/apache/commons/configuration2/builder/AutoSaveListener.updateFileHandler:(Lorg/apache/commons/configuration2/io/FileHandler;)V
      27: aload_0
      28: aconst_null
      29: putfield      #25                 // Field autoSaveListener:Lorg/apache/commons/configuration2/builder/AutoSaveListener;
      32: return

  private void initEncoding(org.apache.commons.configuration2.io.FileHandler);
    Code:
       0: aload_1
       1: invokevirtual #49                 // Method org/apache/commons/configuration2/io/FileHandler.getEncoding:()Ljava/lang/String;
       4: invokestatic  #50                 // Method org/apache/commons/lang3/StringUtils.isEmpty:(Ljava/lang/CharSequence;)Z
       7: ifeq          27
      10: aload_0
      11: invokevirtual #51                 // Method getResultClass:()Ljava/lang/Class;
      14: invokestatic  #52                 // Method getDefaultEncoding:(Ljava/lang/Class;)Ljava/lang/String;
      17: astore_2
      18: aload_2
      19: ifnull        27
      22: aload_1
      23: aload_2
      24: invokevirtual #53                 // Method org/apache/commons/configuration2/io/FileHandler.setEncoding:(Ljava/lang/String;)V
      27: return

  private static java.util.Map<java.lang.Class<?>, java.lang.String> initializeDefaultEncodings();
    Code:
       0: new           #54                 // class java/util/concurrent/ConcurrentHashMap
       3: dup
       4: invokespecial #55                 // Method java/util/concurrent/ConcurrentHashMap."<init>":()V
       7: astore_0
       8: aload_0
       9: ldc           #56                 // class org/apache/commons/configuration2/PropertiesConfiguration
      11: ldc           #57                 // String ISO-8859-1
      13: invokeinterface #17,  3           // InterfaceMethod java/util/Map.put:(Ljava/lang/Object;Ljava/lang/Object;)Ljava/lang/Object;
      18: pop
      19: aload_0
      20: ldc           #58                 // class org/apache/commons/configuration2/XMLPropertiesConfiguration
      22: ldc           #59                 // String UTF-8
      24: invokeinterface #17,  3           // InterfaceMethod java/util/Map.put:(Ljava/lang/Object;Ljava/lang/Object;)Ljava/lang/Object;
      29: pop
      30: aload_0
      31: areturn

  protected void initResultInstance(org.apache.commons.configuration2.ImmutableConfiguration) throws org.apache.commons.configuration2.ex.ConfigurationException;
    Code:
       0: aload_0
       1: aload_1
       2: checkcast     #60                 // class org/apache/commons/configuration2/FileBasedConfiguration
       5: invokevirtual #61                 // Method initResultInstance:(Lorg/apache/commons/configuration2/FileBasedConfiguration;)V
       8: return

  public org.apache.commons.configuration2.builder.BasicConfigurationBuilder configure(org.apache.commons.configuration2.builder.BuilderParameters[]);
    Code:
       0: aload_0
       1: aload_1
       2: invokevirtual #62                 // Method configure:([Lorg/apache/commons/configuration2/builder/BuilderParameters;)Lorg/apache/commons/configuration2/builder/FileBasedConfigurationBuilder;
       5: areturn

  static {};
    Code:
       0: invokestatic  #63                 // Method initializeDefaultEncodings:()Ljava/util/Map;
       3: putstatic     #4                  // Field DEFAULT_ENCODINGS:Ljava/util/Map;
       6: return
}
