Compiled from "EnvironmentPBEConfig.java"
public class org.jasypt.encryption.pbe.config.EnvironmentPBEConfig extends org.jasypt.encryption.pbe.config.SimplePBEConfig {
  private java.lang.String algorithmEnvName;

  private java.lang.String keyObtentionIterationsEnvName;

  private java.lang.String passwordEnvName;

  private java.lang.String saltGeneratorClassNameEnvName;

  private java.lang.String providerNameEnvName;

  private java.lang.String providerClassNameEnvName;

  private java.lang.String poolSizeEnvName;

  private java.lang.String algorithmSysPropertyName;

  private java.lang.String keyObtentionIterationsSysPropertyName;

  private java.lang.String passwordSysPropertyName;

  private java.lang.String saltGeneratorClassNameSysPropertyName;

  private java.lang.String providerNameSysPropertyName;

  private java.lang.String providerClassNameSysPropertyName;

  private java.lang.String poolSizeSysPropertyName;

  public org.jasypt.encryption.pbe.config.EnvironmentPBEConfig();
    Code:
       0: aload_0
       1: invokespecial #1                  // Method org/jasypt/encryption/pbe/config/SimplePBEConfig."<init>":()V
       4: aload_0
       5: aconst_null
       6: putfield      #2                  // Field algorithmEnvName:Ljava/lang/String;
       9: aload_0
      10: aconst_null
      11: putfield      #3                  // Field keyObtentionIterationsEnvName:Ljava/lang/String;
      14: aload_0
      15: aconst_null
      16: putfield      #4                  // Field passwordEnvName:Ljava/lang/String;
      19: aload_0
      20: aconst_null
      21: putfield      #5                  // Field saltGeneratorClassNameEnvName:Ljava/lang/String;
      24: aload_0
      25: aconst_null
      26: putfield      #6                  // Field providerNameEnvName:Ljava/lang/String;
      29: aload_0
      30: aconst_null
      31: putfield      #7                  // Field providerClassNameEnvName:Ljava/lang/String;
      34: aload_0
      35: aconst_null
      36: putfield      #8                  // Field poolSizeEnvName:Ljava/lang/String;
      39: aload_0
      40: aconst_null
      41: putfield      #9                  // Field algorithmSysPropertyName:Ljava/lang/String;
      44: aload_0
      45: aconst_null
      46: putfield      #10                 // Field keyObtentionIterationsSysPropertyName:Ljava/lang/String;
      49: aload_0
      50: aconst_null
      51: putfield      #11                 // Field passwordSysPropertyName:Ljava/lang/String;
      54: aload_0
      55: aconst_null
      56: putfield      #12                 // Field saltGeneratorClassNameSysPropertyName:Ljava/lang/String;
      59: aload_0
      60: aconst_null
      61: putfield      #13                 // Field providerNameSysPropertyName:Ljava/lang/String;
      64: aload_0
      65: aconst_null
      66: putfield      #14                 // Field providerClassNameSysPropertyName:Ljava/lang/String;
      69: aload_0
      70: aconst_null
      71: putfield      #15                 // Field poolSizeSysPropertyName:Ljava/lang/String;
      74: return

  public java.lang.String getAlgorithmEnvName();
    Code:
       0: aload_0
       1: getfield      #2                  // Field algorithmEnvName:Ljava/lang/String;
       4: areturn

  public void setAlgorithmEnvName(java.lang.String);
    Code:
       0: aload_0
       1: aload_1
       2: putfield      #2                  // Field algorithmEnvName:Ljava/lang/String;
       5: aload_1
       6: ifnonnull     17
       9: aload_0
      10: aconst_null
      11: invokespecial #16                 // Method org/jasypt/encryption/pbe/config/SimplePBEConfig.setAlgorithm:(Ljava/lang/String;)V
      14: goto          30
      17: aload_0
      18: aconst_null
      19: putfield      #9                  // Field algorithmSysPropertyName:Ljava/lang/String;
      22: aload_0
      23: aload_1
      24: invokestatic  #17                 // Method java/lang/System.getenv:(Ljava/lang/String;)Ljava/lang/String;
      27: invokespecial #16                 // Method org/jasypt/encryption/pbe/config/SimplePBEConfig.setAlgorithm:(Ljava/lang/String;)V
      30: return

  public java.lang.String getAlgorithmSysPropertyName();
    Code:
       0: aload_0
       1: getfield      #9                  // Field algorithmSysPropertyName:Ljava/lang/String;
       4: areturn

  public void setAlgorithmSysPropertyName(java.lang.String);
    Code:
       0: aload_0
       1: aload_1
       2: putfield      #9                  // Field algorithmSysPropertyName:Ljava/lang/String;
       5: aload_1
       6: ifnonnull     17
       9: aload_0
      10: aconst_null
      11: invokespecial #16                 // Method org/jasypt/encryption/pbe/config/SimplePBEConfig.setAlgorithm:(Ljava/lang/String;)V
      14: goto          30
      17: aload_0
      18: aconst_null
      19: putfield      #2                  // Field algorithmEnvName:Ljava/lang/String;
      22: aload_0
      23: aload_1
      24: invokestatic  #18                 // Method java/lang/System.getProperty:(Ljava/lang/String;)Ljava/lang/String;
      27: invokespecial #16                 // Method org/jasypt/encryption/pbe/config/SimplePBEConfig.setAlgorithm:(Ljava/lang/String;)V
      30: return

  public java.lang.String getKeyObtentionIterationsEnvName();
    Code:
       0: aload_0
       1: getfield      #3                  // Field keyObtentionIterationsEnvName:Ljava/lang/String;
       4: areturn

  public void setKeyObtentionIterationsEnvName(java.lang.String);
    Code:
       0: aload_0
       1: aload_1
       2: putfield      #3                  // Field keyObtentionIterationsEnvName:Ljava/lang/String;
       5: aload_1
       6: ifnonnull     20
       9: aload_0
      10: aconst_null
      11: checkcast     #19                 // class java/lang/Integer
      14: invokespecial #20                 // Method org/jasypt/encryption/pbe/config/SimplePBEConfig.setKeyObtentionIterations:(Ljava/lang/Integer;)V
      17: goto          33
      20: aload_0
      21: aconst_null
      22: putfield      #10                 // Field keyObtentionIterationsSysPropertyName:Ljava/lang/String;
      25: aload_0
      26: aload_1
      27: invokestatic  #17                 // Method java/lang/System.getenv:(Ljava/lang/String;)Ljava/lang/String;
      30: invokespecial #21                 // Method org/jasypt/encryption/pbe/config/SimplePBEConfig.setKeyObtentionIterations:(Ljava/lang/String;)V
      33: return

  public java.lang.String getKeyObtentionIterationsSysPropertyName();
    Code:
       0: aload_0
       1: getfield      #10                 // Field keyObtentionIterationsSysPropertyName:Ljava/lang/String;
       4: areturn

  public void setKeyObtentionIterationsSysPropertyName(java.lang.String);
    Code:
       0: aload_0
       1: aload_1
       2: putfield      #10                 // Field keyObtentionIterationsSysPropertyName:Ljava/lang/String;
       5: aload_1
       6: ifnonnull     20
       9: aload_0
      10: aconst_null
      11: checkcast     #19                 // class java/lang/Integer
      14: invokespecial #20                 // Method org/jasypt/encryption/pbe/config/SimplePBEConfig.setKeyObtentionIterations:(Ljava/lang/Integer;)V
      17: goto          33
      20: aload_0
      21: aconst_null
      22: putfield      #3                  // Field keyObtentionIterationsEnvName:Ljava/lang/String;
      25: aload_0
      26: aload_1
      27: invokestatic  #18                 // Method java/lang/System.getProperty:(Ljava/lang/String;)Ljava/lang/String;
      30: invokespecial #21                 // Method org/jasypt/encryption/pbe/config/SimplePBEConfig.setKeyObtentionIterations:(Ljava/lang/String;)V
      33: return

  public java.lang.String getPasswordEnvName();
    Code:
       0: aload_0
       1: getfield      #4                  // Field passwordEnvName:Ljava/lang/String;
       4: areturn

  public void setPasswordEnvName(java.lang.String);
    Code:
       0: aload_0
       1: aload_1
       2: putfield      #4                  // Field passwordEnvName:Ljava/lang/String;
       5: aload_1
       6: ifnonnull     17
       9: aload_0
      10: aconst_null
      11: invokespecial #22                 // Method org/jasypt/encryption/pbe/config/SimplePBEConfig.setPassword:(Ljava/lang/String;)V
      14: goto          30
      17: aload_0
      18: aconst_null
      19: putfield      #11                 // Field passwordSysPropertyName:Ljava/lang/String;
      22: aload_0
      23: aload_1
      24: invokestatic  #17                 // Method java/lang/System.getenv:(Ljava/lang/String;)Ljava/lang/String;
      27: invokespecial #22                 // Method org/jasypt/encryption/pbe/config/SimplePBEConfig.setPassword:(Ljava/lang/String;)V
      30: return

  public java.lang.String getPasswordSysPropertyName();
    Code:
       0: aload_0
       1: getfield      #11                 // Field passwordSysPropertyName:Ljava/lang/String;
       4: areturn

  public void setPasswordSysPropertyName(java.lang.String);
    Code:
       0: aload_0
       1: aload_1
       2: putfield      #11                 // Field passwordSysPropertyName:Ljava/lang/String;
       5: aload_1
       6: ifnonnull     17
       9: aload_0
      10: aconst_null
      11: invokespecial #22                 // Method org/jasypt/encryption/pbe/config/SimplePBEConfig.setPassword:(Ljava/lang/String;)V
      14: goto          30
      17: aload_0
      18: aconst_null
      19: putfield      #4                  // Field passwordEnvName:Ljava/lang/String;
      22: aload_0
      23: aload_1
      24: invokestatic  #18                 // Method java/lang/System.getProperty:(Ljava/lang/String;)Ljava/lang/String;
      27: invokespecial #22                 // Method org/jasypt/encryption/pbe/config/SimplePBEConfig.setPassword:(Ljava/lang/String;)V
      30: return

  public java.lang.String getSaltGeneratorClassNameEnvName();
    Code:
       0: aload_0
       1: getfield      #5                  // Field saltGeneratorClassNameEnvName:Ljava/lang/String;
       4: areturn

  public void setSaltGeneratorClassNameEnvName(java.lang.String);
    Code:
       0: aload_0
       1: aload_1
       2: putfield      #5                  // Field saltGeneratorClassNameEnvName:Ljava/lang/String;
       5: aload_1
       6: ifnonnull     17
       9: aload_0
      10: aconst_null
      11: invokespecial #23                 // Method org/jasypt/encryption/pbe/config/SimplePBEConfig.setSaltGenerator:(Lorg/jasypt/salt/SaltGenerator;)V
      14: goto          32
      17: aload_0
      18: aconst_null
      19: putfield      #12                 // Field saltGeneratorClassNameSysPropertyName:Ljava/lang/String;
      22: aload_1
      23: invokestatic  #17                 // Method java/lang/System.getenv:(Ljava/lang/String;)Ljava/lang/String;
      26: astore_2
      27: aload_0
      28: aload_2
      29: invokespecial #24                 // Method org/jasypt/encryption/pbe/config/SimplePBEConfig.setSaltGeneratorClassName:(Ljava/lang/String;)V
      32: return

  public java.lang.String getSaltGeneratorClassNameSysPropertyName();
    Code:
       0: aload_0
       1: getfield      #12                 // Field saltGeneratorClassNameSysPropertyName:Ljava/lang/String;
       4: areturn

  public void setSaltGeneratorClassNameSysPropertyName(java.lang.String);
    Code:
       0: aload_0
       1: aload_1
       2: putfield      #12                 // Field saltGeneratorClassNameSysPropertyName:Ljava/lang/String;
       5: aload_1
       6: ifnonnull     17
       9: aload_0
      10: aconst_null
      11: invokespecial #23                 // Method org/jasypt/encryption/pbe/config/SimplePBEConfig.setSaltGenerator:(Lorg/jasypt/salt/SaltGenerator;)V
      14: goto          32
      17: aload_0
      18: aconst_null
      19: putfield      #5                  // Field saltGeneratorClassNameEnvName:Ljava/lang/String;
      22: aload_1
      23: invokestatic  #18                 // Method java/lang/System.getProperty:(Ljava/lang/String;)Ljava/lang/String;
      26: astore_2
      27: aload_0
      28: aload_2
      29: invokespecial #24                 // Method org/jasypt/encryption/pbe/config/SimplePBEConfig.setSaltGeneratorClassName:(Ljava/lang/String;)V
      32: return

  public java.lang.String getProviderNameEnvName();
    Code:
       0: aload_0
       1: getfield      #6                  // Field providerNameEnvName:Ljava/lang/String;
       4: areturn

  public void setProviderNameEnvName(java.lang.String);
    Code:
       0: aload_0
       1: aload_1
       2: putfield      #6                  // Field providerNameEnvName:Ljava/lang/String;
       5: aload_1
       6: ifnonnull     17
       9: aload_0
      10: aconst_null
      11: invokespecial #25                 // Method org/jasypt/encryption/pbe/config/SimplePBEConfig.setProviderName:(Ljava/lang/String;)V
      14: goto          30
      17: aload_0
      18: aconst_null
      19: putfield      #13                 // Field providerNameSysPropertyName:Ljava/lang/String;
      22: aload_0
      23: aload_1
      24: invokestatic  #17                 // Method java/lang/System.getenv:(Ljava/lang/String;)Ljava/lang/String;
      27: invokespecial #25                 // Method org/jasypt/encryption/pbe/config/SimplePBEConfig.setProviderName:(Ljava/lang/String;)V
      30: return

  public java.lang.String getProviderNameSysPropertyName();
    Code:
       0: aload_0
       1: getfield      #13                 // Field providerNameSysPropertyName:Ljava/lang/String;
       4: areturn

  public void setProviderNameSysPropertyName(java.lang.String);
    Code:
       0: aload_0
       1: aload_1
       2: putfield      #13                 // Field providerNameSysPropertyName:Ljava/lang/String;
       5: aload_1
       6: ifnonnull     17
       9: aload_0
      10: aconst_null
      11: invokespecial #25                 // Method org/jasypt/encryption/pbe/config/SimplePBEConfig.setProviderName:(Ljava/lang/String;)V
      14: goto          30
      17: aload_0
      18: aconst_null
      19: putfield      #6                  // Field providerNameEnvName:Ljava/lang/String;
      22: aload_0
      23: aload_1
      24: invokestatic  #18                 // Method java/lang/System.getProperty:(Ljava/lang/String;)Ljava/lang/String;
      27: invokespecial #25                 // Method org/jasypt/encryption/pbe/config/SimplePBEConfig.setProviderName:(Ljava/lang/String;)V
      30: return

  public java.lang.String getProviderClassNameEnvName();
    Code:
       0: aload_0
       1: getfield      #7                  // Field providerClassNameEnvName:Ljava/lang/String;
       4: areturn

  public void setProviderClassNameEnvName(java.lang.String);
    Code:
       0: aload_0
       1: aload_1
       2: putfield      #7                  // Field providerClassNameEnvName:Ljava/lang/String;
       5: aload_1
       6: ifnonnull     17
       9: aload_0
      10: aconst_null
      11: invokespecial #26                 // Method org/jasypt/encryption/pbe/config/SimplePBEConfig.setProvider:(Ljava/security/Provider;)V
      14: goto          32
      17: aload_0
      18: aconst_null
      19: putfield      #14                 // Field providerClassNameSysPropertyName:Ljava/lang/String;
      22: aload_1
      23: invokestatic  #17                 // Method java/lang/System.getenv:(Ljava/lang/String;)Ljava/lang/String;
      26: astore_2
      27: aload_0
      28: aload_2
      29: invokespecial #27                 // Method org/jasypt/encryption/pbe/config/SimplePBEConfig.setProviderClassName:(Ljava/lang/String;)V
      32: return

  public java.lang.String getProviderClassNameSysPropertyName();
    Code:
       0: aload_0
       1: getfield      #14                 // Field providerClassNameSysPropertyName:Ljava/lang/String;
       4: areturn

  public void setProviderClassNameSysPropertyName(java.lang.String);
    Code:
       0: aload_0
       1: aload_1
       2: putfield      #14                 // Field providerClassNameSysPropertyName:Ljava/lang/String;
       5: aload_1
       6: ifnonnull     17
       9: aload_0
      10: aconst_null
      11: invokespecial #26                 // Method org/jasypt/encryption/pbe/config/SimplePBEConfig.setProvider:(Ljava/security/Provider;)V
      14: goto          32
      17: aload_0
      18: aconst_null
      19: putfield      #7                  // Field providerClassNameEnvName:Ljava/lang/String;
      22: aload_1
      23: invokestatic  #18                 // Method java/lang/System.getProperty:(Ljava/lang/String;)Ljava/lang/String;
      26: astore_2
      27: aload_0
      28: aload_2
      29: invokespecial #27                 // Method org/jasypt/encryption/pbe/config/SimplePBEConfig.setProviderClassName:(Ljava/lang/String;)V
      32: return

  public java.lang.String getPoolSizeEnvName();
    Code:
       0: aload_0
       1: getfield      #8                  // Field poolSizeEnvName:Ljava/lang/String;
       4: areturn

  public void setPoolSizeEnvName(java.lang.String);
    Code:
       0: aload_0
       1: aload_1
       2: putfield      #8                  // Field poolSizeEnvName:Ljava/lang/String;
       5: aload_1
       6: ifnonnull     20
       9: aload_0
      10: aconst_null
      11: checkcast     #28                 // class java/lang/String
      14: invokespecial #29                 // Method org/jasypt/encryption/pbe/config/SimplePBEConfig.setPoolSize:(Ljava/lang/String;)V
      17: goto          33
      20: aload_0
      21: aconst_null
      22: putfield      #15                 // Field poolSizeSysPropertyName:Ljava/lang/String;
      25: aload_0
      26: aload_1
      27: invokestatic  #17                 // Method java/lang/System.getenv:(Ljava/lang/String;)Ljava/lang/String;
      30: invokespecial #29                 // Method org/jasypt/encryption/pbe/config/SimplePBEConfig.setPoolSize:(Ljava/lang/String;)V
      33: return

  public java.lang.String getPoolSizeSysPropertyName();
    Code:
       0: aload_0
       1: getfield      #15                 // Field poolSizeSysPropertyName:Ljava/lang/String;
       4: areturn

  public void setPoolSizeSysPropertyName(java.lang.String);
    Code:
       0: aload_0
       1: aload_1
       2: putfield      #15                 // Field poolSizeSysPropertyName:Ljava/lang/String;
       5: aload_1
       6: ifnonnull     20
       9: aload_0
      10: aconst_null
      11: checkcast     #28                 // class java/lang/String
      14: invokespecial #29                 // Method org/jasypt/encryption/pbe/config/SimplePBEConfig.setPoolSize:(Ljava/lang/String;)V
      17: goto          33
      20: aload_0
      21: aconst_null
      22: putfield      #8                  // Field poolSizeEnvName:Ljava/lang/String;
      25: aload_0
      26: aload_1
      27: invokestatic  #18                 // Method java/lang/System.getProperty:(Ljava/lang/String;)Ljava/lang/String;
      30: invokespecial #29                 // Method org/jasypt/encryption/pbe/config/SimplePBEConfig.setPoolSize:(Ljava/lang/String;)V
      33: return

  public void setAlgorithm(java.lang.String);
    Code:
       0: aload_0
       1: aconst_null
       2: putfield      #2                  // Field algorithmEnvName:Ljava/lang/String;
       5: aload_0
       6: aconst_null
       7: putfield      #9                  // Field algorithmSysPropertyName:Ljava/lang/String;
      10: aload_0
      11: aload_1
      12: invokespecial #16                 // Method org/jasypt/encryption/pbe/config/SimplePBEConfig.setAlgorithm:(Ljava/lang/String;)V
      15: return

  public void setKeyObtentionIterations(java.lang.Integer);
    Code:
       0: aload_0
       1: aconst_null
       2: putfield      #3                  // Field keyObtentionIterationsEnvName:Ljava/lang/String;
       5: aload_0
       6: aconst_null
       7: putfield      #10                 // Field keyObtentionIterationsSysPropertyName:Ljava/lang/String;
      10: aload_0
      11: aload_1
      12: invokespecial #20                 // Method org/jasypt/encryption/pbe/config/SimplePBEConfig.setKeyObtentionIterations:(Ljava/lang/Integer;)V
      15: return

  public void setKeyObtentionIterations(java.lang.String);
    Code:
       0: aload_0
       1: aconst_null
       2: putfield      #3                  // Field keyObtentionIterationsEnvName:Ljava/lang/String;
       5: aload_0
       6: aconst_null
       7: putfield      #10                 // Field keyObtentionIterationsSysPropertyName:Ljava/lang/String;
      10: aload_0
      11: aload_1
      12: invokespecial #21                 // Method org/jasypt/encryption/pbe/config/SimplePBEConfig.setKeyObtentionIterations:(Ljava/lang/String;)V
      15: return

  public void setPassword(java.lang.String);
    Code:
       0: aload_0
       1: aconst_null
       2: putfield      #4                  // Field passwordEnvName:Ljava/lang/String;
       5: aload_0
       6: aconst_null
       7: putfield      #11                 // Field passwordSysPropertyName:Ljava/lang/String;
      10: aload_0
      11: aload_1
      12: invokespecial #22                 // Method org/jasypt/encryption/pbe/config/SimplePBEConfig.setPassword:(Ljava/lang/String;)V
      15: return

  public void setPasswordCharArray(char[]);
    Code:
       0: aload_0
       1: aconst_null
       2: putfield      #4                  // Field passwordEnvName:Ljava/lang/String;
       5: aload_0
       6: aconst_null
       7: putfield      #11                 // Field passwordSysPropertyName:Ljava/lang/String;
      10: aload_0
      11: aload_1
      12: invokespecial #30                 // Method org/jasypt/encryption/pbe/config/SimplePBEConfig.setPasswordCharArray:([C)V
      15: return

  public void setSaltGenerator(org.jasypt.salt.SaltGenerator);
    Code:
       0: aload_0
       1: aconst_null
       2: putfield      #5                  // Field saltGeneratorClassNameEnvName:Ljava/lang/String;
       5: aload_0
       6: aconst_null
       7: putfield      #12                 // Field saltGeneratorClassNameSysPropertyName:Ljava/lang/String;
      10: aload_0
      11: aload_1
      12: invokespecial #23                 // Method org/jasypt/encryption/pbe/config/SimplePBEConfig.setSaltGenerator:(Lorg/jasypt/salt/SaltGenerator;)V
      15: return

  public void setSaltGeneratorClassName(java.lang.String);
    Code:
       0: aload_0
       1: aconst_null
       2: putfield      #5                  // Field saltGeneratorClassNameEnvName:Ljava/lang/String;
       5: aload_0
       6: aconst_null
       7: putfield      #12                 // Field saltGeneratorClassNameSysPropertyName:Ljava/lang/String;
      10: aload_0
      11: aload_1
      12: invokespecial #24                 // Method org/jasypt/encryption/pbe/config/SimplePBEConfig.setSaltGeneratorClassName:(Ljava/lang/String;)V
      15: return

  public void setProviderName(java.lang.String);
    Code:
       0: aload_0
       1: aconst_null
       2: putfield      #6                  // Field providerNameEnvName:Ljava/lang/String;
       5: aload_0
       6: aconst_null
       7: putfield      #13                 // Field providerNameSysPropertyName:Ljava/lang/String;
      10: aload_0
      11: aload_1
      12: invokespecial #25                 // Method org/jasypt/encryption/pbe/config/SimplePBEConfig.setProviderName:(Ljava/lang/String;)V
      15: return

  public void setProvider(java.security.Provider);
    Code:
       0: aload_0
       1: aconst_null
       2: putfield      #7                  // Field providerClassNameEnvName:Ljava/lang/String;
       5: aload_0
       6: aconst_null
       7: putfield      #14                 // Field providerClassNameSysPropertyName:Ljava/lang/String;
      10: aload_0
      11: aload_1
      12: invokespecial #26                 // Method org/jasypt/encryption/pbe/config/SimplePBEConfig.setProvider:(Ljava/security/Provider;)V
      15: return

  public void setProviderClassName(java.lang.String);
    Code:
       0: aload_0
       1: aconst_null
       2: putfield      #7                  // Field providerClassNameEnvName:Ljava/lang/String;
       5: aload_0
       6: aconst_null
       7: putfield      #14                 // Field providerClassNameSysPropertyName:Ljava/lang/String;
      10: aload_0
      11: aload_1
      12: invokespecial #27                 // Method org/jasypt/encryption/pbe/config/SimplePBEConfig.setProviderClassName:(Ljava/lang/String;)V
      15: return

  public void setPoolSize(java.lang.Integer);
    Code:
       0: aload_0
       1: aconst_null
       2: putfield      #8                  // Field poolSizeEnvName:Ljava/lang/String;
       5: aload_0
       6: aconst_null
       7: putfield      #15                 // Field poolSizeSysPropertyName:Ljava/lang/String;
      10: aload_0
      11: aload_1
      12: invokespecial #31                 // Method org/jasypt/encryption/pbe/config/SimplePBEConfig.setPoolSize:(Ljava/lang/Integer;)V
      15: return

  public void setPoolSize(java.lang.String);
    Code:
       0: aload_0
       1: aconst_null
       2: putfield      #8                  // Field poolSizeEnvName:Ljava/lang/String;
       5: aload_0
       6: aconst_null
       7: putfield      #15                 // Field poolSizeSysPropertyName:Ljava/lang/String;
      10: aload_0
      11: aload_1
      12: invokespecial #29                 // Method org/jasypt/encryption/pbe/config/SimplePBEConfig.setPoolSize:(Ljava/lang/String;)V
      15: return
}
