Compiled from "WebDavResponse.java"
public class org.asynchttpclient.webdav.WebDavResponse implements org.asynchttpclient.Response {
  private final org.asynchttpclient.Response response;

  private final org.w3c.dom.Document document;

  org.asynchttpclient.webdav.WebDavResponse(org.asynchttpclient.Response, org.w3c.dom.Document);
    Code:
       0: aload_0
       1: invokespecial #1                  // Method java/lang/Object."<init>":()V
       4: aload_0
       5: aload_1
       6: putfield      #2                  // Field response:Lorg/asynchttpclient/Response;
       9: aload_0
      10: aload_2
      11: putfield      #3                  // Field document:Lorg/w3c/dom/Document;
      14: return

  public int getStatusCode();
    Code:
       0: aload_0
       1: getfield      #2                  // Field response:Lorg/asynchttpclient/Response;
       4: invokeinterface #4,  1            // InterfaceMethod org/asynchttpclient/Response.getStatusCode:()I
       9: ireturn

  public java.lang.String getStatusText();
    Code:
       0: aload_0
       1: getfield      #2                  // Field response:Lorg/asynchttpclient/Response;
       4: invokeinterface #5,  1            // InterfaceMethod org/asynchttpclient/Response.getStatusText:()Ljava/lang/String;
       9: areturn

  public byte[] getResponseBodyAsBytes();
    Code:
       0: aload_0
       1: getfield      #2                  // Field response:Lorg/asynchttpclient/Response;
       4: invokeinterface #6,  1            // InterfaceMethod org/asynchttpclient/Response.getResponseBodyAsBytes:()[B
       9: areturn

  public java.nio.ByteBuffer getResponseBodyAsByteBuffer();
    Code:
       0: aload_0
       1: getfield      #2                  // Field response:Lorg/asynchttpclient/Response;
       4: invokeinterface #7,  1            // InterfaceMethod org/asynchttpclient/Response.getResponseBodyAsByteBuffer:()Ljava/nio/ByteBuffer;
       9: areturn

  public java.io.InputStream getResponseBodyAsStream();
    Code:
       0: aload_0
       1: getfield      #2                  // Field response:Lorg/asynchttpclient/Response;
       4: invokeinterface #8,  1            // InterfaceMethod org/asynchttpclient/Response.getResponseBodyAsStream:()Ljava/io/InputStream;
       9: areturn

  public java.lang.String getResponseBody();
    Code:
       0: aload_0
       1: getfield      #2                  // Field response:Lorg/asynchttpclient/Response;
       4: invokeinterface #9,  1            // InterfaceMethod org/asynchttpclient/Response.getResponseBody:()Ljava/lang/String;
       9: areturn

  public java.lang.String getResponseBody(java.nio.charset.Charset);
    Code:
       0: aload_0
       1: getfield      #2                  // Field response:Lorg/asynchttpclient/Response;
       4: aload_1
       5: invokeinterface #10,  2           // InterfaceMethod org/asynchttpclient/Response.getResponseBody:(Ljava/nio/charset/Charset;)Ljava/lang/String;
      10: areturn

  public org.asynchttpclient.uri.Uri getUri();
    Code:
       0: aload_0
       1: getfield      #2                  // Field response:Lorg/asynchttpclient/Response;
       4: invokeinterface #11,  1           // InterfaceMethod org/asynchttpclient/Response.getUri:()Lorg/asynchttpclient/uri/Uri;
       9: areturn

  public java.lang.String getContentType();
    Code:
       0: aload_0
       1: getfield      #2                  // Field response:Lorg/asynchttpclient/Response;
       4: invokeinterface #12,  1           // InterfaceMethod org/asynchttpclient/Response.getContentType:()Ljava/lang/String;
       9: areturn

  public java.lang.String getHeader(java.lang.CharSequence);
    Code:
       0: aload_0
       1: getfield      #2                  // Field response:Lorg/asynchttpclient/Response;
       4: aload_1
       5: invokeinterface #13,  2           // InterfaceMethod org/asynchttpclient/Response.getHeader:(Ljava/lang/CharSequence;)Ljava/lang/String;
      10: areturn

  public java.util.List<java.lang.String> getHeaders(java.lang.CharSequence);
    Code:
       0: aload_0
       1: getfield      #2                  // Field response:Lorg/asynchttpclient/Response;
       4: aload_1
       5: invokeinterface #14,  2           // InterfaceMethod org/asynchttpclient/Response.getHeaders:(Ljava/lang/CharSequence;)Ljava/util/List;
      10: areturn

  public io.netty.handler.codec.http.HttpHeaders getHeaders();
    Code:
       0: aload_0
       1: getfield      #2                  // Field response:Lorg/asynchttpclient/Response;
       4: invokeinterface #15,  1           // InterfaceMethod org/asynchttpclient/Response.getHeaders:()Lio/netty/handler/codec/http/HttpHeaders;
       9: areturn

  public boolean isRedirected();
    Code:
       0: aload_0
       1: getfield      #2                  // Field response:Lorg/asynchttpclient/Response;
       4: invokeinterface #16,  1           // InterfaceMethod org/asynchttpclient/Response.isRedirected:()Z
       9: ireturn

  public java.util.List<io.netty.handler.codec.http.cookie.Cookie> getCookies();
    Code:
       0: aload_0
       1: getfield      #2                  // Field response:Lorg/asynchttpclient/Response;
       4: invokeinterface #17,  1           // InterfaceMethod org/asynchttpclient/Response.getCookies:()Ljava/util/List;
       9: areturn

  public boolean hasResponseStatus();
    Code:
       0: aload_0
       1: getfield      #2                  // Field response:Lorg/asynchttpclient/Response;
       4: invokeinterface #18,  1           // InterfaceMethod org/asynchttpclient/Response.hasResponseStatus:()Z
       9: ireturn

  public boolean hasResponseHeaders();
    Code:
       0: aload_0
       1: getfield      #2                  // Field response:Lorg/asynchttpclient/Response;
       4: invokeinterface #19,  1           // InterfaceMethod org/asynchttpclient/Response.hasResponseHeaders:()Z
       9: ireturn

  public boolean hasResponseBody();
    Code:
       0: aload_0
       1: getfield      #2                  // Field response:Lorg/asynchttpclient/Response;
       4: invokeinterface #20,  1           // InterfaceMethod org/asynchttpclient/Response.hasResponseBody:()Z
       9: ireturn

  public java.net.SocketAddress getRemoteAddress();
    Code:
       0: aload_0
       1: getfield      #2                  // Field response:Lorg/asynchttpclient/Response;
       4: invokeinterface #21,  1           // InterfaceMethod org/asynchttpclient/Response.getRemoteAddress:()Ljava/net/SocketAddress;
       9: areturn

  public java.net.SocketAddress getLocalAddress();
    Code:
       0: aload_0
       1: getfield      #2                  // Field response:Lorg/asynchttpclient/Response;
       4: invokeinterface #22,  1           // InterfaceMethod org/asynchttpclient/Response.getLocalAddress:()Ljava/net/SocketAddress;
       9: areturn

  public org.w3c.dom.Document getBodyAsXML();
    Code:
       0: aload_0
       1: getfield      #3                  // Field document:Lorg/w3c/dom/Document;
       4: areturn
}
