Compiled from "ShadowNoFileLockStore.java"
public class com.arjuna.ats.internal.arjuna.objectstore.ShadowNoFileLockStore extends com.arjuna.ats.internal.arjuna.objectstore.ShadowingStore {
  public com.arjuna.ats.internal.arjuna.objectstore.ShadowNoFileLockStore(com.arjuna.ats.arjuna.common.ObjectStoreEnvironmentBean) throws com.arjuna.ats.arjuna.exceptions.ObjectStoreException;
    Code:
       0: aload_0
       1: aload_1
       2: invokespecial #1                  // Method com/arjuna/ats/internal/arjuna/objectstore/ShadowingStore."<init>":(Lcom/arjuna/ats/arjuna/common/ObjectStoreEnvironmentBean;)V
       5: return

  protected boolean lock(java.io.File, int, boolean);
    Code:
       0: iconst_1
       1: ireturn

  protected boolean unlock(java.io.File);
    Code:
       0: iconst_1
       1: ireturn
}
