Compiled from "PropertyDialog.java"
public class org.eclipse.ui.internal.dialogs.PropertyDialog extends org.eclipse.ui.internal.dialogs.FilteredPreferenceDialog {
  private org.eclipse.jface.viewers.ISelection selection;

  private static java.lang.String lastPropertyId;

  static {};
    Code:
       0: aconst_null
       1: putstatic     #185                // Field lastPropertyId:Ljava/lang/String;
       4: return

  public static org.eclipse.ui.internal.dialogs.PropertyDialog createDialogOn(org.eclipse.swt.widgets.Shell, java.lang.String, java.lang.Object);
    Code:
       0: new           #111                // class org/eclipse/ui/internal/dialogs/PropertyPageManager
       3: dup
       4: invokespecial #207                // Method org/eclipse/ui/internal/dialogs/PropertyPageManager."<init>":()V
       7: astore_3
       8: ldc           #1                  // String
      10: astore        4
      12: aload_2
      13: ifnonnull     18
      16: aconst_null
      17: areturn
      18: invokestatic  #205                // Method org/eclipse/ui/internal/dialogs/PropertyPageContributorManager.getManager:()Lorg/eclipse/ui/internal/dialogs/PropertyPageContributorManager;
      21: aload_3
      22: aload_2
      23: invokevirtual #206                // Method org/eclipse/ui/internal/dialogs/PropertyPageContributorManager.contribute:(Lorg/eclipse/ui/internal/dialogs/PropertyPageManager;Ljava/lang/Object;)Z
      26: pop
      27: aload_3
      28: iconst_0
      29: invokevirtual #208                // Method org/eclipse/ui/internal/dialogs/PropertyPageManager.getElements:(I)Ljava/util/List;
      32: invokeinterface #210,  1          // InterfaceMethod java/util/List.iterator:()Ljava/util/Iterator;
      37: astore        5
      39: aload_2
      40: invokestatic  #203                // Method getName:(Ljava/lang/Object;)Ljava/lang/String;
      43: astore        6
      45: aload         5
      47: invokeinterface #209,  1          // InterfaceMethod java/util/Iterator.hasNext:()Z
      52: ifne          95
      55: ldc           #1                  // String
      57: aload         6
      59: invokevirtual #187                // Method java/lang/String.equals:(Ljava/lang/Object;)Z
      62: ifeq          78
      65: aload_0
      66: getstatic     #181                // Field org/eclipse/ui/internal/WorkbenchMessages.PropertyDialog_messageTitle:Ljava/lang/String;
      69: getstatic     #183                // Field org/eclipse/ui/internal/WorkbenchMessages.PropertyDialog_noPropertyMessageForUnknown:Ljava/lang/String;
      72: invokestatic  #193                // Method org/eclipse/jface/dialogs/MessageDialog.openInformation:(Lorg/eclipse/swt/widgets/Shell;Ljava/lang/String;Ljava/lang/String;)V
      75: goto          93
      78: aload_0
      79: getstatic     #181                // Field org/eclipse/ui/internal/WorkbenchMessages.PropertyDialog_messageTitle:Ljava/lang/String;
      82: getstatic     #182                // Field org/eclipse/ui/internal/WorkbenchMessages.PropertyDialog_noPropertyMessage:Ljava/lang/String;
      85: aload         6
      87: invokestatic  #195                // Method org/eclipse/osgi/util/NLS.bind:(Ljava/lang/String;Ljava/lang/Object;)Ljava/lang/String;
      90: invokestatic  #193                // Method org/eclipse/jface/dialogs/MessageDialog.openInformation:(Lorg/eclipse/swt/widgets/Shell;Ljava/lang/String;Ljava/lang/String;)V
      93: aconst_null
      94: areturn
      95: getstatic     #184                // Field org/eclipse/ui/internal/WorkbenchMessages.PropertyDialog_propertyMessage:Ljava/lang/String;
      98: aload         6
     100: invokestatic  #195                // Method org/eclipse/osgi/util/NLS.bind:(Ljava/lang/String;Ljava/lang/Object;)Ljava/lang/String;
     103: astore        4
     105: new           #109                // class org/eclipse/ui/internal/dialogs/PropertyDialog
     108: dup
     109: aload_0
     110: aload_3
     111: new           #101                // class org/eclipse/jface/viewers/StructuredSelection
     114: dup
     115: aload_2
     116: invokespecial #194                // Method org/eclipse/jface/viewers/StructuredSelection."<init>":(Ljava/lang/Object;)V
     119: invokespecial #204                // Method "<init>":(Lorg/eclipse/swt/widgets/Shell;Lorg/eclipse/jface/preference/PreferenceManager;Lorg/eclipse/jface/viewers/ISelection;)V
     122: astore        7
     124: aload_1
     125: ifnull        134
     128: aload         7
     130: aload_1
     131: invokevirtual #200                // Method setSelectedNode:(Ljava/lang/String;)V
     134: aload         7
     136: invokevirtual #199                // Method create:()V
     139: aload         7
     141: invokevirtual #202                // Method getShell:()Lorg/eclipse/swt/widgets/Shell;
     144: aload         4
     146: invokevirtual #196                // Method org/eclipse/swt/widgets/Shell.setText:(Ljava/lang/String;)V
     149: invokestatic  #197                // Method org/eclipse/ui/PlatformUI.getWorkbench:()Lorg/eclipse/ui/IWorkbench;
     152: invokeinterface #212,  1          // InterfaceMethod org/eclipse/ui/IWorkbench.getHelpSystem:()Lorg/eclipse/ui/help/IWorkbenchHelpSystem;
     157: aload         7
     159: invokevirtual #202                // Method getShell:()Lorg/eclipse/swt/widgets/Shell;
     162: ldc           #4                  // String org.eclipse.ui.property_dialog_context
     164: invokeinterface #213,  3          // InterfaceMethod org/eclipse/ui/help/IWorkbenchHelpSystem.setHelp:(Lorg/eclipse/swt/widgets/Control;Ljava/lang/String;)V
     169: aload         7
     171: areturn

  protected void addButtonsToHelpControl(org.eclipse.swt.widgets.Control);
    Code:
       0: return

  private static java.lang.String getName(java.lang.Object);
    Code:
       0: aload_0
       1: instanceof    #100                // class org/eclipse/jface/viewers/IStructuredSelection
       4: ifeq          20
       7: aload_0
       8: checkcast     #100                // class org/eclipse/jface/viewers/IStructuredSelection
      11: invokeinterface #211,  1          // InterfaceMethod org/eclipse/jface/viewers/IStructuredSelection.toArray:()[Ljava/lang/Object;
      16: astore_1
      17: goto          29
      20: iconst_1
      21: anewarray     #93                 // class java/lang/Object
      24: dup
      25: iconst_0
      26: aload_0
      27: aastore
      28: astore_1
      29: new           #95                 // class java/lang/StringBuilder
      32: dup
      33: invokespecial #189                // Method java/lang/StringBuilder."<init>":()V
      36: astore_2
      37: iconst_0
      38: istore_3
      39: goto          107
      42: aload_1
      43: iload_3
      44: aaload
      45: astore_0
      46: iload_3
      47: iconst_2
      48: if_icmple     61
      51: aload_2
      52: ldc           #2                  // String  ...
      54: invokevirtual #191                // Method java/lang/StringBuilder.append:(Ljava/lang/String;)Ljava/lang/StringBuilder;
      57: pop
      58: goto          113
      61: aload_0
      62: ldc           #6                  // class org/eclipse/ui/model/IWorkbenchAdapter
      64: invokestatic  #192                // Method org/eclipse/core/runtime/Adapters.adapt:(Ljava/lang/Object;Ljava/lang/Class;)Ljava/lang/Object;
      67: checkcast     #6                  // class org/eclipse/ui/model/IWorkbenchAdapter
      70: astore        4
      72: aload         4
      74: ifnull        104
      77: aload_2
      78: invokevirtual #188                // Method java/lang/StringBuilder.length:()I
      81: ifle          91
      84: aload_2
      85: ldc           #3                  // String ,
      87: invokevirtual #191                // Method java/lang/StringBuilder.append:(Ljava/lang/String;)Ljava/lang/StringBuilder;
      90: pop
      91: aload_2
      92: aload         4
      94: aload_0
      95: invokeinterface #214,  2          // InterfaceMethod org/eclipse/ui/model/IWorkbenchAdapter.getLabel:(Ljava/lang/Object;)Ljava/lang/String;
     100: invokevirtual #191                // Method java/lang/StringBuilder.append:(Ljava/lang/String;)Ljava/lang/StringBuilder;
     103: pop
     104: iinc          3, 1
     107: iload_3
     108: aload_1
     109: arraylength
     110: if_icmplt     42
     113: aload_2
     114: invokevirtual #190                // Method java/lang/StringBuilder.toString:()Ljava/lang/String;
     117: areturn

  public org.eclipse.ui.internal.dialogs.PropertyDialog(org.eclipse.swt.widgets.Shell, org.eclipse.jface.preference.PreferenceManager, org.eclipse.jface.viewers.ISelection);
    Code:
       0: aload_0
       1: aload_1
       2: aload_2
       3: invokespecial #198                // Method org/eclipse/ui/internal/dialogs/FilteredPreferenceDialog."<init>":(Lorg/eclipse/swt/widgets/Shell;Lorg/eclipse/jface/preference/PreferenceManager;)V
       6: aload_0
       7: aload_3
       8: invokevirtual #201                // Method setSelection:(Lorg/eclipse/jface/viewers/ISelection;)V
      11: return

  public org.eclipse.jface.viewers.ISelection getSelection();
    Code:
       0: aload_0
       1: getfield      #186                // Field selection:Lorg/eclipse/jface/viewers/ISelection;
       4: areturn

  public void setSelection(org.eclipse.jface.viewers.ISelection);
    Code:
       0: aload_0
       1: aload_1
       2: putfield      #186                // Field selection:Lorg/eclipse/jface/viewers/ISelection;
       5: return

  protected java.lang.String getSelectedNodePreference();
    Code:
       0: getstatic     #185                // Field lastPropertyId:Ljava/lang/String;
       3: areturn

  protected void setSelectedNodePreference(java.lang.String);
    Code:
       0: aload_1
       1: putstatic     #185                // Field lastPropertyId:Ljava/lang/String;
       4: return

  protected java.lang.String getContributionType();
    Code:
       0: ldc           #5                  // String property
       2: areturn
}
