Compiled from "ShowViewDialog.java"
public class org.eclipse.ui.internal.dialogs.ShowViewDialog extends org.eclipse.jface.dialogs.Dialog implements org.eclipse.jface.viewers.ISelectionChangedListener,org.eclipse.jface.viewers.IDoubleClickListener {
  private static final java.lang.String DIALOG_SETTING_SECTION_NAME;

  private static final int LIST_HEIGHT;

  private static final int LIST_WIDTH;

  private static final java.lang.String STORE_EXPANDED_CATEGORIES_ID;

  private static final java.lang.String STORE_SELECTED_VIEW_ID;

  private org.eclipse.ui.dialogs.FilteredTree filteredTree;

  private org.eclipse.swt.graphics.Color dimmedForeground;

  private org.eclipse.swt.widgets.Button okButton;

  private org.eclipse.e4.ui.model.application.MApplication application;

  private org.eclipse.e4.ui.model.application.descriptor.basic.MPartDescriptor[] viewDescs;

  private org.eclipse.swt.widgets.Label descriptionHint;

  private org.eclipse.e4.core.contexts.IEclipseContext context;

  private org.eclipse.e4.ui.workbench.modeling.EModelService modelService;

  private org.eclipse.e4.ui.model.application.ui.basic.MWindow window;

  private org.eclipse.e4.ui.workbench.modeling.EPartService partService;

  public org.eclipse.ui.internal.dialogs.ShowViewDialog(org.eclipse.swt.widgets.Shell, org.eclipse.e4.ui.model.application.MApplication, org.eclipse.e4.ui.model.application.ui.basic.MWindow, org.eclipse.e4.ui.workbench.modeling.EModelService, org.eclipse.e4.ui.workbench.modeling.EPartService, org.eclipse.e4.core.contexts.IEclipseContext);
    Code:
       0: aload_0
       1: aload_1
       2: invokespecial #534                // Method org/eclipse/jface/dialogs/Dialog."<init>":(Lorg/eclipse/swt/widgets/Shell;)V
       5: aload_0
       6: iconst_0
       7: anewarray     #249                // class org/eclipse/e4/ui/model/application/descriptor/basic/MPartDescriptor
      10: putfield      #512                // Field viewDescs:[Lorg/eclipse/e4/ui/model/application/descriptor/basic/MPartDescriptor;
      13: aload_0
      14: aload_2
      15: putfield      #511                // Field application:Lorg/eclipse/e4/ui/model/application/MApplication;
      18: aload_0
      19: aload_3
      20: putfield      #513                // Field window:Lorg/eclipse/e4/ui/model/application/ui/basic/MWindow;
      23: aload_0
      24: aload         4
      26: putfield      #514                // Field modelService:Lorg/eclipse/e4/ui/workbench/modeling/EModelService;
      29: aload_0
      30: aload         5
      32: putfield      #515                // Field partService:Lorg/eclipse/e4/ui/workbench/modeling/EPartService;
      35: aload_0
      36: aload         6
      38: putfield      #510                // Field context:Lorg/eclipse/e4/core/contexts/IEclipseContext;
      41: return

  protected void buttonPressed(int);
    Code:
       0: iload_1
       1: ifne          8
       4: aload_0
       5: invokevirtual #586                // Method saveWidgetValues:()V
       8: aload_0
       9: iload_1
      10: invokespecial #533                // Method org/eclipse/jface/dialogs/Dialog.buttonPressed:(I)V
      13: return

  protected void cancelPressed();
    Code:
       0: aload_0
       1: iconst_0
       2: anewarray     #249                // class org/eclipse/e4/ui/model/application/descriptor/basic/MPartDescriptor
       5: putfield      #512                // Field viewDescs:[Lorg/eclipse/e4/ui/model/application/descriptor/basic/MPartDescriptor;
       8: aload_0
       9: invokespecial #532                // Method org/eclipse/jface/dialogs/Dialog.cancelPressed:()V
      12: return

  protected void configureShell(org.eclipse.swt.widgets.Shell);
    Code:
       0: aload_0
       1: aload_1
       2: invokespecial #535                // Method org/eclipse/jface/dialogs/Dialog.configureShell:(Lorg/eclipse/swt/widgets/Shell;)V
       5: aload_1
       6: getstatic     #509                // Field org/eclipse/ui/internal/WorkbenchMessages.ShowView_shellTitle:Ljava/lang/String;
       9: invokevirtual #577                // Method org/eclipse/swt/widgets/Shell.setText:(Ljava/lang/String;)V
      12: aload_0
      13: getfield      #510                // Field context:Lorg/eclipse/e4/core/contexts/IEclipseContext;
      16: ldc           #7                  // class org/eclipse/e4/ui/services/help/EHelpService
      18: invokeinterface #611,  2          // InterfaceMethod org/eclipse/e4/core/contexts/IEclipseContext.get:(Ljava/lang/Class;)Ljava/lang/Object;
      23: checkcast     #7                  // class org/eclipse/e4/ui/services/help/EHelpService
      26: astore_2
      27: aload_2
      28: ifnull        40
      31: aload_2
      32: aload_1
      33: ldc           #6                  // String org.eclipse.ui.show_view_dialog_context
      35: invokeinterface #615,  3          // InterfaceMethod org/eclipse/e4/ui/services/help/EHelpService.setHelp:(Ljava/lang/Object;Ljava/lang/String;)V
      40: return

  protected void createButtonsForButtonBar(org.eclipse.swt.widgets.Composite);
    Code:
       0: aload_0
       1: aload_0
       2: aload_1
       3: iconst_0
       4: getstatic     #507                // Field org/eclipse/ui/internal/WorkbenchMessages.ShowView_open_button_label:Ljava/lang/String;
       7: iconst_1
       8: invokevirtual #600                // Method createButton:(Lorg/eclipse/swt/widgets/Composite;ILjava/lang/String;Z)Lorg/eclipse/swt/widgets/Button;
      11: putfield      #517                // Field okButton:Lorg/eclipse/swt/widgets/Button;
      14: aload_0
      15: aload_1
      16: iconst_1
      17: ldc           #5                  // String cancel
      19: invokestatic  #537                // Method org/eclipse/jface/resource/JFaceResources.getString:(Ljava/lang/String;)Ljava/lang/String;
      22: iconst_0
      23: invokevirtual #600                // Method createButton:(Lorg/eclipse/swt/widgets/Composite;ILjava/lang/String;Z)Lorg/eclipse/swt/widgets/Button;
      26: pop
      27: aload_0
      28: invokevirtual #587                // Method updateButtons:()V
      31: return

  protected org.eclipse.swt.widgets.Control createDialogArea(org.eclipse.swt.widgets.Composite);
    Code:
       0: aload_0
       1: aload_1
       2: invokespecial #536                // Method org/eclipse/jface/dialogs/Dialog.createDialogArea:(Lorg/eclipse/swt/widgets/Composite;)Lorg/eclipse/swt/widgets/Control;
       5: checkcast     #267                // class org/eclipse/swt/widgets/Composite
       8: astore_2
       9: aload_2
      10: aload_1
      11: invokevirtual #563                // Method org/eclipse/swt/widgets/Composite.getFont:()Lorg/eclipse/swt/graphics/Font;
      14: invokevirtual #564                // Method org/eclipse/swt/widgets/Composite.setFont:(Lorg/eclipse/swt/graphics/Font;)V
      17: aload_0
      18: aload_2
      19: invokevirtual #596                // Method createFilteredTreeViewer:(Lorg/eclipse/swt/widgets/Composite;)V
      22: aload_0
      23: aload_0
      24: getfield      #519                // Field filteredTree:Lorg/eclipse/ui/dialogs/FilteredTree;
      27: invokevirtual #598                // Method layoutTopControl:(Lorg/eclipse/swt/widgets/Control;)V
      30: aload_0
      31: new           #270                // class org/eclipse/swt/widgets/Label
      34: dup
      35: aload_2
      36: bipush        64
      38: invokespecial #576                // Method org/eclipse/swt/widgets/Label."<init>":(Lorg/eclipse/swt/widgets/Composite;I)V
      41: putfield      #518                // Field descriptionHint:Lorg/eclipse/swt/widgets/Label;
      44: aload_0
      45: getfield      #518                // Field descriptionHint:Lorg/eclipse/swt/widgets/Label;
      48: getstatic     #508                // Field org/eclipse/ui/internal/WorkbenchMessages.ShowView_selectViewHelp:Ljava/lang/String;
      51: invokevirtual #575                // Method org/eclipse/swt/widgets/Label.setText:(Ljava/lang/String;)V
      54: aload_0
      55: getfield      #518                // Field descriptionHint:Lorg/eclipse/swt/widgets/Label;
      58: new           #265                // class org/eclipse/swt/layout/GridData
      61: dup
      62: iconst_4
      63: ldc           #1                  // int 16777216
      65: iconst_1
      66: iconst_0
      67: invokespecial #561                // Method org/eclipse/swt/layout/GridData."<init>":(IIZZ)V
      70: invokevirtual #574                // Method org/eclipse/swt/widgets/Label.setLayoutData:(Ljava/lang/Object;)V
      73: aload_0
      74: getfield      #518                // Field descriptionHint:Lorg/eclipse/swt/widgets/Label;
      77: iconst_0
      78: invokevirtual #573                // Method org/eclipse/swt/widgets/Label.setVisible:(Z)V
      81: aload_0
      82: invokevirtual #585                // Method restoreWidgetValues:()V
      85: aload_2
      86: invokestatic  #597                // Method applyDialogFont:(Lorg/eclipse/swt/widgets/Control;)V
      89: aload_2
      90: areturn

  private static org.eclipse.swt.graphics.RGB blend(org.eclipse.swt.graphics.RGB, org.eclipse.swt.graphics.RGB, int);
    Code:
       0: aload_0
       1: getfield      #503                // Field org/eclipse/swt/graphics/RGB.red:I
       4: aload_1
       5: getfield      #503                // Field org/eclipse/swt/graphics/RGB.red:I
       8: iload_2
       9: invokestatic  #590                // Method blend:(III)I
      12: istore_3
      13: aload_0
      14: getfield      #502                // Field org/eclipse/swt/graphics/RGB.green:I
      17: aload_1
      18: getfield      #502                // Field org/eclipse/swt/graphics/RGB.green:I
      21: iload_2
      22: invokestatic  #590                // Method blend:(III)I
      25: istore        4
      27: aload_0
      28: getfield      #501                // Field org/eclipse/swt/graphics/RGB.blue:I
      31: aload_1
      32: getfield      #501                // Field org/eclipse/swt/graphics/RGB.blue:I
      35: iload_2
      36: invokestatic  #590                // Method blend:(III)I
      39: istore        5
      41: new           #264                // class org/eclipse/swt/graphics/RGB
      44: dup
      45: iload_3
      46: iload         4
      48: iload         5
      50: invokespecial #559                // Method org/eclipse/swt/graphics/RGB."<init>":(III)V
      53: areturn

  private static int blend(int, int, int);
    Code:
       0: iload_2
       1: iload_0
       2: imul
       3: bipush        100
       5: iload_2
       6: isub
       7: iload_1
       8: imul
       9: iadd
      10: bipush        100
      12: idiv
      13: istore_3
      14: sipush        255
      17: iload_3
      18: invokestatic  #520                // Method java/lang/Math.min:(II)I
      21: ireturn

  private void createFilteredTreeViewer(org.eclipse.swt.widgets.Composite);
    Code:
       0: new           #283                // class org/eclipse/ui/internal/dialogs/ViewPatternFilter
       3: dup
       4: invokespecial #607                // Method org/eclipse/ui/internal/dialogs/ViewPatternFilter."<init>":()V
       7: astore_2
       8: sipush        2818
      11: istore_3
      12: aload_0
      13: new           #273                // class org/eclipse/ui/dialogs/FilteredTree
      16: dup
      17: aload_1
      18: iload_3
      19: aload_2
      20: iconst_1
      21: iconst_1
      22: invokespecial #584                // Method org/eclipse/ui/dialogs/FilteredTree."<init>":(Lorg/eclipse/swt/widgets/Composite;ILorg/eclipse/ui/dialogs/PatternFilter;ZZ)V
      25: putfield      #519                // Field filteredTree:Lorg/eclipse/ui/dialogs/FilteredTree;
      28: aload_0
      29: getfield      #519                // Field filteredTree:Lorg/eclipse/ui/dialogs/FilteredTree;
      32: iconst_1
      33: invokevirtual #579                // Method org/eclipse/ui/dialogs/FilteredTree.setQuickSelectionMode:(Z)V
      36: aload_0
      37: getfield      #519                // Field filteredTree:Lorg/eclipse/ui/dialogs/FilteredTree;
      40: aload_1
      41: invokevirtual #565                // Method org/eclipse/swt/widgets/Composite.getDisplay:()Lorg/eclipse/swt/widgets/Display;
      44: bipush        22
      46: invokevirtual #571                // Method org/eclipse/swt/widgets/Display.getSystemColor:(I)Lorg/eclipse/swt/graphics/Color;
      49: invokevirtual #581                // Method org/eclipse/ui/dialogs/FilteredTree.setBackground:(Lorg/eclipse/swt/graphics/Color;)V
      52: aload_0
      53: getfield      #519                // Field filteredTree:Lorg/eclipse/ui/dialogs/FilteredTree;
      56: invokevirtual #580                // Method org/eclipse/ui/dialogs/FilteredTree.getViewer:()Lorg/eclipse/jface/viewers/TreeViewer;
      59: astore        4
      61: aload         4
      63: invokevirtual #556                // Method org/eclipse/jface/viewers/TreeViewer.getControl:()Lorg/eclipse/swt/widgets/Control;
      66: astore        5
      68: aload         5
      70: invokevirtual #569                // Method org/eclipse/swt/widgets/Control.getForeground:()Lorg/eclipse/swt/graphics/Color;
      73: invokevirtual #557                // Method org/eclipse/swt/graphics/Color.getRGB:()Lorg/eclipse/swt/graphics/RGB;
      76: aload         5
      78: invokevirtual #568                // Method org/eclipse/swt/widgets/Control.getBackground:()Lorg/eclipse/swt/graphics/Color;
      81: invokevirtual #557                // Method org/eclipse/swt/graphics/Color.getRGB:()Lorg/eclipse/swt/graphics/RGB;
      84: bipush        60
      86: invokestatic  #599                // Method blend:(Lorg/eclipse/swt/graphics/RGB;Lorg/eclipse/swt/graphics/RGB;I)Lorg/eclipse/swt/graphics/RGB;
      89: astore        6
      91: aload_0
      92: new           #263                // class org/eclipse/swt/graphics/Color
      95: dup
      96: aload         5
      98: invokevirtual #570                // Method org/eclipse/swt/widgets/Control.getDisplay:()Lorg/eclipse/swt/widgets/Display;
     101: aload         6
     103: invokespecial #558                // Method org/eclipse/swt/graphics/Color."<init>":(Lorg/eclipse/swt/graphics/Device;Lorg/eclipse/swt/graphics/RGB;)V
     106: putfield      #516                // Field dimmedForeground:Lorg/eclipse/swt/graphics/Color;
     109: aload         4
     111: new           #282                // class org/eclipse/ui/internal/dialogs/ViewLabelProvider
     114: dup
     115: aload_0
     116: getfield      #510                // Field context:Lorg/eclipse/e4/core/contexts/IEclipseContext;
     119: aload_0
     120: getfield      #514                // Field modelService:Lorg/eclipse/e4/ui/workbench/modeling/EModelService;
     123: aload_0
     124: getfield      #515                // Field partService:Lorg/eclipse/e4/ui/workbench/modeling/EPartService;
     127: aload_0
     128: getfield      #513                // Field window:Lorg/eclipse/e4/ui/model/application/ui/basic/MWindow;
     131: aload_0
     132: getfield      #516                // Field dimmedForeground:Lorg/eclipse/swt/graphics/Color;
     135: invokespecial #606                // Method org/eclipse/ui/internal/dialogs/ViewLabelProvider."<init>":(Lorg/eclipse/e4/core/contexts/IEclipseContext;Lorg/eclipse/e4/ui/workbench/modeling/EModelService;Lorg/eclipse/e4/ui/workbench/modeling/EPartService;Lorg/eclipse/e4/ui/model/application/ui/basic/MWindow;Lorg/eclipse/swt/graphics/Color;)V
     138: invokevirtual #548                // Method org/eclipse/jface/viewers/TreeViewer.setLabelProvider:(Lorg/eclipse/jface/viewers/IBaseLabelProvider;)V
     141: aload         4
     143: new           #281                // class org/eclipse/ui/internal/dialogs/ViewContentProvider
     146: dup
     147: aload_0
     148: getfield      #511                // Field application:Lorg/eclipse/e4/ui/model/application/MApplication;
     151: invokespecial #605                // Method org/eclipse/ui/internal/dialogs/ViewContentProvider."<init>":(Lorg/eclipse/e4/ui/model/application/MApplication;)V
     154: invokevirtual #550                // Method org/eclipse/jface/viewers/TreeViewer.setContentProvider:(Lorg/eclipse/jface/viewers/IContentProvider;)V
     157: aload         4
     159: new           #280                // class org/eclipse/ui/internal/dialogs/ViewComparator
     162: dup
     163: invokespecial #604                // Method org/eclipse/ui/internal/dialogs/ViewComparator."<init>":()V
     166: invokevirtual #555                // Method org/eclipse/jface/viewers/TreeViewer.setComparator:(Lorg/eclipse/jface/viewers/ViewerComparator;)V
     169: aload         4
     171: aload_0
     172: getfield      #511                // Field application:Lorg/eclipse/e4/ui/model/application/MApplication;
     175: invokevirtual #543                // Method org/eclipse/jface/viewers/TreeViewer.setInput:(Ljava/lang/Object;)V
     178: aload         4
     180: aload_0
     181: invokevirtual #553                // Method org/eclipse/jface/viewers/TreeViewer.addSelectionChangedListener:(Lorg/eclipse/jface/viewers/ISelectionChangedListener;)V
     184: aload         4
     186: aload_0
     187: invokevirtual #551                // Method org/eclipse/jface/viewers/TreeViewer.addDoubleClickListener:(Lorg/eclipse/jface/viewers/IDoubleClickListener;)V
     190: aload         4
     192: invokevirtual #556                // Method org/eclipse/jface/viewers/TreeViewer.getControl:()Lorg/eclipse/swt/widgets/Control;
     195: new           #277                // class org/eclipse/ui/internal/dialogs/ShowViewDialog$1
     198: dup
     199: aload_0
     200: invokespecial #601                // Method org/eclipse/ui/internal/dialogs/ShowViewDialog$1."<init>":(Lorg/eclipse/ui/internal/dialogs/ShowViewDialog;)V
     203: invokevirtual #567                // Method org/eclipse/swt/widgets/Control.addKeyListener:(Lorg/eclipse/swt/events/KeyListener;)V
     206: aload_0
     207: aload_0
     208: getfield      #519                // Field filteredTree:Lorg/eclipse/ui/dialogs/FilteredTree;
     211: invokevirtual #580                // Method org/eclipse/ui/dialogs/FilteredTree.getViewer:()Lorg/eclipse/jface/viewers/TreeViewer;
     214: invokevirtual #595                // Method hasAtMostOneView:(Lorg/eclipse/jface/viewers/TreeViewer;)Z
     217: ifeq          240
     220: aload_0
     221: getfield      #519                // Field filteredTree:Lorg/eclipse/ui/dialogs/FilteredTree;
     224: invokevirtual #583                // Method org/eclipse/ui/dialogs/FilteredTree.getFilterControl:()Lorg/eclipse/swt/widgets/Text;
     227: astore        7
     229: aload         7
     231: ifnull        240
     234: aload         7
     236: iconst_0
     237: invokevirtual #578                // Method org/eclipse/swt/widgets/Text.setEnabled:(Z)V
     240: return

  private boolean hasAtMostOneView(org.eclipse.jface.viewers.TreeViewer);
    Code:
       0: aload_1
       1: invokevirtual #549                // Method org/eclipse/jface/viewers/TreeViewer.getContentProvider:()Lorg/eclipse/jface/viewers/IContentProvider;
       4: checkcast     #257                // class org/eclipse/jface/viewers/ITreeContentProvider
       7: astore_2
       8: aload_2
       9: aload_1
      10: invokevirtual #541                // Method org/eclipse/jface/viewers/TreeViewer.getInput:()Ljava/lang/Object;
      13: invokeinterface #625,  2          // InterfaceMethod org/eclipse/jface/viewers/ITreeContentProvider.getElements:(Ljava/lang/Object;)[Ljava/lang/Object;
      18: astore_3
      19: aload_3
      20: arraylength
      21: iconst_1
      22: if_icmpgt     50
      25: aload_3
      26: arraylength
      27: ifne          32
      30: iconst_1
      31: ireturn
      32: aload_2
      33: aload_3
      34: iconst_0
      35: aaload
      36: invokeinterface #624,  2          // InterfaceMethod org/eclipse/jface/viewers/ITreeContentProvider.hasChildren:(Ljava/lang/Object;)Z
      41: ifeq          48
      44: iconst_0
      45: goto          49
      48: iconst_1
      49: ireturn
      50: iconst_0
      51: ireturn

  public void doubleClick(org.eclipse.jface.viewers.DoubleClickEvent);
    Code:
       0: aload_1
       1: invokevirtual #538                // Method org/eclipse/jface/viewers/DoubleClickEvent.getSelection:()Lorg/eclipse/jface/viewers/ISelection;
       4: checkcast     #256                // class org/eclipse/jface/viewers/IStructuredSelection
       7: astore_2
       8: aload_2
       9: invokeinterface #622,  1          // InterfaceMethod org/eclipse/jface/viewers/IStructuredSelection.getFirstElement:()Ljava/lang/Object;
      14: astore_3
      15: aload_0
      16: getfield      #519                // Field filteredTree:Lorg/eclipse/ui/dialogs/FilteredTree;
      19: invokevirtual #580                // Method org/eclipse/ui/dialogs/FilteredTree.getViewer:()Lorg/eclipse/jface/viewers/TreeViewer;
      22: aload_3
      23: invokevirtual #545                // Method org/eclipse/jface/viewers/TreeViewer.isExpandable:(Ljava/lang/Object;)Z
      26: ifeq          62
      29: aload_0
      30: getfield      #519                // Field filteredTree:Lorg/eclipse/ui/dialogs/FilteredTree;
      33: invokevirtual #580                // Method org/eclipse/ui/dialogs/FilteredTree.getViewer:()Lorg/eclipse/jface/viewers/TreeViewer;
      36: aload_3
      37: aload_0
      38: getfield      #519                // Field filteredTree:Lorg/eclipse/ui/dialogs/FilteredTree;
      41: invokevirtual #580                // Method org/eclipse/ui/dialogs/FilteredTree.getViewer:()Lorg/eclipse/jface/viewers/TreeViewer;
      44: aload_3
      45: invokevirtual #544                // Method org/eclipse/jface/viewers/TreeViewer.getExpandedState:(Ljava/lang/Object;)Z
      48: ifeq          55
      51: iconst_0
      52: goto          56
      55: iconst_1
      56: invokevirtual #546                // Method org/eclipse/jface/viewers/TreeViewer.setExpandedState:(Ljava/lang/Object;Z)V
      59: goto          84
      62: aload_0
      63: getfield      #512                // Field viewDescs:[Lorg/eclipse/e4/ui/model/application/descriptor/basic/MPartDescriptor;
      66: arraylength
      67: ifle          84
      70: aload_0
      71: invokevirtual #586                // Method saveWidgetValues:()V
      74: aload_0
      75: iconst_0
      76: invokevirtual #589                // Method setReturnCode:(I)V
      79: aload_0
      80: invokevirtual #588                // Method close:()Z
      83: pop
      84: return

  protected org.eclipse.jface.dialogs.IDialogSettings getDialogSettings();
    Code:
       0: invokestatic  #529                // Method org/eclipse/e4/ui/internal/workbench/swt/WorkbenchSWTActivator.getDefault:()Lorg/eclipse/e4/ui/internal/workbench/swt/WorkbenchSWTActivator;
       3: invokevirtual #530                // Method org/eclipse/e4/ui/internal/workbench/swt/WorkbenchSWTActivator.getDialogSettings:()Lorg/eclipse/jface/dialogs/IDialogSettings;
       6: astore_1
       7: aload_1
       8: ldc           #2                  // String ShowViewDialog
      10: invokeinterface #621,  2          // InterfaceMethod org/eclipse/jface/dialogs/IDialogSettings.getSection:(Ljava/lang/String;)Lorg/eclipse/jface/dialogs/IDialogSettings;
      15: astore_2
      16: aload_2
      17: ifnonnull     29
      20: aload_1
      21: ldc           #2                  // String ShowViewDialog
      23: invokeinterface #620,  2          // InterfaceMethod org/eclipse/jface/dialogs/IDialogSettings.addNewSection:(Ljava/lang/String;)Lorg/eclipse/jface/dialogs/IDialogSettings;
      28: astore_2
      29: aload_2
      30: areturn

  public org.eclipse.e4.ui.model.application.descriptor.basic.MPartDescriptor[] getSelection();
    Code:
       0: aload_0
       1: getfield      #512                // Field viewDescs:[Lorg/eclipse/e4/ui/model/application/descriptor/basic/MPartDescriptor;
       4: areturn

  private void layoutTopControl(org.eclipse.swt.widgets.Control);
    Code:
       0: new           #265                // class org/eclipse/swt/layout/GridData
       3: dup
       4: sipush        1808
       7: invokespecial #560                // Method org/eclipse/swt/layout/GridData."<init>":(I)V
      10: astore_2
      11: aload_2
      12: sipush        250
      15: putfield      #505                // Field org/eclipse/swt/layout/GridData.widthHint:I
      18: aload_2
      19: sipush        300
      22: putfield      #504                // Field org/eclipse/swt/layout/GridData.heightHint:I
      25: aload_1
      26: aload_2
      27: invokevirtual #566                // Method org/eclipse/swt/widgets/Control.setLayoutData:(Ljava/lang/Object;)V
      30: return

  protected void restoreWidgetValues();
    Code:
       0: aload_0
       1: invokevirtual #593                // Method getDialogSettings:()Lorg/eclipse/jface/dialogs/IDialogSettings;
       4: astore_1
       5: aload_1
       6: ldc           #3                  // String ShowViewDialog.STORE_EXPANDED_CATEGORIES_ID
       8: invokeinterface #617,  2          // InterfaceMethod org/eclipse/jface/dialogs/IDialogSettings.getArray:(Ljava/lang/String;)[Ljava/lang/String;
      13: astore_2
      14: aload_2
      15: ifnonnull     19
      18: return
      19: aload_2
      20: arraylength
      21: ifle          35
      24: aload_0
      25: getfield      #519                // Field filteredTree:Lorg/eclipse/ui/dialogs/FilteredTree;
      28: invokevirtual #580                // Method org/eclipse/ui/dialogs/FilteredTree.getViewer:()Lorg/eclipse/jface/viewers/TreeViewer;
      31: aload_2
      32: invokevirtual #547                // Method org/eclipse/jface/viewers/TreeViewer.setExpandedElements:([Ljava/lang/Object;)V
      35: aload_1
      36: ldc           #4                  // String ShowViewDialog.STORE_SELECTED_VIEW_ID
      38: invokeinterface #616,  2          // InterfaceMethod org/eclipse/jface/dialogs/IDialogSettings.get:(Ljava/lang/String;)Ljava/lang/String;
      43: astore_3
      44: aload_3
      45: ifnull        130
      48: aload_0
      49: getfield      #511                // Field application:Lorg/eclipse/e4/ui/model/application/MApplication;
      52: invokeinterface #612,  1          // InterfaceMethod org/eclipse/e4/ui/model/application/MApplication.getDescriptors:()Ljava/util/List;
      57: astore        4
      59: aload         4
      61: invokeinterface #610,  1          // InterfaceMethod java/util/List.iterator:()Ljava/util/Iterator;
      66: astore        6
      68: goto          120
      71: aload         6
      73: invokeinterface #609,  1          // InterfaceMethod java/util/Iterator.next:()Ljava/lang/Object;
      78: checkcast     #249                // class org/eclipse/e4/ui/model/application/descriptor/basic/MPartDescriptor
      81: astore        5
      83: aload_3
      84: aload         5
      86: invokeinterface #613,  1          // InterfaceMethod org/eclipse/e4/ui/model/application/descriptor/basic/MPartDescriptor.getElementId:()Ljava/lang/String;
      91: invokevirtual #524                // Method java/lang/String.equals:(Ljava/lang/Object;)Z
      94: ifeq          120
      97: aload_0
      98: getfield      #519                // Field filteredTree:Lorg/eclipse/ui/dialogs/FilteredTree;
     101: invokevirtual #580                // Method org/eclipse/ui/dialogs/FilteredTree.getViewer:()Lorg/eclipse/jface/viewers/TreeViewer;
     104: new           #260                // class org/eclipse/jface/viewers/StructuredSelection
     107: dup
     108: aload         5
     110: invokespecial #540                // Method org/eclipse/jface/viewers/StructuredSelection."<init>":(Ljava/lang/Object;)V
     113: iconst_1
     114: invokevirtual #552                // Method org/eclipse/jface/viewers/TreeViewer.setSelection:(Lorg/eclipse/jface/viewers/ISelection;Z)V
     117: goto          130
     120: aload         6
     122: invokeinterface #608,  1          // InterfaceMethod java/util/Iterator.hasNext:()Z
     127: ifne          71
     130: return

  protected void saveWidgetValues();
    Code:
       0: aload_0
       1: invokevirtual #593                // Method getDialogSettings:()Lorg/eclipse/jface/dialogs/IDialogSettings;
       4: astore_1
       5: aload_0
       6: getfield      #519                // Field filteredTree:Lorg/eclipse/ui/dialogs/FilteredTree;
       9: invokevirtual #580                // Method org/eclipse/ui/dialogs/FilteredTree.getViewer:()Lorg/eclipse/jface/viewers/TreeViewer;
      12: invokevirtual #542                // Method org/eclipse/jface/viewers/TreeViewer.getExpandedElements:()[Ljava/lang/Object;
      15: astore_2
      16: aload_2
      17: arraylength
      18: anewarray     #241                // class java/lang/String
      21: astore_3
      22: iconst_0
      23: istore        4
      25: goto          71
      28: aload_2
      29: iload         4
      31: aaload
      32: instanceof    #249                // class org/eclipse/e4/ui/model/application/descriptor/basic/MPartDescriptor
      35: ifeq          57
      38: aload_3
      39: iload         4
      41: aload_2
      42: iload         4
      44: aaload
      45: checkcast     #249                // class org/eclipse/e4/ui/model/application/descriptor/basic/MPartDescriptor
      48: invokeinterface #613,  1          // InterfaceMethod org/eclipse/e4/ui/model/application/descriptor/basic/MPartDescriptor.getElementId:()Ljava/lang/String;
      53: aastore
      54: goto          68
      57: aload_3
      58: iload         4
      60: aload_2
      61: iload         4
      63: aaload
      64: invokevirtual #521                // Method java/lang/Object.toString:()Ljava/lang/String;
      67: aastore
      68: iinc          4, 1
      71: iload         4
      73: aload_2
      74: arraylength
      75: if_icmplt     28
      78: aload_1
      79: ldc           #3                  // String ShowViewDialog.STORE_EXPANDED_CATEGORIES_ID
      81: aload_3
      82: invokeinterface #619,  3          // InterfaceMethod org/eclipse/jface/dialogs/IDialogSettings.put:(Ljava/lang/String;[Ljava/lang/String;)V
      87: ldc_w         #236                // String
      90: astore        4
      92: aload_0
      93: getfield      #512                // Field viewDescs:[Lorg/eclipse/e4/ui/model/application/descriptor/basic/MPartDescriptor;
      96: arraylength
      97: ifle          113
     100: aload_0
     101: getfield      #512                // Field viewDescs:[Lorg/eclipse/e4/ui/model/application/descriptor/basic/MPartDescriptor;
     104: iconst_0
     105: aaload
     106: invokeinterface #613,  1          // InterfaceMethod org/eclipse/e4/ui/model/application/descriptor/basic/MPartDescriptor.getElementId:()Ljava/lang/String;
     111: astore        4
     113: aload_1
     114: ldc           #4                  // String ShowViewDialog.STORE_SELECTED_VIEW_ID
     116: aload         4
     118: invokeinterface #618,  3          // InterfaceMethod org/eclipse/jface/dialogs/IDialogSettings.put:(Ljava/lang/String;Ljava/lang/String;)V
     123: return

  public void selectionChanged(org.eclipse.jface.viewers.SelectionChangedEvent);
    Code:
       0: aload_0
       1: aload_1
       2: invokevirtual #594                // Method updateSelection:(Lorg/eclipse/jface/viewers/SelectionChangedEvent;)V
       5: aload_0
       6: invokevirtual #587                // Method updateButtons:()V
       9: ldc_w         #236                // String
      12: astore_2
      13: aload_0
      14: getfield      #512                // Field viewDescs:[Lorg/eclipse/e4/ui/model/application/descriptor/basic/MPartDescriptor;
      17: arraylength
      18: ifle          48
      21: aload_0
      22: getfield      #512                // Field viewDescs:[Lorg/eclipse/e4/ui/model/application/descriptor/basic/MPartDescriptor;
      25: iconst_0
      26: aaload
      27: invokeinterface #614,  1          // InterfaceMethod org/eclipse/e4/ui/model/application/descriptor/basic/MPartDescriptor.getTooltip:()Ljava/lang/String;
      32: astore_2
      33: aload_2
      34: aload_0
      35: getfield      #512                // Field viewDescs:[Lorg/eclipse/e4/ui/model/application/descriptor/basic/MPartDescriptor;
      38: iconst_0
      39: aaload
      40: aload_0
      41: getfield      #510                // Field context:Lorg/eclipse/e4/core/contexts/IEclipseContext;
      44: invokestatic  #531                // Method org/eclipse/e4/ui/model/LocalizationHelper.getLocalized:(Ljava/lang/String;Lorg/eclipse/e4/ui/model/application/MApplicationElement;Lorg/eclipse/e4/core/contexts/IEclipseContext;)Ljava/lang/String;
      47: astore_2
      48: aload_2
      49: ifnull        63
      52: aload_2
      53: invokevirtual #522                // Method java/lang/String.length:()I
      56: ifle          63
      59: iconst_1
      60: goto          64
      63: iconst_0
      64: istore_3
      65: aload_0
      66: getfield      #518                // Field descriptionHint:Lorg/eclipse/swt/widgets/Label;
      69: aload_0
      70: getfield      #512                // Field viewDescs:[Lorg/eclipse/e4/ui/model/application/descriptor/basic/MPartDescriptor;
      73: arraylength
      74: iconst_1
      75: if_icmpne     86
      78: iload_3
      79: ifeq          86
      82: iconst_1
      83: goto          87
      86: iconst_0
      87: invokevirtual #573                // Method org/eclipse/swt/widgets/Label.setVisible:(Z)V
      90: return

  protected void updateButtons();
    Code:
       0: aload_0
       1: getfield      #517                // Field okButton:Lorg/eclipse/swt/widgets/Button;
       4: ifnull        27
       7: aload_0
       8: getfield      #517                // Field okButton:Lorg/eclipse/swt/widgets/Button;
      11: aload_0
      12: invokevirtual #592                // Method getSelection:()[Lorg/eclipse/e4/ui/model/application/descriptor/basic/MPartDescriptor;
      15: arraylength
      16: ifle          23
      19: iconst_1
      20: goto          24
      23: iconst_0
      24: invokevirtual #562                // Method org/eclipse/swt/widgets/Button.setEnabled:(Z)V
      27: return

  protected void updateSelection(org.eclipse.jface.viewers.SelectionChangedEvent);
    Code:
       0: new           #242                // class java/util/ArrayList
       3: dup
       4: invokespecial #526                // Method java/util/ArrayList."<init>":()V
       7: astore_2
       8: aload_1
       9: invokevirtual #539                // Method org/eclipse/jface/viewers/SelectionChangedEvent.getStructuredSelection:()Lorg/eclipse/jface/viewers/IStructuredSelection;
      12: invokeinterface #623,  1          // InterfaceMethod org/eclipse/jface/viewers/IStructuredSelection.iterator:()Ljava/util/Iterator;
      17: astore        4
      19: goto          46
      22: aload         4
      24: invokeinterface #609,  1          // InterfaceMethod java/util/Iterator.next:()Ljava/lang/Object;
      29: astore_3
      30: aload_3
      31: instanceof    #249                // class org/eclipse/e4/ui/model/application/descriptor/basic/MPartDescriptor
      34: ifeq          46
      37: aload_2
      38: aload_3
      39: checkcast     #249                // class org/eclipse/e4/ui/model/application/descriptor/basic/MPartDescriptor
      42: invokevirtual #527                // Method java/util/ArrayList.add:(Ljava/lang/Object;)Z
      45: pop
      46: aload         4
      48: invokeinterface #608,  1          // InterfaceMethod java/util/Iterator.hasNext:()Z
      53: ifne          22
      56: aload_0
      57: aload_2
      58: invokevirtual #525                // Method java/util/ArrayList.size:()I
      61: anewarray     #249                // class org/eclipse/e4/ui/model/application/descriptor/basic/MPartDescriptor
      64: putfield      #512                // Field viewDescs:[Lorg/eclipse/e4/ui/model/application/descriptor/basic/MPartDescriptor;
      67: aload_2
      68: aload_0
      69: getfield      #512                // Field viewDescs:[Lorg/eclipse/e4/ui/model/application/descriptor/basic/MPartDescriptor;
      72: invokevirtual #528                // Method java/util/ArrayList.toArray:([Ljava/lang/Object;)[Ljava/lang/Object;
      75: pop
      76: return

  protected org.eclipse.jface.dialogs.IDialogSettings getDialogBoundsSettings();
    Code:
       0: aload_0
       1: invokevirtual #593                // Method getDialogSettings:()Lorg/eclipse/jface/dialogs/IDialogSettings;
       4: areturn

  void handleTreeViewerKeyPressed(org.eclipse.swt.events.KeyEvent);
    Code:
       0: aload_0
       1: getfield      #518                // Field descriptionHint:Lorg/eclipse/swt/widgets/Label;
       4: invokevirtual #572                // Method org/eclipse/swt/widgets/Label.isVisible:()Z
       7: ifeq          112
      10: aload_1
      11: getfield      #499                // Field org/eclipse/swt/events/KeyEvent.keyCode:I
      14: ldc_w         #235                // int 16777227
      17: if_icmpne     112
      20: aload_1
      21: getfield      #500                // Field org/eclipse/swt/events/KeyEvent.stateMask:I
      24: ifne          112
      27: aload_0
      28: getfield      #519                // Field filteredTree:Lorg/eclipse/ui/dialogs/FilteredTree;
      31: invokevirtual #580                // Method org/eclipse/ui/dialogs/FilteredTree.getViewer:()Lorg/eclipse/jface/viewers/TreeViewer;
      34: invokevirtual #554                // Method org/eclipse/jface/viewers/TreeViewer.getStructuredSelection:()Lorg/eclipse/jface/viewers/ITreeSelection;
      37: astore_2
      38: aload_2
      39: invokeinterface #626,  1          // InterfaceMethod org/eclipse/jface/viewers/ITreeSelection.size:()I
      44: iconst_1
      45: if_icmpne     112
      48: aload_2
      49: invokeinterface #627,  1          // InterfaceMethod org/eclipse/jface/viewers/ITreeSelection.getFirstElement:()Ljava/lang/Object;
      54: astore_3
      55: aload_3
      56: instanceof    #249                // class org/eclipse/e4/ui/model/application/descriptor/basic/MPartDescriptor
      59: ifeq          112
      62: aload_3
      63: checkcast     #249                // class org/eclipse/e4/ui/model/application/descriptor/basic/MPartDescriptor
      66: invokeinterface #614,  1          // InterfaceMethod org/eclipse/e4/ui/model/application/descriptor/basic/MPartDescriptor.getTooltip:()Ljava/lang/String;
      71: astore        4
      73: aload         4
      75: aload_3
      76: checkcast     #249                // class org/eclipse/e4/ui/model/application/descriptor/basic/MPartDescriptor
      79: aload_0
      80: getfield      #510                // Field context:Lorg/eclipse/e4/core/contexts/IEclipseContext;
      83: invokestatic  #531                // Method org/eclipse/e4/ui/model/LocalizationHelper.getLocalized:(Ljava/lang/String;Lorg/eclipse/e4/ui/model/application/MApplicationElement;Lorg/eclipse/e4/core/contexts/IEclipseContext;)Ljava/lang/String;
      86: astore        4
      88: aload         4
      90: ifnull        106
      93: aload         4
      95: invokevirtual #523                // Method java/lang/String.isEmpty:()Z
      98: ifeq          106
     101: getstatic     #506                // Field org/eclipse/ui/internal/WorkbenchMessages.ShowView_noDesc:Ljava/lang/String;
     104: astore        4
     106: aload_0
     107: aload         4
     109: invokevirtual #591                // Method popUp:(Ljava/lang/String;)V
     112: return

  private void popUp(java.lang.String);
    Code:
       0: new           #278                // class org/eclipse/ui/internal/dialogs/ShowViewDialog$2
       3: dup
       4: aload_0
       5: aload_0
       6: getfield      #519                // Field filteredTree:Lorg/eclipse/ui/dialogs/FilteredTree;
       9: invokevirtual #582                // Method org/eclipse/ui/dialogs/FilteredTree.getShell:()Lorg/eclipse/swt/widgets/Shell;
      12: ldc_w         #234                // int 540676
      15: iconst_1
      16: iconst_0
      17: iconst_0
      18: iconst_0
      19: iconst_0
      20: aconst_null
      21: aconst_null
      22: aload_1
      23: invokespecial #603                // Method org/eclipse/ui/internal/dialogs/ShowViewDialog$2."<init>":(Lorg/eclipse/ui/internal/dialogs/ShowViewDialog;Lorg/eclipse/swt/widgets/Shell;IZZZZZLjava/lang/String;Ljava/lang/String;Ljava/lang/String;)V
      26: invokevirtual #602                // Method org/eclipse/ui/internal/dialogs/ShowViewDialog$2.open:()I
      29: pop
      30: return

  protected boolean isResizable();
    Code:
       0: iconst_1
       1: ireturn
}
