Compiled from "ViewsPreferencePage.java"
class org.eclipse.ui.internal.dialogs.ViewsPreferencePage$NotificationPopUp extends org.eclipse.jface.notifications.AbstractNotificationPopup {
  final org.eclipse.ui.internal.dialogs.ViewsPreferencePage this$0;

  public org.eclipse.ui.internal.dialogs.ViewsPreferencePage$NotificationPopUp(org.eclipse.ui.internal.dialogs.ViewsPreferencePage, org.eclipse.swt.widgets.Display);
    Code:
       0: aload_0
       1: aload_1
       2: putfield      #100                // Field this$0:Lorg/eclipse/ui/internal/dialogs/ViewsPreferencePage;
       5: aload_0
       6: aload_2
       7: invokespecial #102                // Method org/eclipse/jface/notifications/AbstractNotificationPopup."<init>":(Lorg/eclipse/swt/widgets/Display;)V
      10: aload_0
      11: lconst_0
      12: invokevirtual #109                // Method setDelayClose:(J)V
      15: aload_0
      16: invokestatic  #108                // Method org/eclipse/ui/PlatformUI.getWorkbench:()Lorg/eclipse/ui/IWorkbench;
      19: invokeinterface #114,  1          // InterfaceMethod org/eclipse/ui/IWorkbench.getActiveWorkbenchWindow:()Lorg/eclipse/ui/IWorkbenchWindow;
      24: invokeinterface #115,  1          // InterfaceMethod org/eclipse/ui/IWorkbenchWindow.getShell:()Lorg/eclipse/swt/widgets/Shell;
      29: invokevirtual #111                // Method setParentShell:(Lorg/eclipse/swt/widgets/Shell;)V
      32: return

  protected java.lang.String getPopupShellTitle();
    Code:
       0: getstatic     #99                 // Field org/eclipse/ui/internal/WorkbenchMessages.ThemeChangeWarningTitle:Ljava/lang/String;
       3: areturn

  protected void createContentArea(org.eclipse.swt.widgets.Composite);
    Code:
       0: aload_1
       1: new           #46                 // class org/eclipse/swt/layout/RowLayout
       4: dup
       5: invokespecial #103                // Method org/eclipse/swt/layout/RowLayout."<init>":()V
       8: invokevirtual #104                // Method org/eclipse/swt/widgets/Composite.setLayout:(Lorg/eclipse/swt/widgets/Layout;)V
      11: new           #48                 // class org/eclipse/swt/widgets/Link
      14: dup
      15: aload_1
      16: bipush        64
      18: invokespecial #107                // Method org/eclipse/swt/widgets/Link."<init>":(Lorg/eclipse/swt/widgets/Composite;I)V
      21: astore_2
      22: aload_2
      23: getstatic     #98                 // Field org/eclipse/ui/internal/WorkbenchMessages.ThemeChangeWarningText:Ljava/lang/String;
      26: invokevirtual #105                // Method org/eclipse/swt/widgets/Link.setText:(Ljava/lang/String;)V
      29: aload_2
      30: invokedynamic #120,  0            // InvokeDynamic #0:accept:()Ljava/util/function/Consumer;
      35: invokestatic  #112                // InterfaceMethod org/eclipse/swt/events/SelectionListener.widgetSelectedAdapter:(Ljava/util/function/Consumer;)Lorg/eclipse/swt/events/SelectionListener;
      38: invokevirtual #106                // Method org/eclipse/swt/widgets/Link.addSelectionListener:(Lorg/eclipse/swt/events/SelectionListener;)V
      41: return

  private static void lambda$0(org.eclipse.swt.events.SelectionEvent);
    Code:
       0: invokestatic  #108                // Method org/eclipse/ui/PlatformUI.getWorkbench:()Lorg/eclipse/ui/IWorkbench;
       3: iconst_1
       4: invokeinterface #113,  2          // InterfaceMethod org/eclipse/ui/IWorkbench.restart:(Z)Z
       9: return
}
