Compiled from "WorkbenchWizardSelectionPage.java"
public abstract class org.eclipse.ui.internal.dialogs.WorkbenchWizardSelectionPage extends org.eclipse.jface.wizard.WizardSelectionPage {
  protected org.eclipse.ui.IWorkbench workbench;

  protected org.eclipse.ui.model.AdaptableList wizardElements;

  public org.eclipse.jface.viewers.TableViewer wizardSelectionViewer;

  protected org.eclipse.jface.viewers.IStructuredSelection currentResourceSelection;

  protected java.lang.String triggerPointId;

  public org.eclipse.ui.internal.dialogs.WorkbenchWizardSelectionPage(java.lang.String, org.eclipse.ui.IWorkbench, org.eclipse.jface.viewers.IStructuredSelection, org.eclipse.ui.model.AdaptableList, java.lang.String);
    Code:
       0: aload_0
       1: aload_1
       2: invokespecial #106                // Method org/eclipse/jface/wizard/WizardSelectionPage."<init>":(Ljava/lang/String;)V
       5: aload_0
       6: aload         4
       8: putfield      #104                // Field wizardElements:Lorg/eclipse/ui/model/AdaptableList;
      11: aload_0
      12: aload_3
      13: putfield      #102                // Field currentResourceSelection:Lorg/eclipse/jface/viewers/IStructuredSelection;
      16: aload_0
      17: aload_2
      18: putfield      #103                // Field workbench:Lorg/eclipse/ui/IWorkbench;
      21: aload_0
      22: aload         5
      24: putfield      #101                // Field triggerPointId:Ljava/lang/String;
      27: aload_0
      28: getstatic     #100                // Field org/eclipse/ui/internal/WorkbenchMessages.Select:Ljava/lang/String;
      31: invokevirtual #110                // Method setTitle:(Ljava/lang/String;)V
      34: return

  protected org.eclipse.ui.internal.dialogs.WorkbenchWizardElement findWizard(java.lang.String);
    Code:
       0: aload_0
       1: getfield      #104                // Field wizardElements:Lorg/eclipse/ui/model/AdaptableList;
       4: invokevirtual #114                // Method org/eclipse/ui/model/AdaptableList.getChildren:()[Ljava/lang/Object;
       7: dup
       8: astore        5
      10: arraylength
      11: istore        4
      13: iconst_0
      14: istore_3
      15: goto          47
      18: aload         5
      20: iload_3
      21: aaload
      22: astore_2
      23: aload_2
      24: checkcast     #54                 // class org/eclipse/ui/internal/dialogs/WorkbenchWizardElement
      27: astore        6
      29: aload         6
      31: invokevirtual #109                // Method org/eclipse/ui/internal/dialogs/WorkbenchWizardElement.getId:()Ljava/lang/String;
      34: aload_1
      35: invokevirtual #105                // Method java/lang/String.equals:(Ljava/lang/Object;)Z
      38: ifeq          44
      41: aload         6
      43: areturn
      44: iinc          3, 1
      47: iload_3
      48: iload         4
      50: if_icmplt     18
      53: aconst_null
      54: areturn

  public org.eclipse.jface.viewers.IStructuredSelection getCurrentResourceSelection();
    Code:
       0: aload_0
       1: getfield      #102                // Field currentResourceSelection:Lorg/eclipse/jface/viewers/IStructuredSelection;
       4: areturn

  public org.eclipse.ui.IWorkbench getWorkbench();
    Code:
       0: aload_0
       1: getfield      #103                // Field workbench:Lorg/eclipse/ui/IWorkbench;
       4: areturn

  public void selectWizardNode(org.eclipse.jface.wizard.IWizardNode);
    Code:
       0: aload_0
       1: aload_1
       2: invokevirtual #112                // Method setSelectedNode:(Lorg/eclipse/jface/wizard/IWizardNode;)V
       5: return

  public org.eclipse.jface.wizard.IWizardPage getNextPage();
    Code:
       0: aload_0
       1: invokevirtual #113                // Method getWorkbench:()Lorg/eclipse/ui/IWorkbench;
       4: invokeinterface #115,  1          // InterfaceMethod org/eclipse/ui/IWorkbench.getActivitySupport:()Lorg/eclipse/ui/activities/IWorkbenchActivitySupport;
       9: invokeinterface #117,  1          // InterfaceMethod org/eclipse/ui/activities/IWorkbenchActivitySupport.getTriggerPointManager:()Lorg/eclipse/ui/activities/ITriggerPointManager;
      14: aload_0
      15: getfield      #101                // Field triggerPointId:Ljava/lang/String;
      18: invokeinterface #116,  2          // InterfaceMethod org/eclipse/ui/activities/ITriggerPointManager.getTriggerPoint:(Ljava/lang/String;)Lorg/eclipse/ui/activities/ITriggerPoint;
      23: astore_1
      24: aload_1
      25: ifnull        39
      28: aload_1
      29: aload_0
      30: invokevirtual #111                // Method getSelectedNode:()Lorg/eclipse/jface/wizard/IWizardNode;
      33: invokestatic  #108                // Method org/eclipse/ui/activities/WorkbenchActivityHelper.allowUseOf:(Lorg/eclipse/ui/activities/ITriggerPoint;Ljava/lang/Object;)Z
      36: ifeq          44
      39: aload_0
      40: invokespecial #107                // Method org/eclipse/jface/wizard/WizardSelectionPage.getNextPage:()Lorg/eclipse/jface/wizard/IWizardPage;
      43: areturn
      44: aconst_null
      45: areturn
}
