Compiled from "V2beta2Autoscaling.java"
public final class io.kubernetes.client.proto.V2beta2Autoscaling$HorizontalPodAutoscalerStatus$Builder extends com.google.protobuf.GeneratedMessageV3$Builder<io.kubernetes.client.proto.V2beta2Autoscaling$HorizontalPodAutoscalerStatus$Builder> implements io.kubernetes.client.proto.V2beta2Autoscaling$HorizontalPodAutoscalerStatusOrBuilder {
  private int bitField0_;

  private long observedGeneration_;

  private io.kubernetes.client.proto.Meta$Time lastScaleTime_;

  private com.google.protobuf.SingleFieldBuilderV3<io.kubernetes.client.proto.Meta$Time, io.kubernetes.client.proto.Meta$Time$Builder, io.kubernetes.client.proto.Meta$TimeOrBuilder> lastScaleTimeBuilder_;

  private int currentReplicas_;

  private int desiredReplicas_;

  private java.util.List<io.kubernetes.client.proto.V2beta2Autoscaling$MetricStatus> currentMetrics_;

  private com.google.protobuf.RepeatedFieldBuilderV3<io.kubernetes.client.proto.V2beta2Autoscaling$MetricStatus, io.kubernetes.client.proto.V2beta2Autoscaling$MetricStatus$Builder, io.kubernetes.client.proto.V2beta2Autoscaling$MetricStatusOrBuilder> currentMetricsBuilder_;

  private java.util.List<io.kubernetes.client.proto.V2beta2Autoscaling$HorizontalPodAutoscalerCondition> conditions_;

  private com.google.protobuf.RepeatedFieldBuilderV3<io.kubernetes.client.proto.V2beta2Autoscaling$HorizontalPodAutoscalerCondition, io.kubernetes.client.proto.V2beta2Autoscaling$HorizontalPodAutoscalerCondition$Builder, io.kubernetes.client.proto.V2beta2Autoscaling$HorizontalPodAutoscalerConditionOrBuilder> conditionsBuilder_;

  public static final com.google.protobuf.Descriptors$Descriptor getDescriptor();
    Code:
       0: invokestatic  #3                  // Method io/kubernetes/client/proto/V2beta2Autoscaling.access$8600:()Lcom/google/protobuf/Descriptors$Descriptor;
       3: areturn

  protected com.google.protobuf.GeneratedMessageV3$FieldAccessorTable internalGetFieldAccessorTable();
    Code:
       0: invokestatic  #4                  // Method io/kubernetes/client/proto/V2beta2Autoscaling.access$8700:()Lcom/google/protobuf/GeneratedMessageV3$FieldAccessorTable;
       3: ldc           #5                  // class io/kubernetes/client/proto/V2beta2Autoscaling$HorizontalPodAutoscalerStatus
       5: ldc           #6                  // class io/kubernetes/client/proto/V2beta2Autoscaling$HorizontalPodAutoscalerStatus$Builder
       7: invokevirtual #7                  // Method com/google/protobuf/GeneratedMessageV3$FieldAccessorTable.ensureFieldAccessorsInitialized:(Ljava/lang/Class;Ljava/lang/Class;)Lcom/google/protobuf/GeneratedMessageV3$FieldAccessorTable;
      10: areturn

  private io.kubernetes.client.proto.V2beta2Autoscaling$HorizontalPodAutoscalerStatus$Builder();
    Code:
       0: aload_0
       1: invokespecial #8                  // Method com/google/protobuf/GeneratedMessageV3$Builder."<init>":()V
       4: aload_0
       5: aconst_null
       6: putfield      #9                  // Field lastScaleTime_:Lio/kubernetes/client/proto/Meta$Time;
       9: aload_0
      10: invokestatic  #10                 // Method java/util/Collections.emptyList:()Ljava/util/List;
      13: putfield      #11                 // Field currentMetrics_:Ljava/util/List;
      16: aload_0
      17: invokestatic  #10                 // Method java/util/Collections.emptyList:()Ljava/util/List;
      20: putfield      #12                 // Field conditions_:Ljava/util/List;
      23: aload_0
      24: invokespecial #13                 // Method maybeForceBuilderInitialization:()V
      27: return

  private io.kubernetes.client.proto.V2beta2Autoscaling$HorizontalPodAutoscalerStatus$Builder(com.google.protobuf.GeneratedMessageV3$BuilderParent);
    Code:
       0: aload_0
       1: aload_1
       2: invokespecial #14                 // Method com/google/protobuf/GeneratedMessageV3$Builder."<init>":(Lcom/google/protobuf/GeneratedMessageV3$BuilderParent;)V
       5: aload_0
       6: aconst_null
       7: putfield      #9                  // Field lastScaleTime_:Lio/kubernetes/client/proto/Meta$Time;
      10: aload_0
      11: invokestatic  #10                 // Method java/util/Collections.emptyList:()Ljava/util/List;
      14: putfield      #11                 // Field currentMetrics_:Ljava/util/List;
      17: aload_0
      18: invokestatic  #10                 // Method java/util/Collections.emptyList:()Ljava/util/List;
      21: putfield      #12                 // Field conditions_:Ljava/util/List;
      24: aload_0
      25: invokespecial #13                 // Method maybeForceBuilderInitialization:()V
      28: return

  private void maybeForceBuilderInitialization();
    Code:
       0: invokestatic  #15                 // Method io/kubernetes/client/proto/V2beta2Autoscaling$HorizontalPodAutoscalerStatus.access$9000:()Z
       3: ifeq          21
       6: aload_0
       7: invokespecial #16                 // Method getLastScaleTimeFieldBuilder:()Lcom/google/protobuf/SingleFieldBuilderV3;
      10: pop
      11: aload_0
      12: invokespecial #17                 // Method getCurrentMetricsFieldBuilder:()Lcom/google/protobuf/RepeatedFieldBuilderV3;
      15: pop
      16: aload_0
      17: invokespecial #18                 // Method getConditionsFieldBuilder:()Lcom/google/protobuf/RepeatedFieldBuilderV3;
      20: pop
      21: return

  public io.kubernetes.client.proto.V2beta2Autoscaling$HorizontalPodAutoscalerStatus$Builder clear();
    Code:
       0: aload_0
       1: invokespecial #19                 // Method com/google/protobuf/GeneratedMessageV3$Builder.clear:()Lcom/google/protobuf/GeneratedMessageV3$Builder;
       4: pop
       5: aload_0
       6: lconst_0
       7: putfield      #20                 // Field observedGeneration_:J
      10: aload_0
      11: aload_0
      12: getfield      #21                 // Field bitField0_:I
      15: bipush        -2
      17: iand
      18: putfield      #21                 // Field bitField0_:I
      21: aload_0
      22: getfield      #22                 // Field lastScaleTimeBuilder_:Lcom/google/protobuf/SingleFieldBuilderV3;
      25: ifnonnull     36
      28: aload_0
      29: aconst_null
      30: putfield      #9                  // Field lastScaleTime_:Lio/kubernetes/client/proto/Meta$Time;
      33: goto          44
      36: aload_0
      37: getfield      #22                 // Field lastScaleTimeBuilder_:Lcom/google/protobuf/SingleFieldBuilderV3;
      40: invokevirtual #23                 // Method com/google/protobuf/SingleFieldBuilderV3.clear:()Lcom/google/protobuf/SingleFieldBuilderV3;
      43: pop
      44: aload_0
      45: aload_0
      46: getfield      #21                 // Field bitField0_:I
      49: bipush        -3
      51: iand
      52: putfield      #21                 // Field bitField0_:I
      55: aload_0
      56: iconst_0
      57: putfield      #24                 // Field currentReplicas_:I
      60: aload_0
      61: aload_0
      62: getfield      #21                 // Field bitField0_:I
      65: bipush        -5
      67: iand
      68: putfield      #21                 // Field bitField0_:I
      71: aload_0
      72: iconst_0
      73: putfield      #25                 // Field desiredReplicas_:I
      76: aload_0
      77: aload_0
      78: getfield      #21                 // Field bitField0_:I
      81: bipush        -9
      83: iand
      84: putfield      #21                 // Field bitField0_:I
      87: aload_0
      88: getfield      #26                 // Field currentMetricsBuilder_:Lcom/google/protobuf/RepeatedFieldBuilderV3;
      91: ifnonnull     115
      94: aload_0
      95: invokestatic  #10                 // Method java/util/Collections.emptyList:()Ljava/util/List;
      98: putfield      #11                 // Field currentMetrics_:Ljava/util/List;
     101: aload_0
     102: aload_0
     103: getfield      #21                 // Field bitField0_:I
     106: bipush        -17
     108: iand
     109: putfield      #21                 // Field bitField0_:I
     112: goto          122
     115: aload_0
     116: getfield      #26                 // Field currentMetricsBuilder_:Lcom/google/protobuf/RepeatedFieldBuilderV3;
     119: invokevirtual #27                 // Method com/google/protobuf/RepeatedFieldBuilderV3.clear:()V
     122: aload_0
     123: getfield      #28                 // Field conditionsBuilder_:Lcom/google/protobuf/RepeatedFieldBuilderV3;
     126: ifnonnull     150
     129: aload_0
     130: invokestatic  #10                 // Method java/util/Collections.emptyList:()Ljava/util/List;
     133: putfield      #12                 // Field conditions_:Ljava/util/List;
     136: aload_0
     137: aload_0
     138: getfield      #21                 // Field bitField0_:I
     141: bipush        -33
     143: iand
     144: putfield      #21                 // Field bitField0_:I
     147: goto          157
     150: aload_0
     151: getfield      #28                 // Field conditionsBuilder_:Lcom/google/protobuf/RepeatedFieldBuilderV3;
     154: invokevirtual #27                 // Method com/google/protobuf/RepeatedFieldBuilderV3.clear:()V
     157: aload_0
     158: areturn

  public com.google.protobuf.Descriptors$Descriptor getDescriptorForType();
    Code:
       0: invokestatic  #3                  // Method io/kubernetes/client/proto/V2beta2Autoscaling.access$8600:()Lcom/google/protobuf/Descriptors$Descriptor;
       3: areturn

  public io.kubernetes.client.proto.V2beta2Autoscaling$HorizontalPodAutoscalerStatus getDefaultInstanceForType();
    Code:
       0: invokestatic  #29                 // Method io/kubernetes/client/proto/V2beta2Autoscaling$HorizontalPodAutoscalerStatus.getDefaultInstance:()Lio/kubernetes/client/proto/V2beta2Autoscaling$HorizontalPodAutoscalerStatus;
       3: areturn

  public io.kubernetes.client.proto.V2beta2Autoscaling$HorizontalPodAutoscalerStatus build();
    Code:
       0: aload_0
       1: invokevirtual #30                 // Method buildPartial:()Lio/kubernetes/client/proto/V2beta2Autoscaling$HorizontalPodAutoscalerStatus;
       4: astore_1
       5: aload_1
       6: invokevirtual #31                 // Method io/kubernetes/client/proto/V2beta2Autoscaling$HorizontalPodAutoscalerStatus.isInitialized:()Z
       9: ifne          17
      12: aload_1
      13: invokestatic  #32                 // Method newUninitializedMessageException:(Lcom/google/protobuf/Message;)Lcom/google/protobuf/UninitializedMessageException;
      16: athrow
      17: aload_1
      18: areturn

  public io.kubernetes.client.proto.V2beta2Autoscaling$HorizontalPodAutoscalerStatus buildPartial();
    Code:
       0: new           #5                  // class io/kubernetes/client/proto/V2beta2Autoscaling$HorizontalPodAutoscalerStatus
       3: dup
       4: aload_0
       5: aconst_null
       6: invokespecial #33                 // Method io/kubernetes/client/proto/V2beta2Autoscaling$HorizontalPodAutoscalerStatus."<init>":(Lcom/google/protobuf/GeneratedMessageV3$Builder;Lio/kubernetes/client/proto/V2beta2Autoscaling$1;)V
       9: astore_1
      10: aload_0
      11: getfield      #21                 // Field bitField0_:I
      14: istore_2
      15: iconst_0
      16: istore_3
      17: iload_2
      18: iconst_1
      19: iand
      20: iconst_1
      21: if_icmpne     28
      24: iload_3
      25: iconst_1
      26: ior
      27: istore_3
      28: aload_1
      29: aload_0
      30: getfield      #20                 // Field observedGeneration_:J
      33: invokestatic  #34                 // Method io/kubernetes/client/proto/V2beta2Autoscaling$HorizontalPodAutoscalerStatus.access$9202:(Lio/kubernetes/client/proto/V2beta2Autoscaling$HorizontalPodAutoscalerStatus;J)J
      36: pop2
      37: iload_2
      38: iconst_2
      39: iand
      40: iconst_2
      41: if_icmpne     48
      44: iload_3
      45: iconst_2
      46: ior
      47: istore_3
      48: aload_0
      49: getfield      #22                 // Field lastScaleTimeBuilder_:Lcom/google/protobuf/SingleFieldBuilderV3;
      52: ifnonnull     67
      55: aload_1
      56: aload_0
      57: getfield      #9                  // Field lastScaleTime_:Lio/kubernetes/client/proto/Meta$Time;
      60: invokestatic  #35                 // Method io/kubernetes/client/proto/V2beta2Autoscaling$HorizontalPodAutoscalerStatus.access$9302:(Lio/kubernetes/client/proto/V2beta2Autoscaling$HorizontalPodAutoscalerStatus;Lio/kubernetes/client/proto/Meta$Time;)Lio/kubernetes/client/proto/Meta$Time;
      63: pop
      64: goto          82
      67: aload_1
      68: aload_0
      69: getfield      #22                 // Field lastScaleTimeBuilder_:Lcom/google/protobuf/SingleFieldBuilderV3;
      72: invokevirtual #36                 // Method com/google/protobuf/SingleFieldBuilderV3.build:()Lcom/google/protobuf/AbstractMessage;
      75: checkcast     #37                 // class io/kubernetes/client/proto/Meta$Time
      78: invokestatic  #35                 // Method io/kubernetes/client/proto/V2beta2Autoscaling$HorizontalPodAutoscalerStatus.access$9302:(Lio/kubernetes/client/proto/V2beta2Autoscaling$HorizontalPodAutoscalerStatus;Lio/kubernetes/client/proto/Meta$Time;)Lio/kubernetes/client/proto/Meta$Time;
      81: pop
      82: iload_2
      83: iconst_4
      84: iand
      85: iconst_4
      86: if_icmpne     93
      89: iload_3
      90: iconst_4
      91: ior
      92: istore_3
      93: aload_1
      94: aload_0
      95: getfield      #24                 // Field currentReplicas_:I
      98: invokestatic  #38                 // Method io/kubernetes/client/proto/V2beta2Autoscaling$HorizontalPodAutoscalerStatus.access$9402:(Lio/kubernetes/client/proto/V2beta2Autoscaling$HorizontalPodAutoscalerStatus;I)I
     101: pop
     102: iload_2
     103: bipush        8
     105: iand
     106: bipush        8
     108: if_icmpne     116
     111: iload_3
     112: bipush        8
     114: ior
     115: istore_3
     116: aload_1
     117: aload_0
     118: getfield      #25                 // Field desiredReplicas_:I
     121: invokestatic  #39                 // Method io/kubernetes/client/proto/V2beta2Autoscaling$HorizontalPodAutoscalerStatus.access$9502:(Lio/kubernetes/client/proto/V2beta2Autoscaling$HorizontalPodAutoscalerStatus;I)I
     124: pop
     125: aload_0
     126: getfield      #26                 // Field currentMetricsBuilder_:Lcom/google/protobuf/RepeatedFieldBuilderV3;
     129: ifnonnull     178
     132: aload_0
     133: getfield      #21                 // Field bitField0_:I
     136: bipush        16
     138: iand
     139: bipush        16
     141: if_icmpne     166
     144: aload_0
     145: aload_0
     146: getfield      #11                 // Field currentMetrics_:Ljava/util/List;
     149: invokestatic  #40                 // Method java/util/Collections.unmodifiableList:(Ljava/util/List;)Ljava/util/List;
     152: putfield      #11                 // Field currentMetrics_:Ljava/util/List;
     155: aload_0
     156: aload_0
     157: getfield      #21                 // Field bitField0_:I
     160: bipush        -17
     162: iand
     163: putfield      #21                 // Field bitField0_:I
     166: aload_1
     167: aload_0
     168: getfield      #11                 // Field currentMetrics_:Ljava/util/List;
     171: invokestatic  #41                 // Method io/kubernetes/client/proto/V2beta2Autoscaling$HorizontalPodAutoscalerStatus.access$9602:(Lio/kubernetes/client/proto/V2beta2Autoscaling$HorizontalPodAutoscalerStatus;Ljava/util/List;)Ljava/util/List;
     174: pop
     175: goto          190
     178: aload_1
     179: aload_0
     180: getfield      #26                 // Field currentMetricsBuilder_:Lcom/google/protobuf/RepeatedFieldBuilderV3;
     183: invokevirtual #42                 // Method com/google/protobuf/RepeatedFieldBuilderV3.build:()Ljava/util/List;
     186: invokestatic  #41                 // Method io/kubernetes/client/proto/V2beta2Autoscaling$HorizontalPodAutoscalerStatus.access$9602:(Lio/kubernetes/client/proto/V2beta2Autoscaling$HorizontalPodAutoscalerStatus;Ljava/util/List;)Ljava/util/List;
     189: pop
     190: aload_0
     191: getfield      #28                 // Field conditionsBuilder_:Lcom/google/protobuf/RepeatedFieldBuilderV3;
     194: ifnonnull     243
     197: aload_0
     198: getfield      #21                 // Field bitField0_:I
     201: bipush        32
     203: iand
     204: bipush        32
     206: if_icmpne     231
     209: aload_0
     210: aload_0
     211: getfield      #12                 // Field conditions_:Ljava/util/List;
     214: invokestatic  #40                 // Method java/util/Collections.unmodifiableList:(Ljava/util/List;)Ljava/util/List;
     217: putfield      #12                 // Field conditions_:Ljava/util/List;
     220: aload_0
     221: aload_0
     222: getfield      #21                 // Field bitField0_:I
     225: bipush        -33
     227: iand
     228: putfield      #21                 // Field bitField0_:I
     231: aload_1
     232: aload_0
     233: getfield      #12                 // Field conditions_:Ljava/util/List;
     236: invokestatic  #43                 // Method io/kubernetes/client/proto/V2beta2Autoscaling$HorizontalPodAutoscalerStatus.access$9702:(Lio/kubernetes/client/proto/V2beta2Autoscaling$HorizontalPodAutoscalerStatus;Ljava/util/List;)Ljava/util/List;
     239: pop
     240: goto          255
     243: aload_1
     244: aload_0
     245: getfield      #28                 // Field conditionsBuilder_:Lcom/google/protobuf/RepeatedFieldBuilderV3;
     248: invokevirtual #42                 // Method com/google/protobuf/RepeatedFieldBuilderV3.build:()Ljava/util/List;
     251: invokestatic  #43                 // Method io/kubernetes/client/proto/V2beta2Autoscaling$HorizontalPodAutoscalerStatus.access$9702:(Lio/kubernetes/client/proto/V2beta2Autoscaling$HorizontalPodAutoscalerStatus;Ljava/util/List;)Ljava/util/List;
     254: pop
     255: aload_1
     256: iload_3
     257: invokestatic  #44                 // Method io/kubernetes/client/proto/V2beta2Autoscaling$HorizontalPodAutoscalerStatus.access$9802:(Lio/kubernetes/client/proto/V2beta2Autoscaling$HorizontalPodAutoscalerStatus;I)I
     260: pop
     261: aload_0
     262: invokevirtual #45                 // Method onBuilt:()V
     265: aload_1
     266: areturn

  public io.kubernetes.client.proto.V2beta2Autoscaling$HorizontalPodAutoscalerStatus$Builder clone();
    Code:
       0: aload_0
       1: invokespecial #46                 // Method com/google/protobuf/GeneratedMessageV3$Builder.clone:()Lcom/google/protobuf/GeneratedMessageV3$Builder;
       4: checkcast     #6                  // class io/kubernetes/client/proto/V2beta2Autoscaling$HorizontalPodAutoscalerStatus$Builder
       7: areturn

  public io.kubernetes.client.proto.V2beta2Autoscaling$HorizontalPodAutoscalerStatus$Builder setField(com.google.protobuf.Descriptors$FieldDescriptor, java.lang.Object);
    Code:
       0: aload_0
       1: aload_1
       2: aload_2
       3: invokespecial #47                 // Method com/google/protobuf/GeneratedMessageV3$Builder.setField:(Lcom/google/protobuf/Descriptors$FieldDescriptor;Ljava/lang/Object;)Lcom/google/protobuf/GeneratedMessageV3$Builder;
       6: checkcast     #6                  // class io/kubernetes/client/proto/V2beta2Autoscaling$HorizontalPodAutoscalerStatus$Builder
       9: areturn

  public io.kubernetes.client.proto.V2beta2Autoscaling$HorizontalPodAutoscalerStatus$Builder clearField(com.google.protobuf.Descriptors$FieldDescriptor);
    Code:
       0: aload_0
       1: aload_1
       2: invokespecial #48                 // Method com/google/protobuf/GeneratedMessageV3$Builder.clearField:(Lcom/google/protobuf/Descriptors$FieldDescriptor;)Lcom/google/protobuf/GeneratedMessageV3$Builder;
       5: checkcast     #6                  // class io/kubernetes/client/proto/V2beta2Autoscaling$HorizontalPodAutoscalerStatus$Builder
       8: areturn

  public io.kubernetes.client.proto.V2beta2Autoscaling$HorizontalPodAutoscalerStatus$Builder clearOneof(com.google.protobuf.Descriptors$OneofDescriptor);
    Code:
       0: aload_0
       1: aload_1
       2: invokespecial #49                 // Method com/google/protobuf/GeneratedMessageV3$Builder.clearOneof:(Lcom/google/protobuf/Descriptors$OneofDescriptor;)Lcom/google/protobuf/GeneratedMessageV3$Builder;
       5: checkcast     #6                  // class io/kubernetes/client/proto/V2beta2Autoscaling$HorizontalPodAutoscalerStatus$Builder
       8: areturn

  public io.kubernetes.client.proto.V2beta2Autoscaling$HorizontalPodAutoscalerStatus$Builder setRepeatedField(com.google.protobuf.Descriptors$FieldDescriptor, int, java.lang.Object);
    Code:
       0: aload_0
       1: aload_1
       2: iload_2
       3: aload_3
       4: invokespecial #50                 // Method com/google/protobuf/GeneratedMessageV3$Builder.setRepeatedField:(Lcom/google/protobuf/Descriptors$FieldDescriptor;ILjava/lang/Object;)Lcom/google/protobuf/GeneratedMessageV3$Builder;
       7: checkcast     #6                  // class io/kubernetes/client/proto/V2beta2Autoscaling$HorizontalPodAutoscalerStatus$Builder
      10: areturn

  public io.kubernetes.client.proto.V2beta2Autoscaling$HorizontalPodAutoscalerStatus$Builder addRepeatedField(com.google.protobuf.Descriptors$FieldDescriptor, java.lang.Object);
    Code:
       0: aload_0
       1: aload_1
       2: aload_2
       3: invokespecial #51                 // Method com/google/protobuf/GeneratedMessageV3$Builder.addRepeatedField:(Lcom/google/protobuf/Descriptors$FieldDescriptor;Ljava/lang/Object;)Lcom/google/protobuf/GeneratedMessageV3$Builder;
       6: checkcast     #6                  // class io/kubernetes/client/proto/V2beta2Autoscaling$HorizontalPodAutoscalerStatus$Builder
       9: areturn

  public io.kubernetes.client.proto.V2beta2Autoscaling$HorizontalPodAutoscalerStatus$Builder mergeFrom(com.google.protobuf.Message);
    Code:
       0: aload_1
       1: instanceof    #5                  // class io/kubernetes/client/proto/V2beta2Autoscaling$HorizontalPodAutoscalerStatus
       4: ifeq          16
       7: aload_0
       8: aload_1
       9: checkcast     #5                  // class io/kubernetes/client/proto/V2beta2Autoscaling$HorizontalPodAutoscalerStatus
      12: invokevirtual #52                 // Method mergeFrom:(Lio/kubernetes/client/proto/V2beta2Autoscaling$HorizontalPodAutoscalerStatus;)Lio/kubernetes/client/proto/V2beta2Autoscaling$HorizontalPodAutoscalerStatus$Builder;
      15: areturn
      16: aload_0
      17: aload_1
      18: invokespecial #53                 // Method com/google/protobuf/GeneratedMessageV3$Builder.mergeFrom:(Lcom/google/protobuf/Message;)Lcom/google/protobuf/AbstractMessage$Builder;
      21: pop
      22: aload_0
      23: areturn

  public io.kubernetes.client.proto.V2beta2Autoscaling$HorizontalPodAutoscalerStatus$Builder mergeFrom(io.kubernetes.client.proto.V2beta2Autoscaling$HorizontalPodAutoscalerStatus);
    Code:
       0: aload_1
       1: invokestatic  #29                 // Method io/kubernetes/client/proto/V2beta2Autoscaling$HorizontalPodAutoscalerStatus.getDefaultInstance:()Lio/kubernetes/client/proto/V2beta2Autoscaling$HorizontalPodAutoscalerStatus;
       4: if_acmpne     9
       7: aload_0
       8: areturn
       9: aload_1
      10: invokevirtual #54                 // Method io/kubernetes/client/proto/V2beta2Autoscaling$HorizontalPodAutoscalerStatus.hasObservedGeneration:()Z
      13: ifeq          25
      16: aload_0
      17: aload_1
      18: invokevirtual #55                 // Method io/kubernetes/client/proto/V2beta2Autoscaling$HorizontalPodAutoscalerStatus.getObservedGeneration:()J
      21: invokevirtual #56                 // Method setObservedGeneration:(J)Lio/kubernetes/client/proto/V2beta2Autoscaling$HorizontalPodAutoscalerStatus$Builder;
      24: pop
      25: aload_1
      26: invokevirtual #57                 // Method io/kubernetes/client/proto/V2beta2Autoscaling$HorizontalPodAutoscalerStatus.hasLastScaleTime:()Z
      29: ifeq          41
      32: aload_0
      33: aload_1
      34: invokevirtual #58                 // Method io/kubernetes/client/proto/V2beta2Autoscaling$HorizontalPodAutoscalerStatus.getLastScaleTime:()Lio/kubernetes/client/proto/Meta$Time;
      37: invokevirtual #59                 // Method mergeLastScaleTime:(Lio/kubernetes/client/proto/Meta$Time;)Lio/kubernetes/client/proto/V2beta2Autoscaling$HorizontalPodAutoscalerStatus$Builder;
      40: pop
      41: aload_1
      42: invokevirtual #60                 // Method io/kubernetes/client/proto/V2beta2Autoscaling$HorizontalPodAutoscalerStatus.hasCurrentReplicas:()Z
      45: ifeq          57
      48: aload_0
      49: aload_1
      50: invokevirtual #61                 // Method io/kubernetes/client/proto/V2beta2Autoscaling$HorizontalPodAutoscalerStatus.getCurrentReplicas:()I
      53: invokevirtual #62                 // Method setCurrentReplicas:(I)Lio/kubernetes/client/proto/V2beta2Autoscaling$HorizontalPodAutoscalerStatus$Builder;
      56: pop
      57: aload_1
      58: invokevirtual #63                 // Method io/kubernetes/client/proto/V2beta2Autoscaling$HorizontalPodAutoscalerStatus.hasDesiredReplicas:()Z
      61: ifeq          73
      64: aload_0
      65: aload_1
      66: invokevirtual #64                 // Method io/kubernetes/client/proto/V2beta2Autoscaling$HorizontalPodAutoscalerStatus.getDesiredReplicas:()I
      69: invokevirtual #65                 // Method setDesiredReplicas:(I)Lio/kubernetes/client/proto/V2beta2Autoscaling$HorizontalPodAutoscalerStatus$Builder;
      72: pop
      73: aload_0
      74: getfield      #26                 // Field currentMetricsBuilder_:Lcom/google/protobuf/RepeatedFieldBuilderV3;
      77: ifnonnull     151
      80: aload_1
      81: invokestatic  #66                 // Method io/kubernetes/client/proto/V2beta2Autoscaling$HorizontalPodAutoscalerStatus.access$9600:(Lio/kubernetes/client/proto/V2beta2Autoscaling$HorizontalPodAutoscalerStatus;)Ljava/util/List;
      84: invokeinterface #67,  1           // InterfaceMethod java/util/List.isEmpty:()Z
      89: ifne          237
      92: aload_0
      93: getfield      #11                 // Field currentMetrics_:Ljava/util/List;
      96: invokeinterface #67,  1           // InterfaceMethod java/util/List.isEmpty:()Z
     101: ifeq          126
     104: aload_0
     105: aload_1
     106: invokestatic  #66                 // Method io/kubernetes/client/proto/V2beta2Autoscaling$HorizontalPodAutoscalerStatus.access$9600:(Lio/kubernetes/client/proto/V2beta2Autoscaling$HorizontalPodAutoscalerStatus;)Ljava/util/List;
     109: putfield      #11                 // Field currentMetrics_:Ljava/util/List;
     112: aload_0
     113: aload_0
     114: getfield      #21                 // Field bitField0_:I
     117: bipush        -17
     119: iand
     120: putfield      #21                 // Field bitField0_:I
     123: goto          144
     126: aload_0
     127: invokespecial #68                 // Method ensureCurrentMetricsIsMutable:()V
     130: aload_0
     131: getfield      #11                 // Field currentMetrics_:Ljava/util/List;
     134: aload_1
     135: invokestatic  #66                 // Method io/kubernetes/client/proto/V2beta2Autoscaling$HorizontalPodAutoscalerStatus.access$9600:(Lio/kubernetes/client/proto/V2beta2Autoscaling$HorizontalPodAutoscalerStatus;)Ljava/util/List;
     138: invokeinterface #69,  2           // InterfaceMethod java/util/List.addAll:(Ljava/util/Collection;)Z
     143: pop
     144: aload_0
     145: invokevirtual #70                 // Method onChanged:()V
     148: goto          237
     151: aload_1
     152: invokestatic  #66                 // Method io/kubernetes/client/proto/V2beta2Autoscaling$HorizontalPodAutoscalerStatus.access$9600:(Lio/kubernetes/client/proto/V2beta2Autoscaling$HorizontalPodAutoscalerStatus;)Ljava/util/List;
     155: invokeinterface #67,  1           // InterfaceMethod java/util/List.isEmpty:()Z
     160: ifne          237
     163: aload_0
     164: getfield      #26                 // Field currentMetricsBuilder_:Lcom/google/protobuf/RepeatedFieldBuilderV3;
     167: invokevirtual #71                 // Method com/google/protobuf/RepeatedFieldBuilderV3.isEmpty:()Z
     170: ifeq          225
     173: aload_0
     174: getfield      #26                 // Field currentMetricsBuilder_:Lcom/google/protobuf/RepeatedFieldBuilderV3;
     177: invokevirtual #72                 // Method com/google/protobuf/RepeatedFieldBuilderV3.dispose:()V
     180: aload_0
     181: aconst_null
     182: putfield      #26                 // Field currentMetricsBuilder_:Lcom/google/protobuf/RepeatedFieldBuilderV3;
     185: aload_0
     186: aload_1
     187: invokestatic  #66                 // Method io/kubernetes/client/proto/V2beta2Autoscaling$HorizontalPodAutoscalerStatus.access$9600:(Lio/kubernetes/client/proto/V2beta2Autoscaling$HorizontalPodAutoscalerStatus;)Ljava/util/List;
     190: putfield      #11                 // Field currentMetrics_:Ljava/util/List;
     193: aload_0
     194: aload_0
     195: getfield      #21                 // Field bitField0_:I
     198: bipush        -17
     200: iand
     201: putfield      #21                 // Field bitField0_:I
     204: aload_0
     205: invokestatic  #73                 // Method io/kubernetes/client/proto/V2beta2Autoscaling$HorizontalPodAutoscalerStatus.access$9900:()Z
     208: ifeq          218
     211: aload_0
     212: invokespecial #17                 // Method getCurrentMetricsFieldBuilder:()Lcom/google/protobuf/RepeatedFieldBuilderV3;
     215: goto          219
     218: aconst_null
     219: putfield      #26                 // Field currentMetricsBuilder_:Lcom/google/protobuf/RepeatedFieldBuilderV3;
     222: goto          237
     225: aload_0
     226: getfield      #26                 // Field currentMetricsBuilder_:Lcom/google/protobuf/RepeatedFieldBuilderV3;
     229: aload_1
     230: invokestatic  #66                 // Method io/kubernetes/client/proto/V2beta2Autoscaling$HorizontalPodAutoscalerStatus.access$9600:(Lio/kubernetes/client/proto/V2beta2Autoscaling$HorizontalPodAutoscalerStatus;)Ljava/util/List;
     233: invokevirtual #74                 // Method com/google/protobuf/RepeatedFieldBuilderV3.addAllMessages:(Ljava/lang/Iterable;)Lcom/google/protobuf/RepeatedFieldBuilderV3;
     236: pop
     237: aload_0
     238: getfield      #28                 // Field conditionsBuilder_:Lcom/google/protobuf/RepeatedFieldBuilderV3;
     241: ifnonnull     315
     244: aload_1
     245: invokestatic  #75                 // Method io/kubernetes/client/proto/V2beta2Autoscaling$HorizontalPodAutoscalerStatus.access$9700:(Lio/kubernetes/client/proto/V2beta2Autoscaling$HorizontalPodAutoscalerStatus;)Ljava/util/List;
     248: invokeinterface #67,  1           // InterfaceMethod java/util/List.isEmpty:()Z
     253: ifne          401
     256: aload_0
     257: getfield      #12                 // Field conditions_:Ljava/util/List;
     260: invokeinterface #67,  1           // InterfaceMethod java/util/List.isEmpty:()Z
     265: ifeq          290
     268: aload_0
     269: aload_1
     270: invokestatic  #75                 // Method io/kubernetes/client/proto/V2beta2Autoscaling$HorizontalPodAutoscalerStatus.access$9700:(Lio/kubernetes/client/proto/V2beta2Autoscaling$HorizontalPodAutoscalerStatus;)Ljava/util/List;
     273: putfield      #12                 // Field conditions_:Ljava/util/List;
     276: aload_0
     277: aload_0
     278: getfield      #21                 // Field bitField0_:I
     281: bipush        -33
     283: iand
     284: putfield      #21                 // Field bitField0_:I
     287: goto          308
     290: aload_0
     291: invokespecial #76                 // Method ensureConditionsIsMutable:()V
     294: aload_0
     295: getfield      #12                 // Field conditions_:Ljava/util/List;
     298: aload_1
     299: invokestatic  #75                 // Method io/kubernetes/client/proto/V2beta2Autoscaling$HorizontalPodAutoscalerStatus.access$9700:(Lio/kubernetes/client/proto/V2beta2Autoscaling$HorizontalPodAutoscalerStatus;)Ljava/util/List;
     302: invokeinterface #69,  2           // InterfaceMethod java/util/List.addAll:(Ljava/util/Collection;)Z
     307: pop
     308: aload_0
     309: invokevirtual #70                 // Method onChanged:()V
     312: goto          401
     315: aload_1
     316: invokestatic  #75                 // Method io/kubernetes/client/proto/V2beta2Autoscaling$HorizontalPodAutoscalerStatus.access$9700:(Lio/kubernetes/client/proto/V2beta2Autoscaling$HorizontalPodAutoscalerStatus;)Ljava/util/List;
     319: invokeinterface #67,  1           // InterfaceMethod java/util/List.isEmpty:()Z
     324: ifne          401
     327: aload_0
     328: getfield      #28                 // Field conditionsBuilder_:Lcom/google/protobuf/RepeatedFieldBuilderV3;
     331: invokevirtual #71                 // Method com/google/protobuf/RepeatedFieldBuilderV3.isEmpty:()Z
     334: ifeq          389
     337: aload_0
     338: getfield      #28                 // Field conditionsBuilder_:Lcom/google/protobuf/RepeatedFieldBuilderV3;
     341: invokevirtual #72                 // Method com/google/protobuf/RepeatedFieldBuilderV3.dispose:()V
     344: aload_0
     345: aconst_null
     346: putfield      #28                 // Field conditionsBuilder_:Lcom/google/protobuf/RepeatedFieldBuilderV3;
     349: aload_0
     350: aload_1
     351: invokestatic  #75                 // Method io/kubernetes/client/proto/V2beta2Autoscaling$HorizontalPodAutoscalerStatus.access$9700:(Lio/kubernetes/client/proto/V2beta2Autoscaling$HorizontalPodAutoscalerStatus;)Ljava/util/List;
     354: putfield      #12                 // Field conditions_:Ljava/util/List;
     357: aload_0
     358: aload_0
     359: getfield      #21                 // Field bitField0_:I
     362: bipush        -33
     364: iand
     365: putfield      #21                 // Field bitField0_:I
     368: aload_0
     369: invokestatic  #77                 // Method io/kubernetes/client/proto/V2beta2Autoscaling$HorizontalPodAutoscalerStatus.access$10000:()Z
     372: ifeq          382
     375: aload_0
     376: invokespecial #18                 // Method getConditionsFieldBuilder:()Lcom/google/protobuf/RepeatedFieldBuilderV3;
     379: goto          383
     382: aconst_null
     383: putfield      #28                 // Field conditionsBuilder_:Lcom/google/protobuf/RepeatedFieldBuilderV3;
     386: goto          401
     389: aload_0
     390: getfield      #28                 // Field conditionsBuilder_:Lcom/google/protobuf/RepeatedFieldBuilderV3;
     393: aload_1
     394: invokestatic  #75                 // Method io/kubernetes/client/proto/V2beta2Autoscaling$HorizontalPodAutoscalerStatus.access$9700:(Lio/kubernetes/client/proto/V2beta2Autoscaling$HorizontalPodAutoscalerStatus;)Ljava/util/List;
     397: invokevirtual #74                 // Method com/google/protobuf/RepeatedFieldBuilderV3.addAllMessages:(Ljava/lang/Iterable;)Lcom/google/protobuf/RepeatedFieldBuilderV3;
     400: pop
     401: aload_0
     402: aload_1
     403: invokestatic  #78                 // Method io/kubernetes/client/proto/V2beta2Autoscaling$HorizontalPodAutoscalerStatus.access$10100:(Lio/kubernetes/client/proto/V2beta2Autoscaling$HorizontalPodAutoscalerStatus;)Lcom/google/protobuf/UnknownFieldSet;
     406: invokevirtual #79                 // Method mergeUnknownFields:(Lcom/google/protobuf/UnknownFieldSet;)Lio/kubernetes/client/proto/V2beta2Autoscaling$HorizontalPodAutoscalerStatus$Builder;
     409: pop
     410: aload_0
     411: invokevirtual #70                 // Method onChanged:()V
     414: aload_0
     415: areturn

  public final boolean isInitialized();
    Code:
       0: iconst_1
       1: ireturn

  public io.kubernetes.client.proto.V2beta2Autoscaling$HorizontalPodAutoscalerStatus$Builder mergeFrom(com.google.protobuf.CodedInputStream, com.google.protobuf.ExtensionRegistryLite) throws java.io.IOException;
    Code:
       0: aconst_null
       1: astore_3
       2: getstatic     #80                 // Field io/kubernetes/client/proto/V2beta2Autoscaling$HorizontalPodAutoscalerStatus.PARSER:Lcom/google/protobuf/Parser;
       5: aload_1
       6: aload_2
       7: invokeinterface #81,  3           // InterfaceMethod com/google/protobuf/Parser.parsePartialFrom:(Lcom/google/protobuf/CodedInputStream;Lcom/google/protobuf/ExtensionRegistryLite;)Ljava/lang/Object;
      12: checkcast     #5                  // class io/kubernetes/client/proto/V2beta2Autoscaling$HorizontalPodAutoscalerStatus
      15: astore_3
      16: aload_3
      17: ifnull        61
      20: aload_0
      21: aload_3
      22: invokevirtual #52                 // Method mergeFrom:(Lio/kubernetes/client/proto/V2beta2Autoscaling$HorizontalPodAutoscalerStatus;)Lio/kubernetes/client/proto/V2beta2Autoscaling$HorizontalPodAutoscalerStatus$Builder;
      25: pop
      26: goto          61
      29: astore        4
      31: aload         4
      33: invokevirtual #83                 // Method com/google/protobuf/InvalidProtocolBufferException.getUnfinishedMessage:()Lcom/google/protobuf/MessageLite;
      36: checkcast     #5                  // class io/kubernetes/client/proto/V2beta2Autoscaling$HorizontalPodAutoscalerStatus
      39: astore_3
      40: aload         4
      42: invokevirtual #84                 // Method com/google/protobuf/InvalidProtocolBufferException.unwrapIOException:()Ljava/io/IOException;
      45: athrow
      46: astore        5
      48: aload_3
      49: ifnull        58
      52: aload_0
      53: aload_3
      54: invokevirtual #52                 // Method mergeFrom:(Lio/kubernetes/client/proto/V2beta2Autoscaling$HorizontalPodAutoscalerStatus;)Lio/kubernetes/client/proto/V2beta2Autoscaling$HorizontalPodAutoscalerStatus$Builder;
      57: pop
      58: aload         5
      60: athrow
      61: aload_0
      62: areturn
    Exception table:
       from    to  target type
           2    16    29   Class com/google/protobuf/InvalidProtocolBufferException
           2    16    46   any
          29    48    46   any

  public boolean hasObservedGeneration();
    Code:
       0: aload_0
       1: getfield      #21                 // Field bitField0_:I
       4: iconst_1
       5: iand
       6: iconst_1
       7: if_icmpne     14
      10: iconst_1
      11: goto          15
      14: iconst_0
      15: ireturn

  public long getObservedGeneration();
    Code:
       0: aload_0
       1: getfield      #20                 // Field observedGeneration_:J
       4: lreturn

  public io.kubernetes.client.proto.V2beta2Autoscaling$HorizontalPodAutoscalerStatus$Builder setObservedGeneration(long);
    Code:
       0: aload_0
       1: dup
       2: getfield      #21                 // Field bitField0_:I
       5: iconst_1
       6: ior
       7: putfield      #21                 // Field bitField0_:I
      10: aload_0
      11: lload_1
      12: putfield      #20                 // Field observedGeneration_:J
      15: aload_0
      16: invokevirtual #70                 // Method onChanged:()V
      19: aload_0
      20: areturn

  public io.kubernetes.client.proto.V2beta2Autoscaling$HorizontalPodAutoscalerStatus$Builder clearObservedGeneration();
    Code:
       0: aload_0
       1: aload_0
       2: getfield      #21                 // Field bitField0_:I
       5: bipush        -2
       7: iand
       8: putfield      #21                 // Field bitField0_:I
      11: aload_0
      12: lconst_0
      13: putfield      #20                 // Field observedGeneration_:J
      16: aload_0
      17: invokevirtual #70                 // Method onChanged:()V
      20: aload_0
      21: areturn

  public boolean hasLastScaleTime();
    Code:
       0: aload_0
       1: getfield      #21                 // Field bitField0_:I
       4: iconst_2
       5: iand
       6: iconst_2
       7: if_icmpne     14
      10: iconst_1
      11: goto          15
      14: iconst_0
      15: ireturn

  public io.kubernetes.client.proto.Meta$Time getLastScaleTime();
    Code:
       0: aload_0
       1: getfield      #22                 // Field lastScaleTimeBuilder_:Lcom/google/protobuf/SingleFieldBuilderV3;
       4: ifnonnull     25
       7: aload_0
       8: getfield      #9                  // Field lastScaleTime_:Lio/kubernetes/client/proto/Meta$Time;
      11: ifnonnull     20
      14: invokestatic  #85                 // Method io/kubernetes/client/proto/Meta$Time.getDefaultInstance:()Lio/kubernetes/client/proto/Meta$Time;
      17: goto          24
      20: aload_0
      21: getfield      #9                  // Field lastScaleTime_:Lio/kubernetes/client/proto/Meta$Time;
      24: areturn
      25: aload_0
      26: getfield      #22                 // Field lastScaleTimeBuilder_:Lcom/google/protobuf/SingleFieldBuilderV3;
      29: invokevirtual #86                 // Method com/google/protobuf/SingleFieldBuilderV3.getMessage:()Lcom/google/protobuf/AbstractMessage;
      32: checkcast     #37                 // class io/kubernetes/client/proto/Meta$Time
      35: areturn

  public io.kubernetes.client.proto.V2beta2Autoscaling$HorizontalPodAutoscalerStatus$Builder setLastScaleTime(io.kubernetes.client.proto.Meta$Time);
    Code:
       0: aload_0
       1: getfield      #22                 // Field lastScaleTimeBuilder_:Lcom/google/protobuf/SingleFieldBuilderV3;
       4: ifnonnull     31
       7: aload_1
       8: ifnonnull     19
      11: new           #87                 // class java/lang/NullPointerException
      14: dup
      15: invokespecial #88                 // Method java/lang/NullPointerException."<init>":()V
      18: athrow
      19: aload_0
      20: aload_1
      21: putfield      #9                  // Field lastScaleTime_:Lio/kubernetes/client/proto/Meta$Time;
      24: aload_0
      25: invokevirtual #70                 // Method onChanged:()V
      28: goto          40
      31: aload_0
      32: getfield      #22                 // Field lastScaleTimeBuilder_:Lcom/google/protobuf/SingleFieldBuilderV3;
      35: aload_1
      36: invokevirtual #89                 // Method com/google/protobuf/SingleFieldBuilderV3.setMessage:(Lcom/google/protobuf/AbstractMessage;)Lcom/google/protobuf/SingleFieldBuilderV3;
      39: pop
      40: aload_0
      41: dup
      42: getfield      #21                 // Field bitField0_:I
      45: iconst_2
      46: ior
      47: putfield      #21                 // Field bitField0_:I
      50: aload_0
      51: areturn

  public io.kubernetes.client.proto.V2beta2Autoscaling$HorizontalPodAutoscalerStatus$Builder setLastScaleTime(io.kubernetes.client.proto.Meta$Time$Builder);
    Code:
       0: aload_0
       1: getfield      #22                 // Field lastScaleTimeBuilder_:Lcom/google/protobuf/SingleFieldBuilderV3;
       4: ifnonnull     22
       7: aload_0
       8: aload_1
       9: invokevirtual #90                 // Method io/kubernetes/client/proto/Meta$Time$Builder.build:()Lio/kubernetes/client/proto/Meta$Time;
      12: putfield      #9                  // Field lastScaleTime_:Lio/kubernetes/client/proto/Meta$Time;
      15: aload_0
      16: invokevirtual #70                 // Method onChanged:()V
      19: goto          34
      22: aload_0
      23: getfield      #22                 // Field lastScaleTimeBuilder_:Lcom/google/protobuf/SingleFieldBuilderV3;
      26: aload_1
      27: invokevirtual #90                 // Method io/kubernetes/client/proto/Meta$Time$Builder.build:()Lio/kubernetes/client/proto/Meta$Time;
      30: invokevirtual #89                 // Method com/google/protobuf/SingleFieldBuilderV3.setMessage:(Lcom/google/protobuf/AbstractMessage;)Lcom/google/protobuf/SingleFieldBuilderV3;
      33: pop
      34: aload_0
      35: dup
      36: getfield      #21                 // Field bitField0_:I
      39: iconst_2
      40: ior
      41: putfield      #21                 // Field bitField0_:I
      44: aload_0
      45: areturn

  public io.kubernetes.client.proto.V2beta2Autoscaling$HorizontalPodAutoscalerStatus$Builder mergeLastScaleTime(io.kubernetes.client.proto.Meta$Time);
    Code:
       0: aload_0
       1: getfield      #22                 // Field lastScaleTimeBuilder_:Lcom/google/protobuf/SingleFieldBuilderV3;
       4: ifnonnull     67
       7: aload_0
       8: getfield      #21                 // Field bitField0_:I
      11: iconst_2
      12: iand
      13: iconst_2
      14: if_icmpne     55
      17: aload_0
      18: getfield      #9                  // Field lastScaleTime_:Lio/kubernetes/client/proto/Meta$Time;
      21: ifnull        55
      24: aload_0
      25: getfield      #9                  // Field lastScaleTime_:Lio/kubernetes/client/proto/Meta$Time;
      28: invokestatic  #85                 // Method io/kubernetes/client/proto/Meta$Time.getDefaultInstance:()Lio/kubernetes/client/proto/Meta$Time;
      31: if_acmpeq     55
      34: aload_0
      35: aload_0
      36: getfield      #9                  // Field lastScaleTime_:Lio/kubernetes/client/proto/Meta$Time;
      39: invokestatic  #91                 // Method io/kubernetes/client/proto/Meta$Time.newBuilder:(Lio/kubernetes/client/proto/Meta$Time;)Lio/kubernetes/client/proto/Meta$Time$Builder;
      42: aload_1
      43: invokevirtual #92                 // Method io/kubernetes/client/proto/Meta$Time$Builder.mergeFrom:(Lio/kubernetes/client/proto/Meta$Time;)Lio/kubernetes/client/proto/Meta$Time$Builder;
      46: invokevirtual #93                 // Method io/kubernetes/client/proto/Meta$Time$Builder.buildPartial:()Lio/kubernetes/client/proto/Meta$Time;
      49: putfield      #9                  // Field lastScaleTime_:Lio/kubernetes/client/proto/Meta$Time;
      52: goto          60
      55: aload_0
      56: aload_1
      57: putfield      #9                  // Field lastScaleTime_:Lio/kubernetes/client/proto/Meta$Time;
      60: aload_0
      61: invokevirtual #70                 // Method onChanged:()V
      64: goto          76
      67: aload_0
      68: getfield      #22                 // Field lastScaleTimeBuilder_:Lcom/google/protobuf/SingleFieldBuilderV3;
      71: aload_1
      72: invokevirtual #94                 // Method com/google/protobuf/SingleFieldBuilderV3.mergeFrom:(Lcom/google/protobuf/AbstractMessage;)Lcom/google/protobuf/SingleFieldBuilderV3;
      75: pop
      76: aload_0
      77: dup
      78: getfield      #21                 // Field bitField0_:I
      81: iconst_2
      82: ior
      83: putfield      #21                 // Field bitField0_:I
      86: aload_0
      87: areturn

  public io.kubernetes.client.proto.V2beta2Autoscaling$HorizontalPodAutoscalerStatus$Builder clearLastScaleTime();
    Code:
       0: aload_0
       1: getfield      #22                 // Field lastScaleTimeBuilder_:Lcom/google/protobuf/SingleFieldBuilderV3;
       4: ifnonnull     19
       7: aload_0
       8: aconst_null
       9: putfield      #9                  // Field lastScaleTime_:Lio/kubernetes/client/proto/Meta$Time;
      12: aload_0
      13: invokevirtual #70                 // Method onChanged:()V
      16: goto          27
      19: aload_0
      20: getfield      #22                 // Field lastScaleTimeBuilder_:Lcom/google/protobuf/SingleFieldBuilderV3;
      23: invokevirtual #23                 // Method com/google/protobuf/SingleFieldBuilderV3.clear:()Lcom/google/protobuf/SingleFieldBuilderV3;
      26: pop
      27: aload_0
      28: aload_0
      29: getfield      #21                 // Field bitField0_:I
      32: bipush        -3
      34: iand
      35: putfield      #21                 // Field bitField0_:I
      38: aload_0
      39: areturn

  public io.kubernetes.client.proto.Meta$Time$Builder getLastScaleTimeBuilder();
    Code:
       0: aload_0
       1: dup
       2: getfield      #21                 // Field bitField0_:I
       5: iconst_2
       6: ior
       7: putfield      #21                 // Field bitField0_:I
      10: aload_0
      11: invokevirtual #70                 // Method onChanged:()V
      14: aload_0
      15: invokespecial #16                 // Method getLastScaleTimeFieldBuilder:()Lcom/google/protobuf/SingleFieldBuilderV3;
      18: invokevirtual #95                 // Method com/google/protobuf/SingleFieldBuilderV3.getBuilder:()Lcom/google/protobuf/AbstractMessage$Builder;
      21: checkcast     #96                 // class io/kubernetes/client/proto/Meta$Time$Builder
      24: areturn

  public io.kubernetes.client.proto.Meta$TimeOrBuilder getLastScaleTimeOrBuilder();
    Code:
       0: aload_0
       1: getfield      #22                 // Field lastScaleTimeBuilder_:Lcom/google/protobuf/SingleFieldBuilderV3;
       4: ifnull        18
       7: aload_0
       8: getfield      #22                 // Field lastScaleTimeBuilder_:Lcom/google/protobuf/SingleFieldBuilderV3;
      11: invokevirtual #97                 // Method com/google/protobuf/SingleFieldBuilderV3.getMessageOrBuilder:()Lcom/google/protobuf/MessageOrBuilder;
      14: checkcast     #98                 // class io/kubernetes/client/proto/Meta$TimeOrBuilder
      17: areturn
      18: aload_0
      19: getfield      #9                  // Field lastScaleTime_:Lio/kubernetes/client/proto/Meta$Time;
      22: ifnonnull     31
      25: invokestatic  #85                 // Method io/kubernetes/client/proto/Meta$Time.getDefaultInstance:()Lio/kubernetes/client/proto/Meta$Time;
      28: goto          35
      31: aload_0
      32: getfield      #9                  // Field lastScaleTime_:Lio/kubernetes/client/proto/Meta$Time;
      35: areturn

  private com.google.protobuf.SingleFieldBuilderV3<io.kubernetes.client.proto.Meta$Time, io.kubernetes.client.proto.Meta$Time$Builder, io.kubernetes.client.proto.Meta$TimeOrBuilder> getLastScaleTimeFieldBuilder();
    Code:
       0: aload_0
       1: getfield      #22                 // Field lastScaleTimeBuilder_:Lcom/google/protobuf/SingleFieldBuilderV3;
       4: ifnonnull     35
       7: aload_0
       8: new           #99                 // class com/google/protobuf/SingleFieldBuilderV3
      11: dup
      12: aload_0
      13: invokevirtual #100                // Method getLastScaleTime:()Lio/kubernetes/client/proto/Meta$Time;
      16: aload_0
      17: invokevirtual #101                // Method getParentForChildren:()Lcom/google/protobuf/GeneratedMessageV3$BuilderParent;
      20: aload_0
      21: invokevirtual #102                // Method isClean:()Z
      24: invokespecial #103                // Method com/google/protobuf/SingleFieldBuilderV3."<init>":(Lcom/google/protobuf/AbstractMessage;Lcom/google/protobuf/AbstractMessage$BuilderParent;Z)V
      27: putfield      #22                 // Field lastScaleTimeBuilder_:Lcom/google/protobuf/SingleFieldBuilderV3;
      30: aload_0
      31: aconst_null
      32: putfield      #9                  // Field lastScaleTime_:Lio/kubernetes/client/proto/Meta$Time;
      35: aload_0
      36: getfield      #22                 // Field lastScaleTimeBuilder_:Lcom/google/protobuf/SingleFieldBuilderV3;
      39: areturn

  public boolean hasCurrentReplicas();
    Code:
       0: aload_0
       1: getfield      #21                 // Field bitField0_:I
       4: iconst_4
       5: iand
       6: iconst_4
       7: if_icmpne     14
      10: iconst_1
      11: goto          15
      14: iconst_0
      15: ireturn

  public int getCurrentReplicas();
    Code:
       0: aload_0
       1: getfield      #24                 // Field currentReplicas_:I
       4: ireturn

  public io.kubernetes.client.proto.V2beta2Autoscaling$HorizontalPodAutoscalerStatus$Builder setCurrentReplicas(int);
    Code:
       0: aload_0
       1: dup
       2: getfield      #21                 // Field bitField0_:I
       5: iconst_4
       6: ior
       7: putfield      #21                 // Field bitField0_:I
      10: aload_0
      11: iload_1
      12: putfield      #24                 // Field currentReplicas_:I
      15: aload_0
      16: invokevirtual #70                 // Method onChanged:()V
      19: aload_0
      20: areturn

  public io.kubernetes.client.proto.V2beta2Autoscaling$HorizontalPodAutoscalerStatus$Builder clearCurrentReplicas();
    Code:
       0: aload_0
       1: aload_0
       2: getfield      #21                 // Field bitField0_:I
       5: bipush        -5
       7: iand
       8: putfield      #21                 // Field bitField0_:I
      11: aload_0
      12: iconst_0
      13: putfield      #24                 // Field currentReplicas_:I
      16: aload_0
      17: invokevirtual #70                 // Method onChanged:()V
      20: aload_0
      21: areturn

  public boolean hasDesiredReplicas();
    Code:
       0: aload_0
       1: getfield      #21                 // Field bitField0_:I
       4: bipush        8
       6: iand
       7: bipush        8
       9: if_icmpne     16
      12: iconst_1
      13: goto          17
      16: iconst_0
      17: ireturn

  public int getDesiredReplicas();
    Code:
       0: aload_0
       1: getfield      #25                 // Field desiredReplicas_:I
       4: ireturn

  public io.kubernetes.client.proto.V2beta2Autoscaling$HorizontalPodAutoscalerStatus$Builder setDesiredReplicas(int);
    Code:
       0: aload_0
       1: dup
       2: getfield      #21                 // Field bitField0_:I
       5: bipush        8
       7: ior
       8: putfield      #21                 // Field bitField0_:I
      11: aload_0
      12: iload_1
      13: putfield      #25                 // Field desiredReplicas_:I
      16: aload_0
      17: invokevirtual #70                 // Method onChanged:()V
      20: aload_0
      21: areturn

  public io.kubernetes.client.proto.V2beta2Autoscaling$HorizontalPodAutoscalerStatus$Builder clearDesiredReplicas();
    Code:
       0: aload_0
       1: aload_0
       2: getfield      #21                 // Field bitField0_:I
       5: bipush        -9
       7: iand
       8: putfield      #21                 // Field bitField0_:I
      11: aload_0
      12: iconst_0
      13: putfield      #25                 // Field desiredReplicas_:I
      16: aload_0
      17: invokevirtual #70                 // Method onChanged:()V
      20: aload_0
      21: areturn

  private void ensureCurrentMetricsIsMutable();
    Code:
       0: aload_0
       1: getfield      #21                 // Field bitField0_:I
       4: bipush        16
       6: iand
       7: bipush        16
       9: if_icmpeq     38
      12: aload_0
      13: new           #104                // class java/util/ArrayList
      16: dup
      17: aload_0
      18: getfield      #11                 // Field currentMetrics_:Ljava/util/List;
      21: invokespecial #105                // Method java/util/ArrayList."<init>":(Ljava/util/Collection;)V
      24: putfield      #11                 // Field currentMetrics_:Ljava/util/List;
      27: aload_0
      28: dup
      29: getfield      #21                 // Field bitField0_:I
      32: bipush        16
      34: ior
      35: putfield      #21                 // Field bitField0_:I
      38: return

  public java.util.List<io.kubernetes.client.proto.V2beta2Autoscaling$MetricStatus> getCurrentMetricsList();
    Code:
       0: aload_0
       1: getfield      #26                 // Field currentMetricsBuilder_:Lcom/google/protobuf/RepeatedFieldBuilderV3;
       4: ifnonnull     15
       7: aload_0
       8: getfield      #11                 // Field currentMetrics_:Ljava/util/List;
      11: invokestatic  #40                 // Method java/util/Collections.unmodifiableList:(Ljava/util/List;)Ljava/util/List;
      14: areturn
      15: aload_0
      16: getfield      #26                 // Field currentMetricsBuilder_:Lcom/google/protobuf/RepeatedFieldBuilderV3;
      19: invokevirtual #106                // Method com/google/protobuf/RepeatedFieldBuilderV3.getMessageList:()Ljava/util/List;
      22: areturn

  public int getCurrentMetricsCount();
    Code:
       0: aload_0
       1: getfield      #26                 // Field currentMetricsBuilder_:Lcom/google/protobuf/RepeatedFieldBuilderV3;
       4: ifnonnull     17
       7: aload_0
       8: getfield      #11                 // Field currentMetrics_:Ljava/util/List;
      11: invokeinterface #107,  1          // InterfaceMethod java/util/List.size:()I
      16: ireturn
      17: aload_0
      18: getfield      #26                 // Field currentMetricsBuilder_:Lcom/google/protobuf/RepeatedFieldBuilderV3;
      21: invokevirtual #108                // Method com/google/protobuf/RepeatedFieldBuilderV3.getCount:()I
      24: ireturn

  public io.kubernetes.client.proto.V2beta2Autoscaling$MetricStatus getCurrentMetrics(int);
    Code:
       0: aload_0
       1: getfield      #26                 // Field currentMetricsBuilder_:Lcom/google/protobuf/RepeatedFieldBuilderV3;
       4: ifnonnull     21
       7: aload_0
       8: getfield      #11                 // Field currentMetrics_:Ljava/util/List;
      11: iload_1
      12: invokeinterface #109,  2          // InterfaceMethod java/util/List.get:(I)Ljava/lang/Object;
      17: checkcast     #110                // class io/kubernetes/client/proto/V2beta2Autoscaling$MetricStatus
      20: areturn
      21: aload_0
      22: getfield      #26                 // Field currentMetricsBuilder_:Lcom/google/protobuf/RepeatedFieldBuilderV3;
      25: iload_1
      26: invokevirtual #111                // Method com/google/protobuf/RepeatedFieldBuilderV3.getMessage:(I)Lcom/google/protobuf/AbstractMessage;
      29: checkcast     #110                // class io/kubernetes/client/proto/V2beta2Autoscaling$MetricStatus
      32: areturn

  public io.kubernetes.client.proto.V2beta2Autoscaling$HorizontalPodAutoscalerStatus$Builder setCurrentMetrics(int, io.kubernetes.client.proto.V2beta2Autoscaling$MetricStatus);
    Code:
       0: aload_0
       1: getfield      #26                 // Field currentMetricsBuilder_:Lcom/google/protobuf/RepeatedFieldBuilderV3;
       4: ifnonnull     42
       7: aload_2
       8: ifnonnull     19
      11: new           #87                 // class java/lang/NullPointerException
      14: dup
      15: invokespecial #88                 // Method java/lang/NullPointerException."<init>":()V
      18: athrow
      19: aload_0
      20: invokespecial #68                 // Method ensureCurrentMetricsIsMutable:()V
      23: aload_0
      24: getfield      #11                 // Field currentMetrics_:Ljava/util/List;
      27: iload_1
      28: aload_2
      29: invokeinterface #112,  3          // InterfaceMethod java/util/List.set:(ILjava/lang/Object;)Ljava/lang/Object;
      34: pop
      35: aload_0
      36: invokevirtual #70                 // Method onChanged:()V
      39: goto          52
      42: aload_0
      43: getfield      #26                 // Field currentMetricsBuilder_:Lcom/google/protobuf/RepeatedFieldBuilderV3;
      46: iload_1
      47: aload_2
      48: invokevirtual #113                // Method com/google/protobuf/RepeatedFieldBuilderV3.setMessage:(ILcom/google/protobuf/AbstractMessage;)Lcom/google/protobuf/RepeatedFieldBuilderV3;
      51: pop
      52: aload_0
      53: areturn

  public io.kubernetes.client.proto.V2beta2Autoscaling$HorizontalPodAutoscalerStatus$Builder setCurrentMetrics(int, io.kubernetes.client.proto.V2beta2Autoscaling$MetricStatus$Builder);
    Code:
       0: aload_0
       1: getfield      #26                 // Field currentMetricsBuilder_:Lcom/google/protobuf/RepeatedFieldBuilderV3;
       4: ifnonnull     33
       7: aload_0
       8: invokespecial #68                 // Method ensureCurrentMetricsIsMutable:()V
      11: aload_0
      12: getfield      #11                 // Field currentMetrics_:Ljava/util/List;
      15: iload_1
      16: aload_2
      17: invokevirtual #114                // Method io/kubernetes/client/proto/V2beta2Autoscaling$MetricStatus$Builder.build:()Lio/kubernetes/client/proto/V2beta2Autoscaling$MetricStatus;
      20: invokeinterface #112,  3          // InterfaceMethod java/util/List.set:(ILjava/lang/Object;)Ljava/lang/Object;
      25: pop
      26: aload_0
      27: invokevirtual #70                 // Method onChanged:()V
      30: goto          46
      33: aload_0
      34: getfield      #26                 // Field currentMetricsBuilder_:Lcom/google/protobuf/RepeatedFieldBuilderV3;
      37: iload_1
      38: aload_2
      39: invokevirtual #114                // Method io/kubernetes/client/proto/V2beta2Autoscaling$MetricStatus$Builder.build:()Lio/kubernetes/client/proto/V2beta2Autoscaling$MetricStatus;
      42: invokevirtual #113                // Method com/google/protobuf/RepeatedFieldBuilderV3.setMessage:(ILcom/google/protobuf/AbstractMessage;)Lcom/google/protobuf/RepeatedFieldBuilderV3;
      45: pop
      46: aload_0
      47: areturn

  public io.kubernetes.client.proto.V2beta2Autoscaling$HorizontalPodAutoscalerStatus$Builder addCurrentMetrics(io.kubernetes.client.proto.V2beta2Autoscaling$MetricStatus);
    Code:
       0: aload_0
       1: getfield      #26                 // Field currentMetricsBuilder_:Lcom/google/protobuf/RepeatedFieldBuilderV3;
       4: ifnonnull     41
       7: aload_1
       8: ifnonnull     19
      11: new           #87                 // class java/lang/NullPointerException
      14: dup
      15: invokespecial #88                 // Method java/lang/NullPointerException."<init>":()V
      18: athrow
      19: aload_0
      20: invokespecial #68                 // Method ensureCurrentMetricsIsMutable:()V
      23: aload_0
      24: getfield      #11                 // Field currentMetrics_:Ljava/util/List;
      27: aload_1
      28: invokeinterface #115,  2          // InterfaceMethod java/util/List.add:(Ljava/lang/Object;)Z
      33: pop
      34: aload_0
      35: invokevirtual #70                 // Method onChanged:()V
      38: goto          50
      41: aload_0
      42: getfield      #26                 // Field currentMetricsBuilder_:Lcom/google/protobuf/RepeatedFieldBuilderV3;
      45: aload_1
      46: invokevirtual #116                // Method com/google/protobuf/RepeatedFieldBuilderV3.addMessage:(Lcom/google/protobuf/AbstractMessage;)Lcom/google/protobuf/RepeatedFieldBuilderV3;
      49: pop
      50: aload_0
      51: areturn

  public io.kubernetes.client.proto.V2beta2Autoscaling$HorizontalPodAutoscalerStatus$Builder addCurrentMetrics(int, io.kubernetes.client.proto.V2beta2Autoscaling$MetricStatus);
    Code:
       0: aload_0
       1: getfield      #26                 // Field currentMetricsBuilder_:Lcom/google/protobuf/RepeatedFieldBuilderV3;
       4: ifnonnull     41
       7: aload_2
       8: ifnonnull     19
      11: new           #87                 // class java/lang/NullPointerException
      14: dup
      15: invokespecial #88                 // Method java/lang/NullPointerException."<init>":()V
      18: athrow
      19: aload_0
      20: invokespecial #68                 // Method ensureCurrentMetricsIsMutable:()V
      23: aload_0
      24: getfield      #11                 // Field currentMetrics_:Ljava/util/List;
      27: iload_1
      28: aload_2
      29: invokeinterface #117,  3          // InterfaceMethod java/util/List.add:(ILjava/lang/Object;)V
      34: aload_0
      35: invokevirtual #70                 // Method onChanged:()V
      38: goto          51
      41: aload_0
      42: getfield      #26                 // Field currentMetricsBuilder_:Lcom/google/protobuf/RepeatedFieldBuilderV3;
      45: iload_1
      46: aload_2
      47: invokevirtual #118                // Method com/google/protobuf/RepeatedFieldBuilderV3.addMessage:(ILcom/google/protobuf/AbstractMessage;)Lcom/google/protobuf/RepeatedFieldBuilderV3;
      50: pop
      51: aload_0
      52: areturn

  public io.kubernetes.client.proto.V2beta2Autoscaling$HorizontalPodAutoscalerStatus$Builder addCurrentMetrics(io.kubernetes.client.proto.V2beta2Autoscaling$MetricStatus$Builder);
    Code:
       0: aload_0
       1: getfield      #26                 // Field currentMetricsBuilder_:Lcom/google/protobuf/RepeatedFieldBuilderV3;
       4: ifnonnull     32
       7: aload_0
       8: invokespecial #68                 // Method ensureCurrentMetricsIsMutable:()V
      11: aload_0
      12: getfield      #11                 // Field currentMetrics_:Ljava/util/List;
      15: aload_1
      16: invokevirtual #114                // Method io/kubernetes/client/proto/V2beta2Autoscaling$MetricStatus$Builder.build:()Lio/kubernetes/client/proto/V2beta2Autoscaling$MetricStatus;
      19: invokeinterface #115,  2          // InterfaceMethod java/util/List.add:(Ljava/lang/Object;)Z
      24: pop
      25: aload_0
      26: invokevirtual #70                 // Method onChanged:()V
      29: goto          44
      32: aload_0
      33: getfield      #26                 // Field currentMetricsBuilder_:Lcom/google/protobuf/RepeatedFieldBuilderV3;
      36: aload_1
      37: invokevirtual #114                // Method io/kubernetes/client/proto/V2beta2Autoscaling$MetricStatus$Builder.build:()Lio/kubernetes/client/proto/V2beta2Autoscaling$MetricStatus;
      40: invokevirtual #116                // Method com/google/protobuf/RepeatedFieldBuilderV3.addMessage:(Lcom/google/protobuf/AbstractMessage;)Lcom/google/protobuf/RepeatedFieldBuilderV3;
      43: pop
      44: aload_0
      45: areturn

  public io.kubernetes.client.proto.V2beta2Autoscaling$HorizontalPodAutoscalerStatus$Builder addCurrentMetrics(int, io.kubernetes.client.proto.V2beta2Autoscaling$MetricStatus$Builder);
    Code:
       0: aload_0
       1: getfield      #26                 // Field currentMetricsBuilder_:Lcom/google/protobuf/RepeatedFieldBuilderV3;
       4: ifnonnull     32
       7: aload_0
       8: invokespecial #68                 // Method ensureCurrentMetricsIsMutable:()V
      11: aload_0
      12: getfield      #11                 // Field currentMetrics_:Ljava/util/List;
      15: iload_1
      16: aload_2
      17: invokevirtual #114                // Method io/kubernetes/client/proto/V2beta2Autoscaling$MetricStatus$Builder.build:()Lio/kubernetes/client/proto/V2beta2Autoscaling$MetricStatus;
      20: invokeinterface #117,  3          // InterfaceMethod java/util/List.add:(ILjava/lang/Object;)V
      25: aload_0
      26: invokevirtual #70                 // Method onChanged:()V
      29: goto          45
      32: aload_0
      33: getfield      #26                 // Field currentMetricsBuilder_:Lcom/google/protobuf/RepeatedFieldBuilderV3;
      36: iload_1
      37: aload_2
      38: invokevirtual #114                // Method io/kubernetes/client/proto/V2beta2Autoscaling$MetricStatus$Builder.build:()Lio/kubernetes/client/proto/V2beta2Autoscaling$MetricStatus;
      41: invokevirtual #118                // Method com/google/protobuf/RepeatedFieldBuilderV3.addMessage:(ILcom/google/protobuf/AbstractMessage;)Lcom/google/protobuf/RepeatedFieldBuilderV3;
      44: pop
      45: aload_0
      46: areturn

  public io.kubernetes.client.proto.V2beta2Autoscaling$HorizontalPodAutoscalerStatus$Builder addAllCurrentMetrics(java.lang.Iterable<? extends io.kubernetes.client.proto.V2beta2Autoscaling$MetricStatus>);
    Code:
       0: aload_0
       1: getfield      #26                 // Field currentMetricsBuilder_:Lcom/google/protobuf/RepeatedFieldBuilderV3;
       4: ifnonnull     26
       7: aload_0
       8: invokespecial #68                 // Method ensureCurrentMetricsIsMutable:()V
      11: aload_1
      12: aload_0
      13: getfield      #11                 // Field currentMetrics_:Ljava/util/List;
      16: invokestatic  #119                // Method com/google/protobuf/AbstractMessageLite$Builder.addAll:(Ljava/lang/Iterable;Ljava/util/List;)V
      19: aload_0
      20: invokevirtual #70                 // Method onChanged:()V
      23: goto          35
      26: aload_0
      27: getfield      #26                 // Field currentMetricsBuilder_:Lcom/google/protobuf/RepeatedFieldBuilderV3;
      30: aload_1
      31: invokevirtual #74                 // Method com/google/protobuf/RepeatedFieldBuilderV3.addAllMessages:(Ljava/lang/Iterable;)Lcom/google/protobuf/RepeatedFieldBuilderV3;
      34: pop
      35: aload_0
      36: areturn

  public io.kubernetes.client.proto.V2beta2Autoscaling$HorizontalPodAutoscalerStatus$Builder clearCurrentMetrics();
    Code:
       0: aload_0
       1: getfield      #26                 // Field currentMetricsBuilder_:Lcom/google/protobuf/RepeatedFieldBuilderV3;
       4: ifnonnull     32
       7: aload_0
       8: invokestatic  #10                 // Method java/util/Collections.emptyList:()Ljava/util/List;
      11: putfield      #11                 // Field currentMetrics_:Ljava/util/List;
      14: aload_0
      15: aload_0
      16: getfield      #21                 // Field bitField0_:I
      19: bipush        -17
      21: iand
      22: putfield      #21                 // Field bitField0_:I
      25: aload_0
      26: invokevirtual #70                 // Method onChanged:()V
      29: goto          39
      32: aload_0
      33: getfield      #26                 // Field currentMetricsBuilder_:Lcom/google/protobuf/RepeatedFieldBuilderV3;
      36: invokevirtual #27                 // Method com/google/protobuf/RepeatedFieldBuilderV3.clear:()V
      39: aload_0
      40: areturn

  public io.kubernetes.client.proto.V2beta2Autoscaling$HorizontalPodAutoscalerStatus$Builder removeCurrentMetrics(int);
    Code:
       0: aload_0
       1: getfield      #26                 // Field currentMetricsBuilder_:Lcom/google/protobuf/RepeatedFieldBuilderV3;
       4: ifnonnull     29
       7: aload_0
       8: invokespecial #68                 // Method ensureCurrentMetricsIsMutable:()V
      11: aload_0
      12: getfield      #11                 // Field currentMetrics_:Ljava/util/List;
      15: iload_1
      16: invokeinterface #120,  2          // InterfaceMethod java/util/List.remove:(I)Ljava/lang/Object;
      21: pop
      22: aload_0
      23: invokevirtual #70                 // Method onChanged:()V
      26: goto          37
      29: aload_0
      30: getfield      #26                 // Field currentMetricsBuilder_:Lcom/google/protobuf/RepeatedFieldBuilderV3;
      33: iload_1
      34: invokevirtual #121                // Method com/google/protobuf/RepeatedFieldBuilderV3.remove:(I)V
      37: aload_0
      38: areturn

  public io.kubernetes.client.proto.V2beta2Autoscaling$MetricStatus$Builder getCurrentMetricsBuilder(int);
    Code:
       0: aload_0
       1: invokespecial #17                 // Method getCurrentMetricsFieldBuilder:()Lcom/google/protobuf/RepeatedFieldBuilderV3;
       4: iload_1
       5: invokevirtual #122                // Method com/google/protobuf/RepeatedFieldBuilderV3.getBuilder:(I)Lcom/google/protobuf/AbstractMessage$Builder;
       8: checkcast     #123                // class io/kubernetes/client/proto/V2beta2Autoscaling$MetricStatus$Builder
      11: areturn

  public io.kubernetes.client.proto.V2beta2Autoscaling$MetricStatusOrBuilder getCurrentMetricsOrBuilder(int);
    Code:
       0: aload_0
       1: getfield      #26                 // Field currentMetricsBuilder_:Lcom/google/protobuf/RepeatedFieldBuilderV3;
       4: ifnonnull     21
       7: aload_0
       8: getfield      #11                 // Field currentMetrics_:Ljava/util/List;
      11: iload_1
      12: invokeinterface #109,  2          // InterfaceMethod java/util/List.get:(I)Ljava/lang/Object;
      17: checkcast     #124                // class io/kubernetes/client/proto/V2beta2Autoscaling$MetricStatusOrBuilder
      20: areturn
      21: aload_0
      22: getfield      #26                 // Field currentMetricsBuilder_:Lcom/google/protobuf/RepeatedFieldBuilderV3;
      25: iload_1
      26: invokevirtual #125                // Method com/google/protobuf/RepeatedFieldBuilderV3.getMessageOrBuilder:(I)Lcom/google/protobuf/MessageOrBuilder;
      29: checkcast     #124                // class io/kubernetes/client/proto/V2beta2Autoscaling$MetricStatusOrBuilder
      32: areturn

  public java.util.List<? extends io.kubernetes.client.proto.V2beta2Autoscaling$MetricStatusOrBuilder> getCurrentMetricsOrBuilderList();
    Code:
       0: aload_0
       1: getfield      #26                 // Field currentMetricsBuilder_:Lcom/google/protobuf/RepeatedFieldBuilderV3;
       4: ifnull        15
       7: aload_0
       8: getfield      #26                 // Field currentMetricsBuilder_:Lcom/google/protobuf/RepeatedFieldBuilderV3;
      11: invokevirtual #126                // Method com/google/protobuf/RepeatedFieldBuilderV3.getMessageOrBuilderList:()Ljava/util/List;
      14: areturn
      15: aload_0
      16: getfield      #11                 // Field currentMetrics_:Ljava/util/List;
      19: invokestatic  #40                 // Method java/util/Collections.unmodifiableList:(Ljava/util/List;)Ljava/util/List;
      22: areturn

  public io.kubernetes.client.proto.V2beta2Autoscaling$MetricStatus$Builder addCurrentMetricsBuilder();
    Code:
       0: aload_0
       1: invokespecial #17                 // Method getCurrentMetricsFieldBuilder:()Lcom/google/protobuf/RepeatedFieldBuilderV3;
       4: invokestatic  #127                // Method io/kubernetes/client/proto/V2beta2Autoscaling$MetricStatus.getDefaultInstance:()Lio/kubernetes/client/proto/V2beta2Autoscaling$MetricStatus;
       7: invokevirtual #128                // Method com/google/protobuf/RepeatedFieldBuilderV3.addBuilder:(Lcom/google/protobuf/AbstractMessage;)Lcom/google/protobuf/AbstractMessage$Builder;
      10: checkcast     #123                // class io/kubernetes/client/proto/V2beta2Autoscaling$MetricStatus$Builder
      13: areturn

  public io.kubernetes.client.proto.V2beta2Autoscaling$MetricStatus$Builder addCurrentMetricsBuilder(int);
    Code:
       0: aload_0
       1: invokespecial #17                 // Method getCurrentMetricsFieldBuilder:()Lcom/google/protobuf/RepeatedFieldBuilderV3;
       4: iload_1
       5: invokestatic  #127                // Method io/kubernetes/client/proto/V2beta2Autoscaling$MetricStatus.getDefaultInstance:()Lio/kubernetes/client/proto/V2beta2Autoscaling$MetricStatus;
       8: invokevirtual #129                // Method com/google/protobuf/RepeatedFieldBuilderV3.addBuilder:(ILcom/google/protobuf/AbstractMessage;)Lcom/google/protobuf/AbstractMessage$Builder;
      11: checkcast     #123                // class io/kubernetes/client/proto/V2beta2Autoscaling$MetricStatus$Builder
      14: areturn

  public java.util.List<io.kubernetes.client.proto.V2beta2Autoscaling$MetricStatus$Builder> getCurrentMetricsBuilderList();
    Code:
       0: aload_0
       1: invokespecial #17                 // Method getCurrentMetricsFieldBuilder:()Lcom/google/protobuf/RepeatedFieldBuilderV3;
       4: invokevirtual #130                // Method com/google/protobuf/RepeatedFieldBuilderV3.getBuilderList:()Ljava/util/List;
       7: areturn

  private com.google.protobuf.RepeatedFieldBuilderV3<io.kubernetes.client.proto.V2beta2Autoscaling$MetricStatus, io.kubernetes.client.proto.V2beta2Autoscaling$MetricStatus$Builder, io.kubernetes.client.proto.V2beta2Autoscaling$MetricStatusOrBuilder> getCurrentMetricsFieldBuilder();
    Code:
       0: aload_0
       1: getfield      #26                 // Field currentMetricsBuilder_:Lcom/google/protobuf/RepeatedFieldBuilderV3;
       4: ifnonnull     52
       7: aload_0
       8: new           #131                // class com/google/protobuf/RepeatedFieldBuilderV3
      11: dup
      12: aload_0
      13: getfield      #11                 // Field currentMetrics_:Ljava/util/List;
      16: aload_0
      17: getfield      #21                 // Field bitField0_:I
      20: bipush        16
      22: iand
      23: bipush        16
      25: if_icmpne     32
      28: iconst_1
      29: goto          33
      32: iconst_0
      33: aload_0
      34: invokevirtual #101                // Method getParentForChildren:()Lcom/google/protobuf/GeneratedMessageV3$BuilderParent;
      37: aload_0
      38: invokevirtual #102                // Method isClean:()Z
      41: invokespecial #132                // Method com/google/protobuf/RepeatedFieldBuilderV3."<init>":(Ljava/util/List;ZLcom/google/protobuf/AbstractMessage$BuilderParent;Z)V
      44: putfield      #26                 // Field currentMetricsBuilder_:Lcom/google/protobuf/RepeatedFieldBuilderV3;
      47: aload_0
      48: aconst_null
      49: putfield      #11                 // Field currentMetrics_:Ljava/util/List;
      52: aload_0
      53: getfield      #26                 // Field currentMetricsBuilder_:Lcom/google/protobuf/RepeatedFieldBuilderV3;
      56: areturn

  private void ensureConditionsIsMutable();
    Code:
       0: aload_0
       1: getfield      #21                 // Field bitField0_:I
       4: bipush        32
       6: iand
       7: bipush        32
       9: if_icmpeq     38
      12: aload_0
      13: new           #104                // class java/util/ArrayList
      16: dup
      17: aload_0
      18: getfield      #12                 // Field conditions_:Ljava/util/List;
      21: invokespecial #105                // Method java/util/ArrayList."<init>":(Ljava/util/Collection;)V
      24: putfield      #12                 // Field conditions_:Ljava/util/List;
      27: aload_0
      28: dup
      29: getfield      #21                 // Field bitField0_:I
      32: bipush        32
      34: ior
      35: putfield      #21                 // Field bitField0_:I
      38: return

  public java.util.List<io.kubernetes.client.proto.V2beta2Autoscaling$HorizontalPodAutoscalerCondition> getConditionsList();
    Code:
       0: aload_0
       1: getfield      #28                 // Field conditionsBuilder_:Lcom/google/protobuf/RepeatedFieldBuilderV3;
       4: ifnonnull     15
       7: aload_0
       8: getfield      #12                 // Field conditions_:Ljava/util/List;
      11: invokestatic  #40                 // Method java/util/Collections.unmodifiableList:(Ljava/util/List;)Ljava/util/List;
      14: areturn
      15: aload_0
      16: getfield      #28                 // Field conditionsBuilder_:Lcom/google/protobuf/RepeatedFieldBuilderV3;
      19: invokevirtual #106                // Method com/google/protobuf/RepeatedFieldBuilderV3.getMessageList:()Ljava/util/List;
      22: areturn

  public int getConditionsCount();
    Code:
       0: aload_0
       1: getfield      #28                 // Field conditionsBuilder_:Lcom/google/protobuf/RepeatedFieldBuilderV3;
       4: ifnonnull     17
       7: aload_0
       8: getfield      #12                 // Field conditions_:Ljava/util/List;
      11: invokeinterface #107,  1          // InterfaceMethod java/util/List.size:()I
      16: ireturn
      17: aload_0
      18: getfield      #28                 // Field conditionsBuilder_:Lcom/google/protobuf/RepeatedFieldBuilderV3;
      21: invokevirtual #108                // Method com/google/protobuf/RepeatedFieldBuilderV3.getCount:()I
      24: ireturn

  public io.kubernetes.client.proto.V2beta2Autoscaling$HorizontalPodAutoscalerCondition getConditions(int);
    Code:
       0: aload_0
       1: getfield      #28                 // Field conditionsBuilder_:Lcom/google/protobuf/RepeatedFieldBuilderV3;
       4: ifnonnull     21
       7: aload_0
       8: getfield      #12                 // Field conditions_:Ljava/util/List;
      11: iload_1
      12: invokeinterface #109,  2          // InterfaceMethod java/util/List.get:(I)Ljava/lang/Object;
      17: checkcast     #133                // class io/kubernetes/client/proto/V2beta2Autoscaling$HorizontalPodAutoscalerCondition
      20: areturn
      21: aload_0
      22: getfield      #28                 // Field conditionsBuilder_:Lcom/google/protobuf/RepeatedFieldBuilderV3;
      25: iload_1
      26: invokevirtual #111                // Method com/google/protobuf/RepeatedFieldBuilderV3.getMessage:(I)Lcom/google/protobuf/AbstractMessage;
      29: checkcast     #133                // class io/kubernetes/client/proto/V2beta2Autoscaling$HorizontalPodAutoscalerCondition
      32: areturn

  public io.kubernetes.client.proto.V2beta2Autoscaling$HorizontalPodAutoscalerStatus$Builder setConditions(int, io.kubernetes.client.proto.V2beta2Autoscaling$HorizontalPodAutoscalerCondition);
    Code:
       0: aload_0
       1: getfield      #28                 // Field conditionsBuilder_:Lcom/google/protobuf/RepeatedFieldBuilderV3;
       4: ifnonnull     42
       7: aload_2
       8: ifnonnull     19
      11: new           #87                 // class java/lang/NullPointerException
      14: dup
      15: invokespecial #88                 // Method java/lang/NullPointerException."<init>":()V
      18: athrow
      19: aload_0
      20: invokespecial #76                 // Method ensureConditionsIsMutable:()V
      23: aload_0
      24: getfield      #12                 // Field conditions_:Ljava/util/List;
      27: iload_1
      28: aload_2
      29: invokeinterface #112,  3          // InterfaceMethod java/util/List.set:(ILjava/lang/Object;)Ljava/lang/Object;
      34: pop
      35: aload_0
      36: invokevirtual #70                 // Method onChanged:()V
      39: goto          52
      42: aload_0
      43: getfield      #28                 // Field conditionsBuilder_:Lcom/google/protobuf/RepeatedFieldBuilderV3;
      46: iload_1
      47: aload_2
      48: invokevirtual #113                // Method com/google/protobuf/RepeatedFieldBuilderV3.setMessage:(ILcom/google/protobuf/AbstractMessage;)Lcom/google/protobuf/RepeatedFieldBuilderV3;
      51: pop
      52: aload_0
      53: areturn

  public io.kubernetes.client.proto.V2beta2Autoscaling$HorizontalPodAutoscalerStatus$Builder setConditions(int, io.kubernetes.client.proto.V2beta2Autoscaling$HorizontalPodAutoscalerCondition$Builder);
    Code:
       0: aload_0
       1: getfield      #28                 // Field conditionsBuilder_:Lcom/google/protobuf/RepeatedFieldBuilderV3;
       4: ifnonnull     33
       7: aload_0
       8: invokespecial #76                 // Method ensureConditionsIsMutable:()V
      11: aload_0
      12: getfield      #12                 // Field conditions_:Ljava/util/List;
      15: iload_1
      16: aload_2
      17: invokevirtual #134                // Method io/kubernetes/client/proto/V2beta2Autoscaling$HorizontalPodAutoscalerCondition$Builder.build:()Lio/kubernetes/client/proto/V2beta2Autoscaling$HorizontalPodAutoscalerCondition;
      20: invokeinterface #112,  3          // InterfaceMethod java/util/List.set:(ILjava/lang/Object;)Ljava/lang/Object;
      25: pop
      26: aload_0
      27: invokevirtual #70                 // Method onChanged:()V
      30: goto          46
      33: aload_0
      34: getfield      #28                 // Field conditionsBuilder_:Lcom/google/protobuf/RepeatedFieldBuilderV3;
      37: iload_1
      38: aload_2
      39: invokevirtual #134                // Method io/kubernetes/client/proto/V2beta2Autoscaling$HorizontalPodAutoscalerCondition$Builder.build:()Lio/kubernetes/client/proto/V2beta2Autoscaling$HorizontalPodAutoscalerCondition;
      42: invokevirtual #113                // Method com/google/protobuf/RepeatedFieldBuilderV3.setMessage:(ILcom/google/protobuf/AbstractMessage;)Lcom/google/protobuf/RepeatedFieldBuilderV3;
      45: pop
      46: aload_0
      47: areturn

  public io.kubernetes.client.proto.V2beta2Autoscaling$HorizontalPodAutoscalerStatus$Builder addConditions(io.kubernetes.client.proto.V2beta2Autoscaling$HorizontalPodAutoscalerCondition);
    Code:
       0: aload_0
       1: getfield      #28                 // Field conditionsBuilder_:Lcom/google/protobuf/RepeatedFieldBuilderV3;
       4: ifnonnull     41
       7: aload_1
       8: ifnonnull     19
      11: new           #87                 // class java/lang/NullPointerException
      14: dup
      15: invokespecial #88                 // Method java/lang/NullPointerException."<init>":()V
      18: athrow
      19: aload_0
      20: invokespecial #76                 // Method ensureConditionsIsMutable:()V
      23: aload_0
      24: getfield      #12                 // Field conditions_:Ljava/util/List;
      27: aload_1
      28: invokeinterface #115,  2          // InterfaceMethod java/util/List.add:(Ljava/lang/Object;)Z
      33: pop
      34: aload_0
      35: invokevirtual #70                 // Method onChanged:()V
      38: goto          50
      41: aload_0
      42: getfield      #28                 // Field conditionsBuilder_:Lcom/google/protobuf/RepeatedFieldBuilderV3;
      45: aload_1
      46: invokevirtual #116                // Method com/google/protobuf/RepeatedFieldBuilderV3.addMessage:(Lcom/google/protobuf/AbstractMessage;)Lcom/google/protobuf/RepeatedFieldBuilderV3;
      49: pop
      50: aload_0
      51: areturn

  public io.kubernetes.client.proto.V2beta2Autoscaling$HorizontalPodAutoscalerStatus$Builder addConditions(int, io.kubernetes.client.proto.V2beta2Autoscaling$HorizontalPodAutoscalerCondition);
    Code:
       0: aload_0
       1: getfield      #28                 // Field conditionsBuilder_:Lcom/google/protobuf/RepeatedFieldBuilderV3;
       4: ifnonnull     41
       7: aload_2
       8: ifnonnull     19
      11: new           #87                 // class java/lang/NullPointerException
      14: dup
      15: invokespecial #88                 // Method java/lang/NullPointerException."<init>":()V
      18: athrow
      19: aload_0
      20: invokespecial #76                 // Method ensureConditionsIsMutable:()V
      23: aload_0
      24: getfield      #12                 // Field conditions_:Ljava/util/List;
      27: iload_1
      28: aload_2
      29: invokeinterface #117,  3          // InterfaceMethod java/util/List.add:(ILjava/lang/Object;)V
      34: aload_0
      35: invokevirtual #70                 // Method onChanged:()V
      38: goto          51
      41: aload_0
      42: getfield      #28                 // Field conditionsBuilder_:Lcom/google/protobuf/RepeatedFieldBuilderV3;
      45: iload_1
      46: aload_2
      47: invokevirtual #118                // Method com/google/protobuf/RepeatedFieldBuilderV3.addMessage:(ILcom/google/protobuf/AbstractMessage;)Lcom/google/protobuf/RepeatedFieldBuilderV3;
      50: pop
      51: aload_0
      52: areturn

  public io.kubernetes.client.proto.V2beta2Autoscaling$HorizontalPodAutoscalerStatus$Builder addConditions(io.kubernetes.client.proto.V2beta2Autoscaling$HorizontalPodAutoscalerCondition$Builder);
    Code:
       0: aload_0
       1: getfield      #28                 // Field conditionsBuilder_:Lcom/google/protobuf/RepeatedFieldBuilderV3;
       4: ifnonnull     32
       7: aload_0
       8: invokespecial #76                 // Method ensureConditionsIsMutable:()V
      11: aload_0
      12: getfield      #12                 // Field conditions_:Ljava/util/List;
      15: aload_1
      16: invokevirtual #134                // Method io/kubernetes/client/proto/V2beta2Autoscaling$HorizontalPodAutoscalerCondition$Builder.build:()Lio/kubernetes/client/proto/V2beta2Autoscaling$HorizontalPodAutoscalerCondition;
      19: invokeinterface #115,  2          // InterfaceMethod java/util/List.add:(Ljava/lang/Object;)Z
      24: pop
      25: aload_0
      26: invokevirtual #70                 // Method onChanged:()V
      29: goto          44
      32: aload_0
      33: getfield      #28                 // Field conditionsBuilder_:Lcom/google/protobuf/RepeatedFieldBuilderV3;
      36: aload_1
      37: invokevirtual #134                // Method io/kubernetes/client/proto/V2beta2Autoscaling$HorizontalPodAutoscalerCondition$Builder.build:()Lio/kubernetes/client/proto/V2beta2Autoscaling$HorizontalPodAutoscalerCondition;
      40: invokevirtual #116                // Method com/google/protobuf/RepeatedFieldBuilderV3.addMessage:(Lcom/google/protobuf/AbstractMessage;)Lcom/google/protobuf/RepeatedFieldBuilderV3;
      43: pop
      44: aload_0
      45: areturn

  public io.kubernetes.client.proto.V2beta2Autoscaling$HorizontalPodAutoscalerStatus$Builder addConditions(int, io.kubernetes.client.proto.V2beta2Autoscaling$HorizontalPodAutoscalerCondition$Builder);
    Code:
       0: aload_0
       1: getfield      #28                 // Field conditionsBuilder_:Lcom/google/protobuf/RepeatedFieldBuilderV3;
       4: ifnonnull     32
       7: aload_0
       8: invokespecial #76                 // Method ensureConditionsIsMutable:()V
      11: aload_0
      12: getfield      #12                 // Field conditions_:Ljava/util/List;
      15: iload_1
      16: aload_2
      17: invokevirtual #134                // Method io/kubernetes/client/proto/V2beta2Autoscaling$HorizontalPodAutoscalerCondition$Builder.build:()Lio/kubernetes/client/proto/V2beta2Autoscaling$HorizontalPodAutoscalerCondition;
      20: invokeinterface #117,  3          // InterfaceMethod java/util/List.add:(ILjava/lang/Object;)V
      25: aload_0
      26: invokevirtual #70                 // Method onChanged:()V
      29: goto          45
      32: aload_0
      33: getfield      #28                 // Field conditionsBuilder_:Lcom/google/protobuf/RepeatedFieldBuilderV3;
      36: iload_1
      37: aload_2
      38: invokevirtual #134                // Method io/kubernetes/client/proto/V2beta2Autoscaling$HorizontalPodAutoscalerCondition$Builder.build:()Lio/kubernetes/client/proto/V2beta2Autoscaling$HorizontalPodAutoscalerCondition;
      41: invokevirtual #118                // Method com/google/protobuf/RepeatedFieldBuilderV3.addMessage:(ILcom/google/protobuf/AbstractMessage;)Lcom/google/protobuf/RepeatedFieldBuilderV3;
      44: pop
      45: aload_0
      46: areturn

  public io.kubernetes.client.proto.V2beta2Autoscaling$HorizontalPodAutoscalerStatus$Builder addAllConditions(java.lang.Iterable<? extends io.kubernetes.client.proto.V2beta2Autoscaling$HorizontalPodAutoscalerCondition>);
    Code:
       0: aload_0
       1: getfield      #28                 // Field conditionsBuilder_:Lcom/google/protobuf/RepeatedFieldBuilderV3;
       4: ifnonnull     26
       7: aload_0
       8: invokespecial #76                 // Method ensureConditionsIsMutable:()V
      11: aload_1
      12: aload_0
      13: getfield      #12                 // Field conditions_:Ljava/util/List;
      16: invokestatic  #119                // Method com/google/protobuf/AbstractMessageLite$Builder.addAll:(Ljava/lang/Iterable;Ljava/util/List;)V
      19: aload_0
      20: invokevirtual #70                 // Method onChanged:()V
      23: goto          35
      26: aload_0
      27: getfield      #28                 // Field conditionsBuilder_:Lcom/google/protobuf/RepeatedFieldBuilderV3;
      30: aload_1
      31: invokevirtual #74                 // Method com/google/protobuf/RepeatedFieldBuilderV3.addAllMessages:(Ljava/lang/Iterable;)Lcom/google/protobuf/RepeatedFieldBuilderV3;
      34: pop
      35: aload_0
      36: areturn

  public io.kubernetes.client.proto.V2beta2Autoscaling$HorizontalPodAutoscalerStatus$Builder clearConditions();
    Code:
       0: aload_0
       1: getfield      #28                 // Field conditionsBuilder_:Lcom/google/protobuf/RepeatedFieldBuilderV3;
       4: ifnonnull     32
       7: aload_0
       8: invokestatic  #10                 // Method java/util/Collections.emptyList:()Ljava/util/List;
      11: putfield      #12                 // Field conditions_:Ljava/util/List;
      14: aload_0
      15: aload_0
      16: getfield      #21                 // Field bitField0_:I
      19: bipush        -33
      21: iand
      22: putfield      #21                 // Field bitField0_:I
      25: aload_0
      26: invokevirtual #70                 // Method onChanged:()V
      29: goto          39
      32: aload_0
      33: getfield      #28                 // Field conditionsBuilder_:Lcom/google/protobuf/RepeatedFieldBuilderV3;
      36: invokevirtual #27                 // Method com/google/protobuf/RepeatedFieldBuilderV3.clear:()V
      39: aload_0
      40: areturn

  public io.kubernetes.client.proto.V2beta2Autoscaling$HorizontalPodAutoscalerStatus$Builder removeConditions(int);
    Code:
       0: aload_0
       1: getfield      #28                 // Field conditionsBuilder_:Lcom/google/protobuf/RepeatedFieldBuilderV3;
       4: ifnonnull     29
       7: aload_0
       8: invokespecial #76                 // Method ensureConditionsIsMutable:()V
      11: aload_0
      12: getfield      #12                 // Field conditions_:Ljava/util/List;
      15: iload_1
      16: invokeinterface #120,  2          // InterfaceMethod java/util/List.remove:(I)Ljava/lang/Object;
      21: pop
      22: aload_0
      23: invokevirtual #70                 // Method onChanged:()V
      26: goto          37
      29: aload_0
      30: getfield      #28                 // Field conditionsBuilder_:Lcom/google/protobuf/RepeatedFieldBuilderV3;
      33: iload_1
      34: invokevirtual #121                // Method com/google/protobuf/RepeatedFieldBuilderV3.remove:(I)V
      37: aload_0
      38: areturn

  public io.kubernetes.client.proto.V2beta2Autoscaling$HorizontalPodAutoscalerCondition$Builder getConditionsBuilder(int);
    Code:
       0: aload_0
       1: invokespecial #18                 // Method getConditionsFieldBuilder:()Lcom/google/protobuf/RepeatedFieldBuilderV3;
       4: iload_1
       5: invokevirtual #122                // Method com/google/protobuf/RepeatedFieldBuilderV3.getBuilder:(I)Lcom/google/protobuf/AbstractMessage$Builder;
       8: checkcast     #135                // class io/kubernetes/client/proto/V2beta2Autoscaling$HorizontalPodAutoscalerCondition$Builder
      11: areturn

  public io.kubernetes.client.proto.V2beta2Autoscaling$HorizontalPodAutoscalerConditionOrBuilder getConditionsOrBuilder(int);
    Code:
       0: aload_0
       1: getfield      #28                 // Field conditionsBuilder_:Lcom/google/protobuf/RepeatedFieldBuilderV3;
       4: ifnonnull     21
       7: aload_0
       8: getfield      #12                 // Field conditions_:Ljava/util/List;
      11: iload_1
      12: invokeinterface #109,  2          // InterfaceMethod java/util/List.get:(I)Ljava/lang/Object;
      17: checkcast     #136                // class io/kubernetes/client/proto/V2beta2Autoscaling$HorizontalPodAutoscalerConditionOrBuilder
      20: areturn
      21: aload_0
      22: getfield      #28                 // Field conditionsBuilder_:Lcom/google/protobuf/RepeatedFieldBuilderV3;
      25: iload_1
      26: invokevirtual #125                // Method com/google/protobuf/RepeatedFieldBuilderV3.getMessageOrBuilder:(I)Lcom/google/protobuf/MessageOrBuilder;
      29: checkcast     #136                // class io/kubernetes/client/proto/V2beta2Autoscaling$HorizontalPodAutoscalerConditionOrBuilder
      32: areturn

  public java.util.List<? extends io.kubernetes.client.proto.V2beta2Autoscaling$HorizontalPodAutoscalerConditionOrBuilder> getConditionsOrBuilderList();
    Code:
       0: aload_0
       1: getfield      #28                 // Field conditionsBuilder_:Lcom/google/protobuf/RepeatedFieldBuilderV3;
       4: ifnull        15
       7: aload_0
       8: getfield      #28                 // Field conditionsBuilder_:Lcom/google/protobuf/RepeatedFieldBuilderV3;
      11: invokevirtual #126                // Method com/google/protobuf/RepeatedFieldBuilderV3.getMessageOrBuilderList:()Ljava/util/List;
      14: areturn
      15: aload_0
      16: getfield      #12                 // Field conditions_:Ljava/util/List;
      19: invokestatic  #40                 // Method java/util/Collections.unmodifiableList:(Ljava/util/List;)Ljava/util/List;
      22: areturn

  public io.kubernetes.client.proto.V2beta2Autoscaling$HorizontalPodAutoscalerCondition$Builder addConditionsBuilder();
    Code:
       0: aload_0
       1: invokespecial #18                 // Method getConditionsFieldBuilder:()Lcom/google/protobuf/RepeatedFieldBuilderV3;
       4: invokestatic  #137                // Method io/kubernetes/client/proto/V2beta2Autoscaling$HorizontalPodAutoscalerCondition.getDefaultInstance:()Lio/kubernetes/client/proto/V2beta2Autoscaling$HorizontalPodAutoscalerCondition;
       7: invokevirtual #128                // Method com/google/protobuf/RepeatedFieldBuilderV3.addBuilder:(Lcom/google/protobuf/AbstractMessage;)Lcom/google/protobuf/AbstractMessage$Builder;
      10: checkcast     #135                // class io/kubernetes/client/proto/V2beta2Autoscaling$HorizontalPodAutoscalerCondition$Builder
      13: areturn

  public io.kubernetes.client.proto.V2beta2Autoscaling$HorizontalPodAutoscalerCondition$Builder addConditionsBuilder(int);
    Code:
       0: aload_0
       1: invokespecial #18                 // Method getConditionsFieldBuilder:()Lcom/google/protobuf/RepeatedFieldBuilderV3;
       4: iload_1
       5: invokestatic  #137                // Method io/kubernetes/client/proto/V2beta2Autoscaling$HorizontalPodAutoscalerCondition.getDefaultInstance:()Lio/kubernetes/client/proto/V2beta2Autoscaling$HorizontalPodAutoscalerCondition;
       8: invokevirtual #129                // Method com/google/protobuf/RepeatedFieldBuilderV3.addBuilder:(ILcom/google/protobuf/AbstractMessage;)Lcom/google/protobuf/AbstractMessage$Builder;
      11: checkcast     #135                // class io/kubernetes/client/proto/V2beta2Autoscaling$HorizontalPodAutoscalerCondition$Builder
      14: areturn

  public java.util.List<io.kubernetes.client.proto.V2beta2Autoscaling$HorizontalPodAutoscalerCondition$Builder> getConditionsBuilderList();
    Code:
       0: aload_0
       1: invokespecial #18                 // Method getConditionsFieldBuilder:()Lcom/google/protobuf/RepeatedFieldBuilderV3;
       4: invokevirtual #130                // Method com/google/protobuf/RepeatedFieldBuilderV3.getBuilderList:()Ljava/util/List;
       7: areturn

  private com.google.protobuf.RepeatedFieldBuilderV3<io.kubernetes.client.proto.V2beta2Autoscaling$HorizontalPodAutoscalerCondition, io.kubernetes.client.proto.V2beta2Autoscaling$HorizontalPodAutoscalerCondition$Builder, io.kubernetes.client.proto.V2beta2Autoscaling$HorizontalPodAutoscalerConditionOrBuilder> getConditionsFieldBuilder();
    Code:
       0: aload_0
       1: getfield      #28                 // Field conditionsBuilder_:Lcom/google/protobuf/RepeatedFieldBuilderV3;
       4: ifnonnull     52
       7: aload_0
       8: new           #131                // class com/google/protobuf/RepeatedFieldBuilderV3
      11: dup
      12: aload_0
      13: getfield      #12                 // Field conditions_:Ljava/util/List;
      16: aload_0
      17: getfield      #21                 // Field bitField0_:I
      20: bipush        32
      22: iand
      23: bipush        32
      25: if_icmpne     32
      28: iconst_1
      29: goto          33
      32: iconst_0
      33: aload_0
      34: invokevirtual #101                // Method getParentForChildren:()Lcom/google/protobuf/GeneratedMessageV3$BuilderParent;
      37: aload_0
      38: invokevirtual #102                // Method isClean:()Z
      41: invokespecial #132                // Method com/google/protobuf/RepeatedFieldBuilderV3."<init>":(Ljava/util/List;ZLcom/google/protobuf/AbstractMessage$BuilderParent;Z)V
      44: putfield      #28                 // Field conditionsBuilder_:Lcom/google/protobuf/RepeatedFieldBuilderV3;
      47: aload_0
      48: aconst_null
      49: putfield      #12                 // Field conditions_:Ljava/util/List;
      52: aload_0
      53: getfield      #28                 // Field conditionsBuilder_:Lcom/google/protobuf/RepeatedFieldBuilderV3;
      56: areturn

  public final io.kubernetes.client.proto.V2beta2Autoscaling$HorizontalPodAutoscalerStatus$Builder setUnknownFields(com.google.protobuf.UnknownFieldSet);
    Code:
       0: aload_0
       1: aload_1
       2: invokespecial #138                // Method com/google/protobuf/GeneratedMessageV3$Builder.setUnknownFields:(Lcom/google/protobuf/UnknownFieldSet;)Lcom/google/protobuf/GeneratedMessageV3$Builder;
       5: checkcast     #6                  // class io/kubernetes/client/proto/V2beta2Autoscaling$HorizontalPodAutoscalerStatus$Builder
       8: areturn

  public final io.kubernetes.client.proto.V2beta2Autoscaling$HorizontalPodAutoscalerStatus$Builder mergeUnknownFields(com.google.protobuf.UnknownFieldSet);
    Code:
       0: aload_0
       1: aload_1
       2: invokespecial #139                // Method com/google/protobuf/GeneratedMessageV3$Builder.mergeUnknownFields:(Lcom/google/protobuf/UnknownFieldSet;)Lcom/google/protobuf/GeneratedMessageV3$Builder;
       5: checkcast     #6                  // class io/kubernetes/client/proto/V2beta2Autoscaling$HorizontalPodAutoscalerStatus$Builder
       8: areturn

  public com.google.protobuf.GeneratedMessageV3$Builder mergeUnknownFields(com.google.protobuf.UnknownFieldSet);
    Code:
       0: aload_0
       1: aload_1
       2: invokevirtual #79                 // Method mergeUnknownFields:(Lcom/google/protobuf/UnknownFieldSet;)Lio/kubernetes/client/proto/V2beta2Autoscaling$HorizontalPodAutoscalerStatus$Builder;
       5: areturn

  public com.google.protobuf.GeneratedMessageV3$Builder setUnknownFields(com.google.protobuf.UnknownFieldSet);
    Code:
       0: aload_0
       1: aload_1
       2: invokevirtual #140                // Method setUnknownFields:(Lcom/google/protobuf/UnknownFieldSet;)Lio/kubernetes/client/proto/V2beta2Autoscaling$HorizontalPodAutoscalerStatus$Builder;
       5: areturn

  public com.google.protobuf.GeneratedMessageV3$Builder addRepeatedField(com.google.protobuf.Descriptors$FieldDescriptor, java.lang.Object);
    Code:
       0: aload_0
       1: aload_1
       2: aload_2
       3: invokevirtual #141                // Method addRepeatedField:(Lcom/google/protobuf/Descriptors$FieldDescriptor;Ljava/lang/Object;)Lio/kubernetes/client/proto/V2beta2Autoscaling$HorizontalPodAutoscalerStatus$Builder;
       6: areturn

  public com.google.protobuf.GeneratedMessageV3$Builder setRepeatedField(com.google.protobuf.Descriptors$FieldDescriptor, int, java.lang.Object);
    Code:
       0: aload_0
       1: aload_1
       2: iload_2
       3: aload_3
       4: invokevirtual #142                // Method setRepeatedField:(Lcom/google/protobuf/Descriptors$FieldDescriptor;ILjava/lang/Object;)Lio/kubernetes/client/proto/V2beta2Autoscaling$HorizontalPodAutoscalerStatus$Builder;
       7: areturn

  public com.google.protobuf.GeneratedMessageV3$Builder clearOneof(com.google.protobuf.Descriptors$OneofDescriptor);
    Code:
       0: aload_0
       1: aload_1
       2: invokevirtual #143                // Method clearOneof:(Lcom/google/protobuf/Descriptors$OneofDescriptor;)Lio/kubernetes/client/proto/V2beta2Autoscaling$HorizontalPodAutoscalerStatus$Builder;
       5: areturn

  public com.google.protobuf.GeneratedMessageV3$Builder clearField(com.google.protobuf.Descriptors$FieldDescriptor);
    Code:
       0: aload_0
       1: aload_1
       2: invokevirtual #144                // Method clearField:(Lcom/google/protobuf/Descriptors$FieldDescriptor;)Lio/kubernetes/client/proto/V2beta2Autoscaling$HorizontalPodAutoscalerStatus$Builder;
       5: areturn

  public com.google.protobuf.GeneratedMessageV3$Builder setField(com.google.protobuf.Descriptors$FieldDescriptor, java.lang.Object);
    Code:
       0: aload_0
       1: aload_1
       2: aload_2
       3: invokevirtual #145                // Method setField:(Lcom/google/protobuf/Descriptors$FieldDescriptor;Ljava/lang/Object;)Lio/kubernetes/client/proto/V2beta2Autoscaling$HorizontalPodAutoscalerStatus$Builder;
       6: areturn

  public com.google.protobuf.GeneratedMessageV3$Builder clear();
    Code:
       0: aload_0
       1: invokevirtual #146                // Method clear:()Lio/kubernetes/client/proto/V2beta2Autoscaling$HorizontalPodAutoscalerStatus$Builder;
       4: areturn

  public com.google.protobuf.GeneratedMessageV3$Builder clone();
    Code:
       0: aload_0
       1: invokevirtual #147                // Method clone:()Lio/kubernetes/client/proto/V2beta2Autoscaling$HorizontalPodAutoscalerStatus$Builder;
       4: areturn

  public com.google.protobuf.AbstractMessage$Builder mergeUnknownFields(com.google.protobuf.UnknownFieldSet);
    Code:
       0: aload_0
       1: aload_1
       2: invokevirtual #79                 // Method mergeUnknownFields:(Lcom/google/protobuf/UnknownFieldSet;)Lio/kubernetes/client/proto/V2beta2Autoscaling$HorizontalPodAutoscalerStatus$Builder;
       5: areturn

  public com.google.protobuf.AbstractMessage$Builder mergeFrom(com.google.protobuf.CodedInputStream, com.google.protobuf.ExtensionRegistryLite) throws java.io.IOException;
    Code:
       0: aload_0
       1: aload_1
       2: aload_2
       3: invokevirtual #148                // Method mergeFrom:(Lcom/google/protobuf/CodedInputStream;Lcom/google/protobuf/ExtensionRegistryLite;)Lio/kubernetes/client/proto/V2beta2Autoscaling$HorizontalPodAutoscalerStatus$Builder;
       6: areturn

  public com.google.protobuf.AbstractMessage$Builder mergeFrom(com.google.protobuf.Message);
    Code:
       0: aload_0
       1: aload_1
       2: invokevirtual #149                // Method mergeFrom:(Lcom/google/protobuf/Message;)Lio/kubernetes/client/proto/V2beta2Autoscaling$HorizontalPodAutoscalerStatus$Builder;
       5: areturn

  public com.google.protobuf.AbstractMessage$Builder clear();
    Code:
       0: aload_0
       1: invokevirtual #146                // Method clear:()Lio/kubernetes/client/proto/V2beta2Autoscaling$HorizontalPodAutoscalerStatus$Builder;
       4: areturn

  public com.google.protobuf.AbstractMessage$Builder clearOneof(com.google.protobuf.Descriptors$OneofDescriptor);
    Code:
       0: aload_0
       1: aload_1
       2: invokevirtual #143                // Method clearOneof:(Lcom/google/protobuf/Descriptors$OneofDescriptor;)Lio/kubernetes/client/proto/V2beta2Autoscaling$HorizontalPodAutoscalerStatus$Builder;
       5: areturn

  public com.google.protobuf.AbstractMessage$Builder clone();
    Code:
       0: aload_0
       1: invokevirtual #147                // Method clone:()Lio/kubernetes/client/proto/V2beta2Autoscaling$HorizontalPodAutoscalerStatus$Builder;
       4: areturn

  public com.google.protobuf.Message$Builder mergeUnknownFields(com.google.protobuf.UnknownFieldSet);
    Code:
       0: aload_0
       1: aload_1
       2: invokevirtual #79                 // Method mergeUnknownFields:(Lcom/google/protobuf/UnknownFieldSet;)Lio/kubernetes/client/proto/V2beta2Autoscaling$HorizontalPodAutoscalerStatus$Builder;
       5: areturn

  public com.google.protobuf.Message$Builder setUnknownFields(com.google.protobuf.UnknownFieldSet);
    Code:
       0: aload_0
       1: aload_1
       2: invokevirtual #140                // Method setUnknownFields:(Lcom/google/protobuf/UnknownFieldSet;)Lio/kubernetes/client/proto/V2beta2Autoscaling$HorizontalPodAutoscalerStatus$Builder;
       5: areturn

  public com.google.protobuf.Message$Builder addRepeatedField(com.google.protobuf.Descriptors$FieldDescriptor, java.lang.Object);
    Code:
       0: aload_0
       1: aload_1
       2: aload_2
       3: invokevirtual #141                // Method addRepeatedField:(Lcom/google/protobuf/Descriptors$FieldDescriptor;Ljava/lang/Object;)Lio/kubernetes/client/proto/V2beta2Autoscaling$HorizontalPodAutoscalerStatus$Builder;
       6: areturn

  public com.google.protobuf.Message$Builder setRepeatedField(com.google.protobuf.Descriptors$FieldDescriptor, int, java.lang.Object);
    Code:
       0: aload_0
       1: aload_1
       2: iload_2
       3: aload_3
       4: invokevirtual #142                // Method setRepeatedField:(Lcom/google/protobuf/Descriptors$FieldDescriptor;ILjava/lang/Object;)Lio/kubernetes/client/proto/V2beta2Autoscaling$HorizontalPodAutoscalerStatus$Builder;
       7: areturn

  public com.google.protobuf.Message$Builder clearOneof(com.google.protobuf.Descriptors$OneofDescriptor);
    Code:
       0: aload_0
       1: aload_1
       2: invokevirtual #143                // Method clearOneof:(Lcom/google/protobuf/Descriptors$OneofDescriptor;)Lio/kubernetes/client/proto/V2beta2Autoscaling$HorizontalPodAutoscalerStatus$Builder;
       5: areturn

  public com.google.protobuf.Message$Builder clearField(com.google.protobuf.Descriptors$FieldDescriptor);
    Code:
       0: aload_0
       1: aload_1
       2: invokevirtual #144                // Method clearField:(Lcom/google/protobuf/Descriptors$FieldDescriptor;)Lio/kubernetes/client/proto/V2beta2Autoscaling$HorizontalPodAutoscalerStatus$Builder;
       5: areturn

  public com.google.protobuf.Message$Builder setField(com.google.protobuf.Descriptors$FieldDescriptor, java.lang.Object);
    Code:
       0: aload_0
       1: aload_1
       2: aload_2
       3: invokevirtual #145                // Method setField:(Lcom/google/protobuf/Descriptors$FieldDescriptor;Ljava/lang/Object;)Lio/kubernetes/client/proto/V2beta2Autoscaling$HorizontalPodAutoscalerStatus$Builder;
       6: areturn

  public com.google.protobuf.Message$Builder mergeFrom(com.google.protobuf.CodedInputStream, com.google.protobuf.ExtensionRegistryLite) throws java.io.IOException;
    Code:
       0: aload_0
       1: aload_1
       2: aload_2
       3: invokevirtual #148                // Method mergeFrom:(Lcom/google/protobuf/CodedInputStream;Lcom/google/protobuf/ExtensionRegistryLite;)Lio/kubernetes/client/proto/V2beta2Autoscaling$HorizontalPodAutoscalerStatus$Builder;
       6: areturn

  public com.google.protobuf.Message$Builder clone();
    Code:
       0: aload_0
       1: invokevirtual #147                // Method clone:()Lio/kubernetes/client/proto/V2beta2Autoscaling$HorizontalPodAutoscalerStatus$Builder;
       4: areturn

  public com.google.protobuf.Message buildPartial();
    Code:
       0: aload_0
       1: invokevirtual #30                 // Method buildPartial:()Lio/kubernetes/client/proto/V2beta2Autoscaling$HorizontalPodAutoscalerStatus;
       4: areturn

  public com.google.protobuf.Message build();
    Code:
       0: aload_0
       1: invokevirtual #150                // Method build:()Lio/kubernetes/client/proto/V2beta2Autoscaling$HorizontalPodAutoscalerStatus;
       4: areturn

  public com.google.protobuf.Message$Builder mergeFrom(com.google.protobuf.Message);
    Code:
       0: aload_0
       1: aload_1
       2: invokevirtual #149                // Method mergeFrom:(Lcom/google/protobuf/Message;)Lio/kubernetes/client/proto/V2beta2Autoscaling$HorizontalPodAutoscalerStatus$Builder;
       5: areturn

  public com.google.protobuf.Message$Builder clear();
    Code:
       0: aload_0
       1: invokevirtual #146                // Method clear:()Lio/kubernetes/client/proto/V2beta2Autoscaling$HorizontalPodAutoscalerStatus$Builder;
       4: areturn

  public com.google.protobuf.MessageLite$Builder mergeFrom(com.google.protobuf.CodedInputStream, com.google.protobuf.ExtensionRegistryLite) throws java.io.IOException;
    Code:
       0: aload_0
       1: aload_1
       2: aload_2
       3: invokevirtual #148                // Method mergeFrom:(Lcom/google/protobuf/CodedInputStream;Lcom/google/protobuf/ExtensionRegistryLite;)Lio/kubernetes/client/proto/V2beta2Autoscaling$HorizontalPodAutoscalerStatus$Builder;
       6: areturn

  public com.google.protobuf.MessageLite$Builder clone();
    Code:
       0: aload_0
       1: invokevirtual #147                // Method clone:()Lio/kubernetes/client/proto/V2beta2Autoscaling$HorizontalPodAutoscalerStatus$Builder;
       4: areturn

  public com.google.protobuf.MessageLite buildPartial();
    Code:
       0: aload_0
       1: invokevirtual #30                 // Method buildPartial:()Lio/kubernetes/client/proto/V2beta2Autoscaling$HorizontalPodAutoscalerStatus;
       4: areturn

  public com.google.protobuf.MessageLite build();
    Code:
       0: aload_0
       1: invokevirtual #150                // Method build:()Lio/kubernetes/client/proto/V2beta2Autoscaling$HorizontalPodAutoscalerStatus;
       4: areturn

  public com.google.protobuf.MessageLite$Builder clear();
    Code:
       0: aload_0
       1: invokevirtual #146                // Method clear:()Lio/kubernetes/client/proto/V2beta2Autoscaling$HorizontalPodAutoscalerStatus$Builder;
       4: areturn

  public com.google.protobuf.MessageLite getDefaultInstanceForType();
    Code:
       0: aload_0
       1: invokevirtual #151                // Method getDefaultInstanceForType:()Lio/kubernetes/client/proto/V2beta2Autoscaling$HorizontalPodAutoscalerStatus;
       4: areturn

  public com.google.protobuf.Message getDefaultInstanceForType();
    Code:
       0: aload_0
       1: invokevirtual #151                // Method getDefaultInstanceForType:()Lio/kubernetes/client/proto/V2beta2Autoscaling$HorizontalPodAutoscalerStatus;
       4: areturn

  public com.google.protobuf.AbstractMessageLite$Builder mergeFrom(com.google.protobuf.CodedInputStream, com.google.protobuf.ExtensionRegistryLite) throws java.io.IOException;
    Code:
       0: aload_0
       1: aload_1
       2: aload_2
       3: invokevirtual #148                // Method mergeFrom:(Lcom/google/protobuf/CodedInputStream;Lcom/google/protobuf/ExtensionRegistryLite;)Lio/kubernetes/client/proto/V2beta2Autoscaling$HorizontalPodAutoscalerStatus$Builder;
       6: areturn

  public com.google.protobuf.AbstractMessageLite$Builder clone();
    Code:
       0: aload_0
       1: invokevirtual #147                // Method clone:()Lio/kubernetes/client/proto/V2beta2Autoscaling$HorizontalPodAutoscalerStatus$Builder;
       4: areturn

  public java.lang.Object clone() throws java.lang.CloneNotSupportedException;
    Code:
       0: aload_0
       1: invokevirtual #147                // Method clone:()Lio/kubernetes/client/proto/V2beta2Autoscaling$HorizontalPodAutoscalerStatus$Builder;
       4: areturn

  io.kubernetes.client.proto.V2beta2Autoscaling$HorizontalPodAutoscalerStatus$Builder(io.kubernetes.client.proto.V2beta2Autoscaling$1);
    Code:
       0: aload_0
       1: invokespecial #2                  // Method "<init>":()V
       4: return

  io.kubernetes.client.proto.V2beta2Autoscaling$HorizontalPodAutoscalerStatus$Builder(com.google.protobuf.GeneratedMessageV3$BuilderParent, io.kubernetes.client.proto.V2beta2Autoscaling$1);
    Code:
       0: aload_0
       1: aload_1
       2: invokespecial #1                  // Method "<init>":(Lcom/google/protobuf/GeneratedMessageV3$BuilderParent;)V
       5: return
}
