Compiled from "DocumentationPluginsManager.java"
public class springfox.documentation.spring.web.plugins.DocumentationPluginsManager {
  private org.springframework.plugin.core.PluginRegistry<springfox.documentation.spi.service.DocumentationPlugin, springfox.documentation.spi.DocumentationType> documentationPlugins;

  private org.springframework.plugin.core.PluginRegistry<springfox.documentation.spi.service.ApiListingBuilderPlugin, springfox.documentation.spi.DocumentationType> apiListingPlugins;

  private org.springframework.plugin.core.PluginRegistry<springfox.documentation.spi.service.ParameterBuilderPlugin, springfox.documentation.spi.DocumentationType> parameterPlugins;

  private org.springframework.plugin.core.PluginRegistry<springfox.documentation.spi.service.ExpandedParameterBuilderPlugin, springfox.documentation.spi.DocumentationType> parameterExpanderPlugins;

  private org.springframework.plugin.core.PluginRegistry<springfox.documentation.spi.service.OperationBuilderPlugin, springfox.documentation.spi.DocumentationType> operationBuilderPlugins;

  private org.springframework.plugin.core.PluginRegistry<springfox.documentation.spi.service.ResourceGroupingStrategy, springfox.documentation.spi.DocumentationType> resourceGroupingStrategies;

  private org.springframework.plugin.core.PluginRegistry<springfox.documentation.spi.service.OperationModelsProviderPlugin, springfox.documentation.spi.DocumentationType> operationModelsProviders;

  private org.springframework.plugin.core.PluginRegistry<springfox.documentation.spi.service.DefaultsProviderPlugin, springfox.documentation.spi.DocumentationType> defaultsProviders;

  private org.springframework.plugin.core.PluginRegistry<springfox.documentation.service.PathDecorator, springfox.documentation.spi.service.contexts.DocumentationContext> pathDecorators;

  private org.springframework.plugin.core.PluginRegistry<springfox.documentation.spi.service.ApiListingScannerPlugin, springfox.documentation.spi.DocumentationType> apiListingScanners;

  public springfox.documentation.spring.web.plugins.DocumentationPluginsManager();
    Code:
       0: aload_0
       1: invokespecial #3                  // Method java/lang/Object."<init>":()V
       4: return

  public java.lang.Iterable<springfox.documentation.spi.service.DocumentationPlugin> documentationPlugins() throws java.lang.IllegalStateException;
    Code:
       0: aload_0
       1: getfield      #4                  // Field documentationPlugins:Lorg/springframework/plugin/core/PluginRegistry;
       4: invokeinterface #5,  1            // InterfaceMethod org/springframework/plugin/core/PluginRegistry.getPlugins:()Ljava/util/List;
       9: astore_1
      10: aload_1
      11: invokestatic  #6                  // Method springfox/documentation/spring/web/plugins/DuplicateGroupsDetector.ensureNoDuplicateGroups:(Ljava/util/List;)V
      14: aload_1
      15: invokeinterface #7,  1            // InterfaceMethod java/util/List.isEmpty:()Z
      20: ifeq          38
      23: iconst_1
      24: anewarray     #8                  // class springfox/documentation/spi/service/DocumentationPlugin
      27: dup
      28: iconst_0
      29: aload_0
      30: invokespecial #9                  // Method defaultDocumentationPlugin:()Lspringfox/documentation/spi/service/DocumentationPlugin;
      33: aastore
      34: invokestatic  #10                 // Method com/google/common/collect/Lists.newArrayList:([Ljava/lang/Object;)Ljava/util/ArrayList;
      37: areturn
      38: aload_1
      39: areturn

  public springfox.documentation.service.Parameter parameter(springfox.documentation.spi.service.contexts.ParameterContext);
    Code:
       0: aload_0
       1: getfield      #11                 // Field parameterPlugins:Lorg/springframework/plugin/core/PluginRegistry;
       4: aload_1
       5: invokevirtual #12                 // Method springfox/documentation/spi/service/contexts/ParameterContext.getDocumentationType:()Lspringfox/documentation/spi/DocumentationType;
       8: invokeinterface #13,  2           // InterfaceMethod org/springframework/plugin/core/PluginRegistry.getPluginsFor:(Ljava/lang/Object;)Ljava/util/List;
      13: invokeinterface #14,  1           // InterfaceMethod java/util/List.iterator:()Ljava/util/Iterator;
      18: astore_2
      19: aload_2
      20: invokeinterface #15,  1           // InterfaceMethod java/util/Iterator.hasNext:()Z
      25: ifeq          48
      28: aload_2
      29: invokeinterface #16,  1           // InterfaceMethod java/util/Iterator.next:()Ljava/lang/Object;
      34: checkcast     #17                 // class springfox/documentation/spi/service/ParameterBuilderPlugin
      37: astore_3
      38: aload_3
      39: aload_1
      40: invokeinterface #18,  2           // InterfaceMethod springfox/documentation/spi/service/ParameterBuilderPlugin.apply:(Lspringfox/documentation/spi/service/contexts/ParameterContext;)V
      45: goto          19
      48: aload_1
      49: invokevirtual #19                 // Method springfox/documentation/spi/service/contexts/ParameterContext.parameterBuilder:()Lspringfox/documentation/builders/ParameterBuilder;
      52: invokevirtual #20                 // Method springfox/documentation/builders/ParameterBuilder.build:()Lspringfox/documentation/service/Parameter;
      55: areturn

  public springfox.documentation.service.Parameter expandParameter(springfox.documentation.spi.service.contexts.ParameterExpansionContext);
    Code:
       0: aload_0
       1: getfield      #21                 // Field parameterExpanderPlugins:Lorg/springframework/plugin/core/PluginRegistry;
       4: aload_1
       5: invokevirtual #22                 // Method springfox/documentation/spi/service/contexts/ParameterExpansionContext.getDocumentationType:()Lspringfox/documentation/spi/DocumentationType;
       8: invokeinterface #13,  2           // InterfaceMethod org/springframework/plugin/core/PluginRegistry.getPluginsFor:(Ljava/lang/Object;)Ljava/util/List;
      13: invokeinterface #14,  1           // InterfaceMethod java/util/List.iterator:()Ljava/util/Iterator;
      18: astore_2
      19: aload_2
      20: invokeinterface #15,  1           // InterfaceMethod java/util/Iterator.hasNext:()Z
      25: ifeq          48
      28: aload_2
      29: invokeinterface #16,  1           // InterfaceMethod java/util/Iterator.next:()Ljava/lang/Object;
      34: checkcast     #23                 // class springfox/documentation/spi/service/ExpandedParameterBuilderPlugin
      37: astore_3
      38: aload_3
      39: aload_1
      40: invokeinterface #24,  2           // InterfaceMethod springfox/documentation/spi/service/ExpandedParameterBuilderPlugin.apply:(Lspringfox/documentation/spi/service/contexts/ParameterExpansionContext;)V
      45: goto          19
      48: aload_1
      49: invokevirtual #25                 // Method springfox/documentation/spi/service/contexts/ParameterExpansionContext.getParameterBuilder:()Lspringfox/documentation/builders/ParameterBuilder;
      52: invokevirtual #20                 // Method springfox/documentation/builders/ParameterBuilder.build:()Lspringfox/documentation/service/Parameter;
      55: areturn

  public springfox.documentation.service.Operation operation(springfox.documentation.spi.service.contexts.OperationContext);
    Code:
       0: aload_0
       1: getfield      #26                 // Field operationBuilderPlugins:Lorg/springframework/plugin/core/PluginRegistry;
       4: aload_1
       5: invokevirtual #27                 // Method springfox/documentation/spi/service/contexts/OperationContext.getDocumentationType:()Lspringfox/documentation/spi/DocumentationType;
       8: invokeinterface #13,  2           // InterfaceMethod org/springframework/plugin/core/PluginRegistry.getPluginsFor:(Ljava/lang/Object;)Ljava/util/List;
      13: invokeinterface #14,  1           // InterfaceMethod java/util/List.iterator:()Ljava/util/Iterator;
      18: astore_2
      19: aload_2
      20: invokeinterface #15,  1           // InterfaceMethod java/util/Iterator.hasNext:()Z
      25: ifeq          48
      28: aload_2
      29: invokeinterface #16,  1           // InterfaceMethod java/util/Iterator.next:()Ljava/lang/Object;
      34: checkcast     #28                 // class springfox/documentation/spi/service/OperationBuilderPlugin
      37: astore_3
      38: aload_3
      39: aload_1
      40: invokeinterface #29,  2           // InterfaceMethod springfox/documentation/spi/service/OperationBuilderPlugin.apply:(Lspringfox/documentation/spi/service/contexts/OperationContext;)V
      45: goto          19
      48: aload_1
      49: invokevirtual #30                 // Method springfox/documentation/spi/service/contexts/OperationContext.operationBuilder:()Lspringfox/documentation/builders/OperationBuilder;
      52: invokevirtual #31                 // Method springfox/documentation/builders/OperationBuilder.build:()Lspringfox/documentation/service/Operation;
      55: areturn

  public springfox.documentation.service.ApiListing apiListing(springfox.documentation.spi.service.contexts.ApiListingContext);
    Code:
       0: aload_0
       1: getfield      #32                 // Field apiListingPlugins:Lorg/springframework/plugin/core/PluginRegistry;
       4: aload_1
       5: invokevirtual #33                 // Method springfox/documentation/spi/service/contexts/ApiListingContext.getDocumentationType:()Lspringfox/documentation/spi/DocumentationType;
       8: invokeinterface #13,  2           // InterfaceMethod org/springframework/plugin/core/PluginRegistry.getPluginsFor:(Ljava/lang/Object;)Ljava/util/List;
      13: invokeinterface #14,  1           // InterfaceMethod java/util/List.iterator:()Ljava/util/Iterator;
      18: astore_2
      19: aload_2
      20: invokeinterface #15,  1           // InterfaceMethod java/util/Iterator.hasNext:()Z
      25: ifeq          48
      28: aload_2
      29: invokeinterface #16,  1           // InterfaceMethod java/util/Iterator.next:()Ljava/lang/Object;
      34: checkcast     #34                 // class springfox/documentation/spi/service/ApiListingBuilderPlugin
      37: astore_3
      38: aload_3
      39: aload_1
      40: invokeinterface #35,  2           // InterfaceMethod springfox/documentation/spi/service/ApiListingBuilderPlugin.apply:(Lspringfox/documentation/spi/service/contexts/ApiListingContext;)V
      45: goto          19
      48: aload_1
      49: invokevirtual #36                 // Method springfox/documentation/spi/service/contexts/ApiListingContext.apiListingBuilder:()Lspringfox/documentation/builders/ApiListingBuilder;
      52: invokevirtual #37                 // Method springfox/documentation/builders/ApiListingBuilder.build:()Lspringfox/documentation/service/ApiListing;
      55: areturn

  public java.util.Set<springfox.documentation.spi.schema.contexts.ModelContext> modelContexts(springfox.documentation.spi.service.contexts.RequestMappingContext);
    Code:
       0: aload_1
       1: invokevirtual #38                 // Method springfox/documentation/spi/service/contexts/RequestMappingContext.getDocumentationContext:()Lspringfox/documentation/spi/service/contexts/DocumentationContext;
       4: invokevirtual #39                 // Method springfox/documentation/spi/service/contexts/DocumentationContext.getDocumentationType:()Lspringfox/documentation/spi/DocumentationType;
       7: astore_2
       8: aload_0
       9: getfield      #40                 // Field operationModelsProviders:Lorg/springframework/plugin/core/PluginRegistry;
      12: aload_2
      13: invokeinterface #13,  2           // InterfaceMethod org/springframework/plugin/core/PluginRegistry.getPluginsFor:(Ljava/lang/Object;)Ljava/util/List;
      18: invokeinterface #14,  1           // InterfaceMethod java/util/List.iterator:()Ljava/util/Iterator;
      23: astore_3
      24: aload_3
      25: invokeinterface #15,  1           // InterfaceMethod java/util/Iterator.hasNext:()Z
      30: ifeq          55
      33: aload_3
      34: invokeinterface #16,  1           // InterfaceMethod java/util/Iterator.next:()Ljava/lang/Object;
      39: checkcast     #41                 // class springfox/documentation/spi/service/OperationModelsProviderPlugin
      42: astore        4
      44: aload         4
      46: aload_1
      47: invokeinterface #42,  2           // InterfaceMethod springfox/documentation/spi/service/OperationModelsProviderPlugin.apply:(Lspringfox/documentation/spi/service/contexts/RequestMappingContext;)V
      52: goto          24
      55: aload_1
      56: invokevirtual #43                 // Method springfox/documentation/spi/service/contexts/RequestMappingContext.operationModelsBuilder:()Lspringfox/documentation/spi/service/contexts/OperationModelContextsBuilder;
      59: invokevirtual #44                 // Method springfox/documentation/spi/service/contexts/OperationModelContextsBuilder.build:()Ljava/util/Set;
      62: areturn

  public springfox.documentation.spi.service.ResourceGroupingStrategy resourceGroupingStrategy(springfox.documentation.spi.DocumentationType);
    Code:
       0: aload_0
       1: getfield      #45                 // Field resourceGroupingStrategies:Lorg/springframework/plugin/core/PluginRegistry;
       4: aload_1
       5: new           #46                 // class springfox/documentation/spring/web/SpringGroupingStrategy
       8: dup
       9: invokespecial #47                 // Method springfox/documentation/spring/web/SpringGroupingStrategy."<init>":()V
      12: invokeinterface #48,  3           // InterfaceMethod org/springframework/plugin/core/PluginRegistry.getPluginFor:(Ljava/lang/Object;Lorg/springframework/plugin/core/Plugin;)Lorg/springframework/plugin/core/Plugin;
      17: checkcast     #49                 // class springfox/documentation/spi/service/ResourceGroupingStrategy
      20: areturn

  private springfox.documentation.spi.service.DocumentationPlugin defaultDocumentationPlugin();
    Code:
       0: new           #50                 // class springfox/documentation/spring/web/plugins/Docket
       3: dup
       4: getstatic     #51                 // Field springfox/documentation/spi/DocumentationType.SWAGGER_2:Lspringfox/documentation/spi/DocumentationType;
       7: invokespecial #52                 // Method springfox/documentation/spring/web/plugins/Docket."<init>":(Lspringfox/documentation/spi/DocumentationType;)V
      10: areturn

  public springfox.documentation.spi.service.contexts.DocumentationContextBuilder createContextBuilder(springfox.documentation.spi.DocumentationType, springfox.documentation.spring.web.plugins.DefaultConfiguration);
    Code:
       0: aload_0
       1: getfield      #53                 // Field defaultsProviders:Lorg/springframework/plugin/core/PluginRegistry;
       4: aload_1
       5: aload_2
       6: invokeinterface #48,  3           // InterfaceMethod org/springframework/plugin/core/PluginRegistry.getPluginFor:(Ljava/lang/Object;Lorg/springframework/plugin/core/Plugin;)Lorg/springframework/plugin/core/Plugin;
      11: checkcast     #54                 // class springfox/documentation/spi/service/DefaultsProviderPlugin
      14: aload_1
      15: invokeinterface #55,  2           // InterfaceMethod springfox/documentation/spi/service/DefaultsProviderPlugin.create:(Lspringfox/documentation/spi/DocumentationType;)Lspringfox/documentation/spi/service/contexts/DocumentationContextBuilder;
      20: aload_0
      21: aload_1
      22: invokevirtual #56                 // Method resourceGroupingStrategy:(Lspringfox/documentation/spi/DocumentationType;)Lspringfox/documentation/spi/service/ResourceGroupingStrategy;
      25: invokevirtual #57                 // Method springfox/documentation/spi/service/contexts/DocumentationContextBuilder.withResourceGroupingStrategy:(Lspringfox/documentation/spi/service/ResourceGroupingStrategy;)Lspringfox/documentation/spi/service/contexts/DocumentationContextBuilder;
      28: areturn

  public com.google.common.base.Function<java.lang.String, java.lang.String> decorator(springfox.documentation.spi.service.contexts.PathContext);
    Code:
       0: new           #58                 // class springfox/documentation/spring/web/plugins/DocumentationPluginsManager$1
       3: dup
       4: aload_0
       5: aload_1
       6: invokespecial #59                 // Method springfox/documentation/spring/web/plugins/DocumentationPluginsManager$1."<init>":(Lspringfox/documentation/spring/web/plugins/DocumentationPluginsManager;Lspringfox/documentation/spi/service/contexts/PathContext;)V
       9: areturn

  private com.google.common.base.Function<? super springfox.documentation.service.PathDecorator, com.google.common.base.Function<java.lang.String, java.lang.String>> toDecorator(springfox.documentation.spi.service.contexts.PathContext);
    Code:
       0: new           #60                 // class springfox/documentation/spring/web/plugins/DocumentationPluginsManager$2
       3: dup
       4: aload_0
       5: aload_1
       6: invokespecial #61                 // Method springfox/documentation/spring/web/plugins/DocumentationPluginsManager$2."<init>":(Lspringfox/documentation/spring/web/plugins/DocumentationPluginsManager;Lspringfox/documentation/spi/service/contexts/PathContext;)V
       9: areturn

  public java.util.Collection<springfox.documentation.service.ApiDescription> additionalListings(springfox.documentation.spring.web.scanners.ApiListingScanningContext);
    Code:
       0: aload_1
       1: invokevirtual #62                 // Method springfox/documentation/spring/web/scanners/ApiListingScanningContext.getDocumentationContext:()Lspringfox/documentation/spi/service/contexts/DocumentationContext;
       4: invokevirtual #39                 // Method springfox/documentation/spi/service/contexts/DocumentationContext.getDocumentationType:()Lspringfox/documentation/spi/DocumentationType;
       7: astore_2
       8: invokestatic  #63                 // Method com/google/common/collect/Lists.newArrayList:()Ljava/util/ArrayList;
      11: astore_3
      12: aload_0
      13: getfield      #64                 // Field apiListingScanners:Lorg/springframework/plugin/core/PluginRegistry;
      16: aload_2
      17: invokeinterface #13,  2           // InterfaceMethod org/springframework/plugin/core/PluginRegistry.getPluginsFor:(Ljava/lang/Object;)Ljava/util/List;
      22: invokeinterface #14,  1           // InterfaceMethod java/util/List.iterator:()Ljava/util/Iterator;
      27: astore        4
      29: aload         4
      31: invokeinterface #15,  1           // InterfaceMethod java/util/Iterator.hasNext:()Z
      36: ifeq          72
      39: aload         4
      41: invokeinterface #16,  1           // InterfaceMethod java/util/Iterator.next:()Ljava/lang/Object;
      46: checkcast     #65                 // class springfox/documentation/spi/service/ApiListingScannerPlugin
      49: astore        5
      51: aload_3
      52: aload         5
      54: aload_1
      55: invokevirtual #62                 // Method springfox/documentation/spring/web/scanners/ApiListingScanningContext.getDocumentationContext:()Lspringfox/documentation/spi/service/contexts/DocumentationContext;
      58: invokeinterface #66,  2           // InterfaceMethod springfox/documentation/spi/service/ApiListingScannerPlugin.apply:(Lspringfox/documentation/spi/service/contexts/DocumentationContext;)Ljava/util/List;
      63: invokeinterface #67,  2           // InterfaceMethod java/util/List.addAll:(Ljava/util/Collection;)Z
      68: pop
      69: goto          29
      72: aload_3
      73: areturn

  static com.google.common.base.Function access$000(springfox.documentation.spring.web.plugins.DocumentationPluginsManager, springfox.documentation.spi.service.contexts.PathContext);
    Code:
       0: aload_0
       1: aload_1
       2: invokespecial #2                  // Method toDecorator:(Lspringfox/documentation/spi/service/contexts/PathContext;)Lcom/google/common/base/Function;
       5: areturn

  static org.springframework.plugin.core.PluginRegistry access$100(springfox.documentation.spring.web.plugins.DocumentationPluginsManager);
    Code:
       0: aload_0
       1: getfield      #1                  // Field pathDecorators:Lorg/springframework/plugin/core/PluginRegistry;
       4: areturn
}
