Compiled from "MapDbDatabaseBuilder.java"
public class technology.dice.dicewhere.building.navigablemap.MapDbDatabaseBuilder implements java.lang.Runnable {
  private final java.util.concurrent.BlockingQueue<technology.dice.dicewhere.lineprocessing.SerializedLine> source;

  private final technology.dice.dicewhere.building.DatabaseBuilderListener listener;

  private final technology.dice.dicewhere.provider.ProviderKey provider;

  private final org.mapdb.DB$TreeMapSink<technology.dice.dicewhere.api.api.IP, byte[]> sink;

  private boolean expectingMore;

  private int processedLines;

  private final technology.dice.dicewhere.decorator.Decorator<? extends technology.dice.dicewhere.decorator.DecoratorInformation> decorator;

  public technology.dice.dicewhere.building.navigablemap.MapDbDatabaseBuilder(technology.dice.dicewhere.provider.ProviderKey, java.util.concurrent.BlockingQueue<technology.dice.dicewhere.lineprocessing.SerializedLine>, technology.dice.dicewhere.building.DatabaseBuilderListener, technology.dice.dicewhere.decorator.Decorator<? extends technology.dice.dicewhere.decorator.DecoratorInformation>);
    Code:
       0: aload_0
       1: getstatic     #1                  // Field technology/dice/dicewhere/building/navigablemap/MapDbDatabaseBuilder$StorageMode.FILE:Ltechnology/dice/dicewhere/building/navigablemap/MapDbDatabaseBuilder$StorageMode;
       4: aload_1
       5: aload_2
       6: aload_3
       7: aload         4
       9: invokespecial #2                  // Method "<init>":(Ltechnology/dice/dicewhere/building/navigablemap/MapDbDatabaseBuilder$StorageMode;Ltechnology/dice/dicewhere/provider/ProviderKey;Ljava/util/concurrent/BlockingQueue;Ltechnology/dice/dicewhere/building/DatabaseBuilderListener;Ltechnology/dice/dicewhere/decorator/Decorator;)V
      12: return

  public technology.dice.dicewhere.building.navigablemap.MapDbDatabaseBuilder(technology.dice.dicewhere.building.navigablemap.MapDbDatabaseBuilder$StorageMode, technology.dice.dicewhere.provider.ProviderKey, java.util.concurrent.BlockingQueue<technology.dice.dicewhere.lineprocessing.SerializedLine>, technology.dice.dicewhere.building.DatabaseBuilderListener);
    Code:
       0: aload_0
       1: aload_1
       2: aload_2
       3: aload_3
       4: aload         4
       6: aconst_null
       7: invokespecial #2                  // Method "<init>":(Ltechnology/dice/dicewhere/building/navigablemap/MapDbDatabaseBuilder$StorageMode;Ltechnology/dice/dicewhere/provider/ProviderKey;Ljava/util/concurrent/BlockingQueue;Ltechnology/dice/dicewhere/building/DatabaseBuilderListener;Ltechnology/dice/dicewhere/decorator/Decorator;)V
      10: return

  public technology.dice.dicewhere.building.navigablemap.MapDbDatabaseBuilder(technology.dice.dicewhere.building.navigablemap.MapDbDatabaseBuilder$StorageMode, technology.dice.dicewhere.provider.ProviderKey, java.util.concurrent.BlockingQueue<technology.dice.dicewhere.lineprocessing.SerializedLine>, technology.dice.dicewhere.building.DatabaseBuilderListener, technology.dice.dicewhere.decorator.Decorator<? extends technology.dice.dicewhere.decorator.DecoratorInformation>);
    Code:
       0: aload_0
       1: invokespecial #3                  // Method java/lang/Object."<init>":()V
       4: aload_0
       5: iconst_0
       6: putfield      #4                  // Field processedLines:I
       9: aload_0
      10: aload_3
      11: putfield      #5                  // Field source:Ljava/util/concurrent/BlockingQueue;
      14: aload_0
      15: iconst_1
      16: putfield      #6                  // Field expectingMore:Z
      19: aload_0
      20: aload         4
      22: putfield      #7                  // Field listener:Ltechnology/dice/dicewhere/building/DatabaseBuilderListener;
      25: aload_0
      26: aload_2
      27: putfield      #8                  // Field provider:Ltechnology/dice/dicewhere/provider/ProviderKey;
      30: aload_0
      31: aload_1
      32: invokespecial #9                  // Method createDB:(Ltechnology/dice/dicewhere/building/navigablemap/MapDbDatabaseBuilder$StorageMode;)Lorg/mapdb/DB;
      35: astore        6
      37: aload         6
      39: aload_2
      40: invokestatic  #10                 // Method java/util/Objects.requireNonNull:(Ljava/lang/Object;)Ljava/lang/Object;
      43: checkcast     #11                 // class technology/dice/dicewhere/provider/ProviderKey
      46: invokevirtual #12                 // Method technology/dice/dicewhere/provider/ProviderKey.name:()Ljava/lang/String;
      49: new           #13                 // class technology/dice/dicewhere/lineprocessing/serializers/IPSerializer
      52: dup
      53: invokespecial #14                 // Method technology/dice/dicewhere/lineprocessing/serializers/IPSerializer."<init>":()V
      56: getstatic     #15                 // Field org/mapdb/Serializer.BYTE_ARRAY:Lorg/mapdb/serializer/GroupSerializer;
      59: invokevirtual #16                 // Method org/mapdb/DB.treeMap:(Ljava/lang/String;Lorg/mapdb/serializer/GroupSerializer;Lorg/mapdb/serializer/GroupSerializer;)Lorg/mapdb/DB$TreeMapMaker;
      62: invokevirtual #17                 // Method org/mapdb/DB$TreeMapMaker.createFromSink:()Lorg/mapdb/DB$TreeMapSink;
      65: astore        7
      67: aload_0
      68: aload         7
      70: putfield      #18                 // Field sink:Lorg/mapdb/DB$TreeMapSink;
      73: aload_0
      74: aload         5
      76: putfield      #19                 // Field decorator:Ltechnology/dice/dicewhere/decorator/Decorator;
      79: return

  private org.mapdb.DB createDB(technology.dice.dicewhere.building.navigablemap.MapDbDatabaseBuilder$StorageMode);
    Code:
       0: getstatic     #20                 // Field technology/dice/dicewhere/building/navigablemap/MapDbDatabaseBuilder$1.$SwitchMap$technology$dice$dicewhere$building$navigablemap$MapDbDatabaseBuilder$StorageMode:[I
       3: aload_1
       4: invokevirtual #21                 // Method technology/dice/dicewhere/building/navigablemap/MapDbDatabaseBuilder$StorageMode.ordinal:()I
       7: iaload
       8: tableswitch   { // 1 to 4
                     1: 40
                     2: 53
                     3: 66
                     4: 79
               default: 79
          }
      40: invokestatic  #22                 // Method org/mapdb/DBMaker.heapDB:()Lorg/mapdb/DBMaker$Maker;
      43: invokevirtual #23                 // Method org/mapdb/DBMaker$Maker.checksumHeaderBypass:()Lorg/mapdb/DBMaker$Maker;
      46: invokevirtual #24                 // Method org/mapdb/DBMaker$Maker.make:()Lorg/mapdb/DB;
      49: astore_2
      50: goto          101
      53: invokestatic  #25                 // Method org/mapdb/DBMaker.memoryDB:()Lorg/mapdb/DBMaker$Maker;
      56: invokevirtual #23                 // Method org/mapdb/DBMaker$Maker.checksumHeaderBypass:()Lorg/mapdb/DBMaker$Maker;
      59: invokevirtual #24                 // Method org/mapdb/DBMaker$Maker.make:()Lorg/mapdb/DB;
      62: astore_2
      63: goto          101
      66: invokestatic  #26                 // Method org/mapdb/DBMaker.memoryDirectDB:()Lorg/mapdb/DBMaker$Maker;
      69: invokevirtual #23                 // Method org/mapdb/DBMaker$Maker.checksumHeaderBypass:()Lorg/mapdb/DBMaker$Maker;
      72: invokevirtual #24                 // Method org/mapdb/DBMaker$Maker.make:()Lorg/mapdb/DB;
      75: astore_2
      76: goto          101
      79: invokestatic  #27                 // Method org/mapdb/DBMaker.tempFileDB:()Lorg/mapdb/DBMaker$Maker;
      82: invokevirtual #23                 // Method org/mapdb/DBMaker$Maker.checksumHeaderBypass:()Lorg/mapdb/DBMaker$Maker;
      85: invokevirtual #28                 // Method org/mapdb/DBMaker$Maker.fileLockDisable:()Lorg/mapdb/DBMaker$Maker;
      88: invokevirtual #29                 // Method org/mapdb/DBMaker$Maker.fileMmapEnable:()Lorg/mapdb/DBMaker$Maker;
      91: invokevirtual #30                 // Method org/mapdb/DBMaker$Maker.fileChannelEnable:()Lorg/mapdb/DBMaker$Maker;
      94: invokevirtual #31                 // Method org/mapdb/DBMaker$Maker.fileDeleteAfterClose:()Lorg/mapdb/DBMaker$Maker;
      97: invokevirtual #24                 // Method org/mapdb/DBMaker$Maker.make:()Lorg/mapdb/DB;
     100: astore_2
     101: aload_2
     102: areturn

  public void dontExpectMore();
    Code:
       0: aload_0
       1: iconst_0
       2: putfield      #6                  // Field expectingMore:Z
       5: return

  public int remainingLines();
    Code:
       0: aload_0
       1: getfield      #5                  // Field source:Ljava/util/concurrent/BlockingQueue;
       4: invokeinterface #32,  1           // InterfaceMethod java/util/concurrent/BlockingQueue.size:()I
       9: ireturn

  public int processedLines();
    Code:
       0: aload_0
       1: getfield      #4                  // Field processedLines:I
       4: ireturn

  protected java.util.Optional<technology.dice.dicewhere.decorator.Decorator<? extends technology.dice.dicewhere.decorator.DecoratorInformation>> getDecorator();
    Code:
       0: aload_0
       1: getfield      #19                 // Field decorator:Ltechnology/dice/dicewhere/decorator/Decorator;
       4: invokestatic  #33                 // Method java/util/Optional.ofNullable:(Ljava/lang/Object;)Ljava/util/Optional;
       7: areturn

  public void run();
    Code:
       0: aload_0
       1: getfield      #6                  // Field expectingMore:Z
       4: ifne          19
       7: aload_0
       8: getfield      #5                  // Field source:Ljava/util/concurrent/BlockingQueue;
      11: invokeinterface #32,  1           // InterfaceMethod java/util/concurrent/BlockingQueue.size:()I
      16: ifle          211
      19: aconst_null
      20: astore_1
      21: new           #34                 // class java/util/ArrayList
      24: dup
      25: aload_0
      26: getfield      #5                  // Field source:Ljava/util/concurrent/BlockingQueue;
      29: invokeinterface #32,  1           // InterfaceMethod java/util/concurrent/BlockingQueue.size:()I
      34: invokespecial #35                 // Method java/util/ArrayList."<init>":(I)V
      37: astore_2
      38: aload_0
      39: getfield      #5                  // Field source:Ljava/util/concurrent/BlockingQueue;
      42: aload_2
      43: aload_0
      44: getfield      #5                  // Field source:Ljava/util/concurrent/BlockingQueue;
      47: invokeinterface #32,  1           // InterfaceMethod java/util/concurrent/BlockingQueue.size:()I
      52: lconst_1
      53: getstatic     #36                 // Field java/util/concurrent/TimeUnit.NANOSECONDS:Ljava/util/concurrent/TimeUnit;
      56: invokestatic  #37                 // Method com/google/common/collect/Queues.drain:(Ljava/util/concurrent/BlockingQueue;Ljava/util/Collection;IJLjava/util/concurrent/TimeUnit;)I
      59: pop
      60: aload_2
      61: invokeinterface #38,  1           // InterfaceMethod java/util/List.iterator:()Ljava/util/Iterator;
      66: astore_3
      67: aload_3
      68: invokeinterface #39,  1           // InterfaceMethod java/util/Iterator.hasNext:()Z
      73: ifeq          179
      76: aload_3
      77: invokeinterface #40,  1           // InterfaceMethod java/util/Iterator.next:()Ljava/lang/Object;
      82: checkcast     #41                 // class technology/dice/dicewhere/lineprocessing/SerializedLine
      85: astore        4
      87: aload         4
      89: astore_1
      90: aload_0
      91: aload         4
      93: invokevirtual #42                 // Method technology/dice/dicewhere/lineprocessing/SerializedLine.getParsedLine:()Ltechnology/dice/dicewhere/parsing/ParsedLine;
      96: invokevirtual #43                 // Method technology/dice/dicewhere/parsing/ParsedLine.getInfo:()Ltechnology/dice/dicewhere/api/api/IpInformation;
      99: invokespecial #44                 // Method decorateEntry:(Ltechnology/dice/dicewhere/api/api/IpInformation;)Ljava/util/stream/Stream;
     102: aload_0
     103: invokedynamic #45,  0             // InvokeDynamic #0:accept:(Ltechnology/dice/dicewhere/building/navigablemap/MapDbDatabaseBuilder;)Ljava/util/function/Consumer;
     108: invokeinterface #46,  2           // InterfaceMethod java/util/stream/Stream.forEach:(Ljava/util/function/Consumer;)V
     113: aload_0
     114: dup
     115: getfield      #4                  // Field processedLines:I
     118: iconst_1
     119: iadd
     120: putfield      #4                  // Field processedLines:I
     123: aload_0
     124: getfield      #7                  // Field listener:Ltechnology/dice/dicewhere/building/DatabaseBuilderListener;
     127: aload_0
     128: getfield      #8                  // Field provider:Ltechnology/dice/dicewhere/provider/ProviderKey;
     131: aload         4
     133: invokeinterface #47,  3           // InterfaceMethod technology/dice/dicewhere/building/DatabaseBuilderListener.lineAdded:(Ltechnology/dice/dicewhere/provider/ProviderKey;Ltechnology/dice/dicewhere/lineprocessing/SerializedLine;)V
     138: goto          176
     141: astore        5
     143: aload_0
     144: getfield      #7                  // Field listener:Ltechnology/dice/dicewhere/building/DatabaseBuilderListener;
     147: aload_0
     148: getfield      #8                  // Field provider:Ltechnology/dice/dicewhere/provider/ProviderKey;
     151: aload_1
     152: aload         5
     154: invokeinterface #49,  4           // InterfaceMethod technology/dice/dicewhere/building/DatabaseBuilderListener.lineOutOfOrder:(Ltechnology/dice/dicewhere/provider/ProviderKey;Ltechnology/dice/dicewhere/lineprocessing/SerializedLine;Ljava/lang/Exception;)V
     159: goto          176
     162: astore        5
     164: new           #51                 // class java/lang/RuntimeException
     167: dup
     168: ldc           #52                 // String Database builder interrupted
     170: aload         5
     172: invokespecial #53                 // Method java/lang/RuntimeException."<init>":(Ljava/lang/String;Ljava/lang/Throwable;)V
     175: athrow
     176: goto          67
     179: goto          208
     182: astore_3
     183: aload_0
     184: getfield      #7                  // Field listener:Ltechnology/dice/dicewhere/building/DatabaseBuilderListener;
     187: aload_0
     188: getfield      #8                  // Field provider:Ltechnology/dice/dicewhere/provider/ProviderKey;
     191: aload_3
     192: invokeinterface #55,  3           // InterfaceMethod technology/dice/dicewhere/building/DatabaseBuilderListener.builderInterrupted:(Ltechnology/dice/dicewhere/provider/ProviderKey;Ljava/lang/InterruptedException;)V
     197: new           #51                 // class java/lang/RuntimeException
     200: dup
     201: ldc           #52                 // String Database builder interrupted
     203: aload_3
     204: invokespecial #53                 // Method java/lang/RuntimeException."<init>":(Ljava/lang/String;Ljava/lang/Throwable;)V
     207: athrow
     208: goto          0
     211: return
    Exception table:
       from    to  target type
          87   138   141   Class org/mapdb/DBException$NotSorted
          87   138   162   Class java/lang/Exception
          38   179   182   Class java/lang/InterruptedException

  private java.util.stream.Stream<technology.dice.dicewhere.api.api.IpInformation> decorateEntry(technology.dice.dicewhere.api.api.IpInformation) throws java.net.UnknownHostException;
    Code:
       0: aload_0
       1: invokevirtual #56                 // Method getDecorator:()Ljava/util/Optional;
       4: invokevirtual #57                 // Method java/util/Optional.isPresent:()Z
       7: ifeq          25
      10: aload_0
      11: invokevirtual #56                 // Method getDecorator:()Ljava/util/Optional;
      14: invokevirtual #58                 // Method java/util/Optional.get:()Ljava/lang/Object;
      17: checkcast     #59                 // class technology/dice/dicewhere/decorator/Decorator
      20: aload_1
      21: invokevirtual #60                 // Method technology/dice/dicewhere/decorator/Decorator.decorate:(Ltechnology/dice/dicewhere/api/api/IpInformation;)Ljava/util/stream/Stream;
      24: areturn
      25: aload_1
      26: invokestatic  #61                 // InterfaceMethod java/util/stream/Stream.of:(Ljava/lang/Object;)Ljava/util/stream/Stream;
      29: areturn

  private technology.dice.dicewhere.lineprocessing.serializers.protobuf.IPInformationProto$IpInformationProto buildIpProtobuf(technology.dice.dicewhere.api.api.IpInformation);
    Code:
       0: invokestatic  #62                 // Method technology/dice/dicewhere/lineprocessing/serializers/protobuf/IPInformationProto$IpInformationProto.newBuilder:()Ltechnology/dice/dicewhere/lineprocessing/serializers/protobuf/IPInformationProto$IpInformationProto$Builder;
       3: aload_1
       4: invokevirtual #63                 // Method technology/dice/dicewhere/api/api/IpInformation.getCity:()Ljava/util/Optional;
       7: ldc           #64                 // String
       9: invokevirtual #65                 // Method java/util/Optional.orElse:(Ljava/lang/Object;)Ljava/lang/Object;
      12: checkcast     #66                 // class java/lang/String
      15: invokevirtual #67                 // Method technology/dice/dicewhere/lineprocessing/serializers/protobuf/IPInformationProto$IpInformationProto$Builder.setCity:(Ljava/lang/String;)Ltechnology/dice/dicewhere/lineprocessing/serializers/protobuf/IPInformationProto$IpInformationProto$Builder;
      18: aload_1
      19: invokevirtual #68                 // Method technology/dice/dicewhere/api/api/IpInformation.getGeonameId:()Ljava/util/Optional;
      22: ldc           #64                 // String
      24: invokevirtual #65                 // Method java/util/Optional.orElse:(Ljava/lang/Object;)Ljava/lang/Object;
      27: checkcast     #66                 // class java/lang/String
      30: invokevirtual #69                 // Method technology/dice/dicewhere/lineprocessing/serializers/protobuf/IPInformationProto$IpInformationProto$Builder.setGeonameId:(Ljava/lang/String;)Ltechnology/dice/dicewhere/lineprocessing/serializers/protobuf/IPInformationProto$IpInformationProto$Builder;
      33: aload_1
      34: invokevirtual #70                 // Method technology/dice/dicewhere/api/api/IpInformation.getCountryCodeAlpha2:()Ljava/lang/String;
      37: invokevirtual #71                 // Method technology/dice/dicewhere/lineprocessing/serializers/protobuf/IPInformationProto$IpInformationProto$Builder.setCountryCodeAlpha2:(Ljava/lang/String;)Ltechnology/dice/dicewhere/lineprocessing/serializers/protobuf/IPInformationProto$IpInformationProto$Builder;
      40: aload_1
      41: invokevirtual #72                 // Method technology/dice/dicewhere/api/api/IpInformation.getLeastSpecificDivision:()Ljava/util/Optional;
      44: ldc           #64                 // String
      46: invokevirtual #65                 // Method java/util/Optional.orElse:(Ljava/lang/Object;)Ljava/lang/Object;
      49: checkcast     #66                 // class java/lang/String
      52: invokevirtual #73                 // Method technology/dice/dicewhere/lineprocessing/serializers/protobuf/IPInformationProto$IpInformationProto$Builder.setLeastSpecificDivision:(Ljava/lang/String;)Ltechnology/dice/dicewhere/lineprocessing/serializers/protobuf/IPInformationProto$IpInformationProto$Builder;
      55: aload_1
      56: invokevirtual #74                 // Method technology/dice/dicewhere/api/api/IpInformation.getMostSpecificDivision:()Ljava/util/Optional;
      59: ldc           #64                 // String
      61: invokevirtual #65                 // Method java/util/Optional.orElse:(Ljava/lang/Object;)Ljava/lang/Object;
      64: checkcast     #66                 // class java/lang/String
      67: invokevirtual #75                 // Method technology/dice/dicewhere/lineprocessing/serializers/protobuf/IPInformationProto$IpInformationProto$Builder.setMostSpecificDivision:(Ljava/lang/String;)Ltechnology/dice/dicewhere/lineprocessing/serializers/protobuf/IPInformationProto$IpInformationProto$Builder;
      70: aload_1
      71: invokevirtual #76                 // Method technology/dice/dicewhere/api/api/IpInformation.getPostcode:()Ljava/util/Optional;
      74: ldc           #64                 // String
      76: invokevirtual #65                 // Method java/util/Optional.orElse:(Ljava/lang/Object;)Ljava/lang/Object;
      79: checkcast     #66                 // class java/lang/String
      82: invokevirtual #77                 // Method technology/dice/dicewhere/lineprocessing/serializers/protobuf/IPInformationProto$IpInformationProto$Builder.setPostcode:(Ljava/lang/String;)Ltechnology/dice/dicewhere/lineprocessing/serializers/protobuf/IPInformationProto$IpInformationProto$Builder;
      85: aload_1
      86: invokevirtual #78                 // Method technology/dice/dicewhere/api/api/IpInformation.getStartOfRange:()Ltechnology/dice/dicewhere/api/api/IP;
      89: invokevirtual #79                 // Method technology/dice/dicewhere/api/api/IP.getBytes:()[B
      92: invokestatic  #80                 // Method com/google/protobuf/ByteString.copyFrom:([B)Lcom/google/protobuf/ByteString;
      95: invokevirtual #81                 // Method technology/dice/dicewhere/lineprocessing/serializers/protobuf/IPInformationProto$IpInformationProto$Builder.setStartOfRange:(Lcom/google/protobuf/ByteString;)Ltechnology/dice/dicewhere/lineprocessing/serializers/protobuf/IPInformationProto$IpInformationProto$Builder;
      98: aload_1
      99: invokevirtual #82                 // Method technology/dice/dicewhere/api/api/IpInformation.getEndOfRange:()Ltechnology/dice/dicewhere/api/api/IP;
     102: invokevirtual #79                 // Method technology/dice/dicewhere/api/api/IP.getBytes:()[B
     105: invokestatic  #80                 // Method com/google/protobuf/ByteString.copyFrom:([B)Lcom/google/protobuf/ByteString;
     108: invokevirtual #83                 // Method technology/dice/dicewhere/lineprocessing/serializers/protobuf/IPInformationProto$IpInformationProto$Builder.setEndOfRange:(Lcom/google/protobuf/ByteString;)Ltechnology/dice/dicewhere/lineprocessing/serializers/protobuf/IPInformationProto$IpInformationProto$Builder;
     111: aload_1
     112: invokevirtual #84                 // Method technology/dice/dicewhere/api/api/IpInformation.isVpn:()Ljava/util/Optional;
     115: aconst_null
     116: invokevirtual #65                 // Method java/util/Optional.orElse:(Ljava/lang/Object;)Ljava/lang/Object;
     119: checkcast     #85                 // class java/lang/Boolean
     122: invokestatic  #86                 // Method technology/dice/dicewhere/utils/ProtoValueConverter.toThreeStateValue:(Ljava/lang/Boolean;)Ltechnology/dice/dicewhere/lineprocessing/serializers/protobuf/ThreeStateValueProto$ThreeStateValue;
     125: invokevirtual #87                 // Method technology/dice/dicewhere/lineprocessing/serializers/protobuf/IPInformationProto$IpInformationProto$Builder.setIsVpn:(Ltechnology/dice/dicewhere/lineprocessing/serializers/protobuf/ThreeStateValueProto$ThreeStateValue;)Ltechnology/dice/dicewhere/lineprocessing/serializers/protobuf/IPInformationProto$IpInformationProto$Builder;
     128: astore_2
     129: aload_1
     130: invokevirtual #88                 // Method technology/dice/dicewhere/api/api/IpInformation.getOriginalLine:()Ljava/util/Optional;
     133: aload_2
     134: dup
     135: invokevirtual #89                 // Method java/lang/Object.getClass:()Ljava/lang/Class;
     138: pop
     139: invokedynamic #90,  0             // InvokeDynamic #1:accept:(Ltechnology/dice/dicewhere/lineprocessing/serializers/protobuf/IPInformationProto$IpInformationProto$Builder;)Ljava/util/function/Consumer;
     144: invokevirtual #91                 // Method java/util/Optional.ifPresent:(Ljava/util/function/Consumer;)V
     147: aload_2
     148: invokevirtual #92                 // Method technology/dice/dicewhere/lineprocessing/serializers/protobuf/IPInformationProto$IpInformationProto$Builder.build:()Ltechnology/dice/dicewhere/lineprocessing/serializers/protobuf/IPInformationProto$IpInformationProto;
     151: areturn

  public technology.dice.dicewhere.building.navigablemap.NavigableMapIpDatabase build();
    Code:
       0: new           #93                 // class technology/dice/dicewhere/building/navigablemap/NavigableMapIpDatabase
       3: dup
       4: aload_0
       5: getfield      #18                 // Field sink:Lorg/mapdb/DB$TreeMapSink;
       8: invokevirtual #94                 // Method org/mapdb/DB$TreeMapSink.create:()Ljava/lang/Object;
      11: checkcast     #95                 // class java/util/NavigableMap
      14: invokespecial #96                 // Method technology/dice/dicewhere/building/navigablemap/NavigableMapIpDatabase."<init>":(Ljava/util/NavigableMap;)V
      17: areturn

  private void lambda$run$0(technology.dice.dicewhere.api.api.IpInformation);
    Code:
       0: aload_0
       1: getfield      #18                 // Field sink:Lorg/mapdb/DB$TreeMapSink;
       4: aload_1
       5: invokevirtual #78                 // Method technology/dice/dicewhere/api/api/IpInformation.getStartOfRange:()Ltechnology/dice/dicewhere/api/api/IP;
       8: aload_0
       9: aload_1
      10: invokespecial #97                 // Method buildIpProtobuf:(Ltechnology/dice/dicewhere/api/api/IpInformation;)Ltechnology/dice/dicewhere/lineprocessing/serializers/protobuf/IPInformationProto$IpInformationProto;
      13: invokevirtual #98                 // Method technology/dice/dicewhere/lineprocessing/serializers/protobuf/IPInformationProto$IpInformationProto.toByteArray:()[B
      16: invokevirtual #99                 // Method org/mapdb/DB$TreeMapSink.put:(Ljava/lang/Object;Ljava/lang/Object;)V
      19: return
}
