public class org.bouncycastle.pqc.math.ntru.polynomial.LongPolynomial5 {
  private long[] coeffs;

  private int numCoeffs;

  public org.bouncycastle.pqc.math.ntru.polynomial.LongPolynomial5(org.bouncycastle.pqc.math.ntru.polynomial.IntegerPolynomial);
    Code:
       0: aload_0
       1: invokespecial #53                 // Method java/lang/Object."<init>":()V
       4: aload_0
       5: aload_1
       6: getfield      #50                 // Field org/bouncycastle/pqc/math/ntru/polynomial/IntegerPolynomial.coeffs:[I
       9: arraylength
      10: putfield      #51                 // Field numCoeffs:I
      13: aload_0
      14: aload_0
      15: getfield      #51                 // Field numCoeffs:I
      18: iconst_4
      19: iadd
      20: iconst_5
      21: idiv
      22: newarray       long
      24: putfield      #52                 // Field coeffs:[J
      27: iconst_0
      28: istore_2
      29: iconst_0
      30: istore_3
      31: iconst_0
      32: istore        4
      34: iload         4
      36: aload_0
      37: getfield      #51                 // Field numCoeffs:I
      40: if_icmpge     82
      43: aload_0
      44: getfield      #52                 // Field coeffs:[J
      47: iload_2
      48: dup2
      49: laload
      50: aload_1
      51: getfield      #50                 // Field org/bouncycastle/pqc/math/ntru/polynomial/IntegerPolynomial.coeffs:[I
      54: iload         4
      56: iaload
      57: i2l
      58: iload_3
      59: lshl
      60: lor
      61: lastore
      62: iinc          3, 12
      65: iload_3
      66: bipush        60
      68: if_icmplt     76
      71: iconst_0
      72: istore_3
      73: iinc          2, 1
      76: iinc          4, 1
      79: goto          34
      82: return

  private org.bouncycastle.pqc.math.ntru.polynomial.LongPolynomial5(long[], int);
    Code:
       0: aload_0
       1: invokespecial #53                 // Method java/lang/Object."<init>":()V
       4: aload_0
       5: aload_1
       6: putfield      #52                 // Field coeffs:[J
       9: aload_0
      10: iload_2
      11: putfield      #51                 // Field numCoeffs:I
      14: return

  public org.bouncycastle.pqc.math.ntru.polynomial.LongPolynomial5 mult(org.bouncycastle.pqc.math.ntru.polynomial.TernaryPolynomial);
    Code:
       0: iconst_5
       1: aload_0
       2: getfield      #52                 // Field coeffs:[J
       5: arraylength
       6: aload_1
       7: invokeinterface #57,  1           // InterfaceMethod org/bouncycastle/pqc/math/ntru/polynomial/TernaryPolynomial.size:()I
      12: iconst_4
      13: iadd
      14: iconst_5
      15: idiv
      16: iadd
      17: iconst_1
      18: isub
      19: multianewarray #31,  2            // class "[[J"
      23: astore_2
      24: aload_1
      25: invokeinterface #59,  1           // InterfaceMethod org/bouncycastle/pqc/math/ntru/polynomial/TernaryPolynomial.getOnes:()[I
      30: astore_3
      31: iconst_0
      32: istore        4
      34: iload         4
      36: aload_3
      37: arraylength
      38: if_icmpeq     116
      41: aload_3
      42: iload         4
      44: iaload
      45: istore        5
      47: iload         5
      49: iconst_5
      50: idiv
      51: istore        6
      53: iload         5
      55: iload         6
      57: iconst_5
      58: imul
      59: isub
      60: istore        7
      62: iconst_0
      63: istore        8
      65: iload         8
      67: aload_0
      68: getfield      #52                 // Field coeffs:[J
      71: arraylength
      72: if_icmpge     110
      75: aload_2
      76: iload         7
      78: aaload
      79: iload         6
      81: aload_2
      82: iload         7
      84: aaload
      85: iload         6
      87: laload
      88: aload_0
      89: getfield      #52                 // Field coeffs:[J
      92: iload         8
      94: laload
      95: ladd
      96: ldc2_w        #27                 // long 576319980446939135l
      99: land
     100: lastore
     101: iinc          6, 1
     104: iinc          8, 1
     107: goto          65
     110: iinc          4, 1
     113: goto          34
     116: aload_1
     117: invokeinterface #58,  1           // InterfaceMethod org/bouncycastle/pqc/math/ntru/polynomial/TernaryPolynomial.getNegOnes:()[I
     122: astore        4
     124: iconst_0
     125: istore        5
     127: iload         5
     129: aload         4
     131: arraylength
     132: if_icmpeq     215
     135: aload         4
     137: iload         5
     139: iaload
     140: istore        6
     142: iload         6
     144: iconst_5
     145: idiv
     146: istore        7
     148: iload         6
     150: iload         7
     152: iconst_5
     153: imul
     154: isub
     155: istore        8
     157: iconst_0
     158: istore        9
     160: iload         9
     162: aload_0
     163: getfield      #52                 // Field coeffs:[J
     166: arraylength
     167: if_icmpge     209
     170: aload_2
     171: iload         8
     173: aaload
     174: iload         7
     176: ldc2_w        #29                 // long 576601524159907840l
     179: aload_2
     180: iload         8
     182: aaload
     183: iload         7
     185: laload
     186: ladd
     187: aload_0
     188: getfield      #52                 // Field coeffs:[J
     191: iload         9
     193: laload
     194: lsub
     195: ldc2_w        #27                 // long 576319980446939135l
     198: land
     199: lastore
     200: iinc          7, 1
     203: iinc          9, 1
     206: goto          160
     209: iinc          5, 1
     212: goto          127
     215: aload_2
     216: iconst_0
     217: aaload
     218: aload_2
     219: iconst_0
     220: aaload
     221: arraylength
     222: iconst_1
     223: iadd
     224: invokestatic  #56                 // Method org/bouncycastle/util/Arrays.copyOf:([JI)[J
     227: astore        5
     229: iconst_1
     230: istore        6
     232: iload         6
     234: iconst_4
     235: if_icmpgt     356
     238: iload         6
     240: bipush        12
     242: imul
     243: istore        7
     245: bipush        60
     247: iload         7
     249: isub
     250: istore        8
     252: lconst_1
     253: iload         8
     255: lshl
     256: lconst_1
     257: lsub
     258: lstore        9
     260: aload_2
     261: iload         6
     263: aaload
     264: arraylength
     265: istore        11
     267: iconst_0
     268: istore        12
     270: iload         12
     272: iload         11
     274: if_icmpge     350
     277: aload_2
     278: iload         6
     280: aaload
     281: iload         12
     283: laload
     284: iload         8
     286: lshr
     287: lstore        13
     289: aload_2
     290: iload         6
     292: aaload
     293: iload         12
     295: laload
     296: lload         9
     298: land
     299: lstore        15
     301: aload         5
     303: iload         12
     305: aload         5
     307: iload         12
     309: laload
     310: lload         15
     312: iload         7
     314: lshl
     315: ladd
     316: ldc2_w        #27                 // long 576319980446939135l
     319: land
     320: lastore
     321: iload         12
     323: iconst_1
     324: iadd
     325: istore        17
     327: aload         5
     329: iload         17
     331: aload         5
     333: iload         17
     335: laload
     336: lload         13
     338: ladd
     339: ldc2_w        #27                 // long 576319980446939135l
     342: land
     343: lastore
     344: iinc          12, 1
     347: goto          270
     350: iinc          6, 1
     353: goto          232
     356: bipush        12
     358: aload_0
     359: getfield      #51                 // Field numCoeffs:I
     362: iconst_5
     363: irem
     364: imul
     365: istore        6
     367: aload_0
     368: getfield      #52                 // Field coeffs:[J
     371: arraylength
     372: iconst_1
     373: isub
     374: istore        7
     376: iload         7
     378: aload         5
     380: arraylength
     381: if_icmpge     535
     384: iload         7
     386: aload_0
     387: getfield      #52                 // Field coeffs:[J
     390: arraylength
     391: iconst_1
     392: isub
     393: if_icmpne     424
     396: aload_0
     397: getfield      #51                 // Field numCoeffs:I
     400: iconst_5
     401: if_icmpne     408
     404: lconst_0
     405: goto          416
     408: aload         5
     410: iload         7
     412: laload
     413: iload         6
     415: lshr
     416: lstore        8
     418: iconst_0
     419: istore        10
     421: goto          442
     424: aload         5
     426: iload         7
     428: laload
     429: lstore        8
     431: iload         7
     433: iconst_5
     434: imul
     435: aload_0
     436: getfield      #51                 // Field numCoeffs:I
     439: isub
     440: istore        10
     442: iload         10
     444: iconst_5
     445: idiv
     446: istore        11
     448: iload         10
     450: iload         11
     452: iconst_5
     453: imul
     454: isub
     455: istore        12
     457: lload         8
     459: bipush        12
     461: iload         12
     463: imul
     464: lshl
     465: lstore        13
     467: lload         8
     469: bipush        12
     471: iconst_5
     472: iload         12
     474: isub
     475: imul
     476: lshr
     477: lstore        15
     479: aload         5
     481: iload         11
     483: aload         5
     485: iload         11
     487: laload
     488: lload         13
     490: ladd
     491: ldc2_w        #27                 // long 576319980446939135l
     494: land
     495: lastore
     496: iload         11
     498: iconst_1
     499: iadd
     500: istore        17
     502: iload         17
     504: aload_0
     505: getfield      #52                 // Field coeffs:[J
     508: arraylength
     509: if_icmpge     529
     512: aload         5
     514: iload         17
     516: aload         5
     518: iload         17
     520: laload
     521: lload         15
     523: ladd
     524: ldc2_w        #27                 // long 576319980446939135l
     527: land
     528: lastore
     529: iinc          7, 1
     532: goto          376
     535: new           #34                 // class org/bouncycastle/pqc/math/ntru/polynomial/LongPolynomial5
     538: dup
     539: aload         5
     541: aload_0
     542: getfield      #51                 // Field numCoeffs:I
     545: invokespecial #55                 // Method "<init>":([JI)V
     548: areturn

  public org.bouncycastle.pqc.math.ntru.polynomial.IntegerPolynomial toIntegerPolynomial();
    Code:
       0: aload_0
       1: getfield      #51                 // Field numCoeffs:I
       4: newarray       int
       6: astore_1
       7: iconst_0
       8: istore_2
       9: iconst_0
      10: istore_3
      11: iconst_0
      12: istore        4
      14: iload         4
      16: aload_0
      17: getfield      #51                 // Field numCoeffs:I
      20: if_icmpge     60
      23: aload_1
      24: iload         4
      26: aload_0
      27: getfield      #52                 // Field coeffs:[J
      30: iload_2
      31: laload
      32: iload_3
      33: lshr
      34: ldc2_w        #25                 // long 2047l
      37: land
      38: l2i
      39: iastore
      40: iinc          3, 12
      43: iload_3
      44: bipush        60
      46: if_icmplt     54
      49: iconst_0
      50: istore_3
      51: iinc          2, 1
      54: iinc          4, 1
      57: goto          14
      60: new           #33                 // class org/bouncycastle/pqc/math/ntru/polynomial/IntegerPolynomial
      63: dup
      64: aload_1
      65: invokespecial #54                 // Method org/bouncycastle/pqc/math/ntru/polynomial/IntegerPolynomial."<init>":([I)V
      68: areturn
}
