Compiled from "StatefulRedisPubSubConnectionImpl.java"
public class io.lettuce.core.pubsub.StatefulRedisPubSubConnectionImpl<K, V> extends io.lettuce.core.StatefulRedisConnectionImpl<K, V> implements io.lettuce.core.pubsub.StatefulRedisPubSubConnection<K, V> {
  private final io.lettuce.core.pubsub.PubSubEndpoint<K, V> endpoint;

  public io.lettuce.core.pubsub.StatefulRedisPubSubConnectionImpl(io.lettuce.core.pubsub.PubSubEndpoint<K, V>, io.lettuce.core.RedisChannelWriter, io.lettuce.core.codec.RedisCodec<K, V>, java.time.Duration);
    Code:
       0: aload_0
       1: aload_2
       2: aload_3
       3: aload         4
       5: invokespecial #1                  // Method io/lettuce/core/StatefulRedisConnectionImpl."<init>":(Lio/lettuce/core/RedisChannelWriter;Lio/lettuce/core/codec/RedisCodec;Ljava/time/Duration;)V
       8: aload_0
       9: aload_1
      10: putfield      #2                  // Field endpoint:Lio/lettuce/core/pubsub/PubSubEndpoint;
      13: return

  public void addListener(io.lettuce.core.pubsub.RedisPubSubListener<K, V>);
    Code:
       0: aload_0
       1: getfield      #2                  // Field endpoint:Lio/lettuce/core/pubsub/PubSubEndpoint;
       4: aload_1
       5: invokevirtual #3                  // Method io/lettuce/core/pubsub/PubSubEndpoint.addListener:(Lio/lettuce/core/pubsub/RedisPubSubListener;)V
       8: return

  public void removeListener(io.lettuce.core.pubsub.RedisPubSubListener<K, V>);
    Code:
       0: aload_0
       1: getfield      #2                  // Field endpoint:Lio/lettuce/core/pubsub/PubSubEndpoint;
       4: aload_1
       5: invokevirtual #4                  // Method io/lettuce/core/pubsub/PubSubEndpoint.removeListener:(Lio/lettuce/core/pubsub/RedisPubSubListener;)V
       8: return

  public io.lettuce.core.pubsub.api.async.RedisPubSubAsyncCommands<K, V> async();
    Code:
       0: aload_0
       1: getfield      #5                  // Field async:Lio/lettuce/core/RedisAsyncCommandsImpl;
       4: checkcast     #6                  // class io/lettuce/core/pubsub/api/async/RedisPubSubAsyncCommands
       7: areturn

  protected io.lettuce.core.pubsub.RedisPubSubAsyncCommandsImpl<K, V> newRedisAsyncCommandsImpl();
    Code:
       0: new           #7                  // class io/lettuce/core/pubsub/RedisPubSubAsyncCommandsImpl
       3: dup
       4: aload_0
       5: aload_0
       6: getfield      #8                  // Field codec:Lio/lettuce/core/codec/RedisCodec;
       9: invokespecial #9                  // Method io/lettuce/core/pubsub/RedisPubSubAsyncCommandsImpl."<init>":(Lio/lettuce/core/pubsub/StatefulRedisPubSubConnection;Lio/lettuce/core/codec/RedisCodec;)V
      12: areturn

  public io.lettuce.core.pubsub.api.sync.RedisPubSubCommands<K, V> sync();
    Code:
       0: aload_0
       1: getfield      #10                 // Field sync:Lio/lettuce/core/api/sync/RedisCommands;
       4: checkcast     #11                 // class io/lettuce/core/pubsub/api/sync/RedisPubSubCommands
       7: areturn

  protected io.lettuce.core.pubsub.api.sync.RedisPubSubCommands<K, V> newRedisSyncCommandsImpl();
    Code:
       0: aload_0
       1: aload_0
       2: invokevirtual #12                 // Method async:()Lio/lettuce/core/pubsub/api/async/RedisPubSubAsyncCommands;
       5: iconst_1
       6: anewarray     #13                 // class java/lang/Class
       9: dup
      10: iconst_0
      11: ldc           #11                 // class io/lettuce/core/pubsub/api/sync/RedisPubSubCommands
      13: aastore
      14: invokevirtual #14                 // Method syncHandler:(Ljava/lang/Object;[Ljava/lang/Class;)Ljava/lang/Object;
      17: checkcast     #11                 // class io/lettuce/core/pubsub/api/sync/RedisPubSubCommands
      20: areturn

  public io.lettuce.core.pubsub.api.reactive.RedisPubSubReactiveCommands<K, V> reactive();
    Code:
       0: aload_0
       1: getfield      #15                 // Field reactive:Lio/lettuce/core/RedisReactiveCommandsImpl;
       4: checkcast     #16                 // class io/lettuce/core/pubsub/api/reactive/RedisPubSubReactiveCommands
       7: areturn

  protected io.lettuce.core.pubsub.RedisPubSubReactiveCommandsImpl<K, V> newRedisReactiveCommandsImpl();
    Code:
       0: new           #17                 // class io/lettuce/core/pubsub/RedisPubSubReactiveCommandsImpl
       3: dup
       4: aload_0
       5: aload_0
       6: getfield      #8                  // Field codec:Lio/lettuce/core/codec/RedisCodec;
       9: invokespecial #18                 // Method io/lettuce/core/pubsub/RedisPubSubReactiveCommandsImpl."<init>":(Lio/lettuce/core/pubsub/StatefulRedisPubSubConnection;Lio/lettuce/core/codec/RedisCodec;)V
      12: areturn

  protected java.util.List<io.lettuce.core.RedisFuture<java.lang.Void>> resubscribe();
    Code:
       0: new           #19                 // class java/util/ArrayList
       3: dup
       4: invokespecial #20                 // Method java/util/ArrayList."<init>":()V
       7: astore_1
       8: aload_0
       9: getfield      #2                  // Field endpoint:Lio/lettuce/core/pubsub/PubSubEndpoint;
      12: invokevirtual #21                 // Method io/lettuce/core/pubsub/PubSubEndpoint.getChannels:()Ljava/util/Set;
      15: invokeinterface #22,  1           // InterfaceMethod java/util/Set.isEmpty:()Z
      20: ifne          50
      23: aload_1
      24: aload_0
      25: invokevirtual #12                 // Method async:()Lio/lettuce/core/pubsub/api/async/RedisPubSubAsyncCommands;
      28: aload_0
      29: aload_0
      30: getfield      #2                  // Field endpoint:Lio/lettuce/core/pubsub/PubSubEndpoint;
      33: invokevirtual #21                 // Method io/lettuce/core/pubsub/PubSubEndpoint.getChannels:()Ljava/util/Set;
      36: invokespecial #23                 // Method toArray:(Ljava/util/Collection;)[Ljava/lang/Object;
      39: invokeinterface #24,  2           // InterfaceMethod io/lettuce/core/pubsub/api/async/RedisPubSubAsyncCommands.subscribe:([Ljava/lang/Object;)Lio/lettuce/core/RedisFuture;
      44: invokeinterface #25,  2           // InterfaceMethod java/util/List.add:(Ljava/lang/Object;)Z
      49: pop
      50: aload_0
      51: getfield      #2                  // Field endpoint:Lio/lettuce/core/pubsub/PubSubEndpoint;
      54: invokevirtual #26                 // Method io/lettuce/core/pubsub/PubSubEndpoint.getPatterns:()Ljava/util/Set;
      57: invokeinterface #22,  1           // InterfaceMethod java/util/Set.isEmpty:()Z
      62: ifne          92
      65: aload_1
      66: aload_0
      67: invokevirtual #12                 // Method async:()Lio/lettuce/core/pubsub/api/async/RedisPubSubAsyncCommands;
      70: aload_0
      71: aload_0
      72: getfield      #2                  // Field endpoint:Lio/lettuce/core/pubsub/PubSubEndpoint;
      75: invokevirtual #26                 // Method io/lettuce/core/pubsub/PubSubEndpoint.getPatterns:()Ljava/util/Set;
      78: invokespecial #23                 // Method toArray:(Ljava/util/Collection;)[Ljava/lang/Object;
      81: invokeinterface #27,  2           // InterfaceMethod io/lettuce/core/pubsub/api/async/RedisPubSubAsyncCommands.psubscribe:([Ljava/lang/Object;)Lio/lettuce/core/RedisFuture;
      86: invokeinterface #25,  2           // InterfaceMethod java/util/List.add:(Ljava/lang/Object;)Z
      91: pop
      92: aload_1
      93: areturn

  private <T> T[] toArray(java.util.Collection<T>);
    Code:
       0: aload_1
       1: invokeinterface #28,  1           // InterfaceMethod java/util/Collection.iterator:()Ljava/util/Iterator;
       6: invokeinterface #29,  1           // InterfaceMethod java/util/Iterator.next:()Ljava/lang/Object;
      11: invokevirtual #30                 // Method java/lang/Object.getClass:()Ljava/lang/Class;
      14: astore_2
      15: aload_2
      16: aload_1
      17: invokeinterface #31,  1           // InterfaceMethod java/util/Collection.size:()I
      22: invokestatic  #32                 // Method java/lang/reflect/Array.newInstance:(Ljava/lang/Class;I)Ljava/lang/Object;
      25: checkcast     #33                 // class "[Ljava/lang/Object;"
      28: checkcast     #33                 // class "[Ljava/lang/Object;"
      31: astore_3
      32: aload_1
      33: aload_3
      34: invokeinterface #34,  2           // InterfaceMethod java/util/Collection.toArray:([Ljava/lang/Object;)[Ljava/lang/Object;
      39: areturn

  public void activated();
    Code:
       0: aload_0
       1: invokespecial #35                 // Method io/lettuce/core/StatefulRedisConnectionImpl.activated:()V
       4: aload_0
       5: invokevirtual #36                 // Method resubscribe:()Ljava/util/List;
       8: pop
       9: return

  public io.lettuce.core.api.sync.RedisCommands sync();
    Code:
       0: aload_0
       1: invokevirtual #37                 // Method sync:()Lio/lettuce/core/pubsub/api/sync/RedisPubSubCommands;
       4: areturn

  protected io.lettuce.core.RedisReactiveCommandsImpl newRedisReactiveCommandsImpl();
    Code:
       0: aload_0
       1: invokevirtual #38                 // Method newRedisReactiveCommandsImpl:()Lio/lettuce/core/pubsub/RedisPubSubReactiveCommandsImpl;
       4: areturn

  public io.lettuce.core.api.reactive.RedisReactiveCommands reactive();
    Code:
       0: aload_0
       1: invokevirtual #39                 // Method reactive:()Lio/lettuce/core/pubsub/api/reactive/RedisPubSubReactiveCommands;
       4: areturn

  protected io.lettuce.core.RedisAsyncCommandsImpl newRedisAsyncCommandsImpl();
    Code:
       0: aload_0
       1: invokevirtual #40                 // Method newRedisAsyncCommandsImpl:()Lio/lettuce/core/pubsub/RedisPubSubAsyncCommandsImpl;
       4: areturn

  protected io.lettuce.core.api.sync.RedisCommands newRedisSyncCommandsImpl();
    Code:
       0: aload_0
       1: invokevirtual #41                 // Method newRedisSyncCommandsImpl:()Lio/lettuce/core/pubsub/api/sync/RedisPubSubCommands;
       4: areturn

  public io.lettuce.core.api.async.RedisAsyncCommands async();
    Code:
       0: aload_0
       1: invokevirtual #12                 // Method async:()Lio/lettuce/core/pubsub/api/async/RedisPubSubAsyncCommands;
       4: areturn
}
