Compiled from "Color.java"
class org.openqa.selenium.support.Color$RgbaPctConverter extends org.openqa.selenium.support.Color$RgbPctConverter {
  private static final java.util.regex.Pattern RGBAPCT_PATTERN;

  private org.openqa.selenium.support.Color$RgbaPctConverter();
    Code:
       0: aload_0
       1: aconst_null
       2: invokespecial #2                  // Method org/openqa/selenium/support/Color$RgbPctConverter."<init>":(Lorg/openqa/selenium/support/Color$1;)V
       5: return

  protected java.util.regex.Pattern getPattern();
    Code:
       0: getstatic     #3                  // Field RGBAPCT_PATTERN:Ljava/util/regex/Pattern;
       3: areturn

  org.openqa.selenium.support.Color$RgbaPctConverter(org.openqa.selenium.support.Color$1);
    Code:
       0: aload_0
       1: invokespecial #1                  // Method "<init>":()V
       4: return

  static {};
    Code:
       0: ldc           #4                  // String ^\\s*rgba\\(\\s*(\\d{1,3}|\\d{1,2}\\.\\d+)%\\s*,\\s*(\\d{1,3}|\\d{1,2}\\.\\d+)%\\s*,\\s*(\\d{1,3}|\\d{1,2}\\.\\d+)%\\s*,\\s*(0|1|0\\.\\d+)\\s*\\)\\s*$
       2: invokestatic  #5                  // Method java/util/regex/Pattern.compile:(Ljava/lang/String;)Ljava/util/regex/Pattern;
       5: putstatic     #3                  // Field RGBAPCT_PATTERN:Ljava/util/regex/Pattern;
       8: return
}
