Compiled from "DeserializationConfig.java"
public final class org.codehaus.jackson.map.DeserializationConfig$Feature extends java.lang.Enum<org.codehaus.jackson.map.DeserializationConfig$Feature> implements org.codehaus.jackson.map.MapperConfig$ConfigFeature {
  public static final org.codehaus.jackson.map.DeserializationConfig$Feature USE_ANNOTATIONS;

  public static final org.codehaus.jackson.map.DeserializationConfig$Feature AUTO_DETECT_SETTERS;

  public static final org.codehaus.jackson.map.DeserializationConfig$Feature AUTO_DETECT_CREATORS;

  public static final org.codehaus.jackson.map.DeserializationConfig$Feature AUTO_DETECT_FIELDS;

  public static final org.codehaus.jackson.map.DeserializationConfig$Feature USE_GETTERS_AS_SETTERS;

  public static final org.codehaus.jackson.map.DeserializationConfig$Feature CAN_OVERRIDE_ACCESS_MODIFIERS;

  public static final org.codehaus.jackson.map.DeserializationConfig$Feature USE_BIG_DECIMAL_FOR_FLOATS;

  public static final org.codehaus.jackson.map.DeserializationConfig$Feature USE_BIG_INTEGER_FOR_INTS;

  public static final org.codehaus.jackson.map.DeserializationConfig$Feature USE_JAVA_ARRAY_FOR_JSON_ARRAY;

  public static final org.codehaus.jackson.map.DeserializationConfig$Feature READ_ENUMS_USING_TO_STRING;

  public static final org.codehaus.jackson.map.DeserializationConfig$Feature FAIL_ON_UNKNOWN_PROPERTIES;

  public static final org.codehaus.jackson.map.DeserializationConfig$Feature FAIL_ON_NULL_FOR_PRIMITIVES;

  public static final org.codehaus.jackson.map.DeserializationConfig$Feature FAIL_ON_NUMBERS_FOR_ENUMS;

  public static final org.codehaus.jackson.map.DeserializationConfig$Feature WRAP_EXCEPTIONS;

  public static final org.codehaus.jackson.map.DeserializationConfig$Feature ACCEPT_SINGLE_VALUE_AS_ARRAY;

  public static final org.codehaus.jackson.map.DeserializationConfig$Feature UNWRAP_ROOT_VALUE;

  public static final org.codehaus.jackson.map.DeserializationConfig$Feature ACCEPT_EMPTY_STRING_AS_NULL_OBJECT;

  final boolean _defaultState;

  private static final org.codehaus.jackson.map.DeserializationConfig$Feature[] $VALUES;

  public static org.codehaus.jackson.map.DeserializationConfig$Feature[] values();
    Code:
       0: getstatic     #1                  // Field $VALUES:[Lorg/codehaus/jackson/map/DeserializationConfig$Feature;
       3: invokevirtual #2                  // Method "[Lorg/codehaus/jackson/map/DeserializationConfig$Feature;".clone:()Ljava/lang/Object;
       6: checkcast     #3                  // class "[Lorg/codehaus/jackson/map/DeserializationConfig$Feature;"
       9: areturn

  public static org.codehaus.jackson.map.DeserializationConfig$Feature valueOf(java.lang.String);
    Code:
       0: ldc_w         #4                  // class org/codehaus/jackson/map/DeserializationConfig$Feature
       3: aload_0
       4: invokestatic  #5                  // Method java/lang/Enum.valueOf:(Ljava/lang/Class;Ljava/lang/String;)Ljava/lang/Enum;
       7: checkcast     #4                  // class org/codehaus/jackson/map/DeserializationConfig$Feature
      10: areturn

  private org.codehaus.jackson.map.DeserializationConfig$Feature(boolean);
    Code:
       0: aload_0
       1: aload_1
       2: iload_2
       3: invokespecial #6                  // Method java/lang/Enum."<init>":(Ljava/lang/String;I)V
       6: aload_0
       7: iload_3
       8: putfield      #7                  // Field _defaultState:Z
      11: return

  public boolean enabledByDefault();
    Code:
       0: aload_0
       1: getfield      #7                  // Field _defaultState:Z
       4: ireturn

  public int getMask();
    Code:
       0: iconst_1
       1: aload_0
       2: invokevirtual #8                  // Method ordinal:()I
       5: ishl
       6: ireturn

  static {};
    Code:
       0: new           #4                  // class org/codehaus/jackson/map/DeserializationConfig$Feature
       3: dup
       4: ldc           #9                  // String USE_ANNOTATIONS
       6: iconst_0
       7: iconst_1
       8: invokespecial #10                 // Method "<init>":(Ljava/lang/String;IZ)V
      11: putstatic     #11                 // Field USE_ANNOTATIONS:Lorg/codehaus/jackson/map/DeserializationConfig$Feature;
      14: new           #4                  // class org/codehaus/jackson/map/DeserializationConfig$Feature
      17: dup
      18: ldc           #12                 // String AUTO_DETECT_SETTERS
      20: iconst_1
      21: iconst_1
      22: invokespecial #10                 // Method "<init>":(Ljava/lang/String;IZ)V
      25: putstatic     #13                 // Field AUTO_DETECT_SETTERS:Lorg/codehaus/jackson/map/DeserializationConfig$Feature;
      28: new           #4                  // class org/codehaus/jackson/map/DeserializationConfig$Feature
      31: dup
      32: ldc           #14                 // String AUTO_DETECT_CREATORS
      34: iconst_2
      35: iconst_1
      36: invokespecial #10                 // Method "<init>":(Ljava/lang/String;IZ)V
      39: putstatic     #15                 // Field AUTO_DETECT_CREATORS:Lorg/codehaus/jackson/map/DeserializationConfig$Feature;
      42: new           #4                  // class org/codehaus/jackson/map/DeserializationConfig$Feature
      45: dup
      46: ldc           #16                 // String AUTO_DETECT_FIELDS
      48: iconst_3
      49: iconst_1
      50: invokespecial #10                 // Method "<init>":(Ljava/lang/String;IZ)V
      53: putstatic     #17                 // Field AUTO_DETECT_FIELDS:Lorg/codehaus/jackson/map/DeserializationConfig$Feature;
      56: new           #4                  // class org/codehaus/jackson/map/DeserializationConfig$Feature
      59: dup
      60: ldc           #18                 // String USE_GETTERS_AS_SETTERS
      62: iconst_4
      63: iconst_1
      64: invokespecial #10                 // Method "<init>":(Ljava/lang/String;IZ)V
      67: putstatic     #19                 // Field USE_GETTERS_AS_SETTERS:Lorg/codehaus/jackson/map/DeserializationConfig$Feature;
      70: new           #4                  // class org/codehaus/jackson/map/DeserializationConfig$Feature
      73: dup
      74: ldc           #20                 // String CAN_OVERRIDE_ACCESS_MODIFIERS
      76: iconst_5
      77: iconst_1
      78: invokespecial #10                 // Method "<init>":(Ljava/lang/String;IZ)V
      81: putstatic     #21                 // Field CAN_OVERRIDE_ACCESS_MODIFIERS:Lorg/codehaus/jackson/map/DeserializationConfig$Feature;
      84: new           #4                  // class org/codehaus/jackson/map/DeserializationConfig$Feature
      87: dup
      88: ldc           #22                 // String USE_BIG_DECIMAL_FOR_FLOATS
      90: bipush        6
      92: iconst_0
      93: invokespecial #10                 // Method "<init>":(Ljava/lang/String;IZ)V
      96: putstatic     #23                 // Field USE_BIG_DECIMAL_FOR_FLOATS:Lorg/codehaus/jackson/map/DeserializationConfig$Feature;
      99: new           #4                  // class org/codehaus/jackson/map/DeserializationConfig$Feature
     102: dup
     103: ldc           #24                 // String USE_BIG_INTEGER_FOR_INTS
     105: bipush        7
     107: iconst_0
     108: invokespecial #10                 // Method "<init>":(Ljava/lang/String;IZ)V
     111: putstatic     #25                 // Field USE_BIG_INTEGER_FOR_INTS:Lorg/codehaus/jackson/map/DeserializationConfig$Feature;
     114: new           #4                  // class org/codehaus/jackson/map/DeserializationConfig$Feature
     117: dup
     118: ldc           #26                 // String USE_JAVA_ARRAY_FOR_JSON_ARRAY
     120: bipush        8
     122: iconst_0
     123: invokespecial #10                 // Method "<init>":(Ljava/lang/String;IZ)V
     126: putstatic     #27                 // Field USE_JAVA_ARRAY_FOR_JSON_ARRAY:Lorg/codehaus/jackson/map/DeserializationConfig$Feature;
     129: new           #4                  // class org/codehaus/jackson/map/DeserializationConfig$Feature
     132: dup
     133: ldc           #28                 // String READ_ENUMS_USING_TO_STRING
     135: bipush        9
     137: iconst_0
     138: invokespecial #10                 // Method "<init>":(Ljava/lang/String;IZ)V
     141: putstatic     #29                 // Field READ_ENUMS_USING_TO_STRING:Lorg/codehaus/jackson/map/DeserializationConfig$Feature;
     144: new           #4                  // class org/codehaus/jackson/map/DeserializationConfig$Feature
     147: dup
     148: ldc           #30                 // String FAIL_ON_UNKNOWN_PROPERTIES
     150: bipush        10
     152: iconst_1
     153: invokespecial #10                 // Method "<init>":(Ljava/lang/String;IZ)V
     156: putstatic     #31                 // Field FAIL_ON_UNKNOWN_PROPERTIES:Lorg/codehaus/jackson/map/DeserializationConfig$Feature;
     159: new           #4                  // class org/codehaus/jackson/map/DeserializationConfig$Feature
     162: dup
     163: ldc           #32                 // String FAIL_ON_NULL_FOR_PRIMITIVES
     165: bipush        11
     167: iconst_0
     168: invokespecial #10                 // Method "<init>":(Ljava/lang/String;IZ)V
     171: putstatic     #33                 // Field FAIL_ON_NULL_FOR_PRIMITIVES:Lorg/codehaus/jackson/map/DeserializationConfig$Feature;
     174: new           #4                  // class org/codehaus/jackson/map/DeserializationConfig$Feature
     177: dup
     178: ldc           #34                 // String FAIL_ON_NUMBERS_FOR_ENUMS
     180: bipush        12
     182: iconst_0
     183: invokespecial #10                 // Method "<init>":(Ljava/lang/String;IZ)V
     186: putstatic     #35                 // Field FAIL_ON_NUMBERS_FOR_ENUMS:Lorg/codehaus/jackson/map/DeserializationConfig$Feature;
     189: new           #4                  // class org/codehaus/jackson/map/DeserializationConfig$Feature
     192: dup
     193: ldc           #36                 // String WRAP_EXCEPTIONS
     195: bipush        13
     197: iconst_1
     198: invokespecial #10                 // Method "<init>":(Ljava/lang/String;IZ)V
     201: putstatic     #37                 // Field WRAP_EXCEPTIONS:Lorg/codehaus/jackson/map/DeserializationConfig$Feature;
     204: new           #4                  // class org/codehaus/jackson/map/DeserializationConfig$Feature
     207: dup
     208: ldc           #38                 // String ACCEPT_SINGLE_VALUE_AS_ARRAY
     210: bipush        14
     212: iconst_0
     213: invokespecial #10                 // Method "<init>":(Ljava/lang/String;IZ)V
     216: putstatic     #39                 // Field ACCEPT_SINGLE_VALUE_AS_ARRAY:Lorg/codehaus/jackson/map/DeserializationConfig$Feature;
     219: new           #4                  // class org/codehaus/jackson/map/DeserializationConfig$Feature
     222: dup
     223: ldc           #40                 // String UNWRAP_ROOT_VALUE
     225: bipush        15
     227: iconst_0
     228: invokespecial #10                 // Method "<init>":(Ljava/lang/String;IZ)V
     231: putstatic     #41                 // Field UNWRAP_ROOT_VALUE:Lorg/codehaus/jackson/map/DeserializationConfig$Feature;
     234: new           #4                  // class org/codehaus/jackson/map/DeserializationConfig$Feature
     237: dup
     238: ldc           #42                 // String ACCEPT_EMPTY_STRING_AS_NULL_OBJECT
     240: bipush        16
     242: iconst_0
     243: invokespecial #10                 // Method "<init>":(Ljava/lang/String;IZ)V
     246: putstatic     #43                 // Field ACCEPT_EMPTY_STRING_AS_NULL_OBJECT:Lorg/codehaus/jackson/map/DeserializationConfig$Feature;
     249: bipush        17
     251: anewarray     #4                  // class org/codehaus/jackson/map/DeserializationConfig$Feature
     254: dup
     255: iconst_0
     256: getstatic     #11                 // Field USE_ANNOTATIONS:Lorg/codehaus/jackson/map/DeserializationConfig$Feature;
     259: aastore
     260: dup
     261: iconst_1
     262: getstatic     #13                 // Field AUTO_DETECT_SETTERS:Lorg/codehaus/jackson/map/DeserializationConfig$Feature;
     265: aastore
     266: dup
     267: iconst_2
     268: getstatic     #15                 // Field AUTO_DETECT_CREATORS:Lorg/codehaus/jackson/map/DeserializationConfig$Feature;
     271: aastore
     272: dup
     273: iconst_3
     274: getstatic     #17                 // Field AUTO_DETECT_FIELDS:Lorg/codehaus/jackson/map/DeserializationConfig$Feature;
     277: aastore
     278: dup
     279: iconst_4
     280: getstatic     #19                 // Field USE_GETTERS_AS_SETTERS:Lorg/codehaus/jackson/map/DeserializationConfig$Feature;
     283: aastore
     284: dup
     285: iconst_5
     286: getstatic     #21                 // Field CAN_OVERRIDE_ACCESS_MODIFIERS:Lorg/codehaus/jackson/map/DeserializationConfig$Feature;
     289: aastore
     290: dup
     291: bipush        6
     293: getstatic     #23                 // Field USE_BIG_DECIMAL_FOR_FLOATS:Lorg/codehaus/jackson/map/DeserializationConfig$Feature;
     296: aastore
     297: dup
     298: bipush        7
     300: getstatic     #25                 // Field USE_BIG_INTEGER_FOR_INTS:Lorg/codehaus/jackson/map/DeserializationConfig$Feature;
     303: aastore
     304: dup
     305: bipush        8
     307: getstatic     #27                 // Field USE_JAVA_ARRAY_FOR_JSON_ARRAY:Lorg/codehaus/jackson/map/DeserializationConfig$Feature;
     310: aastore
     311: dup
     312: bipush        9
     314: getstatic     #29                 // Field READ_ENUMS_USING_TO_STRING:Lorg/codehaus/jackson/map/DeserializationConfig$Feature;
     317: aastore
     318: dup
     319: bipush        10
     321: getstatic     #31                 // Field FAIL_ON_UNKNOWN_PROPERTIES:Lorg/codehaus/jackson/map/DeserializationConfig$Feature;
     324: aastore
     325: dup
     326: bipush        11
     328: getstatic     #33                 // Field FAIL_ON_NULL_FOR_PRIMITIVES:Lorg/codehaus/jackson/map/DeserializationConfig$Feature;
     331: aastore
     332: dup
     333: bipush        12
     335: getstatic     #35                 // Field FAIL_ON_NUMBERS_FOR_ENUMS:Lorg/codehaus/jackson/map/DeserializationConfig$Feature;
     338: aastore
     339: dup
     340: bipush        13
     342: getstatic     #37                 // Field WRAP_EXCEPTIONS:Lorg/codehaus/jackson/map/DeserializationConfig$Feature;
     345: aastore
     346: dup
     347: bipush        14
     349: getstatic     #39                 // Field ACCEPT_SINGLE_VALUE_AS_ARRAY:Lorg/codehaus/jackson/map/DeserializationConfig$Feature;
     352: aastore
     353: dup
     354: bipush        15
     356: getstatic     #41                 // Field UNWRAP_ROOT_VALUE:Lorg/codehaus/jackson/map/DeserializationConfig$Feature;
     359: aastore
     360: dup
     361: bipush        16
     363: getstatic     #43                 // Field ACCEPT_EMPTY_STRING_AS_NULL_OBJECT:Lorg/codehaus/jackson/map/DeserializationConfig$Feature;
     366: aastore
     367: putstatic     #1                  // Field $VALUES:[Lorg/codehaus/jackson/map/DeserializationConfig$Feature;
     370: return
}
