Compiled from "PropertyNamingStrategy.java"
public abstract class org.codehaus.jackson.map.PropertyNamingStrategy$PropertyNamingStrategyBase extends org.codehaus.jackson.map.PropertyNamingStrategy {
  public org.codehaus.jackson.map.PropertyNamingStrategy$PropertyNamingStrategyBase();
    Code:
       0: aload_0
       1: invokespecial #1                  // Method org/codehaus/jackson/map/PropertyNamingStrategy."<init>":()V
       4: return

  public java.lang.String nameForField(org.codehaus.jackson.map.MapperConfig<?>, org.codehaus.jackson.map.introspect.AnnotatedField, java.lang.String);
    Code:
       0: aload_0
       1: aload_3
       2: invokevirtual #2                  // Method translate:(Ljava/lang/String;)Ljava/lang/String;
       5: areturn

  public java.lang.String nameForGetterMethod(org.codehaus.jackson.map.MapperConfig<?>, org.codehaus.jackson.map.introspect.AnnotatedMethod, java.lang.String);
    Code:
       0: aload_0
       1: aload_3
       2: invokevirtual #2                  // Method translate:(Ljava/lang/String;)Ljava/lang/String;
       5: areturn

  public java.lang.String nameForSetterMethod(org.codehaus.jackson.map.MapperConfig<?>, org.codehaus.jackson.map.introspect.AnnotatedMethod, java.lang.String);
    Code:
       0: aload_0
       1: aload_3
       2: invokevirtual #2                  // Method translate:(Ljava/lang/String;)Ljava/lang/String;
       5: areturn

  public java.lang.String nameForConstructorParameter(org.codehaus.jackson.map.MapperConfig<?>, org.codehaus.jackson.map.introspect.AnnotatedParameter, java.lang.String);
    Code:
       0: aload_0
       1: aload_3
       2: invokevirtual #2                  // Method translate:(Ljava/lang/String;)Ljava/lang/String;
       5: areturn

  public abstract java.lang.String translate(java.lang.String);
}
