Compiled from "DFSOutputStream.java"
public class org.apache.hadoop.hdfs.DFSOutputStream extends org.apache.hadoop.fs.FSOutputSummer implements org.apache.hadoop.fs.Syncable,org.apache.hadoop.fs.CanSetDropBehind,org.apache.hadoop.fs.StreamCapabilities {
  static final org.slf4j.Logger LOG;

  static final int CREATE_RETRY_COUNT;

  static org.apache.hadoop.crypto.CryptoProtocolVersion[] SUPPORTED_CRYPTO_VERSIONS;

  protected final org.apache.hadoop.hdfs.DFSClient dfsClient;

  protected final org.apache.hadoop.hdfs.util.ByteArrayManager byteArrayManager;

  protected volatile boolean closed;

  protected final java.lang.String src;

  protected final long fileId;

  protected final long blockSize;

  protected final int bytesPerChecksum;

  protected org.apache.hadoop.hdfs.DFSPacket currentPacket;

  protected org.apache.hadoop.hdfs.DataStreamer streamer;

  protected int packetSize;

  protected int chunksPerPacket;

  protected long lastFlushOffset;

  private long initialFileSize;

  private final short blockReplication;

  protected boolean shouldSyncBlock;

  private final java.util.EnumSet<org.apache.hadoop.hdfs.AddBlockFlag> addBlockFlags;

  protected final java.util.concurrent.atomic.AtomicReference<org.apache.hadoop.hdfs.server.datanode.CachingStrategy> cachingStrategy;

  private org.apache.hadoop.fs.FileEncryptionInfo fileEncryptionInfo;

  private int writePacketSize;

  static final boolean $assertionsDisabled;

  protected org.apache.hadoop.hdfs.DFSPacket createPacket(int, int, long, long, boolean) throws java.io.InterruptedIOException;
    Code:
       0: getstatic     #1                  // Field org/apache/hadoop/hdfs/protocol/datatransfer/PacketHeader.PKT_MAX_HEADER_LEN:I
       3: iload_1
       4: iadd
       5: istore        9
       7: aload_0
       8: getfield      #2                  // Field byteArrayManager:Lorg/apache/hadoop/hdfs/util/ByteArrayManager;
      11: iload         9
      13: invokevirtual #3                  // Method org/apache/hadoop/hdfs/util/ByteArrayManager.newByteArray:(I)[B
      16: astore        8
      18: goto          63
      21: astore        10
      23: new           #5                  // class java/io/InterruptedIOException
      26: dup
      27: new           #6                  // class java/lang/StringBuilder
      30: dup
      31: invokespecial #7                  // Method java/lang/StringBuilder."<init>":()V
      34: ldc           #8                  // String seqno=
      36: invokevirtual #9                  // Method java/lang/StringBuilder.append:(Ljava/lang/String;)Ljava/lang/StringBuilder;
      39: lload         5
      41: invokevirtual #10                 // Method java/lang/StringBuilder.append:(J)Ljava/lang/StringBuilder;
      44: invokevirtual #11                 // Method java/lang/StringBuilder.toString:()Ljava/lang/String;
      47: invokespecial #12                 // Method java/io/InterruptedIOException."<init>":(Ljava/lang/String;)V
      50: astore        11
      52: aload         11
      54: aload         10
      56: invokevirtual #13                 // Method java/io/InterruptedIOException.initCause:(Ljava/lang/Throwable;)Ljava/lang/Throwable;
      59: pop
      60: aload         11
      62: athrow
      63: new           #14                 // class org/apache/hadoop/hdfs/DFSPacket
      66: dup
      67: aload         8
      69: iload_2
      70: lload_3
      71: lload         5
      73: aload_0
      74: invokevirtual #15                 // Method getChecksumSize:()I
      77: iload         7
      79: invokespecial #16                 // Method org/apache/hadoop/hdfs/DFSPacket."<init>":([BIJJIZ)V
      82: areturn
    Exception table:
       from    to  target type
           7    18    21   Class java/lang/InterruptedException

  protected void checkClosed() throws java.io.IOException;
    Code:
       0: aload_0
       1: invokevirtual #17                 // Method isClosed:()Z
       4: ifeq          17
       7: aload_0
       8: invokevirtual #18                 // Method getStreamer:()Lorg/apache/hadoop/hdfs/DataStreamer;
      11: invokevirtual #19                 // Method org/apache/hadoop/hdfs/DataStreamer.getLastException:()Lorg/apache/hadoop/hdfs/DataStreamer$LastExceptionInStreamer;
      14: invokevirtual #20                 // Method org/apache/hadoop/hdfs/DataStreamer$LastExceptionInStreamer.throwException4Close:()V
      17: return

  public synchronized org.apache.hadoop.hdfs.protocol.DatanodeInfo[] getPipeline();
    Code:
       0: aload_0
       1: invokevirtual #18                 // Method getStreamer:()Lorg/apache/hadoop/hdfs/DataStreamer;
       4: invokevirtual #21                 // Method org/apache/hadoop/hdfs/DataStreamer.streamerClosed:()Z
       7: ifeq          12
      10: aconst_null
      11: areturn
      12: aload_0
      13: invokevirtual #18                 // Method getStreamer:()Lorg/apache/hadoop/hdfs/DataStreamer;
      16: invokevirtual #22                 // Method org/apache/hadoop/hdfs/DataStreamer.getNodes:()[Lorg/apache/hadoop/hdfs/protocol/DatanodeInfo;
      19: astore_1
      20: aload_1
      21: ifnonnull     26
      24: aconst_null
      25: areturn
      26: aload_1
      27: arraylength
      28: anewarray     #23                 // class org/apache/hadoop/hdfs/protocol/DatanodeInfo
      31: astore_2
      32: aload_1
      33: iconst_0
      34: aload_2
      35: iconst_0
      36: aload_1
      37: arraylength
      38: invokestatic  #24                 // Method java/lang/System.arraycopy:(Ljava/lang/Object;ILjava/lang/Object;II)V
      41: aload_2
      42: areturn

  private static org.apache.hadoop.util.DataChecksum getChecksum4Compute(org.apache.hadoop.util.DataChecksum, org.apache.hadoop.hdfs.protocol.HdfsFileStatus);
    Code:
       0: aload_1
       1: invokestatic  #25                 // Method org/apache/hadoop/hdfs/DataStreamer.isLazyPersist:(Lorg/apache/hadoop/hdfs/protocol/HdfsFileStatus;)Z
       4: ifeq          28
       7: aload_1
       8: invokeinterface #26,  1           // InterfaceMethod org/apache/hadoop/hdfs/protocol/HdfsFileStatus.getReplication:()S
      13: iconst_1
      14: if_icmpne     28
      17: getstatic     #27                 // Field org/apache/hadoop/util/DataChecksum$Type.NULL:Lorg/apache/hadoop/util/DataChecksum$Type;
      20: aload_0
      21: invokevirtual #28                 // Method org/apache/hadoop/util/DataChecksum.getBytesPerChecksum:()I
      24: invokestatic  #29                 // Method org/apache/hadoop/util/DataChecksum.newDataChecksum:(Lorg/apache/hadoop/util/DataChecksum$Type;I)Lorg/apache/hadoop/util/DataChecksum;
      27: areturn
      28: aload_0
      29: areturn

  private org.apache.hadoop.hdfs.DFSOutputStream(org.apache.hadoop.hdfs.DFSClient, java.lang.String, java.util.EnumSet<org.apache.hadoop.fs.CreateFlag>, org.apache.hadoop.util.Progressable, org.apache.hadoop.hdfs.protocol.HdfsFileStatus, org.apache.hadoop.util.DataChecksum);
    Code:
       0: aload_0
       1: aload         6
       3: aload         5
       5: invokestatic  #30                 // Method getChecksum4Compute:(Lorg/apache/hadoop/util/DataChecksum;Lorg/apache/hadoop/hdfs/protocol/HdfsFileStatus;)Lorg/apache/hadoop/util/DataChecksum;
       8: invokespecial #31                 // Method org/apache/hadoop/fs/FSOutputSummer."<init>":(Lorg/apache/hadoop/util/DataChecksum;)V
      11: aload_0
      12: iconst_0
      13: putfield      #32                 // Field closed:Z
      16: aload_0
      17: aconst_null
      18: putfield      #33                 // Field currentPacket:Lorg/apache/hadoop/hdfs/DFSPacket;
      21: aload_0
      22: iconst_0
      23: putfield      #34                 // Field packetSize:I
      26: aload_0
      27: iconst_0
      28: putfield      #35                 // Field chunksPerPacket:I
      31: aload_0
      32: lconst_0
      33: putfield      #36                 // Field lastFlushOffset:J
      36: aload_0
      37: lconst_0
      38: putfield      #37                 // Field initialFileSize:J
      41: aload_0
      42: iconst_0
      43: putfield      #38                 // Field shouldSyncBlock:Z
      46: aload_0
      47: aload_1
      48: putfield      #39                 // Field dfsClient:Lorg/apache/hadoop/hdfs/DFSClient;
      51: aload_0
      52: aload_2
      53: putfield      #40                 // Field src:Ljava/lang/String;
      56: aload_0
      57: aload         5
      59: invokeinterface #41,  1           // InterfaceMethod org/apache/hadoop/hdfs/protocol/HdfsFileStatus.getFileId:()J
      64: putfield      #42                 // Field fileId:J
      67: aload_0
      68: aload         5
      70: invokeinterface #43,  1           // InterfaceMethod org/apache/hadoop/hdfs/protocol/HdfsFileStatus.getBlockSize:()J
      75: putfield      #44                 // Field blockSize:J
      78: aload_0
      79: aload         5
      81: invokeinterface #26,  1           // InterfaceMethod org/apache/hadoop/hdfs/protocol/HdfsFileStatus.getReplication:()S
      86: putfield      #45                 // Field blockReplication:S
      89: aload_0
      90: aload         5
      92: invokeinterface #46,  1           // InterfaceMethod org/apache/hadoop/hdfs/protocol/HdfsFileStatus.getFileEncryptionInfo:()Lorg/apache/hadoop/fs/FileEncryptionInfo;
      97: putfield      #47                 // Field fileEncryptionInfo:Lorg/apache/hadoop/fs/FileEncryptionInfo;
     100: aload_0
     101: new           #48                 // class java/util/concurrent/atomic/AtomicReference
     104: dup
     105: aload_1
     106: invokevirtual #49                 // Method org/apache/hadoop/hdfs/DFSClient.getDefaultWriteCachingStrategy:()Lorg/apache/hadoop/hdfs/server/datanode/CachingStrategy;
     109: invokespecial #50                 // Method java/util/concurrent/atomic/AtomicReference."<init>":(Ljava/lang/Object;)V
     112: putfield      #51                 // Field cachingStrategy:Ljava/util/concurrent/atomic/AtomicReference;
     115: aload_0
     116: ldc           #52                 // class org/apache/hadoop/hdfs/AddBlockFlag
     118: invokestatic  #53                 // Method java/util/EnumSet.noneOf:(Ljava/lang/Class;)Ljava/util/EnumSet;
     121: putfield      #54                 // Field addBlockFlags:Ljava/util/EnumSet;
     124: aload_3
     125: getstatic     #55                 // Field org/apache/hadoop/fs/CreateFlag.NO_LOCAL_WRITE:Lorg/apache/hadoop/fs/CreateFlag;
     128: invokevirtual #56                 // Method java/util/EnumSet.contains:(Ljava/lang/Object;)Z
     131: ifeq          145
     134: aload_0
     135: getfield      #54                 // Field addBlockFlags:Ljava/util/EnumSet;
     138: getstatic     #57                 // Field org/apache/hadoop/hdfs/AddBlockFlag.NO_LOCAL_WRITE:Lorg/apache/hadoop/hdfs/AddBlockFlag;
     141: invokevirtual #58                 // Method java/util/EnumSet.add:(Ljava/lang/Object;)Z
     144: pop
     145: aload_3
     146: getstatic     #59                 // Field org/apache/hadoop/fs/CreateFlag.IGNORE_CLIENT_LOCALITY:Lorg/apache/hadoop/fs/CreateFlag;
     149: invokevirtual #56                 // Method java/util/EnumSet.contains:(Ljava/lang/Object;)Z
     152: ifeq          166
     155: aload_0
     156: getfield      #54                 // Field addBlockFlags:Ljava/util/EnumSet;
     159: getstatic     #60                 // Field org/apache/hadoop/hdfs/AddBlockFlag.IGNORE_CLIENT_LOCALITY:Lorg/apache/hadoop/hdfs/AddBlockFlag;
     162: invokevirtual #58                 // Method java/util/EnumSet.add:(Ljava/lang/Object;)Z
     165: pop
     166: aload         4
     168: ifnull        182
     171: getstatic     #61                 // Field org/apache/hadoop/hdfs/DFSClient.LOG:Lorg/slf4j/Logger;
     174: ldc           #62                 // String Set non-null progress callback on DFSOutputStream {}
     176: aload_2
     177: invokeinterface #63,  3           // InterfaceMethod org/slf4j/Logger.debug:(Ljava/lang/String;Ljava/lang/Object;)V
     182: aload_0
     183: invokespecial #64                 // Method initWritePacketSize:()V
     186: aload_0
     187: aload         6
     189: invokevirtual #28                 // Method org/apache/hadoop/util/DataChecksum.getBytesPerChecksum:()I
     192: putfield      #65                 // Field bytesPerChecksum:I
     195: aload_0
     196: getfield      #65                 // Field bytesPerChecksum:I
     199: ifgt          237
     202: new           #66                 // class org/apache/hadoop/HadoopIllegalArgumentException
     205: dup
     206: new           #6                  // class java/lang/StringBuilder
     209: dup
     210: invokespecial #7                  // Method java/lang/StringBuilder."<init>":()V
     213: ldc           #67                 // String Invalid value: bytesPerChecksum =
     215: invokevirtual #9                  // Method java/lang/StringBuilder.append:(Ljava/lang/String;)Ljava/lang/StringBuilder;
     218: aload_0
     219: getfield      #65                 // Field bytesPerChecksum:I
     222: invokevirtual #68                 // Method java/lang/StringBuilder.append:(I)Ljava/lang/StringBuilder;
     225: ldc           #69                 // String  <= 0
     227: invokevirtual #9                  // Method java/lang/StringBuilder.append:(Ljava/lang/String;)Ljava/lang/StringBuilder;
     230: invokevirtual #11                 // Method java/lang/StringBuilder.toString:()Ljava/lang/String;
     233: invokespecial #70                 // Method org/apache/hadoop/HadoopIllegalArgumentException."<init>":(Ljava/lang/String;)V
     236: athrow
     237: aload_0
     238: getfield      #44                 // Field blockSize:J
     241: aload_0
     242: getfield      #65                 // Field bytesPerChecksum:I
     245: i2l
     246: lrem
     247: lconst_0
     248: lcmp
     249: ifeq          299
     252: new           #66                 // class org/apache/hadoop/HadoopIllegalArgumentException
     255: dup
     256: new           #6                  // class java/lang/StringBuilder
     259: dup
     260: invokespecial #7                  // Method java/lang/StringBuilder."<init>":()V
     263: ldc           #72                 // String Invalid values: dfs.bytes-per-checksum (=
     265: invokevirtual #9                  // Method java/lang/StringBuilder.append:(Ljava/lang/String;)Ljava/lang/StringBuilder;
     268: aload_0
     269: getfield      #65                 // Field bytesPerChecksum:I
     272: invokevirtual #68                 // Method java/lang/StringBuilder.append:(I)Ljava/lang/StringBuilder;
     275: ldc           #73                 // String ) must divide block size (=
     277: invokevirtual #9                  // Method java/lang/StringBuilder.append:(Ljava/lang/String;)Ljava/lang/StringBuilder;
     280: aload_0
     281: getfield      #44                 // Field blockSize:J
     284: invokevirtual #10                 // Method java/lang/StringBuilder.append:(J)Ljava/lang/StringBuilder;
     287: ldc           #74                 // String ).
     289: invokevirtual #9                  // Method java/lang/StringBuilder.append:(Ljava/lang/String;)Ljava/lang/StringBuilder;
     292: invokevirtual #11                 // Method java/lang/StringBuilder.toString:()Ljava/lang/String;
     295: invokespecial #70                 // Method org/apache/hadoop/HadoopIllegalArgumentException."<init>":(Ljava/lang/String;)V
     298: athrow
     299: aload_0
     300: aload_1
     301: invokevirtual #75                 // Method org/apache/hadoop/hdfs/DFSClient.getClientContext:()Lorg/apache/hadoop/hdfs/ClientContext;
     304: invokevirtual #76                 // Method org/apache/hadoop/hdfs/ClientContext.getByteArrayManager:()Lorg/apache/hadoop/hdfs/util/ByteArrayManager;
     307: putfield      #2                  // Field byteArrayManager:Lorg/apache/hadoop/hdfs/util/ByteArrayManager;
     310: return

  private void initWritePacketSize();
    Code:
       0: aload_0
       1: aload_0
       2: getfield      #39                 // Field dfsClient:Lorg/apache/hadoop/hdfs/DFSClient;
       5: invokevirtual #77                 // Method org/apache/hadoop/hdfs/DFSClient.getConf:()Lorg/apache/hadoop/hdfs/client/impl/DfsClientConf;
       8: invokevirtual #78                 // Method org/apache/hadoop/hdfs/client/impl/DfsClientConf.getWritePacketSize:()I
      11: putfield      #79                 // Field writePacketSize:I
      14: aload_0
      15: getfield      #79                 // Field writePacketSize:I
      18: ldc           #81                 // int 16777216
      20: if_icmple     49
      23: getstatic     #82                 // Field LOG:Lorg/slf4j/Logger;
      26: ldc           #83                 // String Configured write packet exceeds {} bytes as max, using {} bytes.
      28: ldc           #81                 // int 16777216
      30: invokestatic  #84                 // Method java/lang/Integer.valueOf:(I)Ljava/lang/Integer;
      33: ldc           #81                 // int 16777216
      35: invokestatic  #84                 // Method java/lang/Integer.valueOf:(I)Ljava/lang/Integer;
      38: invokeinterface #85,  4           // InterfaceMethod org/slf4j/Logger.warn:(Ljava/lang/String;Ljava/lang/Object;Ljava/lang/Object;)V
      43: aload_0
      44: ldc           #81                 // int 16777216
      46: putfield      #79                 // Field writePacketSize:I
      49: return

  protected org.apache.hadoop.hdfs.DFSOutputStream(org.apache.hadoop.hdfs.DFSClient, java.lang.String, org.apache.hadoop.hdfs.protocol.HdfsFileStatus, java.util.EnumSet<org.apache.hadoop.fs.CreateFlag>, org.apache.hadoop.util.Progressable, org.apache.hadoop.util.DataChecksum, java.lang.String[], boolean);
    Code:
       0: aload_0
       1: aload_1
       2: aload_2
       3: aload         4
       5: aload         5
       7: aload_3
       8: aload         6
      10: invokespecial #86                 // Method "<init>":(Lorg/apache/hadoop/hdfs/DFSClient;Ljava/lang/String;Ljava/util/EnumSet;Lorg/apache/hadoop/util/Progressable;Lorg/apache/hadoop/hdfs/protocol/HdfsFileStatus;Lorg/apache/hadoop/util/DataChecksum;)V
      13: aload_0
      14: aload         4
      16: getstatic     #87                 // Field org/apache/hadoop/fs/CreateFlag.SYNC_BLOCK:Lorg/apache/hadoop/fs/CreateFlag;
      19: invokevirtual #56                 // Method java/util/EnumSet.contains:(Ljava/lang/Object;)Z
      22: putfield      #38                 // Field shouldSyncBlock:Z
      25: aload_0
      26: aload_1
      27: invokevirtual #77                 // Method org/apache/hadoop/hdfs/DFSClient.getConf:()Lorg/apache/hadoop/hdfs/client/impl/DfsClientConf;
      30: invokevirtual #78                 // Method org/apache/hadoop/hdfs/client/impl/DfsClientConf.getWritePacketSize:()I
      33: aload_0
      34: getfield      #65                 // Field bytesPerChecksum:I
      37: invokevirtual #88                 // Method computePacketChunkSize:(II)V
      40: iload         8
      42: ifeq          78
      45: aload_0
      46: new           #89                 // class org/apache/hadoop/hdfs/DataStreamer
      49: dup
      50: aload_3
      51: aconst_null
      52: aload_1
      53: aload_2
      54: aload         5
      56: aload         6
      58: aload_0
      59: getfield      #51                 // Field cachingStrategy:Ljava/util/concurrent/atomic/AtomicReference;
      62: aload_0
      63: getfield      #2                  // Field byteArrayManager:Lorg/apache/hadoop/hdfs/util/ByteArrayManager;
      66: aload         7
      68: aload_0
      69: getfield      #54                 // Field addBlockFlags:Ljava/util/EnumSet;
      72: invokespecial #90                 // Method org/apache/hadoop/hdfs/DataStreamer."<init>":(Lorg/apache/hadoop/hdfs/protocol/HdfsFileStatus;Lorg/apache/hadoop/hdfs/protocol/ExtendedBlock;Lorg/apache/hadoop/hdfs/DFSClient;Ljava/lang/String;Lorg/apache/hadoop/util/Progressable;Lorg/apache/hadoop/util/DataChecksum;Ljava/util/concurrent/atomic/AtomicReference;Lorg/apache/hadoop/hdfs/util/ByteArrayManager;[Ljava/lang/String;Ljava/util/EnumSet;)V
      75: putfield      #91                 // Field streamer:Lorg/apache/hadoop/hdfs/DataStreamer;
      78: return

  static org.apache.hadoop.hdfs.DFSOutputStream newStreamForCreate(org.apache.hadoop.hdfs.DFSClient, java.lang.String, org.apache.hadoop.fs.permission.FsPermission, java.util.EnumSet<org.apache.hadoop.fs.CreateFlag>, boolean, short, long, org.apache.hadoop.util.Progressable, org.apache.hadoop.util.DataChecksum, java.lang.String[], java.lang.String) throws java.io.IOException;
    Code:
       0: aload_0
       1: ldc           #92                 // String newStreamForCreate
       3: aload_1
       4: invokevirtual #93                 // Method org/apache/hadoop/hdfs/DFSClient.newPathTraceScope:(Ljava/lang/String;Ljava/lang/String;)Lorg/apache/htrace/core/TraceScope;
       7: astore        12
       9: aconst_null
      10: astore        13
      12: aconst_null
      13: astore        14
      15: iconst_1
      16: istore        15
      18: bipush        10
      20: istore        16
      22: iload         15
      24: ifeq          189
      27: iconst_0
      28: istore        15
      30: aload_0
      31: getfield      #95                 // Field org/apache/hadoop/hdfs/DFSClient.namenode:Lorg/apache/hadoop/hdfs/protocol/ClientProtocol;
      34: aload_1
      35: aload_2
      36: aload_0
      37: getfield      #96                 // Field org/apache/hadoop/hdfs/DFSClient.clientName:Ljava/lang/String;
      40: new           #97                 // class org/apache/hadoop/io/EnumSetWritable
      43: dup
      44: aload_3
      45: invokespecial #98                 // Method org/apache/hadoop/io/EnumSetWritable."<init>":(Ljava/util/EnumSet;)V
      48: iload         4
      50: iload         5
      52: lload         6
      54: getstatic     #99                 // Field SUPPORTED_CRYPTO_VERSIONS:[Lorg/apache/hadoop/crypto/CryptoProtocolVersion;
      57: aload         11
      59: invokeinterface #100,  11         // InterfaceMethod org/apache/hadoop/hdfs/protocol/ClientProtocol.create:(Ljava/lang/String;Lorg/apache/hadoop/fs/permission/FsPermission;Ljava/lang/String;Lorg/apache/hadoop/io/EnumSetWritable;ZSJ[Lorg/apache/hadoop/crypto/CryptoProtocolVersion;Ljava/lang/String;)Lorg/apache/hadoop/hdfs/protocol/HdfsFileStatus;
      64: astore        14
      66: goto          189
      69: astore        17
      71: aload         17
      73: bipush        12
      75: anewarray     #102                // class java/lang/Class
      78: dup
      79: iconst_0
      80: ldc           #103                // class org/apache/hadoop/security/AccessControlException
      82: aastore
      83: dup
      84: iconst_1
      85: ldc           #104                // class org/apache/hadoop/hdfs/protocol/DSQuotaExceededException
      87: aastore
      88: dup
      89: iconst_2
      90: ldc           #105                // class org/apache/hadoop/hdfs/protocol/QuotaByStorageTypeExceededException
      92: aastore
      93: dup
      94: iconst_3
      95: ldc           #106                // class org/apache/hadoop/fs/FileAlreadyExistsException
      97: aastore
      98: dup
      99: iconst_4
     100: ldc           #107                // class java/io/FileNotFoundException
     102: aastore
     103: dup
     104: iconst_5
     105: ldc           #108                // class org/apache/hadoop/fs/ParentNotDirectoryException
     107: aastore
     108: dup
     109: bipush        6
     111: ldc           #109                // class org/apache/hadoop/hdfs/protocol/NSQuotaExceededException
     113: aastore
     114: dup
     115: bipush        7
     117: ldc           #110                // class org/apache/hadoop/hdfs/server/namenode/RetryStartFileException
     119: aastore
     120: dup
     121: bipush        8
     123: ldc           #111                // class org/apache/hadoop/hdfs/server/namenode/SafeModeException
     125: aastore
     126: dup
     127: bipush        9
     129: ldc           #112                // class org/apache/hadoop/hdfs/protocol/UnresolvedPathException
     131: aastore
     132: dup
     133: bipush        10
     135: ldc           #113                // class org/apache/hadoop/hdfs/protocol/SnapshotAccessControlException
     137: aastore
     138: dup
     139: bipush        11
     141: ldc           #114                // class org/apache/hadoop/hdfs/UnknownCryptoProtocolVersionException
     143: aastore
     144: invokevirtual #115                // Method org/apache/hadoop/ipc/RemoteException.unwrapRemoteException:([Ljava/lang/Class;)Ljava/io/IOException;
     147: astore        18
     149: aload         18
     151: instanceof    #110                // class org/apache/hadoop/hdfs/server/namenode/RetryStartFileException
     154: ifeq          183
     157: iload         16
     159: ifle          171
     162: iconst_1
     163: istore        15
     165: iinc          16, -1
     168: goto          186
     171: new           #116                // class java/io/IOException
     174: dup
     175: ldc           #117                // String Too many retries because of encryption zone operations
     177: aload         18
     179: invokespecial #118                // Method java/io/IOException."<init>":(Ljava/lang/String;Ljava/lang/Throwable;)V
     182: athrow
     183: aload         18
     185: athrow
     186: goto          22
     189: aload         14
     191: ldc           #119                // String HdfsFileStatus should not be null!
     193: invokestatic  #120                // Method com/google/common/base/Preconditions.checkNotNull:(Ljava/lang/Object;Ljava/lang/Object;)Ljava/lang/Object;
     196: pop
     197: aload         14
     199: invokeinterface #121,  1          // InterfaceMethod org/apache/hadoop/hdfs/protocol/HdfsFileStatus.getErasureCodingPolicy:()Lorg/apache/hadoop/hdfs/protocol/ErasureCodingPolicy;
     204: ifnull        230
     207: new           #122                // class org/apache/hadoop/hdfs/DFSStripedOutputStream
     210: dup
     211: aload_0
     212: aload_1
     213: aload         14
     215: aload_3
     216: aload         8
     218: aload         9
     220: aload         10
     222: invokespecial #123                // Method org/apache/hadoop/hdfs/DFSStripedOutputStream."<init>":(Lorg/apache/hadoop/hdfs/DFSClient;Ljava/lang/String;Lorg/apache/hadoop/hdfs/protocol/HdfsFileStatus;Ljava/util/EnumSet;Lorg/apache/hadoop/util/Progressable;Lorg/apache/hadoop/util/DataChecksum;[Ljava/lang/String;)V
     225: astore        17
     227: goto          251
     230: new           #94                 // class org/apache/hadoop/hdfs/DFSOutputStream
     233: dup
     234: aload_0
     235: aload_1
     236: aload         14
     238: aload_3
     239: aload         8
     241: aload         9
     243: aload         10
     245: iconst_1
     246: invokespecial #124                // Method "<init>":(Lorg/apache/hadoop/hdfs/DFSClient;Ljava/lang/String;Lorg/apache/hadoop/hdfs/protocol/HdfsFileStatus;Ljava/util/EnumSet;Lorg/apache/hadoop/util/Progressable;Lorg/apache/hadoop/util/DataChecksum;[Ljava/lang/String;Z)V
     249: astore        17
     251: aload         17
     253: invokevirtual #125                // Method start:()V
     256: aload         17
     258: astore        18
     260: aload         12
     262: ifnull        295
     265: aload         13
     267: ifnull        290
     270: aload         12
     272: invokevirtual #126                // Method org/apache/htrace/core/TraceScope.close:()V
     275: goto          295
     278: astore        19
     280: aload         13
     282: aload         19
     284: invokevirtual #128                // Method java/lang/Throwable.addSuppressed:(Ljava/lang/Throwable;)V
     287: goto          295
     290: aload         12
     292: invokevirtual #126                // Method org/apache/htrace/core/TraceScope.close:()V
     295: aload         18
     297: areturn
     298: astore        14
     300: aload         14
     302: astore        13
     304: aload         14
     306: athrow
     307: astore        20
     309: aload         12
     311: ifnull        344
     314: aload         13
     316: ifnull        339
     319: aload         12
     321: invokevirtual #126                // Method org/apache/htrace/core/TraceScope.close:()V
     324: goto          344
     327: astore        21
     329: aload         13
     331: aload         21
     333: invokevirtual #128                // Method java/lang/Throwable.addSuppressed:(Ljava/lang/Throwable;)V
     336: goto          344
     339: aload         12
     341: invokevirtual #126                // Method org/apache/htrace/core/TraceScope.close:()V
     344: aload         20
     346: athrow
    Exception table:
       from    to  target type
          30    66    69   Class org/apache/hadoop/ipc/RemoteException
         270   275   278   Class java/lang/Throwable
          12   260   298   Class java/lang/Throwable
          12   260   307   any
         319   324   327   Class java/lang/Throwable
         298   309   307   any

  private org.apache.hadoop.hdfs.DFSOutputStream(org.apache.hadoop.hdfs.DFSClient, java.lang.String, java.util.EnumSet<org.apache.hadoop.fs.CreateFlag>, org.apache.hadoop.util.Progressable, org.apache.hadoop.hdfs.protocol.LocatedBlock, org.apache.hadoop.hdfs.protocol.HdfsFileStatus, org.apache.hadoop.util.DataChecksum, java.lang.String[]) throws java.io.IOException;
    Code:
       0: aload_0
       1: aload_1
       2: aload_2
       3: aload_3
       4: aload         4
       6: aload         6
       8: aload         7
      10: invokespecial #86                 // Method "<init>":(Lorg/apache/hadoop/hdfs/DFSClient;Ljava/lang/String;Ljava/util/EnumSet;Lorg/apache/hadoop/util/Progressable;Lorg/apache/hadoop/hdfs/protocol/HdfsFileStatus;Lorg/apache/hadoop/util/DataChecksum;)V
      13: aload_0
      14: aload         6
      16: invokeinterface #129,  1          // InterfaceMethod org/apache/hadoop/hdfs/protocol/HdfsFileStatus.getLen:()J
      21: putfield      #37                 // Field initialFileSize:J
      24: aload_0
      25: aload_3
      26: getstatic     #87                 // Field org/apache/hadoop/fs/CreateFlag.SYNC_BLOCK:Lorg/apache/hadoop/fs/CreateFlag;
      29: invokevirtual #56                 // Method java/util/EnumSet.contains:(Ljava/lang/Object;)Z
      32: putfield      #38                 // Field shouldSyncBlock:Z
      35: aload_3
      36: getstatic     #130                // Field org/apache/hadoop/fs/CreateFlag.NEW_BLOCK:Lorg/apache/hadoop/fs/CreateFlag;
      39: invokevirtual #56                 // Method java/util/EnumSet.contains:(Ljava/lang/Object;)Z
      42: istore        9
      44: aload_0
      45: aload         6
      47: invokeinterface #46,  1           // InterfaceMethod org/apache/hadoop/hdfs/protocol/HdfsFileStatus.getFileEncryptionInfo:()Lorg/apache/hadoop/fs/FileEncryptionInfo;
      52: putfield      #47                 // Field fileEncryptionInfo:Lorg/apache/hadoop/fs/FileEncryptionInfo;
      55: iload         9
      57: ifne          124
      60: aload         5
      62: ifnull        124
      65: aload_0
      66: new           #89                 // class org/apache/hadoop/hdfs/DataStreamer
      69: dup
      70: aload         5
      72: aload         6
      74: aload_1
      75: aload_2
      76: aload         4
      78: aload         7
      80: aload_0
      81: getfield      #51                 // Field cachingStrategy:Ljava/util/concurrent/atomic/AtomicReference;
      84: aload_0
      85: getfield      #2                  // Field byteArrayManager:Lorg/apache/hadoop/hdfs/util/ByteArrayManager;
      88: invokespecial #131                // Method org/apache/hadoop/hdfs/DataStreamer."<init>":(Lorg/apache/hadoop/hdfs/protocol/LocatedBlock;Lorg/apache/hadoop/hdfs/protocol/HdfsFileStatus;Lorg/apache/hadoop/hdfs/DFSClient;Ljava/lang/String;Lorg/apache/hadoop/util/Progressable;Lorg/apache/hadoop/util/DataChecksum;Ljava/util/concurrent/atomic/AtomicReference;Lorg/apache/hadoop/hdfs/util/ByteArrayManager;)V
      91: putfield      #91                 // Field streamer:Lorg/apache/hadoop/hdfs/DataStreamer;
      94: aload_0
      95: invokevirtual #18                 // Method getStreamer:()Lorg/apache/hadoop/hdfs/DataStreamer;
      98: aload         5
     100: invokevirtual #132                // Method org/apache/hadoop/hdfs/protocol/LocatedBlock.getBlockSize:()J
     103: invokevirtual #133                // Method org/apache/hadoop/hdfs/DataStreamer.setBytesCurBlock:(J)V
     106: aload_0
     107: aload         6
     109: invokespecial #134                // Method adjustPacketChunkSize:(Lorg/apache/hadoop/hdfs/protocol/HdfsFileStatus;)V
     112: aload_0
     113: invokevirtual #18                 // Method getStreamer:()Lorg/apache/hadoop/hdfs/DataStreamer;
     116: aload         5
     118: invokevirtual #135                // Method org/apache/hadoop/hdfs/DataStreamer.setPipelineInConstruction:(Lorg/apache/hadoop/hdfs/protocol/LocatedBlock;)V
     121: goto          186
     124: aload_0
     125: aload_1
     126: invokevirtual #77                 // Method org/apache/hadoop/hdfs/DFSClient.getConf:()Lorg/apache/hadoop/hdfs/client/impl/DfsClientConf;
     129: invokevirtual #78                 // Method org/apache/hadoop/hdfs/client/impl/DfsClientConf.getWritePacketSize:()I
     132: aload_0
     133: getfield      #65                 // Field bytesPerChecksum:I
     136: invokevirtual #88                 // Method computePacketChunkSize:(II)V
     139: aload_0
     140: new           #89                 // class org/apache/hadoop/hdfs/DataStreamer
     143: dup
     144: aload         6
     146: aload         5
     148: ifnull        159
     151: aload         5
     153: invokevirtual #136                // Method org/apache/hadoop/hdfs/protocol/LocatedBlock.getBlock:()Lorg/apache/hadoop/hdfs/protocol/ExtendedBlock;
     156: goto          160
     159: aconst_null
     160: aload_1
     161: aload_2
     162: aload         4
     164: aload         7
     166: aload_0
     167: getfield      #51                 // Field cachingStrategy:Ljava/util/concurrent/atomic/AtomicReference;
     170: aload_0
     171: getfield      #2                  // Field byteArrayManager:Lorg/apache/hadoop/hdfs/util/ByteArrayManager;
     174: aload         8
     176: aload_0
     177: getfield      #54                 // Field addBlockFlags:Ljava/util/EnumSet;
     180: invokespecial #90                 // Method org/apache/hadoop/hdfs/DataStreamer."<init>":(Lorg/apache/hadoop/hdfs/protocol/HdfsFileStatus;Lorg/apache/hadoop/hdfs/protocol/ExtendedBlock;Lorg/apache/hadoop/hdfs/DFSClient;Ljava/lang/String;Lorg/apache/hadoop/util/Progressable;Lorg/apache/hadoop/util/DataChecksum;Ljava/util/concurrent/atomic/AtomicReference;Lorg/apache/hadoop/hdfs/util/ByteArrayManager;[Ljava/lang/String;Ljava/util/EnumSet;)V
     183: putfield      #91                 // Field streamer:Lorg/apache/hadoop/hdfs/DataStreamer;
     186: return

  private void adjustPacketChunkSize(org.apache.hadoop.hdfs.protocol.HdfsFileStatus) throws java.io.IOException;
    Code:
       0: aload_1
       1: invokeinterface #129,  1          // InterfaceMethod org/apache/hadoop/hdfs/protocol/HdfsFileStatus.getLen:()J
       6: aload_0
       7: getfield      #44                 // Field blockSize:J
      10: lrem
      11: lstore_2
      12: aload_0
      13: getfield      #44                 // Field blockSize:J
      16: lload_2
      17: lsub
      18: l2i
      19: istore        4
      21: aload_1
      22: invokeinterface #129,  1          // InterfaceMethod org/apache/hadoop/hdfs/protocol/HdfsFileStatus.getLen:()J
      27: aload_0
      28: getfield      #65                 // Field bytesPerChecksum:I
      31: i2l
      32: lrem
      33: l2i
      34: istore        5
      36: aload_0
      37: getfield      #65                 // Field bytesPerChecksum:I
      40: iload         5
      42: isub
      43: istore        6
      45: iload         4
      47: i2l
      48: aload_0
      49: getfield      #44                 // Field blockSize:J
      52: lcmp
      53: ifne          91
      56: new           #116                // class java/io/IOException
      59: dup
      60: new           #6                  // class java/lang/StringBuilder
      63: dup
      64: invokespecial #7                  // Method java/lang/StringBuilder."<init>":()V
      67: ldc           #137                // String The last block for file
      69: invokevirtual #9                  // Method java/lang/StringBuilder.append:(Ljava/lang/String;)Ljava/lang/StringBuilder;
      72: aload_0
      73: getfield      #40                 // Field src:Ljava/lang/String;
      76: invokevirtual #9                  // Method java/lang/StringBuilder.append:(Ljava/lang/String;)Ljava/lang/StringBuilder;
      79: ldc           #138                // String  is full.
      81: invokevirtual #9                  // Method java/lang/StringBuilder.append:(Ljava/lang/String;)Ljava/lang/StringBuilder;
      84: invokevirtual #11                 // Method java/lang/StringBuilder.toString:()Ljava/lang/String;
      87: invokespecial #139                // Method java/io/IOException."<init>":(Ljava/lang/String;)V
      90: athrow
      91: iload         5
      93: ifle          125
      96: iload         6
      98: ifle          125
     101: aload_0
     102: iconst_0
     103: iload         6
     105: invokevirtual #88                 // Method computePacketChunkSize:(II)V
     108: aload_0
     109: iload         6
     111: invokevirtual #140                // Method setChecksumBufSize:(I)V
     114: aload_0
     115: invokevirtual #18                 // Method getStreamer:()Lorg/apache/hadoop/hdfs/DataStreamer;
     118: iconst_1
     119: invokevirtual #141                // Method org/apache/hadoop/hdfs/DataStreamer.setAppendChunk:(Z)V
     122: goto          148
     125: aload_0
     126: aload_0
     127: getfield      #39                 // Field dfsClient:Lorg/apache/hadoop/hdfs/DFSClient;
     130: invokevirtual #77                 // Method org/apache/hadoop/hdfs/DFSClient.getConf:()Lorg/apache/hadoop/hdfs/client/impl/DfsClientConf;
     133: invokevirtual #78                 // Method org/apache/hadoop/hdfs/client/impl/DfsClientConf.getWritePacketSize:()I
     136: iload         4
     138: invokestatic  #142                // Method java/lang/Math.min:(II)I
     141: aload_0
     142: getfield      #65                 // Field bytesPerChecksum:I
     145: invokevirtual #88                 // Method computePacketChunkSize:(II)V
     148: return

  static org.apache.hadoop.hdfs.DFSOutputStream newStreamForAppend(org.apache.hadoop.hdfs.DFSClient, java.lang.String, java.util.EnumSet<org.apache.hadoop.fs.CreateFlag>, org.apache.hadoop.util.Progressable, org.apache.hadoop.hdfs.protocol.LocatedBlock, org.apache.hadoop.hdfs.protocol.HdfsFileStatus, org.apache.hadoop.util.DataChecksum, java.lang.String[]) throws java.io.IOException;
    Code:
       0: aload         5
       2: invokeinterface #121,  1          // InterfaceMethod org/apache/hadoop/hdfs/protocol/HdfsFileStatus.getErasureCodingPolicy:()Lorg/apache/hadoop/hdfs/protocol/ErasureCodingPolicy;
       7: ifnull        20
      10: new           #116                // class java/io/IOException
      13: dup
      14: ldc           #143                // String Not support appending to a striping layout file yet.
      16: invokespecial #139                // Method java/io/IOException."<init>":(Ljava/lang/String;)V
      19: athrow
      20: aload_0
      21: ldc           #144                // String newStreamForAppend
      23: aload_1
      24: invokevirtual #93                 // Method org/apache/hadoop/hdfs/DFSClient.newPathTraceScope:(Ljava/lang/String;Ljava/lang/String;)Lorg/apache/htrace/core/TraceScope;
      27: astore        8
      29: aconst_null
      30: astore        9
      32: new           #94                 // class org/apache/hadoop/hdfs/DFSOutputStream
      35: dup
      36: aload_0
      37: aload_1
      38: aload_2
      39: aload_3
      40: aload         4
      42: aload         5
      44: aload         6
      46: aload         7
      48: invokespecial #145                // Method "<init>":(Lorg/apache/hadoop/hdfs/DFSClient;Ljava/lang/String;Ljava/util/EnumSet;Lorg/apache/hadoop/util/Progressable;Lorg/apache/hadoop/hdfs/protocol/LocatedBlock;Lorg/apache/hadoop/hdfs/protocol/HdfsFileStatus;Lorg/apache/hadoop/util/DataChecksum;[Ljava/lang/String;)V
      51: astore        10
      53: aload         10
      55: invokevirtual #125                // Method start:()V
      58: aload         10
      60: astore        11
      62: aload         8
      64: ifnull        97
      67: aload         9
      69: ifnull        92
      72: aload         8
      74: invokevirtual #126                // Method org/apache/htrace/core/TraceScope.close:()V
      77: goto          97
      80: astore        12
      82: aload         9
      84: aload         12
      86: invokevirtual #128                // Method java/lang/Throwable.addSuppressed:(Ljava/lang/Throwable;)V
      89: goto          97
      92: aload         8
      94: invokevirtual #126                // Method org/apache/htrace/core/TraceScope.close:()V
      97: aload         11
      99: areturn
     100: astore        10
     102: aload         10
     104: astore        9
     106: aload         10
     108: athrow
     109: astore        13
     111: aload         8
     113: ifnull        146
     116: aload         9
     118: ifnull        141
     121: aload         8
     123: invokevirtual #126                // Method org/apache/htrace/core/TraceScope.close:()V
     126: goto          146
     129: astore        14
     131: aload         9
     133: aload         14
     135: invokevirtual #128                // Method java/lang/Throwable.addSuppressed:(Ljava/lang/Throwable;)V
     138: goto          146
     141: aload         8
     143: invokevirtual #126                // Method org/apache/htrace/core/TraceScope.close:()V
     146: aload         13
     148: athrow
    Exception table:
       from    to  target type
          72    77    80   Class java/lang/Throwable
          32    62   100   Class java/lang/Throwable
          32    62   109   any
         121   126   129   Class java/lang/Throwable
         100   111   109   any

  protected void computePacketChunkSize(int, int);
    Code:
       0: iload_1
       1: getstatic     #1                  // Field org/apache/hadoop/hdfs/protocol/datatransfer/PacketHeader.PKT_MAX_HEADER_LEN:I
       4: isub
       5: istore_3
       6: iload_2
       7: aload_0
       8: invokevirtual #15                 // Method getChecksumSize:()I
      11: iadd
      12: istore        4
      14: aload_0
      15: iload_3
      16: iload         4
      18: idiv
      19: iconst_1
      20: invokestatic  #146                // Method java/lang/Math.max:(II)I
      23: putfield      #35                 // Field chunksPerPacket:I
      26: aload_0
      27: iload         4
      29: aload_0
      30: getfield      #35                 // Field chunksPerPacket:I
      33: imul
      34: putfield      #34                 // Field packetSize:I
      37: getstatic     #61                 // Field org/apache/hadoop/hdfs/DFSClient.LOG:Lorg/slf4j/Logger;
      40: ldc           #147                // String computePacketChunkSize: src={}, chunkSize={}, chunksPerPacket={}, packetSize={}
      42: iconst_4
      43: anewarray     #148                // class java/lang/Object
      46: dup
      47: iconst_0
      48: aload_0
      49: getfield      #40                 // Field src:Ljava/lang/String;
      52: aastore
      53: dup
      54: iconst_1
      55: iload         4
      57: invokestatic  #84                 // Method java/lang/Integer.valueOf:(I)Ljava/lang/Integer;
      60: aastore
      61: dup
      62: iconst_2
      63: aload_0
      64: getfield      #35                 // Field chunksPerPacket:I
      67: invokestatic  #84                 // Method java/lang/Integer.valueOf:(I)Ljava/lang/Integer;
      70: aastore
      71: dup
      72: iconst_3
      73: aload_0
      74: getfield      #34                 // Field packetSize:I
      77: invokestatic  #84                 // Method java/lang/Integer.valueOf:(I)Ljava/lang/Integer;
      80: aastore
      81: invokeinterface #149,  3          // InterfaceMethod org/slf4j/Logger.debug:(Ljava/lang/String;[Ljava/lang/Object;)V
      86: return

  protected org.apache.htrace.core.TraceScope createWriteTraceScope();
    Code:
       0: aload_0
       1: getfield      #39                 // Field dfsClient:Lorg/apache/hadoop/hdfs/DFSClient;
       4: ldc           #150                // String DFSOutputStream#write
       6: aload_0
       7: getfield      #40                 // Field src:Ljava/lang/String;
      10: invokevirtual #93                 // Method org/apache/hadoop/hdfs/DFSClient.newPathTraceScope:(Ljava/lang/String;Ljava/lang/String;)Lorg/apache/htrace/core/TraceScope;
      13: areturn

  protected synchronized void writeChunk(byte[], int, int, byte[], int, int) throws java.io.IOException;
    Code:
       0: aload_0
       1: iload_3
       2: iload         5
       4: iload         6
       6: invokespecial #151                // Method writeChunkPrepare:(III)V
       9: aload_0
      10: getfield      #33                 // Field currentPacket:Lorg/apache/hadoop/hdfs/DFSPacket;
      13: aload         4
      15: iload         5
      17: iload         6
      19: invokevirtual #152                // Method org/apache/hadoop/hdfs/DFSPacket.writeChecksum:([BII)V
      22: aload_0
      23: getfield      #33                 // Field currentPacket:Lorg/apache/hadoop/hdfs/DFSPacket;
      26: aload_1
      27: iload_2
      28: iload_3
      29: invokevirtual #153                // Method org/apache/hadoop/hdfs/DFSPacket.writeData:([BII)V
      32: aload_0
      33: getfield      #33                 // Field currentPacket:Lorg/apache/hadoop/hdfs/DFSPacket;
      36: invokevirtual #154                // Method org/apache/hadoop/hdfs/DFSPacket.incNumChunks:()V
      39: aload_0
      40: invokevirtual #18                 // Method getStreamer:()Lorg/apache/hadoop/hdfs/DataStreamer;
      43: iload_3
      44: i2l
      45: invokevirtual #155                // Method org/apache/hadoop/hdfs/DataStreamer.incBytesCurBlock:(J)V
      48: aload_0
      49: getfield      #33                 // Field currentPacket:Lorg/apache/hadoop/hdfs/DFSPacket;
      52: invokevirtual #156                // Method org/apache/hadoop/hdfs/DFSPacket.getNumChunks:()I
      55: aload_0
      56: getfield      #33                 // Field currentPacket:Lorg/apache/hadoop/hdfs/DFSPacket;
      59: invokevirtual #157                // Method org/apache/hadoop/hdfs/DFSPacket.getMaxChunks:()I
      62: if_icmpeq     80
      65: aload_0
      66: invokevirtual #18                 // Method getStreamer:()Lorg/apache/hadoop/hdfs/DataStreamer;
      69: invokevirtual #158                // Method org/apache/hadoop/hdfs/DataStreamer.getBytesCurBlock:()J
      72: aload_0
      73: getfield      #44                 // Field blockSize:J
      76: lcmp
      77: ifne          84
      80: aload_0
      81: invokevirtual #159                // Method enqueueCurrentPacketFull:()V
      84: return

  protected synchronized void writeChunk(java.nio.ByteBuffer, int, byte[], int, int) throws java.io.IOException;
    Code:
       0: aload_0
       1: iload_2
       2: iload         4
       4: iload         5
       6: invokespecial #151                // Method writeChunkPrepare:(III)V
       9: aload_0
      10: getfield      #33                 // Field currentPacket:Lorg/apache/hadoop/hdfs/DFSPacket;
      13: aload_3
      14: iload         4
      16: iload         5
      18: invokevirtual #152                // Method org/apache/hadoop/hdfs/DFSPacket.writeChecksum:([BII)V
      21: aload_0
      22: getfield      #33                 // Field currentPacket:Lorg/apache/hadoop/hdfs/DFSPacket;
      25: aload_1
      26: iload_2
      27: invokevirtual #160                // Method org/apache/hadoop/hdfs/DFSPacket.writeData:(Ljava/nio/ByteBuffer;I)V
      30: aload_0
      31: getfield      #33                 // Field currentPacket:Lorg/apache/hadoop/hdfs/DFSPacket;
      34: invokevirtual #154                // Method org/apache/hadoop/hdfs/DFSPacket.incNumChunks:()V
      37: aload_0
      38: invokevirtual #18                 // Method getStreamer:()Lorg/apache/hadoop/hdfs/DataStreamer;
      41: iload_2
      42: i2l
      43: invokevirtual #155                // Method org/apache/hadoop/hdfs/DataStreamer.incBytesCurBlock:(J)V
      46: aload_0
      47: getfield      #33                 // Field currentPacket:Lorg/apache/hadoop/hdfs/DFSPacket;
      50: invokevirtual #156                // Method org/apache/hadoop/hdfs/DFSPacket.getNumChunks:()I
      53: aload_0
      54: getfield      #33                 // Field currentPacket:Lorg/apache/hadoop/hdfs/DFSPacket;
      57: invokevirtual #157                // Method org/apache/hadoop/hdfs/DFSPacket.getMaxChunks:()I
      60: if_icmpeq     78
      63: aload_0
      64: invokevirtual #18                 // Method getStreamer:()Lorg/apache/hadoop/hdfs/DataStreamer;
      67: invokevirtual #158                // Method org/apache/hadoop/hdfs/DataStreamer.getBytesCurBlock:()J
      70: aload_0
      71: getfield      #44                 // Field blockSize:J
      74: lcmp
      75: ifne          82
      78: aload_0
      79: invokevirtual #159                // Method enqueueCurrentPacketFull:()V
      82: return

  private synchronized void writeChunkPrepare(int, int, int) throws java.io.IOException;
    Code:
       0: aload_0
       1: getfield      #39                 // Field dfsClient:Lorg/apache/hadoop/hdfs/DFSClient;
       4: invokevirtual #161                // Method org/apache/hadoop/hdfs/DFSClient.checkOpen:()V
       7: aload_0
       8: invokevirtual #162                // Method checkClosed:()V
      11: iload_1
      12: aload_0
      13: getfield      #65                 // Field bytesPerChecksum:I
      16: if_icmple     58
      19: new           #116                // class java/io/IOException
      22: dup
      23: new           #6                  // class java/lang/StringBuilder
      26: dup
      27: invokespecial #7                  // Method java/lang/StringBuilder."<init>":()V
      30: ldc           #163                // String writeChunk() buffer size is
      32: invokevirtual #9                  // Method java/lang/StringBuilder.append:(Ljava/lang/String;)Ljava/lang/StringBuilder;
      35: iload_1
      36: invokevirtual #68                 // Method java/lang/StringBuilder.append:(I)Ljava/lang/StringBuilder;
      39: ldc           #164                // String  is larger than supported  bytesPerChecksum
      41: invokevirtual #9                  // Method java/lang/StringBuilder.append:(Ljava/lang/String;)Ljava/lang/StringBuilder;
      44: aload_0
      45: getfield      #65                 // Field bytesPerChecksum:I
      48: invokevirtual #68                 // Method java/lang/StringBuilder.append:(I)Ljava/lang/StringBuilder;
      51: invokevirtual #11                 // Method java/lang/StringBuilder.toString:()Ljava/lang/String;
      54: invokespecial #139                // Method java/io/IOException."<init>":(Ljava/lang/String;)V
      57: athrow
      58: iload_3
      59: ifeq          109
      62: iload_3
      63: aload_0
      64: invokevirtual #15                 // Method getChecksumSize:()I
      67: if_icmpeq     109
      70: new           #116                // class java/io/IOException
      73: dup
      74: new           #6                  // class java/lang/StringBuilder
      77: dup
      78: invokespecial #7                  // Method java/lang/StringBuilder."<init>":()V
      81: ldc           #165                // String writeChunk() checksum size is supposed to be
      83: invokevirtual #9                  // Method java/lang/StringBuilder.append:(Ljava/lang/String;)Ljava/lang/StringBuilder;
      86: aload_0
      87: invokevirtual #15                 // Method getChecksumSize:()I
      90: invokevirtual #68                 // Method java/lang/StringBuilder.append:(I)Ljava/lang/StringBuilder;
      93: ldc           #166                // String  but found to be
      95: invokevirtual #9                  // Method java/lang/StringBuilder.append:(Ljava/lang/String;)Ljava/lang/StringBuilder;
      98: iload_3
      99: invokevirtual #68                 // Method java/lang/StringBuilder.append:(I)Ljava/lang/StringBuilder;
     102: invokevirtual #11                 // Method java/lang/StringBuilder.toString:()Ljava/lang/String;
     105: invokespecial #139                // Method java/io/IOException."<init>":(Ljava/lang/String;)V
     108: athrow
     109: aload_0
     110: getfield      #33                 // Field currentPacket:Lorg/apache/hadoop/hdfs/DFSPacket;
     113: ifnonnull     219
     116: aload_0
     117: aload_0
     118: aload_0
     119: getfield      #34                 // Field packetSize:I
     122: aload_0
     123: getfield      #35                 // Field chunksPerPacket:I
     126: aload_0
     127: invokevirtual #18                 // Method getStreamer:()Lorg/apache/hadoop/hdfs/DataStreamer;
     130: invokevirtual #158                // Method org/apache/hadoop/hdfs/DataStreamer.getBytesCurBlock:()J
     133: aload_0
     134: invokevirtual #18                 // Method getStreamer:()Lorg/apache/hadoop/hdfs/DataStreamer;
     137: invokevirtual #167                // Method org/apache/hadoop/hdfs/DataStreamer.getAndIncCurrentSeqno:()J
     140: iconst_0
     141: invokevirtual #168                // Method createPacket:(IIJJZ)Lorg/apache/hadoop/hdfs/DFSPacket;
     144: putfield      #33                 // Field currentPacket:Lorg/apache/hadoop/hdfs/DFSPacket;
     147: getstatic     #61                 // Field org/apache/hadoop/hdfs/DFSClient.LOG:Lorg/slf4j/Logger;
     150: ldc           #169                // String WriteChunk allocating new packet seqno={}, src={}, packetSize={}, chunksPerPacket={}, bytesCurBlock={}, output stream={}
     152: bipush        6
     154: anewarray     #148                // class java/lang/Object
     157: dup
     158: iconst_0
     159: aload_0
     160: getfield      #33                 // Field currentPacket:Lorg/apache/hadoop/hdfs/DFSPacket;
     163: invokevirtual #170                // Method org/apache/hadoop/hdfs/DFSPacket.getSeqno:()J
     166: invokestatic  #171                // Method java/lang/Long.valueOf:(J)Ljava/lang/Long;
     169: aastore
     170: dup
     171: iconst_1
     172: aload_0
     173: getfield      #40                 // Field src:Ljava/lang/String;
     176: aastore
     177: dup
     178: iconst_2
     179: aload_0
     180: getfield      #34                 // Field packetSize:I
     183: invokestatic  #84                 // Method java/lang/Integer.valueOf:(I)Ljava/lang/Integer;
     186: aastore
     187: dup
     188: iconst_3
     189: aload_0
     190: getfield      #35                 // Field chunksPerPacket:I
     193: invokestatic  #84                 // Method java/lang/Integer.valueOf:(I)Ljava/lang/Integer;
     196: aastore
     197: dup
     198: iconst_4
     199: aload_0
     200: invokevirtual #18                 // Method getStreamer:()Lorg/apache/hadoop/hdfs/DataStreamer;
     203: invokevirtual #158                // Method org/apache/hadoop/hdfs/DataStreamer.getBytesCurBlock:()J
     206: invokestatic  #171                // Method java/lang/Long.valueOf:(J)Ljava/lang/Long;
     209: aastore
     210: dup
     211: iconst_5
     212: aload_0
     213: aastore
     214: invokeinterface #149,  3          // InterfaceMethod org/slf4j/Logger.debug:(Ljava/lang/String;[Ljava/lang/Object;)V
     219: return

  void enqueueCurrentPacket() throws java.io.IOException;
    Code:
       0: aload_0
       1: invokevirtual #18                 // Method getStreamer:()Lorg/apache/hadoop/hdfs/DataStreamer;
       4: aload_0
       5: getfield      #33                 // Field currentPacket:Lorg/apache/hadoop/hdfs/DFSPacket;
       8: invokevirtual #172                // Method org/apache/hadoop/hdfs/DataStreamer.waitAndQueuePacket:(Lorg/apache/hadoop/hdfs/DFSPacket;)V
      11: aload_0
      12: aconst_null
      13: putfield      #33                 // Field currentPacket:Lorg/apache/hadoop/hdfs/DFSPacket;
      16: return

  synchronized void enqueueCurrentPacketFull() throws java.io.IOException;
    Code:
       0: getstatic     #82                 // Field LOG:Lorg/slf4j/Logger;
       3: ldc           #173                // String enqueue full {}, src={}, bytesCurBlock={}, blockSize={}, appendChunk={}, {}
       5: bipush        6
       7: anewarray     #148                // class java/lang/Object
      10: dup
      11: iconst_0
      12: aload_0
      13: getfield      #33                 // Field currentPacket:Lorg/apache/hadoop/hdfs/DFSPacket;
      16: aastore
      17: dup
      18: iconst_1
      19: aload_0
      20: getfield      #40                 // Field src:Ljava/lang/String;
      23: aastore
      24: dup
      25: iconst_2
      26: aload_0
      27: invokevirtual #18                 // Method getStreamer:()Lorg/apache/hadoop/hdfs/DataStreamer;
      30: invokevirtual #158                // Method org/apache/hadoop/hdfs/DataStreamer.getBytesCurBlock:()J
      33: invokestatic  #171                // Method java/lang/Long.valueOf:(J)Ljava/lang/Long;
      36: aastore
      37: dup
      38: iconst_3
      39: aload_0
      40: getfield      #44                 // Field blockSize:J
      43: invokestatic  #171                // Method java/lang/Long.valueOf:(J)Ljava/lang/Long;
      46: aastore
      47: dup
      48: iconst_4
      49: aload_0
      50: invokevirtual #18                 // Method getStreamer:()Lorg/apache/hadoop/hdfs/DataStreamer;
      53: invokevirtual #174                // Method org/apache/hadoop/hdfs/DataStreamer.getAppendChunk:()Z
      56: invokestatic  #175                // Method java/lang/Boolean.valueOf:(Z)Ljava/lang/Boolean;
      59: aastore
      60: dup
      61: iconst_5
      62: aload_0
      63: invokevirtual #18                 // Method getStreamer:()Lorg/apache/hadoop/hdfs/DataStreamer;
      66: aastore
      67: invokeinterface #149,  3          // InterfaceMethod org/slf4j/Logger.debug:(Ljava/lang/String;[Ljava/lang/Object;)V
      72: aload_0
      73: invokevirtual #176                // Method enqueueCurrentPacket:()V
      76: aload_0
      77: invokevirtual #177                // Method adjustChunkBoundary:()V
      80: aload_0
      81: invokevirtual #178                // Method endBlock:()V
      84: return

  void setCurrentPacketToEmpty() throws java.io.InterruptedIOException;
    Code:
       0: aload_0
       1: aload_0
       2: iconst_0
       3: iconst_0
       4: aload_0
       5: invokevirtual #18                 // Method getStreamer:()Lorg/apache/hadoop/hdfs/DataStreamer;
       8: invokevirtual #158                // Method org/apache/hadoop/hdfs/DataStreamer.getBytesCurBlock:()J
      11: aload_0
      12: invokevirtual #18                 // Method getStreamer:()Lorg/apache/hadoop/hdfs/DataStreamer;
      15: invokevirtual #167                // Method org/apache/hadoop/hdfs/DataStreamer.getAndIncCurrentSeqno:()J
      18: iconst_1
      19: invokevirtual #168                // Method createPacket:(IIJJZ)Lorg/apache/hadoop/hdfs/DFSPacket;
      22: putfield      #33                 // Field currentPacket:Lorg/apache/hadoop/hdfs/DFSPacket;
      25: aload_0
      26: getfield      #33                 // Field currentPacket:Lorg/apache/hadoop/hdfs/DFSPacket;
      29: aload_0
      30: getfield      #38                 // Field shouldSyncBlock:Z
      33: invokevirtual #179                // Method org/apache/hadoop/hdfs/DFSPacket.setSyncBlock:(Z)V
      36: return

  protected void adjustChunkBoundary();
    Code:
       0: aload_0
       1: invokevirtual #18                 // Method getStreamer:()Lorg/apache/hadoop/hdfs/DataStreamer;
       4: invokevirtual #174                // Method org/apache/hadoop/hdfs/DataStreamer.getAppendChunk:()Z
       7: ifeq          40
      10: aload_0
      11: invokevirtual #18                 // Method getStreamer:()Lorg/apache/hadoop/hdfs/DataStreamer;
      14: invokevirtual #158                // Method org/apache/hadoop/hdfs/DataStreamer.getBytesCurBlock:()J
      17: aload_0
      18: getfield      #65                 // Field bytesPerChecksum:I
      21: i2l
      22: lrem
      23: lconst_0
      24: lcmp
      25: ifne          40
      28: aload_0
      29: invokevirtual #18                 // Method getStreamer:()Lorg/apache/hadoop/hdfs/DataStreamer;
      32: iconst_0
      33: invokevirtual #141                // Method org/apache/hadoop/hdfs/DataStreamer.setAppendChunk:(Z)V
      36: aload_0
      37: invokevirtual #180                // Method resetChecksumBufSize:()V
      40: aload_0
      41: invokevirtual #18                 // Method getStreamer:()Lorg/apache/hadoop/hdfs/DataStreamer;
      44: invokevirtual #174                // Method org/apache/hadoop/hdfs/DataStreamer.getAppendChunk:()Z
      47: ifne          81
      50: aload_0
      51: getfield      #44                 // Field blockSize:J
      54: aload_0
      55: invokevirtual #18                 // Method getStreamer:()Lorg/apache/hadoop/hdfs/DataStreamer;
      58: invokevirtual #158                // Method org/apache/hadoop/hdfs/DataStreamer.getBytesCurBlock:()J
      61: lsub
      62: aload_0
      63: getfield      #79                 // Field writePacketSize:I
      66: i2l
      67: invokestatic  #181                // Method java/lang/Math.min:(JJ)J
      70: l2i
      71: istore_1
      72: aload_0
      73: iload_1
      74: aload_0
      75: getfield      #65                 // Field bytesPerChecksum:I
      78: invokevirtual #88                 // Method computePacketChunkSize:(II)V
      81: return

  void setAppendChunk(boolean);
    Code:
       0: aload_0
       1: invokevirtual #18                 // Method getStreamer:()Lorg/apache/hadoop/hdfs/DataStreamer;
       4: iload_1
       5: invokevirtual #141                // Method org/apache/hadoop/hdfs/DataStreamer.setAppendChunk:(Z)V
       8: return

  void setBytesCurBlock(long);
    Code:
       0: aload_0
       1: invokevirtual #18                 // Method getStreamer:()Lorg/apache/hadoop/hdfs/DataStreamer;
       4: lload_1
       5: invokevirtual #133                // Method org/apache/hadoop/hdfs/DataStreamer.setBytesCurBlock:(J)V
       8: return

  void endBlock() throws java.io.IOException;
    Code:
       0: aload_0
       1: invokevirtual #18                 // Method getStreamer:()Lorg/apache/hadoop/hdfs/DataStreamer;
       4: invokevirtual #158                // Method org/apache/hadoop/hdfs/DataStreamer.getBytesCurBlock:()J
       7: aload_0
       8: getfield      #44                 // Field blockSize:J
      11: lcmp
      12: ifne          36
      15: aload_0
      16: invokevirtual #182                // Method setCurrentPacketToEmpty:()V
      19: aload_0
      20: invokevirtual #176                // Method enqueueCurrentPacket:()V
      23: aload_0
      24: invokevirtual #18                 // Method getStreamer:()Lorg/apache/hadoop/hdfs/DataStreamer;
      27: lconst_0
      28: invokevirtual #133                // Method org/apache/hadoop/hdfs/DataStreamer.setBytesCurBlock:(J)V
      31: aload_0
      32: lconst_0
      33: putfield      #36                 // Field lastFlushOffset:J
      36: return

  public boolean hasCapability(java.lang.String);
    Code:
       0: aload_1
       1: invokestatic  #183                // Method org/apache/hadoop/util/StringUtils.toLowerCase:(Ljava/lang/String;)Ljava/lang/String;
       4: astore_2
       5: iconst_m1
       6: istore_3
       7: aload_2
       8: invokevirtual #184                // Method java/lang/String.hashCode:()I
      11: lookupswitch  { // 2
           -1220002916: 50
              99591939: 36
               default: 61
          }
      36: aload_2
      37: ldc           #185                // String hsync
      39: invokevirtual #186                // Method java/lang/String.equals:(Ljava/lang/Object;)Z
      42: ifeq          61
      45: iconst_0
      46: istore_3
      47: goto          61
      50: aload_2
      51: ldc           #187                // String hflush
      53: invokevirtual #186                // Method java/lang/String.equals:(Ljava/lang/Object;)Z
      56: ifeq          61
      59: iconst_1
      60: istore_3
      61: iload_3
      62: lookupswitch  { // 2
                     0: 88
                     1: 88
               default: 90
          }
      88: iconst_1
      89: ireturn
      90: iconst_0
      91: ireturn

  public void hflush() throws java.io.IOException;
    Code:
       0: aload_0
       1: getfield      #39                 // Field dfsClient:Lorg/apache/hadoop/hdfs/DFSClient;
       4: ldc           #187                // String hflush
       6: aload_0
       7: getfield      #40                 // Field src:Ljava/lang/String;
      10: invokevirtual #93                 // Method org/apache/hadoop/hdfs/DFSClient.newPathTraceScope:(Ljava/lang/String;Ljava/lang/String;)Lorg/apache/htrace/core/TraceScope;
      13: astore_1
      14: aconst_null
      15: astore_2
      16: aload_0
      17: iconst_0
      18: ldc           #188                // class org/apache/hadoop/hdfs/client/HdfsDataOutputStream$SyncFlag
      20: invokestatic  #53                 // Method java/util/EnumSet.noneOf:(Ljava/lang/Class;)Ljava/util/EnumSet;
      23: invokespecial #189                // Method flushOrSync:(ZLjava/util/EnumSet;)V
      26: aload_1
      27: ifnull        97
      30: aload_2
      31: ifnull        50
      34: aload_1
      35: invokevirtual #126                // Method org/apache/htrace/core/TraceScope.close:()V
      38: goto          97
      41: astore_3
      42: aload_2
      43: aload_3
      44: invokevirtual #128                // Method java/lang/Throwable.addSuppressed:(Ljava/lang/Throwable;)V
      47: goto          97
      50: aload_1
      51: invokevirtual #126                // Method org/apache/htrace/core/TraceScope.close:()V
      54: goto          97
      57: astore_3
      58: aload_3
      59: astore_2
      60: aload_3
      61: athrow
      62: astore        4
      64: aload_1
      65: ifnull        94
      68: aload_2
      69: ifnull        90
      72: aload_1
      73: invokevirtual #126                // Method org/apache/htrace/core/TraceScope.close:()V
      76: goto          94
      79: astore        5
      81: aload_2
      82: aload         5
      84: invokevirtual #128                // Method java/lang/Throwable.addSuppressed:(Ljava/lang/Throwable;)V
      87: goto          94
      90: aload_1
      91: invokevirtual #126                // Method org/apache/htrace/core/TraceScope.close:()V
      94: aload         4
      96: athrow
      97: return
    Exception table:
       from    to  target type
          34    38    41   Class java/lang/Throwable
          16    26    57   Class java/lang/Throwable
          16    26    62   any
          72    76    79   Class java/lang/Throwable
          57    64    62   any

  public void hsync() throws java.io.IOException;
    Code:
       0: aload_0
       1: getfield      #39                 // Field dfsClient:Lorg/apache/hadoop/hdfs/DFSClient;
       4: ldc           #185                // String hsync
       6: aload_0
       7: getfield      #40                 // Field src:Ljava/lang/String;
      10: invokevirtual #93                 // Method org/apache/hadoop/hdfs/DFSClient.newPathTraceScope:(Ljava/lang/String;Ljava/lang/String;)Lorg/apache/htrace/core/TraceScope;
      13: astore_1
      14: aconst_null
      15: astore_2
      16: aload_0
      17: iconst_1
      18: ldc           #188                // class org/apache/hadoop/hdfs/client/HdfsDataOutputStream$SyncFlag
      20: invokestatic  #53                 // Method java/util/EnumSet.noneOf:(Ljava/lang/Class;)Ljava/util/EnumSet;
      23: invokespecial #189                // Method flushOrSync:(ZLjava/util/EnumSet;)V
      26: aload_1
      27: ifnull        97
      30: aload_2
      31: ifnull        50
      34: aload_1
      35: invokevirtual #126                // Method org/apache/htrace/core/TraceScope.close:()V
      38: goto          97
      41: astore_3
      42: aload_2
      43: aload_3
      44: invokevirtual #128                // Method java/lang/Throwable.addSuppressed:(Ljava/lang/Throwable;)V
      47: goto          97
      50: aload_1
      51: invokevirtual #126                // Method org/apache/htrace/core/TraceScope.close:()V
      54: goto          97
      57: astore_3
      58: aload_3
      59: astore_2
      60: aload_3
      61: athrow
      62: astore        4
      64: aload_1
      65: ifnull        94
      68: aload_2
      69: ifnull        90
      72: aload_1
      73: invokevirtual #126                // Method org/apache/htrace/core/TraceScope.close:()V
      76: goto          94
      79: astore        5
      81: aload_2
      82: aload         5
      84: invokevirtual #128                // Method java/lang/Throwable.addSuppressed:(Ljava/lang/Throwable;)V
      87: goto          94
      90: aload_1
      91: invokevirtual #126                // Method org/apache/htrace/core/TraceScope.close:()V
      94: aload         4
      96: athrow
      97: return
    Exception table:
       from    to  target type
          34    38    41   Class java/lang/Throwable
          16    26    57   Class java/lang/Throwable
          16    26    62   any
          72    76    79   Class java/lang/Throwable
          57    64    62   any

  public void hsync(java.util.EnumSet<org.apache.hadoop.hdfs.client.HdfsDataOutputStream$SyncFlag>) throws java.io.IOException;
    Code:
       0: aload_0
       1: getfield      #39                 // Field dfsClient:Lorg/apache/hadoop/hdfs/DFSClient;
       4: ldc           #185                // String hsync
       6: aload_0
       7: getfield      #40                 // Field src:Ljava/lang/String;
      10: invokevirtual #93                 // Method org/apache/hadoop/hdfs/DFSClient.newPathTraceScope:(Ljava/lang/String;Ljava/lang/String;)Lorg/apache/htrace/core/TraceScope;
      13: astore_2
      14: aconst_null
      15: astore_3
      16: aload_0
      17: iconst_1
      18: aload_1
      19: invokespecial #189                // Method flushOrSync:(ZLjava/util/EnumSet;)V
      22: aload_2
      23: ifnull        98
      26: aload_3
      27: ifnull        48
      30: aload_2
      31: invokevirtual #126                // Method org/apache/htrace/core/TraceScope.close:()V
      34: goto          98
      37: astore        4
      39: aload_3
      40: aload         4
      42: invokevirtual #128                // Method java/lang/Throwable.addSuppressed:(Ljava/lang/Throwable;)V
      45: goto          98
      48: aload_2
      49: invokevirtual #126                // Method org/apache/htrace/core/TraceScope.close:()V
      52: goto          98
      55: astore        4
      57: aload         4
      59: astore_3
      60: aload         4
      62: athrow
      63: astore        5
      65: aload_2
      66: ifnull        95
      69: aload_3
      70: ifnull        91
      73: aload_2
      74: invokevirtual #126                // Method org/apache/htrace/core/TraceScope.close:()V
      77: goto          95
      80: astore        6
      82: aload_3
      83: aload         6
      85: invokevirtual #128                // Method java/lang/Throwable.addSuppressed:(Ljava/lang/Throwable;)V
      88: goto          95
      91: aload_2
      92: invokevirtual #126                // Method org/apache/htrace/core/TraceScope.close:()V
      95: aload         5
      97: athrow
      98: return
    Exception table:
       from    to  target type
          30    34    37   Class java/lang/Throwable
          16    22    55   Class java/lang/Throwable
          16    22    63   any
          73    77    80   Class java/lang/Throwable
          55    65    63   any

  private void flushOrSync(boolean, java.util.EnumSet<org.apache.hadoop.hdfs.client.HdfsDataOutputStream$SyncFlag>) throws java.io.IOException;
    Code:
       0: aload_0
       1: getfield      #39                 // Field dfsClient:Lorg/apache/hadoop/hdfs/DFSClient;
       4: invokevirtual #161                // Method org/apache/hadoop/hdfs/DFSClient.checkOpen:()V
       7: aload_0
       8: invokevirtual #162                // Method checkClosed:()V
      11: ldc2_w        #190                // long -1l
      14: lstore        5
      16: aload_2
      17: getstatic     #192                // Field org/apache/hadoop/hdfs/client/HdfsDataOutputStream$SyncFlag.UPDATE_LENGTH:Lorg/apache/hadoop/hdfs/client/HdfsDataOutputStream$SyncFlag;
      20: invokevirtual #56                 // Method java/util/EnumSet.contains:(Ljava/lang/Object;)Z
      23: istore        7
      25: aload_2
      26: getstatic     #193                // Field org/apache/hadoop/hdfs/client/HdfsDataOutputStream$SyncFlag.END_BLOCK:Lorg/apache/hadoop/hdfs/client/HdfsDataOutputStream$SyncFlag;
      29: invokevirtual #56                 // Method java/util/EnumSet.contains:(Ljava/lang/Object;)Z
      32: istore        8
      34: aload_0
      35: dup
      36: astore        9
      38: monitorenter
      39: aload_0
      40: iload         8
      42: ifne          49
      45: iconst_1
      46: goto          50
      49: iconst_0
      50: iconst_1
      51: invokevirtual #194                // Method flushBuffer:(ZZ)I
      54: istore        10
      56: getstatic     #61                 // Field org/apache/hadoop/hdfs/DFSClient.LOG:Lorg/slf4j/Logger;
      59: ldc           #195                // String DFSClient flush():  bytesCurBlock={}, lastFlushOffset={}, createNewBlock={}
      61: iconst_3
      62: anewarray     #148                // class java/lang/Object
      65: dup
      66: iconst_0
      67: aload_0
      68: invokevirtual #18                 // Method getStreamer:()Lorg/apache/hadoop/hdfs/DataStreamer;
      71: invokevirtual #158                // Method org/apache/hadoop/hdfs/DataStreamer.getBytesCurBlock:()J
      74: invokestatic  #171                // Method java/lang/Long.valueOf:(J)Ljava/lang/Long;
      77: aastore
      78: dup
      79: iconst_1
      80: aload_0
      81: getfield      #36                 // Field lastFlushOffset:J
      84: invokestatic  #171                // Method java/lang/Long.valueOf:(J)Ljava/lang/Long;
      87: aastore
      88: dup
      89: iconst_2
      90: iload         8
      92: invokestatic  #175                // Method java/lang/Boolean.valueOf:(Z)Ljava/lang/Boolean;
      95: aastore
      96: invokeinterface #149,  3          // InterfaceMethod org/slf4j/Logger.debug:(Ljava/lang/String;[Ljava/lang/Object;)V
     101: aload_0
     102: getfield      #36                 // Field lastFlushOffset:J
     105: aload_0
     106: invokevirtual #18                 // Method getStreamer:()Lorg/apache/hadoop/hdfs/DataStreamer;
     109: invokevirtual #158                // Method org/apache/hadoop/hdfs/DataStreamer.getBytesCurBlock:()J
     112: lcmp
     113: ifeq          206
     116: getstatic     #196                // Field $assertionsDisabled:Z
     119: ifne          145
     122: aload_0
     123: invokevirtual #18                 // Method getStreamer:()Lorg/apache/hadoop/hdfs/DataStreamer;
     126: invokevirtual #158                // Method org/apache/hadoop/hdfs/DataStreamer.getBytesCurBlock:()J
     129: aload_0
     130: getfield      #36                 // Field lastFlushOffset:J
     133: lcmp
     134: ifgt          145
     137: new           #197                // class java/lang/AssertionError
     140: dup
     141: invokespecial #198                // Method java/lang/AssertionError."<init>":()V
     144: athrow
     145: aload_0
     146: aload_0
     147: invokevirtual #18                 // Method getStreamer:()Lorg/apache/hadoop/hdfs/DataStreamer;
     150: invokevirtual #158                // Method org/apache/hadoop/hdfs/DataStreamer.getBytesCurBlock:()J
     153: putfield      #36                 // Field lastFlushOffset:J
     156: iload_1
     157: ifeq          284
     160: aload_0
     161: getfield      #33                 // Field currentPacket:Lorg/apache/hadoop/hdfs/DFSPacket;
     164: ifnonnull     284
     167: iload         8
     169: ifne          284
     172: aload_0
     173: aload_0
     174: aload_0
     175: getfield      #34                 // Field packetSize:I
     178: aload_0
     179: getfield      #35                 // Field chunksPerPacket:I
     182: aload_0
     183: invokevirtual #18                 // Method getStreamer:()Lorg/apache/hadoop/hdfs/DataStreamer;
     186: invokevirtual #158                // Method org/apache/hadoop/hdfs/DataStreamer.getBytesCurBlock:()J
     189: aload_0
     190: invokevirtual #18                 // Method getStreamer:()Lorg/apache/hadoop/hdfs/DataStreamer;
     193: invokevirtual #167                // Method org/apache/hadoop/hdfs/DataStreamer.getAndIncCurrentSeqno:()J
     196: iconst_0
     197: invokevirtual #168                // Method createPacket:(IIJJZ)Lorg/apache/hadoop/hdfs/DFSPacket;
     200: putfield      #33                 // Field currentPacket:Lorg/apache/hadoop/hdfs/DFSPacket;
     203: goto          284
     206: iload_1
     207: ifeq          261
     210: aload_0
     211: invokevirtual #18                 // Method getStreamer:()Lorg/apache/hadoop/hdfs/DataStreamer;
     214: invokevirtual #158                // Method org/apache/hadoop/hdfs/DataStreamer.getBytesCurBlock:()J
     217: lconst_0
     218: lcmp
     219: ifle          261
     222: iload         8
     224: ifne          261
     227: aload_0
     228: aload_0
     229: aload_0
     230: getfield      #34                 // Field packetSize:I
     233: aload_0
     234: getfield      #35                 // Field chunksPerPacket:I
     237: aload_0
     238: invokevirtual #18                 // Method getStreamer:()Lorg/apache/hadoop/hdfs/DataStreamer;
     241: invokevirtual #158                // Method org/apache/hadoop/hdfs/DataStreamer.getBytesCurBlock:()J
     244: aload_0
     245: invokevirtual #18                 // Method getStreamer:()Lorg/apache/hadoop/hdfs/DataStreamer;
     248: invokevirtual #167                // Method org/apache/hadoop/hdfs/DataStreamer.getAndIncCurrentSeqno:()J
     251: iconst_0
     252: invokevirtual #168                // Method createPacket:(IIJJZ)Lorg/apache/hadoop/hdfs/DFSPacket;
     255: putfield      #33                 // Field currentPacket:Lorg/apache/hadoop/hdfs/DFSPacket;
     258: goto          284
     261: aload_0
     262: getfield      #33                 // Field currentPacket:Lorg/apache/hadoop/hdfs/DFSPacket;
     265: ifnull        284
     268: aload_0
     269: getfield      #33                 // Field currentPacket:Lorg/apache/hadoop/hdfs/DFSPacket;
     272: aload_0
     273: getfield      #2                  // Field byteArrayManager:Lorg/apache/hadoop/hdfs/util/ByteArrayManager;
     276: invokevirtual #199                // Method org/apache/hadoop/hdfs/DFSPacket.releaseBuffer:(Lorg/apache/hadoop/hdfs/util/ByteArrayManager;)V
     279: aload_0
     280: aconst_null
     281: putfield      #33                 // Field currentPacket:Lorg/apache/hadoop/hdfs/DFSPacket;
     284: aload_0
     285: getfield      #33                 // Field currentPacket:Lorg/apache/hadoop/hdfs/DFSPacket;
     288: ifnull        303
     291: aload_0
     292: getfield      #33                 // Field currentPacket:Lorg/apache/hadoop/hdfs/DFSPacket;
     295: iload_1
     296: invokevirtual #179                // Method org/apache/hadoop/hdfs/DFSPacket.setSyncBlock:(Z)V
     299: aload_0
     300: invokevirtual #176                // Method enqueueCurrentPacket:()V
     303: iload         8
     305: ifeq          388
     308: aload_0
     309: invokevirtual #18                 // Method getStreamer:()Lorg/apache/hadoop/hdfs/DataStreamer;
     312: invokevirtual #158                // Method org/apache/hadoop/hdfs/DataStreamer.getBytesCurBlock:()J
     315: lconst_0
     316: lcmp
     317: ifle          388
     320: aload_0
     321: aload_0
     322: iconst_0
     323: iconst_0
     324: aload_0
     325: invokevirtual #18                 // Method getStreamer:()Lorg/apache/hadoop/hdfs/DataStreamer;
     328: invokevirtual #158                // Method org/apache/hadoop/hdfs/DataStreamer.getBytesCurBlock:()J
     331: aload_0
     332: invokevirtual #18                 // Method getStreamer:()Lorg/apache/hadoop/hdfs/DataStreamer;
     335: invokevirtual #167                // Method org/apache/hadoop/hdfs/DataStreamer.getAndIncCurrentSeqno:()J
     338: iconst_1
     339: invokevirtual #168                // Method createPacket:(IIJJZ)Lorg/apache/hadoop/hdfs/DFSPacket;
     342: putfield      #33                 // Field currentPacket:Lorg/apache/hadoop/hdfs/DFSPacket;
     345: aload_0
     346: getfield      #33                 // Field currentPacket:Lorg/apache/hadoop/hdfs/DFSPacket;
     349: aload_0
     350: getfield      #38                 // Field shouldSyncBlock:Z
     353: ifne          360
     356: iload_1
     357: ifeq          364
     360: iconst_1
     361: goto          365
     364: iconst_0
     365: invokevirtual #179                // Method org/apache/hadoop/hdfs/DFSPacket.setSyncBlock:(Z)V
     368: aload_0
     369: invokevirtual #176                // Method enqueueCurrentPacket:()V
     372: aload_0
     373: invokevirtual #18                 // Method getStreamer:()Lorg/apache/hadoop/hdfs/DataStreamer;
     376: lconst_0
     377: invokevirtual #133                // Method org/apache/hadoop/hdfs/DataStreamer.setBytesCurBlock:(J)V
     380: aload_0
     381: lconst_0
     382: putfield      #36                 // Field lastFlushOffset:J
     385: goto          406
     388: aload_0
     389: invokevirtual #18                 // Method getStreamer:()Lorg/apache/hadoop/hdfs/DataStreamer;
     392: aload_0
     393: invokevirtual #18                 // Method getStreamer:()Lorg/apache/hadoop/hdfs/DataStreamer;
     396: invokevirtual #158                // Method org/apache/hadoop/hdfs/DataStreamer.getBytesCurBlock:()J
     399: iload         10
     401: i2l
     402: lsub
     403: invokevirtual #133                // Method org/apache/hadoop/hdfs/DataStreamer.setBytesCurBlock:(J)V
     406: aload_0
     407: invokevirtual #18                 // Method getStreamer:()Lorg/apache/hadoop/hdfs/DataStreamer;
     410: invokevirtual #200                // Method org/apache/hadoop/hdfs/DataStreamer.getLastQueuedSeqno:()J
     413: lstore_3
     414: aload         9
     416: monitorexit
     417: goto          428
     420: astore        11
     422: aload         9
     424: monitorexit
     425: aload         11
     427: athrow
     428: aload_0
     429: invokevirtual #18                 // Method getStreamer:()Lorg/apache/hadoop/hdfs/DataStreamer;
     432: lload_3
     433: invokevirtual #201                // Method org/apache/hadoop/hdfs/DataStreamer.waitForAckedSeqno:(J)V
     436: iload         7
     438: ifne          454
     441: aload_0
     442: invokevirtual #18                 // Method getStreamer:()Lorg/apache/hadoop/hdfs/DataStreamer;
     445: invokevirtual #202                // Method org/apache/hadoop/hdfs/DataStreamer.getPersistBlocks:()Ljava/util/concurrent/atomic/AtomicBoolean;
     448: invokevirtual #203                // Method java/util/concurrent/atomic/AtomicBoolean.get:()Z
     451: ifeq          505
     454: aload_0
     455: dup
     456: astore        9
     458: monitorenter
     459: aload_0
     460: invokevirtual #18                 // Method getStreamer:()Lorg/apache/hadoop/hdfs/DataStreamer;
     463: invokevirtual #21                 // Method org/apache/hadoop/hdfs/DataStreamer.streamerClosed:()Z
     466: ifne          491
     469: aload_0
     470: invokevirtual #18                 // Method getStreamer:()Lorg/apache/hadoop/hdfs/DataStreamer;
     473: invokevirtual #204                // Method org/apache/hadoop/hdfs/DataStreamer.getBlock:()Lorg/apache/hadoop/hdfs/protocol/ExtendedBlock;
     476: ifnull        491
     479: aload_0
     480: invokevirtual #18                 // Method getStreamer:()Lorg/apache/hadoop/hdfs/DataStreamer;
     483: invokevirtual #204                // Method org/apache/hadoop/hdfs/DataStreamer.getBlock:()Lorg/apache/hadoop/hdfs/protocol/ExtendedBlock;
     486: invokevirtual #205                // Method org/apache/hadoop/hdfs/protocol/ExtendedBlock.getNumBytes:()J
     489: lstore        5
     491: aload         9
     493: monitorexit
     494: goto          505
     497: astore        12
     499: aload         9
     501: monitorexit
     502: aload         12
     504: athrow
     505: aload_0
     506: invokevirtual #18                 // Method getStreamer:()Lorg/apache/hadoop/hdfs/DataStreamer;
     509: invokevirtual #202                // Method org/apache/hadoop/hdfs/DataStreamer.getPersistBlocks:()Ljava/util/concurrent/atomic/AtomicBoolean;
     512: iconst_0
     513: invokevirtual #206                // Method java/util/concurrent/atomic/AtomicBoolean.getAndSet:(Z)Z
     516: ifne          524
     519: iload         7
     521: ifeq          597
     524: aload_0
     525: getfield      #39                 // Field dfsClient:Lorg/apache/hadoop/hdfs/DFSClient;
     528: getfield      #95                 // Field org/apache/hadoop/hdfs/DFSClient.namenode:Lorg/apache/hadoop/hdfs/protocol/ClientProtocol;
     531: aload_0
     532: getfield      #40                 // Field src:Ljava/lang/String;
     535: aload_0
     536: getfield      #42                 // Field fileId:J
     539: aload_0
     540: getfield      #39                 // Field dfsClient:Lorg/apache/hadoop/hdfs/DFSClient;
     543: getfield      #96                 // Field org/apache/hadoop/hdfs/DFSClient.clientName:Ljava/lang/String;
     546: lload         5
     548: invokeinterface #207,  7          // InterfaceMethod org/apache/hadoop/hdfs/protocol/ClientProtocol.fsync:(Ljava/lang/String;JLjava/lang/String;J)V
     553: goto          597
     556: astore        9
     558: getstatic     #61                 // Field org/apache/hadoop/hdfs/DFSClient.LOG:Lorg/slf4j/Logger;
     561: new           #6                  // class java/lang/StringBuilder
     564: dup
     565: invokespecial #7                  // Method java/lang/StringBuilder."<init>":()V
     568: ldc           #208                // String Unable to persist blocks in hflush for
     570: invokevirtual #9                  // Method java/lang/StringBuilder.append:(Ljava/lang/String;)Ljava/lang/StringBuilder;
     573: aload_0
     574: getfield      #40                 // Field src:Ljava/lang/String;
     577: invokevirtual #9                  // Method java/lang/StringBuilder.append:(Ljava/lang/String;)Ljava/lang/StringBuilder;
     580: invokevirtual #11                 // Method java/lang/StringBuilder.toString:()Ljava/lang/String;
     583: aload         9
     585: invokeinterface #209,  3          // InterfaceMethod org/slf4j/Logger.warn:(Ljava/lang/String;Ljava/lang/Throwable;)V
     590: aload_0
     591: invokevirtual #162                // Method checkClosed:()V
     594: aload         9
     596: athrow
     597: aload_0
     598: dup
     599: astore        9
     601: monitorenter
     602: aload_0
     603: invokevirtual #18                 // Method getStreamer:()Lorg/apache/hadoop/hdfs/DataStreamer;
     606: invokevirtual #21                 // Method org/apache/hadoop/hdfs/DataStreamer.streamerClosed:()Z
     609: ifne          619
     612: aload_0
     613: invokevirtual #18                 // Method getStreamer:()Lorg/apache/hadoop/hdfs/DataStreamer;
     616: invokevirtual #210                // Method org/apache/hadoop/hdfs/DataStreamer.setHflush:()V
     619: aload         9
     621: monitorexit
     622: goto          633
     625: astore        13
     627: aload         9
     629: monitorexit
     630: aload         13
     632: athrow
     633: goto          695
     636: astore_3
     637: aload_3
     638: athrow
     639: astore_3
     640: getstatic     #61                 // Field org/apache/hadoop/hdfs/DFSClient.LOG:Lorg/slf4j/Logger;
     643: ldc           #211                // String Error while syncing
     645: aload_3
     646: invokeinterface #209,  3          // InterfaceMethod org/slf4j/Logger.warn:(Ljava/lang/String;Ljava/lang/Throwable;)V
     651: aload_0
     652: dup
     653: astore        4
     655: monitorenter
     656: aload_0
     657: invokevirtual #17                 // Method isClosed:()Z
     660: ifne          679
     663: aload_0
     664: invokevirtual #18                 // Method getStreamer:()Lorg/apache/hadoop/hdfs/DataStreamer;
     667: invokevirtual #19                 // Method org/apache/hadoop/hdfs/DataStreamer.getLastException:()Lorg/apache/hadoop/hdfs/DataStreamer$LastExceptionInStreamer;
     670: aload_3
     671: invokevirtual #212                // Method org/apache/hadoop/hdfs/DataStreamer$LastExceptionInStreamer.set:(Ljava/lang/Throwable;)V
     674: aload_0
     675: iconst_1
     676: invokevirtual #213                // Method closeThreads:(Z)V
     679: aload         4
     681: monitorexit
     682: goto          693
     685: astore        14
     687: aload         4
     689: monitorexit
     690: aload         14
     692: athrow
     693: aload_3
     694: athrow
     695: return
    Exception table:
       from    to  target type
          39   417   420   any
         420   425   420   any
         459   494   497   any
         497   502   497   any
         524   553   556   Class java/io/IOException
         602   622   625   any
         625   630   625   any
          11   633   636   Class java/io/InterruptedIOException
          11   633   639   Class java/io/IOException
         656   682   685   any
         685   690   685   any

  public synchronized int getNumCurrentReplicas() throws java.io.IOException;
    Code:
       0: aload_0
       1: invokevirtual #214                // Method getCurrentBlockReplication:()I
       4: ireturn

  public synchronized int getCurrentBlockReplication() throws java.io.IOException;
    Code:
       0: aload_0
       1: getfield      #39                 // Field dfsClient:Lorg/apache/hadoop/hdfs/DFSClient;
       4: invokevirtual #161                // Method org/apache/hadoop/hdfs/DFSClient.checkOpen:()V
       7: aload_0
       8: invokevirtual #162                // Method checkClosed:()V
      11: aload_0
      12: invokevirtual #18                 // Method getStreamer:()Lorg/apache/hadoop/hdfs/DataStreamer;
      15: invokevirtual #21                 // Method org/apache/hadoop/hdfs/DataStreamer.streamerClosed:()Z
      18: ifeq          26
      21: aload_0
      22: getfield      #45                 // Field blockReplication:S
      25: ireturn
      26: aload_0
      27: invokevirtual #18                 // Method getStreamer:()Lorg/apache/hadoop/hdfs/DataStreamer;
      30: invokevirtual #22                 // Method org/apache/hadoop/hdfs/DataStreamer.getNodes:()[Lorg/apache/hadoop/hdfs/protocol/DatanodeInfo;
      33: astore_1
      34: aload_1
      35: ifnonnull     43
      38: aload_0
      39: getfield      #45                 // Field blockReplication:S
      42: ireturn
      43: aload_1
      44: arraylength
      45: ireturn

  protected void flushInternal() throws java.io.IOException;
    Code:
       0: aload_0
       1: invokevirtual #215                // Method flushInternalWithoutWaitingAck:()J
       4: lstore_1
       5: aload_0
       6: invokevirtual #18                 // Method getStreamer:()Lorg/apache/hadoop/hdfs/DataStreamer;
       9: lload_1
      10: invokevirtual #201                // Method org/apache/hadoop/hdfs/DataStreamer.waitForAckedSeqno:(J)V
      13: return

  protected synchronized void start();
    Code:
       0: aload_0
       1: invokevirtual #18                 // Method getStreamer:()Lorg/apache/hadoop/hdfs/DataStreamer;
       4: invokevirtual #216                // Method org/apache/hadoop/hdfs/DataStreamer.start:()V
       7: return

  void abort() throws java.io.IOException;
    Code:
       0: new           #217                // class org/apache/hadoop/io/MultipleIOException$Builder
       3: dup
       4: invokespecial #218                // Method org/apache/hadoop/io/MultipleIOException$Builder."<init>":()V
       7: astore_1
       8: aload_0
       9: dup
      10: astore_2
      11: monitorenter
      12: aload_0
      13: invokevirtual #17                 // Method isClosed:()Z
      16: ifeq          22
      19: aload_2
      20: monitorexit
      21: return
      22: aload_0
      23: invokevirtual #18                 // Method getStreamer:()Lorg/apache/hadoop/hdfs/DataStreamer;
      26: invokevirtual #19                 // Method org/apache/hadoop/hdfs/DataStreamer.getLastException:()Lorg/apache/hadoop/hdfs/DataStreamer$LastExceptionInStreamer;
      29: new           #116                // class java/io/IOException
      32: dup
      33: new           #6                  // class java/lang/StringBuilder
      36: dup
      37: invokespecial #7                  // Method java/lang/StringBuilder."<init>":()V
      40: ldc           #219                // String Lease timeout of
      42: invokevirtual #9                  // Method java/lang/StringBuilder.append:(Ljava/lang/String;)Ljava/lang/StringBuilder;
      45: aload_0
      46: getfield      #39                 // Field dfsClient:Lorg/apache/hadoop/hdfs/DFSClient;
      49: invokevirtual #77                 // Method org/apache/hadoop/hdfs/DFSClient.getConf:()Lorg/apache/hadoop/hdfs/client/impl/DfsClientConf;
      52: invokevirtual #220                // Method org/apache/hadoop/hdfs/client/impl/DfsClientConf.getHdfsTimeout:()I
      55: sipush        1000
      58: idiv
      59: invokevirtual #68                 // Method java/lang/StringBuilder.append:(I)Ljava/lang/StringBuilder;
      62: ldc           #221                // String  seconds expired.
      64: invokevirtual #9                  // Method java/lang/StringBuilder.append:(Ljava/lang/String;)Ljava/lang/StringBuilder;
      67: invokevirtual #11                 // Method java/lang/StringBuilder.toString:()Ljava/lang/String;
      70: invokespecial #139                // Method java/io/IOException."<init>":(Ljava/lang/String;)V
      73: invokevirtual #212                // Method org/apache/hadoop/hdfs/DataStreamer$LastExceptionInStreamer.set:(Ljava/lang/Throwable;)V
      76: aload_0
      77: iconst_1
      78: invokevirtual #213                // Method closeThreads:(Z)V
      81: goto          90
      84: astore_3
      85: aload_1
      86: aload_3
      87: invokevirtual #222                // Method org/apache/hadoop/io/MultipleIOException$Builder.add:(Ljava/lang/Throwable;)V
      90: aload_2
      91: monitorexit
      92: goto          102
      95: astore        4
      97: aload_2
      98: monitorexit
      99: aload         4
     101: athrow
     102: aload_1
     103: invokevirtual #223                // Method org/apache/hadoop/io/MultipleIOException$Builder.build:()Ljava/io/IOException;
     106: astore_2
     107: aload_2
     108: ifnull        113
     111: aload_2
     112: athrow
     113: return
    Exception table:
       from    to  target type
          76    81    84   Class java/io/IOException
          12    21    95   any
          22    92    95   any
          95    99    95   any

  boolean isClosed();
    Code:
       0: aload_0
       1: getfield      #32                 // Field closed:Z
       4: ifne          17
       7: aload_0
       8: invokevirtual #18                 // Method getStreamer:()Lorg/apache/hadoop/hdfs/DataStreamer;
      11: invokevirtual #21                 // Method org/apache/hadoop/hdfs/DataStreamer.streamerClosed:()Z
      14: ifeq          21
      17: iconst_1
      18: goto          22
      21: iconst_0
      22: ireturn

  void setClosed();
    Code:
       0: aload_0
       1: iconst_1
       2: putfield      #32                 // Field closed:Z
       5: aload_0
       6: getfield      #39                 // Field dfsClient:Lorg/apache/hadoop/hdfs/DFSClient;
       9: aload_0
      10: getfield      #42                 // Field fileId:J
      13: invokevirtual #224                // Method org/apache/hadoop/hdfs/DFSClient.endFileLease:(J)V
      16: aload_0
      17: invokevirtual #18                 // Method getStreamer:()Lorg/apache/hadoop/hdfs/DataStreamer;
      20: invokevirtual #225                // Method org/apache/hadoop/hdfs/DataStreamer.release:()V
      23: return

  protected void closeThreads(boolean) throws java.io.IOException;
    Code:
       0: aload_0
       1: invokevirtual #18                 // Method getStreamer:()Lorg/apache/hadoop/hdfs/DataStreamer;
       4: iload_1
       5: invokevirtual #226                // Method org/apache/hadoop/hdfs/DataStreamer.close:(Z)V
       8: aload_0
       9: invokevirtual #18                 // Method getStreamer:()Lorg/apache/hadoop/hdfs/DataStreamer;
      12: invokevirtual #227                // Method org/apache/hadoop/hdfs/DataStreamer.join:()V
      15: aload_0
      16: invokevirtual #18                 // Method getStreamer:()Lorg/apache/hadoop/hdfs/DataStreamer;
      19: invokevirtual #228                // Method org/apache/hadoop/hdfs/DataStreamer.closeSocket:()V
      22: aload_0
      23: invokevirtual #18                 // Method getStreamer:()Lorg/apache/hadoop/hdfs/DataStreamer;
      26: invokevirtual #229                // Method org/apache/hadoop/hdfs/DataStreamer.setSocketToNull:()V
      29: aload_0
      30: invokevirtual #230                // Method setClosed:()V
      33: goto          61
      36: astore_2
      37: new           #116                // class java/io/IOException
      40: dup
      41: ldc           #231                // String Failed to shutdown streamer
      43: invokespecial #139                // Method java/io/IOException."<init>":(Ljava/lang/String;)V
      46: athrow
      47: astore_3
      48: aload_0
      49: invokevirtual #18                 // Method getStreamer:()Lorg/apache/hadoop/hdfs/DataStreamer;
      52: invokevirtual #229                // Method org/apache/hadoop/hdfs/DataStreamer.setSocketToNull:()V
      55: aload_0
      56: invokevirtual #230                // Method setClosed:()V
      59: aload_3
      60: athrow
      61: return
    Exception table:
       from    to  target type
           0    22    36   Class java/lang/InterruptedException
           0    22    47   any
          36    48    47   any

  public void close() throws java.io.IOException;
    Code:
       0: new           #217                // class org/apache/hadoop/io/MultipleIOException$Builder
       3: dup
       4: invokespecial #218                // Method org/apache/hadoop/io/MultipleIOException$Builder."<init>":()V
       7: astore_1
       8: aload_0
       9: dup
      10: astore_2
      11: monitorenter
      12: aload_0
      13: getfield      #39                 // Field dfsClient:Lorg/apache/hadoop/hdfs/DFSClient;
      16: ldc           #232                // String DFSOutputStream#close
      18: aload_0
      19: getfield      #40                 // Field src:Ljava/lang/String;
      22: invokevirtual #93                 // Method org/apache/hadoop/hdfs/DFSClient.newPathTraceScope:(Ljava/lang/String;Ljava/lang/String;)Lorg/apache/htrace/core/TraceScope;
      25: astore_3
      26: aconst_null
      27: astore        4
      29: aload_0
      30: invokevirtual #233                // Method closeImpl:()V
      33: aload_3
      34: ifnull        114
      37: aload         4
      39: ifnull        61
      42: aload_3
      43: invokevirtual #126                // Method org/apache/htrace/core/TraceScope.close:()V
      46: goto          114
      49: astore        5
      51: aload         4
      53: aload         5
      55: invokevirtual #128                // Method java/lang/Throwable.addSuppressed:(Ljava/lang/Throwable;)V
      58: goto          114
      61: aload_3
      62: invokevirtual #126                // Method org/apache/htrace/core/TraceScope.close:()V
      65: goto          114
      68: astore        5
      70: aload         5
      72: astore        4
      74: aload         5
      76: athrow
      77: astore        6
      79: aload_3
      80: ifnull        111
      83: aload         4
      85: ifnull        107
      88: aload_3
      89: invokevirtual #126                // Method org/apache/htrace/core/TraceScope.close:()V
      92: goto          111
      95: astore        7
      97: aload         4
      99: aload         7
     101: invokevirtual #128                // Method java/lang/Throwable.addSuppressed:(Ljava/lang/Throwable;)V
     104: goto          111
     107: aload_3
     108: invokevirtual #126                // Method org/apache/htrace/core/TraceScope.close:()V
     111: aload         6
     113: athrow
     114: goto          123
     117: astore_3
     118: aload_1
     119: aload_3
     120: invokevirtual #222                // Method org/apache/hadoop/io/MultipleIOException$Builder.add:(Ljava/lang/Throwable;)V
     123: aload_2
     124: monitorexit
     125: goto          135
     128: astore        8
     130: aload_2
     131: monitorexit
     132: aload         8
     134: athrow
     135: aload_1
     136: invokevirtual #223                // Method org/apache/hadoop/io/MultipleIOException$Builder.build:()Ljava/io/IOException;
     139: astore_2
     140: aload_2
     141: ifnull        146
     144: aload_2
     145: athrow
     146: return
    Exception table:
       from    to  target type
          42    46    49   Class java/lang/Throwable
          29    33    68   Class java/lang/Throwable
          29    33    77   any
          88    92    95   Class java/lang/Throwable
          68    79    77   any
          12   114   117   Class java/io/IOException
          12   125   128   any
         128   132   128   any

  protected synchronized void closeImpl() throws java.io.IOException;
    Code:
       0: aload_0
       1: invokevirtual #17                 // Method isClosed:()Z
       4: ifeq          97
       7: getstatic     #82                 // Field LOG:Lorg/slf4j/Logger;
      10: ldc           #234                // String Closing an already closed stream. [Stream:{}, streamer:{}]
      12: aload_0
      13: getfield      #32                 // Field closed:Z
      16: invokestatic  #175                // Method java/lang/Boolean.valueOf:(Z)Ljava/lang/Boolean;
      19: aload_0
      20: invokevirtual #18                 // Method getStreamer:()Lorg/apache/hadoop/hdfs/DataStreamer;
      23: invokevirtual #21                 // Method org/apache/hadoop/hdfs/DataStreamer.streamerClosed:()Z
      26: invokestatic  #175                // Method java/lang/Boolean.valueOf:(Z)Ljava/lang/Boolean;
      29: invokeinterface #235,  4          // InterfaceMethod org/slf4j/Logger.debug:(Ljava/lang/String;Ljava/lang/Object;Ljava/lang/Object;)V
      34: aload_0
      35: invokevirtual #18                 // Method getStreamer:()Lorg/apache/hadoop/hdfs/DataStreamer;
      38: invokevirtual #19                 // Method org/apache/hadoop/hdfs/DataStreamer.getLastException:()Lorg/apache/hadoop/hdfs/DataStreamer$LastExceptionInStreamer;
      41: iconst_1
      42: invokevirtual #236                // Method org/apache/hadoop/hdfs/DataStreamer$LastExceptionInStreamer.check:(Z)V
      45: aload_0
      46: getfield      #32                 // Field closed:Z
      49: ifne          96
      52: aload_0
      53: iconst_1
      54: invokevirtual #213                // Method closeThreads:(Z)V
      57: goto          96
      60: astore_1
      61: aload_0
      62: aload_1
      63: invokespecial #237                // Method cleanupAndRethrowIOException:(Ljava/io/IOException;)V
      66: aload_0
      67: getfield      #32                 // Field closed:Z
      70: ifne          96
      73: aload_0
      74: iconst_1
      75: invokevirtual #213                // Method closeThreads:(Z)V
      78: goto          96
      81: astore_2
      82: aload_0
      83: getfield      #32                 // Field closed:Z
      86: ifne          94
      89: aload_0
      90: iconst_1
      91: invokevirtual #213                // Method closeThreads:(Z)V
      94: aload_2
      95: athrow
      96: return
      97: aload_0
      98: invokevirtual #238                // Method flushBuffer:()V
     101: aload_0
     102: getfield      #33                 // Field currentPacket:Lorg/apache/hadoop/hdfs/DFSPacket;
     105: ifnull        112
     108: aload_0
     109: invokevirtual #176                // Method enqueueCurrentPacket:()V
     112: aload_0
     113: invokevirtual #18                 // Method getStreamer:()Lorg/apache/hadoop/hdfs/DataStreamer;
     116: invokevirtual #158                // Method org/apache/hadoop/hdfs/DataStreamer.getBytesCurBlock:()J
     119: lconst_0
     120: lcmp
     121: ifeq          128
     124: aload_0
     125: invokevirtual #182                // Method setCurrentPacketToEmpty:()V
     128: aload_0
     129: invokevirtual #239                // Method flushInternal:()V
     132: goto          141
     135: astore_1
     136: aload_0
     137: aload_1
     138: invokespecial #237                // Method cleanupAndRethrowIOException:(Ljava/io/IOException;)V
     141: aload_0
     142: invokespecial #240                // Method completeFile:()V
     145: aload_0
     146: iconst_1
     147: invokevirtual #213                // Method closeThreads:(Z)V
     150: goto          170
     153: astore_1
     154: aload_0
     155: iconst_1
     156: invokevirtual #213                // Method closeThreads:(Z)V
     159: goto          170
     162: astore_3
     163: aload_0
     164: iconst_1
     165: invokevirtual #213                // Method closeThreads:(Z)V
     168: aload_3
     169: athrow
     170: return
    Exception table:
       from    to  target type
          34    45    60   Class java/io/IOException
          34    45    81   any
          60    66    81   any
         128   132   135   Class java/io/IOException
          97   145   153   Class java/nio/channels/ClosedChannelException
          97   145   162   any

  private void completeFile() throws java.io.IOException;
    Code:
       0: aload_0
       1: invokevirtual #18                 // Method getStreamer:()Lorg/apache/hadoop/hdfs/DataStreamer;
       4: invokevirtual #204                // Method org/apache/hadoop/hdfs/DataStreamer.getBlock:()Lorg/apache/hadoop/hdfs/protocol/ExtendedBlock;
       7: astore_1
       8: aload_0
       9: getfield      #39                 // Field dfsClient:Lorg/apache/hadoop/hdfs/DFSClient;
      12: invokevirtual #242                // Method org/apache/hadoop/hdfs/DFSClient.getTracer:()Lorg/apache/htrace/core/Tracer;
      15: ldc           #243                // String completeFile
      17: invokevirtual #244                // Method org/apache/htrace/core/Tracer.newScope:(Ljava/lang/String;)Lorg/apache/htrace/core/TraceScope;
      20: astore_2
      21: aconst_null
      22: astore_3
      23: aload_0
      24: aload_1
      25: invokevirtual #245                // Method completeFile:(Lorg/apache/hadoop/hdfs/protocol/ExtendedBlock;)V
      28: aload_2
      29: ifnull        104
      32: aload_3
      33: ifnull        54
      36: aload_2
      37: invokevirtual #126                // Method org/apache/htrace/core/TraceScope.close:()V
      40: goto          104
      43: astore        4
      45: aload_3
      46: aload         4
      48: invokevirtual #128                // Method java/lang/Throwable.addSuppressed:(Ljava/lang/Throwable;)V
      51: goto          104
      54: aload_2
      55: invokevirtual #126                // Method org/apache/htrace/core/TraceScope.close:()V
      58: goto          104
      61: astore        4
      63: aload         4
      65: astore_3
      66: aload         4
      68: athrow
      69: astore        5
      71: aload_2
      72: ifnull        101
      75: aload_3
      76: ifnull        97
      79: aload_2
      80: invokevirtual #126                // Method org/apache/htrace/core/TraceScope.close:()V
      83: goto          101
      86: astore        6
      88: aload_3
      89: aload         6
      91: invokevirtual #128                // Method java/lang/Throwable.addSuppressed:(Ljava/lang/Throwable;)V
      94: goto          101
      97: aload_2
      98: invokevirtual #126                // Method org/apache/htrace/core/TraceScope.close:()V
     101: aload         5
     103: athrow
     104: return
    Exception table:
       from    to  target type
          36    40    43   Class java/lang/Throwable
          23    28    61   Class java/lang/Throwable
          23    28    69   any
          79    83    86   Class java/lang/Throwable
          61    71    69   any

  private boolean exceptionNeedsCleanup(java.io.IOException);
    Code:
       0: aload_1
       1: instanceof    #104                // class org/apache/hadoop/hdfs/protocol/DSQuotaExceededException
       4: ifne          14
       7: aload_1
       8: instanceof    #105                // class org/apache/hadoop/hdfs/protocol/QuotaByStorageTypeExceededException
      11: ifeq          18
      14: iconst_1
      15: goto          19
      18: iconst_0
      19: ireturn

  private void cleanupAndRethrowIOException(java.io.IOException) throws java.io.IOException;
    Code:
       0: aload_0
       1: aload_1
       2: invokespecial #246                // Method exceptionNeedsCleanup:(Ljava/io/IOException;)Z
       5: ifeq          39
       8: new           #217                // class org/apache/hadoop/io/MultipleIOException$Builder
      11: dup
      12: invokespecial #218                // Method org/apache/hadoop/io/MultipleIOException$Builder."<init>":()V
      15: astore_2
      16: aload_2
      17: aload_1
      18: invokevirtual #222                // Method org/apache/hadoop/io/MultipleIOException$Builder.add:(Ljava/lang/Throwable;)V
      21: aload_0
      22: invokespecial #240                // Method completeFile:()V
      25: goto          39
      28: astore_3
      29: aload_2
      30: aload_3
      31: invokevirtual #222                // Method org/apache/hadoop/io/MultipleIOException$Builder.add:(Ljava/lang/Throwable;)V
      34: aload_2
      35: invokevirtual #223                // Method org/apache/hadoop/io/MultipleIOException$Builder.build:()Ljava/io/IOException;
      38: athrow
      39: aload_1
      40: athrow
    Exception table:
       from    to  target type
          21    25    28   Class java/io/IOException

  protected void completeFile(org.apache.hadoop.hdfs.protocol.ExtendedBlock) throws java.io.IOException;
    Code:
       0: invokestatic  #247                // Method org/apache/hadoop/util/Time.monotonicNow:()J
       3: lstore_2
       4: aload_0
       5: getfield      #39                 // Field dfsClient:Lorg/apache/hadoop/hdfs/DFSClient;
       8: invokevirtual #77                 // Method org/apache/hadoop/hdfs/DFSClient.getConf:()Lorg/apache/hadoop/hdfs/client/impl/DfsClientConf;
      11: astore        4
      13: aload         4
      15: invokevirtual #248                // Method org/apache/hadoop/hdfs/client/impl/DfsClientConf.getBlockWriteLocateFollowingInitialDelayMs:()I
      18: i2l
      19: lstore        5
      21: iconst_0
      22: istore        7
      24: aload         4
      26: invokevirtual #249                // Method org/apache/hadoop/hdfs/client/impl/DfsClientConf.getNumBlockWriteLocateFollowingRetry:()I
      29: istore        8
      31: iload         7
      33: ifne          287
      36: aload_0
      37: getfield      #39                 // Field dfsClient:Lorg/apache/hadoop/hdfs/DFSClient;
      40: getfield      #95                 // Field org/apache/hadoop/hdfs/DFSClient.namenode:Lorg/apache/hadoop/hdfs/protocol/ClientProtocol;
      43: aload_0
      44: getfield      #40                 // Field src:Ljava/lang/String;
      47: aload_0
      48: getfield      #39                 // Field dfsClient:Lorg/apache/hadoop/hdfs/DFSClient;
      51: getfield      #96                 // Field org/apache/hadoop/hdfs/DFSClient.clientName:Ljava/lang/String;
      54: aload_1
      55: aload_0
      56: getfield      #42                 // Field fileId:J
      59: invokeinterface #250,  6          // InterfaceMethod org/apache/hadoop/hdfs/protocol/ClientProtocol.complete:(Ljava/lang/String;Ljava/lang/String;Lorg/apache/hadoop/hdfs/protocol/ExtendedBlock;J)Z
      64: istore        7
      66: iload         7
      68: ifne          31
      71: aload         4
      73: invokevirtual #220                // Method org/apache/hadoop/hdfs/client/impl/DfsClientConf.getHdfsTimeout:()I
      76: istore        9
      78: aload_0
      79: getfield      #39                 // Field dfsClient:Lorg/apache/hadoop/hdfs/DFSClient;
      82: getfield      #251                // Field org/apache/hadoop/hdfs/DFSClient.clientRunning:Z
      85: ifeq          105
      88: iload         9
      90: ifle          162
      93: lload_2
      94: iload         9
      96: i2l
      97: ladd
      98: invokestatic  #247                // Method org/apache/hadoop/util/Time.monotonicNow:()J
     101: lcmp
     102: ifge          162
     105: new           #6                  // class java/lang/StringBuilder
     108: dup
     109: invokespecial #7                  // Method java/lang/StringBuilder."<init>":()V
     112: ldc           #252                // String Unable to close file because dfsclient  was unable to contact the HDFS servers. clientRunning
     114: invokevirtual #9                  // Method java/lang/StringBuilder.append:(Ljava/lang/String;)Ljava/lang/StringBuilder;
     117: aload_0
     118: getfield      #39                 // Field dfsClient:Lorg/apache/hadoop/hdfs/DFSClient;
     121: getfield      #251                // Field org/apache/hadoop/hdfs/DFSClient.clientRunning:Z
     124: invokevirtual #253                // Method java/lang/StringBuilder.append:(Z)Ljava/lang/StringBuilder;
     127: ldc           #254                // String  hdfsTimeout
     129: invokevirtual #9                  // Method java/lang/StringBuilder.append:(Ljava/lang/String;)Ljava/lang/StringBuilder;
     132: iload         9
     134: invokevirtual #68                 // Method java/lang/StringBuilder.append:(I)Ljava/lang/StringBuilder;
     137: invokevirtual #11                 // Method java/lang/StringBuilder.toString:()Ljava/lang/String;
     140: astore        10
     142: getstatic     #61                 // Field org/apache/hadoop/hdfs/DFSClient.LOG:Lorg/slf4j/Logger;
     145: aload         10
     147: invokeinterface #255,  2          // InterfaceMethod org/slf4j/Logger.info:(Ljava/lang/String;)V
     152: new           #116                // class java/io/IOException
     155: dup
     156: aload         10
     158: invokespecial #139                // Method java/io/IOException."<init>":(Ljava/lang/String;)V
     161: athrow
     162: iload         8
     164: ifne          201
     167: new           #116                // class java/io/IOException
     170: dup
     171: new           #6                  // class java/lang/StringBuilder
     174: dup
     175: invokespecial #7                  // Method java/lang/StringBuilder."<init>":()V
     178: ldc_w         #256                // String Unable to close file because the last block
     181: invokevirtual #9                  // Method java/lang/StringBuilder.append:(Ljava/lang/String;)Ljava/lang/StringBuilder;
     184: aload_1
     185: invokevirtual #257                // Method java/lang/StringBuilder.append:(Ljava/lang/Object;)Ljava/lang/StringBuilder;
     188: ldc_w         #258                // String  does not have enough number of replicas.
     191: invokevirtual #9                  // Method java/lang/StringBuilder.append:(Ljava/lang/String;)Ljava/lang/StringBuilder;
     194: invokevirtual #11                 // Method java/lang/StringBuilder.toString:()Ljava/lang/String;
     197: invokespecial #139                // Method java/io/IOException."<init>":(Ljava/lang/String;)V
     200: athrow
     201: iinc          8, -1
     204: lload         5
     206: invokestatic  #259                // Method java/lang/Thread.sleep:(J)V
     209: lload         5
     211: ldc2_w        #260                // long 2l
     214: lmul
     215: lstore        5
     217: invokestatic  #247                // Method org/apache/hadoop/util/Time.monotonicNow:()J
     220: lload_2
     221: lsub
     222: ldc2_w        #262                // long 5000l
     225: lcmp
     226: ifle          266
     229: getstatic     #61                 // Field org/apache/hadoop/hdfs/DFSClient.LOG:Lorg/slf4j/Logger;
     232: new           #6                  // class java/lang/StringBuilder
     235: dup
     236: invokespecial #7                  // Method java/lang/StringBuilder."<init>":()V
     239: ldc_w         #264                // String Could not complete
     242: invokevirtual #9                  // Method java/lang/StringBuilder.append:(Ljava/lang/String;)Ljava/lang/StringBuilder;
     245: aload_0
     246: getfield      #40                 // Field src:Ljava/lang/String;
     249: invokevirtual #9                  // Method java/lang/StringBuilder.append:(Ljava/lang/String;)Ljava/lang/StringBuilder;
     252: ldc_w         #265                // String  retrying...
     255: invokevirtual #9                  // Method java/lang/StringBuilder.append:(Ljava/lang/String;)Ljava/lang/StringBuilder;
     258: invokevirtual #11                 // Method java/lang/StringBuilder.toString:()Ljava/lang/String;
     261: invokeinterface #255,  2          // InterfaceMethod org/slf4j/Logger.info:(Ljava/lang/String;)V
     266: goto          284
     269: astore        10
     271: getstatic     #61                 // Field org/apache/hadoop/hdfs/DFSClient.LOG:Lorg/slf4j/Logger;
     274: ldc_w         #266                // String Caught exception
     277: aload         10
     279: invokeinterface #209,  3          // InterfaceMethod org/slf4j/Logger.warn:(Ljava/lang/String;Ljava/lang/Throwable;)V
     284: goto          31
     287: return
    Exception table:
       from    to  target type
         162   266   269   Class java/lang/InterruptedException

  public void setArtificialSlowdown(long);
    Code:
       0: aload_0
       1: invokevirtual #18                 // Method getStreamer:()Lorg/apache/hadoop/hdfs/DataStreamer;
       4: lload_1
       5: invokevirtual #267                // Method org/apache/hadoop/hdfs/DataStreamer.setArtificialSlowdown:(J)V
       8: return

  public synchronized void setChunksPerPacket(int);
    Code:
       0: aload_0
       1: aload_0
       2: getfield      #35                 // Field chunksPerPacket:I
       5: iload_1
       6: invokestatic  #142                // Method java/lang/Math.min:(II)I
       9: putfield      #35                 // Field chunksPerPacket:I
      12: aload_0
      13: aload_0
      14: getfield      #65                 // Field bytesPerChecksum:I
      17: aload_0
      18: invokevirtual #15                 // Method getChecksumSize:()I
      21: iadd
      22: aload_0
      23: getfield      #35                 // Field chunksPerPacket:I
      26: imul
      27: putfield      #34                 // Field packetSize:I
      30: return

  public long getInitialLen();
    Code:
       0: aload_0
       1: getfield      #37                 // Field initialFileSize:J
       4: lreturn

  protected java.util.EnumSet<org.apache.hadoop.hdfs.AddBlockFlag> getAddBlockFlags();
    Code:
       0: aload_0
       1: getfield      #54                 // Field addBlockFlags:Ljava/util/EnumSet;
       4: areturn

  public org.apache.hadoop.fs.FileEncryptionInfo getFileEncryptionInfo();
    Code:
       0: aload_0
       1: getfield      #47                 // Field fileEncryptionInfo:Lorg/apache/hadoop/fs/FileEncryptionInfo;
       4: areturn

  synchronized org.apache.hadoop.security.token.Token<org.apache.hadoop.hdfs.security.token.block.BlockTokenIdentifier> getBlockToken();
    Code:
       0: aload_0
       1: invokevirtual #18                 // Method getStreamer:()Lorg/apache/hadoop/hdfs/DataStreamer;
       4: invokevirtual #268                // Method org/apache/hadoop/hdfs/DataStreamer.getBlockToken:()Lorg/apache/hadoop/security/token/Token;
       7: areturn

  protected long flushInternalWithoutWaitingAck() throws java.io.IOException;
    Code:
       0: aload_0
       1: dup
       2: astore_3
       3: monitorenter
       4: aload_0
       5: getfield      #39                 // Field dfsClient:Lorg/apache/hadoop/hdfs/DFSClient;
       8: invokevirtual #161                // Method org/apache/hadoop/hdfs/DFSClient.checkOpen:()V
      11: aload_0
      12: invokevirtual #162                // Method checkClosed:()V
      15: aload_0
      16: invokevirtual #18                 // Method getStreamer:()Lorg/apache/hadoop/hdfs/DataStreamer;
      19: aload_0
      20: getfield      #33                 // Field currentPacket:Lorg/apache/hadoop/hdfs/DFSPacket;
      23: invokevirtual #269                // Method org/apache/hadoop/hdfs/DataStreamer.queuePacket:(Lorg/apache/hadoop/hdfs/DFSPacket;)V
      26: aload_0
      27: aconst_null
      28: putfield      #33                 // Field currentPacket:Lorg/apache/hadoop/hdfs/DFSPacket;
      31: aload_0
      32: invokevirtual #18                 // Method getStreamer:()Lorg/apache/hadoop/hdfs/DataStreamer;
      35: invokevirtual #200                // Method org/apache/hadoop/hdfs/DataStreamer.getLastQueuedSeqno:()J
      38: lstore_1
      39: aload_3
      40: monitorexit
      41: goto          51
      44: astore        4
      46: aload_3
      47: monitorexit
      48: aload         4
      50: athrow
      51: lload_1
      52: lreturn
    Exception table:
       from    to  target type
           4    41    44   any
          44    48    44   any

  public void setDropBehind(java.lang.Boolean) throws java.io.IOException;
    Code:
       0: aload_0
       1: getfield      #51                 // Field cachingStrategy:Ljava/util/concurrent/atomic/AtomicReference;
       4: invokevirtual #270                // Method java/util/concurrent/atomic/AtomicReference.get:()Ljava/lang/Object;
       7: checkcast     #271                // class org/apache/hadoop/hdfs/server/datanode/CachingStrategy
      10: astore_2
      11: new           #272                // class org/apache/hadoop/hdfs/server/datanode/CachingStrategy$Builder
      14: dup
      15: aload_2
      16: invokespecial #273                // Method org/apache/hadoop/hdfs/server/datanode/CachingStrategy$Builder."<init>":(Lorg/apache/hadoop/hdfs/server/datanode/CachingStrategy;)V
      19: aload_1
      20: invokevirtual #274                // Method org/apache/hadoop/hdfs/server/datanode/CachingStrategy$Builder.setDropBehind:(Ljava/lang/Boolean;)Lorg/apache/hadoop/hdfs/server/datanode/CachingStrategy$Builder;
      23: invokevirtual #275                // Method org/apache/hadoop/hdfs/server/datanode/CachingStrategy$Builder.build:()Lorg/apache/hadoop/hdfs/server/datanode/CachingStrategy;
      26: astore_3
      27: aload_0
      28: getfield      #51                 // Field cachingStrategy:Ljava/util/concurrent/atomic/AtomicReference;
      31: aload_2
      32: aload_3
      33: invokevirtual #276                // Method java/util/concurrent/atomic/AtomicReference.compareAndSet:(Ljava/lang/Object;Ljava/lang/Object;)Z
      36: ifeq          0
      39: return

  org.apache.hadoop.hdfs.protocol.ExtendedBlock getBlock();
    Code:
       0: aload_0
       1: invokevirtual #18                 // Method getStreamer:()Lorg/apache/hadoop/hdfs/DataStreamer;
       4: invokevirtual #204                // Method org/apache/hadoop/hdfs/DataStreamer.getBlock:()Lorg/apache/hadoop/hdfs/protocol/ExtendedBlock;
       7: areturn

  public long getFileId();
    Code:
       0: aload_0
       1: getfield      #42                 // Field fileId:J
       4: lreturn

  java.lang.String getSrc();
    Code:
       0: aload_0
       1: getfield      #40                 // Field src:Ljava/lang/String;
       4: areturn

  protected org.apache.hadoop.hdfs.DataStreamer getStreamer();
    Code:
       0: aload_0
       1: getfield      #91                 // Field streamer:Lorg/apache/hadoop/hdfs/DataStreamer;
       4: areturn

  public java.lang.String toString();
    Code:
       0: new           #6                  // class java/lang/StringBuilder
       3: dup
       4: invokespecial #7                  // Method java/lang/StringBuilder."<init>":()V
       7: aload_0
       8: invokevirtual #277                // Method java/lang/Object.getClass:()Ljava/lang/Class;
      11: invokevirtual #278                // Method java/lang/Class.getSimpleName:()Ljava/lang/String;
      14: invokevirtual #9                  // Method java/lang/StringBuilder.append:(Ljava/lang/String;)Ljava/lang/StringBuilder;
      17: ldc_w         #279                // String :
      20: invokevirtual #9                  // Method java/lang/StringBuilder.append:(Ljava/lang/String;)Ljava/lang/StringBuilder;
      23: aload_0
      24: getfield      #91                 // Field streamer:Lorg/apache/hadoop/hdfs/DataStreamer;
      27: invokevirtual #257                // Method java/lang/StringBuilder.append:(Ljava/lang/Object;)Ljava/lang/StringBuilder;
      30: invokevirtual #11                 // Method java/lang/StringBuilder.toString:()Ljava/lang/String;
      33: areturn

  static org.apache.hadoop.hdfs.protocol.LocatedBlock addBlock(org.apache.hadoop.hdfs.protocol.DatanodeInfo[], org.apache.hadoop.hdfs.DFSClient, java.lang.String, org.apache.hadoop.hdfs.protocol.ExtendedBlock, long, java.lang.String[], java.util.EnumSet<org.apache.hadoop.hdfs.AddBlockFlag>) throws java.io.IOException;
    Code:
       0: aload_1
       1: invokevirtual #77                 // Method org/apache/hadoop/hdfs/DFSClient.getConf:()Lorg/apache/hadoop/hdfs/client/impl/DfsClientConf;
       4: astore        8
       6: aload         8
       8: invokevirtual #249                // Method org/apache/hadoop/hdfs/client/impl/DfsClientConf.getNumBlockWriteLocateFollowingRetry:()I
      11: istore        9
      13: aload         8
      15: invokevirtual #248                // Method org/apache/hadoop/hdfs/client/impl/DfsClientConf.getBlockWriteLocateFollowingInitialDelayMs:()I
      18: i2l
      19: lstore        10
      21: invokestatic  #247                // Method org/apache/hadoop/util/Time.monotonicNow:()J
      24: lstore        12
      26: aload_1
      27: getfield      #95                 // Field org/apache/hadoop/hdfs/DFSClient.namenode:Lorg/apache/hadoop/hdfs/protocol/ClientProtocol;
      30: aload_2
      31: aload_1
      32: getfield      #96                 // Field org/apache/hadoop/hdfs/DFSClient.clientName:Ljava/lang/String;
      35: aload_3
      36: aload_0
      37: lload         4
      39: aload         6
      41: aload         7
      43: invokeinterface #280,  9          // InterfaceMethod org/apache/hadoop/hdfs/protocol/ClientProtocol.addBlock:(Ljava/lang/String;Ljava/lang/String;Lorg/apache/hadoop/hdfs/protocol/ExtendedBlock;[Lorg/apache/hadoop/hdfs/protocol/DatanodeInfo;J[Ljava/lang/String;Ljava/util/EnumSet;)Lorg/apache/hadoop/hdfs/protocol/LocatedBlock;
      48: areturn
      49: astore        14
      51: aload         14
      53: bipush        6
      55: anewarray     #102                // class java/lang/Class
      58: dup
      59: iconst_0
      60: ldc           #107                // class java/io/FileNotFoundException
      62: aastore
      63: dup
      64: iconst_1
      65: ldc           #103                // class org/apache/hadoop/security/AccessControlException
      67: aastore
      68: dup
      69: iconst_2
      70: ldc           #109                // class org/apache/hadoop/hdfs/protocol/NSQuotaExceededException
      72: aastore
      73: dup
      74: iconst_3
      75: ldc           #104                // class org/apache/hadoop/hdfs/protocol/DSQuotaExceededException
      77: aastore
      78: dup
      79: iconst_4
      80: ldc           #105                // class org/apache/hadoop/hdfs/protocol/QuotaByStorageTypeExceededException
      82: aastore
      83: dup
      84: iconst_5
      85: ldc           #112                // class org/apache/hadoop/hdfs/protocol/UnresolvedPathException
      87: aastore
      88: invokevirtual #115                // Method org/apache/hadoop/ipc/RemoteException.unwrapRemoteException:([Ljava/lang/Class;)Ljava/io/IOException;
      91: astore        15
      93: aload         15
      95: aload         14
      97: if_acmpeq     103
     100: aload         15
     102: athrow
     103: ldc_w         #281                // class org/apache/hadoop/hdfs/server/namenode/NotReplicatedYetException
     106: invokevirtual #282                // Method java/lang/Class.getName:()Ljava/lang/String;
     109: aload         14
     111: invokevirtual #283                // Method org/apache/hadoop/ipc/RemoteException.getClassName:()Ljava/lang/String;
     114: invokevirtual #186                // Method java/lang/String.equals:(Ljava/lang/Object;)Z
     117: ifeq          273
     120: iload         9
     122: ifne          128
     125: aload         14
     127: athrow
     128: iinc          9, -1
     131: getstatic     #82                 // Field LOG:Lorg/slf4j/Logger;
     134: ldc_w         #284                // String Exception while adding a block
     137: aload         14
     139: invokeinterface #285,  3          // InterfaceMethod org/slf4j/Logger.info:(Ljava/lang/String;Ljava/lang/Throwable;)V
     144: invokestatic  #247                // Method org/apache/hadoop/util/Time.monotonicNow:()J
     147: lload         12
     149: lsub
     150: lstore        16
     152: lload         16
     154: ldc2_w        #262                // long 5000l
     157: lcmp
     158: ifle          200
     161: getstatic     #82                 // Field LOG:Lorg/slf4j/Logger;
     164: new           #6                  // class java/lang/StringBuilder
     167: dup
     168: invokespecial #7                  // Method java/lang/StringBuilder."<init>":()V
     171: ldc_w         #286                // String Waiting for replication for
     174: invokevirtual #9                  // Method java/lang/StringBuilder.append:(Ljava/lang/String;)Ljava/lang/StringBuilder;
     177: lload         16
     179: ldc2_w        #287                // long 1000l
     182: ldiv
     183: invokevirtual #10                 // Method java/lang/StringBuilder.append:(J)Ljava/lang/StringBuilder;
     186: ldc_w         #289                // String  seconds
     189: invokevirtual #9                  // Method java/lang/StringBuilder.append:(Ljava/lang/String;)Ljava/lang/StringBuilder;
     192: invokevirtual #11                 // Method java/lang/StringBuilder.toString:()Ljava/lang/String;
     195: invokeinterface #255,  2          // InterfaceMethod org/slf4j/Logger.info:(Ljava/lang/String;)V
     200: getstatic     #82                 // Field LOG:Lorg/slf4j/Logger;
     203: new           #6                  // class java/lang/StringBuilder
     206: dup
     207: invokespecial #7                  // Method java/lang/StringBuilder."<init>":()V
     210: ldc_w         #290                // String NotReplicatedYetException sleeping
     213: invokevirtual #9                  // Method java/lang/StringBuilder.append:(Ljava/lang/String;)Ljava/lang/StringBuilder;
     216: aload_2
     217: invokevirtual #9                  // Method java/lang/StringBuilder.append:(Ljava/lang/String;)Ljava/lang/StringBuilder;
     220: ldc_w         #291                // String  retries left
     223: invokevirtual #9                  // Method java/lang/StringBuilder.append:(Ljava/lang/String;)Ljava/lang/StringBuilder;
     226: iload         9
     228: invokevirtual #68                 // Method java/lang/StringBuilder.append:(I)Ljava/lang/StringBuilder;
     231: invokevirtual #11                 // Method java/lang/StringBuilder.toString:()Ljava/lang/String;
     234: invokeinterface #292,  2          // InterfaceMethod org/slf4j/Logger.warn:(Ljava/lang/String;)V
     239: lload         10
     241: invokestatic  #259                // Method java/lang/Thread.sleep:(J)V
     244: lload         10
     246: ldc2_w        #260                // long 2l
     249: lmul
     250: lstore        10
     252: goto          270
     255: astore        18
     257: getstatic     #82                 // Field LOG:Lorg/slf4j/Logger;
     260: ldc_w         #293                // String Caught exception
     263: aload         18
     265: invokeinterface #209,  3          // InterfaceMethod org/slf4j/Logger.warn:(Ljava/lang/String;Ljava/lang/Throwable;)V
     270: goto          276
     273: aload         14
     275: athrow
     276: goto          26
    Exception table:
       from    to  target type
          26    48    49   Class org/apache/hadoop/ipc/RemoteException
         200   252   255   Class java/lang/InterruptedException

  static {};
    Code:
       0: ldc           #94                 // class org/apache/hadoop/hdfs/DFSOutputStream
       2: invokevirtual #294                // Method java/lang/Class.desiredAssertionStatus:()Z
       5: ifne          12
       8: iconst_1
       9: goto          13
      12: iconst_0
      13: putstatic     #196                // Field $assertionsDisabled:Z
      16: ldc           #94                 // class org/apache/hadoop/hdfs/DFSOutputStream
      18: invokestatic  #295                // Method org/slf4j/LoggerFactory.getLogger:(Ljava/lang/Class;)Lorg/slf4j/Logger;
      21: putstatic     #82                 // Field LOG:Lorg/slf4j/Logger;
      24: invokestatic  #296                // Method org/apache/hadoop/crypto/CryptoProtocolVersion.supported:()[Lorg/apache/hadoop/crypto/CryptoProtocolVersion;
      27: putstatic     #99                 // Field SUPPORTED_CRYPTO_VERSIONS:[Lorg/apache/hadoop/crypto/CryptoProtocolVersion;
      30: return
}
