Compiled from "DistributedFileSystem.java"
class org.apache.hadoop.hdfs.DistributedFileSystem$21 extends org.apache.hadoop.fs.FileSystemLinkResolver<org.apache.hadoop.fs.QuotaUsage> {
  final org.apache.hadoop.hdfs.DistributedFileSystem this$0;

  org.apache.hadoop.hdfs.DistributedFileSystem$21(org.apache.hadoop.hdfs.DistributedFileSystem);
    Code:
       0: aload_0
       1: aload_1
       2: putfield      #1                  // Field this$0:Lorg/apache/hadoop/hdfs/DistributedFileSystem;
       5: aload_0
       6: invokespecial #2                  // Method org/apache/hadoop/fs/FileSystemLinkResolver."<init>":()V
       9: return

  public org.apache.hadoop.fs.QuotaUsage doCall(org.apache.hadoop.fs.Path) throws java.io.IOException, org.apache.hadoop.fs.UnresolvedLinkException;
    Code:
       0: aload_0
       1: getfield      #1                  // Field this$0:Lorg/apache/hadoop/hdfs/DistributedFileSystem;
       4: getfield      #3                  // Field org/apache/hadoop/hdfs/DistributedFileSystem.dfs:Lorg/apache/hadoop/hdfs/DFSClient;
       7: aload_0
       8: getfield      #1                  // Field this$0:Lorg/apache/hadoop/hdfs/DistributedFileSystem;
      11: aload_1
      12: invokevirtual #4                  // Method org/apache/hadoop/hdfs/DistributedFileSystem.getPathName:(Lorg/apache/hadoop/fs/Path;)Ljava/lang/String;
      15: invokevirtual #5                  // Method org/apache/hadoop/hdfs/DFSClient.getQuotaUsage:(Ljava/lang/String;)Lorg/apache/hadoop/fs/QuotaUsage;
      18: areturn

  public org.apache.hadoop.fs.QuotaUsage next(org.apache.hadoop.fs.FileSystem, org.apache.hadoop.fs.Path) throws java.io.IOException;
    Code:
       0: aload_1
       1: aload_2
       2: invokevirtual #6                  // Method org/apache/hadoop/fs/FileSystem.getQuotaUsage:(Lorg/apache/hadoop/fs/Path;)Lorg/apache/hadoop/fs/QuotaUsage;
       5: areturn

  public java.lang.Object next(org.apache.hadoop.fs.FileSystem, org.apache.hadoop.fs.Path) throws java.io.IOException;
    Code:
       0: aload_0
       1: aload_1
       2: aload_2
       3: invokevirtual #7                  // Method next:(Lorg/apache/hadoop/fs/FileSystem;Lorg/apache/hadoop/fs/Path;)Lorg/apache/hadoop/fs/QuotaUsage;
       6: areturn

  public java.lang.Object doCall(org.apache.hadoop.fs.Path) throws java.io.IOException, org.apache.hadoop.fs.UnresolvedLinkException;
    Code:
       0: aload_0
       1: aload_1
       2: invokevirtual #8                  // Method doCall:(Lorg/apache/hadoop/fs/Path;)Lorg/apache/hadoop/fs/QuotaUsage;
       5: areturn
}
