Compiled from "PeerCache.java"
class org.apache.hadoop.hdfs.PeerCache$1 implements java.lang.Runnable {
  final org.apache.hadoop.hdfs.PeerCache this$0;

  org.apache.hadoop.hdfs.PeerCache$1(org.apache.hadoop.hdfs.PeerCache);
    Code:
       0: aload_0
       1: aload_1
       2: putfield      #1                  // Field this$0:Lorg/apache/hadoop/hdfs/PeerCache;
       5: aload_0
       6: invokespecial #2                  // Method java/lang/Object."<init>":()V
       9: return

  public void run();
    Code:
       0: aload_0
       1: getfield      #1                  // Field this$0:Lorg/apache/hadoop/hdfs/PeerCache;
       4: invokestatic  #3                  // Method org/apache/hadoop/hdfs/PeerCache.access$000:(Lorg/apache/hadoop/hdfs/PeerCache;)V
       7: aload_0
       8: getfield      #1                  // Field this$0:Lorg/apache/hadoop/hdfs/PeerCache;
      11: invokevirtual #4                  // Method org/apache/hadoop/hdfs/PeerCache.clear:()V
      14: goto          38
      17: astore_1
      18: aload_0
      19: getfield      #1                  // Field this$0:Lorg/apache/hadoop/hdfs/PeerCache;
      22: invokevirtual #4                  // Method org/apache/hadoop/hdfs/PeerCache.clear:()V
      25: goto          38
      28: astore_2
      29: aload_0
      30: getfield      #1                  // Field this$0:Lorg/apache/hadoop/hdfs/PeerCache;
      33: invokevirtual #4                  // Method org/apache/hadoop/hdfs/PeerCache.clear:()V
      36: aload_2
      37: athrow
      38: return
    Exception table:
       from    to  target type
           0     7    17   Class java/lang/InterruptedException
           0     7    28   any

  public java.lang.String toString();
    Code:
       0: aload_0
       1: getfield      #1                  // Field this$0:Lorg/apache/hadoop/hdfs/PeerCache;
       4: invokestatic  #6                  // Method java/lang/String.valueOf:(Ljava/lang/Object;)Ljava/lang/String;
       7: areturn
}
