Compiled from "ReadStatistics.java"
public class org.apache.hadoop.hdfs.ReadStatistics {
  private long totalBytesRead;

  private long totalLocalBytesRead;

  private long totalShortCircuitBytesRead;

  private long totalZeroCopyBytesRead;

  private org.apache.hadoop.hdfs.protocol.BlockType blockType;

  private long totalEcDecodingTimeMillis;

  public org.apache.hadoop.hdfs.ReadStatistics();
    Code:
       0: aload_0
       1: invokespecial #1                  // Method java/lang/Object."<init>":()V
       4: aload_0
       5: getstatic     #2                  // Field org/apache/hadoop/hdfs/protocol/BlockType.CONTIGUOUS:Lorg/apache/hadoop/hdfs/protocol/BlockType;
       8: putfield      #3                  // Field blockType:Lorg/apache/hadoop/hdfs/protocol/BlockType;
      11: aload_0
      12: invokevirtual #4                  // Method clear:()V
      15: return

  public org.apache.hadoop.hdfs.ReadStatistics(org.apache.hadoop.hdfs.ReadStatistics);
    Code:
       0: aload_0
       1: invokespecial #1                  // Method java/lang/Object."<init>":()V
       4: aload_0
       5: getstatic     #2                  // Field org/apache/hadoop/hdfs/protocol/BlockType.CONTIGUOUS:Lorg/apache/hadoop/hdfs/protocol/BlockType;
       8: putfield      #3                  // Field blockType:Lorg/apache/hadoop/hdfs/protocol/BlockType;
      11: aload_0
      12: aload_1
      13: invokevirtual #5                  // Method getTotalBytesRead:()J
      16: putfield      #6                  // Field totalBytesRead:J
      19: aload_0
      20: aload_1
      21: invokevirtual #7                  // Method getTotalLocalBytesRead:()J
      24: putfield      #8                  // Field totalLocalBytesRead:J
      27: aload_0
      28: aload_1
      29: invokevirtual #9                  // Method getTotalShortCircuitBytesRead:()J
      32: putfield      #10                 // Field totalShortCircuitBytesRead:J
      35: aload_0
      36: aload_1
      37: invokevirtual #11                 // Method getTotalZeroCopyBytesRead:()J
      40: putfield      #12                 // Field totalZeroCopyBytesRead:J
      43: return

  public synchronized long getTotalBytesRead();
    Code:
       0: aload_0
       1: getfield      #6                  // Field totalBytesRead:J
       4: lreturn

  public synchronized long getTotalLocalBytesRead();
    Code:
       0: aload_0
       1: getfield      #8                  // Field totalLocalBytesRead:J
       4: lreturn

  public synchronized long getTotalShortCircuitBytesRead();
    Code:
       0: aload_0
       1: getfield      #10                 // Field totalShortCircuitBytesRead:J
       4: lreturn

  public synchronized long getTotalZeroCopyBytesRead();
    Code:
       0: aload_0
       1: getfield      #12                 // Field totalZeroCopyBytesRead:J
       4: lreturn

  public synchronized long getRemoteBytesRead();
    Code:
       0: aload_0
       1: getfield      #6                  // Field totalBytesRead:J
       4: aload_0
       5: getfield      #8                  // Field totalLocalBytesRead:J
       8: lsub
       9: lreturn

  public synchronized org.apache.hadoop.hdfs.protocol.BlockType getBlockType();
    Code:
       0: aload_0
       1: getfield      #3                  // Field blockType:Lorg/apache/hadoop/hdfs/protocol/BlockType;
       4: areturn

  public synchronized long getTotalEcDecodingTimeMillis();
    Code:
       0: aload_0
       1: getfield      #13                 // Field totalEcDecodingTimeMillis:J
       4: lreturn

  public synchronized void addRemoteBytes(long);
    Code:
       0: aload_0
       1: dup
       2: getfield      #6                  // Field totalBytesRead:J
       5: lload_1
       6: ladd
       7: putfield      #6                  // Field totalBytesRead:J
      10: return

  public synchronized void addLocalBytes(long);
    Code:
       0: aload_0
       1: dup
       2: getfield      #6                  // Field totalBytesRead:J
       5: lload_1
       6: ladd
       7: putfield      #6                  // Field totalBytesRead:J
      10: aload_0
      11: dup
      12: getfield      #8                  // Field totalLocalBytesRead:J
      15: lload_1
      16: ladd
      17: putfield      #8                  // Field totalLocalBytesRead:J
      20: return

  public synchronized void addShortCircuitBytes(long);
    Code:
       0: aload_0
       1: dup
       2: getfield      #6                  // Field totalBytesRead:J
       5: lload_1
       6: ladd
       7: putfield      #6                  // Field totalBytesRead:J
      10: aload_0
      11: dup
      12: getfield      #8                  // Field totalLocalBytesRead:J
      15: lload_1
      16: ladd
      17: putfield      #8                  // Field totalLocalBytesRead:J
      20: aload_0
      21: dup
      22: getfield      #10                 // Field totalShortCircuitBytesRead:J
      25: lload_1
      26: ladd
      27: putfield      #10                 // Field totalShortCircuitBytesRead:J
      30: return

  public synchronized void addZeroCopyBytes(long);
    Code:
       0: aload_0
       1: dup
       2: getfield      #6                  // Field totalBytesRead:J
       5: lload_1
       6: ladd
       7: putfield      #6                  // Field totalBytesRead:J
      10: aload_0
      11: dup
      12: getfield      #8                  // Field totalLocalBytesRead:J
      15: lload_1
      16: ladd
      17: putfield      #8                  // Field totalLocalBytesRead:J
      20: aload_0
      21: dup
      22: getfield      #10                 // Field totalShortCircuitBytesRead:J
      25: lload_1
      26: ladd
      27: putfield      #10                 // Field totalShortCircuitBytesRead:J
      30: aload_0
      31: dup
      32: getfield      #12                 // Field totalZeroCopyBytesRead:J
      35: lload_1
      36: ladd
      37: putfield      #12                 // Field totalZeroCopyBytesRead:J
      40: return

  public synchronized void addErasureCodingDecodingTime(long);
    Code:
       0: aload_0
       1: dup
       2: getfield      #13                 // Field totalEcDecodingTimeMillis:J
       5: lload_1
       6: ladd
       7: putfield      #13                 // Field totalEcDecodingTimeMillis:J
      10: return

  synchronized void setBlockType(org.apache.hadoop.hdfs.protocol.BlockType);
    Code:
       0: aload_0
       1: aload_1
       2: putfield      #3                  // Field blockType:Lorg/apache/hadoop/hdfs/protocol/BlockType;
       5: return

  public synchronized void clear();
    Code:
       0: aload_0
       1: lconst_0
       2: putfield      #6                  // Field totalBytesRead:J
       5: aload_0
       6: lconst_0
       7: putfield      #8                  // Field totalLocalBytesRead:J
      10: aload_0
      11: lconst_0
      12: putfield      #10                 // Field totalShortCircuitBytesRead:J
      15: aload_0
      16: lconst_0
      17: putfield      #12                 // Field totalZeroCopyBytesRead:J
      20: aload_0
      21: lconst_0
      22: putfield      #13                 // Field totalEcDecodingTimeMillis:J
      25: return
}
