Compiled from "PostCacheEventFilter.java"
public class org.infinispan.notifications.cachelistener.filter.PostCacheEventFilter<K, V> implements org.infinispan.notifications.cachelistener.filter.CacheEventFilter<K, V> {
  public org.infinispan.notifications.cachelistener.filter.PostCacheEventFilter();
    Code:
       0: aload_0
       1: invokespecial #1                  // Method java/lang/Object."<init>":()V
       4: return

  public boolean accept(K, V, org.infinispan.metadata.Metadata, V, org.infinispan.metadata.Metadata, org.infinispan.notifications.cachelistener.filter.EventType);
    Code:
       0: aload         6
       2: invokevirtual #2                  // Method org/infinispan/notifications/cachelistener/filter/EventType.isPreEvent:()Z
       5: ifne          12
       8: iconst_1
       9: goto          13
      12: iconst_0
      13: ireturn
}
