Compiled from "TaglibFactory.java"
class freemarker.ext.jsp.TaglibFactory$WebXmlParser extends org.xml.sax.helpers.DefaultHandler {
  private static final java.lang.String E_TAGLIB;

  private static final java.lang.String E_TAGLIB_LOCATION;

  private static final java.lang.String E_TAGLIB_URI;

  private java.lang.StringBuilder cDataCollector;

  private java.lang.String taglibUriCData;

  private java.lang.String taglibLocationCData;

  private org.xml.sax.Locator locator;

  final freemarker.ext.jsp.TaglibFactory this$0;

  private freemarker.ext.jsp.TaglibFactory$WebXmlParser(freemarker.ext.jsp.TaglibFactory);
    Code:
       0: aload_0
       1: aload_1
       2: putfield      #3                  // Field this$0:Lfreemarker/ext/jsp/TaglibFactory;
       5: aload_0
       6: invokespecial #4                  // Method org/xml/sax/helpers/DefaultHandler."<init>":()V
       9: return

  public void setDocumentLocator(org.xml.sax.Locator);
    Code:
       0: aload_0
       1: aload_1
       2: putfield      #5                  // Field locator:Lorg/xml/sax/Locator;
       5: return

  public void startElement(java.lang.String, java.lang.String, java.lang.String, org.xml.sax.Attributes);
    Code:
       0: ldc           #7                  // String taglib-uri
       2: aload_3
       3: invokevirtual #8                  // Method java/lang/String.equals:(Ljava/lang/Object;)Z
       6: ifne          18
       9: ldc           #9                  // String taglib-location
      11: aload_3
      12: invokevirtual #8                  // Method java/lang/String.equals:(Ljava/lang/Object;)Z
      15: ifeq          29
      18: aload_0
      19: new           #10                 // class java/lang/StringBuilder
      22: dup
      23: invokespecial #11                 // Method java/lang/StringBuilder."<init>":()V
      26: putfield      #12                 // Field cDataCollector:Ljava/lang/StringBuilder;
      29: return

  public void characters(char[], int, int);
    Code:
       0: aload_0
       1: getfield      #12                 // Field cDataCollector:Ljava/lang/StringBuilder;
       4: ifnull        18
       7: aload_0
       8: getfield      #12                 // Field cDataCollector:Ljava/lang/StringBuilder;
      11: aload_1
      12: iload_2
      13: iload_3
      14: invokevirtual #13                 // Method java/lang/StringBuilder.append:([CII)Ljava/lang/StringBuilder;
      17: pop
      18: return

  public void endElement(java.lang.String, java.lang.String, java.lang.String) throws freemarker.ext.jsp.TaglibFactory$TldParsingSAXException;
    Code:
       0: ldc           #7                  // String taglib-uri
       2: aload_3
       3: invokevirtual #8                  // Method java/lang/String.equals:(Ljava/lang/Object;)Z
       6: ifeq          31
       9: aload_0
      10: aload_0
      11: getfield      #12                 // Field cDataCollector:Ljava/lang/StringBuilder;
      14: invokevirtual #14                 // Method java/lang/StringBuilder.toString:()Ljava/lang/String;
      17: invokevirtual #15                 // Method java/lang/String.trim:()Ljava/lang/String;
      20: putfield      #16                 // Field taglibUriCData:Ljava/lang/String;
      23: aload_0
      24: aconst_null
      25: putfield      #12                 // Field cDataCollector:Ljava/lang/StringBuilder;
      28: goto          230
      31: ldc           #9                  // String taglib-location
      33: aload_3
      34: invokevirtual #8                  // Method java/lang/String.equals:(Ljava/lang/Object;)Z
      37: ifeq          164
      40: aload_0
      41: aload_0
      42: getfield      #12                 // Field cDataCollector:Ljava/lang/StringBuilder;
      45: invokevirtual #14                 // Method java/lang/StringBuilder.toString:()Ljava/lang/String;
      48: invokevirtual #15                 // Method java/lang/String.trim:()Ljava/lang/String;
      51: putfield      #17                 // Field taglibLocationCData:Ljava/lang/String;
      54: aload_0
      55: getfield      #17                 // Field taglibLocationCData:Ljava/lang/String;
      58: invokevirtual #18                 // Method java/lang/String.length:()I
      61: ifne          78
      64: new           #19                 // class freemarker/ext/jsp/TaglibFactory$TldParsingSAXException
      67: dup
      68: ldc           #20                 // String Required \"taglib-uri\" element was missing or empty
      70: aload_0
      71: getfield      #5                  // Field locator:Lorg/xml/sax/Locator;
      74: invokespecial #21                 // Method freemarker/ext/jsp/TaglibFactory$TldParsingSAXException."<init>":(Ljava/lang/String;Lorg/xml/sax/Locator;)V
      77: athrow
      78: aload_0
      79: getfield      #17                 // Field taglibLocationCData:Ljava/lang/String;
      82: invokestatic  #22                 // Method freemarker/ext/jsp/TaglibFactory.access$1400:(Ljava/lang/String;)I
      85: iconst_2
      86: if_icmpne     115
      89: aload_0
      90: new           #10                 // class java/lang/StringBuilder
      93: dup
      94: invokespecial #11                 // Method java/lang/StringBuilder."<init>":()V
      97: ldc           #23                 // String /WEB-INF/
      99: invokevirtual #24                 // Method java/lang/StringBuilder.append:(Ljava/lang/String;)Ljava/lang/StringBuilder;
     102: aload_0
     103: getfield      #17                 // Field taglibLocationCData:Ljava/lang/String;
     106: invokevirtual #24                 // Method java/lang/StringBuilder.append:(Ljava/lang/String;)Ljava/lang/StringBuilder;
     109: invokevirtual #14                 // Method java/lang/StringBuilder.toString:()Ljava/lang/String;
     112: putfield      #17                 // Field taglibLocationCData:Ljava/lang/String;
     115: goto          156
     118: astore        4
     120: new           #19                 // class freemarker/ext/jsp/TaglibFactory$TldParsingSAXException
     123: dup
     124: new           #10                 // class java/lang/StringBuilder
     127: dup
     128: invokespecial #11                 // Method java/lang/StringBuilder."<init>":()V
     131: ldc           #26                 // String Failed to detect URI type for:
     133: invokevirtual #24                 // Method java/lang/StringBuilder.append:(Ljava/lang/String;)Ljava/lang/StringBuilder;
     136: aload_0
     137: getfield      #17                 // Field taglibLocationCData:Ljava/lang/String;
     140: invokevirtual #24                 // Method java/lang/StringBuilder.append:(Ljava/lang/String;)Ljava/lang/StringBuilder;
     143: invokevirtual #14                 // Method java/lang/StringBuilder.toString:()Ljava/lang/String;
     146: aload_0
     147: getfield      #5                  // Field locator:Lorg/xml/sax/Locator;
     150: aload         4
     152: invokespecial #27                 // Method freemarker/ext/jsp/TaglibFactory$TldParsingSAXException."<init>":(Ljava/lang/String;Lorg/xml/sax/Locator;Ljava/lang/Throwable;)V
     155: athrow
     156: aload_0
     157: aconst_null
     158: putfield      #12                 // Field cDataCollector:Ljava/lang/StringBuilder;
     161: goto          230
     164: ldc           #28                 // String taglib
     166: aload_3
     167: invokevirtual #8                  // Method java/lang/String.equals:(Ljava/lang/Object;)Z
     170: ifeq          230
     173: aload_0
     174: getfield      #3                  // Field this$0:Lfreemarker/ext/jsp/TaglibFactory;
     177: aload_0
     178: getfield      #17                 // Field taglibLocationCData:Ljava/lang/String;
     181: invokestatic  #29                 // Method freemarker/ext/jsp/TaglibFactory.access$1500:(Ljava/lang/String;)Z
     184: ifeq          208
     187: new           #30                 // class freemarker/ext/jsp/TaglibFactory$ServletContextJarEntryTldLocation
     190: dup
     191: aload_0
     192: getfield      #3                  // Field this$0:Lfreemarker/ext/jsp/TaglibFactory;
     195: aload_0
     196: getfield      #17                 // Field taglibLocationCData:Ljava/lang/String;
     199: ldc           #31                 // String /META-INF/taglib.tld
     201: aconst_null
     202: invokespecial #32                 // Method freemarker/ext/jsp/TaglibFactory$ServletContextJarEntryTldLocation."<init>":(Lfreemarker/ext/jsp/TaglibFactory;Ljava/lang/String;Ljava/lang/String;Lfreemarker/ext/jsp/TaglibFactory$1;)V
     205: goto          223
     208: new           #33                 // class freemarker/ext/jsp/TaglibFactory$ServletContextTldLocation
     211: dup
     212: aload_0
     213: getfield      #3                  // Field this$0:Lfreemarker/ext/jsp/TaglibFactory;
     216: aload_0
     217: getfield      #17                 // Field taglibLocationCData:Ljava/lang/String;
     220: invokespecial #34                 // Method freemarker/ext/jsp/TaglibFactory$ServletContextTldLocation."<init>":(Lfreemarker/ext/jsp/TaglibFactory;Ljava/lang/String;)V
     223: aload_0
     224: getfield      #16                 // Field taglibUriCData:Ljava/lang/String;
     227: invokestatic  #35                 // Method freemarker/ext/jsp/TaglibFactory.access$1600:(Lfreemarker/ext/jsp/TaglibFactory;Lfreemarker/ext/jsp/TaglibFactory$TldLocation;Ljava/lang/String;)V
     230: return
    Exception table:
       from    to  target type
          78   115   118   Class java/net/MalformedURLException

  freemarker.ext.jsp.TaglibFactory$WebXmlParser(freemarker.ext.jsp.TaglibFactory, freemarker.ext.jsp.TaglibFactory$1);
    Code:
       0: aload_0
       1: aload_1
       2: invokespecial #2                  // Method "<init>":(Lfreemarker/ext/jsp/TaglibFactory;)V
       5: return
}
