Compiled from "ConditionInParameter.java"
public class org.h2.expression.ConditionInParameter extends org.h2.expression.Condition {
  private final org.h2.engine.Database database;

  private org.h2.expression.Expression left;

  private final org.h2.expression.Parameter parameter;

  public org.h2.expression.ConditionInParameter(org.h2.engine.Database, org.h2.expression.Expression, org.h2.expression.Parameter);
    Code:
       0: aload_0
       1: invokespecial #1                  // Method org/h2/expression/Condition."<init>":()V
       4: aload_0
       5: aload_1
       6: putfield      #2                  // Field database:Lorg/h2/engine/Database;
       9: aload_0
      10: aload_2
      11: putfield      #3                  // Field left:Lorg/h2/expression/Expression;
      14: aload_0
      15: aload_3
      16: putfield      #4                  // Field parameter:Lorg/h2/expression/Parameter;
      19: return

  public org.h2.value.Value getValue(org.h2.engine.Session);
    Code:
       0: aload_0
       1: getfield      #3                  // Field left:Lorg/h2/expression/Expression;
       4: aload_1
       5: invokevirtual #5                  // Method org/h2/expression/Expression.getValue:(Lorg/h2/engine/Session;)Lorg/h2/value/Value;
       8: astore_2
       9: aload_2
      10: getstatic     #6                  // Field org/h2/value/ValueNull.INSTANCE:Lorg/h2/value/ValueNull;
      13: if_acmpne     18
      16: aload_2
      17: areturn
      18: iconst_0
      19: istore_3
      20: iconst_0
      21: istore        4
      23: aload_0
      24: getfield      #4                  // Field parameter:Lorg/h2/expression/Parameter;
      27: aload_1
      28: invokevirtual #7                  // Method org/h2/expression/Parameter.getValue:(Lorg/h2/engine/Session;)Lorg/h2/value/Value;
      31: astore        5
      33: aload         5
      35: instanceof    #8                  // class org/h2/value/ValueArray
      38: ifeq          126
      41: aload         5
      43: checkcast     #8                  // class org/h2/value/ValueArray
      46: invokevirtual #9                  // Method org/h2/value/ValueArray.getList:()[Lorg/h2/value/Value;
      49: astore        6
      51: aload         6
      53: arraylength
      54: istore        7
      56: iconst_0
      57: istore        8
      59: iload         8
      61: iload         7
      63: if_icmpge     123
      66: aload         6
      68: iload         8
      70: aaload
      71: astore        9
      73: aload         9
      75: getstatic     #6                  // Field org/h2/value/ValueNull.INSTANCE:Lorg/h2/value/ValueNull;
      78: if_acmpne     87
      81: iconst_1
      82: istore        4
      84: goto          117
      87: aload         9
      89: aload_2
      90: invokevirtual #10                 // Method org/h2/value/Value.getType:()I
      93: invokevirtual #11                 // Method org/h2/value/Value.convertTo:(I)Lorg/h2/value/Value;
      96: astore        9
      98: aload_0
      99: getfield      #2                  // Field database:Lorg/h2/engine/Database;
     102: aload_2
     103: aload         9
     105: iconst_0
     106: invokestatic  #12                 // Method org/h2/expression/Comparison.compareNotNull:(Lorg/h2/engine/Database;Lorg/h2/value/Value;Lorg/h2/value/Value;I)Z
     109: istore_3
     110: iload_3
     111: ifeq          117
     114: goto          123
     117: iinc          8, 1
     120: goto          59
     123: goto          163
     126: aload         5
     128: getstatic     #6                  // Field org/h2/value/ValueNull.INSTANCE:Lorg/h2/value/ValueNull;
     131: if_acmpne     140
     134: iconst_1
     135: istore        4
     137: goto          163
     140: aload         5
     142: aload_2
     143: invokevirtual #10                 // Method org/h2/value/Value.getType:()I
     146: invokevirtual #11                 // Method org/h2/value/Value.convertTo:(I)Lorg/h2/value/Value;
     149: astore        5
     151: aload_0
     152: getfield      #2                  // Field database:Lorg/h2/engine/Database;
     155: aload_2
     156: aload         5
     158: iconst_0
     159: invokestatic  #12                 // Method org/h2/expression/Comparison.compareNotNull:(Lorg/h2/engine/Database;Lorg/h2/value/Value;Lorg/h2/value/Value;I)Z
     162: istore_3
     163: iload_3
     164: ifne          176
     167: iload         4
     169: ifeq          176
     172: getstatic     #6                  // Field org/h2/value/ValueNull.INSTANCE:Lorg/h2/value/ValueNull;
     175: areturn
     176: iload_3
     177: invokestatic  #13                 // Method org/h2/value/ValueBoolean.get:(Z)Lorg/h2/value/ValueBoolean;
     180: areturn

  public void mapColumns(org.h2.table.ColumnResolver, int);
    Code:
       0: aload_0
       1: getfield      #3                  // Field left:Lorg/h2/expression/Expression;
       4: aload_1
       5: iload_2
       6: invokevirtual #14                 // Method org/h2/expression/Expression.mapColumns:(Lorg/h2/table/ColumnResolver;I)V
       9: return

  public org.h2.expression.Expression optimize(org.h2.engine.Session);
    Code:
       0: aload_0
       1: aload_0
       2: getfield      #3                  // Field left:Lorg/h2/expression/Expression;
       5: aload_1
       6: invokevirtual #15                 // Method org/h2/expression/Expression.optimize:(Lorg/h2/engine/Session;)Lorg/h2/expression/Expression;
       9: putfield      #3                  // Field left:Lorg/h2/expression/Expression;
      12: aload_0
      13: getfield      #3                  // Field left:Lorg/h2/expression/Expression;
      16: invokevirtual #16                 // Method org/h2/expression/Expression.isConstant:()Z
      19: ifeq          37
      22: aload_0
      23: getfield      #3                  // Field left:Lorg/h2/expression/Expression;
      26: invokestatic  #17                 // Method org/h2/expression/ValueExpression.getNull:()Lorg/h2/expression/ValueExpression;
      29: if_acmpne     37
      32: aload_0
      33: getfield      #3                  // Field left:Lorg/h2/expression/Expression;
      36: areturn
      37: aload_0
      38: areturn

  public void createIndexConditions(org.h2.engine.Session, org.h2.table.TableFilter);
    Code:
       0: aload_0
       1: getfield      #3                  // Field left:Lorg/h2/expression/Expression;
       4: instanceof    #18                 // class org/h2/expression/ExpressionColumn
       7: ifne          11
      10: return
      11: aload_0
      12: getfield      #3                  // Field left:Lorg/h2/expression/Expression;
      15: checkcast     #18                 // class org/h2/expression/ExpressionColumn
      18: astore_3
      19: aload_2
      20: aload_3
      21: invokevirtual #19                 // Method org/h2/expression/ExpressionColumn.getTableFilter:()Lorg/h2/table/TableFilter;
      24: if_acmpeq     28
      27: return
      28: aload_2
      29: aload_3
      30: new           #20                 // class org/h2/expression/ConditionInParameter$ParameterList
      33: dup
      34: aload_0
      35: getfield      #4                  // Field parameter:Lorg/h2/expression/Parameter;
      38: invokespecial #21                 // Method org/h2/expression/ConditionInParameter$ParameterList."<init>":(Lorg/h2/expression/Parameter;)V
      41: invokestatic  #22                 // Method org/h2/index/IndexCondition.getInList:(Lorg/h2/expression/ExpressionColumn;Ljava/util/List;)Lorg/h2/index/IndexCondition;
      44: invokevirtual #23                 // Method org/h2/table/TableFilter.addIndexCondition:(Lorg/h2/index/IndexCondition;)V
      47: return

  public void setEvaluatable(org.h2.table.TableFilter, boolean);
    Code:
       0: aload_0
       1: getfield      #3                  // Field left:Lorg/h2/expression/Expression;
       4: aload_1
       5: iload_2
       6: invokevirtual #24                 // Method org/h2/expression/Expression.setEvaluatable:(Lorg/h2/table/TableFilter;Z)V
       9: return

  public java.lang.String getSQL();
    Code:
       0: new           #25                 // class java/lang/StringBuilder
       3: dup
       4: invokespecial #26                 // Method java/lang/StringBuilder."<init>":()V
       7: bipush        40
       9: invokevirtual #27                 // Method java/lang/StringBuilder.append:(C)Ljava/lang/StringBuilder;
      12: aload_0
      13: getfield      #3                  // Field left:Lorg/h2/expression/Expression;
      16: invokevirtual #28                 // Method org/h2/expression/Expression.getSQL:()Ljava/lang/String;
      19: invokevirtual #29                 // Method java/lang/StringBuilder.append:(Ljava/lang/String;)Ljava/lang/StringBuilder;
      22: ldc           #30                 // String  = ANY(
      24: invokevirtual #29                 // Method java/lang/StringBuilder.append:(Ljava/lang/String;)Ljava/lang/StringBuilder;
      27: aload_0
      28: getfield      #4                  // Field parameter:Lorg/h2/expression/Parameter;
      31: invokevirtual #31                 // Method org/h2/expression/Parameter.getSQL:()Ljava/lang/String;
      34: invokevirtual #29                 // Method java/lang/StringBuilder.append:(Ljava/lang/String;)Ljava/lang/StringBuilder;
      37: ldc           #32                 // String ))
      39: invokevirtual #29                 // Method java/lang/StringBuilder.append:(Ljava/lang/String;)Ljava/lang/StringBuilder;
      42: invokevirtual #33                 // Method java/lang/StringBuilder.toString:()Ljava/lang/String;
      45: areturn

  public void updateAggregate(org.h2.engine.Session);
    Code:
       0: aload_0
       1: getfield      #3                  // Field left:Lorg/h2/expression/Expression;
       4: aload_1
       5: invokevirtual #34                 // Method org/h2/expression/Expression.updateAggregate:(Lorg/h2/engine/Session;)V
       8: return

  public boolean isEverything(org.h2.expression.ExpressionVisitor);
    Code:
       0: aload_0
       1: getfield      #3                  // Field left:Lorg/h2/expression/Expression;
       4: aload_1
       5: invokevirtual #35                 // Method org/h2/expression/Expression.isEverything:(Lorg/h2/expression/ExpressionVisitor;)Z
       8: ifeq          26
      11: aload_0
      12: getfield      #4                  // Field parameter:Lorg/h2/expression/Parameter;
      15: aload_1
      16: invokevirtual #36                 // Method org/h2/expression/Parameter.isEverything:(Lorg/h2/expression/ExpressionVisitor;)Z
      19: ifeq          26
      22: iconst_1
      23: goto          27
      26: iconst_0
      27: ireturn

  public int getCost();
    Code:
       0: aload_0
       1: getfield      #3                  // Field left:Lorg/h2/expression/Expression;
       4: invokevirtual #37                 // Method org/h2/expression/Expression.getCost:()I
       7: ireturn

  public int getDisplaySize();
    Code:
       0: aload_0
       1: invokespecial #38                 // Method org/h2/expression/Condition.getDisplaySize:()I
       4: ireturn

  public long getPrecision();
    Code:
       0: aload_0
       1: invokespecial #39                 // Method org/h2/expression/Condition.getPrecision:()J
       4: lreturn

  public int getScale();
    Code:
       0: aload_0
       1: invokespecial #40                 // Method org/h2/expression/Condition.getScale:()I
       4: ireturn

  public int getType();
    Code:
       0: aload_0
       1: invokespecial #41                 // Method org/h2/expression/Condition.getType:()I
       4: ireturn
}
