Compiled from "Operation.java"
public class org.h2.expression.Operation extends org.h2.expression.Expression {
  private org.h2.expression.Operation$OpType opType;

  private org.h2.expression.Expression left;

  private org.h2.expression.Expression right;

  private int dataType;

  private boolean convertRight;

  public org.h2.expression.Operation(org.h2.expression.Operation$OpType, org.h2.expression.Expression, org.h2.expression.Expression);
    Code:
       0: aload_0
       1: invokespecial #1                  // Method org/h2/expression/Expression."<init>":()V
       4: aload_0
       5: iconst_1
       6: putfield      #2                  // Field convertRight:Z
       9: aload_0
      10: aload_1
      11: putfield      #3                  // Field opType:Lorg/h2/expression/Operation$OpType;
      14: aload_0
      15: aload_2
      16: putfield      #4                  // Field left:Lorg/h2/expression/Expression;
      19: aload_0
      20: aload_3
      21: putfield      #5                  // Field right:Lorg/h2/expression/Expression;
      24: return

  public java.lang.String getSQL();
    Code:
       0: aload_0
       1: getfield      #3                  // Field opType:Lorg/h2/expression/Operation$OpType;
       4: getstatic     #6                  // Field org/h2/expression/Operation$OpType.NEGATE:Lorg/h2/expression/Operation$OpType;
       7: if_acmpne     39
      10: new           #7                  // class java/lang/StringBuilder
      13: dup
      14: invokespecial #8                  // Method java/lang/StringBuilder."<init>":()V
      17: ldc           #9                  // String -
      19: invokevirtual #10                 // Method java/lang/StringBuilder.append:(Ljava/lang/String;)Ljava/lang/StringBuilder;
      22: aload_0
      23: getfield      #4                  // Field left:Lorg/h2/expression/Expression;
      26: invokevirtual #11                 // Method org/h2/expression/Expression.getSQL:()Ljava/lang/String;
      29: invokevirtual #10                 // Method java/lang/StringBuilder.append:(Ljava/lang/String;)Ljava/lang/StringBuilder;
      32: invokevirtual #12                 // Method java/lang/StringBuilder.toString:()Ljava/lang/String;
      35: astore_1
      36: goto          87
      39: new           #7                  // class java/lang/StringBuilder
      42: dup
      43: invokespecial #8                  // Method java/lang/StringBuilder."<init>":()V
      46: aload_0
      47: getfield      #4                  // Field left:Lorg/h2/expression/Expression;
      50: invokevirtual #11                 // Method org/h2/expression/Expression.getSQL:()Ljava/lang/String;
      53: invokevirtual #10                 // Method java/lang/StringBuilder.append:(Ljava/lang/String;)Ljava/lang/StringBuilder;
      56: ldc           #13                 // String
      58: invokevirtual #10                 // Method java/lang/StringBuilder.append:(Ljava/lang/String;)Ljava/lang/StringBuilder;
      61: aload_0
      62: invokespecial #14                 // Method getOperationToken:()Ljava/lang/String;
      65: invokevirtual #10                 // Method java/lang/StringBuilder.append:(Ljava/lang/String;)Ljava/lang/StringBuilder;
      68: ldc           #13                 // String
      70: invokevirtual #10                 // Method java/lang/StringBuilder.append:(Ljava/lang/String;)Ljava/lang/StringBuilder;
      73: aload_0
      74: getfield      #5                  // Field right:Lorg/h2/expression/Expression;
      77: invokevirtual #11                 // Method org/h2/expression/Expression.getSQL:()Ljava/lang/String;
      80: invokevirtual #10                 // Method java/lang/StringBuilder.append:(Ljava/lang/String;)Ljava/lang/StringBuilder;
      83: invokevirtual #12                 // Method java/lang/StringBuilder.toString:()Ljava/lang/String;
      86: astore_1
      87: new           #7                  // class java/lang/StringBuilder
      90: dup
      91: invokespecial #8                  // Method java/lang/StringBuilder."<init>":()V
      94: ldc           #15                 // String (
      96: invokevirtual #10                 // Method java/lang/StringBuilder.append:(Ljava/lang/String;)Ljava/lang/StringBuilder;
      99: aload_1
     100: invokevirtual #10                 // Method java/lang/StringBuilder.append:(Ljava/lang/String;)Ljava/lang/StringBuilder;
     103: ldc           #16                 // String )
     105: invokevirtual #10                 // Method java/lang/StringBuilder.append:(Ljava/lang/String;)Ljava/lang/StringBuilder;
     108: invokevirtual #12                 // Method java/lang/StringBuilder.toString:()Ljava/lang/String;
     111: areturn

  private java.lang.String getOperationToken();
    Code:
       0: getstatic     #17                 // Field org/h2/expression/Operation$1.$SwitchMap$org$h2$expression$Operation$OpType:[I
       3: aload_0
       4: getfield      #3                  // Field opType:Lorg/h2/expression/Operation$OpType;
       7: invokevirtual #18                 // Method org/h2/expression/Operation$OpType.ordinal:()I
      10: iaload
      11: tableswitch   { // 1 to 7
                     1: 52
                     2: 55
                     3: 58
                     4: 61
                     5: 64
                     6: 67
                     7: 70
               default: 73
          }
      52: ldc           #19                 // String -
      54: areturn
      55: ldc           #20                 // String ||
      57: areturn
      58: ldc           #21                 // String +
      60: areturn
      61: ldc           #19                 // String -
      63: areturn
      64: ldc           #22                 // String *
      66: areturn
      67: ldc           #23                 // String /
      69: areturn
      70: ldc           #24                 // String %
      72: areturn
      73: new           #7                  // class java/lang/StringBuilder
      76: dup
      77: invokespecial #8                  // Method java/lang/StringBuilder."<init>":()V
      80: ldc           #25                 // String opType=
      82: invokevirtual #10                 // Method java/lang/StringBuilder.append:(Ljava/lang/String;)Ljava/lang/StringBuilder;
      85: aload_0
      86: getfield      #3                  // Field opType:Lorg/h2/expression/Operation$OpType;
      89: invokevirtual #26                 // Method java/lang/StringBuilder.append:(Ljava/lang/Object;)Ljava/lang/StringBuilder;
      92: invokevirtual #12                 // Method java/lang/StringBuilder.toString:()Ljava/lang/String;
      95: invokestatic  #27                 // Method org/h2/message/DbException.throwInternalError:(Ljava/lang/String;)Ljava/lang/RuntimeException;
      98: athrow

  public org.h2.value.Value getValue(org.h2.engine.Session);
    Code:
       0: aload_0
       1: getfield      #4                  // Field left:Lorg/h2/expression/Expression;
       4: aload_1
       5: invokevirtual #28                 // Method org/h2/expression/Expression.getValue:(Lorg/h2/engine/Session;)Lorg/h2/value/Value;
       8: aload_0
       9: getfield      #29                 // Field dataType:I
      12: invokevirtual #30                 // Method org/h2/value/Value.convertTo:(I)Lorg/h2/value/Value;
      15: astore_2
      16: aload_0
      17: getfield      #5                  // Field right:Lorg/h2/expression/Expression;
      20: ifnonnull     28
      23: aconst_null
      24: astore_3
      25: goto          53
      28: aload_0
      29: getfield      #5                  // Field right:Lorg/h2/expression/Expression;
      32: aload_1
      33: invokevirtual #28                 // Method org/h2/expression/Expression.getValue:(Lorg/h2/engine/Session;)Lorg/h2/value/Value;
      36: astore_3
      37: aload_0
      38: getfield      #2                  // Field convertRight:Z
      41: ifeq          53
      44: aload_3
      45: aload_0
      46: getfield      #29                 // Field dataType:I
      49: invokevirtual #30                 // Method org/h2/value/Value.convertTo:(I)Lorg/h2/value/Value;
      52: astore_3
      53: getstatic     #17                 // Field org/h2/expression/Operation$1.$SwitchMap$org$h2$expression$Operation$OpType:[I
      56: aload_0
      57: getfield      #3                  // Field opType:Lorg/h2/expression/Operation$OpType;
      60: invokevirtual #18                 // Method org/h2/expression/Operation$OpType.ordinal:()I
      63: iaload
      64: tableswitch   { // 1 to 7
                     1: 108
                     2: 124
                     3: 229
                     4: 253
                     5: 277
                     6: 301
                     7: 325
               default: 349
          }
     108: aload_2
     109: getstatic     #31                 // Field org/h2/value/ValueNull.INSTANCE:Lorg/h2/value/ValueNull;
     112: if_acmpne     119
     115: aload_2
     116: goto          123
     119: aload_2
     120: invokevirtual #32                 // Method org/h2/value/Value.negate:()Lorg/h2/value/Value;
     123: areturn
     124: aload_1
     125: invokevirtual #33                 // Method org/h2/engine/Session.getDatabase:()Lorg/h2/engine/Database;
     128: invokevirtual #34                 // Method org/h2/engine/Database.getMode:()Lorg/h2/engine/Mode;
     131: astore        4
     133: aload_2
     134: getstatic     #31                 // Field org/h2/value/ValueNull.INSTANCE:Lorg/h2/value/ValueNull;
     137: if_acmpne     154
     140: aload         4
     142: getfield      #35                 // Field org/h2/engine/Mode.nullConcatIsNull:Z
     145: ifeq          152
     148: getstatic     #31                 // Field org/h2/value/ValueNull.INSTANCE:Lorg/h2/value/ValueNull;
     151: areturn
     152: aload_3
     153: areturn
     154: aload_3
     155: getstatic     #31                 // Field org/h2/value/ValueNull.INSTANCE:Lorg/h2/value/ValueNull;
     158: if_acmpne     175
     161: aload         4
     163: getfield      #35                 // Field org/h2/engine/Mode.nullConcatIsNull:Z
     166: ifeq          173
     169: getstatic     #31                 // Field org/h2/value/ValueNull.INSTANCE:Lorg/h2/value/ValueNull;
     172: areturn
     173: aload_2
     174: areturn
     175: aload_2
     176: invokevirtual #36                 // Method org/h2/value/Value.getString:()Ljava/lang/String;
     179: astore        5
     181: aload_3
     182: invokevirtual #36                 // Method org/h2/value/Value.getString:()Ljava/lang/String;
     185: astore        6
     187: new           #7                  // class java/lang/StringBuilder
     190: dup
     191: aload         5
     193: invokevirtual #37                 // Method java/lang/String.length:()I
     196: aload         6
     198: invokevirtual #37                 // Method java/lang/String.length:()I
     201: iadd
     202: invokespecial #38                 // Method java/lang/StringBuilder."<init>":(I)V
     205: astore        7
     207: aload         7
     209: aload         5
     211: invokevirtual #10                 // Method java/lang/StringBuilder.append:(Ljava/lang/String;)Ljava/lang/StringBuilder;
     214: aload         6
     216: invokevirtual #10                 // Method java/lang/StringBuilder.append:(Ljava/lang/String;)Ljava/lang/StringBuilder;
     219: pop
     220: aload         7
     222: invokevirtual #12                 // Method java/lang/StringBuilder.toString:()Ljava/lang/String;
     225: invokestatic  #39                 // Method org/h2/value/ValueString.get:(Ljava/lang/String;)Lorg/h2/value/Value;
     228: areturn
     229: aload_2
     230: getstatic     #31                 // Field org/h2/value/ValueNull.INSTANCE:Lorg/h2/value/ValueNull;
     233: if_acmpeq     243
     236: aload_3
     237: getstatic     #31                 // Field org/h2/value/ValueNull.INSTANCE:Lorg/h2/value/ValueNull;
     240: if_acmpne     247
     243: getstatic     #31                 // Field org/h2/value/ValueNull.INSTANCE:Lorg/h2/value/ValueNull;
     246: areturn
     247: aload_2
     248: aload_3
     249: invokevirtual #40                 // Method org/h2/value/Value.add:(Lorg/h2/value/Value;)Lorg/h2/value/Value;
     252: areturn
     253: aload_2
     254: getstatic     #31                 // Field org/h2/value/ValueNull.INSTANCE:Lorg/h2/value/ValueNull;
     257: if_acmpeq     267
     260: aload_3
     261: getstatic     #31                 // Field org/h2/value/ValueNull.INSTANCE:Lorg/h2/value/ValueNull;
     264: if_acmpne     271
     267: getstatic     #31                 // Field org/h2/value/ValueNull.INSTANCE:Lorg/h2/value/ValueNull;
     270: areturn
     271: aload_2
     272: aload_3
     273: invokevirtual #41                 // Method org/h2/value/Value.subtract:(Lorg/h2/value/Value;)Lorg/h2/value/Value;
     276: areturn
     277: aload_2
     278: getstatic     #31                 // Field org/h2/value/ValueNull.INSTANCE:Lorg/h2/value/ValueNull;
     281: if_acmpeq     291
     284: aload_3
     285: getstatic     #31                 // Field org/h2/value/ValueNull.INSTANCE:Lorg/h2/value/ValueNull;
     288: if_acmpne     295
     291: getstatic     #31                 // Field org/h2/value/ValueNull.INSTANCE:Lorg/h2/value/ValueNull;
     294: areturn
     295: aload_2
     296: aload_3
     297: invokevirtual #42                 // Method org/h2/value/Value.multiply:(Lorg/h2/value/Value;)Lorg/h2/value/Value;
     300: areturn
     301: aload_2
     302: getstatic     #31                 // Field org/h2/value/ValueNull.INSTANCE:Lorg/h2/value/ValueNull;
     305: if_acmpeq     315
     308: aload_3
     309: getstatic     #31                 // Field org/h2/value/ValueNull.INSTANCE:Lorg/h2/value/ValueNull;
     312: if_acmpne     319
     315: getstatic     #31                 // Field org/h2/value/ValueNull.INSTANCE:Lorg/h2/value/ValueNull;
     318: areturn
     319: aload_2
     320: aload_3
     321: invokevirtual #43                 // Method org/h2/value/Value.divide:(Lorg/h2/value/Value;)Lorg/h2/value/Value;
     324: areturn
     325: aload_2
     326: getstatic     #31                 // Field org/h2/value/ValueNull.INSTANCE:Lorg/h2/value/ValueNull;
     329: if_acmpeq     339
     332: aload_3
     333: getstatic     #31                 // Field org/h2/value/ValueNull.INSTANCE:Lorg/h2/value/ValueNull;
     336: if_acmpne     343
     339: getstatic     #31                 // Field org/h2/value/ValueNull.INSTANCE:Lorg/h2/value/ValueNull;
     342: areturn
     343: aload_2
     344: aload_3
     345: invokevirtual #44                 // Method org/h2/value/Value.modulus:(Lorg/h2/value/Value;)Lorg/h2/value/Value;
     348: areturn
     349: new           #7                  // class java/lang/StringBuilder
     352: dup
     353: invokespecial #8                  // Method java/lang/StringBuilder."<init>":()V
     356: ldc           #45                 // String type=
     358: invokevirtual #10                 // Method java/lang/StringBuilder.append:(Ljava/lang/String;)Ljava/lang/StringBuilder;
     361: aload_0
     362: getfield      #3                  // Field opType:Lorg/h2/expression/Operation$OpType;
     365: invokevirtual #26                 // Method java/lang/StringBuilder.append:(Ljava/lang/Object;)Ljava/lang/StringBuilder;
     368: invokevirtual #12                 // Method java/lang/StringBuilder.toString:()Ljava/lang/String;
     371: invokestatic  #27                 // Method org/h2/message/DbException.throwInternalError:(Ljava/lang/String;)Ljava/lang/RuntimeException;
     374: athrow

  public void mapColumns(org.h2.table.ColumnResolver, int);
    Code:
       0: aload_0
       1: getfield      #4                  // Field left:Lorg/h2/expression/Expression;
       4: aload_1
       5: iload_2
       6: invokevirtual #46                 // Method org/h2/expression/Expression.mapColumns:(Lorg/h2/table/ColumnResolver;I)V
       9: aload_0
      10: getfield      #5                  // Field right:Lorg/h2/expression/Expression;
      13: ifnull        25
      16: aload_0
      17: getfield      #5                  // Field right:Lorg/h2/expression/Expression;
      20: aload_1
      21: iload_2
      22: invokevirtual #46                 // Method org/h2/expression/Expression.mapColumns:(Lorg/h2/table/ColumnResolver;I)V
      25: return

  public org.h2.expression.Expression optimize(org.h2.engine.Session);
    Code:
       0: aload_0
       1: aload_0
       2: getfield      #4                  // Field left:Lorg/h2/expression/Expression;
       5: aload_1
       6: invokevirtual #47                 // Method org/h2/expression/Expression.optimize:(Lorg/h2/engine/Session;)Lorg/h2/expression/Expression;
       9: putfield      #4                  // Field left:Lorg/h2/expression/Expression;
      12: getstatic     #17                 // Field org/h2/expression/Operation$1.$SwitchMap$org$h2$expression$Operation$OpType:[I
      15: aload_0
      16: getfield      #3                  // Field opType:Lorg/h2/expression/Operation$OpType;
      19: invokevirtual #18                 // Method org/h2/expression/Operation$OpType.ordinal:()I
      22: iaload
      23: tableswitch   { // 1 to 7
                     1: 64
                     2: 92
                     3: 139
                     4: 139
                     5: 139
                     6: 139
                     7: 139
               default: 1045
          }
      64: aload_0
      65: aload_0
      66: getfield      #4                  // Field left:Lorg/h2/expression/Expression;
      69: invokevirtual #48                 // Method org/h2/expression/Expression.getType:()I
      72: putfield      #29                 // Field dataType:I
      75: aload_0
      76: getfield      #29                 // Field dataType:I
      79: iconst_m1
      80: if_icmpne     1071
      83: aload_0
      84: bipush        6
      86: putfield      #29                 // Field dataType:I
      89: goto          1071
      92: aload_0
      93: aload_0
      94: getfield      #5                  // Field right:Lorg/h2/expression/Expression;
      97: aload_1
      98: invokevirtual #47                 // Method org/h2/expression/Expression.optimize:(Lorg/h2/engine/Session;)Lorg/h2/expression/Expression;
     101: putfield      #5                  // Field right:Lorg/h2/expression/Expression;
     104: aload_0
     105: bipush        13
     107: putfield      #29                 // Field dataType:I
     110: aload_0
     111: getfield      #4                  // Field left:Lorg/h2/expression/Expression;
     114: invokevirtual #49                 // Method org/h2/expression/Expression.isConstant:()Z
     117: ifeq          1071
     120: aload_0
     121: getfield      #5                  // Field right:Lorg/h2/expression/Expression;
     124: invokevirtual #49                 // Method org/h2/expression/Expression.isConstant:()Z
     127: ifeq          1071
     130: aload_0
     131: aload_1
     132: invokevirtual #50                 // Method getValue:(Lorg/h2/engine/Session;)Lorg/h2/value/Value;
     135: invokestatic  #51                 // Method org/h2/expression/ValueExpression.get:(Lorg/h2/value/Value;)Lorg/h2/expression/ValueExpression;
     138: areturn
     139: aload_0
     140: aload_0
     141: getfield      #5                  // Field right:Lorg/h2/expression/Expression;
     144: aload_1
     145: invokevirtual #47                 // Method org/h2/expression/Expression.optimize:(Lorg/h2/engine/Session;)Lorg/h2/expression/Expression;
     148: putfield      #5                  // Field right:Lorg/h2/expression/Expression;
     151: aload_0
     152: getfield      #4                  // Field left:Lorg/h2/expression/Expression;
     155: invokevirtual #48                 // Method org/h2/expression/Expression.getType:()I
     158: istore_2
     159: aload_0
     160: getfield      #5                  // Field right:Lorg/h2/expression/Expression;
     163: invokevirtual #48                 // Method org/h2/expression/Expression.getType:()I
     166: istore_3
     167: iload_2
     168: ifne          175
     171: iload_3
     172: ifeq          185
     175: iload_2
     176: iconst_m1
     177: if_icmpne     233
     180: iload_3
     181: iconst_m1
     182: if_icmpne     233
     185: aload_0
     186: getfield      #3                  // Field opType:Lorg/h2/expression/Operation$OpType;
     189: getstatic     #52                 // Field org/h2/expression/Operation$OpType.PLUS:Lorg/h2/expression/Operation$OpType;
     192: if_acmpne     224
     195: aload_1
     196: invokevirtual #33                 // Method org/h2/engine/Session.getDatabase:()Lorg/h2/engine/Database;
     199: invokevirtual #34                 // Method org/h2/engine/Database.getMode:()Lorg/h2/engine/Mode;
     202: getfield      #53                 // Field org/h2/engine/Mode.allowPlusForStringConcat:Z
     205: ifeq          224
     208: aload_0
     209: bipush        13
     211: putfield      #29                 // Field dataType:I
     214: aload_0
     215: getstatic     #54                 // Field org/h2/expression/Operation$OpType.CONCAT:Lorg/h2/expression/Operation$OpType;
     218: putfield      #3                  // Field opType:Lorg/h2/expression/Operation$OpType;
     221: goto          1071
     224: aload_0
     225: bipush        6
     227: putfield      #29                 // Field dataType:I
     230: goto          1071
     233: iload_2
     234: bipush        10
     236: if_icmpeq     269
     239: iload_2
     240: bipush        11
     242: if_icmpeq     269
     245: iload_2
     246: bipush        9
     248: if_icmpeq     269
     251: iload_3
     252: bipush        10
     254: if_icmpeq     269
     257: iload_3
     258: bipush        11
     260: if_icmpeq     269
     263: iload_3
     264: bipush        9
     266: if_icmpne     1003
     269: aload_0
     270: getfield      #3                  // Field opType:Lorg/h2/expression/Operation$OpType;
     273: getstatic     #52                 // Field org/h2/expression/Operation$OpType.PLUS:Lorg/h2/expression/Operation$OpType;
     276: if_acmpne     497
     279: iload_3
     280: iload_2
     281: iload_3
     282: invokestatic  #55                 // Method org/h2/value/Value.getHigherOrder:(II)I
     285: if_icmpeq     300
     288: aload_0
     289: invokespecial #56                 // Method swap:()V
     292: iload_2
     293: istore        4
     295: iload_3
     296: istore_2
     297: iload         4
     299: istore_3
     300: iload_2
     301: iconst_4
     302: if_icmpne     362
     305: aload_1
     306: invokevirtual #33                 // Method org/h2/engine/Session.getDatabase:()Lorg/h2/engine/Database;
     309: ldc           #57                 // String DATEADD
     311: invokestatic  #58                 // Method org/h2/expression/Function.getFunction:(Lorg/h2/engine/Database;Ljava/lang/String;)Lorg/h2/expression/Function;
     314: astore        4
     316: aload         4
     318: iconst_0
     319: ldc           #59                 // String DAY
     321: invokestatic  #39                 // Method org/h2/value/ValueString.get:(Ljava/lang/String;)Lorg/h2/value/Value;
     324: invokestatic  #51                 // Method org/h2/expression/ValueExpression.get:(Lorg/h2/value/Value;)Lorg/h2/expression/ValueExpression;
     327: invokevirtual #60                 // Method org/h2/expression/Function.setParameter:(ILorg/h2/expression/Expression;)V
     330: aload         4
     332: iconst_1
     333: aload_0
     334: getfield      #4                  // Field left:Lorg/h2/expression/Expression;
     337: invokevirtual #60                 // Method org/h2/expression/Function.setParameter:(ILorg/h2/expression/Expression;)V
     340: aload         4
     342: iconst_2
     343: aload_0
     344: getfield      #5                  // Field right:Lorg/h2/expression/Expression;
     347: invokevirtual #60                 // Method org/h2/expression/Function.setParameter:(ILorg/h2/expression/Expression;)V
     350: aload         4
     352: invokevirtual #61                 // Method org/h2/expression/Function.doneWithParameters:()V
     355: aload         4
     357: aload_1
     358: invokevirtual #62                 // Method org/h2/expression/Function.optimize:(Lorg/h2/engine/Session;)Lorg/h2/expression/Expression;
     361: areturn
     362: iload_2
     363: bipush        6
     365: if_icmpeq     380
     368: iload_2
     369: bipush        8
     371: if_icmpeq     380
     374: iload_2
     375: bipush        7
     377: if_icmpne     463
     380: aload_1
     381: invokevirtual #33                 // Method org/h2/engine/Session.getDatabase:()Lorg/h2/engine/Database;
     384: ldc           #57                 // String DATEADD
     386: invokestatic  #58                 // Method org/h2/expression/Function.getFunction:(Lorg/h2/engine/Database;Ljava/lang/String;)Lorg/h2/expression/Function;
     389: astore        4
     391: aload         4
     393: iconst_0
     394: ldc           #63                 // String SECOND
     396: invokestatic  #39                 // Method org/h2/value/ValueString.get:(Ljava/lang/String;)Lorg/h2/value/Value;
     399: invokestatic  #51                 // Method org/h2/expression/ValueExpression.get:(Lorg/h2/value/Value;)Lorg/h2/expression/ValueExpression;
     402: invokevirtual #60                 // Method org/h2/expression/Function.setParameter:(ILorg/h2/expression/Expression;)V
     405: aload_0
     406: new           #64                 // class org/h2/expression/Operation
     409: dup
     410: getstatic     #65                 // Field org/h2/expression/Operation$OpType.MULTIPLY:Lorg/h2/expression/Operation$OpType;
     413: ldc           #66                 // int 86400
     415: invokestatic  #67                 // Method org/h2/value/ValueInt.get:(I)Lorg/h2/value/ValueInt;
     418: invokestatic  #51                 // Method org/h2/expression/ValueExpression.get:(Lorg/h2/value/Value;)Lorg/h2/expression/ValueExpression;
     421: aload_0
     422: getfield      #4                  // Field left:Lorg/h2/expression/Expression;
     425: invokespecial #68                 // Method "<init>":(Lorg/h2/expression/Operation$OpType;Lorg/h2/expression/Expression;Lorg/h2/expression/Expression;)V
     428: putfield      #4                  // Field left:Lorg/h2/expression/Expression;
     431: aload         4
     433: iconst_1
     434: aload_0
     435: getfield      #4                  // Field left:Lorg/h2/expression/Expression;
     438: invokevirtual #60                 // Method org/h2/expression/Function.setParameter:(ILorg/h2/expression/Expression;)V
     441: aload         4
     443: iconst_2
     444: aload_0
     445: getfield      #5                  // Field right:Lorg/h2/expression/Expression;
     448: invokevirtual #60                 // Method org/h2/expression/Function.setParameter:(ILorg/h2/expression/Expression;)V
     451: aload         4
     453: invokevirtual #61                 // Method org/h2/expression/Function.doneWithParameters:()V
     456: aload         4
     458: aload_1
     459: invokevirtual #62                 // Method org/h2/expression/Function.optimize:(Lorg/h2/engine/Session;)Lorg/h2/expression/Expression;
     462: areturn
     463: iload_2
     464: bipush        9
     466: if_icmpne     483
     469: iload_3
     470: bipush        9
     472: if_icmpne     483
     475: aload_0
     476: bipush        9
     478: putfield      #29                 // Field dataType:I
     481: aload_0
     482: areturn
     483: iload_2
     484: bipush        9
     486: if_icmpne     952
     489: aload_0
     490: bipush        11
     492: putfield      #29                 // Field dataType:I
     495: aload_0
     496: areturn
     497: aload_0
     498: getfield      #3                  // Field opType:Lorg/h2/expression/Operation$OpType;
     501: getstatic     #69                 // Field org/h2/expression/Operation$OpType.MINUS:Lorg/h2/expression/Operation$OpType;
     504: if_acmpne     871
     507: iload_2
     508: bipush        10
     510: if_icmpeq     519
     513: iload_2
     514: bipush        11
     516: if_icmpne     612
     519: iload_3
     520: iconst_4
     521: if_icmpne     612
     524: aload_1
     525: invokevirtual #33                 // Method org/h2/engine/Session.getDatabase:()Lorg/h2/engine/Database;
     528: ldc           #57                 // String DATEADD
     530: invokestatic  #58                 // Method org/h2/expression/Function.getFunction:(Lorg/h2/engine/Database;Ljava/lang/String;)Lorg/h2/expression/Function;
     533: astore        4
     535: aload         4
     537: iconst_0
     538: ldc           #59                 // String DAY
     540: invokestatic  #39                 // Method org/h2/value/ValueString.get:(Ljava/lang/String;)Lorg/h2/value/Value;
     543: invokestatic  #51                 // Method org/h2/expression/ValueExpression.get:(Lorg/h2/value/Value;)Lorg/h2/expression/ValueExpression;
     546: invokevirtual #60                 // Method org/h2/expression/Function.setParameter:(ILorg/h2/expression/Expression;)V
     549: aload_0
     550: new           #64                 // class org/h2/expression/Operation
     553: dup
     554: getstatic     #6                  // Field org/h2/expression/Operation$OpType.NEGATE:Lorg/h2/expression/Operation$OpType;
     557: aload_0
     558: getfield      #5                  // Field right:Lorg/h2/expression/Expression;
     561: aconst_null
     562: invokespecial #68                 // Method "<init>":(Lorg/h2/expression/Operation$OpType;Lorg/h2/expression/Expression;Lorg/h2/expression/Expression;)V
     565: putfield      #5                  // Field right:Lorg/h2/expression/Expression;
     568: aload_0
     569: aload_0
     570: getfield      #5                  // Field right:Lorg/h2/expression/Expression;
     573: aload_1
     574: invokevirtual #47                 // Method org/h2/expression/Expression.optimize:(Lorg/h2/engine/Session;)Lorg/h2/expression/Expression;
     577: putfield      #5                  // Field right:Lorg/h2/expression/Expression;
     580: aload         4
     582: iconst_1
     583: aload_0
     584: getfield      #5                  // Field right:Lorg/h2/expression/Expression;
     587: invokevirtual #60                 // Method org/h2/expression/Function.setParameter:(ILorg/h2/expression/Expression;)V
     590: aload         4
     592: iconst_2
     593: aload_0
     594: getfield      #4                  // Field left:Lorg/h2/expression/Expression;
     597: invokevirtual #60                 // Method org/h2/expression/Function.setParameter:(ILorg/h2/expression/Expression;)V
     600: aload         4
     602: invokevirtual #61                 // Method org/h2/expression/Function.doneWithParameters:()V
     605: aload         4
     607: aload_1
     608: invokevirtual #62                 // Method org/h2/expression/Function.optimize:(Lorg/h2/engine/Session;)Lorg/h2/expression/Expression;
     611: areturn
     612: iload_2
     613: bipush        10
     615: if_icmpeq     624
     618: iload_2
     619: bipush        11
     621: if_icmpne     756
     624: iload_3
     625: bipush        6
     627: if_icmpeq     642
     630: iload_3
     631: bipush        8
     633: if_icmpeq     642
     636: iload_3
     637: bipush        7
     639: if_icmpne     756
     642: aload_1
     643: invokevirtual #33                 // Method org/h2/engine/Session.getDatabase:()Lorg/h2/engine/Database;
     646: ldc           #57                 // String DATEADD
     648: invokestatic  #58                 // Method org/h2/expression/Function.getFunction:(Lorg/h2/engine/Database;Ljava/lang/String;)Lorg/h2/expression/Function;
     651: astore        4
     653: aload         4
     655: iconst_0
     656: ldc           #63                 // String SECOND
     658: invokestatic  #39                 // Method org/h2/value/ValueString.get:(Ljava/lang/String;)Lorg/h2/value/Value;
     661: invokestatic  #51                 // Method org/h2/expression/ValueExpression.get:(Lorg/h2/value/Value;)Lorg/h2/expression/ValueExpression;
     664: invokevirtual #60                 // Method org/h2/expression/Function.setParameter:(ILorg/h2/expression/Expression;)V
     667: aload_0
     668: new           #64                 // class org/h2/expression/Operation
     671: dup
     672: getstatic     #65                 // Field org/h2/expression/Operation$OpType.MULTIPLY:Lorg/h2/expression/Operation$OpType;
     675: ldc           #66                 // int 86400
     677: invokestatic  #67                 // Method org/h2/value/ValueInt.get:(I)Lorg/h2/value/ValueInt;
     680: invokestatic  #51                 // Method org/h2/expression/ValueExpression.get:(Lorg/h2/value/Value;)Lorg/h2/expression/ValueExpression;
     683: aload_0
     684: getfield      #5                  // Field right:Lorg/h2/expression/Expression;
     687: invokespecial #68                 // Method "<init>":(Lorg/h2/expression/Operation$OpType;Lorg/h2/expression/Expression;Lorg/h2/expression/Expression;)V
     690: putfield      #5                  // Field right:Lorg/h2/expression/Expression;
     693: aload_0
     694: new           #64                 // class org/h2/expression/Operation
     697: dup
     698: getstatic     #6                  // Field org/h2/expression/Operation$OpType.NEGATE:Lorg/h2/expression/Operation$OpType;
     701: aload_0
     702: getfield      #5                  // Field right:Lorg/h2/expression/Expression;
     705: aconst_null
     706: invokespecial #68                 // Method "<init>":(Lorg/h2/expression/Operation$OpType;Lorg/h2/expression/Expression;Lorg/h2/expression/Expression;)V
     709: putfield      #5                  // Field right:Lorg/h2/expression/Expression;
     712: aload_0
     713: aload_0
     714: getfield      #5                  // Field right:Lorg/h2/expression/Expression;
     717: aload_1
     718: invokevirtual #47                 // Method org/h2/expression/Expression.optimize:(Lorg/h2/engine/Session;)Lorg/h2/expression/Expression;
     721: putfield      #5                  // Field right:Lorg/h2/expression/Expression;
     724: aload         4
     726: iconst_1
     727: aload_0
     728: getfield      #5                  // Field right:Lorg/h2/expression/Expression;
     731: invokevirtual #60                 // Method org/h2/expression/Function.setParameter:(ILorg/h2/expression/Expression;)V
     734: aload         4
     736: iconst_2
     737: aload_0
     738: getfield      #4                  // Field left:Lorg/h2/expression/Expression;
     741: invokevirtual #60                 // Method org/h2/expression/Function.setParameter:(ILorg/h2/expression/Expression;)V
     744: aload         4
     746: invokevirtual #61                 // Method org/h2/expression/Function.doneWithParameters:()V
     749: aload         4
     751: aload_1
     752: invokevirtual #62                 // Method org/h2/expression/Function.optimize:(Lorg/h2/engine/Session;)Lorg/h2/expression/Expression;
     755: areturn
     756: iload_2
     757: bipush        10
     759: if_icmpeq     768
     762: iload_2
     763: bipush        11
     765: if_icmpne     851
     768: iload_3
     769: bipush        9
     771: if_icmpne     782
     774: aload_0
     775: bipush        11
     777: putfield      #29                 // Field dataType:I
     780: aload_0
     781: areturn
     782: iload_3
     783: bipush        10
     785: if_icmpeq     794
     788: iload_3
     789: bipush        11
     791: if_icmpne     952
     794: aload_1
     795: invokevirtual #33                 // Method org/h2/engine/Session.getDatabase:()Lorg/h2/engine/Database;
     798: ldc           #70                 // String DATEDIFF
     800: invokestatic  #58                 // Method org/h2/expression/Function.getFunction:(Lorg/h2/engine/Database;Ljava/lang/String;)Lorg/h2/expression/Function;
     803: astore        4
     805: aload         4
     807: iconst_0
     808: ldc           #59                 // String DAY
     810: invokestatic  #39                 // Method org/h2/value/ValueString.get:(Ljava/lang/String;)Lorg/h2/value/Value;
     813: invokestatic  #51                 // Method org/h2/expression/ValueExpression.get:(Lorg/h2/value/Value;)Lorg/h2/expression/ValueExpression;
     816: invokevirtual #60                 // Method org/h2/expression/Function.setParameter:(ILorg/h2/expression/Expression;)V
     819: aload         4
     821: iconst_1
     822: aload_0
     823: getfield      #5                  // Field right:Lorg/h2/expression/Expression;
     826: invokevirtual #60                 // Method org/h2/expression/Function.setParameter:(ILorg/h2/expression/Expression;)V
     829: aload         4
     831: iconst_2
     832: aload_0
     833: getfield      #4                  // Field left:Lorg/h2/expression/Expression;
     836: invokevirtual #60                 // Method org/h2/expression/Function.setParameter:(ILorg/h2/expression/Expression;)V
     839: aload         4
     841: invokevirtual #61                 // Method org/h2/expression/Function.doneWithParameters:()V
     844: aload         4
     846: aload_1
     847: invokevirtual #62                 // Method org/h2/expression/Function.optimize:(Lorg/h2/engine/Session;)Lorg/h2/expression/Expression;
     850: areturn
     851: iload_2
     852: bipush        9
     854: if_icmpne     952
     857: iload_3
     858: bipush        9
     860: if_icmpne     952
     863: aload_0
     864: bipush        9
     866: putfield      #29                 // Field dataType:I
     869: aload_0
     870: areturn
     871: aload_0
     872: getfield      #3                  // Field opType:Lorg/h2/expression/Operation$OpType;
     875: getstatic     #65                 // Field org/h2/expression/Operation$OpType.MULTIPLY:Lorg/h2/expression/Operation$OpType;
     878: if_acmpne     923
     881: iload_2
     882: bipush        9
     884: if_icmpne     900
     887: aload_0
     888: bipush        9
     890: putfield      #29                 // Field dataType:I
     893: aload_0
     894: iconst_0
     895: putfield      #2                  // Field convertRight:Z
     898: aload_0
     899: areturn
     900: iload_3
     901: bipush        9
     903: if_icmpne     952
     906: aload_0
     907: invokespecial #56                 // Method swap:()V
     910: aload_0
     911: bipush        9
     913: putfield      #29                 // Field dataType:I
     916: aload_0
     917: iconst_0
     918: putfield      #2                  // Field convertRight:Z
     921: aload_0
     922: areturn
     923: aload_0
     924: getfield      #3                  // Field opType:Lorg/h2/expression/Operation$OpType;
     927: getstatic     #71                 // Field org/h2/expression/Operation$OpType.DIVIDE:Lorg/h2/expression/Operation$OpType;
     930: if_acmpne     952
     933: iload_2
     934: bipush        9
     936: if_icmpne     952
     939: aload_0
     940: bipush        9
     942: putfield      #29                 // Field dataType:I
     945: aload_0
     946: iconst_0
     947: putfield      #2                  // Field convertRight:Z
     950: aload_0
     951: areturn
     952: new           #7                  // class java/lang/StringBuilder
     955: dup
     956: invokespecial #8                  // Method java/lang/StringBuilder."<init>":()V
     959: iload_2
     960: invokestatic  #72                 // Method org/h2/value/DataType.getDataType:(I)Lorg/h2/value/DataType;
     963: getfield      #73                 // Field org/h2/value/DataType.name:Ljava/lang/String;
     966: invokevirtual #10                 // Method java/lang/StringBuilder.append:(Ljava/lang/String;)Ljava/lang/StringBuilder;
     969: ldc           #13                 // String
     971: invokevirtual #10                 // Method java/lang/StringBuilder.append:(Ljava/lang/String;)Ljava/lang/StringBuilder;
     974: aload_0
     975: invokespecial #14                 // Method getOperationToken:()Ljava/lang/String;
     978: invokevirtual #10                 // Method java/lang/StringBuilder.append:(Ljava/lang/String;)Ljava/lang/StringBuilder;
     981: ldc           #13                 // String
     983: invokevirtual #10                 // Method java/lang/StringBuilder.append:(Ljava/lang/String;)Ljava/lang/StringBuilder;
     986: iload_3
     987: invokestatic  #72                 // Method org/h2/value/DataType.getDataType:(I)Lorg/h2/value/DataType;
     990: getfield      #73                 // Field org/h2/value/DataType.name:Ljava/lang/String;
     993: invokevirtual #10                 // Method java/lang/StringBuilder.append:(Ljava/lang/String;)Ljava/lang/StringBuilder;
     996: invokevirtual #12                 // Method java/lang/StringBuilder.toString:()Ljava/lang/String;
     999: invokestatic  #74                 // Method org/h2/message/DbException.getUnsupportedException:(Ljava/lang/String;)Lorg/h2/message/DbException;
    1002: athrow
    1003: aload_0
    1004: iload_2
    1005: iload_3
    1006: invokestatic  #55                 // Method org/h2/value/Value.getHigherOrder:(II)I
    1009: putfield      #29                 // Field dataType:I
    1012: aload_0
    1013: getfield      #29                 // Field dataType:I
    1016: invokestatic  #75                 // Method org/h2/value/DataType.isStringType:(I)Z
    1019: ifeq          1071
    1022: aload_1
    1023: invokevirtual #33                 // Method org/h2/engine/Session.getDatabase:()Lorg/h2/engine/Database;
    1026: invokevirtual #34                 // Method org/h2/engine/Database.getMode:()Lorg/h2/engine/Mode;
    1029: getfield      #53                 // Field org/h2/engine/Mode.allowPlusForStringConcat:Z
    1032: ifeq          1071
    1035: aload_0
    1036: getstatic     #54                 // Field org/h2/expression/Operation$OpType.CONCAT:Lorg/h2/expression/Operation$OpType;
    1039: putfield      #3                  // Field opType:Lorg/h2/expression/Operation$OpType;
    1042: goto          1071
    1045: new           #7                  // class java/lang/StringBuilder
    1048: dup
    1049: invokespecial #8                  // Method java/lang/StringBuilder."<init>":()V
    1052: ldc           #45                 // String type=
    1054: invokevirtual #10                 // Method java/lang/StringBuilder.append:(Ljava/lang/String;)Ljava/lang/StringBuilder;
    1057: aload_0
    1058: getfield      #3                  // Field opType:Lorg/h2/expression/Operation$OpType;
    1061: invokevirtual #26                 // Method java/lang/StringBuilder.append:(Ljava/lang/Object;)Ljava/lang/StringBuilder;
    1064: invokevirtual #12                 // Method java/lang/StringBuilder.toString:()Ljava/lang/String;
    1067: invokestatic  #27                 // Method org/h2/message/DbException.throwInternalError:(Ljava/lang/String;)Ljava/lang/RuntimeException;
    1070: pop
    1071: aload_0
    1072: getfield      #4                  // Field left:Lorg/h2/expression/Expression;
    1075: invokevirtual #49                 // Method org/h2/expression/Expression.isConstant:()Z
    1078: ifeq          1107
    1081: aload_0
    1082: getfield      #5                  // Field right:Lorg/h2/expression/Expression;
    1085: ifnull        1098
    1088: aload_0
    1089: getfield      #5                  // Field right:Lorg/h2/expression/Expression;
    1092: invokevirtual #49                 // Method org/h2/expression/Expression.isConstant:()Z
    1095: ifeq          1107
    1098: aload_0
    1099: aload_1
    1100: invokevirtual #50                 // Method getValue:(Lorg/h2/engine/Session;)Lorg/h2/value/Value;
    1103: invokestatic  #51                 // Method org/h2/expression/ValueExpression.get:(Lorg/h2/value/Value;)Lorg/h2/expression/ValueExpression;
    1106: areturn
    1107: aload_0
    1108: areturn

  private void swap();
    Code:
       0: aload_0
       1: getfield      #4                  // Field left:Lorg/h2/expression/Expression;
       4: astore_1
       5: aload_0
       6: aload_0
       7: getfield      #5                  // Field right:Lorg/h2/expression/Expression;
      10: putfield      #4                  // Field left:Lorg/h2/expression/Expression;
      13: aload_0
      14: aload_1
      15: putfield      #5                  // Field right:Lorg/h2/expression/Expression;
      18: return

  public void setEvaluatable(org.h2.table.TableFilter, boolean);
    Code:
       0: aload_0
       1: getfield      #4                  // Field left:Lorg/h2/expression/Expression;
       4: aload_1
       5: iload_2
       6: invokevirtual #76                 // Method org/h2/expression/Expression.setEvaluatable:(Lorg/h2/table/TableFilter;Z)V
       9: aload_0
      10: getfield      #5                  // Field right:Lorg/h2/expression/Expression;
      13: ifnull        25
      16: aload_0
      17: getfield      #5                  // Field right:Lorg/h2/expression/Expression;
      20: aload_1
      21: iload_2
      22: invokevirtual #76                 // Method org/h2/expression/Expression.setEvaluatable:(Lorg/h2/table/TableFilter;Z)V
      25: return

  public int getType();
    Code:
       0: aload_0
       1: getfield      #29                 // Field dataType:I
       4: ireturn

  public long getPrecision();
    Code:
       0: aload_0
       1: getfield      #5                  // Field right:Lorg/h2/expression/Expression;
       4: ifnull        70
       7: getstatic     #17                 // Field org/h2/expression/Operation$1.$SwitchMap$org$h2$expression$Operation$OpType:[I
      10: aload_0
      11: getfield      #3                  // Field opType:Lorg/h2/expression/Operation$OpType;
      14: invokevirtual #18                 // Method org/h2/expression/Operation$OpType.ordinal:()I
      17: iaload
      18: lookupswitch  { // 1
                     2: 36
               default: 52
          }
      36: aload_0
      37: getfield      #4                  // Field left:Lorg/h2/expression/Expression;
      40: invokevirtual #77                 // Method org/h2/expression/Expression.getPrecision:()J
      43: aload_0
      44: getfield      #5                  // Field right:Lorg/h2/expression/Expression;
      47: invokevirtual #77                 // Method org/h2/expression/Expression.getPrecision:()J
      50: ladd
      51: lreturn
      52: aload_0
      53: getfield      #4                  // Field left:Lorg/h2/expression/Expression;
      56: invokevirtual #77                 // Method org/h2/expression/Expression.getPrecision:()J
      59: aload_0
      60: getfield      #5                  // Field right:Lorg/h2/expression/Expression;
      63: invokevirtual #77                 // Method org/h2/expression/Expression.getPrecision:()J
      66: invokestatic  #78                 // Method java/lang/Math.max:(JJ)J
      69: lreturn
      70: aload_0
      71: getfield      #4                  // Field left:Lorg/h2/expression/Expression;
      74: invokevirtual #77                 // Method org/h2/expression/Expression.getPrecision:()J
      77: lreturn

  public int getDisplaySize();
    Code:
       0: aload_0
       1: getfield      #5                  // Field right:Lorg/h2/expression/Expression;
       4: ifnull        75
       7: getstatic     #17                 // Field org/h2/expression/Operation$1.$SwitchMap$org$h2$expression$Operation$OpType:[I
      10: aload_0
      11: getfield      #3                  // Field opType:Lorg/h2/expression/Operation$OpType;
      14: invokevirtual #18                 // Method org/h2/expression/Operation$OpType.ordinal:()I
      17: iaload
      18: lookupswitch  { // 1
                     2: 36
               default: 57
          }
      36: aload_0
      37: getfield      #4                  // Field left:Lorg/h2/expression/Expression;
      40: invokevirtual #79                 // Method org/h2/expression/Expression.getDisplaySize:()I
      43: i2l
      44: aload_0
      45: getfield      #5                  // Field right:Lorg/h2/expression/Expression;
      48: invokevirtual #79                 // Method org/h2/expression/Expression.getDisplaySize:()I
      51: i2l
      52: ladd
      53: invokestatic  #80                 // Method org/h2/util/MathUtils.convertLongToInt:(J)I
      56: ireturn
      57: aload_0
      58: getfield      #4                  // Field left:Lorg/h2/expression/Expression;
      61: invokevirtual #79                 // Method org/h2/expression/Expression.getDisplaySize:()I
      64: aload_0
      65: getfield      #5                  // Field right:Lorg/h2/expression/Expression;
      68: invokevirtual #79                 // Method org/h2/expression/Expression.getDisplaySize:()I
      71: invokestatic  #81                 // Method java/lang/Math.max:(II)I
      74: ireturn
      75: aload_0
      76: getfield      #4                  // Field left:Lorg/h2/expression/Expression;
      79: invokevirtual #79                 // Method org/h2/expression/Expression.getDisplaySize:()I
      82: ireturn

  public int getScale();
    Code:
       0: aload_0
       1: getfield      #5                  // Field right:Lorg/h2/expression/Expression;
       4: ifnull        25
       7: aload_0
       8: getfield      #4                  // Field left:Lorg/h2/expression/Expression;
      11: invokevirtual #82                 // Method org/h2/expression/Expression.getScale:()I
      14: aload_0
      15: getfield      #5                  // Field right:Lorg/h2/expression/Expression;
      18: invokevirtual #82                 // Method org/h2/expression/Expression.getScale:()I
      21: invokestatic  #81                 // Method java/lang/Math.max:(II)I
      24: ireturn
      25: aload_0
      26: getfield      #4                  // Field left:Lorg/h2/expression/Expression;
      29: invokevirtual #82                 // Method org/h2/expression/Expression.getScale:()I
      32: ireturn

  public void updateAggregate(org.h2.engine.Session);
    Code:
       0: aload_0
       1: getfield      #4                  // Field left:Lorg/h2/expression/Expression;
       4: aload_1
       5: invokevirtual #83                 // Method org/h2/expression/Expression.updateAggregate:(Lorg/h2/engine/Session;)V
       8: aload_0
       9: getfield      #5                  // Field right:Lorg/h2/expression/Expression;
      12: ifnull        23
      15: aload_0
      16: getfield      #5                  // Field right:Lorg/h2/expression/Expression;
      19: aload_1
      20: invokevirtual #83                 // Method org/h2/expression/Expression.updateAggregate:(Lorg/h2/engine/Session;)V
      23: return

  public boolean isEverything(org.h2.expression.ExpressionVisitor);
    Code:
       0: aload_0
       1: getfield      #4                  // Field left:Lorg/h2/expression/Expression;
       4: aload_1
       5: invokevirtual #84                 // Method org/h2/expression/Expression.isEverything:(Lorg/h2/expression/ExpressionVisitor;)Z
       8: ifeq          33
      11: aload_0
      12: getfield      #5                  // Field right:Lorg/h2/expression/Expression;
      15: ifnull        29
      18: aload_0
      19: getfield      #5                  // Field right:Lorg/h2/expression/Expression;
      22: aload_1
      23: invokevirtual #84                 // Method org/h2/expression/Expression.isEverything:(Lorg/h2/expression/ExpressionVisitor;)Z
      26: ifeq          33
      29: iconst_1
      30: goto          34
      33: iconst_0
      34: ireturn

  public int getCost();
    Code:
       0: aload_0
       1: getfield      #4                  // Field left:Lorg/h2/expression/Expression;
       4: invokevirtual #85                 // Method org/h2/expression/Expression.getCost:()I
       7: iconst_1
       8: iadd
       9: aload_0
      10: getfield      #5                  // Field right:Lorg/h2/expression/Expression;
      13: ifnonnull     20
      16: iconst_0
      17: goto          27
      20: aload_0
      21: getfield      #5                  // Field right:Lorg/h2/expression/Expression;
      24: invokevirtual #85                 // Method org/h2/expression/Expression.getCost:()I
      27: iadd
      28: ireturn
}
