Compiled from "Variable.java"
public class org.h2.expression.Variable extends org.h2.expression.Expression {
  private final java.lang.String name;

  private org.h2.value.Value lastValue;

  public org.h2.expression.Variable(org.h2.engine.Session, java.lang.String);
    Code:
       0: aload_0
       1: invokespecial #1                  // Method org/h2/expression/Expression."<init>":()V
       4: aload_0
       5: aload_2
       6: putfield      #2                  // Field name:Ljava/lang/String;
       9: aload_0
      10: aload_1
      11: aload_2
      12: invokevirtual #3                  // Method org/h2/engine/Session.getVariable:(Ljava/lang/String;)Lorg/h2/value/Value;
      15: putfield      #4                  // Field lastValue:Lorg/h2/value/Value;
      18: return

  public int getCost();
    Code:
       0: iconst_0
       1: ireturn

  public int getDisplaySize();
    Code:
       0: aload_0
       1: getfield      #4                  // Field lastValue:Lorg/h2/value/Value;
       4: invokevirtual #5                  // Method org/h2/value/Value.getDisplaySize:()I
       7: ireturn

  public long getPrecision();
    Code:
       0: aload_0
       1: getfield      #4                  // Field lastValue:Lorg/h2/value/Value;
       4: invokevirtual #6                  // Method org/h2/value/Value.getPrecision:()J
       7: lreturn

  public java.lang.String getSQL();
    Code:
       0: new           #7                  // class java/lang/StringBuilder
       3: dup
       4: invokespecial #8                  // Method java/lang/StringBuilder."<init>":()V
       7: ldc           #9                  // String @
       9: invokevirtual #10                 // Method java/lang/StringBuilder.append:(Ljava/lang/String;)Ljava/lang/StringBuilder;
      12: aload_0
      13: getfield      #2                  // Field name:Ljava/lang/String;
      16: invokestatic  #11                 // Method org/h2/command/Parser.quoteIdentifier:(Ljava/lang/String;)Ljava/lang/String;
      19: invokevirtual #10                 // Method java/lang/StringBuilder.append:(Ljava/lang/String;)Ljava/lang/StringBuilder;
      22: invokevirtual #12                 // Method java/lang/StringBuilder.toString:()Ljava/lang/String;
      25: areturn

  public int getScale();
    Code:
       0: aload_0
       1: getfield      #4                  // Field lastValue:Lorg/h2/value/Value;
       4: invokevirtual #13                 // Method org/h2/value/Value.getScale:()I
       7: ireturn

  public int getType();
    Code:
       0: aload_0
       1: getfield      #4                  // Field lastValue:Lorg/h2/value/Value;
       4: invokevirtual #14                 // Method org/h2/value/Value.getType:()I
       7: ireturn

  public org.h2.value.Value getValue(org.h2.engine.Session);
    Code:
       0: aload_0
       1: aload_1
       2: aload_0
       3: getfield      #2                  // Field name:Ljava/lang/String;
       6: invokevirtual #3                  // Method org/h2/engine/Session.getVariable:(Ljava/lang/String;)Lorg/h2/value/Value;
       9: putfield      #4                  // Field lastValue:Lorg/h2/value/Value;
      12: aload_0
      13: getfield      #4                  // Field lastValue:Lorg/h2/value/Value;
      16: areturn

  public boolean isEverything(org.h2.expression.ExpressionVisitor);
    Code:
       0: aload_1
       1: invokevirtual #15                 // Method org/h2/expression/ExpressionVisitor.getType:()I
       4: tableswitch   { // 0 to 9
                     0: 60
                     1: 60
                     2: 62
                     3: 60
                     4: 60
                     5: 60
                     6: 60
                     7: 60
                     8: 60
                     9: 60
               default: 64
          }
      60: iconst_1
      61: ireturn
      62: iconst_0
      63: ireturn
      64: new           #7                  // class java/lang/StringBuilder
      67: dup
      68: invokespecial #8                  // Method java/lang/StringBuilder."<init>":()V
      71: ldc           #16                 // String type=
      73: invokevirtual #10                 // Method java/lang/StringBuilder.append:(Ljava/lang/String;)Ljava/lang/StringBuilder;
      76: aload_1
      77: invokevirtual #15                 // Method org/h2/expression/ExpressionVisitor.getType:()I
      80: invokevirtual #17                 // Method java/lang/StringBuilder.append:(I)Ljava/lang/StringBuilder;
      83: invokevirtual #12                 // Method java/lang/StringBuilder.toString:()Ljava/lang/String;
      86: invokestatic  #18                 // Method org/h2/message/DbException.throwInternalError:(Ljava/lang/String;)Ljava/lang/RuntimeException;
      89: athrow

  public void mapColumns(org.h2.table.ColumnResolver, int);
    Code:
       0: return

  public org.h2.expression.Expression optimize(org.h2.engine.Session);
    Code:
       0: aload_0
       1: areturn

  public void setEvaluatable(org.h2.table.TableFilter, boolean);
    Code:
       0: return

  public void updateAggregate(org.h2.engine.Session);
    Code:
       0: return

  public java.lang.String getName();
    Code:
       0: aload_0
       1: getfield      #2                  // Field name:Ljava/lang/String;
       4: areturn
}
