Compiled from "Wildcard.java"
public class org.h2.expression.Wildcard extends org.h2.expression.Expression {
  private final java.lang.String schema;

  private final java.lang.String table;

  public org.h2.expression.Wildcard(java.lang.String, java.lang.String);
    Code:
       0: aload_0
       1: invokespecial #1                  // Method org/h2/expression/Expression."<init>":()V
       4: aload_0
       5: aload_1
       6: putfield      #2                  // Field schema:Ljava/lang/String;
       9: aload_0
      10: aload_2
      11: putfield      #3                  // Field table:Ljava/lang/String;
      14: return

  public boolean isWildcard();
    Code:
       0: iconst_1
       1: ireturn

  public org.h2.value.Value getValue(org.h2.engine.Session);
    Code:
       0: aload_0
       1: invokevirtual #4                  // Method toString:()Ljava/lang/String;
       4: invokestatic  #5                  // Method org/h2/message/DbException.throwInternalError:(Ljava/lang/String;)Ljava/lang/RuntimeException;
       7: athrow

  public int getType();
    Code:
       0: aload_0
       1: invokevirtual #4                  // Method toString:()Ljava/lang/String;
       4: invokestatic  #5                  // Method org/h2/message/DbException.throwInternalError:(Ljava/lang/String;)Ljava/lang/RuntimeException;
       7: athrow

  public void mapColumns(org.h2.table.ColumnResolver, int);
    Code:
       0: ldc           #6                  // int 42000
       2: aload_0
       3: getfield      #3                  // Field table:Ljava/lang/String;
       6: invokestatic  #7                  // Method org/h2/message/DbException.get:(ILjava/lang/String;)Lorg/h2/message/DbException;
       9: athrow

  public org.h2.expression.Expression optimize(org.h2.engine.Session);
    Code:
       0: ldc           #6                  // int 42000
       2: aload_0
       3: getfield      #3                  // Field table:Ljava/lang/String;
       6: invokestatic  #7                  // Method org/h2/message/DbException.get:(ILjava/lang/String;)Lorg/h2/message/DbException;
       9: athrow

  public void setEvaluatable(org.h2.table.TableFilter, boolean);
    Code:
       0: aload_0
       1: invokevirtual #4                  // Method toString:()Ljava/lang/String;
       4: invokestatic  #5                  // Method org/h2/message/DbException.throwInternalError:(Ljava/lang/String;)Ljava/lang/RuntimeException;
       7: pop
       8: return

  public int getScale();
    Code:
       0: aload_0
       1: invokevirtual #4                  // Method toString:()Ljava/lang/String;
       4: invokestatic  #5                  // Method org/h2/message/DbException.throwInternalError:(Ljava/lang/String;)Ljava/lang/RuntimeException;
       7: athrow

  public long getPrecision();
    Code:
       0: aload_0
       1: invokevirtual #4                  // Method toString:()Ljava/lang/String;
       4: invokestatic  #5                  // Method org/h2/message/DbException.throwInternalError:(Ljava/lang/String;)Ljava/lang/RuntimeException;
       7: athrow

  public int getDisplaySize();
    Code:
       0: aload_0
       1: invokevirtual #4                  // Method toString:()Ljava/lang/String;
       4: invokestatic  #5                  // Method org/h2/message/DbException.throwInternalError:(Ljava/lang/String;)Ljava/lang/RuntimeException;
       7: athrow

  public java.lang.String getTableAlias();
    Code:
       0: aload_0
       1: getfield      #3                  // Field table:Ljava/lang/String;
       4: areturn

  public java.lang.String getSchemaName();
    Code:
       0: aload_0
       1: getfield      #2                  // Field schema:Ljava/lang/String;
       4: areturn

  public java.lang.String getSQL();
    Code:
       0: aload_0
       1: getfield      #3                  // Field table:Ljava/lang/String;
       4: ifnonnull     10
       7: ldc           #8                  // String *
       9: areturn
      10: new           #9                  // class java/lang/StringBuilder
      13: dup
      14: invokespecial #10                 // Method java/lang/StringBuilder."<init>":()V
      17: aload_0
      18: getfield      #3                  // Field table:Ljava/lang/String;
      21: invokestatic  #11                 // Method org/h2/util/StringUtils.quoteIdentifier:(Ljava/lang/String;)Ljava/lang/String;
      24: invokevirtual #12                 // Method java/lang/StringBuilder.append:(Ljava/lang/String;)Ljava/lang/StringBuilder;
      27: ldc           #13                 // String .*
      29: invokevirtual #12                 // Method java/lang/StringBuilder.append:(Ljava/lang/String;)Ljava/lang/StringBuilder;
      32: invokevirtual #14                 // Method java/lang/StringBuilder.toString:()Ljava/lang/String;
      35: areturn

  public void updateAggregate(org.h2.engine.Session);
    Code:
       0: aload_0
       1: invokevirtual #4                  // Method toString:()Ljava/lang/String;
       4: invokestatic  #5                  // Method org/h2/message/DbException.throwInternalError:(Ljava/lang/String;)Ljava/lang/RuntimeException;
       7: pop
       8: return

  public boolean isEverything(org.h2.expression.ExpressionVisitor);
    Code:
       0: aload_1
       1: invokevirtual #15                 // Method org/h2/expression/ExpressionVisitor.getType:()I
       4: bipush        8
       6: if_icmpne     11
       9: iconst_1
      10: ireturn
      11: new           #9                  // class java/lang/StringBuilder
      14: dup
      15: invokespecial #10                 // Method java/lang/StringBuilder."<init>":()V
      18: ldc           #16                 // String
      20: invokevirtual #12                 // Method java/lang/StringBuilder.append:(Ljava/lang/String;)Ljava/lang/StringBuilder;
      23: aload_1
      24: invokevirtual #15                 // Method org/h2/expression/ExpressionVisitor.getType:()I
      27: invokevirtual #17                 // Method java/lang/StringBuilder.append:(I)Ljava/lang/StringBuilder;
      30: invokevirtual #14                 // Method java/lang/StringBuilder.toString:()Ljava/lang/String;
      33: invokestatic  #5                  // Method org/h2/message/DbException.throwInternalError:(Ljava/lang/String;)Ljava/lang/RuntimeException;
      36: athrow

  public int getCost();
    Code:
       0: aload_0
       1: invokevirtual #4                  // Method toString:()Ljava/lang/String;
       4: invokestatic  #5                  // Method org/h2/message/DbException.throwInternalError:(Ljava/lang/String;)Ljava/lang/RuntimeException;
       7: athrow
}
