Compiled from "GrpcService.java"
public final class io.grpc.xds.shaded.io.envoyproxy.envoy.config.core.v3.GrpcService$GoogleGrpc$Builder extends com.google.protobuf.GeneratedMessageV3$Builder<io.grpc.xds.shaded.io.envoyproxy.envoy.config.core.v3.GrpcService$GoogleGrpc$Builder> implements io.grpc.xds.shaded.io.envoyproxy.envoy.config.core.v3.GrpcService$GoogleGrpcOrBuilder {
  private int bitField0_;

  private java.lang.Object targetUri_;

  private io.grpc.xds.shaded.io.envoyproxy.envoy.config.core.v3.GrpcService$GoogleGrpc$ChannelCredentials channelCredentials_;

  private com.google.protobuf.SingleFieldBuilderV3<io.grpc.xds.shaded.io.envoyproxy.envoy.config.core.v3.GrpcService$GoogleGrpc$ChannelCredentials, io.grpc.xds.shaded.io.envoyproxy.envoy.config.core.v3.GrpcService$GoogleGrpc$ChannelCredentials$Builder, io.grpc.xds.shaded.io.envoyproxy.envoy.config.core.v3.GrpcService$GoogleGrpc$ChannelCredentialsOrBuilder> channelCredentialsBuilder_;

  private java.util.List<io.grpc.xds.shaded.io.envoyproxy.envoy.config.core.v3.GrpcService$GoogleGrpc$CallCredentials> callCredentials_;

  private com.google.protobuf.RepeatedFieldBuilderV3<io.grpc.xds.shaded.io.envoyproxy.envoy.config.core.v3.GrpcService$GoogleGrpc$CallCredentials, io.grpc.xds.shaded.io.envoyproxy.envoy.config.core.v3.GrpcService$GoogleGrpc$CallCredentials$Builder, io.grpc.xds.shaded.io.envoyproxy.envoy.config.core.v3.GrpcService$GoogleGrpc$CallCredentialsOrBuilder> callCredentialsBuilder_;

  private java.lang.Object statPrefix_;

  private java.lang.Object credentialsFactoryName_;

  private com.google.protobuf.Struct config_;

  private com.google.protobuf.SingleFieldBuilderV3<com.google.protobuf.Struct, com.google.protobuf.Struct$Builder, com.google.protobuf.StructOrBuilder> configBuilder_;

  private com.google.protobuf.UInt32Value perStreamBufferLimitBytes_;

  private com.google.protobuf.SingleFieldBuilderV3<com.google.protobuf.UInt32Value, com.google.protobuf.UInt32Value$Builder, com.google.protobuf.UInt32ValueOrBuilder> perStreamBufferLimitBytesBuilder_;

  private io.grpc.xds.shaded.io.envoyproxy.envoy.config.core.v3.GrpcService$GoogleGrpc$ChannelArgs channelArgs_;

  private com.google.protobuf.SingleFieldBuilderV3<io.grpc.xds.shaded.io.envoyproxy.envoy.config.core.v3.GrpcService$GoogleGrpc$ChannelArgs, io.grpc.xds.shaded.io.envoyproxy.envoy.config.core.v3.GrpcService$GoogleGrpc$ChannelArgs$Builder, io.grpc.xds.shaded.io.envoyproxy.envoy.config.core.v3.GrpcService$GoogleGrpc$ChannelArgsOrBuilder> channelArgsBuilder_;

  public static final com.google.protobuf.Descriptors$Descriptor getDescriptor();
    Code:
       0: getstatic     #123                // Field io/grpc/xds/shaded/io/envoyproxy/envoy/config/core/v3/GrpcServiceProto.internal_static_envoy_config_core_v3_GrpcService_GoogleGrpc_descriptor:Lcom/google/protobuf/Descriptors$Descriptor;
       3: areturn

  protected com.google.protobuf.GeneratedMessageV3$FieldAccessorTable internalGetFieldAccessorTable();
    Code:
       0: getstatic     #129                // Field io/grpc/xds/shaded/io/envoyproxy/envoy/config/core/v3/GrpcServiceProto.internal_static_envoy_config_core_v3_GrpcService_GoogleGrpc_fieldAccessorTable:Lcom/google/protobuf/GeneratedMessageV3$FieldAccessorTable;
       3: ldc           #10                 // class io/grpc/xds/shaded/io/envoyproxy/envoy/config/core/v3/GrpcService$GoogleGrpc
       5: ldc           #2                  // class io/grpc/xds/shaded/io/envoyproxy/envoy/config/core/v3/GrpcService$GoogleGrpc$Builder
       7: invokevirtual #133                // Method com/google/protobuf/GeneratedMessageV3$FieldAccessorTable.ensureFieldAccessorsInitialized:(Ljava/lang/Class;Ljava/lang/Class;)Lcom/google/protobuf/GeneratedMessageV3$FieldAccessorTable;
      10: areturn

  private io.grpc.xds.shaded.io.envoyproxy.envoy.config.core.v3.GrpcService$GoogleGrpc$Builder();
    Code:
       0: aload_0
       1: invokespecial #139                // Method com/google/protobuf/GeneratedMessageV3$Builder."<init>":()V
       4: aload_0
       5: ldc           #141                // String
       7: putfield      #143                // Field targetUri_:Ljava/lang/Object;
      10: aload_0
      11: invokestatic  #149                // Method java/util/Collections.emptyList:()Ljava/util/List;
      14: putfield      #151                // Field callCredentials_:Ljava/util/List;
      17: aload_0
      18: ldc           #141                // String
      20: putfield      #153                // Field statPrefix_:Ljava/lang/Object;
      23: aload_0
      24: ldc           #141                // String
      26: putfield      #155                // Field credentialsFactoryName_:Ljava/lang/Object;
      29: aload_0
      30: invokespecial #158                // Method maybeForceBuilderInitialization:()V
      33: return

  private io.grpc.xds.shaded.io.envoyproxy.envoy.config.core.v3.GrpcService$GoogleGrpc$Builder(com.google.protobuf.GeneratedMessageV3$BuilderParent);
    Code:
       0: aload_0
       1: aload_1
       2: invokespecial #161                // Method com/google/protobuf/GeneratedMessageV3$Builder."<init>":(Lcom/google/protobuf/GeneratedMessageV3$BuilderParent;)V
       5: aload_0
       6: ldc           #141                // String
       8: putfield      #143                // Field targetUri_:Ljava/lang/Object;
      11: aload_0
      12: invokestatic  #149                // Method java/util/Collections.emptyList:()Ljava/util/List;
      15: putfield      #151                // Field callCredentials_:Ljava/util/List;
      18: aload_0
      19: ldc           #141                // String
      21: putfield      #153                // Field statPrefix_:Ljava/lang/Object;
      24: aload_0
      25: ldc           #141                // String
      27: putfield      #155                // Field credentialsFactoryName_:Ljava/lang/Object;
      30: aload_0
      31: invokespecial #158                // Method maybeForceBuilderInitialization:()V
      34: return

  private void maybeForceBuilderInitialization();
    Code:
       0: invokestatic  #167                // Method io/grpc/xds/shaded/io/envoyproxy/envoy/config/core/v3/GrpcService$GoogleGrpc.access$12600:()Z
       3: ifeq          11
       6: aload_0
       7: invokespecial #171                // Method getCallCredentialsFieldBuilder:()Lcom/google/protobuf/RepeatedFieldBuilderV3;
      10: pop
      11: return

  public io.grpc.xds.shaded.io.envoyproxy.envoy.config.core.v3.GrpcService$GoogleGrpc$Builder clear();
    Code:
       0: aload_0
       1: invokespecial #176                // Method com/google/protobuf/GeneratedMessageV3$Builder.clear:()Lcom/google/protobuf/GeneratedMessageV3$Builder;
       4: pop
       5: aload_0
       6: ldc           #141                // String
       8: putfield      #143                // Field targetUri_:Ljava/lang/Object;
      11: aload_0
      12: getfield      #178                // Field channelCredentialsBuilder_:Lcom/google/protobuf/SingleFieldBuilderV3;
      15: ifnonnull     26
      18: aload_0
      19: aconst_null
      20: putfield      #180                // Field channelCredentials_:Lio/grpc/xds/shaded/io/envoyproxy/envoy/config/core/v3/GrpcService$GoogleGrpc$ChannelCredentials;
      23: goto          36
      26: aload_0
      27: aconst_null
      28: putfield      #180                // Field channelCredentials_:Lio/grpc/xds/shaded/io/envoyproxy/envoy/config/core/v3/GrpcService$GoogleGrpc$ChannelCredentials;
      31: aload_0
      32: aconst_null
      33: putfield      #178                // Field channelCredentialsBuilder_:Lcom/google/protobuf/SingleFieldBuilderV3;
      36: aload_0
      37: getfield      #182                // Field callCredentialsBuilder_:Lcom/google/protobuf/RepeatedFieldBuilderV3;
      40: ifnonnull     64
      43: aload_0
      44: invokestatic  #149                // Method java/util/Collections.emptyList:()Ljava/util/List;
      47: putfield      #151                // Field callCredentials_:Ljava/util/List;
      50: aload_0
      51: aload_0
      52: getfield      #184                // Field bitField0_:I
      55: bipush        -2
      57: iand
      58: putfield      #184                // Field bitField0_:I
      61: goto          71
      64: aload_0
      65: getfield      #182                // Field callCredentialsBuilder_:Lcom/google/protobuf/RepeatedFieldBuilderV3;
      68: invokevirtual #188                // Method com/google/protobuf/RepeatedFieldBuilderV3.clear:()V
      71: aload_0
      72: ldc           #141                // String
      74: putfield      #153                // Field statPrefix_:Ljava/lang/Object;
      77: aload_0
      78: ldc           #141                // String
      80: putfield      #155                // Field credentialsFactoryName_:Ljava/lang/Object;
      83: aload_0
      84: getfield      #190                // Field configBuilder_:Lcom/google/protobuf/SingleFieldBuilderV3;
      87: ifnonnull     98
      90: aload_0
      91: aconst_null
      92: putfield      #192                // Field config_:Lcom/google/protobuf/Struct;
      95: goto          108
      98: aload_0
      99: aconst_null
     100: putfield      #192                // Field config_:Lcom/google/protobuf/Struct;
     103: aload_0
     104: aconst_null
     105: putfield      #190                // Field configBuilder_:Lcom/google/protobuf/SingleFieldBuilderV3;
     108: aload_0
     109: getfield      #194                // Field perStreamBufferLimitBytesBuilder_:Lcom/google/protobuf/SingleFieldBuilderV3;
     112: ifnonnull     123
     115: aload_0
     116: aconst_null
     117: putfield      #196                // Field perStreamBufferLimitBytes_:Lcom/google/protobuf/UInt32Value;
     120: goto          133
     123: aload_0
     124: aconst_null
     125: putfield      #196                // Field perStreamBufferLimitBytes_:Lcom/google/protobuf/UInt32Value;
     128: aload_0
     129: aconst_null
     130: putfield      #194                // Field perStreamBufferLimitBytesBuilder_:Lcom/google/protobuf/SingleFieldBuilderV3;
     133: aload_0
     134: getfield      #198                // Field channelArgsBuilder_:Lcom/google/protobuf/SingleFieldBuilderV3;
     137: ifnonnull     148
     140: aload_0
     141: aconst_null
     142: putfield      #200                // Field channelArgs_:Lio/grpc/xds/shaded/io/envoyproxy/envoy/config/core/v3/GrpcService$GoogleGrpc$ChannelArgs;
     145: goto          158
     148: aload_0
     149: aconst_null
     150: putfield      #200                // Field channelArgs_:Lio/grpc/xds/shaded/io/envoyproxy/envoy/config/core/v3/GrpcService$GoogleGrpc$ChannelArgs;
     153: aload_0
     154: aconst_null
     155: putfield      #198                // Field channelArgsBuilder_:Lcom/google/protobuf/SingleFieldBuilderV3;
     158: aload_0
     159: areturn

  public com.google.protobuf.Descriptors$Descriptor getDescriptorForType();
    Code:
       0: getstatic     #123                // Field io/grpc/xds/shaded/io/envoyproxy/envoy/config/core/v3/GrpcServiceProto.internal_static_envoy_config_core_v3_GrpcService_GoogleGrpc_descriptor:Lcom/google/protobuf/Descriptors$Descriptor;
       3: areturn

  public io.grpc.xds.shaded.io.envoyproxy.envoy.config.core.v3.GrpcService$GoogleGrpc getDefaultInstanceForType();
    Code:
       0: invokestatic  #206                // Method io/grpc/xds/shaded/io/envoyproxy/envoy/config/core/v3/GrpcService$GoogleGrpc.getDefaultInstance:()Lio/grpc/xds/shaded/io/envoyproxy/envoy/config/core/v3/GrpcService$GoogleGrpc;
       3: areturn

  public io.grpc.xds.shaded.io.envoyproxy.envoy.config.core.v3.GrpcService$GoogleGrpc build();
    Code:
       0: aload_0
       1: invokevirtual #210                // Method buildPartial:()Lio/grpc/xds/shaded/io/envoyproxy/envoy/config/core/v3/GrpcService$GoogleGrpc;
       4: astore_1
       5: aload_1
       6: invokevirtual #213                // Method io/grpc/xds/shaded/io/envoyproxy/envoy/config/core/v3/GrpcService$GoogleGrpc.isInitialized:()Z
       9: ifne          17
      12: aload_1
      13: invokestatic  #217                // Method newUninitializedMessageException:(Lcom/google/protobuf/Message;)Lcom/google/protobuf/UninitializedMessageException;
      16: athrow
      17: aload_1
      18: areturn

  public io.grpc.xds.shaded.io.envoyproxy.envoy.config.core.v3.GrpcService$GoogleGrpc buildPartial();
    Code:
       0: new           #10                 // class io/grpc/xds/shaded/io/envoyproxy/envoy/config/core/v3/GrpcService$GoogleGrpc
       3: dup
       4: aload_0
       5: aconst_null
       6: invokespecial #222                // Method io/grpc/xds/shaded/io/envoyproxy/envoy/config/core/v3/GrpcService$GoogleGrpc."<init>":(Lcom/google/protobuf/GeneratedMessageV3$Builder;Lio/grpc/xds/shaded/io/envoyproxy/envoy/config/core/v3/GrpcService$1;)V
       9: astore_1
      10: aload_0
      11: getfield      #184                // Field bitField0_:I
      14: istore_2
      15: aload_1
      16: aload_0
      17: getfield      #143                // Field targetUri_:Ljava/lang/Object;
      20: invokestatic  #226                // Method io/grpc/xds/shaded/io/envoyproxy/envoy/config/core/v3/GrpcService$GoogleGrpc.access$12802:(Lio/grpc/xds/shaded/io/envoyproxy/envoy/config/core/v3/GrpcService$GoogleGrpc;Ljava/lang/Object;)Ljava/lang/Object;
      23: pop
      24: aload_0
      25: getfield      #178                // Field channelCredentialsBuilder_:Lcom/google/protobuf/SingleFieldBuilderV3;
      28: ifnonnull     43
      31: aload_1
      32: aload_0
      33: getfield      #180                // Field channelCredentials_:Lio/grpc/xds/shaded/io/envoyproxy/envoy/config/core/v3/GrpcService$GoogleGrpc$ChannelCredentials;
      36: invokestatic  #230                // Method io/grpc/xds/shaded/io/envoyproxy/envoy/config/core/v3/GrpcService$GoogleGrpc.access$12902:(Lio/grpc/xds/shaded/io/envoyproxy/envoy/config/core/v3/GrpcService$GoogleGrpc;Lio/grpc/xds/shaded/io/envoyproxy/envoy/config/core/v3/GrpcService$GoogleGrpc$ChannelCredentials;)Lio/grpc/xds/shaded/io/envoyproxy/envoy/config/core/v3/GrpcService$GoogleGrpc$ChannelCredentials;
      39: pop
      40: goto          58
      43: aload_1
      44: aload_0
      45: getfield      #178                // Field channelCredentialsBuilder_:Lcom/google/protobuf/SingleFieldBuilderV3;
      48: invokevirtual #235                // Method com/google/protobuf/SingleFieldBuilderV3.build:()Lcom/google/protobuf/AbstractMessage;
      51: checkcast     #15                 // class io/grpc/xds/shaded/io/envoyproxy/envoy/config/core/v3/GrpcService$GoogleGrpc$ChannelCredentials
      54: invokestatic  #230                // Method io/grpc/xds/shaded/io/envoyproxy/envoy/config/core/v3/GrpcService$GoogleGrpc.access$12902:(Lio/grpc/xds/shaded/io/envoyproxy/envoy/config/core/v3/GrpcService$GoogleGrpc;Lio/grpc/xds/shaded/io/envoyproxy/envoy/config/core/v3/GrpcService$GoogleGrpc$ChannelCredentials;)Lio/grpc/xds/shaded/io/envoyproxy/envoy/config/core/v3/GrpcService$GoogleGrpc$ChannelCredentials;
      57: pop
      58: aload_0
      59: getfield      #182                // Field callCredentialsBuilder_:Lcom/google/protobuf/RepeatedFieldBuilderV3;
      62: ifnonnull     108
      65: aload_0
      66: getfield      #184                // Field bitField0_:I
      69: iconst_1
      70: iand
      71: ifeq          96
      74: aload_0
      75: aload_0
      76: getfield      #151                // Field callCredentials_:Ljava/util/List;
      79: invokestatic  #239                // Method java/util/Collections.unmodifiableList:(Ljava/util/List;)Ljava/util/List;
      82: putfield      #151                // Field callCredentials_:Ljava/util/List;
      85: aload_0
      86: aload_0
      87: getfield      #184                // Field bitField0_:I
      90: bipush        -2
      92: iand
      93: putfield      #184                // Field bitField0_:I
      96: aload_1
      97: aload_0
      98: getfield      #151                // Field callCredentials_:Ljava/util/List;
     101: invokestatic  #243                // Method io/grpc/xds/shaded/io/envoyproxy/envoy/config/core/v3/GrpcService$GoogleGrpc.access$13002:(Lio/grpc/xds/shaded/io/envoyproxy/envoy/config/core/v3/GrpcService$GoogleGrpc;Ljava/util/List;)Ljava/util/List;
     104: pop
     105: goto          120
     108: aload_1
     109: aload_0
     110: getfield      #182                // Field callCredentialsBuilder_:Lcom/google/protobuf/RepeatedFieldBuilderV3;
     113: invokevirtual #245                // Method com/google/protobuf/RepeatedFieldBuilderV3.build:()Ljava/util/List;
     116: invokestatic  #243                // Method io/grpc/xds/shaded/io/envoyproxy/envoy/config/core/v3/GrpcService$GoogleGrpc.access$13002:(Lio/grpc/xds/shaded/io/envoyproxy/envoy/config/core/v3/GrpcService$GoogleGrpc;Ljava/util/List;)Ljava/util/List;
     119: pop
     120: aload_1
     121: aload_0
     122: getfield      #153                // Field statPrefix_:Ljava/lang/Object;
     125: invokestatic  #248                // Method io/grpc/xds/shaded/io/envoyproxy/envoy/config/core/v3/GrpcService$GoogleGrpc.access$13102:(Lio/grpc/xds/shaded/io/envoyproxy/envoy/config/core/v3/GrpcService$GoogleGrpc;Ljava/lang/Object;)Ljava/lang/Object;
     128: pop
     129: aload_1
     130: aload_0
     131: getfield      #155                // Field credentialsFactoryName_:Ljava/lang/Object;
     134: invokestatic  #251                // Method io/grpc/xds/shaded/io/envoyproxy/envoy/config/core/v3/GrpcService$GoogleGrpc.access$13202:(Lio/grpc/xds/shaded/io/envoyproxy/envoy/config/core/v3/GrpcService$GoogleGrpc;Ljava/lang/Object;)Ljava/lang/Object;
     137: pop
     138: aload_0
     139: getfield      #190                // Field configBuilder_:Lcom/google/protobuf/SingleFieldBuilderV3;
     142: ifnonnull     157
     145: aload_1
     146: aload_0
     147: getfield      #192                // Field config_:Lcom/google/protobuf/Struct;
     150: invokestatic  #255                // Method io/grpc/xds/shaded/io/envoyproxy/envoy/config/core/v3/GrpcService$GoogleGrpc.access$13302:(Lio/grpc/xds/shaded/io/envoyproxy/envoy/config/core/v3/GrpcService$GoogleGrpc;Lcom/google/protobuf/Struct;)Lcom/google/protobuf/Struct;
     153: pop
     154: goto          172
     157: aload_1
     158: aload_0
     159: getfield      #190                // Field configBuilder_:Lcom/google/protobuf/SingleFieldBuilderV3;
     162: invokevirtual #235                // Method com/google/protobuf/SingleFieldBuilderV3.build:()Lcom/google/protobuf/AbstractMessage;
     165: checkcast     #34                 // class com/google/protobuf/Struct
     168: invokestatic  #255                // Method io/grpc/xds/shaded/io/envoyproxy/envoy/config/core/v3/GrpcService$GoogleGrpc.access$13302:(Lio/grpc/xds/shaded/io/envoyproxy/envoy/config/core/v3/GrpcService$GoogleGrpc;Lcom/google/protobuf/Struct;)Lcom/google/protobuf/Struct;
     171: pop
     172: aload_0
     173: getfield      #194                // Field perStreamBufferLimitBytesBuilder_:Lcom/google/protobuf/SingleFieldBuilderV3;
     176: ifnonnull     191
     179: aload_1
     180: aload_0
     181: getfield      #196                // Field perStreamBufferLimitBytes_:Lcom/google/protobuf/UInt32Value;
     184: invokestatic  #259                // Method io/grpc/xds/shaded/io/envoyproxy/envoy/config/core/v3/GrpcService$GoogleGrpc.access$13402:(Lio/grpc/xds/shaded/io/envoyproxy/envoy/config/core/v3/GrpcService$GoogleGrpc;Lcom/google/protobuf/UInt32Value;)Lcom/google/protobuf/UInt32Value;
     187: pop
     188: goto          206
     191: aload_1
     192: aload_0
     193: getfield      #194                // Field perStreamBufferLimitBytesBuilder_:Lcom/google/protobuf/SingleFieldBuilderV3;
     196: invokevirtual #235                // Method com/google/protobuf/SingleFieldBuilderV3.build:()Lcom/google/protobuf/AbstractMessage;
     199: checkcast     #38                 // class com/google/protobuf/UInt32Value
     202: invokestatic  #259                // Method io/grpc/xds/shaded/io/envoyproxy/envoy/config/core/v3/GrpcService$GoogleGrpc.access$13402:(Lio/grpc/xds/shaded/io/envoyproxy/envoy/config/core/v3/GrpcService$GoogleGrpc;Lcom/google/protobuf/UInt32Value;)Lcom/google/protobuf/UInt32Value;
     205: pop
     206: aload_0
     207: getfield      #198                // Field channelArgsBuilder_:Lcom/google/protobuf/SingleFieldBuilderV3;
     210: ifnonnull     225
     213: aload_1
     214: aload_0
     215: getfield      #200                // Field channelArgs_:Lio/grpc/xds/shaded/io/envoyproxy/envoy/config/core/v3/GrpcService$GoogleGrpc$ChannelArgs;
     218: invokestatic  #263                // Method io/grpc/xds/shaded/io/envoyproxy/envoy/config/core/v3/GrpcService$GoogleGrpc.access$13502:(Lio/grpc/xds/shaded/io/envoyproxy/envoy/config/core/v3/GrpcService$GoogleGrpc;Lio/grpc/xds/shaded/io/envoyproxy/envoy/config/core/v3/GrpcService$GoogleGrpc$ChannelArgs;)Lio/grpc/xds/shaded/io/envoyproxy/envoy/config/core/v3/GrpcService$GoogleGrpc$ChannelArgs;
     221: pop
     222: goto          240
     225: aload_1
     226: aload_0
     227: getfield      #198                // Field channelArgsBuilder_:Lcom/google/protobuf/SingleFieldBuilderV3;
     230: invokevirtual #235                // Method com/google/protobuf/SingleFieldBuilderV3.build:()Lcom/google/protobuf/AbstractMessage;
     233: checkcast     #40                 // class io/grpc/xds/shaded/io/envoyproxy/envoy/config/core/v3/GrpcService$GoogleGrpc$ChannelArgs
     236: invokestatic  #263                // Method io/grpc/xds/shaded/io/envoyproxy/envoy/config/core/v3/GrpcService$GoogleGrpc.access$13502:(Lio/grpc/xds/shaded/io/envoyproxy/envoy/config/core/v3/GrpcService$GoogleGrpc;Lio/grpc/xds/shaded/io/envoyproxy/envoy/config/core/v3/GrpcService$GoogleGrpc$ChannelArgs;)Lio/grpc/xds/shaded/io/envoyproxy/envoy/config/core/v3/GrpcService$GoogleGrpc$ChannelArgs;
     239: pop
     240: aload_0
     241: invokevirtual #266                // Method onBuilt:()V
     244: aload_1
     245: areturn

  public io.grpc.xds.shaded.io.envoyproxy.envoy.config.core.v3.GrpcService$GoogleGrpc$Builder clone();
    Code:
       0: aload_0
       1: invokespecial #270                // Method com/google/protobuf/GeneratedMessageV3$Builder.clone:()Lcom/google/protobuf/GeneratedMessageV3$Builder;
       4: checkcast     #2                  // class io/grpc/xds/shaded/io/envoyproxy/envoy/config/core/v3/GrpcService$GoogleGrpc$Builder
       7: areturn

  public io.grpc.xds.shaded.io.envoyproxy.envoy.config.core.v3.GrpcService$GoogleGrpc$Builder setField(com.google.protobuf.Descriptors$FieldDescriptor, java.lang.Object);
    Code:
       0: aload_0
       1: aload_1
       2: aload_2
       3: invokespecial #275                // Method com/google/protobuf/GeneratedMessageV3$Builder.setField:(Lcom/google/protobuf/Descriptors$FieldDescriptor;Ljava/lang/Object;)Lcom/google/protobuf/GeneratedMessageV3$Builder;
       6: checkcast     #2                  // class io/grpc/xds/shaded/io/envoyproxy/envoy/config/core/v3/GrpcService$GoogleGrpc$Builder
       9: areturn

  public io.grpc.xds.shaded.io.envoyproxy.envoy.config.core.v3.GrpcService$GoogleGrpc$Builder clearField(com.google.protobuf.Descriptors$FieldDescriptor);
    Code:
       0: aload_0
       1: aload_1
       2: invokespecial #283                // Method com/google/protobuf/GeneratedMessageV3$Builder.clearField:(Lcom/google/protobuf/Descriptors$FieldDescriptor;)Lcom/google/protobuf/GeneratedMessageV3$Builder;
       5: checkcast     #2                  // class io/grpc/xds/shaded/io/envoyproxy/envoy/config/core/v3/GrpcService$GoogleGrpc$Builder
       8: areturn

  public io.grpc.xds.shaded.io.envoyproxy.envoy.config.core.v3.GrpcService$GoogleGrpc$Builder clearOneof(com.google.protobuf.Descriptors$OneofDescriptor);
    Code:
       0: aload_0
       1: aload_1
       2: invokespecial #288                // Method com/google/protobuf/GeneratedMessageV3$Builder.clearOneof:(Lcom/google/protobuf/Descriptors$OneofDescriptor;)Lcom/google/protobuf/GeneratedMessageV3$Builder;
       5: checkcast     #2                  // class io/grpc/xds/shaded/io/envoyproxy/envoy/config/core/v3/GrpcService$GoogleGrpc$Builder
       8: areturn

  public io.grpc.xds.shaded.io.envoyproxy.envoy.config.core.v3.GrpcService$GoogleGrpc$Builder setRepeatedField(com.google.protobuf.Descriptors$FieldDescriptor, int, java.lang.Object);
    Code:
       0: aload_0
       1: aload_1
       2: iload_2
       3: aload_3
       4: invokespecial #295                // Method com/google/protobuf/GeneratedMessageV3$Builder.setRepeatedField:(Lcom/google/protobuf/Descriptors$FieldDescriptor;ILjava/lang/Object;)Lcom/google/protobuf/GeneratedMessageV3$Builder;
       7: checkcast     #2                  // class io/grpc/xds/shaded/io/envoyproxy/envoy/config/core/v3/GrpcService$GoogleGrpc$Builder
      10: areturn

  public io.grpc.xds.shaded.io.envoyproxy.envoy.config.core.v3.GrpcService$GoogleGrpc$Builder addRepeatedField(com.google.protobuf.Descriptors$FieldDescriptor, java.lang.Object);
    Code:
       0: aload_0
       1: aload_1
       2: aload_2
       3: invokespecial #299                // Method com/google/protobuf/GeneratedMessageV3$Builder.addRepeatedField:(Lcom/google/protobuf/Descriptors$FieldDescriptor;Ljava/lang/Object;)Lcom/google/protobuf/GeneratedMessageV3$Builder;
       6: checkcast     #2                  // class io/grpc/xds/shaded/io/envoyproxy/envoy/config/core/v3/GrpcService$GoogleGrpc$Builder
       9: areturn

  public io.grpc.xds.shaded.io.envoyproxy.envoy.config.core.v3.GrpcService$GoogleGrpc$Builder mergeFrom(com.google.protobuf.Message);
    Code:
       0: aload_1
       1: instanceof    #10                 // class io/grpc/xds/shaded/io/envoyproxy/envoy/config/core/v3/GrpcService$GoogleGrpc
       4: ifeq          16
       7: aload_0
       8: aload_1
       9: checkcast     #10                 // class io/grpc/xds/shaded/io/envoyproxy/envoy/config/core/v3/GrpcService$GoogleGrpc
      12: invokevirtual #304                // Method mergeFrom:(Lio/grpc/xds/shaded/io/envoyproxy/envoy/config/core/v3/GrpcService$GoogleGrpc;)Lio/grpc/xds/shaded/io/envoyproxy/envoy/config/core/v3/GrpcService$GoogleGrpc$Builder;
      15: areturn
      16: aload_0
      17: aload_1
      18: invokespecial #307                // Method com/google/protobuf/GeneratedMessageV3$Builder.mergeFrom:(Lcom/google/protobuf/Message;)Lcom/google/protobuf/AbstractMessage$Builder;
      21: pop
      22: aload_0
      23: areturn

  public io.grpc.xds.shaded.io.envoyproxy.envoy.config.core.v3.GrpcService$GoogleGrpc$Builder mergeFrom(io.grpc.xds.shaded.io.envoyproxy.envoy.config.core.v3.GrpcService$GoogleGrpc);
    Code:
       0: aload_1
       1: invokestatic  #206                // Method io/grpc/xds/shaded/io/envoyproxy/envoy/config/core/v3/GrpcService$GoogleGrpc.getDefaultInstance:()Lio/grpc/xds/shaded/io/envoyproxy/envoy/config/core/v3/GrpcService$GoogleGrpc;
       4: if_acmpne     9
       7: aload_0
       8: areturn
       9: aload_1
      10: invokevirtual #313                // Method io/grpc/xds/shaded/io/envoyproxy/envoy/config/core/v3/GrpcService$GoogleGrpc.getTargetUri:()Ljava/lang/String;
      13: invokevirtual #318                // Method java/lang/String.isEmpty:()Z
      16: ifne          31
      19: aload_0
      20: aload_1
      21: invokestatic  #322                // Method io/grpc/xds/shaded/io/envoyproxy/envoy/config/core/v3/GrpcService$GoogleGrpc.access$12800:(Lio/grpc/xds/shaded/io/envoyproxy/envoy/config/core/v3/GrpcService$GoogleGrpc;)Ljava/lang/Object;
      24: putfield      #143                // Field targetUri_:Ljava/lang/Object;
      27: aload_0
      28: invokevirtual #325                // Method onChanged:()V
      31: aload_1
      32: invokevirtual #328                // Method io/grpc/xds/shaded/io/envoyproxy/envoy/config/core/v3/GrpcService$GoogleGrpc.hasChannelCredentials:()Z
      35: ifeq          47
      38: aload_0
      39: aload_1
      40: invokevirtual #332                // Method io/grpc/xds/shaded/io/envoyproxy/envoy/config/core/v3/GrpcService$GoogleGrpc.getChannelCredentials:()Lio/grpc/xds/shaded/io/envoyproxy/envoy/config/core/v3/GrpcService$GoogleGrpc$ChannelCredentials;
      43: invokevirtual #336                // Method mergeChannelCredentials:(Lio/grpc/xds/shaded/io/envoyproxy/envoy/config/core/v3/GrpcService$GoogleGrpc$ChannelCredentials;)Lio/grpc/xds/shaded/io/envoyproxy/envoy/config/core/v3/GrpcService$GoogleGrpc$Builder;
      46: pop
      47: aload_0
      48: getfield      #182                // Field callCredentialsBuilder_:Lcom/google/protobuf/RepeatedFieldBuilderV3;
      51: ifnonnull     125
      54: aload_1
      55: invokestatic  #340                // Method io/grpc/xds/shaded/io/envoyproxy/envoy/config/core/v3/GrpcService$GoogleGrpc.access$13000:(Lio/grpc/xds/shaded/io/envoyproxy/envoy/config/core/v3/GrpcService$GoogleGrpc;)Ljava/util/List;
      58: invokeinterface #343,  1          // InterfaceMethod java/util/List.isEmpty:()Z
      63: ifne          211
      66: aload_0
      67: getfield      #151                // Field callCredentials_:Ljava/util/List;
      70: invokeinterface #343,  1          // InterfaceMethod java/util/List.isEmpty:()Z
      75: ifeq          100
      78: aload_0
      79: aload_1
      80: invokestatic  #340                // Method io/grpc/xds/shaded/io/envoyproxy/envoy/config/core/v3/GrpcService$GoogleGrpc.access$13000:(Lio/grpc/xds/shaded/io/envoyproxy/envoy/config/core/v3/GrpcService$GoogleGrpc;)Ljava/util/List;
      83: putfield      #151                // Field callCredentials_:Ljava/util/List;
      86: aload_0
      87: aload_0
      88: getfield      #184                // Field bitField0_:I
      91: bipush        -2
      93: iand
      94: putfield      #184                // Field bitField0_:I
      97: goto          118
     100: aload_0
     101: invokespecial #346                // Method ensureCallCredentialsIsMutable:()V
     104: aload_0
     105: getfield      #151                // Field callCredentials_:Ljava/util/List;
     108: aload_1
     109: invokestatic  #340                // Method io/grpc/xds/shaded/io/envoyproxy/envoy/config/core/v3/GrpcService$GoogleGrpc.access$13000:(Lio/grpc/xds/shaded/io/envoyproxy/envoy/config/core/v3/GrpcService$GoogleGrpc;)Ljava/util/List;
     112: invokeinterface #350,  2          // InterfaceMethod java/util/List.addAll:(Ljava/util/Collection;)Z
     117: pop
     118: aload_0
     119: invokevirtual #325                // Method onChanged:()V
     122: goto          211
     125: aload_1
     126: invokestatic  #340                // Method io/grpc/xds/shaded/io/envoyproxy/envoy/config/core/v3/GrpcService$GoogleGrpc.access$13000:(Lio/grpc/xds/shaded/io/envoyproxy/envoy/config/core/v3/GrpcService$GoogleGrpc;)Ljava/util/List;
     129: invokeinterface #343,  1          // InterfaceMethod java/util/List.isEmpty:()Z
     134: ifne          211
     137: aload_0
     138: getfield      #182                // Field callCredentialsBuilder_:Lcom/google/protobuf/RepeatedFieldBuilderV3;
     141: invokevirtual #351                // Method com/google/protobuf/RepeatedFieldBuilderV3.isEmpty:()Z
     144: ifeq          199
     147: aload_0
     148: getfield      #182                // Field callCredentialsBuilder_:Lcom/google/protobuf/RepeatedFieldBuilderV3;
     151: invokevirtual #354                // Method com/google/protobuf/RepeatedFieldBuilderV3.dispose:()V
     154: aload_0
     155: aconst_null
     156: putfield      #182                // Field callCredentialsBuilder_:Lcom/google/protobuf/RepeatedFieldBuilderV3;
     159: aload_0
     160: aload_1
     161: invokestatic  #340                // Method io/grpc/xds/shaded/io/envoyproxy/envoy/config/core/v3/GrpcService$GoogleGrpc.access$13000:(Lio/grpc/xds/shaded/io/envoyproxy/envoy/config/core/v3/GrpcService$GoogleGrpc;)Ljava/util/List;
     164: putfield      #151                // Field callCredentials_:Ljava/util/List;
     167: aload_0
     168: aload_0
     169: getfield      #184                // Field bitField0_:I
     172: bipush        -2
     174: iand
     175: putfield      #184                // Field bitField0_:I
     178: aload_0
     179: invokestatic  #357                // Method io/grpc/xds/shaded/io/envoyproxy/envoy/config/core/v3/GrpcService$GoogleGrpc.access$13600:()Z
     182: ifeq          192
     185: aload_0
     186: invokespecial #171                // Method getCallCredentialsFieldBuilder:()Lcom/google/protobuf/RepeatedFieldBuilderV3;
     189: goto          193
     192: aconst_null
     193: putfield      #182                // Field callCredentialsBuilder_:Lcom/google/protobuf/RepeatedFieldBuilderV3;
     196: goto          211
     199: aload_0
     200: getfield      #182                // Field callCredentialsBuilder_:Lcom/google/protobuf/RepeatedFieldBuilderV3;
     203: aload_1
     204: invokestatic  #340                // Method io/grpc/xds/shaded/io/envoyproxy/envoy/config/core/v3/GrpcService$GoogleGrpc.access$13000:(Lio/grpc/xds/shaded/io/envoyproxy/envoy/config/core/v3/GrpcService$GoogleGrpc;)Ljava/util/List;
     207: invokevirtual #361                // Method com/google/protobuf/RepeatedFieldBuilderV3.addAllMessages:(Ljava/lang/Iterable;)Lcom/google/protobuf/RepeatedFieldBuilderV3;
     210: pop
     211: aload_1
     212: invokevirtual #364                // Method io/grpc/xds/shaded/io/envoyproxy/envoy/config/core/v3/GrpcService$GoogleGrpc.getStatPrefix:()Ljava/lang/String;
     215: invokevirtual #318                // Method java/lang/String.isEmpty:()Z
     218: ifne          233
     221: aload_0
     222: aload_1
     223: invokestatic  #367                // Method io/grpc/xds/shaded/io/envoyproxy/envoy/config/core/v3/GrpcService$GoogleGrpc.access$13100:(Lio/grpc/xds/shaded/io/envoyproxy/envoy/config/core/v3/GrpcService$GoogleGrpc;)Ljava/lang/Object;
     226: putfield      #153                // Field statPrefix_:Ljava/lang/Object;
     229: aload_0
     230: invokevirtual #325                // Method onChanged:()V
     233: aload_1
     234: invokevirtual #370                // Method io/grpc/xds/shaded/io/envoyproxy/envoy/config/core/v3/GrpcService$GoogleGrpc.getCredentialsFactoryName:()Ljava/lang/String;
     237: invokevirtual #318                // Method java/lang/String.isEmpty:()Z
     240: ifne          255
     243: aload_0
     244: aload_1
     245: invokestatic  #373                // Method io/grpc/xds/shaded/io/envoyproxy/envoy/config/core/v3/GrpcService$GoogleGrpc.access$13200:(Lio/grpc/xds/shaded/io/envoyproxy/envoy/config/core/v3/GrpcService$GoogleGrpc;)Ljava/lang/Object;
     248: putfield      #155                // Field credentialsFactoryName_:Ljava/lang/Object;
     251: aload_0
     252: invokevirtual #325                // Method onChanged:()V
     255: aload_1
     256: invokevirtual #376                // Method io/grpc/xds/shaded/io/envoyproxy/envoy/config/core/v3/GrpcService$GoogleGrpc.hasConfig:()Z
     259: ifeq          271
     262: aload_0
     263: aload_1
     264: invokevirtual #380                // Method io/grpc/xds/shaded/io/envoyproxy/envoy/config/core/v3/GrpcService$GoogleGrpc.getConfig:()Lcom/google/protobuf/Struct;
     267: invokevirtual #384                // Method mergeConfig:(Lcom/google/protobuf/Struct;)Lio/grpc/xds/shaded/io/envoyproxy/envoy/config/core/v3/GrpcService$GoogleGrpc$Builder;
     270: pop
     271: aload_1
     272: invokevirtual #387                // Method io/grpc/xds/shaded/io/envoyproxy/envoy/config/core/v3/GrpcService$GoogleGrpc.hasPerStreamBufferLimitBytes:()Z
     275: ifeq          287
     278: aload_0
     279: aload_1
     280: invokevirtual #391                // Method io/grpc/xds/shaded/io/envoyproxy/envoy/config/core/v3/GrpcService$GoogleGrpc.getPerStreamBufferLimitBytes:()Lcom/google/protobuf/UInt32Value;
     283: invokevirtual #395                // Method mergePerStreamBufferLimitBytes:(Lcom/google/protobuf/UInt32Value;)Lio/grpc/xds/shaded/io/envoyproxy/envoy/config/core/v3/GrpcService$GoogleGrpc$Builder;
     286: pop
     287: aload_1
     288: invokevirtual #398                // Method io/grpc/xds/shaded/io/envoyproxy/envoy/config/core/v3/GrpcService$GoogleGrpc.hasChannelArgs:()Z
     291: ifeq          303
     294: aload_0
     295: aload_1
     296: invokevirtual #402                // Method io/grpc/xds/shaded/io/envoyproxy/envoy/config/core/v3/GrpcService$GoogleGrpc.getChannelArgs:()Lio/grpc/xds/shaded/io/envoyproxy/envoy/config/core/v3/GrpcService$GoogleGrpc$ChannelArgs;
     299: invokevirtual #406                // Method mergeChannelArgs:(Lio/grpc/xds/shaded/io/envoyproxy/envoy/config/core/v3/GrpcService$GoogleGrpc$ChannelArgs;)Lio/grpc/xds/shaded/io/envoyproxy/envoy/config/core/v3/GrpcService$GoogleGrpc$Builder;
     302: pop
     303: aload_0
     304: aload_1
     305: invokestatic  #410                // Method io/grpc/xds/shaded/io/envoyproxy/envoy/config/core/v3/GrpcService$GoogleGrpc.access$13700:(Lio/grpc/xds/shaded/io/envoyproxy/envoy/config/core/v3/GrpcService$GoogleGrpc;)Lcom/google/protobuf/UnknownFieldSet;
     308: invokevirtual #414                // Method mergeUnknownFields:(Lcom/google/protobuf/UnknownFieldSet;)Lio/grpc/xds/shaded/io/envoyproxy/envoy/config/core/v3/GrpcService$GoogleGrpc$Builder;
     311: pop
     312: aload_0
     313: invokevirtual #325                // Method onChanged:()V
     316: aload_0
     317: areturn

  public final boolean isInitialized();
    Code:
       0: iconst_1
       1: ireturn

  public io.grpc.xds.shaded.io.envoyproxy.envoy.config.core.v3.GrpcService$GoogleGrpc$Builder mergeFrom(com.google.protobuf.CodedInputStream, com.google.protobuf.ExtensionRegistryLite) throws java.io.IOException;
    Code:
       0: aconst_null
       1: astore_3
       2: invokestatic  #423                // Method io/grpc/xds/shaded/io/envoyproxy/envoy/config/core/v3/GrpcService$GoogleGrpc.access$13800:()Lcom/google/protobuf/Parser;
       5: aload_1
       6: aload_2
       7: invokeinterface #429,  3          // InterfaceMethod com/google/protobuf/Parser.parsePartialFrom:(Lcom/google/protobuf/CodedInputStream;Lcom/google/protobuf/ExtensionRegistryLite;)Ljava/lang/Object;
      12: checkcast     #10                 // class io/grpc/xds/shaded/io/envoyproxy/envoy/config/core/v3/GrpcService$GoogleGrpc
      15: astore_3
      16: aload_3
      17: ifnull        61
      20: aload_0
      21: aload_3
      22: invokevirtual #304                // Method mergeFrom:(Lio/grpc/xds/shaded/io/envoyproxy/envoy/config/core/v3/GrpcService$GoogleGrpc;)Lio/grpc/xds/shaded/io/envoyproxy/envoy/config/core/v3/GrpcService$GoogleGrpc$Builder;
      25: pop
      26: goto          61
      29: astore        4
      31: aload         4
      33: invokevirtual #437                // Method com/google/protobuf/InvalidProtocolBufferException.getUnfinishedMessage:()Lcom/google/protobuf/MessageLite;
      36: checkcast     #10                 // class io/grpc/xds/shaded/io/envoyproxy/envoy/config/core/v3/GrpcService$GoogleGrpc
      39: astore_3
      40: aload         4
      42: invokevirtual #441                // Method com/google/protobuf/InvalidProtocolBufferException.unwrapIOException:()Ljava/io/IOException;
      45: athrow
      46: astore        5
      48: aload_3
      49: ifnull        58
      52: aload_0
      53: aload_3
      54: invokevirtual #304                // Method mergeFrom:(Lio/grpc/xds/shaded/io/envoyproxy/envoy/config/core/v3/GrpcService$GoogleGrpc;)Lio/grpc/xds/shaded/io/envoyproxy/envoy/config/core/v3/GrpcService$GoogleGrpc$Builder;
      57: pop
      58: aload         5
      60: athrow
      61: aload_0
      62: areturn
    Exception table:
       from    to  target type
           2    16    29   Class com/google/protobuf/InvalidProtocolBufferException
           2    16    46   any
          29    48    46   any

  public java.lang.String getTargetUri();
    Code:
       0: aload_0
       1: getfield      #143                // Field targetUri_:Ljava/lang/Object;
       4: astore_1
       5: aload_1
       6: instanceof    #315                // class java/lang/String
       9: ifne          29
      12: aload_1
      13: checkcast     #452                // class com/google/protobuf/ByteString
      16: astore_2
      17: aload_2
      18: invokevirtual #455                // Method com/google/protobuf/ByteString.toStringUtf8:()Ljava/lang/String;
      21: astore_3
      22: aload_0
      23: aload_3
      24: putfield      #143                // Field targetUri_:Ljava/lang/Object;
      27: aload_3
      28: areturn
      29: aload_1
      30: checkcast     #315                // class java/lang/String
      33: areturn

  public com.google.protobuf.ByteString getTargetUriBytes();
    Code:
       0: aload_0
       1: getfield      #143                // Field targetUri_:Ljava/lang/Object;
       4: astore_1
       5: aload_1
       6: instanceof    #315                // class java/lang/String
       9: ifeq          27
      12: aload_1
      13: checkcast     #315                // class java/lang/String
      16: invokestatic  #468                // Method com/google/protobuf/ByteString.copyFromUtf8:(Ljava/lang/String;)Lcom/google/protobuf/ByteString;
      19: astore_2
      20: aload_0
      21: aload_2
      22: putfield      #143                // Field targetUri_:Ljava/lang/Object;
      25: aload_2
      26: areturn
      27: aload_1
      28: checkcast     #452                // class com/google/protobuf/ByteString
      31: areturn

  public io.grpc.xds.shaded.io.envoyproxy.envoy.config.core.v3.GrpcService$GoogleGrpc$Builder setTargetUri(java.lang.String);
    Code:
       0: aload_1
       1: ifnonnull     12
       4: new           #473                // class java/lang/NullPointerException
       7: dup
       8: invokespecial #474                // Method java/lang/NullPointerException."<init>":()V
      11: athrow
      12: aload_0
      13: aload_1
      14: putfield      #143                // Field targetUri_:Ljava/lang/Object;
      17: aload_0
      18: invokevirtual #325                // Method onChanged:()V
      21: aload_0
      22: areturn

  public io.grpc.xds.shaded.io.envoyproxy.envoy.config.core.v3.GrpcService$GoogleGrpc$Builder clearTargetUri();
    Code:
       0: aload_0
       1: invokestatic  #206                // Method io/grpc/xds/shaded/io/envoyproxy/envoy/config/core/v3/GrpcService$GoogleGrpc.getDefaultInstance:()Lio/grpc/xds/shaded/io/envoyproxy/envoy/config/core/v3/GrpcService$GoogleGrpc;
       4: invokevirtual #313                // Method io/grpc/xds/shaded/io/envoyproxy/envoy/config/core/v3/GrpcService$GoogleGrpc.getTargetUri:()Ljava/lang/String;
       7: putfield      #143                // Field targetUri_:Ljava/lang/Object;
      10: aload_0
      11: invokevirtual #325                // Method onChanged:()V
      14: aload_0
      15: areturn

  public io.grpc.xds.shaded.io.envoyproxy.envoy.config.core.v3.GrpcService$GoogleGrpc$Builder setTargetUriBytes(com.google.protobuf.ByteString);
    Code:
       0: aload_1
       1: ifnonnull     12
       4: new           #473                // class java/lang/NullPointerException
       7: dup
       8: invokespecial #474                // Method java/lang/NullPointerException."<init>":()V
      11: athrow
      12: aload_1
      13: invokestatic  #481                // Method io/grpc/xds/shaded/io/envoyproxy/envoy/config/core/v3/GrpcService$GoogleGrpc.access$13900:(Lcom/google/protobuf/ByteString;)V
      16: aload_0
      17: aload_1
      18: putfield      #143                // Field targetUri_:Ljava/lang/Object;
      21: aload_0
      22: invokevirtual #325                // Method onChanged:()V
      25: aload_0
      26: areturn

  public boolean hasChannelCredentials();
    Code:
       0: aload_0
       1: getfield      #178                // Field channelCredentialsBuilder_:Lcom/google/protobuf/SingleFieldBuilderV3;
       4: ifnonnull     14
       7: aload_0
       8: getfield      #180                // Field channelCredentials_:Lio/grpc/xds/shaded/io/envoyproxy/envoy/config/core/v3/GrpcService$GoogleGrpc$ChannelCredentials;
      11: ifnull        18
      14: iconst_1
      15: goto          19
      18: iconst_0
      19: ireturn

  public io.grpc.xds.shaded.io.envoyproxy.envoy.config.core.v3.GrpcService$GoogleGrpc$ChannelCredentials getChannelCredentials();
    Code:
       0: aload_0
       1: getfield      #178                // Field channelCredentialsBuilder_:Lcom/google/protobuf/SingleFieldBuilderV3;
       4: ifnonnull     25
       7: aload_0
       8: getfield      #180                // Field channelCredentials_:Lio/grpc/xds/shaded/io/envoyproxy/envoy/config/core/v3/GrpcService$GoogleGrpc$ChannelCredentials;
      11: ifnonnull     20
      14: invokestatic  #483                // Method io/grpc/xds/shaded/io/envoyproxy/envoy/config/core/v3/GrpcService$GoogleGrpc$ChannelCredentials.getDefaultInstance:()Lio/grpc/xds/shaded/io/envoyproxy/envoy/config/core/v3/GrpcService$GoogleGrpc$ChannelCredentials;
      17: goto          24
      20: aload_0
      21: getfield      #180                // Field channelCredentials_:Lio/grpc/xds/shaded/io/envoyproxy/envoy/config/core/v3/GrpcService$GoogleGrpc$ChannelCredentials;
      24: areturn
      25: aload_0
      26: getfield      #178                // Field channelCredentialsBuilder_:Lcom/google/protobuf/SingleFieldBuilderV3;
      29: invokevirtual #486                // Method com/google/protobuf/SingleFieldBuilderV3.getMessage:()Lcom/google/protobuf/AbstractMessage;
      32: checkcast     #15                 // class io/grpc/xds/shaded/io/envoyproxy/envoy/config/core/v3/GrpcService$GoogleGrpc$ChannelCredentials
      35: areturn

  public io.grpc.xds.shaded.io.envoyproxy.envoy.config.core.v3.GrpcService$GoogleGrpc$Builder setChannelCredentials(io.grpc.xds.shaded.io.envoyproxy.envoy.config.core.v3.GrpcService$GoogleGrpc$ChannelCredentials);
    Code:
       0: aload_0
       1: getfield      #178                // Field channelCredentialsBuilder_:Lcom/google/protobuf/SingleFieldBuilderV3;
       4: ifnonnull     31
       7: aload_1
       8: ifnonnull     19
      11: new           #473                // class java/lang/NullPointerException
      14: dup
      15: invokespecial #474                // Method java/lang/NullPointerException."<init>":()V
      18: athrow
      19: aload_0
      20: aload_1
      21: putfield      #180                // Field channelCredentials_:Lio/grpc/xds/shaded/io/envoyproxy/envoy/config/core/v3/GrpcService$GoogleGrpc$ChannelCredentials;
      24: aload_0
      25: invokevirtual #325                // Method onChanged:()V
      28: goto          40
      31: aload_0
      32: getfield      #178                // Field channelCredentialsBuilder_:Lcom/google/protobuf/SingleFieldBuilderV3;
      35: aload_1
      36: invokevirtual #491                // Method com/google/protobuf/SingleFieldBuilderV3.setMessage:(Lcom/google/protobuf/AbstractMessage;)Lcom/google/protobuf/SingleFieldBuilderV3;
      39: pop
      40: aload_0
      41: areturn

  public io.grpc.xds.shaded.io.envoyproxy.envoy.config.core.v3.GrpcService$GoogleGrpc$Builder setChannelCredentials(io.grpc.xds.shaded.io.envoyproxy.envoy.config.core.v3.GrpcService$GoogleGrpc$ChannelCredentials$Builder);
    Code:
       0: aload_0
       1: getfield      #178                // Field channelCredentialsBuilder_:Lcom/google/protobuf/SingleFieldBuilderV3;
       4: ifnonnull     22
       7: aload_0
       8: aload_1
       9: invokevirtual #494                // Method io/grpc/xds/shaded/io/envoyproxy/envoy/config/core/v3/GrpcService$GoogleGrpc$ChannelCredentials$Builder.build:()Lio/grpc/xds/shaded/io/envoyproxy/envoy/config/core/v3/GrpcService$GoogleGrpc$ChannelCredentials;
      12: putfield      #180                // Field channelCredentials_:Lio/grpc/xds/shaded/io/envoyproxy/envoy/config/core/v3/GrpcService$GoogleGrpc$ChannelCredentials;
      15: aload_0
      16: invokevirtual #325                // Method onChanged:()V
      19: goto          34
      22: aload_0
      23: getfield      #178                // Field channelCredentialsBuilder_:Lcom/google/protobuf/SingleFieldBuilderV3;
      26: aload_1
      27: invokevirtual #494                // Method io/grpc/xds/shaded/io/envoyproxy/envoy/config/core/v3/GrpcService$GoogleGrpc$ChannelCredentials$Builder.build:()Lio/grpc/xds/shaded/io/envoyproxy/envoy/config/core/v3/GrpcService$GoogleGrpc$ChannelCredentials;
      30: invokevirtual #491                // Method com/google/protobuf/SingleFieldBuilderV3.setMessage:(Lcom/google/protobuf/AbstractMessage;)Lcom/google/protobuf/SingleFieldBuilderV3;
      33: pop
      34: aload_0
      35: areturn

  public io.grpc.xds.shaded.io.envoyproxy.envoy.config.core.v3.GrpcService$GoogleGrpc$Builder mergeChannelCredentials(io.grpc.xds.shaded.io.envoyproxy.envoy.config.core.v3.GrpcService$GoogleGrpc$ChannelCredentials);
    Code:
       0: aload_0
       1: getfield      #178                // Field channelCredentialsBuilder_:Lcom/google/protobuf/SingleFieldBuilderV3;
       4: ifnonnull     47
       7: aload_0
       8: getfield      #180                // Field channelCredentials_:Lio/grpc/xds/shaded/io/envoyproxy/envoy/config/core/v3/GrpcService$GoogleGrpc$ChannelCredentials;
      11: ifnull        35
      14: aload_0
      15: aload_0
      16: getfield      #180                // Field channelCredentials_:Lio/grpc/xds/shaded/io/envoyproxy/envoy/config/core/v3/GrpcService$GoogleGrpc$ChannelCredentials;
      19: invokestatic  #500                // Method io/grpc/xds/shaded/io/envoyproxy/envoy/config/core/v3/GrpcService$GoogleGrpc$ChannelCredentials.newBuilder:(Lio/grpc/xds/shaded/io/envoyproxy/envoy/config/core/v3/GrpcService$GoogleGrpc$ChannelCredentials;)Lio/grpc/xds/shaded/io/envoyproxy/envoy/config/core/v3/GrpcService$GoogleGrpc$ChannelCredentials$Builder;
      22: aload_1
      23: invokevirtual #502                // Method io/grpc/xds/shaded/io/envoyproxy/envoy/config/core/v3/GrpcService$GoogleGrpc$ChannelCredentials$Builder.mergeFrom:(Lio/grpc/xds/shaded/io/envoyproxy/envoy/config/core/v3/GrpcService$GoogleGrpc$ChannelCredentials;)Lio/grpc/xds/shaded/io/envoyproxy/envoy/config/core/v3/GrpcService$GoogleGrpc$ChannelCredentials$Builder;
      26: invokevirtual #504                // Method io/grpc/xds/shaded/io/envoyproxy/envoy/config/core/v3/GrpcService$GoogleGrpc$ChannelCredentials$Builder.buildPartial:()Lio/grpc/xds/shaded/io/envoyproxy/envoy/config/core/v3/GrpcService$GoogleGrpc$ChannelCredentials;
      29: putfield      #180                // Field channelCredentials_:Lio/grpc/xds/shaded/io/envoyproxy/envoy/config/core/v3/GrpcService$GoogleGrpc$ChannelCredentials;
      32: goto          40
      35: aload_0
      36: aload_1
      37: putfield      #180                // Field channelCredentials_:Lio/grpc/xds/shaded/io/envoyproxy/envoy/config/core/v3/GrpcService$GoogleGrpc$ChannelCredentials;
      40: aload_0
      41: invokevirtual #325                // Method onChanged:()V
      44: goto          56
      47: aload_0
      48: getfield      #178                // Field channelCredentialsBuilder_:Lcom/google/protobuf/SingleFieldBuilderV3;
      51: aload_1
      52: invokevirtual #506                // Method com/google/protobuf/SingleFieldBuilderV3.mergeFrom:(Lcom/google/protobuf/AbstractMessage;)Lcom/google/protobuf/SingleFieldBuilderV3;
      55: pop
      56: aload_0
      57: areturn

  public io.grpc.xds.shaded.io.envoyproxy.envoy.config.core.v3.GrpcService$GoogleGrpc$Builder clearChannelCredentials();
    Code:
       0: aload_0
       1: getfield      #178                // Field channelCredentialsBuilder_:Lcom/google/protobuf/SingleFieldBuilderV3;
       4: ifnonnull     19
       7: aload_0
       8: aconst_null
       9: putfield      #180                // Field channelCredentials_:Lio/grpc/xds/shaded/io/envoyproxy/envoy/config/core/v3/GrpcService$GoogleGrpc$ChannelCredentials;
      12: aload_0
      13: invokevirtual #325                // Method onChanged:()V
      16: goto          29
      19: aload_0
      20: aconst_null
      21: putfield      #180                // Field channelCredentials_:Lio/grpc/xds/shaded/io/envoyproxy/envoy/config/core/v3/GrpcService$GoogleGrpc$ChannelCredentials;
      24: aload_0
      25: aconst_null
      26: putfield      #178                // Field channelCredentialsBuilder_:Lcom/google/protobuf/SingleFieldBuilderV3;
      29: aload_0
      30: areturn

  public io.grpc.xds.shaded.io.envoyproxy.envoy.config.core.v3.GrpcService$GoogleGrpc$ChannelCredentials$Builder getChannelCredentialsBuilder();
    Code:
       0: aload_0
       1: invokevirtual #325                // Method onChanged:()V
       4: aload_0
       5: invokespecial #513                // Method getChannelCredentialsFieldBuilder:()Lcom/google/protobuf/SingleFieldBuilderV3;
       8: invokevirtual #517                // Method com/google/protobuf/SingleFieldBuilderV3.getBuilder:()Lcom/google/protobuf/AbstractMessage$Builder;
      11: checkcast     #18                 // class io/grpc/xds/shaded/io/envoyproxy/envoy/config/core/v3/GrpcService$GoogleGrpc$ChannelCredentials$Builder
      14: areturn

  public io.grpc.xds.shaded.io.envoyproxy.envoy.config.core.v3.GrpcService$GoogleGrpc$ChannelCredentialsOrBuilder getChannelCredentialsOrBuilder();
    Code:
       0: aload_0
       1: getfield      #178                // Field channelCredentialsBuilder_:Lcom/google/protobuf/SingleFieldBuilderV3;
       4: ifnull        18
       7: aload_0
       8: getfield      #178                // Field channelCredentialsBuilder_:Lcom/google/protobuf/SingleFieldBuilderV3;
      11: invokevirtual #523                // Method com/google/protobuf/SingleFieldBuilderV3.getMessageOrBuilder:()Lcom/google/protobuf/MessageOrBuilder;
      14: checkcast     #21                 // class io/grpc/xds/shaded/io/envoyproxy/envoy/config/core/v3/GrpcService$GoogleGrpc$ChannelCredentialsOrBuilder
      17: areturn
      18: aload_0
      19: getfield      #180                // Field channelCredentials_:Lio/grpc/xds/shaded/io/envoyproxy/envoy/config/core/v3/GrpcService$GoogleGrpc$ChannelCredentials;
      22: ifnonnull     31
      25: invokestatic  #483                // Method io/grpc/xds/shaded/io/envoyproxy/envoy/config/core/v3/GrpcService$GoogleGrpc$ChannelCredentials.getDefaultInstance:()Lio/grpc/xds/shaded/io/envoyproxy/envoy/config/core/v3/GrpcService$GoogleGrpc$ChannelCredentials;
      28: goto          35
      31: aload_0
      32: getfield      #180                // Field channelCredentials_:Lio/grpc/xds/shaded/io/envoyproxy/envoy/config/core/v3/GrpcService$GoogleGrpc$ChannelCredentials;
      35: areturn

  private com.google.protobuf.SingleFieldBuilderV3<io.grpc.xds.shaded.io.envoyproxy.envoy.config.core.v3.GrpcService$GoogleGrpc$ChannelCredentials, io.grpc.xds.shaded.io.envoyproxy.envoy.config.core.v3.GrpcService$GoogleGrpc$ChannelCredentials$Builder, io.grpc.xds.shaded.io.envoyproxy.envoy.config.core.v3.GrpcService$GoogleGrpc$ChannelCredentialsOrBuilder> getChannelCredentialsFieldBuilder();
    Code:
       0: aload_0
       1: getfield      #178                // Field channelCredentialsBuilder_:Lcom/google/protobuf/SingleFieldBuilderV3;
       4: ifnonnull     35
       7: aload_0
       8: new           #232                // class com/google/protobuf/SingleFieldBuilderV3
      11: dup
      12: aload_0
      13: invokevirtual #525                // Method getChannelCredentials:()Lio/grpc/xds/shaded/io/envoyproxy/envoy/config/core/v3/GrpcService$GoogleGrpc$ChannelCredentials;
      16: aload_0
      17: invokevirtual #529                // Method getParentForChildren:()Lcom/google/protobuf/GeneratedMessageV3$BuilderParent;
      20: aload_0
      21: invokevirtual #532                // Method isClean:()Z
      24: invokespecial #535                // Method com/google/protobuf/SingleFieldBuilderV3."<init>":(Lcom/google/protobuf/AbstractMessage;Lcom/google/protobuf/AbstractMessage$BuilderParent;Z)V
      27: putfield      #178                // Field channelCredentialsBuilder_:Lcom/google/protobuf/SingleFieldBuilderV3;
      30: aload_0
      31: aconst_null
      32: putfield      #180                // Field channelCredentials_:Lio/grpc/xds/shaded/io/envoyproxy/envoy/config/core/v3/GrpcService$GoogleGrpc$ChannelCredentials;
      35: aload_0
      36: getfield      #178                // Field channelCredentialsBuilder_:Lcom/google/protobuf/SingleFieldBuilderV3;
      39: areturn

  private void ensureCallCredentialsIsMutable();
    Code:
       0: aload_0
       1: getfield      #184                // Field bitField0_:I
       4: iconst_1
       5: iand
       6: ifne          34
       9: aload_0
      10: new           #537                // class java/util/ArrayList
      13: dup
      14: aload_0
      15: getfield      #151                // Field callCredentials_:Ljava/util/List;
      18: invokespecial #540                // Method java/util/ArrayList."<init>":(Ljava/util/Collection;)V
      21: putfield      #151                // Field callCredentials_:Ljava/util/List;
      24: aload_0
      25: dup
      26: getfield      #184                // Field bitField0_:I
      29: iconst_1
      30: ior
      31: putfield      #184                // Field bitField0_:I
      34: return

  public java.util.List<io.grpc.xds.shaded.io.envoyproxy.envoy.config.core.v3.GrpcService$GoogleGrpc$CallCredentials> getCallCredentialsList();
    Code:
       0: aload_0
       1: getfield      #182                // Field callCredentialsBuilder_:Lcom/google/protobuf/RepeatedFieldBuilderV3;
       4: ifnonnull     15
       7: aload_0
       8: getfield      #151                // Field callCredentials_:Ljava/util/List;
      11: invokestatic  #239                // Method java/util/Collections.unmodifiableList:(Ljava/util/List;)Ljava/util/List;
      14: areturn
      15: aload_0
      16: getfield      #182                // Field callCredentialsBuilder_:Lcom/google/protobuf/RepeatedFieldBuilderV3;
      19: invokevirtual #545                // Method com/google/protobuf/RepeatedFieldBuilderV3.getMessageList:()Ljava/util/List;
      22: areturn

  public int getCallCredentialsCount();
    Code:
       0: aload_0
       1: getfield      #182                // Field callCredentialsBuilder_:Lcom/google/protobuf/RepeatedFieldBuilderV3;
       4: ifnonnull     17
       7: aload_0
       8: getfield      #151                // Field callCredentials_:Ljava/util/List;
      11: invokeinterface #550,  1          // InterfaceMethod java/util/List.size:()I
      16: ireturn
      17: aload_0
      18: getfield      #182                // Field callCredentialsBuilder_:Lcom/google/protobuf/RepeatedFieldBuilderV3;
      21: invokevirtual #553                // Method com/google/protobuf/RepeatedFieldBuilderV3.getCount:()I
      24: ireturn

  public io.grpc.xds.shaded.io.envoyproxy.envoy.config.core.v3.GrpcService$GoogleGrpc$CallCredentials getCallCredentials(int);
    Code:
       0: aload_0
       1: getfield      #182                // Field callCredentialsBuilder_:Lcom/google/protobuf/RepeatedFieldBuilderV3;
       4: ifnonnull     21
       7: aload_0
       8: getfield      #151                // Field callCredentials_:Ljava/util/List;
      11: iload_1
      12: invokeinterface #559,  2          // InterfaceMethod java/util/List.get:(I)Ljava/lang/Object;
      17: checkcast     #24                 // class io/grpc/xds/shaded/io/envoyproxy/envoy/config/core/v3/GrpcService$GoogleGrpc$CallCredentials
      20: areturn
      21: aload_0
      22: getfield      #182                // Field callCredentialsBuilder_:Lcom/google/protobuf/RepeatedFieldBuilderV3;
      25: iload_1
      26: invokevirtual #562                // Method com/google/protobuf/RepeatedFieldBuilderV3.getMessage:(I)Lcom/google/protobuf/AbstractMessage;
      29: checkcast     #24                 // class io/grpc/xds/shaded/io/envoyproxy/envoy/config/core/v3/GrpcService$GoogleGrpc$CallCredentials
      32: areturn

  public io.grpc.xds.shaded.io.envoyproxy.envoy.config.core.v3.GrpcService$GoogleGrpc$Builder setCallCredentials(int, io.grpc.xds.shaded.io.envoyproxy.envoy.config.core.v3.GrpcService$GoogleGrpc$CallCredentials);
    Code:
       0: aload_0
       1: getfield      #182                // Field callCredentialsBuilder_:Lcom/google/protobuf/RepeatedFieldBuilderV3;
       4: ifnonnull     42
       7: aload_2
       8: ifnonnull     19
      11: new           #473                // class java/lang/NullPointerException
      14: dup
      15: invokespecial #474                // Method java/lang/NullPointerException."<init>":()V
      18: athrow
      19: aload_0
      20: invokespecial #346                // Method ensureCallCredentialsIsMutable:()V
      23: aload_0
      24: getfield      #151                // Field callCredentials_:Ljava/util/List;
      27: iload_1
      28: aload_2
      29: invokeinterface #568,  3          // InterfaceMethod java/util/List.set:(ILjava/lang/Object;)Ljava/lang/Object;
      34: pop
      35: aload_0
      36: invokevirtual #325                // Method onChanged:()V
      39: goto          52
      42: aload_0
      43: getfield      #182                // Field callCredentialsBuilder_:Lcom/google/protobuf/RepeatedFieldBuilderV3;
      46: iload_1
      47: aload_2
      48: invokevirtual #571                // Method com/google/protobuf/RepeatedFieldBuilderV3.setMessage:(ILcom/google/protobuf/AbstractMessage;)Lcom/google/protobuf/RepeatedFieldBuilderV3;
      51: pop
      52: aload_0
      53: areturn

  public io.grpc.xds.shaded.io.envoyproxy.envoy.config.core.v3.GrpcService$GoogleGrpc$Builder setCallCredentials(int, io.grpc.xds.shaded.io.envoyproxy.envoy.config.core.v3.GrpcService$GoogleGrpc$CallCredentials$Builder);
    Code:
       0: aload_0
       1: getfield      #182                // Field callCredentialsBuilder_:Lcom/google/protobuf/RepeatedFieldBuilderV3;
       4: ifnonnull     33
       7: aload_0
       8: invokespecial #346                // Method ensureCallCredentialsIsMutable:()V
      11: aload_0
      12: getfield      #151                // Field callCredentials_:Ljava/util/List;
      15: iload_1
      16: aload_2
      17: invokevirtual #576                // Method io/grpc/xds/shaded/io/envoyproxy/envoy/config/core/v3/GrpcService$GoogleGrpc$CallCredentials$Builder.build:()Lio/grpc/xds/shaded/io/envoyproxy/envoy/config/core/v3/GrpcService$GoogleGrpc$CallCredentials;
      20: invokeinterface #568,  3          // InterfaceMethod java/util/List.set:(ILjava/lang/Object;)Ljava/lang/Object;
      25: pop
      26: aload_0
      27: invokevirtual #325                // Method onChanged:()V
      30: goto          46
      33: aload_0
      34: getfield      #182                // Field callCredentialsBuilder_:Lcom/google/protobuf/RepeatedFieldBuilderV3;
      37: iload_1
      38: aload_2
      39: invokevirtual #576                // Method io/grpc/xds/shaded/io/envoyproxy/envoy/config/core/v3/GrpcService$GoogleGrpc$CallCredentials$Builder.build:()Lio/grpc/xds/shaded/io/envoyproxy/envoy/config/core/v3/GrpcService$GoogleGrpc$CallCredentials;
      42: invokevirtual #571                // Method com/google/protobuf/RepeatedFieldBuilderV3.setMessage:(ILcom/google/protobuf/AbstractMessage;)Lcom/google/protobuf/RepeatedFieldBuilderV3;
      45: pop
      46: aload_0
      47: areturn

  public io.grpc.xds.shaded.io.envoyproxy.envoy.config.core.v3.GrpcService$GoogleGrpc$Builder addCallCredentials(io.grpc.xds.shaded.io.envoyproxy.envoy.config.core.v3.GrpcService$GoogleGrpc$CallCredentials);
    Code:
       0: aload_0
       1: getfield      #182                // Field callCredentialsBuilder_:Lcom/google/protobuf/RepeatedFieldBuilderV3;
       4: ifnonnull     41
       7: aload_1
       8: ifnonnull     19
      11: new           #473                // class java/lang/NullPointerException
      14: dup
      15: invokespecial #474                // Method java/lang/NullPointerException."<init>":()V
      18: athrow
      19: aload_0
      20: invokespecial #346                // Method ensureCallCredentialsIsMutable:()V
      23: aload_0
      24: getfield      #151                // Field callCredentials_:Ljava/util/List;
      27: aload_1
      28: invokeinterface #583,  2          // InterfaceMethod java/util/List.add:(Ljava/lang/Object;)Z
      33: pop
      34: aload_0
      35: invokevirtual #325                // Method onChanged:()V
      38: goto          50
      41: aload_0
      42: getfield      #182                // Field callCredentialsBuilder_:Lcom/google/protobuf/RepeatedFieldBuilderV3;
      45: aload_1
      46: invokevirtual #587                // Method com/google/protobuf/RepeatedFieldBuilderV3.addMessage:(Lcom/google/protobuf/AbstractMessage;)Lcom/google/protobuf/RepeatedFieldBuilderV3;
      49: pop
      50: aload_0
      51: areturn

  public io.grpc.xds.shaded.io.envoyproxy.envoy.config.core.v3.GrpcService$GoogleGrpc$Builder addCallCredentials(int, io.grpc.xds.shaded.io.envoyproxy.envoy.config.core.v3.GrpcService$GoogleGrpc$CallCredentials);
    Code:
       0: aload_0
       1: getfield      #182                // Field callCredentialsBuilder_:Lcom/google/protobuf/RepeatedFieldBuilderV3;
       4: ifnonnull     41
       7: aload_2
       8: ifnonnull     19
      11: new           #473                // class java/lang/NullPointerException
      14: dup
      15: invokespecial #474                // Method java/lang/NullPointerException."<init>":()V
      18: athrow
      19: aload_0
      20: invokespecial #346                // Method ensureCallCredentialsIsMutable:()V
      23: aload_0
      24: getfield      #151                // Field callCredentials_:Ljava/util/List;
      27: iload_1
      28: aload_2
      29: invokeinterface #590,  3          // InterfaceMethod java/util/List.add:(ILjava/lang/Object;)V
      34: aload_0
      35: invokevirtual #325                // Method onChanged:()V
      38: goto          51
      41: aload_0
      42: getfield      #182                // Field callCredentialsBuilder_:Lcom/google/protobuf/RepeatedFieldBuilderV3;
      45: iload_1
      46: aload_2
      47: invokevirtual #592                // Method com/google/protobuf/RepeatedFieldBuilderV3.addMessage:(ILcom/google/protobuf/AbstractMessage;)Lcom/google/protobuf/RepeatedFieldBuilderV3;
      50: pop
      51: aload_0
      52: areturn

  public io.grpc.xds.shaded.io.envoyproxy.envoy.config.core.v3.GrpcService$GoogleGrpc$Builder addCallCredentials(io.grpc.xds.shaded.io.envoyproxy.envoy.config.core.v3.GrpcService$GoogleGrpc$CallCredentials$Builder);
    Code:
       0: aload_0
       1: getfield      #182                // Field callCredentialsBuilder_:Lcom/google/protobuf/RepeatedFieldBuilderV3;
       4: ifnonnull     32
       7: aload_0
       8: invokespecial #346                // Method ensureCallCredentialsIsMutable:()V
      11: aload_0
      12: getfield      #151                // Field callCredentials_:Ljava/util/List;
      15: aload_1
      16: invokevirtual #576                // Method io/grpc/xds/shaded/io/envoyproxy/envoy/config/core/v3/GrpcService$GoogleGrpc$CallCredentials$Builder.build:()Lio/grpc/xds/shaded/io/envoyproxy/envoy/config/core/v3/GrpcService$GoogleGrpc$CallCredentials;
      19: invokeinterface #583,  2          // InterfaceMethod java/util/List.add:(Ljava/lang/Object;)Z
      24: pop
      25: aload_0
      26: invokevirtual #325                // Method onChanged:()V
      29: goto          44
      32: aload_0
      33: getfield      #182                // Field callCredentialsBuilder_:Lcom/google/protobuf/RepeatedFieldBuilderV3;
      36: aload_1
      37: invokevirtual #576                // Method io/grpc/xds/shaded/io/envoyproxy/envoy/config/core/v3/GrpcService$GoogleGrpc$CallCredentials$Builder.build:()Lio/grpc/xds/shaded/io/envoyproxy/envoy/config/core/v3/GrpcService$GoogleGrpc$CallCredentials;
      40: invokevirtual #587                // Method com/google/protobuf/RepeatedFieldBuilderV3.addMessage:(Lcom/google/protobuf/AbstractMessage;)Lcom/google/protobuf/RepeatedFieldBuilderV3;
      43: pop
      44: aload_0
      45: areturn

  public io.grpc.xds.shaded.io.envoyproxy.envoy.config.core.v3.GrpcService$GoogleGrpc$Builder addCallCredentials(int, io.grpc.xds.shaded.io.envoyproxy.envoy.config.core.v3.GrpcService$GoogleGrpc$CallCredentials$Builder);
    Code:
       0: aload_0
       1: getfield      #182                // Field callCredentialsBuilder_:Lcom/google/protobuf/RepeatedFieldBuilderV3;
       4: ifnonnull     32
       7: aload_0
       8: invokespecial #346                // Method ensureCallCredentialsIsMutable:()V
      11: aload_0
      12: getfield      #151                // Field callCredentials_:Ljava/util/List;
      15: iload_1
      16: aload_2
      17: invokevirtual #576                // Method io/grpc/xds/shaded/io/envoyproxy/envoy/config/core/v3/GrpcService$GoogleGrpc$CallCredentials$Builder.build:()Lio/grpc/xds/shaded/io/envoyproxy/envoy/config/core/v3/GrpcService$GoogleGrpc$CallCredentials;
      20: invokeinterface #590,  3          // InterfaceMethod java/util/List.add:(ILjava/lang/Object;)V
      25: aload_0
      26: invokevirtual #325                // Method onChanged:()V
      29: goto          45
      32: aload_0
      33: getfield      #182                // Field callCredentialsBuilder_:Lcom/google/protobuf/RepeatedFieldBuilderV3;
      36: iload_1
      37: aload_2
      38: invokevirtual #576                // Method io/grpc/xds/shaded/io/envoyproxy/envoy/config/core/v3/GrpcService$GoogleGrpc$CallCredentials$Builder.build:()Lio/grpc/xds/shaded/io/envoyproxy/envoy/config/core/v3/GrpcService$GoogleGrpc$CallCredentials;
      41: invokevirtual #592                // Method com/google/protobuf/RepeatedFieldBuilderV3.addMessage:(ILcom/google/protobuf/AbstractMessage;)Lcom/google/protobuf/RepeatedFieldBuilderV3;
      44: pop
      45: aload_0
      46: areturn

  public io.grpc.xds.shaded.io.envoyproxy.envoy.config.core.v3.GrpcService$GoogleGrpc$Builder addAllCallCredentials(java.lang.Iterable<? extends io.grpc.xds.shaded.io.envoyproxy.envoy.config.core.v3.GrpcService$GoogleGrpc$CallCredentials>);
    Code:
       0: aload_0
       1: getfield      #182                // Field callCredentialsBuilder_:Lcom/google/protobuf/RepeatedFieldBuilderV3;
       4: ifnonnull     26
       7: aload_0
       8: invokespecial #346                // Method ensureCallCredentialsIsMutable:()V
      11: aload_1
      12: aload_0
      13: getfield      #151                // Field callCredentials_:Ljava/util/List;
      16: invokestatic  #599                // Method com/google/protobuf/AbstractMessageLite$Builder.addAll:(Ljava/lang/Iterable;Ljava/util/List;)V
      19: aload_0
      20: invokevirtual #325                // Method onChanged:()V
      23: goto          35
      26: aload_0
      27: getfield      #182                // Field callCredentialsBuilder_:Lcom/google/protobuf/RepeatedFieldBuilderV3;
      30: aload_1
      31: invokevirtual #361                // Method com/google/protobuf/RepeatedFieldBuilderV3.addAllMessages:(Ljava/lang/Iterable;)Lcom/google/protobuf/RepeatedFieldBuilderV3;
      34: pop
      35: aload_0
      36: areturn

  public io.grpc.xds.shaded.io.envoyproxy.envoy.config.core.v3.GrpcService$GoogleGrpc$Builder clearCallCredentials();
    Code:
       0: aload_0
       1: getfield      #182                // Field callCredentialsBuilder_:Lcom/google/protobuf/RepeatedFieldBuilderV3;
       4: ifnonnull     32
       7: aload_0
       8: invokestatic  #149                // Method java/util/Collections.emptyList:()Ljava/util/List;
      11: putfield      #151                // Field callCredentials_:Ljava/util/List;
      14: aload_0
      15: aload_0
      16: getfield      #184                // Field bitField0_:I
      19: bipush        -2
      21: iand
      22: putfield      #184                // Field bitField0_:I
      25: aload_0
      26: invokevirtual #325                // Method onChanged:()V
      29: goto          39
      32: aload_0
      33: getfield      #182                // Field callCredentialsBuilder_:Lcom/google/protobuf/RepeatedFieldBuilderV3;
      36: invokevirtual #188                // Method com/google/protobuf/RepeatedFieldBuilderV3.clear:()V
      39: aload_0
      40: areturn

  public io.grpc.xds.shaded.io.envoyproxy.envoy.config.core.v3.GrpcService$GoogleGrpc$Builder removeCallCredentials(int);
    Code:
       0: aload_0
       1: getfield      #182                // Field callCredentialsBuilder_:Lcom/google/protobuf/RepeatedFieldBuilderV3;
       4: ifnonnull     29
       7: aload_0
       8: invokespecial #346                // Method ensureCallCredentialsIsMutable:()V
      11: aload_0
      12: getfield      #151                // Field callCredentials_:Ljava/util/List;
      15: iload_1
      16: invokeinterface #608,  2          // InterfaceMethod java/util/List.remove:(I)Ljava/lang/Object;
      21: pop
      22: aload_0
      23: invokevirtual #325                // Method onChanged:()V
      26: goto          37
      29: aload_0
      30: getfield      #182                // Field callCredentialsBuilder_:Lcom/google/protobuf/RepeatedFieldBuilderV3;
      33: iload_1
      34: invokevirtual #611                // Method com/google/protobuf/RepeatedFieldBuilderV3.remove:(I)V
      37: aload_0
      38: areturn

  public io.grpc.xds.shaded.io.envoyproxy.envoy.config.core.v3.GrpcService$GoogleGrpc$CallCredentials$Builder getCallCredentialsBuilder(int);
    Code:
       0: aload_0
       1: invokespecial #171                // Method getCallCredentialsFieldBuilder:()Lcom/google/protobuf/RepeatedFieldBuilderV3;
       4: iload_1
       5: invokevirtual #616                // Method com/google/protobuf/RepeatedFieldBuilderV3.getBuilder:(I)Lcom/google/protobuf/AbstractMessage$Builder;
       8: checkcast     #27                 // class io/grpc/xds/shaded/io/envoyproxy/envoy/config/core/v3/GrpcService$GoogleGrpc$CallCredentials$Builder
      11: areturn

  public io.grpc.xds.shaded.io.envoyproxy.envoy.config.core.v3.GrpcService$GoogleGrpc$CallCredentialsOrBuilder getCallCredentialsOrBuilder(int);
    Code:
       0: aload_0
       1: getfield      #182                // Field callCredentialsBuilder_:Lcom/google/protobuf/RepeatedFieldBuilderV3;
       4: ifnonnull     21
       7: aload_0
       8: getfield      #151                // Field callCredentials_:Ljava/util/List;
      11: iload_1
      12: invokeinterface #559,  2          // InterfaceMethod java/util/List.get:(I)Ljava/lang/Object;
      17: checkcast     #29                 // class io/grpc/xds/shaded/io/envoyproxy/envoy/config/core/v3/GrpcService$GoogleGrpc$CallCredentialsOrBuilder
      20: areturn
      21: aload_0
      22: getfield      #182                // Field callCredentialsBuilder_:Lcom/google/protobuf/RepeatedFieldBuilderV3;
      25: iload_1
      26: invokevirtual #621                // Method com/google/protobuf/RepeatedFieldBuilderV3.getMessageOrBuilder:(I)Lcom/google/protobuf/MessageOrBuilder;
      29: checkcast     #29                 // class io/grpc/xds/shaded/io/envoyproxy/envoy/config/core/v3/GrpcService$GoogleGrpc$CallCredentialsOrBuilder
      32: areturn

  public java.util.List<? extends io.grpc.xds.shaded.io.envoyproxy.envoy.config.core.v3.GrpcService$GoogleGrpc$CallCredentialsOrBuilder> getCallCredentialsOrBuilderList();
    Code:
       0: aload_0
       1: getfield      #182                // Field callCredentialsBuilder_:Lcom/google/protobuf/RepeatedFieldBuilderV3;
       4: ifnull        15
       7: aload_0
       8: getfield      #182                // Field callCredentialsBuilder_:Lcom/google/protobuf/RepeatedFieldBuilderV3;
      11: invokevirtual #626                // Method com/google/protobuf/RepeatedFieldBuilderV3.getMessageOrBuilderList:()Ljava/util/List;
      14: areturn
      15: aload_0
      16: getfield      #151                // Field callCredentials_:Ljava/util/List;
      19: invokestatic  #239                // Method java/util/Collections.unmodifiableList:(Ljava/util/List;)Ljava/util/List;
      22: areturn

  public io.grpc.xds.shaded.io.envoyproxy.envoy.config.core.v3.GrpcService$GoogleGrpc$CallCredentials$Builder addCallCredentialsBuilder();
    Code:
       0: aload_0
       1: invokespecial #171                // Method getCallCredentialsFieldBuilder:()Lcom/google/protobuf/RepeatedFieldBuilderV3;
       4: invokestatic  #630                // Method io/grpc/xds/shaded/io/envoyproxy/envoy/config/core/v3/GrpcService$GoogleGrpc$CallCredentials.getDefaultInstance:()Lio/grpc/xds/shaded/io/envoyproxy/envoy/config/core/v3/GrpcService$GoogleGrpc$CallCredentials;
       7: invokevirtual #634                // Method com/google/protobuf/RepeatedFieldBuilderV3.addBuilder:(Lcom/google/protobuf/AbstractMessage;)Lcom/google/protobuf/AbstractMessage$Builder;
      10: checkcast     #27                 // class io/grpc/xds/shaded/io/envoyproxy/envoy/config/core/v3/GrpcService$GoogleGrpc$CallCredentials$Builder
      13: areturn

  public io.grpc.xds.shaded.io.envoyproxy.envoy.config.core.v3.GrpcService$GoogleGrpc$CallCredentials$Builder addCallCredentialsBuilder(int);
    Code:
       0: aload_0
       1: invokespecial #171                // Method getCallCredentialsFieldBuilder:()Lcom/google/protobuf/RepeatedFieldBuilderV3;
       4: iload_1
       5: invokestatic  #630                // Method io/grpc/xds/shaded/io/envoyproxy/envoy/config/core/v3/GrpcService$GoogleGrpc$CallCredentials.getDefaultInstance:()Lio/grpc/xds/shaded/io/envoyproxy/envoy/config/core/v3/GrpcService$GoogleGrpc$CallCredentials;
       8: invokevirtual #637                // Method com/google/protobuf/RepeatedFieldBuilderV3.addBuilder:(ILcom/google/protobuf/AbstractMessage;)Lcom/google/protobuf/AbstractMessage$Builder;
      11: checkcast     #27                 // class io/grpc/xds/shaded/io/envoyproxy/envoy/config/core/v3/GrpcService$GoogleGrpc$CallCredentials$Builder
      14: areturn

  public java.util.List<io.grpc.xds.shaded.io.envoyproxy.envoy.config.core.v3.GrpcService$GoogleGrpc$CallCredentials$Builder> getCallCredentialsBuilderList();
    Code:
       0: aload_0
       1: invokespecial #171                // Method getCallCredentialsFieldBuilder:()Lcom/google/protobuf/RepeatedFieldBuilderV3;
       4: invokevirtual #642                // Method com/google/protobuf/RepeatedFieldBuilderV3.getBuilderList:()Ljava/util/List;
       7: areturn

  private com.google.protobuf.RepeatedFieldBuilderV3<io.grpc.xds.shaded.io.envoyproxy.envoy.config.core.v3.GrpcService$GoogleGrpc$CallCredentials, io.grpc.xds.shaded.io.envoyproxy.envoy.config.core.v3.GrpcService$GoogleGrpc$CallCredentials$Builder, io.grpc.xds.shaded.io.envoyproxy.envoy.config.core.v3.GrpcService$GoogleGrpc$CallCredentialsOrBuilder> getCallCredentialsFieldBuilder();
    Code:
       0: aload_0
       1: getfield      #182                // Field callCredentialsBuilder_:Lcom/google/protobuf/RepeatedFieldBuilderV3;
       4: ifnonnull     49
       7: aload_0
       8: new           #186                // class com/google/protobuf/RepeatedFieldBuilderV3
      11: dup
      12: aload_0
      13: getfield      #151                // Field callCredentials_:Ljava/util/List;
      16: aload_0
      17: getfield      #184                // Field bitField0_:I
      20: iconst_1
      21: iand
      22: ifeq          29
      25: iconst_1
      26: goto          30
      29: iconst_0
      30: aload_0
      31: invokevirtual #529                // Method getParentForChildren:()Lcom/google/protobuf/GeneratedMessageV3$BuilderParent;
      34: aload_0
      35: invokevirtual #532                // Method isClean:()Z
      38: invokespecial #646                // Method com/google/protobuf/RepeatedFieldBuilderV3."<init>":(Ljava/util/List;ZLcom/google/protobuf/AbstractMessage$BuilderParent;Z)V
      41: putfield      #182                // Field callCredentialsBuilder_:Lcom/google/protobuf/RepeatedFieldBuilderV3;
      44: aload_0
      45: aconst_null
      46: putfield      #151                // Field callCredentials_:Ljava/util/List;
      49: aload_0
      50: getfield      #182                // Field callCredentialsBuilder_:Lcom/google/protobuf/RepeatedFieldBuilderV3;
      53: areturn

  public java.lang.String getStatPrefix();
    Code:
       0: aload_0
       1: getfield      #153                // Field statPrefix_:Ljava/lang/Object;
       4: astore_1
       5: aload_1
       6: instanceof    #315                // class java/lang/String
       9: ifne          29
      12: aload_1
      13: checkcast     #452                // class com/google/protobuf/ByteString
      16: astore_2
      17: aload_2
      18: invokevirtual #455                // Method com/google/protobuf/ByteString.toStringUtf8:()Ljava/lang/String;
      21: astore_3
      22: aload_0
      23: aload_3
      24: putfield      #153                // Field statPrefix_:Ljava/lang/Object;
      27: aload_3
      28: areturn
      29: aload_1
      30: checkcast     #315                // class java/lang/String
      33: areturn

  public com.google.protobuf.ByteString getStatPrefixBytes();
    Code:
       0: aload_0
       1: getfield      #153                // Field statPrefix_:Ljava/lang/Object;
       4: astore_1
       5: aload_1
       6: instanceof    #315                // class java/lang/String
       9: ifeq          27
      12: aload_1
      13: checkcast     #315                // class java/lang/String
      16: invokestatic  #468                // Method com/google/protobuf/ByteString.copyFromUtf8:(Ljava/lang/String;)Lcom/google/protobuf/ByteString;
      19: astore_2
      20: aload_0
      21: aload_2
      22: putfield      #153                // Field statPrefix_:Ljava/lang/Object;
      25: aload_2
      26: areturn
      27: aload_1
      28: checkcast     #452                // class com/google/protobuf/ByteString
      31: areturn

  public io.grpc.xds.shaded.io.envoyproxy.envoy.config.core.v3.GrpcService$GoogleGrpc$Builder setStatPrefix(java.lang.String);
    Code:
       0: aload_1
       1: ifnonnull     12
       4: new           #473                // class java/lang/NullPointerException
       7: dup
       8: invokespecial #474                // Method java/lang/NullPointerException."<init>":()V
      11: athrow
      12: aload_0
      13: aload_1
      14: putfield      #153                // Field statPrefix_:Ljava/lang/Object;
      17: aload_0
      18: invokevirtual #325                // Method onChanged:()V
      21: aload_0
      22: areturn

  public io.grpc.xds.shaded.io.envoyproxy.envoy.config.core.v3.GrpcService$GoogleGrpc$Builder clearStatPrefix();
    Code:
       0: aload_0
       1: invokestatic  #206                // Method io/grpc/xds/shaded/io/envoyproxy/envoy/config/core/v3/GrpcService$GoogleGrpc.getDefaultInstance:()Lio/grpc/xds/shaded/io/envoyproxy/envoy/config/core/v3/GrpcService$GoogleGrpc;
       4: invokevirtual #364                // Method io/grpc/xds/shaded/io/envoyproxy/envoy/config/core/v3/GrpcService$GoogleGrpc.getStatPrefix:()Ljava/lang/String;
       7: putfield      #153                // Field statPrefix_:Ljava/lang/Object;
      10: aload_0
      11: invokevirtual #325                // Method onChanged:()V
      14: aload_0
      15: areturn

  public io.grpc.xds.shaded.io.envoyproxy.envoy.config.core.v3.GrpcService$GoogleGrpc$Builder setStatPrefixBytes(com.google.protobuf.ByteString);
    Code:
       0: aload_1
       1: ifnonnull     12
       4: new           #473                // class java/lang/NullPointerException
       7: dup
       8: invokespecial #474                // Method java/lang/NullPointerException."<init>":()V
      11: athrow
      12: aload_1
      13: invokestatic  #653                // Method io/grpc/xds/shaded/io/envoyproxy/envoy/config/core/v3/GrpcService$GoogleGrpc.access$14000:(Lcom/google/protobuf/ByteString;)V
      16: aload_0
      17: aload_1
      18: putfield      #153                // Field statPrefix_:Ljava/lang/Object;
      21: aload_0
      22: invokevirtual #325                // Method onChanged:()V
      25: aload_0
      26: areturn

  public java.lang.String getCredentialsFactoryName();
    Code:
       0: aload_0
       1: getfield      #155                // Field credentialsFactoryName_:Ljava/lang/Object;
       4: astore_1
       5: aload_1
       6: instanceof    #315                // class java/lang/String
       9: ifne          29
      12: aload_1
      13: checkcast     #452                // class com/google/protobuf/ByteString
      16: astore_2
      17: aload_2
      18: invokevirtual #455                // Method com/google/protobuf/ByteString.toStringUtf8:()Ljava/lang/String;
      21: astore_3
      22: aload_0
      23: aload_3
      24: putfield      #155                // Field credentialsFactoryName_:Ljava/lang/Object;
      27: aload_3
      28: areturn
      29: aload_1
      30: checkcast     #315                // class java/lang/String
      33: areturn

  public com.google.protobuf.ByteString getCredentialsFactoryNameBytes();
    Code:
       0: aload_0
       1: getfield      #155                // Field credentialsFactoryName_:Ljava/lang/Object;
       4: astore_1
       5: aload_1
       6: instanceof    #315                // class java/lang/String
       9: ifeq          27
      12: aload_1
      13: checkcast     #315                // class java/lang/String
      16: invokestatic  #468                // Method com/google/protobuf/ByteString.copyFromUtf8:(Ljava/lang/String;)Lcom/google/protobuf/ByteString;
      19: astore_2
      20: aload_0
      21: aload_2
      22: putfield      #155                // Field credentialsFactoryName_:Ljava/lang/Object;
      25: aload_2
      26: areturn
      27: aload_1
      28: checkcast     #452                // class com/google/protobuf/ByteString
      31: areturn

  public io.grpc.xds.shaded.io.envoyproxy.envoy.config.core.v3.GrpcService$GoogleGrpc$Builder setCredentialsFactoryName(java.lang.String);
    Code:
       0: aload_1
       1: ifnonnull     12
       4: new           #473                // class java/lang/NullPointerException
       7: dup
       8: invokespecial #474                // Method java/lang/NullPointerException."<init>":()V
      11: athrow
      12: aload_0
      13: aload_1
      14: putfield      #155                // Field credentialsFactoryName_:Ljava/lang/Object;
      17: aload_0
      18: invokevirtual #325                // Method onChanged:()V
      21: aload_0
      22: areturn

  public io.grpc.xds.shaded.io.envoyproxy.envoy.config.core.v3.GrpcService$GoogleGrpc$Builder clearCredentialsFactoryName();
    Code:
       0: aload_0
       1: invokestatic  #206                // Method io/grpc/xds/shaded/io/envoyproxy/envoy/config/core/v3/GrpcService$GoogleGrpc.getDefaultInstance:()Lio/grpc/xds/shaded/io/envoyproxy/envoy/config/core/v3/GrpcService$GoogleGrpc;
       4: invokevirtual #370                // Method io/grpc/xds/shaded/io/envoyproxy/envoy/config/core/v3/GrpcService$GoogleGrpc.getCredentialsFactoryName:()Ljava/lang/String;
       7: putfield      #155                // Field credentialsFactoryName_:Ljava/lang/Object;
      10: aload_0
      11: invokevirtual #325                // Method onChanged:()V
      14: aload_0
      15: areturn

  public io.grpc.xds.shaded.io.envoyproxy.envoy.config.core.v3.GrpcService$GoogleGrpc$Builder setCredentialsFactoryNameBytes(com.google.protobuf.ByteString);
    Code:
       0: aload_1
       1: ifnonnull     12
       4: new           #473                // class java/lang/NullPointerException
       7: dup
       8: invokespecial #474                // Method java/lang/NullPointerException."<init>":()V
      11: athrow
      12: aload_1
      13: invokestatic  #660                // Method io/grpc/xds/shaded/io/envoyproxy/envoy/config/core/v3/GrpcService$GoogleGrpc.access$14100:(Lcom/google/protobuf/ByteString;)V
      16: aload_0
      17: aload_1
      18: putfield      #155                // Field credentialsFactoryName_:Ljava/lang/Object;
      21: aload_0
      22: invokevirtual #325                // Method onChanged:()V
      25: aload_0
      26: areturn

  public boolean hasConfig();
    Code:
       0: aload_0
       1: getfield      #190                // Field configBuilder_:Lcom/google/protobuf/SingleFieldBuilderV3;
       4: ifnonnull     14
       7: aload_0
       8: getfield      #192                // Field config_:Lcom/google/protobuf/Struct;
      11: ifnull        18
      14: iconst_1
      15: goto          19
      18: iconst_0
      19: ireturn

  public com.google.protobuf.Struct getConfig();
    Code:
       0: aload_0
       1: getfield      #190                // Field configBuilder_:Lcom/google/protobuf/SingleFieldBuilderV3;
       4: ifnonnull     25
       7: aload_0
       8: getfield      #192                // Field config_:Lcom/google/protobuf/Struct;
      11: ifnonnull     20
      14: invokestatic  #662                // Method com/google/protobuf/Struct.getDefaultInstance:()Lcom/google/protobuf/Struct;
      17: goto          24
      20: aload_0
      21: getfield      #192                // Field config_:Lcom/google/protobuf/Struct;
      24: areturn
      25: aload_0
      26: getfield      #190                // Field configBuilder_:Lcom/google/protobuf/SingleFieldBuilderV3;
      29: invokevirtual #486                // Method com/google/protobuf/SingleFieldBuilderV3.getMessage:()Lcom/google/protobuf/AbstractMessage;
      32: checkcast     #34                 // class com/google/protobuf/Struct
      35: areturn

  public io.grpc.xds.shaded.io.envoyproxy.envoy.config.core.v3.GrpcService$GoogleGrpc$Builder setConfig(com.google.protobuf.Struct);
    Code:
       0: aload_0
       1: getfield      #190                // Field configBuilder_:Lcom/google/protobuf/SingleFieldBuilderV3;
       4: ifnonnull     31
       7: aload_1
       8: ifnonnull     19
      11: new           #473                // class java/lang/NullPointerException
      14: dup
      15: invokespecial #474                // Method java/lang/NullPointerException."<init>":()V
      18: athrow
      19: aload_0
      20: aload_1
      21: putfield      #192                // Field config_:Lcom/google/protobuf/Struct;
      24: aload_0
      25: invokevirtual #325                // Method onChanged:()V
      28: goto          40
      31: aload_0
      32: getfield      #190                // Field configBuilder_:Lcom/google/protobuf/SingleFieldBuilderV3;
      35: aload_1
      36: invokevirtual #491                // Method com/google/protobuf/SingleFieldBuilderV3.setMessage:(Lcom/google/protobuf/AbstractMessage;)Lcom/google/protobuf/SingleFieldBuilderV3;
      39: pop
      40: aload_0
      41: areturn

  public io.grpc.xds.shaded.io.envoyproxy.envoy.config.core.v3.GrpcService$GoogleGrpc$Builder setConfig(com.google.protobuf.Struct$Builder);
    Code:
       0: aload_0
       1: getfield      #190                // Field configBuilder_:Lcom/google/protobuf/SingleFieldBuilderV3;
       4: ifnonnull     22
       7: aload_0
       8: aload_1
       9: invokevirtual #666                // Method com/google/protobuf/Struct$Builder.build:()Lcom/google/protobuf/Struct;
      12: putfield      #192                // Field config_:Lcom/google/protobuf/Struct;
      15: aload_0
      16: invokevirtual #325                // Method onChanged:()V
      19: goto          34
      22: aload_0
      23: getfield      #190                // Field configBuilder_:Lcom/google/protobuf/SingleFieldBuilderV3;
      26: aload_1
      27: invokevirtual #666                // Method com/google/protobuf/Struct$Builder.build:()Lcom/google/protobuf/Struct;
      30: invokevirtual #491                // Method com/google/protobuf/SingleFieldBuilderV3.setMessage:(Lcom/google/protobuf/AbstractMessage;)Lcom/google/protobuf/SingleFieldBuilderV3;
      33: pop
      34: aload_0
      35: areturn

  public io.grpc.xds.shaded.io.envoyproxy.envoy.config.core.v3.GrpcService$GoogleGrpc$Builder mergeConfig(com.google.protobuf.Struct);
    Code:
       0: aload_0
       1: getfield      #190                // Field configBuilder_:Lcom/google/protobuf/SingleFieldBuilderV3;
       4: ifnonnull     47
       7: aload_0
       8: getfield      #192                // Field config_:Lcom/google/protobuf/Struct;
      11: ifnull        35
      14: aload_0
      15: aload_0
      16: getfield      #192                // Field config_:Lcom/google/protobuf/Struct;
      19: invokestatic  #670                // Method com/google/protobuf/Struct.newBuilder:(Lcom/google/protobuf/Struct;)Lcom/google/protobuf/Struct$Builder;
      22: aload_1
      23: invokevirtual #672                // Method com/google/protobuf/Struct$Builder.mergeFrom:(Lcom/google/protobuf/Struct;)Lcom/google/protobuf/Struct$Builder;
      26: invokevirtual #674                // Method com/google/protobuf/Struct$Builder.buildPartial:()Lcom/google/protobuf/Struct;
      29: putfield      #192                // Field config_:Lcom/google/protobuf/Struct;
      32: goto          40
      35: aload_0
      36: aload_1
      37: putfield      #192                // Field config_:Lcom/google/protobuf/Struct;
      40: aload_0
      41: invokevirtual #325                // Method onChanged:()V
      44: goto          56
      47: aload_0
      48: getfield      #190                // Field configBuilder_:Lcom/google/protobuf/SingleFieldBuilderV3;
      51: aload_1
      52: invokevirtual #506                // Method com/google/protobuf/SingleFieldBuilderV3.mergeFrom:(Lcom/google/protobuf/AbstractMessage;)Lcom/google/protobuf/SingleFieldBuilderV3;
      55: pop
      56: aload_0
      57: areturn

  public io.grpc.xds.shaded.io.envoyproxy.envoy.config.core.v3.GrpcService$GoogleGrpc$Builder clearConfig();
    Code:
       0: aload_0
       1: getfield      #190                // Field configBuilder_:Lcom/google/protobuf/SingleFieldBuilderV3;
       4: ifnonnull     19
       7: aload_0
       8: aconst_null
       9: putfield      #192                // Field config_:Lcom/google/protobuf/Struct;
      12: aload_0
      13: invokevirtual #325                // Method onChanged:()V
      16: goto          29
      19: aload_0
      20: aconst_null
      21: putfield      #192                // Field config_:Lcom/google/protobuf/Struct;
      24: aload_0
      25: aconst_null
      26: putfield      #190                // Field configBuilder_:Lcom/google/protobuf/SingleFieldBuilderV3;
      29: aload_0
      30: areturn

  public com.google.protobuf.Struct$Builder getConfigBuilder();
    Code:
       0: aload_0
       1: invokevirtual #325                // Method onChanged:()V
       4: aload_0
       5: invokespecial #680                // Method getConfigFieldBuilder:()Lcom/google/protobuf/SingleFieldBuilderV3;
       8: invokevirtual #517                // Method com/google/protobuf/SingleFieldBuilderV3.getBuilder:()Lcom/google/protobuf/AbstractMessage$Builder;
      11: checkcast     #32                 // class com/google/protobuf/Struct$Builder
      14: areturn

  public com.google.protobuf.StructOrBuilder getConfigOrBuilder();
    Code:
       0: aload_0
       1: getfield      #190                // Field configBuilder_:Lcom/google/protobuf/SingleFieldBuilderV3;
       4: ifnull        18
       7: aload_0
       8: getfield      #190                // Field configBuilder_:Lcom/google/protobuf/SingleFieldBuilderV3;
      11: invokevirtual #523                // Method com/google/protobuf/SingleFieldBuilderV3.getMessageOrBuilder:()Lcom/google/protobuf/MessageOrBuilder;
      14: checkcast     #684                // class com/google/protobuf/StructOrBuilder
      17: areturn
      18: aload_0
      19: getfield      #192                // Field config_:Lcom/google/protobuf/Struct;
      22: ifnonnull     31
      25: invokestatic  #662                // Method com/google/protobuf/Struct.getDefaultInstance:()Lcom/google/protobuf/Struct;
      28: goto          35
      31: aload_0
      32: getfield      #192                // Field config_:Lcom/google/protobuf/Struct;
      35: areturn

  private com.google.protobuf.SingleFieldBuilderV3<com.google.protobuf.Struct, com.google.protobuf.Struct$Builder, com.google.protobuf.StructOrBuilder> getConfigFieldBuilder();
    Code:
       0: aload_0
       1: getfield      #190                // Field configBuilder_:Lcom/google/protobuf/SingleFieldBuilderV3;
       4: ifnonnull     35
       7: aload_0
       8: new           #232                // class com/google/protobuf/SingleFieldBuilderV3
      11: dup
      12: aload_0
      13: invokevirtual #686                // Method getConfig:()Lcom/google/protobuf/Struct;
      16: aload_0
      17: invokevirtual #529                // Method getParentForChildren:()Lcom/google/protobuf/GeneratedMessageV3$BuilderParent;
      20: aload_0
      21: invokevirtual #532                // Method isClean:()Z
      24: invokespecial #535                // Method com/google/protobuf/SingleFieldBuilderV3."<init>":(Lcom/google/protobuf/AbstractMessage;Lcom/google/protobuf/AbstractMessage$BuilderParent;Z)V
      27: putfield      #190                // Field configBuilder_:Lcom/google/protobuf/SingleFieldBuilderV3;
      30: aload_0
      31: aconst_null
      32: putfield      #192                // Field config_:Lcom/google/protobuf/Struct;
      35: aload_0
      36: getfield      #190                // Field configBuilder_:Lcom/google/protobuf/SingleFieldBuilderV3;
      39: areturn

  public boolean hasPerStreamBufferLimitBytes();
    Code:
       0: aload_0
       1: getfield      #194                // Field perStreamBufferLimitBytesBuilder_:Lcom/google/protobuf/SingleFieldBuilderV3;
       4: ifnonnull     14
       7: aload_0
       8: getfield      #196                // Field perStreamBufferLimitBytes_:Lcom/google/protobuf/UInt32Value;
      11: ifnull        18
      14: iconst_1
      15: goto          19
      18: iconst_0
      19: ireturn

  public com.google.protobuf.UInt32Value getPerStreamBufferLimitBytes();
    Code:
       0: aload_0
       1: getfield      #194                // Field perStreamBufferLimitBytesBuilder_:Lcom/google/protobuf/SingleFieldBuilderV3;
       4: ifnonnull     25
       7: aload_0
       8: getfield      #196                // Field perStreamBufferLimitBytes_:Lcom/google/protobuf/UInt32Value;
      11: ifnonnull     20
      14: invokestatic  #688                // Method com/google/protobuf/UInt32Value.getDefaultInstance:()Lcom/google/protobuf/UInt32Value;
      17: goto          24
      20: aload_0
      21: getfield      #196                // Field perStreamBufferLimitBytes_:Lcom/google/protobuf/UInt32Value;
      24: areturn
      25: aload_0
      26: getfield      #194                // Field perStreamBufferLimitBytesBuilder_:Lcom/google/protobuf/SingleFieldBuilderV3;
      29: invokevirtual #486                // Method com/google/protobuf/SingleFieldBuilderV3.getMessage:()Lcom/google/protobuf/AbstractMessage;
      32: checkcast     #38                 // class com/google/protobuf/UInt32Value
      35: areturn

  public io.grpc.xds.shaded.io.envoyproxy.envoy.config.core.v3.GrpcService$GoogleGrpc$Builder setPerStreamBufferLimitBytes(com.google.protobuf.UInt32Value);
    Code:
       0: aload_0
       1: getfield      #194                // Field perStreamBufferLimitBytesBuilder_:Lcom/google/protobuf/SingleFieldBuilderV3;
       4: ifnonnull     31
       7: aload_1
       8: ifnonnull     19
      11: new           #473                // class java/lang/NullPointerException
      14: dup
      15: invokespecial #474                // Method java/lang/NullPointerException."<init>":()V
      18: athrow
      19: aload_0
      20: aload_1
      21: putfield      #196                // Field perStreamBufferLimitBytes_:Lcom/google/protobuf/UInt32Value;
      24: aload_0
      25: invokevirtual #325                // Method onChanged:()V
      28: goto          40
      31: aload_0
      32: getfield      #194                // Field perStreamBufferLimitBytesBuilder_:Lcom/google/protobuf/SingleFieldBuilderV3;
      35: aload_1
      36: invokevirtual #491                // Method com/google/protobuf/SingleFieldBuilderV3.setMessage:(Lcom/google/protobuf/AbstractMessage;)Lcom/google/protobuf/SingleFieldBuilderV3;
      39: pop
      40: aload_0
      41: areturn

  public io.grpc.xds.shaded.io.envoyproxy.envoy.config.core.v3.GrpcService$GoogleGrpc$Builder setPerStreamBufferLimitBytes(com.google.protobuf.UInt32Value$Builder);
    Code:
       0: aload_0
       1: getfield      #194                // Field perStreamBufferLimitBytesBuilder_:Lcom/google/protobuf/SingleFieldBuilderV3;
       4: ifnonnull     22
       7: aload_0
       8: aload_1
       9: invokevirtual #692                // Method com/google/protobuf/UInt32Value$Builder.build:()Lcom/google/protobuf/UInt32Value;
      12: putfield      #196                // Field perStreamBufferLimitBytes_:Lcom/google/protobuf/UInt32Value;
      15: aload_0
      16: invokevirtual #325                // Method onChanged:()V
      19: goto          34
      22: aload_0
      23: getfield      #194                // Field perStreamBufferLimitBytesBuilder_:Lcom/google/protobuf/SingleFieldBuilderV3;
      26: aload_1
      27: invokevirtual #692                // Method com/google/protobuf/UInt32Value$Builder.build:()Lcom/google/protobuf/UInt32Value;
      30: invokevirtual #491                // Method com/google/protobuf/SingleFieldBuilderV3.setMessage:(Lcom/google/protobuf/AbstractMessage;)Lcom/google/protobuf/SingleFieldBuilderV3;
      33: pop
      34: aload_0
      35: areturn

  public io.grpc.xds.shaded.io.envoyproxy.envoy.config.core.v3.GrpcService$GoogleGrpc$Builder mergePerStreamBufferLimitBytes(com.google.protobuf.UInt32Value);
    Code:
       0: aload_0
       1: getfield      #194                // Field perStreamBufferLimitBytesBuilder_:Lcom/google/protobuf/SingleFieldBuilderV3;
       4: ifnonnull     47
       7: aload_0
       8: getfield      #196                // Field perStreamBufferLimitBytes_:Lcom/google/protobuf/UInt32Value;
      11: ifnull        35
      14: aload_0
      15: aload_0
      16: getfield      #196                // Field perStreamBufferLimitBytes_:Lcom/google/protobuf/UInt32Value;
      19: invokestatic  #696                // Method com/google/protobuf/UInt32Value.newBuilder:(Lcom/google/protobuf/UInt32Value;)Lcom/google/protobuf/UInt32Value$Builder;
      22: aload_1
      23: invokevirtual #698                // Method com/google/protobuf/UInt32Value$Builder.mergeFrom:(Lcom/google/protobuf/UInt32Value;)Lcom/google/protobuf/UInt32Value$Builder;
      26: invokevirtual #700                // Method com/google/protobuf/UInt32Value$Builder.buildPartial:()Lcom/google/protobuf/UInt32Value;
      29: putfield      #196                // Field perStreamBufferLimitBytes_:Lcom/google/protobuf/UInt32Value;
      32: goto          40
      35: aload_0
      36: aload_1
      37: putfield      #196                // Field perStreamBufferLimitBytes_:Lcom/google/protobuf/UInt32Value;
      40: aload_0
      41: invokevirtual #325                // Method onChanged:()V
      44: goto          56
      47: aload_0
      48: getfield      #194                // Field perStreamBufferLimitBytesBuilder_:Lcom/google/protobuf/SingleFieldBuilderV3;
      51: aload_1
      52: invokevirtual #506                // Method com/google/protobuf/SingleFieldBuilderV3.mergeFrom:(Lcom/google/protobuf/AbstractMessage;)Lcom/google/protobuf/SingleFieldBuilderV3;
      55: pop
      56: aload_0
      57: areturn

  public io.grpc.xds.shaded.io.envoyproxy.envoy.config.core.v3.GrpcService$GoogleGrpc$Builder clearPerStreamBufferLimitBytes();
    Code:
       0: aload_0
       1: getfield      #194                // Field perStreamBufferLimitBytesBuilder_:Lcom/google/protobuf/SingleFieldBuilderV3;
       4: ifnonnull     19
       7: aload_0
       8: aconst_null
       9: putfield      #196                // Field perStreamBufferLimitBytes_:Lcom/google/protobuf/UInt32Value;
      12: aload_0
      13: invokevirtual #325                // Method onChanged:()V
      16: goto          29
      19: aload_0
      20: aconst_null
      21: putfield      #196                // Field perStreamBufferLimitBytes_:Lcom/google/protobuf/UInt32Value;
      24: aload_0
      25: aconst_null
      26: putfield      #194                // Field perStreamBufferLimitBytesBuilder_:Lcom/google/protobuf/SingleFieldBuilderV3;
      29: aload_0
      30: areturn

  public com.google.protobuf.UInt32Value$Builder getPerStreamBufferLimitBytesBuilder();
    Code:
       0: aload_0
       1: invokevirtual #325                // Method onChanged:()V
       4: aload_0
       5: invokespecial #706                // Method getPerStreamBufferLimitBytesFieldBuilder:()Lcom/google/protobuf/SingleFieldBuilderV3;
       8: invokevirtual #517                // Method com/google/protobuf/SingleFieldBuilderV3.getBuilder:()Lcom/google/protobuf/AbstractMessage$Builder;
      11: checkcast     #36                 // class com/google/protobuf/UInt32Value$Builder
      14: areturn

  public com.google.protobuf.UInt32ValueOrBuilder getPerStreamBufferLimitBytesOrBuilder();
    Code:
       0: aload_0
       1: getfield      #194                // Field perStreamBufferLimitBytesBuilder_:Lcom/google/protobuf/SingleFieldBuilderV3;
       4: ifnull        18
       7: aload_0
       8: getfield      #194                // Field perStreamBufferLimitBytesBuilder_:Lcom/google/protobuf/SingleFieldBuilderV3;
      11: invokevirtual #523                // Method com/google/protobuf/SingleFieldBuilderV3.getMessageOrBuilder:()Lcom/google/protobuf/MessageOrBuilder;
      14: checkcast     #710                // class com/google/protobuf/UInt32ValueOrBuilder
      17: areturn
      18: aload_0
      19: getfield      #196                // Field perStreamBufferLimitBytes_:Lcom/google/protobuf/UInt32Value;
      22: ifnonnull     31
      25: invokestatic  #688                // Method com/google/protobuf/UInt32Value.getDefaultInstance:()Lcom/google/protobuf/UInt32Value;
      28: goto          35
      31: aload_0
      32: getfield      #196                // Field perStreamBufferLimitBytes_:Lcom/google/protobuf/UInt32Value;
      35: areturn

  private com.google.protobuf.SingleFieldBuilderV3<com.google.protobuf.UInt32Value, com.google.protobuf.UInt32Value$Builder, com.google.protobuf.UInt32ValueOrBuilder> getPerStreamBufferLimitBytesFieldBuilder();
    Code:
       0: aload_0
       1: getfield      #194                // Field perStreamBufferLimitBytesBuilder_:Lcom/google/protobuf/SingleFieldBuilderV3;
       4: ifnonnull     35
       7: aload_0
       8: new           #232                // class com/google/protobuf/SingleFieldBuilderV3
      11: dup
      12: aload_0
      13: invokevirtual #712                // Method getPerStreamBufferLimitBytes:()Lcom/google/protobuf/UInt32Value;
      16: aload_0
      17: invokevirtual #529                // Method getParentForChildren:()Lcom/google/protobuf/GeneratedMessageV3$BuilderParent;
      20: aload_0
      21: invokevirtual #532                // Method isClean:()Z
      24: invokespecial #535                // Method com/google/protobuf/SingleFieldBuilderV3."<init>":(Lcom/google/protobuf/AbstractMessage;Lcom/google/protobuf/AbstractMessage$BuilderParent;Z)V
      27: putfield      #194                // Field perStreamBufferLimitBytesBuilder_:Lcom/google/protobuf/SingleFieldBuilderV3;
      30: aload_0
      31: aconst_null
      32: putfield      #196                // Field perStreamBufferLimitBytes_:Lcom/google/protobuf/UInt32Value;
      35: aload_0
      36: getfield      #194                // Field perStreamBufferLimitBytesBuilder_:Lcom/google/protobuf/SingleFieldBuilderV3;
      39: areturn

  public boolean hasChannelArgs();
    Code:
       0: aload_0
       1: getfield      #198                // Field channelArgsBuilder_:Lcom/google/protobuf/SingleFieldBuilderV3;
       4: ifnonnull     14
       7: aload_0
       8: getfield      #200                // Field channelArgs_:Lio/grpc/xds/shaded/io/envoyproxy/envoy/config/core/v3/GrpcService$GoogleGrpc$ChannelArgs;
      11: ifnull        18
      14: iconst_1
      15: goto          19
      18: iconst_0
      19: ireturn

  public io.grpc.xds.shaded.io.envoyproxy.envoy.config.core.v3.GrpcService$GoogleGrpc$ChannelArgs getChannelArgs();
    Code:
       0: aload_0
       1: getfield      #198                // Field channelArgsBuilder_:Lcom/google/protobuf/SingleFieldBuilderV3;
       4: ifnonnull     25
       7: aload_0
       8: getfield      #200                // Field channelArgs_:Lio/grpc/xds/shaded/io/envoyproxy/envoy/config/core/v3/GrpcService$GoogleGrpc$ChannelArgs;
      11: ifnonnull     20
      14: invokestatic  #714                // Method io/grpc/xds/shaded/io/envoyproxy/envoy/config/core/v3/GrpcService$GoogleGrpc$ChannelArgs.getDefaultInstance:()Lio/grpc/xds/shaded/io/envoyproxy/envoy/config/core/v3/GrpcService$GoogleGrpc$ChannelArgs;
      17: goto          24
      20: aload_0
      21: getfield      #200                // Field channelArgs_:Lio/grpc/xds/shaded/io/envoyproxy/envoy/config/core/v3/GrpcService$GoogleGrpc$ChannelArgs;
      24: areturn
      25: aload_0
      26: getfield      #198                // Field channelArgsBuilder_:Lcom/google/protobuf/SingleFieldBuilderV3;
      29: invokevirtual #486                // Method com/google/protobuf/SingleFieldBuilderV3.getMessage:()Lcom/google/protobuf/AbstractMessage;
      32: checkcast     #40                 // class io/grpc/xds/shaded/io/envoyproxy/envoy/config/core/v3/GrpcService$GoogleGrpc$ChannelArgs
      35: areturn

  public io.grpc.xds.shaded.io.envoyproxy.envoy.config.core.v3.GrpcService$GoogleGrpc$Builder setChannelArgs(io.grpc.xds.shaded.io.envoyproxy.envoy.config.core.v3.GrpcService$GoogleGrpc$ChannelArgs);
    Code:
       0: aload_0
       1: getfield      #198                // Field channelArgsBuilder_:Lcom/google/protobuf/SingleFieldBuilderV3;
       4: ifnonnull     31
       7: aload_1
       8: ifnonnull     19
      11: new           #473                // class java/lang/NullPointerException
      14: dup
      15: invokespecial #474                // Method java/lang/NullPointerException."<init>":()V
      18: athrow
      19: aload_0
      20: aload_1
      21: putfield      #200                // Field channelArgs_:Lio/grpc/xds/shaded/io/envoyproxy/envoy/config/core/v3/GrpcService$GoogleGrpc$ChannelArgs;
      24: aload_0
      25: invokevirtual #325                // Method onChanged:()V
      28: goto          40
      31: aload_0
      32: getfield      #198                // Field channelArgsBuilder_:Lcom/google/protobuf/SingleFieldBuilderV3;
      35: aload_1
      36: invokevirtual #491                // Method com/google/protobuf/SingleFieldBuilderV3.setMessage:(Lcom/google/protobuf/AbstractMessage;)Lcom/google/protobuf/SingleFieldBuilderV3;
      39: pop
      40: aload_0
      41: areturn

  public io.grpc.xds.shaded.io.envoyproxy.envoy.config.core.v3.GrpcService$GoogleGrpc$Builder setChannelArgs(io.grpc.xds.shaded.io.envoyproxy.envoy.config.core.v3.GrpcService$GoogleGrpc$ChannelArgs$Builder);
    Code:
       0: aload_0
       1: getfield      #198                // Field channelArgsBuilder_:Lcom/google/protobuf/SingleFieldBuilderV3;
       4: ifnonnull     22
       7: aload_0
       8: aload_1
       9: invokevirtual #718                // Method io/grpc/xds/shaded/io/envoyproxy/envoy/config/core/v3/GrpcService$GoogleGrpc$ChannelArgs$Builder.build:()Lio/grpc/xds/shaded/io/envoyproxy/envoy/config/core/v3/GrpcService$GoogleGrpc$ChannelArgs;
      12: putfield      #200                // Field channelArgs_:Lio/grpc/xds/shaded/io/envoyproxy/envoy/config/core/v3/GrpcService$GoogleGrpc$ChannelArgs;
      15: aload_0
      16: invokevirtual #325                // Method onChanged:()V
      19: goto          34
      22: aload_0
      23: getfield      #198                // Field channelArgsBuilder_:Lcom/google/protobuf/SingleFieldBuilderV3;
      26: aload_1
      27: invokevirtual #718                // Method io/grpc/xds/shaded/io/envoyproxy/envoy/config/core/v3/GrpcService$GoogleGrpc$ChannelArgs$Builder.build:()Lio/grpc/xds/shaded/io/envoyproxy/envoy/config/core/v3/GrpcService$GoogleGrpc$ChannelArgs;
      30: invokevirtual #491                // Method com/google/protobuf/SingleFieldBuilderV3.setMessage:(Lcom/google/protobuf/AbstractMessage;)Lcom/google/protobuf/SingleFieldBuilderV3;
      33: pop
      34: aload_0
      35: areturn

  public io.grpc.xds.shaded.io.envoyproxy.envoy.config.core.v3.GrpcService$GoogleGrpc$Builder mergeChannelArgs(io.grpc.xds.shaded.io.envoyproxy.envoy.config.core.v3.GrpcService$GoogleGrpc$ChannelArgs);
    Code:
       0: aload_0
       1: getfield      #198                // Field channelArgsBuilder_:Lcom/google/protobuf/SingleFieldBuilderV3;
       4: ifnonnull     47
       7: aload_0
       8: getfield      #200                // Field channelArgs_:Lio/grpc/xds/shaded/io/envoyproxy/envoy/config/core/v3/GrpcService$GoogleGrpc$ChannelArgs;
      11: ifnull        35
      14: aload_0
      15: aload_0
      16: getfield      #200                // Field channelArgs_:Lio/grpc/xds/shaded/io/envoyproxy/envoy/config/core/v3/GrpcService$GoogleGrpc$ChannelArgs;
      19: invokestatic  #722                // Method io/grpc/xds/shaded/io/envoyproxy/envoy/config/core/v3/GrpcService$GoogleGrpc$ChannelArgs.newBuilder:(Lio/grpc/xds/shaded/io/envoyproxy/envoy/config/core/v3/GrpcService$GoogleGrpc$ChannelArgs;)Lio/grpc/xds/shaded/io/envoyproxy/envoy/config/core/v3/GrpcService$GoogleGrpc$ChannelArgs$Builder;
      22: aload_1
      23: invokevirtual #724                // Method io/grpc/xds/shaded/io/envoyproxy/envoy/config/core/v3/GrpcService$GoogleGrpc$ChannelArgs$Builder.mergeFrom:(Lio/grpc/xds/shaded/io/envoyproxy/envoy/config/core/v3/GrpcService$GoogleGrpc$ChannelArgs;)Lio/grpc/xds/shaded/io/envoyproxy/envoy/config/core/v3/GrpcService$GoogleGrpc$ChannelArgs$Builder;
      26: invokevirtual #726                // Method io/grpc/xds/shaded/io/envoyproxy/envoy/config/core/v3/GrpcService$GoogleGrpc$ChannelArgs$Builder.buildPartial:()Lio/grpc/xds/shaded/io/envoyproxy/envoy/config/core/v3/GrpcService$GoogleGrpc$ChannelArgs;
      29: putfield      #200                // Field channelArgs_:Lio/grpc/xds/shaded/io/envoyproxy/envoy/config/core/v3/GrpcService$GoogleGrpc$ChannelArgs;
      32: goto          40
      35: aload_0
      36: aload_1
      37: putfield      #200                // Field channelArgs_:Lio/grpc/xds/shaded/io/envoyproxy/envoy/config/core/v3/GrpcService$GoogleGrpc$ChannelArgs;
      40: aload_0
      41: invokevirtual #325                // Method onChanged:()V
      44: goto          56
      47: aload_0
      48: getfield      #198                // Field channelArgsBuilder_:Lcom/google/protobuf/SingleFieldBuilderV3;
      51: aload_1
      52: invokevirtual #506                // Method com/google/protobuf/SingleFieldBuilderV3.mergeFrom:(Lcom/google/protobuf/AbstractMessage;)Lcom/google/protobuf/SingleFieldBuilderV3;
      55: pop
      56: aload_0
      57: areturn

  public io.grpc.xds.shaded.io.envoyproxy.envoy.config.core.v3.GrpcService$GoogleGrpc$Builder clearChannelArgs();
    Code:
       0: aload_0
       1: getfield      #198                // Field channelArgsBuilder_:Lcom/google/protobuf/SingleFieldBuilderV3;
       4: ifnonnull     19
       7: aload_0
       8: aconst_null
       9: putfield      #200                // Field channelArgs_:Lio/grpc/xds/shaded/io/envoyproxy/envoy/config/core/v3/GrpcService$GoogleGrpc$ChannelArgs;
      12: aload_0
      13: invokevirtual #325                // Method onChanged:()V
      16: goto          29
      19: aload_0
      20: aconst_null
      21: putfield      #200                // Field channelArgs_:Lio/grpc/xds/shaded/io/envoyproxy/envoy/config/core/v3/GrpcService$GoogleGrpc$ChannelArgs;
      24: aload_0
      25: aconst_null
      26: putfield      #198                // Field channelArgsBuilder_:Lcom/google/protobuf/SingleFieldBuilderV3;
      29: aload_0
      30: areturn

  public io.grpc.xds.shaded.io.envoyproxy.envoy.config.core.v3.GrpcService$GoogleGrpc$ChannelArgs$Builder getChannelArgsBuilder();
    Code:
       0: aload_0
       1: invokevirtual #325                // Method onChanged:()V
       4: aload_0
       5: invokespecial #732                // Method getChannelArgsFieldBuilder:()Lcom/google/protobuf/SingleFieldBuilderV3;
       8: invokevirtual #517                // Method com/google/protobuf/SingleFieldBuilderV3.getBuilder:()Lcom/google/protobuf/AbstractMessage$Builder;
      11: checkcast     #43                 // class io/grpc/xds/shaded/io/envoyproxy/envoy/config/core/v3/GrpcService$GoogleGrpc$ChannelArgs$Builder
      14: areturn

  public io.grpc.xds.shaded.io.envoyproxy.envoy.config.core.v3.GrpcService$GoogleGrpc$ChannelArgsOrBuilder getChannelArgsOrBuilder();
    Code:
       0: aload_0
       1: getfield      #198                // Field channelArgsBuilder_:Lcom/google/protobuf/SingleFieldBuilderV3;
       4: ifnull        18
       7: aload_0
       8: getfield      #198                // Field channelArgsBuilder_:Lcom/google/protobuf/SingleFieldBuilderV3;
      11: invokevirtual #523                // Method com/google/protobuf/SingleFieldBuilderV3.getMessageOrBuilder:()Lcom/google/protobuf/MessageOrBuilder;
      14: checkcast     #45                 // class io/grpc/xds/shaded/io/envoyproxy/envoy/config/core/v3/GrpcService$GoogleGrpc$ChannelArgsOrBuilder
      17: areturn
      18: aload_0
      19: getfield      #200                // Field channelArgs_:Lio/grpc/xds/shaded/io/envoyproxy/envoy/config/core/v3/GrpcService$GoogleGrpc$ChannelArgs;
      22: ifnonnull     31
      25: invokestatic  #714                // Method io/grpc/xds/shaded/io/envoyproxy/envoy/config/core/v3/GrpcService$GoogleGrpc$ChannelArgs.getDefaultInstance:()Lio/grpc/xds/shaded/io/envoyproxy/envoy/config/core/v3/GrpcService$GoogleGrpc$ChannelArgs;
      28: goto          35
      31: aload_0
      32: getfield      #200                // Field channelArgs_:Lio/grpc/xds/shaded/io/envoyproxy/envoy/config/core/v3/GrpcService$GoogleGrpc$ChannelArgs;
      35: areturn

  private com.google.protobuf.SingleFieldBuilderV3<io.grpc.xds.shaded.io.envoyproxy.envoy.config.core.v3.GrpcService$GoogleGrpc$ChannelArgs, io.grpc.xds.shaded.io.envoyproxy.envoy.config.core.v3.GrpcService$GoogleGrpc$ChannelArgs$Builder, io.grpc.xds.shaded.io.envoyproxy.envoy.config.core.v3.GrpcService$GoogleGrpc$ChannelArgsOrBuilder> getChannelArgsFieldBuilder();
    Code:
       0: aload_0
       1: getfield      #198                // Field channelArgsBuilder_:Lcom/google/protobuf/SingleFieldBuilderV3;
       4: ifnonnull     35
       7: aload_0
       8: new           #232                // class com/google/protobuf/SingleFieldBuilderV3
      11: dup
      12: aload_0
      13: invokevirtual #736                // Method getChannelArgs:()Lio/grpc/xds/shaded/io/envoyproxy/envoy/config/core/v3/GrpcService$GoogleGrpc$ChannelArgs;
      16: aload_0
      17: invokevirtual #529                // Method getParentForChildren:()Lcom/google/protobuf/GeneratedMessageV3$BuilderParent;
      20: aload_0
      21: invokevirtual #532                // Method isClean:()Z
      24: invokespecial #535                // Method com/google/protobuf/SingleFieldBuilderV3."<init>":(Lcom/google/protobuf/AbstractMessage;Lcom/google/protobuf/AbstractMessage$BuilderParent;Z)V
      27: putfield      #198                // Field channelArgsBuilder_:Lcom/google/protobuf/SingleFieldBuilderV3;
      30: aload_0
      31: aconst_null
      32: putfield      #200                // Field channelArgs_:Lio/grpc/xds/shaded/io/envoyproxy/envoy/config/core/v3/GrpcService$GoogleGrpc$ChannelArgs;
      35: aload_0
      36: getfield      #198                // Field channelArgsBuilder_:Lcom/google/protobuf/SingleFieldBuilderV3;
      39: areturn

  public final io.grpc.xds.shaded.io.envoyproxy.envoy.config.core.v3.GrpcService$GoogleGrpc$Builder setUnknownFields(com.google.protobuf.UnknownFieldSet);
    Code:
       0: aload_0
       1: aload_1
       2: invokespecial #740                // Method com/google/protobuf/GeneratedMessageV3$Builder.setUnknownFields:(Lcom/google/protobuf/UnknownFieldSet;)Lcom/google/protobuf/GeneratedMessageV3$Builder;
       5: checkcast     #2                  // class io/grpc/xds/shaded/io/envoyproxy/envoy/config/core/v3/GrpcService$GoogleGrpc$Builder
       8: areturn

  public final io.grpc.xds.shaded.io.envoyproxy.envoy.config.core.v3.GrpcService$GoogleGrpc$Builder mergeUnknownFields(com.google.protobuf.UnknownFieldSet);
    Code:
       0: aload_0
       1: aload_1
       2: invokespecial #744                // Method com/google/protobuf/GeneratedMessageV3$Builder.mergeUnknownFields:(Lcom/google/protobuf/UnknownFieldSet;)Lcom/google/protobuf/GeneratedMessageV3$Builder;
       5: checkcast     #2                  // class io/grpc/xds/shaded/io/envoyproxy/envoy/config/core/v3/GrpcService$GoogleGrpc$Builder
       8: areturn

  public com.google.protobuf.GeneratedMessageV3$Builder mergeUnknownFields(com.google.protobuf.UnknownFieldSet);
    Code:
       0: aload_0
       1: aload_1
       2: invokevirtual #414                // Method mergeUnknownFields:(Lcom/google/protobuf/UnknownFieldSet;)Lio/grpc/xds/shaded/io/envoyproxy/envoy/config/core/v3/GrpcService$GoogleGrpc$Builder;
       5: areturn

  public com.google.protobuf.GeneratedMessageV3$Builder setUnknownFields(com.google.protobuf.UnknownFieldSet);
    Code:
       0: aload_0
       1: aload_1
       2: invokevirtual #746                // Method setUnknownFields:(Lcom/google/protobuf/UnknownFieldSet;)Lio/grpc/xds/shaded/io/envoyproxy/envoy/config/core/v3/GrpcService$GoogleGrpc$Builder;
       5: areturn

  public com.google.protobuf.GeneratedMessageV3$Builder addRepeatedField(com.google.protobuf.Descriptors$FieldDescriptor, java.lang.Object);
    Code:
       0: aload_0
       1: aload_1
       2: aload_2
       3: invokevirtual #748                // Method addRepeatedField:(Lcom/google/protobuf/Descriptors$FieldDescriptor;Ljava/lang/Object;)Lio/grpc/xds/shaded/io/envoyproxy/envoy/config/core/v3/GrpcService$GoogleGrpc$Builder;
       6: areturn

  public com.google.protobuf.GeneratedMessageV3$Builder setRepeatedField(com.google.protobuf.Descriptors$FieldDescriptor, int, java.lang.Object);
    Code:
       0: aload_0
       1: aload_1
       2: iload_2
       3: aload_3
       4: invokevirtual #750                // Method setRepeatedField:(Lcom/google/protobuf/Descriptors$FieldDescriptor;ILjava/lang/Object;)Lio/grpc/xds/shaded/io/envoyproxy/envoy/config/core/v3/GrpcService$GoogleGrpc$Builder;
       7: areturn

  public com.google.protobuf.GeneratedMessageV3$Builder clearOneof(com.google.protobuf.Descriptors$OneofDescriptor);
    Code:
       0: aload_0
       1: aload_1
       2: invokevirtual #752                // Method clearOneof:(Lcom/google/protobuf/Descriptors$OneofDescriptor;)Lio/grpc/xds/shaded/io/envoyproxy/envoy/config/core/v3/GrpcService$GoogleGrpc$Builder;
       5: areturn

  public com.google.protobuf.GeneratedMessageV3$Builder clearField(com.google.protobuf.Descriptors$FieldDescriptor);
    Code:
       0: aload_0
       1: aload_1
       2: invokevirtual #754                // Method clearField:(Lcom/google/protobuf/Descriptors$FieldDescriptor;)Lio/grpc/xds/shaded/io/envoyproxy/envoy/config/core/v3/GrpcService$GoogleGrpc$Builder;
       5: areturn

  public com.google.protobuf.GeneratedMessageV3$Builder setField(com.google.protobuf.Descriptors$FieldDescriptor, java.lang.Object);
    Code:
       0: aload_0
       1: aload_1
       2: aload_2
       3: invokevirtual #756                // Method setField:(Lcom/google/protobuf/Descriptors$FieldDescriptor;Ljava/lang/Object;)Lio/grpc/xds/shaded/io/envoyproxy/envoy/config/core/v3/GrpcService$GoogleGrpc$Builder;
       6: areturn

  public com.google.protobuf.GeneratedMessageV3$Builder clear();
    Code:
       0: aload_0
       1: invokevirtual #758                // Method clear:()Lio/grpc/xds/shaded/io/envoyproxy/envoy/config/core/v3/GrpcService$GoogleGrpc$Builder;
       4: areturn

  public com.google.protobuf.GeneratedMessageV3$Builder clone();
    Code:
       0: aload_0
       1: invokevirtual #760                // Method clone:()Lio/grpc/xds/shaded/io/envoyproxy/envoy/config/core/v3/GrpcService$GoogleGrpc$Builder;
       4: areturn

  public com.google.protobuf.AbstractMessage$Builder mergeUnknownFields(com.google.protobuf.UnknownFieldSet);
    Code:
       0: aload_0
       1: aload_1
       2: invokevirtual #414                // Method mergeUnknownFields:(Lcom/google/protobuf/UnknownFieldSet;)Lio/grpc/xds/shaded/io/envoyproxy/envoy/config/core/v3/GrpcService$GoogleGrpc$Builder;
       5: areturn

  public com.google.protobuf.AbstractMessage$Builder mergeFrom(com.google.protobuf.CodedInputStream, com.google.protobuf.ExtensionRegistryLite) throws java.io.IOException;
    Code:
       0: aload_0
       1: aload_1
       2: aload_2
       3: invokevirtual #764                // Method mergeFrom:(Lcom/google/protobuf/CodedInputStream;Lcom/google/protobuf/ExtensionRegistryLite;)Lio/grpc/xds/shaded/io/envoyproxy/envoy/config/core/v3/GrpcService$GoogleGrpc$Builder;
       6: areturn

  public com.google.protobuf.AbstractMessage$Builder mergeFrom(com.google.protobuf.Message);
    Code:
       0: aload_0
       1: aload_1
       2: invokevirtual #766                // Method mergeFrom:(Lcom/google/protobuf/Message;)Lio/grpc/xds/shaded/io/envoyproxy/envoy/config/core/v3/GrpcService$GoogleGrpc$Builder;
       5: areturn

  public com.google.protobuf.AbstractMessage$Builder clear();
    Code:
       0: aload_0
       1: invokevirtual #758                // Method clear:()Lio/grpc/xds/shaded/io/envoyproxy/envoy/config/core/v3/GrpcService$GoogleGrpc$Builder;
       4: areturn

  public com.google.protobuf.AbstractMessage$Builder clearOneof(com.google.protobuf.Descriptors$OneofDescriptor);
    Code:
       0: aload_0
       1: aload_1
       2: invokevirtual #752                // Method clearOneof:(Lcom/google/protobuf/Descriptors$OneofDescriptor;)Lio/grpc/xds/shaded/io/envoyproxy/envoy/config/core/v3/GrpcService$GoogleGrpc$Builder;
       5: areturn

  public com.google.protobuf.AbstractMessage$Builder clone();
    Code:
       0: aload_0
       1: invokevirtual #760                // Method clone:()Lio/grpc/xds/shaded/io/envoyproxy/envoy/config/core/v3/GrpcService$GoogleGrpc$Builder;
       4: areturn

  public com.google.protobuf.Message$Builder mergeUnknownFields(com.google.protobuf.UnknownFieldSet);
    Code:
       0: aload_0
       1: aload_1
       2: invokevirtual #414                // Method mergeUnknownFields:(Lcom/google/protobuf/UnknownFieldSet;)Lio/grpc/xds/shaded/io/envoyproxy/envoy/config/core/v3/GrpcService$GoogleGrpc$Builder;
       5: areturn

  public com.google.protobuf.Message$Builder setUnknownFields(com.google.protobuf.UnknownFieldSet);
    Code:
       0: aload_0
       1: aload_1
       2: invokevirtual #746                // Method setUnknownFields:(Lcom/google/protobuf/UnknownFieldSet;)Lio/grpc/xds/shaded/io/envoyproxy/envoy/config/core/v3/GrpcService$GoogleGrpc$Builder;
       5: areturn

  public com.google.protobuf.Message$Builder addRepeatedField(com.google.protobuf.Descriptors$FieldDescriptor, java.lang.Object);
    Code:
       0: aload_0
       1: aload_1
       2: aload_2
       3: invokevirtual #748                // Method addRepeatedField:(Lcom/google/protobuf/Descriptors$FieldDescriptor;Ljava/lang/Object;)Lio/grpc/xds/shaded/io/envoyproxy/envoy/config/core/v3/GrpcService$GoogleGrpc$Builder;
       6: areturn

  public com.google.protobuf.Message$Builder setRepeatedField(com.google.protobuf.Descriptors$FieldDescriptor, int, java.lang.Object);
    Code:
       0: aload_0
       1: aload_1
       2: iload_2
       3: aload_3
       4: invokevirtual #750                // Method setRepeatedField:(Lcom/google/protobuf/Descriptors$FieldDescriptor;ILjava/lang/Object;)Lio/grpc/xds/shaded/io/envoyproxy/envoy/config/core/v3/GrpcService$GoogleGrpc$Builder;
       7: areturn

  public com.google.protobuf.Message$Builder clearOneof(com.google.protobuf.Descriptors$OneofDescriptor);
    Code:
       0: aload_0
       1: aload_1
       2: invokevirtual #752                // Method clearOneof:(Lcom/google/protobuf/Descriptors$OneofDescriptor;)Lio/grpc/xds/shaded/io/envoyproxy/envoy/config/core/v3/GrpcService$GoogleGrpc$Builder;
       5: areturn

  public com.google.protobuf.Message$Builder clearField(com.google.protobuf.Descriptors$FieldDescriptor);
    Code:
       0: aload_0
       1: aload_1
       2: invokevirtual #754                // Method clearField:(Lcom/google/protobuf/Descriptors$FieldDescriptor;)Lio/grpc/xds/shaded/io/envoyproxy/envoy/config/core/v3/GrpcService$GoogleGrpc$Builder;
       5: areturn

  public com.google.protobuf.Message$Builder setField(com.google.protobuf.Descriptors$FieldDescriptor, java.lang.Object);
    Code:
       0: aload_0
       1: aload_1
       2: aload_2
       3: invokevirtual #756                // Method setField:(Lcom/google/protobuf/Descriptors$FieldDescriptor;Ljava/lang/Object;)Lio/grpc/xds/shaded/io/envoyproxy/envoy/config/core/v3/GrpcService$GoogleGrpc$Builder;
       6: areturn

  public com.google.protobuf.Message$Builder mergeFrom(com.google.protobuf.CodedInputStream, com.google.protobuf.ExtensionRegistryLite) throws java.io.IOException;
    Code:
       0: aload_0
       1: aload_1
       2: aload_2
       3: invokevirtual #764                // Method mergeFrom:(Lcom/google/protobuf/CodedInputStream;Lcom/google/protobuf/ExtensionRegistryLite;)Lio/grpc/xds/shaded/io/envoyproxy/envoy/config/core/v3/GrpcService$GoogleGrpc$Builder;
       6: areturn

  public com.google.protobuf.Message$Builder clone();
    Code:
       0: aload_0
       1: invokevirtual #760                // Method clone:()Lio/grpc/xds/shaded/io/envoyproxy/envoy/config/core/v3/GrpcService$GoogleGrpc$Builder;
       4: areturn

  public com.google.protobuf.Message buildPartial();
    Code:
       0: aload_0
       1: invokevirtual #210                // Method buildPartial:()Lio/grpc/xds/shaded/io/envoyproxy/envoy/config/core/v3/GrpcService$GoogleGrpc;
       4: areturn

  public com.google.protobuf.Message build();
    Code:
       0: aload_0
       1: invokevirtual #777                // Method build:()Lio/grpc/xds/shaded/io/envoyproxy/envoy/config/core/v3/GrpcService$GoogleGrpc;
       4: areturn

  public com.google.protobuf.Message$Builder mergeFrom(com.google.protobuf.Message);
    Code:
       0: aload_0
       1: aload_1
       2: invokevirtual #766                // Method mergeFrom:(Lcom/google/protobuf/Message;)Lio/grpc/xds/shaded/io/envoyproxy/envoy/config/core/v3/GrpcService$GoogleGrpc$Builder;
       5: areturn

  public com.google.protobuf.Message$Builder clear();
    Code:
       0: aload_0
       1: invokevirtual #758                // Method clear:()Lio/grpc/xds/shaded/io/envoyproxy/envoy/config/core/v3/GrpcService$GoogleGrpc$Builder;
       4: areturn

  public com.google.protobuf.MessageLite$Builder mergeFrom(com.google.protobuf.CodedInputStream, com.google.protobuf.ExtensionRegistryLite) throws java.io.IOException;
    Code:
       0: aload_0
       1: aload_1
       2: aload_2
       3: invokevirtual #764                // Method mergeFrom:(Lcom/google/protobuf/CodedInputStream;Lcom/google/protobuf/ExtensionRegistryLite;)Lio/grpc/xds/shaded/io/envoyproxy/envoy/config/core/v3/GrpcService$GoogleGrpc$Builder;
       6: areturn

  public com.google.protobuf.MessageLite$Builder clone();
    Code:
       0: aload_0
       1: invokevirtual #760                // Method clone:()Lio/grpc/xds/shaded/io/envoyproxy/envoy/config/core/v3/GrpcService$GoogleGrpc$Builder;
       4: areturn

  public com.google.protobuf.MessageLite buildPartial();
    Code:
       0: aload_0
       1: invokevirtual #210                // Method buildPartial:()Lio/grpc/xds/shaded/io/envoyproxy/envoy/config/core/v3/GrpcService$GoogleGrpc;
       4: areturn

  public com.google.protobuf.MessageLite build();
    Code:
       0: aload_0
       1: invokevirtual #777                // Method build:()Lio/grpc/xds/shaded/io/envoyproxy/envoy/config/core/v3/GrpcService$GoogleGrpc;
       4: areturn

  public com.google.protobuf.MessageLite$Builder clear();
    Code:
       0: aload_0
       1: invokevirtual #758                // Method clear:()Lio/grpc/xds/shaded/io/envoyproxy/envoy/config/core/v3/GrpcService$GoogleGrpc$Builder;
       4: areturn

  public com.google.protobuf.MessageLite getDefaultInstanceForType();
    Code:
       0: aload_0
       1: invokevirtual #782                // Method getDefaultInstanceForType:()Lio/grpc/xds/shaded/io/envoyproxy/envoy/config/core/v3/GrpcService$GoogleGrpc;
       4: areturn

  public com.google.protobuf.Message getDefaultInstanceForType();
    Code:
       0: aload_0
       1: invokevirtual #782                // Method getDefaultInstanceForType:()Lio/grpc/xds/shaded/io/envoyproxy/envoy/config/core/v3/GrpcService$GoogleGrpc;
       4: areturn

  public com.google.protobuf.AbstractMessageLite$Builder mergeFrom(com.google.protobuf.CodedInputStream, com.google.protobuf.ExtensionRegistryLite) throws java.io.IOException;
    Code:
       0: aload_0
       1: aload_1
       2: aload_2
       3: invokevirtual #764                // Method mergeFrom:(Lcom/google/protobuf/CodedInputStream;Lcom/google/protobuf/ExtensionRegistryLite;)Lio/grpc/xds/shaded/io/envoyproxy/envoy/config/core/v3/GrpcService$GoogleGrpc$Builder;
       6: areturn

  public com.google.protobuf.AbstractMessageLite$Builder clone();
    Code:
       0: aload_0
       1: invokevirtual #760                // Method clone:()Lio/grpc/xds/shaded/io/envoyproxy/envoy/config/core/v3/GrpcService$GoogleGrpc$Builder;
       4: areturn

  public java.lang.Object clone() throws java.lang.CloneNotSupportedException;
    Code:
       0: aload_0
       1: invokevirtual #760                // Method clone:()Lio/grpc/xds/shaded/io/envoyproxy/envoy/config/core/v3/GrpcService$GoogleGrpc$Builder;
       4: areturn

  io.grpc.xds.shaded.io.envoyproxy.envoy.config.core.v3.GrpcService$GoogleGrpc$Builder(io.grpc.xds.shaded.io.envoyproxy.envoy.config.core.v3.GrpcService$1);
    Code:
       0: aload_0
       1: invokespecial #789                // Method "<init>":()V
       4: return

  io.grpc.xds.shaded.io.envoyproxy.envoy.config.core.v3.GrpcService$GoogleGrpc$Builder(com.google.protobuf.GeneratedMessageV3$BuilderParent, io.grpc.xds.shaded.io.envoyproxy.envoy.config.core.v3.GrpcService$1);
    Code:
       0: aload_0
       1: aload_1
       2: invokespecial #793                // Method "<init>":(Lcom/google/protobuf/GeneratedMessageV3$BuilderParent;)V
       5: return
}
