Compiled from "Http1ProtocolOptions.java"
public final class io.grpc.xds.shaded.io.envoyproxy.envoy.config.core.v3.Http1ProtocolOptions$Builder extends com.google.protobuf.GeneratedMessageV3$Builder<io.grpc.xds.shaded.io.envoyproxy.envoy.config.core.v3.Http1ProtocolOptions$Builder> implements io.grpc.xds.shaded.io.envoyproxy.envoy.config.core.v3.Http1ProtocolOptionsOrBuilder {
  private com.google.protobuf.BoolValue allowAbsoluteUrl_;

  private com.google.protobuf.SingleFieldBuilderV3<com.google.protobuf.BoolValue, com.google.protobuf.BoolValue$Builder, com.google.protobuf.BoolValueOrBuilder> allowAbsoluteUrlBuilder_;

  private boolean acceptHttp10_;

  private java.lang.Object defaultHostForHttp10_;

  private io.grpc.xds.shaded.io.envoyproxy.envoy.config.core.v3.Http1ProtocolOptions$HeaderKeyFormat headerKeyFormat_;

  private com.google.protobuf.SingleFieldBuilderV3<io.grpc.xds.shaded.io.envoyproxy.envoy.config.core.v3.Http1ProtocolOptions$HeaderKeyFormat, io.grpc.xds.shaded.io.envoyproxy.envoy.config.core.v3.Http1ProtocolOptions$HeaderKeyFormat$Builder, io.grpc.xds.shaded.io.envoyproxy.envoy.config.core.v3.Http1ProtocolOptions$HeaderKeyFormatOrBuilder> headerKeyFormatBuilder_;

  private boolean enableTrailers_;

  private boolean allowChunkedLength_;

  private com.google.protobuf.BoolValue overrideStreamErrorOnInvalidHttpMessage_;

  private com.google.protobuf.SingleFieldBuilderV3<com.google.protobuf.BoolValue, com.google.protobuf.BoolValue$Builder, com.google.protobuf.BoolValueOrBuilder> overrideStreamErrorOnInvalidHttpMessageBuilder_;

  public static final com.google.protobuf.Descriptors$Descriptor getDescriptor();
    Code:
       0: getstatic     #87                 // Field io/grpc/xds/shaded/io/envoyproxy/envoy/config/core/v3/ProtocolProto.internal_static_envoy_config_core_v3_Http1ProtocolOptions_descriptor:Lcom/google/protobuf/Descriptors$Descriptor;
       3: areturn

  protected com.google.protobuf.GeneratedMessageV3$FieldAccessorTable internalGetFieldAccessorTable();
    Code:
       0: getstatic     #93                 // Field io/grpc/xds/shaded/io/envoyproxy/envoy/config/core/v3/ProtocolProto.internal_static_envoy_config_core_v3_Http1ProtocolOptions_fieldAccessorTable:Lcom/google/protobuf/GeneratedMessageV3$FieldAccessorTable;
       3: ldc           #17                 // class io/grpc/xds/shaded/io/envoyproxy/envoy/config/core/v3/Http1ProtocolOptions
       5: ldc           #2                  // class io/grpc/xds/shaded/io/envoyproxy/envoy/config/core/v3/Http1ProtocolOptions$Builder
       7: invokevirtual #97                 // Method com/google/protobuf/GeneratedMessageV3$FieldAccessorTable.ensureFieldAccessorsInitialized:(Ljava/lang/Class;Ljava/lang/Class;)Lcom/google/protobuf/GeneratedMessageV3$FieldAccessorTable;
      10: areturn

  private io.grpc.xds.shaded.io.envoyproxy.envoy.config.core.v3.Http1ProtocolOptions$Builder();
    Code:
       0: aload_0
       1: invokespecial #103                // Method com/google/protobuf/GeneratedMessageV3$Builder."<init>":()V
       4: aload_0
       5: ldc           #105                // String
       7: putfield      #107                // Field defaultHostForHttp10_:Ljava/lang/Object;
      10: aload_0
      11: invokespecial #110                // Method maybeForceBuilderInitialization:()V
      14: return

  private io.grpc.xds.shaded.io.envoyproxy.envoy.config.core.v3.Http1ProtocolOptions$Builder(com.google.protobuf.GeneratedMessageV3$BuilderParent);
    Code:
       0: aload_0
       1: aload_1
       2: invokespecial #113                // Method com/google/protobuf/GeneratedMessageV3$Builder."<init>":(Lcom/google/protobuf/GeneratedMessageV3$BuilderParent;)V
       5: aload_0
       6: ldc           #105                // String
       8: putfield      #107                // Field defaultHostForHttp10_:Ljava/lang/Object;
      11: aload_0
      12: invokespecial #110                // Method maybeForceBuilderInitialization:()V
      15: return

  private void maybeForceBuilderInitialization();
    Code:
       0: invokestatic  #119                // Method io/grpc/xds/shaded/io/envoyproxy/envoy/config/core/v3/Http1ProtocolOptions.access$1800:()Z
       3: ifeq          6
       6: return

  public io.grpc.xds.shaded.io.envoyproxy.envoy.config.core.v3.Http1ProtocolOptions$Builder clear();
    Code:
       0: aload_0
       1: invokespecial #124                // Method com/google/protobuf/GeneratedMessageV3$Builder.clear:()Lcom/google/protobuf/GeneratedMessageV3$Builder;
       4: pop
       5: aload_0
       6: getfield      #126                // Field allowAbsoluteUrlBuilder_:Lcom/google/protobuf/SingleFieldBuilderV3;
       9: ifnonnull     20
      12: aload_0
      13: aconst_null
      14: putfield      #128                // Field allowAbsoluteUrl_:Lcom/google/protobuf/BoolValue;
      17: goto          30
      20: aload_0
      21: aconst_null
      22: putfield      #128                // Field allowAbsoluteUrl_:Lcom/google/protobuf/BoolValue;
      25: aload_0
      26: aconst_null
      27: putfield      #126                // Field allowAbsoluteUrlBuilder_:Lcom/google/protobuf/SingleFieldBuilderV3;
      30: aload_0
      31: iconst_0
      32: putfield      #130                // Field acceptHttp10_:Z
      35: aload_0
      36: ldc           #105                // String
      38: putfield      #107                // Field defaultHostForHttp10_:Ljava/lang/Object;
      41: aload_0
      42: getfield      #132                // Field headerKeyFormatBuilder_:Lcom/google/protobuf/SingleFieldBuilderV3;
      45: ifnonnull     56
      48: aload_0
      49: aconst_null
      50: putfield      #134                // Field headerKeyFormat_:Lio/grpc/xds/shaded/io/envoyproxy/envoy/config/core/v3/Http1ProtocolOptions$HeaderKeyFormat;
      53: goto          66
      56: aload_0
      57: aconst_null
      58: putfield      #134                // Field headerKeyFormat_:Lio/grpc/xds/shaded/io/envoyproxy/envoy/config/core/v3/Http1ProtocolOptions$HeaderKeyFormat;
      61: aload_0
      62: aconst_null
      63: putfield      #132                // Field headerKeyFormatBuilder_:Lcom/google/protobuf/SingleFieldBuilderV3;
      66: aload_0
      67: iconst_0
      68: putfield      #136                // Field enableTrailers_:Z
      71: aload_0
      72: iconst_0
      73: putfield      #138                // Field allowChunkedLength_:Z
      76: aload_0
      77: getfield      #140                // Field overrideStreamErrorOnInvalidHttpMessageBuilder_:Lcom/google/protobuf/SingleFieldBuilderV3;
      80: ifnonnull     91
      83: aload_0
      84: aconst_null
      85: putfield      #142                // Field overrideStreamErrorOnInvalidHttpMessage_:Lcom/google/protobuf/BoolValue;
      88: goto          101
      91: aload_0
      92: aconst_null
      93: putfield      #142                // Field overrideStreamErrorOnInvalidHttpMessage_:Lcom/google/protobuf/BoolValue;
      96: aload_0
      97: aconst_null
      98: putfield      #140                // Field overrideStreamErrorOnInvalidHttpMessageBuilder_:Lcom/google/protobuf/SingleFieldBuilderV3;
     101: aload_0
     102: areturn

  public com.google.protobuf.Descriptors$Descriptor getDescriptorForType();
    Code:
       0: getstatic     #87                 // Field io/grpc/xds/shaded/io/envoyproxy/envoy/config/core/v3/ProtocolProto.internal_static_envoy_config_core_v3_Http1ProtocolOptions_descriptor:Lcom/google/protobuf/Descriptors$Descriptor;
       3: areturn

  public io.grpc.xds.shaded.io.envoyproxy.envoy.config.core.v3.Http1ProtocolOptions getDefaultInstanceForType();
    Code:
       0: invokestatic  #148                // Method io/grpc/xds/shaded/io/envoyproxy/envoy/config/core/v3/Http1ProtocolOptions.getDefaultInstance:()Lio/grpc/xds/shaded/io/envoyproxy/envoy/config/core/v3/Http1ProtocolOptions;
       3: areturn

  public io.grpc.xds.shaded.io.envoyproxy.envoy.config.core.v3.Http1ProtocolOptions build();
    Code:
       0: aload_0
       1: invokevirtual #152                // Method buildPartial:()Lio/grpc/xds/shaded/io/envoyproxy/envoy/config/core/v3/Http1ProtocolOptions;
       4: astore_1
       5: aload_1
       6: invokevirtual #155                // Method io/grpc/xds/shaded/io/envoyproxy/envoy/config/core/v3/Http1ProtocolOptions.isInitialized:()Z
       9: ifne          17
      12: aload_1
      13: invokestatic  #159                // Method newUninitializedMessageException:(Lcom/google/protobuf/Message;)Lcom/google/protobuf/UninitializedMessageException;
      16: athrow
      17: aload_1
      18: areturn

  public io.grpc.xds.shaded.io.envoyproxy.envoy.config.core.v3.Http1ProtocolOptions buildPartial();
    Code:
       0: new           #17                 // class io/grpc/xds/shaded/io/envoyproxy/envoy/config/core/v3/Http1ProtocolOptions
       3: dup
       4: aload_0
       5: aconst_null
       6: invokespecial #164                // Method io/grpc/xds/shaded/io/envoyproxy/envoy/config/core/v3/Http1ProtocolOptions."<init>":(Lcom/google/protobuf/GeneratedMessageV3$Builder;Lio/grpc/xds/shaded/io/envoyproxy/envoy/config/core/v3/Http1ProtocolOptions$1;)V
       9: astore_1
      10: aload_0
      11: getfield      #126                // Field allowAbsoluteUrlBuilder_:Lcom/google/protobuf/SingleFieldBuilderV3;
      14: ifnonnull     29
      17: aload_1
      18: aload_0
      19: getfield      #128                // Field allowAbsoluteUrl_:Lcom/google/protobuf/BoolValue;
      22: invokestatic  #168                // Method io/grpc/xds/shaded/io/envoyproxy/envoy/config/core/v3/Http1ProtocolOptions.access$2002:(Lio/grpc/xds/shaded/io/envoyproxy/envoy/config/core/v3/Http1ProtocolOptions;Lcom/google/protobuf/BoolValue;)Lcom/google/protobuf/BoolValue;
      25: pop
      26: goto          44
      29: aload_1
      30: aload_0
      31: getfield      #126                // Field allowAbsoluteUrlBuilder_:Lcom/google/protobuf/SingleFieldBuilderV3;
      34: invokevirtual #173                // Method com/google/protobuf/SingleFieldBuilderV3.build:()Lcom/google/protobuf/AbstractMessage;
      37: checkcast     #12                 // class com/google/protobuf/BoolValue
      40: invokestatic  #168                // Method io/grpc/xds/shaded/io/envoyproxy/envoy/config/core/v3/Http1ProtocolOptions.access$2002:(Lio/grpc/xds/shaded/io/envoyproxy/envoy/config/core/v3/Http1ProtocolOptions;Lcom/google/protobuf/BoolValue;)Lcom/google/protobuf/BoolValue;
      43: pop
      44: aload_1
      45: aload_0
      46: getfield      #130                // Field acceptHttp10_:Z
      49: invokestatic  #177                // Method io/grpc/xds/shaded/io/envoyproxy/envoy/config/core/v3/Http1ProtocolOptions.access$2102:(Lio/grpc/xds/shaded/io/envoyproxy/envoy/config/core/v3/Http1ProtocolOptions;Z)Z
      52: pop
      53: aload_1
      54: aload_0
      55: getfield      #107                // Field defaultHostForHttp10_:Ljava/lang/Object;
      58: invokestatic  #181                // Method io/grpc/xds/shaded/io/envoyproxy/envoy/config/core/v3/Http1ProtocolOptions.access$2202:(Lio/grpc/xds/shaded/io/envoyproxy/envoy/config/core/v3/Http1ProtocolOptions;Ljava/lang/Object;)Ljava/lang/Object;
      61: pop
      62: aload_0
      63: getfield      #132                // Field headerKeyFormatBuilder_:Lcom/google/protobuf/SingleFieldBuilderV3;
      66: ifnonnull     81
      69: aload_1
      70: aload_0
      71: getfield      #134                // Field headerKeyFormat_:Lio/grpc/xds/shaded/io/envoyproxy/envoy/config/core/v3/Http1ProtocolOptions$HeaderKeyFormat;
      74: invokestatic  #185                // Method io/grpc/xds/shaded/io/envoyproxy/envoy/config/core/v3/Http1ProtocolOptions.access$2302:(Lio/grpc/xds/shaded/io/envoyproxy/envoy/config/core/v3/Http1ProtocolOptions;Lio/grpc/xds/shaded/io/envoyproxy/envoy/config/core/v3/Http1ProtocolOptions$HeaderKeyFormat;)Lio/grpc/xds/shaded/io/envoyproxy/envoy/config/core/v3/Http1ProtocolOptions$HeaderKeyFormat;
      77: pop
      78: goto          96
      81: aload_1
      82: aload_0
      83: getfield      #132                // Field headerKeyFormatBuilder_:Lcom/google/protobuf/SingleFieldBuilderV3;
      86: invokevirtual #173                // Method com/google/protobuf/SingleFieldBuilderV3.build:()Lcom/google/protobuf/AbstractMessage;
      89: checkcast     #15                 // class io/grpc/xds/shaded/io/envoyproxy/envoy/config/core/v3/Http1ProtocolOptions$HeaderKeyFormat
      92: invokestatic  #185                // Method io/grpc/xds/shaded/io/envoyproxy/envoy/config/core/v3/Http1ProtocolOptions.access$2302:(Lio/grpc/xds/shaded/io/envoyproxy/envoy/config/core/v3/Http1ProtocolOptions;Lio/grpc/xds/shaded/io/envoyproxy/envoy/config/core/v3/Http1ProtocolOptions$HeaderKeyFormat;)Lio/grpc/xds/shaded/io/envoyproxy/envoy/config/core/v3/Http1ProtocolOptions$HeaderKeyFormat;
      95: pop
      96: aload_1
      97: aload_0
      98: getfield      #136                // Field enableTrailers_:Z
     101: invokestatic  #188                // Method io/grpc/xds/shaded/io/envoyproxy/envoy/config/core/v3/Http1ProtocolOptions.access$2402:(Lio/grpc/xds/shaded/io/envoyproxy/envoy/config/core/v3/Http1ProtocolOptions;Z)Z
     104: pop
     105: aload_1
     106: aload_0
     107: getfield      #138                // Field allowChunkedLength_:Z
     110: invokestatic  #191                // Method io/grpc/xds/shaded/io/envoyproxy/envoy/config/core/v3/Http1ProtocolOptions.access$2502:(Lio/grpc/xds/shaded/io/envoyproxy/envoy/config/core/v3/Http1ProtocolOptions;Z)Z
     113: pop
     114: aload_0
     115: getfield      #140                // Field overrideStreamErrorOnInvalidHttpMessageBuilder_:Lcom/google/protobuf/SingleFieldBuilderV3;
     118: ifnonnull     133
     121: aload_1
     122: aload_0
     123: getfield      #142                // Field overrideStreamErrorOnInvalidHttpMessage_:Lcom/google/protobuf/BoolValue;
     126: invokestatic  #194                // Method io/grpc/xds/shaded/io/envoyproxy/envoy/config/core/v3/Http1ProtocolOptions.access$2602:(Lio/grpc/xds/shaded/io/envoyproxy/envoy/config/core/v3/Http1ProtocolOptions;Lcom/google/protobuf/BoolValue;)Lcom/google/protobuf/BoolValue;
     129: pop
     130: goto          148
     133: aload_1
     134: aload_0
     135: getfield      #140                // Field overrideStreamErrorOnInvalidHttpMessageBuilder_:Lcom/google/protobuf/SingleFieldBuilderV3;
     138: invokevirtual #173                // Method com/google/protobuf/SingleFieldBuilderV3.build:()Lcom/google/protobuf/AbstractMessage;
     141: checkcast     #12                 // class com/google/protobuf/BoolValue
     144: invokestatic  #194                // Method io/grpc/xds/shaded/io/envoyproxy/envoy/config/core/v3/Http1ProtocolOptions.access$2602:(Lio/grpc/xds/shaded/io/envoyproxy/envoy/config/core/v3/Http1ProtocolOptions;Lcom/google/protobuf/BoolValue;)Lcom/google/protobuf/BoolValue;
     147: pop
     148: aload_0
     149: invokevirtual #197                // Method onBuilt:()V
     152: aload_1
     153: areturn

  public io.grpc.xds.shaded.io.envoyproxy.envoy.config.core.v3.Http1ProtocolOptions$Builder clone();
    Code:
       0: aload_0
       1: invokespecial #200                // Method com/google/protobuf/GeneratedMessageV3$Builder.clone:()Lcom/google/protobuf/GeneratedMessageV3$Builder;
       4: checkcast     #2                  // class io/grpc/xds/shaded/io/envoyproxy/envoy/config/core/v3/Http1ProtocolOptions$Builder
       7: areturn

  public io.grpc.xds.shaded.io.envoyproxy.envoy.config.core.v3.Http1ProtocolOptions$Builder setField(com.google.protobuf.Descriptors$FieldDescriptor, java.lang.Object);
    Code:
       0: aload_0
       1: aload_1
       2: aload_2
       3: invokespecial #205                // Method com/google/protobuf/GeneratedMessageV3$Builder.setField:(Lcom/google/protobuf/Descriptors$FieldDescriptor;Ljava/lang/Object;)Lcom/google/protobuf/GeneratedMessageV3$Builder;
       6: checkcast     #2                  // class io/grpc/xds/shaded/io/envoyproxy/envoy/config/core/v3/Http1ProtocolOptions$Builder
       9: areturn

  public io.grpc.xds.shaded.io.envoyproxy.envoy.config.core.v3.Http1ProtocolOptions$Builder clearField(com.google.protobuf.Descriptors$FieldDescriptor);
    Code:
       0: aload_0
       1: aload_1
       2: invokespecial #213                // Method com/google/protobuf/GeneratedMessageV3$Builder.clearField:(Lcom/google/protobuf/Descriptors$FieldDescriptor;)Lcom/google/protobuf/GeneratedMessageV3$Builder;
       5: checkcast     #2                  // class io/grpc/xds/shaded/io/envoyproxy/envoy/config/core/v3/Http1ProtocolOptions$Builder
       8: areturn

  public io.grpc.xds.shaded.io.envoyproxy.envoy.config.core.v3.Http1ProtocolOptions$Builder clearOneof(com.google.protobuf.Descriptors$OneofDescriptor);
    Code:
       0: aload_0
       1: aload_1
       2: invokespecial #218                // Method com/google/protobuf/GeneratedMessageV3$Builder.clearOneof:(Lcom/google/protobuf/Descriptors$OneofDescriptor;)Lcom/google/protobuf/GeneratedMessageV3$Builder;
       5: checkcast     #2                  // class io/grpc/xds/shaded/io/envoyproxy/envoy/config/core/v3/Http1ProtocolOptions$Builder
       8: areturn

  public io.grpc.xds.shaded.io.envoyproxy.envoy.config.core.v3.Http1ProtocolOptions$Builder setRepeatedField(com.google.protobuf.Descriptors$FieldDescriptor, int, java.lang.Object);
    Code:
       0: aload_0
       1: aload_1
       2: iload_2
       3: aload_3
       4: invokespecial #225                // Method com/google/protobuf/GeneratedMessageV3$Builder.setRepeatedField:(Lcom/google/protobuf/Descriptors$FieldDescriptor;ILjava/lang/Object;)Lcom/google/protobuf/GeneratedMessageV3$Builder;
       7: checkcast     #2                  // class io/grpc/xds/shaded/io/envoyproxy/envoy/config/core/v3/Http1ProtocolOptions$Builder
      10: areturn

  public io.grpc.xds.shaded.io.envoyproxy.envoy.config.core.v3.Http1ProtocolOptions$Builder addRepeatedField(com.google.protobuf.Descriptors$FieldDescriptor, java.lang.Object);
    Code:
       0: aload_0
       1: aload_1
       2: aload_2
       3: invokespecial #230                // Method com/google/protobuf/GeneratedMessageV3$Builder.addRepeatedField:(Lcom/google/protobuf/Descriptors$FieldDescriptor;Ljava/lang/Object;)Lcom/google/protobuf/GeneratedMessageV3$Builder;
       6: checkcast     #2                  // class io/grpc/xds/shaded/io/envoyproxy/envoy/config/core/v3/Http1ProtocolOptions$Builder
       9: areturn

  public io.grpc.xds.shaded.io.envoyproxy.envoy.config.core.v3.Http1ProtocolOptions$Builder mergeFrom(com.google.protobuf.Message);
    Code:
       0: aload_1
       1: instanceof    #17                 // class io/grpc/xds/shaded/io/envoyproxy/envoy/config/core/v3/Http1ProtocolOptions
       4: ifeq          16
       7: aload_0
       8: aload_1
       9: checkcast     #17                 // class io/grpc/xds/shaded/io/envoyproxy/envoy/config/core/v3/Http1ProtocolOptions
      12: invokevirtual #235                // Method mergeFrom:(Lio/grpc/xds/shaded/io/envoyproxy/envoy/config/core/v3/Http1ProtocolOptions;)Lio/grpc/xds/shaded/io/envoyproxy/envoy/config/core/v3/Http1ProtocolOptions$Builder;
      15: areturn
      16: aload_0
      17: aload_1
      18: invokespecial #238                // Method com/google/protobuf/GeneratedMessageV3$Builder.mergeFrom:(Lcom/google/protobuf/Message;)Lcom/google/protobuf/AbstractMessage$Builder;
      21: pop
      22: aload_0
      23: areturn

  public io.grpc.xds.shaded.io.envoyproxy.envoy.config.core.v3.Http1ProtocolOptions$Builder mergeFrom(io.grpc.xds.shaded.io.envoyproxy.envoy.config.core.v3.Http1ProtocolOptions);
    Code:
       0: aload_1
       1: invokestatic  #148                // Method io/grpc/xds/shaded/io/envoyproxy/envoy/config/core/v3/Http1ProtocolOptions.getDefaultInstance:()Lio/grpc/xds/shaded/io/envoyproxy/envoy/config/core/v3/Http1ProtocolOptions;
       4: if_acmpne     9
       7: aload_0
       8: areturn
       9: aload_1
      10: invokevirtual #243                // Method io/grpc/xds/shaded/io/envoyproxy/envoy/config/core/v3/Http1ProtocolOptions.hasAllowAbsoluteUrl:()Z
      13: ifeq          25
      16: aload_0
      17: aload_1
      18: invokevirtual #247                // Method io/grpc/xds/shaded/io/envoyproxy/envoy/config/core/v3/Http1ProtocolOptions.getAllowAbsoluteUrl:()Lcom/google/protobuf/BoolValue;
      21: invokevirtual #251                // Method mergeAllowAbsoluteUrl:(Lcom/google/protobuf/BoolValue;)Lio/grpc/xds/shaded/io/envoyproxy/envoy/config/core/v3/Http1ProtocolOptions$Builder;
      24: pop
      25: aload_1
      26: invokevirtual #254                // Method io/grpc/xds/shaded/io/envoyproxy/envoy/config/core/v3/Http1ProtocolOptions.getAcceptHttp10:()Z
      29: ifeq          41
      32: aload_0
      33: aload_1
      34: invokevirtual #254                // Method io/grpc/xds/shaded/io/envoyproxy/envoy/config/core/v3/Http1ProtocolOptions.getAcceptHttp10:()Z
      37: invokevirtual #258                // Method setAcceptHttp10:(Z)Lio/grpc/xds/shaded/io/envoyproxy/envoy/config/core/v3/Http1ProtocolOptions$Builder;
      40: pop
      41: aload_1
      42: invokevirtual #262                // Method io/grpc/xds/shaded/io/envoyproxy/envoy/config/core/v3/Http1ProtocolOptions.getDefaultHostForHttp10:()Ljava/lang/String;
      45: invokevirtual #267                // Method java/lang/String.isEmpty:()Z
      48: ifne          63
      51: aload_0
      52: aload_1
      53: invokestatic  #271                // Method io/grpc/xds/shaded/io/envoyproxy/envoy/config/core/v3/Http1ProtocolOptions.access$2200:(Lio/grpc/xds/shaded/io/envoyproxy/envoy/config/core/v3/Http1ProtocolOptions;)Ljava/lang/Object;
      56: putfield      #107                // Field defaultHostForHttp10_:Ljava/lang/Object;
      59: aload_0
      60: invokevirtual #274                // Method onChanged:()V
      63: aload_1
      64: invokevirtual #277                // Method io/grpc/xds/shaded/io/envoyproxy/envoy/config/core/v3/Http1ProtocolOptions.hasHeaderKeyFormat:()Z
      67: ifeq          79
      70: aload_0
      71: aload_1
      72: invokevirtual #281                // Method io/grpc/xds/shaded/io/envoyproxy/envoy/config/core/v3/Http1ProtocolOptions.getHeaderKeyFormat:()Lio/grpc/xds/shaded/io/envoyproxy/envoy/config/core/v3/Http1ProtocolOptions$HeaderKeyFormat;
      75: invokevirtual #285                // Method mergeHeaderKeyFormat:(Lio/grpc/xds/shaded/io/envoyproxy/envoy/config/core/v3/Http1ProtocolOptions$HeaderKeyFormat;)Lio/grpc/xds/shaded/io/envoyproxy/envoy/config/core/v3/Http1ProtocolOptions$Builder;
      78: pop
      79: aload_1
      80: invokevirtual #288                // Method io/grpc/xds/shaded/io/envoyproxy/envoy/config/core/v3/Http1ProtocolOptions.getEnableTrailers:()Z
      83: ifeq          95
      86: aload_0
      87: aload_1
      88: invokevirtual #288                // Method io/grpc/xds/shaded/io/envoyproxy/envoy/config/core/v3/Http1ProtocolOptions.getEnableTrailers:()Z
      91: invokevirtual #291                // Method setEnableTrailers:(Z)Lio/grpc/xds/shaded/io/envoyproxy/envoy/config/core/v3/Http1ProtocolOptions$Builder;
      94: pop
      95: aload_1
      96: invokevirtual #294                // Method io/grpc/xds/shaded/io/envoyproxy/envoy/config/core/v3/Http1ProtocolOptions.getAllowChunkedLength:()Z
      99: ifeq          111
     102: aload_0
     103: aload_1
     104: invokevirtual #294                // Method io/grpc/xds/shaded/io/envoyproxy/envoy/config/core/v3/Http1ProtocolOptions.getAllowChunkedLength:()Z
     107: invokevirtual #297                // Method setAllowChunkedLength:(Z)Lio/grpc/xds/shaded/io/envoyproxy/envoy/config/core/v3/Http1ProtocolOptions$Builder;
     110: pop
     111: aload_1
     112: invokevirtual #300                // Method io/grpc/xds/shaded/io/envoyproxy/envoy/config/core/v3/Http1ProtocolOptions.hasOverrideStreamErrorOnInvalidHttpMessage:()Z
     115: ifeq          127
     118: aload_0
     119: aload_1
     120: invokevirtual #303                // Method io/grpc/xds/shaded/io/envoyproxy/envoy/config/core/v3/Http1ProtocolOptions.getOverrideStreamErrorOnInvalidHttpMessage:()Lcom/google/protobuf/BoolValue;
     123: invokevirtual #306                // Method mergeOverrideStreamErrorOnInvalidHttpMessage:(Lcom/google/protobuf/BoolValue;)Lio/grpc/xds/shaded/io/envoyproxy/envoy/config/core/v3/Http1ProtocolOptions$Builder;
     126: pop
     127: aload_0
     128: aload_1
     129: invokestatic  #310                // Method io/grpc/xds/shaded/io/envoyproxy/envoy/config/core/v3/Http1ProtocolOptions.access$2700:(Lio/grpc/xds/shaded/io/envoyproxy/envoy/config/core/v3/Http1ProtocolOptions;)Lcom/google/protobuf/UnknownFieldSet;
     132: invokevirtual #314                // Method mergeUnknownFields:(Lcom/google/protobuf/UnknownFieldSet;)Lio/grpc/xds/shaded/io/envoyproxy/envoy/config/core/v3/Http1ProtocolOptions$Builder;
     135: pop
     136: aload_0
     137: invokevirtual #274                // Method onChanged:()V
     140: aload_0
     141: areturn

  public final boolean isInitialized();
    Code:
       0: iconst_1
       1: ireturn

  public io.grpc.xds.shaded.io.envoyproxy.envoy.config.core.v3.Http1ProtocolOptions$Builder mergeFrom(com.google.protobuf.CodedInputStream, com.google.protobuf.ExtensionRegistryLite) throws java.io.IOException;
    Code:
       0: aconst_null
       1: astore_3
       2: invokestatic  #323                // Method io/grpc/xds/shaded/io/envoyproxy/envoy/config/core/v3/Http1ProtocolOptions.access$2800:()Lcom/google/protobuf/Parser;
       5: aload_1
       6: aload_2
       7: invokeinterface #329,  3          // InterfaceMethod com/google/protobuf/Parser.parsePartialFrom:(Lcom/google/protobuf/CodedInputStream;Lcom/google/protobuf/ExtensionRegistryLite;)Ljava/lang/Object;
      12: checkcast     #17                 // class io/grpc/xds/shaded/io/envoyproxy/envoy/config/core/v3/Http1ProtocolOptions
      15: astore_3
      16: aload_3
      17: ifnull        61
      20: aload_0
      21: aload_3
      22: invokevirtual #235                // Method mergeFrom:(Lio/grpc/xds/shaded/io/envoyproxy/envoy/config/core/v3/Http1ProtocolOptions;)Lio/grpc/xds/shaded/io/envoyproxy/envoy/config/core/v3/Http1ProtocolOptions$Builder;
      25: pop
      26: goto          61
      29: astore        4
      31: aload         4
      33: invokevirtual #337                // Method com/google/protobuf/InvalidProtocolBufferException.getUnfinishedMessage:()Lcom/google/protobuf/MessageLite;
      36: checkcast     #17                 // class io/grpc/xds/shaded/io/envoyproxy/envoy/config/core/v3/Http1ProtocolOptions
      39: astore_3
      40: aload         4
      42: invokevirtual #341                // Method com/google/protobuf/InvalidProtocolBufferException.unwrapIOException:()Ljava/io/IOException;
      45: athrow
      46: astore        5
      48: aload_3
      49: ifnull        58
      52: aload_0
      53: aload_3
      54: invokevirtual #235                // Method mergeFrom:(Lio/grpc/xds/shaded/io/envoyproxy/envoy/config/core/v3/Http1ProtocolOptions;)Lio/grpc/xds/shaded/io/envoyproxy/envoy/config/core/v3/Http1ProtocolOptions$Builder;
      57: pop
      58: aload         5
      60: athrow
      61: aload_0
      62: areturn
    Exception table:
       from    to  target type
           2    16    29   Class com/google/protobuf/InvalidProtocolBufferException
           2    16    46   any
          29    48    46   any

  public boolean hasAllowAbsoluteUrl();
    Code:
       0: aload_0
       1: getfield      #126                // Field allowAbsoluteUrlBuilder_:Lcom/google/protobuf/SingleFieldBuilderV3;
       4: ifnonnull     14
       7: aload_0
       8: getfield      #128                // Field allowAbsoluteUrl_:Lcom/google/protobuf/BoolValue;
      11: ifnull        18
      14: iconst_1
      15: goto          19
      18: iconst_0
      19: ireturn

  public com.google.protobuf.BoolValue getAllowAbsoluteUrl();
    Code:
       0: aload_0
       1: getfield      #126                // Field allowAbsoluteUrlBuilder_:Lcom/google/protobuf/SingleFieldBuilderV3;
       4: ifnonnull     25
       7: aload_0
       8: getfield      #128                // Field allowAbsoluteUrl_:Lcom/google/protobuf/BoolValue;
      11: ifnonnull     20
      14: invokestatic  #352                // Method com/google/protobuf/BoolValue.getDefaultInstance:()Lcom/google/protobuf/BoolValue;
      17: goto          24
      20: aload_0
      21: getfield      #128                // Field allowAbsoluteUrl_:Lcom/google/protobuf/BoolValue;
      24: areturn
      25: aload_0
      26: getfield      #126                // Field allowAbsoluteUrlBuilder_:Lcom/google/protobuf/SingleFieldBuilderV3;
      29: invokevirtual #355                // Method com/google/protobuf/SingleFieldBuilderV3.getMessage:()Lcom/google/protobuf/AbstractMessage;
      32: checkcast     #12                 // class com/google/protobuf/BoolValue
      35: areturn

  public io.grpc.xds.shaded.io.envoyproxy.envoy.config.core.v3.Http1ProtocolOptions$Builder setAllowAbsoluteUrl(com.google.protobuf.BoolValue);
    Code:
       0: aload_0
       1: getfield      #126                // Field allowAbsoluteUrlBuilder_:Lcom/google/protobuf/SingleFieldBuilderV3;
       4: ifnonnull     31
       7: aload_1
       8: ifnonnull     19
      11: new           #358                // class java/lang/NullPointerException
      14: dup
      15: invokespecial #359                // Method java/lang/NullPointerException."<init>":()V
      18: athrow
      19: aload_0
      20: aload_1
      21: putfield      #128                // Field allowAbsoluteUrl_:Lcom/google/protobuf/BoolValue;
      24: aload_0
      25: invokevirtual #274                // Method onChanged:()V
      28: goto          40
      31: aload_0
      32: getfield      #126                // Field allowAbsoluteUrlBuilder_:Lcom/google/protobuf/SingleFieldBuilderV3;
      35: aload_1
      36: invokevirtual #363                // Method com/google/protobuf/SingleFieldBuilderV3.setMessage:(Lcom/google/protobuf/AbstractMessage;)Lcom/google/protobuf/SingleFieldBuilderV3;
      39: pop
      40: aload_0
      41: areturn

  public io.grpc.xds.shaded.io.envoyproxy.envoy.config.core.v3.Http1ProtocolOptions$Builder setAllowAbsoluteUrl(com.google.protobuf.BoolValue$Builder);
    Code:
       0: aload_0
       1: getfield      #126                // Field allowAbsoluteUrlBuilder_:Lcom/google/protobuf/SingleFieldBuilderV3;
       4: ifnonnull     22
       7: aload_0
       8: aload_1
       9: invokevirtual #366                // Method com/google/protobuf/BoolValue$Builder.build:()Lcom/google/protobuf/BoolValue;
      12: putfield      #128                // Field allowAbsoluteUrl_:Lcom/google/protobuf/BoolValue;
      15: aload_0
      16: invokevirtual #274                // Method onChanged:()V
      19: goto          34
      22: aload_0
      23: getfield      #126                // Field allowAbsoluteUrlBuilder_:Lcom/google/protobuf/SingleFieldBuilderV3;
      26: aload_1
      27: invokevirtual #366                // Method com/google/protobuf/BoolValue$Builder.build:()Lcom/google/protobuf/BoolValue;
      30: invokevirtual #363                // Method com/google/protobuf/SingleFieldBuilderV3.setMessage:(Lcom/google/protobuf/AbstractMessage;)Lcom/google/protobuf/SingleFieldBuilderV3;
      33: pop
      34: aload_0
      35: areturn

  public io.grpc.xds.shaded.io.envoyproxy.envoy.config.core.v3.Http1ProtocolOptions$Builder mergeAllowAbsoluteUrl(com.google.protobuf.BoolValue);
    Code:
       0: aload_0
       1: getfield      #126                // Field allowAbsoluteUrlBuilder_:Lcom/google/protobuf/SingleFieldBuilderV3;
       4: ifnonnull     47
       7: aload_0
       8: getfield      #128                // Field allowAbsoluteUrl_:Lcom/google/protobuf/BoolValue;
      11: ifnull        35
      14: aload_0
      15: aload_0
      16: getfield      #128                // Field allowAbsoluteUrl_:Lcom/google/protobuf/BoolValue;
      19: invokestatic  #372                // Method com/google/protobuf/BoolValue.newBuilder:(Lcom/google/protobuf/BoolValue;)Lcom/google/protobuf/BoolValue$Builder;
      22: aload_1
      23: invokevirtual #374                // Method com/google/protobuf/BoolValue$Builder.mergeFrom:(Lcom/google/protobuf/BoolValue;)Lcom/google/protobuf/BoolValue$Builder;
      26: invokevirtual #376                // Method com/google/protobuf/BoolValue$Builder.buildPartial:()Lcom/google/protobuf/BoolValue;
      29: putfield      #128                // Field allowAbsoluteUrl_:Lcom/google/protobuf/BoolValue;
      32: goto          40
      35: aload_0
      36: aload_1
      37: putfield      #128                // Field allowAbsoluteUrl_:Lcom/google/protobuf/BoolValue;
      40: aload_0
      41: invokevirtual #274                // Method onChanged:()V
      44: goto          56
      47: aload_0
      48: getfield      #126                // Field allowAbsoluteUrlBuilder_:Lcom/google/protobuf/SingleFieldBuilderV3;
      51: aload_1
      52: invokevirtual #378                // Method com/google/protobuf/SingleFieldBuilderV3.mergeFrom:(Lcom/google/protobuf/AbstractMessage;)Lcom/google/protobuf/SingleFieldBuilderV3;
      55: pop
      56: aload_0
      57: areturn

  public io.grpc.xds.shaded.io.envoyproxy.envoy.config.core.v3.Http1ProtocolOptions$Builder clearAllowAbsoluteUrl();
    Code:
       0: aload_0
       1: getfield      #126                // Field allowAbsoluteUrlBuilder_:Lcom/google/protobuf/SingleFieldBuilderV3;
       4: ifnonnull     19
       7: aload_0
       8: aconst_null
       9: putfield      #128                // Field allowAbsoluteUrl_:Lcom/google/protobuf/BoolValue;
      12: aload_0
      13: invokevirtual #274                // Method onChanged:()V
      16: goto          29
      19: aload_0
      20: aconst_null
      21: putfield      #128                // Field allowAbsoluteUrl_:Lcom/google/protobuf/BoolValue;
      24: aload_0
      25: aconst_null
      26: putfield      #126                // Field allowAbsoluteUrlBuilder_:Lcom/google/protobuf/SingleFieldBuilderV3;
      29: aload_0
      30: areturn

  public com.google.protobuf.BoolValue$Builder getAllowAbsoluteUrlBuilder();
    Code:
       0: aload_0
       1: invokevirtual #274                // Method onChanged:()V
       4: aload_0
       5: invokespecial #385                // Method getAllowAbsoluteUrlFieldBuilder:()Lcom/google/protobuf/SingleFieldBuilderV3;
       8: invokevirtual #389                // Method com/google/protobuf/SingleFieldBuilderV3.getBuilder:()Lcom/google/protobuf/AbstractMessage$Builder;
      11: checkcast     #10                 // class com/google/protobuf/BoolValue$Builder
      14: areturn

  public com.google.protobuf.BoolValueOrBuilder getAllowAbsoluteUrlOrBuilder();
    Code:
       0: aload_0
       1: getfield      #126                // Field allowAbsoluteUrlBuilder_:Lcom/google/protobuf/SingleFieldBuilderV3;
       4: ifnull        18
       7: aload_0
       8: getfield      #126                // Field allowAbsoluteUrlBuilder_:Lcom/google/protobuf/SingleFieldBuilderV3;
      11: invokevirtual #395                // Method com/google/protobuf/SingleFieldBuilderV3.getMessageOrBuilder:()Lcom/google/protobuf/MessageOrBuilder;
      14: checkcast     #397                // class com/google/protobuf/BoolValueOrBuilder
      17: areturn
      18: aload_0
      19: getfield      #128                // Field allowAbsoluteUrl_:Lcom/google/protobuf/BoolValue;
      22: ifnonnull     31
      25: invokestatic  #352                // Method com/google/protobuf/BoolValue.getDefaultInstance:()Lcom/google/protobuf/BoolValue;
      28: goto          35
      31: aload_0
      32: getfield      #128                // Field allowAbsoluteUrl_:Lcom/google/protobuf/BoolValue;
      35: areturn

  private com.google.protobuf.SingleFieldBuilderV3<com.google.protobuf.BoolValue, com.google.protobuf.BoolValue$Builder, com.google.protobuf.BoolValueOrBuilder> getAllowAbsoluteUrlFieldBuilder();
    Code:
       0: aload_0
       1: getfield      #126                // Field allowAbsoluteUrlBuilder_:Lcom/google/protobuf/SingleFieldBuilderV3;
       4: ifnonnull     35
       7: aload_0
       8: new           #170                // class com/google/protobuf/SingleFieldBuilderV3
      11: dup
      12: aload_0
      13: invokevirtual #399                // Method getAllowAbsoluteUrl:()Lcom/google/protobuf/BoolValue;
      16: aload_0
      17: invokevirtual #403                // Method getParentForChildren:()Lcom/google/protobuf/GeneratedMessageV3$BuilderParent;
      20: aload_0
      21: invokevirtual #406                // Method isClean:()Z
      24: invokespecial #409                // Method com/google/protobuf/SingleFieldBuilderV3."<init>":(Lcom/google/protobuf/AbstractMessage;Lcom/google/protobuf/AbstractMessage$BuilderParent;Z)V
      27: putfield      #126                // Field allowAbsoluteUrlBuilder_:Lcom/google/protobuf/SingleFieldBuilderV3;
      30: aload_0
      31: aconst_null
      32: putfield      #128                // Field allowAbsoluteUrl_:Lcom/google/protobuf/BoolValue;
      35: aload_0
      36: getfield      #126                // Field allowAbsoluteUrlBuilder_:Lcom/google/protobuf/SingleFieldBuilderV3;
      39: areturn

  public boolean getAcceptHttp10();
    Code:
       0: aload_0
       1: getfield      #130                // Field acceptHttp10_:Z
       4: ireturn

  public io.grpc.xds.shaded.io.envoyproxy.envoy.config.core.v3.Http1ProtocolOptions$Builder setAcceptHttp10(boolean);
    Code:
       0: aload_0
       1: iload_1
       2: putfield      #130                // Field acceptHttp10_:Z
       5: aload_0
       6: invokevirtual #274                // Method onChanged:()V
       9: aload_0
      10: areturn

  public io.grpc.xds.shaded.io.envoyproxy.envoy.config.core.v3.Http1ProtocolOptions$Builder clearAcceptHttp10();
    Code:
       0: aload_0
       1: iconst_0
       2: putfield      #130                // Field acceptHttp10_:Z
       5: aload_0
       6: invokevirtual #274                // Method onChanged:()V
       9: aload_0
      10: areturn

  public java.lang.String getDefaultHostForHttp10();
    Code:
       0: aload_0
       1: getfield      #107                // Field defaultHostForHttp10_:Ljava/lang/Object;
       4: astore_1
       5: aload_1
       6: instanceof    #264                // class java/lang/String
       9: ifne          29
      12: aload_1
      13: checkcast     #412                // class com/google/protobuf/ByteString
      16: astore_2
      17: aload_2
      18: invokevirtual #415                // Method com/google/protobuf/ByteString.toStringUtf8:()Ljava/lang/String;
      21: astore_3
      22: aload_0
      23: aload_3
      24: putfield      #107                // Field defaultHostForHttp10_:Ljava/lang/Object;
      27: aload_3
      28: areturn
      29: aload_1
      30: checkcast     #264                // class java/lang/String
      33: areturn

  public com.google.protobuf.ByteString getDefaultHostForHttp10Bytes();
    Code:
       0: aload_0
       1: getfield      #107                // Field defaultHostForHttp10_:Ljava/lang/Object;
       4: astore_1
       5: aload_1
       6: instanceof    #264                // class java/lang/String
       9: ifeq          27
      12: aload_1
      13: checkcast     #264                // class java/lang/String
      16: invokestatic  #428                // Method com/google/protobuf/ByteString.copyFromUtf8:(Ljava/lang/String;)Lcom/google/protobuf/ByteString;
      19: astore_2
      20: aload_0
      21: aload_2
      22: putfield      #107                // Field defaultHostForHttp10_:Ljava/lang/Object;
      25: aload_2
      26: areturn
      27: aload_1
      28: checkcast     #412                // class com/google/protobuf/ByteString
      31: areturn

  public io.grpc.xds.shaded.io.envoyproxy.envoy.config.core.v3.Http1ProtocolOptions$Builder setDefaultHostForHttp10(java.lang.String);
    Code:
       0: aload_1
       1: ifnonnull     12
       4: new           #358                // class java/lang/NullPointerException
       7: dup
       8: invokespecial #359                // Method java/lang/NullPointerException."<init>":()V
      11: athrow
      12: aload_0
      13: aload_1
      14: putfield      #107                // Field defaultHostForHttp10_:Ljava/lang/Object;
      17: aload_0
      18: invokevirtual #274                // Method onChanged:()V
      21: aload_0
      22: areturn

  public io.grpc.xds.shaded.io.envoyproxy.envoy.config.core.v3.Http1ProtocolOptions$Builder clearDefaultHostForHttp10();
    Code:
       0: aload_0
       1: invokestatic  #148                // Method io/grpc/xds/shaded/io/envoyproxy/envoy/config/core/v3/Http1ProtocolOptions.getDefaultInstance:()Lio/grpc/xds/shaded/io/envoyproxy/envoy/config/core/v3/Http1ProtocolOptions;
       4: invokevirtual #262                // Method io/grpc/xds/shaded/io/envoyproxy/envoy/config/core/v3/Http1ProtocolOptions.getDefaultHostForHttp10:()Ljava/lang/String;
       7: putfield      #107                // Field defaultHostForHttp10_:Ljava/lang/Object;
      10: aload_0
      11: invokevirtual #274                // Method onChanged:()V
      14: aload_0
      15: areturn

  public io.grpc.xds.shaded.io.envoyproxy.envoy.config.core.v3.Http1ProtocolOptions$Builder setDefaultHostForHttp10Bytes(com.google.protobuf.ByteString);
    Code:
       0: aload_1
       1: ifnonnull     12
       4: new           #358                // class java/lang/NullPointerException
       7: dup
       8: invokespecial #359                // Method java/lang/NullPointerException."<init>":()V
      11: athrow
      12: aload_1
      13: invokestatic  #438                // Method io/grpc/xds/shaded/io/envoyproxy/envoy/config/core/v3/Http1ProtocolOptions.access$2900:(Lcom/google/protobuf/ByteString;)V
      16: aload_0
      17: aload_1
      18: putfield      #107                // Field defaultHostForHttp10_:Ljava/lang/Object;
      21: aload_0
      22: invokevirtual #274                // Method onChanged:()V
      25: aload_0
      26: areturn

  public boolean hasHeaderKeyFormat();
    Code:
       0: aload_0
       1: getfield      #132                // Field headerKeyFormatBuilder_:Lcom/google/protobuf/SingleFieldBuilderV3;
       4: ifnonnull     14
       7: aload_0
       8: getfield      #134                // Field headerKeyFormat_:Lio/grpc/xds/shaded/io/envoyproxy/envoy/config/core/v3/Http1ProtocolOptions$HeaderKeyFormat;
      11: ifnull        18
      14: iconst_1
      15: goto          19
      18: iconst_0
      19: ireturn

  public io.grpc.xds.shaded.io.envoyproxy.envoy.config.core.v3.Http1ProtocolOptions$HeaderKeyFormat getHeaderKeyFormat();
    Code:
       0: aload_0
       1: getfield      #132                // Field headerKeyFormatBuilder_:Lcom/google/protobuf/SingleFieldBuilderV3;
       4: ifnonnull     25
       7: aload_0
       8: getfield      #134                // Field headerKeyFormat_:Lio/grpc/xds/shaded/io/envoyproxy/envoy/config/core/v3/Http1ProtocolOptions$HeaderKeyFormat;
      11: ifnonnull     20
      14: invokestatic  #440                // Method io/grpc/xds/shaded/io/envoyproxy/envoy/config/core/v3/Http1ProtocolOptions$HeaderKeyFormat.getDefaultInstance:()Lio/grpc/xds/shaded/io/envoyproxy/envoy/config/core/v3/Http1ProtocolOptions$HeaderKeyFormat;
      17: goto          24
      20: aload_0
      21: getfield      #134                // Field headerKeyFormat_:Lio/grpc/xds/shaded/io/envoyproxy/envoy/config/core/v3/Http1ProtocolOptions$HeaderKeyFormat;
      24: areturn
      25: aload_0
      26: getfield      #132                // Field headerKeyFormatBuilder_:Lcom/google/protobuf/SingleFieldBuilderV3;
      29: invokevirtual #355                // Method com/google/protobuf/SingleFieldBuilderV3.getMessage:()Lcom/google/protobuf/AbstractMessage;
      32: checkcast     #15                 // class io/grpc/xds/shaded/io/envoyproxy/envoy/config/core/v3/Http1ProtocolOptions$HeaderKeyFormat
      35: areturn

  public io.grpc.xds.shaded.io.envoyproxy.envoy.config.core.v3.Http1ProtocolOptions$Builder setHeaderKeyFormat(io.grpc.xds.shaded.io.envoyproxy.envoy.config.core.v3.Http1ProtocolOptions$HeaderKeyFormat);
    Code:
       0: aload_0
       1: getfield      #132                // Field headerKeyFormatBuilder_:Lcom/google/protobuf/SingleFieldBuilderV3;
       4: ifnonnull     31
       7: aload_1
       8: ifnonnull     19
      11: new           #358                // class java/lang/NullPointerException
      14: dup
      15: invokespecial #359                // Method java/lang/NullPointerException."<init>":()V
      18: athrow
      19: aload_0
      20: aload_1
      21: putfield      #134                // Field headerKeyFormat_:Lio/grpc/xds/shaded/io/envoyproxy/envoy/config/core/v3/Http1ProtocolOptions$HeaderKeyFormat;
      24: aload_0
      25: invokevirtual #274                // Method onChanged:()V
      28: goto          40
      31: aload_0
      32: getfield      #132                // Field headerKeyFormatBuilder_:Lcom/google/protobuf/SingleFieldBuilderV3;
      35: aload_1
      36: invokevirtual #363                // Method com/google/protobuf/SingleFieldBuilderV3.setMessage:(Lcom/google/protobuf/AbstractMessage;)Lcom/google/protobuf/SingleFieldBuilderV3;
      39: pop
      40: aload_0
      41: areturn

  public io.grpc.xds.shaded.io.envoyproxy.envoy.config.core.v3.Http1ProtocolOptions$Builder setHeaderKeyFormat(io.grpc.xds.shaded.io.envoyproxy.envoy.config.core.v3.Http1ProtocolOptions$HeaderKeyFormat$Builder);
    Code:
       0: aload_0
       1: getfield      #132                // Field headerKeyFormatBuilder_:Lcom/google/protobuf/SingleFieldBuilderV3;
       4: ifnonnull     22
       7: aload_0
       8: aload_1
       9: invokevirtual #444                // Method io/grpc/xds/shaded/io/envoyproxy/envoy/config/core/v3/Http1ProtocolOptions$HeaderKeyFormat$Builder.build:()Lio/grpc/xds/shaded/io/envoyproxy/envoy/config/core/v3/Http1ProtocolOptions$HeaderKeyFormat;
      12: putfield      #134                // Field headerKeyFormat_:Lio/grpc/xds/shaded/io/envoyproxy/envoy/config/core/v3/Http1ProtocolOptions$HeaderKeyFormat;
      15: aload_0
      16: invokevirtual #274                // Method onChanged:()V
      19: goto          34
      22: aload_0
      23: getfield      #132                // Field headerKeyFormatBuilder_:Lcom/google/protobuf/SingleFieldBuilderV3;
      26: aload_1
      27: invokevirtual #444                // Method io/grpc/xds/shaded/io/envoyproxy/envoy/config/core/v3/Http1ProtocolOptions$HeaderKeyFormat$Builder.build:()Lio/grpc/xds/shaded/io/envoyproxy/envoy/config/core/v3/Http1ProtocolOptions$HeaderKeyFormat;
      30: invokevirtual #363                // Method com/google/protobuf/SingleFieldBuilderV3.setMessage:(Lcom/google/protobuf/AbstractMessage;)Lcom/google/protobuf/SingleFieldBuilderV3;
      33: pop
      34: aload_0
      35: areturn

  public io.grpc.xds.shaded.io.envoyproxy.envoy.config.core.v3.Http1ProtocolOptions$Builder mergeHeaderKeyFormat(io.grpc.xds.shaded.io.envoyproxy.envoy.config.core.v3.Http1ProtocolOptions$HeaderKeyFormat);
    Code:
       0: aload_0
       1: getfield      #132                // Field headerKeyFormatBuilder_:Lcom/google/protobuf/SingleFieldBuilderV3;
       4: ifnonnull     47
       7: aload_0
       8: getfield      #134                // Field headerKeyFormat_:Lio/grpc/xds/shaded/io/envoyproxy/envoy/config/core/v3/Http1ProtocolOptions$HeaderKeyFormat;
      11: ifnull        35
      14: aload_0
      15: aload_0
      16: getfield      #134                // Field headerKeyFormat_:Lio/grpc/xds/shaded/io/envoyproxy/envoy/config/core/v3/Http1ProtocolOptions$HeaderKeyFormat;
      19: invokestatic  #448                // Method io/grpc/xds/shaded/io/envoyproxy/envoy/config/core/v3/Http1ProtocolOptions$HeaderKeyFormat.newBuilder:(Lio/grpc/xds/shaded/io/envoyproxy/envoy/config/core/v3/Http1ProtocolOptions$HeaderKeyFormat;)Lio/grpc/xds/shaded/io/envoyproxy/envoy/config/core/v3/Http1ProtocolOptions$HeaderKeyFormat$Builder;
      22: aload_1
      23: invokevirtual #450                // Method io/grpc/xds/shaded/io/envoyproxy/envoy/config/core/v3/Http1ProtocolOptions$HeaderKeyFormat$Builder.mergeFrom:(Lio/grpc/xds/shaded/io/envoyproxy/envoy/config/core/v3/Http1ProtocolOptions$HeaderKeyFormat;)Lio/grpc/xds/shaded/io/envoyproxy/envoy/config/core/v3/Http1ProtocolOptions$HeaderKeyFormat$Builder;
      26: invokevirtual #452                // Method io/grpc/xds/shaded/io/envoyproxy/envoy/config/core/v3/Http1ProtocolOptions$HeaderKeyFormat$Builder.buildPartial:()Lio/grpc/xds/shaded/io/envoyproxy/envoy/config/core/v3/Http1ProtocolOptions$HeaderKeyFormat;
      29: putfield      #134                // Field headerKeyFormat_:Lio/grpc/xds/shaded/io/envoyproxy/envoy/config/core/v3/Http1ProtocolOptions$HeaderKeyFormat;
      32: goto          40
      35: aload_0
      36: aload_1
      37: putfield      #134                // Field headerKeyFormat_:Lio/grpc/xds/shaded/io/envoyproxy/envoy/config/core/v3/Http1ProtocolOptions$HeaderKeyFormat;
      40: aload_0
      41: invokevirtual #274                // Method onChanged:()V
      44: goto          56
      47: aload_0
      48: getfield      #132                // Field headerKeyFormatBuilder_:Lcom/google/protobuf/SingleFieldBuilderV3;
      51: aload_1
      52: invokevirtual #378                // Method com/google/protobuf/SingleFieldBuilderV3.mergeFrom:(Lcom/google/protobuf/AbstractMessage;)Lcom/google/protobuf/SingleFieldBuilderV3;
      55: pop
      56: aload_0
      57: areturn

  public io.grpc.xds.shaded.io.envoyproxy.envoy.config.core.v3.Http1ProtocolOptions$Builder clearHeaderKeyFormat();
    Code:
       0: aload_0
       1: getfield      #132                // Field headerKeyFormatBuilder_:Lcom/google/protobuf/SingleFieldBuilderV3;
       4: ifnonnull     19
       7: aload_0
       8: aconst_null
       9: putfield      #134                // Field headerKeyFormat_:Lio/grpc/xds/shaded/io/envoyproxy/envoy/config/core/v3/Http1ProtocolOptions$HeaderKeyFormat;
      12: aload_0
      13: invokevirtual #274                // Method onChanged:()V
      16: goto          29
      19: aload_0
      20: aconst_null
      21: putfield      #134                // Field headerKeyFormat_:Lio/grpc/xds/shaded/io/envoyproxy/envoy/config/core/v3/Http1ProtocolOptions$HeaderKeyFormat;
      24: aload_0
      25: aconst_null
      26: putfield      #132                // Field headerKeyFormatBuilder_:Lcom/google/protobuf/SingleFieldBuilderV3;
      29: aload_0
      30: areturn

  public io.grpc.xds.shaded.io.envoyproxy.envoy.config.core.v3.Http1ProtocolOptions$HeaderKeyFormat$Builder getHeaderKeyFormatBuilder();
    Code:
       0: aload_0
       1: invokevirtual #274                // Method onChanged:()V
       4: aload_0
       5: invokespecial #458                // Method getHeaderKeyFormatFieldBuilder:()Lcom/google/protobuf/SingleFieldBuilderV3;
       8: invokevirtual #389                // Method com/google/protobuf/SingleFieldBuilderV3.getBuilder:()Lcom/google/protobuf/AbstractMessage$Builder;
      11: checkcast     #20                 // class io/grpc/xds/shaded/io/envoyproxy/envoy/config/core/v3/Http1ProtocolOptions$HeaderKeyFormat$Builder
      14: areturn

  public io.grpc.xds.shaded.io.envoyproxy.envoy.config.core.v3.Http1ProtocolOptions$HeaderKeyFormatOrBuilder getHeaderKeyFormatOrBuilder();
    Code:
       0: aload_0
       1: getfield      #132                // Field headerKeyFormatBuilder_:Lcom/google/protobuf/SingleFieldBuilderV3;
       4: ifnull        18
       7: aload_0
       8: getfield      #132                // Field headerKeyFormatBuilder_:Lcom/google/protobuf/SingleFieldBuilderV3;
      11: invokevirtual #395                // Method com/google/protobuf/SingleFieldBuilderV3.getMessageOrBuilder:()Lcom/google/protobuf/MessageOrBuilder;
      14: checkcast     #22                 // class io/grpc/xds/shaded/io/envoyproxy/envoy/config/core/v3/Http1ProtocolOptions$HeaderKeyFormatOrBuilder
      17: areturn
      18: aload_0
      19: getfield      #134                // Field headerKeyFormat_:Lio/grpc/xds/shaded/io/envoyproxy/envoy/config/core/v3/Http1ProtocolOptions$HeaderKeyFormat;
      22: ifnonnull     31
      25: invokestatic  #440                // Method io/grpc/xds/shaded/io/envoyproxy/envoy/config/core/v3/Http1ProtocolOptions$HeaderKeyFormat.getDefaultInstance:()Lio/grpc/xds/shaded/io/envoyproxy/envoy/config/core/v3/Http1ProtocolOptions$HeaderKeyFormat;
      28: goto          35
      31: aload_0
      32: getfield      #134                // Field headerKeyFormat_:Lio/grpc/xds/shaded/io/envoyproxy/envoy/config/core/v3/Http1ProtocolOptions$HeaderKeyFormat;
      35: areturn

  private com.google.protobuf.SingleFieldBuilderV3<io.grpc.xds.shaded.io.envoyproxy.envoy.config.core.v3.Http1ProtocolOptions$HeaderKeyFormat, io.grpc.xds.shaded.io.envoyproxy.envoy.config.core.v3.Http1ProtocolOptions$HeaderKeyFormat$Builder, io.grpc.xds.shaded.io.envoyproxy.envoy.config.core.v3.Http1ProtocolOptions$HeaderKeyFormatOrBuilder> getHeaderKeyFormatFieldBuilder();
    Code:
       0: aload_0
       1: getfield      #132                // Field headerKeyFormatBuilder_:Lcom/google/protobuf/SingleFieldBuilderV3;
       4: ifnonnull     35
       7: aload_0
       8: new           #170                // class com/google/protobuf/SingleFieldBuilderV3
      11: dup
      12: aload_0
      13: invokevirtual #462                // Method getHeaderKeyFormat:()Lio/grpc/xds/shaded/io/envoyproxy/envoy/config/core/v3/Http1ProtocolOptions$HeaderKeyFormat;
      16: aload_0
      17: invokevirtual #403                // Method getParentForChildren:()Lcom/google/protobuf/GeneratedMessageV3$BuilderParent;
      20: aload_0
      21: invokevirtual #406                // Method isClean:()Z
      24: invokespecial #409                // Method com/google/protobuf/SingleFieldBuilderV3."<init>":(Lcom/google/protobuf/AbstractMessage;Lcom/google/protobuf/AbstractMessage$BuilderParent;Z)V
      27: putfield      #132                // Field headerKeyFormatBuilder_:Lcom/google/protobuf/SingleFieldBuilderV3;
      30: aload_0
      31: aconst_null
      32: putfield      #134                // Field headerKeyFormat_:Lio/grpc/xds/shaded/io/envoyproxy/envoy/config/core/v3/Http1ProtocolOptions$HeaderKeyFormat;
      35: aload_0
      36: getfield      #132                // Field headerKeyFormatBuilder_:Lcom/google/protobuf/SingleFieldBuilderV3;
      39: areturn

  public boolean getEnableTrailers();
    Code:
       0: aload_0
       1: getfield      #136                // Field enableTrailers_:Z
       4: ireturn

  public io.grpc.xds.shaded.io.envoyproxy.envoy.config.core.v3.Http1ProtocolOptions$Builder setEnableTrailers(boolean);
    Code:
       0: aload_0
       1: iload_1
       2: putfield      #136                // Field enableTrailers_:Z
       5: aload_0
       6: invokevirtual #274                // Method onChanged:()V
       9: aload_0
      10: areturn

  public io.grpc.xds.shaded.io.envoyproxy.envoy.config.core.v3.Http1ProtocolOptions$Builder clearEnableTrailers();
    Code:
       0: aload_0
       1: iconst_0
       2: putfield      #136                // Field enableTrailers_:Z
       5: aload_0
       6: invokevirtual #274                // Method onChanged:()V
       9: aload_0
      10: areturn

  public boolean getAllowChunkedLength();
    Code:
       0: aload_0
       1: getfield      #138                // Field allowChunkedLength_:Z
       4: ireturn

  public io.grpc.xds.shaded.io.envoyproxy.envoy.config.core.v3.Http1ProtocolOptions$Builder setAllowChunkedLength(boolean);
    Code:
       0: aload_0
       1: iload_1
       2: putfield      #138                // Field allowChunkedLength_:Z
       5: aload_0
       6: invokevirtual #274                // Method onChanged:()V
       9: aload_0
      10: areturn

  public io.grpc.xds.shaded.io.envoyproxy.envoy.config.core.v3.Http1ProtocolOptions$Builder clearAllowChunkedLength();
    Code:
       0: aload_0
       1: iconst_0
       2: putfield      #138                // Field allowChunkedLength_:Z
       5: aload_0
       6: invokevirtual #274                // Method onChanged:()V
       9: aload_0
      10: areturn

  public boolean hasOverrideStreamErrorOnInvalidHttpMessage();
    Code:
       0: aload_0
       1: getfield      #140                // Field overrideStreamErrorOnInvalidHttpMessageBuilder_:Lcom/google/protobuf/SingleFieldBuilderV3;
       4: ifnonnull     14
       7: aload_0
       8: getfield      #142                // Field overrideStreamErrorOnInvalidHttpMessage_:Lcom/google/protobuf/BoolValue;
      11: ifnull        18
      14: iconst_1
      15: goto          19
      18: iconst_0
      19: ireturn

  public com.google.protobuf.BoolValue getOverrideStreamErrorOnInvalidHttpMessage();
    Code:
       0: aload_0
       1: getfield      #140                // Field overrideStreamErrorOnInvalidHttpMessageBuilder_:Lcom/google/protobuf/SingleFieldBuilderV3;
       4: ifnonnull     25
       7: aload_0
       8: getfield      #142                // Field overrideStreamErrorOnInvalidHttpMessage_:Lcom/google/protobuf/BoolValue;
      11: ifnonnull     20
      14: invokestatic  #352                // Method com/google/protobuf/BoolValue.getDefaultInstance:()Lcom/google/protobuf/BoolValue;
      17: goto          24
      20: aload_0
      21: getfield      #142                // Field overrideStreamErrorOnInvalidHttpMessage_:Lcom/google/protobuf/BoolValue;
      24: areturn
      25: aload_0
      26: getfield      #140                // Field overrideStreamErrorOnInvalidHttpMessageBuilder_:Lcom/google/protobuf/SingleFieldBuilderV3;
      29: invokevirtual #355                // Method com/google/protobuf/SingleFieldBuilderV3.getMessage:()Lcom/google/protobuf/AbstractMessage;
      32: checkcast     #12                 // class com/google/protobuf/BoolValue
      35: areturn

  public io.grpc.xds.shaded.io.envoyproxy.envoy.config.core.v3.Http1ProtocolOptions$Builder setOverrideStreamErrorOnInvalidHttpMessage(com.google.protobuf.BoolValue);
    Code:
       0: aload_0
       1: getfield      #140                // Field overrideStreamErrorOnInvalidHttpMessageBuilder_:Lcom/google/protobuf/SingleFieldBuilderV3;
       4: ifnonnull     31
       7: aload_1
       8: ifnonnull     19
      11: new           #358                // class java/lang/NullPointerException
      14: dup
      15: invokespecial #359                // Method java/lang/NullPointerException."<init>":()V
      18: athrow
      19: aload_0
      20: aload_1
      21: putfield      #142                // Field overrideStreamErrorOnInvalidHttpMessage_:Lcom/google/protobuf/BoolValue;
      24: aload_0
      25: invokevirtual #274                // Method onChanged:()V
      28: goto          40
      31: aload_0
      32: getfield      #140                // Field overrideStreamErrorOnInvalidHttpMessageBuilder_:Lcom/google/protobuf/SingleFieldBuilderV3;
      35: aload_1
      36: invokevirtual #363                // Method com/google/protobuf/SingleFieldBuilderV3.setMessage:(Lcom/google/protobuf/AbstractMessage;)Lcom/google/protobuf/SingleFieldBuilderV3;
      39: pop
      40: aload_0
      41: areturn

  public io.grpc.xds.shaded.io.envoyproxy.envoy.config.core.v3.Http1ProtocolOptions$Builder setOverrideStreamErrorOnInvalidHttpMessage(com.google.protobuf.BoolValue$Builder);
    Code:
       0: aload_0
       1: getfield      #140                // Field overrideStreamErrorOnInvalidHttpMessageBuilder_:Lcom/google/protobuf/SingleFieldBuilderV3;
       4: ifnonnull     22
       7: aload_0
       8: aload_1
       9: invokevirtual #366                // Method com/google/protobuf/BoolValue$Builder.build:()Lcom/google/protobuf/BoolValue;
      12: putfield      #142                // Field overrideStreamErrorOnInvalidHttpMessage_:Lcom/google/protobuf/BoolValue;
      15: aload_0
      16: invokevirtual #274                // Method onChanged:()V
      19: goto          34
      22: aload_0
      23: getfield      #140                // Field overrideStreamErrorOnInvalidHttpMessageBuilder_:Lcom/google/protobuf/SingleFieldBuilderV3;
      26: aload_1
      27: invokevirtual #366                // Method com/google/protobuf/BoolValue$Builder.build:()Lcom/google/protobuf/BoolValue;
      30: invokevirtual #363                // Method com/google/protobuf/SingleFieldBuilderV3.setMessage:(Lcom/google/protobuf/AbstractMessage;)Lcom/google/protobuf/SingleFieldBuilderV3;
      33: pop
      34: aload_0
      35: areturn

  public io.grpc.xds.shaded.io.envoyproxy.envoy.config.core.v3.Http1ProtocolOptions$Builder mergeOverrideStreamErrorOnInvalidHttpMessage(com.google.protobuf.BoolValue);
    Code:
       0: aload_0
       1: getfield      #140                // Field overrideStreamErrorOnInvalidHttpMessageBuilder_:Lcom/google/protobuf/SingleFieldBuilderV3;
       4: ifnonnull     47
       7: aload_0
       8: getfield      #142                // Field overrideStreamErrorOnInvalidHttpMessage_:Lcom/google/protobuf/BoolValue;
      11: ifnull        35
      14: aload_0
      15: aload_0
      16: getfield      #142                // Field overrideStreamErrorOnInvalidHttpMessage_:Lcom/google/protobuf/BoolValue;
      19: invokestatic  #372                // Method com/google/protobuf/BoolValue.newBuilder:(Lcom/google/protobuf/BoolValue;)Lcom/google/protobuf/BoolValue$Builder;
      22: aload_1
      23: invokevirtual #374                // Method com/google/protobuf/BoolValue$Builder.mergeFrom:(Lcom/google/protobuf/BoolValue;)Lcom/google/protobuf/BoolValue$Builder;
      26: invokevirtual #376                // Method com/google/protobuf/BoolValue$Builder.buildPartial:()Lcom/google/protobuf/BoolValue;
      29: putfield      #142                // Field overrideStreamErrorOnInvalidHttpMessage_:Lcom/google/protobuf/BoolValue;
      32: goto          40
      35: aload_0
      36: aload_1
      37: putfield      #142                // Field overrideStreamErrorOnInvalidHttpMessage_:Lcom/google/protobuf/BoolValue;
      40: aload_0
      41: invokevirtual #274                // Method onChanged:()V
      44: goto          56
      47: aload_0
      48: getfield      #140                // Field overrideStreamErrorOnInvalidHttpMessageBuilder_:Lcom/google/protobuf/SingleFieldBuilderV3;
      51: aload_1
      52: invokevirtual #378                // Method com/google/protobuf/SingleFieldBuilderV3.mergeFrom:(Lcom/google/protobuf/AbstractMessage;)Lcom/google/protobuf/SingleFieldBuilderV3;
      55: pop
      56: aload_0
      57: areturn

  public io.grpc.xds.shaded.io.envoyproxy.envoy.config.core.v3.Http1ProtocolOptions$Builder clearOverrideStreamErrorOnInvalidHttpMessage();
    Code:
       0: aload_0
       1: getfield      #140                // Field overrideStreamErrorOnInvalidHttpMessageBuilder_:Lcom/google/protobuf/SingleFieldBuilderV3;
       4: ifnonnull     19
       7: aload_0
       8: aconst_null
       9: putfield      #142                // Field overrideStreamErrorOnInvalidHttpMessage_:Lcom/google/protobuf/BoolValue;
      12: aload_0
      13: invokevirtual #274                // Method onChanged:()V
      16: goto          29
      19: aload_0
      20: aconst_null
      21: putfield      #142                // Field overrideStreamErrorOnInvalidHttpMessage_:Lcom/google/protobuf/BoolValue;
      24: aload_0
      25: aconst_null
      26: putfield      #140                // Field overrideStreamErrorOnInvalidHttpMessageBuilder_:Lcom/google/protobuf/SingleFieldBuilderV3;
      29: aload_0
      30: areturn

  public com.google.protobuf.BoolValue$Builder getOverrideStreamErrorOnInvalidHttpMessageBuilder();
    Code:
       0: aload_0
       1: invokevirtual #274                // Method onChanged:()V
       4: aload_0
       5: invokespecial #470                // Method getOverrideStreamErrorOnInvalidHttpMessageFieldBuilder:()Lcom/google/protobuf/SingleFieldBuilderV3;
       8: invokevirtual #389                // Method com/google/protobuf/SingleFieldBuilderV3.getBuilder:()Lcom/google/protobuf/AbstractMessage$Builder;
      11: checkcast     #10                 // class com/google/protobuf/BoolValue$Builder
      14: areturn

  public com.google.protobuf.BoolValueOrBuilder getOverrideStreamErrorOnInvalidHttpMessageOrBuilder();
    Code:
       0: aload_0
       1: getfield      #140                // Field overrideStreamErrorOnInvalidHttpMessageBuilder_:Lcom/google/protobuf/SingleFieldBuilderV3;
       4: ifnull        18
       7: aload_0
       8: getfield      #140                // Field overrideStreamErrorOnInvalidHttpMessageBuilder_:Lcom/google/protobuf/SingleFieldBuilderV3;
      11: invokevirtual #395                // Method com/google/protobuf/SingleFieldBuilderV3.getMessageOrBuilder:()Lcom/google/protobuf/MessageOrBuilder;
      14: checkcast     #397                // class com/google/protobuf/BoolValueOrBuilder
      17: areturn
      18: aload_0
      19: getfield      #142                // Field overrideStreamErrorOnInvalidHttpMessage_:Lcom/google/protobuf/BoolValue;
      22: ifnonnull     31
      25: invokestatic  #352                // Method com/google/protobuf/BoolValue.getDefaultInstance:()Lcom/google/protobuf/BoolValue;
      28: goto          35
      31: aload_0
      32: getfield      #142                // Field overrideStreamErrorOnInvalidHttpMessage_:Lcom/google/protobuf/BoolValue;
      35: areturn

  private com.google.protobuf.SingleFieldBuilderV3<com.google.protobuf.BoolValue, com.google.protobuf.BoolValue$Builder, com.google.protobuf.BoolValueOrBuilder> getOverrideStreamErrorOnInvalidHttpMessageFieldBuilder();
    Code:
       0: aload_0
       1: getfield      #140                // Field overrideStreamErrorOnInvalidHttpMessageBuilder_:Lcom/google/protobuf/SingleFieldBuilderV3;
       4: ifnonnull     35
       7: aload_0
       8: new           #170                // class com/google/protobuf/SingleFieldBuilderV3
      11: dup
      12: aload_0
      13: invokevirtual #472                // Method getOverrideStreamErrorOnInvalidHttpMessage:()Lcom/google/protobuf/BoolValue;
      16: aload_0
      17: invokevirtual #403                // Method getParentForChildren:()Lcom/google/protobuf/GeneratedMessageV3$BuilderParent;
      20: aload_0
      21: invokevirtual #406                // Method isClean:()Z
      24: invokespecial #409                // Method com/google/protobuf/SingleFieldBuilderV3."<init>":(Lcom/google/protobuf/AbstractMessage;Lcom/google/protobuf/AbstractMessage$BuilderParent;Z)V
      27: putfield      #140                // Field overrideStreamErrorOnInvalidHttpMessageBuilder_:Lcom/google/protobuf/SingleFieldBuilderV3;
      30: aload_0
      31: aconst_null
      32: putfield      #142                // Field overrideStreamErrorOnInvalidHttpMessage_:Lcom/google/protobuf/BoolValue;
      35: aload_0
      36: getfield      #140                // Field overrideStreamErrorOnInvalidHttpMessageBuilder_:Lcom/google/protobuf/SingleFieldBuilderV3;
      39: areturn

  public final io.grpc.xds.shaded.io.envoyproxy.envoy.config.core.v3.Http1ProtocolOptions$Builder setUnknownFields(com.google.protobuf.UnknownFieldSet);
    Code:
       0: aload_0
       1: aload_1
       2: invokespecial #476                // Method com/google/protobuf/GeneratedMessageV3$Builder.setUnknownFields:(Lcom/google/protobuf/UnknownFieldSet;)Lcom/google/protobuf/GeneratedMessageV3$Builder;
       5: checkcast     #2                  // class io/grpc/xds/shaded/io/envoyproxy/envoy/config/core/v3/Http1ProtocolOptions$Builder
       8: areturn

  public final io.grpc.xds.shaded.io.envoyproxy.envoy.config.core.v3.Http1ProtocolOptions$Builder mergeUnknownFields(com.google.protobuf.UnknownFieldSet);
    Code:
       0: aload_0
       1: aload_1
       2: invokespecial #480                // Method com/google/protobuf/GeneratedMessageV3$Builder.mergeUnknownFields:(Lcom/google/protobuf/UnknownFieldSet;)Lcom/google/protobuf/GeneratedMessageV3$Builder;
       5: checkcast     #2                  // class io/grpc/xds/shaded/io/envoyproxy/envoy/config/core/v3/Http1ProtocolOptions$Builder
       8: areturn

  public com.google.protobuf.GeneratedMessageV3$Builder mergeUnknownFields(com.google.protobuf.UnknownFieldSet);
    Code:
       0: aload_0
       1: aload_1
       2: invokevirtual #314                // Method mergeUnknownFields:(Lcom/google/protobuf/UnknownFieldSet;)Lio/grpc/xds/shaded/io/envoyproxy/envoy/config/core/v3/Http1ProtocolOptions$Builder;
       5: areturn

  public com.google.protobuf.GeneratedMessageV3$Builder setUnknownFields(com.google.protobuf.UnknownFieldSet);
    Code:
       0: aload_0
       1: aload_1
       2: invokevirtual #482                // Method setUnknownFields:(Lcom/google/protobuf/UnknownFieldSet;)Lio/grpc/xds/shaded/io/envoyproxy/envoy/config/core/v3/Http1ProtocolOptions$Builder;
       5: areturn

  public com.google.protobuf.GeneratedMessageV3$Builder addRepeatedField(com.google.protobuf.Descriptors$FieldDescriptor, java.lang.Object);
    Code:
       0: aload_0
       1: aload_1
       2: aload_2
       3: invokevirtual #484                // Method addRepeatedField:(Lcom/google/protobuf/Descriptors$FieldDescriptor;Ljava/lang/Object;)Lio/grpc/xds/shaded/io/envoyproxy/envoy/config/core/v3/Http1ProtocolOptions$Builder;
       6: areturn

  public com.google.protobuf.GeneratedMessageV3$Builder setRepeatedField(com.google.protobuf.Descriptors$FieldDescriptor, int, java.lang.Object);
    Code:
       0: aload_0
       1: aload_1
       2: iload_2
       3: aload_3
       4: invokevirtual #486                // Method setRepeatedField:(Lcom/google/protobuf/Descriptors$FieldDescriptor;ILjava/lang/Object;)Lio/grpc/xds/shaded/io/envoyproxy/envoy/config/core/v3/Http1ProtocolOptions$Builder;
       7: areturn

  public com.google.protobuf.GeneratedMessageV3$Builder clearOneof(com.google.protobuf.Descriptors$OneofDescriptor);
    Code:
       0: aload_0
       1: aload_1
       2: invokevirtual #488                // Method clearOneof:(Lcom/google/protobuf/Descriptors$OneofDescriptor;)Lio/grpc/xds/shaded/io/envoyproxy/envoy/config/core/v3/Http1ProtocolOptions$Builder;
       5: areturn

  public com.google.protobuf.GeneratedMessageV3$Builder clearField(com.google.protobuf.Descriptors$FieldDescriptor);
    Code:
       0: aload_0
       1: aload_1
       2: invokevirtual #490                // Method clearField:(Lcom/google/protobuf/Descriptors$FieldDescriptor;)Lio/grpc/xds/shaded/io/envoyproxy/envoy/config/core/v3/Http1ProtocolOptions$Builder;
       5: areturn

  public com.google.protobuf.GeneratedMessageV3$Builder setField(com.google.protobuf.Descriptors$FieldDescriptor, java.lang.Object);
    Code:
       0: aload_0
       1: aload_1
       2: aload_2
       3: invokevirtual #492                // Method setField:(Lcom/google/protobuf/Descriptors$FieldDescriptor;Ljava/lang/Object;)Lio/grpc/xds/shaded/io/envoyproxy/envoy/config/core/v3/Http1ProtocolOptions$Builder;
       6: areturn

  public com.google.protobuf.GeneratedMessageV3$Builder clear();
    Code:
       0: aload_0
       1: invokevirtual #494                // Method clear:()Lio/grpc/xds/shaded/io/envoyproxy/envoy/config/core/v3/Http1ProtocolOptions$Builder;
       4: areturn

  public com.google.protobuf.GeneratedMessageV3$Builder clone();
    Code:
       0: aload_0
       1: invokevirtual #496                // Method clone:()Lio/grpc/xds/shaded/io/envoyproxy/envoy/config/core/v3/Http1ProtocolOptions$Builder;
       4: areturn

  public com.google.protobuf.AbstractMessage$Builder mergeUnknownFields(com.google.protobuf.UnknownFieldSet);
    Code:
       0: aload_0
       1: aload_1
       2: invokevirtual #314                // Method mergeUnknownFields:(Lcom/google/protobuf/UnknownFieldSet;)Lio/grpc/xds/shaded/io/envoyproxy/envoy/config/core/v3/Http1ProtocolOptions$Builder;
       5: areturn

  public com.google.protobuf.AbstractMessage$Builder mergeFrom(com.google.protobuf.CodedInputStream, com.google.protobuf.ExtensionRegistryLite) throws java.io.IOException;
    Code:
       0: aload_0
       1: aload_1
       2: aload_2
       3: invokevirtual #500                // Method mergeFrom:(Lcom/google/protobuf/CodedInputStream;Lcom/google/protobuf/ExtensionRegistryLite;)Lio/grpc/xds/shaded/io/envoyproxy/envoy/config/core/v3/Http1ProtocolOptions$Builder;
       6: areturn

  public com.google.protobuf.AbstractMessage$Builder mergeFrom(com.google.protobuf.Message);
    Code:
       0: aload_0
       1: aload_1
       2: invokevirtual #502                // Method mergeFrom:(Lcom/google/protobuf/Message;)Lio/grpc/xds/shaded/io/envoyproxy/envoy/config/core/v3/Http1ProtocolOptions$Builder;
       5: areturn

  public com.google.protobuf.AbstractMessage$Builder clear();
    Code:
       0: aload_0
       1: invokevirtual #494                // Method clear:()Lio/grpc/xds/shaded/io/envoyproxy/envoy/config/core/v3/Http1ProtocolOptions$Builder;
       4: areturn

  public com.google.protobuf.AbstractMessage$Builder clearOneof(com.google.protobuf.Descriptors$OneofDescriptor);
    Code:
       0: aload_0
       1: aload_1
       2: invokevirtual #488                // Method clearOneof:(Lcom/google/protobuf/Descriptors$OneofDescriptor;)Lio/grpc/xds/shaded/io/envoyproxy/envoy/config/core/v3/Http1ProtocolOptions$Builder;
       5: areturn

  public com.google.protobuf.AbstractMessage$Builder clone();
    Code:
       0: aload_0
       1: invokevirtual #496                // Method clone:()Lio/grpc/xds/shaded/io/envoyproxy/envoy/config/core/v3/Http1ProtocolOptions$Builder;
       4: areturn

  public com.google.protobuf.Message$Builder mergeUnknownFields(com.google.protobuf.UnknownFieldSet);
    Code:
       0: aload_0
       1: aload_1
       2: invokevirtual #314                // Method mergeUnknownFields:(Lcom/google/protobuf/UnknownFieldSet;)Lio/grpc/xds/shaded/io/envoyproxy/envoy/config/core/v3/Http1ProtocolOptions$Builder;
       5: areturn

  public com.google.protobuf.Message$Builder setUnknownFields(com.google.protobuf.UnknownFieldSet);
    Code:
       0: aload_0
       1: aload_1
       2: invokevirtual #482                // Method setUnknownFields:(Lcom/google/protobuf/UnknownFieldSet;)Lio/grpc/xds/shaded/io/envoyproxy/envoy/config/core/v3/Http1ProtocolOptions$Builder;
       5: areturn

  public com.google.protobuf.Message$Builder addRepeatedField(com.google.protobuf.Descriptors$FieldDescriptor, java.lang.Object);
    Code:
       0: aload_0
       1: aload_1
       2: aload_2
       3: invokevirtual #484                // Method addRepeatedField:(Lcom/google/protobuf/Descriptors$FieldDescriptor;Ljava/lang/Object;)Lio/grpc/xds/shaded/io/envoyproxy/envoy/config/core/v3/Http1ProtocolOptions$Builder;
       6: areturn

  public com.google.protobuf.Message$Builder setRepeatedField(com.google.protobuf.Descriptors$FieldDescriptor, int, java.lang.Object);
    Code:
       0: aload_0
       1: aload_1
       2: iload_2
       3: aload_3
       4: invokevirtual #486                // Method setRepeatedField:(Lcom/google/protobuf/Descriptors$FieldDescriptor;ILjava/lang/Object;)Lio/grpc/xds/shaded/io/envoyproxy/envoy/config/core/v3/Http1ProtocolOptions$Builder;
       7: areturn

  public com.google.protobuf.Message$Builder clearOneof(com.google.protobuf.Descriptors$OneofDescriptor);
    Code:
       0: aload_0
       1: aload_1
       2: invokevirtual #488                // Method clearOneof:(Lcom/google/protobuf/Descriptors$OneofDescriptor;)Lio/grpc/xds/shaded/io/envoyproxy/envoy/config/core/v3/Http1ProtocolOptions$Builder;
       5: areturn

  public com.google.protobuf.Message$Builder clearField(com.google.protobuf.Descriptors$FieldDescriptor);
    Code:
       0: aload_0
       1: aload_1
       2: invokevirtual #490                // Method clearField:(Lcom/google/protobuf/Descriptors$FieldDescriptor;)Lio/grpc/xds/shaded/io/envoyproxy/envoy/config/core/v3/Http1ProtocolOptions$Builder;
       5: areturn

  public com.google.protobuf.Message$Builder setField(com.google.protobuf.Descriptors$FieldDescriptor, java.lang.Object);
    Code:
       0: aload_0
       1: aload_1
       2: aload_2
       3: invokevirtual #492                // Method setField:(Lcom/google/protobuf/Descriptors$FieldDescriptor;Ljava/lang/Object;)Lio/grpc/xds/shaded/io/envoyproxy/envoy/config/core/v3/Http1ProtocolOptions$Builder;
       6: areturn

  public com.google.protobuf.Message$Builder mergeFrom(com.google.protobuf.CodedInputStream, com.google.protobuf.ExtensionRegistryLite) throws java.io.IOException;
    Code:
       0: aload_0
       1: aload_1
       2: aload_2
       3: invokevirtual #500                // Method mergeFrom:(Lcom/google/protobuf/CodedInputStream;Lcom/google/protobuf/ExtensionRegistryLite;)Lio/grpc/xds/shaded/io/envoyproxy/envoy/config/core/v3/Http1ProtocolOptions$Builder;
       6: areturn

  public com.google.protobuf.Message$Builder clone();
    Code:
       0: aload_0
       1: invokevirtual #496                // Method clone:()Lio/grpc/xds/shaded/io/envoyproxy/envoy/config/core/v3/Http1ProtocolOptions$Builder;
       4: areturn

  public com.google.protobuf.Message buildPartial();
    Code:
       0: aload_0
       1: invokevirtual #152                // Method buildPartial:()Lio/grpc/xds/shaded/io/envoyproxy/envoy/config/core/v3/Http1ProtocolOptions;
       4: areturn

  public com.google.protobuf.Message build();
    Code:
       0: aload_0
       1: invokevirtual #513                // Method build:()Lio/grpc/xds/shaded/io/envoyproxy/envoy/config/core/v3/Http1ProtocolOptions;
       4: areturn

  public com.google.protobuf.Message$Builder mergeFrom(com.google.protobuf.Message);
    Code:
       0: aload_0
       1: aload_1
       2: invokevirtual #502                // Method mergeFrom:(Lcom/google/protobuf/Message;)Lio/grpc/xds/shaded/io/envoyproxy/envoy/config/core/v3/Http1ProtocolOptions$Builder;
       5: areturn

  public com.google.protobuf.Message$Builder clear();
    Code:
       0: aload_0
       1: invokevirtual #494                // Method clear:()Lio/grpc/xds/shaded/io/envoyproxy/envoy/config/core/v3/Http1ProtocolOptions$Builder;
       4: areturn

  public com.google.protobuf.MessageLite$Builder mergeFrom(com.google.protobuf.CodedInputStream, com.google.protobuf.ExtensionRegistryLite) throws java.io.IOException;
    Code:
       0: aload_0
       1: aload_1
       2: aload_2
       3: invokevirtual #500                // Method mergeFrom:(Lcom/google/protobuf/CodedInputStream;Lcom/google/protobuf/ExtensionRegistryLite;)Lio/grpc/xds/shaded/io/envoyproxy/envoy/config/core/v3/Http1ProtocolOptions$Builder;
       6: areturn

  public com.google.protobuf.MessageLite$Builder clone();
    Code:
       0: aload_0
       1: invokevirtual #496                // Method clone:()Lio/grpc/xds/shaded/io/envoyproxy/envoy/config/core/v3/Http1ProtocolOptions$Builder;
       4: areturn

  public com.google.protobuf.MessageLite buildPartial();
    Code:
       0: aload_0
       1: invokevirtual #152                // Method buildPartial:()Lio/grpc/xds/shaded/io/envoyproxy/envoy/config/core/v3/Http1ProtocolOptions;
       4: areturn

  public com.google.protobuf.MessageLite build();
    Code:
       0: aload_0
       1: invokevirtual #513                // Method build:()Lio/grpc/xds/shaded/io/envoyproxy/envoy/config/core/v3/Http1ProtocolOptions;
       4: areturn

  public com.google.protobuf.MessageLite$Builder clear();
    Code:
       0: aload_0
       1: invokevirtual #494                // Method clear:()Lio/grpc/xds/shaded/io/envoyproxy/envoy/config/core/v3/Http1ProtocolOptions$Builder;
       4: areturn

  public com.google.protobuf.MessageLite getDefaultInstanceForType();
    Code:
       0: aload_0
       1: invokevirtual #518                // Method getDefaultInstanceForType:()Lio/grpc/xds/shaded/io/envoyproxy/envoy/config/core/v3/Http1ProtocolOptions;
       4: areturn

  public com.google.protobuf.Message getDefaultInstanceForType();
    Code:
       0: aload_0
       1: invokevirtual #518                // Method getDefaultInstanceForType:()Lio/grpc/xds/shaded/io/envoyproxy/envoy/config/core/v3/Http1ProtocolOptions;
       4: areturn

  public com.google.protobuf.AbstractMessageLite$Builder mergeFrom(com.google.protobuf.CodedInputStream, com.google.protobuf.ExtensionRegistryLite) throws java.io.IOException;
    Code:
       0: aload_0
       1: aload_1
       2: aload_2
       3: invokevirtual #500                // Method mergeFrom:(Lcom/google/protobuf/CodedInputStream;Lcom/google/protobuf/ExtensionRegistryLite;)Lio/grpc/xds/shaded/io/envoyproxy/envoy/config/core/v3/Http1ProtocolOptions$Builder;
       6: areturn

  public com.google.protobuf.AbstractMessageLite$Builder clone();
    Code:
       0: aload_0
       1: invokevirtual #496                // Method clone:()Lio/grpc/xds/shaded/io/envoyproxy/envoy/config/core/v3/Http1ProtocolOptions$Builder;
       4: areturn

  public java.lang.Object clone() throws java.lang.CloneNotSupportedException;
    Code:
       0: aload_0
       1: invokevirtual #496                // Method clone:()Lio/grpc/xds/shaded/io/envoyproxy/envoy/config/core/v3/Http1ProtocolOptions$Builder;
       4: areturn

  io.grpc.xds.shaded.io.envoyproxy.envoy.config.core.v3.Http1ProtocolOptions$Builder(io.grpc.xds.shaded.io.envoyproxy.envoy.config.core.v3.Http1ProtocolOptions$1);
    Code:
       0: aload_0
       1: invokespecial #525                // Method "<init>":()V
       4: return

  io.grpc.xds.shaded.io.envoyproxy.envoy.config.core.v3.Http1ProtocolOptions$Builder(com.google.protobuf.GeneratedMessageV3$BuilderParent, io.grpc.xds.shaded.io.envoyproxy.envoy.config.core.v3.Http1ProtocolOptions$1);
    Code:
       0: aload_0
       1: aload_1
       2: invokespecial #529                // Method "<init>":(Lcom/google/protobuf/GeneratedMessageV3$BuilderParent;)V
       5: return
}
