Compiled from "Http1ProtocolOptions.java"
public final class io.grpc.xds.shaded.io.envoyproxy.envoy.config.core.v3.Http1ProtocolOptions$HeaderKeyFormat extends com.google.protobuf.GeneratedMessageV3 implements io.grpc.xds.shaded.io.envoyproxy.envoy.config.core.v3.Http1ProtocolOptions$HeaderKeyFormatOrBuilder {
  private static final long serialVersionUID;

  private int headerFormatCase_;

  private java.lang.Object headerFormat_;

  public static final int PROPER_CASE_WORDS_FIELD_NUMBER;

  public static final int STATEFUL_FORMATTER_FIELD_NUMBER;

  private byte memoizedIsInitialized;

  private static final io.grpc.xds.shaded.io.envoyproxy.envoy.config.core.v3.Http1ProtocolOptions$HeaderKeyFormat DEFAULT_INSTANCE;

  private static final com.google.protobuf.Parser<io.grpc.xds.shaded.io.envoyproxy.envoy.config.core.v3.Http1ProtocolOptions$HeaderKeyFormat> PARSER;

  private io.grpc.xds.shaded.io.envoyproxy.envoy.config.core.v3.Http1ProtocolOptions$HeaderKeyFormat(com.google.protobuf.GeneratedMessageV3$Builder<?>);
    Code:
       0: aload_0
       1: aload_1
       2: invokespecial #85                 // Method com/google/protobuf/GeneratedMessageV3."<init>":(Lcom/google/protobuf/GeneratedMessageV3$Builder;)V
       5: aload_0
       6: iconst_0
       7: putfield      #87                 // Field headerFormatCase_:I
      10: aload_0
      11: iconst_m1
      12: putfield      #89                 // Field memoizedIsInitialized:B
      15: return

  private io.grpc.xds.shaded.io.envoyproxy.envoy.config.core.v3.Http1ProtocolOptions$HeaderKeyFormat();
    Code:
       0: aload_0
       1: invokespecial #96                 // Method com/google/protobuf/GeneratedMessageV3."<init>":()V
       4: aload_0
       5: iconst_0
       6: putfield      #87                 // Field headerFormatCase_:I
       9: aload_0
      10: iconst_m1
      11: putfield      #89                 // Field memoizedIsInitialized:B
      14: return

  protected java.lang.Object newInstance(com.google.protobuf.GeneratedMessageV3$UnusedPrivateParameter);
    Code:
       0: new           #2                  // class io/grpc/xds/shaded/io/envoyproxy/envoy/config/core/v3/Http1ProtocolOptions$HeaderKeyFormat
       3: dup
       4: invokespecial #99                 // Method "<init>":()V
       7: areturn

  public final com.google.protobuf.UnknownFieldSet getUnknownFields();
    Code:
       0: aload_0
       1: getfield      #107                // Field unknownFields:Lcom/google/protobuf/UnknownFieldSet;
       4: areturn

  private io.grpc.xds.shaded.io.envoyproxy.envoy.config.core.v3.Http1ProtocolOptions$HeaderKeyFormat(com.google.protobuf.CodedInputStream, com.google.protobuf.ExtensionRegistryLite) throws com.google.protobuf.InvalidProtocolBufferException;
    Code:
       0: aload_0
       1: invokespecial #99                 // Method "<init>":()V
       4: aload_2
       5: ifnonnull     16
       8: new           #114                // class java/lang/NullPointerException
      11: dup
      12: invokespecial #115                // Method java/lang/NullPointerException."<init>":()V
      15: athrow
      16: invokestatic  #123                // Method com/google/protobuf/UnknownFieldSet.newBuilder:()Lcom/google/protobuf/UnknownFieldSet$Builder;
      19: astore_3
      20: iconst_0
      21: istore        4
      23: iload         4
      25: ifne          238
      28: aload_1
      29: invokevirtual #127                // Method com/google/protobuf/CodedInputStream.readTag:()I
      32: istore        5
      34: iload         5
      36: lookupswitch  { // 3
                     0: 72
                    10: 78
                    66: 148
               default: 220
          }
      72: iconst_1
      73: istore        4
      75: goto          235
      78: aconst_null
      79: astore        6
      81: aload_0
      82: getfield      #87                 // Field headerFormatCase_:I
      85: iconst_1
      86: if_icmpne     101
      89: aload_0
      90: getfield      #129                // Field headerFormat_:Ljava/lang/Object;
      93: checkcast     #18                 // class io/grpc/xds/shaded/io/envoyproxy/envoy/config/core/v3/Http1ProtocolOptions$HeaderKeyFormat$ProperCaseWords
      96: invokevirtual #133                // Method io/grpc/xds/shaded/io/envoyproxy/envoy/config/core/v3/Http1ProtocolOptions$HeaderKeyFormat$ProperCaseWords.toBuilder:()Lio/grpc/xds/shaded/io/envoyproxy/envoy/config/core/v3/Http1ProtocolOptions$HeaderKeyFormat$ProperCaseWords$Builder;
      99: astore        6
     101: aload_0
     102: aload_1
     103: invokestatic  #137                // Method io/grpc/xds/shaded/io/envoyproxy/envoy/config/core/v3/Http1ProtocolOptions$HeaderKeyFormat$ProperCaseWords.parser:()Lcom/google/protobuf/Parser;
     106: aload_2
     107: invokevirtual #141                // Method com/google/protobuf/CodedInputStream.readMessage:(Lcom/google/protobuf/Parser;Lcom/google/protobuf/ExtensionRegistryLite;)Lcom/google/protobuf/MessageLite;
     110: putfield      #129                // Field headerFormat_:Ljava/lang/Object;
     113: aload         6
     115: ifnull        140
     118: aload         6
     120: aload_0
     121: getfield      #129                // Field headerFormat_:Ljava/lang/Object;
     124: checkcast     #18                 // class io/grpc/xds/shaded/io/envoyproxy/envoy/config/core/v3/Http1ProtocolOptions$HeaderKeyFormat$ProperCaseWords
     127: invokevirtual #145                // Method io/grpc/xds/shaded/io/envoyproxy/envoy/config/core/v3/Http1ProtocolOptions$HeaderKeyFormat$ProperCaseWords$Builder.mergeFrom:(Lio/grpc/xds/shaded/io/envoyproxy/envoy/config/core/v3/Http1ProtocolOptions$HeaderKeyFormat$ProperCaseWords;)Lio/grpc/xds/shaded/io/envoyproxy/envoy/config/core/v3/Http1ProtocolOptions$HeaderKeyFormat$ProperCaseWords$Builder;
     130: pop
     131: aload_0
     132: aload         6
     134: invokevirtual #149                // Method io/grpc/xds/shaded/io/envoyproxy/envoy/config/core/v3/Http1ProtocolOptions$HeaderKeyFormat$ProperCaseWords$Builder.buildPartial:()Lio/grpc/xds/shaded/io/envoyproxy/envoy/config/core/v3/Http1ProtocolOptions$HeaderKeyFormat$ProperCaseWords;
     137: putfield      #129                // Field headerFormat_:Ljava/lang/Object;
     140: aload_0
     141: iconst_1
     142: putfield      #87                 // Field headerFormatCase_:I
     145: goto          235
     148: aconst_null
     149: astore        6
     151: aload_0
     152: getfield      #87                 // Field headerFormatCase_:I
     155: bipush        8
     157: if_icmpne     172
     160: aload_0
     161: getfield      #129                // Field headerFormat_:Ljava/lang/Object;
     164: checkcast     #35                 // class io/grpc/xds/shaded/io/envoyproxy/envoy/config/core/v3/TypedExtensionConfig
     167: invokevirtual #152                // Method io/grpc/xds/shaded/io/envoyproxy/envoy/config/core/v3/TypedExtensionConfig.toBuilder:()Lio/grpc/xds/shaded/io/envoyproxy/envoy/config/core/v3/TypedExtensionConfig$Builder;
     170: astore        6
     172: aload_0
     173: aload_1
     174: invokestatic  #153                // Method io/grpc/xds/shaded/io/envoyproxy/envoy/config/core/v3/TypedExtensionConfig.parser:()Lcom/google/protobuf/Parser;
     177: aload_2
     178: invokevirtual #141                // Method com/google/protobuf/CodedInputStream.readMessage:(Lcom/google/protobuf/Parser;Lcom/google/protobuf/ExtensionRegistryLite;)Lcom/google/protobuf/MessageLite;
     181: putfield      #129                // Field headerFormat_:Ljava/lang/Object;
     184: aload         6
     186: ifnull        211
     189: aload         6
     191: aload_0
     192: getfield      #129                // Field headerFormat_:Ljava/lang/Object;
     195: checkcast     #35                 // class io/grpc/xds/shaded/io/envoyproxy/envoy/config/core/v3/TypedExtensionConfig
     198: invokevirtual #156                // Method io/grpc/xds/shaded/io/envoyproxy/envoy/config/core/v3/TypedExtensionConfig$Builder.mergeFrom:(Lio/grpc/xds/shaded/io/envoyproxy/envoy/config/core/v3/TypedExtensionConfig;)Lio/grpc/xds/shaded/io/envoyproxy/envoy/config/core/v3/TypedExtensionConfig$Builder;
     201: pop
     202: aload_0
     203: aload         6
     205: invokevirtual #159                // Method io/grpc/xds/shaded/io/envoyproxy/envoy/config/core/v3/TypedExtensionConfig$Builder.buildPartial:()Lio/grpc/xds/shaded/io/envoyproxy/envoy/config/core/v3/TypedExtensionConfig;
     208: putfield      #129                // Field headerFormat_:Ljava/lang/Object;
     211: aload_0
     212: bipush        8
     214: putfield      #87                 // Field headerFormatCase_:I
     217: goto          235
     220: aload_0
     221: aload_1
     222: aload_3
     223: aload_2
     224: iload         5
     226: invokevirtual #163                // Method parseUnknownField:(Lcom/google/protobuf/CodedInputStream;Lcom/google/protobuf/UnknownFieldSet$Builder;Lcom/google/protobuf/ExtensionRegistryLite;I)Z
     229: ifne          235
     232: iconst_1
     233: istore        4
     235: goto          23
     238: aload_0
     239: aload_3
     240: invokevirtual #166                // Method com/google/protobuf/UnknownFieldSet$Builder.build:()Lcom/google/protobuf/UnknownFieldSet;
     243: putfield      #107                // Field unknownFields:Lcom/google/protobuf/UnknownFieldSet;
     246: aload_0
     247: invokevirtual #169                // Method makeExtensionsImmutable:()V
     250: goto          295
     253: astore        4
     255: aload         4
     257: aload_0
     258: invokevirtual #173                // Method com/google/protobuf/InvalidProtocolBufferException.setUnfinishedMessage:(Lcom/google/protobuf/MessageLite;)Lcom/google/protobuf/InvalidProtocolBufferException;
     261: athrow
     262: astore        4
     264: new           #110                // class com/google/protobuf/InvalidProtocolBufferException
     267: dup
     268: aload         4
     270: invokespecial #176                // Method com/google/protobuf/InvalidProtocolBufferException."<init>":(Ljava/io/IOException;)V
     273: aload_0
     274: invokevirtual #173                // Method com/google/protobuf/InvalidProtocolBufferException.setUnfinishedMessage:(Lcom/google/protobuf/MessageLite;)Lcom/google/protobuf/InvalidProtocolBufferException;
     277: athrow
     278: astore        7
     280: aload_0
     281: aload_3
     282: invokevirtual #166                // Method com/google/protobuf/UnknownFieldSet$Builder.build:()Lcom/google/protobuf/UnknownFieldSet;
     285: putfield      #107                // Field unknownFields:Lcom/google/protobuf/UnknownFieldSet;
     288: aload_0
     289: invokevirtual #169                // Method makeExtensionsImmutable:()V
     292: aload         7
     294: athrow
     295: return
    Exception table:
       from    to  target type
          20   238   253   Class com/google/protobuf/InvalidProtocolBufferException
          20   238   262   Class java/io/IOException
          20   238   278   any
         253   280   278   any

  public static final com.google.protobuf.Descriptors$Descriptor getDescriptor();
    Code:
       0: getstatic     #200                // Field io/grpc/xds/shaded/io/envoyproxy/envoy/config/core/v3/ProtocolProto.internal_static_envoy_config_core_v3_Http1ProtocolOptions_HeaderKeyFormat_descriptor:Lcom/google/protobuf/Descriptors$Descriptor;
       3: areturn

  protected com.google.protobuf.GeneratedMessageV3$FieldAccessorTable internalGetFieldAccessorTable();
    Code:
       0: getstatic     #206                // Field io/grpc/xds/shaded/io/envoyproxy/envoy/config/core/v3/ProtocolProto.internal_static_envoy_config_core_v3_Http1ProtocolOptions_HeaderKeyFormat_fieldAccessorTable:Lcom/google/protobuf/GeneratedMessageV3$FieldAccessorTable;
       3: ldc           #2                  // class io/grpc/xds/shaded/io/envoyproxy/envoy/config/core/v3/Http1ProtocolOptions$HeaderKeyFormat
       5: ldc           #12                 // class io/grpc/xds/shaded/io/envoyproxy/envoy/config/core/v3/Http1ProtocolOptions$HeaderKeyFormat$Builder
       7: invokevirtual #210                // Method com/google/protobuf/GeneratedMessageV3$FieldAccessorTable.ensureFieldAccessorsInitialized:(Ljava/lang/Class;Ljava/lang/Class;)Lcom/google/protobuf/GeneratedMessageV3$FieldAccessorTable;
      10: areturn

  public io.grpc.xds.shaded.io.envoyproxy.envoy.config.core.v3.Http1ProtocolOptions$HeaderKeyFormat$HeaderFormatCase getHeaderFormatCase();
    Code:
       0: aload_0
       1: getfield      #87                 // Field headerFormatCase_:I
       4: invokestatic  #216                // Method io/grpc/xds/shaded/io/envoyproxy/envoy/config/core/v3/Http1ProtocolOptions$HeaderKeyFormat$HeaderFormatCase.forNumber:(I)Lio/grpc/xds/shaded/io/envoyproxy/envoy/config/core/v3/Http1ProtocolOptions$HeaderKeyFormat$HeaderFormatCase;
       7: areturn

  public boolean hasProperCaseWords();
    Code:
       0: aload_0
       1: getfield      #87                 // Field headerFormatCase_:I
       4: iconst_1
       5: if_icmpne     12
       8: iconst_1
       9: goto          13
      12: iconst_0
      13: ireturn

  public io.grpc.xds.shaded.io.envoyproxy.envoy.config.core.v3.Http1ProtocolOptions$HeaderKeyFormat$ProperCaseWords getProperCaseWords();
    Code:
       0: aload_0
       1: getfield      #87                 // Field headerFormatCase_:I
       4: iconst_1
       5: if_icmpne     16
       8: aload_0
       9: getfield      #129                // Field headerFormat_:Ljava/lang/Object;
      12: checkcast     #18                 // class io/grpc/xds/shaded/io/envoyproxy/envoy/config/core/v3/Http1ProtocolOptions$HeaderKeyFormat$ProperCaseWords
      15: areturn
      16: invokestatic  #222                // Method io/grpc/xds/shaded/io/envoyproxy/envoy/config/core/v3/Http1ProtocolOptions$HeaderKeyFormat$ProperCaseWords.getDefaultInstance:()Lio/grpc/xds/shaded/io/envoyproxy/envoy/config/core/v3/Http1ProtocolOptions$HeaderKeyFormat$ProperCaseWords;
      19: areturn

  public io.grpc.xds.shaded.io.envoyproxy.envoy.config.core.v3.Http1ProtocolOptions$HeaderKeyFormat$ProperCaseWordsOrBuilder getProperCaseWordsOrBuilder();
    Code:
       0: aload_0
       1: getfield      #87                 // Field headerFormatCase_:I
       4: iconst_1
       5: if_icmpne     16
       8: aload_0
       9: getfield      #129                // Field headerFormat_:Ljava/lang/Object;
      12: checkcast     #18                 // class io/grpc/xds/shaded/io/envoyproxy/envoy/config/core/v3/Http1ProtocolOptions$HeaderKeyFormat$ProperCaseWords
      15: areturn
      16: invokestatic  #222                // Method io/grpc/xds/shaded/io/envoyproxy/envoy/config/core/v3/Http1ProtocolOptions$HeaderKeyFormat$ProperCaseWords.getDefaultInstance:()Lio/grpc/xds/shaded/io/envoyproxy/envoy/config/core/v3/Http1ProtocolOptions$HeaderKeyFormat$ProperCaseWords;
      19: areturn

  public boolean hasStatefulFormatter();
    Code:
       0: aload_0
       1: getfield      #87                 // Field headerFormatCase_:I
       4: bipush        8
       6: if_icmpne     13
       9: iconst_1
      10: goto          14
      13: iconst_0
      14: ireturn

  public io.grpc.xds.shaded.io.envoyproxy.envoy.config.core.v3.TypedExtensionConfig getStatefulFormatter();
    Code:
       0: aload_0
       1: getfield      #87                 // Field headerFormatCase_:I
       4: bipush        8
       6: if_icmpne     17
       9: aload_0
      10: getfield      #129                // Field headerFormat_:Ljava/lang/Object;
      13: checkcast     #35                 // class io/grpc/xds/shaded/io/envoyproxy/envoy/config/core/v3/TypedExtensionConfig
      16: areturn
      17: invokestatic  #228                // Method io/grpc/xds/shaded/io/envoyproxy/envoy/config/core/v3/TypedExtensionConfig.getDefaultInstance:()Lio/grpc/xds/shaded/io/envoyproxy/envoy/config/core/v3/TypedExtensionConfig;
      20: areturn

  public io.grpc.xds.shaded.io.envoyproxy.envoy.config.core.v3.TypedExtensionConfigOrBuilder getStatefulFormatterOrBuilder();
    Code:
       0: aload_0
       1: getfield      #87                 // Field headerFormatCase_:I
       4: bipush        8
       6: if_icmpne     17
       9: aload_0
      10: getfield      #129                // Field headerFormat_:Ljava/lang/Object;
      13: checkcast     #35                 // class io/grpc/xds/shaded/io/envoyproxy/envoy/config/core/v3/TypedExtensionConfig
      16: areturn
      17: invokestatic  #228                // Method io/grpc/xds/shaded/io/envoyproxy/envoy/config/core/v3/TypedExtensionConfig.getDefaultInstance:()Lio/grpc/xds/shaded/io/envoyproxy/envoy/config/core/v3/TypedExtensionConfig;
      20: areturn

  public final boolean isInitialized();
    Code:
       0: aload_0
       1: getfield      #89                 // Field memoizedIsInitialized:B
       4: istore_1
       5: iload_1
       6: iconst_1
       7: if_icmpne     12
      10: iconst_1
      11: ireturn
      12: iload_1
      13: ifne          18
      16: iconst_0
      17: ireturn
      18: aload_0
      19: iconst_1
      20: putfield      #89                 // Field memoizedIsInitialized:B
      23: iconst_1
      24: ireturn

  public void writeTo(com.google.protobuf.CodedOutputStream) throws java.io.IOException;
    Code:
       0: aload_0
       1: getfield      #87                 // Field headerFormatCase_:I
       4: iconst_1
       5: if_icmpne     20
       8: aload_1
       9: iconst_1
      10: aload_0
      11: getfield      #129                // Field headerFormat_:Ljava/lang/Object;
      14: checkcast     #18                 // class io/grpc/xds/shaded/io/envoyproxy/envoy/config/core/v3/Http1ProtocolOptions$HeaderKeyFormat$ProperCaseWords
      17: invokevirtual #239                // Method com/google/protobuf/CodedOutputStream.writeMessage:(ILcom/google/protobuf/MessageLite;)V
      20: aload_0
      21: getfield      #87                 // Field headerFormatCase_:I
      24: bipush        8
      26: if_icmpne     42
      29: aload_1
      30: bipush        8
      32: aload_0
      33: getfield      #129                // Field headerFormat_:Ljava/lang/Object;
      36: checkcast     #35                 // class io/grpc/xds/shaded/io/envoyproxy/envoy/config/core/v3/TypedExtensionConfig
      39: invokevirtual #239                // Method com/google/protobuf/CodedOutputStream.writeMessage:(ILcom/google/protobuf/MessageLite;)V
      42: aload_0
      43: getfield      #107                // Field unknownFields:Lcom/google/protobuf/UnknownFieldSet;
      46: aload_1
      47: invokevirtual #241                // Method com/google/protobuf/UnknownFieldSet.writeTo:(Lcom/google/protobuf/CodedOutputStream;)V
      50: return

  public int getSerializedSize();
    Code:
       0: aload_0
       1: getfield      #247                // Field memoizedSize:I
       4: istore_1
       5: iload_1
       6: iconst_m1
       7: if_icmpeq     12
      10: iload_1
      11: ireturn
      12: iconst_0
      13: istore_1
      14: aload_0
      15: getfield      #87                 // Field headerFormatCase_:I
      18: iconst_1
      19: if_icmpne     36
      22: iload_1
      23: iconst_1
      24: aload_0
      25: getfield      #129                // Field headerFormat_:Ljava/lang/Object;
      28: checkcast     #18                 // class io/grpc/xds/shaded/io/envoyproxy/envoy/config/core/v3/Http1ProtocolOptions$HeaderKeyFormat$ProperCaseWords
      31: invokestatic  #251                // Method com/google/protobuf/CodedOutputStream.computeMessageSize:(ILcom/google/protobuf/MessageLite;)I
      34: iadd
      35: istore_1
      36: aload_0
      37: getfield      #87                 // Field headerFormatCase_:I
      40: bipush        8
      42: if_icmpne     60
      45: iload_1
      46: bipush        8
      48: aload_0
      49: getfield      #129                // Field headerFormat_:Ljava/lang/Object;
      52: checkcast     #35                 // class io/grpc/xds/shaded/io/envoyproxy/envoy/config/core/v3/TypedExtensionConfig
      55: invokestatic  #251                // Method com/google/protobuf/CodedOutputStream.computeMessageSize:(ILcom/google/protobuf/MessageLite;)I
      58: iadd
      59: istore_1
      60: iload_1
      61: aload_0
      62: getfield      #107                // Field unknownFields:Lcom/google/protobuf/UnknownFieldSet;
      65: invokevirtual #253                // Method com/google/protobuf/UnknownFieldSet.getSerializedSize:()I
      68: iadd
      69: istore_1
      70: aload_0
      71: iload_1
      72: putfield      #247                // Field memoizedSize:I
      75: iload_1
      76: ireturn

  public boolean equals(java.lang.Object);
    Code:
       0: aload_1
       1: aload_0
       2: if_acmpne     7
       5: iconst_1
       6: ireturn
       7: aload_1
       8: instanceof    #2                  // class io/grpc/xds/shaded/io/envoyproxy/envoy/config/core/v3/Http1ProtocolOptions$HeaderKeyFormat
      11: ifne          20
      14: aload_0
      15: aload_1
      16: invokespecial #258                // Method com/google/protobuf/GeneratedMessageV3.equals:(Ljava/lang/Object;)Z
      19: ireturn
      20: aload_1
      21: checkcast     #2                  // class io/grpc/xds/shaded/io/envoyproxy/envoy/config/core/v3/Http1ProtocolOptions$HeaderKeyFormat
      24: astore_2
      25: aload_0
      26: invokevirtual #260                // Method getHeaderFormatCase:()Lio/grpc/xds/shaded/io/envoyproxy/envoy/config/core/v3/Http1ProtocolOptions$HeaderKeyFormat$HeaderFormatCase;
      29: aload_2
      30: invokevirtual #260                // Method getHeaderFormatCase:()Lio/grpc/xds/shaded/io/envoyproxy/envoy/config/core/v3/Http1ProtocolOptions$HeaderKeyFormat$HeaderFormatCase;
      33: invokevirtual #261                // Method io/grpc/xds/shaded/io/envoyproxy/envoy/config/core/v3/Http1ProtocolOptions$HeaderKeyFormat$HeaderFormatCase.equals:(Ljava/lang/Object;)Z
      36: ifne          41
      39: iconst_0
      40: ireturn
      41: aload_0
      42: getfield      #87                 // Field headerFormatCase_:I
      45: lookupswitch  { // 3
                     0: 112
                     1: 80
                     8: 96
               default: 112
          }
      80: aload_0
      81: invokevirtual #263                // Method getProperCaseWords:()Lio/grpc/xds/shaded/io/envoyproxy/envoy/config/core/v3/Http1ProtocolOptions$HeaderKeyFormat$ProperCaseWords;
      84: aload_2
      85: invokevirtual #263                // Method getProperCaseWords:()Lio/grpc/xds/shaded/io/envoyproxy/envoy/config/core/v3/Http1ProtocolOptions$HeaderKeyFormat$ProperCaseWords;
      88: invokevirtual #264                // Method io/grpc/xds/shaded/io/envoyproxy/envoy/config/core/v3/Http1ProtocolOptions$HeaderKeyFormat$ProperCaseWords.equals:(Ljava/lang/Object;)Z
      91: ifne          112
      94: iconst_0
      95: ireturn
      96: aload_0
      97: invokevirtual #266                // Method getStatefulFormatter:()Lio/grpc/xds/shaded/io/envoyproxy/envoy/config/core/v3/TypedExtensionConfig;
     100: aload_2
     101: invokevirtual #266                // Method getStatefulFormatter:()Lio/grpc/xds/shaded/io/envoyproxy/envoy/config/core/v3/TypedExtensionConfig;
     104: invokevirtual #267                // Method io/grpc/xds/shaded/io/envoyproxy/envoy/config/core/v3/TypedExtensionConfig.equals:(Ljava/lang/Object;)Z
     107: ifne          112
     110: iconst_0
     111: ireturn
     112: aload_0
     113: getfield      #107                // Field unknownFields:Lcom/google/protobuf/UnknownFieldSet;
     116: aload_2
     117: getfield      #107                // Field unknownFields:Lcom/google/protobuf/UnknownFieldSet;
     120: invokevirtual #268                // Method com/google/protobuf/UnknownFieldSet.equals:(Ljava/lang/Object;)Z
     123: ifne          128
     126: iconst_0
     127: ireturn
     128: iconst_1
     129: ireturn

  public int hashCode();
    Code:
       0: aload_0
       1: getfield      #274                // Field memoizedHashCode:I
       4: ifeq          12
       7: aload_0
       8: getfield      #274                // Field memoizedHashCode:I
      11: ireturn
      12: bipush        41
      14: istore_1
      15: bipush        19
      17: iload_1
      18: imul
      19: invokestatic  #276                // Method getDescriptor:()Lcom/google/protobuf/Descriptors$Descriptor;
      22: invokevirtual #280                // Method java/lang/Object.hashCode:()I
      25: iadd
      26: istore_1
      27: aload_0
      28: getfield      #87                 // Field headerFormatCase_:I
      31: lookupswitch  { // 3
                     0: 111
                     1: 64
                     8: 87
               default: 111
          }
      64: bipush        37
      66: iload_1
      67: imul
      68: iconst_1
      69: iadd
      70: istore_1
      71: bipush        53
      73: iload_1
      74: imul
      75: aload_0
      76: invokevirtual #263                // Method getProperCaseWords:()Lio/grpc/xds/shaded/io/envoyproxy/envoy/config/core/v3/Http1ProtocolOptions$HeaderKeyFormat$ProperCaseWords;
      79: invokevirtual #281                // Method io/grpc/xds/shaded/io/envoyproxy/envoy/config/core/v3/Http1ProtocolOptions$HeaderKeyFormat$ProperCaseWords.hashCode:()I
      82: iadd
      83: istore_1
      84: goto          111
      87: bipush        37
      89: iload_1
      90: imul
      91: bipush        8
      93: iadd
      94: istore_1
      95: bipush        53
      97: iload_1
      98: imul
      99: aload_0
     100: invokevirtual #266                // Method getStatefulFormatter:()Lio/grpc/xds/shaded/io/envoyproxy/envoy/config/core/v3/TypedExtensionConfig;
     103: invokevirtual #282                // Method io/grpc/xds/shaded/io/envoyproxy/envoy/config/core/v3/TypedExtensionConfig.hashCode:()I
     106: iadd
     107: istore_1
     108: goto          111
     111: bipush        29
     113: iload_1
     114: imul
     115: aload_0
     116: getfield      #107                // Field unknownFields:Lcom/google/protobuf/UnknownFieldSet;
     119: invokevirtual #283                // Method com/google/protobuf/UnknownFieldSet.hashCode:()I
     122: iadd
     123: istore_1
     124: aload_0
     125: iload_1
     126: putfield      #274                // Field memoizedHashCode:I
     129: iload_1
     130: ireturn

  public static io.grpc.xds.shaded.io.envoyproxy.envoy.config.core.v3.Http1ProtocolOptions$HeaderKeyFormat parseFrom(java.nio.ByteBuffer) throws com.google.protobuf.InvalidProtocolBufferException;
    Code:
       0: getstatic     #288                // Field PARSER:Lcom/google/protobuf/Parser;
       3: aload_0
       4: invokeinterface #293,  2          // InterfaceMethod com/google/protobuf/Parser.parseFrom:(Ljava/nio/ByteBuffer;)Ljava/lang/Object;
       9: checkcast     #2                  // class io/grpc/xds/shaded/io/envoyproxy/envoy/config/core/v3/Http1ProtocolOptions$HeaderKeyFormat
      12: areturn

  public static io.grpc.xds.shaded.io.envoyproxy.envoy.config.core.v3.Http1ProtocolOptions$HeaderKeyFormat parseFrom(java.nio.ByteBuffer, com.google.protobuf.ExtensionRegistryLite) throws com.google.protobuf.InvalidProtocolBufferException;
    Code:
       0: getstatic     #288                // Field PARSER:Lcom/google/protobuf/Parser;
       3: aload_0
       4: aload_1
       5: invokeinterface #299,  3          // InterfaceMethod com/google/protobuf/Parser.parseFrom:(Ljava/nio/ByteBuffer;Lcom/google/protobuf/ExtensionRegistryLite;)Ljava/lang/Object;
      10: checkcast     #2                  // class io/grpc/xds/shaded/io/envoyproxy/envoy/config/core/v3/Http1ProtocolOptions$HeaderKeyFormat
      13: areturn

  public static io.grpc.xds.shaded.io.envoyproxy.envoy.config.core.v3.Http1ProtocolOptions$HeaderKeyFormat parseFrom(com.google.protobuf.ByteString) throws com.google.protobuf.InvalidProtocolBufferException;
    Code:
       0: getstatic     #288                // Field PARSER:Lcom/google/protobuf/Parser;
       3: aload_0
       4: invokeinterface #303,  2          // InterfaceMethod com/google/protobuf/Parser.parseFrom:(Lcom/google/protobuf/ByteString;)Ljava/lang/Object;
       9: checkcast     #2                  // class io/grpc/xds/shaded/io/envoyproxy/envoy/config/core/v3/Http1ProtocolOptions$HeaderKeyFormat
      12: areturn

  public static io.grpc.xds.shaded.io.envoyproxy.envoy.config.core.v3.Http1ProtocolOptions$HeaderKeyFormat parseFrom(com.google.protobuf.ByteString, com.google.protobuf.ExtensionRegistryLite) throws com.google.protobuf.InvalidProtocolBufferException;
    Code:
       0: getstatic     #288                // Field PARSER:Lcom/google/protobuf/Parser;
       3: aload_0
       4: aload_1
       5: invokeinterface #308,  3          // InterfaceMethod com/google/protobuf/Parser.parseFrom:(Lcom/google/protobuf/ByteString;Lcom/google/protobuf/ExtensionRegistryLite;)Ljava/lang/Object;
      10: checkcast     #2                  // class io/grpc/xds/shaded/io/envoyproxy/envoy/config/core/v3/Http1ProtocolOptions$HeaderKeyFormat
      13: areturn

  public static io.grpc.xds.shaded.io.envoyproxy.envoy.config.core.v3.Http1ProtocolOptions$HeaderKeyFormat parseFrom(byte[]) throws com.google.protobuf.InvalidProtocolBufferException;
    Code:
       0: getstatic     #288                // Field PARSER:Lcom/google/protobuf/Parser;
       3: aload_0
       4: invokeinterface #312,  2          // InterfaceMethod com/google/protobuf/Parser.parseFrom:([B)Ljava/lang/Object;
       9: checkcast     #2                  // class io/grpc/xds/shaded/io/envoyproxy/envoy/config/core/v3/Http1ProtocolOptions$HeaderKeyFormat
      12: areturn

  public static io.grpc.xds.shaded.io.envoyproxy.envoy.config.core.v3.Http1ProtocolOptions$HeaderKeyFormat parseFrom(byte[], com.google.protobuf.ExtensionRegistryLite) throws com.google.protobuf.InvalidProtocolBufferException;
    Code:
       0: getstatic     #288                // Field PARSER:Lcom/google/protobuf/Parser;
       3: aload_0
       4: aload_1
       5: invokeinterface #317,  3          // InterfaceMethod com/google/protobuf/Parser.parseFrom:([BLcom/google/protobuf/ExtensionRegistryLite;)Ljava/lang/Object;
      10: checkcast     #2                  // class io/grpc/xds/shaded/io/envoyproxy/envoy/config/core/v3/Http1ProtocolOptions$HeaderKeyFormat
      13: areturn

  public static io.grpc.xds.shaded.io.envoyproxy.envoy.config.core.v3.Http1ProtocolOptions$HeaderKeyFormat parseFrom(java.io.InputStream) throws java.io.IOException;
    Code:
       0: getstatic     #288                // Field PARSER:Lcom/google/protobuf/Parser;
       3: aload_0
       4: invokestatic  #322                // Method com/google/protobuf/GeneratedMessageV3.parseWithIOException:(Lcom/google/protobuf/Parser;Ljava/io/InputStream;)Lcom/google/protobuf/Message;
       7: checkcast     #2                  // class io/grpc/xds/shaded/io/envoyproxy/envoy/config/core/v3/Http1ProtocolOptions$HeaderKeyFormat
      10: areturn

  public static io.grpc.xds.shaded.io.envoyproxy.envoy.config.core.v3.Http1ProtocolOptions$HeaderKeyFormat parseFrom(java.io.InputStream, com.google.protobuf.ExtensionRegistryLite) throws java.io.IOException;
    Code:
       0: getstatic     #288                // Field PARSER:Lcom/google/protobuf/Parser;
       3: aload_0
       4: aload_1
       5: invokestatic  #327                // Method com/google/protobuf/GeneratedMessageV3.parseWithIOException:(Lcom/google/protobuf/Parser;Ljava/io/InputStream;Lcom/google/protobuf/ExtensionRegistryLite;)Lcom/google/protobuf/Message;
       8: checkcast     #2                  // class io/grpc/xds/shaded/io/envoyproxy/envoy/config/core/v3/Http1ProtocolOptions$HeaderKeyFormat
      11: areturn

  public static io.grpc.xds.shaded.io.envoyproxy.envoy.config.core.v3.Http1ProtocolOptions$HeaderKeyFormat parseDelimitedFrom(java.io.InputStream) throws java.io.IOException;
    Code:
       0: getstatic     #288                // Field PARSER:Lcom/google/protobuf/Parser;
       3: aload_0
       4: invokestatic  #331                // Method com/google/protobuf/GeneratedMessageV3.parseDelimitedWithIOException:(Lcom/google/protobuf/Parser;Ljava/io/InputStream;)Lcom/google/protobuf/Message;
       7: checkcast     #2                  // class io/grpc/xds/shaded/io/envoyproxy/envoy/config/core/v3/Http1ProtocolOptions$HeaderKeyFormat
      10: areturn

  public static io.grpc.xds.shaded.io.envoyproxy.envoy.config.core.v3.Http1ProtocolOptions$HeaderKeyFormat parseDelimitedFrom(java.io.InputStream, com.google.protobuf.ExtensionRegistryLite) throws java.io.IOException;
    Code:
       0: getstatic     #288                // Field PARSER:Lcom/google/protobuf/Parser;
       3: aload_0
       4: aload_1
       5: invokestatic  #333                // Method com/google/protobuf/GeneratedMessageV3.parseDelimitedWithIOException:(Lcom/google/protobuf/Parser;Ljava/io/InputStream;Lcom/google/protobuf/ExtensionRegistryLite;)Lcom/google/protobuf/Message;
       8: checkcast     #2                  // class io/grpc/xds/shaded/io/envoyproxy/envoy/config/core/v3/Http1ProtocolOptions$HeaderKeyFormat
      11: areturn

  public static io.grpc.xds.shaded.io.envoyproxy.envoy.config.core.v3.Http1ProtocolOptions$HeaderKeyFormat parseFrom(com.google.protobuf.CodedInputStream) throws java.io.IOException;
    Code:
       0: getstatic     #288                // Field PARSER:Lcom/google/protobuf/Parser;
       3: aload_0
       4: invokestatic  #337                // Method com/google/protobuf/GeneratedMessageV3.parseWithIOException:(Lcom/google/protobuf/Parser;Lcom/google/protobuf/CodedInputStream;)Lcom/google/protobuf/Message;
       7: checkcast     #2                  // class io/grpc/xds/shaded/io/envoyproxy/envoy/config/core/v3/Http1ProtocolOptions$HeaderKeyFormat
      10: areturn

  public static io.grpc.xds.shaded.io.envoyproxy.envoy.config.core.v3.Http1ProtocolOptions$HeaderKeyFormat parseFrom(com.google.protobuf.CodedInputStream, com.google.protobuf.ExtensionRegistryLite) throws java.io.IOException;
    Code:
       0: getstatic     #288                // Field PARSER:Lcom/google/protobuf/Parser;
       3: aload_0
       4: aload_1
       5: invokestatic  #341                // Method com/google/protobuf/GeneratedMessageV3.parseWithIOException:(Lcom/google/protobuf/Parser;Lcom/google/protobuf/CodedInputStream;Lcom/google/protobuf/ExtensionRegistryLite;)Lcom/google/protobuf/Message;
       8: checkcast     #2                  // class io/grpc/xds/shaded/io/envoyproxy/envoy/config/core/v3/Http1ProtocolOptions$HeaderKeyFormat
      11: areturn

  public io.grpc.xds.shaded.io.envoyproxy.envoy.config.core.v3.Http1ProtocolOptions$HeaderKeyFormat$Builder newBuilderForType();
    Code:
       0: invokestatic  #345                // Method newBuilder:()Lio/grpc/xds/shaded/io/envoyproxy/envoy/config/core/v3/Http1ProtocolOptions$HeaderKeyFormat$Builder;
       3: areturn

  public static io.grpc.xds.shaded.io.envoyproxy.envoy.config.core.v3.Http1ProtocolOptions$HeaderKeyFormat$Builder newBuilder();
    Code:
       0: getstatic     #347                // Field DEFAULT_INSTANCE:Lio/grpc/xds/shaded/io/envoyproxy/envoy/config/core/v3/Http1ProtocolOptions$HeaderKeyFormat;
       3: invokevirtual #349                // Method toBuilder:()Lio/grpc/xds/shaded/io/envoyproxy/envoy/config/core/v3/Http1ProtocolOptions$HeaderKeyFormat$Builder;
       6: areturn

  public static io.grpc.xds.shaded.io.envoyproxy.envoy.config.core.v3.Http1ProtocolOptions$HeaderKeyFormat$Builder newBuilder(io.grpc.xds.shaded.io.envoyproxy.envoy.config.core.v3.Http1ProtocolOptions$HeaderKeyFormat);
    Code:
       0: getstatic     #347                // Field DEFAULT_INSTANCE:Lio/grpc/xds/shaded/io/envoyproxy/envoy/config/core/v3/Http1ProtocolOptions$HeaderKeyFormat;
       3: invokevirtual #349                // Method toBuilder:()Lio/grpc/xds/shaded/io/envoyproxy/envoy/config/core/v3/Http1ProtocolOptions$HeaderKeyFormat$Builder;
       6: aload_0
       7: invokevirtual #352                // Method io/grpc/xds/shaded/io/envoyproxy/envoy/config/core/v3/Http1ProtocolOptions$HeaderKeyFormat$Builder.mergeFrom:(Lio/grpc/xds/shaded/io/envoyproxy/envoy/config/core/v3/Http1ProtocolOptions$HeaderKeyFormat;)Lio/grpc/xds/shaded/io/envoyproxy/envoy/config/core/v3/Http1ProtocolOptions$HeaderKeyFormat$Builder;
      10: areturn

  public io.grpc.xds.shaded.io.envoyproxy.envoy.config.core.v3.Http1ProtocolOptions$HeaderKeyFormat$Builder toBuilder();
    Code:
       0: aload_0
       1: getstatic     #347                // Field DEFAULT_INSTANCE:Lio/grpc/xds/shaded/io/envoyproxy/envoy/config/core/v3/Http1ProtocolOptions$HeaderKeyFormat;
       4: if_acmpne     18
       7: new           #12                 // class io/grpc/xds/shaded/io/envoyproxy/envoy/config/core/v3/Http1ProtocolOptions$HeaderKeyFormat$Builder
      10: dup
      11: aconst_null
      12: invokespecial #356                // Method io/grpc/xds/shaded/io/envoyproxy/envoy/config/core/v3/Http1ProtocolOptions$HeaderKeyFormat$Builder."<init>":(Lio/grpc/xds/shaded/io/envoyproxy/envoy/config/core/v3/Http1ProtocolOptions$1;)V
      15: goto          30
      18: new           #12                 // class io/grpc/xds/shaded/io/envoyproxy/envoy/config/core/v3/Http1ProtocolOptions$HeaderKeyFormat$Builder
      21: dup
      22: aconst_null
      23: invokespecial #356                // Method io/grpc/xds/shaded/io/envoyproxy/envoy/config/core/v3/Http1ProtocolOptions$HeaderKeyFormat$Builder."<init>":(Lio/grpc/xds/shaded/io/envoyproxy/envoy/config/core/v3/Http1ProtocolOptions$1;)V
      26: aload_0
      27: invokevirtual #352                // Method io/grpc/xds/shaded/io/envoyproxy/envoy/config/core/v3/Http1ProtocolOptions$HeaderKeyFormat$Builder.mergeFrom:(Lio/grpc/xds/shaded/io/envoyproxy/envoy/config/core/v3/Http1ProtocolOptions$HeaderKeyFormat;)Lio/grpc/xds/shaded/io/envoyproxy/envoy/config/core/v3/Http1ProtocolOptions$HeaderKeyFormat$Builder;
      30: areturn

  protected io.grpc.xds.shaded.io.envoyproxy.envoy.config.core.v3.Http1ProtocolOptions$HeaderKeyFormat$Builder newBuilderForType(com.google.protobuf.GeneratedMessageV3$BuilderParent);
    Code:
       0: new           #12                 // class io/grpc/xds/shaded/io/envoyproxy/envoy/config/core/v3/Http1ProtocolOptions$HeaderKeyFormat$Builder
       3: dup
       4: aload_1
       5: aconst_null
       6: invokespecial #360                // Method io/grpc/xds/shaded/io/envoyproxy/envoy/config/core/v3/Http1ProtocolOptions$HeaderKeyFormat$Builder."<init>":(Lcom/google/protobuf/GeneratedMessageV3$BuilderParent;Lio/grpc/xds/shaded/io/envoyproxy/envoy/config/core/v3/Http1ProtocolOptions$1;)V
       9: astore_2
      10: aload_2
      11: areturn

  public static io.grpc.xds.shaded.io.envoyproxy.envoy.config.core.v3.Http1ProtocolOptions$HeaderKeyFormat getDefaultInstance();
    Code:
       0: getstatic     #347                // Field DEFAULT_INSTANCE:Lio/grpc/xds/shaded/io/envoyproxy/envoy/config/core/v3/Http1ProtocolOptions$HeaderKeyFormat;
       3: areturn

  public static com.google.protobuf.Parser<io.grpc.xds.shaded.io.envoyproxy.envoy.config.core.v3.Http1ProtocolOptions$HeaderKeyFormat> parser();
    Code:
       0: getstatic     #288                // Field PARSER:Lcom/google/protobuf/Parser;
       3: areturn

  public com.google.protobuf.Parser<io.grpc.xds.shaded.io.envoyproxy.envoy.config.core.v3.Http1ProtocolOptions$HeaderKeyFormat> getParserForType();
    Code:
       0: getstatic     #288                // Field PARSER:Lcom/google/protobuf/Parser;
       3: areturn

  public io.grpc.xds.shaded.io.envoyproxy.envoy.config.core.v3.Http1ProtocolOptions$HeaderKeyFormat getDefaultInstanceForType();
    Code:
       0: getstatic     #347                // Field DEFAULT_INSTANCE:Lio/grpc/xds/shaded/io/envoyproxy/envoy/config/core/v3/Http1ProtocolOptions$HeaderKeyFormat;
       3: areturn

  protected com.google.protobuf.Message$Builder newBuilderForType(com.google.protobuf.GeneratedMessageV3$BuilderParent);
    Code:
       0: aload_0
       1: aload_1
       2: invokevirtual #370                // Method newBuilderForType:(Lcom/google/protobuf/GeneratedMessageV3$BuilderParent;)Lio/grpc/xds/shaded/io/envoyproxy/envoy/config/core/v3/Http1ProtocolOptions$HeaderKeyFormat$Builder;
       5: areturn

  public com.google.protobuf.Message$Builder toBuilder();
    Code:
       0: aload_0
       1: invokevirtual #349                // Method toBuilder:()Lio/grpc/xds/shaded/io/envoyproxy/envoy/config/core/v3/Http1ProtocolOptions$HeaderKeyFormat$Builder;
       4: areturn

  public com.google.protobuf.Message$Builder newBuilderForType();
    Code:
       0: aload_0
       1: invokevirtual #373                // Method newBuilderForType:()Lio/grpc/xds/shaded/io/envoyproxy/envoy/config/core/v3/Http1ProtocolOptions$HeaderKeyFormat$Builder;
       4: areturn

  public com.google.protobuf.MessageLite$Builder toBuilder();
    Code:
       0: aload_0
       1: invokevirtual #349                // Method toBuilder:()Lio/grpc/xds/shaded/io/envoyproxy/envoy/config/core/v3/Http1ProtocolOptions$HeaderKeyFormat$Builder;
       4: areturn

  public com.google.protobuf.MessageLite$Builder newBuilderForType();
    Code:
       0: aload_0
       1: invokevirtual #373                // Method newBuilderForType:()Lio/grpc/xds/shaded/io/envoyproxy/envoy/config/core/v3/Http1ProtocolOptions$HeaderKeyFormat$Builder;
       4: areturn

  public com.google.protobuf.MessageLite getDefaultInstanceForType();
    Code:
       0: aload_0
       1: invokevirtual #377                // Method getDefaultInstanceForType:()Lio/grpc/xds/shaded/io/envoyproxy/envoy/config/core/v3/Http1ProtocolOptions$HeaderKeyFormat;
       4: areturn

  public com.google.protobuf.Message getDefaultInstanceForType();
    Code:
       0: aload_0
       1: invokevirtual #377                // Method getDefaultInstanceForType:()Lio/grpc/xds/shaded/io/envoyproxy/envoy/config/core/v3/Http1ProtocolOptions$HeaderKeyFormat;
       4: areturn

  static boolean access$900();
    Code:
       0: getstatic     #382                // Field alwaysUseFieldBuilders:Z
       3: ireturn

  io.grpc.xds.shaded.io.envoyproxy.envoy.config.core.v3.Http1ProtocolOptions$HeaderKeyFormat(com.google.protobuf.GeneratedMessageV3$Builder, io.grpc.xds.shaded.io.envoyproxy.envoy.config.core.v3.Http1ProtocolOptions$1);
    Code:
       0: aload_0
       1: aload_1
       2: invokespecial #384                // Method "<init>":(Lcom/google/protobuf/GeneratedMessageV3$Builder;)V
       5: return

  static java.lang.Object access$1102(io.grpc.xds.shaded.io.envoyproxy.envoy.config.core.v3.Http1ProtocolOptions$HeaderKeyFormat, java.lang.Object);
    Code:
       0: aload_0
       1: aload_1
       2: dup_x1
       3: putfield      #129                // Field headerFormat_:Ljava/lang/Object;
       6: areturn

  static int access$1202(io.grpc.xds.shaded.io.envoyproxy.envoy.config.core.v3.Http1ProtocolOptions$HeaderKeyFormat, int);
    Code:
       0: aload_0
       1: iload_1
       2: dup_x1
       3: putfield      #87                 // Field headerFormatCase_:I
       6: ireturn

  static com.google.protobuf.UnknownFieldSet access$1300(io.grpc.xds.shaded.io.envoyproxy.envoy.config.core.v3.Http1ProtocolOptions$HeaderKeyFormat);
    Code:
       0: aload_0
       1: getfield      #107                // Field unknownFields:Lcom/google/protobuf/UnknownFieldSet;
       4: areturn

  static com.google.protobuf.Parser access$1400();
    Code:
       0: getstatic     #288                // Field PARSER:Lcom/google/protobuf/Parser;
       3: areturn

  io.grpc.xds.shaded.io.envoyproxy.envoy.config.core.v3.Http1ProtocolOptions$HeaderKeyFormat(com.google.protobuf.CodedInputStream, com.google.protobuf.ExtensionRegistryLite, io.grpc.xds.shaded.io.envoyproxy.envoy.config.core.v3.Http1ProtocolOptions$1) throws com.google.protobuf.InvalidProtocolBufferException;
    Code:
       0: aload_0
       1: aload_1
       2: aload_2
       3: invokespecial #397                // Method "<init>":(Lcom/google/protobuf/CodedInputStream;Lcom/google/protobuf/ExtensionRegistryLite;)V
       6: return

  static {};
    Code:
       0: new           #2                  // class io/grpc/xds/shaded/io/envoyproxy/envoy/config/core/v3/Http1ProtocolOptions$HeaderKeyFormat
       3: dup
       4: invokespecial #99                 // Method "<init>":()V
       7: putstatic     #347                // Field DEFAULT_INSTANCE:Lio/grpc/xds/shaded/io/envoyproxy/envoy/config/core/v3/Http1ProtocolOptions$HeaderKeyFormat;
      10: new           #24                 // class io/grpc/xds/shaded/io/envoyproxy/envoy/config/core/v3/Http1ProtocolOptions$HeaderKeyFormat$1
      13: dup
      14: invokespecial #400                // Method io/grpc/xds/shaded/io/envoyproxy/envoy/config/core/v3/Http1ProtocolOptions$HeaderKeyFormat$1."<init>":()V
      17: putstatic     #288                // Field PARSER:Lcom/google/protobuf/Parser;
      20: return
}
