Compiled from "DynamicMessage.java"
class akka.protobuf.DynamicMessage$1 extends akka.protobuf.AbstractParser<akka.protobuf.DynamicMessage> {
  final akka.protobuf.DynamicMessage this$0;

  akka.protobuf.DynamicMessage$1(akka.protobuf.DynamicMessage);
    Code:
       0: aload_0
       1: aload_1
       2: putfield      #1                  // Field this$0:Lakka/protobuf/DynamicMessage;
       5: aload_0
       6: invokespecial #2                  // Method akka/protobuf/AbstractParser."<init>":()V
       9: return

  public akka.protobuf.DynamicMessage parsePartialFrom(akka.protobuf.CodedInputStream, akka.protobuf.ExtensionRegistryLite) throws akka.protobuf.InvalidProtocolBufferException;
    Code:
       0: aload_0
       1: getfield      #1                  // Field this$0:Lakka/protobuf/DynamicMessage;
       4: invokestatic  #3                  // Method akka/protobuf/DynamicMessage.access$200:(Lakka/protobuf/DynamicMessage;)Lakka/protobuf/Descriptors$Descriptor;
       7: invokestatic  #4                  // Method akka/protobuf/DynamicMessage.newBuilder:(Lakka/protobuf/Descriptors$Descriptor;)Lakka/protobuf/DynamicMessage$Builder;
      10: astore_3
      11: aload_3
      12: aload_1
      13: aload_2
      14: invokevirtual #5                  // Method akka/protobuf/DynamicMessage$Builder.mergeFrom:(Lakka/protobuf/CodedInputStream;Lakka/protobuf/ExtensionRegistryLite;)Lakka/protobuf/AbstractMessage$Builder;
      17: pop
      18: goto          55
      21: astore        4
      23: aload         4
      25: aload_3
      26: invokevirtual #7                  // Method akka/protobuf/DynamicMessage$Builder.buildPartial:()Lakka/protobuf/DynamicMessage;
      29: invokevirtual #8                  // Method akka/protobuf/InvalidProtocolBufferException.setUnfinishedMessage:(Lakka/protobuf/MessageLite;)Lakka/protobuf/InvalidProtocolBufferException;
      32: athrow
      33: astore        4
      35: new           #6                  // class akka/protobuf/InvalidProtocolBufferException
      38: dup
      39: aload         4
      41: invokevirtual #10                 // Method java/io/IOException.getMessage:()Ljava/lang/String;
      44: invokespecial #11                 // Method akka/protobuf/InvalidProtocolBufferException."<init>":(Ljava/lang/String;)V
      47: aload_3
      48: invokevirtual #7                  // Method akka/protobuf/DynamicMessage$Builder.buildPartial:()Lakka/protobuf/DynamicMessage;
      51: invokevirtual #8                  // Method akka/protobuf/InvalidProtocolBufferException.setUnfinishedMessage:(Lakka/protobuf/MessageLite;)Lakka/protobuf/InvalidProtocolBufferException;
      54: athrow
      55: aload_3
      56: invokevirtual #7                  // Method akka/protobuf/DynamicMessage$Builder.buildPartial:()Lakka/protobuf/DynamicMessage;
      59: areturn
    Exception table:
       from    to  target type
          11    18    21   Class akka/protobuf/InvalidProtocolBufferException
          11    18    33   Class java/io/IOException

  public java.lang.Object parsePartialFrom(akka.protobuf.CodedInputStream, akka.protobuf.ExtensionRegistryLite) throws akka.protobuf.InvalidProtocolBufferException;
    Code:
       0: aload_0
       1: aload_1
       2: aload_2
       3: invokevirtual #12                 // Method parsePartialFrom:(Lakka/protobuf/CodedInputStream;Lakka/protobuf/ExtensionRegistryLite;)Lakka/protobuf/DynamicMessage;
       6: areturn
}
