Compiled from "GeneratedMessage.java"
class akka.protobuf.GeneratedMessage$GeneratedExtension$1 implements akka.protobuf.GeneratedMessage$ExtensionDescriptorRetriever {
  final akka.protobuf.Descriptors$FieldDescriptor val$descriptor;

  final akka.protobuf.GeneratedMessage$GeneratedExtension this$0;

  akka.protobuf.GeneratedMessage$GeneratedExtension$1(akka.protobuf.GeneratedMessage$GeneratedExtension, akka.protobuf.Descriptors$FieldDescriptor);
    Code:
       0: aload_0
       1: aload_1
       2: putfield      #1                  // Field this$0:Lakka/protobuf/GeneratedMessage$GeneratedExtension;
       5: aload_0
       6: aload_2
       7: putfield      #2                  // Field val$descriptor:Lakka/protobuf/Descriptors$FieldDescriptor;
      10: aload_0
      11: invokespecial #3                  // Method java/lang/Object."<init>":()V
      14: return

  public akka.protobuf.Descriptors$FieldDescriptor getDescriptor();
    Code:
       0: aload_0
       1: getfield      #2                  // Field val$descriptor:Lakka/protobuf/Descriptors$FieldDescriptor;
       4: areturn
}
