Compiled from "Message.java"
public interface akka.protobuf.Message$Builder extends akka.protobuf.MessageLite$Builder,akka.protobuf.MessageOrBuilder {
  public abstract akka.protobuf.Message$Builder clear();

  public abstract akka.protobuf.Message$Builder mergeFrom(akka.protobuf.Message);

  public abstract akka.protobuf.Message build();

  public abstract akka.protobuf.Message buildPartial();

  public abstract akka.protobuf.Message$Builder clone();

  public abstract akka.protobuf.Message$Builder mergeFrom(akka.protobuf.CodedInputStream) throws java.io.IOException;

  public abstract akka.protobuf.Message$Builder mergeFrom(akka.protobuf.CodedInputStream, akka.protobuf.ExtensionRegistryLite) throws java.io.IOException;

  public abstract akka.protobuf.Descriptors$Descriptor getDescriptorForType();

  public abstract akka.protobuf.Message$Builder newBuilderForField(akka.protobuf.Descriptors$FieldDescriptor);

  public abstract akka.protobuf.Message$Builder getFieldBuilder(akka.protobuf.Descriptors$FieldDescriptor);

  public abstract akka.protobuf.Message$Builder setField(akka.protobuf.Descriptors$FieldDescriptor, java.lang.Object);

  public abstract akka.protobuf.Message$Builder clearField(akka.protobuf.Descriptors$FieldDescriptor);

  public abstract akka.protobuf.Message$Builder setRepeatedField(akka.protobuf.Descriptors$FieldDescriptor, int, java.lang.Object);

  public abstract akka.protobuf.Message$Builder addRepeatedField(akka.protobuf.Descriptors$FieldDescriptor, java.lang.Object);

  public abstract akka.protobuf.Message$Builder setUnknownFields(akka.protobuf.UnknownFieldSet);

  public abstract akka.protobuf.Message$Builder mergeUnknownFields(akka.protobuf.UnknownFieldSet);

  public abstract akka.protobuf.Message$Builder mergeFrom(akka.protobuf.ByteString) throws akka.protobuf.InvalidProtocolBufferException;

  public abstract akka.protobuf.Message$Builder mergeFrom(akka.protobuf.ByteString, akka.protobuf.ExtensionRegistryLite) throws akka.protobuf.InvalidProtocolBufferException;

  public abstract akka.protobuf.Message$Builder mergeFrom(byte[]) throws akka.protobuf.InvalidProtocolBufferException;

  public abstract akka.protobuf.Message$Builder mergeFrom(byte[], int, int) throws akka.protobuf.InvalidProtocolBufferException;

  public abstract akka.protobuf.Message$Builder mergeFrom(byte[], akka.protobuf.ExtensionRegistryLite) throws akka.protobuf.InvalidProtocolBufferException;

  public abstract akka.protobuf.Message$Builder mergeFrom(byte[], int, int, akka.protobuf.ExtensionRegistryLite) throws akka.protobuf.InvalidProtocolBufferException;

  public abstract akka.protobuf.Message$Builder mergeFrom(java.io.InputStream) throws java.io.IOException;

  public abstract akka.protobuf.Message$Builder mergeFrom(java.io.InputStream, akka.protobuf.ExtensionRegistryLite) throws java.io.IOException;

  public abstract boolean mergeDelimitedFrom(java.io.InputStream) throws java.io.IOException;

  public abstract boolean mergeDelimitedFrom(java.io.InputStream, akka.protobuf.ExtensionRegistryLite) throws java.io.IOException;

  public default akka.protobuf.MessageLite$Builder mergeFrom(java.io.InputStream, akka.protobuf.ExtensionRegistryLite) throws java.io.IOException;
    Code:
       0: aload_0
       1: aload_1
       2: aload_2
       3: invokeinterface #1,  3            // InterfaceMethod mergeFrom:(Ljava/io/InputStream;Lakka/protobuf/ExtensionRegistryLite;)Lakka/protobuf/Message$Builder;
       8: areturn

  public default akka.protobuf.MessageLite$Builder mergeFrom(java.io.InputStream) throws java.io.IOException;
    Code:
       0: aload_0
       1: aload_1
       2: invokeinterface #2,  2            // InterfaceMethod mergeFrom:(Ljava/io/InputStream;)Lakka/protobuf/Message$Builder;
       7: areturn

  public default akka.protobuf.MessageLite$Builder mergeFrom(byte[], int, int, akka.protobuf.ExtensionRegistryLite) throws akka.protobuf.InvalidProtocolBufferException;
    Code:
       0: aload_0
       1: aload_1
       2: iload_2
       3: iload_3
       4: aload         4
       6: invokeinterface #3,  5            // InterfaceMethod mergeFrom:([BIILakka/protobuf/ExtensionRegistryLite;)Lakka/protobuf/Message$Builder;
      11: areturn

  public default akka.protobuf.MessageLite$Builder mergeFrom(byte[], akka.protobuf.ExtensionRegistryLite) throws akka.protobuf.InvalidProtocolBufferException;
    Code:
       0: aload_0
       1: aload_1
       2: aload_2
       3: invokeinterface #4,  3            // InterfaceMethod mergeFrom:([BLakka/protobuf/ExtensionRegistryLite;)Lakka/protobuf/Message$Builder;
       8: areturn

  public default akka.protobuf.MessageLite$Builder mergeFrom(byte[], int, int) throws akka.protobuf.InvalidProtocolBufferException;
    Code:
       0: aload_0
       1: aload_1
       2: iload_2
       3: iload_3
       4: invokeinterface #5,  4            // InterfaceMethod mergeFrom:([BII)Lakka/protobuf/Message$Builder;
       9: areturn

  public default akka.protobuf.MessageLite$Builder mergeFrom(byte[]) throws akka.protobuf.InvalidProtocolBufferException;
    Code:
       0: aload_0
       1: aload_1
       2: invokeinterface #6,  2            // InterfaceMethod mergeFrom:([B)Lakka/protobuf/Message$Builder;
       7: areturn

  public default akka.protobuf.MessageLite$Builder mergeFrom(akka.protobuf.ByteString, akka.protobuf.ExtensionRegistryLite) throws akka.protobuf.InvalidProtocolBufferException;
    Code:
       0: aload_0
       1: aload_1
       2: aload_2
       3: invokeinterface #7,  3            // InterfaceMethod mergeFrom:(Lakka/protobuf/ByteString;Lakka/protobuf/ExtensionRegistryLite;)Lakka/protobuf/Message$Builder;
       8: areturn

  public default akka.protobuf.MessageLite$Builder mergeFrom(akka.protobuf.ByteString) throws akka.protobuf.InvalidProtocolBufferException;
    Code:
       0: aload_0
       1: aload_1
       2: invokeinterface #8,  2            // InterfaceMethod mergeFrom:(Lakka/protobuf/ByteString;)Lakka/protobuf/Message$Builder;
       7: areturn

  public default akka.protobuf.MessageLite$Builder mergeFrom(akka.protobuf.CodedInputStream, akka.protobuf.ExtensionRegistryLite) throws java.io.IOException;
    Code:
       0: aload_0
       1: aload_1
       2: aload_2
       3: invokeinterface #9,  3            // InterfaceMethod mergeFrom:(Lakka/protobuf/CodedInputStream;Lakka/protobuf/ExtensionRegistryLite;)Lakka/protobuf/Message$Builder;
       8: areturn

  public default akka.protobuf.MessageLite$Builder mergeFrom(akka.protobuf.CodedInputStream) throws java.io.IOException;
    Code:
       0: aload_0
       1: aload_1
       2: invokeinterface #10,  2           // InterfaceMethod mergeFrom:(Lakka/protobuf/CodedInputStream;)Lakka/protobuf/Message$Builder;
       7: areturn

  public default akka.protobuf.MessageLite$Builder clone();
    Code:
       0: aload_0
       1: invokeinterface #11,  1           // InterfaceMethod clone:()Lakka/protobuf/Message$Builder;
       6: areturn

  public default akka.protobuf.MessageLite buildPartial();
    Code:
       0: aload_0
       1: invokeinterface #12,  1           // InterfaceMethod buildPartial:()Lakka/protobuf/Message;
       6: areturn

  public default akka.protobuf.MessageLite build();
    Code:
       0: aload_0
       1: invokeinterface #13,  1           // InterfaceMethod build:()Lakka/protobuf/Message;
       6: areturn

  public default akka.protobuf.MessageLite$Builder clear();
    Code:
       0: aload_0
       1: invokeinterface #14,  1           // InterfaceMethod clear:()Lakka/protobuf/Message$Builder;
       6: areturn
}
