Compiled from "MaintenanceOptions.kt"
public final class io.vertx.kotlin.ext.consul.MaintenanceOptionsKt {
  public static final io.vertx.ext.consul.MaintenanceOptions maintenanceOptionsOf(java.lang.Boolean, java.lang.String, java.lang.String);
    Code:
       0: new           #10                 // class io/vertx/ext/consul/MaintenanceOptions
       3: dup
       4: invokespecial #14                 // Method io/vertx/ext/consul/MaintenanceOptions."<init>":()V
       7: astore_3
       8: iconst_0
       9: istore        4
      11: iconst_0
      12: istore        5
      14: aload_3
      15: astore        6
      17: iconst_0
      18: istore        7
      20: aload_0
      21: ifnull        34
      24: aload         6
      26: aload_0
      27: invokevirtual #20                 // Method java/lang/Boolean.booleanValue:()Z
      30: invokevirtual #24                 // Method io/vertx/ext/consul/MaintenanceOptions.setEnable:(Z)Lio/vertx/ext/consul/MaintenanceOptions;
      33: pop
      34: aload_1
      35: ifnull        45
      38: aload         6
      40: aload_1
      41: invokevirtual #28                 // Method io/vertx/ext/consul/MaintenanceOptions.setId:(Ljava/lang/String;)Lio/vertx/ext/consul/MaintenanceOptions;
      44: pop
      45: aload_2
      46: ifnull        56
      49: aload         6
      51: aload_2
      52: invokevirtual #31                 // Method io/vertx/ext/consul/MaintenanceOptions.setReason:(Ljava/lang/String;)Lio/vertx/ext/consul/MaintenanceOptions;
      55: pop
      56: nop
      57: aload_3
      58: areturn

  public static io.vertx.ext.consul.MaintenanceOptions maintenanceOptionsOf$default(java.lang.Boolean, java.lang.String, java.lang.String, int, java.lang.Object);
    Code:
       0: iload_3
       1: iconst_1
       2: iand
       3: ifeq          11
       6: aconst_null
       7: checkcast     #16                 // class java/lang/Boolean
      10: astore_0
      11: iload_3
      12: iconst_2
      13: iand
      14: ifeq          22
      17: aconst_null
      18: checkcast     #42                 // class java/lang/String
      21: astore_1
      22: iload_3
      23: iconst_4
      24: iand
      25: ifeq          33
      28: aconst_null
      29: checkcast     #42                 // class java/lang/String
      32: astore_2
      33: aload_0
      34: aload_1
      35: aload_2
      36: invokestatic  #46                 // Method maintenanceOptionsOf:(Ljava/lang/Boolean;Ljava/lang/String;Ljava/lang/String;)Lio/vertx/ext/consul/MaintenanceOptions;
      39: areturn

  public static final io.vertx.ext.consul.MaintenanceOptions MaintenanceOptions(java.lang.Boolean, java.lang.String, java.lang.String);
    Code:
       0: new           #10                 // class io/vertx/ext/consul/MaintenanceOptions
       3: dup
       4: invokespecial #14                 // Method io/vertx/ext/consul/MaintenanceOptions."<init>":()V
       7: astore_3
       8: iconst_0
       9: istore        4
      11: iconst_0
      12: istore        5
      14: aload_3
      15: astore        6
      17: iconst_0
      18: istore        7
      20: aload_0
      21: ifnull        34
      24: aload         6
      26: aload_0
      27: invokevirtual #20                 // Method java/lang/Boolean.booleanValue:()Z
      30: invokevirtual #24                 // Method io/vertx/ext/consul/MaintenanceOptions.setEnable:(Z)Lio/vertx/ext/consul/MaintenanceOptions;
      33: pop
      34: aload_1
      35: ifnull        45
      38: aload         6
      40: aload_1
      41: invokevirtual #28                 // Method io/vertx/ext/consul/MaintenanceOptions.setId:(Ljava/lang/String;)Lio/vertx/ext/consul/MaintenanceOptions;
      44: pop
      45: aload_2
      46: ifnull        56
      49: aload         6
      51: aload_2
      52: invokevirtual #31                 // Method io/vertx/ext/consul/MaintenanceOptions.setReason:(Ljava/lang/String;)Lio/vertx/ext/consul/MaintenanceOptions;
      55: pop
      56: nop
      57: aload_3
      58: areturn

  public static io.vertx.ext.consul.MaintenanceOptions MaintenanceOptions$default(java.lang.Boolean, java.lang.String, java.lang.String, int, java.lang.Object);
    Code:
       0: iload_3
       1: iconst_1
       2: iand
       3: ifeq          11
       6: aconst_null
       7: checkcast     #16                 // class java/lang/Boolean
      10: astore_0
      11: iload_3
      12: iconst_2
      13: iand
      14: ifeq          22
      17: aconst_null
      18: checkcast     #42                 // class java/lang/String
      21: astore_1
      22: iload_3
      23: iconst_4
      24: iand
      25: ifeq          33
      28: aconst_null
      29: checkcast     #42                 // class java/lang/String
      32: astore_2
      33: aload_0
      34: aload_1
      35: aload_2
      36: invokestatic  #59                 // Method MaintenanceOptions:(Ljava/lang/Boolean;Ljava/lang/String;Ljava/lang/String;)Lio/vertx/ext/consul/MaintenanceOptions;
      39: areturn
}
