Compiled from "Session.kt"
public final class io.vertx.kotlin.ext.consul.SessionKt {
  public static final io.vertx.ext.consul.Session sessionOf(java.lang.Iterable<java.lang.String>, java.lang.Long, java.lang.String, java.lang.Long, java.lang.Long, java.lang.String);
    Code:
       0: new           #11                 // class io/vertx/ext/consul/Session
       3: dup
       4: invokespecial #15                 // Method io/vertx/ext/consul/Session."<init>":()V
       7: astore        6
       9: iconst_0
      10: istore        7
      12: iconst_0
      13: istore        8
      15: aload         6
      17: astore        9
      19: iconst_0
      20: istore        10
      22: aload_0
      23: ifnull        36
      26: aload         9
      28: aload_0
      29: invokestatic  #21                 // Method kotlin/collections/CollectionsKt.toList:(Ljava/lang/Iterable;)Ljava/util/List;
      32: invokevirtual #25                 // Method io/vertx/ext/consul/Session.setChecks:(Ljava/util/List;)Lio/vertx/ext/consul/Session;
      35: pop
      36: aload_1
      37: ifnull        50
      40: aload         9
      42: aload_1
      43: invokevirtual #31                 // Method java/lang/Long.longValue:()J
      46: invokevirtual #35                 // Method io/vertx/ext/consul/Session.setCreateIndex:(J)Lio/vertx/ext/consul/Session;
      49: pop
      50: aload_2
      51: ifnull        61
      54: aload         9
      56: aload_2
      57: invokevirtual #39                 // Method io/vertx/ext/consul/Session.setId:(Ljava/lang/String;)Lio/vertx/ext/consul/Session;
      60: pop
      61: aload_3
      62: ifnull        75
      65: aload         9
      67: aload_3
      68: invokevirtual #31                 // Method java/lang/Long.longValue:()J
      71: invokevirtual #42                 // Method io/vertx/ext/consul/Session.setIndex:(J)Lio/vertx/ext/consul/Session;
      74: pop
      75: aload         4
      77: ifnull        91
      80: aload         9
      82: aload         4
      84: invokevirtual #31                 // Method java/lang/Long.longValue:()J
      87: invokevirtual #45                 // Method io/vertx/ext/consul/Session.setLockDelay:(J)Lio/vertx/ext/consul/Session;
      90: pop
      91: aload         5
      93: ifnull        104
      96: aload         9
      98: aload         5
     100: invokevirtual #48                 // Method io/vertx/ext/consul/Session.setNode:(Ljava/lang/String;)Lio/vertx/ext/consul/Session;
     103: pop
     104: nop
     105: aload         6
     107: areturn

  public static io.vertx.ext.consul.Session sessionOf$default(java.lang.Iterable, java.lang.Long, java.lang.String, java.lang.Long, java.lang.Long, java.lang.String, int, java.lang.Object);
    Code:
       0: iload         6
       2: iconst_1
       3: iand
       4: ifeq          12
       7: aconst_null
       8: checkcast     #63                 // class java/lang/Iterable
      11: astore_0
      12: iload         6
      14: iconst_2
      15: iand
      16: ifeq          24
      19: aconst_null
      20: checkcast     #27                 // class java/lang/Long
      23: astore_1
      24: iload         6
      26: iconst_4
      27: iand
      28: ifeq          36
      31: aconst_null
      32: checkcast     #65                 // class java/lang/String
      35: astore_2
      36: iload         6
      38: bipush        8
      40: iand
      41: ifeq          49
      44: aconst_null
      45: checkcast     #27                 // class java/lang/Long
      48: astore_3
      49: iload         6
      51: bipush        16
      53: iand
      54: ifeq          63
      57: aconst_null
      58: checkcast     #27                 // class java/lang/Long
      61: astore        4
      63: iload         6
      65: bipush        32
      67: iand
      68: ifeq          77
      71: aconst_null
      72: checkcast     #65                 // class java/lang/String
      75: astore        5
      77: aload_0
      78: aload_1
      79: aload_2
      80: aload_3
      81: aload         4
      83: aload         5
      85: invokestatic  #69                 // Method sessionOf:(Ljava/lang/Iterable;Ljava/lang/Long;Ljava/lang/String;Ljava/lang/Long;Ljava/lang/Long;Ljava/lang/String;)Lio/vertx/ext/consul/Session;
      88: areturn

  public static final io.vertx.ext.consul.Session Session(java.lang.Iterable<java.lang.String>, java.lang.Long, java.lang.String, java.lang.Long, java.lang.Long, java.lang.String);
    Code:
       0: new           #11                 // class io/vertx/ext/consul/Session
       3: dup
       4: invokespecial #15                 // Method io/vertx/ext/consul/Session."<init>":()V
       7: astore        6
       9: iconst_0
      10: istore        7
      12: iconst_0
      13: istore        8
      15: aload         6
      17: astore        9
      19: iconst_0
      20: istore        10
      22: aload_0
      23: ifnull        36
      26: aload         9
      28: aload_0
      29: invokestatic  #21                 // Method kotlin/collections/CollectionsKt.toList:(Ljava/lang/Iterable;)Ljava/util/List;
      32: invokevirtual #25                 // Method io/vertx/ext/consul/Session.setChecks:(Ljava/util/List;)Lio/vertx/ext/consul/Session;
      35: pop
      36: aload_1
      37: ifnull        50
      40: aload         9
      42: aload_1
      43: invokevirtual #31                 // Method java/lang/Long.longValue:()J
      46: invokevirtual #35                 // Method io/vertx/ext/consul/Session.setCreateIndex:(J)Lio/vertx/ext/consul/Session;
      49: pop
      50: aload_2
      51: ifnull        61
      54: aload         9
      56: aload_2
      57: invokevirtual #39                 // Method io/vertx/ext/consul/Session.setId:(Ljava/lang/String;)Lio/vertx/ext/consul/Session;
      60: pop
      61: aload_3
      62: ifnull        75
      65: aload         9
      67: aload_3
      68: invokevirtual #31                 // Method java/lang/Long.longValue:()J
      71: invokevirtual #42                 // Method io/vertx/ext/consul/Session.setIndex:(J)Lio/vertx/ext/consul/Session;
      74: pop
      75: aload         4
      77: ifnull        91
      80: aload         9
      82: aload         4
      84: invokevirtual #31                 // Method java/lang/Long.longValue:()J
      87: invokevirtual #45                 // Method io/vertx/ext/consul/Session.setLockDelay:(J)Lio/vertx/ext/consul/Session;
      90: pop
      91: aload         5
      93: ifnull        104
      96: aload         9
      98: aload         5
     100: invokevirtual #48                 // Method io/vertx/ext/consul/Session.setNode:(Ljava/lang/String;)Lio/vertx/ext/consul/Session;
     103: pop
     104: nop
     105: aload         6
     107: areturn

  public static io.vertx.ext.consul.Session Session$default(java.lang.Iterable, java.lang.Long, java.lang.String, java.lang.Long, java.lang.Long, java.lang.String, int, java.lang.Object);
    Code:
       0: iload         6
       2: iconst_1
       3: iand
       4: ifeq          12
       7: aconst_null
       8: checkcast     #63                 // class java/lang/Iterable
      11: astore_0
      12: iload         6
      14: iconst_2
      15: iand
      16: ifeq          24
      19: aconst_null
      20: checkcast     #27                 // class java/lang/Long
      23: astore_1
      24: iload         6
      26: iconst_4
      27: iand
      28: ifeq          36
      31: aconst_null
      32: checkcast     #65                 // class java/lang/String
      35: astore_2
      36: iload         6
      38: bipush        8
      40: iand
      41: ifeq          49
      44: aconst_null
      45: checkcast     #27                 // class java/lang/Long
      48: astore_3
      49: iload         6
      51: bipush        16
      53: iand
      54: ifeq          63
      57: aconst_null
      58: checkcast     #27                 // class java/lang/Long
      61: astore        4
      63: iload         6
      65: bipush        32
      67: iand
      68: ifeq          77
      71: aconst_null
      72: checkcast     #65                 // class java/lang/String
      75: astore        5
      77: aload_0
      78: aload_1
      79: aload_2
      80: aload_3
      81: aload         4
      83: aload         5
      85: invokestatic  #82                 // Method Session:(Ljava/lang/Iterable;Ljava/lang/Long;Ljava/lang/String;Ljava/lang/Long;Ljava/lang/Long;Ljava/lang/String;)Lio/vertx/ext/consul/Session;
      88: areturn
}
