Compiled from "RoutesCollector.java"
public class org.apache.camel.spring.boot.RoutesCollector implements org.springframework.context.ApplicationListener<org.springframework.context.event.ContextRefreshedEvent> {
  private static final org.slf4j.Logger LOG;

  private final org.springframework.context.ApplicationContext applicationContext;

  private final java.util.List<org.apache.camel.spring.boot.CamelContextConfiguration> camelContextConfigurations;

  private final org.apache.camel.spring.boot.CamelConfigurationProperties configurationProperties;

  public org.apache.camel.spring.boot.RoutesCollector(org.springframework.context.ApplicationContext, java.util.List<org.apache.camel.spring.boot.CamelContextConfiguration>, org.apache.camel.spring.boot.CamelConfigurationProperties);
    Code:
       0: aload_0
       1: invokespecial #1                  // Method java/lang/Object."<init>":()V
       4: aload_0
       5: aload_1
       6: putfield      #2                  // Field applicationContext:Lorg/springframework/context/ApplicationContext;
       9: aload_0
      10: new           #3                  // class java/util/ArrayList
      13: dup
      14: aload_2
      15: invokespecial #4                  // Method java/util/ArrayList."<init>":(Ljava/util/Collection;)V
      18: putfield      #5                  // Field camelContextConfigurations:Ljava/util/List;
      21: aload_0
      22: aload_3
      23: putfield      #6                  // Field configurationProperties:Lorg/apache/camel/spring/boot/CamelConfigurationProperties;
      26: return

  public void onApplicationEvent(org.springframework.context.event.ContextRefreshedEvent);
    Code:
       0: aload_1
       1: invokevirtual #7                  // Method org/springframework/context/event/ContextRefreshedEvent.getApplicationContext:()Lorg/springframework/context/ApplicationContext;
       4: astore_2
       5: aload_0
       6: getfield      #2                  // Field applicationContext:Lorg/springframework/context/ApplicationContext;
       9: aload_2
      10: invokevirtual #8                  // Method java/lang/Object.equals:(Ljava/lang/Object;)Z
      13: ifeq          438
      16: aload_1
      17: invokevirtual #7                  // Method org/springframework/context/event/ContextRefreshedEvent.getApplicationContext:()Lorg/springframework/context/ApplicationContext;
      20: ldc           #9                  // class org/apache/camel/CamelContext
      22: invokeinterface #10,  2           // InterfaceMethod org/springframework/context/ApplicationContext.getBean:(Ljava/lang/Class;)Ljava/lang/Object;
      27: checkcast     #9                  // class org/apache/camel/CamelContext
      30: astore_3
      31: aload_3
      32: invokeinterface #11,  1           // InterfaceMethod org/apache/camel/CamelContext.getStatus:()Lorg/apache/camel/ServiceStatus;
      37: invokevirtual #12                 // Method org/apache/camel/ServiceStatus.isStopped:()Z
      40: ifeq          425
      43: getstatic     #13                 // Field LOG:Lorg/slf4j/Logger;
      46: ldc           #14                 // String Post-processing CamelContext bean: {}
      48: aload_3
      49: invokeinterface #15,  1           // InterfaceMethod org/apache/camel/CamelContext.getName:()Ljava/lang/String;
      54: invokeinterface #16,  3           // InterfaceMethod org/slf4j/Logger.debug:(Ljava/lang/String;Ljava/lang/Object;)V
      59: aload_2
      60: ldc           #17                 // class org/apache/camel/RoutesBuilder
      62: invokeinterface #18,  2           // InterfaceMethod org/springframework/context/ApplicationContext.getBeansOfType:(Ljava/lang/Class;)Ljava/util/Map;
      67: invokeinterface #19,  1           // InterfaceMethod java/util/Map.values:()Ljava/util/Collection;
      72: invokeinterface #20,  1           // InterfaceMethod java/util/Collection.iterator:()Ljava/util/Iterator;
      77: astore        4
      79: aload         4
      81: invokeinterface #21,  1           // InterfaceMethod java/util/Iterator.hasNext:()Z
      86: ifeq          174
      89: aload         4
      91: invokeinterface #22,  1           // InterfaceMethod java/util/Iterator.next:()Ljava/lang/Object;
      96: checkcast     #17                 // class org/apache/camel/RoutesBuilder
      99: astore        5
     101: aload         5
     103: invokevirtual #23                 // Method java/lang/Object.getClass:()Ljava/lang/Class;
     106: invokevirtual #24                 // Method java/lang/Class.getModifiers:()I
     109: invokestatic  #25                 // Method java/lang/reflect/Modifier.isAbstract:(I)Z
     112: istore        6
     114: ldc           #26                 // class org/apache/camel/spring/boot/FatJarRouter
     116: aload         5
     118: invokevirtual #23                 // Method java/lang/Object.getClass:()Ljava/lang/Class;
     121: invokevirtual #8                  // Method java/lang/Object.equals:(Ljava/lang/Object;)Z
     124: istore        7
     126: iload         6
     128: ifne          171
     131: iload         7
     133: ifne          171
     136: getstatic     #13                 // Field LOG:Lorg/slf4j/Logger;
     139: ldc           #27                 // String Injecting following route into the CamelContext: {}
     141: aload         5
     143: invokeinterface #16,  3           // InterfaceMethod org/slf4j/Logger.debug:(Ljava/lang/String;Ljava/lang/Object;)V
     148: aload_3
     149: aload         5
     151: invokeinterface #28,  2           // InterfaceMethod org/apache/camel/CamelContext.addRoutes:(Lorg/apache/camel/RoutesBuilder;)V
     156: goto          171
     159: astore        8
     161: new           #30                 // class org/apache/camel/spring/boot/CamelSpringBootInitializationException
     164: dup
     165: aload         8
     167: invokespecial #31                 // Method org/apache/camel/spring/boot/CamelSpringBootInitializationException."<init>":(Ljava/lang/Throwable;)V
     170: athrow
     171: goto          79
     174: aload_0
     175: getfield      #6                  // Field configurationProperties:Lorg/apache/camel/spring/boot/CamelConfigurationProperties;
     178: invokevirtual #32                 // Method org/apache/camel/spring/boot/CamelConfigurationProperties.getXmlRoutes:()Ljava/lang/String;
     181: ldc           #33                 // String false
     183: invokevirtual #34                 // Method java/lang/String.equals:(Ljava/lang/Object;)Z
     186: ifne          193
     189: iconst_1
     190: goto          194
     193: iconst_0
     194: istore        4
     196: iload         4
     198: ifeq          214
     201: aload_0
     202: aload_2
     203: aload_3
     204: aload_0
     205: getfield      #6                  // Field configurationProperties:Lorg/apache/camel/spring/boot/CamelConfigurationProperties;
     208: invokevirtual #32                 // Method org/apache/camel/spring/boot/CamelConfigurationProperties.getXmlRoutes:()Ljava/lang/String;
     211: invokespecial #35                 // Method loadXmlRoutes:(Lorg/springframework/context/ApplicationContext;Lorg/apache/camel/CamelContext;Ljava/lang/String;)V
     214: aload_0
     215: getfield      #6                  // Field configurationProperties:Lorg/apache/camel/spring/boot/CamelConfigurationProperties;
     218: invokevirtual #36                 // Method org/apache/camel/spring/boot/CamelConfigurationProperties.getXmlRests:()Ljava/lang/String;
     221: ldc           #33                 // String false
     223: invokevirtual #34                 // Method java/lang/String.equals:(Ljava/lang/Object;)Z
     226: ifne          233
     229: iconst_1
     230: goto          234
     233: iconst_0
     234: istore        5
     236: iload         5
     238: ifeq          254
     241: aload_0
     242: aload_2
     243: aload_3
     244: aload_0
     245: getfield      #6                  // Field configurationProperties:Lorg/apache/camel/spring/boot/CamelConfigurationProperties;
     248: invokevirtual #36                 // Method org/apache/camel/spring/boot/CamelConfigurationProperties.getXmlRests:()Ljava/lang/String;
     251: invokespecial #37                 // Method loadXmlRests:(Lorg/springframework/context/ApplicationContext;Lorg/apache/camel/CamelContext;Ljava/lang/String;)V
     254: aload_0
     255: getfield      #5                  // Field camelContextConfigurations:Ljava/util/List;
     258: invokeinterface #38,  1           // InterfaceMethod java/util/List.iterator:()Ljava/util/Iterator;
     263: astore        6
     265: aload         6
     267: invokeinterface #21,  1           // InterfaceMethod java/util/Iterator.hasNext:()Z
     272: ifeq          310
     275: aload         6
     277: invokeinterface #22,  1           // InterfaceMethod java/util/Iterator.next:()Ljava/lang/Object;
     282: checkcast     #39                 // class org/apache/camel/spring/boot/CamelContextConfiguration
     285: astore        7
     287: getstatic     #13                 // Field LOG:Lorg/slf4j/Logger;
     290: ldc           #40                 // String CamelContextConfiguration found. Invoking beforeApplicationStart: {}
     292: aload         7
     294: invokeinterface #16,  3           // InterfaceMethod org/slf4j/Logger.debug:(Ljava/lang/String;Ljava/lang/Object;)V
     299: aload         7
     301: aload_3
     302: invokeinterface #41,  2           // InterfaceMethod org/apache/camel/spring/boot/CamelContextConfiguration.beforeApplicationStart:(Lorg/apache/camel/CamelContext;)V
     307: goto          265
     310: aload_0
     311: getfield      #6                  // Field configurationProperties:Lorg/apache/camel/spring/boot/CamelConfigurationProperties;
     314: invokevirtual #42                 // Method org/apache/camel/spring/boot/CamelConfigurationProperties.isMainRunController:()Z
     317: ifeq          349
     320: getstatic     #13                 // Field LOG:Lorg/slf4j/Logger;
     323: ldc           #43                 // String Starting CamelMainRunController to ensure the main thread keeps running
     325: invokeinterface #44,  2           // InterfaceMethod org/slf4j/Logger.info:(Ljava/lang/String;)V
     330: new           #45                 // class org/apache/camel/spring/boot/CamelMainRunController
     333: dup
     334: aload_2
     335: aload_3
     336: invokespecial #46                 // Method org/apache/camel/spring/boot/CamelMainRunController."<init>":(Lorg/springframework/context/ApplicationContext;Lorg/apache/camel/CamelContext;)V
     339: astore        6
     341: aload         6
     343: invokevirtual #47                 // Method org/apache/camel/spring/boot/CamelMainRunController.start:()V
     346: goto          354
     349: aload_0
     350: aload_3
     351: invokespecial #48                 // Method maybeStart:(Lorg/apache/camel/CamelContext;)V
     354: aload_0
     355: getfield      #5                  // Field camelContextConfigurations:Ljava/util/List;
     358: invokeinterface #38,  1           // InterfaceMethod java/util/List.iterator:()Ljava/util/Iterator;
     363: astore        6
     365: aload         6
     367: invokeinterface #21,  1           // InterfaceMethod java/util/Iterator.hasNext:()Z
     372: ifeq          410
     375: aload         6
     377: invokeinterface #22,  1           // InterfaceMethod java/util/Iterator.next:()Ljava/lang/Object;
     382: checkcast     #39                 // class org/apache/camel/spring/boot/CamelContextConfiguration
     385: astore        7
     387: getstatic     #13                 // Field LOG:Lorg/slf4j/Logger;
     390: ldc           #49                 // String CamelContextConfiguration found. Invoking afterApplicationStart: {}
     392: aload         7
     394: invokeinterface #16,  3           // InterfaceMethod org/slf4j/Logger.debug:(Ljava/lang/String;Ljava/lang/Object;)V
     399: aload         7
     401: aload_3
     402: invokeinterface #50,  2           // InterfaceMethod org/apache/camel/spring/boot/CamelContextConfiguration.afterApplicationStart:(Lorg/apache/camel/CamelContext;)V
     407: goto          365
     410: goto          435
     413: astore        4
     415: new           #30                 // class org/apache/camel/spring/boot/CamelSpringBootInitializationException
     418: dup
     419: aload         4
     421: invokespecial #31                 // Method org/apache/camel/spring/boot/CamelSpringBootInitializationException."<init>":(Ljava/lang/Throwable;)V
     424: athrow
     425: getstatic     #13                 // Field LOG:Lorg/slf4j/Logger;
     428: ldc           #51                 // String Camel already started, not adding routes.
     430: invokeinterface #52,  2           // InterfaceMethod org/slf4j/Logger.debug:(Ljava/lang/String;)V
     435: goto          449
     438: getstatic     #13                 // Field LOG:Lorg/slf4j/Logger;
     441: ldc           #53                 // String Ignore ContextRefreshedEvent: {}
     443: aload_1
     444: invokeinterface #16,  3           // InterfaceMethod org/slf4j/Logger.debug:(Ljava/lang/String;Ljava/lang/Object;)V
     449: return
    Exception table:
       from    to  target type
         136   156   159   Class java/lang/Exception
         174   410   413   Class java/lang/Exception

  private void maybeStart(org.apache.camel.CamelContext) throws java.lang.Exception;
    Code:
       0: ldc           #54                 // String true
       2: ldc           #55                 // String skipStartingCamelContext
       4: invokestatic  #56                 // Method java/lang/System.getProperty:(Ljava/lang/String;)Ljava/lang/String;
       7: invokevirtual #57                 // Method java/lang/String.equalsIgnoreCase:(Ljava/lang/String;)Z
      10: istore_2
      11: iload_2
      12: ifeq          28
      15: getstatic     #13                 // Field LOG:Lorg/slf4j/Logger;
      18: ldc           #58                 // String Skipping starting CamelContext as system property skipStartingCamelContext is set to be true.
      20: invokeinterface #44,  2           // InterfaceMethod org/slf4j/Logger.info:(Ljava/lang/String;)V
      25: goto          34
      28: aload_1
      29: invokeinterface #59,  1           // InterfaceMethod org/apache/camel/CamelContext.start:()V
      34: return

  private void loadXmlRoutes(org.springframework.context.ApplicationContext, org.apache.camel.CamelContext, java.lang.String) throws java.lang.Exception;
    Code:
       0: getstatic     #13                 // Field LOG:Lorg/slf4j/Logger;
       3: ldc           #60                 // String Loading additional Camel XML routes from: {}
       5: aload_3
       6: invokeinterface #61,  3           // InterfaceMethod org/slf4j/Logger.info:(Ljava/lang/String;Ljava/lang/Object;)V
      11: aload_1
      12: aload_3
      13: invokeinterface #62,  2           // InterfaceMethod org/springframework/context/ApplicationContext.getResources:(Ljava/lang/String;)[Lorg/springframework/core/io/Resource;
      18: astore        4
      20: aload         4
      22: astore        5
      24: aload         5
      26: arraylength
      27: istore        6
      29: iconst_0
      30: istore        7
      32: iload         7
      34: iload         6
      36: if_icmpge     90
      39: aload         5
      41: iload         7
      43: aaload
      44: astore        8
      46: getstatic     #13                 // Field LOG:Lorg/slf4j/Logger;
      49: ldc           #63                 // String Found XML route: {}
      51: aload         8
      53: invokeinterface #16,  3           // InterfaceMethod org/slf4j/Logger.debug:(Ljava/lang/String;Ljava/lang/Object;)V
      58: aload_2
      59: aload         8
      61: invokeinterface #64,  1           // InterfaceMethod org/springframework/core/io/Resource.getInputStream:()Ljava/io/InputStream;
      66: invokeinterface #65,  2           // InterfaceMethod org/apache/camel/CamelContext.loadRoutesDefinition:(Ljava/io/InputStream;)Lorg/apache/camel/model/RoutesDefinition;
      71: astore        9
      73: aload_2
      74: aload         9
      76: invokevirtual #66                 // Method org/apache/camel/model/RoutesDefinition.getRoutes:()Ljava/util/List;
      79: invokeinterface #67,  2           // InterfaceMethod org/apache/camel/CamelContext.addRouteDefinitions:(Ljava/util/Collection;)V
      84: iinc          7, 1
      87: goto          32
      90: goto          106
      93: astore        4
      95: getstatic     #13                 // Field LOG:Lorg/slf4j/Logger;
      98: ldc           #69                 // String No XML routes found in {}. Skipping XML routes detection.
     100: aload_3
     101: invokeinterface #16,  3           // InterfaceMethod org/slf4j/Logger.debug:(Ljava/lang/String;Ljava/lang/Object;)V
     106: return
    Exception table:
       from    to  target type
          11    90    93   Class java/io/FileNotFoundException

  private void loadXmlRests(org.springframework.context.ApplicationContext, org.apache.camel.CamelContext, java.lang.String);
    Code:
       0: getstatic     #13                 // Field LOG:Lorg/slf4j/Logger;
       3: ldc           #70                 // String Loading additional Camel XML rests from: {}
       5: aload_3
       6: invokeinterface #61,  3           // InterfaceMethod org/slf4j/Logger.info:(Ljava/lang/String;Ljava/lang/Object;)V
      11: aload_1
      12: aload_3
      13: invokeinterface #62,  2           // InterfaceMethod org/springframework/context/ApplicationContext.getResources:(Ljava/lang/String;)[Lorg/springframework/core/io/Resource;
      18: astore        4
      20: aload         4
      22: astore        5
      24: aload         5
      26: arraylength
      27: istore        6
      29: iconst_0
      30: istore        7
      32: iload         7
      34: iload         6
      36: if_icmpge     131
      39: aload         5
      41: iload         7
      43: aaload
      44: astore        8
      46: aload_2
      47: aload         8
      49: invokeinterface #64,  1           // InterfaceMethod org/springframework/core/io/Resource.getInputStream:()Ljava/io/InputStream;
      54: invokeinterface #71,  2           // InterfaceMethod org/apache/camel/CamelContext.loadRestsDefinition:(Ljava/io/InputStream;)Lorg/apache/camel/model/rest/RestsDefinition;
      59: astore        9
      61: aload_2
      62: aload         9
      64: invokevirtual #72                 // Method org/apache/camel/model/rest/RestsDefinition.getRests:()Ljava/util/List;
      67: invokeinterface #73,  2           // InterfaceMethod org/apache/camel/CamelContext.addRestDefinitions:(Ljava/util/Collection;)V
      72: aload         9
      74: invokevirtual #72                 // Method org/apache/camel/model/rest/RestsDefinition.getRests:()Ljava/util/List;
      77: invokeinterface #38,  1           // InterfaceMethod java/util/List.iterator:()Ljava/util/Iterator;
      82: astore        10
      84: aload         10
      86: invokeinterface #21,  1           // InterfaceMethod java/util/Iterator.hasNext:()Z
      91: ifeq          125
      94: aload         10
      96: invokeinterface #22,  1           // InterfaceMethod java/util/Iterator.next:()Ljava/lang/Object;
     101: checkcast     #74                 // class org/apache/camel/model/rest/RestDefinition
     104: astore        11
     106: aload         11
     108: aload_2
     109: invokevirtual #75                 // Method org/apache/camel/model/rest/RestDefinition.asRouteDefinition:(Lorg/apache/camel/CamelContext;)Ljava/util/List;
     112: astore        12
     114: aload_2
     115: aload         12
     117: invokeinterface #67,  2           // InterfaceMethod org/apache/camel/CamelContext.addRouteDefinitions:(Ljava/util/Collection;)V
     122: goto          84
     125: iinc          7, 1
     128: goto          32
     131: goto          162
     134: astore        4
     136: getstatic     #13                 // Field LOG:Lorg/slf4j/Logger;
     139: ldc           #76                 // String No XML rests found in {}. Skipping XML rests detection.
     141: aload_3
     142: invokeinterface #16,  3           // InterfaceMethod org/slf4j/Logger.debug:(Ljava/lang/String;Ljava/lang/Object;)V
     147: goto          162
     150: astore        4
     152: new           #77                 // class java/lang/RuntimeException
     155: dup
     156: aload         4
     158: invokespecial #78                 // Method java/lang/RuntimeException."<init>":(Ljava/lang/Throwable;)V
     161: athrow
     162: return
    Exception table:
       from    to  target type
          11   131   134   Class java/io/FileNotFoundException
          11   131   150   Class java/lang/Exception

  public void onApplicationEvent(org.springframework.context.ApplicationEvent);
    Code:
       0: aload_0
       1: aload_1
       2: checkcast     #79                 // class org/springframework/context/event/ContextRefreshedEvent
       5: invokevirtual #80                 // Method onApplicationEvent:(Lorg/springframework/context/event/ContextRefreshedEvent;)V
       8: return

  static {};
    Code:
       0: ldc           #81                 // class org/apache/camel/spring/boot/RoutesCollector
       2: invokestatic  #82                 // Method org/slf4j/LoggerFactory.getLogger:(Ljava/lang/Class;)Lorg/slf4j/Logger;
       5: putstatic     #13                 // Field LOG:Lorg/slf4j/Logger;
       8: return
}
