Compiled from "TypeConversionConfiguration.java"
public class org.apache.camel.spring.boot.TypeConversionConfiguration {
  public org.apache.camel.spring.boot.TypeConversionConfiguration();
    Code:
       0: aload_0
       1: invokespecial #1                  // Method java/lang/Object."<init>":()V
       4: return

  org.apache.camel.TypeConverter typeConverter(org.apache.camel.CamelContext);
    Code:
       0: aload_1
       1: invokeinterface #2,  1            // InterfaceMethod org/apache/camel/CamelContext.getTypeConverter:()Lorg/apache/camel/TypeConverter;
       6: areturn

  org.apache.camel.spring.boot.SpringTypeConverter springTypeConverter(org.apache.camel.CamelContext, org.springframework.core.convert.ConversionService[]);
    Code:
       0: new           #3                  // class org/apache/camel/spring/boot/SpringTypeConverter
       3: dup
       4: aload_2
       5: invokestatic  #4                  // Method java/util/Arrays.asList:([Ljava/lang/Object;)Ljava/util/List;
       8: invokespecial #5                  // Method org/apache/camel/spring/boot/SpringTypeConverter."<init>":(Ljava/util/List;)V
      11: astore_3
      12: aload_1
      13: invokeinterface #6,  1            // InterfaceMethod org/apache/camel/CamelContext.getTypeConverterRegistry:()Lorg/apache/camel/spi/TypeConverterRegistry;
      18: aload_3
      19: iconst_1
      20: invokeinterface #7,  3            // InterfaceMethod org/apache/camel/spi/TypeConverterRegistry.addFallbackTypeConverter:(Lorg/apache/camel/TypeConverter;Z)V
      25: aload_3
      26: areturn

  org.springframework.core.convert.ConversionService defaultCamelConversionService(org.springframework.context.ApplicationContext);
    Code:
       0: new           #8                  // class org/springframework/core/convert/support/DefaultConversionService
       3: dup
       4: invokespecial #9                  // Method org/springframework/core/convert/support/DefaultConversionService."<init>":()V
       7: astore_2
       8: aload_1
       9: ldc           #10                 // class org/springframework/core/convert/converter/Converter
      11: invokeinterface #11,  2           // InterfaceMethod org/springframework/context/ApplicationContext.getBeansOfType:(Ljava/lang/Class;)Ljava/util/Map;
      16: invokeinterface #12,  1           // InterfaceMethod java/util/Map.values:()Ljava/util/Collection;
      21: invokeinterface #13,  1           // InterfaceMethod java/util/Collection.iterator:()Ljava/util/Iterator;
      26: astore_3
      27: aload_3
      28: invokeinterface #14,  1           // InterfaceMethod java/util/Iterator.hasNext:()Z
      33: ifeq          56
      36: aload_3
      37: invokeinterface #15,  1           // InterfaceMethod java/util/Iterator.next:()Ljava/lang/Object;
      42: checkcast     #10                 // class org/springframework/core/convert/converter/Converter
      45: astore        4
      47: aload_2
      48: aload         4
      50: invokevirtual #16                 // Method org/springframework/core/convert/support/DefaultConversionService.addConverter:(Lorg/springframework/core/convert/converter/Converter;)V
      53: goto          27
      56: aload_2
      57: areturn
}
