Compiled from "Simulator.java"
public class org.yamcs.simulator.Simulator extends java.lang.Thread {
  protected java.util.concurrent.BlockingQueue<org.yamcs.simulator.CCSDSPacket> pendingCommands;

  private int DEFAULT_MAX_LENGTH;

  private int maxLength;

  private org.yamcs.simulator.SimulationConfiguration simConfig;

  private org.yamcs.simulator.TelemetryLink tmLink;

  private boolean isLos;

  private org.yamcs.simulator.LosStore losStore;

  private org.yamcs.simulator.ui.SimWindow simWindow;

  private static final org.slf4j.Logger log;

  public org.yamcs.simulator.Simulator(org.yamcs.simulator.SimulationConfiguration);
    Code:
       0: aload_0
       1: invokespecial #1                  // Method java/lang/Thread."<init>":()V
       4: aload_0
       5: new           #2                  // class java/util/concurrent/ArrayBlockingQueue
       8: dup
       9: bipush        100
      11: invokespecial #3                  // Method java/util/concurrent/ArrayBlockingQueue."<init>":(I)V
      14: putfield      #4                  // Field pendingCommands:Ljava/util/concurrent/BlockingQueue;
      17: aload_0
      18: ldc           #5                  // int 65542
      20: putfield      #6                  // Field DEFAULT_MAX_LENGTH:I
      23: aload_0
      24: aload_0
      25: getfield      #6                  // Field DEFAULT_MAX_LENGTH:I
      28: putfield      #7                  // Field maxLength:I
      31: aload_0
      32: iconst_0
      33: putfield      #8                  // Field isLos:Z
      36: aload_0
      37: aload_1
      38: putfield      #9                  // Field simConfig:Lorg/yamcs/simulator/SimulationConfiguration;
      41: aload_0
      42: new           #10                 // class org/yamcs/simulator/TelemetryLink
      45: dup
      46: aload_0
      47: aload_1
      48: invokespecial #11                 // Method org/yamcs/simulator/TelemetryLink."<init>":(Lorg/yamcs/simulator/Simulator;Lorg/yamcs/simulator/SimulationConfiguration;)V
      51: putfield      #12                 // Field tmLink:Lorg/yamcs/simulator/TelemetryLink;
      54: aload_0
      55: new           #13                 // class org/yamcs/simulator/LosStore
      58: dup
      59: aload_0
      60: aload_1
      61: invokespecial #14                 // Method org/yamcs/simulator/LosStore."<init>":(Lorg/yamcs/simulator/Simulator;Lorg/yamcs/simulator/SimulationConfiguration;)V
      64: putfield      #15                 // Field losStore:Lorg/yamcs/simulator/LosStore;
      67: return

  public void run();
    Code:
       0: aload_0
       1: getfield      #9                  // Field simConfig:Lorg/yamcs/simulator/SimulationConfiguration;
       4: invokevirtual #16                 // Method org/yamcs/simulator/SimulationConfiguration.getServerConnections:()Ljava/util/List;
       7: invokeinterface #17,  1           // InterfaceMethod java/util/List.iterator:()Ljava/util/Iterator;
      12: astore_1
      13: aload_1
      14: invokeinterface #18,  1           // InterfaceMethod java/util/Iterator.hasNext:()Z
      19: ifeq          87
      22: aload_1
      23: invokeinterface #19,  1           // InterfaceMethod java/util/Iterator.next:()Ljava/lang/Object;
      28: checkcast     #20                 // class org/yamcs/simulator/ServerConnection
      31: astore_2
      32: aload_0
      33: getfield      #12                 // Field tmLink:Lorg/yamcs/simulator/TelemetryLink;
      36: aload_2
      37: invokevirtual #21                 // Method org/yamcs/simulator/TelemetryLink.yamcsServerConnect:(Lorg/yamcs/simulator/ServerConnection;)V
      40: new           #22                 // class java/lang/Thread
      43: dup
      44: aload_0
      45: aload_2
      46: invokedynamic #23,  0             // InvokeDynamic #0:run:(Lorg/yamcs/simulator/Simulator;Lorg/yamcs/simulator/ServerConnection;)Ljava/lang/Runnable;
      51: invokespecial #24                 // Method java/lang/Thread."<init>":(Ljava/lang/Runnable;)V
      54: invokevirtual #25                 // Method java/lang/Thread.start:()V
      57: getstatic     #26                 // Field log:Lorg/slf4j/Logger;
      60: ldc           #27                 // String Start TM thread
      62: invokeinterface #28,  2           // InterfaceMethod org/slf4j/Logger.debug:(Ljava/lang/String;)V
      67: new           #22                 // class java/lang/Thread
      70: dup
      71: aload_0
      72: aload_2
      73: invokedynamic #29,  0             // InvokeDynamic #1:run:(Lorg/yamcs/simulator/Simulator;Lorg/yamcs/simulator/ServerConnection;)Ljava/lang/Runnable;
      78: invokespecial #24                 // Method java/lang/Thread."<init>":(Ljava/lang/Runnable;)V
      81: invokevirtual #25                 // Method java/lang/Thread.start:()V
      84: goto          13
      87: return

  protected org.yamcs.simulator.CCSDSPacket readPacket(java.io.DataInputStream);
    Code:
       0: bipush        6
       2: newarray       byte
       4: astore_2
       5: aload_1
       6: aload_2
       7: invokevirtual #30                 // Method java/io/DataInputStream.readFully:([B)V
      10: aload_2
      11: iconst_4
      12: baload
      13: sipush        255
      16: iand
      17: bipush        8
      19: ishl
      20: aload_2
      21: iconst_5
      22: baload
      23: sipush        255
      26: iand
      27: iadd
      28: iconst_1
      29: iadd
      30: istore_3
      31: iload_3
      32: aload_0
      33: getfield      #7                  // Field maxLength:I
      36: bipush        6
      38: isub
      39: if_icmple     84
      42: new           #31                 // class java/io/IOException
      45: dup
      46: new           #32                 // class java/lang/StringBuilder
      49: dup
      50: invokespecial #33                 // Method java/lang/StringBuilder."<init>":()V
      53: ldc           #34                 // String Remaining packet length too big:
      55: invokevirtual #35                 // Method java/lang/StringBuilder.append:(Ljava/lang/String;)Ljava/lang/StringBuilder;
      58: iload_3
      59: invokevirtual #36                 // Method java/lang/StringBuilder.append:(I)Ljava/lang/StringBuilder;
      62: ldc           #37                 // String  maximum allowed is
      64: invokevirtual #35                 // Method java/lang/StringBuilder.append:(Ljava/lang/String;)Ljava/lang/StringBuilder;
      67: aload_0
      68: getfield      #7                  // Field maxLength:I
      71: bipush        6
      73: isub
      74: invokevirtual #36                 // Method java/lang/StringBuilder.append:(I)Ljava/lang/StringBuilder;
      77: invokevirtual #38                 // Method java/lang/StringBuilder.toString:()Ljava/lang/String;
      80: invokespecial #39                 // Method java/io/IOException."<init>":(Ljava/lang/String;)V
      83: athrow
      84: bipush        6
      86: iload_3
      87: iadd
      88: newarray       byte
      90: astore        4
      92: aload_2
      93: iconst_0
      94: aload         4
      96: iconst_0
      97: bipush        6
      99: invokestatic  #40                 // Method java/lang/System.arraycopy:(Ljava/lang/Object;ILjava/lang/Object;II)V
     102: aload_1
     103: aload         4
     105: bipush        6
     107: iload_3
     108: invokevirtual #41                 // Method java/io/DataInputStream.readFully:([BII)V
     111: new           #42                 // class org/yamcs/simulator/CCSDSPacket
     114: dup
     115: aload         4
     117: invokestatic  #43                 // Method java/nio/ByteBuffer.wrap:([B)Ljava/nio/ByteBuffer;
     120: invokespecial #44                 // Method org/yamcs/simulator/CCSDSPacket."<init>":(Ljava/nio/ByteBuffer;)V
     123: astore        5
     125: aload_0
     126: getfield      #12                 // Field tmLink:Lorg/yamcs/simulator/TelemetryLink;
     129: aload_0
     130: aload         5
     132: iconst_0
     133: iconst_0
     134: invokevirtual #45                 // Method ackPacket:(Lorg/yamcs/simulator/CCSDSPacket;II)Lorg/yamcs/simulator/CCSDSPacket;
     137: invokevirtual #46                 // Method org/yamcs/simulator/TelemetryLink.ackPacketSend:(Lorg/yamcs/simulator/CCSDSPacket;)V
     140: aload         5
     142: areturn
     143: astore_2
     144: getstatic     #26                 // Field log:Lorg/slf4j/Logger;
     147: new           #32                 // class java/lang/StringBuilder
     150: dup
     151: invokespecial #33                 // Method java/lang/StringBuilder."<init>":()V
     154: ldc           #47                 // String Connection lost:
     156: invokevirtual #35                 // Method java/lang/StringBuilder.append:(Ljava/lang/String;)Ljava/lang/StringBuilder;
     159: aload_2
     160: invokevirtual #48                 // Method java/io/IOException.getMessage:()Ljava/lang/String;
     163: invokevirtual #35                 // Method java/lang/StringBuilder.append:(Ljava/lang/String;)Ljava/lang/StringBuilder;
     166: invokevirtual #38                 // Method java/lang/StringBuilder.toString:()Ljava/lang/String;
     169: aload_2
     170: invokeinterface #49,  3           // InterfaceMethod org/slf4j/Logger.error:(Ljava/lang/String;Ljava/lang/Throwable;)V
     175: goto          210
     178: astore_2
     179: getstatic     #26                 // Field log:Lorg/slf4j/Logger;
     182: new           #32                 // class java/lang/StringBuilder
     185: dup
     186: invokespecial #33                 // Method java/lang/StringBuilder."<init>":()V
     189: ldc           #51                 // String Error reading command
     191: invokevirtual #35                 // Method java/lang/StringBuilder.append:(Ljava/lang/String;)Ljava/lang/StringBuilder;
     194: aload_2
     195: invokevirtual #52                 // Method java/lang/Exception.getMessage:()Ljava/lang/String;
     198: invokevirtual #35                 // Method java/lang/StringBuilder.append:(Ljava/lang/String;)Ljava/lang/StringBuilder;
     201: invokevirtual #38                 // Method java/lang/StringBuilder.toString:()Ljava/lang/String;
     204: aload_2
     205: invokeinterface #49,  3           // InterfaceMethod org/slf4j/Logger.error:(Ljava/lang/String;Ljava/lang/Throwable;)V
     210: aconst_null
     211: areturn
    Exception table:
       from    to  target type
           0   142   143   Class java/io/IOException
           0   142   178   Class java/lang/Exception

  public org.yamcs.simulator.SimulationConfiguration getSimulationConfiguration();
    Code:
       0: aload_0
       1: getfield      #9                  // Field simConfig:Lorg/yamcs/simulator/SimulationConfiguration;
       4: areturn

  public org.yamcs.simulator.LosStore getLosStore();
    Code:
       0: aload_0
       1: getfield      #15                 // Field losStore:Lorg/yamcs/simulator/LosStore;
       4: areturn

  public boolean isLOS();
    Code:
       0: aload_0
       1: getfield      #8                  // Field isLos:Z
       4: ireturn

  public void setLOS(boolean);
    Code:
       0: aload_0
       1: iload_1
       2: putfield      #8                  // Field isLos:Z
       5: return

  public org.yamcs.simulator.TelemetryLink getTMLink();
    Code:
       0: aload_0
       1: getfield      #12                 // Field tmLink:Lorg/yamcs/simulator/TelemetryLink;
       4: areturn

  protected void transmitTM(org.yamcs.simulator.CCSDSPacket);
    Code:
       0: aload_0
       1: getfield      #12                 // Field tmLink:Lorg/yamcs/simulator/TelemetryLink;
       4: aload_1
       5: invokevirtual #53                 // Method org/yamcs/simulator/TelemetryLink.tmTransmit:(Lorg/yamcs/simulator/CCSDSPacket;)V
       8: return

  protected void transmitAck(org.yamcs.simulator.CCSDSPacket);
    Code:
       0: aload_0
       1: getfield      #12                 // Field tmLink:Lorg/yamcs/simulator/TelemetryLink;
       4: aload_1
       5: invokevirtual #53                 // Method org/yamcs/simulator/TelemetryLink.tmTransmit:(Lorg/yamcs/simulator/CCSDSPacket;)V
       8: return

  public void dumpLosDataFile(java.lang.String);
    Code:
       0: aload_1
       1: ifnonnull     12
       4: aload_0
       5: getfield      #15                 // Field losStore:Lorg/yamcs/simulator/LosStore;
       8: invokevirtual #54                 // Method org/yamcs/simulator/LosStore.getCurrentFileName:()Ljava/lang/String;
      11: astore_1
      12: aload_0
      13: getfield      #15                 // Field losStore:Lorg/yamcs/simulator/LosStore;
      16: aload_1
      17: invokevirtual #55                 // Method org/yamcs/simulator/LosStore.readLosFile:(Ljava/lang/String;)Ljava/io/DataInputStream;
      20: astore_2
      21: aload_2
      22: ifnonnull     26
      25: return
      26: new           #2                  // class java/util/concurrent/ArrayBlockingQueue
      29: dup
      30: sipush        1000
      33: invokespecial #3                  // Method java/util/concurrent/ArrayBlockingQueue."<init>":(I)V
      36: astore_3
      37: aload_2
      38: invokevirtual #56                 // Method java/io/DataInputStream.available:()I
      41: ifle          68
      44: aload_0
      45: aload_2
      46: invokevirtual #57                 // Method readPacket:(Ljava/io/DataInputStream;)Lorg/yamcs/simulator/CCSDSPacket;
      49: astore        4
      51: aload         4
      53: ifnull        65
      56: aload_3
      57: aload         4
      59: invokeinterface #58,  2           // InterfaceMethod java/util/Queue.add:(Ljava/lang/Object;)Z
      64: pop
      65: goto          37
      68: goto          78
      71: astore        4
      73: aload         4
      75: invokevirtual #59                 // Method java/io/IOException.printStackTrace:()V
      78: aload_3
      79: invokeinterface #60,  1           // InterfaceMethod java/util/Queue.iterator:()Ljava/util/Iterator;
      84: astore        4
      86: aload         4
      88: invokeinterface #18,  1           // InterfaceMethod java/util/Iterator.hasNext:()Z
      93: ifeq          157
      96: aload         4
      98: invokeinterface #19,  1           // InterfaceMethod java/util/Iterator.next:()Ljava/lang/Object;
     103: checkcast     #42                 // class org/yamcs/simulator/CCSDSPacket
     106: astore        5
     108: aload_0
     109: getfield      #9                  // Field simConfig:Lorg/yamcs/simulator/SimulationConfiguration;
     112: invokevirtual #16                 // Method org/yamcs/simulator/SimulationConfiguration.getServerConnections:()Ljava/util/List;
     115: invokeinterface #17,  1           // InterfaceMethod java/util/List.iterator:()Ljava/util/Iterator;
     120: astore        6
     122: aload         6
     124: invokeinterface #18,  1           // InterfaceMethod java/util/Iterator.hasNext:()Z
     129: ifeq          154
     132: aload         6
     134: invokeinterface #19,  1           // InterfaceMethod java/util/Iterator.next:()Ljava/lang/Object;
     139: checkcast     #20                 // class org/yamcs/simulator/ServerConnection
     142: astore        7
     144: aload         7
     146: aload         5
     148: invokevirtual #61                 // Method org/yamcs/simulator/ServerConnection.setTmDumpPacket:(Lorg/yamcs/simulator/CCSDSPacket;)V
     151: goto          122
     154: goto          86
     157: aload_1
     158: invokestatic  #62                 // Method buildLosTransmittedRecordingPacket:(Ljava/lang/String;)Lorg/yamcs/simulator/CCSDSPacket;
     161: astore        4
     163: aload_0
     164: getfield      #9                  // Field simConfig:Lorg/yamcs/simulator/SimulationConfiguration;
     167: invokevirtual #16                 // Method org/yamcs/simulator/SimulationConfiguration.getServerConnections:()Ljava/util/List;
     170: invokeinterface #17,  1           // InterfaceMethod java/util/List.iterator:()Ljava/util/Iterator;
     175: astore        5
     177: aload         5
     179: invokeinterface #18,  1           // InterfaceMethod java/util/Iterator.hasNext:()Z
     184: ifeq          209
     187: aload         5
     189: invokeinterface #19,  1           // InterfaceMethod java/util/Iterator.next:()Ljava/lang/Object;
     194: checkcast     #20                 // class org/yamcs/simulator/ServerConnection
     197: astore        6
     199: aload         6
     201: aload         4
     203: invokevirtual #61                 // Method org/yamcs/simulator/ServerConnection.setTmDumpPacket:(Lorg/yamcs/simulator/CCSDSPacket;)V
     206: goto          177
     209: return
    Exception table:
       from    to  target type
          37    68    71   Class java/io/IOException

  private static org.yamcs.simulator.CCSDSPacket buildLosTransmittedRecordingPacket(java.lang.String);
    Code:
       0: new           #42                 // class org/yamcs/simulator/CCSDSPacket
       3: dup
       4: iconst_0
       5: iconst_2
       6: bipush        10
       8: invokespecial #63                 // Method org/yamcs/simulator/CCSDSPacket."<init>":(III)V
      11: astore_1
      12: aload_1
      13: aload_0
      14: invokevirtual #64                 // Method java/lang/String.getBytes:()[B
      17: invokevirtual #65                 // Method org/yamcs/simulator/CCSDSPacket.appendUserDataBuffer:([B)V
      20: aload_1
      21: iconst_1
      22: newarray       byte
      24: invokevirtual #65                 // Method org/yamcs/simulator/CCSDSPacket.appendUserDataBuffer:([B)V
      27: aload_1
      28: areturn

  public void deleteLosDataFile(java.lang.String);
    Code:
       0: aload_0
       1: getfield      #15                 // Field losStore:Lorg/yamcs/simulator/LosStore;
       4: aload_1
       5: invokevirtual #66                 // Method org/yamcs/simulator/LosStore.deleteFile:(Ljava/lang/String;)V
       8: aload_1
       9: invokestatic  #67                 // Method buildLosDeletedRecordingPacket:(Ljava/lang/String;)Lorg/yamcs/simulator/CCSDSPacket;
      12: astore_2
      13: aload_0
      14: getfield      #9                  // Field simConfig:Lorg/yamcs/simulator/SimulationConfiguration;
      17: invokevirtual #16                 // Method org/yamcs/simulator/SimulationConfiguration.getServerConnections:()Ljava/util/List;
      20: invokeinterface #17,  1           // InterfaceMethod java/util/List.iterator:()Ljava/util/Iterator;
      25: astore_3
      26: aload_3
      27: invokeinterface #18,  1           // InterfaceMethod java/util/Iterator.hasNext:()Z
      32: ifeq          55
      35: aload_3
      36: invokeinterface #19,  1           // InterfaceMethod java/util/Iterator.next:()Ljava/lang/Object;
      41: checkcast     #20                 // class org/yamcs/simulator/ServerConnection
      44: astore        4
      46: aload         4
      48: aload_2
      49: invokevirtual #61                 // Method org/yamcs/simulator/ServerConnection.setTmDumpPacket:(Lorg/yamcs/simulator/CCSDSPacket;)V
      52: goto          26
      55: return

  private static org.yamcs.simulator.CCSDSPacket buildLosDeletedRecordingPacket(java.lang.String);
    Code:
       0: new           #42                 // class org/yamcs/simulator/CCSDSPacket
       3: dup
       4: iconst_0
       5: iconst_2
       6: bipush        11
       8: invokespecial #63                 // Method org/yamcs/simulator/CCSDSPacket."<init>":(III)V
      11: astore_1
      12: aload_1
      13: aload_0
      14: invokevirtual #64                 // Method java/lang/String.getBytes:()[B
      17: invokevirtual #65                 // Method org/yamcs/simulator/CCSDSPacket.appendUserDataBuffer:([B)V
      20: aload_1
      21: iconst_1
      22: newarray       byte
      24: invokevirtual #65                 // Method org/yamcs/simulator/CCSDSPacket.appendUserDataBuffer:([B)V
      27: aload_1
      28: areturn

  public org.yamcs.simulator.ui.SimWindow getSimWindow();
    Code:
       0: aload_0
       1: getfield      #68                 // Field simWindow:Lorg/yamcs/simulator/ui/SimWindow;
       4: areturn

  public void setSimWindow(org.yamcs.simulator.ui.SimWindow);
    Code:
       0: aload_0
       1: aload_1
       2: putfield      #68                 // Field simWindow:Lorg/yamcs/simulator/ui/SimWindow;
       5: return

  public void startTriggeringLos();
    Code:
       0: aload_0
       1: getfield      #15                 // Field losStore:Lorg/yamcs/simulator/LosStore;
       4: invokevirtual #69                 // Method org/yamcs/simulator/LosStore.startTriggeringLos:()V
       7: return

  public void stopTriggeringLos();
    Code:
       0: aload_0
       1: getfield      #15                 // Field losStore:Lorg/yamcs/simulator/LosStore;
       4: invokevirtual #70                 // Method org/yamcs/simulator/LosStore.stopTriggeringLos:()V
       7: return

  protected org.yamcs.simulator.CCSDSPacket ackPacket(org.yamcs.simulator.CCSDSPacket, int, int);
    Code:
       0: new           #42                 // class org/yamcs/simulator/CCSDSPacket
       3: dup
       4: iconst_0
       5: aload_1
       6: invokevirtual #71                 // Method org/yamcs/simulator/CCSDSPacket.getPacketType:()I
       9: sipush        2000
      12: invokespecial #63                 // Method org/yamcs/simulator/CCSDSPacket."<init>":(III)V
      15: astore        4
      17: aload         4
      19: bipush        101
      21: invokevirtual #72                 // Method org/yamcs/simulator/CCSDSPacket.setApid:(I)V
      24: aload_1
      25: invokevirtual #73                 // Method org/yamcs/simulator/CCSDSPacket.getPacketId:()I
      28: istore        5
      30: bipush        10
      32: invokestatic  #74                 // Method java/nio/ByteBuffer.allocate:(I)Ljava/nio/ByteBuffer;
      35: astore        6
      37: aload         6
      39: iconst_0
      40: iload         5
      42: invokevirtual #75                 // Method java/nio/ByteBuffer.putInt:(II)Ljava/nio/ByteBuffer;
      45: pop
      46: aload         6
      48: iconst_4
      49: aload_1
      50: invokevirtual #76                 // Method org/yamcs/simulator/CCSDSPacket.getSeq:()I
      53: invokevirtual #75                 // Method java/nio/ByteBuffer.putInt:(II)Ljava/nio/ByteBuffer;
      56: pop
      57: aload         6
      59: bipush        8
      61: iload_2
      62: i2b
      63: invokevirtual #77                 // Method java/nio/ByteBuffer.put:(IB)Ljava/nio/ByteBuffer;
      66: pop
      67: aload         6
      69: bipush        9
      71: iload_3
      72: i2b
      73: invokevirtual #77                 // Method java/nio/ByteBuffer.put:(IB)Ljava/nio/ByteBuffer;
      76: pop
      77: aload         4
      79: aload         6
      81: invokevirtual #78                 // Method java/nio/ByteBuffer.array:()[B
      84: invokevirtual #65                 // Method org/yamcs/simulator/CCSDSPacket.appendUserDataBuffer:([B)V
      87: aload         4
      89: areturn

  private void lambda$run$1(org.yamcs.simulator.ServerConnection);
    Code:
       0: aload_0
       1: getfield      #12                 // Field tmLink:Lorg/yamcs/simulator/TelemetryLink;
       4: aload_1
       5: invokevirtual #79                 // Method org/yamcs/simulator/TelemetryLink.packetSend:(Lorg/yamcs/simulator/ServerConnection;)V
       8: return

  private void lambda$run$0(org.yamcs.simulator.ServerConnection);
    Code:
       0: aload_0
       1: new           #80                 // class java/io/DataInputStream
       4: dup
       5: aload_1
       6: invokevirtual #81                 // Method org/yamcs/simulator/ServerConnection.getTcSocket:()Ljava/net/Socket;
       9: invokevirtual #82                 // Method java/net/Socket.getInputStream:()Ljava/io/InputStream;
      12: invokespecial #83                 // Method java/io/DataInputStream."<init>":(Ljava/io/InputStream;)V
      15: invokevirtual #57                 // Method readPacket:(Ljava/io/DataInputStream;)Lorg/yamcs/simulator/CCSDSPacket;
      18: astore_2
      19: aload_2
      20: ifnull        33
      23: aload_0
      24: getfield      #4                  // Field pendingCommands:Ljava/util/concurrent/BlockingQueue;
      27: aload_2
      28: invokeinterface #84,  2           // InterfaceMethod java/util/concurrent/BlockingQueue.put:(Ljava/lang/Object;)V
      33: goto          0
      36: astore_2
      37: aload_1
      38: iconst_0
      39: invokevirtual #85                 // Method org/yamcs/simulator/ServerConnection.setConnected:(Z)V
      42: aload_0
      43: getfield      #12                 // Field tmLink:Lorg/yamcs/simulator/TelemetryLink;
      46: aload_1
      47: invokevirtual #21                 // Method org/yamcs/simulator/TelemetryLink.yamcsServerConnect:(Lorg/yamcs/simulator/ServerConnection;)V
      50: goto          0
      53: astore_2
      54: getstatic     #26                 // Field log:Lorg/slf4j/Logger;
      57: ldc           #87                 // String Read packets interrupted.
      59: aload_2
      60: invokeinterface #88,  3           // InterfaceMethod org/slf4j/Logger.warn:(Ljava/lang/String;Ljava/lang/Throwable;)V
      65: invokestatic  #89                 // Method java/lang/Thread.currentThread:()Ljava/lang/Thread;
      68: invokevirtual #90                 // Method java/lang/Thread.interrupt:()V
      71: goto          0
    Exception table:
       from    to  target type
           0    33    36   Class java/io/IOException
           0    33    53   Class java/lang/InterruptedException

  static {};
    Code:
       0: ldc           #91                 // class org/yamcs/simulator/Simulator
       2: invokestatic  #92                 // Method org/slf4j/LoggerFactory.getLogger:(Ljava/lang/Class;)Lorg/slf4j/Logger;
       5: putstatic     #26                 // Field log:Lorg/slf4j/Logger;
       8: return
}
