Compiled from "InvalidChangeBatchException.java"
public class com.amazonaws.services.route53.model.InvalidChangeBatchException extends com.amazonaws.AmazonServiceException {
  private static final long serialVersionUID;

  private com.amazonaws.internal.SdkInternalList<java.lang.String> messages;

  public com.amazonaws.services.route53.model.InvalidChangeBatchException(java.lang.String);
    Code:
       0: aload_0
       1: aload_1
       2: invokespecial #1                  // Method com/amazonaws/AmazonServiceException."<init>":(Ljava/lang/String;)V
       5: return

  public java.util.List<java.lang.String> getMessages();
    Code:
       0: aload_0
       1: getfield      #2                  // Field messages:Lcom/amazonaws/internal/SdkInternalList;
       4: ifnonnull     18
       7: aload_0
       8: new           #3                  // class com/amazonaws/internal/SdkInternalList
      11: dup
      12: invokespecial #4                  // Method com/amazonaws/internal/SdkInternalList."<init>":()V
      15: putfield      #2                  // Field messages:Lcom/amazonaws/internal/SdkInternalList;
      18: aload_0
      19: getfield      #2                  // Field messages:Lcom/amazonaws/internal/SdkInternalList;
      22: areturn

  public void setMessages(java.util.Collection<java.lang.String>);
    Code:
       0: aload_1
       1: ifnonnull     10
       4: aload_0
       5: aconst_null
       6: putfield      #2                  // Field messages:Lcom/amazonaws/internal/SdkInternalList;
       9: return
      10: aload_0
      11: new           #3                  // class com/amazonaws/internal/SdkInternalList
      14: dup
      15: aload_1
      16: invokespecial #5                  // Method com/amazonaws/internal/SdkInternalList."<init>":(Ljava/util/Collection;)V
      19: putfield      #2                  // Field messages:Lcom/amazonaws/internal/SdkInternalList;
      22: return

  public com.amazonaws.services.route53.model.InvalidChangeBatchException withMessages(java.lang.String...);
    Code:
       0: aload_0
       1: getfield      #2                  // Field messages:Lcom/amazonaws/internal/SdkInternalList;
       4: ifnonnull     20
       7: aload_0
       8: new           #3                  // class com/amazonaws/internal/SdkInternalList
      11: dup
      12: aload_1
      13: arraylength
      14: invokespecial #6                  // Method com/amazonaws/internal/SdkInternalList."<init>":(I)V
      17: invokevirtual #7                  // Method setMessages:(Ljava/util/Collection;)V
      20: aload_1
      21: astore_2
      22: aload_2
      23: arraylength
      24: istore_3
      25: iconst_0
      26: istore        4
      28: iload         4
      30: iload_3
      31: if_icmpge     56
      34: aload_2
      35: iload         4
      37: aaload
      38: astore        5
      40: aload_0
      41: getfield      #2                  // Field messages:Lcom/amazonaws/internal/SdkInternalList;
      44: aload         5
      46: invokevirtual #8                  // Method com/amazonaws/internal/SdkInternalList.add:(Ljava/lang/Object;)Z
      49: pop
      50: iinc          4, 1
      53: goto          28
      56: aload_0
      57: areturn

  public com.amazonaws.services.route53.model.InvalidChangeBatchException withMessages(java.util.Collection<java.lang.String>);
    Code:
       0: aload_0
       1: aload_1
       2: invokevirtual #7                  // Method setMessages:(Ljava/util/Collection;)V
       5: aload_0
       6: areturn
}
