Compiled from "QueryResultsRegionImpl.java"
class org.hibernate.cache.infinispan.query.QueryResultsRegionImpl$PostTransactionQueryUpdate extends org.hibernate.cache.infinispan.util.InvocationAfterCompletion {
  private final org.hibernate.engine.spi.SessionImplementor session;

  private final java.lang.Object key;

  private final java.lang.Object value;

  final org.hibernate.cache.infinispan.query.QueryResultsRegionImpl this$0;

  public org.hibernate.cache.infinispan.query.QueryResultsRegionImpl$PostTransactionQueryUpdate(org.hibernate.cache.infinispan.query.QueryResultsRegionImpl, org.hibernate.resource.transaction.TransactionCoordinator, org.hibernate.engine.spi.SessionImplementor, java.lang.Object, java.lang.Object);
    Code:
       0: aload_0
       1: aload_1
       2: putfield      #1                  // Field this$0:Lorg/hibernate/cache/infinispan/query/QueryResultsRegionImpl;
       5: aload_0
       6: aload_2
       7: aload_1
       8: invokestatic  #2                  // Method org/hibernate/cache/infinispan/query/QueryResultsRegionImpl.access$000:(Lorg/hibernate/cache/infinispan/query/QueryResultsRegionImpl;)Lorg/infinispan/AdvancedCache;
      11: aload_1
      12: invokestatic  #3                  // Method org/hibernate/cache/infinispan/query/QueryResultsRegionImpl.access$100:(Lorg/hibernate/cache/infinispan/query/QueryResultsRegionImpl;)Z
      15: invokespecial #4                  // Method org/hibernate/cache/infinispan/util/InvocationAfterCompletion."<init>":(Lorg/hibernate/resource/transaction/TransactionCoordinator;Lorg/infinispan/AdvancedCache;Z)V
      18: aload_0
      19: aload_3
      20: putfield      #5                  // Field session:Lorg/hibernate/engine/spi/SessionImplementor;
      23: aload_0
      24: aload         4
      26: putfield      #6                  // Field key:Ljava/lang/Object;
      29: aload_0
      30: aload         5
      32: putfield      #7                  // Field value:Ljava/lang/Object;
      35: return

  public void afterCompletion(int);
    Code:
       0: aload_0
       1: getfield      #1                  // Field this$0:Lorg/hibernate/cache/infinispan/query/QueryResultsRegionImpl;
       4: invokestatic  #8                  // Method org/hibernate/cache/infinispan/query/QueryResultsRegionImpl.access$200:(Lorg/hibernate/cache/infinispan/query/QueryResultsRegionImpl;)Ljava/util/concurrent/ConcurrentMap;
       7: aload_0
       8: getfield      #5                  // Field session:Lorg/hibernate/engine/spi/SessionImplementor;
      11: invokeinterface #9,  2            // InterfaceMethod java/util/concurrent/ConcurrentMap.remove:(Ljava/lang/Object;)Ljava/lang/Object;
      16: pop
      17: aload_0
      18: iload_1
      19: invokespecial #10                 // Method org/hibernate/cache/infinispan/util/InvocationAfterCompletion.afterCompletion:(I)V
      22: return

  protected void invoke(boolean, org.infinispan.AdvancedCache);
    Code:
       0: iload_1
       1: ifeq          19
       4: aload_2
       5: aload_0
       6: getfield      #6                  // Field key:Ljava/lang/Object;
       9: aload_0
      10: getfield      #7                  // Field value:Ljava/lang/Object;
      13: invokeinterface #11,  3           // InterfaceMethod org/infinispan/AdvancedCache.put:(Ljava/lang/Object;Ljava/lang/Object;)Ljava/lang/Object;
      18: pop
      19: return
}
