Compiled from "CarbonTomcatRealm.java"
class org.wso2.carbon.tomcat.ext.realms.CarbonTomcatRealm$GenericCarbonPrincipal extends org.apache.catalina.realm.GenericPrincipal {
  private java.lang.String tenantDomain;

  public org.wso2.carbon.tomcat.ext.realms.CarbonTomcatRealm$GenericCarbonPrincipal(java.lang.String);
    Code:
       0: aload_0
       1: aload_1
       2: aconst_null
       3: aload_1
       4: invokestatic  #1                  // Method getCarbonRoles:(Ljava/lang/String;)Ljava/util/List;
       7: invokespecial #2                  // Method org/apache/catalina/realm/GenericPrincipal."<init>":(Ljava/lang/String;Ljava/lang/String;Ljava/util/List;)V
      10: aload_0
      11: aconst_null
      12: putfield      #3                  // Field tenantDomain:Ljava/lang/String;
      15: aload_0
      16: aconst_null
      17: putfield      #3                  // Field tenantDomain:Ljava/lang/String;
      20: aload_1
      21: ldc           #4                  // String @
      23: invokevirtual #5                  // Method java/lang/String.contains:(Ljava/lang/CharSequence;)Z
      26: ifeq          45
      29: aload_0
      30: aload_1
      31: aload_1
      32: bipush        64
      34: invokevirtual #6                  // Method java/lang/String.indexOf:(I)I
      37: iconst_1
      38: iadd
      39: invokevirtual #7                  // Method java/lang/String.substring:(I)Ljava/lang/String;
      42: putfield      #3                  // Field tenantDomain:Ljava/lang/String;
      45: return

  private static java.util.List<java.lang.String> getCarbonRoles(java.lang.String);
    Code:
       0: aconst_null
       1: astore_1
       2: aload_0
       3: ldc           #4                  // String @
       5: invokevirtual #5                  // Method java/lang/String.contains:(Ljava/lang/CharSequence;)Z
       8: ifeq          24
      11: aload_0
      12: aload_0
      13: bipush        64
      15: invokevirtual #6                  // Method java/lang/String.indexOf:(I)I
      18: iconst_1
      19: iadd
      20: invokevirtual #7                  // Method java/lang/String.substring:(I)Ljava/lang/String;
      23: astore_1
      24: invokestatic  #8                  // Method org/wso2/carbon/tomcat/ext/internal/CarbonRealmServiceHolder.getRealmService:()Lorg/wso2/carbon/user/core/service/RealmService;
      27: astore_2
      28: aload_2
      29: invokeinterface #9,  1            // InterfaceMethod org/wso2/carbon/user/api/UserRealmService.getTenantManager:()Lorg/wso2/carbon/user/api/TenantManager;
      34: aload_1
      35: invokeinterface #10,  2           // InterfaceMethod org/wso2/carbon/user/api/TenantManager.getTenantId:(Ljava/lang/String;)I
      40: istore_3
      41: aload_0
      42: invokestatic  #11                 // Method org/wso2/carbon/tomcat/ext/realms/CarbonTomcatRealm.access$000:(Ljava/lang/String;)Ljava/lang/String;
      45: astore        4
      47: aload_2
      48: iload_3
      49: invokeinterface #12,  2           // InterfaceMethod org/wso2/carbon/user/api/UserRealmService.getTenantUserRealm:(I)Lorg/wso2/carbon/user/api/UserRealm;
      54: invokeinterface #13,  1           // InterfaceMethod org/wso2/carbon/user/api/UserRealm.getUserStoreManager:()Lorg/wso2/carbon/user/api/UserStoreManager;
      59: aload         4
      61: invokeinterface #14,  2           // InterfaceMethod org/wso2/carbon/user/api/UserStoreManager.getRoleListOfUser:(Ljava/lang/String;)[Ljava/lang/String;
      66: astore        5
      68: aload         5
      70: invokestatic  #15                 // Method java/util/Arrays.asList:([Ljava/lang/Object;)Ljava/util/List;
      73: areturn
      74: astore_1
      75: invokestatic  #17                 // Method org/wso2/carbon/tomcat/ext/realms/CarbonTomcatRealm.access$100:()Lorg/apache/commons/logging/Log;
      78: new           #18                 // class java/lang/StringBuilder
      81: dup
      82: invokespecial #19                 // Method java/lang/StringBuilder."<init>":()V
      85: ldc           #20                 // String Error occurred while retrieving the roles of the user -
      87: invokevirtual #21                 // Method java/lang/StringBuilder.append:(Ljava/lang/String;)Ljava/lang/StringBuilder;
      90: aload_0
      91: invokevirtual #21                 // Method java/lang/StringBuilder.append:(Ljava/lang/String;)Ljava/lang/StringBuilder;
      94: invokevirtual #22                 // Method java/lang/StringBuilder.toString:()Ljava/lang/String;
      97: aload_1
      98: invokeinterface #23,  3           // InterfaceMethod org/apache/commons/logging/Log.error:(Ljava/lang/Object;Ljava/lang/Throwable;)V
     103: aconst_null
     104: areturn
    Exception table:
       from    to  target type
           0    73    74   Class org/wso2/carbon/user/api/UserStoreException

  public java.lang.String getPassword();
    Code:
       0: new           #24                 // class java/lang/IllegalStateException
       3: dup
       4: ldc           #25                 // String When CarbonTomcatRealm is in operation this method Principal.getPassword() should never be called
       6: invokespecial #26                 // Method java/lang/IllegalStateException."<init>":(Ljava/lang/String;)V
       9: athrow

  public boolean hasRole(java.lang.String);
    Code:
       0: invokestatic  #8                  // Method org/wso2/carbon/tomcat/ext/internal/CarbonRealmServiceHolder.getRealmService:()Lorg/wso2/carbon/user/core/service/RealmService;
       3: astore_2
       4: aload_2
       5: invokeinterface #9,  1            // InterfaceMethod org/wso2/carbon/user/api/UserRealmService.getTenantManager:()Lorg/wso2/carbon/user/api/TenantManager;
      10: aload_0
      11: getfield      #3                  // Field tenantDomain:Ljava/lang/String;
      14: invokeinterface #10,  2           // InterfaceMethod org/wso2/carbon/user/api/TenantManager.getTenantId:(Ljava/lang/String;)I
      19: istore_3
      20: aload_0
      21: getfield      #27                 // Field name:Ljava/lang/String;
      24: bipush        64
      26: invokevirtual #28                 // Method java/lang/String.lastIndexOf:(I)I
      29: istore        4
      31: iload         4
      33: iconst_m1
      34: if_icmpne     44
      37: aload_0
      38: getfield      #27                 // Field name:Ljava/lang/String;
      41: goto          54
      44: aload_0
      45: getfield      #27                 // Field name:Ljava/lang/String;
      48: iconst_0
      49: iload         4
      51: invokevirtual #29                 // Method java/lang/String.substring:(II)Ljava/lang/String;
      54: astore        5
      56: invokestatic  #8                  // Method org/wso2/carbon/tomcat/ext/internal/CarbonRealmServiceHolder.getRealmService:()Lorg/wso2/carbon/user/core/service/RealmService;
      59: iload_3
      60: invokeinterface #30,  2           // InterfaceMethod org/wso2/carbon/user/core/service/RealmService.getTenantUserRealm:(I)Lorg/wso2/carbon/user/api/UserRealm;
      65: invokeinterface #13,  1           // InterfaceMethod org/wso2/carbon/user/api/UserRealm.getUserStoreManager:()Lorg/wso2/carbon/user/api/UserStoreManager;
      70: aload         5
      72: invokeinterface #14,  2           // InterfaceMethod org/wso2/carbon/user/api/UserStoreManager.getRoleListOfUser:(Ljava/lang/String;)[Ljava/lang/String;
      77: astore        6
      79: aload         6
      81: invokestatic  #31                 // Method java/util/Arrays.sort:([Ljava/lang/Object;)V
      84: aload         6
      86: aload_1
      87: invokestatic  #32                 // Method java/util/Arrays.binarySearch:([Ljava/lang/Object;Ljava/lang/Object;)I
      90: iconst_m1
      91: if_icmple     98
      94: iconst_1
      95: goto          99
      98: iconst_0
      99: ireturn
     100: astore_2
     101: invokestatic  #17                 // Method org/wso2/carbon/tomcat/ext/realms/CarbonTomcatRealm.access$100:()Lorg/apache/commons/logging/Log;
     104: ldc           #33                 // String Cannot check role
     106: aload_2
     107: invokeinterface #23,  3           // InterfaceMethod org/apache/commons/logging/Log.error:(Ljava/lang/Object;Ljava/lang/Throwable;)V
     112: iconst_0
     113: ireturn
    Exception table:
       from    to  target type
           0    99   100   Class org/wso2/carbon/user/api/UserStoreException
}
