Compiled from "BytecodeProviderImpl.java"
public class org.hibernate.bytecode.internal.javassist.BytecodeProviderImpl implements org.hibernate.bytecode.spi.BytecodeProvider {
  private static final org.hibernate.internal.CoreMessageLogger LOG;

  public org.hibernate.bytecode.internal.javassist.BytecodeProviderImpl();
    Code:
       0: aload_0
       1: invokespecial #1                  // Method java/lang/Object."<init>":()V
       4: return

  public org.hibernate.bytecode.spi.ProxyFactoryFactory getProxyFactoryFactory();
    Code:
       0: new           #2                  // class org/hibernate/bytecode/internal/javassist/ProxyFactoryFactoryImpl
       3: dup
       4: invokespecial #3                  // Method org/hibernate/bytecode/internal/javassist/ProxyFactoryFactoryImpl."<init>":()V
       7: areturn

  public org.hibernate.bytecode.spi.ReflectionOptimizer getReflectionOptimizer(java.lang.Class, java.lang.String[], java.lang.String[], java.lang.Class[]);
    Code:
       0: aload_1
       1: invokestatic  #4                  // Method org/hibernate/bytecode/internal/javassist/FastClass.create:(Ljava/lang/Class;)Lorg/hibernate/bytecode/internal/javassist/FastClass;
       4: astore        5
       6: aload_1
       7: aload_2
       8: aload_3
       9: aload         4
      11: invokestatic  #5                  // Method org/hibernate/bytecode/internal/javassist/BulkAccessor.create:(Ljava/lang/Class;[Ljava/lang/String;[Ljava/lang/String;[Ljava/lang/Class;)Lorg/hibernate/bytecode/internal/javassist/BulkAccessor;
      14: astore        6
      16: aload_1
      17: invokevirtual #6                  // Method java/lang/Class.isInterface:()Z
      20: ifne          65
      23: aload_1
      24: invokevirtual #7                  // Method java/lang/Class.getModifiers:()I
      27: invokestatic  #8                  // Method java/lang/reflect/Modifier.isAbstract:(I)Z
      30: ifne          65
      33: aload         5
      35: ifnonnull     44
      38: aconst_null
      39: astore        6
      41: goto          65
      44: aload         5
      46: invokevirtual #9                  // Method org/hibernate/bytecode/internal/javassist/FastClass.newInstance:()Ljava/lang/Object;
      49: astore        7
      51: aload         6
      53: aload         7
      55: aload         6
      57: aload         7
      59: invokevirtual #10                 // Method org/hibernate/bytecode/internal/javassist/BulkAccessor.getPropertyValues:(Ljava/lang/Object;)[Ljava/lang/Object;
      62: invokevirtual #11                 // Method org/hibernate/bytecode/internal/javassist/BulkAccessor.setPropertyValues:(Ljava/lang/Object;[Ljava/lang/Object;)V
      65: goto          196
      68: astore        7
      70: aconst_null
      71: astore        5
      73: aconst_null
      74: astore        6
      76: getstatic     #13                 // Field LOG:Lorg/hibernate/internal/CoreMessageLogger;
      79: invokeinterface #14,  1           // InterfaceMethod org/hibernate/internal/CoreMessageLogger.isDebugEnabled:()Z
      84: ifeq          196
      87: iconst_0
      88: istore        8
      90: aload         7
      92: instanceof    #15                 // class org/hibernate/bytecode/internal/javassist/BulkAccessorException
      95: ifeq          108
      98: aload         7
     100: checkcast     #15                 // class org/hibernate/bytecode/internal/javassist/BulkAccessorException
     103: invokevirtual #16                 // Method org/hibernate/bytecode/internal/javassist/BulkAccessorException.getIndex:()I
     106: istore        8
     108: iload         8
     110: iflt          166
     113: getstatic     #13                 // Field LOG:Lorg/hibernate/internal/CoreMessageLogger;
     116: ldc           #17                 // String Reflection optimizer disabled for %s [%s: %s (property %s)]
     118: iconst_4
     119: anewarray     #18                 // class java/lang/Object
     122: dup
     123: iconst_0
     124: aload_1
     125: invokevirtual #19                 // Method java/lang/Class.getName:()Ljava/lang/String;
     128: aastore
     129: dup
     130: iconst_1
     131: aload         7
     133: invokevirtual #20                 // Method java/lang/Object.getClass:()Ljava/lang/Class;
     136: invokevirtual #19                 // Method java/lang/Class.getName:()Ljava/lang/String;
     139: invokestatic  #21                 // Method org/hibernate/internal/util/StringHelper.unqualify:(Ljava/lang/String;)Ljava/lang/String;
     142: aastore
     143: dup
     144: iconst_2
     145: aload         7
     147: invokevirtual #22                 // Method java/lang/Throwable.getMessage:()Ljava/lang/String;
     150: aastore
     151: dup
     152: iconst_3
     153: aload_3
     154: iload         8
     156: aaload
     157: aastore
     158: invokeinterface #23,  3           // InterfaceMethod org/hibernate/internal/CoreMessageLogger.debugf:(Ljava/lang/String;[Ljava/lang/Object;)V
     163: goto          196
     166: getstatic     #13                 // Field LOG:Lorg/hibernate/internal/CoreMessageLogger;
     169: ldc           #24                 // String Reflection optimizer disabled for %s [%s: %s]
     171: aload_1
     172: invokevirtual #19                 // Method java/lang/Class.getName:()Ljava/lang/String;
     175: aload         7
     177: invokevirtual #20                 // Method java/lang/Object.getClass:()Ljava/lang/Class;
     180: invokevirtual #19                 // Method java/lang/Class.getName:()Ljava/lang/String;
     183: invokestatic  #21                 // Method org/hibernate/internal/util/StringHelper.unqualify:(Ljava/lang/String;)Ljava/lang/String;
     186: aload         7
     188: invokevirtual #22                 // Method java/lang/Throwable.getMessage:()Ljava/lang/String;
     191: invokeinterface #25,  5           // InterfaceMethod org/hibernate/internal/CoreMessageLogger.debugf:(Ljava/lang/String;Ljava/lang/Object;Ljava/lang/Object;Ljava/lang/Object;)V
     196: aload         5
     198: ifnull        233
     201: aload         6
     203: ifnull        233
     206: new           #26                 // class org/hibernate/bytecode/internal/javassist/ReflectionOptimizerImpl
     209: dup
     210: new           #27                 // class org/hibernate/bytecode/internal/javassist/InstantiationOptimizerAdapter
     213: dup
     214: aload         5
     216: invokespecial #28                 // Method org/hibernate/bytecode/internal/javassist/InstantiationOptimizerAdapter."<init>":(Lorg/hibernate/bytecode/internal/javassist/FastClass;)V
     219: new           #29                 // class org/hibernate/bytecode/internal/javassist/AccessOptimizerAdapter
     222: dup
     223: aload         6
     225: aload_1
     226: invokespecial #30                 // Method org/hibernate/bytecode/internal/javassist/AccessOptimizerAdapter."<init>":(Lorg/hibernate/bytecode/internal/javassist/BulkAccessor;Ljava/lang/Class;)V
     229: invokespecial #31                 // Method org/hibernate/bytecode/internal/javassist/ReflectionOptimizerImpl."<init>":(Lorg/hibernate/bytecode/spi/ReflectionOptimizer$InstantiationOptimizer;Lorg/hibernate/bytecode/spi/ReflectionOptimizer$AccessOptimizer;)V
     232: areturn
     233: aconst_null
     234: areturn
    Exception table:
       from    to  target type
           0    65    68   Class java/lang/Throwable

  public org.hibernate.bytecode.spi.ClassTransformer getTransformer(org.hibernate.bytecode.buildtime.spi.ClassFilter, org.hibernate.bytecode.buildtime.spi.FieldFilter);
    Code:
       0: new           #32                 // class org/hibernate/bytecode/internal/javassist/JavassistClassTransformer
       3: dup
       4: aload_1
       5: aload_2
       6: invokespecial #33                 // Method org/hibernate/bytecode/internal/javassist/JavassistClassTransformer."<init>":(Lorg/hibernate/bytecode/buildtime/spi/ClassFilter;Lorg/hibernate/bytecode/buildtime/spi/FieldFilter;)V
       9: areturn

  public org.hibernate.bytecode.spi.EntityInstrumentationMetadata getEntityInstrumentationMetadata(java.lang.Class);
    Code:
       0: new           #34                 // class org/hibernate/bytecode/internal/javassist/BytecodeProviderImpl$EntityInstrumentationMetadataImpl
       3: dup
       4: aload_1
       5: aconst_null
       6: invokespecial #35                 // Method org/hibernate/bytecode/internal/javassist/BytecodeProviderImpl$EntityInstrumentationMetadataImpl."<init>":(Ljava/lang/Class;Lorg/hibernate/bytecode/internal/javassist/BytecodeProviderImpl$1;)V
       9: areturn

  static {};
    Code:
       0: ldc           #36                 // class org/hibernate/internal/CoreMessageLogger
       2: ldc           #37                 // class org/hibernate/bytecode/internal/javassist/BytecodeProviderImpl
       4: invokevirtual #19                 // Method java/lang/Class.getName:()Ljava/lang/String;
       7: invokestatic  #38                 // Method org/jboss/logging/Logger.getMessageLogger:(Ljava/lang/Class;Ljava/lang/String;)Ljava/lang/Object;
      10: checkcast     #36                 // class org/hibernate/internal/CoreMessageLogger
      13: putstatic     #13                 // Field LOG:Lorg/hibernate/internal/CoreMessageLogger;
      16: return
}
