Compiled from "XMLFilterElementParametersConverter.java"
public class org.xwiki.filter.xml.internal.parameter.XMLFilterElementParametersConverter extends com.thoughtworks.xstream.converters.collections.MapConverter {
  public org.xwiki.filter.xml.internal.parameter.XMLFilterElementParametersConverter(com.thoughtworks.xstream.mapper.Mapper);
    Code:
       0: aload_0
       1: aload_1
       2: invokespecial #1                  // Method com/thoughtworks/xstream/converters/collections/MapConverter."<init>":(Lcom/thoughtworks/xstream/mapper/Mapper;)V
       5: return

  public boolean canConvert(java.lang.Class);
    Code:
       0: aload_1
       1: ldc           #2                  // class org/xwiki/filter/FilterEventParameters
       3: invokevirtual #3                  // Method java/lang/Object.equals:(Ljava/lang/Object;)Z
       6: ireturn

  protected java.lang.Object createCollection(java.lang.Class);
    Code:
       0: new           #2                  // class org/xwiki/filter/FilterEventParameters
       3: dup
       4: invokespecial #4                  // Method org/xwiki/filter/FilterEventParameters."<init>":()V
       7: areturn
}
