Compiled from "ScramInvalidServerSignatureException.java"
public class org.postgresql.shaded.com.ongres.scram.common.exception.ScramInvalidServerSignatureException extends org.postgresql.shaded.com.ongres.scram.common.exception.ScramException {
  public org.postgresql.shaded.com.ongres.scram.common.exception.ScramInvalidServerSignatureException(java.lang.String);
    Code:
       0: aload_0
       1: aload_1
       2: invokespecial #9                  // Method org/postgresql/shaded/com/ongres/scram/common/exception/ScramException."<init>":(Ljava/lang/String;)V
       5: return

  public org.postgresql.shaded.com.ongres.scram.common.exception.ScramInvalidServerSignatureException(java.lang.String, java.lang.Throwable);
    Code:
       0: aload_0
       1: aload_1
       2: aload_2
       3: invokespecial #16                 // Method org/postgresql/shaded/com/ongres/scram/common/exception/ScramException."<init>":(Ljava/lang/String;Ljava/lang/Throwable;)V
       6: return
}
