Compiled from "ProjectListDownloader.java"
public class org.sonarsource.sonarlint.core.container.connected.update.ProjectListDownloader {
  private final org.sonarsource.sonarlint.core.serverapi.component.ComponentApi componentApi;

  private final org.sonarsource.sonarlint.core.container.storage.ServerProjectsStore store;

  public org.sonarsource.sonarlint.core.container.connected.update.ProjectListDownloader(org.sonarsource.sonarlint.core.serverapi.ServerApiHelper, org.sonarsource.sonarlint.core.container.storage.ServerProjectsStore);
    Code:
       0: aload_0
       1: invokespecial #14                 // Method java/lang/Object."<init>":()V
       4: aload_0
       5: new           #16                 // class org/sonarsource/sonarlint/core/serverapi/ServerApi
       8: dup
       9: aload_1
      10: invokespecial #19                 // Method org/sonarsource/sonarlint/core/serverapi/ServerApi."<init>":(Lorg/sonarsource/sonarlint/core/serverapi/ServerApiHelper;)V
      13: invokevirtual #23                 // Method org/sonarsource/sonarlint/core/serverapi/ServerApi.component:()Lorg/sonarsource/sonarlint/core/serverapi/component/ComponentApi;
      16: putfield      #25                 // Field componentApi:Lorg/sonarsource/sonarlint/core/serverapi/component/ComponentApi;
      19: aload_0
      20: aload_2
      21: putfield      #27                 // Field store:Lorg/sonarsource/sonarlint/core/container/storage/ServerProjectsStore;
      24: return

  public java.util.Map<java.lang.String, org.sonarsource.sonarlint.core.serverapi.component.ServerProject> fetch(org.sonarsource.sonarlint.core.commons.progress.ProgressMonitor);
    Code:
       0: aload_0
       1: getfield      #25                 // Field componentApi:Lorg/sonarsource/sonarlint/core/serverapi/component/ComponentApi;
       4: aload_1
       5: invokevirtual #40                 // Method org/sonarsource/sonarlint/core/serverapi/component/ComponentApi.getAllProjects:(Lorg/sonarsource/sonarlint/core/commons/progress/ProgressMonitor;)Ljava/util/List;
       8: astore_2
       9: aload_0
      10: getfield      #27                 // Field store:Lorg/sonarsource/sonarlint/core/container/storage/ServerProjectsStore;
      13: aload_2
      14: invokevirtual #45                 // Method org/sonarsource/sonarlint/core/container/storage/ServerProjectsStore.store:(Ljava/util/List;)V
      17: aload_0
      18: getfield      #27                 // Field store:Lorg/sonarsource/sonarlint/core/container/storage/ServerProjectsStore;
      21: invokevirtual #49                 // Method org/sonarsource/sonarlint/core/container/storage/ServerProjectsStore.getAll:()Ljava/util/Map;
      24: areturn
}
