Compiled from "Tokenizer.java"
final class ch.qos.logback.core.subst.Tokenizer$TokenizerState extends java.lang.Enum<ch.qos.logback.core.subst.Tokenizer$TokenizerState> {
  public static final ch.qos.logback.core.subst.Tokenizer$TokenizerState LITERAL_STATE;

  public static final ch.qos.logback.core.subst.Tokenizer$TokenizerState START_STATE;

  public static final ch.qos.logback.core.subst.Tokenizer$TokenizerState DEFAULT_VAL_STATE;

  private static final ch.qos.logback.core.subst.Tokenizer$TokenizerState[] $VALUES;

  public static ch.qos.logback.core.subst.Tokenizer$TokenizerState[] values();
    Code:
       0: getstatic     #13                 // Field $VALUES:[Lch/qos/logback/core/subst/Tokenizer$TokenizerState;
       3: invokevirtual #17                 // Method "[Lch/qos/logback/core/subst/Tokenizer$TokenizerState;".clone:()Ljava/lang/Object;
       6: checkcast     #18                 // class "[Lch/qos/logback/core/subst/Tokenizer$TokenizerState;"
       9: areturn

  public static ch.qos.logback.core.subst.Tokenizer$TokenizerState valueOf(java.lang.String);
    Code:
       0: ldc           #1                  // class ch/qos/logback/core/subst/Tokenizer$TokenizerState
       2: aload_0
       3: invokestatic  #22                 // Method java/lang/Enum.valueOf:(Ljava/lang/Class;Ljava/lang/String;)Ljava/lang/Enum;
       6: checkcast     #1                  // class ch/qos/logback/core/subst/Tokenizer$TokenizerState
       9: areturn

  private ch.qos.logback.core.subst.Tokenizer$TokenizerState();
    Code:
       0: aload_0
       1: aload_1
       2: iload_2
       3: invokespecial #28                 // Method java/lang/Enum."<init>":(Ljava/lang/String;I)V
       6: return

  private static ch.qos.logback.core.subst.Tokenizer$TokenizerState[] $values();
    Code:
       0: iconst_3
       1: anewarray     #1                  // class ch/qos/logback/core/subst/Tokenizer$TokenizerState
       4: dup
       5: iconst_0
       6: getstatic     #3                  // Field LITERAL_STATE:Lch/qos/logback/core/subst/Tokenizer$TokenizerState;
       9: aastore
      10: dup
      11: iconst_1
      12: getstatic     #7                  // Field START_STATE:Lch/qos/logback/core/subst/Tokenizer$TokenizerState;
      15: aastore
      16: dup
      17: iconst_2
      18: getstatic     #10                 // Field DEFAULT_VAL_STATE:Lch/qos/logback/core/subst/Tokenizer$TokenizerState;
      21: aastore
      22: areturn

  static {};
    Code:
       0: new           #1                  // class ch/qos/logback/core/subst/Tokenizer$TokenizerState
       3: dup
       4: ldc           #32                 // String LITERAL_STATE
       6: iconst_0
       7: invokespecial #33                 // Method "<init>":(Ljava/lang/String;I)V
      10: putstatic     #3                  // Field LITERAL_STATE:Lch/qos/logback/core/subst/Tokenizer$TokenizerState;
      13: new           #1                  // class ch/qos/logback/core/subst/Tokenizer$TokenizerState
      16: dup
      17: ldc           #34                 // String START_STATE
      19: iconst_1
      20: invokespecial #33                 // Method "<init>":(Ljava/lang/String;I)V
      23: putstatic     #7                  // Field START_STATE:Lch/qos/logback/core/subst/Tokenizer$TokenizerState;
      26: new           #1                  // class ch/qos/logback/core/subst/Tokenizer$TokenizerState
      29: dup
      30: ldc           #35                 // String DEFAULT_VAL_STATE
      32: iconst_2
      33: invokespecial #33                 // Method "<init>":(Ljava/lang/String;I)V
      36: putstatic     #10                 // Field DEFAULT_VAL_STATE:Lch/qos/logback/core/subst/Tokenizer$TokenizerState;
      39: invokestatic  #36                 // Method $values:()[Lch/qos/logback/core/subst/Tokenizer$TokenizerState;
      42: putstatic     #13                 // Field $VALUES:[Lch/qos/logback/core/subst/Tokenizer$TokenizerState;
      45: return
}
