Compiled from "DynamicDefaultKey.java"
class com.vladsch.flexmark.util.collection.DynamicDefaultKey$1 implements com.vladsch.flexmark.util.collection.DataValueFactory<T> {
  final com.vladsch.flexmark.util.options.DataKey val$defaultKey;

  com.vladsch.flexmark.util.collection.DynamicDefaultKey$1(com.vladsch.flexmark.util.options.DataKey);
    Code:
       0: aload_0
       1: aload_1
       2: putfield      #1                  // Field val$defaultKey:Lcom/vladsch/flexmark/util/options/DataKey;
       5: aload_0
       6: invokespecial #2                  // Method java/lang/Object."<init>":()V
       9: return

  public T create(com.vladsch.flexmark.util.options.DataHolder);
    Code:
       0: aload_0
       1: getfield      #1                  // Field val$defaultKey:Lcom/vladsch/flexmark/util/options/DataKey;
       4: aload_1
       5: invokevirtual #3                  // Method com/vladsch/flexmark/util/options/DataKey.getFrom:(Lcom/vladsch/flexmark/util/options/DataHolder;)Ljava/lang/Object;
       8: areturn

  public java.lang.Object create(java.lang.Object);
    Code:
       0: aload_0
       1: aload_1
       2: checkcast     #4                  // class com/vladsch/flexmark/util/options/DataHolder
       5: invokevirtual #5                  // Method create:(Lcom/vladsch/flexmark/util/options/DataHolder;)Ljava/lang/Object;
       8: areturn
}
