Compiled from "OrderedMultiMap.java"
class com.vladsch.flexmark.util.collection.OrderedMultiMap$3 implements com.vladsch.flexmark.util.collection.iteration.Indexed<java.util.Map$Entry<K, V>> {
  final com.vladsch.flexmark.util.collection.OrderedMultiMap this$0;

  com.vladsch.flexmark.util.collection.OrderedMultiMap$3(com.vladsch.flexmark.util.collection.OrderedMultiMap);
    Code:
       0: aload_0
       1: aload_1
       2: putfield      #1                  // Field this$0:Lcom/vladsch/flexmark/util/collection/OrderedMultiMap;
       5: aload_0
       6: invokespecial #2                  // Method java/lang/Object."<init>":()V
       9: return

  public java.util.Map$Entry<K, V> get(int);
    Code:
       0: aload_0
       1: getfield      #1                  // Field this$0:Lcom/vladsch/flexmark/util/collection/OrderedMultiMap;
       4: iload_1
       5: invokestatic  #3                  // Method com/vladsch/flexmark/util/collection/OrderedMultiMap.access$800:(Lcom/vladsch/flexmark/util/collection/OrderedMultiMap;I)Ljava/util/Map$Entry;
       8: areturn

  public void set(int, java.util.Map$Entry<K, V>);
    Code:
       0: new           #4                  // class java/lang/UnsupportedOperationException
       3: dup
       4: invokespecial #5                  // Method java/lang/UnsupportedOperationException."<init>":()V
       7: athrow

  public void removeAt(int);
    Code:
       0: aload_0
       1: getfield      #1                  // Field this$0:Lcom/vladsch/flexmark/util/collection/OrderedMultiMap;
       4: iload_1
       5: invokestatic  #6                  // Method com/vladsch/flexmark/util/collection/OrderedMultiMap.access$900:(Lcom/vladsch/flexmark/util/collection/OrderedMultiMap;I)Z
       8: pop
       9: return

  public int size();
    Code:
       0: aload_0
       1: getfield      #1                  // Field this$0:Lcom/vladsch/flexmark/util/collection/OrderedMultiMap;
       4: invokevirtual #7                  // Method com/vladsch/flexmark/util/collection/OrderedMultiMap.size:()I
       7: ireturn

  public int modificationCount();
    Code:
       0: aload_0
       1: getfield      #1                  // Field this$0:Lcom/vladsch/flexmark/util/collection/OrderedMultiMap;
       4: invokevirtual #8                  // Method com/vladsch/flexmark/util/collection/OrderedMultiMap.getModificationCount:()I
       7: ireturn

  public void set(int, java.lang.Object);
    Code:
       0: aload_0
       1: iload_1
       2: aload_2
       3: checkcast     #9                  // class java/util/Map$Entry
       6: invokevirtual #10                 // Method set:(ILjava/util/Map$Entry;)V
       9: return

  public java.lang.Object get(int);
    Code:
       0: aload_0
       1: iload_1
       2: invokevirtual #11                 // Method get:(I)Ljava/util/Map$Entry;
       5: areturn
}
