Compiled from "CoreXMLDeserializers.java"
public class org.apache.htrace.shaded.fasterxml.jackson.databind.ext.CoreXMLDeserializers$Std extends org.apache.htrace.shaded.fasterxml.jackson.databind.deser.std.FromStringDeserializer<java.lang.Object> {
  private static final long serialVersionUID;

  protected final int _kind;

  public org.apache.htrace.shaded.fasterxml.jackson.databind.ext.CoreXMLDeserializers$Std(java.lang.Class<?>, int);
    Code:
       0: aload_0
       1: aload_1
       2: invokespecial #20                 // Method org/apache/htrace/shaded/fasterxml/jackson/databind/deser/std/FromStringDeserializer."<init>":(Ljava/lang/Class;)V
       5: aload_0
       6: iload_2
       7: putfield      #22                 // Field _kind:I
      10: return

  public java.lang.Object deserialize(org.apache.htrace.shaded.fasterxml.jackson.core.JsonParser, org.apache.htrace.shaded.fasterxml.jackson.databind.DeserializationContext) throws java.io.IOException, org.apache.htrace.shaded.fasterxml.jackson.core.JsonProcessingException;
    Code:
       0: aload_0
       1: getfield      #22                 // Field _kind:I
       4: iconst_2
       5: if_icmpne     63
       8: aload_0
       9: aload_1
      10: aload_2
      11: invokevirtual #38                 // Method _parseDate:(Lorg/apache/htrace/shaded/fasterxml/jackson/core/JsonParser;Lorg/apache/htrace/shaded/fasterxml/jackson/databind/DeserializationContext;)Ljava/util/Date;
      14: astore_3
      15: aload_3
      16: ifnonnull     21
      19: aconst_null
      20: areturn
      21: new           #42                 // class java/util/GregorianCalendar
      24: dup
      25: invokespecial #45                 // Method java/util/GregorianCalendar."<init>":()V
      28: astore        4
      30: aload         4
      32: aload_3
      33: invokevirtual #49                 // Method java/util/GregorianCalendar.setTime:(Ljava/util/Date;)V
      36: aload_2
      37: invokevirtual #55                 // Method org/apache/htrace/shaded/fasterxml/jackson/databind/DeserializationContext.getTimeZone:()Ljava/util/TimeZone;
      40: astore        5
      42: aload         5
      44: ifnull        54
      47: aload         4
      49: aload         5
      51: invokevirtual #59                 // Method java/util/GregorianCalendar.setTimeZone:(Ljava/util/TimeZone;)V
      54: getstatic     #65                 // Field org/apache/htrace/shaded/fasterxml/jackson/databind/ext/CoreXMLDeserializers._dataTypeFactory:Ljavax/xml/datatype/DatatypeFactory;
      57: aload         4
      59: invokevirtual #71                 // Method javax/xml/datatype/DatatypeFactory.newXMLGregorianCalendar:(Ljava/util/GregorianCalendar;)Ljavax/xml/datatype/XMLGregorianCalendar;
      62: areturn
      63: aload_0
      64: aload_1
      65: aload_2
      66: invokespecial #73                 // Method org/apache/htrace/shaded/fasterxml/jackson/databind/deser/std/FromStringDeserializer.deserialize:(Lorg/apache/htrace/shaded/fasterxml/jackson/core/JsonParser;Lorg/apache/htrace/shaded/fasterxml/jackson/databind/DeserializationContext;)Ljava/lang/Object;
      69: areturn

  protected java.lang.Object _deserialize(java.lang.String, org.apache.htrace.shaded.fasterxml.jackson.databind.DeserializationContext) throws java.lang.IllegalArgumentException;
    Code:
       0: aload_0
       1: getfield      #22                 // Field _kind:I
       4: lookupswitch  { // 2
                     1: 32
                     3: 40
               default: 45
          }
      32: getstatic     #65                 // Field org/apache/htrace/shaded/fasterxml/jackson/databind/ext/CoreXMLDeserializers._dataTypeFactory:Ljavax/xml/datatype/DatatypeFactory;
      35: aload_1
      36: invokevirtual #91                 // Method javax/xml/datatype/DatatypeFactory.newDuration:(Ljava/lang/String;)Ljavax/xml/datatype/Duration;
      39: areturn
      40: aload_1
      41: invokestatic  #97                 // Method javax/xml/namespace/QName.valueOf:(Ljava/lang/String;)Ljavax/xml/namespace/QName;
      44: areturn
      45: new           #99                 // class java/lang/IllegalStateException
      48: dup
      49: invokespecial #100                // Method java/lang/IllegalStateException."<init>":()V
      52: athrow
}
