Compiled from "RowServiceInputStream.java"
public class org.hpccsystems.dfs.client.RowServiceInputStream$RestartInformation {
  public long streamPos;

  public byte[] tokenBin;

  public org.hpccsystems.dfs.client.RowServiceInputStream$RestartInformation();
    Code:
       0: aload_0
       1: invokespecial #1                  // Method java/lang/Object."<init>":()V
       4: aload_0
       5: lconst_0
       6: putfield      #2                  // Field streamPos:J
       9: aload_0
      10: aconst_null
      11: putfield      #3                  // Field tokenBin:[B
      14: return
}
