Compiled from "AggregateFuture.java"
class com.google.common.util.concurrent.AggregateFuture$2 implements java.lang.Runnable {
  final com.google.common.collect.ImmutableCollection val$localFutures;

  final com.google.common.util.concurrent.AggregateFuture this$0;

  com.google.common.util.concurrent.AggregateFuture$2(com.google.common.util.concurrent.AggregateFuture, com.google.common.collect.ImmutableCollection);
    Code:
       0: aload_0
       1: aload_1
       2: putfield      #1                  // Field this$0:Lcom/google/common/util/concurrent/AggregateFuture;
       5: aload_0
       6: aload_2
       7: putfield      #2                  // Field val$localFutures:Lcom/google/common/collect/ImmutableCollection;
      10: aload_0
      11: invokespecial #3                  // Method java/lang/Object."<init>":()V
      14: return

  public void run();
    Code:
       0: aload_0
       1: getfield      #1                  // Field this$0:Lcom/google/common/util/concurrent/AggregateFuture;
       4: aload_0
       5: getfield      #2                  // Field val$localFutures:Lcom/google/common/collect/ImmutableCollection;
       8: invokestatic  #4                  // Method com/google/common/util/concurrent/AggregateFuture.access$200:(Lcom/google/common/util/concurrent/AggregateFuture;Lcom/google/common/collect/ImmutableCollection;)V
      11: return
}
