Compiled from "MoreExecutors.java"
class com.google.common.util.concurrent.MoreExecutors$5 implements java.util.concurrent.Executor {
  final java.util.concurrent.Executor val$delegate;

  final com.google.common.util.concurrent.AbstractFuture val$future;

  com.google.common.util.concurrent.MoreExecutors$5(java.util.concurrent.Executor, com.google.common.util.concurrent.AbstractFuture);
    Code:
       0: aload_0
       1: aload_1
       2: putfield      #1                  // Field val$delegate:Ljava/util/concurrent/Executor;
       5: aload_0
       6: aload_2
       7: putfield      #2                  // Field val$future:Lcom/google/common/util/concurrent/AbstractFuture;
      10: aload_0
      11: invokespecial #3                  // Method java/lang/Object."<init>":()V
      14: return

  public void execute(java.lang.Runnable);
    Code:
       0: aload_0
       1: getfield      #1                  // Field val$delegate:Ljava/util/concurrent/Executor;
       4: aload_1
       5: invokeinterface #4,  2            // InterfaceMethod java/util/concurrent/Executor.execute:(Ljava/lang/Runnable;)V
      10: goto          23
      13: astore_2
      14: aload_0
      15: getfield      #2                  // Field val$future:Lcom/google/common/util/concurrent/AbstractFuture;
      18: aload_2
      19: invokevirtual #6                  // Method com/google/common/util/concurrent/AbstractFuture.setException:(Ljava/lang/Throwable;)Z
      22: pop
      23: return
    Exception table:
       from    to  target type
           0    10    13   Class java/util/concurrent/RejectedExecutionException
}
