Compiled from "contexts.scala"
public abstract class unfiltered.jetty.ContextAdder$class {
  public static unfiltered.jetty.ContextAdder plan(unfiltered.jetty.ContextAdder, javax.servlet.Filter);
    Code:
       0: aload_0
       1: new           #9                  // class unfiltered/jetty/FilterAdder
       4: dup
       5: getstatic     #15                 // Field unfiltered/jetty/BasicFilterHolder$.MODULE$:Lunfiltered/jetty/BasicFilterHolder$;
       8: aload_1
       9: invokevirtual #19                 // Method unfiltered/jetty/BasicFilterHolder$.apply:(Ljavax/servlet/Filter;)Lorg/eclipse/jetty/servlet/FilterHolder;
      12: getstatic     #24                 // Field unfiltered/jetty/FilterAdder$.MODULE$:Lunfiltered/jetty/FilterAdder$;
      15: invokevirtual #28                 // Method unfiltered/jetty/FilterAdder$.apply$default$2:()Ljava/lang/String;
      18: getstatic     #24                 // Field unfiltered/jetty/FilterAdder$.MODULE$:Lunfiltered/jetty/FilterAdder$;
      21: invokevirtual #32                 // Method unfiltered/jetty/FilterAdder$.apply$default$3:()Ljava/util/EnumSet;
      24: invokespecial #36                 // Method unfiltered/jetty/FilterAdder."<init>":(Lorg/eclipse/jetty/servlet/FilterHolder;Ljava/lang/String;Ljava/util/EnumSet;)V
      27: invokeinterface #42,  2           // InterfaceMethod unfiltered/jetty/ContextAdder.filterAdder:(Lunfiltered/jetty/FilterAdder;)Lunfiltered/jetty/ContextAdder;
      32: areturn

  public static unfiltered.jetty.ContextAdder filter(unfiltered.jetty.ContextAdder, javax.servlet.Filter);
    Code:
       0: aload_0
       1: aload_1
       2: invokeinterface #49,  2           // InterfaceMethod unfiltered/jetty/ContextAdder.plan:(Ljavax/servlet/Filter;)Lunfiltered/jetty/ContextAdder;
       7: areturn

  public static void $init$(unfiltered.jetty.ContextAdder);
    Code:
       0: return
}
