Compiled from "Update.java"
public abstract class org.apache.jena.update.Update implements org.apache.jena.sparql.util.PrintSerializable {
  public org.apache.jena.update.Update();
    Code:
       0: aload_0
       1: invokespecial #1                  // Method java/lang/Object."<init>":()V
       4: return

  public abstract void visit(org.apache.jena.sparql.modify.request.UpdateVisitor);

  public void output(org.apache.jena.atlas.io.IndentedWriter, org.apache.jena.sparql.serializer.SerializationContext);
    Code:
       0: aload_0
       1: aload_1
       2: aload_2
       3: invokestatic  #2                  // Method org/apache/jena/sparql/modify/request/UpdateWriter.output:(Lorg/apache/jena/update/Update;Lorg/apache/jena/atlas/io/IndentedWriter;Lorg/apache/jena/sparql/serializer/SerializationContext;)V
       6: return

  public void output(org.apache.jena.atlas.io.IndentedWriter);
    Code:
       0: aload_0
       1: aload_1
       2: aconst_null
       3: invokestatic  #2                  // Method org/apache/jena/sparql/modify/request/UpdateWriter.output:(Lorg/apache/jena/update/Update;Lorg/apache/jena/atlas/io/IndentedWriter;Lorg/apache/jena/sparql/serializer/SerializationContext;)V
       6: return

  public java.lang.String toString(org.apache.jena.shared.PrefixMapping);
    Code:
       0: aload_0
       1: aload_1
       2: invokestatic  #3                  // Method org/apache/jena/sparql/util/QueryOutputUtils.toString:(Lorg/apache/jena/sparql/util/PrintSerializable;Lorg/apache/jena/shared/PrefixMapping;)Ljava/lang/String;
       5: areturn

  public java.lang.String toString();
    Code:
       0: aload_0
       1: invokestatic  #4                  // Method org/apache/jena/atlas/io/PrintUtils.toString:(Lorg/apache/jena/atlas/io/Printable;)Ljava/lang/String;
       4: areturn

  public abstract boolean equalTo(org.apache.jena.update.Update, org.apache.jena.sparql.util.NodeIsomorphismMap);
}
