Compiled from "DiscoveryProto.java"
public final class io.grpc.xds.shaded.io.envoyproxy.envoy.service.discovery.v3.DiscoveryProto {
  static final com.google.protobuf.Descriptors$Descriptor internal_static_envoy_service_discovery_v3_DiscoveryRequest_descriptor;

  static final com.google.protobuf.GeneratedMessageV3$FieldAccessorTable internal_static_envoy_service_discovery_v3_DiscoveryRequest_fieldAccessorTable;

  static final com.google.protobuf.Descriptors$Descriptor internal_static_envoy_service_discovery_v3_DiscoveryResponse_descriptor;

  static final com.google.protobuf.GeneratedMessageV3$FieldAccessorTable internal_static_envoy_service_discovery_v3_DiscoveryResponse_fieldAccessorTable;

  static final com.google.protobuf.Descriptors$Descriptor internal_static_envoy_service_discovery_v3_DeltaDiscoveryRequest_descriptor;

  static final com.google.protobuf.GeneratedMessageV3$FieldAccessorTable internal_static_envoy_service_discovery_v3_DeltaDiscoveryRequest_fieldAccessorTable;

  static final com.google.protobuf.Descriptors$Descriptor internal_static_envoy_service_discovery_v3_DeltaDiscoveryRequest_InitialResourceVersionsEntry_descriptor;

  static final com.google.protobuf.GeneratedMessageV3$FieldAccessorTable internal_static_envoy_service_discovery_v3_DeltaDiscoveryRequest_InitialResourceVersionsEntry_fieldAccessorTable;

  static final com.google.protobuf.Descriptors$Descriptor internal_static_envoy_service_discovery_v3_DeltaDiscoveryResponse_descriptor;

  static final com.google.protobuf.GeneratedMessageV3$FieldAccessorTable internal_static_envoy_service_discovery_v3_DeltaDiscoveryResponse_fieldAccessorTable;

  static final com.google.protobuf.Descriptors$Descriptor internal_static_envoy_service_discovery_v3_Resource_descriptor;

  static final com.google.protobuf.GeneratedMessageV3$FieldAccessorTable internal_static_envoy_service_discovery_v3_Resource_fieldAccessorTable;

  static final com.google.protobuf.Descriptors$Descriptor internal_static_envoy_service_discovery_v3_Resource_CacheControl_descriptor;

  static final com.google.protobuf.GeneratedMessageV3$FieldAccessorTable internal_static_envoy_service_discovery_v3_Resource_CacheControl_fieldAccessorTable;

  private static com.google.protobuf.Descriptors$FileDescriptor descriptor;

  private io.grpc.xds.shaded.io.envoyproxy.envoy.service.discovery.v3.DiscoveryProto();
    Code:
       0: aload_0
       1: invokespecial #45                 // Method java/lang/Object."<init>":()V
       4: return

  public static void registerAllExtensions(com.google.protobuf.ExtensionRegistryLite);
    Code:
       0: return

  public static void registerAllExtensions(com.google.protobuf.ExtensionRegistry);
    Code:
       0: aload_0
       1: invokestatic  #54                 // Method registerAllExtensions:(Lcom/google/protobuf/ExtensionRegistryLite;)V
       4: return

  public static com.google.protobuf.Descriptors$FileDescriptor getDescriptor();
    Code:
       0: getstatic     #59                 // Field descriptor:Lcom/google/protobuf/Descriptors$FileDescriptor;
       3: areturn

  static {};
    Code:
       0: iconst_1
       1: anewarray     #62                 // class java/lang/String
       4: dup
       5: iconst_0
       6: ldc           #64                 // String \n*envoy/service/discovery/v3/discovery.proto\u0012\u001aenvoy.service.discovery.v3\u001a\u001fenvoy/config/core/v3/base.proto\u001a\u0019google/protobuf/any.proto\u001a\u001egoogle/protobuf/duration.proto\u001a\u0017google/rpc/status.proto\u001a\u001dudpa/annotations/status.proto\u001a!udpa/annotations/versioning.proto\"ä\u0001\n\u0010DiscoveryRequest\u0012\u0014\n\fversion_info\u0018\u0001 \u0001(\t\u0012(\n\u0004node\u0018\u0002 \u0001(\u000b2\u001a.envoy.config.core.v3.Node\u0012\u0016\n\u000eresource_names\u0018\u0003 \u0003(\t\u0012\u0010\n\btype_url\u0018\u0004 \u0001(\t\u0012\u0016\n\u000eresponse_nonce\u0018\u0005 \u0001(\t\u0012(\n\ferror_detail\u0018\u0006 \u0001(\u000b2\u0012.google.rpc.Status:$\u009aÅ\u0088\u001e\u001f\n\u001denvoy.api.v2.DiscoveryRequest\"å\u0001\n\u0011DiscoveryResponse\u0012\u0014\n\fversion_info\u0018\u0001 \u0001(\t\u0012\'\n\tresources\u0018\u0002 \u0003(\u000b2\u0014.google.protobuf.Any\u0012\u000e\n\u0006canary\u0018\u0003 \u0001(\b\u0012\u0010\n\btype_url\u0018\u0004 \u0001(\t\u0012\r\n\u0005nonce\u0018\u0005 \u0001(\t\u00129\n\rcontrol_plane\u0018\u0006 \u0001(\u000b2\".envoy.config.core.v3.ControlPlane:%\u009aÅ\u0088\u001e \n\u001eenvoy.api.v2.DiscoveryResponse\"¹\u0003\n\u0015DeltaDiscoveryRequest\u0012(\n\u0004node\u0018\u0001 \u0001(\u000b2\u001a.envoy.config.core.v3.Node\u0012\u0010\n\btype_url\u0018\u0002 \u0001(\t\u0012 \n\u0018resource_names_subscribe\u0018\u0003 \u0003(\t\u0012\"\n\u001aresource_names_unsubscribe\u0018\u0004 \u0003(\t\u0012q\n\u0019initial_resource_versions\u0018\u0005 \u0003(\u000b2N.envoy.service.discovery.v3.DeltaDiscoveryRequest.InitialResourceVersionsEntry\u0012\u0016\n\u000eresponse_nonce\u0018\u0006 \u0001(\t\u0012(\n\ferror_detail\u0018\u0007 \u0001(\u000b2\u0012.google.rpc.Status\u001a>\n\u001cInitialResourceVersionsEntry\u0012\u000b\n\u0003key\u0018\u0001 \u0001(\t\u0012\r\n\u0005value\u0018\u0002 \u0001(\t:\u00028\u0001:)\u009aÅ\u0088\u001e$\n\"envoy.api.v2.DeltaDiscoveryRequest\"\u0091\u0002\n\u0016DeltaDiscoveryResponse\u0012\u001b\n\u0013system_version_info\u0018\u0001 \u0001(\t\u00127\n\tresources\u0018\u0002 \u0003(\u000b2$.envoy.service.discovery.v3.Resource\u0012\u0010\n\btype_url\u0018\u0004 \u0001(\t\u0012\u0019\n\u0011removed_resources\u0018\u0006 \u0003(\t\u0012\r\n\u0005nonce\u0018\u0005 \u0001(\t\u00129\n\rcontrol_plane\u0018\u0007 \u0001(\u000b2\".envoy.config.core.v3.ControlPlane:*\u009aÅ\u0088\u001e%\n#envoy.api.v2.DeltaDiscoveryResponse\"\u0098\u0002\n\bResource\u0012\f\n\u0004name\u0018\u0003 \u0001(\t\u0012\u000f\n\u0007aliases\u0018\u0004 \u0003(\t\u0012\u000f\n\u0007version\u0018\u0001 \u0001(\t\u0012&\n\bresource\u0018\u0002 \u0001(\u000b2\u0014.google.protobuf.Any\u0012&\n\u0003ttl\u0018\u0006 \u0001(\u000b2\u0019.google.protobuf.Duration\u0012H\n\rcache_control\u0018\u0007 \u0001(\u000b21.envoy.service.discovery.v3.Resource.CacheControl\u001a$\n\fCacheControl\u0012\u0014\n\fdo_not_cache\u0018\u0001 \u0001(\b:\u001c\u009aÅ\u0088\u001e\u0017\n\u0015envoy.api.v2.ResourceBD\n(io.envoyproxy.envoy.service.discovery.v3B\u000eDiscoveryProtoP\u0001º\u0080ÈÑ\u0006\u0002\u0010\u0002b\u0006proto3
       8: aastore
       9: astore_0
      10: aload_0
      11: bipush        6
      13: anewarray     #17                 // class com/google/protobuf/Descriptors$FileDescriptor
      16: dup
      17: iconst_0
      18: invokestatic  #68                 // Method io/grpc/xds/shaded/io/envoyproxy/envoy/config/core/v3/BaseProto.getDescriptor:()Lcom/google/protobuf/Descriptors$FileDescriptor;
      21: aastore
      22: dup
      23: iconst_1
      24: invokestatic  #71                 // Method com/google/protobuf/AnyProto.getDescriptor:()Lcom/google/protobuf/Descriptors$FileDescriptor;
      27: aastore
      28: dup
      29: iconst_2
      30: invokestatic  #74                 // Method com/google/protobuf/DurationProto.getDescriptor:()Lcom/google/protobuf/Descriptors$FileDescriptor;
      33: aastore
      34: dup
      35: iconst_3
      36: invokestatic  #77                 // Method com/google/rpc/StatusProto.getDescriptor:()Lcom/google/protobuf/Descriptors$FileDescriptor;
      39: aastore
      40: dup
      41: iconst_4
      42: invokestatic  #80                 // Method io/grpc/xds/shaded/udpa/annotations/Status.getDescriptor:()Lcom/google/protobuf/Descriptors$FileDescriptor;
      45: aastore
      46: dup
      47: iconst_5
      48: invokestatic  #83                 // Method io/grpc/xds/shaded/udpa/annotations/Versioning.getDescriptor:()Lcom/google/protobuf/Descriptors$FileDescriptor;
      51: aastore
      52: invokestatic  #87                 // Method com/google/protobuf/Descriptors$FileDescriptor.internalBuildGeneratedFileFrom:([Ljava/lang/String;[Lcom/google/protobuf/Descriptors$FileDescriptor;)Lcom/google/protobuf/Descriptors$FileDescriptor;
      55: putstatic     #59                 // Field descriptor:Lcom/google/protobuf/Descriptors$FileDescriptor;
      58: invokestatic  #88                 // Method getDescriptor:()Lcom/google/protobuf/Descriptors$FileDescriptor;
      61: invokevirtual #92                 // Method com/google/protobuf/Descriptors$FileDescriptor.getMessageTypes:()Ljava/util/List;
      64: iconst_0
      65: invokeinterface #98,  2           // InterfaceMethod java/util/List.get:(I)Ljava/lang/Object;
      70: checkcast     #7                  // class com/google/protobuf/Descriptors$Descriptor
      73: putstatic     #100                // Field internal_static_envoy_service_discovery_v3_DiscoveryRequest_descriptor:Lcom/google/protobuf/Descriptors$Descriptor;
      76: new           #12                 // class com/google/protobuf/GeneratedMessageV3$FieldAccessorTable
      79: dup
      80: getstatic     #100                // Field internal_static_envoy_service_discovery_v3_DiscoveryRequest_descriptor:Lcom/google/protobuf/Descriptors$Descriptor;
      83: bipush        6
      85: anewarray     #62                 // class java/lang/String
      88: dup
      89: iconst_0
      90: ldc           #102                // String VersionInfo
      92: aastore
      93: dup
      94: iconst_1
      95: ldc           #104                // String Node
      97: aastore
      98: dup
      99: iconst_2
     100: ldc           #106                // String ResourceNames
     102: aastore
     103: dup
     104: iconst_3
     105: ldc           #108                // String TypeUrl
     107: aastore
     108: dup
     109: iconst_4
     110: ldc           #110                // String ResponseNonce
     112: aastore
     113: dup
     114: iconst_5
     115: ldc           #112                // String ErrorDetail
     117: aastore
     118: invokespecial #115                // Method com/google/protobuf/GeneratedMessageV3$FieldAccessorTable."<init>":(Lcom/google/protobuf/Descriptors$Descriptor;[Ljava/lang/String;)V
     121: putstatic     #117                // Field internal_static_envoy_service_discovery_v3_DiscoveryRequest_fieldAccessorTable:Lcom/google/protobuf/GeneratedMessageV3$FieldAccessorTable;
     124: invokestatic  #88                 // Method getDescriptor:()Lcom/google/protobuf/Descriptors$FileDescriptor;
     127: invokevirtual #92                 // Method com/google/protobuf/Descriptors$FileDescriptor.getMessageTypes:()Ljava/util/List;
     130: iconst_1
     131: invokeinterface #98,  2           // InterfaceMethod java/util/List.get:(I)Ljava/lang/Object;
     136: checkcast     #7                  // class com/google/protobuf/Descriptors$Descriptor
     139: putstatic     #119                // Field internal_static_envoy_service_discovery_v3_DiscoveryResponse_descriptor:Lcom/google/protobuf/Descriptors$Descriptor;
     142: new           #12                 // class com/google/protobuf/GeneratedMessageV3$FieldAccessorTable
     145: dup
     146: getstatic     #119                // Field internal_static_envoy_service_discovery_v3_DiscoveryResponse_descriptor:Lcom/google/protobuf/Descriptors$Descriptor;
     149: bipush        6
     151: anewarray     #62                 // class java/lang/String
     154: dup
     155: iconst_0
     156: ldc           #102                // String VersionInfo
     158: aastore
     159: dup
     160: iconst_1
     161: ldc           #121                // String Resources
     163: aastore
     164: dup
     165: iconst_2
     166: ldc           #123                // String Canary
     168: aastore
     169: dup
     170: iconst_3
     171: ldc           #108                // String TypeUrl
     173: aastore
     174: dup
     175: iconst_4
     176: ldc           #125                // String Nonce
     178: aastore
     179: dup
     180: iconst_5
     181: ldc           #127                // String ControlPlane
     183: aastore
     184: invokespecial #115                // Method com/google/protobuf/GeneratedMessageV3$FieldAccessorTable."<init>":(Lcom/google/protobuf/Descriptors$Descriptor;[Ljava/lang/String;)V
     187: putstatic     #129                // Field internal_static_envoy_service_discovery_v3_DiscoveryResponse_fieldAccessorTable:Lcom/google/protobuf/GeneratedMessageV3$FieldAccessorTable;
     190: invokestatic  #88                 // Method getDescriptor:()Lcom/google/protobuf/Descriptors$FileDescriptor;
     193: invokevirtual #92                 // Method com/google/protobuf/Descriptors$FileDescriptor.getMessageTypes:()Ljava/util/List;
     196: iconst_2
     197: invokeinterface #98,  2           // InterfaceMethod java/util/List.get:(I)Ljava/lang/Object;
     202: checkcast     #7                  // class com/google/protobuf/Descriptors$Descriptor
     205: putstatic     #131                // Field internal_static_envoy_service_discovery_v3_DeltaDiscoveryRequest_descriptor:Lcom/google/protobuf/Descriptors$Descriptor;
     208: new           #12                 // class com/google/protobuf/GeneratedMessageV3$FieldAccessorTable
     211: dup
     212: getstatic     #131                // Field internal_static_envoy_service_discovery_v3_DeltaDiscoveryRequest_descriptor:Lcom/google/protobuf/Descriptors$Descriptor;
     215: bipush        7
     217: anewarray     #62                 // class java/lang/String
     220: dup
     221: iconst_0
     222: ldc           #104                // String Node
     224: aastore
     225: dup
     226: iconst_1
     227: ldc           #108                // String TypeUrl
     229: aastore
     230: dup
     231: iconst_2
     232: ldc           #133                // String ResourceNamesSubscribe
     234: aastore
     235: dup
     236: iconst_3
     237: ldc           #135                // String ResourceNamesUnsubscribe
     239: aastore
     240: dup
     241: iconst_4
     242: ldc           #137                // String InitialResourceVersions
     244: aastore
     245: dup
     246: iconst_5
     247: ldc           #110                // String ResponseNonce
     249: aastore
     250: dup
     251: bipush        6
     253: ldc           #112                // String ErrorDetail
     255: aastore
     256: invokespecial #115                // Method com/google/protobuf/GeneratedMessageV3$FieldAccessorTable."<init>":(Lcom/google/protobuf/Descriptors$Descriptor;[Ljava/lang/String;)V
     259: putstatic     #139                // Field internal_static_envoy_service_discovery_v3_DeltaDiscoveryRequest_fieldAccessorTable:Lcom/google/protobuf/GeneratedMessageV3$FieldAccessorTable;
     262: getstatic     #131                // Field internal_static_envoy_service_discovery_v3_DeltaDiscoveryRequest_descriptor:Lcom/google/protobuf/Descriptors$Descriptor;
     265: invokevirtual #142                // Method com/google/protobuf/Descriptors$Descriptor.getNestedTypes:()Ljava/util/List;
     268: iconst_0
     269: invokeinterface #98,  2           // InterfaceMethod java/util/List.get:(I)Ljava/lang/Object;
     274: checkcast     #7                  // class com/google/protobuf/Descriptors$Descriptor
     277: putstatic     #144                // Field internal_static_envoy_service_discovery_v3_DeltaDiscoveryRequest_InitialResourceVersionsEntry_descriptor:Lcom/google/protobuf/Descriptors$Descriptor;
     280: new           #12                 // class com/google/protobuf/GeneratedMessageV3$FieldAccessorTable
     283: dup
     284: getstatic     #144                // Field internal_static_envoy_service_discovery_v3_DeltaDiscoveryRequest_InitialResourceVersionsEntry_descriptor:Lcom/google/protobuf/Descriptors$Descriptor;
     287: iconst_2
     288: anewarray     #62                 // class java/lang/String
     291: dup
     292: iconst_0
     293: ldc           #146                // String Key
     295: aastore
     296: dup
     297: iconst_1
     298: ldc           #148                // String Value
     300: aastore
     301: invokespecial #115                // Method com/google/protobuf/GeneratedMessageV3$FieldAccessorTable."<init>":(Lcom/google/protobuf/Descriptors$Descriptor;[Ljava/lang/String;)V
     304: putstatic     #150                // Field internal_static_envoy_service_discovery_v3_DeltaDiscoveryRequest_InitialResourceVersionsEntry_fieldAccessorTable:Lcom/google/protobuf/GeneratedMessageV3$FieldAccessorTable;
     307: invokestatic  #88                 // Method getDescriptor:()Lcom/google/protobuf/Descriptors$FileDescriptor;
     310: invokevirtual #92                 // Method com/google/protobuf/Descriptors$FileDescriptor.getMessageTypes:()Ljava/util/List;
     313: iconst_3
     314: invokeinterface #98,  2           // InterfaceMethod java/util/List.get:(I)Ljava/lang/Object;
     319: checkcast     #7                  // class com/google/protobuf/Descriptors$Descriptor
     322: putstatic     #152                // Field internal_static_envoy_service_discovery_v3_DeltaDiscoveryResponse_descriptor:Lcom/google/protobuf/Descriptors$Descriptor;
     325: new           #12                 // class com/google/protobuf/GeneratedMessageV3$FieldAccessorTable
     328: dup
     329: getstatic     #152                // Field internal_static_envoy_service_discovery_v3_DeltaDiscoveryResponse_descriptor:Lcom/google/protobuf/Descriptors$Descriptor;
     332: bipush        6
     334: anewarray     #62                 // class java/lang/String
     337: dup
     338: iconst_0
     339: ldc           #154                // String SystemVersionInfo
     341: aastore
     342: dup
     343: iconst_1
     344: ldc           #121                // String Resources
     346: aastore
     347: dup
     348: iconst_2
     349: ldc           #108                // String TypeUrl
     351: aastore
     352: dup
     353: iconst_3
     354: ldc           #156                // String RemovedResources
     356: aastore
     357: dup
     358: iconst_4
     359: ldc           #125                // String Nonce
     361: aastore
     362: dup
     363: iconst_5
     364: ldc           #127                // String ControlPlane
     366: aastore
     367: invokespecial #115                // Method com/google/protobuf/GeneratedMessageV3$FieldAccessorTable."<init>":(Lcom/google/protobuf/Descriptors$Descriptor;[Ljava/lang/String;)V
     370: putstatic     #158                // Field internal_static_envoy_service_discovery_v3_DeltaDiscoveryResponse_fieldAccessorTable:Lcom/google/protobuf/GeneratedMessageV3$FieldAccessorTable;
     373: invokestatic  #88                 // Method getDescriptor:()Lcom/google/protobuf/Descriptors$FileDescriptor;
     376: invokevirtual #92                 // Method com/google/protobuf/Descriptors$FileDescriptor.getMessageTypes:()Ljava/util/List;
     379: iconst_4
     380: invokeinterface #98,  2           // InterfaceMethod java/util/List.get:(I)Ljava/lang/Object;
     385: checkcast     #7                  // class com/google/protobuf/Descriptors$Descriptor
     388: putstatic     #160                // Field internal_static_envoy_service_discovery_v3_Resource_descriptor:Lcom/google/protobuf/Descriptors$Descriptor;
     391: new           #12                 // class com/google/protobuf/GeneratedMessageV3$FieldAccessorTable
     394: dup
     395: getstatic     #160                // Field internal_static_envoy_service_discovery_v3_Resource_descriptor:Lcom/google/protobuf/Descriptors$Descriptor;
     398: bipush        6
     400: anewarray     #62                 // class java/lang/String
     403: dup
     404: iconst_0
     405: ldc           #162                // String Name
     407: aastore
     408: dup
     409: iconst_1
     410: ldc           #164                // String Aliases
     412: aastore
     413: dup
     414: iconst_2
     415: ldc           #166                // String Version
     417: aastore
     418: dup
     419: iconst_3
     420: ldc           #168                // String Resource
     422: aastore
     423: dup
     424: iconst_4
     425: ldc           #170                // String Ttl
     427: aastore
     428: dup
     429: iconst_5
     430: ldc           #172                // String CacheControl
     432: aastore
     433: invokespecial #115                // Method com/google/protobuf/GeneratedMessageV3$FieldAccessorTable."<init>":(Lcom/google/protobuf/Descriptors$Descriptor;[Ljava/lang/String;)V
     436: putstatic     #174                // Field internal_static_envoy_service_discovery_v3_Resource_fieldAccessorTable:Lcom/google/protobuf/GeneratedMessageV3$FieldAccessorTable;
     439: getstatic     #160                // Field internal_static_envoy_service_discovery_v3_Resource_descriptor:Lcom/google/protobuf/Descriptors$Descriptor;
     442: invokevirtual #142                // Method com/google/protobuf/Descriptors$Descriptor.getNestedTypes:()Ljava/util/List;
     445: iconst_0
     446: invokeinterface #98,  2           // InterfaceMethod java/util/List.get:(I)Ljava/lang/Object;
     451: checkcast     #7                  // class com/google/protobuf/Descriptors$Descriptor
     454: putstatic     #176                // Field internal_static_envoy_service_discovery_v3_Resource_CacheControl_descriptor:Lcom/google/protobuf/Descriptors$Descriptor;
     457: new           #12                 // class com/google/protobuf/GeneratedMessageV3$FieldAccessorTable
     460: dup
     461: getstatic     #176                // Field internal_static_envoy_service_discovery_v3_Resource_CacheControl_descriptor:Lcom/google/protobuf/Descriptors$Descriptor;
     464: iconst_1
     465: anewarray     #62                 // class java/lang/String
     468: dup
     469: iconst_0
     470: ldc           #178                // String DoNotCache
     472: aastore
     473: invokespecial #115                // Method com/google/protobuf/GeneratedMessageV3$FieldAccessorTable."<init>":(Lcom/google/protobuf/Descriptors$Descriptor;[Ljava/lang/String;)V
     476: putstatic     #180                // Field internal_static_envoy_service_discovery_v3_Resource_CacheControl_fieldAccessorTable:Lcom/google/protobuf/GeneratedMessageV3$FieldAccessorTable;
     479: invokestatic  #186                // Method com/google/protobuf/ExtensionRegistry.newInstance:()Lcom/google/protobuf/ExtensionRegistry;
     482: astore_1
     483: aload_1
     484: getstatic     #190                // Field io/grpc/xds/shaded/udpa/annotations/Status.fileStatus:Lcom/google/protobuf/GeneratedMessage$GeneratedExtension;
     487: invokevirtual #194                // Method com/google/protobuf/ExtensionRegistry.add:(Lcom/google/protobuf/GeneratedMessage$GeneratedExtension;)V
     490: aload_1
     491: getstatic     #197                // Field io/grpc/xds/shaded/udpa/annotations/Versioning.versioning:Lcom/google/protobuf/GeneratedMessage$GeneratedExtension;
     494: invokevirtual #194                // Method com/google/protobuf/ExtensionRegistry.add:(Lcom/google/protobuf/GeneratedMessage$GeneratedExtension;)V
     497: getstatic     #59                 // Field descriptor:Lcom/google/protobuf/Descriptors$FileDescriptor;
     500: aload_1
     501: invokestatic  #201                // Method com/google/protobuf/Descriptors$FileDescriptor.internalUpdateFileDescriptor:(Lcom/google/protobuf/Descriptors$FileDescriptor;Lcom/google/protobuf/ExtensionRegistry;)V
     504: invokestatic  #68                 // Method io/grpc/xds/shaded/io/envoyproxy/envoy/config/core/v3/BaseProto.getDescriptor:()Lcom/google/protobuf/Descriptors$FileDescriptor;
     507: pop
     508: invokestatic  #71                 // Method com/google/protobuf/AnyProto.getDescriptor:()Lcom/google/protobuf/Descriptors$FileDescriptor;
     511: pop
     512: invokestatic  #74                 // Method com/google/protobuf/DurationProto.getDescriptor:()Lcom/google/protobuf/Descriptors$FileDescriptor;
     515: pop
     516: invokestatic  #77                 // Method com/google/rpc/StatusProto.getDescriptor:()Lcom/google/protobuf/Descriptors$FileDescriptor;
     519: pop
     520: invokestatic  #80                 // Method io/grpc/xds/shaded/udpa/annotations/Status.getDescriptor:()Lcom/google/protobuf/Descriptors$FileDescriptor;
     523: pop
     524: invokestatic  #83                 // Method io/grpc/xds/shaded/udpa/annotations/Versioning.getDescriptor:()Lcom/google/protobuf/Descriptors$FileDescriptor;
     527: pop
     528: return
}
