Compiled from "ClusterSystemResource.java"
public class org.graylog2.rest.resources.cluster.ClusterSystemResource extends org.graylog2.shared.rest.resources.ProxiedResource {
  private static final org.slf4j.Logger LOG;

  public org.graylog2.rest.resources.cluster.ClusterSystemResource(org.graylog2.cluster.NodeService, org.graylog2.rest.RemoteInterfaceProvider, javax.ws.rs.core.HttpHeaders, java.util.concurrent.ExecutorService) throws org.graylog2.cluster.NodeNotFoundException;
    Code:
       0: aload_0
       1: aload_3
       2: aload_1
       3: aload_2
       4: aload         4
       6: invokespecial #1                  // Method org/graylog2/shared/rest/resources/ProxiedResource."<init>":(Ljavax/ws/rs/core/HttpHeaders;Lorg/graylog2/cluster/NodeService;Lorg/graylog2/rest/RemoteInterfaceProvider;Ljava/util/concurrent/ExecutorService;)V
       9: return

  public java.util.Map<java.lang.String, java.util.Optional<org.graylog2.rest.models.system.responses.SystemOverviewResponse>> get();
    Code:
       0: aload_0
       1: invokedynamic #2,  0              // InvokeDynamic #0:apply:()Ljava/util/function/Function;
       6: aload_0
       7: ldc           #3                  // class org/graylog2/shared/rest/resources/system/RemoteSystemResource
       9: invokevirtual #4                  // Method createRemoteInterfaceProvider:(Ljava/lang/Class;)Ljava/util/function/Function;
      12: invokevirtual #5                  // Method getForAllNodes:(Ljava/util/function/Function;Ljava/util/function/Function;)Ljava/util/Map;
      15: areturn

  public org.graylog2.rest.models.system.responses.SystemJVMResponse jvm(java.lang.String) throws java.io.IOException, org.graylog2.cluster.NodeNotFoundException;
    Code:
       0: aload_0
       1: getfield      #6                  // Field nodeService:Lorg/graylog2/cluster/NodeService;
       4: aload_1
       5: invokeinterface #7,  2            // InterfaceMethod org/graylog2/cluster/NodeService.byNodeId:(Ljava/lang/String;)Lorg/graylog2/cluster/Node;
      10: astore_2
      11: aload_0
      12: getfield      #8                  // Field remoteInterfaceProvider:Lorg/graylog2/rest/RemoteInterfaceProvider;
      15: aload_2
      16: aload_0
      17: getfield      #9                  // Field authenticationToken:Ljava/lang/String;
      20: ldc           #3                  // class org/graylog2/shared/rest/resources/system/RemoteSystemResource
      22: invokevirtual #10                 // Method org/graylog2/rest/RemoteInterfaceProvider.get:(Lorg/graylog2/cluster/Node;Ljava/lang/String;Ljava/lang/Class;)Ljava/lang/Object;
      25: checkcast     #3                  // class org/graylog2/shared/rest/resources/system/RemoteSystemResource
      28: astore_3
      29: aload_3
      30: invokeinterface #11,  1           // InterfaceMethod org/graylog2/shared/rest/resources/system/RemoteSystemResource.jvm:()Lretrofit2/Call;
      35: invokeinterface #12,  1           // InterfaceMethod retrofit2/Call.execute:()Lretrofit2/Response;
      40: astore        4
      42: aload         4
      44: invokevirtual #13                 // Method retrofit2/Response.isSuccessful:()Z
      47: ifeq          59
      50: aload         4
      52: invokevirtual #14                 // Method retrofit2/Response.body:()Ljava/lang/Object;
      55: checkcast     #15                 // class org/graylog2/rest/models/system/responses/SystemJVMResponse
      58: areturn
      59: getstatic     #16                 // Field LOG:Lorg/slf4j/Logger;
      62: ldc           #17                 // String Unable to get jvm information on node {}: {}
      64: aload_1
      65: aload         4
      67: invokevirtual #18                 // Method retrofit2/Response.message:()Ljava/lang/String;
      70: invokeinterface #19,  4           // InterfaceMethod org/slf4j/Logger.warn:(Ljava/lang/String;Ljava/lang/Object;Ljava/lang/Object;)V
      75: new           #20                 // class javax/ws/rs/WebApplicationException
      78: dup
      79: aload         4
      81: invokevirtual #18                 // Method retrofit2/Response.message:()Ljava/lang/String;
      84: getstatic     #21                 // Field javax/ws/rs/core/Response$Status.BAD_GATEWAY:Ljavax/ws/rs/core/Response$Status;
      87: invokespecial #22                 // Method javax/ws/rs/WebApplicationException."<init>":(Ljava/lang/String;Ljavax/ws/rs/core/Response$Status;)V
      90: athrow

  public org.graylog2.rest.models.system.responses.SystemThreadDumpResponse threadDump(java.lang.String) throws java.io.IOException, org.graylog2.cluster.NodeNotFoundException;
    Code:
       0: aload_0
       1: getfield      #6                  // Field nodeService:Lorg/graylog2/cluster/NodeService;
       4: aload_1
       5: invokeinterface #7,  2            // InterfaceMethod org/graylog2/cluster/NodeService.byNodeId:(Ljava/lang/String;)Lorg/graylog2/cluster/Node;
      10: astore_2
      11: aload_0
      12: getfield      #8                  // Field remoteInterfaceProvider:Lorg/graylog2/rest/RemoteInterfaceProvider;
      15: aload_2
      16: aload_0
      17: getfield      #9                  // Field authenticationToken:Ljava/lang/String;
      20: ldc           #3                  // class org/graylog2/shared/rest/resources/system/RemoteSystemResource
      22: invokevirtual #10                 // Method org/graylog2/rest/RemoteInterfaceProvider.get:(Lorg/graylog2/cluster/Node;Ljava/lang/String;Ljava/lang/Class;)Ljava/lang/Object;
      25: checkcast     #3                  // class org/graylog2/shared/rest/resources/system/RemoteSystemResource
      28: astore_3
      29: aload_3
      30: invokeinterface #23,  1           // InterfaceMethod org/graylog2/shared/rest/resources/system/RemoteSystemResource.threadDump:()Lretrofit2/Call;
      35: invokeinterface #12,  1           // InterfaceMethod retrofit2/Call.execute:()Lretrofit2/Response;
      40: astore        4
      42: aload         4
      44: invokevirtual #13                 // Method retrofit2/Response.isSuccessful:()Z
      47: ifeq          59
      50: aload         4
      52: invokevirtual #14                 // Method retrofit2/Response.body:()Ljava/lang/Object;
      55: checkcast     #24                 // class org/graylog2/rest/models/system/responses/SystemThreadDumpResponse
      58: areturn
      59: getstatic     #16                 // Field LOG:Lorg/slf4j/Logger;
      62: ldc           #25                 // String Unable to get thread dump on node {}: {}
      64: aload_1
      65: aload         4
      67: invokevirtual #18                 // Method retrofit2/Response.message:()Ljava/lang/String;
      70: invokeinterface #19,  4           // InterfaceMethod org/slf4j/Logger.warn:(Ljava/lang/String;Ljava/lang/Object;Ljava/lang/Object;)V
      75: new           #20                 // class javax/ws/rs/WebApplicationException
      78: dup
      79: aload         4
      81: invokevirtual #18                 // Method retrofit2/Response.message:()Ljava/lang/String;
      84: getstatic     #21                 // Field javax/ws/rs/core/Response$Status.BAD_GATEWAY:Ljavax/ws/rs/core/Response$Status;
      87: invokespecial #22                 // Method javax/ws/rs/WebApplicationException."<init>":(Ljava/lang/String;Ljavax/ws/rs/core/Response$Status;)V
      90: athrow

  static {};
    Code:
       0: ldc           #26                 // class org/graylog2/rest/resources/cluster/ClusterSystemResource
       2: invokestatic  #27                 // Method org/slf4j/LoggerFactory.getLogger:(Ljava/lang/Class;)Lorg/slf4j/Logger;
       5: putstatic     #16                 // Field LOG:Lorg/slf4j/Logger;
       8: return
}
