Compiled from "UserAuthClient.java"
public class cicada.authorization.UserAuthClient {
  static final org.apache.log4j.Logger log;

  static final byte[] lock;

  public cicada.authorization.UserAuthClient();
    Code:
       0: aload_0
       1: invokespecial #1                  // Method java/lang/Object."<init>":()V
       4: return

  public static cicada.authorization.config.GetUserIdRet getUserId(java.lang.String);
    Code:
       0: ldc           #2                  // class cicada/authorization/config/UserSessionService$Iface
       2: invokestatic  #3                  // Method cicada/core/BeanFactory.getBeanByType:(Ljava/lang/Class;)Ljava/lang/Object;
       5: checkcast     #2                  // class cicada/authorization/config/UserSessionService$Iface
       8: astore_1
       9: aload_1
      10: ifnull        38
      13: getstatic     #4                  // Field lock:[B
      16: dup
      17: astore_2
      18: monitorenter
      19: aload_1
      20: aload_0
      21: invokeinterface #5,  2            // InterfaceMethod cicada/authorization/config/UserSessionService$Iface.GetUserId:(Ljava/lang/String;)Lcicada/authorization/config/GetUserIdRet;
      26: astore_3
      27: aload_3
      28: aload_2
      29: monitorexit
      30: areturn
      31: astore        4
      33: aload_2
      34: monitorexit
      35: aload         4
      37: athrow
      38: goto          53
      41: astore_2
      42: aload_2
      43: invokevirtual #7                  // Method java/lang/Exception.printStackTrace:()V
      46: getstatic     #8                  // Field log:Lorg/apache/log4j/Logger;
      49: aload_2
      50: invokevirtual #9                  // Method org/apache/log4j/Logger.error:(Ljava/lang/Object;)V
      53: getstatic     #8                  // Field log:Lorg/apache/log4j/Logger;
      56: ldc           #10                 // String cicada.authorization 版块获取thrift 服务错误,返回空值
      58: invokevirtual #9                  // Method org/apache/log4j/Logger.error:(Ljava/lang/Object;)V
      61: aconst_null
      62: areturn
    Exception table:
       from    to  target type
          19    30    31   any
          31    35    31   any
           9    30    41   Class java/lang/Exception
          31    38    41   Class java/lang/Exception

  static {};
    Code:
       0: ldc           #11                 // class cicada/authorization/UserAuthClient
       2: invokestatic  #12                 // Method org/apache/log4j/Logger.getLogger:(Ljava/lang/Class;)Lorg/apache/log4j/Logger;
       5: putstatic     #8                  // Field log:Lorg/apache/log4j/Logger;
       8: iconst_1
       9: newarray       byte
      11: putstatic     #4                  // Field lock:[B
      14: return
}
