Compiled from "PlexusAnnotatedMetadata.java"
public final class org.sonatype.guice.plexus.scanners.PlexusAnnotatedMetadata implements org.sonatype.guice.plexus.config.PlexusBeanMetadata {
  private final java.util.Map<?, ?> variables;

  public org.sonatype.guice.plexus.scanners.PlexusAnnotatedMetadata(java.util.Map<?, ?>);
    Code:
       0: aload_0
       1: invokespecial #1                  // Method java/lang/Object."<init>":()V
       4: aload_0
       5: aload_1
       6: putfield      #2                  // Field variables:Ljava/util/Map;
       9: return

  public boolean isEmpty();
    Code:
       0: iconst_0
       1: ireturn

  public org.codehaus.plexus.component.annotations.Configuration getConfiguration(org.sonatype.guice.bean.reflect.BeanProperty<?>);
    Code:
       0: aload_1
       1: ldc_w         #3                  // class org/codehaus/plexus/component/annotations/Configuration
       4: invokeinterface #4,  2            // InterfaceMethod org/sonatype/guice/bean/reflect/BeanProperty.getAnnotation:(Ljava/lang/Class;)Ljava/lang/annotation/Annotation;
       9: checkcast     #3                  // class org/codehaus/plexus/component/annotations/Configuration
      12: astore_2
      13: aload_2
      14: ifnull        66
      17: aload_0
      18: getfield      #2                  // Field variables:Ljava/util/Map;
      21: ifnull        66
      24: aload_2
      25: invokeinterface #5,  1            // InterfaceMethod org/codehaus/plexus/component/annotations/Configuration.value:()Ljava/lang/String;
      30: astore_3
      31: aload_3
      32: aload_0
      33: getfield      #2                  // Field variables:Ljava/util/Map;
      36: invokestatic  #6                  // Method org/codehaus/plexus/util/StringUtils.interpolate:(Ljava/lang/String;Ljava/util/Map;)Ljava/lang/String;
      39: astore        4
      41: aload         4
      43: aload_3
      44: invokevirtual #7                  // Method java/lang/String.equals:(Ljava/lang/Object;)Z
      47: ifne          66
      50: new           #8                  // class org/sonatype/guice/plexus/annotations/ConfigurationImpl
      53: dup
      54: aload_2
      55: invokeinterface #9,  1            // InterfaceMethod org/codehaus/plexus/component/annotations/Configuration.name:()Ljava/lang/String;
      60: aload         4
      62: invokespecial #10                 // Method org/sonatype/guice/plexus/annotations/ConfigurationImpl."<init>":(Ljava/lang/String;Ljava/lang/String;)V
      65: areturn
      66: aload_2
      67: areturn

  public org.codehaus.plexus.component.annotations.Requirement getRequirement(org.sonatype.guice.bean.reflect.BeanProperty<?>);
    Code:
       0: aload_1
       1: ldc_w         #11                 // class org/codehaus/plexus/component/annotations/Requirement
       4: invokeinterface #4,  2            // InterfaceMethod org/sonatype/guice/bean/reflect/BeanProperty.getAnnotation:(Ljava/lang/Class;)Ljava/lang/annotation/Annotation;
       9: checkcast     #11                 // class org/codehaus/plexus/component/annotations/Requirement
      12: areturn
}
