Compiled from "PreferenceTransferElement.java"
class org.eclipse.ui.internal.preferences.PreferenceTransferElement$PreferenceFilter implements org.eclipse.core.runtime.preferences.IPreferenceFilter {
  private java.lang.String[] scopes;

  private java.util.Map<java.lang.String, java.util.Map<java.lang.String, org.eclipse.core.runtime.preferences.PreferenceFilterEntry[]>> mappings;

  public org.eclipse.ui.internal.preferences.PreferenceTransferElement$PreferenceFilter(java.lang.String[], java.util.Map<java.lang.String, java.util.Map<java.lang.String, org.eclipse.core.runtime.preferences.PreferenceFilterEntry[]>>);
    Code:
       0: aload_0
       1: invokespecial #38                 // Method java/lang/Object."<init>":()V
       4: aload_0
       5: aload_1
       6: putfield      #36                 // Field scopes:[Ljava/lang/String;
       9: aload_0
      10: aload_2
      11: putfield      #37                 // Field mappings:Ljava/util/Map;
      14: return

  public java.lang.String[] getScopes();
    Code:
       0: aload_0
       1: getfield      #36                 // Field scopes:[Ljava/lang/String;
       4: areturn

  public java.util.Map<java.lang.String, org.eclipse.core.runtime.preferences.PreferenceFilterEntry[]> getMapping(java.lang.String);
    Code:
       0: aload_0
       1: getfield      #37                 // Field mappings:Ljava/util/Map;
       4: aload_1
       5: invokeinterface #39,  2           // InterfaceMethod java/util/Map.get:(Ljava/lang/Object;)Ljava/lang/Object;
      10: checkcast     #18                 // class java/util/Map
      13: areturn
}
