Compiled from "AbstractEncounterCounter.java"
class com.mchange.v2.encounter.AbstractEncounterCounter implements com.mchange.v2.encounter.EncounterCounter {
  static final java.lang.Long ONE;

  java.util.Map m;

  com.mchange.v2.encounter.AbstractEncounterCounter(java.util.Map);
    Code:
       0: aload_0
       1: invokespecial #1                  // Method java/lang/Object."<init>":()V
       4: aload_0
       5: aload_1
       6: putfield      #2                  // Field m:Ljava/util/Map;
       9: return

  public long encounter(java.lang.Object);
    Code:
       0: aload_0
       1: getfield      #2                  // Field m:Ljava/util/Map;
       4: aload_1
       5: invokeinterface #3,  2            // InterfaceMethod java/util/Map.get:(Ljava/lang/Object;)Ljava/lang/Object;
      10: checkcast     #4                  // class java/lang/Long
      13: astore_2
      14: aload_2
      15: ifnonnull     28
      18: lconst_0
      19: lstore        4
      21: getstatic     #5                  // Field ONE:Ljava/lang/Long;
      24: astore_3
      25: goto          46
      28: aload_2
      29: invokevirtual #6                  // Method java/lang/Long.longValue:()J
      32: lstore        4
      34: new           #4                  // class java/lang/Long
      37: dup
      38: lload         4
      40: lconst_1
      41: ladd
      42: invokespecial #7                  // Method java/lang/Long."<init>":(J)V
      45: astore_3
      46: aload_0
      47: getfield      #2                  // Field m:Ljava/util/Map;
      50: aload_1
      51: aload_3
      52: invokeinterface #8,  3            // InterfaceMethod java/util/Map.put:(Ljava/lang/Object;Ljava/lang/Object;)Ljava/lang/Object;
      57: pop
      58: lload         4
      60: lreturn

  public long reset(java.lang.Object);
    Code:
       0: aload_0
       1: aload_1
       2: invokevirtual #9                  // Method encounter:(Ljava/lang/Object;)J
       5: lstore_2
       6: aload_0
       7: getfield      #2                  // Field m:Ljava/util/Map;
      10: aload_1
      11: invokeinterface #10,  2           // InterfaceMethod java/util/Map.remove:(Ljava/lang/Object;)Ljava/lang/Object;
      16: pop
      17: lload_2
      18: lreturn

  public void resetAll();
    Code:
       0: aload_0
       1: getfield      #2                  // Field m:Ljava/util/Map;
       4: invokeinterface #11,  1           // InterfaceMethod java/util/Map.clear:()V
       9: return

  static {};
    Code:
       0: new           #4                  // class java/lang/Long
       3: dup
       4: lconst_1
       5: invokespecial #7                  // Method java/lang/Long."<init>":(J)V
       8: putstatic     #5                  // Field ONE:Ljava/lang/Long;
      11: return
}
