Compiled from "DefaultWebTestClient.java"
class org.springframework.test.web.reactive.server.DefaultWebTestClient$DefaultResponseSpec implements org.springframework.test.web.reactive.server.WebTestClient$ResponseSpec {
  private final org.springframework.test.web.reactive.server.ExchangeResult exchangeResult;

  private final org.springframework.web.reactive.function.client.ClientResponse response;

  private final java.time.Duration timeout;

  org.springframework.test.web.reactive.server.DefaultWebTestClient$DefaultResponseSpec(org.springframework.test.web.reactive.server.WiretapConnector$Info, org.springframework.web.reactive.function.client.ClientResponse, java.lang.String, java.time.Duration);
    Code:
       0: aload_0
       1: invokespecial #1                  // Method java/lang/Object."<init>":()V
       4: aload_0
       5: aload_1
       6: aload_3
       7: invokevirtual #2                  // Method org/springframework/test/web/reactive/server/WiretapConnector$Info.createExchangeResult:(Ljava/lang/String;)Lorg/springframework/test/web/reactive/server/ExchangeResult;
      10: putfield      #3                  // Field exchangeResult:Lorg/springframework/test/web/reactive/server/ExchangeResult;
      13: aload_0
      14: aload_2
      15: putfield      #4                  // Field response:Lorg/springframework/web/reactive/function/client/ClientResponse;
      18: aload_0
      19: aload         4
      21: putfield      #5                  // Field timeout:Ljava/time/Duration;
      24: return

  public org.springframework.test.web.reactive.server.StatusAssertions expectStatus();
    Code:
       0: new           #6                  // class org/springframework/test/web/reactive/server/StatusAssertions
       3: dup
       4: aload_0
       5: getfield      #3                  // Field exchangeResult:Lorg/springframework/test/web/reactive/server/ExchangeResult;
       8: aload_0
       9: invokespecial #7                  // Method org/springframework/test/web/reactive/server/StatusAssertions."<init>":(Lorg/springframework/test/web/reactive/server/ExchangeResult;Lorg/springframework/test/web/reactive/server/WebTestClient$ResponseSpec;)V
      12: areturn

  public org.springframework.test.web.reactive.server.HeaderAssertions expectHeader();
    Code:
       0: new           #8                  // class org/springframework/test/web/reactive/server/HeaderAssertions
       3: dup
       4: aload_0
       5: getfield      #3                  // Field exchangeResult:Lorg/springframework/test/web/reactive/server/ExchangeResult;
       8: aload_0
       9: invokespecial #9                  // Method org/springframework/test/web/reactive/server/HeaderAssertions."<init>":(Lorg/springframework/test/web/reactive/server/ExchangeResult;Lorg/springframework/test/web/reactive/server/WebTestClient$ResponseSpec;)V
      12: areturn

  public <B> org.springframework.test.web.reactive.server.WebTestClient$BodySpec<B, ?> expectBody(java.lang.Class<B>);
    Code:
       0: aload_0
       1: getfield      #4                  // Field response:Lorg/springframework/web/reactive/function/client/ClientResponse;
       4: aload_1
       5: invokeinterface #10,  2           // InterfaceMethod org/springframework/web/reactive/function/client/ClientResponse.bodyToMono:(Ljava/lang/Class;)Lreactor/core/publisher/Mono;
      10: aload_0
      11: getfield      #5                  // Field timeout:Ljava/time/Duration;
      14: invokevirtual #11                 // Method reactor/core/publisher/Mono.block:(Ljava/time/Duration;)Ljava/lang/Object;
      17: astore_2
      18: new           #12                 // class org/springframework/test/web/reactive/server/EntityExchangeResult
      21: dup
      22: aload_0
      23: getfield      #3                  // Field exchangeResult:Lorg/springframework/test/web/reactive/server/ExchangeResult;
      26: aload_2
      27: invokespecial #13                 // Method org/springframework/test/web/reactive/server/EntityExchangeResult."<init>":(Lorg/springframework/test/web/reactive/server/ExchangeResult;Ljava/lang/Object;)V
      30: astore_3
      31: new           #14                 // class org/springframework/test/web/reactive/server/DefaultWebTestClient$DefaultBodySpec
      34: dup
      35: aload_3
      36: invokespecial #15                 // Method org/springframework/test/web/reactive/server/DefaultWebTestClient$DefaultBodySpec."<init>":(Lorg/springframework/test/web/reactive/server/EntityExchangeResult;)V
      39: areturn

  public <B> org.springframework.test.web.reactive.server.WebTestClient$BodySpec<B, ?> expectBody(org.springframework.core.ParameterizedTypeReference<B>);
    Code:
       0: aload_0
       1: getfield      #4                  // Field response:Lorg/springframework/web/reactive/function/client/ClientResponse;
       4: aload_1
       5: invokeinterface #16,  2           // InterfaceMethod org/springframework/web/reactive/function/client/ClientResponse.bodyToMono:(Lorg/springframework/core/ParameterizedTypeReference;)Lreactor/core/publisher/Mono;
      10: aload_0
      11: getfield      #5                  // Field timeout:Ljava/time/Duration;
      14: invokevirtual #11                 // Method reactor/core/publisher/Mono.block:(Ljava/time/Duration;)Ljava/lang/Object;
      17: astore_2
      18: new           #12                 // class org/springframework/test/web/reactive/server/EntityExchangeResult
      21: dup
      22: aload_0
      23: getfield      #3                  // Field exchangeResult:Lorg/springframework/test/web/reactive/server/ExchangeResult;
      26: aload_2
      27: invokespecial #13                 // Method org/springframework/test/web/reactive/server/EntityExchangeResult."<init>":(Lorg/springframework/test/web/reactive/server/ExchangeResult;Ljava/lang/Object;)V
      30: astore_3
      31: new           #14                 // class org/springframework/test/web/reactive/server/DefaultWebTestClient$DefaultBodySpec
      34: dup
      35: aload_3
      36: invokespecial #15                 // Method org/springframework/test/web/reactive/server/DefaultWebTestClient$DefaultBodySpec."<init>":(Lorg/springframework/test/web/reactive/server/EntityExchangeResult;)V
      39: areturn

  public <E> org.springframework.test.web.reactive.server.WebTestClient$ListBodySpec<E> expectBodyList(java.lang.Class<E>);
    Code:
       0: aload_0
       1: aload_0
       2: getfield      #4                  // Field response:Lorg/springframework/web/reactive/function/client/ClientResponse;
       5: aload_1
       6: invokeinterface #17,  2           // InterfaceMethod org/springframework/web/reactive/function/client/ClientResponse.bodyToFlux:(Ljava/lang/Class;)Lreactor/core/publisher/Flux;
      11: invokespecial #18                 // Method getListBodySpec:(Lreactor/core/publisher/Flux;)Lorg/springframework/test/web/reactive/server/WebTestClient$ListBodySpec;
      14: areturn

  public <E> org.springframework.test.web.reactive.server.WebTestClient$ListBodySpec<E> expectBodyList(org.springframework.core.ParameterizedTypeReference<E>);
    Code:
       0: aload_0
       1: getfield      #4                  // Field response:Lorg/springframework/web/reactive/function/client/ClientResponse;
       4: aload_1
       5: invokeinterface #19,  2           // InterfaceMethod org/springframework/web/reactive/function/client/ClientResponse.bodyToFlux:(Lorg/springframework/core/ParameterizedTypeReference;)Lreactor/core/publisher/Flux;
      10: astore_2
      11: aload_0
      12: aload_2
      13: invokespecial #18                 // Method getListBodySpec:(Lreactor/core/publisher/Flux;)Lorg/springframework/test/web/reactive/server/WebTestClient$ListBodySpec;
      16: areturn

  private <E> org.springframework.test.web.reactive.server.WebTestClient$ListBodySpec<E> getListBodySpec(reactor.core.publisher.Flux<E>);
    Code:
       0: aload_1
       1: invokevirtual #20                 // Method reactor/core/publisher/Flux.collectList:()Lreactor/core/publisher/Mono;
       4: aload_0
       5: getfield      #5                  // Field timeout:Ljava/time/Duration;
       8: invokevirtual #11                 // Method reactor/core/publisher/Mono.block:(Ljava/time/Duration;)Ljava/lang/Object;
      11: checkcast     #21                 // class java/util/List
      14: astore_2
      15: new           #12                 // class org/springframework/test/web/reactive/server/EntityExchangeResult
      18: dup
      19: aload_0
      20: getfield      #3                  // Field exchangeResult:Lorg/springframework/test/web/reactive/server/ExchangeResult;
      23: aload_2
      24: invokespecial #13                 // Method org/springframework/test/web/reactive/server/EntityExchangeResult."<init>":(Lorg/springframework/test/web/reactive/server/ExchangeResult;Ljava/lang/Object;)V
      27: astore_3
      28: new           #22                 // class org/springframework/test/web/reactive/server/DefaultWebTestClient$DefaultListBodySpec
      31: dup
      32: aload_3
      33: invokespecial #23                 // Method org/springframework/test/web/reactive/server/DefaultWebTestClient$DefaultListBodySpec."<init>":(Lorg/springframework/test/web/reactive/server/EntityExchangeResult;)V
      36: areturn

  public org.springframework.test.web.reactive.server.WebTestClient$BodyContentSpec expectBody();
    Code:
       0: aload_0
       1: getfield      #4                  // Field response:Lorg/springframework/web/reactive/function/client/ClientResponse;
       4: ldc           #24                 // class org/springframework/core/io/ByteArrayResource
       6: invokeinterface #10,  2           // InterfaceMethod org/springframework/web/reactive/function/client/ClientResponse.bodyToMono:(Ljava/lang/Class;)Lreactor/core/publisher/Mono;
      11: aload_0
      12: getfield      #5                  // Field timeout:Ljava/time/Duration;
      15: invokevirtual #11                 // Method reactor/core/publisher/Mono.block:(Ljava/time/Duration;)Ljava/lang/Object;
      18: checkcast     #24                 // class org/springframework/core/io/ByteArrayResource
      21: astore_1
      22: aload_1
      23: ifnull        33
      26: aload_1
      27: invokevirtual #25                 // Method org/springframework/core/io/ByteArrayResource.getByteArray:()[B
      30: goto          34
      33: aconst_null
      34: astore_2
      35: new           #12                 // class org/springframework/test/web/reactive/server/EntityExchangeResult
      38: dup
      39: aload_0
      40: getfield      #3                  // Field exchangeResult:Lorg/springframework/test/web/reactive/server/ExchangeResult;
      43: aload_2
      44: invokespecial #13                 // Method org/springframework/test/web/reactive/server/EntityExchangeResult."<init>":(Lorg/springframework/test/web/reactive/server/ExchangeResult;Ljava/lang/Object;)V
      47: astore_3
      48: new           #26                 // class org/springframework/test/web/reactive/server/DefaultWebTestClient$DefaultBodyContentSpec
      51: dup
      52: aload_3
      53: invokespecial #27                 // Method org/springframework/test/web/reactive/server/DefaultWebTestClient$DefaultBodyContentSpec."<init>":(Lorg/springframework/test/web/reactive/server/EntityExchangeResult;)V
      56: areturn

  public <T> org.springframework.test.web.reactive.server.FluxExchangeResult<T> returnResult(java.lang.Class<T>);
    Code:
       0: aload_0
       1: getfield      #4                  // Field response:Lorg/springframework/web/reactive/function/client/ClientResponse;
       4: aload_1
       5: invokeinterface #17,  2           // InterfaceMethod org/springframework/web/reactive/function/client/ClientResponse.bodyToFlux:(Ljava/lang/Class;)Lreactor/core/publisher/Flux;
      10: astore_2
      11: new           #28                 // class org/springframework/test/web/reactive/server/FluxExchangeResult
      14: dup
      15: aload_0
      16: getfield      #3                  // Field exchangeResult:Lorg/springframework/test/web/reactive/server/ExchangeResult;
      19: aload_2
      20: aload_0
      21: getfield      #5                  // Field timeout:Ljava/time/Duration;
      24: invokespecial #29                 // Method org/springframework/test/web/reactive/server/FluxExchangeResult."<init>":(Lorg/springframework/test/web/reactive/server/ExchangeResult;Lreactor/core/publisher/Flux;Ljava/time/Duration;)V
      27: areturn

  public <T> org.springframework.test.web.reactive.server.FluxExchangeResult<T> returnResult(org.springframework.core.ParameterizedTypeReference<T>);
    Code:
       0: aload_0
       1: getfield      #4                  // Field response:Lorg/springframework/web/reactive/function/client/ClientResponse;
       4: aload_1
       5: invokeinterface #19,  2           // InterfaceMethod org/springframework/web/reactive/function/client/ClientResponse.bodyToFlux:(Lorg/springframework/core/ParameterizedTypeReference;)Lreactor/core/publisher/Flux;
      10: astore_2
      11: new           #28                 // class org/springframework/test/web/reactive/server/FluxExchangeResult
      14: dup
      15: aload_0
      16: getfield      #3                  // Field exchangeResult:Lorg/springframework/test/web/reactive/server/ExchangeResult;
      19: aload_2
      20: aload_0
      21: getfield      #5                  // Field timeout:Ljava/time/Duration;
      24: invokespecial #29                 // Method org/springframework/test/web/reactive/server/FluxExchangeResult."<init>":(Lorg/springframework/test/web/reactive/server/ExchangeResult;Lreactor/core/publisher/Flux;Ljava/time/Duration;)V
      27: areturn
}
