Compiled from "TypePool.java"
public class org.assertj.core.internal.bytebuddy.pool.TypePool$Default$LazyTypeDescription$GenericTypeToken$Resolution$Raw$RawAnnotatedType extends org.assertj.core.internal.bytebuddy.description.type.TypeDescription$Generic$OfNonGenericType {
  private final org.assertj.core.internal.bytebuddy.pool.TypePool typePool;

  private final java.lang.String typePath;

  private final java.util.Map<java.lang.String, java.util.List<org.assertj.core.internal.bytebuddy.pool.TypePool$Default$LazyTypeDescription$AnnotationToken>> annotationTokens;

  private final org.assertj.core.internal.bytebuddy.description.type.TypeDescription typeDescription;

  protected org.assertj.core.internal.bytebuddy.pool.TypePool$Default$LazyTypeDescription$GenericTypeToken$Resolution$Raw$RawAnnotatedType(org.assertj.core.internal.bytebuddy.pool.TypePool, java.lang.String, java.util.Map<java.lang.String, java.util.List<org.assertj.core.internal.bytebuddy.pool.TypePool$Default$LazyTypeDescription$AnnotationToken>>, org.assertj.core.internal.bytebuddy.description.type.TypeDescription);
    Code:
       0: aload_0
       1: invokespecial #55                 // Method org/assertj/core/internal/bytebuddy/description/type/TypeDescription$Generic$OfNonGenericType."<init>":()V
       4: aload_0
       5: aload_1
       6: putfield      #57                 // Field typePool:Lorg/assertj/core/internal/bytebuddy/pool/TypePool;
       9: aload_0
      10: aload_2
      11: putfield      #59                 // Field typePath:Ljava/lang/String;
      14: aload_0
      15: aload_3
      16: putfield      #61                 // Field annotationTokens:Ljava/util/Map;
      19: aload_0
      20: aload         4
      22: putfield      #63                 // Field typeDescription:Lorg/assertj/core/internal/bytebuddy/description/type/TypeDescription;
      25: return

  protected static org.assertj.core.internal.bytebuddy.description.type.TypeDescription$Generic of(org.assertj.core.internal.bytebuddy.pool.TypePool, java.util.Map<java.lang.String, java.util.List<org.assertj.core.internal.bytebuddy.pool.TypePool$Default$LazyTypeDescription$AnnotationToken>>, java.lang.String);
    Code:
       0: new           #2                  // class org/assertj/core/internal/bytebuddy/pool/TypePool$Default$LazyTypeDescription$GenericTypeToken$Resolution$Raw$RawAnnotatedType
       3: dup
       4: aload_0
       5: ldc           #69                 // String
       7: aload_1
       8: ifnonnull     17
      11: invokestatic  #75                 // Method java/util/Collections.emptyMap:()Ljava/util/Map;
      14: goto          18
      17: aload_1
      18: aload_0
      19: aload_2
      20: invokestatic  #83                 // Method org/assertj/core/internal/bytebuddy/pool/TypePool$Default$LazyTypeDescription$TokenizedGenericType.toErasure:(Lorg/assertj/core/internal/bytebuddy/pool/TypePool;Ljava/lang/String;)Lorg/assertj/core/internal/bytebuddy/description/type/TypeDescription;
      23: invokespecial #85                 // Method "<init>":(Lorg/assertj/core/internal/bytebuddy/pool/TypePool;Ljava/lang/String;Ljava/util/Map;Lorg/assertj/core/internal/bytebuddy/description/type/TypeDescription;)V
      26: areturn

  public org.assertj.core.internal.bytebuddy.description.type.TypeDescription asErasure();
    Code:
       0: aload_0
       1: getfield      #63                 // Field typeDescription:Lorg/assertj/core/internal/bytebuddy/description/type/TypeDescription;
       4: areturn

  public org.assertj.core.internal.bytebuddy.description.type.TypeDescription$Generic getOwnerType();
    Code:
       0: aload_0
       1: getfield      #63                 // Field typeDescription:Lorg/assertj/core/internal/bytebuddy/description/type/TypeDescription;
       4: invokeinterface #93,  1           // InterfaceMethod org/assertj/core/internal/bytebuddy/description/type/TypeDescription.getDeclaringType:()Lorg/assertj/core/internal/bytebuddy/description/type/TypeDescription;
       9: astore_1
      10: aload_1
      11: ifnonnull     20
      14: getstatic     #97                 // Field org/assertj/core/internal/bytebuddy/description/type/TypeDescription$Generic.UNDEFINED:Lorg/assertj/core/internal/bytebuddy/description/type/TypeDescription$Generic;
      17: goto          40
      20: new           #2                  // class org/assertj/core/internal/bytebuddy/pool/TypePool$Default$LazyTypeDescription$GenericTypeToken$Resolution$Raw$RawAnnotatedType
      23: dup
      24: aload_0
      25: getfield      #57                 // Field typePool:Lorg/assertj/core/internal/bytebuddy/pool/TypePool;
      28: aload_0
      29: getfield      #59                 // Field typePath:Ljava/lang/String;
      32: aload_0
      33: getfield      #61                 // Field annotationTokens:Ljava/util/Map;
      36: aload_1
      37: invokespecial #85                 // Method "<init>":(Lorg/assertj/core/internal/bytebuddy/pool/TypePool;Ljava/lang/String;Ljava/util/Map;Lorg/assertj/core/internal/bytebuddy/description/type/TypeDescription;)V
      40: areturn

  public org.assertj.core.internal.bytebuddy.description.type.TypeDescription$Generic getComponentType();
    Code:
       0: aload_0
       1: getfield      #63                 // Field typeDescription:Lorg/assertj/core/internal/bytebuddy/description/type/TypeDescription;
       4: invokeinterface #101,  1          // InterfaceMethod org/assertj/core/internal/bytebuddy/description/type/TypeDescription.getComponentType:()Lorg/assertj/core/internal/bytebuddy/description/type/TypeDescription;
       9: astore_1
      10: aload_1
      11: ifnonnull     20
      14: getstatic     #97                 // Field org/assertj/core/internal/bytebuddy/description/type/TypeDescription$Generic.UNDEFINED:Lorg/assertj/core/internal/bytebuddy/description/type/TypeDescription$Generic;
      17: goto          58
      20: new           #2                  // class org/assertj/core/internal/bytebuddy/pool/TypePool$Default$LazyTypeDescription$GenericTypeToken$Resolution$Raw$RawAnnotatedType
      23: dup
      24: aload_0
      25: getfield      #57                 // Field typePool:Lorg/assertj/core/internal/bytebuddy/pool/TypePool;
      28: new           #103                // class java/lang/StringBuilder
      31: dup
      32: invokespecial #104                // Method java/lang/StringBuilder."<init>":()V
      35: aload_0
      36: getfield      #59                 // Field typePath:Ljava/lang/String;
      39: invokevirtual #108                // Method java/lang/StringBuilder.append:(Ljava/lang/String;)Ljava/lang/StringBuilder;
      42: bipush        91
      44: invokevirtual #111                // Method java/lang/StringBuilder.append:(C)Ljava/lang/StringBuilder;
      47: invokevirtual #115                // Method java/lang/StringBuilder.toString:()Ljava/lang/String;
      50: aload_0
      51: getfield      #61                 // Field annotationTokens:Ljava/util/Map;
      54: aload_1
      55: invokespecial #85                 // Method "<init>":(Lorg/assertj/core/internal/bytebuddy/pool/TypePool;Ljava/lang/String;Ljava/util/Map;Lorg/assertj/core/internal/bytebuddy/description/type/TypeDescription;)V
      58: areturn

  public org.assertj.core.internal.bytebuddy.description.annotation.AnnotationList getDeclaredAnnotations();
    Code:
       0: new           #103                // class java/lang/StringBuilder
       3: dup
       4: aload_0
       5: getfield      #59                 // Field typePath:Ljava/lang/String;
       8: invokespecial #121                // Method java/lang/StringBuilder."<init>":(Ljava/lang/String;)V
      11: astore_1
      12: iconst_0
      13: istore_2
      14: iload_2
      15: aload_0
      16: getfield      #63                 // Field typeDescription:Lorg/assertj/core/internal/bytebuddy/description/type/TypeDescription;
      19: invokeinterface #125,  1          // InterfaceMethod org/assertj/core/internal/bytebuddy/description/type/TypeDescription.getSegmentCount:()I
      24: if_icmpge     40
      27: aload_1
      28: bipush        46
      30: invokevirtual #111                // Method java/lang/StringBuilder.append:(C)Ljava/lang/StringBuilder;
      33: astore_1
      34: iinc          2, 1
      37: goto          14
      40: aload_0
      41: getfield      #57                 // Field typePool:Lorg/assertj/core/internal/bytebuddy/pool/TypePool;
      44: aload_0
      45: getfield      #61                 // Field annotationTokens:Ljava/util/Map;
      48: aload_1
      49: invokevirtual #115                // Method java/lang/StringBuilder.toString:()Ljava/lang/String;
      52: invokeinterface #129,  2          // InterfaceMethod java/util/Map.get:(Ljava/lang/Object;)Ljava/lang/Object;
      57: checkcast     #131                // class java/util/List
      60: invokestatic  #135                // Method org/assertj/core/internal/bytebuddy/pool/TypePool$Default$LazyTypeDescription$LazyAnnotationDescription.asListOfNullable:(Lorg/assertj/core/internal/bytebuddy/pool/TypePool;Ljava/util/List;)Lorg/assertj/core/internal/bytebuddy/description/annotation/AnnotationList;
      63: areturn

  public org.assertj.core.internal.bytebuddy.description.type.TypeDefinition getComponentType();
    Code:
       0: aload_0
       1: invokevirtual #141                // Method getComponentType:()Lorg/assertj/core/internal/bytebuddy/description/type/TypeDescription$Generic;
       4: areturn
}
