Compiled from "TypePool.java"
public class org.assertj.core.internal.bytebuddy.pool.TypePool$Default$LazyTypeDescription$GenericTypeToken$Resolution$Raw$RawAnnotatedType$LazyRawAnnotatedTypeList extends org.assertj.core.internal.bytebuddy.description.type.TypeList$Generic$AbstractBase {
  private final org.assertj.core.internal.bytebuddy.pool.TypePool typePool;

  private final java.util.Map<java.lang.Integer, java.util.Map<java.lang.String, java.util.List<org.assertj.core.internal.bytebuddy.pool.TypePool$Default$LazyTypeDescription$AnnotationToken>>> annotationTokens;

  private final java.util.List<java.lang.String> descriptors;

  protected org.assertj.core.internal.bytebuddy.pool.TypePool$Default$LazyTypeDescription$GenericTypeToken$Resolution$Raw$RawAnnotatedType$LazyRawAnnotatedTypeList(org.assertj.core.internal.bytebuddy.pool.TypePool, java.util.Map<java.lang.Integer, java.util.Map<java.lang.String, java.util.List<org.assertj.core.internal.bytebuddy.pool.TypePool$Default$LazyTypeDescription$AnnotationToken>>>, java.util.List<java.lang.String>);
    Code:
       0: aload_0
       1: invokespecial #57                 // Method org/assertj/core/internal/bytebuddy/description/type/TypeList$Generic$AbstractBase."<init>":()V
       4: aload_0
       5: aload_1
       6: putfield      #59                 // Field typePool:Lorg/assertj/core/internal/bytebuddy/pool/TypePool;
       9: aload_0
      10: aload_2
      11: putfield      #61                 // Field annotationTokens:Ljava/util/Map;
      14: aload_0
      15: aload_3
      16: putfield      #63                 // Field descriptors:Ljava/util/List;
      19: return

  protected static org.assertj.core.internal.bytebuddy.description.type.TypeList$Generic of(org.assertj.core.internal.bytebuddy.pool.TypePool, java.util.Map<java.lang.Integer, java.util.Map<java.lang.String, java.util.List<org.assertj.core.internal.bytebuddy.pool.TypePool$Default$LazyTypeDescription$AnnotationToken>>>, java.util.List<java.lang.String>);
    Code:
       0: new           #2                  // class org/assertj/core/internal/bytebuddy/pool/TypePool$Default$LazyTypeDescription$GenericTypeToken$Resolution$Raw$RawAnnotatedType$LazyRawAnnotatedTypeList
       3: dup
       4: aload_0
       5: aload_1
       6: ifnonnull     15
       9: invokestatic  #73                 // Method java/util/Collections.emptyMap:()Ljava/util/Map;
      12: goto          16
      15: aload_1
      16: aload_2
      17: invokespecial #79                 // Method "<init>":(Lorg/assertj/core/internal/bytebuddy/pool/TypePool;Ljava/util/Map;Ljava/util/List;)V
      20: areturn

  public org.assertj.core.internal.bytebuddy.description.type.TypeDescription$Generic get(int);
    Code:
       0: aload_0
       1: getfield      #59                 // Field typePool:Lorg/assertj/core/internal/bytebuddy/pool/TypePool;
       4: aload_0
       5: getfield      #61                 // Field annotationTokens:Ljava/util/Map;
       8: iload_1
       9: invokestatic  #87                 // Method java/lang/Integer.valueOf:(I)Ljava/lang/Integer;
      12: invokeinterface #90,  2           // InterfaceMethod java/util/Map.get:(Ljava/lang/Object;)Ljava/lang/Object;
      17: checkcast     #75                 // class java/util/Map
      20: aload_0
      21: getfield      #63                 // Field descriptors:Ljava/util/List;
      24: iload_1
      25: invokeinterface #93,  2           // InterfaceMethod java/util/List.get:(I)Ljava/lang/Object;
      30: checkcast     #95                 // class java/lang/String
      33: invokestatic  #98                 // Method org/assertj/core/internal/bytebuddy/pool/TypePool$Default$LazyTypeDescription$GenericTypeToken$Resolution$Raw$RawAnnotatedType.of:(Lorg/assertj/core/internal/bytebuddy/pool/TypePool;Ljava/util/Map;Ljava/lang/String;)Lorg/assertj/core/internal/bytebuddy/description/type/TypeDescription$Generic;
      36: areturn

  public int size();
    Code:
       0: aload_0
       1: getfield      #63                 // Field descriptors:Ljava/util/List;
       4: invokeinterface #104,  1          // InterfaceMethod java/util/List.size:()I
       9: ireturn

  public org.assertj.core.internal.bytebuddy.description.type.TypeList asErasures();
    Code:
       0: new           #40                 // class org/assertj/core/internal/bytebuddy/pool/TypePool$Default$LazyTypeDescription$LazyTypeList
       3: dup
       4: aload_0
       5: getfield      #59                 // Field typePool:Lorg/assertj/core/internal/bytebuddy/pool/TypePool;
       8: aload_0
       9: getfield      #63                 // Field descriptors:Ljava/util/List;
      12: aconst_null
      13: invokespecial #109                // Method org/assertj/core/internal/bytebuddy/pool/TypePool$Default$LazyTypeDescription$LazyTypeList."<init>":(Lorg/assertj/core/internal/bytebuddy/pool/TypePool;Ljava/util/List;Lorg/assertj/core/internal/bytebuddy/pool/TypePool$1;)V
      16: areturn

  public org.assertj.core.internal.bytebuddy.description.type.TypeList$Generic asRawTypes();
    Code:
       0: aload_0
       1: areturn

  public int getStackSize();
    Code:
       0: iconst_0
       1: istore_1
       2: aload_0
       3: getfield      #63                 // Field descriptors:Ljava/util/List;
       6: invokeinterface #116,  1          // InterfaceMethod java/util/List.iterator:()Ljava/util/Iterator;
      11: astore_2
      12: aload_2
      13: invokeinterface #122,  1          // InterfaceMethod java/util/Iterator.hasNext:()Z
      18: ifeq          44
      21: aload_2
      22: invokeinterface #126,  1          // InterfaceMethod java/util/Iterator.next:()Ljava/lang/Object;
      27: checkcast     #95                 // class java/lang/String
      30: astore_3
      31: iload_1
      32: aload_3
      33: invokestatic  #132                // Method org/assertj/core/internal/bytebuddy/jar/asm/Type.getType:(Ljava/lang/String;)Lorg/assertj/core/internal/bytebuddy/jar/asm/Type;
      36: invokevirtual #135                // Method org/assertj/core/internal/bytebuddy/jar/asm/Type.getSize:()I
      39: iadd
      40: istore_1
      41: goto          12
      44: iload_1
      45: ireturn

  public java.lang.Object get(int);
    Code:
       0: aload_0
       1: iload_1
       2: invokevirtual #140                // Method get:(I)Lorg/assertj/core/internal/bytebuddy/description/type/TypeDescription$Generic;
       5: areturn
}
