Compiled from "LowerFunction.java"
public class org.hibernate.jpa.criteria.expression.function.LowerFunction extends org.hibernate.jpa.criteria.expression.function.ParameterizedFunctionExpression<java.lang.String> implements java.io.Serializable {
  public static final java.lang.String NAME;

  public org.hibernate.jpa.criteria.expression.function.LowerFunction(org.hibernate.jpa.criteria.CriteriaBuilderImpl, javax.persistence.criteria.Expression<java.lang.String>);
    Code:
       0: aload_0
       1: aload_1
       2: ldc           #1                  // class java/lang/String
       4: ldc           #3                  // String lower
       6: iconst_1
       7: anewarray     #4                  // class javax/persistence/criteria/Expression
      10: dup
      11: iconst_0
      12: aload_2
      13: aastore
      14: invokespecial #5                  // Method org/hibernate/jpa/criteria/expression/function/ParameterizedFunctionExpression."<init>":(Lorg/hibernate/jpa/criteria/CriteriaBuilderImpl;Ljava/lang/Class;Ljava/lang/String;[Ljavax/persistence/criteria/Expression;)V
      17: return

  protected boolean isStandardJpaFunction();
    Code:
       0: iconst_1
       1: ireturn
}
