Compiled from "FormParamInjector.java"
public class org.jboss.resteasy.core.FormParamInjector extends org.jboss.resteasy.core.StringParameterInjector implements org.jboss.resteasy.core.ValueInjector {
  private boolean encode;

  public org.jboss.resteasy.core.FormParamInjector(java.lang.Class, java.lang.reflect.Type, java.lang.reflect.AccessibleObject, java.lang.String, java.lang.String, boolean, java.lang.annotation.Annotation[], org.jboss.resteasy.spi.ResteasyProviderFactory);
    Code:
       0: aload_0
       1: aload_1
       2: aload_2
       3: aload         4
       5: ldc           #1                  // class javax/ws/rs/FormParam
       7: aload         5
       9: aload_3
      10: aload         7
      12: aload         8
      14: invokespecial #2                  // Method org/jboss/resteasy/core/StringParameterInjector."<init>":(Ljava/lang/Class;Ljava/lang/reflect/Type;Ljava/lang/String;Ljava/lang/Class;Ljava/lang/String;Ljava/lang/reflect/AccessibleObject;[Ljava/lang/annotation/Annotation;Lorg/jboss/resteasy/spi/ResteasyProviderFactory;)V
      17: aload_0
      18: iload         6
      20: putfield      #3                  // Field encode:Z
      23: return

  public java.lang.Object inject(org.jboss.resteasy.spi.HttpRequest, org.jboss.resteasy.spi.HttpResponse);
    Code:
       0: aload_1
       1: invokeinterface #4,  1            // InterfaceMethod org/jboss/resteasy/spi/HttpRequest.getDecodedFormParameters:()Ljavax/ws/rs/core/MultivaluedMap;
       6: aload_0
       7: getfield      #5                  // Field paramName:Ljava/lang/String;
      10: invokeinterface #6,  2            // InterfaceMethod javax/ws/rs/core/MultivaluedMap.get:(Ljava/lang/Object;)Ljava/lang/Object;
      15: checkcast     #7                  // class java/util/List
      18: astore_3
      19: aload_3
      20: ifnonnull     32
      23: aload_0
      24: aconst_null
      25: invokevirtual #8                  // Method extractValues:(Ljava/util/List;)Ljava/lang/Object;
      28: pop
      29: goto          97
      32: aload_0
      33: getfield      #3                  // Field encode:Z
      36: ifeq          97
      39: new           #9                  // class java/util/ArrayList
      42: dup
      43: invokespecial #10                 // Method java/util/ArrayList."<init>":()V
      46: astore        4
      48: aload_3
      49: invokeinterface #11,  1           // InterfaceMethod java/util/List.iterator:()Ljava/util/Iterator;
      54: astore        5
      56: aload         5
      58: invokeinterface #12,  1           // InterfaceMethod java/util/Iterator.hasNext:()Z
      63: ifeq          94
      66: aload         5
      68: invokeinterface #13,  1           // InterfaceMethod java/util/Iterator.next:()Ljava/lang/Object;
      73: checkcast     #14                 // class java/lang/String
      76: astore        6
      78: aload         4
      80: aload         6
      82: invokestatic  #15                 // Method java/net/URLEncoder.encode:(Ljava/lang/String;)Ljava/lang/String;
      85: invokeinterface #16,  2           // InterfaceMethod java/util/List.add:(Ljava/lang/Object;)Z
      90: pop
      91: goto          56
      94: aload         4
      96: astore_3
      97: aload_0
      98: aload_3
      99: invokevirtual #8                  // Method extractValues:(Ljava/util/List;)Ljava/lang/Object;
     102: areturn

  public java.lang.Object inject();
    Code:
       0: new           #17                 // class java/lang/RuntimeException
       3: dup
       4: getstatic     #18                 // Field org/jboss/resteasy/resteasy_jaxrs/i18n/Messages.MESSAGES:Lorg/jboss/resteasy/resteasy_jaxrs/i18n/Messages;
       7: invokeinterface #19,  1           // InterfaceMethod org/jboss/resteasy/resteasy_jaxrs/i18n/Messages.illegalToInjectFormParam:()Ljava/lang/String;
      12: invokespecial #20                 // Method java/lang/RuntimeException."<init>":(Ljava/lang/String;)V
      15: athrow
}
