Compiled from "ParentRunner.java"
class org.junit.runners.ParentRunner$4 implements java.lang.Runnable {
  final java.lang.Object val$each;

  final org.junit.runner.notification.RunNotifier val$notifier;

  final org.junit.runners.ParentRunner this$0;

  org.junit.runners.ParentRunner$4(org.junit.runners.ParentRunner, java.lang.Object, org.junit.runner.notification.RunNotifier);
    Code:
       0: aload_0
       1: aload_1
       2: putfield      #1                  // Field this$0:Lorg/junit/runners/ParentRunner;
       5: aload_0
       6: aload_2
       7: putfield      #2                  // Field val$each:Ljava/lang/Object;
      10: aload_0
      11: aload_3
      12: putfield      #3                  // Field val$notifier:Lorg/junit/runner/notification/RunNotifier;
      15: aload_0
      16: invokespecial #4                  // Method java/lang/Object."<init>":()V
      19: return

  public void run();
    Code:
       0: aload_0
       1: getfield      #1                  // Field this$0:Lorg/junit/runners/ParentRunner;
       4: aload_0
       5: getfield      #2                  // Field val$each:Ljava/lang/Object;
       8: aload_0
       9: getfield      #3                  // Field val$notifier:Lorg/junit/runner/notification/RunNotifier;
      12: invokevirtual #5                  // Method org/junit/runners/ParentRunner.runChild:(Ljava/lang/Object;Lorg/junit/runner/notification/RunNotifier;)V
      15: return
}
