Compiled from "ParentRunner.java"
class org.junit.runners.ParentRunner$3 extends org.junit.runners.model.Statement {
  final org.junit.runners.model.Statement val$statement;

  final org.junit.runners.ParentRunner this$0;

  org.junit.runners.ParentRunner$3(org.junit.runners.ParentRunner, org.junit.runners.model.Statement);
    Code:
       0: aload_0
       1: aload_1
       2: putfield      #1                  // Field this$0:Lorg/junit/runners/ParentRunner;
       5: aload_0
       6: aload_2
       7: putfield      #2                  // Field val$statement:Lorg/junit/runners/model/Statement;
      10: aload_0
      11: invokespecial #3                  // Method org/junit/runners/model/Statement."<init>":()V
      14: return

  public void evaluate() throws java.lang.Throwable;
    Code:
       0: aload_0
       1: getfield      #2                  // Field val$statement:Lorg/junit/runners/model/Statement;
       4: invokevirtual #4                  // Method org/junit/runners/model/Statement.evaluate:()V
       7: invokestatic  #5                  // Method java/lang/Thread.interrupted:()Z
      10: pop
      11: goto          21
      14: astore_1
      15: invokestatic  #5                  // Method java/lang/Thread.interrupted:()Z
      18: pop
      19: aload_1
      20: athrow
      21: return
    Exception table:
       from    to  target type
           0     7    14   any
          14    15    14   any
}
