Compiled from "Cluster.java"
public interface software.amazon.awssdk.services.ecs.model.Cluster$Builder extends software.amazon.awssdk.core.SdkPojo, software.amazon.awssdk.utils.builder.CopyableBuilder<software.amazon.awssdk.services.ecs.model.Cluster$Builder, software.amazon.awssdk.services.ecs.model.Cluster> {
  public abstract software.amazon.awssdk.services.ecs.model.Cluster$Builder clusterArn(java.lang.String);

  public abstract software.amazon.awssdk.services.ecs.model.Cluster$Builder clusterName(java.lang.String);

  public abstract software.amazon.awssdk.services.ecs.model.Cluster$Builder configuration(software.amazon.awssdk.services.ecs.model.ClusterConfiguration);

  public default software.amazon.awssdk.services.ecs.model.Cluster$Builder configuration(java.util.function.Consumer<software.amazon.awssdk.services.ecs.model.ClusterConfiguration$Builder>);
    Code:
       0: aload_0
       1: invokestatic  #1                  // Method software/amazon/awssdk/services/ecs/model/ClusterConfiguration.builder:()Lsoftware/amazon/awssdk/services/ecs/model/ClusterConfiguration$Builder;
       4: aload_1
       5: invokeinterface #2,  2            // InterfaceMethod software/amazon/awssdk/services/ecs/model/ClusterConfiguration$Builder.applyMutation:(Ljava/util/function/Consumer;)Lsoftware/amazon/awssdk/utils/builder/SdkBuilder;
      10: checkcast     #3                  // class software/amazon/awssdk/services/ecs/model/ClusterConfiguration$Builder
      13: invokeinterface #4,  1            // InterfaceMethod software/amazon/awssdk/services/ecs/model/ClusterConfiguration$Builder.build:()Ljava/lang/Object;
      18: checkcast     #5                  // class software/amazon/awssdk/services/ecs/model/ClusterConfiguration
      21: invokeinterface #6,  2            // InterfaceMethod configuration:(Lsoftware/amazon/awssdk/services/ecs/model/ClusterConfiguration;)Lsoftware/amazon/awssdk/services/ecs/model/Cluster$Builder;
      26: areturn

  public abstract software.amazon.awssdk.services.ecs.model.Cluster$Builder status(java.lang.String);

  public abstract software.amazon.awssdk.services.ecs.model.Cluster$Builder registeredContainerInstancesCount(java.lang.Integer);

  public abstract software.amazon.awssdk.services.ecs.model.Cluster$Builder runningTasksCount(java.lang.Integer);

  public abstract software.amazon.awssdk.services.ecs.model.Cluster$Builder pendingTasksCount(java.lang.Integer);

  public abstract software.amazon.awssdk.services.ecs.model.Cluster$Builder activeServicesCount(java.lang.Integer);

  public abstract software.amazon.awssdk.services.ecs.model.Cluster$Builder statistics(java.util.Collection<software.amazon.awssdk.services.ecs.model.KeyValuePair>);

  public abstract software.amazon.awssdk.services.ecs.model.Cluster$Builder statistics(software.amazon.awssdk.services.ecs.model.KeyValuePair...);

  public abstract software.amazon.awssdk.services.ecs.model.Cluster$Builder statistics(java.util.function.Consumer<software.amazon.awssdk.services.ecs.model.KeyValuePair$Builder>...);

  public abstract software.amazon.awssdk.services.ecs.model.Cluster$Builder tags(java.util.Collection<software.amazon.awssdk.services.ecs.model.Tag>);

  public abstract software.amazon.awssdk.services.ecs.model.Cluster$Builder tags(software.amazon.awssdk.services.ecs.model.Tag...);

  public abstract software.amazon.awssdk.services.ecs.model.Cluster$Builder tags(java.util.function.Consumer<software.amazon.awssdk.services.ecs.model.Tag$Builder>...);

  public abstract software.amazon.awssdk.services.ecs.model.Cluster$Builder settings(java.util.Collection<software.amazon.awssdk.services.ecs.model.ClusterSetting>);

  public abstract software.amazon.awssdk.services.ecs.model.Cluster$Builder settings(software.amazon.awssdk.services.ecs.model.ClusterSetting...);

  public abstract software.amazon.awssdk.services.ecs.model.Cluster$Builder settings(java.util.function.Consumer<software.amazon.awssdk.services.ecs.model.ClusterSetting$Builder>...);

  public abstract software.amazon.awssdk.services.ecs.model.Cluster$Builder capacityProviders(java.util.Collection<java.lang.String>);

  public abstract software.amazon.awssdk.services.ecs.model.Cluster$Builder capacityProviders(java.lang.String...);

  public abstract software.amazon.awssdk.services.ecs.model.Cluster$Builder defaultCapacityProviderStrategy(java.util.Collection<software.amazon.awssdk.services.ecs.model.CapacityProviderStrategyItem>);

  public abstract software.amazon.awssdk.services.ecs.model.Cluster$Builder defaultCapacityProviderStrategy(software.amazon.awssdk.services.ecs.model.CapacityProviderStrategyItem...);

  public abstract software.amazon.awssdk.services.ecs.model.Cluster$Builder defaultCapacityProviderStrategy(java.util.function.Consumer<software.amazon.awssdk.services.ecs.model.CapacityProviderStrategyItem$Builder>...);

  public abstract software.amazon.awssdk.services.ecs.model.Cluster$Builder attachments(java.util.Collection<software.amazon.awssdk.services.ecs.model.Attachment>);

  public abstract software.amazon.awssdk.services.ecs.model.Cluster$Builder attachments(software.amazon.awssdk.services.ecs.model.Attachment...);

  public abstract software.amazon.awssdk.services.ecs.model.Cluster$Builder attachments(java.util.function.Consumer<software.amazon.awssdk.services.ecs.model.Attachment$Builder>...);

  public abstract software.amazon.awssdk.services.ecs.model.Cluster$Builder attachmentsStatus(java.lang.String);
}
