Compiled from "StartTaskRequest.java"
public interface software.amazon.awssdk.services.ecs.model.StartTaskRequest$Builder extends software.amazon.awssdk.services.ecs.model.EcsRequest$Builder, software.amazon.awssdk.core.SdkPojo, software.amazon.awssdk.utils.builder.CopyableBuilder<software.amazon.awssdk.services.ecs.model.StartTaskRequest$Builder, software.amazon.awssdk.services.ecs.model.StartTaskRequest> {
  public abstract software.amazon.awssdk.services.ecs.model.StartTaskRequest$Builder cluster(java.lang.String);

  public abstract software.amazon.awssdk.services.ecs.model.StartTaskRequest$Builder containerInstances(java.util.Collection<java.lang.String>);

  public abstract software.amazon.awssdk.services.ecs.model.StartTaskRequest$Builder containerInstances(java.lang.String...);

  public abstract software.amazon.awssdk.services.ecs.model.StartTaskRequest$Builder enableECSManagedTags(java.lang.Boolean);

  public abstract software.amazon.awssdk.services.ecs.model.StartTaskRequest$Builder enableExecuteCommand(java.lang.Boolean);

  public abstract software.amazon.awssdk.services.ecs.model.StartTaskRequest$Builder group(java.lang.String);

  public abstract software.amazon.awssdk.services.ecs.model.StartTaskRequest$Builder networkConfiguration(software.amazon.awssdk.services.ecs.model.NetworkConfiguration);

  public default software.amazon.awssdk.services.ecs.model.StartTaskRequest$Builder networkConfiguration(java.util.function.Consumer<software.amazon.awssdk.services.ecs.model.NetworkConfiguration$Builder>);
    Code:
       0: aload_0
       1: invokestatic  #1                  // Method software/amazon/awssdk/services/ecs/model/NetworkConfiguration.builder:()Lsoftware/amazon/awssdk/services/ecs/model/NetworkConfiguration$Builder;
       4: aload_1
       5: invokeinterface #2,  2            // InterfaceMethod software/amazon/awssdk/services/ecs/model/NetworkConfiguration$Builder.applyMutation:(Ljava/util/function/Consumer;)Lsoftware/amazon/awssdk/utils/builder/SdkBuilder;
      10: checkcast     #3                  // class software/amazon/awssdk/services/ecs/model/NetworkConfiguration$Builder
      13: invokeinterface #4,  1            // InterfaceMethod software/amazon/awssdk/services/ecs/model/NetworkConfiguration$Builder.build:()Ljava/lang/Object;
      18: checkcast     #5                  // class software/amazon/awssdk/services/ecs/model/NetworkConfiguration
      21: invokeinterface #6,  2            // InterfaceMethod networkConfiguration:(Lsoftware/amazon/awssdk/services/ecs/model/NetworkConfiguration;)Lsoftware/amazon/awssdk/services/ecs/model/StartTaskRequest$Builder;
      26: areturn

  public abstract software.amazon.awssdk.services.ecs.model.StartTaskRequest$Builder overrides(software.amazon.awssdk.services.ecs.model.TaskOverride);

  public default software.amazon.awssdk.services.ecs.model.StartTaskRequest$Builder overrides(java.util.function.Consumer<software.amazon.awssdk.services.ecs.model.TaskOverride$Builder>);
    Code:
       0: aload_0
       1: invokestatic  #7                  // Method software/amazon/awssdk/services/ecs/model/TaskOverride.builder:()Lsoftware/amazon/awssdk/services/ecs/model/TaskOverride$Builder;
       4: aload_1
       5: invokeinterface #8,  2            // InterfaceMethod software/amazon/awssdk/services/ecs/model/TaskOverride$Builder.applyMutation:(Ljava/util/function/Consumer;)Lsoftware/amazon/awssdk/utils/builder/SdkBuilder;
      10: checkcast     #9                  // class software/amazon/awssdk/services/ecs/model/TaskOverride$Builder
      13: invokeinterface #10,  1           // InterfaceMethod software/amazon/awssdk/services/ecs/model/TaskOverride$Builder.build:()Ljava/lang/Object;
      18: checkcast     #11                 // class software/amazon/awssdk/services/ecs/model/TaskOverride
      21: invokeinterface #12,  2           // InterfaceMethod overrides:(Lsoftware/amazon/awssdk/services/ecs/model/TaskOverride;)Lsoftware/amazon/awssdk/services/ecs/model/StartTaskRequest$Builder;
      26: areturn

  public abstract software.amazon.awssdk.services.ecs.model.StartTaskRequest$Builder propagateTags(java.lang.String);

  public abstract software.amazon.awssdk.services.ecs.model.StartTaskRequest$Builder propagateTags(software.amazon.awssdk.services.ecs.model.PropagateTags);

  public abstract software.amazon.awssdk.services.ecs.model.StartTaskRequest$Builder referenceId(java.lang.String);

  public abstract software.amazon.awssdk.services.ecs.model.StartTaskRequest$Builder startedBy(java.lang.String);

  public abstract software.amazon.awssdk.services.ecs.model.StartTaskRequest$Builder tags(java.util.Collection<software.amazon.awssdk.services.ecs.model.Tag>);

  public abstract software.amazon.awssdk.services.ecs.model.StartTaskRequest$Builder tags(software.amazon.awssdk.services.ecs.model.Tag...);

  public abstract software.amazon.awssdk.services.ecs.model.StartTaskRequest$Builder tags(java.util.function.Consumer<software.amazon.awssdk.services.ecs.model.Tag$Builder>...);

  public abstract software.amazon.awssdk.services.ecs.model.StartTaskRequest$Builder taskDefinition(java.lang.String);

  public abstract software.amazon.awssdk.services.ecs.model.StartTaskRequest$Builder overrideConfiguration(software.amazon.awssdk.awscore.AwsRequestOverrideConfiguration);

  public abstract software.amazon.awssdk.services.ecs.model.StartTaskRequest$Builder overrideConfiguration(java.util.function.Consumer<software.amazon.awssdk.awscore.AwsRequestOverrideConfiguration$Builder>);

  public default software.amazon.awssdk.awscore.AwsRequest$Builder overrideConfiguration(java.util.function.Consumer);
    Code:
       0: aload_0
       1: aload_1
       2: invokeinterface #13,  2           // InterfaceMethod overrideConfiguration:(Ljava/util/function/Consumer;)Lsoftware/amazon/awssdk/services/ecs/model/StartTaskRequest$Builder;
       7: areturn

  public default software.amazon.awssdk.awscore.AwsRequest$Builder overrideConfiguration(software.amazon.awssdk.awscore.AwsRequestOverrideConfiguration);
    Code:
       0: aload_0
       1: aload_1
       2: invokeinterface #14,  2           // InterfaceMethod overrideConfiguration:(Lsoftware/amazon/awssdk/awscore/AwsRequestOverrideConfiguration;)Lsoftware/amazon/awssdk/services/ecs/model/StartTaskRequest$Builder;
       7: areturn
}
