Compiled from "HttpRequest.java"
public final class com.google.logging.type.HttpRequest extends com.google.protobuf.GeneratedMessageV3 implements com.google.logging.type.HttpRequestOrBuilder {
  private static final long serialVersionUID;

  public static final int REQUEST_METHOD_FIELD_NUMBER;

  private volatile java.lang.Object requestMethod_;

  public static final int REQUEST_URL_FIELD_NUMBER;

  private volatile java.lang.Object requestUrl_;

  public static final int REQUEST_SIZE_FIELD_NUMBER;

  private long requestSize_;

  public static final int STATUS_FIELD_NUMBER;

  private int status_;

  public static final int RESPONSE_SIZE_FIELD_NUMBER;

  private long responseSize_;

  public static final int USER_AGENT_FIELD_NUMBER;

  private volatile java.lang.Object userAgent_;

  public static final int REMOTE_IP_FIELD_NUMBER;

  private volatile java.lang.Object remoteIp_;

  public static final int SERVER_IP_FIELD_NUMBER;

  private volatile java.lang.Object serverIp_;

  public static final int REFERER_FIELD_NUMBER;

  private volatile java.lang.Object referer_;

  public static final int LATENCY_FIELD_NUMBER;

  private com.google.protobuf.Duration latency_;

  public static final int CACHE_LOOKUP_FIELD_NUMBER;

  private boolean cacheLookup_;

  public static final int CACHE_HIT_FIELD_NUMBER;

  private boolean cacheHit_;

  public static final int CACHE_VALIDATED_WITH_ORIGIN_SERVER_FIELD_NUMBER;

  private boolean cacheValidatedWithOriginServer_;

  public static final int CACHE_FILL_BYTES_FIELD_NUMBER;

  private long cacheFillBytes_;

  public static final int PROTOCOL_FIELD_NUMBER;

  private volatile java.lang.Object protocol_;

  private byte memoizedIsInitialized;

  private static final com.google.logging.type.HttpRequest DEFAULT_INSTANCE;

  private static final com.google.protobuf.Parser<com.google.logging.type.HttpRequest> PARSER;

  private com.google.logging.type.HttpRequest(com.google.protobuf.GeneratedMessageV3$Builder<?>);
    Code:
       0: aload_0
       1: aload_1
       2: invokespecial #22                 // Method com/google/protobuf/GeneratedMessageV3."<init>":(Lcom/google/protobuf/GeneratedMessageV3$Builder;)V
       5: aload_0
       6: iconst_m1
       7: putfield      #23                 // Field memoizedIsInitialized:B
      10: return

  private com.google.logging.type.HttpRequest();
    Code:
       0: aload_0
       1: invokespecial #24                 // Method com/google/protobuf/GeneratedMessageV3."<init>":()V
       4: aload_0
       5: iconst_m1
       6: putfield      #23                 // Field memoizedIsInitialized:B
       9: aload_0
      10: ldc           #25                 // String
      12: putfield      #19                 // Field requestMethod_:Ljava/lang/Object;
      15: aload_0
      16: ldc           #25                 // String
      18: putfield      #18                 // Field requestUrl_:Ljava/lang/Object;
      21: aload_0
      22: ldc           #25                 // String
      24: putfield      #14                 // Field userAgent_:Ljava/lang/Object;
      27: aload_0
      28: ldc           #25                 // String
      30: putfield      #13                 // Field remoteIp_:Ljava/lang/Object;
      33: aload_0
      34: ldc           #25                 // String
      36: putfield      #12                 // Field serverIp_:Ljava/lang/Object;
      39: aload_0
      40: ldc           #25                 // String
      42: putfield      #11                 // Field referer_:Ljava/lang/Object;
      45: aload_0
      46: ldc           #25                 // String
      48: putfield      #5                  // Field protocol_:Ljava/lang/Object;
      51: return

  protected java.lang.Object newInstance(com.google.protobuf.GeneratedMessageV3$UnusedPrivateParameter);
    Code:
       0: new           #26                 // class com/google/logging/type/HttpRequest
       3: dup
       4: invokespecial #27                 // Method "<init>":()V
       7: areturn

  public final com.google.protobuf.UnknownFieldSet getUnknownFields();
    Code:
       0: aload_0
       1: getfield      #4                  // Field unknownFields:Lcom/google/protobuf/UnknownFieldSet;
       4: areturn

  private com.google.logging.type.HttpRequest(com.google.protobuf.CodedInputStream, com.google.protobuf.ExtensionRegistryLite) throws com.google.protobuf.InvalidProtocolBufferException;
    Code:
       0: aload_0
       1: invokespecial #27                 // Method "<init>":()V
       4: aload_2
       5: ifnonnull     16
       8: new           #28                 // class java/lang/NullPointerException
      11: dup
      12: invokespecial #29                 // Method java/lang/NullPointerException."<init>":()V
      15: athrow
      16: invokestatic  #30                 // Method com/google/protobuf/UnknownFieldSet.newBuilder:()Lcom/google/protobuf/UnknownFieldSet$Builder;
      19: astore_3
      20: iconst_0
      21: istore        4
      23: iload         4
      25: ifne          443
      28: aload_1
      29: invokevirtual #31                 // Method com/google/protobuf/CodedInputStream.readTag:()I
      32: istore        5
      34: iload         5
      36: lookupswitch  { // 16
                     0: 176
                    10: 182
                    18: 197
                    24: 212
                    32: 223
                    40: 234
                    50: 245
                    58: 260
                    66: 275
                    72: 290
                    80: 301
                    88: 312
                    96: 323
                   106: 334
                   114: 349
                   122: 410
               default: 425
          }
     176: iconst_1
     177: istore        4
     179: goto          440
     182: aload_1
     183: invokevirtual #32                 // Method com/google/protobuf/CodedInputStream.readStringRequireUtf8:()Ljava/lang/String;
     186: astore        6
     188: aload_0
     189: aload         6
     191: putfield      #19                 // Field requestMethod_:Ljava/lang/Object;
     194: goto          440
     197: aload_1
     198: invokevirtual #32                 // Method com/google/protobuf/CodedInputStream.readStringRequireUtf8:()Ljava/lang/String;
     201: astore        6
     203: aload_0
     204: aload         6
     206: putfield      #18                 // Field requestUrl_:Ljava/lang/Object;
     209: goto          440
     212: aload_0
     213: aload_1
     214: invokevirtual #33                 // Method com/google/protobuf/CodedInputStream.readInt64:()J
     217: putfield      #17                 // Field requestSize_:J
     220: goto          440
     223: aload_0
     224: aload_1
     225: invokevirtual #34                 // Method com/google/protobuf/CodedInputStream.readInt32:()I
     228: putfield      #16                 // Field status_:I
     231: goto          440
     234: aload_0
     235: aload_1
     236: invokevirtual #33                 // Method com/google/protobuf/CodedInputStream.readInt64:()J
     239: putfield      #15                 // Field responseSize_:J
     242: goto          440
     245: aload_1
     246: invokevirtual #32                 // Method com/google/protobuf/CodedInputStream.readStringRequireUtf8:()Ljava/lang/String;
     249: astore        6
     251: aload_0
     252: aload         6
     254: putfield      #14                 // Field userAgent_:Ljava/lang/Object;
     257: goto          440
     260: aload_1
     261: invokevirtual #32                 // Method com/google/protobuf/CodedInputStream.readStringRequireUtf8:()Ljava/lang/String;
     264: astore        6
     266: aload_0
     267: aload         6
     269: putfield      #13                 // Field remoteIp_:Ljava/lang/Object;
     272: goto          440
     275: aload_1
     276: invokevirtual #32                 // Method com/google/protobuf/CodedInputStream.readStringRequireUtf8:()Ljava/lang/String;
     279: astore        6
     281: aload_0
     282: aload         6
     284: putfield      #11                 // Field referer_:Ljava/lang/Object;
     287: goto          440
     290: aload_0
     291: aload_1
     292: invokevirtual #35                 // Method com/google/protobuf/CodedInputStream.readBool:()Z
     295: putfield      #8                  // Field cacheHit_:Z
     298: goto          440
     301: aload_0
     302: aload_1
     303: invokevirtual #35                 // Method com/google/protobuf/CodedInputStream.readBool:()Z
     306: putfield      #7                  // Field cacheValidatedWithOriginServer_:Z
     309: goto          440
     312: aload_0
     313: aload_1
     314: invokevirtual #35                 // Method com/google/protobuf/CodedInputStream.readBool:()Z
     317: putfield      #9                  // Field cacheLookup_:Z
     320: goto          440
     323: aload_0
     324: aload_1
     325: invokevirtual #33                 // Method com/google/protobuf/CodedInputStream.readInt64:()J
     328: putfield      #6                  // Field cacheFillBytes_:J
     331: goto          440
     334: aload_1
     335: invokevirtual #32                 // Method com/google/protobuf/CodedInputStream.readStringRequireUtf8:()Ljava/lang/String;
     338: astore        6
     340: aload_0
     341: aload         6
     343: putfield      #12                 // Field serverIp_:Ljava/lang/Object;
     346: goto          440
     349: aconst_null
     350: astore        6
     352: aload_0
     353: getfield      #10                 // Field latency_:Lcom/google/protobuf/Duration;
     356: ifnull        368
     359: aload_0
     360: getfield      #10                 // Field latency_:Lcom/google/protobuf/Duration;
     363: invokevirtual #36                 // Method com/google/protobuf/Duration.toBuilder:()Lcom/google/protobuf/Duration$Builder;
     366: astore        6
     368: aload_0
     369: aload_1
     370: invokestatic  #37                 // Method com/google/protobuf/Duration.parser:()Lcom/google/protobuf/Parser;
     373: aload_2
     374: invokevirtual #38                 // Method com/google/protobuf/CodedInputStream.readMessage:(Lcom/google/protobuf/Parser;Lcom/google/protobuf/ExtensionRegistryLite;)Lcom/google/protobuf/MessageLite;
     377: checkcast     #39                 // class com/google/protobuf/Duration
     380: putfield      #10                 // Field latency_:Lcom/google/protobuf/Duration;
     383: aload         6
     385: ifnull        440
     388: aload         6
     390: aload_0
     391: getfield      #10                 // Field latency_:Lcom/google/protobuf/Duration;
     394: invokevirtual #40                 // Method com/google/protobuf/Duration$Builder.mergeFrom:(Lcom/google/protobuf/Duration;)Lcom/google/protobuf/Duration$Builder;
     397: pop
     398: aload_0
     399: aload         6
     401: invokevirtual #41                 // Method com/google/protobuf/Duration$Builder.buildPartial:()Lcom/google/protobuf/Duration;
     404: putfield      #10                 // Field latency_:Lcom/google/protobuf/Duration;
     407: goto          440
     410: aload_1
     411: invokevirtual #32                 // Method com/google/protobuf/CodedInputStream.readStringRequireUtf8:()Ljava/lang/String;
     414: astore        6
     416: aload_0
     417: aload         6
     419: putfield      #5                  // Field protocol_:Ljava/lang/Object;
     422: goto          440
     425: aload_0
     426: aload_1
     427: aload_3
     428: aload_2
     429: iload         5
     431: invokevirtual #42                 // Method parseUnknownField:(Lcom/google/protobuf/CodedInputStream;Lcom/google/protobuf/UnknownFieldSet$Builder;Lcom/google/protobuf/ExtensionRegistryLite;I)Z
     434: ifne          440
     437: iconst_1
     438: istore        4
     440: goto          23
     443: aload_0
     444: aload_3
     445: invokevirtual #43                 // Method com/google/protobuf/UnknownFieldSet$Builder.build:()Lcom/google/protobuf/UnknownFieldSet;
     448: putfield      #4                  // Field unknownFields:Lcom/google/protobuf/UnknownFieldSet;
     451: aload_0
     452: invokevirtual #44                 // Method makeExtensionsImmutable:()V
     455: goto          500
     458: astore        4
     460: aload         4
     462: aload_0
     463: invokevirtual #46                 // Method com/google/protobuf/InvalidProtocolBufferException.setUnfinishedMessage:(Lcom/google/protobuf/MessageLite;)Lcom/google/protobuf/InvalidProtocolBufferException;
     466: athrow
     467: astore        4
     469: new           #45                 // class com/google/protobuf/InvalidProtocolBufferException
     472: dup
     473: aload         4
     475: invokespecial #48                 // Method com/google/protobuf/InvalidProtocolBufferException."<init>":(Ljava/io/IOException;)V
     478: aload_0
     479: invokevirtual #46                 // Method com/google/protobuf/InvalidProtocolBufferException.setUnfinishedMessage:(Lcom/google/protobuf/MessageLite;)Lcom/google/protobuf/InvalidProtocolBufferException;
     482: athrow
     483: astore        7
     485: aload_0
     486: aload_3
     487: invokevirtual #43                 // Method com/google/protobuf/UnknownFieldSet$Builder.build:()Lcom/google/protobuf/UnknownFieldSet;
     490: putfield      #4                  // Field unknownFields:Lcom/google/protobuf/UnknownFieldSet;
     493: aload_0
     494: invokevirtual #44                 // Method makeExtensionsImmutable:()V
     497: aload         7
     499: athrow
     500: return
    Exception table:
       from    to  target type
          20   443   458   Class com/google/protobuf/InvalidProtocolBufferException
          20   443   467   Class java/io/IOException
          20   443   483   any
         458   485   483   any

  public static final com.google.protobuf.Descriptors$Descriptor getDescriptor();
    Code:
       0: getstatic     #49                 // Field com/google/logging/type/HttpRequestProto.internal_static_google_logging_type_HttpRequest_descriptor:Lcom/google/protobuf/Descriptors$Descriptor;
       3: areturn

  protected com.google.protobuf.GeneratedMessageV3$FieldAccessorTable internalGetFieldAccessorTable();
    Code:
       0: getstatic     #50                 // Field com/google/logging/type/HttpRequestProto.internal_static_google_logging_type_HttpRequest_fieldAccessorTable:Lcom/google/protobuf/GeneratedMessageV3$FieldAccessorTable;
       3: ldc           #26                 // class com/google/logging/type/HttpRequest
       5: ldc           #51                 // class com/google/logging/type/HttpRequest$Builder
       7: invokevirtual #52                 // Method com/google/protobuf/GeneratedMessageV3$FieldAccessorTable.ensureFieldAccessorsInitialized:(Ljava/lang/Class;Ljava/lang/Class;)Lcom/google/protobuf/GeneratedMessageV3$FieldAccessorTable;
      10: areturn

  public java.lang.String getRequestMethod();
    Code:
       0: aload_0
       1: getfield      #19                 // Field requestMethod_:Ljava/lang/Object;
       4: astore_1
       5: aload_1
       6: instanceof    #53                 // class java/lang/String
       9: ifeq          17
      12: aload_1
      13: checkcast     #53                 // class java/lang/String
      16: areturn
      17: aload_1
      18: checkcast     #54                 // class com/google/protobuf/ByteString
      21: astore_2
      22: aload_2
      23: invokevirtual #55                 // Method com/google/protobuf/ByteString.toStringUtf8:()Ljava/lang/String;
      26: astore_3
      27: aload_0
      28: aload_3
      29: putfield      #19                 // Field requestMethod_:Ljava/lang/Object;
      32: aload_3
      33: areturn

  public com.google.protobuf.ByteString getRequestMethodBytes();
    Code:
       0: aload_0
       1: getfield      #19                 // Field requestMethod_:Ljava/lang/Object;
       4: astore_1
       5: aload_1
       6: instanceof    #53                 // class java/lang/String
       9: ifeq          27
      12: aload_1
      13: checkcast     #53                 // class java/lang/String
      16: invokestatic  #56                 // Method com/google/protobuf/ByteString.copyFromUtf8:(Ljava/lang/String;)Lcom/google/protobuf/ByteString;
      19: astore_2
      20: aload_0
      21: aload_2
      22: putfield      #19                 // Field requestMethod_:Ljava/lang/Object;
      25: aload_2
      26: areturn
      27: aload_1
      28: checkcast     #54                 // class com/google/protobuf/ByteString
      31: areturn

  public java.lang.String getRequestUrl();
    Code:
       0: aload_0
       1: getfield      #18                 // Field requestUrl_:Ljava/lang/Object;
       4: astore_1
       5: aload_1
       6: instanceof    #53                 // class java/lang/String
       9: ifeq          17
      12: aload_1
      13: checkcast     #53                 // class java/lang/String
      16: areturn
      17: aload_1
      18: checkcast     #54                 // class com/google/protobuf/ByteString
      21: astore_2
      22: aload_2
      23: invokevirtual #55                 // Method com/google/protobuf/ByteString.toStringUtf8:()Ljava/lang/String;
      26: astore_3
      27: aload_0
      28: aload_3
      29: putfield      #18                 // Field requestUrl_:Ljava/lang/Object;
      32: aload_3
      33: areturn

  public com.google.protobuf.ByteString getRequestUrlBytes();
    Code:
       0: aload_0
       1: getfield      #18                 // Field requestUrl_:Ljava/lang/Object;
       4: astore_1
       5: aload_1
       6: instanceof    #53                 // class java/lang/String
       9: ifeq          27
      12: aload_1
      13: checkcast     #53                 // class java/lang/String
      16: invokestatic  #56                 // Method com/google/protobuf/ByteString.copyFromUtf8:(Ljava/lang/String;)Lcom/google/protobuf/ByteString;
      19: astore_2
      20: aload_0
      21: aload_2
      22: putfield      #18                 // Field requestUrl_:Ljava/lang/Object;
      25: aload_2
      26: areturn
      27: aload_1
      28: checkcast     #54                 // class com/google/protobuf/ByteString
      31: areturn

  public long getRequestSize();
    Code:
       0: aload_0
       1: getfield      #17                 // Field requestSize_:J
       4: lreturn

  public int getStatus();
    Code:
       0: aload_0
       1: getfield      #16                 // Field status_:I
       4: ireturn

  public long getResponseSize();
    Code:
       0: aload_0
       1: getfield      #15                 // Field responseSize_:J
       4: lreturn

  public java.lang.String getUserAgent();
    Code:
       0: aload_0
       1: getfield      #14                 // Field userAgent_:Ljava/lang/Object;
       4: astore_1
       5: aload_1
       6: instanceof    #53                 // class java/lang/String
       9: ifeq          17
      12: aload_1
      13: checkcast     #53                 // class java/lang/String
      16: areturn
      17: aload_1
      18: checkcast     #54                 // class com/google/protobuf/ByteString
      21: astore_2
      22: aload_2
      23: invokevirtual #55                 // Method com/google/protobuf/ByteString.toStringUtf8:()Ljava/lang/String;
      26: astore_3
      27: aload_0
      28: aload_3
      29: putfield      #14                 // Field userAgent_:Ljava/lang/Object;
      32: aload_3
      33: areturn

  public com.google.protobuf.ByteString getUserAgentBytes();
    Code:
       0: aload_0
       1: getfield      #14                 // Field userAgent_:Ljava/lang/Object;
       4: astore_1
       5: aload_1
       6: instanceof    #53                 // class java/lang/String
       9: ifeq          27
      12: aload_1
      13: checkcast     #53                 // class java/lang/String
      16: invokestatic  #56                 // Method com/google/protobuf/ByteString.copyFromUtf8:(Ljava/lang/String;)Lcom/google/protobuf/ByteString;
      19: astore_2
      20: aload_0
      21: aload_2
      22: putfield      #14                 // Field userAgent_:Ljava/lang/Object;
      25: aload_2
      26: areturn
      27: aload_1
      28: checkcast     #54                 // class com/google/protobuf/ByteString
      31: areturn

  public java.lang.String getRemoteIp();
    Code:
       0: aload_0
       1: getfield      #13                 // Field remoteIp_:Ljava/lang/Object;
       4: astore_1
       5: aload_1
       6: instanceof    #53                 // class java/lang/String
       9: ifeq          17
      12: aload_1
      13: checkcast     #53                 // class java/lang/String
      16: areturn
      17: aload_1
      18: checkcast     #54                 // class com/google/protobuf/ByteString
      21: astore_2
      22: aload_2
      23: invokevirtual #55                 // Method com/google/protobuf/ByteString.toStringUtf8:()Ljava/lang/String;
      26: astore_3
      27: aload_0
      28: aload_3
      29: putfield      #13                 // Field remoteIp_:Ljava/lang/Object;
      32: aload_3
      33: areturn

  public com.google.protobuf.ByteString getRemoteIpBytes();
    Code:
       0: aload_0
       1: getfield      #13                 // Field remoteIp_:Ljava/lang/Object;
       4: astore_1
       5: aload_1
       6: instanceof    #53                 // class java/lang/String
       9: ifeq          27
      12: aload_1
      13: checkcast     #53                 // class java/lang/String
      16: invokestatic  #56                 // Method com/google/protobuf/ByteString.copyFromUtf8:(Ljava/lang/String;)Lcom/google/protobuf/ByteString;
      19: astore_2
      20: aload_0
      21: aload_2
      22: putfield      #13                 // Field remoteIp_:Ljava/lang/Object;
      25: aload_2
      26: areturn
      27: aload_1
      28: checkcast     #54                 // class com/google/protobuf/ByteString
      31: areturn

  public java.lang.String getServerIp();
    Code:
       0: aload_0
       1: getfield      #12                 // Field serverIp_:Ljava/lang/Object;
       4: astore_1
       5: aload_1
       6: instanceof    #53                 // class java/lang/String
       9: ifeq          17
      12: aload_1
      13: checkcast     #53                 // class java/lang/String
      16: areturn
      17: aload_1
      18: checkcast     #54                 // class com/google/protobuf/ByteString
      21: astore_2
      22: aload_2
      23: invokevirtual #55                 // Method com/google/protobuf/ByteString.toStringUtf8:()Ljava/lang/String;
      26: astore_3
      27: aload_0
      28: aload_3
      29: putfield      #12                 // Field serverIp_:Ljava/lang/Object;
      32: aload_3
      33: areturn

  public com.google.protobuf.ByteString getServerIpBytes();
    Code:
       0: aload_0
       1: getfield      #12                 // Field serverIp_:Ljava/lang/Object;
       4: astore_1
       5: aload_1
       6: instanceof    #53                 // class java/lang/String
       9: ifeq          27
      12: aload_1
      13: checkcast     #53                 // class java/lang/String
      16: invokestatic  #56                 // Method com/google/protobuf/ByteString.copyFromUtf8:(Ljava/lang/String;)Lcom/google/protobuf/ByteString;
      19: astore_2
      20: aload_0
      21: aload_2
      22: putfield      #12                 // Field serverIp_:Ljava/lang/Object;
      25: aload_2
      26: areturn
      27: aload_1
      28: checkcast     #54                 // class com/google/protobuf/ByteString
      31: areturn

  public java.lang.String getReferer();
    Code:
       0: aload_0
       1: getfield      #11                 // Field referer_:Ljava/lang/Object;
       4: astore_1
       5: aload_1
       6: instanceof    #53                 // class java/lang/String
       9: ifeq          17
      12: aload_1
      13: checkcast     #53                 // class java/lang/String
      16: areturn
      17: aload_1
      18: checkcast     #54                 // class com/google/protobuf/ByteString
      21: astore_2
      22: aload_2
      23: invokevirtual #55                 // Method com/google/protobuf/ByteString.toStringUtf8:()Ljava/lang/String;
      26: astore_3
      27: aload_0
      28: aload_3
      29: putfield      #11                 // Field referer_:Ljava/lang/Object;
      32: aload_3
      33: areturn

  public com.google.protobuf.ByteString getRefererBytes();
    Code:
       0: aload_0
       1: getfield      #11                 // Field referer_:Ljava/lang/Object;
       4: astore_1
       5: aload_1
       6: instanceof    #53                 // class java/lang/String
       9: ifeq          27
      12: aload_1
      13: checkcast     #53                 // class java/lang/String
      16: invokestatic  #56                 // Method com/google/protobuf/ByteString.copyFromUtf8:(Ljava/lang/String;)Lcom/google/protobuf/ByteString;
      19: astore_2
      20: aload_0
      21: aload_2
      22: putfield      #11                 // Field referer_:Ljava/lang/Object;
      25: aload_2
      26: areturn
      27: aload_1
      28: checkcast     #54                 // class com/google/protobuf/ByteString
      31: areturn

  public boolean hasLatency();
    Code:
       0: aload_0
       1: getfield      #10                 // Field latency_:Lcom/google/protobuf/Duration;
       4: ifnull        11
       7: iconst_1
       8: goto          12
      11: iconst_0
      12: ireturn

  public com.google.protobuf.Duration getLatency();
    Code:
       0: aload_0
       1: getfield      #10                 // Field latency_:Lcom/google/protobuf/Duration;
       4: ifnonnull     13
       7: invokestatic  #57                 // Method com/google/protobuf/Duration.getDefaultInstance:()Lcom/google/protobuf/Duration;
      10: goto          17
      13: aload_0
      14: getfield      #10                 // Field latency_:Lcom/google/protobuf/Duration;
      17: areturn

  public com.google.protobuf.DurationOrBuilder getLatencyOrBuilder();
    Code:
       0: aload_0
       1: invokevirtual #58                 // Method getLatency:()Lcom/google/protobuf/Duration;
       4: areturn

  public boolean getCacheLookup();
    Code:
       0: aload_0
       1: getfield      #9                  // Field cacheLookup_:Z
       4: ireturn

  public boolean getCacheHit();
    Code:
       0: aload_0
       1: getfield      #8                  // Field cacheHit_:Z
       4: ireturn

  public boolean getCacheValidatedWithOriginServer();
    Code:
       0: aload_0
       1: getfield      #7                  // Field cacheValidatedWithOriginServer_:Z
       4: ireturn

  public long getCacheFillBytes();
    Code:
       0: aload_0
       1: getfield      #6                  // Field cacheFillBytes_:J
       4: lreturn

  public java.lang.String getProtocol();
    Code:
       0: aload_0
       1: getfield      #5                  // Field protocol_:Ljava/lang/Object;
       4: astore_1
       5: aload_1
       6: instanceof    #53                 // class java/lang/String
       9: ifeq          17
      12: aload_1
      13: checkcast     #53                 // class java/lang/String
      16: areturn
      17: aload_1
      18: checkcast     #54                 // class com/google/protobuf/ByteString
      21: astore_2
      22: aload_2
      23: invokevirtual #55                 // Method com/google/protobuf/ByteString.toStringUtf8:()Ljava/lang/String;
      26: astore_3
      27: aload_0
      28: aload_3
      29: putfield      #5                  // Field protocol_:Ljava/lang/Object;
      32: aload_3
      33: areturn

  public com.google.protobuf.ByteString getProtocolBytes();
    Code:
       0: aload_0
       1: getfield      #5                  // Field protocol_:Ljava/lang/Object;
       4: astore_1
       5: aload_1
       6: instanceof    #53                 // class java/lang/String
       9: ifeq          27
      12: aload_1
      13: checkcast     #53                 // class java/lang/String
      16: invokestatic  #56                 // Method com/google/protobuf/ByteString.copyFromUtf8:(Ljava/lang/String;)Lcom/google/protobuf/ByteString;
      19: astore_2
      20: aload_0
      21: aload_2
      22: putfield      #5                  // Field protocol_:Ljava/lang/Object;
      25: aload_2
      26: areturn
      27: aload_1
      28: checkcast     #54                 // class com/google/protobuf/ByteString
      31: areturn

  public final boolean isInitialized();
    Code:
       0: aload_0
       1: getfield      #23                 // Field memoizedIsInitialized:B
       4: istore_1
       5: iload_1
       6: iconst_1
       7: if_icmpne     12
      10: iconst_1
      11: ireturn
      12: iload_1
      13: ifne          18
      16: iconst_0
      17: ireturn
      18: aload_0
      19: iconst_1
      20: putfield      #23                 // Field memoizedIsInitialized:B
      23: iconst_1
      24: ireturn

  public void writeTo(com.google.protobuf.CodedOutputStream) throws java.io.IOException;
    Code:
       0: aload_0
       1: invokevirtual #59                 // Method getRequestMethodBytes:()Lcom/google/protobuf/ByteString;
       4: invokevirtual #60                 // Method com/google/protobuf/ByteString.isEmpty:()Z
       7: ifne          19
      10: aload_1
      11: iconst_1
      12: aload_0
      13: getfield      #19                 // Field requestMethod_:Ljava/lang/Object;
      16: invokestatic  #61                 // Method com/google/protobuf/GeneratedMessageV3.writeString:(Lcom/google/protobuf/CodedOutputStream;ILjava/lang/Object;)V
      19: aload_0
      20: invokevirtual #62                 // Method getRequestUrlBytes:()Lcom/google/protobuf/ByteString;
      23: invokevirtual #60                 // Method com/google/protobuf/ByteString.isEmpty:()Z
      26: ifne          38
      29: aload_1
      30: iconst_2
      31: aload_0
      32: getfield      #18                 // Field requestUrl_:Ljava/lang/Object;
      35: invokestatic  #61                 // Method com/google/protobuf/GeneratedMessageV3.writeString:(Lcom/google/protobuf/CodedOutputStream;ILjava/lang/Object;)V
      38: aload_0
      39: getfield      #17                 // Field requestSize_:J
      42: lconst_0
      43: lcmp
      44: ifeq          56
      47: aload_1
      48: iconst_3
      49: aload_0
      50: getfield      #17                 // Field requestSize_:J
      53: invokevirtual #63                 // Method com/google/protobuf/CodedOutputStream.writeInt64:(IJ)V
      56: aload_0
      57: getfield      #16                 // Field status_:I
      60: ifeq          72
      63: aload_1
      64: iconst_4
      65: aload_0
      66: getfield      #16                 // Field status_:I
      69: invokevirtual #64                 // Method com/google/protobuf/CodedOutputStream.writeInt32:(II)V
      72: aload_0
      73: getfield      #15                 // Field responseSize_:J
      76: lconst_0
      77: lcmp
      78: ifeq          90
      81: aload_1
      82: iconst_5
      83: aload_0
      84: getfield      #15                 // Field responseSize_:J
      87: invokevirtual #63                 // Method com/google/protobuf/CodedOutputStream.writeInt64:(IJ)V
      90: aload_0
      91: invokevirtual #65                 // Method getUserAgentBytes:()Lcom/google/protobuf/ByteString;
      94: invokevirtual #60                 // Method com/google/protobuf/ByteString.isEmpty:()Z
      97: ifne          110
     100: aload_1
     101: bipush        6
     103: aload_0
     104: getfield      #14                 // Field userAgent_:Ljava/lang/Object;
     107: invokestatic  #61                 // Method com/google/protobuf/GeneratedMessageV3.writeString:(Lcom/google/protobuf/CodedOutputStream;ILjava/lang/Object;)V
     110: aload_0
     111: invokevirtual #66                 // Method getRemoteIpBytes:()Lcom/google/protobuf/ByteString;
     114: invokevirtual #60                 // Method com/google/protobuf/ByteString.isEmpty:()Z
     117: ifne          130
     120: aload_1
     121: bipush        7
     123: aload_0
     124: getfield      #13                 // Field remoteIp_:Ljava/lang/Object;
     127: invokestatic  #61                 // Method com/google/protobuf/GeneratedMessageV3.writeString:(Lcom/google/protobuf/CodedOutputStream;ILjava/lang/Object;)V
     130: aload_0
     131: invokevirtual #67                 // Method getRefererBytes:()Lcom/google/protobuf/ByteString;
     134: invokevirtual #60                 // Method com/google/protobuf/ByteString.isEmpty:()Z
     137: ifne          150
     140: aload_1
     141: bipush        8
     143: aload_0
     144: getfield      #11                 // Field referer_:Ljava/lang/Object;
     147: invokestatic  #61                 // Method com/google/protobuf/GeneratedMessageV3.writeString:(Lcom/google/protobuf/CodedOutputStream;ILjava/lang/Object;)V
     150: aload_0
     151: getfield      #8                  // Field cacheHit_:Z
     154: ifeq          167
     157: aload_1
     158: bipush        9
     160: aload_0
     161: getfield      #8                  // Field cacheHit_:Z
     164: invokevirtual #68                 // Method com/google/protobuf/CodedOutputStream.writeBool:(IZ)V
     167: aload_0
     168: getfield      #7                  // Field cacheValidatedWithOriginServer_:Z
     171: ifeq          184
     174: aload_1
     175: bipush        10
     177: aload_0
     178: getfield      #7                  // Field cacheValidatedWithOriginServer_:Z
     181: invokevirtual #68                 // Method com/google/protobuf/CodedOutputStream.writeBool:(IZ)V
     184: aload_0
     185: getfield      #9                  // Field cacheLookup_:Z
     188: ifeq          201
     191: aload_1
     192: bipush        11
     194: aload_0
     195: getfield      #9                  // Field cacheLookup_:Z
     198: invokevirtual #68                 // Method com/google/protobuf/CodedOutputStream.writeBool:(IZ)V
     201: aload_0
     202: getfield      #6                  // Field cacheFillBytes_:J
     205: lconst_0
     206: lcmp
     207: ifeq          220
     210: aload_1
     211: bipush        12
     213: aload_0
     214: getfield      #6                  // Field cacheFillBytes_:J
     217: invokevirtual #63                 // Method com/google/protobuf/CodedOutputStream.writeInt64:(IJ)V
     220: aload_0
     221: invokevirtual #69                 // Method getServerIpBytes:()Lcom/google/protobuf/ByteString;
     224: invokevirtual #60                 // Method com/google/protobuf/ByteString.isEmpty:()Z
     227: ifne          240
     230: aload_1
     231: bipush        13
     233: aload_0
     234: getfield      #12                 // Field serverIp_:Ljava/lang/Object;
     237: invokestatic  #61                 // Method com/google/protobuf/GeneratedMessageV3.writeString:(Lcom/google/protobuf/CodedOutputStream;ILjava/lang/Object;)V
     240: aload_0
     241: getfield      #10                 // Field latency_:Lcom/google/protobuf/Duration;
     244: ifnull        257
     247: aload_1
     248: bipush        14
     250: aload_0
     251: invokevirtual #58                 // Method getLatency:()Lcom/google/protobuf/Duration;
     254: invokevirtual #70                 // Method com/google/protobuf/CodedOutputStream.writeMessage:(ILcom/google/protobuf/MessageLite;)V
     257: aload_0
     258: invokevirtual #71                 // Method getProtocolBytes:()Lcom/google/protobuf/ByteString;
     261: invokevirtual #60                 // Method com/google/protobuf/ByteString.isEmpty:()Z
     264: ifne          277
     267: aload_1
     268: bipush        15
     270: aload_0
     271: getfield      #5                  // Field protocol_:Ljava/lang/Object;
     274: invokestatic  #61                 // Method com/google/protobuf/GeneratedMessageV3.writeString:(Lcom/google/protobuf/CodedOutputStream;ILjava/lang/Object;)V
     277: aload_0
     278: getfield      #4                  // Field unknownFields:Lcom/google/protobuf/UnknownFieldSet;
     281: aload_1
     282: invokevirtual #72                 // Method com/google/protobuf/UnknownFieldSet.writeTo:(Lcom/google/protobuf/CodedOutputStream;)V
     285: return

  public int getSerializedSize();
    Code:
       0: aload_0
       1: getfield      #73                 // Field memoizedSize:I
       4: istore_1
       5: iload_1
       6: iconst_m1
       7: if_icmpeq     12
      10: iload_1
      11: ireturn
      12: iconst_0
      13: istore_1
      14: aload_0
      15: invokevirtual #59                 // Method getRequestMethodBytes:()Lcom/google/protobuf/ByteString;
      18: invokevirtual #60                 // Method com/google/protobuf/ByteString.isEmpty:()Z
      21: ifne          35
      24: iload_1
      25: iconst_1
      26: aload_0
      27: getfield      #19                 // Field requestMethod_:Ljava/lang/Object;
      30: invokestatic  #74                 // Method com/google/protobuf/GeneratedMessageV3.computeStringSize:(ILjava/lang/Object;)I
      33: iadd
      34: istore_1
      35: aload_0
      36: invokevirtual #62                 // Method getRequestUrlBytes:()Lcom/google/protobuf/ByteString;
      39: invokevirtual #60                 // Method com/google/protobuf/ByteString.isEmpty:()Z
      42: ifne          56
      45: iload_1
      46: iconst_2
      47: aload_0
      48: getfield      #18                 // Field requestUrl_:Ljava/lang/Object;
      51: invokestatic  #74                 // Method com/google/protobuf/GeneratedMessageV3.computeStringSize:(ILjava/lang/Object;)I
      54: iadd
      55: istore_1
      56: aload_0
      57: getfield      #17                 // Field requestSize_:J
      60: lconst_0
      61: lcmp
      62: ifeq          76
      65: iload_1
      66: iconst_3
      67: aload_0
      68: getfield      #17                 // Field requestSize_:J
      71: invokestatic  #75                 // Method com/google/protobuf/CodedOutputStream.computeInt64Size:(IJ)I
      74: iadd
      75: istore_1
      76: aload_0
      77: getfield      #16                 // Field status_:I
      80: ifeq          94
      83: iload_1
      84: iconst_4
      85: aload_0
      86: getfield      #16                 // Field status_:I
      89: invokestatic  #76                 // Method com/google/protobuf/CodedOutputStream.computeInt32Size:(II)I
      92: iadd
      93: istore_1
      94: aload_0
      95: getfield      #15                 // Field responseSize_:J
      98: lconst_0
      99: lcmp
     100: ifeq          114
     103: iload_1
     104: iconst_5
     105: aload_0
     106: getfield      #15                 // Field responseSize_:J
     109: invokestatic  #75                 // Method com/google/protobuf/CodedOutputStream.computeInt64Size:(IJ)I
     112: iadd
     113: istore_1
     114: aload_0
     115: invokevirtual #65                 // Method getUserAgentBytes:()Lcom/google/protobuf/ByteString;
     118: invokevirtual #60                 // Method com/google/protobuf/ByteString.isEmpty:()Z
     121: ifne          136
     124: iload_1
     125: bipush        6
     127: aload_0
     128: getfield      #14                 // Field userAgent_:Ljava/lang/Object;
     131: invokestatic  #74                 // Method com/google/protobuf/GeneratedMessageV3.computeStringSize:(ILjava/lang/Object;)I
     134: iadd
     135: istore_1
     136: aload_0
     137: invokevirtual #66                 // Method getRemoteIpBytes:()Lcom/google/protobuf/ByteString;
     140: invokevirtual #60                 // Method com/google/protobuf/ByteString.isEmpty:()Z
     143: ifne          158
     146: iload_1
     147: bipush        7
     149: aload_0
     150: getfield      #13                 // Field remoteIp_:Ljava/lang/Object;
     153: invokestatic  #74                 // Method com/google/protobuf/GeneratedMessageV3.computeStringSize:(ILjava/lang/Object;)I
     156: iadd
     157: istore_1
     158: aload_0
     159: invokevirtual #67                 // Method getRefererBytes:()Lcom/google/protobuf/ByteString;
     162: invokevirtual #60                 // Method com/google/protobuf/ByteString.isEmpty:()Z
     165: ifne          180
     168: iload_1
     169: bipush        8
     171: aload_0
     172: getfield      #11                 // Field referer_:Ljava/lang/Object;
     175: invokestatic  #74                 // Method com/google/protobuf/GeneratedMessageV3.computeStringSize:(ILjava/lang/Object;)I
     178: iadd
     179: istore_1
     180: aload_0
     181: getfield      #8                  // Field cacheHit_:Z
     184: ifeq          199
     187: iload_1
     188: bipush        9
     190: aload_0
     191: getfield      #8                  // Field cacheHit_:Z
     194: invokestatic  #77                 // Method com/google/protobuf/CodedOutputStream.computeBoolSize:(IZ)I
     197: iadd
     198: istore_1
     199: aload_0
     200: getfield      #7                  // Field cacheValidatedWithOriginServer_:Z
     203: ifeq          218
     206: iload_1
     207: bipush        10
     209: aload_0
     210: getfield      #7                  // Field cacheValidatedWithOriginServer_:Z
     213: invokestatic  #77                 // Method com/google/protobuf/CodedOutputStream.computeBoolSize:(IZ)I
     216: iadd
     217: istore_1
     218: aload_0
     219: getfield      #9                  // Field cacheLookup_:Z
     222: ifeq          237
     225: iload_1
     226: bipush        11
     228: aload_0
     229: getfield      #9                  // Field cacheLookup_:Z
     232: invokestatic  #77                 // Method com/google/protobuf/CodedOutputStream.computeBoolSize:(IZ)I
     235: iadd
     236: istore_1
     237: aload_0
     238: getfield      #6                  // Field cacheFillBytes_:J
     241: lconst_0
     242: lcmp
     243: ifeq          258
     246: iload_1
     247: bipush        12
     249: aload_0
     250: getfield      #6                  // Field cacheFillBytes_:J
     253: invokestatic  #75                 // Method com/google/protobuf/CodedOutputStream.computeInt64Size:(IJ)I
     256: iadd
     257: istore_1
     258: aload_0
     259: invokevirtual #69                 // Method getServerIpBytes:()Lcom/google/protobuf/ByteString;
     262: invokevirtual #60                 // Method com/google/protobuf/ByteString.isEmpty:()Z
     265: ifne          280
     268: iload_1
     269: bipush        13
     271: aload_0
     272: getfield      #12                 // Field serverIp_:Ljava/lang/Object;
     275: invokestatic  #74                 // Method com/google/protobuf/GeneratedMessageV3.computeStringSize:(ILjava/lang/Object;)I
     278: iadd
     279: istore_1
     280: aload_0
     281: getfield      #10                 // Field latency_:Lcom/google/protobuf/Duration;
     284: ifnull        299
     287: iload_1
     288: bipush        14
     290: aload_0
     291: invokevirtual #58                 // Method getLatency:()Lcom/google/protobuf/Duration;
     294: invokestatic  #78                 // Method com/google/protobuf/CodedOutputStream.computeMessageSize:(ILcom/google/protobuf/MessageLite;)I
     297: iadd
     298: istore_1
     299: aload_0
     300: invokevirtual #71                 // Method getProtocolBytes:()Lcom/google/protobuf/ByteString;
     303: invokevirtual #60                 // Method com/google/protobuf/ByteString.isEmpty:()Z
     306: ifne          321
     309: iload_1
     310: bipush        15
     312: aload_0
     313: getfield      #5                  // Field protocol_:Ljava/lang/Object;
     316: invokestatic  #74                 // Method com/google/protobuf/GeneratedMessageV3.computeStringSize:(ILjava/lang/Object;)I
     319: iadd
     320: istore_1
     321: iload_1
     322: aload_0
     323: getfield      #4                  // Field unknownFields:Lcom/google/protobuf/UnknownFieldSet;
     326: invokevirtual #79                 // Method com/google/protobuf/UnknownFieldSet.getSerializedSize:()I
     329: iadd
     330: istore_1
     331: aload_0
     332: iload_1
     333: putfield      #73                 // Field memoizedSize:I
     336: iload_1
     337: ireturn

  public boolean equals(java.lang.Object);
    Code:
       0: aload_1
       1: aload_0
       2: if_acmpne     7
       5: iconst_1
       6: ireturn
       7: aload_1
       8: instanceof    #26                 // class com/google/logging/type/HttpRequest
      11: ifne          20
      14: aload_0
      15: aload_1
      16: invokespecial #80                 // Method com/google/protobuf/GeneratedMessageV3.equals:(Ljava/lang/Object;)Z
      19: ireturn
      20: aload_1
      21: checkcast     #26                 // class com/google/logging/type/HttpRequest
      24: astore_2
      25: aload_0
      26: invokevirtual #81                 // Method getRequestMethod:()Ljava/lang/String;
      29: aload_2
      30: invokevirtual #81                 // Method getRequestMethod:()Ljava/lang/String;
      33: invokevirtual #82                 // Method java/lang/String.equals:(Ljava/lang/Object;)Z
      36: ifne          41
      39: iconst_0
      40: ireturn
      41: aload_0
      42: invokevirtual #83                 // Method getRequestUrl:()Ljava/lang/String;
      45: aload_2
      46: invokevirtual #83                 // Method getRequestUrl:()Ljava/lang/String;
      49: invokevirtual #82                 // Method java/lang/String.equals:(Ljava/lang/Object;)Z
      52: ifne          57
      55: iconst_0
      56: ireturn
      57: aload_0
      58: invokevirtual #84                 // Method getRequestSize:()J
      61: aload_2
      62: invokevirtual #84                 // Method getRequestSize:()J
      65: lcmp
      66: ifeq          71
      69: iconst_0
      70: ireturn
      71: aload_0
      72: invokevirtual #85                 // Method getStatus:()I
      75: aload_2
      76: invokevirtual #85                 // Method getStatus:()I
      79: if_icmpeq     84
      82: iconst_0
      83: ireturn
      84: aload_0
      85: invokevirtual #86                 // Method getResponseSize:()J
      88: aload_2
      89: invokevirtual #86                 // Method getResponseSize:()J
      92: lcmp
      93: ifeq          98
      96: iconst_0
      97: ireturn
      98: aload_0
      99: invokevirtual #87                 // Method getUserAgent:()Ljava/lang/String;
     102: aload_2
     103: invokevirtual #87                 // Method getUserAgent:()Ljava/lang/String;
     106: invokevirtual #82                 // Method java/lang/String.equals:(Ljava/lang/Object;)Z
     109: ifne          114
     112: iconst_0
     113: ireturn
     114: aload_0
     115: invokevirtual #88                 // Method getRemoteIp:()Ljava/lang/String;
     118: aload_2
     119: invokevirtual #88                 // Method getRemoteIp:()Ljava/lang/String;
     122: invokevirtual #82                 // Method java/lang/String.equals:(Ljava/lang/Object;)Z
     125: ifne          130
     128: iconst_0
     129: ireturn
     130: aload_0
     131: invokevirtual #89                 // Method getServerIp:()Ljava/lang/String;
     134: aload_2
     135: invokevirtual #89                 // Method getServerIp:()Ljava/lang/String;
     138: invokevirtual #82                 // Method java/lang/String.equals:(Ljava/lang/Object;)Z
     141: ifne          146
     144: iconst_0
     145: ireturn
     146: aload_0
     147: invokevirtual #90                 // Method getReferer:()Ljava/lang/String;
     150: aload_2
     151: invokevirtual #90                 // Method getReferer:()Ljava/lang/String;
     154: invokevirtual #82                 // Method java/lang/String.equals:(Ljava/lang/Object;)Z
     157: ifne          162
     160: iconst_0
     161: ireturn
     162: aload_0
     163: invokevirtual #91                 // Method hasLatency:()Z
     166: aload_2
     167: invokevirtual #91                 // Method hasLatency:()Z
     170: if_icmpeq     175
     173: iconst_0
     174: ireturn
     175: aload_0
     176: invokevirtual #91                 // Method hasLatency:()Z
     179: ifeq          198
     182: aload_0
     183: invokevirtual #58                 // Method getLatency:()Lcom/google/protobuf/Duration;
     186: aload_2
     187: invokevirtual #58                 // Method getLatency:()Lcom/google/protobuf/Duration;
     190: invokevirtual #92                 // Method com/google/protobuf/Duration.equals:(Ljava/lang/Object;)Z
     193: ifne          198
     196: iconst_0
     197: ireturn
     198: aload_0
     199: invokevirtual #93                 // Method getCacheLookup:()Z
     202: aload_2
     203: invokevirtual #93                 // Method getCacheLookup:()Z
     206: if_icmpeq     211
     209: iconst_0
     210: ireturn
     211: aload_0
     212: invokevirtual #94                 // Method getCacheHit:()Z
     215: aload_2
     216: invokevirtual #94                 // Method getCacheHit:()Z
     219: if_icmpeq     224
     222: iconst_0
     223: ireturn
     224: aload_0
     225: invokevirtual #95                 // Method getCacheValidatedWithOriginServer:()Z
     228: aload_2
     229: invokevirtual #95                 // Method getCacheValidatedWithOriginServer:()Z
     232: if_icmpeq     237
     235: iconst_0
     236: ireturn
     237: aload_0
     238: invokevirtual #96                 // Method getCacheFillBytes:()J
     241: aload_2
     242: invokevirtual #96                 // Method getCacheFillBytes:()J
     245: lcmp
     246: ifeq          251
     249: iconst_0
     250: ireturn
     251: aload_0
     252: invokevirtual #97                 // Method getProtocol:()Ljava/lang/String;
     255: aload_2
     256: invokevirtual #97                 // Method getProtocol:()Ljava/lang/String;
     259: invokevirtual #82                 // Method java/lang/String.equals:(Ljava/lang/Object;)Z
     262: ifne          267
     265: iconst_0
     266: ireturn
     267: aload_0
     268: getfield      #4                  // Field unknownFields:Lcom/google/protobuf/UnknownFieldSet;
     271: aload_2
     272: getfield      #4                  // Field unknownFields:Lcom/google/protobuf/UnknownFieldSet;
     275: invokevirtual #98                 // Method com/google/protobuf/UnknownFieldSet.equals:(Ljava/lang/Object;)Z
     278: ifne          283
     281: iconst_0
     282: ireturn
     283: iconst_1
     284: ireturn

  public int hashCode();
    Code:
       0: aload_0
       1: getfield      #99                 // Field memoizedHashCode:I
       4: ifeq          12
       7: aload_0
       8: getfield      #99                 // Field memoizedHashCode:I
      11: ireturn
      12: bipush        41
      14: istore_1
      15: bipush        19
      17: iload_1
      18: imul
      19: invokestatic  #100                // Method getDescriptor:()Lcom/google/protobuf/Descriptors$Descriptor;
      22: invokevirtual #101                // Method java/lang/Object.hashCode:()I
      25: iadd
      26: istore_1
      27: bipush        37
      29: iload_1
      30: imul
      31: iconst_1
      32: iadd
      33: istore_1
      34: bipush        53
      36: iload_1
      37: imul
      38: aload_0
      39: invokevirtual #81                 // Method getRequestMethod:()Ljava/lang/String;
      42: invokevirtual #102                // Method java/lang/String.hashCode:()I
      45: iadd
      46: istore_1
      47: bipush        37
      49: iload_1
      50: imul
      51: iconst_2
      52: iadd
      53: istore_1
      54: bipush        53
      56: iload_1
      57: imul
      58: aload_0
      59: invokevirtual #83                 // Method getRequestUrl:()Ljava/lang/String;
      62: invokevirtual #102                // Method java/lang/String.hashCode:()I
      65: iadd
      66: istore_1
      67: bipush        37
      69: iload_1
      70: imul
      71: iconst_3
      72: iadd
      73: istore_1
      74: bipush        53
      76: iload_1
      77: imul
      78: aload_0
      79: invokevirtual #84                 // Method getRequestSize:()J
      82: invokestatic  #103                // Method com/google/protobuf/Internal.hashLong:(J)I
      85: iadd
      86: istore_1
      87: bipush        37
      89: iload_1
      90: imul
      91: iconst_4
      92: iadd
      93: istore_1
      94: bipush        53
      96: iload_1
      97: imul
      98: aload_0
      99: invokevirtual #85                 // Method getStatus:()I
     102: iadd
     103: istore_1
     104: bipush        37
     106: iload_1
     107: imul
     108: iconst_5
     109: iadd
     110: istore_1
     111: bipush        53
     113: iload_1
     114: imul
     115: aload_0
     116: invokevirtual #86                 // Method getResponseSize:()J
     119: invokestatic  #103                // Method com/google/protobuf/Internal.hashLong:(J)I
     122: iadd
     123: istore_1
     124: bipush        37
     126: iload_1
     127: imul
     128: bipush        6
     130: iadd
     131: istore_1
     132: bipush        53
     134: iload_1
     135: imul
     136: aload_0
     137: invokevirtual #87                 // Method getUserAgent:()Ljava/lang/String;
     140: invokevirtual #102                // Method java/lang/String.hashCode:()I
     143: iadd
     144: istore_1
     145: bipush        37
     147: iload_1
     148: imul
     149: bipush        7
     151: iadd
     152: istore_1
     153: bipush        53
     155: iload_1
     156: imul
     157: aload_0
     158: invokevirtual #88                 // Method getRemoteIp:()Ljava/lang/String;
     161: invokevirtual #102                // Method java/lang/String.hashCode:()I
     164: iadd
     165: istore_1
     166: bipush        37
     168: iload_1
     169: imul
     170: bipush        13
     172: iadd
     173: istore_1
     174: bipush        53
     176: iload_1
     177: imul
     178: aload_0
     179: invokevirtual #89                 // Method getServerIp:()Ljava/lang/String;
     182: invokevirtual #102                // Method java/lang/String.hashCode:()I
     185: iadd
     186: istore_1
     187: bipush        37
     189: iload_1
     190: imul
     191: bipush        8
     193: iadd
     194: istore_1
     195: bipush        53
     197: iload_1
     198: imul
     199: aload_0
     200: invokevirtual #90                 // Method getReferer:()Ljava/lang/String;
     203: invokevirtual #102                // Method java/lang/String.hashCode:()I
     206: iadd
     207: istore_1
     208: aload_0
     209: invokevirtual #91                 // Method hasLatency:()Z
     212: ifeq          236
     215: bipush        37
     217: iload_1
     218: imul
     219: bipush        14
     221: iadd
     222: istore_1
     223: bipush        53
     225: iload_1
     226: imul
     227: aload_0
     228: invokevirtual #58                 // Method getLatency:()Lcom/google/protobuf/Duration;
     231: invokevirtual #104                // Method com/google/protobuf/Duration.hashCode:()I
     234: iadd
     235: istore_1
     236: bipush        37
     238: iload_1
     239: imul
     240: bipush        11
     242: iadd
     243: istore_1
     244: bipush        53
     246: iload_1
     247: imul
     248: aload_0
     249: invokevirtual #93                 // Method getCacheLookup:()Z
     252: invokestatic  #105                // Method com/google/protobuf/Internal.hashBoolean:(Z)I
     255: iadd
     256: istore_1
     257: bipush        37
     259: iload_1
     260: imul
     261: bipush        9
     263: iadd
     264: istore_1
     265: bipush        53
     267: iload_1
     268: imul
     269: aload_0
     270: invokevirtual #94                 // Method getCacheHit:()Z
     273: invokestatic  #105                // Method com/google/protobuf/Internal.hashBoolean:(Z)I
     276: iadd
     277: istore_1
     278: bipush        37
     280: iload_1
     281: imul
     282: bipush        10
     284: iadd
     285: istore_1
     286: bipush        53
     288: iload_1
     289: imul
     290: aload_0
     291: invokevirtual #95                 // Method getCacheValidatedWithOriginServer:()Z
     294: invokestatic  #105                // Method com/google/protobuf/Internal.hashBoolean:(Z)I
     297: iadd
     298: istore_1
     299: bipush        37
     301: iload_1
     302: imul
     303: bipush        12
     305: iadd
     306: istore_1
     307: bipush        53
     309: iload_1
     310: imul
     311: aload_0
     312: invokevirtual #96                 // Method getCacheFillBytes:()J
     315: invokestatic  #103                // Method com/google/protobuf/Internal.hashLong:(J)I
     318: iadd
     319: istore_1
     320: bipush        37
     322: iload_1
     323: imul
     324: bipush        15
     326: iadd
     327: istore_1
     328: bipush        53
     330: iload_1
     331: imul
     332: aload_0
     333: invokevirtual #97                 // Method getProtocol:()Ljava/lang/String;
     336: invokevirtual #102                // Method java/lang/String.hashCode:()I
     339: iadd
     340: istore_1
     341: bipush        29
     343: iload_1
     344: imul
     345: aload_0
     346: getfield      #4                  // Field unknownFields:Lcom/google/protobuf/UnknownFieldSet;
     349: invokevirtual #106                // Method com/google/protobuf/UnknownFieldSet.hashCode:()I
     352: iadd
     353: istore_1
     354: aload_0
     355: iload_1
     356: putfield      #99                 // Field memoizedHashCode:I
     359: iload_1
     360: ireturn

  public static com.google.logging.type.HttpRequest parseFrom(java.nio.ByteBuffer) throws com.google.protobuf.InvalidProtocolBufferException;
    Code:
       0: getstatic     #3                  // Field PARSER:Lcom/google/protobuf/Parser;
       3: aload_0
       4: invokeinterface #107,  2          // InterfaceMethod com/google/protobuf/Parser.parseFrom:(Ljava/nio/ByteBuffer;)Ljava/lang/Object;
       9: checkcast     #26                 // class com/google/logging/type/HttpRequest
      12: areturn

  public static com.google.logging.type.HttpRequest parseFrom(java.nio.ByteBuffer, com.google.protobuf.ExtensionRegistryLite) throws com.google.protobuf.InvalidProtocolBufferException;
    Code:
       0: getstatic     #3                  // Field PARSER:Lcom/google/protobuf/Parser;
       3: aload_0
       4: aload_1
       5: invokeinterface #108,  3          // InterfaceMethod com/google/protobuf/Parser.parseFrom:(Ljava/nio/ByteBuffer;Lcom/google/protobuf/ExtensionRegistryLite;)Ljava/lang/Object;
      10: checkcast     #26                 // class com/google/logging/type/HttpRequest
      13: areturn

  public static com.google.logging.type.HttpRequest parseFrom(com.google.protobuf.ByteString) throws com.google.protobuf.InvalidProtocolBufferException;
    Code:
       0: getstatic     #3                  // Field PARSER:Lcom/google/protobuf/Parser;
       3: aload_0
       4: invokeinterface #109,  2          // InterfaceMethod com/google/protobuf/Parser.parseFrom:(Lcom/google/protobuf/ByteString;)Ljava/lang/Object;
       9: checkcast     #26                 // class com/google/logging/type/HttpRequest
      12: areturn

  public static com.google.logging.type.HttpRequest parseFrom(com.google.protobuf.ByteString, com.google.protobuf.ExtensionRegistryLite) throws com.google.protobuf.InvalidProtocolBufferException;
    Code:
       0: getstatic     #3                  // Field PARSER:Lcom/google/protobuf/Parser;
       3: aload_0
       4: aload_1
       5: invokeinterface #110,  3          // InterfaceMethod com/google/protobuf/Parser.parseFrom:(Lcom/google/protobuf/ByteString;Lcom/google/protobuf/ExtensionRegistryLite;)Ljava/lang/Object;
      10: checkcast     #26                 // class com/google/logging/type/HttpRequest
      13: areturn

  public static com.google.logging.type.HttpRequest parseFrom(byte[]) throws com.google.protobuf.InvalidProtocolBufferException;
    Code:
       0: getstatic     #3                  // Field PARSER:Lcom/google/protobuf/Parser;
       3: aload_0
       4: invokeinterface #111,  2          // InterfaceMethod com/google/protobuf/Parser.parseFrom:([B)Ljava/lang/Object;
       9: checkcast     #26                 // class com/google/logging/type/HttpRequest
      12: areturn

  public static com.google.logging.type.HttpRequest parseFrom(byte[], com.google.protobuf.ExtensionRegistryLite) throws com.google.protobuf.InvalidProtocolBufferException;
    Code:
       0: getstatic     #3                  // Field PARSER:Lcom/google/protobuf/Parser;
       3: aload_0
       4: aload_1
       5: invokeinterface #112,  3          // InterfaceMethod com/google/protobuf/Parser.parseFrom:([BLcom/google/protobuf/ExtensionRegistryLite;)Ljava/lang/Object;
      10: checkcast     #26                 // class com/google/logging/type/HttpRequest
      13: areturn

  public static com.google.logging.type.HttpRequest parseFrom(java.io.InputStream) throws java.io.IOException;
    Code:
       0: getstatic     #3                  // Field PARSER:Lcom/google/protobuf/Parser;
       3: aload_0
       4: invokestatic  #113                // Method com/google/protobuf/GeneratedMessageV3.parseWithIOException:(Lcom/google/protobuf/Parser;Ljava/io/InputStream;)Lcom/google/protobuf/Message;
       7: checkcast     #26                 // class com/google/logging/type/HttpRequest
      10: areturn

  public static com.google.logging.type.HttpRequest parseFrom(java.io.InputStream, com.google.protobuf.ExtensionRegistryLite) throws java.io.IOException;
    Code:
       0: getstatic     #3                  // Field PARSER:Lcom/google/protobuf/Parser;
       3: aload_0
       4: aload_1
       5: invokestatic  #114                // Method com/google/protobuf/GeneratedMessageV3.parseWithIOException:(Lcom/google/protobuf/Parser;Ljava/io/InputStream;Lcom/google/protobuf/ExtensionRegistryLite;)Lcom/google/protobuf/Message;
       8: checkcast     #26                 // class com/google/logging/type/HttpRequest
      11: areturn

  public static com.google.logging.type.HttpRequest parseDelimitedFrom(java.io.InputStream) throws java.io.IOException;
    Code:
       0: getstatic     #3                  // Field PARSER:Lcom/google/protobuf/Parser;
       3: aload_0
       4: invokestatic  #115                // Method com/google/protobuf/GeneratedMessageV3.parseDelimitedWithIOException:(Lcom/google/protobuf/Parser;Ljava/io/InputStream;)Lcom/google/protobuf/Message;
       7: checkcast     #26                 // class com/google/logging/type/HttpRequest
      10: areturn

  public static com.google.logging.type.HttpRequest parseDelimitedFrom(java.io.InputStream, com.google.protobuf.ExtensionRegistryLite) throws java.io.IOException;
    Code:
       0: getstatic     #3                  // Field PARSER:Lcom/google/protobuf/Parser;
       3: aload_0
       4: aload_1
       5: invokestatic  #116                // Method com/google/protobuf/GeneratedMessageV3.parseDelimitedWithIOException:(Lcom/google/protobuf/Parser;Ljava/io/InputStream;Lcom/google/protobuf/ExtensionRegistryLite;)Lcom/google/protobuf/Message;
       8: checkcast     #26                 // class com/google/logging/type/HttpRequest
      11: areturn

  public static com.google.logging.type.HttpRequest parseFrom(com.google.protobuf.CodedInputStream) throws java.io.IOException;
    Code:
       0: getstatic     #3                  // Field PARSER:Lcom/google/protobuf/Parser;
       3: aload_0
       4: invokestatic  #117                // Method com/google/protobuf/GeneratedMessageV3.parseWithIOException:(Lcom/google/protobuf/Parser;Lcom/google/protobuf/CodedInputStream;)Lcom/google/protobuf/Message;
       7: checkcast     #26                 // class com/google/logging/type/HttpRequest
      10: areturn

  public static com.google.logging.type.HttpRequest parseFrom(com.google.protobuf.CodedInputStream, com.google.protobuf.ExtensionRegistryLite) throws java.io.IOException;
    Code:
       0: getstatic     #3                  // Field PARSER:Lcom/google/protobuf/Parser;
       3: aload_0
       4: aload_1
       5: invokestatic  #118                // Method com/google/protobuf/GeneratedMessageV3.parseWithIOException:(Lcom/google/protobuf/Parser;Lcom/google/protobuf/CodedInputStream;Lcom/google/protobuf/ExtensionRegistryLite;)Lcom/google/protobuf/Message;
       8: checkcast     #26                 // class com/google/logging/type/HttpRequest
      11: areturn

  public com.google.logging.type.HttpRequest$Builder newBuilderForType();
    Code:
       0: invokestatic  #119                // Method newBuilder:()Lcom/google/logging/type/HttpRequest$Builder;
       3: areturn

  public static com.google.logging.type.HttpRequest$Builder newBuilder();
    Code:
       0: getstatic     #120                // Field DEFAULT_INSTANCE:Lcom/google/logging/type/HttpRequest;
       3: invokevirtual #121                // Method toBuilder:()Lcom/google/logging/type/HttpRequest$Builder;
       6: areturn

  public static com.google.logging.type.HttpRequest$Builder newBuilder(com.google.logging.type.HttpRequest);
    Code:
       0: getstatic     #120                // Field DEFAULT_INSTANCE:Lcom/google/logging/type/HttpRequest;
       3: invokevirtual #121                // Method toBuilder:()Lcom/google/logging/type/HttpRequest$Builder;
       6: aload_0
       7: invokevirtual #122                // Method com/google/logging/type/HttpRequest$Builder.mergeFrom:(Lcom/google/logging/type/HttpRequest;)Lcom/google/logging/type/HttpRequest$Builder;
      10: areturn

  public com.google.logging.type.HttpRequest$Builder toBuilder();
    Code:
       0: aload_0
       1: getstatic     #120                // Field DEFAULT_INSTANCE:Lcom/google/logging/type/HttpRequest;
       4: if_acmpne     18
       7: new           #51                 // class com/google/logging/type/HttpRequest$Builder
      10: dup
      11: aconst_null
      12: invokespecial #123                // Method com/google/logging/type/HttpRequest$Builder."<init>":(Lcom/google/logging/type/HttpRequest$1;)V
      15: goto          30
      18: new           #51                 // class com/google/logging/type/HttpRequest$Builder
      21: dup
      22: aconst_null
      23: invokespecial #123                // Method com/google/logging/type/HttpRequest$Builder."<init>":(Lcom/google/logging/type/HttpRequest$1;)V
      26: aload_0
      27: invokevirtual #122                // Method com/google/logging/type/HttpRequest$Builder.mergeFrom:(Lcom/google/logging/type/HttpRequest;)Lcom/google/logging/type/HttpRequest$Builder;
      30: areturn

  protected com.google.logging.type.HttpRequest$Builder newBuilderForType(com.google.protobuf.GeneratedMessageV3$BuilderParent);
    Code:
       0: new           #51                 // class com/google/logging/type/HttpRequest$Builder
       3: dup
       4: aload_1
       5: aconst_null
       6: invokespecial #124                // Method com/google/logging/type/HttpRequest$Builder."<init>":(Lcom/google/protobuf/GeneratedMessageV3$BuilderParent;Lcom/google/logging/type/HttpRequest$1;)V
       9: astore_2
      10: aload_2
      11: areturn

  public static com.google.logging.type.HttpRequest getDefaultInstance();
    Code:
       0: getstatic     #120                // Field DEFAULT_INSTANCE:Lcom/google/logging/type/HttpRequest;
       3: areturn

  public static com.google.protobuf.Parser<com.google.logging.type.HttpRequest> parser();
    Code:
       0: getstatic     #3                  // Field PARSER:Lcom/google/protobuf/Parser;
       3: areturn

  public com.google.protobuf.Parser<com.google.logging.type.HttpRequest> getParserForType();
    Code:
       0: getstatic     #3                  // Field PARSER:Lcom/google/protobuf/Parser;
       3: areturn

  public com.google.logging.type.HttpRequest getDefaultInstanceForType();
    Code:
       0: getstatic     #120                // Field DEFAULT_INSTANCE:Lcom/google/logging/type/HttpRequest;
       3: areturn

  protected com.google.protobuf.Message$Builder newBuilderForType(com.google.protobuf.GeneratedMessageV3$BuilderParent);
    Code:
       0: aload_0
       1: aload_1
       2: invokevirtual #125                // Method newBuilderForType:(Lcom/google/protobuf/GeneratedMessageV3$BuilderParent;)Lcom/google/logging/type/HttpRequest$Builder;
       5: areturn

  public com.google.protobuf.Message$Builder toBuilder();
    Code:
       0: aload_0
       1: invokevirtual #121                // Method toBuilder:()Lcom/google/logging/type/HttpRequest$Builder;
       4: areturn

  public com.google.protobuf.Message$Builder newBuilderForType();
    Code:
       0: aload_0
       1: invokevirtual #126                // Method newBuilderForType:()Lcom/google/logging/type/HttpRequest$Builder;
       4: areturn

  public com.google.protobuf.MessageLite$Builder toBuilder();
    Code:
       0: aload_0
       1: invokevirtual #121                // Method toBuilder:()Lcom/google/logging/type/HttpRequest$Builder;
       4: areturn

  public com.google.protobuf.MessageLite$Builder newBuilderForType();
    Code:
       0: aload_0
       1: invokevirtual #126                // Method newBuilderForType:()Lcom/google/logging/type/HttpRequest$Builder;
       4: areturn

  public com.google.protobuf.MessageLite getDefaultInstanceForType();
    Code:
       0: aload_0
       1: invokevirtual #127                // Method getDefaultInstanceForType:()Lcom/google/logging/type/HttpRequest;
       4: areturn

  public com.google.protobuf.Message getDefaultInstanceForType();
    Code:
       0: aload_0
       1: invokevirtual #127                // Method getDefaultInstanceForType:()Lcom/google/logging/type/HttpRequest;
       4: areturn

  static boolean access$200();
    Code:
       0: getstatic     #21                 // Field alwaysUseFieldBuilders:Z
       3: ireturn

  com.google.logging.type.HttpRequest(com.google.protobuf.GeneratedMessageV3$Builder, com.google.logging.type.HttpRequest$1);
    Code:
       0: aload_0
       1: aload_1
       2: invokespecial #20                 // Method "<init>":(Lcom/google/protobuf/GeneratedMessageV3$Builder;)V
       5: return

  static java.lang.Object access$402(com.google.logging.type.HttpRequest, java.lang.Object);
    Code:
       0: aload_0
       1: aload_1
       2: dup_x1
       3: putfield      #19                 // Field requestMethod_:Ljava/lang/Object;
       6: areturn

  static java.lang.Object access$502(com.google.logging.type.HttpRequest, java.lang.Object);
    Code:
       0: aload_0
       1: aload_1
       2: dup_x1
       3: putfield      #18                 // Field requestUrl_:Ljava/lang/Object;
       6: areturn

  static long access$602(com.google.logging.type.HttpRequest, long);
    Code:
       0: aload_0
       1: lload_1
       2: dup2_x1
       3: putfield      #17                 // Field requestSize_:J
       6: lreturn

  static int access$702(com.google.logging.type.HttpRequest, int);
    Code:
       0: aload_0
       1: iload_1
       2: dup_x1
       3: putfield      #16                 // Field status_:I
       6: ireturn

  static long access$802(com.google.logging.type.HttpRequest, long);
    Code:
       0: aload_0
       1: lload_1
       2: dup2_x1
       3: putfield      #15                 // Field responseSize_:J
       6: lreturn

  static java.lang.Object access$902(com.google.logging.type.HttpRequest, java.lang.Object);
    Code:
       0: aload_0
       1: aload_1
       2: dup_x1
       3: putfield      #14                 // Field userAgent_:Ljava/lang/Object;
       6: areturn

  static java.lang.Object access$1002(com.google.logging.type.HttpRequest, java.lang.Object);
    Code:
       0: aload_0
       1: aload_1
       2: dup_x1
       3: putfield      #13                 // Field remoteIp_:Ljava/lang/Object;
       6: areturn

  static java.lang.Object access$1102(com.google.logging.type.HttpRequest, java.lang.Object);
    Code:
       0: aload_0
       1: aload_1
       2: dup_x1
       3: putfield      #12                 // Field serverIp_:Ljava/lang/Object;
       6: areturn

  static java.lang.Object access$1202(com.google.logging.type.HttpRequest, java.lang.Object);
    Code:
       0: aload_0
       1: aload_1
       2: dup_x1
       3: putfield      #11                 // Field referer_:Ljava/lang/Object;
       6: areturn

  static com.google.protobuf.Duration access$1302(com.google.logging.type.HttpRequest, com.google.protobuf.Duration);
    Code:
       0: aload_0
       1: aload_1
       2: dup_x1
       3: putfield      #10                 // Field latency_:Lcom/google/protobuf/Duration;
       6: areturn

  static boolean access$1402(com.google.logging.type.HttpRequest, boolean);
    Code:
       0: aload_0
       1: iload_1
       2: dup_x1
       3: putfield      #9                  // Field cacheLookup_:Z
       6: ireturn

  static boolean access$1502(com.google.logging.type.HttpRequest, boolean);
    Code:
       0: aload_0
       1: iload_1
       2: dup_x1
       3: putfield      #8                  // Field cacheHit_:Z
       6: ireturn

  static boolean access$1602(com.google.logging.type.HttpRequest, boolean);
    Code:
       0: aload_0
       1: iload_1
       2: dup_x1
       3: putfield      #7                  // Field cacheValidatedWithOriginServer_:Z
       6: ireturn

  static long access$1702(com.google.logging.type.HttpRequest, long);
    Code:
       0: aload_0
       1: lload_1
       2: dup2_x1
       3: putfield      #6                  // Field cacheFillBytes_:J
       6: lreturn

  static java.lang.Object access$1802(com.google.logging.type.HttpRequest, java.lang.Object);
    Code:
       0: aload_0
       1: aload_1
       2: dup_x1
       3: putfield      #5                  // Field protocol_:Ljava/lang/Object;
       6: areturn

  static java.lang.Object access$400(com.google.logging.type.HttpRequest);
    Code:
       0: aload_0
       1: getfield      #19                 // Field requestMethod_:Ljava/lang/Object;
       4: areturn

  static java.lang.Object access$500(com.google.logging.type.HttpRequest);
    Code:
       0: aload_0
       1: getfield      #18                 // Field requestUrl_:Ljava/lang/Object;
       4: areturn

  static java.lang.Object access$900(com.google.logging.type.HttpRequest);
    Code:
       0: aload_0
       1: getfield      #14                 // Field userAgent_:Ljava/lang/Object;
       4: areturn

  static java.lang.Object access$1000(com.google.logging.type.HttpRequest);
    Code:
       0: aload_0
       1: getfield      #13                 // Field remoteIp_:Ljava/lang/Object;
       4: areturn

  static java.lang.Object access$1100(com.google.logging.type.HttpRequest);
    Code:
       0: aload_0
       1: getfield      #12                 // Field serverIp_:Ljava/lang/Object;
       4: areturn

  static java.lang.Object access$1200(com.google.logging.type.HttpRequest);
    Code:
       0: aload_0
       1: getfield      #11                 // Field referer_:Ljava/lang/Object;
       4: areturn

  static java.lang.Object access$1800(com.google.logging.type.HttpRequest);
    Code:
       0: aload_0
       1: getfield      #5                  // Field protocol_:Ljava/lang/Object;
       4: areturn

  static com.google.protobuf.UnknownFieldSet access$1900(com.google.logging.type.HttpRequest);
    Code:
       0: aload_0
       1: getfield      #4                  // Field unknownFields:Lcom/google/protobuf/UnknownFieldSet;
       4: areturn

  static com.google.protobuf.Parser access$2000();
    Code:
       0: getstatic     #3                  // Field PARSER:Lcom/google/protobuf/Parser;
       3: areturn

  static void access$2100(com.google.protobuf.ByteString) throws java.lang.IllegalArgumentException;
    Code:
       0: aload_0
       1: invokestatic  #2                  // Method checkByteStringIsUtf8:(Lcom/google/protobuf/ByteString;)V
       4: return

  static void access$2200(com.google.protobuf.ByteString) throws java.lang.IllegalArgumentException;
    Code:
       0: aload_0
       1: invokestatic  #2                  // Method checkByteStringIsUtf8:(Lcom/google/protobuf/ByteString;)V
       4: return

  static void access$2300(com.google.protobuf.ByteString) throws java.lang.IllegalArgumentException;
    Code:
       0: aload_0
       1: invokestatic  #2                  // Method checkByteStringIsUtf8:(Lcom/google/protobuf/ByteString;)V
       4: return

  static void access$2400(com.google.protobuf.ByteString) throws java.lang.IllegalArgumentException;
    Code:
       0: aload_0
       1: invokestatic  #2                  // Method checkByteStringIsUtf8:(Lcom/google/protobuf/ByteString;)V
       4: return

  static void access$2500(com.google.protobuf.ByteString) throws java.lang.IllegalArgumentException;
    Code:
       0: aload_0
       1: invokestatic  #2                  // Method checkByteStringIsUtf8:(Lcom/google/protobuf/ByteString;)V
       4: return

  static void access$2600(com.google.protobuf.ByteString) throws java.lang.IllegalArgumentException;
    Code:
       0: aload_0
       1: invokestatic  #2                  // Method checkByteStringIsUtf8:(Lcom/google/protobuf/ByteString;)V
       4: return

  static void access$2700(com.google.protobuf.ByteString) throws java.lang.IllegalArgumentException;
    Code:
       0: aload_0
       1: invokestatic  #2                  // Method checkByteStringIsUtf8:(Lcom/google/protobuf/ByteString;)V
       4: return

  com.google.logging.type.HttpRequest(com.google.protobuf.CodedInputStream, com.google.protobuf.ExtensionRegistryLite, com.google.logging.type.HttpRequest$1) throws com.google.protobuf.InvalidProtocolBufferException;
    Code:
       0: aload_0
       1: aload_1
       2: aload_2
       3: invokespecial #1                  // Method "<init>":(Lcom/google/protobuf/CodedInputStream;Lcom/google/protobuf/ExtensionRegistryLite;)V
       6: return

  static {};
    Code:
       0: new           #26                 // class com/google/logging/type/HttpRequest
       3: dup
       4: invokespecial #27                 // Method "<init>":()V
       7: putstatic     #120                // Field DEFAULT_INSTANCE:Lcom/google/logging/type/HttpRequest;
      10: new           #128                // class com/google/logging/type/HttpRequest$1
      13: dup
      14: invokespecial #129                // Method com/google/logging/type/HttpRequest$1."<init>":()V
      17: putstatic     #3                  // Field PARSER:Lcom/google/protobuf/Parser;
      20: return
}
