class org.bouncycastle.cms.OriginatorId implements org.bouncycastle.util.Selector {
  private byte[] subjectKeyId;

  private org.bouncycastle.asn1.x500.X500Name issuer;

  private java.math.BigInteger serialNumber;

  public org.bouncycastle.cms.OriginatorId(byte[]);
    Code:
       0: aload_0
       1: invokespecial #55                 // Method java/lang/Object."<init>":()V
       4: aload_0
       5: aload_1
       6: invokespecial #59                 // Method setSubjectKeyID:([B)V
       9: return

  private void setSubjectKeyID(byte[]);
    Code:
       0: aload_0
       1: aload_1
       2: putfield      #52                 // Field subjectKeyId:[B
       5: return

  public org.bouncycastle.cms.OriginatorId(org.bouncycastle.asn1.x500.X500Name, java.math.BigInteger);
    Code:
       0: aload_0
       1: invokespecial #55                 // Method java/lang/Object."<init>":()V
       4: aload_0
       5: aload_1
       6: aload_2
       7: invokespecial #61                 // Method setIssuerAndSerial:(Lorg/bouncycastle/asn1/x500/X500Name;Ljava/math/BigInteger;)V
      10: return

  private void setIssuerAndSerial(org.bouncycastle.asn1.x500.X500Name, java.math.BigInteger);
    Code:
       0: aload_0
       1: aload_1
       2: putfield      #54                 // Field issuer:Lorg/bouncycastle/asn1/x500/X500Name;
       5: aload_0
       6: aload_2
       7: putfield      #53                 // Field serialNumber:Ljava/math/BigInteger;
      10: return

  public org.bouncycastle.cms.OriginatorId(org.bouncycastle.asn1.x500.X500Name, java.math.BigInteger, byte[]);
    Code:
       0: aload_0
       1: invokespecial #55                 // Method java/lang/Object."<init>":()V
       4: aload_0
       5: aload_1
       6: aload_2
       7: invokespecial #61                 // Method setIssuerAndSerial:(Lorg/bouncycastle/asn1/x500/X500Name;Ljava/math/BigInteger;)V
      10: aload_0
      11: aload_3
      12: invokespecial #59                 // Method setSubjectKeyID:([B)V
      15: return

  public org.bouncycastle.asn1.x500.X500Name getIssuer();
    Code:
       0: aload_0
       1: getfield      #54                 // Field issuer:Lorg/bouncycastle/asn1/x500/X500Name;
       4: areturn

  public java.lang.Object clone();
    Code:
       0: new           #29                 // class org/bouncycastle/cms/OriginatorId
       3: dup
       4: aload_0
       5: getfield      #54                 // Field issuer:Lorg/bouncycastle/asn1/x500/X500Name;
       8: aload_0
       9: getfield      #53                 // Field serialNumber:Ljava/math/BigInteger;
      12: aload_0
      13: getfield      #52                 // Field subjectKeyId:[B
      16: invokespecial #62                 // Method "<init>":(Lorg/bouncycastle/asn1/x500/X500Name;Ljava/math/BigInteger;[B)V
      19: areturn

  public int hashCode();
    Code:
       0: aload_0
       1: getfield      #52                 // Field subjectKeyId:[B
       4: invokestatic  #63                 // Method org/bouncycastle/util/Arrays.hashCode:([B)I
       7: istore_1
       8: aload_0
       9: getfield      #53                 // Field serialNumber:Ljava/math/BigInteger;
      12: ifnull        25
      15: iload_1
      16: aload_0
      17: getfield      #53                 // Field serialNumber:Ljava/math/BigInteger;
      20: invokevirtual #57                 // Method java/math/BigInteger.hashCode:()I
      23: ixor
      24: istore_1
      25: aload_0
      26: getfield      #54                 // Field issuer:Lorg/bouncycastle/asn1/x500/X500Name;
      29: ifnull        42
      32: iload_1
      33: aload_0
      34: getfield      #54                 // Field issuer:Lorg/bouncycastle/asn1/x500/X500Name;
      37: invokevirtual #58                 // Method org/bouncycastle/asn1/x500/X500Name.hashCode:()I
      40: ixor
      41: istore_1
      42: iload_1
      43: ireturn

  public boolean equals(java.lang.Object);
    Code:
       0: aload_1
       1: instanceof    #29                 // class org/bouncycastle/cms/OriginatorId
       4: ifne          9
       7: iconst_0
       8: ireturn
       9: aload_1
      10: checkcast     #29                 // class org/bouncycastle/cms/OriginatorId
      13: astore_2
      14: aload_0
      15: getfield      #52                 // Field subjectKeyId:[B
      18: aload_2
      19: getfield      #52                 // Field subjectKeyId:[B
      22: invokestatic  #64                 // Method org/bouncycastle/util/Arrays.areEqual:([B[B)Z
      25: ifeq          62
      28: aload_0
      29: aload_0
      30: getfield      #53                 // Field serialNumber:Ljava/math/BigInteger;
      33: aload_2
      34: getfield      #53                 // Field serialNumber:Ljava/math/BigInteger;
      37: invokespecial #60                 // Method equalsObj:(Ljava/lang/Object;Ljava/lang/Object;)Z
      40: ifeq          62
      43: aload_0
      44: aload_0
      45: getfield      #54                 // Field issuer:Lorg/bouncycastle/asn1/x500/X500Name;
      48: aload_2
      49: getfield      #54                 // Field issuer:Lorg/bouncycastle/asn1/x500/X500Name;
      52: invokespecial #60                 // Method equalsObj:(Ljava/lang/Object;Ljava/lang/Object;)Z
      55: ifeq          62
      58: iconst_1
      59: goto          63
      62: iconst_0
      63: ireturn

  private boolean equalsObj(java.lang.Object, java.lang.Object);
    Code:
       0: aload_1
       1: ifnull        12
       4: aload_1
       5: aload_2
       6: invokevirtual #56                 // Method java/lang/Object.equals:(Ljava/lang/Object;)Z
       9: goto          21
      12: aload_2
      13: ifnonnull     20
      16: iconst_1
      17: goto          21
      20: iconst_0
      21: ireturn

  public boolean match(java.lang.Object);
    Code:
       0: iconst_0
       1: ireturn
}
