public abstract class org.bouncycastle.cms.RecipientInformation {
  protected org.bouncycastle.cms.RecipientId rid;

  protected org.bouncycastle.asn1.x509.AlgorithmIdentifier keyEncAlg;

  protected org.bouncycastle.asn1.x509.AlgorithmIdentifier messageAlgorithm;

  protected org.bouncycastle.cms.CMSSecureReadable secureReadable;

  private org.bouncycastle.cms.AuthAttributesProvider additionalData;

  private byte[] resultMac;

  private org.bouncycastle.cms.RecipientOperator operator;

  org.bouncycastle.cms.RecipientInformation(org.bouncycastle.asn1.x509.AlgorithmIdentifier, org.bouncycastle.asn1.x509.AlgorithmIdentifier, org.bouncycastle.cms.CMSSecureReadable, org.bouncycastle.cms.AuthAttributesProvider);
    Code:
       0: aload_0
       1: invokespecial #170                // Method java/lang/Object."<init>":()V
       4: aload_0
       5: aload_1
       6: putfield      #160                // Field keyEncAlg:Lorg/bouncycastle/asn1/x509/AlgorithmIdentifier;
       9: aload_0
      10: aload_2
      11: putfield      #161                // Field messageAlgorithm:Lorg/bouncycastle/asn1/x509/AlgorithmIdentifier;
      14: aload_0
      15: aload_3
      16: putfield      #163                // Field secureReadable:Lorg/bouncycastle/cms/CMSSecureReadable;
      19: aload_0
      20: aload         4
      22: putfield      #162                // Field additionalData:Lorg/bouncycastle/cms/AuthAttributesProvider;
      25: return

  public org.bouncycastle.cms.RecipientId getRID();
    Code:
       0: aload_0
       1: getfield      #164                // Field rid:Lorg/bouncycastle/cms/RecipientId;
       4: areturn

  private byte[] encodeObj(org.bouncycastle.asn1.ASN1Encodable) throws java.io.IOException;
    Code:
       0: aload_1
       1: ifnull        14
       4: aload_1
       5: invokeinterface #194,  1          // InterfaceMethod org/bouncycastle/asn1/ASN1Encodable.toASN1Primitive:()Lorg/bouncycastle/asn1/ASN1Primitive;
      10: invokevirtual #177                // Method org/bouncycastle/asn1/ASN1Primitive.getEncoded:()[B
      13: areturn
      14: aconst_null
      15: areturn

  public org.bouncycastle.asn1.x509.AlgorithmIdentifier getKeyEncryptionAlgorithm();
    Code:
       0: aload_0
       1: getfield      #160                // Field keyEncAlg:Lorg/bouncycastle/asn1/x509/AlgorithmIdentifier;
       4: areturn

  public java.lang.String getKeyEncryptionAlgOID();
    Code:
       0: aload_0
       1: getfield      #160                // Field keyEncAlg:Lorg/bouncycastle/asn1/x509/AlgorithmIdentifier;
       4: invokevirtual #180                // Method org/bouncycastle/asn1/x509/AlgorithmIdentifier.getAlgorithm:()Lorg/bouncycastle/asn1/ASN1ObjectIdentifier;
       7: invokevirtual #176                // Method org/bouncycastle/asn1/ASN1ObjectIdentifier.getId:()Ljava/lang/String;
      10: areturn

  public byte[] getKeyEncryptionAlgParams();
    Code:
       0: aload_0
       1: aload_0
       2: getfield      #160                // Field keyEncAlg:Lorg/bouncycastle/asn1/x509/AlgorithmIdentifier;
       5: invokevirtual #179                // Method org/bouncycastle/asn1/x509/AlgorithmIdentifier.getParameters:()Lorg/bouncycastle/asn1/ASN1Encodable;
       8: invokespecial #186                // Method encodeObj:(Lorg/bouncycastle/asn1/ASN1Encodable;)[B
      11: areturn
      12: astore_1
      13: new           #78                 // class java/lang/RuntimeException
      16: dup
      17: new           #79                 // class java/lang/StringBuilder
      20: dup
      21: invokespecial #172                // Method java/lang/StringBuilder."<init>":()V
      24: ldc           #2                  // String exception getting encryption parameters
      26: invokevirtual #175                // Method java/lang/StringBuilder.append:(Ljava/lang/String;)Ljava/lang/StringBuilder;
      29: aload_1
      30: invokevirtual #174                // Method java/lang/StringBuilder.append:(Ljava/lang/Object;)Ljava/lang/StringBuilder;
      33: invokevirtual #173                // Method java/lang/StringBuilder.toString:()Ljava/lang/String;
      36: invokespecial #171                // Method java/lang/RuntimeException."<init>":(Ljava/lang/String;)V
      39: athrow
    Exception table:
       from    to  target type
           0    11    12   Class java/lang/Exception

  public byte[] getContentDigest();
    Code:
       0: aload_0
       1: getfield      #163                // Field secureReadable:Lorg/bouncycastle/cms/CMSSecureReadable;
       4: instanceof    #87                 // class org/bouncycastle/cms/CMSEnvelopedHelper$CMSDigestAuthenticatedSecureReadable
       7: ifeq          21
      10: aload_0
      11: getfield      #163                // Field secureReadable:Lorg/bouncycastle/cms/CMSSecureReadable;
      14: checkcast     #87                 // class org/bouncycastle/cms/CMSEnvelopedHelper$CMSDigestAuthenticatedSecureReadable
      17: invokevirtual #181                // Method org/bouncycastle/cms/CMSEnvelopedHelper$CMSDigestAuthenticatedSecureReadable.getDigest:()[B
      20: areturn
      21: aconst_null
      22: areturn

  public byte[] getMac();
    Code:
       0: aload_0
       1: getfield      #159                // Field resultMac:[B
       4: ifnonnull     100
       7: aload_0
       8: getfield      #165                // Field operator:Lorg/bouncycastle/cms/RecipientOperator;
      11: invokevirtual #189                // Method org/bouncycastle/cms/RecipientOperator.isMacBased:()Z
      14: ifeq          100
      17: aload_0
      18: getfield      #162                // Field additionalData:Lorg/bouncycastle/cms/AuthAttributesProvider;
      21: ifnull        89
      24: aload_0
      25: getfield      #165                // Field operator:Lorg/bouncycastle/cms/RecipientOperator;
      28: new           #72                 // class java/io/ByteArrayInputStream
      31: dup
      32: aload_0
      33: getfield      #162                // Field additionalData:Lorg/bouncycastle/cms/AuthAttributesProvider;
      36: invokeinterface #196,  1          // InterfaceMethod org/bouncycastle/cms/AuthAttributesProvider.getAuthAttributes:()Lorg/bouncycastle/asn1/ASN1Set;
      41: ldc           #1                  // String DER
      43: invokevirtual #178                // Method org/bouncycastle/asn1/ASN1Set.getEncoded:(Ljava/lang/String;)[B
      46: invokespecial #166                // Method java/io/ByteArrayInputStream."<init>":([B)V
      49: invokevirtual #192                // Method org/bouncycastle/cms/RecipientOperator.getInputStream:(Ljava/io/InputStream;)Ljava/io/InputStream;
      52: invokestatic  #193                // Method org/bouncycastle/util/io/Streams.drain:(Ljava/io/InputStream;)V
      55: goto          89
      58: astore_1
      59: new           #76                 // class java/lang/IllegalStateException
      62: dup
      63: new           #79                 // class java/lang/StringBuilder
      66: dup
      67: invokespecial #172                // Method java/lang/StringBuilder."<init>":()V
      70: ldc           #3                  // String unable to drain input:
      72: invokevirtual #175                // Method java/lang/StringBuilder.append:(Ljava/lang/String;)Ljava/lang/StringBuilder;
      75: aload_1
      76: invokevirtual #167                // Method java/io/IOException.getMessage:()Ljava/lang/String;
      79: invokevirtual #175                // Method java/lang/StringBuilder.append:(Ljava/lang/String;)Ljava/lang/StringBuilder;
      82: invokevirtual #173                // Method java/lang/StringBuilder.toString:()Ljava/lang/String;
      85: invokespecial #169                // Method java/lang/IllegalStateException."<init>":(Ljava/lang/String;)V
      88: athrow
      89: aload_0
      90: aload_0
      91: getfield      #165                // Field operator:Lorg/bouncycastle/cms/RecipientOperator;
      94: invokevirtual #190                // Method org/bouncycastle/cms/RecipientOperator.getMac:()[B
      97: putfield      #159                // Field resultMac:[B
     100: aload_0
     101: getfield      #159                // Field resultMac:[B
     104: areturn
    Exception table:
       from    to  target type
          24    55    58   Class java/io/IOException

  public byte[] getContent(org.bouncycastle.cms.Recipient) throws org.bouncycastle.cms.CMSException;
    Code:
       0: aload_0
       1: aload_1
       2: invokevirtual #187                // Method getContentStream:(Lorg/bouncycastle/cms/Recipient;)Lorg/bouncycastle/cms/CMSTypedStream;
       5: invokevirtual #183                // Method org/bouncycastle/cms/CMSTypedStream.getContentStream:()Ljava/io/InputStream;
       8: invokestatic  #185                // Method org/bouncycastle/cms/CMSUtils.streamToByteArray:(Ljava/io/InputStream;)[B
      11: areturn
      12: astore_2
      13: new           #88                 // class org/bouncycastle/cms/CMSException
      16: dup
      17: new           #79                 // class java/lang/StringBuilder
      20: dup
      21: invokespecial #172                // Method java/lang/StringBuilder."<init>":()V
      24: ldc           #4                  // String unable to parse internal stream:
      26: invokevirtual #175                // Method java/lang/StringBuilder.append:(Ljava/lang/String;)Ljava/lang/StringBuilder;
      29: aload_2
      30: invokevirtual #167                // Method java/io/IOException.getMessage:()Ljava/lang/String;
      33: invokevirtual #175                // Method java/lang/StringBuilder.append:(Ljava/lang/String;)Ljava/lang/StringBuilder;
      36: invokevirtual #173                // Method java/lang/StringBuilder.toString:()Ljava/lang/String;
      39: aload_2
      40: invokespecial #182                // Method org/bouncycastle/cms/CMSException."<init>":(Ljava/lang/String;Ljava/lang/Exception;)V
      43: athrow
    Exception table:
       from    to  target type
           0    11    12   Class java/io/IOException

  public org.bouncycastle.cms.CMSTypedStream getContentStream(org.bouncycastle.cms.Recipient) throws org.bouncycastle.cms.CMSException, java.io.IOException;
    Code:
       0: aload_0
       1: aload_0
       2: aload_1
       3: invokevirtual #188                // Method getRecipientOperator:(Lorg/bouncycastle/cms/Recipient;)Lorg/bouncycastle/cms/RecipientOperator;
       6: putfield      #165                // Field operator:Lorg/bouncycastle/cms/RecipientOperator;
       9: aload_0
      10: getfield      #162                // Field additionalData:Lorg/bouncycastle/cms/AuthAttributesProvider;
      13: ifnull        93
      16: aload_0
      17: getfield      #162                // Field additionalData:Lorg/bouncycastle/cms/AuthAttributesProvider;
      20: invokeinterface #195,  1          // InterfaceMethod org/bouncycastle/cms/AuthAttributesProvider.isAead:()Z
      25: ifeq          76
      28: aload_0
      29: getfield      #165                // Field operator:Lorg/bouncycastle/cms/RecipientOperator;
      32: invokevirtual #191                // Method org/bouncycastle/cms/RecipientOperator.getAADStream:()Ljava/io/OutputStream;
      35: aload_0
      36: getfield      #162                // Field additionalData:Lorg/bouncycastle/cms/AuthAttributesProvider;
      39: invokeinterface #196,  1          // InterfaceMethod org/bouncycastle/cms/AuthAttributesProvider.getAuthAttributes:()Lorg/bouncycastle/asn1/ASN1Set;
      44: ldc           #1                  // String DER
      46: invokevirtual #178                // Method org/bouncycastle/asn1/ASN1Set.getEncoded:(Ljava/lang/String;)[B
      49: invokevirtual #168                // Method java/io/OutputStream.write:([B)V
      52: new           #90                 // class org/bouncycastle/cms/CMSTypedStream
      55: dup
      56: aload_0
      57: getfield      #165                // Field operator:Lorg/bouncycastle/cms/RecipientOperator;
      60: aload_0
      61: getfield      #163                // Field secureReadable:Lorg/bouncycastle/cms/CMSSecureReadable;
      64: invokeinterface #197,  1          // InterfaceMethod org/bouncycastle/cms/CMSSecureReadable.getInputStream:()Ljava/io/InputStream;
      69: invokevirtual #192                // Method org/bouncycastle/cms/RecipientOperator.getInputStream:(Ljava/io/InputStream;)Ljava/io/InputStream;
      72: invokespecial #184                // Method org/bouncycastle/cms/CMSTypedStream."<init>":(Ljava/io/InputStream;)V
      75: areturn
      76: new           #90                 // class org/bouncycastle/cms/CMSTypedStream
      79: dup
      80: aload_0
      81: getfield      #163                // Field secureReadable:Lorg/bouncycastle/cms/CMSSecureReadable;
      84: invokeinterface #197,  1          // InterfaceMethod org/bouncycastle/cms/CMSSecureReadable.getInputStream:()Ljava/io/InputStream;
      89: invokespecial #184                // Method org/bouncycastle/cms/CMSTypedStream."<init>":(Ljava/io/InputStream;)V
      92: areturn
      93: new           #90                 // class org/bouncycastle/cms/CMSTypedStream
      96: dup
      97: aload_0
      98: getfield      #165                // Field operator:Lorg/bouncycastle/cms/RecipientOperator;
     101: aload_0
     102: getfield      #163                // Field secureReadable:Lorg/bouncycastle/cms/CMSSecureReadable;
     105: invokeinterface #197,  1          // InterfaceMethod org/bouncycastle/cms/CMSSecureReadable.getInputStream:()Ljava/io/InputStream;
     110: invokevirtual #192                // Method org/bouncycastle/cms/RecipientOperator.getInputStream:(Ljava/io/InputStream;)Ljava/io/InputStream;
     113: invokespecial #184                // Method org/bouncycastle/cms/CMSTypedStream."<init>":(Ljava/io/InputStream;)V
     116: areturn

  protected abstract org.bouncycastle.cms.RecipientOperator getRecipientOperator(org.bouncycastle.cms.Recipient) throws org.bouncycastle.cms.CMSException, java.io.IOException;
}
