Compiled from "LegacySupport.java"
class org.jboss.as.security.LegacySupport$LegacyModulesAttributeReader implements org.jboss.as.controller.OperationStepHandler {
  private java.lang.String newKeyName;

  org.jboss.as.security.LegacySupport$LegacyModulesAttributeReader(java.lang.String);
    Code:
       0: aload_0
       1: invokespecial #1                  // Method java/lang/Object."<init>":()V
       4: aload_0
       5: aload_1
       6: putfield      #2                  // Field newKeyName:Ljava/lang/String;
       9: return

  public void execute(org.jboss.as.controller.OperationContext, org.jboss.dmr.ModelNode) throws org.jboss.as.controller.OperationFailedException;
    Code:
       0: aload_1
       1: getstatic     #3                  // Field org/jboss/as/controller/PathAddress.EMPTY_ADDRESS:Lorg/jboss/as/controller/PathAddress;
       4: invokeinterface #4,  2            // InterfaceMethod org/jboss/as/controller/OperationContext.readResource:(Lorg/jboss/as/controller/PathAddress;)Lorg/jboss/as/controller/registry/Resource;
       9: astore_3
      10: aload_3
      11: invokestatic  #5                  // Method org/jboss/as/controller/registry/Resource$Tools.readModel:(Lorg/jboss/as/controller/registry/Resource;)Lorg/jboss/dmr/ModelNode;
      14: aload_0
      15: getfield      #2                  // Field newKeyName:Ljava/lang/String;
      18: invokevirtual #6                  // Method org/jboss/dmr/ModelNode.get:(Ljava/lang/String;)Lorg/jboss/dmr/ModelNode;
      21: astore        4
      23: new           #7                  // class org/jboss/dmr/ModelNode
      26: dup
      27: invokespecial #8                  // Method org/jboss/dmr/ModelNode."<init>":()V
      30: astore        5
      32: aload         4
      34: invokevirtual #9                  // Method org/jboss/dmr/ModelNode.isDefined:()Z
      37: ifeq          92
      40: aload         4
      42: invokevirtual #10                 // Method org/jboss/dmr/ModelNode.asPropertyList:()Ljava/util/List;
      45: astore        6
      47: aload         6
      49: invokeinterface #11,  1           // InterfaceMethod java/util/List.iterator:()Ljava/util/Iterator;
      54: astore        7
      56: aload         7
      58: invokeinterface #12,  1           // InterfaceMethod java/util/Iterator.hasNext:()Z
      63: ifeq          92
      66: aload         7
      68: invokeinterface #13,  1           // InterfaceMethod java/util/Iterator.next:()Ljava/lang/Object;
      73: checkcast     #14                 // class org/jboss/dmr/Property
      76: astore        8
      78: aload         5
      80: aload         8
      82: invokevirtual #15                 // Method org/jboss/dmr/Property.getValue:()Lorg/jboss/dmr/ModelNode;
      85: invokevirtual #16                 // Method org/jboss/dmr/ModelNode.add:(Lorg/jboss/dmr/ModelNode;)Lorg/jboss/dmr/ModelNode;
      88: pop
      89: goto          56
      92: aload_1
      93: invokeinterface #17,  1           // InterfaceMethod org/jboss/as/controller/OperationContext.getResult:()Lorg/jboss/dmr/ModelNode;
      98: aload         5
     100: invokevirtual #18                 // Method org/jboss/dmr/ModelNode.set:(Lorg/jboss/dmr/ModelNode;)Lorg/jboss/dmr/ModelNode;
     103: pop
     104: return
}
