Compiled from "VariableSubstitutor.java"
public class org.webswing.server.common.util.VariableSubstitutor {
  private java.util.Map<java.lang.String, java.lang.String> customVars;

  private org.apache.commons.lang3.text.StrSubstitutor subs;

  public static org.webswing.server.common.util.VariableSubstitutor basic();
    Code:
       0: new           #2                  // class org/webswing/server/common/util/VariableSubstitutor
       3: dup
       4: new           #3                  // class java/util/HashMap
       7: dup
       8: invokespecial #4                  // Method java/util/HashMap."<init>":()V
      11: invokespecial #5                  // Method "<init>":(Ljava/util/Map;)V
      14: areturn

  public static org.webswing.server.common.util.VariableSubstitutor forSwingInstance(org.webswing.server.common.model.SecuredPathConfig, java.lang.String, java.util.Map<java.lang.String, java.io.Serializable>, java.lang.String, java.lang.String, java.lang.String, java.lang.String);
    Code:
       0: new           #3                  // class java/util/HashMap
       3: dup
       4: invokespecial #4                  // Method java/util/HashMap."<init>":()V
       7: astore        7
       9: aload_1
      10: ifnull        24
      13: aload         7
      15: ldc           #7                  // String user
      17: aload_1
      18: invokeinterface #8,  3            // InterfaceMethod java/util/Map.put:(Ljava/lang/Object;Ljava/lang/Object;)Ljava/lang/Object;
      23: pop
      24: aload_2
      25: ifnull        120
      28: aload_2
      29: invokeinterface #9,  1            // InterfaceMethod java/util/Map.entrySet:()Ljava/util/Set;
      34: invokeinterface #10,  1           // InterfaceMethod java/util/Set.iterator:()Ljava/util/Iterator;
      39: astore        8
      41: aload         8
      43: invokeinterface #11,  1           // InterfaceMethod java/util/Iterator.hasNext:()Z
      48: ifeq          120
      51: aload         8
      53: invokeinterface #12,  1           // InterfaceMethod java/util/Iterator.next:()Ljava/lang/Object;
      58: checkcast     #13                 // class java/util/Map$Entry
      61: astore        9
      63: aload         7
      65: new           #14                 // class java/lang/StringBuilder
      68: dup
      69: invokespecial #15                 // Method java/lang/StringBuilder."<init>":()V
      72: ldc           #16                 // String user.
      74: invokevirtual #17                 // Method java/lang/StringBuilder.append:(Ljava/lang/String;)Ljava/lang/StringBuilder;
      77: aload         9
      79: invokeinterface #18,  1           // InterfaceMethod java/util/Map$Entry.getKey:()Ljava/lang/Object;
      84: checkcast     #19                 // class java/lang/String
      87: invokevirtual #17                 // Method java/lang/StringBuilder.append:(Ljava/lang/String;)Ljava/lang/StringBuilder;
      90: invokevirtual #20                 // Method java/lang/StringBuilder.toString:()Ljava/lang/String;
      93: aload         9
      95: invokeinterface #21,  1           // InterfaceMethod java/util/Map$Entry.getValue:()Ljava/lang/Object;
     100: checkcast     #22                 // class java/io/Serializable
     103: invokevirtual #23                 // Method java/lang/Object.toString:()Ljava/lang/String;
     106: invokeinterface #8,  3            // InterfaceMethod java/util/Map.put:(Ljava/lang/Object;Ljava/lang/Object;)Ljava/lang/Object;
     111: pop
     112: goto          117
     115: astore        10
     117: goto          41
     120: aload_3
     121: ifnull        135
     124: aload         7
     126: ldc           #25                 // String clientId
     128: aload_3
     129: invokeinterface #8,  3            // InterfaceMethod java/util/Map.put:(Ljava/lang/Object;Ljava/lang/Object;)Ljava/lang/Object;
     134: pop
     135: aload         4
     137: ifnull        152
     140: aload         7
     142: ldc           #26                 // String clientIp
     144: aload         4
     146: invokeinterface #8,  3            // InterfaceMethod java/util/Map.put:(Ljava/lang/Object;Ljava/lang/Object;)Ljava/lang/Object;
     151: pop
     152: aload         5
     154: ifnull        169
     157: aload         7
     159: ldc           #27                 // String clientLocale
     161: aload         5
     163: invokeinterface #8,  3            // InterfaceMethod java/util/Map.put:(Ljava/lang/Object;Ljava/lang/Object;)Ljava/lang/Object;
     168: pop
     169: aload         6
     171: ifnull        186
     174: aload         7
     176: ldc           #28                 // String customArgs
     178: aload         6
     180: invokeinterface #8,  3            // InterfaceMethod java/util/Map.put:(Ljava/lang/Object;Ljava/lang/Object;)Ljava/lang/Object;
     185: pop
     186: aload_0
     187: ifnull        222
     190: aload         7
     192: ldc           #29                 // String webswing.homeFolder
     194: aload_0
     195: invokeinterface #30,  1           // InterfaceMethod org/webswing/server/common/model/SecuredPathConfig.getHomeDir:()Ljava/lang/String;
     200: invokeinterface #8,  3            // InterfaceMethod java/util/Map.put:(Ljava/lang/Object;Ljava/lang/Object;)Ljava/lang/Object;
     205: pop
     206: aload         7
     208: ldc           #31                 // String webswing.appPath
     210: aload_0
     211: invokeinterface #32,  1           // InterfaceMethod org/webswing/server/common/model/SecuredPathConfig.getPath:()Ljava/lang/String;
     216: invokeinterface #8,  3            // InterfaceMethod java/util/Map.put:(Ljava/lang/Object;Ljava/lang/Object;)Ljava/lang/Object;
     221: pop
     222: new           #2                  // class org/webswing/server/common/util/VariableSubstitutor
     225: dup
     226: aload         7
     228: invokespecial #5                  // Method "<init>":(Ljava/util/Map;)V
     231: areturn
    Exception table:
       from    to  target type
          63   112   115   Class java/lang/Exception

  public static org.webswing.server.common.util.VariableSubstitutor forSwingApp(org.webswing.server.common.model.SecuredPathConfig);
    Code:
       0: new           #3                  // class java/util/HashMap
       3: dup
       4: invokespecial #4                  // Method java/util/HashMap."<init>":()V
       7: astore_1
       8: aload_0
       9: ifnull        42
      12: aload_1
      13: ldc           #29                 // String webswing.homeFolder
      15: aload_0
      16: invokeinterface #30,  1           // InterfaceMethod org/webswing/server/common/model/SecuredPathConfig.getHomeDir:()Ljava/lang/String;
      21: invokeinterface #8,  3            // InterfaceMethod java/util/Map.put:(Ljava/lang/Object;Ljava/lang/Object;)Ljava/lang/Object;
      26: pop
      27: aload_1
      28: ldc           #31                 // String webswing.appPath
      30: aload_0
      31: invokeinterface #32,  1           // InterfaceMethod org/webswing/server/common/model/SecuredPathConfig.getPath:()Ljava/lang/String;
      36: invokeinterface #8,  3            // InterfaceMethod java/util/Map.put:(Ljava/lang/Object;Ljava/lang/Object;)Ljava/lang/Object;
      41: pop
      42: new           #2                  // class org/webswing/server/common/util/VariableSubstitutor
      45: dup
      46: aload_1
      47: invokespecial #5                  // Method "<init>":(Ljava/util/Map;)V
      50: areturn

  public org.webswing.server.common.util.VariableSubstitutor(java.util.Map<java.lang.String, java.lang.String>);
    Code:
       0: aload_0
       1: invokespecial #33                 // Method java/lang/Object."<init>":()V
       4: aload_0
       5: aload_1
       6: putfield      #1                  // Field customVars:Ljava/util/Map;
       9: aload_0
      10: new           #34                 // class org/apache/commons/lang3/text/StrSubstitutor
      13: dup
      14: new           #35                 // class org/webswing/server/common/util/VariableSubstitutor$1
      17: dup
      18: aload_0
      19: invokespecial #36                 // Method org/webswing/server/common/util/VariableSubstitutor$1."<init>":(Lorg/webswing/server/common/util/VariableSubstitutor;)V
      22: invokespecial #37                 // Method org/apache/commons/lang3/text/StrSubstitutor."<init>":(Lorg/apache/commons/lang3/text/StrLookup;)V
      25: putfield      #38                 // Field subs:Lorg/apache/commons/lang3/text/StrSubstitutor;
      28: return

  public java.lang.String replace(java.lang.String);
    Code:
       0: aload_0
       1: getfield      #38                 // Field subs:Lorg/apache/commons/lang3/text/StrSubstitutor;
       4: aload_1
       5: invokevirtual #39                 // Method org/apache/commons/lang3/text/StrSubstitutor.replace:(Ljava/lang/String;)Ljava/lang/String;
       8: areturn

  public java.util.Map<java.lang.String, java.lang.String> getVariableMap();
    Code:
       0: new           #3                  // class java/util/HashMap
       3: dup
       4: invokespecial #4                  // Method java/util/HashMap."<init>":()V
       7: astore_1
       8: aload_1
       9: invokestatic  #40                 // Method java/lang/System.getenv:()Ljava/util/Map;
      12: invokeinterface #41,  2           // InterfaceMethod java/util/Map.putAll:(Ljava/util/Map;)V
      17: invokestatic  #42                 // Method java/lang/System.getProperties:()Ljava/util/Properties;
      20: invokevirtual #43                 // Method java/util/Properties.stringPropertyNames:()Ljava/util/Set;
      23: invokeinterface #10,  1           // InterfaceMethod java/util/Set.iterator:()Ljava/util/Iterator;
      28: astore_2
      29: aload_2
      30: invokeinterface #11,  1           // InterfaceMethod java/util/Iterator.hasNext:()Z
      35: ifeq          66
      38: aload_2
      39: invokeinterface #12,  1           // InterfaceMethod java/util/Iterator.next:()Ljava/lang/Object;
      44: checkcast     #19                 // class java/lang/String
      47: astore_3
      48: aload_1
      49: aload_3
      50: invokestatic  #42                 // Method java/lang/System.getProperties:()Ljava/util/Properties;
      53: aload_3
      54: invokevirtual #44                 // Method java/util/Properties.getProperty:(Ljava/lang/String;)Ljava/lang/String;
      57: invokeinterface #8,  3            // InterfaceMethod java/util/Map.put:(Ljava/lang/Object;Ljava/lang/Object;)Ljava/lang/Object;
      62: pop
      63: goto          29
      66: aload_1
      67: aload_0
      68: getfield      #1                  // Field customVars:Ljava/util/Map;
      71: invokeinterface #41,  2           // InterfaceMethod java/util/Map.putAll:(Ljava/util/Map;)V
      76: aload_1
      77: areturn

  static java.util.Map access$000(org.webswing.server.common.util.VariableSubstitutor);
    Code:
       0: aload_0
       1: getfield      #1                  // Field customVars:Ljava/util/Map;
       4: areturn
}
