Compiled from "PeerNameResolvingHandler.java"
public final class io.undertow.server.handlers.PeerNameResolvingHandler$ResolveType extends java.lang.Enum<io.undertow.server.handlers.PeerNameResolvingHandler$ResolveType> {
  public static final io.undertow.server.handlers.PeerNameResolvingHandler$ResolveType FORWARD;

  public static final io.undertow.server.handlers.PeerNameResolvingHandler$ResolveType REVERSE;

  public static final io.undertow.server.handlers.PeerNameResolvingHandler$ResolveType FORWARD_AND_REVERSE;

  private static final io.undertow.server.handlers.PeerNameResolvingHandler$ResolveType[] $VALUES;

  public static io.undertow.server.handlers.PeerNameResolvingHandler$ResolveType[] values();
    Code:
       0: getstatic     #1                  // Field $VALUES:[Lio/undertow/server/handlers/PeerNameResolvingHandler$ResolveType;
       3: invokevirtual #2                  // Method "[Lio/undertow/server/handlers/PeerNameResolvingHandler$ResolveType;".clone:()Ljava/lang/Object;
       6: checkcast     #3                  // class "[Lio/undertow/server/handlers/PeerNameResolvingHandler$ResolveType;"
       9: areturn

  public static io.undertow.server.handlers.PeerNameResolvingHandler$ResolveType valueOf(java.lang.String);
    Code:
       0: ldc           #4                  // class io/undertow/server/handlers/PeerNameResolvingHandler$ResolveType
       2: aload_0
       3: invokestatic  #5                  // Method java/lang/Enum.valueOf:(Ljava/lang/Class;Ljava/lang/String;)Ljava/lang/Enum;
       6: checkcast     #4                  // class io/undertow/server/handlers/PeerNameResolvingHandler$ResolveType
       9: areturn

  private io.undertow.server.handlers.PeerNameResolvingHandler$ResolveType();
    Code:
       0: aload_0
       1: aload_1
       2: iload_2
       3: invokespecial #6                  // Method java/lang/Enum."<init>":(Ljava/lang/String;I)V
       6: return

  static {};
    Code:
       0: new           #4                  // class io/undertow/server/handlers/PeerNameResolvingHandler$ResolveType
       3: dup
       4: ldc           #7                  // String FORWARD
       6: iconst_0
       7: invokespecial #8                  // Method "<init>":(Ljava/lang/String;I)V
      10: putstatic     #9                  // Field FORWARD:Lio/undertow/server/handlers/PeerNameResolvingHandler$ResolveType;
      13: new           #4                  // class io/undertow/server/handlers/PeerNameResolvingHandler$ResolveType
      16: dup
      17: ldc           #10                 // String REVERSE
      19: iconst_1
      20: invokespecial #8                  // Method "<init>":(Ljava/lang/String;I)V
      23: putstatic     #11                 // Field REVERSE:Lio/undertow/server/handlers/PeerNameResolvingHandler$ResolveType;
      26: new           #4                  // class io/undertow/server/handlers/PeerNameResolvingHandler$ResolveType
      29: dup
      30: ldc           #12                 // String FORWARD_AND_REVERSE
      32: iconst_2
      33: invokespecial #8                  // Method "<init>":(Ljava/lang/String;I)V
      36: putstatic     #13                 // Field FORWARD_AND_REVERSE:Lio/undertow/server/handlers/PeerNameResolvingHandler$ResolveType;
      39: iconst_3
      40: anewarray     #4                  // class io/undertow/server/handlers/PeerNameResolvingHandler$ResolveType
      43: dup
      44: iconst_0
      45: getstatic     #9                  // Field FORWARD:Lio/undertow/server/handlers/PeerNameResolvingHandler$ResolveType;
      48: aastore
      49: dup
      50: iconst_1
      51: getstatic     #11                 // Field REVERSE:Lio/undertow/server/handlers/PeerNameResolvingHandler$ResolveType;
      54: aastore
      55: dup
      56: iconst_2
      57: getstatic     #13                 // Field FORWARD_AND_REVERSE:Lio/undertow/server/handlers/PeerNameResolvingHandler$ResolveType;
      60: aastore
      61: putstatic     #1                  // Field $VALUES:[Lio/undertow/server/handlers/PeerNameResolvingHandler$ResolveType;
      64: return
}
