Compiled from "DoneableServiceMonitor.java"
class io.dekorate.prometheus.model.DoneableServiceMonitor$1 implements io.dekorate.deps.kubernetes.api.builder.Function<io.dekorate.prometheus.model.ServiceMonitor, io.dekorate.prometheus.model.ServiceMonitor> {
  final io.dekorate.prometheus.model.DoneableServiceMonitor this$0;

  io.dekorate.prometheus.model.DoneableServiceMonitor$1(io.dekorate.prometheus.model.DoneableServiceMonitor);
    Code:
       0: aload_0
       1: aload_1
       2: putfield      #1                  // Field this$0:Lio/dekorate/prometheus/model/DoneableServiceMonitor;
       5: aload_0
       6: invokespecial #2                  // Method java/lang/Object."<init>":()V
       9: return

  public io.dekorate.prometheus.model.ServiceMonitor apply(io.dekorate.prometheus.model.ServiceMonitor);
    Code:
       0: aload_1
       1: areturn

  public java.lang.Object apply(java.lang.Object);
    Code:
       0: aload_0
       1: aload_1
       2: checkcast     #3                  // class io/dekorate/prometheus/model/ServiceMonitor
       5: invokevirtual #4                  // Method apply:(Lio/dekorate/prometheus/model/ServiceMonitor;)Lio/dekorate/prometheus/model/ServiceMonitor;
       8: areturn
}
