Compiled from "VirtualJarFileInputStream.java"
class org.jboss.vfs.VirtualJarFileInputStream$ProcessedEntry {
  private final java.util.jar.JarEntry jarEntry;

  private final long offset;

  private long crc;

  final org.jboss.vfs.VirtualJarFileInputStream this$0;

  private org.jboss.vfs.VirtualJarFileInputStream$ProcessedEntry(org.jboss.vfs.VirtualJarFileInputStream, java.util.jar.JarEntry, long);
    Code:
       0: aload_0
       1: aload_1
       2: putfield      #5                  // Field this$0:Lorg/jboss/vfs/VirtualJarFileInputStream;
       5: aload_0
       6: invokespecial #6                  // Method java/lang/Object."<init>":()V
       9: aload_0
      10: aload_2
      11: putfield      #2                  // Field jarEntry:Ljava/util/jar/JarEntry;
      14: aload_0
      15: lload_3
      16: putfield      #1                  // Field offset:J
      19: return

  static long access$102(org.jboss.vfs.VirtualJarFileInputStream$ProcessedEntry, long);
    Code:
       0: aload_0
       1: lload_1
       2: dup2_x1
       3: putfield      #4                  // Field crc:J
       6: lreturn

  org.jboss.vfs.VirtualJarFileInputStream$ProcessedEntry(org.jboss.vfs.VirtualJarFileInputStream, java.util.jar.JarEntry, long, org.jboss.vfs.VirtualJarFileInputStream$1);
    Code:
       0: aload_0
       1: aload_1
       2: aload_2
       3: lload_3
       4: invokespecial #3                  // Method "<init>":(Lorg/jboss/vfs/VirtualJarFileInputStream;Ljava/util/jar/JarEntry;J)V
       7: return

  static java.util.jar.JarEntry access$400(org.jboss.vfs.VirtualJarFileInputStream$ProcessedEntry);
    Code:
       0: aload_0
       1: getfield      #2                  // Field jarEntry:Ljava/util/jar/JarEntry;
       4: areturn

  static long access$100(org.jboss.vfs.VirtualJarFileInputStream$ProcessedEntry);
    Code:
       0: aload_0
       1: getfield      #4                  // Field crc:J
       4: lreturn

  static long access$500(org.jboss.vfs.VirtualJarFileInputStream$ProcessedEntry);
    Code:
       0: aload_0
       1: getfield      #1                  // Field offset:J
       4: lreturn
}
