Compiled from "BytesToNameCanonicalizer.java"
public final class com.fasterxml.jackson.core.sym.BytesToNameCanonicalizer {
  private static final int DEFAULT_T_SIZE;

  private static final int MAX_T_SIZE;

  static final int MAX_ENTRIES_FOR_REUSE;

  private static final int MAX_COLL_CHAIN_LENGTH;

  static final int MIN_HASH_SIZE;

  static final int INITIAL_COLLISION_LEN;

  static final int LAST_VALID_BUCKET;

  protected final com.fasterxml.jackson.core.sym.BytesToNameCanonicalizer _parent;

  protected final java.util.concurrent.atomic.AtomicReference<com.fasterxml.jackson.core.sym.BytesToNameCanonicalizer$TableInfo> _tableInfo;

  private final int _seed;

  protected boolean _intern;

  protected final boolean _failOnDoS;

  protected int _count;

  protected int _longestCollisionList;

  protected int _hashMask;

  protected int[] _hash;

  protected com.fasterxml.jackson.core.sym.Name[] _mainNames;

  protected com.fasterxml.jackson.core.sym.BytesToNameCanonicalizer$Bucket[] _collList;

  protected int _collCount;

  protected int _collEnd;

  private transient boolean _needRehash;

  private boolean _hashShared;

  private boolean _namesShared;

  private boolean _collListShared;

  protected java.util.BitSet _overflows;

  private static final int MULT;

  private static final int MULT2;

  private static final int MULT3;

  private com.fasterxml.jackson.core.sym.BytesToNameCanonicalizer(int, boolean, int, boolean);
    Code:
       0: aload_0
       1: invokespecial #1                  // Method java/lang/Object."<init>":()V
       4: aload_0
       5: aconst_null
       6: putfield      #2                  // Field _parent:Lcom/fasterxml/jackson/core/sym/BytesToNameCanonicalizer;
       9: aload_0
      10: iload_3
      11: putfield      #3                  // Field _seed:I
      14: aload_0
      15: iload_2
      16: putfield      #4                  // Field _intern:Z
      19: aload_0
      20: iload         4
      22: putfield      #5                  // Field _failOnDoS:Z
      25: iload_1
      26: bipush        16
      28: if_icmpge     37
      31: bipush        16
      33: istore_1
      34: goto          68
      37: iload_1
      38: iload_1
      39: iconst_1
      40: isub
      41: iand
      42: ifeq          68
      45: bipush        16
      47: istore        5
      49: iload         5
      51: iload_1
      52: if_icmpge     65
      55: iload         5
      57: iload         5
      59: iadd
      60: istore        5
      62: goto          49
      65: iload         5
      67: istore_1
      68: aload_0
      69: new           #6                  // class java/util/concurrent/atomic/AtomicReference
      72: dup
      73: aload_0
      74: iload_1
      75: invokespecial #7                  // Method initTableInfo:(I)Lcom/fasterxml/jackson/core/sym/BytesToNameCanonicalizer$TableInfo;
      78: invokespecial #8                  // Method java/util/concurrent/atomic/AtomicReference."<init>":(Ljava/lang/Object;)V
      81: putfield      #9                  // Field _tableInfo:Ljava/util/concurrent/atomic/AtomicReference;
      84: return

  private com.fasterxml.jackson.core.sym.BytesToNameCanonicalizer(com.fasterxml.jackson.core.sym.BytesToNameCanonicalizer, boolean, int, boolean, com.fasterxml.jackson.core.sym.BytesToNameCanonicalizer$TableInfo);
    Code:
       0: aload_0
       1: invokespecial #1                  // Method java/lang/Object."<init>":()V
       4: aload_0
       5: aload_1
       6: putfield      #2                  // Field _parent:Lcom/fasterxml/jackson/core/sym/BytesToNameCanonicalizer;
       9: aload_0
      10: iload_3
      11: putfield      #3                  // Field _seed:I
      14: aload_0
      15: iload_2
      16: putfield      #4                  // Field _intern:Z
      19: aload_0
      20: iload         4
      22: putfield      #5                  // Field _failOnDoS:Z
      25: aload_0
      26: aconst_null
      27: putfield      #9                  // Field _tableInfo:Ljava/util/concurrent/atomic/AtomicReference;
      30: aload_0
      31: aload         5
      33: getfield      #10                 // Field com/fasterxml/jackson/core/sym/BytesToNameCanonicalizer$TableInfo.count:I
      36: putfield      #11                 // Field _count:I
      39: aload_0
      40: aload         5
      42: getfield      #12                 // Field com/fasterxml/jackson/core/sym/BytesToNameCanonicalizer$TableInfo.mainHashMask:I
      45: putfield      #13                 // Field _hashMask:I
      48: aload_0
      49: aload         5
      51: getfield      #14                 // Field com/fasterxml/jackson/core/sym/BytesToNameCanonicalizer$TableInfo.mainHash:[I
      54: putfield      #15                 // Field _hash:[I
      57: aload_0
      58: aload         5
      60: getfield      #16                 // Field com/fasterxml/jackson/core/sym/BytesToNameCanonicalizer$TableInfo.mainNames:[Lcom/fasterxml/jackson/core/sym/Name;
      63: putfield      #17                 // Field _mainNames:[Lcom/fasterxml/jackson/core/sym/Name;
      66: aload_0
      67: aload         5
      69: getfield      #18                 // Field com/fasterxml/jackson/core/sym/BytesToNameCanonicalizer$TableInfo.collList:[Lcom/fasterxml/jackson/core/sym/BytesToNameCanonicalizer$Bucket;
      72: putfield      #19                 // Field _collList:[Lcom/fasterxml/jackson/core/sym/BytesToNameCanonicalizer$Bucket;
      75: aload_0
      76: aload         5
      78: getfield      #20                 // Field com/fasterxml/jackson/core/sym/BytesToNameCanonicalizer$TableInfo.collCount:I
      81: putfield      #21                 // Field _collCount:I
      84: aload_0
      85: aload         5
      87: getfield      #22                 // Field com/fasterxml/jackson/core/sym/BytesToNameCanonicalizer$TableInfo.collEnd:I
      90: putfield      #23                 // Field _collEnd:I
      93: aload_0
      94: aload         5
      96: getfield      #24                 // Field com/fasterxml/jackson/core/sym/BytesToNameCanonicalizer$TableInfo.longestCollisionList:I
      99: putfield      #25                 // Field _longestCollisionList:I
     102: aload_0
     103: iconst_0
     104: putfield      #26                 // Field _needRehash:Z
     107: aload_0
     108: iconst_1
     109: putfield      #27                 // Field _hashShared:Z
     112: aload_0
     113: iconst_1
     114: putfield      #28                 // Field _namesShared:Z
     117: aload_0
     118: iconst_1
     119: putfield      #29                 // Field _collListShared:Z
     122: return

  private com.fasterxml.jackson.core.sym.BytesToNameCanonicalizer$TableInfo initTableInfo(int);
    Code:
       0: new           #30                 // class com/fasterxml/jackson/core/sym/BytesToNameCanonicalizer$TableInfo
       3: dup
       4: iconst_0
       5: iload_1
       6: iconst_1
       7: isub
       8: iload_1
       9: newarray       int
      11: iload_1
      12: anewarray     #31                 // class com/fasterxml/jackson/core/sym/Name
      15: aconst_null
      16: iconst_0
      17: iconst_0
      18: iconst_0
      19: invokespecial #32                 // Method com/fasterxml/jackson/core/sym/BytesToNameCanonicalizer$TableInfo."<init>":(II[I[Lcom/fasterxml/jackson/core/sym/Name;[Lcom/fasterxml/jackson/core/sym/BytesToNameCanonicalizer$Bucket;III)V
      22: areturn

  public static com.fasterxml.jackson.core.sym.BytesToNameCanonicalizer createRoot();
    Code:
       0: invokestatic  #33                 // Method java/lang/System.currentTimeMillis:()J
       3: lstore_0
       4: lload_0
       5: l2i
       6: lload_0
       7: bipush        32
       9: lushr
      10: l2i
      11: iadd
      12: iconst_1
      13: ior
      14: istore_2
      15: iload_2
      16: invokestatic  #34                 // Method createRoot:(I)Lcom/fasterxml/jackson/core/sym/BytesToNameCanonicalizer;
      19: areturn

  protected static com.fasterxml.jackson.core.sym.BytesToNameCanonicalizer createRoot(int);
    Code:
       0: new           #35                 // class com/fasterxml/jackson/core/sym/BytesToNameCanonicalizer
       3: dup
       4: bipush        64
       6: iconst_1
       7: iload_0
       8: iconst_1
       9: invokespecial #36                 // Method "<init>":(IZIZ)V
      12: areturn

  public com.fasterxml.jackson.core.sym.BytesToNameCanonicalizer makeChild(int);
    Code:
       0: new           #35                 // class com/fasterxml/jackson/core/sym/BytesToNameCanonicalizer
       3: dup
       4: aload_0
       5: getstatic     #37                 // Field com/fasterxml/jackson/core/JsonFactory$Feature.INTERN_FIELD_NAMES:Lcom/fasterxml/jackson/core/JsonFactory$Feature;
       8: iload_1
       9: invokevirtual #38                 // Method com/fasterxml/jackson/core/JsonFactory$Feature.enabledIn:(I)Z
      12: aload_0
      13: getfield      #3                  // Field _seed:I
      16: getstatic     #39                 // Field com/fasterxml/jackson/core/JsonFactory$Feature.FAIL_ON_SYMBOL_HASH_OVERFLOW:Lcom/fasterxml/jackson/core/JsonFactory$Feature;
      19: iload_1
      20: invokevirtual #38                 // Method com/fasterxml/jackson/core/JsonFactory$Feature.enabledIn:(I)Z
      23: aload_0
      24: getfield      #9                  // Field _tableInfo:Ljava/util/concurrent/atomic/AtomicReference;
      27: invokevirtual #40                 // Method java/util/concurrent/atomic/AtomicReference.get:()Ljava/lang/Object;
      30: checkcast     #30                 // class com/fasterxml/jackson/core/sym/BytesToNameCanonicalizer$TableInfo
      33: invokespecial #41                 // Method "<init>":(Lcom/fasterxml/jackson/core/sym/BytesToNameCanonicalizer;ZIZLcom/fasterxml/jackson/core/sym/BytesToNameCanonicalizer$TableInfo;)V
      36: areturn

  public com.fasterxml.jackson.core.sym.BytesToNameCanonicalizer makeChild(boolean, boolean);
    Code:
       0: new           #35                 // class com/fasterxml/jackson/core/sym/BytesToNameCanonicalizer
       3: dup
       4: aload_0
       5: iload_2
       6: aload_0
       7: getfield      #3                  // Field _seed:I
      10: iconst_1
      11: aload_0
      12: getfield      #9                  // Field _tableInfo:Ljava/util/concurrent/atomic/AtomicReference;
      15: invokevirtual #40                 // Method java/util/concurrent/atomic/AtomicReference.get:()Ljava/lang/Object;
      18: checkcast     #30                 // class com/fasterxml/jackson/core/sym/BytesToNameCanonicalizer$TableInfo
      21: invokespecial #41                 // Method "<init>":(Lcom/fasterxml/jackson/core/sym/BytesToNameCanonicalizer;ZIZLcom/fasterxml/jackson/core/sym/BytesToNameCanonicalizer$TableInfo;)V
      24: areturn

  public void release();
    Code:
       0: aload_0
       1: getfield      #2                  // Field _parent:Lcom/fasterxml/jackson/core/sym/BytesToNameCanonicalizer;
       4: ifnull        44
       7: aload_0
       8: invokevirtual #42                 // Method maybeDirty:()Z
      11: ifeq          44
      14: aload_0
      15: getfield      #2                  // Field _parent:Lcom/fasterxml/jackson/core/sym/BytesToNameCanonicalizer;
      18: new           #30                 // class com/fasterxml/jackson/core/sym/BytesToNameCanonicalizer$TableInfo
      21: dup
      22: aload_0
      23: invokespecial #43                 // Method com/fasterxml/jackson/core/sym/BytesToNameCanonicalizer$TableInfo."<init>":(Lcom/fasterxml/jackson/core/sym/BytesToNameCanonicalizer;)V
      26: invokespecial #44                 // Method mergeChild:(Lcom/fasterxml/jackson/core/sym/BytesToNameCanonicalizer$TableInfo;)V
      29: aload_0
      30: iconst_1
      31: putfield      #27                 // Field _hashShared:Z
      34: aload_0
      35: iconst_1
      36: putfield      #28                 // Field _namesShared:Z
      39: aload_0
      40: iconst_1
      41: putfield      #29                 // Field _collListShared:Z
      44: return

  private void mergeChild(com.fasterxml.jackson.core.sym.BytesToNameCanonicalizer$TableInfo);
    Code:
       0: aload_1
       1: getfield      #10                 // Field com/fasterxml/jackson/core/sym/BytesToNameCanonicalizer$TableInfo.count:I
       4: istore_2
       5: aload_0
       6: getfield      #9                  // Field _tableInfo:Ljava/util/concurrent/atomic/AtomicReference;
       9: invokevirtual #40                 // Method java/util/concurrent/atomic/AtomicReference.get:()Ljava/lang/Object;
      12: checkcast     #30                 // class com/fasterxml/jackson/core/sym/BytesToNameCanonicalizer$TableInfo
      15: astore_3
      16: iload_2
      17: aload_3
      18: getfield      #10                 // Field com/fasterxml/jackson/core/sym/BytesToNameCanonicalizer$TableInfo.count:I
      21: if_icmpne     25
      24: return
      25: iload_2
      26: sipush        6000
      29: if_icmple     39
      32: aload_0
      33: bipush        64
      35: invokespecial #7                  // Method initTableInfo:(I)Lcom/fasterxml/jackson/core/sym/BytesToNameCanonicalizer$TableInfo;
      38: astore_1
      39: aload_0
      40: getfield      #9                  // Field _tableInfo:Ljava/util/concurrent/atomic/AtomicReference;
      43: aload_3
      44: aload_1
      45: invokevirtual #45                 // Method java/util/concurrent/atomic/AtomicReference.compareAndSet:(Ljava/lang/Object;Ljava/lang/Object;)Z
      48: pop
      49: return

  public int size();
    Code:
       0: aload_0
       1: getfield      #9                  // Field _tableInfo:Ljava/util/concurrent/atomic/AtomicReference;
       4: ifnull        21
       7: aload_0
       8: getfield      #9                  // Field _tableInfo:Ljava/util/concurrent/atomic/AtomicReference;
      11: invokevirtual #40                 // Method java/util/concurrent/atomic/AtomicReference.get:()Ljava/lang/Object;
      14: checkcast     #30                 // class com/fasterxml/jackson/core/sym/BytesToNameCanonicalizer$TableInfo
      17: getfield      #10                 // Field com/fasterxml/jackson/core/sym/BytesToNameCanonicalizer$TableInfo.count:I
      20: ireturn
      21: aload_0
      22: getfield      #11                 // Field _count:I
      25: ireturn

  public int bucketCount();
    Code:
       0: aload_0
       1: getfield      #15                 // Field _hash:[I
       4: arraylength
       5: ireturn

  public boolean maybeDirty();
    Code:
       0: aload_0
       1: getfield      #27                 // Field _hashShared:Z
       4: ifne          11
       7: iconst_1
       8: goto          12
      11: iconst_0
      12: ireturn

  public int hashSeed();
    Code:
       0: aload_0
       1: getfield      #3                  // Field _seed:I
       4: ireturn

  public int collisionCount();
    Code:
       0: aload_0
       1: getfield      #21                 // Field _collCount:I
       4: ireturn

  public int maxCollisionLength();
    Code:
       0: aload_0
       1: getfield      #25                 // Field _longestCollisionList:I
       4: ireturn

  public static com.fasterxml.jackson.core.sym.Name getEmptyName();
    Code:
       0: invokestatic  #46                 // Method com/fasterxml/jackson/core/sym/Name1.getEmptyName:()Lcom/fasterxml/jackson/core/sym/Name1;
       3: areturn

  public com.fasterxml.jackson.core.sym.Name findName(int);
    Code:
       0: aload_0
       1: iload_1
       2: invokevirtual #47                 // Method calcHash:(I)I
       5: istore_2
       6: iload_2
       7: aload_0
       8: getfield      #13                 // Field _hashMask:I
      11: iand
      12: istore_3
      13: aload_0
      14: getfield      #15                 // Field _hash:[I
      17: iload_3
      18: iaload
      19: istore        4
      21: iload         4
      23: bipush        8
      25: ishr
      26: iload_2
      27: ixor
      28: bipush        8
      30: ishl
      31: ifne          64
      34: aload_0
      35: getfield      #17                 // Field _mainNames:[Lcom/fasterxml/jackson/core/sym/Name;
      38: iload_3
      39: aaload
      40: astore        5
      42: aload         5
      44: ifnonnull     49
      47: aconst_null
      48: areturn
      49: aload         5
      51: iload_1
      52: invokevirtual #48                 // Method com/fasterxml/jackson/core/sym/Name.equals:(I)Z
      55: ifeq          61
      58: aload         5
      60: areturn
      61: goto          71
      64: iload         4
      66: ifne          71
      69: aconst_null
      70: areturn
      71: iload         4
      73: sipush        255
      76: iand
      77: istore        4
      79: iload         4
      81: ifle          110
      84: iinc          4, -1
      87: aload_0
      88: getfield      #19                 // Field _collList:[Lcom/fasterxml/jackson/core/sym/BytesToNameCanonicalizer$Bucket;
      91: iload         4
      93: aaload
      94: astore        5
      96: aload         5
      98: ifnull        110
     101: aload         5
     103: iload_2
     104: iload_1
     105: iconst_0
     106: invokevirtual #49                 // Method com/fasterxml/jackson/core/sym/BytesToNameCanonicalizer$Bucket.find:(III)Lcom/fasterxml/jackson/core/sym/Name;
     109: areturn
     110: aconst_null
     111: areturn

  public com.fasterxml.jackson.core.sym.Name findName(int, int);
    Code:
       0: iload_2
       1: ifne          12
       4: aload_0
       5: iload_1
       6: invokevirtual #47                 // Method calcHash:(I)I
       9: goto          18
      12: aload_0
      13: iload_1
      14: iload_2
      15: invokevirtual #50                 // Method calcHash:(II)I
      18: istore_3
      19: iload_3
      20: aload_0
      21: getfield      #13                 // Field _hashMask:I
      24: iand
      25: istore        4
      27: aload_0
      28: getfield      #15                 // Field _hash:[I
      31: iload         4
      33: iaload
      34: istore        5
      36: iload         5
      38: bipush        8
      40: ishr
      41: iload_3
      42: ixor
      43: bipush        8
      45: ishl
      46: ifne          81
      49: aload_0
      50: getfield      #17                 // Field _mainNames:[Lcom/fasterxml/jackson/core/sym/Name;
      53: iload         4
      55: aaload
      56: astore        6
      58: aload         6
      60: ifnonnull     65
      63: aconst_null
      64: areturn
      65: aload         6
      67: iload_1
      68: iload_2
      69: invokevirtual #51                 // Method com/fasterxml/jackson/core/sym/Name.equals:(II)Z
      72: ifeq          78
      75: aload         6
      77: areturn
      78: goto          88
      81: iload         5
      83: ifne          88
      86: aconst_null
      87: areturn
      88: iload         5
      90: sipush        255
      93: iand
      94: istore        5
      96: iload         5
      98: ifle          127
     101: iinc          5, -1
     104: aload_0
     105: getfield      #19                 // Field _collList:[Lcom/fasterxml/jackson/core/sym/BytesToNameCanonicalizer$Bucket;
     108: iload         5
     110: aaload
     111: astore        6
     113: aload         6
     115: ifnull        127
     118: aload         6
     120: iload_3
     121: iload_1
     122: iload_2
     123: invokevirtual #49                 // Method com/fasterxml/jackson/core/sym/BytesToNameCanonicalizer$Bucket.find:(III)Lcom/fasterxml/jackson/core/sym/Name;
     126: areturn
     127: aconst_null
     128: areturn

  public com.fasterxml.jackson.core.sym.Name findName(int, int, int);
    Code:
       0: aload_0
       1: iload_1
       2: iload_2
       3: iload_3
       4: invokevirtual #52                 // Method calcHash:(III)I
       7: istore        4
       9: iload         4
      11: aload_0
      12: getfield      #13                 // Field _hashMask:I
      15: iand
      16: istore        5
      18: aload_0
      19: getfield      #15                 // Field _hash:[I
      22: iload         5
      24: iaload
      25: istore        6
      27: iload         6
      29: bipush        8
      31: ishr
      32: iload         4
      34: ixor
      35: bipush        8
      37: ishl
      38: ifne          74
      41: aload_0
      42: getfield      #17                 // Field _mainNames:[Lcom/fasterxml/jackson/core/sym/Name;
      45: iload         5
      47: aaload
      48: astore        7
      50: aload         7
      52: ifnonnull     57
      55: aconst_null
      56: areturn
      57: aload         7
      59: iload_1
      60: iload_2
      61: iload_3
      62: invokevirtual #53                 // Method com/fasterxml/jackson/core/sym/Name.equals:(III)Z
      65: ifeq          71
      68: aload         7
      70: areturn
      71: goto          81
      74: iload         6
      76: ifne          81
      79: aconst_null
      80: areturn
      81: iload         6
      83: sipush        255
      86: iand
      87: istore        6
      89: iload         6
      91: ifle          122
      94: iinc          6, -1
      97: aload_0
      98: getfield      #19                 // Field _collList:[Lcom/fasterxml/jackson/core/sym/BytesToNameCanonicalizer$Bucket;
     101: iload         6
     103: aaload
     104: astore        7
     106: aload         7
     108: ifnull        122
     111: aload         7
     113: iload         4
     115: iload_1
     116: iload_2
     117: iload_3
     118: invokevirtual #54                 // Method com/fasterxml/jackson/core/sym/BytesToNameCanonicalizer$Bucket.find:(IIII)Lcom/fasterxml/jackson/core/sym/Name;
     121: areturn
     122: aconst_null
     123: areturn

  public com.fasterxml.jackson.core.sym.Name findName(int[], int);
    Code:
       0: iload_2
       1: iconst_4
       2: if_icmpge     44
       5: iload_2
       6: iconst_3
       7: if_icmpne     24
      10: aload_0
      11: aload_1
      12: iconst_0
      13: iaload
      14: aload_1
      15: iconst_1
      16: iaload
      17: aload_1
      18: iconst_2
      19: iaload
      20: invokevirtual #55                 // Method findName:(III)Lcom/fasterxml/jackson/core/sym/Name;
      23: areturn
      24: aload_0
      25: aload_1
      26: iconst_0
      27: iaload
      28: iload_2
      29: iconst_2
      30: if_icmpge     37
      33: iconst_0
      34: goto          40
      37: aload_1
      38: iconst_1
      39: iaload
      40: invokevirtual #56                 // Method findName:(II)Lcom/fasterxml/jackson/core/sym/Name;
      43: areturn
      44: aload_0
      45: aload_1
      46: iload_2
      47: invokevirtual #57                 // Method calcHash:([II)I
      50: istore_3
      51: iload_3
      52: aload_0
      53: getfield      #13                 // Field _hashMask:I
      56: iand
      57: istore        4
      59: aload_0
      60: getfield      #15                 // Field _hash:[I
      63: iload         4
      65: iaload
      66: istore        5
      68: iload         5
      70: bipush        8
      72: ishr
      73: iload_3
      74: ixor
      75: bipush        8
      77: ishl
      78: ifne          111
      81: aload_0
      82: getfield      #17                 // Field _mainNames:[Lcom/fasterxml/jackson/core/sym/Name;
      85: iload         4
      87: aaload
      88: astore        6
      90: aload         6
      92: ifnull        105
      95: aload         6
      97: aload_1
      98: iload_2
      99: invokevirtual #58                 // Method com/fasterxml/jackson/core/sym/Name.equals:([II)Z
     102: ifeq          108
     105: aload         6
     107: areturn
     108: goto          118
     111: iload         5
     113: ifne          118
     116: aconst_null
     117: areturn
     118: iload         5
     120: sipush        255
     123: iand
     124: istore        5
     126: iload         5
     128: ifle          157
     131: iinc          5, -1
     134: aload_0
     135: getfield      #19                 // Field _collList:[Lcom/fasterxml/jackson/core/sym/BytesToNameCanonicalizer$Bucket;
     138: iload         5
     140: aaload
     141: astore        6
     143: aload         6
     145: ifnull        157
     148: aload         6
     150: iload_3
     151: aload_1
     152: iload_2
     153: invokevirtual #59                 // Method com/fasterxml/jackson/core/sym/BytesToNameCanonicalizer$Bucket.find:(I[II)Lcom/fasterxml/jackson/core/sym/Name;
     156: areturn
     157: aconst_null
     158: areturn

  public com.fasterxml.jackson.core.sym.Name addName(java.lang.String, int, int);
    Code:
       0: aload_0
       1: getfield      #4                  // Field _intern:Z
       4: ifeq          15
       7: getstatic     #60                 // Field com/fasterxml/jackson/core/util/InternCache.instance:Lcom/fasterxml/jackson/core/util/InternCache;
      10: aload_1
      11: invokevirtual #61                 // Method com/fasterxml/jackson/core/util/InternCache.intern:(Ljava/lang/String;)Ljava/lang/String;
      14: astore_1
      15: iload_3
      16: ifne          27
      19: aload_0
      20: iload_2
      21: invokevirtual #47                 // Method calcHash:(I)I
      24: goto          33
      27: aload_0
      28: iload_2
      29: iload_3
      30: invokevirtual #50                 // Method calcHash:(II)I
      33: istore        4
      35: iload         4
      37: aload_1
      38: iload_2
      39: iload_3
      40: invokestatic  #62                 // Method constructName:(ILjava/lang/String;II)Lcom/fasterxml/jackson/core/sym/Name;
      43: astore        5
      45: aload_0
      46: iload         4
      48: aload         5
      50: invokespecial #63                 // Method _addSymbol:(ILcom/fasterxml/jackson/core/sym/Name;)V
      53: aload         5
      55: areturn

  public com.fasterxml.jackson.core.sym.Name addName(java.lang.String, int[], int);
    Code:
       0: aload_0
       1: getfield      #4                  // Field _intern:Z
       4: ifeq          15
       7: getstatic     #60                 // Field com/fasterxml/jackson/core/util/InternCache.instance:Lcom/fasterxml/jackson/core/util/InternCache;
      10: aload_1
      11: invokevirtual #61                 // Method com/fasterxml/jackson/core/util/InternCache.intern:(Ljava/lang/String;)Ljava/lang/String;
      14: astore_1
      15: iload_3
      16: iconst_4
      17: if_icmpge     75
      20: iload_3
      21: iconst_1
      22: if_icmpne     37
      25: aload_0
      26: aload_2
      27: iconst_0
      28: iaload
      29: invokevirtual #47                 // Method calcHash:(I)I
      32: istore        4
      34: goto          83
      37: iload_3
      38: iconst_2
      39: if_icmpne     57
      42: aload_0
      43: aload_2
      44: iconst_0
      45: iaload
      46: aload_2
      47: iconst_1
      48: iaload
      49: invokevirtual #50                 // Method calcHash:(II)I
      52: istore        4
      54: goto          83
      57: aload_0
      58: aload_2
      59: iconst_0
      60: iaload
      61: aload_2
      62: iconst_1
      63: iaload
      64: aload_2
      65: iconst_2
      66: iaload
      67: invokevirtual #52                 // Method calcHash:(III)I
      70: istore        4
      72: goto          83
      75: aload_0
      76: aload_2
      77: iload_3
      78: invokevirtual #57                 // Method calcHash:([II)I
      81: istore        4
      83: iload         4
      85: aload_1
      86: aload_2
      87: iload_3
      88: invokestatic  #64                 // Method constructName:(ILjava/lang/String;[II)Lcom/fasterxml/jackson/core/sym/Name;
      91: astore        5
      93: aload_0
      94: iload         4
      96: aload         5
      98: invokespecial #63                 // Method _addSymbol:(ILcom/fasterxml/jackson/core/sym/Name;)V
     101: aload         5
     103: areturn

  public int calcHash(int);
    Code:
       0: iload_1
       1: aload_0
       2: getfield      #3                  // Field _seed:I
       5: ixor
       6: istore_2
       7: iload_2
       8: iload_2
       9: bipush        15
      11: iushr
      12: iadd
      13: istore_2
      14: iload_2
      15: iload_2
      16: bipush        9
      18: iushr
      19: ixor
      20: istore_2
      21: iload_2
      22: ireturn

  public int calcHash(int, int);
    Code:
       0: iload_1
       1: istore_3
       2: iload_3
       3: iload_3
       4: bipush        15
       6: iushr
       7: ixor
       8: istore_3
       9: iload_3
      10: iload_2
      11: bipush        33
      13: imul
      14: iadd
      15: istore_3
      16: iload_3
      17: aload_0
      18: getfield      #3                  // Field _seed:I
      21: ixor
      22: istore_3
      23: iload_3
      24: iload_3
      25: bipush        7
      27: iushr
      28: iadd
      29: istore_3
      30: iload_3
      31: iload_3
      32: iconst_4
      33: iushr
      34: ixor
      35: istore_3
      36: iload_3
      37: ireturn

  public int calcHash(int, int, int);
    Code:
       0: iload_1
       1: aload_0
       2: getfield      #3                  // Field _seed:I
       5: ixor
       6: istore        4
       8: iload         4
      10: iload         4
      12: bipush        9
      14: iushr
      15: iadd
      16: istore        4
      18: iload         4
      20: bipush        33
      22: imul
      23: istore        4
      25: iload         4
      27: iload_2
      28: iadd
      29: istore        4
      31: iload         4
      33: ldc           #65                 // int 65599
      35: imul
      36: istore        4
      38: iload         4
      40: iload         4
      42: bipush        15
      44: iushr
      45: iadd
      46: istore        4
      48: iload         4
      50: iload_3
      51: ixor
      52: istore        4
      54: iload         4
      56: iload         4
      58: bipush        17
      60: iushr
      61: iadd
      62: istore        4
      64: iload         4
      66: iload         4
      68: bipush        15
      70: iushr
      71: iadd
      72: istore        4
      74: iload         4
      76: iload         4
      78: bipush        9
      80: ishl
      81: ixor
      82: istore        4
      84: iload         4
      86: ireturn

  public int calcHash(int[], int);
    Code:
       0: iload_2
       1: iconst_4
       2: if_icmpge     13
       5: new           #66                 // class java/lang/IllegalArgumentException
       8: dup
       9: invokespecial #67                 // Method java/lang/IllegalArgumentException."<init>":()V
      12: athrow
      13: aload_1
      14: iconst_0
      15: iaload
      16: aload_0
      17: getfield      #3                  // Field _seed:I
      20: ixor
      21: istore_3
      22: iload_3
      23: iload_3
      24: bipush        9
      26: iushr
      27: iadd
      28: istore_3
      29: iload_3
      30: bipush        33
      32: imul
      33: istore_3
      34: iload_3
      35: aload_1
      36: iconst_1
      37: iaload
      38: iadd
      39: istore_3
      40: iload_3
      41: ldc           #65                 // int 65599
      43: imul
      44: istore_3
      45: iload_3
      46: iload_3
      47: bipush        15
      49: iushr
      50: iadd
      51: istore_3
      52: iload_3
      53: aload_1
      54: iconst_2
      55: iaload
      56: ixor
      57: istore_3
      58: iload_3
      59: iload_3
      60: bipush        17
      62: iushr
      63: iadd
      64: istore_3
      65: iconst_3
      66: istore        4
      68: iload         4
      70: iload_2
      71: if_icmpge     103
      74: iload_3
      75: bipush        31
      77: imul
      78: aload_1
      79: iload         4
      81: iaload
      82: ixor
      83: istore_3
      84: iload_3
      85: iload_3
      86: iconst_3
      87: iushr
      88: iadd
      89: istore_3
      90: iload_3
      91: iload_3
      92: bipush        7
      94: ishl
      95: ixor
      96: istore_3
      97: iinc          4, 1
     100: goto          68
     103: iload_3
     104: iload_3
     105: bipush        15
     107: iushr
     108: iadd
     109: istore_3
     110: iload_3
     111: iload_3
     112: bipush        9
     114: ishl
     115: ixor
     116: istore_3
     117: iload_3
     118: ireturn

  protected static int[] calcQuads(byte[]);
    Code:
       0: aload_0
       1: arraylength
       2: istore_1
       3: iload_1
       4: iconst_3
       5: iadd
       6: iconst_4
       7: idiv
       8: newarray       int
      10: astore_2
      11: iconst_0
      12: istore_3
      13: iload_3
      14: iload_1
      15: if_icmpge     109
      18: aload_0
      19: iload_3
      20: baload
      21: sipush        255
      24: iand
      25: istore        4
      27: iinc          3, 1
      30: iload_3
      31: iload_1
      32: if_icmpge     96
      35: iload         4
      37: bipush        8
      39: ishl
      40: aload_0
      41: iload_3
      42: baload
      43: sipush        255
      46: iand
      47: ior
      48: istore        4
      50: iinc          3, 1
      53: iload_3
      54: iload_1
      55: if_icmpge     96
      58: iload         4
      60: bipush        8
      62: ishl
      63: aload_0
      64: iload_3
      65: baload
      66: sipush        255
      69: iand
      70: ior
      71: istore        4
      73: iinc          3, 1
      76: iload_3
      77: iload_1
      78: if_icmpge     96
      81: iload         4
      83: bipush        8
      85: ishl
      86: aload_0
      87: iload_3
      88: baload
      89: sipush        255
      92: iand
      93: ior
      94: istore        4
      96: aload_2
      97: iload_3
      98: iconst_2
      99: ishr
     100: iload         4
     102: iastore
     103: iinc          3, 1
     106: goto          13
     109: aload_2
     110: areturn

  private void _addSymbol(int, com.fasterxml.jackson.core.sym.Name);
    Code:
       0: aload_0
       1: getfield      #27                 // Field _hashShared:Z
       4: ifeq          11
       7: aload_0
       8: invokespecial #68                 // Method unshareMain:()V
      11: aload_0
      12: getfield      #26                 // Field _needRehash:Z
      15: ifeq          22
      18: aload_0
      19: invokespecial #69                 // Method rehash:()V
      22: aload_0
      23: dup
      24: getfield      #11                 // Field _count:I
      27: iconst_1
      28: iadd
      29: putfield      #11                 // Field _count:I
      32: iload_1
      33: aload_0
      34: getfield      #13                 // Field _hashMask:I
      37: iand
      38: istore_3
      39: aload_0
      40: getfield      #17                 // Field _mainNames:[Lcom/fasterxml/jackson/core/sym/Name;
      43: iload_3
      44: aaload
      45: ifnonnull     79
      48: aload_0
      49: getfield      #15                 // Field _hash:[I
      52: iload_3
      53: iload_1
      54: bipush        8
      56: ishl
      57: iastore
      58: aload_0
      59: getfield      #28                 // Field _namesShared:Z
      62: ifeq          69
      65: aload_0
      66: invokespecial #70                 // Method unshareNames:()V
      69: aload_0
      70: getfield      #17                 // Field _mainNames:[Lcom/fasterxml/jackson/core/sym/Name;
      73: iload_3
      74: aload_2
      75: aastore
      76: goto          261
      79: aload_0
      80: getfield      #29                 // Field _collListShared:Z
      83: ifeq          90
      86: aload_0
      87: invokespecial #71                 // Method unshareCollision:()V
      90: aload_0
      91: dup
      92: getfield      #21                 // Field _collCount:I
      95: iconst_1
      96: iadd
      97: putfield      #21                 // Field _collCount:I
     100: aload_0
     101: getfield      #15                 // Field _hash:[I
     104: iload_3
     105: iaload
     106: istore        4
     108: iload         4
     110: sipush        255
     113: iand
     114: istore        5
     116: iload         5
     118: ifne          190
     121: aload_0
     122: getfield      #23                 // Field _collEnd:I
     125: sipush        254
     128: if_icmpgt     164
     131: aload_0
     132: getfield      #23                 // Field _collEnd:I
     135: istore        5
     137: aload_0
     138: dup
     139: getfield      #23                 // Field _collEnd:I
     142: iconst_1
     143: iadd
     144: putfield      #23                 // Field _collEnd:I
     147: iload         5
     149: aload_0
     150: getfield      #19                 // Field _collList:[Lcom/fasterxml/jackson/core/sym/BytesToNameCanonicalizer$Bucket;
     153: arraylength
     154: if_icmplt     170
     157: aload_0
     158: invokespecial #72                 // Method expandCollision:()V
     161: goto          170
     164: aload_0
     165: invokespecial #73                 // Method findBestBucket:()I
     168: istore        5
     170: aload_0
     171: getfield      #15                 // Field _hash:[I
     174: iload_3
     175: iload         4
     177: sipush        -256
     180: iand
     181: iload         5
     183: iconst_1
     184: iadd
     185: ior
     186: iastore
     187: goto          193
     190: iinc          5, -1
     193: new           #74                 // class com/fasterxml/jackson/core/sym/BytesToNameCanonicalizer$Bucket
     196: dup
     197: aload_2
     198: aload_0
     199: getfield      #19                 // Field _collList:[Lcom/fasterxml/jackson/core/sym/BytesToNameCanonicalizer$Bucket;
     202: iload         5
     204: aaload
     205: invokespecial #75                 // Method com/fasterxml/jackson/core/sym/BytesToNameCanonicalizer$Bucket."<init>":(Lcom/fasterxml/jackson/core/sym/Name;Lcom/fasterxml/jackson/core/sym/BytesToNameCanonicalizer$Bucket;)V
     208: astore        6
     210: aload         6
     212: getfield      #76                 // Field com/fasterxml/jackson/core/sym/BytesToNameCanonicalizer$Bucket.length:I
     215: istore        7
     217: iload         7
     219: sipush        200
     222: if_icmple     236
     225: aload_0
     226: iload         5
     228: aload         6
     230: invokespecial #77                 // Method _handleSpillOverflow:(ILcom/fasterxml/jackson/core/sym/BytesToNameCanonicalizer$Bucket;)V
     233: goto          261
     236: aload_0
     237: getfield      #19                 // Field _collList:[Lcom/fasterxml/jackson/core/sym/BytesToNameCanonicalizer$Bucket;
     240: iload         5
     242: aload         6
     244: aastore
     245: aload_0
     246: aload         6
     248: getfield      #76                 // Field com/fasterxml/jackson/core/sym/BytesToNameCanonicalizer$Bucket.length:I
     251: aload_0
     252: getfield      #25                 // Field _longestCollisionList:I
     255: invokestatic  #78                 // Method java/lang/Math.max:(II)I
     258: putfield      #25                 // Field _longestCollisionList:I
     261: aload_0
     262: getfield      #15                 // Field _hash:[I
     265: arraylength
     266: istore        4
     268: aload_0
     269: getfield      #11                 // Field _count:I
     272: iload         4
     274: iconst_1
     275: ishr
     276: if_icmple     319
     279: iload         4
     281: iconst_2
     282: ishr
     283: istore        5
     285: aload_0
     286: getfield      #11                 // Field _count:I
     289: iload         4
     291: iload         5
     293: isub
     294: if_icmple     305
     297: aload_0
     298: iconst_1
     299: putfield      #26                 // Field _needRehash:Z
     302: goto          319
     305: aload_0
     306: getfield      #21                 // Field _collCount:I
     309: iload         5
     311: if_icmplt     319
     314: aload_0
     315: iconst_1
     316: putfield      #26                 // Field _needRehash:Z
     319: return

  private void _handleSpillOverflow(int, com.fasterxml.jackson.core.sym.BytesToNameCanonicalizer$Bucket);
    Code:
       0: aload_0
       1: getfield      #79                 // Field _overflows:Ljava/util/BitSet;
       4: ifnonnull     29
       7: aload_0
       8: new           #80                 // class java/util/BitSet
      11: dup
      12: invokespecial #81                 // Method java/util/BitSet."<init>":()V
      15: putfield      #79                 // Field _overflows:Ljava/util/BitSet;
      18: aload_0
      19: getfield      #79                 // Field _overflows:Ljava/util/BitSet;
      22: iload_1
      23: invokevirtual #82                 // Method java/util/BitSet.set:(I)V
      26: goto          70
      29: aload_0
      30: getfield      #79                 // Field _overflows:Ljava/util/BitSet;
      33: iload_1
      34: invokevirtual #83                 // Method java/util/BitSet.get:(I)Z
      37: ifeq          62
      40: aload_0
      41: getfield      #5                  // Field _failOnDoS:Z
      44: ifeq          54
      47: aload_0
      48: sipush        200
      51: invokevirtual #84                 // Method reportTooManyCollisions:(I)V
      54: aload_0
      55: iconst_0
      56: putfield      #4                  // Field _intern:Z
      59: goto          70
      62: aload_0
      63: getfield      #79                 // Field _overflows:Ljava/util/BitSet;
      66: iload_1
      67: invokevirtual #82                 // Method java/util/BitSet.set:(I)V
      70: aload_0
      71: getfield      #19                 // Field _collList:[Lcom/fasterxml/jackson/core/sym/BytesToNameCanonicalizer$Bucket;
      74: iload_1
      75: aconst_null
      76: aastore
      77: aload_0
      78: dup
      79: getfield      #11                 // Field _count:I
      82: aload_2
      83: getfield      #76                 // Field com/fasterxml/jackson/core/sym/BytesToNameCanonicalizer$Bucket.length:I
      86: isub
      87: putfield      #11                 // Field _count:I
      90: aload_0
      91: iconst_m1
      92: putfield      #25                 // Field _longestCollisionList:I
      95: return

  private void rehash();
    Code:
       0: aload_0
       1: iconst_0
       2: putfield      #26                 // Field _needRehash:Z
       5: aload_0
       6: iconst_0
       7: putfield      #28                 // Field _namesShared:Z
      10: aload_0
      11: getfield      #15                 // Field _hash:[I
      14: astore_1
      15: aload_1
      16: arraylength
      17: istore_2
      18: iload_2
      19: iload_2
      20: iadd
      21: istore_3
      22: iload_3
      23: ldc           #85                 // int 65536
      25: if_icmple     33
      28: aload_0
      29: invokespecial #86                 // Method nukeSymbols:()V
      32: return
      33: aload_0
      34: iload_3
      35: newarray       int
      37: putfield      #15                 // Field _hash:[I
      40: aload_0
      41: iload_3
      42: iconst_1
      43: isub
      44: putfield      #13                 // Field _hashMask:I
      47: aload_0
      48: getfield      #17                 // Field _mainNames:[Lcom/fasterxml/jackson/core/sym/Name;
      51: astore        4
      53: aload_0
      54: iload_3
      55: anewarray     #31                 // class com/fasterxml/jackson/core/sym/Name
      58: putfield      #17                 // Field _mainNames:[Lcom/fasterxml/jackson/core/sym/Name;
      61: iconst_0
      62: istore        5
      64: iconst_0
      65: istore        6
      67: iload         6
      69: iload_2
      70: if_icmpge     131
      73: aload         4
      75: iload         6
      77: aaload
      78: astore        7
      80: aload         7
      82: ifnull        125
      85: iinc          5, 1
      88: aload         7
      90: invokevirtual #87                 // Method com/fasterxml/jackson/core/sym/Name.hashCode:()I
      93: istore        8
      95: iload         8
      97: aload_0
      98: getfield      #13                 // Field _hashMask:I
     101: iand
     102: istore        9
     104: aload_0
     105: getfield      #17                 // Field _mainNames:[Lcom/fasterxml/jackson/core/sym/Name;
     108: iload         9
     110: aload         7
     112: aastore
     113: aload_0
     114: getfield      #15                 // Field _hash:[I
     117: iload         9
     119: iload         8
     121: bipush        8
     123: ishl
     124: iastore
     125: iinc          6, 1
     128: goto          67
     131: aload_0
     132: getfield      #23                 // Field _collEnd:I
     135: istore        6
     137: iload         6
     139: ifne          148
     142: aload_0
     143: iconst_0
     144: putfield      #25                 // Field _longestCollisionList:I
     147: return
     148: aload_0
     149: iconst_0
     150: putfield      #21                 // Field _collCount:I
     153: aload_0
     154: iconst_0
     155: putfield      #23                 // Field _collEnd:I
     158: aload_0
     159: iconst_0
     160: putfield      #29                 // Field _collListShared:Z
     163: iconst_0
     164: istore        7
     166: aload_0
     167: getfield      #19                 // Field _collList:[Lcom/fasterxml/jackson/core/sym/BytesToNameCanonicalizer$Bucket;
     170: astore        8
     172: aload_0
     173: aload         8
     175: arraylength
     176: anewarray     #74                 // class com/fasterxml/jackson/core/sym/BytesToNameCanonicalizer$Bucket
     179: putfield      #19                 // Field _collList:[Lcom/fasterxml/jackson/core/sym/BytesToNameCanonicalizer$Bucket;
     182: iconst_0
     183: istore        9
     185: iload         9
     187: iload         6
     189: if_icmpge     424
     192: aload         8
     194: iload         9
     196: aaload
     197: astore        10
     199: aload         10
     201: ifnull        418
     204: iinc          5, 1
     207: aload         10
     209: getfield      #88                 // Field com/fasterxml/jackson/core/sym/BytesToNameCanonicalizer$Bucket.name:Lcom/fasterxml/jackson/core/sym/Name;
     212: astore        11
     214: aload         11
     216: invokevirtual #87                 // Method com/fasterxml/jackson/core/sym/Name.hashCode:()I
     219: istore        12
     221: iload         12
     223: aload_0
     224: getfield      #13                 // Field _hashMask:I
     227: iand
     228: istore        13
     230: aload_0
     231: getfield      #15                 // Field _hash:[I
     234: iload         13
     236: iaload
     237: istore        14
     239: aload_0
     240: getfield      #17                 // Field _mainNames:[Lcom/fasterxml/jackson/core/sym/Name;
     243: iload         13
     245: aaload
     246: ifnonnull     273
     249: aload_0
     250: getfield      #15                 // Field _hash:[I
     253: iload         13
     255: iload         12
     257: bipush        8
     259: ishl
     260: iastore
     261: aload_0
     262: getfield      #17                 // Field _mainNames:[Lcom/fasterxml/jackson/core/sym/Name;
     265: iload         13
     267: aload         11
     269: aastore
     270: goto          408
     273: aload_0
     274: dup
     275: getfield      #21                 // Field _collCount:I
     278: iconst_1
     279: iadd
     280: putfield      #21                 // Field _collCount:I
     283: iload         14
     285: sipush        255
     288: iand
     289: istore        15
     291: iload         15
     293: ifne          366
     296: aload_0
     297: getfield      #23                 // Field _collEnd:I
     300: sipush        254
     303: if_icmpgt     339
     306: aload_0
     307: getfield      #23                 // Field _collEnd:I
     310: istore        15
     312: aload_0
     313: dup
     314: getfield      #23                 // Field _collEnd:I
     317: iconst_1
     318: iadd
     319: putfield      #23                 // Field _collEnd:I
     322: iload         15
     324: aload_0
     325: getfield      #19                 // Field _collList:[Lcom/fasterxml/jackson/core/sym/BytesToNameCanonicalizer$Bucket;
     328: arraylength
     329: if_icmplt     345
     332: aload_0
     333: invokespecial #72                 // Method expandCollision:()V
     336: goto          345
     339: aload_0
     340: invokespecial #73                 // Method findBestBucket:()I
     343: istore        15
     345: aload_0
     346: getfield      #15                 // Field _hash:[I
     349: iload         13
     351: iload         14
     353: sipush        -256
     356: iand
     357: iload         15
     359: iconst_1
     360: iadd
     361: ior
     362: iastore
     363: goto          369
     366: iinc          15, -1
     369: new           #74                 // class com/fasterxml/jackson/core/sym/BytesToNameCanonicalizer$Bucket
     372: dup
     373: aload         11
     375: aload_0
     376: getfield      #19                 // Field _collList:[Lcom/fasterxml/jackson/core/sym/BytesToNameCanonicalizer$Bucket;
     379: iload         15
     381: aaload
     382: invokespecial #75                 // Method com/fasterxml/jackson/core/sym/BytesToNameCanonicalizer$Bucket."<init>":(Lcom/fasterxml/jackson/core/sym/Name;Lcom/fasterxml/jackson/core/sym/BytesToNameCanonicalizer$Bucket;)V
     385: astore        16
     387: aload_0
     388: getfield      #19                 // Field _collList:[Lcom/fasterxml/jackson/core/sym/BytesToNameCanonicalizer$Bucket;
     391: iload         15
     393: aload         16
     395: aastore
     396: iload         7
     398: aload         16
     400: getfield      #76                 // Field com/fasterxml/jackson/core/sym/BytesToNameCanonicalizer$Bucket.length:I
     403: invokestatic  #78                 // Method java/lang/Math.max:(II)I
     406: istore        7
     408: aload         10
     410: getfield      #89                 // Field com/fasterxml/jackson/core/sym/BytesToNameCanonicalizer$Bucket.next:Lcom/fasterxml/jackson/core/sym/BytesToNameCanonicalizer$Bucket;
     413: astore        10
     415: goto          199
     418: iinc          9, 1
     421: goto          185
     424: aload_0
     425: iload         7
     427: putfield      #25                 // Field _longestCollisionList:I
     430: iload         5
     432: aload_0
     433: getfield      #11                 // Field _count:I
     436: if_icmpeq     479
     439: new           #90                 // class java/lang/RuntimeException
     442: dup
     443: new           #91                 // class java/lang/StringBuilder
     446: dup
     447: invokespecial #92                 // Method java/lang/StringBuilder."<init>":()V
     450: ldc           #93                 // String Internal error: count after rehash
     452: invokevirtual #94                 // Method java/lang/StringBuilder.append:(Ljava/lang/String;)Ljava/lang/StringBuilder;
     455: iload         5
     457: invokevirtual #95                 // Method java/lang/StringBuilder.append:(I)Ljava/lang/StringBuilder;
     460: ldc           #96                 // String ; should be
     462: invokevirtual #94                 // Method java/lang/StringBuilder.append:(Ljava/lang/String;)Ljava/lang/StringBuilder;
     465: aload_0
     466: getfield      #11                 // Field _count:I
     469: invokevirtual #95                 // Method java/lang/StringBuilder.append:(I)Ljava/lang/StringBuilder;
     472: invokevirtual #97                 // Method java/lang/StringBuilder.toString:()Ljava/lang/String;
     475: invokespecial #98                 // Method java/lang/RuntimeException."<init>":(Ljava/lang/String;)V
     478: athrow
     479: return

  private void nukeSymbols();
    Code:
       0: aload_0
       1: iconst_0
       2: putfield      #11                 // Field _count:I
       5: aload_0
       6: iconst_0
       7: putfield      #25                 // Field _longestCollisionList:I
      10: aload_0
      11: getfield      #15                 // Field _hash:[I
      14: iconst_0
      15: invokestatic  #99                 // Method java/util/Arrays.fill:([II)V
      18: aload_0
      19: getfield      #17                 // Field _mainNames:[Lcom/fasterxml/jackson/core/sym/Name;
      22: aconst_null
      23: invokestatic  #100                // Method java/util/Arrays.fill:([Ljava/lang/Object;Ljava/lang/Object;)V
      26: aload_0
      27: getfield      #19                 // Field _collList:[Lcom/fasterxml/jackson/core/sym/BytesToNameCanonicalizer$Bucket;
      30: aconst_null
      31: invokestatic  #100                // Method java/util/Arrays.fill:([Ljava/lang/Object;Ljava/lang/Object;)V
      34: aload_0
      35: iconst_0
      36: putfield      #21                 // Field _collCount:I
      39: aload_0
      40: iconst_0
      41: putfield      #23                 // Field _collEnd:I
      44: return

  private int findBestBucket();
    Code:
       0: aload_0
       1: getfield      #19                 // Field _collList:[Lcom/fasterxml/jackson/core/sym/BytesToNameCanonicalizer$Bucket;
       4: astore_1
       5: ldc           #101                // int 2147483647
       7: istore_2
       8: iconst_m1
       9: istore_3
      10: iconst_0
      11: istore        4
      13: aload_0
      14: getfield      #23                 // Field _collEnd:I
      17: istore        5
      19: iload         4
      21: iload         5
      23: if_icmpge     74
      26: aload_1
      27: iload         4
      29: aaload
      30: astore        6
      32: aload         6
      34: ifnonnull     40
      37: iload         4
      39: ireturn
      40: aload         6
      42: getfield      #76                 // Field com/fasterxml/jackson/core/sym/BytesToNameCanonicalizer$Bucket.length:I
      45: istore        7
      47: iload         7
      49: iload_2
      50: if_icmpge     68
      53: iload         7
      55: iconst_1
      56: if_icmpne     62
      59: iload         4
      61: ireturn
      62: iload         7
      64: istore_2
      65: iload         4
      67: istore_3
      68: iinc          4, 1
      71: goto          19
      74: iload_3
      75: ireturn

  private void unshareMain();
    Code:
       0: aload_0
       1: getfield      #15                 // Field _hash:[I
       4: astore_1
       5: aload_0
       6: aload_1
       7: aload_1
       8: arraylength
       9: invokestatic  #102                // Method java/util/Arrays.copyOf:([II)[I
      12: putfield      #15                 // Field _hash:[I
      15: aload_0
      16: iconst_0
      17: putfield      #27                 // Field _hashShared:Z
      20: return

  private void unshareCollision();
    Code:
       0: aload_0
       1: getfield      #19                 // Field _collList:[Lcom/fasterxml/jackson/core/sym/BytesToNameCanonicalizer$Bucket;
       4: astore_1
       5: aload_1
       6: ifnonnull     21
       9: aload_0
      10: bipush        32
      12: anewarray     #74                 // class com/fasterxml/jackson/core/sym/BytesToNameCanonicalizer$Bucket
      15: putfield      #19                 // Field _collList:[Lcom/fasterxml/jackson/core/sym/BytesToNameCanonicalizer$Bucket;
      18: goto          34
      21: aload_0
      22: aload_1
      23: aload_1
      24: arraylength
      25: invokestatic  #103                // Method java/util/Arrays.copyOf:([Ljava/lang/Object;I)[Ljava/lang/Object;
      28: checkcast     #104                // class "[Lcom/fasterxml/jackson/core/sym/BytesToNameCanonicalizer$Bucket;"
      31: putfield      #19                 // Field _collList:[Lcom/fasterxml/jackson/core/sym/BytesToNameCanonicalizer$Bucket;
      34: aload_0
      35: iconst_0
      36: putfield      #29                 // Field _collListShared:Z
      39: return

  private void unshareNames();
    Code:
       0: aload_0
       1: getfield      #17                 // Field _mainNames:[Lcom/fasterxml/jackson/core/sym/Name;
       4: astore_1
       5: aload_0
       6: aload_1
       7: aload_1
       8: arraylength
       9: invokestatic  #103                // Method java/util/Arrays.copyOf:([Ljava/lang/Object;I)[Ljava/lang/Object;
      12: checkcast     #105                // class "[Lcom/fasterxml/jackson/core/sym/Name;"
      15: putfield      #17                 // Field _mainNames:[Lcom/fasterxml/jackson/core/sym/Name;
      18: aload_0
      19: iconst_0
      20: putfield      #28                 // Field _namesShared:Z
      23: return

  private void expandCollision();
    Code:
       0: aload_0
       1: getfield      #19                 // Field _collList:[Lcom/fasterxml/jackson/core/sym/BytesToNameCanonicalizer$Bucket;
       4: astore_1
       5: aload_0
       6: aload_1
       7: aload_1
       8: arraylength
       9: iconst_2
      10: imul
      11: invokestatic  #103                // Method java/util/Arrays.copyOf:([Ljava/lang/Object;I)[Ljava/lang/Object;
      14: checkcast     #104                // class "[Lcom/fasterxml/jackson/core/sym/BytesToNameCanonicalizer$Bucket;"
      17: putfield      #19                 // Field _collList:[Lcom/fasterxml/jackson/core/sym/BytesToNameCanonicalizer$Bucket;
      20: return

  private static com.fasterxml.jackson.core.sym.Name constructName(int, java.lang.String, int, int);
    Code:
       0: iload_3
       1: ifne          15
       4: new           #106                // class com/fasterxml/jackson/core/sym/Name1
       7: dup
       8: aload_1
       9: iload_0
      10: iload_2
      11: invokespecial #107                // Method com/fasterxml/jackson/core/sym/Name1."<init>":(Ljava/lang/String;II)V
      14: areturn
      15: new           #108                // class com/fasterxml/jackson/core/sym/Name2
      18: dup
      19: aload_1
      20: iload_0
      21: iload_2
      22: iload_3
      23: invokespecial #109                // Method com/fasterxml/jackson/core/sym/Name2."<init>":(Ljava/lang/String;III)V
      26: areturn

  private static com.fasterxml.jackson.core.sym.Name constructName(int, java.lang.String, int[], int);
    Code:
       0: iload_3
       1: iconst_4
       2: if_icmpge     80
       5: iload_3
       6: tableswitch   { // 1 to 3
                     1: 32
                     2: 45
                     3: 61
               default: 61
          }
      32: new           #106                // class com/fasterxml/jackson/core/sym/Name1
      35: dup
      36: aload_1
      37: iload_0
      38: aload_2
      39: iconst_0
      40: iaload
      41: invokespecial #107                // Method com/fasterxml/jackson/core/sym/Name1."<init>":(Ljava/lang/String;II)V
      44: areturn
      45: new           #108                // class com/fasterxml/jackson/core/sym/Name2
      48: dup
      49: aload_1
      50: iload_0
      51: aload_2
      52: iconst_0
      53: iaload
      54: aload_2
      55: iconst_1
      56: iaload
      57: invokespecial #109                // Method com/fasterxml/jackson/core/sym/Name2."<init>":(Ljava/lang/String;III)V
      60: areturn
      61: new           #110                // class com/fasterxml/jackson/core/sym/Name3
      64: dup
      65: aload_1
      66: iload_0
      67: aload_2
      68: iconst_0
      69: iaload
      70: aload_2
      71: iconst_1
      72: iaload
      73: aload_2
      74: iconst_2
      75: iaload
      76: invokespecial #111                // Method com/fasterxml/jackson/core/sym/Name3."<init>":(Ljava/lang/String;IIII)V
      79: areturn
      80: aload_1
      81: iload_0
      82: aload_2
      83: iload_3
      84: invokestatic  #112                // Method com/fasterxml/jackson/core/sym/NameN.construct:(Ljava/lang/String;I[II)Lcom/fasterxml/jackson/core/sym/NameN;
      87: areturn

  protected void reportTooManyCollisions(int);
    Code:
       0: new           #113                // class java/lang/IllegalStateException
       3: dup
       4: new           #91                 // class java/lang/StringBuilder
       7: dup
       8: invokespecial #92                 // Method java/lang/StringBuilder."<init>":()V
      11: ldc           #114                // String Longest collision chain in symbol table (of size
      13: invokevirtual #94                 // Method java/lang/StringBuilder.append:(Ljava/lang/String;)Ljava/lang/StringBuilder;
      16: aload_0
      17: getfield      #11                 // Field _count:I
      20: invokevirtual #95                 // Method java/lang/StringBuilder.append:(I)Ljava/lang/StringBuilder;
      23: ldc           #115                // String ) now exceeds maximum,
      25: invokevirtual #94                 // Method java/lang/StringBuilder.append:(Ljava/lang/String;)Ljava/lang/StringBuilder;
      28: iload_1
      29: invokevirtual #95                 // Method java/lang/StringBuilder.append:(I)Ljava/lang/StringBuilder;
      32: ldc           #116                // String  -- suspect a DoS attack based on hash collisions
      34: invokevirtual #94                 // Method java/lang/StringBuilder.append:(Ljava/lang/String;)Ljava/lang/StringBuilder;
      37: invokevirtual #97                 // Method java/lang/StringBuilder.toString:()Ljava/lang/String;
      40: invokespecial #117                // Method java/lang/IllegalStateException."<init>":(Ljava/lang/String;)V
      43: athrow
}
