Compiled from "AddressType.java"
public class net.java.slee.resource.diameter.rf.events.avp.AddressType implements net.java.slee.resource.diameter.base.events.avp.Enumerated,java.io.Serializable {
  private static final long serialVersionUID;

  public static final int _ALPHANUMERIC_SHORTCODE;

  public static final int _E_MAIL_ADDRESS;

  public static final int _IPV4_ADDRESS;

  public static final int _IPV6_ADDRESS;

  public static final int _MSISDN;

  public static final int _NUMERIC_SHORTCODE;

  public static final int _OTHER;

  public static final net.java.slee.resource.diameter.rf.events.avp.AddressType ALPHANUMERIC_SHORTCODE;

  public static final net.java.slee.resource.diameter.rf.events.avp.AddressType E_MAIL_ADDRESS;

  public static final net.java.slee.resource.diameter.rf.events.avp.AddressType IPV4_ADDRESS;

  public static final net.java.slee.resource.diameter.rf.events.avp.AddressType IPV6_ADDRESS;

  public static final net.java.slee.resource.diameter.rf.events.avp.AddressType MSISDN;

  public static final net.java.slee.resource.diameter.rf.events.avp.AddressType NUMERIC_SHORTCODE;

  public static final net.java.slee.resource.diameter.rf.events.avp.AddressType OTHER;

  private int value;

  private net.java.slee.resource.diameter.rf.events.avp.AddressType(int);
    Code:
       0: aload_0
       1: invokespecial #1                  // Method java/lang/Object."<init>":()V
       4: aload_0
       5: iconst_0
       6: putfield      #2                  // Field value:I
       9: aload_0
      10: iload_1
      11: putfield      #2                  // Field value:I
      14: return

  public static net.java.slee.resource.diameter.rf.events.avp.AddressType fromInt(int);
    Code:
       0: iload_0
       1: tableswitch   { // 0 to 6
                     0: 48
                     1: 60
                     2: 52
                     3: 56
                     4: 64
                     5: 44
                     6: 68
               default: 72
          }
      44: getstatic     #3                  // Field ALPHANUMERIC_SHORTCODE:Lnet/java/slee/resource/diameter/rf/events/avp/AddressType;
      47: areturn
      48: getstatic     #4                  // Field E_MAIL_ADDRESS:Lnet/java/slee/resource/diameter/rf/events/avp/AddressType;
      51: areturn
      52: getstatic     #5                  // Field IPV4_ADDRESS:Lnet/java/slee/resource/diameter/rf/events/avp/AddressType;
      55: areturn
      56: getstatic     #6                  // Field IPV6_ADDRESS:Lnet/java/slee/resource/diameter/rf/events/avp/AddressType;
      59: areturn
      60: getstatic     #7                  // Field MSISDN:Lnet/java/slee/resource/diameter/rf/events/avp/AddressType;
      63: areturn
      64: getstatic     #8                  // Field NUMERIC_SHORTCODE:Lnet/java/slee/resource/diameter/rf/events/avp/AddressType;
      67: areturn
      68: getstatic     #9                  // Field OTHER:Lnet/java/slee/resource/diameter/rf/events/avp/AddressType;
      71: areturn
      72: new           #10                 // class java/lang/IllegalArgumentException
      75: dup
      76: new           #11                 // class java/lang/StringBuilder
      79: dup
      80: invokespecial #12                 // Method java/lang/StringBuilder."<init>":()V
      83: ldc           #13                 // String Invalid DisconnectCause value:
      85: invokevirtual #14                 // Method java/lang/StringBuilder.append:(Ljava/lang/String;)Ljava/lang/StringBuilder;
      88: iload_0
      89: invokevirtual #15                 // Method java/lang/StringBuilder.append:(I)Ljava/lang/StringBuilder;
      92: invokevirtual #16                 // Method java/lang/StringBuilder.toString:()Ljava/lang/String;
      95: invokespecial #17                 // Method java/lang/IllegalArgumentException."<init>":(Ljava/lang/String;)V
      98: athrow

  public int getValue();
    Code:
       0: aload_0
       1: getfield      #2                  // Field value:I
       4: ireturn

  public java.lang.String toString();
    Code:
       0: aload_0
       1: getfield      #2                  // Field value:I
       4: tableswitch   { // 0 to 6
                     0: 51
                     1: 60
                     2: 54
                     3: 57
                     4: 63
                     5: 48
                     6: 66
               default: 69
          }
      48: ldc           #18                 // String ALPHANUMERIC_SHORTCODE
      50: areturn
      51: ldc           #19                 // String E_MAIL_ADDRESS
      53: areturn
      54: ldc           #20                 // String IPV4_ADDRESS
      56: areturn
      57: ldc           #21                 // String IPV6_ADDRESS
      59: areturn
      60: ldc           #22                 // String MSISDN
      62: areturn
      63: ldc           #23                 // String NUMERIC_SHORTCODE
      65: areturn
      66: ldc           #24                 // String OTHER
      68: areturn
      69: ldc           #25                 // String <Invalid Value>
      71: areturn

  private java.lang.Object readResolve() throws java.io.StreamCorruptedException;
    Code:
       0: aload_0
       1: getfield      #2                  // Field value:I
       4: invokestatic  #26                 // Method fromInt:(I)Lnet/java/slee/resource/diameter/rf/events/avp/AddressType;
       7: areturn
       8: astore_1
       9: new           #27                 // class java/io/StreamCorruptedException
      12: dup
      13: new           #11                 // class java/lang/StringBuilder
      16: dup
      17: invokespecial #12                 // Method java/lang/StringBuilder."<init>":()V
      20: ldc           #28                 // String Invalid internal state found:
      22: invokevirtual #14                 // Method java/lang/StringBuilder.append:(Ljava/lang/String;)Ljava/lang/StringBuilder;
      25: aload_0
      26: getfield      #2                  // Field value:I
      29: invokevirtual #15                 // Method java/lang/StringBuilder.append:(I)Ljava/lang/StringBuilder;
      32: invokevirtual #16                 // Method java/lang/StringBuilder.toString:()Ljava/lang/String;
      35: invokespecial #29                 // Method java/io/StreamCorruptedException."<init>":(Ljava/lang/String;)V
      38: athrow
    Exception table:
       from    to  target type
           0     7     8   Class java/lang/IllegalArgumentException

  static {};
    Code:
       0: new           #30                 // class net/java/slee/resource/diameter/rf/events/avp/AddressType
       3: dup
       4: iconst_5
       5: invokespecial #31                 // Method "<init>":(I)V
       8: putstatic     #3                  // Field ALPHANUMERIC_SHORTCODE:Lnet/java/slee/resource/diameter/rf/events/avp/AddressType;
      11: new           #30                 // class net/java/slee/resource/diameter/rf/events/avp/AddressType
      14: dup
      15: iconst_0
      16: invokespecial #31                 // Method "<init>":(I)V
      19: putstatic     #4                  // Field E_MAIL_ADDRESS:Lnet/java/slee/resource/diameter/rf/events/avp/AddressType;
      22: new           #30                 // class net/java/slee/resource/diameter/rf/events/avp/AddressType
      25: dup
      26: iconst_2
      27: invokespecial #31                 // Method "<init>":(I)V
      30: putstatic     #5                  // Field IPV4_ADDRESS:Lnet/java/slee/resource/diameter/rf/events/avp/AddressType;
      33: new           #30                 // class net/java/slee/resource/diameter/rf/events/avp/AddressType
      36: dup
      37: iconst_3
      38: invokespecial #31                 // Method "<init>":(I)V
      41: putstatic     #6                  // Field IPV6_ADDRESS:Lnet/java/slee/resource/diameter/rf/events/avp/AddressType;
      44: new           #30                 // class net/java/slee/resource/diameter/rf/events/avp/AddressType
      47: dup
      48: iconst_1
      49: invokespecial #31                 // Method "<init>":(I)V
      52: putstatic     #7                  // Field MSISDN:Lnet/java/slee/resource/diameter/rf/events/avp/AddressType;
      55: new           #30                 // class net/java/slee/resource/diameter/rf/events/avp/AddressType
      58: dup
      59: iconst_4
      60: invokespecial #31                 // Method "<init>":(I)V
      63: putstatic     #8                  // Field NUMERIC_SHORTCODE:Lnet/java/slee/resource/diameter/rf/events/avp/AddressType;
      66: new           #30                 // class net/java/slee/resource/diameter/rf/events/avp/AddressType
      69: dup
      70: bipush        6
      72: invokespecial #31                 // Method "<init>":(I)V
      75: putstatic     #9                  // Field OTHER:Lnet/java/slee/resource/diameter/rf/events/avp/AddressType;
      78: return
}
