Compiled from "AllAxiomsStrategy.java"
public class org.protege.editor.owl.model.selection.axioms.AllAxiomsStrategy extends org.protege.editor.owl.model.selection.axioms.AbstractAxiomSelectionStrategy {
  public org.protege.editor.owl.model.selection.axioms.AllAxiomsStrategy();
    Code:
       0: aload_0
       1: invokespecial #1                  // Method org/protege/editor/owl/model/selection/axioms/AbstractAxiomSelectionStrategy."<init>":()V
       4: return

  public java.lang.String getName();
    Code:
       0: ldc           #2                  // String All axioms in the specified ontologies
       2: areturn

  public java.util.Set<org.semanticweb.owlapi.model.OWLAxiom> getAxioms(java.util.Set<org.semanticweb.owlapi.model.OWLOntology>);
    Code:
       0: new           #3                  // class java/util/HashSet
       3: dup
       4: invokespecial #4                  // Method java/util/HashSet."<init>":()V
       7: astore_2
       8: aload_1
       9: invokeinterface #5,  1            // InterfaceMethod java/util/Set.iterator:()Ljava/util/Iterator;
      14: astore_3
      15: aload_3
      16: invokeinterface #6,  1            // InterfaceMethod java/util/Iterator.hasNext:()Z
      21: ifeq          52
      24: aload_3
      25: invokeinterface #7,  1            // InterfaceMethod java/util/Iterator.next:()Ljava/lang/Object;
      30: checkcast     #8                  // class org/semanticweb/owlapi/model/OWLOntology
      33: astore        4
      35: aload_2
      36: aload         4
      38: invokeinterface #9,  1            // InterfaceMethod org/semanticweb/owlapi/model/OWLOntology.getAxioms:()Ljava/util/Set;
      43: invokeinterface #10,  2           // InterfaceMethod java/util/Set.addAll:(Ljava/util/Collection;)Z
      48: pop
      49: goto          15
      52: aload_2
      53: areturn
}
