Compiled from "ClassUtils.java"
public class org.apache.avro.util.ClassUtils {
  private org.apache.avro.util.ClassUtils();
    Code:
       0: aload_0
       1: invokespecial #1                  // Method java/lang/Object."<init>":()V
       4: return

  public static java.lang.Class<?> forName(java.lang.String) throws java.lang.ClassNotFoundException;
    Code:
       0: ldc_w         #2                  // class org/apache/avro/util/ClassUtils
       3: aload_0
       4: invokestatic  #3                  // Method forName:(Ljava/lang/Class;Ljava/lang/String;)Ljava/lang/Class;
       7: areturn

  public static java.lang.Class<?> forName(java.lang.Class<?>, java.lang.String) throws java.lang.ClassNotFoundException;
    Code:
       0: aconst_null
       1: astore_2
       2: aload_0
       3: invokevirtual #4                  // Method java/lang/Class.getClassLoader:()Ljava/lang/ClassLoader;
       6: ifnull        18
       9: aload_1
      10: aload_0
      11: invokevirtual #4                  // Method java/lang/Class.getClassLoader:()Ljava/lang/ClassLoader;
      14: invokestatic  #5                  // Method forName:(Ljava/lang/String;Ljava/lang/ClassLoader;)Ljava/lang/Class;
      17: astore_2
      18: aload_2
      19: ifnonnull     42
      22: invokestatic  #6                  // Method java/lang/Thread.currentThread:()Ljava/lang/Thread;
      25: invokevirtual #7                  // Method java/lang/Thread.getContextClassLoader:()Ljava/lang/ClassLoader;
      28: ifnull        42
      31: aload_1
      32: invokestatic  #6                  // Method java/lang/Thread.currentThread:()Ljava/lang/Thread;
      35: invokevirtual #7                  // Method java/lang/Thread.getContextClassLoader:()Ljava/lang/ClassLoader;
      38: invokestatic  #5                  // Method forName:(Ljava/lang/String;Ljava/lang/ClassLoader;)Ljava/lang/Class;
      41: astore_2
      42: aload_2
      43: ifnonnull     73
      46: new           #8                  // class java/lang/ClassNotFoundException
      49: dup
      50: new           #9                  // class java/lang/StringBuilder
      53: dup
      54: invokespecial #10                 // Method java/lang/StringBuilder."<init>":()V
      57: ldc           #11                 // String Failed to load class
      59: invokevirtual #12                 // Method java/lang/StringBuilder.append:(Ljava/lang/String;)Ljava/lang/StringBuilder;
      62: aload_1
      63: invokevirtual #12                 // Method java/lang/StringBuilder.append:(Ljava/lang/String;)Ljava/lang/StringBuilder;
      66: invokevirtual #13                 // Method java/lang/StringBuilder.toString:()Ljava/lang/String;
      69: invokespecial #14                 // Method java/lang/ClassNotFoundException."<init>":(Ljava/lang/String;)V
      72: athrow
      73: aload_2
      74: areturn

  public static java.lang.Class<?> forName(java.lang.ClassLoader, java.lang.String) throws java.lang.ClassNotFoundException;
    Code:
       0: aconst_null
       1: astore_2
       2: aload_0
       3: ifnull        12
       6: aload_1
       7: aload_0
       8: invokestatic  #5                  // Method forName:(Ljava/lang/String;Ljava/lang/ClassLoader;)Ljava/lang/Class;
      11: astore_2
      12: aload_2
      13: ifnonnull     36
      16: invokestatic  #6                  // Method java/lang/Thread.currentThread:()Ljava/lang/Thread;
      19: invokevirtual #7                  // Method java/lang/Thread.getContextClassLoader:()Ljava/lang/ClassLoader;
      22: ifnull        36
      25: aload_1
      26: invokestatic  #6                  // Method java/lang/Thread.currentThread:()Ljava/lang/Thread;
      29: invokevirtual #7                  // Method java/lang/Thread.getContextClassLoader:()Ljava/lang/ClassLoader;
      32: invokestatic  #5                  // Method forName:(Ljava/lang/String;Ljava/lang/ClassLoader;)Ljava/lang/Class;
      35: astore_2
      36: aload_2
      37: ifnonnull     67
      40: new           #8                  // class java/lang/ClassNotFoundException
      43: dup
      44: new           #9                  // class java/lang/StringBuilder
      47: dup
      48: invokespecial #10                 // Method java/lang/StringBuilder."<init>":()V
      51: ldc           #11                 // String Failed to load class
      53: invokevirtual #12                 // Method java/lang/StringBuilder.append:(Ljava/lang/String;)Ljava/lang/StringBuilder;
      56: aload_1
      57: invokevirtual #12                 // Method java/lang/StringBuilder.append:(Ljava/lang/String;)Ljava/lang/StringBuilder;
      60: invokevirtual #13                 // Method java/lang/StringBuilder.toString:()Ljava/lang/String;
      63: invokespecial #14                 // Method java/lang/ClassNotFoundException."<init>":(Ljava/lang/String;)V
      66: athrow
      67: aload_2
      68: areturn

  private static java.lang.Class<?> forName(java.lang.String, java.lang.ClassLoader);
    Code:
       0: aconst_null
       1: astore_2
       2: aload_1
       3: ifnull        21
       6: aload_0
       7: ifnull        21
      10: aload_0
      11: iconst_1
      12: aload_1
      13: invokestatic  #15                 // Method java/lang/Class.forName:(Ljava/lang/String;ZLjava/lang/ClassLoader;)Ljava/lang/Class;
      16: astore_2
      17: goto          21
      20: astore_3
      21: aload_2
      22: areturn
    Exception table:
       from    to  target type
          10    17    20   Class java/lang/ClassNotFoundException
}
