Compiled from "OnClassCondition.java"
final class org.springframework.boot.autoconfigure.condition.OnClassCondition$ThreadedOutcomesResolver implements org.springframework.boot.autoconfigure.condition.OnClassCondition$OutcomesResolver {
  private final java.lang.Thread thread;

  private volatile org.springframework.boot.autoconfigure.condition.ConditionOutcome[] outcomes;

  private org.springframework.boot.autoconfigure.condition.OnClassCondition$ThreadedOutcomesResolver(org.springframework.boot.autoconfigure.condition.OnClassCondition$OutcomesResolver);
    Code:
       0: aload_0
       1: invokespecial #3                  // Method java/lang/Object."<init>":()V
       4: aload_0
       5: new           #4                  // class java/lang/Thread
       8: dup
       9: new           #5                  // class org/springframework/boot/autoconfigure/condition/OnClassCondition$ThreadedOutcomesResolver$1
      12: dup
      13: aload_0
      14: aload_1
      15: invokespecial #6                  // Method org/springframework/boot/autoconfigure/condition/OnClassCondition$ThreadedOutcomesResolver$1."<init>":(Lorg/springframework/boot/autoconfigure/condition/OnClassCondition$ThreadedOutcomesResolver;Lorg/springframework/boot/autoconfigure/condition/OnClassCondition$OutcomesResolver;)V
      18: invokespecial #7                  // Method java/lang/Thread."<init>":(Ljava/lang/Runnable;)V
      21: putfield      #8                  // Field thread:Ljava/lang/Thread;
      24: aload_0
      25: getfield      #8                  // Field thread:Ljava/lang/Thread;
      28: invokevirtual #9                  // Method java/lang/Thread.start:()V
      31: return

  public org.springframework.boot.autoconfigure.condition.ConditionOutcome[] resolveOutcomes();
    Code:
       0: aload_0
       1: getfield      #8                  // Field thread:Ljava/lang/Thread;
       4: invokevirtual #10                 // Method java/lang/Thread.join:()V
       7: goto          17
      10: astore_1
      11: invokestatic  #12                 // Method java/lang/Thread.currentThread:()Ljava/lang/Thread;
      14: invokevirtual #13                 // Method java/lang/Thread.interrupt:()V
      17: aload_0
      18: getfield      #1                  // Field outcomes:[Lorg/springframework/boot/autoconfigure/condition/ConditionOutcome;
      21: areturn
    Exception table:
       from    to  target type
           0     7    10   Class java/lang/InterruptedException

  org.springframework.boot.autoconfigure.condition.OnClassCondition$ThreadedOutcomesResolver(org.springframework.boot.autoconfigure.condition.OnClassCondition$OutcomesResolver, org.springframework.boot.autoconfigure.condition.OnClassCondition$1);
    Code:
       0: aload_0
       1: aload_1
       2: invokespecial #2                  // Method "<init>":(Lorg/springframework/boot/autoconfigure/condition/OnClassCondition$OutcomesResolver;)V
       5: return

  static org.springframework.boot.autoconfigure.condition.ConditionOutcome[] access$402(org.springframework.boot.autoconfigure.condition.OnClassCondition$ThreadedOutcomesResolver, org.springframework.boot.autoconfigure.condition.ConditionOutcome[]);
    Code:
       0: aload_0
       1: aload_1
       2: dup_x1
       3: putfield      #1                  // Field outcomes:[Lorg/springframework/boot/autoconfigure/condition/ConditionOutcome;
       6: areturn
}
