Compiled from "AbstractDeploymentPlanBuilder.java"
class org.jboss.as.controller.client.helpers.domain.impl.AbstractDeploymentPlanBuilder {
  private final org.jboss.as.controller.client.helpers.domain.impl.DeploymentSetPlanImpl setPlan;

  private final boolean rollbackAcrossGroups;

  org.jboss.as.controller.client.helpers.domain.impl.AbstractDeploymentPlanBuilder();
    Code:
       0: aload_0
       1: invokespecial #1                  // Method java/lang/Object."<init>":()V
       4: aload_0
       5: new           #2                  // class org/jboss/as/controller/client/helpers/domain/impl/DeploymentSetPlanImpl
       8: dup
       9: invokespecial #3                  // Method org/jboss/as/controller/client/helpers/domain/impl/DeploymentSetPlanImpl."<init>":()V
      12: putfield      #4                  // Field setPlan:Lorg/jboss/as/controller/client/helpers/domain/impl/DeploymentSetPlanImpl;
      15: aload_0
      16: iconst_0
      17: putfield      #5                  // Field rollbackAcrossGroups:Z
      20: return

  org.jboss.as.controller.client.helpers.domain.impl.AbstractDeploymentPlanBuilder(org.jboss.as.controller.client.helpers.domain.impl.AbstractDeploymentPlanBuilder, boolean);
    Code:
       0: aload_0
       1: invokespecial #1                  // Method java/lang/Object."<init>":()V
       4: aload_0
       5: aload_1
       6: getfield      #4                  // Field setPlan:Lorg/jboss/as/controller/client/helpers/domain/impl/DeploymentSetPlanImpl;
       9: putfield      #4                  // Field setPlan:Lorg/jboss/as/controller/client/helpers/domain/impl/DeploymentSetPlanImpl;
      12: aload_0
      13: iload_2
      14: putfield      #5                  // Field rollbackAcrossGroups:Z
      17: return

  org.jboss.as.controller.client.helpers.domain.impl.AbstractDeploymentPlanBuilder(org.jboss.as.controller.client.helpers.domain.impl.AbstractDeploymentPlanBuilder, org.jboss.as.controller.client.helpers.domain.impl.DeploymentSetPlanImpl);
    Code:
       0: aload_0
       1: invokespecial #1                  // Method java/lang/Object."<init>":()V
       4: aload_0
       5: aload_2
       6: putfield      #4                  // Field setPlan:Lorg/jboss/as/controller/client/helpers/domain/impl/DeploymentSetPlanImpl;
       9: aload_0
      10: aload_1
      11: getfield      #5                  // Field rollbackAcrossGroups:Z
      14: putfield      #5                  // Field rollbackAcrossGroups:Z
      17: return

  public org.jboss.as.controller.client.helpers.domain.DeploymentAction getLastAction();
    Code:
       0: aload_0
       1: invokevirtual #6                  // Method getCurrentDeploymentSetPlan:()Lorg/jboss/as/controller/client/helpers/domain/impl/DeploymentSetPlanImpl;
       4: invokevirtual #7                  // Method org/jboss/as/controller/client/helpers/domain/impl/DeploymentSetPlanImpl.getLastAction:()Lorg/jboss/as/controller/client/helpers/domain/DeploymentAction;
       7: areturn

  org.jboss.as.controller.client.helpers.domain.impl.DeploymentSetPlanImpl getCurrentDeploymentSetPlan();
    Code:
       0: aload_0
       1: getfield      #4                  // Field setPlan:Lorg/jboss/as/controller/client/helpers/domain/impl/DeploymentSetPlanImpl;
       4: areturn

  public org.jboss.as.controller.client.helpers.domain.DeploymentPlan build();
    Code:
       0: new           #8                  // class org/jboss/as/controller/client/helpers/domain/impl/DeploymentPlanImpl
       3: dup
       4: aload_0
       5: getfield      #4                  // Field setPlan:Lorg/jboss/as/controller/client/helpers/domain/impl/DeploymentSetPlanImpl;
       8: aload_0
       9: getfield      #5                  // Field rollbackAcrossGroups:Z
      12: invokespecial #9                  // Method org/jboss/as/controller/client/helpers/domain/impl/DeploymentPlanImpl."<init>":(Lorg/jboss/as/controller/client/helpers/domain/impl/DeploymentSetPlanImpl;Z)V
      15: areturn
}
