Compiled from "PodSecurityPolicySpecBuilder.java"
public class io.dekorate.deps.kubernetes.api.model.policy.PodSecurityPolicySpecBuilder extends io.dekorate.deps.kubernetes.api.model.policy.PodSecurityPolicySpecFluentImpl<io.dekorate.deps.kubernetes.api.model.policy.PodSecurityPolicySpecBuilder> implements io.dekorate.deps.kubernetes.api.builder.VisitableBuilder<io.dekorate.deps.kubernetes.api.model.policy.PodSecurityPolicySpec, io.dekorate.deps.kubernetes.api.model.policy.PodSecurityPolicySpecBuilder> {
  io.dekorate.deps.kubernetes.api.model.policy.PodSecurityPolicySpecFluent<?> fluent;

  java.lang.Boolean validationEnabled;

  public io.dekorate.deps.kubernetes.api.model.policy.PodSecurityPolicySpecBuilder();
    Code:
       0: aload_0
       1: iconst_1
       2: invokestatic  #21                 // Method java/lang/Boolean.valueOf:(Z)Ljava/lang/Boolean;
       5: invokespecial #24                 // Method "<init>":(Ljava/lang/Boolean;)V
       8: return

  public io.dekorate.deps.kubernetes.api.model.policy.PodSecurityPolicySpecBuilder(java.lang.Boolean);
    Code:
       0: aload_0
       1: new           #28                 // class io/dekorate/deps/kubernetes/api/model/policy/PodSecurityPolicySpec
       4: dup
       5: invokespecial #30                 // Method io/dekorate/deps/kubernetes/api/model/policy/PodSecurityPolicySpec."<init>":()V
       8: aload_1
       9: invokespecial #33                 // Method "<init>":(Lio/dekorate/deps/kubernetes/api/model/policy/PodSecurityPolicySpec;Ljava/lang/Boolean;)V
      12: return

  public io.dekorate.deps.kubernetes.api.model.policy.PodSecurityPolicySpecBuilder(io.dekorate.deps.kubernetes.api.model.policy.PodSecurityPolicySpecFluent<?>);
    Code:
       0: aload_0
       1: aload_1
       2: iconst_1
       3: invokestatic  #21                 // Method java/lang/Boolean.valueOf:(Z)Ljava/lang/Boolean;
       6: invokespecial #38                 // Method "<init>":(Lio/dekorate/deps/kubernetes/api/model/policy/PodSecurityPolicySpecFluent;Ljava/lang/Boolean;)V
       9: return

  public io.dekorate.deps.kubernetes.api.model.policy.PodSecurityPolicySpecBuilder(io.dekorate.deps.kubernetes.api.model.policy.PodSecurityPolicySpecFluent<?>, java.lang.Boolean);
    Code:
       0: aload_0
       1: aload_1
       2: new           #28                 // class io/dekorate/deps/kubernetes/api/model/policy/PodSecurityPolicySpec
       5: dup
       6: invokespecial #30                 // Method io/dekorate/deps/kubernetes/api/model/policy/PodSecurityPolicySpec."<init>":()V
       9: aload_2
      10: invokespecial #42                 // Method "<init>":(Lio/dekorate/deps/kubernetes/api/model/policy/PodSecurityPolicySpecFluent;Lio/dekorate/deps/kubernetes/api/model/policy/PodSecurityPolicySpec;Ljava/lang/Boolean;)V
      13: return

  public io.dekorate.deps.kubernetes.api.model.policy.PodSecurityPolicySpecBuilder(io.dekorate.deps.kubernetes.api.model.policy.PodSecurityPolicySpecFluent<?>, io.dekorate.deps.kubernetes.api.model.policy.PodSecurityPolicySpec);
    Code:
       0: aload_0
       1: aload_1
       2: aload_2
       3: iconst_1
       4: invokestatic  #21                 // Method java/lang/Boolean.valueOf:(Z)Ljava/lang/Boolean;
       7: invokespecial #42                 // Method "<init>":(Lio/dekorate/deps/kubernetes/api/model/policy/PodSecurityPolicySpecFluent;Lio/dekorate/deps/kubernetes/api/model/policy/PodSecurityPolicySpec;Ljava/lang/Boolean;)V
      10: return

  public io.dekorate.deps.kubernetes.api.model.policy.PodSecurityPolicySpecBuilder(io.dekorate.deps.kubernetes.api.model.policy.PodSecurityPolicySpecFluent<?>, io.dekorate.deps.kubernetes.api.model.policy.PodSecurityPolicySpec, java.lang.Boolean);
    Code:
       0: aload_0
       1: invokespecial #48                 // Method io/dekorate/deps/kubernetes/api/model/policy/PodSecurityPolicySpecFluentImpl."<init>":()V
       4: aload_0
       5: aload_1
       6: putfield      #50                 // Field fluent:Lio/dekorate/deps/kubernetes/api/model/policy/PodSecurityPolicySpecFluent;
       9: aload_1
      10: aload_2
      11: invokevirtual #54                 // Method io/dekorate/deps/kubernetes/api/model/policy/PodSecurityPolicySpec.getAllowPrivilegeEscalation:()Ljava/lang/Boolean;
      14: invokeinterface #60,  2           // InterfaceMethod io/dekorate/deps/kubernetes/api/model/policy/PodSecurityPolicySpecFluent.withAllowPrivilegeEscalation:(Ljava/lang/Boolean;)Lio/dekorate/deps/kubernetes/api/model/policy/PodSecurityPolicySpecFluent;
      19: pop
      20: aload_1
      21: aload_2
      22: invokevirtual #64                 // Method io/dekorate/deps/kubernetes/api/model/policy/PodSecurityPolicySpec.getAllowedCSIDrivers:()Ljava/util/List;
      25: invokeinterface #68,  2           // InterfaceMethod io/dekorate/deps/kubernetes/api/model/policy/PodSecurityPolicySpecFluent.withAllowedCSIDrivers:(Ljava/util/List;)Lio/dekorate/deps/kubernetes/api/model/policy/PodSecurityPolicySpecFluent;
      30: pop
      31: aload_1
      32: aload_2
      33: invokevirtual #71                 // Method io/dekorate/deps/kubernetes/api/model/policy/PodSecurityPolicySpec.getAllowedCapabilities:()Ljava/util/List;
      36: invokeinterface #74,  2           // InterfaceMethod io/dekorate/deps/kubernetes/api/model/policy/PodSecurityPolicySpecFluent.withAllowedCapabilities:(Ljava/util/List;)Lio/dekorate/deps/kubernetes/api/model/policy/PodSecurityPolicySpecFluent;
      41: pop
      42: aload_1
      43: aload_2
      44: invokevirtual #77                 // Method io/dekorate/deps/kubernetes/api/model/policy/PodSecurityPolicySpec.getAllowedFlexVolumes:()Ljava/util/List;
      47: invokeinterface #80,  2           // InterfaceMethod io/dekorate/deps/kubernetes/api/model/policy/PodSecurityPolicySpecFluent.withAllowedFlexVolumes:(Ljava/util/List;)Lio/dekorate/deps/kubernetes/api/model/policy/PodSecurityPolicySpecFluent;
      52: pop
      53: aload_1
      54: aload_2
      55: invokevirtual #83                 // Method io/dekorate/deps/kubernetes/api/model/policy/PodSecurityPolicySpec.getAllowedHostPaths:()Ljava/util/List;
      58: invokeinterface #86,  2           // InterfaceMethod io/dekorate/deps/kubernetes/api/model/policy/PodSecurityPolicySpecFluent.withAllowedHostPaths:(Ljava/util/List;)Lio/dekorate/deps/kubernetes/api/model/policy/PodSecurityPolicySpecFluent;
      63: pop
      64: aload_1
      65: aload_2
      66: invokevirtual #89                 // Method io/dekorate/deps/kubernetes/api/model/policy/PodSecurityPolicySpec.getAllowedProcMountTypes:()Ljava/util/List;
      69: invokeinterface #92,  2           // InterfaceMethod io/dekorate/deps/kubernetes/api/model/policy/PodSecurityPolicySpecFluent.withAllowedProcMountTypes:(Ljava/util/List;)Lio/dekorate/deps/kubernetes/api/model/policy/PodSecurityPolicySpecFluent;
      74: pop
      75: aload_1
      76: aload_2
      77: invokevirtual #95                 // Method io/dekorate/deps/kubernetes/api/model/policy/PodSecurityPolicySpec.getAllowedUnsafeSysctls:()Ljava/util/List;
      80: invokeinterface #98,  2           // InterfaceMethod io/dekorate/deps/kubernetes/api/model/policy/PodSecurityPolicySpecFluent.withAllowedUnsafeSysctls:(Ljava/util/List;)Lio/dekorate/deps/kubernetes/api/model/policy/PodSecurityPolicySpecFluent;
      85: pop
      86: aload_1
      87: aload_2
      88: invokevirtual #101                // Method io/dekorate/deps/kubernetes/api/model/policy/PodSecurityPolicySpec.getDefaultAddCapabilities:()Ljava/util/List;
      91: invokeinterface #104,  2          // InterfaceMethod io/dekorate/deps/kubernetes/api/model/policy/PodSecurityPolicySpecFluent.withDefaultAddCapabilities:(Ljava/util/List;)Lio/dekorate/deps/kubernetes/api/model/policy/PodSecurityPolicySpecFluent;
      96: pop
      97: aload_1
      98: aload_2
      99: invokevirtual #107                // Method io/dekorate/deps/kubernetes/api/model/policy/PodSecurityPolicySpec.getDefaultAllowPrivilegeEscalation:()Ljava/lang/Boolean;
     102: invokeinterface #110,  2          // InterfaceMethod io/dekorate/deps/kubernetes/api/model/policy/PodSecurityPolicySpecFluent.withDefaultAllowPrivilegeEscalation:(Ljava/lang/Boolean;)Lio/dekorate/deps/kubernetes/api/model/policy/PodSecurityPolicySpecFluent;
     107: pop
     108: aload_1
     109: aload_2
     110: invokevirtual #113                // Method io/dekorate/deps/kubernetes/api/model/policy/PodSecurityPolicySpec.getForbiddenSysctls:()Ljava/util/List;
     113: invokeinterface #116,  2          // InterfaceMethod io/dekorate/deps/kubernetes/api/model/policy/PodSecurityPolicySpecFluent.withForbiddenSysctls:(Ljava/util/List;)Lio/dekorate/deps/kubernetes/api/model/policy/PodSecurityPolicySpecFluent;
     118: pop
     119: aload_1
     120: aload_2
     121: invokevirtual #120                // Method io/dekorate/deps/kubernetes/api/model/policy/PodSecurityPolicySpec.getFsGroup:()Lio/dekorate/deps/kubernetes/api/model/policy/FSGroupStrategyOptions;
     124: invokeinterface #124,  2          // InterfaceMethod io/dekorate/deps/kubernetes/api/model/policy/PodSecurityPolicySpecFluent.withFsGroup:(Lio/dekorate/deps/kubernetes/api/model/policy/FSGroupStrategyOptions;)Lio/dekorate/deps/kubernetes/api/model/policy/PodSecurityPolicySpecFluent;
     129: pop
     130: aload_1
     131: aload_2
     132: invokevirtual #127                // Method io/dekorate/deps/kubernetes/api/model/policy/PodSecurityPolicySpec.getHostIPC:()Ljava/lang/Boolean;
     135: invokeinterface #130,  2          // InterfaceMethod io/dekorate/deps/kubernetes/api/model/policy/PodSecurityPolicySpecFluent.withHostIPC:(Ljava/lang/Boolean;)Lio/dekorate/deps/kubernetes/api/model/policy/PodSecurityPolicySpecFluent;
     140: pop
     141: aload_1
     142: aload_2
     143: invokevirtual #133                // Method io/dekorate/deps/kubernetes/api/model/policy/PodSecurityPolicySpec.getHostNetwork:()Ljava/lang/Boolean;
     146: invokeinterface #136,  2          // InterfaceMethod io/dekorate/deps/kubernetes/api/model/policy/PodSecurityPolicySpecFluent.withHostNetwork:(Ljava/lang/Boolean;)Lio/dekorate/deps/kubernetes/api/model/policy/PodSecurityPolicySpecFluent;
     151: pop
     152: aload_1
     153: aload_2
     154: invokevirtual #139                // Method io/dekorate/deps/kubernetes/api/model/policy/PodSecurityPolicySpec.getHostPID:()Ljava/lang/Boolean;
     157: invokeinterface #142,  2          // InterfaceMethod io/dekorate/deps/kubernetes/api/model/policy/PodSecurityPolicySpecFluent.withHostPID:(Ljava/lang/Boolean;)Lio/dekorate/deps/kubernetes/api/model/policy/PodSecurityPolicySpecFluent;
     162: pop
     163: aload_1
     164: aload_2
     165: invokevirtual #145                // Method io/dekorate/deps/kubernetes/api/model/policy/PodSecurityPolicySpec.getHostPorts:()Ljava/util/List;
     168: invokeinterface #148,  2          // InterfaceMethod io/dekorate/deps/kubernetes/api/model/policy/PodSecurityPolicySpecFluent.withHostPorts:(Ljava/util/List;)Lio/dekorate/deps/kubernetes/api/model/policy/PodSecurityPolicySpecFluent;
     173: pop
     174: aload_1
     175: aload_2
     176: invokevirtual #151                // Method io/dekorate/deps/kubernetes/api/model/policy/PodSecurityPolicySpec.getPrivileged:()Ljava/lang/Boolean;
     179: invokeinterface #154,  2          // InterfaceMethod io/dekorate/deps/kubernetes/api/model/policy/PodSecurityPolicySpecFluent.withPrivileged:(Ljava/lang/Boolean;)Lio/dekorate/deps/kubernetes/api/model/policy/PodSecurityPolicySpecFluent;
     184: pop
     185: aload_1
     186: aload_2
     187: invokevirtual #157                // Method io/dekorate/deps/kubernetes/api/model/policy/PodSecurityPolicySpec.getReadOnlyRootFilesystem:()Ljava/lang/Boolean;
     190: invokeinterface #160,  2          // InterfaceMethod io/dekorate/deps/kubernetes/api/model/policy/PodSecurityPolicySpecFluent.withReadOnlyRootFilesystem:(Ljava/lang/Boolean;)Lio/dekorate/deps/kubernetes/api/model/policy/PodSecurityPolicySpecFluent;
     195: pop
     196: aload_1
     197: aload_2
     198: invokevirtual #163                // Method io/dekorate/deps/kubernetes/api/model/policy/PodSecurityPolicySpec.getRequiredDropCapabilities:()Ljava/util/List;
     201: invokeinterface #166,  2          // InterfaceMethod io/dekorate/deps/kubernetes/api/model/policy/PodSecurityPolicySpecFluent.withRequiredDropCapabilities:(Ljava/util/List;)Lio/dekorate/deps/kubernetes/api/model/policy/PodSecurityPolicySpecFluent;
     206: pop
     207: aload_1
     208: aload_2
     209: invokevirtual #170                // Method io/dekorate/deps/kubernetes/api/model/policy/PodSecurityPolicySpec.getRunAsGroup:()Lio/dekorate/deps/kubernetes/api/model/policy/RunAsGroupStrategyOptions;
     212: invokeinterface #174,  2          // InterfaceMethod io/dekorate/deps/kubernetes/api/model/policy/PodSecurityPolicySpecFluent.withRunAsGroup:(Lio/dekorate/deps/kubernetes/api/model/policy/RunAsGroupStrategyOptions;)Lio/dekorate/deps/kubernetes/api/model/policy/PodSecurityPolicySpecFluent;
     217: pop
     218: aload_1
     219: aload_2
     220: invokevirtual #178                // Method io/dekorate/deps/kubernetes/api/model/policy/PodSecurityPolicySpec.getRunAsUser:()Lio/dekorate/deps/kubernetes/api/model/policy/KubernetesRunAsUserStrategyOptions;
     223: invokeinterface #182,  2          // InterfaceMethod io/dekorate/deps/kubernetes/api/model/policy/PodSecurityPolicySpecFluent.withRunAsUser:(Lio/dekorate/deps/kubernetes/api/model/policy/KubernetesRunAsUserStrategyOptions;)Lio/dekorate/deps/kubernetes/api/model/policy/PodSecurityPolicySpecFluent;
     228: pop
     229: aload_1
     230: aload_2
     231: invokevirtual #186                // Method io/dekorate/deps/kubernetes/api/model/policy/PodSecurityPolicySpec.getRuntimeClass:()Lio/dekorate/deps/kubernetes/api/model/policy/RuntimeClassStrategyOptions;
     234: invokeinterface #190,  2          // InterfaceMethod io/dekorate/deps/kubernetes/api/model/policy/PodSecurityPolicySpecFluent.withRuntimeClass:(Lio/dekorate/deps/kubernetes/api/model/policy/RuntimeClassStrategyOptions;)Lio/dekorate/deps/kubernetes/api/model/policy/PodSecurityPolicySpecFluent;
     239: pop
     240: aload_1
     241: aload_2
     242: invokevirtual #194                // Method io/dekorate/deps/kubernetes/api/model/policy/PodSecurityPolicySpec.getSeLinux:()Lio/dekorate/deps/kubernetes/api/model/policy/SELinuxStrategyOptions;
     245: invokeinterface #198,  2          // InterfaceMethod io/dekorate/deps/kubernetes/api/model/policy/PodSecurityPolicySpecFluent.withSeLinux:(Lio/dekorate/deps/kubernetes/api/model/policy/SELinuxStrategyOptions;)Lio/dekorate/deps/kubernetes/api/model/policy/PodSecurityPolicySpecFluent;
     250: pop
     251: aload_1
     252: aload_2
     253: invokevirtual #202                // Method io/dekorate/deps/kubernetes/api/model/policy/PodSecurityPolicySpec.getSupplementalGroups:()Lio/dekorate/deps/kubernetes/api/model/policy/SupplementalGroupsStrategyOptions;
     256: invokeinterface #206,  2          // InterfaceMethod io/dekorate/deps/kubernetes/api/model/policy/PodSecurityPolicySpecFluent.withSupplementalGroups:(Lio/dekorate/deps/kubernetes/api/model/policy/SupplementalGroupsStrategyOptions;)Lio/dekorate/deps/kubernetes/api/model/policy/PodSecurityPolicySpecFluent;
     261: pop
     262: aload_1
     263: aload_2
     264: invokevirtual #209                // Method io/dekorate/deps/kubernetes/api/model/policy/PodSecurityPolicySpec.getVolumes:()Ljava/util/List;
     267: invokeinterface #212,  2          // InterfaceMethod io/dekorate/deps/kubernetes/api/model/policy/PodSecurityPolicySpecFluent.withVolumes:(Ljava/util/List;)Lio/dekorate/deps/kubernetes/api/model/policy/PodSecurityPolicySpecFluent;
     272: pop
     273: aload_0
     274: aload_3
     275: putfield      #214                // Field validationEnabled:Ljava/lang/Boolean;
     278: return

  public io.dekorate.deps.kubernetes.api.model.policy.PodSecurityPolicySpecBuilder(io.dekorate.deps.kubernetes.api.model.policy.PodSecurityPolicySpec);
    Code:
       0: aload_0
       1: aload_1
       2: iconst_1
       3: invokestatic  #21                 // Method java/lang/Boolean.valueOf:(Z)Ljava/lang/Boolean;
       6: invokespecial #33                 // Method "<init>":(Lio/dekorate/deps/kubernetes/api/model/policy/PodSecurityPolicySpec;Ljava/lang/Boolean;)V
       9: return

  public io.dekorate.deps.kubernetes.api.model.policy.PodSecurityPolicySpecBuilder(io.dekorate.deps.kubernetes.api.model.policy.PodSecurityPolicySpec, java.lang.Boolean);
    Code:
       0: aload_0
       1: invokespecial #48                 // Method io/dekorate/deps/kubernetes/api/model/policy/PodSecurityPolicySpecFluentImpl."<init>":()V
       4: aload_0
       5: aload_0
       6: putfield      #50                 // Field fluent:Lio/dekorate/deps/kubernetes/api/model/policy/PodSecurityPolicySpecFluent;
       9: aload_0
      10: aload_1
      11: invokevirtual #54                 // Method io/dekorate/deps/kubernetes/api/model/policy/PodSecurityPolicySpec.getAllowPrivilegeEscalation:()Ljava/lang/Boolean;
      14: invokevirtual #216                // Method withAllowPrivilegeEscalation:(Ljava/lang/Boolean;)Lio/dekorate/deps/kubernetes/api/model/policy/PodSecurityPolicySpecFluent;
      17: pop
      18: aload_0
      19: aload_1
      20: invokevirtual #64                 // Method io/dekorate/deps/kubernetes/api/model/policy/PodSecurityPolicySpec.getAllowedCSIDrivers:()Ljava/util/List;
      23: invokevirtual #217                // Method withAllowedCSIDrivers:(Ljava/util/List;)Lio/dekorate/deps/kubernetes/api/model/policy/PodSecurityPolicySpecFluent;
      26: pop
      27: aload_0
      28: aload_1
      29: invokevirtual #71                 // Method io/dekorate/deps/kubernetes/api/model/policy/PodSecurityPolicySpec.getAllowedCapabilities:()Ljava/util/List;
      32: invokevirtual #218                // Method withAllowedCapabilities:(Ljava/util/List;)Lio/dekorate/deps/kubernetes/api/model/policy/PodSecurityPolicySpecFluent;
      35: pop
      36: aload_0
      37: aload_1
      38: invokevirtual #77                 // Method io/dekorate/deps/kubernetes/api/model/policy/PodSecurityPolicySpec.getAllowedFlexVolumes:()Ljava/util/List;
      41: invokevirtual #219                // Method withAllowedFlexVolumes:(Ljava/util/List;)Lio/dekorate/deps/kubernetes/api/model/policy/PodSecurityPolicySpecFluent;
      44: pop
      45: aload_0
      46: aload_1
      47: invokevirtual #83                 // Method io/dekorate/deps/kubernetes/api/model/policy/PodSecurityPolicySpec.getAllowedHostPaths:()Ljava/util/List;
      50: invokevirtual #220                // Method withAllowedHostPaths:(Ljava/util/List;)Lio/dekorate/deps/kubernetes/api/model/policy/PodSecurityPolicySpecFluent;
      53: pop
      54: aload_0
      55: aload_1
      56: invokevirtual #89                 // Method io/dekorate/deps/kubernetes/api/model/policy/PodSecurityPolicySpec.getAllowedProcMountTypes:()Ljava/util/List;
      59: invokevirtual #221                // Method withAllowedProcMountTypes:(Ljava/util/List;)Lio/dekorate/deps/kubernetes/api/model/policy/PodSecurityPolicySpecFluent;
      62: pop
      63: aload_0
      64: aload_1
      65: invokevirtual #95                 // Method io/dekorate/deps/kubernetes/api/model/policy/PodSecurityPolicySpec.getAllowedUnsafeSysctls:()Ljava/util/List;
      68: invokevirtual #222                // Method withAllowedUnsafeSysctls:(Ljava/util/List;)Lio/dekorate/deps/kubernetes/api/model/policy/PodSecurityPolicySpecFluent;
      71: pop
      72: aload_0
      73: aload_1
      74: invokevirtual #101                // Method io/dekorate/deps/kubernetes/api/model/policy/PodSecurityPolicySpec.getDefaultAddCapabilities:()Ljava/util/List;
      77: invokevirtual #223                // Method withDefaultAddCapabilities:(Ljava/util/List;)Lio/dekorate/deps/kubernetes/api/model/policy/PodSecurityPolicySpecFluent;
      80: pop
      81: aload_0
      82: aload_1
      83: invokevirtual #107                // Method io/dekorate/deps/kubernetes/api/model/policy/PodSecurityPolicySpec.getDefaultAllowPrivilegeEscalation:()Ljava/lang/Boolean;
      86: invokevirtual #224                // Method withDefaultAllowPrivilegeEscalation:(Ljava/lang/Boolean;)Lio/dekorate/deps/kubernetes/api/model/policy/PodSecurityPolicySpecFluent;
      89: pop
      90: aload_0
      91: aload_1
      92: invokevirtual #113                // Method io/dekorate/deps/kubernetes/api/model/policy/PodSecurityPolicySpec.getForbiddenSysctls:()Ljava/util/List;
      95: invokevirtual #225                // Method withForbiddenSysctls:(Ljava/util/List;)Lio/dekorate/deps/kubernetes/api/model/policy/PodSecurityPolicySpecFluent;
      98: pop
      99: aload_0
     100: aload_1
     101: invokevirtual #120                // Method io/dekorate/deps/kubernetes/api/model/policy/PodSecurityPolicySpec.getFsGroup:()Lio/dekorate/deps/kubernetes/api/model/policy/FSGroupStrategyOptions;
     104: invokevirtual #226                // Method withFsGroup:(Lio/dekorate/deps/kubernetes/api/model/policy/FSGroupStrategyOptions;)Lio/dekorate/deps/kubernetes/api/model/policy/PodSecurityPolicySpecFluent;
     107: pop
     108: aload_0
     109: aload_1
     110: invokevirtual #127                // Method io/dekorate/deps/kubernetes/api/model/policy/PodSecurityPolicySpec.getHostIPC:()Ljava/lang/Boolean;
     113: invokevirtual #227                // Method withHostIPC:(Ljava/lang/Boolean;)Lio/dekorate/deps/kubernetes/api/model/policy/PodSecurityPolicySpecFluent;
     116: pop
     117: aload_0
     118: aload_1
     119: invokevirtual #133                // Method io/dekorate/deps/kubernetes/api/model/policy/PodSecurityPolicySpec.getHostNetwork:()Ljava/lang/Boolean;
     122: invokevirtual #228                // Method withHostNetwork:(Ljava/lang/Boolean;)Lio/dekorate/deps/kubernetes/api/model/policy/PodSecurityPolicySpecFluent;
     125: pop
     126: aload_0
     127: aload_1
     128: invokevirtual #139                // Method io/dekorate/deps/kubernetes/api/model/policy/PodSecurityPolicySpec.getHostPID:()Ljava/lang/Boolean;
     131: invokevirtual #229                // Method withHostPID:(Ljava/lang/Boolean;)Lio/dekorate/deps/kubernetes/api/model/policy/PodSecurityPolicySpecFluent;
     134: pop
     135: aload_0
     136: aload_1
     137: invokevirtual #145                // Method io/dekorate/deps/kubernetes/api/model/policy/PodSecurityPolicySpec.getHostPorts:()Ljava/util/List;
     140: invokevirtual #230                // Method withHostPorts:(Ljava/util/List;)Lio/dekorate/deps/kubernetes/api/model/policy/PodSecurityPolicySpecFluent;
     143: pop
     144: aload_0
     145: aload_1
     146: invokevirtual #151                // Method io/dekorate/deps/kubernetes/api/model/policy/PodSecurityPolicySpec.getPrivileged:()Ljava/lang/Boolean;
     149: invokevirtual #231                // Method withPrivileged:(Ljava/lang/Boolean;)Lio/dekorate/deps/kubernetes/api/model/policy/PodSecurityPolicySpecFluent;
     152: pop
     153: aload_0
     154: aload_1
     155: invokevirtual #157                // Method io/dekorate/deps/kubernetes/api/model/policy/PodSecurityPolicySpec.getReadOnlyRootFilesystem:()Ljava/lang/Boolean;
     158: invokevirtual #232                // Method withReadOnlyRootFilesystem:(Ljava/lang/Boolean;)Lio/dekorate/deps/kubernetes/api/model/policy/PodSecurityPolicySpecFluent;
     161: pop
     162: aload_0
     163: aload_1
     164: invokevirtual #163                // Method io/dekorate/deps/kubernetes/api/model/policy/PodSecurityPolicySpec.getRequiredDropCapabilities:()Ljava/util/List;
     167: invokevirtual #233                // Method withRequiredDropCapabilities:(Ljava/util/List;)Lio/dekorate/deps/kubernetes/api/model/policy/PodSecurityPolicySpecFluent;
     170: pop
     171: aload_0
     172: aload_1
     173: invokevirtual #170                // Method io/dekorate/deps/kubernetes/api/model/policy/PodSecurityPolicySpec.getRunAsGroup:()Lio/dekorate/deps/kubernetes/api/model/policy/RunAsGroupStrategyOptions;
     176: invokevirtual #234                // Method withRunAsGroup:(Lio/dekorate/deps/kubernetes/api/model/policy/RunAsGroupStrategyOptions;)Lio/dekorate/deps/kubernetes/api/model/policy/PodSecurityPolicySpecFluent;
     179: pop
     180: aload_0
     181: aload_1
     182: invokevirtual #178                // Method io/dekorate/deps/kubernetes/api/model/policy/PodSecurityPolicySpec.getRunAsUser:()Lio/dekorate/deps/kubernetes/api/model/policy/KubernetesRunAsUserStrategyOptions;
     185: invokevirtual #235                // Method withRunAsUser:(Lio/dekorate/deps/kubernetes/api/model/policy/KubernetesRunAsUserStrategyOptions;)Lio/dekorate/deps/kubernetes/api/model/policy/PodSecurityPolicySpecFluent;
     188: pop
     189: aload_0
     190: aload_1
     191: invokevirtual #186                // Method io/dekorate/deps/kubernetes/api/model/policy/PodSecurityPolicySpec.getRuntimeClass:()Lio/dekorate/deps/kubernetes/api/model/policy/RuntimeClassStrategyOptions;
     194: invokevirtual #236                // Method withRuntimeClass:(Lio/dekorate/deps/kubernetes/api/model/policy/RuntimeClassStrategyOptions;)Lio/dekorate/deps/kubernetes/api/model/policy/PodSecurityPolicySpecFluent;
     197: pop
     198: aload_0
     199: aload_1
     200: invokevirtual #194                // Method io/dekorate/deps/kubernetes/api/model/policy/PodSecurityPolicySpec.getSeLinux:()Lio/dekorate/deps/kubernetes/api/model/policy/SELinuxStrategyOptions;
     203: invokevirtual #237                // Method withSeLinux:(Lio/dekorate/deps/kubernetes/api/model/policy/SELinuxStrategyOptions;)Lio/dekorate/deps/kubernetes/api/model/policy/PodSecurityPolicySpecFluent;
     206: pop
     207: aload_0
     208: aload_1
     209: invokevirtual #202                // Method io/dekorate/deps/kubernetes/api/model/policy/PodSecurityPolicySpec.getSupplementalGroups:()Lio/dekorate/deps/kubernetes/api/model/policy/SupplementalGroupsStrategyOptions;
     212: invokevirtual #238                // Method withSupplementalGroups:(Lio/dekorate/deps/kubernetes/api/model/policy/SupplementalGroupsStrategyOptions;)Lio/dekorate/deps/kubernetes/api/model/policy/PodSecurityPolicySpecFluent;
     215: pop
     216: aload_0
     217: aload_1
     218: invokevirtual #209                // Method io/dekorate/deps/kubernetes/api/model/policy/PodSecurityPolicySpec.getVolumes:()Ljava/util/List;
     221: invokevirtual #239                // Method withVolumes:(Ljava/util/List;)Lio/dekorate/deps/kubernetes/api/model/policy/PodSecurityPolicySpecFluent;
     224: pop
     225: aload_0
     226: aload_2
     227: putfield      #214                // Field validationEnabled:Ljava/lang/Boolean;
     230: return

  public io.dekorate.deps.kubernetes.api.model.policy.PodSecurityPolicySpec build();
    Code:
       0: new           #28                 // class io/dekorate/deps/kubernetes/api/model/policy/PodSecurityPolicySpec
       3: dup
       4: aload_0
       5: getfield      #50                 // Field fluent:Lio/dekorate/deps/kubernetes/api/model/policy/PodSecurityPolicySpecFluent;
       8: invokeinterface #244,  1          // InterfaceMethod io/dekorate/deps/kubernetes/api/model/policy/PodSecurityPolicySpecFluent.isAllowPrivilegeEscalation:()Ljava/lang/Boolean;
      13: aload_0
      14: getfield      #50                 // Field fluent:Lio/dekorate/deps/kubernetes/api/model/policy/PodSecurityPolicySpecFluent;
      17: invokeinterface #245,  1          // InterfaceMethod io/dekorate/deps/kubernetes/api/model/policy/PodSecurityPolicySpecFluent.getAllowedCSIDrivers:()Ljava/util/List;
      22: aload_0
      23: getfield      #50                 // Field fluent:Lio/dekorate/deps/kubernetes/api/model/policy/PodSecurityPolicySpecFluent;
      26: invokeinterface #246,  1          // InterfaceMethod io/dekorate/deps/kubernetes/api/model/policy/PodSecurityPolicySpecFluent.getAllowedCapabilities:()Ljava/util/List;
      31: aload_0
      32: getfield      #50                 // Field fluent:Lio/dekorate/deps/kubernetes/api/model/policy/PodSecurityPolicySpecFluent;
      35: invokeinterface #247,  1          // InterfaceMethod io/dekorate/deps/kubernetes/api/model/policy/PodSecurityPolicySpecFluent.getAllowedFlexVolumes:()Ljava/util/List;
      40: aload_0
      41: getfield      #50                 // Field fluent:Lio/dekorate/deps/kubernetes/api/model/policy/PodSecurityPolicySpecFluent;
      44: invokeinterface #248,  1          // InterfaceMethod io/dekorate/deps/kubernetes/api/model/policy/PodSecurityPolicySpecFluent.getAllowedHostPaths:()Ljava/util/List;
      49: aload_0
      50: getfield      #50                 // Field fluent:Lio/dekorate/deps/kubernetes/api/model/policy/PodSecurityPolicySpecFluent;
      53: invokeinterface #249,  1          // InterfaceMethod io/dekorate/deps/kubernetes/api/model/policy/PodSecurityPolicySpecFluent.getAllowedProcMountTypes:()Ljava/util/List;
      58: aload_0
      59: getfield      #50                 // Field fluent:Lio/dekorate/deps/kubernetes/api/model/policy/PodSecurityPolicySpecFluent;
      62: invokeinterface #250,  1          // InterfaceMethod io/dekorate/deps/kubernetes/api/model/policy/PodSecurityPolicySpecFluent.getAllowedUnsafeSysctls:()Ljava/util/List;
      67: aload_0
      68: getfield      #50                 // Field fluent:Lio/dekorate/deps/kubernetes/api/model/policy/PodSecurityPolicySpecFluent;
      71: invokeinterface #251,  1          // InterfaceMethod io/dekorate/deps/kubernetes/api/model/policy/PodSecurityPolicySpecFluent.getDefaultAddCapabilities:()Ljava/util/List;
      76: aload_0
      77: getfield      #50                 // Field fluent:Lio/dekorate/deps/kubernetes/api/model/policy/PodSecurityPolicySpecFluent;
      80: invokeinterface #254,  1          // InterfaceMethod io/dekorate/deps/kubernetes/api/model/policy/PodSecurityPolicySpecFluent.isDefaultAllowPrivilegeEscalation:()Ljava/lang/Boolean;
      85: aload_0
      86: getfield      #50                 // Field fluent:Lio/dekorate/deps/kubernetes/api/model/policy/PodSecurityPolicySpecFluent;
      89: invokeinterface #255,  1          // InterfaceMethod io/dekorate/deps/kubernetes/api/model/policy/PodSecurityPolicySpecFluent.getForbiddenSysctls:()Ljava/util/List;
      94: aload_0
      95: getfield      #50                 // Field fluent:Lio/dekorate/deps/kubernetes/api/model/policy/PodSecurityPolicySpecFluent;
      98: invokeinterface #256,  1          // InterfaceMethod io/dekorate/deps/kubernetes/api/model/policy/PodSecurityPolicySpecFluent.getFsGroup:()Lio/dekorate/deps/kubernetes/api/model/policy/FSGroupStrategyOptions;
     103: aload_0
     104: getfield      #50                 // Field fluent:Lio/dekorate/deps/kubernetes/api/model/policy/PodSecurityPolicySpecFluent;
     107: invokeinterface #259,  1          // InterfaceMethod io/dekorate/deps/kubernetes/api/model/policy/PodSecurityPolicySpecFluent.isHostIPC:()Ljava/lang/Boolean;
     112: aload_0
     113: getfield      #50                 // Field fluent:Lio/dekorate/deps/kubernetes/api/model/policy/PodSecurityPolicySpecFluent;
     116: invokeinterface #262,  1          // InterfaceMethod io/dekorate/deps/kubernetes/api/model/policy/PodSecurityPolicySpecFluent.isHostNetwork:()Ljava/lang/Boolean;
     121: aload_0
     122: getfield      #50                 // Field fluent:Lio/dekorate/deps/kubernetes/api/model/policy/PodSecurityPolicySpecFluent;
     125: invokeinterface #265,  1          // InterfaceMethod io/dekorate/deps/kubernetes/api/model/policy/PodSecurityPolicySpecFluent.isHostPID:()Ljava/lang/Boolean;
     130: aload_0
     131: getfield      #50                 // Field fluent:Lio/dekorate/deps/kubernetes/api/model/policy/PodSecurityPolicySpecFluent;
     134: invokeinterface #266,  1          // InterfaceMethod io/dekorate/deps/kubernetes/api/model/policy/PodSecurityPolicySpecFluent.getHostPorts:()Ljava/util/List;
     139: aload_0
     140: getfield      #50                 // Field fluent:Lio/dekorate/deps/kubernetes/api/model/policy/PodSecurityPolicySpecFluent;
     143: invokeinterface #269,  1          // InterfaceMethod io/dekorate/deps/kubernetes/api/model/policy/PodSecurityPolicySpecFluent.isPrivileged:()Ljava/lang/Boolean;
     148: aload_0
     149: getfield      #50                 // Field fluent:Lio/dekorate/deps/kubernetes/api/model/policy/PodSecurityPolicySpecFluent;
     152: invokeinterface #272,  1          // InterfaceMethod io/dekorate/deps/kubernetes/api/model/policy/PodSecurityPolicySpecFluent.isReadOnlyRootFilesystem:()Ljava/lang/Boolean;
     157: aload_0
     158: getfield      #50                 // Field fluent:Lio/dekorate/deps/kubernetes/api/model/policy/PodSecurityPolicySpecFluent;
     161: invokeinterface #273,  1          // InterfaceMethod io/dekorate/deps/kubernetes/api/model/policy/PodSecurityPolicySpecFluent.getRequiredDropCapabilities:()Ljava/util/List;
     166: aload_0
     167: getfield      #50                 // Field fluent:Lio/dekorate/deps/kubernetes/api/model/policy/PodSecurityPolicySpecFluent;
     170: invokeinterface #274,  1          // InterfaceMethod io/dekorate/deps/kubernetes/api/model/policy/PodSecurityPolicySpecFluent.getRunAsGroup:()Lio/dekorate/deps/kubernetes/api/model/policy/RunAsGroupStrategyOptions;
     175: aload_0
     176: getfield      #50                 // Field fluent:Lio/dekorate/deps/kubernetes/api/model/policy/PodSecurityPolicySpecFluent;
     179: invokeinterface #275,  1          // InterfaceMethod io/dekorate/deps/kubernetes/api/model/policy/PodSecurityPolicySpecFluent.getRunAsUser:()Lio/dekorate/deps/kubernetes/api/model/policy/KubernetesRunAsUserStrategyOptions;
     184: aload_0
     185: getfield      #50                 // Field fluent:Lio/dekorate/deps/kubernetes/api/model/policy/PodSecurityPolicySpecFluent;
     188: invokeinterface #276,  1          // InterfaceMethod io/dekorate/deps/kubernetes/api/model/policy/PodSecurityPolicySpecFluent.getRuntimeClass:()Lio/dekorate/deps/kubernetes/api/model/policy/RuntimeClassStrategyOptions;
     193: aload_0
     194: getfield      #50                 // Field fluent:Lio/dekorate/deps/kubernetes/api/model/policy/PodSecurityPolicySpecFluent;
     197: invokeinterface #277,  1          // InterfaceMethod io/dekorate/deps/kubernetes/api/model/policy/PodSecurityPolicySpecFluent.getSeLinux:()Lio/dekorate/deps/kubernetes/api/model/policy/SELinuxStrategyOptions;
     202: aload_0
     203: getfield      #50                 // Field fluent:Lio/dekorate/deps/kubernetes/api/model/policy/PodSecurityPolicySpecFluent;
     206: invokeinterface #278,  1          // InterfaceMethod io/dekorate/deps/kubernetes/api/model/policy/PodSecurityPolicySpecFluent.getSupplementalGroups:()Lio/dekorate/deps/kubernetes/api/model/policy/SupplementalGroupsStrategyOptions;
     211: aload_0
     212: getfield      #50                 // Field fluent:Lio/dekorate/deps/kubernetes/api/model/policy/PodSecurityPolicySpecFluent;
     215: invokeinterface #279,  1          // InterfaceMethod io/dekorate/deps/kubernetes/api/model/policy/PodSecurityPolicySpecFluent.getVolumes:()Ljava/util/List;
     220: invokespecial #282                // Method io/dekorate/deps/kubernetes/api/model/policy/PodSecurityPolicySpec."<init>":(Ljava/lang/Boolean;Ljava/util/List;Ljava/util/List;Ljava/util/List;Ljava/util/List;Ljava/util/List;Ljava/util/List;Ljava/util/List;Ljava/lang/Boolean;Ljava/util/List;Lio/dekorate/deps/kubernetes/api/model/policy/FSGroupStrategyOptions;Ljava/lang/Boolean;Ljava/lang/Boolean;Ljava/lang/Boolean;Ljava/util/List;Ljava/lang/Boolean;Ljava/lang/Boolean;Ljava/util/List;Lio/dekorate/deps/kubernetes/api/model/policy/RunAsGroupStrategyOptions;Lio/dekorate/deps/kubernetes/api/model/policy/KubernetesRunAsUserStrategyOptions;Lio/dekorate/deps/kubernetes/api/model/policy/RuntimeClassStrategyOptions;Lio/dekorate/deps/kubernetes/api/model/policy/SELinuxStrategyOptions;Lio/dekorate/deps/kubernetes/api/model/policy/SupplementalGroupsStrategyOptions;Ljava/util/List;)V
     223: astore_1
     224: aload_1
     225: areturn

  public boolean equals(java.lang.Object);
    Code:
       0: aload_0
       1: aload_1
       2: if_acmpne     7
       5: iconst_1
       6: ireturn
       7: aload_1
       8: ifnull        22
      11: aload_0
      12: invokevirtual #291                // Method java/lang/Object.getClass:()Ljava/lang/Class;
      15: aload_1
      16: invokevirtual #291                // Method java/lang/Object.getClass:()Ljava/lang/Class;
      19: if_acmpeq     24
      22: iconst_0
      23: ireturn
      24: aload_0
      25: aload_1
      26: invokespecial #293                // Method io/dekorate/deps/kubernetes/api/model/policy/PodSecurityPolicySpecFluentImpl.equals:(Ljava/lang/Object;)Z
      29: ifne          34
      32: iconst_0
      33: ireturn
      34: aload_1
      35: checkcast     #2                  // class io/dekorate/deps/kubernetes/api/model/policy/PodSecurityPolicySpecBuilder
      38: astore_2
      39: aload_0
      40: getfield      #50                 // Field fluent:Lio/dekorate/deps/kubernetes/api/model/policy/PodSecurityPolicySpecFluent;
      43: ifnull        71
      46: aload_0
      47: getfield      #50                 // Field fluent:Lio/dekorate/deps/kubernetes/api/model/policy/PodSecurityPolicySpecFluent;
      50: aload_0
      51: if_acmpeq     71
      54: aload_0
      55: getfield      #50                 // Field fluent:Lio/dekorate/deps/kubernetes/api/model/policy/PodSecurityPolicySpecFluent;
      58: aload_2
      59: getfield      #50                 // Field fluent:Lio/dekorate/deps/kubernetes/api/model/policy/PodSecurityPolicySpecFluent;
      62: invokevirtual #294                // Method java/lang/Object.equals:(Ljava/lang/Object;)Z
      65: ifne          88
      68: goto          86
      71: aload_2
      72: getfield      #50                 // Field fluent:Lio/dekorate/deps/kubernetes/api/model/policy/PodSecurityPolicySpecFluent;
      75: ifnull        88
      78: aload_0
      79: getfield      #50                 // Field fluent:Lio/dekorate/deps/kubernetes/api/model/policy/PodSecurityPolicySpecFluent;
      82: aload_0
      83: if_acmpeq     88
      86: iconst_0
      87: ireturn
      88: aload_0
      89: getfield      #214                // Field validationEnabled:Ljava/lang/Boolean;
      92: ifnull        112
      95: aload_0
      96: getfield      #214                // Field validationEnabled:Ljava/lang/Boolean;
      99: aload_2
     100: getfield      #214                // Field validationEnabled:Ljava/lang/Boolean;
     103: invokevirtual #295                // Method java/lang/Boolean.equals:(Ljava/lang/Object;)Z
     106: ifne          121
     109: goto          119
     112: aload_2
     113: getfield      #214                // Field validationEnabled:Ljava/lang/Boolean;
     116: ifnull        121
     119: iconst_0
     120: ireturn
     121: iconst_1
     122: ireturn

  public java.lang.Object build();
    Code:
       0: aload_0
       1: invokevirtual #301                // Method build:()Lio/dekorate/deps/kubernetes/api/model/policy/PodSecurityPolicySpec;
       4: areturn
}
