Compiled from "SELinuxStrategyOptionsFluentImpl.java"
public class io.dekorate.deps.kubernetes.api.model.policy.SELinuxStrategyOptionsFluentImpl$SeLinuxOptionsNestedImpl<N> extends io.dekorate.deps.kubernetes.api.model.SELinuxOptionsFluentImpl<io.dekorate.deps.kubernetes.api.model.policy.SELinuxStrategyOptionsFluent$SeLinuxOptionsNested<N>> implements io.dekorate.deps.kubernetes.api.model.policy.SELinuxStrategyOptionsFluent$SeLinuxOptionsNested<N>, io.dekorate.deps.kubernetes.api.builder.Nested<N> {
  private final io.dekorate.deps.kubernetes.api.model.SELinuxOptionsBuilder builder;

  final io.dekorate.deps.kubernetes.api.model.policy.SELinuxStrategyOptionsFluentImpl this$0;

  io.dekorate.deps.kubernetes.api.model.policy.SELinuxStrategyOptionsFluentImpl$SeLinuxOptionsNestedImpl(io.dekorate.deps.kubernetes.api.model.policy.SELinuxStrategyOptionsFluentImpl, io.dekorate.deps.kubernetes.api.model.SELinuxOptions);
    Code:
       0: aload_0
       1: aload_1
       2: putfield      #24                 // Field this$0:Lio/dekorate/deps/kubernetes/api/model/policy/SELinuxStrategyOptionsFluentImpl;
       5: aload_0
       6: invokespecial #27                 // Method io/dekorate/deps/kubernetes/api/model/SELinuxOptionsFluentImpl."<init>":()V
       9: aload_0
      10: new           #29                 // class io/dekorate/deps/kubernetes/api/model/SELinuxOptionsBuilder
      13: dup
      14: aload_0
      15: aload_2
      16: invokespecial #32                 // Method io/dekorate/deps/kubernetes/api/model/SELinuxOptionsBuilder."<init>":(Lio/dekorate/deps/kubernetes/api/model/SELinuxOptionsFluent;Lio/dekorate/deps/kubernetes/api/model/SELinuxOptions;)V
      19: putfield      #34                 // Field builder:Lio/dekorate/deps/kubernetes/api/model/SELinuxOptionsBuilder;
      22: return

  io.dekorate.deps.kubernetes.api.model.policy.SELinuxStrategyOptionsFluentImpl$SeLinuxOptionsNestedImpl(io.dekorate.deps.kubernetes.api.model.policy.SELinuxStrategyOptionsFluentImpl);
    Code:
       0: aload_0
       1: aload_1
       2: putfield      #24                 // Field this$0:Lio/dekorate/deps/kubernetes/api/model/policy/SELinuxStrategyOptionsFluentImpl;
       5: aload_0
       6: invokespecial #27                 // Method io/dekorate/deps/kubernetes/api/model/SELinuxOptionsFluentImpl."<init>":()V
       9: aload_0
      10: new           #29                 // class io/dekorate/deps/kubernetes/api/model/SELinuxOptionsBuilder
      13: dup
      14: aload_0
      15: invokespecial #43                 // Method io/dekorate/deps/kubernetes/api/model/SELinuxOptionsBuilder."<init>":(Lio/dekorate/deps/kubernetes/api/model/SELinuxOptionsFluent;)V
      18: putfield      #34                 // Field builder:Lio/dekorate/deps/kubernetes/api/model/SELinuxOptionsBuilder;
      21: return

  public N and();
    Code:
       0: aload_0
       1: getfield      #24                 // Field this$0:Lio/dekorate/deps/kubernetes/api/model/policy/SELinuxStrategyOptionsFluentImpl;
       4: aload_0
       5: getfield      #34                 // Field builder:Lio/dekorate/deps/kubernetes/api/model/SELinuxOptionsBuilder;
       8: invokevirtual #50                 // Method io/dekorate/deps/kubernetes/api/model/SELinuxOptionsBuilder.build:()Lio/dekorate/deps/kubernetes/api/model/SELinuxOptions;
      11: invokevirtual #54                 // Method io/dekorate/deps/kubernetes/api/model/policy/SELinuxStrategyOptionsFluentImpl.withSeLinuxOptions:(Lio/dekorate/deps/kubernetes/api/model/SELinuxOptions;)Lio/dekorate/deps/kubernetes/api/model/policy/SELinuxStrategyOptionsFluent;
      14: areturn

  public N endSeLinuxOptions();
    Code:
       0: aload_0
       1: invokevirtual #57                 // Method and:()Ljava/lang/Object;
       4: areturn
}
