Compiled from "GraphPlain.java"
class org.apache.jena.graph.impl.GraphPlain$1 extends org.apache.jena.graph.impl.WrappedCapabilities {
  final org.apache.jena.graph.impl.GraphPlain this$0;

  org.apache.jena.graph.impl.GraphPlain$1(org.apache.jena.graph.impl.GraphPlain, org.apache.jena.graph.Capabilities);
    Code:
       0: aload_0
       1: aload_1
       2: putfield      #1                  // Field this$0:Lorg/apache/jena/graph/impl/GraphPlain;
       5: aload_0
       6: aload_2
       7: invokespecial #2                  // Method org/apache/jena/graph/impl/WrappedCapabilities."<init>":(Lorg/apache/jena/graph/Capabilities;)V
      10: return

  public boolean handlesLiteralTyping();
    Code:
       0: iconst_0
       1: ireturn
}
