Compiled from "LoggingProfileConsumer.java"
public interface org.wildfly.swarm.config.logging.LoggingProfileConsumer<T extends org.wildfly.swarm.config.logging.LoggingProfile<T>> {
  public abstract void accept(T);

  public default org.wildfly.swarm.config.logging.LoggingProfileConsumer<T> andThen(org.wildfly.swarm.config.logging.LoggingProfileConsumer<T>);
    Code:
       0: aload_0
       1: aload_1
       2: invokedynamic #1,  0              // InvokeDynamic #0:accept:(Lorg/wildfly/swarm/config/logging/LoggingProfileConsumer;Lorg/wildfly/swarm/config/logging/LoggingProfileConsumer;)Lorg/wildfly/swarm/config/logging/LoggingProfileConsumer;
       7: areturn

  private void lambda$andThen$204(org.wildfly.swarm.config.logging.LoggingProfileConsumer, org.wildfly.swarm.config.logging.LoggingProfile);
    Code:
       0: aload_0
       1: aload_2
       2: invokeinterface #2,  2            // InterfaceMethod accept:(Lorg/wildfly/swarm/config/logging/LoggingProfile;)V
       7: aload_1
       8: aload_2
       9: invokeinterface #2,  2            // InterfaceMethod accept:(Lorg/wildfly/swarm/config/logging/LoggingProfile;)V
      14: return
}
