Compiled from "HttpServletResponseHeaders.java"
public class org.jboss.resteasy.plugins.server.servlet.HttpServletResponseHeaders implements javax.ws.rs.core.MultivaluedMap<java.lang.String, java.lang.Object> {
  private org.jboss.resteasy.util.CaseInsensitiveMap cachedHeaders;

  private javax.servlet.http.HttpServletResponse response;

  private org.jboss.resteasy.spi.ResteasyProviderFactory factory;

  public org.jboss.resteasy.plugins.server.servlet.HttpServletResponseHeaders(javax.servlet.http.HttpServletResponse, org.jboss.resteasy.spi.ResteasyProviderFactory);
    Code:
       0: aload_0
       1: invokespecial #1                  // Method java/lang/Object."<init>":()V
       4: aload_0
       5: new           #2                  // class org/jboss/resteasy/util/CaseInsensitiveMap
       8: dup
       9: invokespecial #3                  // Method org/jboss/resteasy/util/CaseInsensitiveMap."<init>":()V
      12: putfield      #4                  // Field cachedHeaders:Lorg/jboss/resteasy/util/CaseInsensitiveMap;
      15: aload_0
      16: aload_1
      17: putfield      #5                  // Field response:Ljavax/servlet/http/HttpServletResponse;
      20: aload_0
      21: aload_2
      22: putfield      #6                  // Field factory:Lorg/jboss/resteasy/spi/ResteasyProviderFactory;
      25: return

  public void addAll(java.lang.String, java.lang.Object...);
    Code:
       0: aload_2
       1: astore_3
       2: aload_3
       3: arraylength
       4: istore        4
       6: iconst_0
       7: istore        5
       9: iload         5
      11: iload         4
      13: if_icmpge     35
      16: aload_3
      17: iload         5
      19: aaload
      20: astore        6
      22: aload_0
      23: aload_1
      24: aload         6
      26: invokevirtual #7                  // Method add:(Ljava/lang/String;Ljava/lang/Object;)V
      29: iinc          5, 1
      32: goto          9
      35: return

  public void addAll(java.lang.String, java.util.List<java.lang.Object>);
    Code:
       0: aload_2
       1: invokeinterface #8,  1            // InterfaceMethod java/util/List.iterator:()Ljava/util/Iterator;
       6: astore_3
       7: aload_3
       8: invokeinterface #9,  1            // InterfaceMethod java/util/Iterator.hasNext:()Z
      13: ifeq          34
      16: aload_3
      17: invokeinterface #10,  1           // InterfaceMethod java/util/Iterator.next:()Ljava/lang/Object;
      22: astore        4
      24: aload_0
      25: aload_1
      26: aload         4
      28: invokevirtual #7                  // Method add:(Ljava/lang/String;Ljava/lang/Object;)V
      31: goto          7
      34: return

  public void addFirst(java.lang.String, java.lang.Object);
    Code:
       0: aload_0
       1: aload_1
       2: invokevirtual #11                 // Method get:(Ljava/lang/Object;)Ljava/util/List;
       5: astore_3
       6: aload_3
       7: ifnonnull     17
      10: aload_0
      11: aload_1
      12: aload_2
      13: invokevirtual #7                  // Method add:(Ljava/lang/String;Ljava/lang/Object;)V
      16: return
      17: aload_3
      18: iconst_0
      19: aload_2
      20: invokeinterface #12,  3           // InterfaceMethod java/util/List.add:(ILjava/lang/Object;)V
      25: return

  public void putSingle(java.lang.String, java.lang.Object);
    Code:
       0: aload_0
       1: getfield      #4                  // Field cachedHeaders:Lorg/jboss/resteasy/util/CaseInsensitiveMap;
       4: aload_1
       5: aload_2
       6: invokevirtual #13                 // Method org/jboss/resteasy/util/CaseInsensitiveMap.putSingle:(Ljava/lang/Object;Ljava/lang/Object;)V
       9: aload_0
      10: getfield      #6                  // Field factory:Lorg/jboss/resteasy/spi/ResteasyProviderFactory;
      13: aload_2
      14: invokevirtual #14                 // Method java/lang/Object.getClass:()Ljava/lang/Class;
      17: invokevirtual #15                 // Method org/jboss/resteasy/spi/ResteasyProviderFactory.getHeaderDelegate:(Ljava/lang/Class;)Ljavax/ws/rs/ext/RuntimeDelegate$HeaderDelegate;
      20: astore_3
      21: aload_3
      22: ifnull        45
      25: aload_0
      26: getfield      #5                  // Field response:Ljavax/servlet/http/HttpServletResponse;
      29: aload_1
      30: aload_3
      31: aload_2
      32: invokeinterface #16,  2           // InterfaceMethod javax/ws/rs/ext/RuntimeDelegate$HeaderDelegate.toString:(Ljava/lang/Object;)Ljava/lang/String;
      37: invokeinterface #17,  3           // InterfaceMethod javax/servlet/http/HttpServletResponse.setHeader:(Ljava/lang/String;Ljava/lang/String;)V
      42: goto          59
      45: aload_0
      46: getfield      #5                  // Field response:Ljavax/servlet/http/HttpServletResponse;
      49: aload_1
      50: aload_2
      51: invokevirtual #18                 // Method java/lang/Object.toString:()Ljava/lang/String;
      54: invokeinterface #17,  3           // InterfaceMethod javax/servlet/http/HttpServletResponse.setHeader:(Ljava/lang/String;Ljava/lang/String;)V
      59: return

  public void add(java.lang.String, java.lang.Object);
    Code:
       0: aload_0
       1: getfield      #4                  // Field cachedHeaders:Lorg/jboss/resteasy/util/CaseInsensitiveMap;
       4: aload_1
       5: aload_2
       6: invokevirtual #19                 // Method org/jboss/resteasy/util/CaseInsensitiveMap.add:(Ljava/lang/Object;Ljava/lang/Object;)V
       9: aload_0
      10: aload_1
      11: aload_2
      12: invokevirtual #20                 // Method addResponseHeader:(Ljava/lang/String;Ljava/lang/Object;)V
      15: return

  protected void addResponseHeader(java.lang.String, java.lang.Object);
    Code:
       0: aload_0
       1: getfield      #6                  // Field factory:Lorg/jboss/resteasy/spi/ResteasyProviderFactory;
       4: aload_2
       5: invokevirtual #14                 // Method java/lang/Object.getClass:()Ljava/lang/Class;
       8: invokevirtual #15                 // Method org/jboss/resteasy/spi/ResteasyProviderFactory.getHeaderDelegate:(Ljava/lang/Class;)Ljavax/ws/rs/ext/RuntimeDelegate$HeaderDelegate;
      11: astore_3
      12: aload_3
      13: ifnull        36
      16: aload_0
      17: getfield      #5                  // Field response:Ljavax/servlet/http/HttpServletResponse;
      20: aload_1
      21: aload_3
      22: aload_2
      23: invokeinterface #16,  2           // InterfaceMethod javax/ws/rs/ext/RuntimeDelegate$HeaderDelegate.toString:(Ljava/lang/Object;)Ljava/lang/String;
      28: invokeinterface #21,  3           // InterfaceMethod javax/servlet/http/HttpServletResponse.addHeader:(Ljava/lang/String;Ljava/lang/String;)V
      33: goto          50
      36: aload_0
      37: getfield      #5                  // Field response:Ljavax/servlet/http/HttpServletResponse;
      40: aload_1
      41: aload_2
      42: invokevirtual #18                 // Method java/lang/Object.toString:()Ljava/lang/String;
      45: invokeinterface #21,  3           // InterfaceMethod javax/servlet/http/HttpServletResponse.addHeader:(Ljava/lang/String;Ljava/lang/String;)V
      50: return

  public java.lang.Object getFirst(java.lang.String);
    Code:
       0: aload_0
       1: getfield      #4                  // Field cachedHeaders:Lorg/jboss/resteasy/util/CaseInsensitiveMap;
       4: aload_1
       5: invokevirtual #22                 // Method org/jboss/resteasy/util/CaseInsensitiveMap.getFirst:(Ljava/lang/Object;)Ljava/lang/Object;
       8: areturn

  public int size();
    Code:
       0: aload_0
       1: getfield      #4                  // Field cachedHeaders:Lorg/jboss/resteasy/util/CaseInsensitiveMap;
       4: invokevirtual #23                 // Method org/jboss/resteasy/util/CaseInsensitiveMap.size:()I
       7: ireturn

  public boolean isEmpty();
    Code:
       0: aload_0
       1: getfield      #4                  // Field cachedHeaders:Lorg/jboss/resteasy/util/CaseInsensitiveMap;
       4: invokevirtual #24                 // Method org/jboss/resteasy/util/CaseInsensitiveMap.isEmpty:()Z
       7: ireturn

  public boolean containsKey(java.lang.Object);
    Code:
       0: aload_0
       1: getfield      #4                  // Field cachedHeaders:Lorg/jboss/resteasy/util/CaseInsensitiveMap;
       4: aload_1
       5: invokevirtual #25                 // Method org/jboss/resteasy/util/CaseInsensitiveMap.containsKey:(Ljava/lang/Object;)Z
       8: ireturn

  public boolean containsValue(java.lang.Object);
    Code:
       0: aload_0
       1: getfield      #4                  // Field cachedHeaders:Lorg/jboss/resteasy/util/CaseInsensitiveMap;
       4: aload_1
       5: invokevirtual #26                 // Method org/jboss/resteasy/util/CaseInsensitiveMap.containsValue:(Ljava/lang/Object;)Z
       8: ireturn

  public java.util.List<java.lang.Object> get(java.lang.Object);
    Code:
       0: aload_0
       1: getfield      #4                  // Field cachedHeaders:Lorg/jboss/resteasy/util/CaseInsensitiveMap;
       4: aload_1
       5: invokevirtual #27                 // Method org/jboss/resteasy/util/CaseInsensitiveMap.get:(Ljava/lang/Object;)Ljava/util/List;
       8: areturn

  public java.util.List<java.lang.Object> put(java.lang.String, java.util.List<java.lang.Object>);
    Code:
       0: aload_2
       1: invokeinterface #8,  1            // InterfaceMethod java/util/List.iterator:()Ljava/util/Iterator;
       6: astore_3
       7: aload_3
       8: invokeinterface #9,  1            // InterfaceMethod java/util/Iterator.hasNext:()Z
      13: ifeq          34
      16: aload_3
      17: invokeinterface #10,  1           // InterfaceMethod java/util/Iterator.next:()Ljava/lang/Object;
      22: astore        4
      24: aload_0
      25: aload_1
      26: aload         4
      28: invokevirtual #20                 // Method addResponseHeader:(Ljava/lang/String;Ljava/lang/Object;)V
      31: goto          7
      34: aload_0
      35: getfield      #4                  // Field cachedHeaders:Lorg/jboss/resteasy/util/CaseInsensitiveMap;
      38: aload_1
      39: aload_2
      40: invokevirtual #28                 // Method org/jboss/resteasy/util/CaseInsensitiveMap.put:(Ljava/lang/Object;Ljava/util/List;)Ljava/util/List;
      43: areturn

  public java.util.List<java.lang.Object> remove(java.lang.Object);
    Code:
       0: new           #29                 // class java/lang/RuntimeException
       3: dup
       4: getstatic     #30                 // Field org/jboss/resteasy/resteasy_jaxrs/i18n/Messages.MESSAGES:Lorg/jboss/resteasy/resteasy_jaxrs/i18n/Messages;
       7: invokeinterface #31,  1           // InterfaceMethod org/jboss/resteasy/resteasy_jaxrs/i18n/Messages.removingHeaderIllegal:()Ljava/lang/String;
      12: invokespecial #32                 // Method java/lang/RuntimeException."<init>":(Ljava/lang/String;)V
      15: athrow

  public void putAll(java.util.Map<? extends java.lang.String, ? extends java.util.List<java.lang.Object>>);
    Code:
       0: aload_1
       1: invokeinterface #33,  1           // InterfaceMethod java/util/Map.entrySet:()Ljava/util/Set;
       6: invokeinterface #34,  1           // InterfaceMethod java/util/Set.iterator:()Ljava/util/Iterator;
      11: astore_2
      12: aload_2
      13: invokeinterface #9,  1            // InterfaceMethod java/util/Iterator.hasNext:()Z
      18: ifeq          91
      21: aload_2
      22: invokeinterface #10,  1           // InterfaceMethod java/util/Iterator.next:()Ljava/lang/Object;
      27: checkcast     #35                 // class java/util/Map$Entry
      30: astore_3
      31: aload_3
      32: invokeinterface #36,  1           // InterfaceMethod java/util/Map$Entry.getValue:()Ljava/lang/Object;
      37: checkcast     #37                 // class java/util/List
      40: astore        4
      42: aload         4
      44: invokeinterface #8,  1            // InterfaceMethod java/util/List.iterator:()Ljava/util/Iterator;
      49: astore        5
      51: aload         5
      53: invokeinterface #9,  1            // InterfaceMethod java/util/Iterator.hasNext:()Z
      58: ifeq          88
      61: aload         5
      63: invokeinterface #10,  1           // InterfaceMethod java/util/Iterator.next:()Ljava/lang/Object;
      68: astore        6
      70: aload_0
      71: aload_3
      72: invokeinterface #38,  1           // InterfaceMethod java/util/Map$Entry.getKey:()Ljava/lang/Object;
      77: checkcast     #39                 // class java/lang/String
      80: aload         6
      82: invokevirtual #7                  // Method add:(Ljava/lang/String;Ljava/lang/Object;)V
      85: goto          51
      88: goto          12
      91: return

  public void clear();
    Code:
       0: new           #29                 // class java/lang/RuntimeException
       3: dup
       4: getstatic     #30                 // Field org/jboss/resteasy/resteasy_jaxrs/i18n/Messages.MESSAGES:Lorg/jboss/resteasy/resteasy_jaxrs/i18n/Messages;
       7: invokeinterface #31,  1           // InterfaceMethod org/jboss/resteasy/resteasy_jaxrs/i18n/Messages.removingHeaderIllegal:()Ljava/lang/String;
      12: invokespecial #32                 // Method java/lang/RuntimeException."<init>":(Ljava/lang/String;)V
      15: athrow

  public java.util.Set<java.lang.String> keySet();
    Code:
       0: aload_0
       1: getfield      #4                  // Field cachedHeaders:Lorg/jboss/resteasy/util/CaseInsensitiveMap;
       4: invokevirtual #40                 // Method org/jboss/resteasy/util/CaseInsensitiveMap.keySet:()Ljava/util/Set;
       7: areturn

  public java.util.Collection<java.util.List<java.lang.Object>> values();
    Code:
       0: aload_0
       1: getfield      #4                  // Field cachedHeaders:Lorg/jboss/resteasy/util/CaseInsensitiveMap;
       4: invokevirtual #41                 // Method org/jboss/resteasy/util/CaseInsensitiveMap.values:()Ljava/util/Collection;
       7: areturn

  public java.util.Set<java.util.Map$Entry<java.lang.String, java.util.List<java.lang.Object>>> entrySet();
    Code:
       0: aload_0
       1: getfield      #4                  // Field cachedHeaders:Lorg/jboss/resteasy/util/CaseInsensitiveMap;
       4: invokevirtual #42                 // Method org/jboss/resteasy/util/CaseInsensitiveMap.entrySet:()Ljava/util/Set;
       7: areturn

  public boolean equals(java.lang.Object);
    Code:
       0: aload_0
       1: getfield      #4                  // Field cachedHeaders:Lorg/jboss/resteasy/util/CaseInsensitiveMap;
       4: aload_1
       5: invokevirtual #43                 // Method org/jboss/resteasy/util/CaseInsensitiveMap.equals:(Ljava/lang/Object;)Z
       8: ireturn

  public int hashCode();
    Code:
       0: aload_0
       1: getfield      #4                  // Field cachedHeaders:Lorg/jboss/resteasy/util/CaseInsensitiveMap;
       4: invokevirtual #44                 // Method org/jboss/resteasy/util/CaseInsensitiveMap.hashCode:()I
       7: ireturn

  public boolean equalsIgnoreValueOrder(javax.ws.rs.core.MultivaluedMap<java.lang.String, java.lang.Object>);
    Code:
       0: aload_0
       1: getfield      #4                  // Field cachedHeaders:Lorg/jboss/resteasy/util/CaseInsensitiveMap;
       4: aload_1
       5: invokevirtual #45                 // Method org/jboss/resteasy/util/CaseInsensitiveMap.equalsIgnoreValueOrder:(Ljavax/ws/rs/core/MultivaluedMap;)Z
       8: ireturn

  public void addFirst(java.lang.Object, java.lang.Object);
    Code:
       0: aload_0
       1: aload_1
       2: checkcast     #39                 // class java/lang/String
       5: aload_2
       6: invokevirtual #46                 // Method addFirst:(Ljava/lang/String;Ljava/lang/Object;)V
       9: return

  public void addAll(java.lang.Object, java.util.List);
    Code:
       0: aload_0
       1: aload_1
       2: checkcast     #39                 // class java/lang/String
       5: aload_2
       6: invokevirtual #47                 // Method addAll:(Ljava/lang/String;Ljava/util/List;)V
       9: return

  public void addAll(java.lang.Object, java.lang.Object[]);
    Code:
       0: aload_0
       1: aload_1
       2: checkcast     #39                 // class java/lang/String
       5: aload_2
       6: invokevirtual #48                 // Method addAll:(Ljava/lang/String;[Ljava/lang/Object;)V
       9: return

  public java.lang.Object getFirst(java.lang.Object);
    Code:
       0: aload_0
       1: aload_1
       2: checkcast     #39                 // class java/lang/String
       5: invokevirtual #49                 // Method getFirst:(Ljava/lang/String;)Ljava/lang/Object;
       8: areturn

  public void add(java.lang.Object, java.lang.Object);
    Code:
       0: aload_0
       1: aload_1
       2: checkcast     #39                 // class java/lang/String
       5: aload_2
       6: invokevirtual #7                  // Method add:(Ljava/lang/String;Ljava/lang/Object;)V
       9: return

  public void putSingle(java.lang.Object, java.lang.Object);
    Code:
       0: aload_0
       1: aload_1
       2: checkcast     #39                 // class java/lang/String
       5: aload_2
       6: invokevirtual #50                 // Method putSingle:(Ljava/lang/String;Ljava/lang/Object;)V
       9: return

  public java.lang.Object remove(java.lang.Object);
    Code:
       0: aload_0
       1: aload_1
       2: invokevirtual #51                 // Method remove:(Ljava/lang/Object;)Ljava/util/List;
       5: areturn

  public java.lang.Object put(java.lang.Object, java.lang.Object);
    Code:
       0: aload_0
       1: aload_1
       2: checkcast     #39                 // class java/lang/String
       5: aload_2
       6: checkcast     #37                 // class java/util/List
       9: invokevirtual #52                 // Method put:(Ljava/lang/String;Ljava/util/List;)Ljava/util/List;
      12: areturn

  public java.lang.Object get(java.lang.Object);
    Code:
       0: aload_0
       1: aload_1
       2: invokevirtual #11                 // Method get:(Ljava/lang/Object;)Ljava/util/List;
       5: areturn
}
