Compiled from "ScheduledExecutorTask.java"
public class org.springframework.scheduling.concurrent.ScheduledExecutorTask {
  private java.lang.Runnable runnable;

  private long delay;

  private long period;

  private java.util.concurrent.TimeUnit timeUnit;

  private boolean fixedRate;

  public org.springframework.scheduling.concurrent.ScheduledExecutorTask();
    Code:
       0: aload_0
       1: invokespecial #1                  // Method java/lang/Object."<init>":()V
       4: aload_0
       5: lconst_0
       6: putfield      #2                  // Field delay:J
       9: aload_0
      10: ldc2_w        #3                  // long -1l
      13: putfield      #5                  // Field period:J
      16: aload_0
      17: getstatic     #6                  // Field java/util/concurrent/TimeUnit.MILLISECONDS:Ljava/util/concurrent/TimeUnit;
      20: putfield      #7                  // Field timeUnit:Ljava/util/concurrent/TimeUnit;
      23: aload_0
      24: iconst_0
      25: putfield      #8                  // Field fixedRate:Z
      28: return

  public org.springframework.scheduling.concurrent.ScheduledExecutorTask(java.lang.Runnable);
    Code:
       0: aload_0
       1: invokespecial #1                  // Method java/lang/Object."<init>":()V
       4: aload_0
       5: lconst_0
       6: putfield      #2                  // Field delay:J
       9: aload_0
      10: ldc2_w        #3                  // long -1l
      13: putfield      #5                  // Field period:J
      16: aload_0
      17: getstatic     #6                  // Field java/util/concurrent/TimeUnit.MILLISECONDS:Ljava/util/concurrent/TimeUnit;
      20: putfield      #7                  // Field timeUnit:Ljava/util/concurrent/TimeUnit;
      23: aload_0
      24: iconst_0
      25: putfield      #8                  // Field fixedRate:Z
      28: aload_0
      29: aload_1
      30: putfield      #9                  // Field runnable:Ljava/lang/Runnable;
      33: return

  public org.springframework.scheduling.concurrent.ScheduledExecutorTask(java.lang.Runnable, long);
    Code:
       0: aload_0
       1: invokespecial #1                  // Method java/lang/Object."<init>":()V
       4: aload_0
       5: lconst_0
       6: putfield      #2                  // Field delay:J
       9: aload_0
      10: ldc2_w        #3                  // long -1l
      13: putfield      #5                  // Field period:J
      16: aload_0
      17: getstatic     #6                  // Field java/util/concurrent/TimeUnit.MILLISECONDS:Ljava/util/concurrent/TimeUnit;
      20: putfield      #7                  // Field timeUnit:Ljava/util/concurrent/TimeUnit;
      23: aload_0
      24: iconst_0
      25: putfield      #8                  // Field fixedRate:Z
      28: aload_0
      29: aload_1
      30: putfield      #9                  // Field runnable:Ljava/lang/Runnable;
      33: aload_0
      34: lload_2
      35: putfield      #2                  // Field delay:J
      38: return

  public org.springframework.scheduling.concurrent.ScheduledExecutorTask(java.lang.Runnable, long, long, boolean);
    Code:
       0: aload_0
       1: invokespecial #1                  // Method java/lang/Object."<init>":()V
       4: aload_0
       5: lconst_0
       6: putfield      #2                  // Field delay:J
       9: aload_0
      10: ldc2_w        #3                  // long -1l
      13: putfield      #5                  // Field period:J
      16: aload_0
      17: getstatic     #6                  // Field java/util/concurrent/TimeUnit.MILLISECONDS:Ljava/util/concurrent/TimeUnit;
      20: putfield      #7                  // Field timeUnit:Ljava/util/concurrent/TimeUnit;
      23: aload_0
      24: iconst_0
      25: putfield      #8                  // Field fixedRate:Z
      28: aload_0
      29: aload_1
      30: putfield      #9                  // Field runnable:Ljava/lang/Runnable;
      33: aload_0
      34: lload_2
      35: putfield      #2                  // Field delay:J
      38: aload_0
      39: lload         4
      41: putfield      #5                  // Field period:J
      44: aload_0
      45: iload         6
      47: putfield      #8                  // Field fixedRate:Z
      50: return

  public void setRunnable(java.lang.Runnable);
    Code:
       0: aload_0
       1: aload_1
       2: putfield      #9                  // Field runnable:Ljava/lang/Runnable;
       5: return

  public java.lang.Runnable getRunnable();
    Code:
       0: aload_0
       1: getfield      #9                  // Field runnable:Ljava/lang/Runnable;
       4: areturn

  public void setDelay(long);
    Code:
       0: aload_0
       1: lload_1
       2: putfield      #2                  // Field delay:J
       5: return

  public long getDelay();
    Code:
       0: aload_0
       1: getfield      #2                  // Field delay:J
       4: lreturn

  public void setPeriod(long);
    Code:
       0: aload_0
       1: lload_1
       2: putfield      #5                  // Field period:J
       5: return

  public long getPeriod();
    Code:
       0: aload_0
       1: getfield      #5                  // Field period:J
       4: lreturn

  public boolean isOneTimeTask();
    Code:
       0: aload_0
       1: getfield      #5                  // Field period:J
       4: lconst_0
       5: lcmp
       6: ifgt          13
       9: iconst_1
      10: goto          14
      13: iconst_0
      14: ireturn

  public void setTimeUnit(java.util.concurrent.TimeUnit);
    Code:
       0: aload_0
       1: aload_1
       2: ifnull        9
       5: aload_1
       6: goto          12
       9: getstatic     #6                  // Field java/util/concurrent/TimeUnit.MILLISECONDS:Ljava/util/concurrent/TimeUnit;
      12: putfield      #7                  // Field timeUnit:Ljava/util/concurrent/TimeUnit;
      15: return

  public java.util.concurrent.TimeUnit getTimeUnit();
    Code:
       0: aload_0
       1: getfield      #7                  // Field timeUnit:Ljava/util/concurrent/TimeUnit;
       4: areturn

  public void setFixedRate(boolean);
    Code:
       0: aload_0
       1: iload_1
       2: putfield      #8                  // Field fixedRate:Z
       5: return

  public boolean isFixedRate();
    Code:
       0: aload_0
       1: getfield      #8                  // Field fixedRate:Z
       4: ireturn
}
