Compiled from "ClassLoaderFactory.java"
final class org.apache.catalina.startup.ClassLoaderFactory$1 implements java.security.PrivilegedAction<java.net.URLClassLoader> {
  final java.lang.ClassLoader val$parent;

  final java.net.URL[] val$array;

  org.apache.catalina.startup.ClassLoaderFactory$1(java.lang.ClassLoader, java.net.URL[]);
    Code:
       0: aload_0
       1: aload_1
       2: putfield      #1                  // Field val$parent:Ljava/lang/ClassLoader;
       5: aload_0
       6: aload_2
       7: putfield      #2                  // Field val$array:[Ljava/net/URL;
      10: aload_0
      11: invokespecial #3                  // Method java/lang/Object."<init>":()V
      14: return

  public java.net.URLClassLoader run();
    Code:
       0: aload_0
       1: getfield      #1                  // Field val$parent:Ljava/lang/ClassLoader;
       4: ifnonnull     19
       7: new           #4                  // class java/net/URLClassLoader
      10: dup
      11: aload_0
      12: getfield      #2                  // Field val$array:[Ljava/net/URL;
      15: invokespecial #5                  // Method java/net/URLClassLoader."<init>":([Ljava/net/URL;)V
      18: areturn
      19: new           #4                  // class java/net/URLClassLoader
      22: dup
      23: aload_0
      24: getfield      #2                  // Field val$array:[Ljava/net/URL;
      27: aload_0
      28: getfield      #1                  // Field val$parent:Ljava/lang/ClassLoader;
      31: invokespecial #6                  // Method java/net/URLClassLoader."<init>":([Ljava/net/URL;Ljava/lang/ClassLoader;)V
      34: areturn

  public java.lang.Object run();
    Code:
       0: aload_0
       1: invokevirtual #7                  // Method run:()Ljava/net/URLClassLoader;
       4: areturn
}
