Compiled from "DynamoDbEndpointProvider.java"
public interface software.amazon.awssdk.services.dynamodb.endpoints.DynamoDbEndpointProvider extends software.amazon.awssdk.endpoints.EndpointProvider {
  public abstract java.util.concurrent.CompletableFuture<software.amazon.awssdk.endpoints.Endpoint> resolveEndpoint(software.amazon.awssdk.services.dynamodb.endpoints.DynamoDbEndpointParams);

  public default java.util.concurrent.CompletableFuture<software.amazon.awssdk.endpoints.Endpoint> resolveEndpoint(java.util.function.Consumer<software.amazon.awssdk.services.dynamodb.endpoints.DynamoDbEndpointParams$Builder>);
    Code:
       0: invokestatic  #1                  // Method software/amazon/awssdk/services/dynamodb/endpoints/DynamoDbEndpointParams.builder:()Lsoftware/amazon/awssdk/services/dynamodb/endpoints/DynamoDbEndpointParams$Builder;
       3: astore_2
       4: aload_1
       5: aload_2
       6: invokeinterface #2,  2            // InterfaceMethod java/util/function/Consumer.accept:(Ljava/lang/Object;)V
      11: aload_0
      12: aload_2
      13: invokeinterface #3,  1            // InterfaceMethod software/amazon/awssdk/services/dynamodb/endpoints/DynamoDbEndpointParams$Builder.build:()Lsoftware/amazon/awssdk/services/dynamodb/endpoints/DynamoDbEndpointParams;
      18: invokeinterface #4,  2            // InterfaceMethod resolveEndpoint:(Lsoftware/amazon/awssdk/services/dynamodb/endpoints/DynamoDbEndpointParams;)Ljava/util/concurrent/CompletableFuture;
      23: areturn

  public static software.amazon.awssdk.services.dynamodb.endpoints.DynamoDbEndpointProvider defaultProvider();
    Code:
       0: new           #5                  // class software/amazon/awssdk/services/dynamodb/endpoints/internal/DefaultDynamoDbEndpointProvider
       3: dup
       4: invokespecial #6                  // Method software/amazon/awssdk/services/dynamodb/endpoints/internal/DefaultDynamoDbEndpointProvider."<init>":()V
       7: areturn
}
