public class org.bouncycastle.crypto.params.GOST3410KeyParameters extends org.bouncycastle.crypto.params.AsymmetricKeyParameter {
  private org.bouncycastle.crypto.params.GOST3410Parameters params;

  public org.bouncycastle.crypto.params.GOST3410KeyParameters(boolean, org.bouncycastle.crypto.params.GOST3410Parameters);
    Code:
       0: aload_0
       1: iload_1
       2: invokespecial #15                 // Method org/bouncycastle/crypto/params/AsymmetricKeyParameter."<init>":(Z)V
       5: aload_0
       6: aload_2
       7: putfield      #14                 // Field params:Lorg/bouncycastle/crypto/params/GOST3410Parameters;
      10: return

  public org.bouncycastle.crypto.params.GOST3410Parameters getParameters();
    Code:
       0: aload_0
       1: getfield      #14                 // Field params:Lorg/bouncycastle/crypto/params/GOST3410Parameters;
       4: areturn
}
