public class org.bouncycastle.crypto.params.SRP6GroupParameters {
  private java.math.BigInteger N;

  private java.math.BigInteger g;

  public org.bouncycastle.crypto.params.SRP6GroupParameters(java.math.BigInteger, java.math.BigInteger);
    Code:
       0: aload_0
       1: invokespecial #19                 // Method java/lang/Object."<init>":()V
       4: aload_0
       5: aload_1
       6: putfield      #17                 // Field N:Ljava/math/BigInteger;
       9: aload_0
      10: aload_2
      11: putfield      #18                 // Field g:Ljava/math/BigInteger;
      14: return

  public java.math.BigInteger getG();
    Code:
       0: aload_0
       1: getfield      #18                 // Field g:Ljava/math/BigInteger;
       4: areturn

  public java.math.BigInteger getN();
    Code:
       0: aload_0
       1: getfield      #17                 // Field N:Ljava/math/BigInteger;
       4: areturn
}
