Compiled from "LocaleType.java"
public class org.hibernate.type.LocaleType extends org.hibernate.type.AbstractSingleColumnStandardBasicType<java.util.Locale> implements org.hibernate.type.LiteralType<java.util.Locale> {
  public static final org.hibernate.type.LocaleType INSTANCE;

  public org.hibernate.type.LocaleType();
    Code:
       0: aload_0
       1: getstatic     #1                  // Field org/hibernate/type/descriptor/sql/VarcharTypeDescriptor.INSTANCE:Lorg/hibernate/type/descriptor/sql/VarcharTypeDescriptor;
       4: getstatic     #2                  // Field org/hibernate/type/descriptor/java/LocaleTypeDescriptor.INSTANCE:Lorg/hibernate/type/descriptor/java/LocaleTypeDescriptor;
       7: invokespecial #3                  // Method org/hibernate/type/AbstractSingleColumnStandardBasicType."<init>":(Lorg/hibernate/type/descriptor/sql/SqlTypeDescriptor;Lorg/hibernate/type/descriptor/java/JavaTypeDescriptor;)V
      10: return

  public java.lang.String getName();
    Code:
       0: ldc           #4                  // String locale
       2: areturn

  protected boolean registerUnderJavaType();
    Code:
       0: iconst_1
       1: ireturn

  public java.lang.String objectToSQLString(java.util.Locale, org.hibernate.dialect.Dialect) throws java.lang.Exception;
    Code:
       0: getstatic     #5                  // Field org/hibernate/type/StringType.INSTANCE:Lorg/hibernate/type/StringType;
       3: aload_0
       4: aload_1
       5: invokevirtual #6                  // Method toString:(Ljava/lang/Object;)Ljava/lang/String;
       8: aload_2
       9: invokevirtual #7                  // Method org/hibernate/type/StringType.objectToSQLString:(Ljava/lang/String;Lorg/hibernate/dialect/Dialect;)Ljava/lang/String;
      12: areturn

  public java.lang.String objectToSQLString(java.lang.Object, org.hibernate.dialect.Dialect) throws java.lang.Exception;
    Code:
       0: aload_0
       1: aload_1
       2: checkcast     #8                  // class java/util/Locale
       5: aload_2
       6: invokevirtual #9                  // Method objectToSQLString:(Ljava/util/Locale;Lorg/hibernate/dialect/Dialect;)Ljava/lang/String;
       9: areturn

  static {};
    Code:
       0: new           #10                 // class org/hibernate/type/LocaleType
       3: dup
       4: invokespecial #11                 // Method "<init>":()V
       7: putstatic     #12                 // Field INSTANCE:Lorg/hibernate/type/LocaleType;
      10: return
}
