Compiled from "ClusteringModelEvaluator.java"
final class org.jpmml.evaluator.clustering.ClusteringModelEvaluator$2 extends com.google.common.cache.CacheLoader<org.dmg.pmml.clustering.Cluster, java.util.List<org.jpmml.evaluator.FieldValue>> {
  org.jpmml.evaluator.clustering.ClusteringModelEvaluator$2();
    Code:
       0: aload_0
       1: invokespecial #1                  // Method com/google/common/cache/CacheLoader."<init>":()V
       4: return

  public java.util.List<org.jpmml.evaluator.FieldValue> load(org.dmg.pmml.clustering.Cluster);
    Code:
       0: aload_1
       1: invokevirtual #2                  // Method org/dmg/pmml/clustering/Cluster.getArray:()Lorg/dmg/pmml/Array;
       4: astore_2
       5: aload_2
       6: invokestatic  #3                  // Method org/jpmml/evaluator/ArrayUtil.asNumberList:(Lorg/dmg/pmml/Array;)Ljava/util/List;
       9: astore_3
      10: aload_3
      11: invokedynamic #4,  0              // InvokeDynamic #0:apply:()Lcom/google/common/base/Function;
      16: invokestatic  #5                  // Method com/google/common/collect/Lists.transform:(Ljava/util/List;Lcom/google/common/base/Function;)Ljava/util/List;
      19: invokestatic  #6                  // Method com/google/common/collect/ImmutableList.copyOf:(Ljava/util/Collection;)Lcom/google/common/collect/ImmutableList;
      22: areturn

  public java.lang.Object load(java.lang.Object) throws java.lang.Exception;
    Code:
       0: aload_0
       1: aload_1
       2: checkcast     #7                  // class org/dmg/pmml/clustering/Cluster
       5: invokevirtual #8                  // Method load:(Lorg/dmg/pmml/clustering/Cluster;)Ljava/util/List;
       8: areturn

  private static org.jpmml.evaluator.FieldValue lambda$load$0(java.lang.Number);
    Code:
       0: getstatic     #9                  // Field org/jpmml/evaluator/TypeInfos.CONTINUOUS_DOUBLE:Lorg/jpmml/evaluator/TypeInfo;
       3: aload_0
       4: invokestatic  #10                 // Method org/jpmml/evaluator/FieldValueUtil.create:(Lorg/jpmml/evaluator/TypeInfo;Ljava/lang/Object;)Lorg/jpmml/evaluator/FieldValue;
       7: areturn
}
