Compiled from "NaiveBayesModelEvaluator.java"
public class org.jpmml.evaluator.naive_bayes.NaiveBayesModelEvaluator extends org.jpmml.evaluator.ModelEvaluator<org.dmg.pmml.naive_bayes.NaiveBayesModel> {
  private transient java.util.List<org.dmg.pmml.naive_bayes.BayesInput> bayesInputs;

  private transient java.util.Map<org.dmg.pmml.FieldName, java.util.Map<java.lang.Object, java.lang.Number>> fieldCountSums;

  private static final com.google.common.cache.LoadingCache<org.dmg.pmml.naive_bayes.NaiveBayesModel, java.util.List<org.dmg.pmml.naive_bayes.BayesInput>> bayesInputCache;

  private static final com.google.common.cache.LoadingCache<org.dmg.pmml.naive_bayes.NaiveBayesModel, java.util.Map<org.dmg.pmml.FieldName, java.util.Map<java.lang.Object, java.lang.Number>>> fieldCountSumCache;

  public org.jpmml.evaluator.naive_bayes.NaiveBayesModelEvaluator(org.dmg.pmml.PMML);
    Code:
       0: aload_0
       1: aload_1
       2: aload_1
       3: ldc           #3                  // class org/dmg/pmml/naive_bayes/NaiveBayesModel
       5: invokestatic  #4                  // Method org/jpmml/evaluator/PMMLUtil.findModel:(Lorg/dmg/pmml/PMML;Ljava/lang/Class;)Lorg/dmg/pmml/Model;
       8: checkcast     #3                  // class org/dmg/pmml/naive_bayes/NaiveBayesModel
      11: invokespecial #5                  // Method "<init>":(Lorg/dmg/pmml/PMML;Lorg/dmg/pmml/naive_bayes/NaiveBayesModel;)V
      14: return

  public org.jpmml.evaluator.naive_bayes.NaiveBayesModelEvaluator(org.dmg.pmml.PMML, org.dmg.pmml.naive_bayes.NaiveBayesModel);
    Code:
       0: aload_0
       1: aload_1
       2: aload_2
       3: invokespecial #6                  // Method org/jpmml/evaluator/ModelEvaluator."<init>":(Lorg/dmg/pmml/PMML;Lorg/dmg/pmml/Model;)V
       6: aload_0
       7: aconst_null
       8: putfield      #7                  // Field bayesInputs:Ljava/util/List;
      11: aload_0
      12: aconst_null
      13: putfield      #8                  // Field fieldCountSums:Ljava/util/Map;
      16: aload_2
      17: invokevirtual #9                  // Method org/dmg/pmml/naive_bayes/NaiveBayesModel.getBayesInputs:()Lorg/dmg/pmml/naive_bayes/BayesInputs;
      20: astore_3
      21: aload_3
      22: ifnonnull     37
      25: new           #10                 // class org/jpmml/evaluator/MissingElementException
      28: dup
      29: aload_2
      30: getstatic     #11                 // Field org/dmg/pmml/naive_bayes/PMMLElements.NAIVEBAYESMODEL_BAYESINPUTS:Ljava/lang/reflect/Field;
      33: invokespecial #12                 // Method org/jpmml/evaluator/MissingElementException."<init>":(Lorg/dmg/pmml/PMMLObject;Ljava/lang/reflect/Field;)V
      36: athrow
      37: aload_3
      38: invokevirtual #13                 // Method org/dmg/pmml/naive_bayes/BayesInputs.hasBayesInputs:()Z
      41: ifne          63
      44: aload_3
      45: invokevirtual #14                 // Method org/dmg/pmml/naive_bayes/BayesInputs.hasExtensions:()Z
      48: ifne          63
      51: new           #10                 // class org/jpmml/evaluator/MissingElementException
      54: dup
      55: aload_3
      56: getstatic     #15                 // Field org/dmg/pmml/naive_bayes/PMMLElements.BAYESINPUTS_BAYESINPUTS:Ljava/lang/reflect/Field;
      59: invokespecial #12                 // Method org/jpmml/evaluator/MissingElementException."<init>":(Lorg/dmg/pmml/PMMLObject;Ljava/lang/reflect/Field;)V
      62: athrow
      63: aload_2
      64: invokevirtual #16                 // Method org/dmg/pmml/naive_bayes/NaiveBayesModel.getBayesOutput:()Lorg/dmg/pmml/naive_bayes/BayesOutput;
      67: astore        4
      69: aload         4
      71: ifnonnull     86
      74: new           #10                 // class org/jpmml/evaluator/MissingElementException
      77: dup
      78: aload_2
      79: getstatic     #17                 // Field org/dmg/pmml/naive_bayes/PMMLElements.NAIVEBAYESMODEL_BAYESOUTPUT:Ljava/lang/reflect/Field;
      82: invokespecial #12                 // Method org/jpmml/evaluator/MissingElementException."<init>":(Lorg/dmg/pmml/PMMLObject;Ljava/lang/reflect/Field;)V
      85: athrow
      86: aload         4
      88: invokevirtual #18                 // Method org/dmg/pmml/naive_bayes/BayesOutput.getTargetValueCounts:()Lorg/dmg/pmml/naive_bayes/TargetValueCounts;
      91: astore        5
      93: aload         5
      95: ifnonnull     111
      98: new           #10                 // class org/jpmml/evaluator/MissingElementException
     101: dup
     102: aload         4
     104: getstatic     #19                 // Field org/dmg/pmml/naive_bayes/PMMLElements.BAYESOUTPUT_TARGETVALUECOUNTS:Ljava/lang/reflect/Field;
     107: invokespecial #12                 // Method org/jpmml/evaluator/MissingElementException."<init>":(Lorg/dmg/pmml/PMMLObject;Ljava/lang/reflect/Field;)V
     110: athrow
     111: aload         5
     113: invokevirtual #20                 // Method org/dmg/pmml/naive_bayes/TargetValueCounts.hasTargetValueCounts:()Z
     116: ifne          132
     119: new           #10                 // class org/jpmml/evaluator/MissingElementException
     122: dup
     123: aload         5
     125: getstatic     #21                 // Field org/dmg/pmml/naive_bayes/PMMLElements.TARGETVALUECOUNTS_TARGETVALUECOUNTS:Ljava/lang/reflect/Field;
     128: invokespecial #12                 // Method org/jpmml/evaluator/MissingElementException."<init>":(Lorg/dmg/pmml/PMMLObject;Ljava/lang/reflect/Field;)V
     131: athrow
     132: return

  public java.lang.String getSummary();
    Code:
       0: ldc           #22                 // String Naive Bayes model
       2: areturn

  protected <V extends java.lang.Number> java.util.Map<org.dmg.pmml.FieldName, ? extends org.jpmml.evaluator.Classification<?, V>> evaluateClassification(org.jpmml.evaluator.ValueFactory<V>, org.jpmml.evaluator.EvaluationContext);
    Code:
       0: aload_0
       1: invokevirtual #23                 // Method getModel:()Lorg/dmg/pmml/Model;
       4: checkcast     #3                  // class org/dmg/pmml/naive_bayes/NaiveBayesModel
       7: astore_3
       8: aload_3
       9: invokevirtual #16                 // Method org/dmg/pmml/naive_bayes/NaiveBayesModel.getBayesOutput:()Lorg/dmg/pmml/naive_bayes/BayesOutput;
      12: astore        4
      14: aload_0
      15: invokevirtual #24                 // Method getTargetField:()Lorg/jpmml/evaluator/TargetField;
      18: astore        5
      20: aload         4
      22: invokevirtual #25                 // Method org/dmg/pmml/naive_bayes/BayesOutput.getField:()Lorg/dmg/pmml/FieldName;
      25: astore        6
      27: aload         6
      29: ifnonnull     45
      32: new           #26                 // class org/jpmml/evaluator/MissingAttributeException
      35: dup
      36: aload         4
      38: getstatic     #27                 // Field org/dmg/pmml/naive_bayes/PMMLAttributes.BAYESOUTPUT_FIELD:Ljava/lang/reflect/Field;
      41: invokespecial #28                 // Method org/jpmml/evaluator/MissingAttributeException."<init>":(Lorg/dmg/pmml/PMMLObject;Ljava/lang/reflect/Field;)V
      44: athrow
      45: aload         6
      47: ifnull        78
      50: aload         5
      52: invokevirtual #29                 // Method org/jpmml/evaluator/TargetField.getFieldName:()Lorg/dmg/pmml/FieldName;
      55: aload         6
      57: invokestatic  #30                 // Method java/util/Objects.equals:(Ljava/lang/Object;Ljava/lang/Object;)Z
      60: ifne          78
      63: new           #31                 // class org/jpmml/evaluator/InvalidAttributeException
      66: dup
      67: aload         4
      69: getstatic     #27                 // Field org/dmg/pmml/naive_bayes/PMMLAttributes.BAYESOUTPUT_FIELD:Ljava/lang/reflect/Field;
      72: aload         6
      74: invokespecial #32                 // Method org/jpmml/evaluator/InvalidAttributeException."<init>":(Lorg/dmg/pmml/PMMLObject;Ljava/lang/reflect/Field;Ljava/lang/Object;)V
      77: athrow
      78: new           #33                 // class org/jpmml/evaluator/naive_bayes/NaiveBayesModelEvaluator$1
      81: dup
      82: aload_0
      83: aload_1
      84: invokespecial #34                 // Method org/jpmml/evaluator/naive_bayes/NaiveBayesModelEvaluator$1."<init>":(Lorg/jpmml/evaluator/naive_bayes/NaiveBayesModelEvaluator;Lorg/jpmml/evaluator/ValueFactory;)V
      87: astore        7
      89: aload         4
      91: invokestatic  #35                 // Method getTargetValueCounts:(Lorg/dmg/pmml/naive_bayes/BayesOutput;)Lorg/dmg/pmml/naive_bayes/TargetValueCounts;
      94: astore        8
      96: aload_0
      97: aload         7
      99: aload         8
     101: invokespecial #36                 // Method calculatePriorProbabilities:(Lorg/jpmml/evaluator/naive_bayes/ProbabilityMap;Lorg/dmg/pmml/naive_bayes/TargetValueCounts;)V
     104: aload_3
     105: invokevirtual #37                 // Method org/dmg/pmml/naive_bayes/NaiveBayesModel.getThreshold:()Ljava/lang/Number;
     108: astore        8
     110: aload         8
     112: ifnonnull     127
     115: new           #26                 // class org/jpmml/evaluator/MissingAttributeException
     118: dup
     119: aload_3
     120: getstatic     #38                 // Field org/dmg/pmml/naive_bayes/PMMLAttributes.NAIVEBAYESMODEL_THRESHOLD:Ljava/lang/reflect/Field;
     123: invokespecial #28                 // Method org/jpmml/evaluator/MissingAttributeException."<init>":(Lorg/dmg/pmml/PMMLObject;Ljava/lang/reflect/Field;)V
     126: athrow
     127: aload_0
     128: invokevirtual #39                 // Method getFieldCountSums:()Ljava/util/Map;
     131: astore        9
     133: aload_0
     134: invokevirtual #40                 // Method getBayesInputs:()Ljava/util/List;
     137: astore        10
     139: aload         10
     141: invokeinterface #41,  1           // InterfaceMethod java/util/List.iterator:()Ljava/util/Iterator;
     146: astore        11
     148: aload         11
     150: invokeinterface #42,  1           // InterfaceMethod java/util/Iterator.hasNext:()Z
     155: ifeq          317
     158: aload         11
     160: invokeinterface #43,  1           // InterfaceMethod java/util/Iterator.next:()Ljava/lang/Object;
     165: checkcast     #44                 // class org/dmg/pmml/naive_bayes/BayesInput
     168: astore        12
     170: aload         12
     172: invokevirtual #45                 // Method org/dmg/pmml/naive_bayes/BayesInput.getField:()Lorg/dmg/pmml/FieldName;
     175: astore        13
     177: aload         13
     179: ifnonnull     195
     182: new           #26                 // class org/jpmml/evaluator/MissingAttributeException
     185: dup
     186: aload         12
     188: getstatic     #46                 // Field org/dmg/pmml/naive_bayes/PMMLAttributes.BAYESINPUT_FIELD:Ljava/lang/reflect/Field;
     191: invokespecial #28                 // Method org/jpmml/evaluator/MissingAttributeException."<init>":(Lorg/dmg/pmml/PMMLObject;Ljava/lang/reflect/Field;)V
     194: athrow
     195: aload_2
     196: aload         13
     198: invokevirtual #47                 // Method org/jpmml/evaluator/EvaluationContext.evaluate:(Lorg/dmg/pmml/FieldName;)Lorg/jpmml/evaluator/FieldValue;
     201: astore        14
     203: aload         14
     205: invokestatic  #48                 // Method org/jpmml/evaluator/FieldValueUtil.isMissing:(Lorg/jpmml/evaluator/FieldValue;)Z
     208: ifeq          214
     211: goto          148
     214: aload         12
     216: invokestatic  #49                 // Method getTargetValueStats:(Lorg/dmg/pmml/naive_bayes/BayesInput;)Lorg/dmg/pmml/naive_bayes/TargetValueStats;
     219: astore        15
     221: aload         15
     223: ifnull        241
     226: aload_0
     227: aload         7
     229: aload         15
     231: aload         8
     233: aload         14
     235: invokespecial #50                 // Method calculateContinuousProbabilities:(Lorg/jpmml/evaluator/naive_bayes/ProbabilityMap;Lorg/dmg/pmml/naive_bayes/TargetValueStats;Ljava/lang/Number;Lorg/jpmml/evaluator/FieldValue;)V
     238: goto          148
     241: aload         12
     243: invokevirtual #51                 // Method org/dmg/pmml/naive_bayes/BayesInput.getDerivedField:()Lorg/dmg/pmml/DerivedField;
     246: astore        16
     248: aload         16
     250: ifnull        274
     253: aload_0
     254: aload         16
     256: aload         14
     258: invokespecial #52                 // Method discretize:(Lorg/dmg/pmml/DerivedField;Lorg/jpmml/evaluator/FieldValue;)Lorg/jpmml/evaluator/FieldValue;
     261: astore        14
     263: aload         14
     265: invokestatic  #48                 // Method org/jpmml/evaluator/FieldValueUtil.isMissing:(Lorg/jpmml/evaluator/FieldValue;)Z
     268: ifeq          274
     271: goto          148
     274: aload         9
     276: aload         13
     278: invokeinterface #53,  2           // InterfaceMethod java/util/Map.get:(Ljava/lang/Object;)Ljava/lang/Object;
     283: checkcast     #54                 // class java/util/Map
     286: astore        17
     288: aload         12
     290: aload         14
     292: invokestatic  #55                 // Method getTargetValueCounts:(Lorg/dmg/pmml/naive_bayes/BayesInput;Lorg/jpmml/evaluator/FieldValue;)Lorg/dmg/pmml/naive_bayes/TargetValueCounts;
     295: astore        18
     297: aload         18
     299: ifnull        314
     302: aload_0
     303: aload         7
     305: aload         18
     307: aload         8
     309: aload         17
     311: invokespecial #56                 // Method calculateDiscreteProbabilities:(Lorg/jpmml/evaluator/naive_bayes/ProbabilityMap;Lorg/dmg/pmml/naive_bayes/TargetValueCounts;Ljava/lang/Number;Ljava/util/Map;)V
     314: goto          148
     317: aload         7
     319: invokestatic  #57                 // Method org/jpmml/evaluator/ValueUtil.normalizeSoftMax:(Ljava/lang/Iterable;)V
     322: new           #58                 // class org/jpmml/evaluator/ProbabilityDistribution
     325: dup
     326: aload         7
     328: invokespecial #59                 // Method org/jpmml/evaluator/ProbabilityDistribution."<init>":(Lorg/jpmml/evaluator/ValueMap;)V
     331: astore        11
     333: aload         5
     335: aload         11
     337: invokestatic  #60                 // Method org/jpmml/evaluator/TargetUtil.evaluateClassification:(Lorg/jpmml/evaluator/TargetField;Lorg/jpmml/evaluator/Classification;)Ljava/util/Map;
     340: areturn

  private org.jpmml.evaluator.FieldValue discretize(org.dmg.pmml.DerivedField, org.jpmml.evaluator.FieldValue);
    Code:
       0: aload_1
       1: invokestatic  #61                 // Method org/jpmml/evaluator/ExpressionUtil.ensureExpression:(Lorg/dmg/pmml/PMMLObject;)Lorg/dmg/pmml/Expression;
       4: astore_3
       5: aload_3
       6: instanceof    #62                 // class org/dmg/pmml/Discretize
       9: ifeq          42
      12: aload_3
      13: checkcast     #62                 // class org/dmg/pmml/Discretize
      16: astore        4
      18: aload         4
      20: aload_2
      21: invokestatic  #63                 // Method org/jpmml/evaluator/DiscretizationUtil.discretize:(Lorg/dmg/pmml/Discretize;Lorg/jpmml/evaluator/FieldValue;)Lorg/jpmml/evaluator/FieldValue;
      24: astore_2
      25: aload_2
      26: invokestatic  #48                 // Method org/jpmml/evaluator/FieldValueUtil.isMissing:(Lorg/jpmml/evaluator/FieldValue;)Z
      29: ifeq          36
      32: getstatic     #64                 // Field org/jpmml/evaluator/FieldValues.MISSING_VALUE:Lorg/jpmml/evaluator/FieldValue;
      35: areturn
      36: aload_2
      37: aload_1
      38: invokevirtual #65                 // Method org/jpmml/evaluator/FieldValue.cast:(Lorg/dmg/pmml/HasType;)Lorg/jpmml/evaluator/FieldValue;
      41: areturn
      42: new           #66                 // class org/jpmml/evaluator/MisplacedElementException
      45: dup
      46: aload_3
      47: invokespecial #67                 // Method org/jpmml/evaluator/MisplacedElementException."<init>":(Lorg/dmg/pmml/PMMLObject;)V
      50: athrow

  private void calculateContinuousProbabilities(org.jpmml.evaluator.naive_bayes.ProbabilityMap<java.lang.Object, ?>, org.dmg.pmml.naive_bayes.TargetValueStats, java.lang.Number, org.jpmml.evaluator.FieldValue);
    Code:
       0: aload         4
       2: invokevirtual #68                 // Method org/jpmml/evaluator/FieldValue.asNumber:()Ljava/lang/Number;
       5: astore        5
       7: aload_2
       8: invokevirtual #69                 // Method org/dmg/pmml/naive_bayes/TargetValueStats.iterator:()Ljava/util/Iterator;
      11: astore        6
      13: aload         6
      15: invokeinterface #42,  1           // InterfaceMethod java/util/Iterator.hasNext:()Z
      20: ifeq          175
      23: aload         6
      25: invokeinterface #43,  1           // InterfaceMethod java/util/Iterator.next:()Ljava/lang/Object;
      30: checkcast     #70                 // class org/dmg/pmml/naive_bayes/TargetValueStat
      33: astore        7
      35: aload         7
      37: invokevirtual #71                 // Method org/dmg/pmml/naive_bayes/TargetValueStat.getValue:()Ljava/lang/Object;
      40: astore        8
      42: aload         8
      44: ifnonnull     60
      47: new           #26                 // class org/jpmml/evaluator/MissingAttributeException
      50: dup
      51: aload         7
      53: getstatic     #72                 // Field org/dmg/pmml/naive_bayes/PMMLAttributes.TARGETVALUESTAT_VALUE:Ljava/lang/reflect/Field;
      56: invokespecial #28                 // Method org/jpmml/evaluator/MissingAttributeException."<init>":(Lorg/dmg/pmml/PMMLObject;Ljava/lang/reflect/Field;)V
      59: athrow
      60: aload         7
      62: invokevirtual #73                 // Method org/dmg/pmml/naive_bayes/TargetValueStat.getContinuousDistribution:()Lorg/dmg/pmml/ContinuousDistribution;
      65: astore        9
      67: aload         9
      69: ifnonnull     111
      72: new           #10                 // class org/jpmml/evaluator/MissingElementException
      75: dup
      76: new           #74                 // class java/lang/StringBuilder
      79: dup
      80: invokespecial #75                 // Method java/lang/StringBuilder."<init>":()V
      83: aload         7
      85: invokevirtual #76                 // Method java/lang/Object.getClass:()Ljava/lang/Class;
      88: invokestatic  #77                 // Method org/jpmml/model/XPathUtil.formatElement:(Ljava/lang/Class;)Ljava/lang/String;
      91: invokevirtual #78                 // Method java/lang/StringBuilder.append:(Ljava/lang/String;)Ljava/lang/StringBuilder;
      94: ldc           #79                 // String /<ContinuousDistribution>
      96: invokevirtual #78                 // Method java/lang/StringBuilder.append:(Ljava/lang/String;)Ljava/lang/StringBuilder;
      99: invokevirtual #80                 // Method java/lang/StringBuilder.toString:()Ljava/lang/String;
     102: invokestatic  #81                 // Method org/jpmml/evaluator/MissingElementException.formatMessage:(Ljava/lang/String;)Ljava/lang/String;
     105: aload         7
     107: invokespecial #82                 // Method org/jpmml/evaluator/MissingElementException."<init>":(Ljava/lang/String;Lorg/dmg/pmml/PMMLObject;)V
     110: athrow
     111: aload         9
     113: instanceof    #83                 // class org/dmg/pmml/GaussianDistribution
     116: ifne          127
     119: aload         9
     121: instanceof    #84                 // class org/dmg/pmml/PoissonDistribution
     124: ifeq          142
     127: aload         9
     129: aload         5
     131: invokestatic  #85                 // Method org/jpmml/evaluator/DistributionUtil.probability:(Lorg/dmg/pmml/ContinuousDistribution;Ljava/lang/Number;)D
     134: invokestatic  #86                 // Method java/lang/Double.valueOf:(D)Ljava/lang/Double;
     137: astore        10
     139: goto          152
     142: new           #66                 // class org/jpmml/evaluator/MisplacedElementException
     145: dup
     146: aload         9
     148: invokespecial #67                 // Method org/jpmml/evaluator/MisplacedElementException."<init>":(Lorg/dmg/pmml/PMMLObject;)V
     151: athrow
     152: aload         10
     154: aload_3
     155: invokestatic  #87                 // Method org/jpmml/evaluator/NumberUtil.compare:(Ljava/lang/Number;Ljava/lang/Number;)I
     158: ifge          164
     161: aload_3
     162: astore        10
     164: aload_1
     165: aload         8
     167: aload         10
     169: invokevirtual #88                 // Method org/jpmml/evaluator/naive_bayes/ProbabilityMap.multiply:(Ljava/lang/Object;Ljava/lang/Number;)V
     172: goto          13
     175: return

  private void calculateDiscreteProbabilities(org.jpmml.evaluator.naive_bayes.ProbabilityMap<java.lang.Object, ?>, org.dmg.pmml.naive_bayes.TargetValueCounts, java.lang.Number, java.util.Map<?, java.lang.Number>);
    Code:
       0: aload_2
       1: invokevirtual #89                 // Method org/dmg/pmml/naive_bayes/TargetValueCounts.iterator:()Ljava/util/Iterator;
       4: astore        5
       6: aload         5
       8: invokeinterface #42,  1           // InterfaceMethod java/util/Iterator.hasNext:()Z
      13: ifeq          135
      16: aload         5
      18: invokeinterface #43,  1           // InterfaceMethod java/util/Iterator.next:()Ljava/lang/Object;
      23: checkcast     #90                 // class org/dmg/pmml/naive_bayes/TargetValueCount
      26: astore        6
      28: aload         6
      30: invokevirtual #91                 // Method org/dmg/pmml/naive_bayes/TargetValueCount.getValue:()Ljava/lang/Object;
      33: astore        7
      35: aload         7
      37: ifnonnull     53
      40: new           #26                 // class org/jpmml/evaluator/MissingAttributeException
      43: dup
      44: aload         6
      46: getstatic     #92                 // Field org/dmg/pmml/naive_bayes/PMMLAttributes.TARGETVALUECOUNT_VALUE:Ljava/lang/reflect/Field;
      49: invokespecial #28                 // Method org/jpmml/evaluator/MissingAttributeException."<init>":(Lorg/dmg/pmml/PMMLObject;Ljava/lang/reflect/Field;)V
      52: athrow
      53: aload         6
      55: invokevirtual #93                 // Method org/dmg/pmml/naive_bayes/TargetValueCount.getCount:()Ljava/lang/Number;
      58: astore        8
      60: aload         8
      62: ifnonnull     78
      65: new           #26                 // class org/jpmml/evaluator/MissingAttributeException
      68: dup
      69: aload         6
      71: getstatic     #94                 // Field org/dmg/pmml/naive_bayes/PMMLAttributes.TARGETVALUECOUNT_COUNT:Ljava/lang/reflect/Field;
      74: invokespecial #28                 // Method org/jpmml/evaluator/MissingAttributeException."<init>":(Lorg/dmg/pmml/PMMLObject;Ljava/lang/reflect/Field;)V
      77: athrow
      78: aload         8
      80: getstatic     #95                 // Field org/apache/commons/math3/util/Precision.EPSILON:D
      83: invokestatic  #96                 // Method org/jpmml/evaluator/VerificationUtil.isZero:(Ljava/lang/Number;D)Z
      86: ifeq          95
      89: aload_3
      90: astore        9
      92: goto          124
      95: aload         4
      97: aload         7
      99: invokeinterface #53,  2           // InterfaceMethod java/util/Map.get:(Ljava/lang/Object;)Ljava/lang/Object;
     104: checkcast     #97                 // class java/lang/Number
     107: astore        10
     109: getstatic     #98                 // Field org/jpmml/evaluator/Functions.DIVIDE:Lorg/jpmml/evaluator/functions/ArithmeticFunction;
     112: aload         8
     114: aload         10
     116: invokestatic  #99                 // Method org/jpmml/evaluator/NumberUtil.asDouble:(Ljava/lang/Number;)Ljava/lang/Double;
     119: invokevirtual #100                // Method org/jpmml/evaluator/functions/ArithmeticFunction.evaluate:(Ljava/lang/Number;Ljava/lang/Number;)Ljava/lang/Number;
     122: astore        9
     124: aload_1
     125: aload         7
     127: aload         9
     129: invokevirtual #88                 // Method org/jpmml/evaluator/naive_bayes/ProbabilityMap.multiply:(Ljava/lang/Object;Ljava/lang/Number;)V
     132: goto          6
     135: return

  private void calculatePriorProbabilities(org.jpmml.evaluator.naive_bayes.ProbabilityMap<java.lang.Object, ?>, org.dmg.pmml.naive_bayes.TargetValueCounts);
    Code:
       0: aload_2
       1: invokevirtual #89                 // Method org/dmg/pmml/naive_bayes/TargetValueCounts.iterator:()Ljava/util/Iterator;
       4: astore_3
       5: aload_3
       6: invokeinterface #42,  1           // InterfaceMethod java/util/Iterator.hasNext:()Z
      11: ifeq          90
      14: aload_3
      15: invokeinterface #43,  1           // InterfaceMethod java/util/Iterator.next:()Ljava/lang/Object;
      20: checkcast     #90                 // class org/dmg/pmml/naive_bayes/TargetValueCount
      23: astore        4
      25: aload         4
      27: invokevirtual #91                 // Method org/dmg/pmml/naive_bayes/TargetValueCount.getValue:()Ljava/lang/Object;
      30: astore        5
      32: aload         5
      34: ifnonnull     50
      37: new           #26                 // class org/jpmml/evaluator/MissingAttributeException
      40: dup
      41: aload         4
      43: getstatic     #92                 // Field org/dmg/pmml/naive_bayes/PMMLAttributes.TARGETVALUECOUNT_VALUE:Ljava/lang/reflect/Field;
      46: invokespecial #28                 // Method org/jpmml/evaluator/MissingAttributeException."<init>":(Lorg/dmg/pmml/PMMLObject;Ljava/lang/reflect/Field;)V
      49: athrow
      50: aload         4
      52: invokevirtual #93                 // Method org/dmg/pmml/naive_bayes/TargetValueCount.getCount:()Ljava/lang/Number;
      55: astore        6
      57: aload         6
      59: ifnonnull     75
      62: new           #26                 // class org/jpmml/evaluator/MissingAttributeException
      65: dup
      66: aload         4
      68: getstatic     #94                 // Field org/dmg/pmml/naive_bayes/PMMLAttributes.TARGETVALUECOUNT_COUNT:Ljava/lang/reflect/Field;
      71: invokespecial #28                 // Method org/jpmml/evaluator/MissingAttributeException."<init>":(Lorg/dmg/pmml/PMMLObject;Ljava/lang/reflect/Field;)V
      74: athrow
      75: aload         6
      77: astore        7
      79: aload_1
      80: aload         5
      82: aload         7
      84: invokevirtual #88                 // Method org/jpmml/evaluator/naive_bayes/ProbabilityMap.multiply:(Ljava/lang/Object;Ljava/lang/Number;)V
      87: goto          5
      90: return

  protected java.util.List<org.dmg.pmml.naive_bayes.BayesInput> getBayesInputs();
    Code:
       0: aload_0
       1: getfield      #7                  // Field bayesInputs:Ljava/util/List;
       4: ifnonnull     21
       7: aload_0
       8: aload_0
       9: getstatic     #101                // Field bayesInputCache:Lcom/google/common/cache/LoadingCache;
      12: invokevirtual #102                // Method getValue:(Lcom/google/common/cache/LoadingCache;)Ljava/lang/Object;
      15: checkcast     #103                // class java/util/List
      18: putfield      #7                  // Field bayesInputs:Ljava/util/List;
      21: aload_0
      22: getfield      #7                  // Field bayesInputs:Ljava/util/List;
      25: areturn

  protected java.util.Map<org.dmg.pmml.FieldName, java.util.Map<java.lang.Object, java.lang.Number>> getFieldCountSums();
    Code:
       0: aload_0
       1: getfield      #8                  // Field fieldCountSums:Ljava/util/Map;
       4: ifnonnull     21
       7: aload_0
       8: aload_0
       9: getstatic     #104                // Field fieldCountSumCache:Lcom/google/common/cache/LoadingCache;
      12: invokevirtual #102                // Method getValue:(Lcom/google/common/cache/LoadingCache;)Ljava/lang/Object;
      15: checkcast     #54                 // class java/util/Map
      18: putfield      #8                  // Field fieldCountSums:Ljava/util/Map;
      21: aload_0
      22: getfield      #8                  // Field fieldCountSums:Ljava/util/Map;
      25: areturn

  private static java.util.Map<org.dmg.pmml.FieldName, java.util.Map<java.lang.Object, java.lang.Number>> calculateFieldCountSums(org.dmg.pmml.naive_bayes.NaiveBayesModel);
    Code:
       0: new           #105                // class java/util/LinkedHashMap
       3: dup
       4: invokespecial #106                // Method java/util/LinkedHashMap."<init>":()V
       7: astore_1
       8: aload_0
       9: getstatic     #101                // Field bayesInputCache:Lcom/google/common/cache/LoadingCache;
      12: invokestatic  #107                // Method org/jpmml/evaluator/CacheUtil.getValue:(Lorg/dmg/pmml/PMMLObject;Lcom/google/common/cache/LoadingCache;)Ljava/lang/Object;
      15: checkcast     #103                // class java/util/List
      18: astore_2
      19: aload_2
      20: invokeinterface #41,  1           // InterfaceMethod java/util/List.iterator:()Ljava/util/Iterator;
      25: astore_3
      26: aload_3
      27: invokeinterface #42,  1           // InterfaceMethod java/util/Iterator.hasNext:()Z
      32: ifeq          256
      35: aload_3
      36: invokeinterface #43,  1           // InterfaceMethod java/util/Iterator.next:()Ljava/lang/Object;
      41: checkcast     #44                 // class org/dmg/pmml/naive_bayes/BayesInput
      44: astore        4
      46: aload         4
      48: invokevirtual #45                 // Method org/dmg/pmml/naive_bayes/BayesInput.getField:()Lorg/dmg/pmml/FieldName;
      51: astore        5
      53: new           #105                // class java/util/LinkedHashMap
      56: dup
      57: invokespecial #106                // Method java/util/LinkedHashMap."<init>":()V
      60: astore        6
      62: aload         4
      64: invokevirtual #108                // Method org/dmg/pmml/naive_bayes/BayesInput.getPairCounts:()Ljava/util/List;
      67: astore        7
      69: aload         7
      71: invokeinterface #41,  1           // InterfaceMethod java/util/List.iterator:()Ljava/util/Iterator;
      76: astore        8
      78: aload         8
      80: invokeinterface #42,  1           // InterfaceMethod java/util/Iterator.hasNext:()Z
      85: ifeq          242
      88: aload         8
      90: invokeinterface #43,  1           // InterfaceMethod java/util/Iterator.next:()Ljava/lang/Object;
      95: checkcast     #109                // class org/dmg/pmml/naive_bayes/PairCounts
      98: astore        9
     100: aload         9
     102: invokevirtual #110                // Method org/dmg/pmml/naive_bayes/PairCounts.getTargetValueCounts:()Lorg/dmg/pmml/naive_bayes/TargetValueCounts;
     105: astore        10
     107: aload         10
     109: invokevirtual #89                 // Method org/dmg/pmml/naive_bayes/TargetValueCounts.iterator:()Ljava/util/Iterator;
     112: astore        11
     114: aload         11
     116: invokeinterface #42,  1           // InterfaceMethod java/util/Iterator.hasNext:()Z
     121: ifeq          239
     124: aload         11
     126: invokeinterface #43,  1           // InterfaceMethod java/util/Iterator.next:()Ljava/lang/Object;
     131: checkcast     #90                 // class org/dmg/pmml/naive_bayes/TargetValueCount
     134: astore        12
     136: aload         12
     138: invokevirtual #91                 // Method org/dmg/pmml/naive_bayes/TargetValueCount.getValue:()Ljava/lang/Object;
     141: astore        13
     143: aload         13
     145: ifnonnull     161
     148: new           #26                 // class org/jpmml/evaluator/MissingAttributeException
     151: dup
     152: aload         12
     154: getstatic     #92                 // Field org/dmg/pmml/naive_bayes/PMMLAttributes.TARGETVALUECOUNT_VALUE:Ljava/lang/reflect/Field;
     157: invokespecial #28                 // Method org/jpmml/evaluator/MissingAttributeException."<init>":(Lorg/dmg/pmml/PMMLObject;Ljava/lang/reflect/Field;)V
     160: athrow
     161: aload         12
     163: invokevirtual #93                 // Method org/dmg/pmml/naive_bayes/TargetValueCount.getCount:()Ljava/lang/Number;
     166: astore        14
     168: aload         14
     170: ifnonnull     186
     173: new           #26                 // class org/jpmml/evaluator/MissingAttributeException
     176: dup
     177: aload         12
     179: getstatic     #94                 // Field org/dmg/pmml/naive_bayes/PMMLAttributes.TARGETVALUECOUNT_COUNT:Ljava/lang/reflect/Field;
     182: invokespecial #28                 // Method org/jpmml/evaluator/MissingAttributeException."<init>":(Lorg/dmg/pmml/PMMLObject;Ljava/lang/reflect/Field;)V
     185: athrow
     186: aload         6
     188: aload         13
     190: invokeinterface #53,  2           // InterfaceMethod java/util/Map.get:(Ljava/lang/Object;)Ljava/lang/Object;
     195: checkcast     #97                 // class java/lang/Number
     198: astore        15
     200: aload         15
     202: ifnonnull     212
     205: aload         14
     207: astore        15
     209: goto          224
     212: getstatic     #111                // Field org/jpmml/evaluator/Functions.ADD:Lorg/jpmml/evaluator/functions/ArithmeticFunction;
     215: aload         15
     217: aload         14
     219: invokevirtual #100                // Method org/jpmml/evaluator/functions/ArithmeticFunction.evaluate:(Ljava/lang/Number;Ljava/lang/Number;)Ljava/lang/Number;
     222: astore        15
     224: aload         6
     226: aload         13
     228: aload         15
     230: invokeinterface #112,  3          // InterfaceMethod java/util/Map.put:(Ljava/lang/Object;Ljava/lang/Object;)Ljava/lang/Object;
     235: pop
     236: goto          114
     239: goto          78
     242: aload_1
     243: aload         5
     245: aload         6
     247: invokeinterface #112,  3          // InterfaceMethod java/util/Map.put:(Ljava/lang/Object;Ljava/lang/Object;)Ljava/lang/Object;
     252: pop
     253: goto          26
     256: aload_1
     257: areturn

  private static java.util.List<org.dmg.pmml.naive_bayes.BayesInput> parseBayesInputs(org.dmg.pmml.naive_bayes.NaiveBayesModel);
    Code:
       0: aload_0
       1: invokevirtual #9                  // Method org/dmg/pmml/naive_bayes/NaiveBayesModel.getBayesInputs:()Lorg/dmg/pmml/naive_bayes/BayesInputs;
       4: astore_1
       5: aload_1
       6: invokevirtual #14                 // Method org/dmg/pmml/naive_bayes/BayesInputs.hasExtensions:()Z
       9: ifne          17
      12: aload_1
      13: invokevirtual #113                // Method org/dmg/pmml/naive_bayes/BayesInputs.getBayesInputs:()Ljava/util/List;
      16: areturn
      17: new           #114                // class java/util/ArrayList
      20: dup
      21: aload_1
      22: invokevirtual #113                // Method org/dmg/pmml/naive_bayes/BayesInputs.getBayesInputs:()Ljava/util/List;
      25: invokespecial #115                // Method java/util/ArrayList."<init>":(Ljava/util/Collection;)V
      28: astore_2
      29: aload_1
      30: invokevirtual #116                // Method org/dmg/pmml/naive_bayes/BayesInputs.getExtensions:()Ljava/util/List;
      33: astore_3
      34: aload_3
      35: invokeinterface #41,  1           // InterfaceMethod java/util/List.iterator:()Ljava/util/Iterator;
      40: astore        4
      42: aload         4
      44: invokeinterface #42,  1           // InterfaceMethod java/util/Iterator.hasNext:()Z
      49: ifeq          129
      52: aload         4
      54: invokeinterface #43,  1           // InterfaceMethod java/util/Iterator.next:()Ljava/lang/Object;
      59: checkcast     #117                // class org/dmg/pmml/Extension
      62: astore        5
      64: aload         5
      66: invokevirtual #118                // Method org/dmg/pmml/Extension.getContent:()Ljava/util/List;
      69: astore        6
      71: aload         6
      73: invokeinterface #41,  1           // InterfaceMethod java/util/List.iterator:()Ljava/util/Iterator;
      78: astore        7
      80: aload         7
      82: invokeinterface #42,  1           // InterfaceMethod java/util/Iterator.hasNext:()Z
      87: ifeq          126
      90: aload         7
      92: invokeinterface #43,  1           // InterfaceMethod java/util/Iterator.next:()Ljava/lang/Object;
      97: astore        8
      99: aload         8
     101: instanceof    #44                 // class org/dmg/pmml/naive_bayes/BayesInput
     104: ifeq          123
     107: aload         8
     109: checkcast     #44                 // class org/dmg/pmml/naive_bayes/BayesInput
     112: astore        9
     114: aload_2
     115: aload         9
     117: invokeinterface #119,  2          // InterfaceMethod java/util/List.add:(Ljava/lang/Object;)Z
     122: pop
     123: goto          80
     126: goto          42
     129: aload_2
     130: areturn

  private static org.dmg.pmml.naive_bayes.TargetValueStats getTargetValueStats(org.dmg.pmml.naive_bayes.BayesInput);
    Code:
       0: aload_0
       1: invokevirtual #120                // Method org/dmg/pmml/naive_bayes/BayesInput.getTargetValueStats:()Lorg/dmg/pmml/naive_bayes/TargetValueStats;
       4: areturn

  private static org.dmg.pmml.naive_bayes.TargetValueCounts getTargetValueCounts(org.dmg.pmml.naive_bayes.BayesInput, org.jpmml.evaluator.FieldValue);
    Code:
       0: aload_0
       1: instanceof    #121                // class org/jpmml/evaluator/MapHolder
       4: ifeq          30
       7: aload_0
       8: checkcast     #121                // class org/jpmml/evaluator/MapHolder
      11: astore_2
      12: aload_2
      13: aload_1
      14: invokevirtual #122                // Method org/jpmml/evaluator/FieldValue.getDataType:()Lorg/dmg/pmml/DataType;
      17: aload_1
      18: invokevirtual #123                // Method org/jpmml/evaluator/FieldValue.getValue:()Ljava/lang/Object;
      21: invokeinterface #124,  3          // InterfaceMethod org/jpmml/evaluator/MapHolder.get:(Lorg/dmg/pmml/DataType;Ljava/lang/Object;)Ljava/lang/Object;
      26: checkcast     #125                // class org/dmg/pmml/naive_bayes/TargetValueCounts
      29: areturn
      30: aload_0
      31: invokevirtual #108                // Method org/dmg/pmml/naive_bayes/BayesInput.getPairCounts:()Ljava/util/List;
      34: astore_2
      35: aload_2
      36: invokeinterface #41,  1           // InterfaceMethod java/util/List.iterator:()Ljava/util/Iterator;
      41: astore_3
      42: aload_3
      43: invokeinterface #42,  1           // InterfaceMethod java/util/Iterator.hasNext:()Z
      48: ifeq          127
      51: aload_3
      52: invokeinterface #43,  1           // InterfaceMethod java/util/Iterator.next:()Ljava/lang/Object;
      57: checkcast     #109                // class org/dmg/pmml/naive_bayes/PairCounts
      60: astore        4
      62: aload         4
      64: invokevirtual #126                // Method org/dmg/pmml/naive_bayes/PairCounts.getValue:()Ljava/lang/Object;
      67: astore        5
      69: aload         5
      71: ifnonnull     87
      74: new           #26                 // class org/jpmml/evaluator/MissingAttributeException
      77: dup
      78: aload         4
      80: getstatic     #127                // Field org/dmg/pmml/naive_bayes/PMMLAttributes.PAIRCOUNTS_VALUE:Ljava/lang/reflect/Field;
      83: invokespecial #28                 // Method org/jpmml/evaluator/MissingAttributeException."<init>":(Lorg/dmg/pmml/PMMLObject;Ljava/lang/reflect/Field;)V
      86: athrow
      87: aload_1
      88: aload         5
      90: invokevirtual #128                // Method org/jpmml/evaluator/FieldValue.equalsValue:(Ljava/lang/Object;)Z
      93: ifeq          124
      96: aload         4
      98: invokevirtual #110                // Method org/dmg/pmml/naive_bayes/PairCounts.getTargetValueCounts:()Lorg/dmg/pmml/naive_bayes/TargetValueCounts;
     101: astore        6
     103: aload         6
     105: ifnonnull     121
     108: new           #10                 // class org/jpmml/evaluator/MissingElementException
     111: dup
     112: aload         4
     114: getstatic     #129                // Field org/dmg/pmml/naive_bayes/PMMLElements.PAIRCOUNTS_TARGETVALUECOUNTS:Ljava/lang/reflect/Field;
     117: invokespecial #12                 // Method org/jpmml/evaluator/MissingElementException."<init>":(Lorg/dmg/pmml/PMMLObject;Ljava/lang/reflect/Field;)V
     120: athrow
     121: aload         6
     123: areturn
     124: goto          42
     127: aconst_null
     128: areturn

  private static org.dmg.pmml.naive_bayes.TargetValueCounts getTargetValueCounts(org.dmg.pmml.naive_bayes.BayesOutput);
    Code:
       0: aload_0
       1: invokevirtual #18                 // Method org/dmg/pmml/naive_bayes/BayesOutput.getTargetValueCounts:()Lorg/dmg/pmml/naive_bayes/TargetValueCounts;
       4: areturn

  static java.util.List access$000(org.dmg.pmml.naive_bayes.NaiveBayesModel);
    Code:
       0: aload_0
       1: invokestatic  #2                  // Method parseBayesInputs:(Lorg/dmg/pmml/naive_bayes/NaiveBayesModel;)Ljava/util/List;
       4: areturn

  static java.util.Map access$100(org.dmg.pmml.naive_bayes.NaiveBayesModel);
    Code:
       0: aload_0
       1: invokestatic  #1                  // Method calculateFieldCountSums:(Lorg/dmg/pmml/naive_bayes/NaiveBayesModel;)Ljava/util/Map;
       4: areturn

  static {};
    Code:
       0: new           #130                // class org/jpmml/evaluator/naive_bayes/NaiveBayesModelEvaluator$2
       3: dup
       4: invokespecial #131                // Method org/jpmml/evaluator/naive_bayes/NaiveBayesModelEvaluator$2."<init>":()V
       7: invokestatic  #132                // Method org/jpmml/evaluator/CacheUtil.buildLoadingCache:(Lcom/google/common/cache/CacheLoader;)Lcom/google/common/cache/LoadingCache;
      10: putstatic     #101                // Field bayesInputCache:Lcom/google/common/cache/LoadingCache;
      13: new           #133                // class org/jpmml/evaluator/naive_bayes/NaiveBayesModelEvaluator$3
      16: dup
      17: invokespecial #134                // Method org/jpmml/evaluator/naive_bayes/NaiveBayesModelEvaluator$3."<init>":()V
      20: invokestatic  #132                // Method org/jpmml/evaluator/CacheUtil.buildLoadingCache:(Lcom/google/common/cache/CacheLoader;)Lcom/google/common/cache/LoadingCache;
      23: putstatic     #104                // Field fieldCountSumCache:Lcom/google/common/cache/LoadingCache;
      26: return
}
