Compiled from "ScreenshotDigest.java"
public class net.thucydides.core.screenshots.ScreenshotDigest {
  private final java.util.Optional<net.thucydides.core.screenshots.BlurLevel> blurLevel;

  private final net.thucydides.core.util.EnvironmentVariables environmentVariables;

  public net.thucydides.core.screenshots.ScreenshotDigest(net.thucydides.core.util.EnvironmentVariables, net.thucydides.core.screenshots.BlurLevel);
    Code:
       0: aload_0
       1: invokespecial #1                  // Method java/lang/Object."<init>":()V
       4: aload_0
       5: aload_1
       6: putfield      #2                  // Field environmentVariables:Lnet/thucydides/core/util/EnvironmentVariables;
       9: aload_0
      10: aload_2
      11: invokestatic  #3                  // Method java/util/Optional.ofNullable:(Ljava/lang/Object;)Ljava/util/Optional;
      14: putfield      #4                  // Field blurLevel:Ljava/util/Optional;
      17: return

  public java.lang.String forScreenshot(java.io.File) throws java.io.IOException;
    Code:
       0: new           #5                  // class java/io/FileInputStream
       3: dup
       4: aload_1
       5: invokespecial #6                  // Method java/io/FileInputStream."<init>":(Ljava/io/File;)V
       8: astore_2
       9: aconst_null
      10: astore_3
      11: new           #7                  // class java/lang/StringBuilder
      14: dup
      15: invokespecial #8                  // Method java/lang/StringBuilder."<init>":()V
      18: aload_2
      19: invokestatic  #9                  // Method org/apache/commons/codec/digest/DigestUtils.sha256Hex:(Ljava/io/InputStream;)Ljava/lang/String;
      22: invokevirtual #10                 // Method java/lang/StringBuilder.append:(Ljava/lang/String;)Ljava/lang/StringBuilder;
      25: ldc           #11                 // String _
      27: invokevirtual #10                 // Method java/lang/StringBuilder.append:(Ljava/lang/String;)Ljava/lang/StringBuilder;
      30: aload_0
      31: getfield      #4                  // Field blurLevel:Ljava/util/Optional;
      34: getstatic     #12                 // Field net/thucydides/core/screenshots/BlurLevel.NONE:Lnet/thucydides/core/screenshots/BlurLevel;
      37: invokevirtual #13                 // Method java/util/Optional.orElse:(Ljava/lang/Object;)Ljava/lang/Object;
      40: checkcast     #14                 // class net/thucydides/core/screenshots/BlurLevel
      43: invokevirtual #15                 // Method net/thucydides/core/screenshots/BlurLevel.toString:()Ljava/lang/String;
      46: invokevirtual #10                 // Method java/lang/StringBuilder.append:(Ljava/lang/String;)Ljava/lang/StringBuilder;
      49: aload_0
      50: invokespecial #16                 // Method optionalWidth:()Ljava/lang/String;
      53: invokevirtual #10                 // Method java/lang/StringBuilder.append:(Ljava/lang/String;)Ljava/lang/StringBuilder;
      56: ldc           #17                 // String .png
      58: invokevirtual #10                 // Method java/lang/StringBuilder.append:(Ljava/lang/String;)Ljava/lang/StringBuilder;
      61: invokevirtual #18                 // Method java/lang/StringBuilder.toString:()Ljava/lang/String;
      64: astore        4
      66: aload_2
      67: ifnull        96
      70: aload_3
      71: ifnull        92
      74: aload_2
      75: invokevirtual #19                 // Method java/io/InputStream.close:()V
      78: goto          96
      81: astore        5
      83: aload_3
      84: aload         5
      86: invokevirtual #21                 // Method java/lang/Throwable.addSuppressed:(Ljava/lang/Throwable;)V
      89: goto          96
      92: aload_2
      93: invokevirtual #19                 // Method java/io/InputStream.close:()V
      96: aload         4
      98: areturn
      99: astore        4
     101: aload         4
     103: astore_3
     104: aload         4
     106: athrow
     107: astore        6
     109: aload_2
     110: ifnull        139
     113: aload_3
     114: ifnull        135
     117: aload_2
     118: invokevirtual #19                 // Method java/io/InputStream.close:()V
     121: goto          139
     124: astore        7
     126: aload_3
     127: aload         7
     129: invokevirtual #21                 // Method java/lang/Throwable.addSuppressed:(Ljava/lang/Throwable;)V
     132: goto          139
     135: aload_2
     136: invokevirtual #19                 // Method java/io/InputStream.close:()V
     139: aload         6
     141: athrow
    Exception table:
       from    to  target type
          74    78    81   Class java/lang/Throwable
          11    66    99   Class java/lang/Throwable
          11    66   107   any
         117   121   124   Class java/lang/Throwable
          99   109   107   any

  private java.lang.String optionalWidth();
    Code:
       0: getstatic     #22                 // Field net/thucydides/core/ThucydidesSystemProperty.THUCYDIDES_RESIZED_IMAGE_WIDTH:Lnet/thucydides/core/ThucydidesSystemProperty;
       3: aload_0
       4: getfield      #2                  // Field environmentVariables:Lnet/thucydides/core/util/EnvironmentVariables;
       7: ldc           #23                 // String
       9: invokevirtual #24                 // Method net/thucydides/core/ThucydidesSystemProperty.from:(Lnet/thucydides/core/util/EnvironmentVariables;Ljava/lang/String;)Ljava/lang/String;
      12: areturn
}
