Compiled from "BloopConverter.scala"
public final class bloop.integrations.gradle.model.BloopConverter$$anonfun$getClassPathItems$1$$anonfun$apply$8 extends scala.runtime.AbstractFunction0<scala.collection.immutable.List<java.nio.file.Path>> implements scala.Serializable {
  public static final long serialVersionUID;

  private final java.io.File f$1;

  public final scala.collection.immutable.List<java.nio.file.Path> apply();
    Code:
       0: getstatic     #26                 // Field scala/collection/immutable/List$.MODULE$:Lscala/collection/immutable/List$;
       3: getstatic     #31                 // Field scala/Predef$.MODULE$:Lscala/Predef$;
       6: iconst_1
       7: anewarray     #33                 // class java/nio/file/Path
      10: dup
      11: iconst_0
      12: aload_0
      13: getfield      #35                 // Field f$1:Ljava/io/File;
      16: invokevirtual #41                 // Method java/io/File.toPath:()Ljava/nio/file/Path;
      19: aastore
      20: checkcast     #43                 // class "[Ljava/lang/Object;"
      23: invokevirtual #47                 // Method scala/Predef$.wrapRefArray:([Ljava/lang/Object;)Lscala/collection/mutable/WrappedArray;
      26: invokevirtual #50                 // Method scala/collection/immutable/List$.apply:(Lscala/collection/Seq;)Lscala/collection/immutable/List;
      29: areturn

  public final java.lang.Object apply();
    Code:
       0: aload_0
       1: invokevirtual #55                 // Method apply:()Lscala/collection/immutable/List;
       4: areturn

  public bloop.integrations.gradle.model.BloopConverter$$anonfun$getClassPathItems$1$$anonfun$apply$8(bloop.integrations.gradle.model.BloopConverter$$anonfun$getClassPathItems$1, java.io.File);
    Code:
       0: aload_0
       1: aload_2
       2: putfield      #35                 // Field f$1:Ljava/io/File;
       5: aload_0
       6: invokespecial #60                 // Method scala/runtime/AbstractFunction0."<init>":()V
       9: return
}
