Compiled from "StorageUpdatePolicy.java"
public final class io.micronaut.data.cosmos.config.StorageUpdatePolicy extends java.lang.Enum<io.micronaut.data.cosmos.config.StorageUpdatePolicy> {
  public static final io.micronaut.data.cosmos.config.StorageUpdatePolicy CREATE_IF_NOT_EXISTS;

  public static final io.micronaut.data.cosmos.config.StorageUpdatePolicy UPDATE;

  public static final io.micronaut.data.cosmos.config.StorageUpdatePolicy NONE;

  private static final io.micronaut.data.cosmos.config.StorageUpdatePolicy[] $VALUES;

  public static io.micronaut.data.cosmos.config.StorageUpdatePolicy[] values();
    Code:
       0: getstatic     #13                 // Field $VALUES:[Lio/micronaut/data/cosmos/config/StorageUpdatePolicy;
       3: invokevirtual #17                 // Method "[Lio/micronaut/data/cosmos/config/StorageUpdatePolicy;".clone:()Ljava/lang/Object;
       6: checkcast     #18                 // class "[Lio/micronaut/data/cosmos/config/StorageUpdatePolicy;"
       9: areturn

  public static io.micronaut.data.cosmos.config.StorageUpdatePolicy valueOf(java.lang.String);
    Code:
       0: ldc           #1                  // class io/micronaut/data/cosmos/config/StorageUpdatePolicy
       2: aload_0
       3: invokestatic  #22                 // Method java/lang/Enum.valueOf:(Ljava/lang/Class;Ljava/lang/String;)Ljava/lang/Enum;
       6: checkcast     #1                  // class io/micronaut/data/cosmos/config/StorageUpdatePolicy
       9: areturn

  private io.micronaut.data.cosmos.config.StorageUpdatePolicy();
    Code:
       0: aload_0
       1: aload_1
       2: iload_2
       3: invokespecial #28                 // Method java/lang/Enum."<init>":(Ljava/lang/String;I)V
       6: return

  private static io.micronaut.data.cosmos.config.StorageUpdatePolicy[] $values();
    Code:
       0: iconst_3
       1: anewarray     #1                  // class io/micronaut/data/cosmos/config/StorageUpdatePolicy
       4: dup
       5: iconst_0
       6: getstatic     #3                  // Field CREATE_IF_NOT_EXISTS:Lio/micronaut/data/cosmos/config/StorageUpdatePolicy;
       9: aastore
      10: dup
      11: iconst_1
      12: getstatic     #7                  // Field UPDATE:Lio/micronaut/data/cosmos/config/StorageUpdatePolicy;
      15: aastore
      16: dup
      17: iconst_2
      18: getstatic     #10                 // Field NONE:Lio/micronaut/data/cosmos/config/StorageUpdatePolicy;
      21: aastore
      22: areturn

  static {};
    Code:
       0: new           #1                  // class io/micronaut/data/cosmos/config/StorageUpdatePolicy
       3: dup
       4: ldc           #32                 // String CREATE_IF_NOT_EXISTS
       6: iconst_0
       7: invokespecial #33                 // Method "<init>":(Ljava/lang/String;I)V
      10: putstatic     #3                  // Field CREATE_IF_NOT_EXISTS:Lio/micronaut/data/cosmos/config/StorageUpdatePolicy;
      13: new           #1                  // class io/micronaut/data/cosmos/config/StorageUpdatePolicy
      16: dup
      17: ldc           #34                 // String UPDATE
      19: iconst_1
      20: invokespecial #33                 // Method "<init>":(Ljava/lang/String;I)V
      23: putstatic     #7                  // Field UPDATE:Lio/micronaut/data/cosmos/config/StorageUpdatePolicy;
      26: new           #1                  // class io/micronaut/data/cosmos/config/StorageUpdatePolicy
      29: dup
      30: ldc           #35                 // String NONE
      32: iconst_2
      33: invokespecial #33                 // Method "<init>":(Ljava/lang/String;I)V
      36: putstatic     #10                 // Field NONE:Lio/micronaut/data/cosmos/config/StorageUpdatePolicy;
      39: invokestatic  #36                 // Method $values:()[Lio/micronaut/data/cosmos/config/StorageUpdatePolicy;
      42: putstatic     #13                 // Field $VALUES:[Lio/micronaut/data/cosmos/config/StorageUpdatePolicy;
      45: return
}
