Compiled from "AuditEvent.java"
public class ca.uhn.fhir.model.dstu2.resource.AuditEvent extends ca.uhn.fhir.model.dstu2.resource.BaseResource implements ca.uhn.fhir.model.api.IResource {
  public static final java.lang.String SP_TYPE;

  public static final ca.uhn.fhir.rest.gclient.TokenClientParam TYPE;

  public static final java.lang.String SP_ACTION;

  public static final ca.uhn.fhir.rest.gclient.TokenClientParam ACTION;

  public static final java.lang.String SP_DATE;

  public static final ca.uhn.fhir.rest.gclient.DateClientParam DATE;

  public static final java.lang.String SP_SUBTYPE;

  public static final ca.uhn.fhir.rest.gclient.TokenClientParam SUBTYPE;

  public static final java.lang.String SP_USER;

  public static final ca.uhn.fhir.rest.gclient.TokenClientParam USER;

  public static final java.lang.String SP_NAME;

  public static final ca.uhn.fhir.rest.gclient.StringClientParam NAME;

  public static final java.lang.String SP_ADDRESS;

  public static final ca.uhn.fhir.rest.gclient.TokenClientParam ADDRESS;

  public static final java.lang.String SP_SOURCE;

  public static final ca.uhn.fhir.rest.gclient.TokenClientParam SOURCE;

  public static final java.lang.String SP_SITE;

  public static final ca.uhn.fhir.rest.gclient.TokenClientParam SITE;

  public static final java.lang.String SP_OBJECT_TYPE;

  public static final ca.uhn.fhir.rest.gclient.TokenClientParam OBJECT_TYPE;

  public static final java.lang.String SP_IDENTITY;

  public static final ca.uhn.fhir.rest.gclient.TokenClientParam IDENTITY;

  public static final java.lang.String SP_REFERENCE;

  public static final ca.uhn.fhir.rest.gclient.ReferenceClientParam REFERENCE;

  public static final java.lang.String SP_DESC;

  public static final ca.uhn.fhir.rest.gclient.StringClientParam DESC;

  public static final java.lang.String SP_PATIENT;

  public static final ca.uhn.fhir.rest.gclient.ReferenceClientParam PATIENT;

  public static final java.lang.String SP_ALTID;

  public static final ca.uhn.fhir.rest.gclient.TokenClientParam ALTID;

  public static final java.lang.String SP_PARTICIPANT;

  public static final ca.uhn.fhir.rest.gclient.ReferenceClientParam PARTICIPANT;

  public static final java.lang.String SP_POLICY;

  public static final ca.uhn.fhir.rest.gclient.UriClientParam POLICY;

  public static final ca.uhn.fhir.model.api.Include INCLUDE_PARTICIPANT;

  public static final ca.uhn.fhir.model.api.Include INCLUDE_PATIENT;

  public static final ca.uhn.fhir.model.api.Include INCLUDE_REFERENCE;

  private ca.uhn.fhir.model.dstu2.resource.AuditEvent$Event myEvent;

  private java.util.List<ca.uhn.fhir.model.dstu2.resource.AuditEvent$Participant> myParticipant;

  private ca.uhn.fhir.model.dstu2.resource.AuditEvent$Source mySource;

  private java.util.List<ca.uhn.fhir.model.dstu2.resource.AuditEvent$ObjectElement> myObject;

  public ca.uhn.fhir.model.dstu2.resource.AuditEvent();
    Code:
       0: aload_0
       1: invokespecial #1                  // Method ca/uhn/fhir/model/dstu2/resource/BaseResource."<init>":()V
       4: return

  public boolean isEmpty();
    Code:
       0: aload_0
       1: invokespecial #7                  // Method ca/uhn/fhir/model/dstu2/resource/BaseResource.isBaseEmpty:()Z
       4: ifeq          49
       7: iconst_4
       8: anewarray     #11                 // class java/lang/Object
      11: dup
      12: iconst_0
      13: aload_0
      14: getfield      #13                 // Field myEvent:Lca/uhn/fhir/model/dstu2/resource/AuditEvent$Event;
      17: aastore
      18: dup
      19: iconst_1
      20: aload_0
      21: getfield      #19                 // Field myParticipant:Ljava/util/List;
      24: aastore
      25: dup
      26: iconst_2
      27: aload_0
      28: getfield      #23                 // Field mySource:Lca/uhn/fhir/model/dstu2/resource/AuditEvent$Source;
      31: aastore
      32: dup
      33: iconst_3
      34: aload_0
      35: getfield      #27                 // Field myObject:Ljava/util/List;
      38: aastore
      39: invokestatic  #30                 // Method ca/uhn/fhir/util/ElementUtil.isEmpty:([Ljava/lang/Object;)Z
      42: ifeq          49
      45: iconst_1
      46: goto          50
      49: iconst_0
      50: ireturn

  public <T extends ca.uhn.fhir.model.api.IElement> java.util.List<T> getAllPopulatedChildElementsOfType(java.lang.Class<T>);
    Code:
       0: aload_1
       1: iconst_4
       2: anewarray     #11                 // class java/lang/Object
       5: dup
       6: iconst_0
       7: aload_0
       8: getfield      #13                 // Field myEvent:Lca/uhn/fhir/model/dstu2/resource/AuditEvent$Event;
      11: aastore
      12: dup
      13: iconst_1
      14: aload_0
      15: getfield      #19                 // Field myParticipant:Ljava/util/List;
      18: aastore
      19: dup
      20: iconst_2
      21: aload_0
      22: getfield      #23                 // Field mySource:Lca/uhn/fhir/model/dstu2/resource/AuditEvent$Source;
      25: aastore
      26: dup
      27: iconst_3
      28: aload_0
      29: getfield      #27                 // Field myObject:Ljava/util/List;
      32: aastore
      33: invokestatic  #36                 // Method ca/uhn/fhir/util/ElementUtil.allPopulatedChildElements:(Ljava/lang/Class;[Ljava/lang/Object;)Ljava/util/List;
      36: areturn

  public ca.uhn.fhir.model.dstu2.resource.AuditEvent$Event getEvent();
    Code:
       0: aload_0
       1: getfield      #13                 // Field myEvent:Lca/uhn/fhir/model/dstu2/resource/AuditEvent$Event;
       4: ifnonnull     18
       7: aload_0
       8: new           #40                 // class ca/uhn/fhir/model/dstu2/resource/AuditEvent$Event
      11: dup
      12: invokespecial #42                 // Method ca/uhn/fhir/model/dstu2/resource/AuditEvent$Event."<init>":()V
      15: putfield      #13                 // Field myEvent:Lca/uhn/fhir/model/dstu2/resource/AuditEvent$Event;
      18: aload_0
      19: getfield      #13                 // Field myEvent:Lca/uhn/fhir/model/dstu2/resource/AuditEvent$Event;
      22: areturn

  public ca.uhn.fhir.model.dstu2.resource.AuditEvent setEvent(ca.uhn.fhir.model.dstu2.resource.AuditEvent$Event);
    Code:
       0: aload_0
       1: aload_1
       2: putfield      #13                 // Field myEvent:Lca/uhn/fhir/model/dstu2/resource/AuditEvent$Event;
       5: aload_0
       6: areturn

  public java.util.List<ca.uhn.fhir.model.dstu2.resource.AuditEvent$Participant> getParticipant();
    Code:
       0: aload_0
       1: getfield      #19                 // Field myParticipant:Ljava/util/List;
       4: ifnonnull     18
       7: aload_0
       8: new           #43                 // class java/util/ArrayList
      11: dup
      12: invokespecial #45                 // Method java/util/ArrayList."<init>":()V
      15: putfield      #19                 // Field myParticipant:Ljava/util/List;
      18: aload_0
      19: getfield      #19                 // Field myParticipant:Ljava/util/List;
      22: areturn

  public ca.uhn.fhir.model.dstu2.resource.AuditEvent setParticipant(java.util.List<ca.uhn.fhir.model.dstu2.resource.AuditEvent$Participant>);
    Code:
       0: aload_0
       1: aload_1
       2: putfield      #19                 // Field myParticipant:Ljava/util/List;
       5: aload_0
       6: areturn

  public ca.uhn.fhir.model.dstu2.resource.AuditEvent$Participant addParticipant();
    Code:
       0: new           #46                 // class ca/uhn/fhir/model/dstu2/resource/AuditEvent$Participant
       3: dup
       4: invokespecial #48                 // Method ca/uhn/fhir/model/dstu2/resource/AuditEvent$Participant."<init>":()V
       7: astore_1
       8: aload_0
       9: invokevirtual #49                 // Method getParticipant:()Ljava/util/List;
      12: aload_1
      13: invokeinterface #53,  2           // InterfaceMethod java/util/List.add:(Ljava/lang/Object;)Z
      18: pop
      19: aload_1
      20: areturn

  public ca.uhn.fhir.model.dstu2.resource.AuditEvent addParticipant(ca.uhn.fhir.model.dstu2.resource.AuditEvent$Participant);
    Code:
       0: aload_1
       1: ifnonnull     14
       4: new           #59                 // class java/lang/NullPointerException
       7: dup
       8: ldc           #61                 // String theValue must not be null
      10: invokespecial #63                 // Method java/lang/NullPointerException."<init>":(Ljava/lang/String;)V
      13: athrow
      14: aload_0
      15: invokevirtual #49                 // Method getParticipant:()Ljava/util/List;
      18: aload_1
      19: invokeinterface #53,  2           // InterfaceMethod java/util/List.add:(Ljava/lang/Object;)Z
      24: pop
      25: aload_0
      26: areturn

  public ca.uhn.fhir.model.dstu2.resource.AuditEvent$Participant getParticipantFirstRep();
    Code:
       0: aload_0
       1: invokevirtual #49                 // Method getParticipant:()Ljava/util/List;
       4: invokeinterface #66,  1           // InterfaceMethod java/util/List.isEmpty:()Z
       9: ifeq          17
      12: aload_0
      13: invokevirtual #68                 // Method addParticipant:()Lca/uhn/fhir/model/dstu2/resource/AuditEvent$Participant;
      16: areturn
      17: aload_0
      18: invokevirtual #49                 // Method getParticipant:()Ljava/util/List;
      21: iconst_0
      22: invokeinterface #72,  2           // InterfaceMethod java/util/List.get:(I)Ljava/lang/Object;
      27: checkcast     #46                 // class ca/uhn/fhir/model/dstu2/resource/AuditEvent$Participant
      30: areturn

  public ca.uhn.fhir.model.dstu2.resource.AuditEvent$Source getSource();
    Code:
       0: aload_0
       1: getfield      #23                 // Field mySource:Lca/uhn/fhir/model/dstu2/resource/AuditEvent$Source;
       4: ifnonnull     18
       7: aload_0
       8: new           #76                 // class ca/uhn/fhir/model/dstu2/resource/AuditEvent$Source
      11: dup
      12: invokespecial #78                 // Method ca/uhn/fhir/model/dstu2/resource/AuditEvent$Source."<init>":()V
      15: putfield      #23                 // Field mySource:Lca/uhn/fhir/model/dstu2/resource/AuditEvent$Source;
      18: aload_0
      19: getfield      #23                 // Field mySource:Lca/uhn/fhir/model/dstu2/resource/AuditEvent$Source;
      22: areturn

  public ca.uhn.fhir.model.dstu2.resource.AuditEvent setSource(ca.uhn.fhir.model.dstu2.resource.AuditEvent$Source);
    Code:
       0: aload_0
       1: aload_1
       2: putfield      #23                 // Field mySource:Lca/uhn/fhir/model/dstu2/resource/AuditEvent$Source;
       5: aload_0
       6: areturn

  public java.util.List<ca.uhn.fhir.model.dstu2.resource.AuditEvent$ObjectElement> getObject();
    Code:
       0: aload_0
       1: getfield      #27                 // Field myObject:Ljava/util/List;
       4: ifnonnull     18
       7: aload_0
       8: new           #43                 // class java/util/ArrayList
      11: dup
      12: invokespecial #45                 // Method java/util/ArrayList."<init>":()V
      15: putfield      #27                 // Field myObject:Ljava/util/List;
      18: aload_0
      19: getfield      #27                 // Field myObject:Ljava/util/List;
      22: areturn

  public ca.uhn.fhir.model.dstu2.resource.AuditEvent setObject(java.util.List<ca.uhn.fhir.model.dstu2.resource.AuditEvent$ObjectElement>);
    Code:
       0: aload_0
       1: aload_1
       2: putfield      #27                 // Field myObject:Ljava/util/List;
       5: aload_0
       6: areturn

  public ca.uhn.fhir.model.dstu2.resource.AuditEvent$ObjectElement addObject();
    Code:
       0: new           #79                 // class ca/uhn/fhir/model/dstu2/resource/AuditEvent$ObjectElement
       3: dup
       4: invokespecial #81                 // Method ca/uhn/fhir/model/dstu2/resource/AuditEvent$ObjectElement."<init>":()V
       7: astore_1
       8: aload_0
       9: invokevirtual #82                 // Method getObject:()Ljava/util/List;
      12: aload_1
      13: invokeinterface #53,  2           // InterfaceMethod java/util/List.add:(Ljava/lang/Object;)Z
      18: pop
      19: aload_1
      20: areturn

  public ca.uhn.fhir.model.dstu2.resource.AuditEvent addObject(ca.uhn.fhir.model.dstu2.resource.AuditEvent$ObjectElement);
    Code:
       0: aload_1
       1: ifnonnull     14
       4: new           #59                 // class java/lang/NullPointerException
       7: dup
       8: ldc           #61                 // String theValue must not be null
      10: invokespecial #63                 // Method java/lang/NullPointerException."<init>":(Ljava/lang/String;)V
      13: athrow
      14: aload_0
      15: invokevirtual #82                 // Method getObject:()Ljava/util/List;
      18: aload_1
      19: invokeinterface #53,  2           // InterfaceMethod java/util/List.add:(Ljava/lang/Object;)Z
      24: pop
      25: aload_0
      26: areturn

  public ca.uhn.fhir.model.dstu2.resource.AuditEvent$ObjectElement getObjectFirstRep();
    Code:
       0: aload_0
       1: invokevirtual #82                 // Method getObject:()Ljava/util/List;
       4: invokeinterface #66,  1           // InterfaceMethod java/util/List.isEmpty:()Z
       9: ifeq          17
      12: aload_0
      13: invokevirtual #85                 // Method addObject:()Lca/uhn/fhir/model/dstu2/resource/AuditEvent$ObjectElement;
      16: areturn
      17: aload_0
      18: invokevirtual #82                 // Method getObject:()Ljava/util/List;
      21: iconst_0
      22: invokeinterface #72,  2           // InterfaceMethod java/util/List.get:(I)Ljava/lang/Object;
      27: checkcast     #79                 // class ca/uhn/fhir/model/dstu2/resource/AuditEvent$ObjectElement
      30: areturn

  public java.lang.String getResourceName();
    Code:
       0: ldc           #89                 // String AuditEvent
       2: areturn

  public ca.uhn.fhir.context.FhirVersionEnum getStructureFhirVersionEnum();
    Code:
       0: getstatic     #91                 // Field ca/uhn/fhir/context/FhirVersionEnum.DSTU2:Lca/uhn/fhir/context/FhirVersionEnum;
       3: areturn

  static {};
    Code:
       0: new           #97                 // class ca/uhn/fhir/rest/gclient/TokenClientParam
       3: dup
       4: ldc           #99                 // String type
       6: invokespecial #101                // Method ca/uhn/fhir/rest/gclient/TokenClientParam."<init>":(Ljava/lang/String;)V
       9: putstatic     #102                // Field TYPE:Lca/uhn/fhir/rest/gclient/TokenClientParam;
      12: new           #97                 // class ca/uhn/fhir/rest/gclient/TokenClientParam
      15: dup
      16: ldc           #106                // String action
      18: invokespecial #101                // Method ca/uhn/fhir/rest/gclient/TokenClientParam."<init>":(Ljava/lang/String;)V
      21: putstatic     #108                // Field ACTION:Lca/uhn/fhir/rest/gclient/TokenClientParam;
      24: new           #111                // class ca/uhn/fhir/rest/gclient/DateClientParam
      27: dup
      28: ldc           #113                // String date
      30: invokespecial #115                // Method ca/uhn/fhir/rest/gclient/DateClientParam."<init>":(Ljava/lang/String;)V
      33: putstatic     #116                // Field DATE:Lca/uhn/fhir/rest/gclient/DateClientParam;
      36: new           #97                 // class ca/uhn/fhir/rest/gclient/TokenClientParam
      39: dup
      40: ldc           #120                // String subtype
      42: invokespecial #101                // Method ca/uhn/fhir/rest/gclient/TokenClientParam."<init>":(Ljava/lang/String;)V
      45: putstatic     #122                // Field SUBTYPE:Lca/uhn/fhir/rest/gclient/TokenClientParam;
      48: new           #97                 // class ca/uhn/fhir/rest/gclient/TokenClientParam
      51: dup
      52: ldc           #125                // String user
      54: invokespecial #101                // Method ca/uhn/fhir/rest/gclient/TokenClientParam."<init>":(Ljava/lang/String;)V
      57: putstatic     #127                // Field USER:Lca/uhn/fhir/rest/gclient/TokenClientParam;
      60: new           #130                // class ca/uhn/fhir/rest/gclient/StringClientParam
      63: dup
      64: ldc           #132                // String name
      66: invokespecial #134                // Method ca/uhn/fhir/rest/gclient/StringClientParam."<init>":(Ljava/lang/String;)V
      69: putstatic     #135                // Field NAME:Lca/uhn/fhir/rest/gclient/StringClientParam;
      72: new           #97                 // class ca/uhn/fhir/rest/gclient/TokenClientParam
      75: dup
      76: ldc           #139                // String address
      78: invokespecial #101                // Method ca/uhn/fhir/rest/gclient/TokenClientParam."<init>":(Ljava/lang/String;)V
      81: putstatic     #141                // Field ADDRESS:Lca/uhn/fhir/rest/gclient/TokenClientParam;
      84: new           #97                 // class ca/uhn/fhir/rest/gclient/TokenClientParam
      87: dup
      88: ldc           #144                // String source
      90: invokespecial #101                // Method ca/uhn/fhir/rest/gclient/TokenClientParam."<init>":(Ljava/lang/String;)V
      93: putstatic     #146                // Field SOURCE:Lca/uhn/fhir/rest/gclient/TokenClientParam;
      96: new           #97                 // class ca/uhn/fhir/rest/gclient/TokenClientParam
      99: dup
     100: ldc           #149                // String site
     102: invokespecial #101                // Method ca/uhn/fhir/rest/gclient/TokenClientParam."<init>":(Ljava/lang/String;)V
     105: putstatic     #151                // Field SITE:Lca/uhn/fhir/rest/gclient/TokenClientParam;
     108: new           #97                 // class ca/uhn/fhir/rest/gclient/TokenClientParam
     111: dup
     112: ldc           #154                // String object-type
     114: invokespecial #101                // Method ca/uhn/fhir/rest/gclient/TokenClientParam."<init>":(Ljava/lang/String;)V
     117: putstatic     #156                // Field OBJECT_TYPE:Lca/uhn/fhir/rest/gclient/TokenClientParam;
     120: new           #97                 // class ca/uhn/fhir/rest/gclient/TokenClientParam
     123: dup
     124: ldc           #159                // String identity
     126: invokespecial #101                // Method ca/uhn/fhir/rest/gclient/TokenClientParam."<init>":(Ljava/lang/String;)V
     129: putstatic     #161                // Field IDENTITY:Lca/uhn/fhir/rest/gclient/TokenClientParam;
     132: new           #164                // class ca/uhn/fhir/rest/gclient/ReferenceClientParam
     135: dup
     136: ldc           #166                // String reference
     138: invokespecial #168                // Method ca/uhn/fhir/rest/gclient/ReferenceClientParam."<init>":(Ljava/lang/String;)V
     141: putstatic     #169                // Field REFERENCE:Lca/uhn/fhir/rest/gclient/ReferenceClientParam;
     144: new           #130                // class ca/uhn/fhir/rest/gclient/StringClientParam
     147: dup
     148: ldc           #173                // String desc
     150: invokespecial #134                // Method ca/uhn/fhir/rest/gclient/StringClientParam."<init>":(Ljava/lang/String;)V
     153: putstatic     #175                // Field DESC:Lca/uhn/fhir/rest/gclient/StringClientParam;
     156: new           #164                // class ca/uhn/fhir/rest/gclient/ReferenceClientParam
     159: dup
     160: ldc           #178                // String patient
     162: invokespecial #168                // Method ca/uhn/fhir/rest/gclient/ReferenceClientParam."<init>":(Ljava/lang/String;)V
     165: putstatic     #180                // Field PATIENT:Lca/uhn/fhir/rest/gclient/ReferenceClientParam;
     168: new           #97                 // class ca/uhn/fhir/rest/gclient/TokenClientParam
     171: dup
     172: ldc           #183                // String altid
     174: invokespecial #101                // Method ca/uhn/fhir/rest/gclient/TokenClientParam."<init>":(Ljava/lang/String;)V
     177: putstatic     #185                // Field ALTID:Lca/uhn/fhir/rest/gclient/TokenClientParam;
     180: new           #164                // class ca/uhn/fhir/rest/gclient/ReferenceClientParam
     183: dup
     184: ldc           #188                // String participant
     186: invokespecial #168                // Method ca/uhn/fhir/rest/gclient/ReferenceClientParam."<init>":(Ljava/lang/String;)V
     189: putstatic     #190                // Field PARTICIPANT:Lca/uhn/fhir/rest/gclient/ReferenceClientParam;
     192: new           #193                // class ca/uhn/fhir/rest/gclient/UriClientParam
     195: dup
     196: ldc           #195                // String policy
     198: invokespecial #197                // Method ca/uhn/fhir/rest/gclient/UriClientParam."<init>":(Ljava/lang/String;)V
     201: putstatic     #198                // Field POLICY:Lca/uhn/fhir/rest/gclient/UriClientParam;
     204: new           #202                // class ca/uhn/fhir/model/api/Include
     207: dup
     208: ldc           #204                // String AuditEvent:participant
     210: invokespecial #206                // Method ca/uhn/fhir/model/api/Include."<init>":(Ljava/lang/String;)V
     213: putstatic     #207                // Field INCLUDE_PARTICIPANT:Lca/uhn/fhir/model/api/Include;
     216: new           #202                // class ca/uhn/fhir/model/api/Include
     219: dup
     220: ldc           #211                // String AuditEvent:patient
     222: invokespecial #206                // Method ca/uhn/fhir/model/api/Include."<init>":(Ljava/lang/String;)V
     225: putstatic     #213                // Field INCLUDE_PATIENT:Lca/uhn/fhir/model/api/Include;
     228: new           #202                // class ca/uhn/fhir/model/api/Include
     231: dup
     232: ldc           #216                // String AuditEvent:reference
     234: invokespecial #206                // Method ca/uhn/fhir/model/api/Include."<init>":(Ljava/lang/String;)V
     237: putstatic     #218                // Field INCLUDE_REFERENCE:Lca/uhn/fhir/model/api/Include;
     240: return
}
