Compiled from "BaseResource.java"
public abstract class ca.uhn.fhir.model.dstu2.resource.BaseResource extends ca.uhn.fhir.model.api.BaseElement implements ca.uhn.fhir.model.api.IResource {
  public static final ca.uhn.fhir.rest.gclient.StringClientParam RES_ID;

  public static final java.lang.String SP_RES_ID;

  private ca.uhn.fhir.model.dstu2.composite.ContainedDt myContained;

  private ca.uhn.fhir.model.primitive.IdDt myId;

  private ca.uhn.fhir.model.primitive.CodeDt myLanguage;

  private ca.uhn.fhir.model.base.resource.ResourceMetadataMap myResourceMetadata;

  private ca.uhn.fhir.model.dstu2.composite.NarrativeDt myText;

  public ca.uhn.fhir.model.dstu2.resource.BaseResource();
    Code:
       0: aload_0
       1: invokespecial #1                  // Method ca/uhn/fhir/model/api/BaseElement."<init>":()V
       4: return

  public ca.uhn.fhir.model.dstu2.composite.ContainedDt getContained();
    Code:
       0: aload_0
       1: getfield      #7                  // Field myContained:Lca/uhn/fhir/model/dstu2/composite/ContainedDt;
       4: ifnonnull     18
       7: aload_0
       8: new           #13                 // class ca/uhn/fhir/model/dstu2/composite/ContainedDt
      11: dup
      12: invokespecial #15                 // Method ca/uhn/fhir/model/dstu2/composite/ContainedDt."<init>":()V
      15: putfield      #7                  // Field myContained:Lca/uhn/fhir/model/dstu2/composite/ContainedDt;
      18: aload_0
      19: getfield      #7                  // Field myContained:Lca/uhn/fhir/model/dstu2/composite/ContainedDt;
      22: areturn

  public ca.uhn.fhir.model.primitive.IdDt getId();
    Code:
       0: aload_0
       1: getfield      #16                 // Field myId:Lca/uhn/fhir/model/primitive/IdDt;
       4: ifnonnull     18
       7: aload_0
       8: new           #20                 // class ca/uhn/fhir/model/primitive/IdDt
      11: dup
      12: invokespecial #22                 // Method ca/uhn/fhir/model/primitive/IdDt."<init>":()V
      15: putfield      #16                 // Field myId:Lca/uhn/fhir/model/primitive/IdDt;
      18: aload_0
      19: getfield      #16                 // Field myId:Lca/uhn/fhir/model/primitive/IdDt;
      22: areturn

  public org.hl7.fhir.instance.model.api.IIdType getIdElement();
    Code:
       0: aload_0
       1: invokevirtual #23                 // Method getId:()Lca/uhn/fhir/model/primitive/IdDt;
       4: areturn

  public ca.uhn.fhir.model.primitive.CodeDt getLanguage();
    Code:
       0: aload_0
       1: getfield      #27                 // Field myLanguage:Lca/uhn/fhir/model/primitive/CodeDt;
       4: ifnonnull     18
       7: aload_0
       8: new           #31                 // class ca/uhn/fhir/model/primitive/CodeDt
      11: dup
      12: invokespecial #33                 // Method ca/uhn/fhir/model/primitive/CodeDt."<init>":()V
      15: putfield      #27                 // Field myLanguage:Lca/uhn/fhir/model/primitive/CodeDt;
      18: aload_0
      19: getfield      #27                 // Field myLanguage:Lca/uhn/fhir/model/primitive/CodeDt;
      22: areturn

  public org.hl7.fhir.instance.model.api.IBaseMetaType getMeta();
    Code:
       0: new           #34                 // class ca/uhn/fhir/model/dstu2/resource/BaseResource$1
       3: dup
       4: aload_0
       5: invokespecial #36                 // Method ca/uhn/fhir/model/dstu2/resource/BaseResource$1."<init>":(Lca/uhn/fhir/model/dstu2/resource/BaseResource;)V
       8: areturn

  public ca.uhn.fhir.model.base.resource.ResourceMetadataMap getResourceMetadata();
    Code:
       0: aload_0
       1: getfield      #39                 // Field myResourceMetadata:Lca/uhn/fhir/model/base/resource/ResourceMetadataMap;
       4: ifnonnull     18
       7: aload_0
       8: new           #43                 // class ca/uhn/fhir/model/base/resource/ResourceMetadataMap
      11: dup
      12: invokespecial #45                 // Method ca/uhn/fhir/model/base/resource/ResourceMetadataMap."<init>":()V
      15: putfield      #39                 // Field myResourceMetadata:Lca/uhn/fhir/model/base/resource/ResourceMetadataMap;
      18: aload_0
      19: getfield      #39                 // Field myResourceMetadata:Lca/uhn/fhir/model/base/resource/ResourceMetadataMap;
      22: areturn

  public ca.uhn.fhir.model.dstu2.composite.NarrativeDt getText();
    Code:
       0: aload_0
       1: getfield      #46                 // Field myText:Lca/uhn/fhir/model/dstu2/composite/NarrativeDt;
       4: ifnonnull     18
       7: aload_0
       8: new           #50                 // class ca/uhn/fhir/model/dstu2/composite/NarrativeDt
      11: dup
      12: invokespecial #52                 // Method ca/uhn/fhir/model/dstu2/composite/NarrativeDt."<init>":()V
      15: putfield      #46                 // Field myText:Lca/uhn/fhir/model/dstu2/composite/NarrativeDt;
      18: aload_0
      19: getfield      #46                 // Field myText:Lca/uhn/fhir/model/dstu2/composite/NarrativeDt;
      22: areturn

  protected boolean isBaseEmpty();
    Code:
       0: aload_0
       1: invokespecial #53                 // Method ca/uhn/fhir/model/api/BaseElement.isBaseEmpty:()Z
       4: ifeq          42
       7: iconst_3
       8: anewarray     #57                 // class ca/uhn/fhir/model/api/IElement
      11: dup
      12: iconst_0
      13: aload_0
      14: getfield      #27                 // Field myLanguage:Lca/uhn/fhir/model/primitive/CodeDt;
      17: aastore
      18: dup
      19: iconst_1
      20: aload_0
      21: getfield      #46                 // Field myText:Lca/uhn/fhir/model/dstu2/composite/NarrativeDt;
      24: aastore
      25: dup
      26: iconst_2
      27: aload_0
      28: getfield      #16                 // Field myId:Lca/uhn/fhir/model/primitive/IdDt;
      31: aastore
      32: invokestatic  #59                 // Method ca/uhn/fhir/util/ElementUtil.isEmpty:([Lca/uhn/fhir/model/api/IElement;)Z
      35: ifeq          42
      38: iconst_1
      39: goto          43
      42: iconst_0
      43: ireturn

  public void setContained(ca.uhn.fhir.model.dstu2.composite.ContainedDt);
    Code:
       0: aload_0
       1: aload_1
       2: putfield      #7                  // Field myContained:Lca/uhn/fhir/model/dstu2/composite/ContainedDt;
       5: return

  public void setId(ca.uhn.fhir.model.primitive.IdDt);
    Code:
       0: aload_0
       1: aload_1
       2: putfield      #16                 // Field myId:Lca/uhn/fhir/model/primitive/IdDt;
       5: return

  public ca.uhn.fhir.model.dstu2.resource.BaseResource setId(org.hl7.fhir.instance.model.api.IIdType);
    Code:
       0: aload_1
       1: instanceof    #20                 // class ca/uhn/fhir/model/primitive/IdDt
       4: ifeq          18
       7: aload_0
       8: aload_1
       9: checkcast     #20                 // class ca/uhn/fhir/model/primitive/IdDt
      12: putfield      #16                 // Field myId:Lca/uhn/fhir/model/primitive/IdDt;
      15: goto          47
      18: aload_1
      19: ifnull        42
      22: aload_0
      23: new           #20                 // class ca/uhn/fhir/model/primitive/IdDt
      26: dup
      27: aload_1
      28: invokeinterface #65,  1           // InterfaceMethod org/hl7/fhir/instance/model/api/IIdType.getValue:()Ljava/lang/String;
      33: invokespecial #71                 // Method ca/uhn/fhir/model/primitive/IdDt."<init>":(Ljava/lang/String;)V
      36: putfield      #16                 // Field myId:Lca/uhn/fhir/model/primitive/IdDt;
      39: goto          47
      42: aload_0
      43: aconst_null
      44: putfield      #16                 // Field myId:Lca/uhn/fhir/model/primitive/IdDt;
      47: aload_0
      48: areturn

  public ca.uhn.fhir.model.dstu2.resource.BaseResource setId(java.lang.String);
    Code:
       0: aload_1
       1: ifnonnull     12
       4: aload_0
       5: aconst_null
       6: putfield      #16                 // Field myId:Lca/uhn/fhir/model/primitive/IdDt;
       9: goto          24
      12: aload_0
      13: new           #20                 // class ca/uhn/fhir/model/primitive/IdDt
      16: dup
      17: aload_1
      18: invokespecial #71                 // Method ca/uhn/fhir/model/primitive/IdDt."<init>":(Ljava/lang/String;)V
      21: putfield      #16                 // Field myId:Lca/uhn/fhir/model/primitive/IdDt;
      24: aload_0
      25: areturn

  public void setLanguage(ca.uhn.fhir.model.primitive.CodeDt);
    Code:
       0: aload_0
       1: aload_1
       2: putfield      #27                 // Field myLanguage:Lca/uhn/fhir/model/primitive/CodeDt;
       5: return

  public void setResourceMetadata(ca.uhn.fhir.model.base.resource.ResourceMetadataMap);
    Code:
       0: aload_1
       1: ldc           #74                 // String The Map must not be null
       3: iconst_0
       4: anewarray     #76                 // class java/lang/Object
       7: invokestatic  #78                 // Method org/apache/commons/lang3/Validate.notNull:(Ljava/lang/Object;Ljava/lang/String;[Ljava/lang/Object;)Ljava/lang/Object;
      10: pop
      11: aload_0
      12: aload_1
      13: putfield      #39                 // Field myResourceMetadata:Lca/uhn/fhir/model/base/resource/ResourceMetadataMap;
      16: return

  public void setText(ca.uhn.fhir.model.dstu2.composite.NarrativeDt);
    Code:
       0: aload_0
       1: aload_1
       2: putfield      #46                 // Field myText:Lca/uhn/fhir/model/dstu2/composite/NarrativeDt;
       5: return

  public java.lang.String toString();
    Code:
       0: new           #84                 // class org/apache/commons/lang3/builder/ToStringBuilder
       3: dup
       4: aload_0
       5: getstatic     #86                 // Field org/apache/commons/lang3/builder/ToStringStyle.SHORT_PREFIX_STYLE:Lorg/apache/commons/lang3/builder/ToStringStyle;
       8: invokespecial #92                 // Method org/apache/commons/lang3/builder/ToStringBuilder."<init>":(Ljava/lang/Object;Lorg/apache/commons/lang3/builder/ToStringStyle;)V
      11: astore_1
      12: aload_1
      13: ldc           #95                 // String id
      15: aload_0
      16: invokevirtual #23                 // Method getId:()Lca/uhn/fhir/model/primitive/IdDt;
      19: invokevirtual #97                 // Method ca/uhn/fhir/model/primitive/IdDt.toUnqualified:()Lca/uhn/fhir/model/primitive/IdDt;
      22: invokevirtual #100                // Method org/apache/commons/lang3/builder/ToStringBuilder.append:(Ljava/lang/String;Ljava/lang/Object;)Lorg/apache/commons/lang3/builder/ToStringBuilder;
      25: pop
      26: aload_1
      27: invokevirtual #104                // Method org/apache/commons/lang3/builder/ToStringBuilder.toString:()Ljava/lang/String;
      30: areturn

  public ca.uhn.fhir.model.base.composite.BaseNarrativeDt getText();
    Code:
       0: aload_0
       1: invokevirtual #107                // Method getText:()Lca/uhn/fhir/model/dstu2/composite/NarrativeDt;
       4: areturn

  public ca.uhn.fhir.model.base.composite.BaseContainedDt getContained();
    Code:
       0: aload_0
       1: invokevirtual #111                // Method getContained:()Lca/uhn/fhir/model/dstu2/composite/ContainedDt;
       4: areturn

  public org.hl7.fhir.instance.model.api.IBaseResource setId(org.hl7.fhir.instance.model.api.IIdType);
    Code:
       0: aload_0
       1: aload_1
       2: invokevirtual #115                // Method setId:(Lorg/hl7/fhir/instance/model/api/IIdType;)Lca/uhn/fhir/model/dstu2/resource/BaseResource;
       5: areturn

  public org.hl7.fhir.instance.model.api.IBaseResource setId(java.lang.String);
    Code:
       0: aload_0
       1: aload_1
       2: invokevirtual #119                // Method setId:(Ljava/lang/String;)Lca/uhn/fhir/model/dstu2/resource/BaseResource;
       5: areturn

  static {};
    Code:
       0: new           #122                // class ca/uhn/fhir/rest/gclient/StringClientParam
       3: dup
       4: ldc           #124                // String _id
       6: invokespecial #126                // Method ca/uhn/fhir/rest/gclient/StringClientParam."<init>":(Ljava/lang/String;)V
       9: putstatic     #127                // Field RES_ID:Lca/uhn/fhir/rest/gclient/StringClientParam;
      12: return
}
