Compiled from "ClaimResponse.java"
public class ca.uhn.fhir.model.dstu2.resource.ClaimResponse extends ca.uhn.fhir.model.dstu2.resource.BaseResource implements ca.uhn.fhir.model.api.IResource {
  public static final java.lang.String SP_IDENTIFIER;

  public static final ca.uhn.fhir.rest.gclient.TokenClientParam IDENTIFIER;

  private java.util.List<ca.uhn.fhir.model.dstu2.composite.IdentifierDt> myIdentifier;

  private ca.uhn.fhir.model.dstu2.composite.ResourceReferenceDt myRequest;

  private ca.uhn.fhir.model.dstu2.composite.CodingDt myRuleset;

  private ca.uhn.fhir.model.dstu2.composite.CodingDt myOriginalRuleset;

  private ca.uhn.fhir.model.primitive.DateTimeDt myCreated;

  private ca.uhn.fhir.model.dstu2.composite.ResourceReferenceDt myOrganization;

  private ca.uhn.fhir.model.dstu2.composite.ResourceReferenceDt myRequestProvider;

  private ca.uhn.fhir.model.dstu2.composite.ResourceReferenceDt myRequestOrganization;

  private ca.uhn.fhir.model.primitive.BoundCodeDt<ca.uhn.fhir.model.dstu2.valueset.RemittanceOutcomeEnum> myOutcome;

  private ca.uhn.fhir.model.primitive.StringDt myDisposition;

  private ca.uhn.fhir.model.dstu2.composite.CodingDt myPayeeType;

  private java.util.List<ca.uhn.fhir.model.dstu2.resource.ClaimResponse$Item> myItem;

  private java.util.List<ca.uhn.fhir.model.dstu2.resource.ClaimResponse$AddItem> myAddItem;

  private java.util.List<ca.uhn.fhir.model.dstu2.resource.ClaimResponse$Error> myError;

  private ca.uhn.fhir.model.dstu2.composite.MoneyDt myTotalCost;

  private ca.uhn.fhir.model.dstu2.composite.MoneyDt myUnallocDeductable;

  private ca.uhn.fhir.model.dstu2.composite.MoneyDt myTotalBenefit;

  private ca.uhn.fhir.model.dstu2.composite.MoneyDt myPaymentAdjustment;

  private ca.uhn.fhir.model.dstu2.composite.CodingDt myPaymentAdjustmentReason;

  private ca.uhn.fhir.model.primitive.DateDt myPaymentDate;

  private ca.uhn.fhir.model.dstu2.composite.MoneyDt myPaymentAmount;

  private ca.uhn.fhir.model.dstu2.composite.IdentifierDt myPaymentRef;

  private ca.uhn.fhir.model.dstu2.composite.CodingDt myReserved;

  private ca.uhn.fhir.model.dstu2.composite.CodingDt myForm;

  private java.util.List<ca.uhn.fhir.model.dstu2.resource.ClaimResponse$Note> myNote;

  private java.util.List<ca.uhn.fhir.model.dstu2.resource.ClaimResponse$Coverage> myCoverage;

  public ca.uhn.fhir.model.dstu2.resource.ClaimResponse();
    Code:
       0: aload_0
       1: invokespecial #1                  // Method ca/uhn/fhir/model/dstu2/resource/BaseResource."<init>":()V
       4: return

  public boolean isEmpty();
    Code:
       0: aload_0
       1: invokespecial #7                  // Method ca/uhn/fhir/model/dstu2/resource/BaseResource.isBaseEmpty:()Z
       4: ifeq          224
       7: bipush        26
       9: anewarray     #11                 // class java/lang/Object
      12: dup
      13: iconst_0
      14: aload_0
      15: getfield      #13                 // Field myIdentifier:Ljava/util/List;
      18: aastore
      19: dup
      20: iconst_1
      21: aload_0
      22: getfield      #19                 // Field myRequest:Lca/uhn/fhir/model/dstu2/composite/ResourceReferenceDt;
      25: aastore
      26: dup
      27: iconst_2
      28: aload_0
      29: getfield      #23                 // Field myRuleset:Lca/uhn/fhir/model/dstu2/composite/CodingDt;
      32: aastore
      33: dup
      34: iconst_3
      35: aload_0
      36: getfield      #27                 // Field myOriginalRuleset:Lca/uhn/fhir/model/dstu2/composite/CodingDt;
      39: aastore
      40: dup
      41: iconst_4
      42: aload_0
      43: getfield      #30                 // Field myCreated:Lca/uhn/fhir/model/primitive/DateTimeDt;
      46: aastore
      47: dup
      48: iconst_5
      49: aload_0
      50: getfield      #34                 // Field myOrganization:Lca/uhn/fhir/model/dstu2/composite/ResourceReferenceDt;
      53: aastore
      54: dup
      55: bipush        6
      57: aload_0
      58: getfield      #37                 // Field myRequestProvider:Lca/uhn/fhir/model/dstu2/composite/ResourceReferenceDt;
      61: aastore
      62: dup
      63: bipush        7
      65: aload_0
      66: getfield      #40                 // Field myRequestOrganization:Lca/uhn/fhir/model/dstu2/composite/ResourceReferenceDt;
      69: aastore
      70: dup
      71: bipush        8
      73: aload_0
      74: getfield      #43                 // Field myOutcome:Lca/uhn/fhir/model/primitive/BoundCodeDt;
      77: aastore
      78: dup
      79: bipush        9
      81: aload_0
      82: getfield      #47                 // Field myDisposition:Lca/uhn/fhir/model/primitive/StringDt;
      85: aastore
      86: dup
      87: bipush        10
      89: aload_0
      90: getfield      #51                 // Field myPayeeType:Lca/uhn/fhir/model/dstu2/composite/CodingDt;
      93: aastore
      94: dup
      95: bipush        11
      97: aload_0
      98: getfield      #54                 // Field myItem:Ljava/util/List;
     101: aastore
     102: dup
     103: bipush        12
     105: aload_0
     106: getfield      #57                 // Field myAddItem:Ljava/util/List;
     109: aastore
     110: dup
     111: bipush        13
     113: aload_0
     114: getfield      #60                 // Field myError:Ljava/util/List;
     117: aastore
     118: dup
     119: bipush        14
     121: aload_0
     122: getfield      #63                 // Field myTotalCost:Lca/uhn/fhir/model/dstu2/composite/MoneyDt;
     125: aastore
     126: dup
     127: bipush        15
     129: aload_0
     130: getfield      #67                 // Field myUnallocDeductable:Lca/uhn/fhir/model/dstu2/composite/MoneyDt;
     133: aastore
     134: dup
     135: bipush        16
     137: aload_0
     138: getfield      #70                 // Field myTotalBenefit:Lca/uhn/fhir/model/dstu2/composite/MoneyDt;
     141: aastore
     142: dup
     143: bipush        17
     145: aload_0
     146: getfield      #73                 // Field myPaymentAdjustment:Lca/uhn/fhir/model/dstu2/composite/MoneyDt;
     149: aastore
     150: dup
     151: bipush        18
     153: aload_0
     154: getfield      #76                 // Field myPaymentAdjustmentReason:Lca/uhn/fhir/model/dstu2/composite/CodingDt;
     157: aastore
     158: dup
     159: bipush        19
     161: aload_0
     162: getfield      #79                 // Field myPaymentDate:Lca/uhn/fhir/model/primitive/DateDt;
     165: aastore
     166: dup
     167: bipush        20
     169: aload_0
     170: getfield      #83                 // Field myPaymentAmount:Lca/uhn/fhir/model/dstu2/composite/MoneyDt;
     173: aastore
     174: dup
     175: bipush        21
     177: aload_0
     178: getfield      #86                 // Field myPaymentRef:Lca/uhn/fhir/model/dstu2/composite/IdentifierDt;
     181: aastore
     182: dup
     183: bipush        22
     185: aload_0
     186: getfield      #90                 // Field myReserved:Lca/uhn/fhir/model/dstu2/composite/CodingDt;
     189: aastore
     190: dup
     191: bipush        23
     193: aload_0
     194: getfield      #93                 // Field myForm:Lca/uhn/fhir/model/dstu2/composite/CodingDt;
     197: aastore
     198: dup
     199: bipush        24
     201: aload_0
     202: getfield      #96                 // Field myNote:Ljava/util/List;
     205: aastore
     206: dup
     207: bipush        25
     209: aload_0
     210: getfield      #99                 // Field myCoverage:Ljava/util/List;
     213: aastore
     214: invokestatic  #102                // Method ca/uhn/fhir/util/ElementUtil.isEmpty:([Ljava/lang/Object;)Z
     217: ifeq          224
     220: iconst_1
     221: goto          225
     224: iconst_0
     225: ireturn

  public <T extends ca.uhn.fhir.model.api.IElement> java.util.List<T> getAllPopulatedChildElementsOfType(java.lang.Class<T>);
    Code:
       0: aload_1
       1: bipush        26
       3: anewarray     #11                 // class java/lang/Object
       6: dup
       7: iconst_0
       8: aload_0
       9: getfield      #13                 // Field myIdentifier:Ljava/util/List;
      12: aastore
      13: dup
      14: iconst_1
      15: aload_0
      16: getfield      #19                 // Field myRequest:Lca/uhn/fhir/model/dstu2/composite/ResourceReferenceDt;
      19: aastore
      20: dup
      21: iconst_2
      22: aload_0
      23: getfield      #23                 // Field myRuleset:Lca/uhn/fhir/model/dstu2/composite/CodingDt;
      26: aastore
      27: dup
      28: iconst_3
      29: aload_0
      30: getfield      #27                 // Field myOriginalRuleset:Lca/uhn/fhir/model/dstu2/composite/CodingDt;
      33: aastore
      34: dup
      35: iconst_4
      36: aload_0
      37: getfield      #30                 // Field myCreated:Lca/uhn/fhir/model/primitive/DateTimeDt;
      40: aastore
      41: dup
      42: iconst_5
      43: aload_0
      44: getfield      #34                 // Field myOrganization:Lca/uhn/fhir/model/dstu2/composite/ResourceReferenceDt;
      47: aastore
      48: dup
      49: bipush        6
      51: aload_0
      52: getfield      #37                 // Field myRequestProvider:Lca/uhn/fhir/model/dstu2/composite/ResourceReferenceDt;
      55: aastore
      56: dup
      57: bipush        7
      59: aload_0
      60: getfield      #40                 // Field myRequestOrganization:Lca/uhn/fhir/model/dstu2/composite/ResourceReferenceDt;
      63: aastore
      64: dup
      65: bipush        8
      67: aload_0
      68: getfield      #43                 // Field myOutcome:Lca/uhn/fhir/model/primitive/BoundCodeDt;
      71: aastore
      72: dup
      73: bipush        9
      75: aload_0
      76: getfield      #47                 // Field myDisposition:Lca/uhn/fhir/model/primitive/StringDt;
      79: aastore
      80: dup
      81: bipush        10
      83: aload_0
      84: getfield      #51                 // Field myPayeeType:Lca/uhn/fhir/model/dstu2/composite/CodingDt;
      87: aastore
      88: dup
      89: bipush        11
      91: aload_0
      92: getfield      #54                 // Field myItem:Ljava/util/List;
      95: aastore
      96: dup
      97: bipush        12
      99: aload_0
     100: getfield      #57                 // Field myAddItem:Ljava/util/List;
     103: aastore
     104: dup
     105: bipush        13
     107: aload_0
     108: getfield      #60                 // Field myError:Ljava/util/List;
     111: aastore
     112: dup
     113: bipush        14
     115: aload_0
     116: getfield      #63                 // Field myTotalCost:Lca/uhn/fhir/model/dstu2/composite/MoneyDt;
     119: aastore
     120: dup
     121: bipush        15
     123: aload_0
     124: getfield      #67                 // Field myUnallocDeductable:Lca/uhn/fhir/model/dstu2/composite/MoneyDt;
     127: aastore
     128: dup
     129: bipush        16
     131: aload_0
     132: getfield      #70                 // Field myTotalBenefit:Lca/uhn/fhir/model/dstu2/composite/MoneyDt;
     135: aastore
     136: dup
     137: bipush        17
     139: aload_0
     140: getfield      #73                 // Field myPaymentAdjustment:Lca/uhn/fhir/model/dstu2/composite/MoneyDt;
     143: aastore
     144: dup
     145: bipush        18
     147: aload_0
     148: getfield      #76                 // Field myPaymentAdjustmentReason:Lca/uhn/fhir/model/dstu2/composite/CodingDt;
     151: aastore
     152: dup
     153: bipush        19
     155: aload_0
     156: getfield      #79                 // Field myPaymentDate:Lca/uhn/fhir/model/primitive/DateDt;
     159: aastore
     160: dup
     161: bipush        20
     163: aload_0
     164: getfield      #83                 // Field myPaymentAmount:Lca/uhn/fhir/model/dstu2/composite/MoneyDt;
     167: aastore
     168: dup
     169: bipush        21
     171: aload_0
     172: getfield      #86                 // Field myPaymentRef:Lca/uhn/fhir/model/dstu2/composite/IdentifierDt;
     175: aastore
     176: dup
     177: bipush        22
     179: aload_0
     180: getfield      #90                 // Field myReserved:Lca/uhn/fhir/model/dstu2/composite/CodingDt;
     183: aastore
     184: dup
     185: bipush        23
     187: aload_0
     188: getfield      #93                 // Field myForm:Lca/uhn/fhir/model/dstu2/composite/CodingDt;
     191: aastore
     192: dup
     193: bipush        24
     195: aload_0
     196: getfield      #96                 // Field myNote:Ljava/util/List;
     199: aastore
     200: dup
     201: bipush        25
     203: aload_0
     204: getfield      #99                 // Field myCoverage:Ljava/util/List;
     207: aastore
     208: invokestatic  #108                // Method ca/uhn/fhir/util/ElementUtil.allPopulatedChildElements:(Ljava/lang/Class;[Ljava/lang/Object;)Ljava/util/List;
     211: areturn

  public java.util.List<ca.uhn.fhir.model.dstu2.composite.IdentifierDt> getIdentifier();
    Code:
       0: aload_0
       1: getfield      #13                 // Field myIdentifier:Ljava/util/List;
       4: ifnonnull     18
       7: aload_0
       8: new           #112                // class java/util/ArrayList
      11: dup
      12: invokespecial #114                // Method java/util/ArrayList."<init>":()V
      15: putfield      #13                 // Field myIdentifier:Ljava/util/List;
      18: aload_0
      19: getfield      #13                 // Field myIdentifier:Ljava/util/List;
      22: areturn

  public ca.uhn.fhir.model.dstu2.resource.ClaimResponse setIdentifier(java.util.List<ca.uhn.fhir.model.dstu2.composite.IdentifierDt>);
    Code:
       0: aload_0
       1: aload_1
       2: putfield      #13                 // Field myIdentifier:Ljava/util/List;
       5: aload_0
       6: areturn

  public ca.uhn.fhir.model.dstu2.composite.IdentifierDt addIdentifier();
    Code:
       0: new           #115                // class ca/uhn/fhir/model/dstu2/composite/IdentifierDt
       3: dup
       4: invokespecial #117                // Method ca/uhn/fhir/model/dstu2/composite/IdentifierDt."<init>":()V
       7: astore_1
       8: aload_0
       9: invokevirtual #118                // Method getIdentifier:()Ljava/util/List;
      12: aload_1
      13: invokeinterface #122,  2          // InterfaceMethod java/util/List.add:(Ljava/lang/Object;)Z
      18: pop
      19: aload_1
      20: areturn

  public ca.uhn.fhir.model.dstu2.resource.ClaimResponse addIdentifier(ca.uhn.fhir.model.dstu2.composite.IdentifierDt);
    Code:
       0: aload_1
       1: ifnonnull     14
       4: new           #128                // class java/lang/NullPointerException
       7: dup
       8: ldc           #130                // String theValue must not be null
      10: invokespecial #132                // Method java/lang/NullPointerException."<init>":(Ljava/lang/String;)V
      13: athrow
      14: aload_0
      15: invokevirtual #118                // Method getIdentifier:()Ljava/util/List;
      18: aload_1
      19: invokeinterface #122,  2          // InterfaceMethod java/util/List.add:(Ljava/lang/Object;)Z
      24: pop
      25: aload_0
      26: areturn

  public ca.uhn.fhir.model.dstu2.composite.IdentifierDt getIdentifierFirstRep();
    Code:
       0: aload_0
       1: invokevirtual #118                // Method getIdentifier:()Ljava/util/List;
       4: invokeinterface #135,  1          // InterfaceMethod java/util/List.isEmpty:()Z
       9: ifeq          17
      12: aload_0
      13: invokevirtual #137                // Method addIdentifier:()Lca/uhn/fhir/model/dstu2/composite/IdentifierDt;
      16: areturn
      17: aload_0
      18: invokevirtual #118                // Method getIdentifier:()Ljava/util/List;
      21: iconst_0
      22: invokeinterface #141,  2          // InterfaceMethod java/util/List.get:(I)Ljava/lang/Object;
      27: checkcast     #115                // class ca/uhn/fhir/model/dstu2/composite/IdentifierDt
      30: areturn

  public ca.uhn.fhir.model.dstu2.composite.ResourceReferenceDt getRequest();
    Code:
       0: aload_0
       1: getfield      #19                 // Field myRequest:Lca/uhn/fhir/model/dstu2/composite/ResourceReferenceDt;
       4: ifnonnull     18
       7: aload_0
       8: new           #145                // class ca/uhn/fhir/model/dstu2/composite/ResourceReferenceDt
      11: dup
      12: invokespecial #147                // Method ca/uhn/fhir/model/dstu2/composite/ResourceReferenceDt."<init>":()V
      15: putfield      #19                 // Field myRequest:Lca/uhn/fhir/model/dstu2/composite/ResourceReferenceDt;
      18: aload_0
      19: getfield      #19                 // Field myRequest:Lca/uhn/fhir/model/dstu2/composite/ResourceReferenceDt;
      22: areturn

  public ca.uhn.fhir.model.dstu2.resource.ClaimResponse setRequest(ca.uhn.fhir.model.dstu2.composite.ResourceReferenceDt);
    Code:
       0: aload_0
       1: aload_1
       2: putfield      #19                 // Field myRequest:Lca/uhn/fhir/model/dstu2/composite/ResourceReferenceDt;
       5: aload_0
       6: areturn

  public ca.uhn.fhir.model.dstu2.composite.CodingDt getRuleset();
    Code:
       0: aload_0
       1: getfield      #23                 // Field myRuleset:Lca/uhn/fhir/model/dstu2/composite/CodingDt;
       4: ifnonnull     18
       7: aload_0
       8: new           #148                // class ca/uhn/fhir/model/dstu2/composite/CodingDt
      11: dup
      12: invokespecial #150                // Method ca/uhn/fhir/model/dstu2/composite/CodingDt."<init>":()V
      15: putfield      #23                 // Field myRuleset:Lca/uhn/fhir/model/dstu2/composite/CodingDt;
      18: aload_0
      19: getfield      #23                 // Field myRuleset:Lca/uhn/fhir/model/dstu2/composite/CodingDt;
      22: areturn

  public ca.uhn.fhir.model.dstu2.resource.ClaimResponse setRuleset(ca.uhn.fhir.model.dstu2.composite.CodingDt);
    Code:
       0: aload_0
       1: aload_1
       2: putfield      #23                 // Field myRuleset:Lca/uhn/fhir/model/dstu2/composite/CodingDt;
       5: aload_0
       6: areturn

  public ca.uhn.fhir.model.dstu2.composite.CodingDt getOriginalRuleset();
    Code:
       0: aload_0
       1: getfield      #27                 // Field myOriginalRuleset:Lca/uhn/fhir/model/dstu2/composite/CodingDt;
       4: ifnonnull     18
       7: aload_0
       8: new           #148                // class ca/uhn/fhir/model/dstu2/composite/CodingDt
      11: dup
      12: invokespecial #150                // Method ca/uhn/fhir/model/dstu2/composite/CodingDt."<init>":()V
      15: putfield      #27                 // Field myOriginalRuleset:Lca/uhn/fhir/model/dstu2/composite/CodingDt;
      18: aload_0
      19: getfield      #27                 // Field myOriginalRuleset:Lca/uhn/fhir/model/dstu2/composite/CodingDt;
      22: areturn

  public ca.uhn.fhir.model.dstu2.resource.ClaimResponse setOriginalRuleset(ca.uhn.fhir.model.dstu2.composite.CodingDt);
    Code:
       0: aload_0
       1: aload_1
       2: putfield      #27                 // Field myOriginalRuleset:Lca/uhn/fhir/model/dstu2/composite/CodingDt;
       5: aload_0
       6: areturn

  public ca.uhn.fhir.model.primitive.DateTimeDt getCreatedElement();
    Code:
       0: aload_0
       1: getfield      #30                 // Field myCreated:Lca/uhn/fhir/model/primitive/DateTimeDt;
       4: ifnonnull     18
       7: aload_0
       8: new           #151                // class ca/uhn/fhir/model/primitive/DateTimeDt
      11: dup
      12: invokespecial #153                // Method ca/uhn/fhir/model/primitive/DateTimeDt."<init>":()V
      15: putfield      #30                 // Field myCreated:Lca/uhn/fhir/model/primitive/DateTimeDt;
      18: aload_0
      19: getfield      #30                 // Field myCreated:Lca/uhn/fhir/model/primitive/DateTimeDt;
      22: areturn

  public java.util.Date getCreated();
    Code:
       0: aload_0
       1: invokevirtual #154                // Method getCreatedElement:()Lca/uhn/fhir/model/primitive/DateTimeDt;
       4: invokevirtual #158                // Method ca/uhn/fhir/model/primitive/DateTimeDt.getValue:()Ljava/lang/Object;
       7: checkcast     #162                // class java/util/Date
      10: areturn

  public ca.uhn.fhir.model.dstu2.resource.ClaimResponse setCreated(ca.uhn.fhir.model.primitive.DateTimeDt);
    Code:
       0: aload_0
       1: aload_1
       2: putfield      #30                 // Field myCreated:Lca/uhn/fhir/model/primitive/DateTimeDt;
       5: aload_0
       6: areturn

  public ca.uhn.fhir.model.dstu2.resource.ClaimResponse setCreated(java.util.Date, ca.uhn.fhir.model.api.TemporalPrecisionEnum);
    Code:
       0: aload_0
       1: new           #151                // class ca/uhn/fhir/model/primitive/DateTimeDt
       4: dup
       5: aload_1
       6: aload_2
       7: invokespecial #164                // Method ca/uhn/fhir/model/primitive/DateTimeDt."<init>":(Ljava/util/Date;Lca/uhn/fhir/model/api/TemporalPrecisionEnum;)V
      10: putfield      #30                 // Field myCreated:Lca/uhn/fhir/model/primitive/DateTimeDt;
      13: aload_0
      14: areturn

  public ca.uhn.fhir.model.dstu2.resource.ClaimResponse setCreatedWithSecondsPrecision(java.util.Date);
    Code:
       0: aload_0
       1: new           #151                // class ca/uhn/fhir/model/primitive/DateTimeDt
       4: dup
       5: aload_1
       6: invokespecial #167                // Method ca/uhn/fhir/model/primitive/DateTimeDt."<init>":(Ljava/util/Date;)V
       9: putfield      #30                 // Field myCreated:Lca/uhn/fhir/model/primitive/DateTimeDt;
      12: aload_0
      13: areturn

  public ca.uhn.fhir.model.dstu2.composite.ResourceReferenceDt getOrganization();
    Code:
       0: aload_0
       1: getfield      #34                 // Field myOrganization:Lca/uhn/fhir/model/dstu2/composite/ResourceReferenceDt;
       4: ifnonnull     18
       7: aload_0
       8: new           #145                // class ca/uhn/fhir/model/dstu2/composite/ResourceReferenceDt
      11: dup
      12: invokespecial #147                // Method ca/uhn/fhir/model/dstu2/composite/ResourceReferenceDt."<init>":()V
      15: putfield      #34                 // Field myOrganization:Lca/uhn/fhir/model/dstu2/composite/ResourceReferenceDt;
      18: aload_0
      19: getfield      #34                 // Field myOrganization:Lca/uhn/fhir/model/dstu2/composite/ResourceReferenceDt;
      22: areturn

  public ca.uhn.fhir.model.dstu2.resource.ClaimResponse setOrganization(ca.uhn.fhir.model.dstu2.composite.ResourceReferenceDt);
    Code:
       0: aload_0
       1: aload_1
       2: putfield      #34                 // Field myOrganization:Lca/uhn/fhir/model/dstu2/composite/ResourceReferenceDt;
       5: aload_0
       6: areturn

  public ca.uhn.fhir.model.dstu2.composite.ResourceReferenceDt getRequestProvider();
    Code:
       0: aload_0
       1: getfield      #37                 // Field myRequestProvider:Lca/uhn/fhir/model/dstu2/composite/ResourceReferenceDt;
       4: ifnonnull     18
       7: aload_0
       8: new           #145                // class ca/uhn/fhir/model/dstu2/composite/ResourceReferenceDt
      11: dup
      12: invokespecial #147                // Method ca/uhn/fhir/model/dstu2/composite/ResourceReferenceDt."<init>":()V
      15: putfield      #37                 // Field myRequestProvider:Lca/uhn/fhir/model/dstu2/composite/ResourceReferenceDt;
      18: aload_0
      19: getfield      #37                 // Field myRequestProvider:Lca/uhn/fhir/model/dstu2/composite/ResourceReferenceDt;
      22: areturn

  public ca.uhn.fhir.model.dstu2.resource.ClaimResponse setRequestProvider(ca.uhn.fhir.model.dstu2.composite.ResourceReferenceDt);
    Code:
       0: aload_0
       1: aload_1
       2: putfield      #37                 // Field myRequestProvider:Lca/uhn/fhir/model/dstu2/composite/ResourceReferenceDt;
       5: aload_0
       6: areturn

  public ca.uhn.fhir.model.dstu2.composite.ResourceReferenceDt getRequestOrganization();
    Code:
       0: aload_0
       1: getfield      #40                 // Field myRequestOrganization:Lca/uhn/fhir/model/dstu2/composite/ResourceReferenceDt;
       4: ifnonnull     18
       7: aload_0
       8: new           #145                // class ca/uhn/fhir/model/dstu2/composite/ResourceReferenceDt
      11: dup
      12: invokespecial #147                // Method ca/uhn/fhir/model/dstu2/composite/ResourceReferenceDt."<init>":()V
      15: putfield      #40                 // Field myRequestOrganization:Lca/uhn/fhir/model/dstu2/composite/ResourceReferenceDt;
      18: aload_0
      19: getfield      #40                 // Field myRequestOrganization:Lca/uhn/fhir/model/dstu2/composite/ResourceReferenceDt;
      22: areturn

  public ca.uhn.fhir.model.dstu2.resource.ClaimResponse setRequestOrganization(ca.uhn.fhir.model.dstu2.composite.ResourceReferenceDt);
    Code:
       0: aload_0
       1: aload_1
       2: putfield      #40                 // Field myRequestOrganization:Lca/uhn/fhir/model/dstu2/composite/ResourceReferenceDt;
       5: aload_0
       6: areturn

  public ca.uhn.fhir.model.primitive.BoundCodeDt<ca.uhn.fhir.model.dstu2.valueset.RemittanceOutcomeEnum> getOutcomeElement();
    Code:
       0: aload_0
       1: getfield      #43                 // Field myOutcome:Lca/uhn/fhir/model/primitive/BoundCodeDt;
       4: ifnonnull     21
       7: aload_0
       8: new           #170                // class ca/uhn/fhir/model/primitive/BoundCodeDt
      11: dup
      12: getstatic     #172                // Field ca/uhn/fhir/model/dstu2/valueset/RemittanceOutcomeEnum.VALUESET_BINDER:Lca/uhn/fhir/model/api/IValueSetEnumBinder;
      15: invokespecial #178                // Method ca/uhn/fhir/model/primitive/BoundCodeDt."<init>":(Lca/uhn/fhir/model/api/IValueSetEnumBinder;)V
      18: putfield      #43                 // Field myOutcome:Lca/uhn/fhir/model/primitive/BoundCodeDt;
      21: aload_0
      22: getfield      #43                 // Field myOutcome:Lca/uhn/fhir/model/primitive/BoundCodeDt;
      25: areturn

  public java.lang.String getOutcome();
    Code:
       0: aload_0
       1: invokevirtual #181                // Method getOutcomeElement:()Lca/uhn/fhir/model/primitive/BoundCodeDt;
       4: invokevirtual #185                // Method ca/uhn/fhir/model/primitive/BoundCodeDt.getValue:()Ljava/lang/Object;
       7: checkcast     #186                // class java/lang/String
      10: areturn

  public ca.uhn.fhir.model.dstu2.resource.ClaimResponse setOutcome(ca.uhn.fhir.model.primitive.BoundCodeDt<ca.uhn.fhir.model.dstu2.valueset.RemittanceOutcomeEnum>);
    Code:
       0: aload_0
       1: aload_1
       2: putfield      #43                 // Field myOutcome:Lca/uhn/fhir/model/primitive/BoundCodeDt;
       5: aload_0
       6: areturn

  public ca.uhn.fhir.model.dstu2.resource.ClaimResponse setOutcome(ca.uhn.fhir.model.dstu2.valueset.RemittanceOutcomeEnum);
    Code:
       0: aload_0
       1: new           #170                // class ca/uhn/fhir/model/primitive/BoundCodeDt
       4: dup
       5: getstatic     #172                // Field ca/uhn/fhir/model/dstu2/valueset/RemittanceOutcomeEnum.VALUESET_BINDER:Lca/uhn/fhir/model/api/IValueSetEnumBinder;
       8: aload_1
       9: invokespecial #188                // Method ca/uhn/fhir/model/primitive/BoundCodeDt."<init>":(Lca/uhn/fhir/model/api/IValueSetEnumBinder;Ljava/lang/Enum;)V
      12: invokevirtual #191                // Method setOutcome:(Lca/uhn/fhir/model/primitive/BoundCodeDt;)Lca/uhn/fhir/model/dstu2/resource/ClaimResponse;
      15: pop
      16: aload_0
      17: areturn

  public ca.uhn.fhir.model.primitive.StringDt getDispositionElement();
    Code:
       0: aload_0
       1: getfield      #47                 // Field myDisposition:Lca/uhn/fhir/model/primitive/StringDt;
       4: ifnonnull     18
       7: aload_0
       8: new           #195                // class ca/uhn/fhir/model/primitive/StringDt
      11: dup
      12: invokespecial #197                // Method ca/uhn/fhir/model/primitive/StringDt."<init>":()V
      15: putfield      #47                 // Field myDisposition:Lca/uhn/fhir/model/primitive/StringDt;
      18: aload_0
      19: getfield      #47                 // Field myDisposition:Lca/uhn/fhir/model/primitive/StringDt;
      22: areturn

  public java.lang.String getDisposition();
    Code:
       0: aload_0
       1: invokevirtual #198                // Method getDispositionElement:()Lca/uhn/fhir/model/primitive/StringDt;
       4: invokevirtual #202                // Method ca/uhn/fhir/model/primitive/StringDt.getValue:()Ljava/lang/Object;
       7: checkcast     #186                // class java/lang/String
      10: areturn

  public ca.uhn.fhir.model.dstu2.resource.ClaimResponse setDisposition(ca.uhn.fhir.model.primitive.StringDt);
    Code:
       0: aload_0
       1: aload_1
       2: putfield      #47                 // Field myDisposition:Lca/uhn/fhir/model/primitive/StringDt;
       5: aload_0
       6: areturn

  public ca.uhn.fhir.model.dstu2.resource.ClaimResponse setDisposition(java.lang.String);
    Code:
       0: aload_0
       1: new           #195                // class ca/uhn/fhir/model/primitive/StringDt
       4: dup
       5: aload_1
       6: invokespecial #203                // Method ca/uhn/fhir/model/primitive/StringDt."<init>":(Ljava/lang/String;)V
       9: putfield      #47                 // Field myDisposition:Lca/uhn/fhir/model/primitive/StringDt;
      12: aload_0
      13: areturn

  public ca.uhn.fhir.model.dstu2.composite.CodingDt getPayeeType();
    Code:
       0: aload_0
       1: getfield      #51                 // Field myPayeeType:Lca/uhn/fhir/model/dstu2/composite/CodingDt;
       4: ifnonnull     18
       7: aload_0
       8: new           #148                // class ca/uhn/fhir/model/dstu2/composite/CodingDt
      11: dup
      12: invokespecial #150                // Method ca/uhn/fhir/model/dstu2/composite/CodingDt."<init>":()V
      15: putfield      #51                 // Field myPayeeType:Lca/uhn/fhir/model/dstu2/composite/CodingDt;
      18: aload_0
      19: getfield      #51                 // Field myPayeeType:Lca/uhn/fhir/model/dstu2/composite/CodingDt;
      22: areturn

  public ca.uhn.fhir.model.dstu2.resource.ClaimResponse setPayeeType(ca.uhn.fhir.model.dstu2.composite.CodingDt);
    Code:
       0: aload_0
       1: aload_1
       2: putfield      #51                 // Field myPayeeType:Lca/uhn/fhir/model/dstu2/composite/CodingDt;
       5: aload_0
       6: areturn

  public java.util.List<ca.uhn.fhir.model.dstu2.resource.ClaimResponse$Item> getItem();
    Code:
       0: aload_0
       1: getfield      #54                 // Field myItem:Ljava/util/List;
       4: ifnonnull     18
       7: aload_0
       8: new           #112                // class java/util/ArrayList
      11: dup
      12: invokespecial #114                // Method java/util/ArrayList."<init>":()V
      15: putfield      #54                 // Field myItem:Ljava/util/List;
      18: aload_0
      19: getfield      #54                 // Field myItem:Ljava/util/List;
      22: areturn

  public ca.uhn.fhir.model.dstu2.resource.ClaimResponse setItem(java.util.List<ca.uhn.fhir.model.dstu2.resource.ClaimResponse$Item>);
    Code:
       0: aload_0
       1: aload_1
       2: putfield      #54                 // Field myItem:Ljava/util/List;
       5: aload_0
       6: areturn

  public ca.uhn.fhir.model.dstu2.resource.ClaimResponse$Item addItem();
    Code:
       0: new           #204                // class ca/uhn/fhir/model/dstu2/resource/ClaimResponse$Item
       3: dup
       4: invokespecial #206                // Method ca/uhn/fhir/model/dstu2/resource/ClaimResponse$Item."<init>":()V
       7: astore_1
       8: aload_0
       9: invokevirtual #207                // Method getItem:()Ljava/util/List;
      12: aload_1
      13: invokeinterface #122,  2          // InterfaceMethod java/util/List.add:(Ljava/lang/Object;)Z
      18: pop
      19: aload_1
      20: areturn

  public ca.uhn.fhir.model.dstu2.resource.ClaimResponse addItem(ca.uhn.fhir.model.dstu2.resource.ClaimResponse$Item);
    Code:
       0: aload_1
       1: ifnonnull     14
       4: new           #128                // class java/lang/NullPointerException
       7: dup
       8: ldc           #130                // String theValue must not be null
      10: invokespecial #132                // Method java/lang/NullPointerException."<init>":(Ljava/lang/String;)V
      13: athrow
      14: aload_0
      15: invokevirtual #207                // Method getItem:()Ljava/util/List;
      18: aload_1
      19: invokeinterface #122,  2          // InterfaceMethod java/util/List.add:(Ljava/lang/Object;)Z
      24: pop
      25: aload_0
      26: areturn

  public ca.uhn.fhir.model.dstu2.resource.ClaimResponse$Item getItemFirstRep();
    Code:
       0: aload_0
       1: invokevirtual #207                // Method getItem:()Ljava/util/List;
       4: invokeinterface #135,  1          // InterfaceMethod java/util/List.isEmpty:()Z
       9: ifeq          17
      12: aload_0
      13: invokevirtual #210                // Method addItem:()Lca/uhn/fhir/model/dstu2/resource/ClaimResponse$Item;
      16: areturn
      17: aload_0
      18: invokevirtual #207                // Method getItem:()Ljava/util/List;
      21: iconst_0
      22: invokeinterface #141,  2          // InterfaceMethod java/util/List.get:(I)Ljava/lang/Object;
      27: checkcast     #204                // class ca/uhn/fhir/model/dstu2/resource/ClaimResponse$Item
      30: areturn

  public java.util.List<ca.uhn.fhir.model.dstu2.resource.ClaimResponse$AddItem> getAddItem();
    Code:
       0: aload_0
       1: getfield      #57                 // Field myAddItem:Ljava/util/List;
       4: ifnonnull     18
       7: aload_0
       8: new           #112                // class java/util/ArrayList
      11: dup
      12: invokespecial #114                // Method java/util/ArrayList."<init>":()V
      15: putfield      #57                 // Field myAddItem:Ljava/util/List;
      18: aload_0
      19: getfield      #57                 // Field myAddItem:Ljava/util/List;
      22: areturn

  public ca.uhn.fhir.model.dstu2.resource.ClaimResponse setAddItem(java.util.List<ca.uhn.fhir.model.dstu2.resource.ClaimResponse$AddItem>);
    Code:
       0: aload_0
       1: aload_1
       2: putfield      #57                 // Field myAddItem:Ljava/util/List;
       5: aload_0
       6: areturn

  public ca.uhn.fhir.model.dstu2.resource.ClaimResponse$AddItem addAddItem();
    Code:
       0: new           #214                // class ca/uhn/fhir/model/dstu2/resource/ClaimResponse$AddItem
       3: dup
       4: invokespecial #216                // Method ca/uhn/fhir/model/dstu2/resource/ClaimResponse$AddItem."<init>":()V
       7: astore_1
       8: aload_0
       9: invokevirtual #217                // Method getAddItem:()Ljava/util/List;
      12: aload_1
      13: invokeinterface #122,  2          // InterfaceMethod java/util/List.add:(Ljava/lang/Object;)Z
      18: pop
      19: aload_1
      20: areturn

  public ca.uhn.fhir.model.dstu2.resource.ClaimResponse addAddItem(ca.uhn.fhir.model.dstu2.resource.ClaimResponse$AddItem);
    Code:
       0: aload_1
       1: ifnonnull     14
       4: new           #128                // class java/lang/NullPointerException
       7: dup
       8: ldc           #130                // String theValue must not be null
      10: invokespecial #132                // Method java/lang/NullPointerException."<init>":(Ljava/lang/String;)V
      13: athrow
      14: aload_0
      15: invokevirtual #217                // Method getAddItem:()Ljava/util/List;
      18: aload_1
      19: invokeinterface #122,  2          // InterfaceMethod java/util/List.add:(Ljava/lang/Object;)Z
      24: pop
      25: aload_0
      26: areturn

  public ca.uhn.fhir.model.dstu2.resource.ClaimResponse$AddItem getAddItemFirstRep();
    Code:
       0: aload_0
       1: invokevirtual #217                // Method getAddItem:()Ljava/util/List;
       4: invokeinterface #135,  1          // InterfaceMethod java/util/List.isEmpty:()Z
       9: ifeq          17
      12: aload_0
      13: invokevirtual #220                // Method addAddItem:()Lca/uhn/fhir/model/dstu2/resource/ClaimResponse$AddItem;
      16: areturn
      17: aload_0
      18: invokevirtual #217                // Method getAddItem:()Ljava/util/List;
      21: iconst_0
      22: invokeinterface #141,  2          // InterfaceMethod java/util/List.get:(I)Ljava/lang/Object;
      27: checkcast     #214                // class ca/uhn/fhir/model/dstu2/resource/ClaimResponse$AddItem
      30: areturn

  public java.util.List<ca.uhn.fhir.model.dstu2.resource.ClaimResponse$Error> getError();
    Code:
       0: aload_0
       1: getfield      #60                 // Field myError:Ljava/util/List;
       4: ifnonnull     18
       7: aload_0
       8: new           #112                // class java/util/ArrayList
      11: dup
      12: invokespecial #114                // Method java/util/ArrayList."<init>":()V
      15: putfield      #60                 // Field myError:Ljava/util/List;
      18: aload_0
      19: getfield      #60                 // Field myError:Ljava/util/List;
      22: areturn

  public ca.uhn.fhir.model.dstu2.resource.ClaimResponse setError(java.util.List<ca.uhn.fhir.model.dstu2.resource.ClaimResponse$Error>);
    Code:
       0: aload_0
       1: aload_1
       2: putfield      #60                 // Field myError:Ljava/util/List;
       5: aload_0
       6: areturn

  public ca.uhn.fhir.model.dstu2.resource.ClaimResponse$Error addError();
    Code:
       0: new           #224                // class ca/uhn/fhir/model/dstu2/resource/ClaimResponse$Error
       3: dup
       4: invokespecial #226                // Method ca/uhn/fhir/model/dstu2/resource/ClaimResponse$Error."<init>":()V
       7: astore_1
       8: aload_0
       9: invokevirtual #227                // Method getError:()Ljava/util/List;
      12: aload_1
      13: invokeinterface #122,  2          // InterfaceMethod java/util/List.add:(Ljava/lang/Object;)Z
      18: pop
      19: aload_1
      20: areturn

  public ca.uhn.fhir.model.dstu2.resource.ClaimResponse addError(ca.uhn.fhir.model.dstu2.resource.ClaimResponse$Error);
    Code:
       0: aload_1
       1: ifnonnull     14
       4: new           #128                // class java/lang/NullPointerException
       7: dup
       8: ldc           #130                // String theValue must not be null
      10: invokespecial #132                // Method java/lang/NullPointerException."<init>":(Ljava/lang/String;)V
      13: athrow
      14: aload_0
      15: invokevirtual #227                // Method getError:()Ljava/util/List;
      18: aload_1
      19: invokeinterface #122,  2          // InterfaceMethod java/util/List.add:(Ljava/lang/Object;)Z
      24: pop
      25: aload_0
      26: areturn

  public ca.uhn.fhir.model.dstu2.resource.ClaimResponse$Error getErrorFirstRep();
    Code:
       0: aload_0
       1: invokevirtual #227                // Method getError:()Ljava/util/List;
       4: invokeinterface #135,  1          // InterfaceMethod java/util/List.isEmpty:()Z
       9: ifeq          17
      12: aload_0
      13: invokevirtual #230                // Method addError:()Lca/uhn/fhir/model/dstu2/resource/ClaimResponse$Error;
      16: areturn
      17: aload_0
      18: invokevirtual #227                // Method getError:()Ljava/util/List;
      21: iconst_0
      22: invokeinterface #141,  2          // InterfaceMethod java/util/List.get:(I)Ljava/lang/Object;
      27: checkcast     #224                // class ca/uhn/fhir/model/dstu2/resource/ClaimResponse$Error
      30: areturn

  public ca.uhn.fhir.model.dstu2.composite.MoneyDt getTotalCost();
    Code:
       0: aload_0
       1: getfield      #63                 // Field myTotalCost:Lca/uhn/fhir/model/dstu2/composite/MoneyDt;
       4: ifnonnull     18
       7: aload_0
       8: new           #234                // class ca/uhn/fhir/model/dstu2/composite/MoneyDt
      11: dup
      12: invokespecial #236                // Method ca/uhn/fhir/model/dstu2/composite/MoneyDt."<init>":()V
      15: putfield      #63                 // Field myTotalCost:Lca/uhn/fhir/model/dstu2/composite/MoneyDt;
      18: aload_0
      19: getfield      #63                 // Field myTotalCost:Lca/uhn/fhir/model/dstu2/composite/MoneyDt;
      22: areturn

  public ca.uhn.fhir.model.dstu2.resource.ClaimResponse setTotalCost(ca.uhn.fhir.model.dstu2.composite.MoneyDt);
    Code:
       0: aload_0
       1: aload_1
       2: putfield      #63                 // Field myTotalCost:Lca/uhn/fhir/model/dstu2/composite/MoneyDt;
       5: aload_0
       6: areturn

  public ca.uhn.fhir.model.dstu2.composite.MoneyDt getUnallocDeductable();
    Code:
       0: aload_0
       1: getfield      #67                 // Field myUnallocDeductable:Lca/uhn/fhir/model/dstu2/composite/MoneyDt;
       4: ifnonnull     18
       7: aload_0
       8: new           #234                // class ca/uhn/fhir/model/dstu2/composite/MoneyDt
      11: dup
      12: invokespecial #236                // Method ca/uhn/fhir/model/dstu2/composite/MoneyDt."<init>":()V
      15: putfield      #67                 // Field myUnallocDeductable:Lca/uhn/fhir/model/dstu2/composite/MoneyDt;
      18: aload_0
      19: getfield      #67                 // Field myUnallocDeductable:Lca/uhn/fhir/model/dstu2/composite/MoneyDt;
      22: areturn

  public ca.uhn.fhir.model.dstu2.resource.ClaimResponse setUnallocDeductable(ca.uhn.fhir.model.dstu2.composite.MoneyDt);
    Code:
       0: aload_0
       1: aload_1
       2: putfield      #67                 // Field myUnallocDeductable:Lca/uhn/fhir/model/dstu2/composite/MoneyDt;
       5: aload_0
       6: areturn

  public ca.uhn.fhir.model.dstu2.composite.MoneyDt getTotalBenefit();
    Code:
       0: aload_0
       1: getfield      #70                 // Field myTotalBenefit:Lca/uhn/fhir/model/dstu2/composite/MoneyDt;
       4: ifnonnull     18
       7: aload_0
       8: new           #234                // class ca/uhn/fhir/model/dstu2/composite/MoneyDt
      11: dup
      12: invokespecial #236                // Method ca/uhn/fhir/model/dstu2/composite/MoneyDt."<init>":()V
      15: putfield      #70                 // Field myTotalBenefit:Lca/uhn/fhir/model/dstu2/composite/MoneyDt;
      18: aload_0
      19: getfield      #70                 // Field myTotalBenefit:Lca/uhn/fhir/model/dstu2/composite/MoneyDt;
      22: areturn

  public ca.uhn.fhir.model.dstu2.resource.ClaimResponse setTotalBenefit(ca.uhn.fhir.model.dstu2.composite.MoneyDt);
    Code:
       0: aload_0
       1: aload_1
       2: putfield      #70                 // Field myTotalBenefit:Lca/uhn/fhir/model/dstu2/composite/MoneyDt;
       5: aload_0
       6: areturn

  public ca.uhn.fhir.model.dstu2.composite.MoneyDt getPaymentAdjustment();
    Code:
       0: aload_0
       1: getfield      #73                 // Field myPaymentAdjustment:Lca/uhn/fhir/model/dstu2/composite/MoneyDt;
       4: ifnonnull     18
       7: aload_0
       8: new           #234                // class ca/uhn/fhir/model/dstu2/composite/MoneyDt
      11: dup
      12: invokespecial #236                // Method ca/uhn/fhir/model/dstu2/composite/MoneyDt."<init>":()V
      15: putfield      #73                 // Field myPaymentAdjustment:Lca/uhn/fhir/model/dstu2/composite/MoneyDt;
      18: aload_0
      19: getfield      #73                 // Field myPaymentAdjustment:Lca/uhn/fhir/model/dstu2/composite/MoneyDt;
      22: areturn

  public ca.uhn.fhir.model.dstu2.resource.ClaimResponse setPaymentAdjustment(ca.uhn.fhir.model.dstu2.composite.MoneyDt);
    Code:
       0: aload_0
       1: aload_1
       2: putfield      #73                 // Field myPaymentAdjustment:Lca/uhn/fhir/model/dstu2/composite/MoneyDt;
       5: aload_0
       6: areturn

  public ca.uhn.fhir.model.dstu2.composite.CodingDt getPaymentAdjustmentReason();
    Code:
       0: aload_0
       1: getfield      #76                 // Field myPaymentAdjustmentReason:Lca/uhn/fhir/model/dstu2/composite/CodingDt;
       4: ifnonnull     18
       7: aload_0
       8: new           #148                // class ca/uhn/fhir/model/dstu2/composite/CodingDt
      11: dup
      12: invokespecial #150                // Method ca/uhn/fhir/model/dstu2/composite/CodingDt."<init>":()V
      15: putfield      #76                 // Field myPaymentAdjustmentReason:Lca/uhn/fhir/model/dstu2/composite/CodingDt;
      18: aload_0
      19: getfield      #76                 // Field myPaymentAdjustmentReason:Lca/uhn/fhir/model/dstu2/composite/CodingDt;
      22: areturn

  public ca.uhn.fhir.model.dstu2.resource.ClaimResponse setPaymentAdjustmentReason(ca.uhn.fhir.model.dstu2.composite.CodingDt);
    Code:
       0: aload_0
       1: aload_1
       2: putfield      #76                 // Field myPaymentAdjustmentReason:Lca/uhn/fhir/model/dstu2/composite/CodingDt;
       5: aload_0
       6: areturn

  public ca.uhn.fhir.model.primitive.DateDt getPaymentDateElement();
    Code:
       0: aload_0
       1: getfield      #79                 // Field myPaymentDate:Lca/uhn/fhir/model/primitive/DateDt;
       4: ifnonnull     18
       7: aload_0
       8: new           #237                // class ca/uhn/fhir/model/primitive/DateDt
      11: dup
      12: invokespecial #239                // Method ca/uhn/fhir/model/primitive/DateDt."<init>":()V
      15: putfield      #79                 // Field myPaymentDate:Lca/uhn/fhir/model/primitive/DateDt;
      18: aload_0
      19: getfield      #79                 // Field myPaymentDate:Lca/uhn/fhir/model/primitive/DateDt;
      22: areturn

  public java.util.Date getPaymentDate();
    Code:
       0: aload_0
       1: invokevirtual #240                // Method getPaymentDateElement:()Lca/uhn/fhir/model/primitive/DateDt;
       4: invokevirtual #244                // Method ca/uhn/fhir/model/primitive/DateDt.getValue:()Ljava/lang/Object;
       7: checkcast     #162                // class java/util/Date
      10: areturn

  public ca.uhn.fhir.model.dstu2.resource.ClaimResponse setPaymentDate(ca.uhn.fhir.model.primitive.DateDt);
    Code:
       0: aload_0
       1: aload_1
       2: putfield      #79                 // Field myPaymentDate:Lca/uhn/fhir/model/primitive/DateDt;
       5: aload_0
       6: areturn

  public ca.uhn.fhir.model.dstu2.resource.ClaimResponse setPaymentDate(java.util.Date, ca.uhn.fhir.model.api.TemporalPrecisionEnum);
    Code:
       0: aload_0
       1: new           #237                // class ca/uhn/fhir/model/primitive/DateDt
       4: dup
       5: aload_1
       6: aload_2
       7: invokespecial #245                // Method ca/uhn/fhir/model/primitive/DateDt."<init>":(Ljava/util/Date;Lca/uhn/fhir/model/api/TemporalPrecisionEnum;)V
      10: putfield      #79                 // Field myPaymentDate:Lca/uhn/fhir/model/primitive/DateDt;
      13: aload_0
      14: areturn

  public ca.uhn.fhir.model.dstu2.resource.ClaimResponse setPaymentDateWithDayPrecision(java.util.Date);
    Code:
       0: aload_0
       1: new           #237                // class ca/uhn/fhir/model/primitive/DateDt
       4: dup
       5: aload_1
       6: invokespecial #246                // Method ca/uhn/fhir/model/primitive/DateDt."<init>":(Ljava/util/Date;)V
       9: putfield      #79                 // Field myPaymentDate:Lca/uhn/fhir/model/primitive/DateDt;
      12: aload_0
      13: areturn

  public ca.uhn.fhir.model.dstu2.composite.MoneyDt getPaymentAmount();
    Code:
       0: aload_0
       1: getfield      #83                 // Field myPaymentAmount:Lca/uhn/fhir/model/dstu2/composite/MoneyDt;
       4: ifnonnull     18
       7: aload_0
       8: new           #234                // class ca/uhn/fhir/model/dstu2/composite/MoneyDt
      11: dup
      12: invokespecial #236                // Method ca/uhn/fhir/model/dstu2/composite/MoneyDt."<init>":()V
      15: putfield      #83                 // Field myPaymentAmount:Lca/uhn/fhir/model/dstu2/composite/MoneyDt;
      18: aload_0
      19: getfield      #83                 // Field myPaymentAmount:Lca/uhn/fhir/model/dstu2/composite/MoneyDt;
      22: areturn

  public ca.uhn.fhir.model.dstu2.resource.ClaimResponse setPaymentAmount(ca.uhn.fhir.model.dstu2.composite.MoneyDt);
    Code:
       0: aload_0
       1: aload_1
       2: putfield      #83                 // Field myPaymentAmount:Lca/uhn/fhir/model/dstu2/composite/MoneyDt;
       5: aload_0
       6: areturn

  public ca.uhn.fhir.model.dstu2.composite.IdentifierDt getPaymentRef();
    Code:
       0: aload_0
       1: getfield      #86                 // Field myPaymentRef:Lca/uhn/fhir/model/dstu2/composite/IdentifierDt;
       4: ifnonnull     18
       7: aload_0
       8: new           #115                // class ca/uhn/fhir/model/dstu2/composite/IdentifierDt
      11: dup
      12: invokespecial #117                // Method ca/uhn/fhir/model/dstu2/composite/IdentifierDt."<init>":()V
      15: putfield      #86                 // Field myPaymentRef:Lca/uhn/fhir/model/dstu2/composite/IdentifierDt;
      18: aload_0
      19: getfield      #86                 // Field myPaymentRef:Lca/uhn/fhir/model/dstu2/composite/IdentifierDt;
      22: areturn

  public ca.uhn.fhir.model.dstu2.resource.ClaimResponse setPaymentRef(ca.uhn.fhir.model.dstu2.composite.IdentifierDt);
    Code:
       0: aload_0
       1: aload_1
       2: putfield      #86                 // Field myPaymentRef:Lca/uhn/fhir/model/dstu2/composite/IdentifierDt;
       5: aload_0
       6: areturn

  public ca.uhn.fhir.model.dstu2.composite.CodingDt getReserved();
    Code:
       0: aload_0
       1: getfield      #90                 // Field myReserved:Lca/uhn/fhir/model/dstu2/composite/CodingDt;
       4: ifnonnull     18
       7: aload_0
       8: new           #148                // class ca/uhn/fhir/model/dstu2/composite/CodingDt
      11: dup
      12: invokespecial #150                // Method ca/uhn/fhir/model/dstu2/composite/CodingDt."<init>":()V
      15: putfield      #90                 // Field myReserved:Lca/uhn/fhir/model/dstu2/composite/CodingDt;
      18: aload_0
      19: getfield      #90                 // Field myReserved:Lca/uhn/fhir/model/dstu2/composite/CodingDt;
      22: areturn

  public ca.uhn.fhir.model.dstu2.resource.ClaimResponse setReserved(ca.uhn.fhir.model.dstu2.composite.CodingDt);
    Code:
       0: aload_0
       1: aload_1
       2: putfield      #90                 // Field myReserved:Lca/uhn/fhir/model/dstu2/composite/CodingDt;
       5: aload_0
       6: areturn

  public ca.uhn.fhir.model.dstu2.composite.CodingDt getForm();
    Code:
       0: aload_0
       1: getfield      #93                 // Field myForm:Lca/uhn/fhir/model/dstu2/composite/CodingDt;
       4: ifnonnull     18
       7: aload_0
       8: new           #148                // class ca/uhn/fhir/model/dstu2/composite/CodingDt
      11: dup
      12: invokespecial #150                // Method ca/uhn/fhir/model/dstu2/composite/CodingDt."<init>":()V
      15: putfield      #93                 // Field myForm:Lca/uhn/fhir/model/dstu2/composite/CodingDt;
      18: aload_0
      19: getfield      #93                 // Field myForm:Lca/uhn/fhir/model/dstu2/composite/CodingDt;
      22: areturn

  public ca.uhn.fhir.model.dstu2.resource.ClaimResponse setForm(ca.uhn.fhir.model.dstu2.composite.CodingDt);
    Code:
       0: aload_0
       1: aload_1
       2: putfield      #93                 // Field myForm:Lca/uhn/fhir/model/dstu2/composite/CodingDt;
       5: aload_0
       6: areturn

  public java.util.List<ca.uhn.fhir.model.dstu2.resource.ClaimResponse$Note> getNote();
    Code:
       0: aload_0
       1: getfield      #96                 // Field myNote:Ljava/util/List;
       4: ifnonnull     18
       7: aload_0
       8: new           #112                // class java/util/ArrayList
      11: dup
      12: invokespecial #114                // Method java/util/ArrayList."<init>":()V
      15: putfield      #96                 // Field myNote:Ljava/util/List;
      18: aload_0
      19: getfield      #96                 // Field myNote:Ljava/util/List;
      22: areturn

  public ca.uhn.fhir.model.dstu2.resource.ClaimResponse setNote(java.util.List<ca.uhn.fhir.model.dstu2.resource.ClaimResponse$Note>);
    Code:
       0: aload_0
       1: aload_1
       2: putfield      #96                 // Field myNote:Ljava/util/List;
       5: aload_0
       6: areturn

  public ca.uhn.fhir.model.dstu2.resource.ClaimResponse$Note addNote();
    Code:
       0: new           #247                // class ca/uhn/fhir/model/dstu2/resource/ClaimResponse$Note
       3: dup
       4: invokespecial #249                // Method ca/uhn/fhir/model/dstu2/resource/ClaimResponse$Note."<init>":()V
       7: astore_1
       8: aload_0
       9: invokevirtual #250                // Method getNote:()Ljava/util/List;
      12: aload_1
      13: invokeinterface #122,  2          // InterfaceMethod java/util/List.add:(Ljava/lang/Object;)Z
      18: pop
      19: aload_1
      20: areturn

  public ca.uhn.fhir.model.dstu2.resource.ClaimResponse addNote(ca.uhn.fhir.model.dstu2.resource.ClaimResponse$Note);
    Code:
       0: aload_1
       1: ifnonnull     14
       4: new           #128                // class java/lang/NullPointerException
       7: dup
       8: ldc           #130                // String theValue must not be null
      10: invokespecial #132                // Method java/lang/NullPointerException."<init>":(Ljava/lang/String;)V
      13: athrow
      14: aload_0
      15: invokevirtual #250                // Method getNote:()Ljava/util/List;
      18: aload_1
      19: invokeinterface #122,  2          // InterfaceMethod java/util/List.add:(Ljava/lang/Object;)Z
      24: pop
      25: aload_0
      26: areturn

  public ca.uhn.fhir.model.dstu2.resource.ClaimResponse$Note getNoteFirstRep();
    Code:
       0: aload_0
       1: invokevirtual #250                // Method getNote:()Ljava/util/List;
       4: invokeinterface #135,  1          // InterfaceMethod java/util/List.isEmpty:()Z
       9: ifeq          17
      12: aload_0
      13: invokevirtual #253                // Method addNote:()Lca/uhn/fhir/model/dstu2/resource/ClaimResponse$Note;
      16: areturn
      17: aload_0
      18: invokevirtual #250                // Method getNote:()Ljava/util/List;
      21: iconst_0
      22: invokeinterface #141,  2          // InterfaceMethod java/util/List.get:(I)Ljava/lang/Object;
      27: checkcast     #247                // class ca/uhn/fhir/model/dstu2/resource/ClaimResponse$Note
      30: areturn

  public java.util.List<ca.uhn.fhir.model.dstu2.resource.ClaimResponse$Coverage> getCoverage();
    Code:
       0: aload_0
       1: getfield      #99                 // Field myCoverage:Ljava/util/List;
       4: ifnonnull     18
       7: aload_0
       8: new           #112                // class java/util/ArrayList
      11: dup
      12: invokespecial #114                // Method java/util/ArrayList."<init>":()V
      15: putfield      #99                 // Field myCoverage:Ljava/util/List;
      18: aload_0
      19: getfield      #99                 // Field myCoverage:Ljava/util/List;
      22: areturn

  public ca.uhn.fhir.model.dstu2.resource.ClaimResponse setCoverage(java.util.List<ca.uhn.fhir.model.dstu2.resource.ClaimResponse$Coverage>);
    Code:
       0: aload_0
       1: aload_1
       2: putfield      #99                 // Field myCoverage:Ljava/util/List;
       5: aload_0
       6: areturn

  public ca.uhn.fhir.model.dstu2.resource.ClaimResponse$Coverage addCoverage();
    Code:
       0: new           #257                // class ca/uhn/fhir/model/dstu2/resource/ClaimResponse$Coverage
       3: dup
       4: invokespecial #259                // Method ca/uhn/fhir/model/dstu2/resource/ClaimResponse$Coverage."<init>":()V
       7: astore_1
       8: aload_0
       9: invokevirtual #260                // Method getCoverage:()Ljava/util/List;
      12: aload_1
      13: invokeinterface #122,  2          // InterfaceMethod java/util/List.add:(Ljava/lang/Object;)Z
      18: pop
      19: aload_1
      20: areturn

  public ca.uhn.fhir.model.dstu2.resource.ClaimResponse addCoverage(ca.uhn.fhir.model.dstu2.resource.ClaimResponse$Coverage);
    Code:
       0: aload_1
       1: ifnonnull     14
       4: new           #128                // class java/lang/NullPointerException
       7: dup
       8: ldc           #130                // String theValue must not be null
      10: invokespecial #132                // Method java/lang/NullPointerException."<init>":(Ljava/lang/String;)V
      13: athrow
      14: aload_0
      15: invokevirtual #260                // Method getCoverage:()Ljava/util/List;
      18: aload_1
      19: invokeinterface #122,  2          // InterfaceMethod java/util/List.add:(Ljava/lang/Object;)Z
      24: pop
      25: aload_0
      26: areturn

  public ca.uhn.fhir.model.dstu2.resource.ClaimResponse$Coverage getCoverageFirstRep();
    Code:
       0: aload_0
       1: invokevirtual #260                // Method getCoverage:()Ljava/util/List;
       4: invokeinterface #135,  1          // InterfaceMethod java/util/List.isEmpty:()Z
       9: ifeq          17
      12: aload_0
      13: invokevirtual #263                // Method addCoverage:()Lca/uhn/fhir/model/dstu2/resource/ClaimResponse$Coverage;
      16: areturn
      17: aload_0
      18: invokevirtual #260                // Method getCoverage:()Ljava/util/List;
      21: iconst_0
      22: invokeinterface #141,  2          // InterfaceMethod java/util/List.get:(I)Ljava/lang/Object;
      27: checkcast     #257                // class ca/uhn/fhir/model/dstu2/resource/ClaimResponse$Coverage
      30: areturn

  public java.lang.String getResourceName();
    Code:
       0: ldc_w         #267                // String ClaimResponse
       3: areturn

  public ca.uhn.fhir.context.FhirVersionEnum getStructureFhirVersionEnum();
    Code:
       0: getstatic     #269                // Field ca/uhn/fhir/context/FhirVersionEnum.DSTU2:Lca/uhn/fhir/context/FhirVersionEnum;
       3: areturn

  static {};
    Code:
       0: new           #275                // class ca/uhn/fhir/rest/gclient/TokenClientParam
       3: dup
       4: ldc_w         #277                // String identifier
       7: invokespecial #279                // Method ca/uhn/fhir/rest/gclient/TokenClientParam."<init>":(Ljava/lang/String;)V
      10: putstatic     #280                // Field IDENTIFIER:Lca/uhn/fhir/rest/gclient/TokenClientParam;
      13: return
}
