Compiled from "Composition.java"
public class ca.uhn.fhir.model.dstu2.resource.Composition extends ca.uhn.fhir.model.dstu2.resource.BaseResource implements ca.uhn.fhir.model.api.IResource {
  public static final java.lang.String SP_TYPE;

  public static final ca.uhn.fhir.rest.gclient.TokenClientParam TYPE;

  public static final java.lang.String SP_CLASS;

  public static final ca.uhn.fhir.rest.gclient.TokenClientParam CLASS;

  public static final java.lang.String SP_DATE;

  public static final ca.uhn.fhir.rest.gclient.DateClientParam DATE;

  public static final java.lang.String SP_SUBJECT;

  public static final ca.uhn.fhir.rest.gclient.ReferenceClientParam SUBJECT;

  public static final java.lang.String SP_AUTHOR;

  public static final ca.uhn.fhir.rest.gclient.ReferenceClientParam AUTHOR;

  public static final java.lang.String SP_ATTESTER;

  public static final ca.uhn.fhir.rest.gclient.ReferenceClientParam ATTESTER;

  public static final java.lang.String SP_CONTEXT;

  public static final ca.uhn.fhir.rest.gclient.TokenClientParam CONTEXT;

  public static final java.lang.String SP_SECTION;

  public static final ca.uhn.fhir.rest.gclient.TokenClientParam SECTION;

  public static final java.lang.String SP_ENTRY;

  public static final ca.uhn.fhir.rest.gclient.ReferenceClientParam ENTRY;

  public static final java.lang.String SP_IDENTIFIER;

  public static final ca.uhn.fhir.rest.gclient.TokenClientParam IDENTIFIER;

  public static final java.lang.String SP_TITLE;

  public static final ca.uhn.fhir.rest.gclient.StringClientParam TITLE;

  public static final java.lang.String SP_STATUS;

  public static final ca.uhn.fhir.rest.gclient.TokenClientParam STATUS;

  public static final java.lang.String SP_CONFIDENTIALITY;

  public static final ca.uhn.fhir.rest.gclient.TokenClientParam CONFIDENTIALITY;

  public static final java.lang.String SP_PERIOD;

  public static final ca.uhn.fhir.rest.gclient.DateClientParam PERIOD;

  public static final java.lang.String SP_PATIENT;

  public static final ca.uhn.fhir.rest.gclient.ReferenceClientParam PATIENT;

  public static final java.lang.String SP_ENCOUNTER;

  public static final ca.uhn.fhir.rest.gclient.ReferenceClientParam ENCOUNTER;

  public static final ca.uhn.fhir.model.api.Include INCLUDE_ATTESTER;

  public static final ca.uhn.fhir.model.api.Include INCLUDE_AUTHOR;

  public static final ca.uhn.fhir.model.api.Include INCLUDE_ENCOUNTER;

  public static final ca.uhn.fhir.model.api.Include INCLUDE_ENTRY;

  public static final ca.uhn.fhir.model.api.Include INCLUDE_PATIENT;

  public static final ca.uhn.fhir.model.api.Include INCLUDE_SUBJECT;

  private ca.uhn.fhir.model.dstu2.composite.IdentifierDt myIdentifier;

  private ca.uhn.fhir.model.primitive.DateTimeDt myDate;

  private ca.uhn.fhir.model.dstu2.composite.CodeableConceptDt myType;

  private ca.uhn.fhir.model.dstu2.composite.CodeableConceptDt myClassElement;

  private ca.uhn.fhir.model.primitive.StringDt myTitle;

  private ca.uhn.fhir.model.primitive.BoundCodeDt<ca.uhn.fhir.model.dstu2.valueset.CompositionStatusEnum> myStatus;

  private ca.uhn.fhir.model.primitive.CodeDt myConfidentiality;

  private ca.uhn.fhir.model.dstu2.composite.ResourceReferenceDt mySubject;

  private java.util.List<ca.uhn.fhir.model.dstu2.composite.ResourceReferenceDt> myAuthor;

  private java.util.List<ca.uhn.fhir.model.dstu2.resource.Composition$Attester> myAttester;

  private ca.uhn.fhir.model.dstu2.composite.ResourceReferenceDt myCustodian;

  private java.util.List<ca.uhn.fhir.model.dstu2.resource.Composition$Event> myEvent;

  private ca.uhn.fhir.model.dstu2.composite.ResourceReferenceDt myEncounter;

  private java.util.List<ca.uhn.fhir.model.dstu2.resource.Composition$Section> mySection;

  public ca.uhn.fhir.model.dstu2.resource.Composition();
    Code:
       0: aload_0
       1: invokespecial #1                  // Method ca/uhn/fhir/model/dstu2/resource/BaseResource."<init>":()V
       4: return

  public boolean isEmpty();
    Code:
       0: aload_0
       1: invokespecial #7                  // Method ca/uhn/fhir/model/dstu2/resource/BaseResource.isBaseEmpty:()Z
       4: ifeq          128
       7: bipush        14
       9: anewarray     #11                 // class java/lang/Object
      12: dup
      13: iconst_0
      14: aload_0
      15: getfield      #13                 // Field myIdentifier:Lca/uhn/fhir/model/dstu2/composite/IdentifierDt;
      18: aastore
      19: dup
      20: iconst_1
      21: aload_0
      22: getfield      #19                 // Field myDate:Lca/uhn/fhir/model/primitive/DateTimeDt;
      25: aastore
      26: dup
      27: iconst_2
      28: aload_0
      29: getfield      #23                 // Field myType:Lca/uhn/fhir/model/dstu2/composite/CodeableConceptDt;
      32: aastore
      33: dup
      34: iconst_3
      35: aload_0
      36: getfield      #27                 // Field myClassElement:Lca/uhn/fhir/model/dstu2/composite/CodeableConceptDt;
      39: aastore
      40: dup
      41: iconst_4
      42: aload_0
      43: getfield      #30                 // Field myTitle:Lca/uhn/fhir/model/primitive/StringDt;
      46: aastore
      47: dup
      48: iconst_5
      49: aload_0
      50: getfield      #34                 // Field myStatus:Lca/uhn/fhir/model/primitive/BoundCodeDt;
      53: aastore
      54: dup
      55: bipush        6
      57: aload_0
      58: getfield      #38                 // Field myConfidentiality:Lca/uhn/fhir/model/primitive/CodeDt;
      61: aastore
      62: dup
      63: bipush        7
      65: aload_0
      66: getfield      #42                 // Field mySubject:Lca/uhn/fhir/model/dstu2/composite/ResourceReferenceDt;
      69: aastore
      70: dup
      71: bipush        8
      73: aload_0
      74: getfield      #46                 // Field myAuthor:Ljava/util/List;
      77: aastore
      78: dup
      79: bipush        9
      81: aload_0
      82: getfield      #50                 // Field myAttester:Ljava/util/List;
      85: aastore
      86: dup
      87: bipush        10
      89: aload_0
      90: getfield      #53                 // Field myCustodian:Lca/uhn/fhir/model/dstu2/composite/ResourceReferenceDt;
      93: aastore
      94: dup
      95: bipush        11
      97: aload_0
      98: getfield      #56                 // Field myEvent:Ljava/util/List;
     101: aastore
     102: dup
     103: bipush        12
     105: aload_0
     106: getfield      #59                 // Field myEncounter:Lca/uhn/fhir/model/dstu2/composite/ResourceReferenceDt;
     109: aastore
     110: dup
     111: bipush        13
     113: aload_0
     114: getfield      #62                 // Field mySection:Ljava/util/List;
     117: aastore
     118: invokestatic  #65                 // Method ca/uhn/fhir/util/ElementUtil.isEmpty:([Ljava/lang/Object;)Z
     121: ifeq          128
     124: iconst_1
     125: goto          129
     128: iconst_0
     129: ireturn

  public <T extends ca.uhn.fhir.model.api.IElement> java.util.List<T> getAllPopulatedChildElementsOfType(java.lang.Class<T>);
    Code:
       0: aload_1
       1: bipush        14
       3: anewarray     #11                 // class java/lang/Object
       6: dup
       7: iconst_0
       8: aload_0
       9: getfield      #13                 // Field myIdentifier:Lca/uhn/fhir/model/dstu2/composite/IdentifierDt;
      12: aastore
      13: dup
      14: iconst_1
      15: aload_0
      16: getfield      #19                 // Field myDate:Lca/uhn/fhir/model/primitive/DateTimeDt;
      19: aastore
      20: dup
      21: iconst_2
      22: aload_0
      23: getfield      #23                 // Field myType:Lca/uhn/fhir/model/dstu2/composite/CodeableConceptDt;
      26: aastore
      27: dup
      28: iconst_3
      29: aload_0
      30: getfield      #27                 // Field myClassElement:Lca/uhn/fhir/model/dstu2/composite/CodeableConceptDt;
      33: aastore
      34: dup
      35: iconst_4
      36: aload_0
      37: getfield      #30                 // Field myTitle:Lca/uhn/fhir/model/primitive/StringDt;
      40: aastore
      41: dup
      42: iconst_5
      43: aload_0
      44: getfield      #34                 // Field myStatus:Lca/uhn/fhir/model/primitive/BoundCodeDt;
      47: aastore
      48: dup
      49: bipush        6
      51: aload_0
      52: getfield      #38                 // Field myConfidentiality:Lca/uhn/fhir/model/primitive/CodeDt;
      55: aastore
      56: dup
      57: bipush        7
      59: aload_0
      60: getfield      #42                 // Field mySubject:Lca/uhn/fhir/model/dstu2/composite/ResourceReferenceDt;
      63: aastore
      64: dup
      65: bipush        8
      67: aload_0
      68: getfield      #46                 // Field myAuthor:Ljava/util/List;
      71: aastore
      72: dup
      73: bipush        9
      75: aload_0
      76: getfield      #50                 // Field myAttester:Ljava/util/List;
      79: aastore
      80: dup
      81: bipush        10
      83: aload_0
      84: getfield      #53                 // Field myCustodian:Lca/uhn/fhir/model/dstu2/composite/ResourceReferenceDt;
      87: aastore
      88: dup
      89: bipush        11
      91: aload_0
      92: getfield      #56                 // Field myEvent:Ljava/util/List;
      95: aastore
      96: dup
      97: bipush        12
      99: aload_0
     100: getfield      #59                 // Field myEncounter:Lca/uhn/fhir/model/dstu2/composite/ResourceReferenceDt;
     103: aastore
     104: dup
     105: bipush        13
     107: aload_0
     108: getfield      #62                 // Field mySection:Ljava/util/List;
     111: aastore
     112: invokestatic  #71                 // Method ca/uhn/fhir/util/ElementUtil.allPopulatedChildElements:(Ljava/lang/Class;[Ljava/lang/Object;)Ljava/util/List;
     115: areturn

  public ca.uhn.fhir.model.dstu2.composite.IdentifierDt getIdentifier();
    Code:
       0: aload_0
       1: getfield      #13                 // Field myIdentifier:Lca/uhn/fhir/model/dstu2/composite/IdentifierDt;
       4: ifnonnull     18
       7: aload_0
       8: new           #75                 // class ca/uhn/fhir/model/dstu2/composite/IdentifierDt
      11: dup
      12: invokespecial #77                 // Method ca/uhn/fhir/model/dstu2/composite/IdentifierDt."<init>":()V
      15: putfield      #13                 // Field myIdentifier:Lca/uhn/fhir/model/dstu2/composite/IdentifierDt;
      18: aload_0
      19: getfield      #13                 // Field myIdentifier:Lca/uhn/fhir/model/dstu2/composite/IdentifierDt;
      22: areturn

  public ca.uhn.fhir.model.dstu2.resource.Composition setIdentifier(ca.uhn.fhir.model.dstu2.composite.IdentifierDt);
    Code:
       0: aload_0
       1: aload_1
       2: putfield      #13                 // Field myIdentifier:Lca/uhn/fhir/model/dstu2/composite/IdentifierDt;
       5: aload_0
       6: areturn

  public ca.uhn.fhir.model.primitive.DateTimeDt getDateElement();
    Code:
       0: aload_0
       1: getfield      #19                 // Field myDate:Lca/uhn/fhir/model/primitive/DateTimeDt;
       4: ifnonnull     18
       7: aload_0
       8: new           #78                 // class ca/uhn/fhir/model/primitive/DateTimeDt
      11: dup
      12: invokespecial #80                 // Method ca/uhn/fhir/model/primitive/DateTimeDt."<init>":()V
      15: putfield      #19                 // Field myDate:Lca/uhn/fhir/model/primitive/DateTimeDt;
      18: aload_0
      19: getfield      #19                 // Field myDate:Lca/uhn/fhir/model/primitive/DateTimeDt;
      22: areturn

  public java.util.Date getDate();
    Code:
       0: aload_0
       1: invokevirtual #81                 // Method getDateElement:()Lca/uhn/fhir/model/primitive/DateTimeDt;
       4: invokevirtual #85                 // Method ca/uhn/fhir/model/primitive/DateTimeDt.getValue:()Ljava/lang/Object;
       7: checkcast     #89                 // class java/util/Date
      10: areturn

  public ca.uhn.fhir.model.dstu2.resource.Composition setDate(ca.uhn.fhir.model.primitive.DateTimeDt);
    Code:
       0: aload_0
       1: aload_1
       2: putfield      #19                 // Field myDate:Lca/uhn/fhir/model/primitive/DateTimeDt;
       5: aload_0
       6: areturn

  public ca.uhn.fhir.model.dstu2.resource.Composition setDate(java.util.Date, ca.uhn.fhir.model.api.TemporalPrecisionEnum);
    Code:
       0: aload_0
       1: new           #78                 // class ca/uhn/fhir/model/primitive/DateTimeDt
       4: dup
       5: aload_1
       6: aload_2
       7: invokespecial #91                 // Method ca/uhn/fhir/model/primitive/DateTimeDt."<init>":(Ljava/util/Date;Lca/uhn/fhir/model/api/TemporalPrecisionEnum;)V
      10: putfield      #19                 // Field myDate:Lca/uhn/fhir/model/primitive/DateTimeDt;
      13: aload_0
      14: areturn

  public ca.uhn.fhir.model.dstu2.resource.Composition setDateWithSecondsPrecision(java.util.Date);
    Code:
       0: aload_0
       1: new           #78                 // class ca/uhn/fhir/model/primitive/DateTimeDt
       4: dup
       5: aload_1
       6: invokespecial #94                 // Method ca/uhn/fhir/model/primitive/DateTimeDt."<init>":(Ljava/util/Date;)V
       9: putfield      #19                 // Field myDate:Lca/uhn/fhir/model/primitive/DateTimeDt;
      12: aload_0
      13: areturn

  public ca.uhn.fhir.model.dstu2.composite.CodeableConceptDt getType();
    Code:
       0: aload_0
       1: getfield      #23                 // Field myType:Lca/uhn/fhir/model/dstu2/composite/CodeableConceptDt;
       4: ifnonnull     18
       7: aload_0
       8: new           #97                 // class ca/uhn/fhir/model/dstu2/composite/CodeableConceptDt
      11: dup
      12: invokespecial #99                 // Method ca/uhn/fhir/model/dstu2/composite/CodeableConceptDt."<init>":()V
      15: putfield      #23                 // Field myType:Lca/uhn/fhir/model/dstu2/composite/CodeableConceptDt;
      18: aload_0
      19: getfield      #23                 // Field myType:Lca/uhn/fhir/model/dstu2/composite/CodeableConceptDt;
      22: areturn

  public ca.uhn.fhir.model.dstu2.resource.Composition setType(ca.uhn.fhir.model.dstu2.composite.CodeableConceptDt);
    Code:
       0: aload_0
       1: aload_1
       2: putfield      #23                 // Field myType:Lca/uhn/fhir/model/dstu2/composite/CodeableConceptDt;
       5: aload_0
       6: areturn

  public ca.uhn.fhir.model.dstu2.composite.CodeableConceptDt getClassElement();
    Code:
       0: aload_0
       1: getfield      #27                 // Field myClassElement:Lca/uhn/fhir/model/dstu2/composite/CodeableConceptDt;
       4: ifnonnull     18
       7: aload_0
       8: new           #97                 // class ca/uhn/fhir/model/dstu2/composite/CodeableConceptDt
      11: dup
      12: invokespecial #99                 // Method ca/uhn/fhir/model/dstu2/composite/CodeableConceptDt."<init>":()V
      15: putfield      #27                 // Field myClassElement:Lca/uhn/fhir/model/dstu2/composite/CodeableConceptDt;
      18: aload_0
      19: getfield      #27                 // Field myClassElement:Lca/uhn/fhir/model/dstu2/composite/CodeableConceptDt;
      22: areturn

  public ca.uhn.fhir.model.dstu2.resource.Composition setClassElement(ca.uhn.fhir.model.dstu2.composite.CodeableConceptDt);
    Code:
       0: aload_0
       1: aload_1
       2: putfield      #27                 // Field myClassElement:Lca/uhn/fhir/model/dstu2/composite/CodeableConceptDt;
       5: aload_0
       6: areturn

  public ca.uhn.fhir.model.primitive.StringDt getTitleElement();
    Code:
       0: aload_0
       1: getfield      #30                 // Field myTitle:Lca/uhn/fhir/model/primitive/StringDt;
       4: ifnonnull     18
       7: aload_0
       8: new           #100                // class ca/uhn/fhir/model/primitive/StringDt
      11: dup
      12: invokespecial #102                // Method ca/uhn/fhir/model/primitive/StringDt."<init>":()V
      15: putfield      #30                 // Field myTitle:Lca/uhn/fhir/model/primitive/StringDt;
      18: aload_0
      19: getfield      #30                 // Field myTitle:Lca/uhn/fhir/model/primitive/StringDt;
      22: areturn

  public java.lang.String getTitle();
    Code:
       0: aload_0
       1: invokevirtual #103                // Method getTitleElement:()Lca/uhn/fhir/model/primitive/StringDt;
       4: invokevirtual #107                // Method ca/uhn/fhir/model/primitive/StringDt.getValue:()Ljava/lang/Object;
       7: checkcast     #108                // class java/lang/String
      10: areturn

  public ca.uhn.fhir.model.dstu2.resource.Composition setTitle(ca.uhn.fhir.model.primitive.StringDt);
    Code:
       0: aload_0
       1: aload_1
       2: putfield      #30                 // Field myTitle:Lca/uhn/fhir/model/primitive/StringDt;
       5: aload_0
       6: areturn

  public ca.uhn.fhir.model.dstu2.resource.Composition setTitle(java.lang.String);
    Code:
       0: aload_0
       1: new           #100                // class ca/uhn/fhir/model/primitive/StringDt
       4: dup
       5: aload_1
       6: invokespecial #110                // Method ca/uhn/fhir/model/primitive/StringDt."<init>":(Ljava/lang/String;)V
       9: putfield      #30                 // Field myTitle:Lca/uhn/fhir/model/primitive/StringDt;
      12: aload_0
      13: areturn

  public ca.uhn.fhir.model.primitive.BoundCodeDt<ca.uhn.fhir.model.dstu2.valueset.CompositionStatusEnum> getStatusElement();
    Code:
       0: aload_0
       1: getfield      #34                 // Field myStatus:Lca/uhn/fhir/model/primitive/BoundCodeDt;
       4: ifnonnull     21
       7: aload_0
       8: new           #113                // class ca/uhn/fhir/model/primitive/BoundCodeDt
      11: dup
      12: getstatic     #115                // Field ca/uhn/fhir/model/dstu2/valueset/CompositionStatusEnum.VALUESET_BINDER:Lca/uhn/fhir/model/api/IValueSetEnumBinder;
      15: invokespecial #121                // Method ca/uhn/fhir/model/primitive/BoundCodeDt."<init>":(Lca/uhn/fhir/model/api/IValueSetEnumBinder;)V
      18: putfield      #34                 // Field myStatus:Lca/uhn/fhir/model/primitive/BoundCodeDt;
      21: aload_0
      22: getfield      #34                 // Field myStatus:Lca/uhn/fhir/model/primitive/BoundCodeDt;
      25: areturn

  public java.lang.String getStatus();
    Code:
       0: aload_0
       1: invokevirtual #124                // Method getStatusElement:()Lca/uhn/fhir/model/primitive/BoundCodeDt;
       4: invokevirtual #128                // Method ca/uhn/fhir/model/primitive/BoundCodeDt.getValue:()Ljava/lang/Object;
       7: checkcast     #108                // class java/lang/String
      10: areturn

  public ca.uhn.fhir.model.dstu2.resource.Composition setStatus(ca.uhn.fhir.model.primitive.BoundCodeDt<ca.uhn.fhir.model.dstu2.valueset.CompositionStatusEnum>);
    Code:
       0: aload_0
       1: aload_1
       2: putfield      #34                 // Field myStatus:Lca/uhn/fhir/model/primitive/BoundCodeDt;
       5: aload_0
       6: areturn

  public ca.uhn.fhir.model.dstu2.resource.Composition setStatus(ca.uhn.fhir.model.dstu2.valueset.CompositionStatusEnum);
    Code:
       0: aload_0
       1: new           #113                // class ca/uhn/fhir/model/primitive/BoundCodeDt
       4: dup
       5: getstatic     #115                // Field ca/uhn/fhir/model/dstu2/valueset/CompositionStatusEnum.VALUESET_BINDER:Lca/uhn/fhir/model/api/IValueSetEnumBinder;
       8: aload_1
       9: invokespecial #129                // Method ca/uhn/fhir/model/primitive/BoundCodeDt."<init>":(Lca/uhn/fhir/model/api/IValueSetEnumBinder;Ljava/lang/Enum;)V
      12: invokevirtual #132                // Method setStatus:(Lca/uhn/fhir/model/primitive/BoundCodeDt;)Lca/uhn/fhir/model/dstu2/resource/Composition;
      15: pop
      16: aload_0
      17: areturn

  public ca.uhn.fhir.model.primitive.CodeDt getConfidentialityElement();
    Code:
       0: aload_0
       1: getfield      #38                 // Field myConfidentiality:Lca/uhn/fhir/model/primitive/CodeDt;
       4: ifnonnull     18
       7: aload_0
       8: new           #136                // class ca/uhn/fhir/model/primitive/CodeDt
      11: dup
      12: invokespecial #138                // Method ca/uhn/fhir/model/primitive/CodeDt."<init>":()V
      15: putfield      #38                 // Field myConfidentiality:Lca/uhn/fhir/model/primitive/CodeDt;
      18: aload_0
      19: getfield      #38                 // Field myConfidentiality:Lca/uhn/fhir/model/primitive/CodeDt;
      22: areturn

  public java.lang.String getConfidentiality();
    Code:
       0: aload_0
       1: invokevirtual #139                // Method getConfidentialityElement:()Lca/uhn/fhir/model/primitive/CodeDt;
       4: invokevirtual #143                // Method ca/uhn/fhir/model/primitive/CodeDt.getValue:()Ljava/lang/Object;
       7: checkcast     #108                // class java/lang/String
      10: areturn

  public ca.uhn.fhir.model.dstu2.resource.Composition setConfidentiality(ca.uhn.fhir.model.primitive.CodeDt);
    Code:
       0: aload_0
       1: aload_1
       2: putfield      #38                 // Field myConfidentiality:Lca/uhn/fhir/model/primitive/CodeDt;
       5: aload_0
       6: areturn

  public ca.uhn.fhir.model.dstu2.resource.Composition setConfidentiality(java.lang.String);
    Code:
       0: aload_0
       1: new           #136                // class ca/uhn/fhir/model/primitive/CodeDt
       4: dup
       5: aload_1
       6: invokespecial #144                // Method ca/uhn/fhir/model/primitive/CodeDt."<init>":(Ljava/lang/String;)V
       9: putfield      #38                 // Field myConfidentiality:Lca/uhn/fhir/model/primitive/CodeDt;
      12: aload_0
      13: areturn

  public ca.uhn.fhir.model.dstu2.composite.ResourceReferenceDt getSubject();
    Code:
       0: aload_0
       1: getfield      #42                 // Field mySubject:Lca/uhn/fhir/model/dstu2/composite/ResourceReferenceDt;
       4: ifnonnull     18
       7: aload_0
       8: new           #145                // class ca/uhn/fhir/model/dstu2/composite/ResourceReferenceDt
      11: dup
      12: invokespecial #147                // Method ca/uhn/fhir/model/dstu2/composite/ResourceReferenceDt."<init>":()V
      15: putfield      #42                 // Field mySubject:Lca/uhn/fhir/model/dstu2/composite/ResourceReferenceDt;
      18: aload_0
      19: getfield      #42                 // Field mySubject:Lca/uhn/fhir/model/dstu2/composite/ResourceReferenceDt;
      22: areturn

  public ca.uhn.fhir.model.dstu2.resource.Composition setSubject(ca.uhn.fhir.model.dstu2.composite.ResourceReferenceDt);
    Code:
       0: aload_0
       1: aload_1
       2: putfield      #42                 // Field mySubject:Lca/uhn/fhir/model/dstu2/composite/ResourceReferenceDt;
       5: aload_0
       6: areturn

  public java.util.List<ca.uhn.fhir.model.dstu2.composite.ResourceReferenceDt> getAuthor();
    Code:
       0: aload_0
       1: getfield      #46                 // Field myAuthor:Ljava/util/List;
       4: ifnonnull     18
       7: aload_0
       8: new           #148                // class java/util/ArrayList
      11: dup
      12: invokespecial #150                // Method java/util/ArrayList."<init>":()V
      15: putfield      #46                 // Field myAuthor:Ljava/util/List;
      18: aload_0
      19: getfield      #46                 // Field myAuthor:Ljava/util/List;
      22: areturn

  public ca.uhn.fhir.model.dstu2.resource.Composition setAuthor(java.util.List<ca.uhn.fhir.model.dstu2.composite.ResourceReferenceDt>);
    Code:
       0: aload_0
       1: aload_1
       2: putfield      #46                 // Field myAuthor:Ljava/util/List;
       5: aload_0
       6: areturn

  public ca.uhn.fhir.model.dstu2.composite.ResourceReferenceDt addAuthor();
    Code:
       0: new           #145                // class ca/uhn/fhir/model/dstu2/composite/ResourceReferenceDt
       3: dup
       4: invokespecial #147                // Method ca/uhn/fhir/model/dstu2/composite/ResourceReferenceDt."<init>":()V
       7: astore_1
       8: aload_0
       9: invokevirtual #151                // Method getAuthor:()Ljava/util/List;
      12: aload_1
      13: invokeinterface #155,  2          // InterfaceMethod java/util/List.add:(Ljava/lang/Object;)Z
      18: pop
      19: aload_1
      20: areturn

  public java.util.List<ca.uhn.fhir.model.dstu2.resource.Composition$Attester> getAttester();
    Code:
       0: aload_0
       1: getfield      #50                 // Field myAttester:Ljava/util/List;
       4: ifnonnull     18
       7: aload_0
       8: new           #148                // class java/util/ArrayList
      11: dup
      12: invokespecial #150                // Method java/util/ArrayList."<init>":()V
      15: putfield      #50                 // Field myAttester:Ljava/util/List;
      18: aload_0
      19: getfield      #50                 // Field myAttester:Ljava/util/List;
      22: areturn

  public ca.uhn.fhir.model.dstu2.resource.Composition setAttester(java.util.List<ca.uhn.fhir.model.dstu2.resource.Composition$Attester>);
    Code:
       0: aload_0
       1: aload_1
       2: putfield      #50                 // Field myAttester:Ljava/util/List;
       5: aload_0
       6: areturn

  public ca.uhn.fhir.model.dstu2.resource.Composition$Attester addAttester();
    Code:
       0: new           #161                // class ca/uhn/fhir/model/dstu2/resource/Composition$Attester
       3: dup
       4: invokespecial #163                // Method ca/uhn/fhir/model/dstu2/resource/Composition$Attester."<init>":()V
       7: astore_1
       8: aload_0
       9: invokevirtual #164                // Method getAttester:()Ljava/util/List;
      12: aload_1
      13: invokeinterface #155,  2          // InterfaceMethod java/util/List.add:(Ljava/lang/Object;)Z
      18: pop
      19: aload_1
      20: areturn

  public ca.uhn.fhir.model.dstu2.resource.Composition addAttester(ca.uhn.fhir.model.dstu2.resource.Composition$Attester);
    Code:
       0: aload_1
       1: ifnonnull     14
       4: new           #167                // class java/lang/NullPointerException
       7: dup
       8: ldc           #169                // String theValue must not be null
      10: invokespecial #171                // Method java/lang/NullPointerException."<init>":(Ljava/lang/String;)V
      13: athrow
      14: aload_0
      15: invokevirtual #164                // Method getAttester:()Ljava/util/List;
      18: aload_1
      19: invokeinterface #155,  2          // InterfaceMethod java/util/List.add:(Ljava/lang/Object;)Z
      24: pop
      25: aload_0
      26: areturn

  public ca.uhn.fhir.model.dstu2.resource.Composition$Attester getAttesterFirstRep();
    Code:
       0: aload_0
       1: invokevirtual #164                // Method getAttester:()Ljava/util/List;
       4: invokeinterface #172,  1          // InterfaceMethod java/util/List.isEmpty:()Z
       9: ifeq          17
      12: aload_0
      13: invokevirtual #174                // Method addAttester:()Lca/uhn/fhir/model/dstu2/resource/Composition$Attester;
      16: areturn
      17: aload_0
      18: invokevirtual #164                // Method getAttester:()Ljava/util/List;
      21: iconst_0
      22: invokeinterface #178,  2          // InterfaceMethod java/util/List.get:(I)Ljava/lang/Object;
      27: checkcast     #161                // class ca/uhn/fhir/model/dstu2/resource/Composition$Attester
      30: areturn

  public ca.uhn.fhir.model.dstu2.composite.ResourceReferenceDt getCustodian();
    Code:
       0: aload_0
       1: getfield      #53                 // Field myCustodian:Lca/uhn/fhir/model/dstu2/composite/ResourceReferenceDt;
       4: ifnonnull     18
       7: aload_0
       8: new           #145                // class ca/uhn/fhir/model/dstu2/composite/ResourceReferenceDt
      11: dup
      12: invokespecial #147                // Method ca/uhn/fhir/model/dstu2/composite/ResourceReferenceDt."<init>":()V
      15: putfield      #53                 // Field myCustodian:Lca/uhn/fhir/model/dstu2/composite/ResourceReferenceDt;
      18: aload_0
      19: getfield      #53                 // Field myCustodian:Lca/uhn/fhir/model/dstu2/composite/ResourceReferenceDt;
      22: areturn

  public ca.uhn.fhir.model.dstu2.resource.Composition setCustodian(ca.uhn.fhir.model.dstu2.composite.ResourceReferenceDt);
    Code:
       0: aload_0
       1: aload_1
       2: putfield      #53                 // Field myCustodian:Lca/uhn/fhir/model/dstu2/composite/ResourceReferenceDt;
       5: aload_0
       6: areturn

  public java.util.List<ca.uhn.fhir.model.dstu2.resource.Composition$Event> getEvent();
    Code:
       0: aload_0
       1: getfield      #56                 // Field myEvent:Ljava/util/List;
       4: ifnonnull     18
       7: aload_0
       8: new           #148                // class java/util/ArrayList
      11: dup
      12: invokespecial #150                // Method java/util/ArrayList."<init>":()V
      15: putfield      #56                 // Field myEvent:Ljava/util/List;
      18: aload_0
      19: getfield      #56                 // Field myEvent:Ljava/util/List;
      22: areturn

  public ca.uhn.fhir.model.dstu2.resource.Composition setEvent(java.util.List<ca.uhn.fhir.model.dstu2.resource.Composition$Event>);
    Code:
       0: aload_0
       1: aload_1
       2: putfield      #56                 // Field myEvent:Ljava/util/List;
       5: aload_0
       6: areturn

  public ca.uhn.fhir.model.dstu2.resource.Composition$Event addEvent();
    Code:
       0: new           #182                // class ca/uhn/fhir/model/dstu2/resource/Composition$Event
       3: dup
       4: invokespecial #184                // Method ca/uhn/fhir/model/dstu2/resource/Composition$Event."<init>":()V
       7: astore_1
       8: aload_0
       9: invokevirtual #185                // Method getEvent:()Ljava/util/List;
      12: aload_1
      13: invokeinterface #155,  2          // InterfaceMethod java/util/List.add:(Ljava/lang/Object;)Z
      18: pop
      19: aload_1
      20: areturn

  public ca.uhn.fhir.model.dstu2.resource.Composition addEvent(ca.uhn.fhir.model.dstu2.resource.Composition$Event);
    Code:
       0: aload_1
       1: ifnonnull     14
       4: new           #167                // class java/lang/NullPointerException
       7: dup
       8: ldc           #169                // String theValue must not be null
      10: invokespecial #171                // Method java/lang/NullPointerException."<init>":(Ljava/lang/String;)V
      13: athrow
      14: aload_0
      15: invokevirtual #185                // Method getEvent:()Ljava/util/List;
      18: aload_1
      19: invokeinterface #155,  2          // InterfaceMethod java/util/List.add:(Ljava/lang/Object;)Z
      24: pop
      25: aload_0
      26: areturn

  public ca.uhn.fhir.model.dstu2.resource.Composition$Event getEventFirstRep();
    Code:
       0: aload_0
       1: invokevirtual #185                // Method getEvent:()Ljava/util/List;
       4: invokeinterface #172,  1          // InterfaceMethod java/util/List.isEmpty:()Z
       9: ifeq          17
      12: aload_0
      13: invokevirtual #188                // Method addEvent:()Lca/uhn/fhir/model/dstu2/resource/Composition$Event;
      16: areturn
      17: aload_0
      18: invokevirtual #185                // Method getEvent:()Ljava/util/List;
      21: iconst_0
      22: invokeinterface #178,  2          // InterfaceMethod java/util/List.get:(I)Ljava/lang/Object;
      27: checkcast     #182                // class ca/uhn/fhir/model/dstu2/resource/Composition$Event
      30: areturn

  public ca.uhn.fhir.model.dstu2.composite.ResourceReferenceDt getEncounter();
    Code:
       0: aload_0
       1: getfield      #59                 // Field myEncounter:Lca/uhn/fhir/model/dstu2/composite/ResourceReferenceDt;
       4: ifnonnull     18
       7: aload_0
       8: new           #145                // class ca/uhn/fhir/model/dstu2/composite/ResourceReferenceDt
      11: dup
      12: invokespecial #147                // Method ca/uhn/fhir/model/dstu2/composite/ResourceReferenceDt."<init>":()V
      15: putfield      #59                 // Field myEncounter:Lca/uhn/fhir/model/dstu2/composite/ResourceReferenceDt;
      18: aload_0
      19: getfield      #59                 // Field myEncounter:Lca/uhn/fhir/model/dstu2/composite/ResourceReferenceDt;
      22: areturn

  public ca.uhn.fhir.model.dstu2.resource.Composition setEncounter(ca.uhn.fhir.model.dstu2.composite.ResourceReferenceDt);
    Code:
       0: aload_0
       1: aload_1
       2: putfield      #59                 // Field myEncounter:Lca/uhn/fhir/model/dstu2/composite/ResourceReferenceDt;
       5: aload_0
       6: areturn

  public java.util.List<ca.uhn.fhir.model.dstu2.resource.Composition$Section> getSection();
    Code:
       0: aload_0
       1: getfield      #62                 // Field mySection:Ljava/util/List;
       4: ifnonnull     18
       7: aload_0
       8: new           #148                // class java/util/ArrayList
      11: dup
      12: invokespecial #150                // Method java/util/ArrayList."<init>":()V
      15: putfield      #62                 // Field mySection:Ljava/util/List;
      18: aload_0
      19: getfield      #62                 // Field mySection:Ljava/util/List;
      22: areturn

  public ca.uhn.fhir.model.dstu2.resource.Composition setSection(java.util.List<ca.uhn.fhir.model.dstu2.resource.Composition$Section>);
    Code:
       0: aload_0
       1: aload_1
       2: putfield      #62                 // Field mySection:Ljava/util/List;
       5: aload_0
       6: areturn

  public ca.uhn.fhir.model.dstu2.resource.Composition$Section addSection();
    Code:
       0: new           #192                // class ca/uhn/fhir/model/dstu2/resource/Composition$Section
       3: dup
       4: invokespecial #194                // Method ca/uhn/fhir/model/dstu2/resource/Composition$Section."<init>":()V
       7: astore_1
       8: aload_0
       9: invokevirtual #195                // Method getSection:()Ljava/util/List;
      12: aload_1
      13: invokeinterface #155,  2          // InterfaceMethod java/util/List.add:(Ljava/lang/Object;)Z
      18: pop
      19: aload_1
      20: areturn

  public ca.uhn.fhir.model.dstu2.resource.Composition addSection(ca.uhn.fhir.model.dstu2.resource.Composition$Section);
    Code:
       0: aload_1
       1: ifnonnull     14
       4: new           #167                // class java/lang/NullPointerException
       7: dup
       8: ldc           #169                // String theValue must not be null
      10: invokespecial #171                // Method java/lang/NullPointerException."<init>":(Ljava/lang/String;)V
      13: athrow
      14: aload_0
      15: invokevirtual #195                // Method getSection:()Ljava/util/List;
      18: aload_1
      19: invokeinterface #155,  2          // InterfaceMethod java/util/List.add:(Ljava/lang/Object;)Z
      24: pop
      25: aload_0
      26: areturn

  public ca.uhn.fhir.model.dstu2.resource.Composition$Section getSectionFirstRep();
    Code:
       0: aload_0
       1: invokevirtual #195                // Method getSection:()Ljava/util/List;
       4: invokeinterface #172,  1          // InterfaceMethod java/util/List.isEmpty:()Z
       9: ifeq          17
      12: aload_0
      13: invokevirtual #198                // Method addSection:()Lca/uhn/fhir/model/dstu2/resource/Composition$Section;
      16: areturn
      17: aload_0
      18: invokevirtual #195                // Method getSection:()Ljava/util/List;
      21: iconst_0
      22: invokeinterface #178,  2          // InterfaceMethod java/util/List.get:(I)Ljava/lang/Object;
      27: checkcast     #192                // class ca/uhn/fhir/model/dstu2/resource/Composition$Section
      30: areturn

  public java.lang.String getResourceName();
    Code:
       0: ldc           #202                // String Composition
       2: areturn

  public ca.uhn.fhir.context.FhirVersionEnum getStructureFhirVersionEnum();
    Code:
       0: getstatic     #204                // Field ca/uhn/fhir/context/FhirVersionEnum.DSTU2:Lca/uhn/fhir/context/FhirVersionEnum;
       3: areturn

  static {};
    Code:
       0: new           #210                // class ca/uhn/fhir/rest/gclient/TokenClientParam
       3: dup
       4: ldc           #212                // String type
       6: invokespecial #214                // Method ca/uhn/fhir/rest/gclient/TokenClientParam."<init>":(Ljava/lang/String;)V
       9: putstatic     #215                // Field TYPE:Lca/uhn/fhir/rest/gclient/TokenClientParam;
      12: new           #210                // class ca/uhn/fhir/rest/gclient/TokenClientParam
      15: dup
      16: ldc           #219                // String class
      18: invokespecial #214                // Method ca/uhn/fhir/rest/gclient/TokenClientParam."<init>":(Ljava/lang/String;)V
      21: putstatic     #221                // Field CLASS:Lca/uhn/fhir/rest/gclient/TokenClientParam;
      24: new           #224                // class ca/uhn/fhir/rest/gclient/DateClientParam
      27: dup
      28: ldc           #226                // String date
      30: invokespecial #228                // Method ca/uhn/fhir/rest/gclient/DateClientParam."<init>":(Ljava/lang/String;)V
      33: putstatic     #229                // Field DATE:Lca/uhn/fhir/rest/gclient/DateClientParam;
      36: new           #233                // class ca/uhn/fhir/rest/gclient/ReferenceClientParam
      39: dup
      40: ldc           #235                // String subject
      42: invokespecial #237                // Method ca/uhn/fhir/rest/gclient/ReferenceClientParam."<init>":(Ljava/lang/String;)V
      45: putstatic     #238                // Field SUBJECT:Lca/uhn/fhir/rest/gclient/ReferenceClientParam;
      48: new           #233                // class ca/uhn/fhir/rest/gclient/ReferenceClientParam
      51: dup
      52: ldc           #242                // String author
      54: invokespecial #237                // Method ca/uhn/fhir/rest/gclient/ReferenceClientParam."<init>":(Ljava/lang/String;)V
      57: putstatic     #244                // Field AUTHOR:Lca/uhn/fhir/rest/gclient/ReferenceClientParam;
      60: new           #233                // class ca/uhn/fhir/rest/gclient/ReferenceClientParam
      63: dup
      64: ldc           #247                // String attester
      66: invokespecial #237                // Method ca/uhn/fhir/rest/gclient/ReferenceClientParam."<init>":(Ljava/lang/String;)V
      69: putstatic     #249                // Field ATTESTER:Lca/uhn/fhir/rest/gclient/ReferenceClientParam;
      72: new           #210                // class ca/uhn/fhir/rest/gclient/TokenClientParam
      75: dup
      76: ldc           #252                // String context
      78: invokespecial #214                // Method ca/uhn/fhir/rest/gclient/TokenClientParam."<init>":(Ljava/lang/String;)V
      81: putstatic     #254                // Field CONTEXT:Lca/uhn/fhir/rest/gclient/TokenClientParam;
      84: new           #210                // class ca/uhn/fhir/rest/gclient/TokenClientParam
      87: dup
      88: ldc_w         #257                // String section
      91: invokespecial #214                // Method ca/uhn/fhir/rest/gclient/TokenClientParam."<init>":(Ljava/lang/String;)V
      94: putstatic     #259                // Field SECTION:Lca/uhn/fhir/rest/gclient/TokenClientParam;
      97: new           #233                // class ca/uhn/fhir/rest/gclient/ReferenceClientParam
     100: dup
     101: ldc_w         #262                // String entry
     104: invokespecial #237                // Method ca/uhn/fhir/rest/gclient/ReferenceClientParam."<init>":(Ljava/lang/String;)V
     107: putstatic     #264                // Field ENTRY:Lca/uhn/fhir/rest/gclient/ReferenceClientParam;
     110: new           #210                // class ca/uhn/fhir/rest/gclient/TokenClientParam
     113: dup
     114: ldc_w         #267                // String identifier
     117: invokespecial #214                // Method ca/uhn/fhir/rest/gclient/TokenClientParam."<init>":(Ljava/lang/String;)V
     120: putstatic     #269                // Field IDENTIFIER:Lca/uhn/fhir/rest/gclient/TokenClientParam;
     123: new           #272                // class ca/uhn/fhir/rest/gclient/StringClientParam
     126: dup
     127: ldc_w         #274                // String title
     130: invokespecial #276                // Method ca/uhn/fhir/rest/gclient/StringClientParam."<init>":(Ljava/lang/String;)V
     133: putstatic     #277                // Field TITLE:Lca/uhn/fhir/rest/gclient/StringClientParam;
     136: new           #210                // class ca/uhn/fhir/rest/gclient/TokenClientParam
     139: dup
     140: ldc_w         #281                // String status
     143: invokespecial #214                // Method ca/uhn/fhir/rest/gclient/TokenClientParam."<init>":(Ljava/lang/String;)V
     146: putstatic     #283                // Field STATUS:Lca/uhn/fhir/rest/gclient/TokenClientParam;
     149: new           #210                // class ca/uhn/fhir/rest/gclient/TokenClientParam
     152: dup
     153: ldc_w         #286                // String confidentiality
     156: invokespecial #214                // Method ca/uhn/fhir/rest/gclient/TokenClientParam."<init>":(Ljava/lang/String;)V
     159: putstatic     #288                // Field CONFIDENTIALITY:Lca/uhn/fhir/rest/gclient/TokenClientParam;
     162: new           #224                // class ca/uhn/fhir/rest/gclient/DateClientParam
     165: dup
     166: ldc_w         #291                // String period
     169: invokespecial #228                // Method ca/uhn/fhir/rest/gclient/DateClientParam."<init>":(Ljava/lang/String;)V
     172: putstatic     #293                // Field PERIOD:Lca/uhn/fhir/rest/gclient/DateClientParam;
     175: new           #233                // class ca/uhn/fhir/rest/gclient/ReferenceClientParam
     178: dup
     179: ldc_w         #296                // String patient
     182: invokespecial #237                // Method ca/uhn/fhir/rest/gclient/ReferenceClientParam."<init>":(Ljava/lang/String;)V
     185: putstatic     #298                // Field PATIENT:Lca/uhn/fhir/rest/gclient/ReferenceClientParam;
     188: new           #233                // class ca/uhn/fhir/rest/gclient/ReferenceClientParam
     191: dup
     192: ldc_w         #301                // String encounter
     195: invokespecial #237                // Method ca/uhn/fhir/rest/gclient/ReferenceClientParam."<init>":(Ljava/lang/String;)V
     198: putstatic     #303                // Field ENCOUNTER:Lca/uhn/fhir/rest/gclient/ReferenceClientParam;
     201: new           #306                // class ca/uhn/fhir/model/api/Include
     204: dup
     205: ldc_w         #308                // String Composition:attester
     208: invokespecial #310                // Method ca/uhn/fhir/model/api/Include."<init>":(Ljava/lang/String;)V
     211: putstatic     #311                // Field INCLUDE_ATTESTER:Lca/uhn/fhir/model/api/Include;
     214: new           #306                // class ca/uhn/fhir/model/api/Include
     217: dup
     218: ldc_w         #315                // String Composition:author
     221: invokespecial #310                // Method ca/uhn/fhir/model/api/Include."<init>":(Ljava/lang/String;)V
     224: putstatic     #317                // Field INCLUDE_AUTHOR:Lca/uhn/fhir/model/api/Include;
     227: new           #306                // class ca/uhn/fhir/model/api/Include
     230: dup
     231: ldc_w         #320                // String Composition:encounter
     234: invokespecial #310                // Method ca/uhn/fhir/model/api/Include."<init>":(Ljava/lang/String;)V
     237: putstatic     #322                // Field INCLUDE_ENCOUNTER:Lca/uhn/fhir/model/api/Include;
     240: new           #306                // class ca/uhn/fhir/model/api/Include
     243: dup
     244: ldc_w         #325                // String Composition:entry
     247: invokespecial #310                // Method ca/uhn/fhir/model/api/Include."<init>":(Ljava/lang/String;)V
     250: putstatic     #327                // Field INCLUDE_ENTRY:Lca/uhn/fhir/model/api/Include;
     253: new           #306                // class ca/uhn/fhir/model/api/Include
     256: dup
     257: ldc_w         #330                // String Composition:patient
     260: invokespecial #310                // Method ca/uhn/fhir/model/api/Include."<init>":(Ljava/lang/String;)V
     263: putstatic     #332                // Field INCLUDE_PATIENT:Lca/uhn/fhir/model/api/Include;
     266: new           #306                // class ca/uhn/fhir/model/api/Include
     269: dup
     270: ldc_w         #335                // String Composition:subject
     273: invokespecial #310                // Method ca/uhn/fhir/model/api/Include."<init>":(Ljava/lang/String;)V
     276: putstatic     #337                // Field INCLUDE_SUBJECT:Lca/uhn/fhir/model/api/Include;
     279: return
}
