Compiled from "Condition.java"
public class ca.uhn.fhir.model.dstu2.resource.Condition extends ca.uhn.fhir.model.dstu2.resource.BaseResource implements ca.uhn.fhir.model.api.IResource {
  public static final java.lang.String SP_CODE;

  public static final ca.uhn.fhir.rest.gclient.TokenClientParam CODE;

  public static final java.lang.String SP_IDENTIFIER;

  public static final ca.uhn.fhir.rest.gclient.TokenClientParam IDENTIFIER;

  public static final java.lang.String SP_CLINICALSTATUS;

  public static final ca.uhn.fhir.rest.gclient.TokenClientParam CLINICALSTATUS;

  public static final java.lang.String SP_SEVERITY;

  public static final ca.uhn.fhir.rest.gclient.TokenClientParam SEVERITY;

  public static final java.lang.String SP_CATEGORY;

  public static final ca.uhn.fhir.rest.gclient.TokenClientParam CATEGORY;

  public static final java.lang.String SP_ONSET;

  public static final ca.uhn.fhir.rest.gclient.DateClientParam ONSET;

  public static final java.lang.String SP_ONSET_INFO;

  public static final ca.uhn.fhir.rest.gclient.StringClientParam ONSET_INFO;

  public static final java.lang.String SP_ENCOUNTER;

  public static final ca.uhn.fhir.rest.gclient.ReferenceClientParam ENCOUNTER;

  public static final java.lang.String SP_ASSERTER;

  public static final ca.uhn.fhir.rest.gclient.ReferenceClientParam ASSERTER;

  public static final java.lang.String SP_DATE_RECORDED;

  public static final ca.uhn.fhir.rest.gclient.DateClientParam DATE_RECORDED;

  public static final java.lang.String SP_EVIDENCE;

  public static final ca.uhn.fhir.rest.gclient.TokenClientParam EVIDENCE;

  public static final java.lang.String SP_BODY_SITE;

  public static final ca.uhn.fhir.rest.gclient.TokenClientParam BODY_SITE;

  public static final java.lang.String SP_STAGE;

  public static final ca.uhn.fhir.rest.gclient.TokenClientParam STAGE;

  public static final java.lang.String SP_PATIENT;

  public static final ca.uhn.fhir.rest.gclient.ReferenceClientParam PATIENT;

  public static final ca.uhn.fhir.model.api.Include INCLUDE_ASSERTER;

  public static final ca.uhn.fhir.model.api.Include INCLUDE_ENCOUNTER;

  public static final ca.uhn.fhir.model.api.Include INCLUDE_PATIENT;

  private java.util.List<ca.uhn.fhir.model.dstu2.composite.IdentifierDt> myIdentifier;

  private ca.uhn.fhir.model.dstu2.composite.ResourceReferenceDt myPatient;

  private ca.uhn.fhir.model.dstu2.composite.ResourceReferenceDt myEncounter;

  private ca.uhn.fhir.model.dstu2.composite.ResourceReferenceDt myAsserter;

  private ca.uhn.fhir.model.primitive.DateDt myDateRecorded;

  private ca.uhn.fhir.model.dstu2.composite.CodeableConceptDt myCode;

  private ca.uhn.fhir.model.dstu2.composite.BoundCodeableConceptDt<ca.uhn.fhir.model.dstu2.valueset.ConditionCategoryCodesEnum> myCategory;

  private ca.uhn.fhir.model.primitive.BoundCodeDt<ca.uhn.fhir.model.dstu2.valueset.ConditionClinicalStatusCodesEnum> myClinicalStatus;

  private ca.uhn.fhir.model.primitive.BoundCodeDt<ca.uhn.fhir.model.dstu2.valueset.ConditionVerificationStatusEnum> myVerificationStatus;

  private ca.uhn.fhir.model.dstu2.composite.CodeableConceptDt mySeverity;

  private ca.uhn.fhir.model.api.IDatatype myOnset;

  private ca.uhn.fhir.model.api.IDatatype myAbatement;

  private ca.uhn.fhir.model.dstu2.resource.Condition$Stage myStage;

  private java.util.List<ca.uhn.fhir.model.dstu2.resource.Condition$Evidence> myEvidence;

  private java.util.List<ca.uhn.fhir.model.dstu2.composite.CodeableConceptDt> myBodySite;

  private ca.uhn.fhir.model.primitive.StringDt myNotes;

  public ca.uhn.fhir.model.dstu2.resource.Condition();
    Code:
       0: aload_0
       1: invokespecial #1                  // Method ca/uhn/fhir/model/dstu2/resource/BaseResource."<init>":()V
       4: return

  public boolean isEmpty();
    Code:
       0: aload_0
       1: invokespecial #7                  // Method ca/uhn/fhir/model/dstu2/resource/BaseResource.isBaseEmpty:()Z
       4: ifeq          144
       7: bipush        16
       9: anewarray     #11                 // class java/lang/Object
      12: dup
      13: iconst_0
      14: aload_0
      15: getfield      #13                 // Field myIdentifier:Ljava/util/List;
      18: aastore
      19: dup
      20: iconst_1
      21: aload_0
      22: getfield      #19                 // Field myPatient:Lca/uhn/fhir/model/dstu2/composite/ResourceReferenceDt;
      25: aastore
      26: dup
      27: iconst_2
      28: aload_0
      29: getfield      #23                 // Field myEncounter:Lca/uhn/fhir/model/dstu2/composite/ResourceReferenceDt;
      32: aastore
      33: dup
      34: iconst_3
      35: aload_0
      36: getfield      #26                 // Field myAsserter:Lca/uhn/fhir/model/dstu2/composite/ResourceReferenceDt;
      39: aastore
      40: dup
      41: iconst_4
      42: aload_0
      43: getfield      #29                 // Field myDateRecorded:Lca/uhn/fhir/model/primitive/DateDt;
      46: aastore
      47: dup
      48: iconst_5
      49: aload_0
      50: getfield      #33                 // Field myCode:Lca/uhn/fhir/model/dstu2/composite/CodeableConceptDt;
      53: aastore
      54: dup
      55: bipush        6
      57: aload_0
      58: getfield      #37                 // Field myCategory:Lca/uhn/fhir/model/dstu2/composite/BoundCodeableConceptDt;
      61: aastore
      62: dup
      63: bipush        7
      65: aload_0
      66: getfield      #41                 // Field myClinicalStatus:Lca/uhn/fhir/model/primitive/BoundCodeDt;
      69: aastore
      70: dup
      71: bipush        8
      73: aload_0
      74: getfield      #45                 // Field myVerificationStatus:Lca/uhn/fhir/model/primitive/BoundCodeDt;
      77: aastore
      78: dup
      79: bipush        9
      81: aload_0
      82: getfield      #48                 // Field mySeverity:Lca/uhn/fhir/model/dstu2/composite/CodeableConceptDt;
      85: aastore
      86: dup
      87: bipush        10
      89: aload_0
      90: getfield      #51                 // Field myOnset:Lca/uhn/fhir/model/api/IDatatype;
      93: aastore
      94: dup
      95: bipush        11
      97: aload_0
      98: getfield      #55                 // Field myAbatement:Lca/uhn/fhir/model/api/IDatatype;
     101: aastore
     102: dup
     103: bipush        12
     105: aload_0
     106: getfield      #58                 // Field myStage:Lca/uhn/fhir/model/dstu2/resource/Condition$Stage;
     109: aastore
     110: dup
     111: bipush        13
     113: aload_0
     114: getfield      #62                 // Field myEvidence:Ljava/util/List;
     117: aastore
     118: dup
     119: bipush        14
     121: aload_0
     122: getfield      #65                 // Field myBodySite:Ljava/util/List;
     125: aastore
     126: dup
     127: bipush        15
     129: aload_0
     130: getfield      #68                 // Field myNotes:Lca/uhn/fhir/model/primitive/StringDt;
     133: aastore
     134: invokestatic  #72                 // Method ca/uhn/fhir/util/ElementUtil.isEmpty:([Ljava/lang/Object;)Z
     137: ifeq          144
     140: iconst_1
     141: goto          145
     144: iconst_0
     145: ireturn

  public <T extends ca.uhn.fhir.model.api.IElement> java.util.List<T> getAllPopulatedChildElementsOfType(java.lang.Class<T>);
    Code:
       0: aload_1
       1: bipush        16
       3: anewarray     #11                 // class java/lang/Object
       6: dup
       7: iconst_0
       8: aload_0
       9: getfield      #13                 // Field myIdentifier:Ljava/util/List;
      12: aastore
      13: dup
      14: iconst_1
      15: aload_0
      16: getfield      #19                 // Field myPatient:Lca/uhn/fhir/model/dstu2/composite/ResourceReferenceDt;
      19: aastore
      20: dup
      21: iconst_2
      22: aload_0
      23: getfield      #23                 // Field myEncounter:Lca/uhn/fhir/model/dstu2/composite/ResourceReferenceDt;
      26: aastore
      27: dup
      28: iconst_3
      29: aload_0
      30: getfield      #26                 // Field myAsserter:Lca/uhn/fhir/model/dstu2/composite/ResourceReferenceDt;
      33: aastore
      34: dup
      35: iconst_4
      36: aload_0
      37: getfield      #29                 // Field myDateRecorded:Lca/uhn/fhir/model/primitive/DateDt;
      40: aastore
      41: dup
      42: iconst_5
      43: aload_0
      44: getfield      #33                 // Field myCode:Lca/uhn/fhir/model/dstu2/composite/CodeableConceptDt;
      47: aastore
      48: dup
      49: bipush        6
      51: aload_0
      52: getfield      #37                 // Field myCategory:Lca/uhn/fhir/model/dstu2/composite/BoundCodeableConceptDt;
      55: aastore
      56: dup
      57: bipush        7
      59: aload_0
      60: getfield      #41                 // Field myClinicalStatus:Lca/uhn/fhir/model/primitive/BoundCodeDt;
      63: aastore
      64: dup
      65: bipush        8
      67: aload_0
      68: getfield      #45                 // Field myVerificationStatus:Lca/uhn/fhir/model/primitive/BoundCodeDt;
      71: aastore
      72: dup
      73: bipush        9
      75: aload_0
      76: getfield      #48                 // Field mySeverity:Lca/uhn/fhir/model/dstu2/composite/CodeableConceptDt;
      79: aastore
      80: dup
      81: bipush        10
      83: aload_0
      84: getfield      #51                 // Field myOnset:Lca/uhn/fhir/model/api/IDatatype;
      87: aastore
      88: dup
      89: bipush        11
      91: aload_0
      92: getfield      #55                 // Field myAbatement:Lca/uhn/fhir/model/api/IDatatype;
      95: aastore
      96: dup
      97: bipush        12
      99: aload_0
     100: getfield      #58                 // Field myStage:Lca/uhn/fhir/model/dstu2/resource/Condition$Stage;
     103: aastore
     104: dup
     105: bipush        13
     107: aload_0
     108: getfield      #62                 // Field myEvidence:Ljava/util/List;
     111: aastore
     112: dup
     113: bipush        14
     115: aload_0
     116: getfield      #65                 // Field myBodySite:Ljava/util/List;
     119: aastore
     120: dup
     121: bipush        15
     123: aload_0
     124: getfield      #68                 // Field myNotes:Lca/uhn/fhir/model/primitive/StringDt;
     127: aastore
     128: invokestatic  #78                 // Method ca/uhn/fhir/util/ElementUtil.allPopulatedChildElements:(Ljava/lang/Class;[Ljava/lang/Object;)Ljava/util/List;
     131: areturn

  public java.util.List<ca.uhn.fhir.model.dstu2.composite.IdentifierDt> getIdentifier();
    Code:
       0: aload_0
       1: getfield      #13                 // Field myIdentifier:Ljava/util/List;
       4: ifnonnull     18
       7: aload_0
       8: new           #82                 // class java/util/ArrayList
      11: dup
      12: invokespecial #84                 // Method java/util/ArrayList."<init>":()V
      15: putfield      #13                 // Field myIdentifier:Ljava/util/List;
      18: aload_0
      19: getfield      #13                 // Field myIdentifier:Ljava/util/List;
      22: areturn

  public ca.uhn.fhir.model.dstu2.resource.Condition setIdentifier(java.util.List<ca.uhn.fhir.model.dstu2.composite.IdentifierDt>);
    Code:
       0: aload_0
       1: aload_1
       2: putfield      #13                 // Field myIdentifier:Ljava/util/List;
       5: aload_0
       6: areturn

  public ca.uhn.fhir.model.dstu2.composite.IdentifierDt addIdentifier();
    Code:
       0: new           #85                 // class ca/uhn/fhir/model/dstu2/composite/IdentifierDt
       3: dup
       4: invokespecial #87                 // Method ca/uhn/fhir/model/dstu2/composite/IdentifierDt."<init>":()V
       7: astore_1
       8: aload_0
       9: invokevirtual #88                 // Method getIdentifier:()Ljava/util/List;
      12: aload_1
      13: invokeinterface #92,  2           // InterfaceMethod java/util/List.add:(Ljava/lang/Object;)Z
      18: pop
      19: aload_1
      20: areturn

  public ca.uhn.fhir.model.dstu2.resource.Condition addIdentifier(ca.uhn.fhir.model.dstu2.composite.IdentifierDt);
    Code:
       0: aload_1
       1: ifnonnull     14
       4: new           #98                 // class java/lang/NullPointerException
       7: dup
       8: ldc           #100                // String theValue must not be null
      10: invokespecial #102                // Method java/lang/NullPointerException."<init>":(Ljava/lang/String;)V
      13: athrow
      14: aload_0
      15: invokevirtual #88                 // Method getIdentifier:()Ljava/util/List;
      18: aload_1
      19: invokeinterface #92,  2           // InterfaceMethod java/util/List.add:(Ljava/lang/Object;)Z
      24: pop
      25: aload_0
      26: areturn

  public ca.uhn.fhir.model.dstu2.composite.IdentifierDt getIdentifierFirstRep();
    Code:
       0: aload_0
       1: invokevirtual #88                 // Method getIdentifier:()Ljava/util/List;
       4: invokeinterface #105,  1          // InterfaceMethod java/util/List.isEmpty:()Z
       9: ifeq          17
      12: aload_0
      13: invokevirtual #107                // Method addIdentifier:()Lca/uhn/fhir/model/dstu2/composite/IdentifierDt;
      16: areturn
      17: aload_0
      18: invokevirtual #88                 // Method getIdentifier:()Ljava/util/List;
      21: iconst_0
      22: invokeinterface #111,  2          // InterfaceMethod java/util/List.get:(I)Ljava/lang/Object;
      27: checkcast     #85                 // class ca/uhn/fhir/model/dstu2/composite/IdentifierDt
      30: areturn

  public ca.uhn.fhir.model.dstu2.composite.ResourceReferenceDt getPatient();
    Code:
       0: aload_0
       1: getfield      #19                 // Field myPatient:Lca/uhn/fhir/model/dstu2/composite/ResourceReferenceDt;
       4: ifnonnull     18
       7: aload_0
       8: new           #115                // class ca/uhn/fhir/model/dstu2/composite/ResourceReferenceDt
      11: dup
      12: invokespecial #117                // Method ca/uhn/fhir/model/dstu2/composite/ResourceReferenceDt."<init>":()V
      15: putfield      #19                 // Field myPatient:Lca/uhn/fhir/model/dstu2/composite/ResourceReferenceDt;
      18: aload_0
      19: getfield      #19                 // Field myPatient:Lca/uhn/fhir/model/dstu2/composite/ResourceReferenceDt;
      22: areturn

  public ca.uhn.fhir.model.dstu2.resource.Condition setPatient(ca.uhn.fhir.model.dstu2.composite.ResourceReferenceDt);
    Code:
       0: aload_0
       1: aload_1
       2: putfield      #19                 // Field myPatient:Lca/uhn/fhir/model/dstu2/composite/ResourceReferenceDt;
       5: aload_0
       6: areturn

  public ca.uhn.fhir.model.dstu2.composite.ResourceReferenceDt getEncounter();
    Code:
       0: aload_0
       1: getfield      #23                 // Field myEncounter:Lca/uhn/fhir/model/dstu2/composite/ResourceReferenceDt;
       4: ifnonnull     18
       7: aload_0
       8: new           #115                // class ca/uhn/fhir/model/dstu2/composite/ResourceReferenceDt
      11: dup
      12: invokespecial #117                // Method ca/uhn/fhir/model/dstu2/composite/ResourceReferenceDt."<init>":()V
      15: putfield      #23                 // Field myEncounter:Lca/uhn/fhir/model/dstu2/composite/ResourceReferenceDt;
      18: aload_0
      19: getfield      #23                 // Field myEncounter:Lca/uhn/fhir/model/dstu2/composite/ResourceReferenceDt;
      22: areturn

  public ca.uhn.fhir.model.dstu2.resource.Condition setEncounter(ca.uhn.fhir.model.dstu2.composite.ResourceReferenceDt);
    Code:
       0: aload_0
       1: aload_1
       2: putfield      #23                 // Field myEncounter:Lca/uhn/fhir/model/dstu2/composite/ResourceReferenceDt;
       5: aload_0
       6: areturn

  public ca.uhn.fhir.model.dstu2.composite.ResourceReferenceDt getAsserter();
    Code:
       0: aload_0
       1: getfield      #26                 // Field myAsserter:Lca/uhn/fhir/model/dstu2/composite/ResourceReferenceDt;
       4: ifnonnull     18
       7: aload_0
       8: new           #115                // class ca/uhn/fhir/model/dstu2/composite/ResourceReferenceDt
      11: dup
      12: invokespecial #117                // Method ca/uhn/fhir/model/dstu2/composite/ResourceReferenceDt."<init>":()V
      15: putfield      #26                 // Field myAsserter:Lca/uhn/fhir/model/dstu2/composite/ResourceReferenceDt;
      18: aload_0
      19: getfield      #26                 // Field myAsserter:Lca/uhn/fhir/model/dstu2/composite/ResourceReferenceDt;
      22: areturn

  public ca.uhn.fhir.model.dstu2.resource.Condition setAsserter(ca.uhn.fhir.model.dstu2.composite.ResourceReferenceDt);
    Code:
       0: aload_0
       1: aload_1
       2: putfield      #26                 // Field myAsserter:Lca/uhn/fhir/model/dstu2/composite/ResourceReferenceDt;
       5: aload_0
       6: areturn

  public ca.uhn.fhir.model.primitive.DateDt getDateRecordedElement();
    Code:
       0: aload_0
       1: getfield      #29                 // Field myDateRecorded:Lca/uhn/fhir/model/primitive/DateDt;
       4: ifnonnull     18
       7: aload_0
       8: new           #118                // class ca/uhn/fhir/model/primitive/DateDt
      11: dup
      12: invokespecial #120                // Method ca/uhn/fhir/model/primitive/DateDt."<init>":()V
      15: putfield      #29                 // Field myDateRecorded:Lca/uhn/fhir/model/primitive/DateDt;
      18: aload_0
      19: getfield      #29                 // Field myDateRecorded:Lca/uhn/fhir/model/primitive/DateDt;
      22: areturn

  public java.util.Date getDateRecorded();
    Code:
       0: aload_0
       1: invokevirtual #121                // Method getDateRecordedElement:()Lca/uhn/fhir/model/primitive/DateDt;
       4: invokevirtual #125                // Method ca/uhn/fhir/model/primitive/DateDt.getValue:()Ljava/lang/Object;
       7: checkcast     #129                // class java/util/Date
      10: areturn

  public ca.uhn.fhir.model.dstu2.resource.Condition setDateRecorded(ca.uhn.fhir.model.primitive.DateDt);
    Code:
       0: aload_0
       1: aload_1
       2: putfield      #29                 // Field myDateRecorded:Lca/uhn/fhir/model/primitive/DateDt;
       5: aload_0
       6: areturn

  public ca.uhn.fhir.model.dstu2.resource.Condition setDateRecorded(java.util.Date, ca.uhn.fhir.model.api.TemporalPrecisionEnum);
    Code:
       0: aload_0
       1: new           #118                // class ca/uhn/fhir/model/primitive/DateDt
       4: dup
       5: aload_1
       6: aload_2
       7: invokespecial #131                // Method ca/uhn/fhir/model/primitive/DateDt."<init>":(Ljava/util/Date;Lca/uhn/fhir/model/api/TemporalPrecisionEnum;)V
      10: putfield      #29                 // Field myDateRecorded:Lca/uhn/fhir/model/primitive/DateDt;
      13: aload_0
      14: areturn

  public ca.uhn.fhir.model.dstu2.resource.Condition setDateRecordedWithDayPrecision(java.util.Date);
    Code:
       0: aload_0
       1: new           #118                // class ca/uhn/fhir/model/primitive/DateDt
       4: dup
       5: aload_1
       6: invokespecial #134                // Method ca/uhn/fhir/model/primitive/DateDt."<init>":(Ljava/util/Date;)V
       9: putfield      #29                 // Field myDateRecorded:Lca/uhn/fhir/model/primitive/DateDt;
      12: aload_0
      13: areturn

  public ca.uhn.fhir.model.dstu2.composite.CodeableConceptDt getCode();
    Code:
       0: aload_0
       1: getfield      #33                 // Field myCode:Lca/uhn/fhir/model/dstu2/composite/CodeableConceptDt;
       4: ifnonnull     18
       7: aload_0
       8: new           #137                // class ca/uhn/fhir/model/dstu2/composite/CodeableConceptDt
      11: dup
      12: invokespecial #139                // Method ca/uhn/fhir/model/dstu2/composite/CodeableConceptDt."<init>":()V
      15: putfield      #33                 // Field myCode:Lca/uhn/fhir/model/dstu2/composite/CodeableConceptDt;
      18: aload_0
      19: getfield      #33                 // Field myCode:Lca/uhn/fhir/model/dstu2/composite/CodeableConceptDt;
      22: areturn

  public ca.uhn.fhir.model.dstu2.resource.Condition setCode(ca.uhn.fhir.model.dstu2.composite.CodeableConceptDt);
    Code:
       0: aload_0
       1: aload_1
       2: putfield      #33                 // Field myCode:Lca/uhn/fhir/model/dstu2/composite/CodeableConceptDt;
       5: aload_0
       6: areturn

  public ca.uhn.fhir.model.dstu2.composite.BoundCodeableConceptDt<ca.uhn.fhir.model.dstu2.valueset.ConditionCategoryCodesEnum> getCategory();
    Code:
       0: aload_0
       1: getfield      #37                 // Field myCategory:Lca/uhn/fhir/model/dstu2/composite/BoundCodeableConceptDt;
       4: ifnonnull     21
       7: aload_0
       8: new           #140                // class ca/uhn/fhir/model/dstu2/composite/BoundCodeableConceptDt
      11: dup
      12: getstatic     #142                // Field ca/uhn/fhir/model/dstu2/valueset/ConditionCategoryCodesEnum.VALUESET_BINDER:Lca/uhn/fhir/model/api/IValueSetEnumBinder;
      15: invokespecial #148                // Method ca/uhn/fhir/model/dstu2/composite/BoundCodeableConceptDt."<init>":(Lca/uhn/fhir/model/api/IValueSetEnumBinder;)V
      18: putfield      #37                 // Field myCategory:Lca/uhn/fhir/model/dstu2/composite/BoundCodeableConceptDt;
      21: aload_0
      22: getfield      #37                 // Field myCategory:Lca/uhn/fhir/model/dstu2/composite/BoundCodeableConceptDt;
      25: areturn

  public ca.uhn.fhir.model.dstu2.resource.Condition setCategory(ca.uhn.fhir.model.dstu2.composite.BoundCodeableConceptDt<ca.uhn.fhir.model.dstu2.valueset.ConditionCategoryCodesEnum>);
    Code:
       0: aload_0
       1: aload_1
       2: putfield      #37                 // Field myCategory:Lca/uhn/fhir/model/dstu2/composite/BoundCodeableConceptDt;
       5: aload_0
       6: areturn

  public ca.uhn.fhir.model.dstu2.resource.Condition setCategory(ca.uhn.fhir.model.dstu2.valueset.ConditionCategoryCodesEnum);
    Code:
       0: aload_0
       1: new           #140                // class ca/uhn/fhir/model/dstu2/composite/BoundCodeableConceptDt
       4: dup
       5: getstatic     #142                // Field ca/uhn/fhir/model/dstu2/valueset/ConditionCategoryCodesEnum.VALUESET_BINDER:Lca/uhn/fhir/model/api/IValueSetEnumBinder;
       8: aload_1
       9: invokespecial #151                // Method ca/uhn/fhir/model/dstu2/composite/BoundCodeableConceptDt."<init>":(Lca/uhn/fhir/model/api/IValueSetEnumBinder;Ljava/lang/Enum;)V
      12: invokevirtual #154                // Method setCategory:(Lca/uhn/fhir/model/dstu2/composite/BoundCodeableConceptDt;)Lca/uhn/fhir/model/dstu2/resource/Condition;
      15: pop
      16: aload_0
      17: areturn

  public ca.uhn.fhir.model.primitive.BoundCodeDt<ca.uhn.fhir.model.dstu2.valueset.ConditionClinicalStatusCodesEnum> getClinicalStatusElement();
    Code:
       0: aload_0
       1: getfield      #41                 // Field myClinicalStatus:Lca/uhn/fhir/model/primitive/BoundCodeDt;
       4: ifnonnull     21
       7: aload_0
       8: new           #158                // class ca/uhn/fhir/model/primitive/BoundCodeDt
      11: dup
      12: getstatic     #160                // Field ca/uhn/fhir/model/dstu2/valueset/ConditionClinicalStatusCodesEnum.VALUESET_BINDER:Lca/uhn/fhir/model/api/IValueSetEnumBinder;
      15: invokespecial #163                // Method ca/uhn/fhir/model/primitive/BoundCodeDt."<init>":(Lca/uhn/fhir/model/api/IValueSetEnumBinder;)V
      18: putfield      #41                 // Field myClinicalStatus:Lca/uhn/fhir/model/primitive/BoundCodeDt;
      21: aload_0
      22: getfield      #41                 // Field myClinicalStatus:Lca/uhn/fhir/model/primitive/BoundCodeDt;
      25: areturn

  public java.lang.String getClinicalStatus();
    Code:
       0: aload_0
       1: invokevirtual #164                // Method getClinicalStatusElement:()Lca/uhn/fhir/model/primitive/BoundCodeDt;
       4: invokevirtual #168                // Method ca/uhn/fhir/model/primitive/BoundCodeDt.getValue:()Ljava/lang/Object;
       7: checkcast     #169                // class java/lang/String
      10: areturn

  public ca.uhn.fhir.model.dstu2.resource.Condition setClinicalStatus(ca.uhn.fhir.model.primitive.BoundCodeDt<ca.uhn.fhir.model.dstu2.valueset.ConditionClinicalStatusCodesEnum>);
    Code:
       0: aload_0
       1: aload_1
       2: putfield      #41                 // Field myClinicalStatus:Lca/uhn/fhir/model/primitive/BoundCodeDt;
       5: aload_0
       6: areturn

  public ca.uhn.fhir.model.dstu2.resource.Condition setClinicalStatus(ca.uhn.fhir.model.dstu2.valueset.ConditionClinicalStatusCodesEnum);
    Code:
       0: aload_0
       1: new           #158                // class ca/uhn/fhir/model/primitive/BoundCodeDt
       4: dup
       5: getstatic     #160                // Field ca/uhn/fhir/model/dstu2/valueset/ConditionClinicalStatusCodesEnum.VALUESET_BINDER:Lca/uhn/fhir/model/api/IValueSetEnumBinder;
       8: aload_1
       9: invokespecial #171                // Method ca/uhn/fhir/model/primitive/BoundCodeDt."<init>":(Lca/uhn/fhir/model/api/IValueSetEnumBinder;Ljava/lang/Enum;)V
      12: invokevirtual #172                // Method setClinicalStatus:(Lca/uhn/fhir/model/primitive/BoundCodeDt;)Lca/uhn/fhir/model/dstu2/resource/Condition;
      15: pop
      16: aload_0
      17: areturn

  public ca.uhn.fhir.model.primitive.BoundCodeDt<ca.uhn.fhir.model.dstu2.valueset.ConditionVerificationStatusEnum> getVerificationStatusElement();
    Code:
       0: aload_0
       1: getfield      #45                 // Field myVerificationStatus:Lca/uhn/fhir/model/primitive/BoundCodeDt;
       4: ifnonnull     21
       7: aload_0
       8: new           #158                // class ca/uhn/fhir/model/primitive/BoundCodeDt
      11: dup
      12: getstatic     #176                // Field ca/uhn/fhir/model/dstu2/valueset/ConditionVerificationStatusEnum.VALUESET_BINDER:Lca/uhn/fhir/model/api/IValueSetEnumBinder;
      15: invokespecial #163                // Method ca/uhn/fhir/model/primitive/BoundCodeDt."<init>":(Lca/uhn/fhir/model/api/IValueSetEnumBinder;)V
      18: putfield      #45                 // Field myVerificationStatus:Lca/uhn/fhir/model/primitive/BoundCodeDt;
      21: aload_0
      22: getfield      #45                 // Field myVerificationStatus:Lca/uhn/fhir/model/primitive/BoundCodeDt;
      25: areturn

  public java.lang.String getVerificationStatus();
    Code:
       0: aload_0
       1: invokevirtual #179                // Method getVerificationStatusElement:()Lca/uhn/fhir/model/primitive/BoundCodeDt;
       4: invokevirtual #168                // Method ca/uhn/fhir/model/primitive/BoundCodeDt.getValue:()Ljava/lang/Object;
       7: checkcast     #169                // class java/lang/String
      10: areturn

  public ca.uhn.fhir.model.dstu2.resource.Condition setVerificationStatus(ca.uhn.fhir.model.primitive.BoundCodeDt<ca.uhn.fhir.model.dstu2.valueset.ConditionVerificationStatusEnum>);
    Code:
       0: aload_0
       1: aload_1
       2: putfield      #45                 // Field myVerificationStatus:Lca/uhn/fhir/model/primitive/BoundCodeDt;
       5: aload_0
       6: areturn

  public ca.uhn.fhir.model.dstu2.resource.Condition setVerificationStatus(ca.uhn.fhir.model.dstu2.valueset.ConditionVerificationStatusEnum);
    Code:
       0: aload_0
       1: new           #158                // class ca/uhn/fhir/model/primitive/BoundCodeDt
       4: dup
       5: getstatic     #176                // Field ca/uhn/fhir/model/dstu2/valueset/ConditionVerificationStatusEnum.VALUESET_BINDER:Lca/uhn/fhir/model/api/IValueSetEnumBinder;
       8: aload_1
       9: invokespecial #171                // Method ca/uhn/fhir/model/primitive/BoundCodeDt."<init>":(Lca/uhn/fhir/model/api/IValueSetEnumBinder;Ljava/lang/Enum;)V
      12: invokevirtual #182                // Method setVerificationStatus:(Lca/uhn/fhir/model/primitive/BoundCodeDt;)Lca/uhn/fhir/model/dstu2/resource/Condition;
      15: pop
      16: aload_0
      17: areturn

  public ca.uhn.fhir.model.dstu2.composite.CodeableConceptDt getSeverity();
    Code:
       0: aload_0
       1: getfield      #48                 // Field mySeverity:Lca/uhn/fhir/model/dstu2/composite/CodeableConceptDt;
       4: ifnonnull     18
       7: aload_0
       8: new           #137                // class ca/uhn/fhir/model/dstu2/composite/CodeableConceptDt
      11: dup
      12: invokespecial #139                // Method ca/uhn/fhir/model/dstu2/composite/CodeableConceptDt."<init>":()V
      15: putfield      #48                 // Field mySeverity:Lca/uhn/fhir/model/dstu2/composite/CodeableConceptDt;
      18: aload_0
      19: getfield      #48                 // Field mySeverity:Lca/uhn/fhir/model/dstu2/composite/CodeableConceptDt;
      22: areturn

  public ca.uhn.fhir.model.dstu2.resource.Condition setSeverity(ca.uhn.fhir.model.dstu2.composite.CodeableConceptDt);
    Code:
       0: aload_0
       1: aload_1
       2: putfield      #48                 // Field mySeverity:Lca/uhn/fhir/model/dstu2/composite/CodeableConceptDt;
       5: aload_0
       6: areturn

  public ca.uhn.fhir.model.api.IDatatype getOnset();
    Code:
       0: aload_0
       1: getfield      #51                 // Field myOnset:Lca/uhn/fhir/model/api/IDatatype;
       4: areturn

  public ca.uhn.fhir.model.dstu2.resource.Condition setOnset(ca.uhn.fhir.model.api.IDatatype);
    Code:
       0: aload_0
       1: aload_1
       2: putfield      #51                 // Field myOnset:Lca/uhn/fhir/model/api/IDatatype;
       5: aload_0
       6: areturn

  public ca.uhn.fhir.model.api.IDatatype getAbatement();
    Code:
       0: aload_0
       1: getfield      #55                 // Field myAbatement:Lca/uhn/fhir/model/api/IDatatype;
       4: areturn

  public ca.uhn.fhir.model.dstu2.resource.Condition setAbatement(ca.uhn.fhir.model.api.IDatatype);
    Code:
       0: aload_0
       1: aload_1
       2: putfield      #55                 // Field myAbatement:Lca/uhn/fhir/model/api/IDatatype;
       5: aload_0
       6: areturn

  public ca.uhn.fhir.model.dstu2.resource.Condition$Stage getStage();
    Code:
       0: aload_0
       1: getfield      #58                 // Field myStage:Lca/uhn/fhir/model/dstu2/resource/Condition$Stage;
       4: ifnonnull     18
       7: aload_0
       8: new           #185                // class ca/uhn/fhir/model/dstu2/resource/Condition$Stage
      11: dup
      12: invokespecial #187                // Method ca/uhn/fhir/model/dstu2/resource/Condition$Stage."<init>":()V
      15: putfield      #58                 // Field myStage:Lca/uhn/fhir/model/dstu2/resource/Condition$Stage;
      18: aload_0
      19: getfield      #58                 // Field myStage:Lca/uhn/fhir/model/dstu2/resource/Condition$Stage;
      22: areturn

  public ca.uhn.fhir.model.dstu2.resource.Condition setStage(ca.uhn.fhir.model.dstu2.resource.Condition$Stage);
    Code:
       0: aload_0
       1: aload_1
       2: putfield      #58                 // Field myStage:Lca/uhn/fhir/model/dstu2/resource/Condition$Stage;
       5: aload_0
       6: areturn

  public java.util.List<ca.uhn.fhir.model.dstu2.resource.Condition$Evidence> getEvidence();
    Code:
       0: aload_0
       1: getfield      #62                 // Field myEvidence:Ljava/util/List;
       4: ifnonnull     18
       7: aload_0
       8: new           #82                 // class java/util/ArrayList
      11: dup
      12: invokespecial #84                 // Method java/util/ArrayList."<init>":()V
      15: putfield      #62                 // Field myEvidence:Ljava/util/List;
      18: aload_0
      19: getfield      #62                 // Field myEvidence:Ljava/util/List;
      22: areturn

  public ca.uhn.fhir.model.dstu2.resource.Condition setEvidence(java.util.List<ca.uhn.fhir.model.dstu2.resource.Condition$Evidence>);
    Code:
       0: aload_0
       1: aload_1
       2: putfield      #62                 // Field myEvidence:Ljava/util/List;
       5: aload_0
       6: areturn

  public ca.uhn.fhir.model.dstu2.resource.Condition$Evidence addEvidence();
    Code:
       0: new           #188                // class ca/uhn/fhir/model/dstu2/resource/Condition$Evidence
       3: dup
       4: invokespecial #190                // Method ca/uhn/fhir/model/dstu2/resource/Condition$Evidence."<init>":()V
       7: astore_1
       8: aload_0
       9: invokevirtual #191                // Method getEvidence:()Ljava/util/List;
      12: aload_1
      13: invokeinterface #92,  2           // InterfaceMethod java/util/List.add:(Ljava/lang/Object;)Z
      18: pop
      19: aload_1
      20: areturn

  public ca.uhn.fhir.model.dstu2.resource.Condition addEvidence(ca.uhn.fhir.model.dstu2.resource.Condition$Evidence);
    Code:
       0: aload_1
       1: ifnonnull     14
       4: new           #98                 // class java/lang/NullPointerException
       7: dup
       8: ldc           #100                // String theValue must not be null
      10: invokespecial #102                // Method java/lang/NullPointerException."<init>":(Ljava/lang/String;)V
      13: athrow
      14: aload_0
      15: invokevirtual #191                // Method getEvidence:()Ljava/util/List;
      18: aload_1
      19: invokeinterface #92,  2           // InterfaceMethod java/util/List.add:(Ljava/lang/Object;)Z
      24: pop
      25: aload_0
      26: areturn

  public ca.uhn.fhir.model.dstu2.resource.Condition$Evidence getEvidenceFirstRep();
    Code:
       0: aload_0
       1: invokevirtual #191                // Method getEvidence:()Ljava/util/List;
       4: invokeinterface #105,  1          // InterfaceMethod java/util/List.isEmpty:()Z
       9: ifeq          17
      12: aload_0
      13: invokevirtual #194                // Method addEvidence:()Lca/uhn/fhir/model/dstu2/resource/Condition$Evidence;
      16: areturn
      17: aload_0
      18: invokevirtual #191                // Method getEvidence:()Ljava/util/List;
      21: iconst_0
      22: invokeinterface #111,  2          // InterfaceMethod java/util/List.get:(I)Ljava/lang/Object;
      27: checkcast     #188                // class ca/uhn/fhir/model/dstu2/resource/Condition$Evidence
      30: areturn

  public java.util.List<ca.uhn.fhir.model.dstu2.composite.CodeableConceptDt> getBodySite();
    Code:
       0: aload_0
       1: getfield      #65                 // Field myBodySite:Ljava/util/List;
       4: ifnonnull     18
       7: aload_0
       8: new           #82                 // class java/util/ArrayList
      11: dup
      12: invokespecial #84                 // Method java/util/ArrayList."<init>":()V
      15: putfield      #65                 // Field myBodySite:Ljava/util/List;
      18: aload_0
      19: getfield      #65                 // Field myBodySite:Ljava/util/List;
      22: areturn

  public ca.uhn.fhir.model.dstu2.resource.Condition setBodySite(java.util.List<ca.uhn.fhir.model.dstu2.composite.CodeableConceptDt>);
    Code:
       0: aload_0
       1: aload_1
       2: putfield      #65                 // Field myBodySite:Ljava/util/List;
       5: aload_0
       6: areturn

  public ca.uhn.fhir.model.dstu2.composite.CodeableConceptDt addBodySite();
    Code:
       0: new           #137                // class ca/uhn/fhir/model/dstu2/composite/CodeableConceptDt
       3: dup
       4: invokespecial #139                // Method ca/uhn/fhir/model/dstu2/composite/CodeableConceptDt."<init>":()V
       7: astore_1
       8: aload_0
       9: invokevirtual #198                // Method getBodySite:()Ljava/util/List;
      12: aload_1
      13: invokeinterface #92,  2           // InterfaceMethod java/util/List.add:(Ljava/lang/Object;)Z
      18: pop
      19: aload_1
      20: areturn

  public ca.uhn.fhir.model.dstu2.resource.Condition addBodySite(ca.uhn.fhir.model.dstu2.composite.CodeableConceptDt);
    Code:
       0: aload_1
       1: ifnonnull     14
       4: new           #98                 // class java/lang/NullPointerException
       7: dup
       8: ldc           #100                // String theValue must not be null
      10: invokespecial #102                // Method java/lang/NullPointerException."<init>":(Ljava/lang/String;)V
      13: athrow
      14: aload_0
      15: invokevirtual #198                // Method getBodySite:()Ljava/util/List;
      18: aload_1
      19: invokeinterface #92,  2           // InterfaceMethod java/util/List.add:(Ljava/lang/Object;)Z
      24: pop
      25: aload_0
      26: areturn

  public ca.uhn.fhir.model.dstu2.composite.CodeableConceptDt getBodySiteFirstRep();
    Code:
       0: aload_0
       1: invokevirtual #198                // Method getBodySite:()Ljava/util/List;
       4: invokeinterface #105,  1          // InterfaceMethod java/util/List.isEmpty:()Z
       9: ifeq          17
      12: aload_0
      13: invokevirtual #201                // Method addBodySite:()Lca/uhn/fhir/model/dstu2/composite/CodeableConceptDt;
      16: areturn
      17: aload_0
      18: invokevirtual #198                // Method getBodySite:()Ljava/util/List;
      21: iconst_0
      22: invokeinterface #111,  2          // InterfaceMethod java/util/List.get:(I)Ljava/lang/Object;
      27: checkcast     #137                // class ca/uhn/fhir/model/dstu2/composite/CodeableConceptDt
      30: areturn

  public ca.uhn.fhir.model.primitive.StringDt getNotesElement();
    Code:
       0: aload_0
       1: getfield      #68                 // Field myNotes:Lca/uhn/fhir/model/primitive/StringDt;
       4: ifnonnull     18
       7: aload_0
       8: new           #205                // class ca/uhn/fhir/model/primitive/StringDt
      11: dup
      12: invokespecial #207                // Method ca/uhn/fhir/model/primitive/StringDt."<init>":()V
      15: putfield      #68                 // Field myNotes:Lca/uhn/fhir/model/primitive/StringDt;
      18: aload_0
      19: getfield      #68                 // Field myNotes:Lca/uhn/fhir/model/primitive/StringDt;
      22: areturn

  public java.lang.String getNotes();
    Code:
       0: aload_0
       1: invokevirtual #208                // Method getNotesElement:()Lca/uhn/fhir/model/primitive/StringDt;
       4: invokevirtual #212                // Method ca/uhn/fhir/model/primitive/StringDt.getValue:()Ljava/lang/Object;
       7: checkcast     #169                // class java/lang/String
      10: areturn

  public ca.uhn.fhir.model.dstu2.resource.Condition setNotes(ca.uhn.fhir.model.primitive.StringDt);
    Code:
       0: aload_0
       1: aload_1
       2: putfield      #68                 // Field myNotes:Lca/uhn/fhir/model/primitive/StringDt;
       5: aload_0
       6: areturn

  public ca.uhn.fhir.model.dstu2.resource.Condition setNotes(java.lang.String);
    Code:
       0: aload_0
       1: new           #205                // class ca/uhn/fhir/model/primitive/StringDt
       4: dup
       5: aload_1
       6: invokespecial #213                // Method ca/uhn/fhir/model/primitive/StringDt."<init>":(Ljava/lang/String;)V
       9: putfield      #68                 // Field myNotes:Lca/uhn/fhir/model/primitive/StringDt;
      12: aload_0
      13: areturn

  public java.lang.String getResourceName();
    Code:
       0: ldc           #214                // String Condition
       2: areturn

  public ca.uhn.fhir.context.FhirVersionEnum getStructureFhirVersionEnum();
    Code:
       0: getstatic     #216                // Field ca/uhn/fhir/context/FhirVersionEnum.DSTU2:Lca/uhn/fhir/context/FhirVersionEnum;
       3: areturn

  static {};
    Code:
       0: new           #222                // class ca/uhn/fhir/rest/gclient/TokenClientParam
       3: dup
       4: ldc           #224                // String code
       6: invokespecial #226                // Method ca/uhn/fhir/rest/gclient/TokenClientParam."<init>":(Ljava/lang/String;)V
       9: putstatic     #227                // Field CODE:Lca/uhn/fhir/rest/gclient/TokenClientParam;
      12: new           #222                // class ca/uhn/fhir/rest/gclient/TokenClientParam
      15: dup
      16: ldc           #231                // String identifier
      18: invokespecial #226                // Method ca/uhn/fhir/rest/gclient/TokenClientParam."<init>":(Ljava/lang/String;)V
      21: putstatic     #233                // Field IDENTIFIER:Lca/uhn/fhir/rest/gclient/TokenClientParam;
      24: new           #222                // class ca/uhn/fhir/rest/gclient/TokenClientParam
      27: dup
      28: ldc           #236                // String clinicalstatus
      30: invokespecial #226                // Method ca/uhn/fhir/rest/gclient/TokenClientParam."<init>":(Ljava/lang/String;)V
      33: putstatic     #238                // Field CLINICALSTATUS:Lca/uhn/fhir/rest/gclient/TokenClientParam;
      36: new           #222                // class ca/uhn/fhir/rest/gclient/TokenClientParam
      39: dup
      40: ldc           #241                // String severity
      42: invokespecial #226                // Method ca/uhn/fhir/rest/gclient/TokenClientParam."<init>":(Ljava/lang/String;)V
      45: putstatic     #243                // Field SEVERITY:Lca/uhn/fhir/rest/gclient/TokenClientParam;
      48: new           #222                // class ca/uhn/fhir/rest/gclient/TokenClientParam
      51: dup
      52: ldc           #246                // String category
      54: invokespecial #226                // Method ca/uhn/fhir/rest/gclient/TokenClientParam."<init>":(Ljava/lang/String;)V
      57: putstatic     #248                // Field CATEGORY:Lca/uhn/fhir/rest/gclient/TokenClientParam;
      60: new           #251                // class ca/uhn/fhir/rest/gclient/DateClientParam
      63: dup
      64: ldc           #253                // String onset
      66: invokespecial #255                // Method ca/uhn/fhir/rest/gclient/DateClientParam."<init>":(Ljava/lang/String;)V
      69: putstatic     #256                // Field ONSET:Lca/uhn/fhir/rest/gclient/DateClientParam;
      72: new           #260                // class ca/uhn/fhir/rest/gclient/StringClientParam
      75: dup
      76: ldc_w         #262                // String onset-info
      79: invokespecial #264                // Method ca/uhn/fhir/rest/gclient/StringClientParam."<init>":(Ljava/lang/String;)V
      82: putstatic     #265                // Field ONSET_INFO:Lca/uhn/fhir/rest/gclient/StringClientParam;
      85: new           #269                // class ca/uhn/fhir/rest/gclient/ReferenceClientParam
      88: dup
      89: ldc_w         #271                // String encounter
      92: invokespecial #273                // Method ca/uhn/fhir/rest/gclient/ReferenceClientParam."<init>":(Ljava/lang/String;)V
      95: putstatic     #274                // Field ENCOUNTER:Lca/uhn/fhir/rest/gclient/ReferenceClientParam;
      98: new           #269                // class ca/uhn/fhir/rest/gclient/ReferenceClientParam
     101: dup
     102: ldc_w         #278                // String asserter
     105: invokespecial #273                // Method ca/uhn/fhir/rest/gclient/ReferenceClientParam."<init>":(Ljava/lang/String;)V
     108: putstatic     #280                // Field ASSERTER:Lca/uhn/fhir/rest/gclient/ReferenceClientParam;
     111: new           #251                // class ca/uhn/fhir/rest/gclient/DateClientParam
     114: dup
     115: ldc_w         #283                // String date-recorded
     118: invokespecial #255                // Method ca/uhn/fhir/rest/gclient/DateClientParam."<init>":(Ljava/lang/String;)V
     121: putstatic     #285                // Field DATE_RECORDED:Lca/uhn/fhir/rest/gclient/DateClientParam;
     124: new           #222                // class ca/uhn/fhir/rest/gclient/TokenClientParam
     127: dup
     128: ldc_w         #288                // String evidence
     131: invokespecial #226                // Method ca/uhn/fhir/rest/gclient/TokenClientParam."<init>":(Ljava/lang/String;)V
     134: putstatic     #290                // Field EVIDENCE:Lca/uhn/fhir/rest/gclient/TokenClientParam;
     137: new           #222                // class ca/uhn/fhir/rest/gclient/TokenClientParam
     140: dup
     141: ldc_w         #293                // String body-site
     144: invokespecial #226                // Method ca/uhn/fhir/rest/gclient/TokenClientParam."<init>":(Ljava/lang/String;)V
     147: putstatic     #295                // Field BODY_SITE:Lca/uhn/fhir/rest/gclient/TokenClientParam;
     150: new           #222                // class ca/uhn/fhir/rest/gclient/TokenClientParam
     153: dup
     154: ldc_w         #298                // String stage
     157: invokespecial #226                // Method ca/uhn/fhir/rest/gclient/TokenClientParam."<init>":(Ljava/lang/String;)V
     160: putstatic     #300                // Field STAGE:Lca/uhn/fhir/rest/gclient/TokenClientParam;
     163: new           #269                // class ca/uhn/fhir/rest/gclient/ReferenceClientParam
     166: dup
     167: ldc_w         #303                // String patient
     170: invokespecial #273                // Method ca/uhn/fhir/rest/gclient/ReferenceClientParam."<init>":(Ljava/lang/String;)V
     173: putstatic     #305                // Field PATIENT:Lca/uhn/fhir/rest/gclient/ReferenceClientParam;
     176: new           #308                // class ca/uhn/fhir/model/api/Include
     179: dup
     180: ldc_w         #310                // String Condition:asserter
     183: invokespecial #312                // Method ca/uhn/fhir/model/api/Include."<init>":(Ljava/lang/String;)V
     186: putstatic     #313                // Field INCLUDE_ASSERTER:Lca/uhn/fhir/model/api/Include;
     189: new           #308                // class ca/uhn/fhir/model/api/Include
     192: dup
     193: ldc_w         #317                // String Condition:encounter
     196: invokespecial #312                // Method ca/uhn/fhir/model/api/Include."<init>":(Ljava/lang/String;)V
     199: putstatic     #319                // Field INCLUDE_ENCOUNTER:Lca/uhn/fhir/model/api/Include;
     202: new           #308                // class ca/uhn/fhir/model/api/Include
     205: dup
     206: ldc_w         #322                // String Condition:patient
     209: invokespecial #312                // Method ca/uhn/fhir/model/api/Include."<init>":(Ljava/lang/String;)V
     212: putstatic     #324                // Field INCLUDE_PATIENT:Lca/uhn/fhir/model/api/Include;
     215: return
}
