Compiled from "DeviceComponent.java"
public class ca.uhn.fhir.model.dstu2.resource.DeviceComponent extends ca.uhn.fhir.model.dstu2.resource.BaseResource implements ca.uhn.fhir.model.api.IResource {
  public static final java.lang.String SP_PARENT;

  public static final ca.uhn.fhir.rest.gclient.ReferenceClientParam PARENT;

  public static final java.lang.String SP_TYPE;

  public static final ca.uhn.fhir.rest.gclient.TokenClientParam TYPE;

  public static final java.lang.String SP_SOURCE;

  public static final ca.uhn.fhir.rest.gclient.ReferenceClientParam SOURCE;

  public static final ca.uhn.fhir.model.api.Include INCLUDE_PARENT;

  public static final ca.uhn.fhir.model.api.Include INCLUDE_SOURCE;

  private ca.uhn.fhir.model.dstu2.composite.CodeableConceptDt myType;

  private ca.uhn.fhir.model.dstu2.composite.IdentifierDt myIdentifier;

  private ca.uhn.fhir.model.primitive.InstantDt myLastSystemChange;

  private ca.uhn.fhir.model.dstu2.composite.ResourceReferenceDt mySource;

  private ca.uhn.fhir.model.dstu2.composite.ResourceReferenceDt myParent;

  private java.util.List<ca.uhn.fhir.model.dstu2.composite.CodeableConceptDt> myOperationalStatus;

  private ca.uhn.fhir.model.dstu2.composite.CodeableConceptDt myParameterGroup;

  private ca.uhn.fhir.model.primitive.BoundCodeDt<ca.uhn.fhir.model.dstu2.valueset.MeasmntPrincipleEnum> myMeasurementPrinciple;

  private java.util.List<ca.uhn.fhir.model.dstu2.resource.DeviceComponent$ProductionSpecification> myProductionSpecification;

  private ca.uhn.fhir.model.dstu2.composite.CodeableConceptDt myLanguageCode;

  public ca.uhn.fhir.model.dstu2.resource.DeviceComponent();
    Code:
       0: aload_0
       1: invokespecial #1                  // Method ca/uhn/fhir/model/dstu2/resource/BaseResource."<init>":()V
       4: return

  public boolean isEmpty();
    Code:
       0: aload_0
       1: invokespecial #7                  // Method ca/uhn/fhir/model/dstu2/resource/BaseResource.isBaseEmpty:()Z
       4: ifeq          96
       7: bipush        10
       9: anewarray     #11                 // class java/lang/Object
      12: dup
      13: iconst_0
      14: aload_0
      15: getfield      #13                 // Field myType:Lca/uhn/fhir/model/dstu2/composite/CodeableConceptDt;
      18: aastore
      19: dup
      20: iconst_1
      21: aload_0
      22: getfield      #19                 // Field myIdentifier:Lca/uhn/fhir/model/dstu2/composite/IdentifierDt;
      25: aastore
      26: dup
      27: iconst_2
      28: aload_0
      29: getfield      #23                 // Field myLastSystemChange:Lca/uhn/fhir/model/primitive/InstantDt;
      32: aastore
      33: dup
      34: iconst_3
      35: aload_0
      36: getfield      #27                 // Field mySource:Lca/uhn/fhir/model/dstu2/composite/ResourceReferenceDt;
      39: aastore
      40: dup
      41: iconst_4
      42: aload_0
      43: getfield      #31                 // Field myParent:Lca/uhn/fhir/model/dstu2/composite/ResourceReferenceDt;
      46: aastore
      47: dup
      48: iconst_5
      49: aload_0
      50: getfield      #34                 // Field myOperationalStatus:Ljava/util/List;
      53: aastore
      54: dup
      55: bipush        6
      57: aload_0
      58: getfield      #38                 // Field myParameterGroup:Lca/uhn/fhir/model/dstu2/composite/CodeableConceptDt;
      61: aastore
      62: dup
      63: bipush        7
      65: aload_0
      66: getfield      #41                 // Field myMeasurementPrinciple:Lca/uhn/fhir/model/primitive/BoundCodeDt;
      69: aastore
      70: dup
      71: bipush        8
      73: aload_0
      74: getfield      #45                 // Field myProductionSpecification:Ljava/util/List;
      77: aastore
      78: dup
      79: bipush        9
      81: aload_0
      82: getfield      #48                 // Field myLanguageCode:Lca/uhn/fhir/model/dstu2/composite/CodeableConceptDt;
      85: aastore
      86: invokestatic  #51                 // Method ca/uhn/fhir/util/ElementUtil.isEmpty:([Ljava/lang/Object;)Z
      89: ifeq          96
      92: iconst_1
      93: goto          97
      96: iconst_0
      97: ireturn

  public <T extends ca.uhn.fhir.model.api.IElement> java.util.List<T> getAllPopulatedChildElementsOfType(java.lang.Class<T>);
    Code:
       0: aload_1
       1: bipush        10
       3: anewarray     #11                 // class java/lang/Object
       6: dup
       7: iconst_0
       8: aload_0
       9: getfield      #13                 // Field myType:Lca/uhn/fhir/model/dstu2/composite/CodeableConceptDt;
      12: aastore
      13: dup
      14: iconst_1
      15: aload_0
      16: getfield      #19                 // Field myIdentifier:Lca/uhn/fhir/model/dstu2/composite/IdentifierDt;
      19: aastore
      20: dup
      21: iconst_2
      22: aload_0
      23: getfield      #23                 // Field myLastSystemChange:Lca/uhn/fhir/model/primitive/InstantDt;
      26: aastore
      27: dup
      28: iconst_3
      29: aload_0
      30: getfield      #27                 // Field mySource:Lca/uhn/fhir/model/dstu2/composite/ResourceReferenceDt;
      33: aastore
      34: dup
      35: iconst_4
      36: aload_0
      37: getfield      #31                 // Field myParent:Lca/uhn/fhir/model/dstu2/composite/ResourceReferenceDt;
      40: aastore
      41: dup
      42: iconst_5
      43: aload_0
      44: getfield      #34                 // Field myOperationalStatus:Ljava/util/List;
      47: aastore
      48: dup
      49: bipush        6
      51: aload_0
      52: getfield      #38                 // Field myParameterGroup:Lca/uhn/fhir/model/dstu2/composite/CodeableConceptDt;
      55: aastore
      56: dup
      57: bipush        7
      59: aload_0
      60: getfield      #41                 // Field myMeasurementPrinciple:Lca/uhn/fhir/model/primitive/BoundCodeDt;
      63: aastore
      64: dup
      65: bipush        8
      67: aload_0
      68: getfield      #45                 // Field myProductionSpecification:Ljava/util/List;
      71: aastore
      72: dup
      73: bipush        9
      75: aload_0
      76: getfield      #48                 // Field myLanguageCode:Lca/uhn/fhir/model/dstu2/composite/CodeableConceptDt;
      79: aastore
      80: invokestatic  #57                 // Method ca/uhn/fhir/util/ElementUtil.allPopulatedChildElements:(Ljava/lang/Class;[Ljava/lang/Object;)Ljava/util/List;
      83: areturn

  public ca.uhn.fhir.model.dstu2.composite.CodeableConceptDt getType();
    Code:
       0: aload_0
       1: getfield      #13                 // Field myType:Lca/uhn/fhir/model/dstu2/composite/CodeableConceptDt;
       4: ifnonnull     18
       7: aload_0
       8: new           #61                 // class ca/uhn/fhir/model/dstu2/composite/CodeableConceptDt
      11: dup
      12: invokespecial #63                 // Method ca/uhn/fhir/model/dstu2/composite/CodeableConceptDt."<init>":()V
      15: putfield      #13                 // Field myType:Lca/uhn/fhir/model/dstu2/composite/CodeableConceptDt;
      18: aload_0
      19: getfield      #13                 // Field myType:Lca/uhn/fhir/model/dstu2/composite/CodeableConceptDt;
      22: areturn

  public ca.uhn.fhir.model.dstu2.resource.DeviceComponent setType(ca.uhn.fhir.model.dstu2.composite.CodeableConceptDt);
    Code:
       0: aload_0
       1: aload_1
       2: putfield      #13                 // Field myType:Lca/uhn/fhir/model/dstu2/composite/CodeableConceptDt;
       5: aload_0
       6: areturn

  public ca.uhn.fhir.model.dstu2.composite.IdentifierDt getIdentifier();
    Code:
       0: aload_0
       1: getfield      #19                 // Field myIdentifier:Lca/uhn/fhir/model/dstu2/composite/IdentifierDt;
       4: ifnonnull     18
       7: aload_0
       8: new           #64                 // class ca/uhn/fhir/model/dstu2/composite/IdentifierDt
      11: dup
      12: invokespecial #66                 // Method ca/uhn/fhir/model/dstu2/composite/IdentifierDt."<init>":()V
      15: putfield      #19                 // Field myIdentifier:Lca/uhn/fhir/model/dstu2/composite/IdentifierDt;
      18: aload_0
      19: getfield      #19                 // Field myIdentifier:Lca/uhn/fhir/model/dstu2/composite/IdentifierDt;
      22: areturn

  public ca.uhn.fhir.model.dstu2.resource.DeviceComponent setIdentifier(ca.uhn.fhir.model.dstu2.composite.IdentifierDt);
    Code:
       0: aload_0
       1: aload_1
       2: putfield      #19                 // Field myIdentifier:Lca/uhn/fhir/model/dstu2/composite/IdentifierDt;
       5: aload_0
       6: areturn

  public ca.uhn.fhir.model.primitive.InstantDt getLastSystemChangeElement();
    Code:
       0: aload_0
       1: getfield      #23                 // Field myLastSystemChange:Lca/uhn/fhir/model/primitive/InstantDt;
       4: ifnonnull     18
       7: aload_0
       8: new           #67                 // class ca/uhn/fhir/model/primitive/InstantDt
      11: dup
      12: invokespecial #69                 // Method ca/uhn/fhir/model/primitive/InstantDt."<init>":()V
      15: putfield      #23                 // Field myLastSystemChange:Lca/uhn/fhir/model/primitive/InstantDt;
      18: aload_0
      19: getfield      #23                 // Field myLastSystemChange:Lca/uhn/fhir/model/primitive/InstantDt;
      22: areturn

  public java.util.Date getLastSystemChange();
    Code:
       0: aload_0
       1: invokevirtual #70                 // Method getLastSystemChangeElement:()Lca/uhn/fhir/model/primitive/InstantDt;
       4: invokevirtual #74                 // Method ca/uhn/fhir/model/primitive/InstantDt.getValue:()Ljava/lang/Object;
       7: checkcast     #78                 // class java/util/Date
      10: areturn

  public ca.uhn.fhir.model.dstu2.resource.DeviceComponent setLastSystemChange(ca.uhn.fhir.model.primitive.InstantDt);
    Code:
       0: aload_0
       1: aload_1
       2: putfield      #23                 // Field myLastSystemChange:Lca/uhn/fhir/model/primitive/InstantDt;
       5: aload_0
       6: areturn

  public ca.uhn.fhir.model.dstu2.resource.DeviceComponent setLastSystemChangeWithMillisPrecision(java.util.Date);
    Code:
       0: aload_0
       1: new           #67                 // class ca/uhn/fhir/model/primitive/InstantDt
       4: dup
       5: aload_1
       6: invokespecial #80                 // Method ca/uhn/fhir/model/primitive/InstantDt."<init>":(Ljava/util/Date;)V
       9: putfield      #23                 // Field myLastSystemChange:Lca/uhn/fhir/model/primitive/InstantDt;
      12: aload_0
      13: areturn

  public ca.uhn.fhir.model.dstu2.resource.DeviceComponent setLastSystemChange(java.util.Date, ca.uhn.fhir.model.api.TemporalPrecisionEnum);
    Code:
       0: aload_0
       1: new           #67                 // class ca/uhn/fhir/model/primitive/InstantDt
       4: dup
       5: aload_1
       6: aload_2
       7: invokespecial #83                 // Method ca/uhn/fhir/model/primitive/InstantDt."<init>":(Ljava/util/Date;Lca/uhn/fhir/model/api/TemporalPrecisionEnum;)V
      10: putfield      #23                 // Field myLastSystemChange:Lca/uhn/fhir/model/primitive/InstantDt;
      13: aload_0
      14: areturn

  public ca.uhn.fhir.model.dstu2.composite.ResourceReferenceDt getSource();
    Code:
       0: aload_0
       1: getfield      #27                 // Field mySource:Lca/uhn/fhir/model/dstu2/composite/ResourceReferenceDt;
       4: ifnonnull     18
       7: aload_0
       8: new           #86                 // class ca/uhn/fhir/model/dstu2/composite/ResourceReferenceDt
      11: dup
      12: invokespecial #88                 // Method ca/uhn/fhir/model/dstu2/composite/ResourceReferenceDt."<init>":()V
      15: putfield      #27                 // Field mySource:Lca/uhn/fhir/model/dstu2/composite/ResourceReferenceDt;
      18: aload_0
      19: getfield      #27                 // Field mySource:Lca/uhn/fhir/model/dstu2/composite/ResourceReferenceDt;
      22: areturn

  public ca.uhn.fhir.model.dstu2.resource.DeviceComponent setSource(ca.uhn.fhir.model.dstu2.composite.ResourceReferenceDt);
    Code:
       0: aload_0
       1: aload_1
       2: putfield      #27                 // Field mySource:Lca/uhn/fhir/model/dstu2/composite/ResourceReferenceDt;
       5: aload_0
       6: areturn

  public ca.uhn.fhir.model.dstu2.composite.ResourceReferenceDt getParent();
    Code:
       0: aload_0
       1: getfield      #31                 // Field myParent:Lca/uhn/fhir/model/dstu2/composite/ResourceReferenceDt;
       4: ifnonnull     18
       7: aload_0
       8: new           #86                 // class ca/uhn/fhir/model/dstu2/composite/ResourceReferenceDt
      11: dup
      12: invokespecial #88                 // Method ca/uhn/fhir/model/dstu2/composite/ResourceReferenceDt."<init>":()V
      15: putfield      #31                 // Field myParent:Lca/uhn/fhir/model/dstu2/composite/ResourceReferenceDt;
      18: aload_0
      19: getfield      #31                 // Field myParent:Lca/uhn/fhir/model/dstu2/composite/ResourceReferenceDt;
      22: areturn

  public ca.uhn.fhir.model.dstu2.resource.DeviceComponent setParent(ca.uhn.fhir.model.dstu2.composite.ResourceReferenceDt);
    Code:
       0: aload_0
       1: aload_1
       2: putfield      #31                 // Field myParent:Lca/uhn/fhir/model/dstu2/composite/ResourceReferenceDt;
       5: aload_0
       6: areturn

  public java.util.List<ca.uhn.fhir.model.dstu2.composite.CodeableConceptDt> getOperationalStatus();
    Code:
       0: aload_0
       1: getfield      #34                 // Field myOperationalStatus:Ljava/util/List;
       4: ifnonnull     18
       7: aload_0
       8: new           #89                 // class java/util/ArrayList
      11: dup
      12: invokespecial #91                 // Method java/util/ArrayList."<init>":()V
      15: putfield      #34                 // Field myOperationalStatus:Ljava/util/List;
      18: aload_0
      19: getfield      #34                 // Field myOperationalStatus:Ljava/util/List;
      22: areturn

  public ca.uhn.fhir.model.dstu2.resource.DeviceComponent setOperationalStatus(java.util.List<ca.uhn.fhir.model.dstu2.composite.CodeableConceptDt>);
    Code:
       0: aload_0
       1: aload_1
       2: putfield      #34                 // Field myOperationalStatus:Ljava/util/List;
       5: aload_0
       6: areturn

  public ca.uhn.fhir.model.dstu2.composite.CodeableConceptDt addOperationalStatus();
    Code:
       0: new           #61                 // class ca/uhn/fhir/model/dstu2/composite/CodeableConceptDt
       3: dup
       4: invokespecial #63                 // Method ca/uhn/fhir/model/dstu2/composite/CodeableConceptDt."<init>":()V
       7: astore_1
       8: aload_0
       9: invokevirtual #92                 // Method getOperationalStatus:()Ljava/util/List;
      12: aload_1
      13: invokeinterface #96,  2           // InterfaceMethod java/util/List.add:(Ljava/lang/Object;)Z
      18: pop
      19: aload_1
      20: areturn

  public ca.uhn.fhir.model.dstu2.resource.DeviceComponent addOperationalStatus(ca.uhn.fhir.model.dstu2.composite.CodeableConceptDt);
    Code:
       0: aload_1
       1: ifnonnull     14
       4: new           #102                // class java/lang/NullPointerException
       7: dup
       8: ldc           #104                // String theValue must not be null
      10: invokespecial #106                // Method java/lang/NullPointerException."<init>":(Ljava/lang/String;)V
      13: athrow
      14: aload_0
      15: invokevirtual #92                 // Method getOperationalStatus:()Ljava/util/List;
      18: aload_1
      19: invokeinterface #96,  2           // InterfaceMethod java/util/List.add:(Ljava/lang/Object;)Z
      24: pop
      25: aload_0
      26: areturn

  public ca.uhn.fhir.model.dstu2.composite.CodeableConceptDt getOperationalStatusFirstRep();
    Code:
       0: aload_0
       1: invokevirtual #92                 // Method getOperationalStatus:()Ljava/util/List;
       4: invokeinterface #109,  1          // InterfaceMethod java/util/List.isEmpty:()Z
       9: ifeq          17
      12: aload_0
      13: invokevirtual #111                // Method addOperationalStatus:()Lca/uhn/fhir/model/dstu2/composite/CodeableConceptDt;
      16: areturn
      17: aload_0
      18: invokevirtual #92                 // Method getOperationalStatus:()Ljava/util/List;
      21: iconst_0
      22: invokeinterface #115,  2          // InterfaceMethod java/util/List.get:(I)Ljava/lang/Object;
      27: checkcast     #61                 // class ca/uhn/fhir/model/dstu2/composite/CodeableConceptDt
      30: areturn

  public ca.uhn.fhir.model.dstu2.composite.CodeableConceptDt getParameterGroup();
    Code:
       0: aload_0
       1: getfield      #38                 // Field myParameterGroup:Lca/uhn/fhir/model/dstu2/composite/CodeableConceptDt;
       4: ifnonnull     18
       7: aload_0
       8: new           #61                 // class ca/uhn/fhir/model/dstu2/composite/CodeableConceptDt
      11: dup
      12: invokespecial #63                 // Method ca/uhn/fhir/model/dstu2/composite/CodeableConceptDt."<init>":()V
      15: putfield      #38                 // Field myParameterGroup:Lca/uhn/fhir/model/dstu2/composite/CodeableConceptDt;
      18: aload_0
      19: getfield      #38                 // Field myParameterGroup:Lca/uhn/fhir/model/dstu2/composite/CodeableConceptDt;
      22: areturn

  public ca.uhn.fhir.model.dstu2.resource.DeviceComponent setParameterGroup(ca.uhn.fhir.model.dstu2.composite.CodeableConceptDt);
    Code:
       0: aload_0
       1: aload_1
       2: putfield      #38                 // Field myParameterGroup:Lca/uhn/fhir/model/dstu2/composite/CodeableConceptDt;
       5: aload_0
       6: areturn

  public ca.uhn.fhir.model.primitive.BoundCodeDt<ca.uhn.fhir.model.dstu2.valueset.MeasmntPrincipleEnum> getMeasurementPrincipleElement();
    Code:
       0: aload_0
       1: getfield      #41                 // Field myMeasurementPrinciple:Lca/uhn/fhir/model/primitive/BoundCodeDt;
       4: ifnonnull     21
       7: aload_0
       8: new           #119                // class ca/uhn/fhir/model/primitive/BoundCodeDt
      11: dup
      12: getstatic     #121                // Field ca/uhn/fhir/model/dstu2/valueset/MeasmntPrincipleEnum.VALUESET_BINDER:Lca/uhn/fhir/model/api/IValueSetEnumBinder;
      15: invokespecial #127                // Method ca/uhn/fhir/model/primitive/BoundCodeDt."<init>":(Lca/uhn/fhir/model/api/IValueSetEnumBinder;)V
      18: putfield      #41                 // Field myMeasurementPrinciple:Lca/uhn/fhir/model/primitive/BoundCodeDt;
      21: aload_0
      22: getfield      #41                 // Field myMeasurementPrinciple:Lca/uhn/fhir/model/primitive/BoundCodeDt;
      25: areturn

  public java.lang.String getMeasurementPrinciple();
    Code:
       0: aload_0
       1: invokevirtual #130                // Method getMeasurementPrincipleElement:()Lca/uhn/fhir/model/primitive/BoundCodeDt;
       4: invokevirtual #134                // Method ca/uhn/fhir/model/primitive/BoundCodeDt.getValue:()Ljava/lang/Object;
       7: checkcast     #135                // class java/lang/String
      10: areturn

  public ca.uhn.fhir.model.dstu2.resource.DeviceComponent setMeasurementPrinciple(ca.uhn.fhir.model.primitive.BoundCodeDt<ca.uhn.fhir.model.dstu2.valueset.MeasmntPrincipleEnum>);
    Code:
       0: aload_0
       1: aload_1
       2: putfield      #41                 // Field myMeasurementPrinciple:Lca/uhn/fhir/model/primitive/BoundCodeDt;
       5: aload_0
       6: areturn

  public ca.uhn.fhir.model.dstu2.resource.DeviceComponent setMeasurementPrinciple(ca.uhn.fhir.model.dstu2.valueset.MeasmntPrincipleEnum);
    Code:
       0: aload_0
       1: new           #119                // class ca/uhn/fhir/model/primitive/BoundCodeDt
       4: dup
       5: getstatic     #121                // Field ca/uhn/fhir/model/dstu2/valueset/MeasmntPrincipleEnum.VALUESET_BINDER:Lca/uhn/fhir/model/api/IValueSetEnumBinder;
       8: aload_1
       9: invokespecial #137                // Method ca/uhn/fhir/model/primitive/BoundCodeDt."<init>":(Lca/uhn/fhir/model/api/IValueSetEnumBinder;Ljava/lang/Enum;)V
      12: invokevirtual #140                // Method setMeasurementPrinciple:(Lca/uhn/fhir/model/primitive/BoundCodeDt;)Lca/uhn/fhir/model/dstu2/resource/DeviceComponent;
      15: pop
      16: aload_0
      17: areturn

  public java.util.List<ca.uhn.fhir.model.dstu2.resource.DeviceComponent$ProductionSpecification> getProductionSpecification();
    Code:
       0: aload_0
       1: getfield      #45                 // Field myProductionSpecification:Ljava/util/List;
       4: ifnonnull     18
       7: aload_0
       8: new           #89                 // class java/util/ArrayList
      11: dup
      12: invokespecial #91                 // Method java/util/ArrayList."<init>":()V
      15: putfield      #45                 // Field myProductionSpecification:Ljava/util/List;
      18: aload_0
      19: getfield      #45                 // Field myProductionSpecification:Ljava/util/List;
      22: areturn

  public ca.uhn.fhir.model.dstu2.resource.DeviceComponent setProductionSpecification(java.util.List<ca.uhn.fhir.model.dstu2.resource.DeviceComponent$ProductionSpecification>);
    Code:
       0: aload_0
       1: aload_1
       2: putfield      #45                 // Field myProductionSpecification:Ljava/util/List;
       5: aload_0
       6: areturn

  public ca.uhn.fhir.model.dstu2.resource.DeviceComponent$ProductionSpecification addProductionSpecification();
    Code:
       0: new           #144                // class ca/uhn/fhir/model/dstu2/resource/DeviceComponent$ProductionSpecification
       3: dup
       4: invokespecial #146                // Method ca/uhn/fhir/model/dstu2/resource/DeviceComponent$ProductionSpecification."<init>":()V
       7: astore_1
       8: aload_0
       9: invokevirtual #147                // Method getProductionSpecification:()Ljava/util/List;
      12: aload_1
      13: invokeinterface #96,  2           // InterfaceMethod java/util/List.add:(Ljava/lang/Object;)Z
      18: pop
      19: aload_1
      20: areturn

  public ca.uhn.fhir.model.dstu2.resource.DeviceComponent addProductionSpecification(ca.uhn.fhir.model.dstu2.resource.DeviceComponent$ProductionSpecification);
    Code:
       0: aload_1
       1: ifnonnull     14
       4: new           #102                // class java/lang/NullPointerException
       7: dup
       8: ldc           #104                // String theValue must not be null
      10: invokespecial #106                // Method java/lang/NullPointerException."<init>":(Ljava/lang/String;)V
      13: athrow
      14: aload_0
      15: invokevirtual #147                // Method getProductionSpecification:()Ljava/util/List;
      18: aload_1
      19: invokeinterface #96,  2           // InterfaceMethod java/util/List.add:(Ljava/lang/Object;)Z
      24: pop
      25: aload_0
      26: areturn

  public ca.uhn.fhir.model.dstu2.resource.DeviceComponent$ProductionSpecification getProductionSpecificationFirstRep();
    Code:
       0: aload_0
       1: invokevirtual #147                // Method getProductionSpecification:()Ljava/util/List;
       4: invokeinterface #109,  1          // InterfaceMethod java/util/List.isEmpty:()Z
       9: ifeq          17
      12: aload_0
      13: invokevirtual #150                // Method addProductionSpecification:()Lca/uhn/fhir/model/dstu2/resource/DeviceComponent$ProductionSpecification;
      16: areturn
      17: aload_0
      18: invokevirtual #147                // Method getProductionSpecification:()Ljava/util/List;
      21: iconst_0
      22: invokeinterface #115,  2          // InterfaceMethod java/util/List.get:(I)Ljava/lang/Object;
      27: checkcast     #144                // class ca/uhn/fhir/model/dstu2/resource/DeviceComponent$ProductionSpecification
      30: areturn

  public ca.uhn.fhir.model.dstu2.composite.CodeableConceptDt getLanguageCode();
    Code:
       0: aload_0
       1: getfield      #48                 // Field myLanguageCode:Lca/uhn/fhir/model/dstu2/composite/CodeableConceptDt;
       4: ifnonnull     18
       7: aload_0
       8: new           #61                 // class ca/uhn/fhir/model/dstu2/composite/CodeableConceptDt
      11: dup
      12: invokespecial #63                 // Method ca/uhn/fhir/model/dstu2/composite/CodeableConceptDt."<init>":()V
      15: putfield      #48                 // Field myLanguageCode:Lca/uhn/fhir/model/dstu2/composite/CodeableConceptDt;
      18: aload_0
      19: getfield      #48                 // Field myLanguageCode:Lca/uhn/fhir/model/dstu2/composite/CodeableConceptDt;
      22: areturn

  public ca.uhn.fhir.model.dstu2.resource.DeviceComponent setLanguageCode(ca.uhn.fhir.model.dstu2.composite.CodeableConceptDt);
    Code:
       0: aload_0
       1: aload_1
       2: putfield      #48                 // Field myLanguageCode:Lca/uhn/fhir/model/dstu2/composite/CodeableConceptDt;
       5: aload_0
       6: areturn

  public java.lang.String getResourceName();
    Code:
       0: ldc           #154                // String DeviceComponent
       2: areturn

  public ca.uhn.fhir.context.FhirVersionEnum getStructureFhirVersionEnum();
    Code:
       0: getstatic     #156                // Field ca/uhn/fhir/context/FhirVersionEnum.DSTU2:Lca/uhn/fhir/context/FhirVersionEnum;
       3: areturn

  static {};
    Code:
       0: new           #162                // class ca/uhn/fhir/rest/gclient/ReferenceClientParam
       3: dup
       4: ldc           #164                // String parent
       6: invokespecial #166                // Method ca/uhn/fhir/rest/gclient/ReferenceClientParam."<init>":(Ljava/lang/String;)V
       9: putstatic     #167                // Field PARENT:Lca/uhn/fhir/rest/gclient/ReferenceClientParam;
      12: new           #171                // class ca/uhn/fhir/rest/gclient/TokenClientParam
      15: dup
      16: ldc           #173                // String type
      18: invokespecial #175                // Method ca/uhn/fhir/rest/gclient/TokenClientParam."<init>":(Ljava/lang/String;)V
      21: putstatic     #176                // Field TYPE:Lca/uhn/fhir/rest/gclient/TokenClientParam;
      24: new           #162                // class ca/uhn/fhir/rest/gclient/ReferenceClientParam
      27: dup
      28: ldc           #180                // String source
      30: invokespecial #166                // Method ca/uhn/fhir/rest/gclient/ReferenceClientParam."<init>":(Ljava/lang/String;)V
      33: putstatic     #182                // Field SOURCE:Lca/uhn/fhir/rest/gclient/ReferenceClientParam;
      36: new           #185                // class ca/uhn/fhir/model/api/Include
      39: dup
      40: ldc           #187                // String DeviceComponent:parent
      42: invokespecial #189                // Method ca/uhn/fhir/model/api/Include."<init>":(Ljava/lang/String;)V
      45: putstatic     #190                // Field INCLUDE_PARENT:Lca/uhn/fhir/model/api/Include;
      48: new           #185                // class ca/uhn/fhir/model/api/Include
      51: dup
      52: ldc           #194                // String DeviceComponent:source
      54: invokespecial #189                // Method ca/uhn/fhir/model/api/Include."<init>":(Ljava/lang/String;)V
      57: putstatic     #196                // Field INCLUDE_SOURCE:Lca/uhn/fhir/model/api/Include;
      60: return
}
