Compiled from "Group.java"
public class ca.uhn.fhir.model.dstu2.resource.Group$Characteristic extends ca.uhn.fhir.model.api.BaseIdentifiableElement implements ca.uhn.fhir.model.api.IResourceBlock {
  private ca.uhn.fhir.model.dstu2.composite.CodeableConceptDt myCode;

  private ca.uhn.fhir.model.api.IDatatype myValue;

  private ca.uhn.fhir.model.primitive.BooleanDt myExclude;

  private ca.uhn.fhir.model.dstu2.composite.PeriodDt myPeriod;

  public ca.uhn.fhir.model.dstu2.resource.Group$Characteristic();
    Code:
       0: aload_0
       1: invokespecial #1                  // Method ca/uhn/fhir/model/api/BaseIdentifiableElement."<init>":()V
       4: return

  public boolean isEmpty();
    Code:
       0: aload_0
       1: invokespecial #7                  // Method ca/uhn/fhir/model/api/BaseIdentifiableElement.isBaseEmpty:()Z
       4: ifeq          49
       7: iconst_4
       8: anewarray     #11                 // class ca/uhn/fhir/model/api/IElement
      11: dup
      12: iconst_0
      13: aload_0
      14: getfield      #13                 // Field myCode:Lca/uhn/fhir/model/dstu2/composite/CodeableConceptDt;
      17: aastore
      18: dup
      19: iconst_1
      20: aload_0
      21: getfield      #19                 // Field myValue:Lca/uhn/fhir/model/api/IDatatype;
      24: aastore
      25: dup
      26: iconst_2
      27: aload_0
      28: getfield      #23                 // Field myExclude:Lca/uhn/fhir/model/primitive/BooleanDt;
      31: aastore
      32: dup
      33: iconst_3
      34: aload_0
      35: getfield      #27                 // Field myPeriod:Lca/uhn/fhir/model/dstu2/composite/PeriodDt;
      38: aastore
      39: invokestatic  #31                 // Method ca/uhn/fhir/util/ElementUtil.isEmpty:([Lca/uhn/fhir/model/api/IElement;)Z
      42: ifeq          49
      45: iconst_1
      46: goto          50
      49: iconst_0
      50: ireturn

  public <T extends ca.uhn.fhir.model.api.IElement> java.util.List<T> getAllPopulatedChildElementsOfType(java.lang.Class<T>);
    Code:
       0: aload_1
       1: iconst_4
       2: anewarray     #37                 // class java/lang/Object
       5: dup
       6: iconst_0
       7: aload_0
       8: getfield      #13                 // Field myCode:Lca/uhn/fhir/model/dstu2/composite/CodeableConceptDt;
      11: aastore
      12: dup
      13: iconst_1
      14: aload_0
      15: getfield      #19                 // Field myValue:Lca/uhn/fhir/model/api/IDatatype;
      18: aastore
      19: dup
      20: iconst_2
      21: aload_0
      22: getfield      #23                 // Field myExclude:Lca/uhn/fhir/model/primitive/BooleanDt;
      25: aastore
      26: dup
      27: iconst_3
      28: aload_0
      29: getfield      #27                 // Field myPeriod:Lca/uhn/fhir/model/dstu2/composite/PeriodDt;
      32: aastore
      33: invokestatic  #39                 // Method ca/uhn/fhir/util/ElementUtil.allPopulatedChildElements:(Ljava/lang/Class;[Ljava/lang/Object;)Ljava/util/List;
      36: areturn

  public ca.uhn.fhir.model.dstu2.composite.CodeableConceptDt getCode();
    Code:
       0: aload_0
       1: getfield      #13                 // Field myCode:Lca/uhn/fhir/model/dstu2/composite/CodeableConceptDt;
       4: ifnonnull     18
       7: aload_0
       8: new           #43                 // class ca/uhn/fhir/model/dstu2/composite/CodeableConceptDt
      11: dup
      12: invokespecial #45                 // Method ca/uhn/fhir/model/dstu2/composite/CodeableConceptDt."<init>":()V
      15: putfield      #13                 // Field myCode:Lca/uhn/fhir/model/dstu2/composite/CodeableConceptDt;
      18: aload_0
      19: getfield      #13                 // Field myCode:Lca/uhn/fhir/model/dstu2/composite/CodeableConceptDt;
      22: areturn

  public ca.uhn.fhir.model.dstu2.resource.Group$Characteristic setCode(ca.uhn.fhir.model.dstu2.composite.CodeableConceptDt);
    Code:
       0: aload_0
       1: aload_1
       2: putfield      #13                 // Field myCode:Lca/uhn/fhir/model/dstu2/composite/CodeableConceptDt;
       5: aload_0
       6: areturn

  public ca.uhn.fhir.model.api.IDatatype getValue();
    Code:
       0: aload_0
       1: getfield      #19                 // Field myValue:Lca/uhn/fhir/model/api/IDatatype;
       4: areturn

  public ca.uhn.fhir.model.dstu2.resource.Group$Characteristic setValue(ca.uhn.fhir.model.api.IDatatype);
    Code:
       0: aload_0
       1: aload_1
       2: putfield      #19                 // Field myValue:Lca/uhn/fhir/model/api/IDatatype;
       5: aload_0
       6: areturn

  public ca.uhn.fhir.model.primitive.BooleanDt getExcludeElement();
    Code:
       0: aload_0
       1: getfield      #23                 // Field myExclude:Lca/uhn/fhir/model/primitive/BooleanDt;
       4: ifnonnull     18
       7: aload_0
       8: new           #46                 // class ca/uhn/fhir/model/primitive/BooleanDt
      11: dup
      12: invokespecial #48                 // Method ca/uhn/fhir/model/primitive/BooleanDt."<init>":()V
      15: putfield      #23                 // Field myExclude:Lca/uhn/fhir/model/primitive/BooleanDt;
      18: aload_0
      19: getfield      #23                 // Field myExclude:Lca/uhn/fhir/model/primitive/BooleanDt;
      22: areturn

  public java.lang.Boolean getExclude();
    Code:
       0: aload_0
       1: invokevirtual #49                 // Method getExcludeElement:()Lca/uhn/fhir/model/primitive/BooleanDt;
       4: invokevirtual #53                 // Method ca/uhn/fhir/model/primitive/BooleanDt.getValue:()Ljava/lang/Object;
       7: checkcast     #57                 // class java/lang/Boolean
      10: areturn

  public ca.uhn.fhir.model.dstu2.resource.Group$Characteristic setExclude(ca.uhn.fhir.model.primitive.BooleanDt);
    Code:
       0: aload_0
       1: aload_1
       2: putfield      #23                 // Field myExclude:Lca/uhn/fhir/model/primitive/BooleanDt;
       5: aload_0
       6: areturn

  public ca.uhn.fhir.model.dstu2.resource.Group$Characteristic setExclude(boolean);
    Code:
       0: aload_0
       1: new           #46                 // class ca/uhn/fhir/model/primitive/BooleanDt
       4: dup
       5: iload_1
       6: invokespecial #59                 // Method ca/uhn/fhir/model/primitive/BooleanDt."<init>":(Z)V
       9: putfield      #23                 // Field myExclude:Lca/uhn/fhir/model/primitive/BooleanDt;
      12: aload_0
      13: areturn

  public ca.uhn.fhir.model.dstu2.composite.PeriodDt getPeriod();
    Code:
       0: aload_0
       1: getfield      #27                 // Field myPeriod:Lca/uhn/fhir/model/dstu2/composite/PeriodDt;
       4: ifnonnull     18
       7: aload_0
       8: new           #62                 // class ca/uhn/fhir/model/dstu2/composite/PeriodDt
      11: dup
      12: invokespecial #64                 // Method ca/uhn/fhir/model/dstu2/composite/PeriodDt."<init>":()V
      15: putfield      #27                 // Field myPeriod:Lca/uhn/fhir/model/dstu2/composite/PeriodDt;
      18: aload_0
      19: getfield      #27                 // Field myPeriod:Lca/uhn/fhir/model/dstu2/composite/PeriodDt;
      22: areturn

  public ca.uhn.fhir.model.dstu2.resource.Group$Characteristic setPeriod(ca.uhn.fhir.model.dstu2.composite.PeriodDt);
    Code:
       0: aload_0
       1: aload_1
       2: putfield      #27                 // Field myPeriod:Lca/uhn/fhir/model/dstu2/composite/PeriodDt;
       5: aload_0
       6: areturn
}
