Compiled from "MedicationOrder.java"
public class ca.uhn.fhir.model.dstu2.resource.MedicationOrder extends ca.uhn.fhir.model.dstu2.resource.BaseResource implements ca.uhn.fhir.model.api.IResource {
  public static final java.lang.String SP_DATEWRITTEN;

  public static final ca.uhn.fhir.rest.gclient.DateClientParam DATEWRITTEN;

  public static final java.lang.String SP_ENCOUNTER;

  public static final ca.uhn.fhir.rest.gclient.ReferenceClientParam ENCOUNTER;

  public static final java.lang.String SP_IDENTIFIER;

  public static final ca.uhn.fhir.rest.gclient.TokenClientParam IDENTIFIER;

  public static final java.lang.String SP_MEDICATION;

  public static final ca.uhn.fhir.rest.gclient.ReferenceClientParam MEDICATION;

  public static final java.lang.String SP_CODE;

  public static final ca.uhn.fhir.rest.gclient.TokenClientParam CODE;

  public static final java.lang.String SP_PATIENT;

  public static final ca.uhn.fhir.rest.gclient.ReferenceClientParam PATIENT;

  public static final java.lang.String SP_STATUS;

  public static final ca.uhn.fhir.rest.gclient.TokenClientParam STATUS;

  public static final java.lang.String SP_PRESCRIBER;

  public static final ca.uhn.fhir.rest.gclient.ReferenceClientParam PRESCRIBER;

  public static final ca.uhn.fhir.model.api.Include INCLUDE_ENCOUNTER;

  public static final ca.uhn.fhir.model.api.Include INCLUDE_MEDICATION;

  public static final ca.uhn.fhir.model.api.Include INCLUDE_PATIENT;

  public static final ca.uhn.fhir.model.api.Include INCLUDE_PRESCRIBER;

  private java.util.List<ca.uhn.fhir.model.dstu2.composite.IdentifierDt> myIdentifier;

  private ca.uhn.fhir.model.primitive.DateTimeDt myDateWritten;

  private ca.uhn.fhir.model.primitive.BoundCodeDt<ca.uhn.fhir.model.dstu2.valueset.MedicationOrderStatusEnum> myStatus;

  private ca.uhn.fhir.model.primitive.DateTimeDt myDateEnded;

  private ca.uhn.fhir.model.dstu2.composite.CodeableConceptDt myReasonEnded;

  private ca.uhn.fhir.model.dstu2.composite.ResourceReferenceDt myPatient;

  private ca.uhn.fhir.model.dstu2.composite.ResourceReferenceDt myPrescriber;

  private ca.uhn.fhir.model.dstu2.composite.ResourceReferenceDt myEncounter;

  private ca.uhn.fhir.model.api.IDatatype myReason;

  private ca.uhn.fhir.model.primitive.StringDt myNote;

  private ca.uhn.fhir.model.api.IDatatype myMedication;

  private java.util.List<ca.uhn.fhir.model.dstu2.resource.MedicationOrder$DosageInstruction> myDosageInstruction;

  private ca.uhn.fhir.model.dstu2.resource.MedicationOrder$DispenseRequest myDispenseRequest;

  private ca.uhn.fhir.model.dstu2.resource.MedicationOrder$Substitution mySubstitution;

  private ca.uhn.fhir.model.dstu2.composite.ResourceReferenceDt myPriorPrescription;

  public ca.uhn.fhir.model.dstu2.resource.MedicationOrder();
    Code:
       0: aload_0
       1: invokespecial #1                  // Method ca/uhn/fhir/model/dstu2/resource/BaseResource."<init>":()V
       4: return

  public boolean isEmpty();
    Code:
       0: aload_0
       1: invokespecial #7                  // Method ca/uhn/fhir/model/dstu2/resource/BaseResource.isBaseEmpty:()Z
       4: ifeq          136
       7: bipush        15
       9: anewarray     #11                 // class java/lang/Object
      12: dup
      13: iconst_0
      14: aload_0
      15: getfield      #13                 // Field myIdentifier:Ljava/util/List;
      18: aastore
      19: dup
      20: iconst_1
      21: aload_0
      22: getfield      #19                 // Field myDateWritten:Lca/uhn/fhir/model/primitive/DateTimeDt;
      25: aastore
      26: dup
      27: iconst_2
      28: aload_0
      29: getfield      #23                 // Field myStatus:Lca/uhn/fhir/model/primitive/BoundCodeDt;
      32: aastore
      33: dup
      34: iconst_3
      35: aload_0
      36: getfield      #27                 // Field myDateEnded:Lca/uhn/fhir/model/primitive/DateTimeDt;
      39: aastore
      40: dup
      41: iconst_4
      42: aload_0
      43: getfield      #30                 // Field myReasonEnded:Lca/uhn/fhir/model/dstu2/composite/CodeableConceptDt;
      46: aastore
      47: dup
      48: iconst_5
      49: aload_0
      50: getfield      #34                 // Field myPatient:Lca/uhn/fhir/model/dstu2/composite/ResourceReferenceDt;
      53: aastore
      54: dup
      55: bipush        6
      57: aload_0
      58: getfield      #38                 // Field myPrescriber:Lca/uhn/fhir/model/dstu2/composite/ResourceReferenceDt;
      61: aastore
      62: dup
      63: bipush        7
      65: aload_0
      66: getfield      #41                 // Field myEncounter:Lca/uhn/fhir/model/dstu2/composite/ResourceReferenceDt;
      69: aastore
      70: dup
      71: bipush        8
      73: aload_0
      74: getfield      #44                 // Field myReason:Lca/uhn/fhir/model/api/IDatatype;
      77: aastore
      78: dup
      79: bipush        9
      81: aload_0
      82: getfield      #48                 // Field myNote:Lca/uhn/fhir/model/primitive/StringDt;
      85: aastore
      86: dup
      87: bipush        10
      89: aload_0
      90: getfield      #52                 // Field myMedication:Lca/uhn/fhir/model/api/IDatatype;
      93: aastore
      94: dup
      95: bipush        11
      97: aload_0
      98: getfield      #55                 // Field myDosageInstruction:Ljava/util/List;
     101: aastore
     102: dup
     103: bipush        12
     105: aload_0
     106: getfield      #58                 // Field myDispenseRequest:Lca/uhn/fhir/model/dstu2/resource/MedicationOrder$DispenseRequest;
     109: aastore
     110: dup
     111: bipush        13
     113: aload_0
     114: getfield      #62                 // Field mySubstitution:Lca/uhn/fhir/model/dstu2/resource/MedicationOrder$Substitution;
     117: aastore
     118: dup
     119: bipush        14
     121: aload_0
     122: getfield      #66                 // Field myPriorPrescription:Lca/uhn/fhir/model/dstu2/composite/ResourceReferenceDt;
     125: aastore
     126: invokestatic  #69                 // Method ca/uhn/fhir/util/ElementUtil.isEmpty:([Ljava/lang/Object;)Z
     129: ifeq          136
     132: iconst_1
     133: goto          137
     136: iconst_0
     137: ireturn

  public <T extends ca.uhn.fhir.model.api.IElement> java.util.List<T> getAllPopulatedChildElementsOfType(java.lang.Class<T>);
    Code:
       0: aload_1
       1: bipush        15
       3: anewarray     #11                 // class java/lang/Object
       6: dup
       7: iconst_0
       8: aload_0
       9: getfield      #13                 // Field myIdentifier:Ljava/util/List;
      12: aastore
      13: dup
      14: iconst_1
      15: aload_0
      16: getfield      #19                 // Field myDateWritten:Lca/uhn/fhir/model/primitive/DateTimeDt;
      19: aastore
      20: dup
      21: iconst_2
      22: aload_0
      23: getfield      #23                 // Field myStatus:Lca/uhn/fhir/model/primitive/BoundCodeDt;
      26: aastore
      27: dup
      28: iconst_3
      29: aload_0
      30: getfield      #27                 // Field myDateEnded:Lca/uhn/fhir/model/primitive/DateTimeDt;
      33: aastore
      34: dup
      35: iconst_4
      36: aload_0
      37: getfield      #30                 // Field myReasonEnded:Lca/uhn/fhir/model/dstu2/composite/CodeableConceptDt;
      40: aastore
      41: dup
      42: iconst_5
      43: aload_0
      44: getfield      #34                 // Field myPatient:Lca/uhn/fhir/model/dstu2/composite/ResourceReferenceDt;
      47: aastore
      48: dup
      49: bipush        6
      51: aload_0
      52: getfield      #38                 // Field myPrescriber:Lca/uhn/fhir/model/dstu2/composite/ResourceReferenceDt;
      55: aastore
      56: dup
      57: bipush        7
      59: aload_0
      60: getfield      #41                 // Field myEncounter:Lca/uhn/fhir/model/dstu2/composite/ResourceReferenceDt;
      63: aastore
      64: dup
      65: bipush        8
      67: aload_0
      68: getfield      #44                 // Field myReason:Lca/uhn/fhir/model/api/IDatatype;
      71: aastore
      72: dup
      73: bipush        9
      75: aload_0
      76: getfield      #48                 // Field myNote:Lca/uhn/fhir/model/primitive/StringDt;
      79: aastore
      80: dup
      81: bipush        10
      83: aload_0
      84: getfield      #52                 // Field myMedication:Lca/uhn/fhir/model/api/IDatatype;
      87: aastore
      88: dup
      89: bipush        11
      91: aload_0
      92: getfield      #55                 // Field myDosageInstruction:Ljava/util/List;
      95: aastore
      96: dup
      97: bipush        12
      99: aload_0
     100: getfield      #58                 // Field myDispenseRequest:Lca/uhn/fhir/model/dstu2/resource/MedicationOrder$DispenseRequest;
     103: aastore
     104: dup
     105: bipush        13
     107: aload_0
     108: getfield      #62                 // Field mySubstitution:Lca/uhn/fhir/model/dstu2/resource/MedicationOrder$Substitution;
     111: aastore
     112: dup
     113: bipush        14
     115: aload_0
     116: getfield      #66                 // Field myPriorPrescription:Lca/uhn/fhir/model/dstu2/composite/ResourceReferenceDt;
     119: aastore
     120: invokestatic  #75                 // Method ca/uhn/fhir/util/ElementUtil.allPopulatedChildElements:(Ljava/lang/Class;[Ljava/lang/Object;)Ljava/util/List;
     123: areturn

  public java.util.List<ca.uhn.fhir.model.dstu2.composite.IdentifierDt> getIdentifier();
    Code:
       0: aload_0
       1: getfield      #13                 // Field myIdentifier:Ljava/util/List;
       4: ifnonnull     18
       7: aload_0
       8: new           #79                 // class java/util/ArrayList
      11: dup
      12: invokespecial #81                 // Method java/util/ArrayList."<init>":()V
      15: putfield      #13                 // Field myIdentifier:Ljava/util/List;
      18: aload_0
      19: getfield      #13                 // Field myIdentifier:Ljava/util/List;
      22: areturn

  public ca.uhn.fhir.model.dstu2.resource.MedicationOrder setIdentifier(java.util.List<ca.uhn.fhir.model.dstu2.composite.IdentifierDt>);
    Code:
       0: aload_0
       1: aload_1
       2: putfield      #13                 // Field myIdentifier:Ljava/util/List;
       5: aload_0
       6: areturn

  public ca.uhn.fhir.model.dstu2.composite.IdentifierDt addIdentifier();
    Code:
       0: new           #82                 // class ca/uhn/fhir/model/dstu2/composite/IdentifierDt
       3: dup
       4: invokespecial #84                 // Method ca/uhn/fhir/model/dstu2/composite/IdentifierDt."<init>":()V
       7: astore_1
       8: aload_0
       9: invokevirtual #85                 // Method getIdentifier:()Ljava/util/List;
      12: aload_1
      13: invokeinterface #89,  2           // InterfaceMethod java/util/List.add:(Ljava/lang/Object;)Z
      18: pop
      19: aload_1
      20: areturn

  public ca.uhn.fhir.model.dstu2.resource.MedicationOrder addIdentifier(ca.uhn.fhir.model.dstu2.composite.IdentifierDt);
    Code:
       0: aload_1
       1: ifnonnull     14
       4: new           #95                 // class java/lang/NullPointerException
       7: dup
       8: ldc           #97                 // String theValue must not be null
      10: invokespecial #99                 // Method java/lang/NullPointerException."<init>":(Ljava/lang/String;)V
      13: athrow
      14: aload_0
      15: invokevirtual #85                 // Method getIdentifier:()Ljava/util/List;
      18: aload_1
      19: invokeinterface #89,  2           // InterfaceMethod java/util/List.add:(Ljava/lang/Object;)Z
      24: pop
      25: aload_0
      26: areturn

  public ca.uhn.fhir.model.dstu2.composite.IdentifierDt getIdentifierFirstRep();
    Code:
       0: aload_0
       1: invokevirtual #85                 // Method getIdentifier:()Ljava/util/List;
       4: invokeinterface #102,  1          // InterfaceMethod java/util/List.isEmpty:()Z
       9: ifeq          17
      12: aload_0
      13: invokevirtual #104                // Method addIdentifier:()Lca/uhn/fhir/model/dstu2/composite/IdentifierDt;
      16: areturn
      17: aload_0
      18: invokevirtual #85                 // Method getIdentifier:()Ljava/util/List;
      21: iconst_0
      22: invokeinterface #108,  2          // InterfaceMethod java/util/List.get:(I)Ljava/lang/Object;
      27: checkcast     #82                 // class ca/uhn/fhir/model/dstu2/composite/IdentifierDt
      30: areturn

  public ca.uhn.fhir.model.primitive.DateTimeDt getDateWrittenElement();
    Code:
       0: aload_0
       1: getfield      #19                 // Field myDateWritten:Lca/uhn/fhir/model/primitive/DateTimeDt;
       4: ifnonnull     18
       7: aload_0
       8: new           #112                // class ca/uhn/fhir/model/primitive/DateTimeDt
      11: dup
      12: invokespecial #114                // Method ca/uhn/fhir/model/primitive/DateTimeDt."<init>":()V
      15: putfield      #19                 // Field myDateWritten:Lca/uhn/fhir/model/primitive/DateTimeDt;
      18: aload_0
      19: getfield      #19                 // Field myDateWritten:Lca/uhn/fhir/model/primitive/DateTimeDt;
      22: areturn

  public java.util.Date getDateWritten();
    Code:
       0: aload_0
       1: invokevirtual #115                // Method getDateWrittenElement:()Lca/uhn/fhir/model/primitive/DateTimeDt;
       4: invokevirtual #119                // Method ca/uhn/fhir/model/primitive/DateTimeDt.getValue:()Ljava/lang/Object;
       7: checkcast     #123                // class java/util/Date
      10: areturn

  public ca.uhn.fhir.model.dstu2.resource.MedicationOrder setDateWritten(ca.uhn.fhir.model.primitive.DateTimeDt);
    Code:
       0: aload_0
       1: aload_1
       2: putfield      #19                 // Field myDateWritten:Lca/uhn/fhir/model/primitive/DateTimeDt;
       5: aload_0
       6: areturn

  public ca.uhn.fhir.model.dstu2.resource.MedicationOrder setDateWritten(java.util.Date, ca.uhn.fhir.model.api.TemporalPrecisionEnum);
    Code:
       0: aload_0
       1: new           #112                // class ca/uhn/fhir/model/primitive/DateTimeDt
       4: dup
       5: aload_1
       6: aload_2
       7: invokespecial #125                // Method ca/uhn/fhir/model/primitive/DateTimeDt."<init>":(Ljava/util/Date;Lca/uhn/fhir/model/api/TemporalPrecisionEnum;)V
      10: putfield      #19                 // Field myDateWritten:Lca/uhn/fhir/model/primitive/DateTimeDt;
      13: aload_0
      14: areturn

  public ca.uhn.fhir.model.dstu2.resource.MedicationOrder setDateWrittenWithSecondsPrecision(java.util.Date);
    Code:
       0: aload_0
       1: new           #112                // class ca/uhn/fhir/model/primitive/DateTimeDt
       4: dup
       5: aload_1
       6: invokespecial #128                // Method ca/uhn/fhir/model/primitive/DateTimeDt."<init>":(Ljava/util/Date;)V
       9: putfield      #19                 // Field myDateWritten:Lca/uhn/fhir/model/primitive/DateTimeDt;
      12: aload_0
      13: areturn

  public ca.uhn.fhir.model.primitive.BoundCodeDt<ca.uhn.fhir.model.dstu2.valueset.MedicationOrderStatusEnum> getStatusElement();
    Code:
       0: aload_0
       1: getfield      #23                 // Field myStatus:Lca/uhn/fhir/model/primitive/BoundCodeDt;
       4: ifnonnull     21
       7: aload_0
       8: new           #131                // class ca/uhn/fhir/model/primitive/BoundCodeDt
      11: dup
      12: getstatic     #133                // Field ca/uhn/fhir/model/dstu2/valueset/MedicationOrderStatusEnum.VALUESET_BINDER:Lca/uhn/fhir/model/api/IValueSetEnumBinder;
      15: invokespecial #139                // Method ca/uhn/fhir/model/primitive/BoundCodeDt."<init>":(Lca/uhn/fhir/model/api/IValueSetEnumBinder;)V
      18: putfield      #23                 // Field myStatus:Lca/uhn/fhir/model/primitive/BoundCodeDt;
      21: aload_0
      22: getfield      #23                 // Field myStatus:Lca/uhn/fhir/model/primitive/BoundCodeDt;
      25: areturn

  public java.lang.String getStatus();
    Code:
       0: aload_0
       1: invokevirtual #142                // Method getStatusElement:()Lca/uhn/fhir/model/primitive/BoundCodeDt;
       4: invokevirtual #146                // Method ca/uhn/fhir/model/primitive/BoundCodeDt.getValue:()Ljava/lang/Object;
       7: checkcast     #147                // class java/lang/String
      10: areturn

  public ca.uhn.fhir.model.dstu2.resource.MedicationOrder setStatus(ca.uhn.fhir.model.primitive.BoundCodeDt<ca.uhn.fhir.model.dstu2.valueset.MedicationOrderStatusEnum>);
    Code:
       0: aload_0
       1: aload_1
       2: putfield      #23                 // Field myStatus:Lca/uhn/fhir/model/primitive/BoundCodeDt;
       5: aload_0
       6: areturn

  public ca.uhn.fhir.model.dstu2.resource.MedicationOrder setStatus(ca.uhn.fhir.model.dstu2.valueset.MedicationOrderStatusEnum);
    Code:
       0: aload_0
       1: new           #131                // class ca/uhn/fhir/model/primitive/BoundCodeDt
       4: dup
       5: getstatic     #133                // Field ca/uhn/fhir/model/dstu2/valueset/MedicationOrderStatusEnum.VALUESET_BINDER:Lca/uhn/fhir/model/api/IValueSetEnumBinder;
       8: aload_1
       9: invokespecial #149                // Method ca/uhn/fhir/model/primitive/BoundCodeDt."<init>":(Lca/uhn/fhir/model/api/IValueSetEnumBinder;Ljava/lang/Enum;)V
      12: invokevirtual #152                // Method setStatus:(Lca/uhn/fhir/model/primitive/BoundCodeDt;)Lca/uhn/fhir/model/dstu2/resource/MedicationOrder;
      15: pop
      16: aload_0
      17: areturn

  public ca.uhn.fhir.model.primitive.DateTimeDt getDateEndedElement();
    Code:
       0: aload_0
       1: getfield      #27                 // Field myDateEnded:Lca/uhn/fhir/model/primitive/DateTimeDt;
       4: ifnonnull     18
       7: aload_0
       8: new           #112                // class ca/uhn/fhir/model/primitive/DateTimeDt
      11: dup
      12: invokespecial #114                // Method ca/uhn/fhir/model/primitive/DateTimeDt."<init>":()V
      15: putfield      #27                 // Field myDateEnded:Lca/uhn/fhir/model/primitive/DateTimeDt;
      18: aload_0
      19: getfield      #27                 // Field myDateEnded:Lca/uhn/fhir/model/primitive/DateTimeDt;
      22: areturn

  public java.util.Date getDateEnded();
    Code:
       0: aload_0
       1: invokevirtual #156                // Method getDateEndedElement:()Lca/uhn/fhir/model/primitive/DateTimeDt;
       4: invokevirtual #119                // Method ca/uhn/fhir/model/primitive/DateTimeDt.getValue:()Ljava/lang/Object;
       7: checkcast     #123                // class java/util/Date
      10: areturn

  public ca.uhn.fhir.model.dstu2.resource.MedicationOrder setDateEnded(ca.uhn.fhir.model.primitive.DateTimeDt);
    Code:
       0: aload_0
       1: aload_1
       2: putfield      #27                 // Field myDateEnded:Lca/uhn/fhir/model/primitive/DateTimeDt;
       5: aload_0
       6: areturn

  public ca.uhn.fhir.model.dstu2.resource.MedicationOrder setDateEnded(java.util.Date, ca.uhn.fhir.model.api.TemporalPrecisionEnum);
    Code:
       0: aload_0
       1: new           #112                // class ca/uhn/fhir/model/primitive/DateTimeDt
       4: dup
       5: aload_1
       6: aload_2
       7: invokespecial #125                // Method ca/uhn/fhir/model/primitive/DateTimeDt."<init>":(Ljava/util/Date;Lca/uhn/fhir/model/api/TemporalPrecisionEnum;)V
      10: putfield      #27                 // Field myDateEnded:Lca/uhn/fhir/model/primitive/DateTimeDt;
      13: aload_0
      14: areturn

  public ca.uhn.fhir.model.dstu2.resource.MedicationOrder setDateEndedWithSecondsPrecision(java.util.Date);
    Code:
       0: aload_0
       1: new           #112                // class ca/uhn/fhir/model/primitive/DateTimeDt
       4: dup
       5: aload_1
       6: invokespecial #128                // Method ca/uhn/fhir/model/primitive/DateTimeDt."<init>":(Ljava/util/Date;)V
       9: putfield      #27                 // Field myDateEnded:Lca/uhn/fhir/model/primitive/DateTimeDt;
      12: aload_0
      13: areturn

  public ca.uhn.fhir.model.dstu2.composite.CodeableConceptDt getReasonEnded();
    Code:
       0: aload_0
       1: getfield      #30                 // Field myReasonEnded:Lca/uhn/fhir/model/dstu2/composite/CodeableConceptDt;
       4: ifnonnull     18
       7: aload_0
       8: new           #159                // class ca/uhn/fhir/model/dstu2/composite/CodeableConceptDt
      11: dup
      12: invokespecial #161                // Method ca/uhn/fhir/model/dstu2/composite/CodeableConceptDt."<init>":()V
      15: putfield      #30                 // Field myReasonEnded:Lca/uhn/fhir/model/dstu2/composite/CodeableConceptDt;
      18: aload_0
      19: getfield      #30                 // Field myReasonEnded:Lca/uhn/fhir/model/dstu2/composite/CodeableConceptDt;
      22: areturn

  public ca.uhn.fhir.model.dstu2.resource.MedicationOrder setReasonEnded(ca.uhn.fhir.model.dstu2.composite.CodeableConceptDt);
    Code:
       0: aload_0
       1: aload_1
       2: putfield      #30                 // Field myReasonEnded:Lca/uhn/fhir/model/dstu2/composite/CodeableConceptDt;
       5: aload_0
       6: areturn

  public ca.uhn.fhir.model.dstu2.composite.ResourceReferenceDt getPatient();
    Code:
       0: aload_0
       1: getfield      #34                 // Field myPatient:Lca/uhn/fhir/model/dstu2/composite/ResourceReferenceDt;
       4: ifnonnull     18
       7: aload_0
       8: new           #162                // class ca/uhn/fhir/model/dstu2/composite/ResourceReferenceDt
      11: dup
      12: invokespecial #164                // Method ca/uhn/fhir/model/dstu2/composite/ResourceReferenceDt."<init>":()V
      15: putfield      #34                 // Field myPatient:Lca/uhn/fhir/model/dstu2/composite/ResourceReferenceDt;
      18: aload_0
      19: getfield      #34                 // Field myPatient:Lca/uhn/fhir/model/dstu2/composite/ResourceReferenceDt;
      22: areturn

  public ca.uhn.fhir.model.dstu2.resource.MedicationOrder setPatient(ca.uhn.fhir.model.dstu2.composite.ResourceReferenceDt);
    Code:
       0: aload_0
       1: aload_1
       2: putfield      #34                 // Field myPatient:Lca/uhn/fhir/model/dstu2/composite/ResourceReferenceDt;
       5: aload_0
       6: areturn

  public ca.uhn.fhir.model.dstu2.composite.ResourceReferenceDt getPrescriber();
    Code:
       0: aload_0
       1: getfield      #38                 // Field myPrescriber:Lca/uhn/fhir/model/dstu2/composite/ResourceReferenceDt;
       4: ifnonnull     18
       7: aload_0
       8: new           #162                // class ca/uhn/fhir/model/dstu2/composite/ResourceReferenceDt
      11: dup
      12: invokespecial #164                // Method ca/uhn/fhir/model/dstu2/composite/ResourceReferenceDt."<init>":()V
      15: putfield      #38                 // Field myPrescriber:Lca/uhn/fhir/model/dstu2/composite/ResourceReferenceDt;
      18: aload_0
      19: getfield      #38                 // Field myPrescriber:Lca/uhn/fhir/model/dstu2/composite/ResourceReferenceDt;
      22: areturn

  public ca.uhn.fhir.model.dstu2.resource.MedicationOrder setPrescriber(ca.uhn.fhir.model.dstu2.composite.ResourceReferenceDt);
    Code:
       0: aload_0
       1: aload_1
       2: putfield      #38                 // Field myPrescriber:Lca/uhn/fhir/model/dstu2/composite/ResourceReferenceDt;
       5: aload_0
       6: areturn

  public ca.uhn.fhir.model.dstu2.composite.ResourceReferenceDt getEncounter();
    Code:
       0: aload_0
       1: getfield      #41                 // Field myEncounter:Lca/uhn/fhir/model/dstu2/composite/ResourceReferenceDt;
       4: ifnonnull     18
       7: aload_0
       8: new           #162                // class ca/uhn/fhir/model/dstu2/composite/ResourceReferenceDt
      11: dup
      12: invokespecial #164                // Method ca/uhn/fhir/model/dstu2/composite/ResourceReferenceDt."<init>":()V
      15: putfield      #41                 // Field myEncounter:Lca/uhn/fhir/model/dstu2/composite/ResourceReferenceDt;
      18: aload_0
      19: getfield      #41                 // Field myEncounter:Lca/uhn/fhir/model/dstu2/composite/ResourceReferenceDt;
      22: areturn

  public ca.uhn.fhir.model.dstu2.resource.MedicationOrder setEncounter(ca.uhn.fhir.model.dstu2.composite.ResourceReferenceDt);
    Code:
       0: aload_0
       1: aload_1
       2: putfield      #41                 // Field myEncounter:Lca/uhn/fhir/model/dstu2/composite/ResourceReferenceDt;
       5: aload_0
       6: areturn

  public ca.uhn.fhir.model.api.IDatatype getReason();
    Code:
       0: aload_0
       1: getfield      #44                 // Field myReason:Lca/uhn/fhir/model/api/IDatatype;
       4: areturn

  public ca.uhn.fhir.model.dstu2.resource.MedicationOrder setReason(ca.uhn.fhir.model.api.IDatatype);
    Code:
       0: aload_0
       1: aload_1
       2: putfield      #44                 // Field myReason:Lca/uhn/fhir/model/api/IDatatype;
       5: aload_0
       6: areturn

  public ca.uhn.fhir.model.primitive.StringDt getNoteElement();
    Code:
       0: aload_0
       1: getfield      #48                 // Field myNote:Lca/uhn/fhir/model/primitive/StringDt;
       4: ifnonnull     18
       7: aload_0
       8: new           #165                // class ca/uhn/fhir/model/primitive/StringDt
      11: dup
      12: invokespecial #167                // Method ca/uhn/fhir/model/primitive/StringDt."<init>":()V
      15: putfield      #48                 // Field myNote:Lca/uhn/fhir/model/primitive/StringDt;
      18: aload_0
      19: getfield      #48                 // Field myNote:Lca/uhn/fhir/model/primitive/StringDt;
      22: areturn

  public java.lang.String getNote();
    Code:
       0: aload_0
       1: invokevirtual #168                // Method getNoteElement:()Lca/uhn/fhir/model/primitive/StringDt;
       4: invokevirtual #172                // Method ca/uhn/fhir/model/primitive/StringDt.getValue:()Ljava/lang/Object;
       7: checkcast     #147                // class java/lang/String
      10: areturn

  public ca.uhn.fhir.model.dstu2.resource.MedicationOrder setNote(ca.uhn.fhir.model.primitive.StringDt);
    Code:
       0: aload_0
       1: aload_1
       2: putfield      #48                 // Field myNote:Lca/uhn/fhir/model/primitive/StringDt;
       5: aload_0
       6: areturn

  public ca.uhn.fhir.model.dstu2.resource.MedicationOrder setNote(java.lang.String);
    Code:
       0: aload_0
       1: new           #165                // class ca/uhn/fhir/model/primitive/StringDt
       4: dup
       5: aload_1
       6: invokespecial #173                // Method ca/uhn/fhir/model/primitive/StringDt."<init>":(Ljava/lang/String;)V
       9: putfield      #48                 // Field myNote:Lca/uhn/fhir/model/primitive/StringDt;
      12: aload_0
      13: areturn

  public ca.uhn.fhir.model.api.IDatatype getMedication();
    Code:
       0: aload_0
       1: getfield      #52                 // Field myMedication:Lca/uhn/fhir/model/api/IDatatype;
       4: areturn

  public ca.uhn.fhir.model.dstu2.resource.MedicationOrder setMedication(ca.uhn.fhir.model.api.IDatatype);
    Code:
       0: aload_0
       1: aload_1
       2: putfield      #52                 // Field myMedication:Lca/uhn/fhir/model/api/IDatatype;
       5: aload_0
       6: areturn

  public java.util.List<ca.uhn.fhir.model.dstu2.resource.MedicationOrder$DosageInstruction> getDosageInstruction();
    Code:
       0: aload_0
       1: getfield      #55                 // Field myDosageInstruction:Ljava/util/List;
       4: ifnonnull     18
       7: aload_0
       8: new           #79                 // class java/util/ArrayList
      11: dup
      12: invokespecial #81                 // Method java/util/ArrayList."<init>":()V
      15: putfield      #55                 // Field myDosageInstruction:Ljava/util/List;
      18: aload_0
      19: getfield      #55                 // Field myDosageInstruction:Ljava/util/List;
      22: areturn

  public ca.uhn.fhir.model.dstu2.resource.MedicationOrder setDosageInstruction(java.util.List<ca.uhn.fhir.model.dstu2.resource.MedicationOrder$DosageInstruction>);
    Code:
       0: aload_0
       1: aload_1
       2: putfield      #55                 // Field myDosageInstruction:Ljava/util/List;
       5: aload_0
       6: areturn

  public ca.uhn.fhir.model.dstu2.resource.MedicationOrder$DosageInstruction addDosageInstruction();
    Code:
       0: new           #174                // class ca/uhn/fhir/model/dstu2/resource/MedicationOrder$DosageInstruction
       3: dup
       4: invokespecial #176                // Method ca/uhn/fhir/model/dstu2/resource/MedicationOrder$DosageInstruction."<init>":()V
       7: astore_1
       8: aload_0
       9: invokevirtual #177                // Method getDosageInstruction:()Ljava/util/List;
      12: aload_1
      13: invokeinterface #89,  2           // InterfaceMethod java/util/List.add:(Ljava/lang/Object;)Z
      18: pop
      19: aload_1
      20: areturn

  public ca.uhn.fhir.model.dstu2.resource.MedicationOrder addDosageInstruction(ca.uhn.fhir.model.dstu2.resource.MedicationOrder$DosageInstruction);
    Code:
       0: aload_1
       1: ifnonnull     14
       4: new           #95                 // class java/lang/NullPointerException
       7: dup
       8: ldc           #97                 // String theValue must not be null
      10: invokespecial #99                 // Method java/lang/NullPointerException."<init>":(Ljava/lang/String;)V
      13: athrow
      14: aload_0
      15: invokevirtual #177                // Method getDosageInstruction:()Ljava/util/List;
      18: aload_1
      19: invokeinterface #89,  2           // InterfaceMethod java/util/List.add:(Ljava/lang/Object;)Z
      24: pop
      25: aload_0
      26: areturn

  public ca.uhn.fhir.model.dstu2.resource.MedicationOrder$DosageInstruction getDosageInstructionFirstRep();
    Code:
       0: aload_0
       1: invokevirtual #177                // Method getDosageInstruction:()Ljava/util/List;
       4: invokeinterface #102,  1          // InterfaceMethod java/util/List.isEmpty:()Z
       9: ifeq          17
      12: aload_0
      13: invokevirtual #180                // Method addDosageInstruction:()Lca/uhn/fhir/model/dstu2/resource/MedicationOrder$DosageInstruction;
      16: areturn
      17: aload_0
      18: invokevirtual #177                // Method getDosageInstruction:()Ljava/util/List;
      21: iconst_0
      22: invokeinterface #108,  2          // InterfaceMethod java/util/List.get:(I)Ljava/lang/Object;
      27: checkcast     #174                // class ca/uhn/fhir/model/dstu2/resource/MedicationOrder$DosageInstruction
      30: areturn

  public ca.uhn.fhir.model.dstu2.resource.MedicationOrder$DispenseRequest getDispenseRequest();
    Code:
       0: aload_0
       1: getfield      #58                 // Field myDispenseRequest:Lca/uhn/fhir/model/dstu2/resource/MedicationOrder$DispenseRequest;
       4: ifnonnull     18
       7: aload_0
       8: new           #184                // class ca/uhn/fhir/model/dstu2/resource/MedicationOrder$DispenseRequest
      11: dup
      12: invokespecial #186                // Method ca/uhn/fhir/model/dstu2/resource/MedicationOrder$DispenseRequest."<init>":()V
      15: putfield      #58                 // Field myDispenseRequest:Lca/uhn/fhir/model/dstu2/resource/MedicationOrder$DispenseRequest;
      18: aload_0
      19: getfield      #58                 // Field myDispenseRequest:Lca/uhn/fhir/model/dstu2/resource/MedicationOrder$DispenseRequest;
      22: areturn

  public ca.uhn.fhir.model.dstu2.resource.MedicationOrder setDispenseRequest(ca.uhn.fhir.model.dstu2.resource.MedicationOrder$DispenseRequest);
    Code:
       0: aload_0
       1: aload_1
       2: putfield      #58                 // Field myDispenseRequest:Lca/uhn/fhir/model/dstu2/resource/MedicationOrder$DispenseRequest;
       5: aload_0
       6: areturn

  public ca.uhn.fhir.model.dstu2.resource.MedicationOrder$Substitution getSubstitution();
    Code:
       0: aload_0
       1: getfield      #62                 // Field mySubstitution:Lca/uhn/fhir/model/dstu2/resource/MedicationOrder$Substitution;
       4: ifnonnull     18
       7: aload_0
       8: new           #187                // class ca/uhn/fhir/model/dstu2/resource/MedicationOrder$Substitution
      11: dup
      12: invokespecial #189                // Method ca/uhn/fhir/model/dstu2/resource/MedicationOrder$Substitution."<init>":()V
      15: putfield      #62                 // Field mySubstitution:Lca/uhn/fhir/model/dstu2/resource/MedicationOrder$Substitution;
      18: aload_0
      19: getfield      #62                 // Field mySubstitution:Lca/uhn/fhir/model/dstu2/resource/MedicationOrder$Substitution;
      22: areturn

  public ca.uhn.fhir.model.dstu2.resource.MedicationOrder setSubstitution(ca.uhn.fhir.model.dstu2.resource.MedicationOrder$Substitution);
    Code:
       0: aload_0
       1: aload_1
       2: putfield      #62                 // Field mySubstitution:Lca/uhn/fhir/model/dstu2/resource/MedicationOrder$Substitution;
       5: aload_0
       6: areturn

  public ca.uhn.fhir.model.dstu2.composite.ResourceReferenceDt getPriorPrescription();
    Code:
       0: aload_0
       1: getfield      #66                 // Field myPriorPrescription:Lca/uhn/fhir/model/dstu2/composite/ResourceReferenceDt;
       4: ifnonnull     18
       7: aload_0
       8: new           #162                // class ca/uhn/fhir/model/dstu2/composite/ResourceReferenceDt
      11: dup
      12: invokespecial #164                // Method ca/uhn/fhir/model/dstu2/composite/ResourceReferenceDt."<init>":()V
      15: putfield      #66                 // Field myPriorPrescription:Lca/uhn/fhir/model/dstu2/composite/ResourceReferenceDt;
      18: aload_0
      19: getfield      #66                 // Field myPriorPrescription:Lca/uhn/fhir/model/dstu2/composite/ResourceReferenceDt;
      22: areturn

  public ca.uhn.fhir.model.dstu2.resource.MedicationOrder setPriorPrescription(ca.uhn.fhir.model.dstu2.composite.ResourceReferenceDt);
    Code:
       0: aload_0
       1: aload_1
       2: putfield      #66                 // Field myPriorPrescription:Lca/uhn/fhir/model/dstu2/composite/ResourceReferenceDt;
       5: aload_0
       6: areturn

  public java.lang.String getResourceName();
    Code:
       0: ldc           #190                // String MedicationOrder
       2: areturn

  public ca.uhn.fhir.context.FhirVersionEnum getStructureFhirVersionEnum();
    Code:
       0: getstatic     #192                // Field ca/uhn/fhir/context/FhirVersionEnum.DSTU2:Lca/uhn/fhir/context/FhirVersionEnum;
       3: areturn

  static {};
    Code:
       0: new           #198                // class ca/uhn/fhir/rest/gclient/DateClientParam
       3: dup
       4: ldc           #200                // String datewritten
       6: invokespecial #202                // Method ca/uhn/fhir/rest/gclient/DateClientParam."<init>":(Ljava/lang/String;)V
       9: putstatic     #203                // Field DATEWRITTEN:Lca/uhn/fhir/rest/gclient/DateClientParam;
      12: new           #207                // class ca/uhn/fhir/rest/gclient/ReferenceClientParam
      15: dup
      16: ldc           #209                // String encounter
      18: invokespecial #211                // Method ca/uhn/fhir/rest/gclient/ReferenceClientParam."<init>":(Ljava/lang/String;)V
      21: putstatic     #212                // Field ENCOUNTER:Lca/uhn/fhir/rest/gclient/ReferenceClientParam;
      24: new           #216                // class ca/uhn/fhir/rest/gclient/TokenClientParam
      27: dup
      28: ldc           #218                // String identifier
      30: invokespecial #220                // Method ca/uhn/fhir/rest/gclient/TokenClientParam."<init>":(Ljava/lang/String;)V
      33: putstatic     #221                // Field IDENTIFIER:Lca/uhn/fhir/rest/gclient/TokenClientParam;
      36: new           #207                // class ca/uhn/fhir/rest/gclient/ReferenceClientParam
      39: dup
      40: ldc           #225                // String medication
      42: invokespecial #211                // Method ca/uhn/fhir/rest/gclient/ReferenceClientParam."<init>":(Ljava/lang/String;)V
      45: putstatic     #227                // Field MEDICATION:Lca/uhn/fhir/rest/gclient/ReferenceClientParam;
      48: new           #216                // class ca/uhn/fhir/rest/gclient/TokenClientParam
      51: dup
      52: ldc           #230                // String code
      54: invokespecial #220                // Method ca/uhn/fhir/rest/gclient/TokenClientParam."<init>":(Ljava/lang/String;)V
      57: putstatic     #232                // Field CODE:Lca/uhn/fhir/rest/gclient/TokenClientParam;
      60: new           #207                // class ca/uhn/fhir/rest/gclient/ReferenceClientParam
      63: dup
      64: ldc           #235                // String patient
      66: invokespecial #211                // Method ca/uhn/fhir/rest/gclient/ReferenceClientParam."<init>":(Ljava/lang/String;)V
      69: putstatic     #237                // Field PATIENT:Lca/uhn/fhir/rest/gclient/ReferenceClientParam;
      72: new           #216                // class ca/uhn/fhir/rest/gclient/TokenClientParam
      75: dup
      76: ldc           #240                // String status
      78: invokespecial #220                // Method ca/uhn/fhir/rest/gclient/TokenClientParam."<init>":(Ljava/lang/String;)V
      81: putstatic     #242                // Field STATUS:Lca/uhn/fhir/rest/gclient/TokenClientParam;
      84: new           #207                // class ca/uhn/fhir/rest/gclient/ReferenceClientParam
      87: dup
      88: ldc           #245                // String prescriber
      90: invokespecial #211                // Method ca/uhn/fhir/rest/gclient/ReferenceClientParam."<init>":(Ljava/lang/String;)V
      93: putstatic     #247                // Field PRESCRIBER:Lca/uhn/fhir/rest/gclient/ReferenceClientParam;
      96: new           #250                // class ca/uhn/fhir/model/api/Include
      99: dup
     100: ldc           #252                // String MedicationOrder:encounter
     102: invokespecial #254                // Method ca/uhn/fhir/model/api/Include."<init>":(Ljava/lang/String;)V
     105: putstatic     #255                // Field INCLUDE_ENCOUNTER:Lca/uhn/fhir/model/api/Include;
     108: new           #250                // class ca/uhn/fhir/model/api/Include
     111: dup
     112: ldc_w         #259                // String MedicationOrder:medication
     115: invokespecial #254                // Method ca/uhn/fhir/model/api/Include."<init>":(Ljava/lang/String;)V
     118: putstatic     #261                // Field INCLUDE_MEDICATION:Lca/uhn/fhir/model/api/Include;
     121: new           #250                // class ca/uhn/fhir/model/api/Include
     124: dup
     125: ldc_w         #264                // String MedicationOrder:patient
     128: invokespecial #254                // Method ca/uhn/fhir/model/api/Include."<init>":(Ljava/lang/String;)V
     131: putstatic     #266                // Field INCLUDE_PATIENT:Lca/uhn/fhir/model/api/Include;
     134: new           #250                // class ca/uhn/fhir/model/api/Include
     137: dup
     138: ldc_w         #269                // String MedicationOrder:prescriber
     141: invokespecial #254                // Method ca/uhn/fhir/model/api/Include."<init>":(Ljava/lang/String;)V
     144: putstatic     #271                // Field INCLUDE_PRESCRIBER:Lca/uhn/fhir/model/api/Include;
     147: return
}
