Compiled from "OperationOutcome.java"
public class ca.uhn.fhir.model.dstu2.resource.OperationOutcome$Issue extends ca.uhn.fhir.model.base.resource.BaseOperationOutcome$BaseIssue implements ca.uhn.fhir.model.api.IResourceBlock {
  private ca.uhn.fhir.model.primitive.BoundCodeDt<ca.uhn.fhir.model.dstu2.valueset.IssueSeverityEnum> mySeverity;

  private ca.uhn.fhir.model.primitive.BoundCodeDt<ca.uhn.fhir.model.dstu2.valueset.IssueTypeEnum> myCode;

  private ca.uhn.fhir.model.dstu2.composite.CodeableConceptDt myDetails;

  private ca.uhn.fhir.model.primitive.StringDt myDiagnostics;

  private java.util.List<ca.uhn.fhir.model.primitive.StringDt> myLocation;

  public ca.uhn.fhir.model.dstu2.resource.OperationOutcome$Issue();
    Code:
       0: aload_0
       1: invokespecial #1                  // Method ca/uhn/fhir/model/base/resource/BaseOperationOutcome$BaseIssue."<init>":()V
       4: return

  public boolean isEmpty();
    Code:
       0: aload_0
       1: invokespecial #7                  // Method ca/uhn/fhir/model/base/resource/BaseOperationOutcome$BaseIssue.isBaseEmpty:()Z
       4: ifeq          56
       7: iconst_5
       8: anewarray     #11                 // class java/lang/Object
      11: dup
      12: iconst_0
      13: aload_0
      14: getfield      #13                 // Field mySeverity:Lca/uhn/fhir/model/primitive/BoundCodeDt;
      17: aastore
      18: dup
      19: iconst_1
      20: aload_0
      21: getfield      #19                 // Field myCode:Lca/uhn/fhir/model/primitive/BoundCodeDt;
      24: aastore
      25: dup
      26: iconst_2
      27: aload_0
      28: getfield      #22                 // Field myDetails:Lca/uhn/fhir/model/dstu2/composite/CodeableConceptDt;
      31: aastore
      32: dup
      33: iconst_3
      34: aload_0
      35: getfield      #26                 // Field myDiagnostics:Lca/uhn/fhir/model/primitive/StringDt;
      38: aastore
      39: dup
      40: iconst_4
      41: aload_0
      42: getfield      #30                 // Field myLocation:Ljava/util/List;
      45: aastore
      46: invokestatic  #34                 // Method ca/uhn/fhir/util/ElementUtil.isEmpty:([Ljava/lang/Object;)Z
      49: ifeq          56
      52: iconst_1
      53: goto          57
      56: iconst_0
      57: ireturn

  public <T extends ca.uhn.fhir.model.api.IElement> java.util.List<T> getAllPopulatedChildElementsOfType(java.lang.Class<T>);
    Code:
       0: aload_1
       1: iconst_5
       2: anewarray     #11                 // class java/lang/Object
       5: dup
       6: iconst_0
       7: aload_0
       8: getfield      #13                 // Field mySeverity:Lca/uhn/fhir/model/primitive/BoundCodeDt;
      11: aastore
      12: dup
      13: iconst_1
      14: aload_0
      15: getfield      #19                 // Field myCode:Lca/uhn/fhir/model/primitive/BoundCodeDt;
      18: aastore
      19: dup
      20: iconst_2
      21: aload_0
      22: getfield      #22                 // Field myDetails:Lca/uhn/fhir/model/dstu2/composite/CodeableConceptDt;
      25: aastore
      26: dup
      27: iconst_3
      28: aload_0
      29: getfield      #26                 // Field myDiagnostics:Lca/uhn/fhir/model/primitive/StringDt;
      32: aastore
      33: dup
      34: iconst_4
      35: aload_0
      36: getfield      #30                 // Field myLocation:Ljava/util/List;
      39: aastore
      40: invokestatic  #40                 // Method ca/uhn/fhir/util/ElementUtil.allPopulatedChildElements:(Ljava/lang/Class;[Ljava/lang/Object;)Ljava/util/List;
      43: areturn

  public ca.uhn.fhir.model.primitive.BoundCodeDt<ca.uhn.fhir.model.dstu2.valueset.IssueSeverityEnum> getSeverityElement();
    Code:
       0: aload_0
       1: getfield      #13                 // Field mySeverity:Lca/uhn/fhir/model/primitive/BoundCodeDt;
       4: ifnonnull     21
       7: aload_0
       8: new           #44                 // class ca/uhn/fhir/model/primitive/BoundCodeDt
      11: dup
      12: getstatic     #46                 // Field ca/uhn/fhir/model/dstu2/valueset/IssueSeverityEnum.VALUESET_BINDER:Lca/uhn/fhir/model/api/IValueSetEnumBinder;
      15: invokespecial #52                 // Method ca/uhn/fhir/model/primitive/BoundCodeDt."<init>":(Lca/uhn/fhir/model/api/IValueSetEnumBinder;)V
      18: putfield      #13                 // Field mySeverity:Lca/uhn/fhir/model/primitive/BoundCodeDt;
      21: aload_0
      22: getfield      #13                 // Field mySeverity:Lca/uhn/fhir/model/primitive/BoundCodeDt;
      25: areturn

  public java.lang.String getSeverity();
    Code:
       0: aload_0
       1: invokevirtual #55                 // Method getSeverityElement:()Lca/uhn/fhir/model/primitive/BoundCodeDt;
       4: invokevirtual #59                 // Method ca/uhn/fhir/model/primitive/BoundCodeDt.getValue:()Ljava/lang/Object;
       7: checkcast     #63                 // class java/lang/String
      10: areturn

  public ca.uhn.fhir.model.dstu2.resource.OperationOutcome$Issue setSeverity(ca.uhn.fhir.model.primitive.BoundCodeDt<ca.uhn.fhir.model.dstu2.valueset.IssueSeverityEnum>);
    Code:
       0: aload_0
       1: aload_1
       2: putfield      #13                 // Field mySeverity:Lca/uhn/fhir/model/primitive/BoundCodeDt;
       5: aload_0
       6: areturn

  public ca.uhn.fhir.model.dstu2.resource.OperationOutcome$Issue setSeverity(ca.uhn.fhir.model.dstu2.valueset.IssueSeverityEnum);
    Code:
       0: aload_0
       1: new           #44                 // class ca/uhn/fhir/model/primitive/BoundCodeDt
       4: dup
       5: getstatic     #46                 // Field ca/uhn/fhir/model/dstu2/valueset/IssueSeverityEnum.VALUESET_BINDER:Lca/uhn/fhir/model/api/IValueSetEnumBinder;
       8: aload_1
       9: invokespecial #65                 // Method ca/uhn/fhir/model/primitive/BoundCodeDt."<init>":(Lca/uhn/fhir/model/api/IValueSetEnumBinder;Ljava/lang/Enum;)V
      12: invokevirtual #68                 // Method setSeverity:(Lca/uhn/fhir/model/primitive/BoundCodeDt;)Lca/uhn/fhir/model/dstu2/resource/OperationOutcome$Issue;
      15: pop
      16: aload_0
      17: areturn

  public ca.uhn.fhir.model.primitive.BoundCodeDt<ca.uhn.fhir.model.dstu2.valueset.IssueTypeEnum> getCodeElement();
    Code:
       0: aload_0
       1: getfield      #19                 // Field myCode:Lca/uhn/fhir/model/primitive/BoundCodeDt;
       4: ifnonnull     21
       7: aload_0
       8: new           #44                 // class ca/uhn/fhir/model/primitive/BoundCodeDt
      11: dup
      12: getstatic     #72                 // Field ca/uhn/fhir/model/dstu2/valueset/IssueTypeEnum.VALUESET_BINDER:Lca/uhn/fhir/model/api/IValueSetEnumBinder;
      15: invokespecial #52                 // Method ca/uhn/fhir/model/primitive/BoundCodeDt."<init>":(Lca/uhn/fhir/model/api/IValueSetEnumBinder;)V
      18: putfield      #19                 // Field myCode:Lca/uhn/fhir/model/primitive/BoundCodeDt;
      21: aload_0
      22: getfield      #19                 // Field myCode:Lca/uhn/fhir/model/primitive/BoundCodeDt;
      25: areturn

  public java.lang.String getCode();
    Code:
       0: aload_0
       1: invokevirtual #75                 // Method getCodeElement:()Lca/uhn/fhir/model/primitive/BoundCodeDt;
       4: invokevirtual #59                 // Method ca/uhn/fhir/model/primitive/BoundCodeDt.getValue:()Ljava/lang/Object;
       7: checkcast     #63                 // class java/lang/String
      10: areturn

  public ca.uhn.fhir.model.dstu2.resource.OperationOutcome$Issue setCode(ca.uhn.fhir.model.primitive.BoundCodeDt<ca.uhn.fhir.model.dstu2.valueset.IssueTypeEnum>);
    Code:
       0: aload_0
       1: aload_1
       2: putfield      #19                 // Field myCode:Lca/uhn/fhir/model/primitive/BoundCodeDt;
       5: aload_0
       6: areturn

  public ca.uhn.fhir.model.dstu2.resource.OperationOutcome$Issue setCode(ca.uhn.fhir.model.dstu2.valueset.IssueTypeEnum);
    Code:
       0: aload_0
       1: new           #44                 // class ca/uhn/fhir/model/primitive/BoundCodeDt
       4: dup
       5: getstatic     #72                 // Field ca/uhn/fhir/model/dstu2/valueset/IssueTypeEnum.VALUESET_BINDER:Lca/uhn/fhir/model/api/IValueSetEnumBinder;
       8: aload_1
       9: invokespecial #65                 // Method ca/uhn/fhir/model/primitive/BoundCodeDt."<init>":(Lca/uhn/fhir/model/api/IValueSetEnumBinder;Ljava/lang/Enum;)V
      12: invokevirtual #78                 // Method setCode:(Lca/uhn/fhir/model/primitive/BoundCodeDt;)Lca/uhn/fhir/model/dstu2/resource/OperationOutcome$Issue;
      15: pop
      16: aload_0
      17: areturn

  public ca.uhn.fhir.model.dstu2.composite.CodeableConceptDt getDetails();
    Code:
       0: aload_0
       1: getfield      #22                 // Field myDetails:Lca/uhn/fhir/model/dstu2/composite/CodeableConceptDt;
       4: ifnonnull     18
       7: aload_0
       8: new           #81                 // class ca/uhn/fhir/model/dstu2/composite/CodeableConceptDt
      11: dup
      12: invokespecial #83                 // Method ca/uhn/fhir/model/dstu2/composite/CodeableConceptDt."<init>":()V
      15: putfield      #22                 // Field myDetails:Lca/uhn/fhir/model/dstu2/composite/CodeableConceptDt;
      18: aload_0
      19: getfield      #22                 // Field myDetails:Lca/uhn/fhir/model/dstu2/composite/CodeableConceptDt;
      22: areturn

  public ca.uhn.fhir.model.dstu2.resource.OperationOutcome$Issue setDetails(ca.uhn.fhir.model.dstu2.composite.CodeableConceptDt);
    Code:
       0: aload_0
       1: aload_1
       2: putfield      #22                 // Field myDetails:Lca/uhn/fhir/model/dstu2/composite/CodeableConceptDt;
       5: aload_0
       6: areturn

  public ca.uhn.fhir.model.primitive.StringDt getDiagnosticsElement();
    Code:
       0: aload_0
       1: getfield      #26                 // Field myDiagnostics:Lca/uhn/fhir/model/primitive/StringDt;
       4: ifnonnull     18
       7: aload_0
       8: new           #84                 // class ca/uhn/fhir/model/primitive/StringDt
      11: dup
      12: invokespecial #86                 // Method ca/uhn/fhir/model/primitive/StringDt."<init>":()V
      15: putfield      #26                 // Field myDiagnostics:Lca/uhn/fhir/model/primitive/StringDt;
      18: aload_0
      19: getfield      #26                 // Field myDiagnostics:Lca/uhn/fhir/model/primitive/StringDt;
      22: areturn

  public java.lang.String getDiagnostics();
    Code:
       0: aload_0
       1: invokevirtual #87                 // Method getDiagnosticsElement:()Lca/uhn/fhir/model/primitive/StringDt;
       4: invokevirtual #91                 // Method ca/uhn/fhir/model/primitive/StringDt.getValue:()Ljava/lang/Object;
       7: checkcast     #63                 // class java/lang/String
      10: areturn

  public ca.uhn.fhir.model.dstu2.resource.OperationOutcome$Issue setDiagnostics(ca.uhn.fhir.model.primitive.StringDt);
    Code:
       0: aload_0
       1: aload_1
       2: putfield      #26                 // Field myDiagnostics:Lca/uhn/fhir/model/primitive/StringDt;
       5: aload_0
       6: areturn

  public ca.uhn.fhir.model.dstu2.resource.OperationOutcome$Issue setDiagnostics(java.lang.String);
    Code:
       0: aload_0
       1: new           #84                 // class ca/uhn/fhir/model/primitive/StringDt
       4: dup
       5: aload_1
       6: invokespecial #92                 // Method ca/uhn/fhir/model/primitive/StringDt."<init>":(Ljava/lang/String;)V
       9: putfield      #26                 // Field myDiagnostics:Lca/uhn/fhir/model/primitive/StringDt;
      12: aload_0
      13: areturn

  public java.util.List<ca.uhn.fhir.model.primitive.StringDt> getLocation();
    Code:
       0: aload_0
       1: getfield      #30                 // Field myLocation:Ljava/util/List;
       4: ifnonnull     18
       7: aload_0
       8: new           #95                 // class java/util/ArrayList
      11: dup
      12: invokespecial #97                 // Method java/util/ArrayList."<init>":()V
      15: putfield      #30                 // Field myLocation:Ljava/util/List;
      18: aload_0
      19: getfield      #30                 // Field myLocation:Ljava/util/List;
      22: areturn

  public ca.uhn.fhir.model.dstu2.resource.OperationOutcome$Issue setLocation(java.util.List<ca.uhn.fhir.model.primitive.StringDt>);
    Code:
       0: aload_0
       1: aload_1
       2: putfield      #30                 // Field myLocation:Ljava/util/List;
       5: aload_0
       6: areturn

  public ca.uhn.fhir.model.primitive.StringDt addLocation();
    Code:
       0: new           #84                 // class ca/uhn/fhir/model/primitive/StringDt
       3: dup
       4: invokespecial #86                 // Method ca/uhn/fhir/model/primitive/StringDt."<init>":()V
       7: astore_1
       8: aload_0
       9: invokevirtual #98                 // Method getLocation:()Ljava/util/List;
      12: aload_1
      13: invokeinterface #102,  2          // InterfaceMethod java/util/List.add:(Ljava/lang/Object;)Z
      18: pop
      19: aload_1
      20: areturn

  public ca.uhn.fhir.model.dstu2.resource.OperationOutcome$Issue addLocation(ca.uhn.fhir.model.primitive.StringDt);
    Code:
       0: aload_1
       1: ifnonnull     14
       4: new           #108                // class java/lang/NullPointerException
       7: dup
       8: ldc           #110                // String theValue must not be null
      10: invokespecial #112                // Method java/lang/NullPointerException."<init>":(Ljava/lang/String;)V
      13: athrow
      14: aload_0
      15: invokevirtual #98                 // Method getLocation:()Ljava/util/List;
      18: aload_1
      19: invokeinterface #102,  2          // InterfaceMethod java/util/List.add:(Ljava/lang/Object;)Z
      24: pop
      25: aload_0
      26: areturn

  public ca.uhn.fhir.model.primitive.StringDt getLocationFirstRep();
    Code:
       0: aload_0
       1: invokevirtual #98                 // Method getLocation:()Ljava/util/List;
       4: invokeinterface #113,  1          // InterfaceMethod java/util/List.isEmpty:()Z
       9: ifeq          17
      12: aload_0
      13: invokevirtual #115                // Method addLocation:()Lca/uhn/fhir/model/primitive/StringDt;
      16: areturn
      17: aload_0
      18: invokevirtual #98                 // Method getLocation:()Ljava/util/List;
      21: iconst_0
      22: invokeinterface #118,  2          // InterfaceMethod java/util/List.get:(I)Ljava/lang/Object;
      27: checkcast     #84                 // class ca/uhn/fhir/model/primitive/StringDt
      30: areturn

  public ca.uhn.fhir.model.dstu2.resource.OperationOutcome$Issue addLocation(java.lang.String);
    Code:
       0: aload_0
       1: getfield      #30                 // Field myLocation:Ljava/util/List;
       4: ifnonnull     18
       7: aload_0
       8: new           #95                 // class java/util/ArrayList
      11: dup
      12: invokespecial #97                 // Method java/util/ArrayList."<init>":()V
      15: putfield      #30                 // Field myLocation:Ljava/util/List;
      18: aload_0
      19: getfield      #30                 // Field myLocation:Ljava/util/List;
      22: new           #84                 // class ca/uhn/fhir/model/primitive/StringDt
      25: dup
      26: aload_1
      27: invokespecial #92                 // Method ca/uhn/fhir/model/primitive/StringDt."<init>":(Ljava/lang/String;)V
      30: invokeinterface #102,  2          // InterfaceMethod java/util/List.add:(Ljava/lang/Object;)Z
      35: pop
      36: aload_0
      37: areturn

  public ca.uhn.fhir.model.primitive.StringDt getDetailsElement();
    Code:
       0: aload_0
       1: invokevirtual #87                 // Method getDiagnosticsElement:()Lca/uhn/fhir/model/primitive/StringDt;
       4: areturn

  public ca.uhn.fhir.model.base.resource.BaseOperationOutcome$BaseIssue setDetails(java.lang.String);
    Code:
       0: aload_0
       1: aload_1
       2: invokevirtual #122                // Method setDiagnostics:(Ljava/lang/String;)Lca/uhn/fhir/model/dstu2/resource/OperationOutcome$Issue;
       5: pop
       6: aload_0
       7: areturn

  public ca.uhn.fhir.model.base.resource.BaseOperationOutcome$BaseIssue setDiagnostics(java.lang.String);
    Code:
       0: aload_0
       1: aload_1
       2: invokevirtual #122                // Method setDiagnostics:(Ljava/lang/String;)Lca/uhn/fhir/model/dstu2/resource/OperationOutcome$Issue;
       5: areturn

  public ca.uhn.fhir.model.base.resource.BaseOperationOutcome$BaseIssue addLocation(java.lang.String);
    Code:
       0: aload_0
       1: aload_1
       2: invokevirtual #126                // Method addLocation:(Ljava/lang/String;)Lca/uhn/fhir/model/dstu2/resource/OperationOutcome$Issue;
       5: areturn

  public ca.uhn.fhir.model.primitive.CodeDt getSeverityElement();
    Code:
       0: aload_0
       1: invokevirtual #55                 // Method getSeverityElement:()Lca/uhn/fhir/model/primitive/BoundCodeDt;
       4: areturn
}
