Compiled from "Organization.java"
public class ca.uhn.fhir.model.dstu2.resource.Organization$Contact extends ca.uhn.fhir.model.api.BaseIdentifiableElement implements ca.uhn.fhir.model.api.IResourceBlock {
  private ca.uhn.fhir.model.dstu2.composite.CodeableConceptDt myPurpose;

  private ca.uhn.fhir.model.dstu2.composite.HumanNameDt myName;

  private java.util.List<ca.uhn.fhir.model.dstu2.composite.ContactPointDt> myTelecom;

  private ca.uhn.fhir.model.dstu2.composite.AddressDt myAddress;

  public ca.uhn.fhir.model.dstu2.resource.Organization$Contact();
    Code:
       0: aload_0
       1: invokespecial #1                  // Method ca/uhn/fhir/model/api/BaseIdentifiableElement."<init>":()V
       4: return

  public boolean isEmpty();
    Code:
       0: aload_0
       1: invokespecial #7                  // Method ca/uhn/fhir/model/api/BaseIdentifiableElement.isBaseEmpty:()Z
       4: ifeq          49
       7: iconst_4
       8: anewarray     #11                 // class java/lang/Object
      11: dup
      12: iconst_0
      13: aload_0
      14: getfield      #13                 // Field myPurpose:Lca/uhn/fhir/model/dstu2/composite/CodeableConceptDt;
      17: aastore
      18: dup
      19: iconst_1
      20: aload_0
      21: getfield      #19                 // Field myName:Lca/uhn/fhir/model/dstu2/composite/HumanNameDt;
      24: aastore
      25: dup
      26: iconst_2
      27: aload_0
      28: getfield      #23                 // Field myTelecom:Ljava/util/List;
      31: aastore
      32: dup
      33: iconst_3
      34: aload_0
      35: getfield      #27                 // Field myAddress:Lca/uhn/fhir/model/dstu2/composite/AddressDt;
      38: aastore
      39: invokestatic  #31                 // Method ca/uhn/fhir/util/ElementUtil.isEmpty:([Ljava/lang/Object;)Z
      42: ifeq          49
      45: iconst_1
      46: goto          50
      49: iconst_0
      50: ireturn

  public <T extends ca.uhn.fhir.model.api.IElement> java.util.List<T> getAllPopulatedChildElementsOfType(java.lang.Class<T>);
    Code:
       0: aload_1
       1: iconst_4
       2: anewarray     #11                 // class java/lang/Object
       5: dup
       6: iconst_0
       7: aload_0
       8: getfield      #13                 // Field myPurpose:Lca/uhn/fhir/model/dstu2/composite/CodeableConceptDt;
      11: aastore
      12: dup
      13: iconst_1
      14: aload_0
      15: getfield      #19                 // Field myName:Lca/uhn/fhir/model/dstu2/composite/HumanNameDt;
      18: aastore
      19: dup
      20: iconst_2
      21: aload_0
      22: getfield      #23                 // Field myTelecom:Ljava/util/List;
      25: aastore
      26: dup
      27: iconst_3
      28: aload_0
      29: getfield      #27                 // Field myAddress:Lca/uhn/fhir/model/dstu2/composite/AddressDt;
      32: aastore
      33: invokestatic  #37                 // Method ca/uhn/fhir/util/ElementUtil.allPopulatedChildElements:(Ljava/lang/Class;[Ljava/lang/Object;)Ljava/util/List;
      36: areturn

  public ca.uhn.fhir.model.dstu2.composite.CodeableConceptDt getPurpose();
    Code:
       0: aload_0
       1: getfield      #13                 // Field myPurpose:Lca/uhn/fhir/model/dstu2/composite/CodeableConceptDt;
       4: ifnonnull     18
       7: aload_0
       8: new           #41                 // class ca/uhn/fhir/model/dstu2/composite/CodeableConceptDt
      11: dup
      12: invokespecial #43                 // Method ca/uhn/fhir/model/dstu2/composite/CodeableConceptDt."<init>":()V
      15: putfield      #13                 // Field myPurpose:Lca/uhn/fhir/model/dstu2/composite/CodeableConceptDt;
      18: aload_0
      19: getfield      #13                 // Field myPurpose:Lca/uhn/fhir/model/dstu2/composite/CodeableConceptDt;
      22: areturn

  public ca.uhn.fhir.model.dstu2.resource.Organization$Contact setPurpose(ca.uhn.fhir.model.dstu2.composite.CodeableConceptDt);
    Code:
       0: aload_0
       1: aload_1
       2: putfield      #13                 // Field myPurpose:Lca/uhn/fhir/model/dstu2/composite/CodeableConceptDt;
       5: aload_0
       6: areturn

  public ca.uhn.fhir.model.dstu2.composite.HumanNameDt getName();
    Code:
       0: aload_0
       1: getfield      #19                 // Field myName:Lca/uhn/fhir/model/dstu2/composite/HumanNameDt;
       4: ifnonnull     18
       7: aload_0
       8: new           #44                 // class ca/uhn/fhir/model/dstu2/composite/HumanNameDt
      11: dup
      12: invokespecial #46                 // Method ca/uhn/fhir/model/dstu2/composite/HumanNameDt."<init>":()V
      15: putfield      #19                 // Field myName:Lca/uhn/fhir/model/dstu2/composite/HumanNameDt;
      18: aload_0
      19: getfield      #19                 // Field myName:Lca/uhn/fhir/model/dstu2/composite/HumanNameDt;
      22: areturn

  public ca.uhn.fhir.model.dstu2.resource.Organization$Contact setName(ca.uhn.fhir.model.dstu2.composite.HumanNameDt);
    Code:
       0: aload_0
       1: aload_1
       2: putfield      #19                 // Field myName:Lca/uhn/fhir/model/dstu2/composite/HumanNameDt;
       5: aload_0
       6: areturn

  public java.util.List<ca.uhn.fhir.model.dstu2.composite.ContactPointDt> getTelecom();
    Code:
       0: aload_0
       1: getfield      #23                 // Field myTelecom:Ljava/util/List;
       4: ifnonnull     18
       7: aload_0
       8: new           #47                 // class java/util/ArrayList
      11: dup
      12: invokespecial #49                 // Method java/util/ArrayList."<init>":()V
      15: putfield      #23                 // Field myTelecom:Ljava/util/List;
      18: aload_0
      19: getfield      #23                 // Field myTelecom:Ljava/util/List;
      22: areturn

  public ca.uhn.fhir.model.dstu2.resource.Organization$Contact setTelecom(java.util.List<ca.uhn.fhir.model.dstu2.composite.ContactPointDt>);
    Code:
       0: aload_0
       1: aload_1
       2: putfield      #23                 // Field myTelecom:Ljava/util/List;
       5: aload_0
       6: areturn

  public ca.uhn.fhir.model.dstu2.composite.ContactPointDt addTelecom();
    Code:
       0: new           #50                 // class ca/uhn/fhir/model/dstu2/composite/ContactPointDt
       3: dup
       4: invokespecial #52                 // Method ca/uhn/fhir/model/dstu2/composite/ContactPointDt."<init>":()V
       7: astore_1
       8: aload_0
       9: invokevirtual #53                 // Method getTelecom:()Ljava/util/List;
      12: aload_1
      13: invokeinterface #57,  2           // InterfaceMethod java/util/List.add:(Ljava/lang/Object;)Z
      18: pop
      19: aload_1
      20: areturn

  public ca.uhn.fhir.model.dstu2.resource.Organization$Contact addTelecom(ca.uhn.fhir.model.dstu2.composite.ContactPointDt);
    Code:
       0: aload_1
       1: ifnonnull     14
       4: new           #63                 // class java/lang/NullPointerException
       7: dup
       8: ldc           #65                 // String theValue must not be null
      10: invokespecial #67                 // Method java/lang/NullPointerException."<init>":(Ljava/lang/String;)V
      13: athrow
      14: aload_0
      15: invokevirtual #53                 // Method getTelecom:()Ljava/util/List;
      18: aload_1
      19: invokeinterface #57,  2           // InterfaceMethod java/util/List.add:(Ljava/lang/Object;)Z
      24: pop
      25: aload_0
      26: areturn

  public ca.uhn.fhir.model.dstu2.composite.ContactPointDt getTelecomFirstRep();
    Code:
       0: aload_0
       1: invokevirtual #53                 // Method getTelecom:()Ljava/util/List;
       4: invokeinterface #70,  1           // InterfaceMethod java/util/List.isEmpty:()Z
       9: ifeq          17
      12: aload_0
      13: invokevirtual #72                 // Method addTelecom:()Lca/uhn/fhir/model/dstu2/composite/ContactPointDt;
      16: areturn
      17: aload_0
      18: invokevirtual #53                 // Method getTelecom:()Ljava/util/List;
      21: iconst_0
      22: invokeinterface #76,  2           // InterfaceMethod java/util/List.get:(I)Ljava/lang/Object;
      27: checkcast     #50                 // class ca/uhn/fhir/model/dstu2/composite/ContactPointDt
      30: areturn

  public ca.uhn.fhir.model.dstu2.composite.AddressDt getAddress();
    Code:
       0: aload_0
       1: getfield      #27                 // Field myAddress:Lca/uhn/fhir/model/dstu2/composite/AddressDt;
       4: ifnonnull     18
       7: aload_0
       8: new           #80                 // class ca/uhn/fhir/model/dstu2/composite/AddressDt
      11: dup
      12: invokespecial #82                 // Method ca/uhn/fhir/model/dstu2/composite/AddressDt."<init>":()V
      15: putfield      #27                 // Field myAddress:Lca/uhn/fhir/model/dstu2/composite/AddressDt;
      18: aload_0
      19: getfield      #27                 // Field myAddress:Lca/uhn/fhir/model/dstu2/composite/AddressDt;
      22: areturn

  public ca.uhn.fhir.model.dstu2.resource.Organization$Contact setAddress(ca.uhn.fhir.model.dstu2.composite.AddressDt);
    Code:
       0: aload_0
       1: aload_1
       2: putfield      #27                 // Field myAddress:Lca/uhn/fhir/model/dstu2/composite/AddressDt;
       5: aload_0
       6: areturn
}
