Compiled from "Subscription.java"
public class ca.uhn.fhir.model.dstu2.resource.Subscription extends ca.uhn.fhir.model.dstu2.resource.BaseResource implements ca.uhn.fhir.model.api.IResource {
  public static final java.lang.String SP_STATUS;

  public static final ca.uhn.fhir.rest.gclient.TokenClientParam STATUS;

  public static final java.lang.String SP_TYPE;

  public static final ca.uhn.fhir.rest.gclient.TokenClientParam TYPE;

  public static final java.lang.String SP_URL;

  public static final ca.uhn.fhir.rest.gclient.UriClientParam URL;

  public static final java.lang.String SP_CRITERIA;

  public static final ca.uhn.fhir.rest.gclient.StringClientParam CRITERIA;

  public static final java.lang.String SP_PAYLOAD;

  public static final ca.uhn.fhir.rest.gclient.StringClientParam PAYLOAD;

  public static final java.lang.String SP_CONTACT;

  public static final ca.uhn.fhir.rest.gclient.TokenClientParam CONTACT;

  public static final java.lang.String SP_TAG;

  public static final ca.uhn.fhir.rest.gclient.TokenClientParam TAG;

  private ca.uhn.fhir.model.primitive.StringDt myCriteria;

  private java.util.List<ca.uhn.fhir.model.dstu2.composite.ContactPointDt> myContact;

  private ca.uhn.fhir.model.primitive.StringDt myReason;

  private ca.uhn.fhir.model.primitive.BoundCodeDt<ca.uhn.fhir.model.dstu2.valueset.SubscriptionStatusEnum> myStatus;

  private ca.uhn.fhir.model.primitive.StringDt myError;

  private ca.uhn.fhir.model.dstu2.resource.Subscription$Channel myChannel;

  private ca.uhn.fhir.model.primitive.InstantDt myEnd;

  private java.util.List<ca.uhn.fhir.model.dstu2.composite.CodingDt> myTag;

  public ca.uhn.fhir.model.dstu2.resource.Subscription();
    Code:
       0: aload_0
       1: invokespecial #1                  // Method ca/uhn/fhir/model/dstu2/resource/BaseResource."<init>":()V
       4: return

  public boolean isEmpty();
    Code:
       0: aload_0
       1: invokespecial #7                  // Method ca/uhn/fhir/model/dstu2/resource/BaseResource.isBaseEmpty:()Z
       4: ifeq          80
       7: bipush        8
       9: anewarray     #11                 // class java/lang/Object
      12: dup
      13: iconst_0
      14: aload_0
      15: getfield      #13                 // Field myCriteria:Lca/uhn/fhir/model/primitive/StringDt;
      18: aastore
      19: dup
      20: iconst_1
      21: aload_0
      22: getfield      #19                 // Field myContact:Ljava/util/List;
      25: aastore
      26: dup
      27: iconst_2
      28: aload_0
      29: getfield      #23                 // Field myReason:Lca/uhn/fhir/model/primitive/StringDt;
      32: aastore
      33: dup
      34: iconst_3
      35: aload_0
      36: getfield      #26                 // Field myStatus:Lca/uhn/fhir/model/primitive/BoundCodeDt;
      39: aastore
      40: dup
      41: iconst_4
      42: aload_0
      43: getfield      #30                 // Field myError:Lca/uhn/fhir/model/primitive/StringDt;
      46: aastore
      47: dup
      48: iconst_5
      49: aload_0
      50: getfield      #33                 // Field myChannel:Lca/uhn/fhir/model/dstu2/resource/Subscription$Channel;
      53: aastore
      54: dup
      55: bipush        6
      57: aload_0
      58: getfield      #37                 // Field myEnd:Lca/uhn/fhir/model/primitive/InstantDt;
      61: aastore
      62: dup
      63: bipush        7
      65: aload_0
      66: getfield      #41                 // Field myTag:Ljava/util/List;
      69: aastore
      70: invokestatic  #44                 // Method ca/uhn/fhir/util/ElementUtil.isEmpty:([Ljava/lang/Object;)Z
      73: ifeq          80
      76: iconst_1
      77: goto          81
      80: iconst_0
      81: ireturn

  public <T extends ca.uhn.fhir.model.api.IElement> java.util.List<T> getAllPopulatedChildElementsOfType(java.lang.Class<T>);
    Code:
       0: aload_1
       1: bipush        8
       3: anewarray     #11                 // class java/lang/Object
       6: dup
       7: iconst_0
       8: aload_0
       9: getfield      #13                 // Field myCriteria:Lca/uhn/fhir/model/primitive/StringDt;
      12: aastore
      13: dup
      14: iconst_1
      15: aload_0
      16: getfield      #19                 // Field myContact:Ljava/util/List;
      19: aastore
      20: dup
      21: iconst_2
      22: aload_0
      23: getfield      #23                 // Field myReason:Lca/uhn/fhir/model/primitive/StringDt;
      26: aastore
      27: dup
      28: iconst_3
      29: aload_0
      30: getfield      #26                 // Field myStatus:Lca/uhn/fhir/model/primitive/BoundCodeDt;
      33: aastore
      34: dup
      35: iconst_4
      36: aload_0
      37: getfield      #30                 // Field myError:Lca/uhn/fhir/model/primitive/StringDt;
      40: aastore
      41: dup
      42: iconst_5
      43: aload_0
      44: getfield      #33                 // Field myChannel:Lca/uhn/fhir/model/dstu2/resource/Subscription$Channel;
      47: aastore
      48: dup
      49: bipush        6
      51: aload_0
      52: getfield      #37                 // Field myEnd:Lca/uhn/fhir/model/primitive/InstantDt;
      55: aastore
      56: dup
      57: bipush        7
      59: aload_0
      60: getfield      #41                 // Field myTag:Ljava/util/List;
      63: aastore
      64: invokestatic  #50                 // Method ca/uhn/fhir/util/ElementUtil.allPopulatedChildElements:(Ljava/lang/Class;[Ljava/lang/Object;)Ljava/util/List;
      67: areturn

  public ca.uhn.fhir.model.primitive.StringDt getCriteriaElement();
    Code:
       0: aload_0
       1: getfield      #13                 // Field myCriteria:Lca/uhn/fhir/model/primitive/StringDt;
       4: ifnonnull     18
       7: aload_0
       8: new           #54                 // class ca/uhn/fhir/model/primitive/StringDt
      11: dup
      12: invokespecial #56                 // Method ca/uhn/fhir/model/primitive/StringDt."<init>":()V
      15: putfield      #13                 // Field myCriteria:Lca/uhn/fhir/model/primitive/StringDt;
      18: aload_0
      19: getfield      #13                 // Field myCriteria:Lca/uhn/fhir/model/primitive/StringDt;
      22: areturn

  public java.lang.String getCriteria();
    Code:
       0: aload_0
       1: invokevirtual #57                 // Method getCriteriaElement:()Lca/uhn/fhir/model/primitive/StringDt;
       4: invokevirtual #61                 // Method ca/uhn/fhir/model/primitive/StringDt.getValue:()Ljava/lang/Object;
       7: checkcast     #65                 // class java/lang/String
      10: areturn

  public ca.uhn.fhir.model.dstu2.resource.Subscription setCriteria(ca.uhn.fhir.model.primitive.StringDt);
    Code:
       0: aload_0
       1: aload_1
       2: putfield      #13                 // Field myCriteria:Lca/uhn/fhir/model/primitive/StringDt;
       5: aload_0
       6: areturn

  public ca.uhn.fhir.model.dstu2.resource.Subscription setCriteria(java.lang.String);
    Code:
       0: aload_0
       1: new           #54                 // class ca/uhn/fhir/model/primitive/StringDt
       4: dup
       5: aload_1
       6: invokespecial #67                 // Method ca/uhn/fhir/model/primitive/StringDt."<init>":(Ljava/lang/String;)V
       9: putfield      #13                 // Field myCriteria:Lca/uhn/fhir/model/primitive/StringDt;
      12: aload_0
      13: areturn

  public java.util.List<ca.uhn.fhir.model.dstu2.composite.ContactPointDt> getContact();
    Code:
       0: aload_0
       1: getfield      #19                 // Field myContact:Ljava/util/List;
       4: ifnonnull     18
       7: aload_0
       8: new           #70                 // class java/util/ArrayList
      11: dup
      12: invokespecial #72                 // Method java/util/ArrayList."<init>":()V
      15: putfield      #19                 // Field myContact:Ljava/util/List;
      18: aload_0
      19: getfield      #19                 // Field myContact:Ljava/util/List;
      22: areturn

  public ca.uhn.fhir.model.dstu2.resource.Subscription setContact(java.util.List<ca.uhn.fhir.model.dstu2.composite.ContactPointDt>);
    Code:
       0: aload_0
       1: aload_1
       2: putfield      #19                 // Field myContact:Ljava/util/List;
       5: aload_0
       6: areturn

  public ca.uhn.fhir.model.dstu2.composite.ContactPointDt addContact();
    Code:
       0: new           #73                 // class ca/uhn/fhir/model/dstu2/composite/ContactPointDt
       3: dup
       4: invokespecial #75                 // Method ca/uhn/fhir/model/dstu2/composite/ContactPointDt."<init>":()V
       7: astore_1
       8: aload_0
       9: invokevirtual #76                 // Method getContact:()Ljava/util/List;
      12: aload_1
      13: invokeinterface #80,  2           // InterfaceMethod java/util/List.add:(Ljava/lang/Object;)Z
      18: pop
      19: aload_1
      20: areturn

  public ca.uhn.fhir.model.dstu2.resource.Subscription addContact(ca.uhn.fhir.model.dstu2.composite.ContactPointDt);
    Code:
       0: aload_1
       1: ifnonnull     14
       4: new           #86                 // class java/lang/NullPointerException
       7: dup
       8: ldc           #88                 // String theValue must not be null
      10: invokespecial #90                 // Method java/lang/NullPointerException."<init>":(Ljava/lang/String;)V
      13: athrow
      14: aload_0
      15: invokevirtual #76                 // Method getContact:()Ljava/util/List;
      18: aload_1
      19: invokeinterface #80,  2           // InterfaceMethod java/util/List.add:(Ljava/lang/Object;)Z
      24: pop
      25: aload_0
      26: areturn

  public ca.uhn.fhir.model.dstu2.composite.ContactPointDt getContactFirstRep();
    Code:
       0: aload_0
       1: invokevirtual #76                 // Method getContact:()Ljava/util/List;
       4: invokeinterface #91,  1           // InterfaceMethod java/util/List.isEmpty:()Z
       9: ifeq          17
      12: aload_0
      13: invokevirtual #93                 // Method addContact:()Lca/uhn/fhir/model/dstu2/composite/ContactPointDt;
      16: areturn
      17: aload_0
      18: invokevirtual #76                 // Method getContact:()Ljava/util/List;
      21: iconst_0
      22: invokeinterface #97,  2           // InterfaceMethod java/util/List.get:(I)Ljava/lang/Object;
      27: checkcast     #73                 // class ca/uhn/fhir/model/dstu2/composite/ContactPointDt
      30: areturn

  public ca.uhn.fhir.model.primitive.StringDt getReasonElement();
    Code:
       0: aload_0
       1: getfield      #23                 // Field myReason:Lca/uhn/fhir/model/primitive/StringDt;
       4: ifnonnull     18
       7: aload_0
       8: new           #54                 // class ca/uhn/fhir/model/primitive/StringDt
      11: dup
      12: invokespecial #56                 // Method ca/uhn/fhir/model/primitive/StringDt."<init>":()V
      15: putfield      #23                 // Field myReason:Lca/uhn/fhir/model/primitive/StringDt;
      18: aload_0
      19: getfield      #23                 // Field myReason:Lca/uhn/fhir/model/primitive/StringDt;
      22: areturn

  public java.lang.String getReason();
    Code:
       0: aload_0
       1: invokevirtual #101                // Method getReasonElement:()Lca/uhn/fhir/model/primitive/StringDt;
       4: invokevirtual #61                 // Method ca/uhn/fhir/model/primitive/StringDt.getValue:()Ljava/lang/Object;
       7: checkcast     #65                 // class java/lang/String
      10: areturn

  public ca.uhn.fhir.model.dstu2.resource.Subscription setReason(ca.uhn.fhir.model.primitive.StringDt);
    Code:
       0: aload_0
       1: aload_1
       2: putfield      #23                 // Field myReason:Lca/uhn/fhir/model/primitive/StringDt;
       5: aload_0
       6: areturn

  public ca.uhn.fhir.model.dstu2.resource.Subscription setReason(java.lang.String);
    Code:
       0: aload_0
       1: new           #54                 // class ca/uhn/fhir/model/primitive/StringDt
       4: dup
       5: aload_1
       6: invokespecial #67                 // Method ca/uhn/fhir/model/primitive/StringDt."<init>":(Ljava/lang/String;)V
       9: putfield      #23                 // Field myReason:Lca/uhn/fhir/model/primitive/StringDt;
      12: aload_0
      13: areturn

  public ca.uhn.fhir.model.primitive.BoundCodeDt<ca.uhn.fhir.model.dstu2.valueset.SubscriptionStatusEnum> getStatusElement();
    Code:
       0: aload_0
       1: getfield      #26                 // Field myStatus:Lca/uhn/fhir/model/primitive/BoundCodeDt;
       4: ifnonnull     21
       7: aload_0
       8: new           #104                // class ca/uhn/fhir/model/primitive/BoundCodeDt
      11: dup
      12: getstatic     #106                // Field ca/uhn/fhir/model/dstu2/valueset/SubscriptionStatusEnum.VALUESET_BINDER:Lca/uhn/fhir/model/api/IValueSetEnumBinder;
      15: invokespecial #112                // Method ca/uhn/fhir/model/primitive/BoundCodeDt."<init>":(Lca/uhn/fhir/model/api/IValueSetEnumBinder;)V
      18: putfield      #26                 // Field myStatus:Lca/uhn/fhir/model/primitive/BoundCodeDt;
      21: aload_0
      22: getfield      #26                 // Field myStatus:Lca/uhn/fhir/model/primitive/BoundCodeDt;
      25: areturn

  public java.lang.String getStatus();
    Code:
       0: aload_0
       1: invokevirtual #115                // Method getStatusElement:()Lca/uhn/fhir/model/primitive/BoundCodeDt;
       4: invokevirtual #119                // Method ca/uhn/fhir/model/primitive/BoundCodeDt.getValue:()Ljava/lang/Object;
       7: checkcast     #65                 // class java/lang/String
      10: areturn

  public ca.uhn.fhir.model.dstu2.resource.Subscription setStatus(ca.uhn.fhir.model.primitive.BoundCodeDt<ca.uhn.fhir.model.dstu2.valueset.SubscriptionStatusEnum>);
    Code:
       0: aload_0
       1: aload_1
       2: putfield      #26                 // Field myStatus:Lca/uhn/fhir/model/primitive/BoundCodeDt;
       5: aload_0
       6: areturn

  public ca.uhn.fhir.model.dstu2.resource.Subscription setStatus(ca.uhn.fhir.model.dstu2.valueset.SubscriptionStatusEnum);
    Code:
       0: aload_0
       1: new           #104                // class ca/uhn/fhir/model/primitive/BoundCodeDt
       4: dup
       5: getstatic     #106                // Field ca/uhn/fhir/model/dstu2/valueset/SubscriptionStatusEnum.VALUESET_BINDER:Lca/uhn/fhir/model/api/IValueSetEnumBinder;
       8: aload_1
       9: invokespecial #120                // Method ca/uhn/fhir/model/primitive/BoundCodeDt."<init>":(Lca/uhn/fhir/model/api/IValueSetEnumBinder;Ljava/lang/Enum;)V
      12: invokevirtual #123                // Method setStatus:(Lca/uhn/fhir/model/primitive/BoundCodeDt;)Lca/uhn/fhir/model/dstu2/resource/Subscription;
      15: pop
      16: aload_0
      17: areturn

  public ca.uhn.fhir.model.primitive.StringDt getErrorElement();
    Code:
       0: aload_0
       1: getfield      #30                 // Field myError:Lca/uhn/fhir/model/primitive/StringDt;
       4: ifnonnull     18
       7: aload_0
       8: new           #54                 // class ca/uhn/fhir/model/primitive/StringDt
      11: dup
      12: invokespecial #56                 // Method ca/uhn/fhir/model/primitive/StringDt."<init>":()V
      15: putfield      #30                 // Field myError:Lca/uhn/fhir/model/primitive/StringDt;
      18: aload_0
      19: getfield      #30                 // Field myError:Lca/uhn/fhir/model/primitive/StringDt;
      22: areturn

  public java.lang.String getError();
    Code:
       0: aload_0
       1: invokevirtual #127                // Method getErrorElement:()Lca/uhn/fhir/model/primitive/StringDt;
       4: invokevirtual #61                 // Method ca/uhn/fhir/model/primitive/StringDt.getValue:()Ljava/lang/Object;
       7: checkcast     #65                 // class java/lang/String
      10: areturn

  public ca.uhn.fhir.model.dstu2.resource.Subscription setError(ca.uhn.fhir.model.primitive.StringDt);
    Code:
       0: aload_0
       1: aload_1
       2: putfield      #30                 // Field myError:Lca/uhn/fhir/model/primitive/StringDt;
       5: aload_0
       6: areturn

  public ca.uhn.fhir.model.dstu2.resource.Subscription setError(java.lang.String);
    Code:
       0: aload_0
       1: new           #54                 // class ca/uhn/fhir/model/primitive/StringDt
       4: dup
       5: aload_1
       6: invokespecial #67                 // Method ca/uhn/fhir/model/primitive/StringDt."<init>":(Ljava/lang/String;)V
       9: putfield      #30                 // Field myError:Lca/uhn/fhir/model/primitive/StringDt;
      12: aload_0
      13: areturn

  public ca.uhn.fhir.model.dstu2.resource.Subscription$Channel getChannel();
    Code:
       0: aload_0
       1: getfield      #33                 // Field myChannel:Lca/uhn/fhir/model/dstu2/resource/Subscription$Channel;
       4: ifnonnull     18
       7: aload_0
       8: new           #130                // class ca/uhn/fhir/model/dstu2/resource/Subscription$Channel
      11: dup
      12: invokespecial #132                // Method ca/uhn/fhir/model/dstu2/resource/Subscription$Channel."<init>":()V
      15: putfield      #33                 // Field myChannel:Lca/uhn/fhir/model/dstu2/resource/Subscription$Channel;
      18: aload_0
      19: getfield      #33                 // Field myChannel:Lca/uhn/fhir/model/dstu2/resource/Subscription$Channel;
      22: areturn

  public ca.uhn.fhir.model.dstu2.resource.Subscription setChannel(ca.uhn.fhir.model.dstu2.resource.Subscription$Channel);
    Code:
       0: aload_0
       1: aload_1
       2: putfield      #33                 // Field myChannel:Lca/uhn/fhir/model/dstu2/resource/Subscription$Channel;
       5: aload_0
       6: areturn

  public ca.uhn.fhir.model.primitive.InstantDt getEndElement();
    Code:
       0: aload_0
       1: getfield      #37                 // Field myEnd:Lca/uhn/fhir/model/primitive/InstantDt;
       4: ifnonnull     18
       7: aload_0
       8: new           #133                // class ca/uhn/fhir/model/primitive/InstantDt
      11: dup
      12: invokespecial #135                // Method ca/uhn/fhir/model/primitive/InstantDt."<init>":()V
      15: putfield      #37                 // Field myEnd:Lca/uhn/fhir/model/primitive/InstantDt;
      18: aload_0
      19: getfield      #37                 // Field myEnd:Lca/uhn/fhir/model/primitive/InstantDt;
      22: areturn

  public java.util.Date getEnd();
    Code:
       0: aload_0
       1: invokevirtual #136                // Method getEndElement:()Lca/uhn/fhir/model/primitive/InstantDt;
       4: invokevirtual #140                // Method ca/uhn/fhir/model/primitive/InstantDt.getValue:()Ljava/lang/Object;
       7: checkcast     #141                // class java/util/Date
      10: areturn

  public ca.uhn.fhir.model.dstu2.resource.Subscription setEnd(ca.uhn.fhir.model.primitive.InstantDt);
    Code:
       0: aload_0
       1: aload_1
       2: putfield      #37                 // Field myEnd:Lca/uhn/fhir/model/primitive/InstantDt;
       5: aload_0
       6: areturn

  public ca.uhn.fhir.model.dstu2.resource.Subscription setEndWithMillisPrecision(java.util.Date);
    Code:
       0: aload_0
       1: new           #133                // class ca/uhn/fhir/model/primitive/InstantDt
       4: dup
       5: aload_1
       6: invokespecial #143                // Method ca/uhn/fhir/model/primitive/InstantDt."<init>":(Ljava/util/Date;)V
       9: putfield      #37                 // Field myEnd:Lca/uhn/fhir/model/primitive/InstantDt;
      12: aload_0
      13: areturn

  public ca.uhn.fhir.model.dstu2.resource.Subscription setEnd(java.util.Date, ca.uhn.fhir.model.api.TemporalPrecisionEnum);
    Code:
       0: aload_0
       1: new           #133                // class ca/uhn/fhir/model/primitive/InstantDt
       4: dup
       5: aload_1
       6: aload_2
       7: invokespecial #146                // Method ca/uhn/fhir/model/primitive/InstantDt."<init>":(Ljava/util/Date;Lca/uhn/fhir/model/api/TemporalPrecisionEnum;)V
      10: putfield      #37                 // Field myEnd:Lca/uhn/fhir/model/primitive/InstantDt;
      13: aload_0
      14: areturn

  public java.util.List<ca.uhn.fhir.model.dstu2.composite.CodingDt> getTag();
    Code:
       0: aload_0
       1: getfield      #41                 // Field myTag:Ljava/util/List;
       4: ifnonnull     18
       7: aload_0
       8: new           #70                 // class java/util/ArrayList
      11: dup
      12: invokespecial #72                 // Method java/util/ArrayList."<init>":()V
      15: putfield      #41                 // Field myTag:Ljava/util/List;
      18: aload_0
      19: getfield      #41                 // Field myTag:Ljava/util/List;
      22: areturn

  public ca.uhn.fhir.model.dstu2.resource.Subscription setTag(java.util.List<ca.uhn.fhir.model.dstu2.composite.CodingDt>);
    Code:
       0: aload_0
       1: aload_1
       2: putfield      #41                 // Field myTag:Ljava/util/List;
       5: aload_0
       6: areturn

  public ca.uhn.fhir.model.dstu2.composite.CodingDt addTag();
    Code:
       0: new           #149                // class ca/uhn/fhir/model/dstu2/composite/CodingDt
       3: dup
       4: invokespecial #151                // Method ca/uhn/fhir/model/dstu2/composite/CodingDt."<init>":()V
       7: astore_1
       8: aload_0
       9: invokevirtual #152                // Method getTag:()Ljava/util/List;
      12: aload_1
      13: invokeinterface #80,  2           // InterfaceMethod java/util/List.add:(Ljava/lang/Object;)Z
      18: pop
      19: aload_1
      20: areturn

  public ca.uhn.fhir.model.dstu2.resource.Subscription addTag(ca.uhn.fhir.model.dstu2.composite.CodingDt);
    Code:
       0: aload_1
       1: ifnonnull     14
       4: new           #86                 // class java/lang/NullPointerException
       7: dup
       8: ldc           #88                 // String theValue must not be null
      10: invokespecial #90                 // Method java/lang/NullPointerException."<init>":(Ljava/lang/String;)V
      13: athrow
      14: aload_0
      15: invokevirtual #152                // Method getTag:()Ljava/util/List;
      18: aload_1
      19: invokeinterface #80,  2           // InterfaceMethod java/util/List.add:(Ljava/lang/Object;)Z
      24: pop
      25: aload_0
      26: areturn

  public ca.uhn.fhir.model.dstu2.composite.CodingDt getTagFirstRep();
    Code:
       0: aload_0
       1: invokevirtual #152                // Method getTag:()Ljava/util/List;
       4: invokeinterface #91,  1           // InterfaceMethod java/util/List.isEmpty:()Z
       9: ifeq          17
      12: aload_0
      13: invokevirtual #155                // Method addTag:()Lca/uhn/fhir/model/dstu2/composite/CodingDt;
      16: areturn
      17: aload_0
      18: invokevirtual #152                // Method getTag:()Ljava/util/List;
      21: iconst_0
      22: invokeinterface #97,  2           // InterfaceMethod java/util/List.get:(I)Ljava/lang/Object;
      27: checkcast     #149                // class ca/uhn/fhir/model/dstu2/composite/CodingDt
      30: areturn

  public java.lang.String getResourceName();
    Code:
       0: ldc           #159                // String Subscription
       2: areturn

  public ca.uhn.fhir.context.FhirVersionEnum getStructureFhirVersionEnum();
    Code:
       0: getstatic     #161                // Field ca/uhn/fhir/context/FhirVersionEnum.DSTU2:Lca/uhn/fhir/context/FhirVersionEnum;
       3: areturn

  static {};
    Code:
       0: new           #167                // class ca/uhn/fhir/rest/gclient/TokenClientParam
       3: dup
       4: ldc           #169                // String status
       6: invokespecial #171                // Method ca/uhn/fhir/rest/gclient/TokenClientParam."<init>":(Ljava/lang/String;)V
       9: putstatic     #172                // Field STATUS:Lca/uhn/fhir/rest/gclient/TokenClientParam;
      12: new           #167                // class ca/uhn/fhir/rest/gclient/TokenClientParam
      15: dup
      16: ldc           #176                // String type
      18: invokespecial #171                // Method ca/uhn/fhir/rest/gclient/TokenClientParam."<init>":(Ljava/lang/String;)V
      21: putstatic     #178                // Field TYPE:Lca/uhn/fhir/rest/gclient/TokenClientParam;
      24: new           #181                // class ca/uhn/fhir/rest/gclient/UriClientParam
      27: dup
      28: ldc           #183                // String url
      30: invokespecial #185                // Method ca/uhn/fhir/rest/gclient/UriClientParam."<init>":(Ljava/lang/String;)V
      33: putstatic     #186                // Field URL:Lca/uhn/fhir/rest/gclient/UriClientParam;
      36: new           #190                // class ca/uhn/fhir/rest/gclient/StringClientParam
      39: dup
      40: ldc           #192                // String criteria
      42: invokespecial #194                // Method ca/uhn/fhir/rest/gclient/StringClientParam."<init>":(Ljava/lang/String;)V
      45: putstatic     #195                // Field CRITERIA:Lca/uhn/fhir/rest/gclient/StringClientParam;
      48: new           #190                // class ca/uhn/fhir/rest/gclient/StringClientParam
      51: dup
      52: ldc           #199                // String payload
      54: invokespecial #194                // Method ca/uhn/fhir/rest/gclient/StringClientParam."<init>":(Ljava/lang/String;)V
      57: putstatic     #201                // Field PAYLOAD:Lca/uhn/fhir/rest/gclient/StringClientParam;
      60: new           #167                // class ca/uhn/fhir/rest/gclient/TokenClientParam
      63: dup
      64: ldc           #204                // String contact
      66: invokespecial #171                // Method ca/uhn/fhir/rest/gclient/TokenClientParam."<init>":(Ljava/lang/String;)V
      69: putstatic     #206                // Field CONTACT:Lca/uhn/fhir/rest/gclient/TokenClientParam;
      72: new           #167                // class ca/uhn/fhir/rest/gclient/TokenClientParam
      75: dup
      76: ldc           #209                // String tag
      78: invokespecial #171                // Method ca/uhn/fhir/rest/gclient/TokenClientParam."<init>":(Ljava/lang/String;)V
      81: putstatic     #211                // Field TAG:Lca/uhn/fhir/rest/gclient/TokenClientParam;
      84: return
}
