Compiled from "ValueSet.java"
public class ca.uhn.fhir.model.dstu2.resource.ValueSet$Expansion extends ca.uhn.fhir.model.api.BaseIdentifiableElement implements ca.uhn.fhir.model.api.IResourceBlock {
  private ca.uhn.fhir.model.primitive.UriDt myIdentifier;

  private ca.uhn.fhir.model.primitive.DateTimeDt myTimestamp;

  private ca.uhn.fhir.model.primitive.IntegerDt myTotal;

  private ca.uhn.fhir.model.primitive.IntegerDt myOffset;

  private java.util.List<ca.uhn.fhir.model.dstu2.resource.ValueSet$ExpansionParameter> myParameter;

  private java.util.List<ca.uhn.fhir.model.dstu2.resource.ValueSet$ExpansionContains> myContains;

  public ca.uhn.fhir.model.dstu2.resource.ValueSet$Expansion();
    Code:
       0: aload_0
       1: invokespecial #1                  // Method ca/uhn/fhir/model/api/BaseIdentifiableElement."<init>":()V
       4: return

  public boolean isEmpty();
    Code:
       0: aload_0
       1: invokespecial #7                  // Method ca/uhn/fhir/model/api/BaseIdentifiableElement.isBaseEmpty:()Z
       4: ifeq          64
       7: bipush        6
       9: anewarray     #11                 // class java/lang/Object
      12: dup
      13: iconst_0
      14: aload_0
      15: getfield      #13                 // Field myIdentifier:Lca/uhn/fhir/model/primitive/UriDt;
      18: aastore
      19: dup
      20: iconst_1
      21: aload_0
      22: getfield      #19                 // Field myTimestamp:Lca/uhn/fhir/model/primitive/DateTimeDt;
      25: aastore
      26: dup
      27: iconst_2
      28: aload_0
      29: getfield      #23                 // Field myTotal:Lca/uhn/fhir/model/primitive/IntegerDt;
      32: aastore
      33: dup
      34: iconst_3
      35: aload_0
      36: getfield      #27                 // Field myOffset:Lca/uhn/fhir/model/primitive/IntegerDt;
      39: aastore
      40: dup
      41: iconst_4
      42: aload_0
      43: getfield      #30                 // Field myParameter:Ljava/util/List;
      46: aastore
      47: dup
      48: iconst_5
      49: aload_0
      50: getfield      #34                 // Field myContains:Ljava/util/List;
      53: aastore
      54: invokestatic  #37                 // Method ca/uhn/fhir/util/ElementUtil.isEmpty:([Ljava/lang/Object;)Z
      57: ifeq          64
      60: iconst_1
      61: goto          65
      64: iconst_0
      65: ireturn

  public <T extends ca.uhn.fhir.model.api.IElement> java.util.List<T> getAllPopulatedChildElementsOfType(java.lang.Class<T>);
    Code:
       0: aload_1
       1: bipush        6
       3: anewarray     #11                 // class java/lang/Object
       6: dup
       7: iconst_0
       8: aload_0
       9: getfield      #13                 // Field myIdentifier:Lca/uhn/fhir/model/primitive/UriDt;
      12: aastore
      13: dup
      14: iconst_1
      15: aload_0
      16: getfield      #19                 // Field myTimestamp:Lca/uhn/fhir/model/primitive/DateTimeDt;
      19: aastore
      20: dup
      21: iconst_2
      22: aload_0
      23: getfield      #23                 // Field myTotal:Lca/uhn/fhir/model/primitive/IntegerDt;
      26: aastore
      27: dup
      28: iconst_3
      29: aload_0
      30: getfield      #27                 // Field myOffset:Lca/uhn/fhir/model/primitive/IntegerDt;
      33: aastore
      34: dup
      35: iconst_4
      36: aload_0
      37: getfield      #30                 // Field myParameter:Ljava/util/List;
      40: aastore
      41: dup
      42: iconst_5
      43: aload_0
      44: getfield      #34                 // Field myContains:Ljava/util/List;
      47: aastore
      48: invokestatic  #43                 // Method ca/uhn/fhir/util/ElementUtil.allPopulatedChildElements:(Ljava/lang/Class;[Ljava/lang/Object;)Ljava/util/List;
      51: areturn

  public ca.uhn.fhir.model.primitive.UriDt getIdentifierElement();
    Code:
       0: aload_0
       1: getfield      #13                 // Field myIdentifier:Lca/uhn/fhir/model/primitive/UriDt;
       4: ifnonnull     18
       7: aload_0
       8: new           #47                 // class ca/uhn/fhir/model/primitive/UriDt
      11: dup
      12: invokespecial #49                 // Method ca/uhn/fhir/model/primitive/UriDt."<init>":()V
      15: putfield      #13                 // Field myIdentifier:Lca/uhn/fhir/model/primitive/UriDt;
      18: aload_0
      19: getfield      #13                 // Field myIdentifier:Lca/uhn/fhir/model/primitive/UriDt;
      22: areturn

  public java.lang.String getIdentifier();
    Code:
       0: aload_0
       1: invokevirtual #50                 // Method getIdentifierElement:()Lca/uhn/fhir/model/primitive/UriDt;
       4: invokevirtual #54                 // Method ca/uhn/fhir/model/primitive/UriDt.getValue:()Ljava/lang/Object;
       7: checkcast     #58                 // class java/lang/String
      10: areturn

  public ca.uhn.fhir.model.dstu2.resource.ValueSet$Expansion setIdentifier(ca.uhn.fhir.model.primitive.UriDt);
    Code:
       0: aload_0
       1: aload_1
       2: putfield      #13                 // Field myIdentifier:Lca/uhn/fhir/model/primitive/UriDt;
       5: aload_0
       6: areturn

  public ca.uhn.fhir.model.dstu2.resource.ValueSet$Expansion setIdentifier(java.lang.String);
    Code:
       0: aload_0
       1: new           #47                 // class ca/uhn/fhir/model/primitive/UriDt
       4: dup
       5: aload_1
       6: invokespecial #60                 // Method ca/uhn/fhir/model/primitive/UriDt."<init>":(Ljava/lang/String;)V
       9: putfield      #13                 // Field myIdentifier:Lca/uhn/fhir/model/primitive/UriDt;
      12: aload_0
      13: areturn

  public ca.uhn.fhir.model.primitive.DateTimeDt getTimestampElement();
    Code:
       0: aload_0
       1: getfield      #19                 // Field myTimestamp:Lca/uhn/fhir/model/primitive/DateTimeDt;
       4: ifnonnull     18
       7: aload_0
       8: new           #63                 // class ca/uhn/fhir/model/primitive/DateTimeDt
      11: dup
      12: invokespecial #65                 // Method ca/uhn/fhir/model/primitive/DateTimeDt."<init>":()V
      15: putfield      #19                 // Field myTimestamp:Lca/uhn/fhir/model/primitive/DateTimeDt;
      18: aload_0
      19: getfield      #19                 // Field myTimestamp:Lca/uhn/fhir/model/primitive/DateTimeDt;
      22: areturn

  public java.util.Date getTimestamp();
    Code:
       0: aload_0
       1: invokevirtual #66                 // Method getTimestampElement:()Lca/uhn/fhir/model/primitive/DateTimeDt;
       4: invokevirtual #70                 // Method ca/uhn/fhir/model/primitive/DateTimeDt.getValue:()Ljava/lang/Object;
       7: checkcast     #71                 // class java/util/Date
      10: areturn

  public ca.uhn.fhir.model.dstu2.resource.ValueSet$Expansion setTimestamp(ca.uhn.fhir.model.primitive.DateTimeDt);
    Code:
       0: aload_0
       1: aload_1
       2: putfield      #19                 // Field myTimestamp:Lca/uhn/fhir/model/primitive/DateTimeDt;
       5: aload_0
       6: areturn

  public ca.uhn.fhir.model.dstu2.resource.ValueSet$Expansion setTimestamp(java.util.Date, ca.uhn.fhir.model.api.TemporalPrecisionEnum);
    Code:
       0: aload_0
       1: new           #63                 // class ca/uhn/fhir/model/primitive/DateTimeDt
       4: dup
       5: aload_1
       6: aload_2
       7: invokespecial #73                 // Method ca/uhn/fhir/model/primitive/DateTimeDt."<init>":(Ljava/util/Date;Lca/uhn/fhir/model/api/TemporalPrecisionEnum;)V
      10: putfield      #19                 // Field myTimestamp:Lca/uhn/fhir/model/primitive/DateTimeDt;
      13: aload_0
      14: areturn

  public ca.uhn.fhir.model.dstu2.resource.ValueSet$Expansion setTimestampWithSecondsPrecision(java.util.Date);
    Code:
       0: aload_0
       1: new           #63                 // class ca/uhn/fhir/model/primitive/DateTimeDt
       4: dup
       5: aload_1
       6: invokespecial #76                 // Method ca/uhn/fhir/model/primitive/DateTimeDt."<init>":(Ljava/util/Date;)V
       9: putfield      #19                 // Field myTimestamp:Lca/uhn/fhir/model/primitive/DateTimeDt;
      12: aload_0
      13: areturn

  public ca.uhn.fhir.model.primitive.IntegerDt getTotalElement();
    Code:
       0: aload_0
       1: getfield      #23                 // Field myTotal:Lca/uhn/fhir/model/primitive/IntegerDt;
       4: ifnonnull     18
       7: aload_0
       8: new           #79                 // class ca/uhn/fhir/model/primitive/IntegerDt
      11: dup
      12: invokespecial #81                 // Method ca/uhn/fhir/model/primitive/IntegerDt."<init>":()V
      15: putfield      #23                 // Field myTotal:Lca/uhn/fhir/model/primitive/IntegerDt;
      18: aload_0
      19: getfield      #23                 // Field myTotal:Lca/uhn/fhir/model/primitive/IntegerDt;
      22: areturn

  public java.lang.Integer getTotal();
    Code:
       0: aload_0
       1: invokevirtual #82                 // Method getTotalElement:()Lca/uhn/fhir/model/primitive/IntegerDt;
       4: invokevirtual #86                 // Method ca/uhn/fhir/model/primitive/IntegerDt.getValue:()Ljava/lang/Object;
       7: checkcast     #87                 // class java/lang/Integer
      10: areturn

  public ca.uhn.fhir.model.dstu2.resource.ValueSet$Expansion setTotal(ca.uhn.fhir.model.primitive.IntegerDt);
    Code:
       0: aload_0
       1: aload_1
       2: putfield      #23                 // Field myTotal:Lca/uhn/fhir/model/primitive/IntegerDt;
       5: aload_0
       6: areturn

  public ca.uhn.fhir.model.dstu2.resource.ValueSet$Expansion setTotal(int);
    Code:
       0: aload_0
       1: new           #79                 // class ca/uhn/fhir/model/primitive/IntegerDt
       4: dup
       5: iload_1
       6: invokespecial #89                 // Method ca/uhn/fhir/model/primitive/IntegerDt."<init>":(I)V
       9: putfield      #23                 // Field myTotal:Lca/uhn/fhir/model/primitive/IntegerDt;
      12: aload_0
      13: areturn

  public ca.uhn.fhir.model.primitive.IntegerDt getOffsetElement();
    Code:
       0: aload_0
       1: getfield      #27                 // Field myOffset:Lca/uhn/fhir/model/primitive/IntegerDt;
       4: ifnonnull     18
       7: aload_0
       8: new           #79                 // class ca/uhn/fhir/model/primitive/IntegerDt
      11: dup
      12: invokespecial #81                 // Method ca/uhn/fhir/model/primitive/IntegerDt."<init>":()V
      15: putfield      #27                 // Field myOffset:Lca/uhn/fhir/model/primitive/IntegerDt;
      18: aload_0
      19: getfield      #27                 // Field myOffset:Lca/uhn/fhir/model/primitive/IntegerDt;
      22: areturn

  public java.lang.Integer getOffset();
    Code:
       0: aload_0
       1: invokevirtual #92                 // Method getOffsetElement:()Lca/uhn/fhir/model/primitive/IntegerDt;
       4: invokevirtual #86                 // Method ca/uhn/fhir/model/primitive/IntegerDt.getValue:()Ljava/lang/Object;
       7: checkcast     #87                 // class java/lang/Integer
      10: areturn

  public ca.uhn.fhir.model.dstu2.resource.ValueSet$Expansion setOffset(ca.uhn.fhir.model.primitive.IntegerDt);
    Code:
       0: aload_0
       1: aload_1
       2: putfield      #27                 // Field myOffset:Lca/uhn/fhir/model/primitive/IntegerDt;
       5: aload_0
       6: areturn

  public ca.uhn.fhir.model.dstu2.resource.ValueSet$Expansion setOffset(int);
    Code:
       0: aload_0
       1: new           #79                 // class ca/uhn/fhir/model/primitive/IntegerDt
       4: dup
       5: iload_1
       6: invokespecial #89                 // Method ca/uhn/fhir/model/primitive/IntegerDt."<init>":(I)V
       9: putfield      #27                 // Field myOffset:Lca/uhn/fhir/model/primitive/IntegerDt;
      12: aload_0
      13: areturn

  public java.util.List<ca.uhn.fhir.model.dstu2.resource.ValueSet$ExpansionParameter> getParameter();
    Code:
       0: aload_0
       1: getfield      #30                 // Field myParameter:Ljava/util/List;
       4: ifnonnull     18
       7: aload_0
       8: new           #95                 // class java/util/ArrayList
      11: dup
      12: invokespecial #97                 // Method java/util/ArrayList."<init>":()V
      15: putfield      #30                 // Field myParameter:Ljava/util/List;
      18: aload_0
      19: getfield      #30                 // Field myParameter:Ljava/util/List;
      22: areturn

  public ca.uhn.fhir.model.dstu2.resource.ValueSet$Expansion setParameter(java.util.List<ca.uhn.fhir.model.dstu2.resource.ValueSet$ExpansionParameter>);
    Code:
       0: aload_0
       1: aload_1
       2: putfield      #30                 // Field myParameter:Ljava/util/List;
       5: aload_0
       6: areturn

  public ca.uhn.fhir.model.dstu2.resource.ValueSet$ExpansionParameter addParameter();
    Code:
       0: new           #98                 // class ca/uhn/fhir/model/dstu2/resource/ValueSet$ExpansionParameter
       3: dup
       4: invokespecial #100                // Method ca/uhn/fhir/model/dstu2/resource/ValueSet$ExpansionParameter."<init>":()V
       7: astore_1
       8: aload_0
       9: invokevirtual #101                // Method getParameter:()Ljava/util/List;
      12: aload_1
      13: invokeinterface #105,  2          // InterfaceMethod java/util/List.add:(Ljava/lang/Object;)Z
      18: pop
      19: aload_1
      20: areturn

  public ca.uhn.fhir.model.dstu2.resource.ValueSet$Expansion addParameter(ca.uhn.fhir.model.dstu2.resource.ValueSet$ExpansionParameter);
    Code:
       0: aload_1
       1: ifnonnull     14
       4: new           #111                // class java/lang/NullPointerException
       7: dup
       8: ldc           #113                // String theValue must not be null
      10: invokespecial #115                // Method java/lang/NullPointerException."<init>":(Ljava/lang/String;)V
      13: athrow
      14: aload_0
      15: invokevirtual #101                // Method getParameter:()Ljava/util/List;
      18: aload_1
      19: invokeinterface #105,  2          // InterfaceMethod java/util/List.add:(Ljava/lang/Object;)Z
      24: pop
      25: aload_0
      26: areturn

  public ca.uhn.fhir.model.dstu2.resource.ValueSet$ExpansionParameter getParameterFirstRep();
    Code:
       0: aload_0
       1: invokevirtual #101                // Method getParameter:()Ljava/util/List;
       4: invokeinterface #116,  1          // InterfaceMethod java/util/List.isEmpty:()Z
       9: ifeq          17
      12: aload_0
      13: invokevirtual #118                // Method addParameter:()Lca/uhn/fhir/model/dstu2/resource/ValueSet$ExpansionParameter;
      16: areturn
      17: aload_0
      18: invokevirtual #101                // Method getParameter:()Ljava/util/List;
      21: iconst_0
      22: invokeinterface #122,  2          // InterfaceMethod java/util/List.get:(I)Ljava/lang/Object;
      27: checkcast     #98                 // class ca/uhn/fhir/model/dstu2/resource/ValueSet$ExpansionParameter
      30: areturn

  public java.util.List<ca.uhn.fhir.model.dstu2.resource.ValueSet$ExpansionContains> getContains();
    Code:
       0: aload_0
       1: getfield      #34                 // Field myContains:Ljava/util/List;
       4: ifnonnull     18
       7: aload_0
       8: new           #95                 // class java/util/ArrayList
      11: dup
      12: invokespecial #97                 // Method java/util/ArrayList."<init>":()V
      15: putfield      #34                 // Field myContains:Ljava/util/List;
      18: aload_0
      19: getfield      #34                 // Field myContains:Ljava/util/List;
      22: areturn

  public ca.uhn.fhir.model.dstu2.resource.ValueSet$Expansion setContains(java.util.List<ca.uhn.fhir.model.dstu2.resource.ValueSet$ExpansionContains>);
    Code:
       0: aload_0
       1: aload_1
       2: putfield      #34                 // Field myContains:Ljava/util/List;
       5: aload_0
       6: areturn

  public ca.uhn.fhir.model.dstu2.resource.ValueSet$ExpansionContains addContains();
    Code:
       0: new           #126                // class ca/uhn/fhir/model/dstu2/resource/ValueSet$ExpansionContains
       3: dup
       4: invokespecial #128                // Method ca/uhn/fhir/model/dstu2/resource/ValueSet$ExpansionContains."<init>":()V
       7: astore_1
       8: aload_0
       9: invokevirtual #129                // Method getContains:()Ljava/util/List;
      12: aload_1
      13: invokeinterface #105,  2          // InterfaceMethod java/util/List.add:(Ljava/lang/Object;)Z
      18: pop
      19: aload_1
      20: areturn

  public ca.uhn.fhir.model.dstu2.resource.ValueSet$Expansion addContains(ca.uhn.fhir.model.dstu2.resource.ValueSet$ExpansionContains);
    Code:
       0: aload_1
       1: ifnonnull     14
       4: new           #111                // class java/lang/NullPointerException
       7: dup
       8: ldc           #113                // String theValue must not be null
      10: invokespecial #115                // Method java/lang/NullPointerException."<init>":(Ljava/lang/String;)V
      13: athrow
      14: aload_0
      15: invokevirtual #129                // Method getContains:()Ljava/util/List;
      18: aload_1
      19: invokeinterface #105,  2          // InterfaceMethod java/util/List.add:(Ljava/lang/Object;)Z
      24: pop
      25: aload_0
      26: areturn

  public ca.uhn.fhir.model.dstu2.resource.ValueSet$ExpansionContains getContainsFirstRep();
    Code:
       0: aload_0
       1: invokevirtual #129                // Method getContains:()Ljava/util/List;
       4: invokeinterface #116,  1          // InterfaceMethod java/util/List.isEmpty:()Z
       9: ifeq          17
      12: aload_0
      13: invokevirtual #132                // Method addContains:()Lca/uhn/fhir/model/dstu2/resource/ValueSet$ExpansionContains;
      16: areturn
      17: aload_0
      18: invokevirtual #129                // Method getContains:()Ljava/util/List;
      21: iconst_0
      22: invokeinterface #122,  2          // InterfaceMethod java/util/List.get:(I)Ljava/lang/Object;
      27: checkcast     #126                // class ca/uhn/fhir/model/dstu2/resource/ValueSet$ExpansionContains
      30: areturn
}
