Compiled from "JettyNpnSslEngine.java"
final class io.netty.handler.ssl.JettyNpnSslEngine extends io.netty.handler.ssl.JdkSslEngine {
  private static boolean available;

  static boolean isAvailable();
    Code:
       0: invokestatic  #1                  // Method updateAvailability:()V
       3: getstatic     #2                  // Field available:Z
       6: ireturn

  private static void updateAvailability();
    Code:
       0: getstatic     #2                  // Field available:Z
       3: ifeq          7
       6: return
       7: ldc           #3                  // String sun.security.ssl.NextProtoNegoExtension
       9: iconst_1
      10: aconst_null
      11: invokestatic  #4                  // Method java/lang/Class.forName:(Ljava/lang/String;ZLjava/lang/ClassLoader;)Ljava/lang/Class;
      14: pop
      15: iconst_1
      16: putstatic     #2                  // Field available:Z
      19: goto          23
      22: astore_0
      23: return
    Exception table:
       from    to  target type
           7    19    22   Class java/lang/Exception

  io.netty.handler.ssl.JettyNpnSslEngine(javax.net.ssl.SSLEngine, io.netty.handler.ssl.JdkApplicationProtocolNegotiator, boolean);
    Code:
       0: aload_0
       1: aload_1
       2: invokespecial #6                  // Method io/netty/handler/ssl/JdkSslEngine."<init>":(Ljavax/net/ssl/SSLEngine;)V
       5: aload_2
       6: ldc           #7                  // String applicationNegotiator
       8: invokestatic  #8                  // Method io/netty/util/internal/ObjectUtil.checkNotNull:(Ljava/lang/Object;Ljava/lang/String;)Ljava/lang/Object;
      11: pop
      12: iload_3
      13: ifeq          62
      16: aload_2
      17: invokeinterface #9,  1            // InterfaceMethod io/netty/handler/ssl/JdkApplicationProtocolNegotiator.protocolListenerFactory:()Lio/netty/handler/ssl/JdkApplicationProtocolNegotiator$ProtocolSelectionListenerFactory;
      22: aload_0
      23: aload_2
      24: invokeinterface #10,  1           // InterfaceMethod io/netty/handler/ssl/JdkApplicationProtocolNegotiator.protocols:()Ljava/util/List;
      29: invokeinterface #11,  3           // InterfaceMethod io/netty/handler/ssl/JdkApplicationProtocolNegotiator$ProtocolSelectionListenerFactory.newListener:(Ljavax/net/ssl/SSLEngine;Ljava/util/List;)Lio/netty/handler/ssl/JdkApplicationProtocolNegotiator$ProtocolSelectionListener;
      34: ldc           #12                 // String protocolListener
      36: invokestatic  #8                  // Method io/netty/util/internal/ObjectUtil.checkNotNull:(Ljava/lang/Object;Ljava/lang/String;)Ljava/lang/Object;
      39: checkcast     #13                 // class io/netty/handler/ssl/JdkApplicationProtocolNegotiator$ProtocolSelectionListener
      42: astore        4
      44: aload_1
      45: new           #14                 // class io/netty/handler/ssl/JettyNpnSslEngine$1
      48: dup
      49: aload_0
      50: aload         4
      52: aload_2
      53: invokespecial #15                 // Method io/netty/handler/ssl/JettyNpnSslEngine$1."<init>":(Lio/netty/handler/ssl/JettyNpnSslEngine;Lio/netty/handler/ssl/JdkApplicationProtocolNegotiator$ProtocolSelectionListener;Lio/netty/handler/ssl/JdkApplicationProtocolNegotiator;)V
      56: invokestatic  #16                 // Method org/eclipse/jetty/npn/NextProtoNego.put:(Ljavax/net/ssl/SSLEngine;Lorg/eclipse/jetty/npn/NextProtoNego$Provider;)V
      59: goto          111
      62: aload_2
      63: invokeinterface #17,  1           // InterfaceMethod io/netty/handler/ssl/JdkApplicationProtocolNegotiator.protocolSelectorFactory:()Lio/netty/handler/ssl/JdkApplicationProtocolNegotiator$ProtocolSelectorFactory;
      68: aload_0
      69: new           #18                 // class java/util/LinkedHashSet
      72: dup
      73: aload_2
      74: invokeinterface #10,  1           // InterfaceMethod io/netty/handler/ssl/JdkApplicationProtocolNegotiator.protocols:()Ljava/util/List;
      79: invokespecial #19                 // Method java/util/LinkedHashSet."<init>":(Ljava/util/Collection;)V
      82: invokeinterface #20,  3           // InterfaceMethod io/netty/handler/ssl/JdkApplicationProtocolNegotiator$ProtocolSelectorFactory.newSelector:(Ljavax/net/ssl/SSLEngine;Ljava/util/Set;)Lio/netty/handler/ssl/JdkApplicationProtocolNegotiator$ProtocolSelector;
      87: ldc           #21                 // String protocolSelector
      89: invokestatic  #8                  // Method io/netty/util/internal/ObjectUtil.checkNotNull:(Ljava/lang/Object;Ljava/lang/String;)Ljava/lang/Object;
      92: checkcast     #22                 // class io/netty/handler/ssl/JdkApplicationProtocolNegotiator$ProtocolSelector
      95: astore        4
      97: aload_1
      98: new           #23                 // class io/netty/handler/ssl/JettyNpnSslEngine$2
     101: dup
     102: aload_0
     103: aload         4
     105: invokespecial #24                 // Method io/netty/handler/ssl/JettyNpnSslEngine$2."<init>":(Lio/netty/handler/ssl/JettyNpnSslEngine;Lio/netty/handler/ssl/JdkApplicationProtocolNegotiator$ProtocolSelector;)V
     108: invokestatic  #16                 // Method org/eclipse/jetty/npn/NextProtoNego.put:(Ljavax/net/ssl/SSLEngine;Lorg/eclipse/jetty/npn/NextProtoNego$Provider;)V
     111: return

  public void closeInbound() throws javax.net.ssl.SSLException;
    Code:
       0: aload_0
       1: invokevirtual #25                 // Method getWrappedEngine:()Ljavax/net/ssl/SSLEngine;
       4: invokestatic  #26                 // Method org/eclipse/jetty/npn/NextProtoNego.remove:(Ljavax/net/ssl/SSLEngine;)Lorg/eclipse/jetty/npn/NextProtoNego$Provider;
       7: pop
       8: aload_0
       9: invokespecial #27                 // Method io/netty/handler/ssl/JdkSslEngine.closeInbound:()V
      12: return

  public void closeOutbound();
    Code:
       0: aload_0
       1: invokevirtual #25                 // Method getWrappedEngine:()Ljavax/net/ssl/SSLEngine;
       4: invokestatic  #26                 // Method org/eclipse/jetty/npn/NextProtoNego.remove:(Ljavax/net/ssl/SSLEngine;)Lorg/eclipse/jetty/npn/NextProtoNego$Provider;
       7: pop
       8: aload_0
       9: invokespecial #28                 // Method io/netty/handler/ssl/JdkSslEngine.closeOutbound:()V
      12: return
}
