Compiled from "OpenSslSessionId.java"
final class io.netty.handler.ssl.OpenSslSessionId {
  private final byte[] id;

  private final int hashCode;

  static final io.netty.handler.ssl.OpenSslSessionId NULL_ID;

  io.netty.handler.ssl.OpenSslSessionId(byte[]);
    Code:
       0: aload_0
       1: invokespecial #1                  // Method java/lang/Object."<init>":()V
       4: aload_0
       5: aload_1
       6: putfield      #2                  // Field id:[B
       9: aload_0
      10: aload_1
      11: invokestatic  #3                  // Method java/util/Arrays.hashCode:([B)I
      14: putfield      #4                  // Field hashCode:I
      17: return

  public boolean equals(java.lang.Object);
    Code:
       0: aload_0
       1: aload_1
       2: if_acmpne     7
       5: iconst_1
       6: ireturn
       7: aload_1
       8: instanceof    #5                  // class io/netty/handler/ssl/OpenSslSessionId
      11: ifne          16
      14: iconst_0
      15: ireturn
      16: aload_0
      17: getfield      #2                  // Field id:[B
      20: aload_1
      21: checkcast     #5                  // class io/netty/handler/ssl/OpenSslSessionId
      24: getfield      #2                  // Field id:[B
      27: invokestatic  #6                  // Method java/util/Arrays.equals:([B[B)Z
      30: ireturn

  public java.lang.String toString();
    Code:
       0: new           #7                  // class java/lang/StringBuilder
       3: dup
       4: invokespecial #8                  // Method java/lang/StringBuilder."<init>":()V
       7: ldc           #9                  // String OpenSslSessionId{id=
       9: invokevirtual #10                 // Method java/lang/StringBuilder.append:(Ljava/lang/String;)Ljava/lang/StringBuilder;
      12: aload_0
      13: getfield      #2                  // Field id:[B
      16: invokestatic  #11                 // Method java/util/Arrays.toString:([B)Ljava/lang/String;
      19: invokevirtual #10                 // Method java/lang/StringBuilder.append:(Ljava/lang/String;)Ljava/lang/StringBuilder;
      22: bipush        125
      24: invokevirtual #12                 // Method java/lang/StringBuilder.append:(C)Ljava/lang/StringBuilder;
      27: invokevirtual #13                 // Method java/lang/StringBuilder.toString:()Ljava/lang/String;
      30: areturn

  public int hashCode();
    Code:
       0: aload_0
       1: getfield      #4                  // Field hashCode:I
       4: ireturn

  byte[] cloneBytes();
    Code:
       0: aload_0
       1: getfield      #2                  // Field id:[B
       4: invokevirtual #14                 // Method "[B".clone:()Ljava/lang/Object;
       7: checkcast     #15                 // class "[B"
      10: areturn

  static {};
    Code:
       0: new           #5                  // class io/netty/handler/ssl/OpenSslSessionId
       3: dup
       4: getstatic     #16                 // Field io/netty/util/internal/EmptyArrays.EMPTY_BYTES:[B
       7: invokespecial #17                 // Method "<init>":([B)V
      10: putstatic     #18                 // Field NULL_ID:Lio/netty/handler/ssl/OpenSslSessionId;
      13: return
}
