Compiled from "Query.java"
public interface org.hibernate.query.Query<R> extends javax.persistence.TypedQuery<R>, org.hibernate.Query<R>, org.hibernate.query.CommonQueryContract {
  public abstract org.hibernate.query.QueryProducer getProducer();

  public abstract java.util.Optional<R> uniqueResultOptional();

  public abstract java.util.stream.Stream<R> stream();

  public abstract org.hibernate.query.Query<R> setParameter(javax.persistence.Parameter<java.time.Instant>, java.time.Instant, javax.persistence.TemporalType);

  public abstract org.hibernate.query.Query<R> setParameter(javax.persistence.Parameter<java.time.LocalDateTime>, java.time.LocalDateTime, javax.persistence.TemporalType);

  public abstract org.hibernate.query.Query<R> setParameter(javax.persistence.Parameter<java.time.ZonedDateTime>, java.time.ZonedDateTime, javax.persistence.TemporalType);

  public abstract org.hibernate.query.Query<R> setParameter(javax.persistence.Parameter<java.time.OffsetDateTime>, java.time.OffsetDateTime, javax.persistence.TemporalType);

  public abstract org.hibernate.query.Query<R> setParameter(java.lang.String, java.time.Instant, javax.persistence.TemporalType);

  public abstract org.hibernate.query.Query<R> setParameter(java.lang.String, java.time.LocalDateTime, javax.persistence.TemporalType);

  public abstract org.hibernate.query.Query<R> setParameter(java.lang.String, java.time.ZonedDateTime, javax.persistence.TemporalType);

  public abstract org.hibernate.query.Query<R> setParameter(java.lang.String, java.time.OffsetDateTime, javax.persistence.TemporalType);

  public abstract org.hibernate.query.Query<R> setParameter(int, java.time.Instant, javax.persistence.TemporalType);

  public abstract org.hibernate.query.Query<R> setParameter(int, java.time.LocalDateTime, javax.persistence.TemporalType);

  public abstract org.hibernate.query.Query<R> setParameter(int, java.time.ZonedDateTime, javax.persistence.TemporalType);

  public abstract org.hibernate.query.Query<R> setParameter(int, java.time.OffsetDateTime, javax.persistence.TemporalType);

  public abstract org.hibernate.ScrollableResults scroll();

  public abstract org.hibernate.ScrollableResults scroll(org.hibernate.ScrollMode);

  public abstract java.util.List<R> list();

  public default java.util.List<R> getResultList();
    Code:
       0: aload_0
       1: invokeinterface #1,  1            // InterfaceMethod list:()Ljava/util/List;
       6: areturn

  public abstract R uniqueResult();

  public default R getSingleResult();
    Code:
       0: aload_0
       1: invokeinterface #2,  1            // InterfaceMethod uniqueResult:()Ljava/lang/Object;
       6: areturn

  public abstract org.hibernate.FlushMode getHibernateFlushMode();

  public abstract org.hibernate.CacheMode getCacheMode();

  public abstract java.lang.String getCacheRegion();

  public abstract java.lang.Integer getFetchSize();

  public abstract org.hibernate.LockOptions getLockOptions();

  public abstract java.lang.String getComment();

  public abstract java.lang.String getQueryString();

  public abstract org.hibernate.query.ParameterMetadata getParameterMetadata();

  public abstract org.hibernate.query.Query<R> setMaxResults(int);

  public abstract org.hibernate.query.Query<R> setFirstResult(int);

  public abstract org.hibernate.query.Query<R> setHint(java.lang.String, java.lang.Object);

  public abstract <T> org.hibernate.query.Query<R> setParameter(javax.persistence.Parameter<T>, T);

  public abstract org.hibernate.query.Query<R> setParameter(javax.persistence.Parameter<java.util.Calendar>, java.util.Calendar, javax.persistence.TemporalType);

  public abstract org.hibernate.query.Query<R> setParameter(javax.persistence.Parameter<java.util.Date>, java.util.Date, javax.persistence.TemporalType);

  public abstract org.hibernate.query.Query<R> setParameter(java.lang.String, java.lang.Object);

  public abstract org.hibernate.query.Query<R> setParameter(java.lang.String, java.lang.Object, org.hibernate.type.Type);

  public abstract org.hibernate.query.Query<R> setParameter(java.lang.String, java.util.Calendar, javax.persistence.TemporalType);

  public abstract org.hibernate.query.Query<R> setParameter(java.lang.String, java.util.Date, javax.persistence.TemporalType);

  public abstract org.hibernate.query.Query<R> setParameter(int, java.lang.Object);

  public abstract org.hibernate.query.Query<R> setParameter(int, java.util.Calendar, javax.persistence.TemporalType);

  public abstract org.hibernate.query.Query<R> setParameter(int, java.util.Date, javax.persistence.TemporalType);

  public abstract <T> org.hibernate.query.Query<R> setParameter(org.hibernate.query.QueryParameter<T>, T);

  public abstract <P> org.hibernate.query.Query<R> setParameter(int, P, javax.persistence.TemporalType);

  public abstract <P> org.hibernate.query.Query<R> setParameter(org.hibernate.query.QueryParameter<P>, P, org.hibernate.type.Type);

  public abstract org.hibernate.query.Query<R> setParameter(int, java.lang.Object, org.hibernate.type.Type);

  public abstract <P> org.hibernate.query.Query<R> setParameter(org.hibernate.query.QueryParameter<P>, P, javax.persistence.TemporalType);

  public abstract <P> org.hibernate.query.Query<R> setParameter(java.lang.String, P, javax.persistence.TemporalType);

  public abstract org.hibernate.query.Query<R> setFlushMode(javax.persistence.FlushModeType);

  public abstract org.hibernate.query.Query<R> setLockMode(javax.persistence.LockModeType);

  public abstract org.hibernate.query.Query<R> setReadOnly(boolean);

  public abstract org.hibernate.query.Query<R> setHibernateFlushMode(org.hibernate.FlushMode);

  public abstract org.hibernate.query.Query<R> setCacheMode(org.hibernate.CacheMode);

  public abstract org.hibernate.query.Query<R> setCacheable(boolean);

  public abstract org.hibernate.query.Query<R> setCacheRegion(java.lang.String);

  public abstract org.hibernate.query.Query<R> setTimeout(int);

  public abstract org.hibernate.query.Query<R> setFetchSize(int);

  public abstract org.hibernate.query.Query<R> setLockOptions(org.hibernate.LockOptions);

  public abstract org.hibernate.query.Query<R> setLockMode(java.lang.String, org.hibernate.LockMode);

  public abstract org.hibernate.query.Query<R> setComment(java.lang.String);

  public abstract org.hibernate.query.Query<R> addQueryHint(java.lang.String);

  public abstract <P> org.hibernate.query.Query<R> setParameterList(org.hibernate.query.QueryParameter<P>, java.util.Collection<P>);

  public abstract org.hibernate.query.Query<R> setParameterList(java.lang.String, java.util.Collection);

  public abstract org.hibernate.query.Query<R> setParameterList(java.lang.String, java.util.Collection, org.hibernate.type.Type);

  public abstract org.hibernate.query.Query<R> setParameterList(java.lang.String, java.lang.Object[], org.hibernate.type.Type);

  public abstract org.hibernate.query.Query<R> setParameterList(java.lang.String, java.lang.Object[]);

  public abstract org.hibernate.query.Query<R> setProperties(java.lang.Object);

  public abstract org.hibernate.query.Query<R> setProperties(java.util.Map);

  public default org.hibernate.query.Query<R> setFlushMode(org.hibernate.FlushMode);
    Code:
       0: aload_0
       1: aload_1
       2: invokeinterface #3,  2            // InterfaceMethod setHibernateFlushMode:(Lorg/hibernate/FlushMode;)Lorg/hibernate/query/Query;
       7: pop
       8: aload_0
       9: areturn

  public default org.hibernate.query.Query<R> setString(int, java.lang.String);
    Code:
       0: aload_0
       1: iload_1
       2: aload_2
       3: getstatic     #4                  // Field org/hibernate/type/StringType.INSTANCE:Lorg/hibernate/type/StringType;
       6: invokeinterface #5,  4            // InterfaceMethod setParameter:(ILjava/lang/Object;Lorg/hibernate/type/Type;)Lorg/hibernate/query/Query;
      11: pop
      12: aload_0
      13: areturn

  public default org.hibernate.query.Query<R> setCharacter(int, char);
    Code:
       0: aload_0
       1: iload_1
       2: iload_2
       3: invokestatic  #6                  // Method java/lang/Character.valueOf:(C)Ljava/lang/Character;
       6: getstatic     #7                  // Field org/hibernate/type/CharacterType.INSTANCE:Lorg/hibernate/type/CharacterType;
       9: invokeinterface #5,  4            // InterfaceMethod setParameter:(ILjava/lang/Object;Lorg/hibernate/type/Type;)Lorg/hibernate/query/Query;
      14: pop
      15: aload_0
      16: areturn

  public default org.hibernate.query.Query<R> setBoolean(int, boolean);
    Code:
       0: aload_0
       1: iload_1
       2: iload_2
       3: invokestatic  #8                  // Method java/lang/Boolean.valueOf:(Z)Ljava/lang/Boolean;
       6: aload_0
       7: iload_1
       8: iload_2
       9: invokestatic  #8                  // Method java/lang/Boolean.valueOf:(Z)Ljava/lang/Boolean;
      12: getstatic     #9                  // Field org/hibernate/type/BooleanType.INSTANCE:Lorg/hibernate/type/BooleanType;
      15: invokeinterface #10,  4           // InterfaceMethod determineProperBooleanType:(ILjava/lang/Object;Lorg/hibernate/type/Type;)Lorg/hibernate/type/Type;
      20: invokeinterface #5,  4            // InterfaceMethod setParameter:(ILjava/lang/Object;Lorg/hibernate/type/Type;)Lorg/hibernate/query/Query;
      25: pop
      26: aload_0
      27: areturn

  public default org.hibernate.query.Query<R> setByte(int, byte);
    Code:
       0: aload_0
       1: iload_1
       2: iload_2
       3: invokestatic  #11                 // Method java/lang/Byte.valueOf:(B)Ljava/lang/Byte;
       6: getstatic     #12                 // Field org/hibernate/type/ByteType.INSTANCE:Lorg/hibernate/type/ByteType;
       9: invokeinterface #5,  4            // InterfaceMethod setParameter:(ILjava/lang/Object;Lorg/hibernate/type/Type;)Lorg/hibernate/query/Query;
      14: pop
      15: aload_0
      16: areturn

  public default org.hibernate.query.Query<R> setShort(int, short);
    Code:
       0: aload_0
       1: iload_1
       2: iload_2
       3: invokestatic  #13                 // Method java/lang/Short.valueOf:(S)Ljava/lang/Short;
       6: getstatic     #14                 // Field org/hibernate/type/ShortType.INSTANCE:Lorg/hibernate/type/ShortType;
       9: invokeinterface #5,  4            // InterfaceMethod setParameter:(ILjava/lang/Object;Lorg/hibernate/type/Type;)Lorg/hibernate/query/Query;
      14: pop
      15: aload_0
      16: areturn

  public default org.hibernate.query.Query<R> setInteger(int, int);
    Code:
       0: aload_0
       1: iload_1
       2: iload_2
       3: invokestatic  #15                 // Method java/lang/Integer.valueOf:(I)Ljava/lang/Integer;
       6: getstatic     #16                 // Field org/hibernate/type/IntegerType.INSTANCE:Lorg/hibernate/type/IntegerType;
       9: invokeinterface #5,  4            // InterfaceMethod setParameter:(ILjava/lang/Object;Lorg/hibernate/type/Type;)Lorg/hibernate/query/Query;
      14: pop
      15: aload_0
      16: areturn

  public default org.hibernate.query.Query<R> setLong(int, long);
    Code:
       0: aload_0
       1: iload_1
       2: lload_2
       3: invokestatic  #17                 // Method java/lang/Long.valueOf:(J)Ljava/lang/Long;
       6: getstatic     #18                 // Field org/hibernate/type/LongType.INSTANCE:Lorg/hibernate/type/LongType;
       9: invokeinterface #5,  4            // InterfaceMethod setParameter:(ILjava/lang/Object;Lorg/hibernate/type/Type;)Lorg/hibernate/query/Query;
      14: pop
      15: aload_0
      16: areturn

  public default org.hibernate.query.Query<R> setFloat(int, float);
    Code:
       0: aload_0
       1: iload_1
       2: fload_2
       3: invokestatic  #19                 // Method java/lang/Float.valueOf:(F)Ljava/lang/Float;
       6: getstatic     #20                 // Field org/hibernate/type/FloatType.INSTANCE:Lorg/hibernate/type/FloatType;
       9: invokeinterface #5,  4            // InterfaceMethod setParameter:(ILjava/lang/Object;Lorg/hibernate/type/Type;)Lorg/hibernate/query/Query;
      14: pop
      15: aload_0
      16: areturn

  public default org.hibernate.query.Query<R> setDouble(int, double);
    Code:
       0: aload_0
       1: iload_1
       2: dload_2
       3: invokestatic  #21                 // Method java/lang/Double.valueOf:(D)Ljava/lang/Double;
       6: getstatic     #22                 // Field org/hibernate/type/DoubleType.INSTANCE:Lorg/hibernate/type/DoubleType;
       9: invokeinterface #5,  4            // InterfaceMethod setParameter:(ILjava/lang/Object;Lorg/hibernate/type/Type;)Lorg/hibernate/query/Query;
      14: pop
      15: aload_0
      16: areturn

  public default org.hibernate.query.Query<R> setBinary(int, byte[]);
    Code:
       0: aload_0
       1: iload_1
       2: aload_2
       3: getstatic     #23                 // Field org/hibernate/type/BinaryType.INSTANCE:Lorg/hibernate/type/BinaryType;
       6: invokeinterface #5,  4            // InterfaceMethod setParameter:(ILjava/lang/Object;Lorg/hibernate/type/Type;)Lorg/hibernate/query/Query;
      11: pop
      12: aload_0
      13: areturn

  public default org.hibernate.query.Query<R> setText(int, java.lang.String);
    Code:
       0: aload_0
       1: iload_1
       2: aload_2
       3: getstatic     #24                 // Field org/hibernate/type/TextType.INSTANCE:Lorg/hibernate/type/TextType;
       6: invokeinterface #5,  4            // InterfaceMethod setParameter:(ILjava/lang/Object;Lorg/hibernate/type/Type;)Lorg/hibernate/query/Query;
      11: pop
      12: aload_0
      13: areturn

  public default org.hibernate.query.Query<R> setSerializable(int, java.io.Serializable);
    Code:
       0: aload_0
       1: iload_1
       2: aload_2
       3: invokeinterface #25,  3           // InterfaceMethod setParameter:(ILjava/lang/Object;)Lorg/hibernate/query/Query;
       8: pop
       9: aload_0
      10: areturn

  public default org.hibernate.query.Query<R> setLocale(int, java.util.Locale);
    Code:
       0: aload_0
       1: iload_1
       2: aload_2
       3: getstatic     #26                 // Field org/hibernate/type/LocaleType.INSTANCE:Lorg/hibernate/type/LocaleType;
       6: invokeinterface #5,  4            // InterfaceMethod setParameter:(ILjava/lang/Object;Lorg/hibernate/type/Type;)Lorg/hibernate/query/Query;
      11: pop
      12: aload_0
      13: areturn

  public default org.hibernate.query.Query<R> setBigDecimal(int, java.math.BigDecimal);
    Code:
       0: aload_0
       1: iload_1
       2: aload_2
       3: getstatic     #27                 // Field org/hibernate/type/BigDecimalType.INSTANCE:Lorg/hibernate/type/BigDecimalType;
       6: invokeinterface #5,  4            // InterfaceMethod setParameter:(ILjava/lang/Object;Lorg/hibernate/type/Type;)Lorg/hibernate/query/Query;
      11: pop
      12: aload_0
      13: areturn

  public default org.hibernate.query.Query<R> setBigInteger(int, java.math.BigInteger);
    Code:
       0: aload_0
       1: iload_1
       2: aload_2
       3: getstatic     #28                 // Field org/hibernate/type/BigIntegerType.INSTANCE:Lorg/hibernate/type/BigIntegerType;
       6: invokeinterface #5,  4            // InterfaceMethod setParameter:(ILjava/lang/Object;Lorg/hibernate/type/Type;)Lorg/hibernate/query/Query;
      11: pop
      12: aload_0
      13: areturn

  public default org.hibernate.query.Query<R> setDate(int, java.util.Date);
    Code:
       0: aload_0
       1: iload_1
       2: aload_2
       3: getstatic     #29                 // Field org/hibernate/type/DateType.INSTANCE:Lorg/hibernate/type/DateType;
       6: invokeinterface #5,  4            // InterfaceMethod setParameter:(ILjava/lang/Object;Lorg/hibernate/type/Type;)Lorg/hibernate/query/Query;
      11: pop
      12: aload_0
      13: areturn

  public default org.hibernate.query.Query<R> setTime(int, java.util.Date);
    Code:
       0: aload_0
       1: iload_1
       2: aload_2
       3: getstatic     #30                 // Field org/hibernate/type/TimeType.INSTANCE:Lorg/hibernate/type/TimeType;
       6: invokeinterface #5,  4            // InterfaceMethod setParameter:(ILjava/lang/Object;Lorg/hibernate/type/Type;)Lorg/hibernate/query/Query;
      11: pop
      12: aload_0
      13: areturn

  public default org.hibernate.query.Query<R> setTimestamp(int, java.util.Date);
    Code:
       0: aload_0
       1: iload_1
       2: aload_2
       3: getstatic     #31                 // Field org/hibernate/type/TimestampType.INSTANCE:Lorg/hibernate/type/TimestampType;
       6: invokeinterface #5,  4            // InterfaceMethod setParameter:(ILjava/lang/Object;Lorg/hibernate/type/Type;)Lorg/hibernate/query/Query;
      11: pop
      12: aload_0
      13: areturn

  public default org.hibernate.query.Query<R> setCalendar(int, java.util.Calendar);
    Code:
       0: aload_0
       1: iload_1
       2: aload_2
       3: getstatic     #31                 // Field org/hibernate/type/TimestampType.INSTANCE:Lorg/hibernate/type/TimestampType;
       6: invokeinterface #5,  4            // InterfaceMethod setParameter:(ILjava/lang/Object;Lorg/hibernate/type/Type;)Lorg/hibernate/query/Query;
      11: pop
      12: aload_0
      13: areturn

  public default org.hibernate.query.Query<R> setCalendarDate(int, java.util.Calendar);
    Code:
       0: aload_0
       1: iload_1
       2: aload_2
       3: getstatic     #29                 // Field org/hibernate/type/DateType.INSTANCE:Lorg/hibernate/type/DateType;
       6: invokeinterface #5,  4            // InterfaceMethod setParameter:(ILjava/lang/Object;Lorg/hibernate/type/Type;)Lorg/hibernate/query/Query;
      11: pop
      12: aload_0
      13: areturn

  public default org.hibernate.query.Query<R> setString(java.lang.String, java.lang.String);
    Code:
       0: aload_0
       1: aload_1
       2: aload_2
       3: getstatic     #4                  // Field org/hibernate/type/StringType.INSTANCE:Lorg/hibernate/type/StringType;
       6: invokeinterface #32,  4           // InterfaceMethod setParameter:(Ljava/lang/String;Ljava/lang/Object;Lorg/hibernate/type/Type;)Lorg/hibernate/query/Query;
      11: pop
      12: aload_0
      13: areturn

  public default org.hibernate.query.Query<R> setCharacter(java.lang.String, char);
    Code:
       0: aload_0
       1: aload_1
       2: iload_2
       3: invokestatic  #6                  // Method java/lang/Character.valueOf:(C)Ljava/lang/Character;
       6: getstatic     #7                  // Field org/hibernate/type/CharacterType.INSTANCE:Lorg/hibernate/type/CharacterType;
       9: invokeinterface #32,  4           // InterfaceMethod setParameter:(Ljava/lang/String;Ljava/lang/Object;Lorg/hibernate/type/Type;)Lorg/hibernate/query/Query;
      14: pop
      15: aload_0
      16: areturn

  public default org.hibernate.query.Query<R> setBoolean(java.lang.String, boolean);
    Code:
       0: aload_0
       1: aload_1
       2: iload_2
       3: invokestatic  #8                  // Method java/lang/Boolean.valueOf:(Z)Ljava/lang/Boolean;
       6: aload_0
       7: aload_1
       8: iload_2
       9: invokestatic  #8                  // Method java/lang/Boolean.valueOf:(Z)Ljava/lang/Boolean;
      12: getstatic     #9                  // Field org/hibernate/type/BooleanType.INSTANCE:Lorg/hibernate/type/BooleanType;
      15: invokeinterface #33,  4           // InterfaceMethod determineProperBooleanType:(Ljava/lang/String;Ljava/lang/Object;Lorg/hibernate/type/Type;)Lorg/hibernate/type/Type;
      20: invokeinterface #32,  4           // InterfaceMethod setParameter:(Ljava/lang/String;Ljava/lang/Object;Lorg/hibernate/type/Type;)Lorg/hibernate/query/Query;
      25: pop
      26: aload_0
      27: areturn

  public default org.hibernate.query.Query<R> setByte(java.lang.String, byte);
    Code:
       0: aload_0
       1: aload_1
       2: iload_2
       3: invokestatic  #11                 // Method java/lang/Byte.valueOf:(B)Ljava/lang/Byte;
       6: getstatic     #12                 // Field org/hibernate/type/ByteType.INSTANCE:Lorg/hibernate/type/ByteType;
       9: invokeinterface #32,  4           // InterfaceMethod setParameter:(Ljava/lang/String;Ljava/lang/Object;Lorg/hibernate/type/Type;)Lorg/hibernate/query/Query;
      14: pop
      15: aload_0
      16: areturn

  public default org.hibernate.query.Query<R> setShort(java.lang.String, short);
    Code:
       0: aload_0
       1: aload_1
       2: iload_2
       3: invokestatic  #13                 // Method java/lang/Short.valueOf:(S)Ljava/lang/Short;
       6: getstatic     #14                 // Field org/hibernate/type/ShortType.INSTANCE:Lorg/hibernate/type/ShortType;
       9: invokeinterface #32,  4           // InterfaceMethod setParameter:(Ljava/lang/String;Ljava/lang/Object;Lorg/hibernate/type/Type;)Lorg/hibernate/query/Query;
      14: pop
      15: aload_0
      16: areturn

  public default org.hibernate.query.Query<R> setInteger(java.lang.String, int);
    Code:
       0: aload_0
       1: aload_1
       2: iload_2
       3: invokestatic  #15                 // Method java/lang/Integer.valueOf:(I)Ljava/lang/Integer;
       6: getstatic     #16                 // Field org/hibernate/type/IntegerType.INSTANCE:Lorg/hibernate/type/IntegerType;
       9: invokeinterface #32,  4           // InterfaceMethod setParameter:(Ljava/lang/String;Ljava/lang/Object;Lorg/hibernate/type/Type;)Lorg/hibernate/query/Query;
      14: pop
      15: aload_0
      16: areturn

  public default org.hibernate.query.Query<R> setLong(java.lang.String, long);
    Code:
       0: aload_0
       1: aload_1
       2: lload_2
       3: invokestatic  #17                 // Method java/lang/Long.valueOf:(J)Ljava/lang/Long;
       6: getstatic     #18                 // Field org/hibernate/type/LongType.INSTANCE:Lorg/hibernate/type/LongType;
       9: invokeinterface #32,  4           // InterfaceMethod setParameter:(Ljava/lang/String;Ljava/lang/Object;Lorg/hibernate/type/Type;)Lorg/hibernate/query/Query;
      14: pop
      15: aload_0
      16: areturn

  public default org.hibernate.query.Query<R> setFloat(java.lang.String, float);
    Code:
       0: aload_0
       1: aload_1
       2: fload_2
       3: invokestatic  #19                 // Method java/lang/Float.valueOf:(F)Ljava/lang/Float;
       6: getstatic     #20                 // Field org/hibernate/type/FloatType.INSTANCE:Lorg/hibernate/type/FloatType;
       9: invokeinterface #32,  4           // InterfaceMethod setParameter:(Ljava/lang/String;Ljava/lang/Object;Lorg/hibernate/type/Type;)Lorg/hibernate/query/Query;
      14: pop
      15: aload_0
      16: areturn

  public default org.hibernate.query.Query<R> setDouble(java.lang.String, double);
    Code:
       0: aload_0
       1: aload_1
       2: dload_2
       3: invokestatic  #21                 // Method java/lang/Double.valueOf:(D)Ljava/lang/Double;
       6: getstatic     #22                 // Field org/hibernate/type/DoubleType.INSTANCE:Lorg/hibernate/type/DoubleType;
       9: invokeinterface #32,  4           // InterfaceMethod setParameter:(Ljava/lang/String;Ljava/lang/Object;Lorg/hibernate/type/Type;)Lorg/hibernate/query/Query;
      14: pop
      15: aload_0
      16: areturn

  public default org.hibernate.query.Query<R> setBinary(java.lang.String, byte[]);
    Code:
       0: aload_0
       1: aload_1
       2: aload_2
       3: getstatic     #23                 // Field org/hibernate/type/BinaryType.INSTANCE:Lorg/hibernate/type/BinaryType;
       6: invokeinterface #32,  4           // InterfaceMethod setParameter:(Ljava/lang/String;Ljava/lang/Object;Lorg/hibernate/type/Type;)Lorg/hibernate/query/Query;
      11: pop
      12: aload_0
      13: areturn

  public default org.hibernate.query.Query<R> setText(java.lang.String, java.lang.String);
    Code:
       0: aload_0
       1: aload_1
       2: aload_2
       3: getstatic     #24                 // Field org/hibernate/type/TextType.INSTANCE:Lorg/hibernate/type/TextType;
       6: invokeinterface #32,  4           // InterfaceMethod setParameter:(Ljava/lang/String;Ljava/lang/Object;Lorg/hibernate/type/Type;)Lorg/hibernate/query/Query;
      11: pop
      12: aload_0
      13: areturn

  public default org.hibernate.query.Query<R> setSerializable(java.lang.String, java.io.Serializable);
    Code:
       0: aload_0
       1: aload_1
       2: aload_2
       3: invokeinterface #34,  3           // InterfaceMethod setParameter:(Ljava/lang/String;Ljava/lang/Object;)Lorg/hibernate/query/Query;
       8: pop
       9: aload_0
      10: areturn

  public default org.hibernate.query.Query<R> setLocale(java.lang.String, java.util.Locale);
    Code:
       0: aload_0
       1: aload_1
       2: aload_2
       3: getstatic     #24                 // Field org/hibernate/type/TextType.INSTANCE:Lorg/hibernate/type/TextType;
       6: invokeinterface #32,  4           // InterfaceMethod setParameter:(Ljava/lang/String;Ljava/lang/Object;Lorg/hibernate/type/Type;)Lorg/hibernate/query/Query;
      11: pop
      12: aload_0
      13: areturn

  public default org.hibernate.query.Query<R> setBigDecimal(java.lang.String, java.math.BigDecimal);
    Code:
       0: aload_0
       1: aload_1
       2: aload_2
       3: getstatic     #27                 // Field org/hibernate/type/BigDecimalType.INSTANCE:Lorg/hibernate/type/BigDecimalType;
       6: invokeinterface #32,  4           // InterfaceMethod setParameter:(Ljava/lang/String;Ljava/lang/Object;Lorg/hibernate/type/Type;)Lorg/hibernate/query/Query;
      11: pop
      12: aload_0
      13: areturn

  public default org.hibernate.query.Query<R> setBigInteger(java.lang.String, java.math.BigInteger);
    Code:
       0: aload_0
       1: aload_1
       2: aload_2
       3: getstatic     #28                 // Field org/hibernate/type/BigIntegerType.INSTANCE:Lorg/hibernate/type/BigIntegerType;
       6: invokeinterface #32,  4           // InterfaceMethod setParameter:(Ljava/lang/String;Ljava/lang/Object;Lorg/hibernate/type/Type;)Lorg/hibernate/query/Query;
      11: pop
      12: aload_0
      13: areturn

  public default org.hibernate.query.Query<R> setDate(java.lang.String, java.util.Date);
    Code:
       0: aload_0
       1: aload_1
       2: aload_2
       3: getstatic     #29                 // Field org/hibernate/type/DateType.INSTANCE:Lorg/hibernate/type/DateType;
       6: invokeinterface #32,  4           // InterfaceMethod setParameter:(Ljava/lang/String;Ljava/lang/Object;Lorg/hibernate/type/Type;)Lorg/hibernate/query/Query;
      11: pop
      12: aload_0
      13: areturn

  public default org.hibernate.query.Query<R> setTime(java.lang.String, java.util.Date);
    Code:
       0: aload_0
       1: aload_1
       2: aload_2
       3: getstatic     #30                 // Field org/hibernate/type/TimeType.INSTANCE:Lorg/hibernate/type/TimeType;
       6: invokeinterface #32,  4           // InterfaceMethod setParameter:(Ljava/lang/String;Ljava/lang/Object;Lorg/hibernate/type/Type;)Lorg/hibernate/query/Query;
      11: pop
      12: aload_0
      13: areturn

  public default org.hibernate.query.Query<R> setTimestamp(java.lang.String, java.util.Date);
    Code:
       0: aload_0
       1: aload_1
       2: aload_2
       3: getstatic     #31                 // Field org/hibernate/type/TimestampType.INSTANCE:Lorg/hibernate/type/TimestampType;
       6: invokeinterface #32,  4           // InterfaceMethod setParameter:(Ljava/lang/String;Ljava/lang/Object;Lorg/hibernate/type/Type;)Lorg/hibernate/query/Query;
      11: pop
      12: aload_0
      13: areturn

  public default org.hibernate.query.Query<R> setCalendar(java.lang.String, java.util.Calendar);
    Code:
       0: aload_0
       1: aload_1
       2: aload_2
       3: getstatic     #31                 // Field org/hibernate/type/TimestampType.INSTANCE:Lorg/hibernate/type/TimestampType;
       6: invokeinterface #32,  4           // InterfaceMethod setParameter:(Ljava/lang/String;Ljava/lang/Object;Lorg/hibernate/type/Type;)Lorg/hibernate/query/Query;
      11: pop
      12: aload_0
      13: areturn

  public default org.hibernate.query.Query<R> setCalendarDate(java.lang.String, java.util.Calendar);
    Code:
       0: aload_0
       1: aload_1
       2: aload_2
       3: getstatic     #29                 // Field org/hibernate/type/DateType.INSTANCE:Lorg/hibernate/type/DateType;
       6: invokeinterface #32,  4           // InterfaceMethod setParameter:(Ljava/lang/String;Ljava/lang/Object;Lorg/hibernate/type/Type;)Lorg/hibernate/query/Query;
      11: pop
      12: aload_0
      13: areturn

  public abstract org.hibernate.query.Query<R> setEntity(int, java.lang.Object);

  public abstract org.hibernate.query.Query<R> setEntity(java.lang.String, java.lang.Object);

  public abstract org.hibernate.query.Query<R> setResultTransformer(org.hibernate.transform.ResultTransformer);

  public default org.hibernate.query.Query<R> setParameters(java.lang.Object[], org.hibernate.type.Type[]);
    Code:
       0: getstatic     #35                 // Field org/hibernate/query/Query$1.$assertionsDisabled:Z
       3: ifne          21
       6: aload_1
       7: arraylength
       8: aload_2
       9: arraylength
      10: if_icmpeq     21
      13: new           #36                 // class java/lang/AssertionError
      16: dup
      17: invokespecial #37                 // Method java/lang/AssertionError."<init>":()V
      20: athrow
      21: iconst_0
      22: istore_3
      23: iload_3
      24: aload_1
      25: arraylength
      26: if_icmpge     49
      29: aload_0
      30: iload_3
      31: aload_1
      32: iload_3
      33: aaload
      34: aload_2
      35: iload_3
      36: aaload
      37: invokeinterface #5,  4            // InterfaceMethod setParameter:(ILjava/lang/Object;Lorg/hibernate/type/Type;)Lorg/hibernate/query/Query;
      42: pop
      43: iinc          3, 1
      46: goto          23
      49: aload_0
      50: areturn

  public default java.util.stream.Stream<R> getResultStream();
    Code:
       0: aload_0
       1: invokeinterface #38,  1           // InterfaceMethod stream:()Ljava/util/stream/Stream;
       6: areturn

  public default javax.persistence.TypedQuery setLockMode(javax.persistence.LockModeType);
    Code:
       0: aload_0
       1: aload_1
       2: invokeinterface #39,  2           // InterfaceMethod setLockMode:(Ljavax/persistence/LockModeType;)Lorg/hibernate/query/Query;
       7: areturn

  public default javax.persistence.TypedQuery setFlushMode(javax.persistence.FlushModeType);
    Code:
       0: aload_0
       1: aload_1
       2: invokeinterface #40,  2           // InterfaceMethod setFlushMode:(Ljavax/persistence/FlushModeType;)Lorg/hibernate/query/Query;
       7: areturn

  public default javax.persistence.TypedQuery setParameter(int, java.util.Date, javax.persistence.TemporalType);
    Code:
       0: aload_0
       1: iload_1
       2: aload_2
       3: aload_3
       4: invokeinterface #41,  4           // InterfaceMethod setParameter:(ILjava/util/Date;Ljavax/persistence/TemporalType;)Lorg/hibernate/query/Query;
       9: areturn

  public default javax.persistence.TypedQuery setParameter(int, java.util.Calendar, javax.persistence.TemporalType);
    Code:
       0: aload_0
       1: iload_1
       2: aload_2
       3: aload_3
       4: invokeinterface #42,  4           // InterfaceMethod setParameter:(ILjava/util/Calendar;Ljavax/persistence/TemporalType;)Lorg/hibernate/query/Query;
       9: areturn

  public default javax.persistence.TypedQuery setParameter(int, java.lang.Object);
    Code:
       0: aload_0
       1: iload_1
       2: aload_2
       3: invokeinterface #25,  3           // InterfaceMethod setParameter:(ILjava/lang/Object;)Lorg/hibernate/query/Query;
       8: areturn

  public default javax.persistence.TypedQuery setParameter(java.lang.String, java.util.Date, javax.persistence.TemporalType);
    Code:
       0: aload_0
       1: aload_1
       2: aload_2
       3: aload_3
       4: invokeinterface #43,  4           // InterfaceMethod setParameter:(Ljava/lang/String;Ljava/util/Date;Ljavax/persistence/TemporalType;)Lorg/hibernate/query/Query;
       9: areturn

  public default javax.persistence.TypedQuery setParameter(java.lang.String, java.util.Calendar, javax.persistence.TemporalType);
    Code:
       0: aload_0
       1: aload_1
       2: aload_2
       3: aload_3
       4: invokeinterface #44,  4           // InterfaceMethod setParameter:(Ljava/lang/String;Ljava/util/Calendar;Ljavax/persistence/TemporalType;)Lorg/hibernate/query/Query;
       9: areturn

  public default javax.persistence.TypedQuery setParameter(java.lang.String, java.lang.Object);
    Code:
       0: aload_0
       1: aload_1
       2: aload_2
       3: invokeinterface #34,  3           // InterfaceMethod setParameter:(Ljava/lang/String;Ljava/lang/Object;)Lorg/hibernate/query/Query;
       8: areturn

  public default javax.persistence.TypedQuery setParameter(javax.persistence.Parameter, java.util.Date, javax.persistence.TemporalType);
    Code:
       0: aload_0
       1: aload_1
       2: aload_2
       3: aload_3
       4: invokeinterface #45,  4           // InterfaceMethod setParameter:(Ljavax/persistence/Parameter;Ljava/util/Date;Ljavax/persistence/TemporalType;)Lorg/hibernate/query/Query;
       9: areturn

  public default javax.persistence.TypedQuery setParameter(javax.persistence.Parameter, java.util.Calendar, javax.persistence.TemporalType);
    Code:
       0: aload_0
       1: aload_1
       2: aload_2
       3: aload_3
       4: invokeinterface #46,  4           // InterfaceMethod setParameter:(Ljavax/persistence/Parameter;Ljava/util/Calendar;Ljavax/persistence/TemporalType;)Lorg/hibernate/query/Query;
       9: areturn

  public default javax.persistence.TypedQuery setParameter(javax.persistence.Parameter, java.lang.Object);
    Code:
       0: aload_0
       1: aload_1
       2: aload_2
       3: invokeinterface #47,  3           // InterfaceMethod setParameter:(Ljavax/persistence/Parameter;Ljava/lang/Object;)Lorg/hibernate/query/Query;
       8: areturn

  public default javax.persistence.TypedQuery setHint(java.lang.String, java.lang.Object);
    Code:
       0: aload_0
       1: aload_1
       2: aload_2
       3: invokeinterface #48,  3           // InterfaceMethod setHint:(Ljava/lang/String;Ljava/lang/Object;)Lorg/hibernate/query/Query;
       8: areturn

  public default javax.persistence.TypedQuery setFirstResult(int);
    Code:
       0: aload_0
       1: iload_1
       2: invokeinterface #49,  2           // InterfaceMethod setFirstResult:(I)Lorg/hibernate/query/Query;
       7: areturn

  public default javax.persistence.TypedQuery setMaxResults(int);
    Code:
       0: aload_0
       1: iload_1
       2: invokeinterface #50,  2           // InterfaceMethod setMaxResults:(I)Lorg/hibernate/query/Query;
       7: areturn

  public default javax.persistence.Query setLockMode(javax.persistence.LockModeType);
    Code:
       0: aload_0
       1: aload_1
       2: invokeinterface #39,  2           // InterfaceMethod setLockMode:(Ljavax/persistence/LockModeType;)Lorg/hibernate/query/Query;
       7: areturn

  public default javax.persistence.Query setFlushMode(javax.persistence.FlushModeType);
    Code:
       0: aload_0
       1: aload_1
       2: invokeinterface #40,  2           // InterfaceMethod setFlushMode:(Ljavax/persistence/FlushModeType;)Lorg/hibernate/query/Query;
       7: areturn

  public default javax.persistence.Query setParameter(int, java.util.Date, javax.persistence.TemporalType);
    Code:
       0: aload_0
       1: iload_1
       2: aload_2
       3: aload_3
       4: invokeinterface #41,  4           // InterfaceMethod setParameter:(ILjava/util/Date;Ljavax/persistence/TemporalType;)Lorg/hibernate/query/Query;
       9: areturn

  public default javax.persistence.Query setParameter(int, java.util.Calendar, javax.persistence.TemporalType);
    Code:
       0: aload_0
       1: iload_1
       2: aload_2
       3: aload_3
       4: invokeinterface #42,  4           // InterfaceMethod setParameter:(ILjava/util/Calendar;Ljavax/persistence/TemporalType;)Lorg/hibernate/query/Query;
       9: areturn

  public default javax.persistence.Query setParameter(int, java.lang.Object);
    Code:
       0: aload_0
       1: iload_1
       2: aload_2
       3: invokeinterface #25,  3           // InterfaceMethod setParameter:(ILjava/lang/Object;)Lorg/hibernate/query/Query;
       8: areturn

  public default javax.persistence.Query setParameter(java.lang.String, java.util.Date, javax.persistence.TemporalType);
    Code:
       0: aload_0
       1: aload_1
       2: aload_2
       3: aload_3
       4: invokeinterface #43,  4           // InterfaceMethod setParameter:(Ljava/lang/String;Ljava/util/Date;Ljavax/persistence/TemporalType;)Lorg/hibernate/query/Query;
       9: areturn

  public default javax.persistence.Query setParameter(java.lang.String, java.util.Calendar, javax.persistence.TemporalType);
    Code:
       0: aload_0
       1: aload_1
       2: aload_2
       3: aload_3
       4: invokeinterface #44,  4           // InterfaceMethod setParameter:(Ljava/lang/String;Ljava/util/Calendar;Ljavax/persistence/TemporalType;)Lorg/hibernate/query/Query;
       9: areturn

  public default javax.persistence.Query setParameter(java.lang.String, java.lang.Object);
    Code:
       0: aload_0
       1: aload_1
       2: aload_2
       3: invokeinterface #34,  3           // InterfaceMethod setParameter:(Ljava/lang/String;Ljava/lang/Object;)Lorg/hibernate/query/Query;
       8: areturn

  public default javax.persistence.Query setParameter(javax.persistence.Parameter, java.util.Date, javax.persistence.TemporalType);
    Code:
       0: aload_0
       1: aload_1
       2: aload_2
       3: aload_3
       4: invokeinterface #45,  4           // InterfaceMethod setParameter:(Ljavax/persistence/Parameter;Ljava/util/Date;Ljavax/persistence/TemporalType;)Lorg/hibernate/query/Query;
       9: areturn

  public default javax.persistence.Query setParameter(javax.persistence.Parameter, java.util.Calendar, javax.persistence.TemporalType);
    Code:
       0: aload_0
       1: aload_1
       2: aload_2
       3: aload_3
       4: invokeinterface #46,  4           // InterfaceMethod setParameter:(Ljavax/persistence/Parameter;Ljava/util/Calendar;Ljavax/persistence/TemporalType;)Lorg/hibernate/query/Query;
       9: areturn

  public default javax.persistence.Query setParameter(javax.persistence.Parameter, java.lang.Object);
    Code:
       0: aload_0
       1: aload_1
       2: aload_2
       3: invokeinterface #47,  3           // InterfaceMethod setParameter:(Ljavax/persistence/Parameter;Ljava/lang/Object;)Lorg/hibernate/query/Query;
       8: areturn

  public default javax.persistence.Query setHint(java.lang.String, java.lang.Object);
    Code:
       0: aload_0
       1: aload_1
       2: aload_2
       3: invokeinterface #48,  3           // InterfaceMethod setHint:(Ljava/lang/String;Ljava/lang/Object;)Lorg/hibernate/query/Query;
       8: areturn

  public default javax.persistence.Query setFirstResult(int);
    Code:
       0: aload_0
       1: iload_1
       2: invokeinterface #49,  2           // InterfaceMethod setFirstResult:(I)Lorg/hibernate/query/Query;
       7: areturn

  public default javax.persistence.Query setMaxResults(int);
    Code:
       0: aload_0
       1: iload_1
       2: invokeinterface #50,  2           // InterfaceMethod setMaxResults:(I)Lorg/hibernate/query/Query;
       7: areturn

  public default org.hibernate.Query setParameters(java.lang.Object[], org.hibernate.type.Type[]);
    Code:
       0: aload_0
       1: aload_1
       2: aload_2
       3: invokeinterface #51,  3           // InterfaceMethod setParameters:([Ljava/lang/Object;[Lorg/hibernate/type/Type;)Lorg/hibernate/query/Query;
       8: areturn

  public default org.hibernate.Query setResultTransformer(org.hibernate.transform.ResultTransformer);
    Code:
       0: aload_0
       1: aload_1
       2: invokeinterface #52,  2           // InterfaceMethod setResultTransformer:(Lorg/hibernate/transform/ResultTransformer;)Lorg/hibernate/query/Query;
       7: areturn

  public default org.hibernate.Query setEntity(java.lang.String, java.lang.Object);
    Code:
       0: aload_0
       1: aload_1
       2: aload_2
       3: invokeinterface #53,  3           // InterfaceMethod setEntity:(Ljava/lang/String;Ljava/lang/Object;)Lorg/hibernate/query/Query;
       8: areturn

  public default org.hibernate.Query setEntity(int, java.lang.Object);
    Code:
       0: aload_0
       1: iload_1
       2: aload_2
       3: invokeinterface #54,  3           // InterfaceMethod setEntity:(ILjava/lang/Object;)Lorg/hibernate/query/Query;
       8: areturn

  public default org.hibernate.Query setCalendarDate(java.lang.String, java.util.Calendar);
    Code:
       0: aload_0
       1: aload_1
       2: aload_2
       3: invokeinterface #55,  3           // InterfaceMethod setCalendarDate:(Ljava/lang/String;Ljava/util/Calendar;)Lorg/hibernate/query/Query;
       8: areturn

  public default org.hibernate.Query setCalendar(java.lang.String, java.util.Calendar);
    Code:
       0: aload_0
       1: aload_1
       2: aload_2
       3: invokeinterface #56,  3           // InterfaceMethod setCalendar:(Ljava/lang/String;Ljava/util/Calendar;)Lorg/hibernate/query/Query;
       8: areturn

  public default org.hibernate.Query setTimestamp(java.lang.String, java.util.Date);
    Code:
       0: aload_0
       1: aload_1
       2: aload_2
       3: invokeinterface #57,  3           // InterfaceMethod setTimestamp:(Ljava/lang/String;Ljava/util/Date;)Lorg/hibernate/query/Query;
       8: areturn

  public default org.hibernate.Query setTime(java.lang.String, java.util.Date);
    Code:
       0: aload_0
       1: aload_1
       2: aload_2
       3: invokeinterface #58,  3           // InterfaceMethod setTime:(Ljava/lang/String;Ljava/util/Date;)Lorg/hibernate/query/Query;
       8: areturn

  public default org.hibernate.Query setDate(java.lang.String, java.util.Date);
    Code:
       0: aload_0
       1: aload_1
       2: aload_2
       3: invokeinterface #59,  3           // InterfaceMethod setDate:(Ljava/lang/String;Ljava/util/Date;)Lorg/hibernate/query/Query;
       8: areturn

  public default org.hibernate.Query setBigInteger(java.lang.String, java.math.BigInteger);
    Code:
       0: aload_0
       1: aload_1
       2: aload_2
       3: invokeinterface #60,  3           // InterfaceMethod setBigInteger:(Ljava/lang/String;Ljava/math/BigInteger;)Lorg/hibernate/query/Query;
       8: areturn

  public default org.hibernate.Query setBigDecimal(java.lang.String, java.math.BigDecimal);
    Code:
       0: aload_0
       1: aload_1
       2: aload_2
       3: invokeinterface #61,  3           // InterfaceMethod setBigDecimal:(Ljava/lang/String;Ljava/math/BigDecimal;)Lorg/hibernate/query/Query;
       8: areturn

  public default org.hibernate.Query setLocale(java.lang.String, java.util.Locale);
    Code:
       0: aload_0
       1: aload_1
       2: aload_2
       3: invokeinterface #62,  3           // InterfaceMethod setLocale:(Ljava/lang/String;Ljava/util/Locale;)Lorg/hibernate/query/Query;
       8: areturn

  public default org.hibernate.Query setSerializable(java.lang.String, java.io.Serializable);
    Code:
       0: aload_0
       1: aload_1
       2: aload_2
       3: invokeinterface #63,  3           // InterfaceMethod setSerializable:(Ljava/lang/String;Ljava/io/Serializable;)Lorg/hibernate/query/Query;
       8: areturn

  public default org.hibernate.Query setText(java.lang.String, java.lang.String);
    Code:
       0: aload_0
       1: aload_1
       2: aload_2
       3: invokeinterface #64,  3           // InterfaceMethod setText:(Ljava/lang/String;Ljava/lang/String;)Lorg/hibernate/query/Query;
       8: areturn

  public default org.hibernate.Query setBinary(java.lang.String, byte[]);
    Code:
       0: aload_0
       1: aload_1
       2: aload_2
       3: invokeinterface #65,  3           // InterfaceMethod setBinary:(Ljava/lang/String;[B)Lorg/hibernate/query/Query;
       8: areturn

  public default org.hibernate.Query setDouble(java.lang.String, double);
    Code:
       0: aload_0
       1: aload_1
       2: dload_2
       3: invokeinterface #66,  4           // InterfaceMethod setDouble:(Ljava/lang/String;D)Lorg/hibernate/query/Query;
       8: areturn

  public default org.hibernate.Query setFloat(java.lang.String, float);
    Code:
       0: aload_0
       1: aload_1
       2: fload_2
       3: invokeinterface #67,  3           // InterfaceMethod setFloat:(Ljava/lang/String;F)Lorg/hibernate/query/Query;
       8: areturn

  public default org.hibernate.Query setLong(java.lang.String, long);
    Code:
       0: aload_0
       1: aload_1
       2: lload_2
       3: invokeinterface #68,  4           // InterfaceMethod setLong:(Ljava/lang/String;J)Lorg/hibernate/query/Query;
       8: areturn

  public default org.hibernate.Query setInteger(java.lang.String, int);
    Code:
       0: aload_0
       1: aload_1
       2: iload_2
       3: invokeinterface #69,  3           // InterfaceMethod setInteger:(Ljava/lang/String;I)Lorg/hibernate/query/Query;
       8: areturn

  public default org.hibernate.Query setShort(java.lang.String, short);
    Code:
       0: aload_0
       1: aload_1
       2: iload_2
       3: invokeinterface #70,  3           // InterfaceMethod setShort:(Ljava/lang/String;S)Lorg/hibernate/query/Query;
       8: areturn

  public default org.hibernate.Query setByte(java.lang.String, byte);
    Code:
       0: aload_0
       1: aload_1
       2: iload_2
       3: invokeinterface #71,  3           // InterfaceMethod setByte:(Ljava/lang/String;B)Lorg/hibernate/query/Query;
       8: areturn

  public default org.hibernate.Query setBoolean(java.lang.String, boolean);
    Code:
       0: aload_0
       1: aload_1
       2: iload_2
       3: invokeinterface #72,  3           // InterfaceMethod setBoolean:(Ljava/lang/String;Z)Lorg/hibernate/query/Query;
       8: areturn

  public default org.hibernate.Query setCharacter(java.lang.String, char);
    Code:
       0: aload_0
       1: aload_1
       2: iload_2
       3: invokeinterface #73,  3           // InterfaceMethod setCharacter:(Ljava/lang/String;C)Lorg/hibernate/query/Query;
       8: areturn

  public default org.hibernate.Query setString(java.lang.String, java.lang.String);
    Code:
       0: aload_0
       1: aload_1
       2: aload_2
       3: invokeinterface #74,  3           // InterfaceMethod setString:(Ljava/lang/String;Ljava/lang/String;)Lorg/hibernate/query/Query;
       8: areturn

  public default org.hibernate.Query setCalendarDate(int, java.util.Calendar);
    Code:
       0: aload_0
       1: iload_1
       2: aload_2
       3: invokeinterface #75,  3           // InterfaceMethod setCalendarDate:(ILjava/util/Calendar;)Lorg/hibernate/query/Query;
       8: areturn

  public default org.hibernate.Query setCalendar(int, java.util.Calendar);
    Code:
       0: aload_0
       1: iload_1
       2: aload_2
       3: invokeinterface #76,  3           // InterfaceMethod setCalendar:(ILjava/util/Calendar;)Lorg/hibernate/query/Query;
       8: areturn

  public default org.hibernate.Query setTimestamp(int, java.util.Date);
    Code:
       0: aload_0
       1: iload_1
       2: aload_2
       3: invokeinterface #77,  3           // InterfaceMethod setTimestamp:(ILjava/util/Date;)Lorg/hibernate/query/Query;
       8: areturn

  public default org.hibernate.Query setTime(int, java.util.Date);
    Code:
       0: aload_0
       1: iload_1
       2: aload_2
       3: invokeinterface #78,  3           // InterfaceMethod setTime:(ILjava/util/Date;)Lorg/hibernate/query/Query;
       8: areturn

  public default org.hibernate.Query setDate(int, java.util.Date);
    Code:
       0: aload_0
       1: iload_1
       2: aload_2
       3: invokeinterface #79,  3           // InterfaceMethod setDate:(ILjava/util/Date;)Lorg/hibernate/query/Query;
       8: areturn

  public default org.hibernate.Query setBigInteger(int, java.math.BigInteger);
    Code:
       0: aload_0
       1: iload_1
       2: aload_2
       3: invokeinterface #80,  3           // InterfaceMethod setBigInteger:(ILjava/math/BigInteger;)Lorg/hibernate/query/Query;
       8: areturn

  public default org.hibernate.Query setBigDecimal(int, java.math.BigDecimal);
    Code:
       0: aload_0
       1: iload_1
       2: aload_2
       3: invokeinterface #81,  3           // InterfaceMethod setBigDecimal:(ILjava/math/BigDecimal;)Lorg/hibernate/query/Query;
       8: areturn

  public default org.hibernate.Query setLocale(int, java.util.Locale);
    Code:
       0: aload_0
       1: iload_1
       2: aload_2
       3: invokeinterface #82,  3           // InterfaceMethod setLocale:(ILjava/util/Locale;)Lorg/hibernate/query/Query;
       8: areturn

  public default org.hibernate.Query setSerializable(int, java.io.Serializable);
    Code:
       0: aload_0
       1: iload_1
       2: aload_2
       3: invokeinterface #83,  3           // InterfaceMethod setSerializable:(ILjava/io/Serializable;)Lorg/hibernate/query/Query;
       8: areturn

  public default org.hibernate.Query setText(int, java.lang.String);
    Code:
       0: aload_0
       1: iload_1
       2: aload_2
       3: invokeinterface #84,  3           // InterfaceMethod setText:(ILjava/lang/String;)Lorg/hibernate/query/Query;
       8: areturn

  public default org.hibernate.Query setBinary(int, byte[]);
    Code:
       0: aload_0
       1: iload_1
       2: aload_2
       3: invokeinterface #85,  3           // InterfaceMethod setBinary:(I[B)Lorg/hibernate/query/Query;
       8: areturn

  public default org.hibernate.Query setDouble(int, double);
    Code:
       0: aload_0
       1: iload_1
       2: dload_2
       3: invokeinterface #86,  4           // InterfaceMethod setDouble:(ID)Lorg/hibernate/query/Query;
       8: areturn

  public default org.hibernate.Query setFloat(int, float);
    Code:
       0: aload_0
       1: iload_1
       2: fload_2
       3: invokeinterface #87,  3           // InterfaceMethod setFloat:(IF)Lorg/hibernate/query/Query;
       8: areturn

  public default org.hibernate.Query setLong(int, long);
    Code:
       0: aload_0
       1: iload_1
       2: lload_2
       3: invokeinterface #88,  4           // InterfaceMethod setLong:(IJ)Lorg/hibernate/query/Query;
       8: areturn

  public default org.hibernate.Query setInteger(int, int);
    Code:
       0: aload_0
       1: iload_1
       2: iload_2
       3: invokeinterface #89,  3           // InterfaceMethod setInteger:(II)Lorg/hibernate/query/Query;
       8: areturn

  public default org.hibernate.Query setShort(int, short);
    Code:
       0: aload_0
       1: iload_1
       2: iload_2
       3: invokeinterface #90,  3           // InterfaceMethod setShort:(IS)Lorg/hibernate/query/Query;
       8: areturn

  public default org.hibernate.Query setByte(int, byte);
    Code:
       0: aload_0
       1: iload_1
       2: iload_2
       3: invokeinterface #91,  3           // InterfaceMethod setByte:(IB)Lorg/hibernate/query/Query;
       8: areturn

  public default org.hibernate.Query setBoolean(int, boolean);
    Code:
       0: aload_0
       1: iload_1
       2: iload_2
       3: invokeinterface #92,  3           // InterfaceMethod setBoolean:(IZ)Lorg/hibernate/query/Query;
       8: areturn

  public default org.hibernate.Query setCharacter(int, char);
    Code:
       0: aload_0
       1: iload_1
       2: iload_2
       3: invokeinterface #93,  3           // InterfaceMethod setCharacter:(IC)Lorg/hibernate/query/Query;
       8: areturn

  public default org.hibernate.Query setString(int, java.lang.String);
    Code:
       0: aload_0
       1: iload_1
       2: aload_2
       3: invokeinterface #94,  3           // InterfaceMethod setString:(ILjava/lang/String;)Lorg/hibernate/query/Query;
       8: areturn

  public default org.hibernate.Query setLockMode(javax.persistence.LockModeType);
    Code:
       0: aload_0
       1: aload_1
       2: invokeinterface #39,  2           // InterfaceMethod setLockMode:(Ljavax/persistence/LockModeType;)Lorg/hibernate/query/Query;
       7: areturn

  public default org.hibernate.Query setFlushMode(javax.persistence.FlushModeType);
    Code:
       0: aload_0
       1: aload_1
       2: invokeinterface #40,  2           // InterfaceMethod setFlushMode:(Ljavax/persistence/FlushModeType;)Lorg/hibernate/query/Query;
       7: areturn

  public default org.hibernate.Query setParameter(int, java.util.Date, javax.persistence.TemporalType);
    Code:
       0: aload_0
       1: iload_1
       2: aload_2
       3: aload_3
       4: invokeinterface #41,  4           // InterfaceMethod setParameter:(ILjava/util/Date;Ljavax/persistence/TemporalType;)Lorg/hibernate/query/Query;
       9: areturn

  public default org.hibernate.Query setParameter(int, java.util.Calendar, javax.persistence.TemporalType);
    Code:
       0: aload_0
       1: iload_1
       2: aload_2
       3: aload_3
       4: invokeinterface #42,  4           // InterfaceMethod setParameter:(ILjava/util/Calendar;Ljavax/persistence/TemporalType;)Lorg/hibernate/query/Query;
       9: areturn

  public default org.hibernate.Query setParameter(java.lang.String, java.util.Date, javax.persistence.TemporalType);
    Code:
       0: aload_0
       1: aload_1
       2: aload_2
       3: aload_3
       4: invokeinterface #43,  4           // InterfaceMethod setParameter:(Ljava/lang/String;Ljava/util/Date;Ljavax/persistence/TemporalType;)Lorg/hibernate/query/Query;
       9: areturn

  public default org.hibernate.Query setParameter(java.lang.String, java.util.Calendar, javax.persistence.TemporalType);
    Code:
       0: aload_0
       1: aload_1
       2: aload_2
       3: aload_3
       4: invokeinterface #44,  4           // InterfaceMethod setParameter:(Ljava/lang/String;Ljava/util/Calendar;Ljavax/persistence/TemporalType;)Lorg/hibernate/query/Query;
       9: areturn

  public default org.hibernate.Query setParameter(javax.persistence.Parameter, java.util.Date, javax.persistence.TemporalType);
    Code:
       0: aload_0
       1: aload_1
       2: aload_2
       3: aload_3
       4: invokeinterface #45,  4           // InterfaceMethod setParameter:(Ljavax/persistence/Parameter;Ljava/util/Date;Ljavax/persistence/TemporalType;)Lorg/hibernate/query/Query;
       9: areturn

  public default org.hibernate.Query setParameter(javax.persistence.Parameter, java.util.Calendar, javax.persistence.TemporalType);
    Code:
       0: aload_0
       1: aload_1
       2: aload_2
       3: aload_3
       4: invokeinterface #46,  4           // InterfaceMethod setParameter:(Ljavax/persistence/Parameter;Ljava/util/Calendar;Ljavax/persistence/TemporalType;)Lorg/hibernate/query/Query;
       9: areturn

  public default org.hibernate.Query setHint(java.lang.String, java.lang.Object);
    Code:
       0: aload_0
       1: aload_1
       2: aload_2
       3: invokeinterface #48,  3           // InterfaceMethod setHint:(Ljava/lang/String;Ljava/lang/Object;)Lorg/hibernate/query/Query;
       8: areturn

  public default org.hibernate.Query setFirstResult(int);
    Code:
       0: aload_0
       1: iload_1
       2: invokeinterface #49,  2           // InterfaceMethod setFirstResult:(I)Lorg/hibernate/query/Query;
       7: areturn

  public default org.hibernate.Query setMaxResults(int);
    Code:
       0: aload_0
       1: iload_1
       2: invokeinterface #50,  2           // InterfaceMethod setMaxResults:(I)Lorg/hibernate/query/Query;
       7: areturn

  public default org.hibernate.Query setProperties(java.util.Map);
    Code:
       0: aload_0
       1: aload_1
       2: invokeinterface #95,  2           // InterfaceMethod setProperties:(Ljava/util/Map;)Lorg/hibernate/query/Query;
       7: areturn

  public default org.hibernate.Query setProperties(java.lang.Object);
    Code:
       0: aload_0
       1: aload_1
       2: invokeinterface #96,  2           // InterfaceMethod setProperties:(Ljava/lang/Object;)Lorg/hibernate/query/Query;
       7: areturn

  public default org.hibernate.Query setParameterList(java.lang.String, java.lang.Object[]);
    Code:
       0: aload_0
       1: aload_1
       2: aload_2
       3: invokeinterface #97,  3           // InterfaceMethod setParameterList:(Ljava/lang/String;[Ljava/lang/Object;)Lorg/hibernate/query/Query;
       8: areturn

  public default org.hibernate.Query setParameterList(java.lang.String, java.lang.Object[], org.hibernate.type.Type);
    Code:
       0: aload_0
       1: aload_1
       2: aload_2
       3: aload_3
       4: invokeinterface #98,  4           // InterfaceMethod setParameterList:(Ljava/lang/String;[Ljava/lang/Object;Lorg/hibernate/type/Type;)Lorg/hibernate/query/Query;
       9: areturn

  public default org.hibernate.Query setParameterList(java.lang.String, java.util.Collection, org.hibernate.type.Type);
    Code:
       0: aload_0
       1: aload_1
       2: aload_2
       3: aload_3
       4: invokeinterface #99,  4           // InterfaceMethod setParameterList:(Ljava/lang/String;Ljava/util/Collection;Lorg/hibernate/type/Type;)Lorg/hibernate/query/Query;
       9: areturn

  public default org.hibernate.Query setParameterList(java.lang.String, java.util.Collection);
    Code:
       0: aload_0
       1: aload_1
       2: aload_2
       3: invokeinterface #100,  3          // InterfaceMethod setParameterList:(Ljava/lang/String;Ljava/util/Collection;)Lorg/hibernate/query/Query;
       8: areturn

  public default org.hibernate.Query setParameterList(org.hibernate.query.QueryParameter, java.util.Collection);
    Code:
       0: aload_0
       1: aload_1
       2: aload_2
       3: invokeinterface #101,  3          // InterfaceMethod setParameterList:(Lorg/hibernate/query/QueryParameter;Ljava/util/Collection;)Lorg/hibernate/query/Query;
       8: areturn

  public default org.hibernate.Query setParameter(int, java.lang.Object, javax.persistence.TemporalType);
    Code:
       0: aload_0
       1: iload_1
       2: aload_2
       3: aload_3
       4: invokeinterface #102,  4          // InterfaceMethod setParameter:(ILjava/lang/Object;Ljavax/persistence/TemporalType;)Lorg/hibernate/query/Query;
       9: areturn

  public default org.hibernate.Query setParameter(java.lang.String, java.lang.Object, javax.persistence.TemporalType);
    Code:
       0: aload_0
       1: aload_1
       2: aload_2
       3: aload_3
       4: invokeinterface #103,  4          // InterfaceMethod setParameter:(Ljava/lang/String;Ljava/lang/Object;Ljavax/persistence/TemporalType;)Lorg/hibernate/query/Query;
       9: areturn

  public default org.hibernate.Query setParameter(org.hibernate.query.QueryParameter, java.lang.Object, javax.persistence.TemporalType);
    Code:
       0: aload_0
       1: aload_1
       2: aload_2
       3: aload_3
       4: invokeinterface #104,  4          // InterfaceMethod setParameter:(Lorg/hibernate/query/QueryParameter;Ljava/lang/Object;Ljavax/persistence/TemporalType;)Lorg/hibernate/query/Query;
       9: areturn

  public default org.hibernate.Query setParameter(int, java.lang.Object, org.hibernate.type.Type);
    Code:
       0: aload_0
       1: iload_1
       2: aload_2
       3: aload_3
       4: invokeinterface #5,  4            // InterfaceMethod setParameter:(ILjava/lang/Object;Lorg/hibernate/type/Type;)Lorg/hibernate/query/Query;
       9: areturn

  public default org.hibernate.Query setParameter(java.lang.String, java.lang.Object, org.hibernate.type.Type);
    Code:
       0: aload_0
       1: aload_1
       2: aload_2
       3: aload_3
       4: invokeinterface #32,  4           // InterfaceMethod setParameter:(Ljava/lang/String;Ljava/lang/Object;Lorg/hibernate/type/Type;)Lorg/hibernate/query/Query;
       9: areturn

  public default org.hibernate.Query setParameter(org.hibernate.query.QueryParameter, java.lang.Object, org.hibernate.type.Type);
    Code:
       0: aload_0
       1: aload_1
       2: aload_2
       3: aload_3
       4: invokeinterface #105,  4          // InterfaceMethod setParameter:(Lorg/hibernate/query/QueryParameter;Ljava/lang/Object;Lorg/hibernate/type/Type;)Lorg/hibernate/query/Query;
       9: areturn

  public default org.hibernate.Query setParameter(int, java.lang.Object);
    Code:
       0: aload_0
       1: iload_1
       2: aload_2
       3: invokeinterface #25,  3           // InterfaceMethod setParameter:(ILjava/lang/Object;)Lorg/hibernate/query/Query;
       8: areturn

  public default org.hibernate.Query setParameter(java.lang.String, java.lang.Object);
    Code:
       0: aload_0
       1: aload_1
       2: aload_2
       3: invokeinterface #34,  3           // InterfaceMethod setParameter:(Ljava/lang/String;Ljava/lang/Object;)Lorg/hibernate/query/Query;
       8: areturn

  public default org.hibernate.Query setParameter(javax.persistence.Parameter, java.lang.Object);
    Code:
       0: aload_0
       1: aload_1
       2: aload_2
       3: invokeinterface #47,  3           // InterfaceMethod setParameter:(Ljavax/persistence/Parameter;Ljava/lang/Object;)Lorg/hibernate/query/Query;
       8: areturn

  public default org.hibernate.Query setParameter(org.hibernate.query.QueryParameter, java.lang.Object);
    Code:
       0: aload_0
       1: aload_1
       2: aload_2
       3: invokeinterface #106,  3          // InterfaceMethod setParameter:(Lorg/hibernate/query/QueryParameter;Ljava/lang/Object;)Lorg/hibernate/query/Query;
       8: areturn

  public default org.hibernate.Query addQueryHint(java.lang.String);
    Code:
       0: aload_0
       1: aload_1
       2: invokeinterface #107,  2          // InterfaceMethod addQueryHint:(Ljava/lang/String;)Lorg/hibernate/query/Query;
       7: areturn

  public default org.hibernate.Query setComment(java.lang.String);
    Code:
       0: aload_0
       1: aload_1
       2: invokeinterface #108,  2          // InterfaceMethod setComment:(Ljava/lang/String;)Lorg/hibernate/query/Query;
       7: areturn

  public default org.hibernate.Query setLockMode(java.lang.String, org.hibernate.LockMode);
    Code:
       0: aload_0
       1: aload_1
       2: aload_2
       3: invokeinterface #109,  3          // InterfaceMethod setLockMode:(Ljava/lang/String;Lorg/hibernate/LockMode;)Lorg/hibernate/query/Query;
       8: areturn

  public default org.hibernate.Query setLockOptions(org.hibernate.LockOptions);
    Code:
       0: aload_0
       1: aload_1
       2: invokeinterface #110,  2          // InterfaceMethod setLockOptions:(Lorg/hibernate/LockOptions;)Lorg/hibernate/query/Query;
       7: areturn

  public default org.hibernate.Query setReadOnly(boolean);
    Code:
       0: aload_0
       1: iload_1
       2: invokeinterface #111,  2          // InterfaceMethod setReadOnly:(Z)Lorg/hibernate/query/Query;
       7: areturn

  public default org.hibernate.Query setFetchSize(int);
    Code:
       0: aload_0
       1: iload_1
       2: invokeinterface #112,  2          // InterfaceMethod setFetchSize:(I)Lorg/hibernate/query/Query;
       7: areturn

  public default org.hibernate.Query setTimeout(int);
    Code:
       0: aload_0
       1: iload_1
       2: invokeinterface #113,  2          // InterfaceMethod setTimeout:(I)Lorg/hibernate/query/Query;
       7: areturn

  public default org.hibernate.Query setCacheRegion(java.lang.String);
    Code:
       0: aload_0
       1: aload_1
       2: invokeinterface #114,  2          // InterfaceMethod setCacheRegion:(Ljava/lang/String;)Lorg/hibernate/query/Query;
       7: areturn

  public default org.hibernate.Query setCacheable(boolean);
    Code:
       0: aload_0
       1: iload_1
       2: invokeinterface #115,  2          // InterfaceMethod setCacheable:(Z)Lorg/hibernate/query/Query;
       7: areturn

  public default org.hibernate.Query setCacheMode(org.hibernate.CacheMode);
    Code:
       0: aload_0
       1: aload_1
       2: invokeinterface #116,  2          // InterfaceMethod setCacheMode:(Lorg/hibernate/CacheMode;)Lorg/hibernate/query/Query;
       7: areturn

  public default org.hibernate.Query setFlushMode(org.hibernate.FlushMode);
    Code:
       0: aload_0
       1: aload_1
       2: invokeinterface #117,  2          // InterfaceMethod setFlushMode:(Lorg/hibernate/FlushMode;)Lorg/hibernate/query/Query;
       7: areturn

  public default org.hibernate.Query setHibernateFlushMode(org.hibernate.FlushMode);
    Code:
       0: aload_0
       1: aload_1
       2: invokeinterface #3,  2            // InterfaceMethod setHibernateFlushMode:(Lorg/hibernate/FlushMode;)Lorg/hibernate/query/Query;
       7: areturn

  public default org.hibernate.BasicQueryContract setReadOnly(boolean);
    Code:
       0: aload_0
       1: iload_1
       2: invokeinterface #111,  2          // InterfaceMethod setReadOnly:(Z)Lorg/hibernate/query/Query;
       7: areturn

  public default org.hibernate.BasicQueryContract setFetchSize(int);
    Code:
       0: aload_0
       1: iload_1
       2: invokeinterface #112,  2          // InterfaceMethod setFetchSize:(I)Lorg/hibernate/query/Query;
       7: areturn

  public default org.hibernate.BasicQueryContract setTimeout(int);
    Code:
       0: aload_0
       1: iload_1
       2: invokeinterface #113,  2          // InterfaceMethod setTimeout:(I)Lorg/hibernate/query/Query;
       7: areturn

  public default org.hibernate.BasicQueryContract setCacheRegion(java.lang.String);
    Code:
       0: aload_0
       1: aload_1
       2: invokeinterface #114,  2          // InterfaceMethod setCacheRegion:(Ljava/lang/String;)Lorg/hibernate/query/Query;
       7: areturn

  public default org.hibernate.BasicQueryContract setCacheable(boolean);
    Code:
       0: aload_0
       1: iload_1
       2: invokeinterface #115,  2          // InterfaceMethod setCacheable:(Z)Lorg/hibernate/query/Query;
       7: areturn

  public default org.hibernate.BasicQueryContract setCacheMode(org.hibernate.CacheMode);
    Code:
       0: aload_0
       1: aload_1
       2: invokeinterface #116,  2          // InterfaceMethod setCacheMode:(Lorg/hibernate/CacheMode;)Lorg/hibernate/query/Query;
       7: areturn

  public default org.hibernate.BasicQueryContract setHibernateFlushMode(org.hibernate.FlushMode);
    Code:
       0: aload_0
       1: aload_1
       2: invokeinterface #3,  2            // InterfaceMethod setHibernateFlushMode:(Lorg/hibernate/FlushMode;)Lorg/hibernate/query/Query;
       7: areturn

  public default org.hibernate.BasicQueryContract setFlushMode(org.hibernate.FlushMode);
    Code:
       0: aload_0
       1: aload_1
       2: invokeinterface #117,  2          // InterfaceMethod setFlushMode:(Lorg/hibernate/FlushMode;)Lorg/hibernate/query/Query;
       7: areturn

  static {};
    Code:
       0: getstatic     #35                 // Field org/hibernate/query/Query$1.$assertionsDisabled:Z
       3: ifeq          6
       6: return
}
