Compiled from "QueryProducer.java"
public interface org.hibernate.query.QueryProducer {
  public abstract org.hibernate.Query getNamedQuery(java.lang.String);

  public abstract org.hibernate.Query createQuery(java.lang.String);

  public abstract <R> org.hibernate.query.Query<R> createQuery(java.lang.String, java.lang.Class<R>);

  public abstract org.hibernate.query.Query createNamedQuery(java.lang.String);

  public abstract <R> org.hibernate.query.Query<R> createNamedQuery(java.lang.String, java.lang.Class<R>);

  public default org.hibernate.SQLQuery createSQLQuery(java.lang.String);
    Code:
       0: aload_0
       1: aload_1
       2: invokeinterface #1,  2            // InterfaceMethod createNativeQuery:(Ljava/lang/String;)Lorg/hibernate/query/NativeQuery;
       7: astore_2
       8: aload_2
       9: ldc           #2                  // String dynamic native SQL query
      11: invokeinterface #3,  2            // InterfaceMethod org/hibernate/query/NativeQuery.setComment:(Ljava/lang/String;)Lorg/hibernate/query/NativeQuery;
      16: pop
      17: aload_2
      18: areturn

  public abstract org.hibernate.query.NativeQuery createNativeQuery(java.lang.String);

  public abstract <R> org.hibernate.query.NativeQuery<R> createNativeQuery(java.lang.String, java.lang.Class<R>);

  public abstract org.hibernate.query.NativeQuery createNativeQuery(java.lang.String, java.lang.String);

  public default org.hibernate.Query getNamedSQLQuery(java.lang.String);
    Code:
       0: aload_0
       1: aload_1
       2: invokeinterface #4,  2            // InterfaceMethod getNamedNativeQuery:(Ljava/lang/String;)Lorg/hibernate/query/NativeQuery;
       7: areturn

  public abstract org.hibernate.query.NativeQuery getNamedNativeQuery(java.lang.String);
}
