Compiled from "DefaultArrayAdapter.java"
class freemarker.template.DefaultArrayAdapter$GenericPrimitiveArrayAdapter extends freemarker.template.DefaultArrayAdapter {
  private final java.lang.Object array;

  private final int length;

  private freemarker.template.DefaultArrayAdapter$GenericPrimitiveArrayAdapter(java.lang.Object, freemarker.template.ObjectWrapper);
    Code:
       0: aload_0
       1: aload_2
       2: aconst_null
       3: invokespecial #2                  // Method freemarker/template/DefaultArrayAdapter."<init>":(Lfreemarker/template/ObjectWrapper;Lfreemarker/template/DefaultArrayAdapter$1;)V
       6: aload_0
       7: aload_1
       8: putfield      #3                  // Field array:Ljava/lang/Object;
      11: aload_0
      12: aload_1
      13: invokestatic  #4                  // Method java/lang/reflect/Array.getLength:(Ljava/lang/Object;)I
      16: putfield      #5                  // Field length:I
      19: return

  public freemarker.template.TemplateModel get(int) throws freemarker.template.TemplateModelException;
    Code:
       0: iload_1
       1: iflt          27
       4: iload_1
       5: aload_0
       6: getfield      #5                  // Field length:I
       9: if_icmpge     27
      12: aload_0
      13: aload_0
      14: getfield      #3                  // Field array:Ljava/lang/Object;
      17: iload_1
      18: invokestatic  #6                  // Method java/lang/reflect/Array.get:(Ljava/lang/Object;I)Ljava/lang/Object;
      21: invokevirtual #7                  // Method wrap:(Ljava/lang/Object;)Lfreemarker/template/TemplateModel;
      24: goto          28
      27: aconst_null
      28: areturn

  public int size() throws freemarker.template.TemplateModelException;
    Code:
       0: aload_0
       1: getfield      #5                  // Field length:I
       4: ireturn

  public java.lang.Object getWrappedObject();
    Code:
       0: aload_0
       1: getfield      #3                  // Field array:Ljava/lang/Object;
       4: areturn

  freemarker.template.DefaultArrayAdapter$GenericPrimitiveArrayAdapter(java.lang.Object, freemarker.template.ObjectWrapper, freemarker.template.DefaultArrayAdapter$1);
    Code:
       0: aload_0
       1: aload_1
       2: aload_2
       3: invokespecial #1                  // Method "<init>":(Ljava/lang/Object;Lfreemarker/template/ObjectWrapper;)V
       6: return
}
