Compiled from "DefaultArrayAdapter.java"
public abstract class freemarker.template.DefaultArrayAdapter extends freemarker.template.WrappingTemplateModel implements freemarker.template.TemplateSequenceModel,freemarker.template.AdapterTemplateModel,freemarker.ext.util.WrapperTemplateModel,java.io.Serializable {
  public static freemarker.template.DefaultArrayAdapter adapt(java.lang.Object, freemarker.template.ObjectWrapperAndUnwrapper);
    Code:
       0: aload_0
       1: invokevirtual #2                  // Method java/lang/Object.getClass:()Ljava/lang/Class;
       4: invokevirtual #3                  // Method java/lang/Class.getComponentType:()Ljava/lang/Class;
       7: astore_2
       8: aload_2
       9: ifnonnull     22
      12: new           #4                  // class java/lang/IllegalArgumentException
      15: dup
      16: ldc           #5                  // String Not an array
      18: invokespecial #6                  // Method java/lang/IllegalArgumentException."<init>":(Ljava/lang/String;)V
      21: athrow
      22: aload_2
      23: invokevirtual #7                  // Method java/lang/Class.isPrimitive:()Z
      26: ifeq          232
      29: aload_2
      30: getstatic     #8                  // Field java/lang/Integer.TYPE:Ljava/lang/Class;
      33: if_acmpne     53
      36: new           #9                  // class freemarker/template/DefaultArrayAdapter$IntArrayAdapter
      39: dup
      40: aload_0
      41: checkcast     #10                 // class "[I"
      44: checkcast     #10                 // class "[I"
      47: aload_1
      48: aconst_null
      49: invokespecial #11                 // Method freemarker/template/DefaultArrayAdapter$IntArrayAdapter."<init>":([ILfreemarker/template/ObjectWrapper;Lfreemarker/template/DefaultArrayAdapter$1;)V
      52: areturn
      53: aload_2
      54: getstatic     #12                 // Field java/lang/Double.TYPE:Ljava/lang/Class;
      57: if_acmpne     77
      60: new           #13                 // class freemarker/template/DefaultArrayAdapter$DoubleArrayAdapter
      63: dup
      64: aload_0
      65: checkcast     #14                 // class "[D"
      68: checkcast     #14                 // class "[D"
      71: aload_1
      72: aconst_null
      73: invokespecial #15                 // Method freemarker/template/DefaultArrayAdapter$DoubleArrayAdapter."<init>":([DLfreemarker/template/ObjectWrapper;Lfreemarker/template/DefaultArrayAdapter$1;)V
      76: areturn
      77: aload_2
      78: getstatic     #16                 // Field java/lang/Long.TYPE:Ljava/lang/Class;
      81: if_acmpne     101
      84: new           #17                 // class freemarker/template/DefaultArrayAdapter$LongArrayAdapter
      87: dup
      88: aload_0
      89: checkcast     #18                 // class "[J"
      92: checkcast     #18                 // class "[J"
      95: aload_1
      96: aconst_null
      97: invokespecial #19                 // Method freemarker/template/DefaultArrayAdapter$LongArrayAdapter."<init>":([JLfreemarker/template/ObjectWrapper;Lfreemarker/template/DefaultArrayAdapter$1;)V
     100: areturn
     101: aload_2
     102: getstatic     #20                 // Field java/lang/Boolean.TYPE:Ljava/lang/Class;
     105: if_acmpne     125
     108: new           #21                 // class freemarker/template/DefaultArrayAdapter$BooleanArrayAdapter
     111: dup
     112: aload_0
     113: checkcast     #22                 // class "[Z"
     116: checkcast     #22                 // class "[Z"
     119: aload_1
     120: aconst_null
     121: invokespecial #23                 // Method freemarker/template/DefaultArrayAdapter$BooleanArrayAdapter."<init>":([ZLfreemarker/template/ObjectWrapper;Lfreemarker/template/DefaultArrayAdapter$1;)V
     124: areturn
     125: aload_2
     126: getstatic     #24                 // Field java/lang/Float.TYPE:Ljava/lang/Class;
     129: if_acmpne     149
     132: new           #25                 // class freemarker/template/DefaultArrayAdapter$FloatArrayAdapter
     135: dup
     136: aload_0
     137: checkcast     #26                 // class "[F"
     140: checkcast     #26                 // class "[F"
     143: aload_1
     144: aconst_null
     145: invokespecial #27                 // Method freemarker/template/DefaultArrayAdapter$FloatArrayAdapter."<init>":([FLfreemarker/template/ObjectWrapper;Lfreemarker/template/DefaultArrayAdapter$1;)V
     148: areturn
     149: aload_2
     150: getstatic     #28                 // Field java/lang/Character.TYPE:Ljava/lang/Class;
     153: if_acmpne     173
     156: new           #29                 // class freemarker/template/DefaultArrayAdapter$CharArrayAdapter
     159: dup
     160: aload_0
     161: checkcast     #30                 // class "[C"
     164: checkcast     #30                 // class "[C"
     167: aload_1
     168: aconst_null
     169: invokespecial #31                 // Method freemarker/template/DefaultArrayAdapter$CharArrayAdapter."<init>":([CLfreemarker/template/ObjectWrapper;Lfreemarker/template/DefaultArrayAdapter$1;)V
     172: areturn
     173: aload_2
     174: getstatic     #32                 // Field java/lang/Short.TYPE:Ljava/lang/Class;
     177: if_acmpne     197
     180: new           #33                 // class freemarker/template/DefaultArrayAdapter$ShortArrayAdapter
     183: dup
     184: aload_0
     185: checkcast     #34                 // class "[S"
     188: checkcast     #34                 // class "[S"
     191: aload_1
     192: aconst_null
     193: invokespecial #35                 // Method freemarker/template/DefaultArrayAdapter$ShortArrayAdapter."<init>":([SLfreemarker/template/ObjectWrapper;Lfreemarker/template/DefaultArrayAdapter$1;)V
     196: areturn
     197: aload_2
     198: getstatic     #36                 // Field java/lang/Byte.TYPE:Ljava/lang/Class;
     201: if_acmpne     221
     204: new           #37                 // class freemarker/template/DefaultArrayAdapter$ByteArrayAdapter
     207: dup
     208: aload_0
     209: checkcast     #38                 // class "[B"
     212: checkcast     #38                 // class "[B"
     215: aload_1
     216: aconst_null
     217: invokespecial #39                 // Method freemarker/template/DefaultArrayAdapter$ByteArrayAdapter."<init>":([BLfreemarker/template/ObjectWrapper;Lfreemarker/template/DefaultArrayAdapter$1;)V
     220: areturn
     221: new           #40                 // class freemarker/template/DefaultArrayAdapter$GenericPrimitiveArrayAdapter
     224: dup
     225: aload_0
     226: aload_1
     227: aconst_null
     228: invokespecial #41                 // Method freemarker/template/DefaultArrayAdapter$GenericPrimitiveArrayAdapter."<init>":(Ljava/lang/Object;Lfreemarker/template/ObjectWrapper;Lfreemarker/template/DefaultArrayAdapter$1;)V
     231: areturn
     232: new           #42                 // class freemarker/template/DefaultArrayAdapter$ObjectArrayAdapter
     235: dup
     236: aload_0
     237: checkcast     #43                 // class "[Ljava/lang/Object;"
     240: checkcast     #43                 // class "[Ljava/lang/Object;"
     243: aload_1
     244: aconst_null
     245: invokespecial #44                 // Method freemarker/template/DefaultArrayAdapter$ObjectArrayAdapter."<init>":([Ljava/lang/Object;Lfreemarker/template/ObjectWrapper;Lfreemarker/template/DefaultArrayAdapter$1;)V
     248: areturn

  private freemarker.template.DefaultArrayAdapter(freemarker.template.ObjectWrapper);
    Code:
       0: aload_0
       1: aload_1
       2: invokespecial #45                 // Method freemarker/template/WrappingTemplateModel."<init>":(Lfreemarker/template/ObjectWrapper;)V
       5: return

  public final java.lang.Object getAdaptedObject(java.lang.Class);
    Code:
       0: aload_0
       1: invokevirtual #46                 // Method getWrappedObject:()Ljava/lang/Object;
       4: areturn

  freemarker.template.DefaultArrayAdapter(freemarker.template.ObjectWrapper, freemarker.template.DefaultArrayAdapter$1);
    Code:
       0: aload_0
       1: aload_1
       2: invokespecial #1                  // Method "<init>":(Lfreemarker/template/ObjectWrapper;)V
       5: return
}
