Compiled from "SimpleObjectWrapper.java"
public class freemarker.template.SimpleObjectWrapper extends freemarker.template.DefaultObjectWrapper {
  static final freemarker.template.SimpleObjectWrapper instance;

  public freemarker.template.SimpleObjectWrapper();
    Code:
       0: aload_0
       1: invokespecial #1                  // Method freemarker/template/DefaultObjectWrapper."<init>":()V
       4: return

  public freemarker.template.SimpleObjectWrapper(freemarker.template.Version);
    Code:
       0: aload_0
       1: aload_1
       2: invokespecial #2                  // Method freemarker/template/DefaultObjectWrapper."<init>":(Lfreemarker/template/Version;)V
       5: return

  protected freemarker.template.TemplateModel handleUnknownType(java.lang.Object) throws freemarker.template.TemplateModelException;
    Code:
       0: new           #3                  // class freemarker/template/TemplateModelException
       3: dup
       4: new           #4                  // class java/lang/StringBuilder
       7: dup
       8: invokespecial #5                  // Method java/lang/StringBuilder."<init>":()V
      11: ldc           #6                  // String SimpleObjectWrapper deliberately won\'t wrap this type:
      13: invokevirtual #7                  // Method java/lang/StringBuilder.append:(Ljava/lang/String;)Ljava/lang/StringBuilder;
      16: aload_1
      17: invokevirtual #8                  // Method java/lang/Object.getClass:()Ljava/lang/Class;
      20: invokevirtual #9                  // Method java/lang/Class.getName:()Ljava/lang/String;
      23: invokevirtual #7                  // Method java/lang/StringBuilder.append:(Ljava/lang/String;)Ljava/lang/StringBuilder;
      26: invokevirtual #10                 // Method java/lang/StringBuilder.toString:()Ljava/lang/String;
      29: invokespecial #11                 // Method freemarker/template/TemplateModelException."<init>":(Ljava/lang/String;)V
      32: athrow

  public freemarker.template.TemplateHashModel wrapAsAPI(java.lang.Object) throws freemarker.template.TemplateModelException;
    Code:
       0: new           #3                  // class freemarker/template/TemplateModelException
       3: dup
       4: ldc           #12                 // String SimpleObjectWrapper deliberately doesn\'t allow ?api.
       6: invokespecial #11                 // Method freemarker/template/TemplateModelException."<init>":(Ljava/lang/String;)V
       9: athrow

  static {};
    Code:
       0: new           #13                 // class freemarker/template/SimpleObjectWrapper
       3: dup
       4: invokespecial #14                 // Method "<init>":()V
       7: putstatic     #15                 // Field instance:Lfreemarker/template/SimpleObjectWrapper;
      10: return
}
