Compiled from "WsRemoteEndpointBase.java"
public abstract class org.apache.tomcat.websocket.WsRemoteEndpointBase implements javax.websocket.RemoteEndpoint {
  protected final org.apache.tomcat.websocket.WsRemoteEndpointImplBase base;

  org.apache.tomcat.websocket.WsRemoteEndpointBase(org.apache.tomcat.websocket.WsRemoteEndpointImplBase);
    Code:
       0: aload_0
       1: invokespecial #1                  // Method java/lang/Object."<init>":()V
       4: aload_0
       5: aload_1
       6: putfield      #2                  // Field base:Lorg/apache/tomcat/websocket/WsRemoteEndpointImplBase;
       9: return

  public final void setBatchingAllowed(boolean) throws java.io.IOException;
    Code:
       0: aload_0
       1: getfield      #2                  // Field base:Lorg/apache/tomcat/websocket/WsRemoteEndpointImplBase;
       4: iload_1
       5: invokevirtual #3                  // Method org/apache/tomcat/websocket/WsRemoteEndpointImplBase.setBatchingAllowed:(Z)V
       8: return

  public final boolean getBatchingAllowed();
    Code:
       0: aload_0
       1: getfield      #2                  // Field base:Lorg/apache/tomcat/websocket/WsRemoteEndpointImplBase;
       4: invokevirtual #4                  // Method org/apache/tomcat/websocket/WsRemoteEndpointImplBase.getBatchingAllowed:()Z
       7: ireturn

  public final void flushBatch() throws java.io.IOException;
    Code:
       0: aload_0
       1: getfield      #2                  // Field base:Lorg/apache/tomcat/websocket/WsRemoteEndpointImplBase;
       4: invokevirtual #5                  // Method org/apache/tomcat/websocket/WsRemoteEndpointImplBase.flushBatch:()V
       7: return

  public final void sendPing(java.nio.ByteBuffer) throws java.io.IOException, java.lang.IllegalArgumentException;
    Code:
       0: aload_0
       1: getfield      #2                  // Field base:Lorg/apache/tomcat/websocket/WsRemoteEndpointImplBase;
       4: aload_1
       5: invokevirtual #6                  // Method org/apache/tomcat/websocket/WsRemoteEndpointImplBase.sendPing:(Ljava/nio/ByteBuffer;)V
       8: return

  public final void sendPong(java.nio.ByteBuffer) throws java.io.IOException, java.lang.IllegalArgumentException;
    Code:
       0: aload_0
       1: getfield      #2                  // Field base:Lorg/apache/tomcat/websocket/WsRemoteEndpointImplBase;
       4: aload_1
       5: invokevirtual #7                  // Method org/apache/tomcat/websocket/WsRemoteEndpointImplBase.sendPong:(Ljava/nio/ByteBuffer;)V
       8: return
}
