Compiled from "ContentAssistField.java"
public class org.eclipse.ui.fieldassist.ContentAssistField extends org.eclipse.jface.fieldassist.DecoratedField {
  private org.eclipse.ui.fieldassist.ContentAssistCommandAdapter adapter;

  private static final java.lang.String CONTENT_ASSIST_DECORATION_ID;

  public org.eclipse.ui.fieldassist.ContentAssistField(org.eclipse.swt.widgets.Composite, int, org.eclipse.jface.fieldassist.IControlCreator, org.eclipse.jface.fieldassist.IControlContentAdapter, org.eclipse.jface.fieldassist.IContentProposalProvider, java.lang.String, char[]);
    Code:
       0: aload_0
       1: aload_1
       2: iload_2
       3: aload_3
       4: invokespecial #127                // Method org/eclipse/jface/fieldassist/DecoratedField."<init>":(Lorg/eclipse/swt/widgets/Composite;ILorg/eclipse/jface/fieldassist/IControlCreator;)V
       7: aload_0
       8: new           #66                 // class org/eclipse/ui/fieldassist/ContentAssistCommandAdapter
      11: dup
      12: aload_0
      13: invokevirtual #142                // Method getControl:()Lorg/eclipse/swt/widgets/Control;
      16: aload         4
      18: aload         5
      20: aload         6
      22: aload         7
      24: invokespecial #137                // Method org/eclipse/ui/fieldassist/ContentAssistCommandAdapter."<init>":(Lorg/eclipse/swt/widgets/Control;Lorg/eclipse/jface/fieldassist/IControlContentAdapter;Lorg/eclipse/jface/fieldassist/IContentProposalProvider;Ljava/lang/String;[C)V
      27: putfield      #122                // Field adapter:Lorg/eclipse/ui/fieldassist/ContentAssistCommandAdapter;
      30: aload_0
      31: aload_0
      32: invokevirtual #138                // Method getFieldDecoration:()Lorg/eclipse/jface/fieldassist/FieldDecoration;
      35: sipush        16512
      38: iconst_1
      39: invokevirtual #141                // Method addFieldDecoration:(Lorg/eclipse/jface/fieldassist/FieldDecoration;IZ)V
      42: return

  public void setEnabled(boolean);
    Code:
       0: aload_0
       1: getfield      #122                // Field adapter:Lorg/eclipse/ui/fieldassist/ContentAssistCommandAdapter;
       4: iload_1
       5: invokevirtual #135                // Method org/eclipse/ui/fieldassist/ContentAssistCommandAdapter.setEnabled:(Z)V
       8: iload_1
       9: ifeq          23
      12: aload_0
      13: aload_0
      14: invokevirtual #138                // Method getFieldDecoration:()Lorg/eclipse/jface/fieldassist/FieldDecoration;
      17: invokevirtual #140                // Method showDecoration:(Lorg/eclipse/jface/fieldassist/FieldDecoration;)V
      20: goto          31
      23: aload_0
      24: aload_0
      25: invokevirtual #138                // Method getFieldDecoration:()Lorg/eclipse/jface/fieldassist/FieldDecoration;
      28: invokevirtual #139                // Method hideDecoration:(Lorg/eclipse/jface/fieldassist/FieldDecoration;)V
      31: return

  private org.eclipse.jface.fieldassist.FieldDecoration getFieldDecoration();
    Code:
       0: invokestatic  #130                // Method org/eclipse/jface/fieldassist/FieldDecorationRegistry.getDefault:()Lorg/eclipse/jface/fieldassist/FieldDecorationRegistry;
       3: astore_1
       4: new           #59                 // class java/lang/StringBuilder
       7: dup
       8: ldc           #2                  // String org.eclipse.ui.fieldAssist.ContentAssistField
      10: invokespecial #125                // Method java/lang/StringBuilder."<init>":(Ljava/lang/String;)V
      13: aload_0
      14: getfield      #122                // Field adapter:Lorg/eclipse/ui/fieldassist/ContentAssistCommandAdapter;
      17: invokevirtual #136                // Method org/eclipse/ui/fieldassist/ContentAssistCommandAdapter.getCommandId:()Ljava/lang/String;
      20: invokevirtual #126                // Method java/lang/StringBuilder.append:(Ljava/lang/String;)Ljava/lang/StringBuilder;
      23: invokevirtual #124                // Method java/lang/StringBuilder.toString:()Ljava/lang/String;
      26: astore_2
      27: aload_1
      28: aload_2
      29: invokevirtual #131                // Method org/eclipse/jface/fieldassist/FieldDecorationRegistry.getFieldDecoration:(Ljava/lang/String;)Lorg/eclipse/jface/fieldassist/FieldDecoration;
      32: astore_3
      33: aload_3
      34: ifnonnull     62
      37: aload_1
      38: ldc           #1                  // String DEC_CONTENT_PROPOSAL
      40: invokevirtual #131                // Method org/eclipse/jface/fieldassist/FieldDecorationRegistry.getFieldDecoration:(Ljava/lang/String;)Lorg/eclipse/jface/fieldassist/FieldDecoration;
      43: astore        4
      45: aload_1
      46: aload_2
      47: aconst_null
      48: aload         4
      50: invokevirtual #129                // Method org/eclipse/jface/fieldassist/FieldDecoration.getImage:()Lorg/eclipse/swt/graphics/Image;
      53: invokevirtual #132                // Method org/eclipse/jface/fieldassist/FieldDecorationRegistry.registerFieldDecoration:(Ljava/lang/String;Ljava/lang/String;Lorg/eclipse/swt/graphics/Image;)V
      56: aload_1
      57: aload_2
      58: invokevirtual #131                // Method org/eclipse/jface/fieldassist/FieldDecorationRegistry.getFieldDecoration:(Ljava/lang/String;)Lorg/eclipse/jface/fieldassist/FieldDecoration;
      61: astore_3
      62: invokestatic  #134                // Method org/eclipse/ui/PlatformUI.getWorkbench:()Lorg/eclipse/ui/IWorkbench;
      65: ldc           #3                  // class org/eclipse/ui/keys/IBindingService
      67: invokeinterface #143,  2          // InterfaceMethod org/eclipse/ui/IWorkbench.getService:(Ljava/lang/Class;)Ljava/lang/Object;
      72: checkcast     #3                  // class org/eclipse/ui/keys/IBindingService
      75: astore        4
      77: aload_3
      78: getstatic     #123                // Field org/eclipse/ui/internal/WorkbenchMessages.ContentAssist_Cue_Description_Key:Ljava/lang/String;
      81: aload         4
      83: aload_0
      84: getfield      #122                // Field adapter:Lorg/eclipse/ui/fieldassist/ContentAssistCommandAdapter;
      87: invokevirtual #136                // Method org/eclipse/ui/fieldassist/ContentAssistCommandAdapter.getCommandId:()Ljava/lang/String;
      90: invokeinterface #144,  2          // InterfaceMethod org/eclipse/ui/keys/IBindingService.getBestActiveBindingFormattedFor:(Ljava/lang/String;)Ljava/lang/String;
      95: invokestatic  #133                // Method org/eclipse/osgi/util/NLS.bind:(Ljava/lang/String;Ljava/lang/Object;)Ljava/lang/String;
      98: invokevirtual #128                // Method org/eclipse/jface/fieldassist/FieldDecoration.setDescription:(Ljava/lang/String;)V
     101: aload_3
     102: areturn

  public org.eclipse.ui.fieldassist.ContentAssistCommandAdapter getContentAssistCommandAdapter();
    Code:
       0: aload_0
       1: getfield      #122                // Field adapter:Lorg/eclipse/ui/fieldassist/ContentAssistCommandAdapter;
       4: areturn
}
