Compiled from "AdviceImpl.java"
public class org.aspectj.internal.lang.reflect.AdviceImpl implements org.aspectj.lang.reflect.Advice {
  private static final java.lang.String AJC_INTERNAL;

  private final org.aspectj.lang.reflect.AdviceKind kind;

  private final java.lang.reflect.Method adviceMethod;

  private org.aspectj.lang.reflect.PointcutExpression pointcutExpression;

  private boolean hasExtraParam;

  private java.lang.reflect.Type[] genericParameterTypes;

  private org.aspectj.lang.reflect.AjType[] parameterTypes;

  private org.aspectj.lang.reflect.AjType[] exceptionTypes;

  protected org.aspectj.internal.lang.reflect.AdviceImpl(java.lang.reflect.Method, java.lang.String, org.aspectj.lang.reflect.AdviceKind);
    Code:
       0: aload_0
       1: invokespecial #1                  // Method java/lang/Object."<init>":()V
       4: aload_0
       5: iconst_0
       6: putfield      #2                  // Field hasExtraParam:Z
       9: aload_0
      10: aload_3
      11: putfield      #3                  // Field kind:Lorg/aspectj/lang/reflect/AdviceKind;
      14: aload_0
      15: aload_1
      16: putfield      #4                  // Field adviceMethod:Ljava/lang/reflect/Method;
      19: aload_0
      20: new           #5                  // class org/aspectj/internal/lang/reflect/PointcutExpressionImpl
      23: dup
      24: aload_2
      25: invokespecial #6                  // Method org/aspectj/internal/lang/reflect/PointcutExpressionImpl."<init>":(Ljava/lang/String;)V
      28: putfield      #7                  // Field pointcutExpression:Lorg/aspectj/lang/reflect/PointcutExpression;
      31: return

  protected org.aspectj.internal.lang.reflect.AdviceImpl(java.lang.reflect.Method, java.lang.String, org.aspectj.lang.reflect.AdviceKind, java.lang.String);
    Code:
       0: aload_0
       1: aload_1
       2: aload_2
       3: aload_3
       4: invokespecial #8                  // Method "<init>":(Ljava/lang/reflect/Method;Ljava/lang/String;Lorg/aspectj/lang/reflect/AdviceKind;)V
       7: aload_0
       8: iconst_1
       9: putfield      #2                  // Field hasExtraParam:Z
      12: return

  public org.aspectj.lang.reflect.AjType getDeclaringType();
    Code:
       0: aload_0
       1: getfield      #4                  // Field adviceMethod:Ljava/lang/reflect/Method;
       4: invokevirtual #9                  // Method java/lang/reflect/Method.getDeclaringClass:()Ljava/lang/Class;
       7: invokestatic  #10                 // Method org/aspectj/lang/reflect/AjTypeSystem.getAjType:(Ljava/lang/Class;)Lorg/aspectj/lang/reflect/AjType;
      10: areturn

  public java.lang.reflect.Type[] getGenericParameterTypes();
    Code:
       0: aload_0
       1: getfield      #11                 // Field genericParameterTypes:[Ljava/lang/reflect/Type;
       4: ifnonnull     139
       7: aload_0
       8: getfield      #4                  // Field adviceMethod:Ljava/lang/reflect/Method;
      11: invokevirtual #12                 // Method java/lang/reflect/Method.getGenericParameterTypes:()[Ljava/lang/reflect/Type;
      14: astore_1
      15: iconst_0
      16: istore_2
      17: aload_1
      18: astore_3
      19: aload_3
      20: arraylength
      21: istore        4
      23: iconst_0
      24: istore        5
      26: iload         5
      28: iload         4
      30: if_icmpge     75
      33: aload_3
      34: iload         5
      36: aaload
      37: astore        6
      39: aload         6
      41: instanceof    #13                 // class java/lang/Class
      44: ifeq          69
      47: aload         6
      49: checkcast     #13                 // class java/lang/Class
      52: invokevirtual #14                 // Method java/lang/Class.getPackage:()Ljava/lang/Package;
      55: invokevirtual #15                 // Method java/lang/Package.getName:()Ljava/lang/String;
      58: ldc           #17                 // String org.aspectj.runtime.internal
      60: invokevirtual #18                 // Method java/lang/String.equals:(Ljava/lang/Object;)Z
      63: ifeq          69
      66: iinc          2, 1
      69: iinc          5, 1
      72: goto          26
      75: aload_0
      76: aload_1
      77: arraylength
      78: iload_2
      79: isub
      80: anewarray     #19                 // class java/lang/reflect/Type
      83: putfield      #11                 // Field genericParameterTypes:[Ljava/lang/reflect/Type;
      86: iconst_0
      87: istore_3
      88: iload_3
      89: aload_0
      90: getfield      #11                 // Field genericParameterTypes:[Ljava/lang/reflect/Type;
      93: arraylength
      94: if_icmpge     139
      97: aload_1
      98: iload_3
      99: aaload
     100: instanceof    #13                 // class java/lang/Class
     103: ifeq          124
     106: aload_0
     107: getfield      #11                 // Field genericParameterTypes:[Ljava/lang/reflect/Type;
     110: iload_3
     111: aload_1
     112: iload_3
     113: aaload
     114: checkcast     #13                 // class java/lang/Class
     117: invokestatic  #10                 // Method org/aspectj/lang/reflect/AjTypeSystem.getAjType:(Ljava/lang/Class;)Lorg/aspectj/lang/reflect/AjType;
     120: aastore
     121: goto          133
     124: aload_0
     125: getfield      #11                 // Field genericParameterTypes:[Ljava/lang/reflect/Type;
     128: iload_3
     129: aload_1
     130: iload_3
     131: aaload
     132: aastore
     133: iinc          3, 1
     136: goto          88
     139: aload_0
     140: getfield      #11                 // Field genericParameterTypes:[Ljava/lang/reflect/Type;
     143: areturn

  public org.aspectj.lang.reflect.AjType<?>[] getParameterTypes();
    Code:
       0: aload_0
       1: getfield      #20                 // Field parameterTypes:[Lorg/aspectj/lang/reflect/AjType;
       4: ifnonnull     104
       7: aload_0
       8: getfield      #4                  // Field adviceMethod:Ljava/lang/reflect/Method;
      11: invokevirtual #21                 // Method java/lang/reflect/Method.getParameterTypes:()[Ljava/lang/Class;
      14: astore_1
      15: iconst_0
      16: istore_2
      17: aload_1
      18: astore_3
      19: aload_3
      20: arraylength
      21: istore        4
      23: iconst_0
      24: istore        5
      26: iload         5
      28: iload         4
      30: if_icmpge     64
      33: aload_3
      34: iload         5
      36: aaload
      37: astore        6
      39: aload         6
      41: invokevirtual #14                 // Method java/lang/Class.getPackage:()Ljava/lang/Package;
      44: invokevirtual #15                 // Method java/lang/Package.getName:()Ljava/lang/String;
      47: ldc           #17                 // String org.aspectj.runtime.internal
      49: invokevirtual #18                 // Method java/lang/String.equals:(Ljava/lang/Object;)Z
      52: ifeq          58
      55: iinc          2, 1
      58: iinc          5, 1
      61: goto          26
      64: aload_0
      65: aload_1
      66: arraylength
      67: iload_2
      68: isub
      69: anewarray     #22                 // class org/aspectj/lang/reflect/AjType
      72: putfield      #20                 // Field parameterTypes:[Lorg/aspectj/lang/reflect/AjType;
      75: iconst_0
      76: istore_3
      77: iload_3
      78: aload_0
      79: getfield      #20                 // Field parameterTypes:[Lorg/aspectj/lang/reflect/AjType;
      82: arraylength
      83: if_icmpge     104
      86: aload_0
      87: getfield      #20                 // Field parameterTypes:[Lorg/aspectj/lang/reflect/AjType;
      90: iload_3
      91: aload_1
      92: iload_3
      93: aaload
      94: invokestatic  #10                 // Method org/aspectj/lang/reflect/AjTypeSystem.getAjType:(Ljava/lang/Class;)Lorg/aspectj/lang/reflect/AjType;
      97: aastore
      98: iinc          3, 1
     101: goto          77
     104: aload_0
     105: getfield      #20                 // Field parameterTypes:[Lorg/aspectj/lang/reflect/AjType;
     108: areturn

  public org.aspectj.lang.reflect.AjType<?>[] getExceptionTypes();
    Code:
       0: aload_0
       1: getfield      #23                 // Field exceptionTypes:[Lorg/aspectj/lang/reflect/AjType;
       4: ifnonnull     50
       7: aload_0
       8: getfield      #4                  // Field adviceMethod:Ljava/lang/reflect/Method;
      11: invokevirtual #24                 // Method java/lang/reflect/Method.getExceptionTypes:()[Ljava/lang/Class;
      14: astore_1
      15: aload_0
      16: aload_1
      17: arraylength
      18: anewarray     #22                 // class org/aspectj/lang/reflect/AjType
      21: putfield      #23                 // Field exceptionTypes:[Lorg/aspectj/lang/reflect/AjType;
      24: iconst_0
      25: istore_2
      26: iload_2
      27: aload_1
      28: arraylength
      29: if_icmpge     50
      32: aload_0
      33: getfield      #23                 // Field exceptionTypes:[Lorg/aspectj/lang/reflect/AjType;
      36: iload_2
      37: aload_1
      38: iload_2
      39: aaload
      40: invokestatic  #10                 // Method org/aspectj/lang/reflect/AjTypeSystem.getAjType:(Ljava/lang/Class;)Lorg/aspectj/lang/reflect/AjType;
      43: aastore
      44: iinc          2, 1
      47: goto          26
      50: aload_0
      51: getfield      #23                 // Field exceptionTypes:[Lorg/aspectj/lang/reflect/AjType;
      54: areturn

  public org.aspectj.lang.reflect.AdviceKind getKind();
    Code:
       0: aload_0
       1: getfield      #3                  // Field kind:Lorg/aspectj/lang/reflect/AdviceKind;
       4: areturn

  public java.lang.String getName();
    Code:
       0: aload_0
       1: getfield      #4                  // Field adviceMethod:Ljava/lang/reflect/Method;
       4: invokevirtual #25                 // Method java/lang/reflect/Method.getName:()Ljava/lang/String;
       7: astore_1
       8: aload_1
       9: ldc           #26                 // String ajc$
      11: invokevirtual #27                 // Method java/lang/String.startsWith:(Ljava/lang/String;)Z
      14: ifeq          44
      17: ldc           #28                 // String
      19: astore_1
      20: aload_0
      21: getfield      #4                  // Field adviceMethod:Ljava/lang/reflect/Method;
      24: ldc           #29                 // class org/aspectj/lang/annotation/AdviceName
      26: invokevirtual #30                 // Method java/lang/reflect/Method.getAnnotation:(Ljava/lang/Class;)Ljava/lang/annotation/Annotation;
      29: checkcast     #29                 // class org/aspectj/lang/annotation/AdviceName
      32: astore_2
      33: aload_2
      34: ifnull        44
      37: aload_2
      38: invokeinterface #31,  1           // InterfaceMethod org/aspectj/lang/annotation/AdviceName.value:()Ljava/lang/String;
      43: astore_1
      44: aload_1
      45: areturn

  public org.aspectj.lang.reflect.PointcutExpression getPointcutExpression();
    Code:
       0: aload_0
       1: getfield      #7                  // Field pointcutExpression:Lorg/aspectj/lang/reflect/PointcutExpression;
       4: areturn

  public java.lang.String toString();
    Code:
       0: new           #32                 // class java/lang/StringBuffer
       3: dup
       4: invokespecial #33                 // Method java/lang/StringBuffer."<init>":()V
       7: astore_1
       8: aload_0
       9: invokevirtual #34                 // Method getName:()Ljava/lang/String;
      12: invokevirtual #35                 // Method java/lang/String.length:()I
      15: ifle          41
      18: aload_1
      19: ldc           #36                 // String @AdviceName(\"
      21: invokevirtual #37                 // Method java/lang/StringBuffer.append:(Ljava/lang/String;)Ljava/lang/StringBuffer;
      24: pop
      25: aload_1
      26: aload_0
      27: invokevirtual #34                 // Method getName:()Ljava/lang/String;
      30: invokevirtual #37                 // Method java/lang/StringBuffer.append:(Ljava/lang/String;)Ljava/lang/StringBuffer;
      33: pop
      34: aload_1
      35: ldc           #38                 // String \")
      37: invokevirtual #37                 // Method java/lang/StringBuffer.append:(Ljava/lang/String;)Ljava/lang/StringBuffer;
      40: pop
      41: aload_0
      42: invokevirtual #39                 // Method getKind:()Lorg/aspectj/lang/reflect/AdviceKind;
      45: getstatic     #40                 // Field org/aspectj/lang/reflect/AdviceKind.AROUND:Lorg/aspectj/lang/reflect/AdviceKind;
      48: if_acmpne     73
      51: aload_1
      52: aload_0
      53: getfield      #4                  // Field adviceMethod:Ljava/lang/reflect/Method;
      56: invokevirtual #41                 // Method java/lang/reflect/Method.getGenericReturnType:()Ljava/lang/reflect/Type;
      59: invokevirtual #42                 // Method java/lang/Object.toString:()Ljava/lang/String;
      62: invokevirtual #37                 // Method java/lang/StringBuffer.append:(Ljava/lang/String;)Ljava/lang/StringBuffer;
      65: pop
      66: aload_1
      67: ldc           #43                 // String
      69: invokevirtual #37                 // Method java/lang/StringBuffer.append:(Ljava/lang/String;)Ljava/lang/StringBuffer;
      72: pop
      73: getstatic     #44                 // Field org/aspectj/internal/lang/reflect/AdviceImpl$1.$SwitchMap$org$aspectj$lang$reflect$AdviceKind:[I
      76: aload_0
      77: invokevirtual #39                 // Method getKind:()Lorg/aspectj/lang/reflect/AdviceKind;
      80: invokevirtual #45                 // Method org/aspectj/lang/reflect/AdviceKind.ordinal:()I
      83: iaload
      84: tableswitch   { // 1 to 5
                     1: 120
                     2: 130
                     3: 140
                     4: 150
                     5: 160
               default: 167
          }
     120: aload_1
     121: ldc           #46                 // String after(
     123: invokevirtual #37                 // Method java/lang/StringBuffer.append:(Ljava/lang/String;)Ljava/lang/StringBuffer;
     126: pop
     127: goto          167
     130: aload_1
     131: ldc           #46                 // String after(
     133: invokevirtual #37                 // Method java/lang/StringBuffer.append:(Ljava/lang/String;)Ljava/lang/StringBuffer;
     136: pop
     137: goto          167
     140: aload_1
     141: ldc           #46                 // String after(
     143: invokevirtual #37                 // Method java/lang/StringBuffer.append:(Ljava/lang/String;)Ljava/lang/StringBuffer;
     146: pop
     147: goto          167
     150: aload_1
     151: ldc           #47                 // String around(
     153: invokevirtual #37                 // Method java/lang/StringBuffer.append:(Ljava/lang/String;)Ljava/lang/StringBuffer;
     156: pop
     157: goto          167
     160: aload_1
     161: ldc           #48                 // String before(
     163: invokevirtual #37                 // Method java/lang/StringBuffer.append:(Ljava/lang/String;)Ljava/lang/StringBuffer;
     166: pop
     167: aload_0
     168: invokevirtual #49                 // Method getParameterTypes:()[Lorg/aspectj/lang/reflect/AjType;
     171: astore_2
     172: aload_2
     173: arraylength
     174: istore_3
     175: aload_0
     176: getfield      #2                  // Field hasExtraParam:Z
     179: ifeq          185
     182: iinc          3, -1
     185: iconst_0
     186: istore        4
     188: iload         4
     190: iload_3
     191: if_icmpge     229
     194: aload_1
     195: aload_2
     196: iload         4
     198: aaload
     199: invokeinterface #50,  1           // InterfaceMethod org/aspectj/lang/reflect/AjType.getName:()Ljava/lang/String;
     204: invokevirtual #37                 // Method java/lang/StringBuffer.append:(Ljava/lang/String;)Ljava/lang/StringBuffer;
     207: pop
     208: iload         4
     210: iconst_1
     211: iadd
     212: iload_3
     213: if_icmpge     223
     216: aload_1
     217: ldc           #51                 // String ,
     219: invokevirtual #37                 // Method java/lang/StringBuffer.append:(Ljava/lang/String;)Ljava/lang/StringBuffer;
     222: pop
     223: iinc          4, 1
     226: goto          188
     229: aload_1
     230: ldc           #52                 // String )
     232: invokevirtual #37                 // Method java/lang/StringBuffer.append:(Ljava/lang/String;)Ljava/lang/StringBuffer;
     235: pop
     236: getstatic     #44                 // Field org/aspectj/internal/lang/reflect/AdviceImpl$1.$SwitchMap$org$aspectj$lang$reflect$AdviceKind:[I
     239: aload_0
     240: invokevirtual #39                 // Method getKind:()Lorg/aspectj/lang/reflect/AdviceKind;
     243: invokevirtual #45                 // Method org/aspectj/lang/reflect/AdviceKind.ordinal:()I
     246: iaload
     247: lookupswitch  { // 2
                     2: 272
                     3: 315
               default: 358
          }
     272: aload_1
     273: ldc           #53                 // String returning
     275: invokevirtual #37                 // Method java/lang/StringBuffer.append:(Ljava/lang/String;)Ljava/lang/StringBuffer;
     278: pop
     279: aload_0
     280: getfield      #2                  // Field hasExtraParam:Z
     283: ifeq          315
     286: aload_1
     287: ldc           #54                 // String (
     289: invokevirtual #37                 // Method java/lang/StringBuffer.append:(Ljava/lang/String;)Ljava/lang/StringBuffer;
     292: pop
     293: aload_1
     294: aload_2
     295: iload_3
     296: iconst_1
     297: isub
     298: aaload
     299: invokeinterface #50,  1           // InterfaceMethod org/aspectj/lang/reflect/AjType.getName:()Ljava/lang/String;
     304: invokevirtual #37                 // Method java/lang/StringBuffer.append:(Ljava/lang/String;)Ljava/lang/StringBuffer;
     307: pop
     308: aload_1
     309: ldc           #52                 // String )
     311: invokevirtual #37                 // Method java/lang/StringBuffer.append:(Ljava/lang/String;)Ljava/lang/StringBuffer;
     314: pop
     315: aload_1
     316: ldc           #55                 // String throwing
     318: invokevirtual #37                 // Method java/lang/StringBuffer.append:(Ljava/lang/String;)Ljava/lang/StringBuffer;
     321: pop
     322: aload_0
     323: getfield      #2                  // Field hasExtraParam:Z
     326: ifeq          358
     329: aload_1
     330: ldc           #54                 // String (
     332: invokevirtual #37                 // Method java/lang/StringBuffer.append:(Ljava/lang/String;)Ljava/lang/StringBuffer;
     335: pop
     336: aload_1
     337: aload_2
     338: iload_3
     339: iconst_1
     340: isub
     341: aaload
     342: invokeinterface #50,  1           // InterfaceMethod org/aspectj/lang/reflect/AjType.getName:()Ljava/lang/String;
     347: invokevirtual #37                 // Method java/lang/StringBuffer.append:(Ljava/lang/String;)Ljava/lang/StringBuffer;
     350: pop
     351: aload_1
     352: ldc           #52                 // String )
     354: invokevirtual #37                 // Method java/lang/StringBuffer.append:(Ljava/lang/String;)Ljava/lang/StringBuffer;
     357: pop
     358: aload_0
     359: invokevirtual #56                 // Method getExceptionTypes:()[Lorg/aspectj/lang/reflect/AjType;
     362: astore        4
     364: aload         4
     366: arraylength
     367: ifle          433
     370: aload_1
     371: ldc           #57                 // String throws
     373: invokevirtual #37                 // Method java/lang/StringBuffer.append:(Ljava/lang/String;)Ljava/lang/StringBuffer;
     376: pop
     377: iconst_0
     378: istore        5
     380: iload         5
     382: aload         4
     384: arraylength
     385: if_icmpge     426
     388: aload_1
     389: aload         4
     391: iload         5
     393: aaload
     394: invokeinterface #50,  1           // InterfaceMethod org/aspectj/lang/reflect/AjType.getName:()Ljava/lang/String;
     399: invokevirtual #37                 // Method java/lang/StringBuffer.append:(Ljava/lang/String;)Ljava/lang/StringBuffer;
     402: pop
     403: iload         5
     405: iconst_1
     406: iadd
     407: aload         4
     409: arraylength
     410: if_icmpge     420
     413: aload_1
     414: ldc           #51                 // String ,
     416: invokevirtual #37                 // Method java/lang/StringBuffer.append:(Ljava/lang/String;)Ljava/lang/StringBuffer;
     419: pop
     420: iinc          5, 1
     423: goto          380
     426: aload_1
     427: ldc           #43                 // String
     429: invokevirtual #37                 // Method java/lang/StringBuffer.append:(Ljava/lang/String;)Ljava/lang/StringBuffer;
     432: pop
     433: aload_1
     434: ldc           #58                 // String :
     436: invokevirtual #37                 // Method java/lang/StringBuffer.append:(Ljava/lang/String;)Ljava/lang/StringBuffer;
     439: pop
     440: aload_1
     441: aload_0
     442: invokevirtual #59                 // Method getPointcutExpression:()Lorg/aspectj/lang/reflect/PointcutExpression;
     445: invokeinterface #60,  1           // InterfaceMethod org/aspectj/lang/reflect/PointcutExpression.asString:()Ljava/lang/String;
     450: invokevirtual #37                 // Method java/lang/StringBuffer.append:(Ljava/lang/String;)Ljava/lang/StringBuffer;
     453: pop
     454: aload_1
     455: invokevirtual #61                 // Method java/lang/StringBuffer.toString:()Ljava/lang/String;
     458: areturn
}
