Compiled from "UnlinkedJythonOperationsImpl.java"
public class freemarker.ext.ant.UnlinkedJythonOperationsImpl implements freemarker.ext.ant.UnlinkedJythonOperations {
  public freemarker.ext.ant.UnlinkedJythonOperationsImpl();
    Code:
       0: aload_0
       1: invokespecial #1                  // Method java/lang/Object."<init>":()V
       4: return

  public void execute(java.lang.String, java.util.Map) throws org.apache.tools.ant.BuildException;
    Code:
       0: aload_0
       1: aload_2
       2: invokespecial #2                  // Method createInterpreter:(Ljava/util/Map;)Lorg/python/util/PythonInterpreter;
       5: astore_3
       6: aload_3
       7: aload_1
       8: invokevirtual #3                  // Method org/python/util/PythonInterpreter.exec:(Ljava/lang/String;)V
      11: return

  public void execute(java.io.File, java.util.Map) throws org.apache.tools.ant.BuildException;
    Code:
       0: aload_0
       1: aload_2
       2: invokespecial #2                  // Method createInterpreter:(Ljava/util/Map;)Lorg/python/util/PythonInterpreter;
       5: astore_3
       6: aload_3
       7: aload_1
       8: invokevirtual #4                  // Method java/io/File.getCanonicalPath:()Ljava/lang/String;
      11: invokevirtual #5                  // Method org/python/util/PythonInterpreter.execfile:(Ljava/lang/String;)V
      14: goto          29
      17: astore        4
      19: new           #7                  // class org/apache/tools/ant/BuildException
      22: dup
      23: aload         4
      25: invokespecial #8                  // Method org/apache/tools/ant/BuildException."<init>":(Ljava/lang/Throwable;)V
      28: athrow
      29: return
    Exception table:
       from    to  target type
           6    14    17   Class java/io/IOException

  private org.python.util.PythonInterpreter createInterpreter(java.util.Map);
    Code:
       0: new           #9                  // class org/python/util/PythonInterpreter
       3: dup
       4: invokespecial #10                 // Method org/python/util/PythonInterpreter."<init>":()V
       7: astore_2
       8: aload_1
       9: invokeinterface #11,  1           // InterfaceMethod java/util/Map.entrySet:()Ljava/util/Set;
      14: invokeinterface #12,  1           // InterfaceMethod java/util/Set.iterator:()Ljava/util/Iterator;
      19: astore_3
      20: aload_3
      21: invokeinterface #13,  1           // InterfaceMethod java/util/Iterator.hasNext:()Z
      26: ifeq          64
      29: aload_3
      30: invokeinterface #14,  1           // InterfaceMethod java/util/Iterator.next:()Ljava/lang/Object;
      35: checkcast     #15                 // class java/util/Map$Entry
      38: astore        4
      40: aload_2
      41: aload         4
      43: invokeinterface #16,  1           // InterfaceMethod java/util/Map$Entry.getKey:()Ljava/lang/Object;
      48: checkcast     #17                 // class java/lang/String
      51: aload         4
      53: invokeinterface #18,  1           // InterfaceMethod java/util/Map$Entry.getValue:()Ljava/lang/Object;
      58: invokevirtual #19                 // Method org/python/util/PythonInterpreter.set:(Ljava/lang/String;Ljava/lang/Object;)V
      61: goto          20
      64: aload_2
      65: areturn
}
