Compiled from "ResumableAsyncHandler.java"
class org.asynchttpclient.handler.resumable.ResumableAsyncHandler$NULLResumableListener implements org.asynchttpclient.handler.resumable.ResumableListener {
  private long length;

  private org.asynchttpclient.handler.resumable.ResumableAsyncHandler$NULLResumableListener();
    Code:
       0: aload_0
       1: invokespecial #2                  // Method java/lang/Object."<init>":()V
       4: aload_0
       5: lconst_0
       6: putfield      #3                  // Field length:J
       9: return

  public void onBytesReceived(java.nio.ByteBuffer);
    Code:
       0: aload_0
       1: dup
       2: getfield      #3                  // Field length:J
       5: aload_1
       6: invokevirtual #4                  // Method java/nio/ByteBuffer.remaining:()I
       9: i2l
      10: ladd
      11: putfield      #3                  // Field length:J
      14: return

  public void onAllBytesReceived();
    Code:
       0: return

  public long length();
    Code:
       0: aload_0
       1: getfield      #3                  // Field length:J
       4: lreturn

  org.asynchttpclient.handler.resumable.ResumableAsyncHandler$NULLResumableListener(org.asynchttpclient.handler.resumable.ResumableAsyncHandler$1);
    Code:
       0: aload_0
       1: invokespecial #1                  // Method "<init>":()V
       4: return
}
