Compiled from "Event.java"
public final class io.dekorate.deps.snakeyaml.events.Event$ID extends java.lang.Enum<io.dekorate.deps.snakeyaml.events.Event$ID> {
  public static final io.dekorate.deps.snakeyaml.events.Event$ID Alias;

  public static final io.dekorate.deps.snakeyaml.events.Event$ID DocumentEnd;

  public static final io.dekorate.deps.snakeyaml.events.Event$ID DocumentStart;

  public static final io.dekorate.deps.snakeyaml.events.Event$ID MappingEnd;

  public static final io.dekorate.deps.snakeyaml.events.Event$ID MappingStart;

  public static final io.dekorate.deps.snakeyaml.events.Event$ID Scalar;

  public static final io.dekorate.deps.snakeyaml.events.Event$ID SequenceEnd;

  public static final io.dekorate.deps.snakeyaml.events.Event$ID SequenceStart;

  public static final io.dekorate.deps.snakeyaml.events.Event$ID StreamEnd;

  public static final io.dekorate.deps.snakeyaml.events.Event$ID StreamStart;

  private static final io.dekorate.deps.snakeyaml.events.Event$ID[] $VALUES;

  public static io.dekorate.deps.snakeyaml.events.Event$ID[] values();
    Code:
       0: getstatic     #26                 // Field $VALUES:[Lio/dekorate/deps/snakeyaml/events/Event$ID;
       3: invokevirtual #31                 // Method "[Lio/dekorate/deps/snakeyaml/events/Event$ID;".clone:()Ljava/lang/Object;
       6: checkcast     #27                 // class "[Lio/dekorate/deps/snakeyaml/events/Event$ID;"
       9: areturn

  public static io.dekorate.deps.snakeyaml.events.Event$ID valueOf(java.lang.String);
    Code:
       0: ldc           #2                  // class io/dekorate/deps/snakeyaml/events/Event$ID
       2: aload_0
       3: invokestatic  #36                 // Method java/lang/Enum.valueOf:(Ljava/lang/Class;Ljava/lang/String;)Ljava/lang/Enum;
       6: checkcast     #2                  // class io/dekorate/deps/snakeyaml/events/Event$ID
       9: areturn

  private io.dekorate.deps.snakeyaml.events.Event$ID();
    Code:
       0: aload_0
       1: aload_1
       2: iload_2
       3: invokespecial #43                 // Method java/lang/Enum."<init>":(Ljava/lang/String;I)V
       6: return

  static {};
    Code:
       0: new           #2                  // class io/dekorate/deps/snakeyaml/events/Event$ID
       3: dup
       4: ldc           #46                 // String Alias
       6: iconst_0
       7: invokespecial #47                 // Method "<init>":(Ljava/lang/String;I)V
      10: putstatic     #49                 // Field Alias:Lio/dekorate/deps/snakeyaml/events/Event$ID;
      13: new           #2                  // class io/dekorate/deps/snakeyaml/events/Event$ID
      16: dup
      17: ldc           #50                 // String DocumentEnd
      19: iconst_1
      20: invokespecial #47                 // Method "<init>":(Ljava/lang/String;I)V
      23: putstatic     #52                 // Field DocumentEnd:Lio/dekorate/deps/snakeyaml/events/Event$ID;
      26: new           #2                  // class io/dekorate/deps/snakeyaml/events/Event$ID
      29: dup
      30: ldc           #53                 // String DocumentStart
      32: iconst_2
      33: invokespecial #47                 // Method "<init>":(Ljava/lang/String;I)V
      36: putstatic     #55                 // Field DocumentStart:Lio/dekorate/deps/snakeyaml/events/Event$ID;
      39: new           #2                  // class io/dekorate/deps/snakeyaml/events/Event$ID
      42: dup
      43: ldc           #56                 // String MappingEnd
      45: iconst_3
      46: invokespecial #47                 // Method "<init>":(Ljava/lang/String;I)V
      49: putstatic     #58                 // Field MappingEnd:Lio/dekorate/deps/snakeyaml/events/Event$ID;
      52: new           #2                  // class io/dekorate/deps/snakeyaml/events/Event$ID
      55: dup
      56: ldc           #59                 // String MappingStart
      58: iconst_4
      59: invokespecial #47                 // Method "<init>":(Ljava/lang/String;I)V
      62: putstatic     #61                 // Field MappingStart:Lio/dekorate/deps/snakeyaml/events/Event$ID;
      65: new           #2                  // class io/dekorate/deps/snakeyaml/events/Event$ID
      68: dup
      69: ldc           #62                 // String Scalar
      71: iconst_5
      72: invokespecial #47                 // Method "<init>":(Ljava/lang/String;I)V
      75: putstatic     #64                 // Field Scalar:Lio/dekorate/deps/snakeyaml/events/Event$ID;
      78: new           #2                  // class io/dekorate/deps/snakeyaml/events/Event$ID
      81: dup
      82: ldc           #65                 // String SequenceEnd
      84: bipush        6
      86: invokespecial #47                 // Method "<init>":(Ljava/lang/String;I)V
      89: putstatic     #67                 // Field SequenceEnd:Lio/dekorate/deps/snakeyaml/events/Event$ID;
      92: new           #2                  // class io/dekorate/deps/snakeyaml/events/Event$ID
      95: dup
      96: ldc           #68                 // String SequenceStart
      98: bipush        7
     100: invokespecial #47                 // Method "<init>":(Ljava/lang/String;I)V
     103: putstatic     #70                 // Field SequenceStart:Lio/dekorate/deps/snakeyaml/events/Event$ID;
     106: new           #2                  // class io/dekorate/deps/snakeyaml/events/Event$ID
     109: dup
     110: ldc           #71                 // String StreamEnd
     112: bipush        8
     114: invokespecial #47                 // Method "<init>":(Ljava/lang/String;I)V
     117: putstatic     #73                 // Field StreamEnd:Lio/dekorate/deps/snakeyaml/events/Event$ID;
     120: new           #2                  // class io/dekorate/deps/snakeyaml/events/Event$ID
     123: dup
     124: ldc           #74                 // String StreamStart
     126: bipush        9
     128: invokespecial #47                 // Method "<init>":(Ljava/lang/String;I)V
     131: putstatic     #76                 // Field StreamStart:Lio/dekorate/deps/snakeyaml/events/Event$ID;
     134: bipush        10
     136: anewarray     #2                  // class io/dekorate/deps/snakeyaml/events/Event$ID
     139: dup
     140: iconst_0
     141: getstatic     #49                 // Field Alias:Lio/dekorate/deps/snakeyaml/events/Event$ID;
     144: aastore
     145: dup
     146: iconst_1
     147: getstatic     #52                 // Field DocumentEnd:Lio/dekorate/deps/snakeyaml/events/Event$ID;
     150: aastore
     151: dup
     152: iconst_2
     153: getstatic     #55                 // Field DocumentStart:Lio/dekorate/deps/snakeyaml/events/Event$ID;
     156: aastore
     157: dup
     158: iconst_3
     159: getstatic     #58                 // Field MappingEnd:Lio/dekorate/deps/snakeyaml/events/Event$ID;
     162: aastore
     163: dup
     164: iconst_4
     165: getstatic     #61                 // Field MappingStart:Lio/dekorate/deps/snakeyaml/events/Event$ID;
     168: aastore
     169: dup
     170: iconst_5
     171: getstatic     #64                 // Field Scalar:Lio/dekorate/deps/snakeyaml/events/Event$ID;
     174: aastore
     175: dup
     176: bipush        6
     178: getstatic     #67                 // Field SequenceEnd:Lio/dekorate/deps/snakeyaml/events/Event$ID;
     181: aastore
     182: dup
     183: bipush        7
     185: getstatic     #70                 // Field SequenceStart:Lio/dekorate/deps/snakeyaml/events/Event$ID;
     188: aastore
     189: dup
     190: bipush        8
     192: getstatic     #73                 // Field StreamEnd:Lio/dekorate/deps/snakeyaml/events/Event$ID;
     195: aastore
     196: dup
     197: bipush        9
     199: getstatic     #76                 // Field StreamStart:Lio/dekorate/deps/snakeyaml/events/Event$ID;
     202: aastore
     203: putstatic     #26                 // Field $VALUES:[Lio/dekorate/deps/snakeyaml/events/Event$ID;
     206: return
}
