Compiled from "AbstractContext.java"
public abstract class org.apache.velocity.context.AbstractContext extends org.apache.velocity.context.InternalContextBase implements org.apache.velocity.context.Context {
  private org.apache.velocity.context.Context innerContext;

  public abstract java.lang.Object internalGet(java.lang.String);

  public abstract java.lang.Object internalPut(java.lang.String, java.lang.Object);

  public abstract boolean internalContainsKey(java.lang.Object);

  public abstract java.lang.Object[] internalGetKeys();

  public abstract java.lang.Object internalRemove(java.lang.Object);

  public org.apache.velocity.context.AbstractContext();
    Code:
       0: aload_0
       1: invokespecial #1                  // Method org/apache/velocity/context/InternalContextBase."<init>":()V
       4: aload_0
       5: aconst_null
       6: putfield      #2                  // Field innerContext:Lorg/apache/velocity/context/Context;
       9: return

  public org.apache.velocity.context.AbstractContext(org.apache.velocity.context.Context);
    Code:
       0: aload_0
       1: invokespecial #1                  // Method org/apache/velocity/context/InternalContextBase."<init>":()V
       4: aload_0
       5: aconst_null
       6: putfield      #2                  // Field innerContext:Lorg/apache/velocity/context/Context;
       9: aload_0
      10: aload_1
      11: putfield      #2                  // Field innerContext:Lorg/apache/velocity/context/Context;
      14: aload_0
      15: getfield      #2                  // Field innerContext:Lorg/apache/velocity/context/Context;
      18: instanceof    #3                  // class org/apache/velocity/context/InternalEventContext
      21: ifeq          41
      24: aload_0
      25: aload_0
      26: getfield      #2                  // Field innerContext:Lorg/apache/velocity/context/Context;
      29: checkcast     #3                  // class org/apache/velocity/context/InternalEventContext
      32: invokeinterface #4,  1            // InterfaceMethod org/apache/velocity/context/InternalEventContext.getEventCartridge:()Lorg/apache/velocity/app/event/EventCartridge;
      37: invokevirtual #5                  // Method attachEventCartridge:(Lorg/apache/velocity/app/event/EventCartridge;)Lorg/apache/velocity/app/event/EventCartridge;
      40: pop
      41: return

  public java.lang.Object put(java.lang.String, java.lang.Object);
    Code:
       0: aload_1
       1: ifnonnull     6
       4: aconst_null
       5: areturn
       6: aload_0
       7: aload_1
       8: invokevirtual #6                  // Method java/lang/String.intern:()Ljava/lang/String;
      11: aload_2
      12: invokevirtual #7                  // Method internalPut:(Ljava/lang/String;Ljava/lang/Object;)Ljava/lang/Object;
      15: areturn

  public java.lang.Object get(java.lang.String);
    Code:
       0: aload_1
       1: ifnonnull     6
       4: aconst_null
       5: areturn
       6: aload_0
       7: aload_1
       8: invokevirtual #8                  // Method internalGet:(Ljava/lang/String;)Ljava/lang/Object;
      11: astore_2
      12: aload_2
      13: ifnonnull     34
      16: aload_0
      17: getfield      #2                  // Field innerContext:Lorg/apache/velocity/context/Context;
      20: ifnull        34
      23: aload_0
      24: getfield      #2                  // Field innerContext:Lorg/apache/velocity/context/Context;
      27: aload_1
      28: invokeinterface #9,  2            // InterfaceMethod org/apache/velocity/context/Context.get:(Ljava/lang/String;)Ljava/lang/Object;
      33: astore_2
      34: aload_2
      35: areturn

  public boolean containsKey(java.lang.Object);
    Code:
       0: aload_1
       1: ifnonnull     6
       4: iconst_0
       5: ireturn
       6: aload_0
       7: aload_1
       8: invokevirtual #10                 // Method internalContainsKey:(Ljava/lang/Object;)Z
      11: istore_2
      12: iload_2
      13: ifne          34
      16: aload_0
      17: getfield      #2                  // Field innerContext:Lorg/apache/velocity/context/Context;
      20: ifnull        34
      23: aload_0
      24: getfield      #2                  // Field innerContext:Lorg/apache/velocity/context/Context;
      27: aload_1
      28: invokeinterface #11,  2           // InterfaceMethod org/apache/velocity/context/Context.containsKey:(Ljava/lang/Object;)Z
      33: istore_2
      34: iload_2
      35: ireturn

  public java.lang.Object[] getKeys();
    Code:
       0: aload_0
       1: invokevirtual #12                 // Method internalGetKeys:()[Ljava/lang/Object;
       4: areturn

  public java.lang.Object remove(java.lang.Object);
    Code:
       0: aload_1
       1: ifnonnull     6
       4: aconst_null
       5: areturn
       6: aload_0
       7: aload_1
       8: invokevirtual #13                 // Method internalRemove:(Ljava/lang/Object;)Ljava/lang/Object;
      11: areturn

  public org.apache.velocity.context.Context getChainedContext();
    Code:
       0: aload_0
       1: getfield      #2                  // Field innerContext:Lorg/apache/velocity/context/Context;
       4: areturn
}
