Compiled from "InfinityNumberComparatorHelper.java"
public final class org.hibernate.validator.internal.constraintvalidators.bv.number.InfinityNumberComparatorHelper {
  public static final java.util.OptionalInt LESS_THAN;

  public static final java.util.OptionalInt FINITE_VALUE;

  public static final java.util.OptionalInt GREATER_THAN;

  private org.hibernate.validator.internal.constraintvalidators.bv.number.InfinityNumberComparatorHelper();
    Code:
       0: aload_0
       1: invokespecial #1                  // Method java/lang/Object."<init>":()V
       4: return

  public static java.util.OptionalInt infinityCheck(java.lang.Double, java.util.OptionalInt);
    Code:
       0: getstatic     #7                  // Field FINITE_VALUE:Ljava/util/OptionalInt;
       3: astore_2
       4: aload_0
       5: invokevirtual #13                 // Method java/lang/Double.doubleValue:()D
       8: ldc2_w        #19                 // double -Infinityd
      11: dcmpl
      12: ifne          22
      15: getstatic     #21                 // Field LESS_THAN:Ljava/util/OptionalInt;
      18: astore_2
      19: goto          49
      22: aload_0
      23: invokevirtual #24                 // Method java/lang/Double.isNaN:()Z
      26: ifeq          34
      29: aload_1
      30: astore_2
      31: goto          49
      34: aload_0
      35: invokevirtual #13                 // Method java/lang/Double.doubleValue:()D
      38: ldc2_w        #28                 // double Infinityd
      41: dcmpl
      42: ifne          49
      45: getstatic     #30                 // Field GREATER_THAN:Ljava/util/OptionalInt;
      48: astore_2
      49: aload_2
      50: areturn

  public static java.util.OptionalInt infinityCheck(java.lang.Float, java.util.OptionalInt);
    Code:
       0: getstatic     #7                  // Field FINITE_VALUE:Ljava/util/OptionalInt;
       3: astore_2
       4: aload_0
       5: invokevirtual #33                 // Method java/lang/Float.floatValue:()F
       8: ldc           #39                 // float -Infinityf
      10: fcmpl
      11: ifne          21
      14: getstatic     #21                 // Field LESS_THAN:Ljava/util/OptionalInt;
      17: astore_2
      18: goto          47
      21: aload_0
      22: invokevirtual #40                 // Method java/lang/Float.isNaN:()Z
      25: ifeq          33
      28: aload_1
      29: astore_2
      30: goto          47
      33: aload_0
      34: invokevirtual #33                 // Method java/lang/Float.floatValue:()F
      37: ldc           #41                 // float Infinityf
      39: fcmpl
      40: ifne          47
      43: getstatic     #30                 // Field GREATER_THAN:Ljava/util/OptionalInt;
      46: astore_2
      47: aload_2
      48: areturn

  static {};
    Code:
       0: iconst_m1
       1: invokestatic  #42                 // Method java/util/OptionalInt.of:(I)Ljava/util/OptionalInt;
       4: putstatic     #21                 // Field LESS_THAN:Ljava/util/OptionalInt;
       7: invokestatic  #48                 // Method java/util/OptionalInt.empty:()Ljava/util/OptionalInt;
      10: putstatic     #7                  // Field FINITE_VALUE:Ljava/util/OptionalInt;
      13: iconst_1
      14: invokestatic  #42                 // Method java/util/OptionalInt.of:(I)Ljava/util/OptionalInt;
      17: putstatic     #30                 // Field GREATER_THAN:Ljava/util/OptionalInt;
      20: return
}
