Compiled from "MetadataFlow.java"
public final class co.cask.cdap.metadata.MetadataFlow extends co.cask.cdap.api.flow.AbstractFlow {
  public static final java.lang.String FLOW_NAME;

  private final co.cask.cdap.metadata.config.NavigatorAppConfig navigatorAppConfig;

  public co.cask.cdap.metadata.MetadataFlow(co.cask.cdap.metadata.config.NavigatorAppConfig);
    Code:
       0: aload_0
       1: invokespecial #1                  // Method co/cask/cdap/api/flow/AbstractFlow."<init>":()V
       4: aload_0
       5: aload_1
       6: putfield      #2                  // Field navigatorAppConfig:Lco/cask/cdap/metadata/config/NavigatorAppConfig;
       9: return

  public void configure();
    Code:
       0: aload_0
       1: ldc           #3                  // String MetadataFlow
       3: invokevirtual #4                  // Method setName:(Ljava/lang/String;)V
       6: aload_0
       7: ldc           #5                  // String Flow that subscribes to Metadata changes and propagates the same to Navigator
       9: invokevirtual #6                  // Method setDescription:(Ljava/lang/String;)V
      12: aload_0
      13: ldc           #7                  // String auditLogConsumer
      15: new           #8                  // class co/cask/cdap/metadata/AuditLogConsumer
      18: dup
      19: aload_0
      20: getfield      #2                  // Field navigatorAppConfig:Lco/cask/cdap/metadata/config/NavigatorAppConfig;
      23: invokevirtual #9                  // Method co/cask/cdap/metadata/config/NavigatorAppConfig.getAuditLogConfig:()Lco/cask/cdap/metadata/config/AuditLogConfig;
      26: invokespecial #10                 // Method co/cask/cdap/metadata/AuditLogConsumer."<init>":(Lco/cask/cdap/metadata/config/AuditLogConfig;)V
      29: invokevirtual #11                 // Method addFlowlet:(Ljava/lang/String;Lco/cask/cdap/api/flow/flowlet/Flowlet;)V
      32: aload_0
      33: ldc           #12                 // String navigatorPublisher
      35: new           #13                 // class co/cask/cdap/metadata/NavigatorPublisher
      38: dup
      39: aload_0
      40: getfield      #2                  // Field navigatorAppConfig:Lco/cask/cdap/metadata/config/NavigatorAppConfig;
      43: invokevirtual #14                 // Method co/cask/cdap/metadata/config/NavigatorAppConfig.getNavigatorConfig:()Lco/cask/cdap/metadata/config/NavigatorConfig;
      46: invokespecial #15                 // Method co/cask/cdap/metadata/NavigatorPublisher."<init>":(Lco/cask/cdap/metadata/config/NavigatorConfig;)V
      49: invokevirtual #11                 // Method addFlowlet:(Ljava/lang/String;Lco/cask/cdap/api/flow/flowlet/Flowlet;)V
      52: aload_0
      53: ldc           #7                  // String auditLogConsumer
      55: ldc           #12                 // String navigatorPublisher
      57: invokevirtual #16                 // Method connect:(Ljava/lang/String;Ljava/lang/String;)V
      60: return
}
