Compiled from "PropertyContext.java"
public class de.flapdoodle.mongoom.mapping.context.PropertyContext<T> implements de.flapdoodle.mongoom.mapping.context.IPropertyContext<T>, de.flapdoodle.mongoom.mapping.entities.IBeanContext<T> {
  private final de.flapdoodle.mongoom.mapping.entities.PropertyTransformationMap propertyTransformationMap;

  private final de.flapdoodle.mongoom.mapping.context.IPropertyContext<?> _parentContext;

  private final de.flapdoodle.mongoom.mapping.properties.IProperty<T> _property;

  public de.flapdoodle.mongoom.mapping.context.PropertyContext(de.flapdoodle.mongoom.mapping.context.IPropertyContext<?>, de.flapdoodle.mongoom.mapping.properties.IProperty<T>);
    Code:
       0: aload_0
       1: invokespecial #3                  // Method java/lang/Object."<init>":()V
       4: aload_0
       5: new           #4                  // class de/flapdoodle/mongoom/mapping/entities/PropertyTransformationMap
       8: dup
       9: invokespecial #5                  // Method de/flapdoodle/mongoom/mapping/entities/PropertyTransformationMap."<init>":()V
      12: putfield      #6                  // Field propertyTransformationMap:Lde/flapdoodle/mongoom/mapping/entities/PropertyTransformationMap;
      15: aload_0
      16: aload_1
      17: putfield      #1                  // Field _parentContext:Lde/flapdoodle/mongoom/mapping/context/IPropertyContext;
      20: aload_0
      21: aload_2
      22: putfield      #2                  // Field _property:Lde/flapdoodle/mongoom/mapping/properties/IProperty;
      25: return

  public de.flapdoodle.mongoom.mapping.context.PropertyContext(de.flapdoodle.mongoom.mapping.context.IPropertyContext<?>);
    Code:
       0: aload_0
       1: aload_1
       2: aconst_null
       3: invokespecial #7                  // Method "<init>":(Lde/flapdoodle/mongoom/mapping/context/IPropertyContext;Lde/flapdoodle/mongoom/mapping/properties/IProperty;)V
       6: return

  public <S> de.flapdoodle.mongoom.mapping.context.IPropertyContext<S> contextFor(de.flapdoodle.mongoom.mapping.properties.IProperty<S>);
    Code:
       0: new           #8                  // class de/flapdoodle/mongoom/mapping/context/PropertyContext
       3: dup
       4: aload_0
       5: aload_1
       6: invokespecial #7                  // Method "<init>":(Lde/flapdoodle/mongoom/mapping/context/IPropertyContext;Lde/flapdoodle/mongoom/mapping/properties/IProperty;)V
       9: areturn

  public <S> void setTransformation(de.flapdoodle.mongoom.mapping.properties.IProperty<S>, de.flapdoodle.mongoom.mapping.ITransformation<S, ?>);
    Code:
       0: aload_0
       1: getfield      #6                  // Field propertyTransformationMap:Lde/flapdoodle/mongoom/mapping/entities/PropertyTransformationMap;
       4: aload_1
       5: aload_2
       6: invokevirtual #9                  // Method de/flapdoodle/mongoom/mapping/entities/PropertyTransformationMap.setTransformation:(Lde/flapdoodle/mongoom/mapping/properties/IProperty;Lde/flapdoodle/mongoom/mapping/ITransformation;)V
       9: return

  public de.flapdoodle.mongoom.mapping.entities.IPropertyTransformations getPropertyTransformations();
    Code:
       0: aload_0
       1: getfield      #6                  // Field propertyTransformationMap:Lde/flapdoodle/mongoom/mapping/entities/PropertyTransformationMap;
       4: invokevirtual #10                 // Method de/flapdoodle/mongoom/mapping/entities/PropertyTransformationMap.readOnly:()Lde/flapdoodle/mongoom/mapping/entities/IPropertyTransformations;
       7: areturn

  public java.lang.Class<T> getViewClass();
    Code:
       0: aload_0
       1: getfield      #2                  // Field _property:Lde/flapdoodle/mongoom/mapping/properties/IProperty;
       4: invokeinterface #11,  1           // InterfaceMethod de/flapdoodle/mongoom/mapping/properties/IProperty.getType:()Ljava/lang/Class;
       9: areturn

  public de.flapdoodle.mongoom.datastore.index.IPropertyIndex propertyIndex();
    Code:
       0: new           #12                 // class de/flapdoodle/mongoom/mapping/context/PropertyContext$Index
       3: dup
       4: aload_0
       5: invokespecial #13                 // Method de/flapdoodle/mongoom/mapping/context/PropertyContext$Index."<init>":(Lde/flapdoodle/mongoom/mapping/context/PropertyContext;)V
       8: areturn

  public void addIndexedInGroup(de.flapdoodle.mongoom.mapping.properties.IPropertyMappedName, de.flapdoodle.mongoom.annotations.index.IndexedInGroup);
    Code:
       0: aload_0
       1: getfield      #1                  // Field _parentContext:Lde/flapdoodle/mongoom/mapping/context/IPropertyContext;
       4: aload_0
       5: getfield      #2                  // Field _property:Lde/flapdoodle/mongoom/mapping/properties/IProperty;
       8: ifnull        27
      11: aload_0
      12: getfield      #2                  // Field _property:Lde/flapdoodle/mongoom/mapping/properties/IProperty;
      15: invokeinterface #14,  1           // InterfaceMethod de/flapdoodle/mongoom/mapping/properties/IProperty.name:()Lde/flapdoodle/mongoom/mapping/naming/PropertyName;
      20: aload_1
      21: invokestatic  #15                 // Method de/flapdoodle/mongoom/mapping/properties/Property.append:(Lde/flapdoodle/mongoom/mapping/properties/IPropertyMappedName;Lde/flapdoodle/mongoom/mapping/properties/IPropertyMappedName;)Lde/flapdoodle/mongoom/mapping/properties/IPropertyMappedName;
      24: goto          28
      27: aload_1
      28: aload_2
      29: invokeinterface #16,  3           // InterfaceMethod de/flapdoodle/mongoom/mapping/context/IPropertyContext.addIndexedInGroup:(Lde/flapdoodle/mongoom/mapping/properties/IPropertyMappedName;Lde/flapdoodle/mongoom/annotations/index/IndexedInGroup;)V
      34: return

  public void setIndexed(de.flapdoodle.mongoom.mapping.properties.IPropertyMappedName, de.flapdoodle.mongoom.annotations.index.Indexed);
    Code:
       0: aload_0
       1: getfield      #1                  // Field _parentContext:Lde/flapdoodle/mongoom/mapping/context/IPropertyContext;
       4: aload_0
       5: getfield      #2                  // Field _property:Lde/flapdoodle/mongoom/mapping/properties/IProperty;
       8: ifnull        27
      11: aload_0
      12: getfield      #2                  // Field _property:Lde/flapdoodle/mongoom/mapping/properties/IProperty;
      15: invokeinterface #14,  1           // InterfaceMethod de/flapdoodle/mongoom/mapping/properties/IProperty.name:()Lde/flapdoodle/mongoom/mapping/naming/PropertyName;
      20: aload_1
      21: invokestatic  #15                 // Method de/flapdoodle/mongoom/mapping/properties/Property.append:(Lde/flapdoodle/mongoom/mapping/properties/IPropertyMappedName;Lde/flapdoodle/mongoom/mapping/properties/IPropertyMappedName;)Lde/flapdoodle/mongoom/mapping/properties/IPropertyMappedName;
      24: goto          28
      27: aload_1
      28: aload_2
      29: invokeinterface #17,  3           // InterfaceMethod de/flapdoodle/mongoom/mapping/context/IPropertyContext.setIndexed:(Lde/flapdoodle/mongoom/mapping/properties/IPropertyMappedName;Lde/flapdoodle/mongoom/annotations/index/Indexed;)V
      34: return

  static de.flapdoodle.mongoom.mapping.properties.IProperty access$000(de.flapdoodle.mongoom.mapping.context.PropertyContext);
    Code:
       0: aload_0
       1: getfield      #2                  // Field _property:Lde/flapdoodle/mongoom/mapping/properties/IProperty;
       4: areturn

  static de.flapdoodle.mongoom.mapping.context.IPropertyContext access$100(de.flapdoodle.mongoom.mapping.context.PropertyContext);
    Code:
       0: aload_0
       1: getfield      #1                  // Field _parentContext:Lde/flapdoodle/mongoom/mapping/context/IPropertyContext;
       4: areturn
}
