Compiled from "OrderingSpecification.java"
public class org.hibernate.sql.ordering.antlr.OrderingSpecification extends org.hibernate.sql.ordering.antlr.NodeSupport {
  private boolean resolved;

  private org.hibernate.sql.ordering.antlr.OrderingSpecification$Ordering ordering;

  public org.hibernate.sql.ordering.antlr.OrderingSpecification();
    Code:
       0: aload_0
       1: invokespecial #1                  // Method org/hibernate/sql/ordering/antlr/NodeSupport."<init>":()V
       4: return

  public org.hibernate.sql.ordering.antlr.OrderingSpecification$Ordering getOrdering();
    Code:
       0: aload_0
       1: getfield      #2                  // Field resolved:Z
       4: ifne          23
       7: aload_0
       8: aload_0
       9: invokevirtual #3                  // Method getText:()Ljava/lang/String;
      12: invokestatic  #4                  // Method resolve:(Ljava/lang/String;)Lorg/hibernate/sql/ordering/antlr/OrderingSpecification$Ordering;
      15: putfield      #5                  // Field ordering:Lorg/hibernate/sql/ordering/antlr/OrderingSpecification$Ordering;
      18: aload_0
      19: iconst_1
      20: putfield      #2                  // Field resolved:Z
      23: aload_0
      24: getfield      #5                  // Field ordering:Lorg/hibernate/sql/ordering/antlr/OrderingSpecification$Ordering;
      27: areturn

  private static org.hibernate.sql.ordering.antlr.OrderingSpecification$Ordering resolve(java.lang.String);
    Code:
       0: getstatic     #6                  // Field org/hibernate/sql/ordering/antlr/OrderingSpecification$Ordering.ASCENDING:Lorg/hibernate/sql/ordering/antlr/OrderingSpecification$Ordering;
       3: invokestatic  #7                  // Method org/hibernate/sql/ordering/antlr/OrderingSpecification$Ordering.access$000:(Lorg/hibernate/sql/ordering/antlr/OrderingSpecification$Ordering;)Ljava/lang/String;
       6: aload_0
       7: invokevirtual #8                  // Method java/lang/String.equals:(Ljava/lang/Object;)Z
      10: ifeq          17
      13: getstatic     #6                  // Field org/hibernate/sql/ordering/antlr/OrderingSpecification$Ordering.ASCENDING:Lorg/hibernate/sql/ordering/antlr/OrderingSpecification$Ordering;
      16: areturn
      17: getstatic     #9                  // Field org/hibernate/sql/ordering/antlr/OrderingSpecification$Ordering.DESCENDING:Lorg/hibernate/sql/ordering/antlr/OrderingSpecification$Ordering;
      20: invokestatic  #7                  // Method org/hibernate/sql/ordering/antlr/OrderingSpecification$Ordering.access$000:(Lorg/hibernate/sql/ordering/antlr/OrderingSpecification$Ordering;)Ljava/lang/String;
      23: aload_0
      24: invokevirtual #8                  // Method java/lang/String.equals:(Ljava/lang/Object;)Z
      27: ifeq          34
      30: getstatic     #9                  // Field org/hibernate/sql/ordering/antlr/OrderingSpecification$Ordering.DESCENDING:Lorg/hibernate/sql/ordering/antlr/OrderingSpecification$Ordering;
      33: areturn
      34: new           #10                 // class java/lang/IllegalStateException
      37: dup
      38: new           #11                 // class java/lang/StringBuilder
      41: dup
      42: invokespecial #12                 // Method java/lang/StringBuilder."<init>":()V
      45: ldc           #13                 // String Unknown ordering [
      47: invokevirtual #14                 // Method java/lang/StringBuilder.append:(Ljava/lang/String;)Ljava/lang/StringBuilder;
      50: aload_0
      51: invokevirtual #14                 // Method java/lang/StringBuilder.append:(Ljava/lang/String;)Ljava/lang/StringBuilder;
      54: ldc           #15                 // String ]
      56: invokevirtual #14                 // Method java/lang/StringBuilder.append:(Ljava/lang/String;)Ljava/lang/StringBuilder;
      59: invokevirtual #16                 // Method java/lang/StringBuilder.toString:()Ljava/lang/String;
      62: invokespecial #17                 // Method java/lang/IllegalStateException."<init>":(Ljava/lang/String;)V
      65: athrow

  public java.lang.String getRenderableText();
    Code:
       0: aload_0
       1: invokevirtual #18                 // Method getOrdering:()Lorg/hibernate/sql/ordering/antlr/OrderingSpecification$Ordering;
       4: invokestatic  #7                  // Method org/hibernate/sql/ordering/antlr/OrderingSpecification$Ordering.access$000:(Lorg/hibernate/sql/ordering/antlr/OrderingSpecification$Ordering;)Ljava/lang/String;
       7: areturn
}
