Compiled from "Months.java"
public final class org.joda.time.Months extends org.joda.time.base.BaseSingleFieldPeriod {
  public static final org.joda.time.Months ZERO;

  public static final org.joda.time.Months ONE;

  public static final org.joda.time.Months TWO;

  public static final org.joda.time.Months THREE;

  public static final org.joda.time.Months FOUR;

  public static final org.joda.time.Months FIVE;

  public static final org.joda.time.Months SIX;

  public static final org.joda.time.Months SEVEN;

  public static final org.joda.time.Months EIGHT;

  public static final org.joda.time.Months NINE;

  public static final org.joda.time.Months TEN;

  public static final org.joda.time.Months ELEVEN;

  public static final org.joda.time.Months TWELVE;

  public static final org.joda.time.Months MAX_VALUE;

  public static final org.joda.time.Months MIN_VALUE;

  private static final org.joda.time.format.PeriodFormatter PARSER;

  private static final long serialVersionUID;

  public static org.joda.time.Months months(int);
    Code:
       0: iload_0
       1: lookupswitch  { // 15
           -2147483648: 188
                     0: 132
                     1: 136
                     2: 140
                     3: 144
                     4: 148
                     5: 152
                     6: 156
                     7: 160
                     8: 164
                     9: 168
                    10: 172
                    11: 176
                    12: 180
            2147483647: 184
               default: 192
          }
     132: getstatic     #1                  // Field ZERO:Lorg/joda/time/Months;
     135: areturn
     136: getstatic     #2                  // Field ONE:Lorg/joda/time/Months;
     139: areturn
     140: getstatic     #3                  // Field TWO:Lorg/joda/time/Months;
     143: areturn
     144: getstatic     #4                  // Field THREE:Lorg/joda/time/Months;
     147: areturn
     148: getstatic     #5                  // Field FOUR:Lorg/joda/time/Months;
     151: areturn
     152: getstatic     #6                  // Field FIVE:Lorg/joda/time/Months;
     155: areturn
     156: getstatic     #7                  // Field SIX:Lorg/joda/time/Months;
     159: areturn
     160: getstatic     #8                  // Field SEVEN:Lorg/joda/time/Months;
     163: areturn
     164: getstatic     #9                  // Field EIGHT:Lorg/joda/time/Months;
     167: areturn
     168: getstatic     #10                 // Field NINE:Lorg/joda/time/Months;
     171: areturn
     172: getstatic     #11                 // Field TEN:Lorg/joda/time/Months;
     175: areturn
     176: getstatic     #12                 // Field ELEVEN:Lorg/joda/time/Months;
     179: areturn
     180: getstatic     #13                 // Field TWELVE:Lorg/joda/time/Months;
     183: areturn
     184: getstatic     #14                 // Field MAX_VALUE:Lorg/joda/time/Months;
     187: areturn
     188: getstatic     #15                 // Field MIN_VALUE:Lorg/joda/time/Months;
     191: areturn
     192: new           #16                 // class org/joda/time/Months
     195: dup
     196: iload_0
     197: invokespecial #17                 // Method "<init>":(I)V
     200: areturn

  public static org.joda.time.Months monthsBetween(org.joda.time.ReadableInstant, org.joda.time.ReadableInstant);
    Code:
       0: aload_0
       1: aload_1
       2: invokestatic  #18                 // Method org/joda/time/DurationFieldType.months:()Lorg/joda/time/DurationFieldType;
       5: invokestatic  #19                 // Method org/joda/time/base/BaseSingleFieldPeriod.between:(Lorg/joda/time/ReadableInstant;Lorg/joda/time/ReadableInstant;Lorg/joda/time/DurationFieldType;)I
       8: istore_2
       9: iload_2
      10: invokestatic  #20                 // Method months:(I)Lorg/joda/time/Months;
      13: areturn

  public static org.joda.time.Months monthsBetween(org.joda.time.ReadablePartial, org.joda.time.ReadablePartial);
    Code:
       0: aload_0
       1: instanceof    #21                 // class org/joda/time/LocalDate
       4: ifeq          51
       7: aload_1
       8: instanceof    #21                 // class org/joda/time/LocalDate
      11: ifeq          51
      14: aload_0
      15: invokeinterface #22,  1           // InterfaceMethod org/joda/time/ReadablePartial.getChronology:()Lorg/joda/time/Chronology;
      20: invokestatic  #23                 // Method org/joda/time/DateTimeUtils.getChronology:(Lorg/joda/time/Chronology;)Lorg/joda/time/Chronology;
      23: astore_2
      24: aload_2
      25: invokevirtual #24                 // Method org/joda/time/Chronology.months:()Lorg/joda/time/DurationField;
      28: aload_1
      29: checkcast     #21                 // class org/joda/time/LocalDate
      32: invokevirtual #25                 // Method org/joda/time/LocalDate.getLocalMillis:()J
      35: aload_0
      36: checkcast     #21                 // class org/joda/time/LocalDate
      39: invokevirtual #25                 // Method org/joda/time/LocalDate.getLocalMillis:()J
      42: invokevirtual #26                 // Method org/joda/time/DurationField.getDifference:(JJ)I
      45: istore_3
      46: iload_3
      47: invokestatic  #20                 // Method months:(I)Lorg/joda/time/Months;
      50: areturn
      51: aload_0
      52: aload_1
      53: getstatic     #1                  // Field ZERO:Lorg/joda/time/Months;
      56: invokestatic  #27                 // Method org/joda/time/base/BaseSingleFieldPeriod.between:(Lorg/joda/time/ReadablePartial;Lorg/joda/time/ReadablePartial;Lorg/joda/time/ReadablePeriod;)I
      59: istore_2
      60: iload_2
      61: invokestatic  #20                 // Method months:(I)Lorg/joda/time/Months;
      64: areturn

  public static org.joda.time.Months monthsIn(org.joda.time.ReadableInterval);
    Code:
       0: aload_0
       1: ifnonnull     8
       4: getstatic     #1                  // Field ZERO:Lorg/joda/time/Months;
       7: areturn
       8: aload_0
       9: invokeinterface #28,  1           // InterfaceMethod org/joda/time/ReadableInterval.getStart:()Lorg/joda/time/DateTime;
      14: aload_0
      15: invokeinterface #29,  1           // InterfaceMethod org/joda/time/ReadableInterval.getEnd:()Lorg/joda/time/DateTime;
      20: invokestatic  #18                 // Method org/joda/time/DurationFieldType.months:()Lorg/joda/time/DurationFieldType;
      23: invokestatic  #19                 // Method org/joda/time/base/BaseSingleFieldPeriod.between:(Lorg/joda/time/ReadableInstant;Lorg/joda/time/ReadableInstant;Lorg/joda/time/DurationFieldType;)I
      26: istore_1
      27: iload_1
      28: invokestatic  #20                 // Method months:(I)Lorg/joda/time/Months;
      31: areturn

  public static org.joda.time.Months parseMonths(java.lang.String);
    Code:
       0: aload_0
       1: ifnonnull     8
       4: getstatic     #1                  // Field ZERO:Lorg/joda/time/Months;
       7: areturn
       8: getstatic     #30                 // Field PARSER:Lorg/joda/time/format/PeriodFormatter;
      11: aload_0
      12: invokevirtual #31                 // Method org/joda/time/format/PeriodFormatter.parsePeriod:(Ljava/lang/String;)Lorg/joda/time/Period;
      15: astore_1
      16: aload_1
      17: invokevirtual #32                 // Method org/joda/time/Period.getMonths:()I
      20: invokestatic  #20                 // Method months:(I)Lorg/joda/time/Months;
      23: areturn

  private org.joda.time.Months(int);
    Code:
       0: aload_0
       1: iload_1
       2: invokespecial #33                 // Method org/joda/time/base/BaseSingleFieldPeriod."<init>":(I)V
       5: return

  private java.lang.Object readResolve();
    Code:
       0: aload_0
       1: invokevirtual #34                 // Method getValue:()I
       4: invokestatic  #20                 // Method months:(I)Lorg/joda/time/Months;
       7: areturn

  public org.joda.time.DurationFieldType getFieldType();
    Code:
       0: invokestatic  #18                 // Method org/joda/time/DurationFieldType.months:()Lorg/joda/time/DurationFieldType;
       3: areturn

  public org.joda.time.PeriodType getPeriodType();
    Code:
       0: invokestatic  #35                 // Method org/joda/time/PeriodType.months:()Lorg/joda/time/PeriodType;
       3: areturn

  public int getMonths();
    Code:
       0: aload_0
       1: invokevirtual #34                 // Method getValue:()I
       4: ireturn

  public org.joda.time.Months plus(int);
    Code:
       0: iload_1
       1: ifne          6
       4: aload_0
       5: areturn
       6: aload_0
       7: invokevirtual #34                 // Method getValue:()I
      10: iload_1
      11: invokestatic  #36                 // Method org/joda/time/field/FieldUtils.safeAdd:(II)I
      14: invokestatic  #20                 // Method months:(I)Lorg/joda/time/Months;
      17: areturn

  public org.joda.time.Months plus(org.joda.time.Months);
    Code:
       0: aload_1
       1: ifnonnull     6
       4: aload_0
       5: areturn
       6: aload_0
       7: aload_1
       8: invokevirtual #34                 // Method getValue:()I
      11: invokevirtual #37                 // Method plus:(I)Lorg/joda/time/Months;
      14: areturn

  public org.joda.time.Months minus(int);
    Code:
       0: aload_0
       1: iload_1
       2: invokestatic  #38                 // Method org/joda/time/field/FieldUtils.safeNegate:(I)I
       5: invokevirtual #37                 // Method plus:(I)Lorg/joda/time/Months;
       8: areturn

  public org.joda.time.Months minus(org.joda.time.Months);
    Code:
       0: aload_1
       1: ifnonnull     6
       4: aload_0
       5: areturn
       6: aload_0
       7: aload_1
       8: invokevirtual #34                 // Method getValue:()I
      11: invokevirtual #39                 // Method minus:(I)Lorg/joda/time/Months;
      14: areturn

  public org.joda.time.Months multipliedBy(int);
    Code:
       0: aload_0
       1: invokevirtual #34                 // Method getValue:()I
       4: iload_1
       5: invokestatic  #40                 // Method org/joda/time/field/FieldUtils.safeMultiply:(II)I
       8: invokestatic  #20                 // Method months:(I)Lorg/joda/time/Months;
      11: areturn

  public org.joda.time.Months dividedBy(int);
    Code:
       0: iload_1
       1: iconst_1
       2: if_icmpne     7
       5: aload_0
       6: areturn
       7: aload_0
       8: invokevirtual #34                 // Method getValue:()I
      11: iload_1
      12: idiv
      13: invokestatic  #20                 // Method months:(I)Lorg/joda/time/Months;
      16: areturn

  public org.joda.time.Months negated();
    Code:
       0: aload_0
       1: invokevirtual #34                 // Method getValue:()I
       4: invokestatic  #38                 // Method org/joda/time/field/FieldUtils.safeNegate:(I)I
       7: invokestatic  #20                 // Method months:(I)Lorg/joda/time/Months;
      10: areturn

  public boolean isGreaterThan(org.joda.time.Months);
    Code:
       0: aload_1
       1: ifnonnull     17
       4: aload_0
       5: invokevirtual #34                 // Method getValue:()I
       8: ifle          15
      11: iconst_1
      12: goto          16
      15: iconst_0
      16: ireturn
      17: aload_0
      18: invokevirtual #34                 // Method getValue:()I
      21: aload_1
      22: invokevirtual #34                 // Method getValue:()I
      25: if_icmple     32
      28: iconst_1
      29: goto          33
      32: iconst_0
      33: ireturn

  public boolean isLessThan(org.joda.time.Months);
    Code:
       0: aload_1
       1: ifnonnull     17
       4: aload_0
       5: invokevirtual #34                 // Method getValue:()I
       8: ifge          15
      11: iconst_1
      12: goto          16
      15: iconst_0
      16: ireturn
      17: aload_0
      18: invokevirtual #34                 // Method getValue:()I
      21: aload_1
      22: invokevirtual #34                 // Method getValue:()I
      25: if_icmpge     32
      28: iconst_1
      29: goto          33
      32: iconst_0
      33: ireturn

  public java.lang.String toString();
    Code:
       0: new           #41                 // class java/lang/StringBuilder
       3: dup
       4: invokespecial #42                 // Method java/lang/StringBuilder."<init>":()V
       7: ldc           #43                 // String P
       9: invokevirtual #44                 // Method java/lang/StringBuilder.append:(Ljava/lang/String;)Ljava/lang/StringBuilder;
      12: aload_0
      13: invokevirtual #34                 // Method getValue:()I
      16: invokestatic  #45                 // Method java/lang/String.valueOf:(I)Ljava/lang/String;
      19: invokevirtual #44                 // Method java/lang/StringBuilder.append:(Ljava/lang/String;)Ljava/lang/StringBuilder;
      22: ldc           #46                 // String M
      24: invokevirtual #44                 // Method java/lang/StringBuilder.append:(Ljava/lang/String;)Ljava/lang/StringBuilder;
      27: invokevirtual #47                 // Method java/lang/StringBuilder.toString:()Ljava/lang/String;
      30: areturn

  static {};
    Code:
       0: new           #16                 // class org/joda/time/Months
       3: dup
       4: iconst_0
       5: invokespecial #17                 // Method "<init>":(I)V
       8: putstatic     #1                  // Field ZERO:Lorg/joda/time/Months;
      11: new           #16                 // class org/joda/time/Months
      14: dup
      15: iconst_1
      16: invokespecial #17                 // Method "<init>":(I)V
      19: putstatic     #2                  // Field ONE:Lorg/joda/time/Months;
      22: new           #16                 // class org/joda/time/Months
      25: dup
      26: iconst_2
      27: invokespecial #17                 // Method "<init>":(I)V
      30: putstatic     #3                  // Field TWO:Lorg/joda/time/Months;
      33: new           #16                 // class org/joda/time/Months
      36: dup
      37: iconst_3
      38: invokespecial #17                 // Method "<init>":(I)V
      41: putstatic     #4                  // Field THREE:Lorg/joda/time/Months;
      44: new           #16                 // class org/joda/time/Months
      47: dup
      48: iconst_4
      49: invokespecial #17                 // Method "<init>":(I)V
      52: putstatic     #5                  // Field FOUR:Lorg/joda/time/Months;
      55: new           #16                 // class org/joda/time/Months
      58: dup
      59: iconst_5
      60: invokespecial #17                 // Method "<init>":(I)V
      63: putstatic     #6                  // Field FIVE:Lorg/joda/time/Months;
      66: new           #16                 // class org/joda/time/Months
      69: dup
      70: bipush        6
      72: invokespecial #17                 // Method "<init>":(I)V
      75: putstatic     #7                  // Field SIX:Lorg/joda/time/Months;
      78: new           #16                 // class org/joda/time/Months
      81: dup
      82: bipush        7
      84: invokespecial #17                 // Method "<init>":(I)V
      87: putstatic     #8                  // Field SEVEN:Lorg/joda/time/Months;
      90: new           #16                 // class org/joda/time/Months
      93: dup
      94: bipush        8
      96: invokespecial #17                 // Method "<init>":(I)V
      99: putstatic     #9                  // Field EIGHT:Lorg/joda/time/Months;
     102: new           #16                 // class org/joda/time/Months
     105: dup
     106: bipush        9
     108: invokespecial #17                 // Method "<init>":(I)V
     111: putstatic     #10                 // Field NINE:Lorg/joda/time/Months;
     114: new           #16                 // class org/joda/time/Months
     117: dup
     118: bipush        10
     120: invokespecial #17                 // Method "<init>":(I)V
     123: putstatic     #11                 // Field TEN:Lorg/joda/time/Months;
     126: new           #16                 // class org/joda/time/Months
     129: dup
     130: bipush        11
     132: invokespecial #17                 // Method "<init>":(I)V
     135: putstatic     #12                 // Field ELEVEN:Lorg/joda/time/Months;
     138: new           #16                 // class org/joda/time/Months
     141: dup
     142: bipush        12
     144: invokespecial #17                 // Method "<init>":(I)V
     147: putstatic     #13                 // Field TWELVE:Lorg/joda/time/Months;
     150: new           #16                 // class org/joda/time/Months
     153: dup
     154: ldc           #48                 // int 2147483647
     156: invokespecial #17                 // Method "<init>":(I)V
     159: putstatic     #14                 // Field MAX_VALUE:Lorg/joda/time/Months;
     162: new           #16                 // class org/joda/time/Months
     165: dup
     166: ldc           #49                 // int -2147483648
     168: invokespecial #17                 // Method "<init>":(I)V
     171: putstatic     #15                 // Field MIN_VALUE:Lorg/joda/time/Months;
     174: invokestatic  #50                 // Method org/joda/time/format/ISOPeriodFormat.standard:()Lorg/joda/time/format/PeriodFormatter;
     177: invokestatic  #35                 // Method org/joda/time/PeriodType.months:()Lorg/joda/time/PeriodType;
     180: invokevirtual #51                 // Method org/joda/time/format/PeriodFormatter.withParseType:(Lorg/joda/time/PeriodType;)Lorg/joda/time/format/PeriodFormatter;
     183: putstatic     #30                 // Field PARSER:Lorg/joda/time/format/PeriodFormatter;
     186: return
}
