Compiled from "JavaKeyStoreProvider.java"
public class org.apache.hadoop.crypto.key.JavaKeyStoreProvider$Factory extends org.apache.hadoop.crypto.key.KeyProviderFactory {
  public org.apache.hadoop.crypto.key.JavaKeyStoreProvider$Factory();
    Code:
       0: aload_0
       1: invokespecial #2                  // Method org/apache/hadoop/crypto/key/KeyProviderFactory."<init>":()V
       4: return

  public org.apache.hadoop.crypto.key.KeyProvider createProvider(java.net.URI, org.apache.hadoop.conf.Configuration) throws java.io.IOException;
    Code:
       0: ldc           #3                  // String jceks
       2: aload_1
       3: invokevirtual #4                  // Method java/net/URI.getScheme:()Ljava/lang/String;
       6: invokevirtual #5                  // Method java/lang/String.equals:(Ljava/lang/Object;)Z
       9: ifeq          23
      12: new           #1                  // class org/apache/hadoop/crypto/key/JavaKeyStoreProvider
      15: dup
      16: aload_1
      17: aload_2
      18: aconst_null
      19: invokespecial #6                  // Method org/apache/hadoop/crypto/key/JavaKeyStoreProvider."<init>":(Ljava/net/URI;Lorg/apache/hadoop/conf/Configuration;Lorg/apache/hadoop/crypto/key/JavaKeyStoreProvider$1;)V
      22: areturn
      23: aconst_null
      24: areturn
}
