Compiled from "UpdateClusterConfigRequest.java"
final class software.amazon.awssdk.services.eks.model.UpdateClusterConfigRequest$BuilderImpl extends software.amazon.awssdk.services.eks.model.EksRequest$BuilderImpl implements software.amazon.awssdk.services.eks.model.UpdateClusterConfigRequest$Builder {
  private java.lang.String name;

  private software.amazon.awssdk.services.eks.model.VpcConfigRequest resourcesVpcConfig;

  private software.amazon.awssdk.services.eks.model.Logging logging;

  private java.lang.String clientRequestToken;

  private software.amazon.awssdk.services.eks.model.UpdateClusterConfigRequest$BuilderImpl();
    Code:
       0: aload_0
       1: invokespecial #7                  // Method software/amazon/awssdk/services/eks/model/EksRequest$BuilderImpl."<init>":()V
       4: return

  private software.amazon.awssdk.services.eks.model.UpdateClusterConfigRequest$BuilderImpl(software.amazon.awssdk.services.eks.model.UpdateClusterConfigRequest);
    Code:
       0: aload_0
       1: aload_1
       2: invokespecial #8                  // Method software/amazon/awssdk/services/eks/model/EksRequest$BuilderImpl."<init>":(Lsoftware/amazon/awssdk/services/eks/model/EksRequest;)V
       5: aload_0
       6: aload_1
       7: invokestatic  #9                  // Method software/amazon/awssdk/services/eks/model/UpdateClusterConfigRequest.access$600:(Lsoftware/amazon/awssdk/services/eks/model/UpdateClusterConfigRequest;)Ljava/lang/String;
      10: invokevirtual #10                 // Method name:(Ljava/lang/String;)Lsoftware/amazon/awssdk/services/eks/model/UpdateClusterConfigRequest$Builder;
      13: pop
      14: aload_0
      15: aload_1
      16: invokestatic  #11                 // Method software/amazon/awssdk/services/eks/model/UpdateClusterConfigRequest.access$700:(Lsoftware/amazon/awssdk/services/eks/model/UpdateClusterConfigRequest;)Lsoftware/amazon/awssdk/services/eks/model/VpcConfigRequest;
      19: invokevirtual #12                 // Method resourcesVpcConfig:(Lsoftware/amazon/awssdk/services/eks/model/VpcConfigRequest;)Lsoftware/amazon/awssdk/services/eks/model/UpdateClusterConfigRequest$Builder;
      22: pop
      23: aload_0
      24: aload_1
      25: invokestatic  #13                 // Method software/amazon/awssdk/services/eks/model/UpdateClusterConfigRequest.access$800:(Lsoftware/amazon/awssdk/services/eks/model/UpdateClusterConfigRequest;)Lsoftware/amazon/awssdk/services/eks/model/Logging;
      28: invokevirtual #14                 // Method logging:(Lsoftware/amazon/awssdk/services/eks/model/Logging;)Lsoftware/amazon/awssdk/services/eks/model/UpdateClusterConfigRequest$Builder;
      31: pop
      32: aload_0
      33: aload_1
      34: invokestatic  #15                 // Method software/amazon/awssdk/services/eks/model/UpdateClusterConfigRequest.access$900:(Lsoftware/amazon/awssdk/services/eks/model/UpdateClusterConfigRequest;)Ljava/lang/String;
      37: invokevirtual #16                 // Method clientRequestToken:(Ljava/lang/String;)Lsoftware/amazon/awssdk/services/eks/model/UpdateClusterConfigRequest$Builder;
      40: pop
      41: return

  public final java.lang.String getName();
    Code:
       0: aload_0
       1: getfield      #6                  // Field name:Ljava/lang/String;
       4: areturn

  public final software.amazon.awssdk.services.eks.model.UpdateClusterConfigRequest$Builder name(java.lang.String);
    Code:
       0: aload_0
       1: aload_1
       2: putfield      #6                  // Field name:Ljava/lang/String;
       5: aload_0
       6: areturn

  public final void setName(java.lang.String);
    Code:
       0: aload_0
       1: aload_1
       2: putfield      #6                  // Field name:Ljava/lang/String;
       5: return

  public final software.amazon.awssdk.services.eks.model.VpcConfigRequest$Builder getResourcesVpcConfig();
    Code:
       0: aload_0
       1: getfield      #5                  // Field resourcesVpcConfig:Lsoftware/amazon/awssdk/services/eks/model/VpcConfigRequest;
       4: ifnull        17
       7: aload_0
       8: getfield      #5                  // Field resourcesVpcConfig:Lsoftware/amazon/awssdk/services/eks/model/VpcConfigRequest;
      11: invokevirtual #17                 // Method software/amazon/awssdk/services/eks/model/VpcConfigRequest.toBuilder:()Lsoftware/amazon/awssdk/services/eks/model/VpcConfigRequest$Builder;
      14: goto          18
      17: aconst_null
      18: areturn

  public final software.amazon.awssdk.services.eks.model.UpdateClusterConfigRequest$Builder resourcesVpcConfig(software.amazon.awssdk.services.eks.model.VpcConfigRequest);
    Code:
       0: aload_0
       1: aload_1
       2: putfield      #5                  // Field resourcesVpcConfig:Lsoftware/amazon/awssdk/services/eks/model/VpcConfigRequest;
       5: aload_0
       6: areturn

  public final void setResourcesVpcConfig(software.amazon.awssdk.services.eks.model.VpcConfigRequest$BuilderImpl);
    Code:
       0: aload_0
       1: aload_1
       2: ifnull        12
       5: aload_1
       6: invokevirtual #18                 // Method software/amazon/awssdk/services/eks/model/VpcConfigRequest$BuilderImpl.build:()Lsoftware/amazon/awssdk/services/eks/model/VpcConfigRequest;
       9: goto          13
      12: aconst_null
      13: putfield      #5                  // Field resourcesVpcConfig:Lsoftware/amazon/awssdk/services/eks/model/VpcConfigRequest;
      16: return

  public final software.amazon.awssdk.services.eks.model.Logging$Builder getLogging();
    Code:
       0: aload_0
       1: getfield      #4                  // Field logging:Lsoftware/amazon/awssdk/services/eks/model/Logging;
       4: ifnull        17
       7: aload_0
       8: getfield      #4                  // Field logging:Lsoftware/amazon/awssdk/services/eks/model/Logging;
      11: invokevirtual #19                 // Method software/amazon/awssdk/services/eks/model/Logging.toBuilder:()Lsoftware/amazon/awssdk/services/eks/model/Logging$Builder;
      14: goto          18
      17: aconst_null
      18: areturn

  public final software.amazon.awssdk.services.eks.model.UpdateClusterConfigRequest$Builder logging(software.amazon.awssdk.services.eks.model.Logging);
    Code:
       0: aload_0
       1: aload_1
       2: putfield      #4                  // Field logging:Lsoftware/amazon/awssdk/services/eks/model/Logging;
       5: aload_0
       6: areturn

  public final void setLogging(software.amazon.awssdk.services.eks.model.Logging$BuilderImpl);
    Code:
       0: aload_0
       1: aload_1
       2: ifnull        12
       5: aload_1
       6: invokevirtual #20                 // Method software/amazon/awssdk/services/eks/model/Logging$BuilderImpl.build:()Lsoftware/amazon/awssdk/services/eks/model/Logging;
       9: goto          13
      12: aconst_null
      13: putfield      #4                  // Field logging:Lsoftware/amazon/awssdk/services/eks/model/Logging;
      16: return

  public final java.lang.String getClientRequestToken();
    Code:
       0: aload_0
       1: getfield      #3                  // Field clientRequestToken:Ljava/lang/String;
       4: areturn

  public final software.amazon.awssdk.services.eks.model.UpdateClusterConfigRequest$Builder clientRequestToken(java.lang.String);
    Code:
       0: aload_0
       1: aload_1
       2: putfield      #3                  // Field clientRequestToken:Ljava/lang/String;
       5: aload_0
       6: areturn

  public final void setClientRequestToken(java.lang.String);
    Code:
       0: aload_0
       1: aload_1
       2: putfield      #3                  // Field clientRequestToken:Ljava/lang/String;
       5: return

  public software.amazon.awssdk.services.eks.model.UpdateClusterConfigRequest$Builder overrideConfiguration(software.amazon.awssdk.awscore.AwsRequestOverrideConfiguration);
    Code:
       0: aload_0
       1: aload_1
       2: invokespecial #21                 // Method software/amazon/awssdk/services/eks/model/EksRequest$BuilderImpl.overrideConfiguration:(Lsoftware/amazon/awssdk/awscore/AwsRequestOverrideConfiguration;)Lsoftware/amazon/awssdk/awscore/AwsRequest$Builder;
       5: pop
       6: aload_0
       7: areturn

  public software.amazon.awssdk.services.eks.model.UpdateClusterConfigRequest$Builder overrideConfiguration(java.util.function.Consumer<software.amazon.awssdk.awscore.AwsRequestOverrideConfiguration$Builder>);
    Code:
       0: aload_0
       1: aload_1
       2: invokespecial #22                 // Method software/amazon/awssdk/services/eks/model/EksRequest$BuilderImpl.overrideConfiguration:(Ljava/util/function/Consumer;)Lsoftware/amazon/awssdk/awscore/AwsRequest$Builder;
       5: pop
       6: aload_0
       7: areturn

  public software.amazon.awssdk.services.eks.model.UpdateClusterConfigRequest build();
    Code:
       0: new           #23                 // class software/amazon/awssdk/services/eks/model/UpdateClusterConfigRequest
       3: dup
       4: aload_0
       5: aconst_null
       6: invokespecial #24                 // Method software/amazon/awssdk/services/eks/model/UpdateClusterConfigRequest."<init>":(Lsoftware/amazon/awssdk/services/eks/model/UpdateClusterConfigRequest$BuilderImpl;Lsoftware/amazon/awssdk/services/eks/model/UpdateClusterConfigRequest$1;)V
       9: areturn

  public java.util.List<software.amazon.awssdk.core.SdkField<?>> sdkFields();
    Code:
       0: invokestatic  #25                 // Method software/amazon/awssdk/services/eks/model/UpdateClusterConfigRequest.access$1100:()Ljava/util/List;
       3: areturn

  public software.amazon.awssdk.services.eks.model.EksRequest build();
    Code:
       0: aload_0
       1: invokevirtual #26                 // Method build:()Lsoftware/amazon/awssdk/services/eks/model/UpdateClusterConfigRequest;
       4: areturn

  public software.amazon.awssdk.awscore.AwsRequest build();
    Code:
       0: aload_0
       1: invokevirtual #26                 // Method build:()Lsoftware/amazon/awssdk/services/eks/model/UpdateClusterConfigRequest;
       4: areturn

  public software.amazon.awssdk.awscore.AwsRequest$Builder overrideConfiguration(java.util.function.Consumer);
    Code:
       0: aload_0
       1: aload_1
       2: invokevirtual #27                 // Method overrideConfiguration:(Ljava/util/function/Consumer;)Lsoftware/amazon/awssdk/services/eks/model/UpdateClusterConfigRequest$Builder;
       5: areturn

  public software.amazon.awssdk.awscore.AwsRequest$Builder overrideConfiguration(software.amazon.awssdk.awscore.AwsRequestOverrideConfiguration);
    Code:
       0: aload_0
       1: aload_1
       2: invokevirtual #28                 // Method overrideConfiguration:(Lsoftware/amazon/awssdk/awscore/AwsRequestOverrideConfiguration;)Lsoftware/amazon/awssdk/services/eks/model/UpdateClusterConfigRequest$Builder;
       5: areturn

  public software.amazon.awssdk.core.SdkRequest build();
    Code:
       0: aload_0
       1: invokevirtual #26                 // Method build:()Lsoftware/amazon/awssdk/services/eks/model/UpdateClusterConfigRequest;
       4: areturn

  public java.lang.Object build();
    Code:
       0: aload_0
       1: invokevirtual #26                 // Method build:()Lsoftware/amazon/awssdk/services/eks/model/UpdateClusterConfigRequest;
       4: areturn

  static java.lang.String access$000(software.amazon.awssdk.services.eks.model.UpdateClusterConfigRequest$BuilderImpl);
    Code:
       0: aload_0
       1: getfield      #6                  // Field name:Ljava/lang/String;
       4: areturn

  static software.amazon.awssdk.services.eks.model.VpcConfigRequest access$100(software.amazon.awssdk.services.eks.model.UpdateClusterConfigRequest$BuilderImpl);
    Code:
       0: aload_0
       1: getfield      #5                  // Field resourcesVpcConfig:Lsoftware/amazon/awssdk/services/eks/model/VpcConfigRequest;
       4: areturn

  static software.amazon.awssdk.services.eks.model.Logging access$200(software.amazon.awssdk.services.eks.model.UpdateClusterConfigRequest$BuilderImpl);
    Code:
       0: aload_0
       1: getfield      #4                  // Field logging:Lsoftware/amazon/awssdk/services/eks/model/Logging;
       4: areturn

  static java.lang.String access$300(software.amazon.awssdk.services.eks.model.UpdateClusterConfigRequest$BuilderImpl);
    Code:
       0: aload_0
       1: getfield      #3                  // Field clientRequestToken:Ljava/lang/String;
       4: areturn

  software.amazon.awssdk.services.eks.model.UpdateClusterConfigRequest$BuilderImpl(software.amazon.awssdk.services.eks.model.UpdateClusterConfigRequest, software.amazon.awssdk.services.eks.model.UpdateClusterConfigRequest$1);
    Code:
       0: aload_0
       1: aload_1
       2: invokespecial #2                  // Method "<init>":(Lsoftware/amazon/awssdk/services/eks/model/UpdateClusterConfigRequest;)V
       5: return

  software.amazon.awssdk.services.eks.model.UpdateClusterConfigRequest$BuilderImpl(software.amazon.awssdk.services.eks.model.UpdateClusterConfigRequest$1);
    Code:
       0: aload_0
       1: invokespecial #1                  // Method "<init>":()V
       4: return
}
