Compiled from "RabbitAnnotationDrivenConfiguration.java"
class org.springframework.boot.autoconfigure.amqp.RabbitAnnotationDrivenConfiguration {
  private final org.springframework.beans.factory.ObjectProvider<org.springframework.amqp.support.converter.MessageConverter> messageConverter;

  private final org.springframework.beans.factory.ObjectProvider<org.springframework.amqp.rabbit.retry.MessageRecoverer> messageRecoverer;

  private final org.springframework.beans.factory.ObjectProvider<org.springframework.boot.autoconfigure.amqp.RabbitRetryTemplateCustomizer> retryTemplateCustomizers;

  private final org.springframework.boot.autoconfigure.amqp.RabbitProperties properties;

  org.springframework.boot.autoconfigure.amqp.RabbitAnnotationDrivenConfiguration(org.springframework.beans.factory.ObjectProvider<org.springframework.amqp.support.converter.MessageConverter>, org.springframework.beans.factory.ObjectProvider<org.springframework.amqp.rabbit.retry.MessageRecoverer>, org.springframework.beans.factory.ObjectProvider<org.springframework.boot.autoconfigure.amqp.RabbitRetryTemplateCustomizer>, org.springframework.boot.autoconfigure.amqp.RabbitProperties);
    Code:
       0: aload_0
       1: invokespecial #1                  // Method java/lang/Object."<init>":()V
       4: aload_0
       5: aload_1
       6: putfield      #2                  // Field messageConverter:Lorg/springframework/beans/factory/ObjectProvider;
       9: aload_0
      10: aload_2
      11: putfield      #3                  // Field messageRecoverer:Lorg/springframework/beans/factory/ObjectProvider;
      14: aload_0
      15: aload_3
      16: putfield      #4                  // Field retryTemplateCustomizers:Lorg/springframework/beans/factory/ObjectProvider;
      19: aload_0
      20: aload         4
      22: putfield      #5                  // Field properties:Lorg/springframework/boot/autoconfigure/amqp/RabbitProperties;
      25: return

  public org.springframework.boot.autoconfigure.amqp.SimpleRabbitListenerContainerFactoryConfigurer simpleRabbitListenerContainerFactoryConfigurer();
    Code:
       0: new           #6                  // class org/springframework/boot/autoconfigure/amqp/SimpleRabbitListenerContainerFactoryConfigurer
       3: dup
       4: invokespecial #7                  // Method org/springframework/boot/autoconfigure/amqp/SimpleRabbitListenerContainerFactoryConfigurer."<init>":()V
       7: astore_1
       8: aload_1
       9: aload_0
      10: getfield      #2                  // Field messageConverter:Lorg/springframework/beans/factory/ObjectProvider;
      13: invokeinterface #8,  1            // InterfaceMethod org/springframework/beans/factory/ObjectProvider.getIfUnique:()Ljava/lang/Object;
      18: checkcast     #9                  // class org/springframework/amqp/support/converter/MessageConverter
      21: invokevirtual #10                 // Method org/springframework/boot/autoconfigure/amqp/SimpleRabbitListenerContainerFactoryConfigurer.setMessageConverter:(Lorg/springframework/amqp/support/converter/MessageConverter;)V
      24: aload_1
      25: aload_0
      26: getfield      #3                  // Field messageRecoverer:Lorg/springframework/beans/factory/ObjectProvider;
      29: invokeinterface #8,  1            // InterfaceMethod org/springframework/beans/factory/ObjectProvider.getIfUnique:()Ljava/lang/Object;
      34: checkcast     #11                 // class org/springframework/amqp/rabbit/retry/MessageRecoverer
      37: invokevirtual #12                 // Method org/springframework/boot/autoconfigure/amqp/SimpleRabbitListenerContainerFactoryConfigurer.setMessageRecoverer:(Lorg/springframework/amqp/rabbit/retry/MessageRecoverer;)V
      40: aload_1
      41: aload_0
      42: getfield      #4                  // Field retryTemplateCustomizers:Lorg/springframework/beans/factory/ObjectProvider;
      45: invokeinterface #13,  1           // InterfaceMethod org/springframework/beans/factory/ObjectProvider.orderedStream:()Ljava/util/stream/Stream;
      50: invokestatic  #14                 // Method java/util/stream/Collectors.toList:()Ljava/util/stream/Collector;
      53: invokeinterface #15,  2           // InterfaceMethod java/util/stream/Stream.collect:(Ljava/util/stream/Collector;)Ljava/lang/Object;
      58: checkcast     #16                 // class java/util/List
      61: invokevirtual #17                 // Method org/springframework/boot/autoconfigure/amqp/SimpleRabbitListenerContainerFactoryConfigurer.setRetryTemplateCustomizers:(Ljava/util/List;)V
      64: aload_1
      65: aload_0
      66: getfield      #5                  // Field properties:Lorg/springframework/boot/autoconfigure/amqp/RabbitProperties;
      69: invokevirtual #18                 // Method org/springframework/boot/autoconfigure/amqp/SimpleRabbitListenerContainerFactoryConfigurer.setRabbitProperties:(Lorg/springframework/boot/autoconfigure/amqp/RabbitProperties;)V
      72: aload_1
      73: areturn

  public org.springframework.amqp.rabbit.config.SimpleRabbitListenerContainerFactory simpleRabbitListenerContainerFactory(org.springframework.boot.autoconfigure.amqp.SimpleRabbitListenerContainerFactoryConfigurer, org.springframework.amqp.rabbit.connection.ConnectionFactory);
    Code:
       0: new           #19                 // class org/springframework/amqp/rabbit/config/SimpleRabbitListenerContainerFactory
       3: dup
       4: invokespecial #20                 // Method org/springframework/amqp/rabbit/config/SimpleRabbitListenerContainerFactory."<init>":()V
       7: astore_3
       8: aload_1
       9: aload_3
      10: aload_2
      11: invokevirtual #21                 // Method org/springframework/boot/autoconfigure/amqp/SimpleRabbitListenerContainerFactoryConfigurer.configure:(Lorg/springframework/amqp/rabbit/config/SimpleRabbitListenerContainerFactory;Lorg/springframework/amqp/rabbit/connection/ConnectionFactory;)V
      14: aload_3
      15: areturn

  public org.springframework.boot.autoconfigure.amqp.DirectRabbitListenerContainerFactoryConfigurer directRabbitListenerContainerFactoryConfigurer();
    Code:
       0: new           #22                 // class org/springframework/boot/autoconfigure/amqp/DirectRabbitListenerContainerFactoryConfigurer
       3: dup
       4: invokespecial #23                 // Method org/springframework/boot/autoconfigure/amqp/DirectRabbitListenerContainerFactoryConfigurer."<init>":()V
       7: astore_1
       8: aload_1
       9: aload_0
      10: getfield      #2                  // Field messageConverter:Lorg/springframework/beans/factory/ObjectProvider;
      13: invokeinterface #8,  1            // InterfaceMethod org/springframework/beans/factory/ObjectProvider.getIfUnique:()Ljava/lang/Object;
      18: checkcast     #9                  // class org/springframework/amqp/support/converter/MessageConverter
      21: invokevirtual #24                 // Method org/springframework/boot/autoconfigure/amqp/DirectRabbitListenerContainerFactoryConfigurer.setMessageConverter:(Lorg/springframework/amqp/support/converter/MessageConverter;)V
      24: aload_1
      25: aload_0
      26: getfield      #3                  // Field messageRecoverer:Lorg/springframework/beans/factory/ObjectProvider;
      29: invokeinterface #8,  1            // InterfaceMethod org/springframework/beans/factory/ObjectProvider.getIfUnique:()Ljava/lang/Object;
      34: checkcast     #11                 // class org/springframework/amqp/rabbit/retry/MessageRecoverer
      37: invokevirtual #25                 // Method org/springframework/boot/autoconfigure/amqp/DirectRabbitListenerContainerFactoryConfigurer.setMessageRecoverer:(Lorg/springframework/amqp/rabbit/retry/MessageRecoverer;)V
      40: aload_1
      41: aload_0
      42: getfield      #4                  // Field retryTemplateCustomizers:Lorg/springframework/beans/factory/ObjectProvider;
      45: invokeinterface #13,  1           // InterfaceMethod org/springframework/beans/factory/ObjectProvider.orderedStream:()Ljava/util/stream/Stream;
      50: invokestatic  #14                 // Method java/util/stream/Collectors.toList:()Ljava/util/stream/Collector;
      53: invokeinterface #15,  2           // InterfaceMethod java/util/stream/Stream.collect:(Ljava/util/stream/Collector;)Ljava/lang/Object;
      58: checkcast     #16                 // class java/util/List
      61: invokevirtual #26                 // Method org/springframework/boot/autoconfigure/amqp/DirectRabbitListenerContainerFactoryConfigurer.setRetryTemplateCustomizers:(Ljava/util/List;)V
      64: aload_1
      65: aload_0
      66: getfield      #5                  // Field properties:Lorg/springframework/boot/autoconfigure/amqp/RabbitProperties;
      69: invokevirtual #27                 // Method org/springframework/boot/autoconfigure/amqp/DirectRabbitListenerContainerFactoryConfigurer.setRabbitProperties:(Lorg/springframework/boot/autoconfigure/amqp/RabbitProperties;)V
      72: aload_1
      73: areturn

  public org.springframework.amqp.rabbit.config.DirectRabbitListenerContainerFactory directRabbitListenerContainerFactory(org.springframework.boot.autoconfigure.amqp.DirectRabbitListenerContainerFactoryConfigurer, org.springframework.amqp.rabbit.connection.ConnectionFactory);
    Code:
       0: new           #28                 // class org/springframework/amqp/rabbit/config/DirectRabbitListenerContainerFactory
       3: dup
       4: invokespecial #29                 // Method org/springframework/amqp/rabbit/config/DirectRabbitListenerContainerFactory."<init>":()V
       7: astore_3
       8: aload_1
       9: aload_3
      10: aload_2
      11: invokevirtual #30                 // Method org/springframework/boot/autoconfigure/amqp/DirectRabbitListenerContainerFactoryConfigurer.configure:(Lorg/springframework/amqp/rabbit/config/DirectRabbitListenerContainerFactory;Lorg/springframework/amqp/rabbit/connection/ConnectionFactory;)V
      14: aload_3
      15: areturn
}
