Compiled from "BlockAction.java"
public interface software.amazon.awssdk.services.wafv2.model.BlockAction$Builder extends software.amazon.awssdk.core.SdkPojo, software.amazon.awssdk.utils.builder.CopyableBuilder<software.amazon.awssdk.services.wafv2.model.BlockAction$Builder, software.amazon.awssdk.services.wafv2.model.BlockAction> {
  public abstract software.amazon.awssdk.services.wafv2.model.BlockAction$Builder customResponse(software.amazon.awssdk.services.wafv2.model.CustomResponse);

  public default software.amazon.awssdk.services.wafv2.model.BlockAction$Builder customResponse(java.util.function.Consumer<software.amazon.awssdk.services.wafv2.model.CustomResponse$Builder>);
    Code:
       0: aload_0
       1: invokestatic  #1                  // Method software/amazon/awssdk/services/wafv2/model/CustomResponse.builder:()Lsoftware/amazon/awssdk/services/wafv2/model/CustomResponse$Builder;
       4: aload_1
       5: invokeinterface #2,  2            // InterfaceMethod software/amazon/awssdk/services/wafv2/model/CustomResponse$Builder.applyMutation:(Ljava/util/function/Consumer;)Lsoftware/amazon/awssdk/utils/builder/SdkBuilder;
      10: checkcast     #3                  // class software/amazon/awssdk/services/wafv2/model/CustomResponse$Builder
      13: invokeinterface #4,  1            // InterfaceMethod software/amazon/awssdk/services/wafv2/model/CustomResponse$Builder.build:()Ljava/lang/Object;
      18: checkcast     #5                  // class software/amazon/awssdk/services/wafv2/model/CustomResponse
      21: invokeinterface #6,  2            // InterfaceMethod customResponse:(Lsoftware/amazon/awssdk/services/wafv2/model/CustomResponse;)Lsoftware/amazon/awssdk/services/wafv2/model/BlockAction$Builder;
      26: areturn
}
