Compiled from "CreateIpSetRequest.java"
public interface software.amazon.awssdk.services.wafv2.model.CreateIpSetRequest$Builder extends software.amazon.awssdk.services.wafv2.model.Wafv2Request$Builder, software.amazon.awssdk.core.SdkPojo, software.amazon.awssdk.utils.builder.CopyableBuilder<software.amazon.awssdk.services.wafv2.model.CreateIpSetRequest$Builder, software.amazon.awssdk.services.wafv2.model.CreateIpSetRequest> {
  public abstract software.amazon.awssdk.services.wafv2.model.CreateIpSetRequest$Builder name(java.lang.String);

  public abstract software.amazon.awssdk.services.wafv2.model.CreateIpSetRequest$Builder scope(java.lang.String);

  public abstract software.amazon.awssdk.services.wafv2.model.CreateIpSetRequest$Builder scope(software.amazon.awssdk.services.wafv2.model.Scope);

  public abstract software.amazon.awssdk.services.wafv2.model.CreateIpSetRequest$Builder description(java.lang.String);

  public abstract software.amazon.awssdk.services.wafv2.model.CreateIpSetRequest$Builder ipAddressVersion(java.lang.String);

  public abstract software.amazon.awssdk.services.wafv2.model.CreateIpSetRequest$Builder ipAddressVersion(software.amazon.awssdk.services.wafv2.model.IPAddressVersion);

  public abstract software.amazon.awssdk.services.wafv2.model.CreateIpSetRequest$Builder addresses(java.util.Collection<java.lang.String>);

  public abstract software.amazon.awssdk.services.wafv2.model.CreateIpSetRequest$Builder addresses(java.lang.String...);

  public abstract software.amazon.awssdk.services.wafv2.model.CreateIpSetRequest$Builder tags(java.util.Collection<software.amazon.awssdk.services.wafv2.model.Tag>);

  public abstract software.amazon.awssdk.services.wafv2.model.CreateIpSetRequest$Builder tags(software.amazon.awssdk.services.wafv2.model.Tag...);

  public abstract software.amazon.awssdk.services.wafv2.model.CreateIpSetRequest$Builder tags(java.util.function.Consumer<software.amazon.awssdk.services.wafv2.model.Tag$Builder>...);

  public abstract software.amazon.awssdk.services.wafv2.model.CreateIpSetRequest$Builder overrideConfiguration(software.amazon.awssdk.awscore.AwsRequestOverrideConfiguration);

  public abstract software.amazon.awssdk.services.wafv2.model.CreateIpSetRequest$Builder overrideConfiguration(java.util.function.Consumer<software.amazon.awssdk.awscore.AwsRequestOverrideConfiguration$Builder>);

  public default software.amazon.awssdk.awscore.AwsRequest$Builder overrideConfiguration(java.util.function.Consumer);
    Code:
       0: aload_0
       1: aload_1
       2: invokeinterface #1,  2            // InterfaceMethod overrideConfiguration:(Ljava/util/function/Consumer;)Lsoftware/amazon/awssdk/services/wafv2/model/CreateIpSetRequest$Builder;
       7: areturn

  public default software.amazon.awssdk.awscore.AwsRequest$Builder overrideConfiguration(software.amazon.awssdk.awscore.AwsRequestOverrideConfiguration);
    Code:
       0: aload_0
       1: aload_1
       2: invokeinterface #2,  2            // InterfaceMethod overrideConfiguration:(Lsoftware/amazon/awssdk/awscore/AwsRequestOverrideConfiguration;)Lsoftware/amazon/awssdk/services/wafv2/model/CreateIpSetRequest$Builder;
       7: areturn
}
