Compiled from "CreateRegexPatternSetResponse.java"
final class software.amazon.awssdk.services.wafv2.model.CreateRegexPatternSetResponse$BuilderImpl extends software.amazon.awssdk.services.wafv2.model.Wafv2Response$BuilderImpl implements software.amazon.awssdk.services.wafv2.model.CreateRegexPatternSetResponse$Builder {
  private software.amazon.awssdk.services.wafv2.model.RegexPatternSetSummary summary;

  private software.amazon.awssdk.services.wafv2.model.CreateRegexPatternSetResponse$BuilderImpl();
    Code:
       0: aload_0
       1: invokespecial #4                  // Method software/amazon/awssdk/services/wafv2/model/Wafv2Response$BuilderImpl."<init>":()V
       4: return

  private software.amazon.awssdk.services.wafv2.model.CreateRegexPatternSetResponse$BuilderImpl(software.amazon.awssdk.services.wafv2.model.CreateRegexPatternSetResponse);
    Code:
       0: aload_0
       1: aload_1
       2: invokespecial #5                  // Method software/amazon/awssdk/services/wafv2/model/Wafv2Response$BuilderImpl."<init>":(Lsoftware/amazon/awssdk/services/wafv2/model/Wafv2Response;)V
       5: aload_0
       6: aload_1
       7: invokestatic  #6                  // Method software/amazon/awssdk/services/wafv2/model/CreateRegexPatternSetResponse.access$300:(Lsoftware/amazon/awssdk/services/wafv2/model/CreateRegexPatternSetResponse;)Lsoftware/amazon/awssdk/services/wafv2/model/RegexPatternSetSummary;
      10: invokevirtual #7                  // Method summary:(Lsoftware/amazon/awssdk/services/wafv2/model/RegexPatternSetSummary;)Lsoftware/amazon/awssdk/services/wafv2/model/CreateRegexPatternSetResponse$Builder;
      13: pop
      14: return

  public final software.amazon.awssdk.services.wafv2.model.RegexPatternSetSummary$Builder getSummary();
    Code:
       0: aload_0
       1: getfield      #3                  // Field summary:Lsoftware/amazon/awssdk/services/wafv2/model/RegexPatternSetSummary;
       4: ifnull        17
       7: aload_0
       8: getfield      #3                  // Field summary:Lsoftware/amazon/awssdk/services/wafv2/model/RegexPatternSetSummary;
      11: invokevirtual #8                  // Method software/amazon/awssdk/services/wafv2/model/RegexPatternSetSummary.toBuilder:()Lsoftware/amazon/awssdk/services/wafv2/model/RegexPatternSetSummary$Builder;
      14: goto          18
      17: aconst_null
      18: areturn

  public final void setSummary(software.amazon.awssdk.services.wafv2.model.RegexPatternSetSummary$BuilderImpl);
    Code:
       0: aload_0
       1: aload_1
       2: ifnull        12
       5: aload_1
       6: invokevirtual #9                  // Method software/amazon/awssdk/services/wafv2/model/RegexPatternSetSummary$BuilderImpl.build:()Lsoftware/amazon/awssdk/services/wafv2/model/RegexPatternSetSummary;
       9: goto          13
      12: aconst_null
      13: putfield      #3                  // Field summary:Lsoftware/amazon/awssdk/services/wafv2/model/RegexPatternSetSummary;
      16: return

  public final software.amazon.awssdk.services.wafv2.model.CreateRegexPatternSetResponse$Builder summary(software.amazon.awssdk.services.wafv2.model.RegexPatternSetSummary);
    Code:
       0: aload_0
       1: aload_1
       2: putfield      #3                  // Field summary:Lsoftware/amazon/awssdk/services/wafv2/model/RegexPatternSetSummary;
       5: aload_0
       6: areturn

  public software.amazon.awssdk.services.wafv2.model.CreateRegexPatternSetResponse build();
    Code:
       0: new           #10                 // class software/amazon/awssdk/services/wafv2/model/CreateRegexPatternSetResponse
       3: dup
       4: aload_0
       5: aconst_null
       6: invokespecial #11                 // Method software/amazon/awssdk/services/wafv2/model/CreateRegexPatternSetResponse."<init>":(Lsoftware/amazon/awssdk/services/wafv2/model/CreateRegexPatternSetResponse$BuilderImpl;Lsoftware/amazon/awssdk/services/wafv2/model/CreateRegexPatternSetResponse$1;)V
       9: areturn

  public java.util.List<software.amazon.awssdk.core.SdkField<?>> sdkFields();
    Code:
       0: invokestatic  #12                 // Method software/amazon/awssdk/services/wafv2/model/CreateRegexPatternSetResponse.access$500:()Ljava/util/List;
       3: areturn

  public software.amazon.awssdk.services.wafv2.model.Wafv2Response build();
    Code:
       0: aload_0
       1: invokevirtual #13                 // Method build:()Lsoftware/amazon/awssdk/services/wafv2/model/CreateRegexPatternSetResponse;
       4: areturn

  public software.amazon.awssdk.awscore.AwsResponse build();
    Code:
       0: aload_0
       1: invokevirtual #13                 // Method build:()Lsoftware/amazon/awssdk/services/wafv2/model/CreateRegexPatternSetResponse;
       4: areturn

  public software.amazon.awssdk.core.SdkResponse build();
    Code:
       0: aload_0
       1: invokevirtual #13                 // Method build:()Lsoftware/amazon/awssdk/services/wafv2/model/CreateRegexPatternSetResponse;
       4: areturn

  public java.lang.Object build();
    Code:
       0: aload_0
       1: invokevirtual #13                 // Method build:()Lsoftware/amazon/awssdk/services/wafv2/model/CreateRegexPatternSetResponse;
       4: areturn

  static software.amazon.awssdk.services.wafv2.model.RegexPatternSetSummary access$000(software.amazon.awssdk.services.wafv2.model.CreateRegexPatternSetResponse$BuilderImpl);
    Code:
       0: aload_0
       1: getfield      #3                  // Field summary:Lsoftware/amazon/awssdk/services/wafv2/model/RegexPatternSetSummary;
       4: areturn

  software.amazon.awssdk.services.wafv2.model.CreateRegexPatternSetResponse$BuilderImpl(software.amazon.awssdk.services.wafv2.model.CreateRegexPatternSetResponse, software.amazon.awssdk.services.wafv2.model.CreateRegexPatternSetResponse$1);
    Code:
       0: aload_0
       1: aload_1
       2: invokespecial #2                  // Method "<init>":(Lsoftware/amazon/awssdk/services/wafv2/model/CreateRegexPatternSetResponse;)V
       5: return

  software.amazon.awssdk.services.wafv2.model.CreateRegexPatternSetResponse$BuilderImpl(software.amazon.awssdk.services.wafv2.model.CreateRegexPatternSetResponse$1);
    Code:
       0: aload_0
       1: invokespecial #1                  // Method "<init>":()V
       4: return
}
