Compiled from "DescribeManagedRuleGroupRequest.java"
final class software.amazon.awssdk.services.wafv2.model.DescribeManagedRuleGroupRequest$BuilderImpl extends software.amazon.awssdk.services.wafv2.model.Wafv2Request$BuilderImpl implements software.amazon.awssdk.services.wafv2.model.DescribeManagedRuleGroupRequest$Builder {
  private java.lang.String vendorName;

  private java.lang.String name;

  private java.lang.String scope;

  private java.lang.String versionName;

  private software.amazon.awssdk.services.wafv2.model.DescribeManagedRuleGroupRequest$BuilderImpl();
    Code:
       0: aload_0
       1: invokespecial #7                  // Method software/amazon/awssdk/services/wafv2/model/Wafv2Request$BuilderImpl."<init>":()V
       4: return

  private software.amazon.awssdk.services.wafv2.model.DescribeManagedRuleGroupRequest$BuilderImpl(software.amazon.awssdk.services.wafv2.model.DescribeManagedRuleGroupRequest);
    Code:
       0: aload_0
       1: aload_1
       2: invokespecial #8                  // Method software/amazon/awssdk/services/wafv2/model/Wafv2Request$BuilderImpl."<init>":(Lsoftware/amazon/awssdk/services/wafv2/model/Wafv2Request;)V
       5: aload_0
       6: aload_1
       7: invokestatic  #9                  // Method software/amazon/awssdk/services/wafv2/model/DescribeManagedRuleGroupRequest.access$600:(Lsoftware/amazon/awssdk/services/wafv2/model/DescribeManagedRuleGroupRequest;)Ljava/lang/String;
      10: invokevirtual #10                 // Method vendorName:(Ljava/lang/String;)Lsoftware/amazon/awssdk/services/wafv2/model/DescribeManagedRuleGroupRequest$Builder;
      13: pop
      14: aload_0
      15: aload_1
      16: invokestatic  #11                 // Method software/amazon/awssdk/services/wafv2/model/DescribeManagedRuleGroupRequest.access$700:(Lsoftware/amazon/awssdk/services/wafv2/model/DescribeManagedRuleGroupRequest;)Ljava/lang/String;
      19: invokevirtual #12                 // Method name:(Ljava/lang/String;)Lsoftware/amazon/awssdk/services/wafv2/model/DescribeManagedRuleGroupRequest$Builder;
      22: pop
      23: aload_0
      24: aload_1
      25: invokestatic  #13                 // Method software/amazon/awssdk/services/wafv2/model/DescribeManagedRuleGroupRequest.access$800:(Lsoftware/amazon/awssdk/services/wafv2/model/DescribeManagedRuleGroupRequest;)Ljava/lang/String;
      28: invokevirtual #14                 // Method scope:(Ljava/lang/String;)Lsoftware/amazon/awssdk/services/wafv2/model/DescribeManagedRuleGroupRequest$Builder;
      31: pop
      32: aload_0
      33: aload_1
      34: invokestatic  #15                 // Method software/amazon/awssdk/services/wafv2/model/DescribeManagedRuleGroupRequest.access$900:(Lsoftware/amazon/awssdk/services/wafv2/model/DescribeManagedRuleGroupRequest;)Ljava/lang/String;
      37: invokevirtual #16                 // Method versionName:(Ljava/lang/String;)Lsoftware/amazon/awssdk/services/wafv2/model/DescribeManagedRuleGroupRequest$Builder;
      40: pop
      41: return

  public final java.lang.String getVendorName();
    Code:
       0: aload_0
       1: getfield      #6                  // Field vendorName:Ljava/lang/String;
       4: areturn

  public final void setVendorName(java.lang.String);
    Code:
       0: aload_0
       1: aload_1
       2: putfield      #6                  // Field vendorName:Ljava/lang/String;
       5: return

  public final software.amazon.awssdk.services.wafv2.model.DescribeManagedRuleGroupRequest$Builder vendorName(java.lang.String);
    Code:
       0: aload_0
       1: aload_1
       2: putfield      #6                  // Field vendorName:Ljava/lang/String;
       5: aload_0
       6: areturn

  public final java.lang.String getName();
    Code:
       0: aload_0
       1: getfield      #5                  // Field name:Ljava/lang/String;
       4: areturn

  public final void setName(java.lang.String);
    Code:
       0: aload_0
       1: aload_1
       2: putfield      #5                  // Field name:Ljava/lang/String;
       5: return

  public final software.amazon.awssdk.services.wafv2.model.DescribeManagedRuleGroupRequest$Builder name(java.lang.String);
    Code:
       0: aload_0
       1: aload_1
       2: putfield      #5                  // Field name:Ljava/lang/String;
       5: aload_0
       6: areturn

  public final java.lang.String getScope();
    Code:
       0: aload_0
       1: getfield      #4                  // Field scope:Ljava/lang/String;
       4: areturn

  public final void setScope(java.lang.String);
    Code:
       0: aload_0
       1: aload_1
       2: putfield      #4                  // Field scope:Ljava/lang/String;
       5: return

  public final software.amazon.awssdk.services.wafv2.model.DescribeManagedRuleGroupRequest$Builder scope(java.lang.String);
    Code:
       0: aload_0
       1: aload_1
       2: putfield      #4                  // Field scope:Ljava/lang/String;
       5: aload_0
       6: areturn

  public final software.amazon.awssdk.services.wafv2.model.DescribeManagedRuleGroupRequest$Builder scope(software.amazon.awssdk.services.wafv2.model.Scope);
    Code:
       0: aload_0
       1: aload_1
       2: ifnonnull     9
       5: aconst_null
       6: goto          13
       9: aload_1
      10: invokevirtual #17                 // Method software/amazon/awssdk/services/wafv2/model/Scope.toString:()Ljava/lang/String;
      13: invokevirtual #14                 // Method scope:(Ljava/lang/String;)Lsoftware/amazon/awssdk/services/wafv2/model/DescribeManagedRuleGroupRequest$Builder;
      16: pop
      17: aload_0
      18: areturn

  public final java.lang.String getVersionName();
    Code:
       0: aload_0
       1: getfield      #3                  // Field versionName:Ljava/lang/String;
       4: areturn

  public final void setVersionName(java.lang.String);
    Code:
       0: aload_0
       1: aload_1
       2: putfield      #3                  // Field versionName:Ljava/lang/String;
       5: return

  public final software.amazon.awssdk.services.wafv2.model.DescribeManagedRuleGroupRequest$Builder versionName(java.lang.String);
    Code:
       0: aload_0
       1: aload_1
       2: putfield      #3                  // Field versionName:Ljava/lang/String;
       5: aload_0
       6: areturn

  public software.amazon.awssdk.services.wafv2.model.DescribeManagedRuleGroupRequest$Builder overrideConfiguration(software.amazon.awssdk.awscore.AwsRequestOverrideConfiguration);
    Code:
       0: aload_0
       1: aload_1
       2: invokespecial #18                 // Method software/amazon/awssdk/services/wafv2/model/Wafv2Request$BuilderImpl.overrideConfiguration:(Lsoftware/amazon/awssdk/awscore/AwsRequestOverrideConfiguration;)Lsoftware/amazon/awssdk/awscore/AwsRequest$Builder;
       5: pop
       6: aload_0
       7: areturn

  public software.amazon.awssdk.services.wafv2.model.DescribeManagedRuleGroupRequest$Builder overrideConfiguration(java.util.function.Consumer<software.amazon.awssdk.awscore.AwsRequestOverrideConfiguration$Builder>);
    Code:
       0: aload_0
       1: aload_1
       2: invokespecial #19                 // Method software/amazon/awssdk/services/wafv2/model/Wafv2Request$BuilderImpl.overrideConfiguration:(Ljava/util/function/Consumer;)Lsoftware/amazon/awssdk/awscore/AwsRequest$Builder;
       5: pop
       6: aload_0
       7: areturn

  public software.amazon.awssdk.services.wafv2.model.DescribeManagedRuleGroupRequest build();
    Code:
       0: new           #20                 // class software/amazon/awssdk/services/wafv2/model/DescribeManagedRuleGroupRequest
       3: dup
       4: aload_0
       5: aconst_null
       6: invokespecial #21                 // Method software/amazon/awssdk/services/wafv2/model/DescribeManagedRuleGroupRequest."<init>":(Lsoftware/amazon/awssdk/services/wafv2/model/DescribeManagedRuleGroupRequest$BuilderImpl;Lsoftware/amazon/awssdk/services/wafv2/model/DescribeManagedRuleGroupRequest$1;)V
       9: areturn

  public java.util.List<software.amazon.awssdk.core.SdkField<?>> sdkFields();
    Code:
       0: invokestatic  #22                 // Method software/amazon/awssdk/services/wafv2/model/DescribeManagedRuleGroupRequest.access$1100:()Ljava/util/List;
       3: areturn

  public software.amazon.awssdk.services.wafv2.model.Wafv2Request build();
    Code:
       0: aload_0
       1: invokevirtual #23                 // Method build:()Lsoftware/amazon/awssdk/services/wafv2/model/DescribeManagedRuleGroupRequest;
       4: areturn

  public software.amazon.awssdk.awscore.AwsRequest build();
    Code:
       0: aload_0
       1: invokevirtual #23                 // Method build:()Lsoftware/amazon/awssdk/services/wafv2/model/DescribeManagedRuleGroupRequest;
       4: areturn

  public software.amazon.awssdk.awscore.AwsRequest$Builder overrideConfiguration(java.util.function.Consumer);
    Code:
       0: aload_0
       1: aload_1
       2: invokevirtual #24                 // Method overrideConfiguration:(Ljava/util/function/Consumer;)Lsoftware/amazon/awssdk/services/wafv2/model/DescribeManagedRuleGroupRequest$Builder;
       5: areturn

  public software.amazon.awssdk.awscore.AwsRequest$Builder overrideConfiguration(software.amazon.awssdk.awscore.AwsRequestOverrideConfiguration);
    Code:
       0: aload_0
       1: aload_1
       2: invokevirtual #25                 // Method overrideConfiguration:(Lsoftware/amazon/awssdk/awscore/AwsRequestOverrideConfiguration;)Lsoftware/amazon/awssdk/services/wafv2/model/DescribeManagedRuleGroupRequest$Builder;
       5: areturn

  public software.amazon.awssdk.core.SdkRequest build();
    Code:
       0: aload_0
       1: invokevirtual #23                 // Method build:()Lsoftware/amazon/awssdk/services/wafv2/model/DescribeManagedRuleGroupRequest;
       4: areturn

  public java.lang.Object build();
    Code:
       0: aload_0
       1: invokevirtual #23                 // Method build:()Lsoftware/amazon/awssdk/services/wafv2/model/DescribeManagedRuleGroupRequest;
       4: areturn

  static java.lang.String access$000(software.amazon.awssdk.services.wafv2.model.DescribeManagedRuleGroupRequest$BuilderImpl);
    Code:
       0: aload_0
       1: getfield      #6                  // Field vendorName:Ljava/lang/String;
       4: areturn

  static java.lang.String access$100(software.amazon.awssdk.services.wafv2.model.DescribeManagedRuleGroupRequest$BuilderImpl);
    Code:
       0: aload_0
       1: getfield      #5                  // Field name:Ljava/lang/String;
       4: areturn

  static java.lang.String access$200(software.amazon.awssdk.services.wafv2.model.DescribeManagedRuleGroupRequest$BuilderImpl);
    Code:
       0: aload_0
       1: getfield      #4                  // Field scope:Ljava/lang/String;
       4: areturn

  static java.lang.String access$300(software.amazon.awssdk.services.wafv2.model.DescribeManagedRuleGroupRequest$BuilderImpl);
    Code:
       0: aload_0
       1: getfield      #3                  // Field versionName:Ljava/lang/String;
       4: areturn

  software.amazon.awssdk.services.wafv2.model.DescribeManagedRuleGroupRequest$BuilderImpl(software.amazon.awssdk.services.wafv2.model.DescribeManagedRuleGroupRequest, software.amazon.awssdk.services.wafv2.model.DescribeManagedRuleGroupRequest$1);
    Code:
       0: aload_0
       1: aload_1
       2: invokespecial #2                  // Method "<init>":(Lsoftware/amazon/awssdk/services/wafv2/model/DescribeManagedRuleGroupRequest;)V
       5: return

  software.amazon.awssdk.services.wafv2.model.DescribeManagedRuleGroupRequest$BuilderImpl(software.amazon.awssdk.services.wafv2.model.DescribeManagedRuleGroupRequest$1);
    Code:
       0: aload_0
       1: invokespecial #1                  // Method "<init>":()V
       4: return
}
