Compiled from "LocalCache.java"
class com.google.common.cache.LocalCache$LoadingValueReference$1 implements com.google.common.base.Function<V, V> {
  final com.google.common.cache.LocalCache$LoadingValueReference this$0;

  com.google.common.cache.LocalCache$LoadingValueReference$1(com.google.common.cache.LocalCache$LoadingValueReference);
    Code:
       0: aload_0
       1: aload_1
       2: putfield      #1                  // Field this$0:Lcom/google/common/cache/LocalCache$LoadingValueReference;
       5: aload_0
       6: invokespecial #2                  // Method java/lang/Object."<init>":()V
       9: return

  public V apply(V);
    Code:
       0: aload_0
       1: getfield      #1                  // Field this$0:Lcom/google/common/cache/LocalCache$LoadingValueReference;
       4: aload_1
       5: invokevirtual #3                  // Method com/google/common/cache/LocalCache$LoadingValueReference.set:(Ljava/lang/Object;)Z
       8: pop
       9: aload_1
      10: areturn
}
