Compiled from "JMSQueueAppender.java"
public class ch.qos.logback.classic.net.JMSQueueAppender extends ch.qos.logback.core.net.JMSAppenderBase<ch.qos.logback.classic.spi.ILoggingEvent> {
  static int SUCCESSIVE_FAILURE_LIMIT;

  java.lang.String queueBindingName;

  java.lang.String qcfBindingName;

  javax.jms.QueueConnection queueConnection;

  javax.jms.QueueSession queueSession;

  javax.jms.QueueSender queueSender;

  int successiveFailureCount;

  private ch.qos.logback.core.spi.PreSerializationTransformer<ch.qos.logback.classic.spi.ILoggingEvent> pst;

  public ch.qos.logback.classic.net.JMSQueueAppender();
    Code:
       0: aload_0
       1: invokespecial #1                  // Method ch/qos/logback/core/net/JMSAppenderBase."<init>":()V
       4: aload_0
       5: iconst_0
       6: putfield      #2                  // Field successiveFailureCount:I
       9: aload_0
      10: new           #3                  // class ch/qos/logback/classic/net/LoggingEventPreSerializationTransformer
      13: dup
      14: invokespecial #4                  // Method ch/qos/logback/classic/net/LoggingEventPreSerializationTransformer."<init>":()V
      17: putfield      #5                  // Field pst:Lch/qos/logback/core/spi/PreSerializationTransformer;
      20: return

  public void setQueueConnectionFactoryBindingName(java.lang.String);
    Code:
       0: aload_0
       1: aload_1
       2: putfield      #6                  // Field qcfBindingName:Ljava/lang/String;
       5: return

  public java.lang.String getQueueConnectionFactoryBindingName();
    Code:
       0: aload_0
       1: getfield      #6                  // Field qcfBindingName:Ljava/lang/String;
       4: areturn

  public void setQueueBindingName(java.lang.String);
    Code:
       0: aload_0
       1: aload_1
       2: putfield      #7                  // Field queueBindingName:Ljava/lang/String;
       5: return

  public java.lang.String getQueueBindingName();
    Code:
       0: aload_0
       1: getfield      #7                  // Field queueBindingName:Ljava/lang/String;
       4: areturn

  public void start();
    Code:
       0: aload_0
       1: invokevirtual #8                  // Method buildJNDIContext:()Ljavax/naming/Context;
       4: astore_2
       5: aload_0
       6: aload_2
       7: aload_0
       8: getfield      #6                  // Field qcfBindingName:Ljava/lang/String;
      11: invokevirtual #9                  // Method lookup:(Ljavax/naming/Context;Ljava/lang/String;)Ljava/lang/Object;
      14: checkcast     #10                 // class javax/jms/QueueConnectionFactory
      17: astore_1
      18: aload_0
      19: getfield      #11                 // Field userName:Ljava/lang/String;
      22: ifnull        46
      25: aload_0
      26: aload_1
      27: aload_0
      28: getfield      #11                 // Field userName:Ljava/lang/String;
      31: aload_0
      32: getfield      #12                 // Field password:Ljava/lang/String;
      35: invokeinterface #13,  3           // InterfaceMethod javax/jms/QueueConnectionFactory.createQueueConnection:(Ljava/lang/String;Ljava/lang/String;)Ljavax/jms/QueueConnection;
      40: putfield      #14                 // Field queueConnection:Ljavax/jms/QueueConnection;
      43: goto          56
      46: aload_0
      47: aload_1
      48: invokeinterface #15,  1           // InterfaceMethod javax/jms/QueueConnectionFactory.createQueueConnection:()Ljavax/jms/QueueConnection;
      53: putfield      #14                 // Field queueConnection:Ljavax/jms/QueueConnection;
      56: aload_0
      57: aload_0
      58: getfield      #14                 // Field queueConnection:Ljavax/jms/QueueConnection;
      61: iconst_0
      62: iconst_1
      63: invokeinterface #16,  3           // InterfaceMethod javax/jms/QueueConnection.createQueueSession:(ZI)Ljavax/jms/QueueSession;
      68: putfield      #17                 // Field queueSession:Ljavax/jms/QueueSession;
      71: aload_0
      72: aload_2
      73: aload_0
      74: getfield      #7                  // Field queueBindingName:Ljava/lang/String;
      77: invokevirtual #9                  // Method lookup:(Ljavax/naming/Context;Ljava/lang/String;)Ljava/lang/Object;
      80: checkcast     #18                 // class javax/jms/Queue
      83: astore_3
      84: aload_0
      85: aload_0
      86: getfield      #17                 // Field queueSession:Ljavax/jms/QueueSession;
      89: aload_3
      90: invokeinterface #19,  2           // InterfaceMethod javax/jms/QueueSession.createSender:(Ljavax/jms/Queue;)Ljavax/jms/QueueSender;
      95: putfield      #20                 // Field queueSender:Ljavax/jms/QueueSender;
      98: aload_0
      99: getfield      #14                 // Field queueConnection:Ljavax/jms/QueueConnection;
     102: invokeinterface #21,  1           // InterfaceMethod javax/jms/QueueConnection.start:()V
     107: aload_2
     108: invokeinterface #22,  1           // InterfaceMethod javax/naming/Context.close:()V
     113: goto          149
     116: astore_2
     117: aload_0
     118: new           #24                 // class java/lang/StringBuilder
     121: dup
     122: invokespecial #25                 // Method java/lang/StringBuilder."<init>":()V
     125: ldc           #26                 // String Error while activating options for appender named [
     127: invokevirtual #27                 // Method java/lang/StringBuilder.append:(Ljava/lang/String;)Ljava/lang/StringBuilder;
     130: aload_0
     131: getfield      #28                 // Field name:Ljava/lang/String;
     134: invokevirtual #27                 // Method java/lang/StringBuilder.append:(Ljava/lang/String;)Ljava/lang/StringBuilder;
     137: ldc           #29                 // String ].
     139: invokevirtual #27                 // Method java/lang/StringBuilder.append:(Ljava/lang/String;)Ljava/lang/StringBuilder;
     142: invokevirtual #30                 // Method java/lang/StringBuilder.toString:()Ljava/lang/String;
     145: aload_2
     146: invokevirtual #31                 // Method addError:(Ljava/lang/String;Ljava/lang/Throwable;)V
     149: aload_0
     150: getfield      #14                 // Field queueConnection:Ljavax/jms/QueueConnection;
     153: ifnull        174
     156: aload_0
     157: getfield      #17                 // Field queueSession:Ljavax/jms/QueueSession;
     160: ifnull        174
     163: aload_0
     164: getfield      #20                 // Field queueSender:Ljavax/jms/QueueSender;
     167: ifnull        174
     170: aload_0
     171: invokespecial #32                 // Method ch/qos/logback/core/net/JMSAppenderBase.start:()V
     174: return
    Exception table:
       from    to  target type
           0   113   116   Class java/lang/Exception

  public synchronized void stop();
    Code:
       0: aload_0
       1: getfield      #33                 // Field started:Z
       4: ifne          8
       7: return
       8: aload_0
       9: iconst_0
      10: putfield      #33                 // Field started:Z
      13: aload_0
      14: getfield      #17                 // Field queueSession:Ljavax/jms/QueueSession;
      17: ifnull        29
      20: aload_0
      21: getfield      #17                 // Field queueSession:Ljavax/jms/QueueSession;
      24: invokeinterface #34,  1           // InterfaceMethod javax/jms/QueueSession.close:()V
      29: aload_0
      30: getfield      #14                 // Field queueConnection:Ljavax/jms/QueueConnection;
      33: ifnull        45
      36: aload_0
      37: getfield      #14                 // Field queueConnection:Ljavax/jms/QueueConnection;
      40: invokeinterface #35,  1           // InterfaceMethod javax/jms/QueueConnection.close:()V
      45: goto          81
      48: astore_1
      49: aload_0
      50: new           #24                 // class java/lang/StringBuilder
      53: dup
      54: invokespecial #25                 // Method java/lang/StringBuilder."<init>":()V
      57: ldc           #36                 // String Error while closing JMSAppender [
      59: invokevirtual #27                 // Method java/lang/StringBuilder.append:(Ljava/lang/String;)Ljava/lang/StringBuilder;
      62: aload_0
      63: getfield      #28                 // Field name:Ljava/lang/String;
      66: invokevirtual #27                 // Method java/lang/StringBuilder.append:(Ljava/lang/String;)Ljava/lang/StringBuilder;
      69: ldc           #29                 // String ].
      71: invokevirtual #27                 // Method java/lang/StringBuilder.append:(Ljava/lang/String;)Ljava/lang/StringBuilder;
      74: invokevirtual #30                 // Method java/lang/StringBuilder.toString:()Ljava/lang/String;
      77: aload_1
      78: invokevirtual #31                 // Method addError:(Ljava/lang/String;Ljava/lang/Throwable;)V
      81: aload_0
      82: aconst_null
      83: putfield      #20                 // Field queueSender:Ljavax/jms/QueueSender;
      86: aload_0
      87: aconst_null
      88: putfield      #17                 // Field queueSession:Ljavax/jms/QueueSession;
      91: aload_0
      92: aconst_null
      93: putfield      #14                 // Field queueConnection:Ljavax/jms/QueueConnection;
      96: return
    Exception table:
       from    to  target type
          13    45    48   Class java/lang/Exception

  public void append(ch.qos.logback.classic.spi.ILoggingEvent);
    Code:
       0: aload_0
       1: invokevirtual #37                 // Method isStarted:()Z
       4: ifne          8
       7: return
       8: aload_0
       9: getfield      #17                 // Field queueSession:Ljavax/jms/QueueSession;
      12: invokeinterface #38,  1           // InterfaceMethod javax/jms/QueueSession.createObjectMessage:()Ljavax/jms/ObjectMessage;
      17: astore_2
      18: aload_0
      19: getfield      #5                  // Field pst:Lch/qos/logback/core/spi/PreSerializationTransformer;
      22: aload_1
      23: invokeinterface #39,  2           // InterfaceMethod ch/qos/logback/core/spi/PreSerializationTransformer.transform:(Ljava/lang/Object;)Ljava/io/Serializable;
      28: astore_3
      29: aload_2
      30: aload_3
      31: invokeinterface #40,  2           // InterfaceMethod javax/jms/ObjectMessage.setObject:(Ljava/io/Serializable;)V
      36: aload_0
      37: getfield      #20                 // Field queueSender:Ljavax/jms/QueueSender;
      40: aload_2
      41: invokeinterface #41,  2           // InterfaceMethod javax/jms/QueueSender.send:(Ljavax/jms/Message;)V
      46: aload_0
      47: iconst_0
      48: putfield      #2                  // Field successiveFailureCount:I
      51: goto          111
      54: astore_2
      55: aload_0
      56: dup
      57: getfield      #2                  // Field successiveFailureCount:I
      60: iconst_1
      61: iadd
      62: putfield      #2                  // Field successiveFailureCount:I
      65: aload_0
      66: getfield      #2                  // Field successiveFailureCount:I
      69: getstatic     #42                 // Field SUCCESSIVE_FAILURE_LIMIT:I
      72: if_icmple     79
      75: aload_0
      76: invokevirtual #43                 // Method stop:()V
      79: aload_0
      80: new           #24                 // class java/lang/StringBuilder
      83: dup
      84: invokespecial #25                 // Method java/lang/StringBuilder."<init>":()V
      87: ldc           #44                 // String Could not send message in JMSQueueAppender [
      89: invokevirtual #27                 // Method java/lang/StringBuilder.append:(Ljava/lang/String;)Ljava/lang/StringBuilder;
      92: aload_0
      93: getfield      #28                 // Field name:Ljava/lang/String;
      96: invokevirtual #27                 // Method java/lang/StringBuilder.append:(Ljava/lang/String;)Ljava/lang/StringBuilder;
      99: ldc           #29                 // String ].
     101: invokevirtual #27                 // Method java/lang/StringBuilder.append:(Ljava/lang/String;)Ljava/lang/StringBuilder;
     104: invokevirtual #30                 // Method java/lang/StringBuilder.toString:()Ljava/lang/String;
     107: aload_2
     108: invokevirtual #31                 // Method addError:(Ljava/lang/String;Ljava/lang/Throwable;)V
     111: return
    Exception table:
       from    to  target type
           8    51    54   Class java/lang/Exception

  protected javax.jms.QueueConnection getQueueConnection();
    Code:
       0: aload_0
       1: getfield      #14                 // Field queueConnection:Ljavax/jms/QueueConnection;
       4: areturn

  protected javax.jms.QueueSession getQueueSession();
    Code:
       0: aload_0
       1: getfield      #17                 // Field queueSession:Ljavax/jms/QueueSession;
       4: areturn

  protected javax.jms.QueueSender getQueueSender();
    Code:
       0: aload_0
       1: getfield      #20                 // Field queueSender:Ljavax/jms/QueueSender;
       4: areturn

  public void append(java.lang.Object);
    Code:
       0: aload_0
       1: aload_1
       2: checkcast     #45                 // class ch/qos/logback/classic/spi/ILoggingEvent
       5: invokevirtual #46                 // Method append:(Lch/qos/logback/classic/spi/ILoggingEvent;)V
       8: return

  static {};
    Code:
       0: iconst_3
       1: putstatic     #42                 // Field SUCCESSIVE_FAILURE_LIMIT:I
       4: return
}
