Compiled from "DistributedProgramLiveInfo.java"
public class co.cask.cdap.proto.DistributedProgramLiveInfo extends co.cask.cdap.proto.ProgramLiveInfo implements co.cask.cdap.proto.Containers {
  private final java.lang.String yarnAppId;

  private final java.util.List<co.cask.cdap.proto.Containers$ContainerInfo> containers;

  private final java.util.List<java.lang.String> services;

  public co.cask.cdap.proto.DistributedProgramLiveInfo(co.cask.cdap.proto.id.ProgramId, java.lang.String);
    Code:
       0: aload_0
       1: aload_1
       2: ldc           #1                  // String distributed
       4: invokespecial #2                  // Method co/cask/cdap/proto/ProgramLiveInfo."<init>":(Lco/cask/cdap/proto/id/ProgramId;Ljava/lang/String;)V
       7: aload_0
       8: new           #3                  // class java/util/ArrayList
      11: dup
      12: invokespecial #4                  // Method java/util/ArrayList."<init>":()V
      15: putfield      #5                  // Field containers:Ljava/util/List;
      18: aload_0
      19: new           #3                  // class java/util/ArrayList
      22: dup
      23: invokespecial #4                  // Method java/util/ArrayList."<init>":()V
      26: putfield      #6                  // Field services:Ljava/util/List;
      29: aload_0
      30: aload_2
      31: putfield      #7                  // Field yarnAppId:Ljava/lang/String;
      34: return

  public java.lang.String getYarnAppId();
    Code:
       0: aload_0
       1: getfield      #7                  // Field yarnAppId:Ljava/lang/String;
       4: areturn

  public java.util.List<co.cask.cdap.proto.Containers$ContainerInfo> getContainers();
    Code:
       0: aload_0
       1: getfield      #5                  // Field containers:Ljava/util/List;
       4: areturn

  public void addContainer(co.cask.cdap.proto.Containers$ContainerInfo);
    Code:
       0: aload_0
       1: getfield      #5                  // Field containers:Ljava/util/List;
       4: aload_1
       5: invokeinterface #8,  2            // InterfaceMethod java/util/List.add:(Ljava/lang/Object;)Z
      10: pop
      11: return

  public void addServices(java.util.List<java.lang.String>);
    Code:
       0: aload_0
       1: getfield      #6                  // Field services:Ljava/util/List;
       4: aload_1
       5: invokeinterface #9,  2            // InterfaceMethod java/util/List.addAll:(Ljava/util/Collection;)Z
      10: pop
      11: return
}
