Compiled from "Id.java"
public final class co.cask.cdap.proto.Id$DatasetType extends co.cask.cdap.proto.Id$NamespacedId {
  private final co.cask.cdap.proto.Id$Namespace namespace;

  private final java.lang.String typeName;

  private co.cask.cdap.proto.Id$DatasetType(co.cask.cdap.proto.Id$Namespace, java.lang.String);
    Code:
       0: aload_0
       1: invokespecial #1                  // Method co/cask/cdap/proto/Id$NamespacedId."<init>":()V
       4: aload_1
       5: ifnonnull     18
       8: new           #2                  // class java/lang/NullPointerException
      11: dup
      12: ldc           #3                  // String Namespace cannot be null.
      14: invokespecial #4                  // Method java/lang/NullPointerException."<init>":(Ljava/lang/String;)V
      17: athrow
      18: aload_2
      19: ifnonnull     32
      22: new           #2                  // class java/lang/NullPointerException
      25: dup
      26: ldc           #5                  // String Dataset type name cannot be null.
      28: invokespecial #4                  // Method java/lang/NullPointerException."<init>":(Ljava/lang/String;)V
      31: athrow
      32: aload_2
      33: invokestatic  #6                  // Method co/cask/cdap/proto/Id.access$400:(Ljava/lang/String;)Z
      36: ifne          71
      39: new           #7                  // class java/lang/IllegalArgumentException
      42: dup
      43: new           #8                  // class java/lang/StringBuilder
      46: dup
      47: invokespecial #9                  // Method java/lang/StringBuilder."<init>":()V
      50: ldc           #10                 // String Invalid characters found in dataset type name \'
      52: invokevirtual #11                 // Method java/lang/StringBuilder.append:(Ljava/lang/String;)Ljava/lang/StringBuilder;
      55: aload_2
      56: invokevirtual #11                 // Method java/lang/StringBuilder.append:(Ljava/lang/String;)Ljava/lang/StringBuilder;
      59: ldc           #12                 // String \'. Allowed characters are ASCII letters, numbers, and _, -, ., or $.
      61: invokevirtual #11                 // Method java/lang/StringBuilder.append:(Ljava/lang/String;)Ljava/lang/StringBuilder;
      64: invokevirtual #13                 // Method java/lang/StringBuilder.toString:()Ljava/lang/String;
      67: invokespecial #14                 // Method java/lang/IllegalArgumentException."<init>":(Ljava/lang/String;)V
      70: athrow
      71: aload_0
      72: aload_1
      73: putfield      #15                 // Field namespace:Lco/cask/cdap/proto/Id$Namespace;
      76: aload_0
      77: aload_2
      78: putfield      #16                 // Field typeName:Ljava/lang/String;
      81: return

  public co.cask.cdap.proto.Id$Namespace getNamespace();
    Code:
       0: aload_0
       1: getfield      #15                 // Field namespace:Lco/cask/cdap/proto/Id$Namespace;
       4: areturn

  public java.lang.String getNamespaceId();
    Code:
       0: aload_0
       1: getfield      #15                 // Field namespace:Lco/cask/cdap/proto/Id$Namespace;
       4: invokevirtual #17                 // Method co/cask/cdap/proto/Id$Namespace.getId:()Ljava/lang/String;
       7: areturn

  public java.lang.String getTypeName();
    Code:
       0: aload_0
       1: getfield      #16                 // Field typeName:Ljava/lang/String;
       4: areturn

  public static co.cask.cdap.proto.Id$DatasetType from(co.cask.cdap.proto.Id$Namespace, java.lang.String);
    Code:
       0: new           #18                 // class co/cask/cdap/proto/Id$DatasetType
       3: dup
       4: aload_0
       5: aload_1
       6: invokespecial #19                 // Method "<init>":(Lco/cask/cdap/proto/Id$Namespace;Ljava/lang/String;)V
       9: areturn

  public static co.cask.cdap.proto.Id$DatasetType from(java.lang.String, java.lang.String);
    Code:
       0: new           #18                 // class co/cask/cdap/proto/Id$DatasetType
       3: dup
       4: aload_0
       5: invokestatic  #20                 // Method co/cask/cdap/proto/Id$Namespace.from:(Ljava/lang/String;)Lco/cask/cdap/proto/Id$Namespace;
       8: aload_1
       9: invokespecial #19                 // Method "<init>":(Lco/cask/cdap/proto/Id$Namespace;Ljava/lang/String;)V
      12: areturn

  public java.lang.String getId();
    Code:
       0: aload_0
       1: getfield      #16                 // Field typeName:Ljava/lang/String;
       4: areturn

  public co.cask.cdap.proto.id.DatasetTypeId toEntityId();
    Code:
       0: new           #21                 // class co/cask/cdap/proto/id/DatasetTypeId
       3: dup
       4: aload_0
       5: getfield      #15                 // Field namespace:Lco/cask/cdap/proto/Id$Namespace;
       8: invokevirtual #17                 // Method co/cask/cdap/proto/Id$Namespace.getId:()Ljava/lang/String;
      11: aload_0
      12: getfield      #16                 // Field typeName:Ljava/lang/String;
      15: invokespecial #22                 // Method co/cask/cdap/proto/id/DatasetTypeId."<init>":(Ljava/lang/String;Ljava/lang/String;)V
      18: areturn

  public co.cask.cdap.proto.id.EntityId toEntityId();
    Code:
       0: aload_0
       1: invokevirtual #23                 // Method toEntityId:()Lco/cask/cdap/proto/id/DatasetTypeId;
       4: areturn
}
