Compiled from "Id.java"
public class co.cask.cdap.proto.Id$Flow$Flowlet extends co.cask.cdap.proto.Id$NamespacedId {
  private final co.cask.cdap.proto.Id$Flow flow;

  private final java.lang.String id;

  private co.cask.cdap.proto.Id$Flow$Flowlet(co.cask.cdap.proto.Id$Flow, java.lang.String);
    Code:
       0: aload_0
       1: invokespecial #1                  // Method co/cask/cdap/proto/Id$NamespacedId."<init>":()V
       4: aload_1
       5: ifnonnull     18
       8: new           #2                  // class java/lang/IllegalArgumentException
      11: dup
      12: ldc           #3                  // String flow cannot be null
      14: invokespecial #4                  // Method java/lang/IllegalArgumentException."<init>":(Ljava/lang/String;)V
      17: athrow
      18: aload_2
      19: ifnonnull     32
      22: new           #2                  // class java/lang/IllegalArgumentException
      25: dup
      26: ldc           #5                  // String id cannot be null
      28: invokespecial #4                  // Method java/lang/IllegalArgumentException."<init>":(Ljava/lang/String;)V
      31: athrow
      32: aload_0
      33: aload_1
      34: putfield      #6                  // Field flow:Lco/cask/cdap/proto/Id$Flow;
      37: aload_0
      38: aload_2
      39: putfield      #7                  // Field id:Ljava/lang/String;
      42: return

  public static co.cask.cdap.proto.Id$Flow$Flowlet from(co.cask.cdap.proto.Id$Flow, java.lang.String);
    Code:
       0: new           #8                  // class co/cask/cdap/proto/Id$Flow$Flowlet
       3: dup
       4: aload_0
       5: aload_1
       6: invokespecial #9                  // Method "<init>":(Lco/cask/cdap/proto/Id$Flow;Ljava/lang/String;)V
       9: areturn

  public static co.cask.cdap.proto.Id$Flow$Flowlet from(co.cask.cdap.proto.Id$Application, java.lang.String, java.lang.String);
    Code:
       0: new           #8                  // class co/cask/cdap/proto/Id$Flow$Flowlet
       3: dup
       4: new           #10                 // class co/cask/cdap/proto/Id$Flow
       7: dup
       8: aload_0
       9: aload_1
      10: aconst_null
      11: invokespecial #11                 // Method co/cask/cdap/proto/Id$Flow."<init>":(Lco/cask/cdap/proto/Id$Application;Ljava/lang/String;Lco/cask/cdap/proto/Id$1;)V
      14: aload_2
      15: invokespecial #9                  // Method "<init>":(Lco/cask/cdap/proto/Id$Flow;Ljava/lang/String;)V
      18: areturn

  public co.cask.cdap.proto.Id$Namespace getNamespace();
    Code:
       0: aload_0
       1: getfield      #6                  // Field flow:Lco/cask/cdap/proto/Id$Flow;
       4: invokevirtual #12                 // Method co/cask/cdap/proto/Id$Flow.getNamespace:()Lco/cask/cdap/proto/Id$Namespace;
       7: areturn

  public java.lang.String getId();
    Code:
       0: aload_0
       1: getfield      #7                  // Field id:Ljava/lang/String;
       4: areturn

  public co.cask.cdap.proto.Id$Flow getFlow();
    Code:
       0: aload_0
       1: getfield      #6                  // Field flow:Lco/cask/cdap/proto/Id$Flow;
       4: areturn

  public co.cask.cdap.proto.id.FlowletId toEntityId();
    Code:
       0: new           #13                 // class co/cask/cdap/proto/id/FlowletId
       3: dup
       4: aload_0
       5: getfield      #6                  // Field flow:Lco/cask/cdap/proto/Id$Flow;
       8: invokevirtual #14                 // Method co/cask/cdap/proto/Id$Flow.getNamespaceId:()Ljava/lang/String;
      11: aload_0
      12: getfield      #6                  // Field flow:Lco/cask/cdap/proto/Id$Flow;
      15: invokevirtual #15                 // Method co/cask/cdap/proto/Id$Flow.getApplicationId:()Ljava/lang/String;
      18: aload_0
      19: getfield      #6                  // Field flow:Lco/cask/cdap/proto/Id$Flow;
      22: invokevirtual #16                 // Method co/cask/cdap/proto/Id$Flow.getId:()Ljava/lang/String;
      25: aload_0
      26: getfield      #7                  // Field id:Ljava/lang/String;
      29: invokespecial #17                 // Method co/cask/cdap/proto/id/FlowletId."<init>":(Ljava/lang/String;Ljava/lang/String;Ljava/lang/String;Ljava/lang/String;)V
      32: areturn

  public co.cask.cdap.proto.id.EntityId toEntityId();
    Code:
       0: aload_0
       1: invokevirtual #18                 // Method toEntityId:()Lco/cask/cdap/proto/id/FlowletId;
       4: areturn
}
