Compiled from "ProgramRecord.java"
public class co.cask.cdap.proto.ProgramRecord {
  private final co.cask.cdap.proto.ProgramType type;

  private final java.lang.String app;

  private final java.lang.String id;

  private final java.lang.String name;

  private final java.lang.String description;

  public co.cask.cdap.proto.ProgramRecord(co.cask.cdap.proto.ProgramType, java.lang.String, java.lang.String, java.lang.String);
    Code:
       0: aload_0
       1: aload_1
       2: aload_2
       3: aload_3
       4: aload_3
       5: aload         4
       7: invokespecial #1                  // Method "<init>":(Lco/cask/cdap/proto/ProgramType;Ljava/lang/String;Ljava/lang/String;Ljava/lang/String;Ljava/lang/String;)V
      10: return

  public co.cask.cdap.proto.ProgramRecord(co.cask.cdap.proto.ProgramType, java.lang.String, java.lang.String, java.lang.String, java.lang.String);
    Code:
       0: aload_0
       1: invokespecial #2                  // Method java/lang/Object."<init>":()V
       4: aload_0
       5: aload_1
       6: putfield      #3                  // Field type:Lco/cask/cdap/proto/ProgramType;
       9: aload_0
      10: aload_2
      11: putfield      #4                  // Field app:Ljava/lang/String;
      14: aload_0
      15: aload_3
      16: putfield      #5                  // Field id:Ljava/lang/String;
      19: aload_0
      20: aload         4
      22: putfield      #6                  // Field name:Ljava/lang/String;
      25: aload_0
      26: aload         5
      28: putfield      #7                  // Field description:Ljava/lang/String;
      31: return

  public co.cask.cdap.proto.ProgramType getType();
    Code:
       0: aload_0
       1: getfield      #3                  // Field type:Lco/cask/cdap/proto/ProgramType;
       4: areturn

  public java.lang.String getApp();
    Code:
       0: aload_0
       1: getfield      #4                  // Field app:Ljava/lang/String;
       4: areturn

  public java.lang.String getId();
    Code:
       0: aload_0
       1: getfield      #5                  // Field id:Ljava/lang/String;
       4: areturn

  public java.lang.String getName();
    Code:
       0: aload_0
       1: getfield      #6                  // Field name:Ljava/lang/String;
       4: areturn

  public java.lang.String getDescription();
    Code:
       0: aload_0
       1: getfield      #7                  // Field description:Ljava/lang/String;
       4: areturn
}
