Compiled from "ProgramTypes.java"
public class co.cask.cdap.proto.ProgramTypes {
  private static final java.util.Map<java.lang.Class<? extends co.cask.cdap.api.ProgramSpecification>, co.cask.cdap.proto.ProgramType> specClassToProgramType;

  public co.cask.cdap.proto.ProgramTypes();
    Code:
       0: aload_0
       1: invokespecial #1                  // Method java/lang/Object."<init>":()V
       4: return

  public static co.cask.cdap.proto.ProgramType fromSpecification(co.cask.cdap.api.ProgramSpecification);
    Code:
       0: aload_0
       1: invokevirtual #2                  // Method java/lang/Object.getClass:()Ljava/lang/Class;
       4: astore_1
       5: getstatic     #3                  // Field specClassToProgramType:Ljava/util/Map;
       8: invokeinterface #4,  1            // InterfaceMethod java/util/Map.entrySet:()Ljava/util/Set;
      13: invokeinterface #5,  1            // InterfaceMethod java/util/Set.iterator:()Ljava/util/Iterator;
      18: astore_2
      19: aload_2
      20: invokeinterface #6,  1            // InterfaceMethod java/util/Iterator.hasNext:()Z
      25: ifeq          67
      28: aload_2
      29: invokeinterface #7,  1            // InterfaceMethod java/util/Iterator.next:()Ljava/lang/Object;
      34: checkcast     #8                  // class java/util/Map$Entry
      37: astore_3
      38: aload_3
      39: invokeinterface #9,  1            // InterfaceMethod java/util/Map$Entry.getKey:()Ljava/lang/Object;
      44: checkcast     #10                 // class java/lang/Class
      47: aload_1
      48: invokevirtual #11                 // Method java/lang/Class.isAssignableFrom:(Ljava/lang/Class;)Z
      51: ifeq          64
      54: aload_3
      55: invokeinterface #12,  1           // InterfaceMethod java/util/Map$Entry.getValue:()Ljava/lang/Object;
      60: checkcast     #13                 // class co/cask/cdap/proto/ProgramType
      63: areturn
      64: goto          19
      67: new           #14                 // class java/lang/IllegalArgumentException
      70: dup
      71: new           #15                 // class java/lang/StringBuilder
      74: dup
      75: invokespecial #16                 // Method java/lang/StringBuilder."<init>":()V
      78: ldc           #17                 // String Unknown specification type:
      80: invokevirtual #18                 // Method java/lang/StringBuilder.append:(Ljava/lang/String;)Ljava/lang/StringBuilder;
      83: aload_1
      84: invokevirtual #19                 // Method java/lang/StringBuilder.append:(Ljava/lang/Object;)Ljava/lang/StringBuilder;
      87: invokevirtual #20                 // Method java/lang/StringBuilder.toString:()Ljava/lang/String;
      90: invokespecial #21                 // Method java/lang/IllegalArgumentException."<init>":(Ljava/lang/String;)V
      93: athrow

  static {};
    Code:
       0: new           #22                 // class java/util/IdentityHashMap
       3: dup
       4: invokespecial #23                 // Method java/util/IdentityHashMap."<init>":()V
       7: putstatic     #3                  // Field specClassToProgramType:Ljava/util/Map;
      10: getstatic     #3                  // Field specClassToProgramType:Ljava/util/Map;
      13: ldc_w         #24                 // class co/cask/cdap/api/flow/FlowSpecification
      16: getstatic     #25                 // Field co/cask/cdap/proto/ProgramType.FLOW:Lco/cask/cdap/proto/ProgramType;
      19: invokeinterface #26,  3           // InterfaceMethod java/util/Map.put:(Ljava/lang/Object;Ljava/lang/Object;)Ljava/lang/Object;
      24: pop
      25: getstatic     #3                  // Field specClassToProgramType:Ljava/util/Map;
      28: ldc_w         #27                 // class co/cask/cdap/api/mapreduce/MapReduceSpecification
      31: getstatic     #28                 // Field co/cask/cdap/proto/ProgramType.MAPREDUCE:Lco/cask/cdap/proto/ProgramType;
      34: invokeinterface #26,  3           // InterfaceMethod java/util/Map.put:(Ljava/lang/Object;Ljava/lang/Object;)Ljava/lang/Object;
      39: pop
      40: getstatic     #3                  // Field specClassToProgramType:Ljava/util/Map;
      43: ldc_w         #29                 // class co/cask/cdap/api/spark/SparkSpecification
      46: getstatic     #30                 // Field co/cask/cdap/proto/ProgramType.SPARK:Lco/cask/cdap/proto/ProgramType;
      49: invokeinterface #26,  3           // InterfaceMethod java/util/Map.put:(Ljava/lang/Object;Ljava/lang/Object;)Ljava/lang/Object;
      54: pop
      55: getstatic     #3                  // Field specClassToProgramType:Ljava/util/Map;
      58: ldc_w         #31                 // class co/cask/cdap/api/workflow/WorkflowSpecification
      61: getstatic     #32                 // Field co/cask/cdap/proto/ProgramType.WORKFLOW:Lco/cask/cdap/proto/ProgramType;
      64: invokeinterface #26,  3           // InterfaceMethod java/util/Map.put:(Ljava/lang/Object;Ljava/lang/Object;)Ljava/lang/Object;
      69: pop
      70: getstatic     #3                  // Field specClassToProgramType:Ljava/util/Map;
      73: ldc_w         #33                 // class co/cask/cdap/api/webapp/WebappSpecification
      76: getstatic     #34                 // Field co/cask/cdap/proto/ProgramType.WEBAPP:Lco/cask/cdap/proto/ProgramType;
      79: invokeinterface #26,  3           // InterfaceMethod java/util/Map.put:(Ljava/lang/Object;Ljava/lang/Object;)Ljava/lang/Object;
      84: pop
      85: getstatic     #3                  // Field specClassToProgramType:Ljava/util/Map;
      88: ldc_w         #35                 // class co/cask/cdap/api/service/ServiceSpecification
      91: getstatic     #36                 // Field co/cask/cdap/proto/ProgramType.SERVICE:Lco/cask/cdap/proto/ProgramType;
      94: invokeinterface #26,  3           // InterfaceMethod java/util/Map.put:(Ljava/lang/Object;Ljava/lang/Object;)Ljava/lang/Object;
      99: pop
     100: getstatic     #3                  // Field specClassToProgramType:Ljava/util/Map;
     103: ldc_w         #37                 // class co/cask/cdap/api/worker/WorkerSpecification
     106: getstatic     #38                 // Field co/cask/cdap/proto/ProgramType.WORKER:Lco/cask/cdap/proto/ProgramType;
     109: invokeinterface #26,  3           // InterfaceMethod java/util/Map.put:(Ljava/lang/Object;Ljava/lang/Object;)Ljava/lang/Object;
     114: pop
     115: return
}
