Compiled from "Headers.java"
class io.nats.client.impl.Headers$Checker {
  java.util.List<java.lang.String> list;

  int len;

  final io.nats.client.impl.Headers this$0;

  io.nats.client.impl.Headers$Checker(java.lang.String, java.util.Collection<java.lang.String>);
    Code:
       0: aload_0
       1: aload_1
       2: putfield      #1                  // Field this$0:Lio/nats/client/impl/Headers;
       5: aload_0
       6: invokespecial #2                  // Method java/lang/Object."<init>":()V
       9: aload_0
      10: new           #3                  // class java/util/ArrayList
      13: dup
      14: invokespecial #4                  // Method java/util/ArrayList."<init>":()V
      17: putfield      #5                  // Field list:Ljava/util/List;
      20: aload_0
      21: iconst_0
      22: putfield      #6                  // Field len:I
      25: aload_1
      26: aload_2
      27: invokestatic  #7                  // Method io/nats/client/impl/Headers.access$000:(Lio/nats/client/impl/Headers;Ljava/lang/String;)V
      30: aload_3
      31: invokeinterface #8,  1            // InterfaceMethod java/util/Collection.isEmpty:()Z
      36: ifne          154
      39: aload_3
      40: invokeinterface #9,  1            // InterfaceMethod java/util/Collection.iterator:()Ljava/util/Iterator;
      45: astore        4
      47: aload         4
      49: invokeinterface #10,  1           // InterfaceMethod java/util/Iterator.hasNext:()Z
      54: ifeq          154
      57: aload         4
      59: invokeinterface #11,  1           // InterfaceMethod java/util/Iterator.next:()Ljava/lang/Object;
      64: checkcast     #12                 // class java/lang/String
      67: astore        5
      69: aload         5
      71: ifnull        151
      74: aload         5
      76: invokevirtual #13                 // Method java/lang/String.isEmpty:()Z
      79: ifeq          112
      82: aload_0
      83: getfield      #5                  // Field list:Ljava/util/List;
      86: aload         5
      88: invokeinterface #14,  2           // InterfaceMethod java/util/List.add:(Ljava/lang/Object;)Z
      93: pop
      94: aload_0
      95: dup
      96: getfield      #6                  // Field len:I
      99: aload_2
     100: invokevirtual #15                 // Method java/lang/String.length:()I
     103: iconst_3
     104: iadd
     105: iadd
     106: putfield      #6                  // Field len:I
     109: goto          151
     112: aload_1
     113: aload         5
     115: invokestatic  #16                 // Method io/nats/client/impl/Headers.access$100:(Lio/nats/client/impl/Headers;Ljava/lang/String;)V
     118: aload_0
     119: getfield      #5                  // Field list:Ljava/util/List;
     122: aload         5
     124: invokeinterface #14,  2           // InterfaceMethod java/util/List.add:(Ljava/lang/Object;)Z
     129: pop
     130: aload_0
     131: dup
     132: getfield      #6                  // Field len:I
     135: aload_2
     136: invokevirtual #15                 // Method java/lang/String.length:()I
     139: aload         5
     141: invokevirtual #15                 // Method java/lang/String.length:()I
     144: iadd
     145: iconst_3
     146: iadd
     147: iadd
     148: putfield      #6                  // Field len:I
     151: goto          47
     154: return

  boolean hasValues();
    Code:
       0: aload_0
       1: getfield      #5                  // Field list:Ljava/util/List;
       4: invokeinterface #17,  1           // InterfaceMethod java/util/List.size:()I
       9: ifle          16
      12: iconst_1
      13: goto          17
      16: iconst_0
      17: ireturn
}
