Compiled from "PushHeartbeatListener.java"
public class org.jumpmind.symmetric.job.PushHeartbeatListener implements org.jumpmind.symmetric.ext.IHeartbeatListener {
  private org.jumpmind.symmetric.service.IDataService dataService;

  private org.jumpmind.symmetric.service.INodeService nodeService;

  private org.jumpmind.symmetric.db.ISymmetricDialect symmetricDialect;

  private org.jumpmind.symmetric.service.IParameterService parameterService;

  public org.jumpmind.symmetric.job.PushHeartbeatListener(org.jumpmind.symmetric.service.IParameterService, org.jumpmind.symmetric.service.IDataService, org.jumpmind.symmetric.service.INodeService, org.jumpmind.symmetric.db.ISymmetricDialect);
    Code:
       0: aload_0
       1: invokespecial #1                  // Method java/lang/Object."<init>":()V
       4: aload_0
       5: aload_1
       6: putfield      #2                  // Field parameterService:Lorg/jumpmind/symmetric/service/IParameterService;
       9: aload_0
      10: aload_2
      11: putfield      #3                  // Field dataService:Lorg/jumpmind/symmetric/service/IDataService;
      14: aload_0
      15: aload_3
      16: putfield      #4                  // Field nodeService:Lorg/jumpmind/symmetric/service/INodeService;
      19: aload_0
      20: aload         4
      22: putfield      #5                  // Field symmetricDialect:Lorg/jumpmind/symmetric/db/ISymmetricDialect;
      25: return

  public void heartbeat(org.jumpmind.symmetric.model.Node, java.util.Set<org.jumpmind.symmetric.model.Node>);
    Code:
       0: aload_0
       1: getfield      #2                  // Field parameterService:Lorg/jumpmind/symmetric/service/IParameterService;
       4: ldc           #6                  // String heartbeat.sync.on.push.enabled
       6: invokeinterface #7,  2            // InterfaceMethod org/jumpmind/symmetric/service/IParameterService.is:(Ljava/lang/String;)Z
      11: ifeq          99
      14: aload_0
      15: getfield      #4                  // Field nodeService:Lorg/jumpmind/symmetric/service/INodeService;
      18: invokeinterface #8,  1            // InterfaceMethod org/jumpmind/symmetric/service/INodeService.isRegistrationServer:()Z
      23: ifne          99
      26: aload_0
      27: getfield      #5                  // Field symmetricDialect:Lorg/jumpmind/symmetric/db/ISymmetricDialect;
      30: invokeinterface #9,  1            // InterfaceMethod org/jumpmind/symmetric/db/ISymmetricDialect.getPlatform:()Lorg/jumpmind/db/platform/IDatabasePlatform;
      35: invokeinterface #10,  1           // InterfaceMethod org/jumpmind/db/platform/IDatabasePlatform.getDatabaseInfo:()Lorg/jumpmind/db/platform/DatabaseInfo;
      40: invokevirtual #11                 // Method org/jumpmind/db/platform/DatabaseInfo.isTriggersSupported:()Z
      43: ifne          99
      46: aload_0
      47: getfield      #3                  // Field dataService:Lorg/jumpmind/symmetric/service/IDataService;
      50: aload_1
      51: iconst_0
      52: invokeinterface #12,  3           // InterfaceMethod org/jumpmind/symmetric/service/IDataService.insertHeartbeatEvent:(Lorg/jumpmind/symmetric/model/Node;Z)V
      57: aload_2
      58: invokeinterface #13,  1           // InterfaceMethod java/util/Set.iterator:()Ljava/util/Iterator;
      63: astore_3
      64: aload_3
      65: invokeinterface #14,  1           // InterfaceMethod java/util/Iterator.hasNext:()Z
      70: ifeq          99
      73: aload_3
      74: invokeinterface #15,  1           // InterfaceMethod java/util/Iterator.next:()Ljava/lang/Object;
      79: checkcast     #16                 // class org/jumpmind/symmetric/model/Node
      82: astore        4
      84: aload_0
      85: getfield      #3                  // Field dataService:Lorg/jumpmind/symmetric/service/IDataService;
      88: aload         4
      90: iconst_0
      91: invokeinterface #12,  3           // InterfaceMethod org/jumpmind/symmetric/service/IDataService.insertHeartbeatEvent:(Lorg/jumpmind/symmetric/model/Node;Z)V
      96: goto          64
      99: return

  public long getTimeBetweenHeartbeatsInSeconds();
    Code:
       0: aload_0
       1: getfield      #2                  // Field parameterService:Lorg/jumpmind/symmetric/service/IParameterService;
       4: ldc           #17                 // String heartbeat.sync.on.push.period.sec
       6: ldc2_w        #18                 // long 600l
       9: invokeinterface #20,  4           // InterfaceMethod org/jumpmind/symmetric/service/IParameterService.getLong:(Ljava/lang/String;J)J
      14: lreturn
}
