Compiled from "AddrRemapper.java"
public class org.hpccsystems.dfs.cluster.AddrRemapper extends org.hpccsystems.dfs.cluster.ClusterRemapper {
  private java.util.HashMap<java.lang.String, java.lang.String> ip_tab;

  private int rowServicePort;

  private boolean usesSSL;

  private static java.util.Comparator<org.hpccsystems.ws.client.wrappers.wsdfu.DFUPartWrapper> FilePartInfoComparator;

  public org.hpccsystems.dfs.cluster.AddrRemapper(org.hpccsystems.dfs.cluster.RemapInfo, org.hpccsystems.ws.client.wrappers.wsdfu.DFUFileAccessInfoWrapper) throws org.hpccsystems.commons.errors.HpccFileException;
    Code:
       0: aload_0
       1: aload_1
       2: invokespecial #1                  // Method org/hpccsystems/dfs/cluster/ClusterRemapper."<init>":(Lorg/hpccsystems/dfs/cluster/RemapInfo;)V
       5: aload_0
       6: aload_2
       7: invokevirtual #2                  // Method org/hpccsystems/ws/client/wrappers/wsdfu/DFUFileAccessInfoWrapper.getFileAccessPort:()Ljava/lang/Integer;
      10: invokevirtual #3                  // Method java/lang/Integer.intValue:()I
      13: putfield      #4                  // Field rowServicePort:I
      16: aload_0
      17: aload_2
      18: invokevirtual #5                  // Method org/hpccsystems/ws/client/wrappers/wsdfu/DFUFileAccessInfoWrapper.getFileAccessSSL:()Ljava/lang/Boolean;
      21: invokevirtual #6                  // Method java/lang/Boolean.booleanValue:()Z
      24: putfield      #7                  // Field usesSSL:Z
      27: aload_2
      28: invokevirtual #8                  // Method org/hpccsystems/ws/client/wrappers/wsdfu/DFUFileAccessInfoWrapper.getAllFilePartCopyLocations:()[Ljava/lang/String;
      31: astore_3
      32: new           #9                  // class java/util/HashSet
      35: dup
      36: aload_3
      37: arraylength
      38: invokespecial #10                 // Method java/util/HashSet."<init>":(I)V
      41: astore        4
      43: aload_3
      44: astore        5
      46: aload         5
      48: arraylength
      49: istore        6
      51: iconst_0
      52: istore        7
      54: iload         7
      56: iload         6
      58: if_icmpge     82
      61: aload         5
      63: iload         7
      65: aaload
      66: astore        8
      68: aload         4
      70: aload         8
      72: invokevirtual #11                 // Method java/util/HashSet.add:(Ljava/lang/Object;)Z
      75: pop
      76: iinc          7, 1
      79: goto          54
      82: aload         4
      84: iconst_0
      85: anewarray     #12                 // class java/lang/String
      88: invokevirtual #13                 // Method java/util/HashSet.toArray:([Ljava/lang/Object;)[Ljava/lang/Object;
      91: checkcast     #14                 // class "[Ljava/lang/String;"
      94: astore        5
      96: aload         5
      98: invokestatic  #15                 // Method java/util/Arrays.sort:([Ljava/lang/Object;)V
     101: aload         5
     103: arraylength
     104: aload_1
     105: invokevirtual #16                 // Method org/hpccsystems/dfs/cluster/RemapInfo.getNodes:()I
     108: if_icmple     168
     111: new           #17                 // class java/lang/StringBuilder
     114: dup
     115: invokespecial #18                 // Method java/lang/StringBuilder."<init>":()V
     118: astore        6
     120: aload         6
     122: ldc           #19                 // String Too many addresses, need
     124: invokevirtual #20                 // Method java/lang/StringBuilder.append:(Ljava/lang/String;)Ljava/lang/StringBuilder;
     127: pop
     128: aload         6
     130: aload         5
     132: arraylength
     133: invokevirtual #21                 // Method java/lang/StringBuilder.append:(I)Ljava/lang/StringBuilder;
     136: pop
     137: aload         6
     139: ldc           #22                 // String  but have only
     141: invokevirtual #20                 // Method java/lang/StringBuilder.append:(Ljava/lang/String;)Ljava/lang/StringBuilder;
     144: pop
     145: aload         6
     147: aload_1
     148: invokevirtual #16                 // Method org/hpccsystems/dfs/cluster/RemapInfo.getNodes:()I
     151: invokevirtual #21                 // Method java/lang/StringBuilder.append:(I)Ljava/lang/StringBuilder;
     154: pop
     155: new           #23                 // class org/hpccsystems/commons/errors/HpccFileException
     158: dup
     159: aload         6
     161: invokevirtual #24                 // Method java/lang/StringBuilder.toString:()Ljava/lang/String;
     164: invokespecial #25                 // Method org/hpccsystems/commons/errors/HpccFileException."<init>":(Ljava/lang/String;)V
     167: athrow
     168: iconst_4
     169: newarray       short
     171: astore        6
     173: new           #26                 // class java/util/StringTokenizer
     176: dup
     177: aload_1
     178: invokevirtual #27                 // Method org/hpccsystems/dfs/cluster/RemapInfo.getBaseIp:()Ljava/lang/String;
     181: ldc           #28                 // String .
     183: invokespecial #29                 // Method java/util/StringTokenizer."<init>":(Ljava/lang/String;Ljava/lang/String;)V
     186: astore        7
     188: aload         7
     190: invokevirtual #30                 // Method java/util/StringTokenizer.countTokens:()I
     193: iconst_4
     194: if_icmpeq     207
     197: new           #31                 // class java/lang/IllegalArgumentException
     200: dup
     201: ldc           #32                 // String Incomplete IP address for target
     203: invokespecial #33                 // Method java/lang/IllegalArgumentException."<init>":(Ljava/lang/String;)V
     206: athrow
     207: iconst_0
     208: istore        8
     210: aload         7
     212: invokevirtual #34                 // Method java/util/StringTokenizer.hasMoreTokens:()Z
     215: ifeq          237
     218: aload         6
     220: iload         8
     222: aload         7
     224: invokevirtual #35                 // Method java/util/StringTokenizer.nextToken:()Ljava/lang/String;
     227: invokestatic  #36                 // Method java/lang/Short.parseShort:(Ljava/lang/String;)S
     230: sastore
     231: iinc          8, 1
     234: goto          210
     237: aload_0
     238: new           #37                 // class java/util/HashMap
     241: dup
     242: aload         5
     244: arraylength
     245: iconst_2
     246: imul
     247: invokespecial #38                 // Method java/util/HashMap."<init>":(I)V
     250: putfield      #39                 // Field ip_tab:Ljava/util/HashMap;
     253: iconst_0
     254: istore        9
     256: iload         9
     258: aload         5
     260: arraylength
     261: if_icmpge     423
     264: new           #17                 // class java/lang/StringBuilder
     267: dup
     268: invokespecial #18                 // Method java/lang/StringBuilder."<init>":()V
     271: astore        10
     273: iconst_0
     274: istore        11
     276: iload         11
     278: iconst_4
     279: if_icmpge     313
     282: aload         10
     284: aload         6
     286: iload         11
     288: saload
     289: invokevirtual #21                 // Method java/lang/StringBuilder.append:(I)Ljava/lang/StringBuilder;
     292: pop
     293: iload         11
     295: iconst_3
     296: if_icmpge     307
     299: aload         10
     301: ldc           #28                 // String .
     303: invokevirtual #20                 // Method java/lang/StringBuilder.append:(Ljava/lang/String;)Ljava/lang/StringBuilder;
     306: pop
     307: iinc          11, 1
     310: goto          276
     313: aload_0
     314: getfield      #39                 // Field ip_tab:Ljava/util/HashMap;
     317: aload         5
     319: iload         9
     321: aaload
     322: aload         10
     324: invokevirtual #24                 // Method java/lang/StringBuilder.toString:()Ljava/lang/String;
     327: invokevirtual #40                 // Method java/util/HashMap.put:(Ljava/lang/Object;Ljava/lang/Object;)Ljava/lang/Object;
     330: pop
     331: aload         6
     333: iconst_3
     334: dup2
     335: saload
     336: iconst_1
     337: iadd
     338: i2s
     339: sastore
     340: aload         6
     342: iconst_3
     343: saload
     344: sipush        256
     347: if_icmpge     353
     350: goto          417
     353: aload         6
     355: iconst_3
     356: iconst_0
     357: sastore
     358: aload         6
     360: iconst_2
     361: dup2
     362: saload
     363: iconst_1
     364: iadd
     365: i2s
     366: sastore
     367: aload         6
     369: iconst_2
     370: saload
     371: sipush        256
     374: if_icmpge     380
     377: goto          417
     380: aload         6
     382: iconst_2
     383: iconst_0
     384: sastore
     385: aload         6
     387: iconst_1
     388: dup2
     389: saload
     390: iconst_1
     391: iadd
     392: i2s
     393: sastore
     394: aload         6
     396: iconst_1
     397: saload
     398: sipush        256
     401: if_icmpge     407
     404: goto          417
     407: new           #31                 // class java/lang/IllegalArgumentException
     410: dup
     411: ldc           #41                 // String Too many nodes for starting address
     413: invokespecial #33                 // Method java/lang/IllegalArgumentException."<init>":(Ljava/lang/String;)V
     416: athrow
     417: iinc          9, 1
     420: goto          256
     423: return

  public java.lang.String[] reviseIPs(java.lang.String[]) throws org.hpccsystems.commons.errors.HpccFileException;
    Code:
       0: aload_1
       1: arraylength
       2: anewarray     #12                 // class java/lang/String
       5: astore_2
       6: iconst_0
       7: istore_3
       8: iload_3
       9: aload_1
      10: arraylength
      11: if_icmpge     59
      14: aload_0
      15: getfield      #39                 // Field ip_tab:Ljava/util/HashMap;
      18: aload_1
      19: iload_3
      20: aaload
      21: invokevirtual #42                 // Method java/util/HashMap.containsKey:(Ljava/lang/Object;)Z
      24: ifne          37
      27: new           #23                 // class org/hpccsystems/commons/errors/HpccFileException
      30: dup
      31: ldc           #43                 // String IP not in cluster ip mapping table
      33: invokespecial #25                 // Method org/hpccsystems/commons/errors/HpccFileException."<init>":(Ljava/lang/String;)V
      36: athrow
      37: aload_2
      38: iload_3
      39: aload_0
      40: getfield      #39                 // Field ip_tab:Ljava/util/HashMap;
      43: aload_1
      44: iload_3
      45: aaload
      46: invokevirtual #44                 // Method java/util/HashMap.get:(Ljava/lang/Object;)Ljava/lang/Object;
      49: checkcast     #12                 // class java/lang/String
      52: aastore
      53: iinc          3, 1
      56: goto          8
      59: aload_2
      60: areturn

  public java.lang.String[] reviseIPs(org.hpccsystems.ws.client.wrappers.wsdfu.DFUFileCopyWrapper[]) throws org.hpccsystems.commons.errors.HpccFileException;
    Code:
       0: aload_1
       1: arraylength
       2: anewarray     #12                 // class java/lang/String
       5: astore_2
       6: iconst_0
       7: istore_3
       8: iload_3
       9: aload_2
      10: arraylength
      11: if_icmpge     65
      14: aload_0
      15: getfield      #39                 // Field ip_tab:Ljava/util/HashMap;
      18: aload_1
      19: iload_3
      20: aaload
      21: invokevirtual #45                 // Method org/hpccsystems/ws/client/wrappers/wsdfu/DFUFileCopyWrapper.getCopyHost:()Ljava/lang/String;
      24: invokevirtual #42                 // Method java/util/HashMap.containsKey:(Ljava/lang/Object;)Z
      27: ifne          40
      30: new           #23                 // class org/hpccsystems/commons/errors/HpccFileException
      33: dup
      34: ldc           #43                 // String IP not in cluster ip mapping table
      36: invokespecial #25                 // Method org/hpccsystems/commons/errors/HpccFileException."<init>":(Ljava/lang/String;)V
      39: athrow
      40: aload_2
      41: iload_3
      42: aload_0
      43: getfield      #39                 // Field ip_tab:Ljava/util/HashMap;
      46: aload_1
      47: iload_3
      48: aaload
      49: invokevirtual #45                 // Method org/hpccsystems/ws/client/wrappers/wsdfu/DFUFileCopyWrapper.getCopyHost:()Ljava/lang/String;
      52: invokevirtual #44                 // Method java/util/HashMap.get:(Ljava/lang/Object;)Ljava/lang/Object;
      55: checkcast     #12                 // class java/lang/String
      58: aastore
      59: iinc          3, 1
      62: goto          8
      65: aload_2
      66: areturn

  public int revisePort(org.hpccsystems.ws.client.wrappers.wsdfu.DFUPartWrapper);
    Code:
       0: aload_0
       1: getfield      #4                  // Field rowServicePort:I
       4: ireturn

  public boolean getUsesSSLConnection(org.hpccsystems.ws.client.wrappers.wsdfu.DFUPartWrapper);
    Code:
       0: aload_0
       1: getfield      #7                  // Field usesSSL:Z
       4: ireturn

  static {};
    Code:
       0: new           #46                 // class org/hpccsystems/dfs/cluster/AddrRemapper$1
       3: dup
       4: invokespecial #47                 // Method org/hpccsystems/dfs/cluster/AddrRemapper$1."<init>":()V
       7: putstatic     #48                 // Field FilePartInfoComparator:Ljava/util/Comparator;
      10: return
}
