Compiled from "NullRemapper.java"
public class org.hpccsystems.dfs.cluster.NullRemapper extends org.hpccsystems.dfs.cluster.ClusterRemapper {
  private int rowServicePort;

  private boolean usesSSL;

  public org.hpccsystems.dfs.cluster.NullRemapper(org.hpccsystems.dfs.cluster.RemapInfo, org.hpccsystems.ws.client.wrappers.wsdfu.DFUFileAccessInfoWrapper) throws org.hpccsystems.commons.errors.HpccFileException;
    Code:
       0: aload_0
       1: aload_1
       2: invokespecial #1                  // Method org/hpccsystems/dfs/cluster/ClusterRemapper."<init>":(Lorg/hpccsystems/dfs/cluster/RemapInfo;)V
       5: aload_0
       6: sipush        7601
       9: putfield      #3                  // Field rowServicePort:I
      12: aload_0
      13: iconst_0
      14: putfield      #4                  // Field usesSSL:Z
      17: aload_1
      18: invokevirtual #5                  // Method org/hpccsystems/dfs/cluster/RemapInfo.isNullMapper:()Z
      21: ifne          34
      24: new           #6                  // class java/lang/IllegalArgumentException
      27: dup
      28: ldc           #7                  // String Incompatible re-mapping information
      30: invokespecial #8                  // Method java/lang/IllegalArgumentException."<init>":(Ljava/lang/String;)V
      33: athrow
      34: aload_0
      35: aload_2
      36: invokevirtual #9                  // Method org/hpccsystems/ws/client/wrappers/wsdfu/DFUFileAccessInfoWrapper.getFileAccessPort:()Ljava/lang/Integer;
      39: invokevirtual #10                 // Method java/lang/Integer.intValue:()I
      42: putfield      #3                  // Field rowServicePort:I
      45: aload_0
      46: aload_2
      47: invokevirtual #11                 // Method org/hpccsystems/ws/client/wrappers/wsdfu/DFUFileAccessInfoWrapper.getFileAccessSSL:()Ljava/lang/Boolean;
      50: invokevirtual #12                 // Method java/lang/Boolean.booleanValue:()Z
      53: putfield      #4                  // Field usesSSL:Z
      56: return

  public java.lang.String[] reviseIPs(org.hpccsystems.ws.client.wrappers.wsdfu.DFUFileCopyWrapper[]) throws org.hpccsystems.commons.errors.HpccFileException;
    Code:
       0: aload_1
       1: arraylength
       2: anewarray     #13                 // class java/lang/String
       5: astore_2
       6: iconst_0
       7: istore_3
       8: iload_3
       9: aload_2
      10: arraylength
      11: if_icmpge     29
      14: aload_2
      15: iload_3
      16: aload_1
      17: iload_3
      18: aaload
      19: invokevirtual #14                 // Method org/hpccsystems/ws/client/wrappers/wsdfu/DFUFileCopyWrapper.getCopyHost:()Ljava/lang/String;
      22: aastore
      23: iinc          3, 1
      26: goto          8
      29: aload_2
      30: areturn

  public java.lang.String[] reviseIPs(java.lang.String[]) throws org.hpccsystems.commons.errors.HpccFileException;
    Code:
       0: aload_1
       1: areturn

  public int revisePort(org.hpccsystems.ws.client.wrappers.wsdfu.DFUPartWrapper);
    Code:
       0: aload_0
       1: getfield      #3                  // Field rowServicePort:I
       4: ireturn

  public boolean getUsesSSLConnection(org.hpccsystems.ws.client.wrappers.wsdfu.DFUPartWrapper);
    Code:
       0: aload_0
       1: getfield      #4                  // Field usesSSL:Z
       4: ireturn
}
