Compiled from "TypeConverters.java"
public class org.apache.logging.log4j.core.config.plugins.convert.TypeConverters$ByteArrayConverter implements org.apache.logging.log4j.core.config.plugins.convert.TypeConverter<byte[]> {
  private static final java.lang.String PREFIX_0x;

  private static final java.lang.String PREFIX_BASE64;

  public org.apache.logging.log4j.core.config.plugins.convert.TypeConverters$ByteArrayConverter();
    Code:
       0: aload_0
       1: invokespecial #1                  // Method java/lang/Object."<init>":()V
       4: return

  public byte[] convert(java.lang.String);
    Code:
       0: aload_1
       1: ifnull        11
       4: aload_1
       5: invokevirtual #2                  // Method java/lang/String.isEmpty:()Z
       8: ifeq          18
      11: getstatic     #3                  // Field org/apache/logging/log4j/util/Constants.EMPTY_BYTE_ARRAY:[B
      14: astore_2
      15: goto          80
      18: aload_1
      19: ldc           #5                  // String Base64:
      21: invokevirtual #6                  // Method java/lang/String.startsWith:(Ljava/lang/String;)Z
      24: ifeq          45
      27: aload_1
      28: ldc           #5                  // String Base64:
      30: invokevirtual #7                  // Method java/lang/String.length:()I
      33: invokevirtual #8                  // Method java/lang/String.substring:(I)Ljava/lang/String;
      36: astore_3
      37: aload_3
      38: invokestatic  #9                  // Method org/apache/logging/log4j/core/config/plugins/convert/Base64Converter.parseBase64Binary:(Ljava/lang/String;)[B
      41: astore_2
      42: goto          80
      45: aload_1
      46: ldc           #10                 // String 0x
      48: invokevirtual #6                  // Method java/lang/String.startsWith:(Ljava/lang/String;)Z
      51: ifeq          72
      54: aload_1
      55: ldc           #10                 // String 0x
      57: invokevirtual #7                  // Method java/lang/String.length:()I
      60: invokevirtual #8                  // Method java/lang/String.substring:(I)Ljava/lang/String;
      63: astore_3
      64: aload_3
      65: invokestatic  #11                 // Method org/apache/logging/log4j/core/config/plugins/convert/HexConverter.parseHexBinary:(Ljava/lang/String;)[B
      68: astore_2
      69: goto          80
      72: aload_1
      73: invokestatic  #12                 // Method java/nio/charset/Charset.defaultCharset:()Ljava/nio/charset/Charset;
      76: invokevirtual #13                 // Method java/lang/String.getBytes:(Ljava/nio/charset/Charset;)[B
      79: astore_2
      80: aload_2
      81: areturn

  public java.lang.Object convert(java.lang.String) throws java.lang.Exception;
    Code:
       0: aload_0
       1: aload_1
       2: invokevirtual #14                 // Method convert:(Ljava/lang/String;)[B
       5: areturn
}
