class org.bouncycastle.cms.CMSAuthenticatedData$1 implements org.bouncycastle.cms.AuthAttributesProvider {
  final org.bouncycastle.cms.CMSAuthenticatedData this$0;

  org.bouncycastle.cms.CMSAuthenticatedData$1(org.bouncycastle.cms.CMSAuthenticatedData);
    Code:
       0: aload_0
       1: aload_1
       2: putfield      #23                 // Field this$0:Lorg/bouncycastle/cms/CMSAuthenticatedData;
       5: aload_0
       6: invokespecial #24                 // Method java/lang/Object."<init>":()V
       9: return

  public org.bouncycastle.asn1.ASN1Set getAuthAttributes();
    Code:
       0: aload_0
       1: getfield      #23                 // Field this$0:Lorg/bouncycastle/cms/CMSAuthenticatedData;
       4: invokestatic  #25                 // Method org/bouncycastle/cms/CMSAuthenticatedData.access$000:(Lorg/bouncycastle/cms/CMSAuthenticatedData;)Lorg/bouncycastle/asn1/ASN1Set;
       7: areturn
}
