Compiled from "SchemaMappingsDocParser.java"
public class es.weso.shapepath.parser.SchemaMappingsDocParser$ContextStepContext extends es.weso.shapepath.parser.SchemaMappingsDocParser$StepExprContext {
  public es.weso.shapepath.parser.SchemaMappingsDocParser$ContextTestContext contextTest();
    Code:
       0: aload_0
       1: ldc           #1                  // class es/weso/shapepath/parser/SchemaMappingsDocParser$ContextTestContext
       3: iconst_0
       4: invokevirtual #2                  // Method getRuleContext:(Ljava/lang/Class;I)Lorg/antlr/v4/runtime/ParserRuleContext;
       7: checkcast     #1                  // class es/weso/shapepath/parser/SchemaMappingsDocParser$ContextTestContext
      10: areturn

  public es.weso.shapepath.parser.SchemaMappingsDocParser$ContextStepContext(es.weso.shapepath.parser.SchemaMappingsDocParser$StepExprContext);
    Code:
       0: aload_0
       1: invokespecial #3                  // Method es/weso/shapepath/parser/SchemaMappingsDocParser$StepExprContext."<init>":()V
       4: aload_0
       5: aload_1
       6: invokevirtual #4                  // Method copyFrom:(Les/weso/shapepath/parser/SchemaMappingsDocParser$StepExprContext;)V
       9: return

  public void enterRule(org.antlr.v4.runtime.tree.ParseTreeListener);
    Code:
       0: aload_1
       1: instanceof    #5                  // class es/weso/shapepath/parser/SchemaMappingsDocListener
       4: ifeq          17
       7: aload_1
       8: checkcast     #5                  // class es/weso/shapepath/parser/SchemaMappingsDocListener
      11: aload_0
      12: invokeinterface #6,  2            // InterfaceMethod es/weso/shapepath/parser/SchemaMappingsDocListener.enterContextStep:(Les/weso/shapepath/parser/SchemaMappingsDocParser$ContextStepContext;)V
      17: return

  public void exitRule(org.antlr.v4.runtime.tree.ParseTreeListener);
    Code:
       0: aload_1
       1: instanceof    #5                  // class es/weso/shapepath/parser/SchemaMappingsDocListener
       4: ifeq          17
       7: aload_1
       8: checkcast     #5                  // class es/weso/shapepath/parser/SchemaMappingsDocListener
      11: aload_0
      12: invokeinterface #7,  2            // InterfaceMethod es/weso/shapepath/parser/SchemaMappingsDocListener.exitContextStep:(Les/weso/shapepath/parser/SchemaMappingsDocParser$ContextStepContext;)V
      17: return

  public <T> T accept(org.antlr.v4.runtime.tree.ParseTreeVisitor<? extends T>);
    Code:
       0: aload_1
       1: instanceof    #8                  // class es/weso/shapepath/parser/SchemaMappingsDocVisitor
       4: ifeq          18
       7: aload_1
       8: checkcast     #8                  // class es/weso/shapepath/parser/SchemaMappingsDocVisitor
      11: aload_0
      12: invokeinterface #9,  2            // InterfaceMethod es/weso/shapepath/parser/SchemaMappingsDocVisitor.visitContextStep:(Les/weso/shapepath/parser/SchemaMappingsDocParser$ContextStepContext;)Ljava/lang/Object;
      17: areturn
      18: aload_1
      19: aload_0
      20: invokeinterface #10,  2           // InterfaceMethod org/antlr/v4/runtime/tree/ParseTreeVisitor.visitChildren:(Lorg/antlr/v4/runtime/tree/RuleNode;)Ljava/lang/Object;
      25: areturn
}
