Compiled from "KeySequence.java"
public final class org.eclipse.ui.keys.KeySequence implements java.lang.Comparable {
  public static final java.lang.String KEY_STROKE_DELIMITER;

  private static final org.eclipse.ui.keys.KeySequence EMPTY_KEY_SEQUENCE;

  private static final int HASH_FACTOR;

  private static final int HASH_INITIAL;

  public static final java.lang.String KEY_STROKE_DELIMITERS;

  private transient int hashCode;

  private transient boolean hashCodeComputed;

  private java.util.List<org.eclipse.ui.keys.KeyStroke> keyStrokes;

  static {};
    Code:
       0: new           #3                  // class org/eclipse/ui/keys/KeySequence
       3: dup
       4: getstatic     #189                // Field java/util/Collections.EMPTY_LIST:Ljava/util/List;
       7: invokespecial #221                // Method "<init>":(Ljava/util/List;)V
      10: putstatic     #194                // Field EMPTY_KEY_SEQUENCE:Lorg/eclipse/ui/keys/KeySequence;
      13: ldc           #3                  // class org/eclipse/ui/keys/KeySequence
      15: invokevirtual #195                // Method java/lang/Class.getName:()Ljava/lang/String;
      18: invokevirtual #199                // Method java/lang/String.hashCode:()I
      21: putstatic     #190                // Field HASH_INITIAL:I
      24: return

  public static org.eclipse.ui.keys.KeySequence getInstance();
    Code:
       0: getstatic     #194                // Field EMPTY_KEY_SEQUENCE:Lorg/eclipse/ui/keys/KeySequence;
       3: areturn

  public static org.eclipse.ui.keys.KeySequence getInstance(org.eclipse.ui.keys.KeySequence, org.eclipse.ui.keys.KeyStroke);
    Code:
       0: aload_0
       1: ifnull        8
       4: aload_1
       5: ifnonnull     16
       8: new           #94                 // class java/lang/NullPointerException
      11: dup
      12: invokespecial #197                // Method java/lang/NullPointerException."<init>":()V
      15: athrow
      16: new           #99                 // class java/util/ArrayList
      19: dup
      20: aload_0
      21: invokevirtual #220                // Method getKeyStrokes:()Ljava/util/List;
      24: invokespecial #205                // Method java/util/ArrayList."<init>":(Ljava/util/Collection;)V
      27: astore_2
      28: aload_2
      29: aload_1
      30: invokeinterface #230,  2          // InterfaceMethod java/util/List.add:(Ljava/lang/Object;)Z
      35: pop
      36: new           #3                  // class org/eclipse/ui/keys/KeySequence
      39: dup
      40: aload_2
      41: invokespecial #221                // Method "<init>":(Ljava/util/List;)V
      44: areturn

  public static org.eclipse.ui.keys.KeySequence getInstance(org.eclipse.ui.keys.KeyStroke);
    Code:
       0: new           #3                  // class org/eclipse/ui/keys/KeySequence
       3: dup
       4: aload_0
       5: invokestatic  #207                // Method java/util/Collections.singletonList:(Ljava/lang/Object;)Ljava/util/List;
       8: invokespecial #221                // Method "<init>":(Ljava/util/List;)V
      11: areturn

  public static org.eclipse.ui.keys.KeySequence getInstance(org.eclipse.ui.keys.KeyStroke[]);
    Code:
       0: new           #3                  // class org/eclipse/ui/keys/KeySequence
       3: dup
       4: aload_0
       5: invokestatic  #206                // Method java/util/Arrays.asList:([Ljava/lang/Object;)Ljava/util/List;
       8: invokespecial #221                // Method "<init>":(Ljava/util/List;)V
      11: areturn

  public static org.eclipse.ui.keys.KeySequence getInstance(java.util.List);
    Code:
       0: new           #3                  // class org/eclipse/ui/keys/KeySequence
       3: dup
       4: aload_0
       5: invokespecial #221                // Method "<init>":(Ljava/util/List;)V
       8: areturn

  public static org.eclipse.ui.keys.KeySequence getInstance(org.eclipse.jface.bindings.keys.KeySequence);
    Code:
       0: aload_0
       1: invokevirtual #211                // Method org/eclipse/jface/bindings/keys/KeySequence.getKeyStrokes:()[Lorg/eclipse/jface/bindings/keys/KeyStroke;
       4: astore_1
       5: aload_1
       6: arraylength
       7: istore_2
       8: new           #99                 // class java/util/ArrayList
      11: dup
      12: iload_2
      13: invokespecial #204                // Method java/util/ArrayList."<init>":(I)V
      16: astore_3
      17: iconst_0
      18: istore        4
      20: goto          53
      23: aload_1
      24: iload         4
      26: aaload
      27: astore        5
      29: aload_3
      30: aload         5
      32: invokevirtual #212                // Method org/eclipse/jface/bindings/keys/KeyStroke.getModifierKeys:()I
      35: aload         5
      37: invokevirtual #213                // Method org/eclipse/jface/bindings/keys/KeyStroke.getNaturalKey:()I
      40: ior
      41: invokestatic  #225                // Method org/eclipse/ui/keys/SWTKeySupport.convertAcceleratorToKeyStroke:(I)Lorg/eclipse/ui/keys/KeyStroke;
      44: invokeinterface #230,  2          // InterfaceMethod java/util/List.add:(Ljava/lang/Object;)Z
      49: pop
      50: iinc          4, 1
      53: iload         4
      55: iload_2
      56: if_icmplt     23
      59: new           #3                  // class org/eclipse/ui/keys/KeySequence
      62: dup
      63: aload_3
      64: invokespecial #221                // Method "<init>":(Ljava/util/List;)V
      67: areturn

  public static org.eclipse.ui.keys.KeySequence getInstance(java.lang.String) throws org.eclipse.ui.keys.ParseException;
    Code:
       0: aload_0
       1: ifnonnull     12
       4: new           #94                 // class java/lang/NullPointerException
       7: dup
       8: invokespecial #197                // Method java/lang/NullPointerException."<init>":()V
      11: athrow
      12: new           #99                 // class java/util/ArrayList
      15: dup
      16: invokespecial #203                // Method java/util/ArrayList."<init>":()V
      19: astore_1
      20: new           #103                // class java/util/StringTokenizer
      23: dup
      24: aload_0
      25: ldc           #1                  // String  \b\r\u007f\u001b\f\n\u0000\t\u000b
      27: invokespecial #210                // Method java/util/StringTokenizer."<init>":(Ljava/lang/String;Ljava/lang/String;)V
      30: astore_2
      31: goto          48
      34: aload_1
      35: aload_2
      36: invokevirtual #209                // Method java/util/StringTokenizer.nextToken:()Ljava/lang/String;
      39: invokestatic  #223                // Method org/eclipse/ui/keys/KeyStroke.getInstance:(Ljava/lang/String;)Lorg/eclipse/ui/keys/KeyStroke;
      42: invokeinterface #230,  2          // InterfaceMethod java/util/List.add:(Ljava/lang/Object;)Z
      47: pop
      48: aload_2
      49: invokevirtual #208                // Method java/util/StringTokenizer.hasMoreTokens:()Z
      52: ifne          34
      55: new           #3                  // class org/eclipse/ui/keys/KeySequence
      58: dup
      59: aload_1
      60: invokespecial #221                // Method "<init>":(Ljava/util/List;)V
      63: areturn
      64: pop
      65: new           #109                // class org/eclipse/ui/keys/ParseException
      68: dup
      69: new           #97                 // class java/lang/StringBuilder
      72: dup
      73: ldc           #2                  // String Could not construct key sequence with these key strokes:
      75: invokespecial #201                // Method java/lang/StringBuilder."<init>":(Ljava/lang/String;)V
      78: aload_1
      79: invokevirtual #202                // Method java/lang/StringBuilder.append:(Ljava/lang/Object;)Ljava/lang/StringBuilder;
      82: invokevirtual #200                // Method java/lang/StringBuilder.toString:()Ljava/lang/String;
      85: invokespecial #224                // Method org/eclipse/ui/keys/ParseException."<init>":(Ljava/lang/String;)V
      88: athrow
    Exception table:
       from    to  target type
          55    63    64   Class java/lang/Throwable

  private org.eclipse.ui.keys.KeySequence(java.util.List<org.eclipse.ui.keys.KeyStroke>);
    Code:
       0: aload_0
       1: invokespecial #198                // Method java/lang/Object."<init>":()V
       4: aload_0
       5: aload_1
       6: ldc           #4                  // class org/eclipse/ui/keys/KeyStroke
       8: invokestatic  #217                // Method org/eclipse/ui/internal/util/Util.safeCopy:(Ljava/util/List;Ljava/lang/Class;)Ljava/util/List;
      11: putfield      #193                // Field keyStrokes:Ljava/util/List;
      14: iconst_0
      15: istore_2
      16: goto          51
      19: aload_0
      20: getfield      #193                // Field keyStrokes:Ljava/util/List;
      23: iload_2
      24: invokeinterface #229,  2          // InterfaceMethod java/util/List.get:(I)Ljava/lang/Object;
      29: checkcast     #4                  // class org/eclipse/ui/keys/KeyStroke
      32: astore_3
      33: aload_3
      34: invokevirtual #222                // Method org/eclipse/ui/keys/KeyStroke.isComplete:()Z
      37: ifne          48
      40: new           #93                 // class java/lang/IllegalArgumentException
      43: dup
      44: invokespecial #196                // Method java/lang/IllegalArgumentException."<init>":()V
      47: athrow
      48: iinc          2, 1
      51: iload_2
      52: aload_0
      53: getfield      #193                // Field keyStrokes:Ljava/util/List;
      56: invokeinterface #227,  1          // InterfaceMethod java/util/List.size:()I
      61: iconst_1
      62: isub
      63: if_icmplt     19
      66: return

  public int compareTo(java.lang.Object);
    Code:
       0: aload_1
       1: checkcast     #3                  // class org/eclipse/ui/keys/KeySequence
       4: astore_2
       5: aload_0
       6: getfield      #193                // Field keyStrokes:Ljava/util/List;
       9: aload_2
      10: getfield      #193                // Field keyStrokes:Ljava/util/List;
      13: invokestatic  #214                // Method org/eclipse/ui/internal/util/Util.compare:(Ljava/util/List;Ljava/util/List;)I
      16: ireturn

  public boolean endsWith(org.eclipse.ui.keys.KeySequence, boolean);
    Code:
       0: aload_1
       1: ifnonnull     12
       4: new           #94                 // class java/lang/NullPointerException
       7: dup
       8: invokespecial #197                // Method java/lang/NullPointerException."<init>":()V
      11: athrow
      12: aload_0
      13: getfield      #193                // Field keyStrokes:Ljava/util/List;
      16: aload_1
      17: getfield      #193                // Field keyStrokes:Ljava/util/List;
      20: iload_2
      21: invokestatic  #215                // Method org/eclipse/ui/internal/util/Util.endsWith:(Ljava/util/List;Ljava/util/List;Z)Z
      24: ireturn

  public boolean equals(java.lang.Object);
    Code:
       0: aload_1
       1: instanceof    #3                  // class org/eclipse/ui/keys/KeySequence
       4: ifne          9
       7: iconst_0
       8: ireturn
       9: aload_0
      10: getfield      #193                // Field keyStrokes:Ljava/util/List;
      13: aload_1
      14: checkcast     #3                  // class org/eclipse/ui/keys/KeySequence
      17: getfield      #193                // Field keyStrokes:Ljava/util/List;
      20: invokeinterface #231,  2          // InterfaceMethod java/util/List.equals:(Ljava/lang/Object;)Z
      25: ireturn

  public java.lang.String format();
    Code:
       0: invokestatic  #218                // Method org/eclipse/ui/keys/KeyFormatterFactory.getDefault:()Lorg/eclipse/ui/keys/IKeyFormatter;
       3: aload_0
       4: invokeinterface #232,  2          // InterfaceMethod org/eclipse/ui/keys/IKeyFormatter.format:(Lorg/eclipse/ui/keys/KeySequence;)Ljava/lang/String;
       9: areturn

  public java.util.List getKeyStrokes();
    Code:
       0: aload_0
       1: getfield      #193                // Field keyStrokes:Ljava/util/List;
       4: areturn

  public int hashCode();
    Code:
       0: aload_0
       1: getfield      #192                // Field hashCodeComputed:Z
       4: ifne          40
       7: aload_0
       8: getstatic     #190                // Field HASH_INITIAL:I
      11: putfield      #191                // Field hashCode:I
      14: aload_0
      15: aload_0
      16: getfield      #191                // Field hashCode:I
      19: bipush        89
      21: imul
      22: aload_0
      23: getfield      #193                // Field keyStrokes:Ljava/util/List;
      26: invokeinterface #226,  1          // InterfaceMethod java/util/List.hashCode:()I
      31: iadd
      32: putfield      #191                // Field hashCode:I
      35: aload_0
      36: iconst_1
      37: putfield      #192                // Field hashCodeComputed:Z
      40: aload_0
      41: getfield      #191                // Field hashCode:I
      44: ireturn

  public boolean isComplete();
    Code:
       0: aload_0
       1: getfield      #193                // Field keyStrokes:Ljava/util/List;
       4: invokeinterface #228,  1          // InterfaceMethod java/util/List.isEmpty:()Z
       9: ifne          43
      12: aload_0
      13: getfield      #193                // Field keyStrokes:Ljava/util/List;
      16: aload_0
      17: getfield      #193                // Field keyStrokes:Ljava/util/List;
      20: invokeinterface #227,  1          // InterfaceMethod java/util/List.size:()I
      25: iconst_1
      26: isub
      27: invokeinterface #229,  2          // InterfaceMethod java/util/List.get:(I)Ljava/lang/Object;
      32: checkcast     #4                  // class org/eclipse/ui/keys/KeyStroke
      35: invokevirtual #222                // Method org/eclipse/ui/keys/KeyStroke.isComplete:()Z
      38: ifne          43
      41: iconst_0
      42: ireturn
      43: iconst_1
      44: ireturn

  public boolean isEmpty();
    Code:
       0: aload_0
       1: getfield      #193                // Field keyStrokes:Ljava/util/List;
       4: invokeinterface #228,  1          // InterfaceMethod java/util/List.isEmpty:()Z
       9: ireturn

  public boolean startsWith(org.eclipse.ui.keys.KeySequence, boolean);
    Code:
       0: aload_1
       1: ifnonnull     12
       4: new           #94                 // class java/lang/NullPointerException
       7: dup
       8: invokespecial #197                // Method java/lang/NullPointerException."<init>":()V
      11: athrow
      12: aload_0
      13: getfield      #193                // Field keyStrokes:Ljava/util/List;
      16: aload_1
      17: getfield      #193                // Field keyStrokes:Ljava/util/List;
      20: iload_2
      21: invokestatic  #216                // Method org/eclipse/ui/internal/util/Util.startsWith:(Ljava/util/List;Ljava/util/List;Z)Z
      24: ireturn

  public java.lang.String toString();
    Code:
       0: invokestatic  #219                // Method org/eclipse/ui/keys/KeyFormatterFactory.getFormalKeyFormatter:()Lorg/eclipse/ui/keys/IKeyFormatter;
       3: aload_0
       4: invokeinterface #232,  2          // InterfaceMethod org/eclipse/ui/keys/IKeyFormatter.format:(Lorg/eclipse/ui/keys/KeySequence;)Ljava/lang/String;
       9: areturn
}
