Compiled from "PathPattern.java"
public final class org.glassfish.jersey.uri.PathPattern extends org.glassfish.jersey.uri.PatternWithGroups {
  public static final org.glassfish.jersey.uri.PathPattern EMPTY_PATTERN;

  public static final org.glassfish.jersey.uri.PathPattern END_OF_PATH_PATTERN;

  public static final org.glassfish.jersey.uri.PathPattern OPEN_ROOT_PATH_PATTERN;

  public static final java.util.Comparator<org.glassfish.jersey.uri.PathPattern> COMPARATOR;

  private final org.glassfish.jersey.uri.UriTemplate template;

  public static org.glassfish.jersey.uri.PathPattern asClosed(org.glassfish.jersey.uri.PathPattern);
    Code:
       0: new           #2                  // class org/glassfish/jersey/uri/PathPattern
       3: dup
       4: aload_0
       5: invokevirtual #3                  // Method getTemplate:()Lorg/glassfish/jersey/uri/UriTemplate;
       8: invokevirtual #4                  // Method org/glassfish/jersey/uri/UriTemplate.getTemplate:()Ljava/lang/String;
      11: getstatic     #5                  // Field org/glassfish/jersey/uri/PathPattern$RightHandPath.capturingZeroSegments:Lorg/glassfish/jersey/uri/PathPattern$RightHandPath;
      14: invokespecial #6                  // Method "<init>":(Ljava/lang/String;Lorg/glassfish/jersey/uri/PathPattern$RightHandPath;)V
      17: areturn

  private org.glassfish.jersey.uri.PathPattern();
    Code:
       0: aload_0
       1: invokespecial #7                  // Method org/glassfish/jersey/uri/PatternWithGroups."<init>":()V
       4: aload_0
       5: getstatic     #8                  // Field org/glassfish/jersey/uri/UriTemplate.EMPTY:Lorg/glassfish/jersey/uri/UriTemplate;
       8: putfield      #1                  // Field template:Lorg/glassfish/jersey/uri/UriTemplate;
      11: return

  public org.glassfish.jersey.uri.PathPattern(java.lang.String);
    Code:
       0: aload_0
       1: new           #9                  // class org/glassfish/jersey/uri/PathTemplate
       4: dup
       5: aload_1
       6: invokespecial #10                 // Method org/glassfish/jersey/uri/PathTemplate."<init>":(Ljava/lang/String;)V
       9: invokespecial #11                 // Method "<init>":(Lorg/glassfish/jersey/uri/PathTemplate;)V
      12: return

  public org.glassfish.jersey.uri.PathPattern(org.glassfish.jersey.uri.PathTemplate);
    Code:
       0: aload_0
       1: aload_1
       2: invokevirtual #12                 // Method org/glassfish/jersey/uri/PathTemplate.getPattern:()Lorg/glassfish/jersey/uri/PatternWithGroups;
       5: invokevirtual #13                 // Method org/glassfish/jersey/uri/PatternWithGroups.getRegex:()Ljava/lang/String;
       8: invokestatic  #14                 // Method postfixWithCapturingGroup:(Ljava/lang/String;)Ljava/lang/String;
      11: aload_1
      12: invokevirtual #15                 // Method org/glassfish/jersey/uri/PathTemplate.getNumberOfRegexGroups:()I
      15: aload_1
      16: invokevirtual #12                 // Method org/glassfish/jersey/uri/PathTemplate.getPattern:()Lorg/glassfish/jersey/uri/PatternWithGroups;
      19: invokevirtual #16                 // Method org/glassfish/jersey/uri/PatternWithGroups.getGroupIndexes:()[I
      22: invokestatic  #17                 // Method addIndexForRightHandPathCapturingGroup:(I[I)[I
      25: invokespecial #18                 // Method org/glassfish/jersey/uri/PatternWithGroups."<init>":(Ljava/lang/String;[I)V
      28: aload_0
      29: aload_1
      30: putfield      #1                  // Field template:Lorg/glassfish/jersey/uri/UriTemplate;
      33: return

  public org.glassfish.jersey.uri.PathPattern(java.lang.String, org.glassfish.jersey.uri.PathPattern$RightHandPath);
    Code:
       0: aload_0
       1: new           #9                  // class org/glassfish/jersey/uri/PathTemplate
       4: dup
       5: aload_1
       6: invokespecial #10                 // Method org/glassfish/jersey/uri/PathTemplate."<init>":(Ljava/lang/String;)V
       9: aload_2
      10: invokespecial #19                 // Method "<init>":(Lorg/glassfish/jersey/uri/PathTemplate;Lorg/glassfish/jersey/uri/PathPattern$RightHandPath;)V
      13: return

  public org.glassfish.jersey.uri.PathPattern(org.glassfish.jersey.uri.PathTemplate, org.glassfish.jersey.uri.PathPattern$RightHandPath);
    Code:
       0: aload_0
       1: aload_1
       2: invokevirtual #12                 // Method org/glassfish/jersey/uri/PathTemplate.getPattern:()Lorg/glassfish/jersey/uri/PatternWithGroups;
       5: invokevirtual #13                 // Method org/glassfish/jersey/uri/PatternWithGroups.getRegex:()Ljava/lang/String;
       8: aload_2
       9: invokestatic  #20                 // Method postfixWithCapturingGroup:(Ljava/lang/String;Lorg/glassfish/jersey/uri/PathPattern$RightHandPath;)Ljava/lang/String;
      12: aload_1
      13: invokevirtual #15                 // Method org/glassfish/jersey/uri/PathTemplate.getNumberOfRegexGroups:()I
      16: aload_1
      17: invokevirtual #12                 // Method org/glassfish/jersey/uri/PathTemplate.getPattern:()Lorg/glassfish/jersey/uri/PatternWithGroups;
      20: invokevirtual #16                 // Method org/glassfish/jersey/uri/PatternWithGroups.getGroupIndexes:()[I
      23: invokestatic  #17                 // Method addIndexForRightHandPathCapturingGroup:(I[I)[I
      26: invokespecial #18                 // Method org/glassfish/jersey/uri/PatternWithGroups."<init>":(Ljava/lang/String;[I)V
      29: aload_0
      30: aload_1
      31: putfield      #1                  // Field template:Lorg/glassfish/jersey/uri/UriTemplate;
      34: return

  public org.glassfish.jersey.uri.UriTemplate getTemplate();
    Code:
       0: aload_0
       1: getfield      #1                  // Field template:Lorg/glassfish/jersey/uri/UriTemplate;
       4: areturn

  private static java.lang.String postfixWithCapturingGroup(java.lang.String);
    Code:
       0: aload_0
       1: getstatic     #21                 // Field org/glassfish/jersey/uri/PathPattern$RightHandPath.capturingZeroOrMoreSegments:Lorg/glassfish/jersey/uri/PathPattern$RightHandPath;
       4: invokestatic  #20                 // Method postfixWithCapturingGroup:(Ljava/lang/String;Lorg/glassfish/jersey/uri/PathPattern$RightHandPath;)Ljava/lang/String;
       7: areturn

  private static java.lang.String postfixWithCapturingGroup(java.lang.String, org.glassfish.jersey.uri.PathPattern$RightHandPath);
    Code:
       0: aload_0
       1: ldc           #22                 // String /
       3: invokevirtual #23                 // Method java/lang/String.endsWith:(Ljava/lang/String;)Z
       6: ifeq          21
       9: aload_0
      10: iconst_0
      11: aload_0
      12: invokevirtual #24                 // Method java/lang/String.length:()I
      15: iconst_1
      16: isub
      17: invokevirtual #25                 // Method java/lang/String.substring:(II)Ljava/lang/String;
      20: astore_0
      21: new           #26                 // class java/lang/StringBuilder
      24: dup
      25: invokespecial #27                 // Method java/lang/StringBuilder."<init>":()V
      28: aload_0
      29: invokevirtual #28                 // Method java/lang/StringBuilder.append:(Ljava/lang/String;)Ljava/lang/StringBuilder;
      32: aload_1
      33: invokestatic  #29                 // Method org/glassfish/jersey/uri/PathPattern$RightHandPath.access$100:(Lorg/glassfish/jersey/uri/PathPattern$RightHandPath;)Ljava/lang/String;
      36: invokevirtual #28                 // Method java/lang/StringBuilder.append:(Ljava/lang/String;)Ljava/lang/StringBuilder;
      39: invokevirtual #30                 // Method java/lang/StringBuilder.toString:()Ljava/lang/String;
      42: areturn

  private static int[] addIndexForRightHandPathCapturingGroup(int, int[]);
    Code:
       0: aload_1
       1: arraylength
       2: ifne          7
       5: aload_1
       6: areturn
       7: aload_1
       8: arraylength
       9: iconst_1
      10: iadd
      11: newarray       int
      13: astore_2
      14: aload_1
      15: iconst_0
      16: aload_2
      17: iconst_0
      18: aload_1
      19: arraylength
      20: invokestatic  #31                 // Method java/lang/System.arraycopy:(Ljava/lang/Object;ILjava/lang/Object;II)V
      23: aload_2
      24: aload_1
      25: arraylength
      26: iload_0
      27: iconst_1
      28: iadd
      29: iastore
      30: aload_2
      31: areturn

  static org.glassfish.jersey.uri.UriTemplate access$000(org.glassfish.jersey.uri.PathPattern);
    Code:
       0: aload_0
       1: getfield      #1                  // Field template:Lorg/glassfish/jersey/uri/UriTemplate;
       4: areturn

  static {};
    Code:
       0: new           #2                  // class org/glassfish/jersey/uri/PathPattern
       3: dup
       4: invokespecial #32                 // Method "<init>":()V
       7: putstatic     #33                 // Field EMPTY_PATTERN:Lorg/glassfish/jersey/uri/PathPattern;
      10: new           #2                  // class org/glassfish/jersey/uri/PathPattern
      13: dup
      14: ldc           #34                 // String
      16: getstatic     #5                  // Field org/glassfish/jersey/uri/PathPattern$RightHandPath.capturingZeroSegments:Lorg/glassfish/jersey/uri/PathPattern$RightHandPath;
      19: invokespecial #6                  // Method "<init>":(Ljava/lang/String;Lorg/glassfish/jersey/uri/PathPattern$RightHandPath;)V
      22: putstatic     #35                 // Field END_OF_PATH_PATTERN:Lorg/glassfish/jersey/uri/PathPattern;
      25: new           #2                  // class org/glassfish/jersey/uri/PathPattern
      28: dup
      29: ldc           #34                 // String
      31: getstatic     #21                 // Field org/glassfish/jersey/uri/PathPattern$RightHandPath.capturingZeroOrMoreSegments:Lorg/glassfish/jersey/uri/PathPattern$RightHandPath;
      34: invokespecial #6                  // Method "<init>":(Ljava/lang/String;Lorg/glassfish/jersey/uri/PathPattern$RightHandPath;)V
      37: putstatic     #36                 // Field OPEN_ROOT_PATH_PATTERN:Lorg/glassfish/jersey/uri/PathPattern;
      40: new           #37                 // class org/glassfish/jersey/uri/PathPattern$1
      43: dup
      44: invokespecial #38                 // Method org/glassfish/jersey/uri/PathPattern$1."<init>":()V
      47: putstatic     #39                 // Field COMPARATOR:Ljava/util/Comparator;
      50: return
}
