Compiled from "RFC2109Spec.java"
public class org.elasticsearch.hadoop.thirdparty.apache.commons.httpclient.cookie.RFC2109Spec extends org.elasticsearch.hadoop.thirdparty.apache.commons.httpclient.cookie.CookieSpecBase {
  private final org.elasticsearch.hadoop.thirdparty.apache.commons.httpclient.util.ParameterFormatter formatter;

  public org.elasticsearch.hadoop.thirdparty.apache.commons.httpclient.cookie.RFC2109Spec();
    Code:
       0: aload_0
       1: invokespecial #11                 // Method org/elasticsearch/hadoop/thirdparty/apache/commons/httpclient/cookie/CookieSpecBase."<init>":()V
       4: aload_0
       5: new           #13                 // class org/elasticsearch/hadoop/thirdparty/apache/commons/httpclient/util/ParameterFormatter
       8: dup
       9: invokespecial #14                 // Method org/elasticsearch/hadoop/thirdparty/apache/commons/httpclient/util/ParameterFormatter."<init>":()V
      12: putfield      #16                 // Field formatter:Lorg/elasticsearch/hadoop/thirdparty/apache/commons/httpclient/util/ParameterFormatter;
      15: aload_0
      16: getfield      #16                 // Field formatter:Lorg/elasticsearch/hadoop/thirdparty/apache/commons/httpclient/util/ParameterFormatter;
      19: iconst_1
      20: invokevirtual #20                 // Method org/elasticsearch/hadoop/thirdparty/apache/commons/httpclient/util/ParameterFormatter.setAlwaysUseQuotes:(Z)V
      23: return

  public void parseAttribute(org.elasticsearch.hadoop.thirdparty.apache.commons.httpclient.NameValuePair, org.elasticsearch.hadoop.thirdparty.apache.commons.httpclient.Cookie) throws org.elasticsearch.hadoop.thirdparty.apache.commons.httpclient.cookie.MalformedCookieException;
    Code:
       0: aload_1
       1: ifnonnull     14
       4: new           #30                 // class java/lang/IllegalArgumentException
       7: dup
       8: ldc           #32                 // String Attribute may not be null.
      10: invokespecial #35                 // Method java/lang/IllegalArgumentException."<init>":(Ljava/lang/String;)V
      13: athrow
      14: aload_2
      15: ifnonnull     28
      18: new           #30                 // class java/lang/IllegalArgumentException
      21: dup
      22: ldc           #37                 // String Cookie may not be null.
      24: invokespecial #35                 // Method java/lang/IllegalArgumentException."<init>":(Ljava/lang/String;)V
      27: athrow
      28: aload_1
      29: invokevirtual #43                 // Method org/elasticsearch/hadoop/thirdparty/apache/commons/httpclient/NameValuePair.getName:()Ljava/lang/String;
      32: invokevirtual #48                 // Method java/lang/String.toLowerCase:()Ljava/lang/String;
      35: astore_3
      36: aload_1
      37: invokevirtual #51                 // Method org/elasticsearch/hadoop/thirdparty/apache/commons/httpclient/NameValuePair.getValue:()Ljava/lang/String;
      40: astore        4
      42: aload_3
      43: ldc           #53                 // String path
      45: invokevirtual #57                 // Method java/lang/String.equals:(Ljava/lang/Object;)Z
      48: ifeq          103
      51: aload         4
      53: ifnonnull     66
      56: new           #26                 // class org/elasticsearch/hadoop/thirdparty/apache/commons/httpclient/cookie/MalformedCookieException
      59: dup
      60: ldc           #59                 // String Missing value for path attribute
      62: invokespecial #60                 // Method org/elasticsearch/hadoop/thirdparty/apache/commons/httpclient/cookie/MalformedCookieException."<init>":(Ljava/lang/String;)V
      65: athrow
      66: aload         4
      68: invokevirtual #63                 // Method java/lang/String.trim:()Ljava/lang/String;
      71: ldc           #65                 // String
      73: invokevirtual #57                 // Method java/lang/String.equals:(Ljava/lang/Object;)Z
      76: ifeq          89
      79: new           #26                 // class org/elasticsearch/hadoop/thirdparty/apache/commons/httpclient/cookie/MalformedCookieException
      82: dup
      83: ldc           #67                 // String Blank value for path attribute
      85: invokespecial #60                 // Method org/elasticsearch/hadoop/thirdparty/apache/commons/httpclient/cookie/MalformedCookieException."<init>":(Ljava/lang/String;)V
      88: athrow
      89: aload_2
      90: aload         4
      92: invokevirtual #72                 // Method org/elasticsearch/hadoop/thirdparty/apache/commons/httpclient/Cookie.setPath:(Ljava/lang/String;)V
      95: aload_2
      96: iconst_1
      97: invokevirtual #75                 // Method org/elasticsearch/hadoop/thirdparty/apache/commons/httpclient/Cookie.setPathAttributeSpecified:(Z)V
     100: goto          181
     103: aload_3
     104: ldc           #77                 // String version
     106: invokevirtual #57                 // Method java/lang/String.equals:(Ljava/lang/Object;)Z
     109: ifeq          175
     112: aload         4
     114: ifnonnull     127
     117: new           #26                 // class org/elasticsearch/hadoop/thirdparty/apache/commons/httpclient/cookie/MalformedCookieException
     120: dup
     121: ldc           #79                 // String Missing value for version attribute
     123: invokespecial #60                 // Method org/elasticsearch/hadoop/thirdparty/apache/commons/httpclient/cookie/MalformedCookieException."<init>":(Ljava/lang/String;)V
     126: athrow
     127: aload_2
     128: aload         4
     130: invokestatic  #85                 // Method java/lang/Integer.parseInt:(Ljava/lang/String;)I
     133: invokevirtual #89                 // Method org/elasticsearch/hadoop/thirdparty/apache/commons/httpclient/Cookie.setVersion:(I)V
     136: goto          172
     139: astore        5
     141: new           #26                 // class org/elasticsearch/hadoop/thirdparty/apache/commons/httpclient/cookie/MalformedCookieException
     144: dup
     145: new           #91                 // class java/lang/StringBuffer
     148: dup
     149: invokespecial #92                 // Method java/lang/StringBuffer."<init>":()V
     152: ldc           #94                 // String Invalid version:
     154: invokevirtual #98                 // Method java/lang/StringBuffer.append:(Ljava/lang/String;)Ljava/lang/StringBuffer;
     157: aload         5
     159: invokevirtual #103                // Method java/lang/Throwable.getMessage:()Ljava/lang/String;
     162: invokevirtual #98                 // Method java/lang/StringBuffer.append:(Ljava/lang/String;)Ljava/lang/StringBuffer;
     165: invokevirtual #106                // Method java/lang/StringBuffer.toString:()Ljava/lang/String;
     168: invokespecial #60                 // Method org/elasticsearch/hadoop/thirdparty/apache/commons/httpclient/cookie/MalformedCookieException."<init>":(Ljava/lang/String;)V
     171: athrow
     172: goto          181
     175: aload_0
     176: aload_1
     177: aload_2
     178: invokespecial #108                // Method org/elasticsearch/hadoop/thirdparty/apache/commons/httpclient/cookie/CookieSpecBase.parseAttribute:(Lorg/elasticsearch/hadoop/thirdparty/apache/commons/httpclient/NameValuePair;Lorg/elasticsearch/hadoop/thirdparty/apache/commons/httpclient/Cookie;)V
     181: return
    Exception table:
       from    to  target type
         127   136   139   Class java/lang/NumberFormatException

  public void validate(java.lang.String, int, java.lang.String, boolean, org.elasticsearch.hadoop.thirdparty.apache.commons.httpclient.Cookie) throws org.elasticsearch.hadoop.thirdparty.apache.commons.httpclient.cookie.MalformedCookieException;
    Code:
       0: getstatic     #123                // Field org/elasticsearch/hadoop/thirdparty/apache/commons/httpclient/cookie/CookieSpecBase.LOG:Lorg/apache/commons/logging/Log;
       3: ldc           #125                // String enter RFC2109Spec.validate(String, int, String, boolean, Cookie)
       5: invokeinterface #131,  2          // InterfaceMethod org/apache/commons/logging/Log.trace:(Ljava/lang/Object;)V
      10: aload_0
      11: aload_1
      12: iload_2
      13: aload_3
      14: iload         4
      16: aload         5
      18: invokespecial #133                // Method org/elasticsearch/hadoop/thirdparty/apache/commons/httpclient/cookie/CookieSpecBase.validate:(Ljava/lang/String;ILjava/lang/String;ZLorg/elasticsearch/hadoop/thirdparty/apache/commons/httpclient/Cookie;)V
      21: aload         5
      23: invokevirtual #43                 // Method org/elasticsearch/hadoop/thirdparty/apache/commons/httpclient/NameValuePair.getName:()Ljava/lang/String;
      26: bipush        32
      28: invokevirtual #137                // Method java/lang/String.indexOf:(I)I
      31: iconst_m1
      32: if_icmpeq     45
      35: new           #26                 // class org/elasticsearch/hadoop/thirdparty/apache/commons/httpclient/cookie/MalformedCookieException
      38: dup
      39: ldc           #139                // String Cookie name may not contain blanks
      41: invokespecial #60                 // Method org/elasticsearch/hadoop/thirdparty/apache/commons/httpclient/cookie/MalformedCookieException."<init>":(Ljava/lang/String;)V
      44: athrow
      45: aload         5
      47: invokevirtual #43                 // Method org/elasticsearch/hadoop/thirdparty/apache/commons/httpclient/NameValuePair.getName:()Ljava/lang/String;
      50: ldc           #141                // String $
      52: invokevirtual #145                // Method java/lang/String.startsWith:(Ljava/lang/String;)Z
      55: ifeq          68
      58: new           #26                 // class org/elasticsearch/hadoop/thirdparty/apache/commons/httpclient/cookie/MalformedCookieException
      61: dup
      62: ldc           #147                // String Cookie name may not start with $
      64: invokespecial #60                 // Method org/elasticsearch/hadoop/thirdparty/apache/commons/httpclient/cookie/MalformedCookieException."<init>":(Ljava/lang/String;)V
      67: athrow
      68: aload         5
      70: invokevirtual #151                // Method org/elasticsearch/hadoop/thirdparty/apache/commons/httpclient/Cookie.isDomainAttributeSpecified:()Z
      73: ifeq          335
      76: aload         5
      78: invokevirtual #154                // Method org/elasticsearch/hadoop/thirdparty/apache/commons/httpclient/Cookie.getDomain:()Ljava/lang/String;
      81: aload_1
      82: invokevirtual #57                 // Method java/lang/String.equals:(Ljava/lang/Object;)Z
      85: ifne          335
      88: aload         5
      90: invokevirtual #154                // Method org/elasticsearch/hadoop/thirdparty/apache/commons/httpclient/Cookie.getDomain:()Ljava/lang/String;
      93: ldc           #156                // String .
      95: invokevirtual #145                // Method java/lang/String.startsWith:(Ljava/lang/String;)Z
      98: ifne          137
     101: new           #26                 // class org/elasticsearch/hadoop/thirdparty/apache/commons/httpclient/cookie/MalformedCookieException
     104: dup
     105: new           #91                 // class java/lang/StringBuffer
     108: dup
     109: invokespecial #92                 // Method java/lang/StringBuffer."<init>":()V
     112: ldc           #158                // String Domain attribute \"
     114: invokevirtual #98                 // Method java/lang/StringBuffer.append:(Ljava/lang/String;)Ljava/lang/StringBuffer;
     117: aload         5
     119: invokevirtual #154                // Method org/elasticsearch/hadoop/thirdparty/apache/commons/httpclient/Cookie.getDomain:()Ljava/lang/String;
     122: invokevirtual #98                 // Method java/lang/StringBuffer.append:(Ljava/lang/String;)Ljava/lang/StringBuffer;
     125: ldc           #160                // String \" violates RFC 2109: domain must start with a dot
     127: invokevirtual #98                 // Method java/lang/StringBuffer.append:(Ljava/lang/String;)Ljava/lang/StringBuffer;
     130: invokevirtual #106                // Method java/lang/StringBuffer.toString:()Ljava/lang/String;
     133: invokespecial #60                 // Method org/elasticsearch/hadoop/thirdparty/apache/commons/httpclient/cookie/MalformedCookieException."<init>":(Ljava/lang/String;)V
     136: athrow
     137: aload         5
     139: invokevirtual #154                // Method org/elasticsearch/hadoop/thirdparty/apache/commons/httpclient/Cookie.getDomain:()Ljava/lang/String;
     142: bipush        46
     144: iconst_1
     145: invokevirtual #163                // Method java/lang/String.indexOf:(II)I
     148: istore        6
     150: iload         6
     152: iflt          170
     155: iload         6
     157: aload         5
     159: invokevirtual #154                // Method org/elasticsearch/hadoop/thirdparty/apache/commons/httpclient/Cookie.getDomain:()Ljava/lang/String;
     162: invokevirtual #167                // Method java/lang/String.length:()I
     165: iconst_1
     166: isub
     167: if_icmpne     206
     170: new           #26                 // class org/elasticsearch/hadoop/thirdparty/apache/commons/httpclient/cookie/MalformedCookieException
     173: dup
     174: new           #91                 // class java/lang/StringBuffer
     177: dup
     178: invokespecial #92                 // Method java/lang/StringBuffer."<init>":()V
     181: ldc           #158                // String Domain attribute \"
     183: invokevirtual #98                 // Method java/lang/StringBuffer.append:(Ljava/lang/String;)Ljava/lang/StringBuffer;
     186: aload         5
     188: invokevirtual #154                // Method org/elasticsearch/hadoop/thirdparty/apache/commons/httpclient/Cookie.getDomain:()Ljava/lang/String;
     191: invokevirtual #98                 // Method java/lang/StringBuffer.append:(Ljava/lang/String;)Ljava/lang/StringBuffer;
     194: ldc           #169                // String \" violates RFC 2109: domain must contain an embedded dot
     196: invokevirtual #98                 // Method java/lang/StringBuffer.append:(Ljava/lang/String;)Ljava/lang/StringBuffer;
     199: invokevirtual #106                // Method java/lang/StringBuffer.toString:()Ljava/lang/String;
     202: invokespecial #60                 // Method org/elasticsearch/hadoop/thirdparty/apache/commons/httpclient/cookie/MalformedCookieException."<init>":(Ljava/lang/String;)V
     205: athrow
     206: aload_1
     207: invokevirtual #48                 // Method java/lang/String.toLowerCase:()Ljava/lang/String;
     210: astore_1
     211: aload_1
     212: aload         5
     214: invokevirtual #154                // Method org/elasticsearch/hadoop/thirdparty/apache/commons/httpclient/Cookie.getDomain:()Ljava/lang/String;
     217: invokevirtual #172                // Method java/lang/String.endsWith:(Ljava/lang/String;)Z
     220: ifne          268
     223: new           #26                 // class org/elasticsearch/hadoop/thirdparty/apache/commons/httpclient/cookie/MalformedCookieException
     226: dup
     227: new           #91                 // class java/lang/StringBuffer
     230: dup
     231: invokespecial #92                 // Method java/lang/StringBuffer."<init>":()V
     234: ldc           #174                // String Illegal domain attribute \"
     236: invokevirtual #98                 // Method java/lang/StringBuffer.append:(Ljava/lang/String;)Ljava/lang/StringBuffer;
     239: aload         5
     241: invokevirtual #154                // Method org/elasticsearch/hadoop/thirdparty/apache/commons/httpclient/Cookie.getDomain:()Ljava/lang/String;
     244: invokevirtual #98                 // Method java/lang/StringBuffer.append:(Ljava/lang/String;)Ljava/lang/StringBuffer;
     247: ldc           #176                // String \". Domain of origin: \"
     249: invokevirtual #98                 // Method java/lang/StringBuffer.append:(Ljava/lang/String;)Ljava/lang/StringBuffer;
     252: aload_1
     253: invokevirtual #98                 // Method java/lang/StringBuffer.append:(Ljava/lang/String;)Ljava/lang/StringBuffer;
     256: ldc           #178                // String \"
     258: invokevirtual #98                 // Method java/lang/StringBuffer.append:(Ljava/lang/String;)Ljava/lang/StringBuffer;
     261: invokevirtual #106                // Method java/lang/StringBuffer.toString:()Ljava/lang/String;
     264: invokespecial #60                 // Method org/elasticsearch/hadoop/thirdparty/apache/commons/httpclient/cookie/MalformedCookieException."<init>":(Ljava/lang/String;)V
     267: athrow
     268: aload_1
     269: iconst_0
     270: aload_1
     271: invokevirtual #167                // Method java/lang/String.length:()I
     274: aload         5
     276: invokevirtual #154                // Method org/elasticsearch/hadoop/thirdparty/apache/commons/httpclient/Cookie.getDomain:()Ljava/lang/String;
     279: invokevirtual #167                // Method java/lang/String.length:()I
     282: isub
     283: invokevirtual #182                // Method java/lang/String.substring:(II)Ljava/lang/String;
     286: astore        7
     288: aload         7
     290: bipush        46
     292: invokevirtual #137                // Method java/lang/String.indexOf:(I)I
     295: iconst_m1
     296: if_icmpeq     335
     299: new           #26                 // class org/elasticsearch/hadoop/thirdparty/apache/commons/httpclient/cookie/MalformedCookieException
     302: dup
     303: new           #91                 // class java/lang/StringBuffer
     306: dup
     307: invokespecial #92                 // Method java/lang/StringBuffer."<init>":()V
     310: ldc           #158                // String Domain attribute \"
     312: invokevirtual #98                 // Method java/lang/StringBuffer.append:(Ljava/lang/String;)Ljava/lang/StringBuffer;
     315: aload         5
     317: invokevirtual #154                // Method org/elasticsearch/hadoop/thirdparty/apache/commons/httpclient/Cookie.getDomain:()Ljava/lang/String;
     320: invokevirtual #98                 // Method java/lang/StringBuffer.append:(Ljava/lang/String;)Ljava/lang/StringBuffer;
     323: ldc           #184                // String \" violates RFC 2109: host minus domain may not contain any dots
     325: invokevirtual #98                 // Method java/lang/StringBuffer.append:(Ljava/lang/String;)Ljava/lang/StringBuffer;
     328: invokevirtual #106                // Method java/lang/StringBuffer.toString:()Ljava/lang/String;
     331: invokespecial #60                 // Method org/elasticsearch/hadoop/thirdparty/apache/commons/httpclient/cookie/MalformedCookieException."<init>":(Ljava/lang/String;)V
     334: athrow
     335: return

  public boolean domainMatch(java.lang.String, java.lang.String);
    Code:
       0: aload_1
       1: aload_2
       2: invokevirtual #57                 // Method java/lang/String.equals:(Ljava/lang/Object;)Z
       5: ifne          25
       8: aload_2
       9: ldc           #156                // String .
      11: invokevirtual #145                // Method java/lang/String.startsWith:(Ljava/lang/String;)Z
      14: ifeq          29
      17: aload_1
      18: aload_2
      19: invokevirtual #172                // Method java/lang/String.endsWith:(Ljava/lang/String;)Z
      22: ifeq          29
      25: iconst_1
      26: goto          30
      29: iconst_0
      30: istore_3
      31: iload_3
      32: ireturn

  private void formatParam(java.lang.StringBuffer, org.elasticsearch.hadoop.thirdparty.apache.commons.httpclient.NameValuePair, int);
    Code:
       0: iload_3
       1: iconst_1
       2: if_icmpge     40
       5: aload_1
       6: aload_2
       7: invokevirtual #43                 // Method org/elasticsearch/hadoop/thirdparty/apache/commons/httpclient/NameValuePair.getName:()Ljava/lang/String;
      10: invokevirtual #98                 // Method java/lang/StringBuffer.append:(Ljava/lang/String;)Ljava/lang/StringBuffer;
      13: pop
      14: aload_1
      15: ldc           #199                // String =
      17: invokevirtual #98                 // Method java/lang/StringBuffer.append:(Ljava/lang/String;)Ljava/lang/StringBuffer;
      20: pop
      21: aload_2
      22: invokevirtual #51                 // Method org/elasticsearch/hadoop/thirdparty/apache/commons/httpclient/NameValuePair.getValue:()Ljava/lang/String;
      25: ifnull        49
      28: aload_1
      29: aload_2
      30: invokevirtual #51                 // Method org/elasticsearch/hadoop/thirdparty/apache/commons/httpclient/NameValuePair.getValue:()Ljava/lang/String;
      33: invokevirtual #98                 // Method java/lang/StringBuffer.append:(Ljava/lang/String;)Ljava/lang/StringBuffer;
      36: pop
      37: goto          49
      40: aload_0
      41: getfield      #16                 // Field formatter:Lorg/elasticsearch/hadoop/thirdparty/apache/commons/httpclient/util/ParameterFormatter;
      44: aload_1
      45: aload_2
      46: invokevirtual #203                // Method org/elasticsearch/hadoop/thirdparty/apache/commons/httpclient/util/ParameterFormatter.format:(Ljava/lang/StringBuffer;Lorg/elasticsearch/hadoop/thirdparty/apache/commons/httpclient/NameValuePair;)V
      49: return

  private void formatCookieAsVer(java.lang.StringBuffer, org.elasticsearch.hadoop.thirdparty.apache.commons.httpclient.Cookie, int);
    Code:
       0: aload_2
       1: invokevirtual #51                 // Method org/elasticsearch/hadoop/thirdparty/apache/commons/httpclient/NameValuePair.getValue:()Ljava/lang/String;
       4: astore        4
       6: aload         4
       8: ifnonnull     15
      11: ldc           #65                 // String
      13: astore        4
      15: aload_0
      16: aload_1
      17: new           #39                 // class org/elasticsearch/hadoop/thirdparty/apache/commons/httpclient/NameValuePair
      20: dup
      21: aload_2
      22: invokevirtual #43                 // Method org/elasticsearch/hadoop/thirdparty/apache/commons/httpclient/NameValuePair.getName:()Ljava/lang/String;
      25: aload         4
      27: invokespecial #211                // Method org/elasticsearch/hadoop/thirdparty/apache/commons/httpclient/NameValuePair."<init>":(Ljava/lang/String;Ljava/lang/String;)V
      30: iload_3
      31: invokespecial #213                // Method formatParam:(Ljava/lang/StringBuffer;Lorg/elasticsearch/hadoop/thirdparty/apache/commons/httpclient/NameValuePair;I)V
      34: aload_2
      35: invokevirtual #216                // Method org/elasticsearch/hadoop/thirdparty/apache/commons/httpclient/Cookie.getPath:()Ljava/lang/String;
      38: ifnull        74
      41: aload_2
      42: invokevirtual #219                // Method org/elasticsearch/hadoop/thirdparty/apache/commons/httpclient/Cookie.isPathAttributeSpecified:()Z
      45: ifeq          74
      48: aload_1
      49: ldc           #221                // String ;
      51: invokevirtual #98                 // Method java/lang/StringBuffer.append:(Ljava/lang/String;)Ljava/lang/StringBuffer;
      54: pop
      55: aload_0
      56: aload_1
      57: new           #39                 // class org/elasticsearch/hadoop/thirdparty/apache/commons/httpclient/NameValuePair
      60: dup
      61: ldc           #223                // String $Path
      63: aload_2
      64: invokevirtual #216                // Method org/elasticsearch/hadoop/thirdparty/apache/commons/httpclient/Cookie.getPath:()Ljava/lang/String;
      67: invokespecial #211                // Method org/elasticsearch/hadoop/thirdparty/apache/commons/httpclient/NameValuePair."<init>":(Ljava/lang/String;Ljava/lang/String;)V
      70: iload_3
      71: invokespecial #213                // Method formatParam:(Ljava/lang/StringBuffer;Lorg/elasticsearch/hadoop/thirdparty/apache/commons/httpclient/NameValuePair;I)V
      74: aload_2
      75: invokevirtual #154                // Method org/elasticsearch/hadoop/thirdparty/apache/commons/httpclient/Cookie.getDomain:()Ljava/lang/String;
      78: ifnull        114
      81: aload_2
      82: invokevirtual #151                // Method org/elasticsearch/hadoop/thirdparty/apache/commons/httpclient/Cookie.isDomainAttributeSpecified:()Z
      85: ifeq          114
      88: aload_1
      89: ldc           #221                // String ;
      91: invokevirtual #98                 // Method java/lang/StringBuffer.append:(Ljava/lang/String;)Ljava/lang/StringBuffer;
      94: pop
      95: aload_0
      96: aload_1
      97: new           #39                 // class org/elasticsearch/hadoop/thirdparty/apache/commons/httpclient/NameValuePair
     100: dup
     101: ldc           #225                // String $Domain
     103: aload_2
     104: invokevirtual #154                // Method org/elasticsearch/hadoop/thirdparty/apache/commons/httpclient/Cookie.getDomain:()Ljava/lang/String;
     107: invokespecial #211                // Method org/elasticsearch/hadoop/thirdparty/apache/commons/httpclient/NameValuePair."<init>":(Ljava/lang/String;Ljava/lang/String;)V
     110: iload_3
     111: invokespecial #213                // Method formatParam:(Ljava/lang/StringBuffer;Lorg/elasticsearch/hadoop/thirdparty/apache/commons/httpclient/NameValuePair;I)V
     114: return

  public java.lang.String formatCookie(org.elasticsearch.hadoop.thirdparty.apache.commons.httpclient.Cookie);
    Code:
       0: getstatic     #123                // Field org/elasticsearch/hadoop/thirdparty/apache/commons/httpclient/cookie/CookieSpecBase.LOG:Lorg/apache/commons/logging/Log;
       3: ldc           #230                // String enter RFC2109Spec.formatCookie(Cookie)
       5: invokeinterface #131,  2          // InterfaceMethod org/apache/commons/logging/Log.trace:(Ljava/lang/Object;)V
      10: aload_1
      11: ifnonnull     24
      14: new           #30                 // class java/lang/IllegalArgumentException
      17: dup
      18: ldc           #232                // String Cookie may not be null
      20: invokespecial #35                 // Method java/lang/IllegalArgumentException."<init>":(Ljava/lang/String;)V
      23: athrow
      24: aload_1
      25: invokevirtual #235                // Method org/elasticsearch/hadoop/thirdparty/apache/commons/httpclient/Cookie.getVersion:()I
      28: istore_2
      29: new           #91                 // class java/lang/StringBuffer
      32: dup
      33: invokespecial #92                 // Method java/lang/StringBuffer."<init>":()V
      36: astore_3
      37: aload_0
      38: aload_3
      39: new           #39                 // class org/elasticsearch/hadoop/thirdparty/apache/commons/httpclient/NameValuePair
      42: dup
      43: ldc           #237                // String $Version
      45: iload_2
      46: invokestatic  #240                // Method java/lang/Integer.toString:(I)Ljava/lang/String;
      49: invokespecial #211                // Method org/elasticsearch/hadoop/thirdparty/apache/commons/httpclient/NameValuePair."<init>":(Ljava/lang/String;Ljava/lang/String;)V
      52: iload_2
      53: invokespecial #213                // Method formatParam:(Ljava/lang/StringBuffer;Lorg/elasticsearch/hadoop/thirdparty/apache/commons/httpclient/NameValuePair;I)V
      56: aload_3
      57: ldc           #221                // String ;
      59: invokevirtual #98                 // Method java/lang/StringBuffer.append:(Ljava/lang/String;)Ljava/lang/StringBuffer;
      62: pop
      63: aload_0
      64: aload_3
      65: aload_1
      66: iload_2
      67: invokespecial #242                // Method formatCookieAsVer:(Ljava/lang/StringBuffer;Lorg/elasticsearch/hadoop/thirdparty/apache/commons/httpclient/Cookie;I)V
      70: aload_3
      71: invokevirtual #106                // Method java/lang/StringBuffer.toString:()Ljava/lang/String;
      74: areturn

  public java.lang.String formatCookies(org.elasticsearch.hadoop.thirdparty.apache.commons.httpclient.Cookie[]);
    Code:
       0: getstatic     #123                // Field org/elasticsearch/hadoop/thirdparty/apache/commons/httpclient/cookie/CookieSpecBase.LOG:Lorg/apache/commons/logging/Log;
       3: ldc           #246                // String enter RFC2109Spec.formatCookieHeader(Cookie[])
       5: invokeinterface #131,  2          // InterfaceMethod org/apache/commons/logging/Log.trace:(Ljava/lang/Object;)V
      10: ldc           #247                // int 2147483647
      12: istore_2
      13: iconst_0
      14: istore_3
      15: goto          41
      18: aload_1
      19: iload_3
      20: aaload
      21: astore        4
      23: aload         4
      25: invokevirtual #235                // Method org/elasticsearch/hadoop/thirdparty/apache/commons/httpclient/Cookie.getVersion:()I
      28: iload_2
      29: if_icmpge     38
      32: aload         4
      34: invokevirtual #235                // Method org/elasticsearch/hadoop/thirdparty/apache/commons/httpclient/Cookie.getVersion:()I
      37: istore_2
      38: iinc          3, 1
      41: iload_3
      42: aload_1
      43: arraylength
      44: if_icmplt     18
      47: new           #91                 // class java/lang/StringBuffer
      50: dup
      51: invokespecial #92                 // Method java/lang/StringBuffer."<init>":()V
      54: astore        4
      56: aload_0
      57: aload         4
      59: new           #39                 // class org/elasticsearch/hadoop/thirdparty/apache/commons/httpclient/NameValuePair
      62: dup
      63: ldc           #237                // String $Version
      65: iload_2
      66: invokestatic  #240                // Method java/lang/Integer.toString:(I)Ljava/lang/String;
      69: invokespecial #211                // Method org/elasticsearch/hadoop/thirdparty/apache/commons/httpclient/NameValuePair."<init>":(Ljava/lang/String;Ljava/lang/String;)V
      72: iload_2
      73: invokespecial #213                // Method formatParam:(Ljava/lang/StringBuffer;Lorg/elasticsearch/hadoop/thirdparty/apache/commons/httpclient/NameValuePair;I)V
      76: iconst_0
      77: istore        5
      79: goto          104
      82: aload         4
      84: ldc           #221                // String ;
      86: invokevirtual #98                 // Method java/lang/StringBuffer.append:(Ljava/lang/String;)Ljava/lang/StringBuffer;
      89: pop
      90: aload_0
      91: aload         4
      93: aload_1
      94: iload         5
      96: aaload
      97: iload_2
      98: invokespecial #242                // Method formatCookieAsVer:(Ljava/lang/StringBuffer;Lorg/elasticsearch/hadoop/thirdparty/apache/commons/httpclient/Cookie;I)V
     101: iinc          5, 1
     104: iload         5
     106: aload_1
     107: arraylength
     108: if_icmplt     82
     111: aload         4
     113: invokevirtual #106                // Method java/lang/StringBuffer.toString:()Ljava/lang/String;
     116: areturn
}
