Compiled from "MessageReactionListRequest.kt"
public final class love.forte.simbot.kaiheila.api.message.MessageReactionListRequestKt {
  public static final boolean isNormal(love.forte.simbot.kaiheila.api.message.MessageReactor);
    Code:
       0: aload_0
       1: ldc           #10                 // String <this>
       3: invokestatic  #16                 // Method kotlin/jvm/internal/Intrinsics.checkNotNullParameter:(Ljava/lang/Object;Ljava/lang/String;)V
       6: aload_0
       7: invokevirtual #22                 // Method love/forte/simbot/kaiheila/api/message/MessageReactor.getStatus:()I
      10: ifne          17
      13: iconst_1
      14: goto          18
      17: iconst_0
      18: ireturn

  public static final boolean isBan(love.forte.simbot.kaiheila.api.message.MessageReactor);
    Code:
       0: aload_0
       1: ldc           #10                 // String <this>
       3: invokestatic  #16                 // Method kotlin/jvm/internal/Intrinsics.checkNotNullParameter:(Ljava/lang/Object;Ljava/lang/String;)V
       6: aload_0
       7: invokevirtual #22                 // Method love/forte/simbot/kaiheila/api/message/MessageReactor.getStatus:()I
      10: bipush        10
      12: if_icmpne     19
      15: iconst_1
      16: goto          20
      19: iconst_0
      20: ireturn
}
