Compiled from "ThrowableProxy.java"
public class org.apache.logging.log4j.core.impl.ThrowableProxy implements java.io.Serializable {
  static final org.apache.logging.log4j.core.impl.ThrowableProxy[] EMPTY_ARRAY;

  private static final char EOL;

  private static final java.lang.String EOL_STR;

  private static final long serialVersionUID;

  private final org.apache.logging.log4j.core.impl.ThrowableProxy causeProxy;

  private int commonElementCount;

  private final org.apache.logging.log4j.core.impl.ExtendedStackTraceElement[] extendedStackTrace;

  private final java.lang.String localizedMessage;

  private final java.lang.String message;

  private final java.lang.String name;

  private final org.apache.logging.log4j.core.impl.ThrowableProxy[] suppressedProxies;

  private final transient java.lang.Throwable throwable;

  org.apache.logging.log4j.core.impl.ThrowableProxy();
    Code:
       0: aload_0
       1: invokespecial #1                  // Method java/lang/Object."<init>":()V
       4: aload_0
       5: aconst_null
       6: putfield      #2                  // Field throwable:Ljava/lang/Throwable;
       9: aload_0
      10: aconst_null
      11: putfield      #3                  // Field name:Ljava/lang/String;
      14: aload_0
      15: getstatic     #4                  // Field org/apache/logging/log4j/core/impl/ExtendedStackTraceElement.EMPTY_ARRAY:[Lorg/apache/logging/log4j/core/impl/ExtendedStackTraceElement;
      18: putfield      #5                  // Field extendedStackTrace:[Lorg/apache/logging/log4j/core/impl/ExtendedStackTraceElement;
      21: aload_0
      22: aconst_null
      23: putfield      #6                  // Field causeProxy:Lorg/apache/logging/log4j/core/impl/ThrowableProxy;
      26: aload_0
      27: aconst_null
      28: putfield      #7                  // Field message:Ljava/lang/String;
      31: aload_0
      32: aconst_null
      33: putfield      #8                  // Field localizedMessage:Ljava/lang/String;
      36: aload_0
      37: getstatic     #9                  // Field EMPTY_ARRAY:[Lorg/apache/logging/log4j/core/impl/ThrowableProxy;
      40: putfield      #10                 // Field suppressedProxies:[Lorg/apache/logging/log4j/core/impl/ThrowableProxy;
      43: return

  public org.apache.logging.log4j.core.impl.ThrowableProxy(java.lang.Throwable);
    Code:
       0: aload_0
       1: aload_1
       2: aconst_null
       3: invokespecial #11                 // Method "<init>":(Ljava/lang/Throwable;Ljava/util/Set;)V
       6: return

  org.apache.logging.log4j.core.impl.ThrowableProxy(java.lang.Throwable, java.util.Set<java.lang.Throwable>);
    Code:
       0: aload_0
       1: invokespecial #1                  // Method java/lang/Object."<init>":()V
       4: aload_0
       5: aload_1
       6: putfield      #2                  // Field throwable:Ljava/lang/Throwable;
       9: aload_0
      10: aload_1
      11: invokevirtual #12                 // Method java/lang/Object.getClass:()Ljava/lang/Class;
      14: invokevirtual #13                 // Method java/lang/Class.getName:()Ljava/lang/String;
      17: putfield      #3                  // Field name:Ljava/lang/String;
      20: aload_0
      21: aload_1
      22: invokevirtual #14                 // Method java/lang/Throwable.getMessage:()Ljava/lang/String;
      25: putfield      #7                  // Field message:Ljava/lang/String;
      28: aload_0
      29: aload_1
      30: invokevirtual #15                 // Method java/lang/Throwable.getLocalizedMessage:()Ljava/lang/String;
      33: putfield      #8                  // Field localizedMessage:Ljava/lang/String;
      36: new           #16                 // class java/util/HashMap
      39: dup
      40: invokespecial #17                 // Method java/util/HashMap."<init>":()V
      43: astore_3
      44: invokestatic  #18                 // Method org/apache/logging/log4j/util/StackLocatorUtil.getCurrentStackTrace:()Ljava/util/Stack;
      47: astore        4
      49: aload_0
      50: aload_0
      51: aload         4
      53: aload_3
      54: aconst_null
      55: aload_1
      56: invokevirtual #19                 // Method java/lang/Throwable.getStackTrace:()[Ljava/lang/StackTraceElement;
      59: invokestatic  #20                 // Method org/apache/logging/log4j/core/impl/ThrowableProxyHelper.toExtendedStackTrace:(Lorg/apache/logging/log4j/core/impl/ThrowableProxy;Ljava/util/Stack;Ljava/util/Map;[Ljava/lang/StackTraceElement;[Ljava/lang/StackTraceElement;)[Lorg/apache/logging/log4j/core/impl/ExtendedStackTraceElement;
      62: putfield      #5                  // Field extendedStackTrace:[Lorg/apache/logging/log4j/core/impl/ExtendedStackTraceElement;
      65: aload_1
      66: invokevirtual #21                 // Method java/lang/Throwable.getCause:()Ljava/lang/Throwable;
      69: astore        5
      71: new           #22                 // class java/util/HashSet
      74: dup
      75: iconst_1
      76: invokespecial #23                 // Method java/util/HashSet."<init>":(I)V
      79: astore        6
      81: aload_0
      82: aload         5
      84: ifnonnull     91
      87: aconst_null
      88: goto          107
      91: new           #24                 // class org/apache/logging/log4j/core/impl/ThrowableProxy
      94: dup
      95: aload_1
      96: aload         4
      98: aload_3
      99: aload         5
     101: aload_2
     102: aload         6
     104: invokespecial #25                 // Method "<init>":(Ljava/lang/Throwable;Ljava/util/Stack;Ljava/util/Map;Ljava/lang/Throwable;Ljava/util/Set;Ljava/util/Set;)V
     107: putfield      #6                  // Field causeProxy:Lorg/apache/logging/log4j/core/impl/ThrowableProxy;
     110: aload_0
     111: aload_1
     112: aload_2
     113: invokestatic  #26                 // Method org/apache/logging/log4j/core/impl/ThrowableProxyHelper.toSuppressedProxies:(Ljava/lang/Throwable;Ljava/util/Set;)[Lorg/apache/logging/log4j/core/impl/ThrowableProxy;
     116: putfield      #10                 // Field suppressedProxies:[Lorg/apache/logging/log4j/core/impl/ThrowableProxy;
     119: return

  private org.apache.logging.log4j.core.impl.ThrowableProxy(java.lang.Throwable, java.util.Stack<java.lang.Class<?>>, java.util.Map<java.lang.String, org.apache.logging.log4j.core.impl.ThrowableProxyHelper$CacheEntry>, java.lang.Throwable, java.util.Set<java.lang.Throwable>, java.util.Set<java.lang.Throwable>);
    Code:
       0: aload_0
       1: invokespecial #1                  // Method java/lang/Object."<init>":()V
       4: aload         6
       6: aload         4
       8: invokeinterface #27,  2           // InterfaceMethod java/util/Set.add:(Ljava/lang/Object;)Z
      13: pop
      14: aload_0
      15: aload         4
      17: putfield      #2                  // Field throwable:Ljava/lang/Throwable;
      20: aload_0
      21: aload         4
      23: invokevirtual #12                 // Method java/lang/Object.getClass:()Ljava/lang/Class;
      26: invokevirtual #13                 // Method java/lang/Class.getName:()Ljava/lang/String;
      29: putfield      #3                  // Field name:Ljava/lang/String;
      32: aload_0
      33: aload_0
      34: getfield      #2                  // Field throwable:Ljava/lang/Throwable;
      37: invokevirtual #14                 // Method java/lang/Throwable.getMessage:()Ljava/lang/String;
      40: putfield      #7                  // Field message:Ljava/lang/String;
      43: aload_0
      44: aload_0
      45: getfield      #2                  // Field throwable:Ljava/lang/Throwable;
      48: invokevirtual #15                 // Method java/lang/Throwable.getLocalizedMessage:()Ljava/lang/String;
      51: putfield      #8                  // Field localizedMessage:Ljava/lang/String;
      54: aload_0
      55: aload_0
      56: aload_2
      57: aload_3
      58: aload_1
      59: invokevirtual #19                 // Method java/lang/Throwable.getStackTrace:()[Ljava/lang/StackTraceElement;
      62: aload         4
      64: invokevirtual #19                 // Method java/lang/Throwable.getStackTrace:()[Ljava/lang/StackTraceElement;
      67: invokestatic  #20                 // Method org/apache/logging/log4j/core/impl/ThrowableProxyHelper.toExtendedStackTrace:(Lorg/apache/logging/log4j/core/impl/ThrowableProxy;Ljava/util/Stack;Ljava/util/Map;[Ljava/lang/StackTraceElement;[Ljava/lang/StackTraceElement;)[Lorg/apache/logging/log4j/core/impl/ExtendedStackTraceElement;
      70: putfield      #5                  // Field extendedStackTrace:[Lorg/apache/logging/log4j/core/impl/ExtendedStackTraceElement;
      73: aload         4
      75: invokevirtual #21                 // Method java/lang/Throwable.getCause:()Ljava/lang/Throwable;
      78: astore        7
      80: aload_0
      81: aload         7
      83: ifnull        98
      86: aload         6
      88: aload         7
      90: invokeinterface #28,  2           // InterfaceMethod java/util/Set.contains:(Ljava/lang/Object;)Z
      95: ifeq          102
      98: aconst_null
      99: goto          118
     102: new           #24                 // class org/apache/logging/log4j/core/impl/ThrowableProxy
     105: dup
     106: aload_1
     107: aload_2
     108: aload_3
     109: aload         7
     111: aload         5
     113: aload         6
     115: invokespecial #25                 // Method "<init>":(Ljava/lang/Throwable;Ljava/util/Stack;Ljava/util/Map;Ljava/lang/Throwable;Ljava/util/Set;Ljava/util/Set;)V
     118: putfield      #6                  // Field causeProxy:Lorg/apache/logging/log4j/core/impl/ThrowableProxy;
     121: aload_0
     122: aload         4
     124: aload         5
     126: invokestatic  #26                 // Method org/apache/logging/log4j/core/impl/ThrowableProxyHelper.toSuppressedProxies:(Ljava/lang/Throwable;Ljava/util/Set;)[Lorg/apache/logging/log4j/core/impl/ThrowableProxy;
     129: putfield      #10                 // Field suppressedProxies:[Lorg/apache/logging/log4j/core/impl/ThrowableProxy;
     132: return

  public boolean equals(java.lang.Object);
    Code:
       0: aload_0
       1: aload_1
       2: if_acmpne     7
       5: iconst_1
       6: ireturn
       7: aload_1
       8: ifnonnull     13
      11: iconst_0
      12: ireturn
      13: aload_0
      14: invokevirtual #12                 // Method java/lang/Object.getClass:()Ljava/lang/Class;
      17: aload_1
      18: invokevirtual #12                 // Method java/lang/Object.getClass:()Ljava/lang/Class;
      21: if_acmpeq     26
      24: iconst_0
      25: ireturn
      26: aload_1
      27: checkcast     #24                 // class org/apache/logging/log4j/core/impl/ThrowableProxy
      30: astore_2
      31: aload_0
      32: getfield      #6                  // Field causeProxy:Lorg/apache/logging/log4j/core/impl/ThrowableProxy;
      35: aload_2
      36: getfield      #6                  // Field causeProxy:Lorg/apache/logging/log4j/core/impl/ThrowableProxy;
      39: invokestatic  #29                 // Method java/util/Objects.equals:(Ljava/lang/Object;Ljava/lang/Object;)Z
      42: ifne          47
      45: iconst_0
      46: ireturn
      47: aload_0
      48: getfield      #30                 // Field commonElementCount:I
      51: aload_2
      52: getfield      #30                 // Field commonElementCount:I
      55: if_icmpeq     60
      58: iconst_0
      59: ireturn
      60: aload_0
      61: getfield      #3                  // Field name:Ljava/lang/String;
      64: aload_2
      65: getfield      #3                  // Field name:Ljava/lang/String;
      68: invokestatic  #29                 // Method java/util/Objects.equals:(Ljava/lang/Object;Ljava/lang/Object;)Z
      71: ifne          76
      74: iconst_0
      75: ireturn
      76: aload_0
      77: getfield      #5                  // Field extendedStackTrace:[Lorg/apache/logging/log4j/core/impl/ExtendedStackTraceElement;
      80: aload_2
      81: getfield      #5                  // Field extendedStackTrace:[Lorg/apache/logging/log4j/core/impl/ExtendedStackTraceElement;
      84: invokestatic  #31                 // Method java/util/Arrays.equals:([Ljava/lang/Object;[Ljava/lang/Object;)Z
      87: ifne          92
      90: iconst_0
      91: ireturn
      92: aload_0
      93: getfield      #10                 // Field suppressedProxies:[Lorg/apache/logging/log4j/core/impl/ThrowableProxy;
      96: aload_2
      97: getfield      #10                 // Field suppressedProxies:[Lorg/apache/logging/log4j/core/impl/ThrowableProxy;
     100: invokestatic  #31                 // Method java/util/Arrays.equals:([Ljava/lang/Object;[Ljava/lang/Object;)Z
     103: ifne          108
     106: iconst_0
     107: ireturn
     108: iconst_1
     109: ireturn

  public void formatWrapper(java.lang.StringBuilder, org.apache.logging.log4j.core.impl.ThrowableProxy, java.lang.String);
    Code:
       0: aload_0
       1: aload_1
       2: aload_2
       3: aconst_null
       4: invokestatic  #32                 // Method org/apache/logging/log4j/core/pattern/PlainTextRenderer.getInstance:()Lorg/apache/logging/log4j/core/pattern/PlainTextRenderer;
       7: aload_3
       8: invokevirtual #33                 // Method formatWrapper:(Ljava/lang/StringBuilder;Lorg/apache/logging/log4j/core/impl/ThrowableProxy;Ljava/util/List;Lorg/apache/logging/log4j/core/pattern/TextRenderer;Ljava/lang/String;)V
      11: return

  public void formatWrapper(java.lang.StringBuilder, org.apache.logging.log4j.core.impl.ThrowableProxy, java.util.List<java.lang.String>, java.lang.String);
    Code:
       0: aload_0
       1: aload_1
       2: aload_2
       3: aload_3
       4: invokestatic  #32                 // Method org/apache/logging/log4j/core/pattern/PlainTextRenderer.getInstance:()Lorg/apache/logging/log4j/core/pattern/PlainTextRenderer;
       7: aload         4
       9: invokevirtual #33                 // Method formatWrapper:(Ljava/lang/StringBuilder;Lorg/apache/logging/log4j/core/impl/ThrowableProxy;Ljava/util/List;Lorg/apache/logging/log4j/core/pattern/TextRenderer;Ljava/lang/String;)V
      12: return

  public void formatWrapper(java.lang.StringBuilder, org.apache.logging.log4j.core.impl.ThrowableProxy, java.util.List<java.lang.String>, org.apache.logging.log4j.core.pattern.TextRenderer, java.lang.String);
    Code:
       0: aload_0
       1: aload_1
       2: aload_2
       3: aload_3
       4: aload         4
       6: aload         5
       8: getstatic     #34                 // Field EOL_STR:Ljava/lang/String;
      11: invokevirtual #35                 // Method formatWrapper:(Ljava/lang/StringBuilder;Lorg/apache/logging/log4j/core/impl/ThrowableProxy;Ljava/util/List;Lorg/apache/logging/log4j/core/pattern/TextRenderer;Ljava/lang/String;Ljava/lang/String;)V
      14: return

  public void formatWrapper(java.lang.StringBuilder, org.apache.logging.log4j.core.impl.ThrowableProxy, java.util.List<java.lang.String>, org.apache.logging.log4j.core.pattern.TextRenderer, java.lang.String, java.lang.String);
    Code:
       0: aload_1
       1: aload_2
       2: aload_3
       3: aload         4
       5: aload         5
       7: aload         6
       9: invokestatic  #36                 // Method org/apache/logging/log4j/core/impl/ThrowableProxyRenderer.formatWrapper:(Ljava/lang/StringBuilder;Lorg/apache/logging/log4j/core/impl/ThrowableProxy;Ljava/util/List;Lorg/apache/logging/log4j/core/pattern/TextRenderer;Ljava/lang/String;Ljava/lang/String;)V
      12: return

  public org.apache.logging.log4j.core.impl.ThrowableProxy getCauseProxy();
    Code:
       0: aload_0
       1: getfield      #6                  // Field causeProxy:Lorg/apache/logging/log4j/core/impl/ThrowableProxy;
       4: areturn

  public java.lang.String getCauseStackTraceAsString(java.lang.String);
    Code:
       0: aload_0
       1: aconst_null
       2: invokestatic  #32                 // Method org/apache/logging/log4j/core/pattern/PlainTextRenderer.getInstance:()Lorg/apache/logging/log4j/core/pattern/PlainTextRenderer;
       5: aload_1
       6: getstatic     #34                 // Field EOL_STR:Ljava/lang/String;
       9: invokevirtual #37                 // Method getCauseStackTraceAsString:(Ljava/util/List;Lorg/apache/logging/log4j/core/pattern/TextRenderer;Ljava/lang/String;Ljava/lang/String;)Ljava/lang/String;
      12: areturn

  public java.lang.String getCauseStackTraceAsString(java.util.List<java.lang.String>, java.lang.String);
    Code:
       0: aload_0
       1: aload_1
       2: invokestatic  #32                 // Method org/apache/logging/log4j/core/pattern/PlainTextRenderer.getInstance:()Lorg/apache/logging/log4j/core/pattern/PlainTextRenderer;
       5: aload_2
       6: getstatic     #34                 // Field EOL_STR:Ljava/lang/String;
       9: invokevirtual #37                 // Method getCauseStackTraceAsString:(Ljava/util/List;Lorg/apache/logging/log4j/core/pattern/TextRenderer;Ljava/lang/String;Ljava/lang/String;)Ljava/lang/String;
      12: areturn

  public java.lang.String getCauseStackTraceAsString(java.util.List<java.lang.String>, org.apache.logging.log4j.core.pattern.TextRenderer, java.lang.String);
    Code:
       0: aload_0
       1: aload_1
       2: aload_2
       3: aload_3
       4: getstatic     #34                 // Field EOL_STR:Ljava/lang/String;
       7: invokevirtual #37                 // Method getCauseStackTraceAsString:(Ljava/util/List;Lorg/apache/logging/log4j/core/pattern/TextRenderer;Ljava/lang/String;Ljava/lang/String;)Ljava/lang/String;
      10: areturn

  public java.lang.String getCauseStackTraceAsString(java.util.List<java.lang.String>, org.apache.logging.log4j.core.pattern.TextRenderer, java.lang.String, java.lang.String);
    Code:
       0: new           #38                 // class java/lang/StringBuilder
       3: dup
       4: invokespecial #39                 // Method java/lang/StringBuilder."<init>":()V
       7: astore        5
       9: aload_0
      10: aload         5
      12: aload_1
      13: aload_2
      14: aload_3
      15: aload         4
      17: invokestatic  #40                 // Method org/apache/logging/log4j/core/impl/ThrowableProxyRenderer.formatCauseStackTrace:(Lorg/apache/logging/log4j/core/impl/ThrowableProxy;Ljava/lang/StringBuilder;Ljava/util/List;Lorg/apache/logging/log4j/core/pattern/TextRenderer;Ljava/lang/String;Ljava/lang/String;)V
      20: aload         5
      22: invokevirtual #41                 // Method java/lang/StringBuilder.toString:()Ljava/lang/String;
      25: areturn

  public int getCommonElementCount();
    Code:
       0: aload_0
       1: getfield      #30                 // Field commonElementCount:I
       4: ireturn

  void setCommonElementCount(int);
    Code:
       0: aload_0
       1: iload_1
       2: putfield      #30                 // Field commonElementCount:I
       5: return

  public org.apache.logging.log4j.core.impl.ExtendedStackTraceElement[] getExtendedStackTrace();
    Code:
       0: aload_0
       1: getfield      #5                  // Field extendedStackTrace:[Lorg/apache/logging/log4j/core/impl/ExtendedStackTraceElement;
       4: areturn

  public java.lang.String getExtendedStackTraceAsString();
    Code:
       0: aload_0
       1: aconst_null
       2: invokestatic  #32                 // Method org/apache/logging/log4j/core/pattern/PlainTextRenderer.getInstance:()Lorg/apache/logging/log4j/core/pattern/PlainTextRenderer;
       5: ldc           #43                 // String
       7: getstatic     #34                 // Field EOL_STR:Ljava/lang/String;
      10: invokevirtual #44                 // Method getExtendedStackTraceAsString:(Ljava/util/List;Lorg/apache/logging/log4j/core/pattern/TextRenderer;Ljava/lang/String;Ljava/lang/String;)Ljava/lang/String;
      13: areturn

  public java.lang.String getExtendedStackTraceAsString(java.lang.String);
    Code:
       0: aload_0
       1: aconst_null
       2: invokestatic  #32                 // Method org/apache/logging/log4j/core/pattern/PlainTextRenderer.getInstance:()Lorg/apache/logging/log4j/core/pattern/PlainTextRenderer;
       5: aload_1
       6: getstatic     #34                 // Field EOL_STR:Ljava/lang/String;
       9: invokevirtual #44                 // Method getExtendedStackTraceAsString:(Ljava/util/List;Lorg/apache/logging/log4j/core/pattern/TextRenderer;Ljava/lang/String;Ljava/lang/String;)Ljava/lang/String;
      12: areturn

  public java.lang.String getExtendedStackTraceAsString(java.util.List<java.lang.String>, java.lang.String);
    Code:
       0: aload_0
       1: aload_1
       2: invokestatic  #32                 // Method org/apache/logging/log4j/core/pattern/PlainTextRenderer.getInstance:()Lorg/apache/logging/log4j/core/pattern/PlainTextRenderer;
       5: aload_2
       6: getstatic     #34                 // Field EOL_STR:Ljava/lang/String;
       9: invokevirtual #44                 // Method getExtendedStackTraceAsString:(Ljava/util/List;Lorg/apache/logging/log4j/core/pattern/TextRenderer;Ljava/lang/String;Ljava/lang/String;)Ljava/lang/String;
      12: areturn

  public java.lang.String getExtendedStackTraceAsString(java.util.List<java.lang.String>, org.apache.logging.log4j.core.pattern.TextRenderer, java.lang.String);
    Code:
       0: aload_0
       1: aload_1
       2: aload_2
       3: aload_3
       4: getstatic     #34                 // Field EOL_STR:Ljava/lang/String;
       7: invokevirtual #44                 // Method getExtendedStackTraceAsString:(Ljava/util/List;Lorg/apache/logging/log4j/core/pattern/TextRenderer;Ljava/lang/String;Ljava/lang/String;)Ljava/lang/String;
      10: areturn

  public java.lang.String getExtendedStackTraceAsString(java.util.List<java.lang.String>, org.apache.logging.log4j.core.pattern.TextRenderer, java.lang.String, java.lang.String);
    Code:
       0: new           #38                 // class java/lang/StringBuilder
       3: dup
       4: sipush        1024
       7: invokespecial #45                 // Method java/lang/StringBuilder."<init>":(I)V
      10: astore        5
      12: aload_0
      13: aload         5
      15: aload_1
      16: aload_2
      17: aload_3
      18: aload         4
      20: invokevirtual #46                 // Method formatExtendedStackTraceTo:(Ljava/lang/StringBuilder;Ljava/util/List;Lorg/apache/logging/log4j/core/pattern/TextRenderer;Ljava/lang/String;Ljava/lang/String;)V
      23: aload         5
      25: invokevirtual #41                 // Method java/lang/StringBuilder.toString:()Ljava/lang/String;
      28: areturn

  public void formatExtendedStackTraceTo(java.lang.StringBuilder, java.util.List<java.lang.String>, org.apache.logging.log4j.core.pattern.TextRenderer, java.lang.String, java.lang.String);
    Code:
       0: aload_0
       1: aload_1
       2: aload_2
       3: aload_3
       4: aload         4
       6: aload         5
       8: invokestatic  #47                 // Method org/apache/logging/log4j/core/impl/ThrowableProxyRenderer.formatExtendedStackTraceTo:(Lorg/apache/logging/log4j/core/impl/ThrowableProxy;Ljava/lang/StringBuilder;Ljava/util/List;Lorg/apache/logging/log4j/core/pattern/TextRenderer;Ljava/lang/String;Ljava/lang/String;)V
      11: return

  public java.lang.String getLocalizedMessage();
    Code:
       0: aload_0
       1: getfield      #8                  // Field localizedMessage:Ljava/lang/String;
       4: areturn

  public java.lang.String getMessage();
    Code:
       0: aload_0
       1: getfield      #7                  // Field message:Ljava/lang/String;
       4: areturn

  public java.lang.String getName();
    Code:
       0: aload_0
       1: getfield      #3                  // Field name:Ljava/lang/String;
       4: areturn

  public java.lang.StackTraceElement[] getStackTrace();
    Code:
       0: aload_0
       1: getfield      #2                  // Field throwable:Ljava/lang/Throwable;
       4: ifnonnull     11
       7: aconst_null
       8: goto          18
      11: aload_0
      12: getfield      #2                  // Field throwable:Ljava/lang/Throwable;
      15: invokevirtual #19                 // Method java/lang/Throwable.getStackTrace:()[Ljava/lang/StackTraceElement;
      18: areturn

  public org.apache.logging.log4j.core.impl.ThrowableProxy[] getSuppressedProxies();
    Code:
       0: aload_0
       1: getfield      #10                 // Field suppressedProxies:[Lorg/apache/logging/log4j/core/impl/ThrowableProxy;
       4: areturn

  public java.lang.String getSuppressedStackTrace(java.lang.String);
    Code:
       0: aload_0
       1: invokevirtual #48                 // Method getSuppressedProxies:()[Lorg/apache/logging/log4j/core/impl/ThrowableProxy;
       4: astore_2
       5: aload_2
       6: ifnull        14
       9: aload_2
      10: arraylength
      11: ifne          17
      14: ldc           #43                 // String
      16: areturn
      17: new           #38                 // class java/lang/StringBuilder
      20: dup
      21: ldc           #49                 // String Suppressed Stack Trace Elements:
      23: invokespecial #50                 // Method java/lang/StringBuilder."<init>":(Ljava/lang/String;)V
      26: bipush        10
      28: invokevirtual #51                 // Method java/lang/StringBuilder.append:(C)Ljava/lang/StringBuilder;
      31: astore_3
      32: aload_2
      33: astore        4
      35: aload         4
      37: arraylength
      38: istore        5
      40: iconst_0
      41: istore        6
      43: iload         6
      45: iload         5
      47: if_icmpge     74
      50: aload         4
      52: iload         6
      54: aaload
      55: astore        7
      57: aload_3
      58: aload         7
      60: aload_1
      61: invokevirtual #52                 // Method getExtendedStackTraceAsString:(Ljava/lang/String;)Ljava/lang/String;
      64: invokevirtual #53                 // Method java/lang/StringBuilder.append:(Ljava/lang/String;)Ljava/lang/StringBuilder;
      67: pop
      68: iinc          6, 1
      71: goto          43
      74: aload_3
      75: invokevirtual #41                 // Method java/lang/StringBuilder.toString:()Ljava/lang/String;
      78: areturn

  public java.lang.Throwable getThrowable();
    Code:
       0: aload_0
       1: getfield      #2                  // Field throwable:Ljava/lang/Throwable;
       4: areturn

  public int hashCode();
    Code:
       0: bipush        31
       2: istore_1
       3: iconst_1
       4: istore_2
       5: bipush        31
       7: iload_2
       8: imul
       9: aload_0
      10: getfield      #6                  // Field causeProxy:Lorg/apache/logging/log4j/core/impl/ThrowableProxy;
      13: ifnonnull     20
      16: iconst_0
      17: goto          27
      20: aload_0
      21: getfield      #6                  // Field causeProxy:Lorg/apache/logging/log4j/core/impl/ThrowableProxy;
      24: invokevirtual #54                 // Method hashCode:()I
      27: iadd
      28: istore_2
      29: bipush        31
      31: iload_2
      32: imul
      33: aload_0
      34: getfield      #30                 // Field commonElementCount:I
      37: iadd
      38: istore_2
      39: bipush        31
      41: iload_2
      42: imul
      43: aload_0
      44: getfield      #5                  // Field extendedStackTrace:[Lorg/apache/logging/log4j/core/impl/ExtendedStackTraceElement;
      47: ifnonnull     54
      50: iconst_0
      51: goto          61
      54: aload_0
      55: getfield      #5                  // Field extendedStackTrace:[Lorg/apache/logging/log4j/core/impl/ExtendedStackTraceElement;
      58: invokestatic  #55                 // Method java/util/Arrays.hashCode:([Ljava/lang/Object;)I
      61: iadd
      62: istore_2
      63: bipush        31
      65: iload_2
      66: imul
      67: aload_0
      68: getfield      #10                 // Field suppressedProxies:[Lorg/apache/logging/log4j/core/impl/ThrowableProxy;
      71: ifnonnull     78
      74: iconst_0
      75: goto          85
      78: aload_0
      79: getfield      #10                 // Field suppressedProxies:[Lorg/apache/logging/log4j/core/impl/ThrowableProxy;
      82: invokestatic  #55                 // Method java/util/Arrays.hashCode:([Ljava/lang/Object;)I
      85: iadd
      86: istore_2
      87: bipush        31
      89: iload_2
      90: imul
      91: aload_0
      92: getfield      #3                  // Field name:Ljava/lang/String;
      95: ifnonnull     102
      98: iconst_0
      99: goto          109
     102: aload_0
     103: getfield      #3                  // Field name:Ljava/lang/String;
     106: invokevirtual #56                 // Method java/lang/String.hashCode:()I
     109: iadd
     110: istore_2
     111: iload_2
     112: ireturn

  public java.lang.String toString();
    Code:
       0: aload_0
       1: getfield      #7                  // Field message:Ljava/lang/String;
       4: astore_1
       5: aload_1
       6: ifnull        38
       9: new           #38                 // class java/lang/StringBuilder
      12: dup
      13: invokespecial #39                 // Method java/lang/StringBuilder."<init>":()V
      16: aload_0
      17: getfield      #3                  // Field name:Ljava/lang/String;
      20: invokevirtual #53                 // Method java/lang/StringBuilder.append:(Ljava/lang/String;)Ljava/lang/StringBuilder;
      23: ldc           #57                 // String :
      25: invokevirtual #53                 // Method java/lang/StringBuilder.append:(Ljava/lang/String;)Ljava/lang/StringBuilder;
      28: aload_1
      29: invokevirtual #53                 // Method java/lang/StringBuilder.append:(Ljava/lang/String;)Ljava/lang/StringBuilder;
      32: invokevirtual #41                 // Method java/lang/StringBuilder.toString:()Ljava/lang/String;
      35: goto          42
      38: aload_0
      39: getfield      #3                  // Field name:Ljava/lang/String;
      42: areturn

  static {};
    Code:
       0: iconst_0
       1: anewarray     #24                 // class org/apache/logging/log4j/core/impl/ThrowableProxy
       4: putstatic     #9                  // Field EMPTY_ARRAY:[Lorg/apache/logging/log4j/core/impl/ThrowableProxy;
       7: bipush        10
       9: invokestatic  #58                 // Method java/lang/String.valueOf:(C)Ljava/lang/String;
      12: putstatic     #34                 // Field EOL_STR:Ljava/lang/String;
      15: return
}
