Compiled from "PRIO.java"
public final class com.kenai.constantine.platform.PRIO extends java.lang.Enum<com.kenai.constantine.platform.PRIO> implements com.kenai.constantine.Constant {
  public static final com.kenai.constantine.platform.PRIO PRIO_MIN;

  public static final com.kenai.constantine.platform.PRIO PRIO_PROCESS;

  public static final com.kenai.constantine.platform.PRIO PRIO_PGRP;

  public static final com.kenai.constantine.platform.PRIO PRIO_USER;

  public static final com.kenai.constantine.platform.PRIO PRIO_MAX;

  public static final com.kenai.constantine.platform.PRIO __UNKNOWN_CONSTANT__;

  private static final com.kenai.constantine.platform.ConstantResolver<com.kenai.constantine.platform.PRIO> resolver;

  private static final com.kenai.constantine.platform.PRIO[] $VALUES;

  public static com.kenai.constantine.platform.PRIO[] values();
    Code:
       0: getstatic     #1                  // Field $VALUES:[Lcom/kenai/constantine/platform/PRIO;
       3: invokevirtual #2                  // Method "[Lcom/kenai/constantine/platform/PRIO;".clone:()Ljava/lang/Object;
       6: checkcast     #3                  // class "[Lcom/kenai/constantine/platform/PRIO;"
       9: areturn

  public static com.kenai.constantine.platform.PRIO valueOf(java.lang.String);
    Code:
       0: ldc           #4                  // class com/kenai/constantine/platform/PRIO
       2: aload_0
       3: invokestatic  #5                  // Method java/lang/Enum.valueOf:(Ljava/lang/Class;Ljava/lang/String;)Ljava/lang/Enum;
       6: checkcast     #4                  // class com/kenai/constantine/platform/PRIO
       9: areturn

  private com.kenai.constantine.platform.PRIO();
    Code:
       0: aload_0
       1: aload_1
       2: iload_2
       3: invokespecial #6                  // Method java/lang/Enum."<init>":(Ljava/lang/String;I)V
       6: return

  public final int value();
    Code:
       0: getstatic     #7                  // Field resolver:Lcom/kenai/constantine/platform/ConstantResolver;
       3: aload_0
       4: invokevirtual #8                  // Method com/kenai/constantine/platform/ConstantResolver.intValue:(Ljava/lang/Enum;)I
       7: ireturn

  public final int intValue();
    Code:
       0: getstatic     #7                  // Field resolver:Lcom/kenai/constantine/platform/ConstantResolver;
       3: aload_0
       4: invokevirtual #9                  // Method com/kenai/constantine/platform/ConstantResolver.longValue:(Ljava/lang/Enum;)J
       7: l2i
       8: ireturn

  public final long longValue();
    Code:
       0: getstatic     #7                  // Field resolver:Lcom/kenai/constantine/platform/ConstantResolver;
       3: aload_0
       4: invokevirtual #9                  // Method com/kenai/constantine/platform/ConstantResolver.longValue:(Ljava/lang/Enum;)J
       7: lreturn

  public final java.lang.String description();
    Code:
       0: getstatic     #7                  // Field resolver:Lcom/kenai/constantine/platform/ConstantResolver;
       3: aload_0
       4: invokevirtual #10                 // Method com/kenai/constantine/platform/ConstantResolver.description:(Ljava/lang/Enum;)Ljava/lang/String;
       7: areturn

  public final boolean defined();
    Code:
       0: iconst_1
       1: ireturn

  public final java.lang.String toString();
    Code:
       0: aload_0
       1: invokevirtual #11                 // Method description:()Ljava/lang/String;
       4: areturn

  public static final com.kenai.constantine.platform.PRIO valueOf(int);
    Code:
       0: getstatic     #7                  // Field resolver:Lcom/kenai/constantine/platform/ConstantResolver;
       3: iload_0
       4: invokevirtual #12                 // Method com/kenai/constantine/platform/ConstantResolver.valueOf:(I)Ljava/lang/Enum;
       7: checkcast     #4                  // class com/kenai/constantine/platform/PRIO
      10: areturn

  static {};
    Code:
       0: new           #4                  // class com/kenai/constantine/platform/PRIO
       3: dup
       4: ldc           #13                 // String PRIO_MIN
       6: iconst_0
       7: invokespecial #14                 // Method "<init>":(Ljava/lang/String;I)V
      10: putstatic     #15                 // Field PRIO_MIN:Lcom/kenai/constantine/platform/PRIO;
      13: new           #4                  // class com/kenai/constantine/platform/PRIO
      16: dup
      17: ldc           #16                 // String PRIO_PROCESS
      19: iconst_1
      20: invokespecial #14                 // Method "<init>":(Ljava/lang/String;I)V
      23: putstatic     #17                 // Field PRIO_PROCESS:Lcom/kenai/constantine/platform/PRIO;
      26: new           #4                  // class com/kenai/constantine/platform/PRIO
      29: dup
      30: ldc           #18                 // String PRIO_PGRP
      32: iconst_2
      33: invokespecial #14                 // Method "<init>":(Ljava/lang/String;I)V
      36: putstatic     #19                 // Field PRIO_PGRP:Lcom/kenai/constantine/platform/PRIO;
      39: new           #4                  // class com/kenai/constantine/platform/PRIO
      42: dup
      43: ldc           #20                 // String PRIO_USER
      45: iconst_3
      46: invokespecial #14                 // Method "<init>":(Ljava/lang/String;I)V
      49: putstatic     #21                 // Field PRIO_USER:Lcom/kenai/constantine/platform/PRIO;
      52: new           #4                  // class com/kenai/constantine/platform/PRIO
      55: dup
      56: ldc           #22                 // String PRIO_MAX
      58: iconst_4
      59: invokespecial #14                 // Method "<init>":(Ljava/lang/String;I)V
      62: putstatic     #23                 // Field PRIO_MAX:Lcom/kenai/constantine/platform/PRIO;
      65: new           #4                  // class com/kenai/constantine/platform/PRIO
      68: dup
      69: ldc           #24                 // String __UNKNOWN_CONSTANT__
      71: iconst_5
      72: invokespecial #14                 // Method "<init>":(Ljava/lang/String;I)V
      75: putstatic     #25                 // Field __UNKNOWN_CONSTANT__:Lcom/kenai/constantine/platform/PRIO;
      78: bipush        6
      80: anewarray     #4                  // class com/kenai/constantine/platform/PRIO
      83: dup
      84: iconst_0
      85: getstatic     #15                 // Field PRIO_MIN:Lcom/kenai/constantine/platform/PRIO;
      88: aastore
      89: dup
      90: iconst_1
      91: getstatic     #17                 // Field PRIO_PROCESS:Lcom/kenai/constantine/platform/PRIO;
      94: aastore
      95: dup
      96: iconst_2
      97: getstatic     #19                 // Field PRIO_PGRP:Lcom/kenai/constantine/platform/PRIO;
     100: aastore
     101: dup
     102: iconst_3
     103: getstatic     #21                 // Field PRIO_USER:Lcom/kenai/constantine/platform/PRIO;
     106: aastore
     107: dup
     108: iconst_4
     109: getstatic     #23                 // Field PRIO_MAX:Lcom/kenai/constantine/platform/PRIO;
     112: aastore
     113: dup
     114: iconst_5
     115: getstatic     #25                 // Field __UNKNOWN_CONSTANT__:Lcom/kenai/constantine/platform/PRIO;
     118: aastore
     119: putstatic     #1                  // Field $VALUES:[Lcom/kenai/constantine/platform/PRIO;
     122: ldc           #4                  // class com/kenai/constantine/platform/PRIO
     124: sipush        20000
     127: sipush        29999
     130: invokestatic  #26                 // Method com/kenai/constantine/platform/ConstantResolver.getResolver:(Ljava/lang/Class;II)Lcom/kenai/constantine/platform/ConstantResolver;
     133: putstatic     #7                  // Field resolver:Lcom/kenai/constantine/platform/ConstantResolver;
     136: return
}
