Compiled from "Parser.java"
final class org.elasticsearch.hadoop.serialization.Parser$Token$2 extends org.elasticsearch.hadoop.serialization.Parser$Token {
  org.elasticsearch.hadoop.serialization.Parser$Token$2(java.lang.String, int);
    Code:
       0: aload_0
       1: aload_1
       2: iload_2
       3: aconst_null
       4: invokespecial #1                  // Method org/elasticsearch/hadoop/serialization/Parser$Token."<init>":(Ljava/lang/String;ILorg/elasticsearch/hadoop/serialization/Parser$1;)V
       7: return

  public boolean isValue();
    Code:
       0: iconst_0
       1: ireturn
}
