Compiled from "UnsafeOutput.java"
public final class com.esotericsoftware.kryo.io.UnsafeOutput extends com.esotericsoftware.kryo.io.Output {
  private boolean supportVarInts;

  private static final boolean isLittleEndian;

  public com.esotericsoftware.kryo.io.UnsafeOutput();
    Code:
       0: aload_0
       1: invokespecial #1                  // Method com/esotericsoftware/kryo/io/Output."<init>":()V
       4: aload_0
       5: iconst_0
       6: putfield      #2                  // Field supportVarInts:Z
       9: return

  public com.esotericsoftware.kryo.io.UnsafeOutput(int);
    Code:
       0: aload_0
       1: iload_1
       2: iload_1
       3: invokespecial #3                  // Method "<init>":(II)V
       6: return

  public com.esotericsoftware.kryo.io.UnsafeOutput(int, int);
    Code:
       0: aload_0
       1: iload_1
       2: iload_2
       3: invokespecial #4                  // Method com/esotericsoftware/kryo/io/Output."<init>":(II)V
       6: aload_0
       7: iconst_0
       8: putfield      #2                  // Field supportVarInts:Z
      11: return

  public com.esotericsoftware.kryo.io.UnsafeOutput(byte[]);
    Code:
       0: aload_0
       1: aload_1
       2: aload_1
       3: arraylength
       4: invokespecial #5                  // Method "<init>":([BI)V
       7: return

  public com.esotericsoftware.kryo.io.UnsafeOutput(byte[], int);
    Code:
       0: aload_0
       1: aload_1
       2: iload_2
       3: invokespecial #6                  // Method com/esotericsoftware/kryo/io/Output."<init>":([BI)V
       6: aload_0
       7: iconst_0
       8: putfield      #2                  // Field supportVarInts:Z
      11: return

  public com.esotericsoftware.kryo.io.UnsafeOutput(java.io.OutputStream);
    Code:
       0: aload_0
       1: aload_1
       2: invokespecial #7                  // Method com/esotericsoftware/kryo/io/Output."<init>":(Ljava/io/OutputStream;)V
       5: aload_0
       6: iconst_0
       7: putfield      #2                  // Field supportVarInts:Z
      10: return

  public com.esotericsoftware.kryo.io.UnsafeOutput(java.io.OutputStream, int);
    Code:
       0: aload_0
       1: aload_1
       2: iload_2
       3: invokespecial #8                  // Method com/esotericsoftware/kryo/io/Output."<init>":(Ljava/io/OutputStream;I)V
       6: aload_0
       7: iconst_0
       8: putfield      #2                  // Field supportVarInts:Z
      11: return

  public final void writeInt(int) throws com.esotericsoftware.kryo.KryoException;
    Code:
       0: aload_0
       1: iconst_4
       2: invokevirtual #9                  // Method require:(I)Z
       5: pop
       6: invokestatic  #10                 // Method com/esotericsoftware/kryo/util/UnsafeUtil.unsafe:()Lsun/misc/Unsafe;
       9: aload_0
      10: getfield      #11                 // Field buffer:[B
      13: getstatic     #12                 // Field com/esotericsoftware/kryo/util/UnsafeUtil.byteArrayBaseOffset:J
      16: aload_0
      17: getfield      #13                 // Field position:I
      20: i2l
      21: ladd
      22: iload_1
      23: invokevirtual #14                 // Method sun/misc/Unsafe.putInt:(Ljava/lang/Object;JI)V
      26: aload_0
      27: dup
      28: getfield      #13                 // Field position:I
      31: iconst_4
      32: iadd
      33: putfield      #13                 // Field position:I
      36: return

  private final void writeLittleEndianInt(int);
    Code:
       0: getstatic     #15                 // Field isLittleEndian:Z
       3: ifeq          14
       6: aload_0
       7: iload_1
       8: invokevirtual #16                 // Method writeInt:(I)V
      11: goto          22
      14: aload_0
      15: iload_1
      16: invokestatic  #17                 // Method com/esotericsoftware/kryo/util/Util.swapInt:(I)I
      19: invokevirtual #16                 // Method writeInt:(I)V
      22: return

  public final void writeFloat(float) throws com.esotericsoftware.kryo.KryoException;
    Code:
       0: aload_0
       1: iconst_4
       2: invokevirtual #9                  // Method require:(I)Z
       5: pop
       6: invokestatic  #10                 // Method com/esotericsoftware/kryo/util/UnsafeUtil.unsafe:()Lsun/misc/Unsafe;
       9: aload_0
      10: getfield      #11                 // Field buffer:[B
      13: getstatic     #12                 // Field com/esotericsoftware/kryo/util/UnsafeUtil.byteArrayBaseOffset:J
      16: aload_0
      17: getfield      #13                 // Field position:I
      20: i2l
      21: ladd
      22: fload_1
      23: invokevirtual #18                 // Method sun/misc/Unsafe.putFloat:(Ljava/lang/Object;JF)V
      26: aload_0
      27: dup
      28: getfield      #13                 // Field position:I
      31: iconst_4
      32: iadd
      33: putfield      #13                 // Field position:I
      36: return

  public final void writeShort(int) throws com.esotericsoftware.kryo.KryoException;
    Code:
       0: aload_0
       1: iconst_2
       2: invokevirtual #9                  // Method require:(I)Z
       5: pop
       6: invokestatic  #10                 // Method com/esotericsoftware/kryo/util/UnsafeUtil.unsafe:()Lsun/misc/Unsafe;
       9: aload_0
      10: getfield      #11                 // Field buffer:[B
      13: getstatic     #12                 // Field com/esotericsoftware/kryo/util/UnsafeUtil.byteArrayBaseOffset:J
      16: aload_0
      17: getfield      #13                 // Field position:I
      20: i2l
      21: ladd
      22: iload_1
      23: i2s
      24: invokevirtual #19                 // Method sun/misc/Unsafe.putShort:(Ljava/lang/Object;JS)V
      27: aload_0
      28: dup
      29: getfield      #13                 // Field position:I
      32: iconst_2
      33: iadd
      34: putfield      #13                 // Field position:I
      37: return

  public final void writeLong(long) throws com.esotericsoftware.kryo.KryoException;
    Code:
       0: aload_0
       1: bipush        8
       3: invokevirtual #9                  // Method require:(I)Z
       6: pop
       7: invokestatic  #10                 // Method com/esotericsoftware/kryo/util/UnsafeUtil.unsafe:()Lsun/misc/Unsafe;
      10: aload_0
      11: getfield      #11                 // Field buffer:[B
      14: getstatic     #12                 // Field com/esotericsoftware/kryo/util/UnsafeUtil.byteArrayBaseOffset:J
      17: aload_0
      18: getfield      #13                 // Field position:I
      21: i2l
      22: ladd
      23: lload_1
      24: invokevirtual #20                 // Method sun/misc/Unsafe.putLong:(Ljava/lang/Object;JJ)V
      27: aload_0
      28: dup
      29: getfield      #13                 // Field position:I
      32: bipush        8
      34: iadd
      35: putfield      #13                 // Field position:I
      38: return

  private final void writeLittleEndianLong(long);
    Code:
       0: getstatic     #15                 // Field isLittleEndian:Z
       3: ifeq          14
       6: aload_0
       7: lload_1
       8: invokevirtual #21                 // Method writeLong:(J)V
      11: goto          22
      14: aload_0
      15: lload_1
      16: invokestatic  #22                 // Method com/esotericsoftware/kryo/util/Util.swapLong:(J)J
      19: invokevirtual #21                 // Method writeLong:(J)V
      22: return

  public final void writeDouble(double) throws com.esotericsoftware.kryo.KryoException;
    Code:
       0: aload_0
       1: bipush        8
       3: invokevirtual #9                  // Method require:(I)Z
       6: pop
       7: invokestatic  #10                 // Method com/esotericsoftware/kryo/util/UnsafeUtil.unsafe:()Lsun/misc/Unsafe;
      10: aload_0
      11: getfield      #11                 // Field buffer:[B
      14: getstatic     #12                 // Field com/esotericsoftware/kryo/util/UnsafeUtil.byteArrayBaseOffset:J
      17: aload_0
      18: getfield      #13                 // Field position:I
      21: i2l
      22: ladd
      23: dload_1
      24: invokevirtual #23                 // Method sun/misc/Unsafe.putDouble:(Ljava/lang/Object;JD)V
      27: aload_0
      28: dup
      29: getfield      #13                 // Field position:I
      32: bipush        8
      34: iadd
      35: putfield      #13                 // Field position:I
      38: return

  public final void writeChar(char) throws com.esotericsoftware.kryo.KryoException;
    Code:
       0: aload_0
       1: iconst_2
       2: invokevirtual #9                  // Method require:(I)Z
       5: pop
       6: invokestatic  #10                 // Method com/esotericsoftware/kryo/util/UnsafeUtil.unsafe:()Lsun/misc/Unsafe;
       9: aload_0
      10: getfield      #11                 // Field buffer:[B
      13: getstatic     #12                 // Field com/esotericsoftware/kryo/util/UnsafeUtil.byteArrayBaseOffset:J
      16: aload_0
      17: getfield      #13                 // Field position:I
      20: i2l
      21: ladd
      22: iload_1
      23: invokevirtual #24                 // Method sun/misc/Unsafe.putChar:(Ljava/lang/Object;JC)V
      26: aload_0
      27: dup
      28: getfield      #13                 // Field position:I
      31: iconst_2
      32: iadd
      33: putfield      #13                 // Field position:I
      36: return

  public final int writeInt(int, boolean) throws com.esotericsoftware.kryo.KryoException;
    Code:
       0: aload_0
       1: getfield      #2                  // Field supportVarInts:Z
       4: ifne          14
       7: aload_0
       8: iload_1
       9: invokevirtual #16                 // Method writeInt:(I)V
      12: iconst_4
      13: ireturn
      14: aload_0
      15: iload_1
      16: iload_2
      17: invokevirtual #25                 // Method writeVarInt:(IZ)I
      20: ireturn

  public final int writeLong(long, boolean) throws com.esotericsoftware.kryo.KryoException;
    Code:
       0: aload_0
       1: getfield      #2                  // Field supportVarInts:Z
       4: ifne          15
       7: aload_0
       8: lload_1
       9: invokevirtual #21                 // Method writeLong:(J)V
      12: bipush        8
      14: ireturn
      15: aload_0
      16: lload_1
      17: iload_3
      18: invokevirtual #26                 // Method writeVarLong:(JZ)I
      21: ireturn

  public final int writeVarInt(int, boolean) throws com.esotericsoftware.kryo.KryoException;
    Code:
       0: iload_1
       1: istore_3
       2: iload_2
       3: ifne          15
       6: iload_3
       7: iconst_1
       8: ishl
       9: iload_3
      10: bipush        31
      12: ishr
      13: ixor
      14: istore_3
      15: iconst_0
      16: istore        4
      18: iload_3
      19: bipush        127
      21: iand
      22: istore        4
      24: iload_3
      25: bipush        7
      27: iushr
      28: istore_3
      29: iload_3
      30: ifne          41
      33: aload_0
      34: iload         4
      36: invokevirtual #27                 // Method write:(I)V
      39: iconst_1
      40: ireturn
      41: iload         4
      43: sipush        128
      46: ior
      47: istore        4
      49: iload         4
      51: iload_3
      52: bipush        127
      54: iand
      55: bipush        8
      57: ishl
      58: ior
      59: istore        4
      61: iload_3
      62: bipush        7
      64: iushr
      65: istore_3
      66: iload_3
      67: ifne          88
      70: aload_0
      71: iload         4
      73: invokespecial #28                 // Method writeLittleEndianInt:(I)V
      76: aload_0
      77: dup
      78: getfield      #13                 // Field position:I
      81: iconst_2
      82: isub
      83: putfield      #13                 // Field position:I
      86: iconst_2
      87: ireturn
      88: iload         4
      90: ldc           #29                 // int 32768
      92: ior
      93: istore        4
      95: iload         4
      97: iload_3
      98: bipush        127
     100: iand
     101: bipush        16
     103: ishl
     104: ior
     105: istore        4
     107: iload_3
     108: bipush        7
     110: iushr
     111: istore_3
     112: iload_3
     113: ifne          134
     116: aload_0
     117: iload         4
     119: invokespecial #28                 // Method writeLittleEndianInt:(I)V
     122: aload_0
     123: dup
     124: getfield      #13                 // Field position:I
     127: iconst_1
     128: isub
     129: putfield      #13                 // Field position:I
     132: iconst_3
     133: ireturn
     134: iload         4
     136: ldc           #30                 // int 8388608
     138: ior
     139: istore        4
     141: iload         4
     143: iload_3
     144: bipush        127
     146: iand
     147: bipush        24
     149: ishl
     150: ior
     151: istore        4
     153: iload_3
     154: bipush        7
     156: iushr
     157: istore_3
     158: iload_3
     159: ifne          180
     162: aload_0
     163: iload         4
     165: invokespecial #28                 // Method writeLittleEndianInt:(I)V
     168: aload_0
     169: dup
     170: getfield      #13                 // Field position:I
     173: iconst_0
     174: isub
     175: putfield      #13                 // Field position:I
     178: iconst_4
     179: ireturn
     180: iload         4
     182: ldc           #31                 // int -2147483648
     184: ior
     185: istore        4
     187: iload         4
     189: i2l
     190: iload_3
     191: bipush        127
     193: iand
     194: i2l
     195: bipush        32
     197: lshl
     198: lor
     199: lstore        5
     201: iload         4
     203: i2l
     204: ldc2_w        #32                 // long 4294967295l
     207: land
     208: l2i
     209: istore        4
     211: aload_0
     212: lload         5
     214: invokespecial #34                 // Method writeLittleEndianLong:(J)V
     217: aload_0
     218: dup
     219: getfield      #13                 // Field position:I
     222: iconst_3
     223: isub
     224: putfield      #13                 // Field position:I
     227: iconst_5
     228: ireturn

  public final int writeVarLong(long, boolean) throws com.esotericsoftware.kryo.KryoException;
    Code:
       0: iload_3
       1: ifne          13
       4: lload_1
       5: iconst_1
       6: lshl
       7: lload_1
       8: bipush        63
      10: lshr
      11: lxor
      12: lstore_1
      13: iconst_0
      14: istore        4
      16: lload_1
      17: ldc2_w        #35                 // long 127l
      20: land
      21: l2i
      22: istore        4
      24: lload_1
      25: bipush        7
      27: lushr
      28: lstore_1
      29: lload_1
      30: lconst_0
      31: lcmp
      32: ifne          43
      35: aload_0
      36: iload         4
      38: invokevirtual #37                 // Method writeByte:(I)V
      41: iconst_1
      42: ireturn
      43: iload         4
      45: sipush        128
      48: ior
      49: istore        4
      51: iload         4
      53: i2l
      54: lload_1
      55: bipush        8
      57: lshl
      58: lor
      59: l2i
      60: istore        4
      62: lload_1
      63: bipush        7
      65: lushr
      66: lstore_1
      67: lload_1
      68: lconst_0
      69: lcmp
      70: ifne          91
      73: aload_0
      74: iload         4
      76: invokespecial #28                 // Method writeLittleEndianInt:(I)V
      79: aload_0
      80: dup
      81: getfield      #13                 // Field position:I
      84: iconst_2
      85: isub
      86: putfield      #13                 // Field position:I
      89: iconst_2
      90: ireturn
      91: iload         4
      93: ldc           #29                 // int 32768
      95: ior
      96: istore        4
      98: iload         4
     100: i2l
     101: lload_1
     102: bipush        16
     104: lshl
     105: lor
     106: l2i
     107: istore        4
     109: lload_1
     110: bipush        7
     112: lushr
     113: lstore_1
     114: lload_1
     115: lconst_0
     116: lcmp
     117: ifne          138
     120: aload_0
     121: iload         4
     123: invokespecial #28                 // Method writeLittleEndianInt:(I)V
     126: aload_0
     127: dup
     128: getfield      #13                 // Field position:I
     131: iconst_1
     132: isub
     133: putfield      #13                 // Field position:I
     136: iconst_3
     137: ireturn
     138: iload         4
     140: ldc           #30                 // int 8388608
     142: ior
     143: istore        4
     145: iload         4
     147: i2l
     148: lload_1
     149: bipush        24
     151: lshl
     152: lor
     153: l2i
     154: istore        4
     156: lload_1
     157: bipush        7
     159: lushr
     160: lstore_1
     161: lload_1
     162: lconst_0
     163: lcmp
     164: ifne          185
     167: aload_0
     168: iload         4
     170: invokespecial #28                 // Method writeLittleEndianInt:(I)V
     173: aload_0
     174: dup
     175: getfield      #13                 // Field position:I
     178: iconst_0
     179: isub
     180: putfield      #13                 // Field position:I
     183: iconst_4
     184: ireturn
     185: iload         4
     187: ldc           #31                 // int -2147483648
     189: ior
     190: istore        4
     192: iload         4
     194: i2l
     195: lload_1
     196: bipush        32
     198: lshl
     199: lor
     200: lstore        5
     202: lload_1
     203: bipush        7
     205: lushr
     206: lstore_1
     207: lload_1
     208: lconst_0
     209: lcmp
     210: ifne          231
     213: aload_0
     214: lload         5
     216: invokespecial #34                 // Method writeLittleEndianLong:(J)V
     219: aload_0
     220: dup
     221: getfield      #13                 // Field position:I
     224: iconst_3
     225: isub
     226: putfield      #13                 // Field position:I
     229: iconst_5
     230: ireturn
     231: lload         5
     233: ldc2_w        #38                 // long 128l
     236: lor
     237: lstore        5
     239: iload         4
     241: i2l
     242: lload_1
     243: bipush        40
     245: lshl
     246: lor
     247: lstore        5
     249: lload_1
     250: bipush        7
     252: lushr
     253: lstore_1
     254: lload_1
     255: lconst_0
     256: lcmp
     257: ifne          279
     260: aload_0
     261: lload         5
     263: invokespecial #34                 // Method writeLittleEndianLong:(J)V
     266: aload_0
     267: dup
     268: getfield      #13                 // Field position:I
     271: iconst_2
     272: isub
     273: putfield      #13                 // Field position:I
     276: bipush        6
     278: ireturn
     279: lload         5
     281: ldc2_w        #40                 // long 32768l
     284: lor
     285: lstore        5
     287: iload         4
     289: i2l
     290: lload_1
     291: bipush        48
     293: lshl
     294: lor
     295: lstore        5
     297: lload_1
     298: bipush        7
     300: lushr
     301: lstore_1
     302: lload_1
     303: lconst_0
     304: lcmp
     305: ifne          327
     308: aload_0
     309: lload         5
     311: invokespecial #34                 // Method writeLittleEndianLong:(J)V
     314: aload_0
     315: dup
     316: getfield      #13                 // Field position:I
     319: iconst_1
     320: isub
     321: putfield      #13                 // Field position:I
     324: bipush        7
     326: ireturn
     327: lload         5
     329: ldc2_w        #42                 // long 8388608l
     332: lor
     333: lstore        5
     335: iload         4
     337: i2l
     338: lload_1
     339: bipush        56
     341: lshl
     342: lor
     343: lstore        5
     345: lload_1
     346: bipush        7
     348: lushr
     349: lstore_1
     350: lload_1
     351: lconst_0
     352: lcmp
     353: ifne          365
     356: aload_0
     357: lload         5
     359: invokespecial #34                 // Method writeLittleEndianLong:(J)V
     362: bipush        8
     364: ireturn
     365: lload         5
     367: ldc2_w        #44                 // long -2147483648l
     370: lor
     371: lstore        5
     373: aload_0
     374: lload         5
     376: invokespecial #34                 // Method writeLittleEndianLong:(J)V
     379: aload_0
     380: lload_1
     381: bipush        7
     383: lushr
     384: l2i
     385: i2b
     386: invokevirtual #27                 // Method write:(I)V
     389: bipush        9
     391: ireturn

  public final void writeInts(int[], boolean) throws com.esotericsoftware.kryo.KryoException;
    Code:
       0: aload_0
       1: getfield      #2                  // Field supportVarInts:Z
       4: ifne          26
       7: aload_1
       8: arraylength
       9: iconst_2
      10: ishl
      11: istore_3
      12: aload_0
      13: aload_1
      14: getstatic     #46                 // Field com/esotericsoftware/kryo/util/UnsafeUtil.intArrayBaseOffset:J
      17: lconst_0
      18: iload_3
      19: i2l
      20: invokespecial #47                 // Method writeBytes:(Ljava/lang/Object;JJJ)V
      23: goto          32
      26: aload_0
      27: aload_1
      28: iload_2
      29: invokespecial #48                 // Method com/esotericsoftware/kryo/io/Output.writeInts:([IZ)V
      32: return

  public final void writeLongs(long[], boolean) throws com.esotericsoftware.kryo.KryoException;
    Code:
       0: aload_0
       1: getfield      #2                  // Field supportVarInts:Z
       4: ifne          26
       7: aload_1
       8: arraylength
       9: iconst_3
      10: ishl
      11: istore_3
      12: aload_0
      13: aload_1
      14: getstatic     #49                 // Field com/esotericsoftware/kryo/util/UnsafeUtil.longArrayBaseOffset:J
      17: lconst_0
      18: iload_3
      19: i2l
      20: invokespecial #47                 // Method writeBytes:(Ljava/lang/Object;JJJ)V
      23: goto          32
      26: aload_0
      27: aload_1
      28: iload_2
      29: invokespecial #50                 // Method com/esotericsoftware/kryo/io/Output.writeLongs:([JZ)V
      32: return

  public final void writeInts(int[]) throws com.esotericsoftware.kryo.KryoException;
    Code:
       0: aload_1
       1: arraylength
       2: iconst_2
       3: ishl
       4: istore_2
       5: aload_0
       6: aload_1
       7: getstatic     #46                 // Field com/esotericsoftware/kryo/util/UnsafeUtil.intArrayBaseOffset:J
      10: lconst_0
      11: iload_2
      12: i2l
      13: invokespecial #47                 // Method writeBytes:(Ljava/lang/Object;JJJ)V
      16: return

  public final void writeLongs(long[]) throws com.esotericsoftware.kryo.KryoException;
    Code:
       0: aload_1
       1: arraylength
       2: iconst_3
       3: ishl
       4: istore_2
       5: aload_0
       6: aload_1
       7: getstatic     #49                 // Field com/esotericsoftware/kryo/util/UnsafeUtil.longArrayBaseOffset:J
      10: lconst_0
      11: iload_2
      12: i2l
      13: invokespecial #47                 // Method writeBytes:(Ljava/lang/Object;JJJ)V
      16: return

  public final void writeFloats(float[]) throws com.esotericsoftware.kryo.KryoException;
    Code:
       0: aload_1
       1: arraylength
       2: iconst_2
       3: ishl
       4: istore_2
       5: aload_0
       6: aload_1
       7: getstatic     #51                 // Field com/esotericsoftware/kryo/util/UnsafeUtil.floatArrayBaseOffset:J
      10: lconst_0
      11: iload_2
      12: i2l
      13: invokespecial #47                 // Method writeBytes:(Ljava/lang/Object;JJJ)V
      16: return

  public final void writeShorts(short[]) throws com.esotericsoftware.kryo.KryoException;
    Code:
       0: aload_1
       1: arraylength
       2: iconst_1
       3: ishl
       4: istore_2
       5: aload_0
       6: aload_1
       7: getstatic     #52                 // Field com/esotericsoftware/kryo/util/UnsafeUtil.shortArrayBaseOffset:J
      10: lconst_0
      11: iload_2
      12: i2l
      13: invokespecial #47                 // Method writeBytes:(Ljava/lang/Object;JJJ)V
      16: return

  public final void writeChars(char[]) throws com.esotericsoftware.kryo.KryoException;
    Code:
       0: aload_1
       1: arraylength
       2: iconst_1
       3: ishl
       4: istore_2
       5: aload_0
       6: aload_1
       7: getstatic     #53                 // Field com/esotericsoftware/kryo/util/UnsafeUtil.charArrayBaseOffset:J
      10: lconst_0
      11: iload_2
      12: i2l
      13: invokespecial #47                 // Method writeBytes:(Ljava/lang/Object;JJJ)V
      16: return

  public final void writeDoubles(double[]) throws com.esotericsoftware.kryo.KryoException;
    Code:
       0: aload_1
       1: arraylength
       2: iconst_3
       3: ishl
       4: istore_2
       5: aload_0
       6: aload_1
       7: getstatic     #54                 // Field com/esotericsoftware/kryo/util/UnsafeUtil.doubleArrayBaseOffset:J
      10: lconst_0
      11: iload_2
      12: i2l
      13: invokespecial #47                 // Method writeBytes:(Ljava/lang/Object;JJJ)V
      16: return

  public final void writeBytes(java.lang.Object, long, long) throws com.esotericsoftware.kryo.KryoException;
    Code:
       0: aload_0
       1: aload_1
       2: lconst_0
       3: lload_2
       4: lload         4
       6: invokespecial #47                 // Method writeBytes:(Ljava/lang/Object;JJJ)V
       9: return

  private final void writeBytes(java.lang.Object, long, long, long) throws com.esotericsoftware.kryo.KryoException;
    Code:
       0: aload_0
       1: getfield      #55                 // Field capacity:I
       4: aload_0
       5: getfield      #13                 // Field position:I
       8: isub
       9: lload         6
      11: l2i
      12: invokestatic  #56                 // Method java/lang/Math.min:(II)I
      15: istore        8
      17: invokestatic  #10                 // Method com/esotericsoftware/kryo/util/UnsafeUtil.unsafe:()Lsun/misc/Unsafe;
      20: aload_1
      21: lload_2
      22: lload         4
      24: ladd
      25: aload_0
      26: getfield      #11                 // Field buffer:[B
      29: getstatic     #12                 // Field com/esotericsoftware/kryo/util/UnsafeUtil.byteArrayBaseOffset:J
      32: aload_0
      33: getfield      #13                 // Field position:I
      36: i2l
      37: ladd
      38: iload         8
      40: i2l
      41: invokevirtual #57                 // Method sun/misc/Unsafe.copyMemory:(Ljava/lang/Object;JLjava/lang/Object;JJ)V
      44: aload_0
      45: dup
      46: getfield      #13                 // Field position:I
      49: iload         8
      51: iadd
      52: putfield      #13                 // Field position:I
      55: lload         6
      57: iload         8
      59: i2l
      60: lsub
      61: lstore        6
      63: lload         6
      65: lconst_0
      66: lcmp
      67: ifne          71
      70: return
      71: lload         4
      73: iload         8
      75: i2l
      76: ladd
      77: lstore        4
      79: aload_0
      80: getfield      #55                 // Field capacity:I
      83: lload         6
      85: l2i
      86: invokestatic  #56                 // Method java/lang/Math.min:(II)I
      89: istore        8
      91: aload_0
      92: iload         8
      94: invokevirtual #9                  // Method require:(I)Z
      97: pop
      98: goto          17

  public boolean supportVarInts();
    Code:
       0: aload_0
       1: getfield      #2                  // Field supportVarInts:Z
       4: ireturn

  public void supportVarInts(boolean);
    Code:
       0: aload_0
       1: iload_1
       2: putfield      #2                  // Field supportVarInts:Z
       5: return

  static {};
    Code:
       0: invokestatic  #58                 // Method java/nio/ByteOrder.nativeOrder:()Ljava/nio/ByteOrder;
       3: getstatic     #59                 // Field java/nio/ByteOrder.LITTLE_ENDIAN:Ljava/nio/ByteOrder;
       6: invokevirtual #60                 // Method java/lang/Object.equals:(Ljava/lang/Object;)Z
       9: putstatic     #15                 // Field isLittleEndian:Z
      12: return
}
