Compiled from "UnsafeMemoryInput.java"
public final class com.esotericsoftware.kryo.io.UnsafeMemoryInput extends com.esotericsoftware.kryo.io.ByteBufferInput {
  private long bufaddress;

  public com.esotericsoftware.kryo.io.UnsafeMemoryInput();
    Code:
       0: aload_0
       1: invokespecial #1                  // Method com/esotericsoftware/kryo/io/ByteBufferInput."<init>":()V
       4: aload_0
       5: iconst_0
       6: putfield      #2                  // Field varIntsEnabled:Z
       9: return

  public com.esotericsoftware.kryo.io.UnsafeMemoryInput(int);
    Code:
       0: aload_0
       1: iload_1
       2: invokespecial #3                  // Method com/esotericsoftware/kryo/io/ByteBufferInput."<init>":(I)V
       5: aload_0
       6: iconst_0
       7: putfield      #2                  // Field varIntsEnabled:Z
      10: aload_0
      11: invokespecial #4                  // Method updateBufferAddress:()V
      14: return

  public com.esotericsoftware.kryo.io.UnsafeMemoryInput(byte[]);
    Code:
       0: aload_0
       1: aload_1
       2: invokespecial #5                  // Method com/esotericsoftware/kryo/io/ByteBufferInput."<init>":([B)V
       5: aload_0
       6: iconst_0
       7: putfield      #2                  // Field varIntsEnabled:Z
      10: aload_0
      11: invokespecial #4                  // Method updateBufferAddress:()V
      14: return

  public com.esotericsoftware.kryo.io.UnsafeMemoryInput(java.nio.ByteBuffer);
    Code:
       0: aload_0
       1: aload_1
       2: invokespecial #6                  // Method com/esotericsoftware/kryo/io/ByteBufferInput."<init>":(Ljava/nio/ByteBuffer;)V
       5: aload_0
       6: iconst_0
       7: putfield      #2                  // Field varIntsEnabled:Z
      10: aload_0
      11: invokespecial #4                  // Method updateBufferAddress:()V
      14: return

  public com.esotericsoftware.kryo.io.UnsafeMemoryInput(long, int);
    Code:
       0: aload_0
       1: lload_1
       2: iload_3
       3: invokespecial #7                  // Method com/esotericsoftware/kryo/io/ByteBufferInput."<init>":(JI)V
       6: aload_0
       7: iconst_0
       8: putfield      #2                  // Field varIntsEnabled:Z
      11: aload_0
      12: invokespecial #4                  // Method updateBufferAddress:()V
      15: return

  public com.esotericsoftware.kryo.io.UnsafeMemoryInput(java.io.InputStream);
    Code:
       0: aload_0
       1: aload_1
       2: invokespecial #8                  // Method com/esotericsoftware/kryo/io/ByteBufferInput."<init>":(Ljava/io/InputStream;)V
       5: aload_0
       6: iconst_0
       7: putfield      #2                  // Field varIntsEnabled:Z
      10: aload_0
      11: invokespecial #4                  // Method updateBufferAddress:()V
      14: return

  public com.esotericsoftware.kryo.io.UnsafeMemoryInput(java.io.InputStream, int);
    Code:
       0: aload_0
       1: aload_1
       2: iload_2
       3: invokespecial #9                  // Method com/esotericsoftware/kryo/io/ByteBufferInput."<init>":(Ljava/io/InputStream;I)V
       6: aload_0
       7: iconst_0
       8: putfield      #2                  // Field varIntsEnabled:Z
      11: aload_0
      12: invokespecial #4                  // Method updateBufferAddress:()V
      15: return

  public void setBuffer(java.nio.ByteBuffer);
    Code:
       0: aload_0
       1: aload_1
       2: invokespecial #10                 // Method com/esotericsoftware/kryo/io/ByteBufferInput.setBuffer:(Ljava/nio/ByteBuffer;)V
       5: aload_0
       6: invokespecial #4                  // Method updateBufferAddress:()V
       9: return

  private void updateBufferAddress();
    Code:
       0: aload_0
       1: aload_0
       2: getfield      #11                 // Field com/esotericsoftware/kryo/io/ByteBufferInput.niobuffer:Ljava/nio/ByteBuffer;
       5: checkcast     #12                 // class sun/nio/ch/DirectBuffer
       8: invokeinterface #13,  1           // InterfaceMethod sun/nio/ch/DirectBuffer.address:()J
      13: putfield      #14                 // Field bufaddress:J
      16: return

  public int readInt() throws com.esotericsoftware.kryo.KryoException;
    Code:
       0: aload_0
       1: iconst_4
       2: invokevirtual #15                 // Method require:(I)I
       5: pop
       6: invokestatic  #16                 // Method com/esotericsoftware/kryo/util/UnsafeUtil.unsafe:()Lsun/misc/Unsafe;
       9: aload_0
      10: getfield      #14                 // Field bufaddress:J
      13: aload_0
      14: getfield      #17                 // Field position:I
      17: i2l
      18: ladd
      19: invokevirtual #18                 // Method sun/misc/Unsafe.getInt:(J)I
      22: istore_1
      23: aload_0
      24: dup
      25: getfield      #17                 // Field position:I
      28: iconst_4
      29: iadd
      30: putfield      #17                 // Field position:I
      33: iload_1
      34: ireturn

  public float readFloat() throws com.esotericsoftware.kryo.KryoException;
    Code:
       0: aload_0
       1: iconst_4
       2: invokevirtual #15                 // Method require:(I)I
       5: pop
       6: invokestatic  #16                 // Method com/esotericsoftware/kryo/util/UnsafeUtil.unsafe:()Lsun/misc/Unsafe;
       9: aload_0
      10: getfield      #14                 // Field bufaddress:J
      13: aload_0
      14: getfield      #17                 // Field position:I
      17: i2l
      18: ladd
      19: invokevirtual #19                 // Method sun/misc/Unsafe.getFloat:(J)F
      22: fstore_1
      23: aload_0
      24: dup
      25: getfield      #17                 // Field position:I
      28: iconst_4
      29: iadd
      30: putfield      #17                 // Field position:I
      33: fload_1
      34: freturn

  public short readShort() throws com.esotericsoftware.kryo.KryoException;
    Code:
       0: aload_0
       1: iconst_2
       2: invokevirtual #15                 // Method require:(I)I
       5: pop
       6: invokestatic  #16                 // Method com/esotericsoftware/kryo/util/UnsafeUtil.unsafe:()Lsun/misc/Unsafe;
       9: aload_0
      10: getfield      #14                 // Field bufaddress:J
      13: aload_0
      14: getfield      #17                 // Field position:I
      17: i2l
      18: ladd
      19: invokevirtual #20                 // Method sun/misc/Unsafe.getShort:(J)S
      22: istore_1
      23: aload_0
      24: dup
      25: getfield      #17                 // Field position:I
      28: iconst_2
      29: iadd
      30: putfield      #17                 // Field position:I
      33: iload_1
      34: ireturn

  public long readLong() throws com.esotericsoftware.kryo.KryoException;
    Code:
       0: aload_0
       1: bipush        8
       3: invokevirtual #15                 // Method require:(I)I
       6: pop
       7: invokestatic  #16                 // Method com/esotericsoftware/kryo/util/UnsafeUtil.unsafe:()Lsun/misc/Unsafe;
      10: aload_0
      11: getfield      #14                 // Field bufaddress:J
      14: aload_0
      15: getfield      #17                 // Field position:I
      18: i2l
      19: ladd
      20: invokevirtual #21                 // Method sun/misc/Unsafe.getLong:(J)J
      23: lstore_1
      24: aload_0
      25: dup
      26: getfield      #17                 // Field position:I
      29: bipush        8
      31: iadd
      32: putfield      #17                 // Field position:I
      35: lload_1
      36: lreturn

  public boolean readBoolean() throws com.esotericsoftware.kryo.KryoException;
    Code:
       0: aload_0
       1: getfield      #11                 // Field com/esotericsoftware/kryo/io/ByteBufferInput.niobuffer:Ljava/nio/ByteBuffer;
       4: aload_0
       5: getfield      #17                 // Field position:I
       8: invokevirtual #22                 // Method java/nio/ByteBuffer.position:(I)Ljava/nio/Buffer;
      11: pop
      12: aload_0
      13: invokespecial #23                 // Method com/esotericsoftware/kryo/io/ByteBufferInput.readBoolean:()Z
      16: ireturn

  public byte readByte() throws com.esotericsoftware.kryo.KryoException;
    Code:
       0: aload_0
       1: getfield      #11                 // Field com/esotericsoftware/kryo/io/ByteBufferInput.niobuffer:Ljava/nio/ByteBuffer;
       4: aload_0
       5: getfield      #17                 // Field position:I
       8: invokevirtual #22                 // Method java/nio/ByteBuffer.position:(I)Ljava/nio/Buffer;
      11: pop
      12: aload_0
      13: invokespecial #24                 // Method com/esotericsoftware/kryo/io/ByteBufferInput.readByte:()B
      16: ireturn

  public char readChar() throws com.esotericsoftware.kryo.KryoException;
    Code:
       0: aload_0
       1: iconst_2
       2: invokevirtual #15                 // Method require:(I)I
       5: pop
       6: invokestatic  #16                 // Method com/esotericsoftware/kryo/util/UnsafeUtil.unsafe:()Lsun/misc/Unsafe;
       9: aload_0
      10: getfield      #14                 // Field bufaddress:J
      13: aload_0
      14: getfield      #17                 // Field position:I
      17: i2l
      18: ladd
      19: invokevirtual #25                 // Method sun/misc/Unsafe.getChar:(J)C
      22: istore_1
      23: aload_0
      24: dup
      25: getfield      #17                 // Field position:I
      28: iconst_2
      29: iadd
      30: putfield      #17                 // Field position:I
      33: iload_1
      34: ireturn

  public double readDouble() throws com.esotericsoftware.kryo.KryoException;
    Code:
       0: aload_0
       1: bipush        8
       3: invokevirtual #15                 // Method require:(I)I
       6: pop
       7: invokestatic  #16                 // Method com/esotericsoftware/kryo/util/UnsafeUtil.unsafe:()Lsun/misc/Unsafe;
      10: aload_0
      11: getfield      #14                 // Field bufaddress:J
      14: aload_0
      15: getfield      #17                 // Field position:I
      18: i2l
      19: ladd
      20: invokevirtual #26                 // Method sun/misc/Unsafe.getDouble:(J)D
      23: dstore_1
      24: aload_0
      25: dup
      26: getfield      #17                 // Field position:I
      29: bipush        8
      31: iadd
      32: putfield      #17                 // Field position:I
      35: dload_1
      36: dreturn

  public int readInt(boolean) throws com.esotericsoftware.kryo.KryoException;
    Code:
       0: aload_0
       1: getfield      #2                  // Field varIntsEnabled:Z
       4: ifne          12
       7: aload_0
       8: invokevirtual #27                 // Method readInt:()I
      11: ireturn
      12: aload_0
      13: iload_1
      14: invokespecial #28                 // Method com/esotericsoftware/kryo/io/ByteBufferInput.readInt:(Z)I
      17: ireturn

  public long readLong(boolean) throws com.esotericsoftware.kryo.KryoException;
    Code:
       0: aload_0
       1: getfield      #2                  // Field varIntsEnabled:Z
       4: ifne          12
       7: aload_0
       8: invokevirtual #29                 // Method readLong:()J
      11: lreturn
      12: aload_0
      13: iload_1
      14: invokespecial #30                 // Method com/esotericsoftware/kryo/io/ByteBufferInput.readLong:(Z)J
      17: lreturn

  public final int[] readInts(int, boolean) throws com.esotericsoftware.kryo.KryoException;
    Code:
       0: aload_0
       1: getfield      #2                  // Field varIntsEnabled:Z
       4: ifne          30
       7: iload_1
       8: iconst_2
       9: ishl
      10: istore_3
      11: iload_1
      12: newarray       int
      14: astore        4
      16: aload_0
      17: aload         4
      19: getstatic     #31                 // Field com/esotericsoftware/kryo/util/UnsafeUtil.intArrayBaseOffset:J
      22: lconst_0
      23: iload_3
      24: invokespecial #32                 // Method readBytes:(Ljava/lang/Object;JJI)V
      27: aload         4
      29: areturn
      30: aload_0
      31: iload_1
      32: iload_2
      33: invokespecial #33                 // Method com/esotericsoftware/kryo/io/ByteBufferInput.readInts:(IZ)[I
      36: areturn

  public final long[] readLongs(int, boolean) throws com.esotericsoftware.kryo.KryoException;
    Code:
       0: aload_0
       1: getfield      #2                  // Field varIntsEnabled:Z
       4: ifne          30
       7: iload_1
       8: iconst_3
       9: ishl
      10: istore_3
      11: iload_1
      12: newarray       long
      14: astore        4
      16: aload_0
      17: aload         4
      19: getstatic     #34                 // Field com/esotericsoftware/kryo/util/UnsafeUtil.longArrayBaseOffset:J
      22: lconst_0
      23: iload_3
      24: invokespecial #32                 // Method readBytes:(Ljava/lang/Object;JJI)V
      27: aload         4
      29: areturn
      30: aload_0
      31: iload_1
      32: iload_2
      33: invokespecial #35                 // Method com/esotericsoftware/kryo/io/ByteBufferInput.readLongs:(IZ)[J
      36: areturn

  public final float[] readFloats(int) throws com.esotericsoftware.kryo.KryoException;
    Code:
       0: iload_1
       1: iconst_2
       2: ishl
       3: istore_2
       4: iload_1
       5: newarray       float
       7: astore_3
       8: aload_0
       9: aload_3
      10: getstatic     #36                 // Field com/esotericsoftware/kryo/util/UnsafeUtil.floatArrayBaseOffset:J
      13: lconst_0
      14: iload_2
      15: invokespecial #32                 // Method readBytes:(Ljava/lang/Object;JJI)V
      18: aload_3
      19: areturn

  public final short[] readShorts(int) throws com.esotericsoftware.kryo.KryoException;
    Code:
       0: iload_1
       1: iconst_1
       2: ishl
       3: istore_2
       4: iload_1
       5: newarray       short
       7: astore_3
       8: aload_0
       9: aload_3
      10: getstatic     #37                 // Field com/esotericsoftware/kryo/util/UnsafeUtil.shortArrayBaseOffset:J
      13: lconst_0
      14: iload_2
      15: invokespecial #32                 // Method readBytes:(Ljava/lang/Object;JJI)V
      18: aload_3
      19: areturn

  public final char[] readChars(int) throws com.esotericsoftware.kryo.KryoException;
    Code:
       0: iload_1
       1: iconst_1
       2: ishl
       3: istore_2
       4: iload_1
       5: newarray       char
       7: astore_3
       8: aload_0
       9: aload_3
      10: getstatic     #38                 // Field com/esotericsoftware/kryo/util/UnsafeUtil.charArrayBaseOffset:J
      13: lconst_0
      14: iload_2
      15: invokespecial #32                 // Method readBytes:(Ljava/lang/Object;JJI)V
      18: aload_3
      19: areturn

  public final double[] readDoubles(int) throws com.esotericsoftware.kryo.KryoException;
    Code:
       0: iload_1
       1: iconst_3
       2: ishl
       3: istore_2
       4: iload_1
       5: newarray       double
       7: astore_3
       8: aload_0
       9: aload_3
      10: getstatic     #39                 // Field com/esotericsoftware/kryo/util/UnsafeUtil.doubleArrayBaseOffset:J
      13: lconst_0
      14: iload_2
      15: invokespecial #32                 // Method readBytes:(Ljava/lang/Object;JJI)V
      18: aload_3
      19: areturn

  public byte[] readBytes(int) throws com.esotericsoftware.kryo.KryoException;
    Code:
       0: iload_1
       1: newarray       byte
       3: astore_2
       4: aload_0
       5: aload_2
       6: lconst_0
       7: aload_2
       8: arraylength
       9: i2l
      10: invokevirtual #40                 // Method readBytes:(Ljava/lang/Object;JJ)V
      13: aload_2
      14: areturn

  public final void readBytes(java.lang.Object, long, long) throws com.esotericsoftware.kryo.KryoException;
    Code:
       0: aload_1
       1: invokevirtual #41                 // Method java/lang/Object.getClass:()Ljava/lang/Class;
       4: invokevirtual #42                 // Method java/lang/Class.isArray:()Z
       7: ifeq          25
      10: aload_0
      11: aload_1
      12: getstatic     #43                 // Field com/esotericsoftware/kryo/util/UnsafeUtil.byteArrayBaseOffset:J
      15: lload_2
      16: lload         4
      18: l2i
      19: invokespecial #32                 // Method readBytes:(Ljava/lang/Object;JJI)V
      22: goto          35
      25: new           #44                 // class com/esotericsoftware/kryo/KryoException
      28: dup
      29: ldc           #45                 // String Only bulk reads of arrays is supported
      31: invokespecial #46                 // Method com/esotericsoftware/kryo/KryoException."<init>":(Ljava/lang/String;)V
      34: athrow
      35: return

  private final void readBytes(java.lang.Object, long, long, int) throws com.esotericsoftware.kryo.KryoException;
    Code:
       0: aload_0
       1: getfield      #47                 // Field limit:I
       4: aload_0
       5: getfield      #17                 // Field position:I
       8: isub
       9: iload         6
      11: invokestatic  #48                 // Method java/lang/Math.min:(II)I
      14: istore        7
      16: invokestatic  #16                 // Method com/esotericsoftware/kryo/util/UnsafeUtil.unsafe:()Lsun/misc/Unsafe;
      19: aconst_null
      20: aload_0
      21: getfield      #14                 // Field bufaddress:J
      24: aload_0
      25: getfield      #17                 // Field position:I
      28: i2l
      29: ladd
      30: aload_1
      31: lload_2
      32: lload         4
      34: ladd
      35: iload         7
      37: i2l
      38: invokevirtual #49                 // Method sun/misc/Unsafe.copyMemory:(Ljava/lang/Object;JLjava/lang/Object;JJ)V
      41: aload_0
      42: dup
      43: getfield      #17                 // Field position:I
      46: iload         7
      48: iadd
      49: putfield      #17                 // Field position:I
      52: iload         6
      54: iload         7
      56: isub
      57: istore        6
      59: iload         6
      61: ifne          67
      64: goto          96
      67: lload         4
      69: iload         7
      71: i2l
      72: ladd
      73: lstore        4
      75: iload         6
      77: aload_0
      78: getfield      #50                 // Field capacity:I
      81: invokestatic  #48                 // Method java/lang/Math.min:(II)I
      84: istore        7
      86: aload_0
      87: iload         7
      89: invokevirtual #15                 // Method require:(I)I
      92: pop
      93: goto          16
      96: return
}
