Compiled from "SpringApplicationAdminJmxAutoConfiguration.java"
public class org.springframework.boot.autoconfigure.admin.SpringApplicationAdminJmxAutoConfiguration {
  private static final java.lang.String JMX_NAME_PROPERTY;

  private static final java.lang.String DEFAULT_JMX_NAME;

  private final java.util.List<org.springframework.jmx.export.MBeanExporter> mbeanExporters;

  private final org.springframework.core.env.Environment environment;

  public org.springframework.boot.autoconfigure.admin.SpringApplicationAdminJmxAutoConfiguration(org.springframework.beans.factory.ObjectProvider<java.util.List<org.springframework.jmx.export.MBeanExporter>>, org.springframework.core.env.Environment);
    Code:
       0: aload_0
       1: invokespecial #1                  // Method java/lang/Object."<init>":()V
       4: aload_0
       5: aload_1
       6: invokeinterface #2,  1            // InterfaceMethod org/springframework/beans/factory/ObjectProvider.getIfAvailable:()Ljava/lang/Object;
      11: checkcast     #3                  // class java/util/List
      14: putfield      #4                  // Field mbeanExporters:Ljava/util/List;
      17: aload_0
      18: aload_2
      19: putfield      #5                  // Field environment:Lorg/springframework/core/env/Environment;
      22: return

  public org.springframework.boot.admin.SpringApplicationAdminMXBeanRegistrar springApplicationAdminRegistrar() throws javax.management.MalformedObjectNameException;
    Code:
       0: aload_0
       1: getfield      #5                  // Field environment:Lorg/springframework/core/env/Environment;
       4: ldc           #7                  // String spring.application.admin.jmx-name
       6: ldc           #8                  // String org.springframework.boot:type=Admin,name=SpringApplication
       8: invokeinterface #9,  3            // InterfaceMethod org/springframework/core/env/Environment.getProperty:(Ljava/lang/String;Ljava/lang/String;)Ljava/lang/String;
      13: astore_1
      14: aload_0
      15: getfield      #4                  // Field mbeanExporters:Ljava/util/List;
      18: ifnull        58
      21: aload_0
      22: getfield      #4                  // Field mbeanExporters:Ljava/util/List;
      25: invokeinterface #10,  1           // InterfaceMethod java/util/List.iterator:()Ljava/util/Iterator;
      30: astore_2
      31: aload_2
      32: invokeinterface #11,  1           // InterfaceMethod java/util/Iterator.hasNext:()Z
      37: ifeq          58
      40: aload_2
      41: invokeinterface #12,  1           // InterfaceMethod java/util/Iterator.next:()Ljava/lang/Object;
      46: checkcast     #13                 // class org/springframework/jmx/export/MBeanExporter
      49: astore_3
      50: aload_3
      51: aload_1
      52: invokevirtual #14                 // Method org/springframework/jmx/export/MBeanExporter.addExcludedBean:(Ljava/lang/String;)V
      55: goto          31
      58: new           #15                 // class org/springframework/boot/admin/SpringApplicationAdminMXBeanRegistrar
      61: dup
      62: aload_1
      63: invokespecial #16                 // Method org/springframework/boot/admin/SpringApplicationAdminMXBeanRegistrar."<init>":(Ljava/lang/String;)V
      66: areturn
}
