Compiled from "DeleteBucketReplicationResponse.java"
final class software.amazon.awssdk.services.s3control.model.DeleteBucketReplicationResponse$BuilderImpl extends software.amazon.awssdk.services.s3control.model.S3ControlResponse$BuilderImpl implements software.amazon.awssdk.services.s3control.model.DeleteBucketReplicationResponse$Builder {
  private software.amazon.awssdk.services.s3control.model.DeleteBucketReplicationResponse$BuilderImpl();
    Code:
       0: aload_0
       1: invokespecial #3                  // Method software/amazon/awssdk/services/s3control/model/S3ControlResponse$BuilderImpl."<init>":()V
       4: return

  private software.amazon.awssdk.services.s3control.model.DeleteBucketReplicationResponse$BuilderImpl(software.amazon.awssdk.services.s3control.model.DeleteBucketReplicationResponse);
    Code:
       0: aload_0
       1: aload_1
       2: invokespecial #4                  // Method software/amazon/awssdk/services/s3control/model/S3ControlResponse$BuilderImpl."<init>":(Lsoftware/amazon/awssdk/services/s3control/model/S3ControlResponse;)V
       5: return

  public software.amazon.awssdk.services.s3control.model.DeleteBucketReplicationResponse build();
    Code:
       0: new           #5                  // class software/amazon/awssdk/services/s3control/model/DeleteBucketReplicationResponse
       3: dup
       4: aload_0
       5: aconst_null
       6: invokespecial #6                  // Method software/amazon/awssdk/services/s3control/model/DeleteBucketReplicationResponse."<init>":(Lsoftware/amazon/awssdk/services/s3control/model/DeleteBucketReplicationResponse$BuilderImpl;Lsoftware/amazon/awssdk/services/s3control/model/DeleteBucketReplicationResponse$1;)V
       9: areturn

  public java.util.List<software.amazon.awssdk.core.SdkField<?>> sdkFields();
    Code:
       0: invokestatic  #7                  // Method software/amazon/awssdk/services/s3control/model/DeleteBucketReplicationResponse.access$300:()Ljava/util/List;
       3: areturn

  public software.amazon.awssdk.services.s3control.model.S3ControlResponse build();
    Code:
       0: aload_0
       1: invokevirtual #8                  // Method build:()Lsoftware/amazon/awssdk/services/s3control/model/DeleteBucketReplicationResponse;
       4: areturn

  public software.amazon.awssdk.awscore.AwsResponse build();
    Code:
       0: aload_0
       1: invokevirtual #8                  // Method build:()Lsoftware/amazon/awssdk/services/s3control/model/DeleteBucketReplicationResponse;
       4: areturn

  public software.amazon.awssdk.core.SdkResponse build();
    Code:
       0: aload_0
       1: invokevirtual #8                  // Method build:()Lsoftware/amazon/awssdk/services/s3control/model/DeleteBucketReplicationResponse;
       4: areturn

  public java.lang.Object build();
    Code:
       0: aload_0
       1: invokevirtual #8                  // Method build:()Lsoftware/amazon/awssdk/services/s3control/model/DeleteBucketReplicationResponse;
       4: areturn

  software.amazon.awssdk.services.s3control.model.DeleteBucketReplicationResponse$BuilderImpl(software.amazon.awssdk.services.s3control.model.DeleteBucketReplicationResponse, software.amazon.awssdk.services.s3control.model.DeleteBucketReplicationResponse$1);
    Code:
       0: aload_0
       1: aload_1
       2: invokespecial #2                  // Method "<init>":(Lsoftware/amazon/awssdk/services/s3control/model/DeleteBucketReplicationResponse;)V
       5: return

  software.amazon.awssdk.services.s3control.model.DeleteBucketReplicationResponse$BuilderImpl(software.amazon.awssdk.services.s3control.model.DeleteBucketReplicationResponse$1);
    Code:
       0: aload_0
       1: invokespecial #1                  // Method "<init>":()V
       4: return
}
