Compiled from "GeneratedManifestEncryption.java"
final class software.amazon.awssdk.services.s3control.model.GeneratedManifestEncryption$BuilderImpl implements software.amazon.awssdk.services.s3control.model.GeneratedManifestEncryption$Builder {
  private software.amazon.awssdk.services.s3control.model.SSES3Encryption sses3;

  private software.amazon.awssdk.services.s3control.model.SSEKMSEncryption ssekms;

  private software.amazon.awssdk.services.s3control.model.GeneratedManifestEncryption$BuilderImpl();
    Code:
       0: aload_0
       1: invokespecial #5                  // Method java/lang/Object."<init>":()V
       4: return

  private software.amazon.awssdk.services.s3control.model.GeneratedManifestEncryption$BuilderImpl(software.amazon.awssdk.services.s3control.model.GeneratedManifestEncryption);
    Code:
       0: aload_0
       1: invokespecial #5                  // Method java/lang/Object."<init>":()V
       4: aload_0
       5: aload_1
       6: invokestatic  #6                  // Method software/amazon/awssdk/services/s3control/model/GeneratedManifestEncryption.access$400:(Lsoftware/amazon/awssdk/services/s3control/model/GeneratedManifestEncryption;)Lsoftware/amazon/awssdk/services/s3control/model/SSES3Encryption;
       9: invokevirtual #7                  // Method sses3:(Lsoftware/amazon/awssdk/services/s3control/model/SSES3Encryption;)Lsoftware/amazon/awssdk/services/s3control/model/GeneratedManifestEncryption$Builder;
      12: pop
      13: aload_0
      14: aload_1
      15: invokestatic  #8                  // Method software/amazon/awssdk/services/s3control/model/GeneratedManifestEncryption.access$500:(Lsoftware/amazon/awssdk/services/s3control/model/GeneratedManifestEncryption;)Lsoftware/amazon/awssdk/services/s3control/model/SSEKMSEncryption;
      18: invokevirtual #9                  // Method ssekms:(Lsoftware/amazon/awssdk/services/s3control/model/SSEKMSEncryption;)Lsoftware/amazon/awssdk/services/s3control/model/GeneratedManifestEncryption$Builder;
      21: pop
      22: return

  public final software.amazon.awssdk.services.s3control.model.SSES3Encryption$Builder getSses3();
    Code:
       0: aload_0
       1: getfield      #4                  // Field sses3:Lsoftware/amazon/awssdk/services/s3control/model/SSES3Encryption;
       4: ifnull        17
       7: aload_0
       8: getfield      #4                  // Field sses3:Lsoftware/amazon/awssdk/services/s3control/model/SSES3Encryption;
      11: invokevirtual #10                 // Method software/amazon/awssdk/services/s3control/model/SSES3Encryption.toBuilder:()Lsoftware/amazon/awssdk/services/s3control/model/SSES3Encryption$Builder;
      14: goto          18
      17: aconst_null
      18: areturn

  public final void setSses3(software.amazon.awssdk.services.s3control.model.SSES3Encryption$BuilderImpl);
    Code:
       0: aload_0
       1: aload_1
       2: ifnull        12
       5: aload_1
       6: invokevirtual #11                 // Method software/amazon/awssdk/services/s3control/model/SSES3Encryption$BuilderImpl.build:()Lsoftware/amazon/awssdk/services/s3control/model/SSES3Encryption;
       9: goto          13
      12: aconst_null
      13: putfield      #4                  // Field sses3:Lsoftware/amazon/awssdk/services/s3control/model/SSES3Encryption;
      16: return

  public final software.amazon.awssdk.services.s3control.model.GeneratedManifestEncryption$Builder sses3(software.amazon.awssdk.services.s3control.model.SSES3Encryption);
    Code:
       0: aload_0
       1: aload_1
       2: putfield      #4                  // Field sses3:Lsoftware/amazon/awssdk/services/s3control/model/SSES3Encryption;
       5: aload_0
       6: areturn

  public final software.amazon.awssdk.services.s3control.model.SSEKMSEncryption$Builder getSsekms();
    Code:
       0: aload_0
       1: getfield      #3                  // Field ssekms:Lsoftware/amazon/awssdk/services/s3control/model/SSEKMSEncryption;
       4: ifnull        17
       7: aload_0
       8: getfield      #3                  // Field ssekms:Lsoftware/amazon/awssdk/services/s3control/model/SSEKMSEncryption;
      11: invokevirtual #12                 // Method software/amazon/awssdk/services/s3control/model/SSEKMSEncryption.toBuilder:()Lsoftware/amazon/awssdk/services/s3control/model/SSEKMSEncryption$Builder;
      14: goto          18
      17: aconst_null
      18: areturn

  public final void setSsekms(software.amazon.awssdk.services.s3control.model.SSEKMSEncryption$BuilderImpl);
    Code:
       0: aload_0
       1: aload_1
       2: ifnull        12
       5: aload_1
       6: invokevirtual #13                 // Method software/amazon/awssdk/services/s3control/model/SSEKMSEncryption$BuilderImpl.build:()Lsoftware/amazon/awssdk/services/s3control/model/SSEKMSEncryption;
       9: goto          13
      12: aconst_null
      13: putfield      #3                  // Field ssekms:Lsoftware/amazon/awssdk/services/s3control/model/SSEKMSEncryption;
      16: return

  public final software.amazon.awssdk.services.s3control.model.GeneratedManifestEncryption$Builder ssekms(software.amazon.awssdk.services.s3control.model.SSEKMSEncryption);
    Code:
       0: aload_0
       1: aload_1
       2: putfield      #3                  // Field ssekms:Lsoftware/amazon/awssdk/services/s3control/model/SSEKMSEncryption;
       5: aload_0
       6: areturn

  public software.amazon.awssdk.services.s3control.model.GeneratedManifestEncryption build();
    Code:
       0: new           #14                 // class software/amazon/awssdk/services/s3control/model/GeneratedManifestEncryption
       3: dup
       4: aload_0
       5: aconst_null
       6: invokespecial #15                 // Method software/amazon/awssdk/services/s3control/model/GeneratedManifestEncryption."<init>":(Lsoftware/amazon/awssdk/services/s3control/model/GeneratedManifestEncryption$BuilderImpl;Lsoftware/amazon/awssdk/services/s3control/model/GeneratedManifestEncryption$1;)V
       9: areturn

  public java.util.List<software.amazon.awssdk.core.SdkField<?>> sdkFields();
    Code:
       0: invokestatic  #16                 // Method software/amazon/awssdk/services/s3control/model/GeneratedManifestEncryption.access$700:()Ljava/util/List;
       3: areturn

  public java.lang.Object build();
    Code:
       0: aload_0
       1: invokevirtual #17                 // Method build:()Lsoftware/amazon/awssdk/services/s3control/model/GeneratedManifestEncryption;
       4: areturn

  static software.amazon.awssdk.services.s3control.model.SSES3Encryption access$000(software.amazon.awssdk.services.s3control.model.GeneratedManifestEncryption$BuilderImpl);
    Code:
       0: aload_0
       1: getfield      #4                  // Field sses3:Lsoftware/amazon/awssdk/services/s3control/model/SSES3Encryption;
       4: areturn

  static software.amazon.awssdk.services.s3control.model.SSEKMSEncryption access$100(software.amazon.awssdk.services.s3control.model.GeneratedManifestEncryption$BuilderImpl);
    Code:
       0: aload_0
       1: getfield      #3                  // Field ssekms:Lsoftware/amazon/awssdk/services/s3control/model/SSEKMSEncryption;
       4: areturn

  software.amazon.awssdk.services.s3control.model.GeneratedManifestEncryption$BuilderImpl(software.amazon.awssdk.services.s3control.model.GeneratedManifestEncryption, software.amazon.awssdk.services.s3control.model.GeneratedManifestEncryption$1);
    Code:
       0: aload_0
       1: aload_1
       2: invokespecial #2                  // Method "<init>":(Lsoftware/amazon/awssdk/services/s3control/model/GeneratedManifestEncryption;)V
       5: return

  software.amazon.awssdk.services.s3control.model.GeneratedManifestEncryption$BuilderImpl(software.amazon.awssdk.services.s3control.model.GeneratedManifestEncryption$1);
    Code:
       0: aload_0
       1: invokespecial #1                  // Method "<init>":()V
       4: return
}
