Compiled from "GetMultiRegionAccessPointResponse.java"
final class software.amazon.awssdk.services.s3control.model.GetMultiRegionAccessPointResponse$BuilderImpl extends software.amazon.awssdk.services.s3control.model.S3ControlResponse$BuilderImpl implements software.amazon.awssdk.services.s3control.model.GetMultiRegionAccessPointResponse$Builder {
  private software.amazon.awssdk.services.s3control.model.MultiRegionAccessPointReport accessPoint;

  private software.amazon.awssdk.services.s3control.model.GetMultiRegionAccessPointResponse$BuilderImpl();
    Code:
       0: aload_0
       1: invokespecial #4                  // Method software/amazon/awssdk/services/s3control/model/S3ControlResponse$BuilderImpl."<init>":()V
       4: return

  private software.amazon.awssdk.services.s3control.model.GetMultiRegionAccessPointResponse$BuilderImpl(software.amazon.awssdk.services.s3control.model.GetMultiRegionAccessPointResponse);
    Code:
       0: aload_0
       1: aload_1
       2: invokespecial #5                  // Method software/amazon/awssdk/services/s3control/model/S3ControlResponse$BuilderImpl."<init>":(Lsoftware/amazon/awssdk/services/s3control/model/S3ControlResponse;)V
       5: aload_0
       6: aload_1
       7: invokestatic  #6                  // Method software/amazon/awssdk/services/s3control/model/GetMultiRegionAccessPointResponse.access$300:(Lsoftware/amazon/awssdk/services/s3control/model/GetMultiRegionAccessPointResponse;)Lsoftware/amazon/awssdk/services/s3control/model/MultiRegionAccessPointReport;
      10: invokevirtual #7                  // Method accessPoint:(Lsoftware/amazon/awssdk/services/s3control/model/MultiRegionAccessPointReport;)Lsoftware/amazon/awssdk/services/s3control/model/GetMultiRegionAccessPointResponse$Builder;
      13: pop
      14: return

  public final software.amazon.awssdk.services.s3control.model.MultiRegionAccessPointReport$Builder getAccessPoint();
    Code:
       0: aload_0
       1: getfield      #3                  // Field accessPoint:Lsoftware/amazon/awssdk/services/s3control/model/MultiRegionAccessPointReport;
       4: ifnull        17
       7: aload_0
       8: getfield      #3                  // Field accessPoint:Lsoftware/amazon/awssdk/services/s3control/model/MultiRegionAccessPointReport;
      11: invokevirtual #8                  // Method software/amazon/awssdk/services/s3control/model/MultiRegionAccessPointReport.toBuilder:()Lsoftware/amazon/awssdk/services/s3control/model/MultiRegionAccessPointReport$Builder;
      14: goto          18
      17: aconst_null
      18: areturn

  public final void setAccessPoint(software.amazon.awssdk.services.s3control.model.MultiRegionAccessPointReport$BuilderImpl);
    Code:
       0: aload_0
       1: aload_1
       2: ifnull        12
       5: aload_1
       6: invokevirtual #9                  // Method software/amazon/awssdk/services/s3control/model/MultiRegionAccessPointReport$BuilderImpl.build:()Lsoftware/amazon/awssdk/services/s3control/model/MultiRegionAccessPointReport;
       9: goto          13
      12: aconst_null
      13: putfield      #3                  // Field accessPoint:Lsoftware/amazon/awssdk/services/s3control/model/MultiRegionAccessPointReport;
      16: return

  public final software.amazon.awssdk.services.s3control.model.GetMultiRegionAccessPointResponse$Builder accessPoint(software.amazon.awssdk.services.s3control.model.MultiRegionAccessPointReport);
    Code:
       0: aload_0
       1: aload_1
       2: putfield      #3                  // Field accessPoint:Lsoftware/amazon/awssdk/services/s3control/model/MultiRegionAccessPointReport;
       5: aload_0
       6: areturn

  public software.amazon.awssdk.services.s3control.model.GetMultiRegionAccessPointResponse build();
    Code:
       0: new           #10                 // class software/amazon/awssdk/services/s3control/model/GetMultiRegionAccessPointResponse
       3: dup
       4: aload_0
       5: aconst_null
       6: invokespecial #11                 // Method software/amazon/awssdk/services/s3control/model/GetMultiRegionAccessPointResponse."<init>":(Lsoftware/amazon/awssdk/services/s3control/model/GetMultiRegionAccessPointResponse$BuilderImpl;Lsoftware/amazon/awssdk/services/s3control/model/GetMultiRegionAccessPointResponse$1;)V
       9: areturn

  public java.util.List<software.amazon.awssdk.core.SdkField<?>> sdkFields();
    Code:
       0: invokestatic  #12                 // Method software/amazon/awssdk/services/s3control/model/GetMultiRegionAccessPointResponse.access$500:()Ljava/util/List;
       3: areturn

  public software.amazon.awssdk.services.s3control.model.S3ControlResponse build();
    Code:
       0: aload_0
       1: invokevirtual #13                 // Method build:()Lsoftware/amazon/awssdk/services/s3control/model/GetMultiRegionAccessPointResponse;
       4: areturn

  public software.amazon.awssdk.awscore.AwsResponse build();
    Code:
       0: aload_0
       1: invokevirtual #13                 // Method build:()Lsoftware/amazon/awssdk/services/s3control/model/GetMultiRegionAccessPointResponse;
       4: areturn

  public software.amazon.awssdk.core.SdkResponse build();
    Code:
       0: aload_0
       1: invokevirtual #13                 // Method build:()Lsoftware/amazon/awssdk/services/s3control/model/GetMultiRegionAccessPointResponse;
       4: areturn

  public java.lang.Object build();
    Code:
       0: aload_0
       1: invokevirtual #13                 // Method build:()Lsoftware/amazon/awssdk/services/s3control/model/GetMultiRegionAccessPointResponse;
       4: areturn

  static software.amazon.awssdk.services.s3control.model.MultiRegionAccessPointReport access$000(software.amazon.awssdk.services.s3control.model.GetMultiRegionAccessPointResponse$BuilderImpl);
    Code:
       0: aload_0
       1: getfield      #3                  // Field accessPoint:Lsoftware/amazon/awssdk/services/s3control/model/MultiRegionAccessPointReport;
       4: areturn

  software.amazon.awssdk.services.s3control.model.GetMultiRegionAccessPointResponse$BuilderImpl(software.amazon.awssdk.services.s3control.model.GetMultiRegionAccessPointResponse, software.amazon.awssdk.services.s3control.model.GetMultiRegionAccessPointResponse$1);
    Code:
       0: aload_0
       1: aload_1
       2: invokespecial #2                  // Method "<init>":(Lsoftware/amazon/awssdk/services/s3control/model/GetMultiRegionAccessPointResponse;)V
       5: return

  software.amazon.awssdk.services.s3control.model.GetMultiRegionAccessPointResponse$BuilderImpl(software.amazon.awssdk.services.s3control.model.GetMultiRegionAccessPointResponse$1);
    Code:
       0: aload_0
       1: invokespecial #1                  // Method "<init>":()V
       4: return
}
