Compiled from "JobListDescriptor.java"
final class software.amazon.awssdk.services.s3control.model.JobListDescriptor$BuilderImpl implements software.amazon.awssdk.services.s3control.model.JobListDescriptor$Builder {
  private java.lang.String jobId;

  private java.lang.String description;

  private java.lang.String operation;

  private java.lang.Integer priority;

  private java.lang.String status;

  private java.time.Instant creationTime;

  private java.time.Instant terminationDate;

  private software.amazon.awssdk.services.s3control.model.JobProgressSummary progressSummary;

  private software.amazon.awssdk.services.s3control.model.JobListDescriptor$BuilderImpl();
    Code:
       0: aload_0
       1: invokespecial #11                 // Method java/lang/Object."<init>":()V
       4: return

  private software.amazon.awssdk.services.s3control.model.JobListDescriptor$BuilderImpl(software.amazon.awssdk.services.s3control.model.JobListDescriptor);
    Code:
       0: aload_0
       1: invokespecial #11                 // Method java/lang/Object."<init>":()V
       4: aload_0
       5: aload_1
       6: invokestatic  #12                 // Method software/amazon/awssdk/services/s3control/model/JobListDescriptor.access$1000:(Lsoftware/amazon/awssdk/services/s3control/model/JobListDescriptor;)Ljava/lang/String;
       9: invokevirtual #13                 // Method jobId:(Ljava/lang/String;)Lsoftware/amazon/awssdk/services/s3control/model/JobListDescriptor$Builder;
      12: pop
      13: aload_0
      14: aload_1
      15: invokestatic  #14                 // Method software/amazon/awssdk/services/s3control/model/JobListDescriptor.access$1100:(Lsoftware/amazon/awssdk/services/s3control/model/JobListDescriptor;)Ljava/lang/String;
      18: invokevirtual #15                 // Method description:(Ljava/lang/String;)Lsoftware/amazon/awssdk/services/s3control/model/JobListDescriptor$Builder;
      21: pop
      22: aload_0
      23: aload_1
      24: invokestatic  #16                 // Method software/amazon/awssdk/services/s3control/model/JobListDescriptor.access$1200:(Lsoftware/amazon/awssdk/services/s3control/model/JobListDescriptor;)Ljava/lang/String;
      27: invokevirtual #17                 // Method operation:(Ljava/lang/String;)Lsoftware/amazon/awssdk/services/s3control/model/JobListDescriptor$Builder;
      30: pop
      31: aload_0
      32: aload_1
      33: invokestatic  #18                 // Method software/amazon/awssdk/services/s3control/model/JobListDescriptor.access$1300:(Lsoftware/amazon/awssdk/services/s3control/model/JobListDescriptor;)Ljava/lang/Integer;
      36: invokevirtual #19                 // Method priority:(Ljava/lang/Integer;)Lsoftware/amazon/awssdk/services/s3control/model/JobListDescriptor$Builder;
      39: pop
      40: aload_0
      41: aload_1
      42: invokestatic  #20                 // Method software/amazon/awssdk/services/s3control/model/JobListDescriptor.access$1400:(Lsoftware/amazon/awssdk/services/s3control/model/JobListDescriptor;)Ljava/lang/String;
      45: invokevirtual #21                 // Method status:(Ljava/lang/String;)Lsoftware/amazon/awssdk/services/s3control/model/JobListDescriptor$Builder;
      48: pop
      49: aload_0
      50: aload_1
      51: invokestatic  #22                 // Method software/amazon/awssdk/services/s3control/model/JobListDescriptor.access$1500:(Lsoftware/amazon/awssdk/services/s3control/model/JobListDescriptor;)Ljava/time/Instant;
      54: invokevirtual #23                 // Method creationTime:(Ljava/time/Instant;)Lsoftware/amazon/awssdk/services/s3control/model/JobListDescriptor$Builder;
      57: pop
      58: aload_0
      59: aload_1
      60: invokestatic  #24                 // Method software/amazon/awssdk/services/s3control/model/JobListDescriptor.access$1600:(Lsoftware/amazon/awssdk/services/s3control/model/JobListDescriptor;)Ljava/time/Instant;
      63: invokevirtual #25                 // Method terminationDate:(Ljava/time/Instant;)Lsoftware/amazon/awssdk/services/s3control/model/JobListDescriptor$Builder;
      66: pop
      67: aload_0
      68: aload_1
      69: invokestatic  #26                 // Method software/amazon/awssdk/services/s3control/model/JobListDescriptor.access$1700:(Lsoftware/amazon/awssdk/services/s3control/model/JobListDescriptor;)Lsoftware/amazon/awssdk/services/s3control/model/JobProgressSummary;
      72: invokevirtual #27                 // Method progressSummary:(Lsoftware/amazon/awssdk/services/s3control/model/JobProgressSummary;)Lsoftware/amazon/awssdk/services/s3control/model/JobListDescriptor$Builder;
      75: pop
      76: return

  public final java.lang.String getJobId();
    Code:
       0: aload_0
       1: getfield      #10                 // Field jobId:Ljava/lang/String;
       4: areturn

  public final void setJobId(java.lang.String);
    Code:
       0: aload_0
       1: aload_1
       2: putfield      #10                 // Field jobId:Ljava/lang/String;
       5: return

  public final software.amazon.awssdk.services.s3control.model.JobListDescriptor$Builder jobId(java.lang.String);
    Code:
       0: aload_0
       1: aload_1
       2: putfield      #10                 // Field jobId:Ljava/lang/String;
       5: aload_0
       6: areturn

  public final java.lang.String getDescription();
    Code:
       0: aload_0
       1: getfield      #9                  // Field description:Ljava/lang/String;
       4: areturn

  public final void setDescription(java.lang.String);
    Code:
       0: aload_0
       1: aload_1
       2: putfield      #9                  // Field description:Ljava/lang/String;
       5: return

  public final software.amazon.awssdk.services.s3control.model.JobListDescriptor$Builder description(java.lang.String);
    Code:
       0: aload_0
       1: aload_1
       2: putfield      #9                  // Field description:Ljava/lang/String;
       5: aload_0
       6: areturn

  public final java.lang.String getOperation();
    Code:
       0: aload_0
       1: getfield      #8                  // Field operation:Ljava/lang/String;
       4: areturn

  public final void setOperation(java.lang.String);
    Code:
       0: aload_0
       1: aload_1
       2: putfield      #8                  // Field operation:Ljava/lang/String;
       5: return

  public final software.amazon.awssdk.services.s3control.model.JobListDescriptor$Builder operation(java.lang.String);
    Code:
       0: aload_0
       1: aload_1
       2: putfield      #8                  // Field operation:Ljava/lang/String;
       5: aload_0
       6: areturn

  public final software.amazon.awssdk.services.s3control.model.JobListDescriptor$Builder operation(software.amazon.awssdk.services.s3control.model.OperationName);
    Code:
       0: aload_0
       1: aload_1
       2: ifnonnull     9
       5: aconst_null
       6: goto          13
       9: aload_1
      10: invokevirtual #28                 // Method software/amazon/awssdk/services/s3control/model/OperationName.toString:()Ljava/lang/String;
      13: invokevirtual #17                 // Method operation:(Ljava/lang/String;)Lsoftware/amazon/awssdk/services/s3control/model/JobListDescriptor$Builder;
      16: pop
      17: aload_0
      18: areturn

  public final java.lang.Integer getPriority();
    Code:
       0: aload_0
       1: getfield      #7                  // Field priority:Ljava/lang/Integer;
       4: areturn

  public final void setPriority(java.lang.Integer);
    Code:
       0: aload_0
       1: aload_1
       2: putfield      #7                  // Field priority:Ljava/lang/Integer;
       5: return

  public final software.amazon.awssdk.services.s3control.model.JobListDescriptor$Builder priority(java.lang.Integer);
    Code:
       0: aload_0
       1: aload_1
       2: putfield      #7                  // Field priority:Ljava/lang/Integer;
       5: aload_0
       6: areturn

  public final java.lang.String getStatus();
    Code:
       0: aload_0
       1: getfield      #6                  // Field status:Ljava/lang/String;
       4: areturn

  public final void setStatus(java.lang.String);
    Code:
       0: aload_0
       1: aload_1
       2: putfield      #6                  // Field status:Ljava/lang/String;
       5: return

  public final software.amazon.awssdk.services.s3control.model.JobListDescriptor$Builder status(java.lang.String);
    Code:
       0: aload_0
       1: aload_1
       2: putfield      #6                  // Field status:Ljava/lang/String;
       5: aload_0
       6: areturn

  public final software.amazon.awssdk.services.s3control.model.JobListDescriptor$Builder status(software.amazon.awssdk.services.s3control.model.JobStatus);
    Code:
       0: aload_0
       1: aload_1
       2: ifnonnull     9
       5: aconst_null
       6: goto          13
       9: aload_1
      10: invokevirtual #29                 // Method software/amazon/awssdk/services/s3control/model/JobStatus.toString:()Ljava/lang/String;
      13: invokevirtual #21                 // Method status:(Ljava/lang/String;)Lsoftware/amazon/awssdk/services/s3control/model/JobListDescriptor$Builder;
      16: pop
      17: aload_0
      18: areturn

  public final java.time.Instant getCreationTime();
    Code:
       0: aload_0
       1: getfield      #5                  // Field creationTime:Ljava/time/Instant;
       4: areturn

  public final void setCreationTime(java.time.Instant);
    Code:
       0: aload_0
       1: aload_1
       2: putfield      #5                  // Field creationTime:Ljava/time/Instant;
       5: return

  public final software.amazon.awssdk.services.s3control.model.JobListDescriptor$Builder creationTime(java.time.Instant);
    Code:
       0: aload_0
       1: aload_1
       2: putfield      #5                  // Field creationTime:Ljava/time/Instant;
       5: aload_0
       6: areturn

  public final java.time.Instant getTerminationDate();
    Code:
       0: aload_0
       1: getfield      #4                  // Field terminationDate:Ljava/time/Instant;
       4: areturn

  public final void setTerminationDate(java.time.Instant);
    Code:
       0: aload_0
       1: aload_1
       2: putfield      #4                  // Field terminationDate:Ljava/time/Instant;
       5: return

  public final software.amazon.awssdk.services.s3control.model.JobListDescriptor$Builder terminationDate(java.time.Instant);
    Code:
       0: aload_0
       1: aload_1
       2: putfield      #4                  // Field terminationDate:Ljava/time/Instant;
       5: aload_0
       6: areturn

  public final software.amazon.awssdk.services.s3control.model.JobProgressSummary$Builder getProgressSummary();
    Code:
       0: aload_0
       1: getfield      #3                  // Field progressSummary:Lsoftware/amazon/awssdk/services/s3control/model/JobProgressSummary;
       4: ifnull        17
       7: aload_0
       8: getfield      #3                  // Field progressSummary:Lsoftware/amazon/awssdk/services/s3control/model/JobProgressSummary;
      11: invokevirtual #30                 // Method software/amazon/awssdk/services/s3control/model/JobProgressSummary.toBuilder:()Lsoftware/amazon/awssdk/services/s3control/model/JobProgressSummary$Builder;
      14: goto          18
      17: aconst_null
      18: areturn

  public final void setProgressSummary(software.amazon.awssdk.services.s3control.model.JobProgressSummary$BuilderImpl);
    Code:
       0: aload_0
       1: aload_1
       2: ifnull        12
       5: aload_1
       6: invokevirtual #31                 // Method software/amazon/awssdk/services/s3control/model/JobProgressSummary$BuilderImpl.build:()Lsoftware/amazon/awssdk/services/s3control/model/JobProgressSummary;
       9: goto          13
      12: aconst_null
      13: putfield      #3                  // Field progressSummary:Lsoftware/amazon/awssdk/services/s3control/model/JobProgressSummary;
      16: return

  public final software.amazon.awssdk.services.s3control.model.JobListDescriptor$Builder progressSummary(software.amazon.awssdk.services.s3control.model.JobProgressSummary);
    Code:
       0: aload_0
       1: aload_1
       2: putfield      #3                  // Field progressSummary:Lsoftware/amazon/awssdk/services/s3control/model/JobProgressSummary;
       5: aload_0
       6: areturn

  public software.amazon.awssdk.services.s3control.model.JobListDescriptor build();
    Code:
       0: new           #32                 // class software/amazon/awssdk/services/s3control/model/JobListDescriptor
       3: dup
       4: aload_0
       5: aconst_null
       6: invokespecial #33                 // Method software/amazon/awssdk/services/s3control/model/JobListDescriptor."<init>":(Lsoftware/amazon/awssdk/services/s3control/model/JobListDescriptor$BuilderImpl;Lsoftware/amazon/awssdk/services/s3control/model/JobListDescriptor$1;)V
       9: areturn

  public java.util.List<software.amazon.awssdk.core.SdkField<?>> sdkFields();
    Code:
       0: invokestatic  #34                 // Method software/amazon/awssdk/services/s3control/model/JobListDescriptor.access$1900:()Ljava/util/List;
       3: areturn

  public java.lang.Object build();
    Code:
       0: aload_0
       1: invokevirtual #35                 // Method build:()Lsoftware/amazon/awssdk/services/s3control/model/JobListDescriptor;
       4: areturn

  static java.lang.String access$000(software.amazon.awssdk.services.s3control.model.JobListDescriptor$BuilderImpl);
    Code:
       0: aload_0
       1: getfield      #10                 // Field jobId:Ljava/lang/String;
       4: areturn

  static java.lang.String access$100(software.amazon.awssdk.services.s3control.model.JobListDescriptor$BuilderImpl);
    Code:
       0: aload_0
       1: getfield      #9                  // Field description:Ljava/lang/String;
       4: areturn

  static java.lang.String access$200(software.amazon.awssdk.services.s3control.model.JobListDescriptor$BuilderImpl);
    Code:
       0: aload_0
       1: getfield      #8                  // Field operation:Ljava/lang/String;
       4: areturn

  static java.lang.Integer access$300(software.amazon.awssdk.services.s3control.model.JobListDescriptor$BuilderImpl);
    Code:
       0: aload_0
       1: getfield      #7                  // Field priority:Ljava/lang/Integer;
       4: areturn

  static java.lang.String access$400(software.amazon.awssdk.services.s3control.model.JobListDescriptor$BuilderImpl);
    Code:
       0: aload_0
       1: getfield      #6                  // Field status:Ljava/lang/String;
       4: areturn

  static java.time.Instant access$500(software.amazon.awssdk.services.s3control.model.JobListDescriptor$BuilderImpl);
    Code:
       0: aload_0
       1: getfield      #5                  // Field creationTime:Ljava/time/Instant;
       4: areturn

  static java.time.Instant access$600(software.amazon.awssdk.services.s3control.model.JobListDescriptor$BuilderImpl);
    Code:
       0: aload_0
       1: getfield      #4                  // Field terminationDate:Ljava/time/Instant;
       4: areturn

  static software.amazon.awssdk.services.s3control.model.JobProgressSummary access$700(software.amazon.awssdk.services.s3control.model.JobListDescriptor$BuilderImpl);
    Code:
       0: aload_0
       1: getfield      #3                  // Field progressSummary:Lsoftware/amazon/awssdk/services/s3control/model/JobProgressSummary;
       4: areturn

  software.amazon.awssdk.services.s3control.model.JobListDescriptor$BuilderImpl(software.amazon.awssdk.services.s3control.model.JobListDescriptor, software.amazon.awssdk.services.s3control.model.JobListDescriptor$1);
    Code:
       0: aload_0
       1: aload_1
       2: invokespecial #2                  // Method "<init>":(Lsoftware/amazon/awssdk/services/s3control/model/JobListDescriptor;)V
       5: return

  software.amazon.awssdk.services.s3control.model.JobListDescriptor$BuilderImpl(software.amazon.awssdk.services.s3control.model.JobListDescriptor$1);
    Code:
       0: aload_0
       1: invokespecial #1                  // Method "<init>":()V
       4: return
}
