Compiled from "S3BucketDestination.java"
public interface software.amazon.awssdk.services.s3control.model.S3BucketDestination$Builder extends software.amazon.awssdk.core.SdkPojo, software.amazon.awssdk.utils.builder.CopyableBuilder<software.amazon.awssdk.services.s3control.model.S3BucketDestination$Builder, software.amazon.awssdk.services.s3control.model.S3BucketDestination> {
  public abstract software.amazon.awssdk.services.s3control.model.S3BucketDestination$Builder format(java.lang.String);

  public abstract software.amazon.awssdk.services.s3control.model.S3BucketDestination$Builder format(software.amazon.awssdk.services.s3control.model.Format);

  public abstract software.amazon.awssdk.services.s3control.model.S3BucketDestination$Builder outputSchemaVersion(java.lang.String);

  public abstract software.amazon.awssdk.services.s3control.model.S3BucketDestination$Builder outputSchemaVersion(software.amazon.awssdk.services.s3control.model.OutputSchemaVersion);

  public abstract software.amazon.awssdk.services.s3control.model.S3BucketDestination$Builder accountId(java.lang.String);

  public abstract software.amazon.awssdk.services.s3control.model.S3BucketDestination$Builder arn(java.lang.String);

  public abstract software.amazon.awssdk.services.s3control.model.S3BucketDestination$Builder prefix(java.lang.String);

  public abstract software.amazon.awssdk.services.s3control.model.S3BucketDestination$Builder encryption(software.amazon.awssdk.services.s3control.model.StorageLensDataExportEncryption);

  public default software.amazon.awssdk.services.s3control.model.S3BucketDestination$Builder encryption(java.util.function.Consumer<software.amazon.awssdk.services.s3control.model.StorageLensDataExportEncryption$Builder>);
    Code:
       0: aload_0
       1: invokestatic  #1                  // Method software/amazon/awssdk/services/s3control/model/StorageLensDataExportEncryption.builder:()Lsoftware/amazon/awssdk/services/s3control/model/StorageLensDataExportEncryption$Builder;
       4: aload_1
       5: invokeinterface #2,  2            // InterfaceMethod software/amazon/awssdk/services/s3control/model/StorageLensDataExportEncryption$Builder.applyMutation:(Ljava/util/function/Consumer;)Lsoftware/amazon/awssdk/utils/builder/SdkBuilder;
      10: checkcast     #3                  // class software/amazon/awssdk/services/s3control/model/StorageLensDataExportEncryption$Builder
      13: invokeinterface #4,  1            // InterfaceMethod software/amazon/awssdk/services/s3control/model/StorageLensDataExportEncryption$Builder.build:()Ljava/lang/Object;
      18: checkcast     #5                  // class software/amazon/awssdk/services/s3control/model/StorageLensDataExportEncryption
      21: invokeinterface #6,  2            // InterfaceMethod encryption:(Lsoftware/amazon/awssdk/services/s3control/model/StorageLensDataExportEncryption;)Lsoftware/amazon/awssdk/services/s3control/model/S3BucketDestination$Builder;
      26: areturn
}
