Compiled from "S3ManifestOutputLocation.java"
public interface software.amazon.awssdk.services.s3control.model.S3ManifestOutputLocation$Builder extends software.amazon.awssdk.core.SdkPojo, software.amazon.awssdk.utils.builder.CopyableBuilder<software.amazon.awssdk.services.s3control.model.S3ManifestOutputLocation$Builder, software.amazon.awssdk.services.s3control.model.S3ManifestOutputLocation> {
  public abstract software.amazon.awssdk.services.s3control.model.S3ManifestOutputLocation$Builder expectedManifestBucketOwner(java.lang.String);

  public abstract software.amazon.awssdk.services.s3control.model.S3ManifestOutputLocation$Builder bucket(java.lang.String);

  public abstract software.amazon.awssdk.services.s3control.model.S3ManifestOutputLocation$Builder manifestPrefix(java.lang.String);

  public abstract software.amazon.awssdk.services.s3control.model.S3ManifestOutputLocation$Builder manifestEncryption(software.amazon.awssdk.services.s3control.model.GeneratedManifestEncryption);

  public default software.amazon.awssdk.services.s3control.model.S3ManifestOutputLocation$Builder manifestEncryption(java.util.function.Consumer<software.amazon.awssdk.services.s3control.model.GeneratedManifestEncryption$Builder>);
    Code:
       0: aload_0
       1: invokestatic  #1                  // Method software/amazon/awssdk/services/s3control/model/GeneratedManifestEncryption.builder:()Lsoftware/amazon/awssdk/services/s3control/model/GeneratedManifestEncryption$Builder;
       4: aload_1
       5: invokeinterface #2,  2            // InterfaceMethod software/amazon/awssdk/services/s3control/model/GeneratedManifestEncryption$Builder.applyMutation:(Ljava/util/function/Consumer;)Lsoftware/amazon/awssdk/utils/builder/SdkBuilder;
      10: checkcast     #3                  // class software/amazon/awssdk/services/s3control/model/GeneratedManifestEncryption$Builder
      13: invokeinterface #4,  1            // InterfaceMethod software/amazon/awssdk/services/s3control/model/GeneratedManifestEncryption$Builder.build:()Ljava/lang/Object;
      18: checkcast     #5                  // class software/amazon/awssdk/services/s3control/model/GeneratedManifestEncryption
      21: invokeinterface #6,  2            // InterfaceMethod manifestEncryption:(Lsoftware/amazon/awssdk/services/s3control/model/GeneratedManifestEncryption;)Lsoftware/amazon/awssdk/services/s3control/model/S3ManifestOutputLocation$Builder;
      26: areturn

  public abstract software.amazon.awssdk.services.s3control.model.S3ManifestOutputLocation$Builder manifestFormat(java.lang.String);

  public abstract software.amazon.awssdk.services.s3control.model.S3ManifestOutputLocation$Builder manifestFormat(software.amazon.awssdk.services.s3control.model.GeneratedManifestFormat);
}
