Compiled from "FunctionEvaluationException.java"
public class org.graylog.plugins.pipelineprocessor.ast.exceptions.FunctionEvaluationException extends org.graylog.plugins.pipelineprocessor.ast.exceptions.LocationAwareEvalException {
  private final org.graylog.plugins.pipelineprocessor.ast.expressions.FunctionExpression functionExpression;

  private final java.lang.Exception exception;

  public org.graylog.plugins.pipelineprocessor.ast.exceptions.FunctionEvaluationException(org.graylog.plugins.pipelineprocessor.ast.expressions.FunctionExpression, java.lang.Exception);
    Code:
       0: aload_0
       1: aload_1
       2: invokevirtual #1                  // Method org/graylog/plugins/pipelineprocessor/ast/expressions/FunctionExpression.getStartToken:()Lorg/antlr/v4/runtime/Token;
       5: aload_2
       6: invokespecial #2                  // Method org/graylog/plugins/pipelineprocessor/ast/exceptions/LocationAwareEvalException."<init>":(Lorg/antlr/v4/runtime/Token;Ljava/lang/Throwable;)V
       9: aload_0
      10: aload_1
      11: putfield      #3                  // Field functionExpression:Lorg/graylog/plugins/pipelineprocessor/ast/expressions/FunctionExpression;
      14: aload_0
      15: aload_2
      16: putfield      #4                  // Field exception:Ljava/lang/Exception;
      19: return

  public org.graylog.plugins.pipelineprocessor.ast.expressions.FunctionExpression getFunctionExpression();
    Code:
       0: aload_0
       1: getfield      #3                  // Field functionExpression:Lorg/graylog/plugins/pipelineprocessor/ast/expressions/FunctionExpression;
       4: areturn

  public java.lang.Exception getException();
    Code:
       0: aload_0
       1: getfield      #4                  // Field exception:Ljava/lang/Exception;
       4: areturn
}
