Compiled from "Type.java"
public final class org.xbill.DNS.Type {
  public static final int A;

  public static final int NS;

  public static final int MD;

  public static final int MF;

  public static final int CNAME;

  public static final int SOA;

  public static final int MB;

  public static final int MG;

  public static final int MR;

  public static final int NULL;

  public static final int WKS;

  public static final int PTR;

  public static final int HINFO;

  public static final int MINFO;

  public static final int MX;

  public static final int TXT;

  public static final int RP;

  public static final int AFSDB;

  public static final int X25;

  public static final int ISDN;

  public static final int RT;

  public static final int NSAP;

  public static final int NSAP_PTR;

  public static final int SIG;

  public static final int KEY;

  public static final int PX;

  public static final int GPOS;

  public static final int AAAA;

  public static final int LOC;

  public static final int NXT;

  public static final int EID;

  public static final int NIMLOC;

  public static final int SRV;

  public static final int ATMA;

  public static final int NAPTR;

  public static final int KX;

  public static final int CERT;

  public static final int A6;

  public static final int DNAME;

  public static final int OPT;

  public static final int APL;

  public static final int DS;

  public static final int SSHFP;

  public static final int IPSECKEY;

  public static final int RRSIG;

  public static final int NSEC;

  public static final int DNSKEY;

  public static final int DHCID;

  public static final int NSEC3;

  public static final int NSEC3PARAM;

  public static final int TLSA;

  public static final int SPF;

  public static final int TKEY;

  public static final int TSIG;

  public static final int IXFR;

  public static final int AXFR;

  public static final int MAILB;

  public static final int MAILA;

  public static final int ANY;

  public static final int URI;

  public static final int DLV;

  private static org.xbill.DNS.Type$TypeMnemonic types;

  private org.xbill.DNS.Type();
    Code:
       0: aload_0
       1: invokespecial #1                  // Method java/lang/Object."<init>":()V
       4: return

  public static void check(int);
    Code:
       0: iload_0
       1: iflt          10
       4: iload_0
       5: ldc           #2                  // int 65535
       7: if_icmple     19
      10: new           #3                  // class org/xbill/DNS/InvalidTypeException
      13: dup
      14: iload_0
      15: invokespecial #4                  // Method org/xbill/DNS/InvalidTypeException."<init>":(I)V
      18: athrow
      19: return

  public static java.lang.String string(int);
    Code:
       0: getstatic     #5                  // Field types:Lorg/xbill/DNS/Type$TypeMnemonic;
       3: iload_0
       4: invokevirtual #6                  // Method org/xbill/DNS/Type$TypeMnemonic.getText:(I)Ljava/lang/String;
       7: areturn

  public static int value(java.lang.String, boolean);
    Code:
       0: getstatic     #5                  // Field types:Lorg/xbill/DNS/Type$TypeMnemonic;
       3: aload_0
       4: invokevirtual #7                  // Method org/xbill/DNS/Type$TypeMnemonic.getValue:(Ljava/lang/String;)I
       7: istore_2
       8: iload_2
       9: iconst_m1
      10: if_icmpne     43
      13: iload_1
      14: ifeq          43
      17: getstatic     #5                  // Field types:Lorg/xbill/DNS/Type$TypeMnemonic;
      20: new           #8                  // class java/lang/StringBuffer
      23: dup
      24: invokespecial #9                  // Method java/lang/StringBuffer."<init>":()V
      27: ldc           #10                 // String TYPE
      29: invokevirtual #11                 // Method java/lang/StringBuffer.append:(Ljava/lang/String;)Ljava/lang/StringBuffer;
      32: aload_0
      33: invokevirtual #11                 // Method java/lang/StringBuffer.append:(Ljava/lang/String;)Ljava/lang/StringBuffer;
      36: invokevirtual #12                 // Method java/lang/StringBuffer.toString:()Ljava/lang/String;
      39: invokevirtual #7                  // Method org/xbill/DNS/Type$TypeMnemonic.getValue:(Ljava/lang/String;)I
      42: istore_2
      43: iload_2
      44: ireturn

  public static int value(java.lang.String);
    Code:
       0: aload_0
       1: iconst_0
       2: invokestatic  #13                 // Method value:(Ljava/lang/String;Z)I
       5: ireturn

  static org.xbill.DNS.Record getProto(int);
    Code:
       0: getstatic     #5                  // Field types:Lorg/xbill/DNS/Type$TypeMnemonic;
       3: iload_0
       4: invokevirtual #14                 // Method org/xbill/DNS/Type$TypeMnemonic.getProto:(I)Lorg/xbill/DNS/Record;
       7: areturn

  public static boolean isRR(int);
    Code:
       0: iload_0
       1: lookupswitch  { // 8
                    41: 76
                   249: 76
                   250: 76
                   251: 76
                   252: 76
                   253: 76
                   254: 76
                   255: 76
               default: 78
          }
      76: iconst_0
      77: ireturn
      78: iconst_1
      79: ireturn

  static {};
    Code:
       0: new           #15                 // class org/xbill/DNS/Type$TypeMnemonic
       3: dup
       4: invokespecial #16                 // Method org/xbill/DNS/Type$TypeMnemonic."<init>":()V
       7: putstatic     #5                  // Field types:Lorg/xbill/DNS/Type$TypeMnemonic;
      10: getstatic     #5                  // Field types:Lorg/xbill/DNS/Type$TypeMnemonic;
      13: iconst_1
      14: ldc           #17                 // String A
      16: new           #18                 // class org/xbill/DNS/ARecord
      19: dup
      20: invokespecial #19                 // Method org/xbill/DNS/ARecord."<init>":()V
      23: invokevirtual #20                 // Method org/xbill/DNS/Type$TypeMnemonic.add:(ILjava/lang/String;Lorg/xbill/DNS/Record;)V
      26: getstatic     #5                  // Field types:Lorg/xbill/DNS/Type$TypeMnemonic;
      29: iconst_2
      30: ldc           #21                 // String NS
      32: new           #22                 // class org/xbill/DNS/NSRecord
      35: dup
      36: invokespecial #23                 // Method org/xbill/DNS/NSRecord."<init>":()V
      39: invokevirtual #20                 // Method org/xbill/DNS/Type$TypeMnemonic.add:(ILjava/lang/String;Lorg/xbill/DNS/Record;)V
      42: getstatic     #5                  // Field types:Lorg/xbill/DNS/Type$TypeMnemonic;
      45: iconst_3
      46: ldc           #24                 // String MD
      48: new           #25                 // class org/xbill/DNS/MDRecord
      51: dup
      52: invokespecial #26                 // Method org/xbill/DNS/MDRecord."<init>":()V
      55: invokevirtual #20                 // Method org/xbill/DNS/Type$TypeMnemonic.add:(ILjava/lang/String;Lorg/xbill/DNS/Record;)V
      58: getstatic     #5                  // Field types:Lorg/xbill/DNS/Type$TypeMnemonic;
      61: iconst_4
      62: ldc           #27                 // String MF
      64: new           #28                 // class org/xbill/DNS/MFRecord
      67: dup
      68: invokespecial #29                 // Method org/xbill/DNS/MFRecord."<init>":()V
      71: invokevirtual #20                 // Method org/xbill/DNS/Type$TypeMnemonic.add:(ILjava/lang/String;Lorg/xbill/DNS/Record;)V
      74: getstatic     #5                  // Field types:Lorg/xbill/DNS/Type$TypeMnemonic;
      77: iconst_5
      78: ldc           #30                 // String CNAME
      80: new           #31                 // class org/xbill/DNS/CNAMERecord
      83: dup
      84: invokespecial #32                 // Method org/xbill/DNS/CNAMERecord."<init>":()V
      87: invokevirtual #20                 // Method org/xbill/DNS/Type$TypeMnemonic.add:(ILjava/lang/String;Lorg/xbill/DNS/Record;)V
      90: getstatic     #5                  // Field types:Lorg/xbill/DNS/Type$TypeMnemonic;
      93: bipush        6
      95: ldc           #33                 // String SOA
      97: new           #34                 // class org/xbill/DNS/SOARecord
     100: dup
     101: invokespecial #35                 // Method org/xbill/DNS/SOARecord."<init>":()V
     104: invokevirtual #20                 // Method org/xbill/DNS/Type$TypeMnemonic.add:(ILjava/lang/String;Lorg/xbill/DNS/Record;)V
     107: getstatic     #5                  // Field types:Lorg/xbill/DNS/Type$TypeMnemonic;
     110: bipush        7
     112: ldc           #36                 // String MB
     114: new           #37                 // class org/xbill/DNS/MBRecord
     117: dup
     118: invokespecial #38                 // Method org/xbill/DNS/MBRecord."<init>":()V
     121: invokevirtual #20                 // Method org/xbill/DNS/Type$TypeMnemonic.add:(ILjava/lang/String;Lorg/xbill/DNS/Record;)V
     124: getstatic     #5                  // Field types:Lorg/xbill/DNS/Type$TypeMnemonic;
     127: bipush        8
     129: ldc           #39                 // String MG
     131: new           #40                 // class org/xbill/DNS/MGRecord
     134: dup
     135: invokespecial #41                 // Method org/xbill/DNS/MGRecord."<init>":()V
     138: invokevirtual #20                 // Method org/xbill/DNS/Type$TypeMnemonic.add:(ILjava/lang/String;Lorg/xbill/DNS/Record;)V
     141: getstatic     #5                  // Field types:Lorg/xbill/DNS/Type$TypeMnemonic;
     144: bipush        9
     146: ldc           #42                 // String MR
     148: new           #43                 // class org/xbill/DNS/MRRecord
     151: dup
     152: invokespecial #44                 // Method org/xbill/DNS/MRRecord."<init>":()V
     155: invokevirtual #20                 // Method org/xbill/DNS/Type$TypeMnemonic.add:(ILjava/lang/String;Lorg/xbill/DNS/Record;)V
     158: getstatic     #5                  // Field types:Lorg/xbill/DNS/Type$TypeMnemonic;
     161: bipush        10
     163: ldc           #45                 // String NULL
     165: new           #46                 // class org/xbill/DNS/NULLRecord
     168: dup
     169: invokespecial #47                 // Method org/xbill/DNS/NULLRecord."<init>":()V
     172: invokevirtual #20                 // Method org/xbill/DNS/Type$TypeMnemonic.add:(ILjava/lang/String;Lorg/xbill/DNS/Record;)V
     175: getstatic     #5                  // Field types:Lorg/xbill/DNS/Type$TypeMnemonic;
     178: bipush        11
     180: ldc           #48                 // String WKS
     182: new           #49                 // class org/xbill/DNS/WKSRecord
     185: dup
     186: invokespecial #50                 // Method org/xbill/DNS/WKSRecord."<init>":()V
     189: invokevirtual #20                 // Method org/xbill/DNS/Type$TypeMnemonic.add:(ILjava/lang/String;Lorg/xbill/DNS/Record;)V
     192: getstatic     #5                  // Field types:Lorg/xbill/DNS/Type$TypeMnemonic;
     195: bipush        12
     197: ldc           #51                 // String PTR
     199: new           #52                 // class org/xbill/DNS/PTRRecord
     202: dup
     203: invokespecial #53                 // Method org/xbill/DNS/PTRRecord."<init>":()V
     206: invokevirtual #20                 // Method org/xbill/DNS/Type$TypeMnemonic.add:(ILjava/lang/String;Lorg/xbill/DNS/Record;)V
     209: getstatic     #5                  // Field types:Lorg/xbill/DNS/Type$TypeMnemonic;
     212: bipush        13
     214: ldc           #54                 // String HINFO
     216: new           #55                 // class org/xbill/DNS/HINFORecord
     219: dup
     220: invokespecial #56                 // Method org/xbill/DNS/HINFORecord."<init>":()V
     223: invokevirtual #20                 // Method org/xbill/DNS/Type$TypeMnemonic.add:(ILjava/lang/String;Lorg/xbill/DNS/Record;)V
     226: getstatic     #5                  // Field types:Lorg/xbill/DNS/Type$TypeMnemonic;
     229: bipush        14
     231: ldc           #57                 // String MINFO
     233: new           #58                 // class org/xbill/DNS/MINFORecord
     236: dup
     237: invokespecial #59                 // Method org/xbill/DNS/MINFORecord."<init>":()V
     240: invokevirtual #20                 // Method org/xbill/DNS/Type$TypeMnemonic.add:(ILjava/lang/String;Lorg/xbill/DNS/Record;)V
     243: getstatic     #5                  // Field types:Lorg/xbill/DNS/Type$TypeMnemonic;
     246: bipush        15
     248: ldc           #60                 // String MX
     250: new           #61                 // class org/xbill/DNS/MXRecord
     253: dup
     254: invokespecial #62                 // Method org/xbill/DNS/MXRecord."<init>":()V
     257: invokevirtual #20                 // Method org/xbill/DNS/Type$TypeMnemonic.add:(ILjava/lang/String;Lorg/xbill/DNS/Record;)V
     260: getstatic     #5                  // Field types:Lorg/xbill/DNS/Type$TypeMnemonic;
     263: bipush        16
     265: ldc           #63                 // String TXT
     267: new           #64                 // class org/xbill/DNS/TXTRecord
     270: dup
     271: invokespecial #65                 // Method org/xbill/DNS/TXTRecord."<init>":()V
     274: invokevirtual #20                 // Method org/xbill/DNS/Type$TypeMnemonic.add:(ILjava/lang/String;Lorg/xbill/DNS/Record;)V
     277: getstatic     #5                  // Field types:Lorg/xbill/DNS/Type$TypeMnemonic;
     280: bipush        17
     282: ldc           #66                 // String RP
     284: new           #67                 // class org/xbill/DNS/RPRecord
     287: dup
     288: invokespecial #68                 // Method org/xbill/DNS/RPRecord."<init>":()V
     291: invokevirtual #20                 // Method org/xbill/DNS/Type$TypeMnemonic.add:(ILjava/lang/String;Lorg/xbill/DNS/Record;)V
     294: getstatic     #5                  // Field types:Lorg/xbill/DNS/Type$TypeMnemonic;
     297: bipush        18
     299: ldc           #69                 // String AFSDB
     301: new           #70                 // class org/xbill/DNS/AFSDBRecord
     304: dup
     305: invokespecial #71                 // Method org/xbill/DNS/AFSDBRecord."<init>":()V
     308: invokevirtual #20                 // Method org/xbill/DNS/Type$TypeMnemonic.add:(ILjava/lang/String;Lorg/xbill/DNS/Record;)V
     311: getstatic     #5                  // Field types:Lorg/xbill/DNS/Type$TypeMnemonic;
     314: bipush        19
     316: ldc           #72                 // String X25
     318: new           #73                 // class org/xbill/DNS/X25Record
     321: dup
     322: invokespecial #74                 // Method org/xbill/DNS/X25Record."<init>":()V
     325: invokevirtual #20                 // Method org/xbill/DNS/Type$TypeMnemonic.add:(ILjava/lang/String;Lorg/xbill/DNS/Record;)V
     328: getstatic     #5                  // Field types:Lorg/xbill/DNS/Type$TypeMnemonic;
     331: bipush        20
     333: ldc           #75                 // String ISDN
     335: new           #76                 // class org/xbill/DNS/ISDNRecord
     338: dup
     339: invokespecial #77                 // Method org/xbill/DNS/ISDNRecord."<init>":()V
     342: invokevirtual #20                 // Method org/xbill/DNS/Type$TypeMnemonic.add:(ILjava/lang/String;Lorg/xbill/DNS/Record;)V
     345: getstatic     #5                  // Field types:Lorg/xbill/DNS/Type$TypeMnemonic;
     348: bipush        21
     350: ldc           #78                 // String RT
     352: new           #79                 // class org/xbill/DNS/RTRecord
     355: dup
     356: invokespecial #80                 // Method org/xbill/DNS/RTRecord."<init>":()V
     359: invokevirtual #20                 // Method org/xbill/DNS/Type$TypeMnemonic.add:(ILjava/lang/String;Lorg/xbill/DNS/Record;)V
     362: getstatic     #5                  // Field types:Lorg/xbill/DNS/Type$TypeMnemonic;
     365: bipush        22
     367: ldc           #81                 // String NSAP
     369: new           #82                 // class org/xbill/DNS/NSAPRecord
     372: dup
     373: invokespecial #83                 // Method org/xbill/DNS/NSAPRecord."<init>":()V
     376: invokevirtual #20                 // Method org/xbill/DNS/Type$TypeMnemonic.add:(ILjava/lang/String;Lorg/xbill/DNS/Record;)V
     379: getstatic     #5                  // Field types:Lorg/xbill/DNS/Type$TypeMnemonic;
     382: bipush        23
     384: ldc           #84                 // String NSAP-PTR
     386: new           #85                 // class org/xbill/DNS/NSAP_PTRRecord
     389: dup
     390: invokespecial #86                 // Method org/xbill/DNS/NSAP_PTRRecord."<init>":()V
     393: invokevirtual #20                 // Method org/xbill/DNS/Type$TypeMnemonic.add:(ILjava/lang/String;Lorg/xbill/DNS/Record;)V
     396: getstatic     #5                  // Field types:Lorg/xbill/DNS/Type$TypeMnemonic;
     399: bipush        24
     401: ldc           #87                 // String SIG
     403: new           #88                 // class org/xbill/DNS/SIGRecord
     406: dup
     407: invokespecial #89                 // Method org/xbill/DNS/SIGRecord."<init>":()V
     410: invokevirtual #20                 // Method org/xbill/DNS/Type$TypeMnemonic.add:(ILjava/lang/String;Lorg/xbill/DNS/Record;)V
     413: getstatic     #5                  // Field types:Lorg/xbill/DNS/Type$TypeMnemonic;
     416: bipush        25
     418: ldc           #90                 // String KEY
     420: new           #91                 // class org/xbill/DNS/KEYRecord
     423: dup
     424: invokespecial #92                 // Method org/xbill/DNS/KEYRecord."<init>":()V
     427: invokevirtual #20                 // Method org/xbill/DNS/Type$TypeMnemonic.add:(ILjava/lang/String;Lorg/xbill/DNS/Record;)V
     430: getstatic     #5                  // Field types:Lorg/xbill/DNS/Type$TypeMnemonic;
     433: bipush        26
     435: ldc           #93                 // String PX
     437: new           #94                 // class org/xbill/DNS/PXRecord
     440: dup
     441: invokespecial #95                 // Method org/xbill/DNS/PXRecord."<init>":()V
     444: invokevirtual #20                 // Method org/xbill/DNS/Type$TypeMnemonic.add:(ILjava/lang/String;Lorg/xbill/DNS/Record;)V
     447: getstatic     #5                  // Field types:Lorg/xbill/DNS/Type$TypeMnemonic;
     450: bipush        27
     452: ldc           #96                 // String GPOS
     454: new           #97                 // class org/xbill/DNS/GPOSRecord
     457: dup
     458: invokespecial #98                 // Method org/xbill/DNS/GPOSRecord."<init>":()V
     461: invokevirtual #20                 // Method org/xbill/DNS/Type$TypeMnemonic.add:(ILjava/lang/String;Lorg/xbill/DNS/Record;)V
     464: getstatic     #5                  // Field types:Lorg/xbill/DNS/Type$TypeMnemonic;
     467: bipush        28
     469: ldc           #99                 // String AAAA
     471: new           #100                // class org/xbill/DNS/AAAARecord
     474: dup
     475: invokespecial #101                // Method org/xbill/DNS/AAAARecord."<init>":()V
     478: invokevirtual #20                 // Method org/xbill/DNS/Type$TypeMnemonic.add:(ILjava/lang/String;Lorg/xbill/DNS/Record;)V
     481: getstatic     #5                  // Field types:Lorg/xbill/DNS/Type$TypeMnemonic;
     484: bipush        29
     486: ldc           #102                // String LOC
     488: new           #103                // class org/xbill/DNS/LOCRecord
     491: dup
     492: invokespecial #104                // Method org/xbill/DNS/LOCRecord."<init>":()V
     495: invokevirtual #20                 // Method org/xbill/DNS/Type$TypeMnemonic.add:(ILjava/lang/String;Lorg/xbill/DNS/Record;)V
     498: getstatic     #5                  // Field types:Lorg/xbill/DNS/Type$TypeMnemonic;
     501: bipush        30
     503: ldc           #105                // String NXT
     505: new           #106                // class org/xbill/DNS/NXTRecord
     508: dup
     509: invokespecial #107                // Method org/xbill/DNS/NXTRecord."<init>":()V
     512: invokevirtual #20                 // Method org/xbill/DNS/Type$TypeMnemonic.add:(ILjava/lang/String;Lorg/xbill/DNS/Record;)V
     515: getstatic     #5                  // Field types:Lorg/xbill/DNS/Type$TypeMnemonic;
     518: bipush        31
     520: ldc           #108                // String EID
     522: invokevirtual #109                // Method org/xbill/DNS/Type$TypeMnemonic.add:(ILjava/lang/String;)V
     525: getstatic     #5                  // Field types:Lorg/xbill/DNS/Type$TypeMnemonic;
     528: bipush        32
     530: ldc           #110                // String NIMLOC
     532: invokevirtual #109                // Method org/xbill/DNS/Type$TypeMnemonic.add:(ILjava/lang/String;)V
     535: getstatic     #5                  // Field types:Lorg/xbill/DNS/Type$TypeMnemonic;
     538: bipush        33
     540: ldc           #111                // String SRV
     542: new           #112                // class org/xbill/DNS/SRVRecord
     545: dup
     546: invokespecial #113                // Method org/xbill/DNS/SRVRecord."<init>":()V
     549: invokevirtual #20                 // Method org/xbill/DNS/Type$TypeMnemonic.add:(ILjava/lang/String;Lorg/xbill/DNS/Record;)V
     552: getstatic     #5                  // Field types:Lorg/xbill/DNS/Type$TypeMnemonic;
     555: bipush        34
     557: ldc           #114                // String ATMA
     559: invokevirtual #109                // Method org/xbill/DNS/Type$TypeMnemonic.add:(ILjava/lang/String;)V
     562: getstatic     #5                  // Field types:Lorg/xbill/DNS/Type$TypeMnemonic;
     565: bipush        35
     567: ldc           #115                // String NAPTR
     569: new           #116                // class org/xbill/DNS/NAPTRRecord
     572: dup
     573: invokespecial #117                // Method org/xbill/DNS/NAPTRRecord."<init>":()V
     576: invokevirtual #20                 // Method org/xbill/DNS/Type$TypeMnemonic.add:(ILjava/lang/String;Lorg/xbill/DNS/Record;)V
     579: getstatic     #5                  // Field types:Lorg/xbill/DNS/Type$TypeMnemonic;
     582: bipush        36
     584: ldc           #118                // String KX
     586: new           #119                // class org/xbill/DNS/KXRecord
     589: dup
     590: invokespecial #120                // Method org/xbill/DNS/KXRecord."<init>":()V
     593: invokevirtual #20                 // Method org/xbill/DNS/Type$TypeMnemonic.add:(ILjava/lang/String;Lorg/xbill/DNS/Record;)V
     596: getstatic     #5                  // Field types:Lorg/xbill/DNS/Type$TypeMnemonic;
     599: bipush        37
     601: ldc           #121                // String CERT
     603: new           #122                // class org/xbill/DNS/CERTRecord
     606: dup
     607: invokespecial #123                // Method org/xbill/DNS/CERTRecord."<init>":()V
     610: invokevirtual #20                 // Method org/xbill/DNS/Type$TypeMnemonic.add:(ILjava/lang/String;Lorg/xbill/DNS/Record;)V
     613: getstatic     #5                  // Field types:Lorg/xbill/DNS/Type$TypeMnemonic;
     616: bipush        38
     618: ldc           #124                // String A6
     620: new           #125                // class org/xbill/DNS/A6Record
     623: dup
     624: invokespecial #126                // Method org/xbill/DNS/A6Record."<init>":()V
     627: invokevirtual #20                 // Method org/xbill/DNS/Type$TypeMnemonic.add:(ILjava/lang/String;Lorg/xbill/DNS/Record;)V
     630: getstatic     #5                  // Field types:Lorg/xbill/DNS/Type$TypeMnemonic;
     633: bipush        39
     635: ldc           #127                // String DNAME
     637: new           #128                // class org/xbill/DNS/DNAMERecord
     640: dup
     641: invokespecial #129                // Method org/xbill/DNS/DNAMERecord."<init>":()V
     644: invokevirtual #20                 // Method org/xbill/DNS/Type$TypeMnemonic.add:(ILjava/lang/String;Lorg/xbill/DNS/Record;)V
     647: getstatic     #5                  // Field types:Lorg/xbill/DNS/Type$TypeMnemonic;
     650: bipush        41
     652: ldc           #130                // String OPT
     654: new           #131                // class org/xbill/DNS/OPTRecord
     657: dup
     658: invokespecial #132                // Method org/xbill/DNS/OPTRecord."<init>":()V
     661: invokevirtual #20                 // Method org/xbill/DNS/Type$TypeMnemonic.add:(ILjava/lang/String;Lorg/xbill/DNS/Record;)V
     664: getstatic     #5                  // Field types:Lorg/xbill/DNS/Type$TypeMnemonic;
     667: bipush        42
     669: ldc           #133                // String APL
     671: new           #134                // class org/xbill/DNS/APLRecord
     674: dup
     675: invokespecial #135                // Method org/xbill/DNS/APLRecord."<init>":()V
     678: invokevirtual #20                 // Method org/xbill/DNS/Type$TypeMnemonic.add:(ILjava/lang/String;Lorg/xbill/DNS/Record;)V
     681: getstatic     #5                  // Field types:Lorg/xbill/DNS/Type$TypeMnemonic;
     684: bipush        43
     686: ldc           #136                // String DS
     688: new           #137                // class org/xbill/DNS/DSRecord
     691: dup
     692: invokespecial #138                // Method org/xbill/DNS/DSRecord."<init>":()V
     695: invokevirtual #20                 // Method org/xbill/DNS/Type$TypeMnemonic.add:(ILjava/lang/String;Lorg/xbill/DNS/Record;)V
     698: getstatic     #5                  // Field types:Lorg/xbill/DNS/Type$TypeMnemonic;
     701: bipush        44
     703: ldc           #139                // String SSHFP
     705: new           #140                // class org/xbill/DNS/SSHFPRecord
     708: dup
     709: invokespecial #141                // Method org/xbill/DNS/SSHFPRecord."<init>":()V
     712: invokevirtual #20                 // Method org/xbill/DNS/Type$TypeMnemonic.add:(ILjava/lang/String;Lorg/xbill/DNS/Record;)V
     715: getstatic     #5                  // Field types:Lorg/xbill/DNS/Type$TypeMnemonic;
     718: bipush        45
     720: ldc           #142                // String IPSECKEY
     722: new           #143                // class org/xbill/DNS/IPSECKEYRecord
     725: dup
     726: invokespecial #144                // Method org/xbill/DNS/IPSECKEYRecord."<init>":()V
     729: invokevirtual #20                 // Method org/xbill/DNS/Type$TypeMnemonic.add:(ILjava/lang/String;Lorg/xbill/DNS/Record;)V
     732: getstatic     #5                  // Field types:Lorg/xbill/DNS/Type$TypeMnemonic;
     735: bipush        46
     737: ldc           #145                // String RRSIG
     739: new           #146                // class org/xbill/DNS/RRSIGRecord
     742: dup
     743: invokespecial #147                // Method org/xbill/DNS/RRSIGRecord."<init>":()V
     746: invokevirtual #20                 // Method org/xbill/DNS/Type$TypeMnemonic.add:(ILjava/lang/String;Lorg/xbill/DNS/Record;)V
     749: getstatic     #5                  // Field types:Lorg/xbill/DNS/Type$TypeMnemonic;
     752: bipush        47
     754: ldc           #148                // String NSEC
     756: new           #149                // class org/xbill/DNS/NSECRecord
     759: dup
     760: invokespecial #150                // Method org/xbill/DNS/NSECRecord."<init>":()V
     763: invokevirtual #20                 // Method org/xbill/DNS/Type$TypeMnemonic.add:(ILjava/lang/String;Lorg/xbill/DNS/Record;)V
     766: getstatic     #5                  // Field types:Lorg/xbill/DNS/Type$TypeMnemonic;
     769: bipush        48
     771: ldc           #151                // String DNSKEY
     773: new           #152                // class org/xbill/DNS/DNSKEYRecord
     776: dup
     777: invokespecial #153                // Method org/xbill/DNS/DNSKEYRecord."<init>":()V
     780: invokevirtual #20                 // Method org/xbill/DNS/Type$TypeMnemonic.add:(ILjava/lang/String;Lorg/xbill/DNS/Record;)V
     783: getstatic     #5                  // Field types:Lorg/xbill/DNS/Type$TypeMnemonic;
     786: bipush        49
     788: ldc           #154                // String DHCID
     790: new           #155                // class org/xbill/DNS/DHCIDRecord
     793: dup
     794: invokespecial #156                // Method org/xbill/DNS/DHCIDRecord."<init>":()V
     797: invokevirtual #20                 // Method org/xbill/DNS/Type$TypeMnemonic.add:(ILjava/lang/String;Lorg/xbill/DNS/Record;)V
     800: getstatic     #5                  // Field types:Lorg/xbill/DNS/Type$TypeMnemonic;
     803: bipush        50
     805: ldc           #157                // String NSEC3
     807: new           #158                // class org/xbill/DNS/NSEC3Record
     810: dup
     811: invokespecial #159                // Method org/xbill/DNS/NSEC3Record."<init>":()V
     814: invokevirtual #20                 // Method org/xbill/DNS/Type$TypeMnemonic.add:(ILjava/lang/String;Lorg/xbill/DNS/Record;)V
     817: getstatic     #5                  // Field types:Lorg/xbill/DNS/Type$TypeMnemonic;
     820: bipush        51
     822: ldc           #160                // String NSEC3PARAM
     824: new           #161                // class org/xbill/DNS/NSEC3PARAMRecord
     827: dup
     828: invokespecial #162                // Method org/xbill/DNS/NSEC3PARAMRecord."<init>":()V
     831: invokevirtual #20                 // Method org/xbill/DNS/Type$TypeMnemonic.add:(ILjava/lang/String;Lorg/xbill/DNS/Record;)V
     834: getstatic     #5                  // Field types:Lorg/xbill/DNS/Type$TypeMnemonic;
     837: bipush        52
     839: ldc           #163                // String TLSA
     841: new           #164                // class org/xbill/DNS/TLSARecord
     844: dup
     845: invokespecial #165                // Method org/xbill/DNS/TLSARecord."<init>":()V
     848: invokevirtual #20                 // Method org/xbill/DNS/Type$TypeMnemonic.add:(ILjava/lang/String;Lorg/xbill/DNS/Record;)V
     851: getstatic     #5                  // Field types:Lorg/xbill/DNS/Type$TypeMnemonic;
     854: bipush        99
     856: ldc           #166                // String SPF
     858: new           #167                // class org/xbill/DNS/SPFRecord
     861: dup
     862: invokespecial #168                // Method org/xbill/DNS/SPFRecord."<init>":()V
     865: invokevirtual #20                 // Method org/xbill/DNS/Type$TypeMnemonic.add:(ILjava/lang/String;Lorg/xbill/DNS/Record;)V
     868: getstatic     #5                  // Field types:Lorg/xbill/DNS/Type$TypeMnemonic;
     871: sipush        249
     874: ldc           #169                // String TKEY
     876: new           #170                // class org/xbill/DNS/TKEYRecord
     879: dup
     880: invokespecial #171                // Method org/xbill/DNS/TKEYRecord."<init>":()V
     883: invokevirtual #20                 // Method org/xbill/DNS/Type$TypeMnemonic.add:(ILjava/lang/String;Lorg/xbill/DNS/Record;)V
     886: getstatic     #5                  // Field types:Lorg/xbill/DNS/Type$TypeMnemonic;
     889: sipush        250
     892: ldc           #172                // String TSIG
     894: new           #173                // class org/xbill/DNS/TSIGRecord
     897: dup
     898: invokespecial #174                // Method org/xbill/DNS/TSIGRecord."<init>":()V
     901: invokevirtual #20                 // Method org/xbill/DNS/Type$TypeMnemonic.add:(ILjava/lang/String;Lorg/xbill/DNS/Record;)V
     904: getstatic     #5                  // Field types:Lorg/xbill/DNS/Type$TypeMnemonic;
     907: sipush        251
     910: ldc           #175                // String IXFR
     912: invokevirtual #109                // Method org/xbill/DNS/Type$TypeMnemonic.add:(ILjava/lang/String;)V
     915: getstatic     #5                  // Field types:Lorg/xbill/DNS/Type$TypeMnemonic;
     918: sipush        252
     921: ldc           #176                // String AXFR
     923: invokevirtual #109                // Method org/xbill/DNS/Type$TypeMnemonic.add:(ILjava/lang/String;)V
     926: getstatic     #5                  // Field types:Lorg/xbill/DNS/Type$TypeMnemonic;
     929: sipush        253
     932: ldc           #177                // String MAILB
     934: invokevirtual #109                // Method org/xbill/DNS/Type$TypeMnemonic.add:(ILjava/lang/String;)V
     937: getstatic     #5                  // Field types:Lorg/xbill/DNS/Type$TypeMnemonic;
     940: sipush        254
     943: ldc           #178                // String MAILA
     945: invokevirtual #109                // Method org/xbill/DNS/Type$TypeMnemonic.add:(ILjava/lang/String;)V
     948: getstatic     #5                  // Field types:Lorg/xbill/DNS/Type$TypeMnemonic;
     951: sipush        255
     954: ldc           #179                // String ANY
     956: invokevirtual #109                // Method org/xbill/DNS/Type$TypeMnemonic.add:(ILjava/lang/String;)V
     959: getstatic     #5                  // Field types:Lorg/xbill/DNS/Type$TypeMnemonic;
     962: sipush        256
     965: ldc           #180                // String URI
     967: new           #181                // class org/xbill/DNS/URIRecord
     970: dup
     971: invokespecial #182                // Method org/xbill/DNS/URIRecord."<init>":()V
     974: invokevirtual #20                 // Method org/xbill/DNS/Type$TypeMnemonic.add:(ILjava/lang/String;Lorg/xbill/DNS/Record;)V
     977: getstatic     #5                  // Field types:Lorg/xbill/DNS/Type$TypeMnemonic;
     980: ldc           #183                // int 32769
     982: ldc           #184                // String DLV
     984: new           #185                // class org/xbill/DNS/DLVRecord
     987: dup
     988: invokespecial #186                // Method org/xbill/DNS/DLVRecord."<init>":()V
     991: invokevirtual #20                 // Method org/xbill/DNS/Type$TypeMnemonic.add:(ILjava/lang/String;Lorg/xbill/DNS/Record;)V
     994: return
}
