Compiled from "ConnectionEventTrigger.java"
class io.lettuce.core.ConnectionEventTrigger extends io.netty.channel.ChannelInboundHandlerAdapter {
  private final io.lettuce.core.ConnectionEvents connectionEvents;

  private final io.lettuce.core.RedisChannelHandler<?, ?> connection;

  private final io.lettuce.core.event.EventBus eventBus;

  io.lettuce.core.ConnectionEventTrigger(io.lettuce.core.ConnectionEvents, io.lettuce.core.RedisChannelHandler<?, ?>, io.lettuce.core.event.EventBus);
    Code:
       0: aload_0
       1: invokespecial #1                  // Method io/netty/channel/ChannelInboundHandlerAdapter."<init>":()V
       4: aload_0
       5: aload_1
       6: putfield      #2                  // Field connectionEvents:Lio/lettuce/core/ConnectionEvents;
       9: aload_0
      10: aload_2
      11: putfield      #3                  // Field connection:Lio/lettuce/core/RedisChannelHandler;
      14: aload_0
      15: aload_3
      16: putfield      #4                  // Field eventBus:Lio/lettuce/core/event/EventBus;
      19: return

  public void channelActive(io.netty.channel.ChannelHandlerContext) throws java.lang.Exception;
    Code:
       0: aload_0
       1: getfield      #2                  // Field connectionEvents:Lio/lettuce/core/ConnectionEvents;
       4: aload_0
       5: getfield      #3                  // Field connection:Lio/lettuce/core/RedisChannelHandler;
       8: aload_1
       9: invokeinterface #5,  1            // InterfaceMethod io/netty/channel/ChannelHandlerContext.channel:()Lio/netty/channel/Channel;
      14: invokeinterface #6,  1            // InterfaceMethod io/netty/channel/Channel.remoteAddress:()Ljava/net/SocketAddress;
      19: invokevirtual #7                  // Method io/lettuce/core/ConnectionEvents.fireEventRedisConnected:(Lio/lettuce/core/RedisChannelHandler;Ljava/net/SocketAddress;)V
      22: aload_0
      23: aload_1
      24: invokespecial #8                  // Method io/netty/channel/ChannelInboundHandlerAdapter.channelActive:(Lio/netty/channel/ChannelHandlerContext;)V
      27: return

  public void channelInactive(io.netty.channel.ChannelHandlerContext) throws java.lang.Exception;
    Code:
       0: aload_0
       1: getfield      #2                  // Field connectionEvents:Lio/lettuce/core/ConnectionEvents;
       4: aload_0
       5: getfield      #3                  // Field connection:Lio/lettuce/core/RedisChannelHandler;
       8: invokevirtual #9                  // Method io/lettuce/core/ConnectionEvents.fireEventRedisDisconnected:(Lio/lettuce/core/RedisChannelHandler;)V
      11: aload_0
      12: getfield      #4                  // Field eventBus:Lio/lettuce/core/event/EventBus;
      15: new           #10                 // class io/lettuce/core/event/connection/ConnectionDeactivatedEvent
      18: dup
      19: aload_1
      20: invokestatic  #11                 // Method local:(Lio/netty/channel/ChannelHandlerContext;)Ljava/net/SocketAddress;
      23: aload_1
      24: invokestatic  #12                 // Method remote:(Lio/netty/channel/ChannelHandlerContext;)Ljava/net/SocketAddress;
      27: invokespecial #13                 // Method io/lettuce/core/event/connection/ConnectionDeactivatedEvent."<init>":(Ljava/net/SocketAddress;Ljava/net/SocketAddress;)V
      30: invokeinterface #14,  2           // InterfaceMethod io/lettuce/core/event/EventBus.publish:(Lio/lettuce/core/event/Event;)V
      35: aload_0
      36: aload_1
      37: invokespecial #15                 // Method io/netty/channel/ChannelInboundHandlerAdapter.channelInactive:(Lio/netty/channel/ChannelHandlerContext;)V
      40: return

  public void exceptionCaught(io.netty.channel.ChannelHandlerContext, java.lang.Throwable) throws java.lang.Exception;
    Code:
       0: aload_0
       1: getfield      #2                  // Field connectionEvents:Lio/lettuce/core/ConnectionEvents;
       4: aload_0
       5: getfield      #3                  // Field connection:Lio/lettuce/core/RedisChannelHandler;
       8: aload_2
       9: invokevirtual #16                 // Method io/lettuce/core/ConnectionEvents.fireEventRedisExceptionCaught:(Lio/lettuce/core/RedisChannelHandler;Ljava/lang/Throwable;)V
      12: aload_0
      13: aload_1
      14: aload_2
      15: invokespecial #17                 // Method io/netty/channel/ChannelInboundHandlerAdapter.exceptionCaught:(Lio/netty/channel/ChannelHandlerContext;Ljava/lang/Throwable;)V
      18: return

  static java.net.SocketAddress remote(io.netty.channel.ChannelHandlerContext);
    Code:
       0: aload_0
       1: invokeinterface #5,  1            // InterfaceMethod io/netty/channel/ChannelHandlerContext.channel:()Lio/netty/channel/Channel;
       6: ifnull        35
       9: aload_0
      10: invokeinterface #5,  1            // InterfaceMethod io/netty/channel/ChannelHandlerContext.channel:()Lio/netty/channel/Channel;
      15: invokeinterface #6,  1            // InterfaceMethod io/netty/channel/Channel.remoteAddress:()Ljava/net/SocketAddress;
      20: ifnull        35
      23: aload_0
      24: invokeinterface #5,  1            // InterfaceMethod io/netty/channel/ChannelHandlerContext.channel:()Lio/netty/channel/Channel;
      29: invokeinterface #6,  1            // InterfaceMethod io/netty/channel/Channel.remoteAddress:()Ljava/net/SocketAddress;
      34: areturn
      35: new           #18                 // class io/netty/channel/local/LocalAddress
      38: dup
      39: ldc           #19                 // String unknown
      41: invokespecial #20                 // Method io/netty/channel/local/LocalAddress."<init>":(Ljava/lang/String;)V
      44: areturn

  static java.net.SocketAddress local(io.netty.channel.ChannelHandlerContext);
    Code:
       0: aload_0
       1: invokeinterface #5,  1            // InterfaceMethod io/netty/channel/ChannelHandlerContext.channel:()Lio/netty/channel/Channel;
       6: astore_1
       7: aload_1
       8: ifnull        27
      11: aload_1
      12: invokeinterface #21,  1           // InterfaceMethod io/netty/channel/Channel.localAddress:()Ljava/net/SocketAddress;
      17: ifnull        27
      20: aload_1
      21: invokeinterface #21,  1           // InterfaceMethod io/netty/channel/Channel.localAddress:()Ljava/net/SocketAddress;
      26: areturn
      27: getstatic     #22                 // Field io/netty/channel/local/LocalAddress.ANY:Lio/netty/channel/local/LocalAddress;
      30: areturn
}
