Compiled from "RedisConnectionException.java"
public class io.lettuce.core.RedisConnectionException extends io.lettuce.core.RedisException {
  public io.lettuce.core.RedisConnectionException(java.lang.String);
    Code:
       0: aload_0
       1: aload_1
       2: invokespecial #1                  // Method io/lettuce/core/RedisException."<init>":(Ljava/lang/String;)V
       5: return

  public io.lettuce.core.RedisConnectionException(java.lang.String, java.lang.Throwable);
    Code:
       0: aload_0
       1: aload_1
       2: aload_2
       3: invokespecial #2                  // Method io/lettuce/core/RedisException."<init>":(Ljava/lang/String;Ljava/lang/Throwable;)V
       6: return

  public static io.lettuce.core.RedisConnectionException create(java.net.SocketAddress, java.lang.Throwable);
    Code:
       0: new           #3                  // class io/lettuce/core/RedisConnectionException
       3: dup
       4: ldc           #4                  // String Unable to connect to %s
       6: iconst_1
       7: anewarray     #5                  // class java/lang/Object
      10: dup
      11: iconst_0
      12: aload_0
      13: aastore
      14: invokestatic  #6                  // Method java/lang/String.format:(Ljava/lang/String;[Ljava/lang/Object;)Ljava/lang/String;
      17: aload_1
      18: invokespecial #7                  // Method "<init>":(Ljava/lang/String;Ljava/lang/Throwable;)V
      21: areturn

  public static boolean isProtectedMode(java.lang.String);
    Code:
       0: aload_0
       1: ifnull        17
       4: aload_0
       5: ldc           #8                  // String DENIED
       7: invokevirtual #9                  // Method java/lang/String.startsWith:(Ljava/lang/String;)Z
      10: ifeq          17
      13: iconst_1
      14: goto          18
      17: iconst_0
      18: ireturn
}
