Compiled from "RedisPublisher.java"
class io.lettuce.core.RedisPublisher$CommandDispatch extends java.lang.Enum<io.lettuce.core.RedisPublisher$CommandDispatch> {
  public static final io.lettuce.core.RedisPublisher$CommandDispatch UNDISPATCHED;

  public static final io.lettuce.core.RedisPublisher$CommandDispatch DISPATCHED;

  private static final io.lettuce.core.RedisPublisher$CommandDispatch[] $VALUES;

  public static io.lettuce.core.RedisPublisher$CommandDispatch[] values();
    Code:
       0: getstatic     #2                  // Field $VALUES:[Lio/lettuce/core/RedisPublisher$CommandDispatch;
       3: invokevirtual #3                  // Method "[Lio/lettuce/core/RedisPublisher$CommandDispatch;".clone:()Ljava/lang/Object;
       6: checkcast     #4                  // class "[Lio/lettuce/core/RedisPublisher$CommandDispatch;"
       9: areturn

  public static io.lettuce.core.RedisPublisher$CommandDispatch valueOf(java.lang.String);
    Code:
       0: ldc           #5                  // class io/lettuce/core/RedisPublisher$CommandDispatch
       2: aload_0
       3: invokestatic  #6                  // Method java/lang/Enum.valueOf:(Ljava/lang/Class;Ljava/lang/String;)Ljava/lang/Enum;
       6: checkcast     #5                  // class io/lettuce/core/RedisPublisher$CommandDispatch
       9: areturn

  private io.lettuce.core.RedisPublisher$CommandDispatch();
    Code:
       0: aload_0
       1: aload_1
       2: iload_2
       3: invokespecial #7                  // Method java/lang/Enum."<init>":(Ljava/lang/String;I)V
       6: return

  void dispatch(io.lettuce.core.RedisPublisher$RedisSubscription<?>);
    Code:
       0: return

  io.lettuce.core.RedisPublisher$CommandDispatch(java.lang.String, int, io.lettuce.core.RedisPublisher$1);
    Code:
       0: aload_0
       1: aload_1
       2: iload_2
       3: invokespecial #1                  // Method "<init>":(Ljava/lang/String;I)V
       6: return

  static {};
    Code:
       0: new           #8                  // class io/lettuce/core/RedisPublisher$CommandDispatch$1
       3: dup
       4: ldc           #9                  // String UNDISPATCHED
       6: iconst_0
       7: invokespecial #10                 // Method io/lettuce/core/RedisPublisher$CommandDispatch$1."<init>":(Ljava/lang/String;I)V
      10: putstatic     #11                 // Field UNDISPATCHED:Lio/lettuce/core/RedisPublisher$CommandDispatch;
      13: new           #5                  // class io/lettuce/core/RedisPublisher$CommandDispatch
      16: dup
      17: ldc           #12                 // String DISPATCHED
      19: iconst_1
      20: invokespecial #1                  // Method "<init>":(Ljava/lang/String;I)V
      23: putstatic     #13                 // Field DISPATCHED:Lio/lettuce/core/RedisPublisher$CommandDispatch;
      26: iconst_2
      27: anewarray     #5                  // class io/lettuce/core/RedisPublisher$CommandDispatch
      30: dup
      31: iconst_0
      32: getstatic     #11                 // Field UNDISPATCHED:Lio/lettuce/core/RedisPublisher$CommandDispatch;
      35: aastore
      36: dup
      37: iconst_1
      38: getstatic     #13                 // Field DISPATCHED:Lio/lettuce/core/RedisPublisher$CommandDispatch;
      41: aastore
      42: putstatic     #2                  // Field $VALUES:[Lio/lettuce/core/RedisPublisher$CommandDispatch;
      45: return
}
