Compiled from "SocketOptions.java"
public class io.lettuce.core.SocketOptions$Builder {
  private java.time.Duration connectTimeout;

  private boolean keepAlive;

  private boolean tcpNoDelay;

  private io.lettuce.core.SocketOptions$Builder();
    Code:
       0: aload_0
       1: invokespecial #6                  // Method java/lang/Object."<init>":()V
       4: aload_0
       5: getstatic     #7                  // Field io/lettuce/core/SocketOptions.DEFAULT_CONNECT_TIMEOUT_DURATION:Ljava/time/Duration;
       8: putfield      #5                  // Field connectTimeout:Ljava/time/Duration;
      11: aload_0
      12: iconst_0
      13: putfield      #4                  // Field keepAlive:Z
      16: aload_0
      17: iconst_0
      18: putfield      #3                  // Field tcpNoDelay:Z
      21: return

  public io.lettuce.core.SocketOptions$Builder connectTimeout(java.time.Duration);
    Code:
       0: aload_1
       1: ldc           #8                  // String Connection timeout must not be null
       3: invokestatic  #9                  // Method io/lettuce/core/internal/LettuceAssert.notNull:(Ljava/lang/Object;Ljava/lang/String;)V
       6: aload_1
       7: invokevirtual #10                 // Method java/time/Duration.toNanos:()J
      10: lconst_0
      11: lcmp
      12: ifle          19
      15: iconst_1
      16: goto          20
      19: iconst_0
      20: ldc           #11                 // String Connect timeout must be greater 0
      22: invokestatic  #12                 // Method io/lettuce/core/internal/LettuceAssert.isTrue:(ZLjava/lang/String;)V
      25: aload_0
      26: aload_1
      27: putfield      #5                  // Field connectTimeout:Ljava/time/Duration;
      30: aload_0
      31: areturn

  public io.lettuce.core.SocketOptions$Builder connectTimeout(long, java.util.concurrent.TimeUnit);
    Code:
       0: lload_1
       1: lconst_0
       2: lcmp
       3: ifle          10
       6: iconst_1
       7: goto          11
      10: iconst_0
      11: ldc           #11                 // String Connect timeout must be greater 0
      13: invokestatic  #12                 // Method io/lettuce/core/internal/LettuceAssert.isTrue:(ZLjava/lang/String;)V
      16: aload_3
      17: ldc           #13                 // String TimeUnit must not be null
      19: invokestatic  #9                  // Method io/lettuce/core/internal/LettuceAssert.notNull:(Ljava/lang/Object;Ljava/lang/String;)V
      22: aload_0
      23: aload_3
      24: lload_1
      25: invokevirtual #14                 // Method java/util/concurrent/TimeUnit.toNanos:(J)J
      28: invokestatic  #15                 // Method java/time/Duration.ofNanos:(J)Ljava/time/Duration;
      31: invokevirtual #16                 // Method connectTimeout:(Ljava/time/Duration;)Lio/lettuce/core/SocketOptions$Builder;
      34: areturn

  public io.lettuce.core.SocketOptions$Builder keepAlive(boolean);
    Code:
       0: aload_0
       1: iload_1
       2: putfield      #4                  // Field keepAlive:Z
       5: aload_0
       6: areturn

  public io.lettuce.core.SocketOptions$Builder tcpNoDelay(boolean);
    Code:
       0: aload_0
       1: iload_1
       2: putfield      #3                  // Field tcpNoDelay:Z
       5: aload_0
       6: areturn

  public io.lettuce.core.SocketOptions build();
    Code:
       0: new           #1                  // class io/lettuce/core/SocketOptions
       3: dup
       4: aload_0
       5: invokespecial #17                 // Method io/lettuce/core/SocketOptions."<init>":(Lio/lettuce/core/SocketOptions$Builder;)V
       8: areturn

  static java.time.Duration access$000(io.lettuce.core.SocketOptions$Builder);
    Code:
       0: aload_0
       1: getfield      #5                  // Field connectTimeout:Ljava/time/Duration;
       4: areturn

  static boolean access$100(io.lettuce.core.SocketOptions$Builder);
    Code:
       0: aload_0
       1: getfield      #4                  // Field keepAlive:Z
       4: ireturn

  static boolean access$200(io.lettuce.core.SocketOptions$Builder);
    Code:
       0: aload_0
       1: getfield      #3                  // Field tcpNoDelay:Z
       4: ireturn

  io.lettuce.core.SocketOptions$Builder(io.lettuce.core.SocketOptions$1);
    Code:
       0: aload_0
       1: invokespecial #2                  // Method "<init>":()V
       4: return
}
