Compiled from "SslConnectionBuilder.java"
class io.lettuce.core.SslConnectionBuilder$SslChannelInitializer$1 extends io.netty.channel.ChannelDuplexHandler {
  final io.lettuce.core.SslConnectionBuilder$SslChannelInitializer this$0;

  io.lettuce.core.SslConnectionBuilder$SslChannelInitializer$1(io.lettuce.core.SslConnectionBuilder$SslChannelInitializer);
    Code:
       0: aload_0
       1: aload_1
       2: putfield      #1                  // Field this$0:Lio/lettuce/core/SslConnectionBuilder$SslChannelInitializer;
       5: aload_0
       6: invokespecial #2                  // Method io/netty/channel/ChannelDuplexHandler."<init>":()V
       9: return

  public void channelActive(io.netty.channel.ChannelHandlerContext) throws java.lang.Exception;
    Code:
       0: aload_0
       1: getfield      #1                  // Field this$0:Lio/lettuce/core/SslConnectionBuilder$SslChannelInitializer;
       4: invokestatic  #3                  // Method io/lettuce/core/SslConnectionBuilder$SslChannelInitializer.access$000:(Lio/lettuce/core/SslConnectionBuilder$SslChannelInitializer;)Lio/lettuce/core/resource/ClientResources;
       7: invokeinterface #4,  1            // InterfaceMethod io/lettuce/core/resource/ClientResources.eventBus:()Lio/lettuce/core/event/EventBus;
      12: new           #5                  // class io/lettuce/core/event/connection/ConnectedEvent
      15: dup
      16: aload_1
      17: invokestatic  #6                  // Method io/lettuce/core/ConnectionEventTrigger.local:(Lio/netty/channel/ChannelHandlerContext;)Ljava/net/SocketAddress;
      20: aload_1
      21: invokestatic  #7                  // Method io/lettuce/core/ConnectionEventTrigger.remote:(Lio/netty/channel/ChannelHandlerContext;)Ljava/net/SocketAddress;
      24: invokespecial #8                  // Method io/lettuce/core/event/connection/ConnectedEvent."<init>":(Ljava/net/SocketAddress;Ljava/net/SocketAddress;)V
      27: invokeinterface #9,  2            // InterfaceMethod io/lettuce/core/event/EventBus.publish:(Lio/lettuce/core/event/Event;)V
      32: aload_0
      33: aload_1
      34: invokespecial #10                 // Method io/netty/channel/ChannelDuplexHandler.channelActive:(Lio/netty/channel/ChannelHandlerContext;)V
      37: return

  public void channelInactive(io.netty.channel.ChannelHandlerContext) throws java.lang.Exception;
    Code:
       0: aload_0
       1: getfield      #1                  // Field this$0:Lio/lettuce/core/SslConnectionBuilder$SslChannelInitializer;
       4: invokestatic  #3                  // Method io/lettuce/core/SslConnectionBuilder$SslChannelInitializer.access$000:(Lio/lettuce/core/SslConnectionBuilder$SslChannelInitializer;)Lio/lettuce/core/resource/ClientResources;
       7: invokeinterface #4,  1            // InterfaceMethod io/lettuce/core/resource/ClientResources.eventBus:()Lio/lettuce/core/event/EventBus;
      12: new           #11                 // class io/lettuce/core/event/connection/DisconnectedEvent
      15: dup
      16: aload_1
      17: invokestatic  #6                  // Method io/lettuce/core/ConnectionEventTrigger.local:(Lio/netty/channel/ChannelHandlerContext;)Ljava/net/SocketAddress;
      20: aload_1
      21: invokestatic  #7                  // Method io/lettuce/core/ConnectionEventTrigger.remote:(Lio/netty/channel/ChannelHandlerContext;)Ljava/net/SocketAddress;
      24: invokespecial #12                 // Method io/lettuce/core/event/connection/DisconnectedEvent."<init>":(Ljava/net/SocketAddress;Ljava/net/SocketAddress;)V
      27: invokeinterface #9,  2            // InterfaceMethod io/lettuce/core/event/EventBus.publish:(Lio/lettuce/core/event/Event;)V
      32: aload_0
      33: aload_1
      34: invokespecial #13                 // Method io/netty/channel/ChannelDuplexHandler.channelInactive:(Lio/netty/channel/ChannelHandlerContext;)V
      37: return
}
