Compiled from "AbstractSearchProcessorFactory.java"
public abstract class io.netty.buffer.search.AbstractSearchProcessorFactory implements io.netty.buffer.search.SearchProcessorFactory {
  public io.netty.buffer.search.AbstractSearchProcessorFactory();
    Code:
       0: aload_0
       1: invokespecial #1                  // Method java/lang/Object."<init>":()V
       4: return

  public static io.netty.buffer.search.KmpSearchProcessorFactory newKmpSearchProcessorFactory(byte[]);
    Code:
       0: new           #2                  // class io/netty/buffer/search/KmpSearchProcessorFactory
       3: dup
       4: aload_0
       5: invokespecial #3                  // Method io/netty/buffer/search/KmpSearchProcessorFactory."<init>":([B)V
       8: areturn

  public static io.netty.buffer.search.BitapSearchProcessorFactory newBitapSearchProcessorFactory(byte[]);
    Code:
       0: new           #4                  // class io/netty/buffer/search/BitapSearchProcessorFactory
       3: dup
       4: aload_0
       5: invokespecial #5                  // Method io/netty/buffer/search/BitapSearchProcessorFactory."<init>":([B)V
       8: areturn
}
