Compiled from "ArtifactoryPromotionSyncServiceImpl.java"
class net.nemerosa.ontrack.extension.artifactory.service.ArtifactoryPromotionSyncServiceImpl$1 extends net.nemerosa.ontrack.model.support.AbstractBranchJob {
  final net.nemerosa.ontrack.model.structure.Branch val$branch;

  final net.nemerosa.ontrack.extension.artifactory.service.ArtifactoryPromotionSyncServiceImpl this$0;

  net.nemerosa.ontrack.extension.artifactory.service.ArtifactoryPromotionSyncServiceImpl$1(net.nemerosa.ontrack.extension.artifactory.service.ArtifactoryPromotionSyncServiceImpl, net.nemerosa.ontrack.model.structure.StructureService, net.nemerosa.ontrack.model.structure.Branch, net.nemerosa.ontrack.model.structure.Branch);
    Code:
       0: aload_0
       1: aload_1
       2: putfield      #1                  // Field this$0:Lnet/nemerosa/ontrack/extension/artifactory/service/ArtifactoryPromotionSyncServiceImpl;
       5: aload_0
       6: aload         4
       8: putfield      #2                  // Field val$branch:Lnet/nemerosa/ontrack/model/structure/Branch;
      11: aload_0
      12: aload_2
      13: aload_3
      14: invokespecial #3                  // Method net/nemerosa/ontrack/model/support/AbstractBranchJob."<init>":(Lnet/nemerosa/ontrack/model/structure/StructureService;Lnet/nemerosa/ontrack/model/structure/Branch;)V
      17: return

  public net.nemerosa.ontrack.job.JobKey getKey();
    Code:
       0: aload_0
       1: getfield      #1                  // Field this$0:Lnet/nemerosa/ontrack/extension/artifactory/service/ArtifactoryPromotionSyncServiceImpl;
       4: aload_0
       5: getfield      #2                  // Field val$branch:Lnet/nemerosa/ontrack/model/structure/Branch;
       8: invokestatic  #4                  // Method net/nemerosa/ontrack/extension/artifactory/service/ArtifactoryPromotionSyncServiceImpl.access$000:(Lnet/nemerosa/ontrack/extension/artifactory/service/ArtifactoryPromotionSyncServiceImpl;Lnet/nemerosa/ontrack/model/structure/Branch;)Lnet/nemerosa/ontrack/job/JobKey;
      11: areturn

  public net.nemerosa.ontrack.job.JobRun getTask();
    Code:
       0: aload_0
       1: aload_0
       2: getfield      #2                  // Field val$branch:Lnet/nemerosa/ontrack/model/structure/Branch;
       5: invokedynamic #5,  0              // InvokeDynamic #0:run:(Lnet/nemerosa/ontrack/extension/artifactory/service/ArtifactoryPromotionSyncServiceImpl$1;Lnet/nemerosa/ontrack/model/structure/Branch;)Lnet/nemerosa/ontrack/job/JobRun;
      10: areturn

  public java.lang.String getDescription();
    Code:
       0: ldc           #6                  // String Synchronisation of promotions with Artifactory for branch %s/%s
       2: iconst_2
       3: anewarray     #7                  // class java/lang/Object
       6: dup
       7: iconst_0
       8: aload_0
       9: getfield      #2                  // Field val$branch:Lnet/nemerosa/ontrack/model/structure/Branch;
      12: invokevirtual #8                  // Method net/nemerosa/ontrack/model/structure/Branch.getProject:()Lnet/nemerosa/ontrack/model/structure/Project;
      15: invokevirtual #9                  // Method net/nemerosa/ontrack/model/structure/Project.getName:()Ljava/lang/String;
      18: aastore
      19: dup
      20: iconst_1
      21: aload_0
      22: getfield      #2                  // Field val$branch:Lnet/nemerosa/ontrack/model/structure/Branch;
      25: invokevirtual #10                 // Method net/nemerosa/ontrack/model/structure/Branch.getName:()Ljava/lang/String;
      28: aastore
      29: invokestatic  #11                 // Method java/lang/String.format:(Ljava/lang/String;[Ljava/lang/Object;)Ljava/lang/String;
      32: areturn

  public boolean isValid();
    Code:
       0: aload_0
       1: invokespecial #12                 // Method net/nemerosa/ontrack/model/support/AbstractBranchJob.isValid:()Z
       4: ifeq          32
       7: aload_0
       8: getfield      #1                  // Field this$0:Lnet/nemerosa/ontrack/extension/artifactory/service/ArtifactoryPromotionSyncServiceImpl;
      11: invokestatic  #13                 // Method net/nemerosa/ontrack/extension/artifactory/service/ArtifactoryPromotionSyncServiceImpl.access$100:(Lnet/nemerosa/ontrack/extension/artifactory/service/ArtifactoryPromotionSyncServiceImpl;)Lnet/nemerosa/ontrack/model/structure/PropertyService;
      14: aload_0
      15: getfield      #2                  // Field val$branch:Lnet/nemerosa/ontrack/model/structure/Branch;
      18: ldc           #14                 // class net/nemerosa/ontrack/extension/artifactory/property/ArtifactoryPromotionSyncPropertyType
      20: invokeinterface #15,  3           // InterfaceMethod net/nemerosa/ontrack/model/structure/PropertyService.hasProperty:(Lnet/nemerosa/ontrack/model/structure/ProjectEntity;Ljava/lang/Class;)Z
      25: ifeq          32
      28: iconst_1
      29: goto          33
      32: iconst_0
      33: ireturn

  private void lambda$getTask$0(net.nemerosa.ontrack.model.structure.Branch, net.nemerosa.ontrack.job.JobRunListener);
    Code:
       0: aload_0
       1: getfield      #1                  // Field this$0:Lnet/nemerosa/ontrack/extension/artifactory/service/ArtifactoryPromotionSyncServiceImpl;
       4: aload_1
       5: aload_2
       6: invokestatic  #16                 // Method net/nemerosa/ontrack/extension/artifactory/service/ArtifactoryPromotionSyncServiceImpl.access$200:(Lnet/nemerosa/ontrack/extension/artifactory/service/ArtifactoryPromotionSyncServiceImpl;Lnet/nemerosa/ontrack/model/structure/Branch;Lnet/nemerosa/ontrack/job/JobRunListener;)V
       9: return
}
