Compiled from "SimpleSocketServer.java"
public class ch.qos.logback.access.net.SimpleSocketServer {
  static int port;

  private static ch.qos.logback.access.spi.AccessContext basicContext;

  public ch.qos.logback.access.net.SimpleSocketServer();
    Code:
       0: aload_0
       1: invokespecial #1                  // Method java/lang/Object."<init>":()V
       4: return

  public static void main(java.lang.String[]) throws java.lang.Exception;
    Code:
       0: aload_0
       1: arraylength
       2: iconst_2
       3: if_icmpne     18
       6: aload_0
       7: iconst_0
       8: aaload
       9: aload_0
      10: iconst_1
      11: aaload
      12: invokestatic  #2                  // Method init:(Ljava/lang/String;Ljava/lang/String;)V
      15: goto          23
      18: ldc           #3                  // String Wrong number of arguments.
      20: invokestatic  #4                  // Method usage:(Ljava/lang/String;)V
      23: invokestatic  #5                  // Method runServer:()V
      26: return

  static void runServer();
    Code:
       0: getstatic     #6                  // Field java/lang/System.out:Ljava/io/PrintStream;
       3: new           #7                  // class java/lang/StringBuilder
       6: dup
       7: invokespecial #8                  // Method java/lang/StringBuilder."<init>":()V
      10: ldc           #9                  // String Listening on port
      12: invokevirtual #10                 // Method java/lang/StringBuilder.append:(Ljava/lang/String;)Ljava/lang/StringBuilder;
      15: getstatic     #11                 // Field port:I
      18: invokevirtual #12                 // Method java/lang/StringBuilder.append:(I)Ljava/lang/StringBuilder;
      21: invokevirtual #13                 // Method java/lang/StringBuilder.toString:()Ljava/lang/String;
      24: invokevirtual #14                 // Method java/io/PrintStream.println:(Ljava/lang/String;)V
      27: new           #15                 // class java/net/ServerSocket
      30: dup
      31: getstatic     #11                 // Field port:I
      34: invokespecial #16                 // Method java/net/ServerSocket."<init>":(I)V
      37: astore_0
      38: getstatic     #6                  // Field java/lang/System.out:Ljava/io/PrintStream;
      41: ldc           #17                 // String Waiting to accept a new client.
      43: invokevirtual #14                 // Method java/io/PrintStream.println:(Ljava/lang/String;)V
      46: aload_0
      47: invokevirtual #18                 // Method java/net/ServerSocket.accept:()Ljava/net/Socket;
      50: astore_1
      51: getstatic     #6                  // Field java/lang/System.out:Ljava/io/PrintStream;
      54: new           #7                  // class java/lang/StringBuilder
      57: dup
      58: invokespecial #8                  // Method java/lang/StringBuilder."<init>":()V
      61: ldc           #19                 // String Connected to client at
      63: invokevirtual #10                 // Method java/lang/StringBuilder.append:(Ljava/lang/String;)Ljava/lang/StringBuilder;
      66: aload_1
      67: invokevirtual #20                 // Method java/net/Socket.getInetAddress:()Ljava/net/InetAddress;
      70: invokevirtual #21                 // Method java/lang/StringBuilder.append:(Ljava/lang/Object;)Ljava/lang/StringBuilder;
      73: invokevirtual #13                 // Method java/lang/StringBuilder.toString:()Ljava/lang/String;
      76: invokevirtual #14                 // Method java/io/PrintStream.println:(Ljava/lang/String;)V
      79: getstatic     #6                  // Field java/lang/System.out:Ljava/io/PrintStream;
      82: ldc           #22                 // String Starting new socket node.
      84: invokevirtual #14                 // Method java/io/PrintStream.println:(Ljava/lang/String;)V
      87: new           #23                 // class java/lang/Thread
      90: dup
      91: new           #24                 // class ch/qos/logback/access/net/SocketNode
      94: dup
      95: aload_1
      96: getstatic     #25                 // Field basicContext:Lch/qos/logback/access/spi/AccessContext;
      99: invokespecial #26                 // Method ch/qos/logback/access/net/SocketNode."<init>":(Ljava/net/Socket;Lch/qos/logback/access/spi/AccessContext;)V
     102: invokespecial #27                 // Method java/lang/Thread."<init>":(Ljava/lang/Runnable;)V
     105: invokevirtual #28                 // Method java/lang/Thread.start:()V
     108: goto          38
     111: astore_0
     112: aload_0
     113: invokevirtual #30                 // Method java/lang/Exception.printStackTrace:()V
     116: return
    Exception table:
       from    to  target type
           0   111   111   Class java/lang/Exception

  static void usage(java.lang.String);
    Code:
       0: getstatic     #31                 // Field java/lang/System.err:Ljava/io/PrintStream;
       3: aload_0
       4: invokevirtual #14                 // Method java/io/PrintStream.println:(Ljava/lang/String;)V
       7: getstatic     #31                 // Field java/lang/System.err:Ljava/io/PrintStream;
      10: new           #7                  // class java/lang/StringBuilder
      13: dup
      14: invokespecial #8                  // Method java/lang/StringBuilder."<init>":()V
      17: ldc           #32                 // String Usage: java
      19: invokevirtual #10                 // Method java/lang/StringBuilder.append:(Ljava/lang/String;)Ljava/lang/StringBuilder;
      22: ldc_w         #33                 // class ch/qos/logback/access/net/SimpleSocketServer
      25: invokevirtual #34                 // Method java/lang/Class.getName:()Ljava/lang/String;
      28: invokevirtual #10                 // Method java/lang/StringBuilder.append:(Ljava/lang/String;)Ljava/lang/StringBuilder;
      31: ldc           #35                 // String  port configFile
      33: invokevirtual #10                 // Method java/lang/StringBuilder.append:(Ljava/lang/String;)Ljava/lang/StringBuilder;
      36: invokevirtual #13                 // Method java/lang/StringBuilder.toString:()Ljava/lang/String;
      39: invokevirtual #14                 // Method java/io/PrintStream.println:(Ljava/lang/String;)V
      42: iconst_1
      43: invokestatic  #36                 // Method java/lang/System.exit:(I)V
      46: return

  static void init(java.lang.String, java.lang.String) throws ch.qos.logback.core.joran.spi.JoranException;
    Code:
       0: aload_0
       1: invokestatic  #37                 // Method java/lang/Integer.parseInt:(Ljava/lang/String;)I
       4: putstatic     #11                 // Field port:I
       7: goto          42
      10: astore_2
      11: aload_2
      12: invokevirtual #39                 // Method java/lang/NumberFormatException.printStackTrace:()V
      15: new           #7                  // class java/lang/StringBuilder
      18: dup
      19: invokespecial #8                  // Method java/lang/StringBuilder."<init>":()V
      22: ldc           #40                 // String Could not interpret port number [
      24: invokevirtual #10                 // Method java/lang/StringBuilder.append:(Ljava/lang/String;)Ljava/lang/StringBuilder;
      27: aload_0
      28: invokevirtual #10                 // Method java/lang/StringBuilder.append:(Ljava/lang/String;)Ljava/lang/StringBuilder;
      31: ldc           #41                 // String ].
      33: invokevirtual #10                 // Method java/lang/StringBuilder.append:(Ljava/lang/String;)Ljava/lang/StringBuilder;
      36: invokevirtual #13                 // Method java/lang/StringBuilder.toString:()Ljava/lang/String;
      39: invokestatic  #4                  // Method usage:(Ljava/lang/String;)V
      42: new           #42                 // class ch/qos/logback/access/spi/AccessContext
      45: dup
      46: invokespecial #43                 // Method ch/qos/logback/access/spi/AccessContext."<init>":()V
      49: putstatic     #25                 // Field basicContext:Lch/qos/logback/access/spi/AccessContext;
      52: aload_1
      53: ldc           #44                 // String .xml
      55: invokevirtual #45                 // Method java/lang/String.endsWith:(Ljava/lang/String;)Z
      58: ifeq          87
      61: new           #46                 // class ch/qos/logback/access/joran/JoranConfigurator
      64: dup
      65: invokespecial #47                 // Method ch/qos/logback/access/joran/JoranConfigurator."<init>":()V
      68: astore_2
      69: aload_2
      70: getstatic     #25                 // Field basicContext:Lch/qos/logback/access/spi/AccessContext;
      73: invokevirtual #48                 // Method ch/qos/logback/access/joran/JoranConfigurator.setContext:(Lch/qos/logback/core/Context;)V
      76: aload_2
      77: aload_1
      78: invokevirtual #49                 // Method ch/qos/logback/access/joran/JoranConfigurator.doConfigure:(Ljava/lang/String;)V
      81: getstatic     #25                 // Field basicContext:Lch/qos/logback/access/spi/AccessContext;
      84: invokestatic  #50                 // Method ch/qos/logback/core/util/StatusPrinter.print:(Lch/qos/logback/core/Context;)V
      87: return
    Exception table:
       from    to  target type
           0     7    10   Class java/lang/NumberFormatException
}
