Compiled from "RabbitMQClient.kt"
final class io.vertx.kotlin.rabbitmq.RabbitMQClientKt$queueDeleteIfAwait$2 extends kotlin.jvm.internal.Lambda implements kotlin.jvm.functions.Function1<io.vertx.core.Handler<io.vertx.core.AsyncResult<io.vertx.core.json.JsonObject>>, kotlin.Unit> {
  final io.vertx.rabbitmq.RabbitMQClient $this_queueDeleteIfAwait;

  final java.lang.String $queue;

  final boolean $ifUnused;

  final boolean $ifEmpty;

  public java.lang.Object invoke(java.lang.Object);
    Code:
       0: aload_0
       1: aload_1
       2: checkcast     #11                 // class io/vertx/core/Handler
       5: invokevirtual #14                 // Method invoke:(Lio/vertx/core/Handler;)V
       8: getstatic     #20                 // Field kotlin/Unit.INSTANCE:Lkotlin/Unit;
      11: areturn

  public final void invoke(io.vertx.core.Handler<io.vertx.core.AsyncResult<io.vertx.core.json.JsonObject>>);
    Code:
       0: aload_1
       1: ldc           #24                 // String it
       3: invokestatic  #30                 // Method kotlin/jvm/internal/Intrinsics.checkParameterIsNotNull:(Ljava/lang/Object;Ljava/lang/String;)V
       6: aload_0
       7: getfield      #34                 // Field $this_queueDeleteIfAwait:Lio/vertx/rabbitmq/RabbitMQClient;
      10: aload_0
      11: getfield      #38                 // Field $queue:Ljava/lang/String;
      14: aload_0
      15: getfield      #42                 // Field $ifUnused:Z
      18: aload_0
      19: getfield      #45                 // Field $ifEmpty:Z
      22: aload_1
      23: invokeinterface #51,  5           // InterfaceMethod io/vertx/rabbitmq/RabbitMQClient.queueDeleteIf:(Ljava/lang/String;ZZLio/vertx/core/Handler;)V
      28: return

  io.vertx.kotlin.rabbitmq.RabbitMQClientKt$queueDeleteIfAwait$2(io.vertx.rabbitmq.RabbitMQClient, java.lang.String, boolean, boolean);
    Code:
       0: aload_0
       1: aload_1
       2: putfield      #34                 // Field $this_queueDeleteIfAwait:Lio/vertx/rabbitmq/RabbitMQClient;
       5: aload_0
       6: aload_2
       7: putfield      #38                 // Field $queue:Ljava/lang/String;
      10: aload_0
      11: iload_3
      12: putfield      #42                 // Field $ifUnused:Z
      15: aload_0
      16: iload         4
      18: putfield      #45                 // Field $ifEmpty:Z
      21: aload_0
      22: iconst_1
      23: invokespecial #59                 // Method kotlin/jvm/internal/Lambda."<init>":(I)V
      26: return
}
