Compiled from "DoubleFieldPutter.java"
public class org.jboss.marshalling.util.DoubleFieldPutter extends org.jboss.marshalling.util.FieldPutter {
  private double value;

  public org.jboss.marshalling.util.DoubleFieldPutter();
    Code:
       0: aload_0
       1: invokespecial #1                  // Method org/jboss/marshalling/util/FieldPutter."<init>":()V
       4: return

  public void write(org.jboss.marshalling.Marshaller) throws java.io.IOException;
    Code:
       0: aload_1
       1: aload_0
       2: getfield      #2                  // Field value:D
       5: invokeinterface #3,  3            // InterfaceMethod org/jboss/marshalling/Marshaller.writeDouble:(D)V
      10: return

  public org.jboss.marshalling.util.Kind getKind();
    Code:
       0: getstatic     #4                  // Field org/jboss/marshalling/util/Kind.DOUBLE:Lorg/jboss/marshalling/util/Kind;
       3: areturn

  public double getDouble();
    Code:
       0: aload_0
       1: getfield      #2                  // Field value:D
       4: dreturn

  public void setDouble(double);
    Code:
       0: aload_0
       1: dload_1
       2: putfield      #2                  // Field value:D
       5: return
}
