Compiled from "WebSocketClient.java"
class io.undertow.websockets.client.WebSocketClient$ConnectionBuilder$1$1$1$2 implements org.xnio.Cancellable {
  final org.xnio.IoFuture val$result;

  final io.undertow.websockets.client.WebSocketClient$ConnectionBuilder$1$1$1 this$3;

  io.undertow.websockets.client.WebSocketClient$ConnectionBuilder$1$1$1$2(io.undertow.websockets.client.WebSocketClient$ConnectionBuilder$1$1$1, org.xnio.IoFuture);
    Code:
       0: aload_0
       1: aload_1
       2: putfield      #1                  // Field this$3:Lio/undertow/websockets/client/WebSocketClient$ConnectionBuilder$1$1$1;
       5: aload_0
       6: aload_2
       7: putfield      #2                  // Field val$result:Lorg/xnio/IoFuture;
      10: aload_0
      11: invokespecial #3                  // Method java/lang/Object."<init>":()V
      14: return

  public org.xnio.Cancellable cancel();
    Code:
       0: aload_0
       1: getfield      #2                  // Field val$result:Lorg/xnio/IoFuture;
       4: invokeinterface #4,  1            // InterfaceMethod org/xnio/IoFuture.cancel:()Lorg/xnio/IoFuture;
       9: pop
      10: aconst_null
      11: areturn
}
