Compiled from "KeyInfoReferenceProvider.java"
public class org.opensaml.xmlsec.keyinfo.impl.provider.KeyInfoReferenceProvider extends org.opensaml.xmlsec.keyinfo.impl.provider.AbstractKeyInfoProvider {
  private final org.slf4j.Logger log;

  public org.opensaml.xmlsec.keyinfo.impl.provider.KeyInfoReferenceProvider();
    Code:
       0: aload_0
       1: invokespecial #1                  // Method org/opensaml/xmlsec/keyinfo/impl/provider/AbstractKeyInfoProvider."<init>":()V
       4: aload_0
       5: ldc_w         #2                  // class org/opensaml/xmlsec/keyinfo/impl/provider/KeyInfoReferenceProvider
       8: invokestatic  #3                  // Method org/slf4j/LoggerFactory.getLogger:(Ljava/lang/Class;)Lorg/slf4j/Logger;
      11: putfield      #4                  // Field log:Lorg/slf4j/Logger;
      14: return

  public boolean handles(org.opensaml.core.xml.XMLObject);
    Code:
       0: aload_0
       1: aload_1
       2: invokevirtual #5                  // Method getKeyInfoReference:(Lorg/opensaml/core/xml/XMLObject;)Lorg/opensaml/xmlsec/signature/KeyInfoReference;
       5: ifnull        12
       8: iconst_1
       9: goto          13
      12: iconst_0
      13: ireturn

  public java.util.Collection<org.opensaml.security.credential.Credential> process(org.opensaml.xmlsec.keyinfo.KeyInfoCredentialResolver, org.opensaml.core.xml.XMLObject, net.shibboleth.utilities.java.support.resolver.CriteriaSet, org.opensaml.xmlsec.keyinfo.impl.KeyInfoResolutionContext) throws org.opensaml.security.SecurityException;
    Code:
       0: aload_0
       1: aload_2
       2: invokevirtual #5                  // Method getKeyInfoReference:(Lorg/opensaml/core/xml/XMLObject;)Lorg/opensaml/xmlsec/signature/KeyInfoReference;
       5: astore        5
       7: aload         5
       9: ifnonnull     14
      12: aconst_null
      13: areturn
      14: aload_0
      15: getfield      #4                  // Field log:Lorg/slf4j/Logger;
      18: ldc           #6                  // String Attempting to follow same-document KeyInfoReference
      20: invokeinterface #7,  2            // InterfaceMethod org/slf4j/Logger.debug:(Ljava/lang/String;)V
      25: aload         5
      27: aload         5
      29: invokeinterface #8,  1            // InterfaceMethod org/opensaml/xmlsec/signature/KeyInfoReference.getURI:()Ljava/lang/String;
      34: iconst_1
      35: invokevirtual #9                  // Method java/lang/String.substring:(I)Ljava/lang/String;
      38: invokeinterface #10,  2           // InterfaceMethod org/opensaml/xmlsec/signature/KeyInfoReference.resolveIDFromRoot:(Ljava/lang/String;)Lorg/opensaml/core/xml/XMLObject;
      43: astore        6
      45: aload         6
      47: ifnonnull     63
      50: aload_0
      51: getfield      #4                  // Field log:Lorg/slf4j/Logger;
      54: ldc           #11                 // String KeyInfoReference URI could not be dereferenced
      56: invokeinterface #12,  2           // InterfaceMethod org/slf4j/Logger.warn:(Ljava/lang/String;)V
      61: aconst_null
      62: areturn
      63: aload         6
      65: instanceof    #13                 // class org/opensaml/xmlsec/signature/KeyInfo
      68: ifne          84
      71: aload_0
      72: getfield      #4                  // Field log:Lorg/slf4j/Logger;
      75: ldc           #14                 // String The product of dereferencing the KeyInfoReference was not a KeyInfo
      77: invokeinterface #12,  2           // InterfaceMethod org/slf4j/Logger.warn:(Ljava/lang/String;)V
      82: aconst_null
      83: areturn
      84: aload         6
      86: checkcast     #13                 // class org/opensaml/xmlsec/signature/KeyInfo
      89: invokeinterface #15,  1           // InterfaceMethod org/opensaml/xmlsec/signature/KeyInfo.getKeyInfoReferences:()Ljava/util/List;
      94: invokeinterface #16,  1           // InterfaceMethod java/util/List.isEmpty:()Z
      99: ifne          115
     102: aload_0
     103: getfield      #4                  // Field log:Lorg/slf4j/Logger;
     106: ldc           #17                 // String The dereferenced KeyInfo contained a KeyInfoReference, cannot process
     108: invokeinterface #12,  2           // InterfaceMethod org/slf4j/Logger.warn:(Ljava/lang/String;)V
     113: aconst_null
     114: areturn
     115: aload_0
     116: getfield      #4                  // Field log:Lorg/slf4j/Logger;
     119: ldc           #18                 // String Recursively processing KeyInfoReference referent
     121: invokeinterface #7,  2            // InterfaceMethod org/slf4j/Logger.debug:(Ljava/lang/String;)V
     126: new           #19                 // class net/shibboleth/utilities/java/support/resolver/CriteriaSet
     129: dup
     130: invokespecial #20                 // Method net/shibboleth/utilities/java/support/resolver/CriteriaSet."<init>":()V
     133: astore        7
     135: aload         7
     137: new           #21                 // class org/opensaml/xmlsec/keyinfo/KeyInfoCriterion
     140: dup
     141: aload         6
     143: checkcast     #13                 // class org/opensaml/xmlsec/signature/KeyInfo
     146: invokespecial #22                 // Method org/opensaml/xmlsec/keyinfo/KeyInfoCriterion."<init>":(Lorg/opensaml/xmlsec/signature/KeyInfo;)V
     149: invokevirtual #23                 // Method net/shibboleth/utilities/java/support/resolver/CriteriaSet.add:(Ljava/lang/Object;)Z
     152: pop
     153: aload_3
     154: invokevirtual #24                 // Method net/shibboleth/utilities/java/support/resolver/CriteriaSet.iterator:()Ljava/util/Iterator;
     157: astore        8
     159: aload         8
     161: invokeinterface #25,  1           // InterfaceMethod java/util/Iterator.hasNext:()Z
     166: ifeq          200
     169: aload         8
     171: invokeinterface #26,  1           // InterfaceMethod java/util/Iterator.next:()Ljava/lang/Object;
     176: checkcast     #27                 // class net/shibboleth/utilities/java/support/resolver/Criterion
     179: astore        9
     181: aload         9
     183: instanceof    #21                 // class org/opensaml/xmlsec/keyinfo/KeyInfoCriterion
     186: ifne          197
     189: aload         7
     191: aload         9
     193: invokevirtual #23                 // Method net/shibboleth/utilities/java/support/resolver/CriteriaSet.add:(Ljava/lang/Object;)Z
     196: pop
     197: goto          159
     200: aload_1
     201: aload         7
     203: invokeinterface #28,  2           // InterfaceMethod org/opensaml/xmlsec/keyinfo/KeyInfoCredentialResolver.resolve:(Ljava/lang/Object;)Ljava/lang/Iterable;
     208: astore        8
     210: aload         8
     212: ifnull        271
     215: new           #29                 // class java/util/ArrayList
     218: dup
     219: invokespecial #30                 // Method java/util/ArrayList."<init>":()V
     222: astore        9
     224: aload         8
     226: invokeinterface #31,  1           // InterfaceMethod java/lang/Iterable.iterator:()Ljava/util/Iterator;
     231: astore        10
     233: aload         10
     235: invokeinterface #25,  1           // InterfaceMethod java/util/Iterator.hasNext:()Z
     240: ifeq          268
     243: aload         10
     245: invokeinterface #26,  1           // InterfaceMethod java/util/Iterator.next:()Ljava/lang/Object;
     250: checkcast     #32                 // class org/opensaml/security/credential/Credential
     253: astore        11
     255: aload         9
     257: aload         11
     259: invokeinterface #33,  2           // InterfaceMethod java/util/Collection.add:(Ljava/lang/Object;)Z
     264: pop
     265: goto          233
     268: aload         9
     270: areturn
     271: goto          289
     274: astore        8
     276: aload_0
     277: getfield      #4                  // Field log:Lorg/slf4j/Logger;
     280: ldc           #35                 // String Exception while resolving credentials from KeyInfoReference referent
     282: aload         8
     284: invokeinterface #36,  3           // InterfaceMethod org/slf4j/Logger.error:(Ljava/lang/String;Ljava/lang/Throwable;)V
     289: aconst_null
     290: areturn
    Exception table:
       from    to  target type
         200   270   274   Class net/shibboleth/utilities/java/support/resolver/ResolverException

  protected org.opensaml.xmlsec.signature.KeyInfoReference getKeyInfoReference(org.opensaml.core.xml.XMLObject);
    Code:
       0: aload_1
       1: instanceof    #37                 // class org/opensaml/xmlsec/signature/KeyInfoReference
       4: ifeq          45
       7: aload_1
       8: checkcast     #37                 // class org/opensaml/xmlsec/signature/KeyInfoReference
      11: astore_2
      12: aload_2
      13: invokeinterface #8,  1            // InterfaceMethod org/opensaml/xmlsec/signature/KeyInfoReference.getURI:()Ljava/lang/String;
      18: astore_3
      19: aload_3
      20: ifnull        34
      23: aload_3
      24: ldc           #38                 // String #
      26: invokevirtual #39                 // Method java/lang/String.startsWith:(Ljava/lang/String;)Z
      29: ifeq          34
      32: aload_2
      33: areturn
      34: aload_0
      35: getfield      #4                  // Field log:Lorg/slf4j/Logger;
      38: ldc           #40                 // String KeyInfoReference did not contain a same-document URI reference, cannot handle
      40: invokeinterface #7,  2            // InterfaceMethod org/slf4j/Logger.debug:(Ljava/lang/String;)V
      45: aconst_null
      46: areturn
}
