Compiled from "RecordBufferPageMgr.java"
public class org.apache.jena.tdb.base.recordbuffer.RecordBufferPageMgr extends org.apache.jena.tdb.base.page.PageBlockMgr<org.apache.jena.tdb.base.recordbuffer.RecordBufferPage> {
  public org.apache.jena.tdb.base.recordbuffer.RecordBufferPageMgr(org.apache.jena.tdb.base.record.RecordFactory, org.apache.jena.tdb.base.block.BlockMgr);
    Code:
       0: aload_0
       1: aconst_null
       2: aload_2
       3: invokespecial #1                  // Method org/apache/jena/tdb/base/page/PageBlockMgr."<init>":(Lorg/apache/jena/tdb/base/block/BlockConverter;Lorg/apache/jena/tdb/base/block/BlockMgr;)V
       6: new           #2                  // class org/apache/jena/tdb/base/recordbuffer/RecordBufferPageMgr$Block2RecordBufferPage
       9: dup
      10: aload_1
      11: invokespecial #3                  // Method org/apache/jena/tdb/base/recordbuffer/RecordBufferPageMgr$Block2RecordBufferPage."<init>":(Lorg/apache/jena/tdb/base/record/RecordFactory;)V
      14: astore_3
      15: aload_0
      16: aload_3
      17: invokespecial #4                  // Method org/apache/jena/tdb/base/page/PageBlockMgr.setConverter:(Lorg/apache/jena/tdb/base/block/BlockConverter;)V
      20: return

  public org.apache.jena.tdb.base.recordbuffer.RecordBufferPage create();
    Code:
       0: aload_0
       1: getstatic     #5                  // Field org/apache/jena/tdb/base/block/BlockType.RECORD_BLOCK:Lorg/apache/jena/tdb/base/block/BlockType;
       4: invokespecial #6                  // Method org/apache/jena/tdb/base/page/PageBlockMgr.create:(Lorg/apache/jena/tdb/base/block/BlockType;)Lorg/apache/jena/tdb/base/page/Page;
       7: checkcast     #7                  // class org/apache/jena/tdb/base/recordbuffer/RecordBufferPage
      10: areturn

  public org.apache.jena.tdb.base.recordbuffer.RecordBufferPage getReadIterator(int);
    Code:
       0: aload_0
       1: getfield      #8                  // Field blockMgr:Lorg/apache/jena/tdb/base/block/BlockMgr;
       4: iload_1
       5: i2l
       6: invokeinterface #9,  3            // InterfaceMethod org/apache/jena/tdb/base/block/BlockMgr.getReadIterator:(J)Lorg/apache/jena/tdb/base/block/Block;
      11: astore_2
      12: aload_0
      13: getfield      #10                 // Field pageFactory:Lorg/apache/jena/tdb/base/block/BlockConverter;
      16: aload_2
      17: invokeinterface #11,  2           // InterfaceMethod org/apache/jena/tdb/base/block/BlockConverter.fromBlock:(Lorg/apache/jena/tdb/base/block/Block;)Lorg/apache/jena/tdb/base/page/Page;
      22: checkcast     #7                  // class org/apache/jena/tdb/base/recordbuffer/RecordBufferPage
      25: astore_3
      26: aload_3
      27: areturn
}
