Compiled from "derivation.scala"
public final class eu.timepit.refined.scalaz.derivation {
  public static <F, G, T, P> G refTypeViaMonadError(scalaz.MonadError<G, java.lang.String>, eu.timepit.refined.api.RefType<F>, eu.timepit.refined.api.Validate<T, P>, G);
    Code:
       0: getstatic     #21                 // Field eu/timepit/refined/scalaz/derivation$.MODULE$:Leu/timepit/refined/scalaz/derivation$;
       3: aload_0
       4: aload_1
       5: aload_2
       6: aload_3
       7: invokevirtual #23                 // Method eu/timepit/refined/scalaz/derivation$.refTypeViaMonadError:(Lscalaz/MonadError;Leu/timepit/refined/api/RefType;Leu/timepit/refined/api/Validate;Ljava/lang/Object;)Ljava/lang/Object;
      10: areturn

  public static <F, G, T, P> G refTypeViaContravariant(scalaz.Contravariant<G>, eu.timepit.refined.api.RefType<F>, G);
    Code:
       0: getstatic     #21                 // Field eu/timepit/refined/scalaz/derivation$.MODULE$:Leu/timepit/refined/scalaz/derivation$;
       3: aload_0
       4: aload_1
       5: aload_2
       6: invokevirtual #29                 // Method eu/timepit/refined/scalaz/derivation$.refTypeViaContravariant:(Lscalaz/Contravariant;Leu/timepit/refined/api/RefType;Ljava/lang/Object;)Ljava/lang/Object;
       9: areturn
}
