Compiled from "ElementPointerPart.java"
public class org.apache.woden.xpointer.ElementPointerPart implements org.apache.woden.xpointer.PointerPart {
  private final org.apache.woden.types.NCName ncname;

  private final java.util.List<java.lang.Integer> childSequence;

  public org.apache.woden.xpointer.ElementPointerPart(org.apache.woden.types.NCName);
    Code:
       0: aload_0
       1: invokespecial #1                  // Method java/lang/Object."<init>":()V
       4: aload_1
       5: ifnonnull     18
       8: new           #2                  // class java/lang/NullPointerException
      11: dup
      12: ldc           #3                  // String The elementID argument is null.
      14: invokespecial #4                  // Method java/lang/NullPointerException."<init>":(Ljava/lang/String;)V
      17: athrow
      18: aload_0
      19: aload_1
      20: putfield      #5                  // Field ncname:Lorg/apache/woden/types/NCName;
      23: aload_0
      24: aconst_null
      25: putfield      #6                  // Field childSequence:Ljava/util/List;
      28: return

  public org.apache.woden.xpointer.ElementPointerPart(java.util.List<java.lang.Integer>);
    Code:
       0: aload_0
       1: invokespecial #1                  // Method java/lang/Object."<init>":()V
       4: aload_1
       5: ifnonnull     18
       8: new           #2                  // class java/lang/NullPointerException
      11: dup
      12: ldc           #7                  // String The childSequence argument is null.
      14: invokespecial #4                  // Method java/lang/NullPointerException."<init>":(Ljava/lang/String;)V
      17: athrow
      18: aload_1
      19: invokeinterface #8,  1            // InterfaceMethod java/util/List.isEmpty:()Z
      24: ifeq          37
      27: new           #9                  // class java/lang/IllegalArgumentException
      30: dup
      31: ldc           #10                 // String The childSequence list is empty.
      33: invokespecial #11                 // Method java/lang/IllegalArgumentException."<init>":(Ljava/lang/String;)V
      36: athrow
      37: aload_0
      38: aconst_null
      39: putfield      #5                  // Field ncname:Lorg/apache/woden/types/NCName;
      42: aload_0
      43: aload_1
      44: putfield      #6                  // Field childSequence:Ljava/util/List;
      47: return

  public org.apache.woden.xpointer.ElementPointerPart(org.apache.woden.types.NCName, java.util.List<java.lang.Integer>);
    Code:
       0: aload_0
       1: invokespecial #1                  // Method java/lang/Object."<init>":()V
       4: aload_1
       5: ifnonnull     18
       8: new           #2                  // class java/lang/NullPointerException
      11: dup
      12: ldc           #3                  // String The elementID argument is null.
      14: invokespecial #4                  // Method java/lang/NullPointerException."<init>":(Ljava/lang/String;)V
      17: athrow
      18: aload_2
      19: ifnonnull     32
      22: new           #2                  // class java/lang/NullPointerException
      25: dup
      26: ldc           #7                  // String The childSequence argument is null.
      28: invokespecial #4                  // Method java/lang/NullPointerException."<init>":(Ljava/lang/String;)V
      31: athrow
      32: aload_2
      33: invokeinterface #8,  1            // InterfaceMethod java/util/List.isEmpty:()Z
      38: ifeq          51
      41: new           #9                  // class java/lang/IllegalArgumentException
      44: dup
      45: ldc           #10                 // String The childSequence list is empty.
      47: invokespecial #11                 // Method java/lang/IllegalArgumentException."<init>":(Ljava/lang/String;)V
      50: athrow
      51: aload_2
      52: iconst_0
      53: invokestatic  #12                 // Method java/lang/Integer.valueOf:(I)Ljava/lang/Integer;
      56: invokeinterface #13,  2           // InterfaceMethod java/util/List.contains:(Ljava/lang/Object;)Z
      61: ifeq          74
      64: new           #9                  // class java/lang/IllegalArgumentException
      67: dup
      68: ldc           #14                 // String the childSequence list must only contain Integers bigger than 0.
      70: invokespecial #11                 // Method java/lang/IllegalArgumentException."<init>":(Ljava/lang/String;)V
      73: athrow
      74: aload_0
      75: aload_1
      76: putfield      #5                  // Field ncname:Lorg/apache/woden/types/NCName;
      79: aload_0
      80: aload_2
      81: putfield      #6                  // Field childSequence:Ljava/util/List;
      84: return

  public org.apache.woden.types.NCName getNCName();
    Code:
       0: aload_0
       1: getfield      #5                  // Field ncname:Lorg/apache/woden/types/NCName;
       4: areturn

  public java.lang.Integer[] getChildSequence();
    Code:
       0: aload_0
       1: getfield      #6                  // Field childSequence:Ljava/util/List;
       4: invokeinterface #15,  1           // InterfaceMethod java/util/List.size:()I
       9: istore_1
      10: iload_1
      11: anewarray     #16                 // class java/lang/Integer
      14: astore_2
      15: iconst_0
      16: istore_3
      17: iload_3
      18: iload_1
      19: if_icmpge     44
      22: aload_2
      23: iload_3
      24: aload_0
      25: getfield      #6                  // Field childSequence:Ljava/util/List;
      28: iload_3
      29: invokeinterface #17,  2           // InterfaceMethod java/util/List.get:(I)Ljava/lang/Object;
      34: checkcast     #16                 // class java/lang/Integer
      37: aastore
      38: iinc          3, 1
      41: goto          17
      44: aload_2
      45: areturn

  public boolean hasNCName();
    Code:
       0: aload_0
       1: getfield      #5                  // Field ncname:Lorg/apache/woden/types/NCName;
       4: ifnull        11
       7: iconst_1
       8: goto          12
      11: iconst_0
      12: ireturn

  public boolean hasChildSequence();
    Code:
       0: aload_0
       1: getfield      #6                  // Field childSequence:Ljava/util/List;
       4: ifnull        11
       7: iconst_1
       8: goto          12
      11: iconst_0
      12: ireturn

  public java.lang.String toString();
    Code:
       0: aload_0
       1: getfield      #6                  // Field childSequence:Ljava/util/List;
       4: ifnonnull     18
       7: aload_0
       8: getfield      #5                  // Field ncname:Lorg/apache/woden/types/NCName;
      11: invokevirtual #18                 // Method org/apache/woden/types/NCName.toString:()Ljava/lang/String;
      14: astore_1
      15: goto          61
      18: aload_0
      19: getfield      #5                  // Field ncname:Lorg/apache/woden/types/NCName;
      22: ifnonnull     33
      25: aload_0
      26: invokespecial #19                 // Method serialiseChildSequence:()Ljava/lang/String;
      29: astore_1
      30: goto          61
      33: new           #20                 // class java/lang/StringBuilder
      36: dup
      37: invokespecial #21                 // Method java/lang/StringBuilder."<init>":()V
      40: aload_0
      41: getfield      #5                  // Field ncname:Lorg/apache/woden/types/NCName;
      44: invokevirtual #18                 // Method org/apache/woden/types/NCName.toString:()Ljava/lang/String;
      47: invokevirtual #22                 // Method java/lang/StringBuilder.append:(Ljava/lang/String;)Ljava/lang/StringBuilder;
      50: aload_0
      51: invokespecial #19                 // Method serialiseChildSequence:()Ljava/lang/String;
      54: invokevirtual #22                 // Method java/lang/StringBuilder.append:(Ljava/lang/String;)Ljava/lang/StringBuilder;
      57: invokevirtual #23                 // Method java/lang/StringBuilder.toString:()Ljava/lang/String;
      60: astore_1
      61: new           #20                 // class java/lang/StringBuilder
      64: dup
      65: invokespecial #21                 // Method java/lang/StringBuilder."<init>":()V
      68: ldc           #24                 // String element(
      70: invokevirtual #22                 // Method java/lang/StringBuilder.append:(Ljava/lang/String;)Ljava/lang/StringBuilder;
      73: aload_1
      74: invokevirtual #22                 // Method java/lang/StringBuilder.append:(Ljava/lang/String;)Ljava/lang/StringBuilder;
      77: ldc           #25                 // String )
      79: invokevirtual #22                 // Method java/lang/StringBuilder.append:(Ljava/lang/String;)Ljava/lang/StringBuilder;
      82: invokevirtual #23                 // Method java/lang/StringBuilder.toString:()Ljava/lang/String;
      85: areturn

  private java.lang.String serialiseChildSequence();
    Code:
       0: new           #26                 // class java/lang/StringBuffer
       3: dup
       4: invokespecial #27                 // Method java/lang/StringBuffer."<init>":()V
       7: astore_1
       8: aload_0
       9: getfield      #6                  // Field childSequence:Ljava/util/List;
      12: invokeinterface #28,  1           // InterfaceMethod java/util/List.iterator:()Ljava/util/Iterator;
      17: astore_2
      18: aload_2
      19: invokeinterface #29,  1           // InterfaceMethod java/util/Iterator.hasNext:()Z
      24: ifeq          67
      27: aload_2
      28: invokeinterface #30,  1           // InterfaceMethod java/util/Iterator.next:()Ljava/lang/Object;
      33: checkcast     #16                 // class java/lang/Integer
      36: astore_3
      37: aload_1
      38: new           #20                 // class java/lang/StringBuilder
      41: dup
      42: invokespecial #21                 // Method java/lang/StringBuilder."<init>":()V
      45: ldc           #31                 // String /
      47: invokevirtual #22                 // Method java/lang/StringBuilder.append:(Ljava/lang/String;)Ljava/lang/StringBuilder;
      50: aload_3
      51: invokevirtual #32                 // Method java/lang/Integer.toString:()Ljava/lang/String;
      54: invokevirtual #22                 // Method java/lang/StringBuilder.append:(Ljava/lang/String;)Ljava/lang/StringBuilder;
      57: invokevirtual #23                 // Method java/lang/StringBuilder.toString:()Ljava/lang/String;
      60: invokevirtual #33                 // Method java/lang/StringBuffer.append:(Ljava/lang/String;)Ljava/lang/StringBuffer;
      63: pop
      64: goto          18
      67: aload_1
      68: invokevirtual #34                 // Method java/lang/StringBuffer.toString:()Ljava/lang/String;
      71: areturn

  public static org.apache.woden.xpointer.ElementPointerPart parseFromString(java.lang.String) throws org.apache.woden.xpointer.InvalidXPointerException;
    Code:
       0: aconst_null
       1: astore_1
       2: aconst_null
       3: astore_2
       4: aload_0
       5: ldc           #31                 // String /
       7: invokevirtual #35                 // Method java/lang/String.indexOf:(Ljava/lang/String;)I
      10: istore_3
      11: iload_3
      12: lookupswitch  { // 2
                    -1: 40
                     0: 74
               default: 77
          }
      40: new           #36                 // class org/apache/woden/types/NCName
      43: dup
      44: aload_0
      45: invokespecial #37                 // Method org/apache/woden/types/NCName."<init>":(Ljava/lang/String;)V
      48: astore_2
      49: goto          65
      52: astore        5
      54: new           #38                 // class org/apache/woden/xpointer/InvalidXPointerException
      57: dup
      58: ldc           #39                 // String Invalid NCName in the XPointer
      60: aload_0
      61: invokespecial #40                 // Method org/apache/woden/xpointer/InvalidXPointerException."<init>":(Ljava/lang/String;Ljava/lang/String;)V
      64: athrow
      65: new           #41                 // class org/apache/woden/xpointer/ElementPointerPart
      68: dup
      69: aload_2
      70: invokespecial #42                 // Method "<init>":(Lorg/apache/woden/types/NCName;)V
      73: areturn
      74: goto          109
      77: new           #36                 // class org/apache/woden/types/NCName
      80: dup
      81: aload_0
      82: iconst_0
      83: iload_3
      84: invokevirtual #43                 // Method java/lang/String.substring:(II)Ljava/lang/String;
      87: invokespecial #37                 // Method org/apache/woden/types/NCName."<init>":(Ljava/lang/String;)V
      90: astore_2
      91: goto          109
      94: astore        5
      96: new           #38                 // class org/apache/woden/xpointer/InvalidXPointerException
      99: dup
     100: ldc           #39                 // String Invalid NCName in the XPointer
     102: aload_0
     103: iconst_0
     104: iload_3
     105: invokespecial #44                 // Method org/apache/woden/xpointer/InvalidXPointerException."<init>":(Ljava/lang/String;Ljava/lang/String;II)V
     108: athrow
     109: new           #45                 // class java/util/ArrayList
     112: dup
     113: invokespecial #46                 // Method java/util/ArrayList."<init>":()V
     116: astore_1
     117: aload_0
     118: ldc           #31                 // String /
     120: iload_3
     121: iconst_1
     122: iadd
     123: invokevirtual #47                 // Method java/lang/String.indexOf:(Ljava/lang/String;I)I
     126: istore        4
     128: iload         4
     130: ifge          154
     133: aload_1
     134: aload_0
     135: iload_3
     136: iconst_1
     137: iadd
     138: aload_0
     139: invokevirtual #48                 // Method java/lang/String.length:()I
     142: invokestatic  #49                 // Method parseIntegerFromChildSequence:(Ljava/lang/String;II)Ljava/lang/Integer;
     145: invokeinterface #50,  2           // InterfaceMethod java/util/List.add:(Ljava/lang/Object;)Z
     150: pop
     151: goto          213
     154: iload         4
     156: ifge          180
     159: aload_1
     160: aload_0
     161: iload_3
     162: iconst_1
     163: iadd
     164: aload_0
     165: invokevirtual #48                 // Method java/lang/String.length:()I
     168: invokestatic  #49                 // Method parseIntegerFromChildSequence:(Ljava/lang/String;II)Ljava/lang/Integer;
     171: invokeinterface #50,  2           // InterfaceMethod java/util/List.add:(Ljava/lang/Object;)Z
     176: pop
     177: goto          213
     180: aload_1
     181: aload_0
     182: iload_3
     183: iconst_1
     184: iadd
     185: iload         4
     187: invokestatic  #49                 // Method parseIntegerFromChildSequence:(Ljava/lang/String;II)Ljava/lang/Integer;
     190: invokeinterface #50,  2           // InterfaceMethod java/util/List.add:(Ljava/lang/Object;)Z
     195: pop
     196: iload         4
     198: istore_3
     199: aload_0
     200: ldc           #31                 // String /
     202: iload_3
     203: iconst_1
     204: iadd
     205: invokevirtual #47                 // Method java/lang/String.indexOf:(Ljava/lang/String;I)I
     208: istore        4
     210: goto          154
     213: aload_2
     214: ifnonnull     226
     217: new           #41                 // class org/apache/woden/xpointer/ElementPointerPart
     220: dup
     221: aload_1
     222: invokespecial #51                 // Method "<init>":(Ljava/util/List;)V
     225: areturn
     226: new           #41                 // class org/apache/woden/xpointer/ElementPointerPart
     229: dup
     230: aload_2
     231: aload_1
     232: invokespecial #52                 // Method "<init>":(Lorg/apache/woden/types/NCName;Ljava/util/List;)V
     235: areturn
    Exception table:
       from    to  target type
          40    49    52   Class java/lang/IllegalArgumentException
          77    91    94   Class java/lang/IllegalArgumentException

  private static java.lang.Integer parseIntegerFromChildSequence(java.lang.String, int, int) throws org.apache.woden.xpointer.InvalidXPointerException;
    Code:
       0: iload_1
       1: iload_2
       2: if_icmpge     33
       5: new           #16                 // class java/lang/Integer
       8: dup
       9: aload_0
      10: iload_1
      11: iload_2
      12: invokevirtual #43                 // Method java/lang/String.substring:(II)Ljava/lang/String;
      15: invokespecial #53                 // Method java/lang/Integer."<init>":(Ljava/lang/String;)V
      18: areturn
      19: astore_3
      20: new           #38                 // class org/apache/woden/xpointer/InvalidXPointerException
      23: dup
      24: ldc           #55                 // String The child sequence part contained a invalid integer.
      26: aload_0
      27: iload_1
      28: iload_2
      29: invokespecial #44                 // Method org/apache/woden/xpointer/InvalidXPointerException."<init>":(Ljava/lang/String;Ljava/lang/String;II)V
      32: athrow
      33: new           #38                 // class org/apache/woden/xpointer/InvalidXPointerException
      36: dup
      37: new           #20                 // class java/lang/StringBuilder
      40: dup
      41: invokespecial #21                 // Method java/lang/StringBuilder."<init>":()V
      44: ldc           #56                 // String The child sequence part contained a empty item at
      46: invokevirtual #22                 // Method java/lang/StringBuilder.append:(Ljava/lang/String;)Ljava/lang/StringBuilder;
      49: iload_1
      50: invokestatic  #57                 // Method java/lang/String.valueOf:(I)Ljava/lang/String;
      53: invokevirtual #22                 // Method java/lang/StringBuilder.append:(Ljava/lang/String;)Ljava/lang/StringBuilder;
      56: invokevirtual #23                 // Method java/lang/StringBuilder.toString:()Ljava/lang/String;
      59: aload_0
      60: iload_1
      61: iload_2
      62: invokespecial #44                 // Method org/apache/woden/xpointer/InvalidXPointerException."<init>":(Ljava/lang/String;Ljava/lang/String;II)V
      65: athrow
    Exception table:
       from    to  target type
           5    18    19   Class java/lang/NumberFormatException
}
