public class org.bouncycastle.pqc.jcajce.provider.rainbow.RainbowKeysToParams {
  public org.bouncycastle.pqc.jcajce.provider.rainbow.RainbowKeysToParams();
    Code:
       0: aload_0
       1: invokespecial #73                 // Method java/lang/Object."<init>":()V
       4: return

  public static org.bouncycastle.crypto.params.AsymmetricKeyParameter generatePublicKeyParameter(java.security.PublicKey) throws java.security.InvalidKeyException;
    Code:
       0: aload_0
       1: instanceof    #44                 // class org/bouncycastle/pqc/jcajce/provider/rainbow/BCRainbowPublicKey
       4: ifeq          36
       7: aload_0
       8: checkcast     #44                 // class org/bouncycastle/pqc/jcajce/provider/rainbow/BCRainbowPublicKey
      11: astore_1
      12: new           #42                 // class org/bouncycastle/pqc/crypto/rainbow/RainbowPublicKeyParameters
      15: dup
      16: aload_1
      17: invokevirtual #87                 // Method org/bouncycastle/pqc/jcajce/provider/rainbow/BCRainbowPublicKey.getDocLength:()I
      20: aload_1
      21: invokevirtual #89                 // Method org/bouncycastle/pqc/jcajce/provider/rainbow/BCRainbowPublicKey.getCoeffQuadratic:()[[S
      24: aload_1
      25: invokevirtual #90                 // Method org/bouncycastle/pqc/jcajce/provider/rainbow/BCRainbowPublicKey.getCoeffSingular:()[[S
      28: aload_1
      29: invokevirtual #88                 // Method org/bouncycastle/pqc/jcajce/provider/rainbow/BCRainbowPublicKey.getCoeffScalar:()[S
      32: invokespecial #80                 // Method org/bouncycastle/pqc/crypto/rainbow/RainbowPublicKeyParameters."<init>":(I[[S[[S[S)V
      35: areturn
      36: new           #40                 // class java/security/InvalidKeyException
      39: dup
      40: new           #39                 // class java/lang/StringBuilder
      43: dup
      44: invokespecial #75                 // Method java/lang/StringBuilder."<init>":()V
      47: ldc           #2                  // String can\'t identify Rainbow public key:
      49: invokevirtual #77                 // Method java/lang/StringBuilder.append:(Ljava/lang/String;)Ljava/lang/StringBuilder;
      52: aload_0
      53: invokevirtual #74                 // Method java/lang/Object.getClass:()Ljava/lang/Class;
      56: invokevirtual #72                 // Method java/lang/Class.getName:()Ljava/lang/String;
      59: invokevirtual #77                 // Method java/lang/StringBuilder.append:(Ljava/lang/String;)Ljava/lang/StringBuilder;
      62: invokevirtual #76                 // Method java/lang/StringBuilder.toString:()Ljava/lang/String;
      65: invokespecial #78                 // Method java/security/InvalidKeyException."<init>":(Ljava/lang/String;)V
      68: athrow

  public static org.bouncycastle.crypto.params.AsymmetricKeyParameter generatePrivateKeyParameter(java.security.PrivateKey) throws java.security.InvalidKeyException;
    Code:
       0: aload_0
       1: instanceof    #43                 // class org/bouncycastle/pqc/jcajce/provider/rainbow/BCRainbowPrivateKey
       4: ifeq          44
       7: aload_0
       8: checkcast     #43                 // class org/bouncycastle/pqc/jcajce/provider/rainbow/BCRainbowPrivateKey
      11: astore_1
      12: new           #41                 // class org/bouncycastle/pqc/crypto/rainbow/RainbowPrivateKeyParameters
      15: dup
      16: aload_1
      17: invokevirtual #84                 // Method org/bouncycastle/pqc/jcajce/provider/rainbow/BCRainbowPrivateKey.getInvA1:()[[S
      20: aload_1
      21: invokevirtual #82                 // Method org/bouncycastle/pqc/jcajce/provider/rainbow/BCRainbowPrivateKey.getB1:()[S
      24: aload_1
      25: invokevirtual #85                 // Method org/bouncycastle/pqc/jcajce/provider/rainbow/BCRainbowPrivateKey.getInvA2:()[[S
      28: aload_1
      29: invokevirtual #83                 // Method org/bouncycastle/pqc/jcajce/provider/rainbow/BCRainbowPrivateKey.getB2:()[S
      32: aload_1
      33: invokevirtual #81                 // Method org/bouncycastle/pqc/jcajce/provider/rainbow/BCRainbowPrivateKey.getVi:()[I
      36: aload_1
      37: invokevirtual #86                 // Method org/bouncycastle/pqc/jcajce/provider/rainbow/BCRainbowPrivateKey.getLayers:()[Lorg/bouncycastle/pqc/crypto/rainbow/Layer;
      40: invokespecial #79                 // Method org/bouncycastle/pqc/crypto/rainbow/RainbowPrivateKeyParameters."<init>":([[S[S[[S[S[I[Lorg/bouncycastle/pqc/crypto/rainbow/Layer;)V
      43: areturn
      44: new           #40                 // class java/security/InvalidKeyException
      47: dup
      48: ldc           #1                  // String can\'t identify Rainbow private key.
      50: invokespecial #78                 // Method java/security/InvalidKeyException."<init>":(Ljava/lang/String;)V
      53: athrow
}
