Compiled from "PartitionMetadata.java"
public class org.joyqueue.client.internal.metadata.domain.PartitionMetadata implements java.io.Serializable {
  private short id;

  private int partitionGroupId;

  private java.lang.String topic;

  private org.joyqueue.network.domain.BrokerNode leader;

  public org.joyqueue.client.internal.metadata.domain.PartitionMetadata(short, int, java.lang.String, org.joyqueue.network.domain.BrokerNode);
    Code:
       0: aload_0
       1: invokespecial #1                  // Method java/lang/Object."<init>":()V
       4: aload_0
       5: iload_1
       6: putfield      #2                  // Field id:S
       9: aload_0
      10: iload_2
      11: putfield      #3                  // Field partitionGroupId:I
      14: aload_0
      15: aload_3
      16: putfield      #4                  // Field topic:Ljava/lang/String;
      19: aload_0
      20: aload         4
      22: putfield      #5                  // Field leader:Lorg/joyqueue/network/domain/BrokerNode;
      25: return

  public short getId();
    Code:
       0: aload_0
       1: getfield      #2                  // Field id:S
       4: ireturn

  public int getPartitionGroupId();
    Code:
       0: aload_0
       1: getfield      #3                  // Field partitionGroupId:I
       4: ireturn

  public java.lang.String getTopic();
    Code:
       0: aload_0
       1: getfield      #4                  // Field topic:Ljava/lang/String;
       4: areturn

  public org.joyqueue.network.domain.BrokerNode getLeader();
    Code:
       0: aload_0
       1: getfield      #5                  // Field leader:Lorg/joyqueue/network/domain/BrokerNode;
       4: areturn

  public boolean equals(java.lang.Object);
    Code:
       0: aload_0
       1: aload_1
       2: if_acmpne     7
       5: iconst_1
       6: ireturn
       7: aload_1
       8: ifnull        22
      11: aload_0
      12: invokevirtual #6                  // Method java/lang/Object.getClass:()Ljava/lang/Class;
      15: aload_1
      16: invokevirtual #6                  // Method java/lang/Object.getClass:()Ljava/lang/Class;
      19: if_acmpeq     24
      22: iconst_0
      23: ireturn
      24: aload_1
      25: checkcast     #7                  // class org/joyqueue/client/internal/metadata/domain/PartitionMetadata
      28: astore_2
      29: aload_0
      30: getfield      #2                  // Field id:S
      33: aload_2
      34: getfield      #2                  // Field id:S
      37: if_icmpne     69
      40: aload_0
      41: getfield      #3                  // Field partitionGroupId:I
      44: aload_2
      45: getfield      #3                  // Field partitionGroupId:I
      48: if_icmpne     69
      51: aload_0
      52: getfield      #4                  // Field topic:Ljava/lang/String;
      55: aload_2
      56: getfield      #4                  // Field topic:Ljava/lang/String;
      59: invokestatic  #8                  // Method com/google/common/base/Objects.equal:(Ljava/lang/Object;Ljava/lang/Object;)Z
      62: ifeq          69
      65: iconst_1
      66: goto          70
      69: iconst_0
      70: ireturn

  public int hashCode();
    Code:
       0: iconst_3
       1: anewarray     #9                  // class java/lang/Object
       4: dup
       5: iconst_0
       6: aload_0
       7: getfield      #2                  // Field id:S
      10: invokestatic  #10                 // Method java/lang/Short.valueOf:(S)Ljava/lang/Short;
      13: aastore
      14: dup
      15: iconst_1
      16: aload_0
      17: getfield      #3                  // Field partitionGroupId:I
      20: invokestatic  #11                 // Method java/lang/Integer.valueOf:(I)Ljava/lang/Integer;
      23: aastore
      24: dup
      25: iconst_2
      26: aload_0
      27: getfield      #4                  // Field topic:Ljava/lang/String;
      30: aastore
      31: invokestatic  #12                 // Method com/google/common/base/Objects.hashCode:([Ljava/lang/Object;)I
      34: ireturn

  public java.lang.String toString();
    Code:
       0: new           #13                 // class java/lang/StringBuilder
       3: dup
       4: invokespecial #14                 // Method java/lang/StringBuilder."<init>":()V
       7: ldc           #15                 // String PartitionMetadata{id=
       9: invokevirtual #16                 // Method java/lang/StringBuilder.append:(Ljava/lang/String;)Ljava/lang/StringBuilder;
      12: aload_0
      13: getfield      #2                  // Field id:S
      16: invokevirtual #17                 // Method java/lang/StringBuilder.append:(I)Ljava/lang/StringBuilder;
      19: ldc           #18                 // String , partitionGroupId=
      21: invokevirtual #16                 // Method java/lang/StringBuilder.append:(Ljava/lang/String;)Ljava/lang/StringBuilder;
      24: aload_0
      25: getfield      #3                  // Field partitionGroupId:I
      28: invokevirtual #17                 // Method java/lang/StringBuilder.append:(I)Ljava/lang/StringBuilder;
      31: ldc           #19                 // String , leader=
      33: invokevirtual #16                 // Method java/lang/StringBuilder.append:(Ljava/lang/String;)Ljava/lang/StringBuilder;
      36: aload_0
      37: getfield      #5                  // Field leader:Lorg/joyqueue/network/domain/BrokerNode;
      40: invokevirtual #20                 // Method java/lang/StringBuilder.append:(Ljava/lang/Object;)Ljava/lang/StringBuilder;
      43: bipush        125
      45: invokevirtual #21                 // Method java/lang/StringBuilder.append:(C)Ljava/lang/StringBuilder;
      48: invokevirtual #22                 // Method java/lang/StringBuilder.toString:()Ljava/lang/String;
      51: areturn
}
