Compiled from "DistributedPubSubMediator.scala"
public class akka.cluster.pubsub.DistributedPubSubMediator$Internal$Delta$ extends scala.runtime.AbstractFunction1<scala.collection.immutable.Iterable<akka.cluster.pubsub.DistributedPubSubMediator$Internal$Bucket>, akka.cluster.pubsub.DistributedPubSubMediator$Internal$Delta> implements scala.Serializable {
  public static final akka.cluster.pubsub.DistributedPubSubMediator$Internal$Delta$ MODULE$;

  public static {};
    Code:
       0: new           #2                  // class akka/cluster/pubsub/DistributedPubSubMediator$Internal$Delta$
       3: invokespecial #15                 // Method "<init>":()V
       6: return

  public final java.lang.String toString();
    Code:
       0: ldc           #19                 // String Delta
       2: areturn

  public akka.cluster.pubsub.DistributedPubSubMediator$Internal$Delta apply(scala.collection.immutable.Iterable<akka.cluster.pubsub.DistributedPubSubMediator$Internal$Bucket>);
    Code:
       0: new           #24                 // class akka/cluster/pubsub/DistributedPubSubMediator$Internal$Delta
       3: dup
       4: aload_1
       5: invokespecial #27                 // Method akka/cluster/pubsub/DistributedPubSubMediator$Internal$Delta."<init>":(Lscala/collection/immutable/Iterable;)V
       8: areturn

  public scala.Option<scala.collection.immutable.Iterable<akka.cluster.pubsub.DistributedPubSubMediator$Internal$Bucket>> unapply(akka.cluster.pubsub.DistributedPubSubMediator$Internal$Delta);
    Code:
       0: aload_1
       1: ifnonnull     10
       4: getstatic     #36                 // Field scala/None$.MODULE$:Lscala/None$;
       7: goto          21
      10: new           #38                 // class scala/Some
      13: dup
      14: aload_1
      15: invokevirtual #41                 // Method akka/cluster/pubsub/DistributedPubSubMediator$Internal$Delta.buckets:()Lscala/collection/immutable/Iterable;
      18: invokespecial #44                 // Method scala/Some."<init>":(Ljava/lang/Object;)V
      21: areturn

  private java.lang.Object readResolve();
    Code:
       0: getstatic     #52                 // Field MODULE$:Lakka/cluster/pubsub/DistributedPubSubMediator$Internal$Delta$;
       3: areturn

  public java.lang.Object apply(java.lang.Object);
    Code:
       0: aload_0
       1: aload_1
       2: checkcast     #55                 // class scala/collection/immutable/Iterable
       5: invokevirtual #57                 // Method apply:(Lscala/collection/immutable/Iterable;)Lakka/cluster/pubsub/DistributedPubSubMediator$Internal$Delta;
       8: areturn

  public akka.cluster.pubsub.DistributedPubSubMediator$Internal$Delta$();
    Code:
       0: aload_0
       1: invokespecial #60                 // Method scala/runtime/AbstractFunction1."<init>":()V
       4: aload_0
       5: putstatic     #52                 // Field MODULE$:Lakka/cluster/pubsub/DistributedPubSubMediator$Internal$Delta$;
       8: return
}
