Compiled from "LocalJobRunner.java"
class org.apache.hadoop.mapred.LocalJobRunner$Job extends java.lang.Thread implements org.apache.hadoop.mapred.TaskUmbilicalProtocol {
  private org.apache.hadoop.fs.Path systemJobDir;

  private org.apache.hadoop.fs.Path systemJobFile;

  private org.apache.hadoop.fs.Path localJobDir;

  private org.apache.hadoop.fs.Path localJobFile;

  private org.apache.hadoop.mapred.JobID id;

  private org.apache.hadoop.mapred.JobConf job;

  private int numMapTasks;

  private int numReduceTasks;

  private float[] partialMapProgress;

  private float[] partialReduceProgress;

  private org.apache.hadoop.mapred.Counters[] mapCounters;

  private org.apache.hadoop.mapred.Counters[] reduceCounters;

  private org.apache.hadoop.mapred.JobStatus status;

  private java.util.List<org.apache.hadoop.mapred.TaskAttemptID> mapIds;

  private org.apache.hadoop.mapred.JobProfile profile;

  private org.apache.hadoop.fs.FileSystem localFs;

  boolean killed;

  private org.apache.hadoop.mapred.LocalDistributedCacheManager localDistributedCacheManager;

  final org.apache.hadoop.mapred.LocalJobRunner this$0;

  public long getProtocolVersion(java.lang.String, long);
    Code:
       0: ldc2_w        #8                  // long 21l
       3: lreturn

  public org.apache.hadoop.ipc.ProtocolSignature getProtocolSignature(java.lang.String, long, int) throws java.io.IOException;
    Code:
       0: aload_0
       1: aload_1
       2: lload_2
       3: iload         4
       5: invokestatic  #10                 // Method org/apache/hadoop/ipc/ProtocolSignature.getProtocolSignature:(Lorg/apache/hadoop/ipc/VersionedProtocol;Ljava/lang/String;JI)Lorg/apache/hadoop/ipc/ProtocolSignature;
       8: areturn

  public org.apache.hadoop.mapred.LocalJobRunner$Job(org.apache.hadoop.mapred.LocalJobRunner, org.apache.hadoop.mapred.JobID, java.lang.String) throws java.io.IOException;
    Code:
       0: aload_0
       1: aload_1
       2: putfield      #11                 // Field this$0:Lorg/apache/hadoop/mapred/LocalJobRunner;
       5: aload_0
       6: invokespecial #12                 // Method java/lang/Thread."<init>":()V
       9: aload_0
      10: new           #13                 // class java/util/ArrayList
      13: dup
      14: invokespecial #14                 // Method java/util/ArrayList."<init>":()V
      17: invokestatic  #15                 // Method java/util/Collections.synchronizedList:(Ljava/util/List;)Ljava/util/List;
      20: putfield      #5                  // Field mapIds:Ljava/util/List;
      23: aload_0
      24: iconst_0
      25: putfield      #16                 // Field killed:Z
      28: aload_0
      29: new           #17                 // class org/apache/hadoop/fs/Path
      32: dup
      33: aload_3
      34: invokespecial #18                 // Method org/apache/hadoop/fs/Path."<init>":(Ljava/lang/String;)V
      37: putfield      #19                 // Field systemJobDir:Lorg/apache/hadoop/fs/Path;
      40: aload_0
      41: new           #17                 // class org/apache/hadoop/fs/Path
      44: dup
      45: aload_0
      46: getfield      #19                 // Field systemJobDir:Lorg/apache/hadoop/fs/Path;
      49: ldc           #20                 // String job.xml
      51: invokespecial #21                 // Method org/apache/hadoop/fs/Path."<init>":(Lorg/apache/hadoop/fs/Path;Ljava/lang/String;)V
      54: putfield      #4                  // Field systemJobFile:Lorg/apache/hadoop/fs/Path;
      57: aload_0
      58: aload_2
      59: putfield      #22                 // Field id:Lorg/apache/hadoop/mapred/JobID;
      62: new           #23                 // class org/apache/hadoop/mapred/JobConf
      65: dup
      66: aload_0
      67: getfield      #4                  // Field systemJobFile:Lorg/apache/hadoop/fs/Path;
      70: invokespecial #24                 // Method org/apache/hadoop/mapred/JobConf."<init>":(Lorg/apache/hadoop/fs/Path;)V
      73: astore        4
      75: aload_0
      76: aload         4
      78: invokestatic  #25                 // Method org/apache/hadoop/fs/FileSystem.getLocal:(Lorg/apache/hadoop/conf/Configuration;)Lorg/apache/hadoop/fs/LocalFileSystem;
      81: putfield      #26                 // Field localFs:Lorg/apache/hadoop/fs/FileSystem;
      84: invokestatic  #27                 // Method org/apache/hadoop/security/UserGroupInformation.getCurrentUser:()Lorg/apache/hadoop/security/UserGroupInformation;
      87: invokevirtual #28                 // Method org/apache/hadoop/security/UserGroupInformation.getShortUserName:()Ljava/lang/String;
      90: astore        5
      92: aload_0
      93: aload_0
      94: getfield      #26                 // Field localFs:Lorg/apache/hadoop/fs/FileSystem;
      97: new           #17                 // class org/apache/hadoop/fs/Path
     100: dup
     101: new           #17                 // class org/apache/hadoop/fs/Path
     104: dup
     105: aload         4
     107: ldc           #29                 // String localRunner/
     109: invokevirtual #30                 // Method org/apache/hadoop/mapred/JobConf.getLocalPath:(Ljava/lang/String;)Lorg/apache/hadoop/fs/Path;
     112: aload         5
     114: invokespecial #21                 // Method org/apache/hadoop/fs/Path."<init>":(Lorg/apache/hadoop/fs/Path;Ljava/lang/String;)V
     117: aload_2
     118: invokevirtual #31                 // Method org/apache/hadoop/mapred/JobID.toString:()Ljava/lang/String;
     121: invokespecial #21                 // Method org/apache/hadoop/fs/Path."<init>":(Lorg/apache/hadoop/fs/Path;Ljava/lang/String;)V
     124: invokevirtual #32                 // Method org/apache/hadoop/fs/FileSystem.makeQualified:(Lorg/apache/hadoop/fs/Path;)Lorg/apache/hadoop/fs/Path;
     127: putfield      #33                 // Field localJobDir:Lorg/apache/hadoop/fs/Path;
     130: aload_0
     131: new           #17                 // class org/apache/hadoop/fs/Path
     134: dup
     135: aload_0
     136: getfield      #33                 // Field localJobDir:Lorg/apache/hadoop/fs/Path;
     139: new           #34                 // class java/lang/StringBuilder
     142: dup
     143: invokespecial #35                 // Method java/lang/StringBuilder."<init>":()V
     146: aload_0
     147: getfield      #22                 // Field id:Lorg/apache/hadoop/mapred/JobID;
     150: invokevirtual #36                 // Method java/lang/StringBuilder.append:(Ljava/lang/Object;)Ljava/lang/StringBuilder;
     153: ldc           #37                 // String .xml
     155: invokevirtual #38                 // Method java/lang/StringBuilder.append:(Ljava/lang/String;)Ljava/lang/StringBuilder;
     158: invokevirtual #39                 // Method java/lang/StringBuilder.toString:()Ljava/lang/String;
     161: invokespecial #21                 // Method org/apache/hadoop/fs/Path."<init>":(Lorg/apache/hadoop/fs/Path;Ljava/lang/String;)V
     164: putfield      #3                  // Field localJobFile:Lorg/apache/hadoop/fs/Path;
     167: aload_0
     168: new           #40                 // class org/apache/hadoop/mapred/LocalDistributedCacheManager
     171: dup
     172: invokespecial #41                 // Method org/apache/hadoop/mapred/LocalDistributedCacheManager."<init>":()V
     175: putfield      #42                 // Field localDistributedCacheManager:Lorg/apache/hadoop/mapred/LocalDistributedCacheManager;
     178: aload_0
     179: getfield      #42                 // Field localDistributedCacheManager:Lorg/apache/hadoop/mapred/LocalDistributedCacheManager;
     182: aload         4
     184: aload_2
     185: invokevirtual #43                 // Method org/apache/hadoop/mapred/LocalDistributedCacheManager.setup:(Lorg/apache/hadoop/mapred/JobConf;Lorg/apache/hadoop/mapred/JobID;)V
     188: aload_0
     189: getfield      #26                 // Field localFs:Lorg/apache/hadoop/fs/FileSystem;
     192: aload_0
     193: getfield      #3                  // Field localJobFile:Lorg/apache/hadoop/fs/Path;
     196: invokevirtual #44                 // Method org/apache/hadoop/fs/FileSystem.create:(Lorg/apache/hadoop/fs/Path;)Lorg/apache/hadoop/fs/FSDataOutputStream;
     199: astore        6
     201: aload         4
     203: aload         6
     205: invokevirtual #45                 // Method org/apache/hadoop/mapred/JobConf.writeXml:(Ljava/io/OutputStream;)V
     208: aload         6
     210: invokevirtual #46                 // Method java/io/OutputStream.close:()V
     213: goto          226
     216: astore        7
     218: aload         6
     220: invokevirtual #46                 // Method java/io/OutputStream.close:()V
     223: aload         7
     225: athrow
     226: aload_0
     227: new           #23                 // class org/apache/hadoop/mapred/JobConf
     230: dup
     231: aload_0
     232: getfield      #3                  // Field localJobFile:Lorg/apache/hadoop/fs/Path;
     235: invokespecial #24                 // Method org/apache/hadoop/mapred/JobConf."<init>":(Lorg/apache/hadoop/fs/Path;)V
     238: putfield      #6                  // Field job:Lorg/apache/hadoop/mapred/JobConf;
     241: aload_0
     242: getfield      #42                 // Field localDistributedCacheManager:Lorg/apache/hadoop/mapred/LocalDistributedCacheManager;
     245: invokevirtual #47                 // Method org/apache/hadoop/mapred/LocalDistributedCacheManager.hasLocalClasspaths:()Z
     248: ifeq          266
     251: aload_0
     252: aload_0
     253: getfield      #42                 // Field localDistributedCacheManager:Lorg/apache/hadoop/mapred/LocalDistributedCacheManager;
     256: aload_0
     257: invokevirtual #48                 // Method getContextClassLoader:()Ljava/lang/ClassLoader;
     260: invokevirtual #49                 // Method org/apache/hadoop/mapred/LocalDistributedCacheManager.makeClassLoader:(Ljava/lang/ClassLoader;)Ljava/lang/ClassLoader;
     263: invokevirtual #50                 // Method setContextClassLoader:(Ljava/lang/ClassLoader;)V
     266: aload_0
     267: new           #51                 // class org/apache/hadoop/mapred/JobProfile
     270: dup
     271: aload_0
     272: getfield      #6                  // Field job:Lorg/apache/hadoop/mapred/JobConf;
     275: invokevirtual #52                 // Method org/apache/hadoop/mapred/JobConf.getUser:()Ljava/lang/String;
     278: aload_0
     279: getfield      #22                 // Field id:Lorg/apache/hadoop/mapred/JobID;
     282: aload_0
     283: getfield      #4                  // Field systemJobFile:Lorg/apache/hadoop/fs/Path;
     286: invokevirtual #53                 // Method org/apache/hadoop/fs/Path.toString:()Ljava/lang/String;
     289: ldc           #54                 // String http://localhost:8080/
     291: aload_0
     292: getfield      #6                  // Field job:Lorg/apache/hadoop/mapred/JobConf;
     295: invokevirtual #55                 // Method org/apache/hadoop/mapred/JobConf.getJobName:()Ljava/lang/String;
     298: invokespecial #56                 // Method org/apache/hadoop/mapred/JobProfile."<init>":(Ljava/lang/String;Lorg/apache/hadoop/mapreduce/JobID;Ljava/lang/String;Ljava/lang/String;Ljava/lang/String;)V
     301: putfield      #57                 // Field profile:Lorg/apache/hadoop/mapred/JobProfile;
     304: aload_0
     305: new           #58                 // class org/apache/hadoop/mapred/JobStatus
     308: dup
     309: aload_0
     310: getfield      #22                 // Field id:Lorg/apache/hadoop/mapred/JobID;
     313: fconst_0
     314: fconst_0
     315: getstatic     #59                 // Field org/apache/hadoop/mapred/JobStatus.RUNNING:I
     318: aload_0
     319: getfield      #57                 // Field profile:Lorg/apache/hadoop/mapred/JobProfile;
     322: invokevirtual #60                 // Method org/apache/hadoop/mapred/JobProfile.getUser:()Ljava/lang/String;
     325: aload_0
     326: getfield      #57                 // Field profile:Lorg/apache/hadoop/mapred/JobProfile;
     329: invokevirtual #61                 // Method org/apache/hadoop/mapred/JobProfile.getJobName:()Ljava/lang/String;
     332: aload_0
     333: getfield      #57                 // Field profile:Lorg/apache/hadoop/mapred/JobProfile;
     336: invokevirtual #62                 // Method org/apache/hadoop/mapred/JobProfile.getJobFile:()Ljava/lang/String;
     339: aload_0
     340: getfield      #57                 // Field profile:Lorg/apache/hadoop/mapred/JobProfile;
     343: invokevirtual #63                 // Method org/apache/hadoop/mapred/JobProfile.getURL:()Ljava/net/URL;
     346: invokevirtual #64                 // Method java/net/URL.toString:()Ljava/lang/String;
     349: invokespecial #65                 // Method org/apache/hadoop/mapred/JobStatus."<init>":(Lorg/apache/hadoop/mapred/JobID;FFILjava/lang/String;Ljava/lang/String;Ljava/lang/String;Ljava/lang/String;)V
     352: putfield      #2                  // Field status:Lorg/apache/hadoop/mapred/JobStatus;
     355: aload_1
     356: invokestatic  #66                 // Method org/apache/hadoop/mapred/LocalJobRunner.access$000:(Lorg/apache/hadoop/mapred/LocalJobRunner;)Ljava/util/HashMap;
     359: aload_0
     360: getfield      #22                 // Field id:Lorg/apache/hadoop/mapred/JobID;
     363: aload_0
     364: invokevirtual #67                 // Method java/util/HashMap.put:(Ljava/lang/Object;Ljava/lang/Object;)Ljava/lang/Object;
     367: pop
     368: aload_0
     369: getfield      #6                  // Field job:Lorg/apache/hadoop/mapred/JobConf;
     372: invokestatic  #68                 // Method org/apache/hadoop/mapreduce/CryptoUtils.isEncryptedSpillEnabled:(Lorg/apache/hadoop/conf/Configuration;)Z
     375: ifeq          452
     378: aload         4
     380: ldc           #70                 // String mapreduce.job.encrypted-intermediate-data-key-size-bits
     382: sipush        128
     385: invokevirtual #71                 // Method org/apache/hadoop/mapred/JobConf.getInt:(Ljava/lang/String;I)I
     388: istore        7
     390: ldc           #72                 // String HmacSHA1
     392: invokestatic  #73                 // Method javax/crypto/KeyGenerator.getInstance:(Ljava/lang/String;)Ljavax/crypto/KeyGenerator;
     395: astore        8
     397: aload         8
     399: iload         7
     401: invokevirtual #74                 // Method javax/crypto/KeyGenerator.init:(I)V
     404: invokestatic  #27                 // Method org/apache/hadoop/security/UserGroupInformation.getCurrentUser:()Lorg/apache/hadoop/security/UserGroupInformation;
     407: invokevirtual #75                 // Method org/apache/hadoop/security/UserGroupInformation.getCredentials:()Lorg/apache/hadoop/security/Credentials;
     410: astore        9
     412: aload         8
     414: invokevirtual #76                 // Method javax/crypto/KeyGenerator.generateKey:()Ljavax/crypto/SecretKey;
     417: invokeinterface #77,  1           // InterfaceMethod javax/crypto/SecretKey.getEncoded:()[B
     422: aload         9
     424: invokestatic  #78                 // Method org/apache/hadoop/mapreduce/security/TokenCache.setEncryptedSpillKey:([BLorg/apache/hadoop/security/Credentials;)V
     427: invokestatic  #27                 // Method org/apache/hadoop/security/UserGroupInformation.getCurrentUser:()Lorg/apache/hadoop/security/UserGroupInformation;
     430: aload         9
     432: invokevirtual #79                 // Method org/apache/hadoop/security/UserGroupInformation.addCredentials:(Lorg/apache/hadoop/security/Credentials;)V
     435: goto          452
     438: astore        7
     440: new           #81                 // class java/io/IOException
     443: dup
     444: ldc           #82                 // String Error generating encrypted spill key
     446: aload         7
     448: invokespecial #83                 // Method java/io/IOException."<init>":(Ljava/lang/String;Ljava/lang/Throwable;)V
     451: athrow
     452: aload_0
     453: invokevirtual #84                 // Method start:()V
     456: return
    Exception table:
       from    to  target type
         201   208   216   any
         216   218   216   any
         378   435   438   Class java/security/NoSuchAlgorithmException

  protected java.util.List<org.apache.hadoop.mapred.LocalJobRunner$Job$RunnableWithThrowable> getMapTaskRunnables(org.apache.hadoop.mapreduce.split.JobSplit$TaskSplitMetaInfo[], org.apache.hadoop.mapred.JobID, java.util.Map<org.apache.hadoop.mapred.TaskAttemptID, org.apache.hadoop.mapred.MapOutputFile>);
    Code:
       0: iconst_0
       1: istore        4
       3: new           #13                 // class java/util/ArrayList
       6: dup
       7: invokespecial #14                 // Method java/util/ArrayList."<init>":()V
      10: astore        5
      12: aload_1
      13: astore        6
      15: aload         6
      17: arraylength
      18: istore        7
      20: iconst_0
      21: istore        8
      23: iload         8
      25: iload         7
      27: if_icmpge     66
      30: aload         6
      32: iload         8
      34: aaload
      35: astore        9
      37: aload         5
      39: new           #85                 // class org/apache/hadoop/mapred/LocalJobRunner$Job$MapTaskRunnable
      42: dup
      43: aload_0
      44: aload         9
      46: iload         4
      48: iinc          4, 1
      51: aload_2
      52: aload_3
      53: invokespecial #86                 // Method org/apache/hadoop/mapred/LocalJobRunner$Job$MapTaskRunnable."<init>":(Lorg/apache/hadoop/mapred/LocalJobRunner$Job;Lorg/apache/hadoop/mapreduce/split/JobSplit$TaskSplitMetaInfo;ILorg/apache/hadoop/mapred/JobID;Ljava/util/Map;)V
      56: invokevirtual #87                 // Method java/util/ArrayList.add:(Ljava/lang/Object;)Z
      59: pop
      60: iinc          8, 1
      63: goto          23
      66: aload         5
      68: areturn

  protected java.util.List<org.apache.hadoop.mapred.LocalJobRunner$Job$RunnableWithThrowable> getReduceTaskRunnables(org.apache.hadoop.mapred.JobID, java.util.Map<org.apache.hadoop.mapred.TaskAttemptID, org.apache.hadoop.mapred.MapOutputFile>);
    Code:
       0: iconst_0
       1: istore_3
       2: new           #13                 // class java/util/ArrayList
       5: dup
       6: invokespecial #14                 // Method java/util/ArrayList."<init>":()V
       9: astore        4
      11: iconst_0
      12: istore        5
      14: iload         5
      16: aload_0
      17: getfield      #88                 // Field numReduceTasks:I
      20: if_icmpge     49
      23: aload         4
      25: new           #89                 // class org/apache/hadoop/mapred/LocalJobRunner$Job$ReduceTaskRunnable
      28: dup
      29: aload_0
      30: iload_3
      31: iinc          3, 1
      34: aload_1
      35: aload_2
      36: invokespecial #90                 // Method org/apache/hadoop/mapred/LocalJobRunner$Job$ReduceTaskRunnable."<init>":(Lorg/apache/hadoop/mapred/LocalJobRunner$Job;ILorg/apache/hadoop/mapred/JobID;Ljava/util/Map;)V
      39: invokevirtual #87                 // Method java/util/ArrayList.add:(Ljava/lang/Object;)Z
      42: pop
      43: iinc          5, 1
      46: goto          14
      49: aload         4
      51: areturn

  private synchronized void initCounters(int, int);
    Code:
       0: aload_0
       1: iload_1
       2: newarray       float
       4: putfield      #91                 // Field partialMapProgress:[F
       7: aload_0
       8: iload_1
       9: anewarray     #92                 // class org/apache/hadoop/mapred/Counters
      12: putfield      #93                 // Field mapCounters:[Lorg/apache/hadoop/mapred/Counters;
      15: iconst_0
      16: istore_3
      17: iload_3
      18: iload_1
      19: if_icmpge     41
      22: aload_0
      23: getfield      #93                 // Field mapCounters:[Lorg/apache/hadoop/mapred/Counters;
      26: iload_3
      27: new           #92                 // class org/apache/hadoop/mapred/Counters
      30: dup
      31: invokespecial #94                 // Method org/apache/hadoop/mapred/Counters."<init>":()V
      34: aastore
      35: iinc          3, 1
      38: goto          17
      41: aload_0
      42: iload_2
      43: newarray       float
      45: putfield      #95                 // Field partialReduceProgress:[F
      48: aload_0
      49: iload_2
      50: anewarray     #92                 // class org/apache/hadoop/mapred/Counters
      53: putfield      #96                 // Field reduceCounters:[Lorg/apache/hadoop/mapred/Counters;
      56: iconst_0
      57: istore_3
      58: iload_3
      59: iload_2
      60: if_icmpge     82
      63: aload_0
      64: getfield      #96                 // Field reduceCounters:[Lorg/apache/hadoop/mapred/Counters;
      67: iload_3
      68: new           #92                 // class org/apache/hadoop/mapred/Counters
      71: dup
      72: invokespecial #94                 // Method org/apache/hadoop/mapred/Counters."<init>":()V
      75: aastore
      76: iinc          3, 1
      79: goto          58
      82: aload_0
      83: iload_1
      84: putfield      #97                 // Field numMapTasks:I
      87: aload_0
      88: iload_2
      89: putfield      #88                 // Field numReduceTasks:I
      92: return

  protected synchronized java.util.concurrent.ExecutorService createMapExecutor();
    Code:
       0: aload_0
       1: getfield      #6                  // Field job:Lorg/apache/hadoop/mapred/JobConf;
       4: ldc           #98                 // String mapreduce.local.map.tasks.maximum
       6: iconst_1
       7: invokevirtual #71                 // Method org/apache/hadoop/mapred/JobConf.getInt:(Ljava/lang/String;I)I
      10: istore_1
      11: iload_1
      12: iconst_1
      13: if_icmpge     26
      16: new           #99                 // class java/lang/IllegalArgumentException
      19: dup
      20: ldc           #100                // String Configured mapreduce.local.map.tasks.maximum must be >= 1
      22: invokespecial #101                // Method java/lang/IllegalArgumentException."<init>":(Ljava/lang/String;)V
      25: athrow
      26: iload_1
      27: aload_0
      28: getfield      #97                 // Field numMapTasks:I
      31: invokestatic  #102                // Method java/lang/Math.min:(II)I
      34: istore_1
      35: iload_1
      36: iconst_1
      37: invokestatic  #103                // Method java/lang/Math.max:(II)I
      40: istore_1
      41: getstatic     #104                // Field org/apache/hadoop/mapred/LocalJobRunner.LOG:Lorg/slf4j/Logger;
      44: ldc           #105                // String Starting mapper thread pool executor.
      46: invokeinterface #106,  2          // InterfaceMethod org/slf4j/Logger.debug:(Ljava/lang/String;)V
      51: getstatic     #104                // Field org/apache/hadoop/mapred/LocalJobRunner.LOG:Lorg/slf4j/Logger;
      54: new           #34                 // class java/lang/StringBuilder
      57: dup
      58: invokespecial #35                 // Method java/lang/StringBuilder."<init>":()V
      61: ldc           #107                // String Max local threads:
      63: invokevirtual #38                 // Method java/lang/StringBuilder.append:(Ljava/lang/String;)Ljava/lang/StringBuilder;
      66: iload_1
      67: invokevirtual #108                // Method java/lang/StringBuilder.append:(I)Ljava/lang/StringBuilder;
      70: invokevirtual #39                 // Method java/lang/StringBuilder.toString:()Ljava/lang/String;
      73: invokeinterface #106,  2          // InterfaceMethod org/slf4j/Logger.debug:(Ljava/lang/String;)V
      78: getstatic     #104                // Field org/apache/hadoop/mapred/LocalJobRunner.LOG:Lorg/slf4j/Logger;
      81: new           #34                 // class java/lang/StringBuilder
      84: dup
      85: invokespecial #35                 // Method java/lang/StringBuilder."<init>":()V
      88: ldc           #109                // String Map tasks to process:
      90: invokevirtual #38                 // Method java/lang/StringBuilder.append:(Ljava/lang/String;)Ljava/lang/StringBuilder;
      93: aload_0
      94: getfield      #97                 // Field numMapTasks:I
      97: invokevirtual #108                // Method java/lang/StringBuilder.append:(I)Ljava/lang/StringBuilder;
     100: invokevirtual #39                 // Method java/lang/StringBuilder.toString:()Ljava/lang/String;
     103: invokeinterface #106,  2          // InterfaceMethod org/slf4j/Logger.debug:(Ljava/lang/String;)V
     108: new           #110                // class com/google/common/util/concurrent/ThreadFactoryBuilder
     111: dup
     112: invokespecial #111                // Method com/google/common/util/concurrent/ThreadFactoryBuilder."<init>":()V
     115: ldc           #112                // String LocalJobRunner Map Task Executor #%d
     117: invokevirtual #113                // Method com/google/common/util/concurrent/ThreadFactoryBuilder.setNameFormat:(Ljava/lang/String;)Lcom/google/common/util/concurrent/ThreadFactoryBuilder;
     120: invokevirtual #114                // Method com/google/common/util/concurrent/ThreadFactoryBuilder.build:()Ljava/util/concurrent/ThreadFactory;
     123: astore_2
     124: iload_1
     125: aload_2
     126: invokestatic  #115                // Method org/apache/hadoop/util/concurrent/HadoopExecutors.newFixedThreadPool:(ILjava/util/concurrent/ThreadFactory;)Ljava/util/concurrent/ExecutorService;
     129: astore_3
     130: aload_3
     131: areturn

  protected synchronized java.util.concurrent.ExecutorService createReduceExecutor();
    Code:
       0: aload_0
       1: getfield      #6                  // Field job:Lorg/apache/hadoop/mapred/JobConf;
       4: ldc           #116                // String mapreduce.local.reduce.tasks.maximum
       6: iconst_1
       7: invokevirtual #71                 // Method org/apache/hadoop/mapred/JobConf.getInt:(Ljava/lang/String;I)I
      10: istore_1
      11: iload_1
      12: iconst_1
      13: if_icmpge     26
      16: new           #99                 // class java/lang/IllegalArgumentException
      19: dup
      20: ldc           #117                // String Configured mapreduce.local.reduce.tasks.maximum must be >= 1
      22: invokespecial #101                // Method java/lang/IllegalArgumentException."<init>":(Ljava/lang/String;)V
      25: athrow
      26: iload_1
      27: aload_0
      28: getfield      #88                 // Field numReduceTasks:I
      31: invokestatic  #102                // Method java/lang/Math.min:(II)I
      34: istore_1
      35: iload_1
      36: iconst_1
      37: invokestatic  #103                // Method java/lang/Math.max:(II)I
      40: istore_1
      41: getstatic     #104                // Field org/apache/hadoop/mapred/LocalJobRunner.LOG:Lorg/slf4j/Logger;
      44: ldc           #118                // String Starting reduce thread pool executor.
      46: invokeinterface #106,  2          // InterfaceMethod org/slf4j/Logger.debug:(Ljava/lang/String;)V
      51: getstatic     #104                // Field org/apache/hadoop/mapred/LocalJobRunner.LOG:Lorg/slf4j/Logger;
      54: new           #34                 // class java/lang/StringBuilder
      57: dup
      58: invokespecial #35                 // Method java/lang/StringBuilder."<init>":()V
      61: ldc           #107                // String Max local threads:
      63: invokevirtual #38                 // Method java/lang/StringBuilder.append:(Ljava/lang/String;)Ljava/lang/StringBuilder;
      66: iload_1
      67: invokevirtual #108                // Method java/lang/StringBuilder.append:(I)Ljava/lang/StringBuilder;
      70: invokevirtual #39                 // Method java/lang/StringBuilder.toString:()Ljava/lang/String;
      73: invokeinterface #106,  2          // InterfaceMethod org/slf4j/Logger.debug:(Ljava/lang/String;)V
      78: getstatic     #104                // Field org/apache/hadoop/mapred/LocalJobRunner.LOG:Lorg/slf4j/Logger;
      81: new           #34                 // class java/lang/StringBuilder
      84: dup
      85: invokespecial #35                 // Method java/lang/StringBuilder."<init>":()V
      88: ldc           #119                // String Reduce tasks to process:
      90: invokevirtual #38                 // Method java/lang/StringBuilder.append:(Ljava/lang/String;)Ljava/lang/StringBuilder;
      93: aload_0
      94: getfield      #88                 // Field numReduceTasks:I
      97: invokevirtual #108                // Method java/lang/StringBuilder.append:(I)Ljava/lang/StringBuilder;
     100: invokevirtual #39                 // Method java/lang/StringBuilder.toString:()Ljava/lang/String;
     103: invokeinterface #106,  2          // InterfaceMethod org/slf4j/Logger.debug:(Ljava/lang/String;)V
     108: iload_1
     109: invokestatic  #120                // Method org/apache/hadoop/util/concurrent/HadoopExecutors.newFixedThreadPool:(I)Ljava/util/concurrent/ExecutorService;
     112: astore_2
     113: aload_2
     114: areturn

  private void runTasks(java.util.List<org.apache.hadoop.mapred.LocalJobRunner$Job$RunnableWithThrowable>, java.util.concurrent.ExecutorService, java.lang.String) throws java.lang.Exception;
    Code:
       0: aload_1
       1: invokeinterface #121,  1          // InterfaceMethod java/util/List.iterator:()Ljava/util/Iterator;
       6: astore        4
       8: aload         4
      10: invokeinterface #122,  1          // InterfaceMethod java/util/Iterator.hasNext:()Z
      15: ifeq          42
      18: aload         4
      20: invokeinterface #123,  1          // InterfaceMethod java/util/Iterator.next:()Ljava/lang/Object;
      25: checkcast     #124                // class java/lang/Runnable
      28: astore        5
      30: aload_2
      31: aload         5
      33: invokeinterface #125,  2          // InterfaceMethod java/util/concurrent/ExecutorService.submit:(Ljava/lang/Runnable;)Ljava/util/concurrent/Future;
      38: pop
      39: goto          8
      42: aload_2
      43: invokeinterface #126,  1          // InterfaceMethod java/util/concurrent/ExecutorService.shutdown:()V
      48: getstatic     #104                // Field org/apache/hadoop/mapred/LocalJobRunner.LOG:Lorg/slf4j/Logger;
      51: new           #34                 // class java/lang/StringBuilder
      54: dup
      55: invokespecial #35                 // Method java/lang/StringBuilder."<init>":()V
      58: ldc           #127                // String Waiting for
      60: invokevirtual #38                 // Method java/lang/StringBuilder.append:(Ljava/lang/String;)Ljava/lang/StringBuilder;
      63: aload_3
      64: invokevirtual #38                 // Method java/lang/StringBuilder.append:(Ljava/lang/String;)Ljava/lang/StringBuilder;
      67: ldc           #128                // String  tasks
      69: invokevirtual #38                 // Method java/lang/StringBuilder.append:(Ljava/lang/String;)Ljava/lang/StringBuilder;
      72: invokevirtual #39                 // Method java/lang/StringBuilder.toString:()Ljava/lang/String;
      75: invokeinterface #129,  2          // InterfaceMethod org/slf4j/Logger.info:(Ljava/lang/String;)V
      80: aload_2
      81: ldc2_w        #131                // long 9223372036854775807l
      84: getstatic     #133                // Field java/util/concurrent/TimeUnit.NANOSECONDS:Ljava/util/concurrent/TimeUnit;
      87: invokeinterface #134,  4          // InterfaceMethod java/util/concurrent/ExecutorService.awaitTermination:(JLjava/util/concurrent/TimeUnit;)Z
      92: pop
      93: goto          108
      96: astore        4
      98: aload_2
      99: invokeinterface #136,  1          // InterfaceMethod java/util/concurrent/ExecutorService.shutdownNow:()Ljava/util/List;
     104: pop
     105: aload         4
     107: athrow
     108: getstatic     #104                // Field org/apache/hadoop/mapred/LocalJobRunner.LOG:Lorg/slf4j/Logger;
     111: new           #34                 // class java/lang/StringBuilder
     114: dup
     115: invokespecial #35                 // Method java/lang/StringBuilder."<init>":()V
     118: aload_3
     119: invokevirtual #38                 // Method java/lang/StringBuilder.append:(Ljava/lang/String;)Ljava/lang/StringBuilder;
     122: ldc           #137                // String  task executor complete.
     124: invokevirtual #38                 // Method java/lang/StringBuilder.append:(Ljava/lang/String;)Ljava/lang/StringBuilder;
     127: invokevirtual #39                 // Method java/lang/StringBuilder.toString:()Ljava/lang/String;
     130: invokeinterface #129,  2          // InterfaceMethod org/slf4j/Logger.info:(Ljava/lang/String;)V
     135: aload_1
     136: invokeinterface #121,  1          // InterfaceMethod java/util/List.iterator:()Ljava/util/Iterator;
     141: astore        4
     143: aload         4
     145: invokeinterface #122,  1          // InterfaceMethod java/util/Iterator.hasNext:()Z
     150: ifeq          189
     153: aload         4
     155: invokeinterface #123,  1          // InterfaceMethod java/util/Iterator.next:()Ljava/lang/Object;
     160: checkcast     #138                // class org/apache/hadoop/mapred/LocalJobRunner$Job$RunnableWithThrowable
     163: astore        5
     165: aload         5
     167: getfield      #139                // Field org/apache/hadoop/mapred/LocalJobRunner$Job$RunnableWithThrowable.storedException:Ljava/lang/Throwable;
     170: ifnull        186
     173: new           #140                // class java/lang/Exception
     176: dup
     177: aload         5
     179: getfield      #139                // Field org/apache/hadoop/mapred/LocalJobRunner$Job$RunnableWithThrowable.storedException:Ljava/lang/Throwable;
     182: invokespecial #141                // Method java/lang/Exception."<init>":(Ljava/lang/Throwable;)V
     185: athrow
     186: goto          143
     189: return
    Exception table:
       from    to  target type
          42    93    96   Class java/lang/InterruptedException

  private org.apache.hadoop.mapreduce.OutputCommitter createOutputCommitter(boolean, org.apache.hadoop.mapred.JobID, org.apache.hadoop.conf.Configuration) throws java.lang.Exception;
    Code:
       0: aconst_null
       1: astore        4
       3: getstatic     #104                // Field org/apache/hadoop/mapred/LocalJobRunner.LOG:Lorg/slf4j/Logger;
       6: new           #34                 // class java/lang/StringBuilder
       9: dup
      10: invokespecial #35                 // Method java/lang/StringBuilder."<init>":()V
      13: ldc           #142                // String OutputCommitter set in config
      15: invokevirtual #38                 // Method java/lang/StringBuilder.append:(Ljava/lang/String;)Ljava/lang/StringBuilder;
      18: aload_3
      19: ldc           #143                // String mapred.output.committer.class
      21: invokevirtual #144                // Method org/apache/hadoop/conf/Configuration.get:(Ljava/lang/String;)Ljava/lang/String;
      24: invokevirtual #38                 // Method java/lang/StringBuilder.append:(Ljava/lang/String;)Ljava/lang/StringBuilder;
      27: invokevirtual #39                 // Method java/lang/StringBuilder.toString:()Ljava/lang/String;
      30: invokeinterface #129,  2          // InterfaceMethod org/slf4j/Logger.info:(Ljava/lang/String;)V
      35: iload_1
      36: ifeq          105
      39: new           #145                // class org/apache/hadoop/mapreduce/TaskID
      42: dup
      43: aload_2
      44: getstatic     #146                // Field org/apache/hadoop/mapreduce/TaskType.MAP:Lorg/apache/hadoop/mapreduce/TaskType;
      47: iconst_0
      48: invokespecial #147                // Method org/apache/hadoop/mapreduce/TaskID."<init>":(Lorg/apache/hadoop/mapreduce/JobID;Lorg/apache/hadoop/mapreduce/TaskType;I)V
      51: astore        5
      53: new           #148                // class org/apache/hadoop/mapreduce/TaskAttemptID
      56: dup
      57: aload         5
      59: iconst_0
      60: invokespecial #149                // Method org/apache/hadoop/mapreduce/TaskAttemptID."<init>":(Lorg/apache/hadoop/mapreduce/TaskID;I)V
      63: astore        6
      65: new           #150                // class org/apache/hadoop/mapreduce/task/TaskAttemptContextImpl
      68: dup
      69: aload_3
      70: aload         6
      72: invokespecial #151                // Method org/apache/hadoop/mapreduce/task/TaskAttemptContextImpl."<init>":(Lorg/apache/hadoop/conf/Configuration;Lorg/apache/hadoop/mapreduce/TaskAttemptID;)V
      75: astore        7
      77: aload         7
      79: invokeinterface #152,  1          // InterfaceMethod org/apache/hadoop/mapreduce/TaskAttemptContext.getOutputFormatClass:()Ljava/lang/Class;
      84: aload_3
      85: invokestatic  #153                // Method org/apache/hadoop/util/ReflectionUtils.newInstance:(Ljava/lang/Class;Lorg/apache/hadoop/conf/Configuration;)Ljava/lang/Object;
      88: checkcast     #154                // class org/apache/hadoop/mapreduce/OutputFormat
      91: astore        8
      93: aload         8
      95: aload         7
      97: invokevirtual #155                // Method org/apache/hadoop/mapreduce/OutputFormat.getOutputCommitter:(Lorg/apache/hadoop/mapreduce/TaskAttemptContext;)Lorg/apache/hadoop/mapreduce/OutputCommitter;
     100: astore        4
     102: goto          124
     105: aload_3
     106: ldc           #143                // String mapred.output.committer.class
     108: ldc           #156                // class org/apache/hadoop/mapred/FileOutputCommitter
     110: ldc           #157                // class org/apache/hadoop/mapred/OutputCommitter
     112: invokevirtual #158                // Method org/apache/hadoop/conf/Configuration.getClass:(Ljava/lang/String;Ljava/lang/Class;Ljava/lang/Class;)Ljava/lang/Class;
     115: aload_3
     116: invokestatic  #153                // Method org/apache/hadoop/util/ReflectionUtils.newInstance:(Ljava/lang/Class;Lorg/apache/hadoop/conf/Configuration;)Ljava/lang/Object;
     119: checkcast     #159                // class org/apache/hadoop/mapreduce/OutputCommitter
     122: astore        4
     124: getstatic     #104                // Field org/apache/hadoop/mapred/LocalJobRunner.LOG:Lorg/slf4j/Logger;
     127: new           #34                 // class java/lang/StringBuilder
     130: dup
     131: invokespecial #35                 // Method java/lang/StringBuilder."<init>":()V
     134: ldc           #160                // String OutputCommitter is
     136: invokevirtual #38                 // Method java/lang/StringBuilder.append:(Ljava/lang/String;)Ljava/lang/StringBuilder;
     139: aload         4
     141: invokevirtual #161                // Method java/lang/Object.getClass:()Ljava/lang/Class;
     144: invokevirtual #162                // Method java/lang/Class.getName:()Ljava/lang/String;
     147: invokevirtual #38                 // Method java/lang/StringBuilder.append:(Ljava/lang/String;)Ljava/lang/StringBuilder;
     150: invokevirtual #39                 // Method java/lang/StringBuilder.toString:()Ljava/lang/String;
     153: invokeinterface #129,  2          // InterfaceMethod org/slf4j/Logger.info:(Ljava/lang/String;)V
     158: aload         4
     160: areturn

  public void run();
    Code:
       0: aload_0
       1: getfield      #57                 // Field profile:Lorg/apache/hadoop/mapred/JobProfile;
       4: invokevirtual #163                // Method org/apache/hadoop/mapred/JobProfile.getJobID:()Lorg/apache/hadoop/mapred/JobID;
       7: astore_1
       8: new           #164                // class org/apache/hadoop/mapred/JobContextImpl
      11: dup
      12: aload_0
      13: getfield      #6                  // Field job:Lorg/apache/hadoop/mapred/JobConf;
      16: aload_1
      17: invokespecial #165                // Method org/apache/hadoop/mapred/JobContextImpl."<init>":(Lorg/apache/hadoop/mapred/JobConf;Lorg/apache/hadoop/mapreduce/JobID;)V
      20: astore_2
      21: aconst_null
      22: astore_3
      23: aload_0
      24: aload_0
      25: getfield      #11                 // Field this$0:Lorg/apache/hadoop/mapred/LocalJobRunner;
      28: invokestatic  #166                // Method org/apache/hadoop/mapred/LocalJobRunner.access$800:(Lorg/apache/hadoop/mapred/LocalJobRunner;)Lorg/apache/hadoop/mapred/JobConf;
      31: invokevirtual #167                // Method org/apache/hadoop/mapred/JobConf.getUseNewMapper:()Z
      34: aload_1
      35: aload_0
      36: getfield      #11                 // Field this$0:Lorg/apache/hadoop/mapred/LocalJobRunner;
      39: invokestatic  #166                // Method org/apache/hadoop/mapred/LocalJobRunner.access$800:(Lorg/apache/hadoop/mapred/LocalJobRunner;)Lorg/apache/hadoop/mapred/JobConf;
      42: invokespecial #168                // Method createOutputCommitter:(ZLorg/apache/hadoop/mapred/JobID;Lorg/apache/hadoop/conf/Configuration;)Lorg/apache/hadoop/mapreduce/OutputCommitter;
      45: astore_3
      46: goto          64
      49: astore        4
      51: getstatic     #104                // Field org/apache/hadoop/mapred/LocalJobRunner.LOG:Lorg/slf4j/Logger;
      54: ldc           #169                // String Failed to createOutputCommitter
      56: aload         4
      58: invokeinterface #170,  3          // InterfaceMethod org/slf4j/Logger.info:(Ljava/lang/String;Ljava/lang/Throwable;)V
      63: return
      64: aload_1
      65: aload_0
      66: getfield      #26                 // Field localFs:Lorg/apache/hadoop/fs/FileSystem;
      69: aload_0
      70: getfield      #11                 // Field this$0:Lorg/apache/hadoop/mapred/LocalJobRunner;
      73: invokestatic  #166                // Method org/apache/hadoop/mapred/LocalJobRunner.access$800:(Lorg/apache/hadoop/mapred/LocalJobRunner;)Lorg/apache/hadoop/mapred/JobConf;
      76: aload_0
      77: getfield      #19                 // Field systemJobDir:Lorg/apache/hadoop/fs/Path;
      80: invokestatic  #171                // Method org/apache/hadoop/mapreduce/split/SplitMetaInfoReader.readSplitMetaInfo:(Lorg/apache/hadoop/mapreduce/JobID;Lorg/apache/hadoop/fs/FileSystem;Lorg/apache/hadoop/conf/Configuration;Lorg/apache/hadoop/fs/Path;)[Lorg/apache/hadoop/mapreduce/split/JobSplit$TaskSplitMetaInfo;
      83: astore        4
      85: aload_0
      86: getfield      #6                  // Field job:Lorg/apache/hadoop/mapred/JobConf;
      89: invokevirtual #172                // Method org/apache/hadoop/mapred/JobConf.getNumReduceTasks:()I
      92: istore        5
      94: aload_3
      95: aload_2
      96: invokevirtual #173                // Method org/apache/hadoop/mapreduce/OutputCommitter.setupJob:(Lorg/apache/hadoop/mapreduce/JobContext;)V
      99: aload_0
     100: getfield      #2                  // Field status:Lorg/apache/hadoop/mapred/JobStatus;
     103: fconst_1
     104: invokevirtual #174                // Method org/apache/hadoop/mapred/JobStatus.setSetupProgress:(F)V
     107: new           #175                // class java/util/HashMap
     110: dup
     111: invokespecial #176                // Method java/util/HashMap."<init>":()V
     114: invokestatic  #177                // Method java/util/Collections.synchronizedMap:(Ljava/util/Map;)Ljava/util/Map;
     117: astore        6
     119: aload_0
     120: aload         4
     122: aload_1
     123: aload         6
     125: invokevirtual #178                // Method getMapTaskRunnables:([Lorg/apache/hadoop/mapreduce/split/JobSplit$TaskSplitMetaInfo;Lorg/apache/hadoop/mapred/JobID;Ljava/util/Map;)Ljava/util/List;
     128: astore        7
     130: aload_0
     131: aload         7
     133: invokeinterface #179,  1          // InterfaceMethod java/util/List.size:()I
     138: iload         5
     140: invokespecial #180                // Method initCounters:(II)V
     143: aload_0
     144: invokevirtual #181                // Method createMapExecutor:()Ljava/util/concurrent/ExecutorService;
     147: astore        8
     149: aload_0
     150: aload         7
     152: aload         8
     154: ldc           #182                // String map
     156: invokespecial #183                // Method runTasks:(Ljava/util/List;Ljava/util/concurrent/ExecutorService;Ljava/lang/String;)V
     159: iload         5
     161: ifle          189
     164: aload_0
     165: aload_1
     166: aload         6
     168: invokevirtual #184                // Method getReduceTaskRunnables:(Lorg/apache/hadoop/mapred/JobID;Ljava/util/Map;)Ljava/util/List;
     171: astore        9
     173: aload_0
     174: invokevirtual #185                // Method createReduceExecutor:()Ljava/util/concurrent/ExecutorService;
     177: astore        10
     179: aload_0
     180: aload         9
     182: aload         10
     184: ldc           #186                // String reduce
     186: invokespecial #183                // Method runTasks:(Ljava/util/List;Ljava/util/concurrent/ExecutorService;Ljava/lang/String;)V
     189: aload         6
     191: invokeinterface #187,  1          // InterfaceMethod java/util/Map.values:()Ljava/util/Collection;
     196: invokeinterface #188,  1          // InterfaceMethod java/util/Collection.iterator:()Ljava/util/Iterator;
     201: astore        9
     203: aload         9
     205: invokeinterface #122,  1          // InterfaceMethod java/util/Iterator.hasNext:()Z
     210: ifeq          233
     213: aload         9
     215: invokeinterface #123,  1          // InterfaceMethod java/util/Iterator.next:()Ljava/lang/Object;
     220: checkcast     #189                // class org/apache/hadoop/mapred/MapOutputFile
     223: astore        10
     225: aload         10
     227: invokevirtual #190                // Method org/apache/hadoop/mapred/MapOutputFile.removeAll:()V
     230: goto          203
     233: goto          285
     236: astore        11
     238: aload         6
     240: invokeinterface #187,  1          // InterfaceMethod java/util/Map.values:()Ljava/util/Collection;
     245: invokeinterface #188,  1          // InterfaceMethod java/util/Collection.iterator:()Ljava/util/Iterator;
     250: astore        12
     252: aload         12
     254: invokeinterface #122,  1          // InterfaceMethod java/util/Iterator.hasNext:()Z
     259: ifeq          282
     262: aload         12
     264: invokeinterface #123,  1          // InterfaceMethod java/util/Iterator.next:()Ljava/lang/Object;
     269: checkcast     #189                // class org/apache/hadoop/mapred/MapOutputFile
     272: astore        13
     274: aload         13
     276: invokevirtual #190                // Method org/apache/hadoop/mapred/MapOutputFile.removeAll:()V
     279: goto          252
     282: aload         11
     284: athrow
     285: aload_3
     286: aload_2
     287: invokevirtual #191                // Method org/apache/hadoop/mapreduce/OutputCommitter.commitJob:(Lorg/apache/hadoop/mapreduce/JobContext;)V
     290: aload_0
     291: getfield      #2                  // Field status:Lorg/apache/hadoop/mapred/JobStatus;
     294: fconst_1
     295: invokevirtual #192                // Method org/apache/hadoop/mapred/JobStatus.setCleanupProgress:(F)V
     298: aload_0
     299: getfield      #16                 // Field killed:Z
     302: ifeq          318
     305: aload_0
     306: getfield      #2                  // Field status:Lorg/apache/hadoop/mapred/JobStatus;
     309: getstatic     #193                // Field org/apache/hadoop/mapred/JobStatus.KILLED:I
     312: invokevirtual #194                // Method org/apache/hadoop/mapred/JobStatus.setRunState:(I)V
     315: goto          328
     318: aload_0
     319: getfield      #2                  // Field status:Lorg/apache/hadoop/mapred/JobStatus;
     322: getstatic     #195                // Field org/apache/hadoop/mapred/JobStatus.SUCCEEDED:I
     325: invokevirtual #194                // Method org/apache/hadoop/mapred/JobStatus.setRunState:(I)V
     328: aload_0
     329: getfield      #6                  // Field job:Lorg/apache/hadoop/mapred/JobConf;
     332: aload_0
     333: getfield      #2                  // Field status:Lorg/apache/hadoop/mapred/JobStatus;
     336: invokestatic  #196                // Method org/apache/hadoop/mapred/JobEndNotifier.localRunnerNotification:(Lorg/apache/hadoop/mapred/JobConf;Lorg/apache/hadoop/mapred/JobStatus;)V
     339: aload_0
     340: getfield      #42                 // Field localDistributedCacheManager:Lorg/apache/hadoop/mapred/LocalDistributedCacheManager;
     343: invokevirtual #197                // Method org/apache/hadoop/mapred/LocalDistributedCacheManager.close:()V
     346: aload_0
     347: getfield      #11                 // Field this$0:Lorg/apache/hadoop/mapred/LocalJobRunner;
     350: invokestatic  #198                // Method org/apache/hadoop/mapred/LocalJobRunner.access$900:(Lorg/apache/hadoop/mapred/LocalJobRunner;)Lorg/apache/hadoop/fs/FileSystem;
     353: aload_0
     354: getfield      #4                  // Field systemJobFile:Lorg/apache/hadoop/fs/Path;
     357: invokevirtual #199                // Method org/apache/hadoop/fs/Path.getParent:()Lorg/apache/hadoop/fs/Path;
     360: iconst_1
     361: invokevirtual #200                // Method org/apache/hadoop/fs/FileSystem.delete:(Lorg/apache/hadoop/fs/Path;Z)Z
     364: pop
     365: aload_0
     366: getfield      #26                 // Field localFs:Lorg/apache/hadoop/fs/FileSystem;
     369: aload_0
     370: getfield      #3                  // Field localJobFile:Lorg/apache/hadoop/fs/Path;
     373: iconst_1
     374: invokevirtual #200                // Method org/apache/hadoop/fs/FileSystem.delete:(Lorg/apache/hadoop/fs/Path;Z)Z
     377: pop
     378: goto          399
     381: astore        14
     383: aload_0
     384: getfield      #26                 // Field localFs:Lorg/apache/hadoop/fs/FileSystem;
     387: aload_0
     388: getfield      #3                  // Field localJobFile:Lorg/apache/hadoop/fs/Path;
     391: iconst_1
     392: invokevirtual #200                // Method org/apache/hadoop/fs/FileSystem.delete:(Lorg/apache/hadoop/fs/Path;Z)Z
     395: pop
     396: aload         14
     398: athrow
     399: goto          460
     402: astore        15
     404: aload_0
     405: getfield      #11                 // Field this$0:Lorg/apache/hadoop/mapred/LocalJobRunner;
     408: invokestatic  #198                // Method org/apache/hadoop/mapred/LocalJobRunner.access$900:(Lorg/apache/hadoop/mapred/LocalJobRunner;)Lorg/apache/hadoop/fs/FileSystem;
     411: aload_0
     412: getfield      #4                  // Field systemJobFile:Lorg/apache/hadoop/fs/Path;
     415: invokevirtual #199                // Method org/apache/hadoop/fs/Path.getParent:()Lorg/apache/hadoop/fs/Path;
     418: iconst_1
     419: invokevirtual #200                // Method org/apache/hadoop/fs/FileSystem.delete:(Lorg/apache/hadoop/fs/Path;Z)Z
     422: pop
     423: aload_0
     424: getfield      #26                 // Field localFs:Lorg/apache/hadoop/fs/FileSystem;
     427: aload_0
     428: getfield      #3                  // Field localJobFile:Lorg/apache/hadoop/fs/Path;
     431: iconst_1
     432: invokevirtual #200                // Method org/apache/hadoop/fs/FileSystem.delete:(Lorg/apache/hadoop/fs/Path;Z)Z
     435: pop
     436: goto          457
     439: astore        16
     441: aload_0
     442: getfield      #26                 // Field localFs:Lorg/apache/hadoop/fs/FileSystem;
     445: aload_0
     446: getfield      #3                  // Field localJobFile:Lorg/apache/hadoop/fs/Path;
     449: iconst_1
     450: invokevirtual #200                // Method org/apache/hadoop/fs/FileSystem.delete:(Lorg/apache/hadoop/fs/Path;Z)Z
     453: pop
     454: aload         16
     456: athrow
     457: aload         15
     459: athrow
     460: goto          959
     463: astore        4
     465: getstatic     #104                // Field org/apache/hadoop/mapred/LocalJobRunner.LOG:Lorg/slf4j/Logger;
     468: new           #34                 // class java/lang/StringBuilder
     471: dup
     472: invokespecial #35                 // Method java/lang/StringBuilder."<init>":()V
     475: ldc           #201                // String Error cleaning up
     477: invokevirtual #38                 // Method java/lang/StringBuilder.append:(Ljava/lang/String;)Ljava/lang/StringBuilder;
     480: aload_0
     481: getfield      #22                 // Field id:Lorg/apache/hadoop/mapred/JobID;
     484: invokevirtual #36                 // Method java/lang/StringBuilder.append:(Ljava/lang/Object;)Ljava/lang/StringBuilder;
     487: ldc           #202                // String :
     489: invokevirtual #38                 // Method java/lang/StringBuilder.append:(Ljava/lang/String;)Ljava/lang/StringBuilder;
     492: aload         4
     494: invokevirtual #36                 // Method java/lang/StringBuilder.append:(Ljava/lang/Object;)Ljava/lang/StringBuilder;
     497: invokevirtual #39                 // Method java/lang/StringBuilder.toString:()Ljava/lang/String;
     500: invokeinterface #203,  2          // InterfaceMethod org/slf4j/Logger.warn:(Ljava/lang/String;)V
     505: goto          959
     508: astore        4
     510: aload_3
     511: aload_2
     512: getstatic     #205                // Field org/apache/hadoop/mapreduce/JobStatus$State.FAILED:Lorg/apache/hadoop/mapreduce/JobStatus$State;
     515: invokevirtual #206                // Method org/apache/hadoop/mapreduce/OutputCommitter.abortJob:(Lorg/apache/hadoop/mapreduce/JobContext;Lorg/apache/hadoop/mapreduce/JobStatus$State;)V
     518: goto          553
     521: astore        5
     523: getstatic     #104                // Field org/apache/hadoop/mapred/LocalJobRunner.LOG:Lorg/slf4j/Logger;
     526: new           #34                 // class java/lang/StringBuilder
     529: dup
     530: invokespecial #35                 // Method java/lang/StringBuilder."<init>":()V
     533: ldc           #207                // String Error cleaning up job:
     535: invokevirtual #38                 // Method java/lang/StringBuilder.append:(Ljava/lang/String;)Ljava/lang/StringBuilder;
     538: aload_0
     539: getfield      #22                 // Field id:Lorg/apache/hadoop/mapred/JobID;
     542: invokevirtual #36                 // Method java/lang/StringBuilder.append:(Ljava/lang/Object;)Ljava/lang/StringBuilder;
     545: invokevirtual #39                 // Method java/lang/StringBuilder.toString:()Ljava/lang/String;
     548: invokeinterface #129,  2          // InterfaceMethod org/slf4j/Logger.info:(Ljava/lang/String;)V
     553: aload_0
     554: getfield      #2                  // Field status:Lorg/apache/hadoop/mapred/JobStatus;
     557: fconst_1
     558: invokevirtual #192                // Method org/apache/hadoop/mapred/JobStatus.setCleanupProgress:(F)V
     561: aload_0
     562: getfield      #16                 // Field killed:Z
     565: ifeq          581
     568: aload_0
     569: getfield      #2                  // Field status:Lorg/apache/hadoop/mapred/JobStatus;
     572: getstatic     #193                // Field org/apache/hadoop/mapred/JobStatus.KILLED:I
     575: invokevirtual #194                // Method org/apache/hadoop/mapred/JobStatus.setRunState:(I)V
     578: goto          591
     581: aload_0
     582: getfield      #2                  // Field status:Lorg/apache/hadoop/mapred/JobStatus;
     585: getstatic     #208                // Field org/apache/hadoop/mapred/JobStatus.FAILED:I
     588: invokevirtual #194                // Method org/apache/hadoop/mapred/JobStatus.setRunState:(I)V
     591: getstatic     #104                // Field org/apache/hadoop/mapred/LocalJobRunner.LOG:Lorg/slf4j/Logger;
     594: aload_0
     595: getfield      #22                 // Field id:Lorg/apache/hadoop/mapred/JobID;
     598: invokevirtual #31                 // Method org/apache/hadoop/mapred/JobID.toString:()Ljava/lang/String;
     601: aload         4
     603: invokeinterface #209,  3          // InterfaceMethod org/slf4j/Logger.warn:(Ljava/lang/String;Ljava/lang/Throwable;)V
     608: aload_0
     609: getfield      #6                  // Field job:Lorg/apache/hadoop/mapred/JobConf;
     612: aload_0
     613: getfield      #2                  // Field status:Lorg/apache/hadoop/mapred/JobStatus;
     616: invokestatic  #196                // Method org/apache/hadoop/mapred/JobEndNotifier.localRunnerNotification:(Lorg/apache/hadoop/mapred/JobConf;Lorg/apache/hadoop/mapred/JobStatus;)V
     619: aload_0
     620: getfield      #42                 // Field localDistributedCacheManager:Lorg/apache/hadoop/mapred/LocalDistributedCacheManager;
     623: invokevirtual #197                // Method org/apache/hadoop/mapred/LocalDistributedCacheManager.close:()V
     626: aload_0
     627: getfield      #11                 // Field this$0:Lorg/apache/hadoop/mapred/LocalJobRunner;
     630: invokestatic  #198                // Method org/apache/hadoop/mapred/LocalJobRunner.access$900:(Lorg/apache/hadoop/mapred/LocalJobRunner;)Lorg/apache/hadoop/fs/FileSystem;
     633: aload_0
     634: getfield      #4                  // Field systemJobFile:Lorg/apache/hadoop/fs/Path;
     637: invokevirtual #199                // Method org/apache/hadoop/fs/Path.getParent:()Lorg/apache/hadoop/fs/Path;
     640: iconst_1
     641: invokevirtual #200                // Method org/apache/hadoop/fs/FileSystem.delete:(Lorg/apache/hadoop/fs/Path;Z)Z
     644: pop
     645: aload_0
     646: getfield      #26                 // Field localFs:Lorg/apache/hadoop/fs/FileSystem;
     649: aload_0
     650: getfield      #3                  // Field localJobFile:Lorg/apache/hadoop/fs/Path;
     653: iconst_1
     654: invokevirtual #200                // Method org/apache/hadoop/fs/FileSystem.delete:(Lorg/apache/hadoop/fs/Path;Z)Z
     657: pop
     658: goto          679
     661: astore        17
     663: aload_0
     664: getfield      #26                 // Field localFs:Lorg/apache/hadoop/fs/FileSystem;
     667: aload_0
     668: getfield      #3                  // Field localJobFile:Lorg/apache/hadoop/fs/Path;
     671: iconst_1
     672: invokevirtual #200                // Method org/apache/hadoop/fs/FileSystem.delete:(Lorg/apache/hadoop/fs/Path;Z)Z
     675: pop
     676: aload         17
     678: athrow
     679: goto          740
     682: astore        18
     684: aload_0
     685: getfield      #11                 // Field this$0:Lorg/apache/hadoop/mapred/LocalJobRunner;
     688: invokestatic  #198                // Method org/apache/hadoop/mapred/LocalJobRunner.access$900:(Lorg/apache/hadoop/mapred/LocalJobRunner;)Lorg/apache/hadoop/fs/FileSystem;
     691: aload_0
     692: getfield      #4                  // Field systemJobFile:Lorg/apache/hadoop/fs/Path;
     695: invokevirtual #199                // Method org/apache/hadoop/fs/Path.getParent:()Lorg/apache/hadoop/fs/Path;
     698: iconst_1
     699: invokevirtual #200                // Method org/apache/hadoop/fs/FileSystem.delete:(Lorg/apache/hadoop/fs/Path;Z)Z
     702: pop
     703: aload_0
     704: getfield      #26                 // Field localFs:Lorg/apache/hadoop/fs/FileSystem;
     707: aload_0
     708: getfield      #3                  // Field localJobFile:Lorg/apache/hadoop/fs/Path;
     711: iconst_1
     712: invokevirtual #200                // Method org/apache/hadoop/fs/FileSystem.delete:(Lorg/apache/hadoop/fs/Path;Z)Z
     715: pop
     716: goto          737
     719: astore        19
     721: aload_0
     722: getfield      #26                 // Field localFs:Lorg/apache/hadoop/fs/FileSystem;
     725: aload_0
     726: getfield      #3                  // Field localJobFile:Lorg/apache/hadoop/fs/Path;
     729: iconst_1
     730: invokevirtual #200                // Method org/apache/hadoop/fs/FileSystem.delete:(Lorg/apache/hadoop/fs/Path;Z)Z
     733: pop
     734: aload         19
     736: athrow
     737: aload         18
     739: athrow
     740: goto          959
     743: astore        4
     745: getstatic     #104                // Field org/apache/hadoop/mapred/LocalJobRunner.LOG:Lorg/slf4j/Logger;
     748: new           #34                 // class java/lang/StringBuilder
     751: dup
     752: invokespecial #35                 // Method java/lang/StringBuilder."<init>":()V
     755: ldc           #201                // String Error cleaning up
     757: invokevirtual #38                 // Method java/lang/StringBuilder.append:(Ljava/lang/String;)Ljava/lang/StringBuilder;
     760: aload_0
     761: getfield      #22                 // Field id:Lorg/apache/hadoop/mapred/JobID;
     764: invokevirtual #36                 // Method java/lang/StringBuilder.append:(Ljava/lang/Object;)Ljava/lang/StringBuilder;
     767: ldc           #202                // String :
     769: invokevirtual #38                 // Method java/lang/StringBuilder.append:(Ljava/lang/String;)Ljava/lang/StringBuilder;
     772: aload         4
     774: invokevirtual #36                 // Method java/lang/StringBuilder.append:(Ljava/lang/Object;)Ljava/lang/StringBuilder;
     777: invokevirtual #39                 // Method java/lang/StringBuilder.toString:()Ljava/lang/String;
     780: invokeinterface #203,  2          // InterfaceMethod org/slf4j/Logger.warn:(Ljava/lang/String;)V
     785: goto          959
     788: astore        20
     790: aload_0
     791: getfield      #42                 // Field localDistributedCacheManager:Lorg/apache/hadoop/mapred/LocalDistributedCacheManager;
     794: invokevirtual #197                // Method org/apache/hadoop/mapred/LocalDistributedCacheManager.close:()V
     797: aload_0
     798: getfield      #11                 // Field this$0:Lorg/apache/hadoop/mapred/LocalJobRunner;
     801: invokestatic  #198                // Method org/apache/hadoop/mapred/LocalJobRunner.access$900:(Lorg/apache/hadoop/mapred/LocalJobRunner;)Lorg/apache/hadoop/fs/FileSystem;
     804: aload_0
     805: getfield      #4                  // Field systemJobFile:Lorg/apache/hadoop/fs/Path;
     808: invokevirtual #199                // Method org/apache/hadoop/fs/Path.getParent:()Lorg/apache/hadoop/fs/Path;
     811: iconst_1
     812: invokevirtual #200                // Method org/apache/hadoop/fs/FileSystem.delete:(Lorg/apache/hadoop/fs/Path;Z)Z
     815: pop
     816: aload_0
     817: getfield      #26                 // Field localFs:Lorg/apache/hadoop/fs/FileSystem;
     820: aload_0
     821: getfield      #3                  // Field localJobFile:Lorg/apache/hadoop/fs/Path;
     824: iconst_1
     825: invokevirtual #200                // Method org/apache/hadoop/fs/FileSystem.delete:(Lorg/apache/hadoop/fs/Path;Z)Z
     828: pop
     829: goto          850
     832: astore        21
     834: aload_0
     835: getfield      #26                 // Field localFs:Lorg/apache/hadoop/fs/FileSystem;
     838: aload_0
     839: getfield      #3                  // Field localJobFile:Lorg/apache/hadoop/fs/Path;
     842: iconst_1
     843: invokevirtual #200                // Method org/apache/hadoop/fs/FileSystem.delete:(Lorg/apache/hadoop/fs/Path;Z)Z
     846: pop
     847: aload         21
     849: athrow
     850: goto          911
     853: astore        22
     855: aload_0
     856: getfield      #11                 // Field this$0:Lorg/apache/hadoop/mapred/LocalJobRunner;
     859: invokestatic  #198                // Method org/apache/hadoop/mapred/LocalJobRunner.access$900:(Lorg/apache/hadoop/mapred/LocalJobRunner;)Lorg/apache/hadoop/fs/FileSystem;
     862: aload_0
     863: getfield      #4                  // Field systemJobFile:Lorg/apache/hadoop/fs/Path;
     866: invokevirtual #199                // Method org/apache/hadoop/fs/Path.getParent:()Lorg/apache/hadoop/fs/Path;
     869: iconst_1
     870: invokevirtual #200                // Method org/apache/hadoop/fs/FileSystem.delete:(Lorg/apache/hadoop/fs/Path;Z)Z
     873: pop
     874: aload_0
     875: getfield      #26                 // Field localFs:Lorg/apache/hadoop/fs/FileSystem;
     878: aload_0
     879: getfield      #3                  // Field localJobFile:Lorg/apache/hadoop/fs/Path;
     882: iconst_1
     883: invokevirtual #200                // Method org/apache/hadoop/fs/FileSystem.delete:(Lorg/apache/hadoop/fs/Path;Z)Z
     886: pop
     887: goto          908
     890: astore        23
     892: aload_0
     893: getfield      #26                 // Field localFs:Lorg/apache/hadoop/fs/FileSystem;
     896: aload_0
     897: getfield      #3                  // Field localJobFile:Lorg/apache/hadoop/fs/Path;
     900: iconst_1
     901: invokevirtual #200                // Method org/apache/hadoop/fs/FileSystem.delete:(Lorg/apache/hadoop/fs/Path;Z)Z
     904: pop
     905: aload         23
     907: athrow
     908: aload         22
     910: athrow
     911: goto          956
     914: astore        21
     916: getstatic     #104                // Field org/apache/hadoop/mapred/LocalJobRunner.LOG:Lorg/slf4j/Logger;
     919: new           #34                 // class java/lang/StringBuilder
     922: dup
     923: invokespecial #35                 // Method java/lang/StringBuilder."<init>":()V
     926: ldc           #201                // String Error cleaning up
     928: invokevirtual #38                 // Method java/lang/StringBuilder.append:(Ljava/lang/String;)Ljava/lang/StringBuilder;
     931: aload_0
     932: getfield      #22                 // Field id:Lorg/apache/hadoop/mapred/JobID;
     935: invokevirtual #36                 // Method java/lang/StringBuilder.append:(Ljava/lang/Object;)Ljava/lang/StringBuilder;
     938: ldc           #202                // String :
     940: invokevirtual #38                 // Method java/lang/StringBuilder.append:(Ljava/lang/String;)Ljava/lang/StringBuilder;
     943: aload         21
     945: invokevirtual #36                 // Method java/lang/StringBuilder.append:(Ljava/lang/Object;)Ljava/lang/StringBuilder;
     948: invokevirtual #39                 // Method java/lang/StringBuilder.toString:()Ljava/lang/String;
     951: invokeinterface #203,  2          // InterfaceMethod org/slf4j/Logger.warn:(Ljava/lang/String;)V
     956: aload         20
     958: athrow
     959: return
    Exception table:
       from    to  target type
          23    46    49   Class java/lang/Exception
         159   189   236   any
         236   238   236   any
         346   365   381   any
         381   383   381   any
         339   346   402   any
         404   423   439   any
         439   441   439   any
         402   404   402   any
         339   460   463   Class java/io/IOException
          64   339   508   Class java/lang/Throwable
         510   518   521   Class java/io/IOException
         626   645   661   any
         661   663   661   any
         619   626   682   any
         684   703   719   any
         719   721   719   any
         682   684   682   any
         619   740   743   Class java/io/IOException
          64   339   788   any
         508   619   788   any
         797   816   832   any
         832   834   832   any
         790   797   853   any
         855   874   890   any
         890   892   890   any
         853   855   853   any
         790   911   914   Class java/io/IOException
         788   790   788   any

  public org.apache.hadoop.mapred.JvmTask getTask(org.apache.hadoop.mapred.JvmContext);
    Code:
       0: aconst_null
       1: areturn

  public synchronized org.apache.hadoop.mapred.AMFeedback statusUpdate(org.apache.hadoop.mapred.TaskAttemptID, org.apache.hadoop.mapred.TaskStatus) throws java.io.IOException, java.lang.InterruptedException;
    Code:
       0: new           #210                // class org/apache/hadoop/mapred/AMFeedback
       3: dup
       4: invokespecial #211                // Method org/apache/hadoop/mapred/AMFeedback."<init>":()V
       7: astore_3
       8: aload_3
       9: iconst_1
      10: invokevirtual #212                // Method org/apache/hadoop/mapred/AMFeedback.setTaskFound:(Z)V
      13: aconst_null
      14: aload_2
      15: if_acmpne     20
      18: aload_3
      19: areturn
      20: new           #213                // class java/io/ByteArrayOutputStream
      23: dup
      24: invokespecial #214                // Method java/io/ByteArrayOutputStream."<init>":()V
      27: astore        4
      29: new           #215                // class java/io/DataOutputStream
      32: dup
      33: aload         4
      35: invokespecial #216                // Method java/io/DataOutputStream."<init>":(Ljava/io/OutputStream;)V
      38: astore        5
      40: aload_2
      41: aload         5
      43: invokevirtual #217                // Method org/apache/hadoop/mapred/TaskStatus.write:(Ljava/io/DataOutput;)V
      46: aload         5
      48: invokevirtual #218                // Method java/io/DataOutputStream.close:()V
      51: aload_2
      52: invokevirtual #219                // Method org/apache/hadoop/mapred/TaskStatus.getIsMap:()Z
      55: invokestatic  #220                // Method org/apache/hadoop/mapred/TaskStatus.createTaskStatus:(Z)Lorg/apache/hadoop/mapred/TaskStatus;
      58: astore_2
      59: aload_2
      60: new           #221                // class java/io/DataInputStream
      63: dup
      64: new           #222                // class java/io/ByteArrayInputStream
      67: dup
      68: aload         4
      70: invokevirtual #223                // Method java/io/ByteArrayOutputStream.toByteArray:()[B
      73: invokespecial #224                // Method java/io/ByteArrayInputStream."<init>":([B)V
      76: invokespecial #225                // Method java/io/DataInputStream."<init>":(Ljava/io/InputStream;)V
      79: invokevirtual #226                // Method org/apache/hadoop/mapred/TaskStatus.readFields:(Ljava/io/DataInput;)V
      82: getstatic     #104                // Field org/apache/hadoop/mapred/LocalJobRunner.LOG:Lorg/slf4j/Logger;
      85: aload_2
      86: invokevirtual #227                // Method org/apache/hadoop/mapred/TaskStatus.getStateString:()Ljava/lang/String;
      89: invokeinterface #129,  2          // InterfaceMethod org/slf4j/Logger.info:(Ljava/lang/String;)V
      94: aload_0
      95: getfield      #5                  // Field mapIds:Ljava/util/List;
      98: aload_1
      99: invokeinterface #228,  2          // InterfaceMethod java/util/List.indexOf:(Ljava/lang/Object;)I
     104: istore        6
     106: iload         6
     108: iflt          199
     111: aload_0
     112: getfield      #97                 // Field numMapTasks:I
     115: i2f
     116: fstore        7
     118: aload_0
     119: getfield      #91                 // Field partialMapProgress:[F
     122: iload         6
     124: aload_2
     125: invokevirtual #229                // Method org/apache/hadoop/mapred/TaskStatus.getProgress:()F
     128: fastore
     129: aload_0
     130: getfield      #93                 // Field mapCounters:[Lorg/apache/hadoop/mapred/Counters;
     133: iload         6
     135: aload_2
     136: invokevirtual #230                // Method org/apache/hadoop/mapred/TaskStatus.getCounters:()Lorg/apache/hadoop/mapred/Counters;
     139: aastore
     140: fconst_0
     141: fstore        8
     143: aload_0
     144: getfield      #91                 // Field partialMapProgress:[F
     147: astore        9
     149: aload         9
     151: arraylength
     152: istore        10
     154: iconst_0
     155: istore        11
     157: iload         11
     159: iload         10
     161: if_icmpge     184
     164: aload         9
     166: iload         11
     168: faload
     169: fstore        12
     171: fload         8
     173: fload         12
     175: fadd
     176: fstore        8
     178: iinc          11, 1
     181: goto          157
     184: aload_0
     185: getfield      #2                  // Field status:Lorg/apache/hadoop/mapred/JobStatus;
     188: fload         8
     190: fload         7
     192: fdiv
     193: invokevirtual #231                // Method org/apache/hadoop/mapred/JobStatus.setMapProgress:(F)V
     196: goto          293
     199: aload_1
     200: invokevirtual #232                // Method org/apache/hadoop/mapred/TaskAttemptID.getTaskID:()Lorg/apache/hadoop/mapred/TaskID;
     203: invokevirtual #233                // Method org/apache/hadoop/mapred/TaskID.getId:()I
     206: istore        7
     208: aload_0
     209: getfield      #88                 // Field numReduceTasks:I
     212: i2f
     213: fstore        8
     215: aload_0
     216: getfield      #95                 // Field partialReduceProgress:[F
     219: iload         7
     221: aload_2
     222: invokevirtual #229                // Method org/apache/hadoop/mapred/TaskStatus.getProgress:()F
     225: fastore
     226: aload_0
     227: getfield      #96                 // Field reduceCounters:[Lorg/apache/hadoop/mapred/Counters;
     230: iload         7
     232: aload_2
     233: invokevirtual #230                // Method org/apache/hadoop/mapred/TaskStatus.getCounters:()Lorg/apache/hadoop/mapred/Counters;
     236: aastore
     237: fconst_0
     238: fstore        9
     240: aload_0
     241: getfield      #95                 // Field partialReduceProgress:[F
     244: astore        10
     246: aload         10
     248: arraylength
     249: istore        11
     251: iconst_0
     252: istore        12
     254: iload         12
     256: iload         11
     258: if_icmpge     281
     261: aload         10
     263: iload         12
     265: faload
     266: fstore        13
     268: fload         9
     270: fload         13
     272: fadd
     273: fstore        9
     275: iinc          12, 1
     278: goto          254
     281: aload_0
     282: getfield      #2                  // Field status:Lorg/apache/hadoop/mapred/JobStatus;
     285: fload         9
     287: fload         8
     289: fdiv
     290: invokevirtual #234                // Method org/apache/hadoop/mapred/JobStatus.setReduceProgress:(F)V
     293: aload_3
     294: areturn

  public synchronized org.apache.hadoop.mapred.Counters getCurrentCounters();
    Code:
       0: aconst_null
       1: aload_0
       2: getfield      #93                 // Field mapCounters:[Lorg/apache/hadoop/mapred/Counters;
       5: if_acmpne     16
       8: new           #92                 // class org/apache/hadoop/mapred/Counters
      11: dup
      12: invokespecial #94                 // Method org/apache/hadoop/mapred/Counters."<init>":()V
      15: areturn
      16: new           #92                 // class org/apache/hadoop/mapred/Counters
      19: dup
      20: invokespecial #94                 // Method org/apache/hadoop/mapred/Counters."<init>":()V
      23: astore_1
      24: aload_0
      25: getfield      #93                 // Field mapCounters:[Lorg/apache/hadoop/mapred/Counters;
      28: astore_2
      29: aload_2
      30: arraylength
      31: istore_3
      32: iconst_0
      33: istore        4
      35: iload         4
      37: iload_3
      38: if_icmpge     60
      41: aload_2
      42: iload         4
      44: aaload
      45: astore        5
      47: aload_1
      48: aload         5
      50: invokestatic  #235                // Method org/apache/hadoop/mapred/Counters.sum:(Lorg/apache/hadoop/mapred/Counters;Lorg/apache/hadoop/mapred/Counters;)Lorg/apache/hadoop/mapred/Counters;
      53: astore_1
      54: iinc          4, 1
      57: goto          35
      60: aconst_null
      61: aload_0
      62: getfield      #96                 // Field reduceCounters:[Lorg/apache/hadoop/mapred/Counters;
      65: if_acmpeq     112
      68: aload_0
      69: getfield      #96                 // Field reduceCounters:[Lorg/apache/hadoop/mapred/Counters;
      72: arraylength
      73: ifle          112
      76: aload_0
      77: getfield      #96                 // Field reduceCounters:[Lorg/apache/hadoop/mapred/Counters;
      80: astore_2
      81: aload_2
      82: arraylength
      83: istore_3
      84: iconst_0
      85: istore        4
      87: iload         4
      89: iload_3
      90: if_icmpge     112
      93: aload_2
      94: iload         4
      96: aaload
      97: astore        5
      99: aload_1
     100: aload         5
     102: invokestatic  #235                // Method org/apache/hadoop/mapred/Counters.sum:(Lorg/apache/hadoop/mapred/Counters;Lorg/apache/hadoop/mapred/Counters;)Lorg/apache/hadoop/mapred/Counters;
     105: astore_1
     106: iinc          4, 1
     109: goto          87
     112: aload_1
     113: areturn

  public void commitPending(org.apache.hadoop.mapred.TaskAttemptID, org.apache.hadoop.mapred.TaskStatus) throws java.io.IOException, java.lang.InterruptedException;
    Code:
       0: aload_0
       1: aload_1
       2: aload_2
       3: invokevirtual #236                // Method statusUpdate:(Lorg/apache/hadoop/mapred/TaskAttemptID;Lorg/apache/hadoop/mapred/TaskStatus;)Lorg/apache/hadoop/mapred/AMFeedback;
       6: pop
       7: return

  public void reportDiagnosticInfo(org.apache.hadoop.mapred.TaskAttemptID, java.lang.String);
    Code:
       0: return

  public void reportNextRecordRange(org.apache.hadoop.mapred.TaskAttemptID, org.apache.hadoop.mapred.SortedRanges$Range) throws java.io.IOException;
    Code:
       0: getstatic     #104                // Field org/apache/hadoop/mapred/LocalJobRunner.LOG:Lorg/slf4j/Logger;
       3: new           #34                 // class java/lang/StringBuilder
       6: dup
       7: invokespecial #35                 // Method java/lang/StringBuilder."<init>":()V
      10: ldc           #237                // String Task
      12: invokevirtual #38                 // Method java/lang/StringBuilder.append:(Ljava/lang/String;)Ljava/lang/StringBuilder;
      15: aload_1
      16: invokevirtual #36                 // Method java/lang/StringBuilder.append:(Ljava/lang/Object;)Ljava/lang/StringBuilder;
      19: ldc           #238                // String  reportedNextRecordRange
      21: invokevirtual #38                 // Method java/lang/StringBuilder.append:(Ljava/lang/String;)Ljava/lang/StringBuilder;
      24: aload_2
      25: invokevirtual #36                 // Method java/lang/StringBuilder.append:(Ljava/lang/Object;)Ljava/lang/StringBuilder;
      28: invokevirtual #39                 // Method java/lang/StringBuilder.toString:()Ljava/lang/String;
      31: invokeinterface #129,  2          // InterfaceMethod org/slf4j/Logger.info:(Ljava/lang/String;)V
      36: return

  public boolean canCommit(org.apache.hadoop.mapred.TaskAttemptID) throws java.io.IOException;
    Code:
       0: iconst_1
       1: ireturn

  public void done(org.apache.hadoop.mapred.TaskAttemptID) throws java.io.IOException;
    Code:
       0: aload_0
       1: getfield      #5                  // Field mapIds:Ljava/util/List;
       4: aload_1
       5: invokeinterface #228,  2          // InterfaceMethod java/util/List.indexOf:(Ljava/lang/Object;)I
      10: istore_2
      11: iload_2
      12: iflt          26
      15: aload_0
      16: getfield      #2                  // Field status:Lorg/apache/hadoop/mapred/JobStatus;
      19: fconst_1
      20: invokevirtual #231                // Method org/apache/hadoop/mapred/JobStatus.setMapProgress:(F)V
      23: goto          34
      26: aload_0
      27: getfield      #2                  // Field status:Lorg/apache/hadoop/mapred/JobStatus;
      30: fconst_1
      31: invokevirtual #234                // Method org/apache/hadoop/mapred/JobStatus.setReduceProgress:(F)V
      34: return

  public synchronized void fsError(org.apache.hadoop.mapred.TaskAttemptID, java.lang.String) throws java.io.IOException;
    Code:
       0: getstatic     #104                // Field org/apache/hadoop/mapred/LocalJobRunner.LOG:Lorg/slf4j/Logger;
       3: new           #34                 // class java/lang/StringBuilder
       6: dup
       7: invokespecial #35                 // Method java/lang/StringBuilder."<init>":()V
      10: ldc           #239                // String FSError:
      12: invokevirtual #38                 // Method java/lang/StringBuilder.append:(Ljava/lang/String;)Ljava/lang/StringBuilder;
      15: aload_2
      16: invokevirtual #38                 // Method java/lang/StringBuilder.append:(Ljava/lang/String;)Ljava/lang/StringBuilder;
      19: ldc           #240                // String from task:
      21: invokevirtual #38                 // Method java/lang/StringBuilder.append:(Ljava/lang/String;)Ljava/lang/StringBuilder;
      24: aload_1
      25: invokevirtual #36                 // Method java/lang/StringBuilder.append:(Ljava/lang/Object;)Ljava/lang/StringBuilder;
      28: invokevirtual #39                 // Method java/lang/StringBuilder.toString:()Ljava/lang/String;
      31: invokeinterface #241,  2          // InterfaceMethod org/slf4j/Logger.error:(Ljava/lang/String;)V
      36: return

  public void shuffleError(org.apache.hadoop.mapred.TaskAttemptID, java.lang.String) throws java.io.IOException;
    Code:
       0: getstatic     #104                // Field org/apache/hadoop/mapred/LocalJobRunner.LOG:Lorg/slf4j/Logger;
       3: new           #34                 // class java/lang/StringBuilder
       6: dup
       7: invokespecial #35                 // Method java/lang/StringBuilder."<init>":()V
      10: ldc           #242                // String shuffleError:
      12: invokevirtual #38                 // Method java/lang/StringBuilder.append:(Ljava/lang/String;)Ljava/lang/StringBuilder;
      15: aload_2
      16: invokevirtual #38                 // Method java/lang/StringBuilder.append:(Ljava/lang/String;)Ljava/lang/StringBuilder;
      19: ldc           #240                // String from task:
      21: invokevirtual #38                 // Method java/lang/StringBuilder.append:(Ljava/lang/String;)Ljava/lang/StringBuilder;
      24: aload_1
      25: invokevirtual #36                 // Method java/lang/StringBuilder.append:(Ljava/lang/Object;)Ljava/lang/StringBuilder;
      28: invokevirtual #39                 // Method java/lang/StringBuilder.toString:()Ljava/lang/String;
      31: invokeinterface #241,  2          // InterfaceMethod org/slf4j/Logger.error:(Ljava/lang/String;)V
      36: return

  public synchronized void fatalError(org.apache.hadoop.mapred.TaskAttemptID, java.lang.String, boolean) throws java.io.IOException;
    Code:
       0: getstatic     #104                // Field org/apache/hadoop/mapred/LocalJobRunner.LOG:Lorg/slf4j/Logger;
       3: new           #34                 // class java/lang/StringBuilder
       6: dup
       7: invokespecial #35                 // Method java/lang/StringBuilder."<init>":()V
      10: ldc           #243                // String Fatal:
      12: invokevirtual #38                 // Method java/lang/StringBuilder.append:(Ljava/lang/String;)Ljava/lang/StringBuilder;
      15: aload_2
      16: invokevirtual #38                 // Method java/lang/StringBuilder.append:(Ljava/lang/String;)Ljava/lang/StringBuilder;
      19: ldc           #244                // String  from task:
      21: invokevirtual #38                 // Method java/lang/StringBuilder.append:(Ljava/lang/String;)Ljava/lang/StringBuilder;
      24: aload_1
      25: invokevirtual #36                 // Method java/lang/StringBuilder.append:(Ljava/lang/Object;)Ljava/lang/StringBuilder;
      28: ldc           #245                // String  fast fail:
      30: invokevirtual #38                 // Method java/lang/StringBuilder.append:(Ljava/lang/String;)Ljava/lang/StringBuilder;
      33: iload_3
      34: invokevirtual #246                // Method java/lang/StringBuilder.append:(Z)Ljava/lang/StringBuilder;
      37: invokevirtual #39                 // Method java/lang/StringBuilder.toString:()Ljava/lang/String;
      40: invokeinterface #241,  2          // InterfaceMethod org/slf4j/Logger.error:(Ljava/lang/String;)V
      45: return

  public org.apache.hadoop.mapred.MapTaskCompletionEventsUpdate getMapCompletionEvents(org.apache.hadoop.mapred.JobID, int, int, org.apache.hadoop.mapred.TaskAttemptID) throws java.io.IOException;
    Code:
       0: new           #247                // class org/apache/hadoop/mapred/MapTaskCompletionEventsUpdate
       3: dup
       4: getstatic     #248                // Field org/apache/hadoop/mapred/TaskCompletionEvent.EMPTY_ARRAY:[Lorg/apache/hadoop/mapred/TaskCompletionEvent;
       7: iconst_0
       8: invokespecial #249                // Method org/apache/hadoop/mapred/MapTaskCompletionEventsUpdate."<init>":([Lorg/apache/hadoop/mapred/TaskCompletionEvent;Z)V
      11: areturn

  public void preempted(org.apache.hadoop.mapred.TaskAttemptID, org.apache.hadoop.mapred.TaskStatus) throws java.io.IOException, java.lang.InterruptedException;
    Code:
       0: return

  public org.apache.hadoop.mapreduce.checkpoint.TaskCheckpointID getCheckpointID(org.apache.hadoop.mapred.TaskID);
    Code:
       0: aconst_null
       1: areturn

  public void setCheckpointID(org.apache.hadoop.mapred.TaskID, org.apache.hadoop.mapreduce.checkpoint.TaskCheckpointID);
    Code:
       0: return

  static org.apache.hadoop.mapred.JobConf access$100(org.apache.hadoop.mapred.LocalJobRunner$Job);
    Code:
       0: aload_0
       1: getfield      #6                  // Field job:Lorg/apache/hadoop/mapred/JobConf;
       4: areturn

  static java.util.List access$200(org.apache.hadoop.mapred.LocalJobRunner$Job);
    Code:
       0: aload_0
       1: getfield      #5                  // Field mapIds:Ljava/util/List;
       4: areturn

  static org.apache.hadoop.fs.Path access$300(org.apache.hadoop.mapred.LocalJobRunner$Job);
    Code:
       0: aload_0
       1: getfield      #4                  // Field systemJobFile:Lorg/apache/hadoop/fs/Path;
       4: areturn

  static org.apache.hadoop.fs.Path access$400(org.apache.hadoop.mapred.LocalJobRunner$Job);
    Code:
       0: aload_0
       1: getfield      #3                  // Field localJobFile:Lorg/apache/hadoop/fs/Path;
       4: areturn

  static org.apache.hadoop.mapred.JobStatus access$1000(org.apache.hadoop.mapred.LocalJobRunner$Job);
    Code:
       0: aload_0
       1: getfield      #2                  // Field status:Lorg/apache/hadoop/mapred/JobStatus;
       4: areturn
}
