Compiled from "ServerProcessReloadHandler.java"
public class org.jboss.as.server.operations.ServerProcessReloadHandler extends org.jboss.as.controller.operations.common.ProcessReloadHandler<org.jboss.as.controller.RunningModeControl> {
  private static final org.jboss.as.controller.AttributeDefinition USE_CURRENT_SERVER_CONFIG;

  private static final org.jboss.as.controller.AttributeDefinition[] ATTRIBUTES;

  public static final org.jboss.as.controller.OperationDefinition DEFINITION;

  public org.jboss.as.server.operations.ServerProcessReloadHandler(org.jboss.msc.service.ServiceName, org.jboss.as.controller.RunningModeControl, org.jboss.as.controller.ControlledProcessState);
    Code:
       0: aload_0
       1: aload_1
       2: aload_2
       3: aload_3
       4: invokespecial #1                  // Method org/jboss/as/controller/operations/common/ProcessReloadHandler."<init>":(Lorg/jboss/msc/service/ServiceName;Lorg/jboss/as/controller/RunningModeControl;Lorg/jboss/as/controller/ControlledProcessState;)V
       7: return

  protected org.jboss.as.controller.operations.common.ProcessReloadHandler$ReloadContext<org.jboss.as.controller.RunningModeControl> initializeReloadContext(org.jboss.as.controller.OperationContext, org.jboss.dmr.ModelNode) throws org.jboss.as.controller.OperationFailedException;
    Code:
       0: aload_1
       1: invokeinterface #2,  1            // InterfaceMethod org/jboss/as/controller/OperationContext.getProcessType:()Lorg/jboss/as/controller/ProcessType;
       6: getstatic     #3                  // Field org/jboss/as/controller/ProcessType.DOMAIN_SERVER:Lorg/jboss/as/controller/ProcessType;
       9: if_acmpeq     16
      12: iconst_1
      13: goto          17
      16: iconst_0
      17: istore_3
      18: iload_3
      19: ifeq          41
      22: getstatic     #4                  // Field ADMIN_ONLY:Lorg/jboss/as/controller/AttributeDefinition;
      25: aload_1
      26: aload_2
      27: invokevirtual #5                  // Method org/jboss/as/controller/AttributeDefinition.resolveModelAttribute:(Lorg/jboss/as/controller/OperationContext;Lorg/jboss/dmr/ModelNode;)Lorg/jboss/dmr/ModelNode;
      30: iconst_0
      31: invokevirtual #6                  // Method org/jboss/dmr/ModelNode.asBoolean:(Z)Z
      34: ifeq          41
      37: iconst_1
      38: goto          42
      41: iconst_0
      42: istore        4
      44: iload_3
      45: ifeq          67
      48: getstatic     #7                  // Field USE_CURRENT_SERVER_CONFIG:Lorg/jboss/as/controller/AttributeDefinition;
      51: aload_1
      52: aload_2
      53: invokevirtual #5                  // Method org/jboss/as/controller/AttributeDefinition.resolveModelAttribute:(Lorg/jboss/as/controller/OperationContext;Lorg/jboss/dmr/ModelNode;)Lorg/jboss/dmr/ModelNode;
      56: iconst_1
      57: invokevirtual #6                  // Method org/jboss/dmr/ModelNode.asBoolean:(Z)Z
      60: ifeq          67
      63: iconst_1
      64: goto          68
      67: iconst_0
      68: istore        5
      70: new           #8                  // class org/jboss/as/server/operations/ServerProcessReloadHandler$1
      73: dup
      74: aload_0
      75: iload         4
      77: iload         5
      79: invokespecial #9                  // Method org/jboss/as/server/operations/ServerProcessReloadHandler$1."<init>":(Lorg/jboss/as/server/operations/ServerProcessReloadHandler;ZZ)V
      82: areturn

  static {};
    Code:
       0: new           #10                 // class org/jboss/as/controller/SimpleAttributeDefinitionBuilder
       3: dup
       4: ldc           #12                 // String use-current-server-config
       6: getstatic     #13                 // Field org/jboss/dmr/ModelType.BOOLEAN:Lorg/jboss/dmr/ModelType;
       9: iconst_1
      10: invokespecial #14                 // Method org/jboss/as/controller/SimpleAttributeDefinitionBuilder."<init>":(Ljava/lang/String;Lorg/jboss/dmr/ModelType;Z)V
      13: new           #15                 // class org/jboss/dmr/ModelNode
      16: dup
      17: iconst_1
      18: invokespecial #16                 // Method org/jboss/dmr/ModelNode."<init>":(Z)V
      21: invokevirtual #17                 // Method org/jboss/as/controller/SimpleAttributeDefinitionBuilder.setDefaultValue:(Lorg/jboss/dmr/ModelNode;)Lorg/jboss/as/controller/AbstractAttributeDefinitionBuilder;
      24: checkcast     #10                 // class org/jboss/as/controller/SimpleAttributeDefinitionBuilder
      27: invokevirtual #18                 // Method org/jboss/as/controller/SimpleAttributeDefinitionBuilder.build:()Lorg/jboss/as/controller/SimpleAttributeDefinition;
      30: putstatic     #7                  // Field USE_CURRENT_SERVER_CONFIG:Lorg/jboss/as/controller/AttributeDefinition;
      33: iconst_2
      34: anewarray     #19                 // class org/jboss/as/controller/AttributeDefinition
      37: dup
      38: iconst_0
      39: getstatic     #4                  // Field ADMIN_ONLY:Lorg/jboss/as/controller/AttributeDefinition;
      42: aastore
      43: dup
      44: iconst_1
      45: getstatic     #7                  // Field USE_CURRENT_SERVER_CONFIG:Lorg/jboss/as/controller/AttributeDefinition;
      48: aastore
      49: putstatic     #20                 // Field ATTRIBUTES:[Lorg/jboss/as/controller/AttributeDefinition;
      52: new           #21                 // class org/jboss/as/controller/SimpleOperationDefinitionBuilder
      55: dup
      56: ldc           #23                 // String reload
      58: iconst_1
      59: anewarray     #24                 // class java/lang/String
      62: dup
      63: iconst_0
      64: ldc           #25                 // String server
      66: aastore
      67: invokestatic  #26                 // Method org/jboss/as/server/controller/descriptions/ServerDescriptions.getResourceDescriptionResolver:([Ljava/lang/String;)Lorg/jboss/as/controller/descriptions/ResourceDescriptionResolver;
      70: invokespecial #27                 // Method org/jboss/as/controller/SimpleOperationDefinitionBuilder."<init>":(Ljava/lang/String;Lorg/jboss/as/controller/descriptions/ResourceDescriptionResolver;)V
      73: getstatic     #20                 // Field ATTRIBUTES:[Lorg/jboss/as/controller/AttributeDefinition;
      76: invokevirtual #28                 // Method org/jboss/as/controller/SimpleOperationDefinitionBuilder.setParameters:([Lorg/jboss/as/controller/AttributeDefinition;)Lorg/jboss/as/controller/SimpleOperationDefinitionBuilder;
      79: invokevirtual #29                 // Method org/jboss/as/controller/SimpleOperationDefinitionBuilder.setRuntimeOnly:()Lorg/jboss/as/controller/SimpleOperationDefinitionBuilder;
      82: invokevirtual #30                 // Method org/jboss/as/controller/SimpleOperationDefinitionBuilder.build:()Lorg/jboss/as/controller/SimpleOperationDefinition;
      85: putstatic     #31                 // Field DEFINITION:Lorg/jboss/as/controller/OperationDefinition;
      88: return
}
