Compiled from "ExtendedByTypesComparator.java"
class org.assertj.core.internal.ExtendedByTypesComparator$1 implements java.util.Comparator<java.lang.Object> {
  org.assertj.core.internal.ExtendedByTypesComparator$1();
    Code:
       0: aload_0
       1: invokespecial #16                 // Method java/lang/Object."<init>":()V
       4: return

  public int compare(java.lang.Object, java.lang.Object);
    Code:
       0: aload_1
       1: aload_2
       2: invokestatic  #26                 // Method org/assertj/core/util/Objects.areEqual:(Ljava/lang/Object;Ljava/lang/Object;)Z
       5: ifeq          12
       8: iconst_0
       9: goto          13
      12: iconst_m1
      13: ireturn

  public java.lang.String toString();
    Code:
       0: ldc           #33                 // String AssertJ Object comparator
       2: areturn
}
