Compiled from "TemplateModel.java"
public final class ru.tinkoff.kora.database.annotation.processor.model.TemplateModel$TemplateParam extends java.lang.Record {
  private final java.lang.String paramName;

  private final java.lang.String template;

  private final java.lang.String rawTemplate;

  public ru.tinkoff.kora.database.annotation.processor.model.TemplateModel$TemplateParam(java.lang.String, java.lang.String, java.lang.String);
    Code:
       0: aload_0
       1: invokespecial #1                  // Method java/lang/Record."<init>":()V
       4: aload_0
       5: aload_1
       6: putfield      #7                  // Field paramName:Ljava/lang/String;
       9: aload_0
      10: aload_2
      11: putfield      #13                 // Field template:Ljava/lang/String;
      14: aload_0
      15: aload_3
      16: putfield      #16                 // Field rawTemplate:Ljava/lang/String;
      19: return

  public final java.lang.String toString();
    Code:
       0: aload_0
       1: invokedynamic #19,  0             // InvokeDynamic #0:toString:(Lru/tinkoff/kora/database/annotation/processor/model/TemplateModel$TemplateParam;)Ljava/lang/String;
       6: areturn

  public final int hashCode();
    Code:
       0: aload_0
       1: invokedynamic #23,  0             // InvokeDynamic #0:hashCode:(Lru/tinkoff/kora/database/annotation/processor/model/TemplateModel$TemplateParam;)I
       6: ireturn

  public final boolean equals(java.lang.Object);
    Code:
       0: aload_0
       1: aload_1
       2: invokedynamic #27,  0             // InvokeDynamic #0:equals:(Lru/tinkoff/kora/database/annotation/processor/model/TemplateModel$TemplateParam;Ljava/lang/Object;)Z
       7: ireturn

  public java.lang.String paramName();
    Code:
       0: aload_0
       1: getfield      #7                  // Field paramName:Ljava/lang/String;
       4: areturn

  public java.lang.String template();
    Code:
       0: aload_0
       1: getfield      #13                 // Field template:Ljava/lang/String;
       4: areturn

  public java.lang.String rawTemplate();
    Code:
       0: aload_0
       1: getfield      #16                 // Field rawTemplate:Ljava/lang/String;
       4: areturn
}
