Compiled from "OperationServiceV2.java"
public class uk.gov.gchq.gaffer.rest.service.v2.OperationServiceV2$OperationDetail {
  private final java.lang.String name;

  private final java.lang.String summary;

  private final java.util.List<uk.gov.gchq.gaffer.rest.service.v2.OperationServiceV2$OperationField> fields;

  private final java.util.Set<java.lang.Class<? extends uk.gov.gchq.gaffer.operation.Operation>> next;

  private final uk.gov.gchq.gaffer.operation.Operation exampleJson;

  private final java.lang.String outputClassName;

  final uk.gov.gchq.gaffer.rest.service.v2.OperationServiceV2 this$0;

  uk.gov.gchq.gaffer.rest.service.v2.OperationServiceV2$OperationDetail(java.lang.Class<? extends uk.gov.gchq.gaffer.operation.Operation>);
    Code:
       0: aload_0
       1: aload_1
       2: putfield      #1                  // Field this$0:Luk/gov/gchq/gaffer/rest/service/v2/OperationServiceV2;
       5: aload_0
       6: invokespecial #2                  // Method java/lang/Object."<init>":()V
       9: aload_0
      10: aload_2
      11: invokevirtual #3                  // Method java/lang/Class.getName:()Ljava/lang/String;
      14: putfield      #4                  // Field name:Ljava/lang/String;
      17: aload_0
      18: aload_2
      19: invokestatic  #5                  // Method uk/gov/gchq/gaffer/rest/service/v2/OperationServiceV2.access$000:(Ljava/lang/Class;)Ljava/lang/String;
      22: putfield      #6                  // Field summary:Ljava/lang/String;
      25: aload_0
      26: aload_1
      27: aload_2
      28: invokestatic  #7                  // Method uk/gov/gchq/gaffer/rest/service/v2/OperationServiceV2.access$100:(Luk/gov/gchq/gaffer/rest/service/v2/OperationServiceV2;Ljava/lang/Class;)Ljava/util/List;
      31: putfield      #8                  // Field fields:Ljava/util/List;
      34: aload_0
      35: aload_1
      36: aload_2
      37: invokestatic  #9                  // Method uk/gov/gchq/gaffer/rest/service/v2/OperationServiceV2.access$200:(Luk/gov/gchq/gaffer/rest/service/v2/OperationServiceV2;Ljava/lang/Class;)Ljava/util/Set;
      40: putfield      #10                 // Field next:Ljava/util/Set;
      43: aload_0
      44: aload_1
      45: aload_2
      46: invokestatic  #11                 // Method uk/gov/gchq/gaffer/rest/service/v2/OperationServiceV2.access$300:(Luk/gov/gchq/gaffer/rest/service/v2/OperationServiceV2;Ljava/lang/Class;)Luk/gov/gchq/gaffer/operation/Operation;
      49: putfield      #12                 // Field exampleJson:Luk/gov/gchq/gaffer/operation/Operation;
      52: goto          90
      55: astore_3
      56: new           #15                 // class uk/gov/gchq/gaffer/core/exception/GafferRuntimeException
      59: dup
      60: new           #16                 // class java/lang/StringBuilder
      63: dup
      64: invokespecial #17                 // Method java/lang/StringBuilder."<init>":()V
      67: ldc           #18                 // String Could not get operation details for class:
      69: invokevirtual #19                 // Method java/lang/StringBuilder.append:(Ljava/lang/String;)Ljava/lang/StringBuilder;
      72: aload_0
      73: getfield      #4                  // Field name:Ljava/lang/String;
      76: invokevirtual #19                 // Method java/lang/StringBuilder.append:(Ljava/lang/String;)Ljava/lang/StringBuilder;
      79: invokevirtual #20                 // Method java/lang/StringBuilder.toString:()Ljava/lang/String;
      82: aload_3
      83: getstatic     #21                 // Field uk/gov/gchq/gaffer/core/exception/Status.BAD_REQUEST:Luk/gov/gchq/gaffer/core/exception/Status;
      86: invokespecial #22                 // Method uk/gov/gchq/gaffer/core/exception/GafferRuntimeException."<init>":(Ljava/lang/String;Ljava/lang/Throwable;Luk/gov/gchq/gaffer/core/exception/Status;)V
      89: athrow
      90: aload_0
      91: aload_1
      92: aload_0
      93: getfield      #12                 // Field exampleJson:Luk/gov/gchq/gaffer/operation/Operation;
      96: invokestatic  #23                 // Method uk/gov/gchq/gaffer/rest/service/v2/OperationServiceV2.access$400:(Luk/gov/gchq/gaffer/rest/service/v2/OperationServiceV2;Luk/gov/gchq/gaffer/operation/Operation;)Ljava/lang/String;
      99: putfield      #24                 // Field outputClassName:Ljava/lang/String;
     102: return
    Exception table:
       from    to  target type
          43    52    55   Class java/lang/IllegalAccessException
          43    52    55   Class java/lang/InstantiationException

  public java.lang.String getName();
    Code:
       0: aload_0
       1: getfield      #4                  // Field name:Ljava/lang/String;
       4: areturn

  public java.lang.String getSummary();
    Code:
       0: aload_0
       1: getfield      #6                  // Field summary:Ljava/lang/String;
       4: areturn

  public java.util.List<uk.gov.gchq.gaffer.rest.service.v2.OperationServiceV2$OperationField> getFields();
    Code:
       0: aload_0
       1: getfield      #8                  // Field fields:Ljava/util/List;
       4: areturn

  public java.util.Set<java.lang.Class<? extends uk.gov.gchq.gaffer.operation.Operation>> getNext();
    Code:
       0: aload_0
       1: getfield      #10                 // Field next:Ljava/util/Set;
       4: areturn

  public uk.gov.gchq.gaffer.operation.Operation getExampleJson();
    Code:
       0: aload_0
       1: getfield      #12                 // Field exampleJson:Luk/gov/gchq/gaffer/operation/Operation;
       4: areturn

  public java.lang.String getOutputClassName();
    Code:
       0: aload_0
       1: getfield      #24                 // Field outputClassName:Ljava/lang/String;
       4: areturn

  public boolean equals(java.lang.Object);
    Code:
       0: aload_0
       1: aload_1
       2: if_acmpne     7
       5: iconst_1
       6: ireturn
       7: aload_1
       8: ifnull        22
      11: aload_0
      12: invokevirtual #25                 // Method java/lang/Object.getClass:()Ljava/lang/Class;
      15: aload_1
      16: invokevirtual #25                 // Method java/lang/Object.getClass:()Ljava/lang/Class;
      19: if_acmpeq     24
      22: iconst_0
      23: ireturn
      24: aload_1
      25: checkcast     #26                 // class uk/gov/gchq/gaffer/rest/service/v2/OperationServiceV2$OperationDetail
      28: astore_2
      29: new           #27                 // class org/apache/commons/lang3/builder/EqualsBuilder
      32: dup
      33: invokespecial #28                 // Method org/apache/commons/lang3/builder/EqualsBuilder."<init>":()V
      36: aload_0
      37: getfield      #4                  // Field name:Ljava/lang/String;
      40: aload_2
      41: getfield      #4                  // Field name:Ljava/lang/String;
      44: invokevirtual #29                 // Method org/apache/commons/lang3/builder/EqualsBuilder.append:(Ljava/lang/Object;Ljava/lang/Object;)Lorg/apache/commons/lang3/builder/EqualsBuilder;
      47: aload_0
      48: getfield      #6                  // Field summary:Ljava/lang/String;
      51: aload_2
      52: getfield      #6                  // Field summary:Ljava/lang/String;
      55: invokevirtual #29                 // Method org/apache/commons/lang3/builder/EqualsBuilder.append:(Ljava/lang/Object;Ljava/lang/Object;)Lorg/apache/commons/lang3/builder/EqualsBuilder;
      58: aload_0
      59: getfield      #8                  // Field fields:Ljava/util/List;
      62: aload_2
      63: getfield      #8                  // Field fields:Ljava/util/List;
      66: invokevirtual #29                 // Method org/apache/commons/lang3/builder/EqualsBuilder.append:(Ljava/lang/Object;Ljava/lang/Object;)Lorg/apache/commons/lang3/builder/EqualsBuilder;
      69: aload_0
      70: getfield      #10                 // Field next:Ljava/util/Set;
      73: aload_2
      74: getfield      #10                 // Field next:Ljava/util/Set;
      77: invokevirtual #29                 // Method org/apache/commons/lang3/builder/EqualsBuilder.append:(Ljava/lang/Object;Ljava/lang/Object;)Lorg/apache/commons/lang3/builder/EqualsBuilder;
      80: aload_0
      81: getfield      #12                 // Field exampleJson:Luk/gov/gchq/gaffer/operation/Operation;
      84: aload_2
      85: getfield      #12                 // Field exampleJson:Luk/gov/gchq/gaffer/operation/Operation;
      88: invokevirtual #29                 // Method org/apache/commons/lang3/builder/EqualsBuilder.append:(Ljava/lang/Object;Ljava/lang/Object;)Lorg/apache/commons/lang3/builder/EqualsBuilder;
      91: invokevirtual #30                 // Method org/apache/commons/lang3/builder/EqualsBuilder.isEquals:()Z
      94: ireturn

  public int hashCode();
    Code:
       0: new           #31                 // class org/apache/commons/lang3/builder/HashCodeBuilder
       3: dup
       4: bipush        17
       6: bipush        37
       8: invokespecial #32                 // Method org/apache/commons/lang3/builder/HashCodeBuilder."<init>":(II)V
      11: aload_0
      12: getfield      #4                  // Field name:Ljava/lang/String;
      15: invokevirtual #33                 // Method org/apache/commons/lang3/builder/HashCodeBuilder.append:(Ljava/lang/Object;)Lorg/apache/commons/lang3/builder/HashCodeBuilder;
      18: aload_0
      19: getfield      #6                  // Field summary:Ljava/lang/String;
      22: invokevirtual #33                 // Method org/apache/commons/lang3/builder/HashCodeBuilder.append:(Ljava/lang/Object;)Lorg/apache/commons/lang3/builder/HashCodeBuilder;
      25: aload_0
      26: getfield      #8                  // Field fields:Ljava/util/List;
      29: invokevirtual #33                 // Method org/apache/commons/lang3/builder/HashCodeBuilder.append:(Ljava/lang/Object;)Lorg/apache/commons/lang3/builder/HashCodeBuilder;
      32: aload_0
      33: getfield      #10                 // Field next:Ljava/util/Set;
      36: invokevirtual #33                 // Method org/apache/commons/lang3/builder/HashCodeBuilder.append:(Ljava/lang/Object;)Lorg/apache/commons/lang3/builder/HashCodeBuilder;
      39: aload_0
      40: getfield      #12                 // Field exampleJson:Luk/gov/gchq/gaffer/operation/Operation;
      43: invokevirtual #33                 // Method org/apache/commons/lang3/builder/HashCodeBuilder.append:(Ljava/lang/Object;)Lorg/apache/commons/lang3/builder/HashCodeBuilder;
      46: invokevirtual #34                 // Method org/apache/commons/lang3/builder/HashCodeBuilder.toHashCode:()I
      49: ireturn

  public java.lang.String toString();
    Code:
       0: new           #35                 // class uk/gov/gchq/gaffer/commonutil/ToStringBuilder
       3: dup
       4: aload_0
       5: invokespecial #36                 // Method uk/gov/gchq/gaffer/commonutil/ToStringBuilder."<init>":(Ljava/lang/Object;)V
       8: ldc           #37                 // String name
      10: aload_0
      11: getfield      #4                  // Field name:Ljava/lang/String;
      14: invokevirtual #38                 // Method uk/gov/gchq/gaffer/commonutil/ToStringBuilder.append:(Ljava/lang/String;Ljava/lang/Object;)Lorg/apache/commons/lang3/builder/ToStringBuilder;
      17: ldc           #39                 // String summary
      19: aload_0
      20: getfield      #6                  // Field summary:Ljava/lang/String;
      23: invokevirtual #40                 // Method org/apache/commons/lang3/builder/ToStringBuilder.append:(Ljava/lang/String;Ljava/lang/Object;)Lorg/apache/commons/lang3/builder/ToStringBuilder;
      26: ldc           #41                 // String fields
      28: aload_0
      29: getfield      #8                  // Field fields:Ljava/util/List;
      32: invokevirtual #40                 // Method org/apache/commons/lang3/builder/ToStringBuilder.append:(Ljava/lang/String;Ljava/lang/Object;)Lorg/apache/commons/lang3/builder/ToStringBuilder;
      35: ldc           #42                 // String next
      37: aload_0
      38: getfield      #10                 // Field next:Ljava/util/Set;
      41: invokevirtual #40                 // Method org/apache/commons/lang3/builder/ToStringBuilder.append:(Ljava/lang/String;Ljava/lang/Object;)Lorg/apache/commons/lang3/builder/ToStringBuilder;
      44: ldc           #43                 // String exampleJson
      46: aload_0
      47: getfield      #12                 // Field exampleJson:Luk/gov/gchq/gaffer/operation/Operation;
      50: invokevirtual #40                 // Method org/apache/commons/lang3/builder/ToStringBuilder.append:(Ljava/lang/String;Ljava/lang/Object;)Lorg/apache/commons/lang3/builder/ToStringBuilder;
      53: invokevirtual #44                 // Method org/apache/commons/lang3/builder/ToStringBuilder.toString:()Ljava/lang/String;
      56: areturn
}
