Compiled from "FunctionStatsImpl.java"
public class org.apache.pulsar.common.policies.data.FunctionStatsImpl implements org.apache.pulsar.common.policies.data.FunctionStats {
  public long receivedTotal;

  public long processedSuccessfullyTotal;

  public long systemExceptionsTotal;

  public long userExceptionsTotal;

  public java.lang.Double avgProcessLatency;

  public org.apache.pulsar.common.policies.data.FunctionInstanceStatsDataBaseImpl oneMin;

  public java.lang.Long lastInvocation;

  public java.util.List<org.apache.pulsar.common.policies.data.FunctionInstanceStatsImpl> instances;

  public void addInstance(org.apache.pulsar.common.policies.data.FunctionInstanceStatsImpl);
    Code:
       0: aload_0
       1: getfield      #1                  // Field instances:Ljava/util/List;
       4: aload_1
       5: invokeinterface #2,  2            // InterfaceMethod java/util/List.add:(Ljava/lang/Object;)Z
      10: pop
      11: return

  public org.apache.pulsar.common.policies.data.FunctionStatsImpl calculateOverall();
    Code:
       0: iconst_0
       1: istore_1
       2: iconst_0
       3: istore_2
       4: aload_0
       5: getfield      #1                  // Field instances:Ljava/util/List;
       8: invokeinterface #3,  1            // InterfaceMethod java/util/List.iterator:()Ljava/util/Iterator;
      13: astore_3
      14: aload_3
      15: invokeinterface #4,  1            // InterfaceMethod java/util/Iterator.hasNext:()Z
      20: ifeq          356
      23: aload_3
      24: invokeinterface #5,  1            // InterfaceMethod java/util/Iterator.next:()Ljava/lang/Object;
      29: checkcast     #6                  // class org/apache/pulsar/common/policies/data/FunctionInstanceStats
      32: astore        4
      34: aload         4
      36: invokeinterface #7,  1            // InterfaceMethod org/apache/pulsar/common/policies/data/FunctionInstanceStats.getMetrics:()Lorg/apache/pulsar/common/policies/data/FunctionInstanceStatsData;
      41: checkcast     #8                  // class org/apache/pulsar/common/policies/data/FunctionInstanceStatsDataImpl
      44: astore        5
      46: aload_0
      47: dup
      48: getfield      #9                  // Field receivedTotal:J
      51: aload         5
      53: getfield      #10                 // Field org/apache/pulsar/common/policies/data/FunctionInstanceStatsDataImpl.receivedTotal:J
      56: ladd
      57: putfield      #9                  // Field receivedTotal:J
      60: aload_0
      61: dup
      62: getfield      #11                 // Field processedSuccessfullyTotal:J
      65: aload         5
      67: getfield      #12                 // Field org/apache/pulsar/common/policies/data/FunctionInstanceStatsDataImpl.processedSuccessfullyTotal:J
      70: ladd
      71: putfield      #11                 // Field processedSuccessfullyTotal:J
      74: aload_0
      75: dup
      76: getfield      #13                 // Field systemExceptionsTotal:J
      79: aload         5
      81: getfield      #14                 // Field org/apache/pulsar/common/policies/data/FunctionInstanceStatsDataImpl.systemExceptionsTotal:J
      84: ladd
      85: putfield      #13                 // Field systemExceptionsTotal:J
      88: aload_0
      89: dup
      90: getfield      #15                 // Field userExceptionsTotal:J
      93: aload         5
      95: getfield      #16                 // Field org/apache/pulsar/common/policies/data/FunctionInstanceStatsDataImpl.userExceptionsTotal:J
      98: ladd
      99: putfield      #15                 // Field userExceptionsTotal:J
     102: aload         5
     104: getfield      #17                 // Field org/apache/pulsar/common/policies/data/FunctionInstanceStatsDataImpl.avgProcessLatency:Ljava/lang/Double;
     107: ifnull        151
     110: aload_0
     111: getfield      #18                 // Field avgProcessLatency:Ljava/lang/Double;
     114: ifnonnull     125
     117: aload_0
     118: dconst_0
     119: invokestatic  #19                 // Method java/lang/Double.valueOf:(D)Ljava/lang/Double;
     122: putfield      #18                 // Field avgProcessLatency:Ljava/lang/Double;
     125: aload_0
     126: aload_0
     127: getfield      #18                 // Field avgProcessLatency:Ljava/lang/Double;
     130: invokevirtual #20                 // Method java/lang/Double.doubleValue:()D
     133: aload         5
     135: getfield      #17                 // Field org/apache/pulsar/common/policies/data/FunctionInstanceStatsDataImpl.avgProcessLatency:Ljava/lang/Double;
     138: invokevirtual #20                 // Method java/lang/Double.doubleValue:()D
     141: dadd
     142: invokestatic  #19                 // Method java/lang/Double.valueOf:(D)Ljava/lang/Double;
     145: putfield      #18                 // Field avgProcessLatency:Ljava/lang/Double;
     148: iinc          1, 1
     151: aload_0
     152: getfield      #21                 // Field oneMin:Lorg/apache/pulsar/common/policies/data/FunctionInstanceStatsDataBaseImpl;
     155: aload_0
     156: getfield      #21                 // Field oneMin:Lorg/apache/pulsar/common/policies/data/FunctionInstanceStatsDataBaseImpl;
     159: invokevirtual #22                 // Method org/apache/pulsar/common/policies/data/FunctionInstanceStatsDataBaseImpl.getReceivedTotal:()J
     162: aload         5
     164: getfield      #23                 // Field org/apache/pulsar/common/policies/data/FunctionInstanceStatsDataImpl.oneMin:Lorg/apache/pulsar/common/policies/data/FunctionInstanceStatsDataBaseImpl;
     167: invokevirtual #22                 // Method org/apache/pulsar/common/policies/data/FunctionInstanceStatsDataBaseImpl.getReceivedTotal:()J
     170: ladd
     171: invokevirtual #24                 // Method org/apache/pulsar/common/policies/data/FunctionInstanceStatsDataBaseImpl.setReceivedTotal:(J)V
     174: aload_0
     175: getfield      #21                 // Field oneMin:Lorg/apache/pulsar/common/policies/data/FunctionInstanceStatsDataBaseImpl;
     178: aload_0
     179: getfield      #21                 // Field oneMin:Lorg/apache/pulsar/common/policies/data/FunctionInstanceStatsDataBaseImpl;
     182: invokevirtual #25                 // Method org/apache/pulsar/common/policies/data/FunctionInstanceStatsDataBaseImpl.getProcessedSuccessfullyTotal:()J
     185: aload         5
     187: getfield      #23                 // Field org/apache/pulsar/common/policies/data/FunctionInstanceStatsDataImpl.oneMin:Lorg/apache/pulsar/common/policies/data/FunctionInstanceStatsDataBaseImpl;
     190: invokevirtual #25                 // Method org/apache/pulsar/common/policies/data/FunctionInstanceStatsDataBaseImpl.getProcessedSuccessfullyTotal:()J
     193: ladd
     194: invokevirtual #26                 // Method org/apache/pulsar/common/policies/data/FunctionInstanceStatsDataBaseImpl.setProcessedSuccessfullyTotal:(J)V
     197: aload_0
     198: getfield      #21                 // Field oneMin:Lorg/apache/pulsar/common/policies/data/FunctionInstanceStatsDataBaseImpl;
     201: aload_0
     202: getfield      #21                 // Field oneMin:Lorg/apache/pulsar/common/policies/data/FunctionInstanceStatsDataBaseImpl;
     205: invokevirtual #27                 // Method org/apache/pulsar/common/policies/data/FunctionInstanceStatsDataBaseImpl.getSystemExceptionsTotal:()J
     208: aload         5
     210: getfield      #23                 // Field org/apache/pulsar/common/policies/data/FunctionInstanceStatsDataImpl.oneMin:Lorg/apache/pulsar/common/policies/data/FunctionInstanceStatsDataBaseImpl;
     213: invokevirtual #27                 // Method org/apache/pulsar/common/policies/data/FunctionInstanceStatsDataBaseImpl.getSystemExceptionsTotal:()J
     216: ladd
     217: invokevirtual #28                 // Method org/apache/pulsar/common/policies/data/FunctionInstanceStatsDataBaseImpl.setSystemExceptionsTotal:(J)V
     220: aload_0
     221: getfield      #21                 // Field oneMin:Lorg/apache/pulsar/common/policies/data/FunctionInstanceStatsDataBaseImpl;
     224: aload_0
     225: getfield      #21                 // Field oneMin:Lorg/apache/pulsar/common/policies/data/FunctionInstanceStatsDataBaseImpl;
     228: invokevirtual #29                 // Method org/apache/pulsar/common/policies/data/FunctionInstanceStatsDataBaseImpl.getUserExceptionsTotal:()J
     231: aload         5
     233: getfield      #23                 // Field org/apache/pulsar/common/policies/data/FunctionInstanceStatsDataImpl.oneMin:Lorg/apache/pulsar/common/policies/data/FunctionInstanceStatsDataBaseImpl;
     236: invokevirtual #29                 // Method org/apache/pulsar/common/policies/data/FunctionInstanceStatsDataBaseImpl.getUserExceptionsTotal:()J
     239: ladd
     240: invokevirtual #30                 // Method org/apache/pulsar/common/policies/data/FunctionInstanceStatsDataBaseImpl.setUserExceptionsTotal:(J)V
     243: aload         5
     245: getfield      #23                 // Field org/apache/pulsar/common/policies/data/FunctionInstanceStatsDataImpl.oneMin:Lorg/apache/pulsar/common/policies/data/FunctionInstanceStatsDataBaseImpl;
     248: invokevirtual #31                 // Method org/apache/pulsar/common/policies/data/FunctionInstanceStatsDataBaseImpl.getAvgProcessLatency:()Ljava/lang/Double;
     251: ifnull        310
     254: aload_0
     255: getfield      #21                 // Field oneMin:Lorg/apache/pulsar/common/policies/data/FunctionInstanceStatsDataBaseImpl;
     258: invokevirtual #31                 // Method org/apache/pulsar/common/policies/data/FunctionInstanceStatsDataBaseImpl.getAvgProcessLatency:()Ljava/lang/Double;
     261: ifnonnull     275
     264: aload_0
     265: getfield      #21                 // Field oneMin:Lorg/apache/pulsar/common/policies/data/FunctionInstanceStatsDataBaseImpl;
     268: dconst_0
     269: invokestatic  #19                 // Method java/lang/Double.valueOf:(D)Ljava/lang/Double;
     272: invokevirtual #32                 // Method org/apache/pulsar/common/policies/data/FunctionInstanceStatsDataBaseImpl.setAvgProcessLatency:(Ljava/lang/Double;)V
     275: aload_0
     276: getfield      #21                 // Field oneMin:Lorg/apache/pulsar/common/policies/data/FunctionInstanceStatsDataBaseImpl;
     279: aload_0
     280: getfield      #21                 // Field oneMin:Lorg/apache/pulsar/common/policies/data/FunctionInstanceStatsDataBaseImpl;
     283: invokevirtual #31                 // Method org/apache/pulsar/common/policies/data/FunctionInstanceStatsDataBaseImpl.getAvgProcessLatency:()Ljava/lang/Double;
     286: invokevirtual #20                 // Method java/lang/Double.doubleValue:()D
     289: aload         5
     291: getfield      #23                 // Field org/apache/pulsar/common/policies/data/FunctionInstanceStatsDataImpl.oneMin:Lorg/apache/pulsar/common/policies/data/FunctionInstanceStatsDataBaseImpl;
     294: invokevirtual #31                 // Method org/apache/pulsar/common/policies/data/FunctionInstanceStatsDataBaseImpl.getAvgProcessLatency:()Ljava/lang/Double;
     297: invokevirtual #20                 // Method java/lang/Double.doubleValue:()D
     300: dadd
     301: invokestatic  #19                 // Method java/lang/Double.valueOf:(D)Ljava/lang/Double;
     304: invokevirtual #32                 // Method org/apache/pulsar/common/policies/data/FunctionInstanceStatsDataBaseImpl.setAvgProcessLatency:(Ljava/lang/Double;)V
     307: iinc          2, 1
     310: aload         5
     312: getfield      #33                 // Field org/apache/pulsar/common/policies/data/FunctionInstanceStatsDataImpl.lastInvocation:Ljava/lang/Long;
     315: ifnull        353
     318: aload_0
     319: getfield      #34                 // Field lastInvocation:Ljava/lang/Long;
     322: ifnull        344
     325: aload         5
     327: getfield      #33                 // Field org/apache/pulsar/common/policies/data/FunctionInstanceStatsDataImpl.lastInvocation:Ljava/lang/Long;
     330: invokevirtual #35                 // Method java/lang/Long.longValue:()J
     333: aload_0
     334: getfield      #34                 // Field lastInvocation:Ljava/lang/Long;
     337: invokevirtual #35                 // Method java/lang/Long.longValue:()J
     340: lcmp
     341: ifle          353
     344: aload_0
     345: aload         5
     347: getfield      #33                 // Field org/apache/pulsar/common/policies/data/FunctionInstanceStatsDataImpl.lastInvocation:Ljava/lang/Long;
     350: putfield      #34                 // Field lastInvocation:Ljava/lang/Long;
     353: goto          14
     356: iload_1
     357: ifle          380
     360: aload_0
     361: aload_0
     362: getfield      #18                 // Field avgProcessLatency:Ljava/lang/Double;
     365: invokevirtual #20                 // Method java/lang/Double.doubleValue:()D
     368: iload_1
     369: i2d
     370: ddiv
     371: invokestatic  #19                 // Method java/lang/Double.valueOf:(D)Ljava/lang/Double;
     374: putfield      #18                 // Field avgProcessLatency:Ljava/lang/Double;
     377: goto          385
     380: aload_0
     381: aconst_null
     382: putfield      #18                 // Field avgProcessLatency:Ljava/lang/Double;
     385: iload_2
     386: ifle          415
     389: aload_0
     390: getfield      #21                 // Field oneMin:Lorg/apache/pulsar/common/policies/data/FunctionInstanceStatsDataBaseImpl;
     393: aload_0
     394: getfield      #21                 // Field oneMin:Lorg/apache/pulsar/common/policies/data/FunctionInstanceStatsDataBaseImpl;
     397: invokevirtual #31                 // Method org/apache/pulsar/common/policies/data/FunctionInstanceStatsDataBaseImpl.getAvgProcessLatency:()Ljava/lang/Double;
     400: invokevirtual #20                 // Method java/lang/Double.doubleValue:()D
     403: iload_2
     404: i2d
     405: ddiv
     406: invokestatic  #19                 // Method java/lang/Double.valueOf:(D)Ljava/lang/Double;
     409: invokevirtual #32                 // Method org/apache/pulsar/common/policies/data/FunctionInstanceStatsDataBaseImpl.setAvgProcessLatency:(Ljava/lang/Double;)V
     412: goto          423
     415: aload_0
     416: getfield      #21                 // Field oneMin:Lorg/apache/pulsar/common/policies/data/FunctionInstanceStatsDataBaseImpl;
     419: aconst_null
     420: invokevirtual #32                 // Method org/apache/pulsar/common/policies/data/FunctionInstanceStatsDataBaseImpl.setAvgProcessLatency:(Ljava/lang/Double;)V
     423: aload_0
     424: areturn

  public static org.apache.pulsar.common.policies.data.FunctionStatsImpl decode(java.lang.String) throws java.io.IOException;
    Code:
       0: invokestatic  #36                 // Method org/apache/pulsar/common/util/ObjectMapperFactory.getThreadLocal:()Lcom/fasterxml/jackson/databind/ObjectMapper;
       3: aload_0
       4: ldc           #37                 // class org/apache/pulsar/common/policies/data/FunctionStatsImpl
       6: invokevirtual #38                 // Method com/fasterxml/jackson/databind/ObjectMapper.readValue:(Ljava/lang/String;Ljava/lang/Class;)Ljava/lang/Object;
       9: checkcast     #37                 // class org/apache/pulsar/common/policies/data/FunctionStatsImpl
      12: areturn

  public org.apache.pulsar.common.policies.data.FunctionStatsImpl();
    Code:
       0: aload_0
       1: invokespecial #39                 // Method java/lang/Object."<init>":()V
       4: aload_0
       5: new           #40                 // class org/apache/pulsar/common/policies/data/FunctionInstanceStatsDataBaseImpl
       8: dup
       9: invokespecial #41                 // Method org/apache/pulsar/common/policies/data/FunctionInstanceStatsDataBaseImpl."<init>":()V
      12: putfield      #21                 // Field oneMin:Lorg/apache/pulsar/common/policies/data/FunctionInstanceStatsDataBaseImpl;
      15: aload_0
      16: new           #42                 // class java/util/LinkedList
      19: dup
      20: invokespecial #43                 // Method java/util/LinkedList."<init>":()V
      23: putfield      #1                  // Field instances:Ljava/util/List;
      26: return

  public long getReceivedTotal();
    Code:
       0: aload_0
       1: getfield      #9                  // Field receivedTotal:J
       4: lreturn

  public long getProcessedSuccessfullyTotal();
    Code:
       0: aload_0
       1: getfield      #11                 // Field processedSuccessfullyTotal:J
       4: lreturn

  public long getSystemExceptionsTotal();
    Code:
       0: aload_0
       1: getfield      #13                 // Field systemExceptionsTotal:J
       4: lreturn

  public long getUserExceptionsTotal();
    Code:
       0: aload_0
       1: getfield      #15                 // Field userExceptionsTotal:J
       4: lreturn

  public java.lang.Double getAvgProcessLatency();
    Code:
       0: aload_0
       1: getfield      #18                 // Field avgProcessLatency:Ljava/lang/Double;
       4: areturn

  public org.apache.pulsar.common.policies.data.FunctionInstanceStatsDataBaseImpl getOneMin();
    Code:
       0: aload_0
       1: getfield      #21                 // Field oneMin:Lorg/apache/pulsar/common/policies/data/FunctionInstanceStatsDataBaseImpl;
       4: areturn

  public java.lang.Long getLastInvocation();
    Code:
       0: aload_0
       1: getfield      #34                 // Field lastInvocation:Ljava/lang/Long;
       4: areturn

  public java.util.List<org.apache.pulsar.common.policies.data.FunctionInstanceStatsImpl> getInstances();
    Code:
       0: aload_0
       1: getfield      #1                  // Field instances:Ljava/util/List;
       4: areturn

  public void setReceivedTotal(long);
    Code:
       0: aload_0
       1: lload_1
       2: putfield      #9                  // Field receivedTotal:J
       5: return

  public void setProcessedSuccessfullyTotal(long);
    Code:
       0: aload_0
       1: lload_1
       2: putfield      #11                 // Field processedSuccessfullyTotal:J
       5: return

  public void setSystemExceptionsTotal(long);
    Code:
       0: aload_0
       1: lload_1
       2: putfield      #13                 // Field systemExceptionsTotal:J
       5: return

  public void setUserExceptionsTotal(long);
    Code:
       0: aload_0
       1: lload_1
       2: putfield      #15                 // Field userExceptionsTotal:J
       5: return

  public void setAvgProcessLatency(java.lang.Double);
    Code:
       0: aload_0
       1: aload_1
       2: putfield      #18                 // Field avgProcessLatency:Ljava/lang/Double;
       5: return

  public void setOneMin(org.apache.pulsar.common.policies.data.FunctionInstanceStatsDataBaseImpl);
    Code:
       0: aload_0
       1: aload_1
       2: putfield      #21                 // Field oneMin:Lorg/apache/pulsar/common/policies/data/FunctionInstanceStatsDataBaseImpl;
       5: return

  public void setLastInvocation(java.lang.Long);
    Code:
       0: aload_0
       1: aload_1
       2: putfield      #34                 // Field lastInvocation:Ljava/lang/Long;
       5: return

  public void setInstances(java.util.List<org.apache.pulsar.common.policies.data.FunctionInstanceStatsImpl>);
    Code:
       0: aload_0
       1: aload_1
       2: putfield      #1                  // Field instances:Ljava/util/List;
       5: return

  public boolean equals(java.lang.Object);
    Code:
       0: aload_1
       1: aload_0
       2: if_acmpne     7
       5: iconst_1
       6: ireturn
       7: aload_1
       8: instanceof    #37                 // class org/apache/pulsar/common/policies/data/FunctionStatsImpl
      11: ifne          16
      14: iconst_0
      15: ireturn
      16: aload_1
      17: checkcast     #37                 // class org/apache/pulsar/common/policies/data/FunctionStatsImpl
      20: astore_2
      21: aload_2
      22: aload_0
      23: invokevirtual #44                 // Method canEqual:(Ljava/lang/Object;)Z
      26: ifne          31
      29: iconst_0
      30: ireturn
      31: aload_0
      32: invokevirtual #45                 // Method getReceivedTotal:()J
      35: aload_2
      36: invokevirtual #45                 // Method getReceivedTotal:()J
      39: lcmp
      40: ifeq          45
      43: iconst_0
      44: ireturn
      45: aload_0
      46: invokevirtual #46                 // Method getProcessedSuccessfullyTotal:()J
      49: aload_2
      50: invokevirtual #46                 // Method getProcessedSuccessfullyTotal:()J
      53: lcmp
      54: ifeq          59
      57: iconst_0
      58: ireturn
      59: aload_0
      60: invokevirtual #47                 // Method getSystemExceptionsTotal:()J
      63: aload_2
      64: invokevirtual #47                 // Method getSystemExceptionsTotal:()J
      67: lcmp
      68: ifeq          73
      71: iconst_0
      72: ireturn
      73: aload_0
      74: invokevirtual #48                 // Method getUserExceptionsTotal:()J
      77: aload_2
      78: invokevirtual #48                 // Method getUserExceptionsTotal:()J
      81: lcmp
      82: ifeq          87
      85: iconst_0
      86: ireturn
      87: aload_0
      88: invokevirtual #49                 // Method getAvgProcessLatency:()Ljava/lang/Double;
      91: astore_3
      92: aload_2
      93: invokevirtual #49                 // Method getAvgProcessLatency:()Ljava/lang/Double;
      96: astore        4
      98: aload_3
      99: ifnonnull     110
     102: aload         4
     104: ifnull        121
     107: goto          119
     110: aload_3
     111: aload         4
     113: invokevirtual #50                 // Method java/lang/Object.equals:(Ljava/lang/Object;)Z
     116: ifne          121
     119: iconst_0
     120: ireturn
     121: aload_0
     122: invokevirtual #51                 // Method getLastInvocation:()Ljava/lang/Long;
     125: astore        5
     127: aload_2
     128: invokevirtual #51                 // Method getLastInvocation:()Ljava/lang/Long;
     131: astore        6
     133: aload         5
     135: ifnonnull     146
     138: aload         6
     140: ifnull        158
     143: goto          156
     146: aload         5
     148: aload         6
     150: invokevirtual #50                 // Method java/lang/Object.equals:(Ljava/lang/Object;)Z
     153: ifne          158
     156: iconst_0
     157: ireturn
     158: aload_0
     159: invokevirtual #52                 // Method getOneMin:()Lorg/apache/pulsar/common/policies/data/FunctionInstanceStatsDataBaseImpl;
     162: astore        7
     164: aload_2
     165: invokevirtual #52                 // Method getOneMin:()Lorg/apache/pulsar/common/policies/data/FunctionInstanceStatsDataBaseImpl;
     168: astore        8
     170: aload         7
     172: ifnonnull     183
     175: aload         8
     177: ifnull        195
     180: goto          193
     183: aload         7
     185: aload         8
     187: invokevirtual #50                 // Method java/lang/Object.equals:(Ljava/lang/Object;)Z
     190: ifne          195
     193: iconst_0
     194: ireturn
     195: aload_0
     196: invokevirtual #53                 // Method getInstances:()Ljava/util/List;
     199: astore        9
     201: aload_2
     202: invokevirtual #53                 // Method getInstances:()Ljava/util/List;
     205: astore        10
     207: aload         9
     209: ifnonnull     220
     212: aload         10
     214: ifnull        232
     217: goto          230
     220: aload         9
     222: aload         10
     224: invokevirtual #50                 // Method java/lang/Object.equals:(Ljava/lang/Object;)Z
     227: ifne          232
     230: iconst_0
     231: ireturn
     232: iconst_1
     233: ireturn

  protected boolean canEqual(java.lang.Object);
    Code:
       0: aload_1
       1: instanceof    #37                 // class org/apache/pulsar/common/policies/data/FunctionStatsImpl
       4: ireturn

  public int hashCode();
    Code:
       0: bipush        59
       2: istore_1
       3: iconst_1
       4: istore_2
       5: aload_0
       6: invokevirtual #45                 // Method getReceivedTotal:()J
       9: lstore_3
      10: iload_2
      11: bipush        59
      13: imul
      14: lload_3
      15: bipush        32
      17: lushr
      18: lload_3
      19: lxor
      20: l2i
      21: iadd
      22: istore_2
      23: aload_0
      24: invokevirtual #46                 // Method getProcessedSuccessfullyTotal:()J
      27: lstore        5
      29: iload_2
      30: bipush        59
      32: imul
      33: lload         5
      35: bipush        32
      37: lushr
      38: lload         5
      40: lxor
      41: l2i
      42: iadd
      43: istore_2
      44: aload_0
      45: invokevirtual #47                 // Method getSystemExceptionsTotal:()J
      48: lstore        7
      50: iload_2
      51: bipush        59
      53: imul
      54: lload         7
      56: bipush        32
      58: lushr
      59: lload         7
      61: lxor
      62: l2i
      63: iadd
      64: istore_2
      65: aload_0
      66: invokevirtual #48                 // Method getUserExceptionsTotal:()J
      69: lstore        9
      71: iload_2
      72: bipush        59
      74: imul
      75: lload         9
      77: bipush        32
      79: lushr
      80: lload         9
      82: lxor
      83: l2i
      84: iadd
      85: istore_2
      86: aload_0
      87: invokevirtual #49                 // Method getAvgProcessLatency:()Ljava/lang/Double;
      90: astore        11
      92: iload_2
      93: bipush        59
      95: imul
      96: aload         11
      98: ifnonnull     106
     101: bipush        43
     103: goto          111
     106: aload         11
     108: invokevirtual #54                 // Method java/lang/Object.hashCode:()I
     111: iadd
     112: istore_2
     113: aload_0
     114: invokevirtual #51                 // Method getLastInvocation:()Ljava/lang/Long;
     117: astore        12
     119: iload_2
     120: bipush        59
     122: imul
     123: aload         12
     125: ifnonnull     133
     128: bipush        43
     130: goto          138
     133: aload         12
     135: invokevirtual #54                 // Method java/lang/Object.hashCode:()I
     138: iadd
     139: istore_2
     140: aload_0
     141: invokevirtual #52                 // Method getOneMin:()Lorg/apache/pulsar/common/policies/data/FunctionInstanceStatsDataBaseImpl;
     144: astore        13
     146: iload_2
     147: bipush        59
     149: imul
     150: aload         13
     152: ifnonnull     160
     155: bipush        43
     157: goto          165
     160: aload         13
     162: invokevirtual #54                 // Method java/lang/Object.hashCode:()I
     165: iadd
     166: istore_2
     167: aload_0
     168: invokevirtual #53                 // Method getInstances:()Ljava/util/List;
     171: astore        14
     173: iload_2
     174: bipush        59
     176: imul
     177: aload         14
     179: ifnonnull     187
     182: bipush        43
     184: goto          192
     187: aload         14
     189: invokevirtual #54                 // Method java/lang/Object.hashCode:()I
     192: iadd
     193: istore_2
     194: iload_2
     195: ireturn

  public java.lang.String toString();
    Code:
       0: new           #55                 // class java/lang/StringBuilder
       3: dup
       4: invokespecial #56                 // Method java/lang/StringBuilder."<init>":()V
       7: ldc           #57                 // String FunctionStatsImpl(receivedTotal=
       9: invokevirtual #58                 // Method java/lang/StringBuilder.append:(Ljava/lang/String;)Ljava/lang/StringBuilder;
      12: aload_0
      13: invokevirtual #45                 // Method getReceivedTotal:()J
      16: invokevirtual #59                 // Method java/lang/StringBuilder.append:(J)Ljava/lang/StringBuilder;
      19: ldc           #60                 // String , processedSuccessfullyTotal=
      21: invokevirtual #58                 // Method java/lang/StringBuilder.append:(Ljava/lang/String;)Ljava/lang/StringBuilder;
      24: aload_0
      25: invokevirtual #46                 // Method getProcessedSuccessfullyTotal:()J
      28: invokevirtual #59                 // Method java/lang/StringBuilder.append:(J)Ljava/lang/StringBuilder;
      31: ldc           #61                 // String , systemExceptionsTotal=
      33: invokevirtual #58                 // Method java/lang/StringBuilder.append:(Ljava/lang/String;)Ljava/lang/StringBuilder;
      36: aload_0
      37: invokevirtual #47                 // Method getSystemExceptionsTotal:()J
      40: invokevirtual #59                 // Method java/lang/StringBuilder.append:(J)Ljava/lang/StringBuilder;
      43: ldc           #62                 // String , userExceptionsTotal=
      45: invokevirtual #58                 // Method java/lang/StringBuilder.append:(Ljava/lang/String;)Ljava/lang/StringBuilder;
      48: aload_0
      49: invokevirtual #48                 // Method getUserExceptionsTotal:()J
      52: invokevirtual #59                 // Method java/lang/StringBuilder.append:(J)Ljava/lang/StringBuilder;
      55: ldc           #63                 // String , avgProcessLatency=
      57: invokevirtual #58                 // Method java/lang/StringBuilder.append:(Ljava/lang/String;)Ljava/lang/StringBuilder;
      60: aload_0
      61: invokevirtual #49                 // Method getAvgProcessLatency:()Ljava/lang/Double;
      64: invokevirtual #64                 // Method java/lang/StringBuilder.append:(Ljava/lang/Object;)Ljava/lang/StringBuilder;
      67: ldc           #65                 // String , oneMin=
      69: invokevirtual #58                 // Method java/lang/StringBuilder.append:(Ljava/lang/String;)Ljava/lang/StringBuilder;
      72: aload_0
      73: invokevirtual #52                 // Method getOneMin:()Lorg/apache/pulsar/common/policies/data/FunctionInstanceStatsDataBaseImpl;
      76: invokevirtual #64                 // Method java/lang/StringBuilder.append:(Ljava/lang/Object;)Ljava/lang/StringBuilder;
      79: ldc           #66                 // String , lastInvocation=
      81: invokevirtual #58                 // Method java/lang/StringBuilder.append:(Ljava/lang/String;)Ljava/lang/StringBuilder;
      84: aload_0
      85: invokevirtual #51                 // Method getLastInvocation:()Ljava/lang/Long;
      88: invokevirtual #64                 // Method java/lang/StringBuilder.append:(Ljava/lang/Object;)Ljava/lang/StringBuilder;
      91: ldc           #67                 // String , instances=
      93: invokevirtual #58                 // Method java/lang/StringBuilder.append:(Ljava/lang/String;)Ljava/lang/StringBuilder;
      96: aload_0
      97: invokevirtual #53                 // Method getInstances:()Ljava/util/List;
     100: invokevirtual #64                 // Method java/lang/StringBuilder.append:(Ljava/lang/Object;)Ljava/lang/StringBuilder;
     103: ldc           #68                 // String )
     105: invokevirtual #58                 // Method java/lang/StringBuilder.append:(Ljava/lang/String;)Ljava/lang/StringBuilder;
     108: invokevirtual #69                 // Method java/lang/StringBuilder.toString:()Ljava/lang/String;
     111: areturn

  public org.apache.pulsar.common.policies.data.FunctionInstanceStatsDataBase getOneMin();
    Code:
       0: aload_0
       1: invokevirtual #52                 // Method getOneMin:()Lorg/apache/pulsar/common/policies/data/FunctionInstanceStatsDataBaseImpl;
       4: areturn

  public org.apache.pulsar.common.policies.data.FunctionStats calculateOverall();
    Code:
       0: aload_0
       1: invokevirtual #70                 // Method calculateOverall:()Lorg/apache/pulsar/common/policies/data/FunctionStatsImpl;
       4: areturn
}
