Compiled from "OffloadPoliciesImpl.java"
public class org.apache.pulsar.common.policies.data.OffloadPoliciesImpl implements java.io.Serializable,org.apache.pulsar.common.policies.data.OffloadPolicies {
  private static final org.slf4j.Logger log;

  private static final long serialVersionUID;

  public static final java.util.List<java.lang.reflect.Field> CONFIGURATION_FIELDS;

  public static final int DEFAULT_MAX_BLOCK_SIZE_IN_BYTES;

  public static final int DEFAULT_READ_BUFFER_SIZE_IN_BYTES;

  public static final int DEFAULT_OFFLOAD_MAX_THREADS;

  public static final int DEFAULT_OFFLOAD_MAX_PREFETCH_ROUNDS;

  public static final com.google.common.collect.ImmutableList<java.lang.String> DRIVER_NAMES;

  public static final java.lang.String DEFAULT_OFFLOADER_DIRECTORY;

  public static final java.lang.Long DEFAULT_OFFLOAD_THRESHOLD_IN_BYTES;

  public static final java.lang.Long DEFAULT_OFFLOAD_DELETION_LAG_IN_MILLIS;

  public static final java.lang.String OFFLOAD_THRESHOLD_NAME_IN_CONF_FILE;

  public static final java.lang.String DELETION_LAG_NAME_IN_CONF_FILE;

  public static final org.apache.pulsar.common.policies.data.OffloadedReadPriority DEFAULT_OFFLOADED_READ_PRIORITY;

  private java.lang.String offloadersDirectory;

  private java.lang.String managedLedgerOffloadDriver;

  private java.lang.Integer managedLedgerOffloadMaxThreads;

  private java.lang.Integer managedLedgerOffloadPrefetchRounds;

  private java.lang.Long managedLedgerOffloadThresholdInBytes;

  private java.lang.Long managedLedgerOffloadDeletionLagInMillis;

  private org.apache.pulsar.common.policies.data.OffloadedReadPriority managedLedgerOffloadedReadPriority;

  private java.lang.String s3ManagedLedgerOffloadRegion;

  private java.lang.String s3ManagedLedgerOffloadBucket;

  private java.lang.String s3ManagedLedgerOffloadServiceEndpoint;

  private java.lang.Integer s3ManagedLedgerOffloadMaxBlockSizeInBytes;

  private java.lang.Integer s3ManagedLedgerOffloadReadBufferSizeInBytes;

  private java.lang.String s3ManagedLedgerOffloadCredentialId;

  private java.lang.String s3ManagedLedgerOffloadCredentialSecret;

  private java.lang.String s3ManagedLedgerOffloadRole;

  private java.lang.String s3ManagedLedgerOffloadRoleSessionName;

  private java.lang.String gcsManagedLedgerOffloadRegion;

  private java.lang.String gcsManagedLedgerOffloadBucket;

  private java.lang.Integer gcsManagedLedgerOffloadMaxBlockSizeInBytes;

  private java.lang.Integer gcsManagedLedgerOffloadReadBufferSizeInBytes;

  private java.lang.String gcsManagedLedgerOffloadServiceAccountKeyFile;

  private java.lang.String fileSystemProfilePath;

  private java.lang.String fileSystemURI;

  private java.lang.String managedLedgerOffloadBucket;

  private java.lang.String managedLedgerOffloadRegion;

  private java.lang.String managedLedgerOffloadServiceEndpoint;

  private java.lang.Integer managedLedgerOffloadMaxBlockSizeInBytes;

  private java.lang.Integer managedLedgerOffloadReadBufferSizeInBytes;

  public static org.apache.pulsar.common.policies.data.OffloadPoliciesImpl create(java.lang.String, java.lang.String, java.lang.String, java.lang.String, java.lang.String, java.lang.String, java.lang.String, java.lang.String, java.lang.Integer, java.lang.Integer, java.lang.Long, java.lang.Long, org.apache.pulsar.common.policies.data.OffloadedReadPriority);
    Code:
       0: invokestatic  #29                 // Method builder:()Lorg/apache/pulsar/common/policies/data/OffloadPoliciesImpl$OffloadPoliciesImplBuilder;
       3: aload_0
       4: invokevirtual #30                 // Method org/apache/pulsar/common/policies/data/OffloadPoliciesImpl$OffloadPoliciesImplBuilder.managedLedgerOffloadDriver:(Ljava/lang/String;)Lorg/apache/pulsar/common/policies/data/OffloadPoliciesImpl$OffloadPoliciesImplBuilder;
       7: aload         10
       9: invokevirtual #31                 // Method org/apache/pulsar/common/policies/data/OffloadPoliciesImpl$OffloadPoliciesImplBuilder.managedLedgerOffloadThresholdInBytes:(Ljava/lang/Long;)Lorg/apache/pulsar/common/policies/data/OffloadPoliciesImpl$OffloadPoliciesImplBuilder;
      12: aload         11
      14: invokevirtual #32                 // Method org/apache/pulsar/common/policies/data/OffloadPoliciesImpl$OffloadPoliciesImplBuilder.managedLedgerOffloadDeletionLagInMillis:(Ljava/lang/Long;)Lorg/apache/pulsar/common/policies/data/OffloadPoliciesImpl$OffloadPoliciesImplBuilder;
      17: aload_2
      18: invokevirtual #33                 // Method org/apache/pulsar/common/policies/data/OffloadPoliciesImpl$OffloadPoliciesImplBuilder.managedLedgerOffloadBucket:(Ljava/lang/String;)Lorg/apache/pulsar/common/policies/data/OffloadPoliciesImpl$OffloadPoliciesImplBuilder;
      21: aload_1
      22: invokevirtual #34                 // Method org/apache/pulsar/common/policies/data/OffloadPoliciesImpl$OffloadPoliciesImplBuilder.managedLedgerOffloadRegion:(Ljava/lang/String;)Lorg/apache/pulsar/common/policies/data/OffloadPoliciesImpl$OffloadPoliciesImplBuilder;
      25: aload_3
      26: invokevirtual #35                 // Method org/apache/pulsar/common/policies/data/OffloadPoliciesImpl$OffloadPoliciesImplBuilder.managedLedgerOffloadServiceEndpoint:(Ljava/lang/String;)Lorg/apache/pulsar/common/policies/data/OffloadPoliciesImpl$OffloadPoliciesImplBuilder;
      29: aload         8
      31: invokevirtual #36                 // Method org/apache/pulsar/common/policies/data/OffloadPoliciesImpl$OffloadPoliciesImplBuilder.managedLedgerOffloadMaxBlockSizeInBytes:(Ljava/lang/Integer;)Lorg/apache/pulsar/common/policies/data/OffloadPoliciesImpl$OffloadPoliciesImplBuilder;
      34: aload         9
      36: invokevirtual #37                 // Method org/apache/pulsar/common/policies/data/OffloadPoliciesImpl$OffloadPoliciesImplBuilder.managedLedgerOffloadReadBufferSizeInBytes:(Ljava/lang/Integer;)Lorg/apache/pulsar/common/policies/data/OffloadPoliciesImpl$OffloadPoliciesImplBuilder;
      39: aload         12
      41: invokevirtual #38                 // Method org/apache/pulsar/common/policies/data/OffloadPoliciesImpl$OffloadPoliciesImplBuilder.managedLedgerOffloadedReadPriority:(Lorg/apache/pulsar/common/policies/data/OffloadedReadPriority;)Lorg/apache/pulsar/common/policies/data/OffloadPoliciesImpl$OffloadPoliciesImplBuilder;
      44: astore        13
      46: aload_0
      47: getstatic     #39                 // Field DRIVER_NAMES:Lcom/google/common/collect/ImmutableList;
      50: iconst_0
      51: invokevirtual #40                 // Method com/google/common/collect/ImmutableList.get:(I)Ljava/lang/Object;
      54: checkcast     #41                 // class java/lang/String
      57: invokevirtual #42                 // Method java/lang/String.equalsIgnoreCase:(Ljava/lang/String;)Z
      60: ifne          80
      63: aload_0
      64: getstatic     #39                 // Field DRIVER_NAMES:Lcom/google/common/collect/ImmutableList;
      67: iconst_1
      68: invokevirtual #40                 // Method com/google/common/collect/ImmutableList.get:(I)Ljava/lang/Object;
      71: checkcast     #41                 // class java/lang/String
      74: invokevirtual #42                 // Method java/lang/String.equalsIgnoreCase:(Ljava/lang/String;)Z
      77: ifeq          160
      80: aload         4
      82: ifnull        93
      85: aload         13
      87: aload         4
      89: invokevirtual #43                 // Method org/apache/pulsar/common/policies/data/OffloadPoliciesImpl$OffloadPoliciesImplBuilder.s3ManagedLedgerOffloadRole:(Ljava/lang/String;)Lorg/apache/pulsar/common/policies/data/OffloadPoliciesImpl$OffloadPoliciesImplBuilder;
      92: pop
      93: aload         5
      95: ifnull        106
      98: aload         13
     100: aload         5
     102: invokevirtual #44                 // Method org/apache/pulsar/common/policies/data/OffloadPoliciesImpl$OffloadPoliciesImplBuilder.s3ManagedLedgerOffloadRoleSessionName:(Ljava/lang/String;)Lorg/apache/pulsar/common/policies/data/OffloadPoliciesImpl$OffloadPoliciesImplBuilder;
     105: pop
     106: aload         6
     108: ifnull        119
     111: aload         13
     113: aload         6
     115: invokevirtual #45                 // Method org/apache/pulsar/common/policies/data/OffloadPoliciesImpl$OffloadPoliciesImplBuilder.s3ManagedLedgerOffloadCredentialId:(Ljava/lang/String;)Lorg/apache/pulsar/common/policies/data/OffloadPoliciesImpl$OffloadPoliciesImplBuilder;
     118: pop
     119: aload         7
     121: ifnull        132
     124: aload         13
     126: aload         7
     128: invokevirtual #46                 // Method org/apache/pulsar/common/policies/data/OffloadPoliciesImpl$OffloadPoliciesImplBuilder.s3ManagedLedgerOffloadCredentialSecret:(Ljava/lang/String;)Lorg/apache/pulsar/common/policies/data/OffloadPoliciesImpl$OffloadPoliciesImplBuilder;
     131: pop
     132: aload         13
     134: aload_1
     135: invokevirtual #47                 // Method org/apache/pulsar/common/policies/data/OffloadPoliciesImpl$OffloadPoliciesImplBuilder.s3ManagedLedgerOffloadRegion:(Ljava/lang/String;)Lorg/apache/pulsar/common/policies/data/OffloadPoliciesImpl$OffloadPoliciesImplBuilder;
     138: aload_2
     139: invokevirtual #48                 // Method org/apache/pulsar/common/policies/data/OffloadPoliciesImpl$OffloadPoliciesImplBuilder.s3ManagedLedgerOffloadBucket:(Ljava/lang/String;)Lorg/apache/pulsar/common/policies/data/OffloadPoliciesImpl$OffloadPoliciesImplBuilder;
     142: aload_3
     143: invokevirtual #49                 // Method org/apache/pulsar/common/policies/data/OffloadPoliciesImpl$OffloadPoliciesImplBuilder.s3ManagedLedgerOffloadServiceEndpoint:(Ljava/lang/String;)Lorg/apache/pulsar/common/policies/data/OffloadPoliciesImpl$OffloadPoliciesImplBuilder;
     146: aload         8
     148: invokevirtual #50                 // Method org/apache/pulsar/common/policies/data/OffloadPoliciesImpl$OffloadPoliciesImplBuilder.s3ManagedLedgerOffloadMaxBlockSizeInBytes:(Ljava/lang/Integer;)Lorg/apache/pulsar/common/policies/data/OffloadPoliciesImpl$OffloadPoliciesImplBuilder;
     151: aload         9
     153: invokevirtual #51                 // Method org/apache/pulsar/common/policies/data/OffloadPoliciesImpl$OffloadPoliciesImplBuilder.s3ManagedLedgerOffloadReadBufferSizeInBytes:(Ljava/lang/Integer;)Lorg/apache/pulsar/common/policies/data/OffloadPoliciesImpl$OffloadPoliciesImplBuilder;
     156: pop
     157: goto          198
     160: aload_0
     161: getstatic     #39                 // Field DRIVER_NAMES:Lcom/google/common/collect/ImmutableList;
     164: iconst_2
     165: invokevirtual #40                 // Method com/google/common/collect/ImmutableList.get:(I)Ljava/lang/Object;
     168: checkcast     #41                 // class java/lang/String
     171: invokevirtual #42                 // Method java/lang/String.equalsIgnoreCase:(Ljava/lang/String;)Z
     174: ifeq          198
     177: aload         13
     179: aload_1
     180: invokevirtual #52                 // Method org/apache/pulsar/common/policies/data/OffloadPoliciesImpl$OffloadPoliciesImplBuilder.gcsManagedLedgerOffloadRegion:(Ljava/lang/String;)Lorg/apache/pulsar/common/policies/data/OffloadPoliciesImpl$OffloadPoliciesImplBuilder;
     183: aload_2
     184: invokevirtual #53                 // Method org/apache/pulsar/common/policies/data/OffloadPoliciesImpl$OffloadPoliciesImplBuilder.gcsManagedLedgerOffloadBucket:(Ljava/lang/String;)Lorg/apache/pulsar/common/policies/data/OffloadPoliciesImpl$OffloadPoliciesImplBuilder;
     187: aload         8
     189: invokevirtual #54                 // Method org/apache/pulsar/common/policies/data/OffloadPoliciesImpl$OffloadPoliciesImplBuilder.gcsManagedLedgerOffloadMaxBlockSizeInBytes:(Ljava/lang/Integer;)Lorg/apache/pulsar/common/policies/data/OffloadPoliciesImpl$OffloadPoliciesImplBuilder;
     192: aload         9
     194: invokevirtual #55                 // Method org/apache/pulsar/common/policies/data/OffloadPoliciesImpl$OffloadPoliciesImplBuilder.gcsManagedLedgerOffloadReadBufferSizeInBytes:(Ljava/lang/Integer;)Lorg/apache/pulsar/common/policies/data/OffloadPoliciesImpl$OffloadPoliciesImplBuilder;
     197: pop
     198: aload         13
     200: invokevirtual #56                 // Method org/apache/pulsar/common/policies/data/OffloadPoliciesImpl$OffloadPoliciesImplBuilder.build:()Lorg/apache/pulsar/common/policies/data/OffloadPoliciesImpl;
     203: areturn

  public static org.apache.pulsar.common.policies.data.OffloadPoliciesImpl create(java.util.Properties);
    Code:
       0: new           #57                 // class org/apache/pulsar/common/policies/data/OffloadPoliciesImpl
       3: dup
       4: invokespecial #58                 // Method "<init>":()V
       7: astore_1
       8: ldc           #57                 // class org/apache/pulsar/common/policies/data/OffloadPoliciesImpl
      10: invokevirtual #59                 // Method java/lang/Class.getDeclaredFields:()[Ljava/lang/reflect/Field;
      13: astore_2
      14: aload_2
      15: invokestatic  #60                 // Method java/util/Arrays.stream:([Ljava/lang/Object;)Ljava/util/stream/Stream;
      18: aload_0
      19: aload_1
      20: invokedynamic #61,  0             // InvokeDynamic #0:accept:(Ljava/util/Properties;Lorg/apache/pulsar/common/policies/data/OffloadPoliciesImpl;)Ljava/util/function/Consumer;
      25: invokeinterface #62,  2           // InterfaceMethod java/util/stream/Stream.forEach:(Ljava/util/function/Consumer;)V
      30: aload_1
      31: aload_0
      32: invokevirtual #63                 // Method compatibleWithBrokerConfigFile:(Ljava/util/Properties;)V
      35: aload_1
      36: areturn

  public static org.apache.pulsar.common.policies.data.OffloadPoliciesImpl$OffloadPoliciesImplBuilder builder();
    Code:
       0: new           #64                 // class org/apache/pulsar/common/policies/data/OffloadPoliciesImpl$OffloadPoliciesImplBuilder
       3: dup
       4: invokespecial #65                 // Method org/apache/pulsar/common/policies/data/OffloadPoliciesImpl$OffloadPoliciesImplBuilder."<init>":()V
       7: areturn

  public void compatibleWithBrokerConfigFile(java.util.Properties);
    Code:
       0: aload_1
       1: ldc           #66                 // String managedLedgerOffloadThresholdInBytes
       3: invokevirtual #67                 // Method java/util/Properties.containsKey:(Ljava/lang/Object;)Z
       6: ifne          34
       9: aload_1
      10: ldc           #68                 // String managedLedgerOffloadAutoTriggerSizeThresholdBytes
      12: invokevirtual #67                 // Method java/util/Properties.containsKey:(Ljava/lang/Object;)Z
      15: ifeq          34
      18: aload_0
      19: aload_1
      20: ldc           #68                 // String managedLedgerOffloadAutoTriggerSizeThresholdBytes
      22: invokevirtual #69                 // Method java/util/Properties.getProperty:(Ljava/lang/String;)Ljava/lang/String;
      25: invokestatic  #70                 // Method java/lang/Long.parseLong:(Ljava/lang/String;)J
      28: invokestatic  #71                 // Method java/lang/Long.valueOf:(J)Ljava/lang/Long;
      31: invokevirtual #72                 // Method setManagedLedgerOffloadThresholdInBytes:(Ljava/lang/Long;)V
      34: aload_1
      35: ldc           #73                 // String managedLedgerOffloadDeletionLagInMillis
      37: invokevirtual #67                 // Method java/util/Properties.containsKey:(Ljava/lang/Object;)Z
      40: ifne          68
      43: aload_1
      44: ldc           #74                 // String managedLedgerOffloadDeletionLagMs
      46: invokevirtual #67                 // Method java/util/Properties.containsKey:(Ljava/lang/Object;)Z
      49: ifeq          68
      52: aload_0
      53: aload_1
      54: ldc           #74                 // String managedLedgerOffloadDeletionLagMs
      56: invokevirtual #69                 // Method java/util/Properties.getProperty:(Ljava/lang/String;)Ljava/lang/String;
      59: invokestatic  #70                 // Method java/lang/Long.parseLong:(Ljava/lang/String;)J
      62: invokestatic  #71                 // Method java/lang/Long.valueOf:(J)Ljava/lang/Long;
      65: invokevirtual #75                 // Method setManagedLedgerOffloadDeletionLagInMillis:(Ljava/lang/Long;)V
      68: return

  public boolean driverSupported();
    Code:
       0: getstatic     #39                 // Field DRIVER_NAMES:Lcom/google/common/collect/ImmutableList;
       3: invokevirtual #76                 // Method com/google/common/collect/ImmutableList.stream:()Ljava/util/stream/Stream;
       6: aload_0
       7: invokedynamic #77,  0             // InvokeDynamic #1:test:(Lorg/apache/pulsar/common/policies/data/OffloadPoliciesImpl;)Ljava/util/function/Predicate;
      12: invokeinterface #78,  2           // InterfaceMethod java/util/stream/Stream.anyMatch:(Ljava/util/function/Predicate;)Z
      17: ireturn

  public static java.lang.String getSupportedDriverNames();
    Code:
       0: getstatic     #39                 // Field DRIVER_NAMES:Lcom/google/common/collect/ImmutableList;
       3: ldc           #79                 // String ,
       5: invokestatic  #80                 // Method org/apache/commons/lang3/StringUtils.join:(Ljava/lang/Iterable;Ljava/lang/String;)Ljava/lang/String;
       8: areturn

  public boolean isS3Driver();
    Code:
       0: aload_0
       1: getfield      #27                 // Field managedLedgerOffloadDriver:Ljava/lang/String;
       4: ifnonnull     9
       7: iconst_0
       8: ireturn
       9: aload_0
      10: getfield      #27                 // Field managedLedgerOffloadDriver:Ljava/lang/String;
      13: getstatic     #39                 // Field DRIVER_NAMES:Lcom/google/common/collect/ImmutableList;
      16: iconst_0
      17: invokevirtual #40                 // Method com/google/common/collect/ImmutableList.get:(I)Ljava/lang/Object;
      20: checkcast     #41                 // class java/lang/String
      23: invokevirtual #42                 // Method java/lang/String.equalsIgnoreCase:(Ljava/lang/String;)Z
      26: ifne          49
      29: aload_0
      30: getfield      #27                 // Field managedLedgerOffloadDriver:Ljava/lang/String;
      33: getstatic     #39                 // Field DRIVER_NAMES:Lcom/google/common/collect/ImmutableList;
      36: iconst_1
      37: invokevirtual #40                 // Method com/google/common/collect/ImmutableList.get:(I)Ljava/lang/Object;
      40: checkcast     #41                 // class java/lang/String
      43: invokevirtual #42                 // Method java/lang/String.equalsIgnoreCase:(Ljava/lang/String;)Z
      46: ifeq          53
      49: iconst_1
      50: goto          54
      53: iconst_0
      54: ireturn

  public boolean isGcsDriver();
    Code:
       0: aload_0
       1: getfield      #27                 // Field managedLedgerOffloadDriver:Ljava/lang/String;
       4: ifnonnull     9
       7: iconst_0
       8: ireturn
       9: aload_0
      10: getfield      #27                 // Field managedLedgerOffloadDriver:Ljava/lang/String;
      13: getstatic     #39                 // Field DRIVER_NAMES:Lcom/google/common/collect/ImmutableList;
      16: iconst_2
      17: invokevirtual #40                 // Method com/google/common/collect/ImmutableList.get:(I)Ljava/lang/Object;
      20: checkcast     #41                 // class java/lang/String
      23: invokevirtual #42                 // Method java/lang/String.equalsIgnoreCase:(Ljava/lang/String;)Z
      26: ireturn

  public boolean isFileSystemDriver();
    Code:
       0: aload_0
       1: getfield      #27                 // Field managedLedgerOffloadDriver:Ljava/lang/String;
       4: ifnonnull     9
       7: iconst_0
       8: ireturn
       9: aload_0
      10: getfield      #27                 // Field managedLedgerOffloadDriver:Ljava/lang/String;
      13: getstatic     #39                 // Field DRIVER_NAMES:Lcom/google/common/collect/ImmutableList;
      16: iconst_3
      17: invokevirtual #40                 // Method com/google/common/collect/ImmutableList.get:(I)Ljava/lang/Object;
      20: checkcast     #41                 // class java/lang/String
      23: invokevirtual #42                 // Method java/lang/String.equalsIgnoreCase:(Ljava/lang/String;)Z
      26: ireturn

  public boolean bucketValid();
    Code:
       0: aload_0
       1: getfield      #27                 // Field managedLedgerOffloadDriver:Ljava/lang/String;
       4: ifnonnull     9
       7: iconst_0
       8: ireturn
       9: aload_0
      10: getfield      #5                  // Field managedLedgerOffloadBucket:Ljava/lang/String;
      13: invokestatic  #81                 // Method org/apache/commons/lang3/StringUtils.isNotEmpty:(Ljava/lang/CharSequence;)Z
      16: ifeq          21
      19: iconst_1
      20: ireturn
      21: aload_0
      22: invokevirtual #82                 // Method isS3Driver:()Z
      25: ifeq          36
      28: aload_0
      29: getfield      #20                 // Field s3ManagedLedgerOffloadBucket:Ljava/lang/String;
      32: invokestatic  #81                 // Method org/apache/commons/lang3/StringUtils.isNotEmpty:(Ljava/lang/CharSequence;)Z
      35: ireturn
      36: aload_0
      37: invokevirtual #83                 // Method isGcsDriver:()Z
      40: ifeq          51
      43: aload_0
      44: getfield      #11                 // Field gcsManagedLedgerOffloadBucket:Ljava/lang/String;
      47: invokestatic  #81                 // Method org/apache/commons/lang3/StringUtils.isNotEmpty:(Ljava/lang/CharSequence;)Z
      50: ireturn
      51: aload_0
      52: invokevirtual #84                 // Method isFileSystemDriver:()Z
      55: ifeq          60
      58: iconst_1
      59: ireturn
      60: iconst_0
      61: ireturn

  public java.util.Properties toProperties();
    Code:
       0: new           #85                 // class java/util/Properties
       3: dup
       4: invokespecial #86                 // Method java/util/Properties."<init>":()V
       7: astore_1
       8: aload_1
       9: ldc           #87                 // String managedLedgerOffloadedReadPriority
      11: aload_0
      12: invokevirtual #88                 // Method getManagedLedgerOffloadedReadPriority:()Lorg/apache/pulsar/common/policies/data/OffloadedReadPriority;
      15: invokestatic  #89                 // Method setProperty:(Ljava/util/Properties;Ljava/lang/String;Ljava/lang/Object;)V
      18: aload_1
      19: ldc           #90                 // String offloadersDirectory
      21: aload_0
      22: invokevirtual #91                 // Method getOffloadersDirectory:()Ljava/lang/String;
      25: invokestatic  #89                 // Method setProperty:(Ljava/util/Properties;Ljava/lang/String;Ljava/lang/Object;)V
      28: aload_1
      29: ldc           #92                 // String managedLedgerOffloadDriver
      31: aload_0
      32: invokevirtual #93                 // Method getManagedLedgerOffloadDriver:()Ljava/lang/String;
      35: invokestatic  #89                 // Method setProperty:(Ljava/util/Properties;Ljava/lang/String;Ljava/lang/Object;)V
      38: aload_1
      39: ldc           #94                 // String managedLedgerOffloadMaxThreads
      41: aload_0
      42: invokevirtual #95                 // Method getManagedLedgerOffloadMaxThreads:()Ljava/lang/Integer;
      45: invokestatic  #89                 // Method setProperty:(Ljava/util/Properties;Ljava/lang/String;Ljava/lang/Object;)V
      48: aload_1
      49: ldc           #96                 // String managedLedgerOffloadPrefetchRounds
      51: aload_0
      52: invokevirtual #97                 // Method getManagedLedgerOffloadPrefetchRounds:()Ljava/lang/Integer;
      55: invokestatic  #89                 // Method setProperty:(Ljava/util/Properties;Ljava/lang/String;Ljava/lang/Object;)V
      58: aload_1
      59: ldc           #66                 // String managedLedgerOffloadThresholdInBytes
      61: aload_0
      62: invokevirtual #98                 // Method getManagedLedgerOffloadThresholdInBytes:()Ljava/lang/Long;
      65: invokestatic  #89                 // Method setProperty:(Ljava/util/Properties;Ljava/lang/String;Ljava/lang/Object;)V
      68: aload_1
      69: ldc           #73                 // String managedLedgerOffloadDeletionLagInMillis
      71: aload_0
      72: invokevirtual #99                 // Method getManagedLedgerOffloadDeletionLagInMillis:()Ljava/lang/Long;
      75: invokestatic  #89                 // Method setProperty:(Ljava/util/Properties;Ljava/lang/String;Ljava/lang/Object;)V
      78: aload_0
      79: invokevirtual #82                 // Method isS3Driver:()Z
      82: ifeq          178
      85: aload_1
      86: ldc           #100                // String s3ManagedLedgerOffloadRegion
      88: aload_0
      89: invokevirtual #101                // Method getS3ManagedLedgerOffloadRegion:()Ljava/lang/String;
      92: invokestatic  #89                 // Method setProperty:(Ljava/util/Properties;Ljava/lang/String;Ljava/lang/Object;)V
      95: aload_1
      96: ldc           #102                // String s3ManagedLedgerOffloadBucket
      98: aload_0
      99: invokevirtual #103                // Method getS3ManagedLedgerOffloadBucket:()Ljava/lang/String;
     102: invokestatic  #89                 // Method setProperty:(Ljava/util/Properties;Ljava/lang/String;Ljava/lang/Object;)V
     105: aload_1
     106: ldc           #104                // String s3ManagedLedgerOffloadServiceEndpoint
     108: aload_0
     109: invokevirtual #105                // Method getS3ManagedLedgerOffloadServiceEndpoint:()Ljava/lang/String;
     112: invokestatic  #89                 // Method setProperty:(Ljava/util/Properties;Ljava/lang/String;Ljava/lang/Object;)V
     115: aload_1
     116: ldc           #106                // String s3ManagedLedgerOffloadMaxBlockSizeInBytes
     118: aload_0
     119: invokevirtual #107                // Method getS3ManagedLedgerOffloadMaxBlockSizeInBytes:()Ljava/lang/Integer;
     122: invokestatic  #89                 // Method setProperty:(Ljava/util/Properties;Ljava/lang/String;Ljava/lang/Object;)V
     125: aload_1
     126: ldc           #108                // String s3ManagedLedgerOffloadCredentialId
     128: aload_0
     129: invokevirtual #109                // Method getS3ManagedLedgerOffloadCredentialId:()Ljava/lang/String;
     132: invokestatic  #89                 // Method setProperty:(Ljava/util/Properties;Ljava/lang/String;Ljava/lang/Object;)V
     135: aload_1
     136: ldc           #110                // String s3ManagedLedgerOffloadCredentialSecret
     138: aload_0
     139: invokevirtual #111                // Method getS3ManagedLedgerOffloadCredentialSecret:()Ljava/lang/String;
     142: invokestatic  #89                 // Method setProperty:(Ljava/util/Properties;Ljava/lang/String;Ljava/lang/Object;)V
     145: aload_1
     146: ldc           #112                // String s3ManagedLedgerOffloadRole
     148: aload_0
     149: invokevirtual #113                // Method getS3ManagedLedgerOffloadRole:()Ljava/lang/String;
     152: invokestatic  #89                 // Method setProperty:(Ljava/util/Properties;Ljava/lang/String;Ljava/lang/Object;)V
     155: aload_1
     156: ldc           #114                // String s3ManagedLedgerOffloadRoleSessionName
     158: aload_0
     159: invokevirtual #115                // Method getS3ManagedLedgerOffloadRoleSessionName:()Ljava/lang/String;
     162: invokestatic  #89                 // Method setProperty:(Ljava/util/Properties;Ljava/lang/String;Ljava/lang/Object;)V
     165: aload_1
     166: ldc           #116                // String s3ManagedLedgerOffloadReadBufferSizeInBytes
     168: aload_0
     169: invokevirtual #117                // Method getS3ManagedLedgerOffloadReadBufferSizeInBytes:()Ljava/lang/Integer;
     172: invokestatic  #89                 // Method setProperty:(Ljava/util/Properties;Ljava/lang/String;Ljava/lang/Object;)V
     175: goto          265
     178: aload_0
     179: invokevirtual #83                 // Method isGcsDriver:()Z
     182: ifeq          238
     185: aload_1
     186: ldc           #118                // String gcsManagedLedgerOffloadRegion
     188: aload_0
     189: invokevirtual #119                // Method getGcsManagedLedgerOffloadRegion:()Ljava/lang/String;
     192: invokestatic  #89                 // Method setProperty:(Ljava/util/Properties;Ljava/lang/String;Ljava/lang/Object;)V
     195: aload_1
     196: ldc           #120                // String gcsManagedLedgerOffloadBucket
     198: aload_0
     199: invokevirtual #121                // Method getGcsManagedLedgerOffloadBucket:()Ljava/lang/String;
     202: invokestatic  #89                 // Method setProperty:(Ljava/util/Properties;Ljava/lang/String;Ljava/lang/Object;)V
     205: aload_1
     206: ldc           #122                // String gcsManagedLedgerOffloadMaxBlockSizeInBytes
     208: aload_0
     209: invokevirtual #123                // Method getGcsManagedLedgerOffloadMaxBlockSizeInBytes:()Ljava/lang/Integer;
     212: invokestatic  #89                 // Method setProperty:(Ljava/util/Properties;Ljava/lang/String;Ljava/lang/Object;)V
     215: aload_1
     216: ldc           #124                // String gcsManagedLedgerOffloadReadBufferSizeInBytes
     218: aload_0
     219: invokevirtual #125                // Method getGcsManagedLedgerOffloadReadBufferSizeInBytes:()Ljava/lang/Integer;
     222: invokestatic  #89                 // Method setProperty:(Ljava/util/Properties;Ljava/lang/String;Ljava/lang/Object;)V
     225: aload_1
     226: ldc           #126                // String gcsManagedLedgerOffloadServiceAccountKeyFile
     228: aload_0
     229: invokevirtual #127                // Method getGcsManagedLedgerOffloadServiceAccountKeyFile:()Ljava/lang/String;
     232: invokestatic  #89                 // Method setProperty:(Ljava/util/Properties;Ljava/lang/String;Ljava/lang/Object;)V
     235: goto          265
     238: aload_0
     239: invokevirtual #84                 // Method isFileSystemDriver:()Z
     242: ifeq          265
     245: aload_1
     246: ldc           #128                // String fileSystemProfilePath
     248: aload_0
     249: invokevirtual #129                // Method getFileSystemProfilePath:()Ljava/lang/String;
     252: invokestatic  #89                 // Method setProperty:(Ljava/util/Properties;Ljava/lang/String;Ljava/lang/Object;)V
     255: aload_1
     256: ldc           #130                // String fileSystemURI
     258: aload_0
     259: invokevirtual #131                // Method getFileSystemURI:()Ljava/lang/String;
     262: invokestatic  #89                 // Method setProperty:(Ljava/util/Properties;Ljava/lang/String;Ljava/lang/Object;)V
     265: aload_1
     266: ldc           #132                // String managedLedgerOffloadBucket
     268: aload_0
     269: invokevirtual #133                // Method getManagedLedgerOffloadBucket:()Ljava/lang/String;
     272: invokestatic  #89                 // Method setProperty:(Ljava/util/Properties;Ljava/lang/String;Ljava/lang/Object;)V
     275: aload_1
     276: ldc           #134                // String managedLedgerOffloadRegion
     278: aload_0
     279: invokevirtual #135                // Method getManagedLedgerOffloadRegion:()Ljava/lang/String;
     282: invokestatic  #89                 // Method setProperty:(Ljava/util/Properties;Ljava/lang/String;Ljava/lang/Object;)V
     285: aload_1
     286: ldc           #136                // String managedLedgerOffloadServiceEndpoint
     288: aload_0
     289: invokevirtual #137                // Method getManagedLedgerOffloadServiceEndpoint:()Ljava/lang/String;
     292: invokestatic  #89                 // Method setProperty:(Ljava/util/Properties;Ljava/lang/String;Ljava/lang/Object;)V
     295: aload_1
     296: ldc           #138                // String managedLedgerOffloadMaxBlockSizeInBytes
     298: aload_0
     299: invokevirtual #139                // Method getManagedLedgerOffloadMaxBlockSizeInBytes:()Ljava/lang/Integer;
     302: invokestatic  #89                 // Method setProperty:(Ljava/util/Properties;Ljava/lang/String;Ljava/lang/Object;)V
     305: aload_1
     306: ldc           #140                // String managedLedgerOffloadReadBufferSizeInBytes
     308: aload_0
     309: invokevirtual #141                // Method getManagedLedgerOffloadReadBufferSizeInBytes:()Ljava/lang/Integer;
     312: invokestatic  #89                 // Method setProperty:(Ljava/util/Properties;Ljava/lang/String;Ljava/lang/Object;)V
     315: aload_1
     316: areturn

  private static void setProperty(java.util.Properties, java.lang.String, java.lang.Object);
    Code:
       0: aload_2
       1: ifnull        29
       4: aload_0
       5: aload_1
       6: new           #142                // class java/lang/StringBuilder
       9: dup
      10: invokespecial #143                // Method java/lang/StringBuilder."<init>":()V
      13: ldc           #144                // String
      15: invokevirtual #145                // Method java/lang/StringBuilder.append:(Ljava/lang/String;)Ljava/lang/StringBuilder;
      18: aload_2
      19: invokevirtual #146                // Method java/lang/StringBuilder.append:(Ljava/lang/Object;)Ljava/lang/StringBuilder;
      22: invokevirtual #147                // Method java/lang/StringBuilder.toString:()Ljava/lang/String;
      25: invokevirtual #148                // Method java/util/Properties.setProperty:(Ljava/lang/String;Ljava/lang/String;)Ljava/lang/Object;
      28: pop
      29: return

  public static org.apache.pulsar.common.policies.data.OffloadPoliciesImpl oldPoliciesCompatible(org.apache.pulsar.common.policies.data.OffloadPoliciesImpl, org.apache.pulsar.common.policies.data.Policies);
    Code:
       0: aload_1
       1: ifnull        22
       4: aload_1
       5: getfield      #149                // Field org/apache/pulsar/common/policies/data/Policies.offload_threshold:J
       8: ldc2_w        #150                // long -1l
      11: lcmp
      12: ifne          24
      15: aload_1
      16: getfield      #152                // Field org/apache/pulsar/common/policies/data/Policies.offload_deletion_lag_ms:Ljava/lang/Long;
      19: ifnonnull     24
      22: aload_0
      23: areturn
      24: aload_0
      25: ifnonnull     36
      28: new           #57                 // class org/apache/pulsar/common/policies/data/OffloadPoliciesImpl
      31: dup
      32: invokespecial #58                 // Method "<init>":()V
      35: astore_0
      36: aload_0
      37: invokevirtual #98                 // Method getManagedLedgerOffloadThresholdInBytes:()Ljava/lang/Long;
      40: ifnonnull     65
      43: aload_1
      44: getfield      #149                // Field org/apache/pulsar/common/policies/data/Policies.offload_threshold:J
      47: ldc2_w        #150                // long -1l
      50: lcmp
      51: ifeq          65
      54: aload_0
      55: aload_1
      56: getfield      #149                // Field org/apache/pulsar/common/policies/data/Policies.offload_threshold:J
      59: invokestatic  #71                 // Method java/lang/Long.valueOf:(J)Ljava/lang/Long;
      62: invokevirtual #72                 // Method setManagedLedgerOffloadThresholdInBytes:(Ljava/lang/Long;)V
      65: aload_0
      66: invokevirtual #99                 // Method getManagedLedgerOffloadDeletionLagInMillis:()Ljava/lang/Long;
      69: ifnonnull     87
      72: aload_1
      73: getfield      #152                // Field org/apache/pulsar/common/policies/data/Policies.offload_deletion_lag_ms:Ljava/lang/Long;
      76: ifnull        87
      79: aload_0
      80: aload_1
      81: getfield      #152                // Field org/apache/pulsar/common/policies/data/Policies.offload_deletion_lag_ms:Ljava/lang/Long;
      84: invokevirtual #75                 // Method setManagedLedgerOffloadDeletionLagInMillis:(Ljava/lang/Long;)V
      87: aload_0
      88: areturn

  public static org.apache.pulsar.common.policies.data.OffloadPoliciesImpl mergeConfiguration(org.apache.pulsar.common.policies.data.OffloadPoliciesImpl, org.apache.pulsar.common.policies.data.OffloadPoliciesImpl, java.util.Properties);
    Code:
       0: iconst_1
       1: istore_3
       2: new           #57                 // class org/apache/pulsar/common/policies/data/OffloadPoliciesImpl
       5: dup
       6: invokespecial #58                 // Method "<init>":()V
       9: astore        4
      11: getstatic     #153                // Field CONFIGURATION_FIELDS:Ljava/util/List;
      14: invokeinterface #154,  1          // InterfaceMethod java/util/List.iterator:()Ljava/util/Iterator;
      19: astore        5
      21: aload         5
      23: invokeinterface #155,  1          // InterfaceMethod java/util/Iterator.hasNext:()Z
      28: ifeq          122
      31: aload         5
      33: invokeinterface #156,  1          // InterfaceMethod java/util/Iterator.next:()Ljava/lang/Object;
      38: checkcast     #157                // class java/lang/reflect/Field
      41: astore        6
      43: aload_0
      44: ifnull        67
      47: aload         6
      49: aload_0
      50: invokevirtual #158                // Method java/lang/reflect/Field.get:(Ljava/lang/Object;)Ljava/lang/Object;
      53: ifnull        67
      56: aload         6
      58: aload_0
      59: invokevirtual #158                // Method java/lang/reflect/Field.get:(Ljava/lang/Object;)Ljava/lang/Object;
      62: astore        7
      64: goto          99
      67: aload_1
      68: ifnull        91
      71: aload         6
      73: aload_1
      74: invokevirtual #158                // Method java/lang/reflect/Field.get:(Ljava/lang/Object;)Ljava/lang/Object;
      77: ifnull        91
      80: aload         6
      82: aload_1
      83: invokevirtual #158                // Method java/lang/reflect/Field.get:(Ljava/lang/Object;)Ljava/lang/Object;
      86: astore        7
      88: goto          99
      91: aload_2
      92: aload         6
      94: invokestatic  #159                // Method getCompatibleValue:(Ljava/util/Properties;Ljava/lang/reflect/Field;)Ljava/lang/Object;
      97: astore        7
      99: aload         7
     101: ifnull        119
     104: aload         6
     106: aload         4
     108: aload         7
     110: invokevirtual #160                // Method java/lang/reflect/Field.set:(Ljava/lang/Object;Ljava/lang/Object;)V
     113: iload_3
     114: ifeq          119
     117: iconst_0
     118: istore_3
     119: goto          21
     122: iload_3
     123: ifeq          128
     126: aconst_null
     127: areturn
     128: aload         4
     130: areturn
     131: astore_3
     132: getstatic     #162                // Field log:Lorg/slf4j/Logger;
     135: ldc           #163                // String Failed to merge configuration.
     137: aload_3
     138: invokeinterface #164,  3          // InterfaceMethod org/slf4j/Logger.error:(Ljava/lang/String;Ljava/lang/Throwable;)V
     143: aconst_null
     144: areturn
    Exception table:
       from    to  target type
           0   127   131   Class java/lang/Exception
         128   130   131   Class java/lang/Exception

  private static java.lang.Object getCompatibleValue(java.util.Properties, java.lang.reflect.Field);
    Code:
       0: aload_1
       1: invokevirtual #165                // Method java/lang/reflect/Field.getName:()Ljava/lang/String;
       4: ldc           #66                 // String managedLedgerOffloadThresholdInBytes
       6: invokevirtual #166                // Method java/lang/String.equals:(Ljava/lang/Object;)Z
       9: ifeq          28
      12: aload_0
      13: ldc           #66                 // String managedLedgerOffloadThresholdInBytes
      15: aload_0
      16: ldc           #68                 // String managedLedgerOffloadAutoTriggerSizeThresholdBytes
      18: invokevirtual #69                 // Method java/util/Properties.getProperty:(Ljava/lang/String;)Ljava/lang/String;
      21: invokevirtual #167                // Method java/util/Properties.getProperty:(Ljava/lang/String;Ljava/lang/String;)Ljava/lang/String;
      24: astore_2
      25: goto          65
      28: aload_1
      29: invokevirtual #165                // Method java/lang/reflect/Field.getName:()Ljava/lang/String;
      32: ldc           #73                 // String managedLedgerOffloadDeletionLagInMillis
      34: invokevirtual #166                // Method java/lang/String.equals:(Ljava/lang/Object;)Z
      37: ifeq          56
      40: aload_0
      41: ldc           #73                 // String managedLedgerOffloadDeletionLagInMillis
      43: aload_0
      44: ldc           #74                 // String managedLedgerOffloadDeletionLagMs
      46: invokevirtual #69                 // Method java/util/Properties.getProperty:(Ljava/lang/String;)Ljava/lang/String;
      49: invokevirtual #167                // Method java/util/Properties.getProperty:(Ljava/lang/String;Ljava/lang/String;)Ljava/lang/String;
      52: astore_2
      53: goto          65
      56: aload_0
      57: aload_1
      58: invokevirtual #165                // Method java/lang/reflect/Field.getName:()Ljava/lang/String;
      61: invokevirtual #168                // Method java/util/Properties.get:(Ljava/lang/Object;)Ljava/lang/Object;
      64: astore_2
      65: aload_2
      66: checkcast     #41                 // class java/lang/String
      69: aload_1
      70: invokestatic  #169                // Method org/apache/pulsar/common/util/FieldParser.value:(Ljava/lang/String;Ljava/lang/reflect/Field;)Ljava/lang/Object;
      73: areturn

  public java.lang.String getOffloadersDirectory();
    Code:
       0: aload_0
       1: getfield      #28                 // Field offloadersDirectory:Ljava/lang/String;
       4: areturn

  public java.lang.String getManagedLedgerOffloadDriver();
    Code:
       0: aload_0
       1: getfield      #27                 // Field managedLedgerOffloadDriver:Ljava/lang/String;
       4: areturn

  public java.lang.Integer getManagedLedgerOffloadMaxThreads();
    Code:
       0: aload_0
       1: getfield      #26                 // Field managedLedgerOffloadMaxThreads:Ljava/lang/Integer;
       4: areturn

  public java.lang.Integer getManagedLedgerOffloadPrefetchRounds();
    Code:
       0: aload_0
       1: getfield      #25                 // Field managedLedgerOffloadPrefetchRounds:Ljava/lang/Integer;
       4: areturn

  public java.lang.Long getManagedLedgerOffloadThresholdInBytes();
    Code:
       0: aload_0
       1: getfield      #24                 // Field managedLedgerOffloadThresholdInBytes:Ljava/lang/Long;
       4: areturn

  public java.lang.Long getManagedLedgerOffloadDeletionLagInMillis();
    Code:
       0: aload_0
       1: getfield      #23                 // Field managedLedgerOffloadDeletionLagInMillis:Ljava/lang/Long;
       4: areturn

  public org.apache.pulsar.common.policies.data.OffloadedReadPriority getManagedLedgerOffloadedReadPriority();
    Code:
       0: aload_0
       1: getfield      #22                 // Field managedLedgerOffloadedReadPriority:Lorg/apache/pulsar/common/policies/data/OffloadedReadPriority;
       4: areturn

  public java.lang.String getS3ManagedLedgerOffloadRegion();
    Code:
       0: aload_0
       1: getfield      #21                 // Field s3ManagedLedgerOffloadRegion:Ljava/lang/String;
       4: areturn

  public java.lang.String getS3ManagedLedgerOffloadBucket();
    Code:
       0: aload_0
       1: getfield      #20                 // Field s3ManagedLedgerOffloadBucket:Ljava/lang/String;
       4: areturn

  public java.lang.String getS3ManagedLedgerOffloadServiceEndpoint();
    Code:
       0: aload_0
       1: getfield      #19                 // Field s3ManagedLedgerOffloadServiceEndpoint:Ljava/lang/String;
       4: areturn

  public java.lang.Integer getS3ManagedLedgerOffloadMaxBlockSizeInBytes();
    Code:
       0: aload_0
       1: getfield      #18                 // Field s3ManagedLedgerOffloadMaxBlockSizeInBytes:Ljava/lang/Integer;
       4: areturn

  public java.lang.Integer getS3ManagedLedgerOffloadReadBufferSizeInBytes();
    Code:
       0: aload_0
       1: getfield      #17                 // Field s3ManagedLedgerOffloadReadBufferSizeInBytes:Ljava/lang/Integer;
       4: areturn

  public java.lang.String getS3ManagedLedgerOffloadCredentialId();
    Code:
       0: aload_0
       1: getfield      #16                 // Field s3ManagedLedgerOffloadCredentialId:Ljava/lang/String;
       4: areturn

  public java.lang.String getS3ManagedLedgerOffloadCredentialSecret();
    Code:
       0: aload_0
       1: getfield      #15                 // Field s3ManagedLedgerOffloadCredentialSecret:Ljava/lang/String;
       4: areturn

  public java.lang.String getS3ManagedLedgerOffloadRole();
    Code:
       0: aload_0
       1: getfield      #14                 // Field s3ManagedLedgerOffloadRole:Ljava/lang/String;
       4: areturn

  public java.lang.String getS3ManagedLedgerOffloadRoleSessionName();
    Code:
       0: aload_0
       1: getfield      #13                 // Field s3ManagedLedgerOffloadRoleSessionName:Ljava/lang/String;
       4: areturn

  public java.lang.String getGcsManagedLedgerOffloadRegion();
    Code:
       0: aload_0
       1: getfield      #12                 // Field gcsManagedLedgerOffloadRegion:Ljava/lang/String;
       4: areturn

  public java.lang.String getGcsManagedLedgerOffloadBucket();
    Code:
       0: aload_0
       1: getfield      #11                 // Field gcsManagedLedgerOffloadBucket:Ljava/lang/String;
       4: areturn

  public java.lang.Integer getGcsManagedLedgerOffloadMaxBlockSizeInBytes();
    Code:
       0: aload_0
       1: getfield      #10                 // Field gcsManagedLedgerOffloadMaxBlockSizeInBytes:Ljava/lang/Integer;
       4: areturn

  public java.lang.Integer getGcsManagedLedgerOffloadReadBufferSizeInBytes();
    Code:
       0: aload_0
       1: getfield      #9                  // Field gcsManagedLedgerOffloadReadBufferSizeInBytes:Ljava/lang/Integer;
       4: areturn

  public java.lang.String getGcsManagedLedgerOffloadServiceAccountKeyFile();
    Code:
       0: aload_0
       1: getfield      #8                  // Field gcsManagedLedgerOffloadServiceAccountKeyFile:Ljava/lang/String;
       4: areturn

  public java.lang.String getFileSystemProfilePath();
    Code:
       0: aload_0
       1: getfield      #7                  // Field fileSystemProfilePath:Ljava/lang/String;
       4: areturn

  public java.lang.String getFileSystemURI();
    Code:
       0: aload_0
       1: getfield      #6                  // Field fileSystemURI:Ljava/lang/String;
       4: areturn

  public java.lang.String getManagedLedgerOffloadBucket();
    Code:
       0: aload_0
       1: getfield      #5                  // Field managedLedgerOffloadBucket:Ljava/lang/String;
       4: areturn

  public java.lang.String getManagedLedgerOffloadRegion();
    Code:
       0: aload_0
       1: getfield      #4                  // Field managedLedgerOffloadRegion:Ljava/lang/String;
       4: areturn

  public java.lang.String getManagedLedgerOffloadServiceEndpoint();
    Code:
       0: aload_0
       1: getfield      #3                  // Field managedLedgerOffloadServiceEndpoint:Ljava/lang/String;
       4: areturn

  public java.lang.Integer getManagedLedgerOffloadMaxBlockSizeInBytes();
    Code:
       0: aload_0
       1: getfield      #2                  // Field managedLedgerOffloadMaxBlockSizeInBytes:Ljava/lang/Integer;
       4: areturn

  public java.lang.Integer getManagedLedgerOffloadReadBufferSizeInBytes();
    Code:
       0: aload_0
       1: getfield      #1                  // Field managedLedgerOffloadReadBufferSizeInBytes:Ljava/lang/Integer;
       4: areturn

  public void setOffloadersDirectory(java.lang.String);
    Code:
       0: aload_0
       1: aload_1
       2: putfield      #28                 // Field offloadersDirectory:Ljava/lang/String;
       5: return

  public void setManagedLedgerOffloadDriver(java.lang.String);
    Code:
       0: aload_0
       1: aload_1
       2: putfield      #27                 // Field managedLedgerOffloadDriver:Ljava/lang/String;
       5: return

  public void setManagedLedgerOffloadMaxThreads(java.lang.Integer);
    Code:
       0: aload_0
       1: aload_1
       2: putfield      #26                 // Field managedLedgerOffloadMaxThreads:Ljava/lang/Integer;
       5: return

  public void setManagedLedgerOffloadPrefetchRounds(java.lang.Integer);
    Code:
       0: aload_0
       1: aload_1
       2: putfield      #25                 // Field managedLedgerOffloadPrefetchRounds:Ljava/lang/Integer;
       5: return

  public void setManagedLedgerOffloadThresholdInBytes(java.lang.Long);
    Code:
       0: aload_0
       1: aload_1
       2: putfield      #24                 // Field managedLedgerOffloadThresholdInBytes:Ljava/lang/Long;
       5: return

  public void setManagedLedgerOffloadDeletionLagInMillis(java.lang.Long);
    Code:
       0: aload_0
       1: aload_1
       2: putfield      #23                 // Field managedLedgerOffloadDeletionLagInMillis:Ljava/lang/Long;
       5: return

  public void setManagedLedgerOffloadedReadPriority(org.apache.pulsar.common.policies.data.OffloadedReadPriority);
    Code:
       0: aload_0
       1: aload_1
       2: putfield      #22                 // Field managedLedgerOffloadedReadPriority:Lorg/apache/pulsar/common/policies/data/OffloadedReadPriority;
       5: return

  public void setS3ManagedLedgerOffloadRegion(java.lang.String);
    Code:
       0: aload_0
       1: aload_1
       2: putfield      #21                 // Field s3ManagedLedgerOffloadRegion:Ljava/lang/String;
       5: return

  public void setS3ManagedLedgerOffloadBucket(java.lang.String);
    Code:
       0: aload_0
       1: aload_1
       2: putfield      #20                 // Field s3ManagedLedgerOffloadBucket:Ljava/lang/String;
       5: return

  public void setS3ManagedLedgerOffloadServiceEndpoint(java.lang.String);
    Code:
       0: aload_0
       1: aload_1
       2: putfield      #19                 // Field s3ManagedLedgerOffloadServiceEndpoint:Ljava/lang/String;
       5: return

  public void setS3ManagedLedgerOffloadMaxBlockSizeInBytes(java.lang.Integer);
    Code:
       0: aload_0
       1: aload_1
       2: putfield      #18                 // Field s3ManagedLedgerOffloadMaxBlockSizeInBytes:Ljava/lang/Integer;
       5: return

  public void setS3ManagedLedgerOffloadReadBufferSizeInBytes(java.lang.Integer);
    Code:
       0: aload_0
       1: aload_1
       2: putfield      #17                 // Field s3ManagedLedgerOffloadReadBufferSizeInBytes:Ljava/lang/Integer;
       5: return

  public void setS3ManagedLedgerOffloadCredentialId(java.lang.String);
    Code:
       0: aload_0
       1: aload_1
       2: putfield      #16                 // Field s3ManagedLedgerOffloadCredentialId:Ljava/lang/String;
       5: return

  public void setS3ManagedLedgerOffloadCredentialSecret(java.lang.String);
    Code:
       0: aload_0
       1: aload_1
       2: putfield      #15                 // Field s3ManagedLedgerOffloadCredentialSecret:Ljava/lang/String;
       5: return

  public void setS3ManagedLedgerOffloadRole(java.lang.String);
    Code:
       0: aload_0
       1: aload_1
       2: putfield      #14                 // Field s3ManagedLedgerOffloadRole:Ljava/lang/String;
       5: return

  public void setS3ManagedLedgerOffloadRoleSessionName(java.lang.String);
    Code:
       0: aload_0
       1: aload_1
       2: putfield      #13                 // Field s3ManagedLedgerOffloadRoleSessionName:Ljava/lang/String;
       5: return

  public void setGcsManagedLedgerOffloadRegion(java.lang.String);
    Code:
       0: aload_0
       1: aload_1
       2: putfield      #12                 // Field gcsManagedLedgerOffloadRegion:Ljava/lang/String;
       5: return

  public void setGcsManagedLedgerOffloadBucket(java.lang.String);
    Code:
       0: aload_0
       1: aload_1
       2: putfield      #11                 // Field gcsManagedLedgerOffloadBucket:Ljava/lang/String;
       5: return

  public void setGcsManagedLedgerOffloadMaxBlockSizeInBytes(java.lang.Integer);
    Code:
       0: aload_0
       1: aload_1
       2: putfield      #10                 // Field gcsManagedLedgerOffloadMaxBlockSizeInBytes:Ljava/lang/Integer;
       5: return

  public void setGcsManagedLedgerOffloadReadBufferSizeInBytes(java.lang.Integer);
    Code:
       0: aload_0
       1: aload_1
       2: putfield      #9                  // Field gcsManagedLedgerOffloadReadBufferSizeInBytes:Ljava/lang/Integer;
       5: return

  public void setGcsManagedLedgerOffloadServiceAccountKeyFile(java.lang.String);
    Code:
       0: aload_0
       1: aload_1
       2: putfield      #8                  // Field gcsManagedLedgerOffloadServiceAccountKeyFile:Ljava/lang/String;
       5: return

  public void setFileSystemProfilePath(java.lang.String);
    Code:
       0: aload_0
       1: aload_1
       2: putfield      #7                  // Field fileSystemProfilePath:Ljava/lang/String;
       5: return

  public void setFileSystemURI(java.lang.String);
    Code:
       0: aload_0
       1: aload_1
       2: putfield      #6                  // Field fileSystemURI:Ljava/lang/String;
       5: return

  public void setManagedLedgerOffloadBucket(java.lang.String);
    Code:
       0: aload_0
       1: aload_1
       2: putfield      #5                  // Field managedLedgerOffloadBucket:Ljava/lang/String;
       5: return

  public void setManagedLedgerOffloadRegion(java.lang.String);
    Code:
       0: aload_0
       1: aload_1
       2: putfield      #4                  // Field managedLedgerOffloadRegion:Ljava/lang/String;
       5: return

  public void setManagedLedgerOffloadServiceEndpoint(java.lang.String);
    Code:
       0: aload_0
       1: aload_1
       2: putfield      #3                  // Field managedLedgerOffloadServiceEndpoint:Ljava/lang/String;
       5: return

  public void setManagedLedgerOffloadMaxBlockSizeInBytes(java.lang.Integer);
    Code:
       0: aload_0
       1: aload_1
       2: putfield      #2                  // Field managedLedgerOffloadMaxBlockSizeInBytes:Ljava/lang/Integer;
       5: return

  public void setManagedLedgerOffloadReadBufferSizeInBytes(java.lang.Integer);
    Code:
       0: aload_0
       1: aload_1
       2: putfield      #1                  // Field managedLedgerOffloadReadBufferSizeInBytes:Ljava/lang/Integer;
       5: return

  public boolean equals(java.lang.Object);
    Code:
       0: aload_1
       1: aload_0
       2: if_acmpne     7
       5: iconst_1
       6: ireturn
       7: aload_1
       8: instanceof    #57                 // class org/apache/pulsar/common/policies/data/OffloadPoliciesImpl
      11: ifne          16
      14: iconst_0
      15: ireturn
      16: aload_1
      17: checkcast     #57                 // class org/apache/pulsar/common/policies/data/OffloadPoliciesImpl
      20: astore_2
      21: aload_2
      22: aload_0
      23: invokevirtual #170                // Method canEqual:(Ljava/lang/Object;)Z
      26: ifne          31
      29: iconst_0
      30: ireturn
      31: aload_0
      32: invokevirtual #95                 // Method getManagedLedgerOffloadMaxThreads:()Ljava/lang/Integer;
      35: astore_3
      36: aload_2
      37: invokevirtual #95                 // Method getManagedLedgerOffloadMaxThreads:()Ljava/lang/Integer;
      40: astore        4
      42: aload_3
      43: ifnonnull     54
      46: aload         4
      48: ifnull        65
      51: goto          63
      54: aload_3
      55: aload         4
      57: invokevirtual #171                // Method java/lang/Object.equals:(Ljava/lang/Object;)Z
      60: ifne          65
      63: iconst_0
      64: ireturn
      65: aload_0
      66: invokevirtual #97                 // Method getManagedLedgerOffloadPrefetchRounds:()Ljava/lang/Integer;
      69: astore        5
      71: aload_2
      72: invokevirtual #97                 // Method getManagedLedgerOffloadPrefetchRounds:()Ljava/lang/Integer;
      75: astore        6
      77: aload         5
      79: ifnonnull     90
      82: aload         6
      84: ifnull        102
      87: goto          100
      90: aload         5
      92: aload         6
      94: invokevirtual #171                // Method java/lang/Object.equals:(Ljava/lang/Object;)Z
      97: ifne          102
     100: iconst_0
     101: ireturn
     102: aload_0
     103: invokevirtual #98                 // Method getManagedLedgerOffloadThresholdInBytes:()Ljava/lang/Long;
     106: astore        7
     108: aload_2
     109: invokevirtual #98                 // Method getManagedLedgerOffloadThresholdInBytes:()Ljava/lang/Long;
     112: astore        8
     114: aload         7
     116: ifnonnull     127
     119: aload         8
     121: ifnull        139
     124: goto          137
     127: aload         7
     129: aload         8
     131: invokevirtual #171                // Method java/lang/Object.equals:(Ljava/lang/Object;)Z
     134: ifne          139
     137: iconst_0
     138: ireturn
     139: aload_0
     140: invokevirtual #99                 // Method getManagedLedgerOffloadDeletionLagInMillis:()Ljava/lang/Long;
     143: astore        9
     145: aload_2
     146: invokevirtual #99                 // Method getManagedLedgerOffloadDeletionLagInMillis:()Ljava/lang/Long;
     149: astore        10
     151: aload         9
     153: ifnonnull     164
     156: aload         10
     158: ifnull        176
     161: goto          174
     164: aload         9
     166: aload         10
     168: invokevirtual #171                // Method java/lang/Object.equals:(Ljava/lang/Object;)Z
     171: ifne          176
     174: iconst_0
     175: ireturn
     176: aload_0
     177: invokevirtual #107                // Method getS3ManagedLedgerOffloadMaxBlockSizeInBytes:()Ljava/lang/Integer;
     180: astore        11
     182: aload_2
     183: invokevirtual #107                // Method getS3ManagedLedgerOffloadMaxBlockSizeInBytes:()Ljava/lang/Integer;
     186: astore        12
     188: aload         11
     190: ifnonnull     201
     193: aload         12
     195: ifnull        213
     198: goto          211
     201: aload         11
     203: aload         12
     205: invokevirtual #171                // Method java/lang/Object.equals:(Ljava/lang/Object;)Z
     208: ifne          213
     211: iconst_0
     212: ireturn
     213: aload_0
     214: invokevirtual #117                // Method getS3ManagedLedgerOffloadReadBufferSizeInBytes:()Ljava/lang/Integer;
     217: astore        13
     219: aload_2
     220: invokevirtual #117                // Method getS3ManagedLedgerOffloadReadBufferSizeInBytes:()Ljava/lang/Integer;
     223: astore        14
     225: aload         13
     227: ifnonnull     238
     230: aload         14
     232: ifnull        250
     235: goto          248
     238: aload         13
     240: aload         14
     242: invokevirtual #171                // Method java/lang/Object.equals:(Ljava/lang/Object;)Z
     245: ifne          250
     248: iconst_0
     249: ireturn
     250: aload_0
     251: invokevirtual #123                // Method getGcsManagedLedgerOffloadMaxBlockSizeInBytes:()Ljava/lang/Integer;
     254: astore        15
     256: aload_2
     257: invokevirtual #123                // Method getGcsManagedLedgerOffloadMaxBlockSizeInBytes:()Ljava/lang/Integer;
     260: astore        16
     262: aload         15
     264: ifnonnull     275
     267: aload         16
     269: ifnull        287
     272: goto          285
     275: aload         15
     277: aload         16
     279: invokevirtual #171                // Method java/lang/Object.equals:(Ljava/lang/Object;)Z
     282: ifne          287
     285: iconst_0
     286: ireturn
     287: aload_0
     288: invokevirtual #125                // Method getGcsManagedLedgerOffloadReadBufferSizeInBytes:()Ljava/lang/Integer;
     291: astore        17
     293: aload_2
     294: invokevirtual #125                // Method getGcsManagedLedgerOffloadReadBufferSizeInBytes:()Ljava/lang/Integer;
     297: astore        18
     299: aload         17
     301: ifnonnull     312
     304: aload         18
     306: ifnull        324
     309: goto          322
     312: aload         17
     314: aload         18
     316: invokevirtual #171                // Method java/lang/Object.equals:(Ljava/lang/Object;)Z
     319: ifne          324
     322: iconst_0
     323: ireturn
     324: aload_0
     325: invokevirtual #139                // Method getManagedLedgerOffloadMaxBlockSizeInBytes:()Ljava/lang/Integer;
     328: astore        19
     330: aload_2
     331: invokevirtual #139                // Method getManagedLedgerOffloadMaxBlockSizeInBytes:()Ljava/lang/Integer;
     334: astore        20
     336: aload         19
     338: ifnonnull     349
     341: aload         20
     343: ifnull        361
     346: goto          359
     349: aload         19
     351: aload         20
     353: invokevirtual #171                // Method java/lang/Object.equals:(Ljava/lang/Object;)Z
     356: ifne          361
     359: iconst_0
     360: ireturn
     361: aload_0
     362: invokevirtual #141                // Method getManagedLedgerOffloadReadBufferSizeInBytes:()Ljava/lang/Integer;
     365: astore        21
     367: aload_2
     368: invokevirtual #141                // Method getManagedLedgerOffloadReadBufferSizeInBytes:()Ljava/lang/Integer;
     371: astore        22
     373: aload         21
     375: ifnonnull     386
     378: aload         22
     380: ifnull        398
     383: goto          396
     386: aload         21
     388: aload         22
     390: invokevirtual #171                // Method java/lang/Object.equals:(Ljava/lang/Object;)Z
     393: ifne          398
     396: iconst_0
     397: ireturn
     398: aload_0
     399: invokevirtual #91                 // Method getOffloadersDirectory:()Ljava/lang/String;
     402: astore        23
     404: aload_2
     405: invokevirtual #91                 // Method getOffloadersDirectory:()Ljava/lang/String;
     408: astore        24
     410: aload         23
     412: ifnonnull     423
     415: aload         24
     417: ifnull        435
     420: goto          433
     423: aload         23
     425: aload         24
     427: invokevirtual #171                // Method java/lang/Object.equals:(Ljava/lang/Object;)Z
     430: ifne          435
     433: iconst_0
     434: ireturn
     435: aload_0
     436: invokevirtual #93                 // Method getManagedLedgerOffloadDriver:()Ljava/lang/String;
     439: astore        25
     441: aload_2
     442: invokevirtual #93                 // Method getManagedLedgerOffloadDriver:()Ljava/lang/String;
     445: astore        26
     447: aload         25
     449: ifnonnull     460
     452: aload         26
     454: ifnull        472
     457: goto          470
     460: aload         25
     462: aload         26
     464: invokevirtual #171                // Method java/lang/Object.equals:(Ljava/lang/Object;)Z
     467: ifne          472
     470: iconst_0
     471: ireturn
     472: aload_0
     473: invokevirtual #88                 // Method getManagedLedgerOffloadedReadPriority:()Lorg/apache/pulsar/common/policies/data/OffloadedReadPriority;
     476: astore        27
     478: aload_2
     479: invokevirtual #88                 // Method getManagedLedgerOffloadedReadPriority:()Lorg/apache/pulsar/common/policies/data/OffloadedReadPriority;
     482: astore        28
     484: aload         27
     486: ifnonnull     497
     489: aload         28
     491: ifnull        509
     494: goto          507
     497: aload         27
     499: aload         28
     501: invokevirtual #171                // Method java/lang/Object.equals:(Ljava/lang/Object;)Z
     504: ifne          509
     507: iconst_0
     508: ireturn
     509: aload_0
     510: invokevirtual #101                // Method getS3ManagedLedgerOffloadRegion:()Ljava/lang/String;
     513: astore        29
     515: aload_2
     516: invokevirtual #101                // Method getS3ManagedLedgerOffloadRegion:()Ljava/lang/String;
     519: astore        30
     521: aload         29
     523: ifnonnull     534
     526: aload         30
     528: ifnull        546
     531: goto          544
     534: aload         29
     536: aload         30
     538: invokevirtual #171                // Method java/lang/Object.equals:(Ljava/lang/Object;)Z
     541: ifne          546
     544: iconst_0
     545: ireturn
     546: aload_0
     547: invokevirtual #103                // Method getS3ManagedLedgerOffloadBucket:()Ljava/lang/String;
     550: astore        31
     552: aload_2
     553: invokevirtual #103                // Method getS3ManagedLedgerOffloadBucket:()Ljava/lang/String;
     556: astore        32
     558: aload         31
     560: ifnonnull     571
     563: aload         32
     565: ifnull        583
     568: goto          581
     571: aload         31
     573: aload         32
     575: invokevirtual #171                // Method java/lang/Object.equals:(Ljava/lang/Object;)Z
     578: ifne          583
     581: iconst_0
     582: ireturn
     583: aload_0
     584: invokevirtual #105                // Method getS3ManagedLedgerOffloadServiceEndpoint:()Ljava/lang/String;
     587: astore        33
     589: aload_2
     590: invokevirtual #105                // Method getS3ManagedLedgerOffloadServiceEndpoint:()Ljava/lang/String;
     593: astore        34
     595: aload         33
     597: ifnonnull     608
     600: aload         34
     602: ifnull        620
     605: goto          618
     608: aload         33
     610: aload         34
     612: invokevirtual #171                // Method java/lang/Object.equals:(Ljava/lang/Object;)Z
     615: ifne          620
     618: iconst_0
     619: ireturn
     620: aload_0
     621: invokevirtual #109                // Method getS3ManagedLedgerOffloadCredentialId:()Ljava/lang/String;
     624: astore        35
     626: aload_2
     627: invokevirtual #109                // Method getS3ManagedLedgerOffloadCredentialId:()Ljava/lang/String;
     630: astore        36
     632: aload         35
     634: ifnonnull     645
     637: aload         36
     639: ifnull        657
     642: goto          655
     645: aload         35
     647: aload         36
     649: invokevirtual #171                // Method java/lang/Object.equals:(Ljava/lang/Object;)Z
     652: ifne          657
     655: iconst_0
     656: ireturn
     657: aload_0
     658: invokevirtual #111                // Method getS3ManagedLedgerOffloadCredentialSecret:()Ljava/lang/String;
     661: astore        37
     663: aload_2
     664: invokevirtual #111                // Method getS3ManagedLedgerOffloadCredentialSecret:()Ljava/lang/String;
     667: astore        38
     669: aload         37
     671: ifnonnull     682
     674: aload         38
     676: ifnull        694
     679: goto          692
     682: aload         37
     684: aload         38
     686: invokevirtual #171                // Method java/lang/Object.equals:(Ljava/lang/Object;)Z
     689: ifne          694
     692: iconst_0
     693: ireturn
     694: aload_0
     695: invokevirtual #113                // Method getS3ManagedLedgerOffloadRole:()Ljava/lang/String;
     698: astore        39
     700: aload_2
     701: invokevirtual #113                // Method getS3ManagedLedgerOffloadRole:()Ljava/lang/String;
     704: astore        40
     706: aload         39
     708: ifnonnull     719
     711: aload         40
     713: ifnull        731
     716: goto          729
     719: aload         39
     721: aload         40
     723: invokevirtual #171                // Method java/lang/Object.equals:(Ljava/lang/Object;)Z
     726: ifne          731
     729: iconst_0
     730: ireturn
     731: aload_0
     732: invokevirtual #115                // Method getS3ManagedLedgerOffloadRoleSessionName:()Ljava/lang/String;
     735: astore        41
     737: aload_2
     738: invokevirtual #115                // Method getS3ManagedLedgerOffloadRoleSessionName:()Ljava/lang/String;
     741: astore        42
     743: aload         41
     745: ifnonnull     756
     748: aload         42
     750: ifnull        768
     753: goto          766
     756: aload         41
     758: aload         42
     760: invokevirtual #171                // Method java/lang/Object.equals:(Ljava/lang/Object;)Z
     763: ifne          768
     766: iconst_0
     767: ireturn
     768: aload_0
     769: invokevirtual #119                // Method getGcsManagedLedgerOffloadRegion:()Ljava/lang/String;
     772: astore        43
     774: aload_2
     775: invokevirtual #119                // Method getGcsManagedLedgerOffloadRegion:()Ljava/lang/String;
     778: astore        44
     780: aload         43
     782: ifnonnull     793
     785: aload         44
     787: ifnull        805
     790: goto          803
     793: aload         43
     795: aload         44
     797: invokevirtual #171                // Method java/lang/Object.equals:(Ljava/lang/Object;)Z
     800: ifne          805
     803: iconst_0
     804: ireturn
     805: aload_0
     806: invokevirtual #121                // Method getGcsManagedLedgerOffloadBucket:()Ljava/lang/String;
     809: astore        45
     811: aload_2
     812: invokevirtual #121                // Method getGcsManagedLedgerOffloadBucket:()Ljava/lang/String;
     815: astore        46
     817: aload         45
     819: ifnonnull     830
     822: aload         46
     824: ifnull        842
     827: goto          840
     830: aload         45
     832: aload         46
     834: invokevirtual #171                // Method java/lang/Object.equals:(Ljava/lang/Object;)Z
     837: ifne          842
     840: iconst_0
     841: ireturn
     842: aload_0
     843: invokevirtual #127                // Method getGcsManagedLedgerOffloadServiceAccountKeyFile:()Ljava/lang/String;
     846: astore        47
     848: aload_2
     849: invokevirtual #127                // Method getGcsManagedLedgerOffloadServiceAccountKeyFile:()Ljava/lang/String;
     852: astore        48
     854: aload         47
     856: ifnonnull     867
     859: aload         48
     861: ifnull        879
     864: goto          877
     867: aload         47
     869: aload         48
     871: invokevirtual #171                // Method java/lang/Object.equals:(Ljava/lang/Object;)Z
     874: ifne          879
     877: iconst_0
     878: ireturn
     879: aload_0
     880: invokevirtual #129                // Method getFileSystemProfilePath:()Ljava/lang/String;
     883: astore        49
     885: aload_2
     886: invokevirtual #129                // Method getFileSystemProfilePath:()Ljava/lang/String;
     889: astore        50
     891: aload         49
     893: ifnonnull     904
     896: aload         50
     898: ifnull        916
     901: goto          914
     904: aload         49
     906: aload         50
     908: invokevirtual #171                // Method java/lang/Object.equals:(Ljava/lang/Object;)Z
     911: ifne          916
     914: iconst_0
     915: ireturn
     916: aload_0
     917: invokevirtual #131                // Method getFileSystemURI:()Ljava/lang/String;
     920: astore        51
     922: aload_2
     923: invokevirtual #131                // Method getFileSystemURI:()Ljava/lang/String;
     926: astore        52
     928: aload         51
     930: ifnonnull     941
     933: aload         52
     935: ifnull        953
     938: goto          951
     941: aload         51
     943: aload         52
     945: invokevirtual #171                // Method java/lang/Object.equals:(Ljava/lang/Object;)Z
     948: ifne          953
     951: iconst_0
     952: ireturn
     953: aload_0
     954: invokevirtual #133                // Method getManagedLedgerOffloadBucket:()Ljava/lang/String;
     957: astore        53
     959: aload_2
     960: invokevirtual #133                // Method getManagedLedgerOffloadBucket:()Ljava/lang/String;
     963: astore        54
     965: aload         53
     967: ifnonnull     978
     970: aload         54
     972: ifnull        990
     975: goto          988
     978: aload         53
     980: aload         54
     982: invokevirtual #171                // Method java/lang/Object.equals:(Ljava/lang/Object;)Z
     985: ifne          990
     988: iconst_0
     989: ireturn
     990: aload_0
     991: invokevirtual #135                // Method getManagedLedgerOffloadRegion:()Ljava/lang/String;
     994: astore        55
     996: aload_2
     997: invokevirtual #135                // Method getManagedLedgerOffloadRegion:()Ljava/lang/String;
    1000: astore        56
    1002: aload         55
    1004: ifnonnull     1015
    1007: aload         56
    1009: ifnull        1027
    1012: goto          1025
    1015: aload         55
    1017: aload         56
    1019: invokevirtual #171                // Method java/lang/Object.equals:(Ljava/lang/Object;)Z
    1022: ifne          1027
    1025: iconst_0
    1026: ireturn
    1027: aload_0
    1028: invokevirtual #137                // Method getManagedLedgerOffloadServiceEndpoint:()Ljava/lang/String;
    1031: astore        57
    1033: aload_2
    1034: invokevirtual #137                // Method getManagedLedgerOffloadServiceEndpoint:()Ljava/lang/String;
    1037: astore        58
    1039: aload         57
    1041: ifnonnull     1052
    1044: aload         58
    1046: ifnull        1064
    1049: goto          1062
    1052: aload         57
    1054: aload         58
    1056: invokevirtual #171                // Method java/lang/Object.equals:(Ljava/lang/Object;)Z
    1059: ifne          1064
    1062: iconst_0
    1063: ireturn
    1064: iconst_1
    1065: ireturn

  protected boolean canEqual(java.lang.Object);
    Code:
       0: aload_1
       1: instanceof    #57                 // class org/apache/pulsar/common/policies/data/OffloadPoliciesImpl
       4: ireturn

  public int hashCode();
    Code:
       0: bipush        59
       2: istore_1
       3: iconst_1
       4: istore_2
       5: aload_0
       6: invokevirtual #95                 // Method getManagedLedgerOffloadMaxThreads:()Ljava/lang/Integer;
       9: astore_3
      10: iload_2
      11: bipush        59
      13: imul
      14: aload_3
      15: ifnonnull     23
      18: bipush        43
      20: goto          27
      23: aload_3
      24: invokevirtual #172                // Method java/lang/Object.hashCode:()I
      27: iadd
      28: istore_2
      29: aload_0
      30: invokevirtual #97                 // Method getManagedLedgerOffloadPrefetchRounds:()Ljava/lang/Integer;
      33: astore        4
      35: iload_2
      36: bipush        59
      38: imul
      39: aload         4
      41: ifnonnull     49
      44: bipush        43
      46: goto          54
      49: aload         4
      51: invokevirtual #172                // Method java/lang/Object.hashCode:()I
      54: iadd
      55: istore_2
      56: aload_0
      57: invokevirtual #98                 // Method getManagedLedgerOffloadThresholdInBytes:()Ljava/lang/Long;
      60: astore        5
      62: iload_2
      63: bipush        59
      65: imul
      66: aload         5
      68: ifnonnull     76
      71: bipush        43
      73: goto          81
      76: aload         5
      78: invokevirtual #172                // Method java/lang/Object.hashCode:()I
      81: iadd
      82: istore_2
      83: aload_0
      84: invokevirtual #99                 // Method getManagedLedgerOffloadDeletionLagInMillis:()Ljava/lang/Long;
      87: astore        6
      89: iload_2
      90: bipush        59
      92: imul
      93: aload         6
      95: ifnonnull     103
      98: bipush        43
     100: goto          108
     103: aload         6
     105: invokevirtual #172                // Method java/lang/Object.hashCode:()I
     108: iadd
     109: istore_2
     110: aload_0
     111: invokevirtual #107                // Method getS3ManagedLedgerOffloadMaxBlockSizeInBytes:()Ljava/lang/Integer;
     114: astore        7
     116: iload_2
     117: bipush        59
     119: imul
     120: aload         7
     122: ifnonnull     130
     125: bipush        43
     127: goto          135
     130: aload         7
     132: invokevirtual #172                // Method java/lang/Object.hashCode:()I
     135: iadd
     136: istore_2
     137: aload_0
     138: invokevirtual #117                // Method getS3ManagedLedgerOffloadReadBufferSizeInBytes:()Ljava/lang/Integer;
     141: astore        8
     143: iload_2
     144: bipush        59
     146: imul
     147: aload         8
     149: ifnonnull     157
     152: bipush        43
     154: goto          162
     157: aload         8
     159: invokevirtual #172                // Method java/lang/Object.hashCode:()I
     162: iadd
     163: istore_2
     164: aload_0
     165: invokevirtual #123                // Method getGcsManagedLedgerOffloadMaxBlockSizeInBytes:()Ljava/lang/Integer;
     168: astore        9
     170: iload_2
     171: bipush        59
     173: imul
     174: aload         9
     176: ifnonnull     184
     179: bipush        43
     181: goto          189
     184: aload         9
     186: invokevirtual #172                // Method java/lang/Object.hashCode:()I
     189: iadd
     190: istore_2
     191: aload_0
     192: invokevirtual #125                // Method getGcsManagedLedgerOffloadReadBufferSizeInBytes:()Ljava/lang/Integer;
     195: astore        10
     197: iload_2
     198: bipush        59
     200: imul
     201: aload         10
     203: ifnonnull     211
     206: bipush        43
     208: goto          216
     211: aload         10
     213: invokevirtual #172                // Method java/lang/Object.hashCode:()I
     216: iadd
     217: istore_2
     218: aload_0
     219: invokevirtual #139                // Method getManagedLedgerOffloadMaxBlockSizeInBytes:()Ljava/lang/Integer;
     222: astore        11
     224: iload_2
     225: bipush        59
     227: imul
     228: aload         11
     230: ifnonnull     238
     233: bipush        43
     235: goto          243
     238: aload         11
     240: invokevirtual #172                // Method java/lang/Object.hashCode:()I
     243: iadd
     244: istore_2
     245: aload_0
     246: invokevirtual #141                // Method getManagedLedgerOffloadReadBufferSizeInBytes:()Ljava/lang/Integer;
     249: astore        12
     251: iload_2
     252: bipush        59
     254: imul
     255: aload         12
     257: ifnonnull     265
     260: bipush        43
     262: goto          270
     265: aload         12
     267: invokevirtual #172                // Method java/lang/Object.hashCode:()I
     270: iadd
     271: istore_2
     272: aload_0
     273: invokevirtual #91                 // Method getOffloadersDirectory:()Ljava/lang/String;
     276: astore        13
     278: iload_2
     279: bipush        59
     281: imul
     282: aload         13
     284: ifnonnull     292
     287: bipush        43
     289: goto          297
     292: aload         13
     294: invokevirtual #172                // Method java/lang/Object.hashCode:()I
     297: iadd
     298: istore_2
     299: aload_0
     300: invokevirtual #93                 // Method getManagedLedgerOffloadDriver:()Ljava/lang/String;
     303: astore        14
     305: iload_2
     306: bipush        59
     308: imul
     309: aload         14
     311: ifnonnull     319
     314: bipush        43
     316: goto          324
     319: aload         14
     321: invokevirtual #172                // Method java/lang/Object.hashCode:()I
     324: iadd
     325: istore_2
     326: aload_0
     327: invokevirtual #88                 // Method getManagedLedgerOffloadedReadPriority:()Lorg/apache/pulsar/common/policies/data/OffloadedReadPriority;
     330: astore        15
     332: iload_2
     333: bipush        59
     335: imul
     336: aload         15
     338: ifnonnull     346
     341: bipush        43
     343: goto          351
     346: aload         15
     348: invokevirtual #172                // Method java/lang/Object.hashCode:()I
     351: iadd
     352: istore_2
     353: aload_0
     354: invokevirtual #101                // Method getS3ManagedLedgerOffloadRegion:()Ljava/lang/String;
     357: astore        16
     359: iload_2
     360: bipush        59
     362: imul
     363: aload         16
     365: ifnonnull     373
     368: bipush        43
     370: goto          378
     373: aload         16
     375: invokevirtual #172                // Method java/lang/Object.hashCode:()I
     378: iadd
     379: istore_2
     380: aload_0
     381: invokevirtual #103                // Method getS3ManagedLedgerOffloadBucket:()Ljava/lang/String;
     384: astore        17
     386: iload_2
     387: bipush        59
     389: imul
     390: aload         17
     392: ifnonnull     400
     395: bipush        43
     397: goto          405
     400: aload         17
     402: invokevirtual #172                // Method java/lang/Object.hashCode:()I
     405: iadd
     406: istore_2
     407: aload_0
     408: invokevirtual #105                // Method getS3ManagedLedgerOffloadServiceEndpoint:()Ljava/lang/String;
     411: astore        18
     413: iload_2
     414: bipush        59
     416: imul
     417: aload         18
     419: ifnonnull     427
     422: bipush        43
     424: goto          432
     427: aload         18
     429: invokevirtual #172                // Method java/lang/Object.hashCode:()I
     432: iadd
     433: istore_2
     434: aload_0
     435: invokevirtual #109                // Method getS3ManagedLedgerOffloadCredentialId:()Ljava/lang/String;
     438: astore        19
     440: iload_2
     441: bipush        59
     443: imul
     444: aload         19
     446: ifnonnull     454
     449: bipush        43
     451: goto          459
     454: aload         19
     456: invokevirtual #172                // Method java/lang/Object.hashCode:()I
     459: iadd
     460: istore_2
     461: aload_0
     462: invokevirtual #111                // Method getS3ManagedLedgerOffloadCredentialSecret:()Ljava/lang/String;
     465: astore        20
     467: iload_2
     468: bipush        59
     470: imul
     471: aload         20
     473: ifnonnull     481
     476: bipush        43
     478: goto          486
     481: aload         20
     483: invokevirtual #172                // Method java/lang/Object.hashCode:()I
     486: iadd
     487: istore_2
     488: aload_0
     489: invokevirtual #113                // Method getS3ManagedLedgerOffloadRole:()Ljava/lang/String;
     492: astore        21
     494: iload_2
     495: bipush        59
     497: imul
     498: aload         21
     500: ifnonnull     508
     503: bipush        43
     505: goto          513
     508: aload         21
     510: invokevirtual #172                // Method java/lang/Object.hashCode:()I
     513: iadd
     514: istore_2
     515: aload_0
     516: invokevirtual #115                // Method getS3ManagedLedgerOffloadRoleSessionName:()Ljava/lang/String;
     519: astore        22
     521: iload_2
     522: bipush        59
     524: imul
     525: aload         22
     527: ifnonnull     535
     530: bipush        43
     532: goto          540
     535: aload         22
     537: invokevirtual #172                // Method java/lang/Object.hashCode:()I
     540: iadd
     541: istore_2
     542: aload_0
     543: invokevirtual #119                // Method getGcsManagedLedgerOffloadRegion:()Ljava/lang/String;
     546: astore        23
     548: iload_2
     549: bipush        59
     551: imul
     552: aload         23
     554: ifnonnull     562
     557: bipush        43
     559: goto          567
     562: aload         23
     564: invokevirtual #172                // Method java/lang/Object.hashCode:()I
     567: iadd
     568: istore_2
     569: aload_0
     570: invokevirtual #121                // Method getGcsManagedLedgerOffloadBucket:()Ljava/lang/String;
     573: astore        24
     575: iload_2
     576: bipush        59
     578: imul
     579: aload         24
     581: ifnonnull     589
     584: bipush        43
     586: goto          594
     589: aload         24
     591: invokevirtual #172                // Method java/lang/Object.hashCode:()I
     594: iadd
     595: istore_2
     596: aload_0
     597: invokevirtual #127                // Method getGcsManagedLedgerOffloadServiceAccountKeyFile:()Ljava/lang/String;
     600: astore        25
     602: iload_2
     603: bipush        59
     605: imul
     606: aload         25
     608: ifnonnull     616
     611: bipush        43
     613: goto          621
     616: aload         25
     618: invokevirtual #172                // Method java/lang/Object.hashCode:()I
     621: iadd
     622: istore_2
     623: aload_0
     624: invokevirtual #129                // Method getFileSystemProfilePath:()Ljava/lang/String;
     627: astore        26
     629: iload_2
     630: bipush        59
     632: imul
     633: aload         26
     635: ifnonnull     643
     638: bipush        43
     640: goto          648
     643: aload         26
     645: invokevirtual #172                // Method java/lang/Object.hashCode:()I
     648: iadd
     649: istore_2
     650: aload_0
     651: invokevirtual #131                // Method getFileSystemURI:()Ljava/lang/String;
     654: astore        27
     656: iload_2
     657: bipush        59
     659: imul
     660: aload         27
     662: ifnonnull     670
     665: bipush        43
     667: goto          675
     670: aload         27
     672: invokevirtual #172                // Method java/lang/Object.hashCode:()I
     675: iadd
     676: istore_2
     677: aload_0
     678: invokevirtual #133                // Method getManagedLedgerOffloadBucket:()Ljava/lang/String;
     681: astore        28
     683: iload_2
     684: bipush        59
     686: imul
     687: aload         28
     689: ifnonnull     697
     692: bipush        43
     694: goto          702
     697: aload         28
     699: invokevirtual #172                // Method java/lang/Object.hashCode:()I
     702: iadd
     703: istore_2
     704: aload_0
     705: invokevirtual #135                // Method getManagedLedgerOffloadRegion:()Ljava/lang/String;
     708: astore        29
     710: iload_2
     711: bipush        59
     713: imul
     714: aload         29
     716: ifnonnull     724
     719: bipush        43
     721: goto          729
     724: aload         29
     726: invokevirtual #172                // Method java/lang/Object.hashCode:()I
     729: iadd
     730: istore_2
     731: aload_0
     732: invokevirtual #137                // Method getManagedLedgerOffloadServiceEndpoint:()Ljava/lang/String;
     735: astore        30
     737: iload_2
     738: bipush        59
     740: imul
     741: aload         30
     743: ifnonnull     751
     746: bipush        43
     748: goto          756
     751: aload         30
     753: invokevirtual #172                // Method java/lang/Object.hashCode:()I
     756: iadd
     757: istore_2
     758: iload_2
     759: ireturn

  public java.lang.String toString();
    Code:
       0: new           #142                // class java/lang/StringBuilder
       3: dup
       4: invokespecial #143                // Method java/lang/StringBuilder."<init>":()V
       7: ldc           #173                // String OffloadPoliciesImpl(offloadersDirectory=
       9: invokevirtual #145                // Method java/lang/StringBuilder.append:(Ljava/lang/String;)Ljava/lang/StringBuilder;
      12: aload_0
      13: invokevirtual #91                 // Method getOffloadersDirectory:()Ljava/lang/String;
      16: invokevirtual #145                // Method java/lang/StringBuilder.append:(Ljava/lang/String;)Ljava/lang/StringBuilder;
      19: ldc           #174                // String , managedLedgerOffloadDriver=
      21: invokevirtual #145                // Method java/lang/StringBuilder.append:(Ljava/lang/String;)Ljava/lang/StringBuilder;
      24: aload_0
      25: invokevirtual #93                 // Method getManagedLedgerOffloadDriver:()Ljava/lang/String;
      28: invokevirtual #145                // Method java/lang/StringBuilder.append:(Ljava/lang/String;)Ljava/lang/StringBuilder;
      31: ldc           #175                // String , managedLedgerOffloadMaxThreads=
      33: invokevirtual #145                // Method java/lang/StringBuilder.append:(Ljava/lang/String;)Ljava/lang/StringBuilder;
      36: aload_0
      37: invokevirtual #95                 // Method getManagedLedgerOffloadMaxThreads:()Ljava/lang/Integer;
      40: invokevirtual #146                // Method java/lang/StringBuilder.append:(Ljava/lang/Object;)Ljava/lang/StringBuilder;
      43: ldc           #176                // String , managedLedgerOffloadPrefetchRounds=
      45: invokevirtual #145                // Method java/lang/StringBuilder.append:(Ljava/lang/String;)Ljava/lang/StringBuilder;
      48: aload_0
      49: invokevirtual #97                 // Method getManagedLedgerOffloadPrefetchRounds:()Ljava/lang/Integer;
      52: invokevirtual #146                // Method java/lang/StringBuilder.append:(Ljava/lang/Object;)Ljava/lang/StringBuilder;
      55: ldc           #177                // String , managedLedgerOffloadThresholdInBytes=
      57: invokevirtual #145                // Method java/lang/StringBuilder.append:(Ljava/lang/String;)Ljava/lang/StringBuilder;
      60: aload_0
      61: invokevirtual #98                 // Method getManagedLedgerOffloadThresholdInBytes:()Ljava/lang/Long;
      64: invokevirtual #146                // Method java/lang/StringBuilder.append:(Ljava/lang/Object;)Ljava/lang/StringBuilder;
      67: ldc           #178                // String , managedLedgerOffloadDeletionLagInMillis=
      69: invokevirtual #145                // Method java/lang/StringBuilder.append:(Ljava/lang/String;)Ljava/lang/StringBuilder;
      72: aload_0
      73: invokevirtual #99                 // Method getManagedLedgerOffloadDeletionLagInMillis:()Ljava/lang/Long;
      76: invokevirtual #146                // Method java/lang/StringBuilder.append:(Ljava/lang/Object;)Ljava/lang/StringBuilder;
      79: ldc           #179                // String , managedLedgerOffloadedReadPriority=
      81: invokevirtual #145                // Method java/lang/StringBuilder.append:(Ljava/lang/String;)Ljava/lang/StringBuilder;
      84: aload_0
      85: invokevirtual #88                 // Method getManagedLedgerOffloadedReadPriority:()Lorg/apache/pulsar/common/policies/data/OffloadedReadPriority;
      88: invokevirtual #146                // Method java/lang/StringBuilder.append:(Ljava/lang/Object;)Ljava/lang/StringBuilder;
      91: ldc           #180                // String , s3ManagedLedgerOffloadRegion=
      93: invokevirtual #145                // Method java/lang/StringBuilder.append:(Ljava/lang/String;)Ljava/lang/StringBuilder;
      96: aload_0
      97: invokevirtual #101                // Method getS3ManagedLedgerOffloadRegion:()Ljava/lang/String;
     100: invokevirtual #145                // Method java/lang/StringBuilder.append:(Ljava/lang/String;)Ljava/lang/StringBuilder;
     103: ldc           #181                // String , s3ManagedLedgerOffloadBucket=
     105: invokevirtual #145                // Method java/lang/StringBuilder.append:(Ljava/lang/String;)Ljava/lang/StringBuilder;
     108: aload_0
     109: invokevirtual #103                // Method getS3ManagedLedgerOffloadBucket:()Ljava/lang/String;
     112: invokevirtual #145                // Method java/lang/StringBuilder.append:(Ljava/lang/String;)Ljava/lang/StringBuilder;
     115: ldc           #182                // String , s3ManagedLedgerOffloadServiceEndpoint=
     117: invokevirtual #145                // Method java/lang/StringBuilder.append:(Ljava/lang/String;)Ljava/lang/StringBuilder;
     120: aload_0
     121: invokevirtual #105                // Method getS3ManagedLedgerOffloadServiceEndpoint:()Ljava/lang/String;
     124: invokevirtual #145                // Method java/lang/StringBuilder.append:(Ljava/lang/String;)Ljava/lang/StringBuilder;
     127: ldc           #183                // String , s3ManagedLedgerOffloadMaxBlockSizeInBytes=
     129: invokevirtual #145                // Method java/lang/StringBuilder.append:(Ljava/lang/String;)Ljava/lang/StringBuilder;
     132: aload_0
     133: invokevirtual #107                // Method getS3ManagedLedgerOffloadMaxBlockSizeInBytes:()Ljava/lang/Integer;
     136: invokevirtual #146                // Method java/lang/StringBuilder.append:(Ljava/lang/Object;)Ljava/lang/StringBuilder;
     139: ldc           #184                // String , s3ManagedLedgerOffloadReadBufferSizeInBytes=
     141: invokevirtual #145                // Method java/lang/StringBuilder.append:(Ljava/lang/String;)Ljava/lang/StringBuilder;
     144: aload_0
     145: invokevirtual #117                // Method getS3ManagedLedgerOffloadReadBufferSizeInBytes:()Ljava/lang/Integer;
     148: invokevirtual #146                // Method java/lang/StringBuilder.append:(Ljava/lang/Object;)Ljava/lang/StringBuilder;
     151: ldc           #185                // String , s3ManagedLedgerOffloadCredentialId=
     153: invokevirtual #145                // Method java/lang/StringBuilder.append:(Ljava/lang/String;)Ljava/lang/StringBuilder;
     156: aload_0
     157: invokevirtual #109                // Method getS3ManagedLedgerOffloadCredentialId:()Ljava/lang/String;
     160: invokevirtual #145                // Method java/lang/StringBuilder.append:(Ljava/lang/String;)Ljava/lang/StringBuilder;
     163: ldc           #186                // String , s3ManagedLedgerOffloadCredentialSecret=
     165: invokevirtual #145                // Method java/lang/StringBuilder.append:(Ljava/lang/String;)Ljava/lang/StringBuilder;
     168: aload_0
     169: invokevirtual #111                // Method getS3ManagedLedgerOffloadCredentialSecret:()Ljava/lang/String;
     172: invokevirtual #145                // Method java/lang/StringBuilder.append:(Ljava/lang/String;)Ljava/lang/StringBuilder;
     175: ldc           #187                // String , s3ManagedLedgerOffloadRole=
     177: invokevirtual #145                // Method java/lang/StringBuilder.append:(Ljava/lang/String;)Ljava/lang/StringBuilder;
     180: aload_0
     181: invokevirtual #113                // Method getS3ManagedLedgerOffloadRole:()Ljava/lang/String;
     184: invokevirtual #145                // Method java/lang/StringBuilder.append:(Ljava/lang/String;)Ljava/lang/StringBuilder;
     187: ldc           #188                // String , s3ManagedLedgerOffloadRoleSessionName=
     189: invokevirtual #145                // Method java/lang/StringBuilder.append:(Ljava/lang/String;)Ljava/lang/StringBuilder;
     192: aload_0
     193: invokevirtual #115                // Method getS3ManagedLedgerOffloadRoleSessionName:()Ljava/lang/String;
     196: invokevirtual #145                // Method java/lang/StringBuilder.append:(Ljava/lang/String;)Ljava/lang/StringBuilder;
     199: ldc           #189                // String , gcsManagedLedgerOffloadRegion=
     201: invokevirtual #145                // Method java/lang/StringBuilder.append:(Ljava/lang/String;)Ljava/lang/StringBuilder;
     204: aload_0
     205: invokevirtual #119                // Method getGcsManagedLedgerOffloadRegion:()Ljava/lang/String;
     208: invokevirtual #145                // Method java/lang/StringBuilder.append:(Ljava/lang/String;)Ljava/lang/StringBuilder;
     211: ldc           #190                // String , gcsManagedLedgerOffloadBucket=
     213: invokevirtual #145                // Method java/lang/StringBuilder.append:(Ljava/lang/String;)Ljava/lang/StringBuilder;
     216: aload_0
     217: invokevirtual #121                // Method getGcsManagedLedgerOffloadBucket:()Ljava/lang/String;
     220: invokevirtual #145                // Method java/lang/StringBuilder.append:(Ljava/lang/String;)Ljava/lang/StringBuilder;
     223: ldc           #191                // String , gcsManagedLedgerOffloadMaxBlockSizeInBytes=
     225: invokevirtual #145                // Method java/lang/StringBuilder.append:(Ljava/lang/String;)Ljava/lang/StringBuilder;
     228: aload_0
     229: invokevirtual #123                // Method getGcsManagedLedgerOffloadMaxBlockSizeInBytes:()Ljava/lang/Integer;
     232: invokevirtual #146                // Method java/lang/StringBuilder.append:(Ljava/lang/Object;)Ljava/lang/StringBuilder;
     235: ldc           #192                // String , gcsManagedLedgerOffloadReadBufferSizeInBytes=
     237: invokevirtual #145                // Method java/lang/StringBuilder.append:(Ljava/lang/String;)Ljava/lang/StringBuilder;
     240: aload_0
     241: invokevirtual #125                // Method getGcsManagedLedgerOffloadReadBufferSizeInBytes:()Ljava/lang/Integer;
     244: invokevirtual #146                // Method java/lang/StringBuilder.append:(Ljava/lang/Object;)Ljava/lang/StringBuilder;
     247: ldc           #193                // String , gcsManagedLedgerOffloadServiceAccountKeyFile=
     249: invokevirtual #145                // Method java/lang/StringBuilder.append:(Ljava/lang/String;)Ljava/lang/StringBuilder;
     252: aload_0
     253: invokevirtual #127                // Method getGcsManagedLedgerOffloadServiceAccountKeyFile:()Ljava/lang/String;
     256: invokevirtual #145                // Method java/lang/StringBuilder.append:(Ljava/lang/String;)Ljava/lang/StringBuilder;
     259: ldc           #194                // String , fileSystemProfilePath=
     261: invokevirtual #145                // Method java/lang/StringBuilder.append:(Ljava/lang/String;)Ljava/lang/StringBuilder;
     264: aload_0
     265: invokevirtual #129                // Method getFileSystemProfilePath:()Ljava/lang/String;
     268: invokevirtual #145                // Method java/lang/StringBuilder.append:(Ljava/lang/String;)Ljava/lang/StringBuilder;
     271: ldc           #195                // String , fileSystemURI=
     273: invokevirtual #145                // Method java/lang/StringBuilder.append:(Ljava/lang/String;)Ljava/lang/StringBuilder;
     276: aload_0
     277: invokevirtual #131                // Method getFileSystemURI:()Ljava/lang/String;
     280: invokevirtual #145                // Method java/lang/StringBuilder.append:(Ljava/lang/String;)Ljava/lang/StringBuilder;
     283: ldc           #196                // String , managedLedgerOffloadBucket=
     285: invokevirtual #145                // Method java/lang/StringBuilder.append:(Ljava/lang/String;)Ljava/lang/StringBuilder;
     288: aload_0
     289: invokevirtual #133                // Method getManagedLedgerOffloadBucket:()Ljava/lang/String;
     292: invokevirtual #145                // Method java/lang/StringBuilder.append:(Ljava/lang/String;)Ljava/lang/StringBuilder;
     295: ldc           #197                // String , managedLedgerOffloadRegion=
     297: invokevirtual #145                // Method java/lang/StringBuilder.append:(Ljava/lang/String;)Ljava/lang/StringBuilder;
     300: aload_0
     301: invokevirtual #135                // Method getManagedLedgerOffloadRegion:()Ljava/lang/String;
     304: invokevirtual #145                // Method java/lang/StringBuilder.append:(Ljava/lang/String;)Ljava/lang/StringBuilder;
     307: ldc           #198                // String , managedLedgerOffloadServiceEndpoint=
     309: invokevirtual #145                // Method java/lang/StringBuilder.append:(Ljava/lang/String;)Ljava/lang/StringBuilder;
     312: aload_0
     313: invokevirtual #137                // Method getManagedLedgerOffloadServiceEndpoint:()Ljava/lang/String;
     316: invokevirtual #145                // Method java/lang/StringBuilder.append:(Ljava/lang/String;)Ljava/lang/StringBuilder;
     319: ldc           #199                // String , managedLedgerOffloadMaxBlockSizeInBytes=
     321: invokevirtual #145                // Method java/lang/StringBuilder.append:(Ljava/lang/String;)Ljava/lang/StringBuilder;
     324: aload_0
     325: invokevirtual #139                // Method getManagedLedgerOffloadMaxBlockSizeInBytes:()Ljava/lang/Integer;
     328: invokevirtual #146                // Method java/lang/StringBuilder.append:(Ljava/lang/Object;)Ljava/lang/StringBuilder;
     331: ldc           #200                // String , managedLedgerOffloadReadBufferSizeInBytes=
     333: invokevirtual #145                // Method java/lang/StringBuilder.append:(Ljava/lang/String;)Ljava/lang/StringBuilder;
     336: aload_0
     337: invokevirtual #141                // Method getManagedLedgerOffloadReadBufferSizeInBytes:()Ljava/lang/Integer;
     340: invokevirtual #146                // Method java/lang/StringBuilder.append:(Ljava/lang/Object;)Ljava/lang/StringBuilder;
     343: ldc           #201                // String )
     345: invokevirtual #145                // Method java/lang/StringBuilder.append:(Ljava/lang/String;)Ljava/lang/StringBuilder;
     348: invokevirtual #147                // Method java/lang/StringBuilder.toString:()Ljava/lang/String;
     351: areturn

  public org.apache.pulsar.common.policies.data.OffloadPoliciesImpl();
    Code:
       0: aload_0
       1: invokespecial #202                // Method java/lang/Object."<init>":()V
       4: aload_0
       5: ldc           #203                // String ./offloaders
       7: putfield      #28                 // Field offloadersDirectory:Ljava/lang/String;
      10: aload_0
      11: aconst_null
      12: putfield      #27                 // Field managedLedgerOffloadDriver:Ljava/lang/String;
      15: aload_0
      16: iconst_2
      17: invokestatic  #204                // Method java/lang/Integer.valueOf:(I)Ljava/lang/Integer;
      20: putfield      #26                 // Field managedLedgerOffloadMaxThreads:Ljava/lang/Integer;
      23: aload_0
      24: iconst_1
      25: invokestatic  #204                // Method java/lang/Integer.valueOf:(I)Ljava/lang/Integer;
      28: putfield      #25                 // Field managedLedgerOffloadPrefetchRounds:Ljava/lang/Integer;
      31: aload_0
      32: getstatic     #205                // Field DEFAULT_OFFLOAD_THRESHOLD_IN_BYTES:Ljava/lang/Long;
      35: putfield      #24                 // Field managedLedgerOffloadThresholdInBytes:Ljava/lang/Long;
      38: aload_0
      39: getstatic     #206                // Field DEFAULT_OFFLOAD_DELETION_LAG_IN_MILLIS:Ljava/lang/Long;
      42: putfield      #23                 // Field managedLedgerOffloadDeletionLagInMillis:Ljava/lang/Long;
      45: aload_0
      46: getstatic     #207                // Field DEFAULT_OFFLOADED_READ_PRIORITY:Lorg/apache/pulsar/common/policies/data/OffloadedReadPriority;
      49: putfield      #22                 // Field managedLedgerOffloadedReadPriority:Lorg/apache/pulsar/common/policies/data/OffloadedReadPriority;
      52: aload_0
      53: aconst_null
      54: putfield      #21                 // Field s3ManagedLedgerOffloadRegion:Ljava/lang/String;
      57: aload_0
      58: aconst_null
      59: putfield      #20                 // Field s3ManagedLedgerOffloadBucket:Ljava/lang/String;
      62: aload_0
      63: aconst_null
      64: putfield      #19                 // Field s3ManagedLedgerOffloadServiceEndpoint:Ljava/lang/String;
      67: aload_0
      68: ldc           #208                // int 67108864
      70: invokestatic  #204                // Method java/lang/Integer.valueOf:(I)Ljava/lang/Integer;
      73: putfield      #18                 // Field s3ManagedLedgerOffloadMaxBlockSizeInBytes:Ljava/lang/Integer;
      76: aload_0
      77: ldc           #209                // int 1048576
      79: invokestatic  #204                // Method java/lang/Integer.valueOf:(I)Ljava/lang/Integer;
      82: putfield      #17                 // Field s3ManagedLedgerOffloadReadBufferSizeInBytes:Ljava/lang/Integer;
      85: aload_0
      86: aconst_null
      87: putfield      #16                 // Field s3ManagedLedgerOffloadCredentialId:Ljava/lang/String;
      90: aload_0
      91: aconst_null
      92: putfield      #15                 // Field s3ManagedLedgerOffloadCredentialSecret:Ljava/lang/String;
      95: aload_0
      96: aconst_null
      97: putfield      #14                 // Field s3ManagedLedgerOffloadRole:Ljava/lang/String;
     100: aload_0
     101: ldc           #210                // String pulsar-s3-offload
     103: putfield      #13                 // Field s3ManagedLedgerOffloadRoleSessionName:Ljava/lang/String;
     106: aload_0
     107: aconst_null
     108: putfield      #12                 // Field gcsManagedLedgerOffloadRegion:Ljava/lang/String;
     111: aload_0
     112: aconst_null
     113: putfield      #11                 // Field gcsManagedLedgerOffloadBucket:Ljava/lang/String;
     116: aload_0
     117: ldc           #208                // int 67108864
     119: invokestatic  #204                // Method java/lang/Integer.valueOf:(I)Ljava/lang/Integer;
     122: putfield      #10                 // Field gcsManagedLedgerOffloadMaxBlockSizeInBytes:Ljava/lang/Integer;
     125: aload_0
     126: ldc           #209                // int 1048576
     128: invokestatic  #204                // Method java/lang/Integer.valueOf:(I)Ljava/lang/Integer;
     131: putfield      #9                  // Field gcsManagedLedgerOffloadReadBufferSizeInBytes:Ljava/lang/Integer;
     134: aload_0
     135: aconst_null
     136: putfield      #8                  // Field gcsManagedLedgerOffloadServiceAccountKeyFile:Ljava/lang/String;
     139: aload_0
     140: aconst_null
     141: putfield      #7                  // Field fileSystemProfilePath:Ljava/lang/String;
     144: aload_0
     145: aconst_null
     146: putfield      #6                  // Field fileSystemURI:Ljava/lang/String;
     149: return

  private boolean lambda$driverSupported$1(java.lang.String);
    Code:
       0: aload_1
       1: aload_0
       2: getfield      #27                 // Field managedLedgerOffloadDriver:Ljava/lang/String;
       5: invokevirtual #42                 // Method java/lang/String.equalsIgnoreCase:(Ljava/lang/String;)Z
       8: ireturn

  private static void lambda$create$0(java.util.Properties, org.apache.pulsar.common.policies.data.OffloadPoliciesImpl, java.lang.reflect.Field);
    Code:
       0: aload_0
       1: aload_2
       2: invokevirtual #165                // Method java/lang/reflect/Field.getName:()Ljava/lang/String;
       5: invokevirtual #67                 // Method java/util/Properties.containsKey:(Ljava/lang/Object;)Z
       8: ifeq          76
      11: aload_2
      12: iconst_1
      13: invokevirtual #211                // Method java/lang/reflect/Field.setAccessible:(Z)V
      16: aload_2
      17: aload_1
      18: aload_0
      19: aload_2
      20: invokevirtual #165                // Method java/lang/reflect/Field.getName:()Ljava/lang/String;
      23: invokevirtual #168                // Method java/util/Properties.get:(Ljava/lang/Object;)Ljava/lang/Object;
      26: checkcast     #41                 // class java/lang/String
      29: aload_2
      30: invokestatic  #169                // Method org/apache/pulsar/common/util/FieldParser.value:(Ljava/lang/String;Ljava/lang/reflect/Field;)Ljava/lang/Object;
      33: invokevirtual #160                // Method java/lang/reflect/Field.set:(Ljava/lang/Object;Ljava/lang/Object;)V
      36: goto          76
      39: astore_3
      40: new           #212                // class java/lang/IllegalArgumentException
      43: dup
      44: ldc           #213                // String failed to initialize %s field while setting value %s
      46: iconst_2
      47: anewarray     #214                // class java/lang/Object
      50: dup
      51: iconst_0
      52: aload_2
      53: invokevirtual #165                // Method java/lang/reflect/Field.getName:()Ljava/lang/String;
      56: aastore
      57: dup
      58: iconst_1
      59: aload_0
      60: aload_2
      61: invokevirtual #165                // Method java/lang/reflect/Field.getName:()Ljava/lang/String;
      64: invokevirtual #168                // Method java/util/Properties.get:(Ljava/lang/Object;)Ljava/lang/Object;
      67: aastore
      68: invokestatic  #215                // Method java/lang/String.format:(Ljava/lang/String;[Ljava/lang/Object;)Ljava/lang/String;
      71: aload_3
      72: invokespecial #216                // Method java/lang/IllegalArgumentException."<init>":(Ljava/lang/String;Ljava/lang/Throwable;)V
      75: athrow
      76: return
    Exception table:
       from    to  target type
          11    36    39   Class java/lang/Exception

  static java.lang.String access$002(org.apache.pulsar.common.policies.data.OffloadPoliciesImpl, java.lang.String);
    Code:
       0: aload_0
       1: aload_1
       2: dup_x1
       3: putfield      #28                 // Field offloadersDirectory:Ljava/lang/String;
       6: areturn

  static java.lang.String access$102(org.apache.pulsar.common.policies.data.OffloadPoliciesImpl, java.lang.String);
    Code:
       0: aload_0
       1: aload_1
       2: dup_x1
       3: putfield      #27                 // Field managedLedgerOffloadDriver:Ljava/lang/String;
       6: areturn

  static java.lang.Integer access$202(org.apache.pulsar.common.policies.data.OffloadPoliciesImpl, java.lang.Integer);
    Code:
       0: aload_0
       1: aload_1
       2: dup_x1
       3: putfield      #26                 // Field managedLedgerOffloadMaxThreads:Ljava/lang/Integer;
       6: areturn

  static java.lang.Integer access$302(org.apache.pulsar.common.policies.data.OffloadPoliciesImpl, java.lang.Integer);
    Code:
       0: aload_0
       1: aload_1
       2: dup_x1
       3: putfield      #25                 // Field managedLedgerOffloadPrefetchRounds:Ljava/lang/Integer;
       6: areturn

  static java.lang.Long access$402(org.apache.pulsar.common.policies.data.OffloadPoliciesImpl, java.lang.Long);
    Code:
       0: aload_0
       1: aload_1
       2: dup_x1
       3: putfield      #24                 // Field managedLedgerOffloadThresholdInBytes:Ljava/lang/Long;
       6: areturn

  static java.lang.Long access$502(org.apache.pulsar.common.policies.data.OffloadPoliciesImpl, java.lang.Long);
    Code:
       0: aload_0
       1: aload_1
       2: dup_x1
       3: putfield      #23                 // Field managedLedgerOffloadDeletionLagInMillis:Ljava/lang/Long;
       6: areturn

  static org.apache.pulsar.common.policies.data.OffloadedReadPriority access$602(org.apache.pulsar.common.policies.data.OffloadPoliciesImpl, org.apache.pulsar.common.policies.data.OffloadedReadPriority);
    Code:
       0: aload_0
       1: aload_1
       2: dup_x1
       3: putfield      #22                 // Field managedLedgerOffloadedReadPriority:Lorg/apache/pulsar/common/policies/data/OffloadedReadPriority;
       6: areturn

  static java.lang.String access$702(org.apache.pulsar.common.policies.data.OffloadPoliciesImpl, java.lang.String);
    Code:
       0: aload_0
       1: aload_1
       2: dup_x1
       3: putfield      #21                 // Field s3ManagedLedgerOffloadRegion:Ljava/lang/String;
       6: areturn

  static java.lang.String access$802(org.apache.pulsar.common.policies.data.OffloadPoliciesImpl, java.lang.String);
    Code:
       0: aload_0
       1: aload_1
       2: dup_x1
       3: putfield      #20                 // Field s3ManagedLedgerOffloadBucket:Ljava/lang/String;
       6: areturn

  static java.lang.String access$902(org.apache.pulsar.common.policies.data.OffloadPoliciesImpl, java.lang.String);
    Code:
       0: aload_0
       1: aload_1
       2: dup_x1
       3: putfield      #19                 // Field s3ManagedLedgerOffloadServiceEndpoint:Ljava/lang/String;
       6: areturn

  static java.lang.Integer access$1002(org.apache.pulsar.common.policies.data.OffloadPoliciesImpl, java.lang.Integer);
    Code:
       0: aload_0
       1: aload_1
       2: dup_x1
       3: putfield      #18                 // Field s3ManagedLedgerOffloadMaxBlockSizeInBytes:Ljava/lang/Integer;
       6: areturn

  static java.lang.Integer access$1102(org.apache.pulsar.common.policies.data.OffloadPoliciesImpl, java.lang.Integer);
    Code:
       0: aload_0
       1: aload_1
       2: dup_x1
       3: putfield      #17                 // Field s3ManagedLedgerOffloadReadBufferSizeInBytes:Ljava/lang/Integer;
       6: areturn

  static java.lang.String access$1202(org.apache.pulsar.common.policies.data.OffloadPoliciesImpl, java.lang.String);
    Code:
       0: aload_0
       1: aload_1
       2: dup_x1
       3: putfield      #16                 // Field s3ManagedLedgerOffloadCredentialId:Ljava/lang/String;
       6: areturn

  static java.lang.String access$1302(org.apache.pulsar.common.policies.data.OffloadPoliciesImpl, java.lang.String);
    Code:
       0: aload_0
       1: aload_1
       2: dup_x1
       3: putfield      #15                 // Field s3ManagedLedgerOffloadCredentialSecret:Ljava/lang/String;
       6: areturn

  static java.lang.String access$1402(org.apache.pulsar.common.policies.data.OffloadPoliciesImpl, java.lang.String);
    Code:
       0: aload_0
       1: aload_1
       2: dup_x1
       3: putfield      #14                 // Field s3ManagedLedgerOffloadRole:Ljava/lang/String;
       6: areturn

  static java.lang.String access$1502(org.apache.pulsar.common.policies.data.OffloadPoliciesImpl, java.lang.String);
    Code:
       0: aload_0
       1: aload_1
       2: dup_x1
       3: putfield      #13                 // Field s3ManagedLedgerOffloadRoleSessionName:Ljava/lang/String;
       6: areturn

  static java.lang.String access$1602(org.apache.pulsar.common.policies.data.OffloadPoliciesImpl, java.lang.String);
    Code:
       0: aload_0
       1: aload_1
       2: dup_x1
       3: putfield      #12                 // Field gcsManagedLedgerOffloadRegion:Ljava/lang/String;
       6: areturn

  static java.lang.String access$1702(org.apache.pulsar.common.policies.data.OffloadPoliciesImpl, java.lang.String);
    Code:
       0: aload_0
       1: aload_1
       2: dup_x1
       3: putfield      #11                 // Field gcsManagedLedgerOffloadBucket:Ljava/lang/String;
       6: areturn

  static java.lang.Integer access$1802(org.apache.pulsar.common.policies.data.OffloadPoliciesImpl, java.lang.Integer);
    Code:
       0: aload_0
       1: aload_1
       2: dup_x1
       3: putfield      #10                 // Field gcsManagedLedgerOffloadMaxBlockSizeInBytes:Ljava/lang/Integer;
       6: areturn

  static java.lang.Integer access$1902(org.apache.pulsar.common.policies.data.OffloadPoliciesImpl, java.lang.Integer);
    Code:
       0: aload_0
       1: aload_1
       2: dup_x1
       3: putfield      #9                  // Field gcsManagedLedgerOffloadReadBufferSizeInBytes:Ljava/lang/Integer;
       6: areturn

  static java.lang.String access$2002(org.apache.pulsar.common.policies.data.OffloadPoliciesImpl, java.lang.String);
    Code:
       0: aload_0
       1: aload_1
       2: dup_x1
       3: putfield      #8                  // Field gcsManagedLedgerOffloadServiceAccountKeyFile:Ljava/lang/String;
       6: areturn

  static java.lang.String access$2102(org.apache.pulsar.common.policies.data.OffloadPoliciesImpl, java.lang.String);
    Code:
       0: aload_0
       1: aload_1
       2: dup_x1
       3: putfield      #7                  // Field fileSystemProfilePath:Ljava/lang/String;
       6: areturn

  static java.lang.String access$2202(org.apache.pulsar.common.policies.data.OffloadPoliciesImpl, java.lang.String);
    Code:
       0: aload_0
       1: aload_1
       2: dup_x1
       3: putfield      #6                  // Field fileSystemURI:Ljava/lang/String;
       6: areturn

  static java.lang.String access$2302(org.apache.pulsar.common.policies.data.OffloadPoliciesImpl, java.lang.String);
    Code:
       0: aload_0
       1: aload_1
       2: dup_x1
       3: putfield      #5                  // Field managedLedgerOffloadBucket:Ljava/lang/String;
       6: areturn

  static java.lang.String access$2402(org.apache.pulsar.common.policies.data.OffloadPoliciesImpl, java.lang.String);
    Code:
       0: aload_0
       1: aload_1
       2: dup_x1
       3: putfield      #4                  // Field managedLedgerOffloadRegion:Ljava/lang/String;
       6: areturn

  static java.lang.String access$2502(org.apache.pulsar.common.policies.data.OffloadPoliciesImpl, java.lang.String);
    Code:
       0: aload_0
       1: aload_1
       2: dup_x1
       3: putfield      #3                  // Field managedLedgerOffloadServiceEndpoint:Ljava/lang/String;
       6: areturn

  static java.lang.Integer access$2602(org.apache.pulsar.common.policies.data.OffloadPoliciesImpl, java.lang.Integer);
    Code:
       0: aload_0
       1: aload_1
       2: dup_x1
       3: putfield      #2                  // Field managedLedgerOffloadMaxBlockSizeInBytes:Ljava/lang/Integer;
       6: areturn

  static java.lang.Integer access$2702(org.apache.pulsar.common.policies.data.OffloadPoliciesImpl, java.lang.Integer);
    Code:
       0: aload_0
       1: aload_1
       2: dup_x1
       3: putfield      #1                  // Field managedLedgerOffloadReadBufferSizeInBytes:Ljava/lang/Integer;
       6: areturn

  static {};
    Code:
       0: ldc           #57                 // class org/apache/pulsar/common/policies/data/OffloadPoliciesImpl
       2: invokestatic  #217                // Method org/slf4j/LoggerFactory.getLogger:(Ljava/lang/Class;)Lorg/slf4j/Logger;
       5: putstatic     #162                // Field log:Lorg/slf4j/Logger;
       8: new           #218                // class java/util/ArrayList
      11: dup
      12: invokespecial #219                // Method java/util/ArrayList."<init>":()V
      15: astore_0
      16: ldc           #57                 // class org/apache/pulsar/common/policies/data/OffloadPoliciesImpl
      18: astore_1
      19: aload_1
      20: invokevirtual #59                 // Method java/lang/Class.getDeclaredFields:()[Ljava/lang/reflect/Field;
      23: astore_2
      24: aload_2
      25: astore_3
      26: aload_3
      27: arraylength
      28: istore        4
      30: iconst_0
      31: istore        5
      33: iload         5
      35: iload         4
      37: if_icmpge     71
      40: aload_3
      41: iload         5
      43: aaload
      44: astore        6
      46: aload         6
      48: ldc           #220                // class org/apache/pulsar/common/policies/data/OffloadPoliciesImpl$Configuration
      50: invokevirtual #221                // Method java/lang/reflect/Field.isAnnotationPresent:(Ljava/lang/Class;)Z
      53: ifeq          65
      56: aload_0
      57: aload         6
      59: invokeinterface #222,  2          // InterfaceMethod java/util/List.add:(Ljava/lang/Object;)Z
      64: pop
      65: iinc          5, 1
      68: goto          33
      71: aload_0
      72: invokestatic  #223                // Method java/util/Collections.unmodifiableList:(Ljava/util/List;)Ljava/util/List;
      75: putstatic     #153                // Field CONFIGURATION_FIELDS:Ljava/util/List;
      78: ldc           #224                // String S3
      80: ldc           #225                // String aws-s3
      82: ldc           #226                // String google-cloud-storage
      84: ldc           #227                // String filesystem
      86: ldc           #228                // String azureblob
      88: ldc           #229                // String aliyun-oss
      90: invokestatic  #230                // Method com/google/common/collect/ImmutableList.of:(Ljava/lang/Object;Ljava/lang/Object;Ljava/lang/Object;Ljava/lang/Object;Ljava/lang/Object;Ljava/lang/Object;)Lcom/google/common/collect/ImmutableList;
      93: putstatic     #39                 // Field DRIVER_NAMES:Lcom/google/common/collect/ImmutableList;
      96: aconst_null
      97: putstatic     #205                // Field DEFAULT_OFFLOAD_THRESHOLD_IN_BYTES:Ljava/lang/Long;
     100: aconst_null
     101: putstatic     #206                // Field DEFAULT_OFFLOAD_DELETION_LAG_IN_MILLIS:Ljava/lang/Long;
     104: getstatic     #231                // Field org/apache/pulsar/common/policies/data/OffloadedReadPriority.TIERED_STORAGE_FIRST:Lorg/apache/pulsar/common/policies/data/OffloadedReadPriority;
     107: putstatic     #207                // Field DEFAULT_OFFLOADED_READ_PRIORITY:Lorg/apache/pulsar/common/policies/data/OffloadedReadPriority;
     110: return
}
