Compiled from "TenantInfoImpl.java"
public class org.apache.pulsar.common.policies.data.TenantInfoImpl implements org.apache.pulsar.common.policies.data.TenantInfo {
  private java.util.Set<java.lang.String> adminRoles;

  private java.util.Set<java.lang.String> allowedClusters;

  public static org.apache.pulsar.common.policies.data.TenantInfoImpl$TenantInfoImplBuilder builder();
    Code:
       0: new           #1                  // class org/apache/pulsar/common/policies/data/TenantInfoImpl$TenantInfoImplBuilder
       3: dup
       4: invokespecial #2                  // Method org/apache/pulsar/common/policies/data/TenantInfoImpl$TenantInfoImplBuilder."<init>":()V
       7: areturn

  public java.util.Set<java.lang.String> getAdminRoles();
    Code:
       0: aload_0
       1: getfield      #3                  // Field adminRoles:Ljava/util/Set;
       4: areturn

  public java.util.Set<java.lang.String> getAllowedClusters();
    Code:
       0: aload_0
       1: getfield      #4                  // Field allowedClusters:Ljava/util/Set;
       4: areturn

  public void setAdminRoles(java.util.Set<java.lang.String>);
    Code:
       0: aload_0
       1: aload_1
       2: putfield      #3                  // Field adminRoles:Ljava/util/Set;
       5: return

  public void setAllowedClusters(java.util.Set<java.lang.String>);
    Code:
       0: aload_0
       1: aload_1
       2: putfield      #4                  // Field allowedClusters:Ljava/util/Set;
       5: return

  public boolean equals(java.lang.Object);
    Code:
       0: aload_1
       1: aload_0
       2: if_acmpne     7
       5: iconst_1
       6: ireturn
       7: aload_1
       8: instanceof    #5                  // class org/apache/pulsar/common/policies/data/TenantInfoImpl
      11: ifne          16
      14: iconst_0
      15: ireturn
      16: aload_1
      17: checkcast     #5                  // class org/apache/pulsar/common/policies/data/TenantInfoImpl
      20: astore_2
      21: aload_2
      22: aload_0
      23: invokevirtual #6                  // Method canEqual:(Ljava/lang/Object;)Z
      26: ifne          31
      29: iconst_0
      30: ireturn
      31: aload_0
      32: invokevirtual #7                  // Method getAdminRoles:()Ljava/util/Set;
      35: astore_3
      36: aload_2
      37: invokevirtual #7                  // Method getAdminRoles:()Ljava/util/Set;
      40: astore        4
      42: aload_3
      43: ifnonnull     54
      46: aload         4
      48: ifnull        65
      51: goto          63
      54: aload_3
      55: aload         4
      57: invokevirtual #8                  // Method java/lang/Object.equals:(Ljava/lang/Object;)Z
      60: ifne          65
      63: iconst_0
      64: ireturn
      65: aload_0
      66: invokevirtual #9                  // Method getAllowedClusters:()Ljava/util/Set;
      69: astore        5
      71: aload_2
      72: invokevirtual #9                  // Method getAllowedClusters:()Ljava/util/Set;
      75: astore        6
      77: aload         5
      79: ifnonnull     90
      82: aload         6
      84: ifnull        102
      87: goto          100
      90: aload         5
      92: aload         6
      94: invokevirtual #8                  // Method java/lang/Object.equals:(Ljava/lang/Object;)Z
      97: ifne          102
     100: iconst_0
     101: ireturn
     102: iconst_1
     103: ireturn

  protected boolean canEqual(java.lang.Object);
    Code:
       0: aload_1
       1: instanceof    #5                  // class org/apache/pulsar/common/policies/data/TenantInfoImpl
       4: ireturn

  public int hashCode();
    Code:
       0: bipush        59
       2: istore_1
       3: iconst_1
       4: istore_2
       5: aload_0
       6: invokevirtual #7                  // Method getAdminRoles:()Ljava/util/Set;
       9: astore_3
      10: iload_2
      11: bipush        59
      13: imul
      14: aload_3
      15: ifnonnull     23
      18: bipush        43
      20: goto          27
      23: aload_3
      24: invokevirtual #10                 // Method java/lang/Object.hashCode:()I
      27: iadd
      28: istore_2
      29: aload_0
      30: invokevirtual #9                  // Method getAllowedClusters:()Ljava/util/Set;
      33: astore        4
      35: iload_2
      36: bipush        59
      38: imul
      39: aload         4
      41: ifnonnull     49
      44: bipush        43
      46: goto          54
      49: aload         4
      51: invokevirtual #10                 // Method java/lang/Object.hashCode:()I
      54: iadd
      55: istore_2
      56: iload_2
      57: ireturn

  public java.lang.String toString();
    Code:
       0: new           #11                 // class java/lang/StringBuilder
       3: dup
       4: invokespecial #12                 // Method java/lang/StringBuilder."<init>":()V
       7: ldc           #13                 // String TenantInfoImpl(adminRoles=
       9: invokevirtual #14                 // Method java/lang/StringBuilder.append:(Ljava/lang/String;)Ljava/lang/StringBuilder;
      12: aload_0
      13: invokevirtual #7                  // Method getAdminRoles:()Ljava/util/Set;
      16: invokevirtual #15                 // Method java/lang/StringBuilder.append:(Ljava/lang/Object;)Ljava/lang/StringBuilder;
      19: ldc           #16                 // String , allowedClusters=
      21: invokevirtual #14                 // Method java/lang/StringBuilder.append:(Ljava/lang/String;)Ljava/lang/StringBuilder;
      24: aload_0
      25: invokevirtual #9                  // Method getAllowedClusters:()Ljava/util/Set;
      28: invokevirtual #15                 // Method java/lang/StringBuilder.append:(Ljava/lang/Object;)Ljava/lang/StringBuilder;
      31: ldc           #17                 // String )
      33: invokevirtual #14                 // Method java/lang/StringBuilder.append:(Ljava/lang/String;)Ljava/lang/StringBuilder;
      36: invokevirtual #18                 // Method java/lang/StringBuilder.toString:()Ljava/lang/String;
      39: areturn

  public org.apache.pulsar.common.policies.data.TenantInfoImpl(java.util.Set<java.lang.String>, java.util.Set<java.lang.String>);
    Code:
       0: aload_0
       1: invokespecial #19                 // Method java/lang/Object."<init>":()V
       4: aload_0
       5: aload_1
       6: putfield      #3                  // Field adminRoles:Ljava/util/Set;
       9: aload_0
      10: aload_2
      11: putfield      #4                  // Field allowedClusters:Ljava/util/Set;
      14: return

  public org.apache.pulsar.common.policies.data.TenantInfoImpl();
    Code:
       0: aload_0
       1: invokespecial #19                 // Method java/lang/Object."<init>":()V
       4: return
}
