Compiled from "HPCCWsCodeSignClient.java"
public class org.hpccsystems.ws.client.HPCCWsCodeSignClient extends org.hpccsystems.ws.client.BaseHPCCWsClient {
  private static final org.apache.logging.log4j.Logger log;

  public static final java.lang.String WSRESOURCESURI;

  private static int DEFAULTSERVICEPORT;

  private static java.lang.String WSDLURL;

  private static void loadWSDLURL();
    Code:
       0: new           #1                  // class org/hpccsystems/ws/client/gen/axis2/wscodesign/v1_01/Ws_codesignStub
       3: dup
       4: invokespecial #2                  // Method org/hpccsystems/ws/client/gen/axis2/wscodesign/v1_01/Ws_codesignStub."<init>":()V
       7: invokestatic  #3                  // Method getServiceWSDLURL:(Lorg/apache/axis2/client/Stub;)Ljava/lang/String;
      10: putstatic     #4                  // Field WSDLURL:Ljava/lang/String;
      13: new           #5                  // class java/net/URL
      16: dup
      17: getstatic     #4                  // Field WSDLURL:Ljava/lang/String;
      20: invokespecial #6                  // Method java/net/URL."<init>":(Ljava/lang/String;)V
      23: invokevirtual #7                  // Method java/net/URL.getPort:()I
      26: putstatic     #8                  // Field DEFAULTSERVICEPORT:I
      29: goto          55
      32: astore_0
      33: getstatic     #11                 // Field log:Lorg/apache/logging/log4j/Logger;
      36: ldc           #12                 // String Unable to establish original WSDL URL
      38: invokeinterface #13,  2           // InterfaceMethod org/apache/logging/log4j/Logger.error:(Ljava/lang/String;)V
      43: getstatic     #11                 // Field log:Lorg/apache/logging/log4j/Logger;
      46: aload_0
      47: invokevirtual #14                 // Method java/io/IOException.getLocalizedMessage:()Ljava/lang/String;
      50: invokeinterface #13,  2           // InterfaceMethod org/apache/logging/log4j/Logger.error:(Ljava/lang/String;)V
      55: return
    Exception table:
       from    to  target type
           0    29    32   Class org/apache/axis2/AxisFault
           0    29    32   Class java/net/MalformedURLException

  public java.lang.String getServiceURI();
    Code:
       0: ldc           #16                 // String /ws_codesign
       2: areturn

  public static java.lang.String getServiceWSDLURL();
    Code:
       0: getstatic     #4                  // Field WSDLURL:Ljava/lang/String;
       3: ifnonnull     9
       6: invokestatic  #17                 // Method loadWSDLURL:()V
       9: getstatic     #4                  // Field WSDLURL:Ljava/lang/String;
      12: areturn

  public static int getServiceWSDLPort();
    Code:
       0: getstatic     #4                  // Field WSDLURL:Ljava/lang/String;
       3: ifnonnull     9
       6: invokestatic  #17                 // Method loadWSDLURL:()V
       9: getstatic     #8                  // Field DEFAULTSERVICEPORT:I
      12: ireturn

  public org.apache.axis2.client.Stub getDefaultStub() throws org.apache.axis2.AxisFault;
    Code:
       0: new           #1                  // class org/hpccsystems/ws/client/gen/axis2/wscodesign/v1_01/Ws_codesignStub
       3: dup
       4: invokespecial #2                  // Method org/hpccsystems/ws/client/gen/axis2/wscodesign/v1_01/Ws_codesignStub."<init>":()V
       7: areturn

  public static org.hpccsystems.ws.client.HPCCWsCodeSignClient get(org.hpccsystems.ws.client.utils.Connection);
    Code:
       0: new           #15                 // class org/hpccsystems/ws/client/HPCCWsCodeSignClient
       3: dup
       4: aload_0
       5: invokespecial #18                 // Method "<init>":(Lorg/hpccsystems/ws/client/utils/Connection;)V
       8: areturn

  public static org.hpccsystems.ws.client.HPCCWsCodeSignClient get(java.lang.String, java.lang.String, java.lang.String, java.lang.String, java.lang.String);
    Code:
       0: new           #19                 // class org/hpccsystems/ws/client/utils/Connection
       3: dup
       4: aload_0
       5: aload_1
       6: aload_2
       7: invokespecial #20                 // Method org/hpccsystems/ws/client/utils/Connection."<init>":(Ljava/lang/String;Ljava/lang/String;Ljava/lang/String;)V
      10: astore        5
      12: aload         5
      14: aload_3
      15: aload         4
      17: invokevirtual #21                 // Method org/hpccsystems/ws/client/utils/Connection.setCredentials:(Ljava/lang/String;Ljava/lang/String;)V
      20: new           #15                 // class org/hpccsystems/ws/client/HPCCWsCodeSignClient
      23: dup
      24: aload         5
      26: invokespecial #18                 // Method "<init>":(Lorg/hpccsystems/ws/client/utils/Connection;)V
      29: areturn

  public static org.hpccsystems.ws.client.HPCCWsCodeSignClient get(java.lang.String, java.lang.String, java.lang.String, java.lang.String, java.lang.String, int);
    Code:
       0: new           #19                 // class org/hpccsystems/ws/client/utils/Connection
       3: dup
       4: aload_0
       5: aload_1
       6: aload_2
       7: invokespecial #20                 // Method org/hpccsystems/ws/client/utils/Connection."<init>":(Ljava/lang/String;Ljava/lang/String;Ljava/lang/String;)V
      10: astore        6
      12: aload         6
      14: aload_3
      15: aload         4
      17: invokevirtual #21                 // Method org/hpccsystems/ws/client/utils/Connection.setCredentials:(Ljava/lang/String;Ljava/lang/String;)V
      20: aload         6
      22: iload         5
      24: invokevirtual #22                 // Method org/hpccsystems/ws/client/utils/Connection.setConnectTimeoutMilli:(I)V
      27: aload         6
      29: iload         5
      31: invokevirtual #23                 // Method org/hpccsystems/ws/client/utils/Connection.setSocketTimeoutMilli:(I)V
      34: new           #15                 // class org/hpccsystems/ws/client/HPCCWsCodeSignClient
      37: dup
      38: aload         6
      40: invokespecial #18                 // Method "<init>":(Lorg/hpccsystems/ws/client/utils/Connection;)V
      43: areturn

  protected org.hpccsystems.ws.client.HPCCWsCodeSignClient(org.hpccsystems.ws.client.utils.Connection);
    Code:
       0: aload_0
       1: invokespecial #24                 // Method org/hpccsystems/ws/client/BaseHPCCWsClient."<init>":()V
       4: aload_0
       5: aload_1
       6: invokevirtual #25                 // Method initWsResourcesClientStub:(Lorg/hpccsystems/ws/client/utils/Connection;)V
       9: return

  protected void initWsResourcesClientStub(org.hpccsystems.ws.client.utils.Connection);
    Code:
       0: aload_0
       1: aload_1
       2: invokevirtual #26                 // Method setActiveConnectionInfo:(Lorg/hpccsystems/ws/client/utils/Connection;)V
       5: aload_0
       6: new           #1                  // class org/hpccsystems/ws/client/gen/axis2/wscodesign/v1_01/Ws_codesignStub
       9: dup
      10: new           #27                 // class java/lang/StringBuilder
      13: dup
      14: invokespecial #28                 // Method java/lang/StringBuilder."<init>":()V
      17: aload_1
      18: invokevirtual #29                 // Method org/hpccsystems/ws/client/utils/Connection.getBaseUrl:()Ljava/lang/String;
      21: invokevirtual #30                 // Method java/lang/StringBuilder.append:(Ljava/lang/String;)Ljava/lang/StringBuilder;
      24: ldc           #16                 // String /ws_codesign
      26: invokevirtual #30                 // Method java/lang/StringBuilder.append:(Ljava/lang/String;)Ljava/lang/StringBuilder;
      29: invokevirtual #31                 // Method java/lang/StringBuilder.toString:()Ljava/lang/String;
      32: invokespecial #32                 // Method org/hpccsystems/ws/client/gen/axis2/wscodesign/v1_01/Ws_codesignStub."<init>":(Ljava/lang/String;)V
      35: aload_1
      36: invokestatic  #33                 // Method setStubOptions:(Lorg/apache/axis2/client/Stub;Lorg/hpccsystems/ws/client/utils/Connection;)Lorg/apache/axis2/client/Stub;
      39: putfield      #34                 // Field stub:Lorg/apache/axis2/client/Stub;
      42: goto          112
      45: astore_2
      46: aload_0
      47: aconst_null
      48: putfield      #34                 // Field stub:Lorg/apache/axis2/client/Stub;
      51: aload_0
      52: ldc           #36                 // String Could not initialize WsCodeSignClient - Review all HPCC connection values
      54: putfield      #37                 // Field initErrMessage:Ljava/lang/String;
      57: aload_2
      58: invokevirtual #38                 // Method java/lang/Exception.getLocalizedMessage:()Ljava/lang/String;
      61: invokevirtual #39                 // Method java/lang/String.isEmpty:()Z
      64: ifne          100
      67: new           #27                 // class java/lang/StringBuilder
      70: dup
      71: invokespecial #28                 // Method java/lang/StringBuilder."<init>":()V
      74: aload_0
      75: dup_x1
      76: getfield      #37                 // Field initErrMessage:Ljava/lang/String;
      79: invokevirtual #30                 // Method java/lang/StringBuilder.append:(Ljava/lang/String;)Ljava/lang/StringBuilder;
      82: ldc           #40                 // String \n
      84: invokevirtual #30                 // Method java/lang/StringBuilder.append:(Ljava/lang/String;)Ljava/lang/StringBuilder;
      87: aload_2
      88: invokevirtual #38                 // Method java/lang/Exception.getLocalizedMessage:()Ljava/lang/String;
      91: invokevirtual #30                 // Method java/lang/StringBuilder.append:(Ljava/lang/String;)Ljava/lang/StringBuilder;
      94: invokevirtual #31                 // Method java/lang/StringBuilder.toString:()Ljava/lang/String;
      97: putfield      #37                 // Field initErrMessage:Ljava/lang/String;
     100: getstatic     #11                 // Field log:Lorg/apache/logging/log4j/Logger;
     103: aload_0
     104: getfield      #37                 // Field initErrMessage:Ljava/lang/String;
     107: invokeinterface #13,  2           // InterfaceMethod org/apache/logging/log4j/Logger.error:(Ljava/lang/String;)V
     112: return
    Exception table:
       from    to  target type
           5    42    45   Class java/lang/Exception

  public org.hpccsystems.ws.client.wrappers.gen.wscodesign.ListUserIDsResponseWrapper listUserIDs(org.hpccsystems.ws.client.wrappers.gen.wscodesign.ListUserIDsRequestWrapper) throws java.lang.Exception;
    Code:
       0: aload_1
       1: ifnonnull     14
       4: new           #35                 // class java/lang/Exception
       7: dup
       8: ldc           #41                 // String HPCCWsCodeSignClient.listUserIDs: Must provide valid ListUserIDsRequestWrapper!
      10: invokespecial #42                 // Method java/lang/Exception."<init>":(Ljava/lang/String;)V
      13: athrow
      14: aload_0
      15: invokevirtual #43                 // Method verifyStub:()Lorg/apache/axis2/client/Stub;
      18: pop
      19: aconst_null
      20: astore_2
      21: aload_0
      22: getfield      #34                 // Field stub:Lorg/apache/axis2/client/Stub;
      25: checkcast     #1                  // class org/hpccsystems/ws/client/gen/axis2/wscodesign/v1_01/Ws_codesignStub
      28: aload_1
      29: invokevirtual #44                 // Method org/hpccsystems/ws/client/wrappers/gen/wscodesign/ListUserIDsRequestWrapper.getRaw:()Lorg/hpccsystems/ws/client/gen/axis2/wscodesign/v1_01/ListUserIDsRequest;
      32: invokevirtual #45                 // Method org/hpccsystems/ws/client/gen/axis2/wscodesign/v1_01/Ws_codesignStub.listUserIDs:(Lorg/hpccsystems/ws/client/gen/axis2/wscodesign/v1_01/ListUserIDsRequest;)Lorg/hpccsystems/ws/client/gen/axis2/wscodesign/v1_01/ListUserIDsResponse;
      35: astore_2
      36: goto          51
      39: astore_3
      40: new           #35                 // class java/lang/Exception
      43: dup
      44: ldc           #47                 // String HPCCWSRESOURCESClient.listUserIDs(ListUserIDsRequestWrapper) encountered RemoteException.
      46: aload_3
      47: invokespecial #48                 // Method java/lang/Exception."<init>":(Ljava/lang/String;Ljava/lang/Throwable;)V
      50: athrow
      51: aload_2
      52: invokevirtual #49                 // Method org/hpccsystems/ws/client/gen/axis2/wscodesign/v1_01/ListUserIDsResponse.getExceptions:()Lorg/hpccsystems/ws/client/gen/axis2/wscodesign/v1_01/ArrayOfEspException;
      55: ifnull        77
      58: aload_2
      59: invokevirtual #49                 // Method org/hpccsystems/ws/client/gen/axis2/wscodesign/v1_01/ListUserIDsResponse.getExceptions:()Lorg/hpccsystems/ws/client/gen/axis2/wscodesign/v1_01/ArrayOfEspException;
      62: astore_3
      63: aload_0
      64: new           #50                 // class org/hpccsystems/ws/client/wrappers/ArrayOfEspExceptionWrapper
      67: dup
      68: aload_3
      69: invokespecial #51                 // Method org/hpccsystems/ws/client/wrappers/ArrayOfEspExceptionWrapper."<init>":(Lorg/hpccsystems/ws/client/gen/axis2/wscodesign/v1_01/ArrayOfEspException;)V
      72: ldc           #52                 // String Error listing userids
      74: invokevirtual #53                 // Method handleEspExceptions:(Lorg/hpccsystems/ws/client/wrappers/ArrayOfEspExceptionWrapper;Ljava/lang/String;)V
      77: new           #54                 // class org/hpccsystems/ws/client/wrappers/gen/wscodesign/ListUserIDsResponseWrapper
      80: dup
      81: aload_2
      82: invokespecial #55                 // Method org/hpccsystems/ws/client/wrappers/gen/wscodesign/ListUserIDsResponseWrapper."<init>":(Lorg/hpccsystems/ws/client/gen/axis2/wscodesign/v1_01/ListUserIDsResponse;)V
      85: areturn
    Exception table:
       from    to  target type
          21    36    39   Class java/rmi/RemoteException

  public org.hpccsystems.ws.client.wrappers.gen.wscodesign.SignResponseWrapper sign(org.hpccsystems.ws.client.wrappers.gen.wscodesign.SignRequestWrapper) throws java.lang.Exception;
    Code:
       0: aload_1
       1: ifnonnull     14
       4: new           #35                 // class java/lang/Exception
       7: dup
       8: ldc           #56                 // String HPCCWsCodeSignClient.sign: Must provide valid SignRequestWrapper!
      10: invokespecial #42                 // Method java/lang/Exception."<init>":(Ljava/lang/String;)V
      13: athrow
      14: aload_0
      15: invokevirtual #43                 // Method verifyStub:()Lorg/apache/axis2/client/Stub;
      18: pop
      19: aconst_null
      20: astore_2
      21: aload_0
      22: getfield      #34                 // Field stub:Lorg/apache/axis2/client/Stub;
      25: checkcast     #1                  // class org/hpccsystems/ws/client/gen/axis2/wscodesign/v1_01/Ws_codesignStub
      28: aload_1
      29: invokevirtual #57                 // Method org/hpccsystems/ws/client/wrappers/gen/wscodesign/SignRequestWrapper.getRaw:()Lorg/hpccsystems/ws/client/gen/axis2/wscodesign/v1_01/SignRequest;
      32: invokevirtual #58                 // Method org/hpccsystems/ws/client/gen/axis2/wscodesign/v1_01/Ws_codesignStub.sign:(Lorg/hpccsystems/ws/client/gen/axis2/wscodesign/v1_01/SignRequest;)Lorg/hpccsystems/ws/client/gen/axis2/wscodesign/v1_01/SignResponse;
      35: astore_2
      36: goto          51
      39: astore_3
      40: new           #35                 // class java/lang/Exception
      43: dup
      44: ldc           #59                 // String HPCCWSRESOURCESClient.sign(ServiceQueryRequestWrapper) encountered RemoteException.
      46: aload_3
      47: invokespecial #48                 // Method java/lang/Exception."<init>":(Ljava/lang/String;Ljava/lang/Throwable;)V
      50: athrow
      51: aload_2
      52: invokevirtual #60                 // Method org/hpccsystems/ws/client/gen/axis2/wscodesign/v1_01/SignResponse.getExceptions:()Lorg/hpccsystems/ws/client/gen/axis2/wscodesign/v1_01/ArrayOfEspException;
      55: ifnull        77
      58: aload_2
      59: invokevirtual #60                 // Method org/hpccsystems/ws/client/gen/axis2/wscodesign/v1_01/SignResponse.getExceptions:()Lorg/hpccsystems/ws/client/gen/axis2/wscodesign/v1_01/ArrayOfEspException;
      62: astore_3
      63: aload_0
      64: new           #50                 // class org/hpccsystems/ws/client/wrappers/ArrayOfEspExceptionWrapper
      67: dup
      68: aload_3
      69: invokespecial #51                 // Method org/hpccsystems/ws/client/wrappers/ArrayOfEspExceptionWrapper."<init>":(Lorg/hpccsystems/ws/client/gen/axis2/wscodesign/v1_01/ArrayOfEspException;)V
      72: ldc           #61                 // String Error signing
      74: invokevirtual #53                 // Method handleEspExceptions:(Lorg/hpccsystems/ws/client/wrappers/ArrayOfEspExceptionWrapper;Ljava/lang/String;)V
      77: new           #62                 // class org/hpccsystems/ws/client/wrappers/gen/wscodesign/SignResponseWrapper
      80: dup
      81: aload_2
      82: invokespecial #63                 // Method org/hpccsystems/ws/client/wrappers/gen/wscodesign/SignResponseWrapper."<init>":(Lorg/hpccsystems/ws/client/gen/axis2/wscodesign/v1_01/SignResponse;)V
      85: areturn
    Exception table:
       from    to  target type
          21    36    39   Class java/rmi/RemoteException

  public org.hpccsystems.ws.client.wrappers.gen.wscodesign.VerifyResponseWrapper verify(org.hpccsystems.ws.client.wrappers.gen.wscodesign.VerifyRequestWrapper) throws java.lang.Exception;
    Code:
       0: aload_1
       1: ifnonnull     14
       4: new           #35                 // class java/lang/Exception
       7: dup
       8: ldc           #64                 // String HPCCWsCodeSignClient.verify: Must provide valid VerifyRequestWrapper!
      10: invokespecial #42                 // Method java/lang/Exception."<init>":(Ljava/lang/String;)V
      13: athrow
      14: aload_0
      15: invokevirtual #43                 // Method verifyStub:()Lorg/apache/axis2/client/Stub;
      18: pop
      19: aconst_null
      20: astore_2
      21: aload_0
      22: getfield      #34                 // Field stub:Lorg/apache/axis2/client/Stub;
      25: checkcast     #1                  // class org/hpccsystems/ws/client/gen/axis2/wscodesign/v1_01/Ws_codesignStub
      28: aload_1
      29: invokevirtual #65                 // Method org/hpccsystems/ws/client/wrappers/gen/wscodesign/VerifyRequestWrapper.getRaw:()Lorg/hpccsystems/ws/client/gen/axis2/wscodesign/v1_01/VerifyRequest;
      32: invokevirtual #66                 // Method org/hpccsystems/ws/client/gen/axis2/wscodesign/v1_01/Ws_codesignStub.verify:(Lorg/hpccsystems/ws/client/gen/axis2/wscodesign/v1_01/VerifyRequest;)Lorg/hpccsystems/ws/client/gen/axis2/wscodesign/v1_01/VerifyResponse;
      35: astore_2
      36: goto          51
      39: astore_3
      40: new           #35                 // class java/lang/Exception
      43: dup
      44: ldc           #67                 // String HPCCWSRESOURCESClient.serviceQuery(ServiceQueryRequestWrapper) encountered RemoteException.
      46: aload_3
      47: invokespecial #48                 // Method java/lang/Exception."<init>":(Ljava/lang/String;Ljava/lang/Throwable;)V
      50: athrow
      51: aload_2
      52: invokevirtual #68                 // Method org/hpccsystems/ws/client/gen/axis2/wscodesign/v1_01/VerifyResponse.getExceptions:()Lorg/hpccsystems/ws/client/gen/axis2/wscodesign/v1_01/ArrayOfEspException;
      55: ifnull        77
      58: aload_2
      59: invokevirtual #68                 // Method org/hpccsystems/ws/client/gen/axis2/wscodesign/v1_01/VerifyResponse.getExceptions:()Lorg/hpccsystems/ws/client/gen/axis2/wscodesign/v1_01/ArrayOfEspException;
      62: astore_3
      63: aload_0
      64: new           #50                 // class org/hpccsystems/ws/client/wrappers/ArrayOfEspExceptionWrapper
      67: dup
      68: aload_3
      69: invokespecial #51                 // Method org/hpccsystems/ws/client/wrappers/ArrayOfEspExceptionWrapper."<init>":(Lorg/hpccsystems/ws/client/gen/axis2/wscodesign/v1_01/ArrayOfEspException;)V
      72: ldc           #69                 // String Error processing service query
      74: invokevirtual #53                 // Method handleEspExceptions:(Lorg/hpccsystems/ws/client/wrappers/ArrayOfEspExceptionWrapper;Ljava/lang/String;)V
      77: new           #70                 // class org/hpccsystems/ws/client/wrappers/gen/wscodesign/VerifyResponseWrapper
      80: dup
      81: aload_2
      82: invokespecial #71                 // Method org/hpccsystems/ws/client/wrappers/gen/wscodesign/VerifyResponseWrapper."<init>":(Lorg/hpccsystems/ws/client/gen/axis2/wscodesign/v1_01/VerifyResponse;)V
      85: areturn
    Exception table:
       from    to  target type
          21    36    39   Class java/rmi/RemoteException

  public boolean ping() throws java.lang.Exception;
    Code:
       0: aload_0
       1: invokevirtual #43                 // Method verifyStub:()Lorg/apache/axis2/client/Stub;
       4: pop
       5: aload_0
       6: getfield      #34                 // Field stub:Lorg/apache/axis2/client/Stub;
       9: checkcast     #1                  // class org/hpccsystems/ws/client/gen/axis2/wscodesign/v1_01/Ws_codesignStub
      12: new           #72                 // class org/hpccsystems/ws/client/gen/axis2/wscodesign/v1_01/Ws_codesignPingRequest
      15: dup
      16: invokespecial #73                 // Method org/hpccsystems/ws/client/gen/axis2/wscodesign/v1_01/Ws_codesignPingRequest."<init>":()V
      19: invokevirtual #74                 // Method org/hpccsystems/ws/client/gen/axis2/wscodesign/v1_01/Ws_codesignStub.ping:(Lorg/hpccsystems/ws/client/gen/axis2/wscodesign/v1_01/Ws_codesignPingRequest;)Lorg/hpccsystems/ws/client/gen/axis2/wscodesign/v1_01/Ws_codesignPingResponse;
      22: pop
      23: goto          41
      26: astore_1
      27: getstatic     #11                 // Field log:Lorg/apache/logging/log4j/Logger;
      30: aload_1
      31: invokevirtual #38                 // Method java/lang/Exception.getLocalizedMessage:()Ljava/lang/String;
      34: invokeinterface #13,  2           // InterfaceMethod org/apache/logging/log4j/Logger.error:(Ljava/lang/String;)V
      39: iconst_0
      40: ireturn
      41: iconst_1
      42: ireturn
    Exception table:
       from    to  target type
           5    23    26   Class java/lang/Exception

  static {};
    Code:
       0: ldc           #15                 // class org/hpccsystems/ws/client/HPCCWsCodeSignClient
       2: invokestatic  #75                 // Method org/apache/logging/log4j/LogManager.getLogger:(Ljava/lang/Class;)Lorg/apache/logging/log4j/Logger;
       5: putstatic     #11                 // Field log:Lorg/apache/logging/log4j/Logger;
       8: iconst_m1
       9: putstatic     #8                  // Field DEFAULTSERVICEPORT:I
      12: aconst_null
      13: putstatic     #4                  // Field WSDLURL:Ljava/lang/String;
      16: return
}
