Compiled from "SecurityActions.java"
final class org.apache.cxf.resource.SecurityActions {
  private org.apache.cxf.resource.SecurityActions();
    Code:
       0: aload_0
       1: invokespecial #1                  // Method java/lang/Object."<init>":()V
       4: return

  static boolean fileExists(java.io.File, java.security.Permission);
    Code:
       0: invokestatic  #2                  // Method java/lang/System.getSecurityManager:()Ljava/lang/SecurityManager;
       3: astore_2
       4: aload_2
       5: ifnonnull     13
       8: aload_0
       9: invokevirtual #3                  // Method java/io/File.exists:()Z
      12: ireturn
      13: aload_2
      14: aload_1
      15: invokevirtual #4                  // Method java/lang/SecurityManager.checkPermission:(Ljava/security/Permission;)V
      18: new           #5                  // class org/apache/cxf/resource/SecurityActions$1
      21: dup
      22: aload_0
      23: invokespecial #6                  // Method org/apache/cxf/resource/SecurityActions$1."<init>":(Ljava/io/File;)V
      26: invokestatic  #7                  // Method java/security/AccessController.doPrivileged:(Ljava/security/PrivilegedAction;)Ljava/lang/Object;
      29: checkcast     #8                  // class java/lang/Boolean
      32: invokevirtual #9                  // Method java/lang/Boolean.booleanValue:()Z
      35: ireturn
}
