Compiled from "JmxMetricWriter.java"
public class org.springframework.boot.actuate.metrics.jmx.JmxMetricWriter$MetricValue {
  private double value;

  private long lastUpdated;

  public org.springframework.boot.actuate.metrics.jmx.JmxMetricWriter$MetricValue();
    Code:
       0: aload_0
       1: invokespecial #1                  // Method java/lang/Object."<init>":()V
       4: aload_0
       5: lconst_0
       6: putfield      #2                  // Field lastUpdated:J
       9: return

  public void setValue(double);
    Code:
       0: aload_0
       1: getfield      #3                  // Field value:D
       4: dload_1
       5: dcmpl
       6: ifeq          16
       9: aload_0
      10: invokestatic  #4                  // Method java/lang/System.currentTimeMillis:()J
      13: putfield      #2                  // Field lastUpdated:J
      16: aload_0
      17: dload_1
      18: putfield      #3                  // Field value:D
      21: return

  public void increment(long);
    Code:
       0: aload_0
       1: invokestatic  #4                  // Method java/lang/System.currentTimeMillis:()J
       4: putfield      #2                  // Field lastUpdated:J
       7: aload_0
       8: dup
       9: getfield      #3                  // Field value:D
      12: lload_1
      13: l2d
      14: dadd
      15: putfield      #3                  // Field value:D
      18: return

  public double getValue();
    Code:
       0: aload_0
       1: getfield      #3                  // Field value:D
       4: dreturn

  public java.util.Date getLastUpdated();
    Code:
       0: new           #5                  // class java/util/Date
       3: dup
       4: aload_0
       5: getfield      #2                  // Field lastUpdated:J
       8: invokespecial #6                  // Method java/util/Date."<init>":(J)V
      11: areturn
}
