Compiled from "BookieAuthZFactory.java"
public class org.apache.bookkeeper.tls.BookieAuthZFactory implements org.apache.bookkeeper.auth.BookieAuthProvider$Factory {
  private static final org.slf4j.Logger log;

  public java.lang.String[] allowedRoles;

  public org.apache.bookkeeper.tls.BookieAuthZFactory();
    Code:
       0: aload_0
       1: invokespecial #2                  // Method java/lang/Object."<init>":()V
       4: return

  public java.lang.String getPluginName();
    Code:
       0: ldc           #3                  // String BookieAuthZFactory
       2: areturn

  public void init(org.apache.bookkeeper.conf.ServerConfiguration) throws java.io.IOException;
    Code:
       0: aload_0
       1: aload_1
       2: invokevirtual #4                  // Method org/apache/bookkeeper/conf/ServerConfiguration.getAuthorizedRoles:()[Ljava/lang/String;
       5: putfield      #5                  // Field allowedRoles:[Ljava/lang/String;
       8: aload_0
       9: getfield      #5                  // Field allowedRoles:[Ljava/lang/String;
      12: ifnull        23
      15: aload_0
      16: getfield      #5                  // Field allowedRoles:[Ljava/lang/String;
      19: arraylength
      20: ifne          33
      23: new           #6                  // class java/lang/RuntimeException
      26: dup
      27: ldc           #7                  // String Configuration option \'bookieAuthProviderFactoryClass\' is set to \'BookieAuthZFactory\' but no roles set for configuration field \'authorizedRoles\'.
      29: invokespecial #8                  // Method java/lang/RuntimeException."<init>":(Ljava/lang/String;)V
      32: athrow
      33: aload_0
      34: getfield      #5                  // Field allowedRoles:[Ljava/lang/String;
      37: astore_2
      38: aload_2
      39: arraylength
      40: istore_3
      41: iconst_0
      42: istore        4
      44: iload         4
      46: iload_3
      47: if_icmpge     80
      50: aload_2
      51: iload         4
      53: aaload
      54: astore        5
      56: aload         5
      58: invokestatic  #9                  // Method com/google/common/base/Strings.isNullOrEmpty:(Ljava/lang/String;)Z
      61: ifeq          74
      64: new           #6                  // class java/lang/RuntimeException
      67: dup
      68: ldc           #7                  // String Configuration option \'bookieAuthProviderFactoryClass\' is set to \'BookieAuthZFactory\' but no roles set for configuration field \'authorizedRoles\'.
      70: invokespecial #8                  // Method java/lang/RuntimeException."<init>":(Ljava/lang/String;)V
      73: athrow
      74: iinc          4, 1
      77: goto          44
      80: return

  public org.apache.bookkeeper.auth.BookieAuthProvider newProvider(org.apache.bookkeeper.proto.BookieConnectionPeer, org.apache.bookkeeper.auth.AuthCallbacks$GenericCallback<java.lang.Void>);
    Code:
       0: new           #10                 // class org/apache/bookkeeper/tls/BookieAuthZFactory$1
       3: dup
       4: aload_0
       5: aload_2
       6: aload_1
       7: invokespecial #11                 // Method org/apache/bookkeeper/tls/BookieAuthZFactory$1."<init>":(Lorg/apache/bookkeeper/tls/BookieAuthZFactory;Lorg/apache/bookkeeper/auth/AuthCallbacks$GenericCallback;Lorg/apache/bookkeeper/proto/BookieConnectionPeer;)V
      10: areturn

  static org.slf4j.Logger access$000();
    Code:
       0: getstatic     #1                  // Field log:Lorg/slf4j/Logger;
       3: areturn

  static {};
    Code:
       0: ldc           #12                 // class org/apache/bookkeeper/tls/BookieAuthZFactory
       2: invokestatic  #13                 // Method org/slf4j/LoggerFactory.getLogger:(Ljava/lang/Class;)Lorg/slf4j/Logger;
       5: putstatic     #1                  // Field log:Lorg/slf4j/Logger;
       8: return
}
