Compiled from "ESchoolParser.java"
public class me.vertretungsplan.parser.ESchoolParser extends me.vertretungsplan.parser.BaseParser {
  private static final java.lang.String BASE_URL;

  private static final java.lang.String ENCODING;

  public me.vertretungsplan.parser.ESchoolParser(me.vertretungsplan.objects.SubstitutionScheduleData, me.vertretungsplan.parser.CookieProvider);
    Code:
       0: aload_0
       1: aload_1
       2: aload_2
       3: invokespecial #1                  // Method me/vertretungsplan/parser/BaseParser."<init>":(Lme/vertretungsplan/objects/SubstitutionScheduleData;Lme/vertretungsplan/parser/CookieProvider;)V
       6: return

  public me.vertretungsplan.objects.SubstitutionSchedule getSubstitutionSchedule() throws java.io.IOException, org.json.JSONException, me.vertretungsplan.exception.CredentialInvalidException;
    Code:
       0: aload_0
       1: getfield      #2                  // Field credential:Lme/vertretungsplan/objects/credential/Credential;
       4: ifnull        46
       7: aload_0
       8: getfield      #2                  // Field credential:Lme/vertretungsplan/objects/credential/Credential;
      11: instanceof    #3                  // class me/vertretungsplan/objects/credential/PasswordCredential
      14: ifeq          46
      17: aload_0
      18: getfield      #2                  // Field credential:Lme/vertretungsplan/objects/credential/Credential;
      21: checkcast     #3                  // class me/vertretungsplan/objects/credential/PasswordCredential
      24: invokevirtual #4                  // Method me/vertretungsplan/objects/credential/PasswordCredential.getPassword:()Ljava/lang/String;
      27: ifnull        46
      30: aload_0
      31: getfield      #2                  // Field credential:Lme/vertretungsplan/objects/credential/Credential;
      34: checkcast     #3                  // class me/vertretungsplan/objects/credential/PasswordCredential
      37: invokevirtual #4                  // Method me/vertretungsplan/objects/credential/PasswordCredential.getPassword:()Ljava/lang/String;
      40: invokevirtual #5                  // Method java/lang/String.isEmpty:()Z
      43: ifeq          56
      46: new           #6                  // class java/io/IOException
      49: dup
      50: ldc           #7                  // String no login
      52: invokespecial #8                  // Method java/io/IOException."<init>":(Ljava/lang/String;)V
      55: athrow
      56: aload_0
      57: getfield      #9                  // Field scheduleData:Lme/vertretungsplan/objects/SubstitutionScheduleData;
      60: invokestatic  #10                 // Method me/vertretungsplan/objects/SubstitutionSchedule.fromData:(Lme/vertretungsplan/objects/SubstitutionScheduleData;)Lme/vertretungsplan/objects/SubstitutionSchedule;
      63: astore_1
      64: new           #11                 // class java/util/ArrayList
      67: dup
      68: invokespecial #12                 // Method java/util/ArrayList."<init>":()V
      71: astore_2
      72: aload_2
      73: new           #13                 // class org/apache/http/message/BasicNameValuePair
      76: dup
      77: ldc           #14                 // String wp
      79: aload_0
      80: getfield      #9                  // Field scheduleData:Lme/vertretungsplan/objects/SubstitutionScheduleData;
      83: invokevirtual #15                 // Method me/vertretungsplan/objects/SubstitutionScheduleData.getData:()Lorg/json/JSONObject;
      86: ldc           #16                 // String id
      88: invokevirtual #17                 // Method org/json/JSONObject.getString:(Ljava/lang/String;)Ljava/lang/String;
      91: invokespecial #18                 // Method org/apache/http/message/BasicNameValuePair."<init>":(Ljava/lang/String;Ljava/lang/String;)V
      94: invokeinterface #19,  2           // InterfaceMethod java/util/List.add:(Ljava/lang/Object;)Z
      99: pop
     100: aload_2
     101: new           #13                 // class org/apache/http/message/BasicNameValuePair
     104: dup
     105: ldc           #20                 // String go
     107: ldc           #21                 // String vplan
     109: invokespecial #18                 // Method org/apache/http/message/BasicNameValuePair."<init>":(Ljava/lang/String;Ljava/lang/String;)V
     112: invokeinterface #19,  2           // InterfaceMethod java/util/List.add:(Ljava/lang/Object;)Z
     117: pop
     118: aload_2
     119: new           #13                 // class org/apache/http/message/BasicNameValuePair
     122: dup
     123: ldc           #22                 // String content
     125: ldc           #23                 // String x14
     127: invokespecial #18                 // Method org/apache/http/message/BasicNameValuePair."<init>":(Ljava/lang/String;Ljava/lang/String;)V
     130: invokeinterface #19,  2           // InterfaceMethod java/util/List.add:(Ljava/lang/Object;)Z
     135: pop
     136: aload_2
     137: new           #13                 // class org/apache/http/message/BasicNameValuePair
     140: dup
     141: ldc           #24                 // String sortby
     143: ldc           #25                 // String S
     145: invokespecial #18                 // Method org/apache/http/message/BasicNameValuePair."<init>":(Ljava/lang/String;Ljava/lang/String;)V
     148: invokeinterface #19,  2           // InterfaceMethod java/util/List.add:(Ljava/lang/Object;)Z
     153: pop
     154: new           #26                 // class java/lang/StringBuilder
     157: dup
     158: invokespecial #27                 // Method java/lang/StringBuilder."<init>":()V
     161: ldc           #28                 // String http://eschool.topackt.com/?
     163: invokevirtual #29                 // Method java/lang/StringBuilder.append:(Ljava/lang/String;)Ljava/lang/StringBuilder;
     166: aload_2
     167: ldc           #30                 // String UTF-8
     169: invokestatic  #31                 // Method org/apache/http/client/utils/URLEncodedUtils.format:(Ljava/util/List;Ljava/lang/String;)Ljava/lang/String;
     172: invokevirtual #29                 // Method java/lang/StringBuilder.append:(Ljava/lang/String;)Ljava/lang/StringBuilder;
     175: invokevirtual #32                 // Method java/lang/StringBuilder.toString:()Ljava/lang/String;
     178: astore_3
     179: aload_0
     180: aload_3
     181: ldc           #33                 // String ISO-8859-1
     183: invokevirtual #34                 // Method httpGet:(Ljava/lang/String;Ljava/lang/String;)Ljava/lang/String;
     186: invokestatic  #35                 // Method org/jsoup/Jsoup.parse:(Ljava/lang/String;)Lorg/jsoup/nodes/Document;
     189: astore        4
     191: aload         4
     193: ldc           #36                 // String form[name=loginform]
     195: invokevirtual #37                 // Method org/jsoup/nodes/Document.select:(Ljava/lang/String;)Lorg/jsoup/select/Elements;
     198: invokevirtual #38                 // Method org/jsoup/select/Elements.size:()I
     201: ifle          312
     204: aload_0
     205: getfield      #9                  // Field scheduleData:Lme/vertretungsplan/objects/SubstitutionScheduleData;
     208: invokevirtual #39                 // Method me/vertretungsplan/objects/SubstitutionScheduleData.getAuthenticationData:()Lme/vertretungsplan/objects/authentication/AuthenticationData;
     211: instanceof    #40                 // class me/vertretungsplan/objects/authentication/PasswordAuthenticationData
     214: ifeq          312
     217: new           #11                 // class java/util/ArrayList
     220: dup
     221: invokespecial #12                 // Method java/util/ArrayList."<init>":()V
     224: astore        5
     226: aload         5
     228: new           #13                 // class org/apache/http/message/BasicNameValuePair
     231: dup
     232: ldc           #41                 // String password
     234: aload_0
     235: getfield      #2                  // Field credential:Lme/vertretungsplan/objects/credential/Credential;
     238: checkcast     #3                  // class me/vertretungsplan/objects/credential/PasswordCredential
     241: invokevirtual #4                  // Method me/vertretungsplan/objects/credential/PasswordCredential.getPassword:()Ljava/lang/String;
     244: invokespecial #18                 // Method org/apache/http/message/BasicNameValuePair."<init>":(Ljava/lang/String;Ljava/lang/String;)V
     247: invokeinterface #19,  2           // InterfaceMethod java/util/List.add:(Ljava/lang/Object;)Z
     252: pop
     253: aload         5
     255: new           #13                 // class org/apache/http/message/BasicNameValuePair
     258: dup
     259: ldc           #42                 // String login
     261: ldc           #43                 // String
     263: invokespecial #18                 // Method org/apache/http/message/BasicNameValuePair."<init>":(Ljava/lang/String;Ljava/lang/String;)V
     266: invokeinterface #19,  2           // InterfaceMethod java/util/List.add:(Ljava/lang/Object;)Z
     271: pop
     272: aload_0
     273: aload_3
     274: ldc           #33                 // String ISO-8859-1
     276: aload         5
     278: invokevirtual #44                 // Method httpPost:(Ljava/lang/String;Ljava/lang/String;Ljava/util/List;)Ljava/lang/String;
     281: invokestatic  #35                 // Method org/jsoup/Jsoup.parse:(Ljava/lang/String;)Lorg/jsoup/nodes/Document;
     284: astore        4
     286: aload         4
     288: ldc           #45                 // String font[color=red]
     290: invokevirtual #37                 // Method org/jsoup/nodes/Document.select:(Ljava/lang/String;)Lorg/jsoup/select/Elements;
     293: invokevirtual #46                 // Method org/jsoup/select/Elements.text:()Ljava/lang/String;
     296: ldc           #47                 // String fehlgeschlagen
     298: invokevirtual #48                 // Method java/lang/String.contains:(Ljava/lang/CharSequence;)Z
     301: ifeq          312
     304: new           #49                 // class me/vertretungsplan/exception/CredentialInvalidException
     307: dup
     308: invokespecial #50                 // Method me/vertretungsplan/exception/CredentialInvalidException."<init>":()V
     311: athrow
     312: aload         4
     314: ldc           #51                 // String #Content table
     316: invokevirtual #37                 // Method org/jsoup/nodes/Document.select:(Ljava/lang/String;)Lorg/jsoup/select/Elements;
     319: invokevirtual #52                 // Method org/jsoup/select/Elements.first:()Lorg/jsoup/nodes/Element;
     322: ldc           #53                 // String td
     324: invokevirtual #54                 // Method org/jsoup/nodes/Element.select:(Ljava/lang/String;)Lorg/jsoup/select/Elements;
     327: iconst_1
     328: invokevirtual #55                 // Method org/jsoup/select/Elements.get:(I)Ljava/lang/Object;
     331: checkcast     #56                 // class org/jsoup/nodes/Element
     334: invokevirtual #57                 // Method org/jsoup/nodes/Element.ownText:()Ljava/lang/String;
     337: astore        5
     339: ldc           #58                 // String Letzte Aktualisierung: (\\d{2}.\\d{2}.\\d{4} - \\d{2}:\\d{2})
     341: invokestatic  #59                 // Method java/util/regex/Pattern.compile:(Ljava/lang/String;)Ljava/util/regex/Pattern;
     344: astore        6
     346: aload         6
     348: aload         5
     350: invokevirtual #60                 // Method java/util/regex/Pattern.matcher:(Ljava/lang/CharSequence;)Ljava/util/regex/Matcher;
     353: astore        7
     355: aload         7
     357: invokevirtual #61                 // Method java/util/regex/Matcher.find:()Z
     360: ifeq          385
     363: ldc           #62                 // String dd.MM.yyyy - HH:mm
     365: invokestatic  #63                 // Method org/joda/time/format/DateTimeFormat.forPattern:(Ljava/lang/String;)Lorg/joda/time/format/DateTimeFormatter;
     368: aload         7
     370: iconst_1
     371: invokevirtual #64                 // Method java/util/regex/Matcher.group:(I)Ljava/lang/String;
     374: invokevirtual #65                 // Method org/joda/time/format/DateTimeFormatter.parseLocalDateTime:(Ljava/lang/String;)Lorg/joda/time/LocalDateTime;
     377: astore        8
     379: aload_1
     380: aload         8
     382: invokevirtual #66                 // Method me/vertretungsplan/objects/SubstitutionSchedule.setLastChange:(Lorg/joda/time/LocalDateTime;)V
     385: aload         4
     387: ldc           #67                 // String center b
     389: invokevirtual #37                 // Method org/jsoup/nodes/Document.select:(Ljava/lang/String;)Lorg/jsoup/select/Elements;
     392: astore        8
     394: aload         4
     396: ldc           #68                 // String table#DATA
     398: invokevirtual #37                 // Method org/jsoup/nodes/Document.select:(Ljava/lang/String;)Lorg/jsoup/select/Elements;
     401: astore        9
     403: aload         9
     405: iconst_0
     406: invokevirtual #55                 // Method org/jsoup/select/Elements.get:(I)Ljava/lang/Object;
     409: checkcast     #56                 // class org/jsoup/nodes/Element
     412: invokevirtual #69                 // Method org/jsoup/nodes/Element.text:()Ljava/lang/String;
     415: ldc           #70                 // String Keine Daten verfügbar
     417: invokevirtual #48                 // Method java/lang/String.contains:(Ljava/lang/CharSequence;)Z
     420: ifne          536
     423: aload         8
     425: invokevirtual #38                 // Method org/jsoup/select/Elements.size:()I
     428: aload         9
     430: invokevirtual #38                 // Method org/jsoup/select/Elements.size:()I
     433: if_icmpeq     446
     436: new           #6                  // class java/io/IOException
     439: dup
     440: ldc           #71                 // String Anzahl Überschriften != Anzahl Tabellen
     442: invokespecial #8                  // Method java/io/IOException."<init>":(Ljava/lang/String;)V
     445: athrow
     446: iconst_0
     447: istore        10
     449: iload         10
     451: aload         8
     453: invokevirtual #38                 // Method org/jsoup/select/Elements.size:()I
     456: if_icmpge     536
     459: new           #72                 // class me/vertretungsplan/objects/SubstitutionScheduleDay
     462: dup
     463: invokespecial #73                 // Method me/vertretungsplan/objects/SubstitutionScheduleDay."<init>":()V
     466: astore        11
     468: getstatic     #74                 // Field java/lang/System.out:Ljava/io/PrintStream;
     471: aload         8
     473: iload         10
     475: invokevirtual #55                 // Method org/jsoup/select/Elements.get:(I)Ljava/lang/Object;
     478: checkcast     #56                 // class org/jsoup/nodes/Element
     481: invokevirtual #69                 // Method org/jsoup/nodes/Element.text:()Ljava/lang/String;
     484: invokevirtual #75                 // Method java/io/PrintStream.println:(Ljava/lang/String;)V
     487: aload         11
     489: aload         8
     491: iload         10
     493: invokevirtual #55                 // Method org/jsoup/select/Elements.get:(I)Ljava/lang/Object;
     496: checkcast     #56                 // class org/jsoup/nodes/Element
     499: invokevirtual #69                 // Method org/jsoup/nodes/Element.text:()Ljava/lang/String;
     502: invokestatic  #76                 // Method me/vertretungsplan/parser/ParserUtils.parseDate:(Ljava/lang/String;)Lorg/joda/time/LocalDate;
     505: invokevirtual #77                 // Method me/vertretungsplan/objects/SubstitutionScheduleDay.setDate:(Lorg/joda/time/LocalDate;)V
     508: aload_0
     509: aload         9
     511: iload         10
     513: invokevirtual #55                 // Method org/jsoup/select/Elements.get:(I)Ljava/lang/Object;
     516: checkcast     #56                 // class org/jsoup/nodes/Element
     519: aload         11
     521: invokespecial #78                 // Method parseTable:(Lorg/jsoup/nodes/Element;Lme/vertretungsplan/objects/SubstitutionScheduleDay;)V
     524: aload_1
     525: aload         11
     527: invokevirtual #79                 // Method me/vertretungsplan/objects/SubstitutionSchedule.addDay:(Lme/vertretungsplan/objects/SubstitutionScheduleDay;)V
     530: iinc          10, 1
     533: goto          449
     536: aload_1
     537: aload_0
     538: invokevirtual #80                 // Method getAllClasses:()Ljava/util/List;
     541: invokevirtual #81                 // Method me/vertretungsplan/objects/SubstitutionSchedule.setClasses:(Ljava/util/List;)V
     544: aload_1
     545: aload_0
     546: invokevirtual #82                 // Method getAllTeachers:()Ljava/util/List;
     549: invokevirtual #83                 // Method me/vertretungsplan/objects/SubstitutionSchedule.setTeachers:(Ljava/util/List;)V
     552: aload_1
     553: areturn

  private void parseTable(org.jsoup.nodes.Element, me.vertretungsplan.objects.SubstitutionScheduleDay);
    Code:
       0: aload_1
       1: ldc           #84                 // String th[colspan=10]
       3: invokevirtual #54                 // Method org/jsoup/nodes/Element.select:(Ljava/lang/String;)Lorg/jsoup/select/Elements;
       6: invokevirtual #85                 // Method org/jsoup/select/Elements.iterator:()Ljava/util/Iterator;
       9: astore_3
      10: aload_3
      11: invokeinterface #86,  1           // InterfaceMethod java/util/Iterator.hasNext:()Z
      16: ifeq          394
      19: aload_3
      20: invokeinterface #87,  1           // InterfaceMethod java/util/Iterator.next:()Ljava/lang/Object;
      25: checkcast     #56                 // class org/jsoup/nodes/Element
      28: astore        4
      30: ldc           #88                 // String (\\d+)\\. Stunde
      32: invokestatic  #59                 // Method java/util/regex/Pattern.compile:(Ljava/lang/String;)Ljava/util/regex/Pattern;
      35: astore        6
      37: aload         6
      39: aload         4
      41: invokevirtual #69                 // Method org/jsoup/nodes/Element.text:()Ljava/lang/String;
      44: invokevirtual #60                 // Method java/util/regex/Pattern.matcher:(Ljava/lang/CharSequence;)Ljava/util/regex/Matcher;
      47: astore        7
      49: aload         7
      51: invokevirtual #61                 // Method java/util/regex/Matcher.find:()Z
      54: ifeq          68
      57: aload         7
      59: iconst_1
      60: invokevirtual #64                 // Method java/util/regex/Matcher.group:(I)Ljava/lang/String;
      63: astore        5
      65: goto          75
      68: aload         4
      70: invokevirtual #69                 // Method org/jsoup/nodes/Element.text:()Ljava/lang/String;
      73: astore        5
      75: aload         4
      77: invokevirtual #89                 // Method org/jsoup/nodes/Element.parent:()Lorg/jsoup/nodes/Element;
      80: invokevirtual #90                 // Method org/jsoup/nodes/Element.nextElementSibling:()Lorg/jsoup/nodes/Element;
      83: invokevirtual #90                 // Method org/jsoup/nodes/Element.nextElementSibling:()Lorg/jsoup/nodes/Element;
      86: astore        8
      88: aload         8
      90: ifnull        391
      93: aload         8
      95: ldc           #91                 // String th
      97: invokevirtual #54                 // Method org/jsoup/nodes/Element.select:(Ljava/lang/String;)Lorg/jsoup/select/Elements;
     100: invokevirtual #38                 // Method org/jsoup/select/Elements.size:()I
     103: ifne          391
     106: new           #92                 // class me/vertretungsplan/objects/Substitution
     109: dup
     110: invokespecial #93                 // Method me/vertretungsplan/objects/Substitution."<init>":()V
     113: astore        9
     115: aload         9
     117: aload         5
     119: invokevirtual #94                 // Method me/vertretungsplan/objects/Substitution.setLesson:(Ljava/lang/String;)V
     122: aload         8
     124: ldc           #53                 // String td
     126: invokevirtual #54                 // Method org/jsoup/nodes/Element.select:(Ljava/lang/String;)Lorg/jsoup/select/Elements;
     129: astore        10
     131: aload         10
     133: iconst_0
     134: invokevirtual #55                 // Method org/jsoup/select/Elements.get:(I)Ljava/lang/Object;
     137: checkcast     #56                 // class org/jsoup/nodes/Element
     140: invokevirtual #69                 // Method org/jsoup/nodes/Element.text:()Ljava/lang/String;
     143: ldc           #95                 // String ,
     145: invokevirtual #96                 // Method java/lang/String.split:(Ljava/lang/String;)[Ljava/lang/String;
     148: astore        11
     150: aload         9
     152: new           #97                 // class java/util/HashSet
     155: dup
     156: aload         11
     158: invokestatic  #98                 // Method java/util/Arrays.asList:([Ljava/lang/Object;)Ljava/util/List;
     161: invokespecial #99                 // Method java/util/HashSet."<init>":(Ljava/util/Collection;)V
     164: invokevirtual #100                // Method me/vertretungsplan/objects/Substitution.setClasses:(Ljava/util/Set;)V
     167: aload         9
     169: aload_0
     170: aload         10
     172: iconst_1
     173: invokevirtual #55                 // Method org/jsoup/select/Elements.get:(I)Ljava/lang/Object;
     176: checkcast     #56                 // class org/jsoup/nodes/Element
     179: invokespecial #101                // Method getPreviousValue:(Lorg/jsoup/nodes/Element;)Ljava/lang/String;
     182: invokevirtual #102                // Method me/vertretungsplan/objects/Substitution.setPreviousTeacher:(Ljava/lang/String;)V
     185: aload         9
     187: aload_0
     188: aload         10
     190: iconst_1
     191: invokevirtual #55                 // Method org/jsoup/select/Elements.get:(I)Ljava/lang/Object;
     194: checkcast     #56                 // class org/jsoup/nodes/Element
     197: invokespecial #103                // Method getNewValue:(Lorg/jsoup/nodes/Element;)Ljava/lang/String;
     200: invokevirtual #104                // Method me/vertretungsplan/objects/Substitution.setTeacher:(Ljava/lang/String;)V
     203: aload         9
     205: aload_0
     206: aload         10
     208: iconst_2
     209: invokevirtual #55                 // Method org/jsoup/select/Elements.get:(I)Ljava/lang/Object;
     212: checkcast     #56                 // class org/jsoup/nodes/Element
     215: invokespecial #101                // Method getPreviousValue:(Lorg/jsoup/nodes/Element;)Ljava/lang/String;
     218: invokevirtual #105                // Method me/vertretungsplan/objects/Substitution.setPreviousSubject:(Ljava/lang/String;)V
     221: aload         9
     223: aload_0
     224: aload         10
     226: iconst_2
     227: invokevirtual #55                 // Method org/jsoup/select/Elements.get:(I)Ljava/lang/Object;
     230: checkcast     #56                 // class org/jsoup/nodes/Element
     233: invokespecial #103                // Method getNewValue:(Lorg/jsoup/nodes/Element;)Ljava/lang/String;
     236: invokevirtual #106                // Method me/vertretungsplan/objects/Substitution.setSubject:(Ljava/lang/String;)V
     239: aload         9
     241: aload_0
     242: aload         10
     244: iconst_3
     245: invokevirtual #55                 // Method org/jsoup/select/Elements.get:(I)Ljava/lang/Object;
     248: checkcast     #56                 // class org/jsoup/nodes/Element
     251: invokespecial #101                // Method getPreviousValue:(Lorg/jsoup/nodes/Element;)Ljava/lang/String;
     254: invokevirtual #107                // Method me/vertretungsplan/objects/Substitution.setPreviousRoom:(Ljava/lang/String;)V
     257: aload         9
     259: aload_0
     260: aload         10
     262: iconst_3
     263: invokevirtual #55                 // Method org/jsoup/select/Elements.get:(I)Ljava/lang/Object;
     266: checkcast     #56                 // class org/jsoup/nodes/Element
     269: invokespecial #103                // Method getNewValue:(Lorg/jsoup/nodes/Element;)Ljava/lang/String;
     272: invokevirtual #108                // Method me/vertretungsplan/objects/Substitution.setRoom:(Ljava/lang/String;)V
     275: aload         10
     277: iconst_4
     278: invokevirtual #55                 // Method org/jsoup/select/Elements.get:(I)Ljava/lang/Object;
     281: checkcast     #56                 // class org/jsoup/nodes/Element
     284: invokevirtual #69                 // Method org/jsoup/nodes/Element.text:()Ljava/lang/String;
     287: invokevirtual #5                  // Method java/lang/String.isEmpty:()Z
     290: ifeq          317
     293: aload         9
     295: ldc           #109                // String Vertretung
     297: invokevirtual #110                // Method me/vertretungsplan/objects/Substitution.setType:(Ljava/lang/String;)V
     300: aload         9
     302: aload_0
     303: getfield      #111                // Field colorProvider:Lme/vertretungsplan/parser/ColorProvider;
     306: ldc           #109                // String Vertretung
     308: invokevirtual #112                // Method me/vertretungsplan/parser/ColorProvider.getColor:(Ljava/lang/String;)Ljava/lang/String;
     311: invokevirtual #113                // Method me/vertretungsplan/objects/Substitution.setColor:(Ljava/lang/String;)V
     314: goto          375
     317: aload         10
     319: iconst_4
     320: invokevirtual #55                 // Method org/jsoup/select/Elements.get:(I)Ljava/lang/Object;
     323: checkcast     #56                 // class org/jsoup/nodes/Element
     326: invokevirtual #69                 // Method org/jsoup/nodes/Element.text:()Ljava/lang/String;
     329: astore        12
     331: aload         9
     333: aload         12
     335: invokevirtual #114                // Method me/vertretungsplan/objects/Substitution.setDesc:(Ljava/lang/String;)V
     338: aload         12
     340: invokestatic  #115                // Method recognizeType:(Ljava/lang/String;)Ljava/lang/String;
     343: astore        13
     345: aload         13
     347: ifnonnull     354
     350: ldc           #109                // String Vertretung
     352: astore        13
     354: aload         9
     356: aload         13
     358: invokevirtual #110                // Method me/vertretungsplan/objects/Substitution.setType:(Ljava/lang/String;)V
     361: aload         9
     363: aload_0
     364: getfield      #111                // Field colorProvider:Lme/vertretungsplan/parser/ColorProvider;
     367: aload         13
     369: invokevirtual #112                // Method me/vertretungsplan/parser/ColorProvider.getColor:(Ljava/lang/String;)Ljava/lang/String;
     372: invokevirtual #113                // Method me/vertretungsplan/objects/Substitution.setColor:(Ljava/lang/String;)V
     375: aload_2
     376: aload         9
     378: invokevirtual #116                // Method me/vertretungsplan/objects/SubstitutionScheduleDay.addSubstitution:(Lme/vertretungsplan/objects/Substitution;)V
     381: aload         8
     383: invokevirtual #90                 // Method org/jsoup/nodes/Element.nextElementSibling:()Lorg/jsoup/nodes/Element;
     386: astore        8
     388: goto          88
     391: goto          10
     394: return

  private java.lang.String getNewValue(org.jsoup.nodes.Element);
    Code:
       0: aload_1
       1: invokevirtual #117                // Method org/jsoup/nodes/Element.textNodes:()Ljava/util/List;
       4: astore_2
       5: aload_2
       6: invokeinterface #118,  1          // InterfaceMethod java/util/List.size:()I
      11: iconst_1
      12: if_icmpne     32
      15: aload_2
      16: iconst_0
      17: invokeinterface #119,  2          // InterfaceMethod java/util/List.get:(I)Ljava/lang/Object;
      22: checkcast     #120                // class org/jsoup/nodes/TextNode
      25: invokevirtual #121                // Method org/jsoup/nodes/TextNode.text:()Ljava/lang/String;
      28: invokevirtual #122                // Method java/lang/String.trim:()Ljava/lang/String;
      31: areturn
      32: aload_2
      33: invokeinterface #118,  1          // InterfaceMethod java/util/List.size:()I
      38: iconst_2
      39: if_icmpne     59
      42: aload_2
      43: iconst_1
      44: invokeinterface #119,  2          // InterfaceMethod java/util/List.get:(I)Ljava/lang/Object;
      49: checkcast     #120                // class org/jsoup/nodes/TextNode
      52: invokevirtual #121                // Method org/jsoup/nodes/TextNode.text:()Ljava/lang/String;
      55: invokevirtual #122                // Method java/lang/String.trim:()Ljava/lang/String;
      58: areturn
      59: aconst_null
      60: areturn

  private java.lang.String getPreviousValue(org.jsoup.nodes.Element);
    Code:
       0: aload_1
       1: invokevirtual #117                // Method org/jsoup/nodes/Element.textNodes:()Ljava/util/List;
       4: astore_2
       5: aload_2
       6: invokeinterface #118,  1          // InterfaceMethod java/util/List.size:()I
      11: iconst_1
      12: if_icmpne     17
      15: aconst_null
      16: areturn
      17: aload_2
      18: invokeinterface #118,  1          // InterfaceMethod java/util/List.size:()I
      23: iconst_2
      24: if_icmpne     44
      27: aload_2
      28: iconst_0
      29: invokeinterface #119,  2          // InterfaceMethod java/util/List.get:(I)Ljava/lang/Object;
      34: checkcast     #120                // class org/jsoup/nodes/TextNode
      37: invokevirtual #121                // Method org/jsoup/nodes/TextNode.text:()Ljava/lang/String;
      40: invokevirtual #122                // Method java/lang/String.trim:()Ljava/lang/String;
      43: areturn
      44: aconst_null
      45: areturn

  public java.util.List<java.lang.String> getAllClasses() throws java.io.IOException, org.json.JSONException;
    Code:
       0: aload_0
       1: invokevirtual #123                // Method getClassesFromJson:()Ljava/util/List;
       4: areturn

  public java.util.List<java.lang.String> getAllTeachers();
    Code:
       0: aconst_null
       1: areturn
}
