Compiled from "ColorsAndFontsPreferencePage.java"
public final class org.eclipse.ui.internal.themes.ColorsAndFontsPreferencePage extends org.eclipse.jface.preference.PreferencePage implements org.eclipse.ui.IWorkbenchPreferencePage {
  private static final java.lang.String EMPTY;

  private static final java.lang.String SPACE;

  private static final java.lang.String SELECTED_ELEMENT_PREF;

  private static final java.lang.String EXPANDED_ELEMENTS_PREF;

  private static final java.lang.String EXPANDED_ELEMENTS_TOKEN;

  private static final char MARKER_CATEGORY;

  private static final char MARKER_COLOR;

  private static final char MARKER_FONT;

  private static final int DEFINITION_NOT_AVAIL_COLOR;

  private static final java.util.ResourceBundle RESOURCE_BUNDLE;

  private java.util.Map<java.lang.String, java.lang.Object[]> categoryMap;

  private org.eclipse.swt.graphics.Font appliedDialogFont;

  private java.util.Map<org.eclipse.ui.internal.themes.ColorDefinition, org.eclipse.swt.graphics.RGB> colorPreferencesToSet;

  private org.eclipse.ui.internal.themes.CascadingColorRegistry colorRegistry;

  private java.util.Map<java.lang.String, org.eclipse.swt.graphics.RGB> colorValuesToSet;

  private org.eclipse.swt.widgets.Composite defaultColorPreview;

  private org.eclipse.swt.widgets.Composite defaultFontPreview;

  private org.eclipse.swt.widgets.Composite defaultNoPreview;

  private org.eclipse.swt.graphics.Font currentFont;

  private org.eclipse.swt.graphics.Color currentColor;

  private org.eclipse.swt.widgets.Canvas colorSampler;

  private org.eclipse.swt.widgets.Canvas fontSampler;

  private java.lang.String fontSampleText;

  private java.util.List<org.eclipse.swt.widgets.Control> dialogFontWidgets;

  private org.eclipse.swt.widgets.Button fontChangeButton;

  private org.eclipse.swt.widgets.Button editDefaultButton;

  private org.eclipse.swt.widgets.Button goToDefaultButton;

  private org.eclipse.swt.widgets.Button expandAllButton;

  private java.util.Map<org.eclipse.ui.internal.themes.FontDefinition, org.eclipse.swt.graphics.FontData[]> fontPreferencesToSet;

  private org.eclipse.ui.internal.themes.CascadingFontRegistry fontRegistry;

  private org.eclipse.swt.widgets.Button fontResetButton;

  private org.eclipse.swt.widgets.Button fontSystemButton;

  private java.util.Map<java.lang.String, org.eclipse.swt.graphics.FontData[]> fontValuesToSet;

  private org.eclipse.swt.widgets.Composite previewComposite;

  private java.util.Map<org.eclipse.ui.internal.themes.ThemeElementCategory, org.eclipse.swt.widgets.Composite> previewMap;

  private java.util.Set<org.eclipse.ui.themes.IThemePreview> previewSet;

  private org.eclipse.swt.custom.StackLayout stackLayout;

  private final org.eclipse.ui.internal.themes.IThemeRegistry themeRegistry;

  private org.eclipse.ui.themes.ITheme currentTheme;

  private org.eclipse.ui.internal.themes.ColorsAndFontsPreferencePage$PresentationLabelProvider labelProvider;

  private org.eclipse.ui.internal.themes.ColorsAndFontsPreferencePage$CascadingThemeExt cascadingTheme;

  private org.eclipse.jface.util.IPropertyChangeListener themeChangeListener;

  private org.eclipse.ui.internal.Workbench workbench;

  private org.eclipse.ui.dialogs.FilteredTree tree;

  private org.eclipse.swt.widgets.Text descriptionText;

  private org.eclipse.e4.core.services.events.IEventBroker eventBroker;

  private org.osgi.service.event.EventHandler themeRegistryRestyledHandler;

  private org.eclipse.e4.ui.css.swt.theme.ITheme currentCSSTheme;

  private org.eclipse.e4.ui.css.swt.theme.IThemeEngine themeEngine;

  static final boolean $assertionsDisabled;

  static {};
    Code:
       0: ldc           #8                  // class org/eclipse/ui/internal/themes/ColorsAndFontsPreferencePage
       2: invokevirtual #1389               // Method java/lang/Class.desiredAssertionStatus:()Z
       5: ifne          12
       8: iconst_1
       9: goto          13
      12: iconst_0
      13: putstatic     #1345               // Field $assertionsDisabled:Z
      16: ldc           #8                  // class org/eclipse/ui/internal/themes/ColorsAndFontsPreferencePage
      18: invokevirtual #1390               // Method java/lang/Class.getName:()Ljava/lang/String;
      21: invokestatic  #1419               // Method java/util/ResourceBundle.getBundle:(Ljava/lang/String;)Ljava/util/ResourceBundle;
      24: putstatic     #1354               // Field RESOURCE_BUNDLE:Ljava/util/ResourceBundle;
      27: return

  public org.eclipse.ui.internal.themes.ColorsAndFontsPreferencePage();
    Code:
       0: aload_0
       1: invokespecial #1423               // Method org/eclipse/jface/preference/PreferencePage."<init>":()V
       4: aload_0
       5: new           #648                // class java/util/HashMap
       8: dup
       9: bipush        7
      11: invokespecial #1416               // Method java/util/HashMap."<init>":(I)V
      14: putfield      #1348               // Field categoryMap:Ljava/util/Map;
      17: aload_0
      18: new           #648                // class java/util/HashMap
      21: dup
      22: bipush        7
      24: invokespecial #1416               // Method java/util/HashMap."<init>":(I)V
      27: putfield      #1349               // Field colorPreferencesToSet:Ljava/util/Map;
      30: aload_0
      31: new           #648                // class java/util/HashMap
      34: dup
      35: bipush        7
      37: invokespecial #1416               // Method java/util/HashMap."<init>":(I)V
      40: putfield      #1350               // Field colorValuesToSet:Ljava/util/Map;
      43: aload_0
      44: new           #646                // class java/util/ArrayList
      47: dup
      48: invokespecial #1411               // Method java/util/ArrayList."<init>":()V
      51: putfield      #1347               // Field dialogFontWidgets:Ljava/util/List;
      54: aload_0
      55: new           #648                // class java/util/HashMap
      58: dup
      59: bipush        7
      61: invokespecial #1416               // Method java/util/HashMap."<init>":(I)V
      64: putfield      #1351               // Field fontPreferencesToSet:Ljava/util/Map;
      67: aload_0
      68: new           #648                // class java/util/HashMap
      71: dup
      72: bipush        7
      74: invokespecial #1416               // Method java/util/HashMap."<init>":(I)V
      77: putfield      #1352               // Field fontValuesToSet:Ljava/util/Map;
      80: aload_0
      81: new           #648                // class java/util/HashMap
      84: dup
      85: bipush        7
      87: invokespecial #1416               // Method java/util/HashMap."<init>":(I)V
      90: putfield      #1353               // Field previewMap:Ljava/util/Map;
      93: aload_0
      94: new           #649                // class java/util/HashSet
      97: dup
      98: bipush        7
     100: invokespecial #1417               // Method java/util/HashSet."<init>":(I)V
     103: putfield      #1355               // Field previewSet:Ljava/util/Set;
     106: aload_0
     107: new           #713                // class org/eclipse/ui/internal/themes/ColorsAndFontsPreferencePage$1
     110: dup
     111: aload_0
     112: invokespecial #1647               // Method org/eclipse/ui/internal/themes/ColorsAndFontsPreferencePage$1."<init>":(Lorg/eclipse/ui/internal/themes/ColorsAndFontsPreferencePage;)V
     115: putfield      #1385               // Field themeRegistryRestyledHandler:Lorg/osgi/service/event/EventHandler;
     118: aload_0
     119: invokestatic  #1541               // Method org/eclipse/ui/internal/WorkbenchPlugin.getDefault:()Lorg/eclipse/ui/internal/WorkbenchPlugin;
     122: invokevirtual #1542               // Method org/eclipse/ui/internal/WorkbenchPlugin.getThemeRegistry:()Lorg/eclipse/ui/internal/themes/IThemeRegistry;
     125: putfield      #1383               // Field themeRegistry:Lorg/eclipse/ui/internal/themes/IThemeRegistry;
     128: return

  public void applyData(java.lang.Object);
    Code:
       0: aload_0
       1: getfield      #1377               // Field tree:Lorg/eclipse/ui/dialogs/FilteredTree;
       4: ifnull        14
       7: aload_1
       8: instanceof    #640                // class java/lang/String
      11: ifne          15
      14: return
      15: aload_0
      16: getfield      #1377               // Field tree:Lorg/eclipse/ui/dialogs/FilteredTree;
      19: invokevirtual #1534               // Method org/eclipse/ui/dialogs/FilteredTree.getViewer:()Lorg/eclipse/jface/viewers/TreeViewer;
      22: invokevirtual #1438               // Method org/eclipse/jface/viewers/TreeViewer.getInput:()Ljava/lang/Object;
      25: checkcast     #728                // class org/eclipse/ui/internal/themes/ThemeRegistry
      28: astore_2
      29: aload_1
      30: checkcast     #640                // class java/lang/String
      33: astore_3
      34: aload_3
      35: ldc           #5                  // String selectCategory:
      37: invokevirtual #1399               // Method java/lang/String.startsWith:(Ljava/lang/String;)Z
      40: ifeq          86
      43: aload_3
      44: bipush        15
      46: invokevirtual #1398               // Method java/lang/String.substring:(I)Ljava/lang/String;
      49: astore        4
      51: aload_2
      52: aload         4
      54: invokevirtual #1676               // Method org/eclipse/ui/internal/themes/ThemeRegistry.findCategory:(Ljava/lang/String;)Lorg/eclipse/ui/internal/themes/ThemeElementCategory;
      57: astore        5
      59: aload         5
      61: ifnull        161
      64: aload_0
      65: aload         5
      67: invokevirtual #1577               // Method selectAndReveal:(Ljava/lang/Object;)V
      70: aload_0
      71: getfield      #1377               // Field tree:Lorg/eclipse/ui/dialogs/FilteredTree;
      74: invokevirtual #1534               // Method org/eclipse/ui/dialogs/FilteredTree.getViewer:()Lorg/eclipse/jface/viewers/TreeViewer;
      77: aload         5
      79: iconst_1
      80: invokevirtual #1445               // Method org/eclipse/jface/viewers/TreeViewer.expandToLevel:(Ljava/lang/Object;I)V
      83: goto          161
      86: aload_3
      87: ldc           #7                  // String selectFont:
      89: invokevirtual #1399               // Method java/lang/String.startsWith:(Ljava/lang/String;)Z
      92: ifeq          125
      95: aload_3
      96: bipush        11
      98: invokevirtual #1398               // Method java/lang/String.substring:(I)Ljava/lang/String;
     101: astore        4
     103: aload_2
     104: aload         4
     106: invokevirtual #1675               // Method org/eclipse/ui/internal/themes/ThemeRegistry.findFont:(Ljava/lang/String;)Lorg/eclipse/ui/internal/themes/FontDefinition;
     109: astore        5
     111: aload         5
     113: ifnull        161
     116: aload_0
     117: aload         5
     119: invokevirtual #1577               // Method selectAndReveal:(Ljava/lang/Object;)V
     122: goto          161
     125: aload_3
     126: ldc           #6                  // String selectColor:
     128: invokevirtual #1399               // Method java/lang/String.startsWith:(Ljava/lang/String;)Z
     131: ifeq          161
     134: aload_3
     135: bipush        12
     137: invokevirtual #1398               // Method java/lang/String.substring:(I)Ljava/lang/String;
     140: astore        4
     142: aload_2
     143: aload         4
     145: invokevirtual #1674               // Method org/eclipse/ui/internal/themes/ThemeRegistry.findColor:(Ljava/lang/String;)Lorg/eclipse/ui/internal/themes/ColorDefinition;
     148: astore        5
     150: aload         5
     152: ifnull        161
     155: aload_0
     156: aload         5
     158: invokevirtual #1577               // Method selectAndReveal:(Ljava/lang/Object;)V
     161: return

  private void selectAndReveal(java.lang.Object);
    Code:
       0: aload_0
       1: getfield      #1377               // Field tree:Lorg/eclipse/ui/dialogs/FilteredTree;
       4: invokevirtual #1534               // Method org/eclipse/ui/dialogs/FilteredTree.getViewer:()Lorg/eclipse/jface/viewers/TreeViewer;
       7: astore_2
       8: aload_2
       9: new           #672                // class org/eclipse/jface/viewers/StructuredSelection
      12: dup
      13: aload_1
      14: invokespecial #1435               // Method org/eclipse/jface/viewers/StructuredSelection."<init>":(Ljava/lang/Object;)V
      17: iconst_0
      18: invokevirtual #1452               // Method org/eclipse/jface/viewers/TreeViewer.setSelection:(Lorg/eclipse/jface/viewers/ISelection;Z)V
      21: aload_2
      22: aload_1
      23: invokevirtual #1441               // Method org/eclipse/jface/viewers/TreeViewer.reveal:(Ljava/lang/Object;)V
      26: aload_2
      27: invokevirtual #1457               // Method org/eclipse/jface/viewers/TreeViewer.getTree:()Lorg/eclipse/swt/widgets/Tree;
      30: invokevirtual #1530               // Method org/eclipse/swt/widgets/Tree.setFocus:()Z
      33: pop
      34: return

  private static boolean equals(java.lang.String, java.lang.String);
    Code:
       0: aload_0
       1: ifnonnull     10
       4: aload_1
       5: ifnonnull     10
       8: iconst_1
       9: ireturn
      10: aload_0
      11: ifnull        18
      14: aload_1
      15: ifnonnull     20
      18: iconst_0
      19: ireturn
      20: aload_0
      21: aload_1
      22: invokevirtual #1396               // Method java/lang/String.equals:(Ljava/lang/Object;)Z
      25: ifeq          30
      28: iconst_1
      29: ireturn
      30: iconst_0
      31: ireturn

  private org.eclipse.e4.ui.css.swt.theme.ITheme getActiveTheme();
    Code:
       0: aload_0
       1: getfield      #1358               // Field themeEngine:Lorg/eclipse/e4/ui/css/swt/theme/IThemeEngine;
       4: ifnull        17
       7: aload_0
       8: getfield      #1358               // Field themeEngine:Lorg/eclipse/e4/ui/css/swt/theme/IThemeEngine;
      11: invokeinterface #1699,  1         // InterfaceMethod org/eclipse/e4/ui/css/swt/theme/IThemeEngine.getActiveTheme:()Lorg/eclipse/e4/ui/css/swt/theme/ITheme;
      16: areturn
      17: aconst_null
      18: areturn

  private org.eclipse.swt.widgets.Button createButton(org.eclipse.swt.widgets.Composite, java.lang.String);
    Code:
       0: new           #690                // class org/eclipse/swt/widgets/Button
       3: dup
       4: aload_1
       5: ldc_w         #603                // int 16777224
       8: invokespecial #1494               // Method org/eclipse/swt/widgets/Button."<init>":(Lorg/eclipse/swt/widgets/Composite;I)V
      11: astore_3
      12: aload_3
      13: aload_2
      14: invokevirtual #1491               // Method org/eclipse/swt/widgets/Button.setText:(Ljava/lang/String;)V
      17: aload_0
      18: aload_3
      19: invokevirtual #1604               // Method myApplyDialogFont:(Lorg/eclipse/swt/widgets/Control;)V
      22: aload_0
      23: aload_3
      24: invokevirtual #1636               // Method setButtonLayoutData:(Lorg/eclipse/swt/widgets/Button;)Lorg/eclipse/swt/layout/GridData;
      27: pop
      28: aload_3
      29: iconst_0
      30: invokevirtual #1490               // Method org/eclipse/swt/widgets/Button.setEnabled:(Z)V
      33: aload_3
      34: areturn

  private org.eclipse.swt.widgets.Label createSeparator(org.eclipse.swt.widgets.Composite);
    Code:
       0: new           #697                // class org/eclipse/swt/widgets/Label
       3: dup
       4: aload_1
       5: iconst_0
       6: invokespecial #1526               // Method org/eclipse/swt/widgets/Label."<init>":(Lorg/eclipse/swt/widgets/Composite;I)V
       9: astore_2
      10: aload_2
      11: aload_1
      12: invokevirtual #1507               // Method org/eclipse/swt/widgets/Composite.getFont:()Lorg/eclipse/swt/graphics/Font;
      15: invokevirtual #1525               // Method org/eclipse/swt/widgets/Label.setFont:(Lorg/eclipse/swt/graphics/Font;)V
      18: aload_2
      19: iconst_0
      20: invokevirtual #1522               // Method org/eclipse/swt/widgets/Label.setVisible:(Z)V
      23: new           #688                // class org/eclipse/swt/layout/GridData
      26: dup
      27: invokespecial #1485               // Method org/eclipse/swt/layout/GridData."<init>":()V
      30: astore_3
      31: aload_3
      32: iconst_4
      33: putfield      #1336               // Field org/eclipse/swt/layout/GridData.horizontalAlignment:I
      36: aload_3
      37: iconst_1
      38: putfield      #1338               // Field org/eclipse/swt/layout/GridData.verticalAlignment:I
      41: aload_3
      42: iconst_4
      43: putfield      #1335               // Field org/eclipse/swt/layout/GridData.heightHint:I
      46: aload_2
      47: aload_3
      48: invokevirtual #1523               // Method org/eclipse/swt/widgets/Label.setLayoutData:(Ljava/lang/Object;)V
      51: aload_2
      52: areturn

  protected org.eclipse.swt.widgets.Control createContents(org.eclipse.swt.widgets.Composite);
    Code:
       0: invokestatic  #1531               // Method org/eclipse/ui/PlatformUI.getWorkbench:()Lorg/eclipse/ui/IWorkbench;
       3: invokeinterface #1706,  1         // InterfaceMethod org/eclipse/ui/IWorkbench.getHelpSystem:()Lorg/eclipse/ui/help/IWorkbenchHelpSystem;
       8: aload_1
       9: ldc_w         #623                // String org.eclipse.ui.font_preference_page_context
      12: invokeinterface #1708,  3         // InterfaceMethod org/eclipse/ui/help/IWorkbenchHelpSystem.setHelp:(Lorg/eclipse/swt/widgets/Control;Ljava/lang/String;)V
      17: aload_1
      18: aload_0
      19: invokedynamic #1753,  0           // InvokeDynamic #9:widgetDisposed:(Lorg/eclipse/ui/internal/themes/ColorsAndFontsPreferencePage;)Lorg/eclipse/swt/events/DisposeListener;
      24: invokevirtual #1506               // Method org/eclipse/swt/widgets/Composite.addDisposeListener:(Lorg/eclipse/swt/events/DisposeListener;)V
      27: new           #674                // class org/eclipse/swt/custom/SashForm
      30: dup
      31: aload_1
      32: sipush        512
      35: invokespecial #1460               // Method org/eclipse/swt/custom/SashForm."<init>":(Lorg/eclipse/swt/widgets/Composite;I)V
      38: astore_2
      39: new           #688                // class org/eclipse/swt/layout/GridData
      42: dup
      43: iconst_4
      44: iconst_4
      45: iconst_1
      46: iconst_1
      47: invokespecial #1487               // Method org/eclipse/swt/layout/GridData."<init>":(IIZZ)V
      50: astore_3
      51: aload_2
      52: aload_3
      53: invokevirtual #1459               // Method org/eclipse/swt/custom/SashForm.setLayoutData:(Ljava/lang/Object;)V
      56: new           #693                // class org/eclipse/swt/widgets/Composite
      59: dup
      60: aload_2
      61: iconst_0
      62: invokespecial #1509               // Method org/eclipse/swt/widgets/Composite."<init>":(Lorg/eclipse/swt/widgets/Composite;I)V
      65: astore        4
      67: new           #689                // class org/eclipse/swt/layout/GridLayout
      70: dup
      71: invokespecial #1488               // Method org/eclipse/swt/layout/GridLayout."<init>":()V
      74: astore        5
      76: aload         5
      78: iconst_2
      79: putfield      #1343               // Field org/eclipse/swt/layout/GridLayout.numColumns:I
      82: aload         5
      84: iconst_0
      85: putfield      #1342               // Field org/eclipse/swt/layout/GridLayout.marginWidth:I
      88: aload         5
      90: iconst_0
      91: putfield      #1340               // Field org/eclipse/swt/layout/GridLayout.marginHeight:I
      94: aload         4
      96: aload_1
      97: invokevirtual #1507               // Method org/eclipse/swt/widgets/Composite.getFont:()Lorg/eclipse/swt/graphics/Font;
     100: invokevirtual #1508               // Method org/eclipse/swt/widgets/Composite.setFont:(Lorg/eclipse/swt/graphics/Font;)V
     103: aload         4
     105: aload         5
     107: invokevirtual #1511               // Method org/eclipse/swt/widgets/Composite.setLayout:(Lorg/eclipse/swt/widgets/Layout;)V
     110: new           #688                // class org/eclipse/swt/layout/GridData
     113: dup
     114: iconst_1
     115: invokespecial #1486               // Method org/eclipse/swt/layout/GridData."<init>":(I)V
     118: astore        6
     120: aload         6
     122: iconst_2
     123: putfield      #1337               // Field org/eclipse/swt/layout/GridData.horizontalSpan:I
     126: new           #697                // class org/eclipse/swt/widgets/Label
     129: dup
     130: aload         4
     132: sipush        16384
     135: invokespecial #1526               // Method org/eclipse/swt/widgets/Label."<init>":(Lorg/eclipse/swt/widgets/Composite;I)V
     138: astore        7
     140: aload         7
     142: getstatic     #1354               // Field RESOURCE_BUNDLE:Ljava/util/ResourceBundle;
     145: ldc_w         #607                // String colorsAndFonts
     148: invokevirtual #1418               // Method java/util/ResourceBundle.getString:(Ljava/lang/String;)Ljava/lang/String;
     151: invokevirtual #1524               // Method org/eclipse/swt/widgets/Label.setText:(Ljava/lang/String;)V
     154: aload_0
     155: aload         7
     157: invokevirtual #1604               // Method myApplyDialogFont:(Lorg/eclipse/swt/widgets/Control;)V
     160: aload         7
     162: aload         6
     164: invokevirtual #1523               // Method org/eclipse/swt/widgets/Label.setLayoutData:(Ljava/lang/Object;)V
     167: aload_0
     168: aload         4
     170: invokevirtual #1602               // Method createTree:(Lorg/eclipse/swt/widgets/Composite;)V
     173: new           #693                // class org/eclipse/swt/widgets/Composite
     176: dup
     177: aload         4
     179: iconst_0
     180: invokespecial #1509               // Method org/eclipse/swt/widgets/Composite."<init>":(Lorg/eclipse/swt/widgets/Composite;I)V
     183: astore        8
     185: new           #688                // class org/eclipse/swt/layout/GridData
     188: dup
     189: sipush        1040
     192: invokespecial #1486               // Method org/eclipse/swt/layout/GridData."<init>":(I)V
     195: astore        6
     197: aload         8
     199: aload         6
     201: invokevirtual #1505               // Method org/eclipse/swt/widgets/Composite.setLayoutData:(Ljava/lang/Object;)V
     204: new           #689                // class org/eclipse/swt/layout/GridLayout
     207: dup
     208: invokespecial #1488               // Method org/eclipse/swt/layout/GridLayout."<init>":()V
     211: astore        5
     213: aload         5
     215: iconst_0
     216: putfield      #1340               // Field org/eclipse/swt/layout/GridLayout.marginHeight:I
     219: aload         5
     221: iconst_0
     222: putfield      #1342               // Field org/eclipse/swt/layout/GridLayout.marginWidth:I
     225: aload         8
     227: aload         5
     229: invokevirtual #1511               // Method org/eclipse/swt/widgets/Composite.setLayout:(Lorg/eclipse/swt/widgets/Layout;)V
     232: new           #697                // class org/eclipse/swt/widgets/Label
     235: dup
     236: aload         8
     238: iconst_0
     239: invokespecial #1526               // Method org/eclipse/swt/widgets/Label."<init>":(Lorg/eclipse/swt/widgets/Composite;I)V
     242: astore        9
     244: new           #688                // class org/eclipse/swt/layout/GridData
     247: dup
     248: sipush        128
     251: invokespecial #1486               // Method org/eclipse/swt/layout/GridData."<init>":(I)V
     254: astore        10
     256: aload         10
     258: aload_0
     259: bipush        12
     261: invokevirtual #1575               // Method convertVerticalDLUsToPixels:(I)I
     264: putfield      #1335               // Field org/eclipse/swt/layout/GridData.heightHint:I
     267: aload         9
     269: aload         10
     271: invokevirtual #1523               // Method org/eclipse/swt/widgets/Label.setLayoutData:(Ljava/lang/Object;)V
     274: aload_0
     275: aload_0
     276: aload         8
     278: getstatic     #1354               // Field RESOURCE_BUNDLE:Ljava/util/ResourceBundle;
     281: ldc_w         #621                // String openChange
     284: invokevirtual #1418               // Method java/util/ResourceBundle.getString:(Ljava/lang/String;)Ljava/lang/String;
     287: invokevirtual #1646               // Method createButton:(Lorg/eclipse/swt/widgets/Composite;Ljava/lang/String;)Lorg/eclipse/swt/widgets/Button;
     290: putfield      #1366               // Field fontChangeButton:Lorg/eclipse/swt/widgets/Button;
     293: aload_0
     294: aload_0
     295: aload         8
     297: getstatic     #1344               // Field org/eclipse/ui/internal/WorkbenchMessages.FontsPreference_useSystemFont:Ljava/lang/String;
     300: invokevirtual #1646               // Method createButton:(Lorg/eclipse/swt/widgets/Composite;Ljava/lang/String;)Lorg/eclipse/swt/widgets/Button;
     303: putfield      #1368               // Field fontSystemButton:Lorg/eclipse/swt/widgets/Button;
     306: aload_0
     307: aload_0
     308: aload         8
     310: getstatic     #1354               // Field RESOURCE_BUNDLE:Ljava/util/ResourceBundle;
     313: ldc_w         #627                // String reset
     316: invokevirtual #1418               // Method java/util/ResourceBundle.getString:(Ljava/lang/String;)Ljava/lang/String;
     319: invokevirtual #1646               // Method createButton:(Lorg/eclipse/swt/widgets/Composite;Ljava/lang/String;)Lorg/eclipse/swt/widgets/Button;
     322: putfield      #1367               // Field fontResetButton:Lorg/eclipse/swt/widgets/Button;
     325: aload_0
     326: aload         8
     328: invokevirtual #1639               // Method createSeparator:(Lorg/eclipse/swt/widgets/Composite;)Lorg/eclipse/swt/widgets/Label;
     331: pop
     332: aload_0
     333: aload_0
     334: aload         8
     336: getstatic     #1354               // Field RESOURCE_BUNDLE:Ljava/util/ResourceBundle;
     339: ldc_w         #610                // String editDefault
     342: invokevirtual #1418               // Method java/util/ResourceBundle.getString:(Ljava/lang/String;)Ljava/lang/String;
     345: invokevirtual #1646               // Method createButton:(Lorg/eclipse/swt/widgets/Composite;Ljava/lang/String;)Lorg/eclipse/swt/widgets/Button;
     348: putfield      #1364               // Field editDefaultButton:Lorg/eclipse/swt/widgets/Button;
     351: aload_0
     352: aload_0
     353: aload         8
     355: getstatic     #1354               // Field RESOURCE_BUNDLE:Ljava/util/ResourceBundle;
     358: ldc_w         #618                // String goToDefault
     361: invokevirtual #1418               // Method java/util/ResourceBundle.getString:(Ljava/lang/String;)Ljava/lang/String;
     364: invokevirtual #1646               // Method createButton:(Lorg/eclipse/swt/widgets/Composite;Ljava/lang/String;)Lorg/eclipse/swt/widgets/Button;
     367: putfield      #1369               // Field goToDefaultButton:Lorg/eclipse/swt/widgets/Button;
     370: aload_0
     371: aload         8
     373: invokevirtual #1639               // Method createSeparator:(Lorg/eclipse/swt/widgets/Composite;)Lorg/eclipse/swt/widgets/Label;
     376: pop
     377: aload_0
     378: aload_0
     379: aload         8
     381: getstatic     #1354               // Field RESOURCE_BUNDLE:Ljava/util/ResourceBundle;
     384: ldc_w         #614                // String expandAll
     387: invokevirtual #1418               // Method java/util/ResourceBundle.getString:(Ljava/lang/String;)Ljava/lang/String;
     390: invokevirtual #1646               // Method createButton:(Lorg/eclipse/swt/widgets/Composite;Ljava/lang/String;)Lorg/eclipse/swt/widgets/Button;
     393: putfield      #1365               // Field expandAllButton:Lorg/eclipse/swt/widgets/Button;
     396: aload_0
     397: getfield      #1365               // Field expandAllButton:Lorg/eclipse/swt/widgets/Button;
     400: iconst_1
     401: invokevirtual #1490               // Method org/eclipse/swt/widgets/Button.setEnabled:(Z)V
     404: aload_0
     405: aload         4
     407: invokevirtual #1601               // Method createDescriptionControl:(Lorg/eclipse/swt/widgets/Composite;)V
     410: new           #693                // class org/eclipse/swt/widgets/Composite
     413: dup
     414: aload_2
     415: iconst_0
     416: invokespecial #1509               // Method org/eclipse/swt/widgets/Composite."<init>":(Lorg/eclipse/swt/widgets/Composite;I)V
     419: astore        11
     421: new           #689                // class org/eclipse/swt/layout/GridLayout
     424: dup
     425: invokespecial #1488               // Method org/eclipse/swt/layout/GridLayout."<init>":()V
     428: astore        12
     430: aload         12
     432: bipush        7
     434: putfield      #1341               // Field org/eclipse/swt/layout/GridLayout.marginTop:I
     437: aload         12
     439: iconst_0
     440: putfield      #1342               // Field org/eclipse/swt/layout/GridLayout.marginWidth:I
     443: aload         12
     445: iconst_0
     446: putfield      #1340               // Field org/eclipse/swt/layout/GridLayout.marginHeight:I
     449: aload         11
     451: aload_1
     452: invokevirtual #1507               // Method org/eclipse/swt/widgets/Composite.getFont:()Lorg/eclipse/swt/graphics/Font;
     455: invokevirtual #1508               // Method org/eclipse/swt/widgets/Composite.setFont:(Lorg/eclipse/swt/graphics/Font;)V
     458: aload         11
     460: aload         12
     462: invokevirtual #1511               // Method org/eclipse/swt/widgets/Composite.setLayout:(Lorg/eclipse/swt/widgets/Layout;)V
     465: new           #693                // class org/eclipse/swt/widgets/Composite
     468: dup
     469: aload         11
     471: iconst_0
     472: invokespecial #1509               // Method org/eclipse/swt/widgets/Composite."<init>":(Lorg/eclipse/swt/widgets/Composite;I)V
     475: astore        13
     477: new           #688                // class org/eclipse/swt/layout/GridData
     480: dup
     481: sipush        1808
     484: invokespecial #1486               // Method org/eclipse/swt/layout/GridData."<init>":(I)V
     487: astore        14
     489: aload         13
     491: aload         14
     493: invokevirtual #1505               // Method org/eclipse/swt/widgets/Composite.setLayoutData:(Ljava/lang/Object;)V
     496: new           #689                // class org/eclipse/swt/layout/GridLayout
     499: dup
     500: iconst_1
     501: iconst_1
     502: invokespecial #1489               // Method org/eclipse/swt/layout/GridLayout."<init>":(IZ)V
     505: astore        15
     507: aload         15
     509: iconst_0
     510: putfield      #1340               // Field org/eclipse/swt/layout/GridLayout.marginHeight:I
     513: aload         15
     515: iconst_0
     516: putfield      #1342               // Field org/eclipse/swt/layout/GridLayout.marginWidth:I
     519: aload         13
     521: aload         15
     523: invokevirtual #1511               // Method org/eclipse/swt/widgets/Composite.setLayout:(Lorg/eclipse/swt/widgets/Layout;)V
     526: new           #697                // class org/eclipse/swt/widgets/Label
     529: dup
     530: aload         13
     532: sipush        16384
     535: invokespecial #1526               // Method org/eclipse/swt/widgets/Label."<init>":(Lorg/eclipse/swt/widgets/Composite;I)V
     538: astore        16
     540: aload         16
     542: getstatic     #1354               // Field RESOURCE_BUNDLE:Ljava/util/ResourceBundle;
     545: ldc_w         #626                // String preview
     548: invokevirtual #1418               // Method java/util/ResourceBundle.getString:(Ljava/lang/String;)Ljava/lang/String;
     551: invokevirtual #1524               // Method org/eclipse/swt/widgets/Label.setText:(Ljava/lang/String;)V
     554: aload_0
     555: aload         16
     557: invokevirtual #1604               // Method myApplyDialogFont:(Lorg/eclipse/swt/widgets/Control;)V
     560: aload_0
     561: new           #693                // class org/eclipse/swt/widgets/Composite
     564: dup
     565: aload         13
     567: iconst_0
     568: invokespecial #1509               // Method org/eclipse/swt/widgets/Composite."<init>":(Lorg/eclipse/swt/widgets/Composite;I)V
     571: putfield      #1375               // Field previewComposite:Lorg/eclipse/swt/widgets/Composite;
     574: aload_0
     575: getfield      #1375               // Field previewComposite:Lorg/eclipse/swt/widgets/Composite;
     578: new           #688                // class org/eclipse/swt/layout/GridData
     581: dup
     582: sipush        1808
     585: invokespecial #1486               // Method org/eclipse/swt/layout/GridData."<init>":(I)V
     588: invokevirtual #1505               // Method org/eclipse/swt/widgets/Composite.setLayoutData:(Ljava/lang/Object;)V
     591: aload_0
     592: new           #675                // class org/eclipse/swt/custom/StackLayout
     595: dup
     596: invokespecial #1461               // Method org/eclipse/swt/custom/StackLayout."<init>":()V
     599: putfield      #1360               // Field stackLayout:Lorg/eclipse/swt/custom/StackLayout;
     602: aload_0
     603: getfield      #1360               // Field stackLayout:Lorg/eclipse/swt/custom/StackLayout;
     606: iconst_0
     607: putfield      #1322               // Field org/eclipse/swt/custom/StackLayout.marginHeight:I
     610: aload_0
     611: getfield      #1360               // Field stackLayout:Lorg/eclipse/swt/custom/StackLayout;
     614: iconst_0
     615: putfield      #1323               // Field org/eclipse/swt/custom/StackLayout.marginWidth:I
     618: aload_0
     619: getfield      #1375               // Field previewComposite:Lorg/eclipse/swt/widgets/Composite;
     622: aload_0
     623: getfield      #1360               // Field stackLayout:Lorg/eclipse/swt/custom/StackLayout;
     626: invokevirtual #1511               // Method org/eclipse/swt/widgets/Composite.setLayout:(Lorg/eclipse/swt/widgets/Layout;)V
     629: aload_0
     630: aload_0
     631: invokevirtual #1599               // Method createFontPreviewControl:()Lorg/eclipse/swt/widgets/Composite;
     634: putfield      #1373               // Field defaultFontPreview:Lorg/eclipse/swt/widgets/Composite;
     637: aload_0
     638: aload_0
     639: invokevirtual #1598               // Method createColorPreviewControl:()Lorg/eclipse/swt/widgets/Composite;
     642: putfield      #1372               // Field defaultColorPreview:Lorg/eclipse/swt/widgets/Composite;
     645: aload_0
     646: aload_0
     647: invokevirtual #1600               // Method createNoPreviewControl:()Lorg/eclipse/swt/widgets/Composite;
     650: putfield      #1374               // Field defaultNoPreview:Lorg/eclipse/swt/widgets/Composite;
     653: aload_0
     654: invokevirtual #1559               // Method hookListeners:()V
     657: aload_0
     658: aload_0
     659: getfield      #1377               // Field tree:Lorg/eclipse/ui/dialogs/FilteredTree;
     662: invokevirtual #1534               // Method org/eclipse/ui/dialogs/FilteredTree.getViewer:()Lorg/eclipse/jface/viewers/TreeViewer;
     665: invokevirtual #1451               // Method org/eclipse/jface/viewers/TreeViewer.getSelection:()Lorg/eclipse/jface/viewers/ISelection;
     668: invokevirtual #1582               // Method updateTreeSelection:(Lorg/eclipse/jface/viewers/ISelection;)V
     671: aload_2
     672: iconst_2
     673: newarray       int
     675: dup
     676: iconst_0
     677: bipush        75
     679: iastore
     680: dup
     681: iconst_1
     682: bipush        25
     684: iastore
     685: invokevirtual #1458               // Method org/eclipse/swt/custom/SashForm.setWeights:([I)V
     688: aload_2
     689: areturn

  private void createTree(org.eclipse.swt.widgets.Composite);
    Code:
       0: aload_0
       1: new           #717                // class org/eclipse/ui/internal/themes/ColorsAndFontsPreferencePage$PresentationLabelProvider
       4: dup
       5: aload_0
       6: invokespecial #1656               // Method org/eclipse/ui/internal/themes/ColorsAndFontsPreferencePage$PresentationLabelProvider."<init>":(Lorg/eclipse/ui/internal/themes/ColorsAndFontsPreferencePage;)V
       9: putfield      #1382               // Field labelProvider:Lorg/eclipse/ui/internal/themes/ColorsAndFontsPreferencePage$PresentationLabelProvider;
      12: new           #714                // class org/eclipse/ui/internal/themes/ColorsAndFontsPreferencePage$2
      15: dup
      16: aload_0
      17: invokespecial #1648               // Method org/eclipse/ui/internal/themes/ColorsAndFontsPreferencePage$2."<init>":(Lorg/eclipse/ui/internal/themes/ColorsAndFontsPreferencePage;)V
      20: astore_2
      21: aload_2
      22: iconst_1
      23: invokevirtual #1538               // Method org/eclipse/ui/dialogs/PatternFilter.setIncludeLeadingWildcard:(Z)V
      26: aload_0
      27: new           #703                // class org/eclipse/ui/dialogs/FilteredTree
      30: dup
      31: aload_1
      32: sipush        2820
      35: aload_2
      36: iconst_1
      37: invokespecial #1537               // Method org/eclipse/ui/dialogs/FilteredTree."<init>":(Lorg/eclipse/swt/widgets/Composite;ILorg/eclipse/ui/dialogs/PatternFilter;Z)V
      40: putfield      #1377               // Field tree:Lorg/eclipse/ui/dialogs/FilteredTree;
      43: aload_0
      44: getfield      #1377               // Field tree:Lorg/eclipse/ui/dialogs/FilteredTree;
      47: iconst_1
      48: invokevirtual #1532               // Method org/eclipse/ui/dialogs/FilteredTree.setQuickSelectionMode:(Z)V
      51: new           #688                // class org/eclipse/swt/layout/GridData
      54: dup
      55: sipush        1808
      58: invokespecial #1486               // Method org/eclipse/swt/layout/GridData."<init>":(I)V
      61: astore_3
      62: aload_3
      63: sipush        285
      66: aload_0
      67: bipush        30
      69: invokevirtual #1576               // Method convertWidthInCharsToPixels:(I)I
      72: invokestatic  #1392               // Method java/lang/Math.max:(II)I
      75: putfield      #1339               // Field org/eclipse/swt/layout/GridData.widthHint:I
      78: aload_3
      79: sipush        175
      82: aload_0
      83: bipush        10
      85: invokevirtual #1574               // Method convertHeightInCharsToPixels:(I)I
      88: invokestatic  #1392               // Method java/lang/Math.max:(II)I
      91: putfield      #1335               // Field org/eclipse/swt/layout/GridData.heightHint:I
      94: aload_0
      95: getfield      #1377               // Field tree:Lorg/eclipse/ui/dialogs/FilteredTree;
      98: aload_3
      99: invokevirtual #1533               // Method org/eclipse/ui/dialogs/FilteredTree.setLayoutData:(Ljava/lang/Object;)V
     102: aload_0
     103: aload_0
     104: getfield      #1377               // Field tree:Lorg/eclipse/ui/dialogs/FilteredTree;
     107: invokevirtual #1534               // Method org/eclipse/ui/dialogs/FilteredTree.getViewer:()Lorg/eclipse/jface/viewers/TreeViewer;
     110: invokevirtual #1456               // Method org/eclipse/jface/viewers/TreeViewer.getControl:()Lorg/eclipse/swt/widgets/Control;
     113: invokevirtual #1604               // Method myApplyDialogFont:(Lorg/eclipse/swt/widgets/Control;)V
     116: aload_0
     117: getfield      #1377               // Field tree:Lorg/eclipse/ui/dialogs/FilteredTree;
     120: invokevirtual #1536               // Method org/eclipse/ui/dialogs/FilteredTree.getFilterControl:()Lorg/eclipse/swt/widgets/Text;
     123: astore        4
     125: aload         4
     127: ifnull        136
     130: aload_0
     131: aload         4
     133: invokevirtual #1604               // Method myApplyDialogFont:(Lorg/eclipse/swt/widgets/Control;)V
     136: aload_0
     137: getfield      #1377               // Field tree:Lorg/eclipse/ui/dialogs/FilteredTree;
     140: invokevirtual #1534               // Method org/eclipse/ui/dialogs/FilteredTree.getViewer:()Lorg/eclipse/jface/viewers/TreeViewer;
     143: aload_0
     144: getfield      #1382               // Field labelProvider:Lorg/eclipse/ui/internal/themes/ColorsAndFontsPreferencePage$PresentationLabelProvider;
     147: invokevirtual #1448               // Method org/eclipse/jface/viewers/TreeViewer.setLabelProvider:(Lorg/eclipse/jface/viewers/IBaseLabelProvider;)V
     150: aload_0
     151: getfield      #1377               // Field tree:Lorg/eclipse/ui/dialogs/FilteredTree;
     154: invokevirtual #1534               // Method org/eclipse/ui/dialogs/FilteredTree.getViewer:()Lorg/eclipse/jface/viewers/TreeViewer;
     157: new           #718                // class org/eclipse/ui/internal/themes/ColorsAndFontsPreferencePage$ThemeContentProvider
     160: dup
     161: aload_0
     162: invokespecial #1657               // Method org/eclipse/ui/internal/themes/ColorsAndFontsPreferencePage$ThemeContentProvider."<init>":(Lorg/eclipse/ui/internal/themes/ColorsAndFontsPreferencePage;)V
     165: invokevirtual #1449               // Method org/eclipse/jface/viewers/TreeViewer.setContentProvider:(Lorg/eclipse/jface/viewers/IContentProvider;)V
     168: aload_0
     169: getfield      #1377               // Field tree:Lorg/eclipse/ui/dialogs/FilteredTree;
     172: invokevirtual #1534               // Method org/eclipse/ui/dialogs/FilteredTree.getViewer:()Lorg/eclipse/jface/viewers/TreeViewer;
     175: new           #715                // class org/eclipse/ui/internal/themes/ColorsAndFontsPreferencePage$3
     178: dup
     179: aload_0
     180: invokespecial #1649               // Method org/eclipse/ui/internal/themes/ColorsAndFontsPreferencePage$3."<init>":(Lorg/eclipse/ui/internal/themes/ColorsAndFontsPreferencePage;)V
     183: invokevirtual #1455               // Method org/eclipse/jface/viewers/TreeViewer.setComparator:(Lorg/eclipse/jface/viewers/ViewerComparator;)V
     186: aload_0
     187: getfield      #1377               // Field tree:Lorg/eclipse/ui/dialogs/FilteredTree;
     190: invokevirtual #1534               // Method org/eclipse/ui/dialogs/FilteredTree.getViewer:()Lorg/eclipse/jface/viewers/TreeViewer;
     193: invokestatic  #1541               // Method org/eclipse/ui/internal/WorkbenchPlugin.getDefault:()Lorg/eclipse/ui/internal/WorkbenchPlugin;
     196: invokevirtual #1542               // Method org/eclipse/ui/internal/WorkbenchPlugin.getThemeRegistry:()Lorg/eclipse/ui/internal/themes/IThemeRegistry;
     199: invokevirtual #1442               // Method org/eclipse/jface/viewers/TreeViewer.setInput:(Ljava/lang/Object;)V
     202: aload_0
     203: getfield      #1377               // Field tree:Lorg/eclipse/ui/dialogs/FilteredTree;
     206: invokevirtual #1534               // Method org/eclipse/ui/dialogs/FilteredTree.getViewer:()Lorg/eclipse/jface/viewers/TreeViewer;
     209: aload_0
     210: invokedynamic #1751,  0           // InvokeDynamic #7:doubleClick:(Lorg/eclipse/ui/internal/themes/ColorsAndFontsPreferencePage;)Lorg/eclipse/jface/viewers/IDoubleClickListener;
     215: invokevirtual #1450               // Method org/eclipse/jface/viewers/TreeViewer.addDoubleClickListener:(Lorg/eclipse/jface/viewers/IDoubleClickListener;)V
     218: aload_0
     219: invokevirtual #1565               // Method restoreTreeExpansion:()V
     222: aload_0
     223: invokevirtual #1566               // Method restoreTreeSelection:()V
     226: return

  public void dispose();
    Code:
       0: aload_0
       1: getfield      #1356               // Field eventBroker:Lorg/eclipse/e4/core/services/events/IEventBroker;
       4: aload_0
       5: getfield      #1385               // Field themeRegistryRestyledHandler:Lorg/osgi/service/event/EventHandler;
       8: invokeinterface #1696,  2         // InterfaceMethod org/eclipse/e4/core/services/events/IEventBroker.unsubscribe:(Lorg/osgi/service/event/EventHandler;)Z
      13: pop
      14: aload_0
      15: getfield      #1378               // Field workbench:Lorg/eclipse/ui/internal/Workbench;
      18: invokevirtual #1539               // Method org/eclipse/ui/internal/Workbench.getThemeManager:()Lorg/eclipse/ui/themes/IThemeManager;
      21: aload_0
      22: getfield      #1359               // Field themeChangeListener:Lorg/eclipse/jface/util/IPropertyChangeListener;
      25: invokeinterface #1721,  2         // InterfaceMethod org/eclipse/ui/themes/IThemeManager.removePropertyChangeListener:(Lorg/eclipse/jface/util/IPropertyChangeListener;)V
      30: aload_0
      31: invokevirtual #1558               // Method clearPreviews:()V
      34: aload_0
      35: getfield      #1379               // Field colorRegistry:Lorg/eclipse/ui/internal/themes/CascadingColorRegistry;
      38: invokevirtual #1545               // Method org/eclipse/ui/internal/themes/CascadingColorRegistry.dispose:()V
      41: aload_0
      42: getfield      #1380               // Field fontRegistry:Lorg/eclipse/ui/internal/themes/CascadingFontRegistry;
      45: invokevirtual #1550               // Method org/eclipse/ui/internal/themes/CascadingFontRegistry.dispose:()V
      48: aload_0
      49: invokespecial #1424               // Method org/eclipse/jface/preference/PreferencePage.dispose:()V
      52: return

  private void clearPreviews();
    Code:
       0: aload_0
       1: getfield      #1381               // Field cascadingTheme:Lorg/eclipse/ui/internal/themes/ColorsAndFontsPreferencePage$CascadingThemeExt;
       4: ifnull        14
       7: aload_0
       8: getfield      #1381               // Field cascadingTheme:Lorg/eclipse/ui/internal/themes/ColorsAndFontsPreferencePage$CascadingThemeExt;
      11: invokevirtual #1650               // Method org/eclipse/ui/internal/themes/ColorsAndFontsPreferencePage$CascadingThemeExt.dispose:()V
      14: aload_0
      15: getfield      #1355               // Field previewSet:Ljava/util/Set;
      18: invokeinterface #1695,  1         // InterfaceMethod java/util/Set.iterator:()Ljava/util/Iterator;
      23: astore_2
      24: goto          68
      27: aload_2
      28: invokeinterface #1680,  1         // InterfaceMethod java/util/Iterator.next:()Ljava/lang/Object;
      33: checkcast     #733                // class org/eclipse/ui/themes/IThemePreview
      36: astore_1
      37: aload_1
      38: invokeinterface #1723,  1         // InterfaceMethod org/eclipse/ui/themes/IThemePreview.dispose:()V
      43: goto          68
      46: astore_3
      47: getstatic     #1354               // Field RESOURCE_BUNDLE:Ljava/util/ResourceBundle;
      50: ldc_w         #613                // String errorDisposePreviewLog
      53: invokevirtual #1418               // Method java/util/ResourceBundle.getString:(Ljava/lang/String;)Ljava/lang/String;
      56: iconst_4
      57: aload_3
      58: invokevirtual #1393               // Method java/lang/RuntimeException.getMessage:()Ljava/lang/String;
      61: aload_3
      62: invokestatic  #1544               // Method org/eclipse/ui/internal/misc/StatusUtil.newStatus:(ILjava/lang/String;Ljava/lang/Throwable;)Lorg/eclipse/core/runtime/IStatus;
      65: invokestatic  #1543               // Method org/eclipse/ui/internal/WorkbenchPlugin.log:(Ljava/lang/String;Lorg/eclipse/core/runtime/IStatus;)V
      68: aload_2
      69: invokeinterface #1679,  1         // InterfaceMethod java/util/Iterator.hasNext:()Z
      74: ifne          27
      77: aload_0
      78: getfield      #1355               // Field previewSet:Ljava/util/Set;
      81: invokeinterface #1693,  1         // InterfaceMethod java/util/Set.clear:()V
      86: return
    Exception table:
       from    to  target type
          37    43    46   Class java/lang/RuntimeException

  private org.eclipse.ui.internal.themes.ColorDefinition getColorAncestor(org.eclipse.ui.internal.themes.ColorDefinition);
    Code:
       0: aload_1
       1: invokevirtual #1555               // Method org/eclipse/ui/internal/themes/ColorDefinition.getDefaultsTo:()Ljava/lang/String;
       4: astore_2
       5: aload_2
       6: ifnonnull     11
       9: aconst_null
      10: areturn
      11: aload_0
      12: getfield      #1383               // Field themeRegistry:Lorg/eclipse/ui/internal/themes/IThemeRegistry;
      15: aload_2
      16: invokeinterface #1715,  2         // InterfaceMethod org/eclipse/ui/internal/themes/IThemeRegistry.findColor:(Ljava/lang/String;)Lorg/eclipse/ui/internal/themes/ColorDefinition;
      21: areturn

  private org.eclipse.swt.graphics.RGB getColorAncestorValue(org.eclipse.ui.internal.themes.ColorDefinition);
    Code:
       0: aload_0
       1: aload_1
       2: invokevirtual #1640               // Method getColorAncestor:(Lorg/eclipse/ui/internal/themes/ColorDefinition;)Lorg/eclipse/ui/internal/themes/ColorDefinition;
       5: astore_2
       6: aload_2
       7: ifnonnull     12
      10: aconst_null
      11: areturn
      12: aload_0
      13: aload_2
      14: invokevirtual #1632               // Method getColorValue:(Lorg/eclipse/ui/internal/themes/ColorDefinition;)Lorg/eclipse/swt/graphics/RGB;
      17: areturn

  private org.eclipse.swt.graphics.RGB getColorValue(org.eclipse.ui.internal.themes.ColorDefinition);
    Code:
       0: aload_1
       1: invokevirtual #1556               // Method org/eclipse/ui/internal/themes/ColorDefinition.getId:()Ljava/lang/String;
       4: astore_2
       5: aload_0
       6: getfield      #1349               // Field colorPreferencesToSet:Ljava/util/Map;
       9: aload_1
      10: invokeinterface #1689,  2         // InterfaceMethod java/util/Map.get:(Ljava/lang/Object;)Ljava/lang/Object;
      15: checkcast     #685                // class org/eclipse/swt/graphics/RGB
      18: astore_3
      19: aload_3
      20: ifnonnull     55
      23: aload_0
      24: getfield      #1350               // Field colorValuesToSet:Ljava/util/Map;
      27: aload_2
      28: invokeinterface #1689,  2         // InterfaceMethod java/util/Map.get:(Ljava/lang/Object;)Ljava/lang/Object;
      33: checkcast     #685                // class org/eclipse/swt/graphics/RGB
      36: astore_3
      37: aload_3
      38: ifnonnull     55
      41: aload_0
      42: getfield      #1384               // Field currentTheme:Lorg/eclipse/ui/themes/ITheme;
      45: invokeinterface #1718,  1         // InterfaceMethod org/eclipse/ui/themes/ITheme.getColorRegistry:()Lorg/eclipse/jface/resource/ColorRegistry;
      50: aload_2
      51: invokevirtual #1426               // Method org/eclipse/jface/resource/ColorRegistry.getRGB:(Ljava/lang/String;)Lorg/eclipse/swt/graphics/RGB;
      54: astore_3
      55: aload_3
      56: areturn

  private org.eclipse.ui.internal.themes.ColorDefinition[] getDescendantColors(org.eclipse.ui.internal.themes.ColorDefinition);
    Code:
       0: new           #646                // class java/util/ArrayList
       3: dup
       4: iconst_5
       5: invokespecial #1412               // Method java/util/ArrayList."<init>":(I)V
       8: astore_2
       9: aload_1
      10: invokevirtual #1556               // Method org/eclipse/ui/internal/themes/ColorDefinition.getId:()Ljava/lang/String;
      13: astore_3
      14: aload_0
      15: getfield      #1383               // Field themeRegistry:Lorg/eclipse/ui/internal/themes/IThemeRegistry;
      18: invokeinterface #1712,  1         // InterfaceMethod org/eclipse/ui/internal/themes/IThemeRegistry.getColors:()[Lorg/eclipse/ui/internal/themes/ColorDefinition;
      23: astore        4
      25: aload         4
      27: arraylength
      28: anewarray     #712                // class org/eclipse/ui/internal/themes/ColorDefinition
      31: astore        5
      33: aload         4
      35: iconst_0
      36: aload         5
      38: iconst_0
      39: aload         5
      41: arraylength
      42: invokestatic  #1408               // Method java/lang/System.arraycopy:(Ljava/lang/Object;ILjava/lang/Object;II)V
      45: aload         5
      47: new           #724                // class org/eclipse/ui/internal/themes/IThemeRegistry$HierarchyComparator
      50: dup
      51: aload         4
      53: invokespecial #1663               // Method org/eclipse/ui/internal/themes/IThemeRegistry$HierarchyComparator."<init>":([Lorg/eclipse/ui/internal/themes/IHierarchalThemeElementDefinition;)V
      56: invokestatic  #1414               // Method java/util/Arrays.sort:([Ljava/lang/Object;Ljava/util/Comparator;)V
      59: aload         5
      61: dup
      62: astore        9
      64: arraylength
      65: istore        8
      67: iconst_0
      68: istore        7
      70: goto          104
      73: aload         9
      75: iload         7
      77: aaload
      78: astore        6
      80: aload_3
      81: aload         6
      83: invokevirtual #1555               // Method org/eclipse/ui/internal/themes/ColorDefinition.getDefaultsTo:()Ljava/lang/String;
      86: invokevirtual #1396               // Method java/lang/String.equals:(Ljava/lang/Object;)Z
      89: ifeq          101
      92: aload_2
      93: aload         6
      95: invokeinterface #1683,  2         // InterfaceMethod java/util/List.add:(Ljava/lang/Object;)Z
     100: pop
     101: iinc          7, 1
     104: iload         7
     106: iload         8
     108: if_icmplt     73
     111: aload_2
     112: aload_2
     113: invokeinterface #1681,  1         // InterfaceMethod java/util/List.size:()I
     118: anewarray     #712                // class org/eclipse/ui/internal/themes/ColorDefinition
     121: invokeinterface #1685,  2         // InterfaceMethod java/util/List.toArray:([Ljava/lang/Object;)[Ljava/lang/Object;
     126: checkcast     #631                // class "[Lorg/eclipse/ui/internal/themes/ColorDefinition;"
     129: areturn

  private org.eclipse.ui.internal.themes.FontDefinition[] getDescendantFonts(org.eclipse.ui.internal.themes.FontDefinition);
    Code:
       0: new           #646                // class java/util/ArrayList
       3: dup
       4: iconst_5
       5: invokespecial #1412               // Method java/util/ArrayList."<init>":(I)V
       8: astore_2
       9: aload_1
      10: invokevirtual #1661               // Method org/eclipse/ui/internal/themes/FontDefinition.getId:()Ljava/lang/String;
      13: astore_3
      14: aload_0
      15: getfield      #1383               // Field themeRegistry:Lorg/eclipse/ui/internal/themes/IThemeRegistry;
      18: invokeinterface #1713,  1         // InterfaceMethod org/eclipse/ui/internal/themes/IThemeRegistry.getFonts:()[Lorg/eclipse/ui/internal/themes/FontDefinition;
      23: astore        4
      25: aload         4
      27: arraylength
      28: anewarray     #719                // class org/eclipse/ui/internal/themes/FontDefinition
      31: astore        5
      33: aload         4
      35: iconst_0
      36: aload         5
      38: iconst_0
      39: aload         5
      41: arraylength
      42: invokestatic  #1408               // Method java/lang/System.arraycopy:(Ljava/lang/Object;ILjava/lang/Object;II)V
      45: aload         5
      47: new           #724                // class org/eclipse/ui/internal/themes/IThemeRegistry$HierarchyComparator
      50: dup
      51: aload         4
      53: invokespecial #1663               // Method org/eclipse/ui/internal/themes/IThemeRegistry$HierarchyComparator."<init>":([Lorg/eclipse/ui/internal/themes/IHierarchalThemeElementDefinition;)V
      56: invokestatic  #1414               // Method java/util/Arrays.sort:([Ljava/lang/Object;Ljava/util/Comparator;)V
      59: aload         5
      61: dup
      62: astore        9
      64: arraylength
      65: istore        8
      67: iconst_0
      68: istore        7
      70: goto          104
      73: aload         9
      75: iload         7
      77: aaload
      78: astore        6
      80: aload_3
      81: aload         6
      83: invokevirtual #1660               // Method org/eclipse/ui/internal/themes/FontDefinition.getDefaultsTo:()Ljava/lang/String;
      86: invokevirtual #1396               // Method java/lang/String.equals:(Ljava/lang/Object;)Z
      89: ifeq          101
      92: aload_2
      93: aload         6
      95: invokeinterface #1683,  2         // InterfaceMethod java/util/List.add:(Ljava/lang/Object;)Z
     100: pop
     101: iinc          7, 1
     104: iload         7
     106: iload         8
     108: if_icmplt     73
     111: aload_2
     112: aload_2
     113: invokeinterface #1681,  1         // InterfaceMethod java/util/List.size:()I
     118: anewarray     #719                // class org/eclipse/ui/internal/themes/FontDefinition
     121: invokeinterface #1685,  2         // InterfaceMethod java/util/List.toArray:([Ljava/lang/Object;)[Ljava/lang/Object;
     126: checkcast     #632                // class "[Lorg/eclipse/ui/internal/themes/FontDefinition;"
     129: areturn

  private org.eclipse.ui.internal.themes.FontDefinition getFontAncestor(org.eclipse.ui.internal.themes.FontDefinition);
    Code:
       0: aload_1
       1: invokevirtual #1660               // Method org/eclipse/ui/internal/themes/FontDefinition.getDefaultsTo:()Ljava/lang/String;
       4: astore_2
       5: aload_2
       6: ifnonnull     11
       9: aconst_null
      10: areturn
      11: aload_0
      12: getfield      #1383               // Field themeRegistry:Lorg/eclipse/ui/internal/themes/IThemeRegistry;
      15: aload_2
      16: invokeinterface #1716,  2         // InterfaceMethod org/eclipse/ui/internal/themes/IThemeRegistry.findFont:(Ljava/lang/String;)Lorg/eclipse/ui/internal/themes/FontDefinition;
      21: areturn

  private org.eclipse.swt.graphics.FontData[] getFontAncestorValue(org.eclipse.ui.internal.themes.FontDefinition);
    Code:
       0: aload_0
       1: aload_1
       2: invokevirtual #1642               // Method getFontAncestor:(Lorg/eclipse/ui/internal/themes/FontDefinition;)Lorg/eclipse/ui/internal/themes/FontDefinition;
       5: astore_2
       6: aload_2
       7: ifnonnull     23
      10: aload_0
      11: invokevirtual #1579               // Method getPreferenceStore:()Lorg/eclipse/jface/preference/IPreferenceStore;
      14: aload_0
      15: aload_1
      16: invokevirtual #1623               // Method createPreferenceKey:(Lorg/eclipse/ui/internal/themes/ThemeElementDefinition;)Ljava/lang/String;
      19: invokestatic  #1422               // Method org/eclipse/jface/preference/PreferenceConverter.getDefaultFontDataArray:(Lorg/eclipse/jface/preference/IPreferenceStore;Ljava/lang/String;)[Lorg/eclipse/swt/graphics/FontData;
      22: areturn
      23: aload_0
      24: aload_2
      25: invokevirtual #1627               // Method getFontValue:(Lorg/eclipse/ui/internal/themes/FontDefinition;)[Lorg/eclipse/swt/graphics/FontData;
      28: areturn

  protected org.eclipse.swt.graphics.FontData[] getFontValue(org.eclipse.ui.internal.themes.FontDefinition);
    Code:
       0: aload_1
       1: invokevirtual #1661               // Method org/eclipse/ui/internal/themes/FontDefinition.getId:()Ljava/lang/String;
       4: astore_2
       5: aload_0
       6: getfield      #1351               // Field fontPreferencesToSet:Ljava/util/Map;
       9: aload_1
      10: invokeinterface #1689,  2         // InterfaceMethod java/util/Map.get:(Ljava/lang/Object;)Ljava/lang/Object;
      15: checkcast     #630                // class "[Lorg/eclipse/swt/graphics/FontData;"
      18: astore_3
      19: aload_3
      20: ifnonnull     55
      23: aload_0
      24: getfield      #1352               // Field fontValuesToSet:Ljava/util/Map;
      27: aload_2
      28: invokeinterface #1689,  2         // InterfaceMethod java/util/Map.get:(Ljava/lang/Object;)Ljava/lang/Object;
      33: checkcast     #630                // class "[Lorg/eclipse/swt/graphics/FontData;"
      36: astore_3
      37: aload_3
      38: ifnonnull     55
      41: aload_0
      42: getfield      #1384               // Field currentTheme:Lorg/eclipse/ui/themes/ITheme;
      45: invokeinterface #1719,  1         // InterfaceMethod org/eclipse/ui/themes/ITheme.getFontRegistry:()Lorg/eclipse/jface/resource/FontRegistry;
      50: aload_2
      51: invokevirtual #1427               // Method org/eclipse/jface/resource/FontRegistry.getFontData:(Ljava/lang/String;)[Lorg/eclipse/swt/graphics/FontData;
      54: astore_3
      55: aload_3
      56: areturn

  protected org.eclipse.ui.internal.themes.ColorDefinition getSelectedColorDefinition();
    Code:
       0: aload_0
       1: getfield      #1377               // Field tree:Lorg/eclipse/ui/dialogs/FilteredTree;
       4: invokevirtual #1534               // Method org/eclipse/ui/dialogs/FilteredTree.getViewer:()Lorg/eclipse/jface/viewers/TreeViewer;
       7: invokevirtual #1454               // Method org/eclipse/jface/viewers/TreeViewer.getStructuredSelection:()Lorg/eclipse/jface/viewers/ITreeSelection;
      10: invokeinterface #1704,  1         // InterfaceMethod org/eclipse/jface/viewers/ITreeSelection.getFirstElement:()Ljava/lang/Object;
      15: astore_1
      16: aload_1
      17: instanceof    #712                // class org/eclipse/ui/internal/themes/ColorDefinition
      20: ifeq          40
      23: aload_0
      24: getfield      #1383               // Field themeRegistry:Lorg/eclipse/ui/internal/themes/IThemeRegistry;
      27: aload_1
      28: checkcast     #712                // class org/eclipse/ui/internal/themes/ColorDefinition
      31: invokevirtual #1556               // Method org/eclipse/ui/internal/themes/ColorDefinition.getId:()Ljava/lang/String;
      34: invokeinterface #1715,  2         // InterfaceMethod org/eclipse/ui/internal/themes/IThemeRegistry.findColor:(Ljava/lang/String;)Lorg/eclipse/ui/internal/themes/ColorDefinition;
      39: areturn
      40: aconst_null
      41: areturn

  protected org.eclipse.ui.internal.themes.FontDefinition getSelectedFontDefinition();
    Code:
       0: aload_0
       1: getfield      #1377               // Field tree:Lorg/eclipse/ui/dialogs/FilteredTree;
       4: invokevirtual #1534               // Method org/eclipse/ui/dialogs/FilteredTree.getViewer:()Lorg/eclipse/jface/viewers/TreeViewer;
       7: invokevirtual #1454               // Method org/eclipse/jface/viewers/TreeViewer.getStructuredSelection:()Lorg/eclipse/jface/viewers/ITreeSelection;
      10: invokeinterface #1704,  1         // InterfaceMethod org/eclipse/jface/viewers/ITreeSelection.getFirstElement:()Ljava/lang/Object;
      15: astore_1
      16: aload_1
      17: instanceof    #719                // class org/eclipse/ui/internal/themes/FontDefinition
      20: ifeq          40
      23: aload_0
      24: getfield      #1383               // Field themeRegistry:Lorg/eclipse/ui/internal/themes/IThemeRegistry;
      27: aload_1
      28: checkcast     #719                // class org/eclipse/ui/internal/themes/FontDefinition
      31: invokevirtual #1661               // Method org/eclipse/ui/internal/themes/FontDefinition.getId:()Ljava/lang/String;
      34: invokeinterface #1716,  2         // InterfaceMethod org/eclipse/ui/internal/themes/IThemeRegistry.findFont:(Ljava/lang/String;)Lorg/eclipse/ui/internal/themes/FontDefinition;
      39: areturn
      40: aconst_null
      41: areturn

  protected boolean isFontSelected();
    Code:
       0: aload_0
       1: getfield      #1377               // Field tree:Lorg/eclipse/ui/dialogs/FilteredTree;
       4: invokevirtual #1534               // Method org/eclipse/ui/dialogs/FilteredTree.getViewer:()Lorg/eclipse/jface/viewers/TreeViewer;
       7: invokevirtual #1454               // Method org/eclipse/jface/viewers/TreeViewer.getStructuredSelection:()Lorg/eclipse/jface/viewers/ITreeSelection;
      10: invokeinterface #1704,  1         // InterfaceMethod org/eclipse/jface/viewers/ITreeSelection.getFirstElement:()Ljava/lang/Object;
      15: astore_1
      16: aload_1
      17: instanceof    #719                // class org/eclipse/ui/internal/themes/FontDefinition
      20: ireturn

  protected boolean isColorSelected();
    Code:
       0: aload_0
       1: getfield      #1377               // Field tree:Lorg/eclipse/ui/dialogs/FilteredTree;
       4: invokevirtual #1534               // Method org/eclipse/ui/dialogs/FilteredTree.getViewer:()Lorg/eclipse/jface/viewers/TreeViewer;
       7: invokevirtual #1454               // Method org/eclipse/jface/viewers/TreeViewer.getStructuredSelection:()Lorg/eclipse/jface/viewers/ITreeSelection;
      10: invokeinterface #1704,  1         // InterfaceMethod org/eclipse/jface/viewers/ITreeSelection.getFirstElement:()Ljava/lang/Object;
      15: astore_1
      16: aload_1
      17: instanceof    #712                // class org/eclipse/ui/internal/themes/ColorDefinition
      20: ireturn

  private void hookListeners();
    Code:
       0: aload_0
       1: getfield      #1377               // Field tree:Lorg/eclipse/ui/dialogs/FilteredTree;
       4: invokevirtual #1534               // Method org/eclipse/ui/dialogs/FilteredTree.getViewer:()Lorg/eclipse/jface/viewers/TreeViewer;
       7: astore_1
       8: aload_1
       9: aload_0
      10: invokedynamic #1752,  0           // InvokeDynamic #8:selectionChanged:(Lorg/eclipse/ui/internal/themes/ColorsAndFontsPreferencePage;)Lorg/eclipse/jface/viewers/ISelectionChangedListener;
      15: invokevirtual #1453               // Method org/eclipse/jface/viewers/TreeViewer.addSelectionChangedListener:(Lorg/eclipse/jface/viewers/ISelectionChangedListener;)V
      18: aload_0
      19: getfield      #1366               // Field fontChangeButton:Lorg/eclipse/swt/widgets/Button;
      22: aload_0
      23: invokedynamic #1745,  0           // InvokeDynamic #0:accept:(Lorg/eclipse/ui/internal/themes/ColorsAndFontsPreferencePage;)Ljava/util/function/Consumer;
      28: invokestatic  #1705               // InterfaceMethod org/eclipse/swt/events/SelectionListener.widgetSelectedAdapter:(Ljava/util/function/Consumer;)Lorg/eclipse/swt/events/SelectionListener;
      31: invokevirtual #1492               // Method org/eclipse/swt/widgets/Button.addSelectionListener:(Lorg/eclipse/swt/events/SelectionListener;)V
      34: aload_0
      35: getfield      #1367               // Field fontResetButton:Lorg/eclipse/swt/widgets/Button;
      38: aload_0
      39: invokedynamic #1746,  0           // InvokeDynamic #1:accept:(Lorg/eclipse/ui/internal/themes/ColorsAndFontsPreferencePage;)Ljava/util/function/Consumer;
      44: invokestatic  #1705               // InterfaceMethod org/eclipse/swt/events/SelectionListener.widgetSelectedAdapter:(Ljava/util/function/Consumer;)Lorg/eclipse/swt/events/SelectionListener;
      47: invokevirtual #1492               // Method org/eclipse/swt/widgets/Button.addSelectionListener:(Lorg/eclipse/swt/events/SelectionListener;)V
      50: aload_0
      51: getfield      #1368               // Field fontSystemButton:Lorg/eclipse/swt/widgets/Button;
      54: aload_0
      55: invokedynamic #1747,  0           // InvokeDynamic #2:accept:(Lorg/eclipse/ui/internal/themes/ColorsAndFontsPreferencePage;)Ljava/util/function/Consumer;
      60: invokestatic  #1705               // InterfaceMethod org/eclipse/swt/events/SelectionListener.widgetSelectedAdapter:(Ljava/util/function/Consumer;)Lorg/eclipse/swt/events/SelectionListener;
      63: invokevirtual #1492               // Method org/eclipse/swt/widgets/Button.addSelectionListener:(Lorg/eclipse/swt/events/SelectionListener;)V
      66: aload_0
      67: getfield      #1364               // Field editDefaultButton:Lorg/eclipse/swt/widgets/Button;
      70: aload_0
      71: invokedynamic #1748,  0           // InvokeDynamic #3:accept:(Lorg/eclipse/ui/internal/themes/ColorsAndFontsPreferencePage;)Ljava/util/function/Consumer;
      76: invokestatic  #1705               // InterfaceMethod org/eclipse/swt/events/SelectionListener.widgetSelectedAdapter:(Ljava/util/function/Consumer;)Lorg/eclipse/swt/events/SelectionListener;
      79: invokevirtual #1492               // Method org/eclipse/swt/widgets/Button.addSelectionListener:(Lorg/eclipse/swt/events/SelectionListener;)V
      82: aload_0
      83: getfield      #1369               // Field goToDefaultButton:Lorg/eclipse/swt/widgets/Button;
      86: aload_0
      87: invokedynamic #1749,  0           // InvokeDynamic #4:accept:(Lorg/eclipse/ui/internal/themes/ColorsAndFontsPreferencePage;)Ljava/util/function/Consumer;
      92: invokestatic  #1705               // InterfaceMethod org/eclipse/swt/events/SelectionListener.widgetSelectedAdapter:(Ljava/util/function/Consumer;)Lorg/eclipse/swt/events/SelectionListener;
      95: invokevirtual #1492               // Method org/eclipse/swt/widgets/Button.addSelectionListener:(Lorg/eclipse/swt/events/SelectionListener;)V
      98: aload_0
      99: getfield      #1365               // Field expandAllButton:Lorg/eclipse/swt/widgets/Button;
     102: aload_0
     103: invokedynamic #1750,  0           // InvokeDynamic #5:accept:(Lorg/eclipse/ui/internal/themes/ColorsAndFontsPreferencePage;)Ljava/util/function/Consumer;
     108: invokestatic  #1705               // InterfaceMethod org/eclipse/swt/events/SelectionListener.widgetSelectedAdapter:(Ljava/util/function/Consumer;)Lorg/eclipse/swt/events/SelectionListener;
     111: invokevirtual #1492               // Method org/eclipse/swt/widgets/Button.addSelectionListener:(Lorg/eclipse/swt/events/SelectionListener;)V
     114: return

  public void init(org.eclipse.ui.IWorkbench);
    Code:
       0: aload_0
       1: aload_1
       2: checkcast     #706                // class org/eclipse/ui/internal/Workbench
       5: putfield      #1378               // Field workbench:Lorg/eclipse/ui/internal/Workbench;
       8: aload_0
       9: aload_0
      10: getfield      #1378               // Field workbench:Lorg/eclipse/ui/internal/Workbench;
      13: ldc_w         #658                // class org/eclipse/e4/ui/css/swt/theme/IThemeEngine
      16: invokevirtual #1540               // Method org/eclipse/ui/internal/Workbench.getService:(Ljava/lang/Class;)Ljava/lang/Object;
      19: checkcast     #658                // class org/eclipse/e4/ui/css/swt/theme/IThemeEngine
      22: putfield      #1358               // Field themeEngine:Lorg/eclipse/e4/ui/css/swt/theme/IThemeEngine;
      25: aload_0
      26: invokestatic  #1678               // Method org/eclipse/ui/internal/util/PrefUtil.getInternalPreferenceStore:()Lorg/eclipse/jface/preference/IPreferenceStore;
      29: invokevirtual #1580               // Method setPreferenceStore:(Lorg/eclipse/jface/preference/IPreferenceStore;)V
      32: aload_1
      33: invokeinterface #1707,  1         // InterfaceMethod org/eclipse/ui/IWorkbench.getThemeManager:()Lorg/eclipse/ui/themes/IThemeManager;
      38: astore_2
      39: aload_0
      40: aload_0
      41: aload_2
      42: invokedynamic #1756,  0           // InvokeDynamic #6:propertyChange:(Lorg/eclipse/ui/internal/themes/ColorsAndFontsPreferencePage;Lorg/eclipse/ui/themes/IThemeManager;)Lorg/eclipse/jface/util/IPropertyChangeListener;
      47: putfield      #1359               // Field themeChangeListener:Lorg/eclipse/jface/util/IPropertyChangeListener;
      50: aload_2
      51: aload_0
      52: getfield      #1359               // Field themeChangeListener:Lorg/eclipse/jface/util/IPropertyChangeListener;
      55: invokeinterface #1720,  2         // InterfaceMethod org/eclipse/ui/themes/IThemeManager.addPropertyChangeListener:(Lorg/eclipse/jface/util/IPropertyChangeListener;)V
      60: aload_0
      61: aload_2
      62: invokevirtual #1621               // Method updateThemeInfo:(Lorg/eclipse/ui/themes/IThemeManager;)V
      65: aload_0
      66: aload_0
      67: getfield      #1378               // Field workbench:Lorg/eclipse/ui/internal/Workbench;
      70: ldc_w         #657                // class org/eclipse/e4/core/services/events/IEventBroker
      73: invokevirtual #1540               // Method org/eclipse/ui/internal/Workbench.getService:(Ljava/lang/Class;)Ljava/lang/Object;
      76: checkcast     #657                // class org/eclipse/e4/core/services/events/IEventBroker
      79: putfield      #1356               // Field eventBroker:Lorg/eclipse/e4/core/services/events/IEventBroker;
      82: aload_0
      83: getfield      #1356               // Field eventBroker:Lorg/eclipse/e4/core/services/events/IEventBroker;
      86: ldc_w         #625                // String org/eclipse/ui/internal/themes/WorkbenchThemeManager/themeRegistryRestyled
      89: aload_0
      90: getfield      #1385               // Field themeRegistryRestyledHandler:Lorg/osgi/service/event/EventHandler;
      93: invokeinterface #1698,  3         // InterfaceMethod org/eclipse/e4/core/services/events/IEventBroker.subscribe:(Ljava/lang/String;Lorg/osgi/service/event/EventHandler;)Z
      98: pop
      99: return

  private void updateThemeInfo(org.eclipse.ui.themes.IThemeManager);
    Code:
       0: aload_0
       1: invokevirtual #1558               // Method clearPreviews:()V
       4: aload_0
       5: getfield      #1348               // Field categoryMap:Ljava/util/Map;
       8: invokeinterface #1686,  1         // InterfaceMethod java/util/Map.clear:()V
      13: aload_0
      14: getfield      #1382               // Field labelProvider:Lorg/eclipse/ui/internal/themes/ColorsAndFontsPreferencePage$PresentationLabelProvider;
      17: ifnull        27
      20: aload_0
      21: getfield      #1382               // Field labelProvider:Lorg/eclipse/ui/internal/themes/ColorsAndFontsPreferencePage$PresentationLabelProvider;
      24: invokevirtual #1654               // Method org/eclipse/ui/internal/themes/ColorsAndFontsPreferencePage$PresentationLabelProvider.dispose:()V
      27: aload_0
      28: getfield      #1379               // Field colorRegistry:Lorg/eclipse/ui/internal/themes/CascadingColorRegistry;
      31: ifnull        41
      34: aload_0
      35: getfield      #1379               // Field colorRegistry:Lorg/eclipse/ui/internal/themes/CascadingColorRegistry;
      38: invokevirtual #1545               // Method org/eclipse/ui/internal/themes/CascadingColorRegistry.dispose:()V
      41: aload_0
      42: getfield      #1380               // Field fontRegistry:Lorg/eclipse/ui/internal/themes/CascadingFontRegistry;
      45: ifnull        55
      48: aload_0
      49: getfield      #1380               // Field fontRegistry:Lorg/eclipse/ui/internal/themes/CascadingFontRegistry;
      52: invokevirtual #1550               // Method org/eclipse/ui/internal/themes/CascadingFontRegistry.dispose:()V
      55: aload_0
      56: aload_1
      57: invokeinterface #1722,  1         // InterfaceMethod org/eclipse/ui/themes/IThemeManager.getCurrentTheme:()Lorg/eclipse/ui/themes/ITheme;
      62: putfield      #1384               // Field currentTheme:Lorg/eclipse/ui/themes/ITheme;
      65: aload_0
      66: aload_0
      67: invokevirtual #1578               // Method getActiveTheme:()Lorg/eclipse/e4/ui/css/swt/theme/ITheme;
      70: putfield      #1357               // Field currentCSSTheme:Lorg/eclipse/e4/ui/css/swt/theme/ITheme;
      73: aload_0
      74: new           #710                // class org/eclipse/ui/internal/themes/CascadingColorRegistry
      77: dup
      78: aload_0
      79: getfield      #1384               // Field currentTheme:Lorg/eclipse/ui/themes/ITheme;
      82: invokeinterface #1718,  1         // InterfaceMethod org/eclipse/ui/themes/ITheme.getColorRegistry:()Lorg/eclipse/jface/resource/ColorRegistry;
      87: invokespecial #1546               // Method org/eclipse/ui/internal/themes/CascadingColorRegistry."<init>":(Lorg/eclipse/jface/resource/ColorRegistry;)V
      90: putfield      #1379               // Field colorRegistry:Lorg/eclipse/ui/internal/themes/CascadingColorRegistry;
      93: aload_0
      94: new           #711                // class org/eclipse/ui/internal/themes/CascadingFontRegistry
      97: dup
      98: aload_0
      99: getfield      #1384               // Field currentTheme:Lorg/eclipse/ui/themes/ITheme;
     102: invokeinterface #1719,  1         // InterfaceMethod org/eclipse/ui/themes/ITheme.getFontRegistry:()Lorg/eclipse/jface/resource/FontRegistry;
     107: invokespecial #1551               // Method org/eclipse/ui/internal/themes/CascadingFontRegistry."<init>":(Lorg/eclipse/jface/resource/FontRegistry;)V
     110: putfield      #1380               // Field fontRegistry:Lorg/eclipse/ui/internal/themes/CascadingFontRegistry;
     113: aload_0
     114: getfield      #1381               // Field cascadingTheme:Lorg/eclipse/ui/internal/themes/ColorsAndFontsPreferencePage$CascadingThemeExt;
     117: ifnull        150
     120: aload_0
     121: getfield      #1381               // Field cascadingTheme:Lorg/eclipse/ui/internal/themes/ColorsAndFontsPreferencePage$CascadingThemeExt;
     124: invokevirtual #1650               // Method org/eclipse/ui/internal/themes/ColorsAndFontsPreferencePage$CascadingThemeExt.dispose:()V
     127: aload_0
     128: new           #716                // class org/eclipse/ui/internal/themes/ColorsAndFontsPreferencePage$CascadingThemeExt
     131: dup
     132: aload_0
     133: getfield      #1384               // Field currentTheme:Lorg/eclipse/ui/themes/ITheme;
     136: aload_0
     137: getfield      #1379               // Field colorRegistry:Lorg/eclipse/ui/internal/themes/CascadingColorRegistry;
     140: aload_0
     141: getfield      #1380               // Field fontRegistry:Lorg/eclipse/ui/internal/themes/CascadingFontRegistry;
     144: invokespecial #1652               // Method org/eclipse/ui/internal/themes/ColorsAndFontsPreferencePage$CascadingThemeExt."<init>":(Lorg/eclipse/ui/themes/ITheme;Lorg/eclipse/ui/internal/themes/CascadingColorRegistry;Lorg/eclipse/ui/internal/themes/CascadingFontRegistry;)V
     147: putfield      #1381               // Field cascadingTheme:Lorg/eclipse/ui/internal/themes/ColorsAndFontsPreferencePage$CascadingThemeExt;
     150: aload_0
     151: getfield      #1351               // Field fontPreferencesToSet:Ljava/util/Map;
     154: invokeinterface #1686,  1         // InterfaceMethod java/util/Map.clear:()V
     159: aload_0
     160: getfield      #1352               // Field fontValuesToSet:Ljava/util/Map;
     163: invokeinterface #1686,  1         // InterfaceMethod java/util/Map.clear:()V
     168: aload_0
     169: getfield      #1349               // Field colorPreferencesToSet:Ljava/util/Map;
     172: invokeinterface #1686,  1         // InterfaceMethod java/util/Map.clear:()V
     177: aload_0
     178: getfield      #1350               // Field colorValuesToSet:Ljava/util/Map;
     181: invokeinterface #1686,  1         // InterfaceMethod java/util/Map.clear:()V
     186: aload_0
     187: getfield      #1382               // Field labelProvider:Lorg/eclipse/ui/internal/themes/ColorsAndFontsPreferencePage$PresentationLabelProvider;
     190: ifnull        200
     193: aload_0
     194: getfield      #1382               // Field labelProvider:Lorg/eclipse/ui/internal/themes/ColorsAndFontsPreferencePage$PresentationLabelProvider;
     197: invokevirtual #1655               // Method org/eclipse/ui/internal/themes/ColorsAndFontsPreferencePage$PresentationLabelProvider.hookListeners:()V
     200: return

  private boolean isDefault(org.eclipse.ui.internal.themes.ColorDefinition);
    Code:
       0: aload_1
       1: invokevirtual #1556               // Method org/eclipse/ui/internal/themes/ColorDefinition.getId:()Ljava/lang/String;
       4: astore_2
       5: aload_0
       6: getfield      #1349               // Field colorPreferencesToSet:Ljava/util/Map;
       9: aload_1
      10: invokeinterface #1687,  2         // InterfaceMethod java/util/Map.containsKey:(Ljava/lang/Object;)Z
      15: ifeq          76
      18: aload_1
      19: invokevirtual #1557               // Method org/eclipse/ui/internal/themes/ColorDefinition.getValue:()Lorg/eclipse/swt/graphics/RGB;
      22: ifnull        50
      25: aload_0
      26: getfield      #1349               // Field colorPreferencesToSet:Ljava/util/Map;
      29: aload_1
      30: invokeinterface #1689,  2         // InterfaceMethod java/util/Map.get:(Ljava/lang/Object;)Ljava/lang/Object;
      35: checkcast     #685                // class org/eclipse/swt/graphics/RGB
      38: aload_1
      39: invokevirtual #1557               // Method org/eclipse/ui/internal/themes/ColorDefinition.getValue:()Lorg/eclipse/swt/graphics/RGB;
      42: invokevirtual #1482               // Method org/eclipse/swt/graphics/RGB.equals:(Ljava/lang/Object;)Z
      45: ifeq          197
      48: iconst_1
      49: ireturn
      50: aload_0
      51: getfield      #1349               // Field colorPreferencesToSet:Ljava/util/Map;
      54: aload_1
      55: invokeinterface #1689,  2         // InterfaceMethod java/util/Map.get:(Ljava/lang/Object;)Ljava/lang/Object;
      60: checkcast     #685                // class org/eclipse/swt/graphics/RGB
      63: aload_0
      64: aload_1
      65: invokevirtual #1631               // Method getColorAncestorValue:(Lorg/eclipse/ui/internal/themes/ColorDefinition;)Lorg/eclipse/swt/graphics/RGB;
      68: invokevirtual #1482               // Method org/eclipse/swt/graphics/RGB.equals:(Ljava/lang/Object;)Z
      71: ifeq          197
      74: iconst_1
      75: ireturn
      76: aload_0
      77: getfield      #1350               // Field colorValuesToSet:Ljava/util/Map;
      80: aload_2
      81: invokeinterface #1687,  2         // InterfaceMethod java/util/Map.containsKey:(Ljava/lang/Object;)Z
      86: ifeq          147
      89: aload_1
      90: invokevirtual #1557               // Method org/eclipse/ui/internal/themes/ColorDefinition.getValue:()Lorg/eclipse/swt/graphics/RGB;
      93: ifnull        121
      96: aload_0
      97: getfield      #1350               // Field colorValuesToSet:Ljava/util/Map;
     100: aload_2
     101: invokeinterface #1689,  2         // InterfaceMethod java/util/Map.get:(Ljava/lang/Object;)Ljava/lang/Object;
     106: checkcast     #685                // class org/eclipse/swt/graphics/RGB
     109: aload_1
     110: invokevirtual #1557               // Method org/eclipse/ui/internal/themes/ColorDefinition.getValue:()Lorg/eclipse/swt/graphics/RGB;
     113: invokevirtual #1482               // Method org/eclipse/swt/graphics/RGB.equals:(Ljava/lang/Object;)Z
     116: ifeq          197
     119: iconst_1
     120: ireturn
     121: aload_0
     122: getfield      #1350               // Field colorValuesToSet:Ljava/util/Map;
     125: aload_2
     126: invokeinterface #1689,  2         // InterfaceMethod java/util/Map.get:(Ljava/lang/Object;)Ljava/lang/Object;
     131: checkcast     #685                // class org/eclipse/swt/graphics/RGB
     134: aload_0
     135: aload_1
     136: invokevirtual #1631               // Method getColorAncestorValue:(Lorg/eclipse/ui/internal/themes/ColorDefinition;)Lorg/eclipse/swt/graphics/RGB;
     139: invokevirtual #1482               // Method org/eclipse/swt/graphics/RGB.equals:(Ljava/lang/Object;)Z
     142: ifeq          197
     145: iconst_1
     146: ireturn
     147: aload_1
     148: invokevirtual #1557               // Method org/eclipse/ui/internal/themes/ColorDefinition.getValue:()Lorg/eclipse/swt/graphics/RGB;
     151: ifnull        173
     154: aload_0
     155: invokevirtual #1579               // Method getPreferenceStore:()Lorg/eclipse/jface/preference/IPreferenceStore;
     158: aload_0
     159: aload_1
     160: invokevirtual #1623               // Method createPreferenceKey:(Lorg/eclipse/ui/internal/themes/ThemeElementDefinition;)Ljava/lang/String;
     163: invokeinterface #1700,  2         // InterfaceMethod org/eclipse/jface/preference/IPreferenceStore.isDefault:(Ljava/lang/String;)Z
     168: ifeq          197
     171: iconst_1
     172: ireturn
     173: aload_0
     174: aload_1
     175: invokevirtual #1632               // Method getColorValue:(Lorg/eclipse/ui/internal/themes/ColorDefinition;)Lorg/eclipse/swt/graphics/RGB;
     178: astore_3
     179: aload_3
     180: ifnull        197
     183: aload_3
     184: aload_0
     185: aload_1
     186: invokevirtual #1631               // Method getColorAncestorValue:(Lorg/eclipse/ui/internal/themes/ColorDefinition;)Lorg/eclipse/swt/graphics/RGB;
     189: invokevirtual #1482               // Method org/eclipse/swt/graphics/RGB.equals:(Ljava/lang/Object;)Z
     192: ifeq          197
     195: iconst_1
     196: ireturn
     197: iconst_0
     198: ireturn

  private boolean isDefault(org.eclipse.ui.internal.themes.FontDefinition);
    Code:
       0: aload_1
       1: invokevirtual #1661               // Method org/eclipse/ui/internal/themes/FontDefinition.getId:()Ljava/lang/String;
       4: astore_2
       5: aload_0
       6: getfield      #1351               // Field fontPreferencesToSet:Ljava/util/Map;
       9: aload_1
      10: invokeinterface #1687,  2         // InterfaceMethod java/util/Map.containsKey:(Ljava/lang/Object;)Z
      15: ifeq          78
      18: aload_1
      19: invokevirtual #1662               // Method org/eclipse/ui/internal/themes/FontDefinition.getValue:()[Lorg/eclipse/swt/graphics/FontData;
      22: ifnull        50
      25: aload_0
      26: getfield      #1351               // Field fontPreferencesToSet:Ljava/util/Map;
      29: aload_1
      30: invokeinterface #1689,  2         // InterfaceMethod java/util/Map.get:(Ljava/lang/Object;)Ljava/lang/Object;
      35: checkcast     #628                // class "[Ljava/lang/Object;"
      38: aload_1
      39: invokevirtual #1662               // Method org/eclipse/ui/internal/themes/FontDefinition.getValue:()[Lorg/eclipse/swt/graphics/FontData;
      42: invokestatic  #1413               // Method java/util/Arrays.equals:([Ljava/lang/Object;[Ljava/lang/Object;)Z
      45: ifeq          203
      48: iconst_1
      49: ireturn
      50: aload_0
      51: aload_1
      52: invokevirtual #1626               // Method getFontAncestorValue:(Lorg/eclipse/ui/internal/themes/FontDefinition;)[Lorg/eclipse/swt/graphics/FontData;
      55: astore_3
      56: aload_0
      57: getfield      #1351               // Field fontPreferencesToSet:Ljava/util/Map;
      60: aload_1
      61: invokeinterface #1689,  2         // InterfaceMethod java/util/Map.get:(Ljava/lang/Object;)Ljava/lang/Object;
      66: checkcast     #628                // class "[Ljava/lang/Object;"
      69: aload_3
      70: invokestatic  #1413               // Method java/util/Arrays.equals:([Ljava/lang/Object;[Ljava/lang/Object;)Z
      73: ifeq          203
      76: iconst_1
      77: ireturn
      78: aload_0
      79: getfield      #1352               // Field fontValuesToSet:Ljava/util/Map;
      82: aload_2
      83: invokeinterface #1687,  2         // InterfaceMethod java/util/Map.containsKey:(Ljava/lang/Object;)Z
      88: ifeq          151
      91: aload_1
      92: invokevirtual #1662               // Method org/eclipse/ui/internal/themes/FontDefinition.getValue:()[Lorg/eclipse/swt/graphics/FontData;
      95: ifnull        123
      98: aload_0
      99: getfield      #1352               // Field fontValuesToSet:Ljava/util/Map;
     102: aload_2
     103: invokeinterface #1689,  2         // InterfaceMethod java/util/Map.get:(Ljava/lang/Object;)Ljava/lang/Object;
     108: checkcast     #628                // class "[Ljava/lang/Object;"
     111: aload_1
     112: invokevirtual #1662               // Method org/eclipse/ui/internal/themes/FontDefinition.getValue:()[Lorg/eclipse/swt/graphics/FontData;
     115: invokestatic  #1413               // Method java/util/Arrays.equals:([Ljava/lang/Object;[Ljava/lang/Object;)Z
     118: ifeq          203
     121: iconst_1
     122: ireturn
     123: aload_0
     124: aload_1
     125: invokevirtual #1626               // Method getFontAncestorValue:(Lorg/eclipse/ui/internal/themes/FontDefinition;)[Lorg/eclipse/swt/graphics/FontData;
     128: astore_3
     129: aload_0
     130: getfield      #1352               // Field fontValuesToSet:Ljava/util/Map;
     133: aload_2
     134: invokeinterface #1689,  2         // InterfaceMethod java/util/Map.get:(Ljava/lang/Object;)Ljava/lang/Object;
     139: checkcast     #628                // class "[Ljava/lang/Object;"
     142: aload_3
     143: invokestatic  #1413               // Method java/util/Arrays.equals:([Ljava/lang/Object;[Ljava/lang/Object;)Z
     146: ifeq          203
     149: iconst_1
     150: ireturn
     151: aload_1
     152: invokevirtual #1662               // Method org/eclipse/ui/internal/themes/FontDefinition.getValue:()[Lorg/eclipse/swt/graphics/FontData;
     155: ifnull        177
     158: aload_0
     159: invokevirtual #1579               // Method getPreferenceStore:()Lorg/eclipse/jface/preference/IPreferenceStore;
     162: aload_0
     163: aload_1
     164: invokevirtual #1623               // Method createPreferenceKey:(Lorg/eclipse/ui/internal/themes/ThemeElementDefinition;)Ljava/lang/String;
     167: invokeinterface #1700,  2         // InterfaceMethod org/eclipse/jface/preference/IPreferenceStore.isDefault:(Ljava/lang/String;)Z
     172: ifeq          203
     175: iconst_1
     176: ireturn
     177: aload_0
     178: aload_1
     179: invokevirtual #1626               // Method getFontAncestorValue:(Lorg/eclipse/ui/internal/themes/FontDefinition;)[Lorg/eclipse/swt/graphics/FontData;
     182: astore_3
     183: aload_3
     184: ifnonnull     189
     187: iconst_1
     188: ireturn
     189: aload_0
     190: aload_1
     191: invokevirtual #1627               // Method getFontValue:(Lorg/eclipse/ui/internal/themes/FontDefinition;)[Lorg/eclipse/swt/graphics/FontData;
     194: aload_3
     195: invokestatic  #1413               // Method java/util/Arrays.equals:([Ljava/lang/Object;[Ljava/lang/Object;)Z
     198: ifeq          203
     201: iconst_1
     202: ireturn
     203: iconst_0
     204: ireturn

  private void myApplyDialogFont(org.eclipse.swt.widgets.Control);
    Code:
       0: aload_1
       1: invokestatic  #1429               // Method org/eclipse/jface/resource/JFaceResources.getDialogFont:()Lorg/eclipse/swt/graphics/Font;
       4: invokevirtual #1512               // Method org/eclipse/swt/widgets/Control.setFont:(Lorg/eclipse/swt/graphics/Font;)V
       7: aload_0
       8: getfield      #1347               // Field dialogFontWidgets:Ljava/util/List;
      11: aload_1
      12: invokeinterface #1683,  2         // InterfaceMethod java/util/List.add:(Ljava/lang/Object;)Z
      17: pop
      18: return

  protected void performApply();
    Code:
       0: aload_0
       1: invokespecial #1425               // Method org/eclipse/jface/preference/PreferencePage.performApply:()V
       4: aload_0
       5: getfield      #1362               // Field appliedDialogFont:Lorg/eclipse/swt/graphics/Font;
       8: astore_1
       9: aload_0
      10: getfield      #1383               // Field themeRegistry:Lorg/eclipse/ui/internal/themes/IThemeRegistry;
      13: ldc_w         #622                // String org.eclipse.jface.dialogfont
      16: invokeinterface #1716,  2         // InterfaceMethod org/eclipse/ui/internal/themes/IThemeRegistry.findFont:(Ljava/lang/String;)Lorg/eclipse/ui/internal/themes/FontDefinition;
      21: astore_2
      22: aload_2
      23: ifnonnull     27
      26: return
      27: aload_0
      28: aload_2
      29: invokevirtual #1627               // Method getFontValue:(Lorg/eclipse/ui/internal/themes/FontDefinition;)[Lorg/eclipse/swt/graphics/FontData;
      32: astore_3
      33: aload_0
      34: new           #680                // class org/eclipse/swt/graphics/Font
      37: dup
      38: aload_0
      39: invokevirtual #1603               // Method getControl:()Lorg/eclipse/swt/widgets/Control;
      42: invokevirtual #1513               // Method org/eclipse/swt/widgets/Control.getDisplay:()Lorg/eclipse/swt/widgets/Display;
      45: aload_3
      46: invokespecial #1467               // Method org/eclipse/swt/graphics/Font."<init>":(Lorg/eclipse/swt/graphics/Device;[Lorg/eclipse/swt/graphics/FontData;)V
      49: putfield      #1362               // Field appliedDialogFont:Lorg/eclipse/swt/graphics/Font;
      52: aload_0
      53: aload_0
      54: getfield      #1362               // Field appliedDialogFont:Lorg/eclipse/swt/graphics/Font;
      57: invokevirtual #1593               // Method updateForDialogFontChange:(Lorg/eclipse/swt/graphics/Font;)V
      60: aload_0
      61: invokevirtual #1596               // Method getApplyButton:()Lorg/eclipse/swt/widgets/Button;
      64: aload_0
      65: getfield      #1362               // Field appliedDialogFont:Lorg/eclipse/swt/graphics/Font;
      68: invokevirtual #1493               // Method org/eclipse/swt/widgets/Button.setFont:(Lorg/eclipse/swt/graphics/Font;)V
      71: aload_0
      72: invokevirtual #1597               // Method getDefaultsButton:()Lorg/eclipse/swt/widgets/Button;
      75: aload_0
      76: getfield      #1362               // Field appliedDialogFont:Lorg/eclipse/swt/graphics/Font;
      79: invokevirtual #1493               // Method org/eclipse/swt/widgets/Button.setFont:(Lorg/eclipse/swt/graphics/Font;)V
      82: aload_1
      83: ifnull        90
      86: aload_1
      87: invokevirtual #1464               // Method org/eclipse/swt/graphics/Font.dispose:()V
      90: aload_0
      91: invokevirtual #1572               // Method performColorOk:()Z
      94: ifeq          108
      97: aload_0
      98: invokevirtual #1573               // Method performFontOk:()Z
     101: ifeq          108
     104: aload_0
     105: invokevirtual #1562               // Method publishThemeRegistryModifiedEvent:()V
     108: return

  private void performColorDefaults();
    Code:
       0: aload_0
       1: getfield      #1383               // Field themeRegistry:Lorg/eclipse/ui/internal/themes/IThemeRegistry;
       4: invokeinterface #1712,  1         // InterfaceMethod org/eclipse/ui/internal/themes/IThemeRegistry.getColors:()[Lorg/eclipse/ui/internal/themes/ColorDefinition;
       9: astore_1
      10: aload_1
      11: arraylength
      12: anewarray     #712                // class org/eclipse/ui/internal/themes/ColorDefinition
      15: astore_2
      16: aload_1
      17: iconst_0
      18: aload_2
      19: iconst_0
      20: aload_1
      21: arraylength
      22: invokestatic  #1408               // Method java/lang/System.arraycopy:(Ljava/lang/Object;ILjava/lang/Object;II)V
      25: aload_2
      26: new           #724                // class org/eclipse/ui/internal/themes/IThemeRegistry$HierarchyComparator
      29: dup
      30: aload_1
      31: invokespecial #1663               // Method org/eclipse/ui/internal/themes/IThemeRegistry$HierarchyComparator."<init>":([Lorg/eclipse/ui/internal/themes/IHierarchalThemeElementDefinition;)V
      34: invokestatic  #1414               // Method java/util/Arrays.sort:([Ljava/lang/Object;Ljava/util/Comparator;)V
      37: aload_2
      38: dup
      39: astore        6
      41: arraylength
      42: istore        5
      44: iconst_0
      45: istore        4
      47: goto          66
      50: aload         6
      52: iload         4
      54: aaload
      55: astore_3
      56: aload_0
      57: aload_3
      58: iconst_1
      59: invokevirtual #1611               // Method resetColor:(Lorg/eclipse/ui/internal/themes/ColorDefinition;Z)Z
      62: pop
      63: iinc          4, 1
      66: iload         4
      68: iload         5
      70: if_icmplt     50
      73: return

  private boolean performColorOk();
    Code:
       0: aload_0
       1: getfield      #1349               // Field colorPreferencesToSet:Ljava/util/Map;
       4: invokeinterface #1688,  1         // InterfaceMethod java/util/Map.entrySet:()Ljava/util/Set;
       9: invokeinterface #1695,  1         // InterfaceMethod java/util/Set.iterator:()Ljava/util/Iterator;
      14: astore_2
      15: goto          90
      18: aload_2
      19: invokeinterface #1680,  1         // InterfaceMethod java/util/Iterator.next:()Ljava/lang/Object;
      24: checkcast     #653                // class java/util/Map$Entry
      27: astore_1
      28: aload_0
      29: aload_1
      30: invokeinterface #1691,  1         // InterfaceMethod java/util/Map$Entry.getKey:()Ljava/lang/Object;
      35: checkcast     #726                // class org/eclipse/ui/internal/themes/ThemeElementDefinition
      38: invokevirtual #1623               // Method createPreferenceKey:(Lorg/eclipse/ui/internal/themes/ThemeElementDefinition;)Ljava/lang/String;
      41: astore_3
      42: aload_1
      43: invokeinterface #1692,  1         // InterfaceMethod java/util/Map$Entry.getValue:()Ljava/lang/Object;
      48: checkcast     #685                // class org/eclipse/swt/graphics/RGB
      51: invokestatic  #1430               // Method org/eclipse/jface/resource/StringConverter.asString:(Lorg/eclipse/swt/graphics/RGB;)Ljava/lang/String;
      54: astore        4
      56: aload_0
      57: invokevirtual #1579               // Method getPreferenceStore:()Lorg/eclipse/jface/preference/IPreferenceStore;
      60: aload_3
      61: invokeinterface #1701,  2         // InterfaceMethod org/eclipse/jface/preference/IPreferenceStore.getString:(Ljava/lang/String;)Ljava/lang/String;
      66: astore        5
      68: aload         4
      70: aload         5
      72: invokevirtual #1396               // Method java/lang/String.equals:(Ljava/lang/Object;)Z
      75: ifne          90
      78: aload_0
      79: invokevirtual #1579               // Method getPreferenceStore:()Lorg/eclipse/jface/preference/IPreferenceStore;
      82: aload_3
      83: aload         4
      85: invokeinterface #1702,  3         // InterfaceMethod org/eclipse/jface/preference/IPreferenceStore.setValue:(Ljava/lang/String;Ljava/lang/String;)V
      90: aload_2
      91: invokeinterface #1679,  1         // InterfaceMethod java/util/Iterator.hasNext:()Z
      96: ifne          18
      99: aload_0
     100: getfield      #1350               // Field colorValuesToSet:Ljava/util/Map;
     103: invokeinterface #1686,  1         // InterfaceMethod java/util/Map.clear:()V
     108: aload_0
     109: getfield      #1349               // Field colorPreferencesToSet:Ljava/util/Map;
     112: invokeinterface #1686,  1         // InterfaceMethod java/util/Map.clear:()V
     117: iconst_1
     118: ireturn

  private java.lang.String createPreferenceKey(org.eclipse.ui.internal.themes.ThemeElementDefinition);
    Code:
       0: aload_1
       1: invokevirtual #1667               // Method org/eclipse/ui/internal/themes/ThemeElementDefinition.isOverridden:()Z
       4: ifne          14
       7: aload_1
       8: invokevirtual #1666               // Method org/eclipse/ui/internal/themes/ThemeElementDefinition.isAddedByCss:()Z
      11: ifeq          30
      14: aload_0
      15: getfield      #1357               // Field currentCSSTheme:Lorg/eclipse/e4/ui/css/swt/theme/ITheme;
      18: aload_0
      19: getfield      #1384               // Field currentTheme:Lorg/eclipse/ui/themes/ITheme;
      22: aload_1
      23: invokevirtual #1671               // Method org/eclipse/ui/internal/themes/ThemeElementDefinition.getId:()Ljava/lang/String;
      26: invokestatic  #1673               // Method org/eclipse/ui/internal/themes/ThemeElementHelper.createPreferenceKey:(Lorg/eclipse/e4/ui/css/swt/theme/ITheme;Lorg/eclipse/ui/themes/ITheme;Ljava/lang/String;)Ljava/lang/String;
      29: areturn
      30: aload_0
      31: getfield      #1384               // Field currentTheme:Lorg/eclipse/ui/themes/ITheme;
      34: aload_1
      35: invokevirtual #1671               // Method org/eclipse/ui/internal/themes/ThemeElementDefinition.getId:()Ljava/lang/String;
      38: invokestatic  #1672               // Method org/eclipse/ui/internal/themes/ThemeElementHelper.createPreferenceKey:(Lorg/eclipse/ui/themes/ITheme;Ljava/lang/String;)Ljava/lang/String;
      41: areturn

  public void performDefaults();
    Code:
       0: aload_0
       1: invokevirtual #1560               // Method performColorDefaults:()V
       4: aload_0
       5: invokevirtual #1561               // Method performFontDefaults:()V
       8: aload_0
       9: invokevirtual #1569               // Method updateControls:()V
      12: aload_0
      13: getfield      #1377               // Field tree:Lorg/eclipse/ui/dialogs/FilteredTree;
      16: invokevirtual #1534               // Method org/eclipse/ui/dialogs/FilteredTree.getViewer:()Lorg/eclipse/jface/viewers/TreeViewer;
      19: invokevirtual #1437               // Method org/eclipse/jface/viewers/TreeViewer.refresh:()V
      22: return

  private void performFontDefaults();
    Code:
       0: aload_0
       1: getfield      #1383               // Field themeRegistry:Lorg/eclipse/ui/internal/themes/IThemeRegistry;
       4: invokeinterface #1713,  1         // InterfaceMethod org/eclipse/ui/internal/themes/IThemeRegistry.getFonts:()[Lorg/eclipse/ui/internal/themes/FontDefinition;
       9: astore_1
      10: aload_1
      11: arraylength
      12: anewarray     #719                // class org/eclipse/ui/internal/themes/FontDefinition
      15: astore_2
      16: aload_1
      17: iconst_0
      18: aload_2
      19: iconst_0
      20: aload_1
      21: arraylength
      22: invokestatic  #1408               // Method java/lang/System.arraycopy:(Ljava/lang/Object;ILjava/lang/Object;II)V
      25: aload_2
      26: new           #724                // class org/eclipse/ui/internal/themes/IThemeRegistry$HierarchyComparator
      29: dup
      30: aload_1
      31: invokespecial #1663               // Method org/eclipse/ui/internal/themes/IThemeRegistry$HierarchyComparator."<init>":([Lorg/eclipse/ui/internal/themes/IHierarchalThemeElementDefinition;)V
      34: invokestatic  #1414               // Method java/util/Arrays.sort:([Ljava/lang/Object;Ljava/util/Comparator;)V
      37: aload_2
      38: dup
      39: astore        6
      41: arraylength
      42: istore        5
      44: iconst_0
      45: istore        4
      47: goto          66
      50: aload         6
      52: iload         4
      54: aaload
      55: astore_3
      56: aload_0
      57: aload_3
      58: iconst_1
      59: invokevirtual #1616               // Method resetFont:(Lorg/eclipse/ui/internal/themes/FontDefinition;Z)Z
      62: pop
      63: iinc          4, 1
      66: iload         4
      68: iload         5
      70: if_icmplt     50
      73: return

  private boolean performFontOk();
    Code:
       0: aload_0
       1: getfield      #1351               // Field fontPreferencesToSet:Ljava/util/Map;
       4: invokeinterface #1688,  1         // InterfaceMethod java/util/Map.entrySet:()Ljava/util/Set;
       9: invokeinterface #1695,  1         // InterfaceMethod java/util/Set.iterator:()Ljava/util/Iterator;
      14: astore_2
      15: goto          90
      18: aload_2
      19: invokeinterface #1680,  1         // InterfaceMethod java/util/Iterator.next:()Ljava/lang/Object;
      24: checkcast     #653                // class java/util/Map$Entry
      27: astore_1
      28: aload_0
      29: aload_1
      30: invokeinterface #1691,  1         // InterfaceMethod java/util/Map$Entry.getKey:()Ljava/lang/Object;
      35: checkcast     #726                // class org/eclipse/ui/internal/themes/ThemeElementDefinition
      38: invokevirtual #1623               // Method createPreferenceKey:(Lorg/eclipse/ui/internal/themes/ThemeElementDefinition;)Ljava/lang/String;
      41: astore_3
      42: aload_1
      43: invokeinterface #1692,  1         // InterfaceMethod java/util/Map$Entry.getValue:()Ljava/lang/Object;
      48: checkcast     #630                // class "[Lorg/eclipse/swt/graphics/FontData;"
      51: invokestatic  #1421               // Method org/eclipse/jface/preference/PreferenceConverter.getStoredRepresentation:([Lorg/eclipse/swt/graphics/FontData;)Ljava/lang/String;
      54: astore        4
      56: aload_0
      57: invokevirtual #1579               // Method getPreferenceStore:()Lorg/eclipse/jface/preference/IPreferenceStore;
      60: aload_3
      61: invokeinterface #1701,  2         // InterfaceMethod org/eclipse/jface/preference/IPreferenceStore.getString:(Ljava/lang/String;)Ljava/lang/String;
      66: astore        5
      68: aload         4
      70: aload         5
      72: invokevirtual #1396               // Method java/lang/String.equals:(Ljava/lang/Object;)Z
      75: ifne          90
      78: aload_0
      79: invokevirtual #1579               // Method getPreferenceStore:()Lorg/eclipse/jface/preference/IPreferenceStore;
      82: aload_3
      83: aload         4
      85: invokeinterface #1702,  3         // InterfaceMethod org/eclipse/jface/preference/IPreferenceStore.setValue:(Ljava/lang/String;Ljava/lang/String;)V
      90: aload_2
      91: invokeinterface #1679,  1         // InterfaceMethod java/util/Iterator.hasNext:()Z
      96: ifne          18
      99: aload_0
     100: getfield      #1352               // Field fontValuesToSet:Ljava/util/Map;
     103: invokeinterface #1686,  1         // InterfaceMethod java/util/Map.clear:()V
     108: aload_0
     109: getfield      #1351               // Field fontPreferencesToSet:Ljava/util/Map;
     112: invokeinterface #1686,  1         // InterfaceMethod java/util/Map.clear:()V
     117: iconst_1
     118: ireturn

  public boolean performOk();
    Code:
       0: aload_0
       1: invokevirtual #1567               // Method saveTreeExpansion:()V
       4: aload_0
       5: invokevirtual #1568               // Method saveTreeSelection:()V
       8: aload_0
       9: invokevirtual #1572               // Method performColorOk:()Z
      12: ifeq          26
      15: aload_0
      16: invokevirtual #1573               // Method performFontOk:()Z
      19: ifeq          26
      22: iconst_1
      23: goto          27
      26: iconst_0
      27: istore_1
      28: iload_1
      29: ifeq          39
      32: invokestatic  #1677               // Method org/eclipse/ui/internal/util/PrefUtil.savePrefs:()V
      35: aload_0
      36: invokevirtual #1562               // Method publishThemeRegistryModifiedEvent:()V
      39: iload_1
      40: ireturn

  private void refreshCategory();
    Code:
       0: aload_0
       1: invokevirtual #1569               // Method updateControls:()V
       4: return

  private boolean resetColor(org.eclipse.ui.internal.themes.ColorDefinition, boolean);
    Code:
       0: iload_2
       1: ifne          12
       4: aload_0
       5: aload_1
       6: invokevirtual #1610               // Method isDefault:(Lorg/eclipse/ui/internal/themes/ColorDefinition;)Z
       9: ifne          57
      12: aload_1
      13: invokevirtual #1557               // Method org/eclipse/ui/internal/themes/ColorDefinition.getValue:()Lorg/eclipse/swt/graphics/RGB;
      16: ifnull        27
      19: aload_1
      20: invokevirtual #1557               // Method org/eclipse/ui/internal/themes/ColorDefinition.getValue:()Lorg/eclipse/swt/graphics/RGB;
      23: astore_3
      24: goto          33
      27: aload_0
      28: aload_1
      29: invokevirtual #1631               // Method getColorAncestorValue:(Lorg/eclipse/ui/internal/themes/ColorDefinition;)Lorg/eclipse/swt/graphics/RGB;
      32: astore_3
      33: aload_3
      34: ifnull        57
      37: aload_0
      38: aload_1
      39: aload_3
      40: iconst_1
      41: invokevirtual #1635               // Method setColorPreferenceValue:(Lorg/eclipse/ui/internal/themes/ColorDefinition;Lorg/eclipse/swt/graphics/RGB;Z)V
      44: aload_0
      45: aload_1
      46: aload_3
      47: invokevirtual #1634               // Method setRegistryValue:(Lorg/eclipse/ui/internal/themes/ColorDefinition;Lorg/eclipse/swt/graphics/RGB;)V
      50: aload_0
      51: aload_1
      52: invokevirtual #1618               // Method refreshElement:(Lorg/eclipse/ui/internal/themes/ThemeElementDefinition;)V
      55: iconst_1
      56: ireturn
      57: iconst_0
      58: ireturn

  protected boolean resetFont(org.eclipse.ui.internal.themes.FontDefinition, boolean);
    Code:
       0: iload_2
       1: ifne          12
       4: aload_0
       5: aload_1
       6: invokevirtual #1615               // Method isDefault:(Lorg/eclipse/ui/internal/themes/FontDefinition;)Z
       9: ifne          78
      12: aload_1
      13: invokevirtual #1658               // Method org/eclipse/ui/internal/themes/FontDefinition.isOverridden:()Z
      16: ifeq          27
      19: aload_1
      20: invokevirtual #1662               // Method org/eclipse/ui/internal/themes/FontDefinition.getValue:()[Lorg/eclipse/swt/graphics/FontData;
      23: astore_3
      24: goto          60
      27: iload_2
      28: ifne          47
      31: aload_1
      32: invokevirtual #1660               // Method org/eclipse/ui/internal/themes/FontDefinition.getDefaultsTo:()Ljava/lang/String;
      35: ifnull        47
      38: aload_0
      39: aload_1
      40: invokevirtual #1626               // Method getFontAncestorValue:(Lorg/eclipse/ui/internal/themes/FontDefinition;)[Lorg/eclipse/swt/graphics/FontData;
      43: astore_3
      44: goto          60
      47: aload_0
      48: invokevirtual #1579               // Method getPreferenceStore:()Lorg/eclipse/jface/preference/IPreferenceStore;
      51: aload_0
      52: aload_1
      53: invokevirtual #1623               // Method createPreferenceKey:(Lorg/eclipse/ui/internal/themes/ThemeElementDefinition;)Ljava/lang/String;
      56: invokestatic  #1422               // Method org/eclipse/jface/preference/PreferenceConverter.getDefaultFontDataArray:(Lorg/eclipse/jface/preference/IPreferenceStore;Ljava/lang/String;)[Lorg/eclipse/swt/graphics/FontData;
      59: astore_3
      60: aload_3
      61: ifnull        78
      64: aload_0
      65: aload_1
      66: aload_3
      67: iconst_1
      68: invokevirtual #1630               // Method setFontPreferenceValue:(Lorg/eclipse/ui/internal/themes/FontDefinition;[Lorg/eclipse/swt/graphics/FontData;Z)V
      71: aload_0
      72: aload_1
      73: invokevirtual #1618               // Method refreshElement:(Lorg/eclipse/ui/internal/themes/ThemeElementDefinition;)V
      76: iconst_1
      77: ireturn
      78: iconst_0
      79: ireturn

  protected void setColorPreferenceValue(org.eclipse.ui.internal.themes.ColorDefinition, org.eclipse.swt.graphics.RGB, boolean);
    Code:
       0: aload_0
       1: aload_1
       2: aload_2
       3: invokevirtual #1633               // Method setDescendantRegistryValues:(Lorg/eclipse/ui/internal/themes/ColorDefinition;Lorg/eclipse/swt/graphics/RGB;)V
       6: aload_0
       7: getfield      #1349               // Field colorPreferencesToSet:Ljava/util/Map;
      10: aload_1
      11: aload_2
      12: invokeinterface #1690,  3         // InterfaceMethod java/util/Map.put:(Ljava/lang/Object;Ljava/lang/Object;)Ljava/lang/Object;
      17: pop
      18: aload_0
      19: aload_1
      20: iload_3
      21: invokevirtual #1620               // Method updateDefinitionState:(Lorg/eclipse/ui/internal/themes/ThemeElementDefinition;Z)V
      24: return

  private void setDescendantRegistryValues(org.eclipse.ui.internal.themes.ColorDefinition, org.eclipse.swt.graphics.RGB);
    Code:
       0: aload_0
       1: aload_1
       2: invokevirtual #1641               // Method getDescendantColors:(Lorg/eclipse/ui/internal/themes/ColorDefinition;)[Lorg/eclipse/ui/internal/themes/ColorDefinition;
       5: dup
       6: astore        6
       8: arraylength
       9: istore        5
      11: iconst_0
      12: istore        4
      14: goto          61
      17: aload         6
      19: iload         4
      21: aaload
      22: astore_3
      23: aload_0
      24: aload_3
      25: invokevirtual #1610               // Method isDefault:(Lorg/eclipse/ui/internal/themes/ColorDefinition;)Z
      28: ifeq          58
      31: aload_0
      32: aload_3
      33: aload_2
      34: invokevirtual #1633               // Method setDescendantRegistryValues:(Lorg/eclipse/ui/internal/themes/ColorDefinition;Lorg/eclipse/swt/graphics/RGB;)V
      37: aload_0
      38: aload_3
      39: aload_2
      40: invokevirtual #1634               // Method setRegistryValue:(Lorg/eclipse/ui/internal/themes/ColorDefinition;Lorg/eclipse/swt/graphics/RGB;)V
      43: aload_0
      44: getfield      #1350               // Field colorValuesToSet:Ljava/util/Map;
      47: aload_3
      48: invokevirtual #1556               // Method org/eclipse/ui/internal/themes/ColorDefinition.getId:()Ljava/lang/String;
      51: aload_2
      52: invokeinterface #1690,  3         // InterfaceMethod java/util/Map.put:(Ljava/lang/Object;Ljava/lang/Object;)Ljava/lang/Object;
      57: pop
      58: iinc          4, 1
      61: iload         4
      63: iload         5
      65: if_icmplt     17
      68: return

  private void setDescendantRegistryValues(org.eclipse.ui.internal.themes.FontDefinition, org.eclipse.swt.graphics.FontData[], boolean);
    Code:
       0: aload_0
       1: aload_1
       2: invokevirtual #1643               // Method getDescendantFonts:(Lorg/eclipse/ui/internal/themes/FontDefinition;)[Lorg/eclipse/ui/internal/themes/FontDefinition;
       5: dup
       6: astore        7
       8: arraylength
       9: istore        6
      11: iconst_0
      12: istore        5
      14: goto          44
      17: aload         7
      19: iload         5
      21: aaload
      22: astore        4
      24: aload_0
      25: aload         4
      27: invokevirtual #1615               // Method isDefault:(Lorg/eclipse/ui/internal/themes/FontDefinition;)Z
      30: ifeq          41
      33: aload_0
      34: aload         4
      36: aload_2
      37: iload_3
      38: invokevirtual #1630               // Method setFontPreferenceValue:(Lorg/eclipse/ui/internal/themes/FontDefinition;[Lorg/eclipse/swt/graphics/FontData;Z)V
      41: iinc          5, 1
      44: iload         5
      46: iload         6
      48: if_icmplt     17
      51: return

  protected void setFontPreferenceValue(org.eclipse.ui.internal.themes.FontDefinition, org.eclipse.swt.graphics.FontData[], boolean);
    Code:
       0: aload_0
       1: aload_1
       2: aload_2
       3: iload_3
       4: invokevirtual #1629               // Method setDescendantRegistryValues:(Lorg/eclipse/ui/internal/themes/FontDefinition;[Lorg/eclipse/swt/graphics/FontData;Z)V
       7: aload_0
       8: getfield      #1351               // Field fontPreferencesToSet:Ljava/util/Map;
      11: aload_1
      12: aload_2
      13: invokeinterface #1690,  3         // InterfaceMethod java/util/Map.put:(Ljava/lang/Object;Ljava/lang/Object;)Ljava/lang/Object;
      18: pop
      19: aload_0
      20: aload_1
      21: aload_2
      22: invokevirtual #1628               // Method setRegistryValue:(Lorg/eclipse/ui/internal/themes/FontDefinition;[Lorg/eclipse/swt/graphics/FontData;)V
      25: aload_0
      26: aload_1
      27: iload_3
      28: invokevirtual #1620               // Method updateDefinitionState:(Lorg/eclipse/ui/internal/themes/ThemeElementDefinition;Z)V
      31: return

  protected void setRegistryValue(org.eclipse.ui.internal.themes.ColorDefinition, org.eclipse.swt.graphics.RGB);
    Code:
       0: aload_0
       1: getfield      #1379               // Field colorRegistry:Lorg/eclipse/ui/internal/themes/CascadingColorRegistry;
       4: aload_1
       5: invokevirtual #1556               // Method org/eclipse/ui/internal/themes/ColorDefinition.getId:()Ljava/lang/String;
       8: aload_2
       9: invokevirtual #1549               // Method org/eclipse/ui/internal/themes/CascadingColorRegistry.put:(Ljava/lang/String;Lorg/eclipse/swt/graphics/RGB;)V
      12: return

  protected void setRegistryValue(org.eclipse.ui.internal.themes.FontDefinition, org.eclipse.swt.graphics.FontData[]);
    Code:
       0: aload_0
       1: getfield      #1380               // Field fontRegistry:Lorg/eclipse/ui/internal/themes/CascadingFontRegistry;
       4: aload_1
       5: invokevirtual #1661               // Method org/eclipse/ui/internal/themes/FontDefinition.getId:()Ljava/lang/String;
       8: aload_2
       9: invokevirtual #1553               // Method org/eclipse/ui/internal/themes/CascadingFontRegistry.put:(Ljava/lang/String;[Lorg/eclipse/swt/graphics/FontData;)V
      12: return

  private org.eclipse.ui.themes.IThemePreview getThemePreview(org.eclipse.ui.internal.themes.ThemeElementCategory) throws org.eclipse.core.runtime.CoreException;
    Code:
       0: aload_1
       1: invokevirtual #1665               // Method org/eclipse/ui/internal/themes/ThemeElementCategory.createPreview:()Lorg/eclipse/ui/themes/IThemePreview;
       4: astore_2
       5: aload_2
       6: ifnull        11
       9: aload_2
      10: areturn
      11: aload_1
      12: invokevirtual #1664               // Method org/eclipse/ui/internal/themes/ThemeElementCategory.getParentId:()Ljava/lang/String;
      15: ifnull        58
      18: aload_0
      19: getfield      #1383               // Field themeRegistry:Lorg/eclipse/ui/internal/themes/IThemeRegistry;
      22: invokeinterface #1714,  1         // InterfaceMethod org/eclipse/ui/internal/themes/IThemeRegistry.getCategories:()[Lorg/eclipse/ui/internal/themes/ThemeElementCategory;
      27: aload_1
      28: invokevirtual #1664               // Method org/eclipse/ui/internal/themes/ThemeElementCategory.getParentId:()Ljava/lang/String;
      31: getstatic     #1386               // Field org/eclipse/ui/internal/themes/IThemeRegistry.ID_COMPARATOR:Ljava/util/Comparator;
      34: invokestatic  #1415               // Method java/util/Arrays.binarySearch:([Ljava/lang/Object;Ljava/lang/Object;Ljava/util/Comparator;)I
      37: istore_3
      38: iload_3
      39: iflt          58
      42: aload_0
      43: aload_0
      44: getfield      #1383               // Field themeRegistry:Lorg/eclipse/ui/internal/themes/IThemeRegistry;
      47: invokeinterface #1714,  1         // InterfaceMethod org/eclipse/ui/internal/themes/IThemeRegistry.getCategories:()[Lorg/eclipse/ui/internal/themes/ThemeElementCategory;
      52: iload_3
      53: aaload
      54: invokevirtual #1645               // Method getThemePreview:(Lorg/eclipse/ui/internal/themes/ThemeElementCategory;)Lorg/eclipse/ui/themes/IThemePreview;
      57: areturn
      58: aconst_null
      59: areturn

  private org.eclipse.ui.internal.themes.ColorsAndFontsPreferencePage$CascadingThemeExt getCascadingTheme();
    Code:
       0: aload_0
       1: getfield      #1381               // Field cascadingTheme:Lorg/eclipse/ui/internal/themes/ColorsAndFontsPreferencePage$CascadingThemeExt;
       4: ifnonnull     30
       7: aload_0
       8: new           #716                // class org/eclipse/ui/internal/themes/ColorsAndFontsPreferencePage$CascadingThemeExt
      11: dup
      12: aload_0
      13: getfield      #1384               // Field currentTheme:Lorg/eclipse/ui/themes/ITheme;
      16: aload_0
      17: getfield      #1379               // Field colorRegistry:Lorg/eclipse/ui/internal/themes/CascadingColorRegistry;
      20: aload_0
      21: getfield      #1380               // Field fontRegistry:Lorg/eclipse/ui/internal/themes/CascadingFontRegistry;
      24: invokespecial #1652               // Method org/eclipse/ui/internal/themes/ColorsAndFontsPreferencePage$CascadingThemeExt."<init>":(Lorg/eclipse/ui/themes/ITheme;Lorg/eclipse/ui/internal/themes/CascadingColorRegistry;Lorg/eclipse/ui/internal/themes/CascadingFontRegistry;)V
      27: putfield      #1381               // Field cascadingTheme:Lorg/eclipse/ui/internal/themes/ColorsAndFontsPreferencePage$CascadingThemeExt;
      30: aload_0
      31: getfield      #1381               // Field cascadingTheme:Lorg/eclipse/ui/internal/themes/ColorsAndFontsPreferencePage$CascadingThemeExt;
      34: areturn

  private void updateForDialogFontChange(org.eclipse.swt.graphics.Font);
    Code:
       0: aload_0
       1: getfield      #1347               // Field dialogFontWidgets:Ljava/util/List;
       4: invokeinterface #1684,  1         // InterfaceMethod java/util/List.iterator:()Ljava/util/Iterator;
       9: astore_2
      10: goto          26
      13: aload_2
      14: invokeinterface #1680,  1         // InterfaceMethod java/util/Iterator.next:()Ljava/lang/Object;
      19: checkcast     #694                // class org/eclipse/swt/widgets/Control
      22: aload_1
      23: invokevirtual #1512               // Method org/eclipse/swt/widgets/Control.setFont:(Lorg/eclipse/swt/graphics/Font;)V
      26: aload_2
      27: invokeinterface #1679,  1         // InterfaceMethod java/util/Iterator.hasNext:()Z
      32: ifne          13
      35: aload_0
      36: getfield      #1382               // Field labelProvider:Lorg/eclipse/ui/internal/themes/ColorsAndFontsPreferencePage$PresentationLabelProvider;
      39: invokevirtual #1653               // Method org/eclipse/ui/internal/themes/ColorsAndFontsPreferencePage$PresentationLabelProvider.clearFontCacheAndUpdate:()V
      42: return

  private void updateTreeSelection(org.eclipse.jface.viewers.ISelection);
    Code:
       0: aconst_null
       1: astore_2
       2: aload_1
       3: checkcast     #669                // class org/eclipse/jface/viewers/IStructuredSelection
       6: invokeinterface #1703,  1         // InterfaceMethod org/eclipse/jface/viewers/IStructuredSelection.getFirstElement:()Ljava/lang/Object;
      11: astore_3
      12: aload_3
      13: instanceof    #725                // class org/eclipse/ui/internal/themes/ThemeElementCategory
      16: ifeq          27
      19: aload_3
      20: checkcast     #725                // class org/eclipse/ui/internal/themes/ThemeElementCategory
      23: astore_2
      24: goto          90
      27: aload_3
      28: instanceof    #712                // class org/eclipse/ui/internal/themes/ColorDefinition
      31: ifeq          60
      34: aload_3
      35: checkcast     #712                // class org/eclipse/ui/internal/themes/ColorDefinition
      38: invokevirtual #1554               // Method org/eclipse/ui/internal/themes/ColorDefinition.getCategoryId:()Ljava/lang/String;
      41: astore        4
      43: invokestatic  #1541               // Method org/eclipse/ui/internal/WorkbenchPlugin.getDefault:()Lorg/eclipse/ui/internal/WorkbenchPlugin;
      46: invokevirtual #1542               // Method org/eclipse/ui/internal/WorkbenchPlugin.getThemeRegistry:()Lorg/eclipse/ui/internal/themes/IThemeRegistry;
      49: aload         4
      51: invokeinterface #1717,  2         // InterfaceMethod org/eclipse/ui/internal/themes/IThemeRegistry.findCategory:(Ljava/lang/String;)Lorg/eclipse/ui/internal/themes/ThemeElementCategory;
      56: astore_2
      57: goto          90
      60: aload_3
      61: instanceof    #719                // class org/eclipse/ui/internal/themes/FontDefinition
      64: ifeq          90
      67: aload_3
      68: checkcast     #719                // class org/eclipse/ui/internal/themes/FontDefinition
      71: invokevirtual #1659               // Method org/eclipse/ui/internal/themes/FontDefinition.getCategoryId:()Ljava/lang/String;
      74: astore        4
      76: invokestatic  #1541               // Method org/eclipse/ui/internal/WorkbenchPlugin.getDefault:()Lorg/eclipse/ui/internal/WorkbenchPlugin;
      79: invokevirtual #1542               // Method org/eclipse/ui/internal/WorkbenchPlugin.getThemeRegistry:()Lorg/eclipse/ui/internal/themes/IThemeRegistry;
      82: aload         4
      84: invokeinterface #1717,  2         // InterfaceMethod org/eclipse/ui/internal/themes/IThemeRegistry.findCategory:(Ljava/lang/String;)Lorg/eclipse/ui/internal/themes/ThemeElementCategory;
      89: astore_2
      90: aconst_null
      91: astore        4
      93: aload_2
      94: ifnull        284
      97: aload_0
      98: getfield      #1353               // Field previewMap:Ljava/util/Map;
     101: aload_2
     102: invokeinterface #1689,  2         // InterfaceMethod java/util/Map.get:(Ljava/lang/Object;)Ljava/lang/Object;
     107: checkcast     #693                // class org/eclipse/swt/widgets/Composite
     110: astore        4
     112: aload         4
     114: ifnonnull     284
     117: aload_0
     118: aload_2
     119: invokevirtual #1645               // Method getThemePreview:(Lorg/eclipse/ui/internal/themes/ThemeElementCategory;)Lorg/eclipse/ui/themes/IThemePreview;
     122: astore        5
     124: aload         5
     126: ifnull        284
     129: new           #693                // class org/eclipse/swt/widgets/Composite
     132: dup
     133: aload_0
     134: getfield      #1375               // Field previewComposite:Lorg/eclipse/swt/widgets/Composite;
     137: iconst_0
     138: invokespecial #1509               // Method org/eclipse/swt/widgets/Composite."<init>":(Lorg/eclipse/swt/widgets/Composite;I)V
     141: astore        4
     143: aload         4
     145: new           #687                // class org/eclipse/swt/layout/FillLayout
     148: dup
     149: invokespecial #1484               // Method org/eclipse/swt/layout/FillLayout."<init>":()V
     152: invokevirtual #1511               // Method org/eclipse/swt/widgets/Composite.setLayout:(Lorg/eclipse/swt/widgets/Layout;)V
     155: aload_0
     156: invokevirtual #1612               // Method getCascadingTheme:()Lorg/eclipse/ui/internal/themes/ColorsAndFontsPreferencePage$CascadingThemeExt;
     159: astore        6
     161: aload         5
     163: aload         4
     165: aload         6
     167: invokeinterface #1724,  3         // InterfaceMethod org/eclipse/ui/themes/IThemePreview.createControl:(Lorg/eclipse/swt/widgets/Composite;Lorg/eclipse/ui/themes/ITheme;)V
     172: aload_0
     173: getfield      #1355               // Field previewSet:Ljava/util/Set;
     176: aload         5
     178: invokeinterface #1694,  2         // InterfaceMethod java/util/Set.add:(Ljava/lang/Object;)Z
     183: pop
     184: aload_0
     185: getfield      #1353               // Field previewMap:Ljava/util/Map;
     188: aload_2
     189: aload         4
     191: invokeinterface #1690,  3         // InterfaceMethod java/util/Map.put:(Ljava/lang/Object;Ljava/lang/Object;)Ljava/lang/Object;
     196: pop
     197: goto          284
     200: astore        5
     202: new           #693                // class org/eclipse/swt/widgets/Composite
     205: dup
     206: aload_0
     207: getfield      #1375               // Field previewComposite:Lorg/eclipse/swt/widgets/Composite;
     210: iconst_0
     211: invokespecial #1509               // Method org/eclipse/swt/widgets/Composite."<init>":(Lorg/eclipse/swt/widgets/Composite;I)V
     214: astore        4
     216: aload         4
     218: new           #687                // class org/eclipse/swt/layout/FillLayout
     221: dup
     222: invokespecial #1484               // Method org/eclipse/swt/layout/FillLayout."<init>":()V
     225: invokevirtual #1511               // Method org/eclipse/swt/widgets/Composite.setLayout:(Lorg/eclipse/swt/widgets/Layout;)V
     228: aload_0
     229: aload         4
     231: invokevirtual #1604               // Method myApplyDialogFont:(Lorg/eclipse/swt/widgets/Control;)V
     234: new           #698                // class org/eclipse/swt/widgets/Text
     237: dup
     238: aload         4
     240: bipush        72
     242: invokespecial #1529               // Method org/eclipse/swt/widgets/Text."<init>":(Lorg/eclipse/swt/widgets/Composite;I)V
     245: astore        6
     247: aload         6
     249: getstatic     #1354               // Field RESOURCE_BUNDLE:Ljava/util/ResourceBundle;
     252: ldc_w         #612                // String errorCreatingPreview
     255: invokevirtual #1418               // Method java/util/ResourceBundle.getString:(Ljava/lang/String;)Ljava/lang/String;
     258: invokevirtual #1528               // Method org/eclipse/swt/widgets/Text.setText:(Ljava/lang/String;)V
     261: getstatic     #1354               // Field RESOURCE_BUNDLE:Ljava/util/ResourceBundle;
     264: ldc_w         #611                // String errorCreatePreviewLog
     267: invokevirtual #1418               // Method java/util/ResourceBundle.getString:(Ljava/lang/String;)Ljava/lang/String;
     270: iconst_4
     271: aload         5
     273: invokevirtual #1420               // Method org/eclipse/core/runtime/CoreException.getMessage:()Ljava/lang/String;
     276: aload         5
     278: invokestatic  #1544               // Method org/eclipse/ui/internal/misc/StatusUtil.newStatus:(ILjava/lang/String;Ljava/lang/Throwable;)Lorg/eclipse/core/runtime/IStatus;
     281: invokestatic  #1543               // Method org/eclipse/ui/internal/WorkbenchPlugin.log:(Ljava/lang/String;Lorg/eclipse/core/runtime/IStatus;)V
     284: aload         4
     286: ifnonnull     327
     289: aload_3
     290: instanceof    #712                // class org/eclipse/ui/internal/themes/ColorDefinition
     293: ifeq          305
     296: aload_0
     297: getfield      #1372               // Field defaultColorPreview:Lorg/eclipse/swt/widgets/Composite;
     300: astore        4
     302: goto          327
     305: aload_3
     306: instanceof    #719                // class org/eclipse/ui/internal/themes/FontDefinition
     309: ifeq          321
     312: aload_0
     313: getfield      #1373               // Field defaultFontPreview:Lorg/eclipse/swt/widgets/Composite;
     316: astore        4
     318: goto          327
     321: aload_0
     322: getfield      #1374               // Field defaultNoPreview:Lorg/eclipse/swt/widgets/Composite;
     325: astore        4
     327: aload_0
     328: getfield      #1360               // Field stackLayout:Lorg/eclipse/swt/custom/StackLayout;
     331: aload         4
     333: putfield      #1324               // Field org/eclipse/swt/custom/StackLayout.topControl:Lorg/eclipse/swt/widgets/Control;
     336: aload_0
     337: getfield      #1375               // Field previewComposite:Lorg/eclipse/swt/widgets/Composite;
     340: invokevirtual #1504               // Method org/eclipse/swt/widgets/Composite.layout:()V
     343: aload_0
     344: invokevirtual #1569               // Method updateControls:()V
     347: return
    Exception table:
       from    to  target type
         117   197   200   Class org/eclipse/core/runtime/CoreException

  private void restoreTreeSelection();
    Code:
       0: aload_0
       1: invokevirtual #1579               // Method getPreferenceStore:()Lorg/eclipse/jface/preference/IPreferenceStore;
       4: ldc           #4                  // String ColorsAndFontsPreferencePage.selectedElement
       6: invokeinterface #1701,  2         // InterfaceMethod org/eclipse/jface/preference/IPreferenceStore.getString:(Ljava/lang/String;)Ljava/lang/String;
      11: astore_1
      12: aload_1
      13: ifnonnull     17
      16: return
      17: aload_0
      18: aload_1
      19: invokevirtual #1644               // Method findElementFromMarker:(Ljava/lang/String;)Lorg/eclipse/ui/internal/themes/IThemeElementDefinition;
      22: astore_2
      23: aload_2
      24: ifnonnull     28
      27: return
      28: aload_0
      29: getfield      #1377               // Field tree:Lorg/eclipse/ui/dialogs/FilteredTree;
      32: invokevirtual #1534               // Method org/eclipse/ui/dialogs/FilteredTree.getViewer:()Lorg/eclipse/jface/viewers/TreeViewer;
      35: new           #672                // class org/eclipse/jface/viewers/StructuredSelection
      38: dup
      39: aload_2
      40: invokespecial #1435               // Method org/eclipse/jface/viewers/StructuredSelection."<init>":(Ljava/lang/Object;)V
      43: iconst_1
      44: invokevirtual #1452               // Method org/eclipse/jface/viewers/TreeViewer.setSelection:(Lorg/eclipse/jface/viewers/ISelection;Z)V
      47: return

  private void saveTreeSelection();
    Code:
       0: aload_0
       1: getfield      #1377               // Field tree:Lorg/eclipse/ui/dialogs/FilteredTree;
       4: invokevirtual #1534               // Method org/eclipse/ui/dialogs/FilteredTree.getViewer:()Lorg/eclipse/jface/viewers/TreeViewer;
       7: invokevirtual #1454               // Method org/eclipse/jface/viewers/TreeViewer.getStructuredSelection:()Lorg/eclipse/jface/viewers/ITreeSelection;
      10: astore_1
      11: aload_1
      12: invokeinterface #1703,  1         // InterfaceMethod org/eclipse/jface/viewers/IStructuredSelection.getFirstElement:()Ljava/lang/Object;
      17: astore_2
      18: new           #641                // class java/lang/StringBuilder
      21: dup
      22: invokespecial #1402               // Method java/lang/StringBuilder."<init>":()V
      25: astore_3
      26: aload_0
      27: aload_3
      28: aload_2
      29: invokevirtual #1622               // Method appendMarkerToBuffer:(Ljava/lang/StringBuilder;Ljava/lang/Object;)V
      32: aload_3
      33: invokevirtual #1401               // Method java/lang/StringBuilder.length:()I
      36: ifle          53
      39: aload_3
      40: aload_2
      41: checkcast     #722                // class org/eclipse/ui/internal/themes/IThemeElementDefinition
      44: invokeinterface #1711,  1         // InterfaceMethod org/eclipse/ui/internal/themes/IThemeElementDefinition.getId:()Ljava/lang/String;
      49: invokevirtual #1407               // Method java/lang/StringBuilder.append:(Ljava/lang/String;)Ljava/lang/StringBuilder;
      52: pop
      53: aload_0
      54: invokevirtual #1579               // Method getPreferenceStore:()Lorg/eclipse/jface/preference/IPreferenceStore;
      57: ldc           #4                  // String ColorsAndFontsPreferencePage.selectedElement
      59: aload_3
      60: invokevirtual #1404               // Method java/lang/StringBuilder.toString:()Ljava/lang/String;
      63: invokeinterface #1702,  3         // InterfaceMethod org/eclipse/jface/preference/IPreferenceStore.setValue:(Ljava/lang/String;Ljava/lang/String;)V
      68: return

  private void restoreTreeExpansion();
    Code:
       0: aload_0
       1: invokevirtual #1579               // Method getPreferenceStore:()Lorg/eclipse/jface/preference/IPreferenceStore;
       4: ldc           #3                  // String ColorsAndFontsPreferencePage.expandedCategories
       6: invokeinterface #1701,  2         // InterfaceMethod org/eclipse/jface/preference/IPreferenceStore.getString:(Ljava/lang/String;)Ljava/lang/String;
      11: astore_1
      12: aload_1
      13: ifnonnull     17
      16: return
      17: aload_1
      18: ldc           #2                  // String \t
      20: invokevirtual #1400               // Method java/lang/String.split:(Ljava/lang/String;)[Ljava/lang/String;
      23: astore_2
      24: aload_2
      25: arraylength
      26: ifne          30
      29: return
      30: new           #646                // class java/util/ArrayList
      33: dup
      34: aload_2
      35: arraylength
      36: invokespecial #1412               // Method java/util/ArrayList."<init>":(I)V
      39: astore_3
      40: aload_2
      41: dup
      42: astore        7
      44: arraylength
      45: istore        6
      47: iconst_0
      48: istore        5
      50: goto          85
      53: aload         7
      55: iload         5
      57: aaload
      58: astore        4
      60: aload_0
      61: aload         4
      63: invokevirtual #1644               // Method findElementFromMarker:(Ljava/lang/String;)Lorg/eclipse/ui/internal/themes/IThemeElementDefinition;
      66: astore        8
      68: aload         8
      70: ifnull        82
      73: aload_3
      74: aload         8
      76: invokeinterface #1683,  2         // InterfaceMethod java/util/List.add:(Ljava/lang/Object;)Z
      81: pop
      82: iinc          5, 1
      85: iload         5
      87: iload         6
      89: if_icmplt     53
      92: aload_0
      93: getfield      #1377               // Field tree:Lorg/eclipse/ui/dialogs/FilteredTree;
      96: invokevirtual #1534               // Method org/eclipse/ui/dialogs/FilteredTree.getViewer:()Lorg/eclipse/jface/viewers/TreeViewer;
      99: aload_3
     100: invokeinterface #1682,  1         // InterfaceMethod java/util/List.toArray:()[Ljava/lang/Object;
     105: invokevirtual #1447               // Method org/eclipse/jface/viewers/TreeViewer.setExpandedElements:([Ljava/lang/Object;)V
     108: return

  private org.eclipse.ui.internal.themes.IThemeElementDefinition findElementFromMarker(java.lang.String);
    Code:
       0: aload_1
       1: invokevirtual #1394               // Method java/lang/String.length:()I
       4: iconst_2
       5: if_icmpge     10
       8: aconst_null
       9: areturn
      10: aload_1
      11: iconst_0
      12: invokevirtual #1395               // Method java/lang/String.charAt:(I)C
      15: istore_2
      16: aload_1
      17: iconst_1
      18: invokevirtual #1398               // Method java/lang/String.substring:(I)Ljava/lang/String;
      21: astore_3
      22: aconst_null
      23: astore        4
      25: iload_2
      26: lookupswitch  { // 3
                    67: 75
                    70: 60
                    84: 90
               default: 102
          }
      60: aload_0
      61: getfield      #1383               // Field themeRegistry:Lorg/eclipse/ui/internal/themes/IThemeRegistry;
      64: aload_3
      65: invokeinterface #1716,  2         // InterfaceMethod org/eclipse/ui/internal/themes/IThemeRegistry.findFont:(Ljava/lang/String;)Lorg/eclipse/ui/internal/themes/FontDefinition;
      70: astore        4
      72: goto          102
      75: aload_0
      76: getfield      #1383               // Field themeRegistry:Lorg/eclipse/ui/internal/themes/IThemeRegistry;
      79: aload_3
      80: invokeinterface #1715,  2         // InterfaceMethod org/eclipse/ui/internal/themes/IThemeRegistry.findColor:(Ljava/lang/String;)Lorg/eclipse/ui/internal/themes/ColorDefinition;
      85: astore        4
      87: goto          102
      90: aload_0
      91: getfield      #1383               // Field themeRegistry:Lorg/eclipse/ui/internal/themes/IThemeRegistry;
      94: aload_3
      95: invokeinterface #1717,  2         // InterfaceMethod org/eclipse/ui/internal/themes/IThemeRegistry.findCategory:(Ljava/lang/String;)Lorg/eclipse/ui/internal/themes/ThemeElementCategory;
     100: astore        4
     102: aload         4
     104: areturn

  private void saveTreeExpansion();
    Code:
       0: aload_0
       1: getfield      #1377               // Field tree:Lorg/eclipse/ui/dialogs/FilteredTree;
       4: invokevirtual #1534               // Method org/eclipse/ui/dialogs/FilteredTree.getViewer:()Lorg/eclipse/jface/viewers/TreeViewer;
       7: invokevirtual #1439               // Method org/eclipse/jface/viewers/TreeViewer.getExpandedElements:()[Ljava/lang/Object;
      10: astore_1
      11: new           #646                // class java/util/ArrayList
      14: dup
      15: aload_1
      16: arraylength
      17: invokespecial #1412               // Method java/util/ArrayList."<init>":(I)V
      20: astore_2
      21: new           #641                // class java/lang/StringBuilder
      24: dup
      25: invokespecial #1402               // Method java/lang/StringBuilder."<init>":()V
      28: astore_3
      29: aload_1
      30: dup
      31: astore        7
      33: arraylength
      34: istore        6
      36: iconst_0
      37: istore        5
      39: goto          97
      42: aload         7
      44: iload         5
      46: aaload
      47: astore        4
      49: aload_0
      50: aload_3
      51: aload         4
      53: invokevirtual #1622               // Method appendMarkerToBuffer:(Ljava/lang/StringBuilder;Ljava/lang/Object;)V
      56: aload_3
      57: invokevirtual #1401               // Method java/lang/StringBuilder.length:()I
      60: ifeq          89
      63: aload_3
      64: aload         4
      66: checkcast     #722                // class org/eclipse/ui/internal/themes/IThemeElementDefinition
      69: invokeinterface #1711,  1         // InterfaceMethod org/eclipse/ui/internal/themes/IThemeElementDefinition.getId:()Ljava/lang/String;
      74: invokevirtual #1407               // Method java/lang/StringBuilder.append:(Ljava/lang/String;)Ljava/lang/StringBuilder;
      77: pop
      78: aload_2
      79: aload_3
      80: invokevirtual #1404               // Method java/lang/StringBuilder.toString:()Ljava/lang/String;
      83: invokeinterface #1683,  2         // InterfaceMethod java/util/List.add:(Ljava/lang/Object;)Z
      88: pop
      89: aload_3
      90: iconst_0
      91: invokevirtual #1403               // Method java/lang/StringBuilder.setLength:(I)V
      94: iinc          5, 1
      97: iload         5
      99: iload         6
     101: if_icmplt     42
     104: aload_2
     105: invokeinterface #1684,  1         // InterfaceMethod java/util/List.iterator:()Ljava/util/Iterator;
     110: astore        4
     112: goto          151
     115: aload         4
     117: invokeinterface #1680,  1         // InterfaceMethod java/util/Iterator.next:()Ljava/lang/Object;
     122: checkcast     #640                // class java/lang/String
     125: astore        5
     127: aload_3
     128: aload         5
     130: invokevirtual #1407               // Method java/lang/StringBuilder.append:(Ljava/lang/String;)Ljava/lang/StringBuilder;
     133: pop
     134: aload         4
     136: invokeinterface #1679,  1         // InterfaceMethod java/util/Iterator.hasNext:()Z
     141: ifeq          151
     144: aload_3
     145: ldc           #2                  // String \t
     147: invokevirtual #1407               // Method java/lang/StringBuilder.append:(Ljava/lang/String;)Ljava/lang/StringBuilder;
     150: pop
     151: aload         4
     153: invokeinterface #1679,  1         // InterfaceMethod java/util/Iterator.hasNext:()Z
     158: ifne          115
     161: aload_0
     162: invokevirtual #1579               // Method getPreferenceStore:()Lorg/eclipse/jface/preference/IPreferenceStore;
     165: ldc           #3                  // String ColorsAndFontsPreferencePage.expandedCategories
     167: aload_3
     168: invokevirtual #1404               // Method java/lang/StringBuilder.toString:()Ljava/lang/String;
     171: invokeinterface #1702,  3         // InterfaceMethod org/eclipse/jface/preference/IPreferenceStore.setValue:(Ljava/lang/String;Ljava/lang/String;)V
     176: return

  private void appendMarkerToBuffer(java.lang.StringBuilder, java.lang.Object);
    Code:
       0: aload_2
       1: instanceof    #719                // class org/eclipse/ui/internal/themes/FontDefinition
       4: ifeq          17
       7: aload_1
       8: bipush        70
      10: invokevirtual #1405               // Method java/lang/StringBuilder.append:(C)Ljava/lang/StringBuilder;
      13: pop
      14: goto          48
      17: aload_2
      18: instanceof    #712                // class org/eclipse/ui/internal/themes/ColorDefinition
      21: ifeq          34
      24: aload_1
      25: bipush        67
      27: invokevirtual #1405               // Method java/lang/StringBuilder.append:(C)Ljava/lang/StringBuilder;
      30: pop
      31: goto          48
      34: aload_2
      35: instanceof    #725                // class org/eclipse/ui/internal/themes/ThemeElementCategory
      38: ifeq          48
      41: aload_1
      42: bipush        84
      44: invokevirtual #1405               // Method java/lang/StringBuilder.append:(C)Ljava/lang/StringBuilder;
      47: pop
      48: return

  private void editFont(org.eclipse.swt.widgets.Display);
    Code:
       0: aload_0
       1: aload_0
       2: invokevirtual #1613               // Method getSelectedFontDefinition:()Lorg/eclipse/ui/internal/themes/FontDefinition;
       5: aload_1
       6: invokevirtual #1638               // Method editFont:(Lorg/eclipse/ui/internal/themes/FontDefinition;Lorg/eclipse/swt/widgets/Display;)V
       9: return

  private void editFont(org.eclipse.ui.internal.themes.FontDefinition, org.eclipse.swt.widgets.Display);
    Code:
       0: aload_1
       1: ifnull        56
       4: new           #696                // class org/eclipse/swt/widgets/FontDialog
       7: dup
       8: aload_0
       9: invokevirtual #1607               // Method getShell:()Lorg/eclipse/swt/widgets/Shell;
      12: invokespecial #1521               // Method org/eclipse/swt/widgets/FontDialog."<init>":(Lorg/eclipse/swt/widgets/Shell;)V
      15: astore_3
      16: aload_3
      17: iconst_0
      18: invokevirtual #1517               // Method org/eclipse/swt/widgets/FontDialog.setEffectsVisible:(Z)V
      21: aload_3
      22: aload_0
      23: aload_1
      24: invokevirtual #1627               // Method getFontValue:(Lorg/eclipse/ui/internal/themes/FontDefinition;)[Lorg/eclipse/swt/graphics/FontData;
      27: invokevirtual #1520               // Method org/eclipse/swt/widgets/FontDialog.setFontList:([Lorg/eclipse/swt/graphics/FontData;)V
      30: aload_3
      31: invokevirtual #1518               // Method org/eclipse/swt/widgets/FontDialog.open:()Lorg/eclipse/swt/graphics/FontData;
      34: astore        4
      36: aload         4
      38: ifnull        56
      41: aload_0
      42: aload_1
      43: aload_3
      44: invokevirtual #1519               // Method org/eclipse/swt/widgets/FontDialog.getFontList:()[Lorg/eclipse/swt/graphics/FontData;
      47: iconst_0
      48: invokevirtual #1630               // Method setFontPreferenceValue:(Lorg/eclipse/ui/internal/themes/FontDefinition;[Lorg/eclipse/swt/graphics/FontData;Z)V
      51: aload_0
      52: aload_1
      53: invokevirtual #1618               // Method refreshElement:(Lorg/eclipse/ui/internal/themes/ThemeElementDefinition;)V
      56: return

  private void editColor(org.eclipse.swt.widgets.Display);
    Code:
       0: aload_0
       1: aload_0
       2: invokevirtual #1608               // Method getSelectedColorDefinition:()Lorg/eclipse/ui/internal/themes/ColorDefinition;
       5: aload_1
       6: invokevirtual #1637               // Method editColor:(Lorg/eclipse/ui/internal/themes/ColorDefinition;Lorg/eclipse/swt/widgets/Display;)V
       9: return

  private void editColor(org.eclipse.ui.internal.themes.ColorDefinition, org.eclipse.swt.widgets.Display);
    Code:
       0: aload_1
       1: ifnonnull     5
       4: return
       5: aload_0
       6: getfield      #1379               // Field colorRegistry:Lorg/eclipse/ui/internal/themes/CascadingColorRegistry;
       9: aload_1
      10: invokevirtual #1556               // Method org/eclipse/ui/internal/themes/ColorDefinition.getId:()Ljava/lang/String;
      13: invokevirtual #1548               // Method org/eclipse/ui/internal/themes/CascadingColorRegistry.getRGB:(Ljava/lang/String;)Lorg/eclipse/swt/graphics/RGB;
      16: astore_3
      17: new           #692                // class org/eclipse/swt/widgets/ColorDialog
      20: dup
      21: aload_2
      22: invokevirtual #1516               // Method org/eclipse/swt/widgets/Display.getActiveShell:()Lorg/eclipse/swt/widgets/Shell;
      25: invokespecial #1503               // Method org/eclipse/swt/widgets/ColorDialog."<init>":(Lorg/eclipse/swt/widgets/Shell;)V
      28: astore        4
      30: aload         4
      32: aload_3
      33: invokevirtual #1502               // Method org/eclipse/swt/widgets/ColorDialog.setRGB:(Lorg/eclipse/swt/graphics/RGB;)V
      36: aload         4
      38: invokevirtual #1501               // Method org/eclipse/swt/widgets/ColorDialog.open:()Lorg/eclipse/swt/graphics/RGB;
      41: astore        5
      43: aload         5
      45: ifnull        77
      48: aload         5
      50: aload_3
      51: invokevirtual #1482               // Method org/eclipse/swt/graphics/RGB.equals:(Ljava/lang/Object;)Z
      54: ifne          77
      57: aload_0
      58: aload_1
      59: aload         5
      61: iconst_0
      62: invokevirtual #1635               // Method setColorPreferenceValue:(Lorg/eclipse/ui/internal/themes/ColorDefinition;Lorg/eclipse/swt/graphics/RGB;Z)V
      65: aload_0
      66: aload_1
      67: aload         5
      69: invokevirtual #1634               // Method setRegistryValue:(Lorg/eclipse/ui/internal/themes/ColorDefinition;Lorg/eclipse/swt/graphics/RGB;)V
      72: aload_0
      73: aload_1
      74: invokevirtual #1618               // Method refreshElement:(Lorg/eclipse/ui/internal/themes/ThemeElementDefinition;)V
      77: return

  protected void updateControls();
    Code:
       0: aload_0
       1: invokevirtual #1613               // Method getSelectedFontDefinition:()Lorg/eclipse/ui/internal/themes/FontDefinition;
       4: astore_1
       5: aload_1
       6: ifnull        87
       9: aload_0
      10: aload_1
      11: invokevirtual #1615               // Method isDefault:(Lorg/eclipse/ui/internal/themes/FontDefinition;)Z
      14: istore_2
      15: aload_0
      16: aload_1
      17: invokevirtual #1617               // Method defaultIsEditable:(Lorg/eclipse/ui/internal/themes/IHierarchalThemeElementDefinition;)Z
      20: istore_3
      21: aload_0
      22: getfield      #1366               // Field fontChangeButton:Lorg/eclipse/swt/widgets/Button;
      25: iconst_1
      26: invokevirtual #1490               // Method org/eclipse/swt/widgets/Button.setEnabled:(Z)V
      29: aload_0
      30: getfield      #1368               // Field fontSystemButton:Lorg/eclipse/swt/widgets/Button;
      33: iconst_1
      34: invokevirtual #1490               // Method org/eclipse/swt/widgets/Button.setEnabled:(Z)V
      37: aload_0
      38: getfield      #1367               // Field fontResetButton:Lorg/eclipse/swt/widgets/Button;
      41: iload_2
      42: ifeq          49
      45: iconst_0
      46: goto          50
      49: iconst_1
      50: invokevirtual #1490               // Method org/eclipse/swt/widgets/Button.setEnabled:(Z)V
      53: aload_0
      54: getfield      #1364               // Field editDefaultButton:Lorg/eclipse/swt/widgets/Button;
      57: iload_3
      58: ifeq          69
      61: iload_2
      62: ifeq          69
      65: iconst_1
      66: goto          70
      69: iconst_0
      70: invokevirtual #1490               // Method org/eclipse/swt/widgets/Button.setEnabled:(Z)V
      73: aload_0
      74: getfield      #1369               // Field goToDefaultButton:Lorg/eclipse/swt/widgets/Button;
      77: iload_3
      78: invokevirtual #1490               // Method org/eclipse/swt/widgets/Button.setEnabled:(Z)V
      81: aload_0
      82: aload_1
      83: invokevirtual #1614               // Method setCurrentFont:(Lorg/eclipse/ui/internal/themes/FontDefinition;)V
      86: return
      87: aload_0
      88: invokevirtual #1608               // Method getSelectedColorDefinition:()Lorg/eclipse/ui/internal/themes/ColorDefinition;
      91: astore_2
      92: aload_2
      93: ifnull        180
      96: aload_0
      97: aload_0
      98: invokevirtual #1608               // Method getSelectedColorDefinition:()Lorg/eclipse/ui/internal/themes/ColorDefinition;
     101: invokevirtual #1610               // Method isDefault:(Lorg/eclipse/ui/internal/themes/ColorDefinition;)Z
     104: istore_3
     105: aload_0
     106: aload_2
     107: invokevirtual #1617               // Method defaultIsEditable:(Lorg/eclipse/ui/internal/themes/IHierarchalThemeElementDefinition;)Z
     110: istore        4
     112: aload_0
     113: getfield      #1366               // Field fontChangeButton:Lorg/eclipse/swt/widgets/Button;
     116: iconst_1
     117: invokevirtual #1490               // Method org/eclipse/swt/widgets/Button.setEnabled:(Z)V
     120: aload_0
     121: getfield      #1368               // Field fontSystemButton:Lorg/eclipse/swt/widgets/Button;
     124: iconst_0
     125: invokevirtual #1490               // Method org/eclipse/swt/widgets/Button.setEnabled:(Z)V
     128: aload_0
     129: getfield      #1367               // Field fontResetButton:Lorg/eclipse/swt/widgets/Button;
     132: iload_3
     133: ifeq          140
     136: iconst_0
     137: goto          141
     140: iconst_1
     141: invokevirtual #1490               // Method org/eclipse/swt/widgets/Button.setEnabled:(Z)V
     144: aload_0
     145: getfield      #1364               // Field editDefaultButton:Lorg/eclipse/swt/widgets/Button;
     148: iload         4
     150: ifeq          161
     153: iload_3
     154: ifeq          161
     157: iconst_1
     158: goto          162
     161: iconst_0
     162: invokevirtual #1490               // Method org/eclipse/swt/widgets/Button.setEnabled:(Z)V
     165: aload_0
     166: getfield      #1369               // Field goToDefaultButton:Lorg/eclipse/swt/widgets/Button;
     169: iload         4
     171: invokevirtual #1490               // Method org/eclipse/swt/widgets/Button.setEnabled:(Z)V
     174: aload_0
     175: aload_2
     176: invokevirtual #1609               // Method setCurrentColor:(Lorg/eclipse/ui/internal/themes/ColorDefinition;)V
     179: return
     180: aload_0
     181: getfield      #1366               // Field fontChangeButton:Lorg/eclipse/swt/widgets/Button;
     184: iconst_0
     185: invokevirtual #1490               // Method org/eclipse/swt/widgets/Button.setEnabled:(Z)V
     188: aload_0
     189: getfield      #1368               // Field fontSystemButton:Lorg/eclipse/swt/widgets/Button;
     192: iconst_0
     193: invokevirtual #1490               // Method org/eclipse/swt/widgets/Button.setEnabled:(Z)V
     196: aload_0
     197: getfield      #1367               // Field fontResetButton:Lorg/eclipse/swt/widgets/Button;
     200: iconst_0
     201: invokevirtual #1490               // Method org/eclipse/swt/widgets/Button.setEnabled:(Z)V
     204: aload_0
     205: getfield      #1364               // Field editDefaultButton:Lorg/eclipse/swt/widgets/Button;
     208: iconst_0
     209: invokevirtual #1490               // Method org/eclipse/swt/widgets/Button.setEnabled:(Z)V
     212: aload_0
     213: getfield      #1369               // Field goToDefaultButton:Lorg/eclipse/swt/widgets/Button;
     216: iconst_0
     217: invokevirtual #1490               // Method org/eclipse/swt/widgets/Button.setEnabled:(Z)V
     220: aload_0
     221: getfield      #1376               // Field descriptionText:Lorg/eclipse/swt/widgets/Text;
     224: ldc           #1                  // String
     226: invokevirtual #1528               // Method org/eclipse/swt/widgets/Text.setText:(Ljava/lang/String;)V
     229: return

  private boolean defaultIsEditable(org.eclipse.ui.internal.themes.IHierarchalThemeElementDefinition);
    Code:
       0: getstatic     #1345               // Field $assertionsDisabled:Z
       3: ifne          28
       6: aload_1
       7: instanceof    #712                // class org/eclipse/ui/internal/themes/ColorDefinition
      10: ifne          28
      13: aload_1
      14: instanceof    #719                // class org/eclipse/ui/internal/themes/FontDefinition
      17: ifne          28
      20: new           #634                // class java/lang/AssertionError
      23: dup
      24: invokespecial #1388               // Method java/lang/AssertionError."<init>":()V
      27: athrow
      28: aload_1
      29: invokeinterface #1710,  1         // InterfaceMethod org/eclipse/ui/internal/themes/IHierarchalThemeElementDefinition.getDefaultsTo:()Ljava/lang/String;
      34: astore_2
      35: aload_2
      36: ifnonnull     41
      39: iconst_0
      40: ireturn
      41: aconst_null
      42: astore_3
      43: aload_1
      44: instanceof    #712                // class org/eclipse/ui/internal/themes/ColorDefinition
      47: ifeq          64
      50: aload_0
      51: getfield      #1383               // Field themeRegistry:Lorg/eclipse/ui/internal/themes/IThemeRegistry;
      54: aload_2
      55: invokeinterface #1715,  2         // InterfaceMethod org/eclipse/ui/internal/themes/IThemeRegistry.findColor:(Ljava/lang/String;)Lorg/eclipse/ui/internal/themes/ColorDefinition;
      60: astore_3
      61: goto          82
      64: aload_1
      65: instanceof    #719                // class org/eclipse/ui/internal/themes/FontDefinition
      68: ifeq          82
      71: aload_0
      72: getfield      #1383               // Field themeRegistry:Lorg/eclipse/ui/internal/themes/IThemeRegistry;
      75: aload_2
      76: invokeinterface #1716,  2         // InterfaceMethod org/eclipse/ui/internal/themes/IThemeRegistry.findFont:(Ljava/lang/String;)Lorg/eclipse/ui/internal/themes/FontDefinition;
      81: astore_3
      82: aload_3
      83: ifnull        97
      86: aload_3
      87: invokeinterface #1709,  1         // InterfaceMethod org/eclipse/ui/internal/themes/IEditable.isEditable:()Z
      92: ifeq          97
      95: iconst_1
      96: ireturn
      97: iconst_0
      98: ireturn

  private org.eclipse.swt.widgets.Composite createNoPreviewControl();
    Code:
       0: new           #693                // class org/eclipse/swt/widgets/Composite
       3: dup
       4: aload_0
       5: getfield      #1375               // Field previewComposite:Lorg/eclipse/swt/widgets/Composite;
       8: iconst_0
       9: invokespecial #1509               // Method org/eclipse/swt/widgets/Composite."<init>":(Lorg/eclipse/swt/widgets/Composite;I)V
      12: astore_1
      13: aload_1
      14: new           #687                // class org/eclipse/swt/layout/FillLayout
      17: dup
      18: invokespecial #1484               // Method org/eclipse/swt/layout/FillLayout."<init>":()V
      21: invokevirtual #1511               // Method org/eclipse/swt/widgets/Composite.setLayout:(Lorg/eclipse/swt/widgets/Layout;)V
      24: new           #697                // class org/eclipse/swt/widgets/Label
      27: dup
      28: aload_1
      29: sipush        16384
      32: invokespecial #1526               // Method org/eclipse/swt/widgets/Label."<init>":(Lorg/eclipse/swt/widgets/Composite;I)V
      35: astore_2
      36: aload_2
      37: getstatic     #1354               // Field RESOURCE_BUNDLE:Ljava/util/ResourceBundle;
      40: ldc_w         #620                // String noPreviewAvailable
      43: invokevirtual #1418               // Method java/util/ResourceBundle.getString:(Ljava/lang/String;)Ljava/lang/String;
      46: invokevirtual #1524               // Method org/eclipse/swt/widgets/Label.setText:(Ljava/lang/String;)V
      49: aload_0
      50: aload_2
      51: invokevirtual #1604               // Method myApplyDialogFont:(Lorg/eclipse/swt/widgets/Control;)V
      54: aload_1
      55: areturn

  private void setCurrentFont(org.eclipse.ui.internal.themes.FontDefinition);
    Code:
       0: aload_0
       1: aload_0
       2: getfield      #1380               // Field fontRegistry:Lorg/eclipse/ui/internal/themes/CascadingFontRegistry;
       5: aload_1
       6: invokevirtual #1661               // Method org/eclipse/ui/internal/themes/FontDefinition.getId:()Ljava/lang/String;
       9: invokevirtual #1552               // Method org/eclipse/ui/internal/themes/CascadingFontRegistry.get:(Ljava/lang/String;)Lorg/eclipse/swt/graphics/Font;
      12: putfield      #1363               // Field currentFont:Lorg/eclipse/swt/graphics/Font;
      15: aload_0
      16: getfield      #1363               // Field currentFont:Lorg/eclipse/swt/graphics/Font;
      19: ifnull        32
      22: aload_0
      23: getfield      #1363               // Field currentFont:Lorg/eclipse/swt/graphics/Font;
      26: invokevirtual #1466               // Method org/eclipse/swt/graphics/Font.getFontData:()[Lorg/eclipse/swt/graphics/FontData;
      29: goto          36
      32: iconst_0
      33: anewarray     #681                // class org/eclipse/swt/graphics/FontData
      36: astore_2
      37: new           #641                // class java/lang/StringBuilder
      40: dup
      41: invokespecial #1402               // Method java/lang/StringBuilder."<init>":()V
      44: astore_3
      45: aload_2
      46: dup
      47: astore        7
      49: arraylength
      50: istore        6
      52: iconst_0
      53: istore        5
      55: goto          158
      58: aload         7
      60: iload         5
      62: aaload
      63: astore        4
      65: aload_3
      66: aload         4
      68: invokevirtual #1470               // Method org/eclipse/swt/graphics/FontData.getName:()Ljava/lang/String;
      71: invokevirtual #1407               // Method java/lang/StringBuilder.append:(Ljava/lang/String;)Ljava/lang/StringBuilder;
      74: pop
      75: aload_3
      76: bipush        32
      78: invokevirtual #1405               // Method java/lang/StringBuilder.append:(C)Ljava/lang/StringBuilder;
      81: pop
      82: aload_3
      83: aload         4
      85: invokevirtual #1468               // Method org/eclipse/swt/graphics/FontData.getHeight:()I
      88: invokevirtual #1406               // Method java/lang/StringBuilder.append:(I)Ljava/lang/StringBuilder;
      91: pop
      92: aload         4
      94: invokevirtual #1469               // Method org/eclipse/swt/graphics/FontData.getStyle:()I
      97: istore        8
      99: iload         8
     101: iconst_1
     102: iand
     103: ifeq          127
     106: aload_3
     107: bipush        32
     109: invokevirtual #1405               // Method java/lang/StringBuilder.append:(C)Ljava/lang/StringBuilder;
     112: pop
     113: aload_3
     114: getstatic     #1354               // Field RESOURCE_BUNDLE:Ljava/util/ResourceBundle;
     117: ldc_w         #606                // String boldFont
     120: invokevirtual #1418               // Method java/util/ResourceBundle.getString:(Ljava/lang/String;)Ljava/lang/String;
     123: invokevirtual #1407               // Method java/lang/StringBuilder.append:(Ljava/lang/String;)Ljava/lang/StringBuilder;
     126: pop
     127: iload         8
     129: iconst_2
     130: iand
     131: ifeq          155
     134: aload_3
     135: bipush        32
     137: invokevirtual #1405               // Method java/lang/StringBuilder.append:(C)Ljava/lang/StringBuilder;
     140: pop
     141: aload_3
     142: getstatic     #1354               // Field RESOURCE_BUNDLE:Ljava/util/ResourceBundle;
     145: ldc_w         #619                // String italicFont
     148: invokevirtual #1418               // Method java/util/ResourceBundle.getString:(Ljava/lang/String;)Ljava/lang/String;
     151: invokevirtual #1407               // Method java/lang/StringBuilder.append:(Ljava/lang/String;)Ljava/lang/StringBuilder;
     154: pop
     155: iinc          5, 1
     158: iload         5
     160: iload         6
     162: if_icmplt     58
     165: aload_0
     166: aload_3
     167: invokevirtual #1404               // Method java/lang/StringBuilder.toString:()Ljava/lang/String;
     170: putfield      #1346               // Field fontSampleText:Ljava/lang/String;
     173: aload_0
     174: getfield      #1376               // Field descriptionText:Lorg/eclipse/swt/widgets/Text;
     177: aload_0
     178: aload_1
     179: invokevirtual #1624               // Method fomatDescription:(Lorg/eclipse/ui/internal/themes/ThemeElementDefinition;)Ljava/lang/String;
     182: invokevirtual #1528               // Method org/eclipse/swt/widgets/Text.setText:(Ljava/lang/String;)V
     185: aload_0
     186: getfield      #1371               // Field fontSampler:Lorg/eclipse/swt/widgets/Canvas;
     189: invokevirtual #1495               // Method org/eclipse/swt/widgets/Canvas.redraw:()V
     192: return

  public void setCurrentColor(org.eclipse.ui.internal.themes.ColorDefinition);
    Code:
       0: aload_0
       1: aload_0
       2: getfield      #1379               // Field colorRegistry:Lorg/eclipse/ui/internal/themes/CascadingColorRegistry;
       5: aload_1
       6: invokevirtual #1556               // Method org/eclipse/ui/internal/themes/ColorDefinition.getId:()Ljava/lang/String;
       9: invokevirtual #1547               // Method org/eclipse/ui/internal/themes/CascadingColorRegistry.get:(Ljava/lang/String;)Lorg/eclipse/swt/graphics/Color;
      12: putfield      #1361               // Field currentColor:Lorg/eclipse/swt/graphics/Color;
      15: aload_0
      16: getfield      #1370               // Field colorSampler:Lorg/eclipse/swt/widgets/Canvas;
      19: invokevirtual #1495               // Method org/eclipse/swt/widgets/Canvas.redraw:()V
      22: aload_0
      23: getfield      #1376               // Field descriptionText:Lorg/eclipse/swt/widgets/Text;
      26: aload_0
      27: aload_1
      28: invokevirtual #1624               // Method fomatDescription:(Lorg/eclipse/ui/internal/themes/ThemeElementDefinition;)Ljava/lang/String;
      31: invokevirtual #1528               // Method org/eclipse/swt/widgets/Text.setText:(Ljava/lang/String;)V
      34: return

  private org.eclipse.swt.widgets.Composite createFontPreviewControl();
    Code:
       0: aload_0
       1: new           #691                // class org/eclipse/swt/widgets/Canvas
       4: dup
       5: aload_0
       6: getfield      #1375               // Field previewComposite:Lorg/eclipse/swt/widgets/Composite;
       9: iconst_0
      10: invokespecial #1499               // Method org/eclipse/swt/widgets/Canvas."<init>":(Lorg/eclipse/swt/widgets/Composite;I)V
      13: putfield      #1371               // Field fontSampler:Lorg/eclipse/swt/widgets/Canvas;
      16: new           #689                // class org/eclipse/swt/layout/GridLayout
      19: dup
      20: invokespecial #1488               // Method org/eclipse/swt/layout/GridLayout."<init>":()V
      23: astore_1
      24: aload_1
      25: iconst_0
      26: putfield      #1342               // Field org/eclipse/swt/layout/GridLayout.marginWidth:I
      29: aload_1
      30: iconst_0
      31: putfield      #1340               // Field org/eclipse/swt/layout/GridLayout.marginHeight:I
      34: aload_0
      35: getfield      #1371               // Field fontSampler:Lorg/eclipse/swt/widgets/Canvas;
      38: aload_1
      39: invokevirtual #1500               // Method org/eclipse/swt/widgets/Canvas.setLayout:(Lorg/eclipse/swt/widgets/Layout;)V
      42: aload_0
      43: getfield      #1371               // Field fontSampler:Lorg/eclipse/swt/widgets/Canvas;
      46: new           #688                // class org/eclipse/swt/layout/GridData
      49: dup
      50: sipush        1808
      53: invokespecial #1486               // Method org/eclipse/swt/layout/GridData."<init>":(I)V
      56: invokevirtual #1496               // Method org/eclipse/swt/widgets/Canvas.setLayoutData:(Ljava/lang/Object;)V
      59: aload_0
      60: getfield      #1371               // Field fontSampler:Lorg/eclipse/swt/widgets/Canvas;
      63: aload_0
      64: invokedynamic #1754,  0           // InvokeDynamic #10:paintControl:(Lorg/eclipse/ui/internal/themes/ColorsAndFontsPreferencePage;)Lorg/eclipse/swt/events/PaintListener;
      69: invokevirtual #1497               // Method org/eclipse/swt/widgets/Canvas.addPaintListener:(Lorg/eclipse/swt/events/PaintListener;)V
      72: aload_0
      73: getfield      #1371               // Field fontSampler:Lorg/eclipse/swt/widgets/Canvas;
      76: areturn

  private void paintFontSample(org.eclipse.swt.graphics.GC);
    Code:
       0: aload_0
       1: getfield      #1363               // Field currentFont:Lorg/eclipse/swt/graphics/Font;
       4: ifnull        17
       7: aload_0
       8: getfield      #1363               // Field currentFont:Lorg/eclipse/swt/graphics/Font;
      11: invokevirtual #1465               // Method org/eclipse/swt/graphics/Font.isDisposed:()Z
      14: ifeq          18
      17: return
      18: aload_0
      19: getfield      #1370               // Field colorSampler:Lorg/eclipse/swt/widgets/Canvas;
      22: invokevirtual #1498               // Method org/eclipse/swt/widgets/Canvas.getClientArea:()Lorg/eclipse/swt/graphics/Rectangle;
      25: astore_2
      26: aload_1
      27: invokevirtual #1480               // Method org/eclipse/swt/graphics/GC.getFontMetrics:()Lorg/eclipse/swt/graphics/FontMetrics;
      30: astore_3
      31: aload_3
      32: invokevirtual #1471               // Method org/eclipse/swt/graphics/FontMetrics.getHeight:()I
      35: istore        4
      37: iload         4
      39: iconst_4
      40: imul
      41: istore        5
      43: aload_2
      44: getfield      #1331               // Field org/eclipse/swt/graphics/Rectangle.height:I
      47: iload         5
      49: if_icmple     74
      52: new           #686                // class org/eclipse/swt/graphics/Rectangle
      55: dup
      56: aload_2
      57: getfield      #1333               // Field org/eclipse/swt/graphics/Rectangle.x:I
      60: aload_2
      61: getfield      #1334               // Field org/eclipse/swt/graphics/Rectangle.y:I
      64: aload_2
      65: getfield      #1332               // Field org/eclipse/swt/graphics/Rectangle.width:I
      68: iload         5
      70: invokespecial #1483               // Method org/eclipse/swt/graphics/Rectangle."<init>":(IIII)V
      73: astore_2
      74: aload_1
      75: aload_0
      76: getfield      #1375               // Field previewComposite:Lorg/eclipse/swt/widgets/Composite;
      79: invokevirtual #1510               // Method org/eclipse/swt/widgets/Composite.getDisplay:()Lorg/eclipse/swt/widgets/Display;
      82: bipush        18
      84: invokevirtual #1514               // Method org/eclipse/swt/widgets/Display.getSystemColor:(I)Lorg/eclipse/swt/graphics/Color;
      87: invokevirtual #1478               // Method org/eclipse/swt/graphics/GC.setForeground:(Lorg/eclipse/swt/graphics/Color;)V
      90: aload_1
      91: iconst_0
      92: iconst_0
      93: aload_2
      94: getfield      #1332               // Field org/eclipse/swt/graphics/Rectangle.width:I
      97: iconst_1
      98: isub
      99: aload_2
     100: getfield      #1331               // Field org/eclipse/swt/graphics/Rectangle.height:I
     103: iconst_1
     104: isub
     105: invokevirtual #1473               // Method org/eclipse/swt/graphics/GC.drawRectangle:(IIII)V
     108: aload_1
     109: aload_0
     110: getfield      #1375               // Field previewComposite:Lorg/eclipse/swt/widgets/Composite;
     113: invokevirtual #1510               // Method org/eclipse/swt/widgets/Composite.getDisplay:()Lorg/eclipse/swt/widgets/Display;
     116: iconst_2
     117: invokevirtual #1514               // Method org/eclipse/swt/widgets/Display.getSystemColor:(I)Lorg/eclipse/swt/graphics/Color;
     120: invokevirtual #1478               // Method org/eclipse/swt/graphics/GC.setForeground:(Lorg/eclipse/swt/graphics/Color;)V
     123: aload_1
     124: aload_0
     125: getfield      #1363               // Field currentFont:Lorg/eclipse/swt/graphics/Font;
     128: invokevirtual #1479               // Method org/eclipse/swt/graphics/GC.setFont:(Lorg/eclipse/swt/graphics/Font;)V
     131: aload_1
     132: invokevirtual #1480               // Method org/eclipse/swt/graphics/GC.getFontMetrics:()Lorg/eclipse/swt/graphics/FontMetrics;
     135: astore        6
     137: aload         6
     139: invokevirtual #1471               // Method org/eclipse/swt/graphics/FontMetrics.getHeight:()I
     142: istore        7
     144: aload_2
     145: getfield      #1334               // Field org/eclipse/swt/graphics/Rectangle.y:I
     148: iconst_5
     149: iadd
     150: istore        8
     152: aload_1
     153: iconst_1
     154: iconst_1
     155: aload_2
     156: getfield      #1332               // Field org/eclipse/swt/graphics/Rectangle.width:I
     159: iconst_2
     160: isub
     161: aload_2
     162: getfield      #1331               // Field org/eclipse/swt/graphics/Rectangle.height:I
     165: iconst_2
     166: isub
     167: invokevirtual #1475               // Method org/eclipse/swt/graphics/GC.setClipping:(IIII)V
     170: aload_1
     171: aload_0
     172: getfield      #1346               // Field fontSampleText:Ljava/lang/String;
     175: aload_2
     176: getfield      #1333               // Field org/eclipse/swt/graphics/Rectangle.x:I
     179: iconst_5
     180: iadd
     181: iload         8
     183: invokevirtual #1476               // Method org/eclipse/swt/graphics/GC.drawText:(Ljava/lang/String;II)V
     186: aload_1
     187: getstatic     #1354               // Field RESOURCE_BUNDLE:Ljava/util/ResourceBundle;
     190: ldc_w         #617                // String fontTextSample
     193: invokevirtual #1418               // Method java/util/ResourceBundle.getString:(Ljava/lang/String;)Ljava/lang/String;
     196: aload_2
     197: getfield      #1333               // Field org/eclipse/swt/graphics/Rectangle.x:I
     200: iconst_5
     201: iadd
     202: iload         8
     204: iload         7
     206: iadd
     207: invokevirtual #1476               // Method org/eclipse/swt/graphics/GC.drawText:(Ljava/lang/String;II)V
     210: return

  private org.eclipse.swt.widgets.Composite createColorPreviewControl();
    Code:
       0: aload_0
       1: new           #691                // class org/eclipse/swt/widgets/Canvas
       4: dup
       5: aload_0
       6: getfield      #1375               // Field previewComposite:Lorg/eclipse/swt/widgets/Composite;
       9: iconst_0
      10: invokespecial #1499               // Method org/eclipse/swt/widgets/Canvas."<init>":(Lorg/eclipse/swt/widgets/Composite;I)V
      13: putfield      #1370               // Field colorSampler:Lorg/eclipse/swt/widgets/Canvas;
      16: new           #689                // class org/eclipse/swt/layout/GridLayout
      19: dup
      20: invokespecial #1488               // Method org/eclipse/swt/layout/GridLayout."<init>":()V
      23: astore_1
      24: aload_1
      25: iconst_0
      26: putfield      #1342               // Field org/eclipse/swt/layout/GridLayout.marginWidth:I
      29: aload_1
      30: iconst_0
      31: putfield      #1340               // Field org/eclipse/swt/layout/GridLayout.marginHeight:I
      34: aload_0
      35: getfield      #1370               // Field colorSampler:Lorg/eclipse/swt/widgets/Canvas;
      38: aload_1
      39: invokevirtual #1500               // Method org/eclipse/swt/widgets/Canvas.setLayout:(Lorg/eclipse/swt/widgets/Layout;)V
      42: aload_0
      43: getfield      #1370               // Field colorSampler:Lorg/eclipse/swt/widgets/Canvas;
      46: new           #688                // class org/eclipse/swt/layout/GridData
      49: dup
      50: sipush        1808
      53: invokespecial #1486               // Method org/eclipse/swt/layout/GridData."<init>":(I)V
      56: invokevirtual #1496               // Method org/eclipse/swt/widgets/Canvas.setLayoutData:(Ljava/lang/Object;)V
      59: aload_0
      60: getfield      #1370               // Field colorSampler:Lorg/eclipse/swt/widgets/Canvas;
      63: aload_0
      64: invokedynamic #1755,  0           // InvokeDynamic #11:paintControl:(Lorg/eclipse/ui/internal/themes/ColorsAndFontsPreferencePage;)Lorg/eclipse/swt/events/PaintListener;
      69: invokevirtual #1497               // Method org/eclipse/swt/widgets/Canvas.addPaintListener:(Lorg/eclipse/swt/events/PaintListener;)V
      72: aload_0
      73: getfield      #1370               // Field colorSampler:Lorg/eclipse/swt/widgets/Canvas;
      76: areturn

  private void paintColorSample(org.eclipse.swt.graphics.GC);
    Code:
       0: aload_0
       1: getfield      #1361               // Field currentColor:Lorg/eclipse/swt/graphics/Color;
       4: ifnull        17
       7: aload_0
       8: getfield      #1361               // Field currentColor:Lorg/eclipse/swt/graphics/Color;
      11: invokevirtual #1462               // Method org/eclipse/swt/graphics/Color.isDisposed:()Z
      14: ifeq          18
      17: return
      18: aload_1
      19: aload_0
      20: getfield      #1375               // Field previewComposite:Lorg/eclipse/swt/widgets/Composite;
      23: invokevirtual #1510               // Method org/eclipse/swt/widgets/Composite.getDisplay:()Lorg/eclipse/swt/widgets/Display;
      26: invokevirtual #1515               // Method org/eclipse/swt/widgets/Display.getSystemFont:()Lorg/eclipse/swt/graphics/Font;
      29: invokevirtual #1479               // Method org/eclipse/swt/graphics/GC.setFont:(Lorg/eclipse/swt/graphics/Font;)V
      32: aload_1
      33: invokevirtual #1480               // Method org/eclipse/swt/graphics/GC.getFontMetrics:()Lorg/eclipse/swt/graphics/FontMetrics;
      36: astore_2
      37: aload_2
      38: invokevirtual #1471               // Method org/eclipse/swt/graphics/FontMetrics.getHeight:()I
      41: istore_3
      42: aload_0
      43: getfield      #1370               // Field colorSampler:Lorg/eclipse/swt/widgets/Canvas;
      46: invokevirtual #1498               // Method org/eclipse/swt/widgets/Canvas.getClientArea:()Lorg/eclipse/swt/graphics/Rectangle;
      49: astore        4
      51: iload_3
      52: iconst_4
      53: imul
      54: istore        5
      56: aload         4
      58: getfield      #1331               // Field org/eclipse/swt/graphics/Rectangle.height:I
      61: iload         5
      63: if_icmple     92
      66: new           #686                // class org/eclipse/swt/graphics/Rectangle
      69: dup
      70: aload         4
      72: getfield      #1333               // Field org/eclipse/swt/graphics/Rectangle.x:I
      75: aload         4
      77: getfield      #1334               // Field org/eclipse/swt/graphics/Rectangle.y:I
      80: aload         4
      82: getfield      #1332               // Field org/eclipse/swt/graphics/Rectangle.width:I
      85: iload         5
      87: invokespecial #1483               // Method org/eclipse/swt/graphics/Rectangle."<init>":(IIII)V
      90: astore        4
      92: getstatic     #1354               // Field RESOURCE_BUNDLE:Ljava/util/ResourceBundle;
      95: ldc_w         #615                // String fontColorSample
      98: invokevirtual #1418               // Method java/util/ResourceBundle.getString:(Ljava/lang/String;)Ljava/lang/String;
     101: astore        6
     103: getstatic     #1354               // Field RESOURCE_BUNDLE:Ljava/util/ResourceBundle;
     106: ldc_w         #616                // String fontColorString
     109: invokevirtual #1418               // Method java/util/ResourceBundle.getString:(Ljava/lang/String;)Ljava/lang/String;
     112: astore        7
     114: aload_0
     115: getfield      #1361               // Field currentColor:Lorg/eclipse/swt/graphics/Color;
     118: invokevirtual #1463               // Method org/eclipse/swt/graphics/Color.getRGB:()Lorg/eclipse/swt/graphics/RGB;
     121: astore        8
     123: aload         7
     125: iconst_3
     126: anewarray     #638                // class java/lang/Object
     129: dup
     130: iconst_0
     131: aload         8
     133: getfield      #1330               // Field org/eclipse/swt/graphics/RGB.red:I
     136: invokestatic  #1391               // Method java/lang/Integer.valueOf:(I)Ljava/lang/Integer;
     139: aastore
     140: dup
     141: iconst_1
     142: aload         8
     144: getfield      #1329               // Field org/eclipse/swt/graphics/RGB.green:I
     147: invokestatic  #1391               // Method java/lang/Integer.valueOf:(I)Ljava/lang/Integer;
     150: aastore
     151: dup
     152: iconst_2
     153: aload         8
     155: getfield      #1328               // Field org/eclipse/swt/graphics/RGB.blue:I
     158: invokestatic  #1391               // Method java/lang/Integer.valueOf:(I)Ljava/lang/Integer;
     161: aastore
     162: invokestatic  #1410               // Method java/text/MessageFormat.format:(Ljava/lang/String;[Ljava/lang/Object;)Ljava/lang/String;
     165: astore        9
     167: aload         4
     169: getfield      #1332               // Field org/eclipse/swt/graphics/Rectangle.width:I
     172: iconst_2
     173: isub
     174: iconst_3
     175: idiv
     176: istore        10
     178: aload         4
     180: getfield      #1331               // Field org/eclipse/swt/graphics/Rectangle.height:I
     183: iconst_2
     184: idiv
     185: istore        11
     187: iload         11
     189: iload_3
     190: isub
     191: iconst_2
     192: idiv
     193: istore        12
     195: iload         12
     197: iconst_1
     198: if_icmpge     204
     201: iconst_1
     202: istore        12
     204: iload         12
     206: aload         4
     208: getfield      #1334               // Field org/eclipse/swt/graphics/Rectangle.y:I
     211: iadd
     212: istore        12
     214: iload         11
     216: iload         12
     218: iadd
     219: istore        13
     221: iload         13
     223: aload         4
     225: getfield      #1331               // Field org/eclipse/swt/graphics/Rectangle.height:I
     228: iconst_2
     229: isub
     230: if_icmple     242
     233: aload         4
     235: getfield      #1331               // Field org/eclipse/swt/graphics/Rectangle.height:I
     238: iconst_2
     239: isub
     240: istore        13
     242: iload         13
     244: aload         4
     246: getfield      #1334               // Field org/eclipse/swt/graphics/Rectangle.y:I
     249: iadd
     250: istore        13
     252: aload_1
     253: aload         6
     255: invokevirtual #1481               // Method org/eclipse/swt/graphics/GC.stringExtent:(Ljava/lang/String;)Lorg/eclipse/swt/graphics/Point;
     258: getfield      #1327               // Field org/eclipse/swt/graphics/Point.x:I
     261: istore        14
     263: iload         10
     265: iload         14
     267: isub
     268: iconst_1
     269: isub
     270: iconst_2
     271: idiv
     272: istore        15
     274: iload         15
     276: iconst_1
     277: if_icmpge     283
     280: iconst_1
     281: istore        15
     283: iload         15
     285: aload         4
     287: getfield      #1333               // Field org/eclipse/swt/graphics/Rectangle.x:I
     290: iadd
     291: istore        15
     293: aload_1
     294: aload         9
     296: invokevirtual #1481               // Method org/eclipse/swt/graphics/GC.stringExtent:(Ljava/lang/String;)Lorg/eclipse/swt/graphics/Point;
     299: getfield      #1327               // Field org/eclipse/swt/graphics/Point.x:I
     302: istore        16
     304: iload         10
     306: iload         16
     308: isub
     309: iconst_1
     310: isub
     311: iconst_2
     312: idiv
     313: istore        17
     315: iload         17
     317: iconst_1
     318: if_icmpge     324
     321: iconst_1
     322: istore        17
     324: iload         17
     326: aload         4
     328: getfield      #1333               // Field org/eclipse/swt/graphics/Rectangle.x:I
     331: iadd
     332: istore        17
     334: aload_1
     335: aload_0
     336: getfield      #1361               // Field currentColor:Lorg/eclipse/swt/graphics/Color;
     339: invokevirtual #1478               // Method org/eclipse/swt/graphics/GC.setForeground:(Lorg/eclipse/swt/graphics/Color;)V
     342: aload_1
     343: aload         6
     345: iload         15
     347: iload         12
     349: invokevirtual #1476               // Method org/eclipse/swt/graphics/GC.drawText:(Ljava/lang/String;II)V
     352: aload_1
     353: aload         9
     355: iload         17
     357: iload         13
     359: invokevirtual #1476               // Method org/eclipse/swt/graphics/GC.drawText:(Ljava/lang/String;II)V
     362: aload_1
     363: aload_0
     364: getfield      #1375               // Field previewComposite:Lorg/eclipse/swt/widgets/Composite;
     367: invokevirtual #1510               // Method org/eclipse/swt/widgets/Composite.getDisplay:()Lorg/eclipse/swt/widgets/Display;
     370: bipush        25
     372: invokevirtual #1514               // Method org/eclipse/swt/widgets/Display.getSystemColor:(I)Lorg/eclipse/swt/graphics/Color;
     375: invokevirtual #1477               // Method org/eclipse/swt/graphics/GC.setBackground:(Lorg/eclipse/swt/graphics/Color;)V
     378: aload         4
     380: getfield      #1332               // Field org/eclipse/swt/graphics/Rectangle.width:I
     383: iconst_2
     384: isub
     385: iload         10
     387: iconst_2
     388: imul
     389: isub
     390: istore        18
     392: aload_1
     393: iload         10
     395: iconst_2
     396: imul
     397: iconst_1
     398: iload         18
     400: aload         4
     402: getfield      #1331               // Field org/eclipse/swt/graphics/Rectangle.height:I
     405: iconst_2
     406: isub
     407: invokevirtual #1474               // Method org/eclipse/swt/graphics/GC.fillRectangle:(IIII)V
     410: aload_1
     411: aload_0
     412: getfield      #1361               // Field currentColor:Lorg/eclipse/swt/graphics/Color;
     415: invokevirtual #1478               // Method org/eclipse/swt/graphics/GC.setForeground:(Lorg/eclipse/swt/graphics/Color;)V
     418: aload_1
     419: aload         6
     421: iload         10
     423: iconst_2
     424: imul
     425: iload         15
     427: iadd
     428: iload         12
     430: invokevirtual #1476               // Method org/eclipse/swt/graphics/GC.drawText:(Ljava/lang/String;II)V
     433: aload_1
     434: aload         9
     436: iload         10
     438: iconst_2
     439: imul
     440: iload         17
     442: iadd
     443: iload         13
     445: invokevirtual #1476               // Method org/eclipse/swt/graphics/GC.drawText:(Ljava/lang/String;II)V
     448: aload_1
     449: aload_0
     450: getfield      #1361               // Field currentColor:Lorg/eclipse/swt/graphics/Color;
     453: invokevirtual #1477               // Method org/eclipse/swt/graphics/GC.setBackground:(Lorg/eclipse/swt/graphics/Color;)V
     456: aload_1
     457: iload         10
     459: iconst_1
     460: iload         10
     462: aload         4
     464: getfield      #1331               // Field org/eclipse/swt/graphics/Rectangle.height:I
     467: iconst_2
     468: isub
     469: invokevirtual #1474               // Method org/eclipse/swt/graphics/GC.fillRectangle:(IIII)V
     472: aload_1
     473: aload_0
     474: getfield      #1375               // Field previewComposite:Lorg/eclipse/swt/widgets/Composite;
     477: invokevirtual #1510               // Method org/eclipse/swt/widgets/Composite.getDisplay:()Lorg/eclipse/swt/widgets/Display;
     480: iconst_2
     481: invokevirtual #1514               // Method org/eclipse/swt/widgets/Display.getSystemColor:(I)Lorg/eclipse/swt/graphics/Color;
     484: invokevirtual #1478               // Method org/eclipse/swt/graphics/GC.setForeground:(Lorg/eclipse/swt/graphics/Color;)V
     487: aload_1
     488: aload         6
     490: iload         10
     492: iload         15
     494: iadd
     495: iload         12
     497: invokevirtual #1476               // Method org/eclipse/swt/graphics/GC.drawText:(Ljava/lang/String;II)V
     500: aload_1
     501: aload_0
     502: getfield      #1375               // Field previewComposite:Lorg/eclipse/swt/widgets/Composite;
     505: invokevirtual #1510               // Method org/eclipse/swt/widgets/Composite.getDisplay:()Lorg/eclipse/swt/widgets/Display;
     508: iconst_1
     509: invokevirtual #1514               // Method org/eclipse/swt/widgets/Display.getSystemColor:(I)Lorg/eclipse/swt/graphics/Color;
     512: invokevirtual #1478               // Method org/eclipse/swt/graphics/GC.setForeground:(Lorg/eclipse/swt/graphics/Color;)V
     515: aload_1
     516: aload         9
     518: iload         10
     520: iload         17
     522: iadd
     523: iload         13
     525: invokevirtual #1476               // Method org/eclipse/swt/graphics/GC.drawText:(Ljava/lang/String;II)V
     528: aload_1
     529: aload_0
     530: getfield      #1375               // Field previewComposite:Lorg/eclipse/swt/widgets/Composite;
     533: invokevirtual #1510               // Method org/eclipse/swt/widgets/Composite.getDisplay:()Lorg/eclipse/swt/widgets/Display;
     536: bipush        18
     538: invokevirtual #1514               // Method org/eclipse/swt/widgets/Display.getSystemColor:(I)Lorg/eclipse/swt/graphics/Color;
     541: invokevirtual #1478               // Method org/eclipse/swt/graphics/GC.setForeground:(Lorg/eclipse/swt/graphics/Color;)V
     544: aload_1
     545: iload         10
     547: iload         11
     549: iload         10
     551: iconst_2
     552: imul
     553: iconst_1
     554: isub
     555: iload         11
     557: invokevirtual #1472               // Method org/eclipse/swt/graphics/GC.drawLine:(IIII)V
     560: aload_1
     561: aload_0
     562: getfield      #1375               // Field previewComposite:Lorg/eclipse/swt/widgets/Composite;
     565: invokevirtual #1510               // Method org/eclipse/swt/widgets/Composite.getDisplay:()Lorg/eclipse/swt/widgets/Display;
     568: bipush        18
     570: invokevirtual #1514               // Method org/eclipse/swt/widgets/Display.getSystemColor:(I)Lorg/eclipse/swt/graphics/Color;
     573: invokevirtual #1478               // Method org/eclipse/swt/graphics/GC.setForeground:(Lorg/eclipse/swt/graphics/Color;)V
     576: aload_1
     577: iconst_0
     578: iconst_0
     579: aload         4
     581: getfield      #1332               // Field org/eclipse/swt/graphics/Rectangle.width:I
     584: iconst_1
     585: isub
     586: aload         4
     588: getfield      #1331               // Field org/eclipse/swt/graphics/Rectangle.height:I
     591: iconst_1
     592: isub
     593: invokevirtual #1473               // Method org/eclipse/swt/graphics/GC.drawRectangle:(IIII)V
     596: return

  private void createDescriptionControl(org.eclipse.swt.widgets.Composite);
    Code:
       0: new           #693                // class org/eclipse/swt/widgets/Composite
       3: dup
       4: aload_1
       5: iconst_0
       6: invokespecial #1509               // Method org/eclipse/swt/widgets/Composite."<init>":(Lorg/eclipse/swt/widgets/Composite;I)V
       9: astore_2
      10: new           #689                // class org/eclipse/swt/layout/GridLayout
      13: dup
      14: invokespecial #1488               // Method org/eclipse/swt/layout/GridLayout."<init>":()V
      17: astore_3
      18: aload_3
      19: iconst_0
      20: putfield      #1342               // Field org/eclipse/swt/layout/GridLayout.marginWidth:I
      23: aload_3
      24: iconst_0
      25: putfield      #1340               // Field org/eclipse/swt/layout/GridLayout.marginHeight:I
      28: aload_2
      29: aload_3
      30: invokevirtual #1511               // Method org/eclipse/swt/widgets/Composite.setLayout:(Lorg/eclipse/swt/widgets/Layout;)V
      33: new           #688                // class org/eclipse/swt/layout/GridData
      36: dup
      37: sipush        768
      40: invokespecial #1486               // Method org/eclipse/swt/layout/GridData."<init>":(I)V
      43: astore        4
      45: aload         4
      47: iconst_2
      48: putfield      #1337               // Field org/eclipse/swt/layout/GridData.horizontalSpan:I
      51: aload_2
      52: aload         4
      54: invokevirtual #1505               // Method org/eclipse/swt/widgets/Composite.setLayoutData:(Ljava/lang/Object;)V
      57: new           #697                // class org/eclipse/swt/widgets/Label
      60: dup
      61: aload_2
      62: sipush        16384
      65: invokespecial #1526               // Method org/eclipse/swt/widgets/Label."<init>":(Lorg/eclipse/swt/widgets/Composite;I)V
      68: astore        5
      70: aload         5
      72: getstatic     #1354               // Field RESOURCE_BUNDLE:Ljava/util/ResourceBundle;
      75: ldc_w         #609                // String description
      78: invokevirtual #1418               // Method java/util/ResourceBundle.getString:(Ljava/lang/String;)Ljava/lang/String;
      81: invokevirtual #1524               // Method org/eclipse/swt/widgets/Label.setText:(Ljava/lang/String;)V
      84: aload_0
      85: aload         5
      87: invokevirtual #1604               // Method myApplyDialogFont:(Lorg/eclipse/swt/widgets/Control;)V
      90: aload_0
      91: new           #698                // class org/eclipse/swt/widgets/Text
      94: dup
      95: aload_2
      96: sipush        2120
      99: invokespecial #1529               // Method org/eclipse/swt/widgets/Text."<init>":(Lorg/eclipse/swt/widgets/Composite;I)V
     102: putfield      #1376               // Field descriptionText:Lorg/eclipse/swt/widgets/Text;
     105: new           #688                // class org/eclipse/swt/layout/GridData
     108: dup
     109: sipush        1808
     112: invokespecial #1486               // Method org/eclipse/swt/layout/GridData."<init>":(I)V
     115: astore        4
     117: aload         4
     119: aload_0
     120: iconst_3
     121: invokevirtual #1574               // Method convertHeightInCharsToPixels:(I)I
     124: putfield      #1335               // Field org/eclipse/swt/layout/GridData.heightHint:I
     127: aload         4
     129: aload_0
     130: bipush        30
     132: invokevirtual #1576               // Method convertWidthInCharsToPixels:(I)I
     135: putfield      #1339               // Field org/eclipse/swt/layout/GridData.widthHint:I
     138: aload_0
     139: getfield      #1376               // Field descriptionText:Lorg/eclipse/swt/widgets/Text;
     142: aload         4
     144: invokevirtual #1527               // Method org/eclipse/swt/widgets/Text.setLayoutData:(Ljava/lang/Object;)V
     147: aload_0
     148: aload_0
     149: getfield      #1376               // Field descriptionText:Lorg/eclipse/swt/widgets/Text;
     152: invokevirtual #1604               // Method myApplyDialogFont:(Lorg/eclipse/swt/widgets/Control;)V
     155: return

  private void publishThemeRegistryModifiedEvent();
    Code:
       0: aload_0
       1: getfield      #1356               // Field eventBroker:Lorg/eclipse/e4/core/services/events/IEventBroker;
       4: ifnull        21
       7: aload_0
       8: getfield      #1356               // Field eventBroker:Lorg/eclipse/e4/core/services/events/IEventBroker;
      11: ldc_w         #624                // String org/eclipse/ui/internal/themes/WorkbenchThemeManager/themeRegistryModified
      14: aconst_null
      15: invokeinterface #1697,  3         // InterfaceMethod org/eclipse/e4/core/services/events/IEventBroker.send:(Ljava/lang/String;Ljava/lang/Object;)Z
      20: pop
      21: return

  private void refreshAllLabels();
    Code:
       0: aload_0
       1: getfield      #1377               // Field tree:Lorg/eclipse/ui/dialogs/FilteredTree;
       4: invokevirtual #1534               // Method org/eclipse/ui/dialogs/FilteredTree.getViewer:()Lorg/eclipse/jface/viewers/TreeViewer;
       7: invokevirtual #1437               // Method org/eclipse/jface/viewers/TreeViewer.refresh:()V
      10: return

  private boolean isAvailableInCurrentTheme(org.eclipse.ui.internal.themes.ThemeElementDefinition);
    Code:
       0: aload_1
       1: instanceof    #712                // class org/eclipse/ui/internal/themes/ColorDefinition
       4: ifeq          55
       7: aload_1
       8: checkcast     #712                // class org/eclipse/ui/internal/themes/ColorDefinition
      11: astore_2
      12: aload_2
      13: invokevirtual #1557               // Method org/eclipse/ui/internal/themes/ColorDefinition.getValue:()Lorg/eclipse/swt/graphics/RGB;
      16: astore_3
      17: aload_3
      18: ifnull        28
      21: aload_3
      22: getstatic     #1387               // Field org/eclipse/ui/internal/themes/WorkbenchThemeManager.EMPTY_COLOR_VALUE:Lorg/eclipse/swt/graphics/RGB;
      25: if_acmpne     37
      28: aload_2
      29: invokevirtual #1555               // Method org/eclipse/ui/internal/themes/ColorDefinition.getDefaultsTo:()Ljava/lang/String;
      32: ifnonnull     37
      35: iconst_0
      36: ireturn
      37: aload_0
      38: getfield      #1379               // Field colorRegistry:Lorg/eclipse/ui/internal/themes/CascadingColorRegistry;
      41: aload_1
      42: invokevirtual #1671               // Method org/eclipse/ui/internal/themes/ThemeElementDefinition.getId:()Ljava/lang/String;
      45: invokevirtual #1547               // Method org/eclipse/ui/internal/themes/CascadingColorRegistry.get:(Ljava/lang/String;)Lorg/eclipse/swt/graphics/Color;
      48: ifnull        53
      51: iconst_1
      52: ireturn
      53: iconst_0
      54: ireturn
      55: iconst_1
      56: ireturn

  private java.lang.String fomatDescription(org.eclipse.ui.internal.themes.ThemeElementDefinition);
    Code:
       0: aload_1
       1: invokevirtual #1670               // Method org/eclipse/ui/internal/themes/ThemeElementDefinition.getDescription:()Ljava/lang/String;
       4: ifnull        14
       7: aload_1
       8: invokevirtual #1670               // Method org/eclipse/ui/internal/themes/ThemeElementDefinition.getDescription:()Ljava/lang/String;
      11: goto          16
      14: ldc           #1                  // String
      16: astore_2
      17: aload_0
      18: aload_1
      19: invokevirtual #1619               // Method isAvailableInCurrentTheme:(Lorg/eclipse/ui/internal/themes/ThemeElementDefinition;)Z
      22: ifeq          27
      25: aload_2
      26: areturn
      27: getstatic     #1354               // Field RESOURCE_BUNDLE:Ljava/util/ResourceBundle;
      30: ldc_w         #608                // String definitionNotAvailInTheme
      33: invokevirtual #1418               // Method java/util/ResourceBundle.getString:(Ljava/lang/String;)Ljava/lang/String;
      36: iconst_1
      37: anewarray     #638                // class java/lang/Object
      40: dup
      41: iconst_0
      42: aload_2
      43: aastore
      44: invokestatic  #1410               // Method java/text/MessageFormat.format:(Ljava/lang/String;[Ljava/lang/Object;)Ljava/lang/String;
      47: invokevirtual #1397               // Method java/lang/String.trim:()Ljava/lang/String;
      50: areturn

  private void updateDefinitionState(org.eclipse.ui.internal.themes.ThemeElementDefinition, boolean);
    Code:
       0: iload_2
       1: ifeq          12
       4: aload_1
       5: iconst_4
       6: invokevirtual #1669               // Method org/eclipse/ui/internal/themes/ThemeElementDefinition.removeState:(I)V
       9: goto          17
      12: aload_1
      13: iconst_4
      14: invokevirtual #1668               // Method org/eclipse/ui/internal/themes/ThemeElementDefinition.appendState:(I)V
      17: return

  private void refreshElement(org.eclipse.ui.internal.themes.ThemeElementDefinition);
    Code:
       0: aload_0
       1: getfield      #1377               // Field tree:Lorg/eclipse/ui/dialogs/FilteredTree;
       4: invokevirtual #1534               // Method org/eclipse/ui/dialogs/FilteredTree.getViewer:()Lorg/eclipse/jface/viewers/TreeViewer;
       7: aload_1
       8: invokevirtual #1440               // Method org/eclipse/jface/viewers/TreeViewer.refresh:(Ljava/lang/Object;)V
      11: aload_0
      12: aload_0
      13: getfield      #1377               // Field tree:Lorg/eclipse/ui/dialogs/FilteredTree;
      16: invokevirtual #1534               // Method org/eclipse/ui/dialogs/FilteredTree.getViewer:()Lorg/eclipse/jface/viewers/TreeViewer;
      19: invokevirtual #1451               // Method org/eclipse/jface/viewers/TreeViewer.getSelection:()Lorg/eclipse/jface/viewers/ISelection;
      22: invokevirtual #1582               // Method updateTreeSelection:(Lorg/eclipse/jface/viewers/ISelection;)V
      25: aload_1
      26: instanceof    #712                // class org/eclipse/ui/internal/themes/ColorDefinition
      29: ifeq          42
      32: aload_1
      33: checkcast     #712                // class org/eclipse/ui/internal/themes/ColorDefinition
      36: invokevirtual #1557               // Method org/eclipse/ui/internal/themes/ColorDefinition.getValue:()Lorg/eclipse/swt/graphics/RGB;
      39: goto          49
      42: aload_1
      43: checkcast     #719                // class org/eclipse/ui/internal/themes/FontDefinition
      46: invokevirtual #1662               // Method org/eclipse/ui/internal/themes/FontDefinition.getValue:()[Lorg/eclipse/swt/graphics/FontData;
      49: astore_2
      50: aload_0
      51: invokevirtual #1612               // Method getCascadingTheme:()Lorg/eclipse/ui/internal/themes/ColorsAndFontsPreferencePage$CascadingThemeExt;
      54: new           #666                // class org/eclipse/jface/util/PropertyChangeEvent
      57: dup
      58: aload_0
      59: aload_1
      60: invokevirtual #1671               // Method org/eclipse/ui/internal/themes/ThemeElementDefinition.getId:()Ljava/lang/String;
      63: aconst_null
      64: aload_2
      65: invokespecial #1432               // Method org/eclipse/jface/util/PropertyChangeEvent."<init>":(Ljava/lang/Object;Ljava/lang/String;Ljava/lang/Object;Ljava/lang/Object;)V
      68: invokevirtual #1651               // Method org/eclipse/ui/internal/themes/ColorsAndFontsPreferencePage$CascadingThemeExt.fire:(Lorg/eclipse/jface/util/PropertyChangeEvent;)V
      71: return

  private void lambda$0(org.eclipse.swt.events.DisposeEvent);
    Code:
       0: aload_0
       1: getfield      #1362               // Field appliedDialogFont:Lorg/eclipse/swt/graphics/Font;
       4: ifnull        14
       7: aload_0
       8: getfield      #1362               // Field appliedDialogFont:Lorg/eclipse/swt/graphics/Font;
      11: invokevirtual #1464               // Method org/eclipse/swt/graphics/Font.dispose:()V
      14: return

  private void lambda$1(org.eclipse.jface.viewers.DoubleClickEvent);
    Code:
       0: aload_1
       1: invokevirtual #1433               // Method org/eclipse/jface/viewers/DoubleClickEvent.getSelection:()Lorg/eclipse/jface/viewers/ISelection;
       4: checkcast     #669                // class org/eclipse/jface/viewers/IStructuredSelection
       7: astore_2
       8: aload_2
       9: invokeinterface #1703,  1         // InterfaceMethod org/eclipse/jface/viewers/IStructuredSelection.getFirstElement:()Ljava/lang/Object;
      14: astore_3
      15: aload_0
      16: getfield      #1377               // Field tree:Lorg/eclipse/ui/dialogs/FilteredTree;
      19: invokevirtual #1534               // Method org/eclipse/ui/dialogs/FilteredTree.getViewer:()Lorg/eclipse/jface/viewers/TreeViewer;
      22: aload_3
      23: invokevirtual #1444               // Method org/eclipse/jface/viewers/TreeViewer.isExpandable:(Ljava/lang/Object;)Z
      26: ifeq          59
      29: aload_0
      30: getfield      #1377               // Field tree:Lorg/eclipse/ui/dialogs/FilteredTree;
      33: invokevirtual #1534               // Method org/eclipse/ui/dialogs/FilteredTree.getViewer:()Lorg/eclipse/jface/viewers/TreeViewer;
      36: aload_3
      37: aload_0
      38: getfield      #1377               // Field tree:Lorg/eclipse/ui/dialogs/FilteredTree;
      41: invokevirtual #1534               // Method org/eclipse/ui/dialogs/FilteredTree.getViewer:()Lorg/eclipse/jface/viewers/TreeViewer;
      44: aload_3
      45: invokevirtual #1443               // Method org/eclipse/jface/viewers/TreeViewer.getExpandedState:(Ljava/lang/Object;)Z
      48: ifeq          55
      51: iconst_0
      52: goto          56
      55: iconst_1
      56: invokevirtual #1446               // Method org/eclipse/jface/viewers/TreeViewer.setExpandedState:(Ljava/lang/Object;Z)V
      59: aload_3
      60: instanceof    #726                // class org/eclipse/ui/internal/themes/ThemeElementDefinition
      63: ifeq          124
      66: aload_3
      67: checkcast     #726                // class org/eclipse/ui/internal/themes/ThemeElementDefinition
      70: astore        4
      72: aload_3
      73: instanceof    #719                // class org/eclipse/ui/internal/themes/FontDefinition
      76: ifeq          93
      79: aload_0
      80: aload_0
      81: getfield      #1377               // Field tree:Lorg/eclipse/ui/dialogs/FilteredTree;
      84: invokevirtual #1535               // Method org/eclipse/ui/dialogs/FilteredTree.getDisplay:()Lorg/eclipse/swt/widgets/Display;
      87: invokevirtual #1606               // Method editFont:(Lorg/eclipse/swt/widgets/Display;)V
      90: goto          120
      93: aload_3
      94: instanceof    #712                // class org/eclipse/ui/internal/themes/ColorDefinition
      97: ifeq          120
     100: aload_0
     101: aload         4
     103: invokevirtual #1619               // Method isAvailableInCurrentTheme:(Lorg/eclipse/ui/internal/themes/ThemeElementDefinition;)Z
     106: ifeq          120
     109: aload_0
     110: aload_0
     111: getfield      #1377               // Field tree:Lorg/eclipse/ui/dialogs/FilteredTree;
     114: invokevirtual #1535               // Method org/eclipse/ui/dialogs/FilteredTree.getDisplay:()Lorg/eclipse/swt/widgets/Display;
     117: invokevirtual #1605               // Method editColor:(Lorg/eclipse/swt/widgets/Display;)V
     120: aload_0
     121: invokevirtual #1569               // Method updateControls:()V
     124: return

  private void lambda$2(org.eclipse.jface.viewers.SelectionChangedEvent);
    Code:
       0: aload_0
       1: aload_1
       2: invokevirtual #1434               // Method org/eclipse/jface/viewers/SelectionChangedEvent.getSelection:()Lorg/eclipse/jface/viewers/ISelection;
       5: invokevirtual #1582               // Method updateTreeSelection:(Lorg/eclipse/jface/viewers/ISelection;)V
       8: return

  private void lambda$3(org.eclipse.swt.events.SelectionEvent);
    Code:
       0: aload_1
       1: getfield      #1326               // Field org/eclipse/swt/events/SelectionEvent.display:Lorg/eclipse/swt/widgets/Display;
       4: astore_2
       5: aload_0
       6: invokevirtual #1571               // Method isFontSelected:()Z
       9: ifeq          20
      12: aload_0
      13: aload_2
      14: invokevirtual #1606               // Method editFont:(Lorg/eclipse/swt/widgets/Display;)V
      17: goto          32
      20: aload_0
      21: invokevirtual #1570               // Method isColorSelected:()Z
      24: ifeq          32
      27: aload_0
      28: aload_2
      29: invokevirtual #1605               // Method editColor:(Lorg/eclipse/swt/widgets/Display;)V
      32: aload_0
      33: invokevirtual #1569               // Method updateControls:()V
      36: return

  private void lambda$4(org.eclipse.swt.events.SelectionEvent);
    Code:
       0: aload_0
       1: invokevirtual #1571               // Method isFontSelected:()Z
       4: ifeq          20
       7: aload_0
       8: aload_0
       9: invokevirtual #1613               // Method getSelectedFontDefinition:()Lorg/eclipse/ui/internal/themes/FontDefinition;
      12: iconst_0
      13: invokevirtual #1616               // Method resetFont:(Lorg/eclipse/ui/internal/themes/FontDefinition;Z)Z
      16: pop
      17: goto          37
      20: aload_0
      21: invokevirtual #1570               // Method isColorSelected:()Z
      24: ifeq          37
      27: aload_0
      28: aload_0
      29: invokevirtual #1608               // Method getSelectedColorDefinition:()Lorg/eclipse/ui/internal/themes/ColorDefinition;
      32: iconst_0
      33: invokevirtual #1611               // Method resetColor:(Lorg/eclipse/ui/internal/themes/ColorDefinition;Z)Z
      36: pop
      37: aload_0
      38: invokevirtual #1569               // Method updateControls:()V
      41: return

  private void lambda$5(org.eclipse.swt.events.SelectionEvent);
    Code:
       0: aload_0
       1: invokevirtual #1613               // Method getSelectedFontDefinition:()Lorg/eclipse/ui/internal/themes/FontDefinition;
       4: astore_2
       5: aload_2
       6: ifnonnull     10
       9: return
      10: invokestatic  #1428               // Method org/eclipse/jface/resource/JFaceResources.getDefaultFont:()Lorg/eclipse/swt/graphics/Font;
      13: invokevirtual #1466               // Method org/eclipse/swt/graphics/Font.getFontData:()[Lorg/eclipse/swt/graphics/FontData;
      16: astore_3
      17: aload_0
      18: aload_2
      19: aload_3
      20: iconst_0
      21: invokevirtual #1630               // Method setFontPreferenceValue:(Lorg/eclipse/ui/internal/themes/FontDefinition;[Lorg/eclipse/swt/graphics/FontData;Z)V
      24: aload_0
      25: invokevirtual #1569               // Method updateControls:()V
      28: return

  private void lambda$6(org.eclipse.swt.events.SelectionEvent);
    Code:
       0: aload_1
       1: getfield      #1326               // Field org/eclipse/swt/events/SelectionEvent.display:Lorg/eclipse/swt/widgets/Display;
       4: astore_2
       5: aload_0
       6: invokevirtual #1613               // Method getSelectedFontDefinition:()Lorg/eclipse/ui/internal/themes/FontDefinition;
       9: astore_3
      10: aload_3
      11: ifnull        43
      14: aload_3
      15: invokevirtual #1660               // Method org/eclipse/ui/internal/themes/FontDefinition.getDefaultsTo:()Ljava/lang/String;
      18: astore        4
      20: aload_0
      21: getfield      #1383               // Field themeRegistry:Lorg/eclipse/ui/internal/themes/IThemeRegistry;
      24: aload         4
      26: invokeinterface #1716,  2         // InterfaceMethod org/eclipse/ui/internal/themes/IThemeRegistry.findFont:(Ljava/lang/String;)Lorg/eclipse/ui/internal/themes/FontDefinition;
      31: astore        5
      33: aload_0
      34: aload         5
      36: aload_2
      37: invokevirtual #1638               // Method editFont:(Lorg/eclipse/ui/internal/themes/FontDefinition;Lorg/eclipse/swt/widgets/Display;)V
      40: goto          81
      43: aload_0
      44: invokevirtual #1608               // Method getSelectedColorDefinition:()Lorg/eclipse/ui/internal/themes/ColorDefinition;
      47: astore        4
      49: aload         4
      51: ifnull        81
      54: aload         4
      56: invokevirtual #1555               // Method org/eclipse/ui/internal/themes/ColorDefinition.getDefaultsTo:()Ljava/lang/String;
      59: astore        5
      61: aload_0
      62: getfield      #1383               // Field themeRegistry:Lorg/eclipse/ui/internal/themes/IThemeRegistry;
      65: aload         5
      67: invokeinterface #1715,  2         // InterfaceMethod org/eclipse/ui/internal/themes/IThemeRegistry.findColor:(Ljava/lang/String;)Lorg/eclipse/ui/internal/themes/ColorDefinition;
      72: astore        6
      74: aload_0
      75: aload         6
      77: aload_2
      78: invokevirtual #1637               // Method editColor:(Lorg/eclipse/ui/internal/themes/ColorDefinition;Lorg/eclipse/swt/widgets/Display;)V
      81: aload_0
      82: invokevirtual #1569               // Method updateControls:()V
      85: return

  private void lambda$7(org.eclipse.swt.events.SelectionEvent);
    Code:
       0: aload_0
       1: invokevirtual #1613               // Method getSelectedFontDefinition:()Lorg/eclipse/ui/internal/themes/FontDefinition;
       4: astore_2
       5: aload_2
       6: ifnull        35
       9: aload_2
      10: invokevirtual #1660               // Method org/eclipse/ui/internal/themes/FontDefinition.getDefaultsTo:()Ljava/lang/String;
      13: astore_3
      14: aload_0
      15: getfield      #1383               // Field themeRegistry:Lorg/eclipse/ui/internal/themes/IThemeRegistry;
      18: aload_3
      19: invokeinterface #1716,  2         // InterfaceMethod org/eclipse/ui/internal/themes/IThemeRegistry.findFont:(Ljava/lang/String;)Lorg/eclipse/ui/internal/themes/FontDefinition;
      24: astore        4
      26: aload_0
      27: aload         4
      29: invokevirtual #1577               // Method selectAndReveal:(Ljava/lang/Object;)V
      32: goto          69
      35: aload_0
      36: invokevirtual #1608               // Method getSelectedColorDefinition:()Lorg/eclipse/ui/internal/themes/ColorDefinition;
      39: astore_3
      40: aload_3
      41: ifnull        69
      44: aload_3
      45: invokevirtual #1555               // Method org/eclipse/ui/internal/themes/ColorDefinition.getDefaultsTo:()Ljava/lang/String;
      48: astore        4
      50: aload_0
      51: getfield      #1383               // Field themeRegistry:Lorg/eclipse/ui/internal/themes/IThemeRegistry;
      54: aload         4
      56: invokeinterface #1715,  2         // InterfaceMethod org/eclipse/ui/internal/themes/IThemeRegistry.findColor:(Ljava/lang/String;)Lorg/eclipse/ui/internal/themes/ColorDefinition;
      61: astore        5
      63: aload_0
      64: aload         5
      66: invokevirtual #1577               // Method selectAndReveal:(Ljava/lang/Object;)V
      69: aload_0
      70: invokevirtual #1569               // Method updateControls:()V
      73: return

  private void lambda$8(org.eclipse.swt.events.SelectionEvent);
    Code:
       0: aload_0
       1: getfield      #1377               // Field tree:Lorg/eclipse/ui/dialogs/FilteredTree;
       4: invokevirtual #1534               // Method org/eclipse/ui/dialogs/FilteredTree.getViewer:()Lorg/eclipse/jface/viewers/TreeViewer;
       7: invokevirtual #1436               // Method org/eclipse/jface/viewers/TreeViewer.expandAll:()V
      10: return

  private void lambda$9(org.eclipse.ui.themes.IThemeManager, org.eclipse.jface.util.PropertyChangeEvent);
    Code:
       0: aload_2
       1: invokevirtual #1431               // Method org/eclipse/jface/util/PropertyChangeEvent.getProperty:()Ljava/lang/String;
       4: ldc_w         #605                // String CHANGE_CURRENT_THEME
       7: invokevirtual #1396               // Method java/lang/String.equals:(Ljava/lang/Object;)Z
      10: ifeq          26
      13: aload_0
      14: aload_1
      15: invokevirtual #1621               // Method updateThemeInfo:(Lorg/eclipse/ui/themes/IThemeManager;)V
      18: aload_0
      19: invokevirtual #1564               // Method refreshCategory:()V
      22: aload_0
      23: invokevirtual #1563               // Method refreshAllLabels:()V
      26: return

  private void lambda$10(org.eclipse.swt.events.PaintEvent);
    Code:
       0: aload_0
       1: getfield      #1363               // Field currentFont:Lorg/eclipse/swt/graphics/Font;
       4: ifnull        15
       7: aload_0
       8: aload_1
       9: getfield      #1325               // Field org/eclipse/swt/events/PaintEvent.gc:Lorg/eclipse/swt/graphics/GC;
      12: invokevirtual #1595               // Method paintFontSample:(Lorg/eclipse/swt/graphics/GC;)V
      15: return

  private void lambda$11(org.eclipse.swt.events.PaintEvent);
    Code:
       0: aload_0
       1: getfield      #1361               // Field currentColor:Lorg/eclipse/swt/graphics/Color;
       4: ifnull        15
       7: aload_0
       8: aload_1
       9: getfield      #1325               // Field org/eclipse/swt/events/PaintEvent.gc:Lorg/eclipse/swt/graphics/GC;
      12: invokevirtual #1594               // Method paintColorSample:(Lorg/eclipse/swt/graphics/GC;)V
      15: return
}
