Compiled from "ClassFileLocator.java"
public class net.bytebuddy.dynamic.ClassFileLocator$Compound implements net.bytebuddy.dynamic.ClassFileLocator,java.io.Closeable {
  private final java.util.List<net.bytebuddy.dynamic.ClassFileLocator> classFileLocators;

  public net.bytebuddy.dynamic.ClassFileLocator$Compound(net.bytebuddy.dynamic.ClassFileLocator...);
    Code:
       0: aload_0
       1: aload_1
       2: invokestatic  #30                 // Method java/util/Arrays.asList:([Ljava/lang/Object;)Ljava/util/List;
       5: invokespecial #33                 // Method "<init>":(Ljava/util/List;)V
       8: return

  public net.bytebuddy.dynamic.ClassFileLocator$Compound(java.util.List<? extends net.bytebuddy.dynamic.ClassFileLocator>);
    Code:
       0: aload_0
       1: invokespecial #40                 // Method java/lang/Object."<init>":()V
       4: aload_0
       5: new           #42                 // class java/util/ArrayList
       8: dup
       9: invokespecial #43                 // Method java/util/ArrayList."<init>":()V
      12: putfield      #45                 // Field classFileLocators:Ljava/util/List;
      15: aload_1
      16: invokeinterface #51,  1           // InterfaceMethod java/util/List.iterator:()Ljava/util/Iterator;
      21: astore_2
      22: aload_2
      23: invokeinterface #57,  1           // InterfaceMethod java/util/Iterator.hasNext:()Z
      28: ifeq          89
      31: aload_2
      32: invokeinterface #61,  1           // InterfaceMethod java/util/Iterator.next:()Ljava/lang/Object;
      37: checkcast     #6                  // class net/bytebuddy/dynamic/ClassFileLocator
      40: astore_3
      41: aload_3
      42: instanceof    #2                  // class net/bytebuddy/dynamic/ClassFileLocator$Compound
      45: ifeq          68
      48: aload_0
      49: getfield      #45                 // Field classFileLocators:Ljava/util/List;
      52: aload_3
      53: checkcast     #2                  // class net/bytebuddy/dynamic/ClassFileLocator$Compound
      56: getfield      #45                 // Field classFileLocators:Ljava/util/List;
      59: invokeinterface #65,  2           // InterfaceMethod java/util/List.addAll:(Ljava/util/Collection;)Z
      64: pop
      65: goto          86
      68: aload_3
      69: instanceof    #15                 // class net/bytebuddy/dynamic/ClassFileLocator$NoOp
      72: ifne          86
      75: aload_0
      76: getfield      #45                 // Field classFileLocators:Ljava/util/List;
      79: aload_3
      80: invokeinterface #69,  2           // InterfaceMethod java/util/List.add:(Ljava/lang/Object;)Z
      85: pop
      86: goto          22
      89: return

  public net.bytebuddy.dynamic.ClassFileLocator$Resolution locate(java.lang.String) throws java.io.IOException;
    Code:
       0: aload_0
       1: getfield      #45                 // Field classFileLocators:Ljava/util/List;
       4: invokeinterface #51,  1           // InterfaceMethod java/util/List.iterator:()Ljava/util/Iterator;
       9: astore_2
      10: aload_2
      11: invokeinterface #57,  1           // InterfaceMethod java/util/Iterator.hasNext:()Z
      16: ifeq          54
      19: aload_2
      20: invokeinterface #61,  1           // InterfaceMethod java/util/Iterator.next:()Ljava/lang/Object;
      25: checkcast     #6                  // class net/bytebuddy/dynamic/ClassFileLocator
      28: astore_3
      29: aload_3
      30: aload_1
      31: invokeinterface #77,  2           // InterfaceMethod net/bytebuddy/dynamic/ClassFileLocator.locate:(Ljava/lang/String;)Lnet/bytebuddy/dynamic/ClassFileLocator$Resolution;
      36: astore        4
      38: aload         4
      40: invokeinterface #80,  1           // InterfaceMethod net/bytebuddy/dynamic/ClassFileLocator$Resolution.isResolved:()Z
      45: ifeq          51
      48: aload         4
      50: areturn
      51: goto          10
      54: new           #18                 // class net/bytebuddy/dynamic/ClassFileLocator$Resolution$Illegal
      57: dup
      58: aload_1
      59: invokespecial #83                 // Method net/bytebuddy/dynamic/ClassFileLocator$Resolution$Illegal."<init>":(Ljava/lang/String;)V
      62: areturn

  public void close() throws java.io.IOException;
    Code:
       0: aload_0
       1: getfield      #45                 // Field classFileLocators:Ljava/util/List;
       4: invokeinterface #51,  1           // InterfaceMethod java/util/List.iterator:()Ljava/util/Iterator;
       9: astore_1
      10: aload_1
      11: invokeinterface #57,  1           // InterfaceMethod java/util/Iterator.hasNext:()Z
      16: ifeq          38
      19: aload_1
      20: invokeinterface #61,  1           // InterfaceMethod java/util/Iterator.next:()Ljava/lang/Object;
      25: checkcast     #6                  // class net/bytebuddy/dynamic/ClassFileLocator
      28: astore_2
      29: aload_2
      30: invokeinterface #90,  1           // InterfaceMethod net/bytebuddy/dynamic/ClassFileLocator.close:()V
      35: goto          10
      38: return

  public boolean equals(java.lang.Object);
    Code:
       0: aload_1
       1: aload_0
       2: if_acmpne     7
       5: iconst_1
       6: ireturn
       7: aload_1
       8: instanceof    #2                  // class net/bytebuddy/dynamic/ClassFileLocator$Compound
      11: ifne          16
      14: iconst_0
      15: ireturn
      16: aload_1
      17: checkcast     #2                  // class net/bytebuddy/dynamic/ClassFileLocator$Compound
      20: astore_2
      21: aload_2
      22: aload_0
      23: invokevirtual #94                 // Method canEqual:(Ljava/lang/Object;)Z
      26: ifne          31
      29: iconst_0
      30: ireturn
      31: aload_0
      32: getfield      #45                 // Field classFileLocators:Ljava/util/List;
      35: astore_3
      36: aload_2
      37: getfield      #45                 // Field classFileLocators:Ljava/util/List;
      40: astore        4
      42: aload_3
      43: ifnonnull     54
      46: aload         4
      48: ifnull        65
      51: goto          63
      54: aload_3
      55: aload         4
      57: invokevirtual #96                 // Method java/lang/Object.equals:(Ljava/lang/Object;)Z
      60: ifne          65
      63: iconst_0
      64: ireturn
      65: iconst_1
      66: ireturn

  protected boolean canEqual(java.lang.Object);
    Code:
       0: aload_1
       1: instanceof    #2                  // class net/bytebuddy/dynamic/ClassFileLocator$Compound
       4: ireturn

  public int hashCode();
    Code:
       0: bipush        59
       2: istore_1
       3: iconst_1
       4: istore_2
       5: aload_0
       6: getfield      #45                 // Field classFileLocators:Ljava/util/List;
       9: astore_3
      10: iload_2
      11: bipush        59
      13: imul
      14: aload_3
      15: ifnonnull     23
      18: bipush        43
      20: goto          27
      23: aload_3
      24: invokevirtual #105                // Method java/lang/Object.hashCode:()I
      27: iadd
      28: istore_2
      29: iload_2
      30: ireturn
}
