Compiled from "ControlledClusterFailover.java"
public class org.apache.pulsar.client.impl.ControlledClusterFailover$ControlledClusterFailoverBuilderImpl implements org.apache.pulsar.client.api.ControlledClusterFailoverBuilder {
  private java.lang.String defaultServiceUrl;

  private java.lang.String urlProvider;

  private java.util.Map<java.lang.String, java.lang.String> header;

  private long interval;

  public org.apache.pulsar.client.impl.ControlledClusterFailover$ControlledClusterFailoverBuilderImpl();
    Code:
       0: aload_0
       1: invokespecial #5                  // Method java/lang/Object."<init>":()V
       4: aload_0
       5: aconst_null
       6: putfield      #1                  // Field header:Ljava/util/Map;
       9: aload_0
      10: ldc2_w        #6                  // long 30000l
      13: putfield      #3                  // Field interval:J
      16: return

  public org.apache.pulsar.client.api.ControlledClusterFailoverBuilder defaultServiceUrl(java.lang.String);
    Code:
       0: aload_1
       1: ifnonnull     14
       4: new           #8                  // class java/lang/NullPointerException
       7: dup
       8: ldc           #9                  // String serviceUrl is marked non-null but is null
      10: invokespecial #10                 // Method java/lang/NullPointerException."<init>":(Ljava/lang/String;)V
      13: athrow
      14: aload_0
      15: aload_1
      16: putfield      #4                  // Field defaultServiceUrl:Ljava/lang/String;
      19: aload_0
      20: areturn

  public org.apache.pulsar.client.api.ControlledClusterFailoverBuilder urlProvider(java.lang.String);
    Code:
       0: aload_1
       1: ifnonnull     14
       4: new           #8                  // class java/lang/NullPointerException
       7: dup
       8: ldc           #11                 // String urlProvider is marked non-null but is null
      10: invokespecial #10                 // Method java/lang/NullPointerException."<init>":(Ljava/lang/String;)V
      13: athrow
      14: aload_0
      15: aload_1
      16: putfield      #2                  // Field urlProvider:Ljava/lang/String;
      19: aload_0
      20: areturn

  public org.apache.pulsar.client.api.ControlledClusterFailoverBuilder urlProviderHeader(java.util.Map<java.lang.String, java.lang.String>);
    Code:
       0: aload_0
       1: aload_1
       2: putfield      #1                  // Field header:Ljava/util/Map;
       5: aload_0
       6: areturn

  public org.apache.pulsar.client.api.ControlledClusterFailoverBuilder checkInterval(long, java.util.concurrent.TimeUnit);
    Code:
       0: aload_3
       1: ifnonnull     14
       4: new           #8                  // class java/lang/NullPointerException
       7: dup
       8: ldc           #12                 // String timeUnit is marked non-null but is null
      10: invokespecial #10                 // Method java/lang/NullPointerException."<init>":(Ljava/lang/String;)V
      13: athrow
      14: aload_0
      15: aload_3
      16: lload_1
      17: invokevirtual #13                 // Method java/util/concurrent/TimeUnit.toMillis:(J)J
      20: putfield      #3                  // Field interval:J
      23: aload_0
      24: areturn

  public org.apache.pulsar.client.api.ServiceUrlProvider build() throws java.io.IOException;
    Code:
       0: aload_0
       1: getfield      #4                  // Field defaultServiceUrl:Ljava/lang/String;
       4: ldc           #14                 // String default service url shouldn\'t be null
       6: invokestatic  #15                 // Method java/util/Objects.requireNonNull:(Ljava/lang/Object;Ljava/lang/String;)Ljava/lang/Object;
       9: pop
      10: aload_0
      11: getfield      #2                  // Field urlProvider:Ljava/lang/String;
      14: ldc           #16                 // String urlProvider shouldn\'t be null
      16: invokestatic  #15                 // Method java/util/Objects.requireNonNull:(Ljava/lang/Object;Ljava/lang/String;)Ljava/lang/Object;
      19: pop
      20: aload_0
      21: getfield      #3                  // Field interval:J
      24: lconst_0
      25: lcmp
      26: ifle          33
      29: iconst_1
      30: goto          34
      33: iconst_0
      34: ldc           #17                 // String checkInterval should > 0
      36: invokestatic  #18                 // Method checkArgument:(ZLjava/lang/Object;)V
      39: new           #19                 // class org/apache/pulsar/client/impl/ControlledClusterFailover
      42: dup
      43: aload_0
      44: aconst_null
      45: invokespecial #20                 // Method org/apache/pulsar/client/impl/ControlledClusterFailover."<init>":(Lorg/apache/pulsar/client/impl/ControlledClusterFailover$ControlledClusterFailoverBuilderImpl;Lorg/apache/pulsar/client/impl/ControlledClusterFailover$1;)V
      48: areturn

  public static void checkArgument(boolean, java.lang.Object);
    Code:
       0: iload_0
       1: ifne          16
       4: new           #21                 // class java/lang/IllegalArgumentException
       7: dup
       8: aload_1
       9: invokestatic  #22                 // Method java/lang/String.valueOf:(Ljava/lang/Object;)Ljava/lang/String;
      12: invokespecial #23                 // Method java/lang/IllegalArgumentException."<init>":(Ljava/lang/String;)V
      15: athrow
      16: return

  static java.lang.String access$000(org.apache.pulsar.client.impl.ControlledClusterFailover$ControlledClusterFailoverBuilderImpl);
    Code:
       0: aload_0
       1: getfield      #4                  // Field defaultServiceUrl:Ljava/lang/String;
       4: areturn

  static long access$100(org.apache.pulsar.client.impl.ControlledClusterFailover$ControlledClusterFailoverBuilderImpl);
    Code:
       0: aload_0
       1: getfield      #3                  // Field interval:J
       4: lreturn

  static java.lang.String access$200(org.apache.pulsar.client.impl.ControlledClusterFailover$ControlledClusterFailoverBuilderImpl);
    Code:
       0: aload_0
       1: getfield      #2                  // Field urlProvider:Ljava/lang/String;
       4: areturn

  static java.util.Map access$300(org.apache.pulsar.client.impl.ControlledClusterFailover$ControlledClusterFailoverBuilderImpl);
    Code:
       0: aload_0
       1: getfield      #1                  // Field header:Ljava/util/Map;
       4: areturn
}
