Compiled from "HttpLookupService.java"
public class org.apache.pulsar.client.impl.HttpLookupService implements org.apache.pulsar.client.impl.LookupService {
  private final org.apache.pulsar.client.impl.HttpClient httpClient;

  private final boolean useTls;

  private final java.lang.String listenerName;

  private static final java.lang.String BasePathV1;

  private static final java.lang.String BasePathV2;

  private static final org.slf4j.Logger log;

  public org.apache.pulsar.client.impl.HttpLookupService(org.apache.pulsar.client.impl.conf.ClientConfigurationData, io.netty.channel.EventLoopGroup) throws org.apache.pulsar.client.api.PulsarClientException;
    Code:
       0: aload_0
       1: invokespecial #1                  // Method java/lang/Object."<init>":()V
       4: aload_0
       5: new           #2                  // class org/apache/pulsar/client/impl/HttpClient
       8: dup
       9: aload_1
      10: aload_2
      11: invokespecial #3                  // Method org/apache/pulsar/client/impl/HttpClient."<init>":(Lorg/apache/pulsar/client/impl/conf/ClientConfigurationData;Lio/netty/channel/EventLoopGroup;)V
      14: putfield      #4                  // Field httpClient:Lorg/apache/pulsar/client/impl/HttpClient;
      17: aload_0
      18: aload_1
      19: invokevirtual #5                  // Method org/apache/pulsar/client/impl/conf/ClientConfigurationData.isUseTls:()Z
      22: putfield      #6                  // Field useTls:Z
      25: aload_0
      26: aload_1
      27: invokevirtual #7                  // Method org/apache/pulsar/client/impl/conf/ClientConfigurationData.getListenerName:()Ljava/lang/String;
      30: putfield      #8                  // Field listenerName:Ljava/lang/String;
      33: return

  public void updateServiceUrl(java.lang.String) throws org.apache.pulsar.client.api.PulsarClientException;
    Code:
       0: aload_0
       1: getfield      #4                  // Field httpClient:Lorg/apache/pulsar/client/impl/HttpClient;
       4: aload_1
       5: invokevirtual #9                  // Method org/apache/pulsar/client/impl/HttpClient.setServiceUrl:(Ljava/lang/String;)V
       8: return

  public java.util.concurrent.CompletableFuture<org.apache.commons.lang3.tuple.Pair<java.net.InetSocketAddress, java.net.InetSocketAddress>> getBroker(org.apache.pulsar.common.naming.TopicName);
    Code:
       0: aload_1
       1: invokevirtual #10                 // Method org/apache/pulsar/common/naming/TopicName.isV2:()Z
       4: ifeq          12
       7: ldc           #12                 // String lookup/v2/topic/
       9: goto          14
      12: ldc           #13                 // String lookup/v2/destination/
      14: astore_2
      15: new           #14                 // class java/lang/StringBuilder
      18: dup
      19: invokespecial #15                 // Method java/lang/StringBuilder."<init>":()V
      22: aload_2
      23: invokevirtual #16                 // Method java/lang/StringBuilder.append:(Ljava/lang/String;)Ljava/lang/StringBuilder;
      26: aload_1
      27: invokevirtual #17                 // Method org/apache/pulsar/common/naming/TopicName.getLookupName:()Ljava/lang/String;
      30: invokevirtual #16                 // Method java/lang/StringBuilder.append:(Ljava/lang/String;)Ljava/lang/StringBuilder;
      33: invokevirtual #18                 // Method java/lang/StringBuilder.toString:()Ljava/lang/String;
      36: astore_3
      37: aload_0
      38: getfield      #8                  // Field listenerName:Ljava/lang/String;
      41: invokestatic  #19                 // Method org/apache/commons/lang3/StringUtils.isBlank:(Ljava/lang/CharSequence;)Z
      44: ifeq          51
      47: aload_3
      48: goto          80
      51: new           #14                 // class java/lang/StringBuilder
      54: dup
      55: invokespecial #15                 // Method java/lang/StringBuilder."<init>":()V
      58: aload_3
      59: invokevirtual #16                 // Method java/lang/StringBuilder.append:(Ljava/lang/String;)Ljava/lang/StringBuilder;
      62: ldc           #20                 // String ?listenerName=
      64: invokevirtual #16                 // Method java/lang/StringBuilder.append:(Ljava/lang/String;)Ljava/lang/StringBuilder;
      67: aload_0
      68: getfield      #8                  // Field listenerName:Ljava/lang/String;
      71: invokestatic  #21                 // Method org/apache/pulsar/common/util/Codec.encode:(Ljava/lang/String;)Ljava/lang/String;
      74: invokevirtual #16                 // Method java/lang/StringBuilder.append:(Ljava/lang/String;)Ljava/lang/StringBuilder;
      77: invokevirtual #18                 // Method java/lang/StringBuilder.toString:()Ljava/lang/String;
      80: astore_3
      81: aload_0
      82: getfield      #4                  // Field httpClient:Lorg/apache/pulsar/client/impl/HttpClient;
      85: aload_3
      86: ldc           #22                 // class org/apache/pulsar/common/lookup/data/LookupData
      88: invokevirtual #23                 // Method org/apache/pulsar/client/impl/HttpClient.get:(Ljava/lang/String;Ljava/lang/Class;)Ljava/util/concurrent/CompletableFuture;
      91: aload_0
      92: aload_1
      93: invokedynamic #24,  0             // InvokeDynamic #0:apply:(Lorg/apache/pulsar/client/impl/HttpLookupService;Lorg/apache/pulsar/common/naming/TopicName;)Ljava/util/function/Function;
      98: invokevirtual #25                 // Method java/util/concurrent/CompletableFuture.thenCompose:(Ljava/util/function/Function;)Ljava/util/concurrent/CompletableFuture;
     101: areturn

  public java.util.concurrent.CompletableFuture<org.apache.pulsar.common.partition.PartitionedTopicMetadata> getPartitionedTopicMetadata(org.apache.pulsar.common.naming.TopicName);
    Code:
       0: aload_1
       1: invokevirtual #10                 // Method org/apache/pulsar/common/naming/TopicName.isV2:()Z
       4: ifeq          12
       7: ldc           #26                 // String admin/v2/%s/partitions
       9: goto          14
      12: ldc           #27                 // String admin/%s/partitions
      14: astore_2
      15: aload_0
      16: getfield      #4                  // Field httpClient:Lorg/apache/pulsar/client/impl/HttpClient;
      19: new           #14                 // class java/lang/StringBuilder
      22: dup
      23: invokespecial #15                 // Method java/lang/StringBuilder."<init>":()V
      26: aload_2
      27: iconst_1
      28: anewarray     #28                 // class java/lang/Object
      31: dup
      32: iconst_0
      33: aload_1
      34: invokevirtual #17                 // Method org/apache/pulsar/common/naming/TopicName.getLookupName:()Ljava/lang/String;
      37: aastore
      38: invokestatic  #29                 // Method java/lang/String.format:(Ljava/lang/String;[Ljava/lang/Object;)Ljava/lang/String;
      41: invokevirtual #16                 // Method java/lang/StringBuilder.append:(Ljava/lang/String;)Ljava/lang/StringBuilder;
      44: ldc           #30                 // String ?checkAllowAutoCreation=true
      46: invokevirtual #16                 // Method java/lang/StringBuilder.append:(Ljava/lang/String;)Ljava/lang/StringBuilder;
      49: invokevirtual #18                 // Method java/lang/StringBuilder.toString:()Ljava/lang/String;
      52: ldc           #31                 // class org/apache/pulsar/common/partition/PartitionedTopicMetadata
      54: invokevirtual #23                 // Method org/apache/pulsar/client/impl/HttpClient.get:(Ljava/lang/String;Ljava/lang/Class;)Ljava/util/concurrent/CompletableFuture;
      57: areturn

  public java.lang.String getServiceUrl();
    Code:
       0: aload_0
       1: getfield      #4                  // Field httpClient:Lorg/apache/pulsar/client/impl/HttpClient;
       4: invokevirtual #32                 // Method org/apache/pulsar/client/impl/HttpClient.getServiceUrl:()Ljava/lang/String;
       7: areturn

  public java.util.concurrent.CompletableFuture<java.util.List<java.lang.String>> getTopicsUnderNamespace(org.apache.pulsar.common.naming.NamespaceName, org.apache.pulsar.common.api.proto.CommandGetTopicsOfNamespace$Mode);
    Code:
       0: new           #33                 // class java/util/concurrent/CompletableFuture
       3: dup
       4: invokespecial #34                 // Method java/util/concurrent/CompletableFuture."<init>":()V
       7: astore_3
       8: aload_1
       9: invokevirtual #35                 // Method org/apache/pulsar/common/naming/NamespaceName.isV2:()Z
      12: ifeq          20
      15: ldc           #36                 // String admin/v2/namespaces/%s/topics?mode=%s
      17: goto          22
      20: ldc           #37                 // String admin/namespaces/%s/destinations?mode=%s
      22: astore        4
      24: aload_0
      25: getfield      #4                  // Field httpClient:Lorg/apache/pulsar/client/impl/HttpClient;
      28: aload         4
      30: iconst_2
      31: anewarray     #28                 // class java/lang/Object
      34: dup
      35: iconst_0
      36: aload_1
      37: aastore
      38: dup
      39: iconst_1
      40: aload_2
      41: invokevirtual #38                 // Method org/apache/pulsar/common/api/proto/CommandGetTopicsOfNamespace$Mode.toString:()Ljava/lang/String;
      44: aastore
      45: invokestatic  #29                 // Method java/lang/String.format:(Ljava/lang/String;[Ljava/lang/Object;)Ljava/lang/String;
      48: ldc           #39                 // class "[Ljava/lang/String;"
      50: invokevirtual #23                 // Method org/apache/pulsar/client/impl/HttpClient.get:(Ljava/lang/String;Ljava/lang/Class;)Ljava/util/concurrent/CompletableFuture;
      53: aload_3
      54: invokedynamic #40,  0             // InvokeDynamic #1:accept:(Ljava/util/concurrent/CompletableFuture;)Ljava/util/function/Consumer;
      59: invokevirtual #41                 // Method java/util/concurrent/CompletableFuture.thenAccept:(Ljava/util/function/Consumer;)Ljava/util/concurrent/CompletableFuture;
      62: aload_1
      63: aload_3
      64: invokedynamic #42,  0             // InvokeDynamic #2:apply:(Lorg/apache/pulsar/common/naming/NamespaceName;Ljava/util/concurrent/CompletableFuture;)Ljava/util/function/Function;
      69: invokevirtual #43                 // Method java/util/concurrent/CompletableFuture.exceptionally:(Ljava/util/function/Function;)Ljava/util/concurrent/CompletableFuture;
      72: pop
      73: aload_3
      74: areturn

  public java.util.concurrent.CompletableFuture<java.util.Optional<org.apache.pulsar.common.schema.SchemaInfo>> getSchema(org.apache.pulsar.common.naming.TopicName);
    Code:
       0: aload_0
       1: aload_1
       2: aconst_null
       3: invokevirtual #44                 // Method getSchema:(Lorg/apache/pulsar/common/naming/TopicName;[B)Ljava/util/concurrent/CompletableFuture;
       6: areturn

  public java.util.concurrent.CompletableFuture<java.util.Optional<org.apache.pulsar.common.schema.SchemaInfo>> getSchema(org.apache.pulsar.common.naming.TopicName, byte[]);
    Code:
       0: new           #33                 // class java/util/concurrent/CompletableFuture
       3: dup
       4: invokespecial #34                 // Method java/util/concurrent/CompletableFuture."<init>":()V
       7: astore_3
       8: aload_1
       9: invokevirtual #45                 // Method org/apache/pulsar/common/naming/TopicName.getSchemaName:()Ljava/lang/String;
      12: astore        4
      14: ldc           #46                 // String admin/v2/schemas/%s/schema
      16: iconst_1
      17: anewarray     #28                 // class java/lang/Object
      20: dup
      21: iconst_0
      22: aload         4
      24: aastore
      25: invokestatic  #29                 // Method java/lang/String.format:(Ljava/lang/String;[Ljava/lang/Object;)Ljava/lang/String;
      28: astore        5
      30: aload_2
      31: ifnull        63
      34: ldc           #47                 // String admin/v2/schemas/%s/schema/%s
      36: iconst_2
      37: anewarray     #28                 // class java/lang/Object
      40: dup
      41: iconst_0
      42: aload         4
      44: aastore
      45: dup
      46: iconst_1
      47: aload_2
      48: invokestatic  #48                 // Method java/nio/ByteBuffer.wrap:([B)Ljava/nio/ByteBuffer;
      51: invokevirtual #49                 // Method java/nio/ByteBuffer.getLong:()J
      54: invokestatic  #50                 // Method java/lang/Long.valueOf:(J)Ljava/lang/Long;
      57: aastore
      58: invokestatic  #29                 // Method java/lang/String.format:(Ljava/lang/String;[Ljava/lang/Object;)Ljava/lang/String;
      61: astore        5
      63: aload_0
      64: getfield      #4                  // Field httpClient:Lorg/apache/pulsar/client/impl/HttpClient;
      67: aload         5
      69: ldc           #51                 // class org/apache/pulsar/common/protocol/schema/GetSchemaResponse
      71: invokevirtual #23                 // Method org/apache/pulsar/client/impl/HttpClient.get:(Ljava/lang/String;Ljava/lang/Class;)Ljava/util/concurrent/CompletableFuture;
      74: aload_3
      75: aload         4
      77: invokedynamic #52,  0             // InvokeDynamic #3:accept:(Ljava/util/concurrent/CompletableFuture;Ljava/lang/String;)Ljava/util/function/Consumer;
      82: invokevirtual #41                 // Method java/util/concurrent/CompletableFuture.thenAccept:(Ljava/util/function/Consumer;)Ljava/util/concurrent/CompletableFuture;
      85: aload_3
      86: aload_1
      87: aload_2
      88: invokedynamic #53,  0             // InvokeDynamic #4:apply:(Ljava/util/concurrent/CompletableFuture;Lorg/apache/pulsar/common/naming/TopicName;[B)Ljava/util/function/Function;
      93: invokevirtual #43                 // Method java/util/concurrent/CompletableFuture.exceptionally:(Ljava/util/function/Function;)Ljava/util/concurrent/CompletableFuture;
      96: pop
      97: aload_3
      98: areturn

  public void close() throws java.lang.Exception;
    Code:
       0: aload_0
       1: getfield      #4                  // Field httpClient:Lorg/apache/pulsar/client/impl/HttpClient;
       4: invokevirtual #54                 // Method org/apache/pulsar/client/impl/HttpClient.close:()V
       7: return

  private static java.lang.Void lambda$getSchema$5(java.util.concurrent.CompletableFuture, org.apache.pulsar.common.naming.TopicName, byte[], java.lang.Throwable);
    Code:
       0: aload_3
       1: invokevirtual #55                 // Method java/lang/Throwable.getCause:()Ljava/lang/Throwable;
       4: instanceof    #56                 // class org/apache/pulsar/client/api/PulsarClientException$NotFoundException
       7: ifeq          21
      10: aload_0
      11: invokestatic  #57                 // Method java/util/Optional.empty:()Ljava/util/Optional;
      14: invokevirtual #58                 // Method java/util/concurrent/CompletableFuture.complete:(Ljava/lang/Object;)Z
      17: pop
      18: goto          70
      21: getstatic     #59                 // Field log:Lorg/slf4j/Logger;
      24: ldc           #60                 // String Failed to get schema for topic {} version {}
      26: iconst_3
      27: anewarray     #28                 // class java/lang/Object
      30: dup
      31: iconst_0
      32: aload_1
      33: aastore
      34: dup
      35: iconst_1
      36: aload_2
      37: ifnull        50
      40: invokestatic  #61                 // Method java/util/Base64.getEncoder:()Ljava/util/Base64$Encoder;
      43: aload_2
      44: invokevirtual #62                 // Method java/util/Base64$Encoder.encodeToString:([B)Ljava/lang/String;
      47: goto          51
      50: aconst_null
      51: aastore
      52: dup
      53: iconst_2
      54: aload_3
      55: invokevirtual #55                 // Method java/lang/Throwable.getCause:()Ljava/lang/Throwable;
      58: aastore
      59: invokeinterface #63,  3           // InterfaceMethod org/slf4j/Logger.warn:(Ljava/lang/String;[Ljava/lang/Object;)V
      64: aload_0
      65: aload_3
      66: invokevirtual #64                 // Method java/util/concurrent/CompletableFuture.completeExceptionally:(Ljava/lang/Throwable;)Z
      69: pop
      70: aconst_null
      71: areturn

  private static void lambda$getSchema$4(java.util.concurrent.CompletableFuture, java.lang.String, org.apache.pulsar.common.protocol.schema.GetSchemaResponse);
    Code:
       0: aload_2
       1: invokevirtual #65                 // Method org/apache/pulsar/common/protocol/schema/GetSchemaResponse.getType:()Lorg/apache/pulsar/common/schema/SchemaType;
       4: getstatic     #66                 // Field org/apache/pulsar/common/schema/SchemaType.KEY_VALUE:Lorg/apache/pulsar/common/schema/SchemaType;
       7: if_acmpne     73
      10: invokestatic  #67                 // Method org/apache/pulsar/common/protocol/schema/SchemaData.builder:()Lorg/apache/pulsar/common/protocol/schema/SchemaData$SchemaDataBuilder;
      13: aload_2
      14: invokevirtual #68                 // Method org/apache/pulsar/common/protocol/schema/GetSchemaResponse.getData:()Ljava/lang/String;
      17: getstatic     #69                 // Field java/nio/charset/StandardCharsets.UTF_8:Ljava/nio/charset/Charset;
      20: invokevirtual #70                 // Method java/lang/String.getBytes:(Ljava/nio/charset/Charset;)[B
      23: invokestatic  #71                 // Method org/apache/pulsar/client/impl/schema/SchemaUtils.convertKeyValueDataStringToSchemaInfoSchema:([B)[B
      26: invokevirtual #72                 // Method org/apache/pulsar/common/protocol/schema/SchemaData$SchemaDataBuilder.data:([B)Lorg/apache/pulsar/common/protocol/schema/SchemaData$SchemaDataBuilder;
      29: aload_2
      30: invokevirtual #65                 // Method org/apache/pulsar/common/protocol/schema/GetSchemaResponse.getType:()Lorg/apache/pulsar/common/schema/SchemaType;
      33: invokevirtual #73                 // Method org/apache/pulsar/common/protocol/schema/SchemaData$SchemaDataBuilder.type:(Lorg/apache/pulsar/common/schema/SchemaType;)Lorg/apache/pulsar/common/protocol/schema/SchemaData$SchemaDataBuilder;
      36: aload_2
      37: invokevirtual #74                 // Method org/apache/pulsar/common/protocol/schema/GetSchemaResponse.getProperties:()Ljava/util/Map;
      40: invokevirtual #75                 // Method org/apache/pulsar/common/protocol/schema/SchemaData$SchemaDataBuilder.props:(Ljava/util/Map;)Lorg/apache/pulsar/common/protocol/schema/SchemaData$SchemaDataBuilder;
      43: invokevirtual #76                 // Method org/apache/pulsar/common/protocol/schema/SchemaData$SchemaDataBuilder.build:()Lorg/apache/pulsar/common/protocol/schema/SchemaData;
      46: astore_3
      47: aload_0
      48: aload_1
      49: aload_3
      50: invokestatic  #77                 // Method org/apache/pulsar/client/impl/schema/SchemaInfoUtil.newSchemaInfo:(Ljava/lang/String;Lorg/apache/pulsar/common/protocol/schema/SchemaData;)Lorg/apache/pulsar/common/schema/SchemaInfo;
      53: invokestatic  #78                 // Method java/util/Optional.of:(Ljava/lang/Object;)Ljava/util/Optional;
      56: invokevirtual #58                 // Method java/util/concurrent/CompletableFuture.complete:(Ljava/lang/Object;)Z
      59: pop
      60: goto          86
      63: astore_3
      64: aload_0
      65: aload_3
      66: invokevirtual #64                 // Method java/util/concurrent/CompletableFuture.completeExceptionally:(Ljava/lang/Throwable;)Z
      69: pop
      70: goto          86
      73: aload_0
      74: aload_1
      75: aload_2
      76: invokestatic  #80                 // Method org/apache/pulsar/client/impl/schema/SchemaInfoUtil.newSchemaInfo:(Ljava/lang/String;Lorg/apache/pulsar/common/protocol/schema/GetSchemaResponse;)Lorg/apache/pulsar/common/schema/SchemaInfo;
      79: invokestatic  #78                 // Method java/util/Optional.of:(Ljava/lang/Object;)Ljava/util/Optional;
      82: invokevirtual #58                 // Method java/util/concurrent/CompletableFuture.complete:(Ljava/lang/Object;)Z
      85: pop
      86: return
    Exception table:
       from    to  target type
          10    60    63   Class java/io/IOException

  private static java.lang.Void lambda$getTopicsUnderNamespace$3(org.apache.pulsar.common.naming.NamespaceName, java.util.concurrent.CompletableFuture, java.lang.Throwable);
    Code:
       0: getstatic     #59                 // Field log:Lorg/slf4j/Logger;
       3: ldc           #81                 // String Failed to getTopicsUnderNamespace namespace {} {}.
       5: aload_0
       6: aload_2
       7: invokevirtual #82                 // Method java/lang/Throwable.getMessage:()Ljava/lang/String;
      10: invokeinterface #83,  4           // InterfaceMethod org/slf4j/Logger.warn:(Ljava/lang/String;Ljava/lang/Object;Ljava/lang/Object;)V
      15: aload_1
      16: aload_2
      17: invokevirtual #64                 // Method java/util/concurrent/CompletableFuture.completeExceptionally:(Ljava/lang/Throwable;)Z
      20: pop
      21: aconst_null
      22: areturn

  private static void lambda$getTopicsUnderNamespace$2(java.util.concurrent.CompletableFuture, java.lang.String[]);
    Code:
       0: new           #84                 // class java/util/ArrayList
       3: dup
       4: invokespecial #85                 // Method java/util/ArrayList."<init>":()V
       7: astore_2
       8: aload_1
       9: invokestatic  #86                 // Method java/util/Arrays.asList:([Ljava/lang/Object;)Ljava/util/List;
      12: aload_2
      13: invokedynamic #87,  0             // InvokeDynamic #5:accept:(Ljava/util/List;)Ljava/util/function/Consumer;
      18: invokeinterface #88,  2           // InterfaceMethod java/util/List.forEach:(Ljava/util/function/Consumer;)V
      23: aload_0
      24: aload_2
      25: invokevirtual #58                 // Method java/util/concurrent/CompletableFuture.complete:(Ljava/lang/Object;)Z
      28: pop
      29: return

  private static void lambda$null$1(java.util.List, java.lang.String);
    Code:
       0: aload_1
       1: invokestatic  #89                 // Method org/apache/pulsar/common/naming/TopicName.get:(Ljava/lang/String;)Lorg/apache/pulsar/common/naming/TopicName;
       4: invokevirtual #90                 // Method org/apache/pulsar/common/naming/TopicName.getPartitionedTopicName:()Ljava/lang/String;
       7: astore_2
       8: aload_0
       9: aload_2
      10: invokeinterface #91,  2           // InterfaceMethod java/util/List.contains:(Ljava/lang/Object;)Z
      15: ifne          26
      18: aload_0
      19: aload_2
      20: invokeinterface #92,  2           // InterfaceMethod java/util/List.add:(Ljava/lang/Object;)Z
      25: pop
      26: return

  private java.util.concurrent.CompletionStage lambda$getBroker$0(org.apache.pulsar.common.naming.TopicName, org.apache.pulsar.common.lookup.data.LookupData);
    Code:
       0: aconst_null
       1: astore_3
       2: aload_0
       3: getfield      #6                  // Field useTls:Z
       6: ifeq          24
       9: new           #93                 // class java/net/URI
      12: dup
      13: aload_2
      14: invokevirtual #94                 // Method org/apache/pulsar/common/lookup/data/LookupData.getBrokerUrlTls:()Ljava/lang/String;
      17: invokespecial #95                 // Method java/net/URI."<init>":(Ljava/lang/String;)V
      20: astore_3
      21: goto          51
      24: aload_2
      25: invokevirtual #96                 // Method org/apache/pulsar/common/lookup/data/LookupData.getBrokerUrl:()Ljava/lang/String;
      28: astore        4
      30: aload         4
      32: ifnonnull     41
      35: aload_2
      36: invokevirtual #97                 // Method org/apache/pulsar/common/lookup/data/LookupData.getNativeUrl:()Ljava/lang/String;
      39: astore        4
      41: new           #93                 // class java/net/URI
      44: dup
      45: aload         4
      47: invokespecial #95                 // Method java/net/URI."<init>":(Ljava/lang/String;)V
      50: astore_3
      51: aload_3
      52: invokevirtual #98                 // Method java/net/URI.getHost:()Ljava/lang/String;
      55: aload_3
      56: invokevirtual #99                 // Method java/net/URI.getPort:()I
      59: invokestatic  #100                // Method java/net/InetSocketAddress.createUnresolved:(Ljava/lang/String;I)Ljava/net/InetSocketAddress;
      62: astore        4
      64: aload         4
      66: aload         4
      68: invokestatic  #101                // Method org/apache/commons/lang3/tuple/Pair.of:(Ljava/lang/Object;Ljava/lang/Object;)Lorg/apache/commons/lang3/tuple/Pair;
      71: invokestatic  #102                // Method java/util/concurrent/CompletableFuture.completedFuture:(Ljava/lang/Object;)Ljava/util/concurrent/CompletableFuture;
      74: areturn
      75: astore        4
      77: getstatic     #59                 // Field log:Lorg/slf4j/Logger;
      80: ldc           #104                // String [{}] Lookup Failed due to invalid url {}, {}
      82: iconst_3
      83: anewarray     #28                 // class java/lang/Object
      86: dup
      87: iconst_0
      88: aload_1
      89: aastore
      90: dup
      91: iconst_1
      92: aload_3
      93: aastore
      94: dup
      95: iconst_2
      96: aload         4
      98: invokevirtual #105                // Method java/lang/Exception.getMessage:()Ljava/lang/String;
     101: aastore
     102: invokeinterface #63,  3           // InterfaceMethod org/slf4j/Logger.warn:(Ljava/lang/String;[Ljava/lang/Object;)V
     107: aload         4
     109: invokestatic  #106                // Method org/apache/pulsar/common/util/FutureUtil.failedFuture:(Ljava/lang/Throwable;)Ljava/util/concurrent/CompletableFuture;
     112: areturn
    Exception table:
       from    to  target type
           2    74    75   Class java/lang/Exception

  static {};
    Code:
       0: ldc           #11                 // class org/apache/pulsar/client/impl/HttpLookupService
       2: invokestatic  #107                // Method org/slf4j/LoggerFactory.getLogger:(Ljava/lang/Class;)Lorg/slf4j/Logger;
       5: putstatic     #59                 // Field log:Lorg/slf4j/Logger;
       8: return
}
