Compiled from "MessageRouterBase.java"
public abstract class org.apache.pulsar.client.impl.MessageRouterBase implements org.apache.pulsar.client.api.MessageRouter {
  private static final long serialVersionUID;

  protected final org.apache.pulsar.client.impl.Hash hash;

  org.apache.pulsar.client.impl.MessageRouterBase(org.apache.pulsar.client.api.HashingScheme);
    Code:
       0: aload_0
       1: invokespecial #1                  // Method java/lang/Object."<init>":()V
       4: getstatic     #2                  // Field org/apache/pulsar/client/impl/MessageRouterBase$1.$SwitchMap$org$apache$pulsar$client$api$HashingScheme:[I
       7: aload_1
       8: invokevirtual #3                  // Method org/apache/pulsar/client/api/HashingScheme.ordinal:()I
      11: iaload
      12: lookupswitch  { // 2
                     1: 40
                     2: 50
               default: 50
          }
      40: aload_0
      41: invokestatic  #4                  // Method org/apache/pulsar/client/impl/JavaStringHash.getInstance:()Lorg/apache/pulsar/client/impl/Hash;
      44: putfield      #5                  // Field hash:Lorg/apache/pulsar/client/impl/Hash;
      47: goto          57
      50: aload_0
      51: invokestatic  #6                  // Method org/apache/pulsar/client/impl/Murmur3Hash32.getInstance:()Lorg/apache/pulsar/client/impl/Hash;
      54: putfield      #5                  // Field hash:Lorg/apache/pulsar/client/impl/Hash;
      57: return
}
