Compiled from "PulsarChannelInitializer.java"
public class org.apache.pulsar.client.impl.PulsarChannelInitializer extends io.netty.channel.ChannelInitializer<io.netty.channel.socket.SocketChannel> {
  private static final org.slf4j.Logger log;

  public static final java.lang.String TLS_HANDLER;

  private final java.util.function.Supplier<org.apache.pulsar.client.impl.ClientCnx> clientCnxSupplier;

  private final boolean tlsEnabled;

  private final boolean tlsEnabledWithKeyStore;

  private final java.net.InetSocketAddress socks5ProxyAddress;

  private final java.lang.String socks5ProxyUsername;

  private final java.lang.String socks5ProxyPassword;

  private final java.util.function.Supplier<io.netty.handler.ssl.SslContext> sslContextSupplier;

  private org.apache.pulsar.common.util.keystoretls.NettySSLContextAutoRefreshBuilder nettySSLContextAutoRefreshBuilder;

  private static final long TLS_CERTIFICATE_CACHE_MILLIS;

  public org.apache.pulsar.client.impl.PulsarChannelInitializer(org.apache.pulsar.client.impl.conf.ClientConfigurationData, java.util.function.Supplier<org.apache.pulsar.client.impl.ClientCnx>) throws java.lang.Exception;
    Code:
       0: aload_0
       1: invokespecial #1                  // Method io/netty/channel/ChannelInitializer."<init>":()V
       4: aload_0
       5: aload_2
       6: putfield      #2                  // Field clientCnxSupplier:Ljava/util/function/Supplier;
       9: aload_0
      10: aload_1
      11: invokevirtual #3                  // Method org/apache/pulsar/client/impl/conf/ClientConfigurationData.isUseTls:()Z
      14: putfield      #4                  // Field tlsEnabled:Z
      17: aload_0
      18: aload_1
      19: invokevirtual #5                  // Method org/apache/pulsar/client/impl/conf/ClientConfigurationData.getSocks5ProxyAddress:()Ljava/net/InetSocketAddress;
      22: putfield      #6                  // Field socks5ProxyAddress:Ljava/net/InetSocketAddress;
      25: aload_0
      26: aload_1
      27: invokevirtual #7                  // Method org/apache/pulsar/client/impl/conf/ClientConfigurationData.getSocks5ProxyUsername:()Ljava/lang/String;
      30: putfield      #8                  // Field socks5ProxyUsername:Ljava/lang/String;
      33: aload_0
      34: aload_1
      35: invokevirtual #9                  // Method org/apache/pulsar/client/impl/conf/ClientConfigurationData.getSocks5ProxyPassword:()Ljava/lang/String;
      38: putfield      #10                 // Field socks5ProxyPassword:Ljava/lang/String;
      41: aload_0
      42: aload_1
      43: invokevirtual #11                 // Method org/apache/pulsar/client/impl/conf/ClientConfigurationData.isUseKeyStoreTls:()Z
      46: putfield      #12                 // Field tlsEnabledWithKeyStore:Z
      49: aload_0
      50: getfield      #4                  // Field tlsEnabled:Z
      53: ifeq          142
      56: aload_0
      57: getfield      #12                 // Field tlsEnabledWithKeyStore:Z
      60: ifeq          116
      63: aload_1
      64: invokevirtual #13                 // Method org/apache/pulsar/client/impl/conf/ClientConfigurationData.getAuthentication:()Lorg/apache/pulsar/client/api/Authentication;
      67: invokeinterface #14,  1           // InterfaceMethod org/apache/pulsar/client/api/Authentication.getAuthData:()Lorg/apache/pulsar/client/api/AuthenticationDataProvider;
      72: astore_3
      73: aload_0
      74: new           #15                 // class org/apache/pulsar/common/util/keystoretls/NettySSLContextAutoRefreshBuilder
      77: dup
      78: aload_1
      79: invokevirtual #16                 // Method org/apache/pulsar/client/impl/conf/ClientConfigurationData.getSslProvider:()Ljava/lang/String;
      82: aload_1
      83: invokevirtual #17                 // Method org/apache/pulsar/client/impl/conf/ClientConfigurationData.isTlsAllowInsecureConnection:()Z
      86: aload_1
      87: invokevirtual #18                 // Method org/apache/pulsar/client/impl/conf/ClientConfigurationData.getTlsTrustStoreType:()Ljava/lang/String;
      90: aload_1
      91: invokevirtual #19                 // Method org/apache/pulsar/client/impl/conf/ClientConfigurationData.getTlsTrustStorePath:()Ljava/lang/String;
      94: aload_1
      95: invokevirtual #20                 // Method org/apache/pulsar/client/impl/conf/ClientConfigurationData.getTlsTrustStorePassword:()Ljava/lang/String;
      98: aload_1
      99: invokevirtual #21                 // Method org/apache/pulsar/client/impl/conf/ClientConfigurationData.getTlsCiphers:()Ljava/util/Set;
     102: aload_1
     103: invokevirtual #22                 // Method org/apache/pulsar/client/impl/conf/ClientConfigurationData.getTlsProtocols:()Ljava/util/Set;
     106: getstatic     #23                 // Field TLS_CERTIFICATE_CACHE_MILLIS:J
     109: aload_3
     110: invokespecial #24                 // Method org/apache/pulsar/common/util/keystoretls/NettySSLContextAutoRefreshBuilder."<init>":(Ljava/lang/String;ZLjava/lang/String;Ljava/lang/String;Ljava/lang/String;Ljava/util/Set;Ljava/util/Set;JLorg/apache/pulsar/client/api/AuthenticationDataProvider;)V
     113: putfield      #25                 // Field nettySSLContextAutoRefreshBuilder:Lorg/apache/pulsar/common/util/keystoretls/NettySSLContextAutoRefreshBuilder;
     116: aload_0
     117: new           #26                 // class org/apache/pulsar/client/util/ObjectCache
     120: dup
     121: aload_1
     122: invokedynamic #27,  0             // InvokeDynamic #0:get:(Lorg/apache/pulsar/client/impl/conf/ClientConfigurationData;)Ljava/util/function/Supplier;
     127: getstatic     #23                 // Field TLS_CERTIFICATE_CACHE_MILLIS:J
     130: getstatic     #28                 // Field java/util/concurrent/TimeUnit.MILLISECONDS:Ljava/util/concurrent/TimeUnit;
     133: invokespecial #29                 // Method org/apache/pulsar/client/util/ObjectCache."<init>":(Ljava/util/function/Supplier;JLjava/util/concurrent/TimeUnit;)V
     136: putfield      #30                 // Field sslContextSupplier:Ljava/util/function/Supplier;
     139: goto          147
     142: aload_0
     143: aconst_null
     144: putfield      #30                 // Field sslContextSupplier:Ljava/util/function/Supplier;
     147: return

  public void initChannel(io.netty.channel.socket.SocketChannel) throws java.lang.Exception;
    Code:
       0: aload_1
       1: invokeinterface #31,  1           // InterfaceMethod io/netty/channel/socket/SocketChannel.pipeline:()Lio/netty/channel/ChannelPipeline;
       6: ldc           #32                 // String ByteBufPairEncoder
       8: aload_0
       9: getfield      #4                  // Field tlsEnabled:Z
      12: ifeq          21
      15: getstatic     #33                 // Field org/apache/pulsar/common/protocol/ByteBufPair.COPYING_ENCODER:Lorg/apache/pulsar/common/protocol/ByteBufPair$CopyingEncoder;
      18: goto          24
      21: getstatic     #34                 // Field org/apache/pulsar/common/protocol/ByteBufPair.ENCODER:Lorg/apache/pulsar/common/protocol/ByteBufPair$Encoder;
      24: invokeinterface #35,  3           // InterfaceMethod io/netty/channel/ChannelPipeline.addLast:(Ljava/lang/String;Lio/netty/channel/ChannelHandler;)Lio/netty/channel/ChannelPipeline;
      29: pop
      30: aload_1
      31: invokeinterface #31,  1           // InterfaceMethod io/netty/channel/socket/SocketChannel.pipeline:()Lio/netty/channel/ChannelPipeline;
      36: ldc           #36                 // String frameDecoder
      38: new           #37                 // class io/netty/handler/codec/LengthFieldBasedFrameDecoder
      41: dup
      42: ldc           #39                 // int 5253120
      44: iconst_0
      45: iconst_4
      46: iconst_0
      47: iconst_4
      48: invokespecial #40                 // Method io/netty/handler/codec/LengthFieldBasedFrameDecoder."<init>":(IIIII)V
      51: invokeinterface #35,  3           // InterfaceMethod io/netty/channel/ChannelPipeline.addLast:(Ljava/lang/String;Lio/netty/channel/ChannelHandler;)Lio/netty/channel/ChannelPipeline;
      56: pop
      57: aload_1
      58: invokeinterface #31,  1           // InterfaceMethod io/netty/channel/socket/SocketChannel.pipeline:()Lio/netty/channel/ChannelPipeline;
      63: ldc           #41                 // String handler
      65: aload_0
      66: getfield      #2                  // Field clientCnxSupplier:Ljava/util/function/Supplier;
      69: invokeinterface #42,  1           // InterfaceMethod java/util/function/Supplier.get:()Ljava/lang/Object;
      74: checkcast     #43                 // class io/netty/channel/ChannelHandler
      77: invokeinterface #35,  3           // InterfaceMethod io/netty/channel/ChannelPipeline.addLast:(Ljava/lang/String;Lio/netty/channel/ChannelHandler;)Lio/netty/channel/ChannelPipeline;
      82: pop
      83: return

  java.util.concurrent.CompletableFuture<io.netty.channel.Channel> initTls(io.netty.channel.Channel, java.net.InetSocketAddress);
    Code:
       0: aload_1
       1: ldc           #44                 // String A channel is required
       3: invokestatic  #45                 // Method java/util/Objects.requireNonNull:(Ljava/lang/Object;Ljava/lang/String;)Ljava/lang/Object;
       6: pop
       7: aload_2
       8: ldc           #46                 // String A sniHost is required
      10: invokestatic  #45                 // Method java/util/Objects.requireNonNull:(Ljava/lang/Object;Ljava/lang/String;)Ljava/lang/Object;
      13: pop
      14: aload_0
      15: getfield      #4                  // Field tlsEnabled:Z
      18: ifne          31
      21: new           #47                 // class java/lang/IllegalStateException
      24: dup
      25: ldc           #48                 // String TLS is not enabled in client configuration
      27: invokespecial #49                 // Method java/lang/IllegalStateException."<init>":(Ljava/lang/String;)V
      30: athrow
      31: new           #50                 // class java/util/concurrent/CompletableFuture
      34: dup
      35: invokespecial #51                 // Method java/util/concurrent/CompletableFuture."<init>":()V
      38: astore_3
      39: aload_1
      40: invokeinterface #52,  1           // InterfaceMethod io/netty/channel/Channel.eventLoop:()Lio/netty/channel/EventLoop;
      45: aload_0
      46: aload_2
      47: aload_1
      48: aload_3
      49: invokedynamic #53,  0             // InvokeDynamic #1:run:(Lorg/apache/pulsar/client/impl/PulsarChannelInitializer;Ljava/net/InetSocketAddress;Lio/netty/channel/Channel;Ljava/util/concurrent/CompletableFuture;)Ljava/lang/Runnable;
      54: invokeinterface #54,  2           // InterfaceMethod io/netty/channel/EventLoop.execute:(Ljava/lang/Runnable;)V
      59: aload_3
      60: areturn

  java.util.concurrent.CompletableFuture<io.netty.channel.Channel> initSocks5IfConfig(io.netty.channel.Channel);
    Code:
       0: new           #50                 // class java/util/concurrent/CompletableFuture
       3: dup
       4: invokespecial #51                 // Method java/util/concurrent/CompletableFuture."<init>":()V
       7: astore_2
       8: aload_0
       9: getfield      #6                  // Field socks5ProxyAddress:Ljava/net/InetSocketAddress;
      12: ifnull        37
      15: aload_1
      16: invokeinterface #52,  1           // InterfaceMethod io/netty/channel/Channel.eventLoop:()Lio/netty/channel/EventLoop;
      21: aload_0
      22: aload_1
      23: aload_2
      24: invokedynamic #55,  0             // InvokeDynamic #2:run:(Lorg/apache/pulsar/client/impl/PulsarChannelInitializer;Lio/netty/channel/Channel;Ljava/util/concurrent/CompletableFuture;)Ljava/lang/Runnable;
      29: invokeinterface #54,  2           // InterfaceMethod io/netty/channel/EventLoop.execute:(Ljava/lang/Runnable;)V
      34: goto          43
      37: aload_2
      38: aload_1
      39: invokevirtual #56                 // Method java/util/concurrent/CompletableFuture.complete:(Ljava/lang/Object;)Z
      42: pop
      43: aload_2
      44: areturn

  public boolean isTlsEnabled();
    Code:
       0: aload_0
       1: getfield      #4                  // Field tlsEnabled:Z
       4: ireturn

  public void initChannel(io.netty.channel.Channel) throws java.lang.Exception;
    Code:
       0: aload_0
       1: aload_1
       2: checkcast     #57                 // class io/netty/channel/socket/SocketChannel
       5: invokevirtual #58                 // Method initChannel:(Lio/netty/channel/socket/SocketChannel;)V
       8: return

  private void lambda$initSocks5IfConfig$2(io.netty.channel.Channel, java.util.concurrent.CompletableFuture);
    Code:
       0: new           #59                 // class io/netty/handler/proxy/Socks5ProxyHandler
       3: dup
       4: aload_0
       5: getfield      #6                  // Field socks5ProxyAddress:Ljava/net/InetSocketAddress;
       8: aload_0
       9: getfield      #8                  // Field socks5ProxyUsername:Ljava/lang/String;
      12: aload_0
      13: getfield      #10                 // Field socks5ProxyPassword:Ljava/lang/String;
      16: invokespecial #60                 // Method io/netty/handler/proxy/Socks5ProxyHandler."<init>":(Ljava/net/SocketAddress;Ljava/lang/String;Ljava/lang/String;)V
      19: astore_3
      20: aload_1
      21: invokeinterface #61,  1           // InterfaceMethod io/netty/channel/Channel.pipeline:()Lio/netty/channel/ChannelPipeline;
      26: aload_3
      27: invokevirtual #62                 // Method io/netty/handler/proxy/Socks5ProxyHandler.protocol:()Ljava/lang/String;
      30: aload_3
      31: invokeinterface #63,  3           // InterfaceMethod io/netty/channel/ChannelPipeline.addFirst:(Ljava/lang/String;Lio/netty/channel/ChannelHandler;)Lio/netty/channel/ChannelPipeline;
      36: pop
      37: aload_2
      38: aload_1
      39: invokevirtual #56                 // Method java/util/concurrent/CompletableFuture.complete:(Ljava/lang/Object;)Z
      42: pop
      43: goto          53
      46: astore_3
      47: aload_2
      48: aload_3
      49: invokevirtual #65                 // Method java/util/concurrent/CompletableFuture.completeExceptionally:(Ljava/lang/Throwable;)Z
      52: pop
      53: return
    Exception table:
       from    to  target type
           0    43    46   Class java/lang/Throwable

  private void lambda$initTls$1(java.net.InetSocketAddress, io.netty.channel.Channel, java.util.concurrent.CompletableFuture);
    Code:
       0: aload_0
       1: getfield      #12                 // Field tlsEnabledWithKeyStore:Z
       4: ifeq          38
       7: new           #66                 // class io/netty/handler/ssl/SslHandler
      10: dup
      11: aload_0
      12: getfield      #25                 // Field nettySSLContextAutoRefreshBuilder:Lorg/apache/pulsar/common/util/keystoretls/NettySSLContextAutoRefreshBuilder;
      15: invokevirtual #67                 // Method org/apache/pulsar/common/util/keystoretls/NettySSLContextAutoRefreshBuilder.get:()Ljava/lang/Object;
      18: checkcast     #68                 // class org/apache/pulsar/common/util/keystoretls/KeyStoreSSLContext
      21: aload_1
      22: invokevirtual #69                 // Method java/net/InetSocketAddress.getHostString:()Ljava/lang/String;
      25: aload_1
      26: invokevirtual #70                 // Method java/net/InetSocketAddress.getPort:()I
      29: invokevirtual #71                 // Method org/apache/pulsar/common/util/keystoretls/KeyStoreSSLContext.createSSLEngine:(Ljava/lang/String;I)Ljavax/net/ssl/SSLEngine;
      32: invokespecial #72                 // Method io/netty/handler/ssl/SslHandler."<init>":(Ljavax/net/ssl/SSLEngine;)V
      35: goto          67
      38: aload_0
      39: getfield      #30                 // Field sslContextSupplier:Ljava/util/function/Supplier;
      42: invokeinterface #42,  1           // InterfaceMethod java/util/function/Supplier.get:()Ljava/lang/Object;
      47: checkcast     #73                 // class io/netty/handler/ssl/SslContext
      50: aload_2
      51: invokeinterface #74,  1           // InterfaceMethod io/netty/channel/Channel.alloc:()Lio/netty/buffer/ByteBufAllocator;
      56: aload_1
      57: invokevirtual #69                 // Method java/net/InetSocketAddress.getHostString:()Ljava/lang/String;
      60: aload_1
      61: invokevirtual #70                 // Method java/net/InetSocketAddress.getPort:()I
      64: invokevirtual #75                 // Method io/netty/handler/ssl/SslContext.newHandler:(Lio/netty/buffer/ByteBufAllocator;Ljava/lang/String;I)Lio/netty/handler/ssl/SslHandler;
      67: astore        4
      69: aload_2
      70: invokeinterface #61,  1           // InterfaceMethod io/netty/channel/Channel.pipeline:()Lio/netty/channel/ChannelPipeline;
      75: ldc           #77                 // String tls
      77: aload         4
      79: invokeinterface #63,  3           // InterfaceMethod io/netty/channel/ChannelPipeline.addFirst:(Ljava/lang/String;Lio/netty/channel/ChannelHandler;)Lio/netty/channel/ChannelPipeline;
      84: pop
      85: aload_3
      86: aload_2
      87: invokevirtual #56                 // Method java/util/concurrent/CompletableFuture.complete:(Ljava/lang/Object;)Z
      90: pop
      91: goto          103
      94: astore        4
      96: aload_3
      97: aload         4
      99: invokevirtual #65                 // Method java/util/concurrent/CompletableFuture.completeExceptionally:(Ljava/lang/Throwable;)Z
     102: pop
     103: return
    Exception table:
       from    to  target type
           0    91    94   Class java/lang/Throwable

  private static io.netty.handler.ssl.SslContext lambda$new$0(org.apache.pulsar.client.impl.conf.ClientConfigurationData);
    Code:
       0: aload_0
       1: invokevirtual #13                 // Method org/apache/pulsar/client/impl/conf/ClientConfigurationData.getAuthentication:()Lorg/apache/pulsar/client/api/Authentication;
       4: invokeinterface #14,  1           // InterfaceMethod org/apache/pulsar/client/api/Authentication.getAuthData:()Lorg/apache/pulsar/client/api/AuthenticationDataProvider;
       9: astore_1
      10: aload_1
      11: invokeinterface #78,  1           // InterfaceMethod org/apache/pulsar/client/api/AuthenticationDataProvider.hasDataForTls:()Z
      16: ifeq          80
      19: aload_1
      20: invokeinterface #79,  1           // InterfaceMethod org/apache/pulsar/client/api/AuthenticationDataProvider.getTlsTrustStoreStream:()Ljava/io/InputStream;
      25: ifnonnull     54
      28: aload_0
      29: invokevirtual #17                 // Method org/apache/pulsar/client/impl/conf/ClientConfigurationData.isTlsAllowInsecureConnection:()Z
      32: aload_0
      33: invokevirtual #80                 // Method org/apache/pulsar/client/impl/conf/ClientConfigurationData.getTlsTrustCertsFilePath:()Ljava/lang/String;
      36: aload_1
      37: invokeinterface #81,  1           // InterfaceMethod org/apache/pulsar/client/api/AuthenticationDataProvider.getTlsCertificates:()[Ljava/security/cert/Certificate;
      42: aload_1
      43: invokeinterface #82,  1           // InterfaceMethod org/apache/pulsar/client/api/AuthenticationDataProvider.getTlsPrivateKey:()Ljava/security/PrivateKey;
      48: invokestatic  #83                 // Method org/apache/pulsar/common/util/SecurityUtility.createNettySslContextForClient:(ZLjava/lang/String;[Ljava/security/cert/Certificate;Ljava/security/PrivateKey;)Lio/netty/handler/ssl/SslContext;
      51: goto          79
      54: aload_0
      55: invokevirtual #17                 // Method org/apache/pulsar/client/impl/conf/ClientConfigurationData.isTlsAllowInsecureConnection:()Z
      58: aload_1
      59: invokeinterface #79,  1           // InterfaceMethod org/apache/pulsar/client/api/AuthenticationDataProvider.getTlsTrustStoreStream:()Ljava/io/InputStream;
      64: aload_1
      65: invokeinterface #81,  1           // InterfaceMethod org/apache/pulsar/client/api/AuthenticationDataProvider.getTlsCertificates:()[Ljava/security/cert/Certificate;
      70: aload_1
      71: invokeinterface #82,  1           // InterfaceMethod org/apache/pulsar/client/api/AuthenticationDataProvider.getTlsPrivateKey:()Ljava/security/PrivateKey;
      76: invokestatic  #84                 // Method org/apache/pulsar/common/util/SecurityUtility.createNettySslContextForClient:(ZLjava/io/InputStream;[Ljava/security/cert/Certificate;Ljava/security/PrivateKey;)Lio/netty/handler/ssl/SslContext;
      79: areturn
      80: aload_0
      81: invokevirtual #17                 // Method org/apache/pulsar/client/impl/conf/ClientConfigurationData.isTlsAllowInsecureConnection:()Z
      84: aload_0
      85: invokevirtual #80                 // Method org/apache/pulsar/client/impl/conf/ClientConfigurationData.getTlsTrustCertsFilePath:()Ljava/lang/String;
      88: invokestatic  #85                 // Method org/apache/pulsar/common/util/SecurityUtility.createNettySslContextForClient:(ZLjava/lang/String;)Lio/netty/handler/ssl/SslContext;
      91: areturn
      92: astore_1
      93: new           #87                 // class java/lang/RuntimeException
      96: dup
      97: ldc           #88                 // String Failed to create TLS context
      99: aload_1
     100: invokespecial #89                 // Method java/lang/RuntimeException."<init>":(Ljava/lang/String;Ljava/lang/Throwable;)V
     103: athrow
    Exception table:
       from    to  target type
           0    79    92   Class java/lang/Exception
          80    91    92   Class java/lang/Exception

  static {};
    Code:
       0: ldc           #76                 // class org/apache/pulsar/client/impl/PulsarChannelInitializer
       2: invokestatic  #90                 // Method org/slf4j/LoggerFactory.getLogger:(Ljava/lang/Class;)Lorg/slf4j/Logger;
       5: putstatic     #91                 // Field log:Lorg/slf4j/Logger;
       8: getstatic     #92                 // Field java/util/concurrent/TimeUnit.MINUTES:Ljava/util/concurrent/TimeUnit;
      11: lconst_1
      12: invokevirtual #93                 // Method java/util/concurrent/TimeUnit.toMillis:(J)J
      15: putstatic     #23                 // Field TLS_CERTIFICATE_CACHE_MILLIS:J
      18: return
}
