Compiled from "TopicMessageImpl.java"
public class org.apache.pulsar.client.impl.TopicMessageImpl<T> implements org.apache.pulsar.client.api.Message<T> {
  private final java.lang.String topicPartitionName;

  private final org.apache.pulsar.client.api.Message<T> msg;

  private final org.apache.pulsar.client.impl.TopicMessageIdImpl messageId;

  final org.apache.pulsar.client.impl.ConsumerImpl receivedByconsumer;

  org.apache.pulsar.client.impl.TopicMessageImpl(java.lang.String, java.lang.String, org.apache.pulsar.client.api.Message<T>, org.apache.pulsar.client.impl.ConsumerImpl);
    Code:
       0: aload_0
       1: invokespecial #1                  // Method java/lang/Object."<init>":()V
       4: aload_0
       5: aload_1
       6: putfield      #2                  // Field topicPartitionName:Ljava/lang/String;
       9: aload_0
      10: aload         4
      12: putfield      #3                  // Field receivedByconsumer:Lorg/apache/pulsar/client/impl/ConsumerImpl;
      15: aload_0
      16: aload_3
      17: putfield      #4                  // Field msg:Lorg/apache/pulsar/client/api/Message;
      20: aload_0
      21: new           #5                  // class org/apache/pulsar/client/impl/TopicMessageIdImpl
      24: dup
      25: aload_1
      26: aload_2
      27: aload_3
      28: invokeinterface #6,  1            // InterfaceMethod org/apache/pulsar/client/api/Message.getMessageId:()Lorg/apache/pulsar/client/api/MessageId;
      33: invokespecial #7                  // Method org/apache/pulsar/client/impl/TopicMessageIdImpl."<init>":(Ljava/lang/String;Ljava/lang/String;Lorg/apache/pulsar/client/api/MessageId;)V
      36: putfield      #8                  // Field messageId:Lorg/apache/pulsar/client/impl/TopicMessageIdImpl;
      39: return

  public java.lang.String getTopicName();
    Code:
       0: aload_0
       1: getfield      #4                  // Field msg:Lorg/apache/pulsar/client/api/Message;
       4: invokeinterface #9,  1            // InterfaceMethod org/apache/pulsar/client/api/Message.getTopicName:()Ljava/lang/String;
       9: areturn

  public java.lang.String getTopicPartitionName();
    Code:
       0: aload_0
       1: getfield      #2                  // Field topicPartitionName:Ljava/lang/String;
       4: areturn

  public org.apache.pulsar.client.api.MessageId getMessageId();
    Code:
       0: aload_0
       1: getfield      #8                  // Field messageId:Lorg/apache/pulsar/client/impl/TopicMessageIdImpl;
       4: areturn

  public org.apache.pulsar.client.api.MessageId getInnerMessageId();
    Code:
       0: aload_0
       1: getfield      #8                  // Field messageId:Lorg/apache/pulsar/client/impl/TopicMessageIdImpl;
       4: invokevirtual #10                 // Method org/apache/pulsar/client/impl/TopicMessageIdImpl.getInnerMessageId:()Lorg/apache/pulsar/client/api/MessageId;
       7: areturn

  public java.util.Map<java.lang.String, java.lang.String> getProperties();
    Code:
       0: aload_0
       1: getfield      #4                  // Field msg:Lorg/apache/pulsar/client/api/Message;
       4: invokeinterface #11,  1           // InterfaceMethod org/apache/pulsar/client/api/Message.getProperties:()Ljava/util/Map;
       9: areturn

  public boolean hasProperty(java.lang.String);
    Code:
       0: aload_0
       1: getfield      #4                  // Field msg:Lorg/apache/pulsar/client/api/Message;
       4: aload_1
       5: invokeinterface #12,  2           // InterfaceMethod org/apache/pulsar/client/api/Message.hasProperty:(Ljava/lang/String;)Z
      10: ireturn

  public java.lang.String getProperty(java.lang.String);
    Code:
       0: aload_0
       1: getfield      #4                  // Field msg:Lorg/apache/pulsar/client/api/Message;
       4: aload_1
       5: invokeinterface #13,  2           // InterfaceMethod org/apache/pulsar/client/api/Message.getProperty:(Ljava/lang/String;)Ljava/lang/String;
      10: areturn

  public byte[] getData();
    Code:
       0: aload_0
       1: getfield      #4                  // Field msg:Lorg/apache/pulsar/client/api/Message;
       4: invokeinterface #14,  1           // InterfaceMethod org/apache/pulsar/client/api/Message.getData:()[B
       9: areturn

  public int size();
    Code:
       0: aload_0
       1: getfield      #4                  // Field msg:Lorg/apache/pulsar/client/api/Message;
       4: invokeinterface #15,  1           // InterfaceMethod org/apache/pulsar/client/api/Message.size:()I
       9: ireturn

  public long getPublishTime();
    Code:
       0: aload_0
       1: getfield      #4                  // Field msg:Lorg/apache/pulsar/client/api/Message;
       4: invokeinterface #16,  1           // InterfaceMethod org/apache/pulsar/client/api/Message.getPublishTime:()J
       9: lreturn

  public long getEventTime();
    Code:
       0: aload_0
       1: getfield      #4                  // Field msg:Lorg/apache/pulsar/client/api/Message;
       4: invokeinterface #17,  1           // InterfaceMethod org/apache/pulsar/client/api/Message.getEventTime:()J
       9: lreturn

  public long getSequenceId();
    Code:
       0: aload_0
       1: getfield      #4                  // Field msg:Lorg/apache/pulsar/client/api/Message;
       4: invokeinterface #18,  1           // InterfaceMethod org/apache/pulsar/client/api/Message.getSequenceId:()J
       9: lreturn

  public java.lang.String getProducerName();
    Code:
       0: aload_0
       1: getfield      #4                  // Field msg:Lorg/apache/pulsar/client/api/Message;
       4: invokeinterface #19,  1           // InterfaceMethod org/apache/pulsar/client/api/Message.getProducerName:()Ljava/lang/String;
       9: areturn

  public boolean hasKey();
    Code:
       0: aload_0
       1: getfield      #4                  // Field msg:Lorg/apache/pulsar/client/api/Message;
       4: invokeinterface #20,  1           // InterfaceMethod org/apache/pulsar/client/api/Message.hasKey:()Z
       9: ireturn

  public java.lang.String getKey();
    Code:
       0: aload_0
       1: getfield      #4                  // Field msg:Lorg/apache/pulsar/client/api/Message;
       4: invokeinterface #21,  1           // InterfaceMethod org/apache/pulsar/client/api/Message.getKey:()Ljava/lang/String;
       9: areturn

  public boolean hasBase64EncodedKey();
    Code:
       0: aload_0
       1: getfield      #4                  // Field msg:Lorg/apache/pulsar/client/api/Message;
       4: invokeinterface #22,  1           // InterfaceMethod org/apache/pulsar/client/api/Message.hasBase64EncodedKey:()Z
       9: ireturn

  public byte[] getKeyBytes();
    Code:
       0: aload_0
       1: getfield      #4                  // Field msg:Lorg/apache/pulsar/client/api/Message;
       4: invokeinterface #23,  1           // InterfaceMethod org/apache/pulsar/client/api/Message.getKeyBytes:()[B
       9: areturn

  public boolean hasOrderingKey();
    Code:
       0: aload_0
       1: getfield      #4                  // Field msg:Lorg/apache/pulsar/client/api/Message;
       4: invokeinterface #24,  1           // InterfaceMethod org/apache/pulsar/client/api/Message.hasOrderingKey:()Z
       9: ireturn

  public byte[] getOrderingKey();
    Code:
       0: aload_0
       1: getfield      #4                  // Field msg:Lorg/apache/pulsar/client/api/Message;
       4: invokeinterface #25,  1           // InterfaceMethod org/apache/pulsar/client/api/Message.getOrderingKey:()[B
       9: areturn

  public T getValue();
    Code:
       0: aload_0
       1: getfield      #4                  // Field msg:Lorg/apache/pulsar/client/api/Message;
       4: invokeinterface #26,  1           // InterfaceMethod org/apache/pulsar/client/api/Message.getValue:()Ljava/lang/Object;
       9: areturn

  public java.util.Optional<org.apache.pulsar.common.api.EncryptionContext> getEncryptionCtx();
    Code:
       0: aload_0
       1: getfield      #4                  // Field msg:Lorg/apache/pulsar/client/api/Message;
       4: invokeinterface #27,  1           // InterfaceMethod org/apache/pulsar/client/api/Message.getEncryptionCtx:()Ljava/util/Optional;
       9: areturn

  public int getRedeliveryCount();
    Code:
       0: aload_0
       1: getfield      #4                  // Field msg:Lorg/apache/pulsar/client/api/Message;
       4: invokeinterface #28,  1           // InterfaceMethod org/apache/pulsar/client/api/Message.getRedeliveryCount:()I
       9: ireturn

  public byte[] getSchemaVersion();
    Code:
       0: aload_0
       1: getfield      #4                  // Field msg:Lorg/apache/pulsar/client/api/Message;
       4: invokeinterface #29,  1           // InterfaceMethod org/apache/pulsar/client/api/Message.getSchemaVersion:()[B
       9: areturn

  public boolean isReplicated();
    Code:
       0: aload_0
       1: getfield      #4                  // Field msg:Lorg/apache/pulsar/client/api/Message;
       4: invokeinterface #30,  1           // InterfaceMethod org/apache/pulsar/client/api/Message.isReplicated:()Z
       9: ireturn

  public java.lang.String getReplicatedFrom();
    Code:
       0: aload_0
       1: getfield      #4                  // Field msg:Lorg/apache/pulsar/client/api/Message;
       4: invokeinterface #31,  1           // InterfaceMethod org/apache/pulsar/client/api/Message.getReplicatedFrom:()Ljava/lang/String;
       9: areturn

  public org.apache.pulsar.client.api.Message<T> getMessage();
    Code:
       0: aload_0
       1: getfield      #4                  // Field msg:Lorg/apache/pulsar/client/api/Message;
       4: areturn

  public org.apache.pulsar.client.api.Schema<T> getSchemaInternal();
    Code:
       0: aload_0
       1: getfield      #4                  // Field msg:Lorg/apache/pulsar/client/api/Message;
       4: instanceof    #32                 // class org/apache/pulsar/client/impl/MessageImpl
       7: ifeq          23
      10: aload_0
      11: getfield      #4                  // Field msg:Lorg/apache/pulsar/client/api/Message;
      14: checkcast     #32                 // class org/apache/pulsar/client/impl/MessageImpl
      17: astore_1
      18: aload_1
      19: invokevirtual #33                 // Method org/apache/pulsar/client/impl/MessageImpl.getSchemaInternal:()Lorg/apache/pulsar/client/api/Schema;
      22: areturn
      23: aconst_null
      24: areturn

  public java.util.Optional<org.apache.pulsar.client.api.Schema<?>> getReaderSchema();
    Code:
       0: aload_0
       1: getfield      #4                  // Field msg:Lorg/apache/pulsar/client/api/Message;
       4: invokeinterface #34,  1           // InterfaceMethod org/apache/pulsar/client/api/Message.getReaderSchema:()Ljava/util/Optional;
       9: areturn

  public void release();
    Code:
       0: aload_0
       1: getfield      #4                  // Field msg:Lorg/apache/pulsar/client/api/Message;
       4: invokeinterface #35,  1           // InterfaceMethod org/apache/pulsar/client/api/Message.release:()V
       9: return

  public boolean hasBrokerPublishTime();
    Code:
       0: aload_0
       1: getfield      #4                  // Field msg:Lorg/apache/pulsar/client/api/Message;
       4: invokeinterface #36,  1           // InterfaceMethod org/apache/pulsar/client/api/Message.hasBrokerPublishTime:()Z
       9: ireturn

  public java.util.Optional<java.lang.Long> getBrokerPublishTime();
    Code:
       0: aload_0
       1: getfield      #4                  // Field msg:Lorg/apache/pulsar/client/api/Message;
       4: invokeinterface #37,  1           // InterfaceMethod org/apache/pulsar/client/api/Message.getBrokerPublishTime:()Ljava/util/Optional;
       9: areturn

  public boolean hasIndex();
    Code:
       0: aload_0
       1: getfield      #4                  // Field msg:Lorg/apache/pulsar/client/api/Message;
       4: invokeinterface #38,  1           // InterfaceMethod org/apache/pulsar/client/api/Message.hasIndex:()Z
       9: ireturn

  public java.util.Optional<java.lang.Long> getIndex();
    Code:
       0: aload_0
       1: getfield      #4                  // Field msg:Lorg/apache/pulsar/client/api/Message;
       4: invokeinterface #39,  1           // InterfaceMethod org/apache/pulsar/client/api/Message.getIndex:()Ljava/util/Optional;
       9: areturn
}
