Compiled from "TransactionMetaStoreHandler.java"
public class org.apache.pulsar.client.impl.TransactionMetaStoreHandler extends org.apache.pulsar.client.impl.HandlerState implements org.apache.pulsar.client.impl.ConnectionHandler$Connection,java.io.Closeable,io.netty.util.TimerTask {
  private static final org.slf4j.Logger LOG;

  private final long transactionCoordinatorId;

  private final org.apache.pulsar.client.impl.ConnectionHandler connectionHandler;

  private final org.apache.pulsar.common.util.collections.ConcurrentLongHashMap<org.apache.pulsar.client.impl.TransactionMetaStoreHandler$OpBase<?>> pendingRequests;

  private final java.util.concurrent.ConcurrentLinkedQueue<org.apache.pulsar.client.impl.TransactionMetaStoreHandler$RequestTime> timeoutQueue;

  protected final io.netty.util.Timer timer;

  private final java.util.concurrent.ExecutorService internalPinnedExecutor;

  private final boolean blockIfReachMaxPendingOps;

  private final java.util.concurrent.Semaphore semaphore;

  private io.netty.util.Timeout requestTimeout;

  private final java.util.concurrent.CompletableFuture<java.lang.Void> connectFuture;

  public org.apache.pulsar.client.impl.TransactionMetaStoreHandler(long, org.apache.pulsar.client.impl.PulsarClientImpl, java.lang.String, java.util.concurrent.CompletableFuture<java.lang.Void>);
    Code:
       0: aload_0
       1: aload_3
       2: aload         4
       4: invokespecial #1                  // Method org/apache/pulsar/client/impl/HandlerState."<init>":(Lorg/apache/pulsar/client/impl/PulsarClientImpl;Ljava/lang/String;)V
       7: aload_0
       8: new           #2                  // class org/apache/pulsar/common/util/collections/ConcurrentLongHashMap
      11: dup
      12: bipush        16
      14: iconst_1
      15: invokespecial #3                  // Method org/apache/pulsar/common/util/collections/ConcurrentLongHashMap."<init>":(II)V
      18: putfield      #4                  // Field pendingRequests:Lorg/apache/pulsar/common/util/collections/ConcurrentLongHashMap;
      21: aload_0
      22: lload_1
      23: putfield      #5                  // Field transactionCoordinatorId:J
      26: aload_0
      27: new           #6                  // class java/util/concurrent/ConcurrentLinkedQueue
      30: dup
      31: invokespecial #7                  // Method java/util/concurrent/ConcurrentLinkedQueue."<init>":()V
      34: putfield      #8                  // Field timeoutQueue:Ljava/util/concurrent/ConcurrentLinkedQueue;
      37: aload_0
      38: iconst_1
      39: putfield      #9                  // Field blockIfReachMaxPendingOps:Z
      42: aload_0
      43: new           #10                 // class java/util/concurrent/Semaphore
      46: dup
      47: sipush        1000
      50: invokespecial #11                 // Method java/util/concurrent/Semaphore."<init>":(I)V
      53: putfield      #12                 // Field semaphore:Ljava/util/concurrent/Semaphore;
      56: aload_0
      57: aload_3
      58: invokevirtual #13                 // Method org/apache/pulsar/client/impl/PulsarClientImpl.timer:()Lio/netty/util/Timer;
      61: aload_0
      62: aload_3
      63: invokevirtual #14                 // Method org/apache/pulsar/client/impl/PulsarClientImpl.getConfiguration:()Lorg/apache/pulsar/client/impl/conf/ClientConfigurationData;
      66: invokevirtual #15                 // Method org/apache/pulsar/client/impl/conf/ClientConfigurationData.getOperationTimeoutMs:()J
      69: getstatic     #16                 // Field java/util/concurrent/TimeUnit.MILLISECONDS:Ljava/util/concurrent/TimeUnit;
      72: invokeinterface #17,  5           // InterfaceMethod io/netty/util/Timer.newTimeout:(Lio/netty/util/TimerTask;JLjava/util/concurrent/TimeUnit;)Lio/netty/util/Timeout;
      77: putfield      #18                 // Field requestTimeout:Lio/netty/util/Timeout;
      80: aload_0
      81: new           #19                 // class org/apache/pulsar/client/impl/ConnectionHandler
      84: dup
      85: aload_0
      86: new           #20                 // class org/apache/pulsar/client/impl/BackoffBuilder
      89: dup
      90: invokespecial #21                 // Method org/apache/pulsar/client/impl/BackoffBuilder."<init>":()V
      93: aload_3
      94: invokevirtual #14                 // Method org/apache/pulsar/client/impl/PulsarClientImpl.getConfiguration:()Lorg/apache/pulsar/client/impl/conf/ClientConfigurationData;
      97: invokevirtual #22                 // Method org/apache/pulsar/client/impl/conf/ClientConfigurationData.getInitialBackoffIntervalNanos:()J
     100: getstatic     #23                 // Field java/util/concurrent/TimeUnit.NANOSECONDS:Ljava/util/concurrent/TimeUnit;
     103: invokevirtual #24                 // Method org/apache/pulsar/client/impl/BackoffBuilder.setInitialTime:(JLjava/util/concurrent/TimeUnit;)Lorg/apache/pulsar/client/impl/BackoffBuilder;
     106: aload_3
     107: invokevirtual #14                 // Method org/apache/pulsar/client/impl/PulsarClientImpl.getConfiguration:()Lorg/apache/pulsar/client/impl/conf/ClientConfigurationData;
     110: invokevirtual #25                 // Method org/apache/pulsar/client/impl/conf/ClientConfigurationData.getMaxBackoffIntervalNanos:()J
     113: getstatic     #23                 // Field java/util/concurrent/TimeUnit.NANOSECONDS:Ljava/util/concurrent/TimeUnit;
     116: invokevirtual #26                 // Method org/apache/pulsar/client/impl/BackoffBuilder.setMax:(JLjava/util/concurrent/TimeUnit;)Lorg/apache/pulsar/client/impl/BackoffBuilder;
     119: ldc2_w        #27                 // long 100l
     122: getstatic     #16                 // Field java/util/concurrent/TimeUnit.MILLISECONDS:Ljava/util/concurrent/TimeUnit;
     125: invokevirtual #29                 // Method org/apache/pulsar/client/impl/BackoffBuilder.setMandatoryStop:(JLjava/util/concurrent/TimeUnit;)Lorg/apache/pulsar/client/impl/BackoffBuilder;
     128: invokevirtual #30                 // Method org/apache/pulsar/client/impl/BackoffBuilder.create:()Lorg/apache/pulsar/client/impl/Backoff;
     131: aload_0
     132: invokespecial #31                 // Method org/apache/pulsar/client/impl/ConnectionHandler."<init>":(Lorg/apache/pulsar/client/impl/HandlerState;Lorg/apache/pulsar/client/impl/Backoff;Lorg/apache/pulsar/client/impl/ConnectionHandler$Connection;)V
     135: putfield      #32                 // Field connectionHandler:Lorg/apache/pulsar/client/impl/ConnectionHandler;
     138: aload_0
     139: aload         5
     141: putfield      #33                 // Field connectFuture:Ljava/util/concurrent/CompletableFuture;
     144: aload_0
     145: getfield      #32                 // Field connectionHandler:Lorg/apache/pulsar/client/impl/ConnectionHandler;
     148: invokevirtual #34                 // Method org/apache/pulsar/client/impl/ConnectionHandler.grabCnx:()V
     151: aload_0
     152: aload_3
     153: invokevirtual #13                 // Method org/apache/pulsar/client/impl/PulsarClientImpl.timer:()Lio/netty/util/Timer;
     156: putfield      #35                 // Field timer:Lio/netty/util/Timer;
     159: aload_0
     160: aload_3
     161: invokevirtual #36                 // Method org/apache/pulsar/client/impl/PulsarClientImpl.getInternalExecutorService:()Ljava/util/concurrent/ExecutorService;
     164: putfield      #37                 // Field internalPinnedExecutor:Ljava/util/concurrent/ExecutorService;
     167: return

  public void connectionFailed(org.apache.pulsar.client.api.PulsarClientException);
    Code:
       0: getstatic     #38                 // Field LOG:Lorg/slf4j/Logger;
       3: ldc           #39                 // String Transaction meta handler with transaction coordinator id {} connection failed.
       5: aload_0
       6: getfield      #5                  // Field transactionCoordinatorId:J
       9: invokestatic  #40                 // Method java/lang/Long.valueOf:(J)Ljava/lang/Long;
      12: aload_1
      13: invokeinterface #41,  4           // InterfaceMethod org/slf4j/Logger.error:(Ljava/lang/String;Ljava/lang/Object;Ljava/lang/Object;)V
      18: aload_0
      19: getfield      #33                 // Field connectFuture:Ljava/util/concurrent/CompletableFuture;
      22: invokevirtual #42                 // Method java/util/concurrent/CompletableFuture.isDone:()Z
      25: ifne          37
      28: aload_0
      29: getfield      #33                 // Field connectFuture:Ljava/util/concurrent/CompletableFuture;
      32: aload_1
      33: invokevirtual #43                 // Method java/util/concurrent/CompletableFuture.completeExceptionally:(Ljava/lang/Throwable;)Z
      36: pop
      37: return

  public void connectionOpened(org.apache.pulsar.client.impl.ClientCnx);
    Code:
       0: aload_0
       1: getfield      #37                 // Field internalPinnedExecutor:Ljava/util/concurrent/ExecutorService;
       4: aload_0
       5: aload_1
       6: invokedynamic #44,  0             // InvokeDynamic #0:run:(Lorg/apache/pulsar/client/impl/TransactionMetaStoreHandler;Lorg/apache/pulsar/client/impl/ClientCnx;)Ljava/lang/Runnable;
      11: invokeinterface #45,  2           // InterfaceMethod java/util/concurrent/ExecutorService.execute:(Ljava/lang/Runnable;)V
      16: return

  private void failPendingRequest();
    Code:
       0: aload_0
       1: getfield      #4                  // Field pendingRequests:Lorg/apache/pulsar/common/util/collections/ConcurrentLongHashMap;
       4: aload_0
       5: invokedynamic #46,  0             // InvokeDynamic #1:accept:(Lorg/apache/pulsar/client/impl/TransactionMetaStoreHandler;)Lorg/apache/pulsar/common/util/collections/ConcurrentLongHashMap$EntryProcessor;
      10: invokevirtual #47                 // Method org/apache/pulsar/common/util/collections/ConcurrentLongHashMap.forEach:(Lorg/apache/pulsar/common/util/collections/ConcurrentLongHashMap$EntryProcessor;)V
      13: aload_0
      14: getfield      #4                  // Field pendingRequests:Lorg/apache/pulsar/common/util/collections/ConcurrentLongHashMap;
      17: invokevirtual #48                 // Method org/apache/pulsar/common/util/collections/ConcurrentLongHashMap.clear:()V
      20: return

  public java.util.concurrent.CompletableFuture<org.apache.pulsar.client.api.transaction.TxnID> newTransactionAsync(long, java.util.concurrent.TimeUnit);
    Code:
       0: getstatic     #38                 // Field LOG:Lorg/slf4j/Logger;
       3: invokeinterface #49,  1           // InterfaceMethod org/slf4j/Logger.isDebugEnabled:()Z
       8: ifeq          29
      11: getstatic     #38                 // Field LOG:Lorg/slf4j/Logger;
      14: ldc           #50                 // String New transaction with timeout in ms {}
      16: aload_3
      17: lload_1
      18: invokevirtual #51                 // Method java/util/concurrent/TimeUnit.toMillis:(J)J
      21: invokestatic  #40                 // Method java/lang/Long.valueOf:(J)Ljava/lang/Long;
      24: invokeinterface #52,  3           // InterfaceMethod org/slf4j/Logger.debug:(Ljava/lang/String;Ljava/lang/Object;)V
      29: new           #53                 // class java/util/concurrent/CompletableFuture
      32: dup
      33: invokespecial #54                 // Method java/util/concurrent/CompletableFuture."<init>":()V
      36: astore        4
      38: aload_0
      39: aload         4
      41: invokespecial #55                 // Method canSendRequest:(Ljava/util/concurrent/CompletableFuture;)Z
      44: ifne          50
      47: aload         4
      49: areturn
      50: aload_0
      51: getfield      #56                 // Field client:Lorg/apache/pulsar/client/impl/PulsarClientImpl;
      54: invokevirtual #57                 // Method org/apache/pulsar/client/impl/PulsarClientImpl.newRequestId:()J
      57: lstore        5
      59: aload_0
      60: getfield      #5                  // Field transactionCoordinatorId:J
      63: lload         5
      65: aload_3
      66: lload_1
      67: invokevirtual #51                 // Method java/util/concurrent/TimeUnit.toMillis:(J)J
      70: invokestatic  #58                 // Method org/apache/pulsar/common/protocol/Commands.newTxn:(JJJ)Lio/netty/buffer/ByteBuf;
      73: astore        7
      75: aload         7
      77: aload         4
      79: aload_0
      80: getfield      #56                 // Field client:Lorg/apache/pulsar/client/impl/PulsarClientImpl;
      83: invokestatic  #59                 // Method org/apache/pulsar/client/impl/TransactionMetaStoreHandler$OpForTxnIdCallBack.create:(Lio/netty/buffer/ByteBuf;Ljava/util/concurrent/CompletableFuture;Lorg/apache/pulsar/client/impl/PulsarClientImpl;)Lorg/apache/pulsar/client/impl/TransactionMetaStoreHandler$OpForTxnIdCallBack;
      86: astore        8
      88: aload_0
      89: getfield      #37                 // Field internalPinnedExecutor:Ljava/util/concurrent/ExecutorService;
      92: aload_0
      93: lload         5
      95: aload         8
      97: invokedynamic #60,  0             // InvokeDynamic #2:run:(Lorg/apache/pulsar/client/impl/TransactionMetaStoreHandler;JLorg/apache/pulsar/client/impl/TransactionMetaStoreHandler$OpForTxnIdCallBack;)Ljava/lang/Runnable;
     102: invokeinterface #45,  2           // InterfaceMethod java/util/concurrent/ExecutorService.execute:(Ljava/lang/Runnable;)V
     107: aload         4
     109: areturn

  void handleNewTxnResponse(org.apache.pulsar.common.api.proto.CommandNewTxnResponse);
    Code:
       0: aload_1
       1: invokevirtual #61                 // Method org/apache/pulsar/common/api/proto/CommandNewTxnResponse.hasError:()Z
       4: istore_2
       5: iload_2
       6: ifeq          23
       9: aload_1
      10: invokevirtual #62                 // Method org/apache/pulsar/common/api/proto/CommandNewTxnResponse.getError:()Lorg/apache/pulsar/common/api/proto/ServerError;
      13: astore_3
      14: aload_1
      15: invokevirtual #63                 // Method org/apache/pulsar/common/api/proto/CommandNewTxnResponse.getMessage:()Ljava/lang/String;
      18: astore        4
      20: goto          28
      23: aconst_null
      24: astore_3
      25: aconst_null
      26: astore        4
      28: new           #64                 // class org/apache/pulsar/client/api/transaction/TxnID
      31: dup
      32: aload_1
      33: invokevirtual #65                 // Method org/apache/pulsar/common/api/proto/CommandNewTxnResponse.getTxnidMostBits:()J
      36: aload_1
      37: invokevirtual #66                 // Method org/apache/pulsar/common/api/proto/CommandNewTxnResponse.getTxnidLeastBits:()J
      40: invokespecial #67                 // Method org/apache/pulsar/client/api/transaction/TxnID."<init>":(JJ)V
      43: astore        5
      45: aload_1
      46: invokevirtual #68                 // Method org/apache/pulsar/common/api/proto/CommandNewTxnResponse.getRequestId:()J
      49: lstore        6
      51: aload_0
      52: getfield      #37                 // Field internalPinnedExecutor:Ljava/util/concurrent/ExecutorService;
      55: aload_0
      56: lload         6
      58: aload         5
      60: iload_2
      61: aload_3
      62: aload         4
      64: invokedynamic #69,  0             // InvokeDynamic #3:run:(Lorg/apache/pulsar/client/impl/TransactionMetaStoreHandler;JLorg/apache/pulsar/client/api/transaction/TxnID;ZLorg/apache/pulsar/common/api/proto/ServerError;Ljava/lang/String;)Ljava/lang/Runnable;
      69: invokeinterface #45,  2           // InterfaceMethod java/util/concurrent/ExecutorService.execute:(Ljava/lang/Runnable;)V
      74: return

  public java.util.concurrent.CompletableFuture<java.lang.Void> addPublishPartitionToTxnAsync(org.apache.pulsar.client.api.transaction.TxnID, java.util.List<java.lang.String>);
    Code:
       0: getstatic     #38                 // Field LOG:Lorg/slf4j/Logger;
       3: invokeinterface #49,  1           // InterfaceMethod org/slf4j/Logger.isDebugEnabled:()Z
       8: ifeq          23
      11: getstatic     #38                 // Field LOG:Lorg/slf4j/Logger;
      14: ldc           #70                 // String Add publish partition {} to txn {}
      16: aload_2
      17: aload_1
      18: invokeinterface #71,  4           // InterfaceMethod org/slf4j/Logger.debug:(Ljava/lang/String;Ljava/lang/Object;Ljava/lang/Object;)V
      23: new           #53                 // class java/util/concurrent/CompletableFuture
      26: dup
      27: invokespecial #54                 // Method java/util/concurrent/CompletableFuture."<init>":()V
      30: astore_3
      31: aload_0
      32: aload_3
      33: invokespecial #55                 // Method canSendRequest:(Ljava/util/concurrent/CompletableFuture;)Z
      36: ifne          41
      39: aload_3
      40: areturn
      41: aload_0
      42: getfield      #56                 // Field client:Lorg/apache/pulsar/client/impl/PulsarClientImpl;
      45: invokevirtual #57                 // Method org/apache/pulsar/client/impl/PulsarClientImpl.newRequestId:()J
      48: lstore        4
      50: lload         4
      52: aload_1
      53: invokevirtual #72                 // Method org/apache/pulsar/client/api/transaction/TxnID.getLeastSigBits:()J
      56: aload_1
      57: invokevirtual #73                 // Method org/apache/pulsar/client/api/transaction/TxnID.getMostSigBits:()J
      60: aload_2
      61: invokestatic  #74                 // Method org/apache/pulsar/common/protocol/Commands.newAddPartitionToTxn:(JJJLjava/util/List;)Lio/netty/buffer/ByteBuf;
      64: astore        6
      66: aload         6
      68: aload_3
      69: aload_0
      70: getfield      #56                 // Field client:Lorg/apache/pulsar/client/impl/PulsarClientImpl;
      73: invokestatic  #75                 // Method org/apache/pulsar/client/impl/TransactionMetaStoreHandler$OpForVoidCallBack.create:(Lio/netty/buffer/ByteBuf;Ljava/util/concurrent/CompletableFuture;Lorg/apache/pulsar/client/impl/PulsarClientImpl;)Lorg/apache/pulsar/client/impl/TransactionMetaStoreHandler$OpForVoidCallBack;
      76: astore        7
      78: aload_0
      79: getfield      #37                 // Field internalPinnedExecutor:Ljava/util/concurrent/ExecutorService;
      82: aload_0
      83: lload         4
      85: aload         7
      87: invokedynamic #76,  0             // InvokeDynamic #4:run:(Lorg/apache/pulsar/client/impl/TransactionMetaStoreHandler;JLorg/apache/pulsar/client/impl/TransactionMetaStoreHandler$OpForVoidCallBack;)Ljava/lang/Runnable;
      92: invokeinterface #45,  2           // InterfaceMethod java/util/concurrent/ExecutorService.execute:(Ljava/lang/Runnable;)V
      97: aload_3
      98: areturn

  void handleAddPublishPartitionToTxnResponse(org.apache.pulsar.common.api.proto.CommandAddPartitionToTxnResponse);
    Code:
       0: aload_1
       1: invokevirtual #77                 // Method org/apache/pulsar/common/api/proto/CommandAddPartitionToTxnResponse.hasError:()Z
       4: istore_2
       5: iload_2
       6: ifeq          23
       9: aload_1
      10: invokevirtual #78                 // Method org/apache/pulsar/common/api/proto/CommandAddPartitionToTxnResponse.getError:()Lorg/apache/pulsar/common/api/proto/ServerError;
      13: astore_3
      14: aload_1
      15: invokevirtual #79                 // Method org/apache/pulsar/common/api/proto/CommandAddPartitionToTxnResponse.getMessage:()Ljava/lang/String;
      18: astore        4
      20: goto          28
      23: aconst_null
      24: astore_3
      25: aconst_null
      26: astore        4
      28: new           #64                 // class org/apache/pulsar/client/api/transaction/TxnID
      31: dup
      32: aload_1
      33: invokevirtual #80                 // Method org/apache/pulsar/common/api/proto/CommandAddPartitionToTxnResponse.getTxnidMostBits:()J
      36: aload_1
      37: invokevirtual #81                 // Method org/apache/pulsar/common/api/proto/CommandAddPartitionToTxnResponse.getTxnidLeastBits:()J
      40: invokespecial #67                 // Method org/apache/pulsar/client/api/transaction/TxnID."<init>":(JJ)V
      43: astore        5
      45: aload_1
      46: invokevirtual #82                 // Method org/apache/pulsar/common/api/proto/CommandAddPartitionToTxnResponse.getRequestId:()J
      49: lstore        6
      51: aload_0
      52: getfield      #37                 // Field internalPinnedExecutor:Ljava/util/concurrent/ExecutorService;
      55: aload_0
      56: lload         6
      58: aload         5
      60: iload_2
      61: aload_3
      62: aload         4
      64: invokedynamic #83,  0             // InvokeDynamic #5:run:(Lorg/apache/pulsar/client/impl/TransactionMetaStoreHandler;JLorg/apache/pulsar/client/api/transaction/TxnID;ZLorg/apache/pulsar/common/api/proto/ServerError;Ljava/lang/String;)Ljava/lang/Runnable;
      69: invokeinterface #45,  2           // InterfaceMethod java/util/concurrent/ExecutorService.execute:(Ljava/lang/Runnable;)V
      74: return

  public java.util.concurrent.CompletableFuture<java.lang.Void> addSubscriptionToTxn(org.apache.pulsar.client.api.transaction.TxnID, java.util.List<org.apache.pulsar.common.api.proto.Subscription>);
    Code:
       0: getstatic     #38                 // Field LOG:Lorg/slf4j/Logger;
       3: invokeinterface #49,  1           // InterfaceMethod org/slf4j/Logger.isDebugEnabled:()Z
       8: ifeq          23
      11: getstatic     #38                 // Field LOG:Lorg/slf4j/Logger;
      14: ldc           #84                 // String Add subscription {} to txn {}.
      16: aload_2
      17: aload_1
      18: invokeinterface #71,  4           // InterfaceMethod org/slf4j/Logger.debug:(Ljava/lang/String;Ljava/lang/Object;Ljava/lang/Object;)V
      23: new           #53                 // class java/util/concurrent/CompletableFuture
      26: dup
      27: invokespecial #54                 // Method java/util/concurrent/CompletableFuture."<init>":()V
      30: astore_3
      31: aload_0
      32: aload_3
      33: invokespecial #55                 // Method canSendRequest:(Ljava/util/concurrent/CompletableFuture;)Z
      36: ifne          41
      39: aload_3
      40: areturn
      41: aload_0
      42: getfield      #56                 // Field client:Lorg/apache/pulsar/client/impl/PulsarClientImpl;
      45: invokevirtual #57                 // Method org/apache/pulsar/client/impl/PulsarClientImpl.newRequestId:()J
      48: lstore        4
      50: lload         4
      52: aload_1
      53: invokevirtual #72                 // Method org/apache/pulsar/client/api/transaction/TxnID.getLeastSigBits:()J
      56: aload_1
      57: invokevirtual #73                 // Method org/apache/pulsar/client/api/transaction/TxnID.getMostSigBits:()J
      60: aload_2
      61: invokestatic  #85                 // Method org/apache/pulsar/common/protocol/Commands.newAddSubscriptionToTxn:(JJJLjava/util/List;)Lio/netty/buffer/ByteBuf;
      64: astore        6
      66: aload         6
      68: aload_3
      69: aload_0
      70: getfield      #56                 // Field client:Lorg/apache/pulsar/client/impl/PulsarClientImpl;
      73: invokestatic  #75                 // Method org/apache/pulsar/client/impl/TransactionMetaStoreHandler$OpForVoidCallBack.create:(Lio/netty/buffer/ByteBuf;Ljava/util/concurrent/CompletableFuture;Lorg/apache/pulsar/client/impl/PulsarClientImpl;)Lorg/apache/pulsar/client/impl/TransactionMetaStoreHandler$OpForVoidCallBack;
      76: astore        7
      78: aload_0
      79: getfield      #37                 // Field internalPinnedExecutor:Ljava/util/concurrent/ExecutorService;
      82: aload_0
      83: lload         4
      85: aload         7
      87: invokedynamic #86,  0             // InvokeDynamic #6:run:(Lorg/apache/pulsar/client/impl/TransactionMetaStoreHandler;JLorg/apache/pulsar/client/impl/TransactionMetaStoreHandler$OpForVoidCallBack;)Ljava/lang/Runnable;
      92: invokeinterface #45,  2           // InterfaceMethod java/util/concurrent/ExecutorService.execute:(Ljava/lang/Runnable;)V
      97: aload_3
      98: areturn

  public void handleAddSubscriptionToTxnResponse(org.apache.pulsar.common.api.proto.CommandAddSubscriptionToTxnResponse);
    Code:
       0: aload_1
       1: invokevirtual #87                 // Method org/apache/pulsar/common/api/proto/CommandAddSubscriptionToTxnResponse.hasError:()Z
       4: istore_2
       5: iload_2
       6: ifeq          23
       9: aload_1
      10: invokevirtual #88                 // Method org/apache/pulsar/common/api/proto/CommandAddSubscriptionToTxnResponse.getError:()Lorg/apache/pulsar/common/api/proto/ServerError;
      13: astore_3
      14: aload_1
      15: invokevirtual #89                 // Method org/apache/pulsar/common/api/proto/CommandAddSubscriptionToTxnResponse.getMessage:()Ljava/lang/String;
      18: astore        4
      20: goto          28
      23: aconst_null
      24: astore_3
      25: aconst_null
      26: astore        4
      28: aload_1
      29: invokevirtual #90                 // Method org/apache/pulsar/common/api/proto/CommandAddSubscriptionToTxnResponse.getRequestId:()J
      32: lstore        5
      34: aload_0
      35: getfield      #37                 // Field internalPinnedExecutor:Ljava/util/concurrent/ExecutorService;
      38: aload_0
      39: lload         5
      41: iload_2
      42: aload_3
      43: aload         4
      45: invokedynamic #91,  0             // InvokeDynamic #7:run:(Lorg/apache/pulsar/client/impl/TransactionMetaStoreHandler;JZLorg/apache/pulsar/common/api/proto/ServerError;Ljava/lang/String;)Ljava/lang/Runnable;
      50: invokeinterface #45,  2           // InterfaceMethod java/util/concurrent/ExecutorService.execute:(Ljava/lang/Runnable;)V
      55: return

  public java.util.concurrent.CompletableFuture<java.lang.Void> endTxnAsync(org.apache.pulsar.client.api.transaction.TxnID, org.apache.pulsar.common.api.proto.TxnAction);
    Code:
       0: getstatic     #38                 // Field LOG:Lorg/slf4j/Logger;
       3: invokeinterface #49,  1           // InterfaceMethod org/slf4j/Logger.isDebugEnabled:()Z
       8: ifeq          23
      11: getstatic     #38                 // Field LOG:Lorg/slf4j/Logger;
      14: ldc           #92                 // String End txn {}, action {}
      16: aload_1
      17: aload_2
      18: invokeinterface #71,  4           // InterfaceMethod org/slf4j/Logger.debug:(Ljava/lang/String;Ljava/lang/Object;Ljava/lang/Object;)V
      23: new           #53                 // class java/util/concurrent/CompletableFuture
      26: dup
      27: invokespecial #54                 // Method java/util/concurrent/CompletableFuture."<init>":()V
      30: astore_3
      31: aload_0
      32: aload_3
      33: invokespecial #55                 // Method canSendRequest:(Ljava/util/concurrent/CompletableFuture;)Z
      36: ifne          41
      39: aload_3
      40: areturn
      41: aload_0
      42: getfield      #56                 // Field client:Lorg/apache/pulsar/client/impl/PulsarClientImpl;
      45: invokevirtual #57                 // Method org/apache/pulsar/client/impl/PulsarClientImpl.newRequestId:()J
      48: lstore        4
      50: lload         4
      52: aload_1
      53: invokevirtual #72                 // Method org/apache/pulsar/client/api/transaction/TxnID.getLeastSigBits:()J
      56: aload_1
      57: invokevirtual #73                 // Method org/apache/pulsar/client/api/transaction/TxnID.getMostSigBits:()J
      60: aload_2
      61: invokestatic  #93                 // Method org/apache/pulsar/common/protocol/Commands.newEndTxn:(JJJLorg/apache/pulsar/common/api/proto/TxnAction;)Lorg/apache/pulsar/common/api/proto/BaseCommand;
      64: astore        6
      66: aload         6
      68: invokestatic  #94                 // Method org/apache/pulsar/common/protocol/Commands.serializeWithSize:(Lorg/apache/pulsar/common/api/proto/BaseCommand;)Lio/netty/buffer/ByteBuf;
      71: astore        7
      73: aload         7
      75: aload_3
      76: aload_0
      77: getfield      #56                 // Field client:Lorg/apache/pulsar/client/impl/PulsarClientImpl;
      80: invokestatic  #75                 // Method org/apache/pulsar/client/impl/TransactionMetaStoreHandler$OpForVoidCallBack.create:(Lio/netty/buffer/ByteBuf;Ljava/util/concurrent/CompletableFuture;Lorg/apache/pulsar/client/impl/PulsarClientImpl;)Lorg/apache/pulsar/client/impl/TransactionMetaStoreHandler$OpForVoidCallBack;
      83: astore        8
      85: aload_0
      86: getfield      #37                 // Field internalPinnedExecutor:Ljava/util/concurrent/ExecutorService;
      89: aload_0
      90: lload         4
      92: aload         8
      94: invokedynamic #95,  0             // InvokeDynamic #8:run:(Lorg/apache/pulsar/client/impl/TransactionMetaStoreHandler;JLorg/apache/pulsar/client/impl/TransactionMetaStoreHandler$OpForVoidCallBack;)Ljava/lang/Runnable;
      99: invokeinterface #45,  2           // InterfaceMethod java/util/concurrent/ExecutorService.execute:(Ljava/lang/Runnable;)V
     104: aload_3
     105: areturn

  void handleEndTxnResponse(org.apache.pulsar.common.api.proto.CommandEndTxnResponse);
    Code:
       0: aload_1
       1: invokevirtual #96                 // Method org/apache/pulsar/common/api/proto/CommandEndTxnResponse.hasError:()Z
       4: istore_2
       5: iload_2
       6: ifeq          23
       9: aload_1
      10: invokevirtual #97                 // Method org/apache/pulsar/common/api/proto/CommandEndTxnResponse.getError:()Lorg/apache/pulsar/common/api/proto/ServerError;
      13: astore_3
      14: aload_1
      15: invokevirtual #98                 // Method org/apache/pulsar/common/api/proto/CommandEndTxnResponse.getMessage:()Ljava/lang/String;
      18: astore        4
      20: goto          28
      23: aconst_null
      24: astore_3
      25: aconst_null
      26: astore        4
      28: new           #64                 // class org/apache/pulsar/client/api/transaction/TxnID
      31: dup
      32: aload_1
      33: invokevirtual #99                 // Method org/apache/pulsar/common/api/proto/CommandEndTxnResponse.getTxnidMostBits:()J
      36: aload_1
      37: invokevirtual #100                // Method org/apache/pulsar/common/api/proto/CommandEndTxnResponse.getTxnidLeastBits:()J
      40: invokespecial #67                 // Method org/apache/pulsar/client/api/transaction/TxnID."<init>":(JJ)V
      43: astore        5
      45: aload_1
      46: invokevirtual #101                // Method org/apache/pulsar/common/api/proto/CommandEndTxnResponse.getRequestId:()J
      49: lstore        6
      51: aload_0
      52: getfield      #37                 // Field internalPinnedExecutor:Ljava/util/concurrent/ExecutorService;
      55: aload_0
      56: lload         6
      58: aload         5
      60: iload_2
      61: aload_3
      62: aload         4
      64: invokedynamic #102,  0            // InvokeDynamic #9:run:(Lorg/apache/pulsar/client/impl/TransactionMetaStoreHandler;JLorg/apache/pulsar/client/api/transaction/TxnID;ZLorg/apache/pulsar/common/api/proto/ServerError;Ljava/lang/String;)Ljava/lang/Runnable;
      69: invokeinterface #45,  2           // InterfaceMethod java/util/concurrent/ExecutorService.execute:(Ljava/lang/Runnable;)V
      74: return

  private boolean checkIfNeedRetryByError(org.apache.pulsar.common.api.proto.ServerError, java.lang.String, org.apache.pulsar.client.impl.TransactionMetaStoreHandler$OpBase<?>);
    Code:
       0: aload_1
       1: getstatic     #103                // Field org/apache/pulsar/common/api/proto/ServerError.TransactionCoordinatorNotFound:Lorg/apache/pulsar/common/api/proto/ServerError;
       4: if_acmpne     34
       7: aload_0
       8: invokevirtual #104                // Method getState:()Lorg/apache/pulsar/client/impl/HandlerState$State;
      11: getstatic     #105                // Field org/apache/pulsar/client/impl/HandlerState$State.Connecting:Lorg/apache/pulsar/client/impl/HandlerState$State;
      14: if_acmpeq     32
      17: aload_0
      18: getfield      #32                 // Field connectionHandler:Lorg/apache/pulsar/client/impl/ConnectionHandler;
      21: new           #106                // class org/apache/pulsar/client/api/transaction/TransactionCoordinatorClientException$CoordinatorNotFoundException
      24: dup
      25: aload_2
      26: invokespecial #107                // Method org/apache/pulsar/client/api/transaction/TransactionCoordinatorClientException$CoordinatorNotFoundException."<init>":(Ljava/lang/String;)V
      29: invokevirtual #108                // Method org/apache/pulsar/client/impl/ConnectionHandler.reconnectLater:(Ljava/lang/Throwable;)V
      32: iconst_1
      33: ireturn
      34: aload_3
      35: ifnull        51
      38: aload_3
      39: getfield      #109                // Field org/apache/pulsar/client/impl/TransactionMetaStoreHandler$OpBase.callback:Ljava/util/concurrent/CompletableFuture;
      42: aload_1
      43: aload_2
      44: invokestatic  #110                // Method getExceptionByServerError:(Lorg/apache/pulsar/common/api/proto/ServerError;Ljava/lang/String;)Lorg/apache/pulsar/client/api/transaction/TransactionCoordinatorClientException;
      47: invokevirtual #43                 // Method java/util/concurrent/CompletableFuture.completeExceptionally:(Ljava/lang/Throwable;)Z
      50: pop
      51: iconst_0
      52: ireturn

  public static org.apache.pulsar.client.api.transaction.TransactionCoordinatorClientException getExceptionByServerError(org.apache.pulsar.common.api.proto.ServerError, java.lang.String);
    Code:
       0: getstatic     #111                // Field org/apache/pulsar/client/impl/TransactionMetaStoreHandler$1.$SwitchMap$org$apache$pulsar$common$api$proto$ServerError:[I
       3: aload_0
       4: invokevirtual #112                // Method org/apache/pulsar/common/api/proto/ServerError.ordinal:()I
       7: iaload
       8: tableswitch   { // 1 to 3
                     1: 36
                     2: 45
                     3: 54
               default: 63
          }
      36: new           #106                // class org/apache/pulsar/client/api/transaction/TransactionCoordinatorClientException$CoordinatorNotFoundException
      39: dup
      40: aload_1
      41: invokespecial #107                // Method org/apache/pulsar/client/api/transaction/TransactionCoordinatorClientException$CoordinatorNotFoundException."<init>":(Ljava/lang/String;)V
      44: areturn
      45: new           #113                // class org/apache/pulsar/client/api/transaction/TransactionCoordinatorClientException$InvalidTxnStatusException
      48: dup
      49: aload_1
      50: invokespecial #114                // Method org/apache/pulsar/client/api/transaction/TransactionCoordinatorClientException$InvalidTxnStatusException."<init>":(Ljava/lang/String;)V
      53: areturn
      54: new           #115                // class org/apache/pulsar/client/api/transaction/TransactionCoordinatorClientException$TransactionNotFoundException
      57: dup
      58: aload_1
      59: invokespecial #116                // Method org/apache/pulsar/client/api/transaction/TransactionCoordinatorClientException$TransactionNotFoundException."<init>":(Ljava/lang/String;)V
      62: areturn
      63: new           #117                // class org/apache/pulsar/client/api/transaction/TransactionCoordinatorClientException
      66: dup
      67: aload_1
      68: invokespecial #118                // Method org/apache/pulsar/client/api/transaction/TransactionCoordinatorClientException."<init>":(Ljava/lang/String;)V
      71: areturn

  private void onResponse(org.apache.pulsar.client.impl.TransactionMetaStoreHandler$OpBase<?>);
    Code:
       0: aload_1
       1: getfield      #119                // Field org/apache/pulsar/client/impl/TransactionMetaStoreHandler$OpBase.cmd:Lio/netty/buffer/ByteBuf;
       4: invokestatic  #120                // Method io/netty/util/ReferenceCountUtil.safeRelease:(Ljava/lang/Object;)V
       7: aload_1
       8: invokevirtual #121                // Method org/apache/pulsar/client/impl/TransactionMetaStoreHandler$OpBase.recycle:()V
      11: aload_0
      12: getfield      #12                 // Field semaphore:Ljava/util/concurrent/Semaphore;
      15: invokevirtual #122                // Method java/util/concurrent/Semaphore.release:()V
      18: return

  private boolean canSendRequest(java.util.concurrent.CompletableFuture<?>);
    Code:
       0: aload_0
       1: getfield      #9                  // Field blockIfReachMaxPendingOps:Z
       4: ifeq          17
       7: aload_0
       8: getfield      #12                 // Field semaphore:Ljava/util/concurrent/Semaphore;
      11: invokevirtual #123                // Method java/util/concurrent/Semaphore.acquire:()V
      14: goto          43
      17: aload_0
      18: getfield      #12                 // Field semaphore:Ljava/util/concurrent/Semaphore;
      21: invokevirtual #124                // Method java/util/concurrent/Semaphore.tryAcquire:()Z
      24: ifne          43
      27: aload_1
      28: new           #117                // class org/apache/pulsar/client/api/transaction/TransactionCoordinatorClientException
      31: dup
      32: ldc           #125                // String Reach max pending ops.
      34: invokespecial #118                // Method org/apache/pulsar/client/api/transaction/TransactionCoordinatorClientException."<init>":(Ljava/lang/String;)V
      37: invokevirtual #43                 // Method java/util/concurrent/CompletableFuture.completeExceptionally:(Ljava/lang/Throwable;)Z
      40: pop
      41: iconst_0
      42: ireturn
      43: goto          64
      46: astore_2
      47: invokestatic  #127                // Method java/lang/Thread.currentThread:()Ljava/lang/Thread;
      50: invokevirtual #128                // Method java/lang/Thread.interrupt:()V
      53: aload_1
      54: aload_2
      55: invokestatic  #129                // Method org/apache/pulsar/client/api/transaction/TransactionCoordinatorClientException.unwrap:(Ljava/lang/Throwable;)Lorg/apache/pulsar/client/api/transaction/TransactionCoordinatorClientException;
      58: invokevirtual #43                 // Method java/util/concurrent/CompletableFuture.completeExceptionally:(Ljava/lang/Throwable;)Z
      61: pop
      62: iconst_0
      63: ireturn
      64: iconst_1
      65: ireturn
    Exception table:
       from    to  target type
           0    42    46   Class java/lang/InterruptedException

  private boolean checkStateAndSendRequest(org.apache.pulsar.client.impl.TransactionMetaStoreHandler$OpBase<?>);
    Code:
       0: getstatic     #130                // Field org/apache/pulsar/client/impl/TransactionMetaStoreHandler$1.$SwitchMap$org$apache$pulsar$client$impl$HandlerState$State:[I
       3: aload_0
       4: invokevirtual #104                // Method getState:()Lorg/apache/pulsar/client/impl/HandlerState$State;
       7: invokevirtual #131                // Method org/apache/pulsar/client/impl/HandlerState$State.ordinal:()I
      10: iaload
      11: tableswitch   { // 1 to 6
                     1: 48
                     2: 113
                     3: 115
                     4: 115
                     5: 164
                     6: 164
               default: 213
          }
      48: aload_0
      49: invokespecial #132                // Method cnx:()Lorg/apache/pulsar/client/impl/ClientCnx;
      52: astore_2
      53: aload_2
      54: ifnull        94
      57: aload_1
      58: getfield      #119                // Field org/apache/pulsar/client/impl/TransactionMetaStoreHandler$OpBase.cmd:Lio/netty/buffer/ByteBuf;
      61: invokevirtual #133                // Method io/netty/buffer/ByteBuf.retain:()Lio/netty/buffer/ByteBuf;
      64: pop
      65: aload_2
      66: invokevirtual #134                // Method org/apache/pulsar/client/impl/ClientCnx.ctx:()Lio/netty/channel/ChannelHandlerContext;
      69: aload_1
      70: getfield      #119                // Field org/apache/pulsar/client/impl/TransactionMetaStoreHandler$OpBase.cmd:Lio/netty/buffer/ByteBuf;
      73: aload_0
      74: invokespecial #132                // Method cnx:()Lorg/apache/pulsar/client/impl/ClientCnx;
      77: invokevirtual #134                // Method org/apache/pulsar/client/impl/ClientCnx.ctx:()Lio/netty/channel/ChannelHandlerContext;
      80: invokeinterface #135,  1          // InterfaceMethod io/netty/channel/ChannelHandlerContext.voidPromise:()Lio/netty/channel/ChannelPromise;
      85: invokeinterface #136,  3          // InterfaceMethod io/netty/channel/ChannelHandlerContext.writeAndFlush:(Ljava/lang/Object;Lio/netty/channel/ChannelPromise;)Lio/netty/channel/ChannelFuture;
      90: pop
      91: goto          111
      94: getstatic     #38                 // Field LOG:Lorg/slf4j/Logger;
      97: ldc           #137                // String The cnx was null when the TC handler was ready
      99: new           #138                // class java/lang/NullPointerException
     102: dup
     103: invokespecial #139                // Method java/lang/NullPointerException."<init>":()V
     106: invokeinterface #140,  3          // InterfaceMethod org/slf4j/Logger.error:(Ljava/lang/String;Ljava/lang/Throwable;)V
     111: iconst_1
     112: ireturn
     113: iconst_1
     114: ireturn
     115: aload_1
     116: getfield      #109                // Field org/apache/pulsar/client/impl/TransactionMetaStoreHandler$OpBase.callback:Ljava/util/concurrent/CompletableFuture;
     119: new           #141                // class org/apache/pulsar/client/api/transaction/TransactionCoordinatorClientException$MetaStoreHandlerNotReadyException
     122: dup
     123: new           #142                // class java/lang/StringBuilder
     126: dup
     127: invokespecial #143                // Method java/lang/StringBuilder."<init>":()V
     130: ldc           #144                // String Transaction meta store handler for tcId
     132: invokevirtual #145                // Method java/lang/StringBuilder.append:(Ljava/lang/String;)Ljava/lang/StringBuilder;
     135: aload_0
     136: getfield      #5                  // Field transactionCoordinatorId:J
     139: invokevirtual #146                // Method java/lang/StringBuilder.append:(J)Ljava/lang/StringBuilder;
     142: ldc           #147                // String  is closing or closed.
     144: invokevirtual #145                // Method java/lang/StringBuilder.append:(Ljava/lang/String;)Ljava/lang/StringBuilder;
     147: invokevirtual #148                // Method java/lang/StringBuilder.toString:()Ljava/lang/String;
     150: invokespecial #149                // Method org/apache/pulsar/client/api/transaction/TransactionCoordinatorClientException$MetaStoreHandlerNotReadyException."<init>":(Ljava/lang/String;)V
     153: invokevirtual #43                 // Method java/util/concurrent/CompletableFuture.completeExceptionally:(Ljava/lang/Throwable;)Z
     156: pop
     157: aload_0
     158: aload_1
     159: invokespecial #150                // Method onResponse:(Lorg/apache/pulsar/client/impl/TransactionMetaStoreHandler$OpBase;)V
     162: iconst_0
     163: ireturn
     164: aload_1
     165: getfield      #109                // Field org/apache/pulsar/client/impl/TransactionMetaStoreHandler$OpBase.callback:Ljava/util/concurrent/CompletableFuture;
     168: new           #141                // class org/apache/pulsar/client/api/transaction/TransactionCoordinatorClientException$MetaStoreHandlerNotReadyException
     171: dup
     172: new           #142                // class java/lang/StringBuilder
     175: dup
     176: invokespecial #143                // Method java/lang/StringBuilder."<init>":()V
     179: ldc           #144                // String Transaction meta store handler for tcId
     181: invokevirtual #145                // Method java/lang/StringBuilder.append:(Ljava/lang/String;)Ljava/lang/StringBuilder;
     184: aload_0
     185: getfield      #5                  // Field transactionCoordinatorId:J
     188: invokevirtual #146                // Method java/lang/StringBuilder.append:(J)Ljava/lang/StringBuilder;
     191: ldc           #151                // String  not connected.
     193: invokevirtual #145                // Method java/lang/StringBuilder.append:(Ljava/lang/String;)Ljava/lang/StringBuilder;
     196: invokevirtual #148                // Method java/lang/StringBuilder.toString:()Ljava/lang/String;
     199: invokespecial #149                // Method org/apache/pulsar/client/api/transaction/TransactionCoordinatorClientException$MetaStoreHandlerNotReadyException."<init>":(Ljava/lang/String;)V
     202: invokevirtual #43                 // Method java/util/concurrent/CompletableFuture.completeExceptionally:(Ljava/lang/Throwable;)Z
     205: pop
     206: aload_0
     207: aload_1
     208: invokespecial #150                // Method onResponse:(Lorg/apache/pulsar/client/impl/TransactionMetaStoreHandler$OpBase;)V
     211: iconst_0
     212: ireturn
     213: aload_1
     214: getfield      #109                // Field org/apache/pulsar/client/impl/TransactionMetaStoreHandler$OpBase.callback:Ljava/util/concurrent/CompletableFuture;
     217: new           #141                // class org/apache/pulsar/client/api/transaction/TransactionCoordinatorClientException$MetaStoreHandlerNotReadyException
     220: dup
     221: aload_0
     222: getfield      #5                  // Field transactionCoordinatorId:J
     225: invokespecial #152                // Method org/apache/pulsar/client/api/transaction/TransactionCoordinatorClientException$MetaStoreHandlerNotReadyException."<init>":(J)V
     228: invokevirtual #43                 // Method java/util/concurrent/CompletableFuture.completeExceptionally:(Ljava/lang/Throwable;)Z
     231: pop
     232: aload_0
     233: aload_1
     234: invokespecial #150                // Method onResponse:(Lorg/apache/pulsar/client/impl/TransactionMetaStoreHandler$OpBase;)V
     237: iconst_0
     238: ireturn

  public void run(io.netty.util.Timeout) throws java.lang.Exception;
    Code:
       0: aload_0
       1: getfield      #37                 // Field internalPinnedExecutor:Ljava/util/concurrent/ExecutorService;
       4: aload_0
       5: aload_1
       6: invokedynamic #153,  0            // InvokeDynamic #10:run:(Lorg/apache/pulsar/client/impl/TransactionMetaStoreHandler;Lio/netty/util/Timeout;)Ljava/lang/Runnable;
      11: invokeinterface #45,  2           // InterfaceMethod java/util/concurrent/ExecutorService.execute:(Ljava/lang/Runnable;)V
      16: return

  private org.apache.pulsar.client.impl.ClientCnx cnx();
    Code:
       0: aload_0
       1: getfield      #32                 // Field connectionHandler:Lorg/apache/pulsar/client/impl/ConnectionHandler;
       4: invokevirtual #154                // Method org/apache/pulsar/client/impl/ConnectionHandler.cnx:()Lorg/apache/pulsar/client/impl/ClientCnx;
       7: areturn

  void connectionClosed(org.apache.pulsar.client.impl.ClientCnx);
    Code:
       0: aload_0
       1: getfield      #32                 // Field connectionHandler:Lorg/apache/pulsar/client/impl/ConnectionHandler;
       4: aload_1
       5: invokevirtual #155                // Method org/apache/pulsar/client/impl/ConnectionHandler.connectionClosed:(Lorg/apache/pulsar/client/impl/ClientCnx;)V
       8: return

  public void close() throws java.io.IOException;
    Code:
       0: aload_0
       1: getfield      #18                 // Field requestTimeout:Lio/netty/util/Timeout;
       4: invokeinterface #156,  1          // InterfaceMethod io/netty/util/Timeout.cancel:()Z
       9: pop
      10: aload_0
      11: getstatic     #157                // Field org/apache/pulsar/client/impl/HandlerState$State.Closed:Lorg/apache/pulsar/client/impl/HandlerState$State;
      14: invokevirtual #158                // Method setState:(Lorg/apache/pulsar/client/impl/HandlerState$State;)V
      17: return

  public org.apache.pulsar.client.impl.HandlerState$State getConnectHandleState();
    Code:
       0: aload_0
       1: invokevirtual #104                // Method getState:()Lorg/apache/pulsar/client/impl/HandlerState$State;
       4: areturn

  public java.lang.String getHandlerName();
    Code:
       0: new           #142                // class java/lang/StringBuilder
       3: dup
       4: invokespecial #143                // Method java/lang/StringBuilder."<init>":()V
       7: ldc           #159                // String Transaction meta store handler [
       9: invokevirtual #145                // Method java/lang/StringBuilder.append:(Ljava/lang/String;)Ljava/lang/StringBuilder;
      12: aload_0
      13: getfield      #5                  // Field transactionCoordinatorId:J
      16: invokevirtual #146                // Method java/lang/StringBuilder.append:(J)Ljava/lang/StringBuilder;
      19: ldc           #160                // String ]
      21: invokevirtual #145                // Method java/lang/StringBuilder.append:(Ljava/lang/String;)Ljava/lang/StringBuilder;
      24: invokevirtual #148                // Method java/lang/StringBuilder.toString:()Ljava/lang/String;
      27: areturn

  public org.apache.pulsar.client.impl.PulsarClientImpl getClient();
    Code:
       0: aload_0
       1: invokespecial #161                // Method org/apache/pulsar/client/impl/HandlerState.getClient:()Lorg/apache/pulsar/client/impl/PulsarClientImpl;
       4: areturn

  private void lambda$run$23(io.netty.util.Timeout);
    Code:
       0: aload_1
       1: invokeinterface #162,  1          // InterfaceMethod io/netty/util/Timeout.isCancelled:()Z
       6: ifeq          10
       9: return
      10: aload_0
      11: invokevirtual #104                // Method getState:()Lorg/apache/pulsar/client/impl/HandlerState$State;
      14: getstatic     #163                // Field org/apache/pulsar/client/impl/HandlerState$State.Closing:Lorg/apache/pulsar/client/impl/HandlerState$State;
      17: if_acmpeq     30
      20: aload_0
      21: invokevirtual #104                // Method getState:()Lorg/apache/pulsar/client/impl/HandlerState$State;
      24: getstatic     #157                // Field org/apache/pulsar/client/impl/HandlerState$State.Closed:Lorg/apache/pulsar/client/impl/HandlerState$State;
      27: if_acmpne     31
      30: return
      31: aload_0
      32: getfield      #8                  // Field timeoutQueue:Ljava/util/concurrent/ConcurrentLinkedQueue;
      35: invokevirtual #164                // Method java/util/concurrent/ConcurrentLinkedQueue.peek:()Ljava/lang/Object;
      38: checkcast     #165                // class org/apache/pulsar/client/impl/TransactionMetaStoreHandler$RequestTime
      41: astore        4
      43: aload         4
      45: ifnull        191
      48: aload         4
      50: getfield      #166                // Field org/apache/pulsar/client/impl/TransactionMetaStoreHandler$RequestTime.creationTimeMs:J
      53: aload_0
      54: getfield      #56                 // Field client:Lorg/apache/pulsar/client/impl/PulsarClientImpl;
      57: invokevirtual #14                 // Method org/apache/pulsar/client/impl/PulsarClientImpl.getConfiguration:()Lorg/apache/pulsar/client/impl/conf/ClientConfigurationData;
      60: invokevirtual #15                 // Method org/apache/pulsar/client/impl/conf/ClientConfigurationData.getOperationTimeoutMs:()J
      63: ladd
      64: invokestatic  #167                // Method java/lang/System.currentTimeMillis:()J
      67: lsub
      68: lconst_0
      69: lcmp
      70: ifgt          191
      73: aload_0
      74: getfield      #8                  // Field timeoutQueue:Ljava/util/concurrent/ConcurrentLinkedQueue;
      77: invokevirtual #168                // Method java/util/concurrent/ConcurrentLinkedQueue.poll:()Ljava/lang/Object;
      80: checkcast     #165                // class org/apache/pulsar/client/impl/TransactionMetaStoreHandler$RequestTime
      83: astore        5
      85: aload         5
      87: ifnull        191
      90: aload_0
      91: getfield      #4                  // Field pendingRequests:Lorg/apache/pulsar/common/util/collections/ConcurrentLongHashMap;
      94: aload         5
      96: getfield      #169                // Field org/apache/pulsar/client/impl/TransactionMetaStoreHandler$RequestTime.requestId:J
      99: invokevirtual #170                // Method org/apache/pulsar/common/util/collections/ConcurrentLongHashMap.remove:(J)Ljava/lang/Object;
     102: checkcast     #171                // class org/apache/pulsar/client/impl/TransactionMetaStoreHandler$OpBase
     105: astore        6
     107: aload         6
     109: ifnull        176
     112: aload         6
     114: getfield      #109                // Field org/apache/pulsar/client/impl/TransactionMetaStoreHandler$OpBase.callback:Ljava/util/concurrent/CompletableFuture;
     117: invokevirtual #42                 // Method java/util/concurrent/CompletableFuture.isDone:()Z
     120: ifne          176
     123: aload         6
     125: getfield      #109                // Field org/apache/pulsar/client/impl/TransactionMetaStoreHandler$OpBase.callback:Ljava/util/concurrent/CompletableFuture;
     128: new           #172                // class org/apache/pulsar/client/api/PulsarClientException$TimeoutException
     131: dup
     132: ldc           #173                // String Could not get response from transaction meta store within given timeout.
     134: invokespecial #174                // Method org/apache/pulsar/client/api/PulsarClientException$TimeoutException."<init>":(Ljava/lang/String;)V
     137: invokevirtual #43                 // Method java/util/concurrent/CompletableFuture.completeExceptionally:(Ljava/lang/Throwable;)Z
     140: pop
     141: getstatic     #38                 // Field LOG:Lorg/slf4j/Logger;
     144: invokeinterface #49,  1           // InterfaceMethod org/slf4j/Logger.isDebugEnabled:()Z
     149: ifeq          170
     152: getstatic     #38                 // Field LOG:Lorg/slf4j/Logger;
     155: ldc           #175                // String Transaction coordinator request {} is timeout.
     157: aload         5
     159: getfield      #169                // Field org/apache/pulsar/client/impl/TransactionMetaStoreHandler$RequestTime.requestId:J
     162: invokestatic  #40                 // Method java/lang/Long.valueOf:(J)Ljava/lang/Long;
     165: invokeinterface #52,  3           // InterfaceMethod org/slf4j/Logger.debug:(Ljava/lang/String;Ljava/lang/Object;)V
     170: aload_0
     171: aload         6
     173: invokespecial #150                // Method onResponse:(Lorg/apache/pulsar/client/impl/TransactionMetaStoreHandler$OpBase;)V
     176: aload_0
     177: getfield      #8                  // Field timeoutQueue:Ljava/util/concurrent/ConcurrentLinkedQueue;
     180: invokevirtual #164                // Method java/util/concurrent/ConcurrentLinkedQueue.peek:()Ljava/lang/Object;
     183: checkcast     #165                // class org/apache/pulsar/client/impl/TransactionMetaStoreHandler$RequestTime
     186: astore        4
     188: goto          43
     191: aload         4
     193: ifnonnull     210
     196: aload_0
     197: getfield      #56                 // Field client:Lorg/apache/pulsar/client/impl/PulsarClientImpl;
     200: invokevirtual #14                 // Method org/apache/pulsar/client/impl/PulsarClientImpl.getConfiguration:()Lorg/apache/pulsar/client/impl/conf/ClientConfigurationData;
     203: invokevirtual #15                 // Method org/apache/pulsar/client/impl/conf/ClientConfigurationData.getOperationTimeoutMs:()J
     206: lstore_2
     207: goto          256
     210: aload         4
     212: getfield      #166                // Field org/apache/pulsar/client/impl/TransactionMetaStoreHandler$RequestTime.creationTimeMs:J
     215: aload_0
     216: getfield      #56                 // Field client:Lorg/apache/pulsar/client/impl/PulsarClientImpl;
     219: invokevirtual #14                 // Method org/apache/pulsar/client/impl/PulsarClientImpl.getConfiguration:()Lorg/apache/pulsar/client/impl/conf/ClientConfigurationData;
     222: invokevirtual #15                 // Method org/apache/pulsar/client/impl/conf/ClientConfigurationData.getOperationTimeoutMs:()J
     225: ladd
     226: invokestatic  #167                // Method java/lang/System.currentTimeMillis:()J
     229: lsub
     230: lstore        5
     232: lload         5
     234: lconst_0
     235: lcmp
     236: ifgt          253
     239: aload_0
     240: getfield      #56                 // Field client:Lorg/apache/pulsar/client/impl/PulsarClientImpl;
     243: invokevirtual #14                 // Method org/apache/pulsar/client/impl/PulsarClientImpl.getConfiguration:()Lorg/apache/pulsar/client/impl/conf/ClientConfigurationData;
     246: invokevirtual #15                 // Method org/apache/pulsar/client/impl/conf/ClientConfigurationData.getOperationTimeoutMs:()J
     249: lstore_2
     250: goto          256
     253: lload         5
     255: lstore_2
     256: aload_0
     257: aload_0
     258: getfield      #56                 // Field client:Lorg/apache/pulsar/client/impl/PulsarClientImpl;
     261: invokevirtual #13                 // Method org/apache/pulsar/client/impl/PulsarClientImpl.timer:()Lio/netty/util/Timer;
     264: aload_0
     265: lload_2
     266: getstatic     #16                 // Field java/util/concurrent/TimeUnit.MILLISECONDS:Ljava/util/concurrent/TimeUnit;
     269: invokeinterface #17,  5           // InterfaceMethod io/netty/util/Timer.newTimeout:(Lio/netty/util/TimerTask;JLjava/util/concurrent/TimeUnit;)Lio/netty/util/Timeout;
     274: putfield      #18                 // Field requestTimeout:Lio/netty/util/Timeout;
     277: return

  private void lambda$handleEndTxnResponse$22(long, org.apache.pulsar.client.api.transaction.TxnID, boolean, org.apache.pulsar.common.api.proto.ServerError, java.lang.String);
    Code:
       0: aload_0
       1: getfield      #4                  // Field pendingRequests:Lorg/apache/pulsar/common/util/collections/ConcurrentLongHashMap;
       4: lload_1
       5: invokevirtual #170                // Method org/apache/pulsar/common/util/collections/ConcurrentLongHashMap.remove:(J)Ljava/lang/Object;
       8: checkcast     #176                // class org/apache/pulsar/client/impl/TransactionMetaStoreHandler$OpForVoidCallBack
      11: astore        7
      13: aload         7
      15: ifnonnull     54
      18: getstatic     #38                 // Field LOG:Lorg/slf4j/Logger;
      21: invokeinterface #49,  1           // InterfaceMethod org/slf4j/Logger.isDebugEnabled:()Z
      26: ifeq          53
      29: getstatic     #38                 // Field LOG:Lorg/slf4j/Logger;
      32: ldc           #177                // String Got end txn response for timeout {} - {}
      34: aload_3
      35: invokevirtual #73                 // Method org/apache/pulsar/client/api/transaction/TxnID.getMostSigBits:()J
      38: invokestatic  #40                 // Method java/lang/Long.valueOf:(J)Ljava/lang/Long;
      41: aload_3
      42: invokevirtual #72                 // Method org/apache/pulsar/client/api/transaction/TxnID.getLeastSigBits:()J
      45: invokestatic  #40                 // Method java/lang/Long.valueOf:(J)Ljava/lang/Long;
      48: invokeinterface #71,  4           // InterfaceMethod org/slf4j/Logger.debug:(Ljava/lang/String;Ljava/lang/Object;Ljava/lang/Object;)V
      53: return
      54: iload         4
      56: ifne          97
      59: getstatic     #38                 // Field LOG:Lorg/slf4j/Logger;
      62: invokeinterface #49,  1           // InterfaceMethod org/slf4j/Logger.isDebugEnabled:()Z
      67: ifeq          84
      70: getstatic     #38                 // Field LOG:Lorg/slf4j/Logger;
      73: ldc           #178                // String Got end txn response success for request {}
      75: lload_1
      76: invokestatic  #40                 // Method java/lang/Long.valueOf:(J)Ljava/lang/Long;
      79: invokeinterface #52,  3           // InterfaceMethod org/slf4j/Logger.debug:(Ljava/lang/String;Ljava/lang/Object;)V
      84: aload         7
      86: getfield      #179                // Field org/apache/pulsar/client/impl/TransactionMetaStoreHandler$OpForVoidCallBack.callback:Ljava/util/concurrent/CompletableFuture;
      89: aconst_null
      90: invokevirtual #180                // Method java/util/concurrent/CompletableFuture.complete:(Ljava/lang/Object;)Z
      93: pop
      94: goto          218
      97: aload_0
      98: aload         5
     100: aload         6
     102: aload         7
     104: invokespecial #181                // Method checkIfNeedRetryByError:(Lorg/apache/pulsar/common/api/proto/ServerError;Ljava/lang/String;Lorg/apache/pulsar/client/impl/TransactionMetaStoreHandler$OpBase;)Z
     107: ifeq          183
     110: getstatic     #38                 // Field LOG:Lorg/slf4j/Logger;
     113: invokeinterface #49,  1           // InterfaceMethod org/slf4j/Logger.isDebugEnabled:()Z
     118: ifeq          141
     121: getstatic     #38                 // Field LOG:Lorg/slf4j/Logger;
     124: ldc           #182                // String Get a response for the {} request {} error TransactionCoordinatorNotFound and try it again
     126: getstatic     #183                // Field org/apache/pulsar/common/api/proto/BaseCommand$Type.END_TXN:Lorg/apache/pulsar/common/api/proto/BaseCommand$Type;
     129: invokevirtual #184                // Method org/apache/pulsar/common/api/proto/BaseCommand$Type.name:()Ljava/lang/String;
     132: lload_1
     133: invokestatic  #40                 // Method java/lang/Long.valueOf:(J)Ljava/lang/Long;
     136: invokeinterface #71,  4           // InterfaceMethod org/slf4j/Logger.debug:(Ljava/lang/String;Ljava/lang/Object;Ljava/lang/Object;)V
     141: aload_0
     142: getfield      #4                  // Field pendingRequests:Lorg/apache/pulsar/common/util/collections/ConcurrentLongHashMap;
     145: lload_1
     146: aload         7
     148: invokevirtual #185                // Method org/apache/pulsar/common/util/collections/ConcurrentLongHashMap.put:(JLjava/lang/Object;)Ljava/lang/Object;
     151: pop
     152: aload_0
     153: getfield      #35                 // Field timer:Lio/netty/util/Timer;
     156: aload_0
     157: lload_1
     158: aload         7
     160: invokedynamic #186,  0            // InvokeDynamic #11:run:(Lorg/apache/pulsar/client/impl/TransactionMetaStoreHandler;JLorg/apache/pulsar/client/impl/TransactionMetaStoreHandler$OpForVoidCallBack;)Lio/netty/util/TimerTask;
     165: aload         7
     167: getfield      #187                // Field org/apache/pulsar/client/impl/TransactionMetaStoreHandler$OpForVoidCallBack.backoff:Lorg/apache/pulsar/client/impl/Backoff;
     170: invokevirtual #188                // Method org/apache/pulsar/client/impl/Backoff.next:()J
     173: getstatic     #16                 // Field java/util/concurrent/TimeUnit.MILLISECONDS:Ljava/util/concurrent/TimeUnit;
     176: invokeinterface #17,  5           // InterfaceMethod io/netty/util/Timer.newTimeout:(Lio/netty/util/TimerTask;JLjava/util/concurrent/TimeUnit;)Lio/netty/util/Timeout;
     181: pop
     182: return
     183: getstatic     #38                 // Field LOG:Lorg/slf4j/Logger;
     186: ldc           #189                // String Got {} response for request {} error {}
     188: iconst_3
     189: anewarray     #190                // class java/lang/Object
     192: dup
     193: iconst_0
     194: getstatic     #183                // Field org/apache/pulsar/common/api/proto/BaseCommand$Type.END_TXN:Lorg/apache/pulsar/common/api/proto/BaseCommand$Type;
     197: invokevirtual #184                // Method org/apache/pulsar/common/api/proto/BaseCommand$Type.name:()Ljava/lang/String;
     200: aastore
     201: dup
     202: iconst_1
     203: lload_1
     204: invokestatic  #40                 // Method java/lang/Long.valueOf:(J)Ljava/lang/Long;
     207: aastore
     208: dup
     209: iconst_2
     210: aload         5
     212: aastore
     213: invokeinterface #191,  3          // InterfaceMethod org/slf4j/Logger.error:(Ljava/lang/String;[Ljava/lang/Object;)V
     218: aload_0
     219: aload         7
     221: invokespecial #150                // Method onResponse:(Lorg/apache/pulsar/client/impl/TransactionMetaStoreHandler$OpBase;)V
     224: return

  private void lambda$null$21(long, org.apache.pulsar.client.impl.TransactionMetaStoreHandler$OpForVoidCallBack, io.netty.util.Timeout) throws java.lang.Exception;
    Code:
       0: aload_0
       1: getfield      #37                 // Field internalPinnedExecutor:Ljava/util/concurrent/ExecutorService;
       4: aload_0
       5: lload_1
       6: aload_3
       7: invokedynamic #192,  0            // InvokeDynamic #12:run:(Lorg/apache/pulsar/client/impl/TransactionMetaStoreHandler;JLorg/apache/pulsar/client/impl/TransactionMetaStoreHandler$OpForVoidCallBack;)Ljava/lang/Runnable;
      12: invokeinterface #45,  2           // InterfaceMethod java/util/concurrent/ExecutorService.execute:(Ljava/lang/Runnable;)V
      17: return

  private void lambda$null$20(long, org.apache.pulsar.client.impl.TransactionMetaStoreHandler$OpForVoidCallBack);
    Code:
       0: aload_0
       1: getfield      #4                  // Field pendingRequests:Lorg/apache/pulsar/common/util/collections/ConcurrentLongHashMap;
       4: lload_1
       5: invokevirtual #193                // Method org/apache/pulsar/common/util/collections/ConcurrentLongHashMap.containsKey:(J)Z
       8: ifne          37
      11: getstatic     #38                 // Field LOG:Lorg/slf4j/Logger;
      14: invokeinterface #49,  1           // InterfaceMethod org/slf4j/Logger.isDebugEnabled:()Z
      19: ifeq          36
      22: getstatic     #38                 // Field LOG:Lorg/slf4j/Logger;
      25: ldc           #194                // String The request {} already timeout
      27: lload_1
      28: invokestatic  #40                 // Method java/lang/Long.valueOf:(J)Ljava/lang/Long;
      31: invokeinterface #52,  3           // InterfaceMethod org/slf4j/Logger.debug:(Ljava/lang/String;Ljava/lang/Object;)V
      36: return
      37: aload_0
      38: aload_3
      39: invokespecial #195                // Method checkStateAndSendRequest:(Lorg/apache/pulsar/client/impl/TransactionMetaStoreHandler$OpBase;)Z
      42: ifne          54
      45: aload_0
      46: getfield      #4                  // Field pendingRequests:Lorg/apache/pulsar/common/util/collections/ConcurrentLongHashMap;
      49: lload_1
      50: invokevirtual #170                // Method org/apache/pulsar/common/util/collections/ConcurrentLongHashMap.remove:(J)Ljava/lang/Object;
      53: pop
      54: return

  private void lambda$endTxnAsync$19(long, org.apache.pulsar.client.impl.TransactionMetaStoreHandler$OpForVoidCallBack);
    Code:
       0: aload_0
       1: getfield      #4                  // Field pendingRequests:Lorg/apache/pulsar/common/util/collections/ConcurrentLongHashMap;
       4: lload_1
       5: aload_3
       6: invokevirtual #185                // Method org/apache/pulsar/common/util/collections/ConcurrentLongHashMap.put:(JLjava/lang/Object;)Ljava/lang/Object;
       9: pop
      10: aload_0
      11: getfield      #8                  // Field timeoutQueue:Ljava/util/concurrent/ConcurrentLinkedQueue;
      14: new           #165                // class org/apache/pulsar/client/impl/TransactionMetaStoreHandler$RequestTime
      17: dup
      18: invokestatic  #167                // Method java/lang/System.currentTimeMillis:()J
      21: lload_1
      22: invokespecial #196                // Method org/apache/pulsar/client/impl/TransactionMetaStoreHandler$RequestTime."<init>":(JJ)V
      25: invokevirtual #197                // Method java/util/concurrent/ConcurrentLinkedQueue.add:(Ljava/lang/Object;)Z
      28: pop
      29: aload_0
      30: aload_3
      31: invokespecial #195                // Method checkStateAndSendRequest:(Lorg/apache/pulsar/client/impl/TransactionMetaStoreHandler$OpBase;)Z
      34: ifne          46
      37: aload_0
      38: getfield      #4                  // Field pendingRequests:Lorg/apache/pulsar/common/util/collections/ConcurrentLongHashMap;
      41: lload_1
      42: invokevirtual #170                // Method org/apache/pulsar/common/util/collections/ConcurrentLongHashMap.remove:(J)Ljava/lang/Object;
      45: pop
      46: return

  private void lambda$handleAddSubscriptionToTxnResponse$18(long, boolean, org.apache.pulsar.common.api.proto.ServerError, java.lang.String);
    Code:
       0: aload_0
       1: getfield      #4                  // Field pendingRequests:Lorg/apache/pulsar/common/util/collections/ConcurrentLongHashMap;
       4: lload_1
       5: invokevirtual #170                // Method org/apache/pulsar/common/util/collections/ConcurrentLongHashMap.remove:(J)Ljava/lang/Object;
       8: checkcast     #176                // class org/apache/pulsar/client/impl/TransactionMetaStoreHandler$OpForVoidCallBack
      11: astore        6
      13: aload         6
      15: ifnonnull     44
      18: getstatic     #38                 // Field LOG:Lorg/slf4j/Logger;
      21: invokeinterface #49,  1           // InterfaceMethod org/slf4j/Logger.isDebugEnabled:()Z
      26: ifeq          43
      29: getstatic     #38                 // Field LOG:Lorg/slf4j/Logger;
      32: ldc           #198                // String Add subscription to txn timeout for request {}.
      34: lload_1
      35: invokestatic  #40                 // Method java/lang/Long.valueOf:(J)Ljava/lang/Long;
      38: invokeinterface #52,  3           // InterfaceMethod org/slf4j/Logger.debug:(Ljava/lang/String;Ljava/lang/Object;)V
      43: return
      44: iload_3
      45: ifne          86
      48: getstatic     #38                 // Field LOG:Lorg/slf4j/Logger;
      51: invokeinterface #49,  1           // InterfaceMethod org/slf4j/Logger.isDebugEnabled:()Z
      56: ifeq          73
      59: getstatic     #38                 // Field LOG:Lorg/slf4j/Logger;
      62: ldc           #199                // String Add subscription to txn success for request {}.
      64: lload_1
      65: invokestatic  #40                 // Method java/lang/Long.valueOf:(J)Ljava/lang/Long;
      68: invokeinterface #52,  3           // InterfaceMethod org/slf4j/Logger.debug:(Ljava/lang/String;Ljava/lang/Object;)V
      73: aload         6
      75: getfield      #179                // Field org/apache/pulsar/client/impl/TransactionMetaStoreHandler$OpForVoidCallBack.callback:Ljava/util/concurrent/CompletableFuture;
      78: aconst_null
      79: invokevirtual #180                // Method java/util/concurrent/CompletableFuture.complete:(Ljava/lang/Object;)Z
      82: pop
      83: goto          223
      86: getstatic     #38                 // Field LOG:Lorg/slf4j/Logger;
      89: ldc           #200                // String Add subscription to txn failed for request {} error {}.
      91: lload_1
      92: invokestatic  #40                 // Method java/lang/Long.valueOf:(J)Ljava/lang/Long;
      95: aload         4
      97: invokeinterface #41,  4           // InterfaceMethod org/slf4j/Logger.error:(Ljava/lang/String;Ljava/lang/Object;Ljava/lang/Object;)V
     102: aload_0
     103: aload         4
     105: aload         5
     107: aload         6
     109: invokespecial #181                // Method checkIfNeedRetryByError:(Lorg/apache/pulsar/common/api/proto/ServerError;Ljava/lang/String;Lorg/apache/pulsar/client/impl/TransactionMetaStoreHandler$OpBase;)Z
     112: ifeq          188
     115: getstatic     #38                 // Field LOG:Lorg/slf4j/Logger;
     118: invokeinterface #49,  1           // InterfaceMethod org/slf4j/Logger.isDebugEnabled:()Z
     123: ifeq          146
     126: getstatic     #38                 // Field LOG:Lorg/slf4j/Logger;
     129: ldc           #201                // String Get a response for {} request {} error TransactionCoordinatorNotFound and try it again
     131: getstatic     #202                // Field org/apache/pulsar/common/api/proto/BaseCommand$Type.ADD_SUBSCRIPTION_TO_TXN:Lorg/apache/pulsar/common/api/proto/BaseCommand$Type;
     134: invokevirtual #184                // Method org/apache/pulsar/common/api/proto/BaseCommand$Type.name:()Ljava/lang/String;
     137: lload_1
     138: invokestatic  #40                 // Method java/lang/Long.valueOf:(J)Ljava/lang/Long;
     141: invokeinterface #71,  4           // InterfaceMethod org/slf4j/Logger.debug:(Ljava/lang/String;Ljava/lang/Object;Ljava/lang/Object;)V
     146: aload_0
     147: getfield      #4                  // Field pendingRequests:Lorg/apache/pulsar/common/util/collections/ConcurrentLongHashMap;
     150: lload_1
     151: aload         6
     153: invokevirtual #185                // Method org/apache/pulsar/common/util/collections/ConcurrentLongHashMap.put:(JLjava/lang/Object;)Ljava/lang/Object;
     156: pop
     157: aload_0
     158: getfield      #35                 // Field timer:Lio/netty/util/Timer;
     161: aload_0
     162: lload_1
     163: aload         6
     165: invokedynamic #203,  0            // InvokeDynamic #13:run:(Lorg/apache/pulsar/client/impl/TransactionMetaStoreHandler;JLorg/apache/pulsar/client/impl/TransactionMetaStoreHandler$OpForVoidCallBack;)Lio/netty/util/TimerTask;
     170: aload         6
     172: getfield      #187                // Field org/apache/pulsar/client/impl/TransactionMetaStoreHandler$OpForVoidCallBack.backoff:Lorg/apache/pulsar/client/impl/Backoff;
     175: invokevirtual #188                // Method org/apache/pulsar/client/impl/Backoff.next:()J
     178: getstatic     #16                 // Field java/util/concurrent/TimeUnit.MILLISECONDS:Ljava/util/concurrent/TimeUnit;
     181: invokeinterface #17,  5           // InterfaceMethod io/netty/util/Timer.newTimeout:(Lio/netty/util/TimerTask;JLjava/util/concurrent/TimeUnit;)Lio/netty/util/Timeout;
     186: pop
     187: return
     188: getstatic     #38                 // Field LOG:Lorg/slf4j/Logger;
     191: ldc           #204                // String {} failed for request {} error {}.
     193: iconst_3
     194: anewarray     #190                // class java/lang/Object
     197: dup
     198: iconst_0
     199: getstatic     #202                // Field org/apache/pulsar/common/api/proto/BaseCommand$Type.ADD_SUBSCRIPTION_TO_TXN:Lorg/apache/pulsar/common/api/proto/BaseCommand$Type;
     202: invokevirtual #184                // Method org/apache/pulsar/common/api/proto/BaseCommand$Type.name:()Ljava/lang/String;
     205: aastore
     206: dup
     207: iconst_1
     208: lload_1
     209: invokestatic  #40                 // Method java/lang/Long.valueOf:(J)Ljava/lang/Long;
     212: aastore
     213: dup
     214: iconst_2
     215: aload         4
     217: aastore
     218: invokeinterface #191,  3          // InterfaceMethod org/slf4j/Logger.error:(Ljava/lang/String;[Ljava/lang/Object;)V
     223: aload_0
     224: aload         6
     226: invokespecial #150                // Method onResponse:(Lorg/apache/pulsar/client/impl/TransactionMetaStoreHandler$OpBase;)V
     229: return

  private void lambda$null$17(long, org.apache.pulsar.client.impl.TransactionMetaStoreHandler$OpForVoidCallBack, io.netty.util.Timeout) throws java.lang.Exception;
    Code:
       0: aload_0
       1: getfield      #37                 // Field internalPinnedExecutor:Ljava/util/concurrent/ExecutorService;
       4: aload_0
       5: lload_1
       6: aload_3
       7: invokedynamic #205,  0            // InvokeDynamic #14:run:(Lorg/apache/pulsar/client/impl/TransactionMetaStoreHandler;JLorg/apache/pulsar/client/impl/TransactionMetaStoreHandler$OpForVoidCallBack;)Ljava/lang/Runnable;
      12: invokeinterface #45,  2           // InterfaceMethod java/util/concurrent/ExecutorService.execute:(Ljava/lang/Runnable;)V
      17: return

  private void lambda$null$16(long, org.apache.pulsar.client.impl.TransactionMetaStoreHandler$OpForVoidCallBack);
    Code:
       0: aload_0
       1: getfield      #4                  // Field pendingRequests:Lorg/apache/pulsar/common/util/collections/ConcurrentLongHashMap;
       4: lload_1
       5: invokevirtual #193                // Method org/apache/pulsar/common/util/collections/ConcurrentLongHashMap.containsKey:(J)Z
       8: ifne          37
      11: getstatic     #38                 // Field LOG:Lorg/slf4j/Logger;
      14: invokeinterface #49,  1           // InterfaceMethod org/slf4j/Logger.isDebugEnabled:()Z
      19: ifeq          36
      22: getstatic     #38                 // Field LOG:Lorg/slf4j/Logger;
      25: ldc           #194                // String The request {} already timeout
      27: lload_1
      28: invokestatic  #40                 // Method java/lang/Long.valueOf:(J)Ljava/lang/Long;
      31: invokeinterface #52,  3           // InterfaceMethod org/slf4j/Logger.debug:(Ljava/lang/String;Ljava/lang/Object;)V
      36: return
      37: aload_0
      38: aload_3
      39: invokespecial #195                // Method checkStateAndSendRequest:(Lorg/apache/pulsar/client/impl/TransactionMetaStoreHandler$OpBase;)Z
      42: ifne          54
      45: aload_0
      46: getfield      #4                  // Field pendingRequests:Lorg/apache/pulsar/common/util/collections/ConcurrentLongHashMap;
      49: lload_1
      50: invokevirtual #170                // Method org/apache/pulsar/common/util/collections/ConcurrentLongHashMap.remove:(J)Ljava/lang/Object;
      53: pop
      54: return

  private void lambda$addSubscriptionToTxn$15(long, org.apache.pulsar.client.impl.TransactionMetaStoreHandler$OpForVoidCallBack);
    Code:
       0: aload_0
       1: getfield      #4                  // Field pendingRequests:Lorg/apache/pulsar/common/util/collections/ConcurrentLongHashMap;
       4: lload_1
       5: aload_3
       6: invokevirtual #185                // Method org/apache/pulsar/common/util/collections/ConcurrentLongHashMap.put:(JLjava/lang/Object;)Ljava/lang/Object;
       9: pop
      10: aload_0
      11: getfield      #8                  // Field timeoutQueue:Ljava/util/concurrent/ConcurrentLinkedQueue;
      14: new           #165                // class org/apache/pulsar/client/impl/TransactionMetaStoreHandler$RequestTime
      17: dup
      18: invokestatic  #167                // Method java/lang/System.currentTimeMillis:()J
      21: lload_1
      22: invokespecial #196                // Method org/apache/pulsar/client/impl/TransactionMetaStoreHandler$RequestTime."<init>":(JJ)V
      25: invokevirtual #197                // Method java/util/concurrent/ConcurrentLinkedQueue.add:(Ljava/lang/Object;)Z
      28: pop
      29: aload_0
      30: aload_3
      31: invokespecial #195                // Method checkStateAndSendRequest:(Lorg/apache/pulsar/client/impl/TransactionMetaStoreHandler$OpBase;)Z
      34: ifne          46
      37: aload_0
      38: getfield      #4                  // Field pendingRequests:Lorg/apache/pulsar/common/util/collections/ConcurrentLongHashMap;
      41: lload_1
      42: invokevirtual #170                // Method org/apache/pulsar/common/util/collections/ConcurrentLongHashMap.remove:(J)Ljava/lang/Object;
      45: pop
      46: return

  private void lambda$handleAddPublishPartitionToTxnResponse$14(long, org.apache.pulsar.client.api.transaction.TxnID, boolean, org.apache.pulsar.common.api.proto.ServerError, java.lang.String);
    Code:
       0: aload_0
       1: getfield      #4                  // Field pendingRequests:Lorg/apache/pulsar/common/util/collections/ConcurrentLongHashMap;
       4: lload_1
       5: invokevirtual #170                // Method org/apache/pulsar/common/util/collections/ConcurrentLongHashMap.remove:(J)Ljava/lang/Object;
       8: checkcast     #176                // class org/apache/pulsar/client/impl/TransactionMetaStoreHandler$OpForVoidCallBack
      11: astore        7
      13: aload         7
      15: ifnonnull     54
      18: getstatic     #38                 // Field LOG:Lorg/slf4j/Logger;
      21: invokeinterface #49,  1           // InterfaceMethod org/slf4j/Logger.isDebugEnabled:()Z
      26: ifeq          53
      29: getstatic     #38                 // Field LOG:Lorg/slf4j/Logger;
      32: ldc           #206                // String Got add publish partition to txn response for timeout {} - {}
      34: aload_3
      35: invokevirtual #73                 // Method org/apache/pulsar/client/api/transaction/TxnID.getMostSigBits:()J
      38: invokestatic  #40                 // Method java/lang/Long.valueOf:(J)Ljava/lang/Long;
      41: aload_3
      42: invokevirtual #72                 // Method org/apache/pulsar/client/api/transaction/TxnID.getLeastSigBits:()J
      45: invokestatic  #40                 // Method java/lang/Long.valueOf:(J)Ljava/lang/Long;
      48: invokeinterface #71,  4           // InterfaceMethod org/slf4j/Logger.debug:(Ljava/lang/String;Ljava/lang/Object;Ljava/lang/Object;)V
      53: return
      54: iload         4
      56: ifne          97
      59: getstatic     #38                 // Field LOG:Lorg/slf4j/Logger;
      62: invokeinterface #49,  1           // InterfaceMethod org/slf4j/Logger.isDebugEnabled:()Z
      67: ifeq          84
      70: getstatic     #38                 // Field LOG:Lorg/slf4j/Logger;
      73: ldc           #207                // String Add publish partition for request {} success.
      75: lload_1
      76: invokestatic  #40                 // Method java/lang/Long.valueOf:(J)Ljava/lang/Long;
      79: invokeinterface #52,  3           // InterfaceMethod org/slf4j/Logger.debug:(Ljava/lang/String;Ljava/lang/Object;)V
      84: aload         7
      86: getfield      #179                // Field org/apache/pulsar/client/impl/TransactionMetaStoreHandler$OpForVoidCallBack.callback:Ljava/util/concurrent/CompletableFuture;
      89: aconst_null
      90: invokevirtual #180                // Method java/util/concurrent/CompletableFuture.complete:(Ljava/lang/Object;)Z
      93: pop
      94: goto          222
      97: aload_0
      98: aload         5
     100: aload         6
     102: aload         7
     104: invokespecial #181                // Method checkIfNeedRetryByError:(Lorg/apache/pulsar/common/api/proto/ServerError;Ljava/lang/String;Lorg/apache/pulsar/client/impl/TransactionMetaStoreHandler$OpBase;)Z
     107: ifeq          183
     110: getstatic     #38                 // Field LOG:Lorg/slf4j/Logger;
     113: invokeinterface #49,  1           // InterfaceMethod org/slf4j/Logger.isDebugEnabled:()Z
     118: ifeq          141
     121: getstatic     #38                 // Field LOG:Lorg/slf4j/Logger;
     124: ldc           #208                // String Get a response for the {} request {}  error TransactionCoordinatorNotFound and try it again
     126: getstatic     #209                // Field org/apache/pulsar/common/api/proto/BaseCommand$Type.ADD_PARTITION_TO_TXN:Lorg/apache/pulsar/common/api/proto/BaseCommand$Type;
     129: invokevirtual #184                // Method org/apache/pulsar/common/api/proto/BaseCommand$Type.name:()Ljava/lang/String;
     132: lload_1
     133: invokestatic  #40                 // Method java/lang/Long.valueOf:(J)Ljava/lang/Long;
     136: invokeinterface #71,  4           // InterfaceMethod org/slf4j/Logger.debug:(Ljava/lang/String;Ljava/lang/Object;Ljava/lang/Object;)V
     141: aload_0
     142: getfield      #4                  // Field pendingRequests:Lorg/apache/pulsar/common/util/collections/ConcurrentLongHashMap;
     145: lload_1
     146: aload         7
     148: invokevirtual #185                // Method org/apache/pulsar/common/util/collections/ConcurrentLongHashMap.put:(JLjava/lang/Object;)Ljava/lang/Object;
     151: pop
     152: aload_0
     153: getfield      #35                 // Field timer:Lio/netty/util/Timer;
     156: aload_0
     157: lload_1
     158: aload         7
     160: invokedynamic #210,  0            // InvokeDynamic #15:run:(Lorg/apache/pulsar/client/impl/TransactionMetaStoreHandler;JLorg/apache/pulsar/client/impl/TransactionMetaStoreHandler$OpForVoidCallBack;)Lio/netty/util/TimerTask;
     165: aload         7
     167: getfield      #187                // Field org/apache/pulsar/client/impl/TransactionMetaStoreHandler$OpForVoidCallBack.backoff:Lorg/apache/pulsar/client/impl/Backoff;
     170: invokevirtual #188                // Method org/apache/pulsar/client/impl/Backoff.next:()J
     173: getstatic     #16                 // Field java/util/concurrent/TimeUnit.MILLISECONDS:Ljava/util/concurrent/TimeUnit;
     176: invokeinterface #17,  5           // InterfaceMethod io/netty/util/Timer.newTimeout:(Lio/netty/util/TimerTask;JLjava/util/concurrent/TimeUnit;)Lio/netty/util/Timeout;
     181: pop
     182: return
     183: getstatic     #38                 // Field LOG:Lorg/slf4j/Logger;
     186: ldc           #211                // String {} for request {} error {} with txnID {}.
     188: iconst_4
     189: anewarray     #190                // class java/lang/Object
     192: dup
     193: iconst_0
     194: getstatic     #209                // Field org/apache/pulsar/common/api/proto/BaseCommand$Type.ADD_PARTITION_TO_TXN:Lorg/apache/pulsar/common/api/proto/BaseCommand$Type;
     197: invokevirtual #184                // Method org/apache/pulsar/common/api/proto/BaseCommand$Type.name:()Ljava/lang/String;
     200: aastore
     201: dup
     202: iconst_1
     203: lload_1
     204: invokestatic  #40                 // Method java/lang/Long.valueOf:(J)Ljava/lang/Long;
     207: aastore
     208: dup
     209: iconst_2
     210: aload         5
     212: aastore
     213: dup
     214: iconst_3
     215: aload_3
     216: aastore
     217: invokeinterface #191,  3          // InterfaceMethod org/slf4j/Logger.error:(Ljava/lang/String;[Ljava/lang/Object;)V
     222: aload_0
     223: aload         7
     225: invokespecial #150                // Method onResponse:(Lorg/apache/pulsar/client/impl/TransactionMetaStoreHandler$OpBase;)V
     228: return

  private void lambda$null$13(long, org.apache.pulsar.client.impl.TransactionMetaStoreHandler$OpForVoidCallBack, io.netty.util.Timeout) throws java.lang.Exception;
    Code:
       0: aload_0
       1: getfield      #37                 // Field internalPinnedExecutor:Ljava/util/concurrent/ExecutorService;
       4: aload_0
       5: lload_1
       6: aload_3
       7: invokedynamic #212,  0            // InvokeDynamic #16:run:(Lorg/apache/pulsar/client/impl/TransactionMetaStoreHandler;JLorg/apache/pulsar/client/impl/TransactionMetaStoreHandler$OpForVoidCallBack;)Ljava/lang/Runnable;
      12: invokeinterface #45,  2           // InterfaceMethod java/util/concurrent/ExecutorService.execute:(Ljava/lang/Runnable;)V
      17: return

  private void lambda$null$12(long, org.apache.pulsar.client.impl.TransactionMetaStoreHandler$OpForVoidCallBack);
    Code:
       0: aload_0
       1: getfield      #4                  // Field pendingRequests:Lorg/apache/pulsar/common/util/collections/ConcurrentLongHashMap;
       4: lload_1
       5: invokevirtual #193                // Method org/apache/pulsar/common/util/collections/ConcurrentLongHashMap.containsKey:(J)Z
       8: ifne          37
      11: getstatic     #38                 // Field LOG:Lorg/slf4j/Logger;
      14: invokeinterface #49,  1           // InterfaceMethod org/slf4j/Logger.isDebugEnabled:()Z
      19: ifeq          36
      22: getstatic     #38                 // Field LOG:Lorg/slf4j/Logger;
      25: ldc           #194                // String The request {} already timeout
      27: lload_1
      28: invokestatic  #40                 // Method java/lang/Long.valueOf:(J)Ljava/lang/Long;
      31: invokeinterface #52,  3           // InterfaceMethod org/slf4j/Logger.debug:(Ljava/lang/String;Ljava/lang/Object;)V
      36: return
      37: aload_0
      38: aload_3
      39: invokespecial #195                // Method checkStateAndSendRequest:(Lorg/apache/pulsar/client/impl/TransactionMetaStoreHandler$OpBase;)Z
      42: ifne          54
      45: aload_0
      46: getfield      #4                  // Field pendingRequests:Lorg/apache/pulsar/common/util/collections/ConcurrentLongHashMap;
      49: lload_1
      50: invokevirtual #170                // Method org/apache/pulsar/common/util/collections/ConcurrentLongHashMap.remove:(J)Ljava/lang/Object;
      53: pop
      54: return

  private void lambda$addPublishPartitionToTxnAsync$11(long, org.apache.pulsar.client.impl.TransactionMetaStoreHandler$OpForVoidCallBack);
    Code:
       0: aload_0
       1: getfield      #4                  // Field pendingRequests:Lorg/apache/pulsar/common/util/collections/ConcurrentLongHashMap;
       4: lload_1
       5: aload_3
       6: invokevirtual #185                // Method org/apache/pulsar/common/util/collections/ConcurrentLongHashMap.put:(JLjava/lang/Object;)Ljava/lang/Object;
       9: pop
      10: aload_0
      11: getfield      #8                  // Field timeoutQueue:Ljava/util/concurrent/ConcurrentLinkedQueue;
      14: new           #165                // class org/apache/pulsar/client/impl/TransactionMetaStoreHandler$RequestTime
      17: dup
      18: invokestatic  #167                // Method java/lang/System.currentTimeMillis:()J
      21: lload_1
      22: invokespecial #196                // Method org/apache/pulsar/client/impl/TransactionMetaStoreHandler$RequestTime."<init>":(JJ)V
      25: invokevirtual #197                // Method java/util/concurrent/ConcurrentLinkedQueue.add:(Ljava/lang/Object;)Z
      28: pop
      29: aload_0
      30: aload_3
      31: invokespecial #195                // Method checkStateAndSendRequest:(Lorg/apache/pulsar/client/impl/TransactionMetaStoreHandler$OpBase;)Z
      34: ifne          46
      37: aload_0
      38: getfield      #4                  // Field pendingRequests:Lorg/apache/pulsar/common/util/collections/ConcurrentLongHashMap;
      41: lload_1
      42: invokevirtual #170                // Method org/apache/pulsar/common/util/collections/ConcurrentLongHashMap.remove:(J)Ljava/lang/Object;
      45: pop
      46: return

  private void lambda$handleNewTxnResponse$10(long, org.apache.pulsar.client.api.transaction.TxnID, boolean, org.apache.pulsar.common.api.proto.ServerError, java.lang.String);
    Code:
       0: aload_0
       1: getfield      #4                  // Field pendingRequests:Lorg/apache/pulsar/common/util/collections/ConcurrentLongHashMap;
       4: lload_1
       5: invokevirtual #170                // Method org/apache/pulsar/common/util/collections/ConcurrentLongHashMap.remove:(J)Ljava/lang/Object;
       8: checkcast     #213                // class org/apache/pulsar/client/impl/TransactionMetaStoreHandler$OpForTxnIdCallBack
      11: astore        7
      13: aload         7
      15: ifnonnull     54
      18: getstatic     #38                 // Field LOG:Lorg/slf4j/Logger;
      21: invokeinterface #49,  1           // InterfaceMethod org/slf4j/Logger.isDebugEnabled:()Z
      26: ifeq          53
      29: getstatic     #38                 // Field LOG:Lorg/slf4j/Logger;
      32: ldc           #214                // String Got new txn response for timeout {} - {}
      34: aload_3
      35: invokevirtual #73                 // Method org/apache/pulsar/client/api/transaction/TxnID.getMostSigBits:()J
      38: invokestatic  #40                 // Method java/lang/Long.valueOf:(J)Ljava/lang/Long;
      41: aload_3
      42: invokevirtual #72                 // Method org/apache/pulsar/client/api/transaction/TxnID.getLeastSigBits:()J
      45: invokestatic  #40                 // Method java/lang/Long.valueOf:(J)Ljava/lang/Long;
      48: invokeinterface #71,  4           // InterfaceMethod org/slf4j/Logger.debug:(Ljava/lang/String;Ljava/lang/Object;Ljava/lang/Object;)V
      53: return
      54: iload         4
      56: ifne          98
      59: getstatic     #38                 // Field LOG:Lorg/slf4j/Logger;
      62: invokeinterface #49,  1           // InterfaceMethod org/slf4j/Logger.isDebugEnabled:()Z
      67: ifeq          85
      70: getstatic     #38                 // Field LOG:Lorg/slf4j/Logger;
      73: ldc           #215                // String Got new txn response {} for request {}
      75: aload_3
      76: lload_1
      77: invokestatic  #40                 // Method java/lang/Long.valueOf:(J)Ljava/lang/Long;
      80: invokeinterface #71,  4           // InterfaceMethod org/slf4j/Logger.debug:(Ljava/lang/String;Ljava/lang/Object;Ljava/lang/Object;)V
      85: aload         7
      87: getfield      #216                // Field org/apache/pulsar/client/impl/TransactionMetaStoreHandler$OpForTxnIdCallBack.callback:Ljava/util/concurrent/CompletableFuture;
      90: aload_3
      91: invokevirtual #180                // Method java/util/concurrent/CompletableFuture.complete:(Ljava/lang/Object;)Z
      94: pop
      95: goto          219
      98: aload_0
      99: aload         5
     101: aload         6
     103: aload         7
     105: invokespecial #181                // Method checkIfNeedRetryByError:(Lorg/apache/pulsar/common/api/proto/ServerError;Ljava/lang/String;Lorg/apache/pulsar/client/impl/TransactionMetaStoreHandler$OpBase;)Z
     108: ifeq          184
     111: getstatic     #38                 // Field LOG:Lorg/slf4j/Logger;
     114: invokeinterface #49,  1           // InterfaceMethod org/slf4j/Logger.isDebugEnabled:()Z
     119: ifeq          142
     122: getstatic     #38                 // Field LOG:Lorg/slf4j/Logger;
     125: ldc           #217                // String Get a response for the {}  request {} error TransactionCoordinatorNotFound and try it again
     127: getstatic     #218                // Field org/apache/pulsar/common/api/proto/BaseCommand$Type.NEW_TXN:Lorg/apache/pulsar/common/api/proto/BaseCommand$Type;
     130: invokevirtual #184                // Method org/apache/pulsar/common/api/proto/BaseCommand$Type.name:()Ljava/lang/String;
     133: lload_1
     134: invokestatic  #40                 // Method java/lang/Long.valueOf:(J)Ljava/lang/Long;
     137: invokeinterface #71,  4           // InterfaceMethod org/slf4j/Logger.debug:(Ljava/lang/String;Ljava/lang/Object;Ljava/lang/Object;)V
     142: aload_0
     143: getfield      #4                  // Field pendingRequests:Lorg/apache/pulsar/common/util/collections/ConcurrentLongHashMap;
     146: lload_1
     147: aload         7
     149: invokevirtual #185                // Method org/apache/pulsar/common/util/collections/ConcurrentLongHashMap.put:(JLjava/lang/Object;)Ljava/lang/Object;
     152: pop
     153: aload_0
     154: getfield      #35                 // Field timer:Lio/netty/util/Timer;
     157: aload_0
     158: lload_1
     159: aload         7
     161: invokedynamic #219,  0            // InvokeDynamic #17:run:(Lorg/apache/pulsar/client/impl/TransactionMetaStoreHandler;JLorg/apache/pulsar/client/impl/TransactionMetaStoreHandler$OpForTxnIdCallBack;)Lio/netty/util/TimerTask;
     166: aload         7
     168: getfield      #220                // Field org/apache/pulsar/client/impl/TransactionMetaStoreHandler$OpForTxnIdCallBack.backoff:Lorg/apache/pulsar/client/impl/Backoff;
     171: invokevirtual #188                // Method org/apache/pulsar/client/impl/Backoff.next:()J
     174: getstatic     #16                 // Field java/util/concurrent/TimeUnit.MILLISECONDS:Ljava/util/concurrent/TimeUnit;
     177: invokeinterface #17,  5           // InterfaceMethod io/netty/util/Timer.newTimeout:(Lio/netty/util/TimerTask;JLjava/util/concurrent/TimeUnit;)Lio/netty/util/Timeout;
     182: pop
     183: return
     184: getstatic     #38                 // Field LOG:Lorg/slf4j/Logger;
     187: ldc           #221                // String Got {} for request {} error {}
     189: iconst_3
     190: anewarray     #190                // class java/lang/Object
     193: dup
     194: iconst_0
     195: getstatic     #218                // Field org/apache/pulsar/common/api/proto/BaseCommand$Type.NEW_TXN:Lorg/apache/pulsar/common/api/proto/BaseCommand$Type;
     198: invokevirtual #184                // Method org/apache/pulsar/common/api/proto/BaseCommand$Type.name:()Ljava/lang/String;
     201: aastore
     202: dup
     203: iconst_1
     204: lload_1
     205: invokestatic  #40                 // Method java/lang/Long.valueOf:(J)Ljava/lang/Long;
     208: aastore
     209: dup
     210: iconst_2
     211: aload         5
     213: aastore
     214: invokeinterface #191,  3          // InterfaceMethod org/slf4j/Logger.error:(Ljava/lang/String;[Ljava/lang/Object;)V
     219: aload_0
     220: aload         7
     222: invokespecial #150                // Method onResponse:(Lorg/apache/pulsar/client/impl/TransactionMetaStoreHandler$OpBase;)V
     225: return

  private void lambda$null$9(long, org.apache.pulsar.client.impl.TransactionMetaStoreHandler$OpForTxnIdCallBack, io.netty.util.Timeout) throws java.lang.Exception;
    Code:
       0: aload_0
       1: getfield      #37                 // Field internalPinnedExecutor:Ljava/util/concurrent/ExecutorService;
       4: aload_0
       5: lload_1
       6: aload_3
       7: invokedynamic #222,  0            // InvokeDynamic #18:run:(Lorg/apache/pulsar/client/impl/TransactionMetaStoreHandler;JLorg/apache/pulsar/client/impl/TransactionMetaStoreHandler$OpForTxnIdCallBack;)Ljava/lang/Runnable;
      12: invokeinterface #45,  2           // InterfaceMethod java/util/concurrent/ExecutorService.execute:(Ljava/lang/Runnable;)V
      17: return

  private void lambda$null$8(long, org.apache.pulsar.client.impl.TransactionMetaStoreHandler$OpForTxnIdCallBack);
    Code:
       0: aload_0
       1: getfield      #4                  // Field pendingRequests:Lorg/apache/pulsar/common/util/collections/ConcurrentLongHashMap;
       4: lload_1
       5: invokevirtual #193                // Method org/apache/pulsar/common/util/collections/ConcurrentLongHashMap.containsKey:(J)Z
       8: ifne          37
      11: getstatic     #38                 // Field LOG:Lorg/slf4j/Logger;
      14: invokeinterface #49,  1           // InterfaceMethod org/slf4j/Logger.isDebugEnabled:()Z
      19: ifeq          36
      22: getstatic     #38                 // Field LOG:Lorg/slf4j/Logger;
      25: ldc           #194                // String The request {} already timeout
      27: lload_1
      28: invokestatic  #40                 // Method java/lang/Long.valueOf:(J)Ljava/lang/Long;
      31: invokeinterface #52,  3           // InterfaceMethod org/slf4j/Logger.debug:(Ljava/lang/String;Ljava/lang/Object;)V
      36: return
      37: aload_0
      38: aload_3
      39: invokespecial #195                // Method checkStateAndSendRequest:(Lorg/apache/pulsar/client/impl/TransactionMetaStoreHandler$OpBase;)Z
      42: ifne          54
      45: aload_0
      46: getfield      #4                  // Field pendingRequests:Lorg/apache/pulsar/common/util/collections/ConcurrentLongHashMap;
      49: lload_1
      50: invokevirtual #170                // Method org/apache/pulsar/common/util/collections/ConcurrentLongHashMap.remove:(J)Ljava/lang/Object;
      53: pop
      54: return

  private void lambda$newTransactionAsync$7(long, org.apache.pulsar.client.impl.TransactionMetaStoreHandler$OpForTxnIdCallBack);
    Code:
       0: aload_0
       1: getfield      #4                  // Field pendingRequests:Lorg/apache/pulsar/common/util/collections/ConcurrentLongHashMap;
       4: lload_1
       5: aload_3
       6: invokevirtual #185                // Method org/apache/pulsar/common/util/collections/ConcurrentLongHashMap.put:(JLjava/lang/Object;)Ljava/lang/Object;
       9: pop
      10: aload_0
      11: getfield      #8                  // Field timeoutQueue:Ljava/util/concurrent/ConcurrentLinkedQueue;
      14: new           #165                // class org/apache/pulsar/client/impl/TransactionMetaStoreHandler$RequestTime
      17: dup
      18: invokestatic  #167                // Method java/lang/System.currentTimeMillis:()J
      21: lload_1
      22: invokespecial #196                // Method org/apache/pulsar/client/impl/TransactionMetaStoreHandler$RequestTime."<init>":(JJ)V
      25: invokevirtual #197                // Method java/util/concurrent/ConcurrentLinkedQueue.add:(Ljava/lang/Object;)Z
      28: pop
      29: aload_0
      30: aload_3
      31: invokespecial #195                // Method checkStateAndSendRequest:(Lorg/apache/pulsar/client/impl/TransactionMetaStoreHandler$OpBase;)Z
      34: ifne          46
      37: aload_0
      38: getfield      #4                  // Field pendingRequests:Lorg/apache/pulsar/common/util/collections/ConcurrentLongHashMap;
      41: lload_1
      42: invokevirtual #170                // Method org/apache/pulsar/common/util/collections/ConcurrentLongHashMap.remove:(J)Ljava/lang/Object;
      45: pop
      46: return

  private void lambda$failPendingRequest$6(long, org.apache.pulsar.client.impl.TransactionMetaStoreHandler$OpBase);
    Code:
       0: aload_3
       1: ifnull        36
       4: aload_3
       5: getfield      #109                // Field org/apache/pulsar/client/impl/TransactionMetaStoreHandler$OpBase.callback:Ljava/util/concurrent/CompletableFuture;
       8: invokevirtual #42                 // Method java/util/concurrent/CompletableFuture.isDone:()Z
      11: ifne          36
      14: aload_3
      15: getfield      #109                // Field org/apache/pulsar/client/impl/TransactionMetaStoreHandler$OpBase.callback:Ljava/util/concurrent/CompletableFuture;
      18: new           #223                // class org/apache/pulsar/client/api/PulsarClientException$AlreadyClosedException
      21: dup
      22: ldc           #224                // String Could not get response from transaction meta store when the transaction meta store has already close.
      24: invokespecial #225                // Method org/apache/pulsar/client/api/PulsarClientException$AlreadyClosedException."<init>":(Ljava/lang/String;)V
      27: invokevirtual #43                 // Method java/util/concurrent/CompletableFuture.completeExceptionally:(Ljava/lang/Throwable;)Z
      30: pop
      31: aload_0
      32: aload_3
      33: invokespecial #150                // Method onResponse:(Lorg/apache/pulsar/client/impl/TransactionMetaStoreHandler$OpBase;)V
      36: return

  private void lambda$connectionOpened$5(org.apache.pulsar.client.impl.ClientCnx);
    Code:
       0: getstatic     #38                 // Field LOG:Lorg/slf4j/Logger;
       3: ldc           #226                // String Transaction meta handler with transaction coordinator id {} connection opened.
       5: aload_0
       6: getfield      #5                  // Field transactionCoordinatorId:J
       9: invokestatic  #40                 // Method java/lang/Long.valueOf:(J)Ljava/lang/Long;
      12: invokeinterface #227,  3          // InterfaceMethod org/slf4j/Logger.info:(Ljava/lang/String;Ljava/lang/Object;)V
      17: aload_0
      18: invokevirtual #104                // Method getState:()Lorg/apache/pulsar/client/impl/HandlerState$State;
      21: getstatic     #163                // Field org/apache/pulsar/client/impl/HandlerState$State.Closing:Lorg/apache/pulsar/client/impl/HandlerState$State;
      24: if_acmpeq     37
      27: aload_0
      28: invokevirtual #104                // Method getState:()Lorg/apache/pulsar/client/impl/HandlerState$State;
      31: getstatic     #157                // Field org/apache/pulsar/client/impl/HandlerState$State.Closed:Lorg/apache/pulsar/client/impl/HandlerState$State;
      34: if_acmpne     49
      37: aload_0
      38: getstatic     #157                // Field org/apache/pulsar/client/impl/HandlerState$State.Closed:Lorg/apache/pulsar/client/impl/HandlerState$State;
      41: invokevirtual #158                // Method setState:(Lorg/apache/pulsar/client/impl/HandlerState$State;)V
      44: aload_0
      45: invokespecial #228                // Method failPendingRequest:()V
      48: return
      49: aload_0
      50: getfield      #32                 // Field connectionHandler:Lorg/apache/pulsar/client/impl/ConnectionHandler;
      53: aload_1
      54: invokevirtual #229                // Method org/apache/pulsar/client/impl/ConnectionHandler.setClientCnx:(Lorg/apache/pulsar/client/impl/ClientCnx;)V
      57: aload_1
      58: aload_0
      59: getfield      #5                  // Field transactionCoordinatorId:J
      62: aload_0
      63: invokevirtual #230                // Method org/apache/pulsar/client/impl/ClientCnx.registerTransactionMetaStoreHandler:(JLorg/apache/pulsar/client/impl/TransactionMetaStoreHandler;)V
      66: aload_1
      67: invokevirtual #231                // Method org/apache/pulsar/client/impl/ClientCnx.getRemoteEndpointProtocolVersion:()I
      70: getstatic     #232                // Field org/apache/pulsar/common/api/proto/ProtocolVersion.v18:Lorg/apache/pulsar/common/api/proto/ProtocolVersion;
      73: invokevirtual #233                // Method org/apache/pulsar/common/api/proto/ProtocolVersion.getValue:()I
      76: if_icmple     128
      79: aload_0
      80: getfield      #56                 // Field client:Lorg/apache/pulsar/client/impl/PulsarClientImpl;
      83: invokevirtual #57                 // Method org/apache/pulsar/client/impl/PulsarClientImpl.newRequestId:()J
      86: lstore_2
      87: aload_0
      88: getfield      #5                  // Field transactionCoordinatorId:J
      91: lload_2
      92: invokestatic  #234                // Method org/apache/pulsar/common/protocol/Commands.newTcClientConnectRequest:(JJ)Lio/netty/buffer/ByteBuf;
      95: astore        4
      97: aload_1
      98: aload         4
     100: lload_2
     101: invokevirtual #235                // Method org/apache/pulsar/client/impl/ClientCnx.sendRequestWithId:(Lio/netty/buffer/ByteBuf;J)Ljava/util/concurrent/CompletableFuture;
     104: aload_0
     105: aload_1
     106: invokedynamic #236,  0            // InvokeDynamic #19:run:(Lorg/apache/pulsar/client/impl/TransactionMetaStoreHandler;Lorg/apache/pulsar/client/impl/ClientCnx;)Ljava/lang/Runnable;
     111: invokevirtual #237                // Method java/util/concurrent/CompletableFuture.thenRun:(Ljava/lang/Runnable;)Ljava/util/concurrent/CompletableFuture;
     114: aload_0
     115: aload_1
     116: invokedynamic #238,  0            // InvokeDynamic #20:apply:(Lorg/apache/pulsar/client/impl/TransactionMetaStoreHandler;Lorg/apache/pulsar/client/impl/ClientCnx;)Ljava/util/function/Function;
     121: invokevirtual #239                // Method java/util/concurrent/CompletableFuture.exceptionally:(Ljava/util/function/Function;)Ljava/util/concurrent/CompletableFuture;
     124: pop
     125: goto          154
     128: aload_0
     129: invokevirtual #240                // Method changeToReadyState:()Z
     132: ifne          145
     135: aload_1
     136: invokevirtual #241                // Method org/apache/pulsar/client/impl/ClientCnx.channel:()Lio/netty/channel/Channel;
     139: invokeinterface #242,  1          // InterfaceMethod io/netty/channel/Channel.close:()Lio/netty/channel/ChannelFuture;
     144: pop
     145: aload_0
     146: getfield      #33                 // Field connectFuture:Ljava/util/concurrent/CompletableFuture;
     149: aconst_null
     150: invokevirtual #180                // Method java/util/concurrent/CompletableFuture.complete:(Ljava/lang/Object;)Z
     153: pop
     154: return

  private java.lang.Void lambda$null$4(org.apache.pulsar.client.impl.ClientCnx, java.lang.Throwable);
    Code:
       0: aload_0
       1: getfield      #37                 // Field internalPinnedExecutor:Ljava/util/concurrent/ExecutorService;
       4: aload_0
       5: aload_2
       6: aload_1
       7: invokedynamic #243,  0            // InvokeDynamic #21:run:(Lorg/apache/pulsar/client/impl/TransactionMetaStoreHandler;Ljava/lang/Throwable;Lorg/apache/pulsar/client/impl/ClientCnx;)Ljava/lang/Runnable;
      12: invokeinterface #45,  2           // InterfaceMethod java/util/concurrent/ExecutorService.execute:(Ljava/lang/Runnable;)V
      17: aconst_null
      18: areturn

  private void lambda$null$3(java.lang.Throwable, org.apache.pulsar.client.impl.ClientCnx);
    Code:
       0: getstatic     #38                 // Field LOG:Lorg/slf4j/Logger;
       3: ldc           #244                // String Transaction coordinator client connect fail! tcId : {}
       5: aload_0
       6: getfield      #5                  // Field transactionCoordinatorId:J
       9: invokestatic  #40                 // Method java/lang/Long.valueOf:(J)Ljava/lang/Long;
      12: aload_1
      13: invokevirtual #245                // Method java/lang/Throwable.getCause:()Ljava/lang/Throwable;
      16: invokeinterface #41,  4           // InterfaceMethod org/slf4j/Logger.error:(Ljava/lang/String;Ljava/lang/Object;Ljava/lang/Object;)V
      21: aload_0
      22: invokevirtual #104                // Method getState:()Lorg/apache/pulsar/client/impl/HandlerState$State;
      25: getstatic     #163                // Field org/apache/pulsar/client/impl/HandlerState$State.Closing:Lorg/apache/pulsar/client/impl/HandlerState$State;
      28: if_acmpeq     51
      31: aload_0
      32: invokevirtual #104                // Method getState:()Lorg/apache/pulsar/client/impl/HandlerState$State;
      35: getstatic     #157                // Field org/apache/pulsar/client/impl/HandlerState$State.Closed:Lorg/apache/pulsar/client/impl/HandlerState$State;
      38: if_acmpeq     51
      41: aload_1
      42: invokevirtual #245                // Method java/lang/Throwable.getCause:()Ljava/lang/Throwable;
      45: instanceof    #246                // class org/apache/pulsar/client/api/PulsarClientException$NotAllowedException
      48: ifeq          71
      51: aload_0
      52: getstatic     #157                // Field org/apache/pulsar/client/impl/HandlerState$State.Closed:Lorg/apache/pulsar/client/impl/HandlerState$State;
      55: invokevirtual #158                // Method setState:(Lorg/apache/pulsar/client/impl/HandlerState$State;)V
      58: aload_2
      59: invokevirtual #241                // Method org/apache/pulsar/client/impl/ClientCnx.channel:()Lio/netty/channel/Channel;
      62: invokeinterface #242,  1          // InterfaceMethod io/netty/channel/Channel.close:()Lio/netty/channel/ChannelFuture;
      67: pop
      68: goto          82
      71: aload_0
      72: getfield      #32                 // Field connectionHandler:Lorg/apache/pulsar/client/impl/ConnectionHandler;
      75: aload_1
      76: invokevirtual #245                // Method java/lang/Throwable.getCause:()Ljava/lang/Throwable;
      79: invokevirtual #108                // Method org/apache/pulsar/client/impl/ConnectionHandler.reconnectLater:(Ljava/lang/Throwable;)V
      82: return

  private void lambda$null$2(org.apache.pulsar.client.impl.ClientCnx);
    Code:
       0: aload_0
       1: getfield      #37                 // Field internalPinnedExecutor:Ljava/util/concurrent/ExecutorService;
       4: aload_0
       5: aload_1
       6: invokedynamic #247,  0            // InvokeDynamic #22:run:(Lorg/apache/pulsar/client/impl/TransactionMetaStoreHandler;Lorg/apache/pulsar/client/impl/ClientCnx;)Ljava/lang/Runnable;
      11: invokeinterface #45,  2           // InterfaceMethod java/util/concurrent/ExecutorService.execute:(Ljava/lang/Runnable;)V
      16: return

  private void lambda$null$1(org.apache.pulsar.client.impl.ClientCnx);
    Code:
       0: getstatic     #38                 // Field LOG:Lorg/slf4j/Logger;
       3: ldc           #248                // String Transaction coordinator client connect success! tcId : {}
       5: aload_0
       6: getfield      #5                  // Field transactionCoordinatorId:J
       9: invokestatic  #40                 // Method java/lang/Long.valueOf:(J)Ljava/lang/Long;
      12: invokeinterface #227,  3          // InterfaceMethod org/slf4j/Logger.info:(Ljava/lang/String;Ljava/lang/Object;)V
      17: aload_0
      18: invokevirtual #240                // Method changeToReadyState:()Z
      21: ifne          41
      24: aload_0
      25: getstatic     #157                // Field org/apache/pulsar/client/impl/HandlerState$State.Closed:Lorg/apache/pulsar/client/impl/HandlerState$State;
      28: invokevirtual #158                // Method setState:(Lorg/apache/pulsar/client/impl/HandlerState$State;)V
      31: aload_1
      32: invokevirtual #241                // Method org/apache/pulsar/client/impl/ClientCnx.channel:()Lio/netty/channel/Channel;
      35: invokeinterface #242,  1          // InterfaceMethod io/netty/channel/Channel.close:()Lio/netty/channel/ChannelFuture;
      40: pop
      41: aload_0
      42: getfield      #33                 // Field connectFuture:Ljava/util/concurrent/CompletableFuture;
      45: invokevirtual #42                 // Method java/util/concurrent/CompletableFuture.isDone:()Z
      48: ifne          60
      51: aload_0
      52: getfield      #33                 // Field connectFuture:Ljava/util/concurrent/CompletableFuture;
      55: aconst_null
      56: invokevirtual #180                // Method java/util/concurrent/CompletableFuture.complete:(Ljava/lang/Object;)Z
      59: pop
      60: aload_0
      61: getfield      #32                 // Field connectionHandler:Lorg/apache/pulsar/client/impl/ConnectionHandler;
      64: invokevirtual #249                // Method org/apache/pulsar/client/impl/ConnectionHandler.resetBackoff:()V
      67: aload_0
      68: getfield      #4                  // Field pendingRequests:Lorg/apache/pulsar/common/util/collections/ConcurrentLongHashMap;
      71: aload_0
      72: invokedynamic #250,  0            // InvokeDynamic #23:accept:(Lorg/apache/pulsar/client/impl/TransactionMetaStoreHandler;)Lorg/apache/pulsar/common/util/collections/ConcurrentLongHashMap$EntryProcessor;
      77: invokevirtual #47                 // Method org/apache/pulsar/common/util/collections/ConcurrentLongHashMap.forEach:(Lorg/apache/pulsar/common/util/collections/ConcurrentLongHashMap$EntryProcessor;)V
      80: return

  private void lambda$null$0(long, org.apache.pulsar.client.impl.TransactionMetaStoreHandler$OpBase);
    Code:
       0: aload_0
       1: aload_3
       2: invokespecial #195                // Method checkStateAndSendRequest:(Lorg/apache/pulsar/client/impl/TransactionMetaStoreHandler$OpBase;)Z
       5: pop
       6: return

  static {};
    Code:
       0: ldc           #251                // class org/apache/pulsar/client/impl/TransactionMetaStoreHandler
       2: invokestatic  #252                // Method org/slf4j/LoggerFactory.getLogger:(Ljava/lang/Class;)Lorg/slf4j/Logger;
       5: putstatic     #38                 // Field LOG:Lorg/slf4j/Logger;
       8: return
}
