Compiled from "WeldContextSetup.java"
class org.jboss.as.weld.arquillian.WeldContextSetup$ContextMapThreadLocal extends java.lang.ThreadLocal<java.util.Map<java.lang.String, java.lang.Object>> {
  private org.jboss.as.weld.arquillian.WeldContextSetup$ContextMapThreadLocal();
    Code:
       0: aload_0
       1: invokespecial #2                  // Method java/lang/ThreadLocal."<init>":()V
       4: return

  protected java.util.Map<java.lang.String, java.lang.Object> initialValue();
    Code:
       0: new           #3                  // class java/util/concurrent/ConcurrentHashMap
       3: dup
       4: invokespecial #4                  // Method java/util/concurrent/ConcurrentHashMap."<init>":()V
       7: areturn

  protected java.lang.Object initialValue();
    Code:
       0: aload_0
       1: invokevirtual #5                  // Method initialValue:()Ljava/util/Map;
       4: areturn

  org.jboss.as.weld.arquillian.WeldContextSetup$ContextMapThreadLocal(org.jboss.as.weld.arquillian.WeldContextSetup$1);
    Code:
       0: aload_0
       1: invokespecial #1                  // Method "<init>":()V
       4: return
}
