Compiled from "All.java"
public class org.apache.neethi.All extends org.apache.neethi.AbstractPolicyOperator {
  public org.apache.neethi.All();
    Code:
       0: aload_0
       1: invokespecial #1                  // Method org/apache/neethi/AbstractPolicyOperator."<init>":()V
       4: return

  public org.apache.neethi.All(org.apache.neethi.PolicyOperator);
    Code:
       0: aload_0
       1: aload_1
       2: invokespecial #2                  // Method org/apache/neethi/AbstractPolicyOperator."<init>":(Lorg/apache/neethi/PolicyOperator;)V
       5: return

  public void addAssertion(org.apache.neethi.Assertion);
    Code:
       0: aload_0
       1: aload_1
       2: invokevirtual #3                  // Method addPolicyComponent:(Lorg/apache/neethi/PolicyComponent;)V
       5: return

  public java.util.List<org.apache.neethi.PolicyComponent> getAssertions();
    Code:
       0: aload_0
       1: getfield      #4                  // Field policyComponents:Ljava/util/List;
       4: areturn

  public void serialize(javax.xml.stream.XMLStreamWriter) throws javax.xml.stream.XMLStreamException;
    Code:
       0: aload_1
       1: invokestatic  #5                  // Method org/apache/neethi/Constants.findPolicyNamespace:(Ljavax/xml/stream/XMLStreamWriter;)Ljava/lang/String;
       4: astore_2
       5: aload_1
       6: aload_2
       7: invokeinterface #6,  2            // InterfaceMethod javax/xml/stream/XMLStreamWriter.getPrefix:(Ljava/lang/String;)Ljava/lang/String;
      12: astore_3
      13: aload_3
      14: ifnonnull     49
      17: aload_1
      18: ldc           #7                  // String wsp
      20: ldc           #8                  // String All
      22: aload_2
      23: invokeinterface #9,  4            // InterfaceMethod javax/xml/stream/XMLStreamWriter.writeStartElement:(Ljava/lang/String;Ljava/lang/String;Ljava/lang/String;)V
      28: aload_1
      29: ldc           #7                  // String wsp
      31: aload_2
      32: invokeinterface #10,  3           // InterfaceMethod javax/xml/stream/XMLStreamWriter.writeNamespace:(Ljava/lang/String;Ljava/lang/String;)V
      37: aload_1
      38: ldc           #7                  // String wsp
      40: aload_2
      41: invokeinterface #11,  3           // InterfaceMethod javax/xml/stream/XMLStreamWriter.setPrefix:(Ljava/lang/String;Ljava/lang/String;)V
      46: goto          58
      49: aload_1
      50: aload_2
      51: ldc           #8                  // String All
      53: invokeinterface #12,  3           // InterfaceMethod javax/xml/stream/XMLStreamWriter.writeStartElement:(Ljava/lang/String;Ljava/lang/String;)V
      58: aload_0
      59: invokevirtual #13                 // Method getPolicyComponents:()Ljava/util/List;
      62: invokeinterface #14,  1           // InterfaceMethod java/util/List.iterator:()Ljava/util/Iterator;
      67: astore        4
      69: aload         4
      71: invokeinterface #15,  1           // InterfaceMethod java/util/Iterator.hasNext:()Z
      76: ifeq          102
      79: aload         4
      81: invokeinterface #16,  1           // InterfaceMethod java/util/Iterator.next:()Ljava/lang/Object;
      86: checkcast     #17                 // class org/apache/neethi/PolicyComponent
      89: astore        5
      91: aload         5
      93: aload_1
      94: invokeinterface #18,  2           // InterfaceMethod org/apache/neethi/PolicyComponent.serialize:(Ljavax/xml/stream/XMLStreamWriter;)V
      99: goto          69
     102: aload_1
     103: invokeinterface #19,  1           // InterfaceMethod javax/xml/stream/XMLStreamWriter.writeEndElement:()V
     108: return

  public short getType();
    Code:
       0: iconst_3
       1: ireturn
}
