Compiled from "LauncherCompat.scala"
public interface wvlet.airframe.launcher.LauncherBaseCompat {
  public static wvlet.airframe.launcher.Launcher addModule$(wvlet.airframe.launcher.LauncherBaseCompat, java.lang.String, java.lang.String, scala.reflect.api.TypeTags$TypeTag);
    Code:
       0: aload_0
       1: aload_1
       2: aload_2
       3: aload_3
       4: invokespecial #23                 // InterfaceMethod addModule:(Ljava/lang/String;Ljava/lang/String;Lscala/reflect/api/TypeTags$TypeTag;)Lwvlet/airframe/launcher/Launcher;
       7: areturn

  public default <M> wvlet.airframe.launcher.Launcher addModule(java.lang.String, java.lang.String, scala.reflect.api.TypeTags$TypeTag<M>);
    Code:
       0: getstatic     #33                 // Field wvlet/airframe/launcher/Launcher$.MODULE$:Lwvlet/airframe/launcher/Launcher$;
       3: aload_0
       4: checkcast     #35                 // class wvlet/airframe/launcher/Launcher
       7: invokevirtual #39                 // Method wvlet/airframe/launcher/Launcher.config:()Lwvlet/airframe/launcher/LauncherConfig;
      10: aload_0
      11: checkcast     #35                 // class wvlet/airframe/launcher/Launcher
      14: invokevirtual #43                 // Method wvlet/airframe/launcher/Launcher.mainLauncher:()Lwvlet/airframe/launcher/CommandLauncher;
      17: aload_1
      18: aload_2
      19: aload_3
      20: invokevirtual #49                 // Method wvlet/airframe/launcher/CommandLauncher.addCommandModule:(Ljava/lang/String;Ljava/lang/String;Lscala/reflect/api/TypeTags$TypeTag;)Lwvlet/airframe/launcher/CommandLauncher;
      23: invokevirtual #53                 // Method wvlet/airframe/launcher/Launcher$.apply:(Lwvlet/airframe/launcher/LauncherConfig;Lwvlet/airframe/launcher/CommandLauncher;)Lwvlet/airframe/launcher/Launcher;
      26: areturn

  public static void $init$(wvlet.airframe.launcher.LauncherBaseCompat);
    Code:
       0: return
}
