Compiled from "InputBuffer.java"
public class org.apache.hadoop.io.InputBuffer extends java.io.FilterInputStream {
  private org.apache.hadoop.io.InputBuffer$Buffer buffer;

  public org.apache.hadoop.io.InputBuffer();
    Code:
       0: aload_0
       1: new           #1                  // class org/apache/hadoop/io/InputBuffer$Buffer
       4: dup
       5: invokespecial #2                  // Method org/apache/hadoop/io/InputBuffer$Buffer."<init>":()V
       8: invokespecial #3                  // Method "<init>":(Lorg/apache/hadoop/io/InputBuffer$Buffer;)V
      11: return

  private org.apache.hadoop.io.InputBuffer(org.apache.hadoop.io.InputBuffer$Buffer);
    Code:
       0: aload_0
       1: aload_1
       2: invokespecial #4                  // Method java/io/FilterInputStream."<init>":(Ljava/io/InputStream;)V
       5: aload_0
       6: aload_1
       7: putfield      #5                  // Field buffer:Lorg/apache/hadoop/io/InputBuffer$Buffer;
      10: return

  public void reset(byte[], int);
    Code:
       0: aload_0
       1: getfield      #5                  // Field buffer:Lorg/apache/hadoop/io/InputBuffer$Buffer;
       4: aload_1
       5: iconst_0
       6: iload_2
       7: invokevirtual #6                  // Method org/apache/hadoop/io/InputBuffer$Buffer.reset:([BII)V
      10: return

  public void reset(byte[], int, int);
    Code:
       0: aload_0
       1: getfield      #5                  // Field buffer:Lorg/apache/hadoop/io/InputBuffer$Buffer;
       4: aload_1
       5: iload_2
       6: iload_3
       7: invokevirtual #6                  // Method org/apache/hadoop/io/InputBuffer$Buffer.reset:([BII)V
      10: return

  public int getPosition();
    Code:
       0: aload_0
       1: getfield      #5                  // Field buffer:Lorg/apache/hadoop/io/InputBuffer$Buffer;
       4: invokevirtual #7                  // Method org/apache/hadoop/io/InputBuffer$Buffer.getPosition:()I
       7: ireturn

  public int getLength();
    Code:
       0: aload_0
       1: getfield      #5                  // Field buffer:Lorg/apache/hadoop/io/InputBuffer$Buffer;
       4: invokevirtual #8                  // Method org/apache/hadoop/io/InputBuffer$Buffer.getLength:()I
       7: ireturn
}
