Compiled from "ExtensionRegistry.java"
class org.jboss.as.controller.extension.ExtensionRegistry$DeploymentManagementResourceRegistration implements org.jboss.as.controller.registry.ManagementResourceRegistration {
  private final org.jboss.as.controller.registry.ManagementResourceRegistration deployments;

  private final org.jboss.as.controller.registry.ManagementResourceRegistration subdeployments;

  public boolean isOrderedChildResource();
    Code:
       0: iconst_0
       1: ireturn

  public java.util.Set<java.lang.String> getOrderedChildTypes();
    Code:
       0: invokestatic  #2                  // Method java/util/Collections.emptySet:()Ljava/util/Set;
       3: areturn

  private org.jboss.as.controller.extension.ExtensionRegistry$DeploymentManagementResourceRegistration(org.jboss.as.controller.registry.ManagementResourceRegistration, org.jboss.as.controller.registry.ManagementResourceRegistration);
    Code:
       0: aload_0
       1: invokespecial #3                  // Method java/lang/Object."<init>":()V
       4: aload_0
       5: aload_1
       6: putfield      #4                  // Field deployments:Lorg/jboss/as/controller/registry/ManagementResourceRegistration;
       9: aload_0
      10: aload_2
      11: putfield      #5                  // Field subdeployments:Lorg/jboss/as/controller/registry/ManagementResourceRegistration;
      14: return

  public org.jboss.as.controller.PathAddress getPathAddress();
    Code:
       0: aload_0
       1: getfield      #4                  // Field deployments:Lorg/jboss/as/controller/registry/ManagementResourceRegistration;
       4: invokeinterface #6,  1            // InterfaceMethod org/jboss/as/controller/registry/ManagementResourceRegistration.getPathAddress:()Lorg/jboss/as/controller/PathAddress;
       9: areturn

  public int getMaxOccurs();
    Code:
       0: aload_0
       1: getfield      #4                  // Field deployments:Lorg/jboss/as/controller/registry/ManagementResourceRegistration;
       4: invokeinterface #7,  1            // InterfaceMethod org/jboss/as/controller/registry/ManagementResourceRegistration.getMaxOccurs:()I
       9: ireturn

  public int getMinOccurs();
    Code:
       0: aload_0
       1: getfield      #4                  // Field deployments:Lorg/jboss/as/controller/registry/ManagementResourceRegistration;
       4: invokeinterface #8,  1            // InterfaceMethod org/jboss/as/controller/registry/ManagementResourceRegistration.getMinOccurs:()I
       9: ireturn

  public boolean isRuntimeOnly();
    Code:
       0: aload_0
       1: getfield      #4                  // Field deployments:Lorg/jboss/as/controller/registry/ManagementResourceRegistration;
       4: invokeinterface #9,  1            // InterfaceMethod org/jboss/as/controller/registry/ManagementResourceRegistration.isRuntimeOnly:()Z
       9: ireturn

  public void setRuntimeOnly(boolean);
    Code:
       0: aload_0
       1: getfield      #4                  // Field deployments:Lorg/jboss/as/controller/registry/ManagementResourceRegistration;
       4: iload_1
       5: invokeinterface #10,  2           // InterfaceMethod org/jboss/as/controller/registry/ManagementResourceRegistration.setRuntimeOnly:(Z)V
      10: aload_0
      11: getfield      #5                  // Field subdeployments:Lorg/jboss/as/controller/registry/ManagementResourceRegistration;
      14: iload_1
      15: invokeinterface #10,  2           // InterfaceMethod org/jboss/as/controller/registry/ManagementResourceRegistration.setRuntimeOnly:(Z)V
      20: return

  public boolean isRemote();
    Code:
       0: aload_0
       1: getfield      #4                  // Field deployments:Lorg/jboss/as/controller/registry/ManagementResourceRegistration;
       4: invokeinterface #11,  1           // InterfaceMethod org/jboss/as/controller/registry/ManagementResourceRegistration.isRemote:()Z
       9: ireturn

  public org.jboss.as.controller.OperationStepHandler getOperationHandler(org.jboss.as.controller.PathAddress, java.lang.String);
    Code:
       0: aload_0
       1: getfield      #4                  // Field deployments:Lorg/jboss/as/controller/registry/ManagementResourceRegistration;
       4: aload_1
       5: aload_2
       6: invokeinterface #12,  3           // InterfaceMethod org/jboss/as/controller/registry/ManagementResourceRegistration.getOperationHandler:(Lorg/jboss/as/controller/PathAddress;Ljava/lang/String;)Lorg/jboss/as/controller/OperationStepHandler;
      11: areturn

  public org.jboss.as.controller.descriptions.DescriptionProvider getOperationDescription(org.jboss.as.controller.PathAddress, java.lang.String);
    Code:
       0: aload_0
       1: getfield      #4                  // Field deployments:Lorg/jboss/as/controller/registry/ManagementResourceRegistration;
       4: aload_1
       5: aload_2
       6: invokeinterface #13,  3           // InterfaceMethod org/jboss/as/controller/registry/ManagementResourceRegistration.getOperationDescription:(Lorg/jboss/as/controller/PathAddress;Ljava/lang/String;)Lorg/jboss/as/controller/descriptions/DescriptionProvider;
      11: areturn

  public java.util.Set<org.jboss.as.controller.registry.OperationEntry$Flag> getOperationFlags(org.jboss.as.controller.PathAddress, java.lang.String);
    Code:
       0: aload_0
       1: getfield      #4                  // Field deployments:Lorg/jboss/as/controller/registry/ManagementResourceRegistration;
       4: aload_1
       5: aload_2
       6: invokeinterface #14,  3           // InterfaceMethod org/jboss/as/controller/registry/ManagementResourceRegistration.getOperationFlags:(Lorg/jboss/as/controller/PathAddress;Ljava/lang/String;)Ljava/util/Set;
      11: areturn

  public org.jboss.as.controller.registry.OperationEntry getOperationEntry(org.jboss.as.controller.PathAddress, java.lang.String);
    Code:
       0: aload_0
       1: getfield      #4                  // Field deployments:Lorg/jboss/as/controller/registry/ManagementResourceRegistration;
       4: aload_1
       5: aload_2
       6: invokeinterface #15,  3           // InterfaceMethod org/jboss/as/controller/registry/ManagementResourceRegistration.getOperationEntry:(Lorg/jboss/as/controller/PathAddress;Ljava/lang/String;)Lorg/jboss/as/controller/registry/OperationEntry;
      11: areturn

  public java.util.Set<java.lang.String> getAttributeNames(org.jboss.as.controller.PathAddress);
    Code:
       0: aload_0
       1: getfield      #4                  // Field deployments:Lorg/jboss/as/controller/registry/ManagementResourceRegistration;
       4: aload_1
       5: invokeinterface #16,  2           // InterfaceMethod org/jboss/as/controller/registry/ManagementResourceRegistration.getAttributeNames:(Lorg/jboss/as/controller/PathAddress;)Ljava/util/Set;
      10: areturn

  public org.jboss.as.controller.registry.AttributeAccess getAttributeAccess(org.jboss.as.controller.PathAddress, java.lang.String);
    Code:
       0: aload_0
       1: getfield      #4                  // Field deployments:Lorg/jboss/as/controller/registry/ManagementResourceRegistration;
       4: aload_1
       5: aload_2
       6: invokeinterface #17,  3           // InterfaceMethod org/jboss/as/controller/registry/ManagementResourceRegistration.getAttributeAccess:(Lorg/jboss/as/controller/PathAddress;Ljava/lang/String;)Lorg/jboss/as/controller/registry/AttributeAccess;
      11: areturn

  public java.util.Map<java.lang.String, org.jboss.as.controller.registry.NotificationEntry> getNotificationDescriptions(org.jboss.as.controller.PathAddress, boolean);
    Code:
       0: aload_0
       1: getfield      #4                  // Field deployments:Lorg/jboss/as/controller/registry/ManagementResourceRegistration;
       4: aload_1
       5: iload_2
       6: invokeinterface #18,  3           // InterfaceMethod org/jboss/as/controller/registry/ManagementResourceRegistration.getNotificationDescriptions:(Lorg/jboss/as/controller/PathAddress;Z)Ljava/util/Map;
      11: areturn

  public java.util.Set<java.lang.String> getChildNames(org.jboss.as.controller.PathAddress);
    Code:
       0: aload_0
       1: getfield      #4                  // Field deployments:Lorg/jboss/as/controller/registry/ManagementResourceRegistration;
       4: aload_1
       5: invokeinterface #19,  2           // InterfaceMethod org/jboss/as/controller/registry/ManagementResourceRegistration.getChildNames:(Lorg/jboss/as/controller/PathAddress;)Ljava/util/Set;
      10: areturn

  public java.util.Set<org.jboss.as.controller.PathElement> getChildAddresses(org.jboss.as.controller.PathAddress);
    Code:
       0: aload_0
       1: getfield      #4                  // Field deployments:Lorg/jboss/as/controller/registry/ManagementResourceRegistration;
       4: aload_1
       5: invokeinterface #20,  2           // InterfaceMethod org/jboss/as/controller/registry/ManagementResourceRegistration.getChildAddresses:(Lorg/jboss/as/controller/PathAddress;)Ljava/util/Set;
      10: areturn

  public org.jboss.as.controller.descriptions.DescriptionProvider getModelDescription(org.jboss.as.controller.PathAddress);
    Code:
       0: aload_0
       1: getfield      #4                  // Field deployments:Lorg/jboss/as/controller/registry/ManagementResourceRegistration;
       4: aload_1
       5: invokeinterface #21,  2           // InterfaceMethod org/jboss/as/controller/registry/ManagementResourceRegistration.getModelDescription:(Lorg/jboss/as/controller/PathAddress;)Lorg/jboss/as/controller/descriptions/DescriptionProvider;
      10: areturn

  public java.util.Map<java.lang.String, org.jboss.as.controller.registry.OperationEntry> getOperationDescriptions(org.jboss.as.controller.PathAddress, boolean);
    Code:
       0: aload_0
       1: getfield      #4                  // Field deployments:Lorg/jboss/as/controller/registry/ManagementResourceRegistration;
       4: aload_1
       5: iload_2
       6: invokeinterface #22,  3           // InterfaceMethod org/jboss/as/controller/registry/ManagementResourceRegistration.getOperationDescriptions:(Lorg/jboss/as/controller/PathAddress;Z)Ljava/util/Map;
      11: areturn

  public org.jboss.as.controller.ProxyController getProxyController(org.jboss.as.controller.PathAddress);
    Code:
       0: aload_0
       1: getfield      #4                  // Field deployments:Lorg/jboss/as/controller/registry/ManagementResourceRegistration;
       4: aload_1
       5: invokeinterface #23,  2           // InterfaceMethod org/jboss/as/controller/registry/ManagementResourceRegistration.getProxyController:(Lorg/jboss/as/controller/PathAddress;)Lorg/jboss/as/controller/ProxyController;
      10: areturn

  public java.util.Set<org.jboss.as.controller.ProxyController> getProxyControllers(org.jboss.as.controller.PathAddress);
    Code:
       0: aload_0
       1: getfield      #4                  // Field deployments:Lorg/jboss/as/controller/registry/ManagementResourceRegistration;
       4: aload_1
       5: invokeinterface #24,  2           // InterfaceMethod org/jboss/as/controller/registry/ManagementResourceRegistration.getProxyControllers:(Lorg/jboss/as/controller/PathAddress;)Ljava/util/Set;
      10: areturn

  public org.jboss.as.controller.registry.ManagementResourceRegistration getOverrideModel(java.lang.String);
    Code:
       0: aload_0
       1: getfield      #4                  // Field deployments:Lorg/jboss/as/controller/registry/ManagementResourceRegistration;
       4: aload_1
       5: invokeinterface #25,  2           // InterfaceMethod org/jboss/as/controller/registry/ManagementResourceRegistration.getOverrideModel:(Ljava/lang/String;)Lorg/jboss/as/controller/registry/ManagementResourceRegistration;
      10: areturn

  public org.jboss.as.controller.registry.ManagementResourceRegistration getSubModel(org.jboss.as.controller.PathAddress);
    Code:
       0: aload_0
       1: getfield      #4                  // Field deployments:Lorg/jboss/as/controller/registry/ManagementResourceRegistration;
       4: aload_1
       5: invokeinterface #26,  2           // InterfaceMethod org/jboss/as/controller/registry/ManagementResourceRegistration.getSubModel:(Lorg/jboss/as/controller/PathAddress;)Lorg/jboss/as/controller/registry/ManagementResourceRegistration;
      10: areturn

  public java.util.List<org.jboss.as.controller.access.management.AccessConstraintDefinition> getAccessConstraints();
    Code:
       0: aload_0
       1: getfield      #4                  // Field deployments:Lorg/jboss/as/controller/registry/ManagementResourceRegistration;
       4: invokeinterface #27,  1           // InterfaceMethod org/jboss/as/controller/registry/ManagementResourceRegistration.getAccessConstraints:()Ljava/util/List;
       9: areturn

  public org.jboss.as.controller.registry.ManagementResourceRegistration registerSubModel(org.jboss.as.controller.ResourceDefinition);
    Code:
       0: aload_0
       1: getfield      #4                  // Field deployments:Lorg/jboss/as/controller/registry/ManagementResourceRegistration;
       4: aload_1
       5: invokeinterface #28,  2           // InterfaceMethod org/jboss/as/controller/registry/ManagementResourceRegistration.registerSubModel:(Lorg/jboss/as/controller/ResourceDefinition;)Lorg/jboss/as/controller/registry/ManagementResourceRegistration;
      10: astore_2
      11: aload_0
      12: getfield      #5                  // Field subdeployments:Lorg/jboss/as/controller/registry/ManagementResourceRegistration;
      15: aload_1
      16: invokeinterface #28,  2           // InterfaceMethod org/jboss/as/controller/registry/ManagementResourceRegistration.registerSubModel:(Lorg/jboss/as/controller/ResourceDefinition;)Lorg/jboss/as/controller/registry/ManagementResourceRegistration;
      21: astore_3
      22: new           #29                 // class org/jboss/as/controller/extension/ExtensionRegistry$DeploymentManagementResourceRegistration
      25: dup
      26: aload_2
      27: aload_3
      28: invokespecial #1                  // Method "<init>":(Lorg/jboss/as/controller/registry/ManagementResourceRegistration;Lorg/jboss/as/controller/registry/ManagementResourceRegistration;)V
      31: areturn

  public void unregisterSubModel(org.jboss.as.controller.PathElement);
    Code:
       0: aload_0
       1: getfield      #4                  // Field deployments:Lorg/jboss/as/controller/registry/ManagementResourceRegistration;
       4: aload_1
       5: invokeinterface #30,  2           // InterfaceMethod org/jboss/as/controller/registry/ManagementResourceRegistration.unregisterSubModel:(Lorg/jboss/as/controller/PathElement;)V
      10: aload_0
      11: getfield      #5                  // Field subdeployments:Lorg/jboss/as/controller/registry/ManagementResourceRegistration;
      14: aload_1
      15: invokeinterface #30,  2           // InterfaceMethod org/jboss/as/controller/registry/ManagementResourceRegistration.unregisterSubModel:(Lorg/jboss/as/controller/PathElement;)V
      20: return

  public boolean isAllowsOverride();
    Code:
       0: aload_0
       1: getfield      #4                  // Field deployments:Lorg/jboss/as/controller/registry/ManagementResourceRegistration;
       4: invokeinterface #31,  1           // InterfaceMethod org/jboss/as/controller/registry/ManagementResourceRegistration.isAllowsOverride:()Z
       9: ireturn

  public org.jboss.as.controller.registry.ManagementResourceRegistration registerOverrideModel(java.lang.String, org.jboss.as.controller.descriptions.OverrideDescriptionProvider);
    Code:
       0: aload_0
       1: getfield      #4                  // Field deployments:Lorg/jboss/as/controller/registry/ManagementResourceRegistration;
       4: aload_1
       5: aload_2
       6: invokeinterface #32,  3           // InterfaceMethod org/jboss/as/controller/registry/ManagementResourceRegistration.registerOverrideModel:(Ljava/lang/String;Lorg/jboss/as/controller/descriptions/OverrideDescriptionProvider;)Lorg/jboss/as/controller/registry/ManagementResourceRegistration;
      11: astore_3
      12: aload_0
      13: getfield      #5                  // Field subdeployments:Lorg/jboss/as/controller/registry/ManagementResourceRegistration;
      16: aload_1
      17: aload_2
      18: invokeinterface #32,  3           // InterfaceMethod org/jboss/as/controller/registry/ManagementResourceRegistration.registerOverrideModel:(Ljava/lang/String;Lorg/jboss/as/controller/descriptions/OverrideDescriptionProvider;)Lorg/jboss/as/controller/registry/ManagementResourceRegistration;
      23: astore        4
      25: new           #29                 // class org/jboss/as/controller/extension/ExtensionRegistry$DeploymentManagementResourceRegistration
      28: dup
      29: aload_3
      30: aload         4
      32: invokespecial #1                  // Method "<init>":(Lorg/jboss/as/controller/registry/ManagementResourceRegistration;Lorg/jboss/as/controller/registry/ManagementResourceRegistration;)V
      35: areturn

  public void unregisterOverrideModel(java.lang.String);
    Code:
       0: aload_0
       1: getfield      #4                  // Field deployments:Lorg/jboss/as/controller/registry/ManagementResourceRegistration;
       4: aload_1
       5: invokeinterface #33,  2           // InterfaceMethod org/jboss/as/controller/registry/ManagementResourceRegistration.unregisterOverrideModel:(Ljava/lang/String;)V
      10: aload_0
      11: getfield      #5                  // Field subdeployments:Lorg/jboss/as/controller/registry/ManagementResourceRegistration;
      14: aload_1
      15: invokeinterface #33,  2           // InterfaceMethod org/jboss/as/controller/registry/ManagementResourceRegistration.unregisterOverrideModel:(Ljava/lang/String;)V
      20: return

  public void registerOperationHandler(org.jboss.as.controller.OperationDefinition, org.jboss.as.controller.OperationStepHandler);
    Code:
       0: aload_0
       1: aload_1
       2: aload_2
       3: iconst_0
       4: invokevirtual #34                 // Method registerOperationHandler:(Lorg/jboss/as/controller/OperationDefinition;Lorg/jboss/as/controller/OperationStepHandler;Z)V
       7: return

  public void registerOperationHandler(org.jboss.as.controller.OperationDefinition, org.jboss.as.controller.OperationStepHandler, boolean);
    Code:
       0: aload_0
       1: getfield      #4                  // Field deployments:Lorg/jboss/as/controller/registry/ManagementResourceRegistration;
       4: aload_1
       5: aload_2
       6: iload_3
       7: invokeinterface #35,  4           // InterfaceMethod org/jboss/as/controller/registry/ManagementResourceRegistration.registerOperationHandler:(Lorg/jboss/as/controller/OperationDefinition;Lorg/jboss/as/controller/OperationStepHandler;Z)V
      12: aload_0
      13: getfield      #5                  // Field subdeployments:Lorg/jboss/as/controller/registry/ManagementResourceRegistration;
      16: aload_1
      17: aload_2
      18: iload_3
      19: invokeinterface #35,  4           // InterfaceMethod org/jboss/as/controller/registry/ManagementResourceRegistration.registerOperationHandler:(Lorg/jboss/as/controller/OperationDefinition;Lorg/jboss/as/controller/OperationStepHandler;Z)V
      24: return

  public void unregisterOperationHandler(java.lang.String);
    Code:
       0: aload_0
       1: getfield      #4                  // Field deployments:Lorg/jboss/as/controller/registry/ManagementResourceRegistration;
       4: aload_1
       5: invokeinterface #36,  2           // InterfaceMethod org/jboss/as/controller/registry/ManagementResourceRegistration.unregisterOperationHandler:(Ljava/lang/String;)V
      10: aload_0
      11: getfield      #5                  // Field subdeployments:Lorg/jboss/as/controller/registry/ManagementResourceRegistration;
      14: aload_1
      15: invokeinterface #36,  2           // InterfaceMethod org/jboss/as/controller/registry/ManagementResourceRegistration.unregisterOperationHandler:(Ljava/lang/String;)V
      20: return

  public void registerReadWriteAttribute(org.jboss.as.controller.AttributeDefinition, org.jboss.as.controller.OperationStepHandler, org.jboss.as.controller.OperationStepHandler);
    Code:
       0: aload_0
       1: getfield      #4                  // Field deployments:Lorg/jboss/as/controller/registry/ManagementResourceRegistration;
       4: aload_1
       5: aload_2
       6: aload_3
       7: invokeinterface #37,  4           // InterfaceMethod org/jboss/as/controller/registry/ManagementResourceRegistration.registerReadWriteAttribute:(Lorg/jboss/as/controller/AttributeDefinition;Lorg/jboss/as/controller/OperationStepHandler;Lorg/jboss/as/controller/OperationStepHandler;)V
      12: aload_0
      13: getfield      #5                  // Field subdeployments:Lorg/jboss/as/controller/registry/ManagementResourceRegistration;
      16: aload_1
      17: aload_2
      18: aload_3
      19: invokeinterface #37,  4           // InterfaceMethod org/jboss/as/controller/registry/ManagementResourceRegistration.registerReadWriteAttribute:(Lorg/jboss/as/controller/AttributeDefinition;Lorg/jboss/as/controller/OperationStepHandler;Lorg/jboss/as/controller/OperationStepHandler;)V
      24: return

  public void registerReadOnlyAttribute(org.jboss.as.controller.AttributeDefinition, org.jboss.as.controller.OperationStepHandler);
    Code:
       0: aload_0
       1: getfield      #4                  // Field deployments:Lorg/jboss/as/controller/registry/ManagementResourceRegistration;
       4: aload_1
       5: aload_2
       6: invokeinterface #38,  3           // InterfaceMethod org/jboss/as/controller/registry/ManagementResourceRegistration.registerReadOnlyAttribute:(Lorg/jboss/as/controller/AttributeDefinition;Lorg/jboss/as/controller/OperationStepHandler;)V
      11: aload_0
      12: getfield      #5                  // Field subdeployments:Lorg/jboss/as/controller/registry/ManagementResourceRegistration;
      15: aload_1
      16: aload_2
      17: invokeinterface #38,  3           // InterfaceMethod org/jboss/as/controller/registry/ManagementResourceRegistration.registerReadOnlyAttribute:(Lorg/jboss/as/controller/AttributeDefinition;Lorg/jboss/as/controller/OperationStepHandler;)V
      22: return

  public void registerMetric(org.jboss.as.controller.AttributeDefinition, org.jboss.as.controller.OperationStepHandler);
    Code:
       0: aload_0
       1: getfield      #4                  // Field deployments:Lorg/jboss/as/controller/registry/ManagementResourceRegistration;
       4: aload_1
       5: aload_2
       6: invokeinterface #39,  3           // InterfaceMethod org/jboss/as/controller/registry/ManagementResourceRegistration.registerMetric:(Lorg/jboss/as/controller/AttributeDefinition;Lorg/jboss/as/controller/OperationStepHandler;)V
      11: aload_0
      12: getfield      #5                  // Field subdeployments:Lorg/jboss/as/controller/registry/ManagementResourceRegistration;
      15: aload_1
      16: aload_2
      17: invokeinterface #39,  3           // InterfaceMethod org/jboss/as/controller/registry/ManagementResourceRegistration.registerMetric:(Lorg/jboss/as/controller/AttributeDefinition;Lorg/jboss/as/controller/OperationStepHandler;)V
      22: return

  public void unregisterAttribute(java.lang.String);
    Code:
       0: aload_0
       1: getfield      #4                  // Field deployments:Lorg/jboss/as/controller/registry/ManagementResourceRegistration;
       4: aload_1
       5: invokeinterface #40,  2           // InterfaceMethod org/jboss/as/controller/registry/ManagementResourceRegistration.unregisterAttribute:(Ljava/lang/String;)V
      10: aload_0
      11: getfield      #5                  // Field subdeployments:Lorg/jboss/as/controller/registry/ManagementResourceRegistration;
      14: aload_1
      15: invokeinterface #40,  2           // InterfaceMethod org/jboss/as/controller/registry/ManagementResourceRegistration.unregisterAttribute:(Ljava/lang/String;)V
      20: return

  public void registerNotification(org.jboss.as.controller.NotificationDefinition, boolean);
    Code:
       0: aload_0
       1: getfield      #4                  // Field deployments:Lorg/jboss/as/controller/registry/ManagementResourceRegistration;
       4: aload_1
       5: iload_2
       6: invokeinterface #41,  3           // InterfaceMethod org/jboss/as/controller/registry/ManagementResourceRegistration.registerNotification:(Lorg/jboss/as/controller/NotificationDefinition;Z)V
      11: aload_0
      12: getfield      #5                  // Field subdeployments:Lorg/jboss/as/controller/registry/ManagementResourceRegistration;
      15: aload_1
      16: iload_2
      17: invokeinterface #41,  3           // InterfaceMethod org/jboss/as/controller/registry/ManagementResourceRegistration.registerNotification:(Lorg/jboss/as/controller/NotificationDefinition;Z)V
      22: return

  public void registerNotification(org.jboss.as.controller.NotificationDefinition);
    Code:
       0: aload_0
       1: getfield      #4                  // Field deployments:Lorg/jboss/as/controller/registry/ManagementResourceRegistration;
       4: aload_1
       5: invokeinterface #42,  2           // InterfaceMethod org/jboss/as/controller/registry/ManagementResourceRegistration.registerNotification:(Lorg/jboss/as/controller/NotificationDefinition;)V
      10: aload_0
      11: getfield      #5                  // Field subdeployments:Lorg/jboss/as/controller/registry/ManagementResourceRegistration;
      14: aload_1
      15: invokeinterface #42,  2           // InterfaceMethod org/jboss/as/controller/registry/ManagementResourceRegistration.registerNotification:(Lorg/jboss/as/controller/NotificationDefinition;)V
      20: return

  public void unregisterNotification(java.lang.String);
    Code:
       0: aload_0
       1: getfield      #4                  // Field deployments:Lorg/jboss/as/controller/registry/ManagementResourceRegistration;
       4: aload_1
       5: invokeinterface #43,  2           // InterfaceMethod org/jboss/as/controller/registry/ManagementResourceRegistration.unregisterNotification:(Ljava/lang/String;)V
      10: aload_0
      11: getfield      #5                  // Field subdeployments:Lorg/jboss/as/controller/registry/ManagementResourceRegistration;
      14: aload_1
      15: invokeinterface #43,  2           // InterfaceMethod org/jboss/as/controller/registry/ManagementResourceRegistration.unregisterNotification:(Ljava/lang/String;)V
      20: return

  public void registerProxyController(org.jboss.as.controller.PathElement, org.jboss.as.controller.ProxyController);
    Code:
       0: aload_0
       1: getfield      #4                  // Field deployments:Lorg/jboss/as/controller/registry/ManagementResourceRegistration;
       4: aload_1
       5: aload_2
       6: invokeinterface #44,  3           // InterfaceMethod org/jboss/as/controller/registry/ManagementResourceRegistration.registerProxyController:(Lorg/jboss/as/controller/PathElement;Lorg/jboss/as/controller/ProxyController;)V
      11: aload_0
      12: getfield      #5                  // Field subdeployments:Lorg/jboss/as/controller/registry/ManagementResourceRegistration;
      15: aload_1
      16: aload_2
      17: invokeinterface #44,  3           // InterfaceMethod org/jboss/as/controller/registry/ManagementResourceRegistration.registerProxyController:(Lorg/jboss/as/controller/PathElement;Lorg/jboss/as/controller/ProxyController;)V
      22: return

  public void unregisterProxyController(org.jboss.as.controller.PathElement);
    Code:
       0: aload_0
       1: getfield      #4                  // Field deployments:Lorg/jboss/as/controller/registry/ManagementResourceRegistration;
       4: aload_1
       5: invokeinterface #45,  2           // InterfaceMethod org/jboss/as/controller/registry/ManagementResourceRegistration.unregisterProxyController:(Lorg/jboss/as/controller/PathElement;)V
      10: aload_0
      11: getfield      #5                  // Field subdeployments:Lorg/jboss/as/controller/registry/ManagementResourceRegistration;
      14: aload_1
      15: invokeinterface #45,  2           // InterfaceMethod org/jboss/as/controller/registry/ManagementResourceRegistration.unregisterProxyController:(Lorg/jboss/as/controller/PathElement;)V
      20: return

  public void registerAlias(org.jboss.as.controller.PathElement, org.jboss.as.controller.registry.AliasEntry);
    Code:
       0: aload_0
       1: getfield      #4                  // Field deployments:Lorg/jboss/as/controller/registry/ManagementResourceRegistration;
       4: aload_1
       5: aload_2
       6: invokeinterface #46,  3           // InterfaceMethod org/jboss/as/controller/registry/ManagementResourceRegistration.registerAlias:(Lorg/jboss/as/controller/PathElement;Lorg/jboss/as/controller/registry/AliasEntry;)V
      11: aload_0
      12: getfield      #5                  // Field subdeployments:Lorg/jboss/as/controller/registry/ManagementResourceRegistration;
      15: aload_1
      16: aload_2
      17: invokeinterface #46,  3           // InterfaceMethod org/jboss/as/controller/registry/ManagementResourceRegistration.registerAlias:(Lorg/jboss/as/controller/PathElement;Lorg/jboss/as/controller/registry/AliasEntry;)V
      22: return

  public void unregisterAlias(org.jboss.as.controller.PathElement);
    Code:
       0: aload_0
       1: getfield      #4                  // Field deployments:Lorg/jboss/as/controller/registry/ManagementResourceRegistration;
       4: aload_1
       5: invokeinterface #47,  2           // InterfaceMethod org/jboss/as/controller/registry/ManagementResourceRegistration.unregisterAlias:(Lorg/jboss/as/controller/PathElement;)V
      10: aload_0
      11: getfield      #5                  // Field subdeployments:Lorg/jboss/as/controller/registry/ManagementResourceRegistration;
      14: aload_1
      15: invokeinterface #47,  2           // InterfaceMethod org/jboss/as/controller/registry/ManagementResourceRegistration.unregisterAlias:(Lorg/jboss/as/controller/PathElement;)V
      20: return

  public void registerCapability(org.jboss.as.controller.capability.RuntimeCapability);
    Code:
       0: aload_0
       1: getfield      #4                  // Field deployments:Lorg/jboss/as/controller/registry/ManagementResourceRegistration;
       4: aload_1
       5: invokeinterface #48,  2           // InterfaceMethod org/jboss/as/controller/registry/ManagementResourceRegistration.registerCapability:(Lorg/jboss/as/controller/capability/RuntimeCapability;)V
      10: aload_0
      11: getfield      #5                  // Field subdeployments:Lorg/jboss/as/controller/registry/ManagementResourceRegistration;
      14: aload_1
      15: invokeinterface #48,  2           // InterfaceMethod org/jboss/as/controller/registry/ManagementResourceRegistration.registerCapability:(Lorg/jboss/as/controller/capability/RuntimeCapability;)V
      20: return

  public org.jboss.as.controller.registry.AliasEntry getAliasEntry();
    Code:
       0: aload_0
       1: getfield      #4                  // Field deployments:Lorg/jboss/as/controller/registry/ManagementResourceRegistration;
       4: invokeinterface #49,  1           // InterfaceMethod org/jboss/as/controller/registry/ManagementResourceRegistration.getAliasEntry:()Lorg/jboss/as/controller/registry/AliasEntry;
       9: areturn

  public boolean isAlias();
    Code:
       0: aload_0
       1: getfield      #4                  // Field deployments:Lorg/jboss/as/controller/registry/ManagementResourceRegistration;
       4: invokeinterface #50,  1           // InterfaceMethod org/jboss/as/controller/registry/ManagementResourceRegistration.isAlias:()Z
       9: ireturn

  public java.util.Set<org.jboss.as.controller.capability.RuntimeCapability> getCapabilities();
    Code:
       0: aload_0
       1: getfield      #4                  // Field deployments:Lorg/jboss/as/controller/registry/ManagementResourceRegistration;
       4: invokeinterface #51,  1           // InterfaceMethod org/jboss/as/controller/registry/ManagementResourceRegistration.getCapabilities:()Ljava/util/Set;
       9: areturn

  public org.jboss.as.controller.registry.ImmutableManagementResourceRegistration getSubModel(org.jboss.as.controller.PathAddress);
    Code:
       0: aload_0
       1: aload_1
       2: invokevirtual #52                 // Method getSubModel:(Lorg/jboss/as/controller/PathAddress;)Lorg/jboss/as/controller/registry/ManagementResourceRegistration;
       5: areturn

  org.jboss.as.controller.extension.ExtensionRegistry$DeploymentManagementResourceRegistration(org.jboss.as.controller.registry.ManagementResourceRegistration, org.jboss.as.controller.registry.ManagementResourceRegistration, org.jboss.as.controller.extension.ExtensionRegistry$1);
    Code:
       0: aload_0
       1: aload_1
       2: aload_2
       3: invokespecial #1                  // Method "<init>":(Lorg/jboss/as/controller/registry/ManagementResourceRegistration;Lorg/jboss/as/controller/registry/ManagementResourceRegistration;)V
       6: return
}
