Compiled from "ExtensionResource.java"
public class org.jboss.as.controller.extension.ExtensionResource implements org.jboss.as.controller.registry.Resource$ResourceEntry {
  private static final java.util.Set<java.lang.String> CHILD_TYPES;

  private final java.lang.String moduleName;

  private final org.jboss.as.controller.extension.ExtensionRegistry extensionRegistry;

  static final boolean $assertionsDisabled;

  public org.jboss.as.controller.extension.ExtensionResource(java.lang.String, org.jboss.as.controller.extension.ExtensionRegistry);
    Code:
       0: aload_0
       1: invokespecial #2                  // Method java/lang/Object."<init>":()V
       4: getstatic     #3                  // Field $assertionsDisabled:Z
       7: ifne          24
      10: aload_1
      11: ifnonnull     24
      14: new           #4                  // class java/lang/AssertionError
      17: dup
      18: ldc           #5                  // String moduleName is null
      20: invokespecial #6                  // Method java/lang/AssertionError."<init>":(Ljava/lang/Object;)V
      23: athrow
      24: getstatic     #3                  // Field $assertionsDisabled:Z
      27: ifne          44
      30: aload_2
      31: ifnonnull     44
      34: new           #4                  // class java/lang/AssertionError
      37: dup
      38: ldc           #7                  // String extensionRegistry is null
      40: invokespecial #6                  // Method java/lang/AssertionError."<init>":(Ljava/lang/Object;)V
      43: athrow
      44: aload_0
      45: aload_1
      46: putfield      #8                  // Field moduleName:Ljava/lang/String;
      49: aload_0
      50: aload_2
      51: putfield      #9                  // Field extensionRegistry:Lorg/jboss/as/controller/extension/ExtensionRegistry;
      54: return

  public java.lang.String getName();
    Code:
       0: aload_0
       1: getfield      #8                  // Field moduleName:Ljava/lang/String;
       4: areturn

  public org.jboss.as.controller.PathElement getPathElement();
    Code:
       0: ldc           #10                 // String extension
       2: aload_0
       3: getfield      #8                  // Field moduleName:Ljava/lang/String;
       6: invokestatic  #11                 // Method org/jboss/as/controller/PathElement.pathElement:(Ljava/lang/String;Ljava/lang/String;)Lorg/jboss/as/controller/PathElement;
       9: areturn

  public org.jboss.dmr.ModelNode getModel();
    Code:
       0: new           #12                 // class org/jboss/dmr/ModelNode
       3: dup
       4: invokespecial #13                 // Method org/jboss/dmr/ModelNode."<init>":()V
       7: astore_1
       8: aload_1
       9: getstatic     #14                 // Field org/jboss/as/controller/extension/ExtensionResourceDefinition.MODULE:Lorg/jboss/as/controller/SimpleAttributeDefinition;
      12: invokevirtual #15                 // Method org/jboss/as/controller/SimpleAttributeDefinition.getName:()Ljava/lang/String;
      15: invokevirtual #16                 // Method org/jboss/dmr/ModelNode.get:(Ljava/lang/String;)Lorg/jboss/dmr/ModelNode;
      18: aload_0
      19: getfield      #8                  // Field moduleName:Ljava/lang/String;
      22: invokevirtual #17                 // Method org/jboss/dmr/ModelNode.set:(Ljava/lang/String;)Lorg/jboss/dmr/ModelNode;
      25: pop
      26: aload_1
      27: areturn

  public void writeModel(org.jboss.dmr.ModelNode);
    Code:
       0: return

  public boolean isModelDefined();
    Code:
       0: iconst_1
       1: ireturn

  public boolean hasChild(org.jboss.as.controller.PathElement);
    Code:
       0: aload_0
       1: aload_1
       2: invokevirtual #18                 // Method org/jboss/as/controller/PathElement.getKey:()Ljava/lang/String;
       5: invokevirtual #19                 // Method getChildrenNames:(Ljava/lang/String;)Ljava/util/Set;
       8: aload_1
       9: invokevirtual #20                 // Method org/jboss/as/controller/PathElement.getValue:()Ljava/lang/String;
      12: invokeinterface #21,  2           // InterfaceMethod java/util/Set.contains:(Ljava/lang/Object;)Z
      17: ireturn

  public org.jboss.as.controller.registry.Resource getChild(org.jboss.as.controller.PathElement);
    Code:
       0: aconst_null
       1: astore_2
       2: ldc           #22                 // String subsystem
       4: aload_1
       5: invokevirtual #18                 // Method org/jboss/as/controller/PathElement.getKey:()Ljava/lang/String;
       8: invokevirtual #23                 // Method java/lang/String.equals:(Ljava/lang/Object;)Z
      11: ifeq          68
      14: aload_0
      15: getfield      #9                  // Field extensionRegistry:Lorg/jboss/as/controller/extension/ExtensionRegistry;
      18: aload_0
      19: getfield      #8                  // Field moduleName:Ljava/lang/String;
      22: invokevirtual #24                 // Method org/jboss/as/controller/extension/ExtensionRegistry.getAvailableSubsystems:(Ljava/lang/String;)Ljava/util/Map;
      25: astore_3
      26: aload_3
      27: ifnull        46
      30: aload_3
      31: aload_1
      32: invokevirtual #20                 // Method org/jboss/as/controller/PathElement.getValue:()Ljava/lang/String;
      35: invokeinterface #25,  2           // InterfaceMethod java/util/Map.get:(Ljava/lang/Object;)Ljava/lang/Object;
      40: checkcast     #26                 // class org/jboss/as/controller/extension/SubsystemInformation
      43: goto          47
      46: aconst_null
      47: astore        4
      49: aload         4
      51: ifnull        68
      54: new           #27                 // class org/jboss/as/controller/extension/ExtensionResource$SubsystemResource
      57: dup
      58: aload_1
      59: invokevirtual #20                 // Method org/jboss/as/controller/PathElement.getValue:()Ljava/lang/String;
      62: aload         4
      64: invokespecial #28                 // Method org/jboss/as/controller/extension/ExtensionResource$SubsystemResource."<init>":(Ljava/lang/String;Lorg/jboss/as/controller/extension/SubsystemInformation;)V
      67: areturn
      68: aload_2
      69: areturn

  public org.jboss.as.controller.registry.Resource requireChild(org.jboss.as.controller.PathElement);
    Code:
       0: aload_0
       1: aload_1
       2: invokevirtual #29                 // Method getChild:(Lorg/jboss/as/controller/PathElement;)Lorg/jboss/as/controller/registry/Resource;
       5: astore_2
       6: aload_2
       7: ifnonnull     19
      10: new           #30                 // class org/jboss/as/controller/registry/Resource$NoSuchResourceException
      13: dup
      14: aload_1
      15: invokespecial #31                 // Method org/jboss/as/controller/registry/Resource$NoSuchResourceException."<init>":(Lorg/jboss/as/controller/PathElement;)V
      18: athrow
      19: aload_2
      20: areturn

  public boolean hasChildren(java.lang.String);
    Code:
       0: aload_0
       1: aload_1
       2: invokevirtual #32                 // Method getChildren:(Ljava/lang/String;)Ljava/util/Set;
       5: invokeinterface #33,  1           // InterfaceMethod java/util/Set.size:()I
      10: ifle          17
      13: iconst_1
      14: goto          18
      17: iconst_0
      18: ireturn

  public org.jboss.as.controller.registry.Resource navigate(org.jboss.as.controller.PathAddress);
    Code:
       0: aload_1
       1: invokevirtual #34                 // Method org/jboss/as/controller/PathAddress.size:()I
       4: istore_2
       5: iload_2
       6: ifne          11
       9: aload_0
      10: areturn
      11: aload_1
      12: iconst_0
      13: invokevirtual #35                 // Method org/jboss/as/controller/PathAddress.getElement:(I)Lorg/jboss/as/controller/PathElement;
      16: astore_3
      17: aload_0
      18: aload_3
      19: invokevirtual #29                 // Method getChild:(Lorg/jboss/as/controller/PathElement;)Lorg/jboss/as/controller/registry/Resource;
      22: astore        4
      24: aload         4
      26: ifnull        52
      29: iload_2
      30: iconst_1
      31: if_icmpne     39
      34: aload         4
      36: goto          51
      39: aload         4
      41: aload_1
      42: iconst_1
      43: invokevirtual #36                 // Method org/jboss/as/controller/PathAddress.subAddress:(I)Lorg/jboss/as/controller/PathAddress;
      46: invokeinterface #37,  2           // InterfaceMethod org/jboss/as/controller/registry/Resource.navigate:(Lorg/jboss/as/controller/PathAddress;)Lorg/jboss/as/controller/registry/Resource;
      51: areturn
      52: new           #30                 // class org/jboss/as/controller/registry/Resource$NoSuchResourceException
      55: dup
      56: aload_3
      57: invokespecial #31                 // Method org/jboss/as/controller/registry/Resource$NoSuchResourceException."<init>":(Lorg/jboss/as/controller/PathElement;)V
      60: athrow

  public java.util.Set<java.lang.String> getChildTypes();
    Code:
       0: getstatic     #38                 // Field CHILD_TYPES:Ljava/util/Set;
       3: areturn

  public java.util.Set<java.lang.String> getChildrenNames(java.lang.String);
    Code:
       0: aconst_null
       1: astore_2
       2: ldc           #22                 // String subsystem
       4: aload_1
       5: invokevirtual #23                 // Method java/lang/String.equals:(Ljava/lang/Object;)Z
       8: ifeq          45
      11: aload_0
      12: getfield      #9                  // Field extensionRegistry:Lorg/jboss/as/controller/extension/ExtensionRegistry;
      15: aload_0
      16: getfield      #8                  // Field moduleName:Ljava/lang/String;
      19: invokevirtual #24                 // Method org/jboss/as/controller/extension/ExtensionRegistry.getAvailableSubsystems:(Ljava/lang/String;)Ljava/util/Map;
      22: astore_3
      23: aload_3
      24: ifnull        43
      27: new           #39                 // class java/util/HashSet
      30: dup
      31: aload_3
      32: invokeinterface #40,  1           // InterfaceMethod java/util/Map.keySet:()Ljava/util/Set;
      37: invokespecial #41                 // Method java/util/HashSet."<init>":(Ljava/util/Collection;)V
      40: goto          44
      43: aconst_null
      44: astore_2
      45: aload_2
      46: ifnull        53
      49: aload_2
      50: goto          56
      53: invokestatic  #42                 // Method java/util/Collections.emptySet:()Ljava/util/Set;
      56: areturn

  public java.util.Set<org.jboss.as.controller.registry.Resource$ResourceEntry> getChildren(java.lang.String);
    Code:
       0: aconst_null
       1: astore_2
       2: ldc           #22                 // String subsystem
       4: aload_1
       5: invokevirtual #23                 // Method java/lang/String.equals:(Ljava/lang/Object;)Z
       8: ifeq          107
      11: new           #39                 // class java/util/HashSet
      14: dup
      15: invokespecial #43                 // Method java/util/HashSet."<init>":()V
      18: astore_2
      19: aload_0
      20: getfield      #9                  // Field extensionRegistry:Lorg/jboss/as/controller/extension/ExtensionRegistry;
      23: aload_0
      24: getfield      #8                  // Field moduleName:Ljava/lang/String;
      27: invokevirtual #24                 // Method org/jboss/as/controller/extension/ExtensionRegistry.getAvailableSubsystems:(Ljava/lang/String;)Ljava/util/Map;
      30: astore_3
      31: aload_3
      32: ifnull        107
      35: aload_3
      36: invokeinterface #44,  1           // InterfaceMethod java/util/Map.entrySet:()Ljava/util/Set;
      41: invokeinterface #45,  1           // InterfaceMethod java/util/Set.iterator:()Ljava/util/Iterator;
      46: astore        4
      48: aload         4
      50: invokeinterface #46,  1           // InterfaceMethod java/util/Iterator.hasNext:()Z
      55: ifeq          107
      58: aload         4
      60: invokeinterface #47,  1           // InterfaceMethod java/util/Iterator.next:()Ljava/lang/Object;
      65: checkcast     #48                 // class java/util/Map$Entry
      68: astore        5
      70: aload_2
      71: new           #27                 // class org/jboss/as/controller/extension/ExtensionResource$SubsystemResource
      74: dup
      75: aload         5
      77: invokeinterface #49,  1           // InterfaceMethod java/util/Map$Entry.getKey:()Ljava/lang/Object;
      82: checkcast     #50                 // class java/lang/String
      85: aload         5
      87: invokeinterface #51,  1           // InterfaceMethod java/util/Map$Entry.getValue:()Ljava/lang/Object;
      92: checkcast     #26                 // class org/jboss/as/controller/extension/SubsystemInformation
      95: invokespecial #28                 // Method org/jboss/as/controller/extension/ExtensionResource$SubsystemResource."<init>":(Ljava/lang/String;Lorg/jboss/as/controller/extension/SubsystemInformation;)V
      98: invokeinterface #52,  2           // InterfaceMethod java/util/Set.add:(Ljava/lang/Object;)Z
     103: pop
     104: goto          48
     107: aload_2
     108: areturn

  public void registerChild(org.jboss.as.controller.PathElement, org.jboss.as.controller.registry.Resource);
    Code:
       0: new           #53                 // class java/lang/UnsupportedOperationException
       3: dup
       4: invokespecial #54                 // Method java/lang/UnsupportedOperationException."<init>":()V
       7: athrow

  public void registerChild(org.jboss.as.controller.PathElement, int, org.jboss.as.controller.registry.Resource);
    Code:
       0: new           #53                 // class java/lang/UnsupportedOperationException
       3: dup
       4: invokespecial #54                 // Method java/lang/UnsupportedOperationException."<init>":()V
       7: athrow

  public org.jboss.as.controller.registry.Resource removeChild(org.jboss.as.controller.PathElement);
    Code:
       0: new           #53                 // class java/lang/UnsupportedOperationException
       3: dup
       4: invokespecial #54                 // Method java/lang/UnsupportedOperationException."<init>":()V
       7: athrow

  public boolean isRuntime();
    Code:
       0: iconst_0
       1: ireturn

  public boolean isProxy();
    Code:
       0: iconst_0
       1: ireturn

  public org.jboss.as.controller.extension.ExtensionResource clone();
    Code:
       0: new           #55                 // class org/jboss/as/controller/extension/ExtensionResource
       3: dup
       4: aload_0
       5: getfield      #8                  // Field moduleName:Ljava/lang/String;
       8: aload_0
       9: getfield      #9                  // Field extensionRegistry:Lorg/jboss/as/controller/extension/ExtensionRegistry;
      12: invokespecial #56                 // Method "<init>":(Ljava/lang/String;Lorg/jboss/as/controller/extension/ExtensionRegistry;)V
      15: areturn

  public java.util.Set<java.lang.String> getOrderedChildTypes();
    Code:
       0: invokestatic  #42                 // Method java/util/Collections.emptySet:()Ljava/util/Set;
       3: areturn

  public java.lang.Object clone() throws java.lang.CloneNotSupportedException;
    Code:
       0: aload_0
       1: invokevirtual #57                 // Method clone:()Lorg/jboss/as/controller/extension/ExtensionResource;
       4: areturn

  public org.jboss.as.controller.registry.Resource clone();
    Code:
       0: aload_0
       1: invokevirtual #57                 // Method clone:()Lorg/jboss/as/controller/extension/ExtensionResource;
       4: areturn

  static {};
    Code:
       0: ldc           #55                 // class org/jboss/as/controller/extension/ExtensionResource
       2: invokevirtual #58                 // Method java/lang/Class.desiredAssertionStatus:()Z
       5: ifne          12
       8: iconst_1
       9: goto          13
      12: iconst_0
      13: putstatic     #3                  // Field $assertionsDisabled:Z
      16: new           #39                 // class java/util/HashSet
      19: dup
      20: iconst_1
      21: anewarray     #50                 // class java/lang/String
      24: dup
      25: iconst_0
      26: ldc           #22                 // String subsystem
      28: aastore
      29: invokestatic  #59                 // Method java/util/Arrays.asList:([Ljava/lang/Object;)Ljava/util/List;
      32: invokespecial #41                 // Method java/util/HashSet."<init>":(Ljava/util/Collection;)V
      35: invokestatic  #60                 // Method java/util/Collections.unmodifiableSet:(Ljava/util/Set;)Ljava/util/Set;
      38: putstatic     #38                 // Field CHILD_TYPES:Ljava/util/Set;
      41: return
}
