Compiled from "TimestampAction.java"
public class ch.qos.logback.core.joran.action.TimestampAction extends ch.qos.logback.core.joran.action.Action {
  static java.lang.String DATE_PATTERN_ATTRIBUTE;

  static java.lang.String TIME_REFERENCE_ATTRIBUTE;

  static java.lang.String CONTEXT_BIRTH;

  boolean inError;

  public ch.qos.logback.core.joran.action.TimestampAction();
    Code:
       0: aload_0
       1: invokespecial #1                  // Method ch/qos/logback/core/joran/action/Action."<init>":()V
       4: aload_0
       5: iconst_0
       6: putfield      #2                  // Field inError:Z
       9: return

  public void begin(ch.qos.logback.core.joran.spi.InterpretationContext, java.lang.String, org.xml.sax.Attributes) throws ch.qos.logback.core.joran.spi.ActionException;
    Code:
       0: aload_3
       1: ldc           #3                  // String key
       3: invokeinterface #4,  2            // InterfaceMethod org/xml/sax/Attributes.getValue:(Ljava/lang/String;)Ljava/lang/String;
       8: astore        4
      10: aload         4
      12: invokestatic  #5                  // Method ch/qos/logback/core/util/OptionHelper.isEmpty:(Ljava/lang/String;)Z
      15: ifeq          29
      18: aload_0
      19: ldc           #6                  // String Attribute named [key] cannot be empty
      21: invokevirtual #7                  // Method addError:(Ljava/lang/String;)V
      24: aload_0
      25: iconst_1
      26: putfield      #2                  // Field inError:Z
      29: aload_3
      30: getstatic     #8                  // Field DATE_PATTERN_ATTRIBUTE:Ljava/lang/String;
      33: invokeinterface #4,  2            // InterfaceMethod org/xml/sax/Attributes.getValue:(Ljava/lang/String;)Ljava/lang/String;
      38: astore        5
      40: aload         5
      42: invokestatic  #5                  // Method ch/qos/logback/core/util/OptionHelper.isEmpty:(Ljava/lang/String;)Z
      45: ifeq          83
      48: aload_0
      49: new           #9                  // class java/lang/StringBuilder
      52: dup
      53: invokespecial #10                 // Method java/lang/StringBuilder."<init>":()V
      56: ldc           #11                 // String Attribute named [
      58: invokevirtual #12                 // Method java/lang/StringBuilder.append:(Ljava/lang/String;)Ljava/lang/StringBuilder;
      61: getstatic     #8                  // Field DATE_PATTERN_ATTRIBUTE:Ljava/lang/String;
      64: invokevirtual #12                 // Method java/lang/StringBuilder.append:(Ljava/lang/String;)Ljava/lang/StringBuilder;
      67: ldc           #13                 // String ] cannot be empty
      69: invokevirtual #12                 // Method java/lang/StringBuilder.append:(Ljava/lang/String;)Ljava/lang/StringBuilder;
      72: invokevirtual #14                 // Method java/lang/StringBuilder.toString:()Ljava/lang/String;
      75: invokevirtual #7                  // Method addError:(Ljava/lang/String;)V
      78: aload_0
      79: iconst_1
      80: putfield      #2                  // Field inError:Z
      83: aload_3
      84: getstatic     #15                 // Field TIME_REFERENCE_ATTRIBUTE:Ljava/lang/String;
      87: invokeinterface #4,  2            // InterfaceMethod org/xml/sax/Attributes.getValue:(Ljava/lang/String;)Ljava/lang/String;
      92: astore        6
      94: getstatic     #16                 // Field CONTEXT_BIRTH:Ljava/lang/String;
      97: aload         6
      99: invokevirtual #17                 // Method java/lang/String.equalsIgnoreCase:(Ljava/lang/String;)Z
     102: ifeq          125
     105: aload_0
     106: ldc           #18                 // String Using context birth as time reference.
     108: invokevirtual #19                 // Method addInfo:(Ljava/lang/String;)V
     111: aload_0
     112: getfield      #20                 // Field context:Lch/qos/logback/core/Context;
     115: invokeinterface #21,  1           // InterfaceMethod ch/qos/logback/core/Context.getBirthTime:()J
     120: lstore        7
     122: goto          136
     125: invokestatic  #22                 // Method java/lang/System.currentTimeMillis:()J
     128: lstore        7
     130: aload_0
     131: ldc           #23                 // String Using current interpretation time, i.e. now, as time reference.
     133: invokevirtual #19                 // Method addInfo:(Ljava/lang/String;)V
     136: aload_0
     137: getfield      #2                  // Field inError:Z
     140: ifeq          144
     143: return
     144: aload_3
     145: ldc           #24                 // String scope
     147: invokeinterface #4,  2            // InterfaceMethod org/xml/sax/Attributes.getValue:(Ljava/lang/String;)Ljava/lang/String;
     152: astore        9
     154: aload         9
     156: invokestatic  #25                 // Method ch/qos/logback/core/joran/action/ActionUtil.stringToScope:(Ljava/lang/String;)Lch/qos/logback/core/joran/action/ActionUtil$Scope;
     159: astore        10
     161: new           #26                 // class ch/qos/logback/core/util/CachingDateFormatter
     164: dup
     165: aload         5
     167: invokespecial #27                 // Method ch/qos/logback/core/util/CachingDateFormatter."<init>":(Ljava/lang/String;)V
     170: astore        11
     172: aload         11
     174: lload         7
     176: invokevirtual #28                 // Method ch/qos/logback/core/util/CachingDateFormatter.format:(J)Ljava/lang/String;
     179: astore        12
     181: aload_0
     182: new           #9                  // class java/lang/StringBuilder
     185: dup
     186: invokespecial #10                 // Method java/lang/StringBuilder."<init>":()V
     189: ldc           #29                 // String Adding property to the context with key=\"
     191: invokevirtual #12                 // Method java/lang/StringBuilder.append:(Ljava/lang/String;)Ljava/lang/StringBuilder;
     194: aload         4
     196: invokevirtual #12                 // Method java/lang/StringBuilder.append:(Ljava/lang/String;)Ljava/lang/StringBuilder;
     199: ldc           #30                 // String \" and value=\"
     201: invokevirtual #12                 // Method java/lang/StringBuilder.append:(Ljava/lang/String;)Ljava/lang/StringBuilder;
     204: aload         12
     206: invokevirtual #12                 // Method java/lang/StringBuilder.append:(Ljava/lang/String;)Ljava/lang/StringBuilder;
     209: ldc           #31                 // String \" to the
     211: invokevirtual #12                 // Method java/lang/StringBuilder.append:(Ljava/lang/String;)Ljava/lang/StringBuilder;
     214: aload         10
     216: invokevirtual #32                 // Method java/lang/StringBuilder.append:(Ljava/lang/Object;)Ljava/lang/StringBuilder;
     219: ldc           #33                 // String  scope
     221: invokevirtual #12                 // Method java/lang/StringBuilder.append:(Ljava/lang/String;)Ljava/lang/StringBuilder;
     224: invokevirtual #14                 // Method java/lang/StringBuilder.toString:()Ljava/lang/String;
     227: invokevirtual #19                 // Method addInfo:(Ljava/lang/String;)V
     230: aload_1
     231: aload         4
     233: aload         12
     235: aload         10
     237: invokestatic  #34                 // Method ch/qos/logback/core/joran/action/ActionUtil.setProperty:(Lch/qos/logback/core/joran/spi/InterpretationContext;Ljava/lang/String;Ljava/lang/String;Lch/qos/logback/core/joran/action/ActionUtil$Scope;)V
     240: return

  public void end(ch.qos.logback.core.joran.spi.InterpretationContext, java.lang.String) throws ch.qos.logback.core.joran.spi.ActionException;
    Code:
       0: return

  static {};
    Code:
       0: ldc           #35                 // String datePattern
       2: putstatic     #8                  // Field DATE_PATTERN_ATTRIBUTE:Ljava/lang/String;
       5: ldc           #36                 // String timeReference
       7: putstatic     #15                 // Field TIME_REFERENCE_ATTRIBUTE:Ljava/lang/String;
      10: ldc           #37                 // String contextBirth
      12: putstatic     #16                 // Field CONTEXT_BIRTH:Ljava/lang/String;
      15: return
}
