Compiled from "PooledPBEStringEncryptor.java"
public final class org.jasypt.encryption.pbe.PooledPBEStringEncryptor implements org.jasypt.encryption.pbe.PBEStringCleanablePasswordEncryptor {
  private final org.jasypt.encryption.pbe.StandardPBEStringEncryptor firstEncryptor;

  private org.jasypt.encryption.pbe.config.PBEConfig config;

  private int poolSize;

  private boolean poolSizeSet;

  private org.jasypt.encryption.pbe.StandardPBEStringEncryptor[] pool;

  private int roundRobin;

  private boolean initialized;

  public org.jasypt.encryption.pbe.PooledPBEStringEncryptor();
    Code:
       0: aload_0
       1: invokespecial #1                  // Method java/lang/Object."<init>":()V
       4: aload_0
       5: aconst_null
       6: putfield      #2                  // Field config:Lorg/jasypt/encryption/pbe/config/PBEConfig;
       9: aload_0
      10: iconst_0
      11: putfield      #3                  // Field poolSize:I
      14: aload_0
      15: iconst_0
      16: putfield      #4                  // Field poolSizeSet:Z
      19: aload_0
      20: iconst_0
      21: putfield      #5                  // Field roundRobin:I
      24: aload_0
      25: iconst_0
      26: putfield      #6                  // Field initialized:Z
      29: aload_0
      30: new           #7                  // class org/jasypt/encryption/pbe/StandardPBEStringEncryptor
      33: dup
      34: invokespecial #8                  // Method org/jasypt/encryption/pbe/StandardPBEStringEncryptor."<init>":()V
      37: putfield      #9                  // Field firstEncryptor:Lorg/jasypt/encryption/pbe/StandardPBEStringEncryptor;
      40: return

  public synchronized void setConfig(org.jasypt.encryption.pbe.config.PBEConfig);
    Code:
       0: aload_0
       1: getfield      #9                  // Field firstEncryptor:Lorg/jasypt/encryption/pbe/StandardPBEStringEncryptor;
       4: aload_1
       5: invokevirtual #10                 // Method org/jasypt/encryption/pbe/StandardPBEStringEncryptor.setConfig:(Lorg/jasypt/encryption/pbe/config/PBEConfig;)V
       8: aload_0
       9: aload_1
      10: putfield      #2                  // Field config:Lorg/jasypt/encryption/pbe/config/PBEConfig;
      13: return

  public void setAlgorithm(java.lang.String);
    Code:
       0: aload_0
       1: getfield      #9                  // Field firstEncryptor:Lorg/jasypt/encryption/pbe/StandardPBEStringEncryptor;
       4: aload_1
       5: invokevirtual #11                 // Method org/jasypt/encryption/pbe/StandardPBEStringEncryptor.setAlgorithm:(Ljava/lang/String;)V
       8: return

  public void setPassword(java.lang.String);
    Code:
       0: aload_0
       1: getfield      #9                  // Field firstEncryptor:Lorg/jasypt/encryption/pbe/StandardPBEStringEncryptor;
       4: aload_1
       5: invokevirtual #12                 // Method org/jasypt/encryption/pbe/StandardPBEStringEncryptor.setPassword:(Ljava/lang/String;)V
       8: return

  public synchronized void setPasswordCharArray(char[]);
    Code:
       0: aload_0
       1: getfield      #9                  // Field firstEncryptor:Lorg/jasypt/encryption/pbe/StandardPBEStringEncryptor;
       4: aload_1
       5: invokevirtual #13                 // Method org/jasypt/encryption/pbe/StandardPBEStringEncryptor.setPasswordCharArray:([C)V
       8: return

  public void setKeyObtentionIterations(int);
    Code:
       0: aload_0
       1: getfield      #9                  // Field firstEncryptor:Lorg/jasypt/encryption/pbe/StandardPBEStringEncryptor;
       4: iload_1
       5: invokevirtual #14                 // Method org/jasypt/encryption/pbe/StandardPBEStringEncryptor.setKeyObtentionIterations:(I)V
       8: return

  public void setSaltGenerator(org.jasypt.salt.SaltGenerator);
    Code:
       0: aload_0
       1: getfield      #9                  // Field firstEncryptor:Lorg/jasypt/encryption/pbe/StandardPBEStringEncryptor;
       4: aload_1
       5: invokevirtual #15                 // Method org/jasypt/encryption/pbe/StandardPBEStringEncryptor.setSaltGenerator:(Lorg/jasypt/salt/SaltGenerator;)V
       8: return

  public void setProviderName(java.lang.String);
    Code:
       0: aload_0
       1: getfield      #9                  // Field firstEncryptor:Lorg/jasypt/encryption/pbe/StandardPBEStringEncryptor;
       4: aload_1
       5: invokevirtual #16                 // Method org/jasypt/encryption/pbe/StandardPBEStringEncryptor.setProviderName:(Ljava/lang/String;)V
       8: return

  public void setProvider(java.security.Provider);
    Code:
       0: aload_0
       1: getfield      #9                  // Field firstEncryptor:Lorg/jasypt/encryption/pbe/StandardPBEStringEncryptor;
       4: aload_1
       5: invokevirtual #17                 // Method org/jasypt/encryption/pbe/StandardPBEStringEncryptor.setProvider:(Ljava/security/Provider;)V
       8: return

  public synchronized void setStringOutputType(java.lang.String);
    Code:
       0: aload_0
       1: getfield      #9                  // Field firstEncryptor:Lorg/jasypt/encryption/pbe/StandardPBEStringEncryptor;
       4: aload_1
       5: invokevirtual #18                 // Method org/jasypt/encryption/pbe/StandardPBEStringEncryptor.setStringOutputType:(Ljava/lang/String;)V
       8: return

  public synchronized void setPoolSize(int);
    Code:
       0: iload_1
       1: ifle          8
       4: iconst_1
       5: goto          9
       8: iconst_0
       9: ldc           #19                 // String Pool size be > 0
      11: invokestatic  #20                 // Method org/jasypt/commons/CommonUtils.validateIsTrue:(ZLjava/lang/String;)V
      14: aload_0
      15: invokevirtual #21                 // Method isInitialized:()Z
      18: ifeq          29
      21: new           #22                 // class org/jasypt/exceptions/AlreadyInitializedException
      24: dup
      25: invokespecial #23                 // Method org/jasypt/exceptions/AlreadyInitializedException."<init>":()V
      28: athrow
      29: aload_0
      30: iload_1
      31: putfield      #3                  // Field poolSize:I
      34: aload_0
      35: iconst_1
      36: putfield      #4                  // Field poolSizeSet:Z
      39: return

  public boolean isInitialized();
    Code:
       0: aload_0
       1: getfield      #6                  // Field initialized:Z
       4: ireturn

  public synchronized void initialize();
    Code:
       0: aload_0
       1: getfield      #6                  // Field initialized:Z
       4: ifne          87
       7: aload_0
       8: getfield      #2                  // Field config:Lorg/jasypt/encryption/pbe/config/PBEConfig;
      11: ifnull        50
      14: aload_0
      15: getfield      #2                  // Field config:Lorg/jasypt/encryption/pbe/config/PBEConfig;
      18: invokeinterface #24,  1           // InterfaceMethod org/jasypt/encryption/pbe/config/PBEConfig.getPoolSize:()Ljava/lang/Integer;
      23: astore_1
      24: aload_0
      25: aload_0
      26: getfield      #4                  // Field poolSizeSet:Z
      29: ifne          36
      32: aload_1
      33: ifnonnull     43
      36: aload_0
      37: getfield      #3                  // Field poolSize:I
      40: goto          47
      43: aload_1
      44: invokevirtual #25                 // Method java/lang/Integer.intValue:()I
      47: putfield      #3                  // Field poolSize:I
      50: aload_0
      51: getfield      #3                  // Field poolSize:I
      54: ifgt          67
      57: new           #26                 // class java/lang/IllegalArgumentException
      60: dup
      61: ldc           #27                 // String Pool size must be set and > 0
      63: invokespecial #28                 // Method java/lang/IllegalArgumentException."<init>":(Ljava/lang/String;)V
      66: athrow
      67: aload_0
      68: aload_0
      69: getfield      #9                  // Field firstEncryptor:Lorg/jasypt/encryption/pbe/StandardPBEStringEncryptor;
      72: aload_0
      73: getfield      #3                  // Field poolSize:I
      76: invokevirtual #29                 // Method org/jasypt/encryption/pbe/StandardPBEStringEncryptor.cloneAndInitializeEncryptor:(I)[Lorg/jasypt/encryption/pbe/StandardPBEStringEncryptor;
      79: putfield      #30                 // Field pool:[Lorg/jasypt/encryption/pbe/StandardPBEStringEncryptor;
      82: aload_0
      83: iconst_1
      84: putfield      #6                  // Field initialized:Z
      87: return

  public java.lang.String encrypt(java.lang.String);
    Code:
       0: aload_0
       1: invokevirtual #21                 // Method isInitialized:()Z
       4: ifne          11
       7: aload_0
       8: invokevirtual #31                 // Method initialize:()V
      11: aload_0
      12: dup
      13: astore_3
      14: monitorenter
      15: aload_0
      16: getfield      #5                  // Field roundRobin:I
      19: istore_2
      20: aload_0
      21: aload_0
      22: getfield      #5                  // Field roundRobin:I
      25: iconst_1
      26: iadd
      27: aload_0
      28: getfield      #3                  // Field poolSize:I
      31: irem
      32: putfield      #5                  // Field roundRobin:I
      35: aload_3
      36: monitorexit
      37: goto          47
      40: astore        4
      42: aload_3
      43: monitorexit
      44: aload         4
      46: athrow
      47: aload_0
      48: getfield      #30                 // Field pool:[Lorg/jasypt/encryption/pbe/StandardPBEStringEncryptor;
      51: iload_2
      52: aaload
      53: aload_1
      54: invokevirtual #32                 // Method org/jasypt/encryption/pbe/StandardPBEStringEncryptor.encrypt:(Ljava/lang/String;)Ljava/lang/String;
      57: areturn
    Exception table:
       from    to  target type
          15    37    40   any
          40    44    40   any

  public java.lang.String decrypt(java.lang.String);
    Code:
       0: aload_0
       1: invokevirtual #21                 // Method isInitialized:()Z
       4: ifne          11
       7: aload_0
       8: invokevirtual #31                 // Method initialize:()V
      11: aload_0
      12: dup
      13: astore_3
      14: monitorenter
      15: aload_0
      16: getfield      #5                  // Field roundRobin:I
      19: istore_2
      20: aload_0
      21: aload_0
      22: getfield      #5                  // Field roundRobin:I
      25: iconst_1
      26: iadd
      27: aload_0
      28: getfield      #3                  // Field poolSize:I
      31: irem
      32: putfield      #5                  // Field roundRobin:I
      35: aload_3
      36: monitorexit
      37: goto          47
      40: astore        4
      42: aload_3
      43: monitorexit
      44: aload         4
      46: athrow
      47: aload_0
      48: getfield      #30                 // Field pool:[Lorg/jasypt/encryption/pbe/StandardPBEStringEncryptor;
      51: iload_2
      52: aaload
      53: aload_1
      54: invokevirtual #33                 // Method org/jasypt/encryption/pbe/StandardPBEStringEncryptor.decrypt:(Ljava/lang/String;)Ljava/lang/String;
      57: areturn
    Exception table:
       from    to  target type
          15    37    40   any
          40    44    40   any
}
