Compiled from "TestHiveFileSystemWasb.java"
public class io.trino.plugin.hive.TestHiveFileSystemWasb extends io.trino.plugin.hive.AbstractTestHiveFileSystem {
  private java.lang.String container;

  private java.lang.String account;

  private java.lang.String accessKey;

  private java.lang.String testDirectory;

  public io.trino.plugin.hive.TestHiveFileSystemWasb();
    Code:
       0: aload_0
       1: invokespecial #1                  // Method io/trino/plugin/hive/AbstractTestHiveFileSystem."<init>":()V
       4: return

  public void setup(java.lang.String, int, java.lang.String, java.lang.String, java.lang.String, java.lang.String, java.lang.String);
    Code:
       0: aload_1
       1: invokestatic  #7                  // Method org/testng/util/Strings.isNullOrEmpty:(Ljava/lang/String;)Z
       4: ifne          11
       7: iconst_1
       8: goto          12
      11: iconst_0
      12: ldc           #13                 // String expected non empty host
      14: invokestatic  #15                 // Method com/google/common/base/Preconditions.checkArgument:(ZLjava/lang/Object;)V
      17: aload_3
      18: invokestatic  #7                  // Method org/testng/util/Strings.isNullOrEmpty:(Ljava/lang/String;)Z
      21: ifne          28
      24: iconst_1
      25: goto          29
      28: iconst_0
      29: ldc           #21                 // String expected non empty databaseName
      31: invokestatic  #15                 // Method com/google/common/base/Preconditions.checkArgument:(ZLjava/lang/Object;)V
      34: aload         4
      36: invokestatic  #7                  // Method org/testng/util/Strings.isNullOrEmpty:(Ljava/lang/String;)Z
      39: ifne          46
      42: iconst_1
      43: goto          47
      46: iconst_0
      47: ldc           #23                 // String expected non empty container
      49: invokestatic  #15                 // Method com/google/common/base/Preconditions.checkArgument:(ZLjava/lang/Object;)V
      52: aload         5
      54: invokestatic  #7                  // Method org/testng/util/Strings.isNullOrEmpty:(Ljava/lang/String;)Z
      57: ifne          64
      60: iconst_1
      61: goto          65
      64: iconst_0
      65: ldc           #25                 // String expected non empty account
      67: invokestatic  #15                 // Method com/google/common/base/Preconditions.checkArgument:(ZLjava/lang/Object;)V
      70: aload         6
      72: invokestatic  #7                  // Method org/testng/util/Strings.isNullOrEmpty:(Ljava/lang/String;)Z
      75: ifne          82
      78: iconst_1
      79: goto          83
      82: iconst_0
      83: ldc           #27                 // String expected non empty accessKey
      85: invokestatic  #15                 // Method com/google/common/base/Preconditions.checkArgument:(ZLjava/lang/Object;)V
      88: aload         7
      90: invokestatic  #7                  // Method org/testng/util/Strings.isNullOrEmpty:(Ljava/lang/String;)Z
      93: ifne          100
      96: iconst_1
      97: goto          101
     100: iconst_0
     101: ldc           #29                 // String expected non empty testDirectory
     103: invokestatic  #15                 // Method com/google/common/base/Preconditions.checkArgument:(ZLjava/lang/Object;)V
     106: aload_0
     107: aload         4
     109: putfield      #31                 // Field container:Ljava/lang/String;
     112: aload_0
     113: aload         5
     115: putfield      #37                 // Field account:Ljava/lang/String;
     118: aload_0
     119: aload         6
     121: putfield      #40                 // Field accessKey:Ljava/lang/String;
     124: aload_0
     125: aload         7
     127: putfield      #43                 // Field testDirectory:Ljava/lang/String;
     130: aload_0
     131: aload_1
     132: iload_2
     133: aload_3
     134: iconst_0
     135: aload_0
     136: invokevirtual #46                 // Method createHdfsConfiguration:()Lio/trino/hdfs/HdfsConfiguration;
     139: invokespecial #50                 // Method io/trino/plugin/hive/AbstractTestHiveFileSystem.setup:(Ljava/lang/String;ILjava/lang/String;ZLio/trino/hdfs/HdfsConfiguration;)V
     142: return

  private io.trino.hdfs.HdfsConfiguration createHdfsConfiguration();
    Code:
       0: new           #54                 // class io/trino/hdfs/azure/TrinoAzureConfigurationInitializer
       3: dup
       4: new           #56                 // class io/trino/hdfs/azure/HiveAzureConfig
       7: dup
       8: invokespecial #58                 // Method io/trino/hdfs/azure/HiveAzureConfig."<init>":()V
      11: aload_0
      12: getfield      #40                 // Field accessKey:Ljava/lang/String;
      15: invokevirtual #59                 // Method io/trino/hdfs/azure/HiveAzureConfig.setWasbAccessKey:(Ljava/lang/String;)Lio/trino/hdfs/azure/HiveAzureConfig;
      18: aload_0
      19: getfield      #37                 // Field account:Ljava/lang/String;
      22: invokevirtual #63                 // Method io/trino/hdfs/azure/HiveAzureConfig.setWasbStorageAccount:(Ljava/lang/String;)Lio/trino/hdfs/azure/HiveAzureConfig;
      25: invokespecial #66                 // Method io/trino/hdfs/azure/TrinoAzureConfigurationInitializer."<init>":(Lio/trino/hdfs/azure/HiveAzureConfig;)V
      28: astore_1
      29: new           #69                 // class io/trino/hdfs/DynamicHdfsConfiguration
      32: dup
      33: new           #71                 // class io/trino/hdfs/HdfsConfigurationInitializer
      36: dup
      37: new           #73                 // class io/trino/hdfs/HdfsConfig
      40: dup
      41: invokespecial #75                 // Method io/trino/hdfs/HdfsConfig."<init>":()V
      44: aload_1
      45: invokestatic  #76                 // Method com/google/common/collect/ImmutableSet.of:(Ljava/lang/Object;)Lcom/google/common/collect/ImmutableSet;
      48: invokespecial #82                 // Method io/trino/hdfs/HdfsConfigurationInitializer."<init>":(Lio/trino/hdfs/HdfsConfig;Ljava/util/Set;)V
      51: invokestatic  #85                 // Method com/google/common/collect/ImmutableSet.of:()Lcom/google/common/collect/ImmutableSet;
      54: invokespecial #88                 // Method io/trino/hdfs/DynamicHdfsConfiguration."<init>":(Lio/trino/hdfs/HdfsConfigurationInitializer;Ljava/util/Set;)V
      57: areturn

  protected org.apache.hadoop.fs.Path getBasePath();
    Code:
       0: new           #91                 // class org/apache/hadoop/fs/Path
       3: dup
       4: ldc           #93                 // String wasb://%s@%s.blob.core.windows.net/%s/
       6: iconst_3
       7: anewarray     #95                 // class java/lang/Object
      10: dup
      11: iconst_0
      12: aload_0
      13: getfield      #31                 // Field container:Ljava/lang/String;
      16: aastore
      17: dup
      18: iconst_1
      19: aload_0
      20: getfield      #37                 // Field account:Ljava/lang/String;
      23: aastore
      24: dup
      25: iconst_2
      26: aload_0
      27: getfield      #43                 // Field testDirectory:Ljava/lang/String;
      30: aastore
      31: invokestatic  #97                 // Method java/lang/String.format:(Ljava/lang/String;[Ljava/lang/Object;)Ljava/lang/String;
      34: invokespecial #103                // Method org/apache/hadoop/fs/Path."<init>":(Ljava/lang/String;)V
      37: areturn
}
