Compiled from "ResourceHandler.java"
public class io.undertow.server.handlers.resource.ResourceHandler implements io.undertow.server.HttpHandler {
  private static final java.util.Set<io.undertow.util.HttpString> KNOWN_METHODS;

  private final java.util.List<java.lang.String> welcomeFiles;

  private volatile boolean directoryListingEnabled;

  private volatile boolean canonicalizePaths;

  private volatile io.undertow.util.MimeMappings mimeMappings;

  private volatile io.undertow.predicate.Predicate cachable;

  private volatile io.undertow.predicate.Predicate allowed;

  private volatile io.undertow.server.handlers.resource.ResourceSupplier resourceSupplier;

  private volatile io.undertow.server.handlers.resource.ResourceManager resourceManager;

  private volatile java.lang.Integer cacheTime;

  private volatile io.undertow.server.handlers.encoding.ContentEncodedResourceManager contentEncodedResourceManager;

  private final io.undertow.server.HttpHandler next;

  public io.undertow.server.handlers.resource.ResourceHandler(io.undertow.server.handlers.resource.ResourceManager);
    Code:
       0: aload_0
       1: aload_1
       2: getstatic     #1                  // Field io/undertow/server/handlers/ResponseCodeHandler.HANDLE_404:Lio/undertow/server/handlers/ResponseCodeHandler;
       5: invokespecial #2                  // Method "<init>":(Lio/undertow/server/handlers/resource/ResourceManager;Lio/undertow/server/HttpHandler;)V
       8: return

  public io.undertow.server.handlers.resource.ResourceHandler(io.undertow.server.handlers.resource.ResourceManager, io.undertow.server.HttpHandler);
    Code:
       0: aload_0
       1: invokespecial #3                  // Method java/lang/Object."<init>":()V
       4: aload_0
       5: new           #4                  // class java/util/concurrent/CopyOnWriteArrayList
       8: dup
       9: iconst_4
      10: anewarray     #5                  // class java/lang/String
      13: dup
      14: iconst_0
      15: ldc           #6                  // String index.html
      17: aastore
      18: dup
      19: iconst_1
      20: ldc           #7                  // String index.htm
      22: aastore
      23: dup
      24: iconst_2
      25: ldc           #8                  // String default.html
      27: aastore
      28: dup
      29: iconst_3
      30: ldc           #9                  // String default.htm
      32: aastore
      33: invokespecial #10                 // Method java/util/concurrent/CopyOnWriteArrayList."<init>":([Ljava/lang/Object;)V
      36: putfield      #11                 // Field welcomeFiles:Ljava/util/List;
      39: aload_0
      40: iconst_0
      41: putfield      #12                 // Field directoryListingEnabled:Z
      44: aload_0
      45: iconst_1
      46: putfield      #13                 // Field canonicalizePaths:Z
      49: aload_0
      50: getstatic     #14                 // Field io/undertow/util/MimeMappings.DEFAULT:Lio/undertow/util/MimeMappings;
      53: putfield      #15                 // Field mimeMappings:Lio/undertow/util/MimeMappings;
      56: aload_0
      57: invokestatic  #16                 // Method io/undertow/predicate/Predicates.truePredicate:()Lio/undertow/predicate/Predicate;
      60: putfield      #17                 // Field cachable:Lio/undertow/predicate/Predicate;
      63: aload_0
      64: invokestatic  #16                 // Method io/undertow/predicate/Predicates.truePredicate:()Lio/undertow/predicate/Predicate;
      67: putfield      #18                 // Field allowed:Lio/undertow/predicate/Predicate;
      70: aload_0
      71: new           #19                 // class io/undertow/server/handlers/resource/DefaultResourceSupplier
      74: dup
      75: aload_1
      76: invokespecial #20                 // Method io/undertow/server/handlers/resource/DefaultResourceSupplier."<init>":(Lio/undertow/server/handlers/resource/ResourceManager;)V
      79: putfield      #21                 // Field resourceSupplier:Lio/undertow/server/handlers/resource/ResourceSupplier;
      82: aload_0
      83: aload_1
      84: putfield      #22                 // Field resourceManager:Lio/undertow/server/handlers/resource/ResourceManager;
      87: aload_0
      88: aload_2
      89: putfield      #23                 // Field next:Lio/undertow/server/HttpHandler;
      92: return

  public io.undertow.server.handlers.resource.ResourceHandler(io.undertow.server.handlers.resource.ResourceSupplier);
    Code:
       0: aload_0
       1: aload_1
       2: getstatic     #1                  // Field io/undertow/server/handlers/ResponseCodeHandler.HANDLE_404:Lio/undertow/server/handlers/ResponseCodeHandler;
       5: invokespecial #24                 // Method "<init>":(Lio/undertow/server/handlers/resource/ResourceSupplier;Lio/undertow/server/HttpHandler;)V
       8: return

  public io.undertow.server.handlers.resource.ResourceHandler(io.undertow.server.handlers.resource.ResourceSupplier, io.undertow.server.HttpHandler);
    Code:
       0: aload_0
       1: invokespecial #3                  // Method java/lang/Object."<init>":()V
       4: aload_0
       5: new           #4                  // class java/util/concurrent/CopyOnWriteArrayList
       8: dup
       9: iconst_4
      10: anewarray     #5                  // class java/lang/String
      13: dup
      14: iconst_0
      15: ldc           #6                  // String index.html
      17: aastore
      18: dup
      19: iconst_1
      20: ldc           #7                  // String index.htm
      22: aastore
      23: dup
      24: iconst_2
      25: ldc           #8                  // String default.html
      27: aastore
      28: dup
      29: iconst_3
      30: ldc           #9                  // String default.htm
      32: aastore
      33: invokespecial #10                 // Method java/util/concurrent/CopyOnWriteArrayList."<init>":([Ljava/lang/Object;)V
      36: putfield      #11                 // Field welcomeFiles:Ljava/util/List;
      39: aload_0
      40: iconst_0
      41: putfield      #12                 // Field directoryListingEnabled:Z
      44: aload_0
      45: iconst_1
      46: putfield      #13                 // Field canonicalizePaths:Z
      49: aload_0
      50: getstatic     #14                 // Field io/undertow/util/MimeMappings.DEFAULT:Lio/undertow/util/MimeMappings;
      53: putfield      #15                 // Field mimeMappings:Lio/undertow/util/MimeMappings;
      56: aload_0
      57: invokestatic  #16                 // Method io/undertow/predicate/Predicates.truePredicate:()Lio/undertow/predicate/Predicate;
      60: putfield      #17                 // Field cachable:Lio/undertow/predicate/Predicate;
      63: aload_0
      64: invokestatic  #16                 // Method io/undertow/predicate/Predicates.truePredicate:()Lio/undertow/predicate/Predicate;
      67: putfield      #18                 // Field allowed:Lio/undertow/predicate/Predicate;
      70: aload_0
      71: aload_1
      72: putfield      #21                 // Field resourceSupplier:Lio/undertow/server/handlers/resource/ResourceSupplier;
      75: aload_0
      76: aload_2
      77: putfield      #23                 // Field next:Lio/undertow/server/HttpHandler;
      80: return

  public io.undertow.server.handlers.resource.ResourceHandler();
    Code:
       0: aload_0
       1: invokespecial #3                  // Method java/lang/Object."<init>":()V
       4: aload_0
       5: new           #4                  // class java/util/concurrent/CopyOnWriteArrayList
       8: dup
       9: iconst_4
      10: anewarray     #5                  // class java/lang/String
      13: dup
      14: iconst_0
      15: ldc           #6                  // String index.html
      17: aastore
      18: dup
      19: iconst_1
      20: ldc           #7                  // String index.htm
      22: aastore
      23: dup
      24: iconst_2
      25: ldc           #8                  // String default.html
      27: aastore
      28: dup
      29: iconst_3
      30: ldc           #9                  // String default.htm
      32: aastore
      33: invokespecial #10                 // Method java/util/concurrent/CopyOnWriteArrayList."<init>":([Ljava/lang/Object;)V
      36: putfield      #11                 // Field welcomeFiles:Ljava/util/List;
      39: aload_0
      40: iconst_0
      41: putfield      #12                 // Field directoryListingEnabled:Z
      44: aload_0
      45: iconst_1
      46: putfield      #13                 // Field canonicalizePaths:Z
      49: aload_0
      50: getstatic     #14                 // Field io/undertow/util/MimeMappings.DEFAULT:Lio/undertow/util/MimeMappings;
      53: putfield      #15                 // Field mimeMappings:Lio/undertow/util/MimeMappings;
      56: aload_0
      57: invokestatic  #16                 // Method io/undertow/predicate/Predicates.truePredicate:()Lio/undertow/predicate/Predicate;
      60: putfield      #17                 // Field cachable:Lio/undertow/predicate/Predicate;
      63: aload_0
      64: invokestatic  #16                 // Method io/undertow/predicate/Predicates.truePredicate:()Lio/undertow/predicate/Predicate;
      67: putfield      #18                 // Field allowed:Lio/undertow/predicate/Predicate;
      70: aload_0
      71: getstatic     #1                  // Field io/undertow/server/handlers/ResponseCodeHandler.HANDLE_404:Lio/undertow/server/handlers/ResponseCodeHandler;
      74: putfield      #23                 // Field next:Lio/undertow/server/HttpHandler;
      77: return

  public void handleRequest(io.undertow.server.HttpServerExchange) throws java.lang.Exception;
    Code:
       0: aload_1
       1: invokevirtual #25                 // Method io/undertow/server/HttpServerExchange.getRequestMethod:()Lio/undertow/util/HttpString;
       4: getstatic     #26                 // Field io/undertow/util/Methods.GET:Lio/undertow/util/HttpString;
       7: invokevirtual #27                 // Method io/undertow/util/HttpString.equals:(Lio/undertow/util/HttpString;)Z
      10: ifne          26
      13: aload_1
      14: invokevirtual #25                 // Method io/undertow/server/HttpServerExchange.getRequestMethod:()Lio/undertow/util/HttpString;
      17: getstatic     #28                 // Field io/undertow/util/Methods.POST:Lio/undertow/util/HttpString;
      20: invokevirtual #27                 // Method io/undertow/util/HttpString.equals:(Lio/undertow/util/HttpString;)Z
      23: ifeq          35
      26: aload_0
      27: aload_1
      28: iconst_1
      29: invokevirtual #29                 // Method serveResource:(Lio/undertow/server/HttpServerExchange;Z)V
      32: goto          131
      35: aload_1
      36: invokevirtual #25                 // Method io/undertow/server/HttpServerExchange.getRequestMethod:()Lio/undertow/util/HttpString;
      39: getstatic     #30                 // Field io/undertow/util/Methods.HEAD:Lio/undertow/util/HttpString;
      42: invokevirtual #27                 // Method io/undertow/util/HttpString.equals:(Lio/undertow/util/HttpString;)Z
      45: ifeq          57
      48: aload_0
      49: aload_1
      50: iconst_0
      51: invokevirtual #29                 // Method serveResource:(Lio/undertow/server/HttpServerExchange;Z)V
      54: goto          131
      57: getstatic     #31                 // Field KNOWN_METHODS:Ljava/util/Set;
      60: aload_1
      61: invokevirtual #25                 // Method io/undertow/server/HttpServerExchange.getRequestMethod:()Lio/undertow/util/HttpString;
      64: invokeinterface #32,  2           // InterfaceMethod java/util/Set.contains:(Ljava/lang/Object;)Z
      69: ifeq          118
      72: aload_1
      73: sipush        405
      76: invokevirtual #34                 // Method io/undertow/server/HttpServerExchange.setStatusCode:(I)Lio/undertow/server/HttpServerExchange;
      79: pop
      80: aload_1
      81: invokevirtual #35                 // Method io/undertow/server/HttpServerExchange.getResponseHeaders:()Lio/undertow/util/HeaderMap;
      84: getstatic     #36                 // Field io/undertow/util/Headers.ALLOW:Lio/undertow/util/HttpString;
      87: ldc           #37                 // String ,
      89: iconst_3
      90: anewarray     #38                 // class java/lang/CharSequence
      93: dup
      94: iconst_0
      95: ldc           #40                 // String GET
      97: aastore
      98: dup
      99: iconst_1
     100: ldc           #41                 // String HEAD
     102: aastore
     103: dup
     104: iconst_2
     105: ldc           #42                 // String POST
     107: aastore
     108: invokestatic  #43                 // Method java/lang/String.join:(Ljava/lang/CharSequence;[Ljava/lang/CharSequence;)Ljava/lang/String;
     111: invokevirtual #44                 // Method io/undertow/util/HeaderMap.add:(Lio/undertow/util/HttpString;Ljava/lang/String;)Lio/undertow/util/HeaderMap;
     114: pop
     115: goto          126
     118: aload_1
     119: sipush        501
     122: invokevirtual #34                 // Method io/undertow/server/HttpServerExchange.setStatusCode:(I)Lio/undertow/server/HttpServerExchange;
     125: pop
     126: aload_1
     127: invokevirtual #45                 // Method io/undertow/server/HttpServerExchange.endExchange:()Lio/undertow/server/HttpServerExchange;
     130: pop
     131: return

  private void serveResource(io.undertow.server.HttpServerExchange, boolean) throws java.lang.Exception;
    Code:
       0: aload_0
       1: getfield      #12                 // Field directoryListingEnabled:Z
       4: ifeq          15
       7: aload_1
       8: invokestatic  #46                 // Method io/undertow/server/handlers/resource/DirectoryUtils.sendRequestedBlobs:(Lio/undertow/server/HttpServerExchange;)Z
      11: ifeq          15
      14: return
      15: aload_0
      16: getfield      #18                 // Field allowed:Lio/undertow/predicate/Predicate;
      19: aload_1
      20: invokeinterface #47,  2           // InterfaceMethod io/undertow/predicate/Predicate.resolve:(Lio/undertow/server/HttpServerExchange;)Z
      25: ifne          42
      28: aload_1
      29: sipush        403
      32: invokevirtual #34                 // Method io/undertow/server/HttpServerExchange.setStatusCode:(I)Lio/undertow/server/HttpServerExchange;
      35: pop
      36: aload_1
      37: invokevirtual #45                 // Method io/undertow/server/HttpServerExchange.endExchange:()Lio/undertow/server/HttpServerExchange;
      40: pop
      41: return
      42: aload_1
      43: getstatic     #48                 // Field io/undertow/server/handlers/cache/ResponseCache.ATTACHMENT_KEY:Lio/undertow/util/AttachmentKey;
      46: invokevirtual #49                 // Method io/undertow/server/HttpServerExchange.getAttachment:(Lio/undertow/util/AttachmentKey;)Ljava/lang/Object;
      49: checkcast     #50                 // class io/undertow/server/handlers/cache/ResponseCache
      52: astore_3
      53: aload_0
      54: getfield      #17                 // Field cachable:Lio/undertow/predicate/Predicate;
      57: aload_1
      58: invokeinterface #47,  2           // InterfaceMethod io/undertow/predicate/Predicate.resolve:(Lio/undertow/server/HttpServerExchange;)Z
      63: istore        4
      65: iload         4
      67: ifeq          144
      70: aload_0
      71: getfield      #51                 // Field cacheTime:Ljava/lang/Integer;
      74: ifnull        144
      77: aload_1
      78: invokevirtual #35                 // Method io/undertow/server/HttpServerExchange.getResponseHeaders:()Lio/undertow/util/HeaderMap;
      81: getstatic     #52                 // Field io/undertow/util/Headers.CACHE_CONTROL:Lio/undertow/util/HttpString;
      84: aload_0
      85: getfield      #51                 // Field cacheTime:Ljava/lang/Integer;
      88: invokedynamic #53,  0             // InvokeDynamic #0:makeConcatWithConstants:(Ljava/lang/Integer;)Ljava/lang/String;
      93: invokevirtual #54                 // Method io/undertow/util/HeaderMap.put:(Lio/undertow/util/HttpString;Ljava/lang/String;)Lio/undertow/util/HeaderMap;
      96: pop
      97: invokestatic  #55                 // Method java/lang/System.currentTimeMillis:()J
     100: getstatic     #56                 // Field java/util/concurrent/TimeUnit.SECONDS:Ljava/util/concurrent/TimeUnit;
     103: aload_0
     104: getfield      #51                 // Field cacheTime:Ljava/lang/Integer;
     107: invokevirtual #57                 // Method java/lang/Integer.intValue:()I
     110: i2l
     111: invokevirtual #58                 // Method java/util/concurrent/TimeUnit.toMillis:(J)J
     114: ladd
     115: lstore        5
     117: new           #59                 // class java/util/Date
     120: dup
     121: lload         5
     123: invokespecial #60                 // Method java/util/Date."<init>":(J)V
     126: invokestatic  #61                 // Method io/undertow/util/DateUtils.toDateString:(Ljava/util/Date;)Ljava/lang/String;
     129: astore        7
     131: aload_1
     132: invokevirtual #35                 // Method io/undertow/server/HttpServerExchange.getResponseHeaders:()Lio/undertow/util/HeaderMap;
     135: getstatic     #62                 // Field io/undertow/util/Headers.EXPIRES:Lio/undertow/util/HttpString;
     138: aload         7
     140: invokevirtual #54                 // Method io/undertow/util/HeaderMap.put:(Lio/undertow/util/HttpString;Ljava/lang/String;)Lio/undertow/util/HeaderMap;
     143: pop
     144: aload_3
     145: ifnull        161
     148: iload         4
     150: ifeq          161
     153: aload_3
     154: invokevirtual #63                 // Method io/undertow/server/handlers/cache/ResponseCache.tryServeResponse:()Z
     157: ifeq          161
     160: return
     161: new           #64                 // class io/undertow/server/handlers/resource/ResourceHandler$1
     164: dup
     165: aload_0
     166: iload_2
     167: invokespecial #65                 // Method io/undertow/server/handlers/resource/ResourceHandler$1."<init>":(Lio/undertow/server/handlers/resource/ResourceHandler;Z)V
     170: astore        5
     172: aload_1
     173: invokevirtual #66                 // Method io/undertow/server/HttpServerExchange.isInIoThread:()Z
     176: ifeq          189
     179: aload_1
     180: aload         5
     182: invokevirtual #67                 // Method io/undertow/server/HttpServerExchange.dispatch:(Lio/undertow/server/HttpHandler;)Lio/undertow/server/HttpServerExchange;
     185: pop
     186: goto          197
     189: aload         5
     191: aload_1
     192: invokeinterface #68,  2           // InterfaceMethod io/undertow/server/HttpHandler.handleRequest:(Lio/undertow/server/HttpServerExchange;)V
     197: return

  private void clearCacheHeaders(io.undertow.server.HttpServerExchange);
    Code:
       0: aload_1
       1: invokevirtual #35                 // Method io/undertow/server/HttpServerExchange.getResponseHeaders:()Lio/undertow/util/HeaderMap;
       4: getstatic     #52                 // Field io/undertow/util/Headers.CACHE_CONTROL:Lio/undertow/util/HttpString;
       7: invokevirtual #69                 // Method io/undertow/util/HeaderMap.remove:(Lio/undertow/util/HttpString;)Ljava/util/Collection;
      10: pop
      11: aload_1
      12: invokevirtual #35                 // Method io/undertow/server/HttpServerExchange.getResponseHeaders:()Lio/undertow/util/HeaderMap;
      15: getstatic     #62                 // Field io/undertow/util/Headers.EXPIRES:Lio/undertow/util/HttpString;
      18: invokevirtual #69                 // Method io/undertow/util/HeaderMap.remove:(Lio/undertow/util/HttpString;)Ljava/util/Collection;
      21: pop
      22: return

  private io.undertow.server.handlers.resource.Resource getIndexFiles(io.undertow.server.HttpServerExchange, io.undertow.server.handlers.resource.ResourceSupplier, java.lang.String, java.util.List<java.lang.String>) throws java.io.IOException;
    Code:
       0: aload_3
       1: ldc           #70                 // String /
       3: invokevirtual #71                 // Method java/lang/String.endsWith:(Ljava/lang/String;)Z
       6: ifeq          15
       9: aload_3
      10: astore        5
      12: goto          23
      15: aload_3
      16: invokedynamic #72,  0             // InvokeDynamic #1:makeConcatWithConstants:(Ljava/lang/String;)Ljava/lang/String;
      21: astore        5
      23: aload         4
      25: invokeinterface #73,  1           // InterfaceMethod java/util/List.iterator:()Ljava/util/Iterator;
      30: astore        6
      32: aload         6
      34: invokeinterface #74,  1           // InterfaceMethod java/util/Iterator.hasNext:()Z
      39: ifeq          87
      42: aload         6
      44: invokeinterface #75,  1           // InterfaceMethod java/util/Iterator.next:()Ljava/lang/Object;
      49: checkcast     #5                  // class java/lang/String
      52: astore        7
      54: aload_2
      55: aload_1
      56: aload_0
      57: aload         5
      59: aload         7
      61: invokedynamic #76,  0             // InvokeDynamic #2:makeConcatWithConstants:(Ljava/lang/String;Ljava/lang/String;)Ljava/lang/String;
      66: invokevirtual #77                 // Method canonicalize:(Ljava/lang/String;)Ljava/lang/String;
      69: invokeinterface #78,  3           // InterfaceMethod io/undertow/server/handlers/resource/ResourceSupplier.getResource:(Lio/undertow/server/HttpServerExchange;Ljava/lang/String;)Lio/undertow/server/handlers/resource/Resource;
      74: astore        8
      76: aload         8
      78: ifnull        84
      81: aload         8
      83: areturn
      84: goto          32
      87: aconst_null
      88: areturn

  private java.lang.String canonicalize(java.lang.String);
    Code:
       0: aload_0
       1: getfield      #13                 // Field canonicalizePaths:Z
       4: ifeq          12
       7: aload_1
       8: invokestatic  #79                 // Method io/undertow/util/CanonicalPathUtils.canonicalize:(Ljava/lang/String;)Ljava/lang/String;
      11: areturn
      12: aload_1
      13: areturn

  public boolean isDirectoryListingEnabled();
    Code:
       0: aload_0
       1: getfield      #12                 // Field directoryListingEnabled:Z
       4: ireturn

  public io.undertow.server.handlers.resource.ResourceHandler setDirectoryListingEnabled(boolean);
    Code:
       0: aload_0
       1: iload_1
       2: putfield      #12                 // Field directoryListingEnabled:Z
       5: aload_0
       6: areturn

  public io.undertow.server.handlers.resource.ResourceHandler addWelcomeFiles(java.lang.String...);
    Code:
       0: aload_0
       1: getfield      #11                 // Field welcomeFiles:Ljava/util/List;
       4: aload_1
       5: invokestatic  #80                 // Method java/util/Arrays.asList:([Ljava/lang/Object;)Ljava/util/List;
       8: invokeinterface #81,  2           // InterfaceMethod java/util/List.addAll:(Ljava/util/Collection;)Z
      13: pop
      14: aload_0
      15: areturn

  public io.undertow.server.handlers.resource.ResourceHandler setWelcomeFiles(java.lang.String...);
    Code:
       0: aload_0
       1: getfield      #11                 // Field welcomeFiles:Ljava/util/List;
       4: invokeinterface #82,  1           // InterfaceMethod java/util/List.clear:()V
       9: aload_0
      10: getfield      #11                 // Field welcomeFiles:Ljava/util/List;
      13: aload_1
      14: invokestatic  #80                 // Method java/util/Arrays.asList:([Ljava/lang/Object;)Ljava/util/List;
      17: invokeinterface #81,  2           // InterfaceMethod java/util/List.addAll:(Ljava/util/Collection;)Z
      22: pop
      23: aload_0
      24: areturn

  public io.undertow.util.MimeMappings getMimeMappings();
    Code:
       0: aload_0
       1: getfield      #15                 // Field mimeMappings:Lio/undertow/util/MimeMappings;
       4: areturn

  public io.undertow.server.handlers.resource.ResourceHandler setMimeMappings(io.undertow.util.MimeMappings);
    Code:
       0: aload_0
       1: aload_1
       2: putfield      #15                 // Field mimeMappings:Lio/undertow/util/MimeMappings;
       5: aload_0
       6: areturn

  public io.undertow.predicate.Predicate getCachable();
    Code:
       0: aload_0
       1: getfield      #17                 // Field cachable:Lio/undertow/predicate/Predicate;
       4: areturn

  public io.undertow.server.handlers.resource.ResourceHandler setCachable(io.undertow.predicate.Predicate);
    Code:
       0: aload_0
       1: aload_1
       2: putfield      #17                 // Field cachable:Lio/undertow/predicate/Predicate;
       5: aload_0
       6: areturn

  public io.undertow.predicate.Predicate getAllowed();
    Code:
       0: aload_0
       1: getfield      #18                 // Field allowed:Lio/undertow/predicate/Predicate;
       4: areturn

  public io.undertow.server.handlers.resource.ResourceHandler setAllowed(io.undertow.predicate.Predicate);
    Code:
       0: aload_0
       1: aload_1
       2: putfield      #18                 // Field allowed:Lio/undertow/predicate/Predicate;
       5: aload_0
       6: areturn

  public io.undertow.server.handlers.resource.ResourceSupplier getResourceSupplier();
    Code:
       0: aload_0
       1: getfield      #21                 // Field resourceSupplier:Lio/undertow/server/handlers/resource/ResourceSupplier;
       4: areturn

  public io.undertow.server.handlers.resource.ResourceHandler setResourceSupplier(io.undertow.server.handlers.resource.ResourceSupplier);
    Code:
       0: aload_0
       1: aload_1
       2: putfield      #21                 // Field resourceSupplier:Lio/undertow/server/handlers/resource/ResourceSupplier;
       5: aload_0
       6: aconst_null
       7: putfield      #22                 // Field resourceManager:Lio/undertow/server/handlers/resource/ResourceManager;
      10: aload_0
      11: areturn

  public io.undertow.server.handlers.resource.ResourceManager getResourceManager();
    Code:
       0: aload_0
       1: getfield      #22                 // Field resourceManager:Lio/undertow/server/handlers/resource/ResourceManager;
       4: areturn

  public io.undertow.server.handlers.resource.ResourceHandler setResourceManager(io.undertow.server.handlers.resource.ResourceManager);
    Code:
       0: aload_0
       1: aload_1
       2: putfield      #22                 // Field resourceManager:Lio/undertow/server/handlers/resource/ResourceManager;
       5: aload_0
       6: new           #19                 // class io/undertow/server/handlers/resource/DefaultResourceSupplier
       9: dup
      10: aload_1
      11: invokespecial #20                 // Method io/undertow/server/handlers/resource/DefaultResourceSupplier."<init>":(Lio/undertow/server/handlers/resource/ResourceManager;)V
      14: putfield      #21                 // Field resourceSupplier:Lio/undertow/server/handlers/resource/ResourceSupplier;
      17: aload_0
      18: areturn

  public java.lang.Integer getCacheTime();
    Code:
       0: aload_0
       1: getfield      #51                 // Field cacheTime:Ljava/lang/Integer;
       4: areturn

  public io.undertow.server.handlers.resource.ResourceHandler setCacheTime(java.lang.Integer);
    Code:
       0: aload_0
       1: aload_1
       2: putfield      #51                 // Field cacheTime:Ljava/lang/Integer;
       5: aload_0
       6: areturn

  public io.undertow.server.handlers.encoding.ContentEncodedResourceManager getContentEncodedResourceManager();
    Code:
       0: aload_0
       1: getfield      #83                 // Field contentEncodedResourceManager:Lio/undertow/server/handlers/encoding/ContentEncodedResourceManager;
       4: areturn

  public io.undertow.server.handlers.resource.ResourceHandler setContentEncodedResourceManager(io.undertow.server.handlers.encoding.ContentEncodedResourceManager);
    Code:
       0: aload_0
       1: aload_1
       2: putfield      #83                 // Field contentEncodedResourceManager:Lio/undertow/server/handlers/encoding/ContentEncodedResourceManager;
       5: aload_0
       6: areturn

  public boolean isCanonicalizePaths();
    Code:
       0: aload_0
       1: getfield      #13                 // Field canonicalizePaths:Z
       4: ireturn

  public void setCanonicalizePaths(boolean);
    Code:
       0: aload_0
       1: iload_1
       2: putfield      #13                 // Field canonicalizePaths:Z
       5: return

  static {};
    Code:
       0: new           #84                 // class java/util/HashSet
       3: dup
       4: invokespecial #85                 // Method java/util/HashSet."<init>":()V
       7: putstatic     #31                 // Field KNOWN_METHODS:Ljava/util/Set;
      10: getstatic     #31                 // Field KNOWN_METHODS:Ljava/util/Set;
      13: getstatic     #86                 // Field io/undertow/util/Methods.OPTIONS:Lio/undertow/util/HttpString;
      16: invokeinterface #87,  2           // InterfaceMethod java/util/Set.add:(Ljava/lang/Object;)Z
      21: pop
      22: getstatic     #31                 // Field KNOWN_METHODS:Ljava/util/Set;
      25: getstatic     #26                 // Field io/undertow/util/Methods.GET:Lio/undertow/util/HttpString;
      28: invokeinterface #87,  2           // InterfaceMethod java/util/Set.add:(Ljava/lang/Object;)Z
      33: pop
      34: getstatic     #31                 // Field KNOWN_METHODS:Ljava/util/Set;
      37: getstatic     #30                 // Field io/undertow/util/Methods.HEAD:Lio/undertow/util/HttpString;
      40: invokeinterface #87,  2           // InterfaceMethod java/util/Set.add:(Ljava/lang/Object;)Z
      45: pop
      46: getstatic     #31                 // Field KNOWN_METHODS:Ljava/util/Set;
      49: getstatic     #28                 // Field io/undertow/util/Methods.POST:Lio/undertow/util/HttpString;
      52: invokeinterface #87,  2           // InterfaceMethod java/util/Set.add:(Ljava/lang/Object;)Z
      57: pop
      58: getstatic     #31                 // Field KNOWN_METHODS:Ljava/util/Set;
      61: getstatic     #88                 // Field io/undertow/util/Methods.PUT:Lio/undertow/util/HttpString;
      64: invokeinterface #87,  2           // InterfaceMethod java/util/Set.add:(Ljava/lang/Object;)Z
      69: pop
      70: getstatic     #31                 // Field KNOWN_METHODS:Ljava/util/Set;
      73: getstatic     #89                 // Field io/undertow/util/Methods.DELETE:Lio/undertow/util/HttpString;
      76: invokeinterface #87,  2           // InterfaceMethod java/util/Set.add:(Ljava/lang/Object;)Z
      81: pop
      82: getstatic     #31                 // Field KNOWN_METHODS:Ljava/util/Set;
      85: getstatic     #90                 // Field io/undertow/util/Methods.TRACE:Lio/undertow/util/HttpString;
      88: invokeinterface #87,  2           // InterfaceMethod java/util/Set.add:(Ljava/lang/Object;)Z
      93: pop
      94: getstatic     #31                 // Field KNOWN_METHODS:Ljava/util/Set;
      97: getstatic     #91                 // Field io/undertow/util/Methods.CONNECT:Lio/undertow/util/HttpString;
     100: invokeinterface #87,  2           // InterfaceMethod java/util/Set.add:(Ljava/lang/Object;)Z
     105: pop
     106: return
}
