Compiled from "DoneableAllowedCSIDriver.java"
public class io.fabric8.kubernetes.api.model.policy.DoneableAllowedCSIDriver extends io.fabric8.kubernetes.api.model.policy.AllowedCSIDriverFluentImpl<io.fabric8.kubernetes.api.model.policy.DoneableAllowedCSIDriver> implements io.fabric8.kubernetes.api.model.Doneable<io.fabric8.kubernetes.api.model.policy.AllowedCSIDriver> {
  private final io.fabric8.kubernetes.api.model.policy.AllowedCSIDriverBuilder builder;

  private final io.fabric8.kubernetes.api.builder.Function<io.fabric8.kubernetes.api.model.policy.AllowedCSIDriver, io.fabric8.kubernetes.api.model.policy.AllowedCSIDriver> function;

  public io.fabric8.kubernetes.api.model.policy.DoneableAllowedCSIDriver(io.fabric8.kubernetes.api.builder.Function<io.fabric8.kubernetes.api.model.policy.AllowedCSIDriver, io.fabric8.kubernetes.api.model.policy.AllowedCSIDriver>);
    Code:
       0: aload_0
       1: invokespecial #1                  // Method io/fabric8/kubernetes/api/model/policy/AllowedCSIDriverFluentImpl."<init>":()V
       4: aload_0
       5: new           #2                  // class io/fabric8/kubernetes/api/model/policy/AllowedCSIDriverBuilder
       8: dup
       9: aload_0
      10: invokespecial #3                  // Method io/fabric8/kubernetes/api/model/policy/AllowedCSIDriverBuilder."<init>":(Lio/fabric8/kubernetes/api/model/policy/AllowedCSIDriverFluent;)V
      13: putfield      #4                  // Field builder:Lio/fabric8/kubernetes/api/model/policy/AllowedCSIDriverBuilder;
      16: aload_0
      17: aload_1
      18: putfield      #5                  // Field function:Lio/fabric8/kubernetes/api/builder/Function;
      21: return

  public io.fabric8.kubernetes.api.model.policy.DoneableAllowedCSIDriver(io.fabric8.kubernetes.api.model.policy.AllowedCSIDriver, io.fabric8.kubernetes.api.builder.Function<io.fabric8.kubernetes.api.model.policy.AllowedCSIDriver, io.fabric8.kubernetes.api.model.policy.AllowedCSIDriver>);
    Code:
       0: aload_0
       1: aload_1
       2: invokespecial #6                  // Method io/fabric8/kubernetes/api/model/policy/AllowedCSIDriverFluentImpl."<init>":(Lio/fabric8/kubernetes/api/model/policy/AllowedCSIDriver;)V
       5: aload_0
       6: new           #2                  // class io/fabric8/kubernetes/api/model/policy/AllowedCSIDriverBuilder
       9: dup
      10: aload_0
      11: aload_1
      12: invokespecial #7                  // Method io/fabric8/kubernetes/api/model/policy/AllowedCSIDriverBuilder."<init>":(Lio/fabric8/kubernetes/api/model/policy/AllowedCSIDriverFluent;Lio/fabric8/kubernetes/api/model/policy/AllowedCSIDriver;)V
      15: putfield      #4                  // Field builder:Lio/fabric8/kubernetes/api/model/policy/AllowedCSIDriverBuilder;
      18: aload_0
      19: aload_2
      20: putfield      #5                  // Field function:Lio/fabric8/kubernetes/api/builder/Function;
      23: return

  public io.fabric8.kubernetes.api.model.policy.DoneableAllowedCSIDriver(io.fabric8.kubernetes.api.model.policy.AllowedCSIDriver);
    Code:
       0: aload_0
       1: aload_1
       2: invokespecial #6                  // Method io/fabric8/kubernetes/api/model/policy/AllowedCSIDriverFluentImpl."<init>":(Lio/fabric8/kubernetes/api/model/policy/AllowedCSIDriver;)V
       5: aload_0
       6: new           #2                  // class io/fabric8/kubernetes/api/model/policy/AllowedCSIDriverBuilder
       9: dup
      10: aload_0
      11: aload_1
      12: invokespecial #7                  // Method io/fabric8/kubernetes/api/model/policy/AllowedCSIDriverBuilder."<init>":(Lio/fabric8/kubernetes/api/model/policy/AllowedCSIDriverFluent;Lio/fabric8/kubernetes/api/model/policy/AllowedCSIDriver;)V
      15: putfield      #4                  // Field builder:Lio/fabric8/kubernetes/api/model/policy/AllowedCSIDriverBuilder;
      18: aload_0
      19: new           #8                  // class io/fabric8/kubernetes/api/model/policy/DoneableAllowedCSIDriver$1
      22: dup
      23: aload_0
      24: invokespecial #9                  // Method io/fabric8/kubernetes/api/model/policy/DoneableAllowedCSIDriver$1."<init>":(Lio/fabric8/kubernetes/api/model/policy/DoneableAllowedCSIDriver;)V
      27: putfield      #5                  // Field function:Lio/fabric8/kubernetes/api/builder/Function;
      30: return

  public io.fabric8.kubernetes.api.model.policy.AllowedCSIDriver done();
    Code:
       0: aload_0
       1: getfield      #5                  // Field function:Lio/fabric8/kubernetes/api/builder/Function;
       4: aload_0
       5: getfield      #4                  // Field builder:Lio/fabric8/kubernetes/api/model/policy/AllowedCSIDriverBuilder;
       8: invokevirtual #10                 // Method io/fabric8/kubernetes/api/model/policy/AllowedCSIDriverBuilder.build:()Lio/fabric8/kubernetes/api/model/policy/AllowedCSIDriver;
      11: invokeinterface #11,  2           // InterfaceMethod io/fabric8/kubernetes/api/builder/Function.apply:(Ljava/lang/Object;)Ljava/lang/Object;
      16: checkcast     #12                 // class io/fabric8/kubernetes/api/model/policy/AllowedCSIDriver
      19: areturn

  public java.lang.Object done();
    Code:
       0: aload_0
       1: invokevirtual #13                 // Method done:()Lio/fabric8/kubernetes/api/model/policy/AllowedCSIDriver;
       4: areturn
}
