Compiled from "IndexWriterV2.java"
class org.jboss.jandex.IndexWriterV2$1 {
  static final int[] $SwitchMap$org$jboss$jandex$TypeTarget$Usage;

  static final int[] $SwitchMap$org$jboss$jandex$Type$Kind;

  static {};
    Code:
       0: invokestatic  #1                  // Method org/jboss/jandex/Type$Kind.values:()[Lorg/jboss/jandex/Type$Kind;
       3: arraylength
       4: newarray       int
       6: putstatic     #2                  // Field $SwitchMap$org$jboss$jandex$Type$Kind:[I
       9: getstatic     #2                  // Field $SwitchMap$org$jboss$jandex$Type$Kind:[I
      12: getstatic     #3                  // Field org/jboss/jandex/Type$Kind.CLASS:Lorg/jboss/jandex/Type$Kind;
      15: invokevirtual #4                  // Method org/jboss/jandex/Type$Kind.ordinal:()I
      18: iconst_1
      19: iastore
      20: goto          24
      23: astore_0
      24: getstatic     #2                  // Field $SwitchMap$org$jboss$jandex$Type$Kind:[I
      27: getstatic     #6                  // Field org/jboss/jandex/Type$Kind.ARRAY:Lorg/jboss/jandex/Type$Kind;
      30: invokevirtual #4                  // Method org/jboss/jandex/Type$Kind.ordinal:()I
      33: iconst_2
      34: iastore
      35: goto          39
      38: astore_0
      39: getstatic     #2                  // Field $SwitchMap$org$jboss$jandex$Type$Kind:[I
      42: getstatic     #7                  // Field org/jboss/jandex/Type$Kind.PRIMITIVE:Lorg/jboss/jandex/Type$Kind;
      45: invokevirtual #4                  // Method org/jboss/jandex/Type$Kind.ordinal:()I
      48: iconst_3
      49: iastore
      50: goto          54
      53: astore_0
      54: getstatic     #2                  // Field $SwitchMap$org$jboss$jandex$Type$Kind:[I
      57: getstatic     #8                  // Field org/jboss/jandex/Type$Kind.VOID:Lorg/jboss/jandex/Type$Kind;
      60: invokevirtual #4                  // Method org/jboss/jandex/Type$Kind.ordinal:()I
      63: iconst_4
      64: iastore
      65: goto          69
      68: astore_0
      69: getstatic     #2                  // Field $SwitchMap$org$jboss$jandex$Type$Kind:[I
      72: getstatic     #9                  // Field org/jboss/jandex/Type$Kind.TYPE_VARIABLE:Lorg/jboss/jandex/Type$Kind;
      75: invokevirtual #4                  // Method org/jboss/jandex/Type$Kind.ordinal:()I
      78: iconst_5
      79: iastore
      80: goto          84
      83: astore_0
      84: getstatic     #2                  // Field $SwitchMap$org$jboss$jandex$Type$Kind:[I
      87: getstatic     #10                 // Field org/jboss/jandex/Type$Kind.UNRESOLVED_TYPE_VARIABLE:Lorg/jboss/jandex/Type$Kind;
      90: invokevirtual #4                  // Method org/jboss/jandex/Type$Kind.ordinal:()I
      93: bipush        6
      95: iastore
      96: goto          100
      99: astore_0
     100: getstatic     #2                  // Field $SwitchMap$org$jboss$jandex$Type$Kind:[I
     103: getstatic     #11                 // Field org/jboss/jandex/Type$Kind.WILDCARD_TYPE:Lorg/jboss/jandex/Type$Kind;
     106: invokevirtual #4                  // Method org/jboss/jandex/Type$Kind.ordinal:()I
     109: bipush        7
     111: iastore
     112: goto          116
     115: astore_0
     116: getstatic     #2                  // Field $SwitchMap$org$jboss$jandex$Type$Kind:[I
     119: getstatic     #12                 // Field org/jboss/jandex/Type$Kind.PARAMETERIZED_TYPE:Lorg/jboss/jandex/Type$Kind;
     122: invokevirtual #4                  // Method org/jboss/jandex/Type$Kind.ordinal:()I
     125: bipush        8
     127: iastore
     128: goto          132
     131: astore_0
     132: invokestatic  #13                 // Method org/jboss/jandex/TypeTarget$Usage.values:()[Lorg/jboss/jandex/TypeTarget$Usage;
     135: arraylength
     136: newarray       int
     138: putstatic     #14                 // Field $SwitchMap$org$jboss$jandex$TypeTarget$Usage:[I
     141: getstatic     #14                 // Field $SwitchMap$org$jboss$jandex$TypeTarget$Usage:[I
     144: getstatic     #15                 // Field org/jboss/jandex/TypeTarget$Usage.EMPTY:Lorg/jboss/jandex/TypeTarget$Usage;
     147: invokevirtual #16                 // Method org/jboss/jandex/TypeTarget$Usage.ordinal:()I
     150: iconst_1
     151: iastore
     152: goto          156
     155: astore_0
     156: getstatic     #14                 // Field $SwitchMap$org$jboss$jandex$TypeTarget$Usage:[I
     159: getstatic     #17                 // Field org/jboss/jandex/TypeTarget$Usage.CLASS_EXTENDS:Lorg/jboss/jandex/TypeTarget$Usage;
     162: invokevirtual #16                 // Method org/jboss/jandex/TypeTarget$Usage.ordinal:()I
     165: iconst_2
     166: iastore
     167: goto          171
     170: astore_0
     171: getstatic     #14                 // Field $SwitchMap$org$jboss$jandex$TypeTarget$Usage:[I
     174: getstatic     #18                 // Field org/jboss/jandex/TypeTarget$Usage.METHOD_PARAMETER:Lorg/jboss/jandex/TypeTarget$Usage;
     177: invokevirtual #16                 // Method org/jboss/jandex/TypeTarget$Usage.ordinal:()I
     180: iconst_3
     181: iastore
     182: goto          186
     185: astore_0
     186: getstatic     #14                 // Field $SwitchMap$org$jboss$jandex$TypeTarget$Usage:[I
     189: getstatic     #19                 // Field org/jboss/jandex/TypeTarget$Usage.TYPE_PARAMETER:Lorg/jboss/jandex/TypeTarget$Usage;
     192: invokevirtual #16                 // Method org/jboss/jandex/TypeTarget$Usage.ordinal:()I
     195: iconst_4
     196: iastore
     197: goto          201
     200: astore_0
     201: getstatic     #14                 // Field $SwitchMap$org$jboss$jandex$TypeTarget$Usage:[I
     204: getstatic     #20                 // Field org/jboss/jandex/TypeTarget$Usage.TYPE_PARAMETER_BOUND:Lorg/jboss/jandex/TypeTarget$Usage;
     207: invokevirtual #16                 // Method org/jboss/jandex/TypeTarget$Usage.ordinal:()I
     210: iconst_5
     211: iastore
     212: goto          216
     215: astore_0
     216: getstatic     #14                 // Field $SwitchMap$org$jboss$jandex$TypeTarget$Usage:[I
     219: getstatic     #21                 // Field org/jboss/jandex/TypeTarget$Usage.THROWS:Lorg/jboss/jandex/TypeTarget$Usage;
     222: invokevirtual #16                 // Method org/jboss/jandex/TypeTarget$Usage.ordinal:()I
     225: bipush        6
     227: iastore
     228: goto          232
     231: astore_0
     232: return
    Exception table:
       from    to  target type
           9    20    23   Class java/lang/NoSuchFieldError
          24    35    38   Class java/lang/NoSuchFieldError
          39    50    53   Class java/lang/NoSuchFieldError
          54    65    68   Class java/lang/NoSuchFieldError
          69    80    83   Class java/lang/NoSuchFieldError
          84    96    99   Class java/lang/NoSuchFieldError
         100   112   115   Class java/lang/NoSuchFieldError
         116   128   131   Class java/lang/NoSuchFieldError
         141   152   155   Class java/lang/NoSuchFieldError
         156   167   170   Class java/lang/NoSuchFieldError
         171   182   185   Class java/lang/NoSuchFieldError
         186   197   200   Class java/lang/NoSuchFieldError
         201   212   215   Class java/lang/NoSuchFieldError
         216   228   231   Class java/lang/NoSuchFieldError
}
