Compiled from "IndexWriterV2.java"
class org.jboss.jandex.IndexWriterV2$ReferenceEntry {
  private int index;

  private boolean written;

  org.jboss.jandex.IndexWriterV2$ReferenceEntry(int);
    Code:
       0: aload_0
       1: invokespecial #3                  // Method java/lang/Object."<init>":()V
       4: aload_0
       5: iload_1
       6: putfield      #2                  // Field index:I
       9: return

  static int access$000(org.jboss.jandex.IndexWriterV2$ReferenceEntry);
    Code:
       0: aload_0
       1: getfield      #2                  // Field index:I
       4: ireturn

  static boolean access$100(org.jboss.jandex.IndexWriterV2$ReferenceEntry);
    Code:
       0: aload_0
       1: getfield      #1                  // Field written:Z
       4: ireturn

  static boolean access$102(org.jboss.jandex.IndexWriterV2$ReferenceEntry, boolean);
    Code:
       0: aload_0
       1: iload_1
       2: dup_x1
       3: putfield      #1                  // Field written:Z
       6: ireturn
}
