Compiled from "MockBackOff.java"
public class com.google.api.client.testing.util.MockBackOff implements com.google.api.client.util.BackOff {
  private long backOffMillis;

  private int maxTries;

  private int numTries;

  public com.google.api.client.testing.util.MockBackOff();
    Code:
       0: aload_0
       1: invokespecial #17                 // Method java/lang/Object."<init>":()V
       4: aload_0
       5: bipush        10
       7: putfield      #19                 // Field maxTries:I
      10: return

  public void reset() throws java.io.IOException;
    Code:
       0: aload_0
       1: iconst_0
       2: putfield      #26                 // Field numTries:I
       5: return

  public long nextBackOffMillis() throws java.io.IOException;
    Code:
       0: aload_0
       1: getfield      #26                 // Field numTries:I
       4: aload_0
       5: getfield      #19                 // Field maxTries:I
       8: if_icmpge     22
      11: aload_0
      12: getfield      #30                 // Field backOffMillis:J
      15: ldc2_w        #31                 // long -1l
      18: lcmp
      19: ifne          26
      22: ldc2_w        #31                 // long -1l
      25: lreturn
      26: aload_0
      27: dup
      28: getfield      #26                 // Field numTries:I
      31: iconst_1
      32: iadd
      33: putfield      #26                 // Field numTries:I
      36: aload_0
      37: getfield      #30                 // Field backOffMillis:J
      40: lreturn

  public com.google.api.client.testing.util.MockBackOff setBackOffMillis(long);
    Code:
       0: lload_1
       1: ldc2_w        #31                 // long -1l
       4: lcmp
       5: ifeq          14
       8: lload_1
       9: lconst_0
      10: lcmp
      11: iflt          18
      14: iconst_1
      15: goto          19
      18: iconst_0
      19: invokestatic  #40                 // Method com/google/api/client/util/Preconditions.checkArgument:(Z)V
      22: aload_0
      23: lload_1
      24: putfield      #30                 // Field backOffMillis:J
      27: aload_0
      28: areturn

  public com.google.api.client.testing.util.MockBackOff setMaxTries(int);
    Code:
       0: iload_1
       1: iflt          8
       4: iconst_1
       5: goto          9
       8: iconst_0
       9: invokestatic  #40                 // Method com/google/api/client/util/Preconditions.checkArgument:(Z)V
      12: aload_0
      13: iload_1
      14: putfield      #19                 // Field maxTries:I
      17: aload_0
      18: areturn

  public final int getMaxTries();
    Code:
       0: aload_0
       1: getfield      #26                 // Field numTries:I
       4: ireturn

  public final int getNumberOfTries();
    Code:
       0: aload_0
       1: getfield      #26                 // Field numTries:I
       4: ireturn
}
