Compiled from "TestableByteArrayOutputStream.java"
public class com.google.api.client.testing.util.TestableByteArrayOutputStream extends java.io.ByteArrayOutputStream {
  private boolean closed;

  public com.google.api.client.testing.util.TestableByteArrayOutputStream();
    Code:
       0: aload_0
       1: invokespecial #12                 // Method java/io/ByteArrayOutputStream."<init>":()V
       4: return

  public void close() throws java.io.IOException;
    Code:
       0: aload_0
       1: iconst_1
       2: putfield      #19                 // Field closed:Z
       5: return

  public final byte[] getBuffer();
    Code:
       0: aload_0
       1: getfield      #25                 // Field buf:[B
       4: areturn

  public final boolean isClosed();
    Code:
       0: aload_0
       1: getfield      #19                 // Field closed:Z
       4: ireturn
}
