Compiled from "MethodInterceptorFactory.java"
public final class org.jboss.invocation.MethodInterceptorFactory implements org.jboss.invocation.InterceptorFactory {
  private final org.jboss.invocation.InterceptorInstanceFactory instanceFactory;

  private final java.lang.reflect.Method interceptorMethod;

  private final boolean changeMethod;

  public org.jboss.invocation.MethodInterceptorFactory(org.jboss.invocation.InterceptorInstanceFactory, java.lang.reflect.Method, boolean);
    Code:
       0: aload_0
       1: invokespecial #18                 // Method java/lang/Object."<init>":()V
       4: aload_0
       5: aload_1
       6: putfield      #20                 // Field instanceFactory:Lorg/jboss/invocation/InterceptorInstanceFactory;
       9: aload_0
      10: aload_2
      11: putfield      #22                 // Field interceptorMethod:Ljava/lang/reflect/Method;
      14: aload_0
      15: iload_3
      16: putfield      #24                 // Field changeMethod:Z
      19: return

  public org.jboss.invocation.MethodInterceptorFactory(org.jboss.invocation.InterceptorInstanceFactory, java.lang.reflect.Method);
    Code:
       0: aload_0
       1: aload_1
       2: aload_2
       3: iconst_0
       4: invokespecial #29                 // Method "<init>":(Lorg/jboss/invocation/InterceptorInstanceFactory;Ljava/lang/reflect/Method;Z)V
       7: return

  public org.jboss.invocation.Interceptor create(org.jboss.invocation.InterceptorFactoryContext);
    Code:
       0: aload_1
       1: invokeinterface #37,  1           // InterfaceMethod org/jboss/invocation/InterceptorFactoryContext.getContextData:()Ljava/util/Map;
       6: astore_2
       7: aload_2
       8: aload_0
       9: invokeinterface #43,  2           // InterfaceMethod java/util/Map.containsKey:(Ljava/lang/Object;)Z
      14: ifeq          28
      17: aload_2
      18: aload_0
      19: invokeinterface #47,  2           // InterfaceMethod java/util/Map.get:(Ljava/lang/Object;)Ljava/lang/Object;
      24: checkcast     #49                 // class org/jboss/invocation/Interceptor
      27: areturn
      28: new           #51                 // class org/jboss/invocation/MethodInterceptor
      31: dup
      32: aload_0
      33: getfield      #20                 // Field instanceFactory:Lorg/jboss/invocation/InterceptorInstanceFactory;
      36: aload_1
      37: invokeinterface #57,  2           // InterfaceMethod org/jboss/invocation/InterceptorInstanceFactory.createInstance:(Lorg/jboss/invocation/InterceptorFactoryContext;)Ljava/lang/Object;
      42: aload_0
      43: getfield      #22                 // Field interceptorMethod:Ljava/lang/reflect/Method;
      46: aload_0
      47: getfield      #24                 // Field changeMethod:Z
      50: invokespecial #60                 // Method org/jboss/invocation/MethodInterceptor."<init>":(Ljava/lang/Object;Ljava/lang/reflect/Method;Z)V
      53: astore_3
      54: aload_2
      55: aload_0
      56: aload_3
      57: invokeinterface #64,  3           // InterfaceMethod java/util/Map.put:(Ljava/lang/Object;Ljava/lang/Object;)Ljava/lang/Object;
      62: pop
      63: aload_3
      64: areturn
}
