Compiled from "SimpleInterceptorFactoryContext.java"
public final class org.jboss.invocation.SimpleInterceptorFactoryContext implements org.jboss.invocation.InterceptorFactoryContext {
  private java.util.Map<java.lang.Object, java.lang.Object> contextData;

  public org.jboss.invocation.SimpleInterceptorFactoryContext();
    Code:
       0: aload_0
       1: invokespecial #14                 // Method java/lang/Object."<init>":()V
       4: return

  public java.util.Map<java.lang.Object, java.lang.Object> getContextData();
    Code:
       0: aload_0
       1: getfield      #20                 // Field contextData:Ljava/util/Map;
       4: astore_1
       5: aload_1
       6: ifnonnull     24
       9: aload_0
      10: new           #22                 // class java/util/HashMap
      13: dup
      14: invokespecial #23                 // Method java/util/HashMap."<init>":()V
      17: dup_x1
      18: putfield      #20                 // Field contextData:Ljava/util/Map;
      21: goto          25
      24: aload_1
      25: areturn
}
