Compiled from "AssertionSpecValidator.java"
public class org.opensaml.saml1.core.validator.AssertionSpecValidator implements org.opensaml.xml.validation.Validator<org.opensaml.saml1.core.Assertion> {
  public org.opensaml.saml1.core.validator.AssertionSpecValidator();
    Code:
       0: aload_0
       1: invokespecial #1                  // Method java/lang/Object."<init>":()V
       4: return

  public void validate(org.opensaml.saml1.core.Assertion) throws org.opensaml.xml.validation.ValidationException;
    Code:
       0: aload_0
       1: aload_1
       2: invokevirtual #2                  // Method validateDoNotCache:(Lorg/opensaml/saml1/core/Assertion;)V
       5: return

  protected void validateDoNotCache(org.opensaml.saml1.core.Assertion) throws org.opensaml.xml.validation.ValidationException;
    Code:
       0: aload_1
       1: invokeinterface #3,  1            // InterfaceMethod org/opensaml/saml1/core/Assertion.getMinorVersion:()I
       6: ifne          73
       9: aload_1
      10: invokeinterface #4,  1            // InterfaceMethod org/opensaml/saml1/core/Assertion.getConditions:()Lorg/opensaml/saml1/core/Conditions;
      15: astore_2
      16: aload_2
      17: ifnull        73
      20: aload_2
      21: invokeinterface #5,  1            // InterfaceMethod org/opensaml/saml1/core/Conditions.getConditions:()Ljava/util/List;
      26: invokeinterface #6,  1            // InterfaceMethod java/util/List.iterator:()Ljava/util/Iterator;
      31: astore_3
      32: aload_3
      33: invokeinterface #7,  1            // InterfaceMethod java/util/Iterator.hasNext:()Z
      38: ifeq          73
      41: aload_3
      42: invokeinterface #8,  1            // InterfaceMethod java/util/Iterator.next:()Ljava/lang/Object;
      47: checkcast     #9                  // class org/opensaml/saml1/core/Condition
      50: astore        4
      52: aload         4
      54: instanceof    #10                 // class org/opensaml/saml1/core/DoNotCacheCondition
      57: ifeq          70
      60: new           #11                 // class org/opensaml/xml/validation/ValidationException
      63: dup
      64: ldc           #12                 // String DoNotCacheCondition not valid in SAML1.0
      66: invokespecial #13                 // Method org/opensaml/xml/validation/ValidationException."<init>":(Ljava/lang/String;)V
      69: athrow
      70: goto          32
      73: return

  public void validate(org.opensaml.xml.XMLObject) throws org.opensaml.xml.validation.ValidationException;
    Code:
       0: aload_0
       1: aload_1
       2: checkcast     #14                 // class org/opensaml/saml1/core/Assertion
       5: invokevirtual #15                 // Method validate:(Lorg/opensaml/saml1/core/Assertion;)V
       8: return
}
