Compiled from "ConfigSourceSymbolProcessor.kt"
public final class ru.tinkoff.kora.config.ksp.processor.ConfigSourceSymbolProcessor extends ru.tinkoff.kora.ksp.common.BaseSymbolProcessor {
  private final com.google.devtools.ksp.processing.CodeGenerator codeGenerator;

  public ru.tinkoff.kora.config.ksp.processor.ConfigSourceSymbolProcessor(com.google.devtools.ksp.processing.SymbolProcessorEnvironment);
    Code:
       0: aload_1
       1: ldc           #9                  // String environment
       3: invokestatic  #15                 // Method kotlin/jvm/internal/Intrinsics.checkNotNullParameter:(Ljava/lang/Object;Ljava/lang/String;)V
       6: aload_0
       7: aload_1
       8: invokespecial #17                 // Method ru/tinkoff/kora/ksp/common/BaseSymbolProcessor."<init>":(Lcom/google/devtools/ksp/processing/SymbolProcessorEnvironment;)V
      11: aload_0
      12: aload_1
      13: invokevirtual #23                 // Method com/google/devtools/ksp/processing/SymbolProcessorEnvironment.getCodeGenerator:()Lcom/google/devtools/ksp/processing/CodeGenerator;
      16: putfield      #27                 // Field codeGenerator:Lcom/google/devtools/ksp/processing/CodeGenerator;
      19: return

  public java.util.List<com.google.devtools.ksp.symbol.KSAnnotated> processRound(com.google.devtools.ksp.processing.Resolver);
    Code:
       0: aload_1
       1: ldc           #35                 // String resolver
       3: invokestatic  #15                 // Method kotlin/jvm/internal/Intrinsics.checkNotNullParameter:(Ljava/lang/Object;Ljava/lang/String;)V
       6: aload_1
       7: ldc           #37                 // class ru/tinkoff/kora/config/common/ConfigSource
       9: invokestatic  #43                 // Method kotlin/jvm/internal/Reflection.getOrCreateKotlinClass:(Ljava/lang/Class;)Lkotlin/reflect/KClass;
      12: invokeinterface #49,  1           // InterfaceMethod kotlin/reflect/KClass.getQualifiedName:()Ljava/lang/String;
      17: dup
      18: invokestatic  #53                 // Method kotlin/jvm/internal/Intrinsics.checkNotNull:(Ljava/lang/Object;)V
      21: iconst_0
      22: iconst_2
      23: aconst_null
      24: invokestatic  #59                 // InterfaceMethod com/google/devtools/ksp/processing/Resolver.getSymbolsWithAnnotation$default:(Lcom/google/devtools/ksp/processing/Resolver;Ljava/lang/String;ZILjava/lang/Object;)Lkotlin/sequences/Sequence;
      27: invokestatic  #65                 // Method kotlin/sequences/SequencesKt.toList:(Lkotlin/sequences/Sequence;)Ljava/util/List;
      30: astore_2
      31: aload_2
      32: checkcast     #67                 // class java/lang/Iterable
      35: astore_3
      36: iconst_0
      37: istore        4
      39: aload_3
      40: invokeinterface #71,  1           // InterfaceMethod java/lang/Iterable.iterator:()Ljava/util/Iterator;
      45: astore        5
      47: aload         5
      49: invokeinterface #77,  1           // InterfaceMethod java/util/Iterator.hasNext:()Z
      54: ifeq          98
      57: aload         5
      59: invokeinterface #81,  1           // InterfaceMethod java/util/Iterator.next:()Ljava/lang/Object;
      64: astore        6
      66: aload         6
      68: checkcast     #83                 // class com/google/devtools/ksp/symbol/KSAnnotated
      71: astore        7
      73: iconst_0
      74: istore        8
      76: aload         7
      78: new           #85                 // class ru/tinkoff/kora/config/ksp/processor/ConfigSourceSymbolProcessor$processRound$1$1
      81: dup
      82: aload_0
      83: invokespecial #88                 // Method ru/tinkoff/kora/config/ksp/processor/ConfigSourceSymbolProcessor$processRound$1$1."<init>":(Lru/tinkoff/kora/config/ksp/processor/ConfigSourceSymbolProcessor;)V
      86: checkcast     #90                 // class kotlin/jvm/functions/Function1
      89: invokestatic  #96                 // Method ru/tinkoff/kora/ksp/common/KspCommonUtilsKt.visitClass:(Lcom/google/devtools/ksp/symbol/KSAnnotated;Lkotlin/jvm/functions/Function1;)Ljava/lang/Object;
      92: pop
      93: nop
      94: nop
      95: goto          47
      98: nop
      99: invokestatic  #102                // Method kotlin/collections/CollectionsKt.emptyList:()Ljava/util/List;
     102: areturn

  public static final com.google.devtools.ksp.processing.CodeGenerator access$getCodeGenerator$p(ru.tinkoff.kora.config.ksp.processor.ConfigSourceSymbolProcessor);
    Code:
       0: aload_0
       1: getfield      #27                 // Field codeGenerator:Lcom/google/devtools/ksp/processing/CodeGenerator;
       4: areturn
}
