Compiled from "ProducerConnectionContext.java"
public class org.hawkular.bus.common.producer.ProducerConnectionContext extends org.hawkular.bus.common.ConnectionContext {
  private javax.jms.MessageProducer producer;

  public org.hawkular.bus.common.producer.ProducerConnectionContext();
    Code:
       0: aload_0
       1: invokespecial #1                  // Method org/hawkular/bus/common/ConnectionContext."<init>":()V
       4: return

  public javax.jms.MessageProducer getMessageProducer();
    Code:
       0: aload_0
       1: getfield      #2                  // Field producer:Ljavax/jms/MessageProducer;
       4: areturn

  public void setMessageProducer(javax.jms.MessageProducer);
    Code:
       0: aload_0
       1: aload_1
       2: putfield      #2                  // Field producer:Ljavax/jms/MessageProducer;
       5: return

  public void close() throws java.io.IOException;
    Code:
       0: aload_0
       1: getfield      #2                  // Field producer:Ljavax/jms/MessageProducer;
       4: ifnull        29
       7: aload_0
       8: getfield      #2                  // Field producer:Ljavax/jms/MessageProducer;
      11: invokeinterface #3,  1            // InterfaceMethod javax/jms/MessageProducer.close:()V
      16: goto          29
      19: astore_1
      20: new           #5                  // class java/io/IOException
      23: dup
      24: aload_1
      25: invokespecial #6                  // Method java/io/IOException."<init>":(Ljava/lang/Throwable;)V
      28: athrow
      29: aload_0
      30: invokespecial #7                  // Method org/hawkular/bus/common/ConnectionContext.close:()V
      33: return
    Exception table:
       from    to  target type
           7    16    19   Class javax/jms/JMSException
}
