Compiled from "Compression.java"
public class com.jcraft.jsch.jcraft.Compression implements com.jcraft.jsch.Compression {
  private static final int BUF_SIZE;

  private final int buffer_margin;

  private int type;

  private com.jcraft.jzlib.ZStream stream;

  private byte[] tmpbuf;

  private byte[] inflated_buf;

  public com.jcraft.jsch.jcraft.Compression();
    Code:
       0: aload_0
       1: invokespecial #1                  // Method java/lang/Object."<init>":()V
       4: aload_0
       5: bipush        52
       7: putfield      #2                  // Field buffer_margin:I
      10: aload_0
      11: sipush        4096
      14: newarray       byte
      16: putfield      #3                  // Field tmpbuf:[B
      19: aload_0
      20: new           #4                  // class com/jcraft/jzlib/ZStream
      23: dup
      24: invokespecial #5                  // Method com/jcraft/jzlib/ZStream."<init>":()V
      27: putfield      #6                  // Field stream:Lcom/jcraft/jzlib/ZStream;
      30: return

  public void init(int, int);
    Code:
       0: iload_1
       1: iconst_1
       2: if_icmpne     22
       5: aload_0
       6: getfield      #6                  // Field stream:Lcom/jcraft/jzlib/ZStream;
       9: iload_2
      10: invokevirtual #7                  // Method com/jcraft/jzlib/ZStream.deflateInit:(I)I
      13: pop
      14: aload_0
      15: iconst_1
      16: putfield      #8                  // Field type:I
      19: goto          48
      22: iload_1
      23: ifne          48
      26: aload_0
      27: getfield      #6                  // Field stream:Lcom/jcraft/jzlib/ZStream;
      30: invokevirtual #9                  // Method com/jcraft/jzlib/ZStream.inflateInit:()I
      33: pop
      34: aload_0
      35: sipush        4096
      38: newarray       byte
      40: putfield      #10                 // Field inflated_buf:[B
      43: aload_0
      44: iconst_0
      45: putfield      #8                  // Field type:I
      48: return

  public byte[] compress(byte[], int, int[]);
    Code:
       0: aload_0
       1: getfield      #6                  // Field stream:Lcom/jcraft/jzlib/ZStream;
       4: aload_1
       5: putfield      #11                 // Field com/jcraft/jzlib/ZStream.next_in:[B
       8: aload_0
       9: getfield      #6                  // Field stream:Lcom/jcraft/jzlib/ZStream;
      12: iload_2
      13: putfield      #12                 // Field com/jcraft/jzlib/ZStream.next_in_index:I
      16: aload_0
      17: getfield      #6                  // Field stream:Lcom/jcraft/jzlib/ZStream;
      20: aload_3
      21: iconst_0
      22: iaload
      23: iload_2
      24: isub
      25: putfield      #13                 // Field com/jcraft/jzlib/ZStream.avail_in:I
      28: iload_2
      29: istore        5
      31: aload_1
      32: astore        6
      34: iconst_0
      35: istore        7
      37: aload_0
      38: getfield      #6                  // Field stream:Lcom/jcraft/jzlib/ZStream;
      41: aload_0
      42: getfield      #3                  // Field tmpbuf:[B
      45: putfield      #14                 // Field com/jcraft/jzlib/ZStream.next_out:[B
      48: aload_0
      49: getfield      #6                  // Field stream:Lcom/jcraft/jzlib/ZStream;
      52: iconst_0
      53: putfield      #15                 // Field com/jcraft/jzlib/ZStream.next_out_index:I
      56: aload_0
      57: getfield      #6                  // Field stream:Lcom/jcraft/jzlib/ZStream;
      60: sipush        4096
      63: putfield      #16                 // Field com/jcraft/jzlib/ZStream.avail_out:I
      66: aload_0
      67: getfield      #6                  // Field stream:Lcom/jcraft/jzlib/ZStream;
      70: iconst_1
      71: invokevirtual #17                 // Method com/jcraft/jzlib/ZStream.deflate:(I)I
      74: istore        4
      76: iload         4
      78: lookupswitch  { // 1
                     0: 96
               default: 177
          }
      96: sipush        4096
      99: aload_0
     100: getfield      #6                  // Field stream:Lcom/jcraft/jzlib/ZStream;
     103: getfield      #16                 // Field com/jcraft/jzlib/ZStream.avail_out:I
     106: isub
     107: istore        7
     109: aload         6
     111: arraylength
     112: iload         5
     114: iload         7
     116: iadd
     117: bipush        52
     119: iadd
     120: if_icmpge     153
     123: iload         5
     125: iload         7
     127: iadd
     128: bipush        52
     130: iadd
     131: iconst_2
     132: imul
     133: newarray       byte
     135: astore        8
     137: aload         6
     139: iconst_0
     140: aload         8
     142: iconst_0
     143: aload         6
     145: arraylength
     146: invokestatic  #18                 // Method java/lang/System.arraycopy:(Ljava/lang/Object;ILjava/lang/Object;II)V
     149: aload         8
     151: astore        6
     153: aload_0
     154: getfield      #3                  // Field tmpbuf:[B
     157: iconst_0
     158: aload         6
     160: iload         5
     162: iload         7
     164: invokestatic  #18                 // Method java/lang/System.arraycopy:(Ljava/lang/Object;ILjava/lang/Object;II)V
     167: iload         5
     169: iload         7
     171: iadd
     172: istore        5
     174: goto          203
     177: getstatic     #19                 // Field java/lang/System.err:Ljava/io/PrintStream;
     180: new           #20                 // class java/lang/StringBuilder
     183: dup
     184: invokespecial #21                 // Method java/lang/StringBuilder."<init>":()V
     187: ldc           #22                 // String compress: deflate returnd
     189: invokevirtual #23                 // Method java/lang/StringBuilder.append:(Ljava/lang/String;)Ljava/lang/StringBuilder;
     192: iload         4
     194: invokevirtual #24                 // Method java/lang/StringBuilder.append:(I)Ljava/lang/StringBuilder;
     197: invokevirtual #25                 // Method java/lang/StringBuilder.toString:()Ljava/lang/String;
     200: invokevirtual #26                 // Method java/io/PrintStream.println:(Ljava/lang/String;)V
     203: aload_0
     204: getfield      #6                  // Field stream:Lcom/jcraft/jzlib/ZStream;
     207: getfield      #16                 // Field com/jcraft/jzlib/ZStream.avail_out:I
     210: ifeq          37
     213: aload_3
     214: iconst_0
     215: iload         5
     217: iastore
     218: aload         6
     220: areturn

  public byte[] uncompress(byte[], int, int[]);
    Code:
       0: iconst_0
       1: istore        4
       3: aload_0
       4: getfield      #6                  // Field stream:Lcom/jcraft/jzlib/ZStream;
       7: aload_1
       8: putfield      #11                 // Field com/jcraft/jzlib/ZStream.next_in:[B
      11: aload_0
      12: getfield      #6                  // Field stream:Lcom/jcraft/jzlib/ZStream;
      15: iload_2
      16: putfield      #12                 // Field com/jcraft/jzlib/ZStream.next_in_index:I
      19: aload_0
      20: getfield      #6                  // Field stream:Lcom/jcraft/jzlib/ZStream;
      23: aload_3
      24: iconst_0
      25: iaload
      26: putfield      #13                 // Field com/jcraft/jzlib/ZStream.avail_in:I
      29: aload_0
      30: getfield      #6                  // Field stream:Lcom/jcraft/jzlib/ZStream;
      33: aload_0
      34: getfield      #3                  // Field tmpbuf:[B
      37: putfield      #14                 // Field com/jcraft/jzlib/ZStream.next_out:[B
      40: aload_0
      41: getfield      #6                  // Field stream:Lcom/jcraft/jzlib/ZStream;
      44: iconst_0
      45: putfield      #15                 // Field com/jcraft/jzlib/ZStream.next_out_index:I
      48: aload_0
      49: getfield      #6                  // Field stream:Lcom/jcraft/jzlib/ZStream;
      52: sipush        4096
      55: putfield      #16                 // Field com/jcraft/jzlib/ZStream.avail_out:I
      58: aload_0
      59: getfield      #6                  // Field stream:Lcom/jcraft/jzlib/ZStream;
      62: iconst_1
      63: invokevirtual #27                 // Method com/jcraft/jzlib/ZStream.inflate:(I)I
      66: istore        5
      68: iload         5
      70: lookupswitch  { // 2
                    -5: 236
                     0: 96
               default: 300
          }
      96: aload_0
      97: getfield      #10                 // Field inflated_buf:[B
     100: arraylength
     101: iload         4
     103: sipush        4096
     106: iadd
     107: aload_0
     108: getfield      #6                  // Field stream:Lcom/jcraft/jzlib/ZStream;
     111: getfield      #16                 // Field com/jcraft/jzlib/ZStream.avail_out:I
     114: isub
     115: if_icmpge     187
     118: aload_0
     119: getfield      #10                 // Field inflated_buf:[B
     122: arraylength
     123: iconst_2
     124: imul
     125: istore        6
     127: iload         6
     129: iload         4
     131: sipush        4096
     134: iadd
     135: aload_0
     136: getfield      #6                  // Field stream:Lcom/jcraft/jzlib/ZStream;
     139: getfield      #16                 // Field com/jcraft/jzlib/ZStream.avail_out:I
     142: isub
     143: if_icmpge     162
     146: iload         4
     148: sipush        4096
     151: iadd
     152: aload_0
     153: getfield      #6                  // Field stream:Lcom/jcraft/jzlib/ZStream;
     156: getfield      #16                 // Field com/jcraft/jzlib/ZStream.avail_out:I
     159: isub
     160: istore        6
     162: iload         6
     164: newarray       byte
     166: astore        7
     168: aload_0
     169: getfield      #10                 // Field inflated_buf:[B
     172: iconst_0
     173: aload         7
     175: iconst_0
     176: iload         4
     178: invokestatic  #18                 // Method java/lang/System.arraycopy:(Ljava/lang/Object;ILjava/lang/Object;II)V
     181: aload_0
     182: aload         7
     184: putfield      #10                 // Field inflated_buf:[B
     187: aload_0
     188: getfield      #3                  // Field tmpbuf:[B
     191: iconst_0
     192: aload_0
     193: getfield      #10                 // Field inflated_buf:[B
     196: iload         4
     198: sipush        4096
     201: aload_0
     202: getfield      #6                  // Field stream:Lcom/jcraft/jzlib/ZStream;
     205: getfield      #16                 // Field com/jcraft/jzlib/ZStream.avail_out:I
     208: isub
     209: invokestatic  #18                 // Method java/lang/System.arraycopy:(Ljava/lang/Object;ILjava/lang/Object;II)V
     212: iload         4
     214: sipush        4096
     217: aload_0
     218: getfield      #6                  // Field stream:Lcom/jcraft/jzlib/ZStream;
     221: getfield      #16                 // Field com/jcraft/jzlib/ZStream.avail_out:I
     224: isub
     225: iadd
     226: istore        4
     228: aload_3
     229: iconst_0
     230: iload         4
     232: iastore
     233: goto          328
     236: iload         4
     238: aload_1
     239: arraylength
     240: iload_2
     241: isub
     242: if_icmple     281
     245: iload         4
     247: iload_2
     248: iadd
     249: newarray       byte
     251: astore        6
     253: aload_1
     254: iconst_0
     255: aload         6
     257: iconst_0
     258: iload_2
     259: invokestatic  #18                 // Method java/lang/System.arraycopy:(Ljava/lang/Object;ILjava/lang/Object;II)V
     262: aload_0
     263: getfield      #10                 // Field inflated_buf:[B
     266: iconst_0
     267: aload         6
     269: iload_2
     270: iload         4
     272: invokestatic  #18                 // Method java/lang/System.arraycopy:(Ljava/lang/Object;ILjava/lang/Object;II)V
     275: aload         6
     277: astore_1
     278: goto          293
     281: aload_0
     282: getfield      #10                 // Field inflated_buf:[B
     285: iconst_0
     286: aload_1
     287: iload_2
     288: iload         4
     290: invokestatic  #18                 // Method java/lang/System.arraycopy:(Ljava/lang/Object;ILjava/lang/Object;II)V
     293: aload_3
     294: iconst_0
     295: iload         4
     297: iastore
     298: aload_1
     299: areturn
     300: getstatic     #19                 // Field java/lang/System.err:Ljava/io/PrintStream;
     303: new           #20                 // class java/lang/StringBuilder
     306: dup
     307: invokespecial #21                 // Method java/lang/StringBuilder."<init>":()V
     310: ldc           #28                 // String uncompress: inflate returnd
     312: invokevirtual #23                 // Method java/lang/StringBuilder.append:(Ljava/lang/String;)Ljava/lang/StringBuilder;
     315: iload         5
     317: invokevirtual #24                 // Method java/lang/StringBuilder.append:(I)Ljava/lang/StringBuilder;
     320: invokevirtual #25                 // Method java/lang/StringBuilder.toString:()Ljava/lang/String;
     323: invokevirtual #26                 // Method java/io/PrintStream.println:(Ljava/lang/String;)V
     326: aconst_null
     327: areturn
     328: goto          29
}
