Compiled from "ThreadStackFactoryImpl.java"
public class org.aspectj.runtime.internal.cflowstack.ThreadStackFactoryImpl implements org.aspectj.runtime.internal.cflowstack.ThreadStackFactory {
  public org.aspectj.runtime.internal.cflowstack.ThreadStackFactoryImpl();
    Code:
       0: aload_0
       1: invokespecial #1                  // Method java/lang/Object."<init>":()V
       4: return

  public org.aspectj.runtime.internal.cflowstack.ThreadStack getNewThreadStack();
    Code:
       0: new           #2                  // class org/aspectj/runtime/internal/cflowstack/ThreadStackFactoryImpl$ThreadStackImpl
       3: dup
       4: aconst_null
       5: invokespecial #3                  // Method org/aspectj/runtime/internal/cflowstack/ThreadStackFactoryImpl$ThreadStackImpl."<init>":(Lorg/aspectj/runtime/internal/cflowstack/ThreadStackFactoryImpl$1;)V
       8: areturn

  public org.aspectj.runtime.internal.cflowstack.ThreadCounter getNewThreadCounter();
    Code:
       0: new           #4                  // class org/aspectj/runtime/internal/cflowstack/ThreadStackFactoryImpl$ThreadCounterImpl
       3: dup
       4: aconst_null
       5: invokespecial #5                  // Method org/aspectj/runtime/internal/cflowstack/ThreadStackFactoryImpl$ThreadCounterImpl."<init>":(Lorg/aspectj/runtime/internal/cflowstack/ThreadStackFactoryImpl$1;)V
       8: areturn
}
