Compiled from "AbstractMultiset.java"
class org.sonar.api.internal.google.common.collect.AbstractMultiset$ElementSet extends org.sonar.api.internal.google.common.collect.Multisets$ElementSet<E> {
  final org.sonar.api.internal.google.common.collect.AbstractMultiset this$0;

  org.sonar.api.internal.google.common.collect.AbstractMultiset$ElementSet(org.sonar.api.internal.google.common.collect.AbstractMultiset);
    Code:
       0: aload_0
       1: aload_1
       2: putfield      #17                 // Field this$0:Lorg/sonar/api/internal/google/common/collect/AbstractMultiset;
       5: aload_0
       6: invokespecial #20                 // Method org/sonar/api/internal/google/common/collect/Multisets$ElementSet."<init>":()V
       9: return

  org.sonar.api.internal.google.common.collect.Multiset<E> multiset();
    Code:
       0: aload_0
       1: getfield      #17                 // Field this$0:Lorg/sonar/api/internal/google/common/collect/AbstractMultiset;
       4: areturn
}
