Compiled from "DenseImmutableTable.java"
final class org.sonar.api.internal.google.common.collect.DenseImmutableTable$RowMap extends org.sonar.api.internal.google.common.collect.DenseImmutableTable$ImmutableArrayMap<R, java.util.Map<C, V>> {
  final org.sonar.api.internal.google.common.collect.DenseImmutableTable this$0;

  private org.sonar.api.internal.google.common.collect.DenseImmutableTable$RowMap(org.sonar.api.internal.google.common.collect.DenseImmutableTable);
    Code:
       0: aload_0
       1: aload_1
       2: putfield      #21                 // Field this$0:Lorg/sonar/api/internal/google/common/collect/DenseImmutableTable;
       5: aload_0
       6: aload_1
       7: invokestatic  #25                 // Method org/sonar/api/internal/google/common/collect/DenseImmutableTable.access$200:(Lorg/sonar/api/internal/google/common/collect/DenseImmutableTable;)[I
      10: arraylength
      11: invokespecial #28                 // Method org/sonar/api/internal/google/common/collect/DenseImmutableTable$ImmutableArrayMap."<init>":(I)V
      14: return

  org.sonar.api.internal.google.common.collect.ImmutableMap<R, java.lang.Integer> keyToIndex();
    Code:
       0: aload_0
       1: getfield      #21                 // Field this$0:Lorg/sonar/api/internal/google/common/collect/DenseImmutableTable;
       4: invokestatic  #37                 // Method org/sonar/api/internal/google/common/collect/DenseImmutableTable.access$600:(Lorg/sonar/api/internal/google/common/collect/DenseImmutableTable;)Lorg/sonar/api/internal/google/common/collect/ImmutableMap;
       7: areturn

  java.util.Map<C, V> getValue(int);
    Code:
       0: new           #14                 // class org/sonar/api/internal/google/common/collect/DenseImmutableTable$Row
       3: dup
       4: aload_0
       5: getfield      #21                 // Field this$0:Lorg/sonar/api/internal/google/common/collect/DenseImmutableTable;
       8: iload_1
       9: invokespecial #42                 // Method org/sonar/api/internal/google/common/collect/DenseImmutableTable$Row."<init>":(Lorg/sonar/api/internal/google/common/collect/DenseImmutableTable;I)V
      12: areturn

  boolean isPartialView();
    Code:
       0: iconst_0
       1: ireturn

  java.lang.Object getValue(int);
    Code:
       0: aload_0
       1: iload_1
       2: invokevirtual #49                 // Method getValue:(I)Ljava/util/Map;
       5: areturn

  org.sonar.api.internal.google.common.collect.DenseImmutableTable$RowMap(org.sonar.api.internal.google.common.collect.DenseImmutableTable, org.sonar.api.internal.google.common.collect.DenseImmutableTable$1);
    Code:
       0: aload_0
       1: aload_1
       2: invokespecial #53                 // Method "<init>":(Lorg/sonar/api/internal/google/common/collect/DenseImmutableTable;)V
       5: return
}
