Compiled from "EmptyContiguousSet.java"
final class org.sonar.api.internal.google.common.collect.EmptyContiguousSet$SerializedForm<C extends java.lang.Comparable> implements java.io.Serializable {
  private final org.sonar.api.internal.google.common.collect.DiscreteDomain<C> domain;

  private static final long serialVersionUID;

  private org.sonar.api.internal.google.common.collect.EmptyContiguousSet$SerializedForm(org.sonar.api.internal.google.common.collect.DiscreteDomain<C>);
    Code:
       0: aload_0
       1: invokespecial #28                 // Method java/lang/Object."<init>":()V
       4: aload_0
       5: aload_1
       6: putfield      #30                 // Field domain:Lorg/sonar/api/internal/google/common/collect/DiscreteDomain;
       9: return

  private java.lang.Object readResolve();
    Code:
       0: new           #13                 // class org/sonar/api/internal/google/common/collect/EmptyContiguousSet
       3: dup
       4: aload_0
       5: getfield      #30                 // Field domain:Lorg/sonar/api/internal/google/common/collect/DiscreteDomain;
       8: invokespecial #37                 // Method org/sonar/api/internal/google/common/collect/EmptyContiguousSet."<init>":(Lorg/sonar/api/internal/google/common/collect/DiscreteDomain;)V
      11: areturn

  org.sonar.api.internal.google.common.collect.EmptyContiguousSet$SerializedForm(org.sonar.api.internal.google.common.collect.DiscreteDomain, org.sonar.api.internal.google.common.collect.EmptyContiguousSet$1);
    Code:
       0: aload_0
       1: aload_1
       2: invokespecial #39                 // Method "<init>":(Lorg/sonar/api/internal/google/common/collect/DiscreteDomain;)V
       5: return
}
