Compiled from "Multimaps.java"
class org.sonar.api.internal.google.common.collect.Multimaps$UnmodifiableMultimap$1 implements org.sonar.api.internal.google.common.base.Function<java.util.Collection<V>, java.util.Collection<V>> {
  final org.sonar.api.internal.google.common.collect.Multimaps$UnmodifiableMultimap this$0;

  org.sonar.api.internal.google.common.collect.Multimaps$UnmodifiableMultimap$1(org.sonar.api.internal.google.common.collect.Multimaps$UnmodifiableMultimap);
    Code:
       0: aload_0
       1: aload_1
       2: putfield      #22                 // Field this$0:Lorg/sonar/api/internal/google/common/collect/Multimaps$UnmodifiableMultimap;
       5: aload_0
       6: invokespecial #25                 // Method java/lang/Object."<init>":()V
       9: return

  public java.util.Collection<V> apply(java.util.Collection<V>);
    Code:
       0: aload_1
       1: invokestatic  #33                 // Method org/sonar/api/internal/google/common/collect/Multimaps.access$000:(Ljava/util/Collection;)Ljava/util/Collection;
       4: areturn

  public java.lang.Object apply(java.lang.Object);
    Code:
       0: aload_0
       1: aload_1
       2: checkcast     #39                 // class java/util/Collection
       5: invokevirtual #41                 // Method apply:(Ljava/util/Collection;)Ljava/util/Collection;
       8: areturn
}
