Compiled from "RegularImmutableSortedMap.java"
class org.sonar.api.internal.google.common.collect.RegularImmutableSortedMap$EntrySet$1 extends org.sonar.api.internal.google.common.collect.ImmutableAsList<java.util.Map$Entry<K, V>> {
  private final org.sonar.api.internal.google.common.collect.ImmutableList<K> keyList;

  final org.sonar.api.internal.google.common.collect.RegularImmutableSortedMap$EntrySet this$1;

  org.sonar.api.internal.google.common.collect.RegularImmutableSortedMap$EntrySet$1(org.sonar.api.internal.google.common.collect.RegularImmutableSortedMap$EntrySet);
    Code:
       0: aload_0
       1: aload_1
       2: putfield      #28                 // Field this$1:Lorg/sonar/api/internal/google/common/collect/RegularImmutableSortedMap$EntrySet;
       5: aload_0
       6: invokespecial #31                 // Method org/sonar/api/internal/google/common/collect/ImmutableAsList."<init>":()V
       9: aload_0
      10: aload_0
      11: getfield      #28                 // Field this$1:Lorg/sonar/api/internal/google/common/collect/RegularImmutableSortedMap$EntrySet;
      14: getfield      #35                 // Field org/sonar/api/internal/google/common/collect/RegularImmutableSortedMap$EntrySet.this$0:Lorg/sonar/api/internal/google/common/collect/RegularImmutableSortedMap;
      17: invokevirtual #39                 // Method org/sonar/api/internal/google/common/collect/RegularImmutableSortedMap.keySet:()Lorg/sonar/api/internal/google/common/collect/ImmutableSortedSet;
      20: invokevirtual #44                 // Method org/sonar/api/internal/google/common/collect/ImmutableSortedSet.asList:()Lorg/sonar/api/internal/google/common/collect/ImmutableList;
      23: putfield      #46                 // Field keyList:Lorg/sonar/api/internal/google/common/collect/ImmutableList;
      26: return

  public java.util.Map$Entry<K, V> get(int);
    Code:
       0: aload_0
       1: getfield      #46                 // Field keyList:Lorg/sonar/api/internal/google/common/collect/ImmutableList;
       4: iload_1
       5: invokevirtual #56                 // Method org/sonar/api/internal/google/common/collect/ImmutableList.get:(I)Ljava/lang/Object;
       8: aload_0
       9: getfield      #28                 // Field this$1:Lorg/sonar/api/internal/google/common/collect/RegularImmutableSortedMap$EntrySet;
      12: getfield      #35                 // Field org/sonar/api/internal/google/common/collect/RegularImmutableSortedMap$EntrySet.this$0:Lorg/sonar/api/internal/google/common/collect/RegularImmutableSortedMap;
      15: invokestatic  #60                 // Method org/sonar/api/internal/google/common/collect/RegularImmutableSortedMap.access$100:(Lorg/sonar/api/internal/google/common/collect/RegularImmutableSortedMap;)Lorg/sonar/api/internal/google/common/collect/ImmutableList;
      18: iload_1
      19: invokevirtual #56                 // Method org/sonar/api/internal/google/common/collect/ImmutableList.get:(I)Ljava/lang/Object;
      22: invokestatic  #66                 // Method org/sonar/api/internal/google/common/collect/Maps.immutableEntry:(Ljava/lang/Object;Ljava/lang/Object;)Ljava/util/Map$Entry;
      25: areturn

  org.sonar.api.internal.google.common.collect.ImmutableCollection<java.util.Map$Entry<K, V>> delegateCollection();
    Code:
       0: aload_0
       1: getfield      #28                 // Field this$1:Lorg/sonar/api/internal/google/common/collect/RegularImmutableSortedMap$EntrySet;
       4: areturn

  public java.lang.Object get(int);
    Code:
       0: aload_0
       1: iload_1
       2: invokevirtual #72                 // Method get:(I)Ljava/util/Map$Entry;
       5: areturn
}
