Compiled from "PlaceholderForType.java"
public class io.dekorate.deps.jackson.databind.type.PlaceholderForType extends io.dekorate.deps.jackson.databind.type.TypeBase {
  private static final long serialVersionUID;

  protected final int _ordinal;

  protected io.dekorate.deps.jackson.databind.JavaType _actualType;

  public io.dekorate.deps.jackson.databind.type.PlaceholderForType(int);
    Code:
       0: aload_0
       1: ldc           #17                 // class java/lang/Object
       3: invokestatic  #23                 // Method io/dekorate/deps/jackson/databind/type/TypeBindings.emptyBindings:()Lio/dekorate/deps/jackson/databind/type/TypeBindings;
       6: invokestatic  #29                 // Method io/dekorate/deps/jackson/databind/type/TypeFactory.unknownType:()Lio/dekorate/deps/jackson/databind/JavaType;
       9: aconst_null
      10: iconst_1
      11: aconst_null
      12: aconst_null
      13: iconst_0
      14: invokespecial #32                 // Method io/dekorate/deps/jackson/databind/type/TypeBase."<init>":(Ljava/lang/Class;Lio/dekorate/deps/jackson/databind/type/TypeBindings;Lio/dekorate/deps/jackson/databind/JavaType;[Lio/dekorate/deps/jackson/databind/JavaType;ILjava/lang/Object;Ljava/lang/Object;Z)V
      17: aload_0
      18: iload_1
      19: putfield      #34                 // Field _ordinal:I
      22: return

  public io.dekorate.deps.jackson.databind.JavaType actualType();
    Code:
       0: aload_0
       1: getfield      #40                 // Field _actualType:Lio/dekorate/deps/jackson/databind/JavaType;
       4: areturn

  public void actualType(io.dekorate.deps.jackson.databind.JavaType);
    Code:
       0: aload_0
       1: aload_1
       2: putfield      #40                 // Field _actualType:Lio/dekorate/deps/jackson/databind/JavaType;
       5: return

  protected java.lang.String buildCanonicalName();
    Code:
       0: aload_0
       1: invokevirtual #47                 // Method toString:()Ljava/lang/String;
       4: areturn

  public java.lang.StringBuilder getGenericSignature(java.lang.StringBuilder);
    Code:
       0: aload_0
       1: aload_1
       2: invokevirtual #52                 // Method getErasedSignature:(Ljava/lang/StringBuilder;)Ljava/lang/StringBuilder;
       5: areturn

  public java.lang.StringBuilder getErasedSignature(java.lang.StringBuilder);
    Code:
       0: aload_1
       1: bipush        36
       3: invokevirtual #60                 // Method java/lang/StringBuilder.append:(C)Ljava/lang/StringBuilder;
       6: aload_0
       7: getfield      #34                 // Field _ordinal:I
      10: iconst_1
      11: iadd
      12: invokevirtual #63                 // Method java/lang/StringBuilder.append:(I)Ljava/lang/StringBuilder;
      15: pop
      16: aload_1
      17: areturn

  public io.dekorate.deps.jackson.databind.JavaType withTypeHandler(java.lang.Object);
    Code:
       0: aload_0
       1: invokespecial #69                 // Method _unsupported:()Ljava/lang/Object;
       4: checkcast     #71                 // class io/dekorate/deps/jackson/databind/JavaType
       7: areturn

  public io.dekorate.deps.jackson.databind.JavaType withContentTypeHandler(java.lang.Object);
    Code:
       0: aload_0
       1: invokespecial #69                 // Method _unsupported:()Ljava/lang/Object;
       4: checkcast     #71                 // class io/dekorate/deps/jackson/databind/JavaType
       7: areturn

  public io.dekorate.deps.jackson.databind.JavaType withValueHandler(java.lang.Object);
    Code:
       0: aload_0
       1: invokespecial #69                 // Method _unsupported:()Ljava/lang/Object;
       4: checkcast     #71                 // class io/dekorate/deps/jackson/databind/JavaType
       7: areturn

  public io.dekorate.deps.jackson.databind.JavaType withContentValueHandler(java.lang.Object);
    Code:
       0: aload_0
       1: invokespecial #69                 // Method _unsupported:()Ljava/lang/Object;
       4: checkcast     #71                 // class io/dekorate/deps/jackson/databind/JavaType
       7: areturn

  public io.dekorate.deps.jackson.databind.JavaType withContentType(io.dekorate.deps.jackson.databind.JavaType);
    Code:
       0: aload_0
       1: invokespecial #69                 // Method _unsupported:()Ljava/lang/Object;
       4: checkcast     #71                 // class io/dekorate/deps/jackson/databind/JavaType
       7: areturn

  public io.dekorate.deps.jackson.databind.JavaType withStaticTyping();
    Code:
       0: aload_0
       1: invokespecial #69                 // Method _unsupported:()Ljava/lang/Object;
       4: checkcast     #71                 // class io/dekorate/deps/jackson/databind/JavaType
       7: areturn

  public io.dekorate.deps.jackson.databind.JavaType refine(java.lang.Class<?>, io.dekorate.deps.jackson.databind.type.TypeBindings, io.dekorate.deps.jackson.databind.JavaType, io.dekorate.deps.jackson.databind.JavaType[]);
    Code:
       0: aload_0
       1: invokespecial #69                 // Method _unsupported:()Ljava/lang/Object;
       4: checkcast     #71                 // class io/dekorate/deps/jackson/databind/JavaType
       7: areturn

  protected io.dekorate.deps.jackson.databind.JavaType _narrow(java.lang.Class<?>);
    Code:
       0: aload_0
       1: invokespecial #69                 // Method _unsupported:()Ljava/lang/Object;
       4: checkcast     #71                 // class io/dekorate/deps/jackson/databind/JavaType
       7: areturn

  public boolean isContainerType();
    Code:
       0: iconst_0
       1: ireturn

  public java.lang.String toString();
    Code:
       0: aload_0
       1: new           #56                 // class java/lang/StringBuilder
       4: dup
       5: invokespecial #100                // Method java/lang/StringBuilder."<init>":()V
       8: invokevirtual #52                 // Method getErasedSignature:(Ljava/lang/StringBuilder;)Ljava/lang/StringBuilder;
      11: invokevirtual #101                // Method java/lang/StringBuilder.toString:()Ljava/lang/String;
      14: areturn

  public boolean equals(java.lang.Object);
    Code:
       0: aload_1
       1: aload_0
       2: if_acmpne     9
       5: iconst_1
       6: goto          10
       9: iconst_0
      10: ireturn

  private <T> T _unsupported();
    Code:
       0: new           #107                // class java/lang/UnsupportedOperationException
       3: dup
       4: new           #56                 // class java/lang/StringBuilder
       7: dup
       8: invokespecial #100                // Method java/lang/StringBuilder."<init>":()V
      11: ldc           #109                // String Operation should not be attempted on
      13: invokevirtual #112                // Method java/lang/StringBuilder.append:(Ljava/lang/String;)Ljava/lang/StringBuilder;
      16: aload_0
      17: invokevirtual #116                // Method java/lang/Object.getClass:()Ljava/lang/Class;
      20: invokevirtual #121                // Method java/lang/Class.getName:()Ljava/lang/String;
      23: invokevirtual #112                // Method java/lang/StringBuilder.append:(Ljava/lang/String;)Ljava/lang/StringBuilder;
      26: invokevirtual #101                // Method java/lang/StringBuilder.toString:()Ljava/lang/String;
      29: invokespecial #124                // Method java/lang/UnsupportedOperationException."<init>":(Ljava/lang/String;)V
      32: athrow
}
