Compiled from "LoggingEventFormattedTimestampJsonProvider.java"
public class net.logstash.logback.composite.loggingevent.LoggingEventFormattedTimestampJsonProvider extends net.logstash.logback.composite.FormattedTimestampJsonProvider<ch.qos.logback.classic.spi.ILoggingEvent, net.logstash.logback.fieldnames.LogstashFieldNames> {
  public net.logstash.logback.composite.loggingevent.LoggingEventFormattedTimestampJsonProvider();
    Code:
       0: aload_0
       1: invokespecial #10                 // Method net/logstash/logback/composite/FormattedTimestampJsonProvider."<init>":()V
       4: return

  protected long getTimestampAsMillis(ch.qos.logback.classic.spi.ILoggingEvent);
    Code:
       0: aload_1
       1: invokeinterface #20,  1           // InterfaceMethod ch/qos/logback/classic/spi/ILoggingEvent.getTimeStamp:()J
       6: lreturn

  protected long getTimestampAsMillis(ch.qos.logback.core.spi.DeferredProcessingAware);
    Code:
       0: aload_0
       1: aload_1
       2: checkcast     #16                 // class ch/qos/logback/classic/spi/ILoggingEvent
       5: invokevirtual #25                 // Method getTimestampAsMillis:(Lch/qos/logback/classic/spi/ILoggingEvent;)J
       8: lreturn
}
