Compiled from "LoggingEventCompositeJsonFormatter.java"
public class net.logstash.logback.composite.loggingevent.LoggingEventCompositeJsonFormatter extends net.logstash.logback.composite.CompositeJsonFormatter<ch.qos.logback.classic.spi.ILoggingEvent> {
  public net.logstash.logback.composite.loggingevent.LoggingEventCompositeJsonFormatter(ch.qos.logback.core.spi.ContextAware);
    Code:
       0: aload_0
       1: aload_1
       2: invokespecial #10                 // Method net/logstash/logback/composite/CompositeJsonFormatter."<init>":(Lch/qos/logback/core/spi/ContextAware;)V
       5: aload_0
       6: new           #12                 // class net/logstash/logback/composite/loggingevent/LoggingEventJsonProviders
       9: dup
      10: invokespecial #15                 // Method net/logstash/logback/composite/loggingevent/LoggingEventJsonProviders."<init>":()V
      13: invokevirtual #19                 // Method setProviders:(Lnet/logstash/logback/composite/JsonProviders;)V
      16: return

  public void setProviders(net.logstash.logback.composite.JsonProviders<ch.qos.logback.classic.spi.ILoggingEvent>);
    Code:
       0: aload_0
       1: aload_1
       2: invokespecial #28                 // Method net/logstash/logback/composite/CompositeJsonFormatter.setProviders:(Lnet/logstash/logback/composite/JsonProviders;)V
       5: return
}
