Compiled from "StoredProcedureQueryImpl.java"
class org.hibernate.jpa.internal.StoredProcedureQueryImpl$ParameterRegistrationImpl$1 implements org.hibernate.jpa.spi.ParameterBind<T> {
  final org.hibernate.jpa.internal.StoredProcedureQueryImpl$ParameterRegistrationImpl this$0;

  org.hibernate.jpa.internal.StoredProcedureQueryImpl$ParameterRegistrationImpl$1(org.hibernate.jpa.internal.StoredProcedureQueryImpl$ParameterRegistrationImpl);
    Code:
       0: aload_0
       1: aload_1
       2: putfield      #1                  // Field this$0:Lorg/hibernate/jpa/internal/StoredProcedureQueryImpl$ParameterRegistrationImpl;
       5: aload_0
       6: invokespecial #2                  // Method java/lang/Object."<init>":()V
       9: return

  public T getValue();
    Code:
       0: aload_0
       1: getfield      #1                  // Field this$0:Lorg/hibernate/jpa/internal/StoredProcedureQueryImpl$ParameterRegistrationImpl;
       4: invokestatic  #3                  // Method org/hibernate/jpa/internal/StoredProcedureQueryImpl$ParameterRegistrationImpl.access$100:(Lorg/hibernate/jpa/internal/StoredProcedureQueryImpl$ParameterRegistrationImpl;)Lorg/hibernate/procedure/ParameterRegistration;
       7: invokeinterface #4,  1            // InterfaceMethod org/hibernate/procedure/ParameterRegistration.getBind:()Lorg/hibernate/procedure/ParameterBind;
      12: invokeinterface #5,  1            // InterfaceMethod org/hibernate/procedure/ParameterBind.getValue:()Ljava/lang/Object;
      17: areturn

  public javax.persistence.TemporalType getSpecifiedTemporalType();
    Code:
       0: aload_0
       1: getfield      #1                  // Field this$0:Lorg/hibernate/jpa/internal/StoredProcedureQueryImpl$ParameterRegistrationImpl;
       4: invokestatic  #3                  // Method org/hibernate/jpa/internal/StoredProcedureQueryImpl$ParameterRegistrationImpl.access$100:(Lorg/hibernate/jpa/internal/StoredProcedureQueryImpl$ParameterRegistrationImpl;)Lorg/hibernate/procedure/ParameterRegistration;
       7: invokeinterface #4,  1            // InterfaceMethod org/hibernate/procedure/ParameterRegistration.getBind:()Lorg/hibernate/procedure/ParameterBind;
      12: invokeinterface #6,  1            // InterfaceMethod org/hibernate/procedure/ParameterBind.getExplicitTemporalType:()Ljavax/persistence/TemporalType;
      17: areturn
}
