Compiled from "ExplanationService.java"
public abstract class org.protege.editor.owl.ui.explanation.ExplanationService implements org.protege.editor.core.plugin.ProtegePluginInstance {
  private static final long serialVersionUID;

  private org.protege.editor.owl.OWLEditorKit editorKit;

  private java.lang.String pluginId;

  private java.lang.String name;

  public org.protege.editor.owl.ui.explanation.ExplanationService();
    Code:
       0: aload_0
       1: invokespecial #1                  // Method java/lang/Object."<init>":()V
       4: return

  public void setup(org.protege.editor.owl.OWLEditorKit, java.lang.String, java.lang.String);
    Code:
       0: aload_0
       1: aload_1
       2: putfield      #2                  // Field editorKit:Lorg/protege/editor/owl/OWLEditorKit;
       5: aload_0
       6: aload_2
       7: putfield      #3                  // Field pluginId:Ljava/lang/String;
      10: aload_0
      11: aload_3
      12: putfield      #4                  // Field name:Ljava/lang/String;
      15: return

  public org.protege.editor.owl.OWLEditorKit getOWLEditorKit();
    Code:
       0: aload_0
       1: getfield      #2                  // Field editorKit:Lorg/protege/editor/owl/OWLEditorKit;
       4: areturn

  public org.protege.editor.owl.model.OWLModelManager getOWLModelManager();
    Code:
       0: aload_0
       1: getfield      #2                  // Field editorKit:Lorg/protege/editor/owl/OWLEditorKit;
       4: invokevirtual #5                  // Method org/protege/editor/owl/OWLEditorKit.getModelManager:()Lorg/protege/editor/owl/model/OWLModelManager;
       7: areturn

  public java.lang.String getPluginId();
    Code:
       0: aload_0
       1: getfield      #3                  // Field pluginId:Ljava/lang/String;
       4: areturn

  public java.lang.String getName();
    Code:
       0: aload_0
       1: getfield      #4                  // Field name:Ljava/lang/String;
       4: areturn

  public java.lang.String toString();
    Code:
       0: aload_0
       1: invokevirtual #6                  // Method getName:()Ljava/lang/String;
       4: areturn

  public abstract void initialise() throws java.lang.Exception;

  public abstract boolean hasExplanation(org.semanticweb.owlapi.model.OWLAxiom);

  public abstract org.protege.editor.owl.ui.explanation.ExplanationResult explain(org.semanticweb.owlapi.model.OWLAxiom);
}
