final class org.bouncycastle.asn1.sec.SECNamedCurves$11 extends org.bouncycastle.asn1.x9.X9ECParametersHolder {
  org.bouncycastle.asn1.sec.SECNamedCurves$11();
    Code:
       0: aload_0
       1: invokespecial #59                 // Method org/bouncycastle/asn1/x9/X9ECParametersHolder."<init>":()V
       4: return

  protected org.bouncycastle.asn1.x9.X9ECParameters createParameters();
    Code:
       0: ldc           #6                  // String FFFFFFFFFFFFFFFFFFFFFFFFFFFFFFFF000000000000000000000001
       2: invokestatic  #55                 // Method org/bouncycastle/asn1/sec/SECNamedCurves.access$000:(Ljava/lang/String;)Ljava/math/BigInteger;
       5: astore_1
       6: ldc           #5                  // String FFFFFFFFFFFFFFFFFFFFFFFFFFFFFFFEFFFFFFFFFFFFFFFFFFFFFFFE
       8: invokestatic  #55                 // Method org/bouncycastle/asn1/sec/SECNamedCurves.access$000:(Ljava/lang/String;)Ljava/math/BigInteger;
      11: astore_2
      12: ldc           #2                  // String B4050A850C04B3ABF54132565044B0B7D7BFD8BA270B39432355FFB4
      14: invokestatic  #55                 // Method org/bouncycastle/asn1/sec/SECNamedCurves.access$000:(Ljava/lang/String;)Ljava/math/BigInteger;
      17: astore_3
      18: ldc           #3                  // String BD71344799D5C7FCDC45B59FA3B9AB8F6A948BC5
      20: invokestatic  #61                 // Method org/bouncycastle/util/encoders/Hex.decodeStrict:(Ljava/lang/String;)[B
      23: astore        4
      25: ldc           #4                  // String FFFFFFFFFFFFFFFFFFFFFFFFFFFF16A2E0B8F03E13DD29455C5C2A3D
      27: invokestatic  #55                 // Method org/bouncycastle/asn1/sec/SECNamedCurves.access$000:(Ljava/lang/String;)Ljava/math/BigInteger;
      30: astore        5
      32: lconst_1
      33: invokestatic  #54                 // Method java/math/BigInteger.valueOf:(J)Ljava/math/BigInteger;
      36: astore        6
      38: new           #36                 // class org/bouncycastle/math/ec/ECCurve$Fp
      41: dup
      42: aload_1
      43: aload_2
      44: aload_3
      45: aload         5
      47: aload         6
      49: invokespecial #60                 // Method org/bouncycastle/math/ec/ECCurve$Fp."<init>":(Ljava/math/BigInteger;Ljava/math/BigInteger;Ljava/math/BigInteger;Ljava/math/BigInteger;Ljava/math/BigInteger;)V
      52: invokestatic  #56                 // Method org/bouncycastle/asn1/sec/SECNamedCurves.access$100:(Lorg/bouncycastle/math/ec/ECCurve;)Lorg/bouncycastle/math/ec/ECCurve;
      55: astore        7
      57: aload         7
      59: ldc           #1                  // String 04B70E0CBD6BB4BF7F321390B94A03C1D356C21122343280D6115C1D21BD376388B5F723FB4C22DFE6CD4375A05A07476444D5819985007E34
      61: invokestatic  #57                 // Method org/bouncycastle/asn1/sec/SECNamedCurves.access$200:(Lorg/bouncycastle/math/ec/ECCurve;Ljava/lang/String;)Lorg/bouncycastle/asn1/x9/X9ECPoint;
      64: astore        8
      66: new           #33                 // class org/bouncycastle/asn1/x9/X9ECParameters
      69: dup
      70: aload         7
      72: aload         8
      74: aload         5
      76: aload         6
      78: aload         4
      80: invokespecial #58                 // Method org/bouncycastle/asn1/x9/X9ECParameters."<init>":(Lorg/bouncycastle/math/ec/ECCurve;Lorg/bouncycastle/asn1/x9/X9ECPoint;Ljava/math/BigInteger;Ljava/math/BigInteger;[B)V
      83: areturn
}
