Compiled from "HymodAdigeEngine.java"
public class org.hortonmachine.hmachine.modules.hydrogeomorphology.adige.hymod.HymodAdigeEngine implements org.hortonmachine.hmachine.modules.hydrogeomorphology.adige.IAdigeEngine {
  private final org.hortonmachine.hmachine.modules.hydrogeomorphology.adige.hymod.HymodInputs hymodInputs;

  private final java.util.List<org.hortonmachine.hmachine.modules.hydrogeomorphology.adige.core.IHillSlope> orderedHillslopes;

  private double[] xSlow;

  private double[] xLoss;

  private double[][] xQuick;

  private final java.util.HashMap<java.lang.Integer, double[]> outDischarge;

  private final java.util.HashMap<java.lang.Integer, double[]> outSubDischarge;

  private final java.util.HashMap<java.lang.Integer, double[]> outDischargeInternal;

  private final java.util.HashMap<java.lang.Integer, java.lang.Integer> index2Basinid;

  private java.util.List<org.hortonmachine.hmachine.modules.hydrogeomorphology.adige.core.IDischargeContributor> dischargeContributorList;

  private final boolean doPrint;

  private final boolean doLog;

  private final org.hortonmachine.gears.libs.monitor.IHMProgressMonitor pm;

  private final java.util.List<java.lang.String> pfaffsList;

  private double[] coeffs;

  public static final double doubleNovalue;

  int conta;

  public org.hortonmachine.hmachine.modules.hydrogeomorphology.adige.hymod.HymodAdigeEngine(org.hortonmachine.hmachine.modules.hydrogeomorphology.adige.hymod.HymodInputs, java.util.List<org.hortonmachine.hmachine.modules.hydrogeomorphology.adige.core.IHillSlope>, java.util.HashMap<java.lang.Integer, java.lang.Integer>, java.util.HashMap<java.lang.Integer, double[]>, java.util.HashMap<java.lang.Integer, double[]>, java.util.List<java.lang.String>, boolean, boolean, org.hortonmachine.gears.libs.monitor.IHMProgressMonitor);
    Code:
       0: aload_0
       1: invokespecial #2                  // Method java/lang/Object."<init>":()V
       4: aload_0
       5: aconst_null
       6: putfield      #3                  // Field xSlow:[D
       9: aload_0
      10: aconst_null
      11: putfield      #4                  // Field xLoss:[D
      14: aload_0
      15: aconst_null
      16: checkcast     #5                  // class "[[D"
      19: putfield      #6                  // Field xQuick:[[D
      22: aload_0
      23: new           #7                  // class java/util/ArrayList
      26: dup
      27: invokespecial #8                  // Method java/util/ArrayList."<init>":()V
      30: putfield      #9                  // Field dischargeContributorList:Ljava/util/List;
      33: aload_0
      34: iconst_0
      35: putfield      #10                 // Field conta:I
      38: aload_0
      39: aload_1
      40: putfield      #11                 // Field hymodInputs:Lorg/hortonmachine/hmachine/modules/hydrogeomorphology/adige/hymod/HymodInputs;
      43: aload_0
      44: aload_2
      45: putfield      #12                 // Field orderedHillslopes:Ljava/util/List;
      48: aload_0
      49: aload_3
      50: putfield      #13                 // Field index2Basinid:Ljava/util/HashMap;
      53: aload_0
      54: aload         4
      56: putfield      #14                 // Field outDischarge:Ljava/util/HashMap;
      59: aload_0
      60: aload         5
      62: putfield      #15                 // Field outSubDischarge:Ljava/util/HashMap;
      65: aload_0
      66: aload         6
      68: putfield      #16                 // Field pfaffsList:Ljava/util/List;
      71: aload_0
      72: iload         7
      74: putfield      #17                 // Field doLog:Z
      77: aload_0
      78: iload         8
      80: putfield      #18                 // Field doPrint:Z
      83: aload_0
      84: aload         9
      86: putfield      #19                 // Field pm:Lorg/hortonmachine/gears/libs/monitor/IHMProgressMonitor;
      89: aload_0
      90: new           #20                 // class java/util/HashMap
      93: dup
      94: invokespecial #21                 // Method java/util/HashMap."<init>":()V
      97: putfield      #22                 // Field outDischargeInternal:Ljava/util/HashMap;
     100: return

  public void addDischargeContributor(org.hortonmachine.hmachine.modules.hydrogeomorphology.adige.core.IDischargeContributor);
    Code:
       0: aload_0
       1: getfield      #9                  // Field dischargeContributorList:Ljava/util/List;
       4: aload_1
       5: invokeinterface #23,  2           // InterfaceMethod java/util/List.add:(Ljava/lang/Object;)Z
      10: pop
      11: return

  public java.util.HashMap<java.lang.Integer, double[]> getDischarge();
    Code:
       0: aload_0
       1: getfield      #14                 // Field outDischarge:Ljava/util/HashMap;
       4: areturn

  public java.util.HashMap<java.lang.Integer, double[]> getSubDischarge();
    Code:
       0: aload_0
       1: getfield      #15                 // Field outSubDischarge:Ljava/util/HashMap;
       4: areturn

  public double[] solve(org.joda.time.DateTime, int, double, double[], double[], double[]) throws java.io.IOException;
    Code:
       0: aload         5
       2: ifnull        141
       5: aload_0
       6: getfield      #12                 // Field orderedHillslopes:Ljava/util/List;
       9: invokeinterface #24,  1           // InterfaceMethod java/util/List.size:()I
      14: iconst_1
      15: isub
      16: istore        8
      18: iload         8
      20: iflt          141
      23: aload_0
      24: getfield      #4                  // Field xLoss:[D
      27: iload         8
      29: aload         5
      31: iload         8
      33: daload
      34: dastore
      35: aload_0
      36: getfield      #3                  // Field xSlow:[D
      39: iload         8
      41: aload         5
      43: iload         8
      45: aload_0
      46: getfield      #12                 // Field orderedHillslopes:Ljava/util/List;
      49: invokeinterface #24,  1           // InterfaceMethod java/util/List.size:()I
      54: iadd
      55: daload
      56: dastore
      57: aload_0
      58: getfield      #6                  // Field xQuick:[[D
      61: iconst_0
      62: aaload
      63: iload         8
      65: aload         5
      67: iload         8
      69: iconst_2
      70: aload_0
      71: getfield      #12                 // Field orderedHillslopes:Ljava/util/List;
      74: invokeinterface #24,  1           // InterfaceMethod java/util/List.size:()I
      79: imul
      80: iadd
      81: daload
      82: dastore
      83: aload_0
      84: getfield      #6                  // Field xQuick:[[D
      87: iconst_1
      88: aaload
      89: iload         8
      91: aload         5
      93: iload         8
      95: iconst_3
      96: aload_0
      97: getfield      #12                 // Field orderedHillslopes:Ljava/util/List;
     100: invokeinterface #24,  1           // InterfaceMethod java/util/List.size:()I
     105: imul
     106: iadd
     107: daload
     108: dastore
     109: aload_0
     110: getfield      #6                  // Field xQuick:[[D
     113: iconst_2
     114: aaload
     115: iload         8
     117: aload         5
     119: iload         8
     121: iconst_4
     122: aload_0
     123: getfield      #12                 // Field orderedHillslopes:Ljava/util/List;
     126: invokeinterface #24,  1           // InterfaceMethod java/util/List.size:()I
     131: imul
     132: iadd
     133: daload
     134: dastore
     135: iinc          8, -1
     138: goto          18
     141: aload         5
     143: ifnonnull     351
     146: aload_0
     147: aload_0
     148: getfield      #12                 // Field orderedHillslopes:Ljava/util/List;
     151: invokeinterface #24,  1           // InterfaceMethod java/util/List.size:()I
     156: newarray       double
     158: putfield      #3                  // Field xSlow:[D
     161: aload_0
     162: aload_0
     163: getfield      #12                 // Field orderedHillslopes:Ljava/util/List;
     166: invokeinterface #24,  1           // InterfaceMethod java/util/List.size:()I
     171: newarray       double
     173: putfield      #25                 // Field coeffs:[D
     176: aload_0
     177: iconst_3
     178: aload_0
     179: getfield      #12                 // Field orderedHillslopes:Ljava/util/List;
     182: invokeinterface #24,  1           // InterfaceMethod java/util/List.size:()I
     187: multianewarray #5,  2             // class "[[D"
     191: putfield      #6                  // Field xQuick:[[D
     194: aload_0
     195: aload_0
     196: getfield      #12                 // Field orderedHillslopes:Ljava/util/List;
     199: invokeinterface #24,  1           // InterfaceMethod java/util/List.size:()I
     204: newarray       double
     206: putfield      #4                  // Field xLoss:[D
     209: aload_0
     210: getfield      #12                 // Field orderedHillslopes:Ljava/util/List;
     213: invokeinterface #24,  1           // InterfaceMethod java/util/List.size:()I
     218: iconst_5
     219: imul
     220: newarray       double
     222: astore        5
     224: aload_0
     225: getfield      #12                 // Field orderedHillslopes:Ljava/util/List;
     228: invokeinterface #24,  1           // InterfaceMethod java/util/List.size:()I
     233: iconst_1
     234: isub
     235: istore        8
     237: iload         8
     239: iflt          351
     242: aload_0
     243: getfield      #12                 // Field orderedHillslopes:Ljava/util/List;
     246: iload         8
     248: invokeinterface #26,  2           // InterfaceMethod java/util/List.get:(I)Ljava/lang/Object;
     253: checkcast     #27                 // class org/hortonmachine/hmachine/modules/hydrogeomorphology/adige/core/IHillSlope
     256: astore        9
     258: aload         9
     260: invokeinterface #28,  1           // InterfaceMethod org/hortonmachine/hmachine/modules/hydrogeomorphology/adige/core/IHillSlope.getHillslopeArea:()D
     265: ldc2_w        #29                 // double 1000000.0d
     268: ddiv
     269: dstore        10
     271: aload_0
     272: getfield      #25                 // Field coeffs:[D
     275: iload         8
     277: ldc2_w        #31                 // double 10.0d
     280: ldc2_w        #33                 // double 9.0d
     283: invokestatic  #35                 // Method java/lang/Math.pow:(DD)D
     286: iload_2
     287: i2d
     288: dmul
     289: ldc2_w        #36                 // double 60.0d
     292: dmul
     293: dload         10
     295: ldc2_w        #31                 // double 10.0d
     298: ldc2_w        #38                 // double 12.0d
     301: invokestatic  #35                 // Method java/lang/Math.pow:(DD)D
     304: dmul
     305: ddiv
     306: dastore
     307: aload_0
     308: getfield      #3                  // Field xSlow:[D
     311: iload         8
     313: dconst_0
     314: aload_0
     315: getfield      #11                 // Field hymodInputs:Lorg/hortonmachine/hmachine/modules/hydrogeomorphology/adige/hymod/HymodInputs;
     318: getfield      #40                 // Field org/hortonmachine/hmachine/modules/hydrogeomorphology/adige/hymod/HymodInputs.pQ0:Ljava/lang/Double;
     321: invokevirtual #41                 // Method java/lang/Double.doubleValue:()D
     324: dmul
     325: aload_0
     326: getfield      #25                 // Field coeffs:[D
     329: iload         8
     331: daload
     332: dmul
     333: aload_0
     334: getfield      #11                 // Field hymodInputs:Lorg/hortonmachine/hmachine/modules/hydrogeomorphology/adige/hymod/HymodInputs;
     337: getfield      #42                 // Field org/hortonmachine/hmachine/modules/hydrogeomorphology/adige/hymod/HymodInputs.pRs:Ljava/lang/Double;
     340: invokevirtual #41                 // Method java/lang/Double.doubleValue:()D
     343: ddiv
     344: dastore
     345: iinc          8, -1
     348: goto          237
     351: aload_0
     352: getfield      #12                 // Field orderedHillslopes:Ljava/util/List;
     355: invokeinterface #24,  1           // InterfaceMethod java/util/List.size:()I
     360: iconst_1
     361: isub
     362: istore        8
     364: iload         8
     366: iflt          859
     369: aload_0
     370: getfield      #12                 // Field orderedHillslopes:Ljava/util/List;
     373: iload         8
     375: invokeinterface #26,  2           // InterfaceMethod java/util/List.get:(I)Ljava/lang/Object;
     380: checkcast     #27                 // class org/hortonmachine/hmachine/modules/hydrogeomorphology/adige/core/IHillSlope
     383: astore        9
     385: aload         6
     387: iload         8
     389: daload
     390: dstore        10
     392: aload         7
     394: iload         8
     396: daload
     397: dstore        12
     399: aload_0
     400: aload_0
     401: getfield      #4                  // Field xLoss:[D
     404: iload         8
     406: daload
     407: dload         10
     409: dload         12
     411: invokespecial #43                 // Method excess:(DDD)[D
     414: astore        14
     416: aload         14
     418: iconst_0
     419: daload
     420: dstore        15
     422: aload         14
     424: iconst_1
     425: daload
     426: dstore        17
     428: aload_0
     429: getfield      #4                  // Field xLoss:[D
     432: iload         8
     434: aload         14
     436: iconst_2
     437: daload
     438: dastore
     439: aload_0
     440: getfield      #11                 // Field hymodInputs:Lorg/hortonmachine/hmachine/modules/hydrogeomorphology/adige/hymod/HymodInputs;
     443: getfield      #44                 // Field org/hortonmachine/hmachine/modules/hydrogeomorphology/adige/hymod/HymodInputs.pAlpha:Ljava/lang/Double;
     446: invokevirtual #41                 // Method java/lang/Double.doubleValue:()D
     449: dload         17
     451: dmul
     452: dload         15
     454: dadd
     455: dstore        19
     457: dconst_1
     458: aload_0
     459: getfield      #11                 // Field hymodInputs:Lorg/hortonmachine/hmachine/modules/hydrogeomorphology/adige/hymod/HymodInputs;
     462: getfield      #44                 // Field org/hortonmachine/hmachine/modules/hydrogeomorphology/adige/hymod/HymodInputs.pAlpha:Ljava/lang/Double;
     465: invokevirtual #41                 // Method java/lang/Double.doubleValue:()D
     468: dsub
     469: dload         17
     471: dmul
     472: dstore        21
     474: dload         21
     476: dstore        23
     478: aload_0
     479: aload_0
     480: getfield      #3                  // Field xSlow:[D
     483: iload         8
     485: daload
     486: dload         23
     488: aload_0
     489: getfield      #11                 // Field hymodInputs:Lorg/hortonmachine/hmachine/modules/hydrogeomorphology/adige/hymod/HymodInputs;
     492: getfield      #42                 // Field org/hortonmachine/hmachine/modules/hydrogeomorphology/adige/hymod/HymodInputs.pRs:Ljava/lang/Double;
     495: invokevirtual #41                 // Method java/lang/Double.doubleValue:()D
     498: dconst_1
     499: invokespecial #45                 // Method linres:(DDDD)[D
     502: astore        25
     504: aload_0
     505: getfield      #3                  // Field xSlow:[D
     508: iload         8
     510: aload         25
     512: iconst_0
     513: daload
     514: dastore
     515: aload         25
     517: iconst_1
     518: daload
     519: dstore        26
     521: dload         26
     523: dstore        28
     525: dload         19
     527: dstore        23
     529: dconst_0
     530: dstore        30
     532: iconst_0
     533: istore        32
     535: iload         32
     537: iconst_3
     538: if_icmpge     600
     541: aload_0
     542: aload_0
     543: getfield      #6                  // Field xQuick:[[D
     546: iload         32
     548: aaload
     549: iload         8
     551: daload
     552: dload         23
     554: aload_0
     555: getfield      #11                 // Field hymodInputs:Lorg/hortonmachine/hmachine/modules/hydrogeomorphology/adige/hymod/HymodInputs;
     558: getfield      #46                 // Field org/hortonmachine/hmachine/modules/hydrogeomorphology/adige/hymod/HymodInputs.pRq:Ljava/lang/Double;
     561: invokevirtual #41                 // Method java/lang/Double.doubleValue:()D
     564: dconst_1
     565: invokespecial #45                 // Method linres:(DDDD)[D
     568: astore        33
     570: aload_0
     571: getfield      #6                  // Field xQuick:[[D
     574: iload         32
     576: aaload
     577: iload         8
     579: aload         33
     581: iconst_0
     582: daload
     583: dastore
     584: aload         33
     586: iconst_1
     587: daload
     588: dstore        30
     590: dload         30
     592: dstore        23
     594: iinc          32, 1
     597: goto          535
     600: aload_0
     601: getfield      #13                 // Field index2Basinid:Ljava/util/HashMap;
     604: iload         8
     606: invokestatic  #47                 // Method java/lang/Integer.valueOf:(I)Ljava/lang/Integer;
     609: invokevirtual #48                 // Method java/util/HashMap.get:(Ljava/lang/Object;)Ljava/lang/Object;
     612: checkcast     #49                 // class java/lang/Integer
     615: astore        32
     617: dload         28
     619: dload         30
     621: dadd
     622: aload_0
     623: getfield      #25                 // Field coeffs:[D
     626: iload         8
     628: daload
     629: ddiv
     630: dstore        33
     632: dload         28
     634: aload_0
     635: getfield      #25                 // Field coeffs:[D
     638: iload         8
     640: daload
     641: ddiv
     642: dstore        35
     644: aload_0
     645: aload         9
     647: dload         33
     649: invokespecial #50                 // Method handleContributors:(Lorg/hortonmachine/hmachine/modules/hydrogeomorphology/adige/core/IHillSlope;D)D
     652: dstore        37
     654: dload         33
     656: dload         37
     658: dadd
     659: dstore        33
     661: aload         9
     663: invokeinterface #51,  1           // InterfaceMethod org/hortonmachine/hmachine/modules/hydrogeomorphology/adige/core/IHillSlope.getPfafstetterNumber:()Lorg/hortonmachine/hmachine/modules/network/PfafstetterNumber;
     668: astore        39
     670: aload_0
     671: getfield      #16                 // Field pfaffsList:Ljava/util/List;
     674: aload         39
     676: invokevirtual #52                 // Method org/hortonmachine/hmachine/modules/network/PfafstetterNumber.toString:()Ljava/lang/String;
     679: invokeinterface #53,  2           // InterfaceMethod java/util/List.contains:(Ljava/lang/Object;)Z
     684: ifeq          723
     687: aload_0
     688: getfield      #14                 // Field outDischarge:Ljava/util/HashMap;
     691: aload         32
     693: iconst_1
     694: newarray       double
     696: dup
     697: iconst_0
     698: dload         33
     700: dastore
     701: invokevirtual #54                 // Method java/util/HashMap.put:(Ljava/lang/Object;Ljava/lang/Object;)Ljava/lang/Object;
     704: pop
     705: aload_0
     706: getfield      #15                 // Field outSubDischarge:Ljava/util/HashMap;
     709: aload         32
     711: iconst_1
     712: newarray       double
     714: dup
     715: iconst_0
     716: dload         35
     718: dastore
     719: invokevirtual #54                 // Method java/util/HashMap.put:(Ljava/lang/Object;Ljava/lang/Object;)Ljava/lang/Object;
     722: pop
     723: aload         5
     725: iload         8
     727: aload_0
     728: getfield      #4                  // Field xLoss:[D
     731: iload         8
     733: daload
     734: dastore
     735: aload         5
     737: iload         8
     739: aload_0
     740: getfield      #12                 // Field orderedHillslopes:Ljava/util/List;
     743: invokeinterface #24,  1           // InterfaceMethod java/util/List.size:()I
     748: iadd
     749: aload_0
     750: getfield      #3                  // Field xSlow:[D
     753: iload         8
     755: daload
     756: dastore
     757: aload         5
     759: iload         8
     761: iconst_2
     762: aload_0
     763: getfield      #12                 // Field orderedHillslopes:Ljava/util/List;
     766: invokeinterface #24,  1           // InterfaceMethod java/util/List.size:()I
     771: imul
     772: iadd
     773: aload_0
     774: getfield      #6                  // Field xQuick:[[D
     777: iconst_0
     778: aaload
     779: iload         8
     781: daload
     782: dastore
     783: aload         5
     785: iload         8
     787: iconst_3
     788: aload_0
     789: getfield      #12                 // Field orderedHillslopes:Ljava/util/List;
     792: invokeinterface #24,  1           // InterfaceMethod java/util/List.size:()I
     797: imul
     798: iadd
     799: aload_0
     800: getfield      #6                  // Field xQuick:[[D
     803: iconst_1
     804: aaload
     805: iload         8
     807: daload
     808: dastore
     809: aload         5
     811: iload         8
     813: iconst_4
     814: aload_0
     815: getfield      #12                 // Field orderedHillslopes:Ljava/util/List;
     818: invokeinterface #24,  1           // InterfaceMethod java/util/List.size:()I
     823: imul
     824: iadd
     825: aload_0
     826: getfield      #6                  // Field xQuick:[[D
     829: iconst_2
     830: aaload
     831: iload         8
     833: daload
     834: dastore
     835: aload_0
     836: getfield      #22                 // Field outDischargeInternal:Ljava/util/HashMap;
     839: aload         32
     841: iconst_1
     842: newarray       double
     844: dup
     845: iconst_0
     846: dload         33
     848: dastore
     849: invokevirtual #54                 // Method java/util/HashMap.put:(Ljava/lang/Object;Ljava/lang/Object;)Ljava/lang/Object;
     852: pop
     853: iinc          8, -1
     856: goto          364
     859: aload         5
     861: areturn

  private double handleContributors(org.hortonmachine.hmachine.modules.hydrogeomorphology.adige.core.IHillSlope, double);
    Code:
       0: dconst_0
       1: dstore        4
       3: aload_1
       4: invokeinterface #55,  1           // InterfaceMethod org/hortonmachine/hmachine/modules/hydrogeomorphology/adige/core/IHillSlope.getConnectedUpstreamElements:()Ljava/util/List;
       9: astore        6
      11: aload         6
      13: ifnull        278
      16: aload         6
      18: invokeinterface #56,  1           // InterfaceMethod java/util/List.iterator:()Ljava/util/Iterator;
      23: astore        7
      25: aload         7
      27: invokeinterface #57,  1           // InterfaceMethod java/util/Iterator.hasNext:()Z
      32: ifeq          278
      35: aload         7
      37: invokeinterface #58,  1           // InterfaceMethod java/util/Iterator.next:()Ljava/lang/Object;
      42: checkcast     #27                 // class org/hortonmachine/hmachine/modules/hydrogeomorphology/adige/core/IHillSlope
      45: astore        8
      47: aload         8
      49: invokeinterface #51,  1           // InterfaceMethod org/hortonmachine/hmachine/modules/hydrogeomorphology/adige/core/IHillSlope.getPfafstetterNumber:()Lorg/hortonmachine/hmachine/modules/network/PfafstetterNumber;
      54: astore        9
      56: aload         8
      58: invokeinterface #59,  1           // InterfaceMethod org/hortonmachine/hmachine/modules/hydrogeomorphology/adige/core/IHillSlope.getHillslopeId:()I
      63: istore        10
      65: aload_0
      66: getfield      #22                 // Field outDischargeInternal:Ljava/util/HashMap;
      69: iload         10
      71: invokestatic  #47                 // Method java/lang/Integer.valueOf:(I)Ljava/lang/Integer;
      74: invokevirtual #48                 // Method java/util/HashMap.get:(Ljava/lang/Object;)Ljava/lang/Object;
      77: checkcast     #60                 // class "[D"
      80: iconst_0
      81: daload
      82: dstore        11
      84: aload_0
      85: getfield      #9                  // Field dischargeContributorList:Ljava/util/List;
      88: invokeinterface #56,  1           // InterfaceMethod java/util/List.iterator:()Ljava/util/Iterator;
      93: astore        13
      95: aload         13
      97: invokeinterface #57,  1           // InterfaceMethod java/util/Iterator.hasNext:()Z
     102: ifeq          257
     105: aload         13
     107: invokeinterface #58,  1           // InterfaceMethod java/util/Iterator.next:()Ljava/lang/Object;
     112: checkcast     #61                 // class org/hortonmachine/hmachine/modules/hydrogeomorphology/adige/core/IDischargeContributor
     115: astore        14
     117: aload         14
     119: aload         9
     121: invokevirtual #52                 // Method org/hortonmachine/hmachine/modules/network/PfafstetterNumber.toString:()Ljava/lang/String;
     124: invokeinterface #62,  2           // InterfaceMethod org/hortonmachine/hmachine/modules/hydrogeomorphology/adige/core/IDischargeContributor.getDischarge:(Ljava/lang/String;)Ljava/lang/Double;
     129: astore        15
     131: aload         15
     133: invokevirtual #41                 // Method java/lang/Double.doubleValue:()D
     136: invokestatic  #63                 // Method org/hortonmachine/gears/libs/modules/HMConstants.isNovalue:(D)Z
     139: ifne          254
     142: aload_0
     143: getfield      #17                 // Field doLog:Z
     146: ifeq          227
     149: aload_0
     150: getfield      #18                 // Field doPrint:Z
     153: ifeq          227
     156: aload_0
     157: getfield      #19                 // Field pm:Lorg/hortonmachine/gears/libs/monitor/IHMProgressMonitor;
     160: new           #64                 // class java/lang/StringBuilder
     163: dup
     164: invokespecial #65                 // Method java/lang/StringBuilder."<init>":()V
     167: ldc           #66                 // String ----> For hillslope
     169: invokevirtual #67                 // Method java/lang/StringBuilder.append:(Ljava/lang/String;)Ljava/lang/StringBuilder;
     172: aload_1
     173: invokeinterface #51,  1           // InterfaceMethod org/hortonmachine/hmachine/modules/hydrogeomorphology/adige/core/IHillSlope.getPfafstetterNumber:()Lorg/hortonmachine/hmachine/modules/network/PfafstetterNumber;
     178: invokevirtual #68                 // Method java/lang/StringBuilder.append:(Ljava/lang/Object;)Ljava/lang/StringBuilder;
     181: ldc           #69                 // String  using hydrometer/dams data in pfafstetter:
     183: invokevirtual #67                 // Method java/lang/StringBuilder.append:(Ljava/lang/String;)Ljava/lang/StringBuilder;
     186: aload         9
     188: invokevirtual #52                 // Method org/hortonmachine/hmachine/modules/network/PfafstetterNumber.toString:()Ljava/lang/String;
     191: invokevirtual #67                 // Method java/lang/StringBuilder.append:(Ljava/lang/String;)Ljava/lang/StringBuilder;
     194: ldc           #70                 // String (meaning added
     196: invokevirtual #67                 // Method java/lang/StringBuilder.append:(Ljava/lang/String;)Ljava/lang/StringBuilder;
     199: aload         15
     201: invokevirtual #68                 // Method java/lang/StringBuilder.append:(Ljava/lang/Object;)Ljava/lang/StringBuilder;
     204: ldc           #71                 // String  instead of
     206: invokevirtual #67                 // Method java/lang/StringBuilder.append:(Ljava/lang/String;)Ljava/lang/StringBuilder;
     209: dload         11
     211: invokevirtual #72                 // Method java/lang/StringBuilder.append:(D)Ljava/lang/StringBuilder;
     214: ldc           #73                 // String )
     216: invokevirtual #67                 // Method java/lang/StringBuilder.append:(Ljava/lang/String;)Ljava/lang/StringBuilder;
     219: invokevirtual #74                 // Method java/lang/StringBuilder.toString:()Ljava/lang/String;
     222: invokeinterface #75,  2           // InterfaceMethod org/hortonmachine/gears/libs/monitor/IHMProgressMonitor.message:(Ljava/lang/String;)V
     227: aload         15
     229: invokevirtual #41                 // Method java/lang/Double.doubleValue:()D
     232: invokestatic  #63                 // Method org/hortonmachine/gears/libs/modules/HMConstants.isNovalue:(D)Z
     235: ifne          254
     238: aload         14
     240: aload         15
     242: invokevirtual #41                 // Method java/lang/Double.doubleValue:()D
     245: dload         11
     247: invokeinterface #76,  5           // InterfaceMethod org/hortonmachine/hmachine/modules/hydrogeomorphology/adige/core/IDischargeContributor.mergeWithDischarge:(DD)D
     252: dstore        11
     254: goto          95
     257: aload_0
     258: dload         11
     260: dload_2
     261: aload         8
     263: invokespecial #77                 // Method doRouting:(DDLorg/hortonmachine/hmachine/modules/hydrogeomorphology/adige/core/IHillSlope;)D
     266: dstore        13
     268: dload         4
     270: dload         13
     272: dadd
     273: dstore        4
     275: goto          25
     278: dload         4
     280: dreturn

  private double doRouting(double, double, org.hortonmachine.hmachine.modules.hydrogeomorphology.adige.core.IHillSlope);
    Code:
       0: dload_1
       1: dreturn

  private double[] excess(double, double, double);
    Code:
       0: iconst_3
       1: newarray       double
       3: astore        7
       5: aload_0
       6: getfield      #11                 // Field hymodInputs:Lorg/hortonmachine/hmachine/modules/hydrogeomorphology/adige/hymod/HymodInputs;
       9: getfield      #78                 // Field org/hortonmachine/hmachine/modules/hydrogeomorphology/adige/hymod/HymodInputs.pB:Ljava/lang/Double;
      12: invokevirtual #41                 // Method java/lang/Double.doubleValue:()D
      15: dstore        8
      17: aload_0
      18: getfield      #11                 // Field hymodInputs:Lorg/hortonmachine/hmachine/modules/hydrogeomorphology/adige/hymod/HymodInputs;
      21: getfield      #79                 // Field org/hortonmachine/hmachine/modules/hydrogeomorphology/adige/hymod/HymodInputs.pCmax:Ljava/lang/Double;
      24: invokevirtual #41                 // Method java/lang/Double.doubleValue:()D
      27: dstore        10
      29: dload_1
      30: dstore        12
      32: dconst_1
      33: dload         8
      35: dconst_1
      36: dadd
      37: dload         12
      39: dmul
      40: dload         10
      42: ddiv
      43: dsub
      44: dstore        14
      46: dconst_1
      47: dload         8
      49: dconst_1
      50: dadd
      51: ddiv
      52: dstore        16
      54: dload         10
      56: dconst_1
      57: dload         14
      59: dload         16
      61: invokestatic  #35                 // Method java/lang/Math.pow:(DD)D
      64: dsub
      65: dmul
      66: dstore        18
      68: dload_3
      69: dload         10
      71: dsub
      72: dload         18
      74: dadd
      75: dconst_0
      76: invokestatic  #80                 // Method java/lang/Math.max:(DD)D
      79: dstore        20
      81: dload_3
      82: dload         20
      84: dsub
      85: dstore_3
      86: dload         18
      88: dload_3
      89: dadd
      90: dload         10
      92: ddiv
      93: dconst_1
      94: invokestatic  #81                 // Method java/lang/Math.min:(DD)D
      97: dstore        22
      99: dconst_1
     100: dload         22
     102: dsub
     103: dstore        24
     105: dload         8
     107: dconst_1
     108: dadd
     109: dstore        26
     111: dload         10
     113: dload         8
     115: dconst_1
     116: dadd
     117: ddiv
     118: dconst_1
     119: dload         24
     121: dload         26
     123: invokestatic  #35                 // Method java/lang/Math.pow:(DD)D
     126: dsub
     127: dmul
     128: dstore        28
     130: dload_3
     131: dload         28
     133: dload         12
     135: dsub
     136: dsub
     137: dconst_0
     138: invokestatic  #80                 // Method java/lang/Math.max:(DD)D
     141: dstore        30
     143: dload         28
     145: dload         5
     147: invokestatic  #81                 // Method java/lang/Math.min:(DD)D
     150: dstore        32
     152: dload         28
     154: dload         32
     156: dsub
     157: dstore        28
     159: aload         7
     161: iconst_0
     162: dload         20
     164: dastore
     165: aload         7
     167: iconst_1
     168: dload         30
     170: dastore
     171: aload         7
     173: iconst_2
     174: dload         28
     176: dastore
     177: dload         28
     179: dload         28
     181: dcmpl
     182: ifne          201
     185: dload         20
     187: dload         20
     189: dcmpl
     190: ifne          201
     193: dload         30
     195: dload         30
     197: dcmpl
     198: ifeq          209
     201: getstatic     #82                 // Field java/lang/System.out:Ljava/io/PrintStream;
     204: ldc           #83                 // String FERMATI
     206: invokevirtual #84                 // Method java/io/PrintStream.println:(Ljava/lang/String;)V
     209: aload         7
     211: areturn

  private double[] linres(double, double, double, double);
    Code:
       0: iconst_2
       1: newarray       double
       3: astore        9
       5: dload_1
       6: dstore        10
       8: dload_3
       9: dload         7
      11: dmul
      12: dload         10
      14: dconst_1
      15: dload         5
      17: dload         7
      19: dmul
      20: dsub
      21: dmul
      22: dadd
      23: dstore        12
      25: dload         12
      27: dload         5
      29: dmul
      30: dstore        14
      32: aload         9
      34: iconst_0
      35: dload         12
      37: dastore
      38: aload         9
      40: iconst_1
      41: dload         14
      43: dastore
      44: aload         9
      46: areturn
}
