Compiled from "MapSimpleSubscription.java"
public class net.openhft.chronicle.engine.pubsub.MapSimpleSubscription<E> implements net.openhft.chronicle.engine.pubsub.SimpleSubscription<E> {
  private static final org.slf4j.Logger LOG;

  private final java.util.Set<net.openhft.chronicle.engine.api.pubsub.Subscriber<E>> subscribers;

  private final net.openhft.chronicle.engine.api.pubsub.Reference<E> currentValue;

  private final java.util.function.Function<java.lang.Object, E> valueReader;

  public net.openhft.chronicle.engine.pubsub.MapSimpleSubscription(net.openhft.chronicle.engine.api.pubsub.Reference<E>, java.util.function.Function<java.lang.Object, E>);
    Code:
       0: aload_0
       1: invokespecial #1                  // Method java/lang/Object."<init>":()V
       4: aload_0
       5: new           #2                  // class java/util/concurrent/CopyOnWriteArraySet
       8: dup
       9: invokespecial #3                  // Method java/util/concurrent/CopyOnWriteArraySet."<init>":()V
      12: putfield      #4                  // Field subscribers:Ljava/util/Set;
      15: aload_0
      16: aload_1
      17: putfield      #5                  // Field currentValue:Lnet/openhft/chronicle/engine/api/pubsub/Reference;
      20: aload_0
      21: aload_2
      22: putfield      #6                  // Field valueReader:Ljava/util/function/Function;
      25: return

  public void registerSubscriber(net.openhft.chronicle.engine.api.tree.RequestContext, net.openhft.chronicle.engine.api.pubsub.Subscriber<E>, net.openhft.chronicle.engine.query.Filter<E>);
    Code:
       0: aload_0
       1: getfield      #4                  // Field subscribers:Ljava/util/Set;
       4: aload_2
       5: invokeinterface #7,  2            // InterfaceMethod java/util/Set.add:(Ljava/lang/Object;)Z
      10: pop
      11: aload_1
      12: invokevirtual #8                  // Method net/openhft/chronicle/engine/api/tree/RequestContext.bootstrap:()Ljava/lang/Boolean;
      15: getstatic     #9                  // Field java/lang/Boolean.FALSE:Ljava/lang/Boolean;
      18: if_acmpeq     52
      21: aload_2
      22: aload_0
      23: getfield      #5                  // Field currentValue:Lnet/openhft/chronicle/engine/api/pubsub/Reference;
      26: invokeinterface #10,  1           // InterfaceMethod net/openhft/chronicle/engine/api/pubsub/Reference.get:()Ljava/lang/Object;
      31: invokeinterface #11,  2           // InterfaceMethod net/openhft/chronicle/engine/api/pubsub/Subscriber.onMessage:(Ljava/lang/Object;)V
      36: goto          52
      39: astore        4
      41: aload_0
      42: getfield      #4                  // Field subscribers:Ljava/util/Set;
      45: aload_2
      46: invokeinterface #13,  2           // InterfaceMethod java/util/Set.remove:(Ljava/lang/Object;)Z
      51: pop
      52: return
    Exception table:
       from    to  target type
          21    36    39   Class net/openhft/chronicle/engine/api/pubsub/InvalidSubscriberException

  public void unregisterSubscriber(net.openhft.chronicle.engine.api.pubsub.Subscriber);
    Code:
       0: aload_0
       1: getfield      #4                  // Field subscribers:Ljava/util/Set;
       4: aload_1
       5: invokeinterface #13,  2           // InterfaceMethod java/util/Set.remove:(Ljava/lang/Object;)Z
      10: pop
      11: aload_1
      12: invokeinterface #14,  1           // InterfaceMethod net/openhft/chronicle/engine/api/pubsub/Subscriber.onEndOfSubscription:()V
      17: return

  public int keySubscriberCount();
    Code:
       0: aload_0
       1: invokevirtual #15                 // Method subscriberCount:()I
       4: ireturn

  public int entrySubscriberCount();
    Code:
       0: iconst_0
       1: ireturn

  public int topicSubscriberCount();
    Code:
       0: iconst_0
       1: ireturn

  public int subscriberCount();
    Code:
       0: aload_0
       1: getfield      #4                  // Field subscribers:Ljava/util/Set;
       4: invokeinterface #16,  1           // InterfaceMethod java/util/Set.size:()I
       9: ireturn

  public void notifyMessage(java.lang.Object);
    Code:
       0: aload_1
       1: instanceof    #17                 // class net/openhft/chronicle/bytes/BytesStore
       4: ifeq          20
       7: aload_0
       8: getfield      #6                  // Field valueReader:Ljava/util/function/Function;
      11: aload_1
      12: invokeinterface #18,  2           // InterfaceMethod java/util/function/Function.apply:(Ljava/lang/Object;)Ljava/lang/Object;
      17: goto          21
      20: aload_1
      21: astore_2
      22: aload_0
      23: getfield      #4                  // Field subscribers:Ljava/util/Set;
      26: aload_2
      27: invokedynamic #19,  0             // InvokeDynamic #0:accept:(Ljava/lang/Object;)Lnet/openhft/chronicle/engine/api/pubsub/SubscriptionConsumer;
      32: invokestatic  #20                 // InterfaceMethod net/openhft/chronicle/engine/api/pubsub/SubscriptionConsumer.notifyEachSubscriber:(Ljava/util/Set;Lnet/openhft/chronicle/engine/api/pubsub/SubscriptionConsumer;)V
      35: goto          91
      38: astore_2
      39: getstatic     #22                 // Field LOG:Lorg/slf4j/Logger;
      42: invokeinterface #23,  1           // InterfaceMethod org/slf4j/Logger.isDebugEnabled:()Z
      47: ifeq          89
      50: invokestatic  #24                 // Method net/openhft/chronicle/core/Jvm.debug:()Lnet/openhft/chronicle/core/onoes/ExceptionHandler;
      53: aload_0
      54: invokevirtual #25                 // Method java/lang/Object.getClass:()Ljava/lang/Class;
      57: new           #26                 // class java/lang/StringBuilder
      60: dup
      61: invokespecial #27                 // Method java/lang/StringBuilder."<init>":()V
      64: ldc           #28                 // String Is
      66: invokevirtual #29                 // Method java/lang/StringBuilder.append:(Ljava/lang/String;)Ljava/lang/StringBuilder;
      69: aload_0
      70: getfield      #6                  // Field valueReader:Ljava/util/function/Function;
      73: invokevirtual #30                 // Method java/lang/StringBuilder.append:(Ljava/lang/Object;)Ljava/lang/StringBuilder;
      76: ldc           #31                 // String  the correct ValueReader?
      78: invokevirtual #29                 // Method java/lang/StringBuilder.append:(Ljava/lang/String;)Ljava/lang/StringBuilder;
      81: invokevirtual #32                 // Method java/lang/StringBuilder.toString:()Ljava/lang/String;
      84: invokeinterface #33,  3           // InterfaceMethod net/openhft/chronicle/core/onoes/ExceptionHandler.on:(Ljava/lang/Class;Ljava/lang/String;)V
      89: aload_2
      90: athrow
      91: return
    Exception table:
       from    to  target type
           0    35    38   Class java/lang/ClassCastException

  public void close();
    Code:
       0: aload_0
       1: getfield      #4                  // Field subscribers:Ljava/util/Set;
       4: invokeinterface #34,  1           // InterfaceMethod java/util/Set.iterator:()Ljava/util/Iterator;
       9: astore_1
      10: aload_1
      11: invokeinterface #35,  1           // InterfaceMethod java/util/Iterator.hasNext:()Z
      16: ifeq          55
      19: aload_1
      20: invokeinterface #36,  1           // InterfaceMethod java/util/Iterator.next:()Ljava/lang/Object;
      25: checkcast     #37                 // class net/openhft/chronicle/engine/api/pubsub/Subscriber
      28: astore_2
      29: aload_2
      30: invokeinterface #14,  1           // InterfaceMethod net/openhft/chronicle/engine/api/pubsub/Subscriber.onEndOfSubscription:()V
      35: goto          52
      38: astore_3
      39: invokestatic  #24                 // Method net/openhft/chronicle/core/Jvm.debug:()Lnet/openhft/chronicle/core/onoes/ExceptionHandler;
      42: aload_0
      43: invokevirtual #25                 // Method java/lang/Object.getClass:()Ljava/lang/Class;
      46: aload_3
      47: invokeinterface #39,  3           // InterfaceMethod net/openhft/chronicle/core/onoes/ExceptionHandler.on:(Ljava/lang/Class;Ljava/lang/Throwable;)V
      52: goto          10
      55: return
    Exception table:
       from    to  target type
          29    35    38   Class java/lang/Exception

  private static void lambda$notifyMessage$0(java.lang.Object, net.openhft.chronicle.engine.api.pubsub.Subscriber) throws net.openhft.chronicle.engine.api.pubsub.InvalidSubscriberException;
    Code:
       0: aload_1
       1: aload_0
       2: invokeinterface #11,  2           // InterfaceMethod net/openhft/chronicle/engine/api/pubsub/Subscriber.onMessage:(Ljava/lang/Object;)V
       7: return

  static {};
    Code:
       0: ldc           #40                 // class net/openhft/chronicle/engine/pubsub/MapSimpleSubscription
       2: invokestatic  #41                 // Method org/slf4j/LoggerFactory.getLogger:(Ljava/lang/Class;)Lorg/slf4j/Logger;
       5: putstatic     #22                 // Field LOG:Lorg/slf4j/Logger;
       8: return
}
