Compiled from "RemoteReference.java"
public class net.openhft.chronicle.engine.pubsub.RemoteReference<E> extends net.openhft.chronicle.network.connection.AbstractStatelessClient<net.openhft.chronicle.engine.server.internal.ReferenceHandler$EventId> implements net.openhft.chronicle.engine.api.pubsub.Reference<E> {
  private static final org.slf4j.Logger LOG;

  private final java.lang.Class<E> messageClass;

  private final java.util.Map<java.lang.Object, java.lang.Long> subscribersToTid;

  public net.openhft.chronicle.engine.pubsub.RemoteReference(net.openhft.chronicle.engine.api.tree.RequestContext, net.openhft.chronicle.engine.api.tree.Asset);
    Code:
       0: aload_0
       1: aload_2
       2: ldc           #4                  // class net/openhft/chronicle/network/connection/TcpChannelHub
       4: invokeinterface #5,  2            // InterfaceMethod net/openhft/chronicle/engine/api/tree/Asset.findView:(Ljava/lang/Class;)Ljava/lang/Object;
       9: checkcast     #4                  // class net/openhft/chronicle/network/connection/TcpChannelHub
      12: aload_1
      13: invokevirtual #6                  // Method net/openhft/chronicle/engine/api/tree/RequestContext.messageType:()Ljava/lang/Class;
      16: aload_2
      17: invokeinterface #7,  1            // InterfaceMethod net/openhft/chronicle/engine/api/tree/Asset.fullName:()Ljava/lang/String;
      22: invokespecial #8                  // Method "<init>":(Lnet/openhft/chronicle/network/connection/TcpChannelHub;Ljava/lang/Class;Ljava/lang/String;)V
      25: return

  public net.openhft.chronicle.engine.pubsub.RemoteReference(net.openhft.chronicle.network.connection.TcpChannelHub, java.lang.Class<E>, java.lang.String) throws net.openhft.chronicle.engine.api.tree.AssetNotFoundException;
    Code:
       0: aload_0
       1: aload_1
       2: lconst_0
       3: aload_3
       4: aload_2
       5: invokestatic  #9                  // Method toUri:(Ljava/lang/String;Ljava/lang/Class;)Ljava/lang/String;
       8: invokespecial #10                 // Method net/openhft/chronicle/network/connection/AbstractStatelessClient."<init>":(Lnet/openhft/chronicle/network/connection/TcpChannelHub;JLjava/lang/String;)V
      11: aload_0
      12: new           #11                 // class java/util/concurrent/ConcurrentHashMap
      15: dup
      16: invokespecial #12                 // Method java/util/concurrent/ConcurrentHashMap."<init>":()V
      19: putfield      #3                  // Field subscribersToTid:Ljava/util/Map;
      22: aload_0
      23: aload_2
      24: putfield      #1                  // Field messageClass:Ljava/lang/Class;
      27: return

  private static java.lang.String toUri(java.lang.String, java.lang.Class);
    Code:
       0: new           #13                 // class java/lang/StringBuilder
       3: dup
       4: invokespecial #14                 // Method java/lang/StringBuilder."<init>":()V
       7: astore_2
       8: aload_2
       9: aload_0
      10: invokevirtual #15                 // Method java/lang/StringBuilder.append:(Ljava/lang/String;)Ljava/lang/StringBuilder;
      13: ldc           #16                 // String ?view=reference
      15: invokevirtual #15                 // Method java/lang/StringBuilder.append:(Ljava/lang/String;)Ljava/lang/StringBuilder;
      18: pop
      19: aload_1
      20: ldc           #17                 // class java/lang/String
      22: if_acmpeq     42
      25: aload_2
      26: ldc           #18                 // String &messageType=
      28: invokevirtual #15                 // Method java/lang/StringBuilder.append:(Ljava/lang/String;)Ljava/lang/StringBuilder;
      31: getstatic     #19                 // Field net/openhft/chronicle/core/pool/ClassAliasPool.CLASS_ALIASES:Lnet/openhft/chronicle/core/pool/ClassAliasPool;
      34: aload_1
      35: invokevirtual #20                 // Method net/openhft/chronicle/core/pool/ClassAliasPool.nameFor:(Ljava/lang/Class;)Ljava/lang/String;
      38: invokevirtual #15                 // Method java/lang/StringBuilder.append:(Ljava/lang/String;)Ljava/lang/StringBuilder;
      41: pop
      42: aload_2
      43: invokevirtual #21                 // Method java/lang/StringBuilder.toString:()Ljava/lang/String;
      46: areturn

  public long set(E);
    Code:
       0: aload_0
       1: aload_1
       2: invokespecial #22                 // Method checkEvent:(Ljava/lang/Object;)V
       5: aload_0
       6: getstatic     #23                 // Field net/openhft/chronicle/engine/server/internal/ReferenceHandler$EventId.set:Lnet/openhft/chronicle/engine/server/internal/ReferenceHandler$EventId;
       9: aload_1
      10: invokedynamic #24,  0             // InvokeDynamic #0:writeValue:(Ljava/lang/Object;)Lnet/openhft/chronicle/wire/WriteValue;
      15: iconst_1
      16: invokevirtual #25                 // Method sendEventAsync:(Lnet/openhft/chronicle/wire/WireKey;Lnet/openhft/chronicle/wire/WriteValue;Z)Z
      19: pop
      20: lconst_0
      21: lreturn

  public E get();
    Code:
       0: aload_0
       1: getstatic     #26                 // Field net/openhft/chronicle/engine/server/internal/ReferenceHandler$EventId.get:Lnet/openhft/chronicle/engine/server/internal/ReferenceHandler$EventId;
       4: aconst_null
       5: aload_0
       6: getfield      #1                  // Field messageClass:Ljava/lang/Class;
       9: invokevirtual #27                 // Method proxyReturnTypedObject:(Lnet/openhft/chronicle/wire/ParameterizeWireKey;Ljava/lang/Object;Ljava/lang/Class;)Ljava/lang/Object;
      12: areturn

  public E getAndSet(E);
    Code:
       0: aload_0
       1: getstatic     #28                 // Field net/openhft/chronicle/engine/server/internal/ReferenceHandler$EventId.getAndSet:Lnet/openhft/chronicle/engine/server/internal/ReferenceHandler$EventId;
       4: aconst_null
       5: aload_0
       6: getfield      #1                  // Field messageClass:Ljava/lang/Class;
       9: iconst_1
      10: anewarray     #29                 // class java/lang/Object
      13: dup
      14: iconst_0
      15: aload_1
      16: aastore
      17: invokevirtual #30                 // Method proxyReturnTypedObject:(Lnet/openhft/chronicle/wire/ParameterizeWireKey;Ljava/lang/Object;Ljava/lang/Class;[Ljava/lang/Object;)Ljava/lang/Object;
      20: areturn

  public void remove();
    Code:
       0: aload_0
       1: getstatic     #31                 // Field net/openhft/chronicle/engine/server/internal/ReferenceHandler$EventId.remove:Lnet/openhft/chronicle/engine/server/internal/ReferenceHandler$EventId;
       4: aconst_null
       5: iconst_1
       6: invokevirtual #25                 // Method sendEventAsync:(Lnet/openhft/chronicle/wire/WireKey;Lnet/openhft/chronicle/wire/WriteValue;Z)Z
       9: pop
      10: return

  public E getAndRemove();
    Code:
       0: aload_0
       1: getstatic     #32                 // Field net/openhft/chronicle/engine/server/internal/ReferenceHandler$EventId.getAndRemove:Lnet/openhft/chronicle/engine/server/internal/ReferenceHandler$EventId;
       4: aconst_null
       5: aload_0
       6: getfield      #1                  // Field messageClass:Ljava/lang/Class;
       9: invokevirtual #27                 // Method proxyReturnTypedObject:(Lnet/openhft/chronicle/wire/ParameterizeWireKey;Ljava/lang/Object;Ljava/lang/Class;)Ljava/lang/Object;
      12: areturn

  public void unregisterSubscriber(net.openhft.chronicle.engine.api.pubsub.Subscriber);
    Code:
       0: aload_0
       1: getfield      #3                  // Field subscribersToTid:Ljava/util/Map;
       4: aload_1
       5: invokeinterface #33,  2           // InterfaceMethod java/util/Map.get:(Ljava/lang/Object;)Ljava/lang/Object;
      10: checkcast     #34                 // class java/lang/Long
      13: astore_2
      14: aload_2
      15: ifnonnull     33
      18: invokestatic  #35                 // Method net/openhft/chronicle/core/Jvm.debug:()Lnet/openhft/chronicle/core/onoes/ExceptionHandler;
      21: aload_0
      22: invokevirtual #36                 // Method java/lang/Object.getClass:()Ljava/lang/Class;
      25: ldc           #37                 // String No subscriber to unsubscribe
      27: invokeinterface #38,  3           // InterfaceMethod net/openhft/chronicle/core/onoes/ExceptionHandler.on:(Ljava/lang/Class;Ljava/lang/String;)V
      32: return
      33: aload_0
      34: getfield      #2                  // Field hub:Lnet/openhft/chronicle/network/connection/TcpChannelHub;
      37: aload_2
      38: invokevirtual #39                 // Method java/lang/Long.longValue:()J
      41: invokevirtual #40                 // Method net/openhft/chronicle/network/connection/TcpChannelHub.preventSubscribeUponReconnect:(J)V
      44: aload_0
      45: getfield      #2                  // Field hub:Lnet/openhft/chronicle/network/connection/TcpChannelHub;
      48: invokevirtual #41                 // Method net/openhft/chronicle/network/connection/TcpChannelHub.isOpen:()Z
      51: ifne          66
      54: aload_0
      55: getfield      #2                  // Field hub:Lnet/openhft/chronicle/network/connection/TcpChannelHub;
      58: aload_2
      59: invokevirtual #39                 // Method java/lang/Long.longValue:()J
      62: invokevirtual #42                 // Method net/openhft/chronicle/network/connection/TcpChannelHub.unsubscribe:(J)V
      65: return
      66: aload_0
      67: getstatic     #43                 // Field net/openhft/chronicle/engine/server/internal/ReferenceHandler$EventId.unregisterSubscriber:Lnet/openhft/chronicle/engine/server/internal/ReferenceHandler$EventId;
      70: aload_2
      71: invokedynamic #44,  0             // InvokeDynamic #1:writeValue:(Ljava/lang/Long;)Lnet/openhft/chronicle/wire/WriteValue;
      76: iconst_0
      77: invokevirtual #25                 // Method sendEventAsync:(Lnet/openhft/chronicle/wire/WireKey;Lnet/openhft/chronicle/wire/WriteValue;Z)Z
      80: pop
      81: return

  public int subscriberCount();
    Code:
       0: aload_0
       1: getstatic     #45                 // Field net/openhft/chronicle/engine/server/internal/ReferenceHandler$EventId.countSubscribers:Lnet/openhft/chronicle/engine/server/internal/ReferenceHandler$EventId;
       4: invokevirtual #46                 // Method proxyReturnInt:(Lnet/openhft/chronicle/wire/WireKey;)I
       7: ireturn

  public void registerSubscriber(boolean, int, net.openhft.chronicle.engine.api.pubsub.Subscriber) throws net.openhft.chronicle.engine.api.tree.AssetNotFoundException;
    Code:
       0: aload_0
       1: getfield      #2                  // Field hub:Lnet/openhft/chronicle/network/connection/TcpChannelHub;
       4: invokevirtual #47                 // Method net/openhft/chronicle/network/connection/TcpChannelHub.outBytesLock:()Ljava/util/concurrent/locks/ReentrantLock;
       7: invokevirtual #48                 // Method java/util/concurrent/locks/ReentrantLock.isHeldByCurrentThread:()Z
      10: ifeq          23
      13: new           #49                 // class java/lang/IllegalStateException
      16: dup
      17: ldc           #50                 // String Cannot view map while debugging
      19: invokespecial #51                 // Method java/lang/IllegalStateException."<init>":(Ljava/lang/String;)V
      22: athrow
      23: new           #52                 // class net/openhft/chronicle/engine/pubsub/RemoteReference$1
      26: dup
      27: aload_0
      28: aload_0
      29: getfield      #2                  // Field hub:Lnet/openhft/chronicle/network/connection/TcpChannelHub;
      32: new           #13                 // class java/lang/StringBuilder
      35: dup
      36: invokespecial #14                 // Method java/lang/StringBuilder."<init>":()V
      39: aload_0
      40: getfield      #53                 // Field csp:Ljava/lang/String;
      43: invokevirtual #15                 // Method java/lang/StringBuilder.append:(Ljava/lang/String;)Ljava/lang/StringBuilder;
      46: ldc           #54                 // String &bootstrap=
      48: invokevirtual #15                 // Method java/lang/StringBuilder.append:(Ljava/lang/String;)Ljava/lang/StringBuilder;
      51: iload_1
      52: invokevirtual #55                 // Method java/lang/StringBuilder.append:(Z)Ljava/lang/StringBuilder;
      55: ldc           #56                 // String &throttlePeriodMs=
      57: invokevirtual #15                 // Method java/lang/StringBuilder.append:(Ljava/lang/String;)Ljava/lang/StringBuilder;
      60: iload_2
      61: invokevirtual #57                 // Method java/lang/StringBuilder.append:(I)Ljava/lang/StringBuilder;
      64: invokevirtual #21                 // Method java/lang/StringBuilder.toString:()Ljava/lang/String;
      67: ldc           #58                 // String Remote Ref registerSubscriber
      69: aload_3
      70: invokespecial #59                 // Method net/openhft/chronicle/engine/pubsub/RemoteReference$1."<init>":(Lnet/openhft/chronicle/engine/pubsub/RemoteReference;Lnet/openhft/chronicle/network/connection/TcpChannelHub;Ljava/lang/String;Ljava/lang/String;Lnet/openhft/chronicle/engine/api/pubsub/Subscriber;)V
      73: astore        4
      75: aload_0
      76: getfield      #2                  // Field hub:Lnet/openhft/chronicle/network/connection/TcpChannelHub;
      79: aload         4
      81: invokevirtual #60                 // Method net/openhft/chronicle/network/connection/TcpChannelHub.subscribe:(Lnet/openhft/chronicle/network/connection/AsyncSubscription;)V
      84: return

  public java.lang.Class getType();
    Code:
       0: aload_0
       1: getfield      #1                  // Field messageClass:Ljava/lang/Class;
       4: areturn

  void onEvent(E, net.openhft.chronicle.engine.api.pubsub.Subscriber<E>);
    Code:
       0: aload_1
       1: ifnonnull     5
       4: return
       5: aload_2
       6: aload_1
       7: invokeinterface #61,  2           // InterfaceMethod net/openhft/chronicle/engine/api/pubsub/Subscriber.onMessage:(Ljava/lang/Object;)V
      12: goto          21
      15: astore_3
      16: aload_0
      17: aload_2
      18: invokevirtual #63                 // Method unregisterSubscriber:(Lnet/openhft/chronicle/engine/api/pubsub/Subscriber;)V
      21: return
    Exception table:
       from    to  target type
           5    12    15   Class net/openhft/chronicle/engine/api/pubsub/InvalidSubscriberException

  private void checkEvent(java.lang.Object);
    Code:
       0: aload_1
       1: ifnonnull     14
       4: new           #64                 // class java/lang/NullPointerException
       7: dup
       8: ldc           #65                 // String event can not be null
      10: invokespecial #66                 // Method java/lang/NullPointerException."<init>":(Ljava/lang/String;)V
      13: athrow
      14: return

  public <R> R applyTo(net.openhft.chronicle.core.util.SerializableFunction<E, R>);
    Code:
       0: aload_0
       1: aload_1
       2: invokedynamic #67,  0             // InvokeDynamic #2:apply:(Lnet/openhft/chronicle/core/util/SerializableFunction;)Lnet/openhft/chronicle/core/util/SerializableBiFunction;
       7: aconst_null
       8: invokevirtual #68                 // Method applyTo:(Lnet/openhft/chronicle/core/util/SerializableBiFunction;Ljava/lang/Object;)Ljava/lang/Object;
      11: areturn

  public void asyncUpdate(net.openhft.chronicle.core.util.SerializableFunction<E, E>);
    Code:
       0: aload_0
       1: aload_1
       2: invokedynamic #69,  0             // InvokeDynamic #3:apply:(Lnet/openhft/chronicle/core/util/SerializableFunction;)Lnet/openhft/chronicle/core/util/SerializableBiFunction;
       7: aconst_null
       8: invokevirtual #70                 // Method asyncUpdate:(Lnet/openhft/chronicle/core/util/SerializableBiFunction;Ljava/lang/Object;)V
      11: return

  public <R> R syncUpdate(net.openhft.chronicle.core.util.SerializableFunction<E, E>, net.openhft.chronicle.core.util.SerializableFunction<E, R>);
    Code:
       0: aload_0
       1: aload_1
       2: invokedynamic #71,  0             // InvokeDynamic #4:apply:(Lnet/openhft/chronicle/core/util/SerializableFunction;)Lnet/openhft/chronicle/core/util/SerializableBiFunction;
       7: aconst_null
       8: aload_2
       9: invokedynamic #72,  0             // InvokeDynamic #5:apply:(Lnet/openhft/chronicle/core/util/SerializableFunction;)Lnet/openhft/chronicle/core/util/SerializableBiFunction;
      14: aconst_null
      15: invokevirtual #73                 // Method syncUpdate:(Lnet/openhft/chronicle/core/util/SerializableBiFunction;Ljava/lang/Object;Lnet/openhft/chronicle/core/util/SerializableBiFunction;Ljava/lang/Object;)Ljava/lang/Object;
      18: areturn

  public <T, R> R applyTo(net.openhft.chronicle.core.util.SerializableBiFunction<E, T, R>, T);
    Code:
       0: aload_0
       1: getstatic     #74                 // Field net/openhft/chronicle/engine/server/internal/ReferenceHandler$EventId.applyTo2:Lnet/openhft/chronicle/engine/server/internal/ReferenceHandler$EventId;
       4: aconst_null
       5: ldc           #29                 // class java/lang/Object
       7: iconst_2
       8: anewarray     #29                 // class java/lang/Object
      11: dup
      12: iconst_0
      13: aload_1
      14: aastore
      15: dup
      16: iconst_1
      17: aload_2
      18: aastore
      19: invokespecial #75                 // Method net/openhft/chronicle/network/connection/AbstractStatelessClient.proxyReturnTypedObject:(Lnet/openhft/chronicle/wire/ParameterizeWireKey;Ljava/lang/Object;Ljava/lang/Class;[Ljava/lang/Object;)Ljava/lang/Object;
      22: areturn

  public <T> void asyncUpdate(net.openhft.chronicle.core.util.SerializableBiFunction<E, T, E>, T);
    Code:
       0: aload_0
       1: getstatic     #76                 // Field net/openhft/chronicle/engine/server/internal/ReferenceHandler$EventId.update2:Lnet/openhft/chronicle/engine/server/internal/ReferenceHandler$EventId;
       4: getstatic     #76                 // Field net/openhft/chronicle/engine/server/internal/ReferenceHandler$EventId.update2:Lnet/openhft/chronicle/engine/server/internal/ReferenceHandler$EventId;
       7: iconst_2
       8: anewarray     #29                 // class java/lang/Object
      11: dup
      12: iconst_0
      13: aload_1
      14: aastore
      15: dup
      16: iconst_1
      17: aload_2
      18: aastore
      19: invokestatic  #77                 // Method toParameters:(Lnet/openhft/chronicle/wire/ParameterizeWireKey;[Ljava/lang/Object;)Lnet/openhft/chronicle/wire/WriteValue;
      22: iconst_1
      23: invokevirtual #25                 // Method sendEventAsync:(Lnet/openhft/chronicle/wire/WireKey;Lnet/openhft/chronicle/wire/WriteValue;Z)Z
      26: pop
      27: return

  public <UT, RT, R> R syncUpdate(net.openhft.chronicle.core.util.SerializableBiFunction<E, UT, E>, UT, net.openhft.chronicle.core.util.SerializableBiFunction<E, RT, R>, RT);
    Code:
       0: aload_0
       1: getstatic     #78                 // Field net/openhft/chronicle/engine/server/internal/ReferenceHandler$EventId.update4:Lnet/openhft/chronicle/engine/server/internal/ReferenceHandler$EventId;
       4: aconst_null
       5: ldc           #29                 // class java/lang/Object
       7: iconst_4
       8: anewarray     #29                 // class java/lang/Object
      11: dup
      12: iconst_0
      13: aload_1
      14: aastore
      15: dup
      16: iconst_1
      17: aload_2
      18: aastore
      19: dup
      20: iconst_2
      21: aload_3
      22: aastore
      23: dup
      24: iconst_3
      25: aload         4
      27: aastore
      28: invokevirtual #30                 // Method proxyReturnTypedObject:(Lnet/openhft/chronicle/wire/ParameterizeWireKey;Ljava/lang/Object;Ljava/lang/Class;[Ljava/lang/Object;)Ljava/lang/Object;
      31: areturn

  private static java.lang.Object $deserializeLambda$(java.lang.invoke.SerializedLambda);
    Code:
       0: aload_0
       1: invokevirtual #79                 // Method java/lang/invoke/SerializedLambda.getImplMethodName:()Ljava/lang/String;
       4: astore_1
       5: iconst_m1
       6: istore_2
       7: aload_1
       8: invokevirtual #80                 // Method java/lang/String.hashCode:()I
      11: lookupswitch  { // 4
           -1579726239: 66
            -119307334: 80
             -85346231: 52
            1986940097: 94
               default: 105
          }
      52: aload_1
      53: ldc           #81                 // String lambda$syncUpdate$75f16b37$1
      55: invokevirtual #82                 // Method java/lang/String.equals:(Ljava/lang/Object;)Z
      58: ifeq          105
      61: iconst_0
      62: istore_2
      63: goto          105
      66: aload_1
      67: ldc           #83                 // String lambda$asyncUpdate$45e507bb$1
      69: invokevirtual #82                 // Method java/lang/String.equals:(Ljava/lang/Object;)Z
      72: ifeq          105
      75: iconst_1
      76: istore_2
      77: goto          105
      80: aload_1
      81: ldc           #84                 // String lambda$syncUpdate$85f688eb$1
      83: invokevirtual #82                 // Method java/lang/String.equals:(Ljava/lang/Object;)Z
      86: ifeq          105
      89: iconst_2
      90: istore_2
      91: goto          105
      94: aload_1
      95: ldc           #85                 // String lambda$applyTo$b415815b$1
      97: invokevirtual #82                 // Method java/lang/String.equals:(Ljava/lang/Object;)Z
     100: ifeq          105
     103: iconst_3
     104: istore_2
     105: iload_2
     106: tableswitch   { // 0 to 3
                     0: 136
                     1: 219
                     2: 302
                     3: 385
               default: 468
          }
     136: aload_0
     137: invokevirtual #86                 // Method java/lang/invoke/SerializedLambda.getImplMethodKind:()I
     140: bipush        6
     142: if_icmpne     468
     145: aload_0
     146: invokevirtual #87                 // Method java/lang/invoke/SerializedLambda.getFunctionalInterfaceClass:()Ljava/lang/String;
     149: ldc           #88                 // String net/openhft/chronicle/core/util/SerializableBiFunction
     151: invokevirtual #89                 // Method java/lang/Object.equals:(Ljava/lang/Object;)Z
     154: ifeq          468
     157: aload_0
     158: invokevirtual #90                 // Method java/lang/invoke/SerializedLambda.getFunctionalInterfaceMethodName:()Ljava/lang/String;
     161: ldc           #91                 // String apply
     163: invokevirtual #89                 // Method java/lang/Object.equals:(Ljava/lang/Object;)Z
     166: ifeq          468
     169: aload_0
     170: invokevirtual #92                 // Method java/lang/invoke/SerializedLambda.getFunctionalInterfaceMethodSignature:()Ljava/lang/String;
     173: ldc           #93                 // String (Ljava/lang/Object;Ljava/lang/Object;)Ljava/lang/Object;
     175: invokevirtual #89                 // Method java/lang/Object.equals:(Ljava/lang/Object;)Z
     178: ifeq          468
     181: aload_0
     182: invokevirtual #94                 // Method java/lang/invoke/SerializedLambda.getImplClass:()Ljava/lang/String;
     185: ldc           #95                 // String net/openhft/chronicle/engine/pubsub/RemoteReference
     187: invokevirtual #89                 // Method java/lang/Object.equals:(Ljava/lang/Object;)Z
     190: ifeq          468
     193: aload_0
     194: invokevirtual #96                 // Method java/lang/invoke/SerializedLambda.getImplMethodSignature:()Ljava/lang/String;
     197: ldc           #97                 // String (Lnet/openhft/chronicle/core/util/SerializableFunction;Ljava/lang/Object;Ljava/lang/Object;)Ljava/lang/Object;
     199: invokevirtual #89                 // Method java/lang/Object.equals:(Ljava/lang/Object;)Z
     202: ifeq          468
     205: aload_0
     206: iconst_0
     207: invokevirtual #98                 // Method java/lang/invoke/SerializedLambda.getCapturedArg:(I)Ljava/lang/Object;
     210: checkcast     #99                 // class net/openhft/chronicle/core/util/SerializableFunction
     213: invokedynamic #72,  0             // InvokeDynamic #5:apply:(Lnet/openhft/chronicle/core/util/SerializableFunction;)Lnet/openhft/chronicle/core/util/SerializableBiFunction;
     218: areturn
     219: aload_0
     220: invokevirtual #86                 // Method java/lang/invoke/SerializedLambda.getImplMethodKind:()I
     223: bipush        6
     225: if_icmpne     468
     228: aload_0
     229: invokevirtual #87                 // Method java/lang/invoke/SerializedLambda.getFunctionalInterfaceClass:()Ljava/lang/String;
     232: ldc           #88                 // String net/openhft/chronicle/core/util/SerializableBiFunction
     234: invokevirtual #89                 // Method java/lang/Object.equals:(Ljava/lang/Object;)Z
     237: ifeq          468
     240: aload_0
     241: invokevirtual #90                 // Method java/lang/invoke/SerializedLambda.getFunctionalInterfaceMethodName:()Ljava/lang/String;
     244: ldc           #91                 // String apply
     246: invokevirtual #89                 // Method java/lang/Object.equals:(Ljava/lang/Object;)Z
     249: ifeq          468
     252: aload_0
     253: invokevirtual #92                 // Method java/lang/invoke/SerializedLambda.getFunctionalInterfaceMethodSignature:()Ljava/lang/String;
     256: ldc           #93                 // String (Ljava/lang/Object;Ljava/lang/Object;)Ljava/lang/Object;
     258: invokevirtual #89                 // Method java/lang/Object.equals:(Ljava/lang/Object;)Z
     261: ifeq          468
     264: aload_0
     265: invokevirtual #94                 // Method java/lang/invoke/SerializedLambda.getImplClass:()Ljava/lang/String;
     268: ldc           #95                 // String net/openhft/chronicle/engine/pubsub/RemoteReference
     270: invokevirtual #89                 // Method java/lang/Object.equals:(Ljava/lang/Object;)Z
     273: ifeq          468
     276: aload_0
     277: invokevirtual #96                 // Method java/lang/invoke/SerializedLambda.getImplMethodSignature:()Ljava/lang/String;
     280: ldc           #97                 // String (Lnet/openhft/chronicle/core/util/SerializableFunction;Ljava/lang/Object;Ljava/lang/Object;)Ljava/lang/Object;
     282: invokevirtual #89                 // Method java/lang/Object.equals:(Ljava/lang/Object;)Z
     285: ifeq          468
     288: aload_0
     289: iconst_0
     290: invokevirtual #98                 // Method java/lang/invoke/SerializedLambda.getCapturedArg:(I)Ljava/lang/Object;
     293: checkcast     #99                 // class net/openhft/chronicle/core/util/SerializableFunction
     296: invokedynamic #69,  0             // InvokeDynamic #3:apply:(Lnet/openhft/chronicle/core/util/SerializableFunction;)Lnet/openhft/chronicle/core/util/SerializableBiFunction;
     301: areturn
     302: aload_0
     303: invokevirtual #86                 // Method java/lang/invoke/SerializedLambda.getImplMethodKind:()I
     306: bipush        6
     308: if_icmpne     468
     311: aload_0
     312: invokevirtual #87                 // Method java/lang/invoke/SerializedLambda.getFunctionalInterfaceClass:()Ljava/lang/String;
     315: ldc           #88                 // String net/openhft/chronicle/core/util/SerializableBiFunction
     317: invokevirtual #89                 // Method java/lang/Object.equals:(Ljava/lang/Object;)Z
     320: ifeq          468
     323: aload_0
     324: invokevirtual #90                 // Method java/lang/invoke/SerializedLambda.getFunctionalInterfaceMethodName:()Ljava/lang/String;
     327: ldc           #91                 // String apply
     329: invokevirtual #89                 // Method java/lang/Object.equals:(Ljava/lang/Object;)Z
     332: ifeq          468
     335: aload_0
     336: invokevirtual #92                 // Method java/lang/invoke/SerializedLambda.getFunctionalInterfaceMethodSignature:()Ljava/lang/String;
     339: ldc           #93                 // String (Ljava/lang/Object;Ljava/lang/Object;)Ljava/lang/Object;
     341: invokevirtual #89                 // Method java/lang/Object.equals:(Ljava/lang/Object;)Z
     344: ifeq          468
     347: aload_0
     348: invokevirtual #94                 // Method java/lang/invoke/SerializedLambda.getImplClass:()Ljava/lang/String;
     351: ldc           #95                 // String net/openhft/chronicle/engine/pubsub/RemoteReference
     353: invokevirtual #89                 // Method java/lang/Object.equals:(Ljava/lang/Object;)Z
     356: ifeq          468
     359: aload_0
     360: invokevirtual #96                 // Method java/lang/invoke/SerializedLambda.getImplMethodSignature:()Ljava/lang/String;
     363: ldc           #97                 // String (Lnet/openhft/chronicle/core/util/SerializableFunction;Ljava/lang/Object;Ljava/lang/Object;)Ljava/lang/Object;
     365: invokevirtual #89                 // Method java/lang/Object.equals:(Ljava/lang/Object;)Z
     368: ifeq          468
     371: aload_0
     372: iconst_0
     373: invokevirtual #98                 // Method java/lang/invoke/SerializedLambda.getCapturedArg:(I)Ljava/lang/Object;
     376: checkcast     #99                 // class net/openhft/chronicle/core/util/SerializableFunction
     379: invokedynamic #71,  0             // InvokeDynamic #4:apply:(Lnet/openhft/chronicle/core/util/SerializableFunction;)Lnet/openhft/chronicle/core/util/SerializableBiFunction;
     384: areturn
     385: aload_0
     386: invokevirtual #86                 // Method java/lang/invoke/SerializedLambda.getImplMethodKind:()I
     389: bipush        6
     391: if_icmpne     468
     394: aload_0
     395: invokevirtual #87                 // Method java/lang/invoke/SerializedLambda.getFunctionalInterfaceClass:()Ljava/lang/String;
     398: ldc           #88                 // String net/openhft/chronicle/core/util/SerializableBiFunction
     400: invokevirtual #89                 // Method java/lang/Object.equals:(Ljava/lang/Object;)Z
     403: ifeq          468
     406: aload_0
     407: invokevirtual #90                 // Method java/lang/invoke/SerializedLambda.getFunctionalInterfaceMethodName:()Ljava/lang/String;
     410: ldc           #91                 // String apply
     412: invokevirtual #89                 // Method java/lang/Object.equals:(Ljava/lang/Object;)Z
     415: ifeq          468
     418: aload_0
     419: invokevirtual #92                 // Method java/lang/invoke/SerializedLambda.getFunctionalInterfaceMethodSignature:()Ljava/lang/String;
     422: ldc           #93                 // String (Ljava/lang/Object;Ljava/lang/Object;)Ljava/lang/Object;
     424: invokevirtual #89                 // Method java/lang/Object.equals:(Ljava/lang/Object;)Z
     427: ifeq          468
     430: aload_0
     431: invokevirtual #94                 // Method java/lang/invoke/SerializedLambda.getImplClass:()Ljava/lang/String;
     434: ldc           #95                 // String net/openhft/chronicle/engine/pubsub/RemoteReference
     436: invokevirtual #89                 // Method java/lang/Object.equals:(Ljava/lang/Object;)Z
     439: ifeq          468
     442: aload_0
     443: invokevirtual #96                 // Method java/lang/invoke/SerializedLambda.getImplMethodSignature:()Ljava/lang/String;
     446: ldc           #97                 // String (Lnet/openhft/chronicle/core/util/SerializableFunction;Ljava/lang/Object;Ljava/lang/Object;)Ljava/lang/Object;
     448: invokevirtual #89                 // Method java/lang/Object.equals:(Ljava/lang/Object;)Z
     451: ifeq          468
     454: aload_0
     455: iconst_0
     456: invokevirtual #98                 // Method java/lang/invoke/SerializedLambda.getCapturedArg:(I)Ljava/lang/Object;
     459: checkcast     #99                 // class net/openhft/chronicle/core/util/SerializableFunction
     462: invokedynamic #67,  0             // InvokeDynamic #2:apply:(Lnet/openhft/chronicle/core/util/SerializableFunction;)Lnet/openhft/chronicle/core/util/SerializableBiFunction;
     467: areturn
     468: new           #100                // class java/lang/IllegalArgumentException
     471: dup
     472: ldc           #101                // String Invalid lambda deserialization
     474: invokespecial #102                // Method java/lang/IllegalArgumentException."<init>":(Ljava/lang/String;)V
     477: athrow

  private static java.lang.Object lambda$syncUpdate$75f16b37$1(net.openhft.chronicle.core.util.SerializableFunction, java.lang.Object, java.lang.Object);
    Code:
       0: aload_0
       1: aload_1
       2: invokeinterface #103,  2          // InterfaceMethod net/openhft/chronicle/core/util/SerializableFunction.apply:(Ljava/lang/Object;)Ljava/lang/Object;
       7: areturn

  private static java.lang.Object lambda$syncUpdate$85f688eb$1(net.openhft.chronicle.core.util.SerializableFunction, java.lang.Object, java.lang.Object);
    Code:
       0: aload_0
       1: aload_1
       2: invokeinterface #103,  2          // InterfaceMethod net/openhft/chronicle/core/util/SerializableFunction.apply:(Ljava/lang/Object;)Ljava/lang/Object;
       7: areturn

  private static java.lang.Object lambda$asyncUpdate$45e507bb$1(net.openhft.chronicle.core.util.SerializableFunction, java.lang.Object, java.lang.Object);
    Code:
       0: aload_0
       1: aload_1
       2: invokeinterface #103,  2          // InterfaceMethod net/openhft/chronicle/core/util/SerializableFunction.apply:(Ljava/lang/Object;)Ljava/lang/Object;
       7: areturn

  private static java.lang.Object lambda$applyTo$b415815b$1(net.openhft.chronicle.core.util.SerializableFunction, java.lang.Object, java.lang.Object);
    Code:
       0: aload_0
       1: aload_1
       2: invokeinterface #103,  2          // InterfaceMethod net/openhft/chronicle/core/util/SerializableFunction.apply:(Ljava/lang/Object;)Ljava/lang/Object;
       7: areturn

  private static void lambda$unregisterSubscriber$1(java.lang.Long, net.openhft.chronicle.wire.ValueOut);
    Code:
       0: aload_1
       1: aload_0
       2: invokevirtual #39                 // Method java/lang/Long.longValue:()J
       5: invokeinterface #104,  3          // InterfaceMethod net/openhft/chronicle/wire/ValueOut.int64:(J)Lnet/openhft/chronicle/wire/WireOut;
      10: pop
      11: return

  private static void lambda$set$0(java.lang.Object, net.openhft.chronicle.wire.ValueOut);
    Code:
       0: aload_1
       1: aload_0
       2: invokeinterface #105,  2          // InterfaceMethod net/openhft/chronicle/wire/ValueOut.object:(Ljava/lang/Object;)Lnet/openhft/chronicle/wire/WireOut;
       7: pop
       8: return

  static java.util.Map access$000(net.openhft.chronicle.engine.pubsub.RemoteReference);
    Code:
       0: aload_0
       1: getfield      #3                  // Field subscribersToTid:Ljava/util/Map;
       4: areturn

  static net.openhft.chronicle.network.connection.TcpChannelHub access$100(net.openhft.chronicle.engine.pubsub.RemoteReference);
    Code:
       0: aload_0
       1: getfield      #2                  // Field hub:Lnet/openhft/chronicle/network/connection/TcpChannelHub;
       4: areturn

  static java.lang.Class access$200(net.openhft.chronicle.engine.pubsub.RemoteReference);
    Code:
       0: aload_0
       1: getfield      #1                  // Field messageClass:Ljava/lang/Class;
       4: areturn

  static {};
    Code:
       0: ldc           #106                // class net/openhft/chronicle/engine/server/internal/ReferenceHandler
       2: invokestatic  #107                // Method org/slf4j/LoggerFactory.getLogger:(Ljava/lang/Class;)Lorg/slf4j/Logger;
       5: putstatic     #108                // Field LOG:Lorg/slf4j/Logger;
       8: return
}
