Compiled from "BlankNodeAllocatorFixedSeedHash.java"
public class org.apache.jena.riot.lang.BlankNodeAllocatorFixedSeedHash extends org.apache.jena.riot.lang.BlankNodeAllocatorHash {
  private java.util.UUID seed;

  public org.apache.jena.riot.lang.BlankNodeAllocatorFixedSeedHash();
    Code:
       0: aload_0
       1: invokestatic  #1                  // Method java/util/UUID.randomUUID:()Ljava/util/UUID;
       4: invokespecial #2                  // Method "<init>":(Ljava/util/UUID;)V
       7: return

  public org.apache.jena.riot.lang.BlankNodeAllocatorFixedSeedHash(java.util.UUID);
    Code:
       0: aload_0
       1: invokespecial #3                  // Method org/apache/jena/riot/lang/BlankNodeAllocatorHash."<init>":()V
       4: aload_1
       5: ifnonnull     18
       8: new           #4                  // class java/lang/NullPointerException
      11: dup
      12: ldc           #5                  // String seed cannot be null
      14: invokespecial #6                  // Method java/lang/NullPointerException."<init>":(Ljava/lang/String;)V
      17: athrow
      18: aload_0
      19: aload_1
      20: putfield      #7                  // Field seed:Ljava/util/UUID;
      23: aload_0
      24: invokevirtual #8                  // Method reset:()V
      27: return

  protected java.util.UUID freshSeed();
    Code:
       0: aload_0
       1: getfield      #7                  // Field seed:Ljava/util/UUID;
       4: ifnonnull     13
       7: invokestatic  #1                  // Method java/util/UUID.randomUUID:()Ljava/util/UUID;
      10: goto          17
      13: aload_0
      14: getfield      #7                  // Field seed:Ljava/util/UUID;
      17: areturn
}
