Compiled from "PersistenceManager.scala"
public class blended.persistence.internal.PersistenceManager extends blended.akka.OSGIActor implements blended.akka.MemoryStash {
  public final blended.persistence.PersistenceBackend blended$persistence$internal$PersistenceManager$$backend;

  private final scala.collection.mutable.ListBuffer<scala.Tuple2<akka.actor.ActorRef, java.lang.Object>> requests;

  public static akka.actor.Props props(blended.akka.OSGIActorConfig, blended.persistence.PersistenceBackend);
    Code:
       0: getstatic     #18                 // Field blended/persistence/internal/PersistenceManager$.MODULE$:Lblended/persistence/internal/PersistenceManager$;
       3: aload_0
       4: aload_1
       5: invokevirtual #20                 // Method blended/persistence/internal/PersistenceManager$.props:(Lblended/akka/OSGIActorConfig;Lblended/persistence/PersistenceBackend;)Lakka/actor/Props;
       8: areturn

  public scala.collection.mutable.ListBuffer<scala.Tuple2<akka.actor.ActorRef, java.lang.Object>> requests();
    Code:
       0: aload_0
       1: getfield      #28                 // Field requests:Lscala/collection/mutable/ListBuffer;
       4: areturn

  public void blended$akka$MemoryStash$_setter_$requests_$eq(scala.collection.mutable.ListBuffer);
    Code:
       0: aload_0
       1: aload_1
       2: putfield      #28                 // Field requests:Lscala/collection/mutable/ListBuffer;
       5: return

  public scala.PartialFunction<java.lang.Object, scala.runtime.BoxedUnit> stashing();
    Code:
       0: aload_0
       1: invokestatic  #40                 // Method blended/akka/MemoryStash$class.stashing:(Lblended/akka/MemoryStash;)Lscala/PartialFunction;
       4: areturn

  public void unstash();
    Code:
       0: aload_0
       1: invokestatic  #45                 // Method blended/akka/MemoryStash$class.unstash:(Lblended/akka/MemoryStash;)V
       4: return

  public scala.PartialFunction<java.lang.Object, scala.runtime.BoxedUnit> receive();
    Code:
       0: aload_0
       1: getstatic     #51                 // Field scala/collection/immutable/List$.MODULE$:Lscala/collection/immutable/List$;
       4: invokevirtual #55                 // Method scala/collection/immutable/List$.empty:()Lscala/collection/immutable/List;
       7: invokevirtual #59                 // Method working:(Lscala/collection/immutable/List;)Lscala/PartialFunction;
      10: areturn

  public scala.PartialFunction<java.lang.Object, scala.runtime.BoxedUnit> working(scala.collection.immutable.List<akka.actor.ActorRef>);
    Code:
       0: getstatic     #64                 // Field akka/event/LoggingReceive$.MODULE$:Lakka/event/LoggingReceive$;
       3: new           #66                 // class blended/persistence/internal/PersistenceManager$$anonfun$working$1
       6: dup
       7: aload_0
       8: aload_1
       9: invokespecial #70                 // Method blended/persistence/internal/PersistenceManager$$anonfun$working$1."<init>":(Lblended/persistence/internal/PersistenceManager;Lscala/collection/immutable/List;)V
      12: aload_0
      13: invokevirtual #74                 // Method context:()Lakka/actor/ActorContext;
      16: invokevirtual #78                 // Method akka/event/LoggingReceive$.apply:(Lscala/PartialFunction;Lakka/actor/ActorContext;)Lscala/PartialFunction;
      19: areturn

  public void postStop();
    Code:
       0: aload_0
       1: getfield      #83                 // Field blended$persistence$internal$PersistenceManager$$backend:Lblended/persistence/PersistenceBackend;
       4: invokeinterface #88,  1           // InterfaceMethod blended/persistence/PersistenceBackend.shutdownBackend:()V
       9: return

  public blended.persistence.internal.PersistenceManager(blended.akka.OSGIActorConfig, blended.persistence.PersistenceBackend);
    Code:
       0: aload_0
       1: aload_2
       2: putfield      #83                 // Field blended$persistence$internal$PersistenceManager$$backend:Lblended/persistence/PersistenceBackend;
       5: aload_0
       6: aload_1
       7: invokespecial #92                 // Method blended/akka/OSGIActor."<init>":(Lblended/akka/OSGIActorConfig;)V
      10: aload_0
      11: invokestatic  #95                 // Method blended/akka/MemoryStash$class.$init$:(Lblended/akka/MemoryStash;)V
      14: return
}
