Compiled from "EC2MetadataClient.java"
public class com.amazonaws.internal.EC2MetadataClient {
  private static final java.lang.String EC2_METADATA_SERVICE_URL;

  public static final java.lang.String SECURITY_CREDENTIALS_RESOURCE;

  private static final org.apache.commons.logging.Log log;

  public com.amazonaws.internal.EC2MetadataClient();
    Code:
       0: aload_0
       1: invokespecial #2                  // Method java/lang/Object."<init>":()V
       4: return

  public java.lang.String getDefaultCredentials() throws java.io.IOException;
    Code:
       0: aload_0
       1: ldc           #4                  // String /latest/meta-data/iam/security-credentials/
       3: invokevirtual #5                  // Method readResource:(Ljava/lang/String;)Ljava/lang/String;
       6: astore_1
       7: aload_1
       8: invokevirtual #6                  // Method java/lang/String.trim:()Ljava/lang/String;
      11: astore_1
      12: aload_1
      13: ldc           #7                  // String \n
      15: invokevirtual #8                  // Method java/lang/String.split:(Ljava/lang/String;)[Ljava/lang/String;
      18: astore_2
      19: aload_2
      20: arraylength
      21: ifne          26
      24: aconst_null
      25: areturn
      26: aload_2
      27: iconst_0
      28: aaload
      29: astore_3
      30: aload_0
      31: new           #9                  // class java/lang/StringBuilder
      34: dup
      35: invokespecial #10                 // Method java/lang/StringBuilder."<init>":()V
      38: ldc           #4                  // String /latest/meta-data/iam/security-credentials/
      40: invokevirtual #11                 // Method java/lang/StringBuilder.append:(Ljava/lang/String;)Ljava/lang/StringBuilder;
      43: aload_3
      44: invokevirtual #11                 // Method java/lang/StringBuilder.append:(Ljava/lang/String;)Ljava/lang/StringBuilder;
      47: invokevirtual #12                 // Method java/lang/StringBuilder.toString:()Ljava/lang/String;
      50: invokevirtual #5                  // Method readResource:(Ljava/lang/String;)Ljava/lang/String;
      53: areturn

  public java.lang.String readResource(java.lang.String) throws java.io.IOException, com.amazonaws.AmazonClientException;
    Code:
       0: aload_0
       1: aload_1
       2: invokespecial #13                 // Method getEc2MetadataServiceUrlForResource:(Ljava/lang/String;)Ljava/net/URL;
       5: astore_2
       6: getstatic     #14                 // Field log:Lorg/apache/commons/logging/Log;
       9: new           #9                  // class java/lang/StringBuilder
      12: dup
      13: invokespecial #10                 // Method java/lang/StringBuilder."<init>":()V
      16: ldc           #15                 // String Connecting to EC2 instance metadata service at URL:
      18: invokevirtual #11                 // Method java/lang/StringBuilder.append:(Ljava/lang/String;)Ljava/lang/StringBuilder;
      21: aload_2
      22: invokevirtual #16                 // Method java/net/URL.toString:()Ljava/lang/String;
      25: invokevirtual #11                 // Method java/lang/StringBuilder.append:(Ljava/lang/String;)Ljava/lang/StringBuilder;
      28: invokevirtual #12                 // Method java/lang/StringBuilder.toString:()Ljava/lang/String;
      31: invokeinterface #17,  2           // InterfaceMethod org/apache/commons/logging/Log.debug:(Ljava/lang/Object;)V
      36: aload_2
      37: invokevirtual #18                 // Method java/net/URL.openConnection:()Ljava/net/URLConnection;
      40: checkcast     #19                 // class java/net/HttpURLConnection
      43: astore_3
      44: aload_3
      45: sipush        2000
      48: invokevirtual #20                 // Method java/net/HttpURLConnection.setConnectTimeout:(I)V
      51: aload_3
      52: sipush        5000
      55: invokevirtual #21                 // Method java/net/HttpURLConnection.setReadTimeout:(I)V
      58: aload_3
      59: ldc           #22                 // String GET
      61: invokevirtual #23                 // Method java/net/HttpURLConnection.setRequestMethod:(Ljava/lang/String;)V
      64: aload_3
      65: iconst_1
      66: invokevirtual #24                 // Method java/net/HttpURLConnection.setDoOutput:(Z)V
      69: aload_3
      70: invokevirtual #25                 // Method java/net/HttpURLConnection.connect:()V
      73: aload_0
      74: aload_3
      75: invokespecial #26                 // Method readResponse:(Ljava/net/HttpURLConnection;)Ljava/lang/String;
      78: areturn

  private java.lang.String readResponse(java.net.HttpURLConnection) throws java.io.IOException;
    Code:
       0: aload_1
       1: invokevirtual #27                 // Method java/net/HttpURLConnection.getResponseCode:()I
       4: sipush        404
       7: if_icmpne     40
      10: new           #28                 // class com/amazonaws/AmazonClientException
      13: dup
      14: new           #9                  // class java/lang/StringBuilder
      17: dup
      18: invokespecial #10                 // Method java/lang/StringBuilder."<init>":()V
      21: ldc           #29                 // String The requested metadata is not found at
      23: invokevirtual #11                 // Method java/lang/StringBuilder.append:(Ljava/lang/String;)Ljava/lang/StringBuilder;
      26: aload_1
      27: invokevirtual #30                 // Method java/net/HttpURLConnection.getURL:()Ljava/net/URL;
      30: invokevirtual #31                 // Method java/lang/StringBuilder.append:(Ljava/lang/Object;)Ljava/lang/StringBuilder;
      33: invokevirtual #12                 // Method java/lang/StringBuilder.toString:()Ljava/lang/String;
      36: invokespecial #32                 // Method com/amazonaws/AmazonClientException."<init>":(Ljava/lang/String;)V
      39: athrow
      40: aload_1
      41: invokevirtual #33                 // Method java/net/HttpURLConnection.getInputStream:()Ljava/io/InputStream;
      44: astore_2
      45: new           #9                  // class java/lang/StringBuilder
      48: dup
      49: invokespecial #10                 // Method java/lang/StringBuilder."<init>":()V
      52: astore_3
      53: aload_2
      54: invokevirtual #34                 // Method java/io/InputStream.read:()I
      57: istore        4
      59: iload         4
      61: iconst_m1
      62: if_icmpne     68
      65: goto          79
      68: aload_3
      69: iload         4
      71: i2c
      72: invokevirtual #35                 // Method java/lang/StringBuilder.append:(C)Ljava/lang/StringBuilder;
      75: pop
      76: goto          53
      79: aload_3
      80: invokevirtual #12                 // Method java/lang/StringBuilder.toString:()Ljava/lang/String;
      83: astore        4
      85: aload_2
      86: invokevirtual #36                 // Method java/io/InputStream.close:()V
      89: aload         4
      91: areturn
      92: astore        5
      94: aload_2
      95: invokevirtual #36                 // Method java/io/InputStream.close:()V
      98: aload         5
     100: athrow
    Exception table:
       from    to  target type
          45    85    92   any
          92    94    92   any

  private java.net.URL getEc2MetadataServiceUrlForResource(java.lang.String) throws java.io.IOException;
    Code:
       0: ldc           #37                 // String http://169.254.169.254
       2: astore_2
       3: ldc           #38                 // String com.amazonaws.sdk.ec2MetadataServiceEndpointOverride
       5: invokestatic  #39                 // Method java/lang/System.getProperty:(Ljava/lang/String;)Ljava/lang/String;
       8: ifnull        17
      11: ldc           #38                 // String com.amazonaws.sdk.ec2MetadataServiceEndpointOverride
      13: invokestatic  #39                 // Method java/lang/System.getProperty:(Ljava/lang/String;)Ljava/lang/String;
      16: astore_2
      17: new           #40                 // class java/net/URL
      20: dup
      21: new           #9                  // class java/lang/StringBuilder
      24: dup
      25: invokespecial #10                 // Method java/lang/StringBuilder."<init>":()V
      28: aload_2
      29: invokevirtual #11                 // Method java/lang/StringBuilder.append:(Ljava/lang/String;)Ljava/lang/StringBuilder;
      32: aload_1
      33: invokevirtual #11                 // Method java/lang/StringBuilder.append:(Ljava/lang/String;)Ljava/lang/StringBuilder;
      36: invokevirtual #12                 // Method java/lang/StringBuilder.toString:()Ljava/lang/String;
      39: invokespecial #41                 // Method java/net/URL."<init>":(Ljava/lang/String;)V
      42: areturn

  static {};
    Code:
       0: ldc           #3                  // class com/amazonaws/internal/EC2MetadataClient
       2: invokestatic  #42                 // Method org/apache/commons/logging/LogFactory.getLog:(Ljava/lang/Class;)Lorg/apache/commons/logging/Log;
       5: putstatic     #14                 // Field log:Lorg/apache/commons/logging/Log;
       8: return
}
