Compiled from "ReflectionTypes.kt"
public final class kotlin.reflect.jvm.internal.impl.builtins.ReflectionTypesKt {
  private static final kotlin.reflect.jvm.internal.impl.name.FqName KOTLIN_REFLECT_FQ_NAME;

  private static final java.lang.String K_FUNCTION_PREFIX;

  private static final java.lang.String K_SUSPEND_FUNCTION_PREFIX;

  public static final kotlin.reflect.jvm.internal.impl.name.FqName getKOTLIN_REFLECT_FQ_NAME();
    Code:
       0: getstatic     #7                  // Field KOTLIN_REFLECT_FQ_NAME:Lkotlin/reflect/jvm/internal/impl/name/FqName;
       3: areturn

  static {};
    Code:
       0: new           #6                  // class kotlin/reflect/jvm/internal/impl/name/FqName
       3: dup
       4: ldc           #3                  // String kotlin.reflect
       6: invokespecial #10                 // Method kotlin/reflect/jvm/internal/impl/name/FqName."<init>":(Ljava/lang/String;)V
       9: putstatic     #7                  // Field KOTLIN_REFLECT_FQ_NAME:Lkotlin/reflect/jvm/internal/impl/name/FqName;
      12: ldc           #1                  // String KFunction
      14: putstatic     #8                  // Field K_FUNCTION_PREFIX:Ljava/lang/String;
      17: ldc           #2                  // String KSuspendFunction
      19: putstatic     #9                  // Field K_SUSPEND_FUNCTION_PREFIX:Ljava/lang/String;
      22: return
}
