Compiled from "FormLoginHandler.java"
public interface io.vertx.ext.web.handler.FormLoginHandler extends io.vertx.ext.web.handler.AuthenticationHandler {
  public static final java.lang.String DEFAULT_USERNAME_PARAM;

  public static final java.lang.String DEFAULT_PASSWORD_PARAM;

  public static final java.lang.String DEFAULT_RETURN_URL_PARAM;

  public static io.vertx.ext.web.handler.FormLoginHandler create(io.vertx.ext.auth.authentication.AuthenticationProvider);
    Code:
       0: new           #1                  // class io/vertx/ext/web/handler/impl/FormLoginHandlerImpl
       3: dup
       4: aload_0
       5: ldc           #3                  // String username
       7: ldc           #4                  // String password
       9: ldc           #5                  // String return_url
      11: aconst_null
      12: invokespecial #6                  // Method io/vertx/ext/web/handler/impl/FormLoginHandlerImpl."<init>":(Lio/vertx/ext/auth/authentication/AuthenticationProvider;Ljava/lang/String;Ljava/lang/String;Ljava/lang/String;Ljava/lang/String;)V
      15: areturn

  public static io.vertx.ext.web.handler.FormLoginHandler create(io.vertx.ext.auth.authentication.AuthenticationProvider, java.lang.String, java.lang.String, java.lang.String, java.lang.String);
    Code:
       0: new           #1                  // class io/vertx/ext/web/handler/impl/FormLoginHandlerImpl
       3: dup
       4: aload_0
       5: aload_1
       6: aload_2
       7: aload_3
       8: aload         4
      10: invokespecial #6                  // Method io/vertx/ext/web/handler/impl/FormLoginHandlerImpl."<init>":(Lio/vertx/ext/auth/authentication/AuthenticationProvider;Ljava/lang/String;Ljava/lang/String;Ljava/lang/String;Ljava/lang/String;)V
      13: areturn

  public abstract io.vertx.ext.web.handler.FormLoginHandler setUsernameParam(java.lang.String);

  public abstract io.vertx.ext.web.handler.FormLoginHandler setPasswordParam(java.lang.String);

  public abstract io.vertx.ext.web.handler.FormLoginHandler setReturnURLParam(java.lang.String);

  public abstract io.vertx.ext.web.handler.FormLoginHandler setDirectLoggedInOKURL(java.lang.String);
}
