Compiled from "ResponseContentTypeHandler.java"
public interface io.vertx.ext.web.handler.ResponseContentTypeHandler extends io.vertx.ext.web.handler.PlatformHandler {
  public static final java.lang.String DEFAULT_DISABLE_FLAG;

  public static io.vertx.ext.web.handler.ResponseContentTypeHandler create();
    Code:
       0: new           #1                  // class io/vertx/ext/web/handler/impl/ResponseContentTypeHandlerImpl
       3: dup
       4: ldc           #3                  // String __vertx.autoContenType.disable
       6: invokespecial #4                  // Method io/vertx/ext/web/handler/impl/ResponseContentTypeHandlerImpl."<init>":(Ljava/lang/String;)V
       9: areturn

  public static io.vertx.ext.web.handler.ResponseContentTypeHandler create(java.lang.String);
    Code:
       0: new           #1                  // class io/vertx/ext/web/handler/impl/ResponseContentTypeHandlerImpl
       3: dup
       4: aload_0
       5: invokespecial #4                  // Method io/vertx/ext/web/handler/impl/ResponseContentTypeHandlerImpl."<init>":(Ljava/lang/String;)V
       8: areturn
}
