Compiled from "MessageSourcePollingTemplate.java"
public class org.springframework.integration.endpoint.MessageSourcePollingTemplate implements org.springframework.integration.endpoint.PollingOperations {
  private final org.springframework.integration.core.MessageSource<?> source;

  public org.springframework.integration.endpoint.MessageSourcePollingTemplate(org.springframework.integration.core.MessageSource<?>);
    Code:
       0: aload_0
       1: invokespecial #1                  // Method java/lang/Object."<init>":()V
       4: aload_1
       5: ldc           #2                  // String \'source\' cannot be null
       7: invokestatic  #3                  // Method org/springframework/util/Assert.notNull:(Ljava/lang/Object;Ljava/lang/String;)V
      10: aload_0
      11: aload_1
      12: putfield      #4                  // Field source:Lorg/springframework/integration/core/MessageSource;
      15: return

  public boolean poll(org.springframework.messaging.MessageHandler);
    Code:
       0: aload_1
       1: ldc           #5                  // String \'handler\' cannot be null
       3: invokestatic  #3                  // Method org/springframework/util/Assert.notNull:(Ljava/lang/Object;Ljava/lang/String;)V
       6: aload_0
       7: getfield      #4                  // Field source:Lorg/springframework/integration/core/MessageSource;
      10: invokeinterface #6,  1            // InterfaceMethod org/springframework/integration/core/MessageSource.receive:()Lorg/springframework/messaging/Message;
      15: astore_2
      16: aload_2
      17: ifnull        58
      20: aload_2
      21: invokestatic  #7                  // Method org/springframework/integration/StaticMessageHeaderAccessor.getAcknowledgmentCallback:(Lorg/springframework/messaging/Message;)Lorg/springframework/integration/acks/AcknowledgmentCallback;
      24: astore_3
      25: aload_1
      26: aload_2
      27: invokeinterface #8,  2            // InterfaceMethod org/springframework/messaging/MessageHandler.handleMessage:(Lorg/springframework/messaging/Message;)V
      32: aload_3
      33: invokestatic  #9                  // Method org/springframework/integration/acks/AckUtils.autoAck:(Lorg/springframework/integration/acks/AcknowledgmentCallback;)V
      36: goto          56
      39: astore        4
      41: aload_3
      42: invokestatic  #11                 // Method org/springframework/integration/acks/AckUtils.autoNack:(Lorg/springframework/integration/acks/AcknowledgmentCallback;)V
      45: new           #12                 // class org/springframework/messaging/MessageHandlingException
      48: dup
      49: aload_2
      50: aload         4
      52: invokespecial #13                 // Method org/springframework/messaging/MessageHandlingException."<init>":(Lorg/springframework/messaging/Message;Ljava/lang/Throwable;)V
      55: athrow
      56: iconst_1
      57: ireturn
      58: iconst_0
      59: ireturn
    Exception table:
       from    to  target type
          25    36    39   Class java/lang/Exception
}
