Compiled from "InMemoryWebSessionStore.java"
class org.springframework.web.server.session.InMemoryWebSessionStore$ExpiredSessionChecker {
  private static final int CHECK_PERIOD;

  private final java.util.concurrent.locks.ReentrantLock lock;

  private java.time.Instant checkTime;

  final org.springframework.web.server.session.InMemoryWebSessionStore this$0;

  private org.springframework.web.server.session.InMemoryWebSessionStore$ExpiredSessionChecker(org.springframework.web.server.session.InMemoryWebSessionStore);
    Code:
       0: aload_0
       1: aload_1
       2: putfield      #2                  // Field this$0:Lorg/springframework/web/server/session/InMemoryWebSessionStore;
       5: aload_0
       6: invokespecial #3                  // Method java/lang/Object."<init>":()V
       9: aload_0
      10: new           #4                  // class java/util/concurrent/locks/ReentrantLock
      13: dup
      14: invokespecial #5                  // Method java/util/concurrent/locks/ReentrantLock."<init>":()V
      17: putfield      #6                  // Field lock:Ljava/util/concurrent/locks/ReentrantLock;
      20: aload_0
      21: aload_0
      22: getfield      #2                  // Field this$0:Lorg/springframework/web/server/session/InMemoryWebSessionStore;
      25: invokestatic  #7                  // Method org/springframework/web/server/session/InMemoryWebSessionStore.access$600:(Lorg/springframework/web/server/session/InMemoryWebSessionStore;)Ljava/time/Clock;
      28: invokevirtual #8                  // Method java/time/Clock.instant:()Ljava/time/Instant;
      31: ldc2_w        #10                 // long 60000l
      34: getstatic     #12                 // Field java/time/temporal/ChronoUnit.MILLIS:Ljava/time/temporal/ChronoUnit;
      37: invokevirtual #13                 // Method java/time/Instant.plus:(JLjava/time/temporal/TemporalUnit;)Ljava/time/Instant;
      40: putfield      #14                 // Field checkTime:Ljava/time/Instant;
      43: return

  public void checkIfNecessary(java.time.Instant);
    Code:
       0: aload_0
       1: getfield      #14                 // Field checkTime:Ljava/time/Instant;
       4: aload_1
       5: invokevirtual #15                 // Method java/time/Instant.isBefore:(Ljava/time/Instant;)Z
       8: ifeq          16
      11: aload_0
      12: aload_1
      13: invokevirtual #16                 // Method removeExpiredSessions:(Ljava/time/Instant;)V
      16: return

  public void removeExpiredSessions(java.time.Instant);
    Code:
       0: aload_0
       1: getfield      #2                  // Field this$0:Lorg/springframework/web/server/session/InMemoryWebSessionStore;
       4: invokestatic  #17                 // Method org/springframework/web/server/session/InMemoryWebSessionStore.access$400:(Lorg/springframework/web/server/session/InMemoryWebSessionStore;)Ljava/util/Map;
       7: invokeinterface #18,  1           // InterfaceMethod java/util/Map.isEmpty:()Z
      12: ifeq          16
      15: return
      16: aload_0
      17: getfield      #6                  // Field lock:Ljava/util/concurrent/locks/ReentrantLock;
      20: invokevirtual #19                 // Method java/util/concurrent/locks/ReentrantLock.tryLock:()Z
      23: ifeq          135
      26: aload_0
      27: getfield      #2                  // Field this$0:Lorg/springframework/web/server/session/InMemoryWebSessionStore;
      30: invokestatic  #17                 // Method org/springframework/web/server/session/InMemoryWebSessionStore.access$400:(Lorg/springframework/web/server/session/InMemoryWebSessionStore;)Ljava/util/Map;
      33: invokeinterface #20,  1           // InterfaceMethod java/util/Map.values:()Ljava/util/Collection;
      38: invokeinterface #21,  1           // InterfaceMethod java/util/Collection.iterator:()Ljava/util/Iterator;
      43: astore_2
      44: aload_2
      45: invokeinterface #22,  1           // InterfaceMethod java/util/Iterator.hasNext:()Z
      50: ifeq          85
      53: aload_2
      54: invokeinterface #23,  1           // InterfaceMethod java/util/Iterator.next:()Ljava/lang/Object;
      59: checkcast     #24                 // class org/springframework/web/server/session/InMemoryWebSessionStore$InMemoryWebSession
      62: astore_3
      63: aload_3
      64: aload_1
      65: invokestatic  #25                 // Method org/springframework/web/server/session/InMemoryWebSessionStore$InMemoryWebSession.access$100:(Lorg/springframework/web/server/session/InMemoryWebSessionStore$InMemoryWebSession;Ljava/time/Instant;)Z
      68: ifeq          82
      71: aload_2
      72: invokeinterface #26,  1           // InterfaceMethod java/util/Iterator.remove:()V
      77: aload_3
      78: invokevirtual #27                 // Method org/springframework/web/server/session/InMemoryWebSessionStore$InMemoryWebSession.invalidate:()Lreactor/core/publisher/Mono;
      81: pop
      82: goto          44
      85: aload_0
      86: aload_1
      87: ldc2_w        #10                 // long 60000l
      90: getstatic     #12                 // Field java/time/temporal/ChronoUnit.MILLIS:Ljava/time/temporal/ChronoUnit;
      93: invokevirtual #13                 // Method java/time/Instant.plus:(JLjava/time/temporal/TemporalUnit;)Ljava/time/Instant;
      96: putfield      #14                 // Field checkTime:Ljava/time/Instant;
      99: aload_0
     100: getfield      #6                  // Field lock:Ljava/util/concurrent/locks/ReentrantLock;
     103: invokevirtual #28                 // Method java/util/concurrent/locks/ReentrantLock.unlock:()V
     106: goto          135
     109: astore        4
     111: aload_0
     112: aload_1
     113: ldc2_w        #10                 // long 60000l
     116: getstatic     #12                 // Field java/time/temporal/ChronoUnit.MILLIS:Ljava/time/temporal/ChronoUnit;
     119: invokevirtual #13                 // Method java/time/Instant.plus:(JLjava/time/temporal/TemporalUnit;)Ljava/time/Instant;
     122: putfield      #14                 // Field checkTime:Ljava/time/Instant;
     125: aload_0
     126: getfield      #6                  // Field lock:Ljava/util/concurrent/locks/ReentrantLock;
     129: invokevirtual #28                 // Method java/util/concurrent/locks/ReentrantLock.unlock:()V
     132: aload         4
     134: athrow
     135: return
    Exception table:
       from    to  target type
          26    85   109   any
         109   111   109   any

  org.springframework.web.server.session.InMemoryWebSessionStore$ExpiredSessionChecker(org.springframework.web.server.session.InMemoryWebSessionStore, org.springframework.web.server.session.InMemoryWebSessionStore$1);
    Code:
       0: aload_0
       1: aload_1
       2: invokespecial #1                  // Method "<init>":(Lorg/springframework/web/server/session/InMemoryWebSessionStore;)V
       5: return
}
