Compiled from "OgmCollectionPersister.java"
public class org.hibernate.ogm.persister.OgmCollectionPersister extends org.hibernate.persister.collection.AbstractCollectionPersister implements org.hibernate.ogm.persister.CollectionPhysicalModel {
  private static final org.hibernate.ogm.util.impl.Log log;

  private final org.hibernate.ogm.type.GridType keyGridType;

  private final org.hibernate.ogm.type.GridType elementGridType;

  private final org.hibernate.ogm.type.GridType indexGridType;

  private final org.hibernate.ogm.type.GridType identifierGridType;

  private final boolean isInverse;

  private final boolean oneToMany;

  private final org.hibernate.ogm.type.GridType gridTypeOfAssociatedId;

  private final org.hibernate.ogm.persister.OgmCollectionPersister$AssociationType associationType;

  private final org.hibernate.ogm.dialect.GridDialect gridDialect;

  private final org.hibernate.ogm.datastore.spi.AssociationContext associationContext;

  public org.hibernate.ogm.persister.OgmCollectionPersister(org.hibernate.mapping.Collection, org.hibernate.cache.spi.access.CollectionRegionAccessStrategy, org.hibernate.cfg.Configuration, org.hibernate.engine.spi.SessionFactoryImplementor) throws org.hibernate.MappingException, org.hibernate.cache.CacheException;
    Code:
       0: aload_0
       1: aload_1
       2: aload_2
       3: aload_3
       4: aload         4
       6: invokespecial #1                  // Method org/hibernate/persister/collection/AbstractCollectionPersister."<init>":(Lorg/hibernate/mapping/Collection;Lorg/hibernate/cache/spi/access/CollectionRegionAccessStrategy;Lorg/hibernate/cfg/Configuration;Lorg/hibernate/engine/spi/SessionFactoryImplementor;)V
       9: aload         4
      11: invokeinterface #2,  1            // InterfaceMethod org/hibernate/engine/spi/SessionFactoryImplementor.getServiceRegistry:()Lorg/hibernate/service/spi/ServiceRegistryImplementor;
      16: astore        5
      18: aload         5
      20: ldc_w         #3                  // class org/hibernate/ogm/type/TypeTranslator
      23: invokeinterface #4,  2            // InterfaceMethod org/hibernate/service/ServiceRegistry.getService:(Ljava/lang/Class;)Lorg/hibernate/service/Service;
      28: checkcast     #3                  // class org/hibernate/ogm/type/TypeTranslator
      31: astore        6
      33: aload_0
      34: aload         5
      36: ldc_w         #5                  // class org/hibernate/ogm/datastore/impl/DatastoreServices
      39: invokeinterface #4,  2            // InterfaceMethod org/hibernate/service/ServiceRegistry.getService:(Ljava/lang/Class;)Lorg/hibernate/service/Service;
      44: checkcast     #5                  // class org/hibernate/ogm/datastore/impl/DatastoreServices
      47: invokeinterface #6,  1            // InterfaceMethod org/hibernate/ogm/datastore/impl/DatastoreServices.getGridDialect:()Lorg/hibernate/ogm/dialect/GridDialect;
      52: putfield      #7                  // Field gridDialect:Lorg/hibernate/ogm/dialect/GridDialect;
      55: aload_0
      56: aload         6
      58: aload_0
      59: invokevirtual #8                  // Method getKeyType:()Lorg/hibernate/type/Type;
      62: invokeinterface #9,  2            // InterfaceMethod org/hibernate/ogm/type/TypeTranslator.getType:(Lorg/hibernate/type/Type;)Lorg/hibernate/ogm/type/GridType;
      67: putfield      #10                 // Field keyGridType:Lorg/hibernate/ogm/type/GridType;
      70: aload_0
      71: aload         6
      73: aload_0
      74: invokevirtual #11                 // Method getElementType:()Lorg/hibernate/type/Type;
      77: invokeinterface #9,  2            // InterfaceMethod org/hibernate/ogm/type/TypeTranslator.getType:(Lorg/hibernate/type/Type;)Lorg/hibernate/ogm/type/GridType;
      82: putfield      #12                 // Field elementGridType:Lorg/hibernate/ogm/type/GridType;
      85: aload_0
      86: aload         6
      88: aload_0
      89: invokevirtual #13                 // Method getIndexType:()Lorg/hibernate/type/Type;
      92: invokeinterface #9,  2            // InterfaceMethod org/hibernate/ogm/type/TypeTranslator.getType:(Lorg/hibernate/type/Type;)Lorg/hibernate/ogm/type/GridType;
      97: putfield      #14                 // Field indexGridType:Lorg/hibernate/ogm/type/GridType;
     100: aload_0
     101: aload         6
     103: aload_0
     104: invokevirtual #15                 // Method getIdentifierType:()Lorg/hibernate/type/Type;
     107: invokeinterface #9,  2            // InterfaceMethod org/hibernate/ogm/type/TypeTranslator.getType:(Lorg/hibernate/type/Type;)Lorg/hibernate/ogm/type/GridType;
     112: putfield      #16                 // Field identifierGridType:Lorg/hibernate/ogm/type/GridType;
     115: aload_0
     116: aload_1
     117: invokevirtual #17                 // Method org/hibernate/mapping/Collection.isInverse:()Z
     120: putfield      #18                 // Field isInverse:Z
     123: aload_0
     124: aload_1
     125: invokevirtual #19                 // Method org/hibernate/mapping/Collection.isOneToMany:()Z
     128: putfield      #20                 // Field oneToMany:Z
     131: aload_1
     132: invokevirtual #19                 // Method org/hibernate/mapping/Collection.isOneToMany:()Z
     135: ifeq          194
     138: aload_0
     139: invokevirtual #21                 // Method getElementPersister:()Lorg/hibernate/persister/entity/EntityPersister;
     142: ifnull        194
     145: aload_0
     146: invokevirtual #11                 // Method getElementType:()Lorg/hibernate/type/Type;
     149: invokeinterface #22,  1           // InterfaceMethod org/hibernate/type/Type.isEntityType:()Z
     154: ifeq          194
     157: aload_0
     158: getstatic     #23                 // Field org/hibernate/ogm/persister/OgmCollectionPersister$AssociationType.EMBEDDED_FK_TO_ENTITY:Lorg/hibernate/ogm/persister/OgmCollectionPersister$AssociationType;
     161: putfield      #24                 // Field associationType:Lorg/hibernate/ogm/persister/OgmCollectionPersister$AssociationType;
     164: aload_0
     165: invokevirtual #11                 // Method getElementType:()Lorg/hibernate/type/Type;
     168: checkcast     #25                 // class org/hibernate/type/EntityType
     171: aload         4
     173: invokevirtual #26                 // Method org/hibernate/type/EntityType.getIdentifierOrUniqueKeyType:(Lorg/hibernate/engine/spi/Mapping;)Lorg/hibernate/type/Type;
     176: astore        7
     178: aload_0
     179: aload         6
     181: aload         7
     183: invokeinterface #9,  2            // InterfaceMethod org/hibernate/ogm/type/TypeTranslator.getType:(Lorg/hibernate/type/Type;)Lorg/hibernate/ogm/type/GridType;
     188: putfield      #27                 // Field gridTypeOfAssociatedId:Lorg/hibernate/ogm/type/GridType;
     191: goto          304
     194: aload_1
     195: invokevirtual #19                 // Method org/hibernate/mapping/Collection.isOneToMany:()Z
     198: ifeq          231
     201: new           #28                 // class org/hibernate/annotations/common/AssertionFailure
     204: dup
     205: new           #29                 // class java/lang/StringBuilder
     208: dup
     209: invokespecial #30                 // Method java/lang/StringBuilder."<init>":()V
     212: ldc           #31                 // String Association marked as one to many but has no ManyToOneType:
     214: invokevirtual #32                 // Method java/lang/StringBuilder.append:(Ljava/lang/String;)Ljava/lang/StringBuilder;
     217: aload_1
     218: invokevirtual #33                 // Method org/hibernate/mapping/Collection.getRole:()Ljava/lang/String;
     221: invokevirtual #32                 // Method java/lang/StringBuilder.append:(Ljava/lang/String;)Ljava/lang/StringBuilder;
     224: invokevirtual #34                 // Method java/lang/StringBuilder.toString:()Ljava/lang/String;
     227: invokespecial #35                 // Method org/hibernate/annotations/common/AssertionFailure."<init>":(Ljava/lang/String;)V
     230: athrow
     231: aload_0
     232: invokevirtual #11                 // Method getElementType:()Lorg/hibernate/type/Type;
     235: invokeinterface #36,  1           // InterfaceMethod org/hibernate/type/Type.isAssociationType:()Z
     240: ifeq          292
     243: aload_0
     244: invokevirtual #11                 // Method getElementType:()Lorg/hibernate/type/Type;
     247: invokeinterface #22,  1           // InterfaceMethod org/hibernate/type/Type.isEntityType:()Z
     252: ifeq          292
     255: aload_0
     256: getstatic     #37                 // Field org/hibernate/ogm/persister/OgmCollectionPersister$AssociationType.ASSOCIATION_TABLE_TO_ENTITY:Lorg/hibernate/ogm/persister/OgmCollectionPersister$AssociationType;
     259: putfield      #24                 // Field associationType:Lorg/hibernate/ogm/persister/OgmCollectionPersister$AssociationType;
     262: aload_0
     263: invokevirtual #11                 // Method getElementType:()Lorg/hibernate/type/Type;
     266: checkcast     #25                 // class org/hibernate/type/EntityType
     269: aload         4
     271: invokevirtual #26                 // Method org/hibernate/type/EntityType.getIdentifierOrUniqueKeyType:(Lorg/hibernate/engine/spi/Mapping;)Lorg/hibernate/type/Type;
     274: astore        7
     276: aload_0
     277: aload         6
     279: aload         7
     281: invokeinterface #9,  2            // InterfaceMethod org/hibernate/ogm/type/TypeTranslator.getType:(Lorg/hibernate/type/Type;)Lorg/hibernate/ogm/type/GridType;
     286: putfield      #27                 // Field gridTypeOfAssociatedId:Lorg/hibernate/ogm/type/GridType;
     289: goto          304
     292: aload_0
     293: aconst_null
     294: putfield      #27                 // Field gridTypeOfAssociatedId:Lorg/hibernate/ogm/type/GridType;
     297: aload_0
     298: getstatic     #38                 // Field org/hibernate/ogm/persister/OgmCollectionPersister$AssociationType.OTHER:Lorg/hibernate/ogm/persister/OgmCollectionPersister$AssociationType;
     301: putfield      #24                 // Field associationType:Lorg/hibernate/ogm/persister/OgmCollectionPersister$AssociationType;
     304: aload_0
     305: aload_0
     306: invokespecial #39                 // Method buildAssociationContext:()Lorg/hibernate/ogm/datastore/spi/AssociationContext;
     309: putfield      #40                 // Field associationContext:Lorg/hibernate/ogm/datastore/spi/AssociationContext;
     312: return

  public org.hibernate.ogm.datastore.spi.AssociationContext getAssociationContext();
    Code:
       0: aload_0
       1: getfield      #40                 // Field associationContext:Lorg/hibernate/ogm/datastore/spi/AssociationContext;
       4: areturn

  private org.hibernate.ogm.datastore.spi.AssociationContext buildAssociationContext();
    Code:
       0: new           #41                 // class java/util/ArrayList
       3: dup
       4: invokespecial #42                 // Method java/util/ArrayList."<init>":()V
       7: astore_1
       8: aload_0
       9: invokevirtual #43                 // Method getIdentifierColumnName:()Ljava/lang/String;
      12: astore_2
      13: aload_2
      14: ifnull        25
      17: aload_1
      18: aload_2
      19: invokeinterface #44,  2           // InterfaceMethod java/util/List.add:(Ljava/lang/Object;)Z
      24: pop
      25: aload_0
      26: invokevirtual #45                 // Method getKeyColumnNames:()[Ljava/lang/String;
      29: astore_3
      30: aload_3
      31: arraylength
      32: istore        4
      34: iconst_0
      35: istore        5
      37: iload         5
      39: iload         4
      41: if_icmpge     65
      44: aload_3
      45: iload         5
      47: aaload
      48: astore        6
      50: aload_1
      51: aload         6
      53: invokeinterface #44,  2           // InterfaceMethod java/util/List.add:(Ljava/lang/Object;)Z
      58: pop
      59: iinc          5, 1
      62: goto          37
      65: aload_0
      66: invokevirtual #46                 // Method getIndexColumnNames:()[Ljava/lang/String;
      69: astore_3
      70: aload_3
      71: ifnull        114
      74: aload_3
      75: astore        4
      77: aload         4
      79: arraylength
      80: istore        5
      82: iconst_0
      83: istore        6
      85: iload         6
      87: iload         5
      89: if_icmpge     114
      92: aload         4
      94: iload         6
      96: aaload
      97: astore        7
      99: aload_1
     100: aload         7
     102: invokeinterface #44,  2           // InterfaceMethod java/util/List.add:(Ljava/lang/Object;)Z
     107: pop
     108: iinc          6, 1
     111: goto          85
     114: aload_0
     115: invokevirtual #47                 // Method getElementColumnNames:()[Ljava/lang/String;
     118: astore_3
     119: aload_3
     120: astore        4
     122: aload         4
     124: arraylength
     125: istore        5
     127: iconst_0
     128: istore        6
     130: iload         6
     132: iload         5
     134: if_icmpge     159
     137: aload         4
     139: iload         6
     141: aaload
     142: astore        7
     144: aload_1
     145: aload         7
     147: invokeinterface #44,  2           // InterfaceMethod java/util/List.add:(Ljava/lang/Object;)Z
     152: pop
     153: iinc          6, 1
     156: goto          130
     159: new           #48                 // class org/hibernate/ogm/datastore/spi/AssociationContext
     162: dup
     163: aload_1
     164: invokespecial #49                 // Method org/hibernate/ogm/datastore/spi/AssociationContext."<init>":(Ljava/util/List;)V
     167: areturn

  public java.lang.Object readKey(java.sql.ResultSet, java.lang.String[], org.hibernate.engine.spi.SessionImplementor) throws org.hibernate.HibernateException, java.sql.SQLException;
    Code:
       0: aload_1
       1: ldc_w         #50                 // class org/hibernate/ogm/jdbc/TupleAsMapResultSet
       4: invokeinterface #51,  2           // InterfaceMethod java/sql/ResultSet.unwrap:(Ljava/lang/Class;)Ljava/lang/Object;
       9: checkcast     #50                 // class org/hibernate/ogm/jdbc/TupleAsMapResultSet
      12: astore        4
      14: aload         4
      16: invokevirtual #52                 // Method org/hibernate/ogm/jdbc/TupleAsMapResultSet.getTuple:()Lorg/hibernate/ogm/datastore/spi/Tuple;
      19: astore        5
      21: aload_0
      22: getfield      #10                 // Field keyGridType:Lorg/hibernate/ogm/type/GridType;
      25: aload         5
      27: aload_2
      28: aload_3
      29: aconst_null
      30: invokeinterface #53,  5           // InterfaceMethod org/hibernate/ogm/type/GridType.nullSafeGet:(Lorg/hibernate/ogm/datastore/spi/Tuple;[Ljava/lang/String;Lorg/hibernate/engine/spi/SessionImplementor;Ljava/lang/Object;)Ljava/lang/Object;
      35: areturn

  public java.lang.Object readElement(java.sql.ResultSet, java.lang.Object, java.lang.String[], org.hibernate.engine.spi.SessionImplementor) throws org.hibernate.HibernateException, java.sql.SQLException;
    Code:
       0: aload_1
       1: ldc_w         #50                 // class org/hibernate/ogm/jdbc/TupleAsMapResultSet
       4: invokeinterface #51,  2           // InterfaceMethod java/sql/ResultSet.unwrap:(Ljava/lang/Class;)Ljava/lang/Object;
       9: checkcast     #50                 // class org/hibernate/ogm/jdbc/TupleAsMapResultSet
      12: astore        5
      14: aload         5
      16: invokevirtual #52                 // Method org/hibernate/ogm/jdbc/TupleAsMapResultSet.getTuple:()Lorg/hibernate/ogm/datastore/spi/Tuple;
      19: astore        6
      21: aload_0
      22: getfield      #12                 // Field elementGridType:Lorg/hibernate/ogm/type/GridType;
      25: aload         6
      27: aload_3
      28: aload         4
      30: aload_2
      31: invokeinterface #53,  5           // InterfaceMethod org/hibernate/ogm/type/GridType.nullSafeGet:(Lorg/hibernate/ogm/datastore/spi/Tuple;[Ljava/lang/String;Lorg/hibernate/engine/spi/SessionImplementor;Ljava/lang/Object;)Ljava/lang/Object;
      36: areturn

  public java.lang.Object readIdentifier(java.sql.ResultSet, java.lang.String, org.hibernate.engine.spi.SessionImplementor) throws org.hibernate.HibernateException, java.sql.SQLException;
    Code:
       0: aload_1
       1: ldc_w         #50                 // class org/hibernate/ogm/jdbc/TupleAsMapResultSet
       4: invokeinterface #51,  2           // InterfaceMethod java/sql/ResultSet.unwrap:(Ljava/lang/Class;)Ljava/lang/Object;
       9: checkcast     #50                 // class org/hibernate/ogm/jdbc/TupleAsMapResultSet
      12: astore        4
      14: aload         4
      16: invokevirtual #52                 // Method org/hibernate/ogm/jdbc/TupleAsMapResultSet.getTuple:()Lorg/hibernate/ogm/datastore/spi/Tuple;
      19: astore        5
      21: aload_0
      22: getfield      #16                 // Field identifierGridType:Lorg/hibernate/ogm/type/GridType;
      25: aload         5
      27: aload_2
      28: aload_3
      29: aconst_null
      30: invokeinterface #54,  5           // InterfaceMethod org/hibernate/ogm/type/GridType.nullSafeGet:(Lorg/hibernate/ogm/datastore/spi/Tuple;Ljava/lang/String;Lorg/hibernate/engine/spi/SessionImplementor;Ljava/lang/Object;)Ljava/lang/Object;
      35: areturn

  public java.lang.Object readIndex(java.sql.ResultSet, java.lang.String[], org.hibernate.engine.spi.SessionImplementor) throws org.hibernate.HibernateException, java.sql.SQLException;
    Code:
       0: aload_1
       1: ldc_w         #50                 // class org/hibernate/ogm/jdbc/TupleAsMapResultSet
       4: invokeinterface #51,  2           // InterfaceMethod java/sql/ResultSet.unwrap:(Ljava/lang/Class;)Ljava/lang/Object;
       9: checkcast     #50                 // class org/hibernate/ogm/jdbc/TupleAsMapResultSet
      12: astore        4
      14: aload         4
      16: invokevirtual #52                 // Method org/hibernate/ogm/jdbc/TupleAsMapResultSet.getTuple:()Lorg/hibernate/ogm/datastore/spi/Tuple;
      19: astore        5
      21: aload_0
      22: getfield      #14                 // Field indexGridType:Lorg/hibernate/ogm/type/GridType;
      25: aload         5
      27: aload_2
      28: aload_3
      29: aconst_null
      30: invokeinterface #53,  5           // InterfaceMethod org/hibernate/ogm/type/GridType.nullSafeGet:(Lorg/hibernate/ogm/datastore/spi/Tuple;[Ljava/lang/String;Lorg/hibernate/engine/spi/SessionImplementor;Ljava/lang/Object;)Ljava/lang/Object;
      35: areturn

  protected org.hibernate.loader.collection.CollectionInitializer createSubselectInitializer(org.hibernate.engine.spi.SubselectFetch, org.hibernate.engine.spi.SessionImplementor);
    Code:
       0: aconst_null
       1: areturn

  protected org.hibernate.loader.collection.CollectionInitializer createCollectionInitializer(org.hibernate.engine.spi.LoadQueryInfluencers) throws org.hibernate.MappingException;
    Code:
       0: new           #55                 // class org/hibernate/ogm/loader/OgmBasicCollectionLoader
       3: dup
       4: aload_0
       5: invokespecial #56                 // Method org/hibernate/ogm/loader/OgmBasicCollectionLoader."<init>":(Lorg/hibernate/ogm/persister/OgmCollectionPersister;)V
       8: areturn

  public org.hibernate.ogm.type.GridType getKeyGridType();
    Code:
       0: aload_0
       1: getfield      #10                 // Field keyGridType:Lorg/hibernate/ogm/type/GridType;
       4: areturn

  public org.hibernate.ogm.type.GridType getElementGridType();
    Code:
       0: aload_0
       1: getfield      #12                 // Field elementGridType:Lorg/hibernate/ogm/type/GridType;
       4: areturn

  public boolean isOneToMany();
    Code:
       0: aload_0
       1: getfield      #20                 // Field oneToMany:Z
       4: ireturn

  public boolean isManyToMany();
    Code:
       0: iconst_1
       1: ireturn

  public boolean isCascadeDeleteEnabled();
    Code:
       0: iconst_0
       1: ireturn

  protected java.lang.String generateDeleteString();
    Code:
       0: aconst_null
       1: areturn

  protected java.lang.String generateDeleteRowString();
    Code:
       0: aconst_null
       1: areturn

  protected java.lang.String generateUpdateRowString();
    Code:
       0: aconst_null
       1: areturn

  protected java.lang.String generateInsertRowString();
    Code:
       0: aconst_null
       1: areturn

  protected int doUpdateRows(java.io.Serializable, org.hibernate.collection.spi.PersistentCollection, org.hibernate.engine.spi.SessionImplementor) throws org.hibernate.HibernateException;
    Code:
       0: aload_0
       1: getfield      #57                 // Field elementColumnIsSettable:[Z
       4: invokestatic  #58                 // Method org/hibernate/internal/util/collections/ArrayHelper.isAllFalse:([Z)Z
       7: ifeq          12
      10: iconst_0
      11: ireturn
      12: iconst_0
      13: istore        4
      15: iconst_0
      16: istore        5
      18: aload_2
      19: aload_0
      20: invokeinterface #59,  2           // InterfaceMethod org/hibernate/collection/spi/PersistentCollection.entries:(Lorg/hibernate/persister/collection/CollectionPersister;)Ljava/util/Iterator;
      25: astore        6
      27: new           #60                 // class org/hibernate/ogm/util/impl/PropertyMetadataProvider
      30: dup
      31: invokespecial #61                 // Method org/hibernate/ogm/util/impl/PropertyMetadataProvider."<init>":()V
      34: aload_0
      35: getfield      #7                  // Field gridDialect:Lorg/hibernate/ogm/dialect/GridDialect;
      38: invokevirtual #62                 // Method org/hibernate/ogm/util/impl/PropertyMetadataProvider.gridDialect:(Lorg/hibernate/ogm/dialect/GridDialect;)Lorg/hibernate/ogm/util/impl/PropertyMetadataProvider;
      41: aload_0
      42: invokevirtual #63                 // Method getTableName:()Ljava/lang/String;
      45: invokevirtual #64                 // Method org/hibernate/ogm/util/impl/PropertyMetadataProvider.tableName:(Ljava/lang/String;)Lorg/hibernate/ogm/util/impl/PropertyMetadataProvider;
      48: aload_1
      49: invokevirtual #65                 // Method org/hibernate/ogm/util/impl/PropertyMetadataProvider.key:(Ljava/lang/Object;)Lorg/hibernate/ogm/util/impl/PropertyMetadataProvider;
      52: aload_0
      53: invokevirtual #45                 // Method getKeyColumnNames:()[Ljava/lang/String;
      56: invokevirtual #66                 // Method org/hibernate/ogm/util/impl/PropertyMetadataProvider.keyColumnNames:([Ljava/lang/String;)Lorg/hibernate/ogm/util/impl/PropertyMetadataProvider;
      59: aload_0
      60: invokevirtual #67                 // Method getKeyGridType:()Lorg/hibernate/ogm/type/GridType;
      63: invokevirtual #68                 // Method org/hibernate/ogm/util/impl/PropertyMetadataProvider.keyGridType:(Lorg/hibernate/ogm/type/GridType;)Lorg/hibernate/ogm/util/impl/PropertyMetadataProvider;
      66: aload_0
      67: invokevirtual #69                 // Method org/hibernate/ogm/util/impl/PropertyMetadataProvider.collectionPersister:(Lorg/hibernate/ogm/persister/OgmCollectionPersister;)Lorg/hibernate/ogm/util/impl/PropertyMetadataProvider;
      70: aload_3
      71: invokevirtual #70                 // Method org/hibernate/ogm/util/impl/PropertyMetadataProvider.session:(Lorg/hibernate/engine/spi/SessionImplementor;)Lorg/hibernate/ogm/util/impl/PropertyMetadataProvider;
      74: astore        7
      76: aload         6
      78: invokeinterface #71,  1           // InterfaceMethod java/util/Iterator.hasNext:()Z
      83: ifeq          253
      86: aload         6
      88: invokeinterface #72,  1           // InterfaceMethod java/util/Iterator.next:()Ljava/lang/Object;
      93: astore        8
      95: aload_2
      96: aload         8
      98: iload         5
     100: aload_0
     101: getfield      #73                 // Field elementType:Lorg/hibernate/type/Type;
     104: invokeinterface #74,  4           // InterfaceMethod org/hibernate/collection/spi/PersistentCollection.needsUpdating:(Ljava/lang/Object;ILorg/hibernate/type/Type;)Z
     109: ifeq          247
     112: aload_0
     113: aload_1
     114: aload_2
     115: aload_3
     116: iload         5
     118: aload         8
     120: invokespecial #75                 // Method getTupleKeyForUpdate:(Ljava/io/Serializable;Lorg/hibernate/collection/spi/PersistentCollection;Lorg/hibernate/engine/spi/SessionImplementor;ILjava/lang/Object;)Lorg/hibernate/ogm/grid/RowKey;
     123: astore        9
     125: aload         7
     127: invokevirtual #76                 // Method org/hibernate/ogm/util/impl/PropertyMetadataProvider.getCollectionMetadata:()Lorg/hibernate/ogm/datastore/spi/Association;
     130: aload         9
     132: invokevirtual #77                 // Method org/hibernate/ogm/datastore/spi/Association.get:(Lorg/hibernate/ogm/grid/RowKey;)Lorg/hibernate/ogm/datastore/spi/Tuple;
     135: astore        10
     137: aload         10
     139: ifnonnull     196
     142: new           #28                 // class org/hibernate/annotations/common/AssertionFailure
     145: dup
     146: new           #29                 // class java/lang/StringBuilder
     149: dup
     150: invokespecial #30                 // Method java/lang/StringBuilder."<init>":()V
     153: ldc           #78                 // String Updating a collection tuple that is not present: table {
     155: invokevirtual #32                 // Method java/lang/StringBuilder.append:(Ljava/lang/String;)Ljava/lang/StringBuilder;
     158: aload_0
     159: invokevirtual #63                 // Method getTableName:()Ljava/lang/String;
     162: invokevirtual #32                 // Method java/lang/StringBuilder.append:(Ljava/lang/String;)Ljava/lang/StringBuilder;
     165: ldc           #79                 // String } collectionKey {
     167: invokevirtual #32                 // Method java/lang/StringBuilder.append:(Ljava/lang/String;)Ljava/lang/StringBuilder;
     170: aload_1
     171: invokevirtual #80                 // Method java/lang/StringBuilder.append:(Ljava/lang/Object;)Ljava/lang/StringBuilder;
     174: ldc           #81                 // String } entry {
     176: invokevirtual #32                 // Method java/lang/StringBuilder.append:(Ljava/lang/String;)Ljava/lang/StringBuilder;
     179: aload         8
     181: invokevirtual #80                 // Method java/lang/StringBuilder.append:(Ljava/lang/Object;)Ljava/lang/StringBuilder;
     184: ldc           #82                 // String }
     186: invokevirtual #32                 // Method java/lang/StringBuilder.append:(Ljava/lang/String;)Ljava/lang/StringBuilder;
     189: invokevirtual #34                 // Method java/lang/StringBuilder.toString:()Ljava/lang/String;
     192: invokespecial #35                 // Method org/hibernate/annotations/common/AssertionFailure."<init>":(Ljava/lang/String;)V
     195: athrow
     196: aload_0
     197: aload_3
     198: aload         10
     200: getstatic     #83                 // Field org/hibernate/ogm/persister/OgmCollectionPersister$Action.REMOVE:Lorg/hibernate/ogm/persister/OgmCollectionPersister$Action;
     203: aload         9
     205: invokespecial #84                 // Method updateInverseSideOfAssociationNavigation:(Lorg/hibernate/engine/spi/SessionImplementor;Lorg/hibernate/ogm/datastore/spi/Tuple;Lorg/hibernate/ogm/persister/OgmCollectionPersister$Action;Lorg/hibernate/ogm/grid/RowKey;)V
     208: aload_0
     209: invokevirtual #85                 // Method getElementGridType:()Lorg/hibernate/ogm/type/GridType;
     212: aload         10
     214: aload_2
     215: aload         8
     217: invokeinterface #86,  2           // InterfaceMethod org/hibernate/collection/spi/PersistentCollection.getElement:(Ljava/lang/Object;)Ljava/lang/Object;
     222: aload_0
     223: invokevirtual #47                 // Method getElementColumnNames:()[Ljava/lang/String;
     226: aload_3
     227: invokeinterface #87,  5           // InterfaceMethod org/hibernate/ogm/type/GridType.nullSafeSet:(Lorg/hibernate/ogm/datastore/spi/Tuple;Ljava/lang/Object;[Ljava/lang/String;Lorg/hibernate/engine/spi/SessionImplementor;)V
     232: aload_0
     233: aload_3
     234: aload         10
     236: getstatic     #88                 // Field org/hibernate/ogm/persister/OgmCollectionPersister$Action.ADD:Lorg/hibernate/ogm/persister/OgmCollectionPersister$Action;
     239: aload         9
     241: invokespecial #84                 // Method updateInverseSideOfAssociationNavigation:(Lorg/hibernate/engine/spi/SessionImplementor;Lorg/hibernate/ogm/datastore/spi/Tuple;Lorg/hibernate/ogm/persister/OgmCollectionPersister$Action;Lorg/hibernate/ogm/grid/RowKey;)V
     244: iinc          4, 1
     247: iinc          5, 1
     250: goto          76
     253: aload         7
     255: invokevirtual #89                 // Method org/hibernate/ogm/util/impl/PropertyMetadataProvider.flushToCache:()V
     258: iload         4
     260: ireturn

  private void completeTuple(org.hibernate.ogm.persister.OgmCollectionPersister$RowKeyAndTuple, org.hibernate.collection.spi.PersistentCollection, org.hibernate.engine.spi.SessionImplementor, java.lang.Object);
    Code:
       0: aload_2
       1: aload         4
       3: invokeinterface #86,  2           // InterfaceMethod org/hibernate/collection/spi/PersistentCollection.getElement:(Ljava/lang/Object;)Ljava/lang/Object;
       8: astore        5
      10: aload_0
      11: invokevirtual #85                 // Method getElementGridType:()Lorg/hibernate/ogm/type/GridType;
      14: aload_1
      15: getfield      #90                 // Field org/hibernate/ogm/persister/OgmCollectionPersister$RowKeyAndTuple.tuple:Lorg/hibernate/ogm/datastore/spi/Tuple;
      18: aload         5
      20: aload_0
      21: invokevirtual #47                 // Method getElementColumnNames:()[Ljava/lang/String;
      24: aload_3
      25: invokeinterface #87,  5           // InterfaceMethod org/hibernate/ogm/type/GridType.nullSafeSet:(Lorg/hibernate/ogm/datastore/spi/Tuple;Ljava/lang/Object;[Ljava/lang/String;Lorg/hibernate/engine/spi/SessionImplementor;)V
      30: return

  private org.hibernate.ogm.persister.OgmCollectionPersister$RowKeyAndTuple createAndPutTupleforInsert(java.io.Serializable, org.hibernate.collection.spi.PersistentCollection, org.hibernate.ogm.util.impl.PropertyMetadataProvider, org.hibernate.engine.spi.SessionImplementor, int, java.lang.Object);
    Code:
       0: aload_0
       1: invokevirtual #91                 // Method initializeRowKeyBuilder:()Lorg/hibernate/ogm/grid/impl/RowKeyBuilder;
       4: astore        7
       6: new           #92                 // class org/hibernate/ogm/datastore/spi/Tuple
       9: dup
      10: getstatic     #93                 // Field org/hibernate/ogm/datastore/impl/EmptyTupleSnapshot.SINGLETON:Lorg/hibernate/ogm/datastore/spi/TupleSnapshot;
      13: invokespecial #94                 // Method org/hibernate/ogm/datastore/spi/Tuple."<init>":(Lorg/hibernate/ogm/datastore/spi/TupleSnapshot;)V
      16: astore        8
      18: aload_0
      19: getfield      #95                 // Field hasIdentifier:Z
      22: ifeq          67
      25: aload_2
      26: aload         6
      28: iload         5
      30: invokeinterface #96,  3           // InterfaceMethod org/hibernate/collection/spi/PersistentCollection.getIdentifier:(Ljava/lang/Object;I)Ljava/lang/Object;
      35: astore        9
      37: iconst_1
      38: anewarray     #97                 // class java/lang/String
      41: dup
      42: iconst_0
      43: aload_0
      44: invokevirtual #43                 // Method getIdentifierColumnName:()Ljava/lang/String;
      47: aastore
      48: astore        10
      50: aload_0
      51: getfield      #16                 // Field identifierGridType:Lorg/hibernate/ogm/type/GridType;
      54: aload         8
      56: aload         9
      58: aload         10
      60: aload         4
      62: invokeinterface #87,  5           // InterfaceMethod org/hibernate/ogm/type/GridType.nullSafeSet:(Lorg/hibernate/ogm/datastore/spi/Tuple;Ljava/lang/Object;[Ljava/lang/String;Lorg/hibernate/engine/spi/SessionImplementor;)V
      67: aload_0
      68: invokevirtual #67                 // Method getKeyGridType:()Lorg/hibernate/ogm/type/GridType;
      71: aload         8
      73: aload_1
      74: aload_0
      75: invokevirtual #45                 // Method getKeyColumnNames:()[Ljava/lang/String;
      78: aload         4
      80: invokeinterface #87,  5           // InterfaceMethod org/hibernate/ogm/type/GridType.nullSafeSet:(Lorg/hibernate/ogm/datastore/spi/Tuple;Ljava/lang/Object;[Ljava/lang/String;Lorg/hibernate/engine/spi/SessionImplementor;)V
      85: aload_0
      86: getfield      #98                 // Field hasIndex:Z
      89: ifeq          131
      92: aload_2
      93: aload         6
      95: iload         5
      97: aload_0
      98: invokeinterface #99,  4           // InterfaceMethod org/hibernate/collection/spi/PersistentCollection.getIndex:(Ljava/lang/Object;ILorg/hibernate/persister/collection/CollectionPersister;)Ljava/lang/Object;
     103: astore        9
     105: aload_0
     106: getfield      #14                 // Field indexGridType:Lorg/hibernate/ogm/type/GridType;
     109: aload         8
     111: aload_0
     112: aload         9
     114: invokevirtual #100                // Method incrementIndexByBase:(Ljava/lang/Object;)Ljava/lang/Object;
     117: aload_0
     118: invokevirtual #46                 // Method getIndexColumnNames:()[Ljava/lang/String;
     121: aload         4
     123: invokeinterface #87,  5           // InterfaceMethod org/hibernate/ogm/type/GridType.nullSafeSet:(Lorg/hibernate/ogm/datastore/spi/Tuple;Ljava/lang/Object;[Ljava/lang/String;Lorg/hibernate/engine/spi/SessionImplementor;)V
     128: goto          160
     131: aload_2
     132: aload         6
     134: invokeinterface #86,  2           // InterfaceMethod org/hibernate/collection/spi/PersistentCollection.getElement:(Ljava/lang/Object;)Ljava/lang/Object;
     139: astore        9
     141: aload_0
     142: invokevirtual #85                 // Method getElementGridType:()Lorg/hibernate/ogm/type/GridType;
     145: aload         8
     147: aload         9
     149: aload_0
     150: invokevirtual #47                 // Method getElementColumnNames:()[Ljava/lang/String;
     153: aload         4
     155: invokeinterface #87,  5           // InterfaceMethod org/hibernate/ogm/type/GridType.nullSafeSet:(Lorg/hibernate/ogm/datastore/spi/Tuple;Ljava/lang/Object;[Ljava/lang/String;Lorg/hibernate/engine/spi/SessionImplementor;)V
     160: new           #101                // class org/hibernate/ogm/persister/OgmCollectionPersister$RowKeyAndTuple
     163: dup
     164: aconst_null
     165: invokespecial #102                // Method org/hibernate/ogm/persister/OgmCollectionPersister$RowKeyAndTuple."<init>":(Lorg/hibernate/ogm/persister/OgmCollectionPersister$1;)V
     168: astore        9
     170: aload         9
     172: aload         7
     174: aload         8
     176: invokevirtual #103                // Method org/hibernate/ogm/grid/impl/RowKeyBuilder.values:(Lorg/hibernate/ogm/datastore/spi/Tuple;)Lorg/hibernate/ogm/grid/impl/RowKeyBuilder;
     179: invokevirtual #104                // Method org/hibernate/ogm/grid/impl/RowKeyBuilder.build:()Lorg/hibernate/ogm/grid/RowKey;
     182: putfield      #105                // Field org/hibernate/ogm/persister/OgmCollectionPersister$RowKeyAndTuple.key:Lorg/hibernate/ogm/grid/RowKey;
     185: aload_3
     186: aload         9
     188: getfield      #105                // Field org/hibernate/ogm/persister/OgmCollectionPersister$RowKeyAndTuple.key:Lorg/hibernate/ogm/grid/RowKey;
     191: invokevirtual #106                // Method org/hibernate/ogm/util/impl/PropertyMetadataProvider.createAndPutAssociationTuple:(Lorg/hibernate/ogm/grid/RowKey;)Lorg/hibernate/ogm/datastore/spi/Tuple;
     194: astore        10
     196: aload         8
     198: invokevirtual #107                // Method org/hibernate/ogm/datastore/spi/Tuple.getColumnNames:()Ljava/util/Set;
     201: invokeinterface #108,  1          // InterfaceMethod java/util/Set.iterator:()Ljava/util/Iterator;
     206: astore        11
     208: aload         11
     210: invokeinterface #71,  1           // InterfaceMethod java/util/Iterator.hasNext:()Z
     215: ifeq          247
     218: aload         11
     220: invokeinterface #72,  1           // InterfaceMethod java/util/Iterator.next:()Ljava/lang/Object;
     225: checkcast     #97                 // class java/lang/String
     228: astore        12
     230: aload         10
     232: aload         12
     234: aload         8
     236: aload         12
     238: invokevirtual #109                // Method org/hibernate/ogm/datastore/spi/Tuple.get:(Ljava/lang/String;)Ljava/lang/Object;
     241: invokevirtual #110                // Method org/hibernate/ogm/datastore/spi/Tuple.put:(Ljava/lang/String;Ljava/lang/Object;)V
     244: goto          208
     247: aload         9
     249: aload         10
     251: putfield      #90                 // Field org/hibernate/ogm/persister/OgmCollectionPersister$RowKeyAndTuple.tuple:Lorg/hibernate/ogm/datastore/spi/Tuple;
     254: aload         9
     256: areturn

  public org.hibernate.ogm.grid.impl.RowKeyBuilder initializeRowKeyBuilder();
    Code:
       0: new           #111                // class org/hibernate/ogm/grid/impl/RowKeyBuilder
       3: dup
       4: invokespecial #112                // Method org/hibernate/ogm/grid/impl/RowKeyBuilder."<init>":()V
       7: aload_0
       8: invokevirtual #63                 // Method getTableName:()Ljava/lang/String;
      11: invokevirtual #113                // Method org/hibernate/ogm/grid/impl/RowKeyBuilder.tableName:(Ljava/lang/String;)Lorg/hibernate/ogm/grid/impl/RowKeyBuilder;
      14: astore_1
      15: aload_0
      16: getfield      #95                 // Field hasIdentifier:Z
      19: ifeq          41
      22: aload_1
      23: iconst_1
      24: anewarray     #97                 // class java/lang/String
      27: dup
      28: iconst_0
      29: aload_0
      30: invokevirtual #43                 // Method getIdentifierColumnName:()Ljava/lang/String;
      33: aastore
      34: invokevirtual #114                // Method org/hibernate/ogm/grid/impl/RowKeyBuilder.addColumns:([Ljava/lang/String;)Lorg/hibernate/ogm/grid/impl/RowKeyBuilder;
      37: pop
      38: goto          92
      41: aload_1
      42: aload_0
      43: invokevirtual #45                 // Method getKeyColumnNames:()[Ljava/lang/String;
      46: invokevirtual #114                // Method org/hibernate/ogm/grid/impl/RowKeyBuilder.addColumns:([Ljava/lang/String;)Lorg/hibernate/ogm/grid/impl/RowKeyBuilder;
      49: pop
      50: aload_0
      51: invokevirtual #115                // Method isOneToMany:()Z
      54: ifne          83
      57: aload_0
      58: getfield      #98                 // Field hasIndex:Z
      61: ifeq          83
      64: aload_0
      65: getfield      #116                // Field indexContainsFormula:Z
      68: ifne          83
      71: aload_1
      72: aload_0
      73: invokevirtual #46                 // Method getIndexColumnNames:()[Ljava/lang/String;
      76: invokevirtual #114                // Method org/hibernate/ogm/grid/impl/RowKeyBuilder.addColumns:([Ljava/lang/String;)Lorg/hibernate/ogm/grid/impl/RowKeyBuilder;
      79: pop
      80: goto          92
      83: aload_1
      84: aload_0
      85: invokevirtual #47                 // Method getElementColumnNames:()[Ljava/lang/String;
      88: invokevirtual #114                // Method org/hibernate/ogm/grid/impl/RowKeyBuilder.addColumns:([Ljava/lang/String;)Lorg/hibernate/ogm/grid/impl/RowKeyBuilder;
      91: pop
      92: aload_1
      93: areturn

  public java.lang.String[] getRowKeyColumnNames();
    Code:
       0: aload_0
       1: invokevirtual #91                 // Method initializeRowKeyBuilder:()Lorg/hibernate/ogm/grid/impl/RowKeyBuilder;
       4: invokevirtual #117                // Method org/hibernate/ogm/grid/impl/RowKeyBuilder.getColumnNames:()[Ljava/lang/String;
       7: areturn

  private org.hibernate.ogm.grid.RowKey getTupleKeyForUpdate(java.io.Serializable, org.hibernate.collection.spi.PersistentCollection, org.hibernate.engine.spi.SessionImplementor, int, java.lang.Object);
    Code:
       0: aload_0
       1: invokevirtual #91                 // Method initializeRowKeyBuilder:()Lorg/hibernate/ogm/grid/impl/RowKeyBuilder;
       4: astore        6
       6: new           #92                 // class org/hibernate/ogm/datastore/spi/Tuple
       9: dup
      10: getstatic     #93                 // Field org/hibernate/ogm/datastore/impl/EmptyTupleSnapshot.SINGLETON:Lorg/hibernate/ogm/datastore/spi/TupleSnapshot;
      13: invokespecial #94                 // Method org/hibernate/ogm/datastore/spi/Tuple."<init>":(Lorg/hibernate/ogm/datastore/spi/TupleSnapshot;)V
      16: astore        7
      18: aload_0
      19: getfield      #95                 // Field hasIdentifier:Z
      22: ifeq          69
      25: aload_2
      26: aload         5
      28: iload         4
      30: invokeinterface #96,  3           // InterfaceMethod org/hibernate/collection/spi/PersistentCollection.getIdentifier:(Ljava/lang/Object;I)Ljava/lang/Object;
      35: astore        8
      37: iconst_1
      38: anewarray     #97                 // class java/lang/String
      41: dup
      42: iconst_0
      43: aload_0
      44: invokevirtual #43                 // Method getIdentifierColumnName:()Ljava/lang/String;
      47: aastore
      48: astore        9
      50: aload_0
      51: getfield      #16                 // Field identifierGridType:Lorg/hibernate/ogm/type/GridType;
      54: aload         7
      56: aload         8
      58: aload         9
      60: aload_3
      61: invokeinterface #87,  5           // InterfaceMethod org/hibernate/ogm/type/GridType.nullSafeSet:(Lorg/hibernate/ogm/datastore/spi/Tuple;Ljava/lang/Object;[Ljava/lang/String;Lorg/hibernate/engine/spi/SessionImplementor;)V
      66: goto          192
      69: aload_0
      70: invokevirtual #67                 // Method getKeyGridType:()Lorg/hibernate/ogm/type/GridType;
      73: aload         7
      75: aload_1
      76: aload_0
      77: invokevirtual #45                 // Method getKeyColumnNames:()[Ljava/lang/String;
      80: aload_3
      81: invokeinterface #87,  5           // InterfaceMethod org/hibernate/ogm/type/GridType.nullSafeSet:(Lorg/hibernate/ogm/datastore/spi/Tuple;Ljava/lang/Object;[Ljava/lang/String;Lorg/hibernate/engine/spi/SessionImplementor;)V
      86: aload_0
      87: invokevirtual #115                // Method isOneToMany:()Z
      90: ifne          145
      93: aload_0
      94: getfield      #98                 // Field hasIndex:Z
      97: ifeq          145
     100: aload_0
     101: getfield      #116                // Field indexContainsFormula:Z
     104: ifne          145
     107: aload_2
     108: aload         5
     110: iload         4
     112: aload_0
     113: invokeinterface #99,  4           // InterfaceMethod org/hibernate/collection/spi/PersistentCollection.getIndex:(Ljava/lang/Object;ILorg/hibernate/persister/collection/CollectionPersister;)Ljava/lang/Object;
     118: astore        8
     120: aload_0
     121: getfield      #14                 // Field indexGridType:Lorg/hibernate/ogm/type/GridType;
     124: aload         7
     126: aload_0
     127: aload         8
     129: invokevirtual #100                // Method incrementIndexByBase:(Ljava/lang/Object;)Ljava/lang/Object;
     132: aload_0
     133: invokevirtual #46                 // Method getIndexColumnNames:()[Ljava/lang/String;
     136: aload_3
     137: invokeinterface #87,  5           // InterfaceMethod org/hibernate/ogm/type/GridType.nullSafeSet:(Lorg/hibernate/ogm/datastore/spi/Tuple;Ljava/lang/Object;[Ljava/lang/String;Lorg/hibernate/engine/spi/SessionImplementor;)V
     142: goto          192
     145: aload_2
     146: aload         5
     148: iload         4
     150: invokeinterface #118,  3          // InterfaceMethod org/hibernate/collection/spi/PersistentCollection.getSnapshotElement:(Ljava/lang/Object;I)Ljava/lang/Object;
     155: astore        8
     157: aload_0
     158: getfield      #119                // Field elementIsPureFormula:Z
     161: ifeq          174
     164: new           #28                 // class org/hibernate/annotations/common/AssertionFailure
     167: dup
     168: ldc           #120                // String cannot use a formula-based element in the where condition
     170: invokespecial #35                 // Method org/hibernate/annotations/common/AssertionFailure."<init>":(Ljava/lang/String;)V
     173: athrow
     174: aload_0
     175: invokevirtual #85                 // Method getElementGridType:()Lorg/hibernate/ogm/type/GridType;
     178: aload         7
     180: aload         8
     182: aload_0
     183: invokevirtual #47                 // Method getElementColumnNames:()[Ljava/lang/String;
     186: aload_3
     187: invokeinterface #87,  5           // InterfaceMethod org/hibernate/ogm/type/GridType.nullSafeSet:(Lorg/hibernate/ogm/datastore/spi/Tuple;Ljava/lang/Object;[Ljava/lang/String;Lorg/hibernate/engine/spi/SessionImplementor;)V
     192: aload         6
     194: aload         7
     196: invokevirtual #103                // Method org/hibernate/ogm/grid/impl/RowKeyBuilder.values:(Lorg/hibernate/ogm/datastore/spi/Tuple;)Lorg/hibernate/ogm/grid/impl/RowKeyBuilder;
     199: invokevirtual #104                // Method org/hibernate/ogm/grid/impl/RowKeyBuilder.build:()Lorg/hibernate/ogm/grid/RowKey;
     202: areturn

  private org.hibernate.ogm.grid.RowKey getTupleKeyForDelete(java.io.Serializable, org.hibernate.collection.spi.PersistentCollection, org.hibernate.engine.spi.SessionImplementor, java.lang.Object, boolean);
    Code:
       0: aload_0
       1: invokevirtual #91                 // Method initializeRowKeyBuilder:()Lorg/hibernate/ogm/grid/impl/RowKeyBuilder;
       4: astore        6
       6: new           #92                 // class org/hibernate/ogm/datastore/spi/Tuple
       9: dup
      10: getstatic     #93                 // Field org/hibernate/ogm/datastore/impl/EmptyTupleSnapshot.SINGLETON:Lorg/hibernate/ogm/datastore/spi/TupleSnapshot;
      13: invokespecial #94                 // Method org/hibernate/ogm/datastore/spi/Tuple."<init>":(Lorg/hibernate/ogm/datastore/spi/TupleSnapshot;)V
      16: astore        7
      18: aload_0
      19: getfield      #95                 // Field hasIdentifier:Z
      22: ifeq          61
      25: aload         4
      27: astore        8
      29: iconst_1
      30: anewarray     #97                 // class java/lang/String
      33: dup
      34: iconst_0
      35: aload_0
      36: invokevirtual #43                 // Method getIdentifierColumnName:()Ljava/lang/String;
      39: aastore
      40: astore        9
      42: aload_0
      43: getfield      #16                 // Field identifierGridType:Lorg/hibernate/ogm/type/GridType;
      46: aload         7
      48: aload         8
      50: aload         9
      52: aload_3
      53: invokeinterface #87,  5           // InterfaceMethod org/hibernate/ogm/type/GridType.nullSafeSet:(Lorg/hibernate/ogm/datastore/spi/Tuple;Ljava/lang/Object;[Ljava/lang/String;Lorg/hibernate/engine/spi/SessionImplementor;)V
      58: goto          151
      61: aload_0
      62: invokevirtual #67                 // Method getKeyGridType:()Lorg/hibernate/ogm/type/GridType;
      65: aload         7
      67: aload_1
      68: aload_0
      69: invokevirtual #45                 // Method getKeyColumnNames:()[Ljava/lang/String;
      72: aload_3
      73: invokeinterface #87,  5           // InterfaceMethod org/hibernate/ogm/type/GridType.nullSafeSet:(Lorg/hibernate/ogm/datastore/spi/Tuple;Ljava/lang/Object;[Ljava/lang/String;Lorg/hibernate/engine/spi/SessionImplementor;)V
      78: iload         5
      80: ifeq          112
      83: aload         4
      85: astore        8
      87: aload_0
      88: getfield      #14                 // Field indexGridType:Lorg/hibernate/ogm/type/GridType;
      91: aload         7
      93: aload_0
      94: aload         8
      96: invokevirtual #100                // Method incrementIndexByBase:(Ljava/lang/Object;)Ljava/lang/Object;
      99: aload_0
     100: invokevirtual #46                 // Method getIndexColumnNames:()[Ljava/lang/String;
     103: aload_3
     104: invokeinterface #87,  5           // InterfaceMethod org/hibernate/ogm/type/GridType.nullSafeSet:(Lorg/hibernate/ogm/datastore/spi/Tuple;Ljava/lang/Object;[Ljava/lang/String;Lorg/hibernate/engine/spi/SessionImplementor;)V
     109: goto          151
     112: aload         4
     114: astore        8
     116: aload_0
     117: getfield      #119                // Field elementIsPureFormula:Z
     120: ifeq          133
     123: new           #28                 // class org/hibernate/annotations/common/AssertionFailure
     126: dup
     127: ldc           #120                // String cannot use a formula-based element in the where condition
     129: invokespecial #35                 // Method org/hibernate/annotations/common/AssertionFailure."<init>":(Ljava/lang/String;)V
     132: athrow
     133: aload_0
     134: invokevirtual #85                 // Method getElementGridType:()Lorg/hibernate/ogm/type/GridType;
     137: aload         7
     139: aload         8
     141: aload_0
     142: invokevirtual #47                 // Method getElementColumnNames:()[Ljava/lang/String;
     145: aload_3
     146: invokeinterface #87,  5           // InterfaceMethod org/hibernate/ogm/type/GridType.nullSafeSet:(Lorg/hibernate/ogm/datastore/spi/Tuple;Ljava/lang/Object;[Ljava/lang/String;Lorg/hibernate/engine/spi/SessionImplementor;)V
     151: aload         6
     153: aload         7
     155: invokevirtual #103                // Method org/hibernate/ogm/grid/impl/RowKeyBuilder.values:(Lorg/hibernate/ogm/datastore/spi/Tuple;)Lorg/hibernate/ogm/grid/impl/RowKeyBuilder;
     158: pop
     159: aload         6
     161: invokevirtual #104                // Method org/hibernate/ogm/grid/impl/RowKeyBuilder.build:()Lorg/hibernate/ogm/grid/RowKey;
     164: areturn

  public int getSize(java.io.Serializable, org.hibernate.engine.spi.SessionImplementor);
    Code:
       0: new           #60                 // class org/hibernate/ogm/util/impl/PropertyMetadataProvider
       3: dup
       4: invokespecial #61                 // Method org/hibernate/ogm/util/impl/PropertyMetadataProvider."<init>":()V
       7: aload_1
       8: invokevirtual #65                 // Method org/hibernate/ogm/util/impl/PropertyMetadataProvider.key:(Ljava/lang/Object;)Lorg/hibernate/ogm/util/impl/PropertyMetadataProvider;
      11: aload_0
      12: invokevirtual #63                 // Method getTableName:()Ljava/lang/String;
      15: invokevirtual #64                 // Method org/hibernate/ogm/util/impl/PropertyMetadataProvider.tableName:(Ljava/lang/String;)Lorg/hibernate/ogm/util/impl/PropertyMetadataProvider;
      18: aload_2
      19: invokevirtual #70                 // Method org/hibernate/ogm/util/impl/PropertyMetadataProvider.session:(Lorg/hibernate/engine/spi/SessionImplementor;)Lorg/hibernate/ogm/util/impl/PropertyMetadataProvider;
      22: aload_0
      23: getfield      #7                  // Field gridDialect:Lorg/hibernate/ogm/dialect/GridDialect;
      26: invokevirtual #62                 // Method org/hibernate/ogm/util/impl/PropertyMetadataProvider.gridDialect:(Lorg/hibernate/ogm/dialect/GridDialect;)Lorg/hibernate/ogm/util/impl/PropertyMetadataProvider;
      29: aload_0
      30: invokevirtual #63                 // Method getTableName:()Ljava/lang/String;
      33: invokevirtual #64                 // Method org/hibernate/ogm/util/impl/PropertyMetadataProvider.tableName:(Ljava/lang/String;)Lorg/hibernate/ogm/util/impl/PropertyMetadataProvider;
      36: aload_0
      37: invokevirtual #67                 // Method getKeyGridType:()Lorg/hibernate/ogm/type/GridType;
      40: invokevirtual #68                 // Method org/hibernate/ogm/util/impl/PropertyMetadataProvider.keyGridType:(Lorg/hibernate/ogm/type/GridType;)Lorg/hibernate/ogm/util/impl/PropertyMetadataProvider;
      43: aload_0
      44: invokevirtual #69                 // Method org/hibernate/ogm/util/impl/PropertyMetadataProvider.collectionPersister:(Lorg/hibernate/ogm/persister/OgmCollectionPersister;)Lorg/hibernate/ogm/util/impl/PropertyMetadataProvider;
      47: aload_0
      48: invokevirtual #45                 // Method getKeyColumnNames:()[Ljava/lang/String;
      51: invokevirtual #66                 // Method org/hibernate/ogm/util/impl/PropertyMetadataProvider.keyColumnNames:([Ljava/lang/String;)Lorg/hibernate/ogm/util/impl/PropertyMetadataProvider;
      54: astore_3
      55: aload_3
      56: invokevirtual #121                // Method org/hibernate/ogm/util/impl/PropertyMetadataProvider.getCollectionMetadataOrNull:()Lorg/hibernate/ogm/datastore/spi/Association;
      59: astore        4
      61: aload         4
      63: ifnonnull     70
      66: iconst_0
      67: goto          75
      70: aload         4
      72: invokevirtual #122                // Method org/hibernate/ogm/datastore/spi/Association.size:()I
      75: ireturn

  public org.hibernate.internal.FilterAliasGenerator getFilterAliasGenerator(java.lang.String);
    Code:
       0: new           #123                // class org/hibernate/internal/StaticFilterAliasGenerator
       3: dup
       4: aload_1
       5: invokespecial #124                // Method org/hibernate/internal/StaticFilterAliasGenerator."<init>":(Ljava/lang/String;)V
       8: areturn

  public void deleteRows(org.hibernate.collection.spi.PersistentCollection, java.io.Serializable, org.hibernate.engine.spi.SessionImplementor) throws org.hibernate.HibernateException;
    Code:
       0: aload_0
       1: getfield      #18                 // Field isInverse:Z
       4: ifne          362
       7: aload_0
       8: invokevirtual #125                // Method isRowDeleteEnabled:()Z
      11: ifeq          362
      14: getstatic     #126                // Field log:Lorg/hibernate/ogm/util/impl/Log;
      17: invokeinterface #127,  1          // InterfaceMethod org/hibernate/ogm/util/impl/Log.isDebugEnabled:()Z
      22: ifeq          60
      25: getstatic     #126                // Field log:Lorg/hibernate/ogm/util/impl/Log;
      28: new           #29                 // class java/lang/StringBuilder
      31: dup
      32: invokespecial #30                 // Method java/lang/StringBuilder."<init>":()V
      35: ldc           #128                // String Deleting rows of collection:
      37: invokevirtual #32                 // Method java/lang/StringBuilder.append:(Ljava/lang/String;)Ljava/lang/StringBuilder;
      40: aload_0
      41: aload_2
      42: aload_0
      43: invokevirtual #129                // Method getFactory:()Lorg/hibernate/engine/spi/SessionFactoryImplementor;
      46: invokestatic  #130                // Method org/hibernate/pretty/MessageHelper.collectionInfoString:(Lorg/hibernate/persister/collection/CollectionPersister;Ljava/io/Serializable;Lorg/hibernate/engine/spi/SessionFactoryImplementor;)Ljava/lang/String;
      49: invokevirtual #32                 // Method java/lang/StringBuilder.append:(Ljava/lang/String;)Ljava/lang/StringBuilder;
      52: invokevirtual #34                 // Method java/lang/StringBuilder.toString:()Ljava/lang/String;
      55: invokeinterface #131,  2          // InterfaceMethod org/hibernate/ogm/util/impl/Log.debug:(Ljava/lang/Object;)V
      60: aload_0
      61: invokevirtual #115                // Method isOneToMany:()Z
      64: ifne          85
      67: aload_0
      68: getfield      #98                 // Field hasIndex:Z
      71: ifeq          85
      74: aload_0
      75: getfield      #116                // Field indexContainsFormula:Z
      78: ifne          85
      81: iconst_1
      82: goto          86
      85: iconst_0
      86: istore        4
      88: new           #60                 // class org/hibernate/ogm/util/impl/PropertyMetadataProvider
      91: dup
      92: invokespecial #61                 // Method org/hibernate/ogm/util/impl/PropertyMetadataProvider."<init>":()V
      95: aload_0
      96: getfield      #7                  // Field gridDialect:Lorg/hibernate/ogm/dialect/GridDialect;
      99: invokevirtual #62                 // Method org/hibernate/ogm/util/impl/PropertyMetadataProvider.gridDialect:(Lorg/hibernate/ogm/dialect/GridDialect;)Lorg/hibernate/ogm/util/impl/PropertyMetadataProvider;
     102: aload_0
     103: invokevirtual #63                 // Method getTableName:()Ljava/lang/String;
     106: invokevirtual #64                 // Method org/hibernate/ogm/util/impl/PropertyMetadataProvider.tableName:(Ljava/lang/String;)Lorg/hibernate/ogm/util/impl/PropertyMetadataProvider;
     109: aload_2
     110: invokevirtual #65                 // Method org/hibernate/ogm/util/impl/PropertyMetadataProvider.key:(Ljava/lang/Object;)Lorg/hibernate/ogm/util/impl/PropertyMetadataProvider;
     113: aload_0
     114: invokevirtual #45                 // Method getKeyColumnNames:()[Ljava/lang/String;
     117: invokevirtual #66                 // Method org/hibernate/ogm/util/impl/PropertyMetadataProvider.keyColumnNames:([Ljava/lang/String;)Lorg/hibernate/ogm/util/impl/PropertyMetadataProvider;
     120: aload_0
     121: invokevirtual #67                 // Method getKeyGridType:()Lorg/hibernate/ogm/type/GridType;
     124: invokevirtual #68                 // Method org/hibernate/ogm/util/impl/PropertyMetadataProvider.keyGridType:(Lorg/hibernate/ogm/type/GridType;)Lorg/hibernate/ogm/util/impl/PropertyMetadataProvider;
     127: aload_0
     128: invokevirtual #69                 // Method org/hibernate/ogm/util/impl/PropertyMetadataProvider.collectionPersister:(Lorg/hibernate/ogm/persister/OgmCollectionPersister;)Lorg/hibernate/ogm/util/impl/PropertyMetadataProvider;
     131: aload_3
     132: invokevirtual #70                 // Method org/hibernate/ogm/util/impl/PropertyMetadataProvider.session:(Lorg/hibernate/engine/spi/SessionImplementor;)Lorg/hibernate/ogm/util/impl/PropertyMetadataProvider;
     135: astore        5
     137: aload_1
     138: aload_0
     139: iload         4
     141: ifne          148
     144: iconst_1
     145: goto          149
     148: iconst_0
     149: invokeinterface #132,  3          // InterfaceMethod org/hibernate/collection/spi/PersistentCollection.getDeletes:(Lorg/hibernate/persister/collection/CollectionPersister;Z)Ljava/util/Iterator;
     154: astore        6
     156: aload         6
     158: invokeinterface #71,  1           // InterfaceMethod java/util/Iterator.hasNext:()Z
     163: ifeq          352
     166: iconst_0
     167: istore        7
     169: aload         6
     171: invokeinterface #71,  1           // InterfaceMethod java/util/Iterator.hasNext:()Z
     176: ifeq          344
     179: aload         6
     181: invokeinterface #72,  1           // InterfaceMethod java/util/Iterator.next:()Ljava/lang/Object;
     186: astore        8
     188: aload_0
     189: aload_2
     190: aload_1
     191: aload_3
     192: aload         8
     194: iload         4
     196: invokespecial #133                // Method getTupleKeyForDelete:(Ljava/io/Serializable;Lorg/hibernate/collection/spi/PersistentCollection;Lorg/hibernate/engine/spi/SessionImplementor;Ljava/lang/Object;Z)Lorg/hibernate/ogm/grid/RowKey;
     199: astore        9
     201: aload         5
     203: invokevirtual #76                 // Method org/hibernate/ogm/util/impl/PropertyMetadataProvider.getCollectionMetadata:()Lorg/hibernate/ogm/datastore/spi/Association;
     206: aload         9
     208: invokevirtual #77                 // Method org/hibernate/ogm/datastore/spi/Association.get:(Lorg/hibernate/ogm/grid/RowKey;)Lorg/hibernate/ogm/datastore/spi/Tuple;
     211: astore        10
     213: aload         10
     215: ifnonnull     272
     218: new           #28                 // class org/hibernate/annotations/common/AssertionFailure
     221: dup
     222: new           #29                 // class java/lang/StringBuilder
     225: dup
     226: invokespecial #30                 // Method java/lang/StringBuilder."<init>":()V
     229: ldc           #134                // String Deleting a collection tuple that is not present: table {
     231: invokevirtual #32                 // Method java/lang/StringBuilder.append:(Ljava/lang/String;)Ljava/lang/StringBuilder;
     234: aload_0
     235: invokevirtual #63                 // Method getTableName:()Ljava/lang/String;
     238: invokevirtual #32                 // Method java/lang/StringBuilder.append:(Ljava/lang/String;)Ljava/lang/StringBuilder;
     241: ldc           #79                 // String } collectionKey {
     243: invokevirtual #32                 // Method java/lang/StringBuilder.append:(Ljava/lang/String;)Ljava/lang/StringBuilder;
     246: aload_2
     247: invokevirtual #80                 // Method java/lang/StringBuilder.append:(Ljava/lang/Object;)Ljava/lang/StringBuilder;
     250: ldc           #81                 // String } entry {
     252: invokevirtual #32                 // Method java/lang/StringBuilder.append:(Ljava/lang/String;)Ljava/lang/StringBuilder;
     255: aload         8
     257: invokevirtual #80                 // Method java/lang/StringBuilder.append:(Ljava/lang/Object;)Ljava/lang/StringBuilder;
     260: ldc           #82                 // String }
     262: invokevirtual #32                 // Method java/lang/StringBuilder.append:(Ljava/lang/String;)Ljava/lang/StringBuilder;
     265: invokevirtual #34                 // Method java/lang/StringBuilder.toString:()Ljava/lang/String;
     268: invokespecial #35                 // Method org/hibernate/annotations/common/AssertionFailure."<init>":(Ljava/lang/String;)V
     271: athrow
     272: aload_0
     273: aload_3
     274: aload         10
     276: getstatic     #83                 // Field org/hibernate/ogm/persister/OgmCollectionPersister$Action.REMOVE:Lorg/hibernate/ogm/persister/OgmCollectionPersister$Action;
     279: aload         9
     281: invokespecial #84                 // Method updateInverseSideOfAssociationNavigation:(Lorg/hibernate/engine/spi/SessionImplementor;Lorg/hibernate/ogm/datastore/spi/Tuple;Lorg/hibernate/ogm/persister/OgmCollectionPersister$Action;Lorg/hibernate/ogm/grid/RowKey;)V
     284: aload         5
     286: invokevirtual #76                 // Method org/hibernate/ogm/util/impl/PropertyMetadataProvider.getCollectionMetadata:()Lorg/hibernate/ogm/datastore/spi/Association;
     289: aload         9
     291: invokevirtual #135                // Method org/hibernate/ogm/datastore/spi/Association.remove:(Lorg/hibernate/ogm/grid/RowKey;)V
     294: iinc          7, 1
     297: getstatic     #126                // Field log:Lorg/hibernate/ogm/util/impl/Log;
     300: invokeinterface #127,  1          // InterfaceMethod org/hibernate/ogm/util/impl/Log.isDebugEnabled:()Z
     305: ifeq          341
     308: getstatic     #126                // Field log:Lorg/hibernate/ogm/util/impl/Log;
     311: new           #29                 // class java/lang/StringBuilder
     314: dup
     315: invokespecial #30                 // Method java/lang/StringBuilder."<init>":()V
     318: ldc           #136                // String done deleting collection rows:
     320: invokevirtual #32                 // Method java/lang/StringBuilder.append:(Ljava/lang/String;)Ljava/lang/StringBuilder;
     323: iload         7
     325: invokevirtual #137                // Method java/lang/StringBuilder.append:(I)Ljava/lang/StringBuilder;
     328: ldc           #138                // String  deleted
     330: invokevirtual #32                 // Method java/lang/StringBuilder.append:(Ljava/lang/String;)Ljava/lang/StringBuilder;
     333: invokevirtual #34                 // Method java/lang/StringBuilder.toString:()Ljava/lang/String;
     336: invokeinterface #131,  2          // InterfaceMethod org/hibernate/ogm/util/impl/Log.debug:(Ljava/lang/Object;)V
     341: goto          169
     344: aload         5
     346: invokevirtual #89                 // Method org/hibernate/ogm/util/impl/PropertyMetadataProvider.flushToCache:()V
     349: goto          362
     352: getstatic     #126                // Field log:Lorg/hibernate/ogm/util/impl/Log;
     355: ldc           #139                // String no rows to delete
     357: invokeinterface #131,  2          // InterfaceMethod org/hibernate/ogm/util/impl/Log.debug:(Ljava/lang/Object;)V
     362: return

  public void insertRows(org.hibernate.collection.spi.PersistentCollection, java.io.Serializable, org.hibernate.engine.spi.SessionImplementor) throws org.hibernate.HibernateException;
    Code:
       0: aload_0
       1: getfield      #18                 // Field isInverse:Z
       4: ifne          279
       7: aload_0
       8: invokevirtual #140                // Method isRowInsertEnabled:()Z
      11: ifeq          279
      14: getstatic     #126                // Field log:Lorg/hibernate/ogm/util/impl/Log;
      17: invokeinterface #127,  1          // InterfaceMethod org/hibernate/ogm/util/impl/Log.isDebugEnabled:()Z
      22: ifeq          60
      25: getstatic     #126                // Field log:Lorg/hibernate/ogm/util/impl/Log;
      28: new           #29                 // class java/lang/StringBuilder
      31: dup
      32: invokespecial #30                 // Method java/lang/StringBuilder."<init>":()V
      35: ldc           #141                // String Inserting rows of collection:
      37: invokevirtual #32                 // Method java/lang/StringBuilder.append:(Ljava/lang/String;)Ljava/lang/StringBuilder;
      40: aload_0
      41: aload_2
      42: aload_0
      43: invokevirtual #129                // Method getFactory:()Lorg/hibernate/engine/spi/SessionFactoryImplementor;
      46: invokestatic  #130                // Method org/hibernate/pretty/MessageHelper.collectionInfoString:(Lorg/hibernate/persister/collection/CollectionPersister;Ljava/io/Serializable;Lorg/hibernate/engine/spi/SessionFactoryImplementor;)Ljava/lang/String;
      49: invokevirtual #32                 // Method java/lang/StringBuilder.append:(Ljava/lang/String;)Ljava/lang/StringBuilder;
      52: invokevirtual #34                 // Method java/lang/StringBuilder.toString:()Ljava/lang/String;
      55: invokeinterface #131,  2          // InterfaceMethod org/hibernate/ogm/util/impl/Log.debug:(Ljava/lang/Object;)V
      60: new           #60                 // class org/hibernate/ogm/util/impl/PropertyMetadataProvider
      63: dup
      64: invokespecial #61                 // Method org/hibernate/ogm/util/impl/PropertyMetadataProvider."<init>":()V
      67: aload_0
      68: getfield      #7                  // Field gridDialect:Lorg/hibernate/ogm/dialect/GridDialect;
      71: invokevirtual #62                 // Method org/hibernate/ogm/util/impl/PropertyMetadataProvider.gridDialect:(Lorg/hibernate/ogm/dialect/GridDialect;)Lorg/hibernate/ogm/util/impl/PropertyMetadataProvider;
      74: aload_0
      75: invokevirtual #63                 // Method getTableName:()Ljava/lang/String;
      78: invokevirtual #64                 // Method org/hibernate/ogm/util/impl/PropertyMetadataProvider.tableName:(Ljava/lang/String;)Lorg/hibernate/ogm/util/impl/PropertyMetadataProvider;
      81: aload_2
      82: invokevirtual #65                 // Method org/hibernate/ogm/util/impl/PropertyMetadataProvider.key:(Ljava/lang/Object;)Lorg/hibernate/ogm/util/impl/PropertyMetadataProvider;
      85: aload_0
      86: invokevirtual #45                 // Method getKeyColumnNames:()[Ljava/lang/String;
      89: invokevirtual #66                 // Method org/hibernate/ogm/util/impl/PropertyMetadataProvider.keyColumnNames:([Ljava/lang/String;)Lorg/hibernate/ogm/util/impl/PropertyMetadataProvider;
      92: aload_0
      93: invokevirtual #67                 // Method getKeyGridType:()Lorg/hibernate/ogm/type/GridType;
      96: invokevirtual #68                 // Method org/hibernate/ogm/util/impl/PropertyMetadataProvider.keyGridType:(Lorg/hibernate/ogm/type/GridType;)Lorg/hibernate/ogm/util/impl/PropertyMetadataProvider;
      99: aload_0
     100: invokevirtual #69                 // Method org/hibernate/ogm/util/impl/PropertyMetadataProvider.collectionPersister:(Lorg/hibernate/ogm/persister/OgmCollectionPersister;)Lorg/hibernate/ogm/util/impl/PropertyMetadataProvider;
     103: aload_3
     104: invokevirtual #70                 // Method org/hibernate/ogm/util/impl/PropertyMetadataProvider.session:(Lorg/hibernate/engine/spi/SessionImplementor;)Lorg/hibernate/ogm/util/impl/PropertyMetadataProvider;
     107: astore        4
     109: aload_1
     110: aload_0
     111: invokeinterface #142,  2          // InterfaceMethod org/hibernate/collection/spi/PersistentCollection.preInsert:(Lorg/hibernate/persister/collection/CollectionPersister;)V
     116: aload_1
     117: aload_0
     118: invokeinterface #59,  2           // InterfaceMethod org/hibernate/collection/spi/PersistentCollection.entries:(Lorg/hibernate/persister/collection/CollectionPersister;)Ljava/util/Iterator;
     123: astore        5
     125: iconst_0
     126: istore        6
     128: iconst_0
     129: istore        7
     131: aload         5
     133: invokeinterface #71,  1           // InterfaceMethod java/util/Iterator.hasNext:()Z
     138: ifeq          230
     141: aload         5
     143: invokeinterface #72,  1           // InterfaceMethod java/util/Iterator.next:()Ljava/lang/Object;
     148: astore        8
     150: aload_1
     151: aload         8
     153: iload         6
     155: aload_0
     156: getfield      #73                 // Field elementType:Lorg/hibernate/type/Type;
     159: invokeinterface #143,  4          // InterfaceMethod org/hibernate/collection/spi/PersistentCollection.needsInserting:(Ljava/lang/Object;ILorg/hibernate/type/Type;)Z
     164: ifeq          224
     167: aload_0
     168: aload_2
     169: aload_1
     170: aload         4
     172: aload_3
     173: iload         6
     175: aload         8
     177: invokespecial #144                // Method createAndPutTupleforInsert:(Ljava/io/Serializable;Lorg/hibernate/collection/spi/PersistentCollection;Lorg/hibernate/ogm/util/impl/PropertyMetadataProvider;Lorg/hibernate/engine/spi/SessionImplementor;ILjava/lang/Object;)Lorg/hibernate/ogm/persister/OgmCollectionPersister$RowKeyAndTuple;
     180: astore        9
     182: aload_0
     183: aload         9
     185: aload_1
     186: aload_3
     187: aload         8
     189: invokespecial #145                // Method completeTuple:(Lorg/hibernate/ogm/persister/OgmCollectionPersister$RowKeyAndTuple;Lorg/hibernate/collection/spi/PersistentCollection;Lorg/hibernate/engine/spi/SessionImplementor;Ljava/lang/Object;)V
     192: aload_0
     193: aload_3
     194: aload         9
     196: getfield      #90                 // Field org/hibernate/ogm/persister/OgmCollectionPersister$RowKeyAndTuple.tuple:Lorg/hibernate/ogm/datastore/spi/Tuple;
     199: getstatic     #88                 // Field org/hibernate/ogm/persister/OgmCollectionPersister$Action.ADD:Lorg/hibernate/ogm/persister/OgmCollectionPersister$Action;
     202: aload         9
     204: getfield      #105                // Field org/hibernate/ogm/persister/OgmCollectionPersister$RowKeyAndTuple.key:Lorg/hibernate/ogm/grid/RowKey;
     207: invokespecial #84                 // Method updateInverseSideOfAssociationNavigation:(Lorg/hibernate/engine/spi/SessionImplementor;Lorg/hibernate/ogm/datastore/spi/Tuple;Lorg/hibernate/ogm/persister/OgmCollectionPersister$Action;Lorg/hibernate/ogm/grid/RowKey;)V
     210: aload_1
     211: aload_0
     212: aload         8
     214: iload         6
     216: invokeinterface #146,  4          // InterfaceMethod org/hibernate/collection/spi/PersistentCollection.afterRowInsert:(Lorg/hibernate/persister/collection/CollectionPersister;Ljava/lang/Object;I)V
     221: iinc          7, 1
     224: iinc          6, 1
     227: goto          131
     230: aload         4
     232: invokevirtual #89                 // Method org/hibernate/ogm/util/impl/PropertyMetadataProvider.flushToCache:()V
     235: getstatic     #126                // Field log:Lorg/hibernate/ogm/util/impl/Log;
     238: invokeinterface #127,  1          // InterfaceMethod org/hibernate/ogm/util/impl/Log.isDebugEnabled:()Z
     243: ifeq          279
     246: getstatic     #126                // Field log:Lorg/hibernate/ogm/util/impl/Log;
     249: new           #29                 // class java/lang/StringBuilder
     252: dup
     253: invokespecial #30                 // Method java/lang/StringBuilder."<init>":()V
     256: ldc           #147                // String done inserting rows:
     258: invokevirtual #32                 // Method java/lang/StringBuilder.append:(Ljava/lang/String;)Ljava/lang/StringBuilder;
     261: iload         7
     263: invokevirtual #137                // Method java/lang/StringBuilder.append:(I)Ljava/lang/StringBuilder;
     266: ldc           #148                // String  inserted
     268: invokevirtual #32                 // Method java/lang/StringBuilder.append:(Ljava/lang/String;)Ljava/lang/StringBuilder;
     271: invokevirtual #34                 // Method java/lang/StringBuilder.toString:()Ljava/lang/String;
     274: invokeinterface #131,  2          // InterfaceMethod org/hibernate/ogm/util/impl/Log.debug:(Ljava/lang/Object;)V
     279: return

  public void recreate(org.hibernate.collection.spi.PersistentCollection, java.io.Serializable, org.hibernate.engine.spi.SessionImplementor) throws org.hibernate.HibernateException;
    Code:
       0: aload_0
       1: getfield      #18                 // Field isInverse:Z
       4: ifne          309
       7: aload_0
       8: invokevirtual #140                // Method isRowInsertEnabled:()Z
      11: ifeq          309
      14: getstatic     #126                // Field log:Lorg/hibernate/ogm/util/impl/Log;
      17: invokeinterface #127,  1          // InterfaceMethod org/hibernate/ogm/util/impl/Log.isDebugEnabled:()Z
      22: ifeq          60
      25: getstatic     #126                // Field log:Lorg/hibernate/ogm/util/impl/Log;
      28: new           #29                 // class java/lang/StringBuilder
      31: dup
      32: invokespecial #30                 // Method java/lang/StringBuilder."<init>":()V
      35: ldc           #149                // String Inserting collection:
      37: invokevirtual #32                 // Method java/lang/StringBuilder.append:(Ljava/lang/String;)Ljava/lang/StringBuilder;
      40: aload_0
      41: aload_2
      42: aload_0
      43: invokevirtual #129                // Method getFactory:()Lorg/hibernate/engine/spi/SessionFactoryImplementor;
      46: invokestatic  #130                // Method org/hibernate/pretty/MessageHelper.collectionInfoString:(Lorg/hibernate/persister/collection/CollectionPersister;Ljava/io/Serializable;Lorg/hibernate/engine/spi/SessionFactoryImplementor;)Ljava/lang/String;
      49: invokevirtual #32                 // Method java/lang/StringBuilder.append:(Ljava/lang/String;)Ljava/lang/StringBuilder;
      52: invokevirtual #34                 // Method java/lang/StringBuilder.toString:()Ljava/lang/String;
      55: invokeinterface #131,  2          // InterfaceMethod org/hibernate/ogm/util/impl/Log.debug:(Ljava/lang/Object;)V
      60: new           #60                 // class org/hibernate/ogm/util/impl/PropertyMetadataProvider
      63: dup
      64: invokespecial #61                 // Method org/hibernate/ogm/util/impl/PropertyMetadataProvider."<init>":()V
      67: aload_0
      68: getfield      #7                  // Field gridDialect:Lorg/hibernate/ogm/dialect/GridDialect;
      71: invokevirtual #62                 // Method org/hibernate/ogm/util/impl/PropertyMetadataProvider.gridDialect:(Lorg/hibernate/ogm/dialect/GridDialect;)Lorg/hibernate/ogm/util/impl/PropertyMetadataProvider;
      74: aload_0
      75: invokevirtual #63                 // Method getTableName:()Ljava/lang/String;
      78: invokevirtual #64                 // Method org/hibernate/ogm/util/impl/PropertyMetadataProvider.tableName:(Ljava/lang/String;)Lorg/hibernate/ogm/util/impl/PropertyMetadataProvider;
      81: aload_2
      82: invokevirtual #65                 // Method org/hibernate/ogm/util/impl/PropertyMetadataProvider.key:(Ljava/lang/Object;)Lorg/hibernate/ogm/util/impl/PropertyMetadataProvider;
      85: aload_0
      86: invokevirtual #45                 // Method getKeyColumnNames:()[Ljava/lang/String;
      89: invokevirtual #66                 // Method org/hibernate/ogm/util/impl/PropertyMetadataProvider.keyColumnNames:([Ljava/lang/String;)Lorg/hibernate/ogm/util/impl/PropertyMetadataProvider;
      92: aload_0
      93: invokevirtual #67                 // Method getKeyGridType:()Lorg/hibernate/ogm/type/GridType;
      96: invokevirtual #68                 // Method org/hibernate/ogm/util/impl/PropertyMetadataProvider.keyGridType:(Lorg/hibernate/ogm/type/GridType;)Lorg/hibernate/ogm/util/impl/PropertyMetadataProvider;
      99: aload_0
     100: invokevirtual #69                 // Method org/hibernate/ogm/util/impl/PropertyMetadataProvider.collectionPersister:(Lorg/hibernate/ogm/persister/OgmCollectionPersister;)Lorg/hibernate/ogm/util/impl/PropertyMetadataProvider;
     103: aload_3
     104: invokevirtual #70                 // Method org/hibernate/ogm/util/impl/PropertyMetadataProvider.session:(Lorg/hibernate/engine/spi/SessionImplementor;)Lorg/hibernate/ogm/util/impl/PropertyMetadataProvider;
     107: astore        4
     109: aload_1
     110: aload_0
     111: invokeinterface #59,  2           // InterfaceMethod org/hibernate/collection/spi/PersistentCollection.entries:(Lorg/hibernate/persister/collection/CollectionPersister;)Ljava/util/Iterator;
     116: astore        5
     118: aload         5
     120: invokeinterface #71,  1           // InterfaceMethod java/util/Iterator.hasNext:()Z
     125: ifeq          288
     128: aload_1
     129: aload_0
     130: invokeinterface #142,  2          // InterfaceMethod org/hibernate/collection/spi/PersistentCollection.preInsert:(Lorg/hibernate/persister/collection/CollectionPersister;)V
     135: iconst_0
     136: istore        6
     138: iconst_0
     139: istore        7
     141: aload         5
     143: invokeinterface #71,  1           // InterfaceMethod java/util/Iterator.hasNext:()Z
     148: ifeq          236
     151: aload         5
     153: invokeinterface #72,  1           // InterfaceMethod java/util/Iterator.next:()Ljava/lang/Object;
     158: astore        8
     160: aload_1
     161: aload         8
     163: iload         6
     165: invokeinterface #150,  3          // InterfaceMethod org/hibernate/collection/spi/PersistentCollection.entryExists:(Ljava/lang/Object;I)Z
     170: ifeq          230
     173: aload_0
     174: aload_2
     175: aload_1
     176: aload         4
     178: aload_3
     179: iload         6
     181: aload         8
     183: invokespecial #144                // Method createAndPutTupleforInsert:(Ljava/io/Serializable;Lorg/hibernate/collection/spi/PersistentCollection;Lorg/hibernate/ogm/util/impl/PropertyMetadataProvider;Lorg/hibernate/engine/spi/SessionImplementor;ILjava/lang/Object;)Lorg/hibernate/ogm/persister/OgmCollectionPersister$RowKeyAndTuple;
     186: astore        9
     188: aload_0
     189: aload         9
     191: aload_1
     192: aload_3
     193: aload         8
     195: invokespecial #145                // Method completeTuple:(Lorg/hibernate/ogm/persister/OgmCollectionPersister$RowKeyAndTuple;Lorg/hibernate/collection/spi/PersistentCollection;Lorg/hibernate/engine/spi/SessionImplementor;Ljava/lang/Object;)V
     198: aload_0
     199: aload_3
     200: aload         9
     202: getfield      #90                 // Field org/hibernate/ogm/persister/OgmCollectionPersister$RowKeyAndTuple.tuple:Lorg/hibernate/ogm/datastore/spi/Tuple;
     205: getstatic     #88                 // Field org/hibernate/ogm/persister/OgmCollectionPersister$Action.ADD:Lorg/hibernate/ogm/persister/OgmCollectionPersister$Action;
     208: aload         9
     210: getfield      #105                // Field org/hibernate/ogm/persister/OgmCollectionPersister$RowKeyAndTuple.key:Lorg/hibernate/ogm/grid/RowKey;
     213: invokespecial #84                 // Method updateInverseSideOfAssociationNavigation:(Lorg/hibernate/engine/spi/SessionImplementor;Lorg/hibernate/ogm/datastore/spi/Tuple;Lorg/hibernate/ogm/persister/OgmCollectionPersister$Action;Lorg/hibernate/ogm/grid/RowKey;)V
     216: aload_1
     217: aload_0
     218: aload         8
     220: iload         6
     222: invokeinterface #146,  4          // InterfaceMethod org/hibernate/collection/spi/PersistentCollection.afterRowInsert:(Lorg/hibernate/persister/collection/CollectionPersister;Ljava/lang/Object;I)V
     227: iinc          7, 1
     230: iinc          6, 1
     233: goto          141
     236: aload         4
     238: invokevirtual #89                 // Method org/hibernate/ogm/util/impl/PropertyMetadataProvider.flushToCache:()V
     241: getstatic     #126                // Field log:Lorg/hibernate/ogm/util/impl/Log;
     244: invokeinterface #127,  1          // InterfaceMethod org/hibernate/ogm/util/impl/Log.isDebugEnabled:()Z
     249: ifeq          285
     252: getstatic     #126                // Field log:Lorg/hibernate/ogm/util/impl/Log;
     255: new           #29                 // class java/lang/StringBuilder
     258: dup
     259: invokespecial #30                 // Method java/lang/StringBuilder."<init>":()V
     262: ldc           #151                // String done inserting collection:
     264: invokevirtual #32                 // Method java/lang/StringBuilder.append:(Ljava/lang/String;)Ljava/lang/StringBuilder;
     267: iload         7
     269: invokevirtual #137                // Method java/lang/StringBuilder.append:(I)Ljava/lang/StringBuilder;
     272: ldc           #152                // String  rows inserted
     274: invokevirtual #32                 // Method java/lang/StringBuilder.append:(Ljava/lang/String;)Ljava/lang/StringBuilder;
     277: invokevirtual #34                 // Method java/lang/StringBuilder.toString:()Ljava/lang/String;
     280: invokeinterface #131,  2          // InterfaceMethod org/hibernate/ogm/util/impl/Log.debug:(Ljava/lang/Object;)V
     285: goto          309
     288: getstatic     #126                // Field log:Lorg/hibernate/ogm/util/impl/Log;
     291: invokeinterface #127,  1          // InterfaceMethod org/hibernate/ogm/util/impl/Log.isDebugEnabled:()Z
     296: ifeq          309
     299: getstatic     #126                // Field log:Lorg/hibernate/ogm/util/impl/Log;
     302: ldc           #153                // String collection was empty
     304: invokeinterface #131,  2          // InterfaceMethod org/hibernate/ogm/util/impl/Log.debug:(Ljava/lang/Object;)V
     309: return

  private void updateInverseSideOfAssociationNavigation(org.hibernate.engine.spi.SessionImplementor, org.hibernate.ogm.datastore.spi.Tuple, org.hibernate.ogm.persister.OgmCollectionPersister$Action, org.hibernate.ogm.grid.RowKey);
    Code:
       0: aload_0
       1: getfield      #24                 // Field associationType:Lorg/hibernate/ogm/persister/OgmCollectionPersister$AssociationType;
       4: getstatic     #23                 // Field org/hibernate/ogm/persister/OgmCollectionPersister$AssociationType.EMBEDDED_FK_TO_ENTITY:Lorg/hibernate/ogm/persister/OgmCollectionPersister$AssociationType;
       7: if_acmpne     264
      10: aload_0
      11: getfield      #27                 // Field gridTypeOfAssociatedId:Lorg/hibernate/ogm/type/GridType;
      14: aload_2
      15: aload_0
      16: invokevirtual #47                 // Method getElementColumnNames:()[Ljava/lang/String;
      19: aload_1
      20: aconst_null
      21: invokeinterface #53,  5           // InterfaceMethod org/hibernate/ogm/type/GridType.nullSafeGet:(Lorg/hibernate/ogm/datastore/spi/Tuple;[Ljava/lang/String;Lorg/hibernate/engine/spi/SessionImplementor;Ljava/lang/Object;)Ljava/lang/Object;
      26: checkcast     #154                // class java/io/Serializable
      29: astore        5
      31: aload_0
      32: invokevirtual #21                 // Method getElementPersister:()Lorg/hibernate/persister/entity/EntityPersister;
      35: checkcast     #155                // class org/hibernate/ogm/persister/OgmEntityPersister
      38: astore        6
      40: aload         6
      42: aload         5
      44: aload_1
      45: invokestatic  #156                // Method org/hibernate/ogm/persister/EntityKeyBuilder.fromPersister:(Lorg/hibernate/ogm/persister/OgmEntityPersister;Ljava/io/Serializable;Lorg/hibernate/engine/spi/SessionImplementor;)Lorg/hibernate/ogm/grid/EntityKey;
      48: astore        7
      50: aload_0
      51: getfield      #7                  // Field gridDialect:Lorg/hibernate/ogm/dialect/GridDialect;
      54: aload         7
      56: aload         6
      58: invokevirtual #157                // Method org/hibernate/ogm/persister/OgmEntityPersister.getTupleContext:()Lorg/hibernate/ogm/datastore/spi/TupleContext;
      61: invokeinterface #158,  3          // InterfaceMethod org/hibernate/ogm/dialect/GridDialect.getTuple:(Lorg/hibernate/ogm/grid/EntityKey;Lorg/hibernate/ogm/datastore/spi/TupleContext;)Lorg/hibernate/ogm/datastore/spi/Tuple;
      66: astore        8
      68: aload         8
      70: ifnonnull     74
      73: return
      74: aload_3
      75: getstatic     #88                 // Field org/hibernate/ogm/persister/OgmCollectionPersister$Action.ADD:Lorg/hibernate/ogm/persister/OgmCollectionPersister$Action;
      78: if_acmpne     133
      81: aload_2
      82: invokevirtual #107                // Method org/hibernate/ogm/datastore/spi/Tuple.getColumnNames:()Ljava/util/Set;
      85: invokeinterface #108,  1          // InterfaceMethod java/util/Set.iterator:()Ljava/util/Iterator;
      90: astore        9
      92: aload         9
      94: invokeinterface #71,  1           // InterfaceMethod java/util/Iterator.hasNext:()Z
      99: ifeq          130
     102: aload         9
     104: invokeinterface #72,  1           // InterfaceMethod java/util/Iterator.next:()Ljava/lang/Object;
     109: checkcast     #97                 // class java/lang/String
     112: astore        10
     114: aload         8
     116: aload         10
     118: aload_2
     119: aload         10
     121: invokevirtual #109                // Method org/hibernate/ogm/datastore/spi/Tuple.get:(Ljava/lang/String;)Ljava/lang/Object;
     124: invokevirtual #110                // Method org/hibernate/ogm/datastore/spi/Tuple.put:(Ljava/lang/String;Ljava/lang/Object;)V
     127: goto          92
     130: goto          248
     133: aload_3
     134: getstatic     #83                 // Field org/hibernate/ogm/persister/OgmCollectionPersister$Action.REMOVE:Lorg/hibernate/ogm/persister/OgmCollectionPersister$Action;
     137: if_acmpne     221
     140: aload_0
     141: getfield      #95                 // Field hasIdentifier:Z
     144: ifeq          177
     147: new           #28                 // class org/hibernate/annotations/common/AssertionFailure
     150: dup
     151: new           #29                 // class java/lang/StringBuilder
     154: dup
     155: invokespecial #30                 // Method java/lang/StringBuilder."<init>":()V
     158: ldc           #159                // String A true OneToMany with an identifier for the collection:
     160: invokevirtual #32                 // Method java/lang/StringBuilder.append:(Ljava/lang/String;)Ljava/lang/StringBuilder;
     163: aload_0
     164: invokevirtual #160                // Method getRole:()Ljava/lang/String;
     167: invokevirtual #32                 // Method java/lang/StringBuilder.append:(Ljava/lang/String;)Ljava/lang/StringBuilder;
     170: invokevirtual #34                 // Method java/lang/StringBuilder.toString:()Ljava/lang/String;
     173: invokespecial #35                 // Method org/hibernate/annotations/common/AssertionFailure."<init>":(Ljava/lang/String;)V
     176: athrow
     177: aload_0
     178: getfield      #98                 // Field hasIndex:Z
     181: ifeq          201
     184: aload_0
     185: getfield      #14                 // Field indexGridType:Lorg/hibernate/ogm/type/GridType;
     188: aload         8
     190: aconst_null
     191: aload_0
     192: invokevirtual #46                 // Method getIndexColumnNames:()[Ljava/lang/String;
     195: aload_1
     196: invokeinterface #87,  5           // InterfaceMethod org/hibernate/ogm/type/GridType.nullSafeSet:(Lorg/hibernate/ogm/datastore/spi/Tuple;Ljava/lang/Object;[Ljava/lang/String;Lorg/hibernate/engine/spi/SessionImplementor;)V
     201: aload_0
     202: getfield      #10                 // Field keyGridType:Lorg/hibernate/ogm/type/GridType;
     205: aload         8
     207: aconst_null
     208: aload_0
     209: invokevirtual #45                 // Method getKeyColumnNames:()[Ljava/lang/String;
     212: aload_1
     213: invokeinterface #87,  5           // InterfaceMethod org/hibernate/ogm/type/GridType.nullSafeSet:(Lorg/hibernate/ogm/datastore/spi/Tuple;Ljava/lang/Object;[Ljava/lang/String;Lorg/hibernate/engine/spi/SessionImplementor;)V
     218: goto          248
     221: new           #28                 // class org/hibernate/annotations/common/AssertionFailure
     224: dup
     225: new           #29                 // class java/lang/StringBuilder
     228: dup
     229: invokespecial #30                 // Method java/lang/StringBuilder."<init>":()V
     232: ldc           #161                // String Unknown action type:
     234: invokevirtual #32                 // Method java/lang/StringBuilder.append:(Ljava/lang/String;)Ljava/lang/StringBuilder;
     237: aload_3
     238: invokevirtual #80                 // Method java/lang/StringBuilder.append:(Ljava/lang/Object;)Ljava/lang/StringBuilder;
     241: invokevirtual #34                 // Method java/lang/StringBuilder.toString:()Ljava/lang/String;
     244: invokespecial #35                 // Method org/hibernate/annotations/common/AssertionFailure."<init>":(Ljava/lang/String;)V
     247: athrow
     248: aload_0
     249: getfield      #7                  // Field gridDialect:Lorg/hibernate/ogm/dialect/GridDialect;
     252: aload         8
     254: aload         7
     256: invokeinterface #162,  3          // InterfaceMethod org/hibernate/ogm/dialect/GridDialect.updateTuple:(Lorg/hibernate/ogm/datastore/spi/Tuple;Lorg/hibernate/ogm/grid/EntityKey;)V
     261: goto          556
     264: aload_0
     265: getfield      #24                 // Field associationType:Lorg/hibernate/ogm/persister/OgmCollectionPersister$AssociationType;
     268: getstatic     #37                 // Field org/hibernate/ogm/persister/OgmCollectionPersister$AssociationType.ASSOCIATION_TABLE_TO_ENTITY:Lorg/hibernate/ogm/persister/OgmCollectionPersister$AssociationType;
     271: if_acmpne     556
     274: aload_0
     275: invokevirtual #47                 // Method getElementColumnNames:()[Ljava/lang/String;
     278: astore        5
     280: aload_2
     281: aload         5
     283: invokestatic  #163                // Method org/hibernate/ogm/util/impl/LogicalPhysicalConverterHelper.getColumnValuesFromResultset:(Lorg/hibernate/ogm/datastore/spi/Tuple;[Ljava/lang/String;)[Ljava/lang/Object;
     286: astore        6
     288: aload_0
     289: getfield      #27                 // Field gridTypeOfAssociatedId:Lorg/hibernate/ogm/type/GridType;
     292: aload_2
     293: aload_0
     294: invokevirtual #47                 // Method getElementColumnNames:()[Ljava/lang/String;
     297: aload_1
     298: aconst_null
     299: invokeinterface #53,  5           // InterfaceMethod org/hibernate/ogm/type/GridType.nullSafeGet:(Lorg/hibernate/ogm/datastore/spi/Tuple;[Ljava/lang/String;Lorg/hibernate/engine/spi/SessionImplementor;Ljava/lang/Object;)Ljava/lang/Object;
     304: checkcast     #154                // class java/io/Serializable
     307: astore        7
     309: new           #60                 // class org/hibernate/ogm/util/impl/PropertyMetadataProvider
     312: dup
     313: invokespecial #61                 // Method org/hibernate/ogm/util/impl/PropertyMetadataProvider."<init>":()V
     316: aload_0
     317: getfield      #7                  // Field gridDialect:Lorg/hibernate/ogm/dialect/GridDialect;
     320: invokevirtual #62                 // Method org/hibernate/ogm/util/impl/PropertyMetadataProvider.gridDialect:(Lorg/hibernate/ogm/dialect/GridDialect;)Lorg/hibernate/ogm/util/impl/PropertyMetadataProvider;
     323: aload         5
     325: invokevirtual #66                 // Method org/hibernate/ogm/util/impl/PropertyMetadataProvider.keyColumnNames:([Ljava/lang/String;)Lorg/hibernate/ogm/util/impl/PropertyMetadataProvider;
     328: aload         6
     330: invokevirtual #164                // Method org/hibernate/ogm/util/impl/PropertyMetadataProvider.keyColumnValues:([Ljava/lang/Object;)Lorg/hibernate/ogm/util/impl/PropertyMetadataProvider;
     333: aload_1
     334: invokevirtual #70                 // Method org/hibernate/ogm/util/impl/PropertyMetadataProvider.session:(Lorg/hibernate/engine/spi/SessionImplementor;)Lorg/hibernate/ogm/util/impl/PropertyMetadataProvider;
     337: aload_0
     338: invokevirtual #69                 // Method org/hibernate/ogm/util/impl/PropertyMetadataProvider.collectionPersister:(Lorg/hibernate/ogm/persister/OgmCollectionPersister;)Lorg/hibernate/ogm/util/impl/PropertyMetadataProvider;
     341: aload_0
     342: invokevirtual #63                 // Method getTableName:()Ljava/lang/String;
     345: invokevirtual #64                 // Method org/hibernate/ogm/util/impl/PropertyMetadataProvider.tableName:(Ljava/lang/String;)Lorg/hibernate/ogm/util/impl/PropertyMetadataProvider;
     348: aload         7
     350: invokevirtual #65                 // Method org/hibernate/ogm/util/impl/PropertyMetadataProvider.key:(Ljava/lang/Object;)Lorg/hibernate/ogm/util/impl/PropertyMetadataProvider;
     353: invokevirtual #165                // Method org/hibernate/ogm/util/impl/PropertyMetadataProvider.inverse:()Lorg/hibernate/ogm/util/impl/PropertyMetadataProvider;
     356: astore        8
     358: aload_3
     359: getstatic     #88                 // Field org/hibernate/ogm/persister/OgmCollectionPersister$Action.ADD:Lorg/hibernate/ogm/persister/OgmCollectionPersister$Action;
     362: if_acmpne     438
     365: aload         8
     367: aload         4
     369: invokevirtual #106                // Method org/hibernate/ogm/util/impl/PropertyMetadataProvider.createAndPutAssociationTuple:(Lorg/hibernate/ogm/grid/RowKey;)Lorg/hibernate/ogm/datastore/spi/Tuple;
     372: astore        9
     374: aload_2
     375: invokevirtual #107                // Method org/hibernate/ogm/datastore/spi/Tuple.getColumnNames:()Ljava/util/Set;
     378: invokeinterface #108,  1          // InterfaceMethod java/util/Set.iterator:()Ljava/util/Iterator;
     383: astore        10
     385: aload         10
     387: invokeinterface #71,  1           // InterfaceMethod java/util/Iterator.hasNext:()Z
     392: ifeq          423
     395: aload         10
     397: invokeinterface #72,  1           // InterfaceMethod java/util/Iterator.next:()Ljava/lang/Object;
     402: checkcast     #97                 // class java/lang/String
     405: astore        11
     407: aload         9
     409: aload         11
     411: aload_2
     412: aload         11
     414: invokevirtual #109                // Method org/hibernate/ogm/datastore/spi/Tuple.get:(Ljava/lang/String;)Ljava/lang/Object;
     417: invokevirtual #110                // Method org/hibernate/ogm/datastore/spi/Tuple.put:(Ljava/lang/String;Ljava/lang/Object;)V
     420: goto          385
     423: aload         8
     425: invokevirtual #76                 // Method org/hibernate/ogm/util/impl/PropertyMetadataProvider.getCollectionMetadata:()Lorg/hibernate/ogm/datastore/spi/Association;
     428: aload         4
     430: aload         9
     432: invokevirtual #166                // Method org/hibernate/ogm/datastore/spi/Association.put:(Lorg/hibernate/ogm/grid/RowKey;Lorg/hibernate/ogm/datastore/spi/Tuple;)V
     435: goto          551
     438: aload_3
     439: getstatic     #83                 // Field org/hibernate/ogm/persister/OgmCollectionPersister$Action.REMOVE:Lorg/hibernate/ogm/persister/OgmCollectionPersister$Action;
     442: if_acmpne     524
     445: aload         4
     447: ifnonnull     511
     450: new           #28                 // class org/hibernate/annotations/common/AssertionFailure
     453: dup
     454: new           #29                 // class java/lang/StringBuilder
     457: dup
     458: invokespecial #30                 // Method java/lang/StringBuilder."<init>":()V
     461: ldc           #134                // String Deleting a collection tuple that is not present: table {
     463: invokevirtual #32                 // Method java/lang/StringBuilder.append:(Ljava/lang/String;)Ljava/lang/StringBuilder;
     466: aload_0
     467: invokevirtual #63                 // Method getTableName:()Ljava/lang/String;
     470: invokevirtual #32                 // Method java/lang/StringBuilder.append:(Ljava/lang/String;)Ljava/lang/StringBuilder;
     473: ldc           #167                // String } key column names {
     475: invokevirtual #32                 // Method java/lang/StringBuilder.append:(Ljava/lang/String;)Ljava/lang/StringBuilder;
     478: aload         5
     480: invokestatic  #168                // Method java/util/Arrays.toString:([Ljava/lang/Object;)Ljava/lang/String;
     483: invokevirtual #32                 // Method java/lang/StringBuilder.append:(Ljava/lang/String;)Ljava/lang/StringBuilder;
     486: ldc           #169                // String } key column values {
     488: invokevirtual #32                 // Method java/lang/StringBuilder.append:(Ljava/lang/String;)Ljava/lang/StringBuilder;
     491: aload         6
     493: invokestatic  #168                // Method java/util/Arrays.toString:([Ljava/lang/Object;)Ljava/lang/String;
     496: invokevirtual #32                 // Method java/lang/StringBuilder.append:(Ljava/lang/String;)Ljava/lang/StringBuilder;
     499: ldc           #82                 // String }
     501: invokevirtual #32                 // Method java/lang/StringBuilder.append:(Ljava/lang/String;)Ljava/lang/StringBuilder;
     504: invokevirtual #34                 // Method java/lang/StringBuilder.toString:()Ljava/lang/String;
     507: invokespecial #35                 // Method org/hibernate/annotations/common/AssertionFailure."<init>":(Ljava/lang/String;)V
     510: athrow
     511: aload         8
     513: invokevirtual #76                 // Method org/hibernate/ogm/util/impl/PropertyMetadataProvider.getCollectionMetadata:()Lorg/hibernate/ogm/datastore/spi/Association;
     516: aload         4
     518: invokevirtual #135                // Method org/hibernate/ogm/datastore/spi/Association.remove:(Lorg/hibernate/ogm/grid/RowKey;)V
     521: goto          551
     524: new           #28                 // class org/hibernate/annotations/common/AssertionFailure
     527: dup
     528: new           #29                 // class java/lang/StringBuilder
     531: dup
     532: invokespecial #30                 // Method java/lang/StringBuilder."<init>":()V
     535: ldc           #161                // String Unknown action type:
     537: invokevirtual #32                 // Method java/lang/StringBuilder.append:(Ljava/lang/String;)Ljava/lang/StringBuilder;
     540: aload_3
     541: invokevirtual #80                 // Method java/lang/StringBuilder.append:(Ljava/lang/Object;)Ljava/lang/StringBuilder;
     544: invokevirtual #34                 // Method java/lang/StringBuilder.toString:()Ljava/lang/String;
     547: invokespecial #35                 // Method org/hibernate/annotations/common/AssertionFailure."<init>":(Ljava/lang/String;)V
     550: athrow
     551: aload         8
     553: invokevirtual #89                 // Method org/hibernate/ogm/util/impl/PropertyMetadataProvider.flushToCache:()V
     556: return

  public void remove(java.io.Serializable, org.hibernate.engine.spi.SessionImplementor) throws org.hibernate.HibernateException;
    Code:
       0: aload_0
       1: getfield      #18                 // Field isInverse:Z
       4: ifne          208
       7: aload_0
       8: invokevirtual #125                // Method isRowDeleteEnabled:()Z
      11: ifeq          208
      14: getstatic     #126                // Field log:Lorg/hibernate/ogm/util/impl/Log;
      17: invokeinterface #127,  1          // InterfaceMethod org/hibernate/ogm/util/impl/Log.isDebugEnabled:()Z
      22: ifeq          60
      25: getstatic     #126                // Field log:Lorg/hibernate/ogm/util/impl/Log;
      28: new           #29                 // class java/lang/StringBuilder
      31: dup
      32: invokespecial #30                 // Method java/lang/StringBuilder."<init>":()V
      35: ldc           #170                // String Deleting collection:
      37: invokevirtual #32                 // Method java/lang/StringBuilder.append:(Ljava/lang/String;)Ljava/lang/StringBuilder;
      40: aload_0
      41: aload_1
      42: aload_0
      43: invokevirtual #129                // Method getFactory:()Lorg/hibernate/engine/spi/SessionFactoryImplementor;
      46: invokestatic  #130                // Method org/hibernate/pretty/MessageHelper.collectionInfoString:(Lorg/hibernate/persister/collection/CollectionPersister;Ljava/io/Serializable;Lorg/hibernate/engine/spi/SessionFactoryImplementor;)Ljava/lang/String;
      49: invokevirtual #32                 // Method java/lang/StringBuilder.append:(Ljava/lang/String;)Ljava/lang/StringBuilder;
      52: invokevirtual #34                 // Method java/lang/StringBuilder.toString:()Ljava/lang/String;
      55: invokeinterface #131,  2          // InterfaceMethod org/hibernate/ogm/util/impl/Log.debug:(Ljava/lang/Object;)V
      60: new           #60                 // class org/hibernate/ogm/util/impl/PropertyMetadataProvider
      63: dup
      64: invokespecial #61                 // Method org/hibernate/ogm/util/impl/PropertyMetadataProvider."<init>":()V
      67: aload_0
      68: getfield      #7                  // Field gridDialect:Lorg/hibernate/ogm/dialect/GridDialect;
      71: invokevirtual #62                 // Method org/hibernate/ogm/util/impl/PropertyMetadataProvider.gridDialect:(Lorg/hibernate/ogm/dialect/GridDialect;)Lorg/hibernate/ogm/util/impl/PropertyMetadataProvider;
      74: aload_0
      75: invokevirtual #63                 // Method getTableName:()Ljava/lang/String;
      78: invokevirtual #64                 // Method org/hibernate/ogm/util/impl/PropertyMetadataProvider.tableName:(Ljava/lang/String;)Lorg/hibernate/ogm/util/impl/PropertyMetadataProvider;
      81: aload_1
      82: invokevirtual #65                 // Method org/hibernate/ogm/util/impl/PropertyMetadataProvider.key:(Ljava/lang/Object;)Lorg/hibernate/ogm/util/impl/PropertyMetadataProvider;
      85: aload_0
      86: invokevirtual #45                 // Method getKeyColumnNames:()[Ljava/lang/String;
      89: invokevirtual #66                 // Method org/hibernate/ogm/util/impl/PropertyMetadataProvider.keyColumnNames:([Ljava/lang/String;)Lorg/hibernate/ogm/util/impl/PropertyMetadataProvider;
      92: aload_0
      93: invokevirtual #67                 // Method getKeyGridType:()Lorg/hibernate/ogm/type/GridType;
      96: invokevirtual #68                 // Method org/hibernate/ogm/util/impl/PropertyMetadataProvider.keyGridType:(Lorg/hibernate/ogm/type/GridType;)Lorg/hibernate/ogm/util/impl/PropertyMetadataProvider;
      99: aload_0
     100: invokevirtual #69                 // Method org/hibernate/ogm/util/impl/PropertyMetadataProvider.collectionPersister:(Lorg/hibernate/ogm/persister/OgmCollectionPersister;)Lorg/hibernate/ogm/util/impl/PropertyMetadataProvider;
     103: aload_2
     104: invokevirtual #70                 // Method org/hibernate/ogm/util/impl/PropertyMetadataProvider.session:(Lorg/hibernate/engine/spi/SessionImplementor;)Lorg/hibernate/ogm/util/impl/PropertyMetadataProvider;
     107: astore_3
     108: aload_0
     109: getfield      #24                 // Field associationType:Lorg/hibernate/ogm/persister/OgmCollectionPersister$AssociationType;
     112: getstatic     #38                 // Field org/hibernate/ogm/persister/OgmCollectionPersister$AssociationType.OTHER:Lorg/hibernate/ogm/persister/OgmCollectionPersister$AssociationType;
     115: if_acmpeq     176
     118: aload_3
     119: invokevirtual #76                 // Method org/hibernate/ogm/util/impl/PropertyMetadataProvider.getCollectionMetadata:()Lorg/hibernate/ogm/datastore/spi/Association;
     122: invokevirtual #171                // Method org/hibernate/ogm/datastore/spi/Association.getKeys:()Ljava/util/Set;
     125: invokeinterface #108,  1          // InterfaceMethod java/util/Set.iterator:()Ljava/util/Iterator;
     130: astore        4
     132: aload         4
     134: invokeinterface #71,  1           // InterfaceMethod java/util/Iterator.hasNext:()Z
     139: ifeq          176
     142: aload         4
     144: invokeinterface #72,  1           // InterfaceMethod java/util/Iterator.next:()Ljava/lang/Object;
     149: checkcast     #172                // class org/hibernate/ogm/grid/RowKey
     152: astore        5
     154: aload_0
     155: aload_2
     156: aload_3
     157: invokevirtual #76                 // Method org/hibernate/ogm/util/impl/PropertyMetadataProvider.getCollectionMetadata:()Lorg/hibernate/ogm/datastore/spi/Association;
     160: aload         5
     162: invokevirtual #77                 // Method org/hibernate/ogm/datastore/spi/Association.get:(Lorg/hibernate/ogm/grid/RowKey;)Lorg/hibernate/ogm/datastore/spi/Tuple;
     165: getstatic     #83                 // Field org/hibernate/ogm/persister/OgmCollectionPersister$Action.REMOVE:Lorg/hibernate/ogm/persister/OgmCollectionPersister$Action;
     168: aload         5
     170: invokespecial #84                 // Method updateInverseSideOfAssociationNavigation:(Lorg/hibernate/engine/spi/SessionImplementor;Lorg/hibernate/ogm/datastore/spi/Tuple;Lorg/hibernate/ogm/persister/OgmCollectionPersister$Action;Lorg/hibernate/ogm/grid/RowKey;)V
     173: goto          132
     176: aload_3
     177: invokevirtual #76                 // Method org/hibernate/ogm/util/impl/PropertyMetadataProvider.getCollectionMetadata:()Lorg/hibernate/ogm/datastore/spi/Association;
     180: invokevirtual #173                // Method org/hibernate/ogm/datastore/spi/Association.clear:()V
     183: aload_3
     184: invokevirtual #89                 // Method org/hibernate/ogm/util/impl/PropertyMetadataProvider.flushToCache:()V
     187: getstatic     #126                // Field log:Lorg/hibernate/ogm/util/impl/Log;
     190: invokeinterface #127,  1          // InterfaceMethod org/hibernate/ogm/util/impl/Log.isDebugEnabled:()Z
     195: ifeq          208
     198: getstatic     #126                // Field log:Lorg/hibernate/ogm/util/impl/Log;
     201: ldc           #174                // String done deleting collection
     203: invokeinterface #131,  2          // InterfaceMethod org/hibernate/ogm/util/impl/Log.debug:(Ljava/lang/Object;)V
     208: return

  public java.lang.String selectFragment(org.hibernate.persister.entity.Joinable, java.lang.String, java.lang.String, java.lang.String, java.lang.String, boolean);
    Code:
       0: aconst_null
       1: areturn

  public java.lang.String whereJoinFragment(java.lang.String, boolean, boolean);
    Code:
       0: aconst_null
       1: areturn

  public java.lang.String fromJoinFragment(java.lang.String, boolean, boolean);
    Code:
       0: aconst_null
       1: areturn

  public boolean consumesEntityAlias();
    Code:
       0: iconst_0
       1: ireturn

  public boolean consumesCollectionAlias();
    Code:
       0: iconst_0
       1: ireturn

  protected void logStaticSQL();
    Code:
       0: getstatic     #126                // Field log:Lorg/hibernate/ogm/util/impl/Log;
       3: invokeinterface #127,  1          // InterfaceMethod org/hibernate/ogm/util/impl/Log.isDebugEnabled:()Z
       8: ifeq          41
      11: getstatic     #126                // Field log:Lorg/hibernate/ogm/util/impl/Log;
      14: new           #29                 // class java/lang/StringBuilder
      17: dup
      18: invokespecial #30                 // Method java/lang/StringBuilder."<init>":()V
      21: ldc           #175                // String No SQL used when using OGM:
      23: invokevirtual #32                 // Method java/lang/StringBuilder.append:(Ljava/lang/String;)Ljava/lang/StringBuilder;
      26: aload_0
      27: invokevirtual #160                // Method getRole:()Ljava/lang/String;
      30: invokevirtual #32                 // Method java/lang/StringBuilder.append:(Ljava/lang/String;)Ljava/lang/StringBuilder;
      33: invokevirtual #34                 // Method java/lang/StringBuilder.toString:()Ljava/lang/String;
      36: invokeinterface #131,  2          // InterfaceMethod org/hibernate/ogm/util/impl/Log.debug:(Ljava/lang/Object;)V
      41: return

  public void postInstantiate() throws org.hibernate.MappingException;
    Code:
       0: return

  protected org.hibernate.loader.collection.CollectionInitializer getAppropriateInitializer(java.io.Serializable, org.hibernate.engine.spi.SessionImplementor);
    Code:
       0: aload_0
       1: aload_2
       2: invokeinterface #176,  1          // InterfaceMethod org/hibernate/engine/spi/SessionImplementor.getLoadQueryInfluencers:()Lorg/hibernate/engine/spi/LoadQueryInfluencers;
       7: invokevirtual #177                // Method createCollectionInitializer:(Lorg/hibernate/engine/spi/LoadQueryInfluencers;)Lorg/hibernate/loader/collection/CollectionInitializer;
      10: areturn

  static {};
    Code:
       0: invokestatic  #178                // Method org/hibernate/ogm/util/impl/LoggerFactory.make:()Lorg/hibernate/ogm/util/impl/Log;
       3: putstatic     #126                // Field log:Lorg/hibernate/ogm/util/impl/Log;
       6: return
}
