Compiled from "Timeline.java"
public final class javafx.animation.Timeline extends javafx.animation.Animation {
  final com.sun.scenario.animation.shared.TimelineClipCore clipCore;

  private final javafx.collections.ObservableList<javafx.animation.KeyFrame> keyFrames;

  public final javafx.collections.ObservableList<javafx.animation.KeyFrame> getKeyFrames();
    Code:
       0: aload_0
       1: getfield      #1                  // Field keyFrames:Ljavafx/collections/ObservableList;
       4: areturn

  public javafx.animation.Timeline(double, javafx.animation.KeyFrame...);
    Code:
       0: aload_0
       1: dload_1
       2: invokespecial #2                  // Method javafx/animation/Animation."<init>":(D)V
       5: aload_0
       6: new           #3                  // class javafx/animation/Timeline$1
       9: dup
      10: aload_0
      11: invokespecial #4                  // Method javafx/animation/Timeline$1."<init>":(Ljavafx/animation/Timeline;)V
      14: putfield      #1                  // Field keyFrames:Ljavafx/collections/ObservableList;
      17: aload_0
      18: new           #5                  // class com/sun/scenario/animation/shared/TimelineClipCore
      21: dup
      22: aload_0
      23: invokespecial #6                  // Method com/sun/scenario/animation/shared/TimelineClipCore."<init>":(Ljavafx/animation/Timeline;)V
      26: putfield      #7                  // Field clipCore:Lcom/sun/scenario/animation/shared/TimelineClipCore;
      29: aload_0
      30: invokevirtual #8                  // Method getKeyFrames:()Ljavafx/collections/ObservableList;
      33: aload_3
      34: invokeinterface #9,  2            // InterfaceMethod javafx/collections/ObservableList.setAll:([Ljava/lang/Object;)Z
      39: pop
      40: return

  public javafx.animation.Timeline(javafx.animation.KeyFrame...);
    Code:
       0: aload_0
       1: invokespecial #10                 // Method javafx/animation/Animation."<init>":()V
       4: aload_0
       5: new           #3                  // class javafx/animation/Timeline$1
       8: dup
       9: aload_0
      10: invokespecial #4                  // Method javafx/animation/Timeline$1."<init>":(Ljavafx/animation/Timeline;)V
      13: putfield      #1                  // Field keyFrames:Ljavafx/collections/ObservableList;
      16: aload_0
      17: new           #5                  // class com/sun/scenario/animation/shared/TimelineClipCore
      20: dup
      21: aload_0
      22: invokespecial #6                  // Method com/sun/scenario/animation/shared/TimelineClipCore."<init>":(Ljavafx/animation/Timeline;)V
      25: putfield      #7                  // Field clipCore:Lcom/sun/scenario/animation/shared/TimelineClipCore;
      28: aload_0
      29: invokevirtual #8                  // Method getKeyFrames:()Ljavafx/collections/ObservableList;
      32: aload_1
      33: invokeinterface #9,  2            // InterfaceMethod javafx/collections/ObservableList.setAll:([Ljava/lang/Object;)Z
      38: pop
      39: return

  public javafx.animation.Timeline(double);
    Code:
       0: aload_0
       1: dload_1
       2: invokespecial #2                  // Method javafx/animation/Animation."<init>":(D)V
       5: aload_0
       6: new           #3                  // class javafx/animation/Timeline$1
       9: dup
      10: aload_0
      11: invokespecial #4                  // Method javafx/animation/Timeline$1."<init>":(Ljavafx/animation/Timeline;)V
      14: putfield      #1                  // Field keyFrames:Ljavafx/collections/ObservableList;
      17: aload_0
      18: new           #5                  // class com/sun/scenario/animation/shared/TimelineClipCore
      21: dup
      22: aload_0
      23: invokespecial #6                  // Method com/sun/scenario/animation/shared/TimelineClipCore."<init>":(Ljavafx/animation/Timeline;)V
      26: putfield      #7                  // Field clipCore:Lcom/sun/scenario/animation/shared/TimelineClipCore;
      29: return

  public javafx.animation.Timeline();
    Code:
       0: aload_0
       1: invokespecial #10                 // Method javafx/animation/Animation."<init>":()V
       4: aload_0
       5: new           #3                  // class javafx/animation/Timeline$1
       8: dup
       9: aload_0
      10: invokespecial #4                  // Method javafx/animation/Timeline$1."<init>":(Ljavafx/animation/Timeline;)V
      13: putfield      #1                  // Field keyFrames:Ljavafx/collections/ObservableList;
      16: aload_0
      17: new           #5                  // class com/sun/scenario/animation/shared/TimelineClipCore
      20: dup
      21: aload_0
      22: invokespecial #6                  // Method com/sun/scenario/animation/shared/TimelineClipCore."<init>":(Ljavafx/animation/Timeline;)V
      25: putfield      #7                  // Field clipCore:Lcom/sun/scenario/animation/shared/TimelineClipCore;
      28: return

  javafx.animation.Timeline(com.sun.scenario.animation.AbstractMasterTimer);
    Code:
       0: aload_0
       1: aload_1
       2: invokespecial #11                 // Method javafx/animation/Animation."<init>":(Lcom/sun/scenario/animation/AbstractMasterTimer;)V
       5: aload_0
       6: new           #3                  // class javafx/animation/Timeline$1
       9: dup
      10: aload_0
      11: invokespecial #4                  // Method javafx/animation/Timeline$1."<init>":(Ljavafx/animation/Timeline;)V
      14: putfield      #1                  // Field keyFrames:Ljavafx/collections/ObservableList;
      17: aload_0
      18: new           #5                  // class com/sun/scenario/animation/shared/TimelineClipCore
      21: dup
      22: aload_0
      23: invokespecial #6                  // Method com/sun/scenario/animation/shared/TimelineClipCore."<init>":(Ljavafx/animation/Timeline;)V
      26: putfield      #7                  // Field clipCore:Lcom/sun/scenario/animation/shared/TimelineClipCore;
      29: return

  void doPlayTo(long, long);
    Code:
       0: aload_0
       1: getfield      #7                  // Field clipCore:Lcom/sun/scenario/animation/shared/TimelineClipCore;
       4: lload_1
       5: invokevirtual #12                 // Method com/sun/scenario/animation/shared/TimelineClipCore.playTo:(J)V
       8: return

  void doJumpTo(long, long, boolean);
    Code:
       0: aload_0
       1: iconst_0
       2: invokevirtual #13                 // Method sync:(Z)V
       5: aload_0
       6: lload_1
       7: invokevirtual #14                 // Method setCurrentTicks:(J)V
      10: aload_0
      11: getfield      #7                  // Field clipCore:Lcom/sun/scenario/animation/shared/TimelineClipCore;
      14: lload_1
      15: iload         5
      17: invokevirtual #15                 // Method com/sun/scenario/animation/shared/TimelineClipCore.jumpTo:(JZ)V
      20: return

  void setCurrentRate(double);
    Code:
       0: aload_0
       1: dload_1
       2: invokespecial #16                 // Method javafx/animation/Animation.setCurrentRate:(D)V
       5: aload_0
       6: getfield      #7                  // Field clipCore:Lcom/sun/scenario/animation/shared/TimelineClipCore;
       9: invokevirtual #17                 // Method com/sun/scenario/animation/shared/TimelineClipCore.notifyCurrentRateChanged:()V
      12: return

  void doStart(boolean);
    Code:
       0: aload_0
       1: iload_1
       2: invokespecial #18                 // Method javafx/animation/Animation.doStart:(Z)V
       5: aload_0
       6: getfield      #7                  // Field clipCore:Lcom/sun/scenario/animation/shared/TimelineClipCore;
       9: iload_1
      10: invokevirtual #19                 // Method com/sun/scenario/animation/shared/TimelineClipCore.start:(Z)V
      13: return

  public void stop();
    Code:
       0: aload_0
       1: getfield      #20                 // Field parent:Ljavafx/animation/Animation;
       4: ifnull        17
       7: new           #21                 // class java/lang/IllegalStateException
      10: dup
      11: ldc           #22                 // String Cannot stop when embedded in another animation
      13: invokespecial #23                 // Method java/lang/IllegalStateException."<init>":(Ljava/lang/String;)V
      16: athrow
      17: aload_0
      18: invokevirtual #24                 // Method getStatus:()Ljavafx/animation/Animation$Status;
      21: getstatic     #25                 // Field javafx/animation/Animation$Status.RUNNING:Ljavafx/animation/Animation$Status;
      24: if_acmpne     34
      27: aload_0
      28: getfield      #7                  // Field clipCore:Lcom/sun/scenario/animation/shared/TimelineClipCore;
      31: invokevirtual #26                 // Method com/sun/scenario/animation/shared/TimelineClipCore.abort:()V
      34: aload_0
      35: invokespecial #27                 // Method javafx/animation/Animation.stop:()V
      38: return
}
