Compiled from "NettyServerCnxn.java"
class org.apache.zookeeper.server.NettyServerCnxn$ResumeMessageEvent implements org.jboss.netty.channel.MessageEvent {
  org.jboss.netty.channel.Channel channel;

  org.apache.zookeeper.server.NettyServerCnxn$ResumeMessageEvent(org.jboss.netty.channel.Channel);
    Code:
       0: aload_0
       1: invokespecial #1                  // Method java/lang/Object."<init>":()V
       4: aload_0
       5: aload_1
       6: putfield      #2                  // Field channel:Lorg/jboss/netty/channel/Channel;
       9: return

  public java.lang.Object getMessage();
    Code:
       0: aconst_null
       1: areturn

  public java.net.SocketAddress getRemoteAddress();
    Code:
       0: aconst_null
       1: areturn

  public org.jboss.netty.channel.Channel getChannel();
    Code:
       0: aload_0
       1: getfield      #2                  // Field channel:Lorg/jboss/netty/channel/Channel;
       4: areturn

  public org.jboss.netty.channel.ChannelFuture getFuture();
    Code:
       0: aconst_null
       1: areturn
}
