Compiled from "TransportConnection.java"
class org.apache.activemq.broker.TransportConnection$2 extends java.lang.Thread {
  final java.io.IOException val$e;

  final org.apache.activemq.broker.TransportConnection this$0;

  org.apache.activemq.broker.TransportConnection$2(org.apache.activemq.broker.TransportConnection, java.lang.String, java.io.IOException);
    Code:
       0: aload_0
       1: aload_1
       2: putfield      #1                  // Field this$0:Lorg/apache/activemq/broker/TransportConnection;
       5: aload_0
       6: aload_3
       7: putfield      #2                  // Field val$e:Ljava/io/IOException;
      10: aload_0
      11: aload_2
      12: invokespecial #3                  // Method java/lang/Thread."<init>":(Ljava/lang/String;)V
      15: return

  public void run();
    Code:
       0: aload_0
       1: getfield      #1                  // Field this$0:Lorg/apache/activemq/broker/TransportConnection;
       4: aload_0
       5: getfield      #2                  // Field val$e:Ljava/io/IOException;
       8: invokevirtual #4                  // Method org/apache/activemq/broker/TransportConnection.serviceException:(Ljava/lang/Throwable;)V
      11: return
}
