Compiled from "TopicMetadataConverter.java"
public class org.joyqueue.client.internal.consumer.converter.TopicMetadataConverter {
  public org.joyqueue.client.internal.consumer.converter.TopicMetadataConverter();
    Code:
       0: aload_0
       1: invokespecial #1                  // Method java/lang/Object."<init>":()V
       4: return

  public static java.util.Map<java.lang.String, org.joyqueue.client.internal.metadata.domain.TopicMetadata> convertToMap(java.util.List<org.joyqueue.client.internal.metadata.domain.TopicMetadata>);
    Code:
       0: aload_0
       1: invokestatic  #2                  // Method org/apache/commons/collections/CollectionUtils.isEmpty:(Ljava/util/Collection;)Z
       4: ifeq          11
       7: invokestatic  #3                  // Method java/util/Collections.emptyMap:()Ljava/util/Map;
      10: areturn
      11: invokestatic  #4                  // Method com/google/common/collect/Maps.newHashMap:()Ljava/util/HashMap;
      14: astore_1
      15: aload_0
      16: invokeinterface #5,  1            // InterfaceMethod java/util/List.iterator:()Ljava/util/Iterator;
      21: astore_2
      22: aload_2
      23: invokeinterface #6,  1            // InterfaceMethod java/util/Iterator.hasNext:()Z
      28: ifeq          56
      31: aload_2
      32: invokeinterface #7,  1            // InterfaceMethod java/util/Iterator.next:()Ljava/lang/Object;
      37: checkcast     #8                  // class org/joyqueue/client/internal/metadata/domain/TopicMetadata
      40: astore_3
      41: aload_1
      42: aload_3
      43: invokevirtual #9                  // Method org/joyqueue/client/internal/metadata/domain/TopicMetadata.getTopic:()Ljava/lang/String;
      46: aload_3
      47: invokeinterface #10,  3           // InterfaceMethod java/util/Map.put:(Ljava/lang/Object;Ljava/lang/Object;)Ljava/lang/Object;
      52: pop
      53: goto          22
      56: aload_1
      57: areturn

  public static java.util.List<java.lang.String> convertToCodeList(java.util.List<org.joyqueue.client.internal.metadata.domain.TopicMetadata>);
    Code:
       0: aload_0
       1: invokestatic  #2                  // Method org/apache/commons/collections/CollectionUtils.isEmpty:(Ljava/util/Collection;)Z
       4: ifeq          11
       7: invokestatic  #11                 // Method java/util/Collections.emptyList:()Ljava/util/List;
      10: areturn
      11: invokestatic  #12                 // Method com/google/common/collect/Lists.newLinkedList:()Ljava/util/LinkedList;
      14: astore_1
      15: aload_0
      16: invokeinterface #5,  1            // InterfaceMethod java/util/List.iterator:()Ljava/util/Iterator;
      21: astore_2
      22: aload_2
      23: invokeinterface #6,  1            // InterfaceMethod java/util/Iterator.hasNext:()Z
      28: ifeq          55
      31: aload_2
      32: invokeinterface #7,  1            // InterfaceMethod java/util/Iterator.next:()Ljava/lang/Object;
      37: checkcast     #8                  // class org/joyqueue/client/internal/metadata/domain/TopicMetadata
      40: astore_3
      41: aload_1
      42: aload_3
      43: invokevirtual #9                  // Method org/joyqueue/client/internal/metadata/domain/TopicMetadata.getTopic:()Ljava/lang/String;
      46: invokeinterface #13,  2           // InterfaceMethod java/util/List.add:(Ljava/lang/Object;)Z
      51: pop
      52: goto          22
      55: aload_1
      56: areturn
}
