Compiled from "HttpResponseStatus.java"
final class io.netty.handler.codec.http.HttpResponseStatus$HttpStatusLineProcessor implements io.netty.util.ByteProcessor {
  private static final byte ASCII_SPACE;

  private final io.netty.util.AsciiString string;

  private int i;

  private int state;

  private io.netty.handler.codec.http.HttpResponseStatus status;

  public io.netty.handler.codec.http.HttpResponseStatus$HttpStatusLineProcessor(io.netty.util.AsciiString);
    Code:
       0: aload_0
       1: invokespecial #1                  // Method java/lang/Object."<init>":()V
       4: aload_0
       5: aload_1
       6: putfield      #2                  // Field string:Lio/netty/util/AsciiString;
       9: return

  public boolean process(byte);
    Code:
       0: aload_0
       1: getfield      #3                  // Field state:I
       4: lookupswitch  { // 2
                     0: 32
                     1: 46
               default: 61
          }
      32: iload_1
      33: bipush        32
      35: if_icmpne     61
      38: aload_0
      39: iconst_1
      40: putfield      #3                  // Field state:I
      43: goto          61
      46: aload_0
      47: aload_0
      48: getfield      #5                  // Field i:I
      51: invokespecial #6                  // Method parseStatus:(I)V
      54: aload_0
      55: iconst_2
      56: putfield      #3                  // Field state:I
      59: iconst_0
      60: ireturn
      61: aload_0
      62: dup
      63: getfield      #5                  // Field i:I
      66: iconst_1
      67: iadd
      68: putfield      #5                  // Field i:I
      71: iconst_1
      72: ireturn

  private void parseStatus(int);
    Code:
       0: aload_0
       1: getfield      #2                  // Field string:Lio/netty/util/AsciiString;
       4: iconst_0
       5: iload_1
       6: invokevirtual #7                  // Method io/netty/util/AsciiString.parseInt:(II)I
       9: istore_2
      10: aload_0
      11: iload_2
      12: invokestatic  #8                  // Method io/netty/handler/codec/http/HttpResponseStatus.valueOf:(I)Lio/netty/handler/codec/http/HttpResponseStatus;
      15: putfield      #9                  // Field status:Lio/netty/handler/codec/http/HttpResponseStatus;
      18: iload_1
      19: aload_0
      20: getfield      #2                  // Field string:Lio/netty/util/AsciiString;
      23: invokevirtual #10                 // Method io/netty/util/AsciiString.length:()I
      26: if_icmpge     74
      29: aload_0
      30: getfield      #2                  // Field string:Lio/netty/util/AsciiString;
      33: iload_1
      34: iconst_1
      35: iadd
      36: aload_0
      37: getfield      #2                  // Field string:Lio/netty/util/AsciiString;
      40: invokevirtual #10                 // Method io/netty/util/AsciiString.length:()I
      43: invokevirtual #11                 // Method io/netty/util/AsciiString.toString:(II)Ljava/lang/String;
      46: astore_3
      47: aload_0
      48: getfield      #9                  // Field status:Lio/netty/handler/codec/http/HttpResponseStatus;
      51: invokevirtual #12                 // Method io/netty/handler/codec/http/HttpResponseStatus.reasonPhrase:()Ljava/lang/String;
      54: aload_3
      55: invokevirtual #13                 // Method java/lang/String.contentEquals:(Ljava/lang/CharSequence;)Z
      58: ifne          74
      61: aload_0
      62: new           #14                 // class io/netty/handler/codec/http/HttpResponseStatus
      65: dup
      66: iload_2
      67: aload_3
      68: invokespecial #15                 // Method io/netty/handler/codec/http/HttpResponseStatus."<init>":(ILjava/lang/String;)V
      71: putfield      #9                  // Field status:Lio/netty/handler/codec/http/HttpResponseStatus;
      74: return

  public io.netty.handler.codec.http.HttpResponseStatus status();
    Code:
       0: aload_0
       1: getfield      #3                  // Field state:I
       4: iconst_1
       5: if_icmpgt     24
       8: aload_0
       9: aload_0
      10: getfield      #2                  // Field string:Lio/netty/util/AsciiString;
      13: invokevirtual #10                 // Method io/netty/util/AsciiString.length:()I
      16: invokespecial #6                  // Method parseStatus:(I)V
      19: aload_0
      20: iconst_3
      21: putfield      #3                  // Field state:I
      24: aload_0
      25: getfield      #9                  // Field status:Lio/netty/handler/codec/http/HttpResponseStatus;
      28: areturn
}
