Compiled from "HttpContentCompressor.java"
public class io.netty.handler.codec.http.HttpContentCompressor extends io.netty.handler.codec.http.HttpContentEncoder {
  private final int compressionLevel;

  private final int windowBits;

  private final int memLevel;

  private io.netty.channel.ChannelHandlerContext ctx;

  public io.netty.handler.codec.http.HttpContentCompressor();
    Code:
       0: aload_0
       1: bipush        6
       3: invokespecial #1                  // Method "<init>":(I)V
       6: return

  public io.netty.handler.codec.http.HttpContentCompressor(int);
    Code:
       0: aload_0
       1: iload_1
       2: bipush        15
       4: bipush        8
       6: invokespecial #2                  // Method "<init>":(III)V
       9: return

  public io.netty.handler.codec.http.HttpContentCompressor(int, int, int);
    Code:
       0: aload_0
       1: invokespecial #3                  // Method io/netty/handler/codec/http/HttpContentEncoder."<init>":()V
       4: iload_1
       5: iflt          14
       8: iload_1
       9: bipush        9
      11: if_icmple     46
      14: new           #4                  // class java/lang/IllegalArgumentException
      17: dup
      18: new           #5                  // class java/lang/StringBuilder
      21: dup
      22: invokespecial #6                  // Method java/lang/StringBuilder."<init>":()V
      25: ldc           #7                  // String compressionLevel:
      27: invokevirtual #8                  // Method java/lang/StringBuilder.append:(Ljava/lang/String;)Ljava/lang/StringBuilder;
      30: iload_1
      31: invokevirtual #9                  // Method java/lang/StringBuilder.append:(I)Ljava/lang/StringBuilder;
      34: ldc           #10                 // String  (expected: 0-9)
      36: invokevirtual #8                  // Method java/lang/StringBuilder.append:(Ljava/lang/String;)Ljava/lang/StringBuilder;
      39: invokevirtual #11                 // Method java/lang/StringBuilder.toString:()Ljava/lang/String;
      42: invokespecial #12                 // Method java/lang/IllegalArgumentException."<init>":(Ljava/lang/String;)V
      45: athrow
      46: iload_2
      47: bipush        9
      49: if_icmplt     58
      52: iload_2
      53: bipush        15
      55: if_icmple     90
      58: new           #4                  // class java/lang/IllegalArgumentException
      61: dup
      62: new           #5                  // class java/lang/StringBuilder
      65: dup
      66: invokespecial #6                  // Method java/lang/StringBuilder."<init>":()V
      69: ldc           #13                 // String windowBits:
      71: invokevirtual #8                  // Method java/lang/StringBuilder.append:(Ljava/lang/String;)Ljava/lang/StringBuilder;
      74: iload_2
      75: invokevirtual #9                  // Method java/lang/StringBuilder.append:(I)Ljava/lang/StringBuilder;
      78: ldc           #14                 // String  (expected: 9-15)
      80: invokevirtual #8                  // Method java/lang/StringBuilder.append:(Ljava/lang/String;)Ljava/lang/StringBuilder;
      83: invokevirtual #11                 // Method java/lang/StringBuilder.toString:()Ljava/lang/String;
      86: invokespecial #12                 // Method java/lang/IllegalArgumentException."<init>":(Ljava/lang/String;)V
      89: athrow
      90: iload_3
      91: iconst_1
      92: if_icmplt     101
      95: iload_3
      96: bipush        9
      98: if_icmple     133
     101: new           #4                  // class java/lang/IllegalArgumentException
     104: dup
     105: new           #5                  // class java/lang/StringBuilder
     108: dup
     109: invokespecial #6                  // Method java/lang/StringBuilder."<init>":()V
     112: ldc           #15                 // String memLevel:
     114: invokevirtual #8                  // Method java/lang/StringBuilder.append:(Ljava/lang/String;)Ljava/lang/StringBuilder;
     117: iload_3
     118: invokevirtual #9                  // Method java/lang/StringBuilder.append:(I)Ljava/lang/StringBuilder;
     121: ldc           #16                 // String  (expected: 1-9)
     123: invokevirtual #8                  // Method java/lang/StringBuilder.append:(Ljava/lang/String;)Ljava/lang/StringBuilder;
     126: invokevirtual #11                 // Method java/lang/StringBuilder.toString:()Ljava/lang/String;
     129: invokespecial #12                 // Method java/lang/IllegalArgumentException."<init>":(Ljava/lang/String;)V
     132: athrow
     133: aload_0
     134: iload_1
     135: putfield      #17                 // Field compressionLevel:I
     138: aload_0
     139: iload_2
     140: putfield      #18                 // Field windowBits:I
     143: aload_0
     144: iload_3
     145: putfield      #19                 // Field memLevel:I
     148: return

  public void handlerAdded(io.netty.channel.ChannelHandlerContext) throws java.lang.Exception;
    Code:
       0: aload_0
       1: aload_1
       2: putfield      #20                 // Field ctx:Lio/netty/channel/ChannelHandlerContext;
       5: return

  protected io.netty.handler.codec.http.HttpContentEncoder$Result beginEncode(io.netty.handler.codec.http.HttpResponse, java.lang.String) throws java.lang.Exception;
    Code:
       0: aload_1
       1: invokeinterface #21,  1           // InterfaceMethod io/netty/handler/codec/http/HttpResponse.headers:()Lio/netty/handler/codec/http/HttpHeaders;
       6: getstatic     #22                 // Field io/netty/handler/codec/http/HttpHeaderNames.CONTENT_ENCODING:Lio/netty/util/AsciiString;
       9: invokevirtual #23                 // Method io/netty/handler/codec/http/HttpHeaders.get:(Ljava/lang/CharSequence;)Ljava/lang/String;
      12: astore_3
      13: aload_3
      14: ifnull        19
      17: aconst_null
      18: areturn
      19: aload_0
      20: aload_2
      21: invokevirtual #24                 // Method determineWrapper:(Ljava/lang/String;)Lio/netty/handler/codec/compression/ZlibWrapper;
      24: astore        4
      26: aload         4
      28: ifnonnull     33
      31: aconst_null
      32: areturn
      33: getstatic     #25                 // Field io/netty/handler/codec/http/HttpContentCompressor$1.$SwitchMap$io$netty$handler$codec$compression$ZlibWrapper:[I
      36: aload         4
      38: invokevirtual #26                 // Method io/netty/handler/codec/compression/ZlibWrapper.ordinal:()I
      41: iaload
      42: lookupswitch  { // 2
                     1: 68
                     2: 75
               default: 82
          }
      68: ldc           #27                 // String gzip
      70: astore        5
      72: goto          90
      75: ldc           #28                 // String deflate
      77: astore        5
      79: goto          90
      82: new           #29                 // class java/lang/Error
      85: dup
      86: invokespecial #30                 // Method java/lang/Error."<init>":()V
      89: athrow
      90: new           #31                 // class io/netty/handler/codec/http/HttpContentEncoder$Result
      93: dup
      94: aload         5
      96: new           #32                 // class io/netty/channel/embedded/EmbeddedChannel
      99: dup
     100: aload_0
     101: getfield      #20                 // Field ctx:Lio/netty/channel/ChannelHandlerContext;
     104: invokeinterface #33,  1           // InterfaceMethod io/netty/channel/ChannelHandlerContext.channel:()Lio/netty/channel/Channel;
     109: invokeinterface #34,  1           // InterfaceMethod io/netty/channel/Channel.id:()Lio/netty/channel/ChannelId;
     114: aload_0
     115: getfield      #20                 // Field ctx:Lio/netty/channel/ChannelHandlerContext;
     118: invokeinterface #33,  1           // InterfaceMethod io/netty/channel/ChannelHandlerContext.channel:()Lio/netty/channel/Channel;
     123: invokeinterface #35,  1           // InterfaceMethod io/netty/channel/Channel.metadata:()Lio/netty/channel/ChannelMetadata;
     128: invokevirtual #36                 // Method io/netty/channel/ChannelMetadata.hasDisconnect:()Z
     131: aload_0
     132: getfield      #20                 // Field ctx:Lio/netty/channel/ChannelHandlerContext;
     135: invokeinterface #33,  1           // InterfaceMethod io/netty/channel/ChannelHandlerContext.channel:()Lio/netty/channel/Channel;
     140: invokeinterface #37,  1           // InterfaceMethod io/netty/channel/Channel.config:()Lio/netty/channel/ChannelConfig;
     145: iconst_1
     146: anewarray     #38                 // class io/netty/channel/ChannelHandler
     149: dup
     150: iconst_0
     151: aload         4
     153: aload_0
     154: getfield      #17                 // Field compressionLevel:I
     157: aload_0
     158: getfield      #18                 // Field windowBits:I
     161: aload_0
     162: getfield      #19                 // Field memLevel:I
     165: invokestatic  #39                 // Method io/netty/handler/codec/compression/ZlibCodecFactory.newZlibEncoder:(Lio/netty/handler/codec/compression/ZlibWrapper;III)Lio/netty/handler/codec/compression/ZlibEncoder;
     168: aastore
     169: invokespecial #40                 // Method io/netty/channel/embedded/EmbeddedChannel."<init>":(Lio/netty/channel/ChannelId;ZLio/netty/channel/ChannelConfig;[Lio/netty/channel/ChannelHandler;)V
     172: invokespecial #41                 // Method io/netty/handler/codec/http/HttpContentEncoder$Result."<init>":(Ljava/lang/String;Lio/netty/channel/embedded/EmbeddedChannel;)V
     175: areturn

  protected io.netty.handler.codec.compression.ZlibWrapper determineWrapper(java.lang.String);
    Code:
       0: ldc           #42                 // float -1.0f
       2: fstore_2
       3: ldc           #42                 // float -1.0f
       5: fstore_3
       6: ldc           #42                 // float -1.0f
       8: fstore        4
      10: aload_1
      11: ldc           #43                 // String ,
      13: invokevirtual #44                 // Method java/lang/String.split:(Ljava/lang/String;)[Ljava/lang/String;
      16: astore        5
      18: aload         5
      20: arraylength
      21: istore        6
      23: iconst_0
      24: istore        7
      26: iload         7
      28: iload         6
      30: if_icmpge     147
      33: aload         5
      35: iload         7
      37: aaload
      38: astore        8
      40: fconst_1
      41: fstore        9
      43: aload         8
      45: bipush        61
      47: invokevirtual #45                 // Method java/lang/String.indexOf:(I)I
      50: istore        10
      52: iload         10
      54: iconst_m1
      55: if_icmpeq     80
      58: aload         8
      60: iload         10
      62: iconst_1
      63: iadd
      64: invokevirtual #46                 // Method java/lang/String.substring:(I)Ljava/lang/String;
      67: invokestatic  #47                 // Method java/lang/Float.parseFloat:(Ljava/lang/String;)F
      70: fstore        9
      72: goto          80
      75: astore        11
      77: fconst_0
      78: fstore        9
      80: aload         8
      82: ldc           #49                 // String *
      84: invokevirtual #50                 // Method java/lang/String.contains:(Ljava/lang/CharSequence;)Z
      87: ifeq          96
      90: fload         9
      92: fstore_2
      93: goto          141
      96: aload         8
      98: ldc           #27                 // String gzip
     100: invokevirtual #50                 // Method java/lang/String.contains:(Ljava/lang/CharSequence;)Z
     103: ifeq          119
     106: fload         9
     108: fload_3
     109: fcmpl
     110: ifle          119
     113: fload         9
     115: fstore_3
     116: goto          141
     119: aload         8
     121: ldc           #28                 // String deflate
     123: invokevirtual #50                 // Method java/lang/String.contains:(Ljava/lang/CharSequence;)Z
     126: ifeq          141
     129: fload         9
     131: fload         4
     133: fcmpl
     134: ifle          141
     137: fload         9
     139: fstore        4
     141: iinc          7, 1
     144: goto          26
     147: fload_3
     148: fconst_0
     149: fcmpl
     150: ifgt          160
     153: fload         4
     155: fconst_0
     156: fcmpl
     157: ifle          175
     160: fload_3
     161: fload         4
     163: fcmpl
     164: iflt          171
     167: getstatic     #51                 // Field io/netty/handler/codec/compression/ZlibWrapper.GZIP:Lio/netty/handler/codec/compression/ZlibWrapper;
     170: areturn
     171: getstatic     #52                 // Field io/netty/handler/codec/compression/ZlibWrapper.ZLIB:Lio/netty/handler/codec/compression/ZlibWrapper;
     174: areturn
     175: fload_2
     176: fconst_0
     177: fcmpl
     178: ifle          204
     181: fload_3
     182: ldc           #42                 // float -1.0f
     184: fcmpl
     185: ifne          192
     188: getstatic     #51                 // Field io/netty/handler/codec/compression/ZlibWrapper.GZIP:Lio/netty/handler/codec/compression/ZlibWrapper;
     191: areturn
     192: fload         4
     194: ldc           #42                 // float -1.0f
     196: fcmpl
     197: ifne          204
     200: getstatic     #52                 // Field io/netty/handler/codec/compression/ZlibWrapper.ZLIB:Lio/netty/handler/codec/compression/ZlibWrapper;
     203: areturn
     204: aconst_null
     205: areturn
    Exception table:
       from    to  target type
          58    72    75   Class java/lang/NumberFormatException
}
