Compiled from "ServletHttpHandlerAdapter.java"
class org.springframework.http.server.reactive.ServletHttpHandlerAdapter$HandlerResultAsyncListener implements javax.servlet.AsyncListener {
  private final java.util.concurrent.atomic.AtomicBoolean isCompleted;

  private final java.lang.String logPrefix;

  public org.springframework.http.server.reactive.ServletHttpHandlerAdapter$HandlerResultAsyncListener(java.util.concurrent.atomic.AtomicBoolean, org.springframework.http.server.reactive.ServletServerHttpRequest);
    Code:
       0: aload_0
       1: invokespecial #1                  // Method java/lang/Object."<init>":()V
       4: aload_0
       5: aload_1
       6: putfield      #2                  // Field isCompleted:Ljava/util/concurrent/atomic/AtomicBoolean;
       9: aload_0
      10: aload_2
      11: invokevirtual #3                  // Method org/springframework/http/server/reactive/ServletServerHttpRequest.getLogPrefix:()Ljava/lang/String;
      14: putfield      #4                  // Field logPrefix:Ljava/lang/String;
      17: return

  public void onTimeout(javax.servlet.AsyncEvent);
    Code:
       0: invokestatic  #5                  // Method org/springframework/http/server/reactive/ServletHttpHandlerAdapter.access$000:()Lorg/apache/commons/logging/Log;
       3: new           #6                  // class java/lang/StringBuilder
       6: dup
       7: invokespecial #7                  // Method java/lang/StringBuilder."<init>":()V
      10: aload_0
      11: getfield      #4                  // Field logPrefix:Ljava/lang/String;
      14: invokevirtual #8                  // Method java/lang/StringBuilder.append:(Ljava/lang/String;)Ljava/lang/StringBuilder;
      17: ldc           #9                  // String Timeout notification
      19: invokevirtual #8                  // Method java/lang/StringBuilder.append:(Ljava/lang/String;)Ljava/lang/StringBuilder;
      22: invokevirtual #10                 // Method java/lang/StringBuilder.toString:()Ljava/lang/String;
      25: invokeinterface #11,  2           // InterfaceMethod org/apache/commons/logging/Log.debug:(Ljava/lang/Object;)V
      30: aload_1
      31: invokevirtual #12                 // Method javax/servlet/AsyncEvent.getAsyncContext:()Ljavax/servlet/AsyncContext;
      34: astore_2
      35: aload_2
      36: aload_0
      37: getfield      #2                  // Field isCompleted:Ljava/util/concurrent/atomic/AtomicBoolean;
      40: aload_2
      41: dup
      42: invokevirtual #13                 // Method java/lang/Object.getClass:()Ljava/lang/Class;
      45: pop
      46: invokedynamic #14,  0             // InvokeDynamic #0:run:(Ljavax/servlet/AsyncContext;)Ljava/lang/Runnable;
      51: invokestatic  #15                 // Method org/springframework/http/server/reactive/ServletHttpHandlerAdapter.access$100:(Ljavax/servlet/AsyncContext;Ljava/util/concurrent/atomic/AtomicBoolean;Ljava/lang/Runnable;)V
      54: return

  public void onError(javax.servlet.AsyncEvent);
    Code:
       0: aload_1
       1: invokevirtual #16                 // Method javax/servlet/AsyncEvent.getThrowable:()Ljava/lang/Throwable;
       4: astore_2
       5: invokestatic  #5                  // Method org/springframework/http/server/reactive/ServletHttpHandlerAdapter.access$000:()Lorg/apache/commons/logging/Log;
       8: new           #6                  // class java/lang/StringBuilder
      11: dup
      12: invokespecial #7                  // Method java/lang/StringBuilder."<init>":()V
      15: aload_0
      16: getfield      #4                  // Field logPrefix:Ljava/lang/String;
      19: invokevirtual #8                  // Method java/lang/StringBuilder.append:(Ljava/lang/String;)Ljava/lang/StringBuilder;
      22: ldc           #17                 // String Error notification:
      24: invokevirtual #8                  // Method java/lang/StringBuilder.append:(Ljava/lang/String;)Ljava/lang/StringBuilder;
      27: aload_2
      28: ifnull        35
      31: aload_2
      32: goto          37
      35: ldc           #18                 // String <no Throwable>
      37: invokevirtual #19                 // Method java/lang/StringBuilder.append:(Ljava/lang/Object;)Ljava/lang/StringBuilder;
      40: invokevirtual #10                 // Method java/lang/StringBuilder.toString:()Ljava/lang/String;
      43: invokeinterface #11,  2           // InterfaceMethod org/apache/commons/logging/Log.debug:(Ljava/lang/Object;)V
      48: aload_1
      49: invokevirtual #12                 // Method javax/servlet/AsyncEvent.getAsyncContext:()Ljavax/servlet/AsyncContext;
      52: astore_3
      53: aload_3
      54: aload_0
      55: getfield      #2                  // Field isCompleted:Ljava/util/concurrent/atomic/AtomicBoolean;
      58: aload_3
      59: dup
      60: invokevirtual #13                 // Method java/lang/Object.getClass:()Ljava/lang/Class;
      63: pop
      64: invokedynamic #14,  0             // InvokeDynamic #0:run:(Ljavax/servlet/AsyncContext;)Ljava/lang/Runnable;
      69: invokestatic  #15                 // Method org/springframework/http/server/reactive/ServletHttpHandlerAdapter.access$100:(Ljavax/servlet/AsyncContext;Ljava/util/concurrent/atomic/AtomicBoolean;Ljava/lang/Runnable;)V
      72: return

  public void onStartAsync(javax.servlet.AsyncEvent);
    Code:
       0: return

  public void onComplete(javax.servlet.AsyncEvent);
    Code:
       0: return
}
