Compiled from "DefaultExpressionEngineSymbols.java"
public class org.apache.commons.configuration2.tree.DefaultExpressionEngineSymbols$Builder {
  private java.lang.String propertyDelimiter;

  private java.lang.String escapedDelimiter;

  private java.lang.String attributeStart;

  private java.lang.String attributeEnd;

  private java.lang.String indexStart;

  private java.lang.String indexEnd;

  public org.apache.commons.configuration2.tree.DefaultExpressionEngineSymbols$Builder();
    Code:
       0: aload_0
       1: invokespecial #7                  // Method java/lang/Object."<init>":()V
       4: return

  public org.apache.commons.configuration2.tree.DefaultExpressionEngineSymbols$Builder(org.apache.commons.configuration2.tree.DefaultExpressionEngineSymbols);
    Code:
       0: aload_0
       1: invokespecial #7                  // Method java/lang/Object."<init>":()V
       4: aload_0
       5: aload_1
       6: invokevirtual #8                  // Method org/apache/commons/configuration2/tree/DefaultExpressionEngineSymbols.getPropertyDelimiter:()Ljava/lang/String;
       9: putfield      #6                  // Field propertyDelimiter:Ljava/lang/String;
      12: aload_0
      13: aload_1
      14: invokevirtual #9                  // Method org/apache/commons/configuration2/tree/DefaultExpressionEngineSymbols.getEscapedDelimiter:()Ljava/lang/String;
      17: putfield      #5                  // Field escapedDelimiter:Ljava/lang/String;
      20: aload_0
      21: aload_1
      22: invokevirtual #10                 // Method org/apache/commons/configuration2/tree/DefaultExpressionEngineSymbols.getIndexStart:()Ljava/lang/String;
      25: putfield      #4                  // Field indexStart:Ljava/lang/String;
      28: aload_0
      29: aload_1
      30: invokevirtual #11                 // Method org/apache/commons/configuration2/tree/DefaultExpressionEngineSymbols.getIndexEnd:()Ljava/lang/String;
      33: putfield      #3                  // Field indexEnd:Ljava/lang/String;
      36: aload_0
      37: aload_1
      38: invokevirtual #12                 // Method org/apache/commons/configuration2/tree/DefaultExpressionEngineSymbols.getAttributeStart:()Ljava/lang/String;
      41: putfield      #2                  // Field attributeStart:Ljava/lang/String;
      44: aload_0
      45: aload_1
      46: invokevirtual #13                 // Method org/apache/commons/configuration2/tree/DefaultExpressionEngineSymbols.getAttributeEnd:()Ljava/lang/String;
      49: putfield      #1                  // Field attributeEnd:Ljava/lang/String;
      52: return

  public org.apache.commons.configuration2.tree.DefaultExpressionEngineSymbols$Builder setPropertyDelimiter(java.lang.String);
    Code:
       0: aload_0
       1: aload_1
       2: putfield      #6                  // Field propertyDelimiter:Ljava/lang/String;
       5: aload_0
       6: areturn

  public org.apache.commons.configuration2.tree.DefaultExpressionEngineSymbols$Builder setEscapedDelimiter(java.lang.String);
    Code:
       0: aload_0
       1: aload_1
       2: putfield      #5                  // Field escapedDelimiter:Ljava/lang/String;
       5: aload_0
       6: areturn

  public org.apache.commons.configuration2.tree.DefaultExpressionEngineSymbols$Builder setIndexStart(java.lang.String);
    Code:
       0: aload_0
       1: aload_1
       2: putfield      #4                  // Field indexStart:Ljava/lang/String;
       5: aload_0
       6: areturn

  public org.apache.commons.configuration2.tree.DefaultExpressionEngineSymbols$Builder setIndexEnd(java.lang.String);
    Code:
       0: aload_0
       1: aload_1
       2: putfield      #3                  // Field indexEnd:Ljava/lang/String;
       5: aload_0
       6: areturn

  public org.apache.commons.configuration2.tree.DefaultExpressionEngineSymbols$Builder setAttributeStart(java.lang.String);
    Code:
       0: aload_0
       1: aload_1
       2: putfield      #2                  // Field attributeStart:Ljava/lang/String;
       5: aload_0
       6: areturn

  public org.apache.commons.configuration2.tree.DefaultExpressionEngineSymbols$Builder setAttributeEnd(java.lang.String);
    Code:
       0: aload_0
       1: aload_1
       2: putfield      #1                  // Field attributeEnd:Ljava/lang/String;
       5: aload_0
       6: areturn

  public org.apache.commons.configuration2.tree.DefaultExpressionEngineSymbols create();
    Code:
       0: new           #14                 // class org/apache/commons/configuration2/tree/DefaultExpressionEngineSymbols
       3: dup
       4: aload_0
       5: aconst_null
       6: invokespecial #15                 // Method org/apache/commons/configuration2/tree/DefaultExpressionEngineSymbols."<init>":(Lorg/apache/commons/configuration2/tree/DefaultExpressionEngineSymbols$Builder;Lorg/apache/commons/configuration2/tree/DefaultExpressionEngineSymbols$1;)V
       9: areturn

  static java.lang.String access$000(org.apache.commons.configuration2.tree.DefaultExpressionEngineSymbols$Builder);
    Code:
       0: aload_0
       1: getfield      #6                  // Field propertyDelimiter:Ljava/lang/String;
       4: areturn

  static java.lang.String access$100(org.apache.commons.configuration2.tree.DefaultExpressionEngineSymbols$Builder);
    Code:
       0: aload_0
       1: getfield      #5                  // Field escapedDelimiter:Ljava/lang/String;
       4: areturn

  static java.lang.String access$200(org.apache.commons.configuration2.tree.DefaultExpressionEngineSymbols$Builder);
    Code:
       0: aload_0
       1: getfield      #4                  // Field indexStart:Ljava/lang/String;
       4: areturn

  static java.lang.String access$300(org.apache.commons.configuration2.tree.DefaultExpressionEngineSymbols$Builder);
    Code:
       0: aload_0
       1: getfield      #3                  // Field indexEnd:Ljava/lang/String;
       4: areturn

  static java.lang.String access$400(org.apache.commons.configuration2.tree.DefaultExpressionEngineSymbols$Builder);
    Code:
       0: aload_0
       1: getfield      #2                  // Field attributeStart:Ljava/lang/String;
       4: areturn

  static java.lang.String access$500(org.apache.commons.configuration2.tree.DefaultExpressionEngineSymbols$Builder);
    Code:
       0: aload_0
       1: getfield      #1                  // Field attributeEnd:Ljava/lang/String;
       4: areturn
}
