Compiled from "ModelTransaction.java"
class org.apache.commons.configuration2.tree.ModelTransaction {
  private static final int MAX_REPLACEMENTS;

  private static final int LEVEL_UNKNOWN;

  private final org.apache.commons.configuration2.tree.TreeData currentData;

  private final org.apache.commons.configuration2.tree.ImmutableNode queryRoot;

  private final org.apache.commons.configuration2.tree.NodeSelector rootNodeSelector;

  private final org.apache.commons.configuration2.tree.NodeKeyResolver<org.apache.commons.configuration2.tree.ImmutableNode> resolver;

  private final java.util.Map<org.apache.commons.configuration2.tree.ImmutableNode, org.apache.commons.configuration2.tree.ImmutableNode> replacementMapping;

  private final java.util.Map<org.apache.commons.configuration2.tree.ImmutableNode, org.apache.commons.configuration2.tree.ImmutableNode> replacedNodes;

  private final java.util.Map<org.apache.commons.configuration2.tree.ImmutableNode, org.apache.commons.configuration2.tree.ImmutableNode> parentMapping;

  private final java.util.Collection<org.apache.commons.configuration2.tree.ImmutableNode> addedNodes;

  private final java.util.Collection<org.apache.commons.configuration2.tree.ImmutableNode> removedNodes;

  private final java.util.Collection<org.apache.commons.configuration2.tree.ImmutableNode> allRemovedNodes;

  private final java.util.SortedMap<java.lang.Integer, java.util.Map<org.apache.commons.configuration2.tree.ImmutableNode, org.apache.commons.configuration2.tree.ModelTransaction$Operations>> operations;

  private java.util.Map<org.apache.commons.configuration2.tree.ImmutableNode, java.lang.Object> newReferences;

  private org.apache.commons.configuration2.tree.ImmutableNode newRoot;

  public org.apache.commons.configuration2.tree.ModelTransaction(org.apache.commons.configuration2.tree.TreeData, org.apache.commons.configuration2.tree.NodeSelector, org.apache.commons.configuration2.tree.NodeKeyResolver<org.apache.commons.configuration2.tree.ImmutableNode>);
    Code:
       0: aload_0
       1: invokespecial #14                 // Method java/lang/Object."<init>":()V
       4: aload_0
       5: aload_1
       6: putfield      #15                 // Field currentData:Lorg/apache/commons/configuration2/tree/TreeData;
       9: aload_0
      10: aload_3
      11: putfield      #16                 // Field resolver:Lorg/apache/commons/configuration2/tree/NodeKeyResolver;
      14: aload_0
      15: aload_0
      16: invokevirtual #17                 // Method getCurrentData:()Lorg/apache/commons/configuration2/tree/TreeData;
      19: invokevirtual #18                 // Method org/apache/commons/configuration2/tree/TreeData.copyReplacementMapping:()Ljava/util/Map;
      22: putfield      #19                 // Field replacementMapping:Ljava/util/Map;
      25: aload_0
      26: new           #20                 // class java/util/HashMap
      29: dup
      30: invokespecial #21                 // Method java/util/HashMap."<init>":()V
      33: putfield      #4                  // Field replacedNodes:Ljava/util/Map;
      36: aload_0
      37: aload_0
      38: invokevirtual #17                 // Method getCurrentData:()Lorg/apache/commons/configuration2/tree/TreeData;
      41: invokevirtual #22                 // Method org/apache/commons/configuration2/tree/TreeData.copyParentMapping:()Ljava/util/Map;
      44: putfield      #12                 // Field parentMapping:Ljava/util/Map;
      47: aload_0
      48: new           #23                 // class java/util/TreeMap
      51: dup
      52: invokespecial #24                 // Method java/util/TreeMap."<init>":()V
      55: putfield      #25                 // Field operations:Ljava/util/SortedMap;
      58: aload_0
      59: new           #26                 // class java/util/LinkedList
      62: dup
      63: invokespecial #27                 // Method java/util/LinkedList."<init>":()V
      66: putfield      #1                  // Field addedNodes:Ljava/util/Collection;
      69: aload_0
      70: new           #26                 // class java/util/LinkedList
      73: dup
      74: invokespecial #27                 // Method java/util/LinkedList."<init>":()V
      77: putfield      #3                  // Field removedNodes:Ljava/util/Collection;
      80: aload_0
      81: new           #26                 // class java/util/LinkedList
      84: dup
      85: invokespecial #27                 // Method java/util/LinkedList."<init>":()V
      88: putfield      #13                 // Field allRemovedNodes:Ljava/util/Collection;
      91: aload_0
      92: aload_0
      93: aload_1
      94: aload_2
      95: invokespecial #28                 // Method initQueryRoot:(Lorg/apache/commons/configuration2/tree/TreeData;Lorg/apache/commons/configuration2/tree/NodeSelector;)Lorg/apache/commons/configuration2/tree/ImmutableNode;
      98: putfield      #29                 // Field queryRoot:Lorg/apache/commons/configuration2/tree/ImmutableNode;
     101: aload_0
     102: aload_2
     103: putfield      #30                 // Field rootNodeSelector:Lorg/apache/commons/configuration2/tree/NodeSelector;
     106: return

  public org.apache.commons.configuration2.tree.NodeKeyResolver<org.apache.commons.configuration2.tree.ImmutableNode> getResolver();
    Code:
       0: aload_0
       1: getfield      #16                 // Field resolver:Lorg/apache/commons/configuration2/tree/NodeKeyResolver;
       4: areturn

  public org.apache.commons.configuration2.tree.ImmutableNode getQueryRoot();
    Code:
       0: aload_0
       1: getfield      #29                 // Field queryRoot:Lorg/apache/commons/configuration2/tree/ImmutableNode;
       4: areturn

  public void addAddNodesOperation(org.apache.commons.configuration2.tree.ImmutableNode, java.util.Collection<? extends org.apache.commons.configuration2.tree.ImmutableNode>);
    Code:
       0: new           #31                 // class org/apache/commons/configuration2/tree/ModelTransaction$ChildrenUpdateOperation
       3: dup
       4: aload_0
       5: aconst_null
       6: invokespecial #32                 // Method org/apache/commons/configuration2/tree/ModelTransaction$ChildrenUpdateOperation."<init>":(Lorg/apache/commons/configuration2/tree/ModelTransaction;Lorg/apache/commons/configuration2/tree/ModelTransaction$1;)V
       9: astore_3
      10: aload_3
      11: aload_2
      12: invokevirtual #33                 // Method org/apache/commons/configuration2/tree/ModelTransaction$ChildrenUpdateOperation.addNewNodes:(Ljava/util/Collection;)V
      15: aload_0
      16: aload_1
      17: iconst_m1
      18: invokevirtual #35                 // Method fetchOperations:(Lorg/apache/commons/configuration2/tree/ImmutableNode;I)Lorg/apache/commons/configuration2/tree/ModelTransaction$Operations;
      21: aload_3
      22: invokevirtual #36                 // Method org/apache/commons/configuration2/tree/ModelTransaction$Operations.addChildrenOperation:(Lorg/apache/commons/configuration2/tree/ModelTransaction$ChildrenUpdateOperation;)V
      25: return

  public void addAddNodeOperation(org.apache.commons.configuration2.tree.ImmutableNode, org.apache.commons.configuration2.tree.ImmutableNode);
    Code:
       0: new           #31                 // class org/apache/commons/configuration2/tree/ModelTransaction$ChildrenUpdateOperation
       3: dup
       4: aload_0
       5: aconst_null
       6: invokespecial #32                 // Method org/apache/commons/configuration2/tree/ModelTransaction$ChildrenUpdateOperation."<init>":(Lorg/apache/commons/configuration2/tree/ModelTransaction;Lorg/apache/commons/configuration2/tree/ModelTransaction$1;)V
       9: astore_3
      10: aload_3
      11: aload_2
      12: invokevirtual #37                 // Method org/apache/commons/configuration2/tree/ModelTransaction$ChildrenUpdateOperation.addNewNode:(Lorg/apache/commons/configuration2/tree/ImmutableNode;)V
      15: aload_0
      16: aload_1
      17: iconst_m1
      18: invokevirtual #35                 // Method fetchOperations:(Lorg/apache/commons/configuration2/tree/ImmutableNode;I)Lorg/apache/commons/configuration2/tree/ModelTransaction$Operations;
      21: aload_3
      22: invokevirtual #36                 // Method org/apache/commons/configuration2/tree/ModelTransaction$Operations.addChildrenOperation:(Lorg/apache/commons/configuration2/tree/ModelTransaction$ChildrenUpdateOperation;)V
      25: return

  public void addAttributeOperation(org.apache.commons.configuration2.tree.ImmutableNode, java.lang.String, java.lang.Object);
    Code:
       0: aload_0
       1: aload_1
       2: iconst_m1
       3: invokevirtual #35                 // Method fetchOperations:(Lorg/apache/commons/configuration2/tree/ImmutableNode;I)Lorg/apache/commons/configuration2/tree/ModelTransaction$Operations;
       6: new           #38                 // class org/apache/commons/configuration2/tree/ModelTransaction$AddAttributeOperation
       9: dup
      10: aload_0
      11: aload_2
      12: aload_3
      13: invokespecial #39                 // Method org/apache/commons/configuration2/tree/ModelTransaction$AddAttributeOperation."<init>":(Lorg/apache/commons/configuration2/tree/ModelTransaction;Ljava/lang/String;Ljava/lang/Object;)V
      16: invokevirtual #40                 // Method org/apache/commons/configuration2/tree/ModelTransaction$Operations.addOperation:(Lorg/apache/commons/configuration2/tree/ModelTransaction$Operation;)V
      19: return

  public void addAttributesOperation(org.apache.commons.configuration2.tree.ImmutableNode, java.util.Map<java.lang.String, java.lang.Object>);
    Code:
       0: aload_0
       1: aload_1
       2: iconst_m1
       3: invokevirtual #35                 // Method fetchOperations:(Lorg/apache/commons/configuration2/tree/ImmutableNode;I)Lorg/apache/commons/configuration2/tree/ModelTransaction$Operations;
       6: new           #41                 // class org/apache/commons/configuration2/tree/ModelTransaction$AddAttributesOperation
       9: dup
      10: aload_0
      11: aload_2
      12: invokespecial #42                 // Method org/apache/commons/configuration2/tree/ModelTransaction$AddAttributesOperation."<init>":(Lorg/apache/commons/configuration2/tree/ModelTransaction;Ljava/util/Map;)V
      15: invokevirtual #40                 // Method org/apache/commons/configuration2/tree/ModelTransaction$Operations.addOperation:(Lorg/apache/commons/configuration2/tree/ModelTransaction$Operation;)V
      18: return

  public void addRemoveNodeOperation(org.apache.commons.configuration2.tree.ImmutableNode, org.apache.commons.configuration2.tree.ImmutableNode);
    Code:
       0: new           #31                 // class org/apache/commons/configuration2/tree/ModelTransaction$ChildrenUpdateOperation
       3: dup
       4: aload_0
       5: aconst_null
       6: invokespecial #32                 // Method org/apache/commons/configuration2/tree/ModelTransaction$ChildrenUpdateOperation."<init>":(Lorg/apache/commons/configuration2/tree/ModelTransaction;Lorg/apache/commons/configuration2/tree/ModelTransaction$1;)V
       9: astore_3
      10: aload_3
      11: aload_2
      12: invokevirtual #43                 // Method org/apache/commons/configuration2/tree/ModelTransaction$ChildrenUpdateOperation.addNodeToRemove:(Lorg/apache/commons/configuration2/tree/ImmutableNode;)V
      15: aload_0
      16: aload_1
      17: iconst_m1
      18: invokevirtual #35                 // Method fetchOperations:(Lorg/apache/commons/configuration2/tree/ImmutableNode;I)Lorg/apache/commons/configuration2/tree/ModelTransaction$Operations;
      21: aload_3
      22: invokevirtual #36                 // Method org/apache/commons/configuration2/tree/ModelTransaction$Operations.addChildrenOperation:(Lorg/apache/commons/configuration2/tree/ModelTransaction$ChildrenUpdateOperation;)V
      25: return

  public void addRemoveAttributeOperation(org.apache.commons.configuration2.tree.ImmutableNode, java.lang.String);
    Code:
       0: aload_0
       1: aload_1
       2: iconst_m1
       3: invokevirtual #35                 // Method fetchOperations:(Lorg/apache/commons/configuration2/tree/ImmutableNode;I)Lorg/apache/commons/configuration2/tree/ModelTransaction$Operations;
       6: new           #44                 // class org/apache/commons/configuration2/tree/ModelTransaction$RemoveAttributeOperation
       9: dup
      10: aload_0
      11: aload_2
      12: invokespecial #45                 // Method org/apache/commons/configuration2/tree/ModelTransaction$RemoveAttributeOperation."<init>":(Lorg/apache/commons/configuration2/tree/ModelTransaction;Ljava/lang/String;)V
      15: invokevirtual #40                 // Method org/apache/commons/configuration2/tree/ModelTransaction$Operations.addOperation:(Lorg/apache/commons/configuration2/tree/ModelTransaction$Operation;)V
      18: return

  public void addClearNodeValueOperation(org.apache.commons.configuration2.tree.ImmutableNode);
    Code:
       0: aload_0
       1: aload_1
       2: aconst_null
       3: invokevirtual #46                 // Method addChangeNodeValueOperation:(Lorg/apache/commons/configuration2/tree/ImmutableNode;Ljava/lang/Object;)V
       6: return

  public void addChangeNodeValueOperation(org.apache.commons.configuration2.tree.ImmutableNode, java.lang.Object);
    Code:
       0: aload_0
       1: aload_1
       2: iconst_m1
       3: invokevirtual #35                 // Method fetchOperations:(Lorg/apache/commons/configuration2/tree/ImmutableNode;I)Lorg/apache/commons/configuration2/tree/ModelTransaction$Operations;
       6: new           #47                 // class org/apache/commons/configuration2/tree/ModelTransaction$ChangeNodeValueOperation
       9: dup
      10: aload_0
      11: aload_2
      12: invokespecial #48                 // Method org/apache/commons/configuration2/tree/ModelTransaction$ChangeNodeValueOperation."<init>":(Lorg/apache/commons/configuration2/tree/ModelTransaction;Ljava/lang/Object;)V
      15: invokevirtual #40                 // Method org/apache/commons/configuration2/tree/ModelTransaction$Operations.addOperation:(Lorg/apache/commons/configuration2/tree/ModelTransaction$Operation;)V
      18: return

  public void addChangeNodeNameOperation(org.apache.commons.configuration2.tree.ImmutableNode, java.lang.String);
    Code:
       0: aload_0
       1: aload_1
       2: iconst_m1
       3: invokevirtual #35                 // Method fetchOperations:(Lorg/apache/commons/configuration2/tree/ImmutableNode;I)Lorg/apache/commons/configuration2/tree/ModelTransaction$Operations;
       6: new           #49                 // class org/apache/commons/configuration2/tree/ModelTransaction$ChangeNodeNameOperation
       9: dup
      10: aload_0
      11: aload_2
      12: invokespecial #50                 // Method org/apache/commons/configuration2/tree/ModelTransaction$ChangeNodeNameOperation."<init>":(Lorg/apache/commons/configuration2/tree/ModelTransaction;Ljava/lang/String;)V
      15: invokevirtual #40                 // Method org/apache/commons/configuration2/tree/ModelTransaction$Operations.addOperation:(Lorg/apache/commons/configuration2/tree/ModelTransaction$Operation;)V
      18: return

  public void addNewReferences(java.util.Map<org.apache.commons.configuration2.tree.ImmutableNode, ?>);
    Code:
       0: aload_0
       1: invokespecial #51                 // Method fetchReferenceMap:()Ljava/util/Map;
       4: aload_1
       5: invokeinterface #52,  2           // InterfaceMethod java/util/Map.putAll:(Ljava/util/Map;)V
      10: return

  public void addNewReference(org.apache.commons.configuration2.tree.ImmutableNode, java.lang.Object);
    Code:
       0: aload_0
       1: invokespecial #51                 // Method fetchReferenceMap:()Ljava/util/Map;
       4: aload_1
       5: aload_2
       6: invokeinterface #53,  3           // InterfaceMethod java/util/Map.put:(Ljava/lang/Object;Ljava/lang/Object;)Ljava/lang/Object;
      11: pop
      12: return

  public org.apache.commons.configuration2.tree.TreeData execute();
    Code:
       0: aload_0
       1: invokespecial #54                 // Method executeOperations:()V
       4: aload_0
       5: invokespecial #55                 // Method updateParentMapping:()V
       8: new           #56                 // class org/apache/commons/configuration2/tree/TreeData
      11: dup
      12: aload_0
      13: getfield      #2                  // Field newRoot:Lorg/apache/commons/configuration2/tree/ImmutableNode;
      16: aload_0
      17: getfield      #12                 // Field parentMapping:Ljava/util/Map;
      20: aload_0
      21: getfield      #19                 // Field replacementMapping:Ljava/util/Map;
      24: aload_0
      25: getfield      #15                 // Field currentData:Lorg/apache/commons/configuration2/tree/TreeData;
      28: invokevirtual #57                 // Method org/apache/commons/configuration2/tree/TreeData.getNodeTracker:()Lorg/apache/commons/configuration2/tree/NodeTracker;
      31: aload_0
      32: getfield      #2                  // Field newRoot:Lorg/apache/commons/configuration2/tree/ImmutableNode;
      35: aload_0
      36: getfield      #30                 // Field rootNodeSelector:Lorg/apache/commons/configuration2/tree/NodeSelector;
      39: aload_0
      40: invokevirtual #58                 // Method getResolver:()Lorg/apache/commons/configuration2/tree/NodeKeyResolver;
      43: aload_0
      44: invokevirtual #17                 // Method getCurrentData:()Lorg/apache/commons/configuration2/tree/TreeData;
      47: invokevirtual #59                 // Method org/apache/commons/configuration2/tree/NodeTracker.update:(Lorg/apache/commons/configuration2/tree/ImmutableNode;Lorg/apache/commons/configuration2/tree/NodeSelector;Lorg/apache/commons/configuration2/tree/NodeKeyResolver;Lorg/apache/commons/configuration2/tree/NodeHandler;)Lorg/apache/commons/configuration2/tree/NodeTracker;
      50: aload_0
      51: invokespecial #60                 // Method updateReferenceTracker:()Lorg/apache/commons/configuration2/tree/ReferenceTracker;
      54: invokespecial #61                 // Method org/apache/commons/configuration2/tree/TreeData."<init>":(Lorg/apache/commons/configuration2/tree/ImmutableNode;Ljava/util/Map;Ljava/util/Map;Lorg/apache/commons/configuration2/tree/NodeTracker;Lorg/apache/commons/configuration2/tree/ReferenceTracker;)V
      57: areturn

  public org.apache.commons.configuration2.tree.TreeData getCurrentData();
    Code:
       0: aload_0
       1: getfield      #15                 // Field currentData:Lorg/apache/commons/configuration2/tree/TreeData;
       4: areturn

  org.apache.commons.configuration2.tree.ImmutableNode getParent(org.apache.commons.configuration2.tree.ImmutableNode);
    Code:
       0: aload_0
       1: invokevirtual #17                 // Method getCurrentData:()Lorg/apache/commons/configuration2/tree/TreeData;
       4: aload_1
       5: invokevirtual #62                 // Method org/apache/commons/configuration2/tree/TreeData.getParent:(Lorg/apache/commons/configuration2/tree/ImmutableNode;)Lorg/apache/commons/configuration2/tree/ImmutableNode;
       8: areturn

  org.apache.commons.configuration2.tree.ModelTransaction$Operations fetchOperations(org.apache.commons.configuration2.tree.ImmutableNode, int);
    Code:
       0: iload_2
       1: iconst_m1
       2: if_icmpne     13
       5: aload_0
       6: aload_1
       7: invokespecial #63                 // Method level:(Lorg/apache/commons/configuration2/tree/ImmutableNode;)I
      10: goto          14
      13: iload_2
      14: invokestatic  #64                 // Method java/lang/Integer.valueOf:(I)Ljava/lang/Integer;
      17: astore_3
      18: aload_0
      19: getfield      #25                 // Field operations:Ljava/util/SortedMap;
      22: aload_3
      23: invokeinterface #65,  2           // InterfaceMethod java/util/SortedMap.get:(Ljava/lang/Object;)Ljava/lang/Object;
      28: checkcast     #66                 // class java/util/Map
      31: astore        4
      33: aload         4
      35: ifnonnull     60
      38: new           #20                 // class java/util/HashMap
      41: dup
      42: invokespecial #21                 // Method java/util/HashMap."<init>":()V
      45: astore        4
      47: aload_0
      48: getfield      #25                 // Field operations:Ljava/util/SortedMap;
      51: aload_3
      52: aload         4
      54: invokeinterface #67,  3           // InterfaceMethod java/util/SortedMap.put:(Ljava/lang/Object;Ljava/lang/Object;)Ljava/lang/Object;
      59: pop
      60: aload         4
      62: aload_1
      63: invokeinterface #68,  2           // InterfaceMethod java/util/Map.get:(Ljava/lang/Object;)Ljava/lang/Object;
      68: checkcast     #69                 // class org/apache/commons/configuration2/tree/ModelTransaction$Operations
      71: astore        5
      73: aload         5
      75: ifnonnull     100
      78: new           #69                 // class org/apache/commons/configuration2/tree/ModelTransaction$Operations
      81: dup
      82: aload_0
      83: aconst_null
      84: invokespecial #70                 // Method org/apache/commons/configuration2/tree/ModelTransaction$Operations."<init>":(Lorg/apache/commons/configuration2/tree/ModelTransaction;Lorg/apache/commons/configuration2/tree/ModelTransaction$1;)V
      87: astore        5
      89: aload         4
      91: aload_1
      92: aload         5
      94: invokeinterface #53,  3           // InterfaceMethod java/util/Map.put:(Ljava/lang/Object;Ljava/lang/Object;)Ljava/lang/Object;
      99: pop
     100: aload         5
     102: areturn

  private org.apache.commons.configuration2.tree.ImmutableNode initQueryRoot(org.apache.commons.configuration2.tree.TreeData, org.apache.commons.configuration2.tree.NodeSelector);
    Code:
       0: aload_2
       1: ifnonnull     11
       4: aload_1
       5: invokevirtual #71                 // Method org/apache/commons/configuration2/tree/TreeData.getRootNode:()Lorg/apache/commons/configuration2/tree/ImmutableNode;
       8: goto          19
      11: aload_1
      12: invokevirtual #57                 // Method org/apache/commons/configuration2/tree/TreeData.getNodeTracker:()Lorg/apache/commons/configuration2/tree/NodeTracker;
      15: aload_2
      16: invokevirtual #72                 // Method org/apache/commons/configuration2/tree/NodeTracker.getTrackedNode:(Lorg/apache/commons/configuration2/tree/NodeSelector;)Lorg/apache/commons/configuration2/tree/ImmutableNode;
      19: areturn

  private int level(org.apache.commons.configuration2.tree.ImmutableNode);
    Code:
       0: aload_0
       1: invokevirtual #17                 // Method getCurrentData:()Lorg/apache/commons/configuration2/tree/TreeData;
       4: aload_1
       5: invokevirtual #62                 // Method org/apache/commons/configuration2/tree/TreeData.getParent:(Lorg/apache/commons/configuration2/tree/ImmutableNode;)Lorg/apache/commons/configuration2/tree/ImmutableNode;
       8: astore_2
       9: iconst_0
      10: istore_3
      11: aload_2
      12: ifnull        30
      15: iinc          3, 1
      18: aload_0
      19: invokevirtual #17                 // Method getCurrentData:()Lorg/apache/commons/configuration2/tree/TreeData;
      22: aload_2
      23: invokevirtual #62                 // Method org/apache/commons/configuration2/tree/TreeData.getParent:(Lorg/apache/commons/configuration2/tree/ImmutableNode;)Lorg/apache/commons/configuration2/tree/ImmutableNode;
      26: astore_2
      27: goto          11
      30: iload_3
      31: ireturn

  private void executeOperations();
    Code:
       0: aload_0
       1: getfield      #25                 // Field operations:Ljava/util/SortedMap;
       4: invokeinterface #73,  1           // InterfaceMethod java/util/SortedMap.isEmpty:()Z
       9: ifne          104
      12: aload_0
      13: getfield      #25                 // Field operations:Ljava/util/SortedMap;
      16: invokeinterface #74,  1           // InterfaceMethod java/util/SortedMap.lastKey:()Ljava/lang/Object;
      21: checkcast     #75                 // class java/lang/Integer
      24: astore_1
      25: aload_0
      26: getfield      #25                 // Field operations:Ljava/util/SortedMap;
      29: aload_1
      30: invokeinterface #76,  2           // InterfaceMethod java/util/SortedMap.remove:(Ljava/lang/Object;)Ljava/lang/Object;
      35: checkcast     #66                 // class java/util/Map
      38: astore_2
      39: aload_2
      40: invokeinterface #77,  1           // InterfaceMethod java/util/Map.entrySet:()Ljava/util/Set;
      45: invokeinterface #78,  1           // InterfaceMethod java/util/Set.iterator:()Ljava/util/Iterator;
      50: astore_3
      51: aload_3
      52: invokeinterface #79,  1           // InterfaceMethod java/util/Iterator.hasNext:()Z
      57: ifeq          101
      60: aload_3
      61: invokeinterface #80,  1           // InterfaceMethod java/util/Iterator.next:()Ljava/lang/Object;
      66: checkcast     #81                 // class java/util/Map$Entry
      69: astore        4
      71: aload         4
      73: invokeinterface #82,  1           // InterfaceMethod java/util/Map$Entry.getValue:()Ljava/lang/Object;
      78: checkcast     #69                 // class org/apache/commons/configuration2/tree/ModelTransaction$Operations
      81: aload         4
      83: invokeinterface #83,  1           // InterfaceMethod java/util/Map$Entry.getKey:()Ljava/lang/Object;
      88: checkcast     #84                 // class org/apache/commons/configuration2/tree/ImmutableNode
      91: aload_1
      92: invokevirtual #85                 // Method java/lang/Integer.intValue:()I
      95: invokevirtual #86                 // Method org/apache/commons/configuration2/tree/ModelTransaction$Operations.apply:(Lorg/apache/commons/configuration2/tree/ImmutableNode;I)V
      98: goto          51
     101: goto          0
     104: return

  private void updateParentMapping();
    Code:
       0: aload_0
       1: getfield      #19                 // Field replacementMapping:Ljava/util/Map;
       4: aload_0
       5: getfield      #4                  // Field replacedNodes:Ljava/util/Map;
       8: invokeinterface #52,  2           // InterfaceMethod java/util/Map.putAll:(Ljava/util/Map;)V
      13: aload_0
      14: getfield      #19                 // Field replacementMapping:Ljava/util/Map;
      17: invokeinterface #87,  1           // InterfaceMethod java/util/Map.size:()I
      22: sipush        200
      25: if_icmple     35
      28: aload_0
      29: invokespecial #88                 // Method rebuildParentMapping:()V
      32: goto          43
      35: aload_0
      36: invokespecial #89                 // Method updateParentMappingForAddedNodes:()V
      39: aload_0
      40: invokespecial #90                 // Method updateParentMappingForRemovedNodes:()V
      43: return

  private void rebuildParentMapping();
    Code:
       0: aload_0
       1: getfield      #19                 // Field replacementMapping:Ljava/util/Map;
       4: invokeinterface #91,  1           // InterfaceMethod java/util/Map.clear:()V
       9: aload_0
      10: getfield      #12                 // Field parentMapping:Ljava/util/Map;
      13: invokeinterface #91,  1           // InterfaceMethod java/util/Map.clear:()V
      18: aload_0
      19: getfield      #12                 // Field parentMapping:Ljava/util/Map;
      22: aload_0
      23: getfield      #2                  // Field newRoot:Lorg/apache/commons/configuration2/tree/ImmutableNode;
      26: invokestatic  #92                 // Method org/apache/commons/configuration2/tree/InMemoryNodeModel.updateParentMapping:(Ljava/util/Map;Lorg/apache/commons/configuration2/tree/ImmutableNode;)V
      29: return

  private void updateParentMappingForAddedNodes();
    Code:
       0: aload_0
       1: getfield      #1                  // Field addedNodes:Ljava/util/Collection;
       4: invokeinterface #93,  1           // InterfaceMethod java/util/Collection.iterator:()Ljava/util/Iterator;
       9: astore_1
      10: aload_1
      11: invokeinterface #79,  1           // InterfaceMethod java/util/Iterator.hasNext:()Z
      16: ifeq          40
      19: aload_1
      20: invokeinterface #80,  1           // InterfaceMethod java/util/Iterator.next:()Ljava/lang/Object;
      25: checkcast     #84                 // class org/apache/commons/configuration2/tree/ImmutableNode
      28: astore_2
      29: aload_0
      30: getfield      #12                 // Field parentMapping:Ljava/util/Map;
      33: aload_2
      34: invokestatic  #92                 // Method org/apache/commons/configuration2/tree/InMemoryNodeModel.updateParentMapping:(Ljava/util/Map;Lorg/apache/commons/configuration2/tree/ImmutableNode;)V
      37: goto          10
      40: return

  private void updateParentMappingForRemovedNodes();
    Code:
       0: aload_0
       1: getfield      #3                  // Field removedNodes:Ljava/util/Collection;
       4: invokeinterface #93,  1           // InterfaceMethod java/util/Collection.iterator:()Ljava/util/Iterator;
       9: astore_1
      10: aload_1
      11: invokeinterface #79,  1           // InterfaceMethod java/util/Iterator.hasNext:()Z
      16: ifeq          37
      19: aload_1
      20: invokeinterface #80,  1           // InterfaceMethod java/util/Iterator.next:()Ljava/lang/Object;
      25: checkcast     #84                 // class org/apache/commons/configuration2/tree/ImmutableNode
      28: astore_2
      29: aload_0
      30: aload_2
      31: invokespecial #94                 // Method removeNodesFromParentAndReplacementMapping:(Lorg/apache/commons/configuration2/tree/ImmutableNode;)V
      34: goto          10
      37: return

  private void removeNodesFromParentAndReplacementMapping(org.apache.commons.configuration2.tree.ImmutableNode);
    Code:
       0: getstatic     #95                 // Field org/apache/commons/configuration2/tree/NodeTreeWalker.INSTANCE:Lorg/apache/commons/configuration2/tree/NodeTreeWalker;
       3: aload_1
       4: new           #96                 // class org/apache/commons/configuration2/tree/ModelTransaction$1
       7: dup
       8: aload_0
       9: invokespecial #97                 // Method org/apache/commons/configuration2/tree/ModelTransaction$1."<init>":(Lorg/apache/commons/configuration2/tree/ModelTransaction;)V
      12: aload_0
      13: invokevirtual #17                 // Method getCurrentData:()Lorg/apache/commons/configuration2/tree/TreeData;
      16: invokevirtual #98                 // Method org/apache/commons/configuration2/tree/NodeTreeWalker.walkBFS:(Ljava/lang/Object;Lorg/apache/commons/configuration2/tree/ConfigurationNodeVisitor;Lorg/apache/commons/configuration2/tree/NodeHandler;)V
      19: return

  private void removeNodeFromReplacementMapping(org.apache.commons.configuration2.tree.ImmutableNode);
    Code:
       0: aload_1
       1: astore_2
       2: aload_0
       3: getfield      #19                 // Field replacementMapping:Ljava/util/Map;
       6: aload_2
       7: invokeinterface #99,  2           // InterfaceMethod java/util/Map.remove:(Ljava/lang/Object;)Ljava/lang/Object;
      12: checkcast     #84                 // class org/apache/commons/configuration2/tree/ImmutableNode
      15: astore_2
      16: aload_2
      17: ifnonnull     2
      20: return

  private org.apache.commons.configuration2.tree.ReferenceTracker updateReferenceTracker();
    Code:
       0: aload_0
       1: getfield      #15                 // Field currentData:Lorg/apache/commons/configuration2/tree/TreeData;
       4: invokevirtual #100                // Method org/apache/commons/configuration2/tree/TreeData.getReferenceTracker:()Lorg/apache/commons/configuration2/tree/ReferenceTracker;
       7: astore_1
       8: aload_0
       9: getfield      #101                // Field newReferences:Ljava/util/Map;
      12: ifnull        24
      15: aload_1
      16: aload_0
      17: getfield      #101                // Field newReferences:Ljava/util/Map;
      20: invokevirtual #102                // Method org/apache/commons/configuration2/tree/ReferenceTracker.addReferences:(Ljava/util/Map;)Lorg/apache/commons/configuration2/tree/ReferenceTracker;
      23: astore_1
      24: aload_1
      25: aload_0
      26: getfield      #4                  // Field replacedNodes:Ljava/util/Map;
      29: aload_0
      30: getfield      #13                 // Field allRemovedNodes:Ljava/util/Collection;
      33: invokevirtual #103                // Method org/apache/commons/configuration2/tree/ReferenceTracker.updateReferences:(Ljava/util/Map;Ljava/util/Collection;)Lorg/apache/commons/configuration2/tree/ReferenceTracker;
      36: areturn

  private java.util.Map<org.apache.commons.configuration2.tree.ImmutableNode, java.lang.Object> fetchReferenceMap();
    Code:
       0: aload_0
       1: getfield      #101                // Field newReferences:Ljava/util/Map;
       4: ifnonnull     18
       7: aload_0
       8: new           #20                 // class java/util/HashMap
      11: dup
      12: invokespecial #21                 // Method java/util/HashMap."<init>":()V
      15: putfield      #101                // Field newReferences:Ljava/util/Map;
      18: aload_0
      19: getfield      #101                // Field newReferences:Ljava/util/Map;
      22: areturn

  private static <E> java.util.Collection<E> concatenate(java.util.Collection<E>, java.util.Collection<? extends E>);
    Code:
       0: aload_1
       1: ifnonnull     6
       4: aload_0
       5: areturn
       6: aload_0
       7: ifnull        14
      10: aload_0
      11: goto          27
      14: new           #104                // class java/util/ArrayList
      17: dup
      18: aload_1
      19: invokeinterface #105,  1          // InterfaceMethod java/util/Collection.size:()I
      24: invokespecial #106                // Method java/util/ArrayList."<init>":(I)V
      27: astore_2
      28: aload_2
      29: aload_1
      30: invokeinterface #107,  2          // InterfaceMethod java/util/Collection.addAll:(Ljava/util/Collection;)Z
      35: pop
      36: aload_2
      37: areturn

  private static <E> java.util.Set<E> concatenate(java.util.Set<E>, java.util.Set<? extends E>);
    Code:
       0: aload_1
       1: ifnonnull     6
       4: aload_0
       5: areturn
       6: aload_0
       7: ifnull        14
      10: aload_0
      11: goto          21
      14: new           #108                // class java/util/HashSet
      17: dup
      18: invokespecial #109                // Method java/util/HashSet."<init>":()V
      21: astore_2
      22: aload_2
      23: aload_1
      24: invokeinterface #110,  2          // InterfaceMethod java/util/Set.addAll:(Ljava/util/Collection;)Z
      29: pop
      30: aload_2
      31: areturn

  private static <K, V> java.util.Map<K, V> concatenate(java.util.Map<K, V>, java.util.Map<? extends K, ? extends V>);
    Code:
       0: aload_1
       1: ifnonnull     6
       4: aload_0
       5: areturn
       6: aload_0
       7: ifnull        14
      10: aload_0
      11: goto          21
      14: new           #20                 // class java/util/HashMap
      17: dup
      18: invokespecial #21                 // Method java/util/HashMap."<init>":()V
      21: astore_2
      22: aload_2
      23: aload_1
      24: invokeinterface #52,  2           // InterfaceMethod java/util/Map.putAll:(Ljava/util/Map;)V
      29: aload_2
      30: areturn

  private static <E> java.util.Collection<E> append(java.util.Collection<E>, E);
    Code:
       0: aload_0
       1: ifnull        8
       4: aload_0
       5: goto          15
       8: new           #26                 // class java/util/LinkedList
      11: dup
      12: invokespecial #27                 // Method java/util/LinkedList."<init>":()V
      15: astore_2
      16: aload_2
      17: aload_1
      18: invokeinterface #111,  2          // InterfaceMethod java/util/Collection.add:(Ljava/lang/Object;)Z
      23: pop
      24: aload_2
      25: areturn

  private static <E> java.util.Set<E> append(java.util.Set<E>, E);
    Code:
       0: aload_0
       1: ifnull        8
       4: aload_0
       5: goto          15
       8: new           #108                // class java/util/HashSet
      11: dup
      12: invokespecial #109                // Method java/util/HashSet."<init>":()V
      15: astore_2
      16: aload_2
      17: aload_1
      18: invokeinterface #112,  2          // InterfaceMethod java/util/Set.add:(Ljava/lang/Object;)Z
      23: pop
      24: aload_2
      25: areturn

  private static <K, V> java.util.Map<K, V> append(java.util.Map<K, V>, K, V);
    Code:
       0: aload_0
       1: ifnull        8
       4: aload_0
       5: goto          15
       8: new           #20                 // class java/util/HashMap
      11: dup
      12: invokespecial #21                 // Method java/util/HashMap."<init>":()V
      15: astore_3
      16: aload_3
      17: aload_1
      18: aload_2
      19: invokeinterface #53,  3           // InterfaceMethod java/util/Map.put:(Ljava/lang/Object;Ljava/lang/Object;)Ljava/lang/Object;
      24: pop
      25: aload_3
      26: areturn

  static java.util.Collection access$200(org.apache.commons.configuration2.tree.ModelTransaction);
    Code:
       0: aload_0
       1: getfield      #13                 // Field allRemovedNodes:Ljava/util/Collection;
       4: areturn

  static java.util.Map access$300(org.apache.commons.configuration2.tree.ModelTransaction);
    Code:
       0: aload_0
       1: getfield      #12                 // Field parentMapping:Ljava/util/Map;
       4: areturn

  static void access$400(org.apache.commons.configuration2.tree.ModelTransaction, org.apache.commons.configuration2.tree.ImmutableNode);
    Code:
       0: aload_0
       1: aload_1
       2: invokespecial #11                 // Method removeNodeFromReplacementMapping:(Lorg/apache/commons/configuration2/tree/ImmutableNode;)V
       5: return

  static java.util.Collection access$600(java.util.Collection, java.util.Collection);
    Code:
       0: aload_0
       1: aload_1
       2: invokestatic  #10                 // Method concatenate:(Ljava/util/Collection;Ljava/util/Collection;)Ljava/util/Collection;
       5: areturn

  static java.util.Map access$700(java.util.Map, java.util.Map);
    Code:
       0: aload_0
       1: aload_1
       2: invokestatic  #9                  // Method concatenate:(Ljava/util/Map;Ljava/util/Map;)Ljava/util/Map;
       5: areturn

  static java.util.Set access$800(java.util.Set, java.util.Set);
    Code:
       0: aload_0
       1: aload_1
       2: invokestatic  #8                  // Method concatenate:(Ljava/util/Set;Ljava/util/Set;)Ljava/util/Set;
       5: areturn

  static java.util.Collection access$900(java.util.Collection, java.lang.Object);
    Code:
       0: aload_0
       1: aload_1
       2: invokestatic  #7                  // Method append:(Ljava/util/Collection;Ljava/lang/Object;)Ljava/util/Collection;
       5: areturn

  static java.util.Map access$1000(java.util.Map, java.lang.Object, java.lang.Object);
    Code:
       0: aload_0
       1: aload_1
       2: aload_2
       3: invokestatic  #6                  // Method append:(Ljava/util/Map;Ljava/lang/Object;Ljava/lang/Object;)Ljava/util/Map;
       6: areturn

  static java.util.Set access$1100(java.util.Set, java.lang.Object);
    Code:
       0: aload_0
       1: aload_1
       2: invokestatic  #5                  // Method append:(Ljava/util/Set;Ljava/lang/Object;)Ljava/util/Set;
       5: areturn

  static java.util.Map access$1200(org.apache.commons.configuration2.tree.ModelTransaction);
    Code:
       0: aload_0
       1: getfield      #4                  // Field replacedNodes:Ljava/util/Map;
       4: areturn

  static java.util.Collection access$1300(org.apache.commons.configuration2.tree.ModelTransaction);
    Code:
       0: aload_0
       1: getfield      #3                  // Field removedNodes:Ljava/util/Collection;
       4: areturn

  static org.apache.commons.configuration2.tree.ImmutableNode access$1402(org.apache.commons.configuration2.tree.ModelTransaction, org.apache.commons.configuration2.tree.ImmutableNode);
    Code:
       0: aload_0
       1: aload_1
       2: dup_x1
       3: putfield      #2                  // Field newRoot:Lorg/apache/commons/configuration2/tree/ImmutableNode;
       6: areturn

  static java.util.Collection access$1500(org.apache.commons.configuration2.tree.ModelTransaction);
    Code:
       0: aload_0
       1: getfield      #1                  // Field addedNodes:Ljava/util/Collection;
       4: areturn
}
