Compiled from "FileCopyUtils.java"
public abstract class org.springframework.util.FileCopyUtils {
  public static final int BUFFER_SIZE;

  public org.springframework.util.FileCopyUtils();
    Code:
       0: aload_0
       1: invokespecial #2                  // Method java/lang/Object."<init>":()V
       4: return

  public static int copy(java.io.File, java.io.File) throws java.io.IOException;
    Code:
       0: aload_0
       1: ldc           #3                  // String No input File specified
       3: invokestatic  #4                  // Method org/springframework/util/Assert.notNull:(Ljava/lang/Object;Ljava/lang/String;)V
       6: aload_1
       7: ldc           #5                  // String No output File specified
       9: invokestatic  #4                  // Method org/springframework/util/Assert.notNull:(Ljava/lang/Object;Ljava/lang/String;)V
      12: aload_0
      13: invokevirtual #6                  // Method java/io/File.toPath:()Ljava/nio/file/Path;
      16: iconst_0
      17: anewarray     #7                  // class java/nio/file/OpenOption
      20: invokestatic  #8                  // Method java/nio/file/Files.newInputStream:(Ljava/nio/file/Path;[Ljava/nio/file/OpenOption;)Ljava/io/InputStream;
      23: aload_1
      24: invokevirtual #6                  // Method java/io/File.toPath:()Ljava/nio/file/Path;
      27: iconst_0
      28: anewarray     #7                  // class java/nio/file/OpenOption
      31: invokestatic  #9                  // Method java/nio/file/Files.newOutputStream:(Ljava/nio/file/Path;[Ljava/nio/file/OpenOption;)Ljava/io/OutputStream;
      34: invokestatic  #10                 // Method copy:(Ljava/io/InputStream;Ljava/io/OutputStream;)I
      37: ireturn

  public static void copy(byte[], java.io.File) throws java.io.IOException;
    Code:
       0: aload_0
       1: ldc           #11                 // String No input byte array specified
       3: invokestatic  #4                  // Method org/springframework/util/Assert.notNull:(Ljava/lang/Object;Ljava/lang/String;)V
       6: aload_1
       7: ldc           #5                  // String No output File specified
       9: invokestatic  #4                  // Method org/springframework/util/Assert.notNull:(Ljava/lang/Object;Ljava/lang/String;)V
      12: new           #12                 // class java/io/ByteArrayInputStream
      15: dup
      16: aload_0
      17: invokespecial #13                 // Method java/io/ByteArrayInputStream."<init>":([B)V
      20: aload_1
      21: invokevirtual #6                  // Method java/io/File.toPath:()Ljava/nio/file/Path;
      24: iconst_0
      25: anewarray     #7                  // class java/nio/file/OpenOption
      28: invokestatic  #9                  // Method java/nio/file/Files.newOutputStream:(Ljava/nio/file/Path;[Ljava/nio/file/OpenOption;)Ljava/io/OutputStream;
      31: invokestatic  #10                 // Method copy:(Ljava/io/InputStream;Ljava/io/OutputStream;)I
      34: pop
      35: return

  public static byte[] copyToByteArray(java.io.File) throws java.io.IOException;
    Code:
       0: aload_0
       1: ldc           #3                  // String No input File specified
       3: invokestatic  #4                  // Method org/springframework/util/Assert.notNull:(Ljava/lang/Object;Ljava/lang/String;)V
       6: aload_0
       7: invokevirtual #6                  // Method java/io/File.toPath:()Ljava/nio/file/Path;
      10: iconst_0
      11: anewarray     #7                  // class java/nio/file/OpenOption
      14: invokestatic  #8                  // Method java/nio/file/Files.newInputStream:(Ljava/nio/file/Path;[Ljava/nio/file/OpenOption;)Ljava/io/InputStream;
      17: invokestatic  #14                 // Method copyToByteArray:(Ljava/io/InputStream;)[B
      20: areturn

  public static int copy(java.io.InputStream, java.io.OutputStream) throws java.io.IOException;
    Code:
       0: aload_0
       1: ldc           #15                 // String No InputStream specified
       3: invokestatic  #4                  // Method org/springframework/util/Assert.notNull:(Ljava/lang/Object;Ljava/lang/String;)V
       6: aload_1
       7: ldc           #16                 // String No OutputStream specified
       9: invokestatic  #4                  // Method org/springframework/util/Assert.notNull:(Ljava/lang/Object;Ljava/lang/String;)V
      12: aload_0
      13: aload_1
      14: invokestatic  #17                 // Method org/springframework/util/StreamUtils.copy:(Ljava/io/InputStream;Ljava/io/OutputStream;)I
      17: istore_2
      18: aload_0
      19: invokevirtual #18                 // Method java/io/InputStream.close:()V
      22: goto          26
      25: astore_3
      26: aload_1
      27: invokevirtual #20                 // Method java/io/OutputStream.close:()V
      30: goto          34
      33: astore_3
      34: iload_2
      35: ireturn
      36: astore        4
      38: aload_0
      39: invokevirtual #18                 // Method java/io/InputStream.close:()V
      42: goto          47
      45: astore        5
      47: aload_1
      48: invokevirtual #20                 // Method java/io/OutputStream.close:()V
      51: goto          56
      54: astore        5
      56: aload         4
      58: athrow
    Exception table:
       from    to  target type
          18    22    25   Class java/io/IOException
          26    30    33   Class java/io/IOException
          12    18    36   any
          38    42    45   Class java/io/IOException
          47    51    54   Class java/io/IOException
          36    38    36   any

  public static void copy(byte[], java.io.OutputStream) throws java.io.IOException;
    Code:
       0: aload_0
       1: ldc           #11                 // String No input byte array specified
       3: invokestatic  #4                  // Method org/springframework/util/Assert.notNull:(Ljava/lang/Object;Ljava/lang/String;)V
       6: aload_1
       7: ldc           #16                 // String No OutputStream specified
       9: invokestatic  #4                  // Method org/springframework/util/Assert.notNull:(Ljava/lang/Object;Ljava/lang/String;)V
      12: aload_1
      13: aload_0
      14: invokevirtual #21                 // Method java/io/OutputStream.write:([B)V
      17: aload_1
      18: invokevirtual #20                 // Method java/io/OutputStream.close:()V
      21: goto          40
      24: astore_2
      25: goto          40
      28: astore_3
      29: aload_1
      30: invokevirtual #20                 // Method java/io/OutputStream.close:()V
      33: goto          38
      36: astore        4
      38: aload_3
      39: athrow
      40: return
    Exception table:
       from    to  target type
          17    21    24   Class java/io/IOException
          12    17    28   any
          29    33    36   Class java/io/IOException

  public static byte[] copyToByteArray(java.io.InputStream) throws java.io.IOException;
    Code:
       0: aload_0
       1: ifnonnull     8
       4: iconst_0
       5: newarray       byte
       7: areturn
       8: new           #22                 // class java/io/ByteArrayOutputStream
      11: dup
      12: sipush        4096
      15: invokespecial #24                 // Method java/io/ByteArrayOutputStream."<init>":(I)V
      18: astore_1
      19: aload_0
      20: aload_1
      21: invokestatic  #10                 // Method copy:(Ljava/io/InputStream;Ljava/io/OutputStream;)I
      24: pop
      25: aload_1
      26: invokevirtual #25                 // Method java/io/ByteArrayOutputStream.toByteArray:()[B
      29: areturn

  public static int copy(java.io.Reader, java.io.Writer) throws java.io.IOException;
    Code:
       0: aload_0
       1: ldc           #26                 // String No Reader specified
       3: invokestatic  #4                  // Method org/springframework/util/Assert.notNull:(Ljava/lang/Object;Ljava/lang/String;)V
       6: aload_1
       7: ldc           #27                 // String No Writer specified
       9: invokestatic  #4                  // Method org/springframework/util/Assert.notNull:(Ljava/lang/Object;Ljava/lang/String;)V
      12: iconst_0
      13: istore_2
      14: sipush        4096
      17: newarray       char
      19: astore_3
      20: iconst_m1
      21: istore        4
      23: aload_0
      24: aload_3
      25: invokevirtual #28                 // Method java/io/Reader.read:([C)I
      28: dup
      29: istore        4
      31: iconst_m1
      32: if_icmpeq     51
      35: aload_1
      36: aload_3
      37: iconst_0
      38: iload         4
      40: invokevirtual #29                 // Method java/io/Writer.write:([CII)V
      43: iload_2
      44: iload         4
      46: iadd
      47: istore_2
      48: goto          23
      51: aload_1
      52: invokevirtual #30                 // Method java/io/Writer.flush:()V
      55: iload_2
      56: istore        5
      58: aload_0
      59: invokevirtual #31                 // Method java/io/Reader.close:()V
      62: goto          67
      65: astore        6
      67: aload_1
      68: invokevirtual #32                 // Method java/io/Writer.close:()V
      71: goto          76
      74: astore        6
      76: iload         5
      78: ireturn
      79: astore        7
      81: aload_0
      82: invokevirtual #31                 // Method java/io/Reader.close:()V
      85: goto          90
      88: astore        8
      90: aload_1
      91: invokevirtual #32                 // Method java/io/Writer.close:()V
      94: goto          99
      97: astore        8
      99: aload         7
     101: athrow
    Exception table:
       from    to  target type
          58    62    65   Class java/io/IOException
          67    71    74   Class java/io/IOException
          12    58    79   any
          81    85    88   Class java/io/IOException
          90    94    97   Class java/io/IOException
          79    81    79   any

  public static void copy(java.lang.String, java.io.Writer) throws java.io.IOException;
    Code:
       0: aload_0
       1: ldc           #33                 // String No input String specified
       3: invokestatic  #4                  // Method org/springframework/util/Assert.notNull:(Ljava/lang/Object;Ljava/lang/String;)V
       6: aload_1
       7: ldc           #27                 // String No Writer specified
       9: invokestatic  #4                  // Method org/springframework/util/Assert.notNull:(Ljava/lang/Object;Ljava/lang/String;)V
      12: aload_1
      13: aload_0
      14: invokevirtual #34                 // Method java/io/Writer.write:(Ljava/lang/String;)V
      17: aload_1
      18: invokevirtual #32                 // Method java/io/Writer.close:()V
      21: goto          40
      24: astore_2
      25: goto          40
      28: astore_3
      29: aload_1
      30: invokevirtual #32                 // Method java/io/Writer.close:()V
      33: goto          38
      36: astore        4
      38: aload_3
      39: athrow
      40: return
    Exception table:
       from    to  target type
          17    21    24   Class java/io/IOException
          12    17    28   any
          29    33    36   Class java/io/IOException

  public static java.lang.String copyToString(java.io.Reader) throws java.io.IOException;
    Code:
       0: aload_0
       1: ifnonnull     7
       4: ldc           #35                 // String
       6: areturn
       7: new           #36                 // class java/io/StringWriter
      10: dup
      11: invokespecial #37                 // Method java/io/StringWriter."<init>":()V
      14: astore_1
      15: aload_0
      16: aload_1
      17: invokestatic  #38                 // Method copy:(Ljava/io/Reader;Ljava/io/Writer;)I
      20: pop
      21: aload_1
      22: invokevirtual #39                 // Method java/io/StringWriter.toString:()Ljava/lang/String;
      25: areturn
}
