Compiled from "ReplicationWorker.java"
class org.apache.bookkeeper.replication.ReplicationWorker$1 extends com.google.common.cache.CacheLoader<java.lang.Long, java.util.concurrent.atomic.AtomicInteger> {
  final org.apache.bookkeeper.replication.ReplicationWorker this$0;

  org.apache.bookkeeper.replication.ReplicationWorker$1(org.apache.bookkeeper.replication.ReplicationWorker);
    Code:
       0: aload_0
       1: aload_1
       2: putfield      #1                  // Field this$0:Lorg/apache/bookkeeper/replication/ReplicationWorker;
       5: aload_0
       6: invokespecial #2                  // Method com/google/common/cache/CacheLoader."<init>":()V
       9: return

  public java.util.concurrent.atomic.AtomicInteger load(java.lang.Long) throws java.lang.Exception;
    Code:
       0: new           #3                  // class java/util/concurrent/atomic/AtomicInteger
       3: dup
       4: invokespecial #4                  // Method java/util/concurrent/atomic/AtomicInteger."<init>":()V
       7: areturn

  public java.lang.Object load(java.lang.Object) throws java.lang.Exception;
    Code:
       0: aload_0
       1: aload_1
       2: checkcast     #5                  // class java/lang/Long
       5: invokevirtual #6                  // Method load:(Ljava/lang/Long;)Ljava/util/concurrent/atomic/AtomicInteger;
       8: areturn
}
