Compiled from "SubjectPolicyContextHandler.java"
public class org.jboss.security.jacc.SubjectPolicyContextHandler implements javax.security.jacc.PolicyContextHandler {
  public static final java.util.HashSet<java.lang.Object> EMPTY_SET;

  public org.jboss.security.jacc.SubjectPolicyContextHandler();
    Code:
       0: aload_0
       1: invokespecial #2                  // Method java/lang/Object."<init>":()V
       4: return

  public java.lang.Object getContext(java.lang.String, java.lang.Object) throws javax.security.jacc.PolicyContextException;
    Code:
       0: aload_1
       1: ldc           #3                  // String javax.security.auth.Subject.container
       3: invokevirtual #4                  // Method java/lang/String.equalsIgnoreCase:(Ljava/lang/String;)Z
       6: ifne          11
       9: aconst_null
      10: areturn
      11: getstatic     #5                  // Field org/jboss/security/jacc/SubjectPolicyContextHandler$GetSubjectAction.ACTION:Ljava/security/PrivilegedAction;
      14: invokestatic  #6                  // Method java/security/AccessController.doPrivileged:(Ljava/security/PrivilegedAction;)Ljava/lang/Object;
      17: checkcast     #7                  // class javax/security/auth/Subject
      20: astore_3
      21: aload_3
      22: areturn

  public java.lang.String[] getKeys() throws javax.security.jacc.PolicyContextException;
    Code:
       0: iconst_1
       1: anewarray     #8                  // class java/lang/String
       4: dup
       5: iconst_0
       6: ldc           #3                  // String javax.security.auth.Subject.container
       8: aastore
       9: astore_1
      10: aload_1
      11: areturn

  public boolean supports(java.lang.String) throws javax.security.jacc.PolicyContextException;
    Code:
       0: aload_1
       1: ldc           #3                  // String javax.security.auth.Subject.container
       3: invokevirtual #4                  // Method java/lang/String.equalsIgnoreCase:(Ljava/lang/String;)Z
       6: ireturn

  static {};
    Code:
       0: new           #9                  // class java/util/HashSet
       3: dup
       4: invokespecial #10                 // Method java/util/HashSet."<init>":()V
       7: putstatic     #11                 // Field EMPTY_SET:Ljava/util/HashSet;
      10: return
}
