Compiled from "ExplicitConstructorInvocationStmt.java"
public final class io.sundr.shaded.com.github.javaparser.ast.stmt.ExplicitConstructorInvocationStmt extends io.sundr.shaded.com.github.javaparser.ast.stmt.Statement {
  private java.util.List<io.sundr.shaded.com.github.javaparser.ast.type.Type> typeArgs;

  private boolean isThis;

  private io.sundr.shaded.com.github.javaparser.ast.expr.Expression expr;

  private java.util.List<io.sundr.shaded.com.github.javaparser.ast.expr.Expression> args;

  public io.sundr.shaded.com.github.javaparser.ast.stmt.ExplicitConstructorInvocationStmt();
    Code:
       0: aload_0
       1: invokespecial #18                 // Method io/sundr/shaded/com/github/javaparser/ast/stmt/Statement."<init>":()V
       4: return

  public io.sundr.shaded.com.github.javaparser.ast.stmt.ExplicitConstructorInvocationStmt(boolean, io.sundr.shaded.com.github.javaparser.ast.expr.Expression, java.util.List<io.sundr.shaded.com.github.javaparser.ast.expr.Expression>);
    Code:
       0: aload_0
       1: invokespecial #18                 // Method io/sundr/shaded/com/github/javaparser/ast/stmt/Statement."<init>":()V
       4: aload_0
       5: iload_1
       6: invokevirtual #25                 // Method setThis:(Z)V
       9: aload_0
      10: aload_2
      11: invokevirtual #29                 // Method setExpr:(Lio/sundr/shaded/com/github/javaparser/ast/expr/Expression;)V
      14: aload_0
      15: aload_3
      16: invokevirtual #33                 // Method setArgs:(Ljava/util/List;)V
      19: return

  public io.sundr.shaded.com.github.javaparser.ast.stmt.ExplicitConstructorInvocationStmt(int, int, int, int, java.util.List<io.sundr.shaded.com.github.javaparser.ast.type.Type>, boolean, io.sundr.shaded.com.github.javaparser.ast.expr.Expression, java.util.List<io.sundr.shaded.com.github.javaparser.ast.expr.Expression>);
    Code:
       0: aload_0
       1: new           #37                 // class io/sundr/shaded/com/github/javaparser/Range
       4: dup
       5: iload_1
       6: iload_2
       7: invokestatic  #43                 // Method io/sundr/shaded/com/github/javaparser/Position.pos:(II)Lio/sundr/shaded/com/github/javaparser/Position;
      10: iload_3
      11: iload         4
      13: invokestatic  #43                 // Method io/sundr/shaded/com/github/javaparser/Position.pos:(II)Lio/sundr/shaded/com/github/javaparser/Position;
      16: invokespecial #46                 // Method io/sundr/shaded/com/github/javaparser/Range."<init>":(Lio/sundr/shaded/com/github/javaparser/Position;Lio/sundr/shaded/com/github/javaparser/Position;)V
      19: aload         5
      21: iload         6
      23: aload         7
      25: aload         8
      27: invokespecial #49                 // Method "<init>":(Lio/sundr/shaded/com/github/javaparser/Range;Ljava/util/List;ZLio/sundr/shaded/com/github/javaparser/ast/expr/Expression;Ljava/util/List;)V
      30: return

  public io.sundr.shaded.com.github.javaparser.ast.stmt.ExplicitConstructorInvocationStmt(io.sundr.shaded.com.github.javaparser.Range, java.util.List<io.sundr.shaded.com.github.javaparser.ast.type.Type>, boolean, io.sundr.shaded.com.github.javaparser.ast.expr.Expression, java.util.List<io.sundr.shaded.com.github.javaparser.ast.expr.Expression>);
    Code:
       0: aload_0
       1: aload_1
       2: invokespecial #57                 // Method io/sundr/shaded/com/github/javaparser/ast/stmt/Statement."<init>":(Lio/sundr/shaded/com/github/javaparser/Range;)V
       5: aload_0
       6: aload_2
       7: invokevirtual #60                 // Method setTypeArgs:(Ljava/util/List;)V
      10: aload_0
      11: iload_3
      12: invokevirtual #25                 // Method setThis:(Z)V
      15: aload_0
      16: aload         4
      18: invokevirtual #29                 // Method setExpr:(Lio/sundr/shaded/com/github/javaparser/ast/expr/Expression;)V
      21: aload_0
      22: aload         5
      24: invokevirtual #33                 // Method setArgs:(Ljava/util/List;)V
      27: return

  public <R, A> R accept(io.sundr.shaded.com.github.javaparser.ast.visitor.GenericVisitor<R, A>, A);
    Code:
       0: aload_1
       1: aload_0
       2: aload_2
       3: invokeinterface #70,  3           // InterfaceMethod io/sundr/shaded/com/github/javaparser/ast/visitor/GenericVisitor.visit:(Lio/sundr/shaded/com/github/javaparser/ast/stmt/ExplicitConstructorInvocationStmt;Ljava/lang/Object;)Ljava/lang/Object;
       8: areturn

  public <A> void accept(io.sundr.shaded.com.github.javaparser.ast.visitor.VoidVisitor<A>, A);
    Code:
       0: aload_1
       1: aload_0
       2: aload_2
       3: invokeinterface #82,  3           // InterfaceMethod io/sundr/shaded/com/github/javaparser/ast/visitor/VoidVisitor.visit:(Lio/sundr/shaded/com/github/javaparser/ast/stmt/ExplicitConstructorInvocationStmt;Ljava/lang/Object;)V
       8: return

  public java.util.List<io.sundr.shaded.com.github.javaparser.ast.expr.Expression> getArgs();
    Code:
       0: aload_0
       1: aload_0
       2: getfield      #88                 // Field args:Ljava/util/List;
       5: invokestatic  #94                 // Method io/sundr/shaded/com/github/javaparser/ast/internal/Utils.ensureNotNull:(Ljava/util/List;)Ljava/util/List;
       8: putfield      #88                 // Field args:Ljava/util/List;
      11: aload_0
      12: getfield      #88                 // Field args:Ljava/util/List;
      15: areturn

  public io.sundr.shaded.com.github.javaparser.ast.expr.Expression getExpr();
    Code:
       0: aload_0
       1: getfield      #98                 // Field expr:Lio/sundr/shaded/com/github/javaparser/ast/expr/Expression;
       4: areturn

  public java.util.List<io.sundr.shaded.com.github.javaparser.ast.type.Type> getTypeArgs();
    Code:
       0: aload_0
       1: aload_0
       2: getfield      #101                // Field typeArgs:Ljava/util/List;
       5: invokestatic  #94                 // Method io/sundr/shaded/com/github/javaparser/ast/internal/Utils.ensureNotNull:(Ljava/util/List;)Ljava/util/List;
       8: putfield      #101                // Field typeArgs:Ljava/util/List;
      11: aload_0
      12: getfield      #101                // Field typeArgs:Ljava/util/List;
      15: areturn

  public boolean isThis();
    Code:
       0: aload_0
       1: getfield      #104                // Field isThis:Z
       4: ireturn

  public void setArgs(java.util.List<io.sundr.shaded.com.github.javaparser.ast.expr.Expression>);
    Code:
       0: aload_0
       1: aload_1
       2: putfield      #88                 // Field args:Ljava/util/List;
       5: aload_0
       6: aload_0
       7: getfield      #88                 // Field args:Ljava/util/List;
      10: invokevirtual #107                // Method setAsParentNodeOf:(Ljava/util/List;)V
      13: return

  public void setExpr(io.sundr.shaded.com.github.javaparser.ast.expr.Expression);
    Code:
       0: aload_0
       1: aload_1
       2: putfield      #98                 // Field expr:Lio/sundr/shaded/com/github/javaparser/ast/expr/Expression;
       5: aload_0
       6: aload_0
       7: getfield      #98                 // Field expr:Lio/sundr/shaded/com/github/javaparser/ast/expr/Expression;
      10: invokevirtual #110                // Method setAsParentNodeOf:(Lio/sundr/shaded/com/github/javaparser/ast/Node;)V
      13: return

  public void setThis(boolean);
    Code:
       0: aload_0
       1: iload_1
       2: putfield      #104                // Field isThis:Z
       5: return

  public void setTypeArgs(java.util.List<io.sundr.shaded.com.github.javaparser.ast.type.Type>);
    Code:
       0: aload_0
       1: aload_1
       2: putfield      #101                // Field typeArgs:Ljava/util/List;
       5: aload_0
       6: aload_0
       7: getfield      #101                // Field typeArgs:Ljava/util/List;
      10: invokevirtual #107                // Method setAsParentNodeOf:(Ljava/util/List;)V
      13: return
}
