Compiled from "GateHandlerWrapper.java"
final class org.wildfly.swarm.undertow.runtime.GateHandlerWrapper$GateHandler implements io.undertow.server.HttpHandler {
  private final io.undertow.server.HttpHandler next;

  final org.wildfly.swarm.undertow.runtime.GateHandlerWrapper this$0;

  private org.wildfly.swarm.undertow.runtime.GateHandlerWrapper$GateHandler(org.wildfly.swarm.undertow.runtime.GateHandlerWrapper, io.undertow.server.HttpHandler);
    Code:
       0: aload_0
       1: aload_1
       2: putfield      #3                  // Field this$0:Lorg/wildfly/swarm/undertow/runtime/GateHandlerWrapper;
       5: aload_0
       6: invokespecial #4                  // Method java/lang/Object."<init>":()V
       9: aload_0
      10: aload_2
      11: putfield      #1                  // Field next:Lio/undertow/server/HttpHandler;
      14: return

  public void handleRequest(io.undertow.server.HttpServerExchange) throws java.lang.Exception;
    Code:
       0: aload_0
       1: getfield      #3                  // Field this$0:Lorg/wildfly/swarm/undertow/runtime/GateHandlerWrapper;
       4: invokestatic  #5                  // Method org/wildfly/swarm/undertow/runtime/GateHandlerWrapper.access$100:(Lorg/wildfly/swarm/undertow/runtime/GateHandlerWrapper;)Z
       7: ifeq          21
      10: aload_0
      11: getfield      #1                  // Field next:Lio/undertow/server/HttpHandler;
      14: aload_1
      15: invokeinterface #6,  2            // InterfaceMethod io/undertow/server/HttpHandler.handleRequest:(Lio/undertow/server/HttpServerExchange;)V
      20: return
      21: aload_0
      22: getfield      #3                  // Field this$0:Lorg/wildfly/swarm/undertow/runtime/GateHandlerWrapper;
      25: dup
      26: astore_2
      27: monitorenter
      28: aload_0
      29: getfield      #3                  // Field this$0:Lorg/wildfly/swarm/undertow/runtime/GateHandlerWrapper;
      32: invokestatic  #5                  // Method org/wildfly/swarm/undertow/runtime/GateHandlerWrapper.access$100:(Lorg/wildfly/swarm/undertow/runtime/GateHandlerWrapper;)Z
      35: ifeq          51
      38: aload_0
      39: getfield      #1                  // Field next:Lio/undertow/server/HttpHandler;
      42: aload_1
      43: invokeinterface #6,  2            // InterfaceMethod io/undertow/server/HttpHandler.handleRequest:(Lio/undertow/server/HttpServerExchange;)V
      48: goto          68
      51: aload_1
      52: getstatic     #7                  // Field io/undertow/util/SameThreadExecutor.INSTANCE:Ljava/util/concurrent/Executor;
      55: new           #8                  // class org/wildfly/swarm/undertow/runtime/GateHandlerWrapper$GateHandler$1
      58: dup
      59: aload_0
      60: aload_1
      61: invokespecial #9                  // Method org/wildfly/swarm/undertow/runtime/GateHandlerWrapper$GateHandler$1."<init>":(Lorg/wildfly/swarm/undertow/runtime/GateHandlerWrapper$GateHandler;Lio/undertow/server/HttpServerExchange;)V
      64: invokevirtual #10                 // Method io/undertow/server/HttpServerExchange.dispatch:(Ljava/util/concurrent/Executor;Ljava/lang/Runnable;)Lio/undertow/server/HttpServerExchange;
      67: pop
      68: aload_2
      69: monitorexit
      70: goto          78
      73: astore_3
      74: aload_2
      75: monitorexit
      76: aload_3
      77: athrow
      78: return
    Exception table:
       from    to  target type
          28    70    73   any
          73    76    73   any

  org.wildfly.swarm.undertow.runtime.GateHandlerWrapper$GateHandler(org.wildfly.swarm.undertow.runtime.GateHandlerWrapper, io.undertow.server.HttpHandler, org.wildfly.swarm.undertow.runtime.GateHandlerWrapper$1);
    Code:
       0: aload_0
       1: aload_1
       2: aload_2
       3: invokespecial #2                  // Method "<init>":(Lorg/wildfly/swarm/undertow/runtime/GateHandlerWrapper;Lio/undertow/server/HttpHandler;)V
       6: return

  static io.undertow.server.HttpHandler access$200(org.wildfly.swarm.undertow.runtime.GateHandlerWrapper$GateHandler);
    Code:
       0: aload_0
       1: getfield      #1                  // Field next:Lio/undertow/server/HttpHandler;
       4: areturn
}
