Compiled from "BookieStateService.java"
public class org.apache.bookkeeper.server.http.service.BookieStateService$BookieState {
  private boolean running;

  private boolean readOnly;

  private boolean shuttingDown;

  private boolean availableForHighPriorityWrites;

  public boolean isRunning();
    Code:
       0: aload_0
       1: getfield      #4                  // Field running:Z
       4: ireturn

  public boolean isReadOnly();
    Code:
       0: aload_0
       1: getfield      #3                  // Field readOnly:Z
       4: ireturn

  public boolean isShuttingDown();
    Code:
       0: aload_0
       1: getfield      #2                  // Field shuttingDown:Z
       4: ireturn

  public boolean isAvailableForHighPriorityWrites();
    Code:
       0: aload_0
       1: getfield      #1                  // Field availableForHighPriorityWrites:Z
       4: ireturn

  public void setRunning(boolean);
    Code:
       0: aload_0
       1: iload_1
       2: putfield      #4                  // Field running:Z
       5: return

  public void setReadOnly(boolean);
    Code:
       0: aload_0
       1: iload_1
       2: putfield      #3                  // Field readOnly:Z
       5: return

  public void setShuttingDown(boolean);
    Code:
       0: aload_0
       1: iload_1
       2: putfield      #2                  // Field shuttingDown:Z
       5: return

  public void setAvailableForHighPriorityWrites(boolean);
    Code:
       0: aload_0
       1: iload_1
       2: putfield      #1                  // Field availableForHighPriorityWrites:Z
       5: return

  public boolean equals(java.lang.Object);
    Code:
       0: aload_1
       1: aload_0
       2: if_acmpne     7
       5: iconst_1
       6: ireturn
       7: aload_1
       8: instanceof    #5                  // class org/apache/bookkeeper/server/http/service/BookieStateService$BookieState
      11: ifne          16
      14: iconst_0
      15: ireturn
      16: aload_1
      17: checkcast     #5                  // class org/apache/bookkeeper/server/http/service/BookieStateService$BookieState
      20: astore_2
      21: aload_2
      22: aload_0
      23: invokevirtual #6                  // Method canEqual:(Ljava/lang/Object;)Z
      26: ifne          31
      29: iconst_0
      30: ireturn
      31: aload_0
      32: invokevirtual #7                  // Method isRunning:()Z
      35: aload_2
      36: invokevirtual #7                  // Method isRunning:()Z
      39: if_icmpeq     44
      42: iconst_0
      43: ireturn
      44: aload_0
      45: invokevirtual #8                  // Method isReadOnly:()Z
      48: aload_2
      49: invokevirtual #8                  // Method isReadOnly:()Z
      52: if_icmpeq     57
      55: iconst_0
      56: ireturn
      57: aload_0
      58: invokevirtual #9                  // Method isShuttingDown:()Z
      61: aload_2
      62: invokevirtual #9                  // Method isShuttingDown:()Z
      65: if_icmpeq     70
      68: iconst_0
      69: ireturn
      70: aload_0
      71: invokevirtual #10                 // Method isAvailableForHighPriorityWrites:()Z
      74: aload_2
      75: invokevirtual #10                 // Method isAvailableForHighPriorityWrites:()Z
      78: if_icmpeq     83
      81: iconst_0
      82: ireturn
      83: iconst_1
      84: ireturn

  protected boolean canEqual(java.lang.Object);
    Code:
       0: aload_1
       1: instanceof    #5                  // class org/apache/bookkeeper/server/http/service/BookieStateService$BookieState
       4: ireturn

  public int hashCode();
    Code:
       0: bipush        59
       2: istore_1
       3: iconst_1
       4: istore_2
       5: iload_2
       6: bipush        59
       8: imul
       9: aload_0
      10: invokevirtual #7                  // Method isRunning:()Z
      13: ifeq          21
      16: bipush        79
      18: goto          23
      21: bipush        97
      23: iadd
      24: istore_2
      25: iload_2
      26: bipush        59
      28: imul
      29: aload_0
      30: invokevirtual #8                  // Method isReadOnly:()Z
      33: ifeq          41
      36: bipush        79
      38: goto          43
      41: bipush        97
      43: iadd
      44: istore_2
      45: iload_2
      46: bipush        59
      48: imul
      49: aload_0
      50: invokevirtual #9                  // Method isShuttingDown:()Z
      53: ifeq          61
      56: bipush        79
      58: goto          63
      61: bipush        97
      63: iadd
      64: istore_2
      65: iload_2
      66: bipush        59
      68: imul
      69: aload_0
      70: invokevirtual #10                 // Method isAvailableForHighPriorityWrites:()Z
      73: ifeq          81
      76: bipush        79
      78: goto          83
      81: bipush        97
      83: iadd
      84: istore_2
      85: iload_2
      86: ireturn

  public java.lang.String toString();
    Code:
       0: new           #11                 // class java/lang/StringBuilder
       3: dup
       4: invokespecial #12                 // Method java/lang/StringBuilder."<init>":()V
       7: ldc           #13                 // String BookieStateService.BookieState(running=
       9: invokevirtual #14                 // Method java/lang/StringBuilder.append:(Ljava/lang/String;)Ljava/lang/StringBuilder;
      12: aload_0
      13: invokevirtual #7                  // Method isRunning:()Z
      16: invokevirtual #15                 // Method java/lang/StringBuilder.append:(Z)Ljava/lang/StringBuilder;
      19: ldc           #16                 // String , readOnly=
      21: invokevirtual #14                 // Method java/lang/StringBuilder.append:(Ljava/lang/String;)Ljava/lang/StringBuilder;
      24: aload_0
      25: invokevirtual #8                  // Method isReadOnly:()Z
      28: invokevirtual #15                 // Method java/lang/StringBuilder.append:(Z)Ljava/lang/StringBuilder;
      31: ldc           #17                 // String , shuttingDown=
      33: invokevirtual #14                 // Method java/lang/StringBuilder.append:(Ljava/lang/String;)Ljava/lang/StringBuilder;
      36: aload_0
      37: invokevirtual #9                  // Method isShuttingDown:()Z
      40: invokevirtual #15                 // Method java/lang/StringBuilder.append:(Z)Ljava/lang/StringBuilder;
      43: ldc           #18                 // String , availableForHighPriorityWrites=
      45: invokevirtual #14                 // Method java/lang/StringBuilder.append:(Ljava/lang/String;)Ljava/lang/StringBuilder;
      48: aload_0
      49: invokevirtual #10                 // Method isAvailableForHighPriorityWrites:()Z
      52: invokevirtual #15                 // Method java/lang/StringBuilder.append:(Z)Ljava/lang/StringBuilder;
      55: ldc           #19                 // String )
      57: invokevirtual #14                 // Method java/lang/StringBuilder.append:(Ljava/lang/String;)Ljava/lang/StringBuilder;
      60: invokevirtual #20                 // Method java/lang/StringBuilder.toString:()Ljava/lang/String;
      63: areturn

  public org.apache.bookkeeper.server.http.service.BookieStateService$BookieState();
    Code:
       0: aload_0
       1: invokespecial #21                 // Method java/lang/Object."<init>":()V
       4: return

  static boolean access$002(org.apache.bookkeeper.server.http.service.BookieStateService$BookieState, boolean);
    Code:
       0: aload_0
       1: iload_1
       2: dup_x1
       3: putfield      #4                  // Field running:Z
       6: ireturn

  static boolean access$102(org.apache.bookkeeper.server.http.service.BookieStateService$BookieState, boolean);
    Code:
       0: aload_0
       1: iload_1
       2: dup_x1
       3: putfield      #3                  // Field readOnly:Z
       6: ireturn

  static boolean access$202(org.apache.bookkeeper.server.http.service.BookieStateService$BookieState, boolean);
    Code:
       0: aload_0
       1: iload_1
       2: dup_x1
       3: putfield      #2                  // Field shuttingDown:Z
       6: ireturn

  static boolean access$302(org.apache.bookkeeper.server.http.service.BookieStateService$BookieState, boolean);
    Code:
       0: aload_0
       1: iload_1
       2: dup_x1
       3: putfield      #1                  // Field availableForHighPriorityWrites:Z
       6: ireturn
}
