Compiled from "CountingOutputStream.java"
public class io.dekorate.deps.commons.compress.utils.CountingOutputStream extends java.io.FilterOutputStream {
  private long bytesWritten;

  public io.dekorate.deps.commons.compress.utils.CountingOutputStream(java.io.OutputStream);
    Code:
       0: aload_0
       1: aload_1
       2: invokespecial #11                 // Method java/io/FilterOutputStream."<init>":(Ljava/io/OutputStream;)V
       5: aload_0
       6: lconst_0
       7: putfield      #13                 // Field bytesWritten:J
      10: return

  public void write(int) throws java.io.IOException;
    Code:
       0: aload_0
       1: getfield      #23                 // Field out:Ljava/io/OutputStream;
       4: iload_1
       5: invokevirtual #27                 // Method java/io/OutputStream.write:(I)V
       8: aload_0
       9: lconst_1
      10: invokevirtual #31                 // Method count:(J)V
      13: return

  public void write(byte[]) throws java.io.IOException;
    Code:
       0: aload_0
       1: aload_1
       2: iconst_0
       3: aload_1
       4: arraylength
       5: invokevirtual #37                 // Method write:([BII)V
       8: return

  public void write(byte[], int, int) throws java.io.IOException;
    Code:
       0: aload_0
       1: getfield      #23                 // Field out:Ljava/io/OutputStream;
       4: aload_1
       5: iload_2
       6: iload_3
       7: invokevirtual #39                 // Method java/io/OutputStream.write:([BII)V
      10: aload_0
      11: iload_3
      12: i2l
      13: invokevirtual #31                 // Method count:(J)V
      16: return

  protected void count(long);
    Code:
       0: lload_1
       1: ldc2_w        #42                 // long -1l
       4: lcmp
       5: ifeq          18
       8: aload_0
       9: dup
      10: getfield      #13                 // Field bytesWritten:J
      13: lload_1
      14: ladd
      15: putfield      #13                 // Field bytesWritten:J
      18: return

  public long getBytesWritten();
    Code:
       0: aload_0
       1: getfield      #13                 // Field bytesWritten:J
       4: lreturn
}
