Compiled from "DefaultToStringStyler.java"
public class org.springframework.core.style.DefaultToStringStyler implements org.springframework.core.style.ToStringStyler {
  private final org.springframework.core.style.ValueStyler valueStyler;

  public org.springframework.core.style.DefaultToStringStyler(org.springframework.core.style.ValueStyler);
    Code:
       0: aload_0
       1: invokespecial #1                  // Method java/lang/Object."<init>":()V
       4: aload_1
       5: ldc           #2                  // String ValueStyler must not be null
       7: invokestatic  #3                  // Method org/springframework/util/Assert.notNull:(Ljava/lang/Object;Ljava/lang/String;)V
      10: aload_0
      11: aload_1
      12: putfield      #4                  // Field valueStyler:Lorg/springframework/core/style/ValueStyler;
      15: return

  protected final org.springframework.core.style.ValueStyler getValueStyler();
    Code:
       0: aload_0
       1: getfield      #4                  // Field valueStyler:Lorg/springframework/core/style/ValueStyler;
       4: areturn

  public void styleStart(java.lang.StringBuilder, java.lang.Object);
    Code:
       0: aload_2
       1: invokevirtual #5                  // Method java/lang/Object.getClass:()Ljava/lang/Class;
       4: invokevirtual #6                  // Method java/lang/Class.isArray:()Z
       7: ifne          36
      10: aload_1
      11: bipush        91
      13: invokevirtual #7                  // Method java/lang/StringBuilder.append:(C)Ljava/lang/StringBuilder;
      16: aload_2
      17: invokevirtual #5                  // Method java/lang/Object.getClass:()Ljava/lang/Class;
      20: invokestatic  #8                  // Method org/springframework/util/ClassUtils.getShortName:(Ljava/lang/Class;)Ljava/lang/String;
      23: invokevirtual #9                  // Method java/lang/StringBuilder.append:(Ljava/lang/String;)Ljava/lang/StringBuilder;
      26: pop
      27: aload_0
      28: aload_1
      29: aload_2
      30: invokespecial #10                 // Method styleIdentityHashCode:(Ljava/lang/StringBuilder;Ljava/lang/Object;)V
      33: goto          62
      36: aload_1
      37: bipush        91
      39: invokevirtual #7                  // Method java/lang/StringBuilder.append:(C)Ljava/lang/StringBuilder;
      42: pop
      43: aload_0
      44: aload_1
      45: aload_2
      46: invokespecial #10                 // Method styleIdentityHashCode:(Ljava/lang/StringBuilder;Ljava/lang/Object;)V
      49: aload_1
      50: bipush        32
      52: invokevirtual #7                  // Method java/lang/StringBuilder.append:(C)Ljava/lang/StringBuilder;
      55: pop
      56: aload_0
      57: aload_1
      58: aload_2
      59: invokevirtual #11                 // Method styleValue:(Ljava/lang/StringBuilder;Ljava/lang/Object;)V
      62: return

  private void styleIdentityHashCode(java.lang.StringBuilder, java.lang.Object);
    Code:
       0: aload_1
       1: bipush        64
       3: invokevirtual #7                  // Method java/lang/StringBuilder.append:(C)Ljava/lang/StringBuilder;
       6: pop
       7: aload_1
       8: aload_2
       9: invokestatic  #12                 // Method org/springframework/util/ObjectUtils.getIdentityHexString:(Ljava/lang/Object;)Ljava/lang/String;
      12: invokevirtual #9                  // Method java/lang/StringBuilder.append:(Ljava/lang/String;)Ljava/lang/StringBuilder;
      15: pop
      16: return

  public void styleEnd(java.lang.StringBuilder, java.lang.Object);
    Code:
       0: aload_1
       1: bipush        93
       3: invokevirtual #7                  // Method java/lang/StringBuilder.append:(C)Ljava/lang/StringBuilder;
       6: pop
       7: return

  public void styleField(java.lang.StringBuilder, java.lang.String, java.lang.Object);
    Code:
       0: aload_0
       1: aload_1
       2: aload_2
       3: invokevirtual #13                 // Method styleFieldStart:(Ljava/lang/StringBuilder;Ljava/lang/String;)V
       6: aload_0
       7: aload_1
       8: aload_3
       9: invokevirtual #11                 // Method styleValue:(Ljava/lang/StringBuilder;Ljava/lang/Object;)V
      12: aload_0
      13: aload_1
      14: aload_2
      15: invokevirtual #14                 // Method styleFieldEnd:(Ljava/lang/StringBuilder;Ljava/lang/String;)V
      18: return

  protected void styleFieldStart(java.lang.StringBuilder, java.lang.String);
    Code:
       0: aload_1
       1: bipush        32
       3: invokevirtual #7                  // Method java/lang/StringBuilder.append:(C)Ljava/lang/StringBuilder;
       6: aload_2
       7: invokevirtual #9                  // Method java/lang/StringBuilder.append:(Ljava/lang/String;)Ljava/lang/StringBuilder;
      10: ldc           #15                 // String  =
      12: invokevirtual #9                  // Method java/lang/StringBuilder.append:(Ljava/lang/String;)Ljava/lang/StringBuilder;
      15: pop
      16: return

  protected void styleFieldEnd(java.lang.StringBuilder, java.lang.String);
    Code:
       0: return

  public void styleValue(java.lang.StringBuilder, java.lang.Object);
    Code:
       0: aload_1
       1: aload_0
       2: getfield      #4                  // Field valueStyler:Lorg/springframework/core/style/ValueStyler;
       5: aload_2
       6: invokeinterface #16,  2           // InterfaceMethod org/springframework/core/style/ValueStyler.style:(Ljava/lang/Object;)Ljava/lang/String;
      11: invokevirtual #9                  // Method java/lang/StringBuilder.append:(Ljava/lang/String;)Ljava/lang/StringBuilder;
      14: pop
      15: return

  public void styleFieldSeparator(java.lang.StringBuilder);
    Code:
       0: aload_1
       1: bipush        44
       3: invokevirtual #7                  // Method java/lang/StringBuilder.append:(C)Ljava/lang/StringBuilder;
       6: pop
       7: return
}
