Compiled from "AndroidLog.kt"
public final class okhttp3.internal.platform.android.AndroidLogHandler extends java.util.logging.Handler {
  public static final okhttp3.internal.platform.android.AndroidLogHandler INSTANCE;

  public void publish(java.util.logging.LogRecord);
    Code:
       0: aload_1
       1: ldc           #9                  // String record
       3: invokestatic  #15                 // Method kotlin/jvm/internal/Intrinsics.checkNotNullParameter:(Ljava/lang/Object;Ljava/lang/String;)V
       6: getstatic     #21                 // Field okhttp3/internal/platform/android/AndroidLog.INSTANCE:Lokhttp3/internal/platform/android/AndroidLog;
       9: aload_1
      10: invokevirtual #27                 // Method java/util/logging/LogRecord.getLoggerName:()Ljava/lang/String;
      13: dup
      14: ldc           #29                 // String record.loggerName
      16: invokestatic  #32                 // Method kotlin/jvm/internal/Intrinsics.checkNotNullExpressionValue:(Ljava/lang/Object;Ljava/lang/String;)V
      19: aload_1
      20: invokestatic  #38                 // Method okhttp3/internal/platform/android/AndroidLogKt.access$getAndroidLevel$p:(Ljava/util/logging/LogRecord;)I
      23: aload_1
      24: invokevirtual #41                 // Method java/util/logging/LogRecord.getMessage:()Ljava/lang/String;
      27: dup
      28: ldc           #43                 // String record.message
      30: invokestatic  #32                 // Method kotlin/jvm/internal/Intrinsics.checkNotNullExpressionValue:(Ljava/lang/Object;Ljava/lang/String;)V
      33: aload_1
      34: invokevirtual #47                 // Method java/util/logging/LogRecord.getThrown:()Ljava/lang/Throwable;
      37: invokevirtual #51                 // Method okhttp3/internal/platform/android/AndroidLog.androidLog$okhttp:(Ljava/lang/String;ILjava/lang/String;Ljava/lang/Throwable;)V
      40: return

  public void flush();
    Code:
       0: return

  public void close();
    Code:
       0: return

  private okhttp3.internal.platform.android.AndroidLogHandler();
    Code:
       0: aload_0
       1: invokespecial #60                 // Method java/util/logging/Handler."<init>":()V
       4: return

  static {};
    Code:
       0: new           #2                  // class okhttp3/internal/platform/android/AndroidLogHandler
       3: dup
       4: invokespecial #76                 // Method "<init>":()V
       7: astore_0
       8: aload_0
       9: putstatic     #78                 // Field INSTANCE:Lokhttp3/internal/platform/android/AndroidLogHandler;
      12: return
}
