Compiled from "HandlerMethodArgumentResolversHolder.java"
public class org.springframework.integration.handler.support.HandlerMethodArgumentResolversHolder {
  private final java.util.List<org.springframework.messaging.handler.invocation.HandlerMethodArgumentResolver> resolvers;

  public org.springframework.integration.handler.support.HandlerMethodArgumentResolversHolder(java.util.List<org.springframework.messaging.handler.invocation.HandlerMethodArgumentResolver>);
    Code:
       0: aload_0
       1: invokespecial #1                  // Method java/lang/Object."<init>":()V
       4: aload_0
       5: new           #2                  // class java/util/ArrayList
       8: dup
       9: aload_1
      10: invokespecial #3                  // Method java/util/ArrayList."<init>":(Ljava/util/Collection;)V
      13: putfield      #4                  // Field resolvers:Ljava/util/List;
      16: return

  public java.util.List<org.springframework.messaging.handler.invocation.HandlerMethodArgumentResolver> getResolvers();
    Code:
       0: aload_0
       1: getfield      #4                  // Field resolvers:Ljava/util/List;
       4: invokestatic  #5                  // Method java/util/Collections.unmodifiableList:(Ljava/util/List;)Ljava/util/List;
       7: areturn

  public void addResolver(org.springframework.messaging.handler.invocation.HandlerMethodArgumentResolver);
    Code:
       0: aload_0
       1: getfield      #4                  // Field resolvers:Ljava/util/List;
       4: aload_1
       5: invokeinterface #6,  2            // InterfaceMethod java/util/List.add:(Ljava/lang/Object;)Z
      10: pop
      11: return

  public boolean removeResolver(org.springframework.messaging.handler.invocation.HandlerMethodArgumentResolver);
    Code:
       0: aload_0
       1: getfield      #4                  // Field resolvers:Ljava/util/List;
       4: aload_1
       5: invokeinterface #7,  2            // InterfaceMethod java/util/List.remove:(Ljava/lang/Object;)Z
      10: ireturn
}
