Compiled from "FastComparator.java"
public abstract class javolution.util.FastComparator<T> implements java.util.Comparator<T>, javolution.xml.XMLSerializable {
  public static final javolution.lang.Configurable<java.lang.Boolean> REHASH_SYSTEM_HASHCODE;

  private static boolean _Rehash;

  public static final javolution.util.FastComparator<java.lang.Object> DEFAULT;

  public static final javolution.util.FastComparator<java.lang.Object> DIRECT;

  public static final javolution.util.FastComparator<java.lang.Object> REHASH;

  public static final javolution.util.FastComparator<java.lang.String> STRING;

  public static final javolution.util.FastComparator<java.lang.Object> IDENTITY;

  public static final javolution.util.FastComparator<java.lang.CharSequence> LEXICAL;

  public javolution.util.FastComparator();
    Code:
       0: aload_0
       1: invokespecial #2                  // Method java/lang/Object."<init>":()V
       4: return

  private static boolean isPoorSystemHash();
    Code:
       0: bipush        64
       2: newarray       boolean
       4: astore_0
       5: iconst_0
       6: istore_1
       7: iload_1
       8: aload_0
       9: arraylength
      10: if_icmpge     37
      13: aload_0
      14: new           #3                  // class java/lang/Object
      17: dup
      18: invokespecial #2                  // Method java/lang/Object."<init>":()V
      21: invokevirtual #4                  // Method java/lang/Object.hashCode:()I
      24: aload_0
      25: arraylength
      26: iconst_1
      27: isub
      28: iand
      29: iconst_1
      30: bastore
      31: iinc          1, 1
      34: goto          7
      37: iconst_0
      38: istore_1
      39: iconst_0
      40: istore_2
      41: iload_2
      42: aload_0
      43: arraylength
      44: if_icmpge     67
      47: iload_1
      48: aload_0
      49: iload_2
      50: iinc          2, 1
      53: baload
      54: ifeq          61
      57: iconst_1
      58: goto          62
      61: iconst_0
      62: iadd
      63: istore_1
      64: goto          41
      67: iload_1
      68: aload_0
      69: arraylength
      70: iconst_2
      71: ishr
      72: if_icmpge     79
      75: iconst_1
      76: goto          80
      79: iconst_0
      80: ireturn

  public abstract int hashCodeOf(T);

  public abstract boolean areEqual(T, T);

  public abstract int compare(T, T);

  static boolean access$002(boolean);
    Code:
       0: iload_0
       1: dup
       2: putstatic     #1                  // Field _Rehash:Z
       5: ireturn

  static boolean access$000();
    Code:
       0: getstatic     #1                  // Field _Rehash:Z
       3: ireturn

  static {};
    Code:
       0: new           #5                  // class javolution/util/FastComparator$1
       3: dup
       4: new           #6                  // class java/lang/Boolean
       7: dup
       8: invokestatic  #7                  // Method isPoorSystemHash:()Z
      11: invokespecial #8                  // Method java/lang/Boolean."<init>":(Z)V
      14: invokespecial #9                  // Method javolution/util/FastComparator$1."<init>":(Ljava/lang/Object;)V
      17: putstatic     #10                 // Field REHASH_SYSTEM_HASHCODE:Ljavolution/lang/Configurable;
      20: getstatic     #10                 // Field REHASH_SYSTEM_HASHCODE:Ljavolution/lang/Configurable;
      23: invokevirtual #11                 // Method javolution/lang/Configurable.get:()Ljava/lang/Object;
      26: checkcast     #6                  // class java/lang/Boolean
      29: invokevirtual #12                 // Method java/lang/Boolean.booleanValue:()Z
      32: putstatic     #1                  // Field _Rehash:Z
      35: new           #13                 // class javolution/util/FastComparator$Default
      38: dup
      39: aconst_null
      40: invokespecial #14                 // Method javolution/util/FastComparator$Default."<init>":(Ljavolution/util/FastComparator$1;)V
      43: putstatic     #15                 // Field DEFAULT:Ljavolution/util/FastComparator;
      46: new           #16                 // class javolution/util/FastComparator$Direct
      49: dup
      50: aconst_null
      51: invokespecial #17                 // Method javolution/util/FastComparator$Direct."<init>":(Ljavolution/util/FastComparator$1;)V
      54: putstatic     #18                 // Field DIRECT:Ljavolution/util/FastComparator;
      57: new           #19                 // class javolution/util/FastComparator$Rehash
      60: dup
      61: aconst_null
      62: invokespecial #20                 // Method javolution/util/FastComparator$Rehash."<init>":(Ljavolution/util/FastComparator$1;)V
      65: putstatic     #21                 // Field REHASH:Ljavolution/util/FastComparator;
      68: new           #22                 // class javolution/util/FastComparator$StringComparator
      71: dup
      72: aconst_null
      73: invokespecial #23                 // Method javolution/util/FastComparator$StringComparator."<init>":(Ljavolution/util/FastComparator$1;)V
      76: putstatic     #24                 // Field STRING:Ljavolution/util/FastComparator;
      79: new           #25                 // class javolution/util/FastComparator$Identity
      82: dup
      83: aconst_null
      84: invokespecial #26                 // Method javolution/util/FastComparator$Identity."<init>":(Ljavolution/util/FastComparator$1;)V
      87: putstatic     #27                 // Field IDENTITY:Ljavolution/util/FastComparator;
      90: new           #28                 // class javolution/util/FastComparator$Lexical
      93: dup
      94: aconst_null
      95: invokespecial #29                 // Method javolution/util/FastComparator$Lexical."<init>":(Ljavolution/util/FastComparator$1;)V
      98: putstatic     #30                 // Field LEXICAL:Ljavolution/util/FastComparator;
     101: return
}
