Compiled from "Index.java"
final class javolution.util.Index$4 implements java.lang.Runnable {
  javolution.util.Index$4();
    Code:
       0: aload_0
       1: invokespecial #1                  // Method java/lang/Object."<init>":()V
       4: return

  public void run();
    Code:
       0: invokestatic  #2                  // Method javolution/util/Index.access$300:()I
       3: istore_1
       4: invokestatic  #2                  // Method javolution/util/Index.access$300:()I
       7: bipush        32
       9: iadd
      10: istore_2
      11: iload_1
      12: iload_2
      13: if_icmpge     78
      16: new           #3                  // class javolution/util/Index
      19: dup
      20: iload_1
      21: ineg
      22: aconst_null
      23: invokespecial #4                  // Method javolution/util/Index."<init>":(ILjavolution/util/Index$1;)V
      26: astore_3
      27: invokestatic  #5                  // Method javolution/util/Index.access$400:()[Ljavolution/util/Index;
      30: arraylength
      31: iload_1
      32: if_icmpgt     66
      35: invokestatic  #5                  // Method javolution/util/Index.access$400:()[Ljavolution/util/Index;
      38: arraylength
      39: iconst_2
      40: imul
      41: anewarray     #3                  // class javolution/util/Index
      44: astore        4
      46: invokestatic  #5                  // Method javolution/util/Index.access$400:()[Ljavolution/util/Index;
      49: iconst_0
      50: aload         4
      52: iconst_0
      53: invokestatic  #5                  // Method javolution/util/Index.access$400:()[Ljavolution/util/Index;
      56: arraylength
      57: invokestatic  #6                  // Method java/lang/System.arraycopy:(Ljava/lang/Object;ILjava/lang/Object;II)V
      60: aload         4
      62: invokestatic  #7                  // Method javolution/util/Index.access$402:([Ljavolution/util/Index;)[Ljavolution/util/Index;
      65: pop
      66: invokestatic  #5                  // Method javolution/util/Index.access$400:()[Ljavolution/util/Index;
      69: iload_1
      70: aload_3
      71: aastore
      72: iinc          1, 1
      75: goto          11
      78: bipush        32
      80: invokestatic  #8                  // Method javolution/util/Index.access$312:(I)I
      83: pop
      84: return
}
