Compiled from "ConfigurationChangeResourceDefinition.java"
class org.jboss.as.domain.management.ConfigurationChangeResourceDefinition$ConfigurationChangeResourceAddHandler extends org.jboss.as.controller.AbstractAddStepHandler {
  public org.jboss.as.domain.management.ConfigurationChangeResourceDefinition$ConfigurationChangeResourceAddHandler();
    Code:
       0: aload_0
       1: iconst_1
       2: anewarray     #1                  // class org/jboss/as/controller/AttributeDefinition
       5: dup
       6: iconst_0
       7: getstatic     #2                  // Field org/jboss/as/domain/management/ConfigurationChangeResourceDefinition.MAX_HISTORY:Lorg/jboss/as/controller/SimpleAttributeDefinition;
      10: aastore
      11: invokespecial #3                  // Method org/jboss/as/controller/AbstractAddStepHandler."<init>":([Lorg/jboss/as/controller/AttributeDefinition;)V
      14: return

  protected void populateModel(org.jboss.as.controller.OperationContext, org.jboss.dmr.ModelNode, org.jboss.as.controller.registry.Resource) throws org.jboss.as.controller.OperationFailedException;
    Code:
       0: aload_0
       1: aload_1
       2: aload_2
       3: aload_3
       4: invokespecial #4                  // Method org/jboss/as/controller/AbstractAddStepHandler.populateModel:(Lorg/jboss/as/controller/OperationContext;Lorg/jboss/dmr/ModelNode;Lorg/jboss/as/controller/registry/Resource;)V
       7: getstatic     #2                  // Field org/jboss/as/domain/management/ConfigurationChangeResourceDefinition.MAX_HISTORY:Lorg/jboss/as/controller/SimpleAttributeDefinition;
      10: aload_1
      11: aload_2
      12: invokevirtual #5                  // Method org/jboss/as/controller/SimpleAttributeDefinition.resolveModelAttribute:(Lorg/jboss/as/controller/OperationContext;Lorg/jboss/dmr/ModelNode;)Lorg/jboss/dmr/ModelNode;
      15: astore        4
      17: getstatic     #2                  // Field org/jboss/as/domain/management/ConfigurationChangeResourceDefinition.MAX_HISTORY:Lorg/jboss/as/controller/SimpleAttributeDefinition;
      20: aload_2
      21: aload_1
      22: getstatic     #6                  // Field org/jboss/as/controller/PathAddress.EMPTY_ADDRESS:Lorg/jboss/as/controller/PathAddress;
      25: invokeinterface #7,  2            // InterfaceMethod org/jboss/as/controller/OperationContext.readResourceForUpdate:(Lorg/jboss/as/controller/PathAddress;)Lorg/jboss/as/controller/registry/Resource;
      30: invokeinterface #8,  1            // InterfaceMethod org/jboss/as/controller/registry/Resource.getModel:()Lorg/jboss/dmr/ModelNode;
      35: invokevirtual #9                  // Method org/jboss/as/controller/SimpleAttributeDefinition.validateAndSet:(Lorg/jboss/dmr/ModelNode;Lorg/jboss/dmr/ModelNode;)V
      38: getstatic     #10                 // Field org/jboss/as/controller/ConfigurationChangesCollector.INSTANCE:Lorg/jboss/as/controller/ConfigurationChangesCollector$ConfigurationChangesCollectorImpl;
      41: aload         4
      43: invokevirtual #11                 // Method org/jboss/dmr/ModelNode.asInt:()I
      46: invokevirtual #12                 // Method org/jboss/as/controller/ConfigurationChangesCollector$ConfigurationChangesCollectorImpl.setMaxHistory:(I)V
      49: return
}
