Compiled from "ApplicationSessionCookieConfig.java"
public class org.apache.catalina.core.ApplicationSessionCookieConfig implements javax.servlet.SessionCookieConfig {
  private static final org.apache.tomcat.util.res.StringManager sm;

  private boolean httpOnly;

  private boolean secure;

  private int maxAge;

  private java.lang.String comment;

  private java.lang.String domain;

  private java.lang.String name;

  private java.lang.String path;

  private org.apache.catalina.core.StandardContext context;

  public org.apache.catalina.core.ApplicationSessionCookieConfig(org.apache.catalina.core.StandardContext);
    Code:
       0: aload_0
       1: invokespecial #1                  // Method java/lang/Object."<init>":()V
       4: aload_0
       5: iconst_m1
       6: putfield      #2                  // Field maxAge:I
       9: aload_0
      10: aload_1
      11: putfield      #3                  // Field context:Lorg/apache/catalina/core/StandardContext;
      14: return

  public java.lang.String getComment();
    Code:
       0: aload_0
       1: getfield      #4                  // Field comment:Ljava/lang/String;
       4: areturn

  public java.lang.String getDomain();
    Code:
       0: aload_0
       1: getfield      #5                  // Field domain:Ljava/lang/String;
       4: areturn

  public int getMaxAge();
    Code:
       0: aload_0
       1: getfield      #2                  // Field maxAge:I
       4: ireturn

  public java.lang.String getName();
    Code:
       0: aload_0
       1: getfield      #6                  // Field name:Ljava/lang/String;
       4: areturn

  public java.lang.String getPath();
    Code:
       0: aload_0
       1: getfield      #7                  // Field path:Ljava/lang/String;
       4: areturn

  public boolean isHttpOnly();
    Code:
       0: aload_0
       1: getfield      #8                  // Field httpOnly:Z
       4: ireturn

  public boolean isSecure();
    Code:
       0: aload_0
       1: getfield      #9                  // Field secure:Z
       4: ireturn

  public void setComment(java.lang.String);
    Code:
       0: aload_0
       1: getfield      #3                  // Field context:Lorg/apache/catalina/core/StandardContext;
       4: invokevirtual #10                 // Method org/apache/catalina/core/StandardContext.getState:()Lorg/apache/catalina/LifecycleState;
       7: getstatic     #11                 // Field org/apache/catalina/LifecycleState.STARTING_PREP:Lorg/apache/catalina/LifecycleState;
      10: invokevirtual #12                 // Method org/apache/catalina/LifecycleState.equals:(Ljava/lang/Object;)Z
      13: ifne          51
      16: new           #13                 // class java/lang/IllegalStateException
      19: dup
      20: getstatic     #14                 // Field sm:Lorg/apache/tomcat/util/res/StringManager;
      23: ldc           #15                 // String applicationSessionCookieConfig.ise
      25: iconst_2
      26: anewarray     #16                 // class java/lang/Object
      29: dup
      30: iconst_0
      31: ldc           #17                 // String comment
      33: aastore
      34: dup
      35: iconst_1
      36: aload_0
      37: getfield      #3                  // Field context:Lorg/apache/catalina/core/StandardContext;
      40: invokevirtual #18                 // Method org/apache/catalina/core/StandardContext.getPath:()Ljava/lang/String;
      43: aastore
      44: invokevirtual #19                 // Method org/apache/tomcat/util/res/StringManager.getString:(Ljava/lang/String;[Ljava/lang/Object;)Ljava/lang/String;
      47: invokespecial #20                 // Method java/lang/IllegalStateException."<init>":(Ljava/lang/String;)V
      50: athrow
      51: aload_0
      52: aload_1
      53: putfield      #4                  // Field comment:Ljava/lang/String;
      56: return

  public void setDomain(java.lang.String);
    Code:
       0: aload_0
       1: getfield      #3                  // Field context:Lorg/apache/catalina/core/StandardContext;
       4: invokevirtual #10                 // Method org/apache/catalina/core/StandardContext.getState:()Lorg/apache/catalina/LifecycleState;
       7: getstatic     #11                 // Field org/apache/catalina/LifecycleState.STARTING_PREP:Lorg/apache/catalina/LifecycleState;
      10: invokevirtual #12                 // Method org/apache/catalina/LifecycleState.equals:(Ljava/lang/Object;)Z
      13: ifne          51
      16: new           #13                 // class java/lang/IllegalStateException
      19: dup
      20: getstatic     #14                 // Field sm:Lorg/apache/tomcat/util/res/StringManager;
      23: ldc           #15                 // String applicationSessionCookieConfig.ise
      25: iconst_2
      26: anewarray     #16                 // class java/lang/Object
      29: dup
      30: iconst_0
      31: ldc           #21                 // String domain name
      33: aastore
      34: dup
      35: iconst_1
      36: aload_0
      37: getfield      #3                  // Field context:Lorg/apache/catalina/core/StandardContext;
      40: invokevirtual #18                 // Method org/apache/catalina/core/StandardContext.getPath:()Ljava/lang/String;
      43: aastore
      44: invokevirtual #19                 // Method org/apache/tomcat/util/res/StringManager.getString:(Ljava/lang/String;[Ljava/lang/Object;)Ljava/lang/String;
      47: invokespecial #20                 // Method java/lang/IllegalStateException."<init>":(Ljava/lang/String;)V
      50: athrow
      51: aload_0
      52: aload_1
      53: putfield      #5                  // Field domain:Ljava/lang/String;
      56: return

  public void setHttpOnly(boolean);
    Code:
       0: aload_0
       1: getfield      #3                  // Field context:Lorg/apache/catalina/core/StandardContext;
       4: invokevirtual #10                 // Method org/apache/catalina/core/StandardContext.getState:()Lorg/apache/catalina/LifecycleState;
       7: getstatic     #11                 // Field org/apache/catalina/LifecycleState.STARTING_PREP:Lorg/apache/catalina/LifecycleState;
      10: invokevirtual #12                 // Method org/apache/catalina/LifecycleState.equals:(Ljava/lang/Object;)Z
      13: ifne          51
      16: new           #13                 // class java/lang/IllegalStateException
      19: dup
      20: getstatic     #14                 // Field sm:Lorg/apache/tomcat/util/res/StringManager;
      23: ldc           #15                 // String applicationSessionCookieConfig.ise
      25: iconst_2
      26: anewarray     #16                 // class java/lang/Object
      29: dup
      30: iconst_0
      31: ldc           #22                 // String HttpOnly
      33: aastore
      34: dup
      35: iconst_1
      36: aload_0
      37: getfield      #3                  // Field context:Lorg/apache/catalina/core/StandardContext;
      40: invokevirtual #18                 // Method org/apache/catalina/core/StandardContext.getPath:()Ljava/lang/String;
      43: aastore
      44: invokevirtual #19                 // Method org/apache/tomcat/util/res/StringManager.getString:(Ljava/lang/String;[Ljava/lang/Object;)Ljava/lang/String;
      47: invokespecial #20                 // Method java/lang/IllegalStateException."<init>":(Ljava/lang/String;)V
      50: athrow
      51: aload_0
      52: iload_1
      53: putfield      #8                  // Field httpOnly:Z
      56: return

  public void setMaxAge(int);
    Code:
       0: aload_0
       1: getfield      #3                  // Field context:Lorg/apache/catalina/core/StandardContext;
       4: invokevirtual #10                 // Method org/apache/catalina/core/StandardContext.getState:()Lorg/apache/catalina/LifecycleState;
       7: getstatic     #11                 // Field org/apache/catalina/LifecycleState.STARTING_PREP:Lorg/apache/catalina/LifecycleState;
      10: invokevirtual #12                 // Method org/apache/catalina/LifecycleState.equals:(Ljava/lang/Object;)Z
      13: ifne          51
      16: new           #13                 // class java/lang/IllegalStateException
      19: dup
      20: getstatic     #14                 // Field sm:Lorg/apache/tomcat/util/res/StringManager;
      23: ldc           #15                 // String applicationSessionCookieConfig.ise
      25: iconst_2
      26: anewarray     #16                 // class java/lang/Object
      29: dup
      30: iconst_0
      31: ldc           #23                 // String max age
      33: aastore
      34: dup
      35: iconst_1
      36: aload_0
      37: getfield      #3                  // Field context:Lorg/apache/catalina/core/StandardContext;
      40: invokevirtual #18                 // Method org/apache/catalina/core/StandardContext.getPath:()Ljava/lang/String;
      43: aastore
      44: invokevirtual #19                 // Method org/apache/tomcat/util/res/StringManager.getString:(Ljava/lang/String;[Ljava/lang/Object;)Ljava/lang/String;
      47: invokespecial #20                 // Method java/lang/IllegalStateException."<init>":(Ljava/lang/String;)V
      50: athrow
      51: aload_0
      52: iload_1
      53: putfield      #2                  // Field maxAge:I
      56: return

  public void setName(java.lang.String);
    Code:
       0: aload_0
       1: getfield      #3                  // Field context:Lorg/apache/catalina/core/StandardContext;
       4: invokevirtual #10                 // Method org/apache/catalina/core/StandardContext.getState:()Lorg/apache/catalina/LifecycleState;
       7: getstatic     #11                 // Field org/apache/catalina/LifecycleState.STARTING_PREP:Lorg/apache/catalina/LifecycleState;
      10: invokevirtual #12                 // Method org/apache/catalina/LifecycleState.equals:(Ljava/lang/Object;)Z
      13: ifne          51
      16: new           #13                 // class java/lang/IllegalStateException
      19: dup
      20: getstatic     #14                 // Field sm:Lorg/apache/tomcat/util/res/StringManager;
      23: ldc           #15                 // String applicationSessionCookieConfig.ise
      25: iconst_2
      26: anewarray     #16                 // class java/lang/Object
      29: dup
      30: iconst_0
      31: ldc           #24                 // String name
      33: aastore
      34: dup
      35: iconst_1
      36: aload_0
      37: getfield      #3                  // Field context:Lorg/apache/catalina/core/StandardContext;
      40: invokevirtual #18                 // Method org/apache/catalina/core/StandardContext.getPath:()Ljava/lang/String;
      43: aastore
      44: invokevirtual #19                 // Method org/apache/tomcat/util/res/StringManager.getString:(Ljava/lang/String;[Ljava/lang/Object;)Ljava/lang/String;
      47: invokespecial #20                 // Method java/lang/IllegalStateException."<init>":(Ljava/lang/String;)V
      50: athrow
      51: aload_0
      52: aload_1
      53: putfield      #6                  // Field name:Ljava/lang/String;
      56: return

  public void setPath(java.lang.String);
    Code:
       0: aload_0
       1: getfield      #3                  // Field context:Lorg/apache/catalina/core/StandardContext;
       4: invokevirtual #10                 // Method org/apache/catalina/core/StandardContext.getState:()Lorg/apache/catalina/LifecycleState;
       7: getstatic     #11                 // Field org/apache/catalina/LifecycleState.STARTING_PREP:Lorg/apache/catalina/LifecycleState;
      10: invokevirtual #12                 // Method org/apache/catalina/LifecycleState.equals:(Ljava/lang/Object;)Z
      13: ifne          51
      16: new           #13                 // class java/lang/IllegalStateException
      19: dup
      20: getstatic     #14                 // Field sm:Lorg/apache/tomcat/util/res/StringManager;
      23: ldc           #15                 // String applicationSessionCookieConfig.ise
      25: iconst_2
      26: anewarray     #16                 // class java/lang/Object
      29: dup
      30: iconst_0
      31: ldc           #25                 // String path
      33: aastore
      34: dup
      35: iconst_1
      36: aload_0
      37: getfield      #3                  // Field context:Lorg/apache/catalina/core/StandardContext;
      40: invokevirtual #18                 // Method org/apache/catalina/core/StandardContext.getPath:()Ljava/lang/String;
      43: aastore
      44: invokevirtual #19                 // Method org/apache/tomcat/util/res/StringManager.getString:(Ljava/lang/String;[Ljava/lang/Object;)Ljava/lang/String;
      47: invokespecial #20                 // Method java/lang/IllegalStateException."<init>":(Ljava/lang/String;)V
      50: athrow
      51: aload_0
      52: aload_1
      53: putfield      #7                  // Field path:Ljava/lang/String;
      56: return

  public void setSecure(boolean);
    Code:
       0: aload_0
       1: getfield      #3                  // Field context:Lorg/apache/catalina/core/StandardContext;
       4: invokevirtual #10                 // Method org/apache/catalina/core/StandardContext.getState:()Lorg/apache/catalina/LifecycleState;
       7: getstatic     #11                 // Field org/apache/catalina/LifecycleState.STARTING_PREP:Lorg/apache/catalina/LifecycleState;
      10: invokevirtual #12                 // Method org/apache/catalina/LifecycleState.equals:(Ljava/lang/Object;)Z
      13: ifne          51
      16: new           #13                 // class java/lang/IllegalStateException
      19: dup
      20: getstatic     #14                 // Field sm:Lorg/apache/tomcat/util/res/StringManager;
      23: ldc           #15                 // String applicationSessionCookieConfig.ise
      25: iconst_2
      26: anewarray     #16                 // class java/lang/Object
      29: dup
      30: iconst_0
      31: ldc           #26                 // String secure
      33: aastore
      34: dup
      35: iconst_1
      36: aload_0
      37: getfield      #3                  // Field context:Lorg/apache/catalina/core/StandardContext;
      40: invokevirtual #18                 // Method org/apache/catalina/core/StandardContext.getPath:()Ljava/lang/String;
      43: aastore
      44: invokevirtual #19                 // Method org/apache/tomcat/util/res/StringManager.getString:(Ljava/lang/String;[Ljava/lang/Object;)Ljava/lang/String;
      47: invokespecial #20                 // Method java/lang/IllegalStateException."<init>":(Ljava/lang/String;)V
      50: athrow
      51: aload_0
      52: iload_1
      53: putfield      #9                  // Field secure:Z
      56: return

  public static javax.servlet.http.Cookie createSessionCookie(org.apache.catalina.Context, java.lang.String, boolean);
    Code:
       0: aload_0
       1: invokeinterface #27,  1           // InterfaceMethod org/apache/catalina/Context.getServletContext:()Ljavax/servlet/ServletContext;
       6: invokeinterface #28,  1           // InterfaceMethod javax/servlet/ServletContext.getSessionCookieConfig:()Ljavax/servlet/SessionCookieConfig;
      11: astore_3
      12: new           #29                 // class javax/servlet/http/Cookie
      15: dup
      16: aload_0
      17: invokestatic  #30                 // Method org/apache/catalina/util/SessionConfig.getSessionCookieName:(Lorg/apache/catalina/Context;)Ljava/lang/String;
      20: aload_1
      21: invokespecial #31                 // Method javax/servlet/http/Cookie."<init>":(Ljava/lang/String;Ljava/lang/String;)V
      24: astore        4
      26: aload         4
      28: aload_3
      29: invokeinterface #32,  1           // InterfaceMethod javax/servlet/SessionCookieConfig.getMaxAge:()I
      34: invokevirtual #33                 // Method javax/servlet/http/Cookie.setMaxAge:(I)V
      37: aload         4
      39: aload_3
      40: invokeinterface #34,  1           // InterfaceMethod javax/servlet/SessionCookieConfig.getComment:()Ljava/lang/String;
      45: invokevirtual #35                 // Method javax/servlet/http/Cookie.setComment:(Ljava/lang/String;)V
      48: aload_0
      49: invokeinterface #36,  1           // InterfaceMethod org/apache/catalina/Context.getSessionCookieDomain:()Ljava/lang/String;
      54: ifnonnull     80
      57: aload_3
      58: invokeinterface #37,  1           // InterfaceMethod javax/servlet/SessionCookieConfig.getDomain:()Ljava/lang/String;
      63: ifnull        91
      66: aload         4
      68: aload_3
      69: invokeinterface #37,  1           // InterfaceMethod javax/servlet/SessionCookieConfig.getDomain:()Ljava/lang/String;
      74: invokevirtual #38                 // Method javax/servlet/http/Cookie.setDomain:(Ljava/lang/String;)V
      77: goto          91
      80: aload         4
      82: aload_0
      83: invokeinterface #36,  1           // InterfaceMethod org/apache/catalina/Context.getSessionCookieDomain:()Ljava/lang/String;
      88: invokevirtual #38                 // Method javax/servlet/http/Cookie.setDomain:(Ljava/lang/String;)V
      91: aload_3
      92: invokeinterface #39,  1           // InterfaceMethod javax/servlet/SessionCookieConfig.isSecure:()Z
      97: ifne          104
     100: iload_2
     101: ifeq          110
     104: aload         4
     106: iconst_1
     107: invokevirtual #40                 // Method javax/servlet/http/Cookie.setSecure:(Z)V
     110: aload_3
     111: invokeinterface #41,  1           // InterfaceMethod javax/servlet/SessionCookieConfig.isHttpOnly:()Z
     116: ifne          128
     119: aload_0
     120: invokeinterface #42,  1           // InterfaceMethod org/apache/catalina/Context.getUseHttpOnly:()Z
     125: ifeq          134
     128: aload         4
     130: iconst_1
     131: invokevirtual #43                 // Method javax/servlet/http/Cookie.setHttpOnly:(Z)V
     134: aload_0
     135: invokeinterface #44,  1           // InterfaceMethod org/apache/catalina/Context.getSessionCookiePath:()Ljava/lang/String;
     140: astore        5
     142: aload         5
     144: ifnull        155
     147: aload         5
     149: invokevirtual #45                 // Method java/lang/String.length:()I
     152: ifne          163
     155: aload_3
     156: invokeinterface #46,  1           // InterfaceMethod javax/servlet/SessionCookieConfig.getPath:()Ljava/lang/String;
     161: astore        5
     163: aload         5
     165: ifnull        176
     168: aload         5
     170: invokevirtual #45                 // Method java/lang/String.length:()I
     173: ifne          184
     176: aload_0
     177: invokeinterface #47,  1           // InterfaceMethod org/apache/catalina/Context.getEncodedPath:()Ljava/lang/String;
     182: astore        5
     184: aload_0
     185: invokeinterface #48,  1           // InterfaceMethod org/apache/catalina/Context.getSessionCookiePathUsesTrailingSlash:()Z
     190: ifeq          228
     193: aload         5
     195: ldc           #49                 // String /
     197: invokevirtual #50                 // Method java/lang/String.endsWith:(Ljava/lang/String;)Z
     200: ifne          240
     203: new           #51                 // class java/lang/StringBuilder
     206: dup
     207: invokespecial #52                 // Method java/lang/StringBuilder."<init>":()V
     210: aload         5
     212: invokevirtual #53                 // Method java/lang/StringBuilder.append:(Ljava/lang/String;)Ljava/lang/StringBuilder;
     215: ldc           #49                 // String /
     217: invokevirtual #53                 // Method java/lang/StringBuilder.append:(Ljava/lang/String;)Ljava/lang/StringBuilder;
     220: invokevirtual #54                 // Method java/lang/StringBuilder.toString:()Ljava/lang/String;
     223: astore        5
     225: goto          240
     228: aload         5
     230: invokevirtual #45                 // Method java/lang/String.length:()I
     233: ifne          240
     236: ldc           #49                 // String /
     238: astore        5
     240: aload         4
     242: aload         5
     244: invokevirtual #55                 // Method javax/servlet/http/Cookie.setPath:(Ljava/lang/String;)V
     247: aload         4
     249: areturn

  static {};
    Code:
       0: ldc           #56                 // String org.apache.catalina.core
       2: invokestatic  #57                 // Method org/apache/tomcat/util/res/StringManager.getManager:(Ljava/lang/String;)Lorg/apache/tomcat/util/res/StringManager;
       5: putstatic     #14                 // Field sm:Lorg/apache/tomcat/util/res/StringManager;
       8: return
}
