Compiled from "MqttProperties.java"
public final class io.netty.handler.codec.mqtt.MqttProperties$UserProperties extends io.netty.handler.codec.mqtt.MqttProperties$MqttProperty<java.util.List<io.netty.handler.codec.mqtt.MqttProperties$StringPair>> {
  public io.netty.handler.codec.mqtt.MqttProperties$UserProperties();
    Code:
       0: aload_0
       1: getstatic     #2                  // Field io/netty/handler/codec/mqtt/MqttProperties$MqttPropertyType.USER_PROPERTY:Lio/netty/handler/codec/mqtt/MqttProperties$MqttPropertyType;
       4: invokestatic  #3                  // Method io/netty/handler/codec/mqtt/MqttProperties$MqttPropertyType.access$000:(Lio/netty/handler/codec/mqtt/MqttProperties$MqttPropertyType;)I
       7: new           #4                  // class java/util/ArrayList
      10: dup
      11: invokespecial #5                  // Method java/util/ArrayList."<init>":()V
      14: invokespecial #6                  // Method io/netty/handler/codec/mqtt/MqttProperties$MqttProperty."<init>":(ILjava/lang/Object;)V
      17: return

  public io.netty.handler.codec.mqtt.MqttProperties$UserProperties(java.util.Collection<io.netty.handler.codec.mqtt.MqttProperties$StringPair>);
    Code:
       0: aload_0
       1: invokespecial #7                  // Method "<init>":()V
       4: aload_0
       5: getfield      #8                  // Field value:Ljava/lang/Object;
       8: checkcast     #9                  // class java/util/List
      11: aload_1
      12: invokeinterface #10,  2           // InterfaceMethod java/util/List.addAll:(Ljava/util/Collection;)Z
      17: pop
      18: return

  private static io.netty.handler.codec.mqtt.MqttProperties$UserProperties fromUserPropertyCollection(java.util.Collection<io.netty.handler.codec.mqtt.MqttProperties$UserProperty>);
    Code:
       0: new           #11                 // class io/netty/handler/codec/mqtt/MqttProperties$UserProperties
       3: dup
       4: invokespecial #7                  // Method "<init>":()V
       7: astore_1
       8: aload_0
       9: invokeinterface #12,  1           // InterfaceMethod java/util/Collection.iterator:()Ljava/util/Iterator;
      14: astore_2
      15: aload_2
      16: invokeinterface #13,  1           // InterfaceMethod java/util/Iterator.hasNext:()Z
      21: ifeq          68
      24: aload_2
      25: invokeinterface #14,  1           // InterfaceMethod java/util/Iterator.next:()Ljava/lang/Object;
      30: checkcast     #15                 // class io/netty/handler/codec/mqtt/MqttProperties$UserProperty
      33: astore_3
      34: aload_1
      35: new           #16                 // class io/netty/handler/codec/mqtt/MqttProperties$StringPair
      38: dup
      39: aload_3
      40: getfield      #17                 // Field io/netty/handler/codec/mqtt/MqttProperties$UserProperty.value:Ljava/lang/Object;
      43: checkcast     #16                 // class io/netty/handler/codec/mqtt/MqttProperties$StringPair
      46: getfield      #18                 // Field io/netty/handler/codec/mqtt/MqttProperties$StringPair.key:Ljava/lang/String;
      49: aload_3
      50: getfield      #17                 // Field io/netty/handler/codec/mqtt/MqttProperties$UserProperty.value:Ljava/lang/Object;
      53: checkcast     #16                 // class io/netty/handler/codec/mqtt/MqttProperties$StringPair
      56: getfield      #19                 // Field io/netty/handler/codec/mqtt/MqttProperties$StringPair.value:Ljava/lang/String;
      59: invokespecial #20                 // Method io/netty/handler/codec/mqtt/MqttProperties$StringPair."<init>":(Ljava/lang/String;Ljava/lang/String;)V
      62: invokevirtual #21                 // Method add:(Lio/netty/handler/codec/mqtt/MqttProperties$StringPair;)V
      65: goto          15
      68: aload_1
      69: areturn

  public void add(io.netty.handler.codec.mqtt.MqttProperties$StringPair);
    Code:
       0: aload_0
       1: getfield      #8                  // Field value:Ljava/lang/Object;
       4: checkcast     #9                  // class java/util/List
       7: aload_1
       8: invokeinterface #22,  2           // InterfaceMethod java/util/List.add:(Ljava/lang/Object;)Z
      13: pop
      14: return

  public void add(java.lang.String, java.lang.String);
    Code:
       0: aload_0
       1: getfield      #8                  // Field value:Ljava/lang/Object;
       4: checkcast     #9                  // class java/util/List
       7: new           #16                 // class io/netty/handler/codec/mqtt/MqttProperties$StringPair
      10: dup
      11: aload_1
      12: aload_2
      13: invokespecial #20                 // Method io/netty/handler/codec/mqtt/MqttProperties$StringPair."<init>":(Ljava/lang/String;Ljava/lang/String;)V
      16: invokeinterface #22,  2           // InterfaceMethod java/util/List.add:(Ljava/lang/Object;)Z
      21: pop
      22: return

  public java.lang.String toString();
    Code:
       0: new           #23                 // class java/lang/StringBuilder
       3: dup
       4: ldc           #24                 // String UserProperties(
       6: invokespecial #25                 // Method java/lang/StringBuilder."<init>":(Ljava/lang/String;)V
       9: astore_1
      10: iconst_1
      11: istore_2
      12: aload_0
      13: getfield      #8                  // Field value:Ljava/lang/Object;
      16: checkcast     #9                  // class java/util/List
      19: invokeinterface #26,  1           // InterfaceMethod java/util/List.iterator:()Ljava/util/Iterator;
      24: astore_3
      25: aload_3
      26: invokeinterface #13,  1           // InterfaceMethod java/util/Iterator.hasNext:()Z
      31: ifeq          97
      34: aload_3
      35: invokeinterface #14,  1           // InterfaceMethod java/util/Iterator.next:()Ljava/lang/Object;
      40: checkcast     #16                 // class io/netty/handler/codec/mqtt/MqttProperties$StringPair
      43: astore        4
      45: iload_2
      46: ifne          56
      49: aload_1
      50: ldc           #27                 // String ,
      52: invokevirtual #28                 // Method java/lang/StringBuilder.append:(Ljava/lang/String;)Ljava/lang/StringBuilder;
      55: pop
      56: aload_1
      57: new           #23                 // class java/lang/StringBuilder
      60: dup
      61: invokespecial #29                 // Method java/lang/StringBuilder."<init>":()V
      64: aload         4
      66: getfield      #18                 // Field io/netty/handler/codec/mqtt/MqttProperties$StringPair.key:Ljava/lang/String;
      69: invokevirtual #28                 // Method java/lang/StringBuilder.append:(Ljava/lang/String;)Ljava/lang/StringBuilder;
      72: ldc           #30                 // String ->
      74: invokevirtual #28                 // Method java/lang/StringBuilder.append:(Ljava/lang/String;)Ljava/lang/StringBuilder;
      77: aload         4
      79: getfield      #19                 // Field io/netty/handler/codec/mqtt/MqttProperties$StringPair.value:Ljava/lang/String;
      82: invokevirtual #28                 // Method java/lang/StringBuilder.append:(Ljava/lang/String;)Ljava/lang/StringBuilder;
      85: invokevirtual #31                 // Method java/lang/StringBuilder.toString:()Ljava/lang/String;
      88: invokevirtual #28                 // Method java/lang/StringBuilder.append:(Ljava/lang/String;)Ljava/lang/StringBuilder;
      91: pop
      92: iconst_0
      93: istore_2
      94: goto          25
      97: aload_1
      98: ldc           #32                 // String )
     100: invokevirtual #28                 // Method java/lang/StringBuilder.append:(Ljava/lang/String;)Ljava/lang/StringBuilder;
     103: pop
     104: aload_1
     105: invokevirtual #31                 // Method java/lang/StringBuilder.toString:()Ljava/lang/String;
     108: areturn

  static io.netty.handler.codec.mqtt.MqttProperties$UserProperties access$100(java.util.Collection);
    Code:
       0: aload_0
       1: invokestatic  #1                  // Method fromUserPropertyCollection:(Ljava/util/Collection;)Lio/netty/handler/codec/mqtt/MqttProperties$UserProperties;
       4: areturn
}
