Compiled from "Style.java"
public final class tk.mybatis.mapper.code.Style extends java.lang.Enum<tk.mybatis.mapper.code.Style> {
  public static final tk.mybatis.mapper.code.Style normal;

  public static final tk.mybatis.mapper.code.Style camelhump;

  public static final tk.mybatis.mapper.code.Style uppercase;

  public static final tk.mybatis.mapper.code.Style lowercase;

  public static final tk.mybatis.mapper.code.Style camelhumpAndUppercase;

  public static final tk.mybatis.mapper.code.Style camelhumpAndLowercase;

  private static final tk.mybatis.mapper.code.Style[] $VALUES;

  public static tk.mybatis.mapper.code.Style[] values();
    Code:
       0: getstatic     #1                  // Field $VALUES:[Ltk/mybatis/mapper/code/Style;
       3: invokevirtual #2                  // Method "[Ltk/mybatis/mapper/code/Style;".clone:()Ljava/lang/Object;
       6: checkcast     #3                  // class "[Ltk/mybatis/mapper/code/Style;"
       9: areturn

  public static tk.mybatis.mapper.code.Style valueOf(java.lang.String);
    Code:
       0: ldc           #4                  // class tk/mybatis/mapper/code/Style
       2: aload_0
       3: invokestatic  #5                  // Method java/lang/Enum.valueOf:(Ljava/lang/Class;Ljava/lang/String;)Ljava/lang/Enum;
       6: checkcast     #4                  // class tk/mybatis/mapper/code/Style
       9: areturn

  private tk.mybatis.mapper.code.Style();
    Code:
       0: aload_0
       1: aload_1
       2: iload_2
       3: invokespecial #6                  // Method java/lang/Enum."<init>":(Ljava/lang/String;I)V
       6: return

  static {};
    Code:
       0: new           #4                  // class tk/mybatis/mapper/code/Style
       3: dup
       4: ldc           #7                  // String normal
       6: iconst_0
       7: invokespecial #8                  // Method "<init>":(Ljava/lang/String;I)V
      10: putstatic     #9                  // Field normal:Ltk/mybatis/mapper/code/Style;
      13: new           #4                  // class tk/mybatis/mapper/code/Style
      16: dup
      17: ldc           #10                 // String camelhump
      19: iconst_1
      20: invokespecial #8                  // Method "<init>":(Ljava/lang/String;I)V
      23: putstatic     #11                 // Field camelhump:Ltk/mybatis/mapper/code/Style;
      26: new           #4                  // class tk/mybatis/mapper/code/Style
      29: dup
      30: ldc           #12                 // String uppercase
      32: iconst_2
      33: invokespecial #8                  // Method "<init>":(Ljava/lang/String;I)V
      36: putstatic     #13                 // Field uppercase:Ltk/mybatis/mapper/code/Style;
      39: new           #4                  // class tk/mybatis/mapper/code/Style
      42: dup
      43: ldc           #14                 // String lowercase
      45: iconst_3
      46: invokespecial #8                  // Method "<init>":(Ljava/lang/String;I)V
      49: putstatic     #15                 // Field lowercase:Ltk/mybatis/mapper/code/Style;
      52: new           #4                  // class tk/mybatis/mapper/code/Style
      55: dup
      56: ldc           #16                 // String camelhumpAndUppercase
      58: iconst_4
      59: invokespecial #8                  // Method "<init>":(Ljava/lang/String;I)V
      62: putstatic     #17                 // Field camelhumpAndUppercase:Ltk/mybatis/mapper/code/Style;
      65: new           #4                  // class tk/mybatis/mapper/code/Style
      68: dup
      69: ldc           #18                 // String camelhumpAndLowercase
      71: iconst_5
      72: invokespecial #8                  // Method "<init>":(Ljava/lang/String;I)V
      75: putstatic     #19                 // Field camelhumpAndLowercase:Ltk/mybatis/mapper/code/Style;
      78: bipush        6
      80: anewarray     #4                  // class tk/mybatis/mapper/code/Style
      83: dup
      84: iconst_0
      85: getstatic     #9                  // Field normal:Ltk/mybatis/mapper/code/Style;
      88: aastore
      89: dup
      90: iconst_1
      91: getstatic     #11                 // Field camelhump:Ltk/mybatis/mapper/code/Style;
      94: aastore
      95: dup
      96: iconst_2
      97: getstatic     #13                 // Field uppercase:Ltk/mybatis/mapper/code/Style;
     100: aastore
     101: dup
     102: iconst_3
     103: getstatic     #15                 // Field lowercase:Ltk/mybatis/mapper/code/Style;
     106: aastore
     107: dup
     108: iconst_4
     109: getstatic     #17                 // Field camelhumpAndUppercase:Ltk/mybatis/mapper/code/Style;
     112: aastore
     113: dup
     114: iconst_5
     115: getstatic     #19                 // Field camelhumpAndLowercase:Ltk/mybatis/mapper/code/Style;
     118: aastore
     119: putstatic     #1                  // Field $VALUES:[Ltk/mybatis/mapper/code/Style;
     122: return
}
