Compiled from "ApiResponse.java"
public class io.kubernetes.client.openapi.ApiResponse<T> {
  private final int statusCode;

  private final java.util.Map<java.lang.String, java.util.List<java.lang.String>> headers;

  private final T data;

  public io.kubernetes.client.openapi.ApiResponse(int, java.util.Map<java.lang.String, java.util.List<java.lang.String>>);
    Code:
       0: aload_0
       1: iload_1
       2: aload_2
       3: aconst_null
       4: invokespecial #1                  // Method "<init>":(ILjava/util/Map;Ljava/lang/Object;)V
       7: return

  public io.kubernetes.client.openapi.ApiResponse(int, java.util.Map<java.lang.String, java.util.List<java.lang.String>>, T);
    Code:
       0: aload_0
       1: invokespecial #2                  // Method java/lang/Object."<init>":()V
       4: aload_0
       5: iload_1
       6: putfield      #3                  // Field statusCode:I
       9: aload_0
      10: aload_2
      11: putfield      #4                  // Field headers:Ljava/util/Map;
      14: aload_0
      15: aload_3
      16: putfield      #5                  // Field data:Ljava/lang/Object;
      19: return

  public int getStatusCode();
    Code:
       0: aload_0
       1: getfield      #3                  // Field statusCode:I
       4: ireturn

  public java.util.Map<java.lang.String, java.util.List<java.lang.String>> getHeaders();
    Code:
       0: aload_0
       1: getfield      #4                  // Field headers:Ljava/util/Map;
       4: areturn

  public T getData();
    Code:
       0: aload_0
       1: getfield      #5                  // Field data:Ljava/lang/Object;
       4: areturn
}
