Compiled from "ResourceMethodContainerFilter.java"
public class org.smallmind.web.jersey.aop.ResourceMethodContainerFilter implements javax.ws.rs.container.ContainerRequestFilter,javax.ws.rs.container.ContainerResponseFilter {
  private static final java.util.concurrent.ConcurrentHashMap<java.lang.Class<? extends javax.xml.bind.annotation.adapters.XmlAdapter>, javax.xml.bind.annotation.adapters.XmlAdapter> ADAPTER_MAP;

  javax.ws.rs.container.ResourceInfo resourceInfo;

  static {};
    Code:
       0: new           #20                 // class java/util/concurrent/ConcurrentHashMap
       3: dup
       4: invokespecial #22                 // Method java/util/concurrent/ConcurrentHashMap."<init>":()V
       7: putstatic     #25                 // Field ADAPTER_MAP:Ljava/util/concurrent/ConcurrentHashMap;
      10: return

  public org.smallmind.web.jersey.aop.ResourceMethodContainerFilter();
    Code:
       0: aload_0
       1: invokespecial #29                 // Method java/lang/Object."<init>":()V
       4: return

  public void filter(javax.ws.rs.container.ContainerRequestContext);
    Code:
       0: aload_0
       1: getfield      #35                 // Field resourceInfo:Ljavax/ws/rs/container/ResourceInfo;
       4: invokeinterface #37,  1           // InterfaceMethod javax/ws/rs/container/ResourceInfo.getResourceMethod:()Ljava/lang/reflect/Method;
       9: ldc           #43                 // class org/smallmind/web/jersey/aop/ResourceMethod
      11: invokevirtual #45                 // Method java/lang/reflect/Method.getAnnotation:(Ljava/lang/Class;)Ljava/lang/annotation/Annotation;
      14: checkcast     #43                 // class org/smallmind/web/jersey/aop/ResourceMethod
      17: dup
      18: astore_2
      19: ifnull        31
      22: aload_2
      23: invokeinterface #51,  1           // InterfaceMethod org/smallmind/web/jersey/aop/ResourceMethod.value:()Ljava/lang/Class;
      28: invokestatic  #55                 // Method org/smallmind/web/jersey/aop/EntityTranslator.storeEntityType:(Ljava/lang/Class;)V
      31: return

  public void filter(javax.ws.rs.container.ContainerRequestContext, javax.ws.rs.container.ContainerResponseContext) throws java.io.IOException;
    Code:
       0: aload_0
       1: getfield      #35                 // Field resourceInfo:Ljavax/ws/rs/container/ResourceInfo;
       4: invokeinterface #37,  1           // InterfaceMethod javax/ws/rs/container/ResourceInfo.getResourceMethod:()Ljava/lang/reflect/Method;
       9: dup
      10: astore_3
      11: ifnull        164
      14: aload_3
      15: ldc           #70                 // class javax/xml/bind/annotation/adapters/XmlJavaTypeAdapter
      17: invokevirtual #45                 // Method java/lang/reflect/Method.getAnnotation:(Ljava/lang/Class;)Ljava/lang/annotation/Annotation;
      20: checkcast     #70                 // class javax/xml/bind/annotation/adapters/XmlJavaTypeAdapter
      23: dup
      24: astore        4
      26: ifnull        164
      29: aload         4
      31: invokeinterface #72,  1           // InterfaceMethod javax/xml/bind/annotation/adapters/XmlJavaTypeAdapter.value:()Ljava/lang/Class;
      36: astore        5
      38: getstatic     #25                 // Field ADAPTER_MAP:Ljava/util/concurrent/ConcurrentHashMap;
      41: aload         5
      43: invokevirtual #73                 // Method java/util/concurrent/ConcurrentHashMap.get:(Ljava/lang/Object;)Ljava/lang/Object;
      46: checkcast     #77                 // class javax/xml/bind/annotation/adapters/XmlAdapter
      49: dup
      50: astore        6
      52: ifnonnull     124
      55: getstatic     #25                 // Field ADAPTER_MAP:Ljava/util/concurrent/ConcurrentHashMap;
      58: dup
      59: astore        7
      61: monitorenter
      62: getstatic     #25                 // Field ADAPTER_MAP:Ljava/util/concurrent/ConcurrentHashMap;
      65: aload         5
      67: invokevirtual #73                 // Method java/util/concurrent/ConcurrentHashMap.get:(Ljava/lang/Object;)Ljava/lang/Object;
      70: checkcast     #77                 // class javax/xml/bind/annotation/adapters/XmlAdapter
      73: dup
      74: astore        6
      76: ifnonnull     114
      79: getstatic     #25                 // Field ADAPTER_MAP:Ljava/util/concurrent/ConcurrentHashMap;
      82: aload         5
      84: aload         5
      86: invokevirtual #79                 // Method java/lang/Class.newInstance:()Ljava/lang/Object;
      89: checkcast     #77                 // class javax/xml/bind/annotation/adapters/XmlAdapter
      92: dup
      93: astore        6
      95: invokevirtual #85                 // Method java/util/concurrent/ConcurrentHashMap.put:(Ljava/lang/Object;Ljava/lang/Object;)Ljava/lang/Object;
      98: pop
      99: goto          114
     102: astore        8
     104: new           #68                 // class java/io/IOException
     107: dup
     108: aload         8
     110: invokespecial #89                 // Method java/io/IOException."<init>":(Ljava/lang/Throwable;)V
     113: athrow
     114: aload         7
     116: monitorexit
     117: goto          124
     120: aload         7
     122: monitorexit
     123: athrow
     124: aload_2
     125: aload         6
     127: aload_2
     128: invokeinterface #92,  1           // InterfaceMethod javax/ws/rs/container/ContainerResponseContext.getEntity:()Ljava/lang/Object;
     133: invokevirtual #97                 // Method javax/xml/bind/annotation/adapters/XmlAdapter.marshal:(Ljava/lang/Object;)Ljava/lang/Object;
     136: invokeinterface #100,  2          // InterfaceMethod javax/ws/rs/container/ContainerResponseContext.setEntity:(Ljava/lang/Object;)V
     141: goto          164
     144: astore        7
     146: new           #68                 // class java/io/IOException
     149: dup
     150: aload         7
     152: invokespecial #89                 // Method java/io/IOException."<init>":(Ljava/lang/Throwable;)V
     155: athrow
     156: astore        9
     158: invokestatic  #104                // Method org/smallmind/web/jersey/aop/EntityTranslator.clearEntity:()V
     161: aload         9
     163: athrow
     164: invokestatic  #104                // Method org/smallmind/web/jersey/aop/EntityTranslator.clearEntity:()V
     167: return
    Exception table:
       from    to  target type
          79    99   102   Class java/lang/InstantiationException
          79    99   102   Class java/lang/IllegalAccessException
          62   117   120   any
         120   123   120   any
         124   141   144   Class java/lang/Exception
           0   156   156   any
}
