Compiled from "TaskQueue.kt"
public final class okhttp3.internal.http2.Http2Connection$ReaderRunnable$headers$$inlined$synchronized$lambda$1 extends okhttp3.internal.concurrent.Task {
  final java.lang.String $name;

  final boolean $cancelable;

  final okhttp3.internal.http2.Http2Stream $newStream$inlined;

  final okhttp3.internal.http2.Http2Connection$ReaderRunnable this$0;

  final okhttp3.internal.http2.Http2Stream $stream$inlined;

  final int $streamId$inlined;

  final java.util.List $headerBlock$inlined;

  final boolean $inFinished$inlined;

  public okhttp3.internal.http2.Http2Connection$ReaderRunnable$headers$$inlined$synchronized$lambda$1(java.lang.String, boolean, java.lang.String, boolean, okhttp3.internal.http2.Http2Stream, okhttp3.internal.http2.Http2Connection$ReaderRunnable, okhttp3.internal.http2.Http2Stream, int, java.util.List, boolean);
    Code:
       0: aload_0
       1: aload_1
       2: putfield      #15                 // Field $name:Ljava/lang/String;
       5: aload_0
       6: iload_2
       7: putfield      #19                 // Field $cancelable:Z
      10: aload_0
      11: aload         5
      13: putfield      #23                 // Field $newStream$inlined:Lokhttp3/internal/http2/Http2Stream;
      16: aload_0
      17: aload         6
      19: putfield      #27                 // Field this$0:Lokhttp3/internal/http2/Http2Connection$ReaderRunnable;
      22: aload_0
      23: aload         7
      25: putfield      #30                 // Field $stream$inlined:Lokhttp3/internal/http2/Http2Stream;
      28: aload_0
      29: iload         8
      31: putfield      #34                 // Field $streamId$inlined:I
      34: aload_0
      35: aload         9
      37: putfield      #38                 // Field $headerBlock$inlined:Ljava/util/List;
      40: aload_0
      41: iload         10
      43: putfield      #41                 // Field $inFinished$inlined:Z
      46: aload_0
      47: aload_3
      48: iload         4
      50: invokespecial #44                 // Method okhttp3/internal/concurrent/Task."<init>":(Ljava/lang/String;Z)V
      53: return

  public long runOnce();
    Code:
       0: iconst_0
       1: istore_1
       2: nop
       3: aload_0
       4: getfield      #27                 // Field this$0:Lokhttp3/internal/http2/Http2Connection$ReaderRunnable;
       7: getfield      #57                 // Field okhttp3/internal/http2/Http2Connection$ReaderRunnable.this$0:Lokhttp3/internal/http2/Http2Connection;
      10: invokevirtual #63                 // Method okhttp3/internal/http2/Http2Connection.getListener$okhttp:()Lokhttp3/internal/http2/Http2Connection$Listener;
      13: aload_0
      14: getfield      #23                 // Field $newStream$inlined:Lokhttp3/internal/http2/Http2Stream;
      17: invokevirtual #69                 // Method okhttp3/internal/http2/Http2Connection$Listener.onStream:(Lokhttp3/internal/http2/Http2Stream;)V
      20: goto          89
      23: astore_2
      24: getstatic     #75                 // Field okhttp3/internal/platform/Platform.Companion:Lokhttp3/internal/platform/Platform$Companion;
      27: invokevirtual #81                 // Method okhttp3/internal/platform/Platform$Companion.get:()Lokhttp3/internal/platform/Platform;
      30: new           #83                 // class java/lang/StringBuilder
      33: dup
      34: invokespecial #86                 // Method java/lang/StringBuilder."<init>":()V
      37: ldc           #88                 // String Http2Connection.Listener failure for
      39: invokevirtual #92                 // Method java/lang/StringBuilder.append:(Ljava/lang/String;)Ljava/lang/StringBuilder;
      42: aload_0
      43: getfield      #27                 // Field this$0:Lokhttp3/internal/http2/Http2Connection$ReaderRunnable;
      46: getfield      #57                 // Field okhttp3/internal/http2/Http2Connection$ReaderRunnable.this$0:Lokhttp3/internal/http2/Http2Connection;
      49: invokevirtual #96                 // Method okhttp3/internal/http2/Http2Connection.getConnectionName$okhttp:()Ljava/lang/String;
      52: invokevirtual #92                 // Method java/lang/StringBuilder.append:(Ljava/lang/String;)Ljava/lang/StringBuilder;
      55: invokevirtual #99                 // Method java/lang/StringBuilder.toString:()Ljava/lang/String;
      58: iconst_4
      59: aload_2
      60: checkcast     #101                // class java/lang/Throwable
      63: invokevirtual #105                // Method okhttp3/internal/platform/Platform.log:(Ljava/lang/String;ILjava/lang/Throwable;)V
      66: iconst_0
      67: istore_3
      68: nop
      69: iconst_0
      70: istore        4
      72: aload_0
      73: getfield      #23                 // Field $newStream$inlined:Lokhttp3/internal/http2/Http2Stream;
      76: getstatic     #111                // Field okhttp3/internal/http2/ErrorCode.PROTOCOL_ERROR:Lokhttp3/internal/http2/ErrorCode;
      79: aload_2
      80: invokevirtual #117                // Method okhttp3/internal/http2/Http2Stream.close:(Lokhttp3/internal/http2/ErrorCode;Ljava/io/IOException;)V
      83: goto          88
      86: astore        5
      88: nop
      89: nop
      90: ldc2_w        #118                // long -1l
      93: lreturn
    Exception table:
       from    to  target type
          68    83    86   Class java/io/IOException
           2    20    23   Class java/io/IOException
}
