Compiled from "UrlEncodedFormEntity.java"
public class org.apache.hc.client5.http.entity.UrlEncodedFormEntity extends org.apache.hc.core5.http.io.entity.StringEntity {
  public org.apache.hc.client5.http.entity.UrlEncodedFormEntity(java.lang.Iterable<? extends org.apache.hc.core5.http.NameValuePair>, java.nio.charset.Charset);
    Code:
       0: aload_0
       1: aload_1
       2: aload_2
       3: ifnull        10
       6: aload_2
       7: goto          16
      10: getstatic     #1                  // Field org/apache/hc/core5/http/ContentType.APPLICATION_FORM_URLENCODED:Lorg/apache/hc/core5/http/ContentType;
      13: invokevirtual #2                  // Method org/apache/hc/core5/http/ContentType.getCharset:()Ljava/nio/charset/Charset;
      16: invokestatic  #3                  // Method org/apache/hc/core5/net/WWWFormCodec.format:(Ljava/lang/Iterable;Ljava/nio/charset/Charset;)Ljava/lang/String;
      19: aload_2
      20: ifnull        33
      23: getstatic     #1                  // Field org/apache/hc/core5/http/ContentType.APPLICATION_FORM_URLENCODED:Lorg/apache/hc/core5/http/ContentType;
      26: aload_2
      27: invokevirtual #4                  // Method org/apache/hc/core5/http/ContentType.withCharset:(Ljava/nio/charset/Charset;)Lorg/apache/hc/core5/http/ContentType;
      30: goto          36
      33: getstatic     #1                  // Field org/apache/hc/core5/http/ContentType.APPLICATION_FORM_URLENCODED:Lorg/apache/hc/core5/http/ContentType;
      36: invokespecial #5                  // Method org/apache/hc/core5/http/io/entity/StringEntity."<init>":(Ljava/lang/String;Lorg/apache/hc/core5/http/ContentType;)V
      39: return

  public org.apache.hc.client5.http.entity.UrlEncodedFormEntity(java.util.List<? extends org.apache.hc.core5.http.NameValuePair>);
    Code:
       0: aload_0
       1: aload_1
       2: aconst_null
       3: invokespecial #6                  // Method "<init>":(Ljava/lang/Iterable;Ljava/nio/charset/Charset;)V
       6: return

  public org.apache.hc.client5.http.entity.UrlEncodedFormEntity(java.lang.Iterable<? extends org.apache.hc.core5.http.NameValuePair>);
    Code:
       0: aload_0
       1: aload_1
       2: aconst_null
       3: invokespecial #6                  // Method "<init>":(Ljava/lang/Iterable;Ljava/nio/charset/Charset;)V
       6: return
}
