Compiled from "PosixFileNameComparator.java"
public class org.jboss.aesh.comparators.PosixFileNameComparator implements java.util.Comparator<java.lang.String> {
  public org.jboss.aesh.comparators.PosixFileNameComparator();
    Code:
       0: aload_0
       1: invokespecial #2                  // Method java/lang/Object."<init>":()V
       4: return

  public int compare(java.lang.String, java.lang.String);
    Code:
       0: aload_1
       1: astore_3
       2: aload_2
       3: astore        4
       5: aload_1
       6: bipush        46
       8: invokevirtual #3                  // Method java/lang/String.indexOf:(I)I
      11: ifne          20
      14: aload_1
      15: iconst_1
      16: invokevirtual #4                  // Method java/lang/String.substring:(I)Ljava/lang/String;
      19: astore_3
      20: aload_2
      21: bipush        46
      23: invokevirtual #3                  // Method java/lang/String.indexOf:(I)I
      26: ifne          36
      29: aload_2
      30: iconst_1
      31: invokevirtual #4                  // Method java/lang/String.substring:(I)Ljava/lang/String;
      34: astore        4
      36: aload_3
      37: aload         4
      39: invokevirtual #5                  // Method java/lang/String.compareTo:(Ljava/lang/String;)I
      42: ifne          51
      45: aload_2
      46: aload_1
      47: invokevirtual #5                  // Method java/lang/String.compareTo:(Ljava/lang/String;)I
      50: ireturn
      51: aload_3
      52: aload         4
      54: invokevirtual #6                  // Method java/lang/String.compareToIgnoreCase:(Ljava/lang/String;)I
      57: ifne          67
      60: aload         4
      62: aload_3
      63: invokevirtual #5                  // Method java/lang/String.compareTo:(Ljava/lang/String;)I
      66: ireturn
      67: aload_3
      68: aload         4
      70: invokevirtual #6                  // Method java/lang/String.compareToIgnoreCase:(Ljava/lang/String;)I
      73: ireturn

  public int compare(java.lang.Object, java.lang.Object);
    Code:
       0: aload_0
       1: aload_1
       2: checkcast     #7                  // class java/lang/String
       5: aload_2
       6: checkcast     #7                  // class java/lang/String
       9: invokevirtual #8                  // Method compare:(Ljava/lang/String;Ljava/lang/String;)I
      12: ireturn
}
