Compiled from "CatchProcessor.java"
class org.apache.camel.processor.CatchProcessor$1 implements org.apache.camel.AsyncCallback {
  final boolean val$handled;

  final org.apache.camel.Exchange val$exchange;

  final org.apache.camel.AsyncCallback val$callback;

  final org.apache.camel.processor.CatchProcessor this$0;

  org.apache.camel.processor.CatchProcessor$1(org.apache.camel.processor.CatchProcessor, boolean, org.apache.camel.Exchange, org.apache.camel.AsyncCallback);
    Code:
       0: aload_0
       1: aload_1
       2: putfield      #24                 // Field this$0:Lorg/apache/camel/processor/CatchProcessor;
       5: aload_0
       6: iload_2
       7: putfield      #26                 // Field val$handled:Z
      10: aload_0
      11: aload_3
      12: putfield      #28                 // Field val$exchange:Lorg/apache/camel/Exchange;
      15: aload_0
      16: aload         4
      18: putfield      #30                 // Field val$callback:Lorg/apache/camel/AsyncCallback;
      21: aload_0
      22: invokespecial #33                 // Method java/lang/Object."<init>":()V
      25: return

  public void done(boolean);
    Code:
       0: aload_0
       1: getfield      #26                 // Field val$handled:Z
       4: ifeq          35
       7: aload_0
       8: getfield      #28                 // Field val$exchange:Lorg/apache/camel/Exchange;
      11: invokeinterface #43,  1           // InterfaceMethod org/apache/camel/Exchange.getContext:()Lorg/apache/camel/CamelContext;
      16: aload_0
      17: getfield      #28                 // Field val$exchange:Lorg/apache/camel/Exchange;
      20: aload_0
      21: getfield      #24                 // Field this$0:Lorg/apache/camel/processor/CatchProcessor;
      24: getfield      #47                 // Field org/apache/camel/processor/CatchProcessor.processor:Lorg/apache/camel/AsyncProcessor;
      27: iconst_0
      28: aconst_null
      29: invokestatic  #53                 // Method org/apache/camel/util/EventHelper.notifyExchangeFailureHandled:(Lorg/apache/camel/CamelContext;Lorg/apache/camel/Exchange;Lorg/apache/camel/Processor;ZLjava/lang/String;)V
      32: goto          72
      35: aload_0
      36: getfield      #28                 // Field val$exchange:Lorg/apache/camel/Exchange;
      39: invokeinterface #57,  1           // InterfaceMethod org/apache/camel/Exchange.getException:()Ljava/lang/Exception;
      44: ifnonnull     72
      47: aload_0
      48: getfield      #28                 // Field val$exchange:Lorg/apache/camel/Exchange;
      51: aload_0
      52: getfield      #28                 // Field val$exchange:Lorg/apache/camel/Exchange;
      55: ldc           #59                 // String CamelExceptionCaught
      57: ldc           #61                 // class java/lang/Exception
      59: invokeinterface #65,  3           // InterfaceMethod org/apache/camel/Exchange.getProperty:(Ljava/lang/String;Ljava/lang/Class;)Ljava/lang/Object;
      64: checkcast     #67                 // class java/lang/Throwable
      67: invokeinterface #71,  2           // InterfaceMethod org/apache/camel/Exchange.setException:(Ljava/lang/Throwable;)V
      72: aload_0
      73: getfield      #28                 // Field val$exchange:Lorg/apache/camel/Exchange;
      76: ldc           #73                 // String CamelRedeliveryExhausted
      78: invokeinterface #77,  2           // InterfaceMethod org/apache/camel/Exchange.removeProperty:(Ljava/lang/String;)Ljava/lang/Object;
      83: pop
      84: iload_1
      85: ifne          95
      88: aload_0
      89: getfield      #28                 // Field val$exchange:Lorg/apache/camel/Exchange;
      92: invokestatic  #83                 // Method org/apache/camel/util/ExchangeHelper.prepareOutToIn:(Lorg/apache/camel/Exchange;)V
      95: aload_0
      96: getfield      #30                 // Field val$callback:Lorg/apache/camel/AsyncCallback;
      99: iload_1
     100: invokeinterface #85,  2           // InterfaceMethod org/apache/camel/AsyncCallback.done:(Z)V
     105: return
}
