Compiled from "DelayProcessorSupport.java"
class org.apache.camel.processor.DelayProcessorSupport$ProcessCall$1 implements org.apache.camel.AsyncCallback {
  final org.apache.camel.processor.DelayProcessorSupport$ProcessCall this$1;

  org.apache.camel.processor.DelayProcessorSupport$ProcessCall$1(org.apache.camel.processor.DelayProcessorSupport$ProcessCall);
    Code:
       0: aload_0
       1: aload_1
       2: putfield      #21                 // Field this$1:Lorg/apache/camel/processor/DelayProcessorSupport$ProcessCall;
       5: aload_0
       6: invokespecial #23                 // Method java/lang/Object."<init>":()V
       9: return

  public void done(boolean);
    Code:
       0: aload_0
       1: getfield      #21                 // Field this$1:Lorg/apache/camel/processor/DelayProcessorSupport$ProcessCall;
       4: getfield      #31                 // Field org/apache/camel/processor/DelayProcessorSupport$ProcessCall.this$0:Lorg/apache/camel/processor/DelayProcessorSupport;
       7: getfield      #35                 // Field org/apache/camel/processor/DelayProcessorSupport.log:Lorg/slf4j/Logger;
      10: ldc           #37                 // String Delayed task done for exchangeId: {}
      12: aload_0
      13: getfield      #21                 // Field this$1:Lorg/apache/camel/processor/DelayProcessorSupport$ProcessCall;
      16: invokestatic  #41                 // Method org/apache/camel/processor/DelayProcessorSupport$ProcessCall.access$100:(Lorg/apache/camel/processor/DelayProcessorSupport$ProcessCall;)Lorg/apache/camel/Exchange;
      19: invokeinterface #47,  1           // InterfaceMethod org/apache/camel/Exchange.getExchangeId:()Ljava/lang/String;
      24: invokeinterface #53,  3           // InterfaceMethod org/slf4j/Logger.trace:(Ljava/lang/String;Ljava/lang/Object;)V
      29: aload_0
      30: getfield      #21                 // Field this$1:Lorg/apache/camel/processor/DelayProcessorSupport$ProcessCall;
      33: invokestatic  #57                 // Method org/apache/camel/processor/DelayProcessorSupport$ProcessCall.access$200:(Lorg/apache/camel/processor/DelayProcessorSupport$ProcessCall;)Lorg/apache/camel/AsyncCallback;
      36: iconst_0
      37: invokeinterface #59,  2           // InterfaceMethod org/apache/camel/AsyncCallback.done:(Z)V
      42: return
}
