Compiled from "Throttler.java"
final class org.apache.camel.processor.Throttler$State extends java.lang.Enum<org.apache.camel.processor.Throttler$State> {
  public static final org.apache.camel.processor.Throttler$State SYNC;

  public static final org.apache.camel.processor.Throttler$State ASYNC;

  public static final org.apache.camel.processor.Throttler$State ASYNC_REJECTED;

  private static final org.apache.camel.processor.Throttler$State[] $VALUES;

  public static org.apache.camel.processor.Throttler$State[] values();
    Code:
       0: getstatic     #19                 // Field $VALUES:[Lorg/apache/camel/processor/Throttler$State;
       3: invokevirtual #24                 // Method "[Lorg/apache/camel/processor/Throttler$State;".clone:()Ljava/lang/Object;
       6: checkcast     #20                 // class "[Lorg/apache/camel/processor/Throttler$State;"
       9: areturn

  public static org.apache.camel.processor.Throttler$State valueOf(java.lang.String);
    Code:
       0: ldc           #2                  // class org/apache/camel/processor/Throttler$State
       2: aload_0
       3: invokestatic  #29                 // Method java/lang/Enum.valueOf:(Ljava/lang/Class;Ljava/lang/String;)Ljava/lang/Enum;
       6: checkcast     #2                  // class org/apache/camel/processor/Throttler$State
       9: areturn

  private org.apache.camel.processor.Throttler$State();
    Code:
       0: aload_0
       1: aload_1
       2: iload_2
       3: invokespecial #35                 // Method java/lang/Enum."<init>":(Ljava/lang/String;I)V
       6: return

  static {};
    Code:
       0: new           #2                  // class org/apache/camel/processor/Throttler$State
       3: dup
       4: ldc           #39                 // String SYNC
       6: iconst_0
       7: invokespecial #40                 // Method "<init>":(Ljava/lang/String;I)V
      10: putstatic     #42                 // Field SYNC:Lorg/apache/camel/processor/Throttler$State;
      13: new           #2                  // class org/apache/camel/processor/Throttler$State
      16: dup
      17: ldc           #43                 // String ASYNC
      19: iconst_1
      20: invokespecial #40                 // Method "<init>":(Ljava/lang/String;I)V
      23: putstatic     #45                 // Field ASYNC:Lorg/apache/camel/processor/Throttler$State;
      26: new           #2                  // class org/apache/camel/processor/Throttler$State
      29: dup
      30: ldc           #46                 // String ASYNC_REJECTED
      32: iconst_2
      33: invokespecial #40                 // Method "<init>":(Ljava/lang/String;I)V
      36: putstatic     #48                 // Field ASYNC_REJECTED:Lorg/apache/camel/processor/Throttler$State;
      39: iconst_3
      40: anewarray     #2                  // class org/apache/camel/processor/Throttler$State
      43: dup
      44: iconst_0
      45: getstatic     #42                 // Field SYNC:Lorg/apache/camel/processor/Throttler$State;
      48: aastore
      49: dup
      50: iconst_1
      51: getstatic     #45                 // Field ASYNC:Lorg/apache/camel/processor/Throttler$State;
      54: aastore
      55: dup
      56: iconst_2
      57: getstatic     #48                 // Field ASYNC_REJECTED:Lorg/apache/camel/processor/Throttler$State;
      60: aastore
      61: putstatic     #19                 // Field $VALUES:[Lorg/apache/camel/processor/Throttler$State;
      64: return
}
