Compiled from "EmbeddedDataSourceConfiguration.java"
public class org.springframework.boot.autoconfigure.jdbc.EmbeddedDataSourceConfiguration implements org.springframework.beans.factory.BeanClassLoaderAware {
  private org.springframework.jdbc.datasource.embedded.EmbeddedDatabase database;

  private java.lang.ClassLoader classLoader;

  private final org.springframework.boot.autoconfigure.jdbc.DataSourceProperties properties;

  public org.springframework.boot.autoconfigure.jdbc.EmbeddedDataSourceConfiguration(org.springframework.boot.autoconfigure.jdbc.DataSourceProperties);
    Code:
       0: aload_0
       1: invokespecial #1                  // Method java/lang/Object."<init>":()V
       4: aload_0
       5: aload_1
       6: putfield      #2                  // Field properties:Lorg/springframework/boot/autoconfigure/jdbc/DataSourceProperties;
       9: return

  public void setBeanClassLoader(java.lang.ClassLoader);
    Code:
       0: aload_0
       1: aload_1
       2: putfield      #3                  // Field classLoader:Ljava/lang/ClassLoader;
       5: return

  public org.springframework.jdbc.datasource.embedded.EmbeddedDatabase dataSource();
    Code:
       0: new           #4                  // class org/springframework/jdbc/datasource/embedded/EmbeddedDatabaseBuilder
       3: dup
       4: invokespecial #5                  // Method org/springframework/jdbc/datasource/embedded/EmbeddedDatabaseBuilder."<init>":()V
       7: aload_0
       8: getfield      #3                  // Field classLoader:Ljava/lang/ClassLoader;
      11: invokestatic  #6                  // Method org/springframework/boot/jdbc/EmbeddedDatabaseConnection.get:(Ljava/lang/ClassLoader;)Lorg/springframework/boot/jdbc/EmbeddedDatabaseConnection;
      14: invokevirtual #7                  // Method org/springframework/boot/jdbc/EmbeddedDatabaseConnection.getType:()Lorg/springframework/jdbc/datasource/embedded/EmbeddedDatabaseType;
      17: invokevirtual #8                  // Method org/springframework/jdbc/datasource/embedded/EmbeddedDatabaseBuilder.setType:(Lorg/springframework/jdbc/datasource/embedded/EmbeddedDatabaseType;)Lorg/springframework/jdbc/datasource/embedded/EmbeddedDatabaseBuilder;
      20: aload_0
      21: getfield      #2                  // Field properties:Lorg/springframework/boot/autoconfigure/jdbc/DataSourceProperties;
      24: invokevirtual #9                  // Method org/springframework/boot/autoconfigure/jdbc/DataSourceProperties.determineDatabaseName:()Ljava/lang/String;
      27: invokevirtual #10                 // Method org/springframework/jdbc/datasource/embedded/EmbeddedDatabaseBuilder.setName:(Ljava/lang/String;)Lorg/springframework/jdbc/datasource/embedded/EmbeddedDatabaseBuilder;
      30: astore_1
      31: aload_0
      32: aload_1
      33: invokevirtual #11                 // Method org/springframework/jdbc/datasource/embedded/EmbeddedDatabaseBuilder.build:()Lorg/springframework/jdbc/datasource/embedded/EmbeddedDatabase;
      36: putfield      #12                 // Field database:Lorg/springframework/jdbc/datasource/embedded/EmbeddedDatabase;
      39: aload_0
      40: getfield      #12                 // Field database:Lorg/springframework/jdbc/datasource/embedded/EmbeddedDatabase;
      43: areturn

  public void close();
    Code:
       0: aload_0
       1: getfield      #12                 // Field database:Lorg/springframework/jdbc/datasource/embedded/EmbeddedDatabase;
       4: ifnull        16
       7: aload_0
       8: getfield      #12                 // Field database:Lorg/springframework/jdbc/datasource/embedded/EmbeddedDatabase;
      11: invokeinterface #13,  1           // InterfaceMethod org/springframework/jdbc/datasource/embedded/EmbeddedDatabase.shutdown:()V
      16: return
}
