Compiled from "CreateEncryptionZoneFlag.java"
public final class org.apache.hadoop.hdfs.client.CreateEncryptionZoneFlag extends java.lang.Enum<org.apache.hadoop.hdfs.client.CreateEncryptionZoneFlag> {
  public static final org.apache.hadoop.hdfs.client.CreateEncryptionZoneFlag NO_TRASH;

  public static final org.apache.hadoop.hdfs.client.CreateEncryptionZoneFlag PROVISION_TRASH;

  private final short mode;

  private static final org.apache.hadoop.hdfs.client.CreateEncryptionZoneFlag[] $VALUES;

  public static org.apache.hadoop.hdfs.client.CreateEncryptionZoneFlag[] values();
    Code:
       0: getstatic     #1                  // Field $VALUES:[Lorg/apache/hadoop/hdfs/client/CreateEncryptionZoneFlag;
       3: invokevirtual #2                  // Method "[Lorg/apache/hadoop/hdfs/client/CreateEncryptionZoneFlag;".clone:()Ljava/lang/Object;
       6: checkcast     #3                  // class "[Lorg/apache/hadoop/hdfs/client/CreateEncryptionZoneFlag;"
       9: areturn

  public static org.apache.hadoop.hdfs.client.CreateEncryptionZoneFlag valueOf(java.lang.String);
    Code:
       0: ldc           #4                  // class org/apache/hadoop/hdfs/client/CreateEncryptionZoneFlag
       2: aload_0
       3: invokestatic  #5                  // Method java/lang/Enum.valueOf:(Ljava/lang/Class;Ljava/lang/String;)Ljava/lang/Enum;
       6: checkcast     #4                  // class org/apache/hadoop/hdfs/client/CreateEncryptionZoneFlag
       9: areturn

  private org.apache.hadoop.hdfs.client.CreateEncryptionZoneFlag(short);
    Code:
       0: aload_0
       1: aload_1
       2: iload_2
       3: invokespecial #6                  // Method java/lang/Enum."<init>":(Ljava/lang/String;I)V
       6: aload_0
       7: iload_3
       8: putfield      #7                  // Field mode:S
      11: return

  public static org.apache.hadoop.hdfs.client.CreateEncryptionZoneFlag valueOf(short);
    Code:
       0: invokestatic  #8                  // Method values:()[Lorg/apache/hadoop/hdfs/client/CreateEncryptionZoneFlag;
       3: astore_1
       4: aload_1
       5: arraylength
       6: istore_2
       7: iconst_0
       8: istore_3
       9: iload_3
      10: iload_2
      11: if_icmpge     37
      14: aload_1
      15: iload_3
      16: aaload
      17: astore        4
      19: aload         4
      21: invokevirtual #9                  // Method getMode:()S
      24: iload_0
      25: if_icmpne     31
      28: aload         4
      30: areturn
      31: iinc          3, 1
      34: goto          9
      37: aconst_null
      38: areturn

  public short getMode();
    Code:
       0: aload_0
       1: getfield      #7                  // Field mode:S
       4: ireturn

  static {};
    Code:
       0: new           #4                  // class org/apache/hadoop/hdfs/client/CreateEncryptionZoneFlag
       3: dup
       4: ldc           #10                 // String NO_TRASH
       6: iconst_0
       7: iconst_0
       8: invokespecial #11                 // Method "<init>":(Ljava/lang/String;IS)V
      11: putstatic     #12                 // Field NO_TRASH:Lorg/apache/hadoop/hdfs/client/CreateEncryptionZoneFlag;
      14: new           #4                  // class org/apache/hadoop/hdfs/client/CreateEncryptionZoneFlag
      17: dup
      18: ldc           #13                 // String PROVISION_TRASH
      20: iconst_1
      21: iconst_1
      22: invokespecial #11                 // Method "<init>":(Ljava/lang/String;IS)V
      25: putstatic     #14                 // Field PROVISION_TRASH:Lorg/apache/hadoop/hdfs/client/CreateEncryptionZoneFlag;
      28: iconst_2
      29: anewarray     #4                  // class org/apache/hadoop/hdfs/client/CreateEncryptionZoneFlag
      32: dup
      33: iconst_0
      34: getstatic     #12                 // Field NO_TRASH:Lorg/apache/hadoop/hdfs/client/CreateEncryptionZoneFlag;
      37: aastore
      38: dup
      39: iconst_1
      40: getstatic     #14                 // Field PROVISION_TRASH:Lorg/apache/hadoop/hdfs/client/CreateEncryptionZoneFlag;
      43: aastore
      44: putstatic     #1                  // Field $VALUES:[Lorg/apache/hadoop/hdfs/client/CreateEncryptionZoneFlag;
      47: return
}
