Compiled from "CriteriaImpl.java"
public final class org.hibernate.internal.CriteriaImpl$CriterionEntry implements java.io.Serializable {
  private final org.hibernate.criterion.Criterion criterion;

  private final org.hibernate.Criteria criteria;

  private org.hibernate.internal.CriteriaImpl$CriterionEntry(org.hibernate.criterion.Criterion, org.hibernate.Criteria);
    Code:
       0: aload_0
       1: invokespecial #2                  // Method java/lang/Object."<init>":()V
       4: aload_0
       5: aload_2
       6: putfield      #3                  // Field criteria:Lorg/hibernate/Criteria;
       9: aload_0
      10: aload_1
      11: putfield      #4                  // Field criterion:Lorg/hibernate/criterion/Criterion;
      14: return

  public org.hibernate.criterion.Criterion getCriterion();
    Code:
       0: aload_0
       1: getfield      #4                  // Field criterion:Lorg/hibernate/criterion/Criterion;
       4: areturn

  public org.hibernate.Criteria getCriteria();
    Code:
       0: aload_0
       1: getfield      #3                  // Field criteria:Lorg/hibernate/Criteria;
       4: areturn

  public java.lang.String toString();
    Code:
       0: aload_0
       1: getfield      #4                  // Field criterion:Lorg/hibernate/criterion/Criterion;
       4: invokevirtual #5                  // Method java/lang/Object.toString:()Ljava/lang/String;
       7: areturn

  org.hibernate.internal.CriteriaImpl$CriterionEntry(org.hibernate.criterion.Criterion, org.hibernate.Criteria, org.hibernate.internal.CriteriaImpl$1);
    Code:
       0: aload_0
       1: aload_1
       2: aload_2
       3: invokespecial #1                  // Method "<init>":(Lorg/hibernate/criterion/Criterion;Lorg/hibernate/Criteria;)V
       6: return
}
