public interface org.bouncycastle.asn1.x509.X509AttributeIdentifiers {
  public static final org.bouncycastle.asn1.ASN1ObjectIdentifier RoleSyntax;

  public static final org.bouncycastle.asn1.ASN1ObjectIdentifier id_pe_ac_auditIdentity;

  public static final org.bouncycastle.asn1.ASN1ObjectIdentifier id_pe_aaControls;

  public static final org.bouncycastle.asn1.ASN1ObjectIdentifier id_pe_ac_proxying;

  public static final org.bouncycastle.asn1.ASN1ObjectIdentifier id_ce_targetInformation;

  public static final org.bouncycastle.asn1.ASN1ObjectIdentifier id_aca;

  public static final org.bouncycastle.asn1.ASN1ObjectIdentifier id_aca_authenticationInfo;

  public static final org.bouncycastle.asn1.ASN1ObjectIdentifier id_aca_accessIdentity;

  public static final org.bouncycastle.asn1.ASN1ObjectIdentifier id_aca_chargingIdentity;

  public static final org.bouncycastle.asn1.ASN1ObjectIdentifier id_aca_group;

  public static final org.bouncycastle.asn1.ASN1ObjectIdentifier id_aca_encAttrs;

  public static final org.bouncycastle.asn1.ASN1ObjectIdentifier id_at_role;

  public static final org.bouncycastle.asn1.ASN1ObjectIdentifier id_at_clearance;

  static {};
    Code:
       0: new           #44                 // class org/bouncycastle/asn1/ASN1ObjectIdentifier
       3: dup
       4: ldc           #5                  // String 2.5.4.72
       6: invokespecial #84                 // Method org/bouncycastle/asn1/ASN1ObjectIdentifier."<init>":(Ljava/lang/String;)V
       9: putstatic     #68                 // Field RoleSyntax:Lorg/bouncycastle/asn1/ASN1ObjectIdentifier;
      12: getstatic     #82                 // Field org/bouncycastle/asn1/x509/X509ObjectIdentifiers.id_pe:Lorg/bouncycastle/asn1/ASN1ObjectIdentifier;
      15: ldc           #7                  // String 4
      17: invokevirtual #85                 // Method org/bouncycastle/asn1/ASN1ObjectIdentifier.branch:(Ljava/lang/String;)Lorg/bouncycastle/asn1/ASN1ObjectIdentifier;
      20: putstatic     #79                 // Field id_pe_ac_auditIdentity:Lorg/bouncycastle/asn1/ASN1ObjectIdentifier;
      23: getstatic     #82                 // Field org/bouncycastle/asn1/x509/X509ObjectIdentifiers.id_pe:Lorg/bouncycastle/asn1/ASN1ObjectIdentifier;
      26: ldc           #9                  // String 6
      28: invokevirtual #85                 // Method org/bouncycastle/asn1/ASN1ObjectIdentifier.branch:(Ljava/lang/String;)Lorg/bouncycastle/asn1/ASN1ObjectIdentifier;
      31: putstatic     #78                 // Field id_pe_aaControls:Lorg/bouncycastle/asn1/ASN1ObjectIdentifier;
      34: getstatic     #82                 // Field org/bouncycastle/asn1/x509/X509ObjectIdentifiers.id_pe:Lorg/bouncycastle/asn1/ASN1ObjectIdentifier;
      37: ldc           #2                  // String 10
      39: invokevirtual #85                 // Method org/bouncycastle/asn1/ASN1ObjectIdentifier.branch:(Ljava/lang/String;)Lorg/bouncycastle/asn1/ASN1ObjectIdentifier;
      42: putstatic     #80                 // Field id_pe_ac_proxying:Lorg/bouncycastle/asn1/ASN1ObjectIdentifier;
      45: getstatic     #81                 // Field org/bouncycastle/asn1/x509/X509ObjectIdentifiers.id_ce:Lorg/bouncycastle/asn1/ASN1ObjectIdentifier;
      48: ldc           #8                  // String 55
      50: invokevirtual #85                 // Method org/bouncycastle/asn1/ASN1ObjectIdentifier.branch:(Ljava/lang/String;)Lorg/bouncycastle/asn1/ASN1ObjectIdentifier;
      53: putstatic     #77                 // Field id_ce_targetInformation:Lorg/bouncycastle/asn1/ASN1ObjectIdentifier;
      56: getstatic     #83                 // Field org/bouncycastle/asn1/x509/X509ObjectIdentifiers.id_pkix:Lorg/bouncycastle/asn1/ASN1ObjectIdentifier;
      59: ldc           #2                  // String 10
      61: invokevirtual #85                 // Method org/bouncycastle/asn1/ASN1ObjectIdentifier.branch:(Ljava/lang/String;)Lorg/bouncycastle/asn1/ASN1ObjectIdentifier;
      64: putstatic     #69                 // Field id_aca:Lorg/bouncycastle/asn1/ASN1ObjectIdentifier;
      67: getstatic     #69                 // Field id_aca:Lorg/bouncycastle/asn1/ASN1ObjectIdentifier;
      70: ldc           #1                  // String 1
      72: invokevirtual #85                 // Method org/bouncycastle/asn1/ASN1ObjectIdentifier.branch:(Ljava/lang/String;)Lorg/bouncycastle/asn1/ASN1ObjectIdentifier;
      75: putstatic     #71                 // Field id_aca_authenticationInfo:Lorg/bouncycastle/asn1/ASN1ObjectIdentifier;
      78: getstatic     #69                 // Field id_aca:Lorg/bouncycastle/asn1/ASN1ObjectIdentifier;
      81: ldc           #3                  // String 2
      83: invokevirtual #85                 // Method org/bouncycastle/asn1/ASN1ObjectIdentifier.branch:(Ljava/lang/String;)Lorg/bouncycastle/asn1/ASN1ObjectIdentifier;
      86: putstatic     #70                 // Field id_aca_accessIdentity:Lorg/bouncycastle/asn1/ASN1ObjectIdentifier;
      89: getstatic     #69                 // Field id_aca:Lorg/bouncycastle/asn1/ASN1ObjectIdentifier;
      92: ldc           #6                  // String 3
      94: invokevirtual #85                 // Method org/bouncycastle/asn1/ASN1ObjectIdentifier.branch:(Ljava/lang/String;)Lorg/bouncycastle/asn1/ASN1ObjectIdentifier;
      97: putstatic     #72                 // Field id_aca_chargingIdentity:Lorg/bouncycastle/asn1/ASN1ObjectIdentifier;
     100: getstatic     #69                 // Field id_aca:Lorg/bouncycastle/asn1/ASN1ObjectIdentifier;
     103: ldc           #7                  // String 4
     105: invokevirtual #85                 // Method org/bouncycastle/asn1/ASN1ObjectIdentifier.branch:(Ljava/lang/String;)Lorg/bouncycastle/asn1/ASN1ObjectIdentifier;
     108: putstatic     #74                 // Field id_aca_group:Lorg/bouncycastle/asn1/ASN1ObjectIdentifier;
     111: getstatic     #69                 // Field id_aca:Lorg/bouncycastle/asn1/ASN1ObjectIdentifier;
     114: ldc           #9                  // String 6
     116: invokevirtual #85                 // Method org/bouncycastle/asn1/ASN1ObjectIdentifier.branch:(Ljava/lang/String;)Lorg/bouncycastle/asn1/ASN1ObjectIdentifier;
     119: putstatic     #73                 // Field id_aca_encAttrs:Lorg/bouncycastle/asn1/ASN1ObjectIdentifier;
     122: new           #44                 // class org/bouncycastle/asn1/ASN1ObjectIdentifier
     125: dup
     126: ldc           #5                  // String 2.5.4.72
     128: invokespecial #84                 // Method org/bouncycastle/asn1/ASN1ObjectIdentifier."<init>":(Ljava/lang/String;)V
     131: putstatic     #76                 // Field id_at_role:Lorg/bouncycastle/asn1/ASN1ObjectIdentifier;
     134: new           #44                 // class org/bouncycastle/asn1/ASN1ObjectIdentifier
     137: dup
     138: ldc           #4                  // String 2.5.1.5.55
     140: invokespecial #84                 // Method org/bouncycastle/asn1/ASN1ObjectIdentifier."<init>":(Ljava/lang/String;)V
     143: putstatic     #75                 // Field id_at_clearance:Lorg/bouncycastle/asn1/ASN1ObjectIdentifier;
     146: return
}
