Compiled from "InternalSerializerHolder.kt"
final class net.mamoe.mirai.api.http.context.serializer.InternalSerializerHolder$serializer$2 extends kotlin.jvm.internal.Lambda implements kotlin.jvm.functions.Function0<net.mamoe.mirai.api.http.adapter.internal.serializer.BuiltinJsonSerializer> {
  public static final net.mamoe.mirai.api.http.context.serializer.InternalSerializerHolder$serializer$2 INSTANCE;

  net.mamoe.mirai.api.http.context.serializer.InternalSerializerHolder$serializer$2();
    Code:
       0: aload_0
       1: iconst_0
       2: invokespecial #12                 // Method kotlin/jvm/internal/Lambda."<init>":(I)V
       5: return

  public final net.mamoe.mirai.api.http.adapter.internal.serializer.BuiltinJsonSerializer invoke();
    Code:
       0: new           #19                 // class net/mamoe/mirai/api/http/adapter/internal/serializer/BuiltinJsonSerializer
       3: dup
       4: invokespecial #21                 // Method net/mamoe/mirai/api/http/adapter/internal/serializer/BuiltinJsonSerializer."<init>":()V
       7: areturn

  public java.lang.Object invoke();
    Code:
       0: aload_0
       1: invokevirtual #24                 // Method invoke:()Lnet/mamoe/mirai/api/http/adapter/internal/serializer/BuiltinJsonSerializer;
       4: areturn

  static {};
    Code:
       0: new           #2                  // class net/mamoe/mirai/api/http/context/serializer/InternalSerializerHolder$serializer$2
       3: dup
       4: invokespecial #26                 // Method "<init>":()V
       7: putstatic     #29                 // Field INSTANCE:Lnet/mamoe/mirai/api/http/context/serializer/InternalSerializerHolder$serializer$2;
      10: return
}
