Compiled from "DefaultCommandContainer.java"
public abstract class org.jboss.aesh.console.command.container.DefaultCommandContainer<C extends org.jboss.aesh.console.command.Command> implements org.jboss.aesh.console.command.container.CommandContainer<C> {
  public org.jboss.aesh.console.command.container.DefaultCommandContainer();
    Code:
       0: aload_0
       1: invokespecial #1                  // Method java/lang/Object."<init>":()V
       4: return

  public org.jboss.aesh.console.command.container.CommandContainerResult executeCommand(org.jboss.aesh.parser.AeshLine, org.jboss.aesh.console.InvocationProviders, org.jboss.aesh.console.AeshContext, org.jboss.aesh.console.command.invocation.CommandInvocation) throws org.jboss.aesh.cl.parser.CommandLineParserException, org.jboss.aesh.cl.validator.OptionValidatorException, org.jboss.aesh.cl.validator.CommandValidatorException, java.io.IOException, java.lang.InterruptedException;
    Code:
       0: aload_0
       1: invokevirtual #2                  // Method getParser:()Lorg/jboss/aesh/cl/parser/CommandLineParser;
       4: aload_1
       5: iconst_0
       6: invokeinterface #3,  3            // InterfaceMethod org/jboss/aesh/cl/parser/CommandLineParser.parse:(Lorg/jboss/aesh/parser/AeshLine;Z)Lorg/jboss/aesh/cl/CommandLine;
      11: astore        5
      13: aload         5
      15: invokevirtual #4                  // Method org/jboss/aesh/cl/CommandLine.getParser:()Lorg/jboss/aesh/cl/parser/CommandLineParser;
      18: invokeinterface #5,  1            // InterfaceMethod org/jboss/aesh/cl/parser/CommandLineParser.getCommandPopulator:()Lorg/jboss/aesh/cl/populator/CommandPopulator;
      23: aload         5
      25: aload_2
      26: aload_3
      27: iconst_1
      28: invokeinterface #6,  5            // InterfaceMethod org/jboss/aesh/cl/populator/CommandPopulator.populateObject:(Lorg/jboss/aesh/cl/CommandLine;Lorg/jboss/aesh/console/InvocationProviders;Lorg/jboss/aesh/console/AeshContext;Z)V
      33: aload         5
      35: invokevirtual #4                  // Method org/jboss/aesh/cl/CommandLine.getParser:()Lorg/jboss/aesh/cl/parser/CommandLineParser;
      38: invokeinterface #7,  1            // InterfaceMethod org/jboss/aesh/cl/parser/CommandLineParser.getProcessedCommand:()Lorg/jboss/aesh/cl/internal/ProcessedCommand;
      43: invokevirtual #8                  // Method org/jboss/aesh/cl/internal/ProcessedCommand.getValidator:()Lorg/jboss/aesh/cl/validator/CommandValidator;
      46: ifnull        85
      49: aload         5
      51: invokevirtual #9                  // Method org/jboss/aesh/cl/CommandLine.hasOptionWithOverrideRequired:()Z
      54: ifne          85
      57: aload         5
      59: invokevirtual #4                  // Method org/jboss/aesh/cl/CommandLine.getParser:()Lorg/jboss/aesh/cl/parser/CommandLineParser;
      62: invokeinterface #7,  1            // InterfaceMethod org/jboss/aesh/cl/parser/CommandLineParser.getProcessedCommand:()Lorg/jboss/aesh/cl/internal/ProcessedCommand;
      67: invokevirtual #8                  // Method org/jboss/aesh/cl/internal/ProcessedCommand.getValidator:()Lorg/jboss/aesh/cl/validator/CommandValidator;
      70: aload         5
      72: invokevirtual #4                  // Method org/jboss/aesh/cl/CommandLine.getParser:()Lorg/jboss/aesh/cl/parser/CommandLineParser;
      75: invokeinterface #10,  1           // InterfaceMethod org/jboss/aesh/cl/parser/CommandLineParser.getCommand:()Lorg/jboss/aesh/console/command/Command;
      80: invokeinterface #11,  2           // InterfaceMethod org/jboss/aesh/cl/validator/CommandValidator.validate:(Lorg/jboss/aesh/console/command/Command;)V
      85: aload         5
      87: invokevirtual #4                  // Method org/jboss/aesh/cl/CommandLine.getParser:()Lorg/jboss/aesh/cl/parser/CommandLineParser;
      90: invokeinterface #10,  1           // InterfaceMethod org/jboss/aesh/cl/parser/CommandLineParser.getCommand:()Lorg/jboss/aesh/console/command/Command;
      95: aload         4
      97: invokeinterface #12,  2           // InterfaceMethod org/jboss/aesh/console/command/Command.execute:(Lorg/jboss/aesh/console/command/invocation/CommandInvocation;)Lorg/jboss/aesh/console/command/CommandResult;
     102: astore        6
     104: new           #13                 // class org/jboss/aesh/console/command/container/CommandContainerResult
     107: dup
     108: aload         5
     110: invokevirtual #4                  // Method org/jboss/aesh/cl/CommandLine.getParser:()Lorg/jboss/aesh/cl/parser/CommandLineParser;
     113: invokeinterface #7,  1            // InterfaceMethod org/jboss/aesh/cl/parser/CommandLineParser.getProcessedCommand:()Lorg/jboss/aesh/cl/internal/ProcessedCommand;
     118: invokevirtual #14                 // Method org/jboss/aesh/cl/internal/ProcessedCommand.getResultHandler:()Lorg/jboss/aesh/cl/result/ResultHandler;
     121: aload         6
     123: invokespecial #15                 // Method org/jboss/aesh/console/command/container/CommandContainerResult."<init>":(Lorg/jboss/aesh/cl/result/ResultHandler;Lorg/jboss/aesh/console/command/CommandResult;)V
     126: areturn

  public java.lang.String printHelp(java.lang.String);
    Code:
       0: aload_0
       1: invokevirtual #2                  // Method getParser:()Lorg/jboss/aesh/cl/parser/CommandLineParser;
       4: invokeinterface #16,  1           // InterfaceMethod org/jboss/aesh/cl/parser/CommandLineParser.isGroupCommand:()Z
       9: ifeq          94
      12: aload_1
      13: ldc           #17                 // String
      15: invokevirtual #18                 // Method java/lang/String.contains:(Ljava/lang/CharSequence;)Z
      18: ifeq          94
      21: aload_1
      22: ldc           #17                 // String
      24: invokevirtual #19                 // Method java/lang/String.split:(Ljava/lang/String;)[Ljava/lang/String;
      27: astore_2
      28: aload_2
      29: arraylength
      30: iconst_1
      31: if_icmple     67
      34: aload_2
      35: iconst_1
      36: aaload
      37: invokevirtual #20                 // Method java/lang/String.length:()I
      40: ifle          67
      43: aload_0
      44: invokevirtual #2                  // Method getParser:()Lorg/jboss/aesh/cl/parser/CommandLineParser;
      47: aload_2
      48: iconst_1
      49: aaload
      50: invokeinterface #21,  2           // InterfaceMethod org/jboss/aesh/cl/parser/CommandLineParser.getChildParser:(Ljava/lang/String;)Lorg/jboss/aesh/cl/parser/CommandLineParser;
      55: astore_3
      56: aload_3
      57: ifnull        67
      60: aload_3
      61: invokeinterface #22,  1           // InterfaceMethod org/jboss/aesh/cl/parser/CommandLineParser.printHelp:()Ljava/lang/String;
      66: areturn
      67: new           #23                 // class java/lang/StringBuilder
      70: dup
      71: invokespecial #24                 // Method java/lang/StringBuilder."<init>":()V
      74: ldc           #25                 // String Child command
      76: invokevirtual #26                 // Method java/lang/StringBuilder.append:(Ljava/lang/String;)Ljava/lang/StringBuilder;
      79: aload_2
      80: iconst_1
      81: aaload
      82: invokevirtual #26                 // Method java/lang/StringBuilder.append:(Ljava/lang/String;)Ljava/lang/StringBuilder;
      85: ldc           #27                 // String  not found.
      87: invokevirtual #26                 // Method java/lang/StringBuilder.append:(Ljava/lang/String;)Ljava/lang/StringBuilder;
      90: invokevirtual #28                 // Method java/lang/StringBuilder.toString:()Ljava/lang/String;
      93: areturn
      94: aload_0
      95: invokevirtual #2                  // Method getParser:()Lorg/jboss/aesh/cl/parser/CommandLineParser;
      98: invokeinterface #22,  1           // InterfaceMethod org/jboss/aesh/cl/parser/CommandLineParser.printHelp:()Ljava/lang/String;
     103: areturn
}
