Compiled from "MapUnmarshaller.java"
public class com.amazonaws.services.dynamodbv2.datamodeling.unmarshallers.MapUnmarshaller extends com.amazonaws.services.dynamodbv2.datamodeling.unmarshallers.MUnmarshaller {
  private static final com.amazonaws.services.dynamodbv2.datamodeling.unmarshallers.MapUnmarshaller INSTANCE;

  private final com.amazonaws.services.dynamodbv2.datamodeling.ArgumentUnmarshaller memberUnmarshaller;

  public static com.amazonaws.services.dynamodbv2.datamodeling.unmarshallers.MapUnmarshaller instance();
    Code:
       0: getstatic     #1                  // Field INSTANCE:Lcom/amazonaws/services/dynamodbv2/datamodeling/unmarshallers/MapUnmarshaller;
       3: areturn

  private com.amazonaws.services.dynamodbv2.datamodeling.unmarshallers.MapUnmarshaller();
    Code:
       0: aload_0
       1: invokespecial #2                  // Method com/amazonaws/services/dynamodbv2/datamodeling/unmarshallers/MUnmarshaller."<init>":()V
       4: aload_0
       5: aconst_null
       6: putfield      #3                  // Field memberUnmarshaller:Lcom/amazonaws/services/dynamodbv2/datamodeling/ArgumentUnmarshaller;
       9: return

  public com.amazonaws.services.dynamodbv2.datamodeling.unmarshallers.MapUnmarshaller(com.amazonaws.services.dynamodbv2.datamodeling.ArgumentUnmarshaller);
    Code:
       0: aload_0
       1: invokespecial #2                  // Method com/amazonaws/services/dynamodbv2/datamodeling/unmarshallers/MUnmarshaller."<init>":()V
       4: aload_1
       5: ifnonnull     18
       8: new           #4                  // class java/lang/NullPointerException
      11: dup
      12: ldc           #5                  // String memberUnmarshaller
      14: invokespecial #6                  // Method java/lang/NullPointerException."<init>":(Ljava/lang/String;)V
      17: athrow
      18: aload_0
      19: aload_1
      20: putfield      #3                  // Field memberUnmarshaller:Lcom/amazonaws/services/dynamodbv2/datamodeling/ArgumentUnmarshaller;
      23: return

  public java.lang.Object unmarshall(com.amazonaws.services.dynamodbv2.model.AttributeValue) throws java.text.ParseException;
    Code:
       0: aload_1
       1: invokevirtual #7                  // Method com/amazonaws/services/dynamodbv2/model/AttributeValue.getM:()Ljava/util/Map;
       4: astore_2
       5: new           #8                  // class java/util/HashMap
       8: dup
       9: invokespecial #9                  // Method java/util/HashMap."<init>":()V
      12: astore_3
      13: aload_2
      14: invokeinterface #10,  1           // InterfaceMethod java/util/Map.entrySet:()Ljava/util/Set;
      19: invokeinterface #11,  1           // InterfaceMethod java/util/Set.iterator:()Ljava/util/Iterator;
      24: astore        4
      26: aload         4
      28: invokeinterface #12,  1           // InterfaceMethod java/util/Iterator.hasNext:()Z
      33: ifeq          104
      36: aload         4
      38: invokeinterface #13,  1           // InterfaceMethod java/util/Iterator.next:()Ljava/lang/Object;
      43: checkcast     #14                 // class java/util/Map$Entry
      46: astore        5
      48: aload_0
      49: getfield      #3                  // Field memberUnmarshaller:Lcom/amazonaws/services/dynamodbv2/datamodeling/ArgumentUnmarshaller;
      52: aload         5
      54: invokeinterface #15,  1           // InterfaceMethod java/util/Map$Entry.getValue:()Ljava/lang/Object;
      59: checkcast     #16                 // class com/amazonaws/services/dynamodbv2/model/AttributeValue
      62: aconst_null
      63: invokeinterface #17,  3           // InterfaceMethod com/amazonaws/services/dynamodbv2/datamodeling/ArgumentUnmarshaller.typeCheck:(Lcom/amazonaws/services/dynamodbv2/model/AttributeValue;Ljava/lang/reflect/Method;)V
      68: aload_3
      69: aload         5
      71: invokeinterface #18,  1           // InterfaceMethod java/util/Map$Entry.getKey:()Ljava/lang/Object;
      76: aload_0
      77: getfield      #3                  // Field memberUnmarshaller:Lcom/amazonaws/services/dynamodbv2/datamodeling/ArgumentUnmarshaller;
      80: aload         5
      82: invokeinterface #15,  1           // InterfaceMethod java/util/Map$Entry.getValue:()Ljava/lang/Object;
      87: checkcast     #16                 // class com/amazonaws/services/dynamodbv2/model/AttributeValue
      90: invokeinterface #19,  2           // InterfaceMethod com/amazonaws/services/dynamodbv2/datamodeling/ArgumentUnmarshaller.unmarshall:(Lcom/amazonaws/services/dynamodbv2/model/AttributeValue;)Ljava/lang/Object;
      95: invokeinterface #20,  3           // InterfaceMethod java/util/Map.put:(Ljava/lang/Object;Ljava/lang/Object;)Ljava/lang/Object;
     100: pop
     101: goto          26
     104: aload_3
     105: areturn

  public void typeCheck(com.amazonaws.services.dynamodbv2.model.AttributeValue, java.lang.reflect.Method);
    Code:
       0: aload_0
       1: aload_1
       2: aload_2
       3: invokespecial #21                 // Method com/amazonaws/services/dynamodbv2/datamodeling/unmarshallers/MUnmarshaller.typeCheck:(Lcom/amazonaws/services/dynamodbv2/model/AttributeValue;Ljava/lang/reflect/Method;)V
       6: return

  static {};
    Code:
       0: new           #22                 // class com/amazonaws/services/dynamodbv2/datamodeling/unmarshallers/MapUnmarshaller
       3: dup
       4: invokespecial #23                 // Method "<init>":()V
       7: putstatic     #1                  // Field INSTANCE:Lcom/amazonaws/services/dynamodbv2/datamodeling/unmarshallers/MapUnmarshaller;
      10: return
}
