Compiled from "ObjectUnmarshaller.java"
public class com.amazonaws.services.dynamodbv2.datamodeling.unmarshallers.ObjectUnmarshaller extends com.amazonaws.services.dynamodbv2.datamodeling.unmarshallers.MUnmarshaller {
  private static final com.amazonaws.services.dynamodbv2.datamodeling.unmarshallers.ObjectUnmarshaller INSTANCE;

  private final com.amazonaws.services.dynamodbv2.datamodeling.ItemConverter converter;

  private final java.lang.Class<?> clazz;

  public static com.amazonaws.services.dynamodbv2.datamodeling.unmarshallers.ObjectUnmarshaller instance();
    Code:
       0: getstatic     #1                  // Field INSTANCE:Lcom/amazonaws/services/dynamodbv2/datamodeling/unmarshallers/ObjectUnmarshaller;
       3: areturn

  private com.amazonaws.services.dynamodbv2.datamodeling.unmarshallers.ObjectUnmarshaller();
    Code:
       0: aload_0
       1: invokespecial #2                  // Method com/amazonaws/services/dynamodbv2/datamodeling/unmarshallers/MUnmarshaller."<init>":()V
       4: aload_0
       5: aconst_null
       6: putfield      #3                  // Field converter:Lcom/amazonaws/services/dynamodbv2/datamodeling/ItemConverter;
       9: aload_0
      10: aconst_null
      11: putfield      #4                  // Field clazz:Ljava/lang/Class;
      14: return

  public com.amazonaws.services.dynamodbv2.datamodeling.unmarshallers.ObjectUnmarshaller(com.amazonaws.services.dynamodbv2.datamodeling.ItemConverter, java.lang.Class<?>);
    Code:
       0: aload_0
       1: invokespecial #2                  // Method com/amazonaws/services/dynamodbv2/datamodeling/unmarshallers/MUnmarshaller."<init>":()V
       4: aload_1
       5: ifnonnull     18
       8: new           #5                  // class java/lang/NullPointerException
      11: dup
      12: ldc           #6                  // String converter
      14: invokespecial #7                  // Method java/lang/NullPointerException."<init>":(Ljava/lang/String;)V
      17: athrow
      18: aload_2
      19: ifnonnull     32
      22: new           #5                  // class java/lang/NullPointerException
      25: dup
      26: ldc           #8                  // String clazz
      28: invokespecial #7                  // Method java/lang/NullPointerException."<init>":(Ljava/lang/String;)V
      31: athrow
      32: aload_0
      33: aload_1
      34: putfield      #3                  // Field converter:Lcom/amazonaws/services/dynamodbv2/datamodeling/ItemConverter;
      37: aload_0
      38: aload_2
      39: putfield      #4                  // Field clazz:Ljava/lang/Class;
      42: return

  public java.lang.Object unmarshall(com.amazonaws.services.dynamodbv2.model.AttributeValue) throws java.text.ParseException;
    Code:
       0: aload_1
       1: invokevirtual #9                  // Method com/amazonaws/services/dynamodbv2/model/AttributeValue.getM:()Ljava/util/Map;
       4: astore_2
       5: aload_0
       6: getfield      #3                  // Field converter:Lcom/amazonaws/services/dynamodbv2/datamodeling/ItemConverter;
       9: aload_0
      10: getfield      #4                  // Field clazz:Ljava/lang/Class;
      13: aload_2
      14: invokeinterface #10,  3           // InterfaceMethod com/amazonaws/services/dynamodbv2/datamodeling/ItemConverter.unconvert:(Ljava/lang/Class;Ljava/util/Map;)Ljava/lang/Object;
      19: areturn

  public void typeCheck(com.amazonaws.services.dynamodbv2.model.AttributeValue, java.lang.reflect.Method);
    Code:
       0: aload_0
       1: aload_1
       2: aload_2
       3: invokespecial #11                 // Method com/amazonaws/services/dynamodbv2/datamodeling/unmarshallers/MUnmarshaller.typeCheck:(Lcom/amazonaws/services/dynamodbv2/model/AttributeValue;Ljava/lang/reflect/Method;)V
       6: return

  static {};
    Code:
       0: new           #12                 // class com/amazonaws/services/dynamodbv2/datamodeling/unmarshallers/ObjectUnmarshaller
       3: dup
       4: invokespecial #13                 // Method "<init>":()V
       7: putstatic     #1                  // Field INSTANCE:Lcom/amazonaws/services/dynamodbv2/datamodeling/unmarshallers/ObjectUnmarshaller;
      10: return
}
