Compiled from "MessageConveyorException.java"
public class ch.qos.cal10n.MessageConveyorException extends java.lang.RuntimeException {
  private static final long serialVersionUID;

  public ch.qos.cal10n.MessageConveyorException(java.lang.String);
    Code:
       0: aload_0
       1: aload_1
       2: invokespecial #1                  // Method java/lang/RuntimeException."<init>":(Ljava/lang/String;)V
       5: return

  public ch.qos.cal10n.MessageConveyorException(java.lang.String, java.lang.Throwable);
    Code:
       0: aload_0
       1: aload_1
       2: aload_2
       3: invokespecial #2                  // Method java/lang/RuntimeException."<init>":(Ljava/lang/String;Ljava/lang/Throwable;)V
       6: return
}
