Compiled from "FixedSubscriberChannelBeanFactoryPostProcessor.java"
public final class org.springframework.integration.config.FixedSubscriberChannelBeanFactoryPostProcessor implements org.springframework.beans.factory.config.BeanFactoryPostProcessor {
  private final java.util.Map<java.lang.String, java.lang.String> candidateFixedChannelHandlerMap;

  private org.springframework.integration.config.FixedSubscriberChannelBeanFactoryPostProcessor(java.util.Map<java.lang.String, java.lang.String>);
    Code:
       0: aload_0
       1: invokespecial #1                  // Method java/lang/Object."<init>":()V
       4: aload_0
       5: aload_1
       6: putfield      #2                  // Field candidateFixedChannelHandlerMap:Ljava/util/Map;
       9: return

  public void postProcessBeanFactory(org.springframework.beans.factory.config.ConfigurableListableBeanFactory) throws org.springframework.beans.BeansException;
    Code:
       0: aload_1
       1: instanceof    #3                  // class org/springframework/beans/factory/support/BeanDefinitionRegistry
       4: ifeq          180
       7: aload_1
       8: checkcast     #3                  // class org/springframework/beans/factory/support/BeanDefinitionRegistry
      11: astore_2
      12: aload_0
      13: getfield      #2                  // Field candidateFixedChannelHandlerMap:Ljava/util/Map;
      16: invokeinterface #4,  1            // InterfaceMethod java/util/Map.size:()I
      21: ifle          180
      24: aload_0
      25: getfield      #2                  // Field candidateFixedChannelHandlerMap:Ljava/util/Map;
      28: invokeinterface #5,  1            // InterfaceMethod java/util/Map.entrySet:()Ljava/util/Set;
      33: invokeinterface #6,  1            // InterfaceMethod java/util/Set.iterator:()Ljava/util/Iterator;
      38: astore_3
      39: aload_3
      40: invokeinterface #7,  1            // InterfaceMethod java/util/Iterator.hasNext:()Z
      45: ifeq          180
      48: aload_3
      49: invokeinterface #8,  1            // InterfaceMethod java/util/Iterator.next:()Ljava/lang/Object;
      54: checkcast     #9                  // class java/util/Map$Entry
      57: astore        4
      59: aload         4
      61: invokeinterface #10,  1           // InterfaceMethod java/util/Map$Entry.getKey:()Ljava/lang/Object;
      66: checkcast     #11                 // class java/lang/String
      69: astore        5
      71: aload         4
      73: invokeinterface #12,  1           // InterfaceMethod java/util/Map$Entry.getValue:()Ljava/lang/Object;
      78: checkcast     #11                 // class java/lang/String
      81: astore        6
      83: aconst_null
      84: astore        7
      86: aload_2
      87: aload         5
      89: invokeinterface #13,  2           // InterfaceMethod org/springframework/beans/factory/support/BeanDefinitionRegistry.containsBeanDefinition:(Ljava/lang/String;)Z
      94: ifeq          107
      97: aload_2
      98: aload         5
     100: invokeinterface #14,  2           // InterfaceMethod org/springframework/beans/factory/support/BeanDefinitionRegistry.getBeanDefinition:(Ljava/lang/String;)Lorg/springframework/beans/factory/config/BeanDefinition;
     105: astore        7
     107: aload         7
     109: ifnull        177
     112: aload_2
     113: aload         6
     115: invokeinterface #13,  2           // InterfaceMethod org/springframework/beans/factory/support/BeanDefinitionRegistry.containsBeanDefinition:(Ljava/lang/String;)Z
     120: ifeq          177
     123: aload_2
     124: aload         6
     126: invokeinterface #14,  2           // InterfaceMethod org/springframework/beans/factory/support/BeanDefinitionRegistry.getBeanDefinition:(Ljava/lang/String;)Lorg/springframework/beans/factory/config/BeanDefinition;
     131: astore        8
     133: ldc           #15                 // class org/springframework/integration/channel/FixedSubscriberChannel
     135: invokevirtual #16                 // Method java/lang/Class.getName:()Ljava/lang/String;
     138: aload         8
     140: invokeinterface #17,  1           // InterfaceMethod org/springframework/beans/factory/config/BeanDefinition.getBeanClassName:()Ljava/lang/String;
     145: invokevirtual #18                 // Method java/lang/String.equals:(Ljava/lang/Object;)Z
     148: ifeq          177
     151: aload         8
     153: invokeinterface #19,  1           // InterfaceMethod org/springframework/beans/factory/config/BeanDefinition.getConstructorArgumentValues:()Lorg/springframework/beans/factory/config/ConstructorArgumentValues;
     158: astore        9
     160: aload         9
     162: invokevirtual #20                 // Method org/springframework/beans/factory/config/ConstructorArgumentValues.isEmpty:()Z
     165: ldc           #21                 // String Only one subscriber is allowed for a FixedSubscriberChannel.
     167: invokestatic  #22                 // Method org/springframework/util/Assert.isTrue:(ZLjava/lang/String;)V
     170: aload         9
     172: aload         7
     174: invokevirtual #23                 // Method org/springframework/beans/factory/config/ConstructorArgumentValues.addGenericArgumentValue:(Ljava/lang/Object;)V
     177: goto          39
     180: return
}
