Compiled from "IntegrationComponentScanRegistrar.java"
class org.springframework.integration.config.IntegrationComponentScanRegistrar$1 extends org.springframework.context.annotation.ClassPathScanningCandidateComponentProvider {
  final org.springframework.integration.config.IntegrationComponentScanRegistrar this$0;

  org.springframework.integration.config.IntegrationComponentScanRegistrar$1(org.springframework.integration.config.IntegrationComponentScanRegistrar, boolean, org.springframework.core.env.Environment);
    Code:
       0: aload_0
       1: aload_1
       2: putfield      #1                  // Field this$0:Lorg/springframework/integration/config/IntegrationComponentScanRegistrar;
       5: aload_0
       6: iload_2
       7: aload_3
       8: invokespecial #2                  // Method org/springframework/context/annotation/ClassPathScanningCandidateComponentProvider."<init>":(ZLorg/springframework/core/env/Environment;)V
      11: return

  protected boolean isCandidateComponent(org.springframework.beans.factory.annotation.AnnotatedBeanDefinition);
    Code:
       0: aload_1
       1: invokeinterface #3,  1            // InterfaceMethod org/springframework/beans/factory/annotation/AnnotatedBeanDefinition.getMetadata:()Lorg/springframework/core/type/AnnotationMetadata;
       6: invokeinterface #4,  1            // InterfaceMethod org/springframework/core/type/AnnotationMetadata.isIndependent:()Z
      11: ifeq          32
      14: aload_1
      15: invokeinterface #3,  1            // InterfaceMethod org/springframework/beans/factory/annotation/AnnotatedBeanDefinition.getMetadata:()Lorg/springframework/core/type/AnnotationMetadata;
      20: invokeinterface #5,  1            // InterfaceMethod org/springframework/core/type/AnnotationMetadata.isAnnotation:()Z
      25: ifne          32
      28: iconst_1
      29: goto          33
      32: iconst_0
      33: ireturn
}
