Compiled from "DelimitedDataOptions.java"
public class org.hpccsystems.ws.client.utils.DelimitedDataOptions implements java.io.Serializable {
  private static final long serialVersionUID;

  public static final java.lang.String csvDefaultSeparate;

  public static final java.lang.String csvDefaultEscape;

  public static final java.lang.String csvDefaultQuote;

  public static final java.lang.String csvDefaultTerminator;

  java.lang.String recordTerminator;

  java.lang.String fieldDelimiter;

  java.lang.String escapeSequence;

  java.lang.String quote;

  public static final org.hpccsystems.ws.client.utils.DelimitedDataOptions DefaultCSVDataOptions;

  public org.hpccsystems.ws.client.utils.DelimitedDataOptions();
    Code:
       0: aload_0
       1: invokespecial #1                  // Method java/lang/Object."<init>":()V
       4: aload_0
       5: ldc           #3                  // String \n
       7: putfield      #4                  // Field recordTerminator:Ljava/lang/String;
      10: aload_0
      11: ldc           #5                  // String \\,
      13: putfield      #6                  // Field fieldDelimiter:Ljava/lang/String;
      16: aload_0
      17: ldc           #7                  // String
      19: putfield      #8                  // Field escapeSequence:Ljava/lang/String;
      22: aload_0
      23: ldc           #9                  // String \'
      25: putfield      #10                 // Field quote:Ljava/lang/String;
      28: return

  public org.hpccsystems.ws.client.utils.DelimitedDataOptions(java.lang.String, java.lang.String, java.lang.String, java.lang.String);
    Code:
       0: aload_0
       1: invokespecial #1                  // Method java/lang/Object."<init>":()V
       4: aload_1
       5: ifnull        23
       8: aload_1
       9: invokevirtual #11                 // Method java/lang/String.length:()I
      12: ifle          23
      15: aload_0
      16: aload_1
      17: putfield      #4                  // Field recordTerminator:Ljava/lang/String;
      20: goto          29
      23: aload_0
      24: ldc           #3                  // String \n
      26: putfield      #4                  // Field recordTerminator:Ljava/lang/String;
      29: aload_2
      30: ifnull        48
      33: aload_2
      34: invokevirtual #11                 // Method java/lang/String.length:()I
      37: ifle          48
      40: aload_0
      41: aload_2
      42: putfield      #6                  // Field fieldDelimiter:Ljava/lang/String;
      45: goto          54
      48: aload_0
      49: ldc           #5                  // String \\,
      51: putfield      #6                  // Field fieldDelimiter:Ljava/lang/String;
      54: aload_3
      55: ifnull        73
      58: aload_3
      59: invokevirtual #11                 // Method java/lang/String.length:()I
      62: ifle          73
      65: aload_0
      66: aload_3
      67: putfield      #8                  // Field escapeSequence:Ljava/lang/String;
      70: goto          79
      73: aload_0
      74: ldc           #7                  // String
      76: putfield      #8                  // Field escapeSequence:Ljava/lang/String;
      79: aload         4
      81: ifnull        101
      84: aload         4
      86: invokevirtual #11                 // Method java/lang/String.length:()I
      89: ifle          101
      92: aload_0
      93: aload         4
      95: putfield      #10                 // Field quote:Ljava/lang/String;
      98: goto          107
     101: aload_0
     102: ldc           #9                  // String \'
     104: putfield      #10                 // Field quote:Ljava/lang/String;
     107: return

  public java.lang.String getRecordTerminator();
    Code:
       0: aload_0
       1: getfield      #4                  // Field recordTerminator:Ljava/lang/String;
       4: areturn

  public void setRecordTerminator(java.lang.String);
    Code:
       0: aload_0
       1: aload_1
       2: putfield      #4                  // Field recordTerminator:Ljava/lang/String;
       5: return

  public java.lang.String getFieldDelimiter();
    Code:
       0: aload_0
       1: getfield      #6                  // Field fieldDelimiter:Ljava/lang/String;
       4: areturn

  public void setFieldDelimiter(java.lang.String);
    Code:
       0: aload_0
       1: aload_1
       2: putfield      #6                  // Field fieldDelimiter:Ljava/lang/String;
       5: return

  public java.lang.String getEscapeSequence();
    Code:
       0: aload_0
       1: getfield      #8                  // Field escapeSequence:Ljava/lang/String;
       4: areturn

  public void setEscapeSequence(java.lang.String);
    Code:
       0: aload_0
       1: aload_1
       2: putfield      #8                  // Field escapeSequence:Ljava/lang/String;
       5: return

  public java.lang.String getQuote();
    Code:
       0: aload_0
       1: getfield      #10                 // Field quote:Ljava/lang/String;
       4: areturn

  public void setQuote(java.lang.String);
    Code:
       0: aload_0
       1: aload_1
       2: putfield      #10                 // Field quote:Ljava/lang/String;
       5: return

  static {};
    Code:
       0: new           #2                  // class org/hpccsystems/ws/client/utils/DelimitedDataOptions
       3: dup
       4: invokespecial #12                 // Method "<init>":()V
       7: putstatic     #13                 // Field DefaultCSVDataOptions:Lorg/hpccsystems/ws/client/utils/DelimitedDataOptions;
      10: return
}
