Compiled from "PooledConnectionFactory.java"
class org.apache.activemq.jms.pool.PooledConnectionFactory$2 implements javax.jms.ConnectionFactory {
  final javax.jms.ConnectionFactory val$toUse;

  final org.apache.activemq.jms.pool.PooledConnectionFactory this$0;

  org.apache.activemq.jms.pool.PooledConnectionFactory$2(org.apache.activemq.jms.pool.PooledConnectionFactory, javax.jms.ConnectionFactory);
    Code:
       0: aload_0
       1: aload_1
       2: putfield      #1                  // Field this$0:Lorg/apache/activemq/jms/pool/PooledConnectionFactory;
       5: aload_0
       6: aload_2
       7: putfield      #2                  // Field val$toUse:Ljavax/jms/ConnectionFactory;
      10: aload_0
      11: invokespecial #3                  // Method java/lang/Object."<init>":()V
      14: return

  public javax.jms.Connection createConnection() throws javax.jms.JMSException;
    Code:
       0: aload_0
       1: getfield      #2                  // Field val$toUse:Ljavax/jms/ConnectionFactory;
       4: checkcast     #4                  // class javax/jms/XAConnectionFactory
       7: invokeinterface #5,  1            // InterfaceMethod javax/jms/XAConnectionFactory.createXAConnection:()Ljavax/jms/XAConnection;
      12: areturn

  public javax.jms.Connection createConnection(java.lang.String, java.lang.String) throws javax.jms.JMSException;
    Code:
       0: aload_0
       1: getfield      #2                  // Field val$toUse:Ljavax/jms/ConnectionFactory;
       4: checkcast     #4                  // class javax/jms/XAConnectionFactory
       7: aload_1
       8: aload_2
       9: invokeinterface #6,  3            // InterfaceMethod javax/jms/XAConnectionFactory.createXAConnection:(Ljava/lang/String;Ljava/lang/String;)Ljavax/jms/XAConnection;
      14: areturn
}
