Compiled from "MutableTypeToInstanceMap.java"
final class com.google.common.reflect.MutableTypeToInstanceMap$UnmodifiableEntry<K, V> extends com.google.common.collect.ForwardingMapEntry<K, V> {
  private final java.util.Map$Entry<K, V> delegate;

  static <K, V> java.util.Set<java.util.Map$Entry<K, V>> transformEntries(java.util.Set<java.util.Map$Entry<K, V>>);
    Code:
       0: new           #3                  // class com/google/common/reflect/MutableTypeToInstanceMap$UnmodifiableEntry$1
       3: dup
       4: aload_0
       5: invokespecial #4                  // Method com/google/common/reflect/MutableTypeToInstanceMap$UnmodifiableEntry$1."<init>":(Ljava/util/Set;)V
       8: areturn

  private static <K, V> java.util.Iterator<java.util.Map$Entry<K, V>> transformEntries(java.util.Iterator<java.util.Map$Entry<K, V>>);
    Code:
       0: aload_0
       1: new           #5                  // class com/google/common/reflect/MutableTypeToInstanceMap$UnmodifiableEntry$2
       4: dup
       5: invokespecial #6                  // Method com/google/common/reflect/MutableTypeToInstanceMap$UnmodifiableEntry$2."<init>":()V
       8: invokestatic  #7                  // Method com/google/common/collect/Iterators.transform:(Ljava/util/Iterator;Lcom/google/common/base/Function;)Ljava/util/Iterator;
      11: areturn

  private com.google.common.reflect.MutableTypeToInstanceMap$UnmodifiableEntry(java.util.Map$Entry<K, V>);
    Code:
       0: aload_0
       1: invokespecial #8                  // Method com/google/common/collect/ForwardingMapEntry."<init>":()V
       4: aload_0
       5: aload_1
       6: invokestatic  #9                  // Method com/google/common/base/Preconditions.checkNotNull:(Ljava/lang/Object;)Ljava/lang/Object;
       9: checkcast     #10                 // class java/util/Map$Entry
      12: putfield      #11                 // Field delegate:Ljava/util/Map$Entry;
      15: return

  protected java.util.Map$Entry<K, V> delegate();
    Code:
       0: aload_0
       1: getfield      #11                 // Field delegate:Ljava/util/Map$Entry;
       4: areturn

  public V setValue(V);
    Code:
       0: new           #12                 // class java/lang/UnsupportedOperationException
       3: dup
       4: invokespecial #13                 // Method java/lang/UnsupportedOperationException."<init>":()V
       7: athrow

  protected java.lang.Object delegate();
    Code:
       0: aload_0
       1: invokevirtual #14                 // Method delegate:()Ljava/util/Map$Entry;
       4: areturn

  static java.util.Iterator access$000(java.util.Iterator);
    Code:
       0: aload_0
       1: invokestatic  #2                  // Method transformEntries:(Ljava/util/Iterator;)Ljava/util/Iterator;
       4: areturn

  com.google.common.reflect.MutableTypeToInstanceMap$UnmodifiableEntry(java.util.Map$Entry, com.google.common.reflect.MutableTypeToInstanceMap$1);
    Code:
       0: aload_0
       1: aload_1
       2: invokespecial #1                  // Method "<init>":(Ljava/util/Map$Entry;)V
       5: return
}
