Compiled from "EnumEntrySyntheticClassDescriptor.java"
class kotlin.reflect.jvm.internal.impl.descriptors.impl.EnumEntrySyntheticClassDescriptor$EnumEntryScope$4 extends kotlin.reflect.jvm.internal.impl.resolve.NonReportingOverrideStrategy {
  final java.util.Set val$result;

  final kotlin.reflect.jvm.internal.impl.descriptors.impl.EnumEntrySyntheticClassDescriptor$EnumEntryScope this$1;

  kotlin.reflect.jvm.internal.impl.descriptors.impl.EnumEntrySyntheticClassDescriptor$EnumEntryScope$4(kotlin.reflect.jvm.internal.impl.descriptors.impl.EnumEntrySyntheticClassDescriptor$EnumEntryScope, java.util.Set);
    Code:
       0: aload_0
       1: aload_1
       2: putfield      #7                  // Field this$1:Lkotlin/reflect/jvm/internal/impl/descriptors/impl/EnumEntrySyntheticClassDescriptor$EnumEntryScope;
       5: aload_0
       6: aload_2
       7: putfield      #8                  // Field val$result:Ljava/util/Set;
      10: aload_0
      11: invokespecial #9                  // Method kotlin/reflect/jvm/internal/impl/resolve/NonReportingOverrideStrategy."<init>":()V
      14: return

  public void addFakeOverride(kotlin.reflect.jvm.internal.impl.descriptors.CallableMemberDescriptor);
    Code:
       0: aload_1
       1: aconst_null
       2: invokestatic  #10                 // Method kotlin/reflect/jvm/internal/impl/resolve/OverridingUtil.resolveUnknownVisibilityForMember:(Lkotlin/reflect/jvm/internal/impl/descriptors/CallableMemberDescriptor;Lkotlin/jvm/functions/Function1;)V
       5: aload_0
       6: getfield      #8                  // Field val$result:Ljava/util/Set;
       9: aload_1
      10: invokeinterface #11,  2           // InterfaceMethod java/util/Set.add:(Ljava/lang/Object;)Z
      15: pop
      16: return

  protected void conflict(kotlin.reflect.jvm.internal.impl.descriptors.CallableMemberDescriptor, kotlin.reflect.jvm.internal.impl.descriptors.CallableMemberDescriptor);
    Code:
       0: return
}
