Compiled from "SelenoidCapabilitiesParser.java"
public class ru.sbtqa.tag.pagefactory.web.capabilities.SelenoidCapabilitiesParser implements ru.sbtqa.tag.pagefactory.web.capabilities.CapabilitiesParser {
  private static final org.slf4j.Logger LOG;

  private static final ru.sbtqa.tag.pagefactory.web.properties.WebConfiguration PROPERTIES;

  private static final java.lang.String VIDEONAME_FORMAT;

  private final org.openqa.selenium.remote.DesiredCapabilities capabilities;

  private static int[] $SWITCH_TABLE$ru$sbtqa$tag$pagefactory$web$support$BrowserName;

  static {};
    Code:
       0: ldc           #1                  // class ru/sbtqa/tag/pagefactory/web/capabilities/SelenoidCapabilitiesParser
       2: invokestatic  #20                 // Method org/slf4j/LoggerFactory.getLogger:(Ljava/lang/Class;)Lorg/slf4j/Logger;
       5: putstatic     #26                 // Field LOG:Lorg/slf4j/Logger;
       8: invokestatic  #28                 // InterfaceMethod ru/sbtqa/tag/pagefactory/web/properties/WebConfiguration.create:()Lru/sbtqa/tag/pagefactory/web/properties/WebConfiguration;
      11: putstatic     #34                 // Field PROPERTIES:Lru/sbtqa/tag/pagefactory/web/properties/WebConfiguration;
      14: new           #36                 // class java/lang/StringBuilder
      17: dup
      18: new           #38                 // class java/text/SimpleDateFormat
      21: dup
      22: ldc           #40                 // String dd.MM.yyyy\'_\'hh:mm:ss
      24: invokespecial #42                 // Method java/text/SimpleDateFormat."<init>":(Ljava/lang/String;)V
      27: new           #46                 // class java/util/Date
      30: dup
      31: invokespecial #48                 // Method java/util/Date."<init>":()V
      34: invokevirtual #50                 // Method java/text/SimpleDateFormat.format:(Ljava/util/Date;)Ljava/lang/String;
      37: invokestatic  #54                 // Method java/lang/String.valueOf:(Ljava/lang/Object;)Ljava/lang/String;
      40: invokespecial #60                 // Method java/lang/StringBuilder."<init>":(Ljava/lang/String;)V
      43: bipush        95
      45: invokevirtual #61                 // Method java/lang/StringBuilder.append:(C)Ljava/lang/StringBuilder;
      48: invokestatic  #65                 // Method java/util/UUID.randomUUID:()Ljava/util/UUID;
      51: invokevirtual #71                 // Method java/util/UUID.toString:()Ljava/lang/String;
      54: invokevirtual #75                 // Method java/lang/StringBuilder.append:(Ljava/lang/String;)Ljava/lang/StringBuilder;
      57: ldc           #78                 // String _%s
      59: invokevirtual #75                 // Method java/lang/StringBuilder.append:(Ljava/lang/String;)Ljava/lang/StringBuilder;
      62: invokevirtual #80                 // Method java/lang/StringBuilder.toString:()Ljava/lang/String;
      65: putstatic     #81                 // Field VIDEONAME_FORMAT:Ljava/lang/String;
      68: return

  public ru.sbtqa.tag.pagefactory.web.capabilities.SelenoidCapabilitiesParser();
    Code:
       0: aload_0
       1: invokespecial #85                 // Method java/lang/Object."<init>":()V
       4: aload_0
       5: new           #86                 // class org/openqa/selenium/remote/DesiredCapabilities
       8: dup
       9: invokespecial #88                 // Method org/openqa/selenium/remote/DesiredCapabilities."<init>":()V
      12: putfield      #89                 // Field capabilities:Lorg/openqa/selenium/remote/DesiredCapabilities;
      15: return

  public org.openqa.selenium.remote.DesiredCapabilities parse();
    Code:
       0: aload_0
       1: getstatic     #34                 // Field PROPERTIES:Lru/sbtqa/tag/pagefactory/web/properties/WebConfiguration;
       4: invokeinterface #96,  1           // InterfaceMethod ru/sbtqa/tag/pagefactory/web/properties/WebConfiguration.getSelenoidBrowserVersion:()Ljava/lang/String;
       9: invokespecial #99                 // Method setVersion:(Ljava/lang/String;)V
      12: aload_0
      13: ldc           #102                // String enableVNC
      15: getstatic     #34                 // Field PROPERTIES:Lru/sbtqa/tag/pagefactory/web/properties/WebConfiguration;
      18: invokeinterface #104,  1          // InterfaceMethod ru/sbtqa/tag/pagefactory/web/properties/WebConfiguration.getSelenoidEnableVNC:()Z
      23: invokespecial #108                // Method setCapability:(Ljava/lang/String;Z)V
      26: aload_0
      27: ldc           #112                // String screenResolution
      29: getstatic     #34                 // Field PROPERTIES:Lru/sbtqa/tag/pagefactory/web/properties/WebConfiguration;
      32: invokeinterface #114,  1          // InterfaceMethod ru/sbtqa/tag/pagefactory/web/properties/WebConfiguration.getSelenoidScreenResolution:()Ljava/lang/String;
      37: invokespecial #117                // Method setCapability:(Ljava/lang/String;Ljava/lang/String;)V
      40: aload_0
      41: ldc           #120                // String enableVideo
      43: getstatic     #34                 // Field PROPERTIES:Lru/sbtqa/tag/pagefactory/web/properties/WebConfiguration;
      46: invokeinterface #122,  1          // InterfaceMethod ru/sbtqa/tag/pagefactory/web/properties/WebConfiguration.getSelenoidEnableVideo:()Z
      51: invokespecial #108                // Method setCapability:(Ljava/lang/String;Z)V
      54: aload_0
      55: ldc           #125                // String videoName
      57: getstatic     #34                 // Field PROPERTIES:Lru/sbtqa/tag/pagefactory/web/properties/WebConfiguration;
      60: invokeinterface #127,  1          // InterfaceMethod ru/sbtqa/tag/pagefactory/web/properties/WebConfiguration.getSelenoidVideoName:()Ljava/lang/String;
      65: getstatic     #81                 // Field VIDEONAME_FORMAT:Ljava/lang/String;
      68: invokespecial #130                // Method setCapability:(Ljava/lang/String;Ljava/lang/String;Ljava/lang/String;)V
      71: aload_0
      72: ldc           #133                // String videoScreenSize
      74: getstatic     #34                 // Field PROPERTIES:Lru/sbtqa/tag/pagefactory/web/properties/WebConfiguration;
      77: invokeinterface #135,  1          // InterfaceMethod ru/sbtqa/tag/pagefactory/web/properties/WebConfiguration.getSelenoidVideoScreenSize:()Ljava/lang/String;
      82: invokespecial #117                // Method setCapability:(Ljava/lang/String;Ljava/lang/String;)V
      85: aload_0
      86: ldc           #138                // String videoFrameRate
      88: getstatic     #34                 // Field PROPERTIES:Lru/sbtqa/tag/pagefactory/web/properties/WebConfiguration;
      91: invokeinterface #140,  1          // InterfaceMethod ru/sbtqa/tag/pagefactory/web/properties/WebConfiguration.getSelenoidVideoFrameRate:()Ljava/lang/String;
      96: invokespecial #117                // Method setCapability:(Ljava/lang/String;Ljava/lang/String;)V
      99: getstatic     #34                 // Field PROPERTIES:Lru/sbtqa/tag/pagefactory/web/properties/WebConfiguration;
     102: invokeinterface #143,  1          // InterfaceMethod ru/sbtqa/tag/pagefactory/web/properties/WebConfiguration.getSelenoidNameOfTests:()Ljava/lang/String;
     107: invokevirtual #146                // Method java/lang/String.trim:()Ljava/lang/String;
     110: invokevirtual #149                // Method java/lang/String.isEmpty:()Z
     113: ifeq          134
     116: invokestatic  #152                // Method ru/sbtqa/tag/pagefactory/environment/Environment.getScenario:()Lcucumber/api/Scenario;
     119: ifnull        134
     122: invokestatic  #152                // Method ru/sbtqa/tag/pagefactory/environment/Environment.getScenario:()Lcucumber/api/Scenario;
     125: invokeinterface #158,  1          // InterfaceMethod cucumber/api/Scenario.getName:()Ljava/lang/String;
     130: astore_1
     131: goto          143
     134: getstatic     #34                 // Field PROPERTIES:Lru/sbtqa/tag/pagefactory/web/properties/WebConfiguration;
     137: invokeinterface #143,  1          // InterfaceMethod ru/sbtqa/tag/pagefactory/web/properties/WebConfiguration.getSelenoidNameOfTests:()Ljava/lang/String;
     142: astore_1
     143: aload_0
     144: ldc           #163                // String name
     146: aload_1
     147: invokespecial #117                // Method setCapability:(Ljava/lang/String;Ljava/lang/String;)V
     150: aload_0
     151: ldc           #165                // String timeZone
     153: getstatic     #34                 // Field PROPERTIES:Lru/sbtqa/tag/pagefactory/web/properties/WebConfiguration;
     156: invokeinterface #167,  1          // InterfaceMethod ru/sbtqa/tag/pagefactory/web/properties/WebConfiguration.getSelenoidTimeZone:()Ljava/lang/String;
     161: invokespecial #117                // Method setCapability:(Ljava/lang/String;Ljava/lang/String;)V
     164: aload_0
     165: ldc           #170                // String hostsEntries
     167: getstatic     #34                 // Field PROPERTIES:Lru/sbtqa/tag/pagefactory/web/properties/WebConfiguration;
     170: invokeinterface #172,  1          // InterfaceMethod ru/sbtqa/tag/pagefactory/web/properties/WebConfiguration.getSelenoidHostEntries:()Ljava/lang/String;
     175: invokespecial #117                // Method setCapability:(Ljava/lang/String;Ljava/lang/String;)V
     178: aload_0
     179: ldc           #175                // String applicationContainers
     181: getstatic     #34                 // Field PROPERTIES:Lru/sbtqa/tag/pagefactory/web/properties/WebConfiguration;
     184: invokeinterface #177,  1          // InterfaceMethod ru/sbtqa/tag/pagefactory/web/properties/WebConfiguration.getSelenoidApplicationContainers:()Ljava/lang/String;
     189: invokespecial #117                // Method setCapability:(Ljava/lang/String;Ljava/lang/String;)V
     192: aload_0
     193: ldc           #180                // String labels
     195: getstatic     #34                 // Field PROPERTIES:Lru/sbtqa/tag/pagefactory/web/properties/WebConfiguration;
     198: invokeinterface #182,  1          // InterfaceMethod ru/sbtqa/tag/pagefactory/web/properties/WebConfiguration.getSelenoidContainerLables:()Ljava/lang/String;
     203: invokespecial #117                // Method setCapability:(Ljava/lang/String;Ljava/lang/String;)V
     206: aload_0
     207: ldc           #185                // String sessionTimeout
     209: getstatic     #34                 // Field PROPERTIES:Lru/sbtqa/tag/pagefactory/web/properties/WebConfiguration;
     212: invokeinterface #187,  1          // InterfaceMethod ru/sbtqa/tag/pagefactory/web/properties/WebConfiguration.getSelenoidSessionTimeout:()Ljava/lang/String;
     217: invokespecial #117                // Method setCapability:(Ljava/lang/String;Ljava/lang/String;)V
     220: aload_0
     221: invokespecial #190                // Method setBrowserDefaultCapabilities:()V
     224: aload_0
     225: getfield      #89                 // Field capabilities:Lorg/openqa/selenium/remote/DesiredCapabilities;
     228: areturn

  private void setCapability(java.lang.String, java.lang.String, java.lang.String);
    Code:
       0: aload_2
       1: invokevirtual #149                // Method java/lang/String.isEmpty:()Z
       4: ifne          30
       7: aload_0
       8: getfield      #89                 // Field capabilities:Lorg/openqa/selenium/remote/DesiredCapabilities;
      11: aload_1
      12: aload_3
      13: iconst_1
      14: anewarray     #3                  // class java/lang/Object
      17: dup
      18: iconst_0
      19: aload_2
      20: aastore
      21: invokestatic  #195                // Method java/lang/String.format:(Ljava/lang/String;[Ljava/lang/Object;)Ljava/lang/String;
      24: invokevirtual #198                // Method org/openqa/selenium/remote/DesiredCapabilities.setCapability:(Ljava/lang/String;Ljava/lang/String;)V
      27: goto          41
      30: getstatic     #26                 // Field LOG:Lorg/slf4j/Logger;
      33: ldc           #199                // String Capability \"{}\" for Selenoid isn\'t set. Using default capability.
      35: aload_1
      36: invokeinterface #201,  3          // InterfaceMethod org/slf4j/Logger.info:(Ljava/lang/String;Ljava/lang/Object;)V
      41: return

  private void setCapability(java.lang.String, java.lang.String);
    Code:
       0: aload_0
       1: aload_1
       2: aload_2
       3: ldc           #209                // String %s
       5: invokespecial #130                // Method setCapability:(Ljava/lang/String;Ljava/lang/String;Ljava/lang/String;)V
       8: return

  private void setCapability(java.lang.String, boolean);
    Code:
       0: aload_0
       1: getfield      #89                 // Field capabilities:Lorg/openqa/selenium/remote/DesiredCapabilities;
       4: aload_1
       5: iload_2
       6: invokevirtual #211                // Method org/openqa/selenium/remote/DesiredCapabilities.setCapability:(Ljava/lang/String;Z)V
       9: return

  private void setVersion(java.lang.String);
    Code:
       0: aload_1
       1: invokevirtual #149                // Method java/lang/String.isEmpty:()Z
       4: ifne          18
       7: aload_0
       8: getfield      #89                 // Field capabilities:Lorg/openqa/selenium/remote/DesiredCapabilities;
      11: aload_1
      12: invokevirtual #213                // Method org/openqa/selenium/remote/DesiredCapabilities.setVersion:(Ljava/lang/String;)V
      15: goto          28
      18: getstatic     #26                 // Field LOG:Lorg/slf4j/Logger;
      21: ldc           #214                // String Capability \"browserVersion\" for Selenoid isn\'t set. Using default capability.
      23: invokeinterface #216,  2          // InterfaceMethod org/slf4j/Logger.info:(Ljava/lang/String;)V
      28: return

  private void setBrowserDefaultCapabilities();
    Code:
       0: invokestatic  #218                // Method $SWITCH_TABLE$ru$sbtqa$tag$pagefactory$web$support$BrowserName:()[I
       3: invokestatic  #221                // Method ru/sbtqa/tag/pagefactory/web/environment/WebEnvironment.getBrowserName:()Lru/sbtqa/tag/pagefactory/web/support/BrowserName;
       6: invokevirtual #227                // Method ru/sbtqa/tag/pagefactory/web/support/BrowserName.ordinal:()I
       9: iaload
      10: lookupswitch  { // 2
                     1: 43
                     6: 36
               default: 50
          }
      36: aload_0
      37: invokespecial #233                // Method handleOpera:()V
      40: goto          50
      43: aload_0
      44: invokespecial #236                // Method handleIe:()V
      47: goto          50
      50: return

  private void handleOpera();
    Code:
       0: new           #239                // class java/util/HashMap
       3: dup
       4: invokespecial #241                // Method java/util/HashMap."<init>":()V
       7: astore_1
       8: aload_1
       9: ldc           #242                // String binary
      11: ldc           #244                // String /usr/bin/opera
      13: invokeinterface #246,  3          // InterfaceMethod java/util/Map.put:(Ljava/lang/Object;Ljava/lang/Object;)Ljava/lang/Object;
      18: pop
      19: aload_0
      20: getfield      #89                 // Field capabilities:Lorg/openqa/selenium/remote/DesiredCapabilities;
      23: ldc           #252                // String operaOptions
      25: aload_1
      26: invokevirtual #254                // Method org/openqa/selenium/remote/DesiredCapabilities.setCapability:(Ljava/lang/String;Ljava/lang/Object;)V
      29: return

  private void handleIe();
    Code:
       0: aload_0
       1: getfield      #89                 // Field capabilities:Lorg/openqa/selenium/remote/DesiredCapabilities;
       4: ldc_w         #259                // String ie.usePerProcessProxy
       7: iconst_1
       8: invokevirtual #211                // Method org/openqa/selenium/remote/DesiredCapabilities.setCapability:(Ljava/lang/String;Z)V
      11: aload_0
      12: getfield      #89                 // Field capabilities:Lorg/openqa/selenium/remote/DesiredCapabilities;
      15: ldc_w         #261                // String ie.browserCommandLineSwitches
      18: ldc_w         #263                // String -private
      21: invokevirtual #198                // Method org/openqa/selenium/remote/DesiredCapabilities.setCapability:(Ljava/lang/String;Ljava/lang/String;)V
      24: aload_0
      25: getfield      #89                 // Field capabilities:Lorg/openqa/selenium/remote/DesiredCapabilities;
      28: ldc_w         #265                // String ie.ensureCleanSession
      31: iconst_1
      32: invokevirtual #211                // Method org/openqa/selenium/remote/DesiredCapabilities.setCapability:(Ljava/lang/String;Z)V
      35: aload_0
      36: getfield      #89                 // Field capabilities:Lorg/openqa/selenium/remote/DesiredCapabilities;
      39: ldc_w         #267                // String requireWindowFocus
      42: iconst_0
      43: invokevirtual #211                // Method org/openqa/selenium/remote/DesiredCapabilities.setCapability:(Ljava/lang/String;Z)V
      46: return

  static int[] $SWITCH_TABLE$ru$sbtqa$tag$pagefactory$web$support$BrowserName();
    Code:
       0: getstatic     #269                // Field $SWITCH_TABLE$ru$sbtqa$tag$pagefactory$web$support$BrowserName:[I
       3: dup
       4: ifnull        8
       7: areturn
       8: pop
       9: invokestatic  #271                // Method ru/sbtqa/tag/pagefactory/web/support/BrowserName.values:()[Lru/sbtqa/tag/pagefactory/web/support/BrowserName;
      12: arraylength
      13: newarray       int
      15: astore_0
      16: aload_0
      17: getstatic     #275                // Field ru/sbtqa/tag/pagefactory/web/support/BrowserName.CHROME:Lru/sbtqa/tag/pagefactory/web/support/BrowserName;
      20: invokevirtual #227                // Method ru/sbtqa/tag/pagefactory/web/support/BrowserName.ordinal:()I
      23: iconst_4
      24: iastore
      25: goto          29
      28: pop
      29: aload_0
      30: getstatic     #279                // Field ru/sbtqa/tag/pagefactory/web/support/BrowserName.EDGE:Lru/sbtqa/tag/pagefactory/web/support/BrowserName;
      33: invokevirtual #227                // Method ru/sbtqa/tag/pagefactory/web/support/BrowserName.ordinal:()I
      36: bipush        8
      38: iastore
      39: goto          43
      42: pop
      43: aload_0
      44: getstatic     #282                // Field ru/sbtqa/tag/pagefactory/web/support/BrowserName.FIREFOX:Lru/sbtqa/tag/pagefactory/web/support/BrowserName;
      47: invokevirtual #227                // Method ru/sbtqa/tag/pagefactory/web/support/BrowserName.ordinal:()I
      50: iconst_5
      51: iastore
      52: goto          56
      55: pop
      56: aload_0
      57: getstatic     #285                // Field ru/sbtqa/tag/pagefactory/web/support/BrowserName.IE:Lru/sbtqa/tag/pagefactory/web/support/BrowserName;
      60: invokevirtual #227                // Method ru/sbtqa/tag/pagefactory/web/support/BrowserName.ordinal:()I
      63: iconst_1
      64: iastore
      65: goto          69
      68: pop
      69: aload_0
      70: getstatic     #288                // Field ru/sbtqa/tag/pagefactory/web/support/BrowserName.IEXPLORE:Lru/sbtqa/tag/pagefactory/web/support/BrowserName;
      73: invokevirtual #227                // Method ru/sbtqa/tag/pagefactory/web/support/BrowserName.ordinal:()I
      76: iconst_3
      77: iastore
      78: goto          82
      81: pop
      82: aload_0
      83: getstatic     #291                // Field ru/sbtqa/tag/pagefactory/web/support/BrowserName.INTERNET_EXPLORER:Lru/sbtqa/tag/pagefactory/web/support/BrowserName;
      86: invokevirtual #227                // Method ru/sbtqa/tag/pagefactory/web/support/BrowserName.ordinal:()I
      89: iconst_2
      90: iastore
      91: goto          95
      94: pop
      95: aload_0
      96: getstatic     #294                // Field ru/sbtqa/tag/pagefactory/web/support/BrowserName.OPERA:Lru/sbtqa/tag/pagefactory/web/support/BrowserName;
      99: invokevirtual #227                // Method ru/sbtqa/tag/pagefactory/web/support/BrowserName.ordinal:()I
     102: bipush        6
     104: iastore
     105: goto          109
     108: pop
     109: aload_0
     110: getstatic     #297                // Field ru/sbtqa/tag/pagefactory/web/support/BrowserName.SAFARI:Lru/sbtqa/tag/pagefactory/web/support/BrowserName;
     113: invokevirtual #227                // Method ru/sbtqa/tag/pagefactory/web/support/BrowserName.ordinal:()I
     116: bipush        7
     118: iastore
     119: goto          123
     122: pop
     123: aload_0
     124: dup
     125: putstatic     #269                // Field $SWITCH_TABLE$ru$sbtqa$tag$pagefactory$web$support$BrowserName:[I
     128: areturn
    Exception table:
       from    to  target type
          16    25    28   Class java/lang/NoSuchFieldError
          29    39    42   Class java/lang/NoSuchFieldError
          43    52    55   Class java/lang/NoSuchFieldError
          56    65    68   Class java/lang/NoSuchFieldError
          69    78    81   Class java/lang/NoSuchFieldError
          82    91    94   Class java/lang/NoSuchFieldError
          95   105   108   Class java/lang/NoSuchFieldError
         109   119   122   Class java/lang/NoSuchFieldError
}
