Compiled from "AbstractCompositeHashFunction.java"
class com.google.common.hash.AbstractCompositeHashFunction$1 implements com.google.common.hash.Hasher {
  final com.google.common.hash.Hasher[] val$hashers;

  final com.google.common.hash.AbstractCompositeHashFunction this$0;

  com.google.common.hash.AbstractCompositeHashFunction$1(com.google.common.hash.AbstractCompositeHashFunction, com.google.common.hash.Hasher[]);
    Code:
       0: aload_0
       1: aload_1
       2: putfield      #1                  // Field this$0:Lcom/google/common/hash/AbstractCompositeHashFunction;
       5: aload_0
       6: aload_2
       7: putfield      #2                  // Field val$hashers:[Lcom/google/common/hash/Hasher;
      10: aload_0
      11: invokespecial #3                  // Method java/lang/Object."<init>":()V
      14: return

  public com.google.common.hash.Hasher putByte(byte);
    Code:
       0: aload_0
       1: getfield      #2                  // Field val$hashers:[Lcom/google/common/hash/Hasher;
       4: astore_2
       5: aload_2
       6: arraylength
       7: istore_3
       8: iconst_0
       9: istore        4
      11: iload         4
      13: iload_3
      14: if_icmpge     38
      17: aload_2
      18: iload         4
      20: aaload
      21: astore        5
      23: aload         5
      25: iload_1
      26: invokeinterface #4,  2            // InterfaceMethod com/google/common/hash/Hasher.putByte:(B)Lcom/google/common/hash/Hasher;
      31: pop
      32: iinc          4, 1
      35: goto          11
      38: aload_0
      39: areturn

  public com.google.common.hash.Hasher putBytes(byte[]);
    Code:
       0: aload_0
       1: getfield      #2                  // Field val$hashers:[Lcom/google/common/hash/Hasher;
       4: astore_2
       5: aload_2
       6: arraylength
       7: istore_3
       8: iconst_0
       9: istore        4
      11: iload         4
      13: iload_3
      14: if_icmpge     38
      17: aload_2
      18: iload         4
      20: aaload
      21: astore        5
      23: aload         5
      25: aload_1
      26: invokeinterface #5,  2            // InterfaceMethod com/google/common/hash/Hasher.putBytes:([B)Lcom/google/common/hash/Hasher;
      31: pop
      32: iinc          4, 1
      35: goto          11
      38: aload_0
      39: areturn

  public com.google.common.hash.Hasher putBytes(byte[], int, int);
    Code:
       0: aload_0
       1: getfield      #2                  // Field val$hashers:[Lcom/google/common/hash/Hasher;
       4: astore        4
       6: aload         4
       8: arraylength
       9: istore        5
      11: iconst_0
      12: istore        6
      14: iload         6
      16: iload         5
      18: if_icmpge     45
      21: aload         4
      23: iload         6
      25: aaload
      26: astore        7
      28: aload         7
      30: aload_1
      31: iload_2
      32: iload_3
      33: invokeinterface #6,  4            // InterfaceMethod com/google/common/hash/Hasher.putBytes:([BII)Lcom/google/common/hash/Hasher;
      38: pop
      39: iinc          6, 1
      42: goto          14
      45: aload_0
      46: areturn

  public com.google.common.hash.Hasher putBytes(java.nio.ByteBuffer);
    Code:
       0: aload_1
       1: invokevirtual #7                  // Method java/nio/ByteBuffer.position:()I
       4: istore_2
       5: aload_0
       6: getfield      #2                  // Field val$hashers:[Lcom/google/common/hash/Hasher;
       9: astore_3
      10: aload_3
      11: arraylength
      12: istore        4
      14: iconst_0
      15: istore        5
      17: iload         5
      19: iload         4
      21: if_icmpge     51
      24: aload_3
      25: iload         5
      27: aaload
      28: astore        6
      30: aload_1
      31: iload_2
      32: invokevirtual #8                  // Method java/nio/ByteBuffer.position:(I)Ljava/nio/Buffer;
      35: pop
      36: aload         6
      38: aload_1
      39: invokeinterface #9,  2            // InterfaceMethod com/google/common/hash/Hasher.putBytes:(Ljava/nio/ByteBuffer;)Lcom/google/common/hash/Hasher;
      44: pop
      45: iinc          5, 1
      48: goto          17
      51: aload_0
      52: areturn

  public com.google.common.hash.Hasher putShort(short);
    Code:
       0: aload_0
       1: getfield      #2                  // Field val$hashers:[Lcom/google/common/hash/Hasher;
       4: astore_2
       5: aload_2
       6: arraylength
       7: istore_3
       8: iconst_0
       9: istore        4
      11: iload         4
      13: iload_3
      14: if_icmpge     38
      17: aload_2
      18: iload         4
      20: aaload
      21: astore        5
      23: aload         5
      25: iload_1
      26: invokeinterface #10,  2           // InterfaceMethod com/google/common/hash/Hasher.putShort:(S)Lcom/google/common/hash/Hasher;
      31: pop
      32: iinc          4, 1
      35: goto          11
      38: aload_0
      39: areturn

  public com.google.common.hash.Hasher putInt(int);
    Code:
       0: aload_0
       1: getfield      #2                  // Field val$hashers:[Lcom/google/common/hash/Hasher;
       4: astore_2
       5: aload_2
       6: arraylength
       7: istore_3
       8: iconst_0
       9: istore        4
      11: iload         4
      13: iload_3
      14: if_icmpge     38
      17: aload_2
      18: iload         4
      20: aaload
      21: astore        5
      23: aload         5
      25: iload_1
      26: invokeinterface #11,  2           // InterfaceMethod com/google/common/hash/Hasher.putInt:(I)Lcom/google/common/hash/Hasher;
      31: pop
      32: iinc          4, 1
      35: goto          11
      38: aload_0
      39: areturn

  public com.google.common.hash.Hasher putLong(long);
    Code:
       0: aload_0
       1: getfield      #2                  // Field val$hashers:[Lcom/google/common/hash/Hasher;
       4: astore_3
       5: aload_3
       6: arraylength
       7: istore        4
       9: iconst_0
      10: istore        5
      12: iload         5
      14: iload         4
      16: if_icmpge     40
      19: aload_3
      20: iload         5
      22: aaload
      23: astore        6
      25: aload         6
      27: lload_1
      28: invokeinterface #12,  3           // InterfaceMethod com/google/common/hash/Hasher.putLong:(J)Lcom/google/common/hash/Hasher;
      33: pop
      34: iinc          5, 1
      37: goto          12
      40: aload_0
      41: areturn

  public com.google.common.hash.Hasher putFloat(float);
    Code:
       0: aload_0
       1: getfield      #2                  // Field val$hashers:[Lcom/google/common/hash/Hasher;
       4: astore_2
       5: aload_2
       6: arraylength
       7: istore_3
       8: iconst_0
       9: istore        4
      11: iload         4
      13: iload_3
      14: if_icmpge     38
      17: aload_2
      18: iload         4
      20: aaload
      21: astore        5
      23: aload         5
      25: fload_1
      26: invokeinterface #13,  2           // InterfaceMethod com/google/common/hash/Hasher.putFloat:(F)Lcom/google/common/hash/Hasher;
      31: pop
      32: iinc          4, 1
      35: goto          11
      38: aload_0
      39: areturn

  public com.google.common.hash.Hasher putDouble(double);
    Code:
       0: aload_0
       1: getfield      #2                  // Field val$hashers:[Lcom/google/common/hash/Hasher;
       4: astore_3
       5: aload_3
       6: arraylength
       7: istore        4
       9: iconst_0
      10: istore        5
      12: iload         5
      14: iload         4
      16: if_icmpge     40
      19: aload_3
      20: iload         5
      22: aaload
      23: astore        6
      25: aload         6
      27: dload_1
      28: invokeinterface #14,  3           // InterfaceMethod com/google/common/hash/Hasher.putDouble:(D)Lcom/google/common/hash/Hasher;
      33: pop
      34: iinc          5, 1
      37: goto          12
      40: aload_0
      41: areturn

  public com.google.common.hash.Hasher putBoolean(boolean);
    Code:
       0: aload_0
       1: getfield      #2                  // Field val$hashers:[Lcom/google/common/hash/Hasher;
       4: astore_2
       5: aload_2
       6: arraylength
       7: istore_3
       8: iconst_0
       9: istore        4
      11: iload         4
      13: iload_3
      14: if_icmpge     38
      17: aload_2
      18: iload         4
      20: aaload
      21: astore        5
      23: aload         5
      25: iload_1
      26: invokeinterface #15,  2           // InterfaceMethod com/google/common/hash/Hasher.putBoolean:(Z)Lcom/google/common/hash/Hasher;
      31: pop
      32: iinc          4, 1
      35: goto          11
      38: aload_0
      39: areturn

  public com.google.common.hash.Hasher putChar(char);
    Code:
       0: aload_0
       1: getfield      #2                  // Field val$hashers:[Lcom/google/common/hash/Hasher;
       4: astore_2
       5: aload_2
       6: arraylength
       7: istore_3
       8: iconst_0
       9: istore        4
      11: iload         4
      13: iload_3
      14: if_icmpge     38
      17: aload_2
      18: iload         4
      20: aaload
      21: astore        5
      23: aload         5
      25: iload_1
      26: invokeinterface #16,  2           // InterfaceMethod com/google/common/hash/Hasher.putChar:(C)Lcom/google/common/hash/Hasher;
      31: pop
      32: iinc          4, 1
      35: goto          11
      38: aload_0
      39: areturn

  public com.google.common.hash.Hasher putUnencodedChars(java.lang.CharSequence);
    Code:
       0: aload_0
       1: getfield      #2                  // Field val$hashers:[Lcom/google/common/hash/Hasher;
       4: astore_2
       5: aload_2
       6: arraylength
       7: istore_3
       8: iconst_0
       9: istore        4
      11: iload         4
      13: iload_3
      14: if_icmpge     38
      17: aload_2
      18: iload         4
      20: aaload
      21: astore        5
      23: aload         5
      25: aload_1
      26: invokeinterface #17,  2           // InterfaceMethod com/google/common/hash/Hasher.putUnencodedChars:(Ljava/lang/CharSequence;)Lcom/google/common/hash/Hasher;
      31: pop
      32: iinc          4, 1
      35: goto          11
      38: aload_0
      39: areturn

  public com.google.common.hash.Hasher putString(java.lang.CharSequence, java.nio.charset.Charset);
    Code:
       0: aload_0
       1: getfield      #2                  // Field val$hashers:[Lcom/google/common/hash/Hasher;
       4: astore_3
       5: aload_3
       6: arraylength
       7: istore        4
       9: iconst_0
      10: istore        5
      12: iload         5
      14: iload         4
      16: if_icmpge     41
      19: aload_3
      20: iload         5
      22: aaload
      23: astore        6
      25: aload         6
      27: aload_1
      28: aload_2
      29: invokeinterface #18,  3           // InterfaceMethod com/google/common/hash/Hasher.putString:(Ljava/lang/CharSequence;Ljava/nio/charset/Charset;)Lcom/google/common/hash/Hasher;
      34: pop
      35: iinc          5, 1
      38: goto          12
      41: aload_0
      42: areturn

  public <T> com.google.common.hash.Hasher putObject(T, com.google.common.hash.Funnel<? super T>);
    Code:
       0: aload_0
       1: getfield      #2                  // Field val$hashers:[Lcom/google/common/hash/Hasher;
       4: astore_3
       5: aload_3
       6: arraylength
       7: istore        4
       9: iconst_0
      10: istore        5
      12: iload         5
      14: iload         4
      16: if_icmpge     41
      19: aload_3
      20: iload         5
      22: aaload
      23: astore        6
      25: aload         6
      27: aload_1
      28: aload_2
      29: invokeinterface #19,  3           // InterfaceMethod com/google/common/hash/Hasher.putObject:(Ljava/lang/Object;Lcom/google/common/hash/Funnel;)Lcom/google/common/hash/Hasher;
      34: pop
      35: iinc          5, 1
      38: goto          12
      41: aload_0
      42: areturn

  public com.google.common.hash.HashCode hash();
    Code:
       0: aload_0
       1: getfield      #1                  // Field this$0:Lcom/google/common/hash/AbstractCompositeHashFunction;
       4: aload_0
       5: getfield      #2                  // Field val$hashers:[Lcom/google/common/hash/Hasher;
       8: invokevirtual #20                 // Method com/google/common/hash/AbstractCompositeHashFunction.makeHash:([Lcom/google/common/hash/Hasher;)Lcom/google/common/hash/HashCode;
      11: areturn

  public com.google.common.hash.PrimitiveSink putString(java.lang.CharSequence, java.nio.charset.Charset);
    Code:
       0: aload_0
       1: aload_1
       2: aload_2
       3: invokevirtual #21                 // Method putString:(Ljava/lang/CharSequence;Ljava/nio/charset/Charset;)Lcom/google/common/hash/Hasher;
       6: areturn

  public com.google.common.hash.PrimitiveSink putUnencodedChars(java.lang.CharSequence);
    Code:
       0: aload_0
       1: aload_1
       2: invokevirtual #22                 // Method putUnencodedChars:(Ljava/lang/CharSequence;)Lcom/google/common/hash/Hasher;
       5: areturn

  public com.google.common.hash.PrimitiveSink putChar(char);
    Code:
       0: aload_0
       1: iload_1
       2: invokevirtual #23                 // Method putChar:(C)Lcom/google/common/hash/Hasher;
       5: areturn

  public com.google.common.hash.PrimitiveSink putBoolean(boolean);
    Code:
       0: aload_0
       1: iload_1
       2: invokevirtual #24                 // Method putBoolean:(Z)Lcom/google/common/hash/Hasher;
       5: areturn

  public com.google.common.hash.PrimitiveSink putDouble(double);
    Code:
       0: aload_0
       1: dload_1
       2: invokevirtual #25                 // Method putDouble:(D)Lcom/google/common/hash/Hasher;
       5: areturn

  public com.google.common.hash.PrimitiveSink putFloat(float);
    Code:
       0: aload_0
       1: fload_1
       2: invokevirtual #26                 // Method putFloat:(F)Lcom/google/common/hash/Hasher;
       5: areturn

  public com.google.common.hash.PrimitiveSink putLong(long);
    Code:
       0: aload_0
       1: lload_1
       2: invokevirtual #27                 // Method putLong:(J)Lcom/google/common/hash/Hasher;
       5: areturn

  public com.google.common.hash.PrimitiveSink putInt(int);
    Code:
       0: aload_0
       1: iload_1
       2: invokevirtual #28                 // Method putInt:(I)Lcom/google/common/hash/Hasher;
       5: areturn

  public com.google.common.hash.PrimitiveSink putShort(short);
    Code:
       0: aload_0
       1: iload_1
       2: invokevirtual #29                 // Method putShort:(S)Lcom/google/common/hash/Hasher;
       5: areturn

  public com.google.common.hash.PrimitiveSink putBytes(java.nio.ByteBuffer);
    Code:
       0: aload_0
       1: aload_1
       2: invokevirtual #30                 // Method putBytes:(Ljava/nio/ByteBuffer;)Lcom/google/common/hash/Hasher;
       5: areturn

  public com.google.common.hash.PrimitiveSink putBytes(byte[], int, int);
    Code:
       0: aload_0
       1: aload_1
       2: iload_2
       3: iload_3
       4: invokevirtual #31                 // Method putBytes:([BII)Lcom/google/common/hash/Hasher;
       7: areturn

  public com.google.common.hash.PrimitiveSink putBytes(byte[]);
    Code:
       0: aload_0
       1: aload_1
       2: invokevirtual #32                 // Method putBytes:([B)Lcom/google/common/hash/Hasher;
       5: areturn

  public com.google.common.hash.PrimitiveSink putByte(byte);
    Code:
       0: aload_0
       1: iload_1
       2: invokevirtual #33                 // Method putByte:(B)Lcom/google/common/hash/Hasher;
       5: areturn
}
