Compiled from "StaticEnumClass.java"
public class net.openhft.chronicle.core.pool.StaticEnumClass<E extends java.lang.Enum<E> & net.openhft.chronicle.core.util.CoreDynamicEnum<E>> extends net.openhft.chronicle.core.pool.EnumCache<E> {
  private final E[] values;

  net.openhft.chronicle.core.pool.StaticEnumClass(java.lang.Class<E>);
    Code:
       0: aload_0
       1: aload_1
       2: invokespecial #1                  // Method net/openhft/chronicle/core/pool/EnumCache."<init>":(Ljava/lang/Class;)V
       5: aload_0
       6: aload_1
       7: invokevirtual #2                  // Method java/lang/Class.getEnumConstants:()[Ljava/lang/Object;
      10: checkcast     #3                  // class "[Ljava/lang/Enum;"
      13: putfield      #4                  // Field values:[Ljava/lang/Enum;
      16: return

  public E valueOf(java.lang.String);
    Code:
       0: aload_1
       1: ifnull        11
       4: aload_1
       5: invokevirtual #5                  // Method java/lang/String.isEmpty:()Z
       8: ifeq          15
      11: aconst_null
      12: goto          23
      15: aload_0
      16: getfield      #6                  // Field type:Ljava/lang/Class;
      19: aload_1
      20: invokestatic  #7                  // Method java/lang/Enum.valueOf:(Ljava/lang/Class;Ljava/lang/String;)Ljava/lang/Enum;
      23: areturn

  public int size();
    Code:
       0: aload_0
       1: getfield      #4                  // Field values:[Ljava/lang/Enum;
       4: arraylength
       5: ireturn

  public E forIndex(int);
    Code:
       0: aload_0
       1: getfield      #4                  // Field values:[Ljava/lang/Enum;
       4: iload_1
       5: aaload
       6: areturn

  public E[] asArray();
    Code:
       0: aload_0
       1: getfield      #4                  // Field values:[Ljava/lang/Enum;
       4: areturn

  public <T> java.util.Map<E, T> createMap();
    Code:
       0: new           #8                  // class java/util/EnumMap
       3: dup
       4: aload_0
       5: getfield      #6                  // Field type:Ljava/lang/Class;
       8: invokespecial #9                  // Method java/util/EnumMap."<init>":(Ljava/lang/Class;)V
      11: areturn

  public java.util.Set<E> createSet();
    Code:
       0: aload_0
       1: getfield      #6                  // Field type:Ljava/lang/Class;
       4: invokestatic  #10                 // Method java/util/EnumSet.noneOf:(Ljava/lang/Class;)Ljava/util/EnumSet;
       7: areturn

  public java.lang.Object[] asArray();
    Code:
       0: aload_0
       1: invokevirtual #11                 // Method asArray:()[Ljava/lang/Enum;
       4: areturn

  public java.lang.Object forIndex(int);
    Code:
       0: aload_0
       1: iload_1
       2: invokevirtual #12                 // Method forIndex:(I)Ljava/lang/Enum;
       5: areturn

  public java.lang.Object valueOf(java.lang.String);
    Code:
       0: aload_0
       1: aload_1
       2: invokevirtual #13                 // Method valueOf:(Ljava/lang/String;)Ljava/lang/Enum;
       5: areturn
}
