Compiled from "DefaultHttp2Connection.java"
class io.netty.handler.codec.http2.DefaultHttp2Connection$DefaultStream implements io.netty.handler.codec.http2.Http2Stream {
  private static final byte META_STATE_SENT_RST;

  private static final byte META_STATE_SENT_HEADERS;

  private static final byte META_STATE_SENT_TRAILERS;

  private static final byte META_STATE_SENT_PUSHPROMISE;

  private static final byte META_STATE_RECV_HEADERS;

  private static final byte META_STATE_RECV_TRAILERS;

  private final int id;

  private final io.netty.handler.codec.http2.DefaultHttp2Connection$DefaultStream$PropertyMap properties;

  private io.netty.handler.codec.http2.Http2Stream$State state;

  private byte metaState;

  final io.netty.handler.codec.http2.DefaultHttp2Connection this$0;

  io.netty.handler.codec.http2.DefaultHttp2Connection$DefaultStream(io.netty.handler.codec.http2.DefaultHttp2Connection, int, io.netty.handler.codec.http2.Http2Stream$State);
    Code:
       0: aload_0
       1: aload_1
       2: putfield      #1                  // Field this$0:Lio/netty/handler/codec/http2/DefaultHttp2Connection;
       5: aload_0
       6: invokespecial #2                  // Method java/lang/Object."<init>":()V
       9: aload_0
      10: new           #3                  // class io/netty/handler/codec/http2/DefaultHttp2Connection$DefaultStream$PropertyMap
      13: dup
      14: aload_0
      15: aconst_null
      16: invokespecial #4                  // Method io/netty/handler/codec/http2/DefaultHttp2Connection$DefaultStream$PropertyMap."<init>":(Lio/netty/handler/codec/http2/DefaultHttp2Connection$DefaultStream;Lio/netty/handler/codec/http2/DefaultHttp2Connection$1;)V
      19: putfield      #5                  // Field properties:Lio/netty/handler/codec/http2/DefaultHttp2Connection$DefaultStream$PropertyMap;
      22: aload_0
      23: iload_2
      24: putfield      #6                  // Field id:I
      27: aload_0
      28: aload_3
      29: putfield      #7                  // Field state:Lio/netty/handler/codec/http2/Http2Stream$State;
      32: return

  public final int id();
    Code:
       0: aload_0
       1: getfield      #6                  // Field id:I
       4: ireturn

  public final io.netty.handler.codec.http2.Http2Stream$State state();
    Code:
       0: aload_0
       1: getfield      #7                  // Field state:Lio/netty/handler/codec/http2/Http2Stream$State;
       4: areturn

  public boolean isResetSent();
    Code:
       0: aload_0
       1: getfield      #8                  // Field metaState:B
       4: iconst_1
       5: iand
       6: ifeq          13
       9: iconst_1
      10: goto          14
      13: iconst_0
      14: ireturn

  public io.netty.handler.codec.http2.Http2Stream resetSent();
    Code:
       0: aload_0
       1: dup
       2: getfield      #8                  // Field metaState:B
       5: iconst_1
       6: ior
       7: i2b
       8: putfield      #8                  // Field metaState:B
      11: aload_0
      12: areturn

  public io.netty.handler.codec.http2.Http2Stream headersSent(boolean);
    Code:
       0: iload_1
       1: ifne          26
       4: aload_0
       5: dup
       6: getfield      #8                  // Field metaState:B
       9: aload_0
      10: invokevirtual #10                 // Method isHeadersSent:()Z
      13: ifeq          20
      16: iconst_4
      17: goto          21
      20: iconst_2
      21: ior
      22: i2b
      23: putfield      #8                  // Field metaState:B
      26: aload_0
      27: areturn

  public boolean isHeadersSent();
    Code:
       0: aload_0
       1: getfield      #8                  // Field metaState:B
       4: iconst_2
       5: iand
       6: ifeq          13
       9: iconst_1
      10: goto          14
      13: iconst_0
      14: ireturn

  public boolean isTrailersSent();
    Code:
       0: aload_0
       1: getfield      #8                  // Field metaState:B
       4: iconst_4
       5: iand
       6: ifeq          13
       9: iconst_1
      10: goto          14
      13: iconst_0
      14: ireturn

  public io.netty.handler.codec.http2.Http2Stream headersReceived(boolean);
    Code:
       0: iload_1
       1: ifne          28
       4: aload_0
       5: dup
       6: getfield      #8                  // Field metaState:B
       9: aload_0
      10: invokevirtual #11                 // Method isHeadersReceived:()Z
      13: ifeq          21
      16: bipush        32
      18: goto          23
      21: bipush        16
      23: ior
      24: i2b
      25: putfield      #8                  // Field metaState:B
      28: aload_0
      29: areturn

  public boolean isHeadersReceived();
    Code:
       0: aload_0
       1: getfield      #8                  // Field metaState:B
       4: bipush        16
       6: iand
       7: ifeq          14
      10: iconst_1
      11: goto          15
      14: iconst_0
      15: ireturn

  public boolean isTrailersReceived();
    Code:
       0: aload_0
       1: getfield      #8                  // Field metaState:B
       4: bipush        32
       6: iand
       7: ifeq          14
      10: iconst_1
      11: goto          15
      14: iconst_0
      15: ireturn

  public io.netty.handler.codec.http2.Http2Stream pushPromiseSent();
    Code:
       0: aload_0
       1: dup
       2: getfield      #8                  // Field metaState:B
       5: bipush        8
       7: ior
       8: i2b
       9: putfield      #8                  // Field metaState:B
      12: aload_0
      13: areturn

  public boolean isPushPromiseSent();
    Code:
       0: aload_0
       1: getfield      #8                  // Field metaState:B
       4: bipush        8
       6: iand
       7: ifeq          14
      10: iconst_1
      11: goto          15
      14: iconst_0
      15: ireturn

  public final <V> V setProperty(io.netty.handler.codec.http2.Http2Connection$PropertyKey, V);
    Code:
       0: aload_0
       1: getfield      #5                  // Field properties:Lio/netty/handler/codec/http2/DefaultHttp2Connection$DefaultStream$PropertyMap;
       4: aload_0
       5: getfield      #1                  // Field this$0:Lio/netty/handler/codec/http2/DefaultHttp2Connection;
       8: aload_1
       9: invokevirtual #12                 // Method io/netty/handler/codec/http2/DefaultHttp2Connection.verifyKey:(Lio/netty/handler/codec/http2/Http2Connection$PropertyKey;)Lio/netty/handler/codec/http2/DefaultHttp2Connection$DefaultPropertyKey;
      12: aload_2
      13: invokevirtual #13                 // Method io/netty/handler/codec/http2/DefaultHttp2Connection$DefaultStream$PropertyMap.add:(Lio/netty/handler/codec/http2/DefaultHttp2Connection$DefaultPropertyKey;Ljava/lang/Object;)Ljava/lang/Object;
      16: areturn

  public final <V> V getProperty(io.netty.handler.codec.http2.Http2Connection$PropertyKey);
    Code:
       0: aload_0
       1: getfield      #5                  // Field properties:Lio/netty/handler/codec/http2/DefaultHttp2Connection$DefaultStream$PropertyMap;
       4: aload_0
       5: getfield      #1                  // Field this$0:Lio/netty/handler/codec/http2/DefaultHttp2Connection;
       8: aload_1
       9: invokevirtual #12                 // Method io/netty/handler/codec/http2/DefaultHttp2Connection.verifyKey:(Lio/netty/handler/codec/http2/Http2Connection$PropertyKey;)Lio/netty/handler/codec/http2/DefaultHttp2Connection$DefaultPropertyKey;
      12: invokevirtual #14                 // Method io/netty/handler/codec/http2/DefaultHttp2Connection$DefaultStream$PropertyMap.get:(Lio/netty/handler/codec/http2/DefaultHttp2Connection$DefaultPropertyKey;)Ljava/lang/Object;
      15: areturn

  public final <V> V removeProperty(io.netty.handler.codec.http2.Http2Connection$PropertyKey);
    Code:
       0: aload_0
       1: getfield      #5                  // Field properties:Lio/netty/handler/codec/http2/DefaultHttp2Connection$DefaultStream$PropertyMap;
       4: aload_0
       5: getfield      #1                  // Field this$0:Lio/netty/handler/codec/http2/DefaultHttp2Connection;
       8: aload_1
       9: invokevirtual #12                 // Method io/netty/handler/codec/http2/DefaultHttp2Connection.verifyKey:(Lio/netty/handler/codec/http2/Http2Connection$PropertyKey;)Lio/netty/handler/codec/http2/DefaultHttp2Connection$DefaultPropertyKey;
      12: invokevirtual #15                 // Method io/netty/handler/codec/http2/DefaultHttp2Connection$DefaultStream$PropertyMap.remove:(Lio/netty/handler/codec/http2/DefaultHttp2Connection$DefaultPropertyKey;)Ljava/lang/Object;
      15: areturn

  public io.netty.handler.codec.http2.Http2Stream open(boolean) throws io.netty.handler.codec.http2.Http2Exception;
    Code:
       0: aload_0
       1: aload_0
       2: getfield      #6                  // Field id:I
       5: aload_0
       6: getfield      #7                  // Field state:Lio/netty/handler/codec/http2/Http2Stream$State;
       9: aload_0
      10: invokevirtual #16                 // Method isLocal:()Z
      13: iload_1
      14: invokestatic  #17                 // Method io/netty/handler/codec/http2/DefaultHttp2Connection.activeState:(ILio/netty/handler/codec/http2/Http2Stream$State;ZZ)Lio/netty/handler/codec/http2/Http2Stream$State;
      17: putfield      #7                  // Field state:Lio/netty/handler/codec/http2/Http2Stream$State;
      20: aload_0
      21: invokevirtual #18                 // Method createdBy:()Lio/netty/handler/codec/http2/DefaultHttp2Connection$DefaultEndpoint;
      24: astore_2
      25: aload_2
      26: invokevirtual #19                 // Method io/netty/handler/codec/http2/DefaultHttp2Connection$DefaultEndpoint.canOpenStream:()Z
      29: ifne          65
      32: getstatic     #20                 // Field io/netty/handler/codec/http2/Http2Error.PROTOCOL_ERROR:Lio/netty/handler/codec/http2/Http2Error;
      35: new           #21                 // class java/lang/StringBuilder
      38: dup
      39: invokespecial #22                 // Method java/lang/StringBuilder."<init>":()V
      42: ldc           #23                 // String Maximum active streams violated for this endpoint:
      44: invokevirtual #24                 // Method java/lang/StringBuilder.append:(Ljava/lang/String;)Ljava/lang/StringBuilder;
      47: aload_2
      48: invokevirtual #25                 // Method io/netty/handler/codec/http2/DefaultHttp2Connection$DefaultEndpoint.maxActiveStreams:()I
      51: invokevirtual #26                 // Method java/lang/StringBuilder.append:(I)Ljava/lang/StringBuilder;
      54: invokevirtual #27                 // Method java/lang/StringBuilder.toString:()Ljava/lang/String;
      57: iconst_0
      58: anewarray     #28                 // class java/lang/Object
      61: invokestatic  #29                 // Method io/netty/handler/codec/http2/Http2Exception.connectionError:(Lio/netty/handler/codec/http2/Http2Error;Ljava/lang/String;[Ljava/lang/Object;)Lio/netty/handler/codec/http2/Http2Exception;
      64: athrow
      65: aload_0
      66: invokevirtual #30                 // Method activate:()V
      69: aload_0
      70: areturn

  void activate();
    Code:
       0: aload_0
       1: getfield      #7                  // Field state:Lio/netty/handler/codec/http2/Http2Stream$State;
       4: getstatic     #31                 // Field io/netty/handler/codec/http2/Http2Stream$State.HALF_CLOSED_LOCAL:Lio/netty/handler/codec/http2/Http2Stream$State;
       7: if_acmpne     19
      10: aload_0
      11: iconst_0
      12: invokevirtual #32                 // Method headersSent:(Z)Lio/netty/handler/codec/http2/Http2Stream;
      15: pop
      16: goto          35
      19: aload_0
      20: getfield      #7                  // Field state:Lio/netty/handler/codec/http2/Http2Stream$State;
      23: getstatic     #33                 // Field io/netty/handler/codec/http2/Http2Stream$State.HALF_CLOSED_REMOTE:Lio/netty/handler/codec/http2/Http2Stream$State;
      26: if_acmpne     35
      29: aload_0
      30: iconst_0
      31: invokevirtual #34                 // Method headersReceived:(Z)Lio/netty/handler/codec/http2/Http2Stream;
      34: pop
      35: aload_0
      36: getfield      #1                  // Field this$0:Lio/netty/handler/codec/http2/DefaultHttp2Connection;
      39: getfield      #35                 // Field io/netty/handler/codec/http2/DefaultHttp2Connection.activeStreams:Lio/netty/handler/codec/http2/DefaultHttp2Connection$ActiveStreams;
      42: aload_0
      43: invokevirtual #36                 // Method io/netty/handler/codec/http2/DefaultHttp2Connection$ActiveStreams.activate:(Lio/netty/handler/codec/http2/DefaultHttp2Connection$DefaultStream;)V
      46: return

  io.netty.handler.codec.http2.Http2Stream close(java.util.Iterator<?>);
    Code:
       0: aload_0
       1: getfield      #7                  // Field state:Lio/netty/handler/codec/http2/Http2Stream$State;
       4: getstatic     #37                 // Field io/netty/handler/codec/http2/Http2Stream$State.CLOSED:Lio/netty/handler/codec/http2/Http2Stream$State;
       7: if_acmpne     12
      10: aload_0
      11: areturn
      12: aload_0
      13: getstatic     #37                 // Field io/netty/handler/codec/http2/Http2Stream$State.CLOSED:Lio/netty/handler/codec/http2/Http2Stream$State;
      16: putfield      #7                  // Field state:Lio/netty/handler/codec/http2/Http2Stream$State;
      19: aload_0
      20: invokevirtual #18                 // Method createdBy:()Lio/netty/handler/codec/http2/DefaultHttp2Connection$DefaultEndpoint;
      23: dup
      24: getfield      #38                 // Field io/netty/handler/codec/http2/DefaultHttp2Connection$DefaultEndpoint.numStreams:I
      27: iconst_1
      28: isub
      29: putfield      #38                 // Field io/netty/handler/codec/http2/DefaultHttp2Connection$DefaultEndpoint.numStreams:I
      32: aload_0
      33: getfield      #1                  // Field this$0:Lio/netty/handler/codec/http2/DefaultHttp2Connection;
      36: getfield      #35                 // Field io/netty/handler/codec/http2/DefaultHttp2Connection.activeStreams:Lio/netty/handler/codec/http2/DefaultHttp2Connection$ActiveStreams;
      39: aload_0
      40: aload_1
      41: invokevirtual #39                 // Method io/netty/handler/codec/http2/DefaultHttp2Connection$ActiveStreams.deactivate:(Lio/netty/handler/codec/http2/DefaultHttp2Connection$DefaultStream;Ljava/util/Iterator;)V
      44: aload_0
      45: areturn

  public io.netty.handler.codec.http2.Http2Stream close();
    Code:
       0: aload_0
       1: aconst_null
       2: invokevirtual #40                 // Method close:(Ljava/util/Iterator;)Lio/netty/handler/codec/http2/Http2Stream;
       5: areturn

  public io.netty.handler.codec.http2.Http2Stream closeLocalSide();
    Code:
       0: getstatic     #41                 // Field io/netty/handler/codec/http2/DefaultHttp2Connection$2.$SwitchMap$io$netty$handler$codec$http2$Http2Stream$State:[I
       3: aload_0
       4: getfield      #7                  // Field state:Lio/netty/handler/codec/http2/Http2Stream$State;
       7: invokevirtual #42                 // Method io/netty/handler/codec/http2/Http2Stream$State.ordinal:()I
      10: iaload
      11: lookupswitch  { // 2
                     4: 36
                     5: 54
               default: 57
          }
      36: aload_0
      37: getstatic     #31                 // Field io/netty/handler/codec/http2/Http2Stream$State.HALF_CLOSED_LOCAL:Lio/netty/handler/codec/http2/Http2Stream$State;
      40: putfield      #7                  // Field state:Lio/netty/handler/codec/http2/Http2Stream$State;
      43: aload_0
      44: getfield      #1                  // Field this$0:Lio/netty/handler/codec/http2/DefaultHttp2Connection;
      47: aload_0
      48: invokevirtual #43                 // Method io/netty/handler/codec/http2/DefaultHttp2Connection.notifyHalfClosed:(Lio/netty/handler/codec/http2/Http2Stream;)V
      51: goto          62
      54: goto          62
      57: aload_0
      58: invokevirtual #44                 // Method close:()Lio/netty/handler/codec/http2/Http2Stream;
      61: pop
      62: aload_0
      63: areturn

  public io.netty.handler.codec.http2.Http2Stream closeRemoteSide();
    Code:
       0: getstatic     #41                 // Field io/netty/handler/codec/http2/DefaultHttp2Connection$2.$SwitchMap$io$netty$handler$codec$http2$Http2Stream$State:[I
       3: aload_0
       4: getfield      #7                  // Field state:Lio/netty/handler/codec/http2/Http2Stream$State;
       7: invokevirtual #42                 // Method io/netty/handler/codec/http2/Http2Stream$State.ordinal:()I
      10: iaload
      11: lookupswitch  { // 2
                     4: 36
                     6: 54
               default: 57
          }
      36: aload_0
      37: getstatic     #33                 // Field io/netty/handler/codec/http2/Http2Stream$State.HALF_CLOSED_REMOTE:Lio/netty/handler/codec/http2/Http2Stream$State;
      40: putfield      #7                  // Field state:Lio/netty/handler/codec/http2/Http2Stream$State;
      43: aload_0
      44: getfield      #1                  // Field this$0:Lio/netty/handler/codec/http2/DefaultHttp2Connection;
      47: aload_0
      48: invokevirtual #43                 // Method io/netty/handler/codec/http2/DefaultHttp2Connection.notifyHalfClosed:(Lio/netty/handler/codec/http2/Http2Stream;)V
      51: goto          62
      54: goto          62
      57: aload_0
      58: invokevirtual #44                 // Method close:()Lio/netty/handler/codec/http2/Http2Stream;
      61: pop
      62: aload_0
      63: areturn

  io.netty.handler.codec.http2.DefaultHttp2Connection$DefaultEndpoint<? extends io.netty.handler.codec.http2.Http2FlowController> createdBy();
    Code:
       0: aload_0
       1: getfield      #1                  // Field this$0:Lio/netty/handler/codec/http2/DefaultHttp2Connection;
       4: getfield      #45                 // Field io/netty/handler/codec/http2/DefaultHttp2Connection.localEndpoint:Lio/netty/handler/codec/http2/DefaultHttp2Connection$DefaultEndpoint;
       7: aload_0
       8: getfield      #6                  // Field id:I
      11: invokevirtual #46                 // Method io/netty/handler/codec/http2/DefaultHttp2Connection$DefaultEndpoint.isValidStreamId:(I)Z
      14: ifeq          27
      17: aload_0
      18: getfield      #1                  // Field this$0:Lio/netty/handler/codec/http2/DefaultHttp2Connection;
      21: getfield      #45                 // Field io/netty/handler/codec/http2/DefaultHttp2Connection.localEndpoint:Lio/netty/handler/codec/http2/DefaultHttp2Connection$DefaultEndpoint;
      24: goto          34
      27: aload_0
      28: getfield      #1                  // Field this$0:Lio/netty/handler/codec/http2/DefaultHttp2Connection;
      31: getfield      #47                 // Field io/netty/handler/codec/http2/DefaultHttp2Connection.remoteEndpoint:Lio/netty/handler/codec/http2/DefaultHttp2Connection$DefaultEndpoint;
      34: areturn

  final boolean isLocal();
    Code:
       0: aload_0
       1: getfield      #1                  // Field this$0:Lio/netty/handler/codec/http2/DefaultHttp2Connection;
       4: getfield      #45                 // Field io/netty/handler/codec/http2/DefaultHttp2Connection.localEndpoint:Lio/netty/handler/codec/http2/DefaultHttp2Connection$DefaultEndpoint;
       7: aload_0
       8: getfield      #6                  // Field id:I
      11: invokevirtual #46                 // Method io/netty/handler/codec/http2/DefaultHttp2Connection$DefaultEndpoint.isValidStreamId:(I)Z
      14: ireturn
}
