Compiled from "DescriptorEquivalenceForOverrides.kt"
final class kotlin.reflect.jvm.internal.impl.resolve.DescriptorEquivalenceForOverrides$areCallableDescriptorsEquivalent$overridingUtil$1 implements kotlin.reflect.jvm.internal.impl.types.checker.KotlinTypeChecker$TypeConstructorEquality {
  final kotlin.reflect.jvm.internal.impl.descriptors.CallableDescriptor $a;

  final kotlin.reflect.jvm.internal.impl.descriptors.CallableDescriptor $b;

  public boolean equals(kotlin.reflect.jvm.internal.impl.types.TypeConstructor, kotlin.reflect.jvm.internal.impl.types.TypeConstructor);
    Code:
       0: aload_0
       1: aload_1
       2: aload_2
       3: invokevirtual #20                 // Method invoke:(Lkotlin/reflect/jvm/internal/impl/types/TypeConstructor;Lkotlin/reflect/jvm/internal/impl/types/TypeConstructor;)Z
       6: ireturn

  public final boolean invoke(kotlin.reflect.jvm.internal.impl.types.TypeConstructor, kotlin.reflect.jvm.internal.impl.types.TypeConstructor);
    Code:
       0: aload_1
       1: ldc           #1                  // String c1
       3: invokestatic  #18                 // Method kotlin/jvm/internal/Intrinsics.checkParameterIsNotNull:(Ljava/lang/Object;Ljava/lang/String;)V
       6: aload_2
       7: ldc           #2                  // String c2
       9: invokestatic  #18                 // Method kotlin/jvm/internal/Intrinsics.checkParameterIsNotNull:(Ljava/lang/Object;Ljava/lang/String;)V
      12: aload_1
      13: aload_2
      14: invokestatic  #17                 // Method kotlin/jvm/internal/Intrinsics.areEqual:(Ljava/lang/Object;Ljava/lang/Object;)Z
      17: ifeq          22
      20: iconst_1
      21: ireturn
      22: aload_1
      23: invokeinterface #22,  1           // InterfaceMethod kotlin/reflect/jvm/internal/impl/types/TypeConstructor.getDeclarationDescriptor:()Lkotlin/reflect/jvm/internal/impl/descriptors/ClassifierDescriptor;
      28: astore_3
      29: aload_2
      30: invokeinterface #22,  1           // InterfaceMethod kotlin/reflect/jvm/internal/impl/types/TypeConstructor.getDeclarationDescriptor:()Lkotlin/reflect/jvm/internal/impl/descriptors/ClassifierDescriptor;
      35: astore        4
      37: aload_3
      38: instanceof    #7                  // class kotlin/reflect/jvm/internal/impl/descriptors/TypeParameterDescriptor
      41: ifeq          52
      44: aload         4
      46: instanceof    #7                  // class kotlin/reflect/jvm/internal/impl/descriptors/TypeParameterDescriptor
      49: ifne          54
      52: iconst_0
      53: ireturn
      54: getstatic     #13                 // Field kotlin/reflect/jvm/internal/impl/resolve/DescriptorEquivalenceForOverrides.INSTANCE:Lkotlin/reflect/jvm/internal/impl/resolve/DescriptorEquivalenceForOverrides;
      57: aload_3
      58: checkcast     #7                  // class kotlin/reflect/jvm/internal/impl/descriptors/TypeParameterDescriptor
      61: aload         4
      63: checkcast     #7                  // class kotlin/reflect/jvm/internal/impl/descriptors/TypeParameterDescriptor
      66: new           #10                 // class kotlin/reflect/jvm/internal/impl/resolve/DescriptorEquivalenceForOverrides$areCallableDescriptorsEquivalent$overridingUtil$1$1
      69: dup
      70: aload_0
      71: invokespecial #21                 // Method kotlin/reflect/jvm/internal/impl/resolve/DescriptorEquivalenceForOverrides$areCallableDescriptorsEquivalent$overridingUtil$1$1."<init>":(Lkotlin/reflect/jvm/internal/impl/resolve/DescriptorEquivalenceForOverrides$areCallableDescriptorsEquivalent$overridingUtil$1;)V
      74: checkcast     #4                  // class kotlin/jvm/functions/Function2
      77: invokestatic  #19                 // Method kotlin/reflect/jvm/internal/impl/resolve/DescriptorEquivalenceForOverrides.access$areTypeParametersEquivalent:(Lkotlin/reflect/jvm/internal/impl/resolve/DescriptorEquivalenceForOverrides;Lkotlin/reflect/jvm/internal/impl/descriptors/TypeParameterDescriptor;Lkotlin/reflect/jvm/internal/impl/descriptors/TypeParameterDescriptor;Lkotlin/jvm/functions/Function2;)Z
      80: ireturn

  kotlin.reflect.jvm.internal.impl.resolve.DescriptorEquivalenceForOverrides$areCallableDescriptorsEquivalent$overridingUtil$1(kotlin.reflect.jvm.internal.impl.descriptors.CallableDescriptor, kotlin.reflect.jvm.internal.impl.descriptors.CallableDescriptor);
    Code:
       0: aload_0
       1: aload_1
       2: putfield      #14                 // Field $a:Lkotlin/reflect/jvm/internal/impl/descriptors/CallableDescriptor;
       5: aload_0
       6: aload_2
       7: putfield      #15                 // Field $b:Lkotlin/reflect/jvm/internal/impl/descriptors/CallableDescriptor;
      10: aload_0
      11: invokespecial #16                 // Method java/lang/Object."<init>":()V
      14: return
}
