Compiled from "OverridingStrategy.kt"
public abstract class kotlin.reflect.jvm.internal.impl.resolve.OverridingStrategy {
  public abstract void addFakeOverride(kotlin.reflect.jvm.internal.impl.descriptors.CallableMemberDescriptor);

  public abstract void overrideConflict(kotlin.reflect.jvm.internal.impl.descriptors.CallableMemberDescriptor, kotlin.reflect.jvm.internal.impl.descriptors.CallableMemberDescriptor);

  public abstract void inheritanceConflict(kotlin.reflect.jvm.internal.impl.descriptors.CallableMemberDescriptor, kotlin.reflect.jvm.internal.impl.descriptors.CallableMemberDescriptor);

  public void setOverriddenDescriptors(kotlin.reflect.jvm.internal.impl.descriptors.CallableMemberDescriptor, java.util.Collection<? extends kotlin.reflect.jvm.internal.impl.descriptors.CallableMemberDescriptor>);
    Code:
       0: aload_1
       1: ldc           #1                  // String member
       3: invokestatic  #8                  // Method kotlin/jvm/internal/Intrinsics.checkParameterIsNotNull:(Ljava/lang/Object;Ljava/lang/String;)V
       6: aload_2
       7: ldc           #2                  // String overridden
       9: invokestatic  #8                  // Method kotlin/jvm/internal/Intrinsics.checkParameterIsNotNull:(Ljava/lang/Object;Ljava/lang/String;)V
      12: aload_1
      13: aload_2
      14: invokeinterface #9,  2            // InterfaceMethod kotlin/reflect/jvm/internal/impl/descriptors/CallableMemberDescriptor.setOverriddenDescriptors:(Ljava/util/Collection;)V
      19: return

  public kotlin.reflect.jvm.internal.impl.resolve.OverridingStrategy();
    Code:
       0: aload_0
       1: invokespecial #7                  // Method java/lang/Object."<init>":()V
       4: return
}
