Compiled from "AckRequestProcessor.java"
class org.apache.zookeeper.server.quorum.AckRequestProcessor implements org.apache.zookeeper.server.RequestProcessor {
  private static final org.slf4j.Logger LOG;

  org.apache.zookeeper.server.quorum.Leader leader;

  org.apache.zookeeper.server.quorum.AckRequestProcessor(org.apache.zookeeper.server.quorum.Leader);
    Code:
       0: aload_0
       1: invokespecial #1                  // Method java/lang/Object."<init>":()V
       4: aload_0
       5: aload_1
       6: putfield      #2                  // Field leader:Lorg/apache/zookeeper/server/quorum/Leader;
       9: return

  public void processRequest(org.apache.zookeeper.server.Request);
    Code:
       0: aload_0
       1: getfield      #2                  // Field leader:Lorg/apache/zookeeper/server/quorum/Leader;
       4: getfield      #3                  // Field org/apache/zookeeper/server/quorum/Leader.self:Lorg/apache/zookeeper/server/quorum/QuorumPeer;
       7: astore_2
       8: aload_2
       9: ifnull        41
      12: aload_1
      13: invokestatic  #4                  // Method org/apache/zookeeper/server/ServerMetrics.getMetrics:()Lorg/apache/zookeeper/server/ServerMetrics;
      16: getfield      #5                  // Field org/apache/zookeeper/server/ServerMetrics.PROPOSAL_ACK_CREATION_LATENCY:Lorg/apache/zookeeper/metrics/Summary;
      19: invokevirtual #6                  // Method org/apache/zookeeper/server/Request.logLatency:(Lorg/apache/zookeeper/metrics/Summary;)V
      22: aload_0
      23: getfield      #2                  // Field leader:Lorg/apache/zookeeper/server/quorum/Leader;
      26: aload_2
      27: invokevirtual #7                  // Method org/apache/zookeeper/server/quorum/QuorumPeer.getId:()J
      30: aload_1
      31: getfield      #8                  // Field org/apache/zookeeper/server/Request.zxid:J
      34: aconst_null
      35: invokevirtual #9                  // Method org/apache/zookeeper/server/quorum/Leader.processAck:(JJLjava/net/SocketAddress;)V
      38: goto          51
      41: getstatic     #10                 // Field LOG:Lorg/slf4j/Logger;
      44: ldc           #11                 // String Null QuorumPeer
      46: invokeinterface #12,  2           // InterfaceMethod org/slf4j/Logger.error:(Ljava/lang/String;)V
      51: return

  public void shutdown();
    Code:
       0: return

  static {};
    Code:
       0: ldc           #13                 // class org/apache/zookeeper/server/quorum/AckRequestProcessor
       2: invokestatic  #14                 // Method org/slf4j/LoggerFactory.getLogger:(Ljava/lang/Class;)Lorg/slf4j/Logger;
       5: putstatic     #10                 // Field LOG:Lorg/slf4j/Logger;
       8: return
}
