Compiled from "LeaderElectionBean.java"
public class org.apache.zookeeper.server.quorum.LeaderElectionBean implements org.apache.zookeeper.server.quorum.LeaderElectionMXBean,org.apache.zookeeper.jmx.ZKMBeanInfo {
  private final java.util.Date startTime;

  public org.apache.zookeeper.server.quorum.LeaderElectionBean();
    Code:
       0: aload_0
       1: invokespecial #1                  // Method java/lang/Object."<init>":()V
       4: aload_0
       5: new           #2                  // class java/util/Date
       8: dup
       9: invokespecial #3                  // Method java/util/Date."<init>":()V
      12: putfield      #4                  // Field startTime:Ljava/util/Date;
      15: return

  public java.lang.String getName();
    Code:
       0: ldc           #5                  // String LeaderElection
       2: areturn

  public boolean isHidden();
    Code:
       0: iconst_0
       1: ireturn

  public java.lang.String getStartTime();
    Code:
       0: aload_0
       1: getfield      #4                  // Field startTime:Ljava/util/Date;
       4: invokevirtual #6                  // Method java/util/Date.toString:()Ljava/lang/String;
       7: areturn
}
