Compiled from "LeaderSessionTracker.java"
public class org.apache.zookeeper.server.quorum.LeaderSessionTracker extends org.apache.zookeeper.server.quorum.UpgradeableSessionTracker {
  private static final org.slf4j.Logger LOG;

  private final org.apache.zookeeper.server.SessionTrackerImpl globalSessionTracker;

  private final long serverId;

  public org.apache.zookeeper.server.quorum.LeaderSessionTracker(org.apache.zookeeper.server.SessionTracker$SessionExpirer, java.util.concurrent.ConcurrentMap<java.lang.Long, java.lang.Integer>, int, long, boolean, org.apache.zookeeper.server.ZooKeeperServerListener);
    Code:
       0: aload_0
       1: invokespecial #1                  // Method org/apache/zookeeper/server/quorum/UpgradeableSessionTracker."<init>":()V
       4: aload_0
       5: new           #2                  // class org/apache/zookeeper/server/SessionTrackerImpl
       8: dup
       9: aload_1
      10: aload_2
      11: iload_3
      12: lload         4
      14: aload         7
      16: invokespecial #3                  // Method org/apache/zookeeper/server/SessionTrackerImpl."<init>":(Lorg/apache/zookeeper/server/SessionTracker$SessionExpirer;Ljava/util/concurrent/ConcurrentMap;IJLorg/apache/zookeeper/server/ZooKeeperServerListener;)V
      19: putfield      #4                  // Field globalSessionTracker:Lorg/apache/zookeeper/server/SessionTrackerImpl;
      22: aload_0
      23: iload         6
      25: putfield      #5                  // Field localSessionsEnabled:Z
      28: aload_0
      29: getfield      #5                  // Field localSessionsEnabled:Z
      32: ifeq          45
      35: aload_0
      36: aload_1
      37: iload_3
      38: lload         4
      40: aload         7
      42: invokevirtual #6                  // Method createLocalSessionTracker:(Lorg/apache/zookeeper/server/SessionTracker$SessionExpirer;IJLorg/apache/zookeeper/server/ZooKeeperServerListener;)V
      45: aload_0
      46: lload         4
      48: putfield      #7                  // Field serverId:J
      51: return

  public void removeSession(long);
    Code:
       0: aload_0
       1: getfield      #8                  // Field localSessionTracker:Lorg/apache/zookeeper/server/quorum/LocalSessionTracker;
       4: ifnull        15
       7: aload_0
       8: getfield      #8                  // Field localSessionTracker:Lorg/apache/zookeeper/server/quorum/LocalSessionTracker;
      11: lload_1
      12: invokevirtual #9                  // Method org/apache/zookeeper/server/quorum/LocalSessionTracker.removeSession:(J)V
      15: aload_0
      16: getfield      #4                  // Field globalSessionTracker:Lorg/apache/zookeeper/server/SessionTrackerImpl;
      19: lload_1
      20: invokevirtual #10                 // Method org/apache/zookeeper/server/SessionTrackerImpl.removeSession:(J)V
      23: return

  public void start();
    Code:
       0: aload_0
       1: getfield      #4                  // Field globalSessionTracker:Lorg/apache/zookeeper/server/SessionTrackerImpl;
       4: invokevirtual #11                 // Method org/apache/zookeeper/server/SessionTrackerImpl.start:()V
       7: aload_0
       8: getfield      #8                  // Field localSessionTracker:Lorg/apache/zookeeper/server/quorum/LocalSessionTracker;
      11: ifnull        21
      14: aload_0
      15: getfield      #8                  // Field localSessionTracker:Lorg/apache/zookeeper/server/quorum/LocalSessionTracker;
      18: invokevirtual #12                 // Method org/apache/zookeeper/server/quorum/LocalSessionTracker.start:()V
      21: return

  public void shutdown();
    Code:
       0: aload_0
       1: getfield      #8                  // Field localSessionTracker:Lorg/apache/zookeeper/server/quorum/LocalSessionTracker;
       4: ifnull        14
       7: aload_0
       8: getfield      #8                  // Field localSessionTracker:Lorg/apache/zookeeper/server/quorum/LocalSessionTracker;
      11: invokevirtual #13                 // Method org/apache/zookeeper/server/quorum/LocalSessionTracker.shutdown:()V
      14: aload_0
      15: getfield      #4                  // Field globalSessionTracker:Lorg/apache/zookeeper/server/SessionTrackerImpl;
      18: invokevirtual #14                 // Method org/apache/zookeeper/server/SessionTrackerImpl.shutdown:()V
      21: return

  public boolean isGlobalSession(long);
    Code:
       0: aload_0
       1: getfield      #4                  // Field globalSessionTracker:Lorg/apache/zookeeper/server/SessionTrackerImpl;
       4: lload_1
       5: invokevirtual #15                 // Method org/apache/zookeeper/server/SessionTrackerImpl.isTrackingSession:(J)Z
       8: ireturn

  public boolean trackSession(long, int);
    Code:
       0: aload_0
       1: getfield      #4                  // Field globalSessionTracker:Lorg/apache/zookeeper/server/SessionTrackerImpl;
       4: lload_1
       5: iload_3
       6: invokevirtual #16                 // Method org/apache/zookeeper/server/SessionTrackerImpl.trackSession:(JI)Z
       9: istore        4
      11: aload_0
      12: getfield      #5                  // Field localSessionsEnabled:Z
      15: ifeq          37
      18: iload         4
      20: ifeq          37
      23: getstatic     #17                 // Field LOG:Lorg/slf4j/Logger;
      26: ldc           #18                 // String Tracking global session 0x{}
      28: lload_1
      29: invokestatic  #19                 // Method java/lang/Long.toHexString:(J)Ljava/lang/String;
      32: invokeinterface #20,  3           // InterfaceMethod org/slf4j/Logger.info:(Ljava/lang/String;Ljava/lang/Object;)V
      37: iload         4
      39: ireturn

  public synchronized boolean commitSession(long, int);
    Code:
       0: aload_0
       1: getfield      #4                  // Field globalSessionTracker:Lorg/apache/zookeeper/server/SessionTrackerImpl;
       4: lload_1
       5: iload_3
       6: invokevirtual #21                 // Method org/apache/zookeeper/server/SessionTrackerImpl.commitSession:(JI)Z
       9: istore        4
      11: iload         4
      13: ifeq          30
      16: getstatic     #17                 // Field LOG:Lorg/slf4j/Logger;
      19: ldc           #22                 // String Committing global session 0x{}
      21: lload_1
      22: invokestatic  #19                 // Method java/lang/Long.toHexString:(J)Ljava/lang/String;
      25: invokeinterface #20,  3           // InterfaceMethod org/slf4j/Logger.info:(Ljava/lang/String;Ljava/lang/Object;)V
      30: aload_0
      31: getfield      #5                  // Field localSessionsEnabled:Z
      34: ifeq          47
      37: aload_0
      38: lload_1
      39: invokevirtual #23                 // Method removeLocalSession:(J)V
      42: aload_0
      43: lload_1
      44: invokevirtual #24                 // Method finishedUpgrading:(J)V
      47: iload         4
      49: ireturn

  public boolean touchSession(long, int);
    Code:
       0: aload_0
       1: getfield      #8                  // Field localSessionTracker:Lorg/apache/zookeeper/server/quorum/LocalSessionTracker;
       4: ifnull        21
       7: aload_0
       8: getfield      #8                  // Field localSessionTracker:Lorg/apache/zookeeper/server/quorum/LocalSessionTracker;
      11: lload_1
      12: iload_3
      13: invokevirtual #25                 // Method org/apache/zookeeper/server/quorum/LocalSessionTracker.touchSession:(JI)Z
      16: ifeq          21
      19: iconst_1
      20: ireturn
      21: aload_0
      22: getfield      #4                  // Field globalSessionTracker:Lorg/apache/zookeeper/server/SessionTrackerImpl;
      25: lload_1
      26: iload_3
      27: invokevirtual #26                 // Method org/apache/zookeeper/server/SessionTrackerImpl.touchSession:(JI)Z
      30: ireturn

  public long createSession(int);
    Code:
       0: aload_0
       1: getfield      #5                  // Field localSessionsEnabled:Z
       4: ifeq          16
       7: aload_0
       8: getfield      #8                  // Field localSessionTracker:Lorg/apache/zookeeper/server/quorum/LocalSessionTracker;
      11: iload_1
      12: invokevirtual #27                 // Method org/apache/zookeeper/server/quorum/LocalSessionTracker.createSession:(I)J
      15: lreturn
      16: aload_0
      17: getfield      #4                  // Field globalSessionTracker:Lorg/apache/zookeeper/server/SessionTrackerImpl;
      20: iload_1
      21: invokevirtual #28                 // Method org/apache/zookeeper/server/SessionTrackerImpl.createSession:(I)J
      24: lreturn

  public static long getServerIdFromSessionId(long);
    Code:
       0: lload_0
       1: bipush        56
       3: lshr
       4: lreturn

  public void checkSession(long, java.lang.Object) throws org.apache.zookeeper.KeeperException$SessionExpiredException, org.apache.zookeeper.KeeperException$SessionMovedException, org.apache.zookeeper.KeeperException$UnknownSessionException;
    Code:
       0: aload_0
       1: getfield      #8                  // Field localSessionTracker:Lorg/apache/zookeeper/server/quorum/LocalSessionTracker;
       4: ifnull        30
       7: aload_0
       8: getfield      #8                  // Field localSessionTracker:Lorg/apache/zookeeper/server/quorum/LocalSessionTracker;
      11: lload_1
      12: aload_3
      13: invokevirtual #29                 // Method org/apache/zookeeper/server/quorum/LocalSessionTracker.checkSession:(JLjava/lang/Object;)V
      16: aload_0
      17: lload_1
      18: invokevirtual #30                 // Method isGlobalSession:(J)Z
      21: ifne          25
      24: return
      25: goto          30
      28: astore        4
      30: aload_0
      31: getfield      #4                  // Field globalSessionTracker:Lorg/apache/zookeeper/server/SessionTrackerImpl;
      34: lload_1
      35: aload_3
      36: invokevirtual #32                 // Method org/apache/zookeeper/server/SessionTrackerImpl.checkSession:(JLjava/lang/Object;)V
      39: return
      40: astore        4
      42: aload_0
      43: getfield      #5                  // Field localSessionsEnabled:Z
      46: ifeq          61
      49: lload_1
      50: invokestatic  #33                 // Method getServerIdFromSessionId:(J)J
      53: aload_0
      54: getfield      #7                  // Field serverId:J
      57: lcmp
      58: ifne          69
      61: new           #34                 // class org/apache/zookeeper/KeeperException$SessionExpiredException
      64: dup
      65: invokespecial #35                 // Method org/apache/zookeeper/KeeperException$SessionExpiredException."<init>":()V
      68: athrow
      69: return
    Exception table:
       from    to  target type
           7    24    28   Class org/apache/zookeeper/KeeperException$UnknownSessionException
          30    39    40   Class org/apache/zookeeper/KeeperException$UnknownSessionException

  public void checkGlobalSession(long, java.lang.Object) throws org.apache.zookeeper.KeeperException$SessionExpiredException, org.apache.zookeeper.KeeperException$SessionMovedException;
    Code:
       0: aload_0
       1: getfield      #4                  // Field globalSessionTracker:Lorg/apache/zookeeper/server/SessionTrackerImpl;
       4: lload_1
       5: aload_3
       6: invokevirtual #32                 // Method org/apache/zookeeper/server/SessionTrackerImpl.checkSession:(JLjava/lang/Object;)V
       9: goto          22
      12: astore        4
      14: new           #34                 // class org/apache/zookeeper/KeeperException$SessionExpiredException
      17: dup
      18: invokespecial #35                 // Method org/apache/zookeeper/KeeperException$SessionExpiredException."<init>":()V
      21: athrow
      22: return
    Exception table:
       from    to  target type
           0     9    12   Class org/apache/zookeeper/KeeperException$UnknownSessionException

  public void setOwner(long, java.lang.Object) throws org.apache.zookeeper.KeeperException$SessionExpiredException;
    Code:
       0: aload_0
       1: getfield      #8                  // Field localSessionTracker:Lorg/apache/zookeeper/server/quorum/LocalSessionTracker;
       4: ifnull        19
       7: aload_0
       8: getfield      #8                  // Field localSessionTracker:Lorg/apache/zookeeper/server/quorum/LocalSessionTracker;
      11: lload_1
      12: aload_3
      13: invokevirtual #36                 // Method org/apache/zookeeper/server/quorum/LocalSessionTracker.setOwner:(JLjava/lang/Object;)V
      16: return
      17: astore        4
      19: aload_0
      20: getfield      #4                  // Field globalSessionTracker:Lorg/apache/zookeeper/server/SessionTrackerImpl;
      23: lload_1
      24: aload_3
      25: invokevirtual #37                 // Method org/apache/zookeeper/server/SessionTrackerImpl.setOwner:(JLjava/lang/Object;)V
      28: return
    Exception table:
       from    to  target type
           7    16    17   Class org/apache/zookeeper/KeeperException$SessionExpiredException

  public void dumpSessions(java.io.PrintWriter);
    Code:
       0: aload_0
       1: getfield      #8                  // Field localSessionTracker:Lorg/apache/zookeeper/server/quorum/LocalSessionTracker;
       4: ifnull        27
       7: aload_1
       8: ldc           #38                 // String Local
      10: invokevirtual #39                 // Method java/io/PrintWriter.print:(Ljava/lang/String;)V
      13: aload_0
      14: getfield      #8                  // Field localSessionTracker:Lorg/apache/zookeeper/server/quorum/LocalSessionTracker;
      17: aload_1
      18: invokevirtual #40                 // Method org/apache/zookeeper/server/quorum/LocalSessionTracker.dumpSessions:(Ljava/io/PrintWriter;)V
      21: aload_1
      22: ldc           #41                 // String Global
      24: invokevirtual #39                 // Method java/io/PrintWriter.print:(Ljava/lang/String;)V
      27: aload_0
      28: getfield      #4                  // Field globalSessionTracker:Lorg/apache/zookeeper/server/SessionTrackerImpl;
      31: aload_1
      32: invokevirtual #42                 // Method org/apache/zookeeper/server/SessionTrackerImpl.dumpSessions:(Ljava/io/PrintWriter;)V
      35: return

  public void setSessionClosing(long);
    Code:
       0: aload_0
       1: getfield      #8                  // Field localSessionTracker:Lorg/apache/zookeeper/server/quorum/LocalSessionTracker;
       4: ifnull        15
       7: aload_0
       8: getfield      #8                  // Field localSessionTracker:Lorg/apache/zookeeper/server/quorum/LocalSessionTracker;
      11: lload_1
      12: invokevirtual #43                 // Method org/apache/zookeeper/server/quorum/LocalSessionTracker.setSessionClosing:(J)V
      15: aload_0
      16: getfield      #4                  // Field globalSessionTracker:Lorg/apache/zookeeper/server/SessionTrackerImpl;
      19: lload_1
      20: invokevirtual #44                 // Method org/apache/zookeeper/server/SessionTrackerImpl.setSessionClosing:(J)V
      23: return

  public java.util.Map<java.lang.Long, java.util.Set<java.lang.Long>> getSessionExpiryMap();
    Code:
       0: aload_0
       1: getfield      #8                  // Field localSessionTracker:Lorg/apache/zookeeper/server/quorum/LocalSessionTracker;
       4: ifnull        18
       7: aload_0
       8: getfield      #8                  // Field localSessionTracker:Lorg/apache/zookeeper/server/quorum/LocalSessionTracker;
      11: invokevirtual #45                 // Method org/apache/zookeeper/server/quorum/LocalSessionTracker.getSessionExpiryMap:()Ljava/util/Map;
      14: astore_1
      15: goto          26
      18: new           #46                 // class java/util/TreeMap
      21: dup
      22: invokespecial #47                 // Method java/util/TreeMap."<init>":()V
      25: astore_1
      26: aload_1
      27: aload_0
      28: getfield      #4                  // Field globalSessionTracker:Lorg/apache/zookeeper/server/SessionTrackerImpl;
      31: invokevirtual #48                 // Method org/apache/zookeeper/server/SessionTrackerImpl.getSessionExpiryMap:()Ljava/util/Map;
      34: invokeinterface #49,  2           // InterfaceMethod java/util/Map.putAll:(Ljava/util/Map;)V
      39: aload_1
      40: areturn

  static {};
    Code:
       0: ldc           #50                 // class org/apache/zookeeper/server/quorum/LeaderSessionTracker
       2: invokestatic  #51                 // Method org/slf4j/LoggerFactory.getLogger:(Ljava/lang/Class;)Lorg/slf4j/Logger;
       5: putstatic     #17                 // Field LOG:Lorg/slf4j/Logger;
       8: return
}
