Compiled from "MethodRegistry.java"
public class org.assertj.core.internal.bytebuddy.dynamic.scaffold.MethodRegistry$Handler$ForImplementation$Compiled implements org.assertj.core.internal.bytebuddy.dynamic.scaffold.MethodRegistry$Handler$Compiled {
  private final org.assertj.core.internal.bytebuddy.implementation.bytecode.ByteCodeAppender byteCodeAppender;

  protected org.assertj.core.internal.bytebuddy.dynamic.scaffold.MethodRegistry$Handler$ForImplementation$Compiled(org.assertj.core.internal.bytebuddy.implementation.bytecode.ByteCodeAppender);
    Code:
       0: aload_0
       1: invokespecial #37                 // Method java/lang/Object."<init>":()V
       4: aload_0
       5: aload_1
       6: putfield      #39                 // Field byteCodeAppender:Lorg/assertj/core/internal/bytebuddy/implementation/bytecode/ByteCodeAppender;
       9: return

  public org.assertj.core.internal.bytebuddy.dynamic.scaffold.TypeWriter$MethodPool$Record assemble(org.assertj.core.internal.bytebuddy.description.method.MethodDescription, org.assertj.core.internal.bytebuddy.implementation.attribute.MethodAttributeAppender, org.assertj.core.internal.bytebuddy.description.modifier.Visibility);
    Code:
       0: new           #29                 // class org/assertj/core/internal/bytebuddy/dynamic/scaffold/TypeWriter$MethodPool$Record$ForDefinedMethod$WithBody
       3: dup
       4: aload_1
       5: aload_0
       6: getfield      #39                 // Field byteCodeAppender:Lorg/assertj/core/internal/bytebuddy/implementation/bytecode/ByteCodeAppender;
       9: aload_2
      10: aload_3
      11: invokespecial #46                 // Method org/assertj/core/internal/bytebuddy/dynamic/scaffold/TypeWriter$MethodPool$Record$ForDefinedMethod$WithBody."<init>":(Lorg/assertj/core/internal/bytebuddy/description/method/MethodDescription;Lorg/assertj/core/internal/bytebuddy/implementation/bytecode/ByteCodeAppender;Lorg/assertj/core/internal/bytebuddy/implementation/attribute/MethodAttributeAppender;Lorg/assertj/core/internal/bytebuddy/description/modifier/Visibility;)V
      14: areturn

  public boolean equals(java.lang.Object);
    Code:
       0: aload_1
       1: aload_0
       2: if_acmpne     7
       5: iconst_1
       6: ireturn
       7: aload_1
       8: instanceof    #2                  // class org/assertj/core/internal/bytebuddy/dynamic/scaffold/MethodRegistry$Handler$ForImplementation$Compiled
      11: ifne          16
      14: iconst_0
      15: ireturn
      16: aload_1
      17: checkcast     #2                  // class org/assertj/core/internal/bytebuddy/dynamic/scaffold/MethodRegistry$Handler$ForImplementation$Compiled
      20: astore_2
      21: aload_2
      22: aload_0
      23: invokevirtual #57                 // Method canEqual:(Ljava/lang/Object;)Z
      26: ifne          31
      29: iconst_0
      30: ireturn
      31: aload_0
      32: getfield      #39                 // Field byteCodeAppender:Lorg/assertj/core/internal/bytebuddy/implementation/bytecode/ByteCodeAppender;
      35: astore_3
      36: aload_2
      37: getfield      #39                 // Field byteCodeAppender:Lorg/assertj/core/internal/bytebuddy/implementation/bytecode/ByteCodeAppender;
      40: astore        4
      42: aload_3
      43: ifnonnull     54
      46: aload         4
      48: ifnull        65
      51: goto          63
      54: aload_3
      55: aload         4
      57: invokevirtual #59                 // Method java/lang/Object.equals:(Ljava/lang/Object;)Z
      60: ifne          65
      63: iconst_0
      64: ireturn
      65: iconst_1
      66: ireturn

  protected boolean canEqual(java.lang.Object);
    Code:
       0: aload_1
       1: instanceof    #2                  // class org/assertj/core/internal/bytebuddy/dynamic/scaffold/MethodRegistry$Handler$ForImplementation$Compiled
       4: ireturn

  public int hashCode();
    Code:
       0: bipush        59
       2: istore_1
       3: iconst_1
       4: istore_2
       5: aload_0
       6: getfield      #39                 // Field byteCodeAppender:Lorg/assertj/core/internal/bytebuddy/implementation/bytecode/ByteCodeAppender;
       9: astore_3
      10: iload_2
      11: bipush        59
      13: imul
      14: aload_3
      15: ifnonnull     23
      18: bipush        43
      20: goto          27
      23: aload_3
      24: invokevirtual #68                 // Method java/lang/Object.hashCode:()I
      27: iadd
      28: istore_2
      29: iload_2
      30: ireturn
}
