Compiled from "TypeInitializer.java"
public class org.assertj.core.internal.bytebuddy.dynamic.scaffold.TypeInitializer$Simple implements org.assertj.core.internal.bytebuddy.dynamic.scaffold.TypeInitializer {
  private final org.assertj.core.internal.bytebuddy.implementation.bytecode.ByteCodeAppender byteCodeAppender;

  public org.assertj.core.internal.bytebuddy.dynamic.scaffold.TypeInitializer$Simple(org.assertj.core.internal.bytebuddy.implementation.bytecode.ByteCodeAppender);
    Code:
       0: aload_0
       1: invokespecial #36                 // Method java/lang/Object."<init>":()V
       4: aload_0
       5: aload_1
       6: putfield      #38                 // Field byteCodeAppender:Lorg/assertj/core/internal/bytebuddy/implementation/bytecode/ByteCodeAppender;
       9: return

  public boolean isDefined();
    Code:
       0: iconst_1
       1: ireturn

  public org.assertj.core.internal.bytebuddy.dynamic.scaffold.TypeInitializer expandWith(org.assertj.core.internal.bytebuddy.implementation.bytecode.ByteCodeAppender);
    Code:
       0: new           #2                  // class org/assertj/core/internal/bytebuddy/dynamic/scaffold/TypeInitializer$Simple
       3: dup
       4: new           #28                 // class org/assertj/core/internal/bytebuddy/implementation/bytecode/ByteCodeAppender$Compound
       7: dup
       8: iconst_2
       9: anewarray     #25                 // class org/assertj/core/internal/bytebuddy/implementation/bytecode/ByteCodeAppender
      12: dup
      13: iconst_0
      14: aload_0
      15: getfield      #38                 // Field byteCodeAppender:Lorg/assertj/core/internal/bytebuddy/implementation/bytecode/ByteCodeAppender;
      18: aastore
      19: dup
      20: iconst_1
      21: aload_1
      22: aastore
      23: invokespecial #47                 // Method org/assertj/core/internal/bytebuddy/implementation/bytecode/ByteCodeAppender$Compound."<init>":([Lorg/assertj/core/internal/bytebuddy/implementation/bytecode/ByteCodeAppender;)V
      26: invokespecial #49                 // Method "<init>":(Lorg/assertj/core/internal/bytebuddy/implementation/bytecode/ByteCodeAppender;)V
      29: areturn

  public org.assertj.core.internal.bytebuddy.dynamic.scaffold.TypeWriter$MethodPool$Record wrap(org.assertj.core.internal.bytebuddy.dynamic.scaffold.TypeWriter$MethodPool$Record);
    Code:
       0: aload_1
       1: aload_0
       2: getfield      #38                 // Field byteCodeAppender:Lorg/assertj/core/internal/bytebuddy/implementation/bytecode/ByteCodeAppender;
       5: invokeinterface #55,  2           // InterfaceMethod org/assertj/core/internal/bytebuddy/dynamic/scaffold/TypeWriter$MethodPool$Record.prepend:(Lorg/assertj/core/internal/bytebuddy/implementation/bytecode/ByteCodeAppender;)Lorg/assertj/core/internal/bytebuddy/dynamic/scaffold/TypeWriter$MethodPool$Record;
      10: areturn

  public org.assertj.core.internal.bytebuddy.implementation.bytecode.ByteCodeAppender$Size apply(org.assertj.core.internal.bytebuddy.jar.asm.MethodVisitor, org.assertj.core.internal.bytebuddy.implementation.Implementation$Context, org.assertj.core.internal.bytebuddy.description.method.MethodDescription);
    Code:
       0: aload_0
       1: getfield      #38                 // Field byteCodeAppender:Lorg/assertj/core/internal/bytebuddy/implementation/bytecode/ByteCodeAppender;
       4: aload_1
       5: aload_2
       6: aload_3
       7: invokeinterface #61,  4           // InterfaceMethod org/assertj/core/internal/bytebuddy/implementation/bytecode/ByteCodeAppender.apply:(Lorg/assertj/core/internal/bytebuddy/jar/asm/MethodVisitor;Lorg/assertj/core/internal/bytebuddy/implementation/Implementation$Context;Lorg/assertj/core/internal/bytebuddy/description/method/MethodDescription;)Lorg/assertj/core/internal/bytebuddy/implementation/bytecode/ByteCodeAppender$Size;
      12: areturn

  public boolean equals(java.lang.Object);
    Code:
       0: aload_1
       1: aload_0
       2: if_acmpne     7
       5: iconst_1
       6: ireturn
       7: aload_1
       8: instanceof    #2                  // class org/assertj/core/internal/bytebuddy/dynamic/scaffold/TypeInitializer$Simple
      11: ifne          16
      14: iconst_0
      15: ireturn
      16: aload_1
      17: checkcast     #2                  // class org/assertj/core/internal/bytebuddy/dynamic/scaffold/TypeInitializer$Simple
      20: astore_2
      21: aload_2
      22: aload_0
      23: invokevirtual #72                 // Method canEqual:(Ljava/lang/Object;)Z
      26: ifne          31
      29: iconst_0
      30: ireturn
      31: aload_0
      32: getfield      #38                 // Field byteCodeAppender:Lorg/assertj/core/internal/bytebuddy/implementation/bytecode/ByteCodeAppender;
      35: astore_3
      36: aload_2
      37: getfield      #38                 // Field byteCodeAppender:Lorg/assertj/core/internal/bytebuddy/implementation/bytecode/ByteCodeAppender;
      40: astore        4
      42: aload_3
      43: ifnonnull     54
      46: aload         4
      48: ifnull        65
      51: goto          63
      54: aload_3
      55: aload         4
      57: invokevirtual #74                 // Method java/lang/Object.equals:(Ljava/lang/Object;)Z
      60: ifne          65
      63: iconst_0
      64: ireturn
      65: iconst_1
      66: ireturn

  protected boolean canEqual(java.lang.Object);
    Code:
       0: aload_1
       1: instanceof    #2                  // class org/assertj/core/internal/bytebuddy/dynamic/scaffold/TypeInitializer$Simple
       4: ireturn

  public int hashCode();
    Code:
       0: bipush        59
       2: istore_1
       3: iconst_1
       4: istore_2
       5: aload_0
       6: getfield      #38                 // Field byteCodeAppender:Lorg/assertj/core/internal/bytebuddy/implementation/bytecode/ByteCodeAppender;
       9: astore_3
      10: iload_2
      11: bipush        59
      13: imul
      14: aload_3
      15: ifnonnull     23
      18: bipush        43
      20: goto          27
      23: aload_3
      24: invokevirtual #83                 // Method java/lang/Object.hashCode:()I
      27: iadd
      28: istore_2
      29: iload_2
      30: ireturn
}
