Compiled from "TypeWriter.java"
public abstract class org.assertj.core.internal.bytebuddy.dynamic.scaffold.TypeWriter$Default<S> implements org.assertj.core.internal.bytebuddy.dynamic.scaffold.TypeWriter<S> {
  private static final java.lang.String DUMP_FOLDER;

  protected final org.assertj.core.internal.bytebuddy.description.type.TypeDescription instrumentedType;

  protected final org.assertj.core.internal.bytebuddy.ClassFileVersion classFileVersion;

  protected final org.assertj.core.internal.bytebuddy.dynamic.scaffold.TypeWriter$FieldPool fieldPool;

  protected final java.util.List<? extends org.assertj.core.internal.bytebuddy.dynamic.DynamicType> auxiliaryTypes;

  protected final org.assertj.core.internal.bytebuddy.description.field.FieldList<org.assertj.core.internal.bytebuddy.description.field.FieldDescription$InDefinedShape> fields;

  protected final org.assertj.core.internal.bytebuddy.description.method.MethodList<?> methods;

  protected final org.assertj.core.internal.bytebuddy.description.method.MethodList<?> instrumentedMethods;

  protected final org.assertj.core.internal.bytebuddy.implementation.LoadedTypeInitializer loadedTypeInitializer;

  protected final org.assertj.core.internal.bytebuddy.dynamic.scaffold.TypeInitializer typeInitializer;

  protected final org.assertj.core.internal.bytebuddy.implementation.attribute.TypeAttributeAppender typeAttributeAppender;

  protected final org.assertj.core.internal.bytebuddy.asm.AsmVisitorWrapper asmVisitorWrapper;

  protected final org.assertj.core.internal.bytebuddy.implementation.attribute.AnnotationValueFilter$Factory annotationValueFilterFactory;

  protected final org.assertj.core.internal.bytebuddy.implementation.attribute.AnnotationRetention annotationRetention;

  protected final org.assertj.core.internal.bytebuddy.implementation.auxiliary.AuxiliaryType$NamingStrategy auxiliaryTypeNamingStrategy;

  protected final org.assertj.core.internal.bytebuddy.implementation.Implementation$Context$Factory implementationContextFactory;

  protected final org.assertj.core.internal.bytebuddy.dynamic.scaffold.TypeValidation typeValidation;

  protected final org.assertj.core.internal.bytebuddy.pool.TypePool typePool;

  protected org.assertj.core.internal.bytebuddy.dynamic.scaffold.TypeWriter$Default(org.assertj.core.internal.bytebuddy.description.type.TypeDescription, org.assertj.core.internal.bytebuddy.ClassFileVersion, org.assertj.core.internal.bytebuddy.dynamic.scaffold.TypeWriter$FieldPool, java.util.List<? extends org.assertj.core.internal.bytebuddy.dynamic.DynamicType>, org.assertj.core.internal.bytebuddy.description.field.FieldList<org.assertj.core.internal.bytebuddy.description.field.FieldDescription$InDefinedShape>, org.assertj.core.internal.bytebuddy.description.method.MethodList<?>, org.assertj.core.internal.bytebuddy.description.method.MethodList<?>, org.assertj.core.internal.bytebuddy.implementation.LoadedTypeInitializer, org.assertj.core.internal.bytebuddy.dynamic.scaffold.TypeInitializer, org.assertj.core.internal.bytebuddy.implementation.attribute.TypeAttributeAppender, org.assertj.core.internal.bytebuddy.asm.AsmVisitorWrapper, org.assertj.core.internal.bytebuddy.implementation.attribute.AnnotationValueFilter$Factory, org.assertj.core.internal.bytebuddy.implementation.attribute.AnnotationRetention, org.assertj.core.internal.bytebuddy.implementation.auxiliary.AuxiliaryType$NamingStrategy, org.assertj.core.internal.bytebuddy.implementation.Implementation$Context$Factory, org.assertj.core.internal.bytebuddy.dynamic.scaffold.TypeValidation, org.assertj.core.internal.bytebuddy.pool.TypePool);
    Code:
       0: aload_0
       1: invokespecial #134                // Method java/lang/Object."<init>":()V
       4: aload_0
       5: aload_1
       6: putfield      #136                // Field instrumentedType:Lorg/assertj/core/internal/bytebuddy/description/type/TypeDescription;
       9: aload_0
      10: aload_2
      11: putfield      #138                // Field classFileVersion:Lorg/assertj/core/internal/bytebuddy/ClassFileVersion;
      14: aload_0
      15: aload_3
      16: putfield      #140                // Field fieldPool:Lorg/assertj/core/internal/bytebuddy/dynamic/scaffold/TypeWriter$FieldPool;
      19: aload_0
      20: aload         4
      22: putfield      #142                // Field auxiliaryTypes:Ljava/util/List;
      25: aload_0
      26: aload         5
      28: putfield      #144                // Field fields:Lorg/assertj/core/internal/bytebuddy/description/field/FieldList;
      31: aload_0
      32: aload         6
      34: putfield      #146                // Field methods:Lorg/assertj/core/internal/bytebuddy/description/method/MethodList;
      37: aload_0
      38: aload         7
      40: putfield      #148                // Field instrumentedMethods:Lorg/assertj/core/internal/bytebuddy/description/method/MethodList;
      43: aload_0
      44: aload         8
      46: putfield      #150                // Field loadedTypeInitializer:Lorg/assertj/core/internal/bytebuddy/implementation/LoadedTypeInitializer;
      49: aload_0
      50: aload         9
      52: putfield      #152                // Field typeInitializer:Lorg/assertj/core/internal/bytebuddy/dynamic/scaffold/TypeInitializer;
      55: aload_0
      56: aload         10
      58: putfield      #154                // Field typeAttributeAppender:Lorg/assertj/core/internal/bytebuddy/implementation/attribute/TypeAttributeAppender;
      61: aload_0
      62: aload         11
      64: putfield      #156                // Field asmVisitorWrapper:Lorg/assertj/core/internal/bytebuddy/asm/AsmVisitorWrapper;
      67: aload_0
      68: aload         14
      70: putfield      #158                // Field auxiliaryTypeNamingStrategy:Lorg/assertj/core/internal/bytebuddy/implementation/auxiliary/AuxiliaryType$NamingStrategy;
      73: aload_0
      74: aload         12
      76: putfield      #160                // Field annotationValueFilterFactory:Lorg/assertj/core/internal/bytebuddy/implementation/attribute/AnnotationValueFilter$Factory;
      79: aload_0
      80: aload         13
      82: putfield      #162                // Field annotationRetention:Lorg/assertj/core/internal/bytebuddy/implementation/attribute/AnnotationRetention;
      85: aload_0
      86: aload         15
      88: putfield      #164                // Field implementationContextFactory:Lorg/assertj/core/internal/bytebuddy/implementation/Implementation$Context$Factory;
      91: aload_0
      92: aload         16
      94: putfield      #166                // Field typeValidation:Lorg/assertj/core/internal/bytebuddy/dynamic/scaffold/TypeValidation;
      97: aload_0
      98: aload         17
     100: putfield      #168                // Field typePool:Lorg/assertj/core/internal/bytebuddy/pool/TypePool;
     103: return

  public static <U> org.assertj.core.internal.bytebuddy.dynamic.scaffold.TypeWriter<U> forCreation(org.assertj.core.internal.bytebuddy.dynamic.scaffold.MethodRegistry$Compiled, org.assertj.core.internal.bytebuddy.dynamic.scaffold.TypeWriter$FieldPool, org.assertj.core.internal.bytebuddy.implementation.attribute.TypeAttributeAppender, org.assertj.core.internal.bytebuddy.asm.AsmVisitorWrapper, org.assertj.core.internal.bytebuddy.ClassFileVersion, org.assertj.core.internal.bytebuddy.implementation.attribute.AnnotationValueFilter$Factory, org.assertj.core.internal.bytebuddy.implementation.attribute.AnnotationRetention, org.assertj.core.internal.bytebuddy.implementation.auxiliary.AuxiliaryType$NamingStrategy, org.assertj.core.internal.bytebuddy.implementation.Implementation$Context$Factory, org.assertj.core.internal.bytebuddy.dynamic.scaffold.TypeValidation, org.assertj.core.internal.bytebuddy.pool.TypePool);
    Code:
       0: new           #14                 // class org/assertj/core/internal/bytebuddy/dynamic/scaffold/TypeWriter$Default$ForCreation
       3: dup
       4: aload_0
       5: invokeinterface #177,  1          // InterfaceMethod org/assertj/core/internal/bytebuddy/dynamic/scaffold/MethodRegistry$Compiled.getInstrumentedType:()Lorg/assertj/core/internal/bytebuddy/description/type/TypeDescription;
      10: aload         4
      12: aload_1
      13: aload_0
      14: invokestatic  #183                // Method java/util/Collections.emptyList:()Ljava/util/List;
      17: aload_0
      18: invokeinterface #177,  1          // InterfaceMethod org/assertj/core/internal/bytebuddy/dynamic/scaffold/MethodRegistry$Compiled.getInstrumentedType:()Lorg/assertj/core/internal/bytebuddy/description/type/TypeDescription;
      23: invokeinterface #189,  1          // InterfaceMethod org/assertj/core/internal/bytebuddy/description/type/TypeDescription.getDeclaredFields:()Lorg/assertj/core/internal/bytebuddy/description/field/FieldList;
      28: aload_0
      29: invokeinterface #193,  1          // InterfaceMethod org/assertj/core/internal/bytebuddy/dynamic/scaffold/MethodRegistry$Compiled.getMethods:()Lorg/assertj/core/internal/bytebuddy/description/method/MethodList;
      34: aload_0
      35: invokeinterface #196,  1          // InterfaceMethod org/assertj/core/internal/bytebuddy/dynamic/scaffold/MethodRegistry$Compiled.getInstrumentedMethods:()Lorg/assertj/core/internal/bytebuddy/description/method/MethodList;
      40: aload_0
      41: invokeinterface #200,  1          // InterfaceMethod org/assertj/core/internal/bytebuddy/dynamic/scaffold/MethodRegistry$Compiled.getLoadedTypeInitializer:()Lorg/assertj/core/internal/bytebuddy/implementation/LoadedTypeInitializer;
      46: aload_0
      47: invokeinterface #204,  1          // InterfaceMethod org/assertj/core/internal/bytebuddy/dynamic/scaffold/MethodRegistry$Compiled.getTypeInitializer:()Lorg/assertj/core/internal/bytebuddy/dynamic/scaffold/TypeInitializer;
      52: aload_2
      53: aload_3
      54: aload         5
      56: aload         6
      58: aload         7
      60: aload         8
      62: aload         9
      64: aload         10
      66: invokespecial #207                // Method org/assertj/core/internal/bytebuddy/dynamic/scaffold/TypeWriter$Default$ForCreation."<init>":(Lorg/assertj/core/internal/bytebuddy/description/type/TypeDescription;Lorg/assertj/core/internal/bytebuddy/ClassFileVersion;Lorg/assertj/core/internal/bytebuddy/dynamic/scaffold/TypeWriter$FieldPool;Lorg/assertj/core/internal/bytebuddy/dynamic/scaffold/TypeWriter$MethodPool;Ljava/util/List;Lorg/assertj/core/internal/bytebuddy/description/field/FieldList;Lorg/assertj/core/internal/bytebuddy/description/method/MethodList;Lorg/assertj/core/internal/bytebuddy/description/method/MethodList;Lorg/assertj/core/internal/bytebuddy/implementation/LoadedTypeInitializer;Lorg/assertj/core/internal/bytebuddy/dynamic/scaffold/TypeInitializer;Lorg/assertj/core/internal/bytebuddy/implementation/attribute/TypeAttributeAppender;Lorg/assertj/core/internal/bytebuddy/asm/AsmVisitorWrapper;Lorg/assertj/core/internal/bytebuddy/implementation/attribute/AnnotationValueFilter$Factory;Lorg/assertj/core/internal/bytebuddy/implementation/attribute/AnnotationRetention;Lorg/assertj/core/internal/bytebuddy/implementation/auxiliary/AuxiliaryType$NamingStrategy;Lorg/assertj/core/internal/bytebuddy/implementation/Implementation$Context$Factory;Lorg/assertj/core/internal/bytebuddy/dynamic/scaffold/TypeValidation;Lorg/assertj/core/internal/bytebuddy/pool/TypePool;)V
      69: areturn

  public static <U> org.assertj.core.internal.bytebuddy.dynamic.scaffold.TypeWriter<U> forRedefinition(org.assertj.core.internal.bytebuddy.dynamic.scaffold.MethodRegistry$Prepared, org.assertj.core.internal.bytebuddy.dynamic.scaffold.TypeWriter$FieldPool, org.assertj.core.internal.bytebuddy.implementation.attribute.TypeAttributeAppender, org.assertj.core.internal.bytebuddy.asm.AsmVisitorWrapper, org.assertj.core.internal.bytebuddy.ClassFileVersion, org.assertj.core.internal.bytebuddy.implementation.attribute.AnnotationValueFilter$Factory, org.assertj.core.internal.bytebuddy.implementation.attribute.AnnotationRetention, org.assertj.core.internal.bytebuddy.implementation.auxiliary.AuxiliaryType$NamingStrategy, org.assertj.core.internal.bytebuddy.implementation.Implementation$Context$Factory, org.assertj.core.internal.bytebuddy.dynamic.scaffold.TypeValidation, org.assertj.core.internal.bytebuddy.pool.TypePool, org.assertj.core.internal.bytebuddy.description.type.TypeDescription, org.assertj.core.internal.bytebuddy.dynamic.ClassFileLocator);
    Code:
       0: new           #17                 // class org/assertj/core/internal/bytebuddy/dynamic/scaffold/TypeWriter$Default$ForInlining
       3: dup
       4: aload_0
       5: invokeinterface #212,  1          // InterfaceMethod org/assertj/core/internal/bytebuddy/dynamic/scaffold/MethodRegistry$Prepared.getInstrumentedType:()Lorg/assertj/core/internal/bytebuddy/description/type/TypeDescription;
      10: aload         4
      12: aload_1
      13: aload_0
      14: getstatic     #216                // Field org/assertj/core/internal/bytebuddy/dynamic/scaffold/subclass/SubclassImplementationTarget$Factory.LEVEL_TYPE:Lorg/assertj/core/internal/bytebuddy/dynamic/scaffold/subclass/SubclassImplementationTarget$Factory;
      17: invokestatic  #183                // Method java/util/Collections.emptyList:()Ljava/util/List;
      20: aload_0
      21: invokeinterface #212,  1          // InterfaceMethod org/assertj/core/internal/bytebuddy/dynamic/scaffold/MethodRegistry$Prepared.getInstrumentedType:()Lorg/assertj/core/internal/bytebuddy/description/type/TypeDescription;
      26: invokeinterface #189,  1          // InterfaceMethod org/assertj/core/internal/bytebuddy/description/type/TypeDescription.getDeclaredFields:()Lorg/assertj/core/internal/bytebuddy/description/field/FieldList;
      31: aload_0
      32: invokeinterface #217,  1          // InterfaceMethod org/assertj/core/internal/bytebuddy/dynamic/scaffold/MethodRegistry$Prepared.getMethods:()Lorg/assertj/core/internal/bytebuddy/description/method/MethodList;
      37: aload_0
      38: invokeinterface #218,  1          // InterfaceMethod org/assertj/core/internal/bytebuddy/dynamic/scaffold/MethodRegistry$Prepared.getInstrumentedMethods:()Lorg/assertj/core/internal/bytebuddy/description/method/MethodList;
      43: aload_0
      44: invokeinterface #219,  1          // InterfaceMethod org/assertj/core/internal/bytebuddy/dynamic/scaffold/MethodRegistry$Prepared.getLoadedTypeInitializer:()Lorg/assertj/core/internal/bytebuddy/implementation/LoadedTypeInitializer;
      49: aload_0
      50: invokeinterface #220,  1          // InterfaceMethod org/assertj/core/internal/bytebuddy/dynamic/scaffold/MethodRegistry$Prepared.getTypeInitializer:()Lorg/assertj/core/internal/bytebuddy/dynamic/scaffold/TypeInitializer;
      55: aload_2
      56: aload_3
      57: aload         5
      59: aload         6
      61: aload         7
      63: aload         8
      65: aload         9
      67: aload         10
      69: aload         11
      71: aload         12
      73: getstatic     #224                // Field org/assertj/core/internal/bytebuddy/dynamic/scaffold/inline/MethodRebaseResolver$Disabled.INSTANCE:Lorg/assertj/core/internal/bytebuddy/dynamic/scaffold/inline/MethodRebaseResolver$Disabled;
      76: invokespecial #227                // Method org/assertj/core/internal/bytebuddy/dynamic/scaffold/TypeWriter$Default$ForInlining."<init>":(Lorg/assertj/core/internal/bytebuddy/description/type/TypeDescription;Lorg/assertj/core/internal/bytebuddy/ClassFileVersion;Lorg/assertj/core/internal/bytebuddy/dynamic/scaffold/TypeWriter$FieldPool;Lorg/assertj/core/internal/bytebuddy/dynamic/scaffold/MethodRegistry$Prepared;Lorg/assertj/core/internal/bytebuddy/implementation/Implementation$Target$Factory;Ljava/util/List;Lorg/assertj/core/internal/bytebuddy/description/field/FieldList;Lorg/assertj/core/internal/bytebuddy/description/method/MethodList;Lorg/assertj/core/internal/bytebuddy/description/method/MethodList;Lorg/assertj/core/internal/bytebuddy/implementation/LoadedTypeInitializer;Lorg/assertj/core/internal/bytebuddy/dynamic/scaffold/TypeInitializer;Lorg/assertj/core/internal/bytebuddy/implementation/attribute/TypeAttributeAppender;Lorg/assertj/core/internal/bytebuddy/asm/AsmVisitorWrapper;Lorg/assertj/core/internal/bytebuddy/implementation/attribute/AnnotationValueFilter$Factory;Lorg/assertj/core/internal/bytebuddy/implementation/attribute/AnnotationRetention;Lorg/assertj/core/internal/bytebuddy/implementation/auxiliary/AuxiliaryType$NamingStrategy;Lorg/assertj/core/internal/bytebuddy/implementation/Implementation$Context$Factory;Lorg/assertj/core/internal/bytebuddy/dynamic/scaffold/TypeValidation;Lorg/assertj/core/internal/bytebuddy/pool/TypePool;Lorg/assertj/core/internal/bytebuddy/description/type/TypeDescription;Lorg/assertj/core/internal/bytebuddy/dynamic/ClassFileLocator;Lorg/assertj/core/internal/bytebuddy/dynamic/scaffold/inline/MethodRebaseResolver;)V
      79: areturn

  public static <U> org.assertj.core.internal.bytebuddy.dynamic.scaffold.TypeWriter<U> forRebasing(org.assertj.core.internal.bytebuddy.dynamic.scaffold.MethodRegistry$Prepared, org.assertj.core.internal.bytebuddy.dynamic.scaffold.TypeWriter$FieldPool, org.assertj.core.internal.bytebuddy.implementation.attribute.TypeAttributeAppender, org.assertj.core.internal.bytebuddy.asm.AsmVisitorWrapper, org.assertj.core.internal.bytebuddy.ClassFileVersion, org.assertj.core.internal.bytebuddy.implementation.attribute.AnnotationValueFilter$Factory, org.assertj.core.internal.bytebuddy.implementation.attribute.AnnotationRetention, org.assertj.core.internal.bytebuddy.implementation.auxiliary.AuxiliaryType$NamingStrategy, org.assertj.core.internal.bytebuddy.implementation.Implementation$Context$Factory, org.assertj.core.internal.bytebuddy.dynamic.scaffold.TypeValidation, org.assertj.core.internal.bytebuddy.pool.TypePool, org.assertj.core.internal.bytebuddy.description.type.TypeDescription, org.assertj.core.internal.bytebuddy.dynamic.ClassFileLocator, org.assertj.core.internal.bytebuddy.dynamic.scaffold.inline.MethodRebaseResolver);
    Code:
       0: new           #17                 // class org/assertj/core/internal/bytebuddy/dynamic/scaffold/TypeWriter$Default$ForInlining
       3: dup
       4: aload_0
       5: invokeinterface #212,  1          // InterfaceMethod org/assertj/core/internal/bytebuddy/dynamic/scaffold/MethodRegistry$Prepared.getInstrumentedType:()Lorg/assertj/core/internal/bytebuddy/description/type/TypeDescription;
      10: aload         4
      12: aload_1
      13: aload_0
      14: new           #72                 // class org/assertj/core/internal/bytebuddy/dynamic/scaffold/inline/RebaseImplementationTarget$Factory
      17: dup
      18: aload         13
      20: invokespecial #236                // Method org/assertj/core/internal/bytebuddy/dynamic/scaffold/inline/RebaseImplementationTarget$Factory."<init>":(Lorg/assertj/core/internal/bytebuddy/dynamic/scaffold/inline/MethodRebaseResolver;)V
      23: aload         13
      25: invokeinterface #239,  1          // InterfaceMethod org/assertj/core/internal/bytebuddy/dynamic/scaffold/inline/MethodRebaseResolver.getAuxiliaryTypes:()Ljava/util/List;
      30: aload_0
      31: invokeinterface #212,  1          // InterfaceMethod org/assertj/core/internal/bytebuddy/dynamic/scaffold/MethodRegistry$Prepared.getInstrumentedType:()Lorg/assertj/core/internal/bytebuddy/description/type/TypeDescription;
      36: invokeinterface #189,  1          // InterfaceMethod org/assertj/core/internal/bytebuddy/description/type/TypeDescription.getDeclaredFields:()Lorg/assertj/core/internal/bytebuddy/description/field/FieldList;
      41: aload_0
      42: invokeinterface #217,  1          // InterfaceMethod org/assertj/core/internal/bytebuddy/dynamic/scaffold/MethodRegistry$Prepared.getMethods:()Lorg/assertj/core/internal/bytebuddy/description/method/MethodList;
      47: aload_0
      48: invokeinterface #218,  1          // InterfaceMethod org/assertj/core/internal/bytebuddy/dynamic/scaffold/MethodRegistry$Prepared.getInstrumentedMethods:()Lorg/assertj/core/internal/bytebuddy/description/method/MethodList;
      53: aload_0
      54: invokeinterface #219,  1          // InterfaceMethod org/assertj/core/internal/bytebuddy/dynamic/scaffold/MethodRegistry$Prepared.getLoadedTypeInitializer:()Lorg/assertj/core/internal/bytebuddy/implementation/LoadedTypeInitializer;
      59: aload_0
      60: invokeinterface #220,  1          // InterfaceMethod org/assertj/core/internal/bytebuddy/dynamic/scaffold/MethodRegistry$Prepared.getTypeInitializer:()Lorg/assertj/core/internal/bytebuddy/dynamic/scaffold/TypeInitializer;
      65: aload_2
      66: aload_3
      67: aload         5
      69: aload         6
      71: aload         7
      73: aload         8
      75: aload         9
      77: aload         10
      79: aload         11
      81: aload         12
      83: aload         13
      85: invokespecial #227                // Method org/assertj/core/internal/bytebuddy/dynamic/scaffold/TypeWriter$Default$ForInlining."<init>":(Lorg/assertj/core/internal/bytebuddy/description/type/TypeDescription;Lorg/assertj/core/internal/bytebuddy/ClassFileVersion;Lorg/assertj/core/internal/bytebuddy/dynamic/scaffold/TypeWriter$FieldPool;Lorg/assertj/core/internal/bytebuddy/dynamic/scaffold/MethodRegistry$Prepared;Lorg/assertj/core/internal/bytebuddy/implementation/Implementation$Target$Factory;Ljava/util/List;Lorg/assertj/core/internal/bytebuddy/description/field/FieldList;Lorg/assertj/core/internal/bytebuddy/description/method/MethodList;Lorg/assertj/core/internal/bytebuddy/description/method/MethodList;Lorg/assertj/core/internal/bytebuddy/implementation/LoadedTypeInitializer;Lorg/assertj/core/internal/bytebuddy/dynamic/scaffold/TypeInitializer;Lorg/assertj/core/internal/bytebuddy/implementation/attribute/TypeAttributeAppender;Lorg/assertj/core/internal/bytebuddy/asm/AsmVisitorWrapper;Lorg/assertj/core/internal/bytebuddy/implementation/attribute/AnnotationValueFilter$Factory;Lorg/assertj/core/internal/bytebuddy/implementation/attribute/AnnotationRetention;Lorg/assertj/core/internal/bytebuddy/implementation/auxiliary/AuxiliaryType$NamingStrategy;Lorg/assertj/core/internal/bytebuddy/implementation/Implementation$Context$Factory;Lorg/assertj/core/internal/bytebuddy/dynamic/scaffold/TypeValidation;Lorg/assertj/core/internal/bytebuddy/pool/TypePool;Lorg/assertj/core/internal/bytebuddy/description/type/TypeDescription;Lorg/assertj/core/internal/bytebuddy/dynamic/ClassFileLocator;Lorg/assertj/core/internal/bytebuddy/dynamic/scaffold/inline/MethodRebaseResolver;)V
      88: areturn

  public org.assertj.core.internal.bytebuddy.dynamic.DynamicType$Unloaded<S> make(org.assertj.core.internal.bytebuddy.dynamic.TypeResolutionStrategy$Resolved);
    Code:
       0: aload_0
       1: aload_1
       2: aload_0
       3: getfield      #152                // Field typeInitializer:Lorg/assertj/core/internal/bytebuddy/dynamic/scaffold/TypeInitializer;
       6: invokeinterface #254,  2          // InterfaceMethod org/assertj/core/internal/bytebuddy/dynamic/TypeResolutionStrategy$Resolved.injectedInto:(Lorg/assertj/core/internal/bytebuddy/dynamic/scaffold/TypeInitializer;)Lorg/assertj/core/internal/bytebuddy/dynamic/scaffold/TypeInitializer;
      11: invokevirtual #258                // Method create:(Lorg/assertj/core/internal/bytebuddy/dynamic/scaffold/TypeInitializer;)Lorg/assertj/core/internal/bytebuddy/dynamic/scaffold/TypeWriter$Default$UnresolvedType;
      14: astore_2
      15: getstatic     #260                // Field DUMP_FOLDER:Ljava/lang/String;
      18: ifnull        51
      21: new           #11                 // class org/assertj/core/internal/bytebuddy/dynamic/scaffold/TypeWriter$Default$ClassDumpAction
      24: dup
      25: getstatic     #260                // Field DUMP_FOLDER:Ljava/lang/String;
      28: aload_0
      29: getfield      #136                // Field instrumentedType:Lorg/assertj/core/internal/bytebuddy/description/type/TypeDescription;
      32: aload_2
      33: invokevirtual #264                // Method org/assertj/core/internal/bytebuddy/dynamic/scaffold/TypeWriter$Default$UnresolvedType.getBinaryRepresentation:()[B
      36: invokespecial #267                // Method org/assertj/core/internal/bytebuddy/dynamic/scaffold/TypeWriter$Default$ClassDumpAction."<init>":(Ljava/lang/String;Lorg/assertj/core/internal/bytebuddy/description/type/TypeDescription;[B)V
      39: invokestatic  #273                // Method java/security/AccessController.doPrivileged:(Ljava/security/PrivilegedExceptionAction;)Ljava/lang/Object;
      42: pop
      43: goto          51
      46: astore_3
      47: aload_3
      48: invokevirtual #276                // Method java/lang/Exception.printStackTrace:()V
      51: aload_2
      52: aload_1
      53: invokevirtual #279                // Method org/assertj/core/internal/bytebuddy/dynamic/scaffold/TypeWriter$Default$UnresolvedType.toDynamicType:(Lorg/assertj/core/internal/bytebuddy/dynamic/TypeResolutionStrategy$Resolved;)Lorg/assertj/core/internal/bytebuddy/dynamic/DynamicType$Unloaded;
      56: areturn
    Exception table:
       from    to  target type
          21    43    46   Class java/lang/Exception

  protected abstract org.assertj.core.internal.bytebuddy.dynamic.scaffold.TypeWriter$Default<S>.UnresolvedType create(org.assertj.core.internal.bytebuddy.dynamic.scaffold.TypeInitializer);

  public boolean equals(java.lang.Object);
    Code:
       0: aload_1
       1: aload_0
       2: if_acmpne     7
       5: iconst_1
       6: ireturn
       7: aload_1
       8: instanceof    #2                  // class org/assertj/core/internal/bytebuddy/dynamic/scaffold/TypeWriter$Default
      11: ifne          16
      14: iconst_0
      15: ireturn
      16: aload_1
      17: checkcast     #2                  // class org/assertj/core/internal/bytebuddy/dynamic/scaffold/TypeWriter$Default
      20: astore_2
      21: aload_2
      22: aload_0
      23: invokevirtual #291                // Method canEqual:(Ljava/lang/Object;)Z
      26: ifne          31
      29: iconst_0
      30: ireturn
      31: aload_0
      32: getfield      #136                // Field instrumentedType:Lorg/assertj/core/internal/bytebuddy/description/type/TypeDescription;
      35: astore_3
      36: aload_2
      37: getfield      #136                // Field instrumentedType:Lorg/assertj/core/internal/bytebuddy/description/type/TypeDescription;
      40: astore        4
      42: aload_3
      43: ifnonnull     54
      46: aload         4
      48: ifnull        65
      51: goto          63
      54: aload_3
      55: aload         4
      57: invokevirtual #293                // Method java/lang/Object.equals:(Ljava/lang/Object;)Z
      60: ifne          65
      63: iconst_0
      64: ireturn
      65: aload_0
      66: getfield      #138                // Field classFileVersion:Lorg/assertj/core/internal/bytebuddy/ClassFileVersion;
      69: astore        5
      71: aload_2
      72: getfield      #138                // Field classFileVersion:Lorg/assertj/core/internal/bytebuddy/ClassFileVersion;
      75: astore        6
      77: aload         5
      79: ifnonnull     90
      82: aload         6
      84: ifnull        102
      87: goto          100
      90: aload         5
      92: aload         6
      94: invokevirtual #293                // Method java/lang/Object.equals:(Ljava/lang/Object;)Z
      97: ifne          102
     100: iconst_0
     101: ireturn
     102: aload_0
     103: getfield      #140                // Field fieldPool:Lorg/assertj/core/internal/bytebuddy/dynamic/scaffold/TypeWriter$FieldPool;
     106: astore        7
     108: aload_2
     109: getfield      #140                // Field fieldPool:Lorg/assertj/core/internal/bytebuddy/dynamic/scaffold/TypeWriter$FieldPool;
     112: astore        8
     114: aload         7
     116: ifnonnull     127
     119: aload         8
     121: ifnull        139
     124: goto          137
     127: aload         7
     129: aload         8
     131: invokevirtual #293                // Method java/lang/Object.equals:(Ljava/lang/Object;)Z
     134: ifne          139
     137: iconst_0
     138: ireturn
     139: aload_0
     140: getfield      #142                // Field auxiliaryTypes:Ljava/util/List;
     143: astore        9
     145: aload_2
     146: getfield      #142                // Field auxiliaryTypes:Ljava/util/List;
     149: astore        10
     151: aload         9
     153: ifnonnull     164
     156: aload         10
     158: ifnull        176
     161: goto          174
     164: aload         9
     166: aload         10
     168: invokevirtual #293                // Method java/lang/Object.equals:(Ljava/lang/Object;)Z
     171: ifne          176
     174: iconst_0
     175: ireturn
     176: aload_0
     177: getfield      #144                // Field fields:Lorg/assertj/core/internal/bytebuddy/description/field/FieldList;
     180: astore        11
     182: aload_2
     183: getfield      #144                // Field fields:Lorg/assertj/core/internal/bytebuddy/description/field/FieldList;
     186: astore        12
     188: aload         11
     190: ifnonnull     201
     193: aload         12
     195: ifnull        213
     198: goto          211
     201: aload         11
     203: aload         12
     205: invokevirtual #293                // Method java/lang/Object.equals:(Ljava/lang/Object;)Z
     208: ifne          213
     211: iconst_0
     212: ireturn
     213: aload_0
     214: getfield      #146                // Field methods:Lorg/assertj/core/internal/bytebuddy/description/method/MethodList;
     217: astore        13
     219: aload_2
     220: getfield      #146                // Field methods:Lorg/assertj/core/internal/bytebuddy/description/method/MethodList;
     223: astore        14
     225: aload         13
     227: ifnonnull     238
     230: aload         14
     232: ifnull        250
     235: goto          248
     238: aload         13
     240: aload         14
     242: invokevirtual #293                // Method java/lang/Object.equals:(Ljava/lang/Object;)Z
     245: ifne          250
     248: iconst_0
     249: ireturn
     250: aload_0
     251: getfield      #148                // Field instrumentedMethods:Lorg/assertj/core/internal/bytebuddy/description/method/MethodList;
     254: astore        15
     256: aload_2
     257: getfield      #148                // Field instrumentedMethods:Lorg/assertj/core/internal/bytebuddy/description/method/MethodList;
     260: astore        16
     262: aload         15
     264: ifnonnull     275
     267: aload         16
     269: ifnull        287
     272: goto          285
     275: aload         15
     277: aload         16
     279: invokevirtual #293                // Method java/lang/Object.equals:(Ljava/lang/Object;)Z
     282: ifne          287
     285: iconst_0
     286: ireturn
     287: aload_0
     288: getfield      #150                // Field loadedTypeInitializer:Lorg/assertj/core/internal/bytebuddy/implementation/LoadedTypeInitializer;
     291: astore        17
     293: aload_2
     294: getfield      #150                // Field loadedTypeInitializer:Lorg/assertj/core/internal/bytebuddy/implementation/LoadedTypeInitializer;
     297: astore        18
     299: aload         17
     301: ifnonnull     312
     304: aload         18
     306: ifnull        324
     309: goto          322
     312: aload         17
     314: aload         18
     316: invokevirtual #293                // Method java/lang/Object.equals:(Ljava/lang/Object;)Z
     319: ifne          324
     322: iconst_0
     323: ireturn
     324: aload_0
     325: getfield      #152                // Field typeInitializer:Lorg/assertj/core/internal/bytebuddy/dynamic/scaffold/TypeInitializer;
     328: astore        19
     330: aload_2
     331: getfield      #152                // Field typeInitializer:Lorg/assertj/core/internal/bytebuddy/dynamic/scaffold/TypeInitializer;
     334: astore        20
     336: aload         19
     338: ifnonnull     349
     341: aload         20
     343: ifnull        361
     346: goto          359
     349: aload         19
     351: aload         20
     353: invokevirtual #293                // Method java/lang/Object.equals:(Ljava/lang/Object;)Z
     356: ifne          361
     359: iconst_0
     360: ireturn
     361: aload_0
     362: getfield      #154                // Field typeAttributeAppender:Lorg/assertj/core/internal/bytebuddy/implementation/attribute/TypeAttributeAppender;
     365: astore        21
     367: aload_2
     368: getfield      #154                // Field typeAttributeAppender:Lorg/assertj/core/internal/bytebuddy/implementation/attribute/TypeAttributeAppender;
     371: astore        22
     373: aload         21
     375: ifnonnull     386
     378: aload         22
     380: ifnull        398
     383: goto          396
     386: aload         21
     388: aload         22
     390: invokevirtual #293                // Method java/lang/Object.equals:(Ljava/lang/Object;)Z
     393: ifne          398
     396: iconst_0
     397: ireturn
     398: aload_0
     399: getfield      #156                // Field asmVisitorWrapper:Lorg/assertj/core/internal/bytebuddy/asm/AsmVisitorWrapper;
     402: astore        23
     404: aload_2
     405: getfield      #156                // Field asmVisitorWrapper:Lorg/assertj/core/internal/bytebuddy/asm/AsmVisitorWrapper;
     408: astore        24
     410: aload         23
     412: ifnonnull     423
     415: aload         24
     417: ifnull        435
     420: goto          433
     423: aload         23
     425: aload         24
     427: invokevirtual #293                // Method java/lang/Object.equals:(Ljava/lang/Object;)Z
     430: ifne          435
     433: iconst_0
     434: ireturn
     435: aload_0
     436: getfield      #160                // Field annotationValueFilterFactory:Lorg/assertj/core/internal/bytebuddy/implementation/attribute/AnnotationValueFilter$Factory;
     439: astore        25
     441: aload_2
     442: getfield      #160                // Field annotationValueFilterFactory:Lorg/assertj/core/internal/bytebuddy/implementation/attribute/AnnotationValueFilter$Factory;
     445: astore        26
     447: aload         25
     449: ifnonnull     460
     452: aload         26
     454: ifnull        472
     457: goto          470
     460: aload         25
     462: aload         26
     464: invokevirtual #293                // Method java/lang/Object.equals:(Ljava/lang/Object;)Z
     467: ifne          472
     470: iconst_0
     471: ireturn
     472: aload_0
     473: getfield      #162                // Field annotationRetention:Lorg/assertj/core/internal/bytebuddy/implementation/attribute/AnnotationRetention;
     476: astore        27
     478: aload_2
     479: getfield      #162                // Field annotationRetention:Lorg/assertj/core/internal/bytebuddy/implementation/attribute/AnnotationRetention;
     482: astore        28
     484: aload         27
     486: ifnonnull     497
     489: aload         28
     491: ifnull        509
     494: goto          507
     497: aload         27
     499: aload         28
     501: invokevirtual #293                // Method java/lang/Object.equals:(Ljava/lang/Object;)Z
     504: ifne          509
     507: iconst_0
     508: ireturn
     509: aload_0
     510: getfield      #158                // Field auxiliaryTypeNamingStrategy:Lorg/assertj/core/internal/bytebuddy/implementation/auxiliary/AuxiliaryType$NamingStrategy;
     513: astore        29
     515: aload_2
     516: getfield      #158                // Field auxiliaryTypeNamingStrategy:Lorg/assertj/core/internal/bytebuddy/implementation/auxiliary/AuxiliaryType$NamingStrategy;
     519: astore        30
     521: aload         29
     523: ifnonnull     534
     526: aload         30
     528: ifnull        546
     531: goto          544
     534: aload         29
     536: aload         30
     538: invokevirtual #293                // Method java/lang/Object.equals:(Ljava/lang/Object;)Z
     541: ifne          546
     544: iconst_0
     545: ireturn
     546: aload_0
     547: getfield      #164                // Field implementationContextFactory:Lorg/assertj/core/internal/bytebuddy/implementation/Implementation$Context$Factory;
     550: astore        31
     552: aload_2
     553: getfield      #164                // Field implementationContextFactory:Lorg/assertj/core/internal/bytebuddy/implementation/Implementation$Context$Factory;
     556: astore        32
     558: aload         31
     560: ifnonnull     571
     563: aload         32
     565: ifnull        583
     568: goto          581
     571: aload         31
     573: aload         32
     575: invokevirtual #293                // Method java/lang/Object.equals:(Ljava/lang/Object;)Z
     578: ifne          583
     581: iconst_0
     582: ireturn
     583: aload_0
     584: getfield      #166                // Field typeValidation:Lorg/assertj/core/internal/bytebuddy/dynamic/scaffold/TypeValidation;
     587: astore        33
     589: aload_2
     590: getfield      #166                // Field typeValidation:Lorg/assertj/core/internal/bytebuddy/dynamic/scaffold/TypeValidation;
     593: astore        34
     595: aload         33
     597: ifnonnull     608
     600: aload         34
     602: ifnull        620
     605: goto          618
     608: aload         33
     610: aload         34
     612: invokevirtual #293                // Method java/lang/Object.equals:(Ljava/lang/Object;)Z
     615: ifne          620
     618: iconst_0
     619: ireturn
     620: aload_0
     621: getfield      #168                // Field typePool:Lorg/assertj/core/internal/bytebuddy/pool/TypePool;
     624: astore        35
     626: aload_2
     627: getfield      #168                // Field typePool:Lorg/assertj/core/internal/bytebuddy/pool/TypePool;
     630: astore        36
     632: aload         35
     634: ifnonnull     645
     637: aload         36
     639: ifnull        657
     642: goto          655
     645: aload         35
     647: aload         36
     649: invokevirtual #293                // Method java/lang/Object.equals:(Ljava/lang/Object;)Z
     652: ifne          657
     655: iconst_0
     656: ireturn
     657: iconst_1
     658: ireturn

  protected boolean canEqual(java.lang.Object);
    Code:
       0: aload_1
       1: instanceof    #2                  // class org/assertj/core/internal/bytebuddy/dynamic/scaffold/TypeWriter$Default
       4: ireturn

  public int hashCode();
    Code:
       0: bipush        59
       2: istore_1
       3: iconst_1
       4: istore_2
       5: aload_0
       6: getfield      #136                // Field instrumentedType:Lorg/assertj/core/internal/bytebuddy/description/type/TypeDescription;
       9: astore_3
      10: iload_2
      11: bipush        59
      13: imul
      14: aload_3
      15: ifnonnull     23
      18: bipush        43
      20: goto          27
      23: aload_3
      24: invokevirtual #335                // Method java/lang/Object.hashCode:()I
      27: iadd
      28: istore_2
      29: aload_0
      30: getfield      #138                // Field classFileVersion:Lorg/assertj/core/internal/bytebuddy/ClassFileVersion;
      33: astore        4
      35: iload_2
      36: bipush        59
      38: imul
      39: aload         4
      41: ifnonnull     49
      44: bipush        43
      46: goto          54
      49: aload         4
      51: invokevirtual #335                // Method java/lang/Object.hashCode:()I
      54: iadd
      55: istore_2
      56: aload_0
      57: getfield      #140                // Field fieldPool:Lorg/assertj/core/internal/bytebuddy/dynamic/scaffold/TypeWriter$FieldPool;
      60: astore        5
      62: iload_2
      63: bipush        59
      65: imul
      66: aload         5
      68: ifnonnull     76
      71: bipush        43
      73: goto          81
      76: aload         5
      78: invokevirtual #335                // Method java/lang/Object.hashCode:()I
      81: iadd
      82: istore_2
      83: aload_0
      84: getfield      #142                // Field auxiliaryTypes:Ljava/util/List;
      87: astore        6
      89: iload_2
      90: bipush        59
      92: imul
      93: aload         6
      95: ifnonnull     103
      98: bipush        43
     100: goto          108
     103: aload         6
     105: invokevirtual #335                // Method java/lang/Object.hashCode:()I
     108: iadd
     109: istore_2
     110: aload_0
     111: getfield      #144                // Field fields:Lorg/assertj/core/internal/bytebuddy/description/field/FieldList;
     114: astore        7
     116: iload_2
     117: bipush        59
     119: imul
     120: aload         7
     122: ifnonnull     130
     125: bipush        43
     127: goto          135
     130: aload         7
     132: invokevirtual #335                // Method java/lang/Object.hashCode:()I
     135: iadd
     136: istore_2
     137: aload_0
     138: getfield      #146                // Field methods:Lorg/assertj/core/internal/bytebuddy/description/method/MethodList;
     141: astore        8
     143: iload_2
     144: bipush        59
     146: imul
     147: aload         8
     149: ifnonnull     157
     152: bipush        43
     154: goto          162
     157: aload         8
     159: invokevirtual #335                // Method java/lang/Object.hashCode:()I
     162: iadd
     163: istore_2
     164: aload_0
     165: getfield      #148                // Field instrumentedMethods:Lorg/assertj/core/internal/bytebuddy/description/method/MethodList;
     168: astore        9
     170: iload_2
     171: bipush        59
     173: imul
     174: aload         9
     176: ifnonnull     184
     179: bipush        43
     181: goto          189
     184: aload         9
     186: invokevirtual #335                // Method java/lang/Object.hashCode:()I
     189: iadd
     190: istore_2
     191: aload_0
     192: getfield      #150                // Field loadedTypeInitializer:Lorg/assertj/core/internal/bytebuddy/implementation/LoadedTypeInitializer;
     195: astore        10
     197: iload_2
     198: bipush        59
     200: imul
     201: aload         10
     203: ifnonnull     211
     206: bipush        43
     208: goto          216
     211: aload         10
     213: invokevirtual #335                // Method java/lang/Object.hashCode:()I
     216: iadd
     217: istore_2
     218: aload_0
     219: getfield      #152                // Field typeInitializer:Lorg/assertj/core/internal/bytebuddy/dynamic/scaffold/TypeInitializer;
     222: astore        11
     224: iload_2
     225: bipush        59
     227: imul
     228: aload         11
     230: ifnonnull     238
     233: bipush        43
     235: goto          243
     238: aload         11
     240: invokevirtual #335                // Method java/lang/Object.hashCode:()I
     243: iadd
     244: istore_2
     245: aload_0
     246: getfield      #154                // Field typeAttributeAppender:Lorg/assertj/core/internal/bytebuddy/implementation/attribute/TypeAttributeAppender;
     249: astore        12
     251: iload_2
     252: bipush        59
     254: imul
     255: aload         12
     257: ifnonnull     265
     260: bipush        43
     262: goto          270
     265: aload         12
     267: invokevirtual #335                // Method java/lang/Object.hashCode:()I
     270: iadd
     271: istore_2
     272: aload_0
     273: getfield      #156                // Field asmVisitorWrapper:Lorg/assertj/core/internal/bytebuddy/asm/AsmVisitorWrapper;
     276: astore        13
     278: iload_2
     279: bipush        59
     281: imul
     282: aload         13
     284: ifnonnull     292
     287: bipush        43
     289: goto          297
     292: aload         13
     294: invokevirtual #335                // Method java/lang/Object.hashCode:()I
     297: iadd
     298: istore_2
     299: aload_0
     300: getfield      #160                // Field annotationValueFilterFactory:Lorg/assertj/core/internal/bytebuddy/implementation/attribute/AnnotationValueFilter$Factory;
     303: astore        14
     305: iload_2
     306: bipush        59
     308: imul
     309: aload         14
     311: ifnonnull     319
     314: bipush        43
     316: goto          324
     319: aload         14
     321: invokevirtual #335                // Method java/lang/Object.hashCode:()I
     324: iadd
     325: istore_2
     326: aload_0
     327: getfield      #162                // Field annotationRetention:Lorg/assertj/core/internal/bytebuddy/implementation/attribute/AnnotationRetention;
     330: astore        15
     332: iload_2
     333: bipush        59
     335: imul
     336: aload         15
     338: ifnonnull     346
     341: bipush        43
     343: goto          351
     346: aload         15
     348: invokevirtual #335                // Method java/lang/Object.hashCode:()I
     351: iadd
     352: istore_2
     353: aload_0
     354: getfield      #158                // Field auxiliaryTypeNamingStrategy:Lorg/assertj/core/internal/bytebuddy/implementation/auxiliary/AuxiliaryType$NamingStrategy;
     357: astore        16
     359: iload_2
     360: bipush        59
     362: imul
     363: aload         16
     365: ifnonnull     373
     368: bipush        43
     370: goto          378
     373: aload         16
     375: invokevirtual #335                // Method java/lang/Object.hashCode:()I
     378: iadd
     379: istore_2
     380: aload_0
     381: getfield      #164                // Field implementationContextFactory:Lorg/assertj/core/internal/bytebuddy/implementation/Implementation$Context$Factory;
     384: astore        17
     386: iload_2
     387: bipush        59
     389: imul
     390: aload         17
     392: ifnonnull     400
     395: bipush        43
     397: goto          405
     400: aload         17
     402: invokevirtual #335                // Method java/lang/Object.hashCode:()I
     405: iadd
     406: istore_2
     407: aload_0
     408: getfield      #166                // Field typeValidation:Lorg/assertj/core/internal/bytebuddy/dynamic/scaffold/TypeValidation;
     411: astore        18
     413: iload_2
     414: bipush        59
     416: imul
     417: aload         18
     419: ifnonnull     427
     422: bipush        43
     424: goto          432
     427: aload         18
     429: invokevirtual #335                // Method java/lang/Object.hashCode:()I
     432: iadd
     433: istore_2
     434: aload_0
     435: getfield      #168                // Field typePool:Lorg/assertj/core/internal/bytebuddy/pool/TypePool;
     438: astore        19
     440: iload_2
     441: bipush        59
     443: imul
     444: aload         19
     446: ifnonnull     454
     449: bipush        43
     451: goto          459
     454: aload         19
     456: invokevirtual #335                // Method java/lang/Object.hashCode:()I
     459: iadd
     460: istore_2
     461: iload_2
     462: ireturn

  static {};
    Code:
       0: new           #360                // class org/assertj/core/internal/bytebuddy/utility/privilege/GetSystemPropertyAction
       3: dup
       4: ldc_w         #362                // String org.assertj.core.internal.bytebuddy.dump
       7: invokespecial #365                // Method org/assertj/core/internal/bytebuddy/utility/privilege/GetSystemPropertyAction."<init>":(Ljava/lang/String;)V
      10: invokestatic  #368                // Method java/security/AccessController.doPrivileged:(Ljava/security/PrivilegedAction;)Ljava/lang/Object;
      13: checkcast     #370                // class java/lang/String
      16: astore_0
      17: goto          23
      20: astore_1
      21: aconst_null
      22: astore_0
      23: aload_0
      24: putstatic     #260                // Field DUMP_FOLDER:Ljava/lang/String;
      27: return
    Exception table:
       from    to  target type
           0    17    20   Class java/lang/RuntimeException
}
