Compiled from "TypeWriter.java"
public class org.assertj.core.internal.bytebuddy.dynamic.scaffold.TypeWriter$MethodPool$Record$AccessBridgeWrapper implements org.assertj.core.internal.bytebuddy.dynamic.scaffold.TypeWriter$MethodPool$Record {
  private final org.assertj.core.internal.bytebuddy.dynamic.scaffold.TypeWriter$MethodPool$Record delegate;

  private final org.assertj.core.internal.bytebuddy.description.type.TypeDescription instrumentedType;

  private final org.assertj.core.internal.bytebuddy.description.method.MethodDescription bridgeTarget;

  private final java.util.Set<org.assertj.core.internal.bytebuddy.description.method.MethodDescription$TypeToken> bridgeTypes;

  private final org.assertj.core.internal.bytebuddy.implementation.attribute.MethodAttributeAppender attributeAppender;

  protected org.assertj.core.internal.bytebuddy.dynamic.scaffold.TypeWriter$MethodPool$Record$AccessBridgeWrapper(org.assertj.core.internal.bytebuddy.dynamic.scaffold.TypeWriter$MethodPool$Record, org.assertj.core.internal.bytebuddy.description.type.TypeDescription, org.assertj.core.internal.bytebuddy.description.method.MethodDescription, java.util.Set<org.assertj.core.internal.bytebuddy.description.method.MethodDescription$TypeToken>, org.assertj.core.internal.bytebuddy.implementation.attribute.MethodAttributeAppender);
    Code:
       0: aload_0
       1: invokespecial #89                 // Method java/lang/Object."<init>":()V
       4: aload_0
       5: aload_1
       6: putfield      #91                 // Field delegate:Lorg/assertj/core/internal/bytebuddy/dynamic/scaffold/TypeWriter$MethodPool$Record;
       9: aload_0
      10: aload_2
      11: putfield      #93                 // Field instrumentedType:Lorg/assertj/core/internal/bytebuddy/description/type/TypeDescription;
      14: aload_0
      15: aload_3
      16: putfield      #95                 // Field bridgeTarget:Lorg/assertj/core/internal/bytebuddy/description/method/MethodDescription;
      19: aload_0
      20: aload         4
      22: putfield      #97                 // Field bridgeTypes:Ljava/util/Set;
      25: aload_0
      26: aload         5
      28: putfield      #99                 // Field attributeAppender:Lorg/assertj/core/internal/bytebuddy/implementation/attribute/MethodAttributeAppender;
      31: return

  public static org.assertj.core.internal.bytebuddy.dynamic.scaffold.TypeWriter$MethodPool$Record of(org.assertj.core.internal.bytebuddy.dynamic.scaffold.TypeWriter$MethodPool$Record, org.assertj.core.internal.bytebuddy.description.type.TypeDescription, org.assertj.core.internal.bytebuddy.description.method.MethodDescription, java.util.Set<org.assertj.core.internal.bytebuddy.description.method.MethodDescription$TypeToken>, org.assertj.core.internal.bytebuddy.implementation.attribute.MethodAttributeAppender);
    Code:
       0: new           #105                // class java/util/HashSet
       3: dup
       4: invokespecial #106                // Method java/util/HashSet."<init>":()V
       7: astore        5
       9: aload_3
      10: invokeinterface #112,  1          // InterfaceMethod java/util/Set.iterator:()Ljava/util/Iterator;
      15: astore        6
      17: aload         6
      19: invokeinterface #118,  1          // InterfaceMethod java/util/Iterator.hasNext:()Z
      24: ifeq          63
      27: aload         6
      29: invokeinterface #122,  1          // InterfaceMethod java/util/Iterator.next:()Ljava/lang/Object;
      34: checkcast     #22                 // class org/assertj/core/internal/bytebuddy/description/method/MethodDescription$TypeToken
      37: astore        7
      39: aload_2
      40: aload         7
      42: invokeinterface #126,  2          // InterfaceMethod org/assertj/core/internal/bytebuddy/description/method/MethodDescription.isBridgeCompatible:(Lorg/assertj/core/internal/bytebuddy/description/method/MethodDescription$TypeToken;)Z
      47: ifeq          60
      50: aload         5
      52: aload         7
      54: invokeinterface #130,  2          // InterfaceMethod java/util/Set.add:(Ljava/lang/Object;)Z
      59: pop
      60: goto          17
      63: aload         5
      65: invokeinterface #133,  1          // InterfaceMethod java/util/Set.isEmpty:()Z
      70: ifne          94
      73: aload_1
      74: invokeinterface #136,  1          // InterfaceMethod org/assertj/core/internal/bytebuddy/description/type/TypeDescription.isInterface:()Z
      79: ifeq          98
      82: aload_0
      83: invokeinterface #140,  1          // InterfaceMethod org/assertj/core/internal/bytebuddy/dynamic/scaffold/TypeWriter$MethodPool$Record.getSort:()Lorg/assertj/core/internal/bytebuddy/dynamic/scaffold/TypeWriter$MethodPool$Record$Sort;
      88: invokevirtual #143                // Method org/assertj/core/internal/bytebuddy/dynamic/scaffold/TypeWriter$MethodPool$Record$Sort.isImplemented:()Z
      91: ifne          98
      94: aload_0
      95: goto          112
      98: new           #2                  // class org/assertj/core/internal/bytebuddy/dynamic/scaffold/TypeWriter$MethodPool$Record$AccessBridgeWrapper
     101: dup
     102: aload_0
     103: aload_1
     104: aload_2
     105: aload         5
     107: aload         4
     109: invokespecial #145                // Method "<init>":(Lorg/assertj/core/internal/bytebuddy/dynamic/scaffold/TypeWriter$MethodPool$Record;Lorg/assertj/core/internal/bytebuddy/description/type/TypeDescription;Lorg/assertj/core/internal/bytebuddy/description/method/MethodDescription;Ljava/util/Set;Lorg/assertj/core/internal/bytebuddy/implementation/attribute/MethodAttributeAppender;)V
     112: areturn

  public org.assertj.core.internal.bytebuddy.dynamic.scaffold.TypeWriter$MethodPool$Record$Sort getSort();
    Code:
       0: aload_0
       1: getfield      #91                 // Field delegate:Lorg/assertj/core/internal/bytebuddy/dynamic/scaffold/TypeWriter$MethodPool$Record;
       4: invokeinterface #140,  1          // InterfaceMethod org/assertj/core/internal/bytebuddy/dynamic/scaffold/TypeWriter$MethodPool$Record.getSort:()Lorg/assertj/core/internal/bytebuddy/dynamic/scaffold/TypeWriter$MethodPool$Record$Sort;
       9: areturn

  public org.assertj.core.internal.bytebuddy.description.method.MethodDescription getMethod();
    Code:
       0: aload_0
       1: getfield      #95                 // Field bridgeTarget:Lorg/assertj/core/internal/bytebuddy/description/method/MethodDescription;
       4: areturn

  public org.assertj.core.internal.bytebuddy.description.modifier.Visibility getVisibility();
    Code:
       0: aload_0
       1: getfield      #91                 // Field delegate:Lorg/assertj/core/internal/bytebuddy/dynamic/scaffold/TypeWriter$MethodPool$Record;
       4: invokeinterface #154,  1          // InterfaceMethod org/assertj/core/internal/bytebuddy/dynamic/scaffold/TypeWriter$MethodPool$Record.getVisibility:()Lorg/assertj/core/internal/bytebuddy/description/modifier/Visibility;
       9: areturn

  public org.assertj.core.internal.bytebuddy.dynamic.scaffold.TypeWriter$MethodPool$Record prepend(org.assertj.core.internal.bytebuddy.implementation.bytecode.ByteCodeAppender);
    Code:
       0: new           #2                  // class org/assertj/core/internal/bytebuddy/dynamic/scaffold/TypeWriter$MethodPool$Record$AccessBridgeWrapper
       3: dup
       4: aload_0
       5: getfield      #91                 // Field delegate:Lorg/assertj/core/internal/bytebuddy/dynamic/scaffold/TypeWriter$MethodPool$Record;
       8: aload_1
       9: invokeinterface #158,  2          // InterfaceMethod org/assertj/core/internal/bytebuddy/dynamic/scaffold/TypeWriter$MethodPool$Record.prepend:(Lorg/assertj/core/internal/bytebuddy/implementation/bytecode/ByteCodeAppender;)Lorg/assertj/core/internal/bytebuddy/dynamic/scaffold/TypeWriter$MethodPool$Record;
      14: aload_0
      15: getfield      #93                 // Field instrumentedType:Lorg/assertj/core/internal/bytebuddy/description/type/TypeDescription;
      18: aload_0
      19: getfield      #95                 // Field bridgeTarget:Lorg/assertj/core/internal/bytebuddy/description/method/MethodDescription;
      22: aload_0
      23: getfield      #97                 // Field bridgeTypes:Ljava/util/Set;
      26: aload_0
      27: getfield      #99                 // Field attributeAppender:Lorg/assertj/core/internal/bytebuddy/implementation/attribute/MethodAttributeAppender;
      30: invokespecial #145                // Method "<init>":(Lorg/assertj/core/internal/bytebuddy/dynamic/scaffold/TypeWriter$MethodPool$Record;Lorg/assertj/core/internal/bytebuddy/description/type/TypeDescription;Lorg/assertj/core/internal/bytebuddy/description/method/MethodDescription;Ljava/util/Set;Lorg/assertj/core/internal/bytebuddy/implementation/attribute/MethodAttributeAppender;)V
      33: areturn

  public void apply(org.assertj.core.internal.bytebuddy.jar.asm.ClassVisitor, org.assertj.core.internal.bytebuddy.implementation.Implementation$Context, org.assertj.core.internal.bytebuddy.implementation.attribute.AnnotationValueFilter$Factory);
    Code:
       0: aload_0
       1: getfield      #91                 // Field delegate:Lorg/assertj/core/internal/bytebuddy/dynamic/scaffold/TypeWriter$MethodPool$Record;
       4: aload_1
       5: aload_2
       6: aload_3
       7: invokeinterface #164,  4          // InterfaceMethod org/assertj/core/internal/bytebuddy/dynamic/scaffold/TypeWriter$MethodPool$Record.apply:(Lorg/assertj/core/internal/bytebuddy/jar/asm/ClassVisitor;Lorg/assertj/core/internal/bytebuddy/implementation/Implementation$Context;Lorg/assertj/core/internal/bytebuddy/implementation/attribute/AnnotationValueFilter$Factory;)V
      12: aload_0
      13: getfield      #97                 // Field bridgeTypes:Ljava/util/Set;
      16: invokeinterface #112,  1          // InterfaceMethod java/util/Set.iterator:()Ljava/util/Iterator;
      21: astore        4
      23: aload         4
      25: invokeinterface #118,  1          // InterfaceMethod java/util/Iterator.hasNext:()Z
      30: ifeq          312
      33: aload         4
      35: invokeinterface #122,  1          // InterfaceMethod java/util/Iterator.next:()Ljava/lang/Object;
      40: checkcast     #22                 // class org/assertj/core/internal/bytebuddy/description/method/MethodDescription$TypeToken
      43: astore        5
      45: new           #19                 // class org/assertj/core/internal/bytebuddy/dynamic/scaffold/TypeWriter$MethodPool$Record$AccessBridgeWrapper$AccessorBridge
      48: dup
      49: aload_0
      50: getfield      #95                 // Field bridgeTarget:Lorg/assertj/core/internal/bytebuddy/description/method/MethodDescription;
      53: aload         5
      55: aload_0
      56: getfield      #93                 // Field instrumentedType:Lorg/assertj/core/internal/bytebuddy/description/type/TypeDescription;
      59: invokespecial #167                // Method org/assertj/core/internal/bytebuddy/dynamic/scaffold/TypeWriter$MethodPool$Record$AccessBridgeWrapper$AccessorBridge."<init>":(Lorg/assertj/core/internal/bytebuddy/description/method/MethodDescription;Lorg/assertj/core/internal/bytebuddy/description/method/MethodDescription$TypeToken;Lorg/assertj/core/internal/bytebuddy/description/type/TypeDescription;)V
      62: astore        6
      64: new           #16                 // class org/assertj/core/internal/bytebuddy/dynamic/scaffold/TypeWriter$MethodPool$Record$AccessBridgeWrapper$BridgeTarget
      67: dup
      68: aload_0
      69: getfield      #95                 // Field bridgeTarget:Lorg/assertj/core/internal/bytebuddy/description/method/MethodDescription;
      72: aload_0
      73: getfield      #93                 // Field instrumentedType:Lorg/assertj/core/internal/bytebuddy/description/type/TypeDescription;
      76: invokespecial #170                // Method org/assertj/core/internal/bytebuddy/dynamic/scaffold/TypeWriter$MethodPool$Record$AccessBridgeWrapper$BridgeTarget."<init>":(Lorg/assertj/core/internal/bytebuddy/description/method/MethodDescription;Lorg/assertj/core/internal/bytebuddy/description/type/TypeDescription;)V
      79: astore        7
      81: aload_1
      82: aload         6
      84: iconst_1
      85: aload_0
      86: invokevirtual #171                // Method getVisibility:()Lorg/assertj/core/internal/bytebuddy/description/modifier/Visibility;
      89: invokeinterface #175,  3          // InterfaceMethod org/assertj/core/internal/bytebuddy/description/method/MethodDescription$InDefinedShape.getActualModifiers:(ZLorg/assertj/core/internal/bytebuddy/description/modifier/Visibility;)I
      94: aload         6
      96: invokeinterface #179,  1          // InterfaceMethod org/assertj/core/internal/bytebuddy/description/method/MethodDescription$InDefinedShape.getInternalName:()Ljava/lang/String;
     101: aload         6
     103: invokeinterface #182,  1          // InterfaceMethod org/assertj/core/internal/bytebuddy/description/method/MethodDescription$InDefinedShape.getDescriptor:()Ljava/lang/String;
     108: getstatic     #186                // Field org/assertj/core/internal/bytebuddy/description/method/MethodDescription.NON_GENERIC_SIGNATURE:Ljava/lang/String;
     111: aload         6
     113: invokeinterface #190,  1          // InterfaceMethod org/assertj/core/internal/bytebuddy/description/method/MethodDescription$InDefinedShape.getExceptionTypes:()Lorg/assertj/core/internal/bytebuddy/description/type/TypeList$Generic;
     118: invokeinterface #194,  1          // InterfaceMethod org/assertj/core/internal/bytebuddy/description/type/TypeList$Generic.asErasures:()Lorg/assertj/core/internal/bytebuddy/description/type/TypeList;
     123: invokeinterface #198,  1          // InterfaceMethod org/assertj/core/internal/bytebuddy/description/type/TypeList.toInternalNames:()[Ljava/lang/String;
     128: invokevirtual #204                // Method org/assertj/core/internal/bytebuddy/jar/asm/ClassVisitor.visitMethod:(ILjava/lang/String;Ljava/lang/String;Ljava/lang/String;[Ljava/lang/String;)Lorg/assertj/core/internal/bytebuddy/jar/asm/MethodVisitor;
     131: astore        8
     133: aload         8
     135: ifnull        309
     138: aload_0
     139: getfield      #99                 // Field attributeAppender:Lorg/assertj/core/internal/bytebuddy/implementation/attribute/MethodAttributeAppender;
     142: aload         8
     144: aload         6
     146: aload_3
     147: aload_0
     148: getfield      #93                 // Field instrumentedType:Lorg/assertj/core/internal/bytebuddy/description/type/TypeDescription;
     151: invokeinterface #208,  2          // InterfaceMethod org/assertj/core/internal/bytebuddy/implementation/attribute/AnnotationValueFilter$Factory.on:(Lorg/assertj/core/internal/bytebuddy/description/type/TypeDescription;)Lorg/assertj/core/internal/bytebuddy/implementation/attribute/AnnotationValueFilter;
     156: invokeinterface #213,  4          // InterfaceMethod org/assertj/core/internal/bytebuddy/implementation/attribute/MethodAttributeAppender.apply:(Lorg/assertj/core/internal/bytebuddy/jar/asm/MethodVisitor;Lorg/assertj/core/internal/bytebuddy/description/method/MethodDescription;Lorg/assertj/core/internal/bytebuddy/implementation/attribute/AnnotationValueFilter;)V
     161: aload         8
     163: invokevirtual #218                // Method org/assertj/core/internal/bytebuddy/jar/asm/MethodVisitor.visitCode:()V
     166: new           #48                 // class org/assertj/core/internal/bytebuddy/implementation/bytecode/ByteCodeAppender$Simple
     169: dup
     170: iconst_4
     171: anewarray     #72                 // class org/assertj/core/internal/bytebuddy/implementation/bytecode/StackManipulation
     174: dup
     175: iconst_0
     176: aload         6
     178: invokestatic  #222                // Method org/assertj/core/internal/bytebuddy/implementation/bytecode/member/MethodVariableAccess.allArgumentsOf:(Lorg/assertj/core/internal/bytebuddy/description/method/MethodDescription;)Lorg/assertj/core/internal/bytebuddy/implementation/bytecode/member/MethodVariableAccess$MethodLoading;
     181: aload         7
     183: invokevirtual #225                // Method org/assertj/core/internal/bytebuddy/implementation/bytecode/member/MethodVariableAccess$MethodLoading.asBridgeOf:(Lorg/assertj/core/internal/bytebuddy/description/method/MethodDescription;)Lorg/assertj/core/internal/bytebuddy/implementation/bytecode/member/MethodVariableAccess$MethodLoading;
     186: invokevirtual #229                // Method org/assertj/core/internal/bytebuddy/implementation/bytecode/member/MethodVariableAccess$MethodLoading.prependThisReference:()Lorg/assertj/core/internal/bytebuddy/implementation/bytecode/StackManipulation;
     189: aastore
     190: dup
     191: iconst_1
     192: aload         7
     194: invokestatic  #233                // Method org/assertj/core/internal/bytebuddy/implementation/bytecode/member/MethodInvocation.invoke:(Lorg/assertj/core/internal/bytebuddy/description/method/MethodDescription$InDefinedShape;)Lorg/assertj/core/internal/bytebuddy/implementation/bytecode/member/MethodInvocation$WithImplicitInvocationTargetType;
     197: aload_0
     198: getfield      #93                 // Field instrumentedType:Lorg/assertj/core/internal/bytebuddy/description/type/TypeDescription;
     201: invokeinterface #237,  2          // InterfaceMethod org/assertj/core/internal/bytebuddy/implementation/bytecode/member/MethodInvocation$WithImplicitInvocationTargetType.virtual:(Lorg/assertj/core/internal/bytebuddy/description/type/TypeDescription;)Lorg/assertj/core/internal/bytebuddy/implementation/bytecode/StackManipulation;
     206: aastore
     207: dup
     208: iconst_2
     209: aload         7
     211: invokeinterface #241,  1          // InterfaceMethod org/assertj/core/internal/bytebuddy/description/method/MethodDescription$InDefinedShape.getReturnType:()Lorg/assertj/core/internal/bytebuddy/description/type/TypeDescription$Generic;
     216: invokeinterface #245,  1          // InterfaceMethod org/assertj/core/internal/bytebuddy/description/type/TypeDescription$Generic.asErasure:()Lorg/assertj/core/internal/bytebuddy/description/type/TypeDescription;
     221: aload         6
     223: invokeinterface #241,  1          // InterfaceMethod org/assertj/core/internal/bytebuddy/description/method/MethodDescription$InDefinedShape.getReturnType:()Lorg/assertj/core/internal/bytebuddy/description/type/TypeDescription$Generic;
     228: invokeinterface #245,  1          // InterfaceMethod org/assertj/core/internal/bytebuddy/description/type/TypeDescription$Generic.asErasure:()Lorg/assertj/core/internal/bytebuddy/description/type/TypeDescription;
     233: invokeinterface #249,  2          // InterfaceMethod org/assertj/core/internal/bytebuddy/description/type/TypeDescription.isAssignableTo:(Lorg/assertj/core/internal/bytebuddy/description/type/TypeDescription;)Z
     238: ifeq          247
     241: getstatic     #253                // Field org/assertj/core/internal/bytebuddy/implementation/bytecode/StackManipulation$Trivial.INSTANCE:Lorg/assertj/core/internal/bytebuddy/implementation/bytecode/StackManipulation$Trivial;
     244: goto          262
     247: aload         6
     249: invokeinterface #241,  1          // InterfaceMethod org/assertj/core/internal/bytebuddy/description/method/MethodDescription$InDefinedShape.getReturnType:()Lorg/assertj/core/internal/bytebuddy/description/type/TypeDescription$Generic;
     254: invokeinterface #245,  1          // InterfaceMethod org/assertj/core/internal/bytebuddy/description/type/TypeDescription$Generic.asErasure:()Lorg/assertj/core/internal/bytebuddy/description/type/TypeDescription;
     259: invokestatic  #261                // Method org/assertj/core/internal/bytebuddy/implementation/bytecode/assign/TypeCasting.to:(Lorg/assertj/core/internal/bytebuddy/description/type/TypeDefinition;)Lorg/assertj/core/internal/bytebuddy/implementation/bytecode/StackManipulation;
     262: aastore
     263: dup
     264: iconst_3
     265: aload         6
     267: invokeinterface #241,  1          // InterfaceMethod org/assertj/core/internal/bytebuddy/description/method/MethodDescription$InDefinedShape.getReturnType:()Lorg/assertj/core/internal/bytebuddy/description/type/TypeDescription$Generic;
     272: invokestatic  #265                // Method org/assertj/core/internal/bytebuddy/implementation/bytecode/member/MethodReturn.of:(Lorg/assertj/core/internal/bytebuddy/description/type/TypeDefinition;)Lorg/assertj/core/internal/bytebuddy/implementation/bytecode/StackManipulation;
     275: aastore
     276: invokespecial #268                // Method org/assertj/core/internal/bytebuddy/implementation/bytecode/ByteCodeAppender$Simple."<init>":([Lorg/assertj/core/internal/bytebuddy/implementation/bytecode/StackManipulation;)V
     279: aload         8
     281: aload_2
     282: aload         6
     284: invokevirtual #271                // Method org/assertj/core/internal/bytebuddy/implementation/bytecode/ByteCodeAppender$Simple.apply:(Lorg/assertj/core/internal/bytebuddy/jar/asm/MethodVisitor;Lorg/assertj/core/internal/bytebuddy/implementation/Implementation$Context;Lorg/assertj/core/internal/bytebuddy/description/method/MethodDescription;)Lorg/assertj/core/internal/bytebuddy/implementation/bytecode/ByteCodeAppender$Size;
     287: astore        9
     289: aload         8
     291: aload         9
     293: invokevirtual #275                // Method org/assertj/core/internal/bytebuddy/implementation/bytecode/ByteCodeAppender$Size.getOperandStackSize:()I
     296: aload         9
     298: invokevirtual #278                // Method org/assertj/core/internal/bytebuddy/implementation/bytecode/ByteCodeAppender$Size.getLocalVariableSize:()I
     301: invokevirtual #282                // Method org/assertj/core/internal/bytebuddy/jar/asm/MethodVisitor.visitMaxs:(II)V
     304: aload         8
     306: invokevirtual #285                // Method org/assertj/core/internal/bytebuddy/jar/asm/MethodVisitor.visitEnd:()V
     309: goto          23
     312: return

  public void applyHead(org.assertj.core.internal.bytebuddy.jar.asm.MethodVisitor);
    Code:
       0: aload_0
       1: getfield      #91                 // Field delegate:Lorg/assertj/core/internal/bytebuddy/dynamic/scaffold/TypeWriter$MethodPool$Record;
       4: aload_1
       5: invokeinterface #301,  2          // InterfaceMethod org/assertj/core/internal/bytebuddy/dynamic/scaffold/TypeWriter$MethodPool$Record.applyHead:(Lorg/assertj/core/internal/bytebuddy/jar/asm/MethodVisitor;)V
      10: return

  public void applyBody(org.assertj.core.internal.bytebuddy.jar.asm.MethodVisitor, org.assertj.core.internal.bytebuddy.implementation.Implementation$Context, org.assertj.core.internal.bytebuddy.implementation.attribute.AnnotationValueFilter$Factory);
    Code:
       0: aload_0
       1: getfield      #91                 // Field delegate:Lorg/assertj/core/internal/bytebuddy/dynamic/scaffold/TypeWriter$MethodPool$Record;
       4: aload_1
       5: aload_2
       6: aload_3
       7: invokeinterface #305,  4          // InterfaceMethod org/assertj/core/internal/bytebuddy/dynamic/scaffold/TypeWriter$MethodPool$Record.applyBody:(Lorg/assertj/core/internal/bytebuddy/jar/asm/MethodVisitor;Lorg/assertj/core/internal/bytebuddy/implementation/Implementation$Context;Lorg/assertj/core/internal/bytebuddy/implementation/attribute/AnnotationValueFilter$Factory;)V
      12: return

  public void applyAttributes(org.assertj.core.internal.bytebuddy.jar.asm.MethodVisitor, org.assertj.core.internal.bytebuddy.implementation.attribute.AnnotationValueFilter$Factory);
    Code:
       0: aload_0
       1: getfield      #91                 // Field delegate:Lorg/assertj/core/internal/bytebuddy/dynamic/scaffold/TypeWriter$MethodPool$Record;
       4: aload_1
       5: aload_2
       6: invokeinterface #309,  3          // InterfaceMethod org/assertj/core/internal/bytebuddy/dynamic/scaffold/TypeWriter$MethodPool$Record.applyAttributes:(Lorg/assertj/core/internal/bytebuddy/jar/asm/MethodVisitor;Lorg/assertj/core/internal/bytebuddy/implementation/attribute/AnnotationValueFilter$Factory;)V
      11: return

  public org.assertj.core.internal.bytebuddy.implementation.bytecode.ByteCodeAppender$Size applyCode(org.assertj.core.internal.bytebuddy.jar.asm.MethodVisitor, org.assertj.core.internal.bytebuddy.implementation.Implementation$Context);
    Code:
       0: aload_0
       1: getfield      #91                 // Field delegate:Lorg/assertj/core/internal/bytebuddy/dynamic/scaffold/TypeWriter$MethodPool$Record;
       4: aload_1
       5: aload_2
       6: invokeinterface #313,  3          // InterfaceMethod org/assertj/core/internal/bytebuddy/dynamic/scaffold/TypeWriter$MethodPool$Record.applyCode:(Lorg/assertj/core/internal/bytebuddy/jar/asm/MethodVisitor;Lorg/assertj/core/internal/bytebuddy/implementation/Implementation$Context;)Lorg/assertj/core/internal/bytebuddy/implementation/bytecode/ByteCodeAppender$Size;
      11: areturn

  public boolean equals(java.lang.Object);
    Code:
       0: aload_1
       1: aload_0
       2: if_acmpne     7
       5: iconst_1
       6: ireturn
       7: aload_1
       8: instanceof    #2                  // class org/assertj/core/internal/bytebuddy/dynamic/scaffold/TypeWriter$MethodPool$Record$AccessBridgeWrapper
      11: ifne          16
      14: iconst_0
      15: ireturn
      16: aload_1
      17: checkcast     #2                  // class org/assertj/core/internal/bytebuddy/dynamic/scaffold/TypeWriter$MethodPool$Record$AccessBridgeWrapper
      20: astore_2
      21: aload_2
      22: aload_0
      23: invokevirtual #317                // Method canEqual:(Ljava/lang/Object;)Z
      26: ifne          31
      29: iconst_0
      30: ireturn
      31: aload_0
      32: getfield      #91                 // Field delegate:Lorg/assertj/core/internal/bytebuddy/dynamic/scaffold/TypeWriter$MethodPool$Record;
      35: astore_3
      36: aload_2
      37: getfield      #91                 // Field delegate:Lorg/assertj/core/internal/bytebuddy/dynamic/scaffold/TypeWriter$MethodPool$Record;
      40: astore        4
      42: aload_3
      43: ifnonnull     54
      46: aload         4
      48: ifnull        65
      51: goto          63
      54: aload_3
      55: aload         4
      57: invokevirtual #319                // Method java/lang/Object.equals:(Ljava/lang/Object;)Z
      60: ifne          65
      63: iconst_0
      64: ireturn
      65: aload_0
      66: getfield      #93                 // Field instrumentedType:Lorg/assertj/core/internal/bytebuddy/description/type/TypeDescription;
      69: astore        5
      71: aload_2
      72: getfield      #93                 // Field instrumentedType:Lorg/assertj/core/internal/bytebuddy/description/type/TypeDescription;
      75: astore        6
      77: aload         5
      79: ifnonnull     90
      82: aload         6
      84: ifnull        102
      87: goto          100
      90: aload         5
      92: aload         6
      94: invokevirtual #319                // Method java/lang/Object.equals:(Ljava/lang/Object;)Z
      97: ifne          102
     100: iconst_0
     101: ireturn
     102: aload_0
     103: getfield      #95                 // Field bridgeTarget:Lorg/assertj/core/internal/bytebuddy/description/method/MethodDescription;
     106: astore        7
     108: aload_2
     109: getfield      #95                 // Field bridgeTarget:Lorg/assertj/core/internal/bytebuddy/description/method/MethodDescription;
     112: astore        8
     114: aload         7
     116: ifnonnull     127
     119: aload         8
     121: ifnull        139
     124: goto          137
     127: aload         7
     129: aload         8
     131: invokevirtual #319                // Method java/lang/Object.equals:(Ljava/lang/Object;)Z
     134: ifne          139
     137: iconst_0
     138: ireturn
     139: aload_0
     140: getfield      #97                 // Field bridgeTypes:Ljava/util/Set;
     143: astore        9
     145: aload_2
     146: getfield      #97                 // Field bridgeTypes:Ljava/util/Set;
     149: astore        10
     151: aload         9
     153: ifnonnull     164
     156: aload         10
     158: ifnull        176
     161: goto          174
     164: aload         9
     166: aload         10
     168: invokevirtual #319                // Method java/lang/Object.equals:(Ljava/lang/Object;)Z
     171: ifne          176
     174: iconst_0
     175: ireturn
     176: aload_0
     177: getfield      #99                 // Field attributeAppender:Lorg/assertj/core/internal/bytebuddy/implementation/attribute/MethodAttributeAppender;
     180: astore        11
     182: aload_2
     183: getfield      #99                 // Field attributeAppender:Lorg/assertj/core/internal/bytebuddy/implementation/attribute/MethodAttributeAppender;
     186: astore        12
     188: aload         11
     190: ifnonnull     201
     193: aload         12
     195: ifnull        213
     198: goto          211
     201: aload         11
     203: aload         12
     205: invokevirtual #319                // Method java/lang/Object.equals:(Ljava/lang/Object;)Z
     208: ifne          213
     211: iconst_0
     212: ireturn
     213: iconst_1
     214: ireturn

  protected boolean canEqual(java.lang.Object);
    Code:
       0: aload_1
       1: instanceof    #2                  // class org/assertj/core/internal/bytebuddy/dynamic/scaffold/TypeWriter$MethodPool$Record$AccessBridgeWrapper
       4: ireturn

  public int hashCode();
    Code:
       0: bipush        59
       2: istore_1
       3: iconst_1
       4: istore_2
       5: aload_0
       6: getfield      #91                 // Field delegate:Lorg/assertj/core/internal/bytebuddy/dynamic/scaffold/TypeWriter$MethodPool$Record;
       9: astore_3
      10: iload_2
      11: bipush        59
      13: imul
      14: aload_3
      15: ifnonnull     23
      18: bipush        43
      20: goto          27
      23: aload_3
      24: invokevirtual #335                // Method java/lang/Object.hashCode:()I
      27: iadd
      28: istore_2
      29: aload_0
      30: getfield      #93                 // Field instrumentedType:Lorg/assertj/core/internal/bytebuddy/description/type/TypeDescription;
      33: astore        4
      35: iload_2
      36: bipush        59
      38: imul
      39: aload         4
      41: ifnonnull     49
      44: bipush        43
      46: goto          54
      49: aload         4
      51: invokevirtual #335                // Method java/lang/Object.hashCode:()I
      54: iadd
      55: istore_2
      56: aload_0
      57: getfield      #95                 // Field bridgeTarget:Lorg/assertj/core/internal/bytebuddy/description/method/MethodDescription;
      60: astore        5
      62: iload_2
      63: bipush        59
      65: imul
      66: aload         5
      68: ifnonnull     76
      71: bipush        43
      73: goto          81
      76: aload         5
      78: invokevirtual #335                // Method java/lang/Object.hashCode:()I
      81: iadd
      82: istore_2
      83: aload_0
      84: getfield      #97                 // Field bridgeTypes:Ljava/util/Set;
      87: astore        6
      89: iload_2
      90: bipush        59
      92: imul
      93: aload         6
      95: ifnonnull     103
      98: bipush        43
     100: goto          108
     103: aload         6
     105: invokevirtual #335                // Method java/lang/Object.hashCode:()I
     108: iadd
     109: istore_2
     110: aload_0
     111: getfield      #99                 // Field attributeAppender:Lorg/assertj/core/internal/bytebuddy/implementation/attribute/MethodAttributeAppender;
     114: astore        7
     116: iload_2
     117: bipush        59
     119: imul
     120: aload         7
     122: ifnonnull     130
     125: bipush        43
     127: goto          135
     130: aload         7
     132: invokevirtual #335                // Method java/lang/Object.hashCode:()I
     135: iadd
     136: istore_2
     137: iload_2
     138: ireturn
}
