Compiled from "AnnotatedRead.scala"
public final class zio.config.AnnotatedRead<A> implements scala.Product, scala.Serializable {
  private final A value;

  private final scala.collection.immutable.Set<zio.config.AnnotatedRead$Annotation> annotations;

  public static <A> scala.Option<scala.Tuple2<A, scala.collection.immutable.Set<zio.config.AnnotatedRead$Annotation>>> unapply(zio.config.AnnotatedRead<A>);
    Code:
       0: getstatic     #21                 // Field zio/config/AnnotatedRead$.MODULE$:Lzio/config/AnnotatedRead$;
       3: aload_0
       4: invokevirtual #23                 // Method zio/config/AnnotatedRead$.unapply:(Lzio/config/AnnotatedRead;)Lscala/Option;
       7: areturn

  public static <A> zio.config.AnnotatedRead<A> apply(A, scala.collection.immutable.Set<zio.config.AnnotatedRead$Annotation>);
    Code:
       0: getstatic     #21                 // Field zio/config/AnnotatedRead$.MODULE$:Lzio/config/AnnotatedRead$;
       3: aload_0
       4: aload_1
       5: invokevirtual #27                 // Method zio/config/AnnotatedRead$.apply:(Ljava/lang/Object;Lscala/collection/immutable/Set;)Lzio/config/AnnotatedRead;
       8: areturn

  public A value();
    Code:
       0: aload_0
       1: getfield      #36                 // Field value:Ljava/lang/Object;
       4: areturn

  public scala.collection.immutable.Set<zio.config.AnnotatedRead$Annotation> annotations();
    Code:
       0: aload_0
       1: getfield      #41                 // Field annotations:Lscala/collection/immutable/Set;
       4: areturn

  public <B> zio.config.AnnotatedRead<B> map(scala.Function1<A, B>);
    Code:
       0: new           #2                  // class zio/config/AnnotatedRead
       3: dup
       4: aload_1
       5: aload_0
       6: invokevirtual #45                 // Method value:()Ljava/lang/Object;
       9: invokeinterface #50,  2           // InterfaceMethod scala/Function1.apply:(Ljava/lang/Object;)Ljava/lang/Object;
      14: aload_0
      15: invokevirtual #52                 // Method annotations:()Lscala/collection/immutable/Set;
      18: invokespecial #56                 // Method "<init>":(Ljava/lang/Object;Lscala/collection/immutable/Set;)V
      21: areturn

  public <E, B> scala.util.Either<E, zio.config.AnnotatedRead<B>> mapEither(scala.Function1<A, scala.util.Either<E, B>>);
    Code:
       0: aload_1
       1: aload_0
       2: invokevirtual #45                 // Method value:()Ljava/lang/Object;
       5: invokeinterface #50,  2           // InterfaceMethod scala/Function1.apply:(Ljava/lang/Object;)Ljava/lang/Object;
      10: checkcast     #62                 // class scala/util/Either
      13: astore_2
      14: aload_2
      15: instanceof    #64                 // class scala/util/Left
      18: ifeq          48
      21: aload_2
      22: checkcast     #64                 // class scala/util/Left
      25: astore_3
      26: aload_3
      27: invokevirtual #67                 // Method scala/util/Left.a:()Ljava/lang/Object;
      30: astore        4
      32: getstatic     #72                 // Field scala/package$.MODULE$:Lscala/package$;
      35: invokevirtual #76                 // Method scala/package$.Left:()Lscala/util/Left$;
      38: aload         4
      40: invokevirtual #81                 // Method scala/util/Left$.apply:(Ljava/lang/Object;)Lscala/util/Left;
      43: astore        5
      45: goto          92
      48: aload_2
      49: instanceof    #83                 // class scala/util/Right
      52: ifeq          95
      55: aload_2
      56: checkcast     #83                 // class scala/util/Right
      59: astore        6
      61: aload         6
      63: invokevirtual #86                 // Method scala/util/Right.b:()Ljava/lang/Object;
      66: astore        7
      68: getstatic     #72                 // Field scala/package$.MODULE$:Lscala/package$;
      71: invokevirtual #90                 // Method scala/package$.Right:()Lscala/util/Right$;
      74: new           #2                  // class zio/config/AnnotatedRead
      77: dup
      78: aload         7
      80: aload_0
      81: invokevirtual #52                 // Method annotations:()Lscala/collection/immutable/Set;
      84: invokespecial #56                 // Method "<init>":(Ljava/lang/Object;Lscala/collection/immutable/Set;)V
      87: invokevirtual #95                 // Method scala/util/Right$.apply:(Ljava/lang/Object;)Lscala/util/Right;
      90: astore        5
      92: aload         5
      94: areturn
      95: new           #97                 // class scala/MatchError
      98: dup
      99: aload_2
     100: invokespecial #100                // Method scala/MatchError."<init>":(Ljava/lang/Object;)V
     103: athrow

  public <B, C> zio.config.AnnotatedRead<C> zipWith(zio.config.AnnotatedRead<B>, scala.Function2<A, B, C>);
    Code:
       0: new           #2                  // class zio/config/AnnotatedRead
       3: dup
       4: aload_2
       5: aload_0
       6: invokevirtual #45                 // Method value:()Ljava/lang/Object;
       9: aload_1
      10: invokevirtual #45                 // Method value:()Ljava/lang/Object;
      13: invokeinterface #107,  3          // InterfaceMethod scala/Function2.apply:(Ljava/lang/Object;Ljava/lang/Object;)Ljava/lang/Object;
      18: aload_0
      19: invokevirtual #52                 // Method annotations:()Lscala/collection/immutable/Set;
      22: aload_1
      23: invokevirtual #52                 // Method annotations:()Lscala/collection/immutable/Set;
      26: invokeinterface #113,  2          // InterfaceMethod scala/collection/immutable/Set.$plus$plus:(Lscala/collection/GenTraversableOnce;)Lscala/collection/Set;
      31: checkcast     #109                // class scala/collection/immutable/Set
      34: invokespecial #56                 // Method "<init>":(Ljava/lang/Object;Lscala/collection/immutable/Set;)V
      37: areturn

  public <A> zio.config.AnnotatedRead<A> copy(A, scala.collection.immutable.Set<zio.config.AnnotatedRead$Annotation>);
    Code:
       0: new           #2                  // class zio/config/AnnotatedRead
       3: dup
       4: aload_1
       5: aload_2
       6: invokespecial #56                 // Method "<init>":(Ljava/lang/Object;Lscala/collection/immutable/Set;)V
       9: areturn

  public <A> A copy$default$1();
    Code:
       0: aload_0
       1: invokevirtual #45                 // Method value:()Ljava/lang/Object;
       4: areturn

  public <A> scala.collection.immutable.Set<zio.config.AnnotatedRead$Annotation> copy$default$2();
    Code:
       0: aload_0
       1: invokevirtual #52                 // Method annotations:()Lscala/collection/immutable/Set;
       4: areturn

  public java.lang.String productPrefix();
    Code:
       0: ldc           #122                // String AnnotatedRead
       2: areturn

  public int productArity();
    Code:
       0: iconst_2
       1: ireturn

  public java.lang.Object productElement(int);
    Code:
       0: iload_1
       1: istore_2
       2: iload_2
       3: tableswitch   { // 0 to 1
                     0: 46
                     1: 39
               default: 24
          }
      24: new           #128                // class java/lang/IndexOutOfBoundsException
      27: dup
      28: iload_1
      29: invokestatic  #134                // Method scala/runtime/BoxesRunTime.boxToInteger:(I)Ljava/lang/Integer;
      32: invokevirtual #137                // Method java/lang/Object.toString:()Ljava/lang/String;
      35: invokespecial #140                // Method java/lang/IndexOutOfBoundsException."<init>":(Ljava/lang/String;)V
      38: athrow
      39: aload_0
      40: invokevirtual #52                 // Method annotations:()Lscala/collection/immutable/Set;
      43: goto          50
      46: aload_0
      47: invokevirtual #45                 // Method value:()Ljava/lang/Object;
      50: areturn

  public scala.collection.Iterator<java.lang.Object> productIterator();
    Code:
       0: getstatic     #149                // Field scala/runtime/ScalaRunTime$.MODULE$:Lscala/runtime/ScalaRunTime$;
       3: aload_0
       4: invokevirtual #153                // Method scala/runtime/ScalaRunTime$.typedProductIterator:(Lscala/Product;)Lscala/collection/Iterator;
       7: areturn

  public boolean canEqual(java.lang.Object);
    Code:
       0: aload_1
       1: instanceof    #2                  // class zio/config/AnnotatedRead
       4: ireturn

  public int hashCode();
    Code:
       0: getstatic     #149                // Field scala/runtime/ScalaRunTime$.MODULE$:Lscala/runtime/ScalaRunTime$;
       3: aload_0
       4: invokevirtual #160                // Method scala/runtime/ScalaRunTime$._hashCode:(Lscala/Product;)I
       7: ireturn

  public java.lang.String toString();
    Code:
       0: getstatic     #149                // Field scala/runtime/ScalaRunTime$.MODULE$:Lscala/runtime/ScalaRunTime$;
       3: aload_0
       4: invokevirtual #164                // Method scala/runtime/ScalaRunTime$._toString:(Lscala/Product;)Ljava/lang/String;
       7: areturn

  public boolean equals(java.lang.Object);
    Code:
       0: aload_0
       1: aload_1
       2: if_acmpeq     86
       5: aload_1
       6: astore_2
       7: aload_2
       8: instanceof    #2                  // class zio/config/AnnotatedRead
      11: ifeq          19
      14: iconst_1
      15: istore_3
      16: goto          21
      19: iconst_0
      20: istore_3
      21: iload_3
      22: ifeq          90
      25: aload_1
      26: checkcast     #2                  // class zio/config/AnnotatedRead
      29: astore        4
      31: aload_0
      32: invokevirtual #45                 // Method value:()Ljava/lang/Object;
      35: aload         4
      37: invokevirtual #45                 // Method value:()Ljava/lang/Object;
      40: invokestatic  #168                // Method scala/runtime/BoxesRunTime.equals:(Ljava/lang/Object;Ljava/lang/Object;)Z
      43: ifeq          82
      46: aload_0
      47: invokevirtual #52                 // Method annotations:()Lscala/collection/immutable/Set;
      50: aload         4
      52: invokevirtual #52                 // Method annotations:()Lscala/collection/immutable/Set;
      55: astore        5
      57: dup
      58: ifnonnull     70
      61: pop
      62: aload         5
      64: ifnull        78
      67: goto          82
      70: aload         5
      72: invokevirtual #170                // Method java/lang/Object.equals:(Ljava/lang/Object;)Z
      75: ifeq          82
      78: iconst_1
      79: goto          83
      82: iconst_0
      83: ifeq          90
      86: iconst_1
      87: goto          91
      90: iconst_0
      91: ireturn

  public zio.config.AnnotatedRead(A, scala.collection.immutable.Set<zio.config.AnnotatedRead$Annotation>);
    Code:
       0: aload_0
       1: aload_1
       2: putfield      #36                 // Field value:Ljava/lang/Object;
       5: aload_0
       6: aload_2
       7: putfield      #41                 // Field annotations:Lscala/collection/immutable/Set;
      10: aload_0
      11: invokespecial #173                // Method java/lang/Object."<init>":()V
      14: aload_0
      15: invokestatic  #179                // Method scala/Product$class.$init$:(Lscala/Product;)V
      18: return
}
