Compiled from "ConfigSourceModule.scala"
public class zio.config.ConfigSourceModule$ConfigSource$These$3$ {
  private volatile zio.config.ConfigSourceModule$ConfigSource$These$3$Both$ Both$module;

  private volatile zio.config.ConfigSourceModule$ConfigSource$These$3$This$ This$module;

  private volatile zio.config.ConfigSourceModule$ConfigSource$These$3$That$ That$module;

  public final zio.config.ConfigSourceModule$ConfigSource$ $outer;

  private zio.config.ConfigSourceModule$ConfigSource$These$3$Both$ Both$lzycompute();
    Code:
       0: aload_0
       1: dup
       2: astore_1
       3: monitorenter
       4: aload_0
       5: getfield      #22                 // Field Both$module:Lzio/config/ConfigSourceModule$ConfigSource$These$3$Both$;
       8: ifnonnull     23
      11: aload_0
      12: new           #24                 // class zio/config/ConfigSourceModule$ConfigSource$These$3$Both$
      15: dup
      16: aload_0
      17: invokespecial #28                 // Method zio/config/ConfigSourceModule$ConfigSource$These$3$Both$."<init>":(Lzio/config/ConfigSourceModule$ConfigSource$These$3$;)V
      20: putfield      #22                 // Field Both$module:Lzio/config/ConfigSourceModule$ConfigSource$These$3$Both$;
      23: getstatic     #34                 // Field scala/runtime/BoxedUnit.UNIT:Lscala/runtime/BoxedUnit;
      26: pop
      27: aload_1
      28: monitorexit
      29: aconst_null
      30: pop
      31: aload_0
      32: getfield      #22                 // Field Both$module:Lzio/config/ConfigSourceModule$ConfigSource$These$3$Both$;
      35: areturn
      36: aload_1
      37: monitorexit
      38: athrow
    Exception table:
       from    to  target type
           4    29    36   any

  private zio.config.ConfigSourceModule$ConfigSource$These$3$This$ This$lzycompute();
    Code:
       0: aload_0
       1: dup
       2: astore_1
       3: monitorenter
       4: aload_0
       5: getfield      #42                 // Field This$module:Lzio/config/ConfigSourceModule$ConfigSource$These$3$This$;
       8: ifnonnull     23
      11: aload_0
      12: new           #44                 // class zio/config/ConfigSourceModule$ConfigSource$These$3$This$
      15: dup
      16: aload_0
      17: invokespecial #45                 // Method zio/config/ConfigSourceModule$ConfigSource$These$3$This$."<init>":(Lzio/config/ConfigSourceModule$ConfigSource$These$3$;)V
      20: putfield      #42                 // Field This$module:Lzio/config/ConfigSourceModule$ConfigSource$These$3$This$;
      23: getstatic     #34                 // Field scala/runtime/BoxedUnit.UNIT:Lscala/runtime/BoxedUnit;
      26: pop
      27: aload_1
      28: monitorexit
      29: aconst_null
      30: pop
      31: aload_0
      32: getfield      #42                 // Field This$module:Lzio/config/ConfigSourceModule$ConfigSource$These$3$This$;
      35: areturn
      36: aload_1
      37: monitorexit
      38: athrow
    Exception table:
       from    to  target type
           4    29    36   any

  private zio.config.ConfigSourceModule$ConfigSource$These$3$That$ That$lzycompute();
    Code:
       0: aload_0
       1: dup
       2: astore_1
       3: monitorenter
       4: aload_0
       5: getfield      #49                 // Field That$module:Lzio/config/ConfigSourceModule$ConfigSource$These$3$That$;
       8: ifnonnull     23
      11: aload_0
      12: new           #51                 // class zio/config/ConfigSourceModule$ConfigSource$These$3$That$
      15: dup
      16: aload_0
      17: invokespecial #52                 // Method zio/config/ConfigSourceModule$ConfigSource$These$3$That$."<init>":(Lzio/config/ConfigSourceModule$ConfigSource$These$3$;)V
      20: putfield      #49                 // Field That$module:Lzio/config/ConfigSourceModule$ConfigSource$These$3$That$;
      23: getstatic     #34                 // Field scala/runtime/BoxedUnit.UNIT:Lscala/runtime/BoxedUnit;
      26: pop
      27: aload_1
      28: monitorexit
      29: aconst_null
      30: pop
      31: aload_0
      32: getfield      #49                 // Field That$module:Lzio/config/ConfigSourceModule$ConfigSource$These$3$That$;
      35: areturn
      36: aload_1
      37: monitorexit
      38: athrow
    Exception table:
       from    to  target type
           4    29    36   any

  public zio.config.ConfigSourceModule$ConfigSource$These$3$Both$ Both();
    Code:
       0: aload_0
       1: getfield      #22                 // Field Both$module:Lzio/config/ConfigSourceModule$ConfigSource$These$3$Both$;
       4: ifnonnull     14
       7: aload_0
       8: invokespecial #55                 // Method Both$lzycompute:()Lzio/config/ConfigSourceModule$ConfigSource$These$3$Both$;
      11: goto          18
      14: aload_0
      15: getfield      #22                 // Field Both$module:Lzio/config/ConfigSourceModule$ConfigSource$These$3$Both$;
      18: areturn

  public zio.config.ConfigSourceModule$ConfigSource$These$3$This$ This();
    Code:
       0: aload_0
       1: getfield      #42                 // Field This$module:Lzio/config/ConfigSourceModule$ConfigSource$These$3$This$;
       4: ifnonnull     14
       7: aload_0
       8: invokespecial #58                 // Method This$lzycompute:()Lzio/config/ConfigSourceModule$ConfigSource$These$3$This$;
      11: goto          18
      14: aload_0
      15: getfield      #42                 // Field This$module:Lzio/config/ConfigSourceModule$ConfigSource$These$3$This$;
      18: areturn

  public zio.config.ConfigSourceModule$ConfigSource$These$3$That$ That();
    Code:
       0: aload_0
       1: getfield      #49                 // Field That$module:Lzio/config/ConfigSourceModule$ConfigSource$These$3$That$;
       4: ifnonnull     14
       7: aload_0
       8: invokespecial #61                 // Method That$lzycompute:()Lzio/config/ConfigSourceModule$ConfigSource$These$3$That$;
      11: goto          18
      14: aload_0
      15: getfield      #49                 // Field That$module:Lzio/config/ConfigSourceModule$ConfigSource$These$3$That$;
      18: areturn

  public zio.config.ConfigSourceModule$ConfigSource$ zio$config$ConfigSourceModule$ConfigSource$These$$$outer();
    Code:
       0: aload_0
       1: getfield      #65                 // Field $outer:Lzio/config/ConfigSourceModule$ConfigSource$;
       4: areturn

  public zio.config.ConfigSourceModule$ConfigSource$These$3$(zio.config.ConfigSourceModule$ConfigSource$);
    Code:
       0: aload_1
       1: ifnonnull     6
       4: aconst_null
       5: athrow
       6: aload_0
       7: aload_1
       8: putfield      #65                 // Field $outer:Lzio/config/ConfigSourceModule$ConfigSource$;
      11: aload_0
      12: invokespecial #69                 // Method java/lang/Object."<init>":()V
      15: return
}
