Compiled from "ConfigDescriptorModule.scala"
public final class zio.config.ConfigDescriptorModule$ConfigDescriptorFunctions$$anonfun$collectAll$3 extends scala.runtime.AbstractFunction1<scala.Tuple2<A, scala.collection.immutable.List<A>>, A> implements scala.Serializable {
  public static final long serialVersionUID;

  public final A apply(scala.Tuple2<A, scala.collection.immutable.List<A>>);
    Code:
       0: aload_1
       1: invokevirtual #25                 // Method scala/Tuple2._1:()Ljava/lang/Object;
       4: areturn

  public final java.lang.Object apply(java.lang.Object);
    Code:
       0: aload_0
       1: aload_1
       2: checkcast     #21                 // class scala/Tuple2
       5: invokevirtual #32                 // Method apply:(Lscala/Tuple2;)Ljava/lang/Object;
       8: areturn

  public zio.config.ConfigDescriptorModule$ConfigDescriptorFunctions$$anonfun$collectAll$3(zio.config.ConfigDescriptorModule$ConfigDescriptorFunctions);
    Code:
       0: aload_0
       1: invokespecial #39                 // Method scala/runtime/AbstractFunction1."<init>":()V
       4: return
}
