Compiled from "ConfigDocsModule.scala"
public class zio.config.ConfigDocsModule$Table$FieldName$ {
  private volatile zio.config.ConfigDocsModule$Table$FieldName$Key$ Key$module;

  private volatile zio.config.ConfigDocsModule$Table$FieldName$Blank$ Blank$module;

  public final zio.config.ConfigDocsModule$Table$ $outer;

  private zio.config.ConfigDocsModule$Table$FieldName$Key$ Key$lzycompute();
    Code:
       0: aload_0
       1: dup
       2: astore_1
       3: monitorenter
       4: aload_0
       5: getfield      #15                 // Field Key$module:Lzio/config/ConfigDocsModule$Table$FieldName$Key$;
       8: ifnonnull     23
      11: aload_0
      12: new           #17                 // class zio/config/ConfigDocsModule$Table$FieldName$Key$
      15: dup
      16: aload_0
      17: invokespecial #21                 // Method zio/config/ConfigDocsModule$Table$FieldName$Key$."<init>":(Lzio/config/ConfigDocsModule$Table$FieldName$;)V
      20: putfield      #15                 // Field Key$module:Lzio/config/ConfigDocsModule$Table$FieldName$Key$;
      23: getstatic     #27                 // Field scala/runtime/BoxedUnit.UNIT:Lscala/runtime/BoxedUnit;
      26: pop
      27: aload_1
      28: monitorexit
      29: aconst_null
      30: pop
      31: aload_0
      32: getfield      #15                 // Field Key$module:Lzio/config/ConfigDocsModule$Table$FieldName$Key$;
      35: areturn
      36: aload_1
      37: monitorexit
      38: athrow
    Exception table:
       from    to  target type
           4    29    36   any

  private zio.config.ConfigDocsModule$Table$FieldName$Blank$ Blank$lzycompute();
    Code:
       0: aload_0
       1: dup
       2: astore_1
       3: monitorenter
       4: aload_0
       5: getfield      #35                 // Field Blank$module:Lzio/config/ConfigDocsModule$Table$FieldName$Blank$;
       8: ifnonnull     23
      11: aload_0
      12: new           #37                 // class zio/config/ConfigDocsModule$Table$FieldName$Blank$
      15: dup
      16: aload_0
      17: invokespecial #38                 // Method zio/config/ConfigDocsModule$Table$FieldName$Blank$."<init>":(Lzio/config/ConfigDocsModule$Table$FieldName$;)V
      20: putfield      #35                 // Field Blank$module:Lzio/config/ConfigDocsModule$Table$FieldName$Blank$;
      23: getstatic     #27                 // Field scala/runtime/BoxedUnit.UNIT:Lscala/runtime/BoxedUnit;
      26: pop
      27: aload_1
      28: monitorexit
      29: aconst_null
      30: pop
      31: aload_0
      32: getfield      #35                 // Field Blank$module:Lzio/config/ConfigDocsModule$Table$FieldName$Blank$;
      35: areturn
      36: aload_1
      37: monitorexit
      38: athrow
    Exception table:
       from    to  target type
           4    29    36   any

  public zio.config.ConfigDocsModule$Table$FieldName$Key$ Key();
    Code:
       0: aload_0
       1: getfield      #15                 // Field Key$module:Lzio/config/ConfigDocsModule$Table$FieldName$Key$;
       4: ifnonnull     14
       7: aload_0
       8: invokespecial #41                 // Method Key$lzycompute:()Lzio/config/ConfigDocsModule$Table$FieldName$Key$;
      11: goto          18
      14: aload_0
      15: getfield      #15                 // Field Key$module:Lzio/config/ConfigDocsModule$Table$FieldName$Key$;
      18: areturn

  public zio.config.ConfigDocsModule$Table$FieldName$Blank$ Blank();
    Code:
       0: aload_0
       1: getfield      #35                 // Field Blank$module:Lzio/config/ConfigDocsModule$Table$FieldName$Blank$;
       4: ifnonnull     14
       7: aload_0
       8: invokespecial #44                 // Method Blank$lzycompute:()Lzio/config/ConfigDocsModule$Table$FieldName$Blank$;
      11: goto          18
      14: aload_0
      15: getfield      #35                 // Field Blank$module:Lzio/config/ConfigDocsModule$Table$FieldName$Blank$;
      18: areturn

  public zio.config.ConfigDocsModule$Table$ zio$config$ConfigDocsModule$Table$FieldName$$$outer();
    Code:
       0: aload_0
       1: getfield      #48                 // Field $outer:Lzio/config/ConfigDocsModule$Table$;
       4: areturn

  public zio.config.ConfigDocsModule$Table$FieldName$(zio.config.ConfigDocsModule$Table$);
    Code:
       0: aload_1
       1: ifnonnull     6
       4: aconst_null
       5: athrow
       6: aload_0
       7: aload_1
       8: putfield      #48                 // Field $outer:Lzio/config/ConfigDocsModule$Table$;
      11: aload_0
      12: invokespecial #52                 // Method java/lang/Object."<init>":()V
      15: return
}
