Compiled from "PropertyType.scala"
public class zio.config.PropertyType$ZioDurationType$ implements zio.config.PropertyType<java.lang.String, java.time.Duration>, scala.Product, scala.Serializable {
  public static final zio.config.PropertyType$ZioDurationType$ MODULE$;

  public static {};
    Code:
       0: new           #2                  // class zio/config/PropertyType$ZioDurationType$
       3: invokespecial #19                 // Method "<init>":()V
       6: return

  public scala.util.Either<zio.config.PropertyType$PropertyReadError<java.lang.String>, java.time.Duration> read(java.lang.String);
    Code:
       0: getstatic     #26                 // Field zio/package$.MODULE$:Lzio/package$;
       3: getstatic     #31                 // Field zio/config/PropertyType$DurationType$.MODULE$:Lzio/config/PropertyType$DurationType$;
       6: aload_1
       7: invokevirtual #33                 // Method zio/config/PropertyType$DurationType$.read:(Ljava/lang/String;)Lscala/util/Either;
      10: invokevirtual #37                 // Method zio/package$.EitherOps:(Lscala/util/Either;)Lzio/EitherCompat$EitherOps;
      13: new           #39                 // class zio/config/PropertyType$ZioDurationType$$anonfun$read$21
      16: dup
      17: invokespecial #40                 // Method zio/config/PropertyType$ZioDurationType$$anonfun$read$21."<init>":()V
      20: invokevirtual #46                 // Method zio/EitherCompat$EitherOps.map:(Lscala/Function1;)Lscala/util/Either;
      23: areturn

  public java.lang.String write(java.time.Duration);
    Code:
       0: getstatic     #31                 // Field zio/config/PropertyType$DurationType$.MODULE$:Lzio/config/PropertyType$DurationType$;
       3: getstatic     #56                 // Field scala/concurrent/duration/Duration$.MODULE$:Lscala/concurrent/duration/Duration$;
       6: aload_1
       7: invokevirtual #62                 // Method java/time/Duration.toNanos:()J
      10: invokevirtual #66                 // Method scala/concurrent/duration/Duration$.fromNanos:(J)Lscala/concurrent/duration/FiniteDuration;
      13: invokevirtual #69                 // Method zio/config/PropertyType$DurationType$.write:(Lscala/concurrent/duration/Duration;)Ljava/lang/String;
      16: areturn

  public java.lang.String productPrefix();
    Code:
       0: ldc           #74                 // String ZioDurationType
       2: areturn

  public int productArity();
    Code:
       0: iconst_0
       1: ireturn

  public scala.runtime.Nothing$ productElement(int);
    Code:
       0: iload_1
       1: istore_2
       2: new           #80                 // class java/lang/IndexOutOfBoundsException
       5: dup
       6: iload_1
       7: invokestatic  #86                 // Method scala/runtime/BoxesRunTime.boxToInteger:(I)Ljava/lang/Integer;
      10: invokevirtual #89                 // Method java/lang/Object.toString:()Ljava/lang/String;
      13: invokespecial #92                 // Method java/lang/IndexOutOfBoundsException."<init>":(Ljava/lang/String;)V
      16: athrow

  public scala.collection.Iterator<scala.runtime.Nothing$> productIterator();
    Code:
       0: getstatic     #101                // Field scala/runtime/ScalaRunTime$.MODULE$:Lscala/runtime/ScalaRunTime$;
       3: aload_0
       4: invokevirtual #105                // Method scala/runtime/ScalaRunTime$.typedProductIterator:(Lscala/Product;)Lscala/collection/Iterator;
       7: areturn

  public boolean canEqual(java.lang.Object);
    Code:
       0: aload_1
       1: instanceof    #2                  // class zio/config/PropertyType$ZioDurationType$
       4: ireturn

  public int hashCode();
    Code:
       0: ldc           #110                // int 1012505102
       2: ireturn

  public java.lang.String toString();
    Code:
       0: ldc           #74                 // String ZioDurationType
       2: areturn

  private java.lang.Object readResolve();
    Code:
       0: getstatic     #114                // Field MODULE$:Lzio/config/PropertyType$ZioDurationType$;
       3: areturn

  public java.lang.Object productElement(int);
    Code:
       0: aload_0
       1: iload_1
       2: invokevirtual #117                // Method productElement:(I)Lscala/runtime/Nothing$;
       5: athrow

  public java.lang.Object write(java.lang.Object);
    Code:
       0: aload_0
       1: aload_1
       2: checkcast     #58                 // class java/time/Duration
       5: invokevirtual #121                // Method write:(Ljava/time/Duration;)Ljava/lang/String;
       8: areturn

  public scala.util.Either read(java.lang.Object);
    Code:
       0: aload_0
       1: aload_1
       2: checkcast     #125                // class java/lang/String
       5: invokevirtual #126                // Method read:(Ljava/lang/String;)Lscala/util/Either;
       8: areturn

  public zio.config.PropertyType$ZioDurationType$();
    Code:
       0: aload_0
       1: invokespecial #128                // Method java/lang/Object."<init>":()V
       4: aload_0
       5: putstatic     #114                // Field MODULE$:Lzio/config/PropertyType$ZioDurationType$;
       8: aload_0
       9: invokestatic  #134                // Method scala/Product$class.$init$:(Lscala/Product;)V
      12: return
}
