Compiled from "PropertyTree.scala"
public final class zio.config.PropertyTree$$anonfun$mapEither$3$$anonfun$apply$3 extends scala.runtime.AbstractFunction1<zio.config.PropertyTree<K, V2>, scala.util.Either<E, scala.collection.immutable.List<zio.config.PropertyTree<K, V2>>>> implements scala.Serializable {
  public static final long serialVersionUID;

  private final scala.util.Either a$1;

  public final scala.util.Either<E, scala.collection.immutable.List<zio.config.PropertyTree<K, V2>>> apply(zio.config.PropertyTree<K, V2>);
    Code:
       0: getstatic     #24                 // Field zio/config/VersionSpecificSupport$.MODULE$:Lzio/config/VersionSpecificSupport$;
       3: aload_0
       4: getfield      #26                 // Field a$1:Lscala/util/Either;
       7: invokevirtual #30                 // Method zio/config/VersionSpecificSupport$.RightBiasedEither:(Lscala/util/Either;)Lzio/config/VersionSpecificSupport$RightBiasedEither;
      10: new           #32                 // class zio/config/PropertyTree$$anonfun$mapEither$3$$anonfun$apply$3$$anonfun$apply$4
      13: dup
      14: aload_0
      15: aload_1
      16: invokespecial #36                 // Method zio/config/PropertyTree$$anonfun$mapEither$3$$anonfun$apply$3$$anonfun$apply$4."<init>":(Lzio/config/PropertyTree$$anonfun$mapEither$3$$anonfun$apply$3;Lzio/config/PropertyTree;)V
      19: invokevirtual #42                 // Method zio/config/VersionSpecificSupport$RightBiasedEither.map:(Lscala/Function1;)Lscala/util/Either;
      22: areturn

  public final java.lang.Object apply(java.lang.Object);
    Code:
       0: aload_0
       1: aload_1
       2: checkcast     #49                 // class zio/config/PropertyTree
       5: invokevirtual #51                 // Method apply:(Lzio/config/PropertyTree;)Lscala/util/Either;
       8: areturn

  public zio.config.PropertyTree$$anonfun$mapEither$3$$anonfun$apply$3(zio.config.PropertyTree<K, V>.$anonfun$mapEither$3);
    Code:
       0: aload_0
       1: aload_2
       2: putfield      #26                 // Field a$1:Lscala/util/Either;
       5: aload_0
       6: invokespecial #57                 // Method scala/runtime/AbstractFunction1."<init>":()V
       9: return
}
