Compiled from "PropertyTreePath.scala"
public final class zio.config.PropertyTreePath$Step$$anonfun$steps$1 extends scala.runtime.AbstractFunction1<scala.util.matching.Regex$Match, java.lang.Object> implements scala.Serializable {
  public static final long serialVersionUID;

  public final boolean apply(scala.util.matching.Regex$Match);
    Code:
       0: new           #21                 // class scala/collection/immutable/StringOps
       3: dup
       4: getstatic     #27                 // Field scala/Predef$.MODULE$:Lscala/Predef$;
       7: aload_1
       8: iconst_0
       9: invokevirtual #33                 // Method scala/util/matching/Regex$Match.group:(I)Ljava/lang/String;
      12: invokevirtual #37                 // Method scala/Predef$.augmentString:(Ljava/lang/String;)Ljava/lang/String;
      15: invokespecial #41                 // Method scala/collection/immutable/StringOps."<init>":(Ljava/lang/String;)V
      18: invokevirtual #45                 // Method scala/collection/immutable/StringOps.nonEmpty:()Z
      21: ireturn

  public final java.lang.Object apply(java.lang.Object);
    Code:
       0: aload_0
       1: aload_1
       2: checkcast     #29                 // class scala/util/matching/Regex$Match
       5: invokevirtual #52                 // Method apply:(Lscala/util/matching/Regex$Match;)Z
       8: invokestatic  #58                 // Method scala/runtime/BoxesRunTime.boxToBoolean:(Z)Ljava/lang/Boolean;
      11: areturn

  public zio.config.PropertyTreePath$Step$$anonfun$steps$1();
    Code:
       0: aload_0
       1: invokespecial #63                 // Method scala/runtime/AbstractFunction1."<init>":()V
       4: return
}
