Compiled from "ReadModule.scala"
public final class zio.config.ReadModule$$anonfun$loopXmapEither$1$1$$anonfun$apply$37 extends scala.runtime.AbstractFunction0<scala.Product> implements scala.Serializable {
  public static final long serialVersionUID;

  private final zio.config.ReadModule$$anonfun$loopXmapEither$1$1 $outer;

  public final zio.config.AnnotatedRead a$1;

  public final scala.Product apply();
    Code:
       0: getstatic     #28                 // Field zio/config/VersionSpecificSupport$.MODULE$:Lzio/config/VersionSpecificSupport$;
       3: aload_0
       4: getfield      #30                 // Field a$1:Lzio/config/AnnotatedRead;
       7: new           #32                 // class zio/config/ReadModule$$anonfun$loopXmapEither$1$1$$anonfun$apply$37$$anonfun$apply$38
      10: dup
      11: aload_0
      12: invokespecial #36                 // Method zio/config/ReadModule$$anonfun$loopXmapEither$1$1$$anonfun$apply$37$$anonfun$apply$38."<init>":(Lzio/config/ReadModule$$anonfun$loopXmapEither$1$1$$anonfun$apply$37;)V
      15: invokevirtual #42                 // Method zio/config/AnnotatedRead.mapEither:(Lscala/Function1;)Lscala/util/Either;
      18: invokevirtual #47                 // Method scala/util/Either.swap:()Lscala/util/Either;
      21: invokevirtual #51                 // Method zio/config/VersionSpecificSupport$.RightBiasedEither:(Lscala/util/Either;)Lzio/config/VersionSpecificSupport$RightBiasedEither;
      24: new           #53                 // class zio/config/ReadModule$$anonfun$loopXmapEither$1$1$$anonfun$apply$37$$anonfun$apply$39
      27: dup
      28: aload_0
      29: invokespecial #54                 // Method zio/config/ReadModule$$anonfun$loopXmapEither$1$1$$anonfun$apply$37$$anonfun$apply$39."<init>":(Lzio/config/ReadModule$$anonfun$loopXmapEither$1$1$$anonfun$apply$37;)V
      32: invokevirtual #59                 // Method zio/config/VersionSpecificSupport$RightBiasedEither.map:(Lscala/Function1;)Lscala/util/Either;
      35: invokevirtual #47                 // Method scala/util/Either.swap:()Lscala/util/Either;
      38: areturn

  public zio.config.ReadModule$$anonfun$loopXmapEither$1$1 zio$config$ReadModule$$anonfun$$anonfun$$$outer();
    Code:
       0: aload_0
       1: getfield      #65                 // Field $outer:Lzio/config/ReadModule$$anonfun$loopXmapEither$1$1;
       4: areturn

  public final java.lang.Object apply();
    Code:
       0: aload_0
       1: invokevirtual #68                 // Method apply:()Lscala/util/Either;
       4: areturn

  public zio.config.ReadModule$$anonfun$loopXmapEither$1$1$$anonfun$apply$37(zio.config.ReadModule$$anonfun$loopXmapEither$1$1, zio.config.AnnotatedRead);
    Code:
       0: aload_1
       1: ifnonnull     6
       4: aconst_null
       5: athrow
       6: aload_0
       7: aload_1
       8: putfield      #65                 // Field $outer:Lzio/config/ReadModule$$anonfun$loopXmapEither$1$1;
      11: aload_0
      12: aload_2
      13: putfield      #30                 // Field a$1:Lzio/config/AnnotatedRead;
      16: aload_0
      17: invokespecial #72                 // Method scala/runtime/AbstractFunction0."<init>":()V
      20: return
}
