Compiled from "ReadModule.scala"
public final class zio.config.ReadModule$$anonfun$loopMap$1$2$$anonfun$apply$44$$anonfun$2 extends scala.runtime.AbstractFunction1<scala.Tuple2<java.lang.String, zio.config.PropertyTree<java.lang.String, java.lang.String>>, scala.Tuple2<java.lang.String, zio.ZManaged<java.lang.Object, zio.config.ReadError<java.lang.String>, zio.config.AnnotatedRead<zio.config.PropertyTree<java.lang.String, java.lang.Object>>>>> implements scala.Serializable {
  public static final long serialVersionUID;

  private final zio.config.ReadModule$$anonfun$loopMap$1$2$$anonfun$apply$44 $outer;

  public final scala.Tuple2<java.lang.String, zio.ZManaged<java.lang.Object, zio.config.ReadError<java.lang.String>, zio.config.AnnotatedRead<zio.config.PropertyTree<java.lang.String, java.lang.Object>>>> apply(scala.Tuple2<java.lang.String, zio.config.PropertyTree<java.lang.String, java.lang.String>>);
    Code:
       0: aload_1
       1: astore_2
       2: aload_2
       3: ifnull        108
       6: aload_2
       7: invokevirtual #24                 // Method scala/Tuple2._1:()Ljava/lang/Object;
      10: checkcast     #26                 // class java/lang/String
      13: astore_3
      14: new           #20                 // class scala/Tuple2
      17: dup
      18: aload_3
      19: aload_0
      20: getfield      #28                 // Field $outer:Lzio/config/ReadModule$$anonfun$loopMap$1$2$$anonfun$apply$44;
      23: invokevirtual #32                 // Method zio/config/ReadModule$$anonfun$loopMap$1$2$$anonfun$apply$44.zio$config$ReadModule$$anonfun$$anonfun$$$outer:()Lzio/config/ReadModule$$anonfun$loopMap$1$2;
      26: invokevirtual #38                 // Method zio/config/ReadModule$$anonfun$loopMap$1$2.zio$config$ReadModule$$anonfun$$$outer:()Lzio/config/ReadModule;
      29: new           #40                 // class zio/config/PropertyTreePath$Step$Key
      32: dup
      33: aload_3
      34: invokespecial #44                 // Method zio/config/PropertyTreePath$Step$Key."<init>":(Ljava/lang/Object;)V
      37: astore        5
      39: aload_0
      40: getfield      #28                 // Field $outer:Lzio/config/ReadModule$$anonfun$loopMap$1$2$$anonfun$apply$44;
      43: invokevirtual #32                 // Method zio/config/ReadModule$$anonfun$loopMap$1$2$$anonfun$apply$44.zio$config$ReadModule$$anonfun$$anonfun$$$outer:()Lzio/config/ReadModule$$anonfun$loopMap$1$2;
      46: getfield      #48                 // Field zio/config/ReadModule$$anonfun$loopMap$1$2.path$6:Lscala/collection/immutable/List;
      49: aload         5
      51: invokevirtual #54                 // Method scala/collection/immutable/List.$colon$colon:(Ljava/lang/Object;)Lscala/collection/immutable/List;
      54: aload_0
      55: getfield      #28                 // Field $outer:Lzio/config/ReadModule$$anonfun$loopMap$1$2$$anonfun$apply$44;
      58: invokevirtual #32                 // Method zio/config/ReadModule$$anonfun$loopMap$1$2$$anonfun$apply$44.zio$config$ReadModule$$anonfun$$anonfun$$$outer:()Lzio/config/ReadModule$$anonfun$loopMap$1$2;
      61: getfield      #58                 // Field zio/config/ReadModule$$anonfun$loopMap$1$2.cfg$7:Lzio/config/ConfigDescriptorModule$ConfigDescriptorAdt$DynamicMap;
      64: invokevirtual #64                 // Method zio/config/ConfigDescriptorModule$ConfigDescriptorAdt$DynamicMap.config:()Lzio/config/ConfigDescriptorModule$ConfigDescriptor;
      67: aload_0
      68: getfield      #28                 // Field $outer:Lzio/config/ReadModule$$anonfun$loopMap$1$2$$anonfun$apply$44;
      71: invokevirtual #32                 // Method zio/config/ReadModule$$anonfun$loopMap$1$2$$anonfun$apply$44.zio$config$ReadModule$$anonfun$$anonfun$$$outer:()Lzio/config/ReadModule$$anonfun$loopMap$1$2;
      74: getfield      #67                 // Field zio/config/ReadModule$$anonfun$loopMap$1$2.descriptions$5:Lscala/collection/immutable/List;
      77: aload_0
      78: getfield      #28                 // Field $outer:Lzio/config/ReadModule$$anonfun$loopMap$1$2$$anonfun$apply$44;
      81: invokevirtual #32                 // Method zio/config/ReadModule$$anonfun$loopMap$1$2$$anonfun$apply$44.zio$config$ReadModule$$anonfun$$anonfun$$$outer:()Lzio/config/ReadModule$$anonfun$loopMap$1$2;
      84: getfield      #70                 // Field zio/config/ReadModule$$anonfun$loopMap$1$2.programSummary$4:Lscala/collection/immutable/List;
      87: aload_0
      88: getfield      #28                 // Field $outer:Lzio/config/ReadModule$$anonfun$loopMap$1$2$$anonfun$apply$44;
      91: invokevirtual #32                 // Method zio/config/ReadModule$$anonfun$loopMap$1$2$$anonfun$apply$44.zio$config$ReadModule$$anonfun$$anonfun$$$outer:()Lzio/config/ReadModule$$anonfun$loopMap$1$2;
      94: getfield      #74                 // Field zio/config/ReadModule$$anonfun$loopMap$1$2.cachedSources$1:Lscala/collection/mutable/Map;
      97: invokestatic  #80                 // Method zio/config/ReadModule$class.loopAny$1:(Lzio/config/ReadModule;Lscala/collection/immutable/List;Lzio/config/ConfigDescriptorModule$ConfigDescriptor;Lscala/collection/immutable/List;Lscala/collection/immutable/List;Lscala/collection/mutable/Map;)Lzio/ZManaged;
     100: invokespecial #83                 // Method scala/Tuple2."<init>":(Ljava/lang/Object;Ljava/lang/Object;)V
     103: astore        4
     105: aload         4
     107: areturn
     108: new           #85                 // class scala/MatchError
     111: dup
     112: aload_2
     113: invokespecial #86                 // Method scala/MatchError."<init>":(Ljava/lang/Object;)V
     116: athrow

  public final java.lang.Object apply(java.lang.Object);
    Code:
       0: aload_0
       1: aload_1
       2: checkcast     #20                 // class scala/Tuple2
       5: invokevirtual #95                 // Method apply:(Lscala/Tuple2;)Lscala/Tuple2;
       8: areturn

  public zio.config.ReadModule$$anonfun$loopMap$1$2$$anonfun$apply$44$$anonfun$2(zio.config.ReadModule$$anonfun$loopMap$1$2$$anonfun$apply$44);
    Code:
       0: aload_1
       1: ifnonnull     6
       4: aconst_null
       5: athrow
       6: aload_0
       7: aload_1
       8: putfield      #28                 // Field $outer:Lzio/config/ReadModule$$anonfun$loopMap$1$2$$anonfun$apply$44;
      11: aload_0
      12: invokespecial #101                // Method scala/runtime/AbstractFunction1."<init>":()V
      15: return
}
