Compiled from "MultiTermVectorsRequest.java"
public class org.elasticsearch.client.core.MultiTermVectorsRequest implements org.elasticsearch.common.xcontent.ToXContentObject,org.elasticsearch.client.Validatable {
  private java.util.List<org.elasticsearch.client.core.TermVectorsRequest> requests;

  public org.elasticsearch.client.core.MultiTermVectorsRequest();
    Code:
       0: aload_0
       1: invokespecial #1                  // Method java/lang/Object."<init>":()V
       4: aload_0
       5: new           #2                  // class java/util/ArrayList
       8: dup
       9: invokespecial #3                  // Method java/util/ArrayList."<init>":()V
      12: putfield      #4                  // Field requests:Ljava/util/List;
      15: return

  public org.elasticsearch.client.core.MultiTermVectorsRequest(java.lang.String[], org.elasticsearch.client.core.TermVectorsRequest);
    Code:
       0: aload_0
       1: invokespecial #1                  // Method java/lang/Object."<init>":()V
       4: aload_0
       5: new           #2                  // class java/util/ArrayList
       8: dup
       9: invokespecial #3                  // Method java/util/ArrayList."<init>":()V
      12: putfield      #4                  // Field requests:Ljava/util/List;
      15: aload_1
      16: astore_3
      17: aload_3
      18: arraylength
      19: istore        4
      21: iconst_0
      22: istore        5
      24: iload         5
      26: iload         4
      28: if_icmpge     63
      31: aload_3
      32: iload         5
      34: aaload
      35: astore        6
      37: aload_2
      38: aload         6
      40: invokestatic  #5                  // Method org/elasticsearch/client/core/TermVectorsRequest.createFromTemplate:(Lorg/elasticsearch/client/core/TermVectorsRequest;Ljava/lang/String;)Lorg/elasticsearch/client/core/TermVectorsRequest;
      43: astore        7
      45: aload_0
      46: getfield      #4                  // Field requests:Ljava/util/List;
      49: aload         7
      51: invokeinterface #6,  2            // InterfaceMethod java/util/List.add:(Ljava/lang/Object;)Z
      56: pop
      57: iinc          5, 1
      60: goto          24
      63: return

  public void add(org.elasticsearch.client.core.TermVectorsRequest);
    Code:
       0: aload_0
       1: getfield      #4                  // Field requests:Ljava/util/List;
       4: aload_1
       5: invokeinterface #6,  2            // InterfaceMethod java/util/List.add:(Ljava/lang/Object;)Z
      10: pop
      11: return

  public org.elasticsearch.common.xcontent.XContentBuilder toXContent(org.elasticsearch.common.xcontent.XContentBuilder, org.elasticsearch.common.xcontent.ToXContent$Params) throws java.io.IOException;
    Code:
       0: aload_1
       1: invokevirtual #7                  // Method org/elasticsearch/common/xcontent/XContentBuilder.startObject:()Lorg/elasticsearch/common/xcontent/XContentBuilder;
       4: pop
       5: aload_1
       6: ldc           #8                  // String docs
       8: invokevirtual #9                  // Method org/elasticsearch/common/xcontent/XContentBuilder.startArray:(Ljava/lang/String;)Lorg/elasticsearch/common/xcontent/XContentBuilder;
      11: pop
      12: aload_0
      13: getfield      #4                  // Field requests:Ljava/util/List;
      16: invokeinterface #10,  1           // InterfaceMethod java/util/List.iterator:()Ljava/util/Iterator;
      21: astore_3
      22: aload_3
      23: invokeinterface #11,  1           // InterfaceMethod java/util/Iterator.hasNext:()Z
      28: ifeq          53
      31: aload_3
      32: invokeinterface #12,  1           // InterfaceMethod java/util/Iterator.next:()Ljava/lang/Object;
      37: checkcast     #13                 // class org/elasticsearch/client/core/TermVectorsRequest
      40: astore        4
      42: aload         4
      44: aload_1
      45: aload_2
      46: invokevirtual #14                 // Method org/elasticsearch/client/core/TermVectorsRequest.toXContent:(Lorg/elasticsearch/common/xcontent/XContentBuilder;Lorg/elasticsearch/common/xcontent/ToXContent$Params;)Lorg/elasticsearch/common/xcontent/XContentBuilder;
      49: pop
      50: goto          22
      53: aload_1
      54: invokevirtual #15                 // Method org/elasticsearch/common/xcontent/XContentBuilder.endArray:()Lorg/elasticsearch/common/xcontent/XContentBuilder;
      57: pop
      58: aload_1
      59: invokevirtual #16                 // Method org/elasticsearch/common/xcontent/XContentBuilder.endObject:()Lorg/elasticsearch/common/xcontent/XContentBuilder;
      62: pop
      63: aload_1
      64: areturn
}
