Compiled from "TimeoutFuture.java"
final class org.apache.jena.ext.com.google.common.util.concurrent.TimeoutFuture<V> extends org.apache.jena.ext.com.google.common.util.concurrent.AbstractFuture$TrustedFuture<V> {
  private org.apache.jena.ext.com.google.common.util.concurrent.ListenableFuture<V> delegateRef;

  private java.util.concurrent.Future<?> timer;

  static <V> org.apache.jena.ext.com.google.common.util.concurrent.ListenableFuture<V> create(org.apache.jena.ext.com.google.common.util.concurrent.ListenableFuture<V>, long, java.util.concurrent.TimeUnit, java.util.concurrent.ScheduledExecutorService);
    Code:
       0: new           #2                  // class org/apache/jena/ext/com/google/common/util/concurrent/TimeoutFuture
       3: dup
       4: aload_0
       5: invokespecial #26                 // Method "<init>":(Lorg/apache/jena/ext/com/google/common/util/concurrent/ListenableFuture;)V
       8: astore        5
      10: new           #9                  // class org/apache/jena/ext/com/google/common/util/concurrent/TimeoutFuture$Fire
      13: dup
      14: aload         5
      16: invokespecial #29                 // Method org/apache/jena/ext/com/google/common/util/concurrent/TimeoutFuture$Fire."<init>":(Lorg/apache/jena/ext/com/google/common/util/concurrent/TimeoutFuture;)V
      19: astore        6
      21: aload         5
      23: aload         4
      25: aload         6
      27: lload_1
      28: aload_3
      29: invokeinterface #35,  5           // InterfaceMethod java/util/concurrent/ScheduledExecutorService.schedule:(Ljava/lang/Runnable;JLjava/util/concurrent/TimeUnit;)Ljava/util/concurrent/ScheduledFuture;
      34: putfield      #37                 // Field timer:Ljava/util/concurrent/Future;
      37: aload_0
      38: aload         6
      40: invokestatic  #43                 // Method org/apache/jena/ext/com/google/common/util/concurrent/MoreExecutors.directExecutor:()Ljava/util/concurrent/Executor;
      43: invokeinterface #49,  3           // InterfaceMethod org/apache/jena/ext/com/google/common/util/concurrent/ListenableFuture.addListener:(Ljava/lang/Runnable;Ljava/util/concurrent/Executor;)V
      48: aload         5
      50: areturn

  private org.apache.jena.ext.com.google.common.util.concurrent.TimeoutFuture(org.apache.jena.ext.com.google.common.util.concurrent.ListenableFuture<V>);
    Code:
       0: aload_0
       1: invokespecial #65                 // Method org/apache/jena/ext/com/google/common/util/concurrent/AbstractFuture$TrustedFuture."<init>":()V
       4: aload_0
       5: aload_1
       6: invokestatic  #71                 // Method org/apache/jena/ext/com/google/common/base/Preconditions.checkNotNull:(Ljava/lang/Object;)Ljava/lang/Object;
       9: checkcast     #45                 // class org/apache/jena/ext/com/google/common/util/concurrent/ListenableFuture
      12: putfield      #73                 // Field delegateRef:Lorg/apache/jena/ext/com/google/common/util/concurrent/ListenableFuture;
      15: return

  protected void afterDone();
    Code:
       0: aload_0
       1: aload_0
       2: getfield      #73                 // Field delegateRef:Lorg/apache/jena/ext/com/google/common/util/concurrent/ListenableFuture;
       5: invokevirtual #79                 // Method maybePropagateCancellation:(Ljava/util/concurrent/Future;)V
       8: aload_0
       9: getfield      #37                 // Field timer:Ljava/util/concurrent/Future;
      12: astore_1
      13: aload_1
      14: ifnull        25
      17: aload_1
      18: iconst_0
      19: invokeinterface #85,  2           // InterfaceMethod java/util/concurrent/Future.cancel:(Z)Z
      24: pop
      25: aload_0
      26: aconst_null
      27: putfield      #73                 // Field delegateRef:Lorg/apache/jena/ext/com/google/common/util/concurrent/ListenableFuture;
      30: aload_0
      31: aconst_null
      32: putfield      #37                 // Field timer:Ljava/util/concurrent/Future;
      35: return

  static org.apache.jena.ext.com.google.common.util.concurrent.ListenableFuture access$000(org.apache.jena.ext.com.google.common.util.concurrent.TimeoutFuture);
    Code:
       0: aload_0
       1: getfield      #73                 // Field delegateRef:Lorg/apache/jena/ext/com/google/common/util/concurrent/ListenableFuture;
       4: areturn
}
