Compiled from "CapturedTypeConstructor.kt"
public final class kotlin.reflect.jvm.internal.impl.resolve.calls.inference.CapturedTypeConstructorKt$wrapWithCapturingSubstitution$2 extends kotlin.reflect.jvm.internal.impl.types.DelegatedTypeSubstitution {
  final kotlin.reflect.jvm.internal.impl.types.TypeSubstitution $this_wrapWithCapturingSubstitution;

  final boolean $needApproximation;

  public boolean approximateContravariantCapturedTypes();
    Code:
       0: aload_0
       1: getfield      #11                 // Field $needApproximation:Z
       4: ireturn

  public kotlin.reflect.jvm.internal.impl.types.TypeProjection get(kotlin.reflect.jvm.internal.impl.types.KotlinType);
    Code:
       0: aload_1
       1: ldc           #1                  // String key
       3: invokestatic  #13                 // Method kotlin/jvm/internal/Intrinsics.checkParameterIsNotNull:(Ljava/lang/Object;Ljava/lang/String;)V
       6: aload_0
       7: aload_1
       8: invokespecial #16                 // Method kotlin/reflect/jvm/internal/impl/types/DelegatedTypeSubstitution.get:(Lkotlin/reflect/jvm/internal/impl/types/KotlinType;)Lkotlin/reflect/jvm/internal/impl/types/TypeProjection;
      11: dup
      12: ifnull        42
      15: aload_1
      16: invokevirtual #17                 // Method kotlin/reflect/jvm/internal/impl/types/KotlinType.getConstructor:()Lkotlin/reflect/jvm/internal/impl/types/TypeConstructor;
      19: invokeinterface #18,  1           // InterfaceMethod kotlin/reflect/jvm/internal/impl/types/TypeConstructor.getDeclarationDescriptor:()Lkotlin/reflect/jvm/internal/impl/descriptors/ClassifierDescriptor;
      24: dup
      25: instanceof    #4                  // class kotlin/reflect/jvm/internal/impl/descriptors/TypeParameterDescriptor
      28: ifne          33
      31: pop
      32: aconst_null
      33: checkcast     #4                  // class kotlin/reflect/jvm/internal/impl/descriptors/TypeParameterDescriptor
      36: invokestatic  #14                 // Method kotlin/reflect/jvm/internal/impl/resolve/calls/inference/CapturedTypeConstructorKt.access$createCapturedIfNeeded:(Lkotlin/reflect/jvm/internal/impl/types/TypeProjection;Lkotlin/reflect/jvm/internal/impl/descriptors/TypeParameterDescriptor;)Lkotlin/reflect/jvm/internal/impl/types/TypeProjection;
      39: goto          44
      42: pop
      43: aconst_null
      44: areturn

  kotlin.reflect.jvm.internal.impl.resolve.calls.inference.CapturedTypeConstructorKt$wrapWithCapturingSubstitution$2(kotlin.reflect.jvm.internal.impl.types.TypeSubstitution, boolean, kotlin.reflect.jvm.internal.impl.types.TypeSubstitution);
    Code:
       0: aload_0
       1: aload_1
       2: putfield      #12                 // Field $this_wrapWithCapturingSubstitution:Lkotlin/reflect/jvm/internal/impl/types/TypeSubstitution;
       5: aload_0
       6: iload_2
       7: putfield      #11                 // Field $needApproximation:Z
      10: aload_0
      11: aload_3
      12: invokespecial #15                 // Method kotlin/reflect/jvm/internal/impl/types/DelegatedTypeSubstitution."<init>":(Lkotlin/reflect/jvm/internal/impl/types/TypeSubstitution;)V
      15: return
}
