Compiled from "CollectionAwareProjectionFactory.java"
class org.springframework.data.jpa.projection.CollectionAwareProjectionFactory$CollectionAwareProjectionInformation extends org.springframework.data.projection.SpelAwareProxyProjectionFactory$SpelAwareProjectionInformation {
  org.springframework.data.jpa.projection.CollectionAwareProjectionFactory$CollectionAwareProjectionInformation(java.lang.Class<?>);
    Code:
       0: aload_0
       1: aload_1
       2: invokespecial #1                  // Method org/springframework/data/projection/SpelAwareProxyProjectionFactory$SpelAwareProjectionInformation."<init>":(Ljava/lang/Class;)V
       5: return

  protected boolean isInputProperty(java.beans.PropertyDescriptor);
    Code:
       0: aload_0
       1: aload_1
       2: invokespecial #2                  // Method org/springframework/data/projection/SpelAwareProxyProjectionFactory$SpelAwareProjectionInformation.isInputProperty:(Ljava/beans/PropertyDescriptor;)Z
       5: ifne          10
       8: iconst_0
       9: ireturn
      10: ldc           #3                  // class java/util/Collection
      12: aload_1
      13: invokevirtual #4                  // Method java/beans/PropertyDescriptor.getPropertyType:()Ljava/lang/Class;
      16: invokevirtual #5                  // Method java/lang/Class.isAssignableFrom:(Ljava/lang/Class;)Z
      19: ifne          38
      22: ldc           #6                  // class java/util/Map
      24: aload_1
      25: invokevirtual #4                  // Method java/beans/PropertyDescriptor.getPropertyType:()Ljava/lang/Class;
      28: invokevirtual #5                  // Method java/lang/Class.isAssignableFrom:(Ljava/lang/Class;)Z
      31: ifne          38
      34: iconst_1
      35: goto          39
      38: iconst_0
      39: ireturn
}
