Compiled from "JMSConduit.java"
class org.apache.cxf.transport.jms.JMSConduit$JMSBusLifeCycleListener implements org.apache.cxf.buslifecycle.BusLifeCycleListener {
  final java.lang.ref.WeakReference<org.apache.cxf.transport.jms.JMSConduit> ref;

  org.apache.cxf.buslifecycle.BusLifeCycleManager blcm;

  org.apache.cxf.transport.jms.JMSConduit$JMSBusLifeCycleListener(org.apache.cxf.transport.jms.JMSConduit, org.apache.cxf.buslifecycle.BusLifeCycleManager);
    Code:
       0: aload_0
       1: invokespecial #1                  // Method java/lang/Object."<init>":()V
       4: aload_0
       5: new           #2                  // class java/lang/ref/WeakReference
       8: dup
       9: aload_1
      10: invokespecial #3                  // Method java/lang/ref/WeakReference."<init>":(Ljava/lang/Object;)V
      13: putfield      #4                  // Field ref:Ljava/lang/ref/WeakReference;
      16: aload_0
      17: aload_2
      18: putfield      #5                  // Field blcm:Lorg/apache/cxf/buslifecycle/BusLifeCycleManager;
      21: aload_0
      22: getfield      #5                  // Field blcm:Lorg/apache/cxf/buslifecycle/BusLifeCycleManager;
      25: aload_0
      26: invokeinterface #6,  2            // InterfaceMethod org/apache/cxf/buslifecycle/BusLifeCycleManager.registerLifeCycleListener:(Lorg/apache/cxf/buslifecycle/BusLifeCycleListener;)V
      31: return

  public void initComplete();
    Code:
       0: return

  public void postShutdown();
    Code:
       0: return

  public void preShutdown();
    Code:
       0: aload_0
       1: invokevirtual #7                  // Method unreg:()V
       4: aload_0
       5: aconst_null
       6: putfield      #5                  // Field blcm:Lorg/apache/cxf/buslifecycle/BusLifeCycleManager;
       9: aload_0
      10: getfield      #4                  // Field ref:Ljava/lang/ref/WeakReference;
      13: invokevirtual #8                  // Method java/lang/ref/WeakReference.get:()Ljava/lang/Object;
      16: checkcast     #9                  // class org/apache/cxf/transport/jms/JMSConduit
      19: astore_1
      20: aload_1
      21: ifnull        34
      24: aload_1
      25: aconst_null
      26: invokestatic  #10                 // Method org/apache/cxf/transport/jms/JMSConduit.access$002:(Lorg/apache/cxf/transport/jms/JMSConduit;Lorg/apache/cxf/transport/jms/JMSConduit$JMSBusLifeCycleListener;)Lorg/apache/cxf/transport/jms/JMSConduit$JMSBusLifeCycleListener;
      29: pop
      30: aload_1
      31: invokevirtual #11                 // Method org/apache/cxf/transport/jms/JMSConduit.close:()V
      34: return

  public void unreg();
    Code:
       0: aload_0
       1: getfield      #5                  // Field blcm:Lorg/apache/cxf/buslifecycle/BusLifeCycleManager;
       4: ifnull        17
       7: aload_0
       8: getfield      #5                  // Field blcm:Lorg/apache/cxf/buslifecycle/BusLifeCycleManager;
      11: aload_0
      12: invokeinterface #12,  2           // InterfaceMethod org/apache/cxf/buslifecycle/BusLifeCycleManager.unregisterLifeCycleListener:(Lorg/apache/cxf/buslifecycle/BusLifeCycleListener;)V
      17: return
}
