Compiled from "MessageStreamUtil.java"
final class org.apache.cxf.transport.jms.MessageStreamUtil {
  private org.apache.cxf.transport.jms.MessageStreamUtil();
    Code:
       0: aload_0
       1: invokespecial #1                  // Method java/lang/Object."<init>":()V
       4: return

  public static void prepareStream(org.apache.cxf.message.Message, boolean, org.apache.cxf.transport.jms.JMSExchangeSender);
    Code:
       0: iload_1
       1: ifeq          31
       4: aload_0
       5: ldc_w         #2                  // class java/io/Writer
       8: new           #3                  // class org/apache/cxf/transport/jms/MessageStreamUtil$SendingWriter
      11: dup
      12: aload_2
      13: aload_0
      14: invokeinterface #4,  1            // InterfaceMethod org/apache/cxf/message/Message.getExchange:()Lorg/apache/cxf/message/Exchange;
      19: aconst_null
      20: invokespecial #5                  // Method org/apache/cxf/transport/jms/MessageStreamUtil$SendingWriter."<init>":(Lorg/apache/cxf/transport/jms/JMSExchangeSender;Lorg/apache/cxf/message/Exchange;Lorg/apache/cxf/transport/jms/MessageStreamUtil$1;)V
      23: invokeinterface #6,  3            // InterfaceMethod org/apache/cxf/message/Message.setContent:(Ljava/lang/Class;Ljava/lang/Object;)V
      28: goto          56
      31: new           #7                  // class org/apache/cxf/transport/jms/MessageStreamUtil$SendingOutputStream
      34: dup
      35: aload_2
      36: aload_0
      37: invokeinterface #4,  1            // InterfaceMethod org/apache/cxf/message/Message.getExchange:()Lorg/apache/cxf/message/Exchange;
      42: invokespecial #8                  // Method org/apache/cxf/transport/jms/MessageStreamUtil$SendingOutputStream."<init>":(Lorg/apache/cxf/transport/jms/JMSExchangeSender;Lorg/apache/cxf/message/Exchange;)V
      45: astore_3
      46: aload_0
      47: ldc_w         #9                  // class java/io/OutputStream
      50: aload_3
      51: invokeinterface #6,  3            // InterfaceMethod org/apache/cxf/message/Message.setContent:(Ljava/lang/Class;Ljava/lang/Object;)V
      56: return

  public static void closeStreams(org.apache.cxf.message.Message) throws java.io.IOException;
    Code:
       0: aload_0
       1: ldc_w         #2                  // class java/io/Writer
       4: invokeinterface #10,  2           // InterfaceMethod org/apache/cxf/message/Message.getContent:(Ljava/lang/Class;)Ljava/lang/Object;
       9: checkcast     #2                  // class java/io/Writer
      12: astore_1
      13: aload_1
      14: ifnull        21
      17: aload_1
      18: invokevirtual #11                 // Method java/io/Writer.close:()V
      21: aload_0
      22: ldc_w         #12                 // class java/io/Reader
      25: invokeinterface #10,  2           // InterfaceMethod org/apache/cxf/message/Message.getContent:(Ljava/lang/Class;)Ljava/lang/Object;
      30: checkcast     #12                 // class java/io/Reader
      33: astore_2
      34: aload_2
      35: ifnull        42
      38: aload_2
      39: invokevirtual #13                 // Method java/io/Reader.close:()V
      42: return
}
