Compiled from "HttpPostRequestDecoder.java"
public final class io.netty.handler.codec.http.multipart.HttpPostRequestDecoder$MultiPartStatus extends java.lang.Enum<io.netty.handler.codec.http.multipart.HttpPostRequestDecoder$MultiPartStatus> {
  public static final io.netty.handler.codec.http.multipart.HttpPostRequestDecoder$MultiPartStatus NOTSTARTED;

  public static final io.netty.handler.codec.http.multipart.HttpPostRequestDecoder$MultiPartStatus PREAMBLE;

  public static final io.netty.handler.codec.http.multipart.HttpPostRequestDecoder$MultiPartStatus HEADERDELIMITER;

  public static final io.netty.handler.codec.http.multipart.HttpPostRequestDecoder$MultiPartStatus DISPOSITION;

  public static final io.netty.handler.codec.http.multipart.HttpPostRequestDecoder$MultiPartStatus FIELD;

  public static final io.netty.handler.codec.http.multipart.HttpPostRequestDecoder$MultiPartStatus FILEUPLOAD;

  public static final io.netty.handler.codec.http.multipart.HttpPostRequestDecoder$MultiPartStatus MIXEDPREAMBLE;

  public static final io.netty.handler.codec.http.multipart.HttpPostRequestDecoder$MultiPartStatus MIXEDDELIMITER;

  public static final io.netty.handler.codec.http.multipart.HttpPostRequestDecoder$MultiPartStatus MIXEDDISPOSITION;

  public static final io.netty.handler.codec.http.multipart.HttpPostRequestDecoder$MultiPartStatus MIXEDFILEUPLOAD;

  public static final io.netty.handler.codec.http.multipart.HttpPostRequestDecoder$MultiPartStatus MIXEDCLOSEDELIMITER;

  public static final io.netty.handler.codec.http.multipart.HttpPostRequestDecoder$MultiPartStatus CLOSEDELIMITER;

  public static final io.netty.handler.codec.http.multipart.HttpPostRequestDecoder$MultiPartStatus PREEPILOGUE;

  public static final io.netty.handler.codec.http.multipart.HttpPostRequestDecoder$MultiPartStatus EPILOGUE;

  private static final io.netty.handler.codec.http.multipart.HttpPostRequestDecoder$MultiPartStatus[] $VALUES;

  public static io.netty.handler.codec.http.multipart.HttpPostRequestDecoder$MultiPartStatus[] values();
    Code:
       0: getstatic     #1                  // Field $VALUES:[Lio/netty/handler/codec/http/multipart/HttpPostRequestDecoder$MultiPartStatus;
       3: invokevirtual #2                  // Method "[Lio/netty/handler/codec/http/multipart/HttpPostRequestDecoder$MultiPartStatus;".clone:()Ljava/lang/Object;
       6: checkcast     #3                  // class "[Lio/netty/handler/codec/http/multipart/HttpPostRequestDecoder$MultiPartStatus;"
       9: areturn

  public static io.netty.handler.codec.http.multipart.HttpPostRequestDecoder$MultiPartStatus valueOf(java.lang.String);
    Code:
       0: ldc_w         #4                  // class io/netty/handler/codec/http/multipart/HttpPostRequestDecoder$MultiPartStatus
       3: aload_0
       4: invokestatic  #5                  // Method java/lang/Enum.valueOf:(Ljava/lang/Class;Ljava/lang/String;)Ljava/lang/Enum;
       7: checkcast     #4                  // class io/netty/handler/codec/http/multipart/HttpPostRequestDecoder$MultiPartStatus
      10: areturn

  private io.netty.handler.codec.http.multipart.HttpPostRequestDecoder$MultiPartStatus();
    Code:
       0: aload_0
       1: aload_1
       2: iload_2
       3: invokespecial #6                  // Method java/lang/Enum."<init>":(Ljava/lang/String;I)V
       6: return

  static {};
    Code:
       0: new           #4                  // class io/netty/handler/codec/http/multipart/HttpPostRequestDecoder$MultiPartStatus
       3: dup
       4: ldc           #7                  // String NOTSTARTED
       6: iconst_0
       7: invokespecial #8                  // Method "<init>":(Ljava/lang/String;I)V
      10: putstatic     #9                  // Field NOTSTARTED:Lio/netty/handler/codec/http/multipart/HttpPostRequestDecoder$MultiPartStatus;
      13: new           #4                  // class io/netty/handler/codec/http/multipart/HttpPostRequestDecoder$MultiPartStatus
      16: dup
      17: ldc           #10                 // String PREAMBLE
      19: iconst_1
      20: invokespecial #8                  // Method "<init>":(Ljava/lang/String;I)V
      23: putstatic     #11                 // Field PREAMBLE:Lio/netty/handler/codec/http/multipart/HttpPostRequestDecoder$MultiPartStatus;
      26: new           #4                  // class io/netty/handler/codec/http/multipart/HttpPostRequestDecoder$MultiPartStatus
      29: dup
      30: ldc           #12                 // String HEADERDELIMITER
      32: iconst_2
      33: invokespecial #8                  // Method "<init>":(Ljava/lang/String;I)V
      36: putstatic     #13                 // Field HEADERDELIMITER:Lio/netty/handler/codec/http/multipart/HttpPostRequestDecoder$MultiPartStatus;
      39: new           #4                  // class io/netty/handler/codec/http/multipart/HttpPostRequestDecoder$MultiPartStatus
      42: dup
      43: ldc           #14                 // String DISPOSITION
      45: iconst_3
      46: invokespecial #8                  // Method "<init>":(Ljava/lang/String;I)V
      49: putstatic     #15                 // Field DISPOSITION:Lio/netty/handler/codec/http/multipart/HttpPostRequestDecoder$MultiPartStatus;
      52: new           #4                  // class io/netty/handler/codec/http/multipart/HttpPostRequestDecoder$MultiPartStatus
      55: dup
      56: ldc           #16                 // String FIELD
      58: iconst_4
      59: invokespecial #8                  // Method "<init>":(Ljava/lang/String;I)V
      62: putstatic     #17                 // Field FIELD:Lio/netty/handler/codec/http/multipart/HttpPostRequestDecoder$MultiPartStatus;
      65: new           #4                  // class io/netty/handler/codec/http/multipart/HttpPostRequestDecoder$MultiPartStatus
      68: dup
      69: ldc           #18                 // String FILEUPLOAD
      71: iconst_5
      72: invokespecial #8                  // Method "<init>":(Ljava/lang/String;I)V
      75: putstatic     #19                 // Field FILEUPLOAD:Lio/netty/handler/codec/http/multipart/HttpPostRequestDecoder$MultiPartStatus;
      78: new           #4                  // class io/netty/handler/codec/http/multipart/HttpPostRequestDecoder$MultiPartStatus
      81: dup
      82: ldc           #20                 // String MIXEDPREAMBLE
      84: bipush        6
      86: invokespecial #8                  // Method "<init>":(Ljava/lang/String;I)V
      89: putstatic     #21                 // Field MIXEDPREAMBLE:Lio/netty/handler/codec/http/multipart/HttpPostRequestDecoder$MultiPartStatus;
      92: new           #4                  // class io/netty/handler/codec/http/multipart/HttpPostRequestDecoder$MultiPartStatus
      95: dup
      96: ldc           #22                 // String MIXEDDELIMITER
      98: bipush        7
     100: invokespecial #8                  // Method "<init>":(Ljava/lang/String;I)V
     103: putstatic     #23                 // Field MIXEDDELIMITER:Lio/netty/handler/codec/http/multipart/HttpPostRequestDecoder$MultiPartStatus;
     106: new           #4                  // class io/netty/handler/codec/http/multipart/HttpPostRequestDecoder$MultiPartStatus
     109: dup
     110: ldc           #24                 // String MIXEDDISPOSITION
     112: bipush        8
     114: invokespecial #8                  // Method "<init>":(Ljava/lang/String;I)V
     117: putstatic     #25                 // Field MIXEDDISPOSITION:Lio/netty/handler/codec/http/multipart/HttpPostRequestDecoder$MultiPartStatus;
     120: new           #4                  // class io/netty/handler/codec/http/multipart/HttpPostRequestDecoder$MultiPartStatus
     123: dup
     124: ldc           #26                 // String MIXEDFILEUPLOAD
     126: bipush        9
     128: invokespecial #8                  // Method "<init>":(Ljava/lang/String;I)V
     131: putstatic     #27                 // Field MIXEDFILEUPLOAD:Lio/netty/handler/codec/http/multipart/HttpPostRequestDecoder$MultiPartStatus;
     134: new           #4                  // class io/netty/handler/codec/http/multipart/HttpPostRequestDecoder$MultiPartStatus
     137: dup
     138: ldc           #28                 // String MIXEDCLOSEDELIMITER
     140: bipush        10
     142: invokespecial #8                  // Method "<init>":(Ljava/lang/String;I)V
     145: putstatic     #29                 // Field MIXEDCLOSEDELIMITER:Lio/netty/handler/codec/http/multipart/HttpPostRequestDecoder$MultiPartStatus;
     148: new           #4                  // class io/netty/handler/codec/http/multipart/HttpPostRequestDecoder$MultiPartStatus
     151: dup
     152: ldc           #30                 // String CLOSEDELIMITER
     154: bipush        11
     156: invokespecial #8                  // Method "<init>":(Ljava/lang/String;I)V
     159: putstatic     #31                 // Field CLOSEDELIMITER:Lio/netty/handler/codec/http/multipart/HttpPostRequestDecoder$MultiPartStatus;
     162: new           #4                  // class io/netty/handler/codec/http/multipart/HttpPostRequestDecoder$MultiPartStatus
     165: dup
     166: ldc           #32                 // String PREEPILOGUE
     168: bipush        12
     170: invokespecial #8                  // Method "<init>":(Ljava/lang/String;I)V
     173: putstatic     #33                 // Field PREEPILOGUE:Lio/netty/handler/codec/http/multipart/HttpPostRequestDecoder$MultiPartStatus;
     176: new           #4                  // class io/netty/handler/codec/http/multipart/HttpPostRequestDecoder$MultiPartStatus
     179: dup
     180: ldc           #34                 // String EPILOGUE
     182: bipush        13
     184: invokespecial #8                  // Method "<init>":(Ljava/lang/String;I)V
     187: putstatic     #35                 // Field EPILOGUE:Lio/netty/handler/codec/http/multipart/HttpPostRequestDecoder$MultiPartStatus;
     190: bipush        14
     192: anewarray     #4                  // class io/netty/handler/codec/http/multipart/HttpPostRequestDecoder$MultiPartStatus
     195: dup
     196: iconst_0
     197: getstatic     #9                  // Field NOTSTARTED:Lio/netty/handler/codec/http/multipart/HttpPostRequestDecoder$MultiPartStatus;
     200: aastore
     201: dup
     202: iconst_1
     203: getstatic     #11                 // Field PREAMBLE:Lio/netty/handler/codec/http/multipart/HttpPostRequestDecoder$MultiPartStatus;
     206: aastore
     207: dup
     208: iconst_2
     209: getstatic     #13                 // Field HEADERDELIMITER:Lio/netty/handler/codec/http/multipart/HttpPostRequestDecoder$MultiPartStatus;
     212: aastore
     213: dup
     214: iconst_3
     215: getstatic     #15                 // Field DISPOSITION:Lio/netty/handler/codec/http/multipart/HttpPostRequestDecoder$MultiPartStatus;
     218: aastore
     219: dup
     220: iconst_4
     221: getstatic     #17                 // Field FIELD:Lio/netty/handler/codec/http/multipart/HttpPostRequestDecoder$MultiPartStatus;
     224: aastore
     225: dup
     226: iconst_5
     227: getstatic     #19                 // Field FILEUPLOAD:Lio/netty/handler/codec/http/multipart/HttpPostRequestDecoder$MultiPartStatus;
     230: aastore
     231: dup
     232: bipush        6
     234: getstatic     #21                 // Field MIXEDPREAMBLE:Lio/netty/handler/codec/http/multipart/HttpPostRequestDecoder$MultiPartStatus;
     237: aastore
     238: dup
     239: bipush        7
     241: getstatic     #23                 // Field MIXEDDELIMITER:Lio/netty/handler/codec/http/multipart/HttpPostRequestDecoder$MultiPartStatus;
     244: aastore
     245: dup
     246: bipush        8
     248: getstatic     #25                 // Field MIXEDDISPOSITION:Lio/netty/handler/codec/http/multipart/HttpPostRequestDecoder$MultiPartStatus;
     251: aastore
     252: dup
     253: bipush        9
     255: getstatic     #27                 // Field MIXEDFILEUPLOAD:Lio/netty/handler/codec/http/multipart/HttpPostRequestDecoder$MultiPartStatus;
     258: aastore
     259: dup
     260: bipush        10
     262: getstatic     #29                 // Field MIXEDCLOSEDELIMITER:Lio/netty/handler/codec/http/multipart/HttpPostRequestDecoder$MultiPartStatus;
     265: aastore
     266: dup
     267: bipush        11
     269: getstatic     #31                 // Field CLOSEDELIMITER:Lio/netty/handler/codec/http/multipart/HttpPostRequestDecoder$MultiPartStatus;
     272: aastore
     273: dup
     274: bipush        12
     276: getstatic     #33                 // Field PREEPILOGUE:Lio/netty/handler/codec/http/multipart/HttpPostRequestDecoder$MultiPartStatus;
     279: aastore
     280: dup
     281: bipush        13
     283: getstatic     #35                 // Field EPILOGUE:Lio/netty/handler/codec/http/multipart/HttpPostRequestDecoder$MultiPartStatus;
     286: aastore
     287: putstatic     #1                  // Field $VALUES:[Lio/netty/handler/codec/http/multipart/HttpPostRequestDecoder$MultiPartStatus;
     290: return
}
