Compiled from "ProxyHandler.java"
class io.undertow.server.handlers.proxy.ProxyHandler$ProxyAction$1 implements io.undertow.client.ClientCallback<io.undertow.client.ClientExchange> {
  final io.undertow.client.ClientRequest val$request;

  final java.lang.String val$remoteHost;

  final io.undertow.server.handlers.proxy.ProxyHandler$ProxyAction this$0;

  io.undertow.server.handlers.proxy.ProxyHandler$ProxyAction$1(io.undertow.server.handlers.proxy.ProxyHandler$ProxyAction, io.undertow.client.ClientRequest, java.lang.String);
    Code:
       0: aload_0
       1: aload_1
       2: putfield      #1                  // Field this$0:Lio/undertow/server/handlers/proxy/ProxyHandler$ProxyAction;
       5: aload_0
       6: aload_2
       7: putfield      #2                  // Field val$request:Lio/undertow/client/ClientRequest;
      10: aload_0
      11: aload_3
      12: putfield      #3                  // Field val$remoteHost:Ljava/lang/String;
      15: aload_0
      16: invokespecial #4                  // Method java/lang/Object."<init>":()V
      19: return

  public void completed(io.undertow.client.ClientExchange);
    Code:
       0: getstatic     #5                  // Field io/undertow/server/handlers/proxy/ProxyHandler.log:Lorg/jboss/logging/Logger;
       3: invokevirtual #6                  // Method org/jboss/logging/Logger.isDebugEnabled:()Z
       6: ifeq          32
       9: getstatic     #5                  // Field io/undertow/server/handlers/proxy/ProxyHandler.log:Lorg/jboss/logging/Logger;
      12: ldc           #7                  // String Sent request %s to target %s for exchange %s
      14: aload_0
      15: getfield      #2                  // Field val$request:Lio/undertow/client/ClientRequest;
      18: aload_0
      19: getfield      #3                  // Field val$remoteHost:Ljava/lang/String;
      22: aload_0
      23: getfield      #1                  // Field this$0:Lio/undertow/server/handlers/proxy/ProxyHandler$ProxyAction;
      26: getfield      #8                  // Field io/undertow/server/handlers/proxy/ProxyHandler$ProxyAction.exchange:Lio/undertow/server/HttpServerExchange;
      29: invokevirtual #9                  // Method org/jboss/logging/Logger.debugf:(Ljava/lang/String;Ljava/lang/Object;Ljava/lang/Object;Ljava/lang/Object;)V
      32: aload_1
      33: getstatic     #10                 // Field io/undertow/server/handlers/proxy/ProxyHandler.EXCHANGE:Lio/undertow/util/AttachmentKey;
      36: aload_0
      37: getfield      #1                  // Field this$0:Lio/undertow/server/handlers/proxy/ProxyHandler$ProxyAction;
      40: getfield      #8                  // Field io/undertow/server/handlers/proxy/ProxyHandler$ProxyAction.exchange:Lio/undertow/server/HttpServerExchange;
      43: invokeinterface #11,  3           // InterfaceMethod io/undertow/client/ClientExchange.putAttachment:(Lio/undertow/util/AttachmentKey;Ljava/lang/Object;)Ljava/lang/Object;
      48: pop
      49: aload_0
      50: getfield      #1                  // Field this$0:Lio/undertow/server/handlers/proxy/ProxyHandler$ProxyAction;
      53: getfield      #8                  // Field io/undertow/server/handlers/proxy/ProxyHandler$ProxyAction.exchange:Lio/undertow/server/HttpServerExchange;
      56: invokestatic  #12                 // Method io/undertow/server/protocol/http/HttpContinue.requiresContinueResponse:(Lio/undertow/server/HttpServerExchange;)Z
      59: istore_2
      60: iload_2
      61: ifeq          78
      64: aload_1
      65: new           #13                 // class io/undertow/server/handlers/proxy/ProxyHandler$ProxyAction$1$1
      68: dup
      69: aload_0
      70: invokespecial #14                 // Method io/undertow/server/handlers/proxy/ProxyHandler$ProxyAction$1$1."<init>":(Lio/undertow/server/handlers/proxy/ProxyHandler$ProxyAction$1;)V
      73: invokeinterface #15,  2           // InterfaceMethod io/undertow/client/ClientExchange.setContinueHandler:(Lio/undertow/client/ContinueNotification;)V
      78: aload_0
      79: getfield      #1                  // Field this$0:Lio/undertow/server/handlers/proxy/ProxyHandler$ProxyAction;
      82: getfield      #8                  // Field io/undertow/server/handlers/proxy/ProxyHandler$ProxyAction.exchange:Lio/undertow/server/HttpServerExchange;
      85: invokevirtual #16                 // Method io/undertow/server/HttpServerExchange.getConnection:()Lio/undertow/server/ServerConnection;
      88: invokevirtual #17                 // Method io/undertow/server/ServerConnection.isPushSupported:()Z
      91: ifeq          122
      94: aload_1
      95: invokeinterface #18,  1           // InterfaceMethod io/undertow/client/ClientExchange.getConnection:()Lio/undertow/client/ClientConnection;
     100: invokeinterface #19,  1           // InterfaceMethod io/undertow/client/ClientConnection.isPushSupported:()Z
     105: ifeq          122
     108: aload_1
     109: new           #20                 // class io/undertow/server/handlers/proxy/ProxyHandler$ProxyAction$1$2
     112: dup
     113: aload_0
     114: invokespecial #21                 // Method io/undertow/server/handlers/proxy/ProxyHandler$ProxyAction$1$2."<init>":(Lio/undertow/server/handlers/proxy/ProxyHandler$ProxyAction$1;)V
     117: invokeinterface #22,  2           // InterfaceMethod io/undertow/client/ClientExchange.setPushHandler:(Lio/undertow/client/PushCallback;)V
     122: aload_1
     123: new           #23                 // class io/undertow/server/handlers/proxy/ProxyHandler$ResponseCallback
     126: dup
     127: aload_0
     128: getfield      #1                  // Field this$0:Lio/undertow/server/handlers/proxy/ProxyHandler$ProxyAction;
     131: getfield      #8                  // Field io/undertow/server/handlers/proxy/ProxyHandler$ProxyAction.exchange:Lio/undertow/server/HttpServerExchange;
     134: aload_0
     135: getfield      #1                  // Field this$0:Lio/undertow/server/handlers/proxy/ProxyHandler$ProxyAction;
     138: getfield      #24                 // Field io/undertow/server/handlers/proxy/ProxyHandler$ProxyAction.proxyClientHandler:Lio/undertow/server/handlers/proxy/ProxyHandler$ProxyClientHandler;
     141: aload_0
     142: getfield      #1                  // Field this$0:Lio/undertow/server/handlers/proxy/ProxyHandler$ProxyAction;
     145: getfield      #25                 // Field io/undertow/server/handlers/proxy/ProxyHandler$ProxyAction.idempotentPredicate:Lio/undertow/predicate/Predicate;
     148: invokespecial #26                 // Method io/undertow/server/handlers/proxy/ProxyHandler$ResponseCallback."<init>":(Lio/undertow/server/HttpServerExchange;Lio/undertow/server/handlers/proxy/ProxyHandler$ProxyClientHandler;Lio/undertow/predicate/Predicate;)V
     151: invokeinterface #27,  2           // InterfaceMethod io/undertow/client/ClientExchange.setResponseListener:(Lio/undertow/client/ClientCallback;)V
     156: new           #28                 // class io/undertow/server/handlers/proxy/ProxyHandler$IoExceptionHandler
     159: dup
     160: aload_0
     161: getfield      #1                  // Field this$0:Lio/undertow/server/handlers/proxy/ProxyHandler$ProxyAction;
     164: getfield      #8                  // Field io/undertow/server/handlers/proxy/ProxyHandler$ProxyAction.exchange:Lio/undertow/server/HttpServerExchange;
     167: aload_0
     168: getfield      #1                  // Field this$0:Lio/undertow/server/handlers/proxy/ProxyHandler$ProxyAction;
     171: getfield      #29                 // Field io/undertow/server/handlers/proxy/ProxyHandler$ProxyAction.clientConnection:Lio/undertow/server/handlers/proxy/ProxyConnection;
     174: invokevirtual #30                 // Method io/undertow/server/handlers/proxy/ProxyConnection.getConnection:()Lio/undertow/client/ClientConnection;
     177: invokespecial #31                 // Method io/undertow/server/handlers/proxy/ProxyHandler$IoExceptionHandler."<init>":(Lio/undertow/server/HttpServerExchange;Lio/undertow/client/ClientConnection;)V
     180: astore_3
     181: iload_2
     182: ifeq          258
     185: aload_1
     186: invokeinterface #32,  1           // InterfaceMethod io/undertow/client/ClientExchange.getRequestChannel:()Lorg/xnio/channels/StreamSinkChannel;
     191: invokeinterface #33,  1           // InterfaceMethod org/xnio/channels/StreamSinkChannel.flush:()Z
     196: ifne          241
     199: aload_1
     200: invokeinterface #32,  1           // InterfaceMethod io/undertow/client/ClientExchange.getRequestChannel:()Lorg/xnio/channels/StreamSinkChannel;
     205: invokeinterface #34,  1           // InterfaceMethod org/xnio/channels/StreamSinkChannel.getWriteSetter:()Lorg/xnio/ChannelListener$Setter;
     210: new           #35                 // class io/undertow/server/handlers/proxy/ProxyHandler$ProxyAction$1$3
     213: dup
     214: aload_0
     215: aload_1
     216: aload_3
     217: invokespecial #36                 // Method io/undertow/server/handlers/proxy/ProxyHandler$ProxyAction$1$3."<init>":(Lio/undertow/server/handlers/proxy/ProxyHandler$ProxyAction$1;Lio/undertow/client/ClientExchange;Lio/undertow/server/handlers/proxy/ProxyHandler$IoExceptionHandler;)V
     220: aload_3
     221: invokestatic  #37                 // Method org/xnio/ChannelListeners.flushingChannelListener:(Lorg/xnio/ChannelListener;Lorg/xnio/ChannelExceptionHandler;)Lorg/xnio/ChannelListener;
     224: invokeinterface #38,  2           // InterfaceMethod org/xnio/ChannelListener$Setter.set:(Lorg/xnio/ChannelListener;)V
     229: aload_1
     230: invokeinterface #32,  1           // InterfaceMethod io/undertow/client/ClientExchange.getRequestChannel:()Lorg/xnio/channels/StreamSinkChannel;
     235: invokeinterface #39,  1           // InterfaceMethod org/xnio/channels/StreamSinkChannel.resumeWrites:()V
     240: return
     241: goto          258
     244: astore        4
     246: aload_3
     247: aload_1
     248: invokeinterface #32,  1           // InterfaceMethod io/undertow/client/ClientExchange.getRequestChannel:()Lorg/xnio/channels/StreamSinkChannel;
     253: aload         4
     255: invokevirtual #41                 // Method io/undertow/server/handlers/proxy/ProxyHandler$IoExceptionHandler.handleException:(Ljava/nio/channels/Channel;Ljava/io/IOException;)V
     258: new           #42                 // class io/undertow/server/handlers/proxy/ProxyHandler$HTTPTrailerChannelListener
     261: dup
     262: aload_0
     263: getfield      #1                  // Field this$0:Lio/undertow/server/handlers/proxy/ProxyHandler$ProxyAction;
     266: getfield      #8                  // Field io/undertow/server/handlers/proxy/ProxyHandler$ProxyAction.exchange:Lio/undertow/server/HttpServerExchange;
     269: aload_1
     270: aload_0
     271: getfield      #1                  // Field this$0:Lio/undertow/server/handlers/proxy/ProxyHandler$ProxyAction;
     274: getfield      #8                  // Field io/undertow/server/handlers/proxy/ProxyHandler$ProxyAction.exchange:Lio/undertow/server/HttpServerExchange;
     277: aload_0
     278: getfield      #1                  // Field this$0:Lio/undertow/server/handlers/proxy/ProxyHandler$ProxyAction;
     281: getfield      #24                 // Field io/undertow/server/handlers/proxy/ProxyHandler$ProxyAction.proxyClientHandler:Lio/undertow/server/handlers/proxy/ProxyHandler$ProxyClientHandler;
     284: aload_0
     285: getfield      #1                  // Field this$0:Lio/undertow/server/handlers/proxy/ProxyHandler$ProxyAction;
     288: getfield      #25                 // Field io/undertow/server/handlers/proxy/ProxyHandler$ProxyAction.idempotentPredicate:Lio/undertow/predicate/Predicate;
     291: invokespecial #43                 // Method io/undertow/server/handlers/proxy/ProxyHandler$HTTPTrailerChannelListener."<init>":(Lio/undertow/util/Attachable;Lio/undertow/util/Attachable;Lio/undertow/server/HttpServerExchange;Lio/undertow/server/handlers/proxy/ProxyHandler$ProxyClientHandler;Lio/undertow/predicate/Predicate;)V
     294: astore        4
     296: aload_0
     297: getfield      #1                  // Field this$0:Lio/undertow/server/handlers/proxy/ProxyHandler$ProxyAction;
     300: getfield      #8                  // Field io/undertow/server/handlers/proxy/ProxyHandler$ProxyAction.exchange:Lio/undertow/server/HttpServerExchange;
     303: invokevirtual #44                 // Method io/undertow/server/HttpServerExchange.isRequestComplete:()Z
     306: ifne          351
     309: aload_0
     310: getfield      #1                  // Field this$0:Lio/undertow/server/handlers/proxy/ProxyHandler$ProxyAction;
     313: getfield      #8                  // Field io/undertow/server/handlers/proxy/ProxyHandler$ProxyAction.exchange:Lio/undertow/server/HttpServerExchange;
     316: invokevirtual #45                 // Method io/undertow/server/HttpServerExchange.getRequestChannel:()Lorg/xnio/channels/StreamSourceChannel;
     319: aload_1
     320: invokeinterface #32,  1           // InterfaceMethod io/undertow/client/ClientExchange.getRequestChannel:()Lorg/xnio/channels/StreamSinkChannel;
     325: invokestatic  #46                 // Method org/xnio/ChannelListeners.closingChannelListener:()Lorg/xnio/ChannelListener;
     328: aload         4
     330: aload_3
     331: aload_3
     332: aload_0
     333: getfield      #1                  // Field this$0:Lio/undertow/server/handlers/proxy/ProxyHandler$ProxyAction;
     336: getfield      #8                  // Field io/undertow/server/handlers/proxy/ProxyHandler$ProxyAction.exchange:Lio/undertow/server/HttpServerExchange;
     339: invokevirtual #16                 // Method io/undertow/server/HttpServerExchange.getConnection:()Lio/undertow/server/ServerConnection;
     342: invokevirtual #47                 // Method io/undertow/server/ServerConnection.getByteBufferPool:()Lio/undertow/connector/ByteBufferPool;
     345: invokestatic  #48                 // Method io/undertow/util/Transfer.initiateTransfer:(Lorg/xnio/channels/StreamSourceChannel;Lorg/xnio/channels/StreamSinkChannel;Lorg/xnio/ChannelListener;Lorg/xnio/ChannelListener;Lorg/xnio/ChannelExceptionHandler;Lorg/xnio/ChannelExceptionHandler;Lio/undertow/connector/ByteBufferPool;)V
     348: goto          362
     351: aload         4
     353: aload_1
     354: invokeinterface #32,  1           // InterfaceMethod io/undertow/client/ClientExchange.getRequestChannel:()Lorg/xnio/channels/StreamSinkChannel;
     359: invokevirtual #49                 // Method io/undertow/server/handlers/proxy/ProxyHandler$HTTPTrailerChannelListener.handleEvent:(Lorg/xnio/channels/StreamSinkChannel;)V
     362: return
    Exception table:
       from    to  target type
         185   240   244   Class java/io/IOException

  public void failed(java.io.IOException);
    Code:
       0: aload_0
       1: getfield      #1                  // Field this$0:Lio/undertow/server/handlers/proxy/ProxyHandler$ProxyAction;
       4: getfield      #8                  // Field io/undertow/server/handlers/proxy/ProxyHandler$ProxyAction.exchange:Lio/undertow/server/HttpServerExchange;
       7: aload_0
       8: getfield      #1                  // Field this$0:Lio/undertow/server/handlers/proxy/ProxyHandler$ProxyAction;
      11: getfield      #24                 // Field io/undertow/server/handlers/proxy/ProxyHandler$ProxyAction.proxyClientHandler:Lio/undertow/server/handlers/proxy/ProxyHandler$ProxyClientHandler;
      14: aload_0
      15: getfield      #1                  // Field this$0:Lio/undertow/server/handlers/proxy/ProxyHandler$ProxyAction;
      18: getfield      #25                 // Field io/undertow/server/handlers/proxy/ProxyHandler$ProxyAction.idempotentPredicate:Lio/undertow/predicate/Predicate;
      21: aload_1
      22: invokestatic  #50                 // Method io/undertow/server/handlers/proxy/ProxyHandler.handleFailure:(Lio/undertow/server/HttpServerExchange;Lio/undertow/server/handlers/proxy/ProxyHandler$ProxyClientHandler;Lio/undertow/predicate/Predicate;Ljava/io/IOException;)V
      25: return

  public void completed(java.lang.Object);
    Code:
       0: aload_0
       1: aload_1
       2: checkcast     #51                 // class io/undertow/client/ClientExchange
       5: invokevirtual #52                 // Method completed:(Lio/undertow/client/ClientExchange;)V
       8: return
}
