Compiled from "StdKeySerializers.java"
public class org.codehaus.jackson.map.ser.std.StdKeySerializers$CalendarKeySerializer extends org.codehaus.jackson.map.ser.std.SerializerBase<java.util.Calendar> {
  protected static final org.codehaus.jackson.map.JsonSerializer<?> instance;

  public org.codehaus.jackson.map.ser.std.StdKeySerializers$CalendarKeySerializer();
    Code:
       0: aload_0
       1: ldc_w         #1                  // class java/util/Calendar
       4: invokespecial #2                  // Method org/codehaus/jackson/map/ser/std/SerializerBase."<init>":(Ljava/lang/Class;)V
       7: return

  public void serialize(java.util.Calendar, org.codehaus.jackson.JsonGenerator, org.codehaus.jackson.map.SerializerProvider) throws java.io.IOException, org.codehaus.jackson.JsonGenerationException;
    Code:
       0: aload_3
       1: aload_1
       2: invokevirtual #3                  // Method java/util/Calendar.getTimeInMillis:()J
       5: aload_2
       6: invokevirtual #4                  // Method org/codehaus/jackson/map/SerializerProvider.defaultSerializeDateKey:(JLorg/codehaus/jackson/JsonGenerator;)V
       9: return

  public void serialize(java.lang.Object, org.codehaus.jackson.JsonGenerator, org.codehaus.jackson.map.SerializerProvider) throws java.io.IOException, org.codehaus.jackson.JsonGenerationException;
    Code:
       0: aload_0
       1: aload_1
       2: checkcast     #1                  // class java/util/Calendar
       5: aload_2
       6: aload_3
       7: invokevirtual #5                  // Method serialize:(Ljava/util/Calendar;Lorg/codehaus/jackson/JsonGenerator;Lorg/codehaus/jackson/map/SerializerProvider;)V
      10: return

  static {};
    Code:
       0: new           #6                  // class org/codehaus/jackson/map/ser/std/StdKeySerializers$CalendarKeySerializer
       3: dup
       4: invokespecial #7                  // Method "<init>":()V
       7: putstatic     #8                  // Field instance:Lorg/codehaus/jackson/map/JsonSerializer;
      10: return
}
