Compiled from "StdKeySerializers.java"
public class org.codehaus.jackson.map.ser.std.StdKeySerializers$StringKeySerializer extends org.codehaus.jackson.map.ser.std.SerializerBase<java.lang.String> {
  public org.codehaus.jackson.map.ser.std.StdKeySerializers$StringKeySerializer();
    Code:
       0: aload_0
       1: ldc_w         #1                  // class java/lang/String
       4: invokespecial #2                  // Method org/codehaus/jackson/map/ser/std/SerializerBase."<init>":(Ljava/lang/Class;)V
       7: return

  public void serialize(java.lang.String, org.codehaus.jackson.JsonGenerator, org.codehaus.jackson.map.SerializerProvider) throws java.io.IOException, org.codehaus.jackson.JsonGenerationException;
    Code:
       0: aload_2
       1: aload_1
       2: invokevirtual #3                  // Method org/codehaus/jackson/JsonGenerator.writeFieldName:(Ljava/lang/String;)V
       5: return

  public void serialize(java.lang.Object, org.codehaus.jackson.JsonGenerator, org.codehaus.jackson.map.SerializerProvider) throws java.io.IOException, org.codehaus.jackson.JsonGenerationException;
    Code:
       0: aload_0
       1: aload_1
       2: checkcast     #1                  // class java/lang/String
       5: aload_2
       6: aload_3
       7: invokevirtual #4                  // Method serialize:(Ljava/lang/String;Lorg/codehaus/jackson/JsonGenerator;Lorg/codehaus/jackson/map/SerializerProvider;)V
      10: return
}
