Compiled from "Element.java"
public final class org.jboss.metadata.parser.servlet.Element extends java.lang.Enum<org.jboss.metadata.parser.servlet.Element> {
  public static final org.jboss.metadata.parser.servlet.Element UNKNOWN;

  public static final org.jboss.metadata.parser.servlet.Element ABSOLUTE_ORDERING;

  public static final org.jboss.metadata.parser.servlet.Element AFTER;

  public static final org.jboss.metadata.parser.servlet.Element ASYNC_SUPPORTED;

  public static final org.jboss.metadata.parser.servlet.Element AUTH_CONSTRAINT;

  public static final org.jboss.metadata.parser.servlet.Element AUTH_METHOD;

  public static final org.jboss.metadata.parser.servlet.Element BEFORE;

  public static final org.jboss.metadata.parser.servlet.Element BUFFER;

  public static final org.jboss.metadata.parser.servlet.Element COMMENT;

  public static final org.jboss.metadata.parser.servlet.Element CONTEXT_PARAM;

  public static final org.jboss.metadata.parser.servlet.Element COOKIE_CONFIG;

  public static final org.jboss.metadata.parser.servlet.Element DEFAULT_CONTENT_TYPE;

  public static final org.jboss.metadata.parser.servlet.Element DEFERRED_SYNTAX_ALLOWED_AS_LITERAL;

  public static final org.jboss.metadata.parser.servlet.Element DENY_UNCOVERED_HTTP_METHODS;

  public static final org.jboss.metadata.parser.servlet.Element DISPATCHER;

  public static final org.jboss.metadata.parser.servlet.Element DISPLAY_NAME;

  public static final org.jboss.metadata.parser.servlet.Element DISTRIBUTABLE;

  public static final org.jboss.metadata.parser.servlet.Element DOMAIN;

  public static final org.jboss.metadata.parser.servlet.Element EL_IGNORED;

  public static final org.jboss.metadata.parser.servlet.Element ENABLED;

  public static final org.jboss.metadata.parser.servlet.Element ENCODING;

  public static final org.jboss.metadata.parser.servlet.Element ERROR_CODE;

  public static final org.jboss.metadata.parser.servlet.Element ERROR_ON_UNDECLARED_NAMESPACE;

  public static final org.jboss.metadata.parser.servlet.Element ERROR_PAGE;

  public static final org.jboss.metadata.parser.servlet.Element EXCEPTION_TYPE;

  public static final org.jboss.metadata.parser.servlet.Element EXTENSION;

  public static final org.jboss.metadata.parser.servlet.Element FILE_SIZE_THRESHOLD;

  public static final org.jboss.metadata.parser.servlet.Element FILTER;

  public static final org.jboss.metadata.parser.servlet.Element FILTER_CLASS;

  public static final org.jboss.metadata.parser.servlet.Element FILTER_NAME;

  public static final org.jboss.metadata.parser.servlet.Element FILTER_MAPPING;

  public static final org.jboss.metadata.parser.servlet.Element FORM_ERROR_PAGE;

  public static final org.jboss.metadata.parser.servlet.Element FORM_LOGIN_CONFIG;

  public static final org.jboss.metadata.parser.servlet.Element FORM_LOGIN_PAGE;

  public static final org.jboss.metadata.parser.servlet.Element HTTP_METHOD;

  public static final org.jboss.metadata.parser.servlet.Element HTTP_METHOD_OMISSION;

  public static final org.jboss.metadata.parser.servlet.Element HTTP_ONLY;

  public static final org.jboss.metadata.parser.servlet.Element INCLUDE_CODA;

  public static final org.jboss.metadata.parser.servlet.Element INCLUDE_PRELUDE;

  public static final org.jboss.metadata.parser.servlet.Element INIT_PARAM;

  public static final org.jboss.metadata.parser.servlet.Element IS_XML;

  public static final org.jboss.metadata.parser.servlet.Element JSP_CONFIG;

  public static final org.jboss.metadata.parser.servlet.Element JSP_FILE;

  public static final org.jboss.metadata.parser.servlet.Element JSP_PROPERTY_GROUP;

  public static final org.jboss.metadata.parser.servlet.Element LISTENER;

  public static final org.jboss.metadata.parser.servlet.Element LISTENER_CLASS;

  public static final org.jboss.metadata.parser.servlet.Element LOAD_ON_STARTUP;

  public static final org.jboss.metadata.parser.servlet.Element LOCALE_ENCODING_MAPPING;

  public static final org.jboss.metadata.parser.servlet.Element LOCALE_ENCODING_MAPPING_LIST;

  public static final org.jboss.metadata.parser.servlet.Element LOCALE;

  public static final org.jboss.metadata.parser.servlet.Element LOCATION;

  public static final org.jboss.metadata.parser.servlet.Element LOGIN_CONFIG;

  public static final org.jboss.metadata.parser.servlet.Element MAX_AGE;

  public static final org.jboss.metadata.parser.servlet.Element MAX_FILE_SIZE;

  public static final org.jboss.metadata.parser.servlet.Element MAX_REQUEST_SIZE;

  public static final org.jboss.metadata.parser.servlet.Element MESSAGE_DESTINATION;

  public static final org.jboss.metadata.parser.servlet.Element MIME_MAPPING;

  public static final org.jboss.metadata.parser.servlet.Element MIME_TYPE;

  public static final org.jboss.metadata.parser.servlet.Element MODULE_NAME;

  public static final org.jboss.metadata.parser.servlet.Element MULTIPART_CONFIG;

  public static final org.jboss.metadata.parser.servlet.Element NAME;

  public static final org.jboss.metadata.parser.servlet.Element ORDERING;

  public static final org.jboss.metadata.parser.servlet.Element OTHERS;

  public static final org.jboss.metadata.parser.servlet.Element PAGE_ENCODING;

  public static final org.jboss.metadata.parser.servlet.Element PATH;

  public static final org.jboss.metadata.parser.servlet.Element REALM_NAME;

  public static final org.jboss.metadata.parser.servlet.Element ROLE_NAME;

  public static final org.jboss.metadata.parser.servlet.Element RUN_AS;

  public static final org.jboss.metadata.parser.servlet.Element SCRIPTING_INVALID;

  public static final org.jboss.metadata.parser.servlet.Element SECURE;

  public static final org.jboss.metadata.parser.servlet.Element SECURITY_CONSTRAINT;

  public static final org.jboss.metadata.parser.servlet.Element SECURITY_ROLE;

  public static final org.jboss.metadata.parser.servlet.Element SECURITY_ROLE_REF;

  public static final org.jboss.metadata.parser.servlet.Element SERVLET;

  public static final org.jboss.metadata.parser.servlet.Element SERVLET_CLASS;

  public static final org.jboss.metadata.parser.servlet.Element SERVLET_MAPPING;

  public static final org.jboss.metadata.parser.servlet.Element SERVLET_NAME;

  public static final org.jboss.metadata.parser.servlet.Element SESSION_CONFIG;

  public static final org.jboss.metadata.parser.servlet.Element SESSION_TIMEOUT;

  public static final org.jboss.metadata.parser.servlet.Element TAGLIB;

  public static final org.jboss.metadata.parser.servlet.Element TAGLIB_LOCATION;

  public static final org.jboss.metadata.parser.servlet.Element TAGLIB_URI;

  public static final org.jboss.metadata.parser.servlet.Element TRACKING_MODE;

  public static final org.jboss.metadata.parser.servlet.Element TRANSPORT_GUARANTEE;

  public static final org.jboss.metadata.parser.servlet.Element TRIM_DIRECTIVE_WHITESPACES;

  public static final org.jboss.metadata.parser.servlet.Element URL_PATTERN;

  public static final org.jboss.metadata.parser.servlet.Element USER_DATA_CONSTRAINT;

  public static final org.jboss.metadata.parser.servlet.Element WEB_RESOURCE_COLLECTION;

  public static final org.jboss.metadata.parser.servlet.Element WEB_RESOURCE_NAME;

  public static final org.jboss.metadata.parser.servlet.Element WELCOME_FILE;

  public static final org.jboss.metadata.parser.servlet.Element WELCOME_FILE_LIST;

  private final java.lang.String name;

  private static final java.util.Map<java.lang.String, org.jboss.metadata.parser.servlet.Element> MAP;

  private static final org.jboss.metadata.parser.servlet.Element[] $VALUES;

  public static org.jboss.metadata.parser.servlet.Element[] values();
    Code:
       0: getstatic     #1                  // Field $VALUES:[Lorg/jboss/metadata/parser/servlet/Element;
       3: invokevirtual #2                  // Method "[Lorg/jboss/metadata/parser/servlet/Element;".clone:()Ljava/lang/Object;
       6: checkcast     #3                  // class "[Lorg/jboss/metadata/parser/servlet/Element;"
       9: areturn

  public static org.jboss.metadata.parser.servlet.Element valueOf(java.lang.String);
    Code:
       0: ldc           #4                  // class org/jboss/metadata/parser/servlet/Element
       2: aload_0
       3: invokestatic  #5                  // Method java/lang/Enum.valueOf:(Ljava/lang/Class;Ljava/lang/String;)Ljava/lang/Enum;
       6: checkcast     #4                  // class org/jboss/metadata/parser/servlet/Element
       9: areturn

  private org.jboss.metadata.parser.servlet.Element(java.lang.String);
    Code:
       0: aload_0
       1: aload_1
       2: iload_2
       3: invokespecial #6                  // Method java/lang/Enum."<init>":(Ljava/lang/String;I)V
       6: aload_0
       7: aload_3
       8: putfield      #7                  // Field name:Ljava/lang/String;
      11: return

  public java.lang.String getLocalName();
    Code:
       0: aload_0
       1: getfield      #7                  // Field name:Ljava/lang/String;
       4: areturn

  public static org.jboss.metadata.parser.servlet.Element forName(java.lang.String);
    Code:
       0: getstatic     #8                  // Field MAP:Ljava/util/Map;
       3: aload_0
       4: invokeinterface #9,  2            // InterfaceMethod java/util/Map.get:(Ljava/lang/Object;)Ljava/lang/Object;
       9: checkcast     #4                  // class org/jboss/metadata/parser/servlet/Element
      12: astore_1
      13: aload_1
      14: ifnonnull     23
      17: getstatic     #10                 // Field UNKNOWN:Lorg/jboss/metadata/parser/servlet/Element;
      20: goto          24
      23: aload_1
      24: areturn

  static {};
    Code:
       0: new           #4                  // class org/jboss/metadata/parser/servlet/Element
       3: dup
       4: ldc           #11                 // String UNKNOWN
       6: iconst_0
       7: aconst_null
       8: invokespecial #12                 // Method "<init>":(Ljava/lang/String;ILjava/lang/String;)V
      11: putstatic     #10                 // Field UNKNOWN:Lorg/jboss/metadata/parser/servlet/Element;
      14: new           #4                  // class org/jboss/metadata/parser/servlet/Element
      17: dup
      18: ldc           #13                 // String ABSOLUTE_ORDERING
      20: iconst_1
      21: ldc           #14                 // String absolute-ordering
      23: invokespecial #12                 // Method "<init>":(Ljava/lang/String;ILjava/lang/String;)V
      26: putstatic     #15                 // Field ABSOLUTE_ORDERING:Lorg/jboss/metadata/parser/servlet/Element;
      29: new           #4                  // class org/jboss/metadata/parser/servlet/Element
      32: dup
      33: ldc           #16                 // String AFTER
      35: iconst_2
      36: ldc           #17                 // String after
      38: invokespecial #12                 // Method "<init>":(Ljava/lang/String;ILjava/lang/String;)V
      41: putstatic     #18                 // Field AFTER:Lorg/jboss/metadata/parser/servlet/Element;
      44: new           #4                  // class org/jboss/metadata/parser/servlet/Element
      47: dup
      48: ldc           #19                 // String ASYNC_SUPPORTED
      50: iconst_3
      51: ldc           #20                 // String async-supported
      53: invokespecial #12                 // Method "<init>":(Ljava/lang/String;ILjava/lang/String;)V
      56: putstatic     #21                 // Field ASYNC_SUPPORTED:Lorg/jboss/metadata/parser/servlet/Element;
      59: new           #4                  // class org/jboss/metadata/parser/servlet/Element
      62: dup
      63: ldc           #22                 // String AUTH_CONSTRAINT
      65: iconst_4
      66: ldc           #23                 // String auth-constraint
      68: invokespecial #12                 // Method "<init>":(Ljava/lang/String;ILjava/lang/String;)V
      71: putstatic     #24                 // Field AUTH_CONSTRAINT:Lorg/jboss/metadata/parser/servlet/Element;
      74: new           #4                  // class org/jboss/metadata/parser/servlet/Element
      77: dup
      78: ldc           #25                 // String AUTH_METHOD
      80: iconst_5
      81: ldc           #26                 // String auth-method
      83: invokespecial #12                 // Method "<init>":(Ljava/lang/String;ILjava/lang/String;)V
      86: putstatic     #27                 // Field AUTH_METHOD:Lorg/jboss/metadata/parser/servlet/Element;
      89: new           #4                  // class org/jboss/metadata/parser/servlet/Element
      92: dup
      93: ldc           #28                 // String BEFORE
      95: bipush        6
      97: ldc           #29                 // String before
      99: invokespecial #12                 // Method "<init>":(Ljava/lang/String;ILjava/lang/String;)V
     102: putstatic     #30                 // Field BEFORE:Lorg/jboss/metadata/parser/servlet/Element;
     105: new           #4                  // class org/jboss/metadata/parser/servlet/Element
     108: dup
     109: ldc           #31                 // String BUFFER
     111: bipush        7
     113: ldc           #32                 // String buffer
     115: invokespecial #12                 // Method "<init>":(Ljava/lang/String;ILjava/lang/String;)V
     118: putstatic     #33                 // Field BUFFER:Lorg/jboss/metadata/parser/servlet/Element;
     121: new           #4                  // class org/jboss/metadata/parser/servlet/Element
     124: dup
     125: ldc           #34                 // String COMMENT
     127: bipush        8
     129: ldc           #35                 // String comment
     131: invokespecial #12                 // Method "<init>":(Ljava/lang/String;ILjava/lang/String;)V
     134: putstatic     #36                 // Field COMMENT:Lorg/jboss/metadata/parser/servlet/Element;
     137: new           #4                  // class org/jboss/metadata/parser/servlet/Element
     140: dup
     141: ldc           #37                 // String CONTEXT_PARAM
     143: bipush        9
     145: ldc           #38                 // String context-param
     147: invokespecial #12                 // Method "<init>":(Ljava/lang/String;ILjava/lang/String;)V
     150: putstatic     #39                 // Field CONTEXT_PARAM:Lorg/jboss/metadata/parser/servlet/Element;
     153: new           #4                  // class org/jboss/metadata/parser/servlet/Element
     156: dup
     157: ldc           #40                 // String COOKIE_CONFIG
     159: bipush        10
     161: ldc           #41                 // String cookie-config
     163: invokespecial #12                 // Method "<init>":(Ljava/lang/String;ILjava/lang/String;)V
     166: putstatic     #42                 // Field COOKIE_CONFIG:Lorg/jboss/metadata/parser/servlet/Element;
     169: new           #4                  // class org/jboss/metadata/parser/servlet/Element
     172: dup
     173: ldc           #43                 // String DEFAULT_CONTENT_TYPE
     175: bipush        11
     177: ldc           #44                 // String default-content-type
     179: invokespecial #12                 // Method "<init>":(Ljava/lang/String;ILjava/lang/String;)V
     182: putstatic     #45                 // Field DEFAULT_CONTENT_TYPE:Lorg/jboss/metadata/parser/servlet/Element;
     185: new           #4                  // class org/jboss/metadata/parser/servlet/Element
     188: dup
     189: ldc           #46                 // String DEFERRED_SYNTAX_ALLOWED_AS_LITERAL
     191: bipush        12
     193: ldc           #47                 // String deferred-syntax-allowed-as-literal
     195: invokespecial #12                 // Method "<init>":(Ljava/lang/String;ILjava/lang/String;)V
     198: putstatic     #48                 // Field DEFERRED_SYNTAX_ALLOWED_AS_LITERAL:Lorg/jboss/metadata/parser/servlet/Element;
     201: new           #4                  // class org/jboss/metadata/parser/servlet/Element
     204: dup
     205: ldc           #49                 // String DENY_UNCOVERED_HTTP_METHODS
     207: bipush        13
     209: ldc           #50                 // String deny-uncovered-http-methods
     211: invokespecial #12                 // Method "<init>":(Ljava/lang/String;ILjava/lang/String;)V
     214: putstatic     #51                 // Field DENY_UNCOVERED_HTTP_METHODS:Lorg/jboss/metadata/parser/servlet/Element;
     217: new           #4                  // class org/jboss/metadata/parser/servlet/Element
     220: dup
     221: ldc           #52                 // String DISPATCHER
     223: bipush        14
     225: ldc           #53                 // String dispatcher
     227: invokespecial #12                 // Method "<init>":(Ljava/lang/String;ILjava/lang/String;)V
     230: putstatic     #54                 // Field DISPATCHER:Lorg/jboss/metadata/parser/servlet/Element;
     233: new           #4                  // class org/jboss/metadata/parser/servlet/Element
     236: dup
     237: ldc           #55                 // String DISPLAY_NAME
     239: bipush        15
     241: ldc           #56                 // String display-name
     243: invokespecial #12                 // Method "<init>":(Ljava/lang/String;ILjava/lang/String;)V
     246: putstatic     #57                 // Field DISPLAY_NAME:Lorg/jboss/metadata/parser/servlet/Element;
     249: new           #4                  // class org/jboss/metadata/parser/servlet/Element
     252: dup
     253: ldc           #58                 // String DISTRIBUTABLE
     255: bipush        16
     257: ldc           #59                 // String distributable
     259: invokespecial #12                 // Method "<init>":(Ljava/lang/String;ILjava/lang/String;)V
     262: putstatic     #60                 // Field DISTRIBUTABLE:Lorg/jboss/metadata/parser/servlet/Element;
     265: new           #4                  // class org/jboss/metadata/parser/servlet/Element
     268: dup
     269: ldc           #61                 // String DOMAIN
     271: bipush        17
     273: ldc           #62                 // String domain
     275: invokespecial #12                 // Method "<init>":(Ljava/lang/String;ILjava/lang/String;)V
     278: putstatic     #63                 // Field DOMAIN:Lorg/jboss/metadata/parser/servlet/Element;
     281: new           #4                  // class org/jboss/metadata/parser/servlet/Element
     284: dup
     285: ldc           #64                 // String EL_IGNORED
     287: bipush        18
     289: ldc           #65                 // String el-ignored
     291: invokespecial #12                 // Method "<init>":(Ljava/lang/String;ILjava/lang/String;)V
     294: putstatic     #66                 // Field EL_IGNORED:Lorg/jboss/metadata/parser/servlet/Element;
     297: new           #4                  // class org/jboss/metadata/parser/servlet/Element
     300: dup
     301: ldc           #67                 // String ENABLED
     303: bipush        19
     305: ldc           #68                 // String enabled
     307: invokespecial #12                 // Method "<init>":(Ljava/lang/String;ILjava/lang/String;)V
     310: putstatic     #69                 // Field ENABLED:Lorg/jboss/metadata/parser/servlet/Element;
     313: new           #4                  // class org/jboss/metadata/parser/servlet/Element
     316: dup
     317: ldc           #70                 // String ENCODING
     319: bipush        20
     321: ldc           #71                 // String encoding
     323: invokespecial #12                 // Method "<init>":(Ljava/lang/String;ILjava/lang/String;)V
     326: putstatic     #72                 // Field ENCODING:Lorg/jboss/metadata/parser/servlet/Element;
     329: new           #4                  // class org/jboss/metadata/parser/servlet/Element
     332: dup
     333: ldc           #73                 // String ERROR_CODE
     335: bipush        21
     337: ldc           #74                 // String error-code
     339: invokespecial #12                 // Method "<init>":(Ljava/lang/String;ILjava/lang/String;)V
     342: putstatic     #75                 // Field ERROR_CODE:Lorg/jboss/metadata/parser/servlet/Element;
     345: new           #4                  // class org/jboss/metadata/parser/servlet/Element
     348: dup
     349: ldc           #76                 // String ERROR_ON_UNDECLARED_NAMESPACE
     351: bipush        22
     353: ldc           #77                 // String error-on-undeclared-namespace
     355: invokespecial #12                 // Method "<init>":(Ljava/lang/String;ILjava/lang/String;)V
     358: putstatic     #78                 // Field ERROR_ON_UNDECLARED_NAMESPACE:Lorg/jboss/metadata/parser/servlet/Element;
     361: new           #4                  // class org/jboss/metadata/parser/servlet/Element
     364: dup
     365: ldc           #79                 // String ERROR_PAGE
     367: bipush        23
     369: ldc           #80                 // String error-page
     371: invokespecial #12                 // Method "<init>":(Ljava/lang/String;ILjava/lang/String;)V
     374: putstatic     #81                 // Field ERROR_PAGE:Lorg/jboss/metadata/parser/servlet/Element;
     377: new           #4                  // class org/jboss/metadata/parser/servlet/Element
     380: dup
     381: ldc           #82                 // String EXCEPTION_TYPE
     383: bipush        24
     385: ldc           #83                 // String exception-type
     387: invokespecial #12                 // Method "<init>":(Ljava/lang/String;ILjava/lang/String;)V
     390: putstatic     #84                 // Field EXCEPTION_TYPE:Lorg/jboss/metadata/parser/servlet/Element;
     393: new           #4                  // class org/jboss/metadata/parser/servlet/Element
     396: dup
     397: ldc           #85                 // String EXTENSION
     399: bipush        25
     401: ldc           #86                 // String extension
     403: invokespecial #12                 // Method "<init>":(Ljava/lang/String;ILjava/lang/String;)V
     406: putstatic     #87                 // Field EXTENSION:Lorg/jboss/metadata/parser/servlet/Element;
     409: new           #4                  // class org/jboss/metadata/parser/servlet/Element
     412: dup
     413: ldc           #88                 // String FILE_SIZE_THRESHOLD
     415: bipush        26
     417: ldc           #89                 // String file-size-threshold
     419: invokespecial #12                 // Method "<init>":(Ljava/lang/String;ILjava/lang/String;)V
     422: putstatic     #90                 // Field FILE_SIZE_THRESHOLD:Lorg/jboss/metadata/parser/servlet/Element;
     425: new           #4                  // class org/jboss/metadata/parser/servlet/Element
     428: dup
     429: ldc           #91                 // String FILTER
     431: bipush        27
     433: ldc           #92                 // String filter
     435: invokespecial #12                 // Method "<init>":(Ljava/lang/String;ILjava/lang/String;)V
     438: putstatic     #93                 // Field FILTER:Lorg/jboss/metadata/parser/servlet/Element;
     441: new           #4                  // class org/jboss/metadata/parser/servlet/Element
     444: dup
     445: ldc           #94                 // String FILTER_CLASS
     447: bipush        28
     449: ldc           #95                 // String filter-class
     451: invokespecial #12                 // Method "<init>":(Ljava/lang/String;ILjava/lang/String;)V
     454: putstatic     #96                 // Field FILTER_CLASS:Lorg/jboss/metadata/parser/servlet/Element;
     457: new           #4                  // class org/jboss/metadata/parser/servlet/Element
     460: dup
     461: ldc           #97                 // String FILTER_NAME
     463: bipush        29
     465: ldc           #98                 // String filter-name
     467: invokespecial #12                 // Method "<init>":(Ljava/lang/String;ILjava/lang/String;)V
     470: putstatic     #99                 // Field FILTER_NAME:Lorg/jboss/metadata/parser/servlet/Element;
     473: new           #4                  // class org/jboss/metadata/parser/servlet/Element
     476: dup
     477: ldc           #100                // String FILTER_MAPPING
     479: bipush        30
     481: ldc           #101                // String filter-mapping
     483: invokespecial #12                 // Method "<init>":(Ljava/lang/String;ILjava/lang/String;)V
     486: putstatic     #102                // Field FILTER_MAPPING:Lorg/jboss/metadata/parser/servlet/Element;
     489: new           #4                  // class org/jboss/metadata/parser/servlet/Element
     492: dup
     493: ldc           #103                // String FORM_ERROR_PAGE
     495: bipush        31
     497: ldc           #104                // String form-error-page
     499: invokespecial #12                 // Method "<init>":(Ljava/lang/String;ILjava/lang/String;)V
     502: putstatic     #105                // Field FORM_ERROR_PAGE:Lorg/jboss/metadata/parser/servlet/Element;
     505: new           #4                  // class org/jboss/metadata/parser/servlet/Element
     508: dup
     509: ldc           #106                // String FORM_LOGIN_CONFIG
     511: bipush        32
     513: ldc           #107                // String form-login-config
     515: invokespecial #12                 // Method "<init>":(Ljava/lang/String;ILjava/lang/String;)V
     518: putstatic     #108                // Field FORM_LOGIN_CONFIG:Lorg/jboss/metadata/parser/servlet/Element;
     521: new           #4                  // class org/jboss/metadata/parser/servlet/Element
     524: dup
     525: ldc           #109                // String FORM_LOGIN_PAGE
     527: bipush        33
     529: ldc           #110                // String form-login-page
     531: invokespecial #12                 // Method "<init>":(Ljava/lang/String;ILjava/lang/String;)V
     534: putstatic     #111                // Field FORM_LOGIN_PAGE:Lorg/jboss/metadata/parser/servlet/Element;
     537: new           #4                  // class org/jboss/metadata/parser/servlet/Element
     540: dup
     541: ldc           #112                // String HTTP_METHOD
     543: bipush        34
     545: ldc           #113                // String http-method
     547: invokespecial #12                 // Method "<init>":(Ljava/lang/String;ILjava/lang/String;)V
     550: putstatic     #114                // Field HTTP_METHOD:Lorg/jboss/metadata/parser/servlet/Element;
     553: new           #4                  // class org/jboss/metadata/parser/servlet/Element
     556: dup
     557: ldc           #115                // String HTTP_METHOD_OMISSION
     559: bipush        35
     561: ldc           #116                // String http-method-omission
     563: invokespecial #12                 // Method "<init>":(Ljava/lang/String;ILjava/lang/String;)V
     566: putstatic     #117                // Field HTTP_METHOD_OMISSION:Lorg/jboss/metadata/parser/servlet/Element;
     569: new           #4                  // class org/jboss/metadata/parser/servlet/Element
     572: dup
     573: ldc           #118                // String HTTP_ONLY
     575: bipush        36
     577: ldc           #119                // String http-only
     579: invokespecial #12                 // Method "<init>":(Ljava/lang/String;ILjava/lang/String;)V
     582: putstatic     #120                // Field HTTP_ONLY:Lorg/jboss/metadata/parser/servlet/Element;
     585: new           #4                  // class org/jboss/metadata/parser/servlet/Element
     588: dup
     589: ldc           #121                // String INCLUDE_CODA
     591: bipush        37
     593: ldc           #122                // String include-coda
     595: invokespecial #12                 // Method "<init>":(Ljava/lang/String;ILjava/lang/String;)V
     598: putstatic     #123                // Field INCLUDE_CODA:Lorg/jboss/metadata/parser/servlet/Element;
     601: new           #4                  // class org/jboss/metadata/parser/servlet/Element
     604: dup
     605: ldc           #124                // String INCLUDE_PRELUDE
     607: bipush        38
     609: ldc           #125                // String include-prelude
     611: invokespecial #12                 // Method "<init>":(Ljava/lang/String;ILjava/lang/String;)V
     614: putstatic     #126                // Field INCLUDE_PRELUDE:Lorg/jboss/metadata/parser/servlet/Element;
     617: new           #4                  // class org/jboss/metadata/parser/servlet/Element
     620: dup
     621: ldc           #127                // String INIT_PARAM
     623: bipush        39
     625: ldc           #128                // String init-param
     627: invokespecial #12                 // Method "<init>":(Ljava/lang/String;ILjava/lang/String;)V
     630: putstatic     #129                // Field INIT_PARAM:Lorg/jboss/metadata/parser/servlet/Element;
     633: new           #4                  // class org/jboss/metadata/parser/servlet/Element
     636: dup
     637: ldc           #130                // String IS_XML
     639: bipush        40
     641: ldc           #131                // String is-xml
     643: invokespecial #12                 // Method "<init>":(Ljava/lang/String;ILjava/lang/String;)V
     646: putstatic     #132                // Field IS_XML:Lorg/jboss/metadata/parser/servlet/Element;
     649: new           #4                  // class org/jboss/metadata/parser/servlet/Element
     652: dup
     653: ldc           #133                // String JSP_CONFIG
     655: bipush        41
     657: ldc           #134                // String jsp-config
     659: invokespecial #12                 // Method "<init>":(Ljava/lang/String;ILjava/lang/String;)V
     662: putstatic     #135                // Field JSP_CONFIG:Lorg/jboss/metadata/parser/servlet/Element;
     665: new           #4                  // class org/jboss/metadata/parser/servlet/Element
     668: dup
     669: ldc           #136                // String JSP_FILE
     671: bipush        42
     673: ldc           #137                // String jsp-file
     675: invokespecial #12                 // Method "<init>":(Ljava/lang/String;ILjava/lang/String;)V
     678: putstatic     #138                // Field JSP_FILE:Lorg/jboss/metadata/parser/servlet/Element;
     681: new           #4                  // class org/jboss/metadata/parser/servlet/Element
     684: dup
     685: ldc           #139                // String JSP_PROPERTY_GROUP
     687: bipush        43
     689: ldc           #140                // String jsp-property-group
     691: invokespecial #12                 // Method "<init>":(Ljava/lang/String;ILjava/lang/String;)V
     694: putstatic     #141                // Field JSP_PROPERTY_GROUP:Lorg/jboss/metadata/parser/servlet/Element;
     697: new           #4                  // class org/jboss/metadata/parser/servlet/Element
     700: dup
     701: ldc           #142                // String LISTENER
     703: bipush        44
     705: ldc           #143                // String listener
     707: invokespecial #12                 // Method "<init>":(Ljava/lang/String;ILjava/lang/String;)V
     710: putstatic     #144                // Field LISTENER:Lorg/jboss/metadata/parser/servlet/Element;
     713: new           #4                  // class org/jboss/metadata/parser/servlet/Element
     716: dup
     717: ldc           #145                // String LISTENER_CLASS
     719: bipush        45
     721: ldc           #146                // String listener-class
     723: invokespecial #12                 // Method "<init>":(Ljava/lang/String;ILjava/lang/String;)V
     726: putstatic     #147                // Field LISTENER_CLASS:Lorg/jboss/metadata/parser/servlet/Element;
     729: new           #4                  // class org/jboss/metadata/parser/servlet/Element
     732: dup
     733: ldc           #148                // String LOAD_ON_STARTUP
     735: bipush        46
     737: ldc           #149                // String load-on-startup
     739: invokespecial #12                 // Method "<init>":(Ljava/lang/String;ILjava/lang/String;)V
     742: putstatic     #150                // Field LOAD_ON_STARTUP:Lorg/jboss/metadata/parser/servlet/Element;
     745: new           #4                  // class org/jboss/metadata/parser/servlet/Element
     748: dup
     749: ldc           #151                // String LOCALE_ENCODING_MAPPING
     751: bipush        47
     753: ldc           #152                // String locale-encoding-mapping
     755: invokespecial #12                 // Method "<init>":(Ljava/lang/String;ILjava/lang/String;)V
     758: putstatic     #153                // Field LOCALE_ENCODING_MAPPING:Lorg/jboss/metadata/parser/servlet/Element;
     761: new           #4                  // class org/jboss/metadata/parser/servlet/Element
     764: dup
     765: ldc           #154                // String LOCALE_ENCODING_MAPPING_LIST
     767: bipush        48
     769: ldc           #155                // String locale-encoding-mapping-list
     771: invokespecial #12                 // Method "<init>":(Ljava/lang/String;ILjava/lang/String;)V
     774: putstatic     #156                // Field LOCALE_ENCODING_MAPPING_LIST:Lorg/jboss/metadata/parser/servlet/Element;
     777: new           #4                  // class org/jboss/metadata/parser/servlet/Element
     780: dup
     781: ldc           #157                // String LOCALE
     783: bipush        49
     785: ldc           #158                // String locale
     787: invokespecial #12                 // Method "<init>":(Ljava/lang/String;ILjava/lang/String;)V
     790: putstatic     #159                // Field LOCALE:Lorg/jboss/metadata/parser/servlet/Element;
     793: new           #4                  // class org/jboss/metadata/parser/servlet/Element
     796: dup
     797: ldc           #160                // String LOCATION
     799: bipush        50
     801: ldc           #161                // String location
     803: invokespecial #12                 // Method "<init>":(Ljava/lang/String;ILjava/lang/String;)V
     806: putstatic     #162                // Field LOCATION:Lorg/jboss/metadata/parser/servlet/Element;
     809: new           #4                  // class org/jboss/metadata/parser/servlet/Element
     812: dup
     813: ldc           #163                // String LOGIN_CONFIG
     815: bipush        51
     817: ldc           #164                // String login-config
     819: invokespecial #12                 // Method "<init>":(Ljava/lang/String;ILjava/lang/String;)V
     822: putstatic     #165                // Field LOGIN_CONFIG:Lorg/jboss/metadata/parser/servlet/Element;
     825: new           #4                  // class org/jboss/metadata/parser/servlet/Element
     828: dup
     829: ldc           #166                // String MAX_AGE
     831: bipush        52
     833: ldc           #167                // String max-age
     835: invokespecial #12                 // Method "<init>":(Ljava/lang/String;ILjava/lang/String;)V
     838: putstatic     #168                // Field MAX_AGE:Lorg/jboss/metadata/parser/servlet/Element;
     841: new           #4                  // class org/jboss/metadata/parser/servlet/Element
     844: dup
     845: ldc           #169                // String MAX_FILE_SIZE
     847: bipush        53
     849: ldc           #170                // String max-file-size
     851: invokespecial #12                 // Method "<init>":(Ljava/lang/String;ILjava/lang/String;)V
     854: putstatic     #171                // Field MAX_FILE_SIZE:Lorg/jboss/metadata/parser/servlet/Element;
     857: new           #4                  // class org/jboss/metadata/parser/servlet/Element
     860: dup
     861: ldc           #172                // String MAX_REQUEST_SIZE
     863: bipush        54
     865: ldc           #173                // String max-request-size
     867: invokespecial #12                 // Method "<init>":(Ljava/lang/String;ILjava/lang/String;)V
     870: putstatic     #174                // Field MAX_REQUEST_SIZE:Lorg/jboss/metadata/parser/servlet/Element;
     873: new           #4                  // class org/jboss/metadata/parser/servlet/Element
     876: dup
     877: ldc           #175                // String MESSAGE_DESTINATION
     879: bipush        55
     881: ldc           #176                // String message-destination
     883: invokespecial #12                 // Method "<init>":(Ljava/lang/String;ILjava/lang/String;)V
     886: putstatic     #177                // Field MESSAGE_DESTINATION:Lorg/jboss/metadata/parser/servlet/Element;
     889: new           #4                  // class org/jboss/metadata/parser/servlet/Element
     892: dup
     893: ldc           #178                // String MIME_MAPPING
     895: bipush        56
     897: ldc           #179                // String mime-mapping
     899: invokespecial #12                 // Method "<init>":(Ljava/lang/String;ILjava/lang/String;)V
     902: putstatic     #180                // Field MIME_MAPPING:Lorg/jboss/metadata/parser/servlet/Element;
     905: new           #4                  // class org/jboss/metadata/parser/servlet/Element
     908: dup
     909: ldc           #181                // String MIME_TYPE
     911: bipush        57
     913: ldc           #182                // String mime-type
     915: invokespecial #12                 // Method "<init>":(Ljava/lang/String;ILjava/lang/String;)V
     918: putstatic     #183                // Field MIME_TYPE:Lorg/jboss/metadata/parser/servlet/Element;
     921: new           #4                  // class org/jboss/metadata/parser/servlet/Element
     924: dup
     925: ldc           #184                // String MODULE_NAME
     927: bipush        58
     929: ldc           #185                // String module-name
     931: invokespecial #12                 // Method "<init>":(Ljava/lang/String;ILjava/lang/String;)V
     934: putstatic     #186                // Field MODULE_NAME:Lorg/jboss/metadata/parser/servlet/Element;
     937: new           #4                  // class org/jboss/metadata/parser/servlet/Element
     940: dup
     941: ldc           #187                // String MULTIPART_CONFIG
     943: bipush        59
     945: ldc           #188                // String multipart-config
     947: invokespecial #12                 // Method "<init>":(Ljava/lang/String;ILjava/lang/String;)V
     950: putstatic     #189                // Field MULTIPART_CONFIG:Lorg/jboss/metadata/parser/servlet/Element;
     953: new           #4                  // class org/jboss/metadata/parser/servlet/Element
     956: dup
     957: ldc           #190                // String NAME
     959: bipush        60
     961: ldc           #191                // String name
     963: invokespecial #12                 // Method "<init>":(Ljava/lang/String;ILjava/lang/String;)V
     966: putstatic     #192                // Field NAME:Lorg/jboss/metadata/parser/servlet/Element;
     969: new           #4                  // class org/jboss/metadata/parser/servlet/Element
     972: dup
     973: ldc           #193                // String ORDERING
     975: bipush        61
     977: ldc           #194                // String ordering
     979: invokespecial #12                 // Method "<init>":(Ljava/lang/String;ILjava/lang/String;)V
     982: putstatic     #195                // Field ORDERING:Lorg/jboss/metadata/parser/servlet/Element;
     985: new           #4                  // class org/jboss/metadata/parser/servlet/Element
     988: dup
     989: ldc           #196                // String OTHERS
     991: bipush        62
     993: ldc           #197                // String others
     995: invokespecial #12                 // Method "<init>":(Ljava/lang/String;ILjava/lang/String;)V
     998: putstatic     #198                // Field OTHERS:Lorg/jboss/metadata/parser/servlet/Element;
    1001: new           #4                  // class org/jboss/metadata/parser/servlet/Element
    1004: dup
    1005: ldc           #199                // String PAGE_ENCODING
    1007: bipush        63
    1009: ldc           #200                // String page-encoding
    1011: invokespecial #12                 // Method "<init>":(Ljava/lang/String;ILjava/lang/String;)V
    1014: putstatic     #201                // Field PAGE_ENCODING:Lorg/jboss/metadata/parser/servlet/Element;
    1017: new           #4                  // class org/jboss/metadata/parser/servlet/Element
    1020: dup
    1021: ldc           #202                // String PATH
    1023: bipush        64
    1025: ldc           #203                // String path
    1027: invokespecial #12                 // Method "<init>":(Ljava/lang/String;ILjava/lang/String;)V
    1030: putstatic     #204                // Field PATH:Lorg/jboss/metadata/parser/servlet/Element;
    1033: new           #4                  // class org/jboss/metadata/parser/servlet/Element
    1036: dup
    1037: ldc           #205                // String REALM_NAME
    1039: bipush        65
    1041: ldc           #206                // String realm-name
    1043: invokespecial #12                 // Method "<init>":(Ljava/lang/String;ILjava/lang/String;)V
    1046: putstatic     #207                // Field REALM_NAME:Lorg/jboss/metadata/parser/servlet/Element;
    1049: new           #4                  // class org/jboss/metadata/parser/servlet/Element
    1052: dup
    1053: ldc           #208                // String ROLE_NAME
    1055: bipush        66
    1057: ldc           #209                // String role-name
    1059: invokespecial #12                 // Method "<init>":(Ljava/lang/String;ILjava/lang/String;)V
    1062: putstatic     #210                // Field ROLE_NAME:Lorg/jboss/metadata/parser/servlet/Element;
    1065: new           #4                  // class org/jboss/metadata/parser/servlet/Element
    1068: dup
    1069: ldc           #211                // String RUN_AS
    1071: bipush        67
    1073: ldc           #212                // String run-as
    1075: invokespecial #12                 // Method "<init>":(Ljava/lang/String;ILjava/lang/String;)V
    1078: putstatic     #213                // Field RUN_AS:Lorg/jboss/metadata/parser/servlet/Element;
    1081: new           #4                  // class org/jboss/metadata/parser/servlet/Element
    1084: dup
    1085: ldc           #214                // String SCRIPTING_INVALID
    1087: bipush        68
    1089: ldc           #215                // String scripting-invalid
    1091: invokespecial #12                 // Method "<init>":(Ljava/lang/String;ILjava/lang/String;)V
    1094: putstatic     #216                // Field SCRIPTING_INVALID:Lorg/jboss/metadata/parser/servlet/Element;
    1097: new           #4                  // class org/jboss/metadata/parser/servlet/Element
    1100: dup
    1101: ldc           #217                // String SECURE
    1103: bipush        69
    1105: ldc           #218                // String secure
    1107: invokespecial #12                 // Method "<init>":(Ljava/lang/String;ILjava/lang/String;)V
    1110: putstatic     #219                // Field SECURE:Lorg/jboss/metadata/parser/servlet/Element;
    1113: new           #4                  // class org/jboss/metadata/parser/servlet/Element
    1116: dup
    1117: ldc           #220                // String SECURITY_CONSTRAINT
    1119: bipush        70
    1121: ldc           #221                // String security-constraint
    1123: invokespecial #12                 // Method "<init>":(Ljava/lang/String;ILjava/lang/String;)V
    1126: putstatic     #222                // Field SECURITY_CONSTRAINT:Lorg/jboss/metadata/parser/servlet/Element;
    1129: new           #4                  // class org/jboss/metadata/parser/servlet/Element
    1132: dup
    1133: ldc           #223                // String SECURITY_ROLE
    1135: bipush        71
    1137: ldc           #224                // String security-role
    1139: invokespecial #12                 // Method "<init>":(Ljava/lang/String;ILjava/lang/String;)V
    1142: putstatic     #225                // Field SECURITY_ROLE:Lorg/jboss/metadata/parser/servlet/Element;
    1145: new           #4                  // class org/jboss/metadata/parser/servlet/Element
    1148: dup
    1149: ldc           #226                // String SECURITY_ROLE_REF
    1151: bipush        72
    1153: ldc           #227                // String security-role-ref
    1155: invokespecial #12                 // Method "<init>":(Ljava/lang/String;ILjava/lang/String;)V
    1158: putstatic     #228                // Field SECURITY_ROLE_REF:Lorg/jboss/metadata/parser/servlet/Element;
    1161: new           #4                  // class org/jboss/metadata/parser/servlet/Element
    1164: dup
    1165: ldc           #229                // String SERVLET
    1167: bipush        73
    1169: ldc           #230                // String servlet
    1171: invokespecial #12                 // Method "<init>":(Ljava/lang/String;ILjava/lang/String;)V
    1174: putstatic     #231                // Field SERVLET:Lorg/jboss/metadata/parser/servlet/Element;
    1177: new           #4                  // class org/jboss/metadata/parser/servlet/Element
    1180: dup
    1181: ldc           #232                // String SERVLET_CLASS
    1183: bipush        74
    1185: ldc           #233                // String servlet-class
    1187: invokespecial #12                 // Method "<init>":(Ljava/lang/String;ILjava/lang/String;)V
    1190: putstatic     #234                // Field SERVLET_CLASS:Lorg/jboss/metadata/parser/servlet/Element;
    1193: new           #4                  // class org/jboss/metadata/parser/servlet/Element
    1196: dup
    1197: ldc           #235                // String SERVLET_MAPPING
    1199: bipush        75
    1201: ldc           #236                // String servlet-mapping
    1203: invokespecial #12                 // Method "<init>":(Ljava/lang/String;ILjava/lang/String;)V
    1206: putstatic     #237                // Field SERVLET_MAPPING:Lorg/jboss/metadata/parser/servlet/Element;
    1209: new           #4                  // class org/jboss/metadata/parser/servlet/Element
    1212: dup
    1213: ldc           #238                // String SERVLET_NAME
    1215: bipush        76
    1217: ldc           #239                // String servlet-name
    1219: invokespecial #12                 // Method "<init>":(Ljava/lang/String;ILjava/lang/String;)V
    1222: putstatic     #240                // Field SERVLET_NAME:Lorg/jboss/metadata/parser/servlet/Element;
    1225: new           #4                  // class org/jboss/metadata/parser/servlet/Element
    1228: dup
    1229: ldc           #241                // String SESSION_CONFIG
    1231: bipush        77
    1233: ldc           #242                // String session-config
    1235: invokespecial #12                 // Method "<init>":(Ljava/lang/String;ILjava/lang/String;)V
    1238: putstatic     #243                // Field SESSION_CONFIG:Lorg/jboss/metadata/parser/servlet/Element;
    1241: new           #4                  // class org/jboss/metadata/parser/servlet/Element
    1244: dup
    1245: ldc           #244                // String SESSION_TIMEOUT
    1247: bipush        78
    1249: ldc           #245                // String session-timeout
    1251: invokespecial #12                 // Method "<init>":(Ljava/lang/String;ILjava/lang/String;)V
    1254: putstatic     #246                // Field SESSION_TIMEOUT:Lorg/jboss/metadata/parser/servlet/Element;
    1257: new           #4                  // class org/jboss/metadata/parser/servlet/Element
    1260: dup
    1261: ldc           #247                // String TAGLIB
    1263: bipush        79
    1265: ldc           #248                // String taglib
    1267: invokespecial #12                 // Method "<init>":(Ljava/lang/String;ILjava/lang/String;)V
    1270: putstatic     #249                // Field TAGLIB:Lorg/jboss/metadata/parser/servlet/Element;
    1273: new           #4                  // class org/jboss/metadata/parser/servlet/Element
    1276: dup
    1277: ldc           #250                // String TAGLIB_LOCATION
    1279: bipush        80
    1281: ldc           #251                // String taglib-location
    1283: invokespecial #12                 // Method "<init>":(Ljava/lang/String;ILjava/lang/String;)V
    1286: putstatic     #252                // Field TAGLIB_LOCATION:Lorg/jboss/metadata/parser/servlet/Element;
    1289: new           #4                  // class org/jboss/metadata/parser/servlet/Element
    1292: dup
    1293: ldc           #253                // String TAGLIB_URI
    1295: bipush        81
    1297: ldc           #254                // String taglib-uri
    1299: invokespecial #12                 // Method "<init>":(Ljava/lang/String;ILjava/lang/String;)V
    1302: putstatic     #255                // Field TAGLIB_URI:Lorg/jboss/metadata/parser/servlet/Element;
    1305: new           #4                  // class org/jboss/metadata/parser/servlet/Element
    1308: dup
    1309: ldc_w         #256                // String TRACKING_MODE
    1312: bipush        82
    1314: ldc_w         #257                // String tracking-mode
    1317: invokespecial #12                 // Method "<init>":(Ljava/lang/String;ILjava/lang/String;)V
    1320: putstatic     #258                // Field TRACKING_MODE:Lorg/jboss/metadata/parser/servlet/Element;
    1323: new           #4                  // class org/jboss/metadata/parser/servlet/Element
    1326: dup
    1327: ldc_w         #259                // String TRANSPORT_GUARANTEE
    1330: bipush        83
    1332: ldc_w         #260                // String transport-guarantee
    1335: invokespecial #12                 // Method "<init>":(Ljava/lang/String;ILjava/lang/String;)V
    1338: putstatic     #261                // Field TRANSPORT_GUARANTEE:Lorg/jboss/metadata/parser/servlet/Element;
    1341: new           #4                  // class org/jboss/metadata/parser/servlet/Element
    1344: dup
    1345: ldc_w         #262                // String TRIM_DIRECTIVE_WHITESPACES
    1348: bipush        84
    1350: ldc_w         #263                // String trim-directive-whitespaces
    1353: invokespecial #12                 // Method "<init>":(Ljava/lang/String;ILjava/lang/String;)V
    1356: putstatic     #264                // Field TRIM_DIRECTIVE_WHITESPACES:Lorg/jboss/metadata/parser/servlet/Element;
    1359: new           #4                  // class org/jboss/metadata/parser/servlet/Element
    1362: dup
    1363: ldc_w         #265                // String URL_PATTERN
    1366: bipush        85
    1368: ldc_w         #266                // String url-pattern
    1371: invokespecial #12                 // Method "<init>":(Ljava/lang/String;ILjava/lang/String;)V
    1374: putstatic     #267                // Field URL_PATTERN:Lorg/jboss/metadata/parser/servlet/Element;
    1377: new           #4                  // class org/jboss/metadata/parser/servlet/Element
    1380: dup
    1381: ldc_w         #268                // String USER_DATA_CONSTRAINT
    1384: bipush        86
    1386: ldc_w         #269                // String user-data-constraint
    1389: invokespecial #12                 // Method "<init>":(Ljava/lang/String;ILjava/lang/String;)V
    1392: putstatic     #270                // Field USER_DATA_CONSTRAINT:Lorg/jboss/metadata/parser/servlet/Element;
    1395: new           #4                  // class org/jboss/metadata/parser/servlet/Element
    1398: dup
    1399: ldc_w         #271                // String WEB_RESOURCE_COLLECTION
    1402: bipush        87
    1404: ldc_w         #272                // String web-resource-collection
    1407: invokespecial #12                 // Method "<init>":(Ljava/lang/String;ILjava/lang/String;)V
    1410: putstatic     #273                // Field WEB_RESOURCE_COLLECTION:Lorg/jboss/metadata/parser/servlet/Element;
    1413: new           #4                  // class org/jboss/metadata/parser/servlet/Element
    1416: dup
    1417: ldc_w         #274                // String WEB_RESOURCE_NAME
    1420: bipush        88
    1422: ldc_w         #275                // String web-resource-name
    1425: invokespecial #12                 // Method "<init>":(Ljava/lang/String;ILjava/lang/String;)V
    1428: putstatic     #276                // Field WEB_RESOURCE_NAME:Lorg/jboss/metadata/parser/servlet/Element;
    1431: new           #4                  // class org/jboss/metadata/parser/servlet/Element
    1434: dup
    1435: ldc_w         #277                // String WELCOME_FILE
    1438: bipush        89
    1440: ldc_w         #278                // String welcome-file
    1443: invokespecial #12                 // Method "<init>":(Ljava/lang/String;ILjava/lang/String;)V
    1446: putstatic     #279                // Field WELCOME_FILE:Lorg/jboss/metadata/parser/servlet/Element;
    1449: new           #4                  // class org/jboss/metadata/parser/servlet/Element
    1452: dup
    1453: ldc_w         #280                // String WELCOME_FILE_LIST
    1456: bipush        90
    1458: ldc_w         #281                // String welcome-file-list
    1461: invokespecial #12                 // Method "<init>":(Ljava/lang/String;ILjava/lang/String;)V
    1464: putstatic     #282                // Field WELCOME_FILE_LIST:Lorg/jboss/metadata/parser/servlet/Element;
    1467: bipush        91
    1469: anewarray     #4                  // class org/jboss/metadata/parser/servlet/Element
    1472: dup
    1473: iconst_0
    1474: getstatic     #10                 // Field UNKNOWN:Lorg/jboss/metadata/parser/servlet/Element;
    1477: aastore
    1478: dup
    1479: iconst_1
    1480: getstatic     #15                 // Field ABSOLUTE_ORDERING:Lorg/jboss/metadata/parser/servlet/Element;
    1483: aastore
    1484: dup
    1485: iconst_2
    1486: getstatic     #18                 // Field AFTER:Lorg/jboss/metadata/parser/servlet/Element;
    1489: aastore
    1490: dup
    1491: iconst_3
    1492: getstatic     #21                 // Field ASYNC_SUPPORTED:Lorg/jboss/metadata/parser/servlet/Element;
    1495: aastore
    1496: dup
    1497: iconst_4
    1498: getstatic     #24                 // Field AUTH_CONSTRAINT:Lorg/jboss/metadata/parser/servlet/Element;
    1501: aastore
    1502: dup
    1503: iconst_5
    1504: getstatic     #27                 // Field AUTH_METHOD:Lorg/jboss/metadata/parser/servlet/Element;
    1507: aastore
    1508: dup
    1509: bipush        6
    1511: getstatic     #30                 // Field BEFORE:Lorg/jboss/metadata/parser/servlet/Element;
    1514: aastore
    1515: dup
    1516: bipush        7
    1518: getstatic     #33                 // Field BUFFER:Lorg/jboss/metadata/parser/servlet/Element;
    1521: aastore
    1522: dup
    1523: bipush        8
    1525: getstatic     #36                 // Field COMMENT:Lorg/jboss/metadata/parser/servlet/Element;
    1528: aastore
    1529: dup
    1530: bipush        9
    1532: getstatic     #39                 // Field CONTEXT_PARAM:Lorg/jboss/metadata/parser/servlet/Element;
    1535: aastore
    1536: dup
    1537: bipush        10
    1539: getstatic     #42                 // Field COOKIE_CONFIG:Lorg/jboss/metadata/parser/servlet/Element;
    1542: aastore
    1543: dup
    1544: bipush        11
    1546: getstatic     #45                 // Field DEFAULT_CONTENT_TYPE:Lorg/jboss/metadata/parser/servlet/Element;
    1549: aastore
    1550: dup
    1551: bipush        12
    1553: getstatic     #48                 // Field DEFERRED_SYNTAX_ALLOWED_AS_LITERAL:Lorg/jboss/metadata/parser/servlet/Element;
    1556: aastore
    1557: dup
    1558: bipush        13
    1560: getstatic     #51                 // Field DENY_UNCOVERED_HTTP_METHODS:Lorg/jboss/metadata/parser/servlet/Element;
    1563: aastore
    1564: dup
    1565: bipush        14
    1567: getstatic     #54                 // Field DISPATCHER:Lorg/jboss/metadata/parser/servlet/Element;
    1570: aastore
    1571: dup
    1572: bipush        15
    1574: getstatic     #57                 // Field DISPLAY_NAME:Lorg/jboss/metadata/parser/servlet/Element;
    1577: aastore
    1578: dup
    1579: bipush        16
    1581: getstatic     #60                 // Field DISTRIBUTABLE:Lorg/jboss/metadata/parser/servlet/Element;
    1584: aastore
    1585: dup
    1586: bipush        17
    1588: getstatic     #63                 // Field DOMAIN:Lorg/jboss/metadata/parser/servlet/Element;
    1591: aastore
    1592: dup
    1593: bipush        18
    1595: getstatic     #66                 // Field EL_IGNORED:Lorg/jboss/metadata/parser/servlet/Element;
    1598: aastore
    1599: dup
    1600: bipush        19
    1602: getstatic     #69                 // Field ENABLED:Lorg/jboss/metadata/parser/servlet/Element;
    1605: aastore
    1606: dup
    1607: bipush        20
    1609: getstatic     #72                 // Field ENCODING:Lorg/jboss/metadata/parser/servlet/Element;
    1612: aastore
    1613: dup
    1614: bipush        21
    1616: getstatic     #75                 // Field ERROR_CODE:Lorg/jboss/metadata/parser/servlet/Element;
    1619: aastore
    1620: dup
    1621: bipush        22
    1623: getstatic     #78                 // Field ERROR_ON_UNDECLARED_NAMESPACE:Lorg/jboss/metadata/parser/servlet/Element;
    1626: aastore
    1627: dup
    1628: bipush        23
    1630: getstatic     #81                 // Field ERROR_PAGE:Lorg/jboss/metadata/parser/servlet/Element;
    1633: aastore
    1634: dup
    1635: bipush        24
    1637: getstatic     #84                 // Field EXCEPTION_TYPE:Lorg/jboss/metadata/parser/servlet/Element;
    1640: aastore
    1641: dup
    1642: bipush        25
    1644: getstatic     #87                 // Field EXTENSION:Lorg/jboss/metadata/parser/servlet/Element;
    1647: aastore
    1648: dup
    1649: bipush        26
    1651: getstatic     #90                 // Field FILE_SIZE_THRESHOLD:Lorg/jboss/metadata/parser/servlet/Element;
    1654: aastore
    1655: dup
    1656: bipush        27
    1658: getstatic     #93                 // Field FILTER:Lorg/jboss/metadata/parser/servlet/Element;
    1661: aastore
    1662: dup
    1663: bipush        28
    1665: getstatic     #96                 // Field FILTER_CLASS:Lorg/jboss/metadata/parser/servlet/Element;
    1668: aastore
    1669: dup
    1670: bipush        29
    1672: getstatic     #99                 // Field FILTER_NAME:Lorg/jboss/metadata/parser/servlet/Element;
    1675: aastore
    1676: dup
    1677: bipush        30
    1679: getstatic     #102                // Field FILTER_MAPPING:Lorg/jboss/metadata/parser/servlet/Element;
    1682: aastore
    1683: dup
    1684: bipush        31
    1686: getstatic     #105                // Field FORM_ERROR_PAGE:Lorg/jboss/metadata/parser/servlet/Element;
    1689: aastore
    1690: dup
    1691: bipush        32
    1693: getstatic     #108                // Field FORM_LOGIN_CONFIG:Lorg/jboss/metadata/parser/servlet/Element;
    1696: aastore
    1697: dup
    1698: bipush        33
    1700: getstatic     #111                // Field FORM_LOGIN_PAGE:Lorg/jboss/metadata/parser/servlet/Element;
    1703: aastore
    1704: dup
    1705: bipush        34
    1707: getstatic     #114                // Field HTTP_METHOD:Lorg/jboss/metadata/parser/servlet/Element;
    1710: aastore
    1711: dup
    1712: bipush        35
    1714: getstatic     #117                // Field HTTP_METHOD_OMISSION:Lorg/jboss/metadata/parser/servlet/Element;
    1717: aastore
    1718: dup
    1719: bipush        36
    1721: getstatic     #120                // Field HTTP_ONLY:Lorg/jboss/metadata/parser/servlet/Element;
    1724: aastore
    1725: dup
    1726: bipush        37
    1728: getstatic     #123                // Field INCLUDE_CODA:Lorg/jboss/metadata/parser/servlet/Element;
    1731: aastore
    1732: dup
    1733: bipush        38
    1735: getstatic     #126                // Field INCLUDE_PRELUDE:Lorg/jboss/metadata/parser/servlet/Element;
    1738: aastore
    1739: dup
    1740: bipush        39
    1742: getstatic     #129                // Field INIT_PARAM:Lorg/jboss/metadata/parser/servlet/Element;
    1745: aastore
    1746: dup
    1747: bipush        40
    1749: getstatic     #132                // Field IS_XML:Lorg/jboss/metadata/parser/servlet/Element;
    1752: aastore
    1753: dup
    1754: bipush        41
    1756: getstatic     #135                // Field JSP_CONFIG:Lorg/jboss/metadata/parser/servlet/Element;
    1759: aastore
    1760: dup
    1761: bipush        42
    1763: getstatic     #138                // Field JSP_FILE:Lorg/jboss/metadata/parser/servlet/Element;
    1766: aastore
    1767: dup
    1768: bipush        43
    1770: getstatic     #141                // Field JSP_PROPERTY_GROUP:Lorg/jboss/metadata/parser/servlet/Element;
    1773: aastore
    1774: dup
    1775: bipush        44
    1777: getstatic     #144                // Field LISTENER:Lorg/jboss/metadata/parser/servlet/Element;
    1780: aastore
    1781: dup
    1782: bipush        45
    1784: getstatic     #147                // Field LISTENER_CLASS:Lorg/jboss/metadata/parser/servlet/Element;
    1787: aastore
    1788: dup
    1789: bipush        46
    1791: getstatic     #150                // Field LOAD_ON_STARTUP:Lorg/jboss/metadata/parser/servlet/Element;
    1794: aastore
    1795: dup
    1796: bipush        47
    1798: getstatic     #153                // Field LOCALE_ENCODING_MAPPING:Lorg/jboss/metadata/parser/servlet/Element;
    1801: aastore
    1802: dup
    1803: bipush        48
    1805: getstatic     #156                // Field LOCALE_ENCODING_MAPPING_LIST:Lorg/jboss/metadata/parser/servlet/Element;
    1808: aastore
    1809: dup
    1810: bipush        49
    1812: getstatic     #159                // Field LOCALE:Lorg/jboss/metadata/parser/servlet/Element;
    1815: aastore
    1816: dup
    1817: bipush        50
    1819: getstatic     #162                // Field LOCATION:Lorg/jboss/metadata/parser/servlet/Element;
    1822: aastore
    1823: dup
    1824: bipush        51
    1826: getstatic     #165                // Field LOGIN_CONFIG:Lorg/jboss/metadata/parser/servlet/Element;
    1829: aastore
    1830: dup
    1831: bipush        52
    1833: getstatic     #168                // Field MAX_AGE:Lorg/jboss/metadata/parser/servlet/Element;
    1836: aastore
    1837: dup
    1838: bipush        53
    1840: getstatic     #171                // Field MAX_FILE_SIZE:Lorg/jboss/metadata/parser/servlet/Element;
    1843: aastore
    1844: dup
    1845: bipush        54
    1847: getstatic     #174                // Field MAX_REQUEST_SIZE:Lorg/jboss/metadata/parser/servlet/Element;
    1850: aastore
    1851: dup
    1852: bipush        55
    1854: getstatic     #177                // Field MESSAGE_DESTINATION:Lorg/jboss/metadata/parser/servlet/Element;
    1857: aastore
    1858: dup
    1859: bipush        56
    1861: getstatic     #180                // Field MIME_MAPPING:Lorg/jboss/metadata/parser/servlet/Element;
    1864: aastore
    1865: dup
    1866: bipush        57
    1868: getstatic     #183                // Field MIME_TYPE:Lorg/jboss/metadata/parser/servlet/Element;
    1871: aastore
    1872: dup
    1873: bipush        58
    1875: getstatic     #186                // Field MODULE_NAME:Lorg/jboss/metadata/parser/servlet/Element;
    1878: aastore
    1879: dup
    1880: bipush        59
    1882: getstatic     #189                // Field MULTIPART_CONFIG:Lorg/jboss/metadata/parser/servlet/Element;
    1885: aastore
    1886: dup
    1887: bipush        60
    1889: getstatic     #192                // Field NAME:Lorg/jboss/metadata/parser/servlet/Element;
    1892: aastore
    1893: dup
    1894: bipush        61
    1896: getstatic     #195                // Field ORDERING:Lorg/jboss/metadata/parser/servlet/Element;
    1899: aastore
    1900: dup
    1901: bipush        62
    1903: getstatic     #198                // Field OTHERS:Lorg/jboss/metadata/parser/servlet/Element;
    1906: aastore
    1907: dup
    1908: bipush        63
    1910: getstatic     #201                // Field PAGE_ENCODING:Lorg/jboss/metadata/parser/servlet/Element;
    1913: aastore
    1914: dup
    1915: bipush        64
    1917: getstatic     #204                // Field PATH:Lorg/jboss/metadata/parser/servlet/Element;
    1920: aastore
    1921: dup
    1922: bipush        65
    1924: getstatic     #207                // Field REALM_NAME:Lorg/jboss/metadata/parser/servlet/Element;
    1927: aastore
    1928: dup
    1929: bipush        66
    1931: getstatic     #210                // Field ROLE_NAME:Lorg/jboss/metadata/parser/servlet/Element;
    1934: aastore
    1935: dup
    1936: bipush        67
    1938: getstatic     #213                // Field RUN_AS:Lorg/jboss/metadata/parser/servlet/Element;
    1941: aastore
    1942: dup
    1943: bipush        68
    1945: getstatic     #216                // Field SCRIPTING_INVALID:Lorg/jboss/metadata/parser/servlet/Element;
    1948: aastore
    1949: dup
    1950: bipush        69
    1952: getstatic     #219                // Field SECURE:Lorg/jboss/metadata/parser/servlet/Element;
    1955: aastore
    1956: dup
    1957: bipush        70
    1959: getstatic     #222                // Field SECURITY_CONSTRAINT:Lorg/jboss/metadata/parser/servlet/Element;
    1962: aastore
    1963: dup
    1964: bipush        71
    1966: getstatic     #225                // Field SECURITY_ROLE:Lorg/jboss/metadata/parser/servlet/Element;
    1969: aastore
    1970: dup
    1971: bipush        72
    1973: getstatic     #228                // Field SECURITY_ROLE_REF:Lorg/jboss/metadata/parser/servlet/Element;
    1976: aastore
    1977: dup
    1978: bipush        73
    1980: getstatic     #231                // Field SERVLET:Lorg/jboss/metadata/parser/servlet/Element;
    1983: aastore
    1984: dup
    1985: bipush        74
    1987: getstatic     #234                // Field SERVLET_CLASS:Lorg/jboss/metadata/parser/servlet/Element;
    1990: aastore
    1991: dup
    1992: bipush        75
    1994: getstatic     #237                // Field SERVLET_MAPPING:Lorg/jboss/metadata/parser/servlet/Element;
    1997: aastore
    1998: dup
    1999: bipush        76
    2001: getstatic     #240                // Field SERVLET_NAME:Lorg/jboss/metadata/parser/servlet/Element;
    2004: aastore
    2005: dup
    2006: bipush        77
    2008: getstatic     #243                // Field SESSION_CONFIG:Lorg/jboss/metadata/parser/servlet/Element;
    2011: aastore
    2012: dup
    2013: bipush        78
    2015: getstatic     #246                // Field SESSION_TIMEOUT:Lorg/jboss/metadata/parser/servlet/Element;
    2018: aastore
    2019: dup
    2020: bipush        79
    2022: getstatic     #249                // Field TAGLIB:Lorg/jboss/metadata/parser/servlet/Element;
    2025: aastore
    2026: dup
    2027: bipush        80
    2029: getstatic     #252                // Field TAGLIB_LOCATION:Lorg/jboss/metadata/parser/servlet/Element;
    2032: aastore
    2033: dup
    2034: bipush        81
    2036: getstatic     #255                // Field TAGLIB_URI:Lorg/jboss/metadata/parser/servlet/Element;
    2039: aastore
    2040: dup
    2041: bipush        82
    2043: getstatic     #258                // Field TRACKING_MODE:Lorg/jboss/metadata/parser/servlet/Element;
    2046: aastore
    2047: dup
    2048: bipush        83
    2050: getstatic     #261                // Field TRANSPORT_GUARANTEE:Lorg/jboss/metadata/parser/servlet/Element;
    2053: aastore
    2054: dup
    2055: bipush        84
    2057: getstatic     #264                // Field TRIM_DIRECTIVE_WHITESPACES:Lorg/jboss/metadata/parser/servlet/Element;
    2060: aastore
    2061: dup
    2062: bipush        85
    2064: getstatic     #267                // Field URL_PATTERN:Lorg/jboss/metadata/parser/servlet/Element;
    2067: aastore
    2068: dup
    2069: bipush        86
    2071: getstatic     #270                // Field USER_DATA_CONSTRAINT:Lorg/jboss/metadata/parser/servlet/Element;
    2074: aastore
    2075: dup
    2076: bipush        87
    2078: getstatic     #273                // Field WEB_RESOURCE_COLLECTION:Lorg/jboss/metadata/parser/servlet/Element;
    2081: aastore
    2082: dup
    2083: bipush        88
    2085: getstatic     #276                // Field WEB_RESOURCE_NAME:Lorg/jboss/metadata/parser/servlet/Element;
    2088: aastore
    2089: dup
    2090: bipush        89
    2092: getstatic     #279                // Field WELCOME_FILE:Lorg/jboss/metadata/parser/servlet/Element;
    2095: aastore
    2096: dup
    2097: bipush        90
    2099: getstatic     #282                // Field WELCOME_FILE_LIST:Lorg/jboss/metadata/parser/servlet/Element;
    2102: aastore
    2103: putstatic     #1                  // Field $VALUES:[Lorg/jboss/metadata/parser/servlet/Element;
    2106: new           #283                // class java/util/HashMap
    2109: dup
    2110: invokespecial #284                // Method java/util/HashMap."<init>":()V
    2113: astore_0
    2114: invokestatic  #285                // Method values:()[Lorg/jboss/metadata/parser/servlet/Element;
    2117: astore_1
    2118: aload_1
    2119: arraylength
    2120: istore_2
    2121: iconst_0
    2122: istore_3
    2123: iload_3
    2124: iload_2
    2125: if_icmpge     2162
    2128: aload_1
    2129: iload_3
    2130: aaload
    2131: astore        4
    2133: aload         4
    2135: invokevirtual #286                // Method getLocalName:()Ljava/lang/String;
    2138: astore        5
    2140: aload         5
    2142: ifnull        2156
    2145: aload_0
    2146: aload         5
    2148: aload         4
    2150: invokeinterface #287,  3          // InterfaceMethod java/util/Map.put:(Ljava/lang/Object;Ljava/lang/Object;)Ljava/lang/Object;
    2155: pop
    2156: iinc          3, 1
    2159: goto          2123
    2162: aload_0
    2163: putstatic     #8                  // Field MAP:Ljava/util/Map;
    2166: return
}
