Compiled from "Bits.java"
public class org.mobicents.media.server.impl.dsp.audio.g729.Bits {
  public org.mobicents.media.server.impl.dsp.audio.g729.Bits();
    Code:
       0: aload_0
       1: invokespecial #1                  // Method java/lang/Object."<init>":()V
       4: return

  public static void prm2bits_ld8k_b(int[], byte[]);
    Code:
       0: aload_1
       1: iconst_0
       2: aload_0
       3: iconst_0
       4: iaload
       5: sipush        255
       8: iand
       9: i2b
      10: bastore
      11: aload_1
      12: iconst_1
      13: aload_0
      14: iconst_1
      15: iaload
      16: sipush        1023
      19: iand
      20: iconst_2
      21: ishr
      22: i2b
      23: bastore
      24: aload_1
      25: iconst_2
      26: aload_0
      27: iconst_1
      28: iaload
      29: iconst_3
      30: iand
      31: bipush        6
      33: ishl
      34: aload_0
      35: iconst_2
      36: iaload
      37: iconst_2
      38: ishr
      39: bipush        63
      41: iand
      42: ior
      43: i2b
      44: bastore
      45: aload_1
      46: iconst_3
      47: aload_0
      48: iconst_2
      49: iaload
      50: iconst_3
      51: iand
      52: bipush        6
      54: ishl
      55: aload_0
      56: iconst_3
      57: iaload
      58: iconst_1
      59: iand
      60: iconst_5
      61: ishl
      62: ior
      63: aload_0
      64: iconst_4
      65: iaload
      66: sipush        8191
      69: iand
      70: bipush        8
      72: ishr
      73: ior
      74: i2b
      75: bastore
      76: aload_1
      77: iconst_4
      78: aload_0
      79: iconst_4
      80: iaload
      81: sipush        255
      84: iand
      85: i2b
      86: bastore
      87: aload_1
      88: iconst_5
      89: aload_0
      90: iconst_5
      91: iaload
      92: bipush        15
      94: iand
      95: iconst_4
      96: ishl
      97: aload_0
      98: bipush        6
     100: iaload
     101: bipush        127
     103: iand
     104: iconst_3
     105: ishr
     106: ior
     107: i2b
     108: bastore
     109: aload_1
     110: bipush        6
     112: aload_0
     113: bipush        6
     115: iaload
     116: bipush        7
     118: iand
     119: iconst_5
     120: ishl
     121: aload_0
     122: bipush        7
     124: iaload
     125: bipush        31
     127: iand
     128: ior
     129: i2b
     130: bastore
     131: aload_1
     132: bipush        7
     134: aload_0
     135: bipush        8
     137: iaload
     138: sipush        8191
     141: iand
     142: iconst_5
     143: ishr
     144: i2b
     145: bastore
     146: aload_1
     147: bipush        8
     149: aload_0
     150: bipush        8
     152: iaload
     153: bipush        31
     155: iand
     156: iconst_3
     157: ishl
     158: aload_0
     159: bipush        9
     161: iaload
     162: bipush        15
     164: iand
     165: iconst_1
     166: ishr
     167: ior
     168: i2b
     169: bastore
     170: aload_1
     171: bipush        9
     173: aload_0
     174: bipush        9
     176: iaload
     177: iconst_1
     178: iand
     179: bipush        7
     181: ishl
     182: aload_0
     183: bipush        10
     185: iaload
     186: bipush        127
     188: iand
     189: ior
     190: i2b
     191: bastore
     192: return

  public static void prm2bits_ld8k(int[], short[]);
    Code:
       0: iconst_0
       1: istore_2
       2: iconst_0
       3: istore_3
       4: aload_1
       5: iload_3
       6: iinc          3, 1
       9: sipush        27425
      12: sastore
      13: aload_1
      14: iload_3
      15: iinc          3, 1
      18: bipush        80
      20: sastore
      21: iconst_0
      22: istore        4
      24: iload         4
      26: bipush        11
      28: if_icmpge     65
      31: aload_0
      32: iload         4
      34: iaload
      35: getstatic     #2                  // Field org/mobicents/media/server/impl/dsp/audio/g729/TabLD8k.bitsno:[I
      38: iload         4
      40: iaload
      41: aload_1
      42: iload_3
      43: invokestatic  #3                  // Method int2bin:(II[SI)V
      46: iload_3
      47: getstatic     #2                  // Field org/mobicents/media/server/impl/dsp/audio/g729/TabLD8k.bitsno:[I
      50: iload         4
      52: iaload
      53: iadd
      54: istore_3
      55: iload         4
      57: iconst_1
      58: iadd
      59: i2s
      60: istore        4
      62: goto          24
      65: return

  public static byte[] toRealBits(short[]);
    Code:
       0: bipush        10
       2: newarray       byte
       4: astore_1
       5: iconst_0
       6: istore_2
       7: iload_2
       8: bipush        80
      10: if_icmpge     65
      13: aload_0
      14: iload_2
      15: iconst_2
      16: iadd
      17: saload
      18: sipush        129
      21: if_icmpne     59
      24: aload_1
      25: iload_2
      26: bipush        8
      28: idiv
      29: baload
      30: istore_3
      31: iconst_1
      32: bipush        7
      34: iload_2
      35: bipush        8
      37: irem
      38: isub
      39: ishl
      40: istore        4
      42: iload_3
      43: iload         4
      45: ior
      46: istore_3
      47: aload_1
      48: iload_2
      49: bipush        8
      51: idiv
      52: sipush        255
      55: iload_3
      56: iand
      57: i2b
      58: bastore
      59: iinc          2, 1
      62: goto          7
      65: aload_1
      66: areturn

  public static short[] fromRealBits(byte[]);
    Code:
       0: bipush        82
       2: newarray       short
       4: astore_1
       5: aload_1
       6: iconst_0
       7: sipush        27425
      10: sastore
      11: aload_1
      12: iconst_1
      13: bipush        80
      15: sastore
      16: iconst_0
      17: istore_2
      18: iload_2
      19: bipush        80
      21: if_icmpge     67
      24: aload_0
      25: iload_2
      26: bipush        8
      28: idiv
      29: baload
      30: iconst_1
      31: bipush        7
      33: iload_2
      34: bipush        8
      36: irem
      37: isub
      38: ishl
      39: iand
      40: ifeq          54
      43: aload_1
      44: iload_2
      45: iconst_2
      46: iadd
      47: sipush        129
      50: sastore
      51: goto          61
      54: aload_1
      55: iload_2
      56: iconst_2
      57: iadd
      58: bipush        127
      60: sastore
      61: iinc          2, 1
      64: goto          18
      67: aload_1
      68: areturn

  static void int2bin(int, int, short[], int);
    Code:
       0: iload_3
       1: iload_1
       2: iadd
       3: istore        4
       5: iconst_0
       6: istore        5
       8: iload         5
      10: iload_1
      11: if_icmpge     61
      14: iload_0
      15: iconst_1
      16: iand
      17: i2s
      18: istore        6
      20: iload         6
      22: ifne          37
      25: aload_2
      26: iinc          4, -1
      29: iload         4
      31: bipush        127
      33: sastore
      34: goto          47
      37: aload_2
      38: iinc          4, -1
      41: iload         4
      43: sipush        129
      46: sastore
      47: iload_0
      48: iconst_1
      49: ishr
      50: istore_0
      51: iload         5
      53: iconst_1
      54: iadd
      55: i2s
      56: istore        5
      58: goto          8
      61: return

  public static void bits2prm_ld8k(short[], int, int[], int);
    Code:
       0: iconst_0
       1: istore        4
       3: iload         4
       5: bipush        11
       7: if_icmpge     46
      10: aload_2
      11: iload         4
      13: iload_3
      14: iadd
      15: getstatic     #2                  // Field org/mobicents/media/server/impl/dsp/audio/g729/TabLD8k.bitsno:[I
      18: iload         4
      20: iaload
      21: aload_0
      22: iload_1
      23: invokestatic  #4                  // Method bin2int:(I[SI)S
      26: iastore
      27: iload_1
      28: getstatic     #2                  // Field org/mobicents/media/server/impl/dsp/audio/g729/TabLD8k.bitsno:[I
      31: iload         4
      33: iaload
      34: iadd
      35: istore_1
      36: iload         4
      38: iconst_1
      39: iadd
      40: i2s
      41: istore        4
      43: goto          3
      46: return

  static short bin2int(int, short[], int);
    Code:
       0: iconst_0
       1: istore_3
       2: iconst_0
       3: istore        4
       5: iload         4
       7: iload_0
       8: if_icmpge     47
      11: iload_3
      12: iconst_1
      13: ishl
      14: i2s
      15: istore_3
      16: aload_1
      17: iload_2
      18: iinc          2, 1
      21: saload
      22: istore        5
      24: iload         5
      26: sipush        129
      29: if_icmpne     37
      32: iload_3
      33: iconst_1
      34: iadd
      35: i2s
      36: istore_3
      37: iload         4
      39: iconst_1
      40: iadd
      41: i2s
      42: istore        4
      44: goto          5
      47: iload_3
      48: ireturn
}
