Compiled from "SecurityActions.java"
final class org.jboss.jca.core.connectionmanager.pool.strategy.SecurityActions$2 implements java.security.PrivilegedAction<java.lang.Boolean> {
  final javax.security.auth.Subject val$s1;

  final javax.security.auth.Subject val$s2;

  org.jboss.jca.core.connectionmanager.pool.strategy.SecurityActions$2(javax.security.auth.Subject, javax.security.auth.Subject);
    Code:
       0: aload_0
       1: aload_1
       2: putfield      #1                  // Field val$s1:Ljavax/security/auth/Subject;
       5: aload_0
       6: aload_2
       7: putfield      #2                  // Field val$s2:Ljavax/security/auth/Subject;
      10: aload_0
      11: invokespecial #3                  // Method java/lang/Object."<init>":()V
      14: return

  public java.lang.Boolean run();
    Code:
       0: aload_0
       1: getfield      #1                  // Field val$s1:Ljavax/security/auth/Subject;
       4: ifnull        21
       7: aload_0
       8: getfield      #1                  // Field val$s1:Ljavax/security/auth/Subject;
      11: aload_0
      12: getfield      #2                  // Field val$s2:Ljavax/security/auth/Subject;
      15: invokevirtual #4                  // Method javax/security/auth/Subject.equals:(Ljava/lang/Object;)Z
      18: goto          33
      21: aload_0
      22: getfield      #2                  // Field val$s2:Ljavax/security/auth/Subject;
      25: ifnonnull     32
      28: iconst_1
      29: goto          33
      32: iconst_0
      33: invokestatic  #5                  // Method java/lang/Boolean.valueOf:(Z)Ljava/lang/Boolean;
      36: areturn

  public java.lang.Object run();
    Code:
       0: aload_0
       1: invokevirtual #6                  // Method run:()Ljava/lang/Boolean;
       4: areturn
}
