Compiled from "RedeliveryPlugin.java"
public class org.apache.activemq.broker.util.RedeliveryPlugin extends org.apache.activemq.broker.BrokerPluginSupport {
  private static final org.slf4j.Logger LOG;

  public static final java.lang.String REDELIVERY_DELAY;

  org.apache.activemq.broker.region.policy.RedeliveryPolicyMap redeliveryPolicyMap;

  boolean sendToDlqIfMaxRetriesExceeded;

  private boolean fallbackToDeadLetter;

  public org.apache.activemq.broker.util.RedeliveryPlugin();
    Code:
       0: aload_0
       1: invokespecial #1                  // Method org/apache/activemq/broker/BrokerPluginSupport."<init>":()V
       4: aload_0
       5: new           #2                  // class org/apache/activemq/broker/region/policy/RedeliveryPolicyMap
       8: dup
       9: invokespecial #3                  // Method org/apache/activemq/broker/region/policy/RedeliveryPolicyMap."<init>":()V
      12: putfield      #4                  // Field redeliveryPolicyMap:Lorg/apache/activemq/broker/region/policy/RedeliveryPolicyMap;
      15: aload_0
      16: iconst_1
      17: putfield      #5                  // Field sendToDlqIfMaxRetriesExceeded:Z
      20: aload_0
      21: iconst_1
      22: putfield      #6                  // Field fallbackToDeadLetter:Z
      25: return

  public org.apache.activemq.broker.Broker installPlugin(org.apache.activemq.broker.Broker) throws java.lang.Exception;
    Code:
       0: aload_1
       1: invokeinterface #7,  1            // InterfaceMethod org/apache/activemq/broker/Broker.getBrokerService:()Lorg/apache/activemq/broker/BrokerService;
       6: invokevirtual #8                  // Method org/apache/activemq/broker/BrokerService.isSchedulerSupport:()Z
       9: ifne          22
      12: new           #9                  // class java/lang/IllegalStateException
      15: dup
      16: ldc           #10                 // String RedeliveryPlugin requires schedulerSupport=true on the broker
      18: invokespecial #11                 // Method java/lang/IllegalStateException."<init>":(Ljava/lang/String;)V
      21: athrow
      22: aload_0
      23: ldc2_w        #12                 // long 1000l
      26: invokespecial #14                 // Method validatePolicyDelay:(J)V
      29: aload_0
      30: aload_1
      31: invokespecial #15                 // Method org/apache/activemq/broker/BrokerPluginSupport.installPlugin:(Lorg/apache/activemq/broker/Broker;)Lorg/apache/activemq/broker/Broker;
      34: areturn

  private void validatePolicyDelay(long);
    Code:
       0: new           #16                 // class org/apache/activemq/filter/AnyDestination
       3: dup
       4: iconst_2
       5: anewarray     #17                 // class org/apache/activemq/command/ActiveMQDestination
       8: dup
       9: iconst_0
      10: new           #18                 // class org/apache/activemq/command/ActiveMQQueue
      13: dup
      14: ldc           #19                 // String >
      16: invokespecial #20                 // Method org/apache/activemq/command/ActiveMQQueue."<init>":(Ljava/lang/String;)V
      19: aastore
      20: dup
      21: iconst_1
      22: new           #21                 // class org/apache/activemq/command/ActiveMQTopic
      25: dup
      26: ldc           #19                 // String >
      28: invokespecial #22                 // Method org/apache/activemq/command/ActiveMQTopic."<init>":(Ljava/lang/String;)V
      31: aastore
      32: invokespecial #23                 // Method org/apache/activemq/filter/AnyDestination."<init>":([Lorg/apache/activemq/command/ActiveMQDestination;)V
      35: astore_3
      36: aload_0
      37: getfield      #4                  // Field redeliveryPolicyMap:Lorg/apache/activemq/broker/region/policy/RedeliveryPolicyMap;
      40: aload_3
      41: invokevirtual #24                 // Method org/apache/activemq/broker/region/policy/RedeliveryPolicyMap.get:(Lorg/apache/activemq/command/ActiveMQDestination;)Ljava/util/Set;
      44: invokeinterface #25,  1           // InterfaceMethod java/util/Set.iterator:()Ljava/util/Iterator;
      49: astore        4
      51: aload         4
      53: invokeinterface #26,  1           // InterfaceMethod java/util/Iterator.hasNext:()Z
      58: ifeq          87
      61: aload         4
      63: invokeinterface #27,  1           // InterfaceMethod java/util/Iterator.next:()Ljava/lang/Object;
      68: astore        5
      70: aload         5
      72: checkcast     #28                 // class org/apache/activemq/RedeliveryPolicy
      75: astore        6
      77: aload_0
      78: lload_1
      79: aload         6
      81: invokespecial #29                 // Method validateLimit:(JLorg/apache/activemq/RedeliveryPolicy;)V
      84: goto          51
      87: aload_0
      88: getfield      #4                  // Field redeliveryPolicyMap:Lorg/apache/activemq/broker/region/policy/RedeliveryPolicyMap;
      91: invokevirtual #30                 // Method org/apache/activemq/broker/region/policy/RedeliveryPolicyMap.getDefaultEntry:()Lorg/apache/activemq/RedeliveryPolicy;
      94: astore        4
      96: aload         4
      98: ifnull        108
     101: aload_0
     102: lload_1
     103: aload         4
     105: invokespecial #29                 // Method validateLimit:(JLorg/apache/activemq/RedeliveryPolicy;)V
     108: return

  private void validateLimit(long, org.apache.activemq.RedeliveryPolicy);
    Code:
       0: aload_3
       1: invokevirtual #31                 // Method org/apache/activemq/RedeliveryPolicy.getInitialRedeliveryDelay:()J
       4: lload_1
       5: lcmp
       6: ifge          45
       9: new           #9                  // class java/lang/IllegalStateException
      12: dup
      13: new           #32                 // class java/lang/StringBuilder
      16: dup
      17: invokespecial #33                 // Method java/lang/StringBuilder."<init>":()V
      20: ldc           #34                 // String RedeliveryPolicy initialRedeliveryDelay must exceed:
      22: invokevirtual #35                 // Method java/lang/StringBuilder.append:(Ljava/lang/String;)Ljava/lang/StringBuilder;
      25: lload_1
      26: invokevirtual #36                 // Method java/lang/StringBuilder.append:(J)Ljava/lang/StringBuilder;
      29: ldc           #37                 // String .
      31: invokevirtual #35                 // Method java/lang/StringBuilder.append:(Ljava/lang/String;)Ljava/lang/StringBuilder;
      34: aload_3
      35: invokevirtual #38                 // Method java/lang/StringBuilder.append:(Ljava/lang/Object;)Ljava/lang/StringBuilder;
      38: invokevirtual #39                 // Method java/lang/StringBuilder.toString:()Ljava/lang/String;
      41: invokespecial #11                 // Method java/lang/IllegalStateException."<init>":(Ljava/lang/String;)V
      44: athrow
      45: aload_3
      46: invokevirtual #40                 // Method org/apache/activemq/RedeliveryPolicy.getRedeliveryDelay:()J
      49: lload_1
      50: lcmp
      51: ifge          90
      54: new           #9                  // class java/lang/IllegalStateException
      57: dup
      58: new           #32                 // class java/lang/StringBuilder
      61: dup
      62: invokespecial #33                 // Method java/lang/StringBuilder."<init>":()V
      65: ldc           #41                 // String RedeliveryPolicy redeliveryDelay must exceed:
      67: invokevirtual #35                 // Method java/lang/StringBuilder.append:(Ljava/lang/String;)Ljava/lang/StringBuilder;
      70: lload_1
      71: invokevirtual #36                 // Method java/lang/StringBuilder.append:(J)Ljava/lang/StringBuilder;
      74: ldc           #37                 // String .
      76: invokevirtual #35                 // Method java/lang/StringBuilder.append:(Ljava/lang/String;)Ljava/lang/StringBuilder;
      79: aload_3
      80: invokevirtual #38                 // Method java/lang/StringBuilder.append:(Ljava/lang/Object;)Ljava/lang/StringBuilder;
      83: invokevirtual #39                 // Method java/lang/StringBuilder.toString:()Ljava/lang/String;
      86: invokespecial #11                 // Method java/lang/IllegalStateException."<init>":(Ljava/lang/String;)V
      89: athrow
      90: return

  public org.apache.activemq.broker.region.policy.RedeliveryPolicyMap getRedeliveryPolicyMap();
    Code:
       0: aload_0
       1: getfield      #4                  // Field redeliveryPolicyMap:Lorg/apache/activemq/broker/region/policy/RedeliveryPolicyMap;
       4: areturn

  public void setRedeliveryPolicyMap(org.apache.activemq.broker.region.policy.RedeliveryPolicyMap);
    Code:
       0: aload_0
       1: aload_1
       2: putfield      #4                  // Field redeliveryPolicyMap:Lorg/apache/activemq/broker/region/policy/RedeliveryPolicyMap;
       5: return

  public boolean isSendToDlqIfMaxRetriesExceeded();
    Code:
       0: aload_0
       1: getfield      #5                  // Field sendToDlqIfMaxRetriesExceeded:Z
       4: ireturn

  public void setSendToDlqIfMaxRetriesExceeded(boolean);
    Code:
       0: aload_0
       1: iload_1
       2: putfield      #5                  // Field sendToDlqIfMaxRetriesExceeded:Z
       5: return

  public boolean isFallbackToDeadLetter();
    Code:
       0: aload_0
       1: getfield      #6                  // Field fallbackToDeadLetter:Z
       4: ireturn

  public void setFallbackToDeadLetter(boolean);
    Code:
       0: aload_0
       1: iload_1
       2: putfield      #6                  // Field fallbackToDeadLetter:Z
       5: return

  public boolean sendToDeadLetterQueue(org.apache.activemq.broker.ConnectionContext, org.apache.activemq.broker.region.MessageReference, org.apache.activemq.broker.region.Subscription, java.lang.Throwable);
    Code:
       0: aload_2
       1: invokeinterface #42,  1           // InterfaceMethod org/apache/activemq/broker/region/MessageReference.isExpired:()Z
       6: ifeq          19
       9: aload_0
      10: aload_1
      11: aload_2
      12: aload_3
      13: aload         4
      15: invokespecial #43                 // Method org/apache/activemq/broker/BrokerPluginSupport.sendToDeadLetterQueue:(Lorg/apache/activemq/broker/ConnectionContext;Lorg/apache/activemq/broker/region/MessageReference;Lorg/apache/activemq/broker/region/Subscription;Ljava/lang/Throwable;)Z
      18: ireturn
      19: aload_2
      20: invokeinterface #44,  1           // InterfaceMethod org/apache/activemq/broker/region/MessageReference.getRegionDestination:()Lorg/apache/activemq/command/Message$MessageDestination;
      25: checkcast     #45                 // class org/apache/activemq/broker/region/Destination
      28: astore        5
      30: aload_0
      31: getfield      #4                  // Field redeliveryPolicyMap:Lorg/apache/activemq/broker/region/policy/RedeliveryPolicyMap;
      34: aload         5
      36: invokeinterface #46,  1           // InterfaceMethod org/apache/activemq/broker/region/Destination.getActiveMQDestination:()Lorg/apache/activemq/command/ActiveMQDestination;
      41: invokevirtual #47                 // Method org/apache/activemq/broker/region/policy/RedeliveryPolicyMap.getEntryFor:(Lorg/apache/activemq/command/ActiveMQDestination;)Lorg/apache/activemq/RedeliveryPolicy;
      44: astore        6
      46: aload         6
      48: ifnull        162
      51: aload         6
      53: invokevirtual #48                 // Method org/apache/activemq/RedeliveryPolicy.getMaximumRedeliveries:()I
      56: istore        7
      58: aload_2
      59: invokeinterface #49,  1           // InterfaceMethod org/apache/activemq/broker/region/MessageReference.getRedeliveryCounter:()I
      64: istore        8
      66: iconst_m1
      67: iload         7
      69: if_icmpeq     79
      72: iload         8
      74: iload         7
      76: if_icmpge     121
      79: iload         8
      81: ifne          92
      84: aload         6
      86: invokevirtual #31                 // Method org/apache/activemq/RedeliveryPolicy.getInitialRedeliveryDelay:()J
      89: goto          103
      92: aload         6
      94: aload_0
      95: aload_2
      96: invokespecial #50                 // Method getExistingDelay:(Lorg/apache/activemq/broker/region/MessageReference;)I
      99: i2l
     100: invokevirtual #51                 // Method org/apache/activemq/RedeliveryPolicy.getNextRedeliveryDelay:(J)J
     103: lstore        9
     105: aload_0
     106: aload_1
     107: aload_2
     108: lload         9
     110: iinc          8, 1
     113: iload         8
     115: invokespecial #52                 // Method scheduleRedelivery:(Lorg/apache/activemq/broker/ConnectionContext;Lorg/apache/activemq/broker/region/MessageReference;JI)V
     118: goto          159
     121: aload_0
     122: invokevirtual #53                 // Method isSendToDlqIfMaxRetriesExceeded:()Z
     125: ifeq          138
     128: aload_0
     129: aload_1
     130: aload_2
     131: aload_3
     132: aload         4
     134: invokespecial #43                 // Method org/apache/activemq/broker/BrokerPluginSupport.sendToDeadLetterQueue:(Lorg/apache/activemq/broker/ConnectionContext;Lorg/apache/activemq/broker/region/MessageReference;Lorg/apache/activemq/broker/region/Subscription;Ljava/lang/Throwable;)Z
     137: ireturn
     138: getstatic     #54                 // Field LOG:Lorg/slf4j/Logger;
     141: ldc           #55                 // String Discarding message that exceeds max redelivery count({}), {}
     143: iload         7
     145: invokestatic  #56                 // Method java/lang/Integer.valueOf:(I)Ljava/lang/Integer;
     148: aload_2
     149: invokeinterface #57,  1           // InterfaceMethod org/apache/activemq/broker/region/MessageReference.getMessageId:()Lorg/apache/activemq/command/MessageId;
     154: invokeinterface #58,  4           // InterfaceMethod org/slf4j/Logger.debug:(Ljava/lang/String;Ljava/lang/Object;Ljava/lang/Object;)V
     159: goto          202
     162: aload_0
     163: invokevirtual #59                 // Method isFallbackToDeadLetter:()Z
     166: ifeq          179
     169: aload_0
     170: aload_1
     171: aload_2
     172: aload_3
     173: aload         4
     175: invokespecial #43                 // Method org/apache/activemq/broker/BrokerPluginSupport.sendToDeadLetterQueue:(Lorg/apache/activemq/broker/ConnectionContext;Lorg/apache/activemq/broker/region/MessageReference;Lorg/apache/activemq/broker/region/Subscription;Ljava/lang/Throwable;)Z
     178: ireturn
     179: getstatic     #54                 // Field LOG:Lorg/slf4j/Logger;
     182: ldc           #60                 // String Ignoring dlq request for: {}, RedeliveryPolicy not found (and no fallback) for: {}
     184: aload_2
     185: invokeinterface #57,  1           // InterfaceMethod org/apache/activemq/broker/region/MessageReference.getMessageId:()Lorg/apache/activemq/command/MessageId;
     190: aload         5
     192: invokeinterface #46,  1           // InterfaceMethod org/apache/activemq/broker/region/Destination.getActiveMQDestination:()Lorg/apache/activemq/command/ActiveMQDestination;
     197: invokeinterface #58,  4           // InterfaceMethod org/slf4j/Logger.debug:(Ljava/lang/String;Ljava/lang/Object;Ljava/lang/Object;)V
     202: iconst_0
     203: ireturn
     204: astore        5
     206: new           #62                 // class java/lang/RuntimeException
     209: dup
     210: new           #32                 // class java/lang/StringBuilder
     213: dup
     214: invokespecial #33                 // Method java/lang/StringBuilder."<init>":()V
     217: ldc           #63                 // String Failed to schedule redelivery for:
     219: invokevirtual #35                 // Method java/lang/StringBuilder.append:(Ljava/lang/String;)Ljava/lang/StringBuilder;
     222: aload_2
     223: invokeinterface #57,  1           // InterfaceMethod org/apache/activemq/broker/region/MessageReference.getMessageId:()Lorg/apache/activemq/command/MessageId;
     228: invokevirtual #38                 // Method java/lang/StringBuilder.append:(Ljava/lang/Object;)Ljava/lang/StringBuilder;
     231: invokevirtual #39                 // Method java/lang/StringBuilder.toString:()Ljava/lang/String;
     234: aload         5
     236: invokespecial #64                 // Method java/lang/RuntimeException."<init>":(Ljava/lang/String;Ljava/lang/Throwable;)V
     239: astore        6
     241: getstatic     #54                 // Field LOG:Lorg/slf4j/Logger;
     244: aload         6
     246: invokevirtual #65                 // Method java/lang/RuntimeException.toString:()Ljava/lang/String;
     249: aload         5
     251: invokeinterface #66,  3           // InterfaceMethod org/slf4j/Logger.error:(Ljava/lang/String;Ljava/lang/Throwable;)V
     256: aload         6
     258: athrow
    Exception table:
       from    to  target type
          19   137   204   Class java/lang/Exception
         138   178   204   Class java/lang/Exception
         179   203   204   Class java/lang/Exception

  private void scheduleRedelivery(org.apache.activemq.broker.ConnectionContext, org.apache.activemq.broker.region.MessageReference, long, int) throws java.lang.Exception;
    Code:
       0: getstatic     #54                 // Field LOG:Lorg/slf4j/Logger;
       3: invokeinterface #67,  1           // InterfaceMethod org/slf4j/Logger.isTraceEnabled:()Z
       8: ifeq          70
      11: aload_2
      12: invokeinterface #44,  1           // InterfaceMethod org/apache/activemq/broker/region/MessageReference.getRegionDestination:()Lorg/apache/activemq/command/Message$MessageDestination;
      17: checkcast     #45                 // class org/apache/activemq/broker/region/Destination
      20: astore        6
      22: getstatic     #54                 // Field LOG:Lorg/slf4j/Logger;
      25: ldc           #68                 // String redelivery #{} of: {} with delay: {}, dest: {}
      27: iconst_4
      28: anewarray     #69                 // class java/lang/Object
      31: dup
      32: iconst_0
      33: iload         5
      35: invokestatic  #56                 // Method java/lang/Integer.valueOf:(I)Ljava/lang/Integer;
      38: aastore
      39: dup
      40: iconst_1
      41: aload_2
      42: invokeinterface #57,  1           // InterfaceMethod org/apache/activemq/broker/region/MessageReference.getMessageId:()Lorg/apache/activemq/command/MessageId;
      47: aastore
      48: dup
      49: iconst_2
      50: lload_3
      51: invokestatic  #70                 // Method java/lang/Long.valueOf:(J)Ljava/lang/Long;
      54: aastore
      55: dup
      56: iconst_3
      57: aload         6
      59: invokeinterface #46,  1           // InterfaceMethod org/apache/activemq/broker/region/Destination.getActiveMQDestination:()Lorg/apache/activemq/command/ActiveMQDestination;
      64: aastore
      65: invokeinterface #71,  3           // InterfaceMethod org/slf4j/Logger.trace:(Ljava/lang/String;[Ljava/lang/Object;)V
      70: aload_2
      71: invokeinterface #72,  1           // InterfaceMethod org/apache/activemq/broker/region/MessageReference.getMessage:()Lorg/apache/activemq/command/Message;
      76: astore        6
      78: aload         6
      80: invokevirtual #73                 // Method org/apache/activemq/command/Message.copy:()Lorg/apache/activemq/command/Message;
      83: astore        7
      85: aload         7
      87: aconst_null
      88: invokevirtual #74                 // Method org/apache/activemq/command/Message.setTransactionId:(Lorg/apache/activemq/command/TransactionId;)V
      91: aload         7
      93: aconst_null
      94: invokevirtual #75                 // Method org/apache/activemq/command/Message.setMemoryUsage:(Lorg/apache/activemq/usage/MemoryUsage;)V
      97: aload         7
      99: ldc           #76                 // String scheduledJobId
     101: invokevirtual #77                 // Method org/apache/activemq/command/Message.removeProperty:(Ljava/lang/String;)V
     104: aload         7
     106: ldc           #78                 // String redeliveryDelay
     108: lload_3
     109: invokestatic  #70                 // Method java/lang/Long.valueOf:(J)Ljava/lang/Long;
     112: invokevirtual #79                 // Method org/apache/activemq/command/Message.setProperty:(Ljava/lang/String;Ljava/lang/Object;)V
     115: aload         7
     117: ldc           #80                 // String AMQ_SCHEDULED_DELAY
     119: lload_3
     120: invokestatic  #70                 // Method java/lang/Long.valueOf:(J)Ljava/lang/Long;
     123: invokevirtual #79                 // Method org/apache/activemq/command/Message.setProperty:(Ljava/lang/String;Ljava/lang/Object;)V
     126: aload         7
     128: iload         5
     130: invokevirtual #81                 // Method org/apache/activemq/command/Message.setRedeliveryCounter:(I)V
     133: aload_1
     134: invokevirtual #82                 // Method org/apache/activemq/broker/ConnectionContext.isProducerFlowControl:()Z
     137: istore        8
     139: aload_1
     140: iconst_0
     141: invokevirtual #83                 // Method org/apache/activemq/broker/ConnectionContext.setProducerFlowControl:(Z)V
     144: new           #84                 // class org/apache/activemq/command/ProducerInfo
     147: dup
     148: invokespecial #85                 // Method org/apache/activemq/command/ProducerInfo."<init>":()V
     151: astore        9
     153: new           #86                 // class org/apache/activemq/state/ProducerState
     156: dup
     157: aload         9
     159: invokespecial #87                 // Method org/apache/activemq/state/ProducerState."<init>":(Lorg/apache/activemq/command/ProducerInfo;)V
     162: astore        10
     164: new           #88                 // class org/apache/activemq/broker/ProducerBrokerExchange
     167: dup
     168: invokespecial #89                 // Method org/apache/activemq/broker/ProducerBrokerExchange."<init>":()V
     171: astore        11
     173: aload         11
     175: aload         10
     177: invokevirtual #90                 // Method org/apache/activemq/broker/ProducerBrokerExchange.setProducerState:(Lorg/apache/activemq/state/ProducerState;)V
     180: aload         11
     182: iconst_1
     183: invokevirtual #91                 // Method org/apache/activemq/broker/ProducerBrokerExchange.setMutable:(Z)V
     186: aload         11
     188: aload_1
     189: invokevirtual #92                 // Method org/apache/activemq/broker/ProducerBrokerExchange.setConnectionContext:(Lorg/apache/activemq/broker/ConnectionContext;)V
     192: aload_1
     193: invokevirtual #93                 // Method org/apache/activemq/broker/ConnectionContext.getBroker:()Lorg/apache/activemq/broker/Broker;
     196: aload         11
     198: aload         7
     200: invokeinterface #94,  3           // InterfaceMethod org/apache/activemq/broker/Broker.send:(Lorg/apache/activemq/broker/ProducerBrokerExchange;Lorg/apache/activemq/command/Message;)V
     205: aload_1
     206: iload         8
     208: invokevirtual #83                 // Method org/apache/activemq/broker/ConnectionContext.setProducerFlowControl:(Z)V
     211: goto          225
     214: astore        12
     216: aload_1
     217: iload         8
     219: invokevirtual #83                 // Method org/apache/activemq/broker/ConnectionContext.setProducerFlowControl:(Z)V
     222: aload         12
     224: athrow
     225: return
    Exception table:
       from    to  target type
         139   205   214   any
         214   216   214   any

  private int getExistingDelay(org.apache.activemq.broker.region.MessageReference) throws java.io.IOException;
    Code:
       0: aload_1
       1: invokeinterface #72,  1           // InterfaceMethod org/apache/activemq/broker/region/MessageReference.getMessage:()Lorg/apache/activemq/command/Message;
       6: ldc           #78                 // String redeliveryDelay
       8: invokevirtual #95                 // Method org/apache/activemq/command/Message.getProperty:(Ljava/lang/String;)Ljava/lang/Object;
      11: astore_2
      12: aload_2
      13: instanceof    #96                 // class java/lang/Long
      16: ifeq          27
      19: aload_2
      20: checkcast     #96                 // class java/lang/Long
      23: invokevirtual #97                 // Method java/lang/Long.intValue:()I
      26: ireturn
      27: iconst_0
      28: ireturn

  static {};
    Code:
       0: ldc_w         #98                 // class org/apache/activemq/broker/util/RedeliveryPlugin
       3: invokestatic  #99                 // Method org/slf4j/LoggerFactory.getLogger:(Ljava/lang/Class;)Lorg/slf4j/Logger;
       6: putstatic     #54                 // Field LOG:Lorg/slf4j/Logger;
       9: return
}
