Compiled from "SubjectAccessReviewOperationImpl.java"
class io.fabric8.openshift.client.dsl.internal.SubjectAccessReviewOperationImpl$CreateableLocalSubjectAccessReviewImpl extends io.fabric8.openshift.client.dsl.CreateableLocalSubjectAccessReview {
  private final okhttp3.OkHttpClient client;

  private final io.fabric8.openshift.api.model.LocalSubjectAccessReviewBuilder builder;

  final io.fabric8.openshift.client.dsl.internal.SubjectAccessReviewOperationImpl this$0;

  private io.fabric8.openshift.client.dsl.internal.SubjectAccessReviewOperationImpl$CreateableLocalSubjectAccessReviewImpl(io.fabric8.openshift.client.dsl.internal.SubjectAccessReviewOperationImpl, okhttp3.OkHttpClient);
    Code:
       0: aload_0
       1: aload_1
       2: putfield      #2                  // Field this$0:Lio/fabric8/openshift/client/dsl/internal/SubjectAccessReviewOperationImpl;
       5: aload_0
       6: invokespecial #3                  // Method io/fabric8/openshift/client/dsl/CreateableLocalSubjectAccessReview."<init>":()V
       9: aload_0
      10: aload_2
      11: putfield      #4                  // Field client:Lokhttp3/OkHttpClient;
      14: aload_0
      15: new           #5                  // class io/fabric8/openshift/api/model/LocalSubjectAccessReviewBuilder
      18: dup
      19: aload_0
      20: invokespecial #6                  // Method io/fabric8/openshift/api/model/LocalSubjectAccessReviewBuilder."<init>":(Lio/fabric8/openshift/api/model/LocalSubjectAccessReviewFluent;)V
      23: putfield      #7                  // Field builder:Lio/fabric8/openshift/api/model/LocalSubjectAccessReviewBuilder;
      26: return

  private io.fabric8.openshift.client.dsl.internal.SubjectAccessReviewOperationImpl$CreateableLocalSubjectAccessReviewImpl(io.fabric8.openshift.client.dsl.internal.SubjectAccessReviewOperationImpl, okhttp3.OkHttpClient, io.fabric8.openshift.api.model.LocalSubjectAccessReviewBuilder);
    Code:
       0: aload_0
       1: aload_1
       2: putfield      #2                  // Field this$0:Lio/fabric8/openshift/client/dsl/internal/SubjectAccessReviewOperationImpl;
       5: aload_0
       6: invokespecial #3                  // Method io/fabric8/openshift/client/dsl/CreateableLocalSubjectAccessReview."<init>":()V
       9: aload_0
      10: aload_2
      11: putfield      #4                  // Field client:Lokhttp3/OkHttpClient;
      14: aload_0
      15: aload_3
      16: putfield      #7                  // Field builder:Lio/fabric8/openshift/api/model/LocalSubjectAccessReviewBuilder;
      19: return

  public io.fabric8.openshift.api.model.SubjectAccessReviewResponse create(io.fabric8.openshift.api.model.LocalSubjectAccessReview...);
    Code:
       0: aload_1
       1: arraylength
       2: iconst_1
       3: if_icmple     16
       6: new           #8                  // class java/lang/IllegalArgumentException
       9: dup
      10: ldc           #9                  // String Too many items to create.
      12: invokespecial #10                 // Method java/lang/IllegalArgumentException."<init>":(Ljava/lang/String;)V
      15: athrow
      16: aload_1
      17: arraylength
      18: iconst_1
      19: if_icmpne     38
      22: aload_0
      23: getfield      #2                  // Field this$0:Lio/fabric8/openshift/client/dsl/internal/SubjectAccessReviewOperationImpl;
      26: aload_1
      27: iconst_0
      28: aaload
      29: ldc           #11                 // class io/fabric8/openshift/api/model/SubjectAccessReviewResponse
      31: invokestatic  #12                 // Method io/fabric8/openshift/client/dsl/internal/SubjectAccessReviewOperationImpl.access$200:(Lio/fabric8/openshift/client/dsl/internal/SubjectAccessReviewOperationImpl;Ljava/lang/Object;Ljava/lang/Class;)Ljava/lang/Object;
      34: checkcast     #11                 // class io/fabric8/openshift/api/model/SubjectAccessReviewResponse
      37: areturn
      38: new           #8                  // class java/lang/IllegalArgumentException
      41: dup
      42: ldc           #13                 // String Nothing to create.
      44: invokespecial #10                 // Method java/lang/IllegalArgumentException."<init>":(Ljava/lang/String;)V
      47: athrow
      48: astore_2
      49: aload_2
      50: invokestatic  #17                 // Method io/fabric8/kubernetes/client/KubernetesClientException.launderThrowable:(Ljava/lang/Throwable;)Ljava/lang/RuntimeException;
      53: athrow
    Exception table:
       from    to  target type
           0    37    48   Class java/lang/InterruptedException
           0    37    48   Class java/util/concurrent/ExecutionException
           0    37    48   Class java/io/IOException
          38    48    48   Class java/lang/InterruptedException
          38    48    48   Class java/util/concurrent/ExecutionException
          38    48    48   Class java/io/IOException

  public io.fabric8.openshift.api.model.SubjectAccessReviewResponse create(io.fabric8.openshift.api.model.LocalSubjectAccessReview);
    Code:
       0: aload_0
       1: iconst_1
       2: anewarray     #18                 // class io/fabric8/openshift/api/model/LocalSubjectAccessReview
       5: dup
       6: iconst_0
       7: aload_1
       8: aastore
       9: invokevirtual #19                 // Method create:([Lio/fabric8/openshift/api/model/LocalSubjectAccessReview;)Lio/fabric8/openshift/api/model/SubjectAccessReviewResponse;
      12: areturn

  public io.fabric8.openshift.client.dsl.CreateableLocalSubjectAccessReview createNew();
    Code:
       0: aload_0
       1: areturn

  public io.fabric8.openshift.api.model.SubjectAccessReviewResponse done();
    Code:
       0: aload_0
       1: aload_0
       2: getfield      #7                  // Field builder:Lio/fabric8/openshift/api/model/LocalSubjectAccessReviewBuilder;
       5: invokevirtual #20                 // Method io/fabric8/openshift/api/model/LocalSubjectAccessReviewBuilder.build:()Lio/fabric8/openshift/api/model/LocalSubjectAccessReview;
       8: invokevirtual #21                 // Method create:(Lio/fabric8/openshift/api/model/LocalSubjectAccessReview;)Lio/fabric8/openshift/api/model/SubjectAccessReviewResponse;
      11: areturn

  public java.lang.Object done();
    Code:
       0: aload_0
       1: invokevirtual #22                 // Method done:()Lio/fabric8/openshift/api/model/SubjectAccessReviewResponse;
       4: areturn

  public java.lang.Object createNew();
    Code:
       0: aload_0
       1: invokevirtual #23                 // Method createNew:()Lio/fabric8/openshift/client/dsl/CreateableLocalSubjectAccessReview;
       4: areturn

  public java.lang.Object create(java.lang.Object);
    Code:
       0: aload_0
       1: aload_1
       2: checkcast     #18                 // class io/fabric8/openshift/api/model/LocalSubjectAccessReview
       5: invokevirtual #21                 // Method create:(Lio/fabric8/openshift/api/model/LocalSubjectAccessReview;)Lio/fabric8/openshift/api/model/SubjectAccessReviewResponse;
       8: areturn

  public java.lang.Object create(java.lang.Object[]);
    Code:
       0: aload_0
       1: aload_1
       2: checkcast     #24                 // class "[Lio/fabric8/openshift/api/model/LocalSubjectAccessReview;"
       5: invokevirtual #19                 // Method create:([Lio/fabric8/openshift/api/model/LocalSubjectAccessReview;)Lio/fabric8/openshift/api/model/SubjectAccessReviewResponse;
       8: areturn

  io.fabric8.openshift.client.dsl.internal.SubjectAccessReviewOperationImpl$CreateableLocalSubjectAccessReviewImpl(io.fabric8.openshift.client.dsl.internal.SubjectAccessReviewOperationImpl, okhttp3.OkHttpClient, io.fabric8.openshift.client.dsl.internal.SubjectAccessReviewOperationImpl$1);
    Code:
       0: aload_0
       1: aload_1
       2: aload_2
       3: invokespecial #1                  // Method "<init>":(Lio/fabric8/openshift/client/dsl/internal/SubjectAccessReviewOperationImpl;Lokhttp3/OkHttpClient;)V
       6: return
}
