Compiled from "OioEventLoopGroup.java"
public class io.netty.channel.oio.OioEventLoopGroup extends io.netty.channel.ThreadPerChannelEventLoopGroup {
  public io.netty.channel.oio.OioEventLoopGroup();
    Code:
       0: aload_0
       1: iconst_0
       2: invokespecial #1                  // Method "<init>":(I)V
       5: return

  public io.netty.channel.oio.OioEventLoopGroup(int);
    Code:
       0: aload_0
       1: iload_1
       2: invokestatic  #2                  // Method java/util/concurrent/Executors.defaultThreadFactory:()Ljava/util/concurrent/ThreadFactory;
       5: invokespecial #3                  // Method "<init>":(ILjava/util/concurrent/ThreadFactory;)V
       8: return

  public io.netty.channel.oio.OioEventLoopGroup(int, java.util.concurrent.Executor);
    Code:
       0: aload_0
       1: iload_1
       2: aload_2
       3: iconst_0
       4: anewarray     #4                  // class java/lang/Object
       7: invokespecial #5                  // Method io/netty/channel/ThreadPerChannelEventLoopGroup."<init>":(ILjava/util/concurrent/Executor;[Ljava/lang/Object;)V
      10: return

  public io.netty.channel.oio.OioEventLoopGroup(int, java.util.concurrent.ThreadFactory);
    Code:
       0: aload_0
       1: iload_1
       2: aload_2
       3: iconst_0
       4: anewarray     #4                  // class java/lang/Object
       7: invokespecial #6                  // Method io/netty/channel/ThreadPerChannelEventLoopGroup."<init>":(ILjava/util/concurrent/ThreadFactory;[Ljava/lang/Object;)V
      10: return
}
