Compiled from "MixinASTTransformation.java"
public class org.codehaus.groovy.ast.MixinASTTransformation extends org.codehaus.groovy.transform.AbstractASTTransformation {
  private static final org.codehaus.groovy.ast.ClassNode MY_TYPE;

  public org.codehaus.groovy.ast.MixinASTTransformation();
    Code:
       0: aload_0
       1: invokespecial #16                 // Method org/codehaus/groovy/transform/AbstractASTTransformation."<init>":()V
       4: return

  public void visit(org.codehaus.groovy.ast.ASTNode[], org.codehaus.groovy.control.SourceUnit);
    Code:
       0: aload_0
       1: aload_1
       2: aload_2
       3: invokevirtual #23                 // Method init:([Lorg/codehaus/groovy/ast/ASTNode;Lorg/codehaus/groovy/control/SourceUnit;)V
       6: aload_1
       7: iconst_0
       8: aaload
       9: checkcast     #25                 // class org/codehaus/groovy/ast/AnnotationNode
      12: astore_3
      13: aload_1
      14: iconst_1
      15: aaload
      16: checkcast     #27                 // class org/codehaus/groovy/ast/AnnotatedNode
      19: astore        4
      21: getstatic     #29                 // Field MY_TYPE:Lorg/codehaus/groovy/ast/ClassNode;
      24: aload_3
      25: invokevirtual #33                 // Method org/codehaus/groovy/ast/AnnotationNode.getClassNode:()Lorg/codehaus/groovy/ast/ClassNode;
      28: invokevirtual #39                 // Method org/codehaus/groovy/ast/ClassNode.equals:(Ljava/lang/Object;)Z
      31: ifne          35
      34: return
      35: aload_3
      36: ldc           #41                 // String value
      38: invokevirtual #45                 // Method org/codehaus/groovy/ast/AnnotationNode.getMember:(Ljava/lang/String;)Lorg/codehaus/groovy/ast/expr/Expression;
      41: astore        5
      43: aload         5
      45: ifnonnull     49
      48: return
      49: aconst_null
      50: astore        6
      52: aload         5
      54: instanceof    #49                 // class org/codehaus/groovy/ast/expr/ClassExpression
      57: ifeq          67
      60: aload         5
      62: astore        6
      64: goto          132
      67: aload         5
      69: instanceof    #51                 // class org/codehaus/groovy/ast/expr/ListExpression
      72: ifeq          132
      75: aload         5
      77: checkcast     #51                 // class org/codehaus/groovy/ast/expr/ListExpression
      80: astore        7
      82: aload         7
      84: invokevirtual #55                 // Method org/codehaus/groovy/ast/expr/ListExpression.getExpressions:()Ljava/util/List;
      87: invokeinterface #61,  1           // InterfaceMethod java/util/List.iterator:()Ljava/util/Iterator;
      92: astore        8
      94: aload         8
      96: invokeinterface #67,  1           // InterfaceMethod java/util/Iterator.hasNext:()Z
     101: ifeq          128
     104: aload         8
     106: invokeinterface #71,  1           // InterfaceMethod java/util/Iterator.next:()Ljava/lang/Object;
     111: checkcast     #47                 // class org/codehaus/groovy/ast/expr/Expression
     114: astore        9
     116: aload         9
     118: instanceof    #49                 // class org/codehaus/groovy/ast/expr/ClassExpression
     121: ifne          125
     124: return
     125: goto          94
     128: aload         5
     130: astore        6
     132: aload         6
     134: ifnonnull     138
     137: return
     138: aload         4
     140: instanceof    #35                 // class org/codehaus/groovy/ast/ClassNode
     143: ifeq          240
     146: aload         4
     148: checkcast     #35                 // class org/codehaus/groovy/ast/ClassNode
     151: astore        7
     153: getstatic     #77                 // Field org/codehaus/groovy/ast/Parameter.EMPTY_ARRAY:[Lorg/codehaus/groovy/ast/Parameter;
     156: astore        8
     158: aload         7
     160: ldc           #79                 // String <clinit>
     162: aload         8
     164: invokevirtual #83                 // Method org/codehaus/groovy/ast/ClassNode.getDeclaredMethod:(Ljava/lang/String;[Lorg/codehaus/groovy/ast/Parameter;)Lorg/codehaus/groovy/ast/MethodNode;
     167: astore        9
     169: aload         9
     171: ifnonnull     205
     174: aload         7
     176: ldc           #79                 // String <clinit>
     178: sipush        4105
     181: getstatic     #88                 // Field org/codehaus/groovy/ast/ClassHelper.VOID_TYPE:Lorg/codehaus/groovy/ast/ClassNode;
     184: aload         8
     186: aconst_null
     187: new           #90                 // class org/codehaus/groovy/ast/stmt/BlockStatement
     190: dup
     191: invokespecial #91                 // Method org/codehaus/groovy/ast/stmt/BlockStatement."<init>":()V
     194: invokevirtual #95                 // Method org/codehaus/groovy/ast/ClassNode.addMethod:(Ljava/lang/String;ILorg/codehaus/groovy/ast/ClassNode;[Lorg/codehaus/groovy/ast/Parameter;[Lorg/codehaus/groovy/ast/ClassNode;Lorg/codehaus/groovy/ast/stmt/Statement;)Lorg/codehaus/groovy/ast/MethodNode;
     197: astore        9
     199: aload         9
     201: iconst_1
     202: invokevirtual #101                // Method org/codehaus/groovy/ast/MethodNode.setSynthetic:(Z)V
     205: aload         9
     207: invokevirtual #106                // Method org/codehaus/groovy/ast/MethodNode.getCode:()Lorg/codehaus/groovy/ast/stmt/Statement;
     210: checkcast     #90                 // class org/codehaus/groovy/ast/stmt/BlockStatement
     213: astore        10
     215: aload         10
     217: aload         7
     219: invokestatic  #112                // Method org/codehaus/groovy/ast/tools/GeneralUtils.classX:(Lorg/codehaus/groovy/ast/ClassNode;)Lorg/codehaus/groovy/ast/expr/ClassExpression;
     222: ldc           #114                // String metaClass
     224: invokestatic  #118                // Method org/codehaus/groovy/ast/tools/GeneralUtils.propX:(Lorg/codehaus/groovy/ast/expr/Expression;Ljava/lang/String;)Lorg/codehaus/groovy/ast/expr/Expression;
     227: ldc           #120                // String mixin
     229: aload         6
     231: invokestatic  #124                // Method org/codehaus/groovy/ast/tools/GeneralUtils.callX:(Lorg/codehaus/groovy/ast/expr/Expression;Ljava/lang/String;Lorg/codehaus/groovy/ast/expr/Expression;)Lorg/codehaus/groovy/ast/expr/MethodCallExpression;
     234: invokestatic  #128                // Method org/codehaus/groovy/ast/tools/GeneralUtils.stmt:(Lorg/codehaus/groovy/ast/expr/Expression;)Lorg/codehaus/groovy/ast/stmt/Statement;
     237: invokevirtual #132                // Method org/codehaus/groovy/ast/stmt/BlockStatement.addStatement:(Lorg/codehaus/groovy/ast/stmt/Statement;)V
     240: return

  static {};
    Code:
       0: ldc           #154                // class groovy/lang/Mixin
       2: invokestatic  #158                // Method org/codehaus/groovy/ast/ClassHelper.make:(Ljava/lang/Class;)Lorg/codehaus/groovy/ast/ClassNode;
       5: putstatic     #29                 // Field MY_TYPE:Lorg/codehaus/groovy/ast/ClassNode;
       8: return
}
