Compiled from "FifoLinkedList.java"
final class org.apache.hc.core5.http2.hpack.FifoLinkedList {
  private final org.apache.hc.core5.http2.hpack.FifoLinkedList$InternalNode master;

  private int length;

  org.apache.hc.core5.http2.hpack.FifoLinkedList();
    Code:
       0: aload_0
       1: invokespecial #1                  // Method java/lang/Object."<init>":()V
       4: aload_0
       5: new           #2                  // class org/apache/hc/core5/http2/hpack/FifoLinkedList$InternalNode
       8: dup
       9: aload_0
      10: aconst_null
      11: invokespecial #3                  // Method org/apache/hc/core5/http2/hpack/FifoLinkedList$InternalNode."<init>":(Lorg/apache/hc/core5/http2/hpack/FifoLinkedList;Lorg/apache/hc/core5/http2/hpack/HPackHeader;)V
      14: putfield      #4                  // Field master:Lorg/apache/hc/core5/http2/hpack/FifoLinkedList$InternalNode;
      17: aload_0
      18: getfield      #4                  // Field master:Lorg/apache/hc/core5/http2/hpack/FifoLinkedList$InternalNode;
      21: aload_0
      22: getfield      #4                  // Field master:Lorg/apache/hc/core5/http2/hpack/FifoLinkedList$InternalNode;
      25: invokestatic  #5                  // Method org/apache/hc/core5/http2/hpack/FifoLinkedList$InternalNode.access$002:(Lorg/apache/hc/core5/http2/hpack/FifoLinkedList$InternalNode;Lorg/apache/hc/core5/http2/hpack/FifoLinkedList$InternalNode;)Lorg/apache/hc/core5/http2/hpack/FifoLinkedList$InternalNode;
      28: pop
      29: aload_0
      30: getfield      #4                  // Field master:Lorg/apache/hc/core5/http2/hpack/FifoLinkedList$InternalNode;
      33: aload_0
      34: getfield      #4                  // Field master:Lorg/apache/hc/core5/http2/hpack/FifoLinkedList$InternalNode;
      37: invokestatic  #6                  // Method org/apache/hc/core5/http2/hpack/FifoLinkedList$InternalNode.access$102:(Lorg/apache/hc/core5/http2/hpack/FifoLinkedList$InternalNode;Lorg/apache/hc/core5/http2/hpack/FifoLinkedList$InternalNode;)Lorg/apache/hc/core5/http2/hpack/FifoLinkedList$InternalNode;
      40: pop
      41: return

  public org.apache.hc.core5.http.Header get(int);
    Code:
       0: iload_1
       1: iflt          12
       4: iload_1
       5: aload_0
       6: getfield      #7                  // Field length:I
       9: if_icmplt     20
      12: new           #8                  // class java/lang/IndexOutOfBoundsException
      15: dup
      16: invokespecial #9                  // Method java/lang/IndexOutOfBoundsException."<init>":()V
      19: athrow
      20: aload_0
      21: getfield      #4                  // Field master:Lorg/apache/hc/core5/http2/hpack/FifoLinkedList$InternalNode;
      24: invokestatic  #10                 // Method org/apache/hc/core5/http2/hpack/FifoLinkedList$InternalNode.access$100:(Lorg/apache/hc/core5/http2/hpack/FifoLinkedList$InternalNode;)Lorg/apache/hc/core5/http2/hpack/FifoLinkedList$InternalNode;
      27: astore_2
      28: iconst_0
      29: istore_3
      30: aload_2
      31: aload_0
      32: getfield      #4                  // Field master:Lorg/apache/hc/core5/http2/hpack/FifoLinkedList$InternalNode;
      35: if_acmpeq     59
      38: iload_1
      39: iload_3
      40: if_icmpne     48
      43: aload_2
      44: invokestatic  #11                 // Method org/apache/hc/core5/http2/hpack/FifoLinkedList$InternalNode.access$200:(Lorg/apache/hc/core5/http2/hpack/FifoLinkedList$InternalNode;)Lorg/apache/hc/core5/http2/hpack/HPackHeader;
      47: areturn
      48: aload_2
      49: invokestatic  #10                 // Method org/apache/hc/core5/http2/hpack/FifoLinkedList$InternalNode.access$100:(Lorg/apache/hc/core5/http2/hpack/FifoLinkedList$InternalNode;)Lorg/apache/hc/core5/http2/hpack/FifoLinkedList$InternalNode;
      52: astore_2
      53: iinc          3, 1
      56: goto          30
      59: aconst_null
      60: areturn

  public int getIndex(org.apache.hc.core5.http2.hpack.FifoLinkedList$InternalNode);
    Code:
       0: aload_1
       1: invokestatic  #12                 // Method org/apache/hc/core5/http2/hpack/FifoLinkedList$InternalNode.access$300:(Lorg/apache/hc/core5/http2/hpack/FifoLinkedList$InternalNode;)I
       4: istore_2
       5: iload_2
       6: iconst_1
       7: if_icmpge     12
      10: iconst_m1
      11: ireturn
      12: aload_0
      13: getfield      #7                  // Field length:I
      16: iload_2
      17: aload_0
      18: getfield      #4                  // Field master:Lorg/apache/hc/core5/http2/hpack/FifoLinkedList$InternalNode;
      21: invokestatic  #13                 // Method org/apache/hc/core5/http2/hpack/FifoLinkedList$InternalNode.access$000:(Lorg/apache/hc/core5/http2/hpack/FifoLinkedList$InternalNode;)Lorg/apache/hc/core5/http2/hpack/FifoLinkedList$InternalNode;
      24: invokestatic  #12                 // Method org/apache/hc/core5/http2/hpack/FifoLinkedList$InternalNode.access$300:(Lorg/apache/hc/core5/http2/hpack/FifoLinkedList$InternalNode;)I
      27: isub
      28: isub
      29: iconst_1
      30: isub
      31: ireturn

  public org.apache.hc.core5.http.Header getFirst();
    Code:
       0: aload_0
       1: getfield      #4                  // Field master:Lorg/apache/hc/core5/http2/hpack/FifoLinkedList$InternalNode;
       4: invokestatic  #10                 // Method org/apache/hc/core5/http2/hpack/FifoLinkedList$InternalNode.access$100:(Lorg/apache/hc/core5/http2/hpack/FifoLinkedList$InternalNode;)Lorg/apache/hc/core5/http2/hpack/FifoLinkedList$InternalNode;
       7: invokestatic  #11                 // Method org/apache/hc/core5/http2/hpack/FifoLinkedList$InternalNode.access$200:(Lorg/apache/hc/core5/http2/hpack/FifoLinkedList$InternalNode;)Lorg/apache/hc/core5/http2/hpack/HPackHeader;
      10: areturn

  public org.apache.hc.core5.http.Header getLast();
    Code:
       0: aload_0
       1: getfield      #4                  // Field master:Lorg/apache/hc/core5/http2/hpack/FifoLinkedList$InternalNode;
       4: invokestatic  #13                 // Method org/apache/hc/core5/http2/hpack/FifoLinkedList$InternalNode.access$000:(Lorg/apache/hc/core5/http2/hpack/FifoLinkedList$InternalNode;)Lorg/apache/hc/core5/http2/hpack/FifoLinkedList$InternalNode;
       7: invokestatic  #11                 // Method org/apache/hc/core5/http2/hpack/FifoLinkedList$InternalNode.access$200:(Lorg/apache/hc/core5/http2/hpack/FifoLinkedList$InternalNode;)Lorg/apache/hc/core5/http2/hpack/HPackHeader;
      10: areturn

  public int size();
    Code:
       0: aload_0
       1: getfield      #7                  // Field length:I
       4: ireturn

  public org.apache.hc.core5.http2.hpack.FifoLinkedList$InternalNode addFirst(org.apache.hc.core5.http2.hpack.HPackHeader);
    Code:
       0: new           #2                  // class org/apache/hc/core5/http2/hpack/FifoLinkedList$InternalNode
       3: dup
       4: aload_0
       5: aload_1
       6: invokespecial #3                  // Method org/apache/hc/core5/http2/hpack/FifoLinkedList$InternalNode."<init>":(Lorg/apache/hc/core5/http2/hpack/FifoLinkedList;Lorg/apache/hc/core5/http2/hpack/HPackHeader;)V
       9: astore_2
      10: aload_0
      11: getfield      #4                  // Field master:Lorg/apache/hc/core5/http2/hpack/FifoLinkedList$InternalNode;
      14: invokestatic  #10                 // Method org/apache/hc/core5/http2/hpack/FifoLinkedList$InternalNode.access$100:(Lorg/apache/hc/core5/http2/hpack/FifoLinkedList$InternalNode;)Lorg/apache/hc/core5/http2/hpack/FifoLinkedList$InternalNode;
      17: astore_3
      18: aload_0
      19: getfield      #4                  // Field master:Lorg/apache/hc/core5/http2/hpack/FifoLinkedList$InternalNode;
      22: aload_2
      23: invokestatic  #6                  // Method org/apache/hc/core5/http2/hpack/FifoLinkedList$InternalNode.access$102:(Lorg/apache/hc/core5/http2/hpack/FifoLinkedList$InternalNode;Lorg/apache/hc/core5/http2/hpack/FifoLinkedList$InternalNode;)Lorg/apache/hc/core5/http2/hpack/FifoLinkedList$InternalNode;
      26: pop
      27: aload_2
      28: aload_0
      29: getfield      #4                  // Field master:Lorg/apache/hc/core5/http2/hpack/FifoLinkedList$InternalNode;
      32: invokestatic  #5                  // Method org/apache/hc/core5/http2/hpack/FifoLinkedList$InternalNode.access$002:(Lorg/apache/hc/core5/http2/hpack/FifoLinkedList$InternalNode;Lorg/apache/hc/core5/http2/hpack/FifoLinkedList$InternalNode;)Lorg/apache/hc/core5/http2/hpack/FifoLinkedList$InternalNode;
      35: pop
      36: aload_2
      37: aload_3
      38: invokestatic  #6                  // Method org/apache/hc/core5/http2/hpack/FifoLinkedList$InternalNode.access$102:(Lorg/apache/hc/core5/http2/hpack/FifoLinkedList$InternalNode;Lorg/apache/hc/core5/http2/hpack/FifoLinkedList$InternalNode;)Lorg/apache/hc/core5/http2/hpack/FifoLinkedList$InternalNode;
      41: pop
      42: aload_3
      43: aload_2
      44: invokestatic  #5                  // Method org/apache/hc/core5/http2/hpack/FifoLinkedList$InternalNode.access$002:(Lorg/apache/hc/core5/http2/hpack/FifoLinkedList$InternalNode;Lorg/apache/hc/core5/http2/hpack/FifoLinkedList$InternalNode;)Lorg/apache/hc/core5/http2/hpack/FifoLinkedList$InternalNode;
      47: pop
      48: aload_2
      49: aload_3
      50: invokestatic  #12                 // Method org/apache/hc/core5/http2/hpack/FifoLinkedList$InternalNode.access$300:(Lorg/apache/hc/core5/http2/hpack/FifoLinkedList$InternalNode;)I
      53: iconst_1
      54: iadd
      55: invokestatic  #14                 // Method org/apache/hc/core5/http2/hpack/FifoLinkedList$InternalNode.access$302:(Lorg/apache/hc/core5/http2/hpack/FifoLinkedList$InternalNode;I)I
      58: pop
      59: aload_0
      60: dup
      61: getfield      #7                  // Field length:I
      64: iconst_1
      65: iadd
      66: putfield      #7                  // Field length:I
      69: aload_2
      70: areturn

  public org.apache.hc.core5.http2.hpack.FifoLinkedList$InternalNode removeLast();
    Code:
       0: aload_0
       1: getfield      #4                  // Field master:Lorg/apache/hc/core5/http2/hpack/FifoLinkedList$InternalNode;
       4: invokestatic  #13                 // Method org/apache/hc/core5/http2/hpack/FifoLinkedList$InternalNode.access$000:(Lorg/apache/hc/core5/http2/hpack/FifoLinkedList$InternalNode;)Lorg/apache/hc/core5/http2/hpack/FifoLinkedList$InternalNode;
       7: astore_1
       8: aload_1
       9: invokestatic  #11                 // Method org/apache/hc/core5/http2/hpack/FifoLinkedList$InternalNode.access$200:(Lorg/apache/hc/core5/http2/hpack/FifoLinkedList$InternalNode;)Lorg/apache/hc/core5/http2/hpack/HPackHeader;
      12: ifnull        68
      15: aload_1
      16: invokestatic  #13                 // Method org/apache/hc/core5/http2/hpack/FifoLinkedList$InternalNode.access$000:(Lorg/apache/hc/core5/http2/hpack/FifoLinkedList$InternalNode;)Lorg/apache/hc/core5/http2/hpack/FifoLinkedList$InternalNode;
      19: astore_2
      20: aload_0
      21: getfield      #4                  // Field master:Lorg/apache/hc/core5/http2/hpack/FifoLinkedList$InternalNode;
      24: aload_2
      25: invokestatic  #5                  // Method org/apache/hc/core5/http2/hpack/FifoLinkedList$InternalNode.access$002:(Lorg/apache/hc/core5/http2/hpack/FifoLinkedList$InternalNode;Lorg/apache/hc/core5/http2/hpack/FifoLinkedList$InternalNode;)Lorg/apache/hc/core5/http2/hpack/FifoLinkedList$InternalNode;
      28: pop
      29: aload_2
      30: aload_0
      31: getfield      #4                  // Field master:Lorg/apache/hc/core5/http2/hpack/FifoLinkedList$InternalNode;
      34: invokestatic  #6                  // Method org/apache/hc/core5/http2/hpack/FifoLinkedList$InternalNode.access$102:(Lorg/apache/hc/core5/http2/hpack/FifoLinkedList$InternalNode;Lorg/apache/hc/core5/http2/hpack/FifoLinkedList$InternalNode;)Lorg/apache/hc/core5/http2/hpack/FifoLinkedList$InternalNode;
      37: pop
      38: aload_1
      39: aconst_null
      40: invokestatic  #5                  // Method org/apache/hc/core5/http2/hpack/FifoLinkedList$InternalNode.access$002:(Lorg/apache/hc/core5/http2/hpack/FifoLinkedList$InternalNode;Lorg/apache/hc/core5/http2/hpack/FifoLinkedList$InternalNode;)Lorg/apache/hc/core5/http2/hpack/FifoLinkedList$InternalNode;
      43: pop
      44: aload_1
      45: aconst_null
      46: invokestatic  #6                  // Method org/apache/hc/core5/http2/hpack/FifoLinkedList$InternalNode.access$102:(Lorg/apache/hc/core5/http2/hpack/FifoLinkedList$InternalNode;Lorg/apache/hc/core5/http2/hpack/FifoLinkedList$InternalNode;)Lorg/apache/hc/core5/http2/hpack/FifoLinkedList$InternalNode;
      49: pop
      50: aload_1
      51: iconst_0
      52: invokestatic  #14                 // Method org/apache/hc/core5/http2/hpack/FifoLinkedList$InternalNode.access$302:(Lorg/apache/hc/core5/http2/hpack/FifoLinkedList$InternalNode;I)I
      55: pop
      56: aload_0
      57: dup
      58: getfield      #7                  // Field length:I
      61: iconst_1
      62: isub
      63: putfield      #7                  // Field length:I
      66: aload_1
      67: areturn
      68: aload_0
      69: getfield      #4                  // Field master:Lorg/apache/hc/core5/http2/hpack/FifoLinkedList$InternalNode;
      72: iconst_0
      73: invokestatic  #14                 // Method org/apache/hc/core5/http2/hpack/FifoLinkedList$InternalNode.access$302:(Lorg/apache/hc/core5/http2/hpack/FifoLinkedList$InternalNode;I)I
      76: pop
      77: aconst_null
      78: areturn

  public void clear();
    Code:
       0: aload_0
       1: getfield      #4                  // Field master:Lorg/apache/hc/core5/http2/hpack/FifoLinkedList$InternalNode;
       4: aload_0
       5: getfield      #4                  // Field master:Lorg/apache/hc/core5/http2/hpack/FifoLinkedList$InternalNode;
       8: invokestatic  #5                  // Method org/apache/hc/core5/http2/hpack/FifoLinkedList$InternalNode.access$002:(Lorg/apache/hc/core5/http2/hpack/FifoLinkedList$InternalNode;Lorg/apache/hc/core5/http2/hpack/FifoLinkedList$InternalNode;)Lorg/apache/hc/core5/http2/hpack/FifoLinkedList$InternalNode;
      11: pop
      12: aload_0
      13: getfield      #4                  // Field master:Lorg/apache/hc/core5/http2/hpack/FifoLinkedList$InternalNode;
      16: aload_0
      17: getfield      #4                  // Field master:Lorg/apache/hc/core5/http2/hpack/FifoLinkedList$InternalNode;
      20: invokestatic  #6                  // Method org/apache/hc/core5/http2/hpack/FifoLinkedList$InternalNode.access$102:(Lorg/apache/hc/core5/http2/hpack/FifoLinkedList$InternalNode;Lorg/apache/hc/core5/http2/hpack/FifoLinkedList$InternalNode;)Lorg/apache/hc/core5/http2/hpack/FifoLinkedList$InternalNode;
      23: pop
      24: aload_0
      25: getfield      #4                  // Field master:Lorg/apache/hc/core5/http2/hpack/FifoLinkedList$InternalNode;
      28: iconst_0
      29: invokestatic  #14                 // Method org/apache/hc/core5/http2/hpack/FifoLinkedList$InternalNode.access$302:(Lorg/apache/hc/core5/http2/hpack/FifoLinkedList$InternalNode;I)I
      32: pop
      33: aload_0
      34: iconst_0
      35: putfield      #7                  // Field length:I
      38: return
}
