Compiled from "HPackDecoder.java"
public final class org.apache.hc.core5.http2.hpack.HPackDecoder {
  private static final java.lang.String UNEXPECTED_EOS;

  private static final java.lang.String MAX_LIMIT_EXCEEDED;

  private final org.apache.hc.core5.http2.hpack.InboundDynamicTable dynamicTable;

  private final org.apache.hc.core5.util.ByteArrayBuffer contentBuf;

  private final java.nio.charset.CharsetDecoder charsetDecoder;

  private java.nio.CharBuffer tmpBuf;

  private int maxTableSize;

  private int maxListSize;

  org.apache.hc.core5.http2.hpack.HPackDecoder(org.apache.hc.core5.http2.hpack.InboundDynamicTable, java.nio.charset.CharsetDecoder);
    Code:
       0: aload_0
       1: invokespecial #1                  // Method java/lang/Object."<init>":()V
       4: aload_0
       5: aload_1
       6: ifnull        13
       9: aload_1
      10: goto          20
      13: new           #2                  // class org/apache/hc/core5/http2/hpack/InboundDynamicTable
      16: dup
      17: invokespecial #3                  // Method org/apache/hc/core5/http2/hpack/InboundDynamicTable."<init>":()V
      20: putfield      #4                  // Field dynamicTable:Lorg/apache/hc/core5/http2/hpack/InboundDynamicTable;
      23: aload_0
      24: new           #5                  // class org/apache/hc/core5/util/ByteArrayBuffer
      27: dup
      28: sipush        256
      31: invokespecial #6                  // Method org/apache/hc/core5/util/ByteArrayBuffer."<init>":(I)V
      34: putfield      #7                  // Field contentBuf:Lorg/apache/hc/core5/util/ByteArrayBuffer;
      37: aload_0
      38: aload_2
      39: putfield      #8                  // Field charsetDecoder:Ljava/nio/charset/CharsetDecoder;
      42: aload_0
      43: aload_1
      44: ifnull        54
      47: aload_1
      48: invokevirtual #9                  // Method org/apache/hc/core5/http2/hpack/InboundDynamicTable.getMaxSize:()I
      51: goto          56
      54: ldc           #10                 // int 2147483647
      56: putfield      #11                 // Field maxTableSize:I
      59: aload_0
      60: ldc           #10                 // int 2147483647
      62: putfield      #12                 // Field maxListSize:I
      65: return

  org.apache.hc.core5.http2.hpack.HPackDecoder(org.apache.hc.core5.http2.hpack.InboundDynamicTable, java.nio.charset.Charset);
    Code:
       0: aload_0
       1: aload_1
       2: aload_2
       3: ifnull        23
       6: getstatic     #13                 // Field java/nio/charset/StandardCharsets.US_ASCII:Ljava/nio/charset/Charset;
       9: aload_2
      10: invokevirtual #14                 // Method java/nio/charset/Charset.equals:(Ljava/lang/Object;)Z
      13: ifne          23
      16: aload_2
      17: invokevirtual #15                 // Method java/nio/charset/Charset.newDecoder:()Ljava/nio/charset/CharsetDecoder;
      20: goto          24
      23: aconst_null
      24: invokespecial #16                 // Method "<init>":(Lorg/apache/hc/core5/http2/hpack/InboundDynamicTable;Ljava/nio/charset/CharsetDecoder;)V
      27: return

  public org.apache.hc.core5.http2.hpack.HPackDecoder(java.nio.charset.Charset);
    Code:
       0: aload_0
       1: new           #2                  // class org/apache/hc/core5/http2/hpack/InboundDynamicTable
       4: dup
       5: invokespecial #3                  // Method org/apache/hc/core5/http2/hpack/InboundDynamicTable."<init>":()V
       8: aload_1
       9: invokespecial #17                 // Method "<init>":(Lorg/apache/hc/core5/http2/hpack/InboundDynamicTable;Ljava/nio/charset/Charset;)V
      12: return

  public org.apache.hc.core5.http2.hpack.HPackDecoder(java.nio.charset.CharsetDecoder);
    Code:
       0: aload_0
       1: new           #2                  // class org/apache/hc/core5/http2/hpack/InboundDynamicTable
       4: dup
       5: invokespecial #3                  // Method org/apache/hc/core5/http2/hpack/InboundDynamicTable."<init>":()V
       8: aload_1
       9: invokespecial #16                 // Method "<init>":(Lorg/apache/hc/core5/http2/hpack/InboundDynamicTable;Ljava/nio/charset/CharsetDecoder;)V
      12: return

  static int readByte(java.nio.ByteBuffer) throws org.apache.hc.core5.http2.hpack.HPackException;
    Code:
       0: aload_0
       1: invokevirtual #18                 // Method java/nio/ByteBuffer.hasRemaining:()Z
       4: ifne          17
       7: new           #19                 // class org/apache/hc/core5/http2/hpack/HPackException
      10: dup
      11: ldc           #20                 // String Unexpected end of HPACK data
      13: invokespecial #21                 // Method org/apache/hc/core5/http2/hpack/HPackException."<init>":(Ljava/lang/String;)V
      16: athrow
      17: aload_0
      18: invokevirtual #22                 // Method java/nio/ByteBuffer.get:()B
      21: sipush        255
      24: iand
      25: ireturn

  static int peekByte(java.nio.ByteBuffer) throws org.apache.hc.core5.http2.hpack.HPackException;
    Code:
       0: aload_0
       1: invokevirtual #18                 // Method java/nio/ByteBuffer.hasRemaining:()Z
       4: ifne          17
       7: new           #19                 // class org/apache/hc/core5/http2/hpack/HPackException
      10: dup
      11: ldc           #20                 // String Unexpected end of HPACK data
      13: invokespecial #21                 // Method org/apache/hc/core5/http2/hpack/HPackException."<init>":(Ljava/lang/String;)V
      16: athrow
      17: aload_0
      18: invokevirtual #23                 // Method java/nio/ByteBuffer.position:()I
      21: istore_1
      22: aload_0
      23: invokevirtual #22                 // Method java/nio/ByteBuffer.get:()B
      26: sipush        255
      29: iand
      30: istore_2
      31: aload_0
      32: iload_1
      33: invokevirtual #24                 // Method java/nio/ByteBuffer.position:(I)Ljava/nio/Buffer;
      36: pop
      37: iload_2
      38: ireturn

  static int decodeInt(java.nio.ByteBuffer, int) throws org.apache.hc.core5.http2.hpack.HPackException;
    Code:
       0: sipush        255
       3: bipush        8
       5: iload_1
       6: isub
       7: iushr
       8: istore_2
       9: aload_0
      10: invokestatic  #25                 // Method readByte:(Ljava/nio/ByteBuffer;)I
      13: iload_2
      14: iand
      15: istore_3
      16: iload_3
      17: iload_2
      18: if_icmpge     23
      21: iload_3
      22: ireturn
      23: iconst_0
      24: istore        4
      26: iload         4
      28: bipush        32
      30: if_icmpge     97
      33: aload_0
      34: invokestatic  #25                 // Method readByte:(Ljava/nio/ByteBuffer;)I
      37: istore        5
      39: iload         5
      41: sipush        128
      44: iand
      45: ifeq          65
      48: iload_3
      49: iload         5
      51: bipush        127
      53: iand
      54: iload         4
      56: ishl
      57: iadd
      58: istore_3
      59: iinc          4, 7
      62: goto          94
      65: iload         4
      67: bipush        28
      69: if_icmpne     84
      72: iload         5
      74: sipush        248
      77: iand
      78: ifeq          84
      81: goto          97
      84: iload_3
      85: iload         5
      87: iload         4
      89: ishl
      90: iadd
      91: istore_3
      92: iload_3
      93: ireturn
      94: goto          26
      97: new           #19                 // class org/apache/hc/core5/http2/hpack/HPackException
     100: dup
     101: ldc           #26                 // String Max integer exceeded
     103: invokespecial #21                 // Method org/apache/hc/core5/http2/hpack/HPackException."<init>":(Ljava/lang/String;)V
     106: athrow

  static void decodePlainString(org.apache.hc.core5.util.ByteArrayBuffer, java.nio.ByteBuffer) throws org.apache.hc.core5.http2.hpack.HPackException;
    Code:
       0: aload_1
       1: bipush        7
       3: invokestatic  #27                 // Method decodeInt:(Ljava/nio/ByteBuffer;I)I
       6: istore_2
       7: aload_1
       8: invokevirtual #28                 // Method java/nio/ByteBuffer.remaining:()I
      11: istore_3
      12: iload_2
      13: iload_3
      14: if_icmple     27
      17: new           #19                 // class org/apache/hc/core5/http2/hpack/HPackException
      20: dup
      21: ldc           #20                 // String Unexpected end of HPACK data
      23: invokespecial #21                 // Method org/apache/hc/core5/http2/hpack/HPackException."<init>":(Ljava/lang/String;)V
      26: athrow
      27: aload_1
      28: invokevirtual #29                 // Method java/nio/ByteBuffer.limit:()I
      31: istore        4
      33: aload_1
      34: iload         4
      36: iload_3
      37: iload_2
      38: isub
      39: isub
      40: invokevirtual #30                 // Method java/nio/ByteBuffer.limit:(I)Ljava/nio/Buffer;
      43: pop
      44: aload_0
      45: aload_1
      46: invokevirtual #31                 // Method org/apache/hc/core5/util/ByteArrayBuffer.append:(Ljava/nio/ByteBuffer;)V
      49: aload_1
      50: iload         4
      52: invokevirtual #30                 // Method java/nio/ByteBuffer.limit:(I)Ljava/nio/Buffer;
      55: pop
      56: return

  static void decodeHuffman(org.apache.hc.core5.util.ByteArrayBuffer, java.nio.ByteBuffer) throws org.apache.hc.core5.http2.hpack.HPackException;
    Code:
       0: aload_1
       1: bipush        7
       3: invokestatic  #27                 // Method decodeInt:(Ljava/nio/ByteBuffer;I)I
       6: istore_2
       7: iload_2
       8: aload_1
       9: invokevirtual #28                 // Method java/nio/ByteBuffer.remaining:()I
      12: if_icmple     25
      15: new           #19                 // class org/apache/hc/core5/http2/hpack/HPackException
      18: dup
      19: ldc           #20                 // String Unexpected end of HPACK data
      21: invokespecial #21                 // Method org/apache/hc/core5/http2/hpack/HPackException."<init>":(Ljava/lang/String;)V
      24: athrow
      25: aload_1
      26: invokevirtual #29                 // Method java/nio/ByteBuffer.limit:()I
      29: istore_3
      30: aload_1
      31: aload_1
      32: invokevirtual #23                 // Method java/nio/ByteBuffer.position:()I
      35: iload_2
      36: iadd
      37: invokevirtual #30                 // Method java/nio/ByteBuffer.limit:(I)Ljava/nio/Buffer;
      40: pop
      41: getstatic     #32                 // Field org/apache/hc/core5/http2/hpack/Huffman.DECODER:Lorg/apache/hc/core5/http2/hpack/HuffmanDecoder;
      44: aload_0
      45: aload_1
      46: invokevirtual #33                 // Method org/apache/hc/core5/http2/hpack/HuffmanDecoder.decode:(Lorg/apache/hc/core5/util/ByteArrayBuffer;Ljava/nio/ByteBuffer;)V
      49: aload_1
      50: iload_3
      51: invokevirtual #30                 // Method java/nio/ByteBuffer.limit:(I)Ljava/nio/Buffer;
      54: pop
      55: return

  void decodeString(org.apache.hc.core5.util.ByteArrayBuffer, java.nio.ByteBuffer) throws org.apache.hc.core5.http2.hpack.HPackException;
    Code:
       0: aload_2
       1: invokestatic  #34                 // Method peekByte:(Ljava/nio/ByteBuffer;)I
       4: istore_3
       5: iload_3
       6: sipush        128
       9: iand
      10: sipush        128
      13: if_icmpne     24
      16: aload_1
      17: aload_2
      18: invokestatic  #35                 // Method decodeHuffman:(Lorg/apache/hc/core5/util/ByteArrayBuffer;Ljava/nio/ByteBuffer;)V
      21: goto          29
      24: aload_1
      25: aload_2
      26: invokestatic  #36                 // Method decodePlainString:(Lorg/apache/hc/core5/util/ByteArrayBuffer;Ljava/nio/ByteBuffer;)V
      29: return

  private void clearState();
    Code:
       0: aload_0
       1: getfield      #37                 // Field tmpBuf:Ljava/nio/CharBuffer;
       4: ifnull        15
       7: aload_0
       8: getfield      #37                 // Field tmpBuf:Ljava/nio/CharBuffer;
      11: invokevirtual #38                 // Method java/nio/CharBuffer.clear:()Ljava/nio/Buffer;
      14: pop
      15: aload_0
      16: getfield      #8                  // Field charsetDecoder:Ljava/nio/charset/CharsetDecoder;
      19: ifnull        30
      22: aload_0
      23: getfield      #8                  // Field charsetDecoder:Ljava/nio/charset/CharsetDecoder;
      26: invokevirtual #39                 // Method java/nio/charset/CharsetDecoder.reset:()Ljava/nio/charset/CharsetDecoder;
      29: pop
      30: aload_0
      31: getfield      #7                  // Field contentBuf:Lorg/apache/hc/core5/util/ByteArrayBuffer;
      34: invokevirtual #40                 // Method org/apache/hc/core5/util/ByteArrayBuffer.clear:()V
      37: return

  private void expandCapacity(int);
    Code:
       0: aload_0
       1: getfield      #37                 // Field tmpBuf:Ljava/nio/CharBuffer;
       4: astore_2
       5: aload_0
       6: iload_1
       7: invokestatic  #41                 // Method java/nio/CharBuffer.allocate:(I)Ljava/nio/CharBuffer;
      10: putfield      #37                 // Field tmpBuf:Ljava/nio/CharBuffer;
      13: aload_2
      14: invokevirtual #42                 // Method java/nio/CharBuffer.flip:()Ljava/nio/Buffer;
      17: pop
      18: aload_0
      19: getfield      #37                 // Field tmpBuf:Ljava/nio/CharBuffer;
      22: aload_2
      23: invokevirtual #43                 // Method java/nio/CharBuffer.put:(Ljava/nio/CharBuffer;)Ljava/nio/CharBuffer;
      26: pop
      27: return

  private void ensureCapacity(int);
    Code:
       0: aload_0
       1: getfield      #37                 // Field tmpBuf:Ljava/nio/CharBuffer;
       4: ifnonnull     21
       7: aload_0
       8: sipush        256
      11: iload_1
      12: invokestatic  #44                 // Method java/lang/Math.max:(II)I
      15: invokestatic  #41                 // Method java/nio/CharBuffer.allocate:(I)Ljava/nio/CharBuffer;
      18: putfield      #37                 // Field tmpBuf:Ljava/nio/CharBuffer;
      21: aload_0
      22: getfield      #37                 // Field tmpBuf:Ljava/nio/CharBuffer;
      25: invokevirtual #45                 // Method java/nio/CharBuffer.remaining:()I
      28: iload_1
      29: iadd
      30: istore_2
      31: iload_2
      32: aload_0
      33: getfield      #37                 // Field tmpBuf:Ljava/nio/CharBuffer;
      36: invokevirtual #46                 // Method java/nio/CharBuffer.capacity:()I
      39: if_icmple     47
      42: aload_0
      43: iload_2
      44: invokespecial #47                 // Method expandCapacity:(I)V
      47: return

  int decodeString(java.nio.ByteBuffer, java.lang.StringBuilder) throws org.apache.hc.core5.http2.hpack.HPackException, java.nio.charset.CharacterCodingException;
    Code:
       0: aload_0
       1: invokespecial #48                 // Method clearState:()V
       4: aload_0
       5: aload_0
       6: getfield      #7                  // Field contentBuf:Lorg/apache/hc/core5/util/ByteArrayBuffer;
       9: aload_1
      10: invokevirtual #49                 // Method decodeString:(Lorg/apache/hc/core5/util/ByteArrayBuffer;Ljava/nio/ByteBuffer;)V
      13: aload_0
      14: getfield      #7                  // Field contentBuf:Lorg/apache/hc/core5/util/ByteArrayBuffer;
      17: invokevirtual #50                 // Method org/apache/hc/core5/util/ByteArrayBuffer.length:()I
      20: istore_3
      21: aload_0
      22: getfield      #8                  // Field charsetDecoder:Ljava/nio/charset/CharsetDecoder;
      25: ifnonnull     70
      28: aload_2
      29: iload_3
      30: invokevirtual #51                 // Method java/lang/StringBuilder.ensureCapacity:(I)V
      33: iconst_0
      34: istore        4
      36: iload         4
      38: iload_3
      39: if_icmpge     67
      42: aload_2
      43: aload_0
      44: getfield      #7                  // Field contentBuf:Lorg/apache/hc/core5/util/ByteArrayBuffer;
      47: iload         4
      49: invokevirtual #52                 // Method org/apache/hc/core5/util/ByteArrayBuffer.byteAt:(I)I
      52: sipush        255
      55: iand
      56: i2c
      57: invokevirtual #53                 // Method java/lang/StringBuilder.append:(C)Ljava/lang/StringBuilder;
      60: pop
      61: iinc          4, 1
      64: goto          36
      67: goto          182
      70: aload_0
      71: getfield      #7                  // Field contentBuf:Lorg/apache/hc/core5/util/ByteArrayBuffer;
      74: invokevirtual #54                 // Method org/apache/hc/core5/util/ByteArrayBuffer.array:()[B
      77: iconst_0
      78: iload_3
      79: invokestatic  #55                 // Method java/nio/ByteBuffer.wrap:([BII)Ljava/nio/ByteBuffer;
      82: astore        4
      84: aload         4
      86: invokevirtual #18                 // Method java/nio/ByteBuffer.hasRemaining:()Z
      89: ifeq          133
      92: aload_0
      93: aload         4
      95: invokevirtual #28                 // Method java/nio/ByteBuffer.remaining:()I
      98: invokespecial #56                 // Method ensureCapacity:(I)V
     101: aload_0
     102: getfield      #8                  // Field charsetDecoder:Ljava/nio/charset/CharsetDecoder;
     105: aload         4
     107: aload_0
     108: getfield      #37                 // Field tmpBuf:Ljava/nio/CharBuffer;
     111: iconst_1
     112: invokevirtual #57                 // Method java/nio/charset/CharsetDecoder.decode:(Ljava/nio/ByteBuffer;Ljava/nio/CharBuffer;Z)Ljava/nio/charset/CoderResult;
     115: astore        5
     117: aload         5
     119: invokevirtual #58                 // Method java/nio/charset/CoderResult.isError:()Z
     122: ifeq          130
     125: aload         5
     127: invokevirtual #59                 // Method java/nio/charset/CoderResult.throwException:()V
     130: goto          84
     133: aload_0
     134: bipush        8
     136: invokespecial #56                 // Method ensureCapacity:(I)V
     139: aload_0
     140: getfield      #8                  // Field charsetDecoder:Ljava/nio/charset/CharsetDecoder;
     143: aload_0
     144: getfield      #37                 // Field tmpBuf:Ljava/nio/CharBuffer;
     147: invokevirtual #60                 // Method java/nio/charset/CharsetDecoder.flush:(Ljava/nio/CharBuffer;)Ljava/nio/charset/CoderResult;
     150: astore        5
     152: aload         5
     154: invokevirtual #58                 // Method java/nio/charset/CoderResult.isError:()Z
     157: ifeq          165
     160: aload         5
     162: invokevirtual #59                 // Method java/nio/charset/CoderResult.throwException:()V
     165: aload_0
     166: getfield      #37                 // Field tmpBuf:Ljava/nio/CharBuffer;
     169: invokevirtual #42                 // Method java/nio/CharBuffer.flip:()Ljava/nio/Buffer;
     172: pop
     173: aload_2
     174: aload_0
     175: getfield      #37                 // Field tmpBuf:Ljava/nio/CharBuffer;
     178: invokevirtual #61                 // Method java/lang/StringBuilder.append:(Ljava/lang/CharSequence;)Ljava/lang/StringBuilder;
     181: pop
     182: iload_3
     183: ireturn

  org.apache.hc.core5.http2.hpack.HPackHeader decodeLiteralHeader(java.nio.ByteBuffer, org.apache.hc.core5.http2.hpack.HPackRepresentation) throws org.apache.hc.core5.http2.hpack.HPackException, java.nio.charset.CharacterCodingException;
    Code:
       0: aload_2
       1: getstatic     #62                 // Field org/apache/hc/core5/http2/hpack/HPackRepresentation.WITH_INDEXING:Lorg/apache/hc/core5/http2/hpack/HPackRepresentation;
       4: if_acmpne     12
       7: bipush        6
       9: goto          13
      12: iconst_4
      13: istore_3
      14: aload_1
      15: iload_3
      16: invokestatic  #27                 // Method decodeInt:(Ljava/nio/ByteBuffer;I)I
      19: istore        4
      21: iload         4
      23: ifne          54
      26: new           #63                 // class java/lang/StringBuilder
      29: dup
      30: invokespecial #64                 // Method java/lang/StringBuilder."<init>":()V
      33: astore        7
      35: aload_0
      36: aload_1
      37: aload         7
      39: invokevirtual #65                 // Method decodeString:(Ljava/nio/ByteBuffer;Ljava/lang/StringBuilder;)I
      42: istore        6
      44: aload         7
      46: invokevirtual #66                 // Method java/lang/StringBuilder.toString:()Ljava/lang/String;
      49: astore        5
      51: goto          94
      54: aload_0
      55: getfield      #4                  // Field dynamicTable:Lorg/apache/hc/core5/http2/hpack/InboundDynamicTable;
      58: iload         4
      60: invokevirtual #67                 // Method org/apache/hc/core5/http2/hpack/InboundDynamicTable.getHeader:(I)Lorg/apache/hc/core5/http2/hpack/HPackHeader;
      63: astore        7
      65: aload         7
      67: ifnonnull     80
      70: new           #19                 // class org/apache/hc/core5/http2/hpack/HPackException
      73: dup
      74: ldc           #68                 // String Invalid header index
      76: invokespecial #21                 // Method org/apache/hc/core5/http2/hpack/HPackException."<init>":(Ljava/lang/String;)V
      79: athrow
      80: aload         7
      82: invokevirtual #69                 // Method org/apache/hc/core5/http2/hpack/HPackHeader.getName:()Ljava/lang/String;
      85: astore        5
      87: aload         7
      89: invokevirtual #70                 // Method org/apache/hc/core5/http2/hpack/HPackHeader.getNameLen:()I
      92: istore        6
      94: new           #63                 // class java/lang/StringBuilder
      97: dup
      98: invokespecial #64                 // Method java/lang/StringBuilder."<init>":()V
     101: astore        7
     103: aload_0
     104: aload_1
     105: aload         7
     107: invokevirtual #65                 // Method decodeString:(Ljava/nio/ByteBuffer;Ljava/lang/StringBuilder;)I
     110: istore        8
     112: aload         7
     114: invokevirtual #66                 // Method java/lang/StringBuilder.toString:()Ljava/lang/String;
     117: astore        9
     119: new           #71                 // class org/apache/hc/core5/http2/hpack/HPackHeader
     122: dup
     123: aload         5
     125: iload         6
     127: aload         9
     129: iload         8
     131: aload_2
     132: getstatic     #72                 // Field org/apache/hc/core5/http2/hpack/HPackRepresentation.NEVER_INDEXED:Lorg/apache/hc/core5/http2/hpack/HPackRepresentation;
     135: if_acmpne     142
     138: iconst_1
     139: goto          143
     142: iconst_0
     143: invokespecial #73                 // Method org/apache/hc/core5/http2/hpack/HPackHeader."<init>":(Ljava/lang/String;ILjava/lang/String;IZ)V
     146: astore        10
     148: aload_2
     149: getstatic     #62                 // Field org/apache/hc/core5/http2/hpack/HPackRepresentation.WITH_INDEXING:Lorg/apache/hc/core5/http2/hpack/HPackRepresentation;
     152: if_acmpne     164
     155: aload_0
     156: getfield      #4                  // Field dynamicTable:Lorg/apache/hc/core5/http2/hpack/InboundDynamicTable;
     159: aload         10
     161: invokevirtual #74                 // Method org/apache/hc/core5/http2/hpack/InboundDynamicTable.add:(Lorg/apache/hc/core5/http2/hpack/HPackHeader;)V
     164: aload         10
     166: areturn

  org.apache.hc.core5.http2.hpack.HPackHeader decodeIndexedHeader(java.nio.ByteBuffer) throws org.apache.hc.core5.http2.hpack.HPackException;
    Code:
       0: aload_1
       1: bipush        7
       3: invokestatic  #27                 // Method decodeInt:(Ljava/nio/ByteBuffer;I)I
       6: istore_2
       7: aload_0
       8: getfield      #4                  // Field dynamicTable:Lorg/apache/hc/core5/http2/hpack/InboundDynamicTable;
      11: iload_2
      12: invokevirtual #67                 // Method org/apache/hc/core5/http2/hpack/InboundDynamicTable.getHeader:(I)Lorg/apache/hc/core5/http2/hpack/HPackHeader;
      15: astore_3
      16: aload_3
      17: ifnonnull     30
      20: new           #19                 // class org/apache/hc/core5/http2/hpack/HPackException
      23: dup
      24: ldc           #68                 // String Invalid header index
      26: invokespecial #21                 // Method org/apache/hc/core5/http2/hpack/HPackException."<init>":(Ljava/lang/String;)V
      29: athrow
      30: aload_3
      31: areturn

  public org.apache.hc.core5.http.Header decodeHeader(java.nio.ByteBuffer) throws org.apache.hc.core5.http2.hpack.HPackException;
    Code:
       0: aload_0
       1: aload_1
       2: invokevirtual #75                 // Method decodeHPackHeader:(Ljava/nio/ByteBuffer;)Lorg/apache/hc/core5/http2/hpack/HPackHeader;
       5: astore_2
       6: aload_2
       7: ifnull        32
      10: new           #76                 // class org/apache/hc/core5/http/message/BasicHeader
      13: dup
      14: aload_2
      15: invokevirtual #69                 // Method org/apache/hc/core5/http2/hpack/HPackHeader.getName:()Ljava/lang/String;
      18: aload_2
      19: invokevirtual #77                 // Method org/apache/hc/core5/http2/hpack/HPackHeader.getValue:()Ljava/lang/String;
      22: aload_2
      23: invokevirtual #78                 // Method org/apache/hc/core5/http2/hpack/HPackHeader.isSensitive:()Z
      26: invokespecial #79                 // Method org/apache/hc/core5/http/message/BasicHeader."<init>":(Ljava/lang/String;Ljava/lang/Object;Z)V
      29: goto          33
      32: aconst_null
      33: areturn

  org.apache.hc.core5.http2.hpack.HPackHeader decodeHPackHeader(java.nio.ByteBuffer) throws org.apache.hc.core5.http2.hpack.HPackException;
    Code:
       0: aload_1
       1: invokevirtual #18                 // Method java/nio/ByteBuffer.hasRemaining:()Z
       4: ifeq          151
       7: aload_1
       8: invokestatic  #34                 // Method peekByte:(Ljava/nio/ByteBuffer;)I
      11: istore_2
      12: iload_2
      13: sipush        128
      16: iand
      17: sipush        128
      20: if_icmpne     29
      23: aload_0
      24: aload_1
      25: invokevirtual #80                 // Method decodeIndexedHeader:(Ljava/nio/ByteBuffer;)Lorg/apache/hc/core5/http2/hpack/HPackHeader;
      28: areturn
      29: iload_2
      30: sipush        192
      33: iand
      34: bipush        64
      36: if_icmpne     48
      39: aload_0
      40: aload_1
      41: getstatic     #62                 // Field org/apache/hc/core5/http2/hpack/HPackRepresentation.WITH_INDEXING:Lorg/apache/hc/core5/http2/hpack/HPackRepresentation;
      44: invokevirtual #81                 // Method decodeLiteralHeader:(Ljava/nio/ByteBuffer;Lorg/apache/hc/core5/http2/hpack/HPackRepresentation;)Lorg/apache/hc/core5/http2/hpack/HPackHeader;
      47: areturn
      48: iload_2
      49: sipush        240
      52: iand
      53: ifne          65
      56: aload_0
      57: aload_1
      58: getstatic     #82                 // Field org/apache/hc/core5/http2/hpack/HPackRepresentation.WITHOUT_INDEXING:Lorg/apache/hc/core5/http2/hpack/HPackRepresentation;
      61: invokevirtual #81                 // Method decodeLiteralHeader:(Ljava/nio/ByteBuffer;Lorg/apache/hc/core5/http2/hpack/HPackRepresentation;)Lorg/apache/hc/core5/http2/hpack/HPackHeader;
      64: areturn
      65: iload_2
      66: sipush        240
      69: iand
      70: bipush        16
      72: if_icmpne     84
      75: aload_0
      76: aload_1
      77: getstatic     #72                 // Field org/apache/hc/core5/http2/hpack/HPackRepresentation.NEVER_INDEXED:Lorg/apache/hc/core5/http2/hpack/HPackRepresentation;
      80: invokevirtual #81                 // Method decodeLiteralHeader:(Ljava/nio/ByteBuffer;Lorg/apache/hc/core5/http2/hpack/HPackRepresentation;)Lorg/apache/hc/core5/http2/hpack/HPackHeader;
      83: areturn
      84: iload_2
      85: sipush        224
      88: iand
      89: bipush        32
      91: if_icmpne     118
      94: aload_1
      95: iconst_5
      96: invokestatic  #27                 // Method decodeInt:(Ljava/nio/ByteBuffer;I)I
      99: istore_3
     100: aload_0
     101: getfield      #4                  // Field dynamicTable:Lorg/apache/hc/core5/http2/hpack/InboundDynamicTable;
     104: aload_0
     105: getfield      #11                 // Field maxTableSize:I
     108: iload_3
     109: invokestatic  #83                 // Method java/lang/Math.min:(II)I
     112: invokevirtual #84                 // Method org/apache/hc/core5/http2/hpack/InboundDynamicTable.setMaxSize:(I)V
     115: goto          148
     118: new           #19                 // class org/apache/hc/core5/http2/hpack/HPackException
     121: dup
     122: new           #63                 // class java/lang/StringBuilder
     125: dup
     126: invokespecial #64                 // Method java/lang/StringBuilder."<init>":()V
     129: ldc           #85                 // String Unexpected header first byte: 0x
     131: invokevirtual #86                 // Method java/lang/StringBuilder.append:(Ljava/lang/String;)Ljava/lang/StringBuilder;
     134: iload_2
     135: invokestatic  #87                 // Method java/lang/Integer.toHexString:(I)Ljava/lang/String;
     138: invokevirtual #86                 // Method java/lang/StringBuilder.append:(Ljava/lang/String;)Ljava/lang/StringBuilder;
     141: invokevirtual #66                 // Method java/lang/StringBuilder.toString:()Ljava/lang/String;
     144: invokespecial #21                 // Method org/apache/hc/core5/http2/hpack/HPackException."<init>":(Ljava/lang/String;)V
     147: athrow
     148: goto          0
     151: aconst_null
     152: areturn
     153: astore_2
     154: new           #19                 // class org/apache/hc/core5/http2/hpack/HPackException
     157: dup
     158: aload_2
     159: invokevirtual #89                 // Method java/nio/charset/CharacterCodingException.getMessage:()Ljava/lang/String;
     162: aload_2
     163: invokespecial #90                 // Method org/apache/hc/core5/http2/hpack/HPackException."<init>":(Ljava/lang/String;Ljava/lang/Exception;)V
     166: athrow
    Exception table:
       from    to  target type
           0    28   153   Class java/nio/charset/CharacterCodingException
          29    47   153   Class java/nio/charset/CharacterCodingException
          48    64   153   Class java/nio/charset/CharacterCodingException
          65    83   153   Class java/nio/charset/CharacterCodingException
          84   152   153   Class java/nio/charset/CharacterCodingException

  public java.util.List<org.apache.hc.core5.http.Header> decodeHeaders(java.nio.ByteBuffer) throws org.apache.hc.core5.http2.hpack.HPackException;
    Code:
       0: aload_0
       1: getfield      #12                 // Field maxListSize:I
       4: ldc           #10                 // int 2147483647
       6: if_icmpge     13
       9: iconst_1
      10: goto          14
      13: iconst_0
      14: istore_2
      15: iconst_0
      16: istore_3
      17: new           #91                 // class java/util/ArrayList
      20: dup
      21: invokespecial #92                 // Method java/util/ArrayList."<init>":()V
      24: astore        4
      26: aload_1
      27: invokevirtual #18                 // Method java/nio/ByteBuffer.hasRemaining:()Z
      30: ifeq          111
      33: aload_0
      34: aload_1
      35: invokevirtual #75                 // Method decodeHPackHeader:(Ljava/nio/ByteBuffer;)Lorg/apache/hc/core5/http2/hpack/HPackHeader;
      38: astore        5
      40: aload         5
      42: ifnonnull     48
      45: goto          111
      48: iload_2
      49: ifeq          78
      52: iload_3
      53: aload         5
      55: invokevirtual #93                 // Method org/apache/hc/core5/http2/hpack/HPackHeader.getTotalSize:()I
      58: iadd
      59: istore_3
      60: iload_3
      61: aload_0
      62: getfield      #12                 // Field maxListSize:I
      65: if_icmplt     78
      68: new           #94                 // class org/apache/hc/core5/http2/hpack/HeaderListConstraintException
      71: dup
      72: ldc           #95                 // String Maximum header list size exceeded
      74: invokespecial #96                 // Method org/apache/hc/core5/http2/hpack/HeaderListConstraintException."<init>":(Ljava/lang/String;)V
      77: athrow
      78: aload         4
      80: new           #76                 // class org/apache/hc/core5/http/message/BasicHeader
      83: dup
      84: aload         5
      86: invokevirtual #69                 // Method org/apache/hc/core5/http2/hpack/HPackHeader.getName:()Ljava/lang/String;
      89: aload         5
      91: invokevirtual #77                 // Method org/apache/hc/core5/http2/hpack/HPackHeader.getValue:()Ljava/lang/String;
      94: aload         5
      96: invokevirtual #78                 // Method org/apache/hc/core5/http2/hpack/HPackHeader.isSensitive:()Z
      99: invokespecial #79                 // Method org/apache/hc/core5/http/message/BasicHeader."<init>":(Ljava/lang/String;Ljava/lang/Object;Z)V
     102: invokeinterface #97,  2           // InterfaceMethod java/util/List.add:(Ljava/lang/Object;)Z
     107: pop
     108: goto          26
     111: aload         4
     113: areturn

  public int getMaxTableSize();
    Code:
       0: aload_0
       1: getfield      #11                 // Field maxTableSize:I
       4: ireturn

  public void setMaxTableSize(int);
    Code:
       0: iload_1
       1: ldc           #98                 // String Max table size
       3: invokestatic  #99                 // Method org/apache/hc/core5/util/Args.notNegative:(ILjava/lang/String;)I
       6: pop
       7: aload_0
       8: iload_1
       9: putfield      #11                 // Field maxTableSize:I
      12: aload_0
      13: getfield      #4                  // Field dynamicTable:Lorg/apache/hc/core5/http2/hpack/InboundDynamicTable;
      16: iload_1
      17: invokevirtual #84                 // Method org/apache/hc/core5/http2/hpack/InboundDynamicTable.setMaxSize:(I)V
      20: return

  public int getMaxListSize();
    Code:
       0: aload_0
       1: getfield      #12                 // Field maxListSize:I
       4: ireturn

  public void setMaxListSize(int);
    Code:
       0: iload_1
       1: ldc           #100                // String Max list size
       3: invokestatic  #99                 // Method org/apache/hc/core5/util/Args.notNegative:(ILjava/lang/String;)I
       6: pop
       7: aload_0
       8: iload_1
       9: putfield      #12                 // Field maxListSize:I
      12: return
}
