Compiled from "Huffman.java"
public final class org.apache.hc.core5.http2.hpack.Huffman {
  static final int[] CODES;

  static final byte[] LENGTHS;

  static final int EOS;

  static final org.apache.hc.core5.http2.hpack.HuffmanEncoder ENCODER;

  static final org.apache.hc.core5.http2.hpack.HuffmanDecoder DECODER;

  private org.apache.hc.core5.http2.hpack.Huffman();
    Code:
       0: aload_0
       1: invokespecial #1                  // Method java/lang/Object."<init>":()V
       4: return

  static {};
    Code:
       0: sipush        257
       3: newarray       int
       5: dup
       6: iconst_0
       7: sipush        8184
      10: iastore
      11: dup
      12: iconst_1
      13: ldc           #2                  // int 8388568
      15: iastore
      16: dup
      17: iconst_2
      18: ldc           #3                  // int 268435426
      20: iastore
      21: dup
      22: iconst_3
      23: ldc           #4                  // int 268435427
      25: iastore
      26: dup
      27: iconst_4
      28: ldc           #5                  // int 268435428
      30: iastore
      31: dup
      32: iconst_5
      33: ldc           #6                  // int 268435429
      35: iastore
      36: dup
      37: bipush        6
      39: ldc           #7                  // int 268435430
      41: iastore
      42: dup
      43: bipush        7
      45: ldc           #8                  // int 268435431
      47: iastore
      48: dup
      49: bipush        8
      51: ldc           #9                  // int 268435432
      53: iastore
      54: dup
      55: bipush        9
      57: ldc           #10                 // int 16777194
      59: iastore
      60: dup
      61: bipush        10
      63: ldc           #11                 // int 1073741820
      65: iastore
      66: dup
      67: bipush        11
      69: ldc           #12                 // int 268435433
      71: iastore
      72: dup
      73: bipush        12
      75: ldc           #13                 // int 268435434
      77: iastore
      78: dup
      79: bipush        13
      81: ldc           #14                 // int 1073741821
      83: iastore
      84: dup
      85: bipush        14
      87: ldc           #15                 // int 268435435
      89: iastore
      90: dup
      91: bipush        15
      93: ldc           #16                 // int 268435436
      95: iastore
      96: dup
      97: bipush        16
      99: ldc           #17                 // int 268435437
     101: iastore
     102: dup
     103: bipush        17
     105: ldc           #18                 // int 268435438
     107: iastore
     108: dup
     109: bipush        18
     111: ldc           #19                 // int 268435439
     113: iastore
     114: dup
     115: bipush        19
     117: ldc           #20                 // int 268435440
     119: iastore
     120: dup
     121: bipush        20
     123: ldc           #21                 // int 268435441
     125: iastore
     126: dup
     127: bipush        21
     129: ldc           #22                 // int 268435442
     131: iastore
     132: dup
     133: bipush        22
     135: ldc           #23                 // int 1073741822
     137: iastore
     138: dup
     139: bipush        23
     141: ldc           #24                 // int 268435443
     143: iastore
     144: dup
     145: bipush        24
     147: ldc           #25                 // int 268435444
     149: iastore
     150: dup
     151: bipush        25
     153: ldc           #26                 // int 268435445
     155: iastore
     156: dup
     157: bipush        26
     159: ldc           #27                 // int 268435446
     161: iastore
     162: dup
     163: bipush        27
     165: ldc           #28                 // int 268435447
     167: iastore
     168: dup
     169: bipush        28
     171: ldc           #29                 // int 268435448
     173: iastore
     174: dup
     175: bipush        29
     177: ldc           #30                 // int 268435449
     179: iastore
     180: dup
     181: bipush        30
     183: ldc           #31                 // int 268435450
     185: iastore
     186: dup
     187: bipush        31
     189: ldc           #32                 // int 268435451
     191: iastore
     192: dup
     193: bipush        32
     195: bipush        20
     197: iastore
     198: dup
     199: bipush        33
     201: sipush        1016
     204: iastore
     205: dup
     206: bipush        34
     208: sipush        1017
     211: iastore
     212: dup
     213: bipush        35
     215: sipush        4090
     218: iastore
     219: dup
     220: bipush        36
     222: sipush        8185
     225: iastore
     226: dup
     227: bipush        37
     229: bipush        21
     231: iastore
     232: dup
     233: bipush        38
     235: sipush        248
     238: iastore
     239: dup
     240: bipush        39
     242: sipush        2042
     245: iastore
     246: dup
     247: bipush        40
     249: sipush        1018
     252: iastore
     253: dup
     254: bipush        41
     256: sipush        1019
     259: iastore
     260: dup
     261: bipush        42
     263: sipush        249
     266: iastore
     267: dup
     268: bipush        43
     270: sipush        2043
     273: iastore
     274: dup
     275: bipush        44
     277: sipush        250
     280: iastore
     281: dup
     282: bipush        45
     284: bipush        22
     286: iastore
     287: dup
     288: bipush        46
     290: bipush        23
     292: iastore
     293: dup
     294: bipush        47
     296: bipush        24
     298: iastore
     299: dup
     300: bipush        48
     302: iconst_0
     303: iastore
     304: dup
     305: bipush        49
     307: iconst_1
     308: iastore
     309: dup
     310: bipush        50
     312: iconst_2
     313: iastore
     314: dup
     315: bipush        51
     317: bipush        25
     319: iastore
     320: dup
     321: bipush        52
     323: bipush        26
     325: iastore
     326: dup
     327: bipush        53
     329: bipush        27
     331: iastore
     332: dup
     333: bipush        54
     335: bipush        28
     337: iastore
     338: dup
     339: bipush        55
     341: bipush        29
     343: iastore
     344: dup
     345: bipush        56
     347: bipush        30
     349: iastore
     350: dup
     351: bipush        57
     353: bipush        31
     355: iastore
     356: dup
     357: bipush        58
     359: bipush        92
     361: iastore
     362: dup
     363: bipush        59
     365: sipush        251
     368: iastore
     369: dup
     370: bipush        60
     372: sipush        32764
     375: iastore
     376: dup
     377: bipush        61
     379: bipush        32
     381: iastore
     382: dup
     383: bipush        62
     385: sipush        4091
     388: iastore
     389: dup
     390: bipush        63
     392: sipush        1020
     395: iastore
     396: dup
     397: bipush        64
     399: sipush        8186
     402: iastore
     403: dup
     404: bipush        65
     406: bipush        33
     408: iastore
     409: dup
     410: bipush        66
     412: bipush        93
     414: iastore
     415: dup
     416: bipush        67
     418: bipush        94
     420: iastore
     421: dup
     422: bipush        68
     424: bipush        95
     426: iastore
     427: dup
     428: bipush        69
     430: bipush        96
     432: iastore
     433: dup
     434: bipush        70
     436: bipush        97
     438: iastore
     439: dup
     440: bipush        71
     442: bipush        98
     444: iastore
     445: dup
     446: bipush        72
     448: bipush        99
     450: iastore
     451: dup
     452: bipush        73
     454: bipush        100
     456: iastore
     457: dup
     458: bipush        74
     460: bipush        101
     462: iastore
     463: dup
     464: bipush        75
     466: bipush        102
     468: iastore
     469: dup
     470: bipush        76
     472: bipush        103
     474: iastore
     475: dup
     476: bipush        77
     478: bipush        104
     480: iastore
     481: dup
     482: bipush        78
     484: bipush        105
     486: iastore
     487: dup
     488: bipush        79
     490: bipush        106
     492: iastore
     493: dup
     494: bipush        80
     496: bipush        107
     498: iastore
     499: dup
     500: bipush        81
     502: bipush        108
     504: iastore
     505: dup
     506: bipush        82
     508: bipush        109
     510: iastore
     511: dup
     512: bipush        83
     514: bipush        110
     516: iastore
     517: dup
     518: bipush        84
     520: bipush        111
     522: iastore
     523: dup
     524: bipush        85
     526: bipush        112
     528: iastore
     529: dup
     530: bipush        86
     532: bipush        113
     534: iastore
     535: dup
     536: bipush        87
     538: bipush        114
     540: iastore
     541: dup
     542: bipush        88
     544: sipush        252
     547: iastore
     548: dup
     549: bipush        89
     551: bipush        115
     553: iastore
     554: dup
     555: bipush        90
     557: sipush        253
     560: iastore
     561: dup
     562: bipush        91
     564: sipush        8187
     567: iastore
     568: dup
     569: bipush        92
     571: ldc           #33                 // int 524272
     573: iastore
     574: dup
     575: bipush        93
     577: sipush        8188
     580: iastore
     581: dup
     582: bipush        94
     584: sipush        16380
     587: iastore
     588: dup
     589: bipush        95
     591: bipush        34
     593: iastore
     594: dup
     595: bipush        96
     597: sipush        32765
     600: iastore
     601: dup
     602: bipush        97
     604: iconst_3
     605: iastore
     606: dup
     607: bipush        98
     609: bipush        35
     611: iastore
     612: dup
     613: bipush        99
     615: iconst_4
     616: iastore
     617: dup
     618: bipush        100
     620: bipush        36
     622: iastore
     623: dup
     624: bipush        101
     626: iconst_5
     627: iastore
     628: dup
     629: bipush        102
     631: bipush        37
     633: iastore
     634: dup
     635: bipush        103
     637: bipush        38
     639: iastore
     640: dup
     641: bipush        104
     643: bipush        39
     645: iastore
     646: dup
     647: bipush        105
     649: bipush        6
     651: iastore
     652: dup
     653: bipush        106
     655: bipush        116
     657: iastore
     658: dup
     659: bipush        107
     661: bipush        117
     663: iastore
     664: dup
     665: bipush        108
     667: bipush        40
     669: iastore
     670: dup
     671: bipush        109
     673: bipush        41
     675: iastore
     676: dup
     677: bipush        110
     679: bipush        42
     681: iastore
     682: dup
     683: bipush        111
     685: bipush        7
     687: iastore
     688: dup
     689: bipush        112
     691: bipush        43
     693: iastore
     694: dup
     695: bipush        113
     697: bipush        118
     699: iastore
     700: dup
     701: bipush        114
     703: bipush        44
     705: iastore
     706: dup
     707: bipush        115
     709: bipush        8
     711: iastore
     712: dup
     713: bipush        116
     715: bipush        9
     717: iastore
     718: dup
     719: bipush        117
     721: bipush        45
     723: iastore
     724: dup
     725: bipush        118
     727: bipush        119
     729: iastore
     730: dup
     731: bipush        119
     733: bipush        120
     735: iastore
     736: dup
     737: bipush        120
     739: bipush        121
     741: iastore
     742: dup
     743: bipush        121
     745: bipush        122
     747: iastore
     748: dup
     749: bipush        122
     751: bipush        123
     753: iastore
     754: dup
     755: bipush        123
     757: sipush        32766
     760: iastore
     761: dup
     762: bipush        124
     764: sipush        2044
     767: iastore
     768: dup
     769: bipush        125
     771: sipush        16381
     774: iastore
     775: dup
     776: bipush        126
     778: sipush        8189
     781: iastore
     782: dup
     783: bipush        127
     785: ldc           #34                 // int 268435452
     787: iastore
     788: dup
     789: sipush        128
     792: ldc           #35                 // int 1048550
     794: iastore
     795: dup
     796: sipush        129
     799: ldc           #36                 // int 4194258
     801: iastore
     802: dup
     803: sipush        130
     806: ldc           #37                 // int 1048551
     808: iastore
     809: dup
     810: sipush        131
     813: ldc           #38                 // int 1048552
     815: iastore
     816: dup
     817: sipush        132
     820: ldc           #39                 // int 4194259
     822: iastore
     823: dup
     824: sipush        133
     827: ldc           #40                 // int 4194260
     829: iastore
     830: dup
     831: sipush        134
     834: ldc           #41                 // int 4194261
     836: iastore
     837: dup
     838: sipush        135
     841: ldc           #42                 // int 8388569
     843: iastore
     844: dup
     845: sipush        136
     848: ldc           #43                 // int 4194262
     850: iastore
     851: dup
     852: sipush        137
     855: ldc           #44                 // int 8388570
     857: iastore
     858: dup
     859: sipush        138
     862: ldc           #45                 // int 8388571
     864: iastore
     865: dup
     866: sipush        139
     869: ldc           #46                 // int 8388572
     871: iastore
     872: dup
     873: sipush        140
     876: ldc           #47                 // int 8388573
     878: iastore
     879: dup
     880: sipush        141
     883: ldc           #48                 // int 8388574
     885: iastore
     886: dup
     887: sipush        142
     890: ldc           #49                 // int 16777195
     892: iastore
     893: dup
     894: sipush        143
     897: ldc           #50                 // int 8388575
     899: iastore
     900: dup
     901: sipush        144
     904: ldc           #51                 // int 16777196
     906: iastore
     907: dup
     908: sipush        145
     911: ldc           #52                 // int 16777197
     913: iastore
     914: dup
     915: sipush        146
     918: ldc           #53                 // int 4194263
     920: iastore
     921: dup
     922: sipush        147
     925: ldc           #54                 // int 8388576
     927: iastore
     928: dup
     929: sipush        148
     932: ldc           #55                 // int 16777198
     934: iastore
     935: dup
     936: sipush        149
     939: ldc           #56                 // int 8388577
     941: iastore
     942: dup
     943: sipush        150
     946: ldc           #57                 // int 8388578
     948: iastore
     949: dup
     950: sipush        151
     953: ldc           #58                 // int 8388579
     955: iastore
     956: dup
     957: sipush        152
     960: ldc           #59                 // int 8388580
     962: iastore
     963: dup
     964: sipush        153
     967: ldc           #60                 // int 2097116
     969: iastore
     970: dup
     971: sipush        154
     974: ldc           #61                 // int 4194264
     976: iastore
     977: dup
     978: sipush        155
     981: ldc           #62                 // int 8388581
     983: iastore
     984: dup
     985: sipush        156
     988: ldc           #63                 // int 4194265
     990: iastore
     991: dup
     992: sipush        157
     995: ldc           #64                 // int 8388582
     997: iastore
     998: dup
     999: sipush        158
    1002: ldc           #65                 // int 8388583
    1004: iastore
    1005: dup
    1006: sipush        159
    1009: ldc           #66                 // int 16777199
    1011: iastore
    1012: dup
    1013: sipush        160
    1016: ldc           #67                 // int 4194266
    1018: iastore
    1019: dup
    1020: sipush        161
    1023: ldc           #68                 // int 2097117
    1025: iastore
    1026: dup
    1027: sipush        162
    1030: ldc           #69                 // int 1048553
    1032: iastore
    1033: dup
    1034: sipush        163
    1037: ldc           #70                 // int 4194267
    1039: iastore
    1040: dup
    1041: sipush        164
    1044: ldc           #71                 // int 4194268
    1046: iastore
    1047: dup
    1048: sipush        165
    1051: ldc           #72                 // int 8388584
    1053: iastore
    1054: dup
    1055: sipush        166
    1058: ldc           #73                 // int 8388585
    1060: iastore
    1061: dup
    1062: sipush        167
    1065: ldc           #74                 // int 2097118
    1067: iastore
    1068: dup
    1069: sipush        168
    1072: ldc           #75                 // int 8388586
    1074: iastore
    1075: dup
    1076: sipush        169
    1079: ldc           #76                 // int 4194269
    1081: iastore
    1082: dup
    1083: sipush        170
    1086: ldc           #77                 // int 4194270
    1088: iastore
    1089: dup
    1090: sipush        171
    1093: ldc           #78                 // int 16777200
    1095: iastore
    1096: dup
    1097: sipush        172
    1100: ldc           #79                 // int 2097119
    1102: iastore
    1103: dup
    1104: sipush        173
    1107: ldc           #80                 // int 4194271
    1109: iastore
    1110: dup
    1111: sipush        174
    1114: ldc           #81                 // int 8388587
    1116: iastore
    1117: dup
    1118: sipush        175
    1121: ldc           #82                 // int 8388588
    1123: iastore
    1124: dup
    1125: sipush        176
    1128: ldc           #83                 // int 2097120
    1130: iastore
    1131: dup
    1132: sipush        177
    1135: ldc           #84                 // int 2097121
    1137: iastore
    1138: dup
    1139: sipush        178
    1142: ldc           #85                 // int 4194272
    1144: iastore
    1145: dup
    1146: sipush        179
    1149: ldc           #86                 // int 2097122
    1151: iastore
    1152: dup
    1153: sipush        180
    1156: ldc           #87                 // int 8388589
    1158: iastore
    1159: dup
    1160: sipush        181
    1163: ldc           #88                 // int 4194273
    1165: iastore
    1166: dup
    1167: sipush        182
    1170: ldc           #89                 // int 8388590
    1172: iastore
    1173: dup
    1174: sipush        183
    1177: ldc           #90                 // int 8388591
    1179: iastore
    1180: dup
    1181: sipush        184
    1184: ldc           #91                 // int 1048554
    1186: iastore
    1187: dup
    1188: sipush        185
    1191: ldc           #92                 // int 4194274
    1193: iastore
    1194: dup
    1195: sipush        186
    1198: ldc           #93                 // int 4194275
    1200: iastore
    1201: dup
    1202: sipush        187
    1205: ldc           #94                 // int 4194276
    1207: iastore
    1208: dup
    1209: sipush        188
    1212: ldc           #95                 // int 8388592
    1214: iastore
    1215: dup
    1216: sipush        189
    1219: ldc           #96                 // int 4194277
    1221: iastore
    1222: dup
    1223: sipush        190
    1226: ldc           #97                 // int 4194278
    1228: iastore
    1229: dup
    1230: sipush        191
    1233: ldc           #98                 // int 8388593
    1235: iastore
    1236: dup
    1237: sipush        192
    1240: ldc           #99                 // int 67108832
    1242: iastore
    1243: dup
    1244: sipush        193
    1247: ldc           #100                // int 67108833
    1249: iastore
    1250: dup
    1251: sipush        194
    1254: ldc           #101                // int 1048555
    1256: iastore
    1257: dup
    1258: sipush        195
    1261: ldc           #102                // int 524273
    1263: iastore
    1264: dup
    1265: sipush        196
    1268: ldc           #103                // int 4194279
    1270: iastore
    1271: dup
    1272: sipush        197
    1275: ldc           #104                // int 8388594
    1277: iastore
    1278: dup
    1279: sipush        198
    1282: ldc           #105                // int 4194280
    1284: iastore
    1285: dup
    1286: sipush        199
    1289: ldc           #106                // int 33554412
    1291: iastore
    1292: dup
    1293: sipush        200
    1296: ldc           #107                // int 67108834
    1298: iastore
    1299: dup
    1300: sipush        201
    1303: ldc           #108                // int 67108835
    1305: iastore
    1306: dup
    1307: sipush        202
    1310: ldc           #109                // int 67108836
    1312: iastore
    1313: dup
    1314: sipush        203
    1317: ldc           #110                // int 134217694
    1319: iastore
    1320: dup
    1321: sipush        204
    1324: ldc           #111                // int 134217695
    1326: iastore
    1327: dup
    1328: sipush        205
    1331: ldc           #112                // int 67108837
    1333: iastore
    1334: dup
    1335: sipush        206
    1338: ldc           #113                // int 16777201
    1340: iastore
    1341: dup
    1342: sipush        207
    1345: ldc           #114                // int 33554413
    1347: iastore
    1348: dup
    1349: sipush        208
    1352: ldc           #115                // int 524274
    1354: iastore
    1355: dup
    1356: sipush        209
    1359: ldc           #116                // int 2097123
    1361: iastore
    1362: dup
    1363: sipush        210
    1366: ldc           #117                // int 67108838
    1368: iastore
    1369: dup
    1370: sipush        211
    1373: ldc           #118                // int 134217696
    1375: iastore
    1376: dup
    1377: sipush        212
    1380: ldc           #119                // int 134217697
    1382: iastore
    1383: dup
    1384: sipush        213
    1387: ldc           #120                // int 67108839
    1389: iastore
    1390: dup
    1391: sipush        214
    1394: ldc           #121                // int 134217698
    1396: iastore
    1397: dup
    1398: sipush        215
    1401: ldc           #122                // int 16777202
    1403: iastore
    1404: dup
    1405: sipush        216
    1408: ldc           #123                // int 2097124
    1410: iastore
    1411: dup
    1412: sipush        217
    1415: ldc           #124                // int 2097125
    1417: iastore
    1418: dup
    1419: sipush        218
    1422: ldc           #125                // int 67108840
    1424: iastore
    1425: dup
    1426: sipush        219
    1429: ldc           #126                // int 67108841
    1431: iastore
    1432: dup
    1433: sipush        220
    1436: ldc           #127                // int 268435453
    1438: iastore
    1439: dup
    1440: sipush        221
    1443: ldc           #128                // int 134217699
    1445: iastore
    1446: dup
    1447: sipush        222
    1450: ldc           #129                // int 134217700
    1452: iastore
    1453: dup
    1454: sipush        223
    1457: ldc           #130                // int 134217701
    1459: iastore
    1460: dup
    1461: sipush        224
    1464: ldc           #131                // int 1048556
    1466: iastore
    1467: dup
    1468: sipush        225
    1471: ldc           #132                // int 16777203
    1473: iastore
    1474: dup
    1475: sipush        226
    1478: ldc           #133                // int 1048557
    1480: iastore
    1481: dup
    1482: sipush        227
    1485: ldc           #134                // int 2097126
    1487: iastore
    1488: dup
    1489: sipush        228
    1492: ldc           #135                // int 4194281
    1494: iastore
    1495: dup
    1496: sipush        229
    1499: ldc           #136                // int 2097127
    1501: iastore
    1502: dup
    1503: sipush        230
    1506: ldc           #137                // int 2097128
    1508: iastore
    1509: dup
    1510: sipush        231
    1513: ldc           #138                // int 8388595
    1515: iastore
    1516: dup
    1517: sipush        232
    1520: ldc           #139                // int 4194282
    1522: iastore
    1523: dup
    1524: sipush        233
    1527: ldc           #140                // int 4194283
    1529: iastore
    1530: dup
    1531: sipush        234
    1534: ldc           #141                // int 33554414
    1536: iastore
    1537: dup
    1538: sipush        235
    1541: ldc           #142                // int 33554415
    1543: iastore
    1544: dup
    1545: sipush        236
    1548: ldc           #143                // int 16777204
    1550: iastore
    1551: dup
    1552: sipush        237
    1555: ldc           #144                // int 16777205
    1557: iastore
    1558: dup
    1559: sipush        238
    1562: ldc           #145                // int 67108842
    1564: iastore
    1565: dup
    1566: sipush        239
    1569: ldc           #146                // int 8388596
    1571: iastore
    1572: dup
    1573: sipush        240
    1576: ldc           #147                // int 67108843
    1578: iastore
    1579: dup
    1580: sipush        241
    1583: ldc           #148                // int 134217702
    1585: iastore
    1586: dup
    1587: sipush        242
    1590: ldc           #149                // int 67108844
    1592: iastore
    1593: dup
    1594: sipush        243
    1597: ldc           #150                // int 67108845
    1599: iastore
    1600: dup
    1601: sipush        244
    1604: ldc           #151                // int 134217703
    1606: iastore
    1607: dup
    1608: sipush        245
    1611: ldc           #152                // int 134217704
    1613: iastore
    1614: dup
    1615: sipush        246
    1618: ldc           #153                // int 134217705
    1620: iastore
    1621: dup
    1622: sipush        247
    1625: ldc           #154                // int 134217706
    1627: iastore
    1628: dup
    1629: sipush        248
    1632: ldc           #155                // int 134217707
    1634: iastore
    1635: dup
    1636: sipush        249
    1639: ldc           #156                // int 268435454
    1641: iastore
    1642: dup
    1643: sipush        250
    1646: ldc           #157                // int 134217708
    1648: iastore
    1649: dup
    1650: sipush        251
    1653: ldc           #158                // int 134217709
    1655: iastore
    1656: dup
    1657: sipush        252
    1660: ldc           #159                // int 134217710
    1662: iastore
    1663: dup
    1664: sipush        253
    1667: ldc           #160                // int 134217711
    1669: iastore
    1670: dup
    1671: sipush        254
    1674: ldc           #161                // int 134217712
    1676: iastore
    1677: dup
    1678: sipush        255
    1681: ldc           #162                // int 67108846
    1683: iastore
    1684: dup
    1685: sipush        256
    1688: ldc           #163                // int 1073741823
    1690: iastore
    1691: putstatic     #164                // Field CODES:[I
    1694: sipush        257
    1697: newarray       byte
    1699: dup
    1700: iconst_0
    1701: bipush        13
    1703: bastore
    1704: dup
    1705: iconst_1
    1706: bipush        23
    1708: bastore
    1709: dup
    1710: iconst_2
    1711: bipush        28
    1713: bastore
    1714: dup
    1715: iconst_3
    1716: bipush        28
    1718: bastore
    1719: dup
    1720: iconst_4
    1721: bipush        28
    1723: bastore
    1724: dup
    1725: iconst_5
    1726: bipush        28
    1728: bastore
    1729: dup
    1730: bipush        6
    1732: bipush        28
    1734: bastore
    1735: dup
    1736: bipush        7
    1738: bipush        28
    1740: bastore
    1741: dup
    1742: bipush        8
    1744: bipush        28
    1746: bastore
    1747: dup
    1748: bipush        9
    1750: bipush        24
    1752: bastore
    1753: dup
    1754: bipush        10
    1756: bipush        30
    1758: bastore
    1759: dup
    1760: bipush        11
    1762: bipush        28
    1764: bastore
    1765: dup
    1766: bipush        12
    1768: bipush        28
    1770: bastore
    1771: dup
    1772: bipush        13
    1774: bipush        30
    1776: bastore
    1777: dup
    1778: bipush        14
    1780: bipush        28
    1782: bastore
    1783: dup
    1784: bipush        15
    1786: bipush        28
    1788: bastore
    1789: dup
    1790: bipush        16
    1792: bipush        28
    1794: bastore
    1795: dup
    1796: bipush        17
    1798: bipush        28
    1800: bastore
    1801: dup
    1802: bipush        18
    1804: bipush        28
    1806: bastore
    1807: dup
    1808: bipush        19
    1810: bipush        28
    1812: bastore
    1813: dup
    1814: bipush        20
    1816: bipush        28
    1818: bastore
    1819: dup
    1820: bipush        21
    1822: bipush        28
    1824: bastore
    1825: dup
    1826: bipush        22
    1828: bipush        30
    1830: bastore
    1831: dup
    1832: bipush        23
    1834: bipush        28
    1836: bastore
    1837: dup
    1838: bipush        24
    1840: bipush        28
    1842: bastore
    1843: dup
    1844: bipush        25
    1846: bipush        28
    1848: bastore
    1849: dup
    1850: bipush        26
    1852: bipush        28
    1854: bastore
    1855: dup
    1856: bipush        27
    1858: bipush        28
    1860: bastore
    1861: dup
    1862: bipush        28
    1864: bipush        28
    1866: bastore
    1867: dup
    1868: bipush        29
    1870: bipush        28
    1872: bastore
    1873: dup
    1874: bipush        30
    1876: bipush        28
    1878: bastore
    1879: dup
    1880: bipush        31
    1882: bipush        28
    1884: bastore
    1885: dup
    1886: bipush        32
    1888: bipush        6
    1890: bastore
    1891: dup
    1892: bipush        33
    1894: bipush        10
    1896: bastore
    1897: dup
    1898: bipush        34
    1900: bipush        10
    1902: bastore
    1903: dup
    1904: bipush        35
    1906: bipush        12
    1908: bastore
    1909: dup
    1910: bipush        36
    1912: bipush        13
    1914: bastore
    1915: dup
    1916: bipush        37
    1918: bipush        6
    1920: bastore
    1921: dup
    1922: bipush        38
    1924: bipush        8
    1926: bastore
    1927: dup
    1928: bipush        39
    1930: bipush        11
    1932: bastore
    1933: dup
    1934: bipush        40
    1936: bipush        10
    1938: bastore
    1939: dup
    1940: bipush        41
    1942: bipush        10
    1944: bastore
    1945: dup
    1946: bipush        42
    1948: bipush        8
    1950: bastore
    1951: dup
    1952: bipush        43
    1954: bipush        11
    1956: bastore
    1957: dup
    1958: bipush        44
    1960: bipush        8
    1962: bastore
    1963: dup
    1964: bipush        45
    1966: bipush        6
    1968: bastore
    1969: dup
    1970: bipush        46
    1972: bipush        6
    1974: bastore
    1975: dup
    1976: bipush        47
    1978: bipush        6
    1980: bastore
    1981: dup
    1982: bipush        48
    1984: iconst_5
    1985: bastore
    1986: dup
    1987: bipush        49
    1989: iconst_5
    1990: bastore
    1991: dup
    1992: bipush        50
    1994: iconst_5
    1995: bastore
    1996: dup
    1997: bipush        51
    1999: bipush        6
    2001: bastore
    2002: dup
    2003: bipush        52
    2005: bipush        6
    2007: bastore
    2008: dup
    2009: bipush        53
    2011: bipush        6
    2013: bastore
    2014: dup
    2015: bipush        54
    2017: bipush        6
    2019: bastore
    2020: dup
    2021: bipush        55
    2023: bipush        6
    2025: bastore
    2026: dup
    2027: bipush        56
    2029: bipush        6
    2031: bastore
    2032: dup
    2033: bipush        57
    2035: bipush        6
    2037: bastore
    2038: dup
    2039: bipush        58
    2041: bipush        7
    2043: bastore
    2044: dup
    2045: bipush        59
    2047: bipush        8
    2049: bastore
    2050: dup
    2051: bipush        60
    2053: bipush        15
    2055: bastore
    2056: dup
    2057: bipush        61
    2059: bipush        6
    2061: bastore
    2062: dup
    2063: bipush        62
    2065: bipush        12
    2067: bastore
    2068: dup
    2069: bipush        63
    2071: bipush        10
    2073: bastore
    2074: dup
    2075: bipush        64
    2077: bipush        13
    2079: bastore
    2080: dup
    2081: bipush        65
    2083: bipush        6
    2085: bastore
    2086: dup
    2087: bipush        66
    2089: bipush        7
    2091: bastore
    2092: dup
    2093: bipush        67
    2095: bipush        7
    2097: bastore
    2098: dup
    2099: bipush        68
    2101: bipush        7
    2103: bastore
    2104: dup
    2105: bipush        69
    2107: bipush        7
    2109: bastore
    2110: dup
    2111: bipush        70
    2113: bipush        7
    2115: bastore
    2116: dup
    2117: bipush        71
    2119: bipush        7
    2121: bastore
    2122: dup
    2123: bipush        72
    2125: bipush        7
    2127: bastore
    2128: dup
    2129: bipush        73
    2131: bipush        7
    2133: bastore
    2134: dup
    2135: bipush        74
    2137: bipush        7
    2139: bastore
    2140: dup
    2141: bipush        75
    2143: bipush        7
    2145: bastore
    2146: dup
    2147: bipush        76
    2149: bipush        7
    2151: bastore
    2152: dup
    2153: bipush        77
    2155: bipush        7
    2157: bastore
    2158: dup
    2159: bipush        78
    2161: bipush        7
    2163: bastore
    2164: dup
    2165: bipush        79
    2167: bipush        7
    2169: bastore
    2170: dup
    2171: bipush        80
    2173: bipush        7
    2175: bastore
    2176: dup
    2177: bipush        81
    2179: bipush        7
    2181: bastore
    2182: dup
    2183: bipush        82
    2185: bipush        7
    2187: bastore
    2188: dup
    2189: bipush        83
    2191: bipush        7
    2193: bastore
    2194: dup
    2195: bipush        84
    2197: bipush        7
    2199: bastore
    2200: dup
    2201: bipush        85
    2203: bipush        7
    2205: bastore
    2206: dup
    2207: bipush        86
    2209: bipush        7
    2211: bastore
    2212: dup
    2213: bipush        87
    2215: bipush        7
    2217: bastore
    2218: dup
    2219: bipush        88
    2221: bipush        8
    2223: bastore
    2224: dup
    2225: bipush        89
    2227: bipush        7
    2229: bastore
    2230: dup
    2231: bipush        90
    2233: bipush        8
    2235: bastore
    2236: dup
    2237: bipush        91
    2239: bipush        13
    2241: bastore
    2242: dup
    2243: bipush        92
    2245: bipush        19
    2247: bastore
    2248: dup
    2249: bipush        93
    2251: bipush        13
    2253: bastore
    2254: dup
    2255: bipush        94
    2257: bipush        14
    2259: bastore
    2260: dup
    2261: bipush        95
    2263: bipush        6
    2265: bastore
    2266: dup
    2267: bipush        96
    2269: bipush        15
    2271: bastore
    2272: dup
    2273: bipush        97
    2275: iconst_5
    2276: bastore
    2277: dup
    2278: bipush        98
    2280: bipush        6
    2282: bastore
    2283: dup
    2284: bipush        99
    2286: iconst_5
    2287: bastore
    2288: dup
    2289: bipush        100
    2291: bipush        6
    2293: bastore
    2294: dup
    2295: bipush        101
    2297: iconst_5
    2298: bastore
    2299: dup
    2300: bipush        102
    2302: bipush        6
    2304: bastore
    2305: dup
    2306: bipush        103
    2308: bipush        6
    2310: bastore
    2311: dup
    2312: bipush        104
    2314: bipush        6
    2316: bastore
    2317: dup
    2318: bipush        105
    2320: iconst_5
    2321: bastore
    2322: dup
    2323: bipush        106
    2325: bipush        7
    2327: bastore
    2328: dup
    2329: bipush        107
    2331: bipush        7
    2333: bastore
    2334: dup
    2335: bipush        108
    2337: bipush        6
    2339: bastore
    2340: dup
    2341: bipush        109
    2343: bipush        6
    2345: bastore
    2346: dup
    2347: bipush        110
    2349: bipush        6
    2351: bastore
    2352: dup
    2353: bipush        111
    2355: iconst_5
    2356: bastore
    2357: dup
    2358: bipush        112
    2360: bipush        6
    2362: bastore
    2363: dup
    2364: bipush        113
    2366: bipush        7
    2368: bastore
    2369: dup
    2370: bipush        114
    2372: bipush        6
    2374: bastore
    2375: dup
    2376: bipush        115
    2378: iconst_5
    2379: bastore
    2380: dup
    2381: bipush        116
    2383: iconst_5
    2384: bastore
    2385: dup
    2386: bipush        117
    2388: bipush        6
    2390: bastore
    2391: dup
    2392: bipush        118
    2394: bipush        7
    2396: bastore
    2397: dup
    2398: bipush        119
    2400: bipush        7
    2402: bastore
    2403: dup
    2404: bipush        120
    2406: bipush        7
    2408: bastore
    2409: dup
    2410: bipush        121
    2412: bipush        7
    2414: bastore
    2415: dup
    2416: bipush        122
    2418: bipush        7
    2420: bastore
    2421: dup
    2422: bipush        123
    2424: bipush        15
    2426: bastore
    2427: dup
    2428: bipush        124
    2430: bipush        11
    2432: bastore
    2433: dup
    2434: bipush        125
    2436: bipush        14
    2438: bastore
    2439: dup
    2440: bipush        126
    2442: bipush        13
    2444: bastore
    2445: dup
    2446: bipush        127
    2448: bipush        28
    2450: bastore
    2451: dup
    2452: sipush        128
    2455: bipush        20
    2457: bastore
    2458: dup
    2459: sipush        129
    2462: bipush        22
    2464: bastore
    2465: dup
    2466: sipush        130
    2469: bipush        20
    2471: bastore
    2472: dup
    2473: sipush        131
    2476: bipush        20
    2478: bastore
    2479: dup
    2480: sipush        132
    2483: bipush        22
    2485: bastore
    2486: dup
    2487: sipush        133
    2490: bipush        22
    2492: bastore
    2493: dup
    2494: sipush        134
    2497: bipush        22
    2499: bastore
    2500: dup
    2501: sipush        135
    2504: bipush        23
    2506: bastore
    2507: dup
    2508: sipush        136
    2511: bipush        22
    2513: bastore
    2514: dup
    2515: sipush        137
    2518: bipush        23
    2520: bastore
    2521: dup
    2522: sipush        138
    2525: bipush        23
    2527: bastore
    2528: dup
    2529: sipush        139
    2532: bipush        23
    2534: bastore
    2535: dup
    2536: sipush        140
    2539: bipush        23
    2541: bastore
    2542: dup
    2543: sipush        141
    2546: bipush        23
    2548: bastore
    2549: dup
    2550: sipush        142
    2553: bipush        24
    2555: bastore
    2556: dup
    2557: sipush        143
    2560: bipush        23
    2562: bastore
    2563: dup
    2564: sipush        144
    2567: bipush        24
    2569: bastore
    2570: dup
    2571: sipush        145
    2574: bipush        24
    2576: bastore
    2577: dup
    2578: sipush        146
    2581: bipush        22
    2583: bastore
    2584: dup
    2585: sipush        147
    2588: bipush        23
    2590: bastore
    2591: dup
    2592: sipush        148
    2595: bipush        24
    2597: bastore
    2598: dup
    2599: sipush        149
    2602: bipush        23
    2604: bastore
    2605: dup
    2606: sipush        150
    2609: bipush        23
    2611: bastore
    2612: dup
    2613: sipush        151
    2616: bipush        23
    2618: bastore
    2619: dup
    2620: sipush        152
    2623: bipush        23
    2625: bastore
    2626: dup
    2627: sipush        153
    2630: bipush        21
    2632: bastore
    2633: dup
    2634: sipush        154
    2637: bipush        22
    2639: bastore
    2640: dup
    2641: sipush        155
    2644: bipush        23
    2646: bastore
    2647: dup
    2648: sipush        156
    2651: bipush        22
    2653: bastore
    2654: dup
    2655: sipush        157
    2658: bipush        23
    2660: bastore
    2661: dup
    2662: sipush        158
    2665: bipush        23
    2667: bastore
    2668: dup
    2669: sipush        159
    2672: bipush        24
    2674: bastore
    2675: dup
    2676: sipush        160
    2679: bipush        22
    2681: bastore
    2682: dup
    2683: sipush        161
    2686: bipush        21
    2688: bastore
    2689: dup
    2690: sipush        162
    2693: bipush        20
    2695: bastore
    2696: dup
    2697: sipush        163
    2700: bipush        22
    2702: bastore
    2703: dup
    2704: sipush        164
    2707: bipush        22
    2709: bastore
    2710: dup
    2711: sipush        165
    2714: bipush        23
    2716: bastore
    2717: dup
    2718: sipush        166
    2721: bipush        23
    2723: bastore
    2724: dup
    2725: sipush        167
    2728: bipush        21
    2730: bastore
    2731: dup
    2732: sipush        168
    2735: bipush        23
    2737: bastore
    2738: dup
    2739: sipush        169
    2742: bipush        22
    2744: bastore
    2745: dup
    2746: sipush        170
    2749: bipush        22
    2751: bastore
    2752: dup
    2753: sipush        171
    2756: bipush        24
    2758: bastore
    2759: dup
    2760: sipush        172
    2763: bipush        21
    2765: bastore
    2766: dup
    2767: sipush        173
    2770: bipush        22
    2772: bastore
    2773: dup
    2774: sipush        174
    2777: bipush        23
    2779: bastore
    2780: dup
    2781: sipush        175
    2784: bipush        23
    2786: bastore
    2787: dup
    2788: sipush        176
    2791: bipush        21
    2793: bastore
    2794: dup
    2795: sipush        177
    2798: bipush        21
    2800: bastore
    2801: dup
    2802: sipush        178
    2805: bipush        22
    2807: bastore
    2808: dup
    2809: sipush        179
    2812: bipush        21
    2814: bastore
    2815: dup
    2816: sipush        180
    2819: bipush        23
    2821: bastore
    2822: dup
    2823: sipush        181
    2826: bipush        22
    2828: bastore
    2829: dup
    2830: sipush        182
    2833: bipush        23
    2835: bastore
    2836: dup
    2837: sipush        183
    2840: bipush        23
    2842: bastore
    2843: dup
    2844: sipush        184
    2847: bipush        20
    2849: bastore
    2850: dup
    2851: sipush        185
    2854: bipush        22
    2856: bastore
    2857: dup
    2858: sipush        186
    2861: bipush        22
    2863: bastore
    2864: dup
    2865: sipush        187
    2868: bipush        22
    2870: bastore
    2871: dup
    2872: sipush        188
    2875: bipush        23
    2877: bastore
    2878: dup
    2879: sipush        189
    2882: bipush        22
    2884: bastore
    2885: dup
    2886: sipush        190
    2889: bipush        22
    2891: bastore
    2892: dup
    2893: sipush        191
    2896: bipush        23
    2898: bastore
    2899: dup
    2900: sipush        192
    2903: bipush        26
    2905: bastore
    2906: dup
    2907: sipush        193
    2910: bipush        26
    2912: bastore
    2913: dup
    2914: sipush        194
    2917: bipush        20
    2919: bastore
    2920: dup
    2921: sipush        195
    2924: bipush        19
    2926: bastore
    2927: dup
    2928: sipush        196
    2931: bipush        22
    2933: bastore
    2934: dup
    2935: sipush        197
    2938: bipush        23
    2940: bastore
    2941: dup
    2942: sipush        198
    2945: bipush        22
    2947: bastore
    2948: dup
    2949: sipush        199
    2952: bipush        25
    2954: bastore
    2955: dup
    2956: sipush        200
    2959: bipush        26
    2961: bastore
    2962: dup
    2963: sipush        201
    2966: bipush        26
    2968: bastore
    2969: dup
    2970: sipush        202
    2973: bipush        26
    2975: bastore
    2976: dup
    2977: sipush        203
    2980: bipush        27
    2982: bastore
    2983: dup
    2984: sipush        204
    2987: bipush        27
    2989: bastore
    2990: dup
    2991: sipush        205
    2994: bipush        26
    2996: bastore
    2997: dup
    2998: sipush        206
    3001: bipush        24
    3003: bastore
    3004: dup
    3005: sipush        207
    3008: bipush        25
    3010: bastore
    3011: dup
    3012: sipush        208
    3015: bipush        19
    3017: bastore
    3018: dup
    3019: sipush        209
    3022: bipush        21
    3024: bastore
    3025: dup
    3026: sipush        210
    3029: bipush        26
    3031: bastore
    3032: dup
    3033: sipush        211
    3036: bipush        27
    3038: bastore
    3039: dup
    3040: sipush        212
    3043: bipush        27
    3045: bastore
    3046: dup
    3047: sipush        213
    3050: bipush        26
    3052: bastore
    3053: dup
    3054: sipush        214
    3057: bipush        27
    3059: bastore
    3060: dup
    3061: sipush        215
    3064: bipush        24
    3066: bastore
    3067: dup
    3068: sipush        216
    3071: bipush        21
    3073: bastore
    3074: dup
    3075: sipush        217
    3078: bipush        21
    3080: bastore
    3081: dup
    3082: sipush        218
    3085: bipush        26
    3087: bastore
    3088: dup
    3089: sipush        219
    3092: bipush        26
    3094: bastore
    3095: dup
    3096: sipush        220
    3099: bipush        28
    3101: bastore
    3102: dup
    3103: sipush        221
    3106: bipush        27
    3108: bastore
    3109: dup
    3110: sipush        222
    3113: bipush        27
    3115: bastore
    3116: dup
    3117: sipush        223
    3120: bipush        27
    3122: bastore
    3123: dup
    3124: sipush        224
    3127: bipush        20
    3129: bastore
    3130: dup
    3131: sipush        225
    3134: bipush        24
    3136: bastore
    3137: dup
    3138: sipush        226
    3141: bipush        20
    3143: bastore
    3144: dup
    3145: sipush        227
    3148: bipush        21
    3150: bastore
    3151: dup
    3152: sipush        228
    3155: bipush        22
    3157: bastore
    3158: dup
    3159: sipush        229
    3162: bipush        21
    3164: bastore
    3165: dup
    3166: sipush        230
    3169: bipush        21
    3171: bastore
    3172: dup
    3173: sipush        231
    3176: bipush        23
    3178: bastore
    3179: dup
    3180: sipush        232
    3183: bipush        22
    3185: bastore
    3186: dup
    3187: sipush        233
    3190: bipush        22
    3192: bastore
    3193: dup
    3194: sipush        234
    3197: bipush        25
    3199: bastore
    3200: dup
    3201: sipush        235
    3204: bipush        25
    3206: bastore
    3207: dup
    3208: sipush        236
    3211: bipush        24
    3213: bastore
    3214: dup
    3215: sipush        237
    3218: bipush        24
    3220: bastore
    3221: dup
    3222: sipush        238
    3225: bipush        26
    3227: bastore
    3228: dup
    3229: sipush        239
    3232: bipush        23
    3234: bastore
    3235: dup
    3236: sipush        240
    3239: bipush        26
    3241: bastore
    3242: dup
    3243: sipush        241
    3246: bipush        27
    3248: bastore
    3249: dup
    3250: sipush        242
    3253: bipush        26
    3255: bastore
    3256: dup
    3257: sipush        243
    3260: bipush        26
    3262: bastore
    3263: dup
    3264: sipush        244
    3267: bipush        27
    3269: bastore
    3270: dup
    3271: sipush        245
    3274: bipush        27
    3276: bastore
    3277: dup
    3278: sipush        246
    3281: bipush        27
    3283: bastore
    3284: dup
    3285: sipush        247
    3288: bipush        27
    3290: bastore
    3291: dup
    3292: sipush        248
    3295: bipush        27
    3297: bastore
    3298: dup
    3299: sipush        249
    3302: bipush        28
    3304: bastore
    3305: dup
    3306: sipush        250
    3309: bipush        27
    3311: bastore
    3312: dup
    3313: sipush        251
    3316: bipush        27
    3318: bastore
    3319: dup
    3320: sipush        252
    3323: bipush        27
    3325: bastore
    3326: dup
    3327: sipush        253
    3330: bipush        27
    3332: bastore
    3333: dup
    3334: sipush        254
    3337: bipush        27
    3339: bastore
    3340: dup
    3341: sipush        255
    3344: bipush        26
    3346: bastore
    3347: dup
    3348: sipush        256
    3351: bipush        30
    3353: bastore
    3354: putstatic     #165                // Field LENGTHS:[B
    3357: new           #166                // class org/apache/hc/core5/http2/hpack/HuffmanEncoder
    3360: dup
    3361: getstatic     #164                // Field CODES:[I
    3364: getstatic     #165                // Field LENGTHS:[B
    3367: invokespecial #167                // Method org/apache/hc/core5/http2/hpack/HuffmanEncoder."<init>":([I[B)V
    3370: putstatic     #168                // Field ENCODER:Lorg/apache/hc/core5/http2/hpack/HuffmanEncoder;
    3373: new           #169                // class org/apache/hc/core5/http2/hpack/HuffmanDecoder
    3376: dup
    3377: getstatic     #164                // Field CODES:[I
    3380: getstatic     #165                // Field LENGTHS:[B
    3383: invokespecial #170                // Method org/apache/hc/core5/http2/hpack/HuffmanDecoder."<init>":([I[B)V
    3386: putstatic     #171                // Field DECODER:Lorg/apache/hc/core5/http2/hpack/HuffmanDecoder;
    3389: return
}
