Compiled from "NativeRandom.java"
public class org.apache.kerby.kerberos.kerb.crypto.random.NativeRandom implements org.apache.kerby.kerberos.kerb.crypto.random.RandomProvider {
  private static final org.slf4j.Logger LOG;

  private java.io.InputStream input;

  private java.lang.String randFile;

  public org.apache.kerby.kerberos.kerb.crypto.random.NativeRandom();
    Code:
       0: aload_0
       1: invokespecial #1                  // Method java/lang/Object."<init>":()V
       4: aload_0
       5: ldc           #2                  // String /dev/urandom
       7: putfield      #3                  // Field randFile:Ljava/lang/String;
      10: return

  public void init();
    Code:
       0: aload_0
       1: aload_0
       2: getfield      #3                  // Field randFile:Ljava/lang/String;
       5: iconst_0
       6: anewarray     #4                  // class java/lang/String
       9: invokestatic  #5                  // Method java/nio/file/Paths.get:(Ljava/lang/String;[Ljava/lang/String;)Ljava/nio/file/Path;
      12: iconst_0
      13: anewarray     #6                  // class java/nio/file/OpenOption
      16: invokestatic  #7                  // Method java/nio/file/Files.newInputStream:(Ljava/nio/file/Path;[Ljava/nio/file/OpenOption;)Ljava/io/InputStream;
      19: putfield      #8                  // Field input:Ljava/io/InputStream;
      22: goto          68
      25: astore_1
      26: getstatic     #10                 // Field LOG:Lorg/slf4j/Logger;
      29: new           #11                 // class java/lang/StringBuilder
      32: dup
      33: invokespecial #12                 // Method java/lang/StringBuilder."<init>":()V
      36: ldc           #13                 // String Failed to init from file:
      38: invokevirtual #14                 // Method java/lang/StringBuilder.append:(Ljava/lang/String;)Ljava/lang/StringBuilder;
      41: aload_0
      42: getfield      #3                  // Field randFile:Ljava/lang/String;
      45: invokevirtual #14                 // Method java/lang/StringBuilder.append:(Ljava/lang/String;)Ljava/lang/StringBuilder;
      48: ldc           #15                 // String .
      50: invokevirtual #14                 // Method java/lang/StringBuilder.append:(Ljava/lang/String;)Ljava/lang/StringBuilder;
      53: aload_1
      54: invokevirtual #16                 // Method java/io/IOException.toString:()Ljava/lang/String;
      57: invokevirtual #14                 // Method java/lang/StringBuilder.append:(Ljava/lang/String;)Ljava/lang/StringBuilder;
      60: invokevirtual #17                 // Method java/lang/StringBuilder.toString:()Ljava/lang/String;
      63: invokeinterface #18,  2           // InterfaceMethod org/slf4j/Logger.error:(Ljava/lang/String;)V
      68: return
    Exception table:
       from    to  target type
           0    22    25   Class java/io/IOException

  public void setSeed(byte[]);
    Code:
       0: aconst_null
       1: astore_2
       2: aload_0
       3: getfield      #3                  // Field randFile:Ljava/lang/String;
       6: iconst_0
       7: anewarray     #4                  // class java/lang/String
      10: invokestatic  #5                  // Method java/nio/file/Paths.get:(Ljava/lang/String;[Ljava/lang/String;)Ljava/nio/file/Path;
      13: iconst_0
      14: anewarray     #6                  // class java/nio/file/OpenOption
      17: invokestatic  #19                 // Method java/nio/file/Files.newOutputStream:(Ljava/nio/file/Path;[Ljava/nio/file/OpenOption;)Ljava/io/OutputStream;
      20: astore_2
      21: aload_2
      22: aload_1
      23: invokevirtual #20                 // Method java/io/OutputStream.write:([B)V
      26: aload_2
      27: invokevirtual #21                 // Method java/io/OutputStream.flush:()V
      30: aload_2
      31: ifnull        212
      34: aload_2
      35: invokevirtual #22                 // Method java/io/OutputStream.close:()V
      38: goto          212
      41: astore_3
      42: getstatic     #10                 // Field LOG:Lorg/slf4j/Logger;
      45: new           #11                 // class java/lang/StringBuilder
      48: dup
      49: invokespecial #12                 // Method java/lang/StringBuilder."<init>":()V
      52: ldc           #23                 // String Failed to close output stream.
      54: invokevirtual #14                 // Method java/lang/StringBuilder.append:(Ljava/lang/String;)Ljava/lang/StringBuilder;
      57: aload_3
      58: invokevirtual #16                 // Method java/io/IOException.toString:()Ljava/lang/String;
      61: invokevirtual #14                 // Method java/lang/StringBuilder.append:(Ljava/lang/String;)Ljava/lang/StringBuilder;
      64: invokevirtual #17                 // Method java/lang/StringBuilder.toString:()Ljava/lang/String;
      67: invokeinterface #18,  2           // InterfaceMethod org/slf4j/Logger.error:(Ljava/lang/String;)V
      72: goto          212
      75: astore_3
      76: getstatic     #10                 // Field LOG:Lorg/slf4j/Logger;
      79: new           #11                 // class java/lang/StringBuilder
      82: dup
      83: invokespecial #12                 // Method java/lang/StringBuilder."<init>":()V
      86: ldc           #24                 // String Failed to write seed to the file:
      88: invokevirtual #14                 // Method java/lang/StringBuilder.append:(Ljava/lang/String;)Ljava/lang/StringBuilder;
      91: aload_0
      92: getfield      #3                  // Field randFile:Ljava/lang/String;
      95: invokevirtual #14                 // Method java/lang/StringBuilder.append:(Ljava/lang/String;)Ljava/lang/StringBuilder;
      98: ldc           #15                 // String .
     100: invokevirtual #14                 // Method java/lang/StringBuilder.append:(Ljava/lang/String;)Ljava/lang/StringBuilder;
     103: aload_3
     104: invokevirtual #16                 // Method java/io/IOException.toString:()Ljava/lang/String;
     107: invokevirtual #14                 // Method java/lang/StringBuilder.append:(Ljava/lang/String;)Ljava/lang/StringBuilder;
     110: invokevirtual #17                 // Method java/lang/StringBuilder.toString:()Ljava/lang/String;
     113: invokeinterface #18,  2           // InterfaceMethod org/slf4j/Logger.error:(Ljava/lang/String;)V
     118: aload_2
     119: ifnull        212
     122: aload_2
     123: invokevirtual #22                 // Method java/io/OutputStream.close:()V
     126: goto          212
     129: astore_3
     130: getstatic     #10                 // Field LOG:Lorg/slf4j/Logger;
     133: new           #11                 // class java/lang/StringBuilder
     136: dup
     137: invokespecial #12                 // Method java/lang/StringBuilder."<init>":()V
     140: ldc           #23                 // String Failed to close output stream.
     142: invokevirtual #14                 // Method java/lang/StringBuilder.append:(Ljava/lang/String;)Ljava/lang/StringBuilder;
     145: aload_3
     146: invokevirtual #16                 // Method java/io/IOException.toString:()Ljava/lang/String;
     149: invokevirtual #14                 // Method java/lang/StringBuilder.append:(Ljava/lang/String;)Ljava/lang/StringBuilder;
     152: invokevirtual #17                 // Method java/lang/StringBuilder.toString:()Ljava/lang/String;
     155: invokeinterface #18,  2           // InterfaceMethod org/slf4j/Logger.error:(Ljava/lang/String;)V
     160: goto          212
     163: astore        4
     165: aload_2
     166: ifnull        209
     169: aload_2
     170: invokevirtual #22                 // Method java/io/OutputStream.close:()V
     173: goto          209
     176: astore        5
     178: getstatic     #10                 // Field LOG:Lorg/slf4j/Logger;
     181: new           #11                 // class java/lang/StringBuilder
     184: dup
     185: invokespecial #12                 // Method java/lang/StringBuilder."<init>":()V
     188: ldc           #23                 // String Failed to close output stream.
     190: invokevirtual #14                 // Method java/lang/StringBuilder.append:(Ljava/lang/String;)Ljava/lang/StringBuilder;
     193: aload         5
     195: invokevirtual #16                 // Method java/io/IOException.toString:()Ljava/lang/String;
     198: invokevirtual #14                 // Method java/lang/StringBuilder.append:(Ljava/lang/String;)Ljava/lang/StringBuilder;
     201: invokevirtual #17                 // Method java/lang/StringBuilder.toString:()Ljava/lang/String;
     204: invokeinterface #18,  2           // InterfaceMethod org/slf4j/Logger.error:(Ljava/lang/String;)V
     209: aload         4
     211: athrow
     212: return
    Exception table:
       from    to  target type
          34    38    41   Class java/io/IOException
           2    30    75   Class java/io/IOException
         122   126   129   Class java/io/IOException
           2    30   163   any
          75   118   163   any
         169   173   176   Class java/io/IOException
         163   165   163   any

  public void nextBytes(byte[]);
    Code:
       0: aload_0
       1: getfield      #8                  // Field input:Ljava/io/InputStream;
       4: aload_1
       5: invokevirtual #25                 // Method java/io/InputStream.read:([B)I
       8: iconst_m1
       9: if_icmpne     20
      12: new           #9                  // class java/io/IOException
      15: dup
      16: invokespecial #26                 // Method java/io/IOException."<init>":()V
      19: athrow
      20: goto          54
      23: astore_2
      24: getstatic     #10                 // Field LOG:Lorg/slf4j/Logger;
      27: new           #11                 // class java/lang/StringBuilder
      30: dup
      31: invokespecial #12                 // Method java/lang/StringBuilder."<init>":()V
      34: ldc           #27                 // String Failed to read nextBytes.
      36: invokevirtual #14                 // Method java/lang/StringBuilder.append:(Ljava/lang/String;)Ljava/lang/StringBuilder;
      39: aload_2
      40: invokevirtual #16                 // Method java/io/IOException.toString:()Ljava/lang/String;
      43: invokevirtual #14                 // Method java/lang/StringBuilder.append:(Ljava/lang/String;)Ljava/lang/StringBuilder;
      46: invokevirtual #17                 // Method java/lang/StringBuilder.toString:()Ljava/lang/String;
      49: invokeinterface #18,  2           // InterfaceMethod org/slf4j/Logger.error:(Ljava/lang/String;)V
      54: return
    Exception table:
       from    to  target type
           0    20    23   Class java/io/IOException

  public void destroy();
    Code:
       0: aload_0
       1: getfield      #8                  // Field input:Ljava/io/InputStream;
       4: invokevirtual #28                 // Method java/io/InputStream.close:()V
       7: goto          41
      10: astore_1
      11: getstatic     #10                 // Field LOG:Lorg/slf4j/Logger;
      14: new           #11                 // class java/lang/StringBuilder
      17: dup
      18: invokespecial #12                 // Method java/lang/StringBuilder."<init>":()V
      21: ldc           #29                 // String Failed to close input stream.
      23: invokevirtual #14                 // Method java/lang/StringBuilder.append:(Ljava/lang/String;)Ljava/lang/StringBuilder;
      26: aload_1
      27: invokevirtual #16                 // Method java/io/IOException.toString:()Ljava/lang/String;
      30: invokevirtual #14                 // Method java/lang/StringBuilder.append:(Ljava/lang/String;)Ljava/lang/StringBuilder;
      33: invokevirtual #17                 // Method java/lang/StringBuilder.toString:()Ljava/lang/String;
      36: invokeinterface #18,  2           // InterfaceMethod org/slf4j/Logger.error:(Ljava/lang/String;)V
      41: return
    Exception table:
       from    to  target type
           0     7    10   Class java/io/IOException

  static {};
    Code:
       0: ldc_w         #30                 // class org/apache/kerby/kerberos/kerb/crypto/random/NativeRandom
       3: invokestatic  #31                 // Method org/slf4j/LoggerFactory.getLogger:(Ljava/lang/Class;)Lorg/slf4j/Logger;
       6: putstatic     #10                 // Field LOG:Lorg/slf4j/Logger;
       9: return
}
