Compiled from "DescriptionFactoryImpl.java"
public class org.apache.axis2.jaxws.description.impl.DescriptionFactoryImpl {
  private static final org.apache.commons.logging.Log log;

  private static java.util.Map<org.apache.axis2.jaxws.description.DescriptionKey, org.apache.axis2.jaxws.description.ServiceDescription> cache;

  private org.apache.axis2.jaxws.description.impl.DescriptionFactoryImpl();
    Code:
       0: aload_0
       1: invokespecial #1                  // Method java/lang/Object."<init>":()V
       4: return

  public static org.apache.axis2.jaxws.description.ServiceDescription createServiceDescription(java.net.URL, javax.xml.namespace.QName, java.lang.Class);
    Code:
       0: aload_0
       1: aload_1
       2: aload_2
       3: aconst_null
       4: aconst_null
       5: invokestatic  #2                  // Method createServiceDescription:(Ljava/net/URL;Ljavax/xml/namespace/QName;Ljava/lang/Class;Lorg/apache/axis2/jaxws/description/builder/DescriptionBuilderComposite;Ljava/lang/Object;)Lorg/apache/axis2/jaxws/description/ServiceDescription;
       8: areturn

  public static org.apache.axis2.jaxws.description.ServiceDescription createServiceDescription(java.net.URL, javax.xml.namespace.QName, java.lang.Class, org.apache.axis2.jaxws.description.builder.DescriptionBuilderComposite, java.lang.Object);
    Code:
       0: invokestatic  #3                  // Method org/apache/axis2/jaxws/description/DescriptionFactory.createClientConfigurationFactory:()Lorg/apache/axis2/jaxws/ClientConfigurationFactory;
       3: invokevirtual #4                  // Method org/apache/axis2/jaxws/ClientConfigurationFactory.getClientConfigurationContext:()Lorg/apache/axis2/context/ConfigurationContext;
       6: astore        5
       8: new           #5                  // class org/apache/axis2/jaxws/description/DescriptionKey
      11: dup
      12: aload_1
      13: aload_0
      14: aload_2
      15: aload         5
      17: aload_3
      18: invokestatic  #6                  // Method org/apache/axis2/jaxws/description/builder/DescriptionBuilderComposite.getServiceRefName:(Lorg/apache/axis2/jaxws/description/builder/DescriptionBuilderComposite;)Ljava/lang/String;
      21: invokespecial #7                  // Method org/apache/axis2/jaxws/description/DescriptionKey."<init>":(Ljavax/xml/namespace/QName;Ljava/net/URL;Ljava/lang/Class;Lorg/apache/axis2/context/ConfigurationContext;Ljava/lang/String;)V
      24: astore        6
      26: getstatic     #8                  // Field log:Lorg/apache/commons/logging/Log;
      29: invokeinterface #9,  1            // InterfaceMethod org/apache/commons/logging/Log.isDebugEnabled:()Z
      34: ifeq          105
      37: getstatic     #8                  // Field log:Lorg/apache/commons/logging/Log;
      40: new           #10                 // class java/lang/StringBuilder
      43: dup
      44: invokespecial #11                 // Method java/lang/StringBuilder."<init>":()V
      47: ldc           #12                 // String Cache Map =
      49: invokevirtual #13                 // Method java/lang/StringBuilder.append:(Ljava/lang/String;)Ljava/lang/StringBuilder;
      52: getstatic     #14                 // Field cache:Ljava/util/Map;
      55: invokevirtual #15                 // Method java/lang/Object.toString:()Ljava/lang/String;
      58: invokevirtual #13                 // Method java/lang/StringBuilder.append:(Ljava/lang/String;)Ljava/lang/StringBuilder;
      61: invokevirtual #16                 // Method java/lang/StringBuilder.toString:()Ljava/lang/String;
      64: invokeinterface #17,  2           // InterfaceMethod org/apache/commons/logging/Log.debug:(Ljava/lang/Object;)V
      69: aload         6
      71: ifnull        105
      74: getstatic     #8                  // Field log:Lorg/apache/commons/logging/Log;
      77: new           #10                 // class java/lang/StringBuilder
      80: dup
      81: invokespecial #11                 // Method java/lang/StringBuilder."<init>":()V
      84: ldc           #18                 // String Description Key =
      86: invokevirtual #13                 // Method java/lang/StringBuilder.append:(Ljava/lang/String;)Ljava/lang/StringBuilder;
      89: aload         6
      91: invokevirtual #19                 // Method org/apache/axis2/jaxws/description/DescriptionKey.printKey:()Ljava/lang/String;
      94: invokevirtual #13                 // Method java/lang/StringBuilder.append:(Ljava/lang/String;)Ljava/lang/StringBuilder;
      97: invokevirtual #16                 // Method java/lang/StringBuilder.toString:()Ljava/lang/String;
     100: invokeinterface #17,  2           // InterfaceMethod org/apache/commons/logging/Log.debug:(Ljava/lang/Object;)V
     105: aconst_null
     106: astore        7
     108: aload         5
     110: dup
     111: astore        8
     113: monitorenter
     114: getstatic     #8                  // Field log:Lorg/apache/commons/logging/Log;
     117: invokeinterface #9,  1            // InterfaceMethod org/apache/commons/logging/Log.isDebugEnabled:()Z
     122: ifeq          135
     125: getstatic     #8                  // Field log:Lorg/apache/commons/logging/Log;
     128: ldc           #20                 // String Check to see if ServiceDescription is found in cache
     130: invokeinterface #17,  2           // InterfaceMethod org/apache/commons/logging/Log.debug:(Ljava/lang/Object;)V
     135: getstatic     #14                 // Field cache:Ljava/util/Map;
     138: aload         6
     140: invokeinterface #21,  2           // InterfaceMethod java/util/Map.get:(Ljava/lang/Object;)Ljava/lang/Object;
     145: checkcast     #22                 // class org/apache/axis2/jaxws/description/ServiceDescription
     148: astore        7
     150: aload         7
     152: ifnull        189
     155: getstatic     #8                  // Field log:Lorg/apache/commons/logging/Log;
     158: invokeinterface #9,  1            // InterfaceMethod org/apache/commons/logging/Log.isDebugEnabled:()Z
     163: ifeq          189
     166: getstatic     #8                  // Field log:Lorg/apache/commons/logging/Log;
     169: ldc           #23                 // String ServiceDescription found in the cache
     171: invokeinterface #17,  2           // InterfaceMethod org/apache/commons/logging/Log.debug:(Ljava/lang/Object;)V
     176: getstatic     #8                  // Field log:Lorg/apache/commons/logging/Log;
     179: aload         7
     181: invokevirtual #15                 // Method java/lang/Object.toString:()Ljava/lang/String;
     184: invokeinterface #17,  2           // InterfaceMethod org/apache/commons/logging/Log.debug:(Ljava/lang/Object;)V
     189: aload         7
     191: ifnonnull     448
     194: getstatic     #8                  // Field log:Lorg/apache/commons/logging/Log;
     197: invokeinterface #9,  1            // InterfaceMethod org/apache/commons/logging/Log.isDebugEnabled:()Z
     202: ifeq          225
     205: getstatic     #8                  // Field log:Lorg/apache/commons/logging/Log;
     208: ldc           #24                 // String ServiceDescription not found in the cache
     210: invokeinterface #17,  2           // InterfaceMethod org/apache/commons/logging/Log.debug:(Ljava/lang/Object;)V
     215: getstatic     #8                  // Field log:Lorg/apache/commons/logging/Log;
     218: ldc           #25                 // String  creating new ServiceDescriptionImpl
     220: invokeinterface #17,  2           // InterfaceMethod org/apache/commons/logging/Log.debug:(Ljava/lang/Object;)V
     225: aconst_null
     226: astore        9
     228: aload_3
     229: ifnull        319
     232: new           #26                 // class org/apache/axis2/jaxws/description/impl/ServiceDescriptionImpl
     235: dup
     236: aload_0
     237: aload_1
     238: aload_2
     239: aload_3
     240: aload         4
     242: invokespecial #27                 // Method org/apache/axis2/jaxws/description/impl/ServiceDescriptionImpl."<init>":(Ljava/net/URL;Ljavax/xml/namespace/QName;Ljava/lang/Class;Lorg/apache/axis2/jaxws/description/builder/DescriptionBuilderComposite;Ljava/lang/Object;)V
     245: astore        9
     247: getstatic     #8                  // Field log:Lorg/apache/commons/logging/Log;
     250: invokeinterface #9,  1            // InterfaceMethod org/apache/commons/logging/Log.isDebugEnabled:()Z
     255: ifeq          331
     258: getstatic     #8                  // Field log:Lorg/apache/commons/logging/Log;
     261: new           #10                 // class java/lang/StringBuilder
     264: dup
     265: invokespecial #11                 // Method java/lang/StringBuilder."<init>":()V
     268: ldc           #28                 // String Client-side service description created with service class:
     270: invokevirtual #13                 // Method java/lang/StringBuilder.append:(Ljava/lang/String;)Ljava/lang/StringBuilder;
     273: aload_2
     274: invokevirtual #29                 // Method java/lang/StringBuilder.append:(Ljava/lang/Object;)Ljava/lang/StringBuilder;
     277: ldc           #30                 // String , Service QN:
     279: invokevirtual #13                 // Method java/lang/StringBuilder.append:(Ljava/lang/String;)Ljava/lang/StringBuilder;
     282: aload_1
     283: invokevirtual #29                 // Method java/lang/StringBuilder.append:(Ljava/lang/Object;)Ljava/lang/StringBuilder;
     286: ldc           #31                 // String , and DBC:
     288: invokevirtual #13                 // Method java/lang/StringBuilder.append:(Ljava/lang/String;)Ljava/lang/StringBuilder;
     291: aload_3
     292: invokevirtual #29                 // Method java/lang/StringBuilder.append:(Ljava/lang/Object;)Ljava/lang/StringBuilder;
     295: invokevirtual #16                 // Method java/lang/StringBuilder.toString:()Ljava/lang/String;
     298: invokeinterface #17,  2           // InterfaceMethod org/apache/commons/logging/Log.debug:(Ljava/lang/Object;)V
     303: getstatic     #8                  // Field log:Lorg/apache/commons/logging/Log;
     306: aload         9
     308: invokevirtual #32                 // Method org/apache/axis2/jaxws/description/impl/ServiceDescriptionImpl.toString:()Ljava/lang/String;
     311: invokeinterface #17,  2           // InterfaceMethod org/apache/commons/logging/Log.debug:(Ljava/lang/Object;)V
     316: goto          331
     319: new           #26                 // class org/apache/axis2/jaxws/description/impl/ServiceDescriptionImpl
     322: dup
     323: aload_0
     324: aload_1
     325: aload_2
     326: invokespecial #33                 // Method org/apache/axis2/jaxws/description/impl/ServiceDescriptionImpl."<init>":(Ljava/net/URL;Ljavax/xml/namespace/QName;Ljava/lang/Class;)V
     329: astore        9
     331: aload         9
     333: aload         5
     335: invokevirtual #34                 // Method org/apache/axis2/jaxws/description/impl/ServiceDescriptionImpl.setAxisConfigContext:(Lorg/apache/axis2/context/ConfigurationContext;)V
     338: aload         9
     340: astore        7
     342: getstatic     #8                  // Field log:Lorg/apache/commons/logging/Log;
     345: invokeinterface #9,  1            // InterfaceMethod org/apache/commons/logging/Log.isDebugEnabled:()Z
     350: ifeq          411
     353: getstatic     #8                  // Field log:Lorg/apache/commons/logging/Log;
     356: new           #10                 // class java/lang/StringBuilder
     359: dup
     360: invokespecial #11                 // Method java/lang/StringBuilder."<init>":()V
     363: ldc           #35                 // String ServiceDescription created with WSDL URL:
     365: invokevirtual #13                 // Method java/lang/StringBuilder.append:(Ljava/lang/String;)Ljava/lang/StringBuilder;
     368: aload_0
     369: invokevirtual #29                 // Method java/lang/StringBuilder.append:(Ljava/lang/Object;)Ljava/lang/StringBuilder;
     372: ldc           #36                 // String ; QName:
     374: invokevirtual #13                 // Method java/lang/StringBuilder.append:(Ljava/lang/String;)Ljava/lang/StringBuilder;
     377: aload_1
     378: invokevirtual #29                 // Method java/lang/StringBuilder.append:(Ljava/lang/Object;)Ljava/lang/StringBuilder;
     381: ldc           #37                 // String ; Class:
     383: invokevirtual #13                 // Method java/lang/StringBuilder.append:(Ljava/lang/String;)Ljava/lang/StringBuilder;
     386: aload_2
     387: invokevirtual #29                 // Method java/lang/StringBuilder.append:(Ljava/lang/Object;)Ljava/lang/StringBuilder;
     390: invokevirtual #16                 // Method java/lang/StringBuilder.toString:()Ljava/lang/String;
     393: invokeinterface #17,  2           // InterfaceMethod org/apache/commons/logging/Log.debug:(Ljava/lang/Object;)V
     398: getstatic     #8                  // Field log:Lorg/apache/commons/logging/Log;
     401: aload         7
     403: invokevirtual #15                 // Method java/lang/Object.toString:()Ljava/lang/String;
     406: invokeinterface #17,  2           // InterfaceMethod org/apache/commons/logging/Log.debug:(Ljava/lang/Object;)V
     411: getstatic     #8                  // Field log:Lorg/apache/commons/logging/Log;
     414: invokeinterface #9,  1            // InterfaceMethod org/apache/commons/logging/Log.isDebugEnabled:()Z
     419: ifeq          432
     422: getstatic     #8                  // Field log:Lorg/apache/commons/logging/Log;
     425: ldc           #38                 // String Caching new ServiceDescription in the cache
     427: invokeinterface #17,  2           // InterfaceMethod org/apache/commons/logging/Log.debug:(Ljava/lang/Object;)V
     432: getstatic     #14                 // Field cache:Ljava/util/Map;
     435: aload         6
     437: aload         7
     439: invokeinterface #39,  3           // InterfaceMethod java/util/Map.put:(Ljava/lang/Object;Ljava/lang/Object;)Ljava/lang/Object;
     444: pop
     445: goto          462
     448: aload         7
     450: checkcast     #26                 // class org/apache/axis2/jaxws/description/impl/ServiceDescriptionImpl
     453: invokevirtual #40                 // Method org/apache/axis2/jaxws/description/impl/ServiceDescriptionImpl.getDescriptionBuilderComposite:()Lorg/apache/axis2/jaxws/description/builder/DescriptionBuilderComposite;
     456: aload         4
     458: aload_3
     459: invokevirtual #41                 // Method org/apache/axis2/jaxws/description/builder/DescriptionBuilderComposite.setSparseComposite:(Ljava/lang/Object;Lorg/apache/axis2/jaxws/description/builder/DescriptionBuilderComposite;)V
     462: aload         7
     464: checkcast     #26                 // class org/apache/axis2/jaxws/description/impl/ServiceDescriptionImpl
     467: invokevirtual #42                 // Method org/apache/axis2/jaxws/description/impl/ServiceDescriptionImpl.registerUse:()V
     470: aload         8
     472: monitorexit
     473: goto          484
     476: astore        10
     478: aload         8
     480: monitorexit
     481: aload         10
     483: athrow
     484: aload         7
     486: areturn
    Exception table:
       from    to  target type
         114   473   476   any
         476   481   476   any

  public static void clearServiceDescriptionCache();
    Code:
       0: getstatic     #14                 // Field cache:Ljava/util/Map;
       3: invokeinterface #43,  1           // InterfaceMethod java/util/Map.clear:()V
       8: return

  public static void clearServiceDescriptionCache(org.apache.axis2.context.ConfigurationContext);
    Code:
       0: aload_0
       1: ifnonnull     5
       4: return
       5: aload_0
       6: dup
       7: astore_1
       8: monitorenter
       9: getstatic     #14                 // Field cache:Ljava/util/Map;
      12: dup
      13: astore_2
      14: monitorenter
      15: getstatic     #14                 // Field cache:Ljava/util/Map;
      18: invokeinterface #44,  1           // InterfaceMethod java/util/Map.keySet:()Ljava/util/Set;
      23: invokeinterface #45,  1           // InterfaceMethod java/util/Set.iterator:()Ljava/util/Iterator;
      28: astore_3
      29: aload_3
      30: invokeinterface #46,  1           // InterfaceMethod java/util/Iterator.hasNext:()Z
      35: ifeq          67
      38: aload_3
      39: invokeinterface #47,  1           // InterfaceMethod java/util/Iterator.next:()Ljava/lang/Object;
      44: checkcast     #5                  // class org/apache/axis2/jaxws/description/DescriptionKey
      47: astore        4
      49: aload         4
      51: invokevirtual #48                 // Method org/apache/axis2/jaxws/description/DescriptionKey.getConfigContext:()Lorg/apache/axis2/context/ConfigurationContext;
      54: aload_0
      55: if_acmpne     64
      58: aload_3
      59: invokeinterface #49,  1           // InterfaceMethod java/util/Iterator.remove:()V
      64: goto          29
      67: aload_2
      68: monitorexit
      69: goto          79
      72: astore        5
      74: aload_2
      75: monitorexit
      76: aload         5
      78: athrow
      79: aload_1
      80: monitorexit
      81: goto          91
      84: astore        6
      86: aload_1
      87: monitorexit
      88: aload         6
      90: athrow
      91: return
    Exception table:
       from    to  target type
          15    69    72   any
          72    76    72   any
           9    81    84   any
          84    88    84   any

  public static org.apache.axis2.jaxws.description.ServiceDescription createServiceDescription(java.lang.Class);
    Code:
       0: aload_0
       1: aconst_null
       2: invokestatic  #50                 // Method createServiceDescription:(Ljava/lang/Class;Lorg/apache/axis2/context/ConfigurationContext;)Lorg/apache/axis2/jaxws/description/ServiceDescription;
       5: areturn

  public static org.apache.axis2.jaxws.description.ServiceDescription createServiceDescription(java.lang.Class, org.apache.axis2.context.ConfigurationContext);
    Code:
       0: aconst_null
       1: astore_2
       2: aload_0
       3: ifnull        157
       6: new           #51                 // class org/apache/axis2/jaxws/description/builder/converter/JavaClassToDBCConverter
       9: dup
      10: aload_0
      11: invokespecial #52                 // Method org/apache/axis2/jaxws/description/builder/converter/JavaClassToDBCConverter."<init>":(Ljava/lang/Class;)V
      14: astore_3
      15: aload_3
      16: invokevirtual #53                 // Method org/apache/axis2/jaxws/description/builder/converter/JavaClassToDBCConverter.produceDBC:()Ljava/util/HashMap;
      19: astore        4
      21: aload         4
      23: aload_1
      24: invokestatic  #54                 // Method createServiceDescriptionFromDBCMap:(Ljava/util/HashMap;Lorg/apache/axis2/context/ConfigurationContext;)Ljava/util/List;
      27: astore        5
      29: aload         5
      31: ifnull        106
      34: aload         5
      36: invokeinterface #55,  1           // InterfaceMethod java/util/List.size:()I
      41: ifle          106
      44: aload         5
      46: iconst_0
      47: invokeinterface #56,  2           // InterfaceMethod java/util/List.get:(I)Ljava/lang/Object;
      52: checkcast     #22                 // class org/apache/axis2/jaxws/description/ServiceDescription
      55: astore_2
      56: getstatic     #8                  // Field log:Lorg/apache/commons/logging/Log;
      59: invokeinterface #9,  1            // InterfaceMethod org/apache/commons/logging/Log.isDebugEnabled:()Z
      64: ifeq          157
      67: getstatic     #8                  // Field log:Lorg/apache/commons/logging/Log;
      70: new           #10                 // class java/lang/StringBuilder
      73: dup
      74: invokespecial #11                 // Method java/lang/StringBuilder."<init>":()V
      77: ldc           #57                 // String ServiceDescription created with class:
      79: invokevirtual #13                 // Method java/lang/StringBuilder.append:(Ljava/lang/String;)Ljava/lang/StringBuilder;
      82: aload_0
      83: invokevirtual #29                 // Method java/lang/StringBuilder.append:(Ljava/lang/Object;)Ljava/lang/StringBuilder;
      86: invokevirtual #16                 // Method java/lang/StringBuilder.toString:()Ljava/lang/String;
      89: invokeinterface #17,  2           // InterfaceMethod org/apache/commons/logging/Log.debug:(Ljava/lang/Object;)V
      94: getstatic     #8                  // Field log:Lorg/apache/commons/logging/Log;
      97: aload_2
      98: invokeinterface #17,  2           // InterfaceMethod org/apache/commons/logging/Log.debug:(Ljava/lang/Object;)V
     103: goto          157
     106: getstatic     #8                  // Field log:Lorg/apache/commons/logging/Log;
     109: invokeinterface #9,  1            // InterfaceMethod org/apache/commons/logging/Log.isDebugEnabled:()Z
     114: ifeq          144
     117: getstatic     #8                  // Field log:Lorg/apache/commons/logging/Log;
     120: new           #10                 // class java/lang/StringBuilder
     123: dup
     124: invokespecial #11                 // Method java/lang/StringBuilder."<init>":()V
     127: ldc           #58                 // String ServiceDesciption was not created for class:
     129: invokevirtual #13                 // Method java/lang/StringBuilder.append:(Ljava/lang/String;)Ljava/lang/StringBuilder;
     132: aload_0
     133: invokevirtual #29                 // Method java/lang/StringBuilder.append:(Ljava/lang/Object;)Ljava/lang/StringBuilder;
     136: invokevirtual #16                 // Method java/lang/StringBuilder.toString:()Ljava/lang/String;
     139: invokeinterface #17,  2           // InterfaceMethod org/apache/commons/logging/Log.debug:(Ljava/lang/Object;)V
     144: ldc           #59                 // String createServiceDescrErr
     146: aload_0
     147: invokevirtual #60                 // Method java/lang/Class.getName:()Ljava/lang/String;
     150: invokestatic  #61                 // Method org/apache/axis2/jaxws/i18n/Messages.getMessage:(Ljava/lang/String;Ljava/lang/String;)Ljava/lang/String;
     153: invokestatic  #62                 // Method org/apache/axis2/jaxws/ExceptionFactory.makeWebServiceException:(Ljava/lang/String;)Ljavax/xml/ws/WebServiceException;
     156: athrow
     157: aload_2
     158: areturn

  public static java.util.List<org.apache.axis2.jaxws.description.ServiceDescription> createServiceDescriptionFromDBCMap(java.util.HashMap<java.lang.String, org.apache.axis2.jaxws.description.builder.DescriptionBuilderComposite>, org.apache.axis2.context.ConfigurationContext, boolean);
    Code:
       0: getstatic     #8                  // Field log:Lorg/apache/commons/logging/Log;
       3: invokeinterface #9,  1            // InterfaceMethod org/apache/commons/logging/Log.isDebugEnabled:()Z
       8: ifeq          21
      11: getstatic     #8                  // Field log:Lorg/apache/commons/logging/Log;
      14: ldc           #63                 // String createServiceDescriptionFromDBCMap(Hashmap<String,DescriptionBuilderComposite>,ConfigurationContext,boolean performVaidation
      16: invokeinterface #17,  2           // InterfaceMethod org/apache/commons/logging/Log.debug:(Ljava/lang/Object;)V
      21: new           #64                 // class java/util/ArrayList
      24: dup
      25: invokespecial #65                 // Method java/util/ArrayList."<init>":()V
      28: astore_3
      29: aload_0
      30: invokevirtual #66                 // Method java/util/HashMap.values:()Ljava/util/Collection;
      33: invokeinterface #67,  1           // InterfaceMethod java/util/Collection.iterator:()Ljava/util/Iterator;
      38: astore        4
      40: aload         4
      42: invokeinterface #46,  1           // InterfaceMethod java/util/Iterator.hasNext:()Z
      47: ifeq          463
      50: aload         4
      52: invokeinterface #47,  1           // InterfaceMethod java/util/Iterator.next:()Ljava/lang/Object;
      57: checkcast     #68                 // class org/apache/axis2/jaxws/description/builder/DescriptionBuilderComposite
      60: astore        5
      62: aload         5
      64: invokestatic  #69                 // Method isImpl:(Lorg/apache/axis2/jaxws/description/builder/DescriptionBuilderComposite;)Z
      67: ifeq          418
      70: aload         5
      72: invokevirtual #70                 // Method org/apache/axis2/jaxws/description/builder/DescriptionBuilderComposite.getServiceQNames:()Ljava/util/Set;
      75: astore        6
      77: aload         6
      79: ifnull        92
      82: aload         6
      84: invokeinterface #71,  1           // InterfaceMethod java/util/Set.isEmpty:()Z
      89: ifeq          228
      92: getstatic     #8                  // Field log:Lorg/apache/commons/logging/Log;
      95: invokeinterface #9,  1            // InterfaceMethod org/apache/commons/logging/Log.isDebugEnabled:()Z
     100: ifeq          113
     103: getstatic     #8                  // Field log:Lorg/apache/commons/logging/Log;
     106: ldc           #72                 // String Adding ServiceDescription instances from composite
     108: invokeinterface #17,  2           // InterfaceMethod org/apache/commons/logging/Log.debug:(Ljava/lang/Object;)V
     113: new           #26                 // class org/apache/axis2/jaxws/description/impl/ServiceDescriptionImpl
     116: dup
     117: aload_0
     118: aload         5
     120: aload_1
     121: invokespecial #73                 // Method org/apache/axis2/jaxws/description/impl/ServiceDescriptionImpl."<init>":(Ljava/util/HashMap;Lorg/apache/axis2/jaxws/description/builder/DescriptionBuilderComposite;Lorg/apache/axis2/context/ConfigurationContext;)V
     124: astore        7
     126: new           #74                 // class org/apache/axis2/jaxws/description/validator/ServiceDescriptionValidator
     129: dup
     130: aload         7
     132: invokespecial #75                 // Method org/apache/axis2/jaxws/description/validator/ServiceDescriptionValidator."<init>":(Lorg/apache/axis2/jaxws/description/ServiceDescription;)V
     135: astore        8
     137: aload         8
     139: iload_2
     140: invokevirtual #76                 // Method org/apache/axis2/jaxws/description/validator/ServiceDescriptionValidator.validate:(Z)Z
     143: ifeq          197
     146: aload_3
     147: aload         7
     149: invokeinterface #77,  2           // InterfaceMethod java/util/List.add:(Ljava/lang/Object;)Z
     154: pop
     155: getstatic     #8                  // Field log:Lorg/apache/commons/logging/Log;
     158: invokeinterface #9,  1            // InterfaceMethod org/apache/commons/logging/Log.isDebugEnabled:()Z
     163: ifeq          225
     166: getstatic     #8                  // Field log:Lorg/apache/commons/logging/Log;
     169: new           #10                 // class java/lang/StringBuilder
     172: dup
     173: invokespecial #11                 // Method java/lang/StringBuilder."<init>":()V
     176: ldc           #78                 // String Service Description created from DescriptionComposite:
     178: invokevirtual #13                 // Method java/lang/StringBuilder.append:(Ljava/lang/String;)Ljava/lang/StringBuilder;
     181: aload         7
     183: invokevirtual #29                 // Method java/lang/StringBuilder.append:(Ljava/lang/Object;)Ljava/lang/StringBuilder;
     186: invokevirtual #16                 // Method java/lang/StringBuilder.toString:()Ljava/lang/String;
     189: invokeinterface #17,  2           // InterfaceMethod org/apache/commons/logging/Log.debug:(Ljava/lang/Object;)V
     194: goto          225
     197: ldc           #79                 // String createSrvcDescrDBCMapErr
     199: aload         8
     201: invokevirtual #80                 // Method org/apache/axis2/jaxws/description/validator/ServiceDescriptionValidator.toString:()Ljava/lang/String;
     204: aload         5
     206: invokevirtual #81                 // Method org/apache/axis2/jaxws/description/builder/DescriptionBuilderComposite.toString:()Ljava/lang/String;
     209: aload         7
     211: invokevirtual #32                 // Method org/apache/axis2/jaxws/description/impl/ServiceDescriptionImpl.toString:()Ljava/lang/String;
     214: invokestatic  #82                 // Method org/apache/axis2/jaxws/i18n/Messages.getMessage:(Ljava/lang/String;Ljava/lang/String;Ljava/lang/String;Ljava/lang/String;)Ljava/lang/String;
     217: astore        9
     219: aload         9
     221: invokestatic  #62                 // Method org/apache/axis2/jaxws/ExceptionFactory.makeWebServiceException:(Ljava/lang/String;)Ljavax/xml/ws/WebServiceException;
     224: athrow
     225: goto          415
     228: aload         6
     230: invokeinterface #45,  1           // InterfaceMethod java/util/Set.iterator:()Ljava/util/Iterator;
     235: astore        7
     237: aload         7
     239: invokeinterface #46,  1           // InterfaceMethod java/util/Iterator.hasNext:()Z
     244: ifeq          415
     247: aload         7
     249: invokeinterface #47,  1           // InterfaceMethod java/util/Iterator.next:()Ljava/lang/Object;
     254: checkcast     #83                 // class javax/xml/namespace/QName
     257: astore        8
     259: getstatic     #8                  // Field log:Lorg/apache/commons/logging/Log;
     262: invokeinterface #9,  1            // InterfaceMethod org/apache/commons/logging/Log.isDebugEnabled:()Z
     267: ifeq          298
     270: getstatic     #8                  // Field log:Lorg/apache/commons/logging/Log;
     273: new           #10                 // class java/lang/StringBuilder
     276: dup
     277: invokespecial #11                 // Method java/lang/StringBuilder."<init>":()V
     280: ldc           #84                 // String Adding ServiceDescription from service QName set for :
     282: invokevirtual #13                 // Method java/lang/StringBuilder.append:(Ljava/lang/String;)Ljava/lang/StringBuilder;
     285: aload         8
     287: invokevirtual #29                 // Method java/lang/StringBuilder.append:(Ljava/lang/Object;)Ljava/lang/StringBuilder;
     290: invokevirtual #16                 // Method java/lang/StringBuilder.toString:()Ljava/lang/String;
     293: invokeinterface #17,  2           // InterfaceMethod org/apache/commons/logging/Log.debug:(Ljava/lang/Object;)V
     298: new           #26                 // class org/apache/axis2/jaxws/description/impl/ServiceDescriptionImpl
     301: dup
     302: aload_0
     303: aload         5
     305: aload_1
     306: aload         8
     308: invokespecial #85                 // Method org/apache/axis2/jaxws/description/impl/ServiceDescriptionImpl."<init>":(Ljava/util/HashMap;Lorg/apache/axis2/jaxws/description/builder/DescriptionBuilderComposite;Lorg/apache/axis2/context/ConfigurationContext;Ljavax/xml/namespace/QName;)V
     311: astore        9
     313: new           #74                 // class org/apache/axis2/jaxws/description/validator/ServiceDescriptionValidator
     316: dup
     317: aload         9
     319: invokespecial #75                 // Method org/apache/axis2/jaxws/description/validator/ServiceDescriptionValidator."<init>":(Lorg/apache/axis2/jaxws/description/ServiceDescription;)V
     322: astore        10
     324: aload         10
     326: iload_2
     327: invokevirtual #76                 // Method org/apache/axis2/jaxws/description/validator/ServiceDescriptionValidator.validate:(Z)Z
     330: ifeq          384
     333: aload_3
     334: aload         9
     336: invokeinterface #77,  2           // InterfaceMethod java/util/List.add:(Ljava/lang/Object;)Z
     341: pop
     342: getstatic     #8                  // Field log:Lorg/apache/commons/logging/Log;
     345: invokeinterface #9,  1            // InterfaceMethod org/apache/commons/logging/Log.isDebugEnabled:()Z
     350: ifeq          412
     353: getstatic     #8                  // Field log:Lorg/apache/commons/logging/Log;
     356: new           #10                 // class java/lang/StringBuilder
     359: dup
     360: invokespecial #11                 // Method java/lang/StringBuilder."<init>":()V
     363: ldc           #78                 // String Service Description created from DescriptionComposite:
     365: invokevirtual #13                 // Method java/lang/StringBuilder.append:(Ljava/lang/String;)Ljava/lang/StringBuilder;
     368: aload         9
     370: invokevirtual #29                 // Method java/lang/StringBuilder.append:(Ljava/lang/Object;)Ljava/lang/StringBuilder;
     373: invokevirtual #16                 // Method java/lang/StringBuilder.toString:()Ljava/lang/String;
     376: invokeinterface #17,  2           // InterfaceMethod org/apache/commons/logging/Log.debug:(Ljava/lang/Object;)V
     381: goto          412
     384: ldc           #79                 // String createSrvcDescrDBCMapErr
     386: aload         10
     388: invokevirtual #80                 // Method org/apache/axis2/jaxws/description/validator/ServiceDescriptionValidator.toString:()Ljava/lang/String;
     391: aload         5
     393: invokevirtual #81                 // Method org/apache/axis2/jaxws/description/builder/DescriptionBuilderComposite.toString:()Ljava/lang/String;
     396: aload         9
     398: invokevirtual #32                 // Method org/apache/axis2/jaxws/description/impl/ServiceDescriptionImpl.toString:()Ljava/lang/String;
     401: invokestatic  #82                 // Method org/apache/axis2/jaxws/i18n/Messages.getMessage:(Ljava/lang/String;Ljava/lang/String;Ljava/lang/String;Ljava/lang/String;)Ljava/lang/String;
     404: astore        11
     406: aload         11
     408: invokestatic  #62                 // Method org/apache/axis2/jaxws/ExceptionFactory.makeWebServiceException:(Ljava/lang/String;)Ljavax/xml/ws/WebServiceException;
     411: athrow
     412: goto          237
     415: goto          460
     418: getstatic     #8                  // Field log:Lorg/apache/commons/logging/Log;
     421: invokeinterface #9,  1            // InterfaceMethod org/apache/commons/logging/Log.isDebugEnabled:()Z
     426: ifeq          460
     429: getstatic     #8                  // Field log:Lorg/apache/commons/logging/Log;
     432: new           #10                 // class java/lang/StringBuilder
     435: dup
     436: invokespecial #11                 // Method java/lang/StringBuilder."<init>":()V
     439: ldc           #86                 // String DBC is not a service impl:
     441: invokevirtual #13                 // Method java/lang/StringBuilder.append:(Ljava/lang/String;)Ljava/lang/StringBuilder;
     444: aload         5
     446: invokevirtual #81                 // Method org/apache/axis2/jaxws/description/builder/DescriptionBuilderComposite.toString:()Ljava/lang/String;
     449: invokevirtual #13                 // Method java/lang/StringBuilder.append:(Ljava/lang/String;)Ljava/lang/StringBuilder;
     452: invokevirtual #16                 // Method java/lang/StringBuilder.toString:()Ljava/lang/String;
     455: invokeinterface #17,  2           // InterfaceMethod org/apache/commons/logging/Log.debug:(Ljava/lang/Object;)V
     460: goto          40
     463: aload_3
     464: areturn

  public static java.util.List<org.apache.axis2.jaxws.description.ServiceDescription> createServiceDescriptionFromDBCMap(java.util.HashMap<java.lang.String, org.apache.axis2.jaxws.description.builder.DescriptionBuilderComposite>, org.apache.axis2.context.ConfigurationContext);
    Code:
       0: getstatic     #8                  // Field log:Lorg/apache/commons/logging/Log;
       3: invokeinterface #9,  1            // InterfaceMethod org/apache/commons/logging/Log.isDebugEnabled:()Z
       8: ifeq          21
      11: getstatic     #8                  // Field log:Lorg/apache/commons/logging/Log;
      14: ldc           #87                 // String createServiceDescriptionFromDBCMap(Hashmap<String,DescriptionBuilderComposite>,ConfigurationContext
      16: invokeinterface #17,  2           // InterfaceMethod org/apache/commons/logging/Log.debug:(Ljava/lang/Object;)V
      21: aload_0
      22: aload_1
      23: iconst_0
      24: invokestatic  #88                 // Method createServiceDescriptionFromDBCMap:(Ljava/util/HashMap;Lorg/apache/axis2/context/ConfigurationContext;Z)Ljava/util/List;
      27: areturn

  public static org.apache.axis2.jaxws.description.EndpointDescription updateEndpoint(org.apache.axis2.jaxws.description.ServiceDescription, java.lang.Class, javax.xml.namespace.QName, org.apache.axis2.jaxws.description.DescriptionFactory$UpdateType, java.lang.String, java.lang.String);
    Code:
       0: aload_0
       1: aload_1
       2: aload_2
       3: aload_3
       4: aconst_null
       5: aconst_null
       6: aload         4
       8: aload         5
      10: invokestatic  #89                 // Method updateEndpoint:(Lorg/apache/axis2/jaxws/description/ServiceDescription;Ljava/lang/Class;Ljavax/xml/namespace/QName;Lorg/apache/axis2/jaxws/description/DescriptionFactory$UpdateType;Lorg/apache/axis2/jaxws/description/builder/DescriptionBuilderComposite;Ljava/lang/Object;Ljava/lang/String;Ljava/lang/String;)Lorg/apache/axis2/jaxws/description/EndpointDescription;
      13: areturn

  public static org.apache.axis2.jaxws.description.EndpointDescription updateEndpoint(org.apache.axis2.jaxws.description.ServiceDescription, java.lang.Class, javax.xml.namespace.QName, org.apache.axis2.jaxws.description.DescriptionFactory$UpdateType, java.lang.Object, java.lang.String, java.lang.String);
    Code:
       0: aload_0
       1: aload_1
       2: aload_2
       3: aload_3
       4: aconst_null
       5: aload         4
       7: aload         5
       9: aload         6
      11: invokestatic  #89                 // Method updateEndpoint:(Lorg/apache/axis2/jaxws/description/ServiceDescription;Ljava/lang/Class;Ljavax/xml/namespace/QName;Lorg/apache/axis2/jaxws/description/DescriptionFactory$UpdateType;Lorg/apache/axis2/jaxws/description/builder/DescriptionBuilderComposite;Ljava/lang/Object;Ljava/lang/String;Ljava/lang/String;)Lorg/apache/axis2/jaxws/description/EndpointDescription;
      14: areturn

  public static org.apache.axis2.jaxws.description.EndpointDescription updateEndpoint(org.apache.axis2.jaxws.description.ServiceDescription, java.lang.Class, javax.xml.namespace.QName, org.apache.axis2.jaxws.description.DescriptionFactory$UpdateType, org.apache.axis2.jaxws.description.builder.DescriptionBuilderComposite, java.lang.Object, java.lang.String, java.lang.String);
    Code:
       0: aconst_null
       1: astore        8
       3: aload_0
       4: dup
       5: astore        9
       7: monitorenter
       8: aload_0
       9: checkcast     #26                 // class org/apache/axis2/jaxws/description/impl/ServiceDescriptionImpl
      12: aload_1
      13: aload_2
      14: aload_3
      15: aload         4
      17: aload         5
      19: aload         6
      21: aload         7
      23: invokevirtual #90                 // Method org/apache/axis2/jaxws/description/impl/ServiceDescriptionImpl.updateEndpointDescription:(Ljava/lang/Class;Ljavax/xml/namespace/QName;Lorg/apache/axis2/jaxws/description/DescriptionFactory$UpdateType;Lorg/apache/axis2/jaxws/description/builder/DescriptionBuilderComposite;Ljava/lang/Object;Ljava/lang/String;Ljava/lang/String;)Lorg/apache/axis2/jaxws/description/EndpointDescription;
      26: astore        8
      28: aload         9
      30: monitorexit
      31: goto          42
      34: astore        10
      36: aload         9
      38: monitorexit
      39: aload         10
      41: athrow
      42: new           #91                 // class org/apache/axis2/jaxws/description/validator/EndpointDescriptionValidator
      45: dup
      46: aload         8
      48: invokespecial #92                 // Method org/apache/axis2/jaxws/description/validator/EndpointDescriptionValidator."<init>":(Lorg/apache/axis2/jaxws/description/EndpointDescription;)V
      51: astore        9
      53: aload         9
      55: invokevirtual #93                 // Method org/apache/axis2/jaxws/description/validator/EndpointDescriptionValidator.validate:()Z
      58: istore        10
      60: iload         10
      62: ifne          83
      65: ldc           #94                 // String endpointDescriptionValidationErrors
      67: aload         9
      69: invokevirtual #95                 // Method org/apache/axis2/jaxws/description/validator/EndpointDescriptionValidator.toString:()Ljava/lang/String;
      72: invokestatic  #61                 // Method org/apache/axis2/jaxws/i18n/Messages.getMessage:(Ljava/lang/String;Ljava/lang/String;)Ljava/lang/String;
      75: astore        11
      77: aload         11
      79: invokestatic  #62                 // Method org/apache/axis2/jaxws/ExceptionFactory.makeWebServiceException:(Ljava/lang/String;)Ljavax/xml/ws/WebServiceException;
      82: athrow
      83: getstatic     #8                  // Field log:Lorg/apache/commons/logging/Log;
      86: invokeinterface #9,  1            // InterfaceMethod org/apache/commons/logging/Log.isDebugEnabled:()Z
      91: ifeq          122
      94: getstatic     #8                  // Field log:Lorg/apache/commons/logging/Log;
      97: new           #10                 // class java/lang/StringBuilder
     100: dup
     101: invokespecial #11                 // Method java/lang/StringBuilder."<init>":()V
     104: ldc           #96                 // String EndpointDescription updated:
     106: invokevirtual #13                 // Method java/lang/StringBuilder.append:(Ljava/lang/String;)Ljava/lang/StringBuilder;
     109: aload         8
     111: invokevirtual #29                 // Method java/lang/StringBuilder.append:(Ljava/lang/Object;)Ljava/lang/StringBuilder;
     114: invokevirtual #16                 // Method java/lang/StringBuilder.toString:()Ljava/lang/String;
     117: invokeinterface #17,  2           // InterfaceMethod org/apache/commons/logging/Log.debug:(Ljava/lang/Object;)V
     122: aload         8
     124: aload         4
     126: invokestatic  #97                 // Method setPropertiesOnEndpointDesc:(Lorg/apache/axis2/jaxws/description/EndpointDescription;Lorg/apache/axis2/jaxws/description/builder/DescriptionBuilderComposite;)V
     129: aload         8
     131: areturn
    Exception table:
       from    to  target type
           8    31    34   any
          34    39    34   any

  public static org.apache.axis2.jaxws.description.EndpointDescription updateEndpoint(org.apache.axis2.jaxws.description.ServiceDescription, java.lang.Class, org.apache.axis2.addressing.EndpointReference, java.lang.String, org.apache.axis2.jaxws.description.DescriptionFactory$UpdateType, java.lang.String, java.lang.String);
    Code:
       0: aload_0
       1: aload_1
       2: aload_2
       3: aload_3
       4: aload         4
       6: aconst_null
       7: aconst_null
       8: aload         5
      10: aload         6
      12: invokestatic  #98                 // Method updateEndpoint:(Lorg/apache/axis2/jaxws/description/ServiceDescription;Ljava/lang/Class;Lorg/apache/axis2/addressing/EndpointReference;Ljava/lang/String;Lorg/apache/axis2/jaxws/description/DescriptionFactory$UpdateType;Lorg/apache/axis2/jaxws/description/builder/DescriptionBuilderComposite;Ljava/lang/Object;Ljava/lang/String;Ljava/lang/String;)Lorg/apache/axis2/jaxws/description/EndpointDescription;
      15: areturn

  public static org.apache.axis2.jaxws.description.EndpointDescription updateEndpoint(org.apache.axis2.jaxws.description.ServiceDescription, java.lang.Class, org.apache.axis2.addressing.EndpointReference, java.lang.String, org.apache.axis2.jaxws.description.DescriptionFactory$UpdateType, java.lang.Object, java.lang.String, java.lang.String);
    Code:
       0: aload_0
       1: aload_1
       2: aload_2
       3: aload_3
       4: aload         4
       6: aconst_null
       7: aload         5
       9: aload         6
      11: aload         7
      13: invokestatic  #98                 // Method updateEndpoint:(Lorg/apache/axis2/jaxws/description/ServiceDescription;Ljava/lang/Class;Lorg/apache/axis2/addressing/EndpointReference;Ljava/lang/String;Lorg/apache/axis2/jaxws/description/DescriptionFactory$UpdateType;Lorg/apache/axis2/jaxws/description/builder/DescriptionBuilderComposite;Ljava/lang/Object;Ljava/lang/String;Ljava/lang/String;)Lorg/apache/axis2/jaxws/description/EndpointDescription;
      16: areturn

  public static org.apache.axis2.jaxws.description.EndpointDescription updateEndpoint(org.apache.axis2.jaxws.description.ServiceDescription, java.lang.Class, org.apache.axis2.addressing.EndpointReference, java.lang.String, org.apache.axis2.jaxws.description.DescriptionFactory$UpdateType, org.apache.axis2.jaxws.description.builder.DescriptionBuilderComposite, java.lang.Object, java.lang.String, java.lang.String);
    Code:
       0: aconst_null
       1: astore        9
       3: aload_2
       4: aload_3
       5: invokestatic  #99                 // Method org/apache/axis2/addressing/EndpointReferenceHelper.getServiceNameMetadata:(Lorg/apache/axis2/addressing/EndpointReference;Ljava/lang/String;)Lorg/apache/axis2/addressing/metadata/ServiceName;
       8: astore        10
      10: aload_0
      11: invokeinterface #100,  1          // InterfaceMethod org/apache/axis2/jaxws/description/ServiceDescription.getServiceQName:()Ljavax/xml/namespace/QName;
      16: astore        11
      18: aload         10
      20: invokevirtual #101                // Method org/apache/axis2/addressing/metadata/ServiceName.getName:()Ljavax/xml/namespace/QName;
      23: ifnull        61
      26: aload         11
      28: aload         10
      30: invokevirtual #101                // Method org/apache/axis2/addressing/metadata/ServiceName.getName:()Ljavax/xml/namespace/QName;
      33: invokevirtual #102                // Method javax/xml/namespace/QName.equals:(Ljava/lang/Object;)Z
      36: ifne          61
      39: ldc           #103                // String serviceNameMismatch
      41: aload         10
      43: invokevirtual #101                // Method org/apache/axis2/addressing/metadata/ServiceName.getName:()Ljavax/xml/namespace/QName;
      46: invokevirtual #104                // Method javax/xml/namespace/QName.toString:()Ljava/lang/String;
      49: aload         11
      51: invokevirtual #104                // Method javax/xml/namespace/QName.toString:()Ljava/lang/String;
      54: invokestatic  #105                // Method org/apache/axis2/jaxws/i18n/Messages.getMessage:(Ljava/lang/String;Ljava/lang/String;Ljava/lang/String;)Ljava/lang/String;
      57: invokestatic  #62                 // Method org/apache/axis2/jaxws/ExceptionFactory.makeWebServiceException:(Ljava/lang/String;)Ljavax/xml/ws/WebServiceException;
      60: athrow
      61: aload         10
      63: invokevirtual #106                // Method org/apache/axis2/addressing/metadata/ServiceName.getEndpointName:()Ljava/lang/String;
      66: ifnull        88
      69: new           #83                 // class javax/xml/namespace/QName
      72: dup
      73: aload         11
      75: invokevirtual #107                // Method javax/xml/namespace/QName.getNamespaceURI:()Ljava/lang/String;
      78: aload         10
      80: invokevirtual #106                // Method org/apache/axis2/addressing/metadata/ServiceName.getEndpointName:()Ljava/lang/String;
      83: invokespecial #108                // Method javax/xml/namespace/QName."<init>":(Ljava/lang/String;Ljava/lang/String;)V
      86: astore        9
      88: goto          107
      91: astore        10
      93: ldc           #110                // String updateEndpointError
      95: aload         10
      97: invokevirtual #111                // Method java/lang/Exception.getMessage:()Ljava/lang/String;
     100: invokestatic  #61                 // Method org/apache/axis2/jaxws/i18n/Messages.getMessage:(Ljava/lang/String;Ljava/lang/String;)Ljava/lang/String;
     103: invokestatic  #62                 // Method org/apache/axis2/jaxws/ExceptionFactory.makeWebServiceException:(Ljava/lang/String;)Ljavax/xml/ws/WebServiceException;
     106: athrow
     107: aload_0
     108: aload_1
     109: aload         9
     111: aload         4
     113: aload         5
     115: aload         6
     117: aload         7
     119: aload         8
     121: invokestatic  #89                 // Method updateEndpoint:(Lorg/apache/axis2/jaxws/description/ServiceDescription;Ljava/lang/Class;Ljavax/xml/namespace/QName;Lorg/apache/axis2/jaxws/description/DescriptionFactory$UpdateType;Lorg/apache/axis2/jaxws/description/builder/DescriptionBuilderComposite;Ljava/lang/Object;Ljava/lang/String;Ljava/lang/String;)Lorg/apache/axis2/jaxws/description/EndpointDescription;
     124: areturn
    Exception table:
       from    to  target type
           3    88    91   Class java/lang/Exception

  public static org.apache.axis2.jaxws.ClientConfigurationFactory getClientConfigurationFactory();
    Code:
       0: invokestatic  #112                // Method org/apache/axis2/jaxws/ClientConfigurationFactory.newInstance:()Lorg/apache/axis2/jaxws/ClientConfigurationFactory;
       3: areturn

  private static boolean isImpl(org.apache.axis2.jaxws.description.builder.DescriptionBuilderComposite);
    Code:
       0: aload_0
       1: invokevirtual #113                // Method org/apache/axis2/jaxws/description/builder/DescriptionBuilderComposite.isInterface:()Z
       4: ifne          23
       7: aload_0
       8: invokevirtual #114                // Method org/apache/axis2/jaxws/description/builder/DescriptionBuilderComposite.getWebServiceAnnot:()Lorg/apache/axis2/jaxws/description/builder/WebServiceAnnot;
      11: ifnonnull     21
      14: aload_0
      15: invokevirtual #115                // Method org/apache/axis2/jaxws/description/builder/DescriptionBuilderComposite.getWebServiceProviderAnnot:()Lorg/apache/axis2/jaxws/description/builder/WebServiceProviderAnnot;
      18: ifnull        23
      21: iconst_1
      22: ireturn
      23: iconst_0
      24: ireturn

  static void setPropertiesOnEndpointDesc(org.apache.axis2.jaxws.description.EndpointDescription, org.apache.axis2.jaxws.description.builder.DescriptionBuilderComposite);
    Code:
       0: aload_1
       1: ifnull        129
       4: aload_1
       5: invokevirtual #116                // Method org/apache/axis2/jaxws/description/builder/DescriptionBuilderComposite.getProperties:()Ljava/util/Map;
       8: ifnull        129
      11: aload_1
      12: invokevirtual #116                // Method org/apache/axis2/jaxws/description/builder/DescriptionBuilderComposite.getProperties:()Ljava/util/Map;
      15: invokeinterface #117,  1          // InterfaceMethod java/util/Map.isEmpty:()Z
      20: ifne          129
      23: aload_1
      24: invokevirtual #116                // Method org/apache/axis2/jaxws/description/builder/DescriptionBuilderComposite.getProperties:()Ljava/util/Map;
      27: invokeinterface #44,  1           // InterfaceMethod java/util/Map.keySet:()Ljava/util/Set;
      32: invokeinterface #45,  1           // InterfaceMethod java/util/Set.iterator:()Ljava/util/Iterator;
      37: astore_2
      38: aload_2
      39: invokeinterface #46,  1           // InterfaceMethod java/util/Iterator.hasNext:()Z
      44: ifeq          129
      47: aload_2
      48: invokeinterface #47,  1           // InterfaceMethod java/util/Iterator.next:()Ljava/lang/Object;
      53: checkcast     #118                // class java/lang/String
      56: astore_3
      57: aload_1
      58: invokevirtual #116                // Method org/apache/axis2/jaxws/description/builder/DescriptionBuilderComposite.getProperties:()Ljava/util/Map;
      61: aload_3
      62: invokeinterface #21,  2           // InterfaceMethod java/util/Map.get:(Ljava/lang/Object;)Ljava/lang/Object;
      67: astore        4
      69: getstatic     #8                  // Field log:Lorg/apache/commons/logging/Log;
      72: invokeinterface #9,  1            // InterfaceMethod org/apache/commons/logging/Log.isDebugEnabled:()Z
      77: ifeq          117
      80: getstatic     #8                  // Field log:Lorg/apache/commons/logging/Log;
      83: new           #10                 // class java/lang/StringBuilder
      86: dup
      87: invokespecial #11                 // Method java/lang/StringBuilder."<init>":()V
      90: ldc           #119                // String Setting property from DBC onto EndpointDescription, key=
      92: invokevirtual #13                 // Method java/lang/StringBuilder.append:(Ljava/lang/String;)Ljava/lang/StringBuilder;
      95: aload_3
      96: invokevirtual #13                 // Method java/lang/StringBuilder.append:(Ljava/lang/String;)Ljava/lang/StringBuilder;
      99: ldc           #120                // String , value=
     101: invokevirtual #13                 // Method java/lang/StringBuilder.append:(Ljava/lang/String;)Ljava/lang/StringBuilder;
     104: aload         4
     106: invokevirtual #29                 // Method java/lang/StringBuilder.append:(Ljava/lang/Object;)Ljava/lang/StringBuilder;
     109: invokevirtual #16                 // Method java/lang/StringBuilder.toString:()Ljava/lang/String;
     112: invokeinterface #17,  2           // InterfaceMethod org/apache/commons/logging/Log.debug:(Ljava/lang/Object;)V
     117: aload_0
     118: aload_3
     119: aload         4
     121: invokeinterface #121,  3          // InterfaceMethod org/apache/axis2/jaxws/description/EndpointDescription.setProperty:(Ljava/lang/String;Ljava/lang/Object;)V
     126: goto          38
     129: return

  public static org.apache.axis2.jaxws.description.ResolvedHandlersDescription createResolvedHandlersDescription();
    Code:
       0: new           #122                // class org/apache/axis2/jaxws/description/impl/ResolvedHandlersDescriptionImpl
       3: dup
       4: invokespecial #123                // Method org/apache/axis2/jaxws/description/impl/ResolvedHandlersDescriptionImpl."<init>":()V
       7: areturn

  static boolean removeFromCache(org.apache.axis2.jaxws.description.impl.ServiceDescriptionImpl);
    Code:
       0: iconst_0
       1: istore_1
       2: aload_0
       3: invokevirtual #124                // Method org/apache/axis2/jaxws/description/impl/ServiceDescriptionImpl.getAxisConfigContext:()Lorg/apache/axis2/context/ConfigurationContext;
       6: astore_2
       7: aload_2
       8: dup
       9: astore_3
      10: monitorenter
      11: aload_0
      12: invokevirtual #125                // Method org/apache/axis2/jaxws/description/impl/ServiceDescriptionImpl.deregisterUse:()V
      15: aload_0
      16: invokevirtual #126                // Method org/apache/axis2/jaxws/description/impl/ServiceDescriptionImpl.isInUse:()Z
      19: ifeq          48
      22: getstatic     #8                  // Field log:Lorg/apache/commons/logging/Log;
      25: invokeinterface #9,  1            // InterfaceMethod org/apache/commons/logging/Log.isDebugEnabled:()Z
      30: ifeq          43
      33: getstatic     #8                  // Field log:Lorg/apache/commons/logging/Log;
      36: ldc           #127                // String ServiceDescription still in use; not removed from cache
      38: invokeinterface #17,  2           // InterfaceMethod org/apache/commons/logging/Log.debug:(Ljava/lang/Object;)V
      43: iconst_0
      44: istore_1
      45: goto          182
      48: getstatic     #8                  // Field log:Lorg/apache/commons/logging/Log;
      51: invokeinterface #9,  1            // InterfaceMethod org/apache/commons/logging/Log.isDebugEnabled:()Z
      56: ifeq          69
      59: getstatic     #8                  // Field log:Lorg/apache/commons/logging/Log;
      62: ldc           #128                // String ServiceDescription not in use; will be removed from cache
      64: invokeinterface #17,  2           // InterfaceMethod org/apache/commons/logging/Log.debug:(Ljava/lang/Object;)V
      69: iconst_1
      70: istore_1
      71: getstatic     #14                 // Field cache:Ljava/util/Map;
      74: dup
      75: astore        4
      77: monitorenter
      78: getstatic     #14                 // Field cache:Ljava/util/Map;
      81: invokeinterface #129,  1          // InterfaceMethod java/util/Map.entrySet:()Ljava/util/Set;
      86: astore        5
      88: aload         5
      90: invokeinterface #45,  1           // InterfaceMethod java/util/Set.iterator:()Ljava/util/Iterator;
      95: astore        6
      97: aload         6
      99: invokeinterface #46,  1           // InterfaceMethod java/util/Iterator.hasNext:()Z
     104: ifeq          168
     107: aload         6
     109: invokeinterface #47,  1           // InterfaceMethod java/util/Iterator.next:()Ljava/lang/Object;
     114: checkcast     #130                // class java/util/Map$Entry
     117: astore        7
     119: aload         7
     121: invokeinterface #131,  1          // InterfaceMethod java/util/Map$Entry.getValue:()Ljava/lang/Object;
     126: checkcast     #22                 // class org/apache/axis2/jaxws/description/ServiceDescription
     129: astore        8
     131: aload_0
     132: aload         8
     134: if_acmpne     165
     137: aload         6
     139: invokeinterface #49,  1           // InterfaceMethod java/util/Iterator.remove:()V
     144: getstatic     #8                  // Field log:Lorg/apache/commons/logging/Log;
     147: invokeinterface #9,  1            // InterfaceMethod org/apache/commons/logging/Log.isDebugEnabled:()Z
     152: ifeq          165
     155: getstatic     #8                  // Field log:Lorg/apache/commons/logging/Log;
     158: ldc           #132                // String Removed service description from cache
     160: invokeinterface #17,  2           // InterfaceMethod org/apache/commons/logging/Log.debug:(Ljava/lang/Object;)V
     165: goto          97
     168: aload         4
     170: monitorexit
     171: goto          182
     174: astore        9
     176: aload         4
     178: monitorexit
     179: aload         9
     181: athrow
     182: aload_3
     183: monitorexit
     184: goto          194
     187: astore        10
     189: aload_3
     190: monitorexit
     191: aload         10
     193: athrow
     194: iload_1
     195: ireturn
    Exception table:
       from    to  target type
          78   171   174   any
         174   179   174   any
          11   184   187   any
         187   191   187   any

  static {};
    Code:
       0: ldc           #133                // class org/apache/axis2/jaxws/description/impl/DescriptionFactoryImpl
       2: invokestatic  #134                // Method org/apache/commons/logging/LogFactory.getLog:(Ljava/lang/Class;)Lorg/apache/commons/logging/Log;
       5: putstatic     #8                  // Field log:Lorg/apache/commons/logging/Log;
       8: new           #135                // class java/util/Hashtable
      11: dup
      12: invokespecial #136                // Method java/util/Hashtable."<init>":()V
      15: putstatic     #14                 // Field cache:Ljava/util/Map;
      18: return
}
