Compiled from "NewInstanceAction.java"
public class org.jboss.weld.security.NewInstanceAction<T> extends org.jboss.weld.security.AbstractGenericReflectionAction<T> implements java.security.PrivilegedExceptionAction<T> {
  public static <T> org.jboss.weld.security.NewInstanceAction<T> of(java.lang.Class<T>);
    Code:
       0: new           #1                  // class org/jboss/weld/security/NewInstanceAction
       3: dup
       4: aload_0
       5: invokespecial #2                  // Method "<init>":(Ljava/lang/Class;)V
       8: areturn

  public org.jboss.weld.security.NewInstanceAction(java.lang.Class<T>);
    Code:
       0: aload_0
       1: aload_1
       2: invokespecial #3                  // Method org/jboss/weld/security/AbstractGenericReflectionAction."<init>":(Ljava/lang/Class;)V
       5: return

  public T run() throws java.lang.InstantiationException, java.lang.IllegalAccessException;
    Code:
       0: aload_0
       1: getfield      #4                  // Field javaClass:Ljava/lang/Class;
       4: invokevirtual #5                  // Method java/lang/Class.newInstance:()Ljava/lang/Object;
       7: areturn
}
