Compiled from "CoreDocumentFragmentSupport.aj"
public class org.apache.axiom.core.CoreDocumentFragmentSupport {
  private static java.lang.Throwable ajc$initFailureCause;

  public static final org.apache.axiom.core.CoreDocumentFragmentSupport ajc$perSingletonInstance;

  static {};
    Code:
       0: invokestatic  #12                 // Method ajc$postClinit:()V
       3: goto          11
       6: astore_0
       7: aload_0
       8: putstatic     #15                 // Field ajc$initFailureCause:Ljava/lang/Throwable;
      11: return
    Exception table:
       from    to  target type
           0     3     6   Class java/lang/Throwable

  public org.apache.axiom.core.CoreDocumentFragmentSupport();
    Code:
       0: aload_0
       1: invokespecial #22                 // Method java/lang/Object."<init>":()V
       4: return

  public static void ajc$interFieldInit$org_apache_axiom_core_CoreDocumentFragmentSupport$org_apache_axiom_core_CoreDocumentFragment$ownerDocument(org.apache.axiom.core.CoreDocumentFragment);
    Code:
       0: return

  public static org.apache.axiom.core.CoreDocument ajc$interFieldGetDispatch$org_apache_axiom_core_CoreDocumentFragmentSupport$org_apache_axiom_core_CoreDocumentFragment$ownerDocument(org.apache.axiom.core.CoreDocumentFragment);
    Code:
       0: aload_0
       1: invokeinterface #35,  1           // InterfaceMethod org/apache/axiom/core/CoreDocumentFragment.ajc$interFieldGet$org_apache_axiom_core_CoreDocumentFragmentSupport$org_apache_axiom_core_CoreDocumentFragment$ownerDocument:()Lorg/apache/axiom/core/CoreDocument;
       6: areturn

  public static void ajc$interFieldSetDispatch$org_apache_axiom_core_CoreDocumentFragmentSupport$org_apache_axiom_core_CoreDocumentFragment$ownerDocument(org.apache.axiom.core.CoreDocumentFragment, org.apache.axiom.core.CoreDocument);
    Code:
       0: aload_0
       1: aload_1
       2: invokeinterface #43,  2           // InterfaceMethod org/apache/axiom/core/CoreDocumentFragment.ajc$interFieldSet$org_apache_axiom_core_CoreDocumentFragmentSupport$org_apache_axiom_core_CoreDocumentFragment$ownerDocument:(Lorg/apache/axiom/core/CoreDocument;)V
       7: return

  public static org.apache.axiom.core.NodeType ajc$interMethod$org_apache_axiom_core_CoreDocumentFragmentSupport$org_apache_axiom_core_CoreDocumentFragment$coreGetNodeType(org.apache.axiom.core.CoreDocumentFragment);
    Code:
       0: getstatic     #52                 // Field org/apache/axiom/core/NodeType.DOCUMENT_FRAGMENT:Lorg/apache/axiom/core/NodeType;
       3: areturn

  public static org.apache.axiom.core.NodeType ajc$interMethodDispatch1$org_apache_axiom_core_CoreDocumentFragmentSupport$org_apache_axiom_core_CoreDocumentFragment$coreGetNodeType(org.apache.axiom.core.CoreDocumentFragment);
    Code:
       0: aload_0
       1: invokeinterface #58,  1           // InterfaceMethod org/apache/axiom/core/CoreDocumentFragment.coreGetNodeType:()Lorg/apache/axiom/core/NodeType;
       6: areturn

  public static org.apache.axiom.core.CoreNode ajc$interMethod$org_apache_axiom_core_CoreDocumentFragmentSupport$org_apache_axiom_core_CoreDocumentFragment$getRootOrOwnerDocument(org.apache.axiom.core.CoreDocumentFragment);
    Code:
       0: aload_0
       1: invokestatic  #65                 // Method ajc$interFieldGetDispatch$org_apache_axiom_core_CoreDocumentFragmentSupport$org_apache_axiom_core_CoreDocumentFragment$ownerDocument:(Lorg/apache/axiom/core/CoreDocumentFragment;)Lorg/apache/axiom/core/CoreDocument;
       4: ifnonnull     9
       7: aload_0
       8: areturn
       9: aload_0
      10: invokestatic  #65                 // Method ajc$interFieldGetDispatch$org_apache_axiom_core_CoreDocumentFragmentSupport$org_apache_axiom_core_CoreDocumentFragment$ownerDocument:(Lorg/apache/axiom/core/CoreDocumentFragment;)Lorg/apache/axiom/core/CoreDocument;
      13: areturn

  public static org.apache.axiom.core.CoreNode ajc$interMethodDispatch1$org_apache_axiom_core_CoreDocumentFragmentSupport$org_apache_axiom_core_CoreDocumentFragment$getRootOrOwnerDocument(org.apache.axiom.core.CoreDocumentFragment);
    Code:
       0: aload_0
       1: invokeinterface #68,  1           // InterfaceMethod org/apache/axiom/core/CoreDocumentFragment.getRootOrOwnerDocument:()Lorg/apache/axiom/core/CoreNode;
       6: areturn

  public static void ajc$interMethod$org_apache_axiom_core_CoreDocumentFragmentSupport$org_apache_axiom_core_CoreDocumentFragment$coreSetOwnerDocument(org.apache.axiom.core.CoreDocumentFragment, org.apache.axiom.core.CoreDocument);
    Code:
       0: aload_0
       1: aload_1
       2: invokestatic  #73                 // Method ajc$interFieldSetDispatch$org_apache_axiom_core_CoreDocumentFragmentSupport$org_apache_axiom_core_CoreDocumentFragment$ownerDocument:(Lorg/apache/axiom/core/CoreDocumentFragment;Lorg/apache/axiom/core/CoreDocument;)V
       5: return

  public static void ajc$interMethodDispatch1$org_apache_axiom_core_CoreDocumentFragmentSupport$org_apache_axiom_core_CoreDocumentFragment$coreSetOwnerDocument(org.apache.axiom.core.CoreDocumentFragment, org.apache.axiom.core.CoreDocument);
    Code:
       0: aload_0
       1: aload_1
       2: invokeinterface #77,  2           // InterfaceMethod org/apache/axiom/core/CoreDocumentFragment.coreSetOwnerDocument:(Lorg/apache/axiom/core/CoreDocument;)V
       7: return

  public static <T> void ajc$interMethod$org_apache_axiom_core_CoreDocumentFragmentSupport$org_apache_axiom_core_CoreDocumentFragment$init(org.apache.axiom.core.CoreDocumentFragment, org.apache.axiom.core.ClonePolicy<T>, T, org.apache.axiom.core.CoreNode);
    Code:
       0: return

  public static <T> void ajc$interMethodDispatch1$org_apache_axiom_core_CoreDocumentFragmentSupport$org_apache_axiom_core_CoreDocumentFragment$init(org.apache.axiom.core.CoreDocumentFragment, org.apache.axiom.core.ClonePolicy<T>, T, org.apache.axiom.core.CoreNode);
    Code:
       0: aload_0
       1: aload_1
       2: aload_2
       3: aload_3
       4: invokeinterface #95,  4           // InterfaceMethod org/apache/axiom/core/CoreDocumentFragment.init:(Lorg/apache/axiom/core/ClonePolicy;Ljava/lang/Object;Lorg/apache/axiom/core/CoreNode;)V
       9: return

  public static org.apache.axiom.core.CoreDocumentFragmentSupport aspectOf();
    Code:
       0: getstatic     #100                // Field ajc$perSingletonInstance:Lorg/apache/axiom/core/CoreDocumentFragmentSupport;
       3: ifnonnull     19
       6: new           #102                // class org/aspectj/lang/NoAspectBoundException
       9: dup
      10: ldc           #104                // String org_apache_axiom_core_CoreDocumentFragmentSupport
      12: getstatic     #15                 // Field ajc$initFailureCause:Ljava/lang/Throwable;
      15: invokespecial #106                // Method org/aspectj/lang/NoAspectBoundException."<init>":(Ljava/lang/String;Ljava/lang/Throwable;)V
      18: athrow
      19: getstatic     #100                // Field ajc$perSingletonInstance:Lorg/apache/axiom/core/CoreDocumentFragmentSupport;
      22: areturn

  public static boolean hasAspect();
    Code:
       0: getstatic     #100                // Field ajc$perSingletonInstance:Lorg/apache/axiom/core/CoreDocumentFragmentSupport;
       3: ifnull        8
       6: iconst_1
       7: ireturn
       8: iconst_0
       9: ireturn

  private static void ajc$postClinit();
    Code:
       0: new           #1                  // class org/apache/axiom/core/CoreDocumentFragmentSupport
       3: dup
       4: invokespecial #111                // Method "<init>":()V
       7: putstatic     #100                // Field ajc$perSingletonInstance:Lorg/apache/axiom/core/CoreDocumentFragmentSupport;
      10: return
}
