Compiled from "JpaIntegrator.java"
class org.hibernate.jpa.event.spi.JpaIntegrator$PersistCascadeStyle extends org.hibernate.engine.spi.CascadeStyles$BaseCascadeStyle {
  private org.hibernate.jpa.event.spi.JpaIntegrator$PersistCascadeStyle();
    Code:
       0: aload_0
       1: invokespecial #2                  // Method org/hibernate/engine/spi/CascadeStyles$BaseCascadeStyle."<init>":()V
       4: return

  public boolean doCascade(org.hibernate.engine.spi.CascadingAction);
    Code:
       0: aload_1
       1: getstatic     #3                  // Field org/hibernate/jpa/event/internal/core/JpaPersistEventListener.PERSIST_SKIPLAZY:Lorg/hibernate/engine/spi/CascadingAction;
       4: if_acmpeq     14
       7: aload_1
       8: getstatic     #4                  // Field org/hibernate/engine/spi/CascadingActions.PERSIST_ON_FLUSH:Lorg/hibernate/engine/spi/CascadingAction;
      11: if_acmpne     18
      14: iconst_1
      15: goto          19
      18: iconst_0
      19: ireturn

  public java.lang.String toString();
    Code:
       0: ldc           #5                  // String STYLE_PERSIST_SKIPLAZY
       2: areturn

  org.hibernate.jpa.event.spi.JpaIntegrator$PersistCascadeStyle(org.hibernate.jpa.event.spi.JpaIntegrator$1);
    Code:
       0: aload_0
       1: invokespecial #1                  // Method "<init>":()V
       4: return
}
