Compiled from "Yaml.java"
class io.dekorate.deps.snakeyaml.Yaml$3 implements java.util.Iterator<io.dekorate.deps.snakeyaml.events.Event> {
  final io.dekorate.deps.snakeyaml.parser.Parser val$parser;

  final io.dekorate.deps.snakeyaml.Yaml this$0;

  io.dekorate.deps.snakeyaml.Yaml$3(io.dekorate.deps.snakeyaml.Yaml, io.dekorate.deps.snakeyaml.parser.Parser);
    Code:
       0: aload_0
       1: aload_1
       2: putfield      #21                 // Field this$0:Lio/dekorate/deps/snakeyaml/Yaml;
       5: aload_0
       6: aload_2
       7: putfield      #23                 // Field val$parser:Lio/dekorate/deps/snakeyaml/parser/Parser;
      10: aload_0
      11: invokespecial #26                 // Method java/lang/Object."<init>":()V
      14: return

  public boolean hasNext();
    Code:
       0: aload_0
       1: getfield      #23                 // Field val$parser:Lio/dekorate/deps/snakeyaml/parser/Parser;
       4: invokeinterface #36,  1           // InterfaceMethod io/dekorate/deps/snakeyaml/parser/Parser.peekEvent:()Lio/dekorate/deps/snakeyaml/events/Event;
       9: ifnull        16
      12: iconst_1
      13: goto          17
      16: iconst_0
      17: ireturn

  public io.dekorate.deps.snakeyaml.events.Event next();
    Code:
       0: aload_0
       1: getfield      #23                 // Field val$parser:Lio/dekorate/deps/snakeyaml/parser/Parser;
       4: invokeinterface #40,  1           // InterfaceMethod io/dekorate/deps/snakeyaml/parser/Parser.getEvent:()Lio/dekorate/deps/snakeyaml/events/Event;
       9: areturn

  public void remove();
    Code:
       0: new           #43                 // class java/lang/UnsupportedOperationException
       3: dup
       4: invokespecial #44                 // Method java/lang/UnsupportedOperationException."<init>":()V
       7: athrow

  public java.lang.Object next();
    Code:
       0: aload_0
       1: invokevirtual #47                 // Method next:()Lio/dekorate/deps/snakeyaml/events/Event;
       4: areturn
}
