Compiled from "Framing.scala"
public class akka.stream.scaladsl.Framing$DelimiterFramingStage extends akka.stream.stage.GraphStage<akka.stream.FlowShape<akka.util.ByteString, akka.util.ByteString>> {
  private final akka.util.ByteString separatorBytes;

  private final int maximumLineBytes;

  private final boolean allowTruncation;

  private final akka.stream.Inlet<akka.util.ByteString> in;

  private final akka.stream.Outlet<akka.util.ByteString> out;

  private final akka.stream.FlowShape<akka.util.ByteString, akka.util.ByteString> shape;

  public akka.util.ByteString separatorBytes();
    Code:
       0: aload_0
       1: getfield      #24                 // Field separatorBytes:Lakka/util/ByteString;
       4: areturn

  public int maximumLineBytes();
    Code:
       0: aload_0
       1: getfield      #29                 // Field maximumLineBytes:I
       4: ireturn

  public boolean allowTruncation();
    Code:
       0: aload_0
       1: getfield      #32                 // Field allowTruncation:Z
       4: ireturn

  public akka.stream.Inlet<akka.util.ByteString> in();
    Code:
       0: aload_0
       1: getfield      #35                 // Field in:Lakka/stream/Inlet;
       4: areturn

  public akka.stream.Outlet<akka.util.ByteString> out();
    Code:
       0: aload_0
       1: getfield      #38                 // Field out:Lakka/stream/Outlet;
       4: areturn

  public akka.stream.FlowShape<akka.util.ByteString, akka.util.ByteString> shape();
    Code:
       0: aload_0
       1: getfield      #41                 // Field shape:Lakka/stream/FlowShape;
       4: areturn

  public akka.stream.Attributes initialAttributes();
    Code:
       0: getstatic     #49                 // Field akka/stream/impl/Stages$DefaultAttributes$.MODULE$:Lakka/stream/impl/Stages$DefaultAttributes$;
       3: invokevirtual #52                 // Method akka/stream/impl/Stages$DefaultAttributes$.delimiterFraming:()Lakka/stream/Attributes;
       6: areturn

  public java.lang.String toString();
    Code:
       0: ldc           #56                 // String DelimiterFraming
       2: areturn

  public akka.stream.stage.GraphStageLogic createLogic(akka.stream.Attributes);
    Code:
       0: new           #60                 // class akka/stream/scaladsl/Framing$DelimiterFramingStage$$anon$2
       3: dup
       4: aload_0
       5: invokespecial #64                 // Method akka/stream/scaladsl/Framing$DelimiterFramingStage$$anon$2."<init>":(Lakka/stream/scaladsl/Framing$DelimiterFramingStage;)V
       8: areturn

  public akka.stream.Shape shape();
    Code:
       0: aload_0
       1: invokevirtual #69                 // Method shape:()Lakka/stream/FlowShape;
       4: areturn

  public akka.stream.scaladsl.Framing$DelimiterFramingStage(akka.util.ByteString, int, boolean);
    Code:
       0: aload_0
       1: aload_1
       2: putfield      #24                 // Field separatorBytes:Lakka/util/ByteString;
       5: aload_0
       6: iload_2
       7: putfield      #29                 // Field maximumLineBytes:I
      10: aload_0
      11: iload_3
      12: putfield      #32                 // Field allowTruncation:Z
      15: aload_0
      16: invokespecial #73                 // Method akka/stream/stage/GraphStage."<init>":()V
      19: aload_0
      20: getstatic     #78                 // Field akka/stream/Inlet$.MODULE$:Lakka/stream/Inlet$;
      23: ldc           #80                 // String DelimiterFramingStage.in
      25: invokevirtual #84                 // Method akka/stream/Inlet$.apply:(Ljava/lang/String;)Lakka/stream/Inlet;
      28: putfield      #35                 // Field in:Lakka/stream/Inlet;
      31: aload_0
      32: getstatic     #89                 // Field akka/stream/Outlet$.MODULE$:Lakka/stream/Outlet$;
      35: ldc           #91                 // String DelimiterFramingStage.out
      37: invokevirtual #94                 // Method akka/stream/Outlet$.apply:(Ljava/lang/String;)Lakka/stream/Outlet;
      40: putfield      #38                 // Field out:Lakka/stream/Outlet;
      43: aload_0
      44: new           #96                 // class akka/stream/FlowShape
      47: dup
      48: aload_0
      49: invokevirtual #98                 // Method in:()Lakka/stream/Inlet;
      52: aload_0
      53: invokevirtual #100                // Method out:()Lakka/stream/Outlet;
      56: invokespecial #103                // Method akka/stream/FlowShape."<init>":(Lakka/stream/Inlet;Lakka/stream/Outlet;)V
      59: putfield      #41                 // Field shape:Lakka/stream/FlowShape;
      62: return
}
