Compiled from "Graph.scala"
public final class akka.stream.scaladsl.GraphDSL$Implicits$BidiFlowShapeArrow<I1, O1, I2, O2> {
  private final akka.stream.BidiShape<I1, O1, I2, O2> bidi;

  public akka.stream.BidiShape<I1, O1, I2, O2> bidi();
    Code:
       0: aload_0
       1: getfield      #12                 // Field bidi:Lakka/stream/BidiShape;
       4: areturn

  public <I3, O3> akka.stream.BidiShape<O1, O3, I3, I2> $less$tilde$greater(akka.stream.BidiShape<O1, O3, I3, I2>, akka.stream.scaladsl.GraphDSL$Builder<?>);
    Code:
       0: getstatic     #22                 // Field akka/stream/scaladsl/GraphDSL$Implicits$BidiFlowShapeArrow$.MODULE$:Lakka/stream/scaladsl/GraphDSL$Implicits$BidiFlowShapeArrow$;
       3: aload_0
       4: invokevirtual #24                 // Method bidi:()Lakka/stream/BidiShape;
       7: aload_1
       8: aload_2
       9: invokevirtual #28                 // Method akka/stream/scaladsl/GraphDSL$Implicits$BidiFlowShapeArrow$.$less$tilde$greater$extension0:(Lakka/stream/BidiShape;Lakka/stream/BidiShape;Lakka/stream/scaladsl/GraphDSL$Builder;)Lakka/stream/BidiShape;
      12: areturn

  public <I3, O3, M> akka.stream.BidiShape<O1, O3, I3, I2> $less$tilde$greater(akka.stream.Graph<akka.stream.BidiShape<O1, O3, I3, I2>, M>, akka.stream.scaladsl.GraphDSL$Builder<?>);
    Code:
       0: getstatic     #22                 // Field akka/stream/scaladsl/GraphDSL$Implicits$BidiFlowShapeArrow$.MODULE$:Lakka/stream/scaladsl/GraphDSL$Implicits$BidiFlowShapeArrow$;
       3: aload_0
       4: invokevirtual #24                 // Method bidi:()Lakka/stream/BidiShape;
       7: aload_1
       8: aload_2
       9: invokevirtual #36                 // Method akka/stream/scaladsl/GraphDSL$Implicits$BidiFlowShapeArrow$.$less$tilde$greater$extension1:(Lakka/stream/BidiShape;Lakka/stream/Graph;Lakka/stream/scaladsl/GraphDSL$Builder;)Lakka/stream/BidiShape;
      12: areturn

  public void $less$tilde$greater(akka.stream.FlowShape<O1, I2>, akka.stream.scaladsl.GraphDSL$Builder<?>);
    Code:
       0: getstatic     #22                 // Field akka/stream/scaladsl/GraphDSL$Implicits$BidiFlowShapeArrow$.MODULE$:Lakka/stream/scaladsl/GraphDSL$Implicits$BidiFlowShapeArrow$;
       3: aload_0
       4: invokevirtual #24                 // Method bidi:()Lakka/stream/BidiShape;
       7: aload_1
       8: aload_2
       9: invokevirtual #43                 // Method akka/stream/scaladsl/GraphDSL$Implicits$BidiFlowShapeArrow$.$less$tilde$greater$extension2:(Lakka/stream/BidiShape;Lakka/stream/FlowShape;Lakka/stream/scaladsl/GraphDSL$Builder;)V
      12: return

  public <M> void $less$tilde$greater(akka.stream.Graph<akka.stream.FlowShape<O1, I2>, M>, akka.stream.scaladsl.GraphDSL$Builder<?>);
    Code:
       0: getstatic     #22                 // Field akka/stream/scaladsl/GraphDSL$Implicits$BidiFlowShapeArrow$.MODULE$:Lakka/stream/scaladsl/GraphDSL$Implicits$BidiFlowShapeArrow$;
       3: aload_0
       4: invokevirtual #24                 // Method bidi:()Lakka/stream/BidiShape;
       7: aload_1
       8: aload_2
       9: invokevirtual #50                 // Method akka/stream/scaladsl/GraphDSL$Implicits$BidiFlowShapeArrow$.$less$tilde$greater$extension3:(Lakka/stream/BidiShape;Lakka/stream/Graph;Lakka/stream/scaladsl/GraphDSL$Builder;)V
      12: return

  public int hashCode();
    Code:
       0: getstatic     #22                 // Field akka/stream/scaladsl/GraphDSL$Implicits$BidiFlowShapeArrow$.MODULE$:Lakka/stream/scaladsl/GraphDSL$Implicits$BidiFlowShapeArrow$;
       3: aload_0
       4: invokevirtual #24                 // Method bidi:()Lakka/stream/BidiShape;
       7: invokevirtual #57                 // Method akka/stream/scaladsl/GraphDSL$Implicits$BidiFlowShapeArrow$.hashCode$extension:(Lakka/stream/BidiShape;)I
      10: ireturn

  public boolean equals(java.lang.Object);
    Code:
       0: getstatic     #22                 // Field akka/stream/scaladsl/GraphDSL$Implicits$BidiFlowShapeArrow$.MODULE$:Lakka/stream/scaladsl/GraphDSL$Implicits$BidiFlowShapeArrow$;
       3: aload_0
       4: invokevirtual #24                 // Method bidi:()Lakka/stream/BidiShape;
       7: aload_1
       8: invokevirtual #63                 // Method akka/stream/scaladsl/GraphDSL$Implicits$BidiFlowShapeArrow$.equals$extension:(Lakka/stream/BidiShape;Ljava/lang/Object;)Z
      11: ireturn

  public akka.stream.scaladsl.GraphDSL$Implicits$BidiFlowShapeArrow(akka.stream.BidiShape<I1, O1, I2, O2>);
    Code:
       0: aload_0
       1: aload_1
       2: putfield      #12                 // Field bidi:Lakka/stream/BidiShape;
       5: aload_0
       6: invokespecial #70                 // Method java/lang/Object."<init>":()V
       9: return
}
