Compiled from "Graph.scala"
public final class akka.stream.scaladsl.Interleave$$anon$3$$anonfun$15$$anon$13 implements akka.stream.stage.InHandler {
  private final akka.stream.scaladsl.Interleave$$anon$3$$anonfun$15 $outer;

  private final akka.stream.Inlet i$4;

  public void onUpstreamFailure(java.lang.Throwable) throws java.lang.Exception;
    Code:
       0: aload_0
       1: aload_1
       2: invokestatic  #22                 // Method akka/stream/stage/InHandler$class.onUpstreamFailure:(Lakka/stream/stage/InHandler;Ljava/lang/Throwable;)V
       5: return

  public void onPush();
    Code:
       0: aload_0
       1: getfield      #30                 // Field $outer:Lakka/stream/scaladsl/Interleave$$anon$3$$anonfun$15;
       4: invokevirtual #34                 // Method akka/stream/scaladsl/Interleave$$anon$3$$anonfun$15.akka$stream$scaladsl$Interleave$$anon$$anonfun$$$outer:()Lakka/stream/scaladsl/Interleave$$anon$3;
       7: aload_0
       8: getfield      #30                 // Field $outer:Lakka/stream/scaladsl/Interleave$$anon$3$$anonfun$15;
      11: invokevirtual #34                 // Method akka/stream/scaladsl/Interleave$$anon$3$$anonfun$15.akka$stream$scaladsl$Interleave$$anon$$anonfun$$$outer:()Lakka/stream/scaladsl/Interleave$$anon$3;
      14: invokevirtual #40                 // Method akka/stream/scaladsl/Interleave$$anon$3.akka$stream$scaladsl$Interleave$$anon$$$outer:()Lakka/stream/scaladsl/Interleave;
      17: invokevirtual #46                 // Method akka/stream/scaladsl/Interleave.out:()Lakka/stream/Outlet;
      20: aload_0
      21: getfield      #30                 // Field $outer:Lakka/stream/scaladsl/Interleave$$anon$3$$anonfun$15;
      24: invokevirtual #34                 // Method akka/stream/scaladsl/Interleave$$anon$3$$anonfun$15.akka$stream$scaladsl$Interleave$$anon$$anonfun$$$outer:()Lakka/stream/scaladsl/Interleave$$anon$3;
      27: aload_0
      28: getfield      #48                 // Field i$4:Lakka/stream/Inlet;
      31: invokevirtual #52                 // Method akka/stream/scaladsl/Interleave$$anon$3.grab:(Lakka/stream/Inlet;)Ljava/lang/Object;
      34: invokevirtual #56                 // Method akka/stream/scaladsl/Interleave$$anon$3.push:(Lakka/stream/Outlet;Ljava/lang/Object;)V
      37: aload_0
      38: getfield      #30                 // Field $outer:Lakka/stream/scaladsl/Interleave$$anon$3$$anonfun$15;
      41: invokevirtual #34                 // Method akka/stream/scaladsl/Interleave$$anon$3$$anonfun$15.akka$stream$scaladsl$Interleave$$anon$$anonfun$$$outer:()Lakka/stream/scaladsl/Interleave$$anon$3;
      44: aload_0
      45: getfield      #30                 // Field $outer:Lakka/stream/scaladsl/Interleave$$anon$3$$anonfun$15;
      48: invokevirtual #34                 // Method akka/stream/scaladsl/Interleave$$anon$3$$anonfun$15.akka$stream$scaladsl$Interleave$$anon$$anonfun$$$outer:()Lakka/stream/scaladsl/Interleave$$anon$3;
      51: invokevirtual #60                 // Method akka/stream/scaladsl/Interleave$$anon$3.akka$stream$scaladsl$Interleave$$anon$$counter:()I
      54: iconst_1
      55: iadd
      56: invokevirtual #64                 // Method akka/stream/scaladsl/Interleave$$anon$3.akka$stream$scaladsl$Interleave$$anon$$counter_$eq:(I)V
      59: aload_0
      60: getfield      #30                 // Field $outer:Lakka/stream/scaladsl/Interleave$$anon$3$$anonfun$15;
      63: invokevirtual #34                 // Method akka/stream/scaladsl/Interleave$$anon$3$$anonfun$15.akka$stream$scaladsl$Interleave$$anon$$anonfun$$$outer:()Lakka/stream/scaladsl/Interleave$$anon$3;
      66: invokevirtual #60                 // Method akka/stream/scaladsl/Interleave$$anon$3.akka$stream$scaladsl$Interleave$$anon$$counter:()I
      69: aload_0
      70: getfield      #30                 // Field $outer:Lakka/stream/scaladsl/Interleave$$anon$3$$anonfun$15;
      73: invokevirtual #34                 // Method akka/stream/scaladsl/Interleave$$anon$3$$anonfun$15.akka$stream$scaladsl$Interleave$$anon$$anonfun$$$outer:()Lakka/stream/scaladsl/Interleave$$anon$3;
      76: invokevirtual #40                 // Method akka/stream/scaladsl/Interleave$$anon$3.akka$stream$scaladsl$Interleave$$anon$$$outer:()Lakka/stream/scaladsl/Interleave;
      79: invokevirtual #67                 // Method akka/stream/scaladsl/Interleave.segmentSize:()I
      82: if_icmpne     95
      85: aload_0
      86: getfield      #30                 // Field $outer:Lakka/stream/scaladsl/Interleave$$anon$3$$anonfun$15;
      89: invokevirtual #34                 // Method akka/stream/scaladsl/Interleave$$anon$3$$anonfun$15.akka$stream$scaladsl$Interleave$$anon$$anonfun$$$outer:()Lakka/stream/scaladsl/Interleave$$anon$3;
      92: invokevirtual #70                 // Method akka/stream/scaladsl/Interleave$$anon$3.akka$stream$scaladsl$Interleave$$anon$$switchToNextInput:()V
      95: return

  public void onUpstreamFinish();
    Code:
       0: aload_0
       1: getfield      #30                 // Field $outer:Lakka/stream/scaladsl/Interleave$$anon$3$$anonfun$15;
       4: invokevirtual #34                 // Method akka/stream/scaladsl/Interleave$$anon$3$$anonfun$15.akka$stream$scaladsl$Interleave$$anon$$anonfun$$$outer:()Lakka/stream/scaladsl/Interleave$$anon$3;
       7: invokevirtual #40                 // Method akka/stream/scaladsl/Interleave$$anon$3.akka$stream$scaladsl$Interleave$$anon$$$outer:()Lakka/stream/scaladsl/Interleave;
      10: invokevirtual #75                 // Method akka/stream/scaladsl/Interleave.eagerClose:()Z
      13: ifeq          29
      16: aload_0
      17: getfield      #30                 // Field $outer:Lakka/stream/scaladsl/Interleave$$anon$3$$anonfun$15;
      20: invokevirtual #34                 // Method akka/stream/scaladsl/Interleave$$anon$3$$anonfun$15.akka$stream$scaladsl$Interleave$$anon$$anonfun$$$outer:()Lakka/stream/scaladsl/Interleave$$anon$3;
      23: invokevirtual #78                 // Method akka/stream/scaladsl/Interleave$$anon$3.completeStage:()V
      26: goto          167
      29: aload_0
      30: getfield      #30                 // Field $outer:Lakka/stream/scaladsl/Interleave$$anon$3$$anonfun$15;
      33: invokevirtual #34                 // Method akka/stream/scaladsl/Interleave$$anon$3$$anonfun$15.akka$stream$scaladsl$Interleave$$anon$$anonfun$$$outer:()Lakka/stream/scaladsl/Interleave$$anon$3;
      36: aload_0
      37: getfield      #30                 // Field $outer:Lakka/stream/scaladsl/Interleave$$anon$3$$anonfun$15;
      40: invokevirtual #34                 // Method akka/stream/scaladsl/Interleave$$anon$3$$anonfun$15.akka$stream$scaladsl$Interleave$$anon$$anonfun$$$outer:()Lakka/stream/scaladsl/Interleave$$anon$3;
      43: invokevirtual #81                 // Method akka/stream/scaladsl/Interleave$$anon$3.akka$stream$scaladsl$Interleave$$anon$$runningUpstreams:()I
      46: iconst_1
      47: isub
      48: invokevirtual #84                 // Method akka/stream/scaladsl/Interleave$$anon$3.akka$stream$scaladsl$Interleave$$anon$$runningUpstreams_$eq:(I)V
      51: aload_0
      52: getfield      #30                 // Field $outer:Lakka/stream/scaladsl/Interleave$$anon$3$$anonfun$15;
      55: invokevirtual #34                 // Method akka/stream/scaladsl/Interleave$$anon$3$$anonfun$15.akka$stream$scaladsl$Interleave$$anon$$anonfun$$$outer:()Lakka/stream/scaladsl/Interleave$$anon$3;
      58: invokevirtual #87                 // Method akka/stream/scaladsl/Interleave$$anon$3.akka$stream$scaladsl$Interleave$$anon$$upstreamsClosed:()Z
      61: ifeq          77
      64: aload_0
      65: getfield      #30                 // Field $outer:Lakka/stream/scaladsl/Interleave$$anon$3$$anonfun$15;
      68: invokevirtual #34                 // Method akka/stream/scaladsl/Interleave$$anon$3$$anonfun$15.akka$stream$scaladsl$Interleave$$anon$$anonfun$$$outer:()Lakka/stream/scaladsl/Interleave$$anon$3;
      71: invokevirtual #78                 // Method akka/stream/scaladsl/Interleave$$anon$3.completeStage:()V
      74: goto          167
      77: aload_0
      78: getfield      #48                 // Field i$4:Lakka/stream/Inlet;
      81: aload_0
      82: getfield      #30                 // Field $outer:Lakka/stream/scaladsl/Interleave$$anon$3$$anonfun$15;
      85: invokevirtual #34                 // Method akka/stream/scaladsl/Interleave$$anon$3$$anonfun$15.akka$stream$scaladsl$Interleave$$anon$$anonfun$$$outer:()Lakka/stream/scaladsl/Interleave$$anon$3;
      88: invokevirtual #91                 // Method akka/stream/scaladsl/Interleave$$anon$3.akka$stream$scaladsl$Interleave$$anon$$currentUpstream:()Lakka/stream/Inlet;
      91: astore_1
      92: dup
      93: ifnonnull     104
      96: pop
      97: aload_1
      98: ifnull        111
     101: goto          167
     104: aload_1
     105: invokevirtual #95                 // Method java/lang/Object.equals:(Ljava/lang/Object;)Z
     108: ifeq          167
     111: aload_0
     112: getfield      #30                 // Field $outer:Lakka/stream/scaladsl/Interleave$$anon$3$$anonfun$15;
     115: invokevirtual #34                 // Method akka/stream/scaladsl/Interleave$$anon$3$$anonfun$15.akka$stream$scaladsl$Interleave$$anon$$anonfun$$$outer:()Lakka/stream/scaladsl/Interleave$$anon$3;
     118: invokevirtual #70                 // Method akka/stream/scaladsl/Interleave$$anon$3.akka$stream$scaladsl$Interleave$$anon$$switchToNextInput:()V
     121: aload_0
     122: getfield      #30                 // Field $outer:Lakka/stream/scaladsl/Interleave$$anon$3$$anonfun$15;
     125: invokevirtual #34                 // Method akka/stream/scaladsl/Interleave$$anon$3$$anonfun$15.akka$stream$scaladsl$Interleave$$anon$$anonfun$$$outer:()Lakka/stream/scaladsl/Interleave$$anon$3;
     128: aload_0
     129: getfield      #30                 // Field $outer:Lakka/stream/scaladsl/Interleave$$anon$3$$anonfun$15;
     132: invokevirtual #34                 // Method akka/stream/scaladsl/Interleave$$anon$3$$anonfun$15.akka$stream$scaladsl$Interleave$$anon$$anonfun$$$outer:()Lakka/stream/scaladsl/Interleave$$anon$3;
     135: invokevirtual #40                 // Method akka/stream/scaladsl/Interleave$$anon$3.akka$stream$scaladsl$Interleave$$anon$$$outer:()Lakka/stream/scaladsl/Interleave;
     138: invokevirtual #46                 // Method akka/stream/scaladsl/Interleave.out:()Lakka/stream/Outlet;
     141: invokevirtual #99                 // Method akka/stream/scaladsl/Interleave$$anon$3.isAvailable:(Lakka/stream/Outlet;)Z
     144: ifeq          167
     147: aload_0
     148: getfield      #30                 // Field $outer:Lakka/stream/scaladsl/Interleave$$anon$3$$anonfun$15;
     151: invokevirtual #34                 // Method akka/stream/scaladsl/Interleave$$anon$3$$anonfun$15.akka$stream$scaladsl$Interleave$$anon$$anonfun$$$outer:()Lakka/stream/scaladsl/Interleave$$anon$3;
     154: aload_0
     155: getfield      #30                 // Field $outer:Lakka/stream/scaladsl/Interleave$$anon$3$$anonfun$15;
     158: invokevirtual #34                 // Method akka/stream/scaladsl/Interleave$$anon$3$$anonfun$15.akka$stream$scaladsl$Interleave$$anon$$anonfun$$$outer:()Lakka/stream/scaladsl/Interleave$$anon$3;
     161: invokevirtual #91                 // Method akka/stream/scaladsl/Interleave$$anon$3.akka$stream$scaladsl$Interleave$$anon$$currentUpstream:()Lakka/stream/Inlet;
     164: invokevirtual #103                // Method akka/stream/scaladsl/Interleave$$anon$3.pull:(Lakka/stream/Inlet;)V
     167: return

  public akka.stream.scaladsl.Interleave$$anon$3$$anonfun$15$$anon$13(akka.stream.scaladsl.Interleave<T>.$anon$3$$anonfun$15);
    Code:
       0: aload_1
       1: ifnonnull     6
       4: aconst_null
       5: athrow
       6: aload_0
       7: aload_1
       8: putfield      #30                 // Field $outer:Lakka/stream/scaladsl/Interleave$$anon$3$$anonfun$15;
      11: aload_0
      12: aload_2
      13: putfield      #48                 // Field i$4:Lakka/stream/Inlet;
      16: aload_0
      17: invokespecial #109                // Method java/lang/Object."<init>":()V
      20: aload_0
      21: invokestatic  #113                // Method akka/stream/stage/InHandler$class.$init$:(Lakka/stream/stage/InHandler;)V
      24: return
}
