Compiled from "StreamConverters.scala"
public final class akka.stream.scaladsl.StreamConverters$$anonfun$javaCollectorParallelUnordered$1$$anonfun$apply$3$$anonfun$apply$5 extends scala.runtime.AbstractFunction0<akka.stream.impl.ReducerState<T, R>> implements scala.Serializable {
  public static final long serialVersionUID;

  private final java.util.stream.Collector collector$1;

  public final akka.stream.impl.ReducerState<T, R> apply();
    Code:
       0: new           #20                 // class akka/stream/impl/ReducerState
       3: dup
       4: aload_0
       5: getfield      #22                 // Field collector$1:Ljava/util/stream/Collector;
       8: invokespecial #26                 // Method akka/stream/impl/ReducerState."<init>":(Ljava/util/stream/Collector;)V
      11: areturn

  public final java.lang.Object apply();
    Code:
       0: aload_0
       1: invokevirtual #31                 // Method apply:()Lakka/stream/impl/ReducerState;
       4: areturn

  public akka.stream.scaladsl.StreamConverters$$anonfun$javaCollectorParallelUnordered$1$$anonfun$apply$3$$anonfun$apply$5(akka.stream.scaladsl.StreamConverters$$anonfun$javaCollectorParallelUnordered$1$$anonfun$apply$3, java.util.stream.Collector);
    Code:
       0: aload_0
       1: aload_2
       2: putfield      #22                 // Field collector$1:Ljava/util/stream/Collector;
       5: aload_0
       6: invokespecial #35                 // Method scala/runtime/AbstractFunction0."<init>":()V
       9: return
}
