Compiled from "ZipWithApply.scala"
public abstract class akka.stream.scaladsl.ZipWithApply$class {
  public static akka.stream.scaladsl.ZipWith2 apply(akka.stream.scaladsl.ZipWithApply, scala.Function2);
    Code:
       0: new           #9                  // class akka/stream/scaladsl/ZipWith2
       3: dup
       4: aload_1
       5: invokespecial #13                 // Method akka/stream/scaladsl/ZipWith2."<init>":(Lscala/Function2;)V
       8: areturn

  public static akka.stream.scaladsl.ZipWith3 apply(akka.stream.scaladsl.ZipWithApply, scala.Function3);
    Code:
       0: new           #20                 // class akka/stream/scaladsl/ZipWith3
       3: dup
       4: aload_1
       5: invokespecial #23                 // Method akka/stream/scaladsl/ZipWith3."<init>":(Lscala/Function3;)V
       8: areturn

  public static akka.stream.scaladsl.ZipWith4 apply(akka.stream.scaladsl.ZipWithApply, scala.Function4);
    Code:
       0: new           #27                 // class akka/stream/scaladsl/ZipWith4
       3: dup
       4: aload_1
       5: invokespecial #30                 // Method akka/stream/scaladsl/ZipWith4."<init>":(Lscala/Function4;)V
       8: areturn

  public static akka.stream.scaladsl.ZipWith5 apply(akka.stream.scaladsl.ZipWithApply, scala.Function5);
    Code:
       0: new           #34                 // class akka/stream/scaladsl/ZipWith5
       3: dup
       4: aload_1
       5: invokespecial #37                 // Method akka/stream/scaladsl/ZipWith5."<init>":(Lscala/Function5;)V
       8: areturn

  public static akka.stream.scaladsl.ZipWith6 apply(akka.stream.scaladsl.ZipWithApply, scala.Function6);
    Code:
       0: new           #41                 // class akka/stream/scaladsl/ZipWith6
       3: dup
       4: aload_1
       5: invokespecial #44                 // Method akka/stream/scaladsl/ZipWith6."<init>":(Lscala/Function6;)V
       8: areturn

  public static akka.stream.scaladsl.ZipWith7 apply(akka.stream.scaladsl.ZipWithApply, scala.Function7);
    Code:
       0: new           #48                 // class akka/stream/scaladsl/ZipWith7
       3: dup
       4: aload_1
       5: invokespecial #51                 // Method akka/stream/scaladsl/ZipWith7."<init>":(Lscala/Function7;)V
       8: areturn

  public static akka.stream.scaladsl.ZipWith8 apply(akka.stream.scaladsl.ZipWithApply, scala.Function8);
    Code:
       0: new           #55                 // class akka/stream/scaladsl/ZipWith8
       3: dup
       4: aload_1
       5: invokespecial #58                 // Method akka/stream/scaladsl/ZipWith8."<init>":(Lscala/Function8;)V
       8: areturn

  public static akka.stream.scaladsl.ZipWith9 apply(akka.stream.scaladsl.ZipWithApply, scala.Function9);
    Code:
       0: new           #62                 // class akka/stream/scaladsl/ZipWith9
       3: dup
       4: aload_1
       5: invokespecial #65                 // Method akka/stream/scaladsl/ZipWith9."<init>":(Lscala/Function9;)V
       8: areturn

  public static akka.stream.scaladsl.ZipWith10 apply(akka.stream.scaladsl.ZipWithApply, scala.Function10);
    Code:
       0: new           #69                 // class akka/stream/scaladsl/ZipWith10
       3: dup
       4: aload_1
       5: invokespecial #72                 // Method akka/stream/scaladsl/ZipWith10."<init>":(Lscala/Function10;)V
       8: areturn

  public static akka.stream.scaladsl.ZipWith11 apply(akka.stream.scaladsl.ZipWithApply, scala.Function11);
    Code:
       0: new           #76                 // class akka/stream/scaladsl/ZipWith11
       3: dup
       4: aload_1
       5: invokespecial #79                 // Method akka/stream/scaladsl/ZipWith11."<init>":(Lscala/Function11;)V
       8: areturn

  public static akka.stream.scaladsl.ZipWith12 apply(akka.stream.scaladsl.ZipWithApply, scala.Function12);
    Code:
       0: new           #83                 // class akka/stream/scaladsl/ZipWith12
       3: dup
       4: aload_1
       5: invokespecial #86                 // Method akka/stream/scaladsl/ZipWith12."<init>":(Lscala/Function12;)V
       8: areturn

  public static akka.stream.scaladsl.ZipWith13 apply(akka.stream.scaladsl.ZipWithApply, scala.Function13);
    Code:
       0: new           #90                 // class akka/stream/scaladsl/ZipWith13
       3: dup
       4: aload_1
       5: invokespecial #93                 // Method akka/stream/scaladsl/ZipWith13."<init>":(Lscala/Function13;)V
       8: areturn

  public static akka.stream.scaladsl.ZipWith14 apply(akka.stream.scaladsl.ZipWithApply, scala.Function14);
    Code:
       0: new           #97                 // class akka/stream/scaladsl/ZipWith14
       3: dup
       4: aload_1
       5: invokespecial #100                // Method akka/stream/scaladsl/ZipWith14."<init>":(Lscala/Function14;)V
       8: areturn

  public static akka.stream.scaladsl.ZipWith15 apply(akka.stream.scaladsl.ZipWithApply, scala.Function15);
    Code:
       0: new           #104                // class akka/stream/scaladsl/ZipWith15
       3: dup
       4: aload_1
       5: invokespecial #107                // Method akka/stream/scaladsl/ZipWith15."<init>":(Lscala/Function15;)V
       8: areturn

  public static akka.stream.scaladsl.ZipWith16 apply(akka.stream.scaladsl.ZipWithApply, scala.Function16);
    Code:
       0: new           #111                // class akka/stream/scaladsl/ZipWith16
       3: dup
       4: aload_1
       5: invokespecial #114                // Method akka/stream/scaladsl/ZipWith16."<init>":(Lscala/Function16;)V
       8: areturn

  public static akka.stream.scaladsl.ZipWith17 apply(akka.stream.scaladsl.ZipWithApply, scala.Function17);
    Code:
       0: new           #118                // class akka/stream/scaladsl/ZipWith17
       3: dup
       4: aload_1
       5: invokespecial #121                // Method akka/stream/scaladsl/ZipWith17."<init>":(Lscala/Function17;)V
       8: areturn

  public static akka.stream.scaladsl.ZipWith18 apply(akka.stream.scaladsl.ZipWithApply, scala.Function18);
    Code:
       0: new           #125                // class akka/stream/scaladsl/ZipWith18
       3: dup
       4: aload_1
       5: invokespecial #128                // Method akka/stream/scaladsl/ZipWith18."<init>":(Lscala/Function18;)V
       8: areturn

  public static akka.stream.scaladsl.ZipWith19 apply(akka.stream.scaladsl.ZipWithApply, scala.Function19);
    Code:
       0: new           #132                // class akka/stream/scaladsl/ZipWith19
       3: dup
       4: aload_1
       5: invokespecial #135                // Method akka/stream/scaladsl/ZipWith19."<init>":(Lscala/Function19;)V
       8: areturn

  public static akka.stream.scaladsl.ZipWith20 apply(akka.stream.scaladsl.ZipWithApply, scala.Function20);
    Code:
       0: new           #139                // class akka/stream/scaladsl/ZipWith20
       3: dup
       4: aload_1
       5: invokespecial #142                // Method akka/stream/scaladsl/ZipWith20."<init>":(Lscala/Function20;)V
       8: areturn

  public static void $init$(akka.stream.scaladsl.ZipWithApply);
    Code:
       0: return
}
