Compiled from "SolrHealthIndicator.java"
public class org.springframework.boot.actuate.health.SolrHealthIndicator extends org.springframework.boot.actuate.health.AbstractHealthIndicator {
  private final org.apache.solr.client.solrj.SolrClient solrClient;

  public org.springframework.boot.actuate.health.SolrHealthIndicator(org.apache.solr.client.solrj.SolrClient);
    Code:
       0: aload_0
       1: invokespecial #1                  // Method org/springframework/boot/actuate/health/AbstractHealthIndicator."<init>":()V
       4: aload_0
       5: aload_1
       6: putfield      #2                  // Field solrClient:Lorg/apache/solr/client/solrj/SolrClient;
       9: return

  protected void doHealthCheck(org.springframework.boot.actuate.health.Health$Builder) throws java.lang.Exception;
    Code:
       0: aload_0
       1: getfield      #2                  // Field solrClient:Lorg/apache/solr/client/solrj/SolrClient;
       4: invokevirtual #3                  // Method org/apache/solr/client/solrj/SolrClient.ping:()Lorg/apache/solr/client/solrj/response/SolrPingResponse;
       7: invokevirtual #4                  // Method org/apache/solr/client/solrj/response/SolrPingResponse.getResponse:()Lorg/apache/solr/common/util/NamedList;
      10: ldc           #5                  // String status
      12: invokevirtual #6                  // Method org/apache/solr/common/util/NamedList.get:(Ljava/lang/String;)Ljava/lang/Object;
      15: astore_2
      16: aload_1
      17: invokevirtual #7                  // Method org/springframework/boot/actuate/health/Health$Builder.up:()Lorg/springframework/boot/actuate/health/Health$Builder;
      20: ldc           #8                  // String solrStatus
      22: aload_2
      23: invokevirtual #9                  // Method org/springframework/boot/actuate/health/Health$Builder.withDetail:(Ljava/lang/String;Ljava/lang/Object;)Lorg/springframework/boot/actuate/health/Health$Builder;
      26: pop
      27: return
}
