Compiled from "IdentNode.java"
public class org.hibernate.hql.internal.ast.tree.IdentNode extends org.hibernate.hql.internal.ast.tree.FromReferenceNode implements org.hibernate.hql.internal.ast.tree.SelectExpression {
  private boolean nakedPropertyRef;

  private java.lang.String[] columns;

  public org.hibernate.hql.internal.ast.tree.IdentNode();
    Code:
       0: aload_0
       1: invokespecial #1                  // Method org/hibernate/hql/internal/ast/tree/FromReferenceNode."<init>":()V
       4: return

  public java.lang.String[] getColumns();
    Code:
       0: aload_0
       1: getfield      #2                  // Field columns:[Ljava/lang/String;
       4: areturn

  public void resolveIndex(antlr.collections.AST) throws antlr.SemanticException;
    Code:
       0: aload_0
       1: invokevirtual #3                  // Method isResolved:()Z
       4: ifeq          14
       7: aload_0
       8: getfield      #4                  // Field nakedPropertyRef:Z
      11: ifne          22
      14: new           #5                  // class java/lang/UnsupportedOperationException
      17: dup
      18: invokespecial #6                  // Method java/lang/UnsupportedOperationException."<init>":()V
      21: athrow
      22: aload_0
      23: invokevirtual #7                  // Method getOriginalText:()Ljava/lang/String;
      26: astore_2
      27: aload_0
      28: invokevirtual #8                  // Method getDataType:()Lorg/hibernate/type/Type;
      31: invokeinterface #9,  1            // InterfaceMethod org/hibernate/type/Type.isCollectionType:()Z
      36: ifne          71
      39: new           #10                 // class antlr/SemanticException
      42: dup
      43: new           #11                 // class java/lang/StringBuilder
      46: dup
      47: invokespecial #12                 // Method java/lang/StringBuilder."<init>":()V
      50: ldc           #13                 // String Collection expected; [
      52: invokevirtual #14                 // Method java/lang/StringBuilder.append:(Ljava/lang/String;)Ljava/lang/StringBuilder;
      55: aload_2
      56: invokevirtual #14                 // Method java/lang/StringBuilder.append:(Ljava/lang/String;)Ljava/lang/StringBuilder;
      59: ldc           #15                 // String ] does not refer to a collection property
      61: invokevirtual #14                 // Method java/lang/StringBuilder.append:(Ljava/lang/String;)Ljava/lang/StringBuilder;
      64: invokevirtual #16                 // Method java/lang/StringBuilder.toString:()Ljava/lang/String;
      67: invokespecial #17                 // Method antlr/SemanticException."<init>":(Ljava/lang/String;)V
      70: athrow
      71: aload_0
      72: invokevirtual #8                  // Method getDataType:()Lorg/hibernate/type/Type;
      75: checkcast     #18                 // class org/hibernate/type/CollectionType
      78: astore_3
      79: aload_3
      80: invokevirtual #19                 // Method org/hibernate/type/CollectionType.getRole:()Ljava/lang/String;
      83: astore        4
      85: aload_0
      86: invokevirtual #20                 // Method getSessionFactoryHelper:()Lorg/hibernate/hql/internal/ast/util/SessionFactoryHelper;
      89: aload         4
      91: invokevirtual #21                 // Method org/hibernate/hql/internal/ast/util/SessionFactoryHelper.requireQueryableCollection:(Ljava/lang/String;)Lorg/hibernate/persister/collection/QueryableCollection;
      94: astore        5
      96: aconst_null
      97: astore        6
      99: aload_0
     100: invokevirtual #22                 // Method getFromElement:()Lorg/hibernate/hql/internal/ast/tree/FromElement;
     103: invokevirtual #23                 // Method org/hibernate/hql/internal/ast/tree/FromElement.getTableAlias:()Ljava/lang/String;
     106: astore        7
     108: getstatic     #24                 // Field org/hibernate/sql/JoinType.INNER_JOIN:Lorg/hibernate/sql/JoinType;
     111: astore        8
     113: iconst_0
     114: istore        9
     116: new           #25                 // class org/hibernate/hql/internal/ast/tree/FromElementFactory
     119: dup
     120: aload_0
     121: invokevirtual #26                 // Method getWalker:()Lorg/hibernate/hql/internal/ast/HqlSqlWalker;
     124: invokevirtual #27                 // Method org/hibernate/hql/internal/ast/HqlSqlWalker.getCurrentFromClause:()Lorg/hibernate/hql/internal/ast/tree/FromClause;
     127: aload_0
     128: invokevirtual #22                 // Method getFromElement:()Lorg/hibernate/hql/internal/ast/tree/FromElement;
     131: aload_2
     132: aload         6
     134: aload_0
     135: invokevirtual #22                 // Method getFromElement:()Lorg/hibernate/hql/internal/ast/tree/FromElement;
     138: aload         7
     140: aload_2
     141: iconst_0
     142: invokevirtual #28                 // Method org/hibernate/hql/internal/ast/tree/FromElement.toColumns:(Ljava/lang/String;Ljava/lang/String;Z)[Ljava/lang/String;
     145: iconst_1
     146: invokespecial #29                 // Method org/hibernate/hql/internal/ast/tree/FromElementFactory."<init>":(Lorg/hibernate/hql/internal/ast/tree/FromClause;Lorg/hibernate/hql/internal/ast/tree/FromElement;Ljava/lang/String;Ljava/lang/String;[Ljava/lang/String;Z)V
     149: astore        10
     151: aload         10
     153: aload         5
     155: aload         4
     157: aload         8
     159: iload         9
     161: iconst_1
     162: invokevirtual #30                 // Method org/hibernate/hql/internal/ast/tree/FromElementFactory.createCollection:(Lorg/hibernate/persister/collection/QueryableCollection;Ljava/lang/String;Lorg/hibernate/sql/JoinType;ZZ)Lorg/hibernate/hql/internal/ast/tree/FromElement;
     165: astore        11
     167: aload_0
     168: aload         11
     170: invokevirtual #31                 // Method setFromElement:(Lorg/hibernate/hql/internal/ast/tree/FromElement;)V
     173: aload_0
     174: invokevirtual #26                 // Method getWalker:()Lorg/hibernate/hql/internal/ast/HqlSqlWalker;
     177: aload         5
     179: invokeinterface #32,  1           // InterfaceMethod org/hibernate/persister/collection/QueryableCollection.getCollectionSpaces:()[Ljava/io/Serializable;
     184: invokevirtual #33                 // Method org/hibernate/hql/internal/ast/HqlSqlWalker.addQuerySpaces:([Ljava/io/Serializable;)V
     187: return

  protected java.lang.String[] resolveColumns(org.hibernate.persister.collection.QueryableCollection);
    Code:
       0: aload_0
       1: invokevirtual #22                 // Method getFromElement:()Lorg/hibernate/hql/internal/ast/tree/FromElement;
       4: astore_2
       5: aload_2
       6: aload_2
       7: invokevirtual #34                 // Method org/hibernate/hql/internal/ast/tree/FromElement.getCollectionTableAlias:()Ljava/lang/String;
      10: ldc           #35                 // String elements
      12: aload_0
      13: invokevirtual #26                 // Method getWalker:()Lorg/hibernate/hql/internal/ast/HqlSqlWalker;
      16: invokevirtual #36                 // Method org/hibernate/hql/internal/ast/HqlSqlWalker.isInSelect:()Z
      19: invokevirtual #28                 // Method org/hibernate/hql/internal/ast/tree/FromElement.toColumns:(Ljava/lang/String;Ljava/lang/String;Z)[Ljava/lang/String;
      22: areturn

  private void initText(java.lang.String[]);
    Code:
       0: ldc           #37                 // String ,
       2: aload_1
       3: invokestatic  #38                 // Method org/hibernate/internal/util/StringHelper.join:(Ljava/lang/String;[Ljava/lang/String;)Ljava/lang/String;
       6: astore_2
       7: aload_1
       8: arraylength
       9: iconst_1
      10: if_icmple     48
      13: aload_0
      14: invokevirtual #26                 // Method getWalker:()Lorg/hibernate/hql/internal/ast/HqlSqlWalker;
      17: invokevirtual #39                 // Method org/hibernate/hql/internal/ast/HqlSqlWalker.isComparativeExpressionClause:()Z
      20: ifeq          48
      23: new           #11                 // class java/lang/StringBuilder
      26: dup
      27: invokespecial #12                 // Method java/lang/StringBuilder."<init>":()V
      30: ldc           #40                 // String (
      32: invokevirtual #14                 // Method java/lang/StringBuilder.append:(Ljava/lang/String;)Ljava/lang/StringBuilder;
      35: aload_2
      36: invokevirtual #14                 // Method java/lang/StringBuilder.append:(Ljava/lang/String;)Ljava/lang/StringBuilder;
      39: ldc           #41                 // String )
      41: invokevirtual #14                 // Method java/lang/StringBuilder.append:(Ljava/lang/String;)Ljava/lang/StringBuilder;
      44: invokevirtual #16                 // Method java/lang/StringBuilder.toString:()Ljava/lang/String;
      47: astore_2
      48: aload_0
      49: aload_2
      50: invokevirtual #42                 // Method setText:(Ljava/lang/String;)V
      53: return

  public void resolve(boolean, boolean, java.lang.String, antlr.collections.AST, antlr.collections.AST);
    Code:
       0: aload_0
       1: invokevirtual #3                  // Method isResolved:()Z
       4: ifne          340
       7: aload_0
       8: invokevirtual #26                 // Method getWalker:()Lorg/hibernate/hql/internal/ast/HqlSqlWalker;
      11: invokevirtual #27                 // Method org/hibernate/hql/internal/ast/HqlSqlWalker.getCurrentFromClause:()Lorg/hibernate/hql/internal/ast/tree/FromClause;
      14: aload_0
      15: invokevirtual #43                 // Method getText:()Ljava/lang/String;
      18: invokevirtual #44                 // Method org/hibernate/hql/internal/ast/tree/FromClause.isFromElementAlias:(Ljava/lang/String;)Z
      21: ifeq          147
      24: aload_0
      25: invokevirtual #26                 // Method getWalker:()Lorg/hibernate/hql/internal/ast/HqlSqlWalker;
      28: invokevirtual #27                 // Method org/hibernate/hql/internal/ast/HqlSqlWalker.getCurrentFromClause:()Lorg/hibernate/hql/internal/ast/tree/FromClause;
      31: aload_0
      32: invokevirtual #43                 // Method getText:()Ljava/lang/String;
      35: invokevirtual #45                 // Method org/hibernate/hql/internal/ast/tree/FromClause.getFromElement:(Ljava/lang/String;)Lorg/hibernate/hql/internal/ast/tree/FromElement;
      38: astore        6
      40: aload         6
      42: invokevirtual #46                 // Method org/hibernate/hql/internal/ast/tree/FromElement.getQueryableCollection:()Lorg/hibernate/persister/collection/QueryableCollection;
      45: ifnull        133
      48: aload         6
      50: invokevirtual #46                 // Method org/hibernate/hql/internal/ast/tree/FromElement.getQueryableCollection:()Lorg/hibernate/persister/collection/QueryableCollection;
      53: invokeinterface #47,  1           // InterfaceMethod org/hibernate/persister/collection/QueryableCollection.getElementType:()Lorg/hibernate/type/Type;
      58: invokeinterface #48,  1           // InterfaceMethod org/hibernate/type/Type.isComponentType:()Z
      63: ifeq          133
      66: aload_0
      67: invokevirtual #26                 // Method getWalker:()Lorg/hibernate/hql/internal/ast/HqlSqlWalker;
      70: invokevirtual #36                 // Method org/hibernate/hql/internal/ast/HqlSqlWalker.isInSelect:()Z
      73: ifeq          125
      76: aload_0
      77: aload         6
      79: invokevirtual #31                 // Method setFromElement:(Lorg/hibernate/hql/internal/ast/tree/FromElement;)V
      82: aload_0
      83: aload         6
      85: invokevirtual #46                 // Method org/hibernate/hql/internal/ast/tree/FromElement.getQueryableCollection:()Lorg/hibernate/persister/collection/QueryableCollection;
      88: invokeinterface #47,  1           // InterfaceMethod org/hibernate/persister/collection/QueryableCollection.getElementType:()Lorg/hibernate/type/Type;
      93: invokespecial #49                 // Method org/hibernate/hql/internal/ast/tree/FromReferenceNode.setDataType:(Lorg/hibernate/type/Type;)V
      96: aload_0
      97: aload_0
      98: aload         6
     100: invokevirtual #46                 // Method org/hibernate/hql/internal/ast/tree/FromElement.getQueryableCollection:()Lorg/hibernate/persister/collection/QueryableCollection;
     103: invokevirtual #50                 // Method resolveColumns:(Lorg/hibernate/persister/collection/QueryableCollection;)[Ljava/lang/String;
     106: putfield      #2                  // Field columns:[Ljava/lang/String;
     109: aload_0
     110: aload_0
     111: invokevirtual #51                 // Method getColumns:()[Ljava/lang/String;
     114: invokespecial #52                 // Method initText:([Ljava/lang/String;)V
     117: aload_0
     118: aconst_null
     119: invokevirtual #53                 // Method setFirstChild:(Lantlr/collections/AST;)V
     122: goto          144
     125: aload_0
     126: invokespecial #54                 // Method resolveAsAlias:()Z
     129: pop
     130: goto          144
     133: aload_0
     134: invokespecial #54                 // Method resolveAsAlias:()Z
     137: ifeq          144
     140: aload_0
     141: invokevirtual #55                 // Method setResolved:()V
     144: goto          316
     147: aload_0
     148: invokevirtual #51                 // Method getColumns:()[Ljava/lang/String;
     151: ifnull        219
     154: aload_0
     155: invokevirtual #26                 // Method getWalker:()Lorg/hibernate/hql/internal/ast/HqlSqlWalker;
     158: invokevirtual #56                 // Method org/hibernate/hql/internal/ast/HqlSqlWalker.getAST:()Lantlr/collections/AST;
     161: instanceof    #57                 // class org/hibernate/hql/internal/ast/tree/AbstractMapComponentNode
     164: ifne          180
     167: aload_0
     168: invokevirtual #26                 // Method getWalker:()Lorg/hibernate/hql/internal/ast/HqlSqlWalker;
     171: invokevirtual #56                 // Method org/hibernate/hql/internal/ast/HqlSqlWalker.getAST:()Lantlr/collections/AST;
     174: instanceof    #58                 // class org/hibernate/hql/internal/ast/tree/IndexNode
     177: ifeq          219
     180: aload_0
     181: invokevirtual #26                 // Method getWalker:()Lorg/hibernate/hql/internal/ast/HqlSqlWalker;
     184: invokevirtual #27                 // Method org/hibernate/hql/internal/ast/HqlSqlWalker.getCurrentFromClause:()Lorg/hibernate/hql/internal/ast/tree/FromClause;
     187: aload_0
     188: invokevirtual #7                  // Method getOriginalText:()Ljava/lang/String;
     191: invokevirtual #44                 // Method org/hibernate/hql/internal/ast/tree/FromClause.isFromElementAlias:(Ljava/lang/String;)Z
     194: ifeq          219
     197: aload_0
     198: aload_0
     199: invokevirtual #7                  // Method getOriginalText:()Ljava/lang/String;
     202: invokevirtual #42                 // Method setText:(Ljava/lang/String;)V
     205: aload_0
     206: invokespecial #54                 // Method resolveAsAlias:()Z
     209: ifeq          316
     212: aload_0
     213: invokevirtual #55                 // Method setResolved:()V
     216: goto          316
     219: aload         4
     221: ifnull        286
     224: aload         4
     226: invokeinterface #59,  1           // InterfaceMethod antlr/collections/AST.getType:()I
     231: bipush        15
     233: if_icmpne     286
     236: aload         4
     238: checkcast     #61                 // class org/hibernate/hql/internal/ast/tree/DotNode
     241: astore        6
     243: aload         4
     245: invokeinterface #62,  1           // InterfaceMethod antlr/collections/AST.getFirstChild:()Lantlr/collections/AST;
     250: aload_0
     251: if_acmpne     270
     254: aload_0
     255: aload         6
     257: invokespecial #63                 // Method resolveAsNakedComponentPropertyRefLHS:(Lorg/hibernate/hql/internal/ast/tree/DotNode;)Z
     260: ifeq          283
     263: aload_0
     264: invokevirtual #55                 // Method setResolved:()V
     267: goto          283
     270: aload_0
     271: aload         6
     273: invokespecial #64                 // Method resolveAsNakedComponentPropertyRefRHS:(Lorg/hibernate/hql/internal/ast/tree/DotNode;)Z
     276: ifeq          283
     279: aload_0
     280: invokevirtual #55                 // Method setResolved:()V
     283: goto          316
     286: aload_0
     287: invokespecial #65                 // Method resolveAsNakedPropertyRef:()Lorg/hibernate/hql/internal/ast/tree/IdentNode$DereferenceType;
     290: astore        6
     292: aload         6
     294: getstatic     #66                 // Field org/hibernate/hql/internal/ast/tree/IdentNode$DereferenceType.PROPERTY_REF:Lorg/hibernate/hql/internal/ast/tree/IdentNode$DereferenceType;
     297: if_acmpne     307
     300: aload_0
     301: invokevirtual #55                 // Method setResolved:()V
     304: goto          316
     307: aload         6
     309: getstatic     #67                 // Field org/hibernate/hql/internal/ast/tree/IdentNode$DereferenceType.COMPONENT_REF:Lorg/hibernate/hql/internal/ast/tree/IdentNode$DereferenceType;
     312: if_acmpne     316
     315: return
     316: aload_0
     317: invokevirtual #3                  // Method isResolved:()Z
     320: ifne          340
     323: aload_0
     324: invokevirtual #26                 // Method getWalker:()Lorg/hibernate/hql/internal/ast/HqlSqlWalker;
     327: invokevirtual #68                 // Method org/hibernate/hql/internal/ast/HqlSqlWalker.getLiteralProcessor:()Lorg/hibernate/hql/internal/ast/util/LiteralProcessor;
     330: aload_0
     331: iconst_0
     332: invokevirtual #69                 // Method org/hibernate/hql/internal/ast/util/LiteralProcessor.processConstant:(Lantlr/collections/AST;Z)V
     335: goto          340
     338: astore        6
     340: return
    Exception table:
       from    to  target type
         323   335   338   Class java/lang/Throwable

  private boolean resolveAsAlias();
    Code:
       0: aload_0
       1: invokevirtual #43                 // Method getText:()Ljava/lang/String;
       4: astore_1
       5: aload_0
       6: invokevirtual #26                 // Method getWalker:()Lorg/hibernate/hql/internal/ast/HqlSqlWalker;
       9: invokevirtual #27                 // Method org/hibernate/hql/internal/ast/HqlSqlWalker.getCurrentFromClause:()Lorg/hibernate/hql/internal/ast/tree/FromClause;
      12: aload_1
      13: invokevirtual #45                 // Method org/hibernate/hql/internal/ast/tree/FromClause.getFromElement:(Ljava/lang/String;)Lorg/hibernate/hql/internal/ast/tree/FromElement;
      16: astore_2
      17: aload_2
      18: ifnonnull     23
      21: iconst_0
      22: ireturn
      23: aload_2
      24: aload_0
      25: invokevirtual #26                 // Method getWalker:()Lorg/hibernate/hql/internal/ast/HqlSqlWalker;
      28: aload_1
      29: invokevirtual #71                 // Method org/hibernate/hql/internal/ast/HqlSqlWalker.getTreatAsDeclarationsByPath:(Ljava/lang/String;)Ljava/util/Set;
      32: invokevirtual #72                 // Method org/hibernate/hql/internal/ast/tree/FromElement.applyTreatAsDeclarations:(Ljava/util/Set;)V
      35: aload_0
      36: sipush        144
      39: invokevirtual #73                 // Method setType:(I)V
      42: aload_0
      43: aload_2
      44: invokevirtual #31                 // Method setFromElement:(Lorg/hibernate/hql/internal/ast/tree/FromElement;)V
      47: aload_2
      48: invokevirtual #74                 // Method org/hibernate/hql/internal/ast/tree/FromElement.getIdentityColumns:()[Ljava/lang/String;
      51: astore_3
      52: aload_0
      53: aload_2
      54: invokevirtual #75                 // Method isFromElementUpdateOrDeleteRoot:(Lorg/hibernate/hql/internal/ast/tree/FromElement;)Z
      57: ifne          79
      60: aload_2
      61: invokevirtual #23                 // Method org/hibernate/hql/internal/ast/tree/FromElement.getTableAlias:()Ljava/lang/String;
      64: invokestatic  #76                 // Method org/hibernate/internal/util/StringHelper.isNotEmpty:(Ljava/lang/String;)Z
      67: ifeq          79
      70: aload_2
      71: invokevirtual #23                 // Method org/hibernate/hql/internal/ast/tree/FromElement.getTableAlias:()Ljava/lang/String;
      74: aload_3
      75: invokestatic  #77                 // Method org/hibernate/internal/util/StringHelper.qualifyIfNot:(Ljava/lang/String;[Ljava/lang/String;)[Ljava/lang/String;
      78: astore_3
      79: aload_0
      80: invokevirtual #26                 // Method getWalker:()Lorg/hibernate/hql/internal/ast/HqlSqlWalker;
      83: invokevirtual #78                 // Method org/hibernate/hql/internal/ast/HqlSqlWalker.getSessionFactoryHelper:()Lorg/hibernate/hql/internal/ast/util/SessionFactoryHelper;
      86: invokevirtual #79                 // Method org/hibernate/hql/internal/ast/util/SessionFactoryHelper.getFactory:()Lorg/hibernate/engine/spi/SessionFactoryImplementor;
      89: invokeinterface #80,  1           // InterfaceMethod org/hibernate/engine/spi/SessionFactoryImplementor.getDialect:()Lorg/hibernate/dialect/Dialect;
      94: astore        4
      96: aload_0
      97: invokevirtual #26                 // Method getWalker:()Lorg/hibernate/hql/internal/ast/HqlSqlWalker;
     100: invokevirtual #81                 // Method org/hibernate/hql/internal/ast/HqlSqlWalker.isInCount:()Z
     103: istore        5
     105: iload         5
     107: ifeq          124
     110: aload_0
     111: invokevirtual #26                 // Method getWalker:()Lorg/hibernate/hql/internal/ast/HqlSqlWalker;
     114: invokevirtual #82                 // Method org/hibernate/hql/internal/ast/HqlSqlWalker.isInCountDistinct:()Z
     117: ifeq          124
     120: iconst_1
     121: goto          125
     124: iconst_0
     125: istore        6
     127: iload         5
     129: ifeq          146
     132: aload_0
     133: invokevirtual #26                 // Method getWalker:()Lorg/hibernate/hql/internal/ast/HqlSqlWalker;
     136: invokevirtual #82                 // Method org/hibernate/hql/internal/ast/HqlSqlWalker.isInCountDistinct:()Z
     139: ifne          146
     142: iconst_1
     143: goto          147
     146: iconst_0
     147: istore        7
     149: aload_3
     150: arraylength
     151: iconst_1
     152: if_icmple     159
     155: iconst_1
     156: goto          160
     159: iconst_0
     160: istore        8
     162: iload         8
     164: ifeq          287
     167: iload         7
     169: ifeq          190
     172: aload         4
     174: invokevirtual #83                 // Method org/hibernate/dialect/Dialect.supportsTupleCounts:()Z
     177: ifne          190
     180: aload_0
     181: aload_3
     182: iconst_0
     183: aaload
     184: invokevirtual #42                 // Method setText:(Ljava/lang/String;)V
     187: goto          285
     190: ldc           #37                 // String ,
     192: aload_3
     193: invokestatic  #38                 // Method org/hibernate/internal/util/StringHelper.join:(Ljava/lang/String;[Ljava/lang/String;)Ljava/lang/String;
     196: astore        9
     198: iload         6
     200: ifeq          211
     203: aload         4
     205: invokevirtual #84                 // Method org/hibernate/dialect/Dialect.requiresParensForTupleDistinctCounts:()Z
     208: ifeq          240
     211: iload         7
     213: ifne          240
     216: aload_0
     217: invokevirtual #26                 // Method getWalker:()Lorg/hibernate/hql/internal/ast/HqlSqlWalker;
     220: invokevirtual #85                 // Method org/hibernate/hql/internal/ast/HqlSqlWalker.getCurrentTopLevelClauseType:()I
     223: bipush        41
     225: if_icmpeq     240
     228: aload_0
     229: invokevirtual #26                 // Method getWalker:()Lorg/hibernate/hql/internal/ast/HqlSqlWalker;
     232: invokevirtual #85                 // Method org/hibernate/hql/internal/ast/HqlSqlWalker.getCurrentTopLevelClauseType:()I
     235: bipush        24
     237: if_icmpne     244
     240: iconst_1
     241: goto          245
     244: iconst_0
     245: istore        10
     247: iload         10
     249: ifne          279
     252: new           #11                 // class java/lang/StringBuilder
     255: dup
     256: invokespecial #12                 // Method java/lang/StringBuilder."<init>":()V
     259: ldc           #40                 // String (
     261: invokevirtual #14                 // Method java/lang/StringBuilder.append:(Ljava/lang/String;)Ljava/lang/StringBuilder;
     264: aload         9
     266: invokevirtual #14                 // Method java/lang/StringBuilder.append:(Ljava/lang/String;)Ljava/lang/StringBuilder;
     269: ldc           #41                 // String )
     271: invokevirtual #14                 // Method java/lang/StringBuilder.append:(Ljava/lang/String;)Ljava/lang/StringBuilder;
     274: invokevirtual #16                 // Method java/lang/StringBuilder.toString:()Ljava/lang/String;
     277: astore        9
     279: aload_0
     280: aload         9
     282: invokevirtual #42                 // Method setText:(Ljava/lang/String;)V
     285: iconst_1
     286: ireturn
     287: aload_3
     288: arraylength
     289: ifle          301
     292: aload_0
     293: aload_3
     294: iconst_0
     295: aaload
     296: invokevirtual #42                 // Method setText:(Ljava/lang/String;)V
     299: iconst_1
     300: ireturn
     301: iconst_0
     302: ireturn

  private org.hibernate.type.Type getNakedPropertyType(org.hibernate.hql.internal.ast.tree.FromElement);
    Code:
       0: aload_1
       1: ifnonnull     6
       4: aconst_null
       5: areturn
       6: aload_0
       7: invokevirtual #7                  // Method getOriginalText:()Ljava/lang/String;
      10: astore_2
      11: aconst_null
      12: astore_3
      13: aload_1
      14: aload_2
      15: aload_2
      16: invokevirtual #87                 // Method org/hibernate/hql/internal/ast/tree/FromElement.getPropertyType:(Ljava/lang/String;Ljava/lang/String;)Lorg/hibernate/type/Type;
      19: astore_3
      20: goto          25
      23: astore        4
      25: aload_3
      26: areturn
    Exception table:
       from    to  target type
          13    20    23   Class java/lang/Throwable

  private org.hibernate.hql.internal.ast.tree.IdentNode$DereferenceType resolveAsNakedPropertyRef();
    Code:
       0: aload_0
       1: invokespecial #88                 // Method locateSingleFromElement:()Lorg/hibernate/hql/internal/ast/tree/FromElement;
       4: astore_1
       5: aload_1
       6: ifnonnull     13
       9: getstatic     #89                 // Field org/hibernate/hql/internal/ast/tree/IdentNode$DereferenceType.UNKNOWN:Lorg/hibernate/hql/internal/ast/tree/IdentNode$DereferenceType;
      12: areturn
      13: aload_1
      14: invokevirtual #90                 // Method org/hibernate/hql/internal/ast/tree/FromElement.getQueryable:()Lorg/hibernate/persister/entity/Queryable;
      17: astore_2
      18: aload_2
      19: ifnonnull     26
      22: getstatic     #89                 // Field org/hibernate/hql/internal/ast/tree/IdentNode$DereferenceType.UNKNOWN:Lorg/hibernate/hql/internal/ast/tree/IdentNode$DereferenceType;
      25: areturn
      26: aload_0
      27: aload_1
      28: invokespecial #91                 // Method getNakedPropertyType:(Lorg/hibernate/hql/internal/ast/tree/FromElement;)Lorg/hibernate/type/Type;
      31: astore_3
      32: aload_3
      33: ifnonnull     40
      36: getstatic     #89                 // Field org/hibernate/hql/internal/ast/tree/IdentNode$DereferenceType.UNKNOWN:Lorg/hibernate/hql/internal/ast/tree/IdentNode$DereferenceType;
      39: areturn
      40: aload_3
      41: invokeinterface #48,  1           // InterfaceMethod org/hibernate/type/Type.isComponentType:()Z
      46: ifne          58
      49: aload_3
      50: invokeinterface #92,  1           // InterfaceMethod org/hibernate/type/Type.isAssociationType:()Z
      55: ifeq          62
      58: getstatic     #67                 // Field org/hibernate/hql/internal/ast/tree/IdentNode$DereferenceType.COMPONENT_REF:Lorg/hibernate/hql/internal/ast/tree/IdentNode$DereferenceType;
      61: areturn
      62: aload_0
      63: aload_1
      64: invokevirtual #31                 // Method setFromElement:(Lorg/hibernate/hql/internal/ast/tree/FromElement;)V
      67: aload_0
      68: invokevirtual #43                 // Method getText:()Ljava/lang/String;
      71: astore        4
      73: aload_0
      74: invokevirtual #26                 // Method getWalker:()Lorg/hibernate/hql/internal/ast/HqlSqlWalker;
      77: invokevirtual #93                 // Method org/hibernate/hql/internal/ast/HqlSqlWalker.isSelectStatement:()Z
      80: ifeq          98
      83: aload_2
      84: aload_1
      85: invokevirtual #23                 // Method org/hibernate/hql/internal/ast/tree/FromElement.getTableAlias:()Ljava/lang/String;
      88: aload         4
      90: invokeinterface #94,  3           // InterfaceMethod org/hibernate/persister/entity/Queryable.toColumns:(Ljava/lang/String;Ljava/lang/String;)[Ljava/lang/String;
      95: goto          106
      98: aload_2
      99: aload         4
     101: invokeinterface #95,  2           // InterfaceMethod org/hibernate/persister/entity/Queryable.toColumns:(Ljava/lang/String;)[Ljava/lang/String;
     106: astore        5
     108: ldc           #37                 // String ,
     110: aload         5
     112: invokestatic  #38                 // Method org/hibernate/internal/util/StringHelper.join:(Ljava/lang/String;[Ljava/lang/String;)Ljava/lang/String;
     115: astore        6
     117: aload_0
     118: aload         5
     120: arraylength
     121: iconst_1
     122: if_icmpne     130
     125: aload         6
     127: goto          155
     130: new           #11                 // class java/lang/StringBuilder
     133: dup
     134: invokespecial #12                 // Method java/lang/StringBuilder."<init>":()V
     137: ldc           #40                 // String (
     139: invokevirtual #14                 // Method java/lang/StringBuilder.append:(Ljava/lang/String;)Ljava/lang/StringBuilder;
     142: aload         6
     144: invokevirtual #14                 // Method java/lang/StringBuilder.append:(Ljava/lang/String;)Ljava/lang/StringBuilder;
     147: ldc           #41                 // String )
     149: invokevirtual #14                 // Method java/lang/StringBuilder.append:(Ljava/lang/String;)Ljava/lang/StringBuilder;
     152: invokevirtual #16                 // Method java/lang/StringBuilder.toString:()Ljava/lang/String;
     155: invokevirtual #42                 // Method setText:(Ljava/lang/String;)V
     158: aload_0
     159: sipush        146
     162: invokevirtual #73                 // Method setType:(I)V
     165: aload_0
     166: aload_3
     167: invokespecial #49                 // Method org/hibernate/hql/internal/ast/tree/FromReferenceNode.setDataType:(Lorg/hibernate/type/Type;)V
     170: aload_0
     171: iconst_1
     172: putfield      #4                  // Field nakedPropertyRef:Z
     175: getstatic     #66                 // Field org/hibernate/hql/internal/ast/tree/IdentNode$DereferenceType.PROPERTY_REF:Lorg/hibernate/hql/internal/ast/tree/IdentNode$DereferenceType;
     178: areturn

  private boolean resolveAsNakedComponentPropertyRefLHS(org.hibernate.hql.internal.ast.tree.DotNode);
    Code:
       0: aload_0
       1: invokespecial #88                 // Method locateSingleFromElement:()Lorg/hibernate/hql/internal/ast/tree/FromElement;
       4: astore_2
       5: aload_2
       6: ifnonnull     11
       9: iconst_0
      10: ireturn
      11: aload_0
      12: aload_2
      13: invokespecial #91                 // Method getNakedPropertyType:(Lorg/hibernate/hql/internal/ast/tree/FromElement;)Lorg/hibernate/type/Type;
      16: astore_3
      17: aload_3
      18: ifnonnull     68
      21: new           #96                 // class org/hibernate/QueryException
      24: dup
      25: new           #11                 // class java/lang/StringBuilder
      28: dup
      29: invokespecial #12                 // Method java/lang/StringBuilder."<init>":()V
      32: ldc           #97                 // String Unable to resolve path [
      34: invokevirtual #14                 // Method java/lang/StringBuilder.append:(Ljava/lang/String;)Ljava/lang/StringBuilder;
      37: aload_1
      38: invokevirtual #98                 // Method org/hibernate/hql/internal/ast/tree/DotNode.getPath:()Ljava/lang/String;
      41: invokevirtual #14                 // Method java/lang/StringBuilder.append:(Ljava/lang/String;)Ljava/lang/StringBuilder;
      44: ldc           #99                 // String ], unexpected token [
      46: invokevirtual #14                 // Method java/lang/StringBuilder.append:(Ljava/lang/String;)Ljava/lang/StringBuilder;
      49: aload_0
      50: invokevirtual #7                  // Method getOriginalText:()Ljava/lang/String;
      53: invokevirtual #14                 // Method java/lang/StringBuilder.append:(Ljava/lang/String;)Ljava/lang/StringBuilder;
      56: ldc           #100                // String ]
      58: invokevirtual #14                 // Method java/lang/StringBuilder.append:(Ljava/lang/String;)Ljava/lang/StringBuilder;
      61: invokevirtual #16                 // Method java/lang/StringBuilder.toString:()Ljava/lang/String;
      64: invokespecial #101                // Method org/hibernate/QueryException."<init>":(Ljava/lang/String;)V
      67: athrow
      68: aload_3
      69: invokeinterface #48,  1           // InterfaceMethod org/hibernate/type/Type.isComponentType:()Z
      74: ifne          112
      77: new           #96                 // class org/hibernate/QueryException
      80: dup
      81: new           #11                 // class java/lang/StringBuilder
      84: dup
      85: invokespecial #12                 // Method java/lang/StringBuilder."<init>":()V
      88: ldc           #102                // String Property \'
      90: invokevirtual #14                 // Method java/lang/StringBuilder.append:(Ljava/lang/String;)Ljava/lang/StringBuilder;
      93: aload_0
      94: invokevirtual #7                  // Method getOriginalText:()Ljava/lang/String;
      97: invokevirtual #14                 // Method java/lang/StringBuilder.append:(Ljava/lang/String;)Ljava/lang/StringBuilder;
     100: ldc           #103                // String \' is not a component.  Use an alias to reference associations or collections.
     102: invokevirtual #14                 // Method java/lang/StringBuilder.append:(Ljava/lang/String;)Ljava/lang/StringBuilder;
     105: invokevirtual #16                 // Method java/lang/StringBuilder.toString:()Ljava/lang/String;
     108: invokespecial #101                // Method org/hibernate/QueryException."<init>":(Ljava/lang/String;)V
     111: athrow
     112: new           #11                 // class java/lang/StringBuilder
     115: dup
     116: invokespecial #12                 // Method java/lang/StringBuilder."<init>":()V
     119: aload_0
     120: invokevirtual #43                 // Method getText:()Ljava/lang/String;
     123: invokevirtual #14                 // Method java/lang/StringBuilder.append:(Ljava/lang/String;)Ljava/lang/StringBuilder;
     126: ldc           #104                // String .
     128: invokevirtual #14                 // Method java/lang/StringBuilder.append:(Ljava/lang/String;)Ljava/lang/StringBuilder;
     131: aload_0
     132: invokevirtual #105                // Method getNextSibling:()Lantlr/collections/AST;
     135: invokeinterface #106,  1          // InterfaceMethod antlr/collections/AST.getText:()Ljava/lang/String;
     140: invokevirtual #14                 // Method java/lang/StringBuilder.append:(Ljava/lang/String;)Ljava/lang/StringBuilder;
     143: invokevirtual #16                 // Method java/lang/StringBuilder.toString:()Ljava/lang/String;
     146: astore        5
     148: aload_2
     149: aload_0
     150: invokevirtual #43                 // Method getText:()Ljava/lang/String;
     153: aload         5
     155: invokevirtual #87                 // Method org/hibernate/hql/internal/ast/tree/FromElement.getPropertyType:(Ljava/lang/String;Ljava/lang/String;)Lorg/hibernate/type/Type;
     158: astore        4
     160: goto          167
     163: astore        6
     165: iconst_0
     166: ireturn
     167: aload_0
     168: aload_2
     169: invokevirtual #31                 // Method setFromElement:(Lorg/hibernate/hql/internal/ast/tree/FromElement;)V
     172: aload_1
     173: aload         5
     175: invokevirtual #107                // Method org/hibernate/hql/internal/ast/tree/DotNode.setPropertyPath:(Ljava/lang/String;)V
     178: aload_1
     179: aload         4
     181: invokevirtual #108                // Method org/hibernate/hql/internal/ast/tree/DotNode.setDataType:(Lorg/hibernate/type/Type;)V
     184: iconst_1
     185: ireturn
    Exception table:
       from    to  target type
         148   160   163   Class java/lang/Throwable

  private boolean resolveAsNakedComponentPropertyRefRHS(org.hibernate.hql.internal.ast.tree.DotNode);
    Code:
       0: aload_0
       1: invokespecial #88                 // Method locateSingleFromElement:()Lorg/hibernate/hql/internal/ast/tree/FromElement;
       4: astore_2
       5: aload_2
       6: ifnonnull     11
       9: iconst_0
      10: ireturn
      11: new           #11                 // class java/lang/StringBuilder
      14: dup
      15: invokespecial #12                 // Method java/lang/StringBuilder."<init>":()V
      18: aload_1
      19: invokevirtual #109                // Method org/hibernate/hql/internal/ast/tree/DotNode.getLhs:()Lorg/hibernate/hql/internal/ast/tree/FromReferenceNode;
      22: invokevirtual #110                // Method org/hibernate/hql/internal/ast/tree/FromReferenceNode.getText:()Ljava/lang/String;
      25: invokevirtual #14                 // Method java/lang/StringBuilder.append:(Ljava/lang/String;)Ljava/lang/StringBuilder;
      28: ldc           #104                // String .
      30: invokevirtual #14                 // Method java/lang/StringBuilder.append:(Ljava/lang/String;)Ljava/lang/StringBuilder;
      33: aload_0
      34: invokevirtual #43                 // Method getText:()Ljava/lang/String;
      37: invokevirtual #14                 // Method java/lang/StringBuilder.append:(Ljava/lang/String;)Ljava/lang/StringBuilder;
      40: invokevirtual #16                 // Method java/lang/StringBuilder.toString:()Ljava/lang/String;
      43: astore        4
      45: aload_2
      46: aload_0
      47: invokevirtual #43                 // Method getText:()Ljava/lang/String;
      50: aload         4
      52: invokevirtual #87                 // Method org/hibernate/hql/internal/ast/tree/FromElement.getPropertyType:(Ljava/lang/String;Ljava/lang/String;)Lorg/hibernate/type/Type;
      55: astore_3
      56: goto          63
      59: astore        5
      61: iconst_0
      62: ireturn
      63: aload_0
      64: aload_2
      65: invokevirtual #31                 // Method setFromElement:(Lorg/hibernate/hql/internal/ast/tree/FromElement;)V
      68: aload_0
      69: aload_3
      70: invokespecial #49                 // Method org/hibernate/hql/internal/ast/tree/FromReferenceNode.setDataType:(Lorg/hibernate/type/Type;)V
      73: aload_0
      74: iconst_1
      75: putfield      #4                  // Field nakedPropertyRef:Z
      78: iconst_1
      79: ireturn
    Exception table:
       from    to  target type
          45    56    59   Class java/lang/Throwable

  private org.hibernate.hql.internal.ast.tree.FromElement locateSingleFromElement();
    Code:
       0: aload_0
       1: invokevirtual #26                 // Method getWalker:()Lorg/hibernate/hql/internal/ast/HqlSqlWalker;
       4: invokevirtual #27                 // Method org/hibernate/hql/internal/ast/HqlSqlWalker.getCurrentFromClause:()Lorg/hibernate/hql/internal/ast/tree/FromClause;
       7: invokevirtual #111                // Method org/hibernate/hql/internal/ast/tree/FromClause.getFromElements:()Ljava/util/List;
      10: astore_1
      11: aload_1
      12: ifnull        25
      15: aload_1
      16: invokeinterface #112,  1          // InterfaceMethod java/util/List.size:()I
      21: iconst_1
      22: if_icmpeq     27
      25: aconst_null
      26: areturn
      27: aload_1
      28: iconst_0
      29: invokeinterface #113,  2          // InterfaceMethod java/util/List.get:(I)Ljava/lang/Object;
      34: checkcast     #114                // class org/hibernate/hql/internal/ast/tree/FromElement
      37: astore_2
      38: aload_2
      39: invokevirtual #115                // Method org/hibernate/hql/internal/ast/tree/FromElement.getClassAlias:()Ljava/lang/String;
      42: ifnull        47
      45: aconst_null
      46: areturn
      47: aload_2
      48: areturn

  public org.hibernate.type.Type getDataType();
    Code:
       0: aload_0
       1: invokespecial #116                // Method org/hibernate/hql/internal/ast/tree/FromReferenceNode.getDataType:()Lorg/hibernate/type/Type;
       4: astore_1
       5: aload_1
       6: ifnull        11
       9: aload_1
      10: areturn
      11: aload_0
      12: invokevirtual #22                 // Method getFromElement:()Lorg/hibernate/hql/internal/ast/tree/FromElement;
      15: astore_2
      16: aload_2
      17: ifnull        25
      20: aload_2
      21: invokevirtual #117                // Method org/hibernate/hql/internal/ast/tree/FromElement.getDataType:()Lorg/hibernate/type/Type;
      24: areturn
      25: aload_0
      26: invokevirtual #26                 // Method getWalker:()Lorg/hibernate/hql/internal/ast/HqlSqlWalker;
      29: invokevirtual #78                 // Method org/hibernate/hql/internal/ast/HqlSqlWalker.getSessionFactoryHelper:()Lorg/hibernate/hql/internal/ast/util/SessionFactoryHelper;
      32: aload_0
      33: invokevirtual #43                 // Method getText:()Ljava/lang/String;
      36: invokevirtual #118                // Method org/hibernate/hql/internal/ast/util/SessionFactoryHelper.findSQLFunction:(Ljava/lang/String;)Lorg/hibernate/dialect/function/SQLFunction;
      39: astore_3
      40: aload_3
      41: ifnull        62
      44: aload_3
      45: aconst_null
      46: aload_0
      47: invokevirtual #26                 // Method getWalker:()Lorg/hibernate/hql/internal/ast/HqlSqlWalker;
      50: invokevirtual #78                 // Method org/hibernate/hql/internal/ast/HqlSqlWalker.getSessionFactoryHelper:()Lorg/hibernate/hql/internal/ast/util/SessionFactoryHelper;
      53: invokevirtual #79                 // Method org/hibernate/hql/internal/ast/util/SessionFactoryHelper.getFactory:()Lorg/hibernate/engine/spi/SessionFactoryImplementor;
      56: invokeinterface #119,  3          // InterfaceMethod org/hibernate/dialect/function/SQLFunction.getReturnType:(Lorg/hibernate/type/Type;Lorg/hibernate/engine/spi/Mapping;)Lorg/hibernate/type/Type;
      61: areturn
      62: aconst_null
      63: areturn

  public void setScalarColumnText(int) throws antlr.SemanticException;
    Code:
       0: aload_0
       1: getfield      #4                  // Field nakedPropertyRef:Z
       4: ifeq          15
       7: aload_0
       8: iload_1
       9: invokestatic  #120                // Method org/hibernate/hql/internal/ast/util/ColumnHelper.generateSingleScalarColumn:(Lorg/hibernate/hql/internal/ast/tree/HqlSqlWalkerNode;I)V
      12: goto          77
      15: aload_0
      16: invokevirtual #22                 // Method getFromElement:()Lorg/hibernate/hql/internal/ast/tree/FromElement;
      19: astore_2
      20: aload_2
      21: ifnull        72
      24: aload_2
      25: invokevirtual #46                 // Method org/hibernate/hql/internal/ast/tree/FromElement.getQueryableCollection:()Lorg/hibernate/persister/collection/QueryableCollection;
      28: ifnull        60
      31: aload_2
      32: invokevirtual #46                 // Method org/hibernate/hql/internal/ast/tree/FromElement.getQueryableCollection:()Lorg/hibernate/persister/collection/QueryableCollection;
      35: invokeinterface #47,  1           // InterfaceMethod org/hibernate/persister/collection/QueryableCollection.getElementType:()Lorg/hibernate/type/Type;
      40: invokeinterface #48,  1           // InterfaceMethod org/hibernate/type/Type.isComponentType:()Z
      45: ifeq          60
      48: aload_0
      49: aload_0
      50: invokevirtual #51                 // Method getColumns:()[Ljava/lang/String;
      53: iload_1
      54: invokestatic  #121                // Method org/hibernate/hql/internal/ast/util/ColumnHelper.generateScalarColumns:(Lorg/hibernate/hql/internal/ast/tree/HqlSqlWalkerNode;[Ljava/lang/String;I)V
      57: goto          77
      60: aload_0
      61: aload_2
      62: iload_1
      63: invokevirtual #122                // Method org/hibernate/hql/internal/ast/tree/FromElement.renderScalarIdentifierSelect:(I)Ljava/lang/String;
      66: invokevirtual #42                 // Method setText:(Ljava/lang/String;)V
      69: goto          77
      72: aload_0
      73: iload_1
      74: invokestatic  #120                // Method org/hibernate/hql/internal/ast/util/ColumnHelper.generateSingleScalarColumn:(Lorg/hibernate/hql/internal/ast/tree/HqlSqlWalkerNode;I)V
      77: return

  public java.lang.String getDisplayText();
    Code:
       0: new           #11                 // class java/lang/StringBuilder
       3: dup
       4: invokespecial #12                 // Method java/lang/StringBuilder."<init>":()V
       7: astore_1
       8: aload_0
       9: invokevirtual #123                // Method getType:()I
      12: sipush        144
      15: if_icmpne     93
      18: aload_1
      19: ldc           #124                // String {alias=
      21: invokevirtual #14                 // Method java/lang/StringBuilder.append:(Ljava/lang/String;)Ljava/lang/StringBuilder;
      24: aload_0
      25: invokevirtual #7                  // Method getOriginalText:()Ljava/lang/String;
      28: invokevirtual #14                 // Method java/lang/StringBuilder.append:(Ljava/lang/String;)Ljava/lang/StringBuilder;
      31: pop
      32: aload_0
      33: invokevirtual #22                 // Method getFromElement:()Lorg/hibernate/hql/internal/ast/tree/FromElement;
      36: ifnonnull     49
      39: aload_1
      40: ldc           #125                // String , no from element
      42: invokevirtual #14                 // Method java/lang/StringBuilder.append:(Ljava/lang/String;)Ljava/lang/StringBuilder;
      45: pop
      46: goto          83
      49: aload_1
      50: ldc           #126                // String , className=
      52: invokevirtual #14                 // Method java/lang/StringBuilder.append:(Ljava/lang/String;)Ljava/lang/StringBuilder;
      55: aload_0
      56: invokevirtual #22                 // Method getFromElement:()Lorg/hibernate/hql/internal/ast/tree/FromElement;
      59: invokevirtual #127                // Method org/hibernate/hql/internal/ast/tree/FromElement.getClassName:()Ljava/lang/String;
      62: invokevirtual #14                 // Method java/lang/StringBuilder.append:(Ljava/lang/String;)Ljava/lang/StringBuilder;
      65: pop
      66: aload_1
      67: ldc           #128                // String , tableAlias=
      69: invokevirtual #14                 // Method java/lang/StringBuilder.append:(Ljava/lang/String;)Ljava/lang/StringBuilder;
      72: aload_0
      73: invokevirtual #22                 // Method getFromElement:()Lorg/hibernate/hql/internal/ast/tree/FromElement;
      76: invokevirtual #23                 // Method org/hibernate/hql/internal/ast/tree/FromElement.getTableAlias:()Ljava/lang/String;
      79: invokevirtual #14                 // Method java/lang/StringBuilder.append:(Ljava/lang/String;)Ljava/lang/StringBuilder;
      82: pop
      83: aload_1
      84: ldc           #129                // String }
      86: invokevirtual #14                 // Method java/lang/StringBuilder.append:(Ljava/lang/String;)Ljava/lang/StringBuilder;
      89: pop
      90: goto          112
      93: aload_1
      94: ldc           #130                // String {originalText=
      96: invokevirtual #14                 // Method java/lang/StringBuilder.append:(Ljava/lang/String;)Ljava/lang/StringBuilder;
      99: aload_0
     100: invokevirtual #7                  // Method getOriginalText:()Ljava/lang/String;
     103: invokevirtual #14                 // Method java/lang/StringBuilder.append:(Ljava/lang/String;)Ljava/lang/StringBuilder;
     106: ldc           #129                // String }
     108: invokevirtual #14                 // Method java/lang/StringBuilder.append:(Ljava/lang/String;)Ljava/lang/StringBuilder;
     111: pop
     112: aload_1
     113: invokevirtual #16                 // Method java/lang/StringBuilder.toString:()Ljava/lang/String;
     116: areturn
}
