Compiled from "InfluxProperties.java"
public class org.springframework.boot.actuate.autoconfigure.metrics.export.influx.InfluxProperties extends org.springframework.boot.actuate.autoconfigure.metrics.export.properties.StepRegistryProperties {
  private java.lang.String db;

  private io.micrometer.influx.InfluxConsistency consistency;

  private java.lang.String userName;

  private java.lang.String password;

  private java.lang.String retentionPolicy;

  private java.lang.String uri;

  private boolean compressed;

  private boolean autoCreateDb;

  public org.springframework.boot.actuate.autoconfigure.metrics.export.influx.InfluxProperties();
    Code:
       0: aload_0
       1: invokespecial #1                  // Method org/springframework/boot/actuate/autoconfigure/metrics/export/properties/StepRegistryProperties."<init>":()V
       4: aload_0
       5: ldc           #2                  // String mydb
       7: putfield      #3                  // Field db:Ljava/lang/String;
      10: aload_0
      11: getstatic     #4                  // Field io/micrometer/influx/InfluxConsistency.ONE:Lio/micrometer/influx/InfluxConsistency;
      14: putfield      #5                  // Field consistency:Lio/micrometer/influx/InfluxConsistency;
      17: aload_0
      18: ldc           #6                  // String http://localhost:8086
      20: putfield      #7                  // Field uri:Ljava/lang/String;
      23: aload_0
      24: iconst_1
      25: putfield      #8                  // Field compressed:Z
      28: aload_0
      29: iconst_1
      30: putfield      #9                  // Field autoCreateDb:Z
      33: return

  public java.lang.String getDb();
    Code:
       0: aload_0
       1: getfield      #3                  // Field db:Ljava/lang/String;
       4: areturn

  public void setDb(java.lang.String);
    Code:
       0: aload_0
       1: aload_1
       2: putfield      #3                  // Field db:Ljava/lang/String;
       5: return

  public io.micrometer.influx.InfluxConsistency getConsistency();
    Code:
       0: aload_0
       1: getfield      #5                  // Field consistency:Lio/micrometer/influx/InfluxConsistency;
       4: areturn

  public void setConsistency(io.micrometer.influx.InfluxConsistency);
    Code:
       0: aload_0
       1: aload_1
       2: putfield      #5                  // Field consistency:Lio/micrometer/influx/InfluxConsistency;
       5: return

  public java.lang.String getUserName();
    Code:
       0: aload_0
       1: getfield      #10                 // Field userName:Ljava/lang/String;
       4: areturn

  public void setUserName(java.lang.String);
    Code:
       0: aload_0
       1: aload_1
       2: putfield      #10                 // Field userName:Ljava/lang/String;
       5: return

  public java.lang.String getPassword();
    Code:
       0: aload_0
       1: getfield      #11                 // Field password:Ljava/lang/String;
       4: areturn

  public void setPassword(java.lang.String);
    Code:
       0: aload_0
       1: aload_1
       2: putfield      #11                 // Field password:Ljava/lang/String;
       5: return

  public java.lang.String getRetentionPolicy();
    Code:
       0: aload_0
       1: getfield      #12                 // Field retentionPolicy:Ljava/lang/String;
       4: areturn

  public void setRetentionPolicy(java.lang.String);
    Code:
       0: aload_0
       1: aload_1
       2: putfield      #12                 // Field retentionPolicy:Ljava/lang/String;
       5: return

  public java.lang.String getUri();
    Code:
       0: aload_0
       1: getfield      #7                  // Field uri:Ljava/lang/String;
       4: areturn

  public void setUri(java.lang.String);
    Code:
       0: aload_0
       1: aload_1
       2: putfield      #7                  // Field uri:Ljava/lang/String;
       5: return

  public boolean isCompressed();
    Code:
       0: aload_0
       1: getfield      #8                  // Field compressed:Z
       4: ireturn

  public void setCompressed(boolean);
    Code:
       0: aload_0
       1: iload_1
       2: putfield      #8                  // Field compressed:Z
       5: return

  public boolean isAutoCreateDb();
    Code:
       0: aload_0
       1: getfield      #9                  // Field autoCreateDb:Z
       4: ireturn

  public void setAutoCreateDb(boolean);
    Code:
       0: aload_0
       1: iload_1
       2: putfield      #9                  // Field autoCreateDb:Z
       5: return
}
