Compiled from "DelegatingDnsResolver.java"
public class com.amazonaws.http.DelegatingDnsResolver implements org.apache.http.conn.DnsResolver {
  private final com.amazonaws.DnsResolver delegate;

  public com.amazonaws.http.DelegatingDnsResolver(com.amazonaws.DnsResolver);
    Code:
       0: aload_0
       1: invokespecial #1                  // Method java/lang/Object."<init>":()V
       4: aload_0
       5: aload_1
       6: putfield      #2                  // Field delegate:Lcom/amazonaws/DnsResolver;
       9: return

  public java.net.InetAddress[] resolve(java.lang.String) throws java.net.UnknownHostException;
    Code:
       0: aload_0
       1: getfield      #2                  // Field delegate:Lcom/amazonaws/DnsResolver;
       4: aload_1
       5: invokeinterface #3,  2            // InterfaceMethod com/amazonaws/DnsResolver.resolve:(Ljava/lang/String;)[Ljava/net/InetAddress;
      10: areturn
}
