Compiled from "UnreachableException.java"
public class org.jgroups.UnreachableException extends java.lang.RuntimeException {
  private static final long serialVersionUID;

  protected final org.jgroups.Address member;

  public org.jgroups.UnreachableException(org.jgroups.Address);
    Code:
       0: aload_0
       1: ldc           #1                  // String UnreachableException
       3: invokespecial #2                  // Method java/lang/RuntimeException."<init>":(Ljava/lang/String;)V
       6: aload_0
       7: aload_1
       8: putfield      #3                  // Field member:Lorg/jgroups/Address;
      11: return

  public org.jgroups.UnreachableException(java.lang.String, org.jgroups.Address);
    Code:
       0: aload_0
       1: aload_1
       2: invokespecial #2                  // Method java/lang/RuntimeException."<init>":(Ljava/lang/String;)V
       5: aload_0
       6: aload_2
       7: putfield      #3                  // Field member:Lorg/jgroups/Address;
      10: return

  public java.lang.String toString();
    Code:
       0: new           #4                  // class java/lang/StringBuilder
       3: dup
       4: invokespecial #5                  // Method java/lang/StringBuilder."<init>":()V
       7: aload_0
       8: invokevirtual #6                  // Method getMessage:()Ljava/lang/String;
      11: invokevirtual #7                  // Method java/lang/StringBuilder.append:(Ljava/lang/String;)Ljava/lang/StringBuilder;
      14: ldc           #8                  // String : member=
      16: invokevirtual #7                  // Method java/lang/StringBuilder.append:(Ljava/lang/String;)Ljava/lang/StringBuilder;
      19: aload_0
      20: getfield      #3                  // Field member:Lorg/jgroups/Address;
      23: invokevirtual #9                  // Method java/lang/StringBuilder.append:(Ljava/lang/Object;)Ljava/lang/StringBuilder;
      26: invokevirtual #10                 // Method java/lang/StringBuilder.toString:()Ljava/lang/String;
      29: areturn
}
