Compiled from "AbstractHttpClient.java"
public abstract class org.apache.http.impl.client.AbstractHttpClient implements org.apache.http.client.HttpClient {
  private final org.apache.commons.logging.Log log;

  private org.apache.http.params.HttpParams defaultParams;

  private org.apache.http.protocol.HttpRequestExecutor requestExec;

  private org.apache.http.conn.ClientConnectionManager connManager;

  private org.apache.http.ConnectionReuseStrategy reuseStrategy;

  private org.apache.http.conn.ConnectionKeepAliveStrategy keepAliveStrategy;

  private org.apache.http.cookie.CookieSpecRegistry supportedCookieSpecs;

  private org.apache.http.auth.AuthSchemeRegistry supportedAuthSchemes;

  private org.apache.http.protocol.BasicHttpProcessor httpProcessor;

  private org.apache.http.client.HttpRequestRetryHandler retryHandler;

  private org.apache.http.client.RedirectHandler redirectHandler;

  private org.apache.http.client.AuthenticationHandler targetAuthHandler;

  private org.apache.http.client.AuthenticationHandler proxyAuthHandler;

  private org.apache.http.client.CookieStore cookieStore;

  private org.apache.http.client.CredentialsProvider credsProvider;

  private org.apache.http.conn.routing.HttpRoutePlanner routePlanner;

  private org.apache.http.client.UserTokenHandler userTokenHandler;

  protected org.apache.http.impl.client.AbstractHttpClient(org.apache.http.conn.ClientConnectionManager, org.apache.http.params.HttpParams);
    Code:
       0: aload_0
       1: invokespecial #1                  // Method java/lang/Object."<init>":()V
       4: aload_0
       5: aload_0
       6: invokevirtual #2                  // Method java/lang/Object.getClass:()Ljava/lang/Class;
       9: invokestatic  #3                  // Method org/apache/commons/logging/LogFactory.getLog:(Ljava/lang/Class;)Lorg/apache/commons/logging/Log;
      12: putfield      #4                  // Field log:Lorg/apache/commons/logging/Log;
      15: aload_0
      16: aload_2
      17: putfield      #5                  // Field defaultParams:Lorg/apache/http/params/HttpParams;
      20: aload_0
      21: aload_1
      22: putfield      #6                  // Field connManager:Lorg/apache/http/conn/ClientConnectionManager;
      25: return

  protected abstract org.apache.http.params.HttpParams createHttpParams();

  protected abstract org.apache.http.protocol.HttpContext createHttpContext();

  protected abstract org.apache.http.protocol.HttpRequestExecutor createRequestExecutor();

  protected abstract org.apache.http.conn.ClientConnectionManager createClientConnectionManager();

  protected abstract org.apache.http.auth.AuthSchemeRegistry createAuthSchemeRegistry();

  protected abstract org.apache.http.cookie.CookieSpecRegistry createCookieSpecRegistry();

  protected abstract org.apache.http.ConnectionReuseStrategy createConnectionReuseStrategy();

  protected abstract org.apache.http.conn.ConnectionKeepAliveStrategy createConnectionKeepAliveStrategy();

  protected abstract org.apache.http.protocol.BasicHttpProcessor createHttpProcessor();

  protected abstract org.apache.http.client.HttpRequestRetryHandler createHttpRequestRetryHandler();

  protected abstract org.apache.http.client.RedirectHandler createRedirectHandler();

  protected abstract org.apache.http.client.AuthenticationHandler createTargetAuthenticationHandler();

  protected abstract org.apache.http.client.AuthenticationHandler createProxyAuthenticationHandler();

  protected abstract org.apache.http.client.CookieStore createCookieStore();

  protected abstract org.apache.http.client.CredentialsProvider createCredentialsProvider();

  protected abstract org.apache.http.conn.routing.HttpRoutePlanner createHttpRoutePlanner();

  protected abstract org.apache.http.client.UserTokenHandler createUserTokenHandler();

  public final synchronized org.apache.http.params.HttpParams getParams();
    Code:
       0: aload_0
       1: getfield      #5                  // Field defaultParams:Lorg/apache/http/params/HttpParams;
       4: ifnonnull     15
       7: aload_0
       8: aload_0
       9: invokevirtual #7                  // Method createHttpParams:()Lorg/apache/http/params/HttpParams;
      12: putfield      #5                  // Field defaultParams:Lorg/apache/http/params/HttpParams;
      15: aload_0
      16: getfield      #5                  // Field defaultParams:Lorg/apache/http/params/HttpParams;
      19: areturn

  public synchronized void setParams(org.apache.http.params.HttpParams);
    Code:
       0: aload_0
       1: aload_1
       2: putfield      #5                  // Field defaultParams:Lorg/apache/http/params/HttpParams;
       5: return

  public final synchronized org.apache.http.conn.ClientConnectionManager getConnectionManager();
    Code:
       0: aload_0
       1: getfield      #6                  // Field connManager:Lorg/apache/http/conn/ClientConnectionManager;
       4: ifnonnull     15
       7: aload_0
       8: aload_0
       9: invokevirtual #8                  // Method createClientConnectionManager:()Lorg/apache/http/conn/ClientConnectionManager;
      12: putfield      #6                  // Field connManager:Lorg/apache/http/conn/ClientConnectionManager;
      15: aload_0
      16: getfield      #6                  // Field connManager:Lorg/apache/http/conn/ClientConnectionManager;
      19: areturn

  public final synchronized org.apache.http.protocol.HttpRequestExecutor getRequestExecutor();
    Code:
       0: aload_0
       1: getfield      #9                  // Field requestExec:Lorg/apache/http/protocol/HttpRequestExecutor;
       4: ifnonnull     15
       7: aload_0
       8: aload_0
       9: invokevirtual #10                 // Method createRequestExecutor:()Lorg/apache/http/protocol/HttpRequestExecutor;
      12: putfield      #9                  // Field requestExec:Lorg/apache/http/protocol/HttpRequestExecutor;
      15: aload_0
      16: getfield      #9                  // Field requestExec:Lorg/apache/http/protocol/HttpRequestExecutor;
      19: areturn

  public final synchronized org.apache.http.auth.AuthSchemeRegistry getAuthSchemes();
    Code:
       0: aload_0
       1: getfield      #11                 // Field supportedAuthSchemes:Lorg/apache/http/auth/AuthSchemeRegistry;
       4: ifnonnull     15
       7: aload_0
       8: aload_0
       9: invokevirtual #12                 // Method createAuthSchemeRegistry:()Lorg/apache/http/auth/AuthSchemeRegistry;
      12: putfield      #11                 // Field supportedAuthSchemes:Lorg/apache/http/auth/AuthSchemeRegistry;
      15: aload_0
      16: getfield      #11                 // Field supportedAuthSchemes:Lorg/apache/http/auth/AuthSchemeRegistry;
      19: areturn

  public synchronized void setAuthSchemes(org.apache.http.auth.AuthSchemeRegistry);
    Code:
       0: aload_0
       1: aload_1
       2: putfield      #11                 // Field supportedAuthSchemes:Lorg/apache/http/auth/AuthSchemeRegistry;
       5: return

  public final synchronized org.apache.http.cookie.CookieSpecRegistry getCookieSpecs();
    Code:
       0: aload_0
       1: getfield      #13                 // Field supportedCookieSpecs:Lorg/apache/http/cookie/CookieSpecRegistry;
       4: ifnonnull     15
       7: aload_0
       8: aload_0
       9: invokevirtual #14                 // Method createCookieSpecRegistry:()Lorg/apache/http/cookie/CookieSpecRegistry;
      12: putfield      #13                 // Field supportedCookieSpecs:Lorg/apache/http/cookie/CookieSpecRegistry;
      15: aload_0
      16: getfield      #13                 // Field supportedCookieSpecs:Lorg/apache/http/cookie/CookieSpecRegistry;
      19: areturn

  public synchronized void setCookieSpecs(org.apache.http.cookie.CookieSpecRegistry);
    Code:
       0: aload_0
       1: aload_1
       2: putfield      #13                 // Field supportedCookieSpecs:Lorg/apache/http/cookie/CookieSpecRegistry;
       5: return

  public final synchronized org.apache.http.ConnectionReuseStrategy getConnectionReuseStrategy();
    Code:
       0: aload_0
       1: getfield      #15                 // Field reuseStrategy:Lorg/apache/http/ConnectionReuseStrategy;
       4: ifnonnull     15
       7: aload_0
       8: aload_0
       9: invokevirtual #16                 // Method createConnectionReuseStrategy:()Lorg/apache/http/ConnectionReuseStrategy;
      12: putfield      #15                 // Field reuseStrategy:Lorg/apache/http/ConnectionReuseStrategy;
      15: aload_0
      16: getfield      #15                 // Field reuseStrategy:Lorg/apache/http/ConnectionReuseStrategy;
      19: areturn

  public synchronized void setReuseStrategy(org.apache.http.ConnectionReuseStrategy);
    Code:
       0: aload_0
       1: aload_1
       2: putfield      #15                 // Field reuseStrategy:Lorg/apache/http/ConnectionReuseStrategy;
       5: return

  public final synchronized org.apache.http.conn.ConnectionKeepAliveStrategy getConnectionKeepAliveStrategy();
    Code:
       0: aload_0
       1: getfield      #17                 // Field keepAliveStrategy:Lorg/apache/http/conn/ConnectionKeepAliveStrategy;
       4: ifnonnull     15
       7: aload_0
       8: aload_0
       9: invokevirtual #18                 // Method createConnectionKeepAliveStrategy:()Lorg/apache/http/conn/ConnectionKeepAliveStrategy;
      12: putfield      #17                 // Field keepAliveStrategy:Lorg/apache/http/conn/ConnectionKeepAliveStrategy;
      15: aload_0
      16: getfield      #17                 // Field keepAliveStrategy:Lorg/apache/http/conn/ConnectionKeepAliveStrategy;
      19: areturn

  public synchronized void setKeepAliveStrategy(org.apache.http.conn.ConnectionKeepAliveStrategy);
    Code:
       0: aload_0
       1: aload_1
       2: putfield      #17                 // Field keepAliveStrategy:Lorg/apache/http/conn/ConnectionKeepAliveStrategy;
       5: return

  public final synchronized org.apache.http.client.HttpRequestRetryHandler getHttpRequestRetryHandler();
    Code:
       0: aload_0
       1: getfield      #19                 // Field retryHandler:Lorg/apache/http/client/HttpRequestRetryHandler;
       4: ifnonnull     15
       7: aload_0
       8: aload_0
       9: invokevirtual #20                 // Method createHttpRequestRetryHandler:()Lorg/apache/http/client/HttpRequestRetryHandler;
      12: putfield      #19                 // Field retryHandler:Lorg/apache/http/client/HttpRequestRetryHandler;
      15: aload_0
      16: getfield      #19                 // Field retryHandler:Lorg/apache/http/client/HttpRequestRetryHandler;
      19: areturn

  public synchronized void setHttpRequestRetryHandler(org.apache.http.client.HttpRequestRetryHandler);
    Code:
       0: aload_0
       1: aload_1
       2: putfield      #19                 // Field retryHandler:Lorg/apache/http/client/HttpRequestRetryHandler;
       5: return

  public final synchronized org.apache.http.client.RedirectHandler getRedirectHandler();
    Code:
       0: aload_0
       1: getfield      #21                 // Field redirectHandler:Lorg/apache/http/client/RedirectHandler;
       4: ifnonnull     15
       7: aload_0
       8: aload_0
       9: invokevirtual #22                 // Method createRedirectHandler:()Lorg/apache/http/client/RedirectHandler;
      12: putfield      #21                 // Field redirectHandler:Lorg/apache/http/client/RedirectHandler;
      15: aload_0
      16: getfield      #21                 // Field redirectHandler:Lorg/apache/http/client/RedirectHandler;
      19: areturn

  public synchronized void setRedirectHandler(org.apache.http.client.RedirectHandler);
    Code:
       0: aload_0
       1: aload_1
       2: putfield      #21                 // Field redirectHandler:Lorg/apache/http/client/RedirectHandler;
       5: return

  public final synchronized org.apache.http.client.AuthenticationHandler getTargetAuthenticationHandler();
    Code:
       0: aload_0
       1: getfield      #23                 // Field targetAuthHandler:Lorg/apache/http/client/AuthenticationHandler;
       4: ifnonnull     15
       7: aload_0
       8: aload_0
       9: invokevirtual #24                 // Method createTargetAuthenticationHandler:()Lorg/apache/http/client/AuthenticationHandler;
      12: putfield      #23                 // Field targetAuthHandler:Lorg/apache/http/client/AuthenticationHandler;
      15: aload_0
      16: getfield      #23                 // Field targetAuthHandler:Lorg/apache/http/client/AuthenticationHandler;
      19: areturn

  public synchronized void setTargetAuthenticationHandler(org.apache.http.client.AuthenticationHandler);
    Code:
       0: aload_0
       1: aload_1
       2: putfield      #23                 // Field targetAuthHandler:Lorg/apache/http/client/AuthenticationHandler;
       5: return

  public final synchronized org.apache.http.client.AuthenticationHandler getProxyAuthenticationHandler();
    Code:
       0: aload_0
       1: getfield      #25                 // Field proxyAuthHandler:Lorg/apache/http/client/AuthenticationHandler;
       4: ifnonnull     15
       7: aload_0
       8: aload_0
       9: invokevirtual #26                 // Method createProxyAuthenticationHandler:()Lorg/apache/http/client/AuthenticationHandler;
      12: putfield      #25                 // Field proxyAuthHandler:Lorg/apache/http/client/AuthenticationHandler;
      15: aload_0
      16: getfield      #25                 // Field proxyAuthHandler:Lorg/apache/http/client/AuthenticationHandler;
      19: areturn

  public synchronized void setProxyAuthenticationHandler(org.apache.http.client.AuthenticationHandler);
    Code:
       0: aload_0
       1: aload_1
       2: putfield      #25                 // Field proxyAuthHandler:Lorg/apache/http/client/AuthenticationHandler;
       5: return

  public final synchronized org.apache.http.client.CookieStore getCookieStore();
    Code:
       0: aload_0
       1: getfield      #27                 // Field cookieStore:Lorg/apache/http/client/CookieStore;
       4: ifnonnull     15
       7: aload_0
       8: aload_0
       9: invokevirtual #28                 // Method createCookieStore:()Lorg/apache/http/client/CookieStore;
      12: putfield      #27                 // Field cookieStore:Lorg/apache/http/client/CookieStore;
      15: aload_0
      16: getfield      #27                 // Field cookieStore:Lorg/apache/http/client/CookieStore;
      19: areturn

  public synchronized void setCookieStore(org.apache.http.client.CookieStore);
    Code:
       0: aload_0
       1: aload_1
       2: putfield      #27                 // Field cookieStore:Lorg/apache/http/client/CookieStore;
       5: return

  public final synchronized org.apache.http.client.CredentialsProvider getCredentialsProvider();
    Code:
       0: aload_0
       1: getfield      #29                 // Field credsProvider:Lorg/apache/http/client/CredentialsProvider;
       4: ifnonnull     15
       7: aload_0
       8: aload_0
       9: invokevirtual #30                 // Method createCredentialsProvider:()Lorg/apache/http/client/CredentialsProvider;
      12: putfield      #29                 // Field credsProvider:Lorg/apache/http/client/CredentialsProvider;
      15: aload_0
      16: getfield      #29                 // Field credsProvider:Lorg/apache/http/client/CredentialsProvider;
      19: areturn

  public synchronized void setCredentialsProvider(org.apache.http.client.CredentialsProvider);
    Code:
       0: aload_0
       1: aload_1
       2: putfield      #29                 // Field credsProvider:Lorg/apache/http/client/CredentialsProvider;
       5: return

  public final synchronized org.apache.http.conn.routing.HttpRoutePlanner getRoutePlanner();
    Code:
       0: aload_0
       1: getfield      #31                 // Field routePlanner:Lorg/apache/http/conn/routing/HttpRoutePlanner;
       4: ifnonnull     15
       7: aload_0
       8: aload_0
       9: invokevirtual #32                 // Method createHttpRoutePlanner:()Lorg/apache/http/conn/routing/HttpRoutePlanner;
      12: putfield      #31                 // Field routePlanner:Lorg/apache/http/conn/routing/HttpRoutePlanner;
      15: aload_0
      16: getfield      #31                 // Field routePlanner:Lorg/apache/http/conn/routing/HttpRoutePlanner;
      19: areturn

  public synchronized void setRoutePlanner(org.apache.http.conn.routing.HttpRoutePlanner);
    Code:
       0: aload_0
       1: aload_1
       2: putfield      #31                 // Field routePlanner:Lorg/apache/http/conn/routing/HttpRoutePlanner;
       5: return

  public final synchronized org.apache.http.client.UserTokenHandler getUserTokenHandler();
    Code:
       0: aload_0
       1: getfield      #33                 // Field userTokenHandler:Lorg/apache/http/client/UserTokenHandler;
       4: ifnonnull     15
       7: aload_0
       8: aload_0
       9: invokevirtual #34                 // Method createUserTokenHandler:()Lorg/apache/http/client/UserTokenHandler;
      12: putfield      #33                 // Field userTokenHandler:Lorg/apache/http/client/UserTokenHandler;
      15: aload_0
      16: getfield      #33                 // Field userTokenHandler:Lorg/apache/http/client/UserTokenHandler;
      19: areturn

  public synchronized void setUserTokenHandler(org.apache.http.client.UserTokenHandler);
    Code:
       0: aload_0
       1: aload_1
       2: putfield      #33                 // Field userTokenHandler:Lorg/apache/http/client/UserTokenHandler;
       5: return

  protected final synchronized org.apache.http.protocol.BasicHttpProcessor getHttpProcessor();
    Code:
       0: aload_0
       1: getfield      #35                 // Field httpProcessor:Lorg/apache/http/protocol/BasicHttpProcessor;
       4: ifnonnull     15
       7: aload_0
       8: aload_0
       9: invokevirtual #36                 // Method createHttpProcessor:()Lorg/apache/http/protocol/BasicHttpProcessor;
      12: putfield      #35                 // Field httpProcessor:Lorg/apache/http/protocol/BasicHttpProcessor;
      15: aload_0
      16: getfield      #35                 // Field httpProcessor:Lorg/apache/http/protocol/BasicHttpProcessor;
      19: areturn

  public synchronized void addResponseInterceptor(org.apache.http.HttpResponseInterceptor);
    Code:
       0: aload_0
       1: invokevirtual #37                 // Method getHttpProcessor:()Lorg/apache/http/protocol/BasicHttpProcessor;
       4: aload_1
       5: invokevirtual #38                 // Method org/apache/http/protocol/BasicHttpProcessor.addInterceptor:(Lorg/apache/http/HttpResponseInterceptor;)V
       8: return

  public synchronized void addResponseInterceptor(org.apache.http.HttpResponseInterceptor, int);
    Code:
       0: aload_0
       1: invokevirtual #37                 // Method getHttpProcessor:()Lorg/apache/http/protocol/BasicHttpProcessor;
       4: aload_1
       5: iload_2
       6: invokevirtual #39                 // Method org/apache/http/protocol/BasicHttpProcessor.addInterceptor:(Lorg/apache/http/HttpResponseInterceptor;I)V
       9: return

  public synchronized org.apache.http.HttpResponseInterceptor getResponseInterceptor(int);
    Code:
       0: aload_0
       1: invokevirtual #37                 // Method getHttpProcessor:()Lorg/apache/http/protocol/BasicHttpProcessor;
       4: iload_1
       5: invokevirtual #40                 // Method org/apache/http/protocol/BasicHttpProcessor.getResponseInterceptor:(I)Lorg/apache/http/HttpResponseInterceptor;
       8: areturn

  public synchronized int getResponseInterceptorCount();
    Code:
       0: aload_0
       1: invokevirtual #37                 // Method getHttpProcessor:()Lorg/apache/http/protocol/BasicHttpProcessor;
       4: invokevirtual #41                 // Method org/apache/http/protocol/BasicHttpProcessor.getResponseInterceptorCount:()I
       7: ireturn

  public synchronized void clearResponseInterceptors();
    Code:
       0: aload_0
       1: invokevirtual #37                 // Method getHttpProcessor:()Lorg/apache/http/protocol/BasicHttpProcessor;
       4: invokevirtual #42                 // Method org/apache/http/protocol/BasicHttpProcessor.clearResponseInterceptors:()V
       7: return

  public synchronized void removeResponseInterceptorByClass(java.lang.Class<? extends org.apache.http.HttpResponseInterceptor>);
    Code:
       0: aload_0
       1: invokevirtual #37                 // Method getHttpProcessor:()Lorg/apache/http/protocol/BasicHttpProcessor;
       4: aload_1
       5: invokevirtual #43                 // Method org/apache/http/protocol/BasicHttpProcessor.removeResponseInterceptorByClass:(Ljava/lang/Class;)V
       8: return

  public synchronized void addRequestInterceptor(org.apache.http.HttpRequestInterceptor);
    Code:
       0: aload_0
       1: invokevirtual #37                 // Method getHttpProcessor:()Lorg/apache/http/protocol/BasicHttpProcessor;
       4: aload_1
       5: invokevirtual #44                 // Method org/apache/http/protocol/BasicHttpProcessor.addInterceptor:(Lorg/apache/http/HttpRequestInterceptor;)V
       8: return

  public synchronized void addRequestInterceptor(org.apache.http.HttpRequestInterceptor, int);
    Code:
       0: aload_0
       1: invokevirtual #37                 // Method getHttpProcessor:()Lorg/apache/http/protocol/BasicHttpProcessor;
       4: aload_1
       5: iload_2
       6: invokevirtual #45                 // Method org/apache/http/protocol/BasicHttpProcessor.addInterceptor:(Lorg/apache/http/HttpRequestInterceptor;I)V
       9: return

  public synchronized org.apache.http.HttpRequestInterceptor getRequestInterceptor(int);
    Code:
       0: aload_0
       1: invokevirtual #37                 // Method getHttpProcessor:()Lorg/apache/http/protocol/BasicHttpProcessor;
       4: iload_1
       5: invokevirtual #46                 // Method org/apache/http/protocol/BasicHttpProcessor.getRequestInterceptor:(I)Lorg/apache/http/HttpRequestInterceptor;
       8: areturn

  public synchronized int getRequestInterceptorCount();
    Code:
       0: aload_0
       1: invokevirtual #37                 // Method getHttpProcessor:()Lorg/apache/http/protocol/BasicHttpProcessor;
       4: invokevirtual #47                 // Method org/apache/http/protocol/BasicHttpProcessor.getRequestInterceptorCount:()I
       7: ireturn

  public synchronized void clearRequestInterceptors();
    Code:
       0: aload_0
       1: invokevirtual #37                 // Method getHttpProcessor:()Lorg/apache/http/protocol/BasicHttpProcessor;
       4: invokevirtual #48                 // Method org/apache/http/protocol/BasicHttpProcessor.clearRequestInterceptors:()V
       7: return

  public synchronized void removeRequestInterceptorByClass(java.lang.Class<? extends org.apache.http.HttpRequestInterceptor>);
    Code:
       0: aload_0
       1: invokevirtual #37                 // Method getHttpProcessor:()Lorg/apache/http/protocol/BasicHttpProcessor;
       4: aload_1
       5: invokevirtual #49                 // Method org/apache/http/protocol/BasicHttpProcessor.removeRequestInterceptorByClass:(Ljava/lang/Class;)V
       8: return

  public final org.apache.http.HttpResponse execute(org.apache.http.client.methods.HttpUriRequest) throws java.io.IOException, org.apache.http.client.ClientProtocolException;
    Code:
       0: aload_0
       1: aload_1
       2: aconst_null
       3: checkcast     #50                 // class org/apache/http/protocol/HttpContext
       6: invokevirtual #51                 // Method execute:(Lorg/apache/http/client/methods/HttpUriRequest;Lorg/apache/http/protocol/HttpContext;)Lorg/apache/http/HttpResponse;
       9: areturn

  public final org.apache.http.HttpResponse execute(org.apache.http.client.methods.HttpUriRequest, org.apache.http.protocol.HttpContext) throws java.io.IOException, org.apache.http.client.ClientProtocolException;
    Code:
       0: aload_1
       1: ifnonnull     14
       4: new           #52                 // class java/lang/IllegalArgumentException
       7: dup
       8: ldc           #53                 // String Request must not be null.
      10: invokespecial #54                 // Method java/lang/IllegalArgumentException."<init>":(Ljava/lang/String;)V
      13: athrow
      14: aload_0
      15: aload_0
      16: aload_1
      17: invokespecial #55                 // Method determineTarget:(Lorg/apache/http/client/methods/HttpUriRequest;)Lorg/apache/http/HttpHost;
      20: aload_1
      21: aload_2
      22: invokevirtual #56                 // Method execute:(Lorg/apache/http/HttpHost;Lorg/apache/http/HttpRequest;Lorg/apache/http/protocol/HttpContext;)Lorg/apache/http/HttpResponse;
      25: areturn

  private org.apache.http.HttpHost determineTarget(org.apache.http.client.methods.HttpUriRequest);
    Code:
       0: aconst_null
       1: astore_2
       2: aload_1
       3: invokeinterface #57,  1           // InterfaceMethod org/apache/http/client/methods/HttpUriRequest.getURI:()Ljava/net/URI;
       8: astore_3
       9: aload_3
      10: invokevirtual #58                 // Method java/net/URI.isAbsolute:()Z
      13: ifeq          36
      16: new           #59                 // class org/apache/http/HttpHost
      19: dup
      20: aload_3
      21: invokevirtual #60                 // Method java/net/URI.getHost:()Ljava/lang/String;
      24: aload_3
      25: invokevirtual #61                 // Method java/net/URI.getPort:()I
      28: aload_3
      29: invokevirtual #62                 // Method java/net/URI.getScheme:()Ljava/lang/String;
      32: invokespecial #63                 // Method org/apache/http/HttpHost."<init>":(Ljava/lang/String;ILjava/lang/String;)V
      35: astore_2
      36: aload_2
      37: areturn

  public final org.apache.http.HttpResponse execute(org.apache.http.HttpHost, org.apache.http.HttpRequest) throws java.io.IOException, org.apache.http.client.ClientProtocolException;
    Code:
       0: aload_0
       1: aload_1
       2: aload_2
       3: aconst_null
       4: checkcast     #50                 // class org/apache/http/protocol/HttpContext
       7: invokevirtual #56                 // Method execute:(Lorg/apache/http/HttpHost;Lorg/apache/http/HttpRequest;Lorg/apache/http/protocol/HttpContext;)Lorg/apache/http/HttpResponse;
      10: areturn

  public final org.apache.http.HttpResponse execute(org.apache.http.HttpHost, org.apache.http.HttpRequest, org.apache.http.protocol.HttpContext) throws java.io.IOException, org.apache.http.client.ClientProtocolException;
    Code:
       0: aload_2
       1: ifnonnull     14
       4: new           #52                 // class java/lang/IllegalArgumentException
       7: dup
       8: ldc           #53                 // String Request must not be null.
      10: invokespecial #54                 // Method java/lang/IllegalArgumentException."<init>":(Ljava/lang/String;)V
      13: athrow
      14: aconst_null
      15: astore        4
      17: aconst_null
      18: astore        5
      20: aload_0
      21: dup
      22: astore        6
      24: monitorenter
      25: aload_0
      26: invokevirtual #64                 // Method createHttpContext:()Lorg/apache/http/protocol/HttpContext;
      29: astore        7
      31: aload_3
      32: ifnonnull     42
      35: aload         7
      37: astore        4
      39: goto          54
      42: new           #65                 // class org/apache/http/protocol/DefaultedHttpContext
      45: dup
      46: aload_3
      47: aload         7
      49: invokespecial #66                 // Method org/apache/http/protocol/DefaultedHttpContext."<init>":(Lorg/apache/http/protocol/HttpContext;Lorg/apache/http/protocol/HttpContext;)V
      52: astore        4
      54: aload_0
      55: aload_0
      56: invokevirtual #67                 // Method getRequestExecutor:()Lorg/apache/http/protocol/HttpRequestExecutor;
      59: aload_0
      60: invokevirtual #68                 // Method getConnectionManager:()Lorg/apache/http/conn/ClientConnectionManager;
      63: aload_0
      64: invokevirtual #69                 // Method getConnectionReuseStrategy:()Lorg/apache/http/ConnectionReuseStrategy;
      67: aload_0
      68: invokevirtual #70                 // Method getConnectionKeepAliveStrategy:()Lorg/apache/http/conn/ConnectionKeepAliveStrategy;
      71: aload_0
      72: invokevirtual #71                 // Method getRoutePlanner:()Lorg/apache/http/conn/routing/HttpRoutePlanner;
      75: aload_0
      76: invokevirtual #37                 // Method getHttpProcessor:()Lorg/apache/http/protocol/BasicHttpProcessor;
      79: invokevirtual #72                 // Method org/apache/http/protocol/BasicHttpProcessor.copy:()Lorg/apache/http/protocol/BasicHttpProcessor;
      82: aload_0
      83: invokevirtual #73                 // Method getHttpRequestRetryHandler:()Lorg/apache/http/client/HttpRequestRetryHandler;
      86: aload_0
      87: invokevirtual #74                 // Method getRedirectHandler:()Lorg/apache/http/client/RedirectHandler;
      90: aload_0
      91: invokevirtual #75                 // Method getTargetAuthenticationHandler:()Lorg/apache/http/client/AuthenticationHandler;
      94: aload_0
      95: invokevirtual #76                 // Method getProxyAuthenticationHandler:()Lorg/apache/http/client/AuthenticationHandler;
      98: aload_0
      99: invokevirtual #77                 // Method getUserTokenHandler:()Lorg/apache/http/client/UserTokenHandler;
     102: aload_0
     103: aload_2
     104: invokevirtual #78                 // Method determineParams:(Lorg/apache/http/HttpRequest;)Lorg/apache/http/params/HttpParams;
     107: invokevirtual #79                 // Method createClientRequestDirector:(Lorg/apache/http/protocol/HttpRequestExecutor;Lorg/apache/http/conn/ClientConnectionManager;Lorg/apache/http/ConnectionReuseStrategy;Lorg/apache/http/conn/ConnectionKeepAliveStrategy;Lorg/apache/http/conn/routing/HttpRoutePlanner;Lorg/apache/http/protocol/HttpProcessor;Lorg/apache/http/client/HttpRequestRetryHandler;Lorg/apache/http/client/RedirectHandler;Lorg/apache/http/client/AuthenticationHandler;Lorg/apache/http/client/AuthenticationHandler;Lorg/apache/http/client/UserTokenHandler;Lorg/apache/http/params/HttpParams;)Lorg/apache/http/client/RequestDirector;
     110: astore        5
     112: aload         6
     114: monitorexit
     115: goto          126
     118: astore        8
     120: aload         6
     122: monitorexit
     123: aload         8
     125: athrow
     126: aload         5
     128: aload_1
     129: aload_2
     130: aload         4
     132: invokeinterface #80,  4           // InterfaceMethod org/apache/http/client/RequestDirector.execute:(Lorg/apache/http/HttpHost;Lorg/apache/http/HttpRequest;Lorg/apache/http/protocol/HttpContext;)Lorg/apache/http/HttpResponse;
     137: areturn
     138: astore        6
     140: new           #82                 // class org/apache/http/client/ClientProtocolException
     143: dup
     144: aload         6
     146: invokespecial #83                 // Method org/apache/http/client/ClientProtocolException."<init>":(Ljava/lang/Throwable;)V
     149: athrow
    Exception table:
       from    to  target type
          25   115   118   any
         118   123   118   any
         126   137   138   Class org/apache/http/HttpException

  protected org.apache.http.client.RequestDirector createClientRequestDirector(org.apache.http.protocol.HttpRequestExecutor, org.apache.http.conn.ClientConnectionManager, org.apache.http.ConnectionReuseStrategy, org.apache.http.conn.ConnectionKeepAliveStrategy, org.apache.http.conn.routing.HttpRoutePlanner, org.apache.http.protocol.HttpProcessor, org.apache.http.client.HttpRequestRetryHandler, org.apache.http.client.RedirectHandler, org.apache.http.client.AuthenticationHandler, org.apache.http.client.AuthenticationHandler, org.apache.http.client.UserTokenHandler, org.apache.http.params.HttpParams);
    Code:
       0: new           #84                 // class org/apache/http/impl/client/DefaultRequestDirector
       3: dup
       4: aload_0
       5: getfield      #4                  // Field log:Lorg/apache/commons/logging/Log;
       8: aload_1
       9: aload_2
      10: aload_3
      11: aload         4
      13: aload         5
      15: aload         6
      17: aload         7
      19: aload         8
      21: aload         9
      23: aload         10
      25: aload         11
      27: aload         12
      29: invokespecial #85                 // Method org/apache/http/impl/client/DefaultRequestDirector."<init>":(Lorg/apache/commons/logging/Log;Lorg/apache/http/protocol/HttpRequestExecutor;Lorg/apache/http/conn/ClientConnectionManager;Lorg/apache/http/ConnectionReuseStrategy;Lorg/apache/http/conn/ConnectionKeepAliveStrategy;Lorg/apache/http/conn/routing/HttpRoutePlanner;Lorg/apache/http/protocol/HttpProcessor;Lorg/apache/http/client/HttpRequestRetryHandler;Lorg/apache/http/client/RedirectHandler;Lorg/apache/http/client/AuthenticationHandler;Lorg/apache/http/client/AuthenticationHandler;Lorg/apache/http/client/UserTokenHandler;Lorg/apache/http/params/HttpParams;)V
      32: areturn

  protected org.apache.http.params.HttpParams determineParams(org.apache.http.HttpRequest);
    Code:
       0: new           #86                 // class org/apache/http/impl/client/ClientParamsStack
       3: dup
       4: aconst_null
       5: aload_0
       6: invokevirtual #87                 // Method getParams:()Lorg/apache/http/params/HttpParams;
       9: aload_1
      10: invokeinterface #88,  1           // InterfaceMethod org/apache/http/HttpRequest.getParams:()Lorg/apache/http/params/HttpParams;
      15: aconst_null
      16: invokespecial #89                 // Method org/apache/http/impl/client/ClientParamsStack."<init>":(Lorg/apache/http/params/HttpParams;Lorg/apache/http/params/HttpParams;Lorg/apache/http/params/HttpParams;Lorg/apache/http/params/HttpParams;)V
      19: areturn

  public <T> T execute(org.apache.http.client.methods.HttpUriRequest, org.apache.http.client.ResponseHandler<? extends T>) throws java.io.IOException, org.apache.http.client.ClientProtocolException;
    Code:
       0: aload_0
       1: aload_1
       2: aload_2
       3: aconst_null
       4: invokevirtual #90                 // Method execute:(Lorg/apache/http/client/methods/HttpUriRequest;Lorg/apache/http/client/ResponseHandler;Lorg/apache/http/protocol/HttpContext;)Ljava/lang/Object;
       7: areturn

  public <T> T execute(org.apache.http.client.methods.HttpUriRequest, org.apache.http.client.ResponseHandler<? extends T>, org.apache.http.protocol.HttpContext) throws java.io.IOException, org.apache.http.client.ClientProtocolException;
    Code:
       0: aload_0
       1: aload_1
       2: invokespecial #55                 // Method determineTarget:(Lorg/apache/http/client/methods/HttpUriRequest;)Lorg/apache/http/HttpHost;
       5: astore        4
       7: aload_0
       8: aload         4
      10: aload_1
      11: aload_2
      12: aload_3
      13: invokevirtual #91                 // Method execute:(Lorg/apache/http/HttpHost;Lorg/apache/http/HttpRequest;Lorg/apache/http/client/ResponseHandler;Lorg/apache/http/protocol/HttpContext;)Ljava/lang/Object;
      16: areturn

  public <T> T execute(org.apache.http.HttpHost, org.apache.http.HttpRequest, org.apache.http.client.ResponseHandler<? extends T>) throws java.io.IOException, org.apache.http.client.ClientProtocolException;
    Code:
       0: aload_0
       1: aload_1
       2: aload_2
       3: aload_3
       4: aconst_null
       5: invokevirtual #91                 // Method execute:(Lorg/apache/http/HttpHost;Lorg/apache/http/HttpRequest;Lorg/apache/http/client/ResponseHandler;Lorg/apache/http/protocol/HttpContext;)Ljava/lang/Object;
       8: areturn

  public <T> T execute(org.apache.http.HttpHost, org.apache.http.HttpRequest, org.apache.http.client.ResponseHandler<? extends T>, org.apache.http.protocol.HttpContext) throws java.io.IOException, org.apache.http.client.ClientProtocolException;
    Code:
       0: aload_3
       1: ifnonnull     14
       4: new           #52                 // class java/lang/IllegalArgumentException
       7: dup
       8: ldc           #92                 // String Response handler must not be null.
      10: invokespecial #54                 // Method java/lang/IllegalArgumentException."<init>":(Ljava/lang/String;)V
      13: athrow
      14: aload_0
      15: aload_1
      16: aload_2
      17: aload         4
      19: invokevirtual #56                 // Method execute:(Lorg/apache/http/HttpHost;Lorg/apache/http/HttpRequest;Lorg/apache/http/protocol/HttpContext;)Lorg/apache/http/HttpResponse;
      22: astore        5
      24: aload_3
      25: aload         5
      27: invokeinterface #93,  2           // InterfaceMethod org/apache/http/client/ResponseHandler.handleResponse:(Lorg/apache/http/HttpResponse;)Ljava/lang/Object;
      32: astore        6
      34: goto          130
      37: astore        7
      39: aload         5
      41: invokeinterface #95,  1           // InterfaceMethod org/apache/http/HttpResponse.getEntity:()Lorg/apache/http/HttpEntity;
      46: astore        8
      48: aload         8
      50: ifnull        78
      53: aload         8
      55: invokeinterface #96,  1           // InterfaceMethod org/apache/http/HttpEntity.consumeContent:()V
      60: goto          78
      63: astore        9
      65: aload_0
      66: getfield      #4                  // Field log:Lorg/apache/commons/logging/Log;
      69: ldc           #97                 // String Error consuming content after an exception.
      71: aload         9
      73: invokeinterface #98,  3           // InterfaceMethod org/apache/commons/logging/Log.warn:(Ljava/lang/Object;Ljava/lang/Throwable;)V
      78: aload         7
      80: instanceof    #99                 // class java/lang/Error
      83: ifeq          92
      86: aload         7
      88: checkcast     #99                 // class java/lang/Error
      91: athrow
      92: aload         7
      94: instanceof    #100                // class java/lang/RuntimeException
      97: ifeq          106
     100: aload         7
     102: checkcast     #100                // class java/lang/RuntimeException
     105: athrow
     106: aload         7
     108: instanceof    #101                // class java/io/IOException
     111: ifeq          120
     114: aload         7
     116: checkcast     #101                // class java/io/IOException
     119: athrow
     120: new           #102                // class java/lang/reflect/UndeclaredThrowableException
     123: dup
     124: aload         7
     126: invokespecial #103                // Method java/lang/reflect/UndeclaredThrowableException."<init>":(Ljava/lang/Throwable;)V
     129: athrow
     130: aload         5
     132: invokeinterface #95,  1           // InterfaceMethod org/apache/http/HttpResponse.getEntity:()Lorg/apache/http/HttpEntity;
     137: astore        7
     139: aload         7
     141: ifnull        151
     144: aload         7
     146: invokeinterface #96,  1           // InterfaceMethod org/apache/http/HttpEntity.consumeContent:()V
     151: aload         6
     153: areturn
    Exception table:
       from    to  target type
          24    34    37   Class java/lang/Throwable
          53    60    63   Class java/lang/Throwable
}
