Compiled from "HttpRedirect.java"
class org.apache.http.impl.client.HttpRedirect extends org.apache.http.client.methods.HttpRequestBase {
  private java.lang.String method;

  public org.apache.http.impl.client.HttpRedirect(java.lang.String, java.net.URI);
    Code:
       0: aload_0
       1: invokespecial #1                  // Method org/apache/http/client/methods/HttpRequestBase."<init>":()V
       4: aload_1
       5: ldc           #2                  // String HEAD
       7: invokevirtual #3                  // Method java/lang/String.equalsIgnoreCase:(Ljava/lang/String;)Z
      10: ifeq          22
      13: aload_0
      14: ldc           #2                  // String HEAD
      16: putfield      #4                  // Field method:Ljava/lang/String;
      19: goto          28
      22: aload_0
      23: ldc           #5                  // String GET
      25: putfield      #4                  // Field method:Ljava/lang/String;
      28: aload_0
      29: aload_2
      30: invokevirtual #6                  // Method setURI:(Ljava/net/URI;)V
      33: return

  public java.lang.String getMethod();
    Code:
       0: aload_0
       1: getfield      #4                  // Field method:Ljava/lang/String;
       4: areturn
}
