Compiled from "Point.java"
public class net.thucydides.core.geometry.Point {
  final java.math.BigDecimal x;

  final java.math.BigDecimal y;

  public net.thucydides.core.geometry.Point(java.math.BigDecimal, java.math.BigDecimal);
    Code:
       0: aload_0
       1: invokespecial #1                  // Method java/lang/Object."<init>":()V
       4: aload_0
       5: aload_1
       6: putfield      #2                  // Field x:Ljava/math/BigDecimal;
       9: aload_0
      10: aload_2
      11: putfield      #3                  // Field y:Ljava/math/BigDecimal;
      14: return

  public static net.thucydides.core.geometry.Point at(int, int);
    Code:
       0: new           #4                  // class net/thucydides/core/geometry/Point
       3: dup
       4: new           #5                  // class java/math/BigDecimal
       7: dup
       8: iload_0
       9: invokespecial #6                  // Method java/math/BigDecimal."<init>":(I)V
      12: new           #5                  // class java/math/BigDecimal
      15: dup
      16: iload_1
      17: invokespecial #6                  // Method java/math/BigDecimal."<init>":(I)V
      20: invokespecial #7                  // Method "<init>":(Ljava/math/BigDecimal;Ljava/math/BigDecimal;)V
      23: areturn

  public static net.thucydides.core.geometry.Point at(long, long);
    Code:
       0: new           #4                  // class net/thucydides/core/geometry/Point
       3: dup
       4: new           #5                  // class java/math/BigDecimal
       7: dup
       8: lload_0
       9: invokespecial #8                  // Method java/math/BigDecimal."<init>":(J)V
      12: new           #5                  // class java/math/BigDecimal
      15: dup
      16: lload_2
      17: invokespecial #8                  // Method java/math/BigDecimal."<init>":(J)V
      20: invokespecial #7                  // Method "<init>":(Ljava/math/BigDecimal;Ljava/math/BigDecimal;)V
      23: areturn

  public static net.thucydides.core.geometry.Point at(java.math.BigDecimal, java.math.BigDecimal);
    Code:
       0: new           #4                  // class net/thucydides/core/geometry/Point
       3: dup
       4: aload_0
       5: aload_1
       6: invokespecial #7                  // Method "<init>":(Ljava/math/BigDecimal;Ljava/math/BigDecimal;)V
       9: areturn

  public java.math.BigDecimal getX();
    Code:
       0: aload_0
       1: getfield      #2                  // Field x:Ljava/math/BigDecimal;
       4: areturn

  public java.math.BigDecimal getY();
    Code:
       0: aload_0
       1: getfield      #3                  // Field y:Ljava/math/BigDecimal;
       4: areturn

  public boolean equals(java.lang.Object);
    Code:
       0: aload_0
       1: aload_1
       2: iconst_0
       3: anewarray     #9                  // class java/lang/String
       6: invokestatic  #10                 // Method org/apache/commons/lang3/builder/EqualsBuilder.reflectionEquals:(Ljava/lang/Object;Ljava/lang/Object;[Ljava/lang/String;)Z
       9: ireturn

  public int hashCode();
    Code:
       0: aload_0
       1: iconst_0
       2: anewarray     #9                  // class java/lang/String
       5: invokestatic  #11                 // Method org/apache/commons/lang3/builder/HashCodeBuilder.reflectionHashCode:(Ljava/lang/Object;[Ljava/lang/String;)I
       8: ireturn

  public java.lang.String toString();
    Code:
       0: new           #12                 // class java/lang/StringBuilder
       3: dup
       4: invokespecial #13                 // Method java/lang/StringBuilder."<init>":()V
       7: ldc           #14                 // String (
       9: invokevirtual #15                 // Method java/lang/StringBuilder.append:(Ljava/lang/String;)Ljava/lang/StringBuilder;
      12: aload_0
      13: getfield      #2                  // Field x:Ljava/math/BigDecimal;
      16: invokevirtual #16                 // Method java/lang/StringBuilder.append:(Ljava/lang/Object;)Ljava/lang/StringBuilder;
      19: ldc           #17                 // String ,
      21: invokevirtual #15                 // Method java/lang/StringBuilder.append:(Ljava/lang/String;)Ljava/lang/StringBuilder;
      24: aload_0
      25: getfield      #3                  // Field y:Ljava/math/BigDecimal;
      28: invokevirtual #16                 // Method java/lang/StringBuilder.append:(Ljava/lang/Object;)Ljava/lang/StringBuilder;
      31: ldc           #18                 // String )
      33: invokevirtual #15                 // Method java/lang/StringBuilder.append:(Ljava/lang/String;)Ljava/lang/StringBuilder;
      36: invokevirtual #19                 // Method java/lang/StringBuilder.toString:()Ljava/lang/String;
      39: areturn
}
