Compiled from "JSDocInfo.java"
final class com.google.javascript.rhino.JSDocInfo$LazilyInitializedInfo implements java.io.Serializable {
  private static final long serialVersionUID;

  com.google.javascript.rhino.JSTypeExpression baseType;

  java.util.List<com.google.javascript.rhino.JSTypeExpression> extendedInterfaces;

  java.util.List<com.google.javascript.rhino.JSTypeExpression> implementedInterfaces;

  java.util.Map<java.lang.String, com.google.javascript.rhino.JSTypeExpression> parameters;

  java.util.List<com.google.javascript.rhino.JSTypeExpression> thrownTypes;

  java.util.List<java.lang.String> templateTypeNames;

  java.util.Set<java.lang.String> disposedParameters;

  java.util.Map<java.lang.String, com.google.javascript.rhino.Node> typeTransformations;

  java.lang.String description;

  java.lang.String meaning;

  java.lang.String deprecated;

  java.lang.String license;

  java.util.Set<java.lang.String> suppressions;

  java.util.Set<java.lang.String> modifies;

  java.lang.String lendsName;

  private int propertyBitField;

  private com.google.javascript.rhino.JSDocInfo$LazilyInitializedInfo();
    Code:
       0: aload_0
       1: invokespecial #2                  // Method java/lang/Object."<init>":()V
       4: aload_0
       5: aconst_null
       6: putfield      #3                  // Field baseType:Lcom/google/javascript/rhino/JSTypeExpression;
       9: aload_0
      10: aconst_null
      11: putfield      #4                  // Field extendedInterfaces:Ljava/util/List;
      14: aload_0
      15: aconst_null
      16: putfield      #5                  // Field implementedInterfaces:Ljava/util/List;
      19: aload_0
      20: aconst_null
      21: putfield      #6                  // Field parameters:Ljava/util/Map;
      24: aload_0
      25: aconst_null
      26: putfield      #7                  // Field thrownTypes:Ljava/util/List;
      29: aload_0
      30: aconst_null
      31: putfield      #8                  // Field templateTypeNames:Ljava/util/List;
      34: aload_0
      35: aconst_null
      36: putfield      #9                  // Field disposedParameters:Ljava/util/Set;
      39: aload_0
      40: aconst_null
      41: putfield      #10                 // Field typeTransformations:Ljava/util/Map;
      44: aload_0
      45: aconst_null
      46: putfield      #11                 // Field description:Ljava/lang/String;
      49: aload_0
      50: aconst_null
      51: putfield      #12                 // Field meaning:Ljava/lang/String;
      54: aload_0
      55: aconst_null
      56: putfield      #13                 // Field deprecated:Ljava/lang/String;
      59: aload_0
      60: aconst_null
      61: putfield      #14                 // Field license:Ljava/lang/String;
      64: aload_0
      65: aconst_null
      66: putfield      #15                 // Field suppressions:Ljava/util/Set;
      69: aload_0
      70: aconst_null
      71: putfield      #16                 // Field modifies:Ljava/util/Set;
      74: aload_0
      75: aconst_null
      76: putfield      #17                 // Field lendsName:Ljava/lang/String;
      79: aload_0
      80: iconst_0
      81: putfield      #18                 // Field propertyBitField:I
      84: return

  public java.lang.String toString();
    Code:
       0: aload_0
       1: invokestatic  #19                 // Method com/google/common/base/MoreObjects.toStringHelper:(Ljava/lang/Object;)Lcom/google/common/base/MoreObjects$ToStringHelper;
       4: ldc           #20                 // String bitfield
       6: aload_0
       7: getfield      #18                 // Field propertyBitField:I
      10: ifne          17
      13: aconst_null
      14: goto          24
      17: aload_0
      18: getfield      #18                 // Field propertyBitField:I
      21: invokestatic  #21                 // Method java/lang/Integer.toHexString:(I)Ljava/lang/String;
      24: invokevirtual #22                 // Method com/google/common/base/MoreObjects$ToStringHelper.add:(Ljava/lang/String;Ljava/lang/Object;)Lcom/google/common/base/MoreObjects$ToStringHelper;
      27: ldc           #23                 // String baseType
      29: aload_0
      30: getfield      #3                  // Field baseType:Lcom/google/javascript/rhino/JSTypeExpression;
      33: invokevirtual #22                 // Method com/google/common/base/MoreObjects$ToStringHelper.add:(Ljava/lang/String;Ljava/lang/Object;)Lcom/google/common/base/MoreObjects$ToStringHelper;
      36: ldc           #24                 // String extendedInterfaces
      38: aload_0
      39: getfield      #4                  // Field extendedInterfaces:Ljava/util/List;
      42: invokevirtual #22                 // Method com/google/common/base/MoreObjects$ToStringHelper.add:(Ljava/lang/String;Ljava/lang/Object;)Lcom/google/common/base/MoreObjects$ToStringHelper;
      45: ldc           #25                 // String implementedInterfaces
      47: aload_0
      48: getfield      #5                  // Field implementedInterfaces:Ljava/util/List;
      51: invokevirtual #22                 // Method com/google/common/base/MoreObjects$ToStringHelper.add:(Ljava/lang/String;Ljava/lang/Object;)Lcom/google/common/base/MoreObjects$ToStringHelper;
      54: ldc           #26                 // String parameters
      56: aload_0
      57: getfield      #6                  // Field parameters:Ljava/util/Map;
      60: invokevirtual #22                 // Method com/google/common/base/MoreObjects$ToStringHelper.add:(Ljava/lang/String;Ljava/lang/Object;)Lcom/google/common/base/MoreObjects$ToStringHelper;
      63: ldc           #27                 // String thrownTypes
      65: aload_0
      66: getfield      #7                  // Field thrownTypes:Ljava/util/List;
      69: invokevirtual #22                 // Method com/google/common/base/MoreObjects$ToStringHelper.add:(Ljava/lang/String;Ljava/lang/Object;)Lcom/google/common/base/MoreObjects$ToStringHelper;
      72: ldc           #28                 // String templateTypeNames
      74: aload_0
      75: getfield      #8                  // Field templateTypeNames:Ljava/util/List;
      78: invokevirtual #22                 // Method com/google/common/base/MoreObjects$ToStringHelper.add:(Ljava/lang/String;Ljava/lang/Object;)Lcom/google/common/base/MoreObjects$ToStringHelper;
      81: ldc           #29                 // String disposedParameters
      83: aload_0
      84: getfield      #9                  // Field disposedParameters:Ljava/util/Set;
      87: invokevirtual #22                 // Method com/google/common/base/MoreObjects$ToStringHelper.add:(Ljava/lang/String;Ljava/lang/Object;)Lcom/google/common/base/MoreObjects$ToStringHelper;
      90: ldc           #30                 // String typeTransformations
      92: aload_0
      93: getfield      #10                 // Field typeTransformations:Ljava/util/Map;
      96: invokevirtual #22                 // Method com/google/common/base/MoreObjects$ToStringHelper.add:(Ljava/lang/String;Ljava/lang/Object;)Lcom/google/common/base/MoreObjects$ToStringHelper;
      99: ldc           #31                 // String description
     101: aload_0
     102: getfield      #11                 // Field description:Ljava/lang/String;
     105: invokevirtual #22                 // Method com/google/common/base/MoreObjects$ToStringHelper.add:(Ljava/lang/String;Ljava/lang/Object;)Lcom/google/common/base/MoreObjects$ToStringHelper;
     108: ldc           #32                 // String meaning
     110: aload_0
     111: getfield      #12                 // Field meaning:Ljava/lang/String;
     114: invokevirtual #22                 // Method com/google/common/base/MoreObjects$ToStringHelper.add:(Ljava/lang/String;Ljava/lang/Object;)Lcom/google/common/base/MoreObjects$ToStringHelper;
     117: ldc           #33                 // String deprecated
     119: aload_0
     120: getfield      #13                 // Field deprecated:Ljava/lang/String;
     123: invokevirtual #22                 // Method com/google/common/base/MoreObjects$ToStringHelper.add:(Ljava/lang/String;Ljava/lang/Object;)Lcom/google/common/base/MoreObjects$ToStringHelper;
     126: ldc           #34                 // String license
     128: aload_0
     129: getfield      #14                 // Field license:Ljava/lang/String;
     132: invokevirtual #22                 // Method com/google/common/base/MoreObjects$ToStringHelper.add:(Ljava/lang/String;Ljava/lang/Object;)Lcom/google/common/base/MoreObjects$ToStringHelper;
     135: ldc           #35                 // String suppressions
     137: aload_0
     138: getfield      #15                 // Field suppressions:Ljava/util/Set;
     141: invokevirtual #22                 // Method com/google/common/base/MoreObjects$ToStringHelper.add:(Ljava/lang/String;Ljava/lang/Object;)Lcom/google/common/base/MoreObjects$ToStringHelper;
     144: ldc           #36                 // String lendsName
     146: aload_0
     147: getfield      #17                 // Field lendsName:Ljava/lang/String;
     150: invokevirtual #22                 // Method com/google/common/base/MoreObjects$ToStringHelper.add:(Ljava/lang/String;Ljava/lang/Object;)Lcom/google/common/base/MoreObjects$ToStringHelper;
     153: invokevirtual #37                 // Method com/google/common/base/MoreObjects$ToStringHelper.omitNullValues:()Lcom/google/common/base/MoreObjects$ToStringHelper;
     156: invokevirtual #38                 // Method com/google/common/base/MoreObjects$ToStringHelper.toString:()Ljava/lang/String;
     159: areturn

  void setBit(int, boolean);
    Code:
       0: aload_0
       1: iload_1
       2: invokespecial #39                 // Method getMaskForBitIndex:(I)I
       5: istore_3
       6: iload_2
       7: ifeq          23
      10: aload_0
      11: dup
      12: getfield      #18                 // Field propertyBitField:I
      15: iload_3
      16: ior
      17: putfield      #18                 // Field propertyBitField:I
      20: goto          33
      23: aload_0
      24: dup
      25: getfield      #18                 // Field propertyBitField:I
      28: iload_3
      29: ixor
      30: putfield      #18                 // Field propertyBitField:I
      33: return

  boolean isBitSet(int);
    Code:
       0: aload_0
       1: iload_1
       2: invokespecial #39                 // Method getMaskForBitIndex:(I)I
       5: istore_2
       6: iload_2
       7: aload_0
       8: getfield      #18                 // Field propertyBitField:I
      11: iand
      12: ifeq          19
      15: iconst_1
      16: goto          20
      19: iconst_0
      20: ireturn

  private int getMaskForBitIndex(int);
    Code:
       0: iload_1
       1: iflt          8
       4: iconst_1
       5: goto          9
       8: iconst_0
       9: ldc           #40                 // String Bit index should be non-negative integer
      11: invokestatic  #41                 // Method com/google/common/base/Preconditions.checkArgument:(ZLjava/lang/Object;)V
      14: iconst_1
      15: iload_1
      16: ishl
      17: ireturn

  com.google.javascript.rhino.JSDocInfo$LazilyInitializedInfo(com.google.javascript.rhino.JSDocInfo$1);
    Code:
       0: aload_0
       1: invokespecial #1                  // Method "<init>":()V
       4: return
}
