Compiled from "JSDocInfo.java"
public final class com.google.javascript.rhino.JSDocInfo$Visibility extends java.lang.Enum<com.google.javascript.rhino.JSDocInfo$Visibility> {
  public static final com.google.javascript.rhino.JSDocInfo$Visibility PRIVATE;

  public static final com.google.javascript.rhino.JSDocInfo$Visibility PACKAGE;

  public static final com.google.javascript.rhino.JSDocInfo$Visibility PROTECTED;

  public static final com.google.javascript.rhino.JSDocInfo$Visibility PUBLIC;

  public static final com.google.javascript.rhino.JSDocInfo$Visibility INHERITED;

  private static final com.google.javascript.rhino.JSDocInfo$Visibility[] $VALUES;

  public static com.google.javascript.rhino.JSDocInfo$Visibility[] values();
    Code:
       0: getstatic     #1                  // Field $VALUES:[Lcom/google/javascript/rhino/JSDocInfo$Visibility;
       3: invokevirtual #2                  // Method "[Lcom/google/javascript/rhino/JSDocInfo$Visibility;".clone:()Ljava/lang/Object;
       6: checkcast     #3                  // class "[Lcom/google/javascript/rhino/JSDocInfo$Visibility;"
       9: areturn

  public static com.google.javascript.rhino.JSDocInfo$Visibility valueOf(java.lang.String);
    Code:
       0: ldc           #4                  // class com/google/javascript/rhino/JSDocInfo$Visibility
       2: aload_0
       3: invokestatic  #5                  // Method java/lang/Enum.valueOf:(Ljava/lang/Class;Ljava/lang/String;)Ljava/lang/Enum;
       6: checkcast     #4                  // class com/google/javascript/rhino/JSDocInfo$Visibility
       9: areturn

  private com.google.javascript.rhino.JSDocInfo$Visibility();
    Code:
       0: aload_0
       1: aload_1
       2: iload_2
       3: invokespecial #6                  // Method java/lang/Enum."<init>":(Ljava/lang/String;I)V
       6: return

  static {};
    Code:
       0: new           #4                  // class com/google/javascript/rhino/JSDocInfo$Visibility
       3: dup
       4: ldc           #7                  // String PRIVATE
       6: iconst_0
       7: invokespecial #8                  // Method "<init>":(Ljava/lang/String;I)V
      10: putstatic     #9                  // Field PRIVATE:Lcom/google/javascript/rhino/JSDocInfo$Visibility;
      13: new           #4                  // class com/google/javascript/rhino/JSDocInfo$Visibility
      16: dup
      17: ldc           #10                 // String PACKAGE
      19: iconst_1
      20: invokespecial #8                  // Method "<init>":(Ljava/lang/String;I)V
      23: putstatic     #11                 // Field PACKAGE:Lcom/google/javascript/rhino/JSDocInfo$Visibility;
      26: new           #4                  // class com/google/javascript/rhino/JSDocInfo$Visibility
      29: dup
      30: ldc           #12                 // String PROTECTED
      32: iconst_2
      33: invokespecial #8                  // Method "<init>":(Ljava/lang/String;I)V
      36: putstatic     #13                 // Field PROTECTED:Lcom/google/javascript/rhino/JSDocInfo$Visibility;
      39: new           #4                  // class com/google/javascript/rhino/JSDocInfo$Visibility
      42: dup
      43: ldc           #14                 // String PUBLIC
      45: iconst_3
      46: invokespecial #8                  // Method "<init>":(Ljava/lang/String;I)V
      49: putstatic     #15                 // Field PUBLIC:Lcom/google/javascript/rhino/JSDocInfo$Visibility;
      52: new           #4                  // class com/google/javascript/rhino/JSDocInfo$Visibility
      55: dup
      56: ldc           #16                 // String INHERITED
      58: iconst_4
      59: invokespecial #8                  // Method "<init>":(Ljava/lang/String;I)V
      62: putstatic     #17                 // Field INHERITED:Lcom/google/javascript/rhino/JSDocInfo$Visibility;
      65: iconst_5
      66: anewarray     #4                  // class com/google/javascript/rhino/JSDocInfo$Visibility
      69: dup
      70: iconst_0
      71: getstatic     #9                  // Field PRIVATE:Lcom/google/javascript/rhino/JSDocInfo$Visibility;
      74: aastore
      75: dup
      76: iconst_1
      77: getstatic     #11                 // Field PACKAGE:Lcom/google/javascript/rhino/JSDocInfo$Visibility;
      80: aastore
      81: dup
      82: iconst_2
      83: getstatic     #13                 // Field PROTECTED:Lcom/google/javascript/rhino/JSDocInfo$Visibility;
      86: aastore
      87: dup
      88: iconst_3
      89: getstatic     #15                 // Field PUBLIC:Lcom/google/javascript/rhino/JSDocInfo$Visibility;
      92: aastore
      93: dup
      94: iconst_4
      95: getstatic     #17                 // Field INHERITED:Lcom/google/javascript/rhino/JSDocInfo$Visibility;
      98: aastore
      99: putstatic     #1                  // Field $VALUES:[Lcom/google/javascript/rhino/JSDocInfo$Visibility;
     102: return
}
