Compiled from "BootstrapMode.java"
public final class org.springframework.data.repository.config.BootstrapMode extends java.lang.Enum<org.springframework.data.repository.config.BootstrapMode> {
  public static final org.springframework.data.repository.config.BootstrapMode DEFAULT;

  public static final org.springframework.data.repository.config.BootstrapMode DEFERRED;

  public static final org.springframework.data.repository.config.BootstrapMode LAZY;

  private static final org.springframework.data.repository.config.BootstrapMode[] $VALUES;

  public static org.springframework.data.repository.config.BootstrapMode[] values();
    Code:
       0: getstatic     #1                  // Field $VALUES:[Lorg/springframework/data/repository/config/BootstrapMode;
       3: invokevirtual #2                  // Method "[Lorg/springframework/data/repository/config/BootstrapMode;".clone:()Ljava/lang/Object;
       6: checkcast     #3                  // class "[Lorg/springframework/data/repository/config/BootstrapMode;"
       9: areturn

  public static org.springframework.data.repository.config.BootstrapMode valueOf(java.lang.String);
    Code:
       0: ldc           #4                  // class org/springframework/data/repository/config/BootstrapMode
       2: aload_0
       3: invokestatic  #5                  // Method java/lang/Enum.valueOf:(Ljava/lang/Class;Ljava/lang/String;)Ljava/lang/Enum;
       6: checkcast     #4                  // class org/springframework/data/repository/config/BootstrapMode
       9: areturn

  private org.springframework.data.repository.config.BootstrapMode();
    Code:
       0: aload_0
       1: aload_1
       2: iload_2
       3: invokespecial #6                  // Method java/lang/Enum."<init>":(Ljava/lang/String;I)V
       6: return

  static {};
    Code:
       0: new           #4                  // class org/springframework/data/repository/config/BootstrapMode
       3: dup
       4: ldc           #7                  // String DEFAULT
       6: iconst_0
       7: invokespecial #8                  // Method "<init>":(Ljava/lang/String;I)V
      10: putstatic     #9                  // Field DEFAULT:Lorg/springframework/data/repository/config/BootstrapMode;
      13: new           #4                  // class org/springframework/data/repository/config/BootstrapMode
      16: dup
      17: ldc           #10                 // String DEFERRED
      19: iconst_1
      20: invokespecial #8                  // Method "<init>":(Ljava/lang/String;I)V
      23: putstatic     #11                 // Field DEFERRED:Lorg/springframework/data/repository/config/BootstrapMode;
      26: new           #4                  // class org/springframework/data/repository/config/BootstrapMode
      29: dup
      30: ldc           #12                 // String LAZY
      32: iconst_2
      33: invokespecial #8                  // Method "<init>":(Ljava/lang/String;I)V
      36: putstatic     #13                 // Field LAZY:Lorg/springframework/data/repository/config/BootstrapMode;
      39: iconst_3
      40: anewarray     #4                  // class org/springframework/data/repository/config/BootstrapMode
      43: dup
      44: iconst_0
      45: getstatic     #9                  // Field DEFAULT:Lorg/springframework/data/repository/config/BootstrapMode;
      48: aastore
      49: dup
      50: iconst_1
      51: getstatic     #11                 // Field DEFERRED:Lorg/springframework/data/repository/config/BootstrapMode;
      54: aastore
      55: dup
      56: iconst_2
      57: getstatic     #13                 // Field LAZY:Lorg/springframework/data/repository/config/BootstrapMode;
      60: aastore
      61: putstatic     #1                  // Field $VALUES:[Lorg/springframework/data/repository/config/BootstrapMode;
      64: return
}
