Compiled from "MultipleFileTransferMonitor.java"
class com.amazonaws.services.s3.transfer.internal.MultipleFileTransferMonitor$1 implements java.util.concurrent.Future<java.lang.Object> {
  final com.amazonaws.services.s3.transfer.internal.MultipleFileTransferMonitor this$0;

  com.amazonaws.services.s3.transfer.internal.MultipleFileTransferMonitor$1(com.amazonaws.services.s3.transfer.internal.MultipleFileTransferMonitor);
    Code:
       0: aload_0
       1: aload_1
       2: putfield      #1                  // Field this$0:Lcom/amazonaws/services/s3/transfer/internal/MultipleFileTransferMonitor;
       5: aload_0
       6: invokespecial #2                  // Method java/lang/Object."<init>":()V
       9: return

  public boolean cancel(boolean);
    Code:
       0: iconst_1
       1: ireturn

  public java.lang.Object get() throws java.lang.InterruptedException, java.util.concurrent.ExecutionException;
    Code:
       0: aconst_null
       1: astore_1
       2: aload_0
       3: getfield      #1                  // Field this$0:Lcom/amazonaws/services/s3/transfer/internal/MultipleFileTransferMonitor;
       6: invokestatic  #3                  // Method com/amazonaws/services/s3/transfer/internal/MultipleFileTransferMonitor.access$000:(Lcom/amazonaws/services/s3/transfer/internal/MultipleFileTransferMonitor;)Ljava/util/Collection;
       9: invokeinterface #4,  1            // InterfaceMethod java/util/Collection.iterator:()Ljava/util/Iterator;
      14: astore_2
      15: aload_2
      16: invokeinterface #5,  1            // InterfaceMethod java/util/Iterator.hasNext:()Z
      21: ifeq          52
      24: aload_2
      25: invokeinterface #6,  1            // InterfaceMethod java/util/Iterator.next:()Ljava/lang/Object;
      30: checkcast     #7                  // class com/amazonaws/services/s3/transfer/internal/AbstractTransfer
      33: astore_3
      34: aload_3
      35: invokevirtual #8                  // Method com/amazonaws/services/s3/transfer/internal/AbstractTransfer.getMonitor:()Lcom/amazonaws/services/s3/transfer/internal/TransferMonitor;
      38: invokeinterface #9,  1            // InterfaceMethod com/amazonaws/services/s3/transfer/internal/TransferMonitor.getFuture:()Ljava/util/concurrent/Future;
      43: invokeinterface #10,  1           // InterfaceMethod java/util/concurrent/Future.get:()Ljava/lang/Object;
      48: astore_1
      49: goto          15
      52: aload_1
      53: areturn

  public java.lang.Object get(long, java.util.concurrent.TimeUnit) throws java.lang.InterruptedException, java.util.concurrent.ExecutionException, java.util.concurrent.TimeoutException;
    Code:
       0: aconst_null
       1: astore        4
       3: aload_0
       4: getfield      #1                  // Field this$0:Lcom/amazonaws/services/s3/transfer/internal/MultipleFileTransferMonitor;
       7: invokestatic  #3                  // Method com/amazonaws/services/s3/transfer/internal/MultipleFileTransferMonitor.access$000:(Lcom/amazonaws/services/s3/transfer/internal/MultipleFileTransferMonitor;)Ljava/util/Collection;
      10: invokeinterface #4,  1            // InterfaceMethod java/util/Collection.iterator:()Ljava/util/Iterator;
      15: astore        5
      17: aload         5
      19: invokeinterface #5,  1            // InterfaceMethod java/util/Iterator.hasNext:()Z
      24: ifeq          61
      27: aload         5
      29: invokeinterface #6,  1            // InterfaceMethod java/util/Iterator.next:()Ljava/lang/Object;
      34: checkcast     #7                  // class com/amazonaws/services/s3/transfer/internal/AbstractTransfer
      37: astore        6
      39: aload         6
      41: invokevirtual #8                  // Method com/amazonaws/services/s3/transfer/internal/AbstractTransfer.getMonitor:()Lcom/amazonaws/services/s3/transfer/internal/TransferMonitor;
      44: invokeinterface #9,  1            // InterfaceMethod com/amazonaws/services/s3/transfer/internal/TransferMonitor.getFuture:()Ljava/util/concurrent/Future;
      49: lload_1
      50: aload_3
      51: invokeinterface #11,  4           // InterfaceMethod java/util/concurrent/Future.get:(JLjava/util/concurrent/TimeUnit;)Ljava/lang/Object;
      56: astore        4
      58: goto          17
      61: aload         4
      63: areturn

  public boolean isCancelled();
    Code:
       0: aload_0
       1: getfield      #1                  // Field this$0:Lcom/amazonaws/services/s3/transfer/internal/MultipleFileTransferMonitor;
       4: invokestatic  #12                 // Method com/amazonaws/services/s3/transfer/internal/MultipleFileTransferMonitor.access$100:(Lcom/amazonaws/services/s3/transfer/internal/MultipleFileTransferMonitor;)Lcom/amazonaws/services/s3/transfer/internal/AbstractTransfer;
       7: invokevirtual #13                 // Method com/amazonaws/services/s3/transfer/internal/AbstractTransfer.getState:()Lcom/amazonaws/services/s3/transfer/Transfer$TransferState;
      10: getstatic     #14                 // Field com/amazonaws/services/s3/transfer/Transfer$TransferState.Canceled:Lcom/amazonaws/services/s3/transfer/Transfer$TransferState;
      13: if_acmpne     20
      16: iconst_1
      17: goto          21
      20: iconst_0
      21: ireturn

  public boolean isDone();
    Code:
       0: aload_0
       1: getfield      #1                  // Field this$0:Lcom/amazonaws/services/s3/transfer/internal/MultipleFileTransferMonitor;
       4: invokevirtual #15                 // Method com/amazonaws/services/s3/transfer/internal/MultipleFileTransferMonitor.isDone:()Z
       7: ireturn
}
