Compiled from "OAuth2SsoProperties.java"
public class org.springframework.boot.autoconfigure.security.oauth2.client.OAuth2SsoProperties {
  public static final java.lang.String DEFAULT_LOGIN_PATH;

  private java.lang.String loginPath;

  private java.lang.Integer filterOrder;

  public org.springframework.boot.autoconfigure.security.oauth2.client.OAuth2SsoProperties();
    Code:
       0: aload_0
       1: invokespecial #1                  // Method java/lang/Object."<init>":()V
       4: aload_0
       5: ldc           #3                  // String /login
       7: putfield      #4                  // Field loginPath:Ljava/lang/String;
      10: return

  public java.lang.String getLoginPath();
    Code:
       0: aload_0
       1: getfield      #4                  // Field loginPath:Ljava/lang/String;
       4: areturn

  public void setLoginPath(java.lang.String);
    Code:
       0: aload_0
       1: aload_1
       2: putfield      #4                  // Field loginPath:Ljava/lang/String;
       5: return

  public java.lang.Integer getFilterOrder();
    Code:
       0: aload_0
       1: getfield      #5                  // Field filterOrder:Ljava/lang/Integer;
       4: areturn

  public void setFilterOrder(java.lang.Integer);
    Code:
       0: aload_0
       1: aload_1
       2: putfield      #5                  // Field filterOrder:Ljava/lang/Integer;
       5: return
}
