Compiled from "LinearGradient.java"
class javafx.scene.paint.LinearGradient$1 {
  static final int[] $SwitchMap$javafx$scene$paint$CycleMethod;

  static {};
    Code:
       0: invokestatic  #1                  // Method javafx/scene/paint/CycleMethod.values:()[Ljavafx/scene/paint/CycleMethod;
       3: arraylength
       4: newarray       int
       6: putstatic     #2                  // Field $SwitchMap$javafx$scene$paint$CycleMethod:[I
       9: getstatic     #2                  // Field $SwitchMap$javafx$scene$paint$CycleMethod:[I
      12: getstatic     #3                  // Field javafx/scene/paint/CycleMethod.REFLECT:Ljavafx/scene/paint/CycleMethod;
      15: invokevirtual #4                  // Method javafx/scene/paint/CycleMethod.ordinal:()I
      18: iconst_1
      19: iastore
      20: goto          24
      23: astore_0
      24: getstatic     #2                  // Field $SwitchMap$javafx$scene$paint$CycleMethod:[I
      27: getstatic     #6                  // Field javafx/scene/paint/CycleMethod.REPEAT:Ljavafx/scene/paint/CycleMethod;
      30: invokevirtual #4                  // Method javafx/scene/paint/CycleMethod.ordinal:()I
      33: iconst_2
      34: iastore
      35: goto          39
      38: astore_0
      39: return
    Exception table:
       from    to  target type
           9    20    23   Class java/lang/NoSuchFieldError
          24    35    38   Class java/lang/NoSuchFieldError
}
