Compiled from "Paint.java"
public abstract class javafx.scene.paint.Paint {
  javafx.scene.paint.Paint();
    Code:
       0: aload_0
       1: invokespecial #1                  // Method java/lang/Object."<init>":()V
       4: return

  boolean acc_isMutable();
    Code:
       0: iconst_0
       1: ireturn

  abstract java.lang.Object acc_getPlatformPaint();

  void acc_addListener(com.sun.javafx.beans.event.AbstractNotifyListener);
    Code:
       0: new           #2                  // class java/lang/UnsupportedOperationException
       3: dup
       4: ldc           #3                  // String Not Supported.
       6: invokespecial #4                  // Method java/lang/UnsupportedOperationException."<init>":(Ljava/lang/String;)V
       9: athrow

  void acc_removeListener(com.sun.javafx.beans.event.AbstractNotifyListener);
    Code:
       0: new           #2                  // class java/lang/UnsupportedOperationException
       3: dup
       4: ldc           #3                  // String Not Supported.
       6: invokespecial #4                  // Method java/lang/UnsupportedOperationException."<init>":(Ljava/lang/String;)V
       9: athrow

  public abstract boolean isOpaque();

  public static javafx.scene.paint.Paint valueOf(java.lang.String);
    Code:
       0: aload_0
       1: ifnonnull     14
       4: new           #5                  // class java/lang/NullPointerException
       7: dup
       8: ldc           #6                  // String paint must be specified
      10: invokespecial #7                  // Method java/lang/NullPointerException."<init>":(Ljava/lang/String;)V
      13: athrow
      14: aload_0
      15: ldc           #8                  // String linear-gradient(
      17: invokevirtual #9                  // Method java/lang/String.startsWith:(Ljava/lang/String;)Z
      20: ifeq          28
      23: aload_0
      24: invokestatic  #10                 // Method javafx/scene/paint/LinearGradient.valueOf:(Ljava/lang/String;)Ljavafx/scene/paint/LinearGradient;
      27: areturn
      28: aload_0
      29: ldc           #11                 // String radial-gradient(
      31: invokevirtual #9                  // Method java/lang/String.startsWith:(Ljava/lang/String;)Z
      34: ifeq          42
      37: aload_0
      38: invokestatic  #12                 // Method javafx/scene/paint/RadialGradient.valueOf:(Ljava/lang/String;)Ljavafx/scene/paint/RadialGradient;
      41: areturn
      42: aload_0
      43: invokestatic  #13                 // Method javafx/scene/paint/Color.valueOf:(Ljava/lang/String;)Ljavafx/scene/paint/Color;
      46: areturn

  static {};
    Code:
       0: new           #14                 // class javafx/scene/paint/Paint$1
       3: dup
       4: invokespecial #15                 // Method javafx/scene/paint/Paint$1."<init>":()V
       7: invokestatic  #16                 // Method com/sun/javafx/tk/Toolkit.setPaintAccessor:(Lcom/sun/javafx/tk/Toolkit$PaintAccessor;)V
      10: return
}
