Compiled from "BaseExpression.java"
public abstract class org.apache.hadoop.fs.shell.find.BaseExpression implements org.apache.hadoop.fs.shell.find.Expression,org.apache.hadoop.conf.Configurable {
  private java.lang.String[] usage;

  private java.lang.String[] help;

  private org.apache.hadoop.fs.shell.find.FindOptions options;

  private org.apache.hadoop.conf.Configuration conf;

  private java.util.LinkedList<java.lang.String> arguments;

  private java.util.LinkedList<org.apache.hadoop.fs.shell.find.Expression> children;

  public org.apache.hadoop.fs.shell.find.BaseExpression();
    Code:
       0: aload_0
       1: invokespecial #1                  // Method java/lang/Object."<init>":()V
       4: aload_0
       5: iconst_1
       6: anewarray     #2                  // class java/lang/String
       9: dup
      10: iconst_0
      11: ldc           #3                  // String Not yet implemented
      13: aastore
      14: putfield      #4                  // Field usage:[Ljava/lang/String;
      17: aload_0
      18: iconst_1
      19: anewarray     #2                  // class java/lang/String
      22: dup
      23: iconst_0
      24: ldc           #3                  // String Not yet implemented
      26: aastore
      27: putfield      #5                  // Field help:[Ljava/lang/String;
      30: aload_0
      31: new           #6                  // class java/util/LinkedList
      34: dup
      35: invokespecial #7                  // Method java/util/LinkedList."<init>":()V
      38: putfield      #8                  // Field arguments:Ljava/util/LinkedList;
      41: aload_0
      42: new           #6                  // class java/util/LinkedList
      45: dup
      46: invokespecial #7                  // Method java/util/LinkedList."<init>":()V
      49: putfield      #9                  // Field children:Ljava/util/LinkedList;
      52: return

  protected void setUsage(java.lang.String[]);
    Code:
       0: aload_0
       1: aload_1
       2: putfield      #4                  // Field usage:[Ljava/lang/String;
       5: return

  protected void setHelp(java.lang.String[]);
    Code:
       0: aload_0
       1: aload_1
       2: putfield      #5                  // Field help:[Ljava/lang/String;
       5: return

  public java.lang.String[] getUsage();
    Code:
       0: aload_0
       1: getfield      #4                  // Field usage:[Ljava/lang/String;
       4: areturn

  public java.lang.String[] getHelp();
    Code:
       0: aload_0
       1: getfield      #5                  // Field help:[Ljava/lang/String;
       4: areturn

  public void setOptions(org.apache.hadoop.fs.shell.find.FindOptions) throws java.io.IOException;
    Code:
       0: aload_0
       1: aload_1
       2: putfield      #10                 // Field options:Lorg/apache/hadoop/fs/shell/find/FindOptions;
       5: aload_0
       6: invokevirtual #11                 // Method getChildren:()Ljava/util/List;
       9: invokeinterface #12,  1           // InterfaceMethod java/util/List.iterator:()Ljava/util/Iterator;
      14: astore_2
      15: aload_2
      16: invokeinterface #13,  1           // InterfaceMethod java/util/Iterator.hasNext:()Z
      21: ifeq          44
      24: aload_2
      25: invokeinterface #14,  1           // InterfaceMethod java/util/Iterator.next:()Ljava/lang/Object;
      30: checkcast     #15                 // class org/apache/hadoop/fs/shell/find/Expression
      33: astore_3
      34: aload_3
      35: aload_1
      36: invokeinterface #16,  2           // InterfaceMethod org/apache/hadoop/fs/shell/find/Expression.setOptions:(Lorg/apache/hadoop/fs/shell/find/FindOptions;)V
      41: goto          15
      44: return

  public void prepare() throws java.io.IOException;
    Code:
       0: aload_0
       1: invokevirtual #11                 // Method getChildren:()Ljava/util/List;
       4: invokeinterface #12,  1           // InterfaceMethod java/util/List.iterator:()Ljava/util/Iterator;
       9: astore_1
      10: aload_1
      11: invokeinterface #13,  1           // InterfaceMethod java/util/Iterator.hasNext:()Z
      16: ifeq          38
      19: aload_1
      20: invokeinterface #14,  1           // InterfaceMethod java/util/Iterator.next:()Ljava/lang/Object;
      25: checkcast     #15                 // class org/apache/hadoop/fs/shell/find/Expression
      28: astore_2
      29: aload_2
      30: invokeinterface #17,  1           // InterfaceMethod org/apache/hadoop/fs/shell/find/Expression.prepare:()V
      35: goto          10
      38: return

  public void finish() throws java.io.IOException;
    Code:
       0: aload_0
       1: invokevirtual #11                 // Method getChildren:()Ljava/util/List;
       4: invokeinterface #12,  1           // InterfaceMethod java/util/List.iterator:()Ljava/util/Iterator;
       9: astore_1
      10: aload_1
      11: invokeinterface #13,  1           // InterfaceMethod java/util/Iterator.hasNext:()Z
      16: ifeq          38
      19: aload_1
      20: invokeinterface #14,  1           // InterfaceMethod java/util/Iterator.next:()Ljava/lang/Object;
      25: checkcast     #15                 // class org/apache/hadoop/fs/shell/find/Expression
      28: astore_2
      29: aload_2
      30: invokeinterface #18,  1           // InterfaceMethod org/apache/hadoop/fs/shell/find/Expression.finish:()V
      35: goto          10
      38: return

  protected org.apache.hadoop.fs.shell.find.FindOptions getOptions();
    Code:
       0: aload_0
       1: getfield      #10                 // Field options:Lorg/apache/hadoop/fs/shell/find/FindOptions;
       4: ifnonnull     17
       7: new           #19                 // class org/apache/hadoop/fs/shell/find/FindOptions
      10: dup
      11: invokespecial #20                 // Method org/apache/hadoop/fs/shell/find/FindOptions."<init>":()V
      14: goto          21
      17: aload_0
      18: getfield      #10                 // Field options:Lorg/apache/hadoop/fs/shell/find/FindOptions;
      21: areturn

  public void setConf(org.apache.hadoop.conf.Configuration);
    Code:
       0: aload_0
       1: aload_1
       2: putfield      #21                 // Field conf:Lorg/apache/hadoop/conf/Configuration;
       5: return

  public org.apache.hadoop.conf.Configuration getConf();
    Code:
       0: aload_0
       1: getfield      #21                 // Field conf:Lorg/apache/hadoop/conf/Configuration;
       4: areturn

  public java.lang.String toString();
    Code:
       0: new           #22                 // class java/lang/StringBuilder
       3: dup
       4: invokespecial #23                 // Method java/lang/StringBuilder."<init>":()V
       7: astore_1
       8: aload_1
       9: aload_0
      10: invokevirtual #24                 // Method java/lang/Object.getClass:()Ljava/lang/Class;
      13: invokevirtual #25                 // Method java/lang/Class.getSimpleName:()Ljava/lang/String;
      16: invokevirtual #26                 // Method java/lang/StringBuilder.append:(Ljava/lang/String;)Ljava/lang/StringBuilder;
      19: pop
      20: aload_1
      21: ldc           #27                 // String (
      23: invokevirtual #26                 // Method java/lang/StringBuilder.append:(Ljava/lang/String;)Ljava/lang/StringBuilder;
      26: pop
      27: iconst_1
      28: istore_2
      29: aload_0
      30: invokevirtual #28                 // Method getArguments:()Ljava/util/List;
      33: invokeinterface #12,  1           // InterfaceMethod java/util/List.iterator:()Ljava/util/Iterator;
      38: astore_3
      39: aload_3
      40: invokeinterface #13,  1           // InterfaceMethod java/util/Iterator.hasNext:()Z
      45: ifeq          85
      48: aload_3
      49: invokeinterface #14,  1           // InterfaceMethod java/util/Iterator.next:()Ljava/lang/Object;
      54: checkcast     #2                  // class java/lang/String
      57: astore        4
      59: iload_2
      60: ifne          73
      63: aload_1
      64: ldc           #29                 // String ,
      66: invokevirtual #26                 // Method java/lang/StringBuilder.append:(Ljava/lang/String;)Ljava/lang/StringBuilder;
      69: pop
      70: goto          75
      73: iconst_0
      74: istore_2
      75: aload_1
      76: aload         4
      78: invokevirtual #26                 // Method java/lang/StringBuilder.append:(Ljava/lang/String;)Ljava/lang/StringBuilder;
      81: pop
      82: goto          39
      85: aload_1
      86: ldc           #30                 // String ;
      88: invokevirtual #26                 // Method java/lang/StringBuilder.append:(Ljava/lang/String;)Ljava/lang/StringBuilder;
      91: pop
      92: iconst_1
      93: istore_2
      94: aload_0
      95: invokevirtual #11                 // Method getChildren:()Ljava/util/List;
      98: invokeinterface #12,  1           // InterfaceMethod java/util/List.iterator:()Ljava/util/Iterator;
     103: astore_3
     104: aload_3
     105: invokeinterface #13,  1           // InterfaceMethod java/util/Iterator.hasNext:()Z
     110: ifeq          153
     113: aload_3
     114: invokeinterface #14,  1           // InterfaceMethod java/util/Iterator.next:()Ljava/lang/Object;
     119: checkcast     #15                 // class org/apache/hadoop/fs/shell/find/Expression
     122: astore        4
     124: iload_2
     125: ifne          138
     128: aload_1
     129: ldc           #29                 // String ,
     131: invokevirtual #26                 // Method java/lang/StringBuilder.append:(Ljava/lang/String;)Ljava/lang/StringBuilder;
     134: pop
     135: goto          140
     138: iconst_0
     139: istore_2
     140: aload_1
     141: aload         4
     143: invokevirtual #31                 // Method java/lang/Object.toString:()Ljava/lang/String;
     146: invokevirtual #26                 // Method java/lang/StringBuilder.append:(Ljava/lang/String;)Ljava/lang/StringBuilder;
     149: pop
     150: goto          104
     153: aload_1
     154: ldc           #32                 // String )
     156: invokevirtual #26                 // Method java/lang/StringBuilder.append:(Ljava/lang/String;)Ljava/lang/StringBuilder;
     159: pop
     160: aload_1
     161: invokevirtual #33                 // Method java/lang/StringBuilder.toString:()Ljava/lang/String;
     164: areturn

  public boolean isAction();
    Code:
       0: aload_0
       1: invokevirtual #11                 // Method getChildren:()Ljava/util/List;
       4: invokeinterface #12,  1           // InterfaceMethod java/util/List.iterator:()Ljava/util/Iterator;
       9: astore_1
      10: aload_1
      11: invokeinterface #13,  1           // InterfaceMethod java/util/Iterator.hasNext:()Z
      16: ifeq          43
      19: aload_1
      20: invokeinterface #14,  1           // InterfaceMethod java/util/Iterator.next:()Ljava/lang/Object;
      25: checkcast     #15                 // class org/apache/hadoop/fs/shell/find/Expression
      28: astore_2
      29: aload_2
      30: invokeinterface #34,  1           // InterfaceMethod org/apache/hadoop/fs/shell/find/Expression.isAction:()Z
      35: ifeq          40
      38: iconst_1
      39: ireturn
      40: goto          10
      43: iconst_0
      44: ireturn

  public boolean isOperator();
    Code:
       0: iconst_0
       1: ireturn

  protected java.util.List<java.lang.String> getArguments();
    Code:
       0: aload_0
       1: getfield      #8                  // Field arguments:Ljava/util/LinkedList;
       4: areturn

  protected java.lang.String getArgument(int) throws java.io.IOException;
    Code:
       0: iload_1
       1: aload_0
       2: getfield      #8                  // Field arguments:Ljava/util/LinkedList;
       5: invokevirtual #35                 // Method java/util/LinkedList.size:()I
       8: if_icmple     38
      11: new           #36                 // class java/io/IOException
      14: dup
      15: new           #22                 // class java/lang/StringBuilder
      18: dup
      19: invokespecial #23                 // Method java/lang/StringBuilder."<init>":()V
      22: ldc           #37                 // String Missing argument at
      24: invokevirtual #26                 // Method java/lang/StringBuilder.append:(Ljava/lang/String;)Ljava/lang/StringBuilder;
      27: iload_1
      28: invokevirtual #38                 // Method java/lang/StringBuilder.append:(I)Ljava/lang/StringBuilder;
      31: invokevirtual #33                 // Method java/lang/StringBuilder.toString:()Ljava/lang/String;
      34: invokespecial #39                 // Method java/io/IOException."<init>":(Ljava/lang/String;)V
      37: athrow
      38: aload_0
      39: getfield      #8                  // Field arguments:Ljava/util/LinkedList;
      42: iload_1
      43: iconst_1
      44: isub
      45: invokevirtual #40                 // Method java/util/LinkedList.get:(I)Ljava/lang/Object;
      48: checkcast     #2                  // class java/lang/String
      51: astore_2
      52: aload_2
      53: ifnonnull     83
      56: new           #36                 // class java/io/IOException
      59: dup
      60: new           #22                 // class java/lang/StringBuilder
      63: dup
      64: invokespecial #23                 // Method java/lang/StringBuilder."<init>":()V
      67: ldc           #41                 // String Null argument at position
      69: invokevirtual #26                 // Method java/lang/StringBuilder.append:(Ljava/lang/String;)Ljava/lang/StringBuilder;
      72: iload_1
      73: invokevirtual #38                 // Method java/lang/StringBuilder.append:(I)Ljava/lang/StringBuilder;
      76: invokevirtual #33                 // Method java/lang/StringBuilder.toString:()Ljava/lang/String;
      79: invokespecial #39                 // Method java/io/IOException."<init>":(Ljava/lang/String;)V
      82: athrow
      83: aload_2
      84: areturn

  protected java.util.List<org.apache.hadoop.fs.shell.find.Expression> getChildren();
    Code:
       0: aload_0
       1: getfield      #9                  // Field children:Ljava/util/LinkedList;
       4: areturn

  public int getPrecedence();
    Code:
       0: iconst_0
       1: ireturn

  public void addChildren(java.util.Deque<org.apache.hadoop.fs.shell.find.Expression>);
    Code:
       0: return

  protected void addChildren(java.util.Deque<org.apache.hadoop.fs.shell.find.Expression>, int);
    Code:
       0: iconst_0
       1: istore_3
       2: iload_3
       3: iload_2
       4: if_icmpge     26
       7: aload_0
       8: aload_1
       9: invokeinterface #42,  1           // InterfaceMethod java/util/Deque.pop:()Ljava/lang/Object;
      14: checkcast     #15                 // class org/apache/hadoop/fs/shell/find/Expression
      17: invokespecial #43                 // Method addChild:(Lorg/apache/hadoop/fs/shell/find/Expression;)V
      20: iinc          3, 1
      23: goto          2
      26: return

  private void addChild(org.apache.hadoop.fs.shell.find.Expression);
    Code:
       0: aload_0
       1: getfield      #9                  // Field children:Ljava/util/LinkedList;
       4: aload_1
       5: invokevirtual #44                 // Method java/util/LinkedList.push:(Ljava/lang/Object;)V
       8: return

  public void addArguments(java.util.Deque<java.lang.String>);
    Code:
       0: return

  protected void addArguments(java.util.Deque<java.lang.String>, int);
    Code:
       0: iconst_0
       1: istore_3
       2: iload_3
       3: iload_2
       4: if_icmpge     26
       7: aload_0
       8: aload_1
       9: invokeinterface #42,  1           // InterfaceMethod java/util/Deque.pop:()Ljava/lang/Object;
      14: checkcast     #2                  // class java/lang/String
      17: invokevirtual #45                 // Method addArgument:(Ljava/lang/String;)V
      20: iinc          3, 1
      23: goto          2
      26: return

  protected void addArgument(java.lang.String);
    Code:
       0: aload_0
       1: getfield      #8                  // Field arguments:Ljava/util/LinkedList;
       4: aload_1
       5: invokevirtual #46                 // Method java/util/LinkedList.add:(Ljava/lang/Object;)Z
       8: pop
       9: return

  protected org.apache.hadoop.fs.FileStatus getFileStatus(org.apache.hadoop.fs.shell.PathData, int) throws java.io.IOException;
    Code:
       0: aload_1
       1: getfield      #47                 // Field org/apache/hadoop/fs/shell/PathData.stat:Lorg/apache/hadoop/fs/FileStatus;
       4: astore_3
       5: aload_3
       6: invokevirtual #48                 // Method org/apache/hadoop/fs/FileStatus.isSymlink:()Z
       9: ifeq          60
      12: aload_0
      13: getfield      #10                 // Field options:Lorg/apache/hadoop/fs/shell/find/FindOptions;
      16: invokevirtual #49                 // Method org/apache/hadoop/fs/shell/find/FindOptions.isFollowLink:()Z
      19: ifne          36
      22: aload_0
      23: getfield      #10                 // Field options:Lorg/apache/hadoop/fs/shell/find/FindOptions;
      26: invokevirtual #50                 // Method org/apache/hadoop/fs/shell/find/FindOptions.isFollowArgLink:()Z
      29: ifeq          60
      32: iload_2
      33: ifne          60
      36: aload_1
      37: getfield      #51                 // Field org/apache/hadoop/fs/shell/PathData.fs:Lorg/apache/hadoop/fs/FileSystem;
      40: aload_3
      41: invokevirtual #52                 // Method org/apache/hadoop/fs/FileStatus.getSymlink:()Lorg/apache/hadoop/fs/Path;
      44: invokevirtual #53                 // Method org/apache/hadoop/fs/FileSystem.resolvePath:(Lorg/apache/hadoop/fs/Path;)Lorg/apache/hadoop/fs/Path;
      47: astore        4
      49: aload_0
      50: aload_1
      51: invokevirtual #54                 // Method getFileSystem:(Lorg/apache/hadoop/fs/shell/PathData;)Lorg/apache/hadoop/fs/FileSystem;
      54: aload         4
      56: invokevirtual #55                 // Method org/apache/hadoop/fs/FileSystem.getFileStatus:(Lorg/apache/hadoop/fs/Path;)Lorg/apache/hadoop/fs/FileStatus;
      59: astore_3
      60: aload_3
      61: areturn

  protected org.apache.hadoop.fs.Path getPath(org.apache.hadoop.fs.shell.PathData) throws java.io.IOException;
    Code:
       0: aload_1
       1: getfield      #56                 // Field org/apache/hadoop/fs/shell/PathData.path:Lorg/apache/hadoop/fs/Path;
       4: areturn

  protected org.apache.hadoop.fs.FileSystem getFileSystem(org.apache.hadoop.fs.shell.PathData) throws java.io.IOException;
    Code:
       0: aload_1
       1: getfield      #51                 // Field org/apache/hadoop/fs/shell/PathData.fs:Lorg/apache/hadoop/fs/FileSystem;
       4: areturn
}
