Compiled from "Print.java"
final class org.apache.hadoop.fs.shell.find.Print extends org.apache.hadoop.fs.shell.find.BaseExpression {
  private static final java.lang.String[] USAGE;

  private static final java.lang.String[] HELP;

  private final java.lang.String suffix;

  public static void registerExpression(org.apache.hadoop.fs.shell.find.ExpressionFactory) throws java.io.IOException;
    Code:
       0: aload_0
       1: ldc           #2                  // class org/apache/hadoop/fs/shell/find/Print
       3: iconst_1
       4: anewarray     #3                  // class java/lang/String
       7: dup
       8: iconst_0
       9: ldc           #4                  // String -print
      11: aastore
      12: invokevirtual #5                  // Method org/apache/hadoop/fs/shell/find/ExpressionFactory.addClass:(Ljava/lang/Class;[Ljava/lang/String;)V
      15: aload_0
      16: ldc           #6                  // class org/apache/hadoop/fs/shell/find/Print$Print0
      18: iconst_1
      19: anewarray     #3                  // class java/lang/String
      22: dup
      23: iconst_0
      24: ldc           #7                  // String -print0
      26: aastore
      27: invokevirtual #5                  // Method org/apache/hadoop/fs/shell/find/ExpressionFactory.addClass:(Ljava/lang/Class;[Ljava/lang/String;)V
      30: return

  public org.apache.hadoop.fs.shell.find.Print();
    Code:
       0: aload_0
       1: ldc           #8                  // String \n
       3: invokespecial #1                  // Method "<init>":(Ljava/lang/String;)V
       6: return

  private org.apache.hadoop.fs.shell.find.Print(java.lang.String);
    Code:
       0: aload_0
       1: invokespecial #9                  // Method org/apache/hadoop/fs/shell/find/BaseExpression."<init>":()V
       4: aload_0
       5: getstatic     #10                 // Field USAGE:[Ljava/lang/String;
       8: invokevirtual #11                 // Method setUsage:([Ljava/lang/String;)V
      11: aload_0
      12: getstatic     #12                 // Field HELP:[Ljava/lang/String;
      15: invokevirtual #13                 // Method setHelp:([Ljava/lang/String;)V
      18: aload_0
      19: aload_1
      20: putfield      #14                 // Field suffix:Ljava/lang/String;
      23: return

  public org.apache.hadoop.fs.shell.find.Result apply(org.apache.hadoop.fs.shell.PathData, int) throws java.io.IOException;
    Code:
       0: aload_0
       1: invokevirtual #15                 // Method getOptions:()Lorg/apache/hadoop/fs/shell/find/FindOptions;
       4: invokevirtual #16                 // Method org/apache/hadoop/fs/shell/find/FindOptions.getOut:()Ljava/io/PrintStream;
       7: new           #17                 // class java/lang/StringBuilder
      10: dup
      11: invokespecial #18                 // Method java/lang/StringBuilder."<init>":()V
      14: aload_1
      15: invokevirtual #19                 // Method org/apache/hadoop/fs/shell/PathData.toString:()Ljava/lang/String;
      18: invokevirtual #20                 // Method java/lang/StringBuilder.append:(Ljava/lang/String;)Ljava/lang/StringBuilder;
      21: aload_0
      22: getfield      #14                 // Field suffix:Ljava/lang/String;
      25: invokevirtual #20                 // Method java/lang/StringBuilder.append:(Ljava/lang/String;)Ljava/lang/StringBuilder;
      28: invokevirtual #21                 // Method java/lang/StringBuilder.toString:()Ljava/lang/String;
      31: invokevirtual #22                 // Method java/io/PrintStream.print:(Ljava/lang/String;)V
      34: getstatic     #23                 // Field org/apache/hadoop/fs/shell/find/Result.PASS:Lorg/apache/hadoop/fs/shell/find/Result;
      37: areturn

  public boolean isAction();
    Code:
       0: iconst_1
       1: ireturn

  org.apache.hadoop.fs.shell.find.Print(java.lang.String, org.apache.hadoop.fs.shell.find.Print$1);
    Code:
       0: aload_0
       1: aload_1
       2: invokespecial #1                  // Method "<init>":(Ljava/lang/String;)V
       5: return

  static {};
    Code:
       0: iconst_2
       1: anewarray     #3                  // class java/lang/String
       4: dup
       5: iconst_0
       6: ldc           #4                  // String -print
       8: aastore
       9: dup
      10: iconst_1
      11: ldc           #7                  // String -print0
      13: aastore
      14: putstatic     #10                 // Field USAGE:[Ljava/lang/String;
      17: iconst_4
      18: anewarray     #3                  // class java/lang/String
      21: dup
      22: iconst_0
      23: ldc           #24                 // String Always evaluates to true. Causes the current pathname to be
      25: aastore
      26: dup
      27: iconst_1
      28: ldc           #25                 // String written to standard output followed by a newline. If the -print0
      30: aastore
      31: dup
      32: iconst_2
      33: ldc           #26                 // String expression is used then an ASCII NULL character is appended rather
      35: aastore
      36: dup
      37: iconst_3
      38: ldc           #27                 // String than a newline.
      40: aastore
      41: putstatic     #12                 // Field HELP:[Ljava/lang/String;
      44: return
}
