Compiled from "Contracts.java"
public class org.apache.hadoop.metrics2.util.Contracts {
  private org.apache.hadoop.metrics2.util.Contracts();
    Code:
       0: aload_0
       1: invokespecial #1                  // Method java/lang/Object."<init>":()V
       4: return

  public static <T> T checkArg(T, boolean, java.lang.Object);
    Code:
       0: iload_1
       1: ifne          38
       4: new           #2                  // class java/lang/IllegalArgumentException
       7: dup
       8: new           #3                  // class java/lang/StringBuilder
      11: dup
      12: invokespecial #4                  // Method java/lang/StringBuilder."<init>":()V
      15: aload_2
      16: invokestatic  #5                  // Method java/lang/String.valueOf:(Ljava/lang/Object;)Ljava/lang/String;
      19: invokevirtual #6                  // Method java/lang/StringBuilder.append:(Ljava/lang/String;)Ljava/lang/StringBuilder;
      22: ldc           #7                  // String :
      24: invokevirtual #6                  // Method java/lang/StringBuilder.append:(Ljava/lang/String;)Ljava/lang/StringBuilder;
      27: aload_0
      28: invokevirtual #8                  // Method java/lang/StringBuilder.append:(Ljava/lang/Object;)Ljava/lang/StringBuilder;
      31: invokevirtual #9                  // Method java/lang/StringBuilder.toString:()Ljava/lang/String;
      34: invokespecial #10                 // Method java/lang/IllegalArgumentException."<init>":(Ljava/lang/String;)V
      37: athrow
      38: aload_0
      39: areturn

  public static int checkArg(int, boolean, java.lang.Object);
    Code:
       0: iload_1
       1: ifne          38
       4: new           #2                  // class java/lang/IllegalArgumentException
       7: dup
       8: new           #3                  // class java/lang/StringBuilder
      11: dup
      12: invokespecial #4                  // Method java/lang/StringBuilder."<init>":()V
      15: aload_2
      16: invokestatic  #5                  // Method java/lang/String.valueOf:(Ljava/lang/Object;)Ljava/lang/String;
      19: invokevirtual #6                  // Method java/lang/StringBuilder.append:(Ljava/lang/String;)Ljava/lang/StringBuilder;
      22: ldc           #7                  // String :
      24: invokevirtual #6                  // Method java/lang/StringBuilder.append:(Ljava/lang/String;)Ljava/lang/StringBuilder;
      27: iload_0
      28: invokevirtual #11                 // Method java/lang/StringBuilder.append:(I)Ljava/lang/StringBuilder;
      31: invokevirtual #9                  // Method java/lang/StringBuilder.toString:()Ljava/lang/String;
      34: invokespecial #10                 // Method java/lang/IllegalArgumentException."<init>":(Ljava/lang/String;)V
      37: athrow
      38: iload_0
      39: ireturn

  public static long checkArg(long, boolean, java.lang.Object);
    Code:
       0: iload_2
       1: ifne          38
       4: new           #2                  // class java/lang/IllegalArgumentException
       7: dup
       8: new           #3                  // class java/lang/StringBuilder
      11: dup
      12: invokespecial #4                  // Method java/lang/StringBuilder."<init>":()V
      15: aload_3
      16: invokestatic  #5                  // Method java/lang/String.valueOf:(Ljava/lang/Object;)Ljava/lang/String;
      19: invokevirtual #6                  // Method java/lang/StringBuilder.append:(Ljava/lang/String;)Ljava/lang/StringBuilder;
      22: ldc           #7                  // String :
      24: invokevirtual #6                  // Method java/lang/StringBuilder.append:(Ljava/lang/String;)Ljava/lang/StringBuilder;
      27: lload_0
      28: invokevirtual #12                 // Method java/lang/StringBuilder.append:(J)Ljava/lang/StringBuilder;
      31: invokevirtual #9                  // Method java/lang/StringBuilder.toString:()Ljava/lang/String;
      34: invokespecial #10                 // Method java/lang/IllegalArgumentException."<init>":(Ljava/lang/String;)V
      37: athrow
      38: lload_0
      39: lreturn

  public static float checkArg(float, boolean, java.lang.Object);
    Code:
       0: iload_1
       1: ifne          38
       4: new           #2                  // class java/lang/IllegalArgumentException
       7: dup
       8: new           #3                  // class java/lang/StringBuilder
      11: dup
      12: invokespecial #4                  // Method java/lang/StringBuilder."<init>":()V
      15: aload_2
      16: invokestatic  #5                  // Method java/lang/String.valueOf:(Ljava/lang/Object;)Ljava/lang/String;
      19: invokevirtual #6                  // Method java/lang/StringBuilder.append:(Ljava/lang/String;)Ljava/lang/StringBuilder;
      22: ldc           #7                  // String :
      24: invokevirtual #6                  // Method java/lang/StringBuilder.append:(Ljava/lang/String;)Ljava/lang/StringBuilder;
      27: fload_0
      28: invokevirtual #13                 // Method java/lang/StringBuilder.append:(F)Ljava/lang/StringBuilder;
      31: invokevirtual #9                  // Method java/lang/StringBuilder.toString:()Ljava/lang/String;
      34: invokespecial #10                 // Method java/lang/IllegalArgumentException."<init>":(Ljava/lang/String;)V
      37: athrow
      38: fload_0
      39: freturn

  public static double checkArg(double, boolean, java.lang.Object);
    Code:
       0: iload_2
       1: ifne          38
       4: new           #2                  // class java/lang/IllegalArgumentException
       7: dup
       8: new           #3                  // class java/lang/StringBuilder
      11: dup
      12: invokespecial #4                  // Method java/lang/StringBuilder."<init>":()V
      15: aload_3
      16: invokestatic  #5                  // Method java/lang/String.valueOf:(Ljava/lang/Object;)Ljava/lang/String;
      19: invokevirtual #6                  // Method java/lang/StringBuilder.append:(Ljava/lang/String;)Ljava/lang/StringBuilder;
      22: ldc           #7                  // String :
      24: invokevirtual #6                  // Method java/lang/StringBuilder.append:(Ljava/lang/String;)Ljava/lang/StringBuilder;
      27: dload_0
      28: invokevirtual #14                 // Method java/lang/StringBuilder.append:(D)Ljava/lang/StringBuilder;
      31: invokevirtual #9                  // Method java/lang/StringBuilder.toString:()Ljava/lang/String;
      34: invokespecial #10                 // Method java/lang/IllegalArgumentException."<init>":(Ljava/lang/String;)V
      37: athrow
      38: dload_0
      39: dreturn
}
