Compiled from "PrimitiveSpreadBuilders.kt"
public abstract class kotlin.jvm.internal.PrimitiveSpreadBuilder<T> {
  private final int size;

  private int position;

  private final T[] spreads;

  public kotlin.jvm.internal.PrimitiveSpreadBuilder(int);
    Code:
       0: aload_0
       1: invokespecial #10                 // Method java/lang/Object."<init>":()V
       4: aload_0
       5: iload_1
       6: putfield      #14                 // Field size:I
       9: aload_0
      10: aload_0
      11: getfield      #14                 // Field size:I
      14: anewarray     #5                  // class java/lang/Object
      17: putfield      #18                 // Field spreads:[Ljava/lang/Object;
      20: return

  protected abstract int getSize(T);

  protected final int getPosition();
    Code:
       0: aload_0
       1: getfield      #29                 // Field position:I
       4: ireturn

  protected final void setPosition(int);
    Code:
       0: aload_0
       1: iload_1
       2: putfield      #29                 // Field position:I
       5: return

  private static void getSpreads$annotations();
    Code:
       0: return

  public final void addSpread(T);
    Code:
       0: aload_1
       1: ldc           #37                 // String spreadArgument
       3: invokestatic  #43                 // Method kotlin/jvm/internal/Intrinsics.checkNotNullParameter:(Ljava/lang/Object;Ljava/lang/String;)V
       6: aload_0
       7: getfield      #18                 // Field spreads:[Ljava/lang/Object;
      10: aload_0
      11: getfield      #29                 // Field position:I
      14: istore_2
      15: aload_0
      16: iload_2
      17: iconst_1
      18: iadd
      19: putfield      #29                 // Field position:I
      22: iload_2
      23: aload_1
      24: aastore
      25: return

  protected final int size();
    Code:
       0: iconst_0
       1: istore_1
       2: new           #46                 // class kotlin/ranges/IntRange
       5: dup
       6: iconst_0
       7: aload_0
       8: getfield      #14                 // Field size:I
      11: iconst_1
      12: isub
      13: invokespecial #49                 // Method kotlin/ranges/IntRange."<init>":(II)V
      16: invokevirtual #53                 // Method kotlin/ranges/IntRange.iterator:()Lkotlin/collections/IntIterator;
      19: astore_2
      20: aload_2
      21: invokevirtual #59                 // Method kotlin/collections/IntIterator.hasNext:()Z
      24: ifeq          58
      27: aload_2
      28: invokevirtual #62                 // Method kotlin/collections/IntIterator.nextInt:()I
      31: istore_3
      32: iload_1
      33: aload_0
      34: getfield      #18                 // Field spreads:[Ljava/lang/Object;
      37: iload_3
      38: aaload
      39: dup
      40: ifnull        51
      43: aload_0
      44: swap
      45: invokevirtual #64                 // Method getSize:(Ljava/lang/Object;)I
      48: goto          53
      51: pop
      52: iconst_1
      53: iadd
      54: istore_1
      55: goto          20
      58: iload_1
      59: ireturn

  protected final T toArray(T, T);
    Code:
       0: aload_1
       1: ldc           #71                 // String values
       3: invokestatic  #43                 // Method kotlin/jvm/internal/Intrinsics.checkNotNullParameter:(Ljava/lang/Object;Ljava/lang/String;)V
       6: aload_2
       7: ldc           #73                 // String result
       9: invokestatic  #43                 // Method kotlin/jvm/internal/Intrinsics.checkNotNullParameter:(Ljava/lang/Object;Ljava/lang/String;)V
      12: iconst_0
      13: istore_3
      14: iconst_0
      15: istore        4
      17: new           #46                 // class kotlin/ranges/IntRange
      20: dup
      21: iconst_0
      22: aload_0
      23: getfield      #14                 // Field size:I
      26: iconst_1
      27: isub
      28: invokespecial #49                 // Method kotlin/ranges/IntRange."<init>":(II)V
      31: invokevirtual #53                 // Method kotlin/ranges/IntRange.iterator:()Lkotlin/collections/IntIterator;
      34: astore        5
      36: aload         5
      38: invokevirtual #59                 // Method kotlin/collections/IntIterator.hasNext:()Z
      41: ifeq          125
      44: aload         5
      46: invokevirtual #62                 // Method kotlin/collections/IntIterator.nextInt:()I
      49: istore        6
      51: aload_0
      52: getfield      #18                 // Field spreads:[Ljava/lang/Object;
      55: iload         6
      57: aaload
      58: astore        7
      60: aload         7
      62: ifnull        36
      65: iload         4
      67: iload         6
      69: if_icmpge     93
      72: aload_1
      73: iload         4
      75: aload_2
      76: iload_3
      77: iload         6
      79: iload         4
      81: isub
      82: invokestatic  #79                 // Method java/lang/System.arraycopy:(Ljava/lang/Object;ILjava/lang/Object;II)V
      85: iload_3
      86: iload         6
      88: iload         4
      90: isub
      91: iadd
      92: istore_3
      93: aload_0
      94: aload         7
      96: invokevirtual #64                 // Method getSize:(Ljava/lang/Object;)I
      99: istore        8
     101: aload         7
     103: iconst_0
     104: aload_2
     105: iload_3
     106: iload         8
     108: invokestatic  #79                 // Method java/lang/System.arraycopy:(Ljava/lang/Object;ILjava/lang/Object;II)V
     111: iload_3
     112: iload         8
     114: iadd
     115: istore_3
     116: iload         6
     118: iconst_1
     119: iadd
     120: istore        4
     122: goto          36
     125: iload         4
     127: aload_0
     128: getfield      #14                 // Field size:I
     131: if_icmpge     149
     134: aload_1
     135: iload         4
     137: aload_2
     138: iload_3
     139: aload_0
     140: getfield      #14                 // Field size:I
     143: iload         4
     145: isub
     146: invokestatic  #79                 // Method java/lang/System.arraycopy:(Ljava/lang/Object;ILjava/lang/Object;II)V
     149: aload_2
     150: areturn
}
