Compiled from "UpdateScriptOperationSerializer.kt"
public final class aws.sdk.kotlin.services.gamelift.transform.UpdateScriptOperationSerializerKt {
  private static final byte[] serializeUpdateScriptOperationBody(aws.smithy.kotlin.runtime.client.ExecutionContext, aws.sdk.kotlin.services.gamelift.model.UpdateScriptRequest);
    Code:
       0: new           #8                  // class aws/smithy/kotlin/runtime/serde/json/JsonSerializer
       3: dup
       4: invokespecial #12                 // Method aws/smithy/kotlin/runtime/serde/json/JsonSerializer."<init>":()V
       7: astore_2
       8: new           #14                 // class aws/smithy/kotlin/runtime/serde/SdkFieldDescriptor
      11: dup
      12: getstatic     #20                 // Field aws/smithy/kotlin/runtime/serde/SerialKind$String.INSTANCE:Laws/smithy/kotlin/runtime/serde/SerialKind$String;
      15: checkcast     #22                 // class aws/smithy/kotlin/runtime/serde/SerialKind
      18: iconst_1
      19: anewarray     #24                 // class aws/smithy/kotlin/runtime/serde/FieldTrait
      22: astore        4
      24: aload         4
      26: iconst_0
      27: new           #26                 // class aws/smithy/kotlin/runtime/serde/json/JsonSerialName
      30: dup
      31: ldc           #28                 // String Name
      33: invokespecial #31                 // Method aws/smithy/kotlin/runtime/serde/json/JsonSerialName."<init>":(Ljava/lang/String;)V
      36: checkcast     #24                 // class aws/smithy/kotlin/runtime/serde/FieldTrait
      39: aastore
      40: aload         4
      42: invokespecial #34                 // Method aws/smithy/kotlin/runtime/serde/SdkFieldDescriptor."<init>":(Laws/smithy/kotlin/runtime/serde/SerialKind;[Laws/smithy/kotlin/runtime/serde/FieldTrait;)V
      45: astore_3
      46: new           #14                 // class aws/smithy/kotlin/runtime/serde/SdkFieldDescriptor
      49: dup
      50: getstatic     #20                 // Field aws/smithy/kotlin/runtime/serde/SerialKind$String.INSTANCE:Laws/smithy/kotlin/runtime/serde/SerialKind$String;
      53: checkcast     #22                 // class aws/smithy/kotlin/runtime/serde/SerialKind
      56: iconst_1
      57: anewarray     #24                 // class aws/smithy/kotlin/runtime/serde/FieldTrait
      60: astore        5
      62: aload         5
      64: iconst_0
      65: new           #26                 // class aws/smithy/kotlin/runtime/serde/json/JsonSerialName
      68: dup
      69: ldc           #36                 // String ScriptId
      71: invokespecial #31                 // Method aws/smithy/kotlin/runtime/serde/json/JsonSerialName."<init>":(Ljava/lang/String;)V
      74: checkcast     #24                 // class aws/smithy/kotlin/runtime/serde/FieldTrait
      77: aastore
      78: aload         5
      80: invokespecial #34                 // Method aws/smithy/kotlin/runtime/serde/SdkFieldDescriptor."<init>":(Laws/smithy/kotlin/runtime/serde/SerialKind;[Laws/smithy/kotlin/runtime/serde/FieldTrait;)V
      83: astore        4
      85: new           #14                 // class aws/smithy/kotlin/runtime/serde/SdkFieldDescriptor
      88: dup
      89: getstatic     #41                 // Field aws/smithy/kotlin/runtime/serde/SerialKind$Struct.INSTANCE:Laws/smithy/kotlin/runtime/serde/SerialKind$Struct;
      92: checkcast     #22                 // class aws/smithy/kotlin/runtime/serde/SerialKind
      95: iconst_1
      96: anewarray     #24                 // class aws/smithy/kotlin/runtime/serde/FieldTrait
      99: astore        6
     101: aload         6
     103: iconst_0
     104: new           #26                 // class aws/smithy/kotlin/runtime/serde/json/JsonSerialName
     107: dup
     108: ldc           #43                 // String StorageLocation
     110: invokespecial #31                 // Method aws/smithy/kotlin/runtime/serde/json/JsonSerialName."<init>":(Ljava/lang/String;)V
     113: checkcast     #24                 // class aws/smithy/kotlin/runtime/serde/FieldTrait
     116: aastore
     117: aload         6
     119: invokespecial #34                 // Method aws/smithy/kotlin/runtime/serde/SdkFieldDescriptor."<init>":(Laws/smithy/kotlin/runtime/serde/SerialKind;[Laws/smithy/kotlin/runtime/serde/FieldTrait;)V
     122: astore        5
     124: new           #14                 // class aws/smithy/kotlin/runtime/serde/SdkFieldDescriptor
     127: dup
     128: getstatic     #20                 // Field aws/smithy/kotlin/runtime/serde/SerialKind$String.INSTANCE:Laws/smithy/kotlin/runtime/serde/SerialKind$String;
     131: checkcast     #22                 // class aws/smithy/kotlin/runtime/serde/SerialKind
     134: iconst_1
     135: anewarray     #24                 // class aws/smithy/kotlin/runtime/serde/FieldTrait
     138: astore        7
     140: aload         7
     142: iconst_0
     143: new           #26                 // class aws/smithy/kotlin/runtime/serde/json/JsonSerialName
     146: dup
     147: ldc           #45                 // String Version
     149: invokespecial #31                 // Method aws/smithy/kotlin/runtime/serde/json/JsonSerialName."<init>":(Ljava/lang/String;)V
     152: checkcast     #24                 // class aws/smithy/kotlin/runtime/serde/FieldTrait
     155: aastore
     156: aload         7
     158: invokespecial #34                 // Method aws/smithy/kotlin/runtime/serde/SdkFieldDescriptor."<init>":(Laws/smithy/kotlin/runtime/serde/SerialKind;[Laws/smithy/kotlin/runtime/serde/FieldTrait;)V
     161: astore        6
     163: new           #14                 // class aws/smithy/kotlin/runtime/serde/SdkFieldDescriptor
     166: dup
     167: getstatic     #50                 // Field aws/smithy/kotlin/runtime/serde/SerialKind$Blob.INSTANCE:Laws/smithy/kotlin/runtime/serde/SerialKind$Blob;
     170: checkcast     #22                 // class aws/smithy/kotlin/runtime/serde/SerialKind
     173: iconst_1
     174: anewarray     #24                 // class aws/smithy/kotlin/runtime/serde/FieldTrait
     177: astore        8
     179: aload         8
     181: iconst_0
     182: new           #26                 // class aws/smithy/kotlin/runtime/serde/json/JsonSerialName
     185: dup
     186: ldc           #52                 // String ZipFile
     188: invokespecial #31                 // Method aws/smithy/kotlin/runtime/serde/json/JsonSerialName."<init>":(Ljava/lang/String;)V
     191: checkcast     #24                 // class aws/smithy/kotlin/runtime/serde/FieldTrait
     194: aastore
     195: aload         8
     197: invokespecial #34                 // Method aws/smithy/kotlin/runtime/serde/SdkFieldDescriptor."<init>":(Laws/smithy/kotlin/runtime/serde/SerialKind;[Laws/smithy/kotlin/runtime/serde/FieldTrait;)V
     200: astore        7
     202: getstatic     #58                 // Field aws/smithy/kotlin/runtime/serde/SdkObjectDescriptor.Companion:Laws/smithy/kotlin/runtime/serde/SdkObjectDescriptor$Companion;
     205: astore        9
     207: iconst_0
     208: istore        10
     210: new           #60                 // class aws/smithy/kotlin/runtime/serde/SdkObjectDescriptor$Builder
     213: dup
     214: invokespecial #61                 // Method aws/smithy/kotlin/runtime/serde/SdkObjectDescriptor$Builder."<init>":()V
     217: astore        11
     219: iconst_0
     220: istore        12
     222: iconst_0
     223: istore        13
     225: aload         11
     227: astore        14
     229: iconst_0
     230: istore        15
     232: aload         14
     234: aload_3
     235: invokevirtual #65                 // Method aws/smithy/kotlin/runtime/serde/SdkObjectDescriptor$Builder.field:(Laws/smithy/kotlin/runtime/serde/SdkFieldDescriptor;)V
     238: aload         14
     240: aload         4
     242: invokevirtual #65                 // Method aws/smithy/kotlin/runtime/serde/SdkObjectDescriptor$Builder.field:(Laws/smithy/kotlin/runtime/serde/SdkFieldDescriptor;)V
     245: aload         14
     247: aload         5
     249: invokevirtual #65                 // Method aws/smithy/kotlin/runtime/serde/SdkObjectDescriptor$Builder.field:(Laws/smithy/kotlin/runtime/serde/SdkFieldDescriptor;)V
     252: aload         14
     254: aload         6
     256: invokevirtual #65                 // Method aws/smithy/kotlin/runtime/serde/SdkObjectDescriptor$Builder.field:(Laws/smithy/kotlin/runtime/serde/SdkFieldDescriptor;)V
     259: aload         14
     261: aload         7
     263: invokevirtual #65                 // Method aws/smithy/kotlin/runtime/serde/SdkObjectDescriptor$Builder.field:(Laws/smithy/kotlin/runtime/serde/SdkFieldDescriptor;)V
     266: nop
     267: aload         11
     269: invokevirtual #69                 // Method aws/smithy/kotlin/runtime/serde/SdkObjectDescriptor$Builder.build:()Laws/smithy/kotlin/runtime/serde/SdkObjectDescriptor;
     272: astore        8
     274: aload_2
     275: checkcast     #71                 // class aws/smithy/kotlin/runtime/serde/Serializer
     278: astore        9
     280: iconst_0
     281: istore        10
     283: aload         9
     285: aload         8
     287: checkcast     #14                 // class aws/smithy/kotlin/runtime/serde/SdkFieldDescriptor
     290: invokeinterface #75,  2           // InterfaceMethod aws/smithy/kotlin/runtime/serde/Serializer.beginStruct:(Laws/smithy/kotlin/runtime/serde/SdkFieldDescriptor;)Laws/smithy/kotlin/runtime/serde/StructSerializer;
     295: astore        11
     297: aload         11
     299: astore        12
     301: iconst_0
     302: istore        13
     304: aload_1
     305: invokevirtual #81                 // Method aws/sdk/kotlin/services/gamelift/model/UpdateScriptRequest.getName:()Ljava/lang/String;
     308: astore        14
     310: aload         14
     312: ifnonnull     318
     315: goto          346
     318: aload         14
     320: astore        15
     322: iconst_0
     323: istore        16
     325: iconst_0
     326: istore        17
     328: aload         15
     330: astore        18
     332: iconst_0
     333: istore        19
     335: aload         12
     337: aload_3
     338: aload         18
     340: invokeinterface #86,  3           // InterfaceMethod aws/smithy/kotlin/runtime/serde/StructSerializer.field:(Laws/smithy/kotlin/runtime/serde/SdkFieldDescriptor;Ljava/lang/String;)V
     345: nop
     346: aload_1
     347: invokevirtual #89                 // Method aws/sdk/kotlin/services/gamelift/model/UpdateScriptRequest.getScriptId:()Ljava/lang/String;
     350: astore        14
     352: aload         14
     354: ifnonnull     360
     357: goto          389
     360: aload         14
     362: astore        15
     364: iconst_0
     365: istore        16
     367: iconst_0
     368: istore        17
     370: aload         15
     372: astore        18
     374: iconst_0
     375: istore        19
     377: aload         12
     379: aload         4
     381: aload         18
     383: invokeinterface #86,  3           // InterfaceMethod aws/smithy/kotlin/runtime/serde/StructSerializer.field:(Laws/smithy/kotlin/runtime/serde/SdkFieldDescriptor;Ljava/lang/String;)V
     388: nop
     389: aload_1
     390: invokevirtual #93                 // Method aws/sdk/kotlin/services/gamelift/model/UpdateScriptRequest.getStorageLocation:()Laws/sdk/kotlin/services/gamelift/model/S3Location;
     393: astore        14
     395: aload         14
     397: ifnonnull     403
     400: goto          436
     403: aload         14
     405: astore        15
     407: iconst_0
     408: istore        16
     410: iconst_0
     411: istore        17
     413: aload         15
     415: astore        18
     417: iconst_0
     418: istore        19
     420: aload         12
     422: aload         5
     424: aload         18
     426: getstatic     #98                 // Field aws/sdk/kotlin/services/gamelift/transform/UpdateScriptOperationSerializerKt$serializeUpdateScriptOperationBody$1$3$1.INSTANCE:Laws/sdk/kotlin/services/gamelift/transform/UpdateScriptOperationSerializerKt$serializeUpdateScriptOperationBody$1$3$1;
     429: checkcast     #100                // class kotlin/jvm/functions/Function2
     432: invokestatic  #105                // Method aws/smithy/kotlin/runtime/serde/SdkSerializableKt.field:(Laws/smithy/kotlin/runtime/serde/StructSerializer;Laws/smithy/kotlin/runtime/serde/SdkFieldDescriptor;Ljava/lang/Object;Lkotlin/jvm/functions/Function2;)V
     435: nop
     436: aload_1
     437: invokevirtual #108                // Method aws/sdk/kotlin/services/gamelift/model/UpdateScriptRequest.getVersion:()Ljava/lang/String;
     440: astore        14
     442: aload         14
     444: ifnonnull     450
     447: goto          479
     450: aload         14
     452: astore        15
     454: iconst_0
     455: istore        16
     457: iconst_0
     458: istore        17
     460: aload         15
     462: astore        18
     464: iconst_0
     465: istore        19
     467: aload         12
     469: aload         6
     471: aload         18
     473: invokeinterface #86,  3           // InterfaceMethod aws/smithy/kotlin/runtime/serde/StructSerializer.field:(Laws/smithy/kotlin/runtime/serde/SdkFieldDescriptor;Ljava/lang/String;)V
     478: nop
     479: aload_1
     480: invokevirtual #112                // Method aws/sdk/kotlin/services/gamelift/model/UpdateScriptRequest.getZipFile:()[B
     483: astore        14
     485: aload         14
     487: ifnonnull     493
     490: goto          525
     493: aload         14
     495: astore        15
     497: iconst_0
     498: istore        16
     500: iconst_0
     501: istore        17
     503: aload         15
     505: astore        18
     507: iconst_0
     508: istore        19
     510: aload         12
     512: aload         7
     514: aload         18
     516: invokestatic  #118                // Method aws/smithy/kotlin/runtime/util/Base64Kt.encodeBase64String:([B)Ljava/lang/String;
     519: invokeinterface #86,  3           // InterfaceMethod aws/smithy/kotlin/runtime/serde/StructSerializer.field:(Laws/smithy/kotlin/runtime/serde/SdkFieldDescriptor;Ljava/lang/String;)V
     524: nop
     525: nop
     526: aload         11
     528: invokeinterface #121,  1          // InterfaceMethod aws/smithy/kotlin/runtime/serde/StructSerializer.endStruct:()V
     533: nop
     534: aload_2
     535: invokevirtual #124                // Method aws/smithy/kotlin/runtime/serde/json/JsonSerializer.toByteArray:()[B
     538: areturn

  public static final byte[] access$serializeUpdateScriptOperationBody(aws.smithy.kotlin.runtime.client.ExecutionContext, aws.sdk.kotlin.services.gamelift.model.UpdateScriptRequest);
    Code:
       0: aload_0
       1: aload_1
       2: invokestatic  #170                // Method serializeUpdateScriptOperationBody:(Laws/smithy/kotlin/runtime/client/ExecutionContext;Laws/sdk/kotlin/services/gamelift/model/UpdateScriptRequest;)[B
       5: areturn
}
