Compiled from "BeanElement.java"
public class org.dom4j.bean.BeanElement extends org.dom4j.tree.DefaultElement {
  private static final org.dom4j.DocumentFactory DOCUMENT_FACTORY;

  private java.lang.Object bean;

  static java.lang.Class class$org$dom4j$bean$BeanElement;

  public org.dom4j.bean.BeanElement(java.lang.String, java.lang.Object);
    Code:
       0: aload_0
       1: getstatic     #6                  // Field DOCUMENT_FACTORY:Lorg/dom4j/DocumentFactory;
       4: aload_1
       5: invokevirtual #7                  // Method org/dom4j/DocumentFactory.createQName:(Ljava/lang/String;)Lorg/dom4j/QName;
       8: aload_2
       9: invokespecial #8                  // Method "<init>":(Lorg/dom4j/QName;Ljava/lang/Object;)V
      12: return

  public org.dom4j.bean.BeanElement(java.lang.String, org.dom4j.Namespace, java.lang.Object);
    Code:
       0: aload_0
       1: getstatic     #6                  // Field DOCUMENT_FACTORY:Lorg/dom4j/DocumentFactory;
       4: aload_1
       5: aload_2
       6: invokevirtual #9                  // Method org/dom4j/DocumentFactory.createQName:(Ljava/lang/String;Lorg/dom4j/Namespace;)Lorg/dom4j/QName;
       9: aload_3
      10: invokespecial #8                  // Method "<init>":(Lorg/dom4j/QName;Ljava/lang/Object;)V
      13: return

  public org.dom4j.bean.BeanElement(org.dom4j.QName, java.lang.Object);
    Code:
       0: aload_0
       1: aload_1
       2: invokespecial #10                 // Method org/dom4j/tree/DefaultElement."<init>":(Lorg/dom4j/QName;)V
       5: aload_0
       6: aload_2
       7: putfield      #11                 // Field bean:Ljava/lang/Object;
      10: return

  public org.dom4j.bean.BeanElement(org.dom4j.QName);
    Code:
       0: aload_0
       1: aload_1
       2: invokespecial #10                 // Method org/dom4j/tree/DefaultElement."<init>":(Lorg/dom4j/QName;)V
       5: return

  public java.lang.Object getData();
    Code:
       0: aload_0
       1: getfield      #11                 // Field bean:Ljava/lang/Object;
       4: areturn

  public void setData(java.lang.Object);
    Code:
       0: aload_0
       1: aload_1
       2: putfield      #11                 // Field bean:Ljava/lang/Object;
       5: aload_0
       6: aconst_null
       7: invokevirtual #12                 // Method setAttributeList:(Ljava/util/List;)V
      10: return

  public org.dom4j.Attribute attribute(java.lang.String);
    Code:
       0: aload_0
       1: invokevirtual #13                 // Method getBeanAttributeList:()Lorg/dom4j/bean/BeanAttributeList;
       4: aload_1
       5: invokevirtual #14                 // Method org/dom4j/bean/BeanAttributeList.attribute:(Ljava/lang/String;)Lorg/dom4j/Attribute;
       8: areturn

  public org.dom4j.Attribute attribute(org.dom4j.QName);
    Code:
       0: aload_0
       1: invokevirtual #13                 // Method getBeanAttributeList:()Lorg/dom4j/bean/BeanAttributeList;
       4: aload_1
       5: invokevirtual #15                 // Method org/dom4j/bean/BeanAttributeList.attribute:(Lorg/dom4j/QName;)Lorg/dom4j/Attribute;
       8: areturn

  public org.dom4j.Element addAttribute(java.lang.String, java.lang.String);
    Code:
       0: aload_0
       1: aload_1
       2: invokevirtual #16                 // Method attribute:(Ljava/lang/String;)Lorg/dom4j/Attribute;
       5: astore_3
       6: aload_3
       7: ifnull        17
      10: aload_3
      11: aload_2
      12: invokeinterface #17,  2           // InterfaceMethod org/dom4j/Attribute.setValue:(Ljava/lang/String;)V
      17: aload_0
      18: areturn

  public org.dom4j.Element addAttribute(org.dom4j.QName, java.lang.String);
    Code:
       0: aload_0
       1: aload_1
       2: invokevirtual #18                 // Method attribute:(Lorg/dom4j/QName;)Lorg/dom4j/Attribute;
       5: astore_3
       6: aload_3
       7: ifnull        17
      10: aload_3
      11: aload_2
      12: invokeinterface #17,  2           // InterfaceMethod org/dom4j/Attribute.setValue:(Ljava/lang/String;)V
      17: aload_0
      18: areturn

  public void setAttributes(java.util.List);
    Code:
       0: new           #19                 // class java/lang/UnsupportedOperationException
       3: dup
       4: ldc           #20                 // String Not implemented yet.
       6: invokespecial #21                 // Method java/lang/UnsupportedOperationException."<init>":(Ljava/lang/String;)V
       9: athrow

  public void setAttributes(org.xml.sax.Attributes, org.dom4j.tree.NamespaceStack, boolean);
    Code:
       0: aload_1
       1: ldc           #22                 // String class
       3: invokeinterface #23,  2           // InterfaceMethod org/xml/sax/Attributes.getValue:(Ljava/lang/String;)Ljava/lang/String;
       8: astore        4
      10: aload         4
      12: ifnull        131
      15: aload         4
      17: iconst_1
      18: getstatic     #24                 // Field class$org$dom4j$bean$BeanElement:Ljava/lang/Class;
      21: ifnonnull     36
      24: ldc           #25                 // String org.dom4j.bean.BeanElement
      26: invokestatic  #26                 // Method class$:(Ljava/lang/String;)Ljava/lang/Class;
      29: dup
      30: putstatic     #24                 // Field class$org$dom4j$bean$BeanElement:Ljava/lang/Class;
      33: goto          39
      36: getstatic     #24                 // Field class$org$dom4j$bean$BeanElement:Ljava/lang/Class;
      39: invokevirtual #27                 // Method java/lang/Class.getClassLoader:()Ljava/lang/ClassLoader;
      42: invokestatic  #28                 // Method java/lang/Class.forName:(Ljava/lang/String;ZLjava/lang/ClassLoader;)Ljava/lang/Class;
      45: astore        5
      47: aload_0
      48: aload         5
      50: invokevirtual #29                 // Method java/lang/Class.newInstance:()Ljava/lang/Object;
      53: invokevirtual #30                 // Method setData:(Ljava/lang/Object;)V
      56: iconst_0
      57: istore        6
      59: iload         6
      61: aload_1
      62: invokeinterface #31,  1           // InterfaceMethod org/xml/sax/Attributes.getLength:()I
      67: if_icmpge     111
      70: aload_1
      71: iload         6
      73: invokeinterface #32,  2           // InterfaceMethod org/xml/sax/Attributes.getLocalName:(I)Ljava/lang/String;
      78: astore        7
      80: ldc           #22                 // String class
      82: aload         7
      84: invokevirtual #33                 // Method java/lang/String.equalsIgnoreCase:(Ljava/lang/String;)Z
      87: ifne          105
      90: aload_0
      91: aload         7
      93: aload_1
      94: iload         6
      96: invokeinterface #34,  2           // InterfaceMethod org/xml/sax/Attributes.getValue:(I)Ljava/lang/String;
     101: invokevirtual #35                 // Method addAttribute:(Ljava/lang/String;Ljava/lang/String;)Lorg/dom4j/Element;
     104: pop
     105: iinc          6, 1
     108: goto          59
     111: goto          138
     114: astore        5
     116: aload_0
     117: invokevirtual #37                 // Method getDocumentFactory:()Lorg/dom4j/DocumentFactory;
     120: checkcast     #38                 // class org/dom4j/bean/BeanDocumentFactory
     123: aload         5
     125: invokevirtual #39                 // Method org/dom4j/bean/BeanDocumentFactory.handleException:(Ljava/lang/Exception;)V
     128: goto          138
     131: aload_0
     132: aload_1
     133: aload_2
     134: iload_3
     135: invokespecial #40                 // Method org/dom4j/tree/DefaultElement.setAttributes:(Lorg/xml/sax/Attributes;Lorg/dom4j/tree/NamespaceStack;Z)V
     138: return
    Exception table:
       from    to  target type
          15   111   114   Class java/lang/Exception

  protected org.dom4j.DocumentFactory getDocumentFactory();
    Code:
       0: getstatic     #6                  // Field DOCUMENT_FACTORY:Lorg/dom4j/DocumentFactory;
       3: areturn

  protected org.dom4j.bean.BeanAttributeList getBeanAttributeList();
    Code:
       0: aload_0
       1: invokevirtual #41                 // Method attributeList:()Ljava/util/List;
       4: checkcast     #42                 // class org/dom4j/bean/BeanAttributeList
       7: areturn

  protected java.util.List createAttributeList();
    Code:
       0: new           #42                 // class org/dom4j/bean/BeanAttributeList
       3: dup
       4: aload_0
       5: invokespecial #43                 // Method org/dom4j/bean/BeanAttributeList."<init>":(Lorg/dom4j/bean/BeanElement;)V
       8: areturn

  protected java.util.List createAttributeList(int);
    Code:
       0: new           #42                 // class org/dom4j/bean/BeanAttributeList
       3: dup
       4: aload_0
       5: invokespecial #43                 // Method org/dom4j/bean/BeanAttributeList."<init>":(Lorg/dom4j/bean/BeanElement;)V
       8: areturn

  static java.lang.Class class$(java.lang.String);
    Code:
       0: aload_0
       1: invokestatic  #1                  // Method java/lang/Class.forName:(Ljava/lang/String;)Ljava/lang/Class;
       4: areturn
       5: astore_1
       6: new           #3                  // class java/lang/NoClassDefFoundError
       9: dup
      10: aload_1
      11: invokevirtual #4                  // Method java/lang/ClassNotFoundException.getMessage:()Ljava/lang/String;
      14: invokespecial #5                  // Method java/lang/NoClassDefFoundError."<init>":(Ljava/lang/String;)V
      17: athrow
    Exception table:
       from    to  target type
           0     4     5   Class java/lang/ClassNotFoundException

  static {};
    Code:
       0: invokestatic  #44                 // Method org/dom4j/bean/BeanDocumentFactory.getInstance:()Lorg/dom4j/DocumentFactory;
       3: putstatic     #6                  // Field DOCUMENT_FACTORY:Lorg/dom4j/DocumentFactory;
       6: return
}
