Compiled from "DrawMode.java"
public final class javafx.scene.shape.DrawMode extends java.lang.Enum<javafx.scene.shape.DrawMode> {
  public static final javafx.scene.shape.DrawMode LINE;

  public static final javafx.scene.shape.DrawMode FILL;

  private static final javafx.scene.shape.DrawMode[] $VALUES;

  public static javafx.scene.shape.DrawMode[] values();
    Code:
       0: getstatic     #1                  // Field $VALUES:[Ljavafx/scene/shape/DrawMode;
       3: invokevirtual #2                  // Method "[Ljavafx/scene/shape/DrawMode;".clone:()Ljava/lang/Object;
       6: checkcast     #3                  // class "[Ljavafx/scene/shape/DrawMode;"
       9: areturn

  public static javafx.scene.shape.DrawMode valueOf(java.lang.String);
    Code:
       0: ldc           #4                  // class javafx/scene/shape/DrawMode
       2: aload_0
       3: invokestatic  #5                  // Method java/lang/Enum.valueOf:(Ljava/lang/Class;Ljava/lang/String;)Ljava/lang/Enum;
       6: checkcast     #4                  // class javafx/scene/shape/DrawMode
       9: areturn

  private javafx.scene.shape.DrawMode();
    Code:
       0: aload_0
       1: aload_1
       2: iload_2
       3: invokespecial #6                  // Method java/lang/Enum."<init>":(Ljava/lang/String;I)V
       6: return

  static {};
    Code:
       0: new           #4                  // class javafx/scene/shape/DrawMode
       3: dup
       4: ldc           #7                  // String LINE
       6: iconst_0
       7: invokespecial #8                  // Method "<init>":(Ljava/lang/String;I)V
      10: putstatic     #9                  // Field LINE:Ljavafx/scene/shape/DrawMode;
      13: new           #4                  // class javafx/scene/shape/DrawMode
      16: dup
      17: ldc           #10                 // String FILL
      19: iconst_1
      20: invokespecial #8                  // Method "<init>":(Ljava/lang/String;I)V
      23: putstatic     #11                 // Field FILL:Ljavafx/scene/shape/DrawMode;
      26: iconst_2
      27: anewarray     #4                  // class javafx/scene/shape/DrawMode
      30: dup
      31: iconst_0
      32: getstatic     #9                  // Field LINE:Ljavafx/scene/shape/DrawMode;
      35: aastore
      36: dup
      37: iconst_1
      38: getstatic     #11                 // Field FILL:Ljavafx/scene/shape/DrawMode;
      41: aastore
      42: putstatic     #1                  // Field $VALUES:[Ljavafx/scene/shape/DrawMode;
      45: return
}
