Compiled from "QuadCurve.java"
class javafx.scene.shape.QuadCurve$1 implements com.sun.javafx.scene.shape.QuadCurveHelper$QuadCurveAccessor {
  javafx.scene.shape.QuadCurve$1();
    Code:
       0: aload_0
       1: invokespecial #1                  // Method java/lang/Object."<init>":()V
       4: return

  public com.sun.javafx.sg.prism.NGNode doCreatePeer(javafx.scene.Node);
    Code:
       0: aload_1
       1: checkcast     #2                  // class javafx/scene/shape/QuadCurve
       4: invokestatic  #3                  // Method javafx/scene/shape/QuadCurve.access$000:(Ljavafx/scene/shape/QuadCurve;)Lcom/sun/javafx/sg/prism/NGNode;
       7: areturn

  public void doUpdatePeer(javafx.scene.Node);
    Code:
       0: aload_1
       1: checkcast     #2                  // class javafx/scene/shape/QuadCurve
       4: invokestatic  #4                  // Method javafx/scene/shape/QuadCurve.access$100:(Ljavafx/scene/shape/QuadCurve;)V
       7: return

  public com.sun.javafx.geom.Shape doConfigShape(javafx.scene.shape.Shape);
    Code:
       0: aload_1
       1: checkcast     #2                  // class javafx/scene/shape/QuadCurve
       4: invokestatic  #5                  // Method javafx/scene/shape/QuadCurve.access$200:(Ljavafx/scene/shape/QuadCurve;)Lcom/sun/javafx/geom/QuadCurve2D;
       7: areturn
}
