Compiled from "ConstructorCallTransformer.java"
class org.codehaus.groovy.transform.sc.transformers.ConstructorCallTransformer$MapStyleConstructorCall extends org.codehaus.groovy.classgen.BytecodeExpression implements groovyjarjarasm.asm.Opcodes {
  private org.codehaus.groovy.transform.sc.transformers.StaticCompilationTransformer staticCompilationTransformer;

  private org.codehaus.groovy.classgen.AsmClassGenerator acg;

  private final org.codehaus.groovy.ast.ClassNode declaringClass;

  private final org.codehaus.groovy.ast.expr.MapExpression map;

  private final org.codehaus.groovy.ast.expr.ConstructorCallExpression originalCall;

  private final boolean innerClassCall;

  public org.codehaus.groovy.transform.sc.transformers.ConstructorCallTransformer$MapStyleConstructorCall(org.codehaus.groovy.transform.sc.transformers.StaticCompilationTransformer, org.codehaus.groovy.ast.ClassNode, org.codehaus.groovy.ast.expr.MapExpression, org.codehaus.groovy.ast.expr.ConstructorCallExpression);
    Code:
       0: aload_0
       1: invokespecial #29                 // Method org/codehaus/groovy/classgen/BytecodeExpression."<init>":()V
       4: aload_0
       5: aload_1
       6: putfield      #31                 // Field staticCompilationTransformer:Lorg/codehaus/groovy/transform/sc/transformers/StaticCompilationTransformer;
       9: aload_0
      10: aload_2
      11: putfield      #33                 // Field declaringClass:Lorg/codehaus/groovy/ast/ClassNode;
      14: aload_0
      15: aload_3
      16: putfield      #35                 // Field map:Lorg/codehaus/groovy/ast/expr/MapExpression;
      19: aload_0
      20: aload         4
      22: putfield      #37                 // Field originalCall:Lorg/codehaus/groovy/ast/expr/ConstructorCallExpression;
      25: aload_0
      26: aload         4
      28: invokevirtual #41                 // Method setSourcePosition:(Lorg/codehaus/groovy/ast/ASTNode;)V
      31: aload_0
      32: aload         4
      34: invokevirtual #44                 // Method copyNodeMetaData:(Lorg/codehaus/groovy/ast/ASTNode;)V
      37: aload         4
      39: invokevirtual #50                 // Method org/codehaus/groovy/ast/expr/ConstructorCallExpression.getArguments:()Lorg/codehaus/groovy/ast/expr/Expression;
      42: instanceof    #52                 // class org/codehaus/groovy/ast/expr/TupleExpression
      45: ifeq          62
      48: aload         4
      50: invokevirtual #50                 // Method org/codehaus/groovy/ast/expr/ConstructorCallExpression.getArguments:()Lorg/codehaus/groovy/ast/expr/Expression;
      53: checkcast     #52                 // class org/codehaus/groovy/ast/expr/TupleExpression
      56: invokevirtual #56                 // Method org/codehaus/groovy/ast/expr/TupleExpression.getExpressions:()Ljava/util/List;
      59: goto          63
      62: aconst_null
      63: astore        5
      65: aload_0
      66: aload         5
      68: ifnull        86
      71: aload         5
      73: invokeinterface #68,  1           // InterfaceMethod java/util/List.size:()I
      78: iconst_2
      79: if_icmpne     86
      82: iconst_1
      83: goto          87
      86: iconst_0
      87: putfield      #70                 // Field innerClassCall:Z
      90: return

  public void visit(org.codehaus.groovy.ast.GroovyCodeVisitor);
    Code:
       0: aload_1
       1: instanceof    #80                 // class org/codehaus/groovy/classgen/AsmClassGenerator
       4: ifeq          18
       7: aload_0
       8: aload_1
       9: checkcast     #80                 // class org/codehaus/groovy/classgen/AsmClassGenerator
      12: putfield      #82                 // Field acg:Lorg/codehaus/groovy/classgen/AsmClassGenerator;
      15: goto          26
      18: aload_0
      19: getfield      #37                 // Field originalCall:Lorg/codehaus/groovy/ast/expr/ConstructorCallExpression;
      22: aload_1
      23: invokevirtual #84                 // Method org/codehaus/groovy/ast/expr/ConstructorCallExpression.visit:(Lorg/codehaus/groovy/ast/GroovyCodeVisitor;)V
      26: aload_0
      27: aload_1
      28: invokespecial #85                 // Method org/codehaus/groovy/classgen/BytecodeExpression.visit:(Lorg/codehaus/groovy/ast/GroovyCodeVisitor;)V
      31: return

  public org.codehaus.groovy.ast.ClassNode getType();
    Code:
       0: aload_0
       1: getfield      #33                 // Field declaringClass:Lorg/codehaus/groovy/ast/ClassNode;
       4: areturn

  public void visit(groovyjarjarasm.asm.MethodVisitor);
    Code:
       0: aload_0
       1: getfield      #82                 // Field acg:Lorg/codehaus/groovy/classgen/AsmClassGenerator;
       4: invokevirtual #94                 // Method org/codehaus/groovy/classgen/AsmClassGenerator.getController:()Lorg/codehaus/groovy/classgen/asm/WriterController;
       7: astore_2
       8: aload_2
       9: invokevirtual #100                // Method org/codehaus/groovy/classgen/asm/WriterController.getOperandStack:()Lorg/codehaus/groovy/classgen/asm/OperandStack;
      12: astore_3
      13: aload_2
      14: invokevirtual #104                // Method org/codehaus/groovy/classgen/asm/WriterController.getCompileStack:()Lorg/codehaus/groovy/classgen/asm/CompileStack;
      17: astore        4
      19: aload         4
      21: ldc           #106                // String tmpObj
      23: aload_0
      24: getfield      #33                 // Field declaringClass:Lorg/codehaus/groovy/ast/ClassNode;
      27: iconst_0
      28: invokevirtual #112                // Method org/codehaus/groovy/classgen/asm/CompileStack.defineTemporaryVariable:(Ljava/lang/String;Lorg/codehaus/groovy/ast/ClassNode;Z)I
      31: istore        5
      33: aload_0
      34: getfield      #33                 // Field declaringClass:Lorg/codehaus/groovy/ast/ClassNode;
      37: invokestatic  #118                // Method org/codehaus/groovy/classgen/asm/BytecodeHelper.getClassInternalName:(Lorg/codehaus/groovy/ast/ClassNode;)Ljava/lang/String;
      40: astore        6
      42: aload_1
      43: sipush        187
      46: aload         6
      48: invokevirtual #124                // Method groovyjarjarasm/asm/MethodVisitor.visitTypeInsn:(ILjava/lang/String;)V
      51: aload_1
      52: bipush        89
      54: invokevirtual #128                // Method groovyjarjarasm/asm/MethodVisitor.visitInsn:(I)V
      57: ldc           #129                // String ()V
      59: astore        7
      61: aload_0
      62: getfield      #70                 // Field innerClassCall:Z
      65: ifeq          143
      68: aload_0
      69: getfield      #33                 // Field declaringClass:Lorg/codehaus/groovy/ast/ClassNode;
      72: invokevirtual #133                // Method org/codehaus/groovy/ast/ClassNode.isRedirectNode:()Z
      75: ifeq          143
      78: aload_0
      79: getfield      #33                 // Field declaringClass:Lorg/codehaus/groovy/ast/ClassNode;
      82: invokevirtual #136                // Method org/codehaus/groovy/ast/ClassNode.redirect:()Lorg/codehaus/groovy/ast/ClassNode;
      85: instanceof    #138                // class org/codehaus/groovy/ast/InnerClassNode
      88: ifeq          143
      91: aload_1
      92: bipush        25
      94: iconst_0
      95: invokevirtual #142                // Method groovyjarjarasm/asm/MethodVisitor.visitVarInsn:(II)V
      98: aload_0
      99: getfield      #33                 // Field declaringClass:Lorg/codehaus/groovy/ast/ClassNode;
     102: invokevirtual #136                // Method org/codehaus/groovy/ast/ClassNode.redirect:()Lorg/codehaus/groovy/ast/ClassNode;
     105: checkcast     #138                // class org/codehaus/groovy/ast/InnerClassNode
     108: astore        8
     110: iconst_1
     111: anewarray     #144                // class org/codehaus/groovy/ast/Parameter
     114: dup
     115: iconst_0
     116: new           #144                // class org/codehaus/groovy/ast/Parameter
     119: dup
     120: aload         8
     122: invokevirtual #147                // Method org/codehaus/groovy/ast/InnerClassNode.getOuterClass:()Lorg/codehaus/groovy/ast/ClassNode;
     125: ldc           #149                // String $p$
     127: invokespecial #152                // Method org/codehaus/groovy/ast/Parameter."<init>":(Lorg/codehaus/groovy/ast/ClassNode;Ljava/lang/String;)V
     130: aastore
     131: astore        9
     133: getstatic     #157                // Field org/codehaus/groovy/ast/ClassHelper.VOID_TYPE:Lorg/codehaus/groovy/ast/ClassNode;
     136: aload         9
     138: invokestatic  #161                // Method org/codehaus/groovy/classgen/asm/BytecodeHelper.getMethodDescriptor:(Lorg/codehaus/groovy/ast/ClassNode;[Lorg/codehaus/groovy/ast/Parameter;)Ljava/lang/String;
     141: astore        7
     143: aload_1
     144: sipush        183
     147: aload         6
     149: ldc           #166                // String <init>
     151: aload         7
     153: iconst_0
     154: invokevirtual #170                // Method groovyjarjarasm/asm/MethodVisitor.visitMethodInsn:(ILjava/lang/String;Ljava/lang/String;Ljava/lang/String;Z)V
     157: aload_1
     158: bipush        58
     160: iload         5
     162: invokevirtual #142                // Method groovyjarjarasm/asm/MethodVisitor.visitVarInsn:(II)V
     165: aload_0
     166: getfield      #35                 // Field map:Lorg/codehaus/groovy/ast/expr/MapExpression;
     169: invokevirtual #173                // Method org/codehaus/groovy/ast/expr/MapExpression.getMapEntryExpressions:()Ljava/util/List;
     172: invokeinterface #177,  1          // InterfaceMethod java/util/List.iterator:()Ljava/util/Iterator;
     177: astore        8
     179: aload         8
     181: invokeinterface #182,  1          // InterfaceMethod java/util/Iterator.hasNext:()Z
     186: ifeq          305
     189: aload         8
     191: invokeinterface #186,  1          // InterfaceMethod java/util/Iterator.next:()Ljava/lang/Object;
     196: checkcast     #188                // class org/codehaus/groovy/ast/expr/MapEntryExpression
     199: astore        9
     201: aload         9
     203: invokevirtual #191                // Method org/codehaus/groovy/ast/expr/MapEntryExpression.getLineNumber:()I
     206: istore        10
     208: aload         9
     210: invokevirtual #194                // Method org/codehaus/groovy/ast/expr/MapEntryExpression.getColumnNumber:()I
     213: istore        11
     215: aload_0
     216: getfield      #31                 // Field staticCompilationTransformer:Lorg/codehaus/groovy/transform/sc/transformers/StaticCompilationTransformer;
     219: aload         9
     221: invokevirtual #197                // Method org/codehaus/groovy/ast/expr/MapEntryExpression.getKeyExpression:()Lorg/codehaus/groovy/ast/expr/Expression;
     224: invokevirtual #201                // Method org/codehaus/groovy/transform/sc/transformers/StaticCompilationTransformer.transform:(Lorg/codehaus/groovy/ast/expr/Expression;)Lorg/codehaus/groovy/ast/expr/Expression;
     227: astore        12
     229: aload_0
     230: getfield      #31                 // Field staticCompilationTransformer:Lorg/codehaus/groovy/transform/sc/transformers/StaticCompilationTransformer;
     233: aload         9
     235: invokevirtual #204                // Method org/codehaus/groovy/ast/expr/MapEntryExpression.getValueExpression:()Lorg/codehaus/groovy/ast/expr/Expression;
     238: invokevirtual #201                // Method org/codehaus/groovy/transform/sc/transformers/StaticCompilationTransformer.transform:(Lorg/codehaus/groovy/ast/expr/Expression;)Lorg/codehaus/groovy/ast/expr/Expression;
     241: astore        13
     243: new           #206                // class org/codehaus/groovy/ast/expr/BinaryExpression
     246: dup
     247: new           #208                // class org/codehaus/groovy/ast/expr/PropertyExpression
     250: dup
     251: new           #12                 // class org/codehaus/groovy/transform/sc/transformers/ConstructorCallTransformer$MapStyleConstructorCall$1
     254: dup
     255: aload_0
     256: iload         5
     258: invokespecial #211                // Method org/codehaus/groovy/transform/sc/transformers/ConstructorCallTransformer$MapStyleConstructorCall$1."<init>":(Lorg/codehaus/groovy/transform/sc/transformers/ConstructorCallTransformer$MapStyleConstructorCall;I)V
     261: aload         12
     263: invokespecial #214                // Method org/codehaus/groovy/ast/expr/PropertyExpression."<init>":(Lorg/codehaus/groovy/ast/expr/Expression;Lorg/codehaus/groovy/ast/expr/Expression;)V
     266: ldc           #216                // String =
     268: iload         10
     270: iload         11
     272: invokestatic  #222                // Method org/codehaus/groovy/syntax/Token.newSymbol:(Ljava/lang/String;II)Lorg/codehaus/groovy/syntax/Token;
     275: aload         13
     277: invokespecial #225                // Method org/codehaus/groovy/ast/expr/BinaryExpression."<init>":(Lorg/codehaus/groovy/ast/expr/Expression;Lorg/codehaus/groovy/syntax/Token;Lorg/codehaus/groovy/ast/expr/Expression;)V
     280: astore        14
     282: aload         14
     284: aload         9
     286: invokevirtual #226                // Method org/codehaus/groovy/ast/expr/BinaryExpression.setSourcePosition:(Lorg/codehaus/groovy/ast/ASTNode;)V
     289: aload         14
     291: aload_0
     292: getfield      #82                 // Field acg:Lorg/codehaus/groovy/classgen/AsmClassGenerator;
     295: invokevirtual #227                // Method org/codehaus/groovy/ast/expr/BinaryExpression.visit:(Lorg/codehaus/groovy/ast/GroovyCodeVisitor;)V
     298: aload_3
     299: invokevirtual #230                // Method org/codehaus/groovy/classgen/asm/OperandStack.pop:()V
     302: goto          179
     305: aload_1
     306: bipush        25
     308: iload         5
     310: invokevirtual #142                // Method groovyjarjarasm/asm/MethodVisitor.visitVarInsn:(II)V
     313: aload         4
     315: iload         5
     317: invokevirtual #233                // Method org/codehaus/groovy/classgen/asm/CompileStack.removeVar:(I)V
     320: return

  static org.codehaus.groovy.ast.ClassNode access$000(org.codehaus.groovy.transform.sc.transformers.ConstructorCallTransformer$MapStyleConstructorCall);
    Code:
       0: aload_0
       1: getfield      #33                 // Field declaringClass:Lorg/codehaus/groovy/ast/ClassNode;
       4: areturn
}
