Compiled from "BinaryMemcacheRequestDecoder.java"
public class io.netty.handler.codec.memcache.binary.BinaryMemcacheRequestDecoder extends io.netty.handler.codec.memcache.binary.AbstractBinaryMemcacheDecoder<io.netty.handler.codec.memcache.binary.BinaryMemcacheRequest> {
  public io.netty.handler.codec.memcache.binary.BinaryMemcacheRequestDecoder();
    Code:
       0: aload_0
       1: sipush        8192
       4: invokespecial #2                  // Method "<init>":(I)V
       7: return

  public io.netty.handler.codec.memcache.binary.BinaryMemcacheRequestDecoder(int);
    Code:
       0: aload_0
       1: iload_1
       2: invokespecial #3                  // Method io/netty/handler/codec/memcache/binary/AbstractBinaryMemcacheDecoder."<init>":(I)V
       5: return

  protected io.netty.handler.codec.memcache.binary.BinaryMemcacheRequest decodeHeader(io.netty.buffer.ByteBuf);
    Code:
       0: new           #4                  // class io/netty/handler/codec/memcache/binary/DefaultBinaryMemcacheRequest
       3: dup
       4: invokespecial #5                  // Method io/netty/handler/codec/memcache/binary/DefaultBinaryMemcacheRequest."<init>":()V
       7: astore_2
       8: aload_2
       9: aload_1
      10: invokevirtual #6                  // Method io/netty/buffer/ByteBuf.readByte:()B
      13: invokevirtual #7                  // Method io/netty/handler/codec/memcache/binary/DefaultBinaryMemcacheRequest.setMagic:(B)Lio/netty/handler/codec/memcache/binary/BinaryMemcacheMessage;
      16: pop
      17: aload_2
      18: aload_1
      19: invokevirtual #6                  // Method io/netty/buffer/ByteBuf.readByte:()B
      22: invokevirtual #8                  // Method io/netty/handler/codec/memcache/binary/DefaultBinaryMemcacheRequest.setOpcode:(B)Lio/netty/handler/codec/memcache/binary/BinaryMemcacheMessage;
      25: pop
      26: aload_2
      27: aload_1
      28: invokevirtual #9                  // Method io/netty/buffer/ByteBuf.readShort:()S
      31: invokevirtual #10                 // Method io/netty/handler/codec/memcache/binary/DefaultBinaryMemcacheRequest.setKeyLength:(S)Lio/netty/handler/codec/memcache/binary/BinaryMemcacheMessage;
      34: pop
      35: aload_2
      36: aload_1
      37: invokevirtual #6                  // Method io/netty/buffer/ByteBuf.readByte:()B
      40: invokevirtual #11                 // Method io/netty/handler/codec/memcache/binary/DefaultBinaryMemcacheRequest.setExtrasLength:(B)Lio/netty/handler/codec/memcache/binary/BinaryMemcacheMessage;
      43: pop
      44: aload_2
      45: aload_1
      46: invokevirtual #6                  // Method io/netty/buffer/ByteBuf.readByte:()B
      49: invokevirtual #12                 // Method io/netty/handler/codec/memcache/binary/DefaultBinaryMemcacheRequest.setDataType:(B)Lio/netty/handler/codec/memcache/binary/BinaryMemcacheMessage;
      52: pop
      53: aload_2
      54: aload_1
      55: invokevirtual #9                  // Method io/netty/buffer/ByteBuf.readShort:()S
      58: invokevirtual #13                 // Method io/netty/handler/codec/memcache/binary/DefaultBinaryMemcacheRequest.setReserved:(S)Lio/netty/handler/codec/memcache/binary/BinaryMemcacheRequest;
      61: pop
      62: aload_2
      63: aload_1
      64: invokevirtual #14                 // Method io/netty/buffer/ByteBuf.readInt:()I
      67: invokevirtual #15                 // Method io/netty/handler/codec/memcache/binary/DefaultBinaryMemcacheRequest.setTotalBodyLength:(I)Lio/netty/handler/codec/memcache/binary/BinaryMemcacheMessage;
      70: pop
      71: aload_2
      72: aload_1
      73: invokevirtual #14                 // Method io/netty/buffer/ByteBuf.readInt:()I
      76: invokevirtual #16                 // Method io/netty/handler/codec/memcache/binary/DefaultBinaryMemcacheRequest.setOpaque:(I)Lio/netty/handler/codec/memcache/binary/BinaryMemcacheMessage;
      79: pop
      80: aload_2
      81: aload_1
      82: invokevirtual #17                 // Method io/netty/buffer/ByteBuf.readLong:()J
      85: invokevirtual #18                 // Method io/netty/handler/codec/memcache/binary/DefaultBinaryMemcacheRequest.setCas:(J)Lio/netty/handler/codec/memcache/binary/BinaryMemcacheMessage;
      88: pop
      89: aload_2
      90: areturn

  protected io.netty.handler.codec.memcache.binary.BinaryMemcacheRequest buildInvalidMessage();
    Code:
       0: new           #4                  // class io/netty/handler/codec/memcache/binary/DefaultBinaryMemcacheRequest
       3: dup
       4: getstatic     #19                 // Field io/netty/buffer/Unpooled.EMPTY_BUFFER:Lio/netty/buffer/ByteBuf;
       7: getstatic     #19                 // Field io/netty/buffer/Unpooled.EMPTY_BUFFER:Lio/netty/buffer/ByteBuf;
      10: invokespecial #20                 // Method io/netty/handler/codec/memcache/binary/DefaultBinaryMemcacheRequest."<init>":(Lio/netty/buffer/ByteBuf;Lio/netty/buffer/ByteBuf;)V
      13: areturn

  protected io.netty.handler.codec.memcache.binary.BinaryMemcacheMessage buildInvalidMessage();
    Code:
       0: aload_0
       1: invokevirtual #21                 // Method buildInvalidMessage:()Lio/netty/handler/codec/memcache/binary/BinaryMemcacheRequest;
       4: areturn

  protected io.netty.handler.codec.memcache.binary.BinaryMemcacheMessage decodeHeader(io.netty.buffer.ByteBuf);
    Code:
       0: aload_0
       1: aload_1
       2: invokevirtual #22                 // Method decodeHeader:(Lio/netty/buffer/ByteBuf;)Lio/netty/handler/codec/memcache/binary/BinaryMemcacheRequest;
       5: areturn
}
