Compiled from "DataSetComponent.java"
public class org.apache.camel.component.dataset.DataSetComponent extends org.apache.camel.impl.UriEndpointComponent {
  public org.apache.camel.component.dataset.DataSetComponent();
    Code:
       0: aload_0
       1: ldc           #9                  // class org/apache/camel/component/dataset/DataSetEndpoint
       3: invokespecial #12                 // Method org/apache/camel/impl/UriEndpointComponent."<init>":(Ljava/lang/Class;)V
       6: return

  protected org.apache.camel.Endpoint createEndpoint(java.lang.String, java.lang.String, java.util.Map<java.lang.String, java.lang.Object>) throws java.lang.Exception;
    Code:
       0: aload_0
       1: invokevirtual #22                 // Method getCamelContext:()Lorg/apache/camel/CamelContext;
       4: aload_2
       5: ldc           #24                 // class org/apache/camel/component/dataset/DataSet
       7: invokestatic  #30                 // Method org/apache/camel/util/CamelContextHelper.mandatoryLookup:(Lorg/apache/camel/CamelContext;Ljava/lang/String;Ljava/lang/Class;)Ljava/lang/Object;
      10: checkcast     #24                 // class org/apache/camel/component/dataset/DataSet
      13: astore        4
      15: new           #9                  // class org/apache/camel/component/dataset/DataSetEndpoint
      18: dup
      19: aload_1
      20: aload_0
      21: aload         4
      23: invokespecial #33                 // Method org/apache/camel/component/dataset/DataSetEndpoint."<init>":(Ljava/lang/String;Lorg/apache/camel/Component;Lorg/apache/camel/component/dataset/DataSet;)V
      26: areturn
}
