Compiled from "PreferredConstructorDiscoverer.java"
public abstract class org.springframework.data.mapping.model.PreferredConstructorDiscoverer$Discoverers extends java.lang.Enum<org.springframework.data.mapping.model.PreferredConstructorDiscoverer$Discoverers> {
  public static final org.springframework.data.mapping.model.PreferredConstructorDiscoverer$Discoverers DEFAULT;

  public static final org.springframework.data.mapping.model.PreferredConstructorDiscoverer$Discoverers KOTLIN;

  private static final org.springframework.core.ParameterNameDiscoverer PARAMETER_NAME_DISCOVERER;

  private static final org.springframework.data.mapping.model.PreferredConstructorDiscoverer$Discoverers[] $VALUES;

  public static org.springframework.data.mapping.model.PreferredConstructorDiscoverer$Discoverers[] values();
    Code:
       0: getstatic     #4                  // Field $VALUES:[Lorg/springframework/data/mapping/model/PreferredConstructorDiscoverer$Discoverers;
       3: invokevirtual #5                  // Method "[Lorg/springframework/data/mapping/model/PreferredConstructorDiscoverer$Discoverers;".clone:()Ljava/lang/Object;
       6: checkcast     #6                  // class "[Lorg/springframework/data/mapping/model/PreferredConstructorDiscoverer$Discoverers;"
       9: areturn

  public static org.springframework.data.mapping.model.PreferredConstructorDiscoverer$Discoverers valueOf(java.lang.String);
    Code:
       0: ldc           #7                  // class org/springframework/data/mapping/model/PreferredConstructorDiscoverer$Discoverers
       2: aload_0
       3: invokestatic  #8                  // Method java/lang/Enum.valueOf:(Ljava/lang/Class;Ljava/lang/String;)Ljava/lang/Enum;
       6: checkcast     #7                  // class org/springframework/data/mapping/model/PreferredConstructorDiscoverer$Discoverers
       9: areturn

  private org.springframework.data.mapping.model.PreferredConstructorDiscoverer$Discoverers();
    Code:
       0: aload_0
       1: aload_1
       2: iload_2
       3: invokespecial #9                  // Method java/lang/Enum."<init>":(Ljava/lang/String;I)V
       6: return

  private static org.springframework.data.mapping.model.PreferredConstructorDiscoverer$Discoverers findDiscoverer(java.lang.Class<?>);
    Code:
       0: aload_0
       1: invokestatic  #10                 // Method org/springframework/data/util/ReflectionUtils.isSupportedKotlinClass:(Ljava/lang/Class;)Z
       4: ifeq          13
       7: getstatic     #11                 // Field KOTLIN:Lorg/springframework/data/mapping/model/PreferredConstructorDiscoverer$Discoverers;
      10: goto          16
      13: getstatic     #12                 // Field DEFAULT:Lorg/springframework/data/mapping/model/PreferredConstructorDiscoverer$Discoverers;
      16: areturn

  abstract <T, P extends org.springframework.data.mapping.PersistentProperty<P>> org.springframework.data.mapping.PreferredConstructor<T, P> discover(org.springframework.data.util.TypeInformation<T>, org.springframework.data.mapping.PersistentEntity<T, P>);

  private static <T, P extends org.springframework.data.mapping.PersistentProperty<P>> org.springframework.data.mapping.PreferredConstructor<T, P> buildPreferredConstructor(java.lang.reflect.Constructor<?>, org.springframework.data.util.TypeInformation<T>, org.springframework.data.mapping.PersistentEntity<T, P>);
    Code:
       0: aload_1
       1: aload_0
       2: invokeinterface #13,  2           // InterfaceMethod org/springframework/data/util/TypeInformation.getParameterTypes:(Ljava/lang/reflect/Constructor;)Ljava/util/List;
       7: astore_3
       8: aload_3
       9: invokeinterface #14,  1           // InterfaceMethod java/util/List.isEmpty:()Z
      14: ifeq          30
      17: new           #15                 // class org/springframework/data/mapping/PreferredConstructor
      20: dup
      21: aload_0
      22: iconst_0
      23: anewarray     #16                 // class org/springframework/data/mapping/PreferredConstructor$Parameter
      26: invokespecial #17                 // Method org/springframework/data/mapping/PreferredConstructor."<init>":(Ljava/lang/reflect/Constructor;[Lorg/springframework/data/mapping/PreferredConstructor$Parameter;)V
      29: areturn
      30: getstatic     #18                 // Field PARAMETER_NAME_DISCOVERER:Lorg/springframework/core/ParameterNameDiscoverer;
      33: aload_0
      34: invokeinterface #19,  2           // InterfaceMethod org/springframework/core/ParameterNameDiscoverer.getParameterNames:(Ljava/lang/reflect/Constructor;)[Ljava/lang/String;
      39: astore        4
      41: aload_3
      42: invokeinterface #20,  1           // InterfaceMethod java/util/List.size:()I
      47: anewarray     #16                 // class org/springframework/data/mapping/PreferredConstructor$Parameter
      50: astore        5
      52: aload_0
      53: invokevirtual #21                 // Method java/lang/reflect/Constructor.getParameterAnnotations:()[[Ljava/lang/annotation/Annotation;
      56: astore        6
      58: iconst_0
      59: istore        7
      61: iload         7
      63: aload_3
      64: invokeinterface #20,  1           // InterfaceMethod java/util/List.size:()I
      69: if_icmpge     133
      72: aload         4
      74: ifnonnull     81
      77: aconst_null
      78: goto          86
      81: aload         4
      83: iload         7
      85: aaload
      86: astore        8
      88: aload_3
      89: iload         7
      91: invokeinterface #22,  2           // InterfaceMethod java/util/List.get:(I)Ljava/lang/Object;
      96: checkcast     #23                 // class org/springframework/data/util/TypeInformation
      99: astore        9
     101: aload         6
     103: iload         7
     105: aaload
     106: astore        10
     108: aload         5
     110: iload         7
     112: new           #16                 // class org/springframework/data/mapping/PreferredConstructor$Parameter
     115: dup
     116: aload         8
     118: aload         9
     120: aload         10
     122: aload_2
     123: invokespecial #24                 // Method org/springframework/data/mapping/PreferredConstructor$Parameter."<init>":(Ljava/lang/String;Lorg/springframework/data/util/TypeInformation;[Ljava/lang/annotation/Annotation;Lorg/springframework/data/mapping/PersistentEntity;)V
     126: aastore
     127: iinc          7, 1
     130: goto          61
     133: new           #15                 // class org/springframework/data/mapping/PreferredConstructor
     136: dup
     137: aload_0
     138: aload         5
     140: invokespecial #17                 // Method org/springframework/data/mapping/PreferredConstructor."<init>":(Ljava/lang/reflect/Constructor;[Lorg/springframework/data/mapping/PreferredConstructor$Parameter;)V
     143: areturn

  static org.springframework.data.mapping.model.PreferredConstructorDiscoverer$Discoverers access$000(java.lang.Class);
    Code:
       0: aload_0
       1: invokestatic  #3                  // Method findDiscoverer:(Ljava/lang/Class;)Lorg/springframework/data/mapping/model/PreferredConstructorDiscoverer$Discoverers;
       4: areturn

  org.springframework.data.mapping.model.PreferredConstructorDiscoverer$Discoverers(java.lang.String, int, org.springframework.data.mapping.model.PreferredConstructorDiscoverer$1);
    Code:
       0: aload_0
       1: aload_1
       2: iload_2
       3: invokespecial #2                  // Method "<init>":(Ljava/lang/String;I)V
       6: return

  static org.springframework.data.mapping.PreferredConstructor access$200(java.lang.reflect.Constructor, org.springframework.data.util.TypeInformation, org.springframework.data.mapping.PersistentEntity);
    Code:
       0: aload_0
       1: aload_1
       2: aload_2
       3: invokestatic  #1                  // Method buildPreferredConstructor:(Ljava/lang/reflect/Constructor;Lorg/springframework/data/util/TypeInformation;Lorg/springframework/data/mapping/PersistentEntity;)Lorg/springframework/data/mapping/PreferredConstructor;
       6: areturn

  static {};
    Code:
       0: new           #25                 // class org/springframework/data/mapping/model/PreferredConstructorDiscoverer$Discoverers$1
       3: dup
       4: ldc           #26                 // String DEFAULT
       6: iconst_0
       7: invokespecial #27                 // Method org/springframework/data/mapping/model/PreferredConstructorDiscoverer$Discoverers$1."<init>":(Ljava/lang/String;I)V
      10: putstatic     #12                 // Field DEFAULT:Lorg/springframework/data/mapping/model/PreferredConstructorDiscoverer$Discoverers;
      13: new           #28                 // class org/springframework/data/mapping/model/PreferredConstructorDiscoverer$Discoverers$2
      16: dup
      17: ldc           #29                 // String KOTLIN
      19: iconst_1
      20: invokespecial #30                 // Method org/springframework/data/mapping/model/PreferredConstructorDiscoverer$Discoverers$2."<init>":(Ljava/lang/String;I)V
      23: putstatic     #11                 // Field KOTLIN:Lorg/springframework/data/mapping/model/PreferredConstructorDiscoverer$Discoverers;
      26: iconst_2
      27: anewarray     #7                  // class org/springframework/data/mapping/model/PreferredConstructorDiscoverer$Discoverers
      30: dup
      31: iconst_0
      32: getstatic     #12                 // Field DEFAULT:Lorg/springframework/data/mapping/model/PreferredConstructorDiscoverer$Discoverers;
      35: aastore
      36: dup
      37: iconst_1
      38: getstatic     #11                 // Field KOTLIN:Lorg/springframework/data/mapping/model/PreferredConstructorDiscoverer$Discoverers;
      41: aastore
      42: putstatic     #4                  // Field $VALUES:[Lorg/springframework/data/mapping/model/PreferredConstructorDiscoverer$Discoverers;
      45: new           #31                 // class org/springframework/core/DefaultParameterNameDiscoverer
      48: dup
      49: invokespecial #32                 // Method org/springframework/core/DefaultParameterNameDiscoverer."<init>":()V
      52: putstatic     #18                 // Field PARAMETER_NAME_DISCOVERER:Lorg/springframework/core/ParameterNameDiscoverer;
      55: return
}
