Compiled from "RouterSpec.java"
class org.springframework.integration.dsl.RouterSpec$1 implements org.springframework.integration.support.context.NamedComponent {
  final java.lang.String val$channelName;

  final org.springframework.integration.dsl.RouterSpec this$0;

  org.springframework.integration.dsl.RouterSpec$1(org.springframework.integration.dsl.RouterSpec, java.lang.String);
    Code:
       0: aload_0
       1: aload_1
       2: putfield      #1                  // Field this$0:Lorg/springframework/integration/dsl/RouterSpec;
       5: aload_0
       6: aload_2
       7: putfield      #2                  // Field val$channelName:Ljava/lang/String;
      10: aload_0
      11: invokespecial #3                  // Method java/lang/Object."<init>":()V
      14: return

  public java.lang.String getComponentName();
    Code:
       0: aload_0
       1: getfield      #2                  // Field val$channelName:Ljava/lang/String;
       4: areturn

  public java.lang.String getComponentType();
    Code:
       0: ldc           #4                  // String channel
       2: areturn
}
