Compiled from "EmptyEntityResolver.java"
final class org.apache.solr.common.EmptyEntityResolver$2 implements javax.xml.stream.XMLResolver {
  org.apache.solr.common.EmptyEntityResolver$2();
    Code:
       0: aload_0
       1: invokespecial #1                  // Method java/lang/Object."<init>":()V
       4: return

  public java.io.InputStream resolveEntity(java.lang.String, java.lang.String, java.lang.String, java.lang.String);
    Code:
       0: getstatic     #2                  // Field org/apache/commons/io/input/ClosedInputStream.CLOSED_INPUT_STREAM:Lorg/apache/commons/io/input/ClosedInputStream;
       3: areturn

  public java.lang.Object resolveEntity(java.lang.String, java.lang.String, java.lang.String, java.lang.String) throws javax.xml.stream.XMLStreamException;
    Code:
       0: aload_0
       1: aload_1
       2: aload_2
       3: aload_3
       4: aload         4
       6: invokevirtual #3                  // Method resolveEntity:(Ljava/lang/String;Ljava/lang/String;Ljava/lang/String;Ljava/lang/String;)Ljava/io/InputStream;
       9: areturn
}
