Compiled from "ErrorUtils.java"
public class kotlin.reflect.jvm.internal.impl.types.ErrorUtils$UninferredParameterTypeConstructor implements kotlin.reflect.jvm.internal.impl.types.TypeConstructor {
  private final kotlin.reflect.jvm.internal.impl.descriptors.TypeParameterDescriptor typeParameterDescriptor;

  private final kotlin.reflect.jvm.internal.impl.types.TypeConstructor errorTypeConstructor;

  public kotlin.reflect.jvm.internal.impl.descriptors.TypeParameterDescriptor getTypeParameterDescriptor();
    Code:
       0: aload_0
       1: getfield      #8                  // Field typeParameterDescriptor:Lkotlin/reflect/jvm/internal/impl/descriptors/TypeParameterDescriptor;
       4: areturn

  public java.util.List<kotlin.reflect.jvm.internal.impl.descriptors.TypeParameterDescriptor> getParameters();
    Code:
       0: aload_0
       1: getfield      #7                  // Field errorTypeConstructor:Lkotlin/reflect/jvm/internal/impl/types/TypeConstructor;
       4: invokeinterface #11,  1           // InterfaceMethod kotlin/reflect/jvm/internal/impl/types/TypeConstructor.getParameters:()Ljava/util/List;
       9: areturn

  public java.util.Collection<kotlin.reflect.jvm.internal.impl.types.KotlinType> getSupertypes();
    Code:
       0: aload_0
       1: getfield      #7                  // Field errorTypeConstructor:Lkotlin/reflect/jvm/internal/impl/types/TypeConstructor;
       4: invokeinterface #12,  1           // InterfaceMethod kotlin/reflect/jvm/internal/impl/types/TypeConstructor.getSupertypes:()Ljava/util/Collection;
       9: areturn

  public boolean isDenotable();
    Code:
       0: aload_0
       1: getfield      #7                  // Field errorTypeConstructor:Lkotlin/reflect/jvm/internal/impl/types/TypeConstructor;
       4: invokeinterface #13,  1           // InterfaceMethod kotlin/reflect/jvm/internal/impl/types/TypeConstructor.isDenotable:()Z
       9: ireturn

  public kotlin.reflect.jvm.internal.impl.descriptors.ClassifierDescriptor getDeclarationDescriptor();
    Code:
       0: aload_0
       1: getfield      #7                  // Field errorTypeConstructor:Lkotlin/reflect/jvm/internal/impl/types/TypeConstructor;
       4: invokeinterface #10,  1           // InterfaceMethod kotlin/reflect/jvm/internal/impl/types/TypeConstructor.getDeclarationDescriptor:()Lkotlin/reflect/jvm/internal/impl/descriptors/ClassifierDescriptor;
       9: areturn

  public kotlin.reflect.jvm.internal.impl.builtins.KotlinBuiltIns getBuiltIns();
    Code:
       0: aload_0
       1: getfield      #8                  // Field typeParameterDescriptor:Lkotlin/reflect/jvm/internal/impl/descriptors/TypeParameterDescriptor;
       4: invokestatic  #9                  // Method kotlin/reflect/jvm/internal/impl/resolve/descriptorUtil/DescriptorUtilsKt.getBuiltIns:(Lkotlin/reflect/jvm/internal/impl/descriptors/DeclarationDescriptor;)Lkotlin/reflect/jvm/internal/impl/builtins/KotlinBuiltIns;
       7: areturn
}
