Compiled from "SocketProcessorBase.java"
public abstract class org.apache.tomcat.util.net.SocketProcessorBase<S> implements java.lang.Runnable {
  protected org.apache.tomcat.util.net.SocketWrapperBase<S> socketWrapper;

  protected org.apache.tomcat.util.net.SocketEvent event;

  public org.apache.tomcat.util.net.SocketProcessorBase(org.apache.tomcat.util.net.SocketWrapperBase<S>, org.apache.tomcat.util.net.SocketEvent);
    Code:
       0: aload_0
       1: invokespecial #1                  // Method java/lang/Object."<init>":()V
       4: aload_0
       5: aload_1
       6: aload_2
       7: invokevirtual #2                  // Method reset:(Lorg/apache/tomcat/util/net/SocketWrapperBase;Lorg/apache/tomcat/util/net/SocketEvent;)V
      10: return

  public void reset(org.apache.tomcat.util.net.SocketWrapperBase<S>, org.apache.tomcat.util.net.SocketEvent);
    Code:
       0: aload_2
       1: invokestatic  #3                  // Method java/util/Objects.requireNonNull:(Ljava/lang/Object;)Ljava/lang/Object;
       4: pop
       5: aload_0
       6: aload_1
       7: putfield      #4                  // Field socketWrapper:Lorg/apache/tomcat/util/net/SocketWrapperBase;
      10: aload_0
      11: aload_2
      12: putfield      #5                  // Field event:Lorg/apache/tomcat/util/net/SocketEvent;
      15: return

  public final void run();
    Code:
       0: aload_0
       1: getfield      #4                  // Field socketWrapper:Lorg/apache/tomcat/util/net/SocketWrapperBase;
       4: dup
       5: astore_1
       6: monitorenter
       7: aload_0
       8: getfield      #4                  // Field socketWrapper:Lorg/apache/tomcat/util/net/SocketWrapperBase;
      11: invokevirtual #6                  // Method org/apache/tomcat/util/net/SocketWrapperBase.isClosed:()Z
      14: ifeq          20
      17: aload_1
      18: monitorexit
      19: return
      20: aload_0
      21: invokevirtual #7                  // Method doRun:()V
      24: aload_1
      25: monitorexit
      26: goto          34
      29: astore_2
      30: aload_1
      31: monitorexit
      32: aload_2
      33: athrow
      34: return
    Exception table:
       from    to  target type
           7    19    29   any
          20    26    29   any
          29    32    29   any

  protected abstract void doRun();
}
