Compiled from "ExecutorProviders.java"
class org.glassfish.jersey.process.internal.ExecutorProviders$ExecutorServiceSupplier implements org.glassfish.jersey.internal.inject.DisposableSupplier<java.util.concurrent.ExecutorService> {
  private final org.glassfish.jersey.spi.ExecutorServiceProvider executorProvider;

  private org.glassfish.jersey.process.internal.ExecutorProviders$ExecutorServiceSupplier(org.glassfish.jersey.spi.ExecutorServiceProvider);
    Code:
       0: aload_0
       1: invokespecial #2                  // Method java/lang/Object."<init>":()V
       4: aload_0
       5: aload_1
       6: putfield      #3                  // Field executorProvider:Lorg/glassfish/jersey/spi/ExecutorServiceProvider;
       9: return

  public java.util.concurrent.ExecutorService get();
    Code:
       0: aload_0
       1: getfield      #3                  // Field executorProvider:Lorg/glassfish/jersey/spi/ExecutorServiceProvider;
       4: invokeinterface #4,  1            // InterfaceMethod org/glassfish/jersey/spi/ExecutorServiceProvider.getExecutorService:()Ljava/util/concurrent/ExecutorService;
       9: areturn

  public void dispose(java.util.concurrent.ExecutorService);
    Code:
       0: aload_0
       1: getfield      #3                  // Field executorProvider:Lorg/glassfish/jersey/spi/ExecutorServiceProvider;
       4: aload_1
       5: invokeinterface #5,  2            // InterfaceMethod org/glassfish/jersey/spi/ExecutorServiceProvider.dispose:(Ljava/util/concurrent/ExecutorService;)V
      10: return

  public void dispose(java.lang.Object);
    Code:
       0: aload_0
       1: aload_1
       2: checkcast     #6                  // class java/util/concurrent/ExecutorService
       5: invokevirtual #7                  // Method dispose:(Ljava/util/concurrent/ExecutorService;)V
       8: return

  public java.lang.Object get();
    Code:
       0: aload_0
       1: invokevirtual #8                  // Method get:()Ljava/util/concurrent/ExecutorService;
       4: areturn

  org.glassfish.jersey.process.internal.ExecutorProviders$ExecutorServiceSupplier(org.glassfish.jersey.spi.ExecutorServiceProvider, org.glassfish.jersey.process.internal.ExecutorProviders$1);
    Code:
       0: aload_0
       1: aload_1
       2: invokespecial #1                  // Method "<init>":(Lorg/glassfish/jersey/spi/ExecutorServiceProvider;)V
       5: return
}
