Compiled from "AbstractIntegerMetric.java"
public abstract class org.protege.editor.owl.ui.metrics.AbstractIntegerMetric extends org.protege.editor.owl.ui.metrics.Metric {
  private java.lang.String metric;

  public org.protege.editor.owl.ui.metrics.AbstractIntegerMetric(java.lang.String);
    Code:
       0: aload_0
       1: aload_1
       2: invokespecial #1                  // Method org/protege/editor/owl/ui/metrics/Metric."<init>":(Ljava/lang/String;)V
       5: return

  public java.lang.String getMetric();
    Code:
       0: aload_0
       1: getfield      #2                  // Field metric:Ljava/lang/String;
       4: areturn

  public void updateMetric();
    Code:
       0: aload_0
       1: aload_0
       2: invokevirtual #3                  // Method getIntMetric:()I
       5: invokestatic  #4                  // Method java/lang/Integer.toString:(I)Ljava/lang/String;
       8: putfield      #2                  // Field metric:Ljava/lang/String;
      11: return

  protected abstract int getIntMetric();
}
