Compiled from "AxiomMetricsViewComponent.java"
public class org.protege.editor.owl.ui.metrics.AxiomMetricsViewComponent extends org.protege.editor.owl.ui.view.AbstractActiveOntologyViewComponent {
  private static final org.slf4j.Logger logger;

  private org.protege.editor.owl.ui.metrics.MetricsPanel metricsPanel;

  public org.protege.editor.owl.ui.metrics.AxiomMetricsViewComponent();
    Code:
       0: aload_0
       1: invokespecial #1                  // Method org/protege/editor/owl/ui/view/AbstractActiveOntologyViewComponent."<init>":()V
       4: return

  protected void initialiseOntologyView() throws java.lang.Exception;
    Code:
       0: aload_0
       1: new           #2                  // class org/protege/editor/owl/ui/metrics/MetricsPanel
       4: dup
       5: aload_0
       6: invokevirtual #3                  // Method getOWLEditorKit:()Lorg/protege/editor/owl/OWLEditorKit;
       9: invokespecial #4                  // Method org/protege/editor/owl/ui/metrics/MetricsPanel."<init>":(Lorg/protege/editor/owl/OWLEditorKit;)V
      12: putfield      #5                  // Field metricsPanel:Lorg/protege/editor/owl/ui/metrics/MetricsPanel;
      15: aload_0
      16: new           #6                  // class java/awt/BorderLayout
      19: dup
      20: invokespecial #7                  // Method java/awt/BorderLayout."<init>":()V
      23: invokevirtual #8                  // Method setLayout:(Ljava/awt/LayoutManager;)V
      26: aload_0
      27: aload_0
      28: getfield      #5                  // Field metricsPanel:Lorg/protege/editor/owl/ui/metrics/MetricsPanel;
      31: invokevirtual #9                  // Method add:(Ljava/awt/Component;)Ljava/awt/Component;
      34: pop
      35: return

  protected void disposeOntologyView();
    Code:
       0: aload_0
       1: getfield      #5                  // Field metricsPanel:Lorg/protege/editor/owl/ui/metrics/MetricsPanel;
       4: invokevirtual #10                 // Method org/protege/editor/owl/ui/metrics/MetricsPanel.dispose:()V
       7: goto          22
      10: astore_1
      11: getstatic     #12                 // Field logger:Lorg/slf4j/Logger;
      14: ldc           #13                 // String An error occurred whilst disposing of the metrics panel
      16: aload_1
      17: invokeinterface #14,  3           // InterfaceMethod org/slf4j/Logger.error:(Ljava/lang/String;Ljava/lang/Throwable;)V
      22: return
    Exception table:
       from    to  target type
           0     7    10   Class java/lang/Exception

  protected void updateView(org.semanticweb.owlapi.model.OWLOntology) throws java.lang.Exception;
    Code:
       0: aload_0
       1: getfield      #5                  // Field metricsPanel:Lorg/protege/editor/owl/ui/metrics/MetricsPanel;
       4: aload_1
       5: invokevirtual #15                 // Method org/protege/editor/owl/ui/metrics/MetricsPanel.updateView:(Lorg/semanticweb/owlapi/model/OWLOntology;)V
       8: return

  static {};
    Code:
       0: ldc           #16                 // class org/protege/editor/owl/ui/metrics/AxiomMetricsViewComponent
       2: invokestatic  #17                 // Method org/slf4j/LoggerFactory.getLogger:(Ljava/lang/Class;)Lorg/slf4j/Logger;
       5: putstatic     #12                 // Field logger:Lorg/slf4j/Logger;
       8: return
}
