Compiled from "ImportsClosureIndividualCountMetric.java"
public class org.protege.editor.owl.ui.metrics.ImportsClosureIndividualCountMetric extends org.protege.editor.owl.ui.metrics.AbstractIntegerMetric {
  public org.protege.editor.owl.ui.metrics.ImportsClosureIndividualCountMetric();
    Code:
       0: aload_0
       1: ldc           #1                  // String Individuals (imported)
       3: invokespecial #2                  // Method org/protege/editor/owl/ui/metrics/AbstractIntegerMetric."<init>":(Ljava/lang/String;)V
       6: return

  protected int getIntMetric();
    Code:
       0: new           #3                  // class java/util/HashSet
       3: dup
       4: invokespecial #4                  // Method java/util/HashSet."<init>":()V
       7: astore_1
       8: aload_0
       9: invokevirtual #5                  // Method getOWLModelManager:()Lorg/protege/editor/owl/model/OWLModelManager;
      12: invokeinterface #6,  1            // InterfaceMethod org/protege/editor/owl/model/OWLModelManager.getActiveOntologies:()Ljava/util/Set;
      17: invokeinterface #7,  1            // InterfaceMethod java/util/Set.iterator:()Ljava/util/Iterator;
      22: astore_2
      23: aload_2
      24: invokeinterface #8,  1            // InterfaceMethod java/util/Iterator.hasNext:()Z
      29: ifeq          58
      32: aload_2
      33: invokeinterface #9,  1            // InterfaceMethod java/util/Iterator.next:()Ljava/lang/Object;
      38: checkcast     #10                 // class org/semanticweb/owlapi/model/OWLOntology
      41: astore_3
      42: aload_1
      43: aload_3
      44: invokeinterface #11,  1           // InterfaceMethod org/semanticweb/owlapi/model/OWLOntology.getIndividualsInSignature:()Ljava/util/Set;
      49: invokeinterface #12,  2           // InterfaceMethod java/util/Set.addAll:(Ljava/util/Collection;)Z
      54: pop
      55: goto          23
      58: aload_1
      59: invokeinterface #13,  1           // InterfaceMethod java/util/Set.size:()I
      64: ireturn
}
