Compiled from "MetricsPanel.java"
class org.protege.editor.owl.ui.metrics.MetricsPanel$1 extends java.awt.event.WindowAdapter {
  final org.protege.editor.owl.ui.OWLAxiomTypeFramePanel val$panel;

  final org.protege.editor.owl.ui.metrics.MetricsPanel this$0;

  org.protege.editor.owl.ui.metrics.MetricsPanel$1(org.protege.editor.owl.ui.metrics.MetricsPanel, org.protege.editor.owl.ui.OWLAxiomTypeFramePanel);
    Code:
       0: aload_0
       1: aload_1
       2: putfield      #1                  // Field this$0:Lorg/protege/editor/owl/ui/metrics/MetricsPanel;
       5: aload_0
       6: aload_2
       7: putfield      #2                  // Field val$panel:Lorg/protege/editor/owl/ui/OWLAxiomTypeFramePanel;
      10: aload_0
      11: invokespecial #3                  // Method java/awt/event/WindowAdapter."<init>":()V
      14: return

  public void windowClosing(java.awt.event.WindowEvent);
    Code:
       0: aload_0
       1: getfield      #2                  // Field val$panel:Lorg/protege/editor/owl/ui/OWLAxiomTypeFramePanel;
       4: invokevirtual #4                  // Method org/protege/editor/owl/ui/OWLAxiomTypeFramePanel.dispose:()V
       7: return
}
