Compiled from "MetricsPanel.java"
class org.protege.editor.owl.ui.metrics.MetricsPanel$4 extends java.awt.event.MouseAdapter {
  final javax.swing.JPanel val$tablePanel;

  final org.protege.editor.owl.ui.metrics.MetricsPanel this$0;

  org.protege.editor.owl.ui.metrics.MetricsPanel$4(org.protege.editor.owl.ui.metrics.MetricsPanel, javax.swing.JPanel);
    Code:
       0: aload_0
       1: aload_1
       2: putfield      #1                  // Field this$0:Lorg/protege/editor/owl/ui/metrics/MetricsPanel;
       5: aload_0
       6: aload_2
       7: putfield      #2                  // Field val$tablePanel:Ljavax/swing/JPanel;
      10: aload_0
      11: invokespecial #3                  // Method java/awt/event/MouseAdapter."<init>":()V
      14: return

  public void mousePressed(java.awt.event.MouseEvent);
    Code:
       0: aload_1
       1: invokevirtual #4                  // Method java/awt/event/MouseEvent.isPopupTrigger:()Z
       4: ifeq          12
       7: aload_0
       8: aload_1
       9: invokespecial #5                  // Method showMenu:(Ljava/awt/event/MouseEvent;)V
      12: return

  public void mouseReleased(java.awt.event.MouseEvent);
    Code:
       0: aload_1
       1: invokevirtual #4                  // Method java/awt/event/MouseEvent.isPopupTrigger:()Z
       4: ifeq          12
       7: aload_0
       8: aload_1
       9: invokespecial #5                  // Method showMenu:(Ljava/awt/event/MouseEvent;)V
      12: return

  private void showMenu(java.awt.event.MouseEvent);
    Code:
       0: new           #6                  // class javax/swing/JPopupMenu
       3: dup
       4: invokespecial #7                  // Method javax/swing/JPopupMenu."<init>":()V
       7: astore_2
       8: aload_2
       9: new           #8                  // class org/protege/editor/owl/ui/metrics/MetricsPanel$4$1
      12: dup
      13: aload_0
      14: ldc           #9                  // String Copy metrics to clipboard
      16: invokespecial #10                 // Method org/protege/editor/owl/ui/metrics/MetricsPanel$4$1."<init>":(Lorg/protege/editor/owl/ui/metrics/MetricsPanel$4;Ljava/lang/String;)V
      19: invokevirtual #11                 // Method javax/swing/JPopupMenu.add:(Ljavax/swing/Action;)Ljavax/swing/JMenuItem;
      22: pop
      23: aload_2
      24: aload_0
      25: getfield      #2                  // Field val$tablePanel:Ljavax/swing/JPanel;
      28: aload_1
      29: invokevirtual #12                 // Method java/awt/event/MouseEvent.getX:()I
      32: aload_1
      33: invokevirtual #13                 // Method java/awt/event/MouseEvent.getY:()I
      36: invokevirtual #14                 // Method javax/swing/JPopupMenu.show:(Ljava/awt/Component;II)V
      39: return
}
