Compiled from "DefaultArraySerializers.java"
public class com.esotericsoftware.kryo.serializers.DefaultArraySerializers$ObjectArraySerializer extends com.esotericsoftware.kryo.Serializer<java.lang.Object[]> {
  private boolean elementsAreSameType;

  private boolean elementsCanBeNull;

  private java.lang.Class[] generics;

  private final java.lang.Class type;

  public com.esotericsoftware.kryo.serializers.DefaultArraySerializers$ObjectArraySerializer(com.esotericsoftware.kryo.Kryo, java.lang.Class);
    Code:
       0: aload_0
       1: invokespecial #2                  // Method com/esotericsoftware/kryo/Serializer."<init>":()V
       4: aload_0
       5: iconst_1
       6: putfield      #3                  // Field elementsCanBeNull:Z
       9: aload_0
      10: iconst_1
      11: invokevirtual #4                  // Method setAcceptsNull:(Z)V
      14: aload_0
      15: aload_2
      16: putfield      #5                  // Field type:Ljava/lang/Class;
      19: aload_2
      20: invokevirtual #6                  // Method java/lang/Class.getComponentType:()Ljava/lang/Class;
      23: astore_3
      24: iconst_0
      25: aload_3
      26: invokevirtual #7                  // Method java/lang/Class.getModifiers:()I
      29: bipush        16
      31: iand
      32: if_icmpeq     39
      35: iconst_1
      36: goto          40
      39: iconst_0
      40: istore        4
      42: iload         4
      44: ifeq          52
      47: aload_0
      48: iconst_1
      49: invokevirtual #9                  // Method setElementsAreSameType:(Z)V
      52: return

  public void write(com.esotericsoftware.kryo.Kryo, com.esotericsoftware.kryo.io.Output, java.lang.Object[]);
    Code:
       0: aload_3
       1: ifnonnull     12
       4: aload_2
       5: iconst_0
       6: iconst_1
       7: invokevirtual #10                 // Method com/esotericsoftware/kryo/io/Output.writeVarInt:(IZ)I
      10: pop
      11: return
      12: aload_2
      13: aload_3
      14: arraylength
      15: iconst_1
      16: iadd
      17: iconst_1
      18: invokevirtual #10                 // Method com/esotericsoftware/kryo/io/Output.writeVarInt:(IZ)I
      21: pop
      22: aload_3
      23: invokevirtual #11                 // Method java/lang/Object.getClass:()Ljava/lang/Class;
      26: invokevirtual #6                  // Method java/lang/Class.getComponentType:()Ljava/lang/Class;
      29: astore        4
      31: aload_0
      32: getfield      #12                 // Field elementsAreSameType:Z
      35: ifne          49
      38: aload         4
      40: invokevirtual #7                  // Method java/lang/Class.getModifiers:()I
      43: invokestatic  #13                 // Method java/lang/reflect/Modifier.isFinal:(I)Z
      46: ifeq          122
      49: aload_1
      50: aload         4
      52: invokevirtual #14                 // Method com/esotericsoftware/kryo/Kryo.getSerializer:(Ljava/lang/Class;)Lcom/esotericsoftware/kryo/Serializer;
      55: astore        5
      57: aload         5
      59: aload_1
      60: aload_0
      61: getfield      #15                 // Field generics:[Ljava/lang/Class;
      64: invokevirtual #16                 // Method com/esotericsoftware/kryo/Serializer.setGenerics:(Lcom/esotericsoftware/kryo/Kryo;[Ljava/lang/Class;)V
      67: iconst_0
      68: istore        6
      70: aload_3
      71: arraylength
      72: istore        7
      74: iload         6
      76: iload         7
      78: if_icmpge     119
      81: aload_0
      82: getfield      #3                  // Field elementsCanBeNull:Z
      85: ifeq          102
      88: aload_1
      89: aload_2
      90: aload_3
      91: iload         6
      93: aaload
      94: aload         5
      96: invokevirtual #17                 // Method com/esotericsoftware/kryo/Kryo.writeObjectOrNull:(Lcom/esotericsoftware/kryo/io/Output;Ljava/lang/Object;Lcom/esotericsoftware/kryo/Serializer;)V
      99: goto          113
     102: aload_1
     103: aload_2
     104: aload_3
     105: iload         6
     107: aaload
     108: aload         5
     110: invokevirtual #18                 // Method com/esotericsoftware/kryo/Kryo.writeObject:(Lcom/esotericsoftware/kryo/io/Output;Ljava/lang/Object;Lcom/esotericsoftware/kryo/Serializer;)V
     113: iinc          6, 1
     116: goto          74
     119: goto          181
     122: iconst_0
     123: istore        5
     125: aload_3
     126: arraylength
     127: istore        6
     129: iload         5
     131: iload         6
     133: if_icmpge     181
     136: aload_3
     137: iload         5
     139: aaload
     140: ifnull        166
     143: aload_1
     144: aload_3
     145: iload         5
     147: aaload
     148: invokevirtual #11                 // Method java/lang/Object.getClass:()Ljava/lang/Class;
     151: invokevirtual #14                 // Method com/esotericsoftware/kryo/Kryo.getSerializer:(Ljava/lang/Class;)Lcom/esotericsoftware/kryo/Serializer;
     154: astore        7
     156: aload         7
     158: aload_1
     159: aload_0
     160: getfield      #15                 // Field generics:[Ljava/lang/Class;
     163: invokevirtual #16                 // Method com/esotericsoftware/kryo/Serializer.setGenerics:(Lcom/esotericsoftware/kryo/Kryo;[Ljava/lang/Class;)V
     166: aload_1
     167: aload_2
     168: aload_3
     169: iload         5
     171: aaload
     172: invokevirtual #19                 // Method com/esotericsoftware/kryo/Kryo.writeClassAndObject:(Lcom/esotericsoftware/kryo/io/Output;Ljava/lang/Object;)V
     175: iinc          5, 1
     178: goto          129
     181: return

  public java.lang.Object[] read(com.esotericsoftware.kryo.Kryo, com.esotericsoftware.kryo.io.Input, java.lang.Class<java.lang.Object[]>);
    Code:
       0: aload_2
       1: iconst_1
       2: invokevirtual #20                 // Method com/esotericsoftware/kryo/io/Input.readVarInt:(Z)I
       5: istore        4
       7: iload         4
       9: ifne          14
      12: aconst_null
      13: areturn
      14: aload_3
      15: invokevirtual #6                  // Method java/lang/Class.getComponentType:()Ljava/lang/Class;
      18: iload         4
      20: iconst_1
      21: isub
      22: invokestatic  #21                 // Method java/lang/reflect/Array.newInstance:(Ljava/lang/Class;I)Ljava/lang/Object;
      25: checkcast     #22                 // class "[Ljava/lang/Object;"
      28: checkcast     #22                 // class "[Ljava/lang/Object;"
      31: astore        5
      33: aload_1
      34: aload         5
      36: invokevirtual #23                 // Method com/esotericsoftware/kryo/Kryo.reference:(Ljava/lang/Object;)V
      39: aload         5
      41: invokevirtual #11                 // Method java/lang/Object.getClass:()Ljava/lang/Class;
      44: invokevirtual #6                  // Method java/lang/Class.getComponentType:()Ljava/lang/Class;
      47: astore        6
      49: aload_0
      50: getfield      #12                 // Field elementsAreSameType:Z
      53: ifne          67
      56: aload         6
      58: invokevirtual #7                  // Method java/lang/Class.getModifiers:()I
      61: invokestatic  #13                 // Method java/lang/reflect/Modifier.isFinal:(I)Z
      64: ifeq          147
      67: aload_1
      68: aload         6
      70: invokevirtual #14                 // Method com/esotericsoftware/kryo/Kryo.getSerializer:(Ljava/lang/Class;)Lcom/esotericsoftware/kryo/Serializer;
      73: astore        7
      75: aload         7
      77: aload_1
      78: aload_0
      79: getfield      #15                 // Field generics:[Ljava/lang/Class;
      82: invokevirtual #16                 // Method com/esotericsoftware/kryo/Serializer.setGenerics:(Lcom/esotericsoftware/kryo/Kryo;[Ljava/lang/Class;)V
      85: iconst_0
      86: istore        8
      88: aload         5
      90: arraylength
      91: istore        9
      93: iload         8
      95: iload         9
      97: if_icmpge     144
     100: aload_0
     101: getfield      #3                  // Field elementsCanBeNull:Z
     104: ifeq          124
     107: aload         5
     109: iload         8
     111: aload_1
     112: aload_2
     113: aload         6
     115: aload         7
     117: invokevirtual #24                 // Method com/esotericsoftware/kryo/Kryo.readObjectOrNull:(Lcom/esotericsoftware/kryo/io/Input;Ljava/lang/Class;Lcom/esotericsoftware/kryo/Serializer;)Ljava/lang/Object;
     120: aastore
     121: goto          138
     124: aload         5
     126: iload         8
     128: aload_1
     129: aload_2
     130: aload         6
     132: aload         7
     134: invokevirtual #25                 // Method com/esotericsoftware/kryo/Kryo.readObject:(Lcom/esotericsoftware/kryo/io/Input;Ljava/lang/Class;Lcom/esotericsoftware/kryo/Serializer;)Ljava/lang/Object;
     137: aastore
     138: iinc          8, 1
     141: goto          93
     144: goto          222
     147: iconst_0
     148: istore        7
     150: aload         5
     152: arraylength
     153: istore        8
     155: iload         7
     157: iload         8
     159: if_icmpge     222
     162: aload_1
     163: aload_2
     164: invokevirtual #26                 // Method com/esotericsoftware/kryo/Kryo.readClass:(Lcom/esotericsoftware/kryo/io/Input;)Lcom/esotericsoftware/kryo/Registration;
     167: astore        9
     169: aload         9
     171: ifnull        210
     174: aload         9
     176: invokevirtual #27                 // Method com/esotericsoftware/kryo/Registration.getSerializer:()Lcom/esotericsoftware/kryo/Serializer;
     179: aload_1
     180: aload_0
     181: getfield      #15                 // Field generics:[Ljava/lang/Class;
     184: invokevirtual #16                 // Method com/esotericsoftware/kryo/Serializer.setGenerics:(Lcom/esotericsoftware/kryo/Kryo;[Ljava/lang/Class;)V
     187: aload         5
     189: iload         7
     191: aload_1
     192: aload_2
     193: aload         9
     195: invokevirtual #28                 // Method com/esotericsoftware/kryo/Registration.getType:()Ljava/lang/Class;
     198: aload         9
     200: invokevirtual #27                 // Method com/esotericsoftware/kryo/Registration.getSerializer:()Lcom/esotericsoftware/kryo/Serializer;
     203: invokevirtual #25                 // Method com/esotericsoftware/kryo/Kryo.readObject:(Lcom/esotericsoftware/kryo/io/Input;Ljava/lang/Class;Lcom/esotericsoftware/kryo/Serializer;)Ljava/lang/Object;
     206: aastore
     207: goto          216
     210: aload         5
     212: iload         7
     214: aconst_null
     215: aastore
     216: iinc          7, 1
     219: goto          155
     222: aload         5
     224: areturn

  public java.lang.Object[] copy(com.esotericsoftware.kryo.Kryo, java.lang.Object[]);
    Code:
       0: aload_2
       1: invokevirtual #11                 // Method java/lang/Object.getClass:()Ljava/lang/Class;
       4: invokevirtual #6                  // Method java/lang/Class.getComponentType:()Ljava/lang/Class;
       7: aload_2
       8: arraylength
       9: invokestatic  #21                 // Method java/lang/reflect/Array.newInstance:(Ljava/lang/Class;I)Ljava/lang/Object;
      12: checkcast     #22                 // class "[Ljava/lang/Object;"
      15: checkcast     #22                 // class "[Ljava/lang/Object;"
      18: astore_3
      19: iconst_0
      20: istore        4
      22: aload_2
      23: arraylength
      24: istore        5
      26: iload         4
      28: iload         5
      30: if_icmpge     51
      33: aload_3
      34: iload         4
      36: aload_1
      37: aload_2
      38: iload         4
      40: aaload
      41: invokevirtual #29                 // Method com/esotericsoftware/kryo/Kryo.copy:(Ljava/lang/Object;)Ljava/lang/Object;
      44: aastore
      45: iinc          4, 1
      48: goto          26
      51: aload_3
      52: areturn

  public void setElementsCanBeNull(boolean);
    Code:
       0: aload_0
       1: iload_1
       2: putfield      #3                  // Field elementsCanBeNull:Z
       5: return

  public void setElementsAreSameType(boolean);
    Code:
       0: aload_0
       1: iload_1
       2: putfield      #12                 // Field elementsAreSameType:Z
       5: return

  public void setGenerics(com.esotericsoftware.kryo.Kryo, java.lang.Class[]);
    Code:
       0: getstatic     #30                 // Field com/esotericsoftware/minlog/Log.TRACE:Z
       3: ifeq          13
       6: ldc           #31                 // String kryo
       8: ldc           #32                 // String setting generics for ObjectArraySerializer
      10: invokestatic  #33                 // Method com/esotericsoftware/minlog/Log.trace:(Ljava/lang/String;Ljava/lang/String;)V
      13: aload_0
      14: aload_2
      15: putfield      #15                 // Field generics:[Ljava/lang/Class;
      18: return

  public java.lang.Object copy(com.esotericsoftware.kryo.Kryo, java.lang.Object);
    Code:
       0: aload_0
       1: aload_1
       2: aload_2
       3: checkcast     #22                 // class "[Ljava/lang/Object;"
       6: invokevirtual #34                 // Method copy:(Lcom/esotericsoftware/kryo/Kryo;[Ljava/lang/Object;)[Ljava/lang/Object;
       9: areturn

  public java.lang.Object read(com.esotericsoftware.kryo.Kryo, com.esotericsoftware.kryo.io.Input, java.lang.Class);
    Code:
       0: aload_0
       1: aload_1
       2: aload_2
       3: aload_3
       4: invokevirtual #35                 // Method read:(Lcom/esotericsoftware/kryo/Kryo;Lcom/esotericsoftware/kryo/io/Input;Ljava/lang/Class;)[Ljava/lang/Object;
       7: areturn

  public void write(com.esotericsoftware.kryo.Kryo, com.esotericsoftware.kryo.io.Output, java.lang.Object);
    Code:
       0: aload_0
       1: aload_1
       2: aload_2
       3: aload_3
       4: checkcast     #22                 // class "[Ljava/lang/Object;"
       7: invokevirtual #36                 // Method write:(Lcom/esotericsoftware/kryo/Kryo;Lcom/esotericsoftware/kryo/io/Output;[Ljava/lang/Object;)V
      10: return
}
