Compiled from "UnsafeCacheFields.java"
final class com.esotericsoftware.kryo.serializers.UnsafeCacheFields$UnsafeRegionField extends com.esotericsoftware.kryo.serializers.UnsafeCacheFields$UnsafeCachedField {
  final long len;

  static final boolean bulkReadsSupported;

  public com.esotericsoftware.kryo.serializers.UnsafeCacheFields$UnsafeRegionField(long, long);
    Code:
       0: aload_0
       1: lload_1
       2: invokespecial #2                  // Method com/esotericsoftware/kryo/serializers/UnsafeCacheFields$UnsafeCachedField."<init>":(J)V
       5: aload_0
       6: lload_3
       7: putfield      #3                  // Field len:J
      10: return

  public final void write(com.esotericsoftware.kryo.io.Output, java.lang.Object);
    Code:
       0: aload_1
       1: instanceof    #4                  // class com/esotericsoftware/kryo/io/UnsafeOutput
       4: ifeq          28
       7: aload_1
       8: checkcast     #4                  // class com/esotericsoftware/kryo/io/UnsafeOutput
      11: astore_3
      12: aload_3
      13: aload_2
      14: aload_0
      15: getfield      #5                  // Field offset:J
      18: aload_0
      19: getfield      #3                  // Field len:J
      22: invokevirtual #6                  // Method com/esotericsoftware/kryo/io/UnsafeOutput.writeBytes:(Ljava/lang/Object;JJ)V
      25: goto          150
      28: aload_1
      29: instanceof    #7                  // class com/esotericsoftware/kryo/io/UnsafeMemoryOutput
      32: ifeq          56
      35: aload_1
      36: checkcast     #7                  // class com/esotericsoftware/kryo/io/UnsafeMemoryOutput
      39: astore_3
      40: aload_3
      41: aload_2
      42: aload_0
      43: getfield      #5                  // Field offset:J
      46: aload_0
      47: getfield      #3                  // Field len:J
      50: invokevirtual #8                  // Method com/esotericsoftware/kryo/io/UnsafeMemoryOutput.writeBytes:(Ljava/lang/Object;JJ)V
      53: goto          150
      56: invokestatic  #9                  // Method com/esotericsoftware/kryo/util/UnsafeUtil.unsafe:()Lsun/misc/Unsafe;
      59: astore        5
      61: aload_0
      62: getfield      #5                  // Field offset:J
      65: lstore_3
      66: lload_3
      67: aload_0
      68: getfield      #5                  // Field offset:J
      71: aload_0
      72: getfield      #3                  // Field len:J
      75: ladd
      76: ldc2_w        #10                 // long 8l
      79: lsub
      80: lcmp
      81: ifge          104
      84: aload_1
      85: aload         5
      87: aload_2
      88: lload_3
      89: invokevirtual #12                 // Method sun/misc/Unsafe.getLong:(Ljava/lang/Object;J)J
      92: invokevirtual #13                 // Method com/esotericsoftware/kryo/io/Output.writeLong:(J)V
      95: lload_3
      96: ldc2_w        #10                 // long 8l
      99: ladd
     100: lstore_3
     101: goto          66
     104: lload_3
     105: aload_0
     106: getfield      #5                  // Field offset:J
     109: aload_0
     110: getfield      #3                  // Field len:J
     113: ladd
     114: lcmp
     115: ifge          150
     118: lload_3
     119: aload_0
     120: getfield      #5                  // Field offset:J
     123: aload_0
     124: getfield      #3                  // Field len:J
     127: ladd
     128: lcmp
     129: ifge          150
     132: aload_1
     133: aload         5
     135: aload_2
     136: lload_3
     137: invokevirtual #14                 // Method sun/misc/Unsafe.getByte:(Ljava/lang/Object;J)B
     140: invokevirtual #15                 // Method com/esotericsoftware/kryo/io/Output.write:(I)V
     143: lload_3
     144: lconst_1
     145: ladd
     146: lstore_3
     147: goto          118
     150: return

  public final void read(com.esotericsoftware.kryo.io.Input, java.lang.Object);
    Code:
       0: aload_0
       1: aload_1
       2: aload_2
       3: invokespecial #16                 // Method readSlow:(Lcom/esotericsoftware/kryo/io/Input;Ljava/lang/Object;)V
       6: return

  private void readSlow(com.esotericsoftware.kryo.io.Input, java.lang.Object);
    Code:
       0: invokestatic  #9                  // Method com/esotericsoftware/kryo/util/UnsafeUtil.unsafe:()Lsun/misc/Unsafe;
       3: astore        5
       5: aload_0
       6: getfield      #5                  // Field offset:J
       9: lstore_3
      10: lload_3
      11: aload_0
      12: getfield      #5                  // Field offset:J
      15: aload_0
      16: getfield      #3                  // Field len:J
      19: ladd
      20: ldc2_w        #10                 // long 8l
      23: lsub
      24: lcmp
      25: ifge          48
      28: aload         5
      30: aload_2
      31: lload_3
      32: aload_1
      33: invokevirtual #17                 // Method com/esotericsoftware/kryo/io/Input.readLong:()J
      36: invokevirtual #18                 // Method sun/misc/Unsafe.putLong:(Ljava/lang/Object;JJ)V
      39: lload_3
      40: ldc2_w        #10                 // long 8l
      43: ladd
      44: lstore_3
      45: goto          10
      48: lload_3
      49: aload_0
      50: getfield      #5                  // Field offset:J
      53: aload_0
      54: getfield      #3                  // Field len:J
      57: ladd
      58: lcmp
      59: ifge          94
      62: lload_3
      63: aload_0
      64: getfield      #5                  // Field offset:J
      67: aload_0
      68: getfield      #3                  // Field len:J
      71: ladd
      72: lcmp
      73: ifge          94
      76: aload         5
      78: aload_2
      79: lload_3
      80: aload_1
      81: invokevirtual #19                 // Method com/esotericsoftware/kryo/io/Input.readByte:()B
      84: invokevirtual #20                 // Method sun/misc/Unsafe.putByte:(Ljava/lang/Object;JB)V
      87: lload_3
      88: lconst_1
      89: ladd
      90: lstore_3
      91: goto          62
      94: return

  public void copy(java.lang.Object, java.lang.Object);
    Code:
       0: invokestatic  #9                  // Method com/esotericsoftware/kryo/util/UnsafeUtil.unsafe:()Lsun/misc/Unsafe;
       3: aload_1
       4: aload_0
       5: getfield      #5                  // Field offset:J
       8: aload_2
       9: aload_0
      10: getfield      #5                  // Field offset:J
      13: aload_0
      14: getfield      #3                  // Field len:J
      17: invokevirtual #21                 // Method sun/misc/Unsafe.copyMemory:(Ljava/lang/Object;JLjava/lang/Object;JJ)V
      20: return
}
