Compiled from "NonNullDefaultAwareTypeAnnotationWalker.java"
public class org.eclipse.jdt.internal.compiler.classfmt.NonNullDefaultAwareTypeAnnotationWalker extends org.eclipse.jdt.internal.compiler.classfmt.TypeAnnotationWalker {
  private int defaultNullness;

  private boolean atDefaultLocation;

  private boolean nextIsDefaultLocation;

  private boolean atTypeBound;

  private boolean nextIsTypeBound;

  private boolean isEmpty;

  org.eclipse.jdt.internal.compiler.env.IBinaryAnnotation nonNullAnnotation;

  org.eclipse.jdt.internal.compiler.lookup.LookupEnvironment environment;

  public org.eclipse.jdt.internal.compiler.classfmt.NonNullDefaultAwareTypeAnnotationWalker(org.eclipse.jdt.internal.compiler.env.IBinaryTypeAnnotation[], int, org.eclipse.jdt.internal.compiler.lookup.LookupEnvironment);
    Code:
       0: aload_0
       1: aload_1
       2: invokespecial #20                 // Method org/eclipse/jdt/internal/compiler/classfmt/TypeAnnotationWalker."<init>":([Lorg/eclipse/jdt/internal/compiler/env/IBinaryTypeAnnotation;)V
       5: aload_0
       6: aload_3
       7: invokestatic  #23                 // Method getNonNullAnnotation:(Lorg/eclipse/jdt/internal/compiler/lookup/LookupEnvironment;)Lorg/eclipse/jdt/internal/compiler/env/IBinaryAnnotation;
      10: putfield      #27                 // Field nonNullAnnotation:Lorg/eclipse/jdt/internal/compiler/env/IBinaryAnnotation;
      13: aload_0
      14: iload_2
      15: putfield      #29                 // Field defaultNullness:I
      18: aload_0
      19: aload_3
      20: putfield      #31                 // Field environment:Lorg/eclipse/jdt/internal/compiler/lookup/LookupEnvironment;
      23: return

  public org.eclipse.jdt.internal.compiler.classfmt.NonNullDefaultAwareTypeAnnotationWalker(int, org.eclipse.jdt.internal.compiler.lookup.LookupEnvironment);
    Code:
       0: aload_0
       1: iload_1
       2: aload_2
       3: invokestatic  #23                 // Method getNonNullAnnotation:(Lorg/eclipse/jdt/internal/compiler/lookup/LookupEnvironment;)Lorg/eclipse/jdt/internal/compiler/env/IBinaryAnnotation;
       6: iconst_0
       7: iconst_0
       8: aload_2
       9: invokespecial #40                 // Method "<init>":(ILorg/eclipse/jdt/internal/compiler/env/IBinaryAnnotation;ZZLorg/eclipse/jdt/internal/compiler/lookup/LookupEnvironment;)V
      12: return

  org.eclipse.jdt.internal.compiler.classfmt.NonNullDefaultAwareTypeAnnotationWalker(org.eclipse.jdt.internal.compiler.env.IBinaryTypeAnnotation[], long, int, int, org.eclipse.jdt.internal.compiler.env.IBinaryAnnotation, boolean, boolean, org.eclipse.jdt.internal.compiler.lookup.LookupEnvironment);
    Code:
       0: aload_0
       1: aload_1
       2: lload_2
       3: iload         4
       5: invokespecial #44                 // Method org/eclipse/jdt/internal/compiler/classfmt/TypeAnnotationWalker."<init>":([Lorg/eclipse/jdt/internal/compiler/env/IBinaryTypeAnnotation;JI)V
       8: aload_0
       9: iload         5
      11: putfield      #29                 // Field defaultNullness:I
      14: aload_0
      15: aload         6
      17: putfield      #27                 // Field nonNullAnnotation:Lorg/eclipse/jdt/internal/compiler/env/IBinaryAnnotation;
      20: aload_0
      21: iload         7
      23: putfield      #47                 // Field atDefaultLocation:Z
      26: aload_0
      27: iload         8
      29: putfield      #49                 // Field atTypeBound:Z
      32: aload_0
      33: aload         9
      35: putfield      #31                 // Field environment:Lorg/eclipse/jdt/internal/compiler/lookup/LookupEnvironment;
      38: return

  org.eclipse.jdt.internal.compiler.classfmt.NonNullDefaultAwareTypeAnnotationWalker(int, org.eclipse.jdt.internal.compiler.env.IBinaryAnnotation, boolean, boolean, org.eclipse.jdt.internal.compiler.lookup.LookupEnvironment);
    Code:
       0: aload_0
       1: aconst_null
       2: lconst_0
       3: iconst_0
       4: invokespecial #44                 // Method org/eclipse/jdt/internal/compiler/classfmt/TypeAnnotationWalker."<init>":([Lorg/eclipse/jdt/internal/compiler/env/IBinaryTypeAnnotation;JI)V
       7: aload_0
       8: aload_2
       9: putfield      #27                 // Field nonNullAnnotation:Lorg/eclipse/jdt/internal/compiler/env/IBinaryAnnotation;
      12: aload_0
      13: iload_1
      14: putfield      #29                 // Field defaultNullness:I
      17: aload_0
      18: iload_3
      19: putfield      #47                 // Field atDefaultLocation:Z
      22: aload_0
      23: iload         4
      25: putfield      #49                 // Field atTypeBound:Z
      28: aload_0
      29: iconst_1
      30: putfield      #54                 // Field isEmpty:Z
      33: aload_0
      34: aload         5
      36: putfield      #31                 // Field environment:Lorg/eclipse/jdt/internal/compiler/lookup/LookupEnvironment;
      39: return

  private static org.eclipse.jdt.internal.compiler.env.IBinaryAnnotation getNonNullAnnotation(org.eclipse.jdt.internal.compiler.lookup.LookupEnvironment);
    Code:
       0: bipush        76
       2: aload_0
       3: invokevirtual #56                 // Method org/eclipse/jdt/internal/compiler/lookup/LookupEnvironment.getNonNullAnnotationName:()[[C
       6: bipush        47
       8: invokestatic  #62                 // Method org/eclipse/jdt/core/compiler/CharOperation.concatWith:([[CC)[C
      11: bipush        59
      13: invokestatic  #68                 // Method org/eclipse/jdt/core/compiler/CharOperation.concat:(C[CC)[C
      16: astore_1
      17: new           #72                 // class org/eclipse/jdt/internal/compiler/classfmt/NonNullDefaultAwareTypeAnnotationWalker$1
      20: dup
      21: aload_1
      22: invokespecial #74                 // Method org/eclipse/jdt/internal/compiler/classfmt/NonNullDefaultAwareTypeAnnotationWalker$1."<init>":([C)V
      25: areturn

  protected org.eclipse.jdt.internal.compiler.classfmt.TypeAnnotationWalker restrict(long, int);
    Code:
       0: aload_0
       1: getfield      #81                 // Field matches:J
       4: lload_1
       5: lcmp
       6: ifne          55
       9: aload_0
      10: getfield      #84                 // Field pathPtr:I
      13: iload_3
      14: if_icmpne     55
      17: aload_0
      18: getfield      #47                 // Field atDefaultLocation:Z
      21: aload_0
      22: getfield      #87                 // Field nextIsDefaultLocation:Z
      25: if_icmpne     55
      28: aload_0
      29: getfield      #49                 // Field atTypeBound:Z
      32: aload_0
      33: getfield      #89                 // Field nextIsTypeBound:Z
      36: if_icmpne     55
      39: aload_0
      40: astore        5
      42: aload_0
      43: iconst_0
      44: putfield      #87                 // Field nextIsDefaultLocation:Z
      47: aload_0
      48: iconst_0
      49: putfield      #89                 // Field nextIsTypeBound:Z
      52: aload         5
      54: areturn
      55: lload_1
      56: lconst_0
      57: lcmp
      58: ifeq          76
      61: aload_0
      62: getfield      #91                 // Field typeAnnotations:[Lorg/eclipse/jdt/internal/compiler/env/IBinaryTypeAnnotation;
      65: ifnull        76
      68: aload_0
      69: getfield      #91                 // Field typeAnnotations:[Lorg/eclipse/jdt/internal/compiler/env/IBinaryTypeAnnotation;
      72: arraylength
      73: ifne          118
      76: new           #1                  // class org/eclipse/jdt/internal/compiler/classfmt/NonNullDefaultAwareTypeAnnotationWalker
      79: dup
      80: aload_0
      81: getfield      #29                 // Field defaultNullness:I
      84: aload_0
      85: getfield      #27                 // Field nonNullAnnotation:Lorg/eclipse/jdt/internal/compiler/env/IBinaryAnnotation;
      88: aload_0
      89: getfield      #87                 // Field nextIsDefaultLocation:Z
      92: aload_0
      93: getfield      #89                 // Field nextIsTypeBound:Z
      96: aload_0
      97: getfield      #31                 // Field environment:Lorg/eclipse/jdt/internal/compiler/lookup/LookupEnvironment;
     100: invokespecial #40                 // Method "<init>":(ILorg/eclipse/jdt/internal/compiler/env/IBinaryAnnotation;ZZLorg/eclipse/jdt/internal/compiler/lookup/LookupEnvironment;)V
     103: astore        5
     105: aload_0
     106: iconst_0
     107: putfield      #87                 // Field nextIsDefaultLocation:Z
     110: aload_0
     111: iconst_0
     112: putfield      #89                 // Field nextIsTypeBound:Z
     115: aload         5
     117: areturn
     118: new           #1                  // class org/eclipse/jdt/internal/compiler/classfmt/NonNullDefaultAwareTypeAnnotationWalker
     121: dup
     122: aload_0
     123: getfield      #91                 // Field typeAnnotations:[Lorg/eclipse/jdt/internal/compiler/env/IBinaryTypeAnnotation;
     126: lload_1
     127: iload_3
     128: aload_0
     129: getfield      #29                 // Field defaultNullness:I
     132: aload_0
     133: getfield      #27                 // Field nonNullAnnotation:Lorg/eclipse/jdt/internal/compiler/env/IBinaryAnnotation;
     136: aload_0
     137: getfield      #87                 // Field nextIsDefaultLocation:Z
     140: aload_0
     141: getfield      #89                 // Field nextIsTypeBound:Z
     144: aload_0
     145: getfield      #31                 // Field environment:Lorg/eclipse/jdt/internal/compiler/lookup/LookupEnvironment;
     148: invokespecial #93                 // Method "<init>":([Lorg/eclipse/jdt/internal/compiler/env/IBinaryTypeAnnotation;JIILorg/eclipse/jdt/internal/compiler/env/IBinaryAnnotation;ZZLorg/eclipse/jdt/internal/compiler/lookup/LookupEnvironment;)V
     151: astore        5
     153: aload_0
     154: iconst_0
     155: putfield      #87                 // Field nextIsDefaultLocation:Z
     158: aload_0
     159: iconst_0
     160: putfield      #89                 // Field nextIsTypeBound:Z
     163: aload         5
     165: areturn
     166: astore        4
     168: aload_0
     169: iconst_0
     170: putfield      #87                 // Field nextIsDefaultLocation:Z
     173: aload_0
     174: iconst_0
     175: putfield      #89                 // Field nextIsTypeBound:Z
     178: aload         4
     180: athrow
    Exception table:
       from    to  target type
           0    42   166   any
          55   105   166   any
         118   153   166   any

  public org.eclipse.jdt.internal.compiler.classfmt.TypeAnnotationWalker toMethodParameter(short);
    Code:
       0: aload_0
       1: getfield      #54                 // Field isEmpty:Z
       4: ifeq          20
       7: aload_0
       8: aload_0
       9: getfield      #81                 // Field matches:J
      12: aload_0
      13: getfield      #84                 // Field pathPtr:I
      16: invokevirtual #100                // Method restrict:(JI)Lorg/eclipse/jdt/internal/compiler/classfmt/TypeAnnotationWalker;
      19: areturn
      20: aload_0
      21: iload_1
      22: invokespecial #102                // Method org/eclipse/jdt/internal/compiler/classfmt/TypeAnnotationWalker.toMethodParameter:(S)Lorg/eclipse/jdt/internal/compiler/classfmt/TypeAnnotationWalker;
      25: areturn

  public org.eclipse.jdt.internal.compiler.classfmt.TypeAnnotationWalker toMethodReturn();
    Code:
       0: aload_0
       1: getfield      #54                 // Field isEmpty:Z
       4: ifeq          20
       7: aload_0
       8: aload_0
       9: getfield      #81                 // Field matches:J
      12: aload_0
      13: getfield      #84                 // Field pathPtr:I
      16: invokevirtual #100                // Method restrict:(JI)Lorg/eclipse/jdt/internal/compiler/classfmt/TypeAnnotationWalker;
      19: areturn
      20: aload_0
      21: invokespecial #108                // Method org/eclipse/jdt/internal/compiler/classfmt/TypeAnnotationWalker.toMethodReturn:()Lorg/eclipse/jdt/internal/compiler/classfmt/TypeAnnotationWalker;
      24: areturn

  public org.eclipse.jdt.internal.compiler.classfmt.TypeAnnotationWalker toTypeBound(short);
    Code:
       0: aload_0
       1: aload_0
       2: getfield      #29                 // Field defaultNullness:I
       5: sipush        256
       8: iand
       9: ifeq          16
      12: iconst_1
      13: goto          17
      16: iconst_0
      17: putfield      #87                 // Field nextIsDefaultLocation:Z
      20: aload_0
      21: iconst_1
      22: putfield      #89                 // Field nextIsTypeBound:Z
      25: aload_0
      26: getfield      #54                 // Field isEmpty:Z
      29: ifeq          45
      32: aload_0
      33: aload_0
      34: getfield      #81                 // Field matches:J
      37: aload_0
      38: getfield      #84                 // Field pathPtr:I
      41: invokevirtual #100                // Method restrict:(JI)Lorg/eclipse/jdt/internal/compiler/classfmt/TypeAnnotationWalker;
      44: areturn
      45: aload_0
      46: iload_1
      47: invokespecial #111                // Method org/eclipse/jdt/internal/compiler/classfmt/TypeAnnotationWalker.toTypeBound:(S)Lorg/eclipse/jdt/internal/compiler/classfmt/TypeAnnotationWalker;
      50: areturn

  public org.eclipse.jdt.internal.compiler.classfmt.TypeAnnotationWalker toTypeParameterBounds(boolean, int);
    Code:
       0: aload_0
       1: aload_0
       2: getfield      #29                 // Field defaultNullness:I
       5: sipush        256
       8: iand
       9: ifeq          16
      12: iconst_1
      13: goto          17
      16: iconst_0
      17: putfield      #87                 // Field nextIsDefaultLocation:Z
      20: aload_0
      21: iconst_1
      22: putfield      #89                 // Field nextIsTypeBound:Z
      25: aload_0
      26: getfield      #54                 // Field isEmpty:Z
      29: ifeq          45
      32: aload_0
      33: aload_0
      34: getfield      #81                 // Field matches:J
      37: aload_0
      38: getfield      #84                 // Field pathPtr:I
      41: invokevirtual #100                // Method restrict:(JI)Lorg/eclipse/jdt/internal/compiler/classfmt/TypeAnnotationWalker;
      44: areturn
      45: aload_0
      46: iload_1
      47: iload_2
      48: invokespecial #116                // Method org/eclipse/jdt/internal/compiler/classfmt/TypeAnnotationWalker.toTypeParameterBounds:(ZI)Lorg/eclipse/jdt/internal/compiler/classfmt/TypeAnnotationWalker;
      51: areturn

  public org.eclipse.jdt.internal.compiler.classfmt.TypeAnnotationWalker toTypeArgument(int);
    Code:
       0: aload_0
       1: aload_0
       2: getfield      #29                 // Field defaultNullness:I
       5: bipush        64
       7: iand
       8: ifeq          15
      11: iconst_1
      12: goto          16
      15: iconst_0
      16: putfield      #87                 // Field nextIsDefaultLocation:Z
      19: aload_0
      20: iconst_0
      21: putfield      #89                 // Field nextIsTypeBound:Z
      24: aload_0
      25: getfield      #54                 // Field isEmpty:Z
      28: ifeq          44
      31: aload_0
      32: aload_0
      33: getfield      #81                 // Field matches:J
      36: aload_0
      37: getfield      #84                 // Field pathPtr:I
      40: invokevirtual #100                // Method restrict:(JI)Lorg/eclipse/jdt/internal/compiler/classfmt/TypeAnnotationWalker;
      43: areturn
      44: aload_0
      45: iload_1
      46: invokespecial #122                // Method org/eclipse/jdt/internal/compiler/classfmt/TypeAnnotationWalker.toTypeArgument:(I)Lorg/eclipse/jdt/internal/compiler/classfmt/TypeAnnotationWalker;
      49: areturn

  public org.eclipse.jdt.internal.compiler.classfmt.TypeAnnotationWalker toTypeParameter(boolean, int);
    Code:
       0: aload_0
       1: aload_0
       2: getfield      #29                 // Field defaultNullness:I
       5: sipush        128
       8: iand
       9: ifeq          16
      12: iconst_1
      13: goto          17
      16: iconst_0
      17: putfield      #87                 // Field nextIsDefaultLocation:Z
      20: aload_0
      21: iconst_0
      22: putfield      #89                 // Field nextIsTypeBound:Z
      25: aload_0
      26: getfield      #54                 // Field isEmpty:Z
      29: ifeq          45
      32: aload_0
      33: aload_0
      34: getfield      #81                 // Field matches:J
      37: aload_0
      38: getfield      #84                 // Field pathPtr:I
      41: invokevirtual #100                // Method restrict:(JI)Lorg/eclipse/jdt/internal/compiler/classfmt/TypeAnnotationWalker;
      44: areturn
      45: aload_0
      46: iload_1
      47: iload_2
      48: invokespecial #126                // Method org/eclipse/jdt/internal/compiler/classfmt/TypeAnnotationWalker.toTypeParameter:(ZI)Lorg/eclipse/jdt/internal/compiler/classfmt/TypeAnnotationWalker;
      51: areturn

  public org.eclipse.jdt.internal.compiler.env.IBinaryAnnotation[] getAnnotationsAtCursor(int);
    Code:
       0: aload_0
       1: getfield      #54                 // Field isEmpty:Z
       4: ifeq          11
       7: aconst_null
       8: goto          16
      11: aload_0
      12: iload_1
      13: invokespecial #130                // Method org/eclipse/jdt/internal/compiler/classfmt/TypeAnnotationWalker.getAnnotationsAtCursor:(I)[Lorg/eclipse/jdt/internal/compiler/env/IBinaryAnnotation;
      16: astore_2
      17: aload_0
      18: getfield      #47                 // Field atDefaultLocation:Z
      21: ifeq          106
      24: iload_1
      25: iconst_m1
      26: if_icmpeq     106
      29: aload_0
      30: getfield      #49                 // Field atTypeBound:Z
      33: ifeq          41
      36: iload_1
      37: iconst_1
      38: if_icmpeq     106
      41: aload_2
      42: ifnull        50
      45: aload_2
      46: arraylength
      47: ifne          62
      50: iconst_1
      51: anewarray     #132                // class org/eclipse/jdt/internal/compiler/env/IBinaryAnnotation
      54: dup
      55: iconst_0
      56: aload_0
      57: getfield      #27                 // Field nonNullAnnotation:Lorg/eclipse/jdt/internal/compiler/env/IBinaryAnnotation;
      60: aastore
      61: areturn
      62: aload_0
      63: getfield      #31                 // Field environment:Lorg/eclipse/jdt/internal/compiler/lookup/LookupEnvironment;
      66: aload_2
      67: invokevirtual #134                // Method org/eclipse/jdt/internal/compiler/lookup/LookupEnvironment.containsNullTypeAnnotation:([Lorg/eclipse/jdt/internal/compiler/env/IBinaryAnnotation;)Z
      70: ifeq          75
      73: aload_2
      74: areturn
      75: aload_2
      76: arraylength
      77: istore_3
      78: iload_3
      79: iconst_1
      80: iadd
      81: anewarray     #132                // class org/eclipse/jdt/internal/compiler/env/IBinaryAnnotation
      84: astore        4
      86: aload_2
      87: iconst_0
      88: aload         4
      90: iconst_0
      91: iload_3
      92: invokestatic  #138                // Method java/lang/System.arraycopy:(Ljava/lang/Object;ILjava/lang/Object;II)V
      95: aload         4
      97: iload_3
      98: aload_0
      99: getfield      #27                 // Field nonNullAnnotation:Lorg/eclipse/jdt/internal/compiler/env/IBinaryAnnotation;
     102: aastore
     103: aload         4
     105: areturn
     106: aload_2
     107: areturn
}
