Compiled from "RewriteCond.java"
public class org.apache.catalina.valves.rewrite.RewriteCond$ResourceCondition extends org.apache.catalina.valves.rewrite.RewriteCond$Condition {
  public int type;

  public org.apache.catalina.valves.rewrite.RewriteCond$ResourceCondition();
    Code:
       0: aload_0
       1: invokespecial #1                  // Method org/apache/catalina/valves/rewrite/RewriteCond$Condition."<init>":()V
       4: aload_0
       5: iconst_0
       6: putfield      #2                  // Field type:I
       9: return

  public boolean evaluate(java.lang.String, org.apache.catalina.valves.rewrite.Resolver);
    Code:
       0: aload_2
       1: aload_0
       2: getfield      #2                  // Field type:I
       5: aload_1
       6: invokevirtual #3                  // Method org/apache/catalina/valves/rewrite/Resolver.resolveResource:(ILjava/lang/String;)Z
       9: ireturn
}
