Compiled from "JTreeASTModel.java"
public class org.stringtemplate.v4.gui.JTreeASTModel implements javax.swing.tree.TreeModel {
  org.antlr.runtime.tree.TreeAdaptor adaptor;

  java.lang.Object root;

  public org.stringtemplate.v4.gui.JTreeASTModel(org.antlr.runtime.tree.TreeAdaptor, java.lang.Object);
    Code:
       0: aload_0
       1: invokespecial #1                  // Method java/lang/Object."<init>":()V
       4: aload_0
       5: aload_1
       6: putfield      #2                  // Field adaptor:Lorg/antlr/runtime/tree/TreeAdaptor;
       9: aload_0
      10: aload_2
      11: putfield      #3                  // Field root:Ljava/lang/Object;
      14: return

  public org.stringtemplate.v4.gui.JTreeASTModel(java.lang.Object);
    Code:
       0: aload_0
       1: invokespecial #1                  // Method java/lang/Object."<init>":()V
       4: aload_0
       5: new           #4                  // class org/antlr/runtime/tree/CommonTreeAdaptor
       8: dup
       9: invokespecial #5                  // Method org/antlr/runtime/tree/CommonTreeAdaptor."<init>":()V
      12: putfield      #2                  // Field adaptor:Lorg/antlr/runtime/tree/TreeAdaptor;
      15: aload_0
      16: aload_1
      17: putfield      #3                  // Field root:Ljava/lang/Object;
      20: return

  public int getChildCount(java.lang.Object);
    Code:
       0: aload_0
       1: getfield      #2                  // Field adaptor:Lorg/antlr/runtime/tree/TreeAdaptor;
       4: aload_1
       5: invokeinterface #6,  2            // InterfaceMethod org/antlr/runtime/tree/TreeAdaptor.getChildCount:(Ljava/lang/Object;)I
      10: ireturn

  public int getIndexOfChild(java.lang.Object, java.lang.Object);
    Code:
       0: aload_1
       1: ifnonnull     6
       4: iconst_m1
       5: ireturn
       6: aload_0
       7: getfield      #2                  // Field adaptor:Lorg/antlr/runtime/tree/TreeAdaptor;
      10: aload_2
      11: invokeinterface #7,  2            // InterfaceMethod org/antlr/runtime/tree/TreeAdaptor.getChildIndex:(Ljava/lang/Object;)I
      16: ireturn

  public java.lang.Object getChild(java.lang.Object, int);
    Code:
       0: aload_0
       1: getfield      #2                  // Field adaptor:Lorg/antlr/runtime/tree/TreeAdaptor;
       4: aload_1
       5: iload_2
       6: invokeinterface #8,  3            // InterfaceMethod org/antlr/runtime/tree/TreeAdaptor.getChild:(Ljava/lang/Object;I)Ljava/lang/Object;
      11: areturn

  public boolean isLeaf(java.lang.Object);
    Code:
       0: aload_0
       1: aload_1
       2: invokevirtual #9                  // Method getChildCount:(Ljava/lang/Object;)I
       5: ifne          12
       8: iconst_1
       9: goto          13
      12: iconst_0
      13: ireturn

  public java.lang.Object getRoot();
    Code:
       0: aload_0
       1: getfield      #3                  // Field root:Ljava/lang/Object;
       4: areturn

  public void valueForPathChanged(javax.swing.tree.TreePath, java.lang.Object);
    Code:
       0: return

  public void addTreeModelListener(javax.swing.event.TreeModelListener);
    Code:
       0: return

  public void removeTreeModelListener(javax.swing.event.TreeModelListener);
    Code:
       0: return
}
