Compiled from "FunctionClassDescriptor.kt"
public final class kotlin.reflect.jvm.internal.impl.builtins.functions.FunctionClassDescriptor$Kind extends java.lang.Enum<kotlin.reflect.jvm.internal.impl.builtins.functions.FunctionClassDescriptor$Kind> {
  public static final kotlin.reflect.jvm.internal.impl.builtins.functions.FunctionClassDescriptor$Kind Function;

  public static final kotlin.reflect.jvm.internal.impl.builtins.functions.FunctionClassDescriptor$Kind SuspendFunction;

  public static final kotlin.reflect.jvm.internal.impl.builtins.functions.FunctionClassDescriptor$Kind KFunction;

  public static final kotlin.reflect.jvm.internal.impl.builtins.functions.FunctionClassDescriptor$Kind KSuspendFunction;

  private static final kotlin.reflect.jvm.internal.impl.builtins.functions.FunctionClassDescriptor$Kind[] $VALUES;

  private final kotlin.reflect.jvm.internal.impl.name.FqName packageFqName;

  private final java.lang.String classNamePrefix;

  public static final kotlin.reflect.jvm.internal.impl.builtins.functions.FunctionClassDescriptor$Kind$Companion Companion;

  static {};
    Code:
       0: iconst_4
       1: anewarray     #17                 // class kotlin/reflect/jvm/internal/impl/builtins/functions/FunctionClassDescriptor$Kind
       4: dup
       5: dup
       6: iconst_0
       7: new           #17                 // class kotlin/reflect/jvm/internal/impl/builtins/functions/FunctionClassDescriptor$Kind
      10: dup
      11: ldc           #3                  // String Function
      13: iconst_0
      14: getstatic     #21                 // Field kotlin/reflect/jvm/internal/impl/builtins/KotlinBuiltIns.BUILT_INS_PACKAGE_FQ_NAME:Lkotlin/reflect/jvm/internal/impl/name/FqName;
      17: dup
      18: ldc           #1                  // String BUILT_INS_PACKAGE_FQ_NAME
      20: invokestatic  #38                 // Method kotlin/jvm/internal/Intrinsics.checkExpressionValueIsNotNull:(Ljava/lang/Object;Ljava/lang/String;)V
      23: ldc           #3                  // String Function
      25: invokespecial #41                 // Method "<init>":(Ljava/lang/String;ILkotlin/reflect/jvm/internal/impl/name/FqName;Ljava/lang/String;)V
      28: dup
      29: putstatic     #24                 // Field Function:Lkotlin/reflect/jvm/internal/impl/builtins/functions/FunctionClassDescriptor$Kind;
      32: aastore
      33: dup
      34: iconst_1
      35: new           #17                 // class kotlin/reflect/jvm/internal/impl/builtins/functions/FunctionClassDescriptor$Kind
      38: dup
      39: ldc           #7                  // String SuspendFunction
      41: iconst_1
      42: getstatic     #30                 // Field kotlin/reflect/jvm/internal/impl/resolve/DescriptorUtils.COROUTINES_PACKAGE_FQ_NAME_RELEASE:Lkotlin/reflect/jvm/internal/impl/name/FqName;
      45: dup
      46: ldc           #2                  // String COROUTINES_PACKAGE_FQ_NAME_RELEASE
      48: invokestatic  #38                 // Method kotlin/jvm/internal/Intrinsics.checkExpressionValueIsNotNull:(Ljava/lang/Object;Ljava/lang/String;)V
      51: ldc           #7                  // String SuspendFunction
      53: invokespecial #41                 // Method "<init>":(Ljava/lang/String;ILkotlin/reflect/jvm/internal/impl/name/FqName;Ljava/lang/String;)V
      56: dup
      57: putstatic     #27                 // Field SuspendFunction:Lkotlin/reflect/jvm/internal/impl/builtins/functions/FunctionClassDescriptor$Kind;
      60: aastore
      61: dup
      62: iconst_2
      63: new           #17                 // class kotlin/reflect/jvm/internal/impl/builtins/functions/FunctionClassDescriptor$Kind
      66: dup
      67: ldc           #4                  // String KFunction
      69: iconst_2
      70: invokestatic  #40                 // Method kotlin/reflect/jvm/internal/impl/builtins/ReflectionTypesKt.getKOTLIN_REFLECT_FQ_NAME:()Lkotlin/reflect/jvm/internal/impl/name/FqName;
      73: ldc           #4                  // String KFunction
      75: invokespecial #41                 // Method "<init>":(Ljava/lang/String;ILkotlin/reflect/jvm/internal/impl/name/FqName;Ljava/lang/String;)V
      78: dup
      79: putstatic     #25                 // Field KFunction:Lkotlin/reflect/jvm/internal/impl/builtins/functions/FunctionClassDescriptor$Kind;
      82: aastore
      83: dup
      84: iconst_3
      85: new           #17                 // class kotlin/reflect/jvm/internal/impl/builtins/functions/FunctionClassDescriptor$Kind
      88: dup
      89: ldc           #5                  // String KSuspendFunction
      91: iconst_3
      92: invokestatic  #40                 // Method kotlin/reflect/jvm/internal/impl/builtins/ReflectionTypesKt.getKOTLIN_REFLECT_FQ_NAME:()Lkotlin/reflect/jvm/internal/impl/name/FqName;
      95: ldc           #5                  // String KSuspendFunction
      97: invokespecial #41                 // Method "<init>":(Ljava/lang/String;ILkotlin/reflect/jvm/internal/impl/name/FqName;Ljava/lang/String;)V
     100: dup
     101: putstatic     #26                 // Field KSuspendFunction:Lkotlin/reflect/jvm/internal/impl/builtins/functions/FunctionClassDescriptor$Kind;
     104: aastore
     105: putstatic     #22                 // Field $VALUES:[Lkotlin/reflect/jvm/internal/impl/builtins/functions/FunctionClassDescriptor$Kind;
     108: new           #18                 // class kotlin/reflect/jvm/internal/impl/builtins/functions/FunctionClassDescriptor$Kind$Companion
     111: dup
     112: aconst_null
     113: invokespecial #42                 // Method kotlin/reflect/jvm/internal/impl/builtins/functions/FunctionClassDescriptor$Kind$Companion."<init>":(Lkotlin/jvm/internal/DefaultConstructorMarker;)V
     116: putstatic     #23                 // Field Companion:Lkotlin/reflect/jvm/internal/impl/builtins/functions/FunctionClassDescriptor$Kind$Companion;
     119: return

  public final kotlin.reflect.jvm.internal.impl.name.Name numberedClassName(int);
    Code:
       0: new           #12                 // class java/lang/StringBuilder
       3: dup
       4: invokespecial #34                 // Method java/lang/StringBuilder."<init>":()V
       7: aload_0
       8: getfield      #28                 // Field classNamePrefix:Ljava/lang/String;
      11: invokevirtual #36                 // Method java/lang/StringBuilder.append:(Ljava/lang/String;)Ljava/lang/StringBuilder;
      14: iload_1
      15: invokevirtual #35                 // Method java/lang/StringBuilder.append:(I)Ljava/lang/StringBuilder;
      18: invokevirtual #37                 // Method java/lang/StringBuilder.toString:()Ljava/lang/String;
      21: invokestatic  #43                 // Method kotlin/reflect/jvm/internal/impl/name/Name.identifier:(Ljava/lang/String;)Lkotlin/reflect/jvm/internal/impl/name/Name;
      24: dup
      25: ldc           #6                  // String Name.identifier(\"$classNamePrefix$arity\")
      27: invokestatic  #38                 // Method kotlin/jvm/internal/Intrinsics.checkExpressionValueIsNotNull:(Ljava/lang/Object;Ljava/lang/String;)V
      30: areturn

  public final kotlin.reflect.jvm.internal.impl.name.FqName getPackageFqName();
    Code:
       0: aload_0
       1: getfield      #29                 // Field packageFqName:Lkotlin/reflect/jvm/internal/impl/name/FqName;
       4: areturn

  public final java.lang.String getClassNamePrefix();
    Code:
       0: aload_0
       1: getfield      #28                 // Field classNamePrefix:Ljava/lang/String;
       4: areturn

  protected kotlin.reflect.jvm.internal.impl.builtins.functions.FunctionClassDescriptor$Kind(kotlin.reflect.jvm.internal.impl.name.FqName, java.lang.String);
    Code:
       0: aload_3
       1: ldc           #9                  // String packageFqName
       3: invokestatic  #39                 // Method kotlin/jvm/internal/Intrinsics.checkParameterIsNotNull:(Ljava/lang/Object;Ljava/lang/String;)V
       6: aload         4
       8: ldc           #8                  // String classNamePrefix
      10: invokestatic  #39                 // Method kotlin/jvm/internal/Intrinsics.checkParameterIsNotNull:(Ljava/lang/Object;Ljava/lang/String;)V
      13: aload_0
      14: aload_1
      15: iload_2
      16: invokespecial #32                 // Method java/lang/Enum."<init>":(Ljava/lang/String;I)V
      19: aload_0
      20: aload_3
      21: putfield      #29                 // Field packageFqName:Lkotlin/reflect/jvm/internal/impl/name/FqName;
      24: aload_0
      25: aload         4
      27: putfield      #28                 // Field classNamePrefix:Ljava/lang/String;
      30: return

  public static kotlin.reflect.jvm.internal.impl.builtins.functions.FunctionClassDescriptor$Kind[] values();
    Code:
       0: getstatic     #22                 // Field $VALUES:[Lkotlin/reflect/jvm/internal/impl/builtins/functions/FunctionClassDescriptor$Kind;
       3: invokevirtual #31                 // Method "[Lkotlin/reflect/jvm/internal/impl/builtins/functions/FunctionClassDescriptor$Kind;".clone:()Ljava/lang/Object;
       6: checkcast     #10                 // class "[Lkotlin/reflect/jvm/internal/impl/builtins/functions/FunctionClassDescriptor$Kind;"
       9: areturn

  public static kotlin.reflect.jvm.internal.impl.builtins.functions.FunctionClassDescriptor$Kind valueOf(java.lang.String);
    Code:
       0: ldc           #17                 // class kotlin/reflect/jvm/internal/impl/builtins/functions/FunctionClassDescriptor$Kind
       2: aload_0
       3: invokestatic  #33                 // Method java/lang/Enum.valueOf:(Ljava/lang/Class;Ljava/lang/String;)Ljava/lang/Enum;
       6: checkcast     #17                 // class kotlin/reflect/jvm/internal/impl/builtins/functions/FunctionClassDescriptor$Kind
       9: areturn
}
