Compiled from "MapType.java"
public final class com.fasterxml.jackson.databind.type.MapType extends com.fasterxml.jackson.databind.type.MapLikeType {
  private static final long serialVersionUID;

  private com.fasterxml.jackson.databind.type.MapType(java.lang.Class<?>, com.fasterxml.jackson.databind.type.TypeBindings, com.fasterxml.jackson.databind.JavaType, com.fasterxml.jackson.databind.JavaType[], com.fasterxml.jackson.databind.JavaType, com.fasterxml.jackson.databind.JavaType, java.lang.Object, java.lang.Object, boolean);
    Code:
       0: aload_0
       1: aload_1
       2: aload_2
       3: aload_3
       4: aload         4
       6: aload         5
       8: aload         6
      10: aload         7
      12: aload         8
      14: iload         9
      16: invokespecial #1                  // Method com/fasterxml/jackson/databind/type/MapLikeType."<init>":(Ljava/lang/Class;Lcom/fasterxml/jackson/databind/type/TypeBindings;Lcom/fasterxml/jackson/databind/JavaType;[Lcom/fasterxml/jackson/databind/JavaType;Lcom/fasterxml/jackson/databind/JavaType;Lcom/fasterxml/jackson/databind/JavaType;Ljava/lang/Object;Ljava/lang/Object;Z)V
      19: return

  protected com.fasterxml.jackson.databind.type.MapType(com.fasterxml.jackson.databind.type.TypeBase, com.fasterxml.jackson.databind.JavaType, com.fasterxml.jackson.databind.JavaType);
    Code:
       0: aload_0
       1: aload_1
       2: aload_2
       3: aload_3
       4: invokespecial #2                  // Method com/fasterxml/jackson/databind/type/MapLikeType."<init>":(Lcom/fasterxml/jackson/databind/type/TypeBase;Lcom/fasterxml/jackson/databind/JavaType;Lcom/fasterxml/jackson/databind/JavaType;)V
       7: return

  public static com.fasterxml.jackson.databind.type.MapType construct(java.lang.Class<?>, com.fasterxml.jackson.databind.type.TypeBindings, com.fasterxml.jackson.databind.JavaType, com.fasterxml.jackson.databind.JavaType[], com.fasterxml.jackson.databind.JavaType, com.fasterxml.jackson.databind.JavaType);
    Code:
       0: new           #3                  // class com/fasterxml/jackson/databind/type/MapType
       3: dup
       4: aload_0
       5: aload_1
       6: aload_2
       7: aload_3
       8: aload         4
      10: aload         5
      12: aconst_null
      13: aconst_null
      14: iconst_0
      15: invokespecial #4                  // Method "<init>":(Ljava/lang/Class;Lcom/fasterxml/jackson/databind/type/TypeBindings;Lcom/fasterxml/jackson/databind/JavaType;[Lcom/fasterxml/jackson/databind/JavaType;Lcom/fasterxml/jackson/databind/JavaType;Lcom/fasterxml/jackson/databind/JavaType;Ljava/lang/Object;Ljava/lang/Object;Z)V
      18: areturn

  public static com.fasterxml.jackson.databind.type.MapType construct(java.lang.Class<?>, com.fasterxml.jackson.databind.JavaType, com.fasterxml.jackson.databind.JavaType);
    Code:
       0: aload_0
       1: invokevirtual #5                  // Method java/lang/Class.getTypeParameters:()[Ljava/lang/reflect/TypeVariable;
       4: astore_3
       5: aload_3
       6: ifnull        15
       9: aload_3
      10: arraylength
      11: iconst_2
      12: if_icmpeq     23
      15: invokestatic  #6                  // Method com/fasterxml/jackson/databind/type/TypeBindings.emptyBindings:()Lcom/fasterxml/jackson/databind/type/TypeBindings;
      18: astore        4
      20: goto          31
      23: aload_0
      24: aload_1
      25: aload_2
      26: invokestatic  #7                  // Method com/fasterxml/jackson/databind/type/TypeBindings.create:(Ljava/lang/Class;Lcom/fasterxml/jackson/databind/JavaType;Lcom/fasterxml/jackson/databind/JavaType;)Lcom/fasterxml/jackson/databind/type/TypeBindings;
      29: astore        4
      31: new           #3                  // class com/fasterxml/jackson/databind/type/MapType
      34: dup
      35: aload_0
      36: aload         4
      38: aload_0
      39: invokestatic  #8                  // Method _bogusSuperClass:(Ljava/lang/Class;)Lcom/fasterxml/jackson/databind/JavaType;
      42: aconst_null
      43: aload_1
      44: aload_2
      45: aconst_null
      46: aconst_null
      47: iconst_0
      48: invokespecial #4                  // Method "<init>":(Ljava/lang/Class;Lcom/fasterxml/jackson/databind/type/TypeBindings;Lcom/fasterxml/jackson/databind/JavaType;[Lcom/fasterxml/jackson/databind/JavaType;Lcom/fasterxml/jackson/databind/JavaType;Lcom/fasterxml/jackson/databind/JavaType;Ljava/lang/Object;Ljava/lang/Object;Z)V
      51: areturn

  protected com.fasterxml.jackson.databind.JavaType _narrow(java.lang.Class<?>);
    Code:
       0: new           #3                  // class com/fasterxml/jackson/databind/type/MapType
       3: dup
       4: aload_1
       5: aload_0
       6: getfield      #9                  // Field _bindings:Lcom/fasterxml/jackson/databind/type/TypeBindings;
       9: aload_0
      10: getfield      #10                 // Field _superClass:Lcom/fasterxml/jackson/databind/JavaType;
      13: aload_0
      14: getfield      #11                 // Field _superInterfaces:[Lcom/fasterxml/jackson/databind/JavaType;
      17: aload_0
      18: getfield      #12                 // Field _keyType:Lcom/fasterxml/jackson/databind/JavaType;
      21: aload_0
      22: getfield      #13                 // Field _valueType:Lcom/fasterxml/jackson/databind/JavaType;
      25: aload_0
      26: getfield      #14                 // Field _valueHandler:Ljava/lang/Object;
      29: aload_0
      30: getfield      #15                 // Field _typeHandler:Ljava/lang/Object;
      33: aload_0
      34: getfield      #16                 // Field _asStatic:Z
      37: invokespecial #4                  // Method "<init>":(Ljava/lang/Class;Lcom/fasterxml/jackson/databind/type/TypeBindings;Lcom/fasterxml/jackson/databind/JavaType;[Lcom/fasterxml/jackson/databind/JavaType;Lcom/fasterxml/jackson/databind/JavaType;Lcom/fasterxml/jackson/databind/JavaType;Ljava/lang/Object;Ljava/lang/Object;Z)V
      40: areturn

  public com.fasterxml.jackson.databind.type.MapType withTypeHandler(java.lang.Object);
    Code:
       0: new           #3                  // class com/fasterxml/jackson/databind/type/MapType
       3: dup
       4: aload_0
       5: getfield      #17                 // Field _class:Ljava/lang/Class;
       8: aload_0
       9: getfield      #9                  // Field _bindings:Lcom/fasterxml/jackson/databind/type/TypeBindings;
      12: aload_0
      13: getfield      #10                 // Field _superClass:Lcom/fasterxml/jackson/databind/JavaType;
      16: aload_0
      17: getfield      #11                 // Field _superInterfaces:[Lcom/fasterxml/jackson/databind/JavaType;
      20: aload_0
      21: getfield      #12                 // Field _keyType:Lcom/fasterxml/jackson/databind/JavaType;
      24: aload_0
      25: getfield      #13                 // Field _valueType:Lcom/fasterxml/jackson/databind/JavaType;
      28: aload_0
      29: getfield      #14                 // Field _valueHandler:Ljava/lang/Object;
      32: aload_1
      33: aload_0
      34: getfield      #16                 // Field _asStatic:Z
      37: invokespecial #4                  // Method "<init>":(Ljava/lang/Class;Lcom/fasterxml/jackson/databind/type/TypeBindings;Lcom/fasterxml/jackson/databind/JavaType;[Lcom/fasterxml/jackson/databind/JavaType;Lcom/fasterxml/jackson/databind/JavaType;Lcom/fasterxml/jackson/databind/JavaType;Ljava/lang/Object;Ljava/lang/Object;Z)V
      40: areturn

  public com.fasterxml.jackson.databind.type.MapType withContentTypeHandler(java.lang.Object);
    Code:
       0: new           #3                  // class com/fasterxml/jackson/databind/type/MapType
       3: dup
       4: aload_0
       5: getfield      #17                 // Field _class:Ljava/lang/Class;
       8: aload_0
       9: getfield      #9                  // Field _bindings:Lcom/fasterxml/jackson/databind/type/TypeBindings;
      12: aload_0
      13: getfield      #10                 // Field _superClass:Lcom/fasterxml/jackson/databind/JavaType;
      16: aload_0
      17: getfield      #11                 // Field _superInterfaces:[Lcom/fasterxml/jackson/databind/JavaType;
      20: aload_0
      21: getfield      #12                 // Field _keyType:Lcom/fasterxml/jackson/databind/JavaType;
      24: aload_0
      25: getfield      #13                 // Field _valueType:Lcom/fasterxml/jackson/databind/JavaType;
      28: aload_1
      29: invokevirtual #18                 // Method com/fasterxml/jackson/databind/JavaType.withTypeHandler:(Ljava/lang/Object;)Lcom/fasterxml/jackson/databind/JavaType;
      32: aload_0
      33: getfield      #14                 // Field _valueHandler:Ljava/lang/Object;
      36: aload_0
      37: getfield      #15                 // Field _typeHandler:Ljava/lang/Object;
      40: aload_0
      41: getfield      #16                 // Field _asStatic:Z
      44: invokespecial #4                  // Method "<init>":(Ljava/lang/Class;Lcom/fasterxml/jackson/databind/type/TypeBindings;Lcom/fasterxml/jackson/databind/JavaType;[Lcom/fasterxml/jackson/databind/JavaType;Lcom/fasterxml/jackson/databind/JavaType;Lcom/fasterxml/jackson/databind/JavaType;Ljava/lang/Object;Ljava/lang/Object;Z)V
      47: areturn

  public com.fasterxml.jackson.databind.type.MapType withValueHandler(java.lang.Object);
    Code:
       0: new           #3                  // class com/fasterxml/jackson/databind/type/MapType
       3: dup
       4: aload_0
       5: getfield      #17                 // Field _class:Ljava/lang/Class;
       8: aload_0
       9: getfield      #9                  // Field _bindings:Lcom/fasterxml/jackson/databind/type/TypeBindings;
      12: aload_0
      13: getfield      #10                 // Field _superClass:Lcom/fasterxml/jackson/databind/JavaType;
      16: aload_0
      17: getfield      #11                 // Field _superInterfaces:[Lcom/fasterxml/jackson/databind/JavaType;
      20: aload_0
      21: getfield      #12                 // Field _keyType:Lcom/fasterxml/jackson/databind/JavaType;
      24: aload_0
      25: getfield      #13                 // Field _valueType:Lcom/fasterxml/jackson/databind/JavaType;
      28: aload_1
      29: aload_0
      30: getfield      #15                 // Field _typeHandler:Ljava/lang/Object;
      33: aload_0
      34: getfield      #16                 // Field _asStatic:Z
      37: invokespecial #4                  // Method "<init>":(Ljava/lang/Class;Lcom/fasterxml/jackson/databind/type/TypeBindings;Lcom/fasterxml/jackson/databind/JavaType;[Lcom/fasterxml/jackson/databind/JavaType;Lcom/fasterxml/jackson/databind/JavaType;Lcom/fasterxml/jackson/databind/JavaType;Ljava/lang/Object;Ljava/lang/Object;Z)V
      40: areturn

  public com.fasterxml.jackson.databind.type.MapType withContentValueHandler(java.lang.Object);
    Code:
       0: new           #3                  // class com/fasterxml/jackson/databind/type/MapType
       3: dup
       4: aload_0
       5: getfield      #17                 // Field _class:Ljava/lang/Class;
       8: aload_0
       9: getfield      #9                  // Field _bindings:Lcom/fasterxml/jackson/databind/type/TypeBindings;
      12: aload_0
      13: getfield      #10                 // Field _superClass:Lcom/fasterxml/jackson/databind/JavaType;
      16: aload_0
      17: getfield      #11                 // Field _superInterfaces:[Lcom/fasterxml/jackson/databind/JavaType;
      20: aload_0
      21: getfield      #12                 // Field _keyType:Lcom/fasterxml/jackson/databind/JavaType;
      24: aload_0
      25: getfield      #13                 // Field _valueType:Lcom/fasterxml/jackson/databind/JavaType;
      28: aload_1
      29: invokevirtual #19                 // Method com/fasterxml/jackson/databind/JavaType.withValueHandler:(Ljava/lang/Object;)Lcom/fasterxml/jackson/databind/JavaType;
      32: aload_0
      33: getfield      #14                 // Field _valueHandler:Ljava/lang/Object;
      36: aload_0
      37: getfield      #15                 // Field _typeHandler:Ljava/lang/Object;
      40: aload_0
      41: getfield      #16                 // Field _asStatic:Z
      44: invokespecial #4                  // Method "<init>":(Ljava/lang/Class;Lcom/fasterxml/jackson/databind/type/TypeBindings;Lcom/fasterxml/jackson/databind/JavaType;[Lcom/fasterxml/jackson/databind/JavaType;Lcom/fasterxml/jackson/databind/JavaType;Lcom/fasterxml/jackson/databind/JavaType;Ljava/lang/Object;Ljava/lang/Object;Z)V
      47: areturn

  public com.fasterxml.jackson.databind.type.MapType withStaticTyping();
    Code:
       0: aload_0
       1: getfield      #16                 // Field _asStatic:Z
       4: ifeq          9
       7: aload_0
       8: areturn
       9: new           #3                  // class com/fasterxml/jackson/databind/type/MapType
      12: dup
      13: aload_0
      14: getfield      #17                 // Field _class:Ljava/lang/Class;
      17: aload_0
      18: getfield      #9                  // Field _bindings:Lcom/fasterxml/jackson/databind/type/TypeBindings;
      21: aload_0
      22: getfield      #10                 // Field _superClass:Lcom/fasterxml/jackson/databind/JavaType;
      25: aload_0
      26: getfield      #11                 // Field _superInterfaces:[Lcom/fasterxml/jackson/databind/JavaType;
      29: aload_0
      30: getfield      #12                 // Field _keyType:Lcom/fasterxml/jackson/databind/JavaType;
      33: invokevirtual #20                 // Method com/fasterxml/jackson/databind/JavaType.withStaticTyping:()Lcom/fasterxml/jackson/databind/JavaType;
      36: aload_0
      37: getfield      #13                 // Field _valueType:Lcom/fasterxml/jackson/databind/JavaType;
      40: invokevirtual #20                 // Method com/fasterxml/jackson/databind/JavaType.withStaticTyping:()Lcom/fasterxml/jackson/databind/JavaType;
      43: aload_0
      44: getfield      #14                 // Field _valueHandler:Ljava/lang/Object;
      47: aload_0
      48: getfield      #15                 // Field _typeHandler:Ljava/lang/Object;
      51: iconst_1
      52: invokespecial #4                  // Method "<init>":(Ljava/lang/Class;Lcom/fasterxml/jackson/databind/type/TypeBindings;Lcom/fasterxml/jackson/databind/JavaType;[Lcom/fasterxml/jackson/databind/JavaType;Lcom/fasterxml/jackson/databind/JavaType;Lcom/fasterxml/jackson/databind/JavaType;Ljava/lang/Object;Ljava/lang/Object;Z)V
      55: areturn

  public com.fasterxml.jackson.databind.JavaType withContentType(com.fasterxml.jackson.databind.JavaType);
    Code:
       0: aload_0
       1: getfield      #13                 // Field _valueType:Lcom/fasterxml/jackson/databind/JavaType;
       4: aload_1
       5: if_acmpne     10
       8: aload_0
       9: areturn
      10: new           #3                  // class com/fasterxml/jackson/databind/type/MapType
      13: dup
      14: aload_0
      15: getfield      #17                 // Field _class:Ljava/lang/Class;
      18: aload_0
      19: getfield      #9                  // Field _bindings:Lcom/fasterxml/jackson/databind/type/TypeBindings;
      22: aload_0
      23: getfield      #10                 // Field _superClass:Lcom/fasterxml/jackson/databind/JavaType;
      26: aload_0
      27: getfield      #11                 // Field _superInterfaces:[Lcom/fasterxml/jackson/databind/JavaType;
      30: aload_0
      31: getfield      #12                 // Field _keyType:Lcom/fasterxml/jackson/databind/JavaType;
      34: aload_1
      35: aload_0
      36: getfield      #14                 // Field _valueHandler:Ljava/lang/Object;
      39: aload_0
      40: getfield      #15                 // Field _typeHandler:Ljava/lang/Object;
      43: aload_0
      44: getfield      #16                 // Field _asStatic:Z
      47: invokespecial #4                  // Method "<init>":(Ljava/lang/Class;Lcom/fasterxml/jackson/databind/type/TypeBindings;Lcom/fasterxml/jackson/databind/JavaType;[Lcom/fasterxml/jackson/databind/JavaType;Lcom/fasterxml/jackson/databind/JavaType;Lcom/fasterxml/jackson/databind/JavaType;Ljava/lang/Object;Ljava/lang/Object;Z)V
      50: areturn

  public com.fasterxml.jackson.databind.type.MapType withKeyType(com.fasterxml.jackson.databind.JavaType);
    Code:
       0: aload_1
       1: aload_0
       2: getfield      #12                 // Field _keyType:Lcom/fasterxml/jackson/databind/JavaType;
       5: if_acmpne     10
       8: aload_0
       9: areturn
      10: new           #3                  // class com/fasterxml/jackson/databind/type/MapType
      13: dup
      14: aload_0
      15: getfield      #17                 // Field _class:Ljava/lang/Class;
      18: aload_0
      19: getfield      #9                  // Field _bindings:Lcom/fasterxml/jackson/databind/type/TypeBindings;
      22: aload_0
      23: getfield      #10                 // Field _superClass:Lcom/fasterxml/jackson/databind/JavaType;
      26: aload_0
      27: getfield      #11                 // Field _superInterfaces:[Lcom/fasterxml/jackson/databind/JavaType;
      30: aload_1
      31: aload_0
      32: getfield      #13                 // Field _valueType:Lcom/fasterxml/jackson/databind/JavaType;
      35: aload_0
      36: getfield      #14                 // Field _valueHandler:Ljava/lang/Object;
      39: aload_0
      40: getfield      #15                 // Field _typeHandler:Ljava/lang/Object;
      43: aload_0
      44: getfield      #16                 // Field _asStatic:Z
      47: invokespecial #4                  // Method "<init>":(Ljava/lang/Class;Lcom/fasterxml/jackson/databind/type/TypeBindings;Lcom/fasterxml/jackson/databind/JavaType;[Lcom/fasterxml/jackson/databind/JavaType;Lcom/fasterxml/jackson/databind/JavaType;Lcom/fasterxml/jackson/databind/JavaType;Ljava/lang/Object;Ljava/lang/Object;Z)V
      50: areturn

  public com.fasterxml.jackson.databind.JavaType refine(java.lang.Class<?>, com.fasterxml.jackson.databind.type.TypeBindings, com.fasterxml.jackson.databind.JavaType, com.fasterxml.jackson.databind.JavaType[]);
    Code:
       0: new           #3                  // class com/fasterxml/jackson/databind/type/MapType
       3: dup
       4: aload_1
       5: aload_2
       6: aload_3
       7: aload         4
       9: aload_0
      10: getfield      #12                 // Field _keyType:Lcom/fasterxml/jackson/databind/JavaType;
      13: aload_0
      14: getfield      #13                 // Field _valueType:Lcom/fasterxml/jackson/databind/JavaType;
      17: aload_0
      18: getfield      #14                 // Field _valueHandler:Ljava/lang/Object;
      21: aload_0
      22: getfield      #15                 // Field _typeHandler:Ljava/lang/Object;
      25: aload_0
      26: getfield      #16                 // Field _asStatic:Z
      29: invokespecial #4                  // Method "<init>":(Ljava/lang/Class;Lcom/fasterxml/jackson/databind/type/TypeBindings;Lcom/fasterxml/jackson/databind/JavaType;[Lcom/fasterxml/jackson/databind/JavaType;Lcom/fasterxml/jackson/databind/JavaType;Lcom/fasterxml/jackson/databind/JavaType;Ljava/lang/Object;Ljava/lang/Object;Z)V
      32: areturn

  public com.fasterxml.jackson.databind.type.MapType withKeyTypeHandler(java.lang.Object);
    Code:
       0: new           #3                  // class com/fasterxml/jackson/databind/type/MapType
       3: dup
       4: aload_0
       5: getfield      #17                 // Field _class:Ljava/lang/Class;
       8: aload_0
       9: getfield      #9                  // Field _bindings:Lcom/fasterxml/jackson/databind/type/TypeBindings;
      12: aload_0
      13: getfield      #10                 // Field _superClass:Lcom/fasterxml/jackson/databind/JavaType;
      16: aload_0
      17: getfield      #11                 // Field _superInterfaces:[Lcom/fasterxml/jackson/databind/JavaType;
      20: aload_0
      21: getfield      #12                 // Field _keyType:Lcom/fasterxml/jackson/databind/JavaType;
      24: aload_1
      25: invokevirtual #18                 // Method com/fasterxml/jackson/databind/JavaType.withTypeHandler:(Ljava/lang/Object;)Lcom/fasterxml/jackson/databind/JavaType;
      28: aload_0
      29: getfield      #13                 // Field _valueType:Lcom/fasterxml/jackson/databind/JavaType;
      32: aload_0
      33: getfield      #14                 // Field _valueHandler:Ljava/lang/Object;
      36: aload_0
      37: getfield      #15                 // Field _typeHandler:Ljava/lang/Object;
      40: aload_0
      41: getfield      #16                 // Field _asStatic:Z
      44: invokespecial #4                  // Method "<init>":(Ljava/lang/Class;Lcom/fasterxml/jackson/databind/type/TypeBindings;Lcom/fasterxml/jackson/databind/JavaType;[Lcom/fasterxml/jackson/databind/JavaType;Lcom/fasterxml/jackson/databind/JavaType;Lcom/fasterxml/jackson/databind/JavaType;Ljava/lang/Object;Ljava/lang/Object;Z)V
      47: areturn

  public com.fasterxml.jackson.databind.type.MapType withKeyValueHandler(java.lang.Object);
    Code:
       0: new           #3                  // class com/fasterxml/jackson/databind/type/MapType
       3: dup
       4: aload_0
       5: getfield      #17                 // Field _class:Ljava/lang/Class;
       8: aload_0
       9: getfield      #9                  // Field _bindings:Lcom/fasterxml/jackson/databind/type/TypeBindings;
      12: aload_0
      13: getfield      #10                 // Field _superClass:Lcom/fasterxml/jackson/databind/JavaType;
      16: aload_0
      17: getfield      #11                 // Field _superInterfaces:[Lcom/fasterxml/jackson/databind/JavaType;
      20: aload_0
      21: getfield      #12                 // Field _keyType:Lcom/fasterxml/jackson/databind/JavaType;
      24: aload_1
      25: invokevirtual #19                 // Method com/fasterxml/jackson/databind/JavaType.withValueHandler:(Ljava/lang/Object;)Lcom/fasterxml/jackson/databind/JavaType;
      28: aload_0
      29: getfield      #13                 // Field _valueType:Lcom/fasterxml/jackson/databind/JavaType;
      32: aload_0
      33: getfield      #14                 // Field _valueHandler:Ljava/lang/Object;
      36: aload_0
      37: getfield      #15                 // Field _typeHandler:Ljava/lang/Object;
      40: aload_0
      41: getfield      #16                 // Field _asStatic:Z
      44: invokespecial #4                  // Method "<init>":(Ljava/lang/Class;Lcom/fasterxml/jackson/databind/type/TypeBindings;Lcom/fasterxml/jackson/databind/JavaType;[Lcom/fasterxml/jackson/databind/JavaType;Lcom/fasterxml/jackson/databind/JavaType;Lcom/fasterxml/jackson/databind/JavaType;Ljava/lang/Object;Ljava/lang/Object;Z)V
      47: areturn

  public java.lang.String toString();
    Code:
       0: new           #21                 // class java/lang/StringBuilder
       3: dup
       4: invokespecial #22                 // Method java/lang/StringBuilder."<init>":()V
       7: ldc           #23                 // String [map type; class
       9: invokevirtual #24                 // Method java/lang/StringBuilder.append:(Ljava/lang/String;)Ljava/lang/StringBuilder;
      12: aload_0
      13: getfield      #17                 // Field _class:Ljava/lang/Class;
      16: invokevirtual #25                 // Method java/lang/Class.getName:()Ljava/lang/String;
      19: invokevirtual #24                 // Method java/lang/StringBuilder.append:(Ljava/lang/String;)Ljava/lang/StringBuilder;
      22: ldc           #26                 // String ,
      24: invokevirtual #24                 // Method java/lang/StringBuilder.append:(Ljava/lang/String;)Ljava/lang/StringBuilder;
      27: aload_0
      28: getfield      #12                 // Field _keyType:Lcom/fasterxml/jackson/databind/JavaType;
      31: invokevirtual #27                 // Method java/lang/StringBuilder.append:(Ljava/lang/Object;)Ljava/lang/StringBuilder;
      34: ldc           #28                 // String  ->
      36: invokevirtual #24                 // Method java/lang/StringBuilder.append:(Ljava/lang/String;)Ljava/lang/StringBuilder;
      39: aload_0
      40: getfield      #13                 // Field _valueType:Lcom/fasterxml/jackson/databind/JavaType;
      43: invokevirtual #27                 // Method java/lang/StringBuilder.append:(Ljava/lang/Object;)Ljava/lang/StringBuilder;
      46: ldc           #29                 // String ]
      48: invokevirtual #24                 // Method java/lang/StringBuilder.append:(Ljava/lang/String;)Ljava/lang/StringBuilder;
      51: invokevirtual #30                 // Method java/lang/StringBuilder.toString:()Ljava/lang/String;
      54: areturn

  public com.fasterxml.jackson.databind.type.MapLikeType withKeyValueHandler(java.lang.Object);
    Code:
       0: aload_0
       1: aload_1
       2: invokevirtual #31                 // Method withKeyValueHandler:(Ljava/lang/Object;)Lcom/fasterxml/jackson/databind/type/MapType;
       5: areturn

  public com.fasterxml.jackson.databind.type.MapLikeType withKeyTypeHandler(java.lang.Object);
    Code:
       0: aload_0
       1: aload_1
       2: invokevirtual #32                 // Method withKeyTypeHandler:(Ljava/lang/Object;)Lcom/fasterxml/jackson/databind/type/MapType;
       5: areturn

  public com.fasterxml.jackson.databind.type.MapLikeType withStaticTyping();
    Code:
       0: aload_0
       1: invokevirtual #33                 // Method withStaticTyping:()Lcom/fasterxml/jackson/databind/type/MapType;
       4: areturn

  public com.fasterxml.jackson.databind.type.MapLikeType withContentValueHandler(java.lang.Object);
    Code:
       0: aload_0
       1: aload_1
       2: invokevirtual #34                 // Method withContentValueHandler:(Ljava/lang/Object;)Lcom/fasterxml/jackson/databind/type/MapType;
       5: areturn

  public com.fasterxml.jackson.databind.type.MapLikeType withValueHandler(java.lang.Object);
    Code:
       0: aload_0
       1: aload_1
       2: invokevirtual #35                 // Method withValueHandler:(Ljava/lang/Object;)Lcom/fasterxml/jackson/databind/type/MapType;
       5: areturn

  public com.fasterxml.jackson.databind.type.MapLikeType withContentTypeHandler(java.lang.Object);
    Code:
       0: aload_0
       1: aload_1
       2: invokevirtual #36                 // Method withContentTypeHandler:(Ljava/lang/Object;)Lcom/fasterxml/jackson/databind/type/MapType;
       5: areturn

  public com.fasterxml.jackson.databind.type.MapLikeType withTypeHandler(java.lang.Object);
    Code:
       0: aload_0
       1: aload_1
       2: invokevirtual #37                 // Method withTypeHandler:(Ljava/lang/Object;)Lcom/fasterxml/jackson/databind/type/MapType;
       5: areturn

  public com.fasterxml.jackson.databind.type.MapLikeType withKeyType(com.fasterxml.jackson.databind.JavaType);
    Code:
       0: aload_0
       1: aload_1
       2: invokevirtual #38                 // Method withKeyType:(Lcom/fasterxml/jackson/databind/JavaType;)Lcom/fasterxml/jackson/databind/type/MapType;
       5: areturn

  public com.fasterxml.jackson.databind.JavaType withContentValueHandler(java.lang.Object);
    Code:
       0: aload_0
       1: aload_1
       2: invokevirtual #34                 // Method withContentValueHandler:(Ljava/lang/Object;)Lcom/fasterxml/jackson/databind/type/MapType;
       5: areturn

  public com.fasterxml.jackson.databind.JavaType withValueHandler(java.lang.Object);
    Code:
       0: aload_0
       1: aload_1
       2: invokevirtual #35                 // Method withValueHandler:(Ljava/lang/Object;)Lcom/fasterxml/jackson/databind/type/MapType;
       5: areturn

  public com.fasterxml.jackson.databind.JavaType withContentTypeHandler(java.lang.Object);
    Code:
       0: aload_0
       1: aload_1
       2: invokevirtual #36                 // Method withContentTypeHandler:(Ljava/lang/Object;)Lcom/fasterxml/jackson/databind/type/MapType;
       5: areturn

  public com.fasterxml.jackson.databind.JavaType withTypeHandler(java.lang.Object);
    Code:
       0: aload_0
       1: aload_1
       2: invokevirtual #37                 // Method withTypeHandler:(Ljava/lang/Object;)Lcom/fasterxml/jackson/databind/type/MapType;
       5: areturn

  public com.fasterxml.jackson.databind.JavaType withStaticTyping();
    Code:
       0: aload_0
       1: invokevirtual #33                 // Method withStaticTyping:()Lcom/fasterxml/jackson/databind/type/MapType;
       4: areturn
}
