Compiled from "DurationUtil.scala"
public class org.sisioh.trinity.infrastructure.DurationUtil$SDurationToTDuration$ {
  public static final org.sisioh.trinity.infrastructure.DurationUtil$SDurationToTDuration$ MODULE$;

  public static {};
    Code:
       0: new           #2                  // class org/sisioh/trinity/infrastructure/DurationUtil$SDurationToTDuration$
       3: invokespecial #12                 // Method "<init>":()V
       6: return

  public final com.twitter.util.Duration toTwitter$extension(scala.concurrent.duration.Duration);
    Code:
       0: getstatic     #19                 // Field com/twitter/util/Duration$.MODULE$:Lcom/twitter/util/Duration$;
       3: aload_1
       4: invokevirtual #25                 // Method scala/concurrent/duration/Duration.length:()J
       7: aload_1
       8: invokevirtual #29                 // Method scala/concurrent/duration/Duration.unit:()Ljava/util/concurrent/TimeUnit;
      11: invokevirtual #33                 // Method com/twitter/util/Duration$.apply:(JLjava/util/concurrent/TimeUnit;)Lcom/twitter/util/Duration;
      14: areturn

  public final int hashCode$extension(scala.concurrent.duration.Duration);
    Code:
       0: aload_1
       1: invokevirtual #42                 // Method java/lang/Object.hashCode:()I
       4: ireturn

  public final boolean equals$extension(scala.concurrent.duration.Duration, java.lang.Object);
    Code:
       0: aload_2
       1: astore_3
       2: aload_3
       3: instanceof    #46                 // class org/sisioh/trinity/infrastructure/DurationUtil$SDurationToTDuration
       6: ifeq          15
       9: iconst_1
      10: istore        4
      12: goto          18
      15: iconst_0
      16: istore        4
      18: iload         4
      20: ifeq          80
      23: aload_2
      24: ifnonnull     33
      27: aconst_null
      28: pop
      29: aconst_null
      30: goto          40
      33: aload_2
      34: checkcast     #46                 // class org/sisioh/trinity/infrastructure/DurationUtil$SDurationToTDuration
      37: invokevirtual #50                 // Method org/sisioh/trinity/infrastructure/DurationUtil$SDurationToTDuration.duration:()Lscala/concurrent/duration/Duration;
      40: astore        5
      42: aload_1
      43: aload         5
      45: astore        6
      47: dup
      48: ifnonnull     60
      51: pop
      52: aload         6
      54: ifnull        68
      57: goto          72
      60: aload         6
      62: invokevirtual #54                 // Method java/lang/Object.equals:(Ljava/lang/Object;)Z
      65: ifeq          72
      68: iconst_1
      69: goto          73
      72: iconst_0
      73: ifeq          80
      76: iconst_1
      77: goto          81
      80: iconst_0
      81: ireturn

  public org.sisioh.trinity.infrastructure.DurationUtil$SDurationToTDuration$();
    Code:
       0: aload_0
       1: invokespecial #57                 // Method java/lang/Object."<init>":()V
       4: aload_0
       5: putstatic     #59                 // Field MODULE$:Lorg/sisioh/trinity/infrastructure/DurationUtil$SDurationToTDuration$;
       8: return
}
