Compiled from "ClusterMessages.java"
final class akka.cluster.protobuf.msg.ClusterMessages$NodeMetrics$NumberType$1 implements akka.protobuf.Internal$EnumLiteMap<akka.cluster.protobuf.msg.ClusterMessages$NodeMetrics$NumberType> {
  akka.cluster.protobuf.msg.ClusterMessages$NodeMetrics$NumberType$1();
    Code:
       0: aload_0
       1: invokespecial #1                  // Method java/lang/Object."<init>":()V
       4: return

  public akka.cluster.protobuf.msg.ClusterMessages$NodeMetrics$NumberType findValueByNumber(int);
    Code:
       0: iload_1
       1: invokestatic  #2                  // Method akka/cluster/protobuf/msg/ClusterMessages$NodeMetrics$NumberType.valueOf:(I)Lakka/cluster/protobuf/msg/ClusterMessages$NodeMetrics$NumberType;
       4: areturn

  public akka.protobuf.Internal$EnumLite findValueByNumber(int);
    Code:
       0: aload_0
       1: iload_1
       2: invokevirtual #3                  // Method findValueByNumber:(I)Lakka/cluster/protobuf/msg/ClusterMessages$NodeMetrics$NumberType;
       5: areturn
}
