Compiled from "ArrayTypeImpl.java"
public class org.eclipse.jdt.internal.compiler.apt.model.ArrayTypeImpl extends org.eclipse.jdt.internal.compiler.apt.model.TypeMirrorImpl implements javax.lang.model.type.ArrayType {
  org.eclipse.jdt.internal.compiler.apt.model.ArrayTypeImpl(org.eclipse.jdt.internal.compiler.apt.dispatch.BaseProcessingEnvImpl, org.eclipse.jdt.internal.compiler.lookup.ArrayBinding);
    Code:
       0: aload_0
       1: aload_1
       2: aload_2
       3: invokespecial #10                 // Method org/eclipse/jdt/internal/compiler/apt/model/TypeMirrorImpl."<init>":(Lorg/eclipse/jdt/internal/compiler/apt/dispatch/BaseProcessingEnvImpl;Lorg/eclipse/jdt/internal/compiler/lookup/Binding;)V
       6: return

  public javax.lang.model.type.TypeMirror getComponentType();
    Code:
       0: aload_0
       1: getfield      #23                 // Field _env:Lorg/eclipse/jdt/internal/compiler/apt/dispatch/BaseProcessingEnvImpl;
       4: invokevirtual #26                 // Method org/eclipse/jdt/internal/compiler/apt/dispatch/BaseProcessingEnvImpl.getFactory:()Lorg/eclipse/jdt/internal/compiler/apt/model/Factory;
       7: aload_0
       8: getfield      #32                 // Field _binding:Lorg/eclipse/jdt/internal/compiler/lookup/Binding;
      11: checkcast     #36                 // class org/eclipse/jdt/internal/compiler/lookup/ArrayBinding
      14: invokevirtual #38                 // Method org/eclipse/jdt/internal/compiler/lookup/ArrayBinding.elementsType:()Lorg/eclipse/jdt/internal/compiler/lookup/TypeBinding;
      17: invokevirtual #42                 // Method org/eclipse/jdt/internal/compiler/apt/model/Factory.newTypeMirror:(Lorg/eclipse/jdt/internal/compiler/lookup/Binding;)Ljavax/lang/model/type/TypeMirror;
      20: areturn

  public <R, P> R accept(javax.lang.model.type.TypeVisitor<R, P>, P);
    Code:
       0: aload_1
       1: aload_0
       2: aload_2
       3: invokeinterface #52,  3           // InterfaceMethod javax/lang/model/type/TypeVisitor.visitArray:(Ljavax/lang/model/type/ArrayType;Ljava/lang/Object;)Ljava/lang/Object;
       8: areturn

  protected org.eclipse.jdt.internal.compiler.lookup.AnnotationBinding[] getAnnotationBindings();
    Code:
       0: aload_0
       1: getfield      #32                 // Field _binding:Lorg/eclipse/jdt/internal/compiler/lookup/Binding;
       4: checkcast     #36                 // class org/eclipse/jdt/internal/compiler/lookup/ArrayBinding
       7: invokevirtual #67                 // Method org/eclipse/jdt/internal/compiler/lookup/ArrayBinding.getTypeAnnotations:()[Lorg/eclipse/jdt/internal/compiler/lookup/AnnotationBinding;
      10: astore_1
      11: getstatic     #70                 // Field org/eclipse/jdt/internal/compiler/lookup/Binding.NO_ANNOTATIONS:[Lorg/eclipse/jdt/internal/compiler/lookup/AnnotationBinding;
      14: astore_2
      15: iconst_0
      16: istore_3
      17: aload_1
      18: ifnonnull     25
      21: iconst_0
      22: goto          27
      25: aload_1
      26: arraylength
      27: istore        4
      29: goto          56
      32: aload_1
      33: iload_3
      34: aaload
      35: ifnonnull     53
      38: aload_1
      39: iconst_0
      40: iload_3
      41: anewarray     #76                 // class org/eclipse/jdt/internal/compiler/lookup/AnnotationBinding
      44: dup
      45: astore_2
      46: iconst_0
      47: iload_3
      48: invokestatic  #78                 // Method java/lang/System.arraycopy:(Ljava/lang/Object;ILjava/lang/Object;II)V
      51: aload_2
      52: areturn
      53: iinc          3, 1
      56: iload_3
      57: iload         4
      59: if_icmplt     32
      62: aload_2
      63: areturn

  public javax.lang.model.type.TypeKind getKind();
    Code:
       0: getstatic     #93                 // Field javax/lang/model/type/TypeKind.ARRAY:Ljavax/lang/model/type/TypeKind;
       3: areturn
}
