Compiled from "TypesImpl.java"
public class org.eclipse.jdt.internal.compiler.apt.model.TypesImpl implements javax.lang.model.util.Types {
  private final org.eclipse.jdt.internal.compiler.apt.dispatch.BaseProcessingEnvImpl _env;

  private static int[] $SWITCH_TABLE$javax$lang$model$type$TypeKind;

  private static int[] $SWITCH_TABLE$javax$lang$model$element$ElementKind;

  public org.eclipse.jdt.internal.compiler.apt.model.TypesImpl(org.eclipse.jdt.internal.compiler.apt.dispatch.BaseProcessingEnvImpl);
    Code:
       0: aload_0
       1: invokespecial #15                 // Method java/lang/Object."<init>":()V
       4: aload_0
       5: aload_1
       6: putfield      #18                 // Field _env:Lorg/eclipse/jdt/internal/compiler/apt/dispatch/BaseProcessingEnvImpl;
       9: return

  public javax.lang.model.element.Element asElement(javax.lang.model.type.TypeMirror);
    Code:
       0: invokestatic  #27                 // Method $SWITCH_TABLE$javax$lang$model$type$TypeKind:()[I
       3: aload_1
       4: invokeinterface #30,  1           // InterfaceMethod javax/lang/model/type/TypeMirror.getKind:()Ljavax/lang/model/type/TypeKind;
       9: invokevirtual #36                 // Method javax/lang/model/type/TypeKind.ordinal:()I
      12: iaload
      13: tableswitch   { // 13 to 15
                    13: 40
                    14: 58
                    15: 40
               default: 58
          }
      40: aload_0
      41: getfield      #18                 // Field _env:Lorg/eclipse/jdt/internal/compiler/apt/dispatch/BaseProcessingEnvImpl;
      44: invokevirtual #42                 // Method org/eclipse/jdt/internal/compiler/apt/dispatch/BaseProcessingEnvImpl.getFactory:()Lorg/eclipse/jdt/internal/compiler/apt/model/Factory;
      47: aload_1
      48: checkcast     #48                 // class org/eclipse/jdt/internal/compiler/apt/model/TypeMirrorImpl
      51: invokevirtual #50                 // Method org/eclipse/jdt/internal/compiler/apt/model/TypeMirrorImpl.binding:()Lorg/eclipse/jdt/internal/compiler/lookup/Binding;
      54: invokevirtual #54                 // Method org/eclipse/jdt/internal/compiler/apt/model/Factory.newElement:(Lorg/eclipse/jdt/internal/compiler/lookup/Binding;)Ljavax/lang/model/element/Element;
      57: areturn
      58: aconst_null
      59: areturn

  public javax.lang.model.type.TypeMirror asMemberOf(javax.lang.model.type.DeclaredType, javax.lang.model.element.Element);
    Code:
       0: aload_2
       1: checkcast     #65                 // class org/eclipse/jdt/internal/compiler/apt/model/ElementImpl
       4: astore_3
       5: aload_1
       6: checkcast     #67                 // class org/eclipse/jdt/internal/compiler/apt/model/DeclaredTypeImpl
       9: astore        4
      11: aload         4
      13: getfield      #69                 // Field org/eclipse/jdt/internal/compiler/apt/model/DeclaredTypeImpl._binding:Lorg/eclipse/jdt/internal/compiler/lookup/Binding;
      16: checkcast     #73                 // class org/eclipse/jdt/internal/compiler/lookup/ReferenceBinding
      19: astore        5
      21: invokestatic  #75                 // Method $SWITCH_TABLE$javax$lang$model$element$ElementKind:()[I
      24: aload_2
      25: invokeinterface #77,  1           // InterfaceMethod javax/lang/model/element/Element.getKind:()Ljavax/lang/model/element/ElementKind;
      30: invokevirtual #82                 // Method javax/lang/model/element/ElementKind.ordinal:()I
      33: iaload
      34: tableswitch   { // 2 to 12
                     2: 298
                     3: 298
                     4: 298
                     5: 298
                     6: 200
                     7: 200
                     8: 396
                     9: 396
                    10: 396
                    11: 92
                    12: 92
               default: 396
          }
      92: aload_3
      93: getfield      #85                 // Field org/eclipse/jdt/internal/compiler/apt/model/ElementImpl._binding:Lorg/eclipse/jdt/internal/compiler/lookup/Binding;
      96: checkcast     #86                 // class org/eclipse/jdt/internal/compiler/lookup/MethodBinding
      99: astore        6
     101: aload         6
     103: getfield      #88                 // Field org/eclipse/jdt/internal/compiler/lookup/MethodBinding.declaringClass:Lorg/eclipse/jdt/internal/compiler/lookup/ReferenceBinding;
     106: aload         5
     108: invokestatic  #92                 // Method org/eclipse/jdt/internal/compiler/lookup/TypeBinding.notEquals:(Lorg/eclipse/jdt/internal/compiler/lookup/TypeBinding;Lorg/eclipse/jdt/internal/compiler/lookup/TypeBinding;)Z
     111: ifeq          124
     114: new           #98                 // class java/lang/IllegalArgumentException
     117: dup
     118: ldc           #100                // String element is not valid for the containing declared type
     120: invokespecial #102                // Method java/lang/IllegalArgumentException."<init>":(Ljava/lang/String;)V
     123: athrow
     124: aload         5
     126: invokevirtual #105                // Method org/eclipse/jdt/internal/compiler/lookup/ReferenceBinding.methods:()[Lorg/eclipse/jdt/internal/compiler/lookup/MethodBinding;
     129: dup
     130: astore        10
     132: arraylength
     133: istore        9
     135: iconst_0
     136: istore        8
     138: goto          190
     141: aload         10
     143: iload         8
     145: aaload
     146: astore        7
     148: aload         7
     150: getfield      #109                // Field org/eclipse/jdt/internal/compiler/lookup/MethodBinding.selector:[C
     153: aload         6
     155: getfield      #109                // Field org/eclipse/jdt/internal/compiler/lookup/MethodBinding.selector:[C
     158: invokestatic  #113                // Method org/eclipse/jdt/core/compiler/CharOperation.equals:([C[C)Z
     161: ifeq          187
     164: aload         7
     166: aload         6
     168: invokevirtual #119                // Method org/eclipse/jdt/internal/compiler/lookup/MethodBinding.areParameterErasuresEqual:(Lorg/eclipse/jdt/internal/compiler/lookup/MethodBinding;)Z
     171: ifeq          187
     174: aload_0
     175: getfield      #18                 // Field _env:Lorg/eclipse/jdt/internal/compiler/apt/dispatch/BaseProcessingEnvImpl;
     178: invokevirtual #42                 // Method org/eclipse/jdt/internal/compiler/apt/dispatch/BaseProcessingEnvImpl.getFactory:()Lorg/eclipse/jdt/internal/compiler/apt/model/Factory;
     181: aload         7
     183: invokevirtual #123                // Method org/eclipse/jdt/internal/compiler/apt/model/Factory.newTypeMirror:(Lorg/eclipse/jdt/internal/compiler/lookup/Binding;)Ljavax/lang/model/type/TypeMirror;
     186: areturn
     187: iinc          8, 1
     190: iload         8
     192: iload         9
     194: if_icmplt     141
     197: goto          396
     200: aload_3
     201: getfield      #85                 // Field org/eclipse/jdt/internal/compiler/apt/model/ElementImpl._binding:Lorg/eclipse/jdt/internal/compiler/lookup/Binding;
     204: checkcast     #127                // class org/eclipse/jdt/internal/compiler/lookup/FieldBinding
     207: astore        7
     209: aload         7
     211: getfield      #129                // Field org/eclipse/jdt/internal/compiler/lookup/FieldBinding.declaringClass:Lorg/eclipse/jdt/internal/compiler/lookup/ReferenceBinding;
     214: aload         5
     216: invokestatic  #92                 // Method org/eclipse/jdt/internal/compiler/lookup/TypeBinding.notEquals:(Lorg/eclipse/jdt/internal/compiler/lookup/TypeBinding;Lorg/eclipse/jdt/internal/compiler/lookup/TypeBinding;)Z
     219: ifeq          232
     222: new           #98                 // class java/lang/IllegalArgumentException
     225: dup
     226: ldc           #100                // String element is not valid for the containing declared type
     228: invokespecial #102                // Method java/lang/IllegalArgumentException."<init>":(Ljava/lang/String;)V
     231: athrow
     232: aload         5
     234: invokevirtual #130                // Method org/eclipse/jdt/internal/compiler/lookup/ReferenceBinding.fields:()[Lorg/eclipse/jdt/internal/compiler/lookup/FieldBinding;
     237: dup
     238: astore        11
     240: arraylength
     241: istore        10
     243: iconst_0
     244: istore        9
     246: goto          288
     249: aload         11
     251: iload         9
     253: aaload
     254: astore        8
     256: aload         8
     258: getfield      #134                // Field org/eclipse/jdt/internal/compiler/lookup/FieldBinding.name:[C
     261: aload         7
     263: getfield      #134                // Field org/eclipse/jdt/internal/compiler/lookup/FieldBinding.name:[C
     266: invokestatic  #113                // Method org/eclipse/jdt/core/compiler/CharOperation.equals:([C[C)Z
     269: ifeq          285
     272: aload_0
     273: getfield      #18                 // Field _env:Lorg/eclipse/jdt/internal/compiler/apt/dispatch/BaseProcessingEnvImpl;
     276: invokevirtual #42                 // Method org/eclipse/jdt/internal/compiler/apt/dispatch/BaseProcessingEnvImpl.getFactory:()Lorg/eclipse/jdt/internal/compiler/apt/model/Factory;
     279: aload         8
     281: invokevirtual #123                // Method org/eclipse/jdt/internal/compiler/apt/model/Factory.newTypeMirror:(Lorg/eclipse/jdt/internal/compiler/lookup/Binding;)Ljavax/lang/model/type/TypeMirror;
     284: areturn
     285: iinc          9, 1
     288: iload         9
     290: iload         10
     292: if_icmplt     249
     295: goto          396
     298: aload_3
     299: getfield      #85                 // Field org/eclipse/jdt/internal/compiler/apt/model/ElementImpl._binding:Lorg/eclipse/jdt/internal/compiler/lookup/Binding;
     302: checkcast     #73                 // class org/eclipse/jdt/internal/compiler/lookup/ReferenceBinding
     305: astore        8
     307: aload         8
     309: invokevirtual #137                // Method org/eclipse/jdt/internal/compiler/lookup/ReferenceBinding.enclosingType:()Lorg/eclipse/jdt/internal/compiler/lookup/ReferenceBinding;
     312: aload         5
     314: invokestatic  #92                 // Method org/eclipse/jdt/internal/compiler/lookup/TypeBinding.notEquals:(Lorg/eclipse/jdt/internal/compiler/lookup/TypeBinding;Lorg/eclipse/jdt/internal/compiler/lookup/TypeBinding;)Z
     317: ifeq          330
     320: new           #98                 // class java/lang/IllegalArgumentException
     323: dup
     324: ldc           #100                // String element is not valid for the containing declared type
     326: invokespecial #102                // Method java/lang/IllegalArgumentException."<init>":(Ljava/lang/String;)V
     329: athrow
     330: aload         5
     332: invokevirtual #141                // Method org/eclipse/jdt/internal/compiler/lookup/ReferenceBinding.memberTypes:()[Lorg/eclipse/jdt/internal/compiler/lookup/ReferenceBinding;
     335: dup
     336: astore        12
     338: arraylength
     339: istore        11
     341: iconst_0
     342: istore        10
     344: goto          386
     347: aload         12
     349: iload         10
     351: aaload
     352: astore        9
     354: aload         9
     356: getfield      #145                // Field org/eclipse/jdt/internal/compiler/lookup/ReferenceBinding.compoundName:[[C
     359: aload         9
     361: getfield      #145                // Field org/eclipse/jdt/internal/compiler/lookup/ReferenceBinding.compoundName:[[C
     364: invokestatic  #149                // Method org/eclipse/jdt/core/compiler/CharOperation.equals:([[C[[C)Z
     367: ifeq          383
     370: aload_0
     371: getfield      #18                 // Field _env:Lorg/eclipse/jdt/internal/compiler/apt/dispatch/BaseProcessingEnvImpl;
     374: invokevirtual #42                 // Method org/eclipse/jdt/internal/compiler/apt/dispatch/BaseProcessingEnvImpl.getFactory:()Lorg/eclipse/jdt/internal/compiler/apt/model/Factory;
     377: aload         9
     379: invokevirtual #123                // Method org/eclipse/jdt/internal/compiler/apt/model/Factory.newTypeMirror:(Lorg/eclipse/jdt/internal/compiler/lookup/Binding;)Ljavax/lang/model/type/TypeMirror;
     382: areturn
     383: iinc          10, 1
     386: iload         10
     388: iload         11
     390: if_icmplt     347
     393: goto          396
     396: new           #98                 // class java/lang/IllegalArgumentException
     399: dup
     400: new           #152                // class java/lang/StringBuilder
     403: dup
     404: ldc           #154                // String element is not valid for the containing declared type: element kind
     406: invokespecial #156                // Method java/lang/StringBuilder."<init>":(Ljava/lang/String;)V
     409: aload_2
     410: invokeinterface #77,  1           // InterfaceMethod javax/lang/model/element/Element.getKind:()Ljavax/lang/model/element/ElementKind;
     415: invokevirtual #157                // Method java/lang/StringBuilder.append:(Ljava/lang/Object;)Ljava/lang/StringBuilder;
     418: invokevirtual #161                // Method java/lang/StringBuilder.toString:()Ljava/lang/String;
     421: invokespecial #102                // Method java/lang/IllegalArgumentException."<init>":(Ljava/lang/String;)V
     424: athrow

  public javax.lang.model.element.TypeElement boxedClass(javax.lang.model.type.PrimitiveType);
    Code:
       0: aload_1
       1: checkcast     #192                // class org/eclipse/jdt/internal/compiler/apt/model/PrimitiveTypeImpl
       4: astore_2
       5: aload_2
       6: getfield      #194                // Field org/eclipse/jdt/internal/compiler/apt/model/PrimitiveTypeImpl._binding:Lorg/eclipse/jdt/internal/compiler/lookup/Binding;
       9: checkcast     #195                // class org/eclipse/jdt/internal/compiler/lookup/BaseTypeBinding
      12: astore_3
      13: aload_0
      14: getfield      #18                 // Field _env:Lorg/eclipse/jdt/internal/compiler/apt/dispatch/BaseProcessingEnvImpl;
      17: invokevirtual #197                // Method org/eclipse/jdt/internal/compiler/apt/dispatch/BaseProcessingEnvImpl.getLookupEnvironment:()Lorg/eclipse/jdt/internal/compiler/lookup/LookupEnvironment;
      20: aload_3
      21: invokevirtual #201                // Method org/eclipse/jdt/internal/compiler/lookup/LookupEnvironment.computeBoxingType:(Lorg/eclipse/jdt/internal/compiler/lookup/TypeBinding;)Lorg/eclipse/jdt/internal/compiler/lookup/TypeBinding;
      24: astore        4
      26: aload_0
      27: getfield      #18                 // Field _env:Lorg/eclipse/jdt/internal/compiler/apt/dispatch/BaseProcessingEnvImpl;
      30: invokevirtual #42                 // Method org/eclipse/jdt/internal/compiler/apt/dispatch/BaseProcessingEnvImpl.getFactory:()Lorg/eclipse/jdt/internal/compiler/apt/model/Factory;
      33: aload         4
      35: invokevirtual #54                 // Method org/eclipse/jdt/internal/compiler/apt/model/Factory.newElement:(Lorg/eclipse/jdt/internal/compiler/lookup/Binding;)Ljavax/lang/model/element/Element;
      38: checkcast     #207                // class javax/lang/model/element/TypeElement
      41: areturn

  public javax.lang.model.type.TypeMirror capture(javax.lang.model.type.TypeMirror);
    Code:
       0: new           #219                // class java/lang/UnsupportedOperationException
       3: dup
       4: ldc           #221                // String NYI: TypesImpl.capture(...)
       6: invokespecial #223                // Method java/lang/UnsupportedOperationException."<init>":(Ljava/lang/String;)V
       9: athrow

  public boolean contains(javax.lang.model.type.TypeMirror, javax.lang.model.type.TypeMirror);
    Code:
       0: invokestatic  #27                 // Method $SWITCH_TABLE$javax$lang$model$type$TypeKind:()[I
       3: aload_1
       4: invokeinterface #30,  1           // InterfaceMethod javax/lang/model/type/TypeMirror.getKind:()Ljavax/lang/model/type/TypeKind;
       9: invokevirtual #36                 // Method javax/lang/model/type/TypeKind.ordinal:()I
      12: iaload
      13: tableswitch   { // 17 to 18
                    17: 36
                    18: 36
               default: 46
          }
      36: new           #98                 // class java/lang/IllegalArgumentException
      39: dup
      40: ldc           #226                // String Executable and package are illegal argument for Types.contains(..)
      42: invokespecial #102                // Method java/lang/IllegalArgumentException."<init>":(Ljava/lang/String;)V
      45: athrow
      46: invokestatic  #27                 // Method $SWITCH_TABLE$javax$lang$model$type$TypeKind:()[I
      49: aload_2
      50: invokeinterface #30,  1           // InterfaceMethod javax/lang/model/type/TypeMirror.getKind:()Ljavax/lang/model/type/TypeKind;
      55: invokevirtual #36                 // Method javax/lang/model/type/TypeKind.ordinal:()I
      58: iaload
      59: tableswitch   { // 17 to 18
                    17: 80
                    18: 80
               default: 90
          }
      80: new           #98                 // class java/lang/IllegalArgumentException
      83: dup
      84: ldc           #226                // String Executable and package are illegal argument for Types.contains(..)
      86: invokespecial #102                // Method java/lang/IllegalArgumentException."<init>":(Ljava/lang/String;)V
      89: athrow
      90: new           #219                // class java/lang/UnsupportedOperationException
      93: dup
      94: new           #152                // class java/lang/StringBuilder
      97: dup
      98: ldc           #228                // String NYI: TypesImpl.contains(
     100: invokespecial #156                // Method java/lang/StringBuilder."<init>":(Ljava/lang/String;)V
     103: aload_1
     104: invokevirtual #157                // Method java/lang/StringBuilder.append:(Ljava/lang/Object;)Ljava/lang/StringBuilder;
     107: ldc           #230                // String ,
     109: invokevirtual #232                // Method java/lang/StringBuilder.append:(Ljava/lang/String;)Ljava/lang/StringBuilder;
     112: aload_2
     113: invokevirtual #157                // Method java/lang/StringBuilder.append:(Ljava/lang/Object;)Ljava/lang/StringBuilder;
     116: ldc           #235                // String )
     118: invokevirtual #232                // Method java/lang/StringBuilder.append:(Ljava/lang/String;)Ljava/lang/StringBuilder;
     121: invokevirtual #161                // Method java/lang/StringBuilder.toString:()Ljava/lang/String;
     124: invokespecial #223                // Method java/lang/UnsupportedOperationException."<init>":(Ljava/lang/String;)V
     127: athrow

  public java.util.List<? extends javax.lang.model.type.TypeMirror> directSupertypes(javax.lang.model.type.TypeMirror);
    Code:
       0: invokestatic  #27                 // Method $SWITCH_TABLE$javax$lang$model$type$TypeKind:()[I
       3: aload_1
       4: invokeinterface #30,  1           // InterfaceMethod javax/lang/model/type/TypeMirror.getKind:()Ljavax/lang/model/type/TypeKind;
       9: invokevirtual #36                 // Method javax/lang/model/type/TypeKind.ordinal:()I
      12: iaload
      13: tableswitch   { // 17 to 18
                    17: 36
                    18: 36
               default: 46
          }
      36: new           #98                 // class java/lang/IllegalArgumentException
      39: dup
      40: ldc           #243                // String Invalid type mirror for directSupertypes
      42: invokespecial #102                // Method java/lang/IllegalArgumentException."<init>":(Ljava/lang/String;)V
      45: athrow
      46: aload_1
      47: checkcast     #48                 // class org/eclipse/jdt/internal/compiler/apt/model/TypeMirrorImpl
      50: astore_2
      51: aload_2
      52: getfield      #245                // Field org/eclipse/jdt/internal/compiler/apt/model/TypeMirrorImpl._binding:Lorg/eclipse/jdt/internal/compiler/lookup/Binding;
      55: astore_3
      56: aload_3
      57: instanceof    #73                 // class org/eclipse/jdt/internal/compiler/lookup/ReferenceBinding
      60: ifeq          166
      63: aload_3
      64: checkcast     #73                 // class org/eclipse/jdt/internal/compiler/lookup/ReferenceBinding
      67: astore        4
      69: new           #246                // class java/util/ArrayList
      72: dup
      73: invokespecial #248                // Method java/util/ArrayList."<init>":()V
      76: astore        5
      78: aload         4
      80: invokevirtual #249                // Method org/eclipse/jdt/internal/compiler/lookup/ReferenceBinding.superclass:()Lorg/eclipse/jdt/internal/compiler/lookup/ReferenceBinding;
      83: astore        6
      85: aload         6
      87: ifnull        108
      90: aload         5
      92: aload_0
      93: getfield      #18                 // Field _env:Lorg/eclipse/jdt/internal/compiler/apt/dispatch/BaseProcessingEnvImpl;
      96: invokevirtual #42                 // Method org/eclipse/jdt/internal/compiler/apt/dispatch/BaseProcessingEnvImpl.getFactory:()Lorg/eclipse/jdt/internal/compiler/apt/model/Factory;
      99: aload         6
     101: invokevirtual #123                // Method org/eclipse/jdt/internal/compiler/apt/model/Factory.newTypeMirror:(Lorg/eclipse/jdt/internal/compiler/lookup/Binding;)Ljavax/lang/model/type/TypeMirror;
     104: invokevirtual #252                // Method java/util/ArrayList.add:(Ljava/lang/Object;)Z
     107: pop
     108: aload         4
     110: invokevirtual #256                // Method org/eclipse/jdt/internal/compiler/lookup/ReferenceBinding.superInterfaces:()[Lorg/eclipse/jdt/internal/compiler/lookup/ReferenceBinding;
     113: dup
     114: astore        10
     116: arraylength
     117: istore        9
     119: iconst_0
     120: istore        8
     122: goto          153
     125: aload         10
     127: iload         8
     129: aaload
     130: astore        7
     132: aload         5
     134: aload_0
     135: getfield      #18                 // Field _env:Lorg/eclipse/jdt/internal/compiler/apt/dispatch/BaseProcessingEnvImpl;
     138: invokevirtual #42                 // Method org/eclipse/jdt/internal/compiler/apt/dispatch/BaseProcessingEnvImpl.getFactory:()Lorg/eclipse/jdt/internal/compiler/apt/model/Factory;
     141: aload         7
     143: invokevirtual #123                // Method org/eclipse/jdt/internal/compiler/apt/model/Factory.newTypeMirror:(Lorg/eclipse/jdt/internal/compiler/lookup/Binding;)Ljavax/lang/model/type/TypeMirror;
     146: invokevirtual #252                // Method java/util/ArrayList.add:(Ljava/lang/Object;)Z
     149: pop
     150: iinc          8, 1
     153: iload         8
     155: iload         9
     157: if_icmplt     125
     160: aload         5
     162: invokestatic  #259                // Method java/util/Collections.unmodifiableList:(Ljava/util/List;)Ljava/util/List;
     165: areturn
     166: invokestatic  #265                // Method java/util/Collections.emptyList:()Ljava/util/List;
     169: areturn

  public javax.lang.model.type.TypeMirror erasure(javax.lang.model.type.TypeMirror);
    Code:
       0: aload_1
       1: checkcast     #48                 // class org/eclipse/jdt/internal/compiler/apt/model/TypeMirrorImpl
       4: astore_2
       5: aload_2
       6: getfield      #245                // Field org/eclipse/jdt/internal/compiler/apt/model/TypeMirrorImpl._binding:Lorg/eclipse/jdt/internal/compiler/lookup/Binding;
       9: astore_3
      10: aload_3
      11: instanceof    #73                 // class org/eclipse/jdt/internal/compiler/lookup/ReferenceBinding
      14: ifeq          35
      17: aload_0
      18: getfield      #18                 // Field _env:Lorg/eclipse/jdt/internal/compiler/apt/dispatch/BaseProcessingEnvImpl;
      21: invokevirtual #42                 // Method org/eclipse/jdt/internal/compiler/apt/dispatch/BaseProcessingEnvImpl.getFactory:()Lorg/eclipse/jdt/internal/compiler/apt/model/Factory;
      24: aload_3
      25: checkcast     #73                 // class org/eclipse/jdt/internal/compiler/lookup/ReferenceBinding
      28: invokevirtual #279                // Method org/eclipse/jdt/internal/compiler/lookup/ReferenceBinding.erasure:()Lorg/eclipse/jdt/internal/compiler/lookup/TypeBinding;
      31: invokevirtual #123                // Method org/eclipse/jdt/internal/compiler/apt/model/Factory.newTypeMirror:(Lorg/eclipse/jdt/internal/compiler/lookup/Binding;)Ljavax/lang/model/type/TypeMirror;
      34: areturn
      35: aload_3
      36: instanceof    #282                // class org/eclipse/jdt/internal/compiler/lookup/ArrayBinding
      39: ifeq          82
      42: aload_3
      43: checkcast     #93                 // class org/eclipse/jdt/internal/compiler/lookup/TypeBinding
      46: astore        4
      48: aload_0
      49: getfield      #18                 // Field _env:Lorg/eclipse/jdt/internal/compiler/apt/dispatch/BaseProcessingEnvImpl;
      52: invokevirtual #42                 // Method org/eclipse/jdt/internal/compiler/apt/dispatch/BaseProcessingEnvImpl.getFactory:()Lorg/eclipse/jdt/internal/compiler/apt/model/Factory;
      55: aload_0
      56: getfield      #18                 // Field _env:Lorg/eclipse/jdt/internal/compiler/apt/dispatch/BaseProcessingEnvImpl;
      59: invokevirtual #197                // Method org/eclipse/jdt/internal/compiler/apt/dispatch/BaseProcessingEnvImpl.getLookupEnvironment:()Lorg/eclipse/jdt/internal/compiler/lookup/LookupEnvironment;
      62: aload         4
      64: invokevirtual #284                // Method org/eclipse/jdt/internal/compiler/lookup/TypeBinding.leafComponentType:()Lorg/eclipse/jdt/internal/compiler/lookup/TypeBinding;
      67: invokevirtual #287                // Method org/eclipse/jdt/internal/compiler/lookup/TypeBinding.erasure:()Lorg/eclipse/jdt/internal/compiler/lookup/TypeBinding;
      70: aload         4
      72: invokevirtual #288                // Method org/eclipse/jdt/internal/compiler/lookup/TypeBinding.dimensions:()I
      75: invokevirtual #291                // Method org/eclipse/jdt/internal/compiler/lookup/LookupEnvironment.createArrayType:(Lorg/eclipse/jdt/internal/compiler/lookup/TypeBinding;I)Lorg/eclipse/jdt/internal/compiler/lookup/ArrayBinding;
      78: invokevirtual #123                // Method org/eclipse/jdt/internal/compiler/apt/model/Factory.newTypeMirror:(Lorg/eclipse/jdt/internal/compiler/lookup/Binding;)Ljavax/lang/model/type/TypeMirror;
      81: areturn
      82: aload_1
      83: areturn

  public javax.lang.model.type.ArrayType getArrayType(javax.lang.model.type.TypeMirror);
    Code:
       0: aload_1
       1: checkcast     #48                 // class org/eclipse/jdt/internal/compiler/apt/model/TypeMirrorImpl
       4: astore_2
       5: aload_2
       6: getfield      #245                // Field org/eclipse/jdt/internal/compiler/apt/model/TypeMirrorImpl._binding:Lorg/eclipse/jdt/internal/compiler/lookup/Binding;
       9: checkcast     #93                 // class org/eclipse/jdt/internal/compiler/lookup/TypeBinding
      12: astore_3
      13: aload_0
      14: getfield      #18                 // Field _env:Lorg/eclipse/jdt/internal/compiler/apt/dispatch/BaseProcessingEnvImpl;
      17: invokevirtual #42                 // Method org/eclipse/jdt/internal/compiler/apt/dispatch/BaseProcessingEnvImpl.getFactory:()Lorg/eclipse/jdt/internal/compiler/apt/model/Factory;
      20: aload_0
      21: getfield      #18                 // Field _env:Lorg/eclipse/jdt/internal/compiler/apt/dispatch/BaseProcessingEnvImpl;
      24: invokevirtual #197                // Method org/eclipse/jdt/internal/compiler/apt/dispatch/BaseProcessingEnvImpl.getLookupEnvironment:()Lorg/eclipse/jdt/internal/compiler/lookup/LookupEnvironment;
      27: aload_3
      28: invokevirtual #284                // Method org/eclipse/jdt/internal/compiler/lookup/TypeBinding.leafComponentType:()Lorg/eclipse/jdt/internal/compiler/lookup/TypeBinding;
      31: aload_3
      32: invokevirtual #288                // Method org/eclipse/jdt/internal/compiler/lookup/TypeBinding.dimensions:()I
      35: iconst_1
      36: iadd
      37: invokevirtual #291                // Method org/eclipse/jdt/internal/compiler/lookup/LookupEnvironment.createArrayType:(Lorg/eclipse/jdt/internal/compiler/lookup/TypeBinding;I)Lorg/eclipse/jdt/internal/compiler/lookup/ArrayBinding;
      40: invokevirtual #123                // Method org/eclipse/jdt/internal/compiler/apt/model/Factory.newTypeMirror:(Lorg/eclipse/jdt/internal/compiler/lookup/Binding;)Ljavax/lang/model/type/TypeMirror;
      43: checkcast     #298                // class javax/lang/model/type/ArrayType
      46: areturn

  public javax.lang.model.type.DeclaredType getDeclaredType(javax.lang.model.element.TypeElement, javax.lang.model.type.TypeMirror...);
    Code:
       0: aload_2
       1: arraylength
       2: istore_3
       3: aload_1
       4: checkcast     #303                // class org/eclipse/jdt/internal/compiler/apt/model/TypeElementImpl
       7: astore        4
       9: aload         4
      11: getfield      #305                // Field org/eclipse/jdt/internal/compiler/apt/model/TypeElementImpl._binding:Lorg/eclipse/jdt/internal/compiler/lookup/Binding;
      14: checkcast     #73                 // class org/eclipse/jdt/internal/compiler/lookup/ReferenceBinding
      17: astore        5
      19: aload         5
      21: invokevirtual #306                // Method org/eclipse/jdt/internal/compiler/lookup/ReferenceBinding.typeVariables:()[Lorg/eclipse/jdt/internal/compiler/lookup/TypeVariableBinding;
      24: astore        6
      26: aload         6
      28: arraylength
      29: istore        7
      31: iload_3
      32: ifne          80
      35: aload         5
      37: invokevirtual #310                // Method org/eclipse/jdt/internal/compiler/lookup/ReferenceBinding.isGenericType:()Z
      40: ifeq          70
      43: aload_0
      44: getfield      #18                 // Field _env:Lorg/eclipse/jdt/internal/compiler/apt/dispatch/BaseProcessingEnvImpl;
      47: invokevirtual #42                 // Method org/eclipse/jdt/internal/compiler/apt/dispatch/BaseProcessingEnvImpl.getFactory:()Lorg/eclipse/jdt/internal/compiler/apt/model/Factory;
      50: aload_0
      51: getfield      #18                 // Field _env:Lorg/eclipse/jdt/internal/compiler/apt/dispatch/BaseProcessingEnvImpl;
      54: invokevirtual #197                // Method org/eclipse/jdt/internal/compiler/apt/dispatch/BaseProcessingEnvImpl.getLookupEnvironment:()Lorg/eclipse/jdt/internal/compiler/lookup/LookupEnvironment;
      57: aload         5
      59: aconst_null
      60: invokevirtual #314                // Method org/eclipse/jdt/internal/compiler/lookup/LookupEnvironment.createRawType:(Lorg/eclipse/jdt/internal/compiler/lookup/ReferenceBinding;Lorg/eclipse/jdt/internal/compiler/lookup/ReferenceBinding;)Lorg/eclipse/jdt/internal/compiler/lookup/RawTypeBinding;
      63: invokevirtual #123                // Method org/eclipse/jdt/internal/compiler/apt/model/Factory.newTypeMirror:(Lorg/eclipse/jdt/internal/compiler/lookup/Binding;)Ljavax/lang/model/type/TypeMirror;
      66: checkcast     #182                // class javax/lang/model/type/DeclaredType
      69: areturn
      70: aload_1
      71: invokeinterface #318,  1          // InterfaceMethod javax/lang/model/element/TypeElement.asType:()Ljavax/lang/model/type/TypeMirror;
      76: checkcast     #182                // class javax/lang/model/type/DeclaredType
      79: areturn
      80: iload_3
      81: iload         7
      83: if_icmpeq     97
      86: new           #98                 // class java/lang/IllegalArgumentException
      89: dup
      90: ldc_w         #322                // String Number of typeArguments doesn\'t match the number of formal parameters of typeElem
      93: invokespecial #102                // Method java/lang/IllegalArgumentException."<init>":(Ljava/lang/String;)V
      96: athrow
      97: iload_3
      98: anewarray     #93                 // class org/eclipse/jdt/internal/compiler/lookup/TypeBinding
     101: astore        8
     103: iconst_0
     104: istore        9
     106: goto          172
     109: aload_2
     110: iload         9
     112: aaload
     113: checkcast     #48                 // class org/eclipse/jdt/internal/compiler/apt/model/TypeMirrorImpl
     116: astore        10
     118: aload         10
     120: getfield      #245                // Field org/eclipse/jdt/internal/compiler/apt/model/TypeMirrorImpl._binding:Lorg/eclipse/jdt/internal/compiler/lookup/Binding;
     123: astore        11
     125: aload         11
     127: instanceof    #93                 // class org/eclipse/jdt/internal/compiler/lookup/TypeBinding
     130: ifne          159
     133: new           #98                 // class java/lang/IllegalArgumentException
     136: dup
     137: new           #152                // class java/lang/StringBuilder
     140: dup
     141: ldc_w         #324                // String Invalid type argument:
     144: invokespecial #156                // Method java/lang/StringBuilder."<init>":(Ljava/lang/String;)V
     147: aload         10
     149: invokevirtual #157                // Method java/lang/StringBuilder.append:(Ljava/lang/Object;)Ljava/lang/StringBuilder;
     152: invokevirtual #161                // Method java/lang/StringBuilder.toString:()Ljava/lang/String;
     155: invokespecial #102                // Method java/lang/IllegalArgumentException."<init>":(Ljava/lang/String;)V
     158: athrow
     159: aload         8
     161: iload         9
     163: aload         11
     165: checkcast     #93                 // class org/eclipse/jdt/internal/compiler/lookup/TypeBinding
     168: aastore
     169: iinc          9, 1
     172: iload         9
     174: iload_3
     175: if_icmplt     109
     178: aload_0
     179: getfield      #18                 // Field _env:Lorg/eclipse/jdt/internal/compiler/apt/dispatch/BaseProcessingEnvImpl;
     182: invokevirtual #42                 // Method org/eclipse/jdt/internal/compiler/apt/dispatch/BaseProcessingEnvImpl.getFactory:()Lorg/eclipse/jdt/internal/compiler/apt/model/Factory;
     185: aload_0
     186: getfield      #18                 // Field _env:Lorg/eclipse/jdt/internal/compiler/apt/dispatch/BaseProcessingEnvImpl;
     189: invokevirtual #197                // Method org/eclipse/jdt/internal/compiler/apt/dispatch/BaseProcessingEnvImpl.getLookupEnvironment:()Lorg/eclipse/jdt/internal/compiler/lookup/LookupEnvironment;
     192: aload         5
     194: aload         8
     196: aconst_null
     197: invokevirtual #326                // Method org/eclipse/jdt/internal/compiler/lookup/LookupEnvironment.createParameterizedType:(Lorg/eclipse/jdt/internal/compiler/lookup/ReferenceBinding;[Lorg/eclipse/jdt/internal/compiler/lookup/TypeBinding;Lorg/eclipse/jdt/internal/compiler/lookup/ReferenceBinding;)Lorg/eclipse/jdt/internal/compiler/lookup/ParameterizedTypeBinding;
     200: invokevirtual #123                // Method org/eclipse/jdt/internal/compiler/apt/model/Factory.newTypeMirror:(Lorg/eclipse/jdt/internal/compiler/lookup/Binding;)Ljavax/lang/model/type/TypeMirror;
     203: checkcast     #182                // class javax/lang/model/type/DeclaredType
     206: areturn

  public javax.lang.model.type.DeclaredType getDeclaredType(javax.lang.model.type.DeclaredType, javax.lang.model.element.TypeElement, javax.lang.model.type.TypeMirror...);
    Code:
       0: aload_3
       1: arraylength
       2: istore        4
       4: aload_2
       5: checkcast     #303                // class org/eclipse/jdt/internal/compiler/apt/model/TypeElementImpl
       8: astore        5
      10: aload         5
      12: getfield      #305                // Field org/eclipse/jdt/internal/compiler/apt/model/TypeElementImpl._binding:Lorg/eclipse/jdt/internal/compiler/lookup/Binding;
      15: checkcast     #73                 // class org/eclipse/jdt/internal/compiler/lookup/ReferenceBinding
      18: astore        6
      20: aload         6
      22: invokevirtual #306                // Method org/eclipse/jdt/internal/compiler/lookup/ReferenceBinding.typeVariables:()[Lorg/eclipse/jdt/internal/compiler/lookup/TypeVariableBinding;
      25: astore        7
      27: aload         7
      29: arraylength
      30: istore        8
      32: aload_1
      33: checkcast     #67                 // class org/eclipse/jdt/internal/compiler/apt/model/DeclaredTypeImpl
      36: astore        9
      38: aload         9
      40: getfield      #69                 // Field org/eclipse/jdt/internal/compiler/apt/model/DeclaredTypeImpl._binding:Lorg/eclipse/jdt/internal/compiler/lookup/Binding;
      43: checkcast     #73                 // class org/eclipse/jdt/internal/compiler/lookup/ReferenceBinding
      46: astore        10
      48: iload         4
      50: ifne          100
      53: aload         6
      55: invokevirtual #310                // Method org/eclipse/jdt/internal/compiler/lookup/ReferenceBinding.isGenericType:()Z
      58: ifeq          89
      61: aload_0
      62: getfield      #18                 // Field _env:Lorg/eclipse/jdt/internal/compiler/apt/dispatch/BaseProcessingEnvImpl;
      65: invokevirtual #42                 // Method org/eclipse/jdt/internal/compiler/apt/dispatch/BaseProcessingEnvImpl.getFactory:()Lorg/eclipse/jdt/internal/compiler/apt/model/Factory;
      68: aload_0
      69: getfield      #18                 // Field _env:Lorg/eclipse/jdt/internal/compiler/apt/dispatch/BaseProcessingEnvImpl;
      72: invokevirtual #197                // Method org/eclipse/jdt/internal/compiler/apt/dispatch/BaseProcessingEnvImpl.getLookupEnvironment:()Lorg/eclipse/jdt/internal/compiler/lookup/LookupEnvironment;
      75: aload         6
      77: aload         10
      79: invokevirtual #314                // Method org/eclipse/jdt/internal/compiler/lookup/LookupEnvironment.createRawType:(Lorg/eclipse/jdt/internal/compiler/lookup/ReferenceBinding;Lorg/eclipse/jdt/internal/compiler/lookup/ReferenceBinding;)Lorg/eclipse/jdt/internal/compiler/lookup/RawTypeBinding;
      82: invokevirtual #123                // Method org/eclipse/jdt/internal/compiler/apt/model/Factory.newTypeMirror:(Lorg/eclipse/jdt/internal/compiler/lookup/Binding;)Ljavax/lang/model/type/TypeMirror;
      85: checkcast     #182                // class javax/lang/model/type/DeclaredType
      88: areturn
      89: new           #219                // class java/lang/UnsupportedOperationException
      92: dup
      93: ldc_w         #347                // String NYI: TypesImpl.getDeclaredType(...) for member types
      96: invokespecial #223                // Method java/lang/UnsupportedOperationException."<init>":(Ljava/lang/String;)V
      99: athrow
     100: iload         4
     102: iload         8
     104: if_icmpeq     118
     107: new           #98                 // class java/lang/IllegalArgumentException
     110: dup
     111: ldc_w         #322                // String Number of typeArguments doesn\'t match the number of formal parameters of typeElem
     114: invokespecial #102                // Method java/lang/IllegalArgumentException."<init>":(Ljava/lang/String;)V
     117: athrow
     118: iload         4
     120: anewarray     #93                 // class org/eclipse/jdt/internal/compiler/lookup/TypeBinding
     123: astore        11
     125: iconst_0
     126: istore        12
     128: goto          194
     131: aload_3
     132: iload         12
     134: aaload
     135: checkcast     #48                 // class org/eclipse/jdt/internal/compiler/apt/model/TypeMirrorImpl
     138: astore        13
     140: aload         13
     142: getfield      #245                // Field org/eclipse/jdt/internal/compiler/apt/model/TypeMirrorImpl._binding:Lorg/eclipse/jdt/internal/compiler/lookup/Binding;
     145: astore        14
     147: aload         14
     149: instanceof    #93                 // class org/eclipse/jdt/internal/compiler/lookup/TypeBinding
     152: ifne          181
     155: new           #98                 // class java/lang/IllegalArgumentException
     158: dup
     159: new           #152                // class java/lang/StringBuilder
     162: dup
     163: ldc_w         #349                // String Invalid type for a type arguments :
     166: invokespecial #156                // Method java/lang/StringBuilder."<init>":(Ljava/lang/String;)V
     169: aload         13
     171: invokevirtual #157                // Method java/lang/StringBuilder.append:(Ljava/lang/Object;)Ljava/lang/StringBuilder;
     174: invokevirtual #161                // Method java/lang/StringBuilder.toString:()Ljava/lang/String;
     177: invokespecial #102                // Method java/lang/IllegalArgumentException."<init>":(Ljava/lang/String;)V
     180: athrow
     181: aload         11
     183: iload         12
     185: aload         14
     187: checkcast     #93                 // class org/eclipse/jdt/internal/compiler/lookup/TypeBinding
     190: aastore
     191: iinc          12, 1
     194: iload         12
     196: iload         4
     198: if_icmplt     131
     201: aload_0
     202: getfield      #18                 // Field _env:Lorg/eclipse/jdt/internal/compiler/apt/dispatch/BaseProcessingEnvImpl;
     205: invokevirtual #42                 // Method org/eclipse/jdt/internal/compiler/apt/dispatch/BaseProcessingEnvImpl.getFactory:()Lorg/eclipse/jdt/internal/compiler/apt/model/Factory;
     208: aload_0
     209: getfield      #18                 // Field _env:Lorg/eclipse/jdt/internal/compiler/apt/dispatch/BaseProcessingEnvImpl;
     212: invokevirtual #197                // Method org/eclipse/jdt/internal/compiler/apt/dispatch/BaseProcessingEnvImpl.getLookupEnvironment:()Lorg/eclipse/jdt/internal/compiler/lookup/LookupEnvironment;
     215: aload         6
     217: aload         11
     219: aload         10
     221: invokevirtual #326                // Method org/eclipse/jdt/internal/compiler/lookup/LookupEnvironment.createParameterizedType:(Lorg/eclipse/jdt/internal/compiler/lookup/ReferenceBinding;[Lorg/eclipse/jdt/internal/compiler/lookup/TypeBinding;Lorg/eclipse/jdt/internal/compiler/lookup/ReferenceBinding;)Lorg/eclipse/jdt/internal/compiler/lookup/ParameterizedTypeBinding;
     224: invokevirtual #123                // Method org/eclipse/jdt/internal/compiler/apt/model/Factory.newTypeMirror:(Lorg/eclipse/jdt/internal/compiler/lookup/Binding;)Ljavax/lang/model/type/TypeMirror;
     227: checkcast     #182                // class javax/lang/model/type/DeclaredType
     230: areturn

  public javax.lang.model.type.NoType getNoType(javax.lang.model.type.TypeKind);
    Code:
       0: aload_0
       1: getfield      #18                 // Field _env:Lorg/eclipse/jdt/internal/compiler/apt/dispatch/BaseProcessingEnvImpl;
       4: invokevirtual #42                 // Method org/eclipse/jdt/internal/compiler/apt/dispatch/BaseProcessingEnvImpl.getFactory:()Lorg/eclipse/jdt/internal/compiler/apt/model/Factory;
       7: aload_1
       8: invokevirtual #353                // Method org/eclipse/jdt/internal/compiler/apt/model/Factory.getNoType:(Ljavax/lang/model/type/TypeKind;)Ljavax/lang/model/type/NoType;
      11: areturn

  public javax.lang.model.type.NullType getNullType();
    Code:
       0: aload_0
       1: getfield      #18                 // Field _env:Lorg/eclipse/jdt/internal/compiler/apt/dispatch/BaseProcessingEnvImpl;
       4: invokevirtual #42                 // Method org/eclipse/jdt/internal/compiler/apt/dispatch/BaseProcessingEnvImpl.getFactory:()Lorg/eclipse/jdt/internal/compiler/apt/model/Factory;
       7: invokevirtual #359                // Method org/eclipse/jdt/internal/compiler/apt/model/Factory.getNullType:()Ljavax/lang/model/type/NullType;
      10: areturn

  public javax.lang.model.type.PrimitiveType getPrimitiveType(javax.lang.model.type.TypeKind);
    Code:
       0: aload_0
       1: getfield      #18                 // Field _env:Lorg/eclipse/jdt/internal/compiler/apt/dispatch/BaseProcessingEnvImpl;
       4: invokevirtual #42                 // Method org/eclipse/jdt/internal/compiler/apt/dispatch/BaseProcessingEnvImpl.getFactory:()Lorg/eclipse/jdt/internal/compiler/apt/model/Factory;
       7: aload_1
       8: invokevirtual #363                // Method org/eclipse/jdt/internal/compiler/apt/model/Factory.getPrimitiveType:(Ljavax/lang/model/type/TypeKind;)Lorg/eclipse/jdt/internal/compiler/apt/model/PrimitiveTypeImpl;
      11: areturn

  public javax.lang.model.type.WildcardType getWildcardType(javax.lang.model.type.TypeMirror, javax.lang.model.type.TypeMirror);
    Code:
       0: aload_1
       1: ifnull        19
       4: aload_2
       5: ifnull        19
       8: new           #98                 // class java/lang/IllegalArgumentException
      11: dup
      12: ldc_w         #368                // String Extends and super bounds cannot be set at the same time
      15: invokespecial #102                // Method java/lang/IllegalArgumentException."<init>":(Ljava/lang/String;)V
      18: athrow
      19: aload_1
      20: ifnull        67
      23: aload_1
      24: checkcast     #48                 // class org/eclipse/jdt/internal/compiler/apt/model/TypeMirrorImpl
      27: astore_3
      28: aload_3
      29: getfield      #245                // Field org/eclipse/jdt/internal/compiler/apt/model/TypeMirrorImpl._binding:Lorg/eclipse/jdt/internal/compiler/lookup/Binding;
      32: checkcast     #93                 // class org/eclipse/jdt/internal/compiler/lookup/TypeBinding
      35: astore        4
      37: aload_0
      38: getfield      #18                 // Field _env:Lorg/eclipse/jdt/internal/compiler/apt/dispatch/BaseProcessingEnvImpl;
      41: invokevirtual #42                 // Method org/eclipse/jdt/internal/compiler/apt/dispatch/BaseProcessingEnvImpl.getFactory:()Lorg/eclipse/jdt/internal/compiler/apt/model/Factory;
      44: aload_0
      45: getfield      #18                 // Field _env:Lorg/eclipse/jdt/internal/compiler/apt/dispatch/BaseProcessingEnvImpl;
      48: invokevirtual #197                // Method org/eclipse/jdt/internal/compiler/apt/dispatch/BaseProcessingEnvImpl.getLookupEnvironment:()Lorg/eclipse/jdt/internal/compiler/lookup/LookupEnvironment;
      51: aconst_null
      52: iconst_0
      53: aload         4
      55: aconst_null
      56: iconst_1
      57: invokevirtual #370                // Method org/eclipse/jdt/internal/compiler/lookup/LookupEnvironment.createWildcard:(Lorg/eclipse/jdt/internal/compiler/lookup/ReferenceBinding;ILorg/eclipse/jdt/internal/compiler/lookup/TypeBinding;[Lorg/eclipse/jdt/internal/compiler/lookup/TypeBinding;I)Lorg/eclipse/jdt/internal/compiler/lookup/WildcardBinding;
      60: invokevirtual #123                // Method org/eclipse/jdt/internal/compiler/apt/model/Factory.newTypeMirror:(Lorg/eclipse/jdt/internal/compiler/lookup/Binding;)Ljavax/lang/model/type/TypeMirror;
      63: checkcast     #374                // class javax/lang/model/type/WildcardType
      66: areturn
      67: aload_2
      68: ifnull        113
      71: aload_2
      72: checkcast     #48                 // class org/eclipse/jdt/internal/compiler/apt/model/TypeMirrorImpl
      75: astore_3
      76: aload_3
      77: getfield      #245                // Field org/eclipse/jdt/internal/compiler/apt/model/TypeMirrorImpl._binding:Lorg/eclipse/jdt/internal/compiler/lookup/Binding;
      80: checkcast     #93                 // class org/eclipse/jdt/internal/compiler/lookup/TypeBinding
      83: astore        4
      85: new           #376                // class org/eclipse/jdt/internal/compiler/apt/model/WildcardTypeImpl
      88: dup
      89: aload_0
      90: getfield      #18                 // Field _env:Lorg/eclipse/jdt/internal/compiler/apt/dispatch/BaseProcessingEnvImpl;
      93: aload_0
      94: getfield      #18                 // Field _env:Lorg/eclipse/jdt/internal/compiler/apt/dispatch/BaseProcessingEnvImpl;
      97: invokevirtual #197                // Method org/eclipse/jdt/internal/compiler/apt/dispatch/BaseProcessingEnvImpl.getLookupEnvironment:()Lorg/eclipse/jdt/internal/compiler/lookup/LookupEnvironment;
     100: aconst_null
     101: iconst_0
     102: aload         4
     104: aconst_null
     105: iconst_2
     106: invokevirtual #370                // Method org/eclipse/jdt/internal/compiler/lookup/LookupEnvironment.createWildcard:(Lorg/eclipse/jdt/internal/compiler/lookup/ReferenceBinding;ILorg/eclipse/jdt/internal/compiler/lookup/TypeBinding;[Lorg/eclipse/jdt/internal/compiler/lookup/TypeBinding;I)Lorg/eclipse/jdt/internal/compiler/lookup/WildcardBinding;
     109: invokespecial #378                // Method org/eclipse/jdt/internal/compiler/apt/model/WildcardTypeImpl."<init>":(Lorg/eclipse/jdt/internal/compiler/apt/dispatch/BaseProcessingEnvImpl;Lorg/eclipse/jdt/internal/compiler/lookup/WildcardBinding;)V
     112: areturn
     113: new           #376                // class org/eclipse/jdt/internal/compiler/apt/model/WildcardTypeImpl
     116: dup
     117: aload_0
     118: getfield      #18                 // Field _env:Lorg/eclipse/jdt/internal/compiler/apt/dispatch/BaseProcessingEnvImpl;
     121: aload_0
     122: getfield      #18                 // Field _env:Lorg/eclipse/jdt/internal/compiler/apt/dispatch/BaseProcessingEnvImpl;
     125: invokevirtual #197                // Method org/eclipse/jdt/internal/compiler/apt/dispatch/BaseProcessingEnvImpl.getLookupEnvironment:()Lorg/eclipse/jdt/internal/compiler/lookup/LookupEnvironment;
     128: aconst_null
     129: iconst_0
     130: aconst_null
     131: aconst_null
     132: iconst_0
     133: invokevirtual #370                // Method org/eclipse/jdt/internal/compiler/lookup/LookupEnvironment.createWildcard:(Lorg/eclipse/jdt/internal/compiler/lookup/ReferenceBinding;ILorg/eclipse/jdt/internal/compiler/lookup/TypeBinding;[Lorg/eclipse/jdt/internal/compiler/lookup/TypeBinding;I)Lorg/eclipse/jdt/internal/compiler/lookup/WildcardBinding;
     136: invokespecial #378                // Method org/eclipse/jdt/internal/compiler/apt/model/WildcardTypeImpl."<init>":(Lorg/eclipse/jdt/internal/compiler/apt/dispatch/BaseProcessingEnvImpl;Lorg/eclipse/jdt/internal/compiler/lookup/WildcardBinding;)V
     139: areturn

  public boolean isAssignable(javax.lang.model.type.TypeMirror, javax.lang.model.type.TypeMirror);
    Code:
       0: aload_1
       1: instanceof    #48                 // class org/eclipse/jdt/internal/compiler/apt/model/TypeMirrorImpl
       4: ifeq          14
       7: aload_2
       8: instanceof    #48                 // class org/eclipse/jdt/internal/compiler/apt/model/TypeMirrorImpl
      11: ifne          16
      14: iconst_0
      15: ireturn
      16: aload_1
      17: checkcast     #48                 // class org/eclipse/jdt/internal/compiler/apt/model/TypeMirrorImpl
      20: invokevirtual #50                 // Method org/eclipse/jdt/internal/compiler/apt/model/TypeMirrorImpl.binding:()Lorg/eclipse/jdt/internal/compiler/lookup/Binding;
      23: astore_3
      24: aload_2
      25: checkcast     #48                 // class org/eclipse/jdt/internal/compiler/apt/model/TypeMirrorImpl
      28: invokevirtual #50                 // Method org/eclipse/jdt/internal/compiler/apt/model/TypeMirrorImpl.binding:()Lorg/eclipse/jdt/internal/compiler/lookup/Binding;
      31: astore        4
      33: aload_3
      34: instanceof    #93                 // class org/eclipse/jdt/internal/compiler/lookup/TypeBinding
      37: ifeq          48
      40: aload         4
      42: instanceof    #93                 // class org/eclipse/jdt/internal/compiler/lookup/TypeBinding
      45: ifne          56
      48: new           #98                 // class java/lang/IllegalArgumentException
      51: dup
      52: invokespecial #386                // Method java/lang/IllegalArgumentException."<init>":()V
      55: athrow
      56: aload_3
      57: checkcast     #93                 // class org/eclipse/jdt/internal/compiler/lookup/TypeBinding
      60: aload         4
      62: checkcast     #93                 // class org/eclipse/jdt/internal/compiler/lookup/TypeBinding
      65: invokevirtual #387                // Method org/eclipse/jdt/internal/compiler/lookup/TypeBinding.isCompatibleWith:(Lorg/eclipse/jdt/internal/compiler/lookup/TypeBinding;)Z
      68: ifeq          73
      71: iconst_1
      72: ireturn
      73: aload_0
      74: getfield      #18                 // Field _env:Lorg/eclipse/jdt/internal/compiler/apt/dispatch/BaseProcessingEnvImpl;
      77: invokevirtual #197                // Method org/eclipse/jdt/internal/compiler/apt/dispatch/BaseProcessingEnvImpl.getLookupEnvironment:()Lorg/eclipse/jdt/internal/compiler/lookup/LookupEnvironment;
      80: aload_3
      81: checkcast     #93                 // class org/eclipse/jdt/internal/compiler/lookup/TypeBinding
      84: invokevirtual #201                // Method org/eclipse/jdt/internal/compiler/lookup/LookupEnvironment.computeBoxingType:(Lorg/eclipse/jdt/internal/compiler/lookup/TypeBinding;)Lorg/eclipse/jdt/internal/compiler/lookup/TypeBinding;
      87: astore        5
      89: aload         5
      91: ifnull        109
      94: aload         5
      96: aload         4
      98: checkcast     #93                 // class org/eclipse/jdt/internal/compiler/lookup/TypeBinding
     101: invokevirtual #387                // Method org/eclipse/jdt/internal/compiler/lookup/TypeBinding.isCompatibleWith:(Lorg/eclipse/jdt/internal/compiler/lookup/TypeBinding;)Z
     104: ifeq          109
     107: iconst_1
     108: ireturn
     109: iconst_0
     110: ireturn

  public boolean isSameType(javax.lang.model.type.TypeMirror, javax.lang.model.type.TypeMirror);
    Code:
       0: aload_1
       1: invokeinterface #30,  1           // InterfaceMethod javax/lang/model/type/TypeMirror.getKind:()Ljavax/lang/model/type/TypeKind;
       6: getstatic     #395                // Field javax/lang/model/type/TypeKind.WILDCARD:Ljavax/lang/model/type/TypeKind;
       9: if_acmpeq     24
      12: aload_2
      13: invokeinterface #30,  1           // InterfaceMethod javax/lang/model/type/TypeMirror.getKind:()Ljavax/lang/model/type/TypeKind;
      18: getstatic     #395                // Field javax/lang/model/type/TypeKind.WILDCARD:Ljavax/lang/model/type/TypeKind;
      21: if_acmpne     26
      24: iconst_0
      25: ireturn
      26: aload_1
      27: aload_2
      28: if_acmpne     33
      31: iconst_1
      32: ireturn
      33: aload_1
      34: instanceof    #48                 // class org/eclipse/jdt/internal/compiler/apt/model/TypeMirrorImpl
      37: ifeq          47
      40: aload_2
      41: instanceof    #48                 // class org/eclipse/jdt/internal/compiler/apt/model/TypeMirrorImpl
      44: ifne          49
      47: iconst_0
      48: ireturn
      49: aload_1
      50: checkcast     #48                 // class org/eclipse/jdt/internal/compiler/apt/model/TypeMirrorImpl
      53: invokevirtual #50                 // Method org/eclipse/jdt/internal/compiler/apt/model/TypeMirrorImpl.binding:()Lorg/eclipse/jdt/internal/compiler/lookup/Binding;
      56: astore_3
      57: aload_2
      58: checkcast     #48                 // class org/eclipse/jdt/internal/compiler/apt/model/TypeMirrorImpl
      61: invokevirtual #50                 // Method org/eclipse/jdt/internal/compiler/apt/model/TypeMirrorImpl.binding:()Lorg/eclipse/jdt/internal/compiler/lookup/Binding;
      64: astore        4
      66: aload_3
      67: aload         4
      69: if_acmpne     74
      72: iconst_1
      73: ireturn
      74: aload_3
      75: instanceof    #93                 // class org/eclipse/jdt/internal/compiler/lookup/TypeBinding
      78: ifeq          89
      81: aload         4
      83: instanceof    #93                 // class org/eclipse/jdt/internal/compiler/lookup/TypeBinding
      86: ifne          91
      89: iconst_0
      90: ireturn
      91: aload_3
      92: checkcast     #93                 // class org/eclipse/jdt/internal/compiler/lookup/TypeBinding
      95: astore        5
      97: aload         4
      99: checkcast     #93                 // class org/eclipse/jdt/internal/compiler/lookup/TypeBinding
     102: astore        6
     104: aload         5
     106: aload         6
     108: invokestatic  #398                // Method org/eclipse/jdt/internal/compiler/lookup/TypeBinding.equalsEquals:(Lorg/eclipse/jdt/internal/compiler/lookup/TypeBinding;Lorg/eclipse/jdt/internal/compiler/lookup/TypeBinding;)Z
     111: ifeq          116
     114: iconst_1
     115: ireturn
     116: aload         5
     118: invokevirtual #401                // Method org/eclipse/jdt/internal/compiler/lookup/TypeBinding.computeUniqueKey:()[C
     121: aload         6
     123: invokevirtual #401                // Method org/eclipse/jdt/internal/compiler/lookup/TypeBinding.computeUniqueKey:()[C
     126: invokestatic  #113                // Method org/eclipse/jdt/core/compiler/CharOperation.equals:([C[C)Z
     129: ireturn

  public boolean isSubsignature(javax.lang.model.type.ExecutableType, javax.lang.model.type.ExecutableType);
    Code:
       0: aload_1
       1: checkcast     #409                // class org/eclipse/jdt/internal/compiler/apt/model/ExecutableTypeImpl
       4: getfield      #411                // Field org/eclipse/jdt/internal/compiler/apt/model/ExecutableTypeImpl._binding:Lorg/eclipse/jdt/internal/compiler/lookup/Binding;
       7: checkcast     #86                 // class org/eclipse/jdt/internal/compiler/lookup/MethodBinding
      10: astore_3
      11: aload_2
      12: checkcast     #409                // class org/eclipse/jdt/internal/compiler/apt/model/ExecutableTypeImpl
      15: getfield      #411                // Field org/eclipse/jdt/internal/compiler/apt/model/ExecutableTypeImpl._binding:Lorg/eclipse/jdt/internal/compiler/lookup/Binding;
      18: checkcast     #86                 // class org/eclipse/jdt/internal/compiler/lookup/MethodBinding
      21: astore        4
      23: aload_3
      24: getfield      #109                // Field org/eclipse/jdt/internal/compiler/lookup/MethodBinding.selector:[C
      27: aload         4
      29: getfield      #109                // Field org/eclipse/jdt/internal/compiler/lookup/MethodBinding.selector:[C
      32: invokestatic  #113                // Method org/eclipse/jdt/core/compiler/CharOperation.equals:([C[C)Z
      35: ifne          40
      38: iconst_0
      39: ireturn
      40: aload_3
      41: aload         4
      43: invokevirtual #119                // Method org/eclipse/jdt/internal/compiler/lookup/MethodBinding.areParameterErasuresEqual:(Lorg/eclipse/jdt/internal/compiler/lookup/MethodBinding;)Z
      46: ifeq          60
      49: aload_3
      50: aload         4
      52: invokevirtual #412                // Method org/eclipse/jdt/internal/compiler/lookup/MethodBinding.areTypeVariableErasuresEqual:(Lorg/eclipse/jdt/internal/compiler/lookup/MethodBinding;)Z
      55: ifeq          60
      58: iconst_1
      59: ireturn
      60: iconst_0
      61: ireturn

  public boolean isSubtype(javax.lang.model.type.TypeMirror, javax.lang.model.type.TypeMirror);
    Code:
       0: aload_1
       1: instanceof    #421                // class org/eclipse/jdt/internal/compiler/apt/model/NoTypeImpl
       4: ifeq          37
       7: aload_2
       8: instanceof    #421                // class org/eclipse/jdt/internal/compiler/apt/model/NoTypeImpl
      11: ifeq          35
      14: aload_1
      15: checkcast     #421                // class org/eclipse/jdt/internal/compiler/apt/model/NoTypeImpl
      18: invokevirtual #423                // Method org/eclipse/jdt/internal/compiler/apt/model/NoTypeImpl.getKind:()Ljavax/lang/model/type/TypeKind;
      21: aload_2
      22: checkcast     #421                // class org/eclipse/jdt/internal/compiler/apt/model/NoTypeImpl
      25: invokevirtual #423                // Method org/eclipse/jdt/internal/compiler/apt/model/NoTypeImpl.getKind:()Ljavax/lang/model/type/TypeKind;
      28: if_acmpne     33
      31: iconst_1
      32: ireturn
      33: iconst_0
      34: ireturn
      35: iconst_0
      36: ireturn
      37: aload_2
      38: instanceof    #421                // class org/eclipse/jdt/internal/compiler/apt/model/NoTypeImpl
      41: ifeq          46
      44: iconst_0
      45: ireturn
      46: aload_1
      47: instanceof    #48                 // class org/eclipse/jdt/internal/compiler/apt/model/TypeMirrorImpl
      50: ifeq          60
      53: aload_2
      54: instanceof    #48                 // class org/eclipse/jdt/internal/compiler/apt/model/TypeMirrorImpl
      57: ifne          62
      60: iconst_0
      61: ireturn
      62: aload_1
      63: aload_2
      64: if_acmpne     69
      67: iconst_1
      68: ireturn
      69: aload_1
      70: checkcast     #48                 // class org/eclipse/jdt/internal/compiler/apt/model/TypeMirrorImpl
      73: invokevirtual #50                 // Method org/eclipse/jdt/internal/compiler/apt/model/TypeMirrorImpl.binding:()Lorg/eclipse/jdt/internal/compiler/lookup/Binding;
      76: astore_3
      77: aload_2
      78: checkcast     #48                 // class org/eclipse/jdt/internal/compiler/apt/model/TypeMirrorImpl
      81: invokevirtual #50                 // Method org/eclipse/jdt/internal/compiler/apt/model/TypeMirrorImpl.binding:()Lorg/eclipse/jdt/internal/compiler/lookup/Binding;
      84: astore        4
      86: aload_3
      87: aload         4
      89: if_acmpne     94
      92: iconst_1
      93: ireturn
      94: aload_3
      95: instanceof    #93                 // class org/eclipse/jdt/internal/compiler/lookup/TypeBinding
      98: ifeq          109
     101: aload         4
     103: instanceof    #93                 // class org/eclipse/jdt/internal/compiler/lookup/TypeBinding
     106: ifne          111
     109: iconst_0
     110: ireturn
     111: aload_3
     112: invokevirtual #424                // Method org/eclipse/jdt/internal/compiler/lookup/Binding.kind:()I
     115: sipush        132
     118: if_icmpeq     132
     121: aload         4
     123: invokevirtual #424                // Method org/eclipse/jdt/internal/compiler/lookup/Binding.kind:()I
     126: sipush        132
     129: if_icmpne     159
     132: aload_3
     133: invokevirtual #424                // Method org/eclipse/jdt/internal/compiler/lookup/Binding.kind:()I
     136: aload         4
     138: invokevirtual #424                // Method org/eclipse/jdt/internal/compiler/lookup/Binding.kind:()I
     141: if_icmpeq     146
     144: iconst_0
     145: ireturn
     146: aload_3
     147: checkcast     #93                 // class org/eclipse/jdt/internal/compiler/lookup/TypeBinding
     150: aload         4
     152: checkcast     #93                 // class org/eclipse/jdt/internal/compiler/lookup/TypeBinding
     155: invokevirtual #387                // Method org/eclipse/jdt/internal/compiler/lookup/TypeBinding.isCompatibleWith:(Lorg/eclipse/jdt/internal/compiler/lookup/TypeBinding;)Z
     158: ireturn
     159: aload_3
     160: checkcast     #93                 // class org/eclipse/jdt/internal/compiler/lookup/TypeBinding
     163: aload         4
     165: checkcast     #93                 // class org/eclipse/jdt/internal/compiler/lookup/TypeBinding
     168: invokevirtual #387                // Method org/eclipse/jdt/internal/compiler/lookup/TypeBinding.isCompatibleWith:(Lorg/eclipse/jdt/internal/compiler/lookup/TypeBinding;)Z
     171: ireturn

  public javax.lang.model.type.PrimitiveType unboxedType(javax.lang.model.type.TypeMirror);
    Code:
       0: aload_1
       1: checkcast     #48                 // class org/eclipse/jdt/internal/compiler/apt/model/TypeMirrorImpl
       4: getfield      #245                // Field org/eclipse/jdt/internal/compiler/apt/model/TypeMirrorImpl._binding:Lorg/eclipse/jdt/internal/compiler/lookup/Binding;
       7: instanceof    #73                 // class org/eclipse/jdt/internal/compiler/lookup/ReferenceBinding
      10: ifne          24
      13: new           #98                 // class java/lang/IllegalArgumentException
      16: dup
      17: ldc_w         #428                // String Given type mirror cannot be unboxed
      20: invokespecial #102                // Method java/lang/IllegalArgumentException."<init>":(Ljava/lang/String;)V
      23: athrow
      24: aload_1
      25: checkcast     #48                 // class org/eclipse/jdt/internal/compiler/apt/model/TypeMirrorImpl
      28: getfield      #245                // Field org/eclipse/jdt/internal/compiler/apt/model/TypeMirrorImpl._binding:Lorg/eclipse/jdt/internal/compiler/lookup/Binding;
      31: checkcast     #73                 // class org/eclipse/jdt/internal/compiler/lookup/ReferenceBinding
      34: astore_2
      35: aload_0
      36: getfield      #18                 // Field _env:Lorg/eclipse/jdt/internal/compiler/apt/dispatch/BaseProcessingEnvImpl;
      39: invokevirtual #197                // Method org/eclipse/jdt/internal/compiler/apt/dispatch/BaseProcessingEnvImpl.getLookupEnvironment:()Lorg/eclipse/jdt/internal/compiler/lookup/LookupEnvironment;
      42: aload_2
      43: invokevirtual #201                // Method org/eclipse/jdt/internal/compiler/lookup/LookupEnvironment.computeBoxingType:(Lorg/eclipse/jdt/internal/compiler/lookup/TypeBinding;)Lorg/eclipse/jdt/internal/compiler/lookup/TypeBinding;
      46: astore_3
      47: aload_3
      48: invokevirtual #430                // Method org/eclipse/jdt/internal/compiler/lookup/TypeBinding.kind:()I
      51: sipush        132
      54: if_icmpeq     65
      57: new           #98                 // class java/lang/IllegalArgumentException
      60: dup
      61: invokespecial #386                // Method java/lang/IllegalArgumentException."<init>":()V
      64: athrow
      65: aload_0
      66: getfield      #18                 // Field _env:Lorg/eclipse/jdt/internal/compiler/apt/dispatch/BaseProcessingEnvImpl;
      69: invokevirtual #42                 // Method org/eclipse/jdt/internal/compiler/apt/dispatch/BaseProcessingEnvImpl.getFactory:()Lorg/eclipse/jdt/internal/compiler/apt/model/Factory;
      72: aload_3
      73: checkcast     #195                // class org/eclipse/jdt/internal/compiler/lookup/BaseTypeBinding
      76: invokevirtual #123                // Method org/eclipse/jdt/internal/compiler/apt/model/Factory.newTypeMirror:(Lorg/eclipse/jdt/internal/compiler/lookup/Binding;)Ljavax/lang/model/type/TypeMirror;
      79: checkcast     #431                // class javax/lang/model/type/PrimitiveType
      82: areturn

  static int[] $SWITCH_TABLE$javax$lang$model$type$TypeKind();
    Code:
       0: getstatic     #434                // Field $SWITCH_TABLE$javax$lang$model$type$TypeKind:[I
       3: dup
       4: ifnull        8
       7: areturn
       8: pop
       9: invokestatic  #436                // Method javax/lang/model/type/TypeKind.values:()[Ljavax/lang/model/type/TypeKind;
      12: arraylength
      13: newarray       int
      15: astore_0
      16: aload_0
      17: getstatic     #440                // Field javax/lang/model/type/TypeKind.ARRAY:Ljavax/lang/model/type/TypeKind;
      20: invokevirtual #36                 // Method javax/lang/model/type/TypeKind.ordinal:()I
      23: bipush        12
      25: iastore
      26: goto          30
      29: pop
      30: aload_0
      31: getstatic     #443                // Field javax/lang/model/type/TypeKind.BOOLEAN:Ljavax/lang/model/type/TypeKind;
      34: invokevirtual #36                 // Method javax/lang/model/type/TypeKind.ordinal:()I
      37: iconst_1
      38: iastore
      39: goto          43
      42: pop
      43: aload_0
      44: getstatic     #446                // Field javax/lang/model/type/TypeKind.BYTE:Ljavax/lang/model/type/TypeKind;
      47: invokevirtual #36                 // Method javax/lang/model/type/TypeKind.ordinal:()I
      50: iconst_2
      51: iastore
      52: goto          56
      55: pop
      56: aload_0
      57: getstatic     #449                // Field javax/lang/model/type/TypeKind.CHAR:Ljavax/lang/model/type/TypeKind;
      60: invokevirtual #36                 // Method javax/lang/model/type/TypeKind.ordinal:()I
      63: bipush        6
      65: iastore
      66: goto          70
      69: pop
      70: aload_0
      71: getstatic     #452                // Field javax/lang/model/type/TypeKind.DECLARED:Ljavax/lang/model/type/TypeKind;
      74: invokevirtual #36                 // Method javax/lang/model/type/TypeKind.ordinal:()I
      77: bipush        13
      79: iastore
      80: goto          84
      83: pop
      84: aload_0
      85: getstatic     #455                // Field javax/lang/model/type/TypeKind.DOUBLE:Ljavax/lang/model/type/TypeKind;
      88: invokevirtual #36                 // Method javax/lang/model/type/TypeKind.ordinal:()I
      91: bipush        8
      93: iastore
      94: goto          98
      97: pop
      98: aload_0
      99: getstatic     #458                // Field javax/lang/model/type/TypeKind.ERROR:Ljavax/lang/model/type/TypeKind;
     102: invokevirtual #36                 // Method javax/lang/model/type/TypeKind.ordinal:()I
     105: bipush        14
     107: iastore
     108: goto          112
     111: pop
     112: aload_0
     113: getstatic     #461                // Field javax/lang/model/type/TypeKind.EXECUTABLE:Ljavax/lang/model/type/TypeKind;
     116: invokevirtual #36                 // Method javax/lang/model/type/TypeKind.ordinal:()I
     119: bipush        18
     121: iastore
     122: goto          126
     125: pop
     126: aload_0
     127: getstatic     #464                // Field javax/lang/model/type/TypeKind.FLOAT:Ljavax/lang/model/type/TypeKind;
     130: invokevirtual #36                 // Method javax/lang/model/type/TypeKind.ordinal:()I
     133: bipush        7
     135: iastore
     136: goto          140
     139: pop
     140: aload_0
     141: getstatic     #467                // Field javax/lang/model/type/TypeKind.INT:Ljavax/lang/model/type/TypeKind;
     144: invokevirtual #36                 // Method javax/lang/model/type/TypeKind.ordinal:()I
     147: iconst_4
     148: iastore
     149: goto          153
     152: pop
     153: aload_0
     154: getstatic     #470                // Field javax/lang/model/type/TypeKind.LONG:Ljavax/lang/model/type/TypeKind;
     157: invokevirtual #36                 // Method javax/lang/model/type/TypeKind.ordinal:()I
     160: iconst_5
     161: iastore
     162: goto          166
     165: pop
     166: aload_0
     167: getstatic     #473                // Field javax/lang/model/type/TypeKind.NONE:Ljavax/lang/model/type/TypeKind;
     170: invokevirtual #36                 // Method javax/lang/model/type/TypeKind.ordinal:()I
     173: bipush        10
     175: iastore
     176: goto          180
     179: pop
     180: aload_0
     181: getstatic     #476                // Field javax/lang/model/type/TypeKind.NULL:Ljavax/lang/model/type/TypeKind;
     184: invokevirtual #36                 // Method javax/lang/model/type/TypeKind.ordinal:()I
     187: bipush        11
     189: iastore
     190: goto          194
     193: pop
     194: aload_0
     195: getstatic     #479                // Field javax/lang/model/type/TypeKind.OTHER:Ljavax/lang/model/type/TypeKind;
     198: invokevirtual #36                 // Method javax/lang/model/type/TypeKind.ordinal:()I
     201: bipush        19
     203: iastore
     204: goto          208
     207: pop
     208: aload_0
     209: getstatic     #482                // Field javax/lang/model/type/TypeKind.PACKAGE:Ljavax/lang/model/type/TypeKind;
     212: invokevirtual #36                 // Method javax/lang/model/type/TypeKind.ordinal:()I
     215: bipush        17
     217: iastore
     218: goto          222
     221: pop
     222: aload_0
     223: getstatic     #485                // Field javax/lang/model/type/TypeKind.SHORT:Ljavax/lang/model/type/TypeKind;
     226: invokevirtual #36                 // Method javax/lang/model/type/TypeKind.ordinal:()I
     229: iconst_3
     230: iastore
     231: goto          235
     234: pop
     235: aload_0
     236: getstatic     #488                // Field javax/lang/model/type/TypeKind.TYPEVAR:Ljavax/lang/model/type/TypeKind;
     239: invokevirtual #36                 // Method javax/lang/model/type/TypeKind.ordinal:()I
     242: bipush        15
     244: iastore
     245: goto          249
     248: pop
     249: aload_0
     250: getstatic     #491                // Field javax/lang/model/type/TypeKind.VOID:Ljavax/lang/model/type/TypeKind;
     253: invokevirtual #36                 // Method javax/lang/model/type/TypeKind.ordinal:()I
     256: bipush        9
     258: iastore
     259: goto          263
     262: pop
     263: aload_0
     264: getstatic     #395                // Field javax/lang/model/type/TypeKind.WILDCARD:Ljavax/lang/model/type/TypeKind;
     267: invokevirtual #36                 // Method javax/lang/model/type/TypeKind.ordinal:()I
     270: bipush        16
     272: iastore
     273: goto          277
     276: pop
     277: aload_0
     278: dup
     279: putstatic     #434                // Field $SWITCH_TABLE$javax$lang$model$type$TypeKind:[I
     282: areturn
    Exception table:
       from    to  target type
          16    26    29   Class java/lang/NoSuchFieldError
          30    39    42   Class java/lang/NoSuchFieldError
          43    52    55   Class java/lang/NoSuchFieldError
          56    66    69   Class java/lang/NoSuchFieldError
          70    80    83   Class java/lang/NoSuchFieldError
          84    94    97   Class java/lang/NoSuchFieldError
          98   108   111   Class java/lang/NoSuchFieldError
         112   122   125   Class java/lang/NoSuchFieldError
         126   136   139   Class java/lang/NoSuchFieldError
         140   149   152   Class java/lang/NoSuchFieldError
         153   162   165   Class java/lang/NoSuchFieldError
         166   176   179   Class java/lang/NoSuchFieldError
         180   190   193   Class java/lang/NoSuchFieldError
         194   204   207   Class java/lang/NoSuchFieldError
         208   218   221   Class java/lang/NoSuchFieldError
         222   231   234   Class java/lang/NoSuchFieldError
         235   245   248   Class java/lang/NoSuchFieldError
         249   259   262   Class java/lang/NoSuchFieldError
         263   273   276   Class java/lang/NoSuchFieldError

  static int[] $SWITCH_TABLE$javax$lang$model$element$ElementKind();
    Code:
       0: getstatic     #497                // Field $SWITCH_TABLE$javax$lang$model$element$ElementKind:[I
       3: dup
       4: ifnull        8
       7: areturn
       8: pop
       9: invokestatic  #499                // Method javax/lang/model/element/ElementKind.values:()[Ljavax/lang/model/element/ElementKind;
      12: arraylength
      13: newarray       int
      15: astore_0
      16: aload_0
      17: getstatic     #502                // Field javax/lang/model/element/ElementKind.ANNOTATION_TYPE:Ljavax/lang/model/element/ElementKind;
      20: invokevirtual #82                 // Method javax/lang/model/element/ElementKind.ordinal:()I
      23: iconst_4
      24: iastore
      25: goto          29
      28: pop
      29: aload_0
      30: getstatic     #506                // Field javax/lang/model/element/ElementKind.CLASS:Ljavax/lang/model/element/ElementKind;
      33: invokevirtual #82                 // Method javax/lang/model/element/ElementKind.ordinal:()I
      36: iconst_3
      37: iastore
      38: goto          42
      41: pop
      42: aload_0
      43: getstatic     #509                // Field javax/lang/model/element/ElementKind.CONSTRUCTOR:Ljavax/lang/model/element/ElementKind;
      46: invokevirtual #82                 // Method javax/lang/model/element/ElementKind.ordinal:()I
      49: bipush        12
      51: iastore
      52: goto          56
      55: pop
      56: aload_0
      57: getstatic     #512                // Field javax/lang/model/element/ElementKind.ENUM:Ljavax/lang/model/element/ElementKind;
      60: invokevirtual #82                 // Method javax/lang/model/element/ElementKind.ordinal:()I
      63: iconst_2
      64: iastore
      65: goto          69
      68: pop
      69: aload_0
      70: getstatic     #515                // Field javax/lang/model/element/ElementKind.ENUM_CONSTANT:Ljavax/lang/model/element/ElementKind;
      73: invokevirtual #82                 // Method javax/lang/model/element/ElementKind.ordinal:()I
      76: bipush        6
      78: iastore
      79: goto          83
      82: pop
      83: aload_0
      84: getstatic     #518                // Field javax/lang/model/element/ElementKind.EXCEPTION_PARAMETER:Ljavax/lang/model/element/ElementKind;
      87: invokevirtual #82                 // Method javax/lang/model/element/ElementKind.ordinal:()I
      90: bipush        10
      92: iastore
      93: goto          97
      96: pop
      97: aload_0
      98: getstatic     #521                // Field javax/lang/model/element/ElementKind.FIELD:Ljavax/lang/model/element/ElementKind;
     101: invokevirtual #82                 // Method javax/lang/model/element/ElementKind.ordinal:()I
     104: bipush        7
     106: iastore
     107: goto          111
     110: pop
     111: aload_0
     112: getstatic     #524                // Field javax/lang/model/element/ElementKind.INSTANCE_INIT:Ljavax/lang/model/element/ElementKind;
     115: invokevirtual #82                 // Method javax/lang/model/element/ElementKind.ordinal:()I
     118: bipush        14
     120: iastore
     121: goto          125
     124: pop
     125: aload_0
     126: getstatic     #527                // Field javax/lang/model/element/ElementKind.INTERFACE:Ljavax/lang/model/element/ElementKind;
     129: invokevirtual #82                 // Method javax/lang/model/element/ElementKind.ordinal:()I
     132: iconst_5
     133: iastore
     134: goto          138
     137: pop
     138: aload_0
     139: getstatic     #530                // Field javax/lang/model/element/ElementKind.LOCAL_VARIABLE:Ljavax/lang/model/element/ElementKind;
     142: invokevirtual #82                 // Method javax/lang/model/element/ElementKind.ordinal:()I
     145: bipush        9
     147: iastore
     148: goto          152
     151: pop
     152: aload_0
     153: getstatic     #533                // Field javax/lang/model/element/ElementKind.METHOD:Ljavax/lang/model/element/ElementKind;
     156: invokevirtual #82                 // Method javax/lang/model/element/ElementKind.ordinal:()I
     159: bipush        11
     161: iastore
     162: goto          166
     165: pop
     166: aload_0
     167: getstatic     #536                // Field javax/lang/model/element/ElementKind.OTHER:Ljavax/lang/model/element/ElementKind;
     170: invokevirtual #82                 // Method javax/lang/model/element/ElementKind.ordinal:()I
     173: bipush        16
     175: iastore
     176: goto          180
     179: pop
     180: aload_0
     181: getstatic     #538                // Field javax/lang/model/element/ElementKind.PACKAGE:Ljavax/lang/model/element/ElementKind;
     184: invokevirtual #82                 // Method javax/lang/model/element/ElementKind.ordinal:()I
     187: iconst_1
     188: iastore
     189: goto          193
     192: pop
     193: aload_0
     194: getstatic     #540                // Field javax/lang/model/element/ElementKind.PARAMETER:Ljavax/lang/model/element/ElementKind;
     197: invokevirtual #82                 // Method javax/lang/model/element/ElementKind.ordinal:()I
     200: bipush        8
     202: iastore
     203: goto          207
     206: pop
     207: aload_0
     208: getstatic     #543                // Field javax/lang/model/element/ElementKind.STATIC_INIT:Ljavax/lang/model/element/ElementKind;
     211: invokevirtual #82                 // Method javax/lang/model/element/ElementKind.ordinal:()I
     214: bipush        13
     216: iastore
     217: goto          221
     220: pop
     221: aload_0
     222: getstatic     #546                // Field javax/lang/model/element/ElementKind.TYPE_PARAMETER:Ljavax/lang/model/element/ElementKind;
     225: invokevirtual #82                 // Method javax/lang/model/element/ElementKind.ordinal:()I
     228: bipush        15
     230: iastore
     231: goto          235
     234: pop
     235: aload_0
     236: dup
     237: putstatic     #497                // Field $SWITCH_TABLE$javax$lang$model$element$ElementKind:[I
     240: areturn
    Exception table:
       from    to  target type
          16    25    28   Class java/lang/NoSuchFieldError
          29    38    41   Class java/lang/NoSuchFieldError
          42    52    55   Class java/lang/NoSuchFieldError
          56    65    68   Class java/lang/NoSuchFieldError
          69    79    82   Class java/lang/NoSuchFieldError
          83    93    96   Class java/lang/NoSuchFieldError
          97   107   110   Class java/lang/NoSuchFieldError
         111   121   124   Class java/lang/NoSuchFieldError
         125   134   137   Class java/lang/NoSuchFieldError
         138   148   151   Class java/lang/NoSuchFieldError
         152   162   165   Class java/lang/NoSuchFieldError
         166   176   179   Class java/lang/NoSuchFieldError
         180   189   192   Class java/lang/NoSuchFieldError
         193   203   206   Class java/lang/NoSuchFieldError
         207   217   220   Class java/lang/NoSuchFieldError
         221   231   234   Class java/lang/NoSuchFieldError
}
