Compiled from "SynchronousActivityTaskPoller.java"
class com.amazonaws.services.simpleworkflow.flow.worker.SynchronousActivityTaskPoller$1 implements java.lang.Runnable {
  final com.amazonaws.services.simpleworkflow.flow.worker.SynchronousActivityTaskPoller this$0;

  private final java.lang.String val$taskToken;

  private final java.lang.String val$reason;

  private final java.lang.String val$details;

  com.amazonaws.services.simpleworkflow.flow.worker.SynchronousActivityTaskPoller$1(com.amazonaws.services.simpleworkflow.flow.worker.SynchronousActivityTaskPoller, java.lang.String, java.lang.String, java.lang.String);
    Code:
       0: aload_0
       1: aload_1
       2: putfield      #16                 // Field this$0:Lcom/amazonaws/services/simpleworkflow/flow/worker/SynchronousActivityTaskPoller;
       5: aload_0
       6: aload_2
       7: putfield      #18                 // Field val$taskToken:Ljava/lang/String;
      10: aload_0
      11: aload_3
      12: putfield      #20                 // Field val$reason:Ljava/lang/String;
      15: aload_0
      16: aload         4
      18: putfield      #22                 // Field val$details:Ljava/lang/String;
      21: aload_0
      22: invokespecial #24                 // Method java/lang/Object."<init>":()V
      25: return

  public void run();
    Code:
       0: aload_0
       1: getfield      #16                 // Field this$0:Lcom/amazonaws/services/simpleworkflow/flow/worker/SynchronousActivityTaskPoller;
       4: aload_0
       5: getfield      #18                 // Field val$taskToken:Ljava/lang/String;
       8: aload_0
       9: getfield      #20                 // Field val$reason:Ljava/lang/String;
      12: aload_0
      13: getfield      #22                 // Field val$details:Ljava/lang/String;
      16: invokevirtual #33                 // Method com/amazonaws/services/simpleworkflow/flow/worker/SynchronousActivityTaskPoller.respondActivityTaskFailed:(Ljava/lang/String;Ljava/lang/String;Ljava/lang/String;)V
      19: return
}
