Compiled from "WorkflowClockImpl.java"
class com.amazonaws.services.simpleworkflow.flow.worker.WorkflowClockImpl implements com.amazonaws.services.simpleworkflow.flow.WorkflowClock {
  private static final org.apache.commons.logging.Log log;

  private final com.amazonaws.services.simpleworkflow.flow.worker.DecisionsHelper decisions;

  private final java.util.Map<java.lang.String, com.amazonaws.services.simpleworkflow.flow.worker.OpenRequestInfo<?, ?>> scheduledTimers;

  private long replayCurrentTimeMilliseconds;

  private boolean replaying;

  static {};
    Code:
       0: ldc           #1                  // class com/amazonaws/services/simpleworkflow/flow/worker/WorkflowClockImpl
       2: invokestatic  #22                 // Method org/apache/commons/logging/LogFactory.getLog:(Ljava/lang/Class;)Lorg/apache/commons/logging/Log;
       5: putstatic     #28                 // Field log:Lorg/apache/commons/logging/Log;
       8: return

  com.amazonaws.services.simpleworkflow.flow.worker.WorkflowClockImpl(com.amazonaws.services.simpleworkflow.flow.worker.DecisionsHelper);
    Code:
       0: aload_0
       1: invokespecial #35                 // Method java/lang/Object."<init>":()V
       4: aload_0
       5: new           #37                 // class java/util/HashMap
       8: dup
       9: invokespecial #39                 // Method java/util/HashMap."<init>":()V
      12: putfield      #40                 // Field scheduledTimers:Ljava/util/Map;
      15: aload_0
      16: iconst_1
      17: putfield      #42                 // Field replaying:Z
      20: aload_0
      21: aload_1
      22: putfield      #44                 // Field decisions:Lcom/amazonaws/services/simpleworkflow/flow/worker/DecisionsHelper;
      25: return

  public long currentTimeMillis();
    Code:
       0: aload_0
       1: getfield      #50                 // Field replayCurrentTimeMilliseconds:J
       4: lreturn

  void setReplayCurrentTimeMilliseconds(long);
    Code:
       0: aload_0
       1: lload_1
       2: putfield      #50                 // Field replayCurrentTimeMilliseconds:J
       5: return

  public boolean isReplaying();
    Code:
       0: aload_0
       1: getfield      #42                 // Field replaying:Z
       4: ireturn

  void setReplaying(boolean);
    Code:
       0: aload_0
       1: iload_1
       2: putfield      #42                 // Field replaying:Z
       5: return

  public com.amazonaws.services.simpleworkflow.flow.core.Promise<java.lang.Void> createTimer(long);
    Code:
       0: aload_0
       1: lload_1
       2: aconst_null
       3: invokevirtual #61                 // Method createTimer:(JLjava/lang/Object;)Lcom/amazonaws/services/simpleworkflow/flow/core/Promise;
       6: areturn

  public <T> com.amazonaws.services.simpleworkflow.flow.core.Promise<T> createTimer(long, T);
    Code:
       0: lload_1
       1: lconst_0
       2: lcmp
       3: ifge          30
       6: new           #66                 // class java/lang/IllegalArgumentException
       9: dup
      10: new           #68                 // class java/lang/StringBuilder
      13: dup
      14: ldc           #70                 // String Negative delaySeconds:
      16: invokespecial #72                 // Method java/lang/StringBuilder."<init>":(Ljava/lang/String;)V
      19: lload_1
      20: invokevirtual #75                 // Method java/lang/StringBuilder.append:(J)Ljava/lang/StringBuilder;
      23: invokevirtual #79                 // Method java/lang/StringBuilder.toString:()Ljava/lang/String;
      26: invokespecial #83                 // Method java/lang/IllegalArgumentException."<init>":(Ljava/lang/String;)V
      29: athrow
      30: lload_1
      31: lconst_0
      32: lcmp
      33: ifne          41
      36: aload_3
      37: invokestatic  #84                 // Method com/amazonaws/services/simpleworkflow/flow/core/Promise.asPromise:(Ljava/lang/Object;)Lcom/amazonaws/services/simpleworkflow/flow/core/Promise;
      40: areturn
      41: new           #90                 // class com/amazonaws/services/simpleworkflow/flow/worker/OpenRequestInfo
      44: dup
      45: aload_3
      46: invokespecial #92                 // Method com/amazonaws/services/simpleworkflow/flow/worker/OpenRequestInfo."<init>":(Ljava/lang/Object;)V
      49: astore        4
      51: new           #95                 // class com/amazonaws/services/simpleworkflow/model/StartTimerDecisionAttributes
      54: dup
      55: invokespecial #97                 // Method com/amazonaws/services/simpleworkflow/model/StartTimerDecisionAttributes."<init>":()V
      58: astore        5
      60: aload         5
      62: lload_1
      63: invokestatic  #98                 // Method java/lang/Long.valueOf:(J)Ljava/lang/Long;
      66: invokestatic  #104                // Method com/amazonaws/services/simpleworkflow/flow/common/FlowHelpers.secondsToDuration:(Ljava/lang/Long;)Ljava/lang/String;
      69: invokevirtual #110                // Method com/amazonaws/services/simpleworkflow/model/StartTimerDecisionAttributes.setStartToFireTimeout:(Ljava/lang/String;)V
      72: aload_0
      73: getfield      #44                 // Field decisions:Lcom/amazonaws/services/simpleworkflow/flow/worker/DecisionsHelper;
      76: invokevirtual #113                // Method com/amazonaws/services/simpleworkflow/flow/worker/DecisionsHelper.getNextId:()Ljava/lang/String;
      79: astore        6
      81: aload         5
      83: aload         6
      85: invokevirtual #118                // Method com/amazonaws/services/simpleworkflow/model/StartTimerDecisionAttributes.setTimerId:(Ljava/lang/String;)V
      88: new           #68                 // class java/lang/StringBuilder
      91: dup
      92: ldc           #121                // String timerId=
      94: invokespecial #72                 // Method java/lang/StringBuilder."<init>":(Ljava/lang/String;)V
      97: aload         5
      99: invokevirtual #123                // Method com/amazonaws/services/simpleworkflow/model/StartTimerDecisionAttributes.getTimerId:()Ljava/lang/String;
     102: invokevirtual #126                // Method java/lang/StringBuilder.append:(Ljava/lang/String;)Ljava/lang/StringBuilder;
     105: ldc           #129                // String , delaySeconds=
     107: invokevirtual #126                // Method java/lang/StringBuilder.append:(Ljava/lang/String;)Ljava/lang/StringBuilder;
     110: aload         5
     112: invokevirtual #131                // Method com/amazonaws/services/simpleworkflow/model/StartTimerDecisionAttributes.getStartToFireTimeout:()Ljava/lang/String;
     115: invokevirtual #126                // Method java/lang/StringBuilder.append:(Ljava/lang/String;)Ljava/lang/StringBuilder;
     118: invokevirtual #79                 // Method java/lang/StringBuilder.toString:()Ljava/lang/String;
     121: astore        7
     123: new           #134                // class com/amazonaws/services/simpleworkflow/flow/worker/WorkflowClockImpl$1
     126: dup
     127: aload_0
     128: iconst_0
     129: anewarray     #85                 // class com/amazonaws/services/simpleworkflow/flow/core/Promise
     132: aload         5
     134: aload_3
     135: aload         4
     137: aload         6
     139: invokespecial #136                // Method com/amazonaws/services/simpleworkflow/flow/worker/WorkflowClockImpl$1."<init>":(Lcom/amazonaws/services/simpleworkflow/flow/worker/WorkflowClockImpl;[Lcom/amazonaws/services/simpleworkflow/flow/core/Promise;Lcom/amazonaws/services/simpleworkflow/model/StartTimerDecisionAttributes;Ljava/lang/Object;Lcom/amazonaws/services/simpleworkflow/flow/worker/OpenRequestInfo;Ljava/lang/String;)V
     142: aload         7
     144: invokevirtual #139                // Method com/amazonaws/services/simpleworkflow/flow/worker/WorkflowClockImpl$1.setName:(Ljava/lang/String;)V
     147: aload         4
     149: new           #68                 // class java/lang/StringBuilder
     152: dup
     153: ldc           #142                // String createTimer
     155: invokespecial #72                 // Method java/lang/StringBuilder."<init>":(Ljava/lang/String;)V
     158: aload         7
     160: invokevirtual #126                // Method java/lang/StringBuilder.append:(Ljava/lang/String;)Ljava/lang/StringBuilder;
     163: invokevirtual #79                 // Method java/lang/StringBuilder.toString:()Ljava/lang/String;
     166: invokevirtual #144                // Method com/amazonaws/services/simpleworkflow/flow/worker/OpenRequestInfo.setResultDescription:(Ljava/lang/String;)V
     169: aload         4
     171: invokevirtual #147                // Method com/amazonaws/services/simpleworkflow/flow/worker/OpenRequestInfo.getResult:()Lcom/amazonaws/services/simpleworkflow/flow/core/Settable;
     174: areturn

  void handleTimerFired(java.lang.Long, com.amazonaws.services.simpleworkflow.model.TimerFiredEventAttributes);
    Code:
       0: aload_2
       1: invokevirtual #166                // Method com/amazonaws/services/simpleworkflow/model/TimerFiredEventAttributes.getTimerId:()Ljava/lang/String;
       4: astore_3
       5: aload_0
       6: getfield      #44                 // Field decisions:Lcom/amazonaws/services/simpleworkflow/flow/worker/DecisionsHelper;
       9: aload_3
      10: invokevirtual #169                // Method com/amazonaws/services/simpleworkflow/flow/worker/DecisionsHelper.handleTimerClosed:(Ljava/lang/String;)Z
      13: ifeq          66
      16: aload_0
      17: getfield      #40                 // Field scheduledTimers:Ljava/util/Map;
      20: aload_3
      21: invokeinterface #173,  2          // InterfaceMethod java/util/Map.remove:(Ljava/lang/Object;)Ljava/lang/Object;
      26: checkcast     #90                 // class com/amazonaws/services/simpleworkflow/flow/worker/OpenRequestInfo
      29: astore        4
      31: aload         4
      33: ifnull        76
      36: aload         4
      38: invokevirtual #179                // Method com/amazonaws/services/simpleworkflow/flow/worker/OpenRequestInfo.getCompletionHandle:()Lcom/amazonaws/services/simpleworkflow/flow/core/ExternalTaskCompletionHandle;
      41: astore        5
      43: aload         4
      45: invokevirtual #147                // Method com/amazonaws/services/simpleworkflow/flow/worker/OpenRequestInfo.getResult:()Lcom/amazonaws/services/simpleworkflow/flow/core/Settable;
      48: aload         4
      50: invokevirtual #183                // Method com/amazonaws/services/simpleworkflow/flow/worker/OpenRequestInfo.getUserContext:()Ljava/lang/Object;
      53: invokevirtual #187                // Method com/amazonaws/services/simpleworkflow/flow/core/Settable.set:(Ljava/lang/Object;)V
      56: aload         5
      58: invokeinterface #192,  1          // InterfaceMethod com/amazonaws/services/simpleworkflow/flow/core/ExternalTaskCompletionHandle.complete:()V
      63: goto          76
      66: getstatic     #28                 // Field log:Lorg/apache/commons/logging/Log;
      69: ldc           #197                // String handleTimerFired not complete
      71: invokeinterface #199,  2          // InterfaceMethod org/apache/commons/logging/Log.debug:(Ljava/lang/Object;)V
      76: return

  void handleStartTimerFailed(com.amazonaws.services.simpleworkflow.model.HistoryEvent);
    Code:
       0: aload_1
       1: invokevirtual #215                // Method com/amazonaws/services/simpleworkflow/model/HistoryEvent.getStartTimerFailedEventAttributes:()Lcom/amazonaws/services/simpleworkflow/model/StartTimerFailedEventAttributes;
       4: astore_2
       5: aload_2
       6: invokevirtual #221                // Method com/amazonaws/services/simpleworkflow/model/StartTimerFailedEventAttributes.getTimerId:()Ljava/lang/String;
       9: astore_3
      10: aload_0
      11: getfield      #44                 // Field decisions:Lcom/amazonaws/services/simpleworkflow/flow/worker/DecisionsHelper;
      14: aload_1
      15: invokevirtual #224                // Method com/amazonaws/services/simpleworkflow/flow/worker/DecisionsHelper.handleStartTimerFailed:(Lcom/amazonaws/services/simpleworkflow/model/HistoryEvent;)Z
      18: ifeq          94
      21: aload_0
      22: getfield      #40                 // Field scheduledTimers:Ljava/util/Map;
      25: aload_3
      26: invokeinterface #173,  2          // InterfaceMethod java/util/Map.remove:(Ljava/lang/Object;)Ljava/lang/Object;
      31: checkcast     #90                 // class com/amazonaws/services/simpleworkflow/flow/worker/OpenRequestInfo
      34: astore        4
      36: aload         4
      38: ifnull        104
      41: aload         4
      43: invokevirtual #179                // Method com/amazonaws/services/simpleworkflow/flow/worker/OpenRequestInfo.getCompletionHandle:()Lcom/amazonaws/services/simpleworkflow/flow/core/ExternalTaskCompletionHandle;
      46: astore        5
      48: aload         4
      50: invokevirtual #183                // Method com/amazonaws/services/simpleworkflow/flow/worker/OpenRequestInfo.getUserContext:()Ljava/lang/Object;
      53: astore        6
      55: aload_2
      56: invokevirtual #227                // Method com/amazonaws/services/simpleworkflow/model/StartTimerFailedEventAttributes.getCause:()Ljava/lang/String;
      59: astore        7
      61: new           #230                // class com/amazonaws/services/simpleworkflow/flow/StartTimerFailedException
      64: dup
      65: aload_1
      66: invokevirtual #232                // Method com/amazonaws/services/simpleworkflow/model/HistoryEvent.getEventId:()Ljava/lang/Long;
      69: invokevirtual #236                // Method java/lang/Long.longValue:()J
      72: aload_3
      73: aload         6
      75: aload         7
      77: invokespecial #239                // Method com/amazonaws/services/simpleworkflow/flow/StartTimerFailedException."<init>":(JLjava/lang/String;Ljava/lang/Object;Ljava/lang/String;)V
      80: astore        8
      82: aload         5
      84: aload         8
      86: invokeinterface #242,  2          // InterfaceMethod com/amazonaws/services/simpleworkflow/flow/core/ExternalTaskCompletionHandle.fail:(Ljava/lang/Throwable;)V
      91: goto          104
      94: getstatic     #28                 // Field log:Lorg/apache/commons/logging/Log;
      97: ldc           #246                // String handleStartTimerFailed not complete
      99: invokeinterface #199,  2          // InterfaceMethod org/apache/commons/logging/Log.debug:(Ljava/lang/Object;)V
     104: return

  void handleTimerCanceled(com.amazonaws.services.simpleworkflow.model.HistoryEvent);
    Code:
       0: aload_1
       1: invokevirtual #256                // Method com/amazonaws/services/simpleworkflow/model/HistoryEvent.getTimerCanceledEventAttributes:()Lcom/amazonaws/services/simpleworkflow/model/TimerCanceledEventAttributes;
       4: astore_2
       5: aload_2
       6: invokevirtual #260                // Method com/amazonaws/services/simpleworkflow/model/TimerCanceledEventAttributes.getTimerId:()Ljava/lang/String;
       9: astore_3
      10: aload_0
      11: getfield      #44                 // Field decisions:Lcom/amazonaws/services/simpleworkflow/flow/worker/DecisionsHelper;
      14: aload_1
      15: invokevirtual #263                // Method com/amazonaws/services/simpleworkflow/flow/worker/DecisionsHelper.handleTimerCanceled:(Lcom/amazonaws/services/simpleworkflow/model/HistoryEvent;)Z
      18: ifeq          69
      21: aload_0
      22: getfield      #40                 // Field scheduledTimers:Ljava/util/Map;
      25: aload_3
      26: invokeinterface #173,  2          // InterfaceMethod java/util/Map.remove:(Ljava/lang/Object;)Ljava/lang/Object;
      31: checkcast     #90                 // class com/amazonaws/services/simpleworkflow/flow/worker/OpenRequestInfo
      34: astore        4
      36: aload         4
      38: ifnull        80
      41: aload         4
      43: invokevirtual #179                // Method com/amazonaws/services/simpleworkflow/flow/worker/OpenRequestInfo.getCompletionHandle:()Lcom/amazonaws/services/simpleworkflow/flow/core/ExternalTaskCompletionHandle;
      46: astore        5
      48: new           #265                // class java/util/concurrent/CancellationException
      51: dup
      52: invokespecial #267                // Method java/util/concurrent/CancellationException."<init>":()V
      55: astore        6
      57: aload         5
      59: aload         6
      61: invokeinterface #242,  2          // InterfaceMethod com/amazonaws/services/simpleworkflow/flow/core/ExternalTaskCompletionHandle.fail:(Ljava/lang/Throwable;)V
      66: goto          80
      69: getstatic     #28                 // Field log:Lorg/apache/commons/logging/Log;
      72: ldc_w         #268                // String handleTimerCanceled not complete
      75: invokeinterface #199,  2          // InterfaceMethod org/apache/commons/logging/Log.debug:(Ljava/lang/Object;)V
      80: return

  static com.amazonaws.services.simpleworkflow.flow.worker.DecisionsHelper access$0(com.amazonaws.services.simpleworkflow.flow.worker.WorkflowClockImpl);
    Code:
       0: aload_0
       1: getfield      #44                 // Field decisions:Lcom/amazonaws/services/simpleworkflow/flow/worker/DecisionsHelper;
       4: areturn

  static java.util.Map access$1(com.amazonaws.services.simpleworkflow.flow.worker.WorkflowClockImpl);
    Code:
       0: aload_0
       1: getfield      #40                 // Field scheduledTimers:Ljava/util/Map;
       4: areturn
}
