Compiled from "ElementIterator.java"
public class org.dom4j.tree.ElementIterator extends org.dom4j.tree.FilterIterator<org.dom4j.Node> {
  public org.dom4j.tree.ElementIterator(java.util.Iterator<org.dom4j.Node>);
    Code:
       0: aload_0
       1: aload_1
       2: invokespecial #1                  // Method org/dom4j/tree/FilterIterator."<init>":(Ljava/util/Iterator;)V
       5: return

  protected boolean matches(org.dom4j.Node);
    Code:
       0: aload_1
       1: instanceof    #2                  // class org/dom4j/Element
       4: ireturn

  protected boolean matches(java.lang.Object);
    Code:
       0: aload_0
       1: aload_1
       2: checkcast     #3                  // class org/dom4j/Node
       5: invokevirtual #4                  // Method matches:(Lorg/dom4j/Node;)Z
       8: ireturn
}
