Compiled from "QNameCache.java"
public class org.dom4j.tree.QNameCache {
  protected java.util.Map<java.lang.String, org.dom4j.QName> noNamespaceCache;

  protected java.util.Map<org.dom4j.Namespace, java.util.Map<java.lang.String, org.dom4j.QName>> namespaceCache;

  private org.dom4j.DocumentFactory documentFactory;

  public org.dom4j.tree.QNameCache();
    Code:
       0: aload_0
       1: invokespecial #1                  // Method java/lang/Object."<init>":()V
       4: aload_0
       5: new           #2                  // class java/util/WeakHashMap
       8: dup
       9: invokespecial #3                  // Method java/util/WeakHashMap."<init>":()V
      12: invokestatic  #4                  // Method java/util/Collections.synchronizedMap:(Ljava/util/Map;)Ljava/util/Map;
      15: putfield      #5                  // Field noNamespaceCache:Ljava/util/Map;
      18: aload_0
      19: new           #2                  // class java/util/WeakHashMap
      22: dup
      23: invokespecial #3                  // Method java/util/WeakHashMap."<init>":()V
      26: invokestatic  #4                  // Method java/util/Collections.synchronizedMap:(Ljava/util/Map;)Ljava/util/Map;
      29: putfield      #6                  // Field namespaceCache:Ljava/util/Map;
      32: return

  public org.dom4j.tree.QNameCache(org.dom4j.DocumentFactory);
    Code:
       0: aload_0
       1: invokespecial #1                  // Method java/lang/Object."<init>":()V
       4: aload_0
       5: new           #2                  // class java/util/WeakHashMap
       8: dup
       9: invokespecial #3                  // Method java/util/WeakHashMap."<init>":()V
      12: invokestatic  #4                  // Method java/util/Collections.synchronizedMap:(Ljava/util/Map;)Ljava/util/Map;
      15: putfield      #5                  // Field noNamespaceCache:Ljava/util/Map;
      18: aload_0
      19: new           #2                  // class java/util/WeakHashMap
      22: dup
      23: invokespecial #3                  // Method java/util/WeakHashMap."<init>":()V
      26: invokestatic  #4                  // Method java/util/Collections.synchronizedMap:(Ljava/util/Map;)Ljava/util/Map;
      29: putfield      #6                  // Field namespaceCache:Ljava/util/Map;
      32: aload_0
      33: aload_1
      34: putfield      #7                  // Field documentFactory:Lorg/dom4j/DocumentFactory;
      37: return

  public java.util.List<org.dom4j.QName> getQNames();
    Code:
       0: new           #8                  // class java/util/ArrayList
       3: dup
       4: invokespecial #9                  // Method java/util/ArrayList."<init>":()V
       7: astore_1
       8: aload_0
       9: getfield      #5                  // Field noNamespaceCache:Ljava/util/Map;
      12: dup
      13: astore_2
      14: monitorenter
      15: aload_1
      16: aload_0
      17: getfield      #5                  // Field noNamespaceCache:Ljava/util/Map;
      20: invokeinterface #10,  1           // InterfaceMethod java/util/Map.values:()Ljava/util/Collection;
      25: invokeinterface #11,  2           // InterfaceMethod java/util/List.addAll:(Ljava/util/Collection;)Z
      30: pop
      31: aload_2
      32: monitorexit
      33: goto          41
      36: astore_3
      37: aload_2
      38: monitorexit
      39: aload_3
      40: athrow
      41: aload_0
      42: getfield      #6                  // Field namespaceCache:Ljava/util/Map;
      45: dup
      46: astore_2
      47: monitorenter
      48: aload_0
      49: getfield      #6                  // Field namespaceCache:Ljava/util/Map;
      52: invokeinterface #10,  1           // InterfaceMethod java/util/Map.values:()Ljava/util/Collection;
      57: invokeinterface #12,  1           // InterfaceMethod java/util/Collection.iterator:()Ljava/util/Iterator;
      62: astore_3
      63: aload_3
      64: invokeinterface #13,  1           // InterfaceMethod java/util/Iterator.hasNext:()Z
      69: ifeq          100
      72: aload_3
      73: invokeinterface #14,  1           // InterfaceMethod java/util/Iterator.next:()Ljava/lang/Object;
      78: checkcast     #15                 // class java/util/Map
      81: astore        4
      83: aload_1
      84: aload         4
      86: invokeinterface #10,  1           // InterfaceMethod java/util/Map.values:()Ljava/util/Collection;
      91: invokeinterface #11,  2           // InterfaceMethod java/util/List.addAll:(Ljava/util/Collection;)Z
      96: pop
      97: goto          63
     100: aload_2
     101: monitorexit
     102: goto          112
     105: astore        5
     107: aload_2
     108: monitorexit
     109: aload         5
     111: athrow
     112: aload_1
     113: areturn
    Exception table:
       from    to  target type
          15    33    36   any
          36    39    36   any
          48   102   105   any
         105   109   105   any

  public org.dom4j.QName get(java.lang.String);
    Code:
       0: aconst_null
       1: astore_2
       2: aload_1
       3: ifnull        23
       6: aload_0
       7: getfield      #5                  // Field noNamespaceCache:Ljava/util/Map;
      10: aload_1
      11: invokeinterface #16,  2           // InterfaceMethod java/util/Map.get:(Ljava/lang/Object;)Ljava/lang/Object;
      16: checkcast     #17                 // class org/dom4j/QName
      19: astore_2
      20: goto          26
      23: ldc           #18                 // String
      25: astore_1
      26: aload_2
      27: ifnonnull     56
      30: aload_0
      31: aload_1
      32: invokevirtual #19                 // Method createQName:(Ljava/lang/String;)Lorg/dom4j/QName;
      35: astore_2
      36: aload_2
      37: aload_0
      38: getfield      #7                  // Field documentFactory:Lorg/dom4j/DocumentFactory;
      41: invokevirtual #20                 // Method org/dom4j/QName.setDocumentFactory:(Lorg/dom4j/DocumentFactory;)V
      44: aload_0
      45: getfield      #5                  // Field noNamespaceCache:Ljava/util/Map;
      48: aload_1
      49: aload_2
      50: invokeinterface #21,  3           // InterfaceMethod java/util/Map.put:(Ljava/lang/Object;Ljava/lang/Object;)Ljava/lang/Object;
      55: pop
      56: aload_2
      57: areturn

  public org.dom4j.QName get(java.lang.String, org.dom4j.Namespace);
    Code:
       0: aload_0
       1: aload_2
       2: invokevirtual #22                 // Method getNamespaceCache:(Lorg/dom4j/Namespace;)Ljava/util/Map;
       5: astore_3
       6: aconst_null
       7: astore        4
       9: aload_1
      10: ifnull        28
      13: aload_3
      14: aload_1
      15: invokeinterface #16,  2           // InterfaceMethod java/util/Map.get:(Ljava/lang/Object;)Ljava/lang/Object;
      20: checkcast     #17                 // class org/dom4j/QName
      23: astore        4
      25: goto          31
      28: ldc           #18                 // String
      30: astore_1
      31: aload         4
      33: ifnonnull     63
      36: aload_0
      37: aload_1
      38: aload_2
      39: invokevirtual #23                 // Method createQName:(Ljava/lang/String;Lorg/dom4j/Namespace;)Lorg/dom4j/QName;
      42: astore        4
      44: aload         4
      46: aload_0
      47: getfield      #7                  // Field documentFactory:Lorg/dom4j/DocumentFactory;
      50: invokevirtual #20                 // Method org/dom4j/QName.setDocumentFactory:(Lorg/dom4j/DocumentFactory;)V
      53: aload_3
      54: aload_1
      55: aload         4
      57: invokeinterface #21,  3           // InterfaceMethod java/util/Map.put:(Ljava/lang/Object;Ljava/lang/Object;)Ljava/lang/Object;
      62: pop
      63: aload         4
      65: areturn

  public org.dom4j.QName get(java.lang.String, org.dom4j.Namespace, java.lang.String);
    Code:
       0: aload_0
       1: aload_2
       2: invokevirtual #22                 // Method getNamespaceCache:(Lorg/dom4j/Namespace;)Ljava/util/Map;
       5: astore        4
       7: aconst_null
       8: astore        5
      10: aload_1
      11: ifnull        30
      14: aload         4
      16: aload_1
      17: invokeinterface #16,  2           // InterfaceMethod java/util/Map.get:(Ljava/lang/Object;)Ljava/lang/Object;
      22: checkcast     #17                 // class org/dom4j/QName
      25: astore        5
      27: goto          33
      30: ldc           #18                 // String
      32: astore_1
      33: aload         5
      35: ifnonnull     67
      38: aload_0
      39: aload_1
      40: aload_2
      41: aload_3
      42: invokevirtual #24                 // Method createQName:(Ljava/lang/String;Lorg/dom4j/Namespace;Ljava/lang/String;)Lorg/dom4j/QName;
      45: astore        5
      47: aload         5
      49: aload_0
      50: getfield      #7                  // Field documentFactory:Lorg/dom4j/DocumentFactory;
      53: invokevirtual #20                 // Method org/dom4j/QName.setDocumentFactory:(Lorg/dom4j/DocumentFactory;)V
      56: aload         4
      58: aload_1
      59: aload         5
      61: invokeinterface #21,  3           // InterfaceMethod java/util/Map.put:(Ljava/lang/Object;Ljava/lang/Object;)Ljava/lang/Object;
      66: pop
      67: aload         5
      69: areturn

  public org.dom4j.QName get(java.lang.String, java.lang.String);
    Code:
       0: aload_1
       1: bipush        58
       3: invokevirtual #25                 // Method java/lang/String.indexOf:(I)I
       6: istore_3
       7: iload_3
       8: ifge          21
      11: aload_0
      12: aload_1
      13: aload_2
      14: invokestatic  #26                 // Method org/dom4j/Namespace.get:(Ljava/lang/String;)Lorg/dom4j/Namespace;
      17: invokevirtual #27                 // Method get:(Ljava/lang/String;Lorg/dom4j/Namespace;)Lorg/dom4j/QName;
      20: areturn
      21: iload_3
      22: ifne          35
      25: new           #28                 // class java/lang/IllegalArgumentException
      28: dup
      29: ldc           #29                 // String Qualified name cannot start with \':\'.
      31: invokespecial #30                 // Method java/lang/IllegalArgumentException."<init>":(Ljava/lang/String;)V
      34: athrow
      35: aload_1
      36: iload_3
      37: iconst_1
      38: iadd
      39: invokevirtual #31                 // Method java/lang/String.substring:(I)Ljava/lang/String;
      42: astore        4
      44: aload_1
      45: iconst_0
      46: iload_3
      47: invokevirtual #32                 // Method java/lang/String.substring:(II)Ljava/lang/String;
      50: astore        5
      52: aload_0
      53: aload         4
      55: aload         5
      57: aload_2
      58: invokestatic  #33                 // Method org/dom4j/Namespace.get:(Ljava/lang/String;Ljava/lang/String;)Lorg/dom4j/Namespace;
      61: invokevirtual #27                 // Method get:(Ljava/lang/String;Lorg/dom4j/Namespace;)Lorg/dom4j/QName;
      64: areturn

  public org.dom4j.QName intern(org.dom4j.QName);
    Code:
       0: aload_0
       1: aload_1
       2: invokevirtual #34                 // Method org/dom4j/QName.getName:()Ljava/lang/String;
       5: aload_1
       6: invokevirtual #35                 // Method org/dom4j/QName.getNamespace:()Lorg/dom4j/Namespace;
       9: aload_1
      10: invokevirtual #36                 // Method org/dom4j/QName.getQualifiedName:()Ljava/lang/String;
      13: invokevirtual #37                 // Method get:(Ljava/lang/String;Lorg/dom4j/Namespace;Ljava/lang/String;)Lorg/dom4j/QName;
      16: areturn

  protected java.util.Map<java.lang.String, org.dom4j.QName> getNamespaceCache(org.dom4j.Namespace);
    Code:
       0: aload_1
       1: getstatic     #38                 // Field org/dom4j/Namespace.NO_NAMESPACE:Lorg/dom4j/Namespace;
       4: if_acmpne     12
       7: aload_0
       8: getfield      #5                  // Field noNamespaceCache:Ljava/util/Map;
      11: areturn
      12: aconst_null
      13: astore_2
      14: aload_1
      15: ifnull        32
      18: aload_0
      19: getfield      #6                  // Field namespaceCache:Ljava/util/Map;
      22: aload_1
      23: invokeinterface #16,  2           // InterfaceMethod java/util/Map.get:(Ljava/lang/Object;)Ljava/lang/Object;
      28: checkcast     #15                 // class java/util/Map
      31: astore_2
      32: aload_2
      33: ifnonnull     53
      36: aload_0
      37: invokevirtual #39                 // Method createMap:()Ljava/util/Map;
      40: astore_2
      41: aload_0
      42: getfield      #6                  // Field namespaceCache:Ljava/util/Map;
      45: aload_1
      46: aload_2
      47: invokeinterface #21,  3           // InterfaceMethod java/util/Map.put:(Ljava/lang/Object;Ljava/lang/Object;)Ljava/lang/Object;
      52: pop
      53: aload_2
      54: areturn

  protected java.util.Map<java.lang.String, org.dom4j.QName> createMap();
    Code:
       0: new           #40                 // class java/util/HashMap
       3: dup
       4: invokespecial #41                 // Method java/util/HashMap."<init>":()V
       7: invokestatic  #4                  // Method java/util/Collections.synchronizedMap:(Ljava/util/Map;)Ljava/util/Map;
      10: areturn

  protected org.dom4j.QName createQName(java.lang.String);
    Code:
       0: new           #17                 // class org/dom4j/QName
       3: dup
       4: aload_1
       5: invokespecial #42                 // Method org/dom4j/QName."<init>":(Ljava/lang/String;)V
       8: areturn

  protected org.dom4j.QName createQName(java.lang.String, org.dom4j.Namespace);
    Code:
       0: new           #17                 // class org/dom4j/QName
       3: dup
       4: aload_1
       5: aload_2
       6: invokespecial #43                 // Method org/dom4j/QName."<init>":(Ljava/lang/String;Lorg/dom4j/Namespace;)V
       9: areturn

  protected org.dom4j.QName createQName(java.lang.String, org.dom4j.Namespace, java.lang.String);
    Code:
       0: new           #17                 // class org/dom4j/QName
       3: dup
       4: aload_1
       5: aload_2
       6: aload_3
       7: invokespecial #44                 // Method org/dom4j/QName."<init>":(Ljava/lang/String;Lorg/dom4j/Namespace;Ljava/lang/String;)V
      10: areturn
}
