Compiled from "Engine.java"
public class org.h2.engine.Engine implements org.h2.engine.SessionFactory {
  private static final org.h2.engine.Engine INSTANCE;

  private static final java.util.Map<java.lang.String, org.h2.engine.Database> DATABASES;

  private volatile long wrongPasswordDelay;

  private boolean jmx;

  private org.h2.engine.Engine();
    Code:
       0: aload_0
       1: invokespecial #1                  // Method java/lang/Object."<init>":()V
       4: aload_0
       5: getstatic     #2                  // Field org/h2/engine/SysProperties.DELAY_WRONG_PASSWORD_MIN:I
       8: i2l
       9: putfield      #3                  // Field wrongPasswordDelay:J
      12: getstatic     #4                  // Field org/h2/engine/SysProperties.THREAD_DEADLOCK_DETECTOR:Z
      15: ifeq          21
      18: invokestatic  #5                  // Method org/h2/util/ThreadDeadlockDetector.init:()V
      21: return

  public static org.h2.engine.Engine getInstance();
    Code:
       0: getstatic     #6                  // Field INSTANCE:Lorg/h2/engine/Engine;
       3: areturn

  private org.h2.engine.Session openSession(org.h2.engine.ConnectionInfo, boolean, java.lang.String);
    Code:
       0: aload_1
       1: invokevirtual #7                  // Method org/h2/engine/ConnectionInfo.getName:()Ljava/lang/String;
       4: astore        4
       6: aload_1
       7: ldc           #8                  // String NO_UPGRADE
       9: iconst_0
      10: invokevirtual #9                  // Method org/h2/engine/ConnectionInfo.removeProperty:(Ljava/lang/String;Z)Z
      13: pop
      14: aload_1
      15: ldc           #10                 // String OPEN_NEW
      17: iconst_0
      18: invokevirtual #11                 // Method org/h2/engine/ConnectionInfo.getProperty:(Ljava/lang/String;Z)Z
      21: istore        6
      23: iconst_0
      24: istore        7
      26: aconst_null
      27: astore        8
      29: getstatic     #12                 // Field DATABASES:Ljava/util/Map;
      32: dup
      33: astore        9
      35: monitorenter
      36: iload         6
      38: ifne          48
      41: aload_1
      42: invokevirtual #13                 // Method org/h2/engine/ConnectionInfo.isUnnamedInMemory:()Z
      45: ifeq          54
      48: aconst_null
      49: astore        5
      51: goto          69
      54: getstatic     #12                 // Field DATABASES:Ljava/util/Map;
      57: aload         4
      59: invokeinterface #14,  2           // InterfaceMethod java/util/Map.get:(Ljava/lang/Object;)Ljava/lang/Object;
      64: checkcast     #15                 // class org/h2/engine/Database
      67: astore        5
      69: aload         5
      71: ifnonnull     182
      74: iload_2
      75: ifeq          94
      78: aload         4
      80: invokestatic  #16                 // Method org/h2/engine/Database.exists:(Ljava/lang/String;)Z
      83: ifne          94
      86: ldc           #17                 // int 90013
      88: aload         4
      90: invokestatic  #18                 // Method org/h2/message/DbException.get:(ILjava/lang/String;)Lorg/h2/message/DbException;
      93: athrow
      94: new           #15                 // class org/h2/engine/Database
      97: dup
      98: aload_1
      99: aload_3
     100: invokespecial #19                 // Method org/h2/engine/Database."<init>":(Lorg/h2/engine/ConnectionInfo;Ljava/lang/String;)V
     103: astore        5
     105: iconst_1
     106: istore        7
     108: aload         5
     110: invokevirtual #20                 // Method org/h2/engine/Database.getAllUsers:()Ljava/util/ArrayList;
     113: invokevirtual #21                 // Method java/util/ArrayList.isEmpty:()Z
     116: ifeq          162
     119: new           #22                 // class org/h2/engine/User
     122: dup
     123: aload         5
     125: aload         5
     127: invokevirtual #23                 // Method org/h2/engine/Database.allocateObjectId:()I
     130: aload_1
     131: invokevirtual #24                 // Method org/h2/engine/ConnectionInfo.getUserName:()Ljava/lang/String;
     134: iconst_0
     135: invokespecial #25                 // Method org/h2/engine/User."<init>":(Lorg/h2/engine/Database;ILjava/lang/String;Z)V
     138: astore        8
     140: aload         8
     142: iconst_1
     143: invokevirtual #26                 // Method org/h2/engine/User.setAdmin:(Z)V
     146: aload         8
     148: aload_1
     149: invokevirtual #27                 // Method org/h2/engine/ConnectionInfo.getUserPasswordHash:()[B
     152: invokevirtual #28                 // Method org/h2/engine/User.setUserPasswordHash:([B)V
     155: aload         5
     157: aload         8
     159: invokevirtual #29                 // Method org/h2/engine/Database.setMasterUser:(Lorg/h2/engine/User;)V
     162: aload_1
     163: invokevirtual #13                 // Method org/h2/engine/ConnectionInfo.isUnnamedInMemory:()Z
     166: ifne          182
     169: getstatic     #12                 // Field DATABASES:Ljava/util/Map;
     172: aload         4
     174: aload         5
     176: invokeinterface #30,  3           // InterfaceMethod java/util/Map.put:(Ljava/lang/Object;Ljava/lang/Object;)Ljava/lang/Object;
     181: pop
     182: aload         9
     184: monitorexit
     185: goto          196
     188: astore        10
     190: aload         9
     192: monitorexit
     193: aload         10
     195: athrow
     196: iload         7
     198: ifeq          206
     201: aload         5
     203: invokevirtual #31                 // Method org/h2/engine/Database.opened:()V
     206: aload         5
     208: invokevirtual #32                 // Method org/h2/engine/Database.isClosing:()Z
     211: ifeq          216
     214: aconst_null
     215: areturn
     216: aload         8
     218: ifnonnull     289
     221: aload         5
     223: aload_3
     224: aload_1
     225: invokevirtual #33                 // Method org/h2/engine/ConnectionInfo.getFilePasswordHash:()[B
     228: invokevirtual #34                 // Method org/h2/engine/Database.validateFilePasswordHash:(Ljava/lang/String;[B)Z
     231: ifeq          265
     234: aload         5
     236: aload_1
     237: invokevirtual #24                 // Method org/h2/engine/ConnectionInfo.getUserName:()Ljava/lang/String;
     240: invokevirtual #35                 // Method org/h2/engine/Database.findUser:(Ljava/lang/String;)Lorg/h2/engine/User;
     243: astore        8
     245: aload         8
     247: ifnull        265
     250: aload         8
     252: aload_1
     253: invokevirtual #27                 // Method org/h2/engine/ConnectionInfo.getUserPasswordHash:()[B
     256: invokevirtual #36                 // Method org/h2/engine/User.validateUserPasswordHash:([B)Z
     259: ifne          265
     262: aconst_null
     263: astore        8
     265: iload         7
     267: ifeq          289
     270: aload         8
     272: ifnull        283
     275: aload         8
     277: invokevirtual #37                 // Method org/h2/engine/User.isAdmin:()Z
     280: ifne          289
     283: aload         5
     285: aconst_null
     286: invokevirtual #38                 // Method org/h2/engine/Database.setEventListener:(Lorg/h2/api/DatabaseEventListener;)V
     289: aload         8
     291: ifnonnull     349
     294: sipush        28000
     297: invokestatic  #39                 // Method org/h2/message/DbException.get:(I)Lorg/h2/message/DbException;
     300: astore        9
     302: aload         5
     304: iconst_2
     305: invokevirtual #40                 // Method org/h2/engine/Database.getTrace:(I)Lorg/h2/message/Trace;
     308: aload         9
     310: new           #41                 // class java/lang/StringBuilder
     313: dup
     314: invokespecial #42                 // Method java/lang/StringBuilder."<init>":()V
     317: ldc           #43                 // String wrong user or password; user: \"
     319: invokevirtual #44                 // Method java/lang/StringBuilder.append:(Ljava/lang/String;)Ljava/lang/StringBuilder;
     322: aload_1
     323: invokevirtual #24                 // Method org/h2/engine/ConnectionInfo.getUserName:()Ljava/lang/String;
     326: invokevirtual #44                 // Method java/lang/StringBuilder.append:(Ljava/lang/String;)Ljava/lang/StringBuilder;
     329: ldc           #45                 // String \"
     331: invokevirtual #44                 // Method java/lang/StringBuilder.append:(Ljava/lang/String;)Ljava/lang/StringBuilder;
     334: invokevirtual #46                 // Method java/lang/StringBuilder.toString:()Ljava/lang/String;
     337: invokevirtual #47                 // Method org/h2/message/Trace.error:(Ljava/lang/Throwable;Ljava/lang/String;)V
     340: aload         5
     342: aconst_null
     343: invokevirtual #48                 // Method org/h2/engine/Database.removeSession:(Lorg/h2/engine/Session;)V
     346: aload         9
     348: athrow
     349: aload_1
     350: aload         5
     352: invokestatic  #49                 // Method checkClustering:(Lorg/h2/engine/ConnectionInfo;Lorg/h2/engine/Database;)V
     355: aload         5
     357: aload         8
     359: invokevirtual #50                 // Method org/h2/engine/Database.createSession:(Lorg/h2/engine/User;)Lorg/h2/engine/Session;
     362: astore        9
     364: aload         9
     366: ifnonnull     371
     369: aconst_null
     370: areturn
     371: aload_1
     372: ldc           #51                 // String JMX
     374: iconst_0
     375: invokevirtual #11                 // Method org/h2/engine/ConnectionInfo.getProperty:(Ljava/lang/String;Z)Z
     378: ifeq          434
     381: ldc           #52                 // String org.h2.jmx.DatabaseInfo.registerMBean
     383: iconst_2
     384: anewarray     #53                 // class java/lang/Object
     387: dup
     388: iconst_0
     389: aload_1
     390: aastore
     391: dup
     392: iconst_1
     393: aload         5
     395: aastore
     396: invokestatic  #54                 // Method org/h2/util/Utils.callStaticMethod:(Ljava/lang/String;[Ljava/lang/Object;)Ljava/lang/Object;
     399: pop
     400: goto          429
     403: astore        10
     405: aload         5
     407: aload         9
     409: invokevirtual #48                 // Method org/h2/engine/Database.removeSession:(Lorg/h2/engine/Session;)V
     412: ldc           #56                 // int 50100
     414: aload         10
     416: iconst_1
     417: anewarray     #57                 // class java/lang/String
     420: dup
     421: iconst_0
     422: ldc           #51                 // String JMX
     424: aastore
     425: invokestatic  #58                 // Method org/h2/message/DbException.get:(ILjava/lang/Throwable;[Ljava/lang/String;)Lorg/h2/message/DbException;
     428: athrow
     429: aload_0
     430: iconst_1
     431: putfield      #59                 // Field jmx:Z
     434: aload         9
     436: areturn
    Exception table:
       from    to  target type
          36   185   188   any
         188   193   188   any
         381   400   403   Class java/lang/Exception

  public org.h2.engine.Session createSession(org.h2.engine.ConnectionInfo);
    Code:
       0: getstatic     #6                  // Field INSTANCE:Lorg/h2/engine/Engine;
       3: aload_1
       4: invokespecial #60                 // Method createSessionAndValidate:(Lorg/h2/engine/ConnectionInfo;)Lorg/h2/engine/Session;
       7: areturn

  private org.h2.engine.Session createSessionAndValidate(org.h2.engine.ConnectionInfo);
    Code:
       0: aconst_null
       1: astore_2
       2: aload_1
       3: ldc           #61                 // String FILE_LOCK
       5: aconst_null
       6: invokevirtual #62                 // Method org/h2/engine/ConnectionInfo.getProperty:(Ljava/lang/String;Ljava/lang/String;)Ljava/lang/String;
       9: astore_3
      10: aload_3
      11: invokestatic  #63                 // Method org/h2/store/FileLock.getFileLockMethod:(Ljava/lang/String;)Lorg/h2/store/FileLockMethod;
      14: astore        4
      16: aload         4
      18: getstatic     #64                 // Field org/h2/store/FileLockMethod.SERIALIZED:Lorg/h2/store/FileLockMethod;
      21: if_acmpne     48
      24: aload_1
      25: ldc           #10                 // String OPEN_NEW
      27: ldc           #65                 // String TRUE
      29: invokevirtual #66                 // Method org/h2/engine/ConnectionInfo.setProperty:(Ljava/lang/String;Ljava/lang/String;)V
      32: aload_1
      33: invokevirtual #67                 // Method org/h2/engine/ConnectionInfo.clone:()Lorg/h2/engine/ConnectionInfo;
      36: astore_2
      37: goto          48
      40: astore        5
      42: aload         5
      44: invokestatic  #69                 // Method org/h2/message/DbException.convert:(Ljava/lang/Throwable;)Lorg/h2/message/DbException;
      47: athrow
      48: aload_0
      49: aload_1
      50: invokespecial #70                 // Method openSession:(Lorg/h2/engine/ConnectionInfo;)Lorg/h2/engine/Session;
      53: astore        5
      55: aload_0
      56: iconst_1
      57: invokespecial #71                 // Method validateUserAndPassword:(Z)V
      60: aload_2
      61: ifnull        70
      64: aload         5
      66: aload_2
      67: invokevirtual #72                 // Method org/h2/engine/Session.setConnectionInfo:(Lorg/h2/engine/ConnectionInfo;)V
      70: aload         5
      72: areturn
      73: astore_2
      74: aload_2
      75: invokevirtual #74                 // Method org/h2/message/DbException.getErrorCode:()I
      78: sipush        28000
      81: if_icmpne     89
      84: aload_0
      85: iconst_0
      86: invokespecial #71                 // Method validateUserAndPassword:(Z)V
      89: aload_2
      90: athrow
    Exception table:
       from    to  target type
          32    37    40   Class java/lang/CloneNotSupportedException
           0    72    73   Class org/h2/message/DbException

  private synchronized org.h2.engine.Session openSession(org.h2.engine.ConnectionInfo);
    Code:
       0: aload_1
       1: ldc           #75                 // String IFEXISTS
       3: iconst_0
       4: invokevirtual #9                  // Method org/h2/engine/ConnectionInfo.removeProperty:(Ljava/lang/String;Z)Z
       7: istore_2
       8: aload_1
       9: ldc           #76                 // String IGNORE_UNKNOWN_SETTINGS
      11: iconst_0
      12: invokevirtual #9                  // Method org/h2/engine/ConnectionInfo.removeProperty:(Ljava/lang/String;Z)Z
      15: istore_3
      16: aload_1
      17: ldc           #77                 // String CIPHER
      19: aconst_null
      20: invokevirtual #78                 // Method org/h2/engine/ConnectionInfo.removeProperty:(Ljava/lang/String;Ljava/lang/String;)Ljava/lang/String;
      23: astore        4
      25: aload_1
      26: ldc           #79                 // String INIT
      28: aconst_null
      29: invokevirtual #78                 // Method org/h2/engine/ConnectionInfo.removeProperty:(Ljava/lang/String;Ljava/lang/String;)Ljava/lang/String;
      32: astore        5
      34: iconst_0
      35: istore        7
      37: aload_0
      38: aload_1
      39: iload_2
      40: aload         4
      42: invokespecial #80                 // Method openSession:(Lorg/h2/engine/ConnectionInfo;ZLjava/lang/String;)Lorg/h2/engine/Session;
      45: astore        6
      47: aload         6
      49: ifnull        55
      52: goto          85
      55: iload         7
      57: ldc           #81                 // int 60000
      59: if_icmple     70
      62: ldc           #82                 // int 90020
      64: ldc           #83                 // String Waited for database closing longer than 1 minute
      66: invokestatic  #18                 // Method org/h2/message/DbException.get:(ILjava/lang/String;)Lorg/h2/message/DbException;
      69: athrow
      70: lconst_1
      71: invokestatic  #84                 // Method java/lang/Thread.sleep:(J)V
      74: goto          79
      77: astore        8
      79: iinc          7, 1
      82: goto          37
      85: aload         6
      87: dup
      88: astore        7
      90: monitorenter
      91: aload         6
      93: iconst_1
      94: invokevirtual #86                 // Method org/h2/engine/Session.setAllowLiterals:(Z)V
      97: invokestatic  #87                 // Method org/h2/engine/DbSettings.getDefaultSettings:()Lorg/h2/engine/DbSettings;
     100: astore        8
     102: aload_1
     103: invokevirtual #88                 // Method org/h2/engine/ConnectionInfo.getKeys:()[Ljava/lang/String;
     106: astore        9
     108: aload         9
     110: arraylength
     111: istore        10
     113: iconst_0
     114: istore        11
     116: iload         11
     118: iload         10
     120: if_icmpge     290
     123: aload         9
     125: iload         11
     127: aaload
     128: astore        12
     130: aload         8
     132: aload         12
     134: invokevirtual #89                 // Method org/h2/engine/DbSettings.containsKey:(Ljava/lang/String;)Z
     137: ifeq          143
     140: goto          284
     143: aload_1
     144: aload         12
     146: invokevirtual #90                 // Method org/h2/engine/ConnectionInfo.getProperty:(Ljava/lang/String;)Ljava/lang/String;
     149: astore        13
     151: aload         6
     153: new           #41                 // class java/lang/StringBuilder
     156: dup
     157: invokespecial #42                 // Method java/lang/StringBuilder."<init>":()V
     160: ldc           #91                 // String SET
     162: invokevirtual #44                 // Method java/lang/StringBuilder.append:(Ljava/lang/String;)Ljava/lang/StringBuilder;
     165: aload         12
     167: invokestatic  #92                 // Method org/h2/command/Parser.quoteIdentifier:(Ljava/lang/String;)Ljava/lang/String;
     170: invokevirtual #44                 // Method java/lang/StringBuilder.append:(Ljava/lang/String;)Ljava/lang/StringBuilder;
     173: ldc           #93                 // String
     175: invokevirtual #44                 // Method java/lang/StringBuilder.append:(Ljava/lang/String;)Ljava/lang/StringBuilder;
     178: aload         13
     180: invokevirtual #44                 // Method java/lang/StringBuilder.append:(Ljava/lang/String;)Ljava/lang/StringBuilder;
     183: invokevirtual #46                 // Method java/lang/StringBuilder.toString:()Ljava/lang/String;
     186: ldc           #94                 // int 2147483647
     188: invokevirtual #95                 // Method org/h2/engine/Session.prepareCommand:(Ljava/lang/String;I)Lorg/h2/command/CommandInterface;
     191: astore        14
     193: aload         14
     195: iconst_0
     196: invokestatic  #96                 // Method java/lang/Boolean.valueOf:(Z)Ljava/lang/Boolean;
     199: invokeinterface #97,  2           // InterfaceMethod org/h2/command/CommandInterface.executeUpdate:(Ljava/lang/Object;)Lorg/h2/result/ResultWithGeneratedKeys;
     204: pop
     205: goto          284
     208: astore        14
     210: aload         14
     212: invokevirtual #74                 // Method org/h2/message/DbException.getErrorCode:()I
     215: ldc           #98                 // int 90040
     217: if_icmpne     260
     220: aload         6
     222: invokevirtual #99                 // Method org/h2/engine/Session.getTrace:()Lorg/h2/message/Trace;
     225: aload         14
     227: new           #41                 // class java/lang/StringBuilder
     230: dup
     231: invokespecial #42                 // Method java/lang/StringBuilder."<init>":()V
     234: ldc           #100                // String admin rights required; user: \"
     236: invokevirtual #44                 // Method java/lang/StringBuilder.append:(Ljava/lang/String;)Ljava/lang/StringBuilder;
     239: aload_1
     240: invokevirtual #24                 // Method org/h2/engine/ConnectionInfo.getUserName:()Ljava/lang/String;
     243: invokevirtual #44                 // Method java/lang/StringBuilder.append:(Ljava/lang/String;)Ljava/lang/StringBuilder;
     246: ldc           #45                 // String \"
     248: invokevirtual #44                 // Method java/lang/StringBuilder.append:(Ljava/lang/String;)Ljava/lang/StringBuilder;
     251: invokevirtual #46                 // Method java/lang/StringBuilder.toString:()Ljava/lang/String;
     254: invokevirtual #47                 // Method org/h2/message/Trace.error:(Ljava/lang/Throwable;Ljava/lang/String;)V
     257: goto          272
     260: aload         6
     262: invokevirtual #99                 // Method org/h2/engine/Session.getTrace:()Lorg/h2/message/Trace;
     265: aload         14
     267: ldc           #101                // String
     269: invokevirtual #47                 // Method org/h2/message/Trace.error:(Ljava/lang/Throwable;Ljava/lang/String;)V
     272: iload_3
     273: ifne          284
     276: aload         6
     278: invokevirtual #102                // Method org/h2/engine/Session.close:()V
     281: aload         14
     283: athrow
     284: iinc          11, 1
     287: goto          116
     290: aload         5
     292: ifnull        335
     295: aload         6
     297: aload         5
     299: ldc           #94                 // int 2147483647
     301: invokevirtual #95                 // Method org/h2/engine/Session.prepareCommand:(Ljava/lang/String;I)Lorg/h2/command/CommandInterface;
     304: astore        9
     306: aload         9
     308: iconst_0
     309: invokestatic  #96                 // Method java/lang/Boolean.valueOf:(Z)Ljava/lang/Boolean;
     312: invokeinterface #97,  2           // InterfaceMethod org/h2/command/CommandInterface.executeUpdate:(Ljava/lang/Object;)Lorg/h2/result/ResultWithGeneratedKeys;
     317: pop
     318: goto          335
     321: astore        9
     323: iload_3
     324: ifne          335
     327: aload         6
     329: invokevirtual #102                // Method org/h2/engine/Session.close:()V
     332: aload         9
     334: athrow
     335: aload         6
     337: iconst_0
     338: invokevirtual #86                 // Method org/h2/engine/Session.setAllowLiterals:(Z)V
     341: aload         6
     343: iconst_1
     344: invokevirtual #103                // Method org/h2/engine/Session.commit:(Z)V
     347: aload         7
     349: monitorexit
     350: goto          361
     353: astore        15
     355: aload         7
     357: monitorexit
     358: aload         15
     360: athrow
     361: aload         6
     363: areturn
    Exception table:
       from    to  target type
          70    74    77   Class java/lang/InterruptedException
         151   205   208   Class org/h2/message/DbException
         295   318   321   Class org/h2/message/DbException
          91   350   353   any
         353   358   353   any

  private static void checkClustering(org.h2.engine.ConnectionInfo, org.h2.engine.Database);
    Code:
       0: aload_0
       1: bipush        13
       3: aconst_null
       4: invokevirtual #104                // Method org/h2/engine/ConnectionInfo.getProperty:(ILjava/lang/String;)Ljava/lang/String;
       7: astore_2
       8: ldc           #105                // String \'\'
      10: aload_2
      11: invokevirtual #106                // Method java/lang/String.equals:(Ljava/lang/Object;)Z
      14: ifeq          18
      17: return
      18: aload_1
      19: invokevirtual #107                // Method org/h2/engine/Database.getCluster:()Ljava/lang/String;
      22: astore_3
      23: ldc           #105                // String \'\'
      25: aload_3
      26: invokevirtual #106                // Method java/lang/String.equals:(Ljava/lang/Object;)Z
      29: ifne          71
      32: ldc           #65                 // String TRUE
      34: aload_2
      35: invokevirtual #106                // Method java/lang/String.equals:(Ljava/lang/Object;)Z
      38: ifne          71
      41: aload_2
      42: aload_3
      43: invokestatic  #108                // Method java/util/Objects.equals:(Ljava/lang/Object;Ljava/lang/Object;)Z
      46: ifne          71
      49: aload_3
      50: ldc           #105                // String \'\'
      52: invokevirtual #106                // Method java/lang/String.equals:(Ljava/lang/Object;)Z
      55: ifeq          64
      58: ldc           #109                // int 90093
      60: invokestatic  #39                 // Method org/h2/message/DbException.get:(I)Lorg/h2/message/DbException;
      63: athrow
      64: ldc           #110                // int 90094
      66: aload_3
      67: invokestatic  #18                 // Method org/h2/message/DbException.get:(ILjava/lang/String;)Lorg/h2/message/DbException;
      70: athrow
      71: return

  void close(java.lang.String);
    Code:
       0: aload_0
       1: getfield      #59                 // Field jmx:Z
       4: ifeq          41
       7: ldc           #111                // String org.h2.jmx.DatabaseInfo.unregisterMBean
       9: iconst_1
      10: anewarray     #53                 // class java/lang/Object
      13: dup
      14: iconst_0
      15: aload_1
      16: aastore
      17: invokestatic  #54                 // Method org/h2/util/Utils.callStaticMethod:(Ljava/lang/String;[Ljava/lang/Object;)Ljava/lang/Object;
      20: pop
      21: goto          41
      24: astore_2
      25: ldc           #56                 // int 50100
      27: aload_2
      28: iconst_1
      29: anewarray     #57                 // class java/lang/String
      32: dup
      33: iconst_0
      34: ldc           #51                 // String JMX
      36: aastore
      37: invokestatic  #58                 // Method org/h2/message/DbException.get:(ILjava/lang/Throwable;[Ljava/lang/String;)Lorg/h2/message/DbException;
      40: athrow
      41: getstatic     #12                 // Field DATABASES:Ljava/util/Map;
      44: dup
      45: astore_2
      46: monitorenter
      47: getstatic     #12                 // Field DATABASES:Ljava/util/Map;
      50: aload_1
      51: invokeinterface #112,  2          // InterfaceMethod java/util/Map.remove:(Ljava/lang/Object;)Ljava/lang/Object;
      56: pop
      57: aload_2
      58: monitorexit
      59: goto          67
      62: astore_3
      63: aload_2
      64: monitorexit
      65: aload_3
      66: athrow
      67: return
    Exception table:
       from    to  target type
           7    21    24   Class java/lang/Exception
          47    59    62   any
          62    65    62   any

  private void validateUserAndPassword(boolean);
    Code:
       0: getstatic     #2                  // Field org/h2/engine/SysProperties.DELAY_WRONG_PASSWORD_MIN:I
       3: istore_2
       4: iload_1
       5: ifeq          72
       8: aload_0
       9: getfield      #3                  // Field wrongPasswordDelay:J
      12: lstore_3
      13: lload_3
      14: iload_2
      15: i2l
      16: lcmp
      17: ifle          69
      20: lload_3
      21: lconst_0
      22: lcmp
      23: ifle          69
      26: getstatic     #6                  // Field INSTANCE:Lorg/h2/engine/Engine;
      29: dup
      30: astore        5
      32: monitorenter
      33: lload_3
      34: l2i
      35: invokestatic  #113                // Method org/h2/util/MathUtils.secureRandomInt:(I)I
      38: i2l
      39: lstore_3
      40: lload_3
      41: invokestatic  #84                 // Method java/lang/Thread.sleep:(J)V
      44: goto          49
      47: astore        6
      49: aload_0
      50: iload_2
      51: i2l
      52: putfield      #3                  // Field wrongPasswordDelay:J
      55: aload         5
      57: monitorexit
      58: goto          69
      61: astore        7
      63: aload         5
      65: monitorexit
      66: aload         7
      68: athrow
      69: goto          181
      72: getstatic     #6                  // Field INSTANCE:Lorg/h2/engine/Engine;
      75: dup
      76: astore_3
      77: monitorenter
      78: aload_0
      79: getfield      #3                  // Field wrongPasswordDelay:J
      82: lstore        4
      84: getstatic     #114                // Field org/h2/engine/SysProperties.DELAY_WRONG_PASSWORD_MAX:I
      87: istore        6
      89: iload         6
      91: ifgt          98
      94: ldc           #94                 // int 2147483647
      96: istore        6
      98: aload_0
      99: dup
     100: getfield      #3                  // Field wrongPasswordDelay:J
     103: aload_0
     104: getfield      #3                  // Field wrongPasswordDelay:J
     107: ladd
     108: putfield      #3                  // Field wrongPasswordDelay:J
     111: aload_0
     112: getfield      #3                  // Field wrongPasswordDelay:J
     115: iload         6
     117: i2l
     118: lcmp
     119: ifgt          131
     122: aload_0
     123: getfield      #3                  // Field wrongPasswordDelay:J
     126: lconst_0
     127: lcmp
     128: ifge          138
     131: aload_0
     132: iload         6
     134: i2l
     135: putfield      #3                  // Field wrongPasswordDelay:J
     138: iload_2
     139: ifle          167
     142: lload         4
     144: invokestatic  #115                // Method org/h2/util/MathUtils.secureRandomLong:()J
     147: ldc2_w        #116                // long 100l
     150: lrem
     151: invokestatic  #118                // Method java/lang/Math.abs:(J)J
     154: ladd
     155: lstore        4
     157: lload         4
     159: invokestatic  #84                 // Method java/lang/Thread.sleep:(J)V
     162: goto          167
     165: astore        7
     167: sipush        28000
     170: invokestatic  #39                 // Method org/h2/message/DbException.get:(I)Lorg/h2/message/DbException;
     173: athrow
     174: astore        8
     176: aload_3
     177: monitorexit
     178: aload         8
     180: athrow
     181: return
    Exception table:
       from    to  target type
          40    44    47   Class java/lang/InterruptedException
          33    58    61   any
          61    66    61   any
         157   162   165   Class java/lang/InterruptedException
          78   178   174   any

  public org.h2.engine.SessionInterface createSession(org.h2.engine.ConnectionInfo) throws java.sql.SQLException;
    Code:
       0: aload_0
       1: aload_1
       2: invokevirtual #119                // Method createSession:(Lorg/h2/engine/ConnectionInfo;)Lorg/h2/engine/Session;
       5: areturn

  static {};
    Code:
       0: new           #120                // class org/h2/engine/Engine
       3: dup
       4: invokespecial #121                // Method "<init>":()V
       7: putstatic     #6                  // Field INSTANCE:Lorg/h2/engine/Engine;
      10: new           #122                // class java/util/HashMap
      13: dup
      14: invokespecial #123                // Method java/util/HashMap."<init>":()V
      17: putstatic     #12                 // Field DATABASES:Ljava/util/Map;
      20: return
}
