Compiled from "Mode.java"
public final class org.h2.engine.Mode$UniqueIndexNullsHandling extends java.lang.Enum<org.h2.engine.Mode$UniqueIndexNullsHandling> {
  public static final org.h2.engine.Mode$UniqueIndexNullsHandling ALLOW_DUPLICATES_WITH_ANY_NULL;

  public static final org.h2.engine.Mode$UniqueIndexNullsHandling ALLOW_DUPLICATES_WITH_ALL_NULLS;

  public static final org.h2.engine.Mode$UniqueIndexNullsHandling FORBID_ANY_DUPLICATES;

  private static final org.h2.engine.Mode$UniqueIndexNullsHandling[] $VALUES;

  public static org.h2.engine.Mode$UniqueIndexNullsHandling[] values();
    Code:
       0: getstatic     #1                  // Field $VALUES:[Lorg/h2/engine/Mode$UniqueIndexNullsHandling;
       3: invokevirtual #2                  // Method "[Lorg/h2/engine/Mode$UniqueIndexNullsHandling;".clone:()Ljava/lang/Object;
       6: checkcast     #3                  // class "[Lorg/h2/engine/Mode$UniqueIndexNullsHandling;"
       9: areturn

  public static org.h2.engine.Mode$UniqueIndexNullsHandling valueOf(java.lang.String);
    Code:
       0: ldc_w         #4                  // class org/h2/engine/Mode$UniqueIndexNullsHandling
       3: aload_0
       4: invokestatic  #5                  // Method java/lang/Enum.valueOf:(Ljava/lang/Class;Ljava/lang/String;)Ljava/lang/Enum;
       7: checkcast     #4                  // class org/h2/engine/Mode$UniqueIndexNullsHandling
      10: areturn

  private org.h2.engine.Mode$UniqueIndexNullsHandling();
    Code:
       0: aload_0
       1: aload_1
       2: iload_2
       3: invokespecial #6                  // Method java/lang/Enum."<init>":(Ljava/lang/String;I)V
       6: return

  static {};
    Code:
       0: new           #4                  // class org/h2/engine/Mode$UniqueIndexNullsHandling
       3: dup
       4: ldc           #7                  // String ALLOW_DUPLICATES_WITH_ANY_NULL
       6: iconst_0
       7: invokespecial #8                  // Method "<init>":(Ljava/lang/String;I)V
      10: putstatic     #9                  // Field ALLOW_DUPLICATES_WITH_ANY_NULL:Lorg/h2/engine/Mode$UniqueIndexNullsHandling;
      13: new           #4                  // class org/h2/engine/Mode$UniqueIndexNullsHandling
      16: dup
      17: ldc           #10                 // String ALLOW_DUPLICATES_WITH_ALL_NULLS
      19: iconst_1
      20: invokespecial #8                  // Method "<init>":(Ljava/lang/String;I)V
      23: putstatic     #11                 // Field ALLOW_DUPLICATES_WITH_ALL_NULLS:Lorg/h2/engine/Mode$UniqueIndexNullsHandling;
      26: new           #4                  // class org/h2/engine/Mode$UniqueIndexNullsHandling
      29: dup
      30: ldc           #12                 // String FORBID_ANY_DUPLICATES
      32: iconst_2
      33: invokespecial #8                  // Method "<init>":(Ljava/lang/String;I)V
      36: putstatic     #13                 // Field FORBID_ANY_DUPLICATES:Lorg/h2/engine/Mode$UniqueIndexNullsHandling;
      39: iconst_3
      40: anewarray     #4                  // class org/h2/engine/Mode$UniqueIndexNullsHandling
      43: dup
      44: iconst_0
      45: getstatic     #9                  // Field ALLOW_DUPLICATES_WITH_ANY_NULL:Lorg/h2/engine/Mode$UniqueIndexNullsHandling;
      48: aastore
      49: dup
      50: iconst_1
      51: getstatic     #11                 // Field ALLOW_DUPLICATES_WITH_ALL_NULLS:Lorg/h2/engine/Mode$UniqueIndexNullsHandling;
      54: aastore
      55: dup
      56: iconst_2
      57: getstatic     #13                 // Field FORBID_ANY_DUPLICATES:Lorg/h2/engine/Mode$UniqueIndexNullsHandling;
      60: aastore
      61: putstatic     #1                  // Field $VALUES:[Lorg/h2/engine/Mode$UniqueIndexNullsHandling;
      64: return
}
