Compiled from "RightOwner.java"
public abstract class org.h2.engine.RightOwner extends org.h2.engine.DbObjectBase {
  private java.util.HashMap<org.h2.engine.Role, org.h2.engine.Right> grantedRoles;

  private java.util.HashMap<org.h2.engine.DbObject, org.h2.engine.Right> grantedRights;

  protected org.h2.engine.RightOwner(org.h2.engine.Database, int, java.lang.String, int);
    Code:
       0: aload_0
       1: invokespecial #1                  // Method org/h2/engine/DbObjectBase."<init>":()V
       4: aload_0
       5: aload_1
       6: iload_2
       7: aload_3
       8: iload         4
      10: invokevirtual #2                  // Method initDbObjectBase:(Lorg/h2/engine/Database;ILjava/lang/String;I)V
      13: return

  public boolean isRoleGranted(org.h2.engine.Role);
    Code:
       0: aload_1
       1: aload_0
       2: if_acmpne     7
       5: iconst_1
       6: ireturn
       7: aload_0
       8: getfield      #3                  // Field grantedRoles:Ljava/util/HashMap;
      11: ifnull        66
      14: aload_0
      15: getfield      #3                  // Field grantedRoles:Ljava/util/HashMap;
      18: invokevirtual #4                  // Method java/util/HashMap.keySet:()Ljava/util/Set;
      21: invokeinterface #5,  1            // InterfaceMethod java/util/Set.iterator:()Ljava/util/Iterator;
      26: astore_2
      27: aload_2
      28: invokeinterface #6,  1            // InterfaceMethod java/util/Iterator.hasNext:()Z
      33: ifeq          66
      36: aload_2
      37: invokeinterface #7,  1            // InterfaceMethod java/util/Iterator.next:()Ljava/lang/Object;
      42: checkcast     #8                  // class org/h2/engine/Role
      45: astore_3
      46: aload_3
      47: aload_1
      48: if_acmpne     53
      51: iconst_1
      52: ireturn
      53: aload_3
      54: aload_1
      55: invokevirtual #9                  // Method org/h2/engine/Role.isRoleGranted:(Lorg/h2/engine/Role;)Z
      58: ifeq          63
      61: iconst_1
      62: ireturn
      63: goto          27
      66: iconst_0
      67: ireturn

  boolean isRightGrantedRecursive(org.h2.table.Table, int);
    Code:
       0: aload_0
       1: getfield      #10                 // Field grantedRights:Ljava/util/HashMap;
       4: ifnull        70
       7: aload_1
       8: ifnull        42
      11: aload_0
      12: getfield      #10                 // Field grantedRights:Ljava/util/HashMap;
      15: aload_1
      16: invokevirtual #11                 // Method org/h2/table/Table.getSchema:()Lorg/h2/schema/Schema;
      19: invokevirtual #12                 // Method java/util/HashMap.get:(Ljava/lang/Object;)Ljava/lang/Object;
      22: checkcast     #13                 // class org/h2/engine/Right
      25: astore_3
      26: aload_3
      27: ifnull        42
      30: aload_3
      31: invokevirtual #14                 // Method org/h2/engine/Right.getRightMask:()I
      34: iload_2
      35: iand
      36: iload_2
      37: if_icmpne     42
      40: iconst_1
      41: ireturn
      42: aload_0
      43: getfield      #10                 // Field grantedRights:Ljava/util/HashMap;
      46: aload_1
      47: invokevirtual #12                 // Method java/util/HashMap.get:(Ljava/lang/Object;)Ljava/lang/Object;
      50: checkcast     #13                 // class org/h2/engine/Right
      53: astore_3
      54: aload_3
      55: ifnull        70
      58: aload_3
      59: invokevirtual #14                 // Method org/h2/engine/Right.getRightMask:()I
      62: iload_2
      63: iand
      64: iload_2
      65: if_icmpne     70
      68: iconst_1
      69: ireturn
      70: aload_0
      71: getfield      #3                  // Field grantedRoles:Ljava/util/HashMap;
      74: ifnull        128
      77: aload_0
      78: getfield      #3                  // Field grantedRoles:Ljava/util/HashMap;
      81: invokevirtual #4                  // Method java/util/HashMap.keySet:()Ljava/util/Set;
      84: invokeinterface #5,  1            // InterfaceMethod java/util/Set.iterator:()Ljava/util/Iterator;
      89: astore        4
      91: aload         4
      93: invokeinterface #6,  1            // InterfaceMethod java/util/Iterator.hasNext:()Z
      98: ifeq          128
     101: aload         4
     103: invokeinterface #7,  1            // InterfaceMethod java/util/Iterator.next:()Ljava/lang/Object;
     108: checkcast     #15                 // class org/h2/engine/RightOwner
     111: astore        5
     113: aload         5
     115: aload_1
     116: iload_2
     117: invokevirtual #16                 // Method isRightGrantedRecursive:(Lorg/h2/table/Table;I)Z
     120: ifeq          125
     123: iconst_1
     124: ireturn
     125: goto          91
     128: iconst_0
     129: ireturn

  public void grantRight(org.h2.engine.DbObject, org.h2.engine.Right);
    Code:
       0: aload_0
       1: getfield      #10                 // Field grantedRights:Ljava/util/HashMap;
       4: ifnonnull     18
       7: aload_0
       8: new           #17                 // class java/util/HashMap
      11: dup
      12: invokespecial #18                 // Method java/util/HashMap."<init>":()V
      15: putfield      #10                 // Field grantedRights:Ljava/util/HashMap;
      18: aload_0
      19: getfield      #10                 // Field grantedRights:Ljava/util/HashMap;
      22: aload_1
      23: aload_2
      24: invokevirtual #19                 // Method java/util/HashMap.put:(Ljava/lang/Object;Ljava/lang/Object;)Ljava/lang/Object;
      27: pop
      28: return

  void revokeRight(org.h2.engine.DbObject);
    Code:
       0: aload_0
       1: getfield      #10                 // Field grantedRights:Ljava/util/HashMap;
       4: ifnonnull     8
       7: return
       8: aload_0
       9: getfield      #10                 // Field grantedRights:Ljava/util/HashMap;
      12: aload_1
      13: invokevirtual #20                 // Method java/util/HashMap.remove:(Ljava/lang/Object;)Ljava/lang/Object;
      16: pop
      17: aload_0
      18: getfield      #10                 // Field grantedRights:Ljava/util/HashMap;
      21: invokevirtual #21                 // Method java/util/HashMap.size:()I
      24: ifne          32
      27: aload_0
      28: aconst_null
      29: putfield      #10                 // Field grantedRights:Ljava/util/HashMap;
      32: return

  public void grantRole(org.h2.engine.Role, org.h2.engine.Right);
    Code:
       0: aload_0
       1: getfield      #3                  // Field grantedRoles:Ljava/util/HashMap;
       4: ifnonnull     18
       7: aload_0
       8: new           #17                 // class java/util/HashMap
      11: dup
      12: invokespecial #18                 // Method java/util/HashMap."<init>":()V
      15: putfield      #3                  // Field grantedRoles:Ljava/util/HashMap;
      18: aload_0
      19: getfield      #3                  // Field grantedRoles:Ljava/util/HashMap;
      22: aload_1
      23: aload_2
      24: invokevirtual #19                 // Method java/util/HashMap.put:(Ljava/lang/Object;Ljava/lang/Object;)Ljava/lang/Object;
      27: pop
      28: return

  void revokeRole(org.h2.engine.Role);
    Code:
       0: aload_0
       1: getfield      #3                  // Field grantedRoles:Ljava/util/HashMap;
       4: ifnonnull     8
       7: return
       8: aload_0
       9: getfield      #3                  // Field grantedRoles:Ljava/util/HashMap;
      12: aload_1
      13: invokevirtual #12                 // Method java/util/HashMap.get:(Ljava/lang/Object;)Ljava/lang/Object;
      16: checkcast     #13                 // class org/h2/engine/Right
      19: astore_2
      20: aload_2
      21: ifnonnull     25
      24: return
      25: aload_0
      26: getfield      #3                  // Field grantedRoles:Ljava/util/HashMap;
      29: aload_1
      30: invokevirtual #20                 // Method java/util/HashMap.remove:(Ljava/lang/Object;)Ljava/lang/Object;
      33: pop
      34: aload_0
      35: getfield      #3                  // Field grantedRoles:Ljava/util/HashMap;
      38: invokevirtual #21                 // Method java/util/HashMap.size:()I
      41: ifne          49
      44: aload_0
      45: aconst_null
      46: putfield      #3                  // Field grantedRoles:Ljava/util/HashMap;
      49: return

  public org.h2.engine.Right getRightForObject(org.h2.engine.DbObject);
    Code:
       0: aload_0
       1: getfield      #10                 // Field grantedRights:Ljava/util/HashMap;
       4: ifnonnull     9
       7: aconst_null
       8: areturn
       9: aload_0
      10: getfield      #10                 // Field grantedRights:Ljava/util/HashMap;
      13: aload_1
      14: invokevirtual #12                 // Method java/util/HashMap.get:(Ljava/lang/Object;)Ljava/lang/Object;
      17: checkcast     #13                 // class org/h2/engine/Right
      20: areturn

  public org.h2.engine.Right getRightForRole(org.h2.engine.Role);
    Code:
       0: aload_0
       1: getfield      #3                  // Field grantedRoles:Ljava/util/HashMap;
       4: ifnonnull     9
       7: aconst_null
       8: areturn
       9: aload_0
      10: getfield      #3                  // Field grantedRoles:Ljava/util/HashMap;
      13: aload_1
      14: invokevirtual #12                 // Method java/util/HashMap.get:(Ljava/lang/Object;)Ljava/lang/Object;
      17: checkcast     #13                 // class org/h2/engine/Right
      20: areturn
}
