Compiled from "Setting.java"
public class org.h2.engine.Setting extends org.h2.engine.DbObjectBase {
  private int intValue;

  private java.lang.String stringValue;

  public org.h2.engine.Setting(org.h2.engine.Database, int, java.lang.String);
    Code:
       0: aload_0
       1: invokespecial #1                  // Method org/h2/engine/DbObjectBase."<init>":()V
       4: aload_0
       5: aload_1
       6: iload_2
       7: aload_3
       8: bipush        10
      10: invokevirtual #2                  // Method initDbObjectBase:(Lorg/h2/engine/Database;ILjava/lang/String;I)V
      13: return

  public void setIntValue(int);
    Code:
       0: aload_0
       1: iload_1
       2: putfield      #3                  // Field intValue:I
       5: return

  public int getIntValue();
    Code:
       0: aload_0
       1: getfield      #3                  // Field intValue:I
       4: ireturn

  public void setStringValue(java.lang.String);
    Code:
       0: aload_0
       1: aload_1
       2: putfield      #4                  // Field stringValue:Ljava/lang/String;
       5: return

  public java.lang.String getStringValue();
    Code:
       0: aload_0
       1: getfield      #4                  // Field stringValue:Ljava/lang/String;
       4: areturn

  public java.lang.String getCreateSQLForCopy(org.h2.table.Table, java.lang.String);
    Code:
       0: aload_0
       1: invokevirtual #5                  // Method toString:()Ljava/lang/String;
       4: invokestatic  #6                  // Method org/h2/message/DbException.throwInternalError:(Ljava/lang/String;)Ljava/lang/RuntimeException;
       7: athrow

  public java.lang.String getDropSQL();
    Code:
       0: aconst_null
       1: areturn

  public java.lang.String getCreateSQL();
    Code:
       0: new           #7                  // class java/lang/StringBuilder
       3: dup
       4: ldc           #8                  // String SET
       6: invokespecial #9                  // Method java/lang/StringBuilder."<init>":(Ljava/lang/String;)V
       9: astore_1
      10: aload_1
      11: aload_0
      12: invokevirtual #10                 // Method getSQL:()Ljava/lang/String;
      15: invokevirtual #11                 // Method java/lang/StringBuilder.append:(Ljava/lang/String;)Ljava/lang/StringBuilder;
      18: bipush        32
      20: invokevirtual #12                 // Method java/lang/StringBuilder.append:(C)Ljava/lang/StringBuilder;
      23: pop
      24: aload_0
      25: getfield      #4                  // Field stringValue:Ljava/lang/String;
      28: ifnull        43
      31: aload_1
      32: aload_0
      33: getfield      #4                  // Field stringValue:Ljava/lang/String;
      36: invokevirtual #11                 // Method java/lang/StringBuilder.append:(Ljava/lang/String;)Ljava/lang/StringBuilder;
      39: pop
      40: goto          52
      43: aload_1
      44: aload_0
      45: getfield      #3                  // Field intValue:I
      48: invokevirtual #13                 // Method java/lang/StringBuilder.append:(I)Ljava/lang/StringBuilder;
      51: pop
      52: aload_1
      53: invokevirtual #14                 // Method java/lang/StringBuilder.toString:()Ljava/lang/String;
      56: areturn

  public int getType();
    Code:
       0: bipush        6
       2: ireturn

  public void removeChildrenAndResources(org.h2.engine.Session);
    Code:
       0: aload_0
       1: getfield      #15                 // Field database:Lorg/h2/engine/Database;
       4: aload_1
       5: aload_0
       6: invokevirtual #16                 // Method getId:()I
       9: invokevirtual #17                 // Method org/h2/engine/Database.removeMeta:(Lorg/h2/engine/Session;I)V
      12: aload_0
      13: invokevirtual #18                 // Method invalidate:()V
      16: return

  public void checkRename();
    Code:
       0: ldc           #19                 // String RENAME
       2: invokestatic  #20                 // Method org/h2/message/DbException.getUnsupportedException:(Ljava/lang/String;)Lorg/h2/message/DbException;
       5: athrow
}
