Compiled from "IndexLib.java"
public class org.apache.jena.tdb.index.IndexLib {
  public org.apache.jena.tdb.index.IndexLib();
    Code:
       0: aload_0
       1: invokespecial #1                  // Method java/lang/Object."<init>":()V
       4: return

  public static void print(java.util.Iterator<org.apache.jena.atlas.lib.tuple.Tuple<org.apache.jena.tdb.store.NodeId>>);
    Code:
       0: iconst_0
       1: istore_1
       2: aload_0
       3: invokeinterface #2,  1            // InterfaceMethod java/util/Iterator.hasNext:()Z
       8: ifeq          51
      11: aload_0
      12: invokeinterface #3,  1            // InterfaceMethod java/util/Iterator.next:()Ljava/lang/Object;
      17: checkcast     #4                  // class org/apache/jena/atlas/lib/tuple/Tuple
      20: astore_2
      21: getstatic     #5                  // Field java/lang/System.out:Ljava/io/PrintStream;
      24: ldc           #6                  // String %2d: %s\n
      26: iconst_2
      27: anewarray     #7                  // class java/lang/Object
      30: dup
      31: iconst_0
      32: iload_1
      33: invokestatic  #8                  // Method java/lang/Integer.valueOf:(I)Ljava/lang/Integer;
      36: aastore
      37: dup
      38: iconst_1
      39: aload_2
      40: aastore
      41: invokevirtual #9                  // Method java/io/PrintStream.printf:(Ljava/lang/String;[Ljava/lang/Object;)Ljava/io/PrintStream;
      44: pop
      45: iinc          1, 1
      48: goto          2
      51: return
}
