Compiled from "IndexWrapper.java"
public class org.apache.jena.tdb.index.IndexWrapper implements org.apache.jena.tdb.index.Index {
  private final org.apache.jena.tdb.index.Index index;

  public org.apache.jena.tdb.index.IndexWrapper(org.apache.jena.tdb.index.Index);
    Code:
       0: aload_0
       1: invokespecial #1                  // Method java/lang/Object."<init>":()V
       4: aload_0
       5: aload_1
       6: putfield      #2                  // Field index:Lorg/apache/jena/tdb/index/Index;
       9: return

  public org.apache.jena.tdb.base.record.Record find(org.apache.jena.tdb.base.record.Record);
    Code:
       0: aload_0
       1: getfield      #2                  // Field index:Lorg/apache/jena/tdb/index/Index;
       4: aload_1
       5: invokeinterface #3,  2            // InterfaceMethod org/apache/jena/tdb/index/Index.find:(Lorg/apache/jena/tdb/base/record/Record;)Lorg/apache/jena/tdb/base/record/Record;
      10: areturn

  public boolean contains(org.apache.jena.tdb.base.record.Record);
    Code:
       0: aload_0
       1: getfield      #2                  // Field index:Lorg/apache/jena/tdb/index/Index;
       4: aload_1
       5: invokeinterface #4,  2            // InterfaceMethod org/apache/jena/tdb/index/Index.contains:(Lorg/apache/jena/tdb/base/record/Record;)Z
      10: ireturn

  public boolean add(org.apache.jena.tdb.base.record.Record);
    Code:
       0: aload_0
       1: getfield      #2                  // Field index:Lorg/apache/jena/tdb/index/Index;
       4: aload_1
       5: invokeinterface #5,  2            // InterfaceMethod org/apache/jena/tdb/index/Index.add:(Lorg/apache/jena/tdb/base/record/Record;)Z
      10: ireturn

  public boolean delete(org.apache.jena.tdb.base.record.Record);
    Code:
       0: aload_0
       1: getfield      #2                  // Field index:Lorg/apache/jena/tdb/index/Index;
       4: aload_1
       5: invokeinterface #6,  2            // InterfaceMethod org/apache/jena/tdb/index/Index.delete:(Lorg/apache/jena/tdb/base/record/Record;)Z
      10: ireturn

  public java.util.Iterator<org.apache.jena.tdb.base.record.Record> iterator();
    Code:
       0: aload_0
       1: getfield      #2                  // Field index:Lorg/apache/jena/tdb/index/Index;
       4: invokeinterface #7,  1            // InterfaceMethod org/apache/jena/tdb/index/Index.iterator:()Ljava/util/Iterator;
       9: areturn

  public boolean isEmpty();
    Code:
       0: aload_0
       1: getfield      #2                  // Field index:Lorg/apache/jena/tdb/index/Index;
       4: invokeinterface #8,  1            // InterfaceMethod org/apache/jena/tdb/index/Index.isEmpty:()Z
       9: ireturn

  public void clear();
    Code:
       0: aload_0
       1: getfield      #2                  // Field index:Lorg/apache/jena/tdb/index/Index;
       4: invokeinterface #9,  1            // InterfaceMethod org/apache/jena/tdb/index/Index.clear:()V
       9: return

  public void sync();
    Code:
       0: aload_0
       1: getfield      #2                  // Field index:Lorg/apache/jena/tdb/index/Index;
       4: invokeinterface #10,  1           // InterfaceMethod org/apache/jena/tdb/index/Index.sync:()V
       9: return

  public void close();
    Code:
       0: aload_0
       1: getfield      #2                  // Field index:Lorg/apache/jena/tdb/index/Index;
       4: invokeinterface #11,  1           // InterfaceMethod org/apache/jena/tdb/index/Index.close:()V
       9: return

  public org.apache.jena.tdb.base.record.RecordFactory getRecordFactory();
    Code:
       0: aload_0
       1: getfield      #2                  // Field index:Lorg/apache/jena/tdb/index/Index;
       4: invokeinterface #12,  1           // InterfaceMethod org/apache/jena/tdb/index/Index.getRecordFactory:()Lorg/apache/jena/tdb/base/record/RecordFactory;
       9: areturn

  public void check();
    Code:
       0: aload_0
       1: getfield      #2                  // Field index:Lorg/apache/jena/tdb/index/Index;
       4: invokeinterface #13,  1           // InterfaceMethod org/apache/jena/tdb/index/Index.check:()V
       9: return

  public long size();
    Code:
       0: aload_0
       1: getfield      #2                  // Field index:Lorg/apache/jena/tdb/index/Index;
       4: invokeinterface #14,  1           // InterfaceMethod org/apache/jena/tdb/index/Index.size:()J
       9: lreturn
}
