public class org.bouncycastle.est.jcajce.JsseESTServiceBuilder extends org.bouncycastle.est.ESTServiceBuilder {
  protected org.bouncycastle.est.jcajce.SSLSocketFactoryCreator socketFactoryCreator;

  protected org.bouncycastle.est.jcajce.JsseHostnameAuthorizer hostNameAuthorizer;

  protected int timeoutMillis;

  protected org.bouncycastle.est.jcajce.ChannelBindingProvider bindingProvider;

  protected java.util.Set<java.lang.String> supportedSuites;

  protected java.lang.Long absoluteLimit;

  protected org.bouncycastle.est.jcajce.SSLSocketFactoryCreatorBuilder sslSocketFactoryCreatorBuilder;

  protected boolean filterCipherSuites;

  public org.bouncycastle.est.jcajce.JsseESTServiceBuilder(java.lang.String, int, org.bouncycastle.est.jcajce.SSLSocketFactoryCreator);
    Code:
       0: aload_0
       1: new           #58                 // class java/lang/StringBuilder
       4: dup
       5: invokespecial #164                // Method java/lang/StringBuilder."<init>":()V
       8: aload_1
       9: invokevirtual #167                // Method java/lang/StringBuilder.append:(Ljava/lang/String;)Ljava/lang/StringBuilder;
      12: ldc           #1                  // String :
      14: invokevirtual #167                // Method java/lang/StringBuilder.append:(Ljava/lang/String;)Ljava/lang/StringBuilder;
      17: iload_2
      18: invokevirtual #166                // Method java/lang/StringBuilder.append:(I)Ljava/lang/StringBuilder;
      21: invokevirtual #165                // Method java/lang/StringBuilder.toString:()Ljava/lang/String;
      24: invokespecial #170                // Method org/bouncycastle/est/ESTServiceBuilder."<init>":(Ljava/lang/String;)V
      27: aload_0
      28: new           #66                 // class org/bouncycastle/est/jcajce/JsseDefaultHostnameAuthorizer
      31: dup
      32: aconst_null
      33: invokespecial #174                // Method org/bouncycastle/est/jcajce/JsseDefaultHostnameAuthorizer."<init>":(Ljava/util/Set;)V
      36: putfield      #158                // Field hostNameAuthorizer:Lorg/bouncycastle/est/jcajce/JsseHostnameAuthorizer;
      39: aload_0
      40: iconst_0
      41: putfield      #152                // Field timeoutMillis:I
      44: aload_0
      45: new           #61                 // class java/util/HashSet
      48: dup
      49: invokespecial #169                // Method java/util/HashSet."<init>":()V
      52: putfield      #155                // Field supportedSuites:Ljava/util/Set;
      55: aload_0
      56: iconst_1
      57: putfield      #153                // Field filterCipherSuites:Z
      60: aload_3
      61: ifnonnull     74
      64: new           #57                 // class java/lang/NullPointerException
      67: dup
      68: ldc           #2                  // String No socket factory creator.
      70: invokespecial #163                // Method java/lang/NullPointerException."<init>":(Ljava/lang/String;)V
      73: athrow
      74: aload_0
      75: aload_3
      76: putfield      #159                // Field socketFactoryCreator:Lorg/bouncycastle/est/jcajce/SSLSocketFactoryCreator;
      79: return

  public org.bouncycastle.est.jcajce.JsseESTServiceBuilder(java.lang.String, org.bouncycastle.est.jcajce.SSLSocketFactoryCreator);
    Code:
       0: aload_0
       1: aload_1
       2: invokespecial #170                // Method org/bouncycastle/est/ESTServiceBuilder."<init>":(Ljava/lang/String;)V
       5: aload_0
       6: new           #66                 // class org/bouncycastle/est/jcajce/JsseDefaultHostnameAuthorizer
       9: dup
      10: aconst_null
      11: invokespecial #174                // Method org/bouncycastle/est/jcajce/JsseDefaultHostnameAuthorizer."<init>":(Ljava/util/Set;)V
      14: putfield      #158                // Field hostNameAuthorizer:Lorg/bouncycastle/est/jcajce/JsseHostnameAuthorizer;
      17: aload_0
      18: iconst_0
      19: putfield      #152                // Field timeoutMillis:I
      22: aload_0
      23: new           #61                 // class java/util/HashSet
      26: dup
      27: invokespecial #169                // Method java/util/HashSet."<init>":()V
      30: putfield      #155                // Field supportedSuites:Ljava/util/Set;
      33: aload_0
      34: iconst_1
      35: putfield      #153                // Field filterCipherSuites:Z
      38: aload_2
      39: ifnonnull     52
      42: new           #57                 // class java/lang/NullPointerException
      45: dup
      46: ldc           #2                  // String No socket factory creator.
      48: invokespecial #163                // Method java/lang/NullPointerException."<init>":(Ljava/lang/String;)V
      51: athrow
      52: aload_0
      53: aload_2
      54: putfield      #159                // Field socketFactoryCreator:Lorg/bouncycastle/est/jcajce/SSLSocketFactoryCreator;
      57: return

  public org.bouncycastle.est.jcajce.JsseESTServiceBuilder(java.lang.String);
    Code:
       0: aload_0
       1: aload_1
       2: invokespecial #170                // Method org/bouncycastle/est/ESTServiceBuilder."<init>":(Ljava/lang/String;)V
       5: aload_0
       6: new           #66                 // class org/bouncycastle/est/jcajce/JsseDefaultHostnameAuthorizer
       9: dup
      10: aconst_null
      11: invokespecial #174                // Method org/bouncycastle/est/jcajce/JsseDefaultHostnameAuthorizer."<init>":(Ljava/util/Set;)V
      14: putfield      #158                // Field hostNameAuthorizer:Lorg/bouncycastle/est/jcajce/JsseHostnameAuthorizer;
      17: aload_0
      18: iconst_0
      19: putfield      #152                // Field timeoutMillis:I
      22: aload_0
      23: new           #61                 // class java/util/HashSet
      26: dup
      27: invokespecial #169                // Method java/util/HashSet."<init>":()V
      30: putfield      #155                // Field supportedSuites:Ljava/util/Set;
      33: aload_0
      34: iconst_1
      35: putfield      #153                // Field filterCipherSuites:Z
      38: aload_0
      39: new           #69                 // class org/bouncycastle/est/jcajce/SSLSocketFactoryCreatorBuilder
      42: dup
      43: invokestatic  #173                // Method org/bouncycastle/est/jcajce/JcaJceUtils.getTrustAllTrustManager:()Ljavax/net/ssl/X509TrustManager;
      46: invokespecial #178                // Method org/bouncycastle/est/jcajce/SSLSocketFactoryCreatorBuilder."<init>":(Ljavax/net/ssl/X509TrustManager;)V
      49: putfield      #160                // Field sslSocketFactoryCreatorBuilder:Lorg/bouncycastle/est/jcajce/SSLSocketFactoryCreatorBuilder;
      52: return

  public org.bouncycastle.est.jcajce.JsseESTServiceBuilder(java.lang.String, int, javax.net.ssl.X509TrustManager);
    Code:
       0: aload_0
       1: new           #58                 // class java/lang/StringBuilder
       4: dup
       5: invokespecial #164                // Method java/lang/StringBuilder."<init>":()V
       8: aload_1
       9: invokevirtual #167                // Method java/lang/StringBuilder.append:(Ljava/lang/String;)Ljava/lang/StringBuilder;
      12: ldc           #1                  // String :
      14: invokevirtual #167                // Method java/lang/StringBuilder.append:(Ljava/lang/String;)Ljava/lang/StringBuilder;
      17: iload_2
      18: invokevirtual #166                // Method java/lang/StringBuilder.append:(I)Ljava/lang/StringBuilder;
      21: invokevirtual #165                // Method java/lang/StringBuilder.toString:()Ljava/lang/String;
      24: invokespecial #170                // Method org/bouncycastle/est/ESTServiceBuilder."<init>":(Ljava/lang/String;)V
      27: aload_0
      28: new           #66                 // class org/bouncycastle/est/jcajce/JsseDefaultHostnameAuthorizer
      31: dup
      32: aconst_null
      33: invokespecial #174                // Method org/bouncycastle/est/jcajce/JsseDefaultHostnameAuthorizer."<init>":(Ljava/util/Set;)V
      36: putfield      #158                // Field hostNameAuthorizer:Lorg/bouncycastle/est/jcajce/JsseHostnameAuthorizer;
      39: aload_0
      40: iconst_0
      41: putfield      #152                // Field timeoutMillis:I
      44: aload_0
      45: new           #61                 // class java/util/HashSet
      48: dup
      49: invokespecial #169                // Method java/util/HashSet."<init>":()V
      52: putfield      #155                // Field supportedSuites:Ljava/util/Set;
      55: aload_0
      56: iconst_1
      57: putfield      #153                // Field filterCipherSuites:Z
      60: aload_0
      61: new           #69                 // class org/bouncycastle/est/jcajce/SSLSocketFactoryCreatorBuilder
      64: dup
      65: aload_3
      66: invokespecial #178                // Method org/bouncycastle/est/jcajce/SSLSocketFactoryCreatorBuilder."<init>":(Ljavax/net/ssl/X509TrustManager;)V
      69: putfield      #160                // Field sslSocketFactoryCreatorBuilder:Lorg/bouncycastle/est/jcajce/SSLSocketFactoryCreatorBuilder;
      72: return

  public org.bouncycastle.est.jcajce.JsseESTServiceBuilder(java.lang.String, javax.net.ssl.X509TrustManager);
    Code:
       0: aload_0
       1: aload_1
       2: invokespecial #170                // Method org/bouncycastle/est/ESTServiceBuilder."<init>":(Ljava/lang/String;)V
       5: aload_0
       6: new           #66                 // class org/bouncycastle/est/jcajce/JsseDefaultHostnameAuthorizer
       9: dup
      10: aconst_null
      11: invokespecial #174                // Method org/bouncycastle/est/jcajce/JsseDefaultHostnameAuthorizer."<init>":(Ljava/util/Set;)V
      14: putfield      #158                // Field hostNameAuthorizer:Lorg/bouncycastle/est/jcajce/JsseHostnameAuthorizer;
      17: aload_0
      18: iconst_0
      19: putfield      #152                // Field timeoutMillis:I
      22: aload_0
      23: new           #61                 // class java/util/HashSet
      26: dup
      27: invokespecial #169                // Method java/util/HashSet."<init>":()V
      30: putfield      #155                // Field supportedSuites:Ljava/util/Set;
      33: aload_0
      34: iconst_1
      35: putfield      #153                // Field filterCipherSuites:Z
      38: aload_0
      39: new           #69                 // class org/bouncycastle/est/jcajce/SSLSocketFactoryCreatorBuilder
      42: dup
      43: aload_2
      44: invokespecial #178                // Method org/bouncycastle/est/jcajce/SSLSocketFactoryCreatorBuilder."<init>":(Ljavax/net/ssl/X509TrustManager;)V
      47: putfield      #160                // Field sslSocketFactoryCreatorBuilder:Lorg/bouncycastle/est/jcajce/SSLSocketFactoryCreatorBuilder;
      50: return

  public org.bouncycastle.est.jcajce.JsseESTServiceBuilder(java.lang.String, int, javax.net.ssl.X509TrustManager[]);
    Code:
       0: aload_0
       1: new           #58                 // class java/lang/StringBuilder
       4: dup
       5: invokespecial #164                // Method java/lang/StringBuilder."<init>":()V
       8: aload_1
       9: invokevirtual #167                // Method java/lang/StringBuilder.append:(Ljava/lang/String;)Ljava/lang/StringBuilder;
      12: ldc           #1                  // String :
      14: invokevirtual #167                // Method java/lang/StringBuilder.append:(Ljava/lang/String;)Ljava/lang/StringBuilder;
      17: iload_2
      18: invokevirtual #166                // Method java/lang/StringBuilder.append:(I)Ljava/lang/StringBuilder;
      21: invokevirtual #165                // Method java/lang/StringBuilder.toString:()Ljava/lang/String;
      24: aload_3
      25: invokespecial #175                // Method "<init>":(Ljava/lang/String;[Ljavax/net/ssl/X509TrustManager;)V
      28: return

  public org.bouncycastle.est.jcajce.JsseESTServiceBuilder(java.lang.String, javax.net.ssl.X509TrustManager[]);
    Code:
       0: aload_0
       1: aload_1
       2: invokespecial #170                // Method org/bouncycastle/est/ESTServiceBuilder."<init>":(Ljava/lang/String;)V
       5: aload_0
       6: new           #66                 // class org/bouncycastle/est/jcajce/JsseDefaultHostnameAuthorizer
       9: dup
      10: aconst_null
      11: invokespecial #174                // Method org/bouncycastle/est/jcajce/JsseDefaultHostnameAuthorizer."<init>":(Ljava/util/Set;)V
      14: putfield      #158                // Field hostNameAuthorizer:Lorg/bouncycastle/est/jcajce/JsseHostnameAuthorizer;
      17: aload_0
      18: iconst_0
      19: putfield      #152                // Field timeoutMillis:I
      22: aload_0
      23: new           #61                 // class java/util/HashSet
      26: dup
      27: invokespecial #169                // Method java/util/HashSet."<init>":()V
      30: putfield      #155                // Field supportedSuites:Ljava/util/Set;
      33: aload_0
      34: iconst_1
      35: putfield      #153                // Field filterCipherSuites:Z
      38: aload_0
      39: new           #69                 // class org/bouncycastle/est/jcajce/SSLSocketFactoryCreatorBuilder
      42: dup
      43: aload_2
      44: invokespecial #179                // Method org/bouncycastle/est/jcajce/SSLSocketFactoryCreatorBuilder."<init>":([Ljavax/net/ssl/X509TrustManager;)V
      47: putfield      #160                // Field sslSocketFactoryCreatorBuilder:Lorg/bouncycastle/est/jcajce/SSLSocketFactoryCreatorBuilder;
      50: return

  public org.bouncycastle.est.jcajce.JsseESTServiceBuilder withHostNameAuthorizer(org.bouncycastle.est.jcajce.JsseHostnameAuthorizer);
    Code:
       0: aload_0
       1: aload_1
       2: putfield      #158                // Field hostNameAuthorizer:Lorg/bouncycastle/est/jcajce/JsseHostnameAuthorizer;
       5: aload_0
       6: areturn

  public org.bouncycastle.est.jcajce.JsseESTServiceBuilder withClientProvider(org.bouncycastle.est.ESTClientProvider);
    Code:
       0: aload_0
       1: aload_1
       2: putfield      #156                // Field clientProvider:Lorg/bouncycastle/est/ESTClientProvider;
       5: aload_0
       6: areturn

  public org.bouncycastle.est.jcajce.JsseESTServiceBuilder withTimeout(int);
    Code:
       0: aload_0
       1: iload_1
       2: putfield      #152                // Field timeoutMillis:I
       5: aload_0
       6: areturn

  public org.bouncycastle.est.jcajce.JsseESTServiceBuilder withReadLimit(long);
    Code:
       0: aload_0
       1: lload_1
       2: invokestatic  #162                // Method java/lang/Long.valueOf:(J)Ljava/lang/Long;
       5: putfield      #154                // Field absoluteLimit:Ljava/lang/Long;
       8: aload_0
       9: areturn

  public org.bouncycastle.est.jcajce.JsseESTServiceBuilder withChannelBindingProvider(org.bouncycastle.est.jcajce.ChannelBindingProvider);
    Code:
       0: aload_0
       1: aload_1
       2: putfield      #157                // Field bindingProvider:Lorg/bouncycastle/est/jcajce/ChannelBindingProvider;
       5: aload_0
       6: areturn

  public org.bouncycastle.est.jcajce.JsseESTServiceBuilder addCipherSuites(java.lang.String);
    Code:
       0: aload_0
       1: getfield      #155                // Field supportedSuites:Ljava/util/Set;
       4: aload_1
       5: invokeinterface #187,  2          // InterfaceMethod java/util/Set.add:(Ljava/lang/Object;)Z
      10: pop
      11: aload_0
      12: areturn

  public org.bouncycastle.est.jcajce.JsseESTServiceBuilder addCipherSuites(java.lang.String[]);
    Code:
       0: aload_0
       1: getfield      #155                // Field supportedSuites:Ljava/util/Set;
       4: aload_1
       5: invokestatic  #168                // Method java/util/Arrays.asList:([Ljava/lang/Object;)Ljava/util/List;
       8: invokeinterface #188,  2          // InterfaceMethod java/util/Set.addAll:(Ljava/util/Collection;)Z
      13: pop
      14: aload_0
      15: areturn

  public org.bouncycastle.est.jcajce.JsseESTServiceBuilder withTLSVersion(java.lang.String);
    Code:
       0: aload_0
       1: getfield      #159                // Field socketFactoryCreator:Lorg/bouncycastle/est/jcajce/SSLSocketFactoryCreator;
       4: ifnull        17
       7: new           #55                 // class java/lang/IllegalStateException
      10: dup
      11: ldc           #3                  // String Socket Factory Creator was defined in the constructor.
      13: invokespecial #161                // Method java/lang/IllegalStateException."<init>":(Ljava/lang/String;)V
      16: athrow
      17: aload_0
      18: getfield      #160                // Field sslSocketFactoryCreatorBuilder:Lorg/bouncycastle/est/jcajce/SSLSocketFactoryCreatorBuilder;
      21: aload_1
      22: invokevirtual #182                // Method org/bouncycastle/est/jcajce/SSLSocketFactoryCreatorBuilder.withTLSVersion:(Ljava/lang/String;)Lorg/bouncycastle/est/jcajce/SSLSocketFactoryCreatorBuilder;
      25: pop
      26: aload_0
      27: areturn

  public org.bouncycastle.est.jcajce.JsseESTServiceBuilder withSecureRandom(java.security.SecureRandom);
    Code:
       0: aload_0
       1: getfield      #159                // Field socketFactoryCreator:Lorg/bouncycastle/est/jcajce/SSLSocketFactoryCreator;
       4: ifnull        17
       7: new           #55                 // class java/lang/IllegalStateException
      10: dup
      11: ldc           #3                  // String Socket Factory Creator was defined in the constructor.
      13: invokespecial #161                // Method java/lang/IllegalStateException."<init>":(Ljava/lang/String;)V
      16: athrow
      17: aload_0
      18: getfield      #160                // Field sslSocketFactoryCreatorBuilder:Lorg/bouncycastle/est/jcajce/SSLSocketFactoryCreatorBuilder;
      21: aload_1
      22: invokevirtual #184                // Method org/bouncycastle/est/jcajce/SSLSocketFactoryCreatorBuilder.withSecureRandom:(Ljava/security/SecureRandom;)Lorg/bouncycastle/est/jcajce/SSLSocketFactoryCreatorBuilder;
      25: pop
      26: aload_0
      27: areturn

  public org.bouncycastle.est.jcajce.JsseESTServiceBuilder withProvider(java.lang.String) throws java.security.NoSuchProviderException;
    Code:
       0: aload_0
       1: getfield      #159                // Field socketFactoryCreator:Lorg/bouncycastle/est/jcajce/SSLSocketFactoryCreator;
       4: ifnull        17
       7: new           #55                 // class java/lang/IllegalStateException
      10: dup
      11: ldc           #3                  // String Socket Factory Creator was defined in the constructor.
      13: invokespecial #161                // Method java/lang/IllegalStateException."<init>":(Ljava/lang/String;)V
      16: athrow
      17: aload_0
      18: getfield      #160                // Field sslSocketFactoryCreatorBuilder:Lorg/bouncycastle/est/jcajce/SSLSocketFactoryCreatorBuilder;
      21: aload_1
      22: invokevirtual #181                // Method org/bouncycastle/est/jcajce/SSLSocketFactoryCreatorBuilder.withProvider:(Ljava/lang/String;)Lorg/bouncycastle/est/jcajce/SSLSocketFactoryCreatorBuilder;
      25: pop
      26: aload_0
      27: areturn

  public org.bouncycastle.est.jcajce.JsseESTServiceBuilder withProvider(java.security.Provider);
    Code:
       0: aload_0
       1: getfield      #159                // Field socketFactoryCreator:Lorg/bouncycastle/est/jcajce/SSLSocketFactoryCreator;
       4: ifnull        17
       7: new           #55                 // class java/lang/IllegalStateException
      10: dup
      11: ldc           #3                  // String Socket Factory Creator was defined in the constructor.
      13: invokespecial #161                // Method java/lang/IllegalStateException."<init>":(Ljava/lang/String;)V
      16: athrow
      17: aload_0
      18: getfield      #160                // Field sslSocketFactoryCreatorBuilder:Lorg/bouncycastle/est/jcajce/SSLSocketFactoryCreatorBuilder;
      21: aload_1
      22: invokevirtual #183                // Method org/bouncycastle/est/jcajce/SSLSocketFactoryCreatorBuilder.withProvider:(Ljava/security/Provider;)Lorg/bouncycastle/est/jcajce/SSLSocketFactoryCreatorBuilder;
      25: pop
      26: aload_0
      27: areturn

  public org.bouncycastle.est.jcajce.JsseESTServiceBuilder withKeyManager(javax.net.ssl.KeyManager);
    Code:
       0: aload_0
       1: getfield      #159                // Field socketFactoryCreator:Lorg/bouncycastle/est/jcajce/SSLSocketFactoryCreator;
       4: ifnull        17
       7: new           #55                 // class java/lang/IllegalStateException
      10: dup
      11: ldc           #3                  // String Socket Factory Creator was defined in the constructor.
      13: invokespecial #161                // Method java/lang/IllegalStateException."<init>":(Ljava/lang/String;)V
      16: athrow
      17: aload_0
      18: getfield      #160                // Field sslSocketFactoryCreatorBuilder:Lorg/bouncycastle/est/jcajce/SSLSocketFactoryCreatorBuilder;
      21: aload_1
      22: invokevirtual #185                // Method org/bouncycastle/est/jcajce/SSLSocketFactoryCreatorBuilder.withKeyManager:(Ljavax/net/ssl/KeyManager;)Lorg/bouncycastle/est/jcajce/SSLSocketFactoryCreatorBuilder;
      25: pop
      26: aload_0
      27: areturn

  public org.bouncycastle.est.jcajce.JsseESTServiceBuilder withKeyManagers(javax.net.ssl.KeyManager[]);
    Code:
       0: aload_0
       1: getfield      #159                // Field socketFactoryCreator:Lorg/bouncycastle/est/jcajce/SSLSocketFactoryCreator;
       4: ifnull        17
       7: new           #55                 // class java/lang/IllegalStateException
      10: dup
      11: ldc           #3                  // String Socket Factory Creator was defined in the constructor.
      13: invokespecial #161                // Method java/lang/IllegalStateException."<init>":(Ljava/lang/String;)V
      16: athrow
      17: aload_0
      18: getfield      #160                // Field sslSocketFactoryCreatorBuilder:Lorg/bouncycastle/est/jcajce/SSLSocketFactoryCreatorBuilder;
      21: aload_1
      22: invokevirtual #186                // Method org/bouncycastle/est/jcajce/SSLSocketFactoryCreatorBuilder.withKeyManagers:([Ljavax/net/ssl/KeyManager;)Lorg/bouncycastle/est/jcajce/SSLSocketFactoryCreatorBuilder;
      25: pop
      26: aload_0
      27: areturn

  public org.bouncycastle.est.jcajce.JsseESTServiceBuilder withFilterCipherSuites(boolean);
    Code:
       0: aload_0
       1: iload_1
       2: putfield      #153                // Field filterCipherSuites:Z
       5: aload_0
       6: areturn

  public org.bouncycastle.est.ESTService build();
    Code:
       0: aload_0
       1: getfield      #157                // Field bindingProvider:Lorg/bouncycastle/est/jcajce/ChannelBindingProvider;
       4: ifnonnull     19
       7: aload_0
       8: new           #68                 // class org/bouncycastle/est/jcajce/JsseESTServiceBuilder$1
      11: dup
      12: aload_0
      13: invokespecial #177                // Method org/bouncycastle/est/jcajce/JsseESTServiceBuilder$1."<init>":(Lorg/bouncycastle/est/jcajce/JsseESTServiceBuilder;)V
      16: putfield      #157                // Field bindingProvider:Lorg/bouncycastle/est/jcajce/ChannelBindingProvider;
      19: aload_0
      20: getfield      #159                // Field socketFactoryCreator:Lorg/bouncycastle/est/jcajce/SSLSocketFactoryCreator;
      23: ifnonnull     37
      26: aload_0
      27: aload_0
      28: getfield      #160                // Field sslSocketFactoryCreatorBuilder:Lorg/bouncycastle/est/jcajce/SSLSocketFactoryCreatorBuilder;
      31: invokevirtual #180                // Method org/bouncycastle/est/jcajce/SSLSocketFactoryCreatorBuilder.build:()Lorg/bouncycastle/est/jcajce/SSLSocketFactoryCreator;
      34: putfield      #159                // Field socketFactoryCreator:Lorg/bouncycastle/est/jcajce/SSLSocketFactoryCreator;
      37: aload_0
      38: getfield      #156                // Field clientProvider:Lorg/bouncycastle/est/ESTClientProvider;
      41: ifnonnull     83
      44: aload_0
      45: new           #64                 // class org/bouncycastle/est/jcajce/DefaultESTHttpClientProvider
      48: dup
      49: aload_0
      50: getfield      #158                // Field hostNameAuthorizer:Lorg/bouncycastle/est/jcajce/JsseHostnameAuthorizer;
      53: aload_0
      54: getfield      #159                // Field socketFactoryCreator:Lorg/bouncycastle/est/jcajce/SSLSocketFactoryCreator;
      57: aload_0
      58: getfield      #152                // Field timeoutMillis:I
      61: aload_0
      62: getfield      #157                // Field bindingProvider:Lorg/bouncycastle/est/jcajce/ChannelBindingProvider;
      65: aload_0
      66: getfield      #155                // Field supportedSuites:Ljava/util/Set;
      69: aload_0
      70: getfield      #154                // Field absoluteLimit:Ljava/lang/Long;
      73: aload_0
      74: getfield      #153                // Field filterCipherSuites:Z
      77: invokespecial #172                // Method org/bouncycastle/est/jcajce/DefaultESTHttpClientProvider."<init>":(Lorg/bouncycastle/est/jcajce/JsseHostnameAuthorizer;Lorg/bouncycastle/est/jcajce/SSLSocketFactoryCreator;ILorg/bouncycastle/est/jcajce/ChannelBindingProvider;Ljava/util/Set;Ljava/lang/Long;Z)V
      80: putfield      #156                // Field clientProvider:Lorg/bouncycastle/est/ESTClientProvider;
      83: aload_0
      84: invokespecial #171                // Method org/bouncycastle/est/ESTServiceBuilder.build:()Lorg/bouncycastle/est/ESTService;
      87: areturn

  public org.bouncycastle.est.ESTServiceBuilder withClientProvider(org.bouncycastle.est.ESTClientProvider);
    Code:
       0: aload_0
       1: aload_1
       2: invokevirtual #176                // Method withClientProvider:(Lorg/bouncycastle/est/ESTClientProvider;)Lorg/bouncycastle/est/jcajce/JsseESTServiceBuilder;
       5: areturn
}
