Compiled from "InvocationContextContainerImpl.java"
public class org.infinispan.context.InvocationContextContainerImpl implements org.infinispan.context.InvocationContextContainer {
  private final java.lang.ThreadLocal<org.infinispan.context.InvocationContext> ctxHolder;

  private java.lang.ClassLoader configuredClassLoader;

  public org.infinispan.context.InvocationContextContainerImpl();
    Code:
       0: aload_0
       1: invokespecial #1                  // Method java/lang/Object."<init>":()V
       4: aload_0
       5: new           #2                  // class java/lang/ThreadLocal
       8: dup
       9: invokespecial #3                  // Method java/lang/ThreadLocal."<init>":()V
      12: putfield      #4                  // Field ctxHolder:Ljava/lang/ThreadLocal;
      15: return

  public void init(org.infinispan.configuration.global.GlobalConfiguration);
    Code:
       0: aload_0
       1: aload_1
       2: invokevirtual #5                  // Method org/infinispan/configuration/global/GlobalConfiguration.classLoader:()Ljava/lang/ClassLoader;
       5: putfield      #6                  // Field configuredClassLoader:Ljava/lang/ClassLoader;
       8: return

  public void stop();
    Code:
       0: aload_0
       1: aconst_null
       2: putfield      #6                  // Field configuredClassLoader:Ljava/lang/ClassLoader;
       5: return

  public org.infinispan.context.InvocationContext getInvocationContext(boolean);
    Code:
       0: aload_0
       1: getfield      #4                  // Field ctxHolder:Ljava/lang/ThreadLocal;
       4: invokevirtual #7                  // Method java/lang/ThreadLocal.get:()Ljava/lang/Object;
       7: checkcast     #8                  // class org/infinispan/context/InvocationContext
      10: astore_2
      11: aload_2
      12: ifnonnull     29
      15: iload_1
      16: ifne          29
      19: new           #9                  // class java/lang/IllegalStateException
      22: dup
      23: ldc           #10                 // String No InvocationContext associated with current thread!
      25: invokespecial #11                 // Method java/lang/IllegalStateException."<init>":(Ljava/lang/String;)V
      28: athrow
      29: aload_2
      30: areturn

  public void setThreadLocal(org.infinispan.context.InvocationContext);
    Code:
       0: aload_0
       1: aload_1
       2: invokespecial #12                 // Method isThreadLocalRequired:(Lorg/infinispan/context/InvocationContext;)Z
       5: ifeq          16
       8: aload_0
       9: getfield      #4                  // Field ctxHolder:Ljava/lang/ThreadLocal;
      12: aload_1
      13: invokevirtual #13                 // Method java/lang/ThreadLocal.set:(Ljava/lang/Object;)V
      16: return

  public void clearThreadLocal();
    Code:
       0: aload_0
       1: getfield      #4                  // Field ctxHolder:Ljava/lang/ThreadLocal;
       4: invokevirtual #14                 // Method java/lang/ThreadLocal.remove:()V
       7: return

  private boolean isThreadLocalRequired(org.infinispan.context.InvocationContext);
    Code:
       0: aload_1
       1: invokeinterface #15,  1           // InterfaceMethod org/infinispan/context/InvocationContext.getClassLoader:()Ljava/lang/ClassLoader;
       6: ifnull        26
       9: aload_1
      10: invokeinterface #15,  1           // InterfaceMethod org/infinispan/context/InvocationContext.getClassLoader:()Ljava/lang/ClassLoader;
      15: aload_0
      16: getfield      #6                  // Field configuredClassLoader:Ljava/lang/ClassLoader;
      19: if_acmpeq     26
      22: iconst_1
      23: goto          27
      26: iconst_0
      27: ireturn
}
